Workbook
Name TitleRegion1.a2.d25.1: 'FY2014 SUMMARY'!$A$1
Name TitleRegion1.a2.o24.2: 'District by Cluster'!$D$24
Name TitleRegion10.a257.o266.2: 'District by Cluster'!$A$227
Name TitleRegion11.a268.o296.2: 'District by Cluster'!$A$268
Name TitleRegion12.a298.o310.2: 'District by Cluster'!$A$298
Name TitleRegion13.a312.o316.2: 'District by Cluster'!$A$298
Name TitleRegion14.a318.o327.2: 'District by Cluster'!$A$298
Name TitleRegion15.a329.o337.2: 'District by Cluster'!$A$298
Name TitleRegion16.a339.o349.2: 'District by Cluster'!$A$339
Name TitleRegion2.a26.o36.2: 'District by Cluster'!$D$24
Name TitleRegion2.f1.i4.1: 'FY2014 SUMMARY'!$G$7
Name TitleRegion3.a38.0101.2: 'District by Cluster'!$C$101
Name TitleRegion4.a103.o124.2: 'District by Cluster'!$A$103
Name TitleRegion5.a126.o169.2: 'District by Cluster'!$A$126
Name TitleRegion6.a171.o188.2: 'District by Cluster'!$A$171
Name TitleRegion7.a190.o225.2: 'District by Cluster'!$A$190
Name TitleRegion8.a227.o242.2: 'District by Cluster'!$A$227
Name TitleRegion9.a244.o255.2: 'District by Cluster'!$A$227

Sheet FY2014 SUMMARY
A1: FY2014 Telecomm Equity Aid | B1: n/a | C1: n/a | D1: n/a | F1: PAYMENTS TO INDIVIDUAL SCHOOLS | H1: n/a | I1: n/a
A2: Based on FY2013 Actual Costs | B2: n/a | C2: n/a | D2: n/a | F2: n/a | G2: n/a | H2: Eligible | I2: Prorated
A3: Proration Rate | B3: 0.43512324 | C3: n/a | D3: n/a | F3: n/a | G3: n/a | H3: Aid Amount | I3: Aid Amount
A4: PAYMENTS TO TELECOM ACCESS CLUSTERS | C4: n/a | D4: n/a | F4: 297-01 | G4: SPRING GROVE SCHOOL DISTRICT | H4: 773.07 | I4: =H4*$B$3 -> 336.38072
A5: n/a | B5: Org # | C5: Eligible | D5: Prorated | F5: rest of column left blank | G5: rest of column left blank | H5: rest of column left blank | I5: rest of column left blank
A6: Cluster | B6: Org Type | C6: Aid Amount | D6: Aid Amount
A7: REGION 3-CENTRAL | B7: 0867-82 | C7: ='District by Cluster'!N25 -> 463943.98 | D7: ='District by Cluster'!O25 -> 201872.81
A8: REGION 2 - ARCC | B8: 0868-82 | C8: ='District by Cluster'!N37 -> 85674.13 | D8: ='District by Cluster'!O37 -> 37278.805
A9: NW LINKS (REGION I) | B9: 0869-82 | C9: ='District by Cluster'!N102 -> 1044903.4 | D9: ='District by Cluster'!O102 -> 453603.17
A10: REGION 10 - SOUTHEAST SERVICE COOP | B10: 0921-83 | C10: ='District by Cluster'!N125 -> 336031.94 | D10: ='District by Cluster'!O125 -> 146215.31
A11: REGION 7-TIES | B11: 0925-82 | C11: ='District by Cluster'!N170 -> 2595093 | D11: ='District by Cluster'!O170 -> 1129185.3
A12: REGION 3-NORTHEAST SERVICE COOP | B12: 0927-83 | C12: ='District by Cluster'!N189 -> 429389.33 | D12: ='District by Cluster'!O189 -> 186837.28
A13: REGION 6 & 8-SW/WC SERVICE COOP | B13: 0991-83 | C13: ='District by Cluster'!N226 -> 715241.31 | D13: ='District by Cluster'!O226 -> 311218.12
A14: EAST CENTRAL MN ED | B14: 6003-50 | C14: ='District by Cluster'!N243 -> 584226.93 | D14: ='District by Cluster'!O243 -> 254210.71
A15: FRESHWATER ED. DIST. | B15: 6004-61 | C15: ='District by Cluster'!N256 -> 176915.71 | D15: ='District by Cluster'!O256 -> 76980.137
A16: MN RIVER VALLEY | B16: 6018-61 | C16: ='District by Cluster'!N267 -> 134056.07 | D16: ='District by Cluster'!O267 -> 58330.912
A17: SOCRATES | B17: 6036-50 | C17: ='District by Cluster'!N297 -> 1033952.4 | D17: ='District by Cluster'!O297 -> 449896.73
A18: LITTLE CROW TELE-MEDIA NETWORK | B18: 6040-50 | C18: ='District by Cluster'!N311 -> 430561 | D18: ='District by Cluster'!O311 -> 187347.1
A19: WASIOJA ED. TECH. COOP | B19: 6048-50 | C19: ='District by Cluster'!N317 -> 98400 | D19: ='District by Cluster'!O317 -> 42816.127
A20: CENTRAL MN ED TECH | B20: 6054-50 | C20: ='District by Cluster'!N328 -> 256664.57 | D20: ='District by Cluster'!O328 -> 111680.72
A21: ITASCA AREA | B21: 6070-50 | C21: ='District by Cluster'!N338 -> 98860.7 | D21: ='District by Cluster'!O338 -> 43016.588
A22: MID STATE ED. DISTRICT | B22: 6979-61 | C22: ='District by Cluster'!N350 -> 152992.44 | D22: ='District by Cluster'!O350 -> 59173.837
A23: Total for Cluster Members | B23: n/a | C23: =SUM(C7:C22) -> 8636906.9 | D23: =SUM(D7:D22) -> 3749663.6
A24: District no Cluster | B24: n/a | C24: =H4 -> 773.07 | D24: =I4 -> 336.38072
A25: TOTAL | B25: n/a | C25: =C23+C24 -> 8637680 | D25: =D23+D24 -> 3750000
A26: end of worksheet

Sheet District by Cluster
A1: REGION 3-CENTRAL 0867-82 | C1: =N25 -> 463943.98 | D1: n/a | E1: n/a | F1: n/a | G1: n/a | H1: n/a | I1: n/a | J1: n/a | K1: n/a | L1: n/a | M1: n/a | N1: Aid Eligible Costs | O1: Prorated
A2: Dist Num | B2: District Or School Name | C2: Dist Type | D2: Cluster Name | E2: Cluster Num | F2: Line Lease Before Erate | G2: Line Lease After Erate | H2: Install Before E Rate | I2: Install After E Rate | J2: COOP Costs | K2: Maint Costs | L2: Total Before E Rate | M2: Total E Rate Discount | N2: Total After E Rate | O2: Aid
A3: 1 | B3: AITKIN PUBLIC SCHOOL DISTRICT | C3: 1 | D3: REGION 3 - CENTRAL | E3: 868 | F3: 18224.36 | G3: 5394.57 | H3: 0 | I3: 0 | J3: 2779.78 | K3: 0 | L3: 21004.14 | M3: 12829.79 | N3: 8174.35 | O3: =N3*'FY2014 SUMMARY'!$B$3 -> 3556.8497
A4: 0001 | B4: MINNEAPOLIS PUBLIC SCHOOL | C4: 3 | D4: REGION 3 - CENTRAL | E4: 867 | L4: 790202.54 | M4: 609042.84 | N4: 181159.7 | O4: =N4*'FY2014 SUMMARY'!$B$3 -> 78826.796
A5: 51 | B5: FOLEY PUBLIC SCHOOL DISTRICT | C5: 1 | D5: REGION 3 - CENTRAL | E5: 867 | F5: 35288.94 | G5: 16448.91 | H5: 0 | I5: 0 | J5: 0 | K5: 0 | L5: 35288.94 | M5: 18840.03 | N5: 16448.91 | O5: =N5*'FY2014 SUMMARY'!$B$3 -> 7157.303
A6: 181 | B6: BRAINERD PUBLIC SCHOOL DISTRICT | C6: 1 | D6: REGION 3 - CENTRAL | E6: 867 | F6: 15039.06 | G6: 4361.33 | H6: 0 | I6: 0 | J6: 0 | K6: 0 | L6: =F6 -> 15039.06 | M6: =F6-G6 -> 10677.73 | N6: =F6-M6 -> 4361.33 | O6: =N6*'FY2014 SUMMARY'!$B$3 -> 1897.716
A7: 182 | B7: CROSBY-IRONTON PUBLIC SCHOOL DIST. | C7: 1 | D7: REGION 3 - CENTRAL | E7: 867 | F7: 23026.64 | G7: 5712.71 | H7: 0 | I7: 0 | J7: 0 | K7: 0 | L7: 23026.64 | M7: 17313.93 | N7: 5712.71 | O7: =N7*'FY2014 SUMMARY'!$B$3 -> 2485.7329
A8: 186 | B8: PEQUOT LAKES PUBLIC SCHOOLS | C8: 1 | D8: REGION 3 - CENTRAL | E8: 867 | F8: 22218.48 | G8: 8887.39 | H8: 0 | I8: 0 | J8: 0 | K8: 0 | L8: 22218.48 | M8: 13331.09 | N8: 8887.39 | O8: =N8*'FY2014 SUMMARY'!$B$3 -> 3867.1099
A9: 463 | B9: EDEN VALLEY-WATKINS SCHOOL DISTRICT | C9: 1 | D9: REGION 3 - CENTRAL | E9: 867 | F9: 38224.09 | G9: 11467.23 | H9: 0 | I9: 0 | J9: 0 | K9: 0 | L9: 38224.09 | M9: 26756.86 | N9: 11467.23 | O9: =N9*'FY2014 SUMMARY'!$B$3 -> 4989.6583
A10: 465 | B10: LITCHFIELD PUBLIC SCHOOL DISTRICT | C10: 1 | D10: REGION 3 - CENTRAL | E10: 867 | F10: 48694.84 | G10: 16069.3 | H10: 0 | I10: 0 | J10: 0 | K10: 0 | L10: 48694.84 | M10: 32625.54 | N10: 16069.3 | O10: =N10*'FY2014 SUMMARY'!$B$3 -> 6992.1259
A11: 466 | B11: DASSEL-COKATO PUBLIC SCHOOL DIST. | C11: 1 | D11: REGION 3 - CENTRAL | E11: 867 | F11: 22218.48 | G11: 7776.47 | H11: 0 | I11: 0 | J11: 0 | K11: 0 | L11: 22218.48 | M11: 14442.01 | N11: 7776.47 | O11: =N11*'FY2014 SUMMARY'!$B$3 -> 3383.7228
A12: 726 | B12: BECKER PUBLIC SCHOOL DISTRICT | C12: 1 | D12: REGION 3 - CENTRAL | E12: 867 | F12: 16276.53 | G12: 8952.09 | H12: 0 | I12: 0 | J12: 0 | K12: 0 | L12: 16276.53 | M12: 7324.44 | N12: 8952.09 | O12: =N12*'FY2014 SUMMARY'!$B$3 -> 3895.2624
A13: 727 | B13: BIG LAKE PUBLIC SCHOOL DISTRICT | C13: 1 | D13: REGION 3 - CENTRAL | E13: 867 | F13: 19847.49 | G13: 9923.74 | H13: 0 | I13: 0 | J13: 0 | K13: 0 | L13: 19847.49 | M13: 9923.75 | N13: 9923.74 | O13: =N13*'FY2014 SUMMARY'!$B$3 -> 4318.0499
A14: 739 | B14: KIMBALL PUBLIC SCHOOL DISTRICT | C14: 1 | D14: REGION 3 - CENTRAL | E14: 867 | F14: 19165.2 | G14: 8624.34 | H14: 0 | I14: 0 | J14: 0 | K14: 0 | L14: 19165.2 | M14: 10540.86 | N14: 8624.34 | O14: =N14*'FY2014 SUMMARY'!$B$3 -> 3752.6508
A15: 741 | B15: PAYNESVILLE PUBLIC SCHOOL DISTRICT | C15: 1 | D15: REGION 3 - CENTRAL | E15: 867 | F15: 16290.79 | G15: 4887.24 | H15: 0 | I15: 0 | J15: 0 | K15: 0 | L15: 16290.79 | M15: 11403.55 | N15: 4887.24 | O15: =N15*'FY2014 SUMMARY'!$B$3 -> 2126.5517
A16: 742 | B16: ST. CLOUD PUBLIC SCHOOL DISTRICT | C16: 1 | D16: REGION 3 - CENTRAL | E16: 867 | F16: 64740 | G16: 21502.8 | H16: 0 | I16: 0 | J16: 0 | K16: 0 | L16: 64740 | M16: 43237.2 | N16: 21502.8 | O16: =N16*'FY2014 SUMMARY'!$B$3 -> 9356.368
A17: 748 | B17: SARTELL-ST. STEPHEN SCHOOL DISTRICT | C17: 1 | D17: REGION 3 - CENTRAL | E17: 867 | F17: 21032.94 | G17: 12619.76 | H17: 0 | I17: 0 | J17: 5524.79 | K17: 0 | L17: 26557.73 | M17: 8413.18 | N17: 18144.55 | O17: =N17*'FY2014 SUMMARY'!$B$3 -> 7895.1154
A18: 750 | B18: ROCORI PUBLIC SCHOOL DISTRICT | C18: 1 | D18: REGION 3 - CENTRAL | E18: 867 | F18: 45512.37 | G18: 22501.56 | H18: 0 | I18: 0 | J18: 0 | K18: 0 | L18: 45512.37 | M18: 23010.81 | N18: 22501.56 | O18: =N18*'FY2014 SUMMARY'!$B$3 -> 9790.9517
A19: 879 | B19: DELANO PUBLIC SCHOOL DISTRICT | C19: 1 | D19: REGION 3 - CENTRAL | E19: 867 | F19: 39289.47 | G19: 23573.68 | H19: 0 | I19: 0 | J19: 0 | K19: 0 | L19: 39289.47 | M19: 15715.79 | N19: 23573.68 | O19: =N19*'FY2014 SUMMARY'!$B$3 -> 10257.456
A20: 881 | B20: MAPLE LAKE PUBLIC SCHOOL DISTRICT | C20: 1 | D20: REGION 3 - CENTRAL | E20: 867 | F20: 17464.05 | G20: 8732.02 | H20: 0 | I20: 0 | J20: 0 | K20: 0 | L20: 17464.05 | M20: 8732.03 | N20: 8732.02 | O20: =N20*'FY2014 SUMMARY'!$B$3 -> 3799.5048
A21: 882 | B21: MONTICELLO PUBLIC SCHOOL DISTRICT | C21: 1 | D21: REGION 3 - CENTRAL | E21: 867 | F21: 23449.95 | G21: 12921.98 | H21: 0 | I21: 0 | J21: 7328 | K21: 0 | L21: 30777.95 | M21: 10527.97 | N21: 20249.98 | O21: =N21*'FY2014 SUMMARY'!$B$3 -> 8811.2369
A22: 883 | B22: ROCKFORD PUBLIC SCHOOL DISTRICT | C22: 1 | D22: REGION 3 - CENTRAL | E22: 867 | F22: 16290.99 | G22: 8145.49 | H22: 0 | I22: 0 | J22: 0 | K22: 0 | L22: 16290.99 | M22: 8145.5 | N22: 8145.49 | O22: =N22*'FY2014 SUMMARY'!$B$3 -> 3544.292
A23: 2174 | B23: PINE RIVER-BACKUS SCHOOL DISTRICT | C23: 1 | D23: REGION 3 - CENTRAL | E23: 867 | F23: 19132.53 | G23: 4001.27 | H23: 0 | I23: 0 | J23: 0 | K23: 0 | L23: 19132.53 | M23: 15131.26 | N23: 4001.27 | O23: =N23*'FY2014 SUMMARY'!$B$3 -> 1741.0456
A24: 2687 | B24: HOWARD LAKE-WAVERLY-WINSTED | C24: 1 | D24: REGION 3 - CENTRAL | E24: 867 | F24: 99217.4 | G24: 44647.83 | H24: 0 | I24: 0 | J24: 0 | K24: 0 | L24: 99217.4 | M24: 54569.57 | N24: 44647.83 | O24: =N24*'FY2014 SUMMARY'!$B$3 -> 19427.308
A25: line left blank intentionally | N25: =SUM(N3:N24) -> 463943.98 | O25: =SUM(O3:O24) -> 201872.81
A26: REGION 2-ARCC 0868-82 | C26: =N37 -> 85674.13
A27: Dist Num | B27: District Or School Name | C27: Dist Type | D27: Cluster Name | E27: Cluster Num | F27: Line Lease Before Erate | G27: Line Lease After Erate | H27: Install Before E Rate | I27: Install After E Rate | J27: COOP Costs | K27: Maint Costs | L27: Total Before E Rate | M27: Total E Rate Discount | N27: Total After E Rate
A28: 4 | B28: MCGREGOR PUBLIC SCHOOL DISTRICT | C28: 1 | D28: REGION 2 - ARCC | E28: 868 | F28: 13471.49 | G28: 2020.72 | H28: 0 | I28: 0 | J28: 847.65 | K28: 0 | L28: 14319.14 | M28: 11450.77 | N28: 2868.37 | O28: =N28*'FY2014 SUMMARY'!$B$3 -> 1248.0944
A29: 91 | B29: BARNUM PUBLIC SCHOOL DISTRICT | C29: 1 | D29: REGION 2 - ARCC | E29: 868 | F29: 9058.27 | G29: 3079.81 | H29: 0 | I29: 0 | J29: 1680.17 | K29: 0 | L29: 10738.44 | M29: 5978.46 | N29: 4759.98 | O29: =N29*'FY2014 SUMMARY'!$B$3 -> 2071.1779
A30: 94 | B30: CLOQUET PUBLIC SCHOOL DISTRICT | C30: 1 | D30: REGION 2 - ARCC | E30: 868 | F30: 39624 | G30: 13076 | H30: 0 | I30: 0 | J30: 5829.42 | K30: 0 | L30: 45453.42 | M30: 26548 | N30: 18905.42 | O30: =N30*'FY2014 SUMMARY'!$B$3 -> 8226.1876
A31: 95 | B31: CROMWELL-WRIGHT PUBLIC SCHOOLS | C31: 1 | D31: REGION 2 - ARCC | E31: 868 | F31: 19882.84 | G31: 6022.84 | H31: 0 | I31: 0 | J31: 673.64 | K31: 0 | L31: 20556.48 | M31: 13860 | N31: 6696.48 | O31: =N31*'FY2014 SUMMARY'!$B$3 -> 2913.7941
A32: 99 | B32: ESKO PUBLIC SCHOOL DISTRICT | C32: 1 | D32: REGION 2 - ARCC | E32: 868 | F32: 11400 | G32: 5700 | H32: 0 | I32: 0 | J32: 2668.11 | K32: 0 | L32: 14068.11 | M32: 5700 | N32: 8368.11 | O32: =N32*'FY2014 SUMMARY'!$B$3 -> 3641.1591
A33: 362 | B33: LITTLEFORK-BIG FALLS SCHOOL DIST. | C33: 1 | D33: REGION 2 - ARCC | E33: 868 | F33: 13098 | G33: 3929 | H33: 0 | I33: 0 | J33: 636.87 | K33: 0 | L33: 13734.87 | M33: 9169 | N33: 4565.87 | O33: =N33*'FY2014 SUMMARY'!$B$3 -> 1986.7161
A34: 577 | B34: WILLOW RIVER PUBLIC SCHOOL DISTRICT | C34: 1 | D34: REGION 2 - ARCC | E34: 868 | F34: 20026.38 | G34: 8482.38 | H34: 0 | I34: 0 | J34: 948.21 | K34: 0 | L34: 20974.59 | M34: 11544 | N34: 9430.59 | O34: =N34*'FY2014 SUMMARY'!$B$3 -> 4103.4689
A35: 696 | B35: ELY PUBLIC SCHOOL DISTRICT | C35: 1 | D35: REGION 2 - ARCC | E35: 868 | F35: 23250 | G35: 7290 | H35: 0 | I35: 0 | J35: 2374.98 | K35: 0 | L35: 25624.98 | M35: 15960 | N35: 9664.98 | O35: =N35*'FY2014 SUMMARY'!$B$3 -> 4205.4574
A36: 700 | B36: HERMANTOWN PUBLIC SCHOOL DISTRICT | C36: 1 | D36: REGION 2 - ARCC | E36: 868 | F36: 7800 | G36: 4680 | H36: 18500 | I36: 11100 | J36: 4634.33 | K36: 0 | L36: 30934.33 | M36: 10520 | N36: 20414.33 | O36: =N36*'FY2014 SUMMARY'!$B$3 -> 8882.7494
A37: line left blank intentionally | N37: =SUM(N28:N36) -> 85674.13 | O37: =SUM(O28:O36) -> 37278.805
A38: REGION 1-NWLINKS 0869-82 | C38: =N102 -> 1044903.4
A39: Dist Num | B39: District Or School Name | C39: Dist Type | D39: Cluster Name | E39: Cluster Num | F39: Line Lease Before Erate | G39: Line Lease After Erate | H39: Install Before E Rate | I39: Install After E Rate | J39: COOP Costs | K39: Maint Costs | L39: Total Before E Rate | M39: Total E Rate Discount | N39: Total After E Rate
A40: 23 | B40: FRAZEE-VERGAS PUBLIC SCHOOL DIST. | C40: 1 | D40: REGION 1 - NWLinks | E40: 0869 | F40: 56337.64 | G40: 16901.29 | H40: 0 | I40: 0 | J40: 750 | K40: 0 | L40: 57087.64 | M40: 39436.35 | N40: =L40-M40 -> 17651.29 | O40: =N40*'FY2014 SUMMARY'!$B$3 -> 7680.4865
A41: 25 | B41: PINE POINT PUBLIC SCHOOL DISTRICT | C41: 1 | D41: REGION 1 - NWLinks | E41: 869 | F41: 16027.97 | G41: 1602.8 | H41: 800 | I41: 80 | J41: 750 | K41: 0 | L41: 17577.97 | M41: 15145.17 | N41: 2432.8 | O41: no tech plan
A42: 32 | B42: BLACKDUCK PUBLIC SCHOOL DISTRICT | C42: 1 | D42: REGION 1 - NWLinks | E42: 0869 | F42: 51368.86 | G42: 10974.57 | H42: 100 | I42: 20 | J42: 1700 | K42: 0 | L42: 53168.86 | M42: 40474.29 | N42: 12694.57 | O42: =N42*'FY2014 SUMMARY'!$B$3 -> 5523.7024
A43: 36 | B43: KELLIHER PUBLIC SCHOOL DISTRICT | C43: 1 | D43: REGION 1 - NWLinks | E43: 869 | F43: 32208.99 | G43: 3220.9 | H43: 100 | I43: 10 | J43: 750 | K43: 0 | L43: 33058.99 | M43: 29078.09 | N43: 3980.9 | O43: =N43*'FY2014 SUMMARY'!$B$3 -> 1732.1821
A44: 38 | B44: RED LAKE PUBLIC SCHOOL DISTRICT | C44: 1 | D44: REGION 1 - NWLinks | E44: 0869 | F44: 103315.54 | G44: 10758.66 | H44: 0 | I44: 0 | J44: 750 | K44: 0 | L44: 104065.54 | M44: 92556.88 | N44: 11508.66 | O44: =N44*'FY2014 SUMMARY'!$B$3 -> 5007.6854
A45: 113 | B45: WALKER-HACKENSACK-AKELEY SCHL. DIST | C45: 1 | D45: REGION 1 - NWLinks | E45: 869 | F45: 45987.5 | G45: 11702.76 | H45: 500 | I45: 120 | J45: 1700 | K45: 0 | L45: 48187.5 | M45: 34664.74 | N45: 13522.76 | O45: =N45*'FY2014 SUMMARY'!$B$3 -> 5884.0671
A46: 146 | B46: BARNESVILLE PUBLIC SCHOOL DIST. | C46: 1 | D46: REGION 1 - NWLinks | E46: 869 | F46: 36168.48 | G46: 18084.24 | H46: 100 | I46: 50 | J46: 750 | K46: 0 | L46: 37018.48 | M46: 18134.24 | N46: 18884.24 | O46: =N46*'FY2014 SUMMARY'!$B$3 -> 8216.9717
A47: 150 | B47: HAWLEY PUBLIC SCHOOL DISTRICT | C47: 1 | D47: REGION 1 - NWLinks | E47: 0869 | F47: 39588.11 | G47: 21773.46 | H47: 100 | I47: 55 | J47: 750 | K47: 0 | L47: 40438.11 | M47: 17859.65 | N47: 22578.46 | O47: =N47*'FY2014 SUMMARY'!$B$3 -> 9824.4127
A48: 152 | B48: MOORHEAD PUBLIC SCHOOL DISTRICT | C48: 1 | D48: REGION 1 - NWLinks | E48: 0869 | F48: 60135.19 | G48: 26271.78 | H48: 0 | I48: 0 | J48: 2650 | K48: 0 | L48: 62785.19 | M48: 33863.41 | N48: 28921.78 | O48: =N48*'FY2014 SUMMARY'!$B$3 -> 12584.539
A49: 162 | B49: BAGLEY PUBLIC SCHOOL DISTRICT | C49: 1 | D49: REGION 1 - NWLinks | E49: 869 | F49: 39563.37 | G49: 10160.97 | H49: 100 | I49: 24 | J49: 1700 | K49: 0 | L49: 41363.37 | M49: 29478.4 | N49: 11884.97 | O49: =N49*'FY2014 SUMMARY'!$B$3 -> 5171.4267
A50: 261 | B50: ASHBY PUBLIC SCHOOL DISTRICT | C50: 1 | D50: REGION 1 - NWLinks | E50: 0869 | F50: 24708.8 | G50: 8979.15 | H50: 100 | I50: 34 | J50: 2650 | K50: 0 | L50: 27458.8 | M50: 15795.65 | N50: 11663.15 | O50: =N50*'FY2014 SUMMARY'!$B$3 -> 5074.9076
A51: 264 | B51: HERMAN-NORCROSS SCHOOL DISTRICT | C51: 1 | D51: REGION 1 - NWLinks | E51: 0869 | F51: 28408.81 | G51: 10237.16 | H51: 0 | I51: 0 | J51: 1700 | K51: 0 | L51: 30108.81 | M51: 18171.65 | N51: 11937.16 | O51: =N51*'FY2014 SUMMARY'!$B$3 -> 5194.1357
A52: 308 | B52: NEVIS PUBLIC SCHOOL DISTRICT | C52: 1 | D52: REGION 1 - NWLinks | E52: 869 | F52: 32596.46 | G52: 8149.11 | H52: 100 | I52: 25 | J52: 750 | K52: 0 | L52: 33446.46 | M52: 24522.35 | N52: 8924.11 | O52: =N52*'FY2014 SUMMARY'!$B$3 -> 3883.0877
A53: 309 | B53: PARK RAPIDS PUBLIC SCHOOL DISTRICT | C53: 1 | D53: REGION 1 - NWLinks | E53: 869 | F53: 19344 | G53: 4449.12 | H53: 0 | I53: 0 | J53: 750 | K53: 0 | L53: 20094 | M53: 14894.88 | N53: 5199.12 | O53: =N53*'FY2014 SUMMARY'!$B$3 -> 2262.2579
... A68: 564 | B68: THIEF RIVER FALLS SCHOOL DISTRICT | C68: 1 | D68: REGION 1 - NWLinks | E68: 869 | F68: 69365.99 | G68: 24278.09 | H68: 0 | I68: 0 | J68: 750 | K68: 0 | L68: 70115.99 | M68: 45087.9 | N68: 25028.09 | O68: =N68*'FY2014 SUMMARY'!$B$3 -> 10890.304
A69: 592 | B69: CLIMAX-SHELLY PUBLIC SCHOOLS | C69: 1 | D69: REGION 1 - NWLinks | E69: 869 | F69: 27085.89 | G69: 5417.18 | H69: 0 | I69: 0 | J69: 750 | K69: 0 | L69: 27835.89 | M69: 21668.71 | N69: 6167.18 | O69: =N69*'FY2014 SUMMARY'!$B$3 -> 2683.4833
A70: 593 | B70: CROOKSTON PUBLIC SCHOOL DISTRICT | C70: 1 | D70: REGION 1 - NWLinks | E70: 0869 | F70: 156240.98 | G70: 50592.79 | H70: 100 | I70: 32 | J70: 1700 | K70: 0 | L70: 158040.98 | M70: 105716.19 | N70: 52324.79 | O70: =N70*'FY2014 SUMMARY'!$B$3 -> 22767.732
A71: 595 | B71: EAST GRAND FORKS PUBLIC SCHOOL DIST | C71: 1 | D71: REGION 1 - NWLinks | E71: 869 | F71: 130583.95 | G71: 63135.81 | H71: 500 | I71: 240 | J71: 1700 | K71: 0 | L71: 132783.95 | M71: 67708.14 | N71: 65075.81 | O71: =N71*'FY2014 SUMMARY'!$B$3 -> 28315.997
A72: 599 | B72: FERTILE-BELTRAMI SCHOOL DISTRICT | C72: 1 | D72: REGION 1 - NWLinks | E72: 0869 | F72: 29522.76 | G72: 10902.36 | H72: 100 | I72: 35 | J72: 1700 | K72: 0 | L72: 31322.76 | M72: 18685.4 | N72: 12637.36 | O72: =N72*'FY2014 SUMMARY'!$B$3 -> 5498.809
A73: 600 | B73: FISHER PUBLIC SCHOOL DISTRICT | C73: 1 | D73: REGION 1 - NWLinks | E73: 869 | F73: 45777.21 | G73: 16022.02 | H73: 100 | I73: 35 | J73: 750 | K73: 0 | L73: 46627.21 | M73: 29820.19 | N73: 16807.02 | O73: =N73*'FY2014 SUMMARY'!$B$3 -> 7313.125
A74: 601 | B74: FOSSTON PUBLIC SCHOOL DISTRICT | C74: 1 | D74: REGION 1 - NWLinks | E74: 0869 | F74: 25436.29 | G74: 8244.08 | H74: 100 | I74: 30 | J74: 1700 | K74: 0 | L74: 27236.29 | M74: 17262.21 | N74: 9974.08 | O74: =N74*'FY2014 SUMMARY'!$B$3 -> 4339.954
A75: 630 | B75: RED LAKE FALLS PUBLIC SCHOOL DIST. | C75: 1 | D75: REGION 1 - NWLinks | E75: 0869 | F75: 25916.92 | G75: 9389.91 | H75: 0 | I75: 0 | J75: 2650 | K75: 0 | L75: 28566.92 | M75: 16527.01 | N75: 12039.91 | O75: =N75*'FY2014 SUMMARY'!$B$3 -> 5238.8447
A76: 676 | B76: BADGER PUBLIC SCHOOL DISTRICT | C76: 1 | D76: REGION 1 - NWLinks | E76: 0869 | F76: 58877.46 | G76: 15376.36 | H76: 0 | I76: 0 | J76: 1700 | K76: 0 | L76: 60577.46 | M76: 43501.1 | N76: 17076.36 | O76: =N76*'FY2014 SUMMARY'!$B$3 -> 7430.3211
A77: 682 | B77: ROSEAU PUBLIC SCHOOL DISTRICT | C77: 1 | D77: REGION 1 - NWLinks | E77: 869 | F77: 59362.81 | G77: 24270.72 | H77: 0 | I77: 0 | J77: 1700 | K77: 0 | L77: 61062.81 | M77: 35092.09 | N77: 25970.72 | O77: =N77*'FY2014 SUMMARY'!$B$3 -> 11300.464
A78: 690 | B78: WARROAD PUBLIC SCHOOL DISTRICT | C78: 1 | D78: REGION 1 - NWLinks | E78: 0869 | F78: 67902.62 | G78: 24241.89 | H78: 100 | I78: 34 | J78: 2650 | K78: 0 | L78: 70652.62 | M78: 43726.73 | N78: 26925.89 | O78: =N78*'FY2014 SUMMARY'!$B$3 -> 11716.081
A79: 768 | B79: HANCOCK PUBLIC SCHOOL DISTRICT | C79: 1 | D79: REGION 1 - NWLinks | E79: 869 | F79: 32935.45 | G79: 12417.4 | H79: 0 | I79: 0 | J79: 2650 | K79: 0 | L79: 35585.45 | M79: 20518.05 | N79: 15067.4 | O79: =N79*'FY2014 SUMMARY'!$B$3 -> 6556.1759
A80: 771 | B80: CHOKIO-ALBERTA PUBLIC SCHOOL DIST. | C80: 1 | D80: REGION 1 - NWLinks | E80: 869 | F80: 17186.39 | G80: 5155.92 | H80: 100 | I80: 30 | J80: 750 | K80: 0 | L80: 18036.39 | M80: 12100.47 | N80: 5935.92 | O80: =N80*'FY2014 SUMMARY'!$B$3 -> 2582.8567
A81: 801 | B81: BROWNS VALLEY PUBLIC SCHOOL DIST. | C81: 1 | D81: REGION 1 - NWLinks | E81: 0869 | F81: 16324.73 | G81: 2285.46 | H81: 1300 | I81: 182 | J81: 750 | K81: 0 | L81: 18374.73 | M81: 15157.27 | N81: 3217.46 | O81: =N81*'FY2014 SUMMARY'!$B$3 -> 1399.9916
A82: 803 | B82: WHEATON AREA PUBLIC SCHOOL DISTRICT | C82: 1 | D82: REGION 1 - NWLinks | E82: 0869 | F82: 39884.27 | G82: 14918.98 | H82: 100 | I82: 36 | J82: 2650 | K82: 0 | L82: 42634.27 | M82: 25029.29 | N82: 17604.98 | O82: =N82*'FY2014 SUMMARY'!$B$3 -> 7660.3359
A83: 846 | B83: BRECKENRIDGE PUBLIC SCHOOL DISTRICT | C83: 1 | D83: REGION 1 - NWLinks | E83: 869 | F83: 29970.35 | G83: 10189.92 | H83: 100 | I83: 34 | J83: 750 | K83: 0 | L83: 30820.35 | M83: 19846.43 | N83: 10973.92 | O83: =N83*'FY2014 SUMMARY'!$B$3 -> 4775.0076
A84: 850 | B84: ROTHSAY PUBLIC SCHOOL DISTRICT | C84: 1 | D84: REGION 1 - NWLinks | E84: 0869 | F84: 32018.01 | G84: 9605.41 | H84: 100 | I84: 30 | J84: 750 | K84: 0 | L84: 32868.01 | M84: 22482.6 | N84: 10385.41 | O84: =N84*'FY2014 SUMMARY'!$B$3 -> 4518.9333
A85: 852 | B85: CAMPBELL-TINTAH PUBLIC SCHOOL DIST. | C85: 1 | D85: REGION 1 - NWLinks | E85: 0869 | F85: 31617.39 | G85: 7024.28 | H85: 100 | I85: 20 | J85: 2650 | K85: 0 | L85: 34367.39 | M85: 24673.11 | N85: 9694.28 | O85: =N85*'FY2014 SUMMARY'!$B$3 -> 4218.2065
A86: 914 | B86: ULEN-HITTERDAL PUBLIC SCHOOL DIST | C86: 1 | D86: REGION 1 - NWLinks | E86: 0869 | F86: 25360.76 | G86: 12680.38 | H86: 100 | I86: 50 | J86: 750 | K86: 0 | L86: 26210.76 | M86: 12730.38 | N86: 13480.38 | O86: =N86*'FY2014 SUMMARY'!$B$3 -> 5865.6266
A87: 2164 | B87: DILWORTH-GLYNDON-FELTON | C87: 1 | D87: REGION 1 - NWLinks | E87: 869 | F87: 28517.2 | G87: 14258.6 | H87: 0 | I87: 0 | J87: 750 | K87: 0 | L87: 29267.2 | M87: 14258.6 | N87: 15008.6 | O87: =N87*'FY2014 SUMMARY'!$B$3 -> 6530.5907
A88: 2171 | B88: KITTSON CENTRAL SCHOOL DISTRICT | C88: 1 | D88: REGION 1 - NWLinks | E88: 869 | F88: 47740.74 | G88: 21027.84 | H88: 100 | I88: 43 | J88: 1700 | K88: 0 | L88: 49540.74 | M88: 26769.9 | N88: 22770.84 | O88: =N88*'FY2014 SUMMARY'!$B$3 -> 9908.1217
A89: 2176 | B89: WARREN-ALVARADO-OSLO SCHOOL DIST. | C89: 1 | D89: REGION 1 - NWLinks | E89: 869 | F89: 36255.89 | G89: 10596.74 | H89: 100 | I89: 24 | J89: 1700 | K89: 0 | L89: 38055.89 | M89: 25735.15 | N89: 12320.74 | O89: =N89*'FY2014 SUMMARY'!$B$3 -> 5361.0403
A90: 2215 | B90: NORMAN COUNTY EAST SCHOOL DISTRICT | C90: 1 | D90: REGION 1 - NWLinks | E90: 869 | F90: 24461.77 | G90: 6115.45 | H90: 100 | I90: 25 | J90: 750 | K90: 0 | L90: 25311.77 | M90: 18421.32 | N90: 6890.45 | O90: =N90*'FY2014 SUMMARY'!$B$3 -> 2998.1949
A91: 2311 | B91: CLEARBROOK-GONVICK SCHOOL DISTRICT | C91: 1 | D91: REGION 1 - NWLinks | E91: 0869 | F91: 78211.12 | G91: 19552.78 | H91: 500 | I91: 125 | J91: 750 | K91: 0 | L91: 79461.12 | M91: 59033.34 | N91: 20427.78 | O91: =N91*'FY2014 SUMMARY'!$B$3 -> 8888.6018
A92: 2358 | B92: TRI-COUNTY SCHOOL DISTRICT | C92: 1 | D92: REGION 1 - NWLinks | E92: 0869 | F92: 67798.81 | G92: 17606.71 | H92: 0 | I92: 0 | J92: 2650 | K92: 0 | L92: 70448.81 | M92: 50192.1 | N92: 20256.71 | O92: =N92*'FY2014 SUMMARY'!$B$3 -> 8814.1653
A93: 2527 | B93: NORMAN COUNTY WEST SCHOOL DISTRICT | C93: 1 | D93: REGION 1 - NWLinks | E93: 0869 | F93: 33401.76 | G93: 8016.43 | H93: 100 | I93: 24 | J93: 750 | K93: 0 | L93: 34251.76 | M93: 25461.33 | N93: 8790.43 | O93: =N93*'FY2014 SUMMARY'!$B$3 -> 3824.9204
A94: 2609 | B94: WIN-E-MAC SCHOOL DISTRICT | C94: 1 | D94: REGION 1 - NWLinks | E94: 869 | F94: 21573.92 | G94: 6472.18 | H94: 100 | I94: 30 | J94: 1700 | K94: 0 | L94: 23373.92 | M94: 15171.74 | N94: 8202.18 | O94: =N94*'FY2014 SUMMARY'!$B$3 -> 3568.9591
... A101: 2906 | B101: RED LAKE COUNTY CENTRAL PUBLIC SCH | C101: 1 | D101: REGION 1 - NWLinks | E101: 0869 | F101: 41467.49 | G101: 8994.3 | H101: 100 | I101: 20 | J101: 3400 | K101: 0 | L101: 44967.49 | M101: 32553.19 | N101: 12414.3 | O101: =N101*'FY2014 SUMMARY'!$B$3 -> 5401.7504
A102: line left blank intentionally | N102: =SUM(N40:N101) -> 1044903.4 | O102: =SUM(O40:O101) -> 453603.17
A103: REGION 10-SOUTHEAST SERVICE COOP 0921-83 | C103: =N125 -> 336031.94
A104: Dist Num | B104: District Or School Name | C104: Dist Type | D104: Cluster Name | E104: Cluster Num | F104: Line Lease Before Erate | G104: Line Lease After Erate | H104: Install Before E Rate | I104: Install After E Rate | J104: COOP Costs | K104: Maint Costs | L104: Total Before E Rate | M104: Total E Rate Discount | N104: Total After E Rate
A105: 255 | B105: PINE ISLAND PUBLIC SCHOOL DIST. | C105: 1 | D105: HOUSTON PUBLIC SCHOOL DISTRICT | E105: 294 | F105: 46215.84 | G105: 21259.32 | H105: 0 | I105: 0 | J105: 3263.97 | K105: 0 | L105: 49479.81 | M105: 24956.52 | N105: 24523.29 | O105: =N105*'FY2014 SUMMARY'!$B$3 -> 10670.653
A106: 531 | B106: BYRON PUBLIC SCHOOL DISTRICT | C106: 1 | D106: HOUSTON PUBLIC SCHOOL DISTRICT | E106: 294 | F106: 21980 | G106: 13188 | H106: 0 | I106: 0 | J106: 3025.95 | K106: 5036.47 | L106: 30042.42 | M106: 8792 | N106: 21250.42 | O106: =N106*'FY2014 SUMMARY'!$B$3 -> 9246.5516
A107: 533 | B107: DOVER-EYOTA PUBLIC SCHOOL DISTRICT | C107: 1 | D107: HOUSTON PUBLIC SCHOOL DISTRICT | E107: 294 | F107: 23625.6 | G107: 14179.2 | H107: 0 | I107: 0 | J107: 750 | K107: 0 | L107: 24375.6 | M107: 9446.4 | N107: 14929.2 | O107: =N107*'FY2014 SUMMARY'!$B$3 -> 6496.0419
A108: 227 | B108: CHATFIELD PUBLIC SCHOOLS | C108: 1 | D108: REGION 10 - SOUTHEAST SERVICE COOP | E108: 921 | F108: 41970.67 | G108: 23083.87 | H108: 0 | I108: 0 | J108: 2730.62 | K108: 0 | L108: 44701.29 | M108: 18886.8 | N108: 25814.49 | O108: =N108*'FY2014 SUMMARY'!$B$3 -> 11232.485
A109: 229 | B109: LANESBORO PUBLIC SCHOOL DISTRICT | C109: 1 | D109: REGION 10 - SOUTHEAST SERVICE COOP | E109: 921 | F109: 18826 | G109: 12400 | H109: 0 | I109: 0 | J109: 750 | K109: 0 | L109: 19576 | M109: 6426 | N109: 13150 | O109: =N109*'FY2014 SUMMARY'!$B$3 -> 5721.8706
A110: 238 | B110: MABEL-CANTON PUBLIC SCHOOL DIST. | C110: 1 | D110: REGION 10 - SOUTHEAST SERVICE COOP | E110: 921 | F110: 20634.45 | G110: 13206.05 | H110: 0 | I110: 0 | J110: 1200 | K110: 0 | L110: 21834.45 | M110: 7428.4 | N110: 14406.05 | O110: =N110*'FY2014 SUMMARY'!$B$3 -> 6268.4072
A111: 239 | B111: RUSHFORD-PETERSON PUBLIC SCHOOLS | C111: 1 | D111: REGION 10 - SOUTHEAST SERVICE COOP | E111: 921 | F111: 29940 | G111: 7110 | H111: 0 | I111: 0 | J111: 750 | K111: 0 | L111: 30690 | M111: 22830 | N111: 7860 | O111: =N111*'FY2014 SUMMARY'!$B$3 -> 3420.0687
A112: 252 | B112: CANNON FALLS PUBLIC SCHOOL DISTRICT | C112: 1 | D112: REGION 10 - SOUTHEAST SERVICE COOP | E112: 921 | F112: 42937.08 | G112: 19321.69 | H112: 0 | I112: 0 | J112: 2557.11 | K112: 0 | L112: 45494.19 | M112: 23615.39 | N112: 21878.8 | O112: =N112*'FY2014 SUMMARY'!$B$3 -> 9519.9743
A113: 256 | B113: RED WING PUBLIC SCHOOL DISTRICT | C113: 1 | D113: REGION 10 - SOUTHEAST SERVICE COOP | E113: 921 | F113: 21511.3 | G113: 7744.07 | H113: 0 | I113: 0 | J113: 2128.37 | K113: 0 | L113: 23639.67 | M113: 13767.23 | N113: 9872.44 | O113: =N113*'FY2014 SUMMARY'!$B$3 -> 4295.7281
A114: 294 | B114: HOUSTON PUBLIC SCHOOL DISTRICT | C114: 1 | D114: REGION 10 - SOUTHEAST SERVICE COOP | E114: 921 | F114: 47952.32 | G114: 27332.84 | H114: 0 | I114: 0 | J114: 1183.59 | K114: 0 | L114: 49135.91 | M114: 20619.48 | N114: 28516.43 | O114: =N114*'FY2014 SUMMARY'!$B$3 -> 12408.161
A115: 495 | B115: GRAND MEADOW PUBLIC SCHOOL DISTRICT | C115: 1 | D115: REGION 10 - SOUTHEAST SERVICE COOP | E115: 921 | F115: 49505.16 | G115: 14900.62 | H115: 0 | I115: 0 | J115: 2190.23 | K115: 0 | L115: 51695.39 | M115: 34604.54 | N115: 17090.85 | O115: =N115*'FY2014 SUMMARY'!$B$3 -> 7436.626
A116: 497 | B116: LYLE PUBLIC SCHOOL DISTRICT | C116: 1 | D116: REGION 10 - SOUTHEAST SERVICE COOP | E116: 921 | F116: 4588.83 | G116: 2845.83 | H116: 0 | I116: 0 | J116: 1988.65 | K116: 0 | L116: 6577.48 | M116: 1743 | N116: 4834.48 | O116: =N116*'FY2014 SUMMARY'!$B$3 -> 2103.5946
A117: 499 | B117: LEROY-OSTRANDER PUBLIC SCHOOLS | C117: 1 | D117: REGION 10 - SOUTHEAST SERVICE COOP | E117: 921 | F117: 15780 | G117: 6834 | H117: 0 | I117: 0 | J117: 1809.49 | K117: 0 | L117: 17589.49 | M117: 8946 | N117: 8643.49 | O117: =N117*'FY2014 SUMMARY'!$B$3 -> 3760.9834
A118: 500 | B118: SOUTHLAND PUBLIC SCHOOL DISTRICT | C118: 1 | D118: REGION 10 - SOUTHEAST SERVICE COOP | E118: 921 | F118: 24550.22 | G118: 9083.84 | H118: 0 | I118: 0 | J118: 1978.22 | K118: 0 | L118: 26528.44 | M118: 15466.38 | N118: 11062.06 | O118: =N118*'FY2014 SUMMARY'!$B$3 -> 4813.3594
A119: 534 | B119: STEWARTVILLE PUBLIC SCHOOL DISTRICT | C119: 1 | D119: REGION 10 - SOUTHEAST SERVICE COOP | E119: 921 | F119: 37693.08 | G119: 19235.58 | H119: 0 | I119: 0 | J119: 1058.7 | K119: 0 | L119: 38751.78 | M119: 18457.5 | N119: 20294.28 | O119: =N119*'FY2014 SUMMARY'!$B$3 -> 8830.5129
... A124: 2899 | B124: PLAINVIEW-ELGIN-MILLVILLE | C124: 1 | D124: REGION 10 - SOUTHEAST SERVICE COOP | E124: 921 | F124: 31452 | G124: 13524.36 | H124: 0 | I124: 0 | J124: 1398 | K124: 0 | L124: 32850 | M124: 17927.64 | N124: 14922.36 | O124: =N124*'FY2014 SUMMARY'!$B$3 -> 6493.0656
...
