Workbook
Name TitleRegion1.a6.m7.13: 'Year End Totals'!$A$1
Name TitleRegion1.a6.p35.1: October!$A$1
Name TitleRegion1.a6.p35.10: July!$A$1
Name TitleRegion1.a6.p35.11: August!$A$1
Name TitleRegion1.a6.p35.12: September!$A$1
Name TitleRegion1.a6.p35.2: November!$A$1
Name TitleRegion1.a6.p35.3: December!$A$1
Name TitleRegion1.a6.p35.4: January!$A$1
Name TitleRegion1.a6.p35.5: February!$A$1
Name TitleRegion1.a6.p35.6: March!$A$1
Name TitleRegion1.a6.p35.7: April!$A$1
Name TitleRegion1.a6.p35.8: May!$A$1
Name TitleRegion1.a6.p35.9: June!$A$1

Sheet October
A1: Year End: | B1: October
A2: Year:
A3: Monthly CACFP Reimbursement:
A4: Monthly Food Program Expenses: | F4: =P35 -> 0
A5: Amount Needed from Other Funding Source: | F5: =F4-F3 -> 0
A6: Date | B6: Check Number | C6: Name (Payee on Check) | D6: Total Amount of Check | E6: Administrative Salaries and Benefits | F6: Travel Expenses (include monitoring staff) | G6: Printing, Office Supplies, Communications | H6: Staff Training | I6: Food Service Salaries and Benefits | J6: Food (include delivery charges) | K6: Purchased Vended Meals | L6: Food Service Equipment | M6: Allowable Nonfood Supplies | N6: Occupancy/ Utilities | O6: Misc. | P6: Specify Misc.
P34: TOTAL
A35: Monthly CACFP Expenses: | D35: =SUM(D7:D34) -> 0 | E35: =SUM(E7:E34) -> 0 | F35: =SUM(F7:F34) -> 0 | G35: =SUM(G7:G34) -> 0 | H35: =SUM(H7:H34) -> 0 | I35: =SUM(I7:I34) -> 0 | J35: =SUM(J7:J34) -> 0 | K35: =SUM(K7:K34) -> 0 | ... O35: =SUM(O7:O34) -> 0 | P35: =SUM(E35:O35) -> 0
A36: End of worksheet

Sheet November
A1: Year End: | B1: November
A2: Year:
A3: Monthly CACFP Reimbursement:
A4: Monthly Food Program Expenses: | F4: =P35 -> 0
A5: Amount Needed from Other Funding Source: | F5: =F4-F3 -> 0
A6: Date | B6: Check Number | C6: Name (Payee on Check) | D6: Total Amount of Check | E6: Administrative Salaries and Benefits | F6: Travel Expenses (include monitoring staff) | G6: Printing, Office Supplies, Communications | H6: Staff Training | I6: Food Service Salaries and Benefits | J6: Food (include delivery charges) | K6: Purchased Vended Meals | L6: Food Service Equipment | M6: Allowable Nonfood Supplies | N6: Occupancy/ Utilities | O6: Misc. | P6: Specify Misc.
P34: TOTAL
A35: Monthly CACFP Expenses: | D35: =SUM(D7:D34) -> 0 | E35: =SUM(E7:E34) -> 0 | F35: =SUM(F7:F34) -> 0 | G35: =SUM(G7:G34) -> 0 | H35: =SUM(H7:H34) -> 0 | I35: =SUM(I7:I34) -> 0 | J35: =SUM(J7:J34) -> 0 | K35: =SUM(K7:K34) -> 0 | ... O35: =SUM(O7:O34) -> 0 | P35: =SUM(E35:O35) -> 0
A36: End of worksheet

Sheet December
A1: Year End: | B1: December
A2: Year:
A3: Monthly CACFP Reimbursement:
A4: Monthly Food Program Expenses: | F4: =P35 -> 0
A5: Amount Needed from Other Funding Source: | F5: =F4-F3 -> 0
A6: Date | B6: Check Number | C6: Name (Payee on Check) | D6: Total Amount of Check | E6: Administrative Salaries and Benefits | F6: Travel Expenses (include monitoring staff) | G6: Printing, Office Supplies, Communications | H6: Staff Training | I6: Food Service Salaries and Benefits | J6: Food (include delivery charges) | K6: Purchased Vended Meals | L6: Food Service Equipment | M6: Allowable Nonfood Supplies | N6: Occupancy/ Utilities | O6: Misc. | P6: Specify Misc.
P34: TOTAL
A35: Monthly CACFP Expenses: | D35: =SUM(D7:D34) -> 0 | E35: =SUM(E7:E34) -> 0 | F35: =SUM(F7:F34) -> 0 | G35: =SUM(G7:G34) -> 0 | H35: =SUM(H7:H34) -> 0 | I35: =SUM(I7:I34) -> 0 | J35: =SUM(J7:J34) -> 0 | K35: =SUM(K7:K34) -> 0 | ... O35: =SUM(O7:O34) -> 0 | P35: =SUM(E35:O35) -> 0
A36: End of worksheet

Sheet January
A1: Year End: | B1: January
A2: Year:
A3: Monthly CACFP Reimbursement:
A4: Monthly Food Program Expenses: | F4: =P35 -> 0
A5: Amount Needed from Other Funding Source: | F5: =F4-F3 -> 0
A6: Date | B6: Check Number | C6: Name (Payee on Check) | D6: Total Amount of Check | E6: Administrative Salaries and Benefits | F6: Travel Expenses (include monitoring staff) | G6: Printing, Office Supplies, Communications | H6: Staff Training | I6: Food Service Salaries and Benefits | J6: Food (include delivery charges) | K6: Purchased Vended Meals | L6: Food Service Equipment | M6: Allowable Nonfood Supplies | N6: Occupancy/ Utilities | O6: Misc. | P6: Specify Misc.
P34: TOTAL
A35: Monthly CACFP Expenses: | D35: =SUM(D7:D34) -> 0 | E35: =SUM(E7:E34) -> 0 | F35: =SUM(F7:F34) -> 0 | G35: =SUM(G7:G34) -> 0 | H35: =SUM(H7:H34) -> 0 | I35: =SUM(I7:I34) -> 0 | J35: =SUM(J7:J34) -> 0 | K35: =SUM(K7:K34) -> 0 | ... O35: =SUM(O7:O34) -> 0 | P35: =SUM(E35:O35) -> 0
A36: End of worksheet

Sheet February
A1: Year End: | B1: February
A2: Year:
A3: Monthly CACFP Reimbursement:
A4: Monthly Food Program Expenses: | F4: =P35 -> 0
A5: Amount Needed from Other Funding Source: | F5: =F4-F3 -> 0
A6: Date | B6: Check Number | C6: Name (Payee on Check) | D6: Total Amount of Check | E6: Administrative Salaries and Benefits | F6: Travel Expenses (include monitoring staff) | G6: Printing, Office Supplies, Communications | H6: Staff Training | I6: Food Service Salaries and Benefits | J6: Food (include delivery charges) | K6: Purchased Vended Meals | L6: Food Service Equipment | M6: Allowable Nonfood Supplies | N6: Occupancy/ Utilities | O6: Misc. | P6: Specify Misc.
P34: TOTAL
A35: Monthly CACFP Expenses: | D35: =SUM(D7:D34) -> 0 | E35: =SUM(E7:E34) -> 0 | F35: =SUM(F7:F34) -> 0 | G35: =SUM(G7:G34) -> 0 | H35: =SUM(H7:H34) -> 0 | I35: =SUM(I7:I34) -> 0 | J35: =SUM(J7:J34) -> 0 | K35: =SUM(K7:K34) -> 0 | ... O35: =SUM(O7:O34) -> 0 | P35: =SUM(E35:O35) -> 0
A36: End of worksheet

Sheet March
A1: Year End: | B1: March
A2: Year:
A3: Monthly CACFP Reimbursement:
A4: Monthly Food Program Expenses: | F4: =P35 -> 0
A5: Amount Needed from Other Funding Source: | F5: =F4-F3 -> 0
A6: Date | B6: Check Number | C6: Name (Payee on Check) | D6: Total Amount of Check | E6: Administrative Salaries and Benefits | F6: Travel Expenses (include monitoring staff) | G6: Printing, Office Supplies, Communications | H6: Staff Training | I6: Food Service Salaries and Benefits | J6: Food (include delivery charges) | K6: Purchased Vended Meals | L6: Food Service Equipment | M6: Allowable Nonfood Supplies | N6: Occupancy/ Utilities | O6: Misc. | P6: Specify Misc.
P34: TOTAL
A35: Monthly CACFP Expenses: | D35: =SUM(D7:D34) -> 0 | E35: =SUM(E7:E34) -> 0 | F35: =SUM(F7:F34) -> 0 | G35: =SUM(G7:G34) -> 0 | H35: =SUM(H7:H34) -> 0 | I35: =SUM(I7:I34) -> 0 | J35: =SUM(J7:J34) -> 0 | K35: =SUM(K7:K34) -> 0 | ... O35: =SUM(O7:O34) -> 0 | P35: =SUM(E35:O35) -> 0
A36: End of worksheet

Sheet April
A1: Year End: | B1: April
A2: Year:
A3: Monthly CACFP Reimbursement:
A4: Monthly Food Program Expenses: | F4: =P35 -> 0
A5: Amount Needed from Other Funding Source: | F5: =F4-F3 -> 0
A6: Date | B6: Check Number | C6: Name (Payee on Check) | D6: Total Amount of Check | E6: Administrative Salaries and Benefits | F6: Travel Expenses (include monitoring staff) | G6: Printing, Office Supplies, Communications | H6: Staff Training | I6: Food Service Salaries and Benefits | J6: Food (include delivery charges) | K6: Purchased Vended Meals | L6: Food Service Equipment | M6: Allowable Nonfood Supplies | N6: Occupancy/ Utilities | O6: Misc. | P6: Specify Misc.
P34: TOTAL
A35: Monthly CACFP Expenses: | D35: =SUM(D7:D34) -> 0 | E35: =SUM(E7:E34) -> 0 | F35: =SUM(F7:F34) -> 0 | G35: =SUM(G7:G34) -> 0 | H35: =SUM(H7:H34) -> 0 | I35: =SUM(I7:I34) -> 0 | J35: =SUM(J7:J34) -> 0 | K35: =SUM(K7:K34) -> 0 | ... O35: =SUM(O7:O34) -> 0 | P35: =SUM(E35:O35) -> 0
A36: End of worksheet

Sheet May
A1: Year End: | B1: May
A2: Year:
A3: Monthly CACFP Reimbursement:
A4: Monthly Food Program Expenses: | F4: =P35 -> 0
A5: Amount Needed from Other Funding Source: | F5: =F4-F3 -> 0
A6: Date | B6: Check Number | C6: Name (Payee on Check) | D6: Total Amount of Check | E6: Administrative Salaries and Benefits | F6: Travel Expenses (include monitoring staff) | G6: Printing, Office Supplies, Communications | H6: Staff Training | I6: Food Service Salaries and Benefits | J6: Food (include delivery charges) | K6: Purchased Vended Meals | L6: Food Service Equipment | M6: Allowable Nonfood Supplies | N6: Occupancy/ Utilities | O6: Misc. | P6: Specify Misc.
P34: TOTAL
A35: Monthly CACFP Expenses: | D35: =SUM(D7:D34) -> 0 | E35: =SUM(E7:E34) -> 0 | F35: =SUM(F7:F34) -> 0 | G35: =SUM(G7:G34) -> 0 | H35: =SUM(H7:H34) -> 0 | I35: =SUM(I7:I34) -> 0 | J35: =SUM(J7:J34) -> 0 | K35: =SUM(K7:K34) -> 0 | ... O35: =SUM(O7:O34) -> 0 | P35: =SUM(E35:O35) -> 0
A36: End of worksheet

Sheet June
A1: Year End: | B1: June
A2: Year:
A3: Monthly CACFP Reimbursement:
A4: Monthly Food Program Expenses: | F4: =P35 -> 0
A5: Amount Needed from Other Funding Source: | F5: =F4-F3 -> 0
A6: Date | B6: Check Number | C6: Name (Payee on Check) | D6: Total Amount of Check | E6: Administrative Salaries and Benefits | F6: Travel Expenses (include monitoring staff) | G6: Printing, Office Supplies, Communications | H6: Staff Training | I6: Food Service Salaries and Benefits | J6: Food (include delivery charges) | K6: Purchased Vended Meals | L6: Food Service Equipment | M6: Allowable Nonfood Supplies | N6: Occupancy/ Utilities | O6: Misc. | P6: Specify Misc.
P34: TOTAL
A35: Monthly CACFP Expenses: | D35: =SUM(D7:D34) -> 0 | E35: =SUM(E7:E34) -> 0 | F35: =SUM(F7:F34) -> 0 | G35: =SUM(G7:G34) -> 0 | H35: =SUM(H7:H34) -> 0 | I35: =SUM(I7:I34) -> 0 | J35: =SUM(J7:J34) -> 0 | K35: =SUM(K7:K34) -> 0 | ... O35: =SUM(O7:O34) -> 0 | P35: =SUM(E35:O35) -> 0
A36: End of worksheet

Sheet July
A1: Year End: | B1: July
A2: Year:
A3: Monthly CACFP Reimbursement:
A4: Monthly Food Program Expenses: | F4: =P35 -> 0
A5: Amount Needed from Other Funding Source: | F5: =F4-F3 -> 0
A6: Date | B6: Check Number | C6: Name (Payee on Check) | D6: Total Amount of Check | E6: Administrative Salaries and Benefits | F6: Travel Expenses (include monitoring staff) | G6: Printing, Office Supplies, Communications | H6: Staff Training | I6: Food Service Salaries and Benefits | J6: Food (include delivery charges) | K6: Purchased Vended Meals | L6: Food Service Equipment | M6: Allowable Nonfood Supplies | N6: Occupancy/ Utilities | O6: Misc. | P6: Specify Misc.
P34: TOTAL
A35: Monthly CACFP Expenses: | D35: =SUM(D7:D34) -> 0 | E35: =SUM(E7:E34) -> 0 | F35: =SUM(F7:F34) -> 0 | G35: =SUM(G7:G34) -> 0 | H35: =SUM(H7:H34) -> 0 | I35: =SUM(I7:I34) -> 0 | J35: =SUM(J7:J34) -> 0 | K35: =SUM(K7:K34) -> 0 | ... O35: =SUM(O7:O34) -> 0 | P35: =SUM(E35:O35) -> 0
A36: End of worksheet

Sheet August
A1: Year End: | B1: August
A2: Year:
A3: Monthly CACFP Reimbursement:
A4: Monthly Food Program Expenses: | F4: =P35 -> 0
A5: Amount Needed from Other Funding Source: | F5: =F4-F3 -> 0
A6: Date | B6: Check Number | C6: Name (Payee on Check) | D6: Total Amount of Check | E6: Administrative Salaries and Benefits | F6: Travel Expenses (include monitoring staff) | G6: Printing, Office Supplies, Communications | H6: Staff Training | I6: Food Service Salaries and Benefits | J6: Food (include delivery charges) | K6: Purchased Vended Meals | L6: Food Service Equipment | M6: Allowable Nonfood Supplies | N6: Occupancy/ Utilities | O6: Misc. | P6: Specify Misc.
P34: TOTAL
A35: Monthly CACFP Expenses: | D35: =SUM(D7:D34) -> 0 | E35: =SUM(E7:E34) -> 0 | F35: =SUM(F7:F34) -> 0 | G35: =SUM(G7:G34) -> 0 | H35: =SUM(H7:H34) -> 0 | I35: =SUM(I7:I34) -> 0 | J35: =SUM(J7:J34) -> 0 | K35: =SUM(K7:K34) -> 0 | ... O35: =SUM(O7:O34) -> 0 | P35: =SUM(E35:O35) -> 0
A36: End of worksheet

Sheet September
A1: Year End: | B1: September
A2: Year:
A3: Monthly CACFP Reimbursement:
A4: Monthly Food Program Expenses: | F4: =P35 -> 0
A5: Amount Needed from Other Funding Source: | F5: =F4-F3 -> 0
A6: Date | B6: Check Number | C6: Name (Payee on Check) | D6: Total Amount of Check | E6: Administrative Salaries and Benefits | F6: Travel Expenses (include monitoring staff) | G6: Printing, Office Supplies, Communications | H6: Staff Training | I6: Food Service Salaries and Benefits | J6: Food (include delivery charges) | K6: Purchased Vended Meals | L6: Food Service Equipment | M6: Allowable Nonfood Supplies | N6: Occupancy/ Utilities | O6: Misc. | P6: Specify Misc.
P34: TOTAL
A35: Monthly CACFP Expenses: | D35: =SUM(D7:D34) -> 0 | E35: =SUM(E7:E34) -> 0 | F35: =SUM(F7:F34) -> 0 | G35: =SUM(G7:G34) -> 0 | H35: =SUM(H7:H34) -> 0 | I35: =SUM(I7:I34) -> 0 | J35: =SUM(J7:J34) -> 0 | K35: =SUM(K7:K34) -> 0 | ... O35: =SUM(O7:O34) -> 0 | P35: =SUM(E35:O35) -> 0
A36: End of worksheet

Sheet Year End Totals
A1: Year End: | B1: October 1 - September 30
A2: Year:
A3: Annual CACFP Reimbursement: | E3: =October!F3+November!F3+December!F3+January!F3+February!F3+March!F3+April!F3+May!F3+June!F3+July!F3+August!F3+September!F3 -> 0
A4: Total Annual Food Program Expenses: | E4: =October!F4+November!F4+December!F4+January!F4+February!F4+March!F4+April!F4+May!F4+June!F4+July!F4+August!F4+September!F4 -> 0
A5: Amount Needed from Other Funding Sources: | E5: =(E4-E3) -> 0
A6: Totals | B6: Administrative Salaries and Benefits | C6: Travel Expenses (include monitoring staff) | D6: Printing, Office Supplies, Communications | E6: Staff Training | F6: Food Service Salaries and Benefits | G6: Food (include delivery charges) | H6: Purchased Vended Meals | I6: Food Service Equipment | J6: Allowable Nonfood Supplies | K6: Occupancy/ Utilities | L6: Misc. | M6: Specify Misc.
A7: Total Annual Food Program Expenses: | B7: =October!E35+November!E35+December!E35+January!E35+February!E35+March!E35+April!E35+May!E35+June!E35+July!E35+August!E35+September!E35 -> 0 | C7: =October!F35+November!F35+December!F35+January!F35+February!F35+March!F35+April!F35+May!F35+June!F35+July!F35+August!F35+September!F35 -> 0 | D7: =October!G35+November!G35+December!G35+January!G35+February!G35+March!G35+April!G35+May!G35+June!G35+July!G35+August!G35+September!G35 -> 0 | E7: =October!H35+November!H35+December!H35+January!H35+February!H35+March!H35+April!H35+May!H35+June!H35+July!H35+August!H35+September!H35 -> 0 | F7: =October!I35+November!I35+December!I35+January!I35+February!I35+March!I35+April!I35+May!I35+June!I35+July!I35+August!I35+September!I35 -> 0 | G7: =October!J35+November!J35+December!J35+January!J35+February!J35+March!J35+April!J35+May!J35+June!J35+July!J35+August!J35+September!J35 -> 0 | H7: =October!K35+November!K35+December!K35+January!K35+February!K35+March!K35+April!K35+May!K35+June!K35+July!K35+August!K35+September!K35 -> 0 | I7: =October!L35+November!L35+December!L35+January!L35+February!L35+March!L35+April!L35+May!L35+June!L35+July!L35+August!L35+September!L35 -> 0 | ... M7: =October!P35+November!P35+December!P35+January!P35+February!P35+March!P35+April!P35+May!P35+June!P35+July!P35+August!P35+September!P35 -> 0
A8: End of worksheet

Sheet Instructions
A1: Directions: Track the monthly food program expenses that are paid with Child and Adult Care Food Program (CACFP) funds and the CACFP reimbursement that is earned each month. Maintain receipts, invoices, cancelled/copies of checks and any other supporting documentation for each expense/reimbursement. Sponsor can use year end totals to complete Food Service/CACFP Budget Information on sponsor application in the Cyber-Linked Interactive Child Nutrition System (CLiCS).
