Workbook
Name Currency_of_reported_figures: [1]ENGLISH!$G$127

Sheet Cover letter

Sheet ENGLISH
E2: ACI Airport Economics Survey 2013
F6: Please submit the completed questionnaire before August 30th 2013 to: | N6: econ@aci.aero
F7: Tel: +1 514 373 1229 | I7: Fax: +1 514 373 1201
F9: INSTRUCTIONS:
F10: The following convention should be used in reporting values in this questionnaire:
F11: — | G11: Please report actual values only (no abridged values);
F12: — | G12: When actual observed values are not available, produce estimated values in italics;
F13: — | G13: When the actual reported value is nil (zero), include the value "0" in the relevant cell;
F14: — | G14: Only when the actual value or an estimate is not available, treat the data item as missing and leave the cell blank.
F16: Note: Certain questionnaire items require respondents to use check boxes and drop down lists. To respond to these items, please click on the appropriate option.
F17: The items with these features include the corresponding drop lists of unit measures to the right of the reported figures in Section 3.1, check boxes in Section 5
F18: and drop lists with predefined options in Sections 2, 4 and 10
F20: ********Please do not alter this questionnaire form by adding columns, rows and/or deleting items.********
C24: Part 1 - Contact Information
L25: 3-letter IATA Airport Code - If the reported figures pertain to more than
C26: Airport Name (Please complete one separate form for EACH airport being reported) | L26: one airport, please list each airport separated by "/" (e.g. XXX/YYY/ZZZ)
C28: Contact person | L28: Telephone Number
C30: Title | L30: Email Address
C35: Part 2 - General Information
C37: ="Total Traffic for Calendar year 2012"&" "&"("&L27&")" -> Total Traffic for Calendar year 2012 ()
C39: 2.1 | D39: Passengers: | J39: 2.5 | K39: Financial Year (please select):
C41: 2.2 | D41: Cargo (metric tons): | J41: 2.6 | K41: Financial figures submitted in:
C43: 2.3 | D43: Movements | J43: 2.7 | K43: Reporting Currency (please select):
C45: 2.4 | D45: WLU: | F45: =IF(AND(ISNUMBER(F39), ISNUMBER(F41)), (F39+10*F41), "") | J45: 2.8 | K45: Suggested exchange rate: 1 USD = | Q45: =IF(ISTEXT(O43), O43, "")
D46: Work Load Unit is equal to 1 passenger or 100 kg of cargo
C50: Part 3.1 - Infrastructure Size (Area) | M50: Unit of measure
M51: (please select)
C52: 3.1.1 | D52: Total Airport Site Area
D53: of which:
C54: 3.1.1.1 | D54: Airside Area
C55: 3.1.1.2 | D55: Landside area
C57: 3.1.2 | D57: Passenger Terminal(s) Building(s) Area
D58: of which:
C59: 3.1.2.1 | D59: Airside Area
C60: 3.1.2.2 | D60: Landside area
C62: 3.1.3 | D62: Cargo Terminal(s) Building(s) Area
C64: 3.1.4 | D64: Commercial Activity Area
D65: (inside and outside the terminal building(s))
D66: of which:
C67: 3.1.4.1 | D67: Food & beverage
C68: 3.1.4.2 | D68: Retail Activity Area
D69: of which:
C70: 3.1.4.2.1 | D70: Duty Free Area
C74: Part 3.2 - Infrastructure Units
C76: Please specify the number of: | J76: Count:
C77: 3.2.1 | D77: Runways (paved landing strips)
C78: 3.2.2 | D78: Contact gates with air bridge (jet bridge)
C79: 3.2.3 | D79: Remote stands (B737-800 or equivalent)
C80: 3.2.4 | D80: Passenger terminals
C81: 3.2.5 | D81: Cargo terminals
C82: 3.2.6 | D82: Passenger check-in desks/counters
C83: 3.2.7 | D83: Self service kiosks operated by airport
C84: 3.2.8 | D84: Individual car parking spaces
C85: 3.2.9 | D85: Retail stores / shops / boutiques
D86: of which:
C87: 3.2.9.1 | D87: Duty-Free shops
C88: 3.2.10 | D88: Restaurants / cafés and other F&B outlets
C92: Part 4 - Pricing, Ownership & Regulation
M93: Please select:
C94: 4.1 | D94: What type of pricing regulation applies to your airport?
C96: 4.2 | D96: Which form of economic oversight applies to your airport?
C98: 4.3 | D98: What is the ownership structure of your airport(s) (i.e. share ownership)?
C100: 4.4 | D100: If there is a private participation/involvement at your airports, please indicate the type:
C102: 4.5 | D102: If applicable, what is the real pre-tax Weighted Average Cost of Capital (WACC) | P102: (%)
D103: allocated by regulators (or specified in concession agreements)?
C104: 4.6 | D104: Does your airport provide an incentive scheme within your pricing structure
D105: to attract new air services or develop existing ones?
C109: Part 5 - Employment
C110: Please tick the Insourced box OR the Outsourced box for each employment activity and record the corresponding number of employees (if available) as both headcounts and full-time equivalents. Insourced refers to activities where personnel are primarily employed by the airport operator directly. Outsourced refers to activities or personnel that are primarily contracted to a third party.
K113: Headcount | O113: Full time equivalent
O114: (FTE)
C115: 5.1 | D115: Total personnel employed by airport operator | I115: → | J115: →
C117: Activities undertaken by airport operator | K117: of which: | O117: of which:
H118: Insourced | I118: Outsourced
C119: 5.1.1 | D119: Management
C120: 5.1.2 | D120: Ground handling services:
D121: of which:
C122: 5.1.2.1 | D122: Passenger handling services
C123: 5.1.2.2 | D123: Ramp handling services
C124: 5.1.2.3 | D124: Cargo handling services
C125: 5.1.3 | D125: Rescue and fire service
C126: 5.1.4 | D126: Car parking services
C127: 5.1.5 | D127: Cleaning services
C128: 5.1.6 | D128: Maintenance services
C129: 5.1.7 | D129: Air traffic control services
C130: 5.1.8 | D130: Passenger security services
D131: of which:
C132: 5.1.8.1 | D132: Other security (e.g. perimeter and cargo security)
C133: 5.1.9 | D133: Concession services (shops, F&B, etc.)
C134: 5.1.10 | D134: Runway, taxiway, apron operations
C135: 5.1.11 | D135: Other
C138: 5.2 | D138: Total number of people working at the airport
D139: (i.e. employed by airport operator and other companies)
D140: (can be estimated by the number of issued airport security passes)
C144: Part 6 - Airport Revenue | F144: =IF(ISTEXT(O43), O43, "")
K145: 2012 (Financial Year) | O145: 2011 (Previous financial year)
C146: 6.1 | D146: Total Airport Revenue (Sum 6.1.1, 6.1.2, 6.1.3) | I146: =IF((SUM(K148,K169,K181))<>K146,(SUM(K148,K169,K181)),"") | K146: =SUM(K148,K169,K181) -> 0 | O146: =SUM(O148,O169,O181) -> 0 | R146: =IF((SUM(O148,O169,O181))<>O146,(SUM(O148,O169,O181)),"")
C148: 6.1.1 | D148: Operating Aeronautical Revenue (sum 6.1.1.1 -6.1.1.12, 6.1.1.13-6.1.1.16) | I148: =IF((SUM(K150:K161,K163:K165,K167))<>K148,(SUM(K150:K161,K163:K165,K167)),"") | K148: =SUM(K150:M161, K163:M165,K167) -> 0 | O148: =SUM(O150:Q161, O163:Q165,O167) -> 0 | R148: =IF((SUM(O150:O161,O163:O165,O167))<>O148,(SUM(O150:O161,O163:O165,O167)),"")
C150: 6.1.1.1 | D150: Landing charges
C151: 6.1.1.2 | D151: Lighting surcharges
...

Sheet FRANÇAIS
E2: ACI Enquête sur l'Économie des Aéroports 2013
F6: Nous vous prions de soumettre le questionnaire dûment rempli avant le 30 Août 2013 à l'adresse de: | P6: econ@aci.aero
F7: Tél: +1 514 373 1229 | I7: Fax: +1 514 373 1201
F9: INSTRUCTIONS:
F10: La convention suivante doit être utilisée pour le rapport de valeurs dans ce questionnaire:
F11: — | G11: Signaler les valeurs réelles seulement (pas de valeurs abrégées);
F12: — | G12: Si les valeurs réelles sont pas disponibles, prière d'indiquer des valeurs estimées en italique;
F13: — | G13: Lorsque la valeur réelle est nulle (zéro), indiquer la valeur;
F14: — | G14: Une cellule doit rester vide seulement au cas où la valeur réelle ou une estimation n'est pas disponible
F16: Remarque: Certains éléments du questionnaire exigent à cocher des cases d'option et à faire des choix des listes déroulantes.
F17: Pour répondre à ces articles, s'il vous plaît choisir l'option appropriée. Les articles avec ces caractéristiques comprennent les listes déroulantes des unités de
F18: mesure vers la droite dans la Section 3.1, des cases à cocher dans la Section 5, des listes déroulantes dans les Sections 2, 4 et 10.
F20: ********Prière de ne pas modifier cette questionnaire en ajoutant ou supprimant des colonnes, des lignes et/ou des éléments********
C24: Partie 1 - Informations de Contact
L25: Le code AITA (3 lettres) - Nous vous prions de séparer chaque aéroport par un "/"
C26: Nom de l'Aéroport (Veuillez compléter un formulaire pour chaque aéroport): | L26: au cas où les chiffres indiqués représentent plusieurs aéroports (ex. XXX/YYY/ZZZ)
C28: Personne à contacter | L28: Numéro de Téléphone
C30: Titre | L30: Adresse courriel
C35: Partie 2 - Informations Générales
C37: ="Trafic total pour l'année 2012"&" "&"("&L27&")" -> Trafic total pour l'année 2012 ()
C39: 2.1 | D39: Passagers: | J39: 2.5 | K39: Année Budgétaire (choisir une option):
C41: 2.2 | D41: Cargo (en tonnes): | J41: 2.6 | K41: Les chiffres financiers soumis en:
C43: 2.3 | D43: Mouvements | J43: 2.7 | K43: La monnaie de présentation (choisir):
C45: 2.4 | D45: L'unité WLU: | F45: =IF(AND(ISNUMBER(F39), ISNUMBER(F41)), (F39+10*F41), "") | J45: 2.8 | K45: Taux de change suggéré: | N45: 1 USD = | Q45: =IF(ISTEXT(O43), O43, "")
D46: Work Load Unit (WLU) est une unité qui correspond à un passager ou 0,1 tonne de fret
C50: Partie 3.1 - Infrastructure (Superficie) | M50: Unité de mesure
M51: (sélectionner)
C52: 3.1.1 | D52: Superficie totale du site de l'aéroport
D53: dont:
C54: 3.1.1.1 | D54: Zone aérienne (ex: côté piste)
C55: 3.1.1.2 | D55: Zone terrestre (ex: côté ville)
C57: 3.1.2 | D57: Superficie totale des terminaux de passagers
D58: dont:
C59: 3.1.2.1 | D59: Zone aérienne
C60: 3.1.2.2 | D60: Zone terrestre
C62: 3.1.3 | D62: Superficie totale des terminaux de frets
C64: 3.1.4 | D64: Zone d'activité commerciale
D65: (à l'intérieur et à l'extérieur des bâtiments du terminal)
D66: dont:
C67: 3.1.4.1 | D67: Aliments & boissons
C68: 3.1.4.2 | D68: La vente au détail
D69: dont:
C70: 3.1.4.2.1 | D70: Zone hors taxes (Duty Free)
C74: Partie 3.2 - Infrastructure (Unités)
C76: S'il vous plaît indiquer le nombre de: | J76: Comte:
C77: 3.2.1 | D77: Pistes d'atterrissage pavées:
C78: 3.2.2 | D78: Portes air bridge avec passerelles d'embarquement:
C79: 3.2.3 | D79: Postes de stationnement (B737-800 ou équivalent)
C80: 3.2.4 | D80: Terminaux de passagers
C81: 3.2.5 | D81: Terminaux de frets
C82: 3.2.6 | D82: Comptoirs d'enregistrement
C83: 3.2.7 | D83: Kiosques libre-service géré par l'aéroport
C84: 3.2.8 | D84: Places de stationnement de voitures individuelles
C85: 3.2.9 | D85: Magasins de détails / boutiques / autres commerces au détail
D86: dont:
C87: 3.2.9.1 | D87: Boutiques hors taxes (Duty Free)
C88: 3.2.10 | D88: Restaurants / cafés et autres commerces de F&B
C92: Partie 4 - Propriété, Structure des Prix et Règlement Economique
M93: Sélectionner
C94: 4.1 | D94: Quel type de réglementation des prix s'applique à votre (vos) aéroport(s)?
C96: 4.2 | D96: Quelle forme de règlementation économique s'applique à votre (vos) aéroport(s)?
C98: 4.3 | D98: Quelle est la structure de propriété de votre (vos) aéroport(s) (ex. actionnariat)?
C100: 4.4 | D100: Si il y a une participation du secteur privé à votre (vos) aéroport(s), s'il vous plaît indiquer le type:
C102: 4.5 | D102: Le cas échéant, quel est le coût moyen pondéré du capital (CMPC), | P102: (%)
D103: alloués par les organismes de réglementation (ou spécifiée dans les contrats de concession)?
C104: 4.6 | D104: Fournissez-vous un mécanisme d'incitation au sein de votre structure de prix
D105: pour attirer de nouveaux services aériens ou de développer celles qui existent déjà?
C109: Partie 5 - Emploi et Opérations
C110: S'il vous plaît cocher la boîte internalisée OU externalisée pour chaque activité et indiquer le numéro correspondant d'employés - le nombre de personnes physiques et équivalents temps plein. Les activités internalisée se réfèrent à des tâches gérées principalement par l'exploitant de l'aéroport. Les activités externalisé se réfèrent à des tâches qui sont principalement contractés à des tiers.
K113: Effectifs: | O113: Équivalent Temps Plein
O114: (ETP)
C115: 5.1 | D115: Total du personnel directement employé par l'opérateur d'aéroport
C117: Les activités menées par l'exploitant d'aéroport | K117: dont: | O117: dont:
H118: Internalisée | I118: Externalisée
C119: 5.1.1 | D119: Gestion
C120: 5.1.2 | D120: Services d'assistance en escales:
D121: dont:
C122: 5.1.2.1 | D122: Services d'assistance des passagers
C123: 5.1.2.2 | D123: Services d'assistance "opérations en piste"
C124: 5.1.2.3 | D124: Services de manutention de fret aérien
C125: 5.1.3 | D125: Service de sécurité incendie
C126: 5.1.4 | D126: Services de stationnement de voitures
C127: 5.1.5 | D127: Services de nettoyage
C128: 5.1.6 | D128: Services d'entretien
C129: 5.1.7 | D129: Services de contrôle du trafic aérien
C130: 5.1.8 | D130: Services de sécurité des passagers
D131: dont:
C132: 5.1.8.1 | D132: Autre sécurité (ex: sécurité du périmètre et cargo)
C133: 5.1.9 | D133: Services de vente au détail et restauration
C134: 5.1.10 | D134: Operations de piste, chemins de roulement, tablier
C135: 5.1.11 | D135: Autre
C138: 5.2 | D138: Total du personnel employé sur le site de l'aéroport
D139: (c'est-à-dire employé par l'exploitant d'aéroport et autres compagnies)
D140: (peut être estimée par le nombre des passes de sécurité délivres)
C144: Partie 6 - Revenue. Chiffre d'Affaires
K145: 2012 (Année budgétaire) | O145: 2011 (Année budg. précédente)
C146: 6.1 | D146: Revenu Total (Somme 6.1.1, 6.1.2, 6.1.3) | I146: =IF((SUM(K148,K169,K181))<>K146,(SUM(K148,K169,K181)),"") | K146: =SUM(K148,K169,K181) -> 0 | O146: =SUM(O148,O169,O181) -> 0 | R146: =IF((SUM(O148,O169,O181))<>O146,(SUM(O148,O169,O181)),"")
C148: 6.1.1 | D148: Redevances Aéronautiques - Résultat d'Exploitation | I148: =IF((SUM(K150:K161,K163:K165,K167))<>K148,(SUM(K150:K161,K163:K165,K167)),"") | K148: =SUM(K150:M161, K163:M165,K167) -> 0 | O148: =SUM(O150:Q161, O163:Q165,O167) -> 0 | R148: =IF((SUM(O150:O161,O163:O165,O167))<>O148,(SUM(O150:O161,O163:O165,O167)),"")
C150: 6.1.1.1 | D150: Redevances d'atterrissage
C151: 6.1.1.2 | D151: Frais supplémentaires d'éclairage de piste d'atterrissage
...

Sheet ESPAÑOL
E2: ACI Encuesta Económica 2013
F6: Por favor, envíe el cuestionario completo antes del 30 de agosto de 2013 a: | O6: econ@aci.aero
F7: Tel: +1 514 373 1229 | I7: Fax: +1 514 373 1201
F9: INSTRUCCIONES:
F10: Las siguientes convenciones deben utilizarse para reportar los valores en este cuestionario:
F11: — | G11: Por favor reporte los valores reales (no valores abreviados);
F12: — | G12: Cuando los valores reales no estén disponibles, indique los valores estimados en cursiva;
F13: — | G13: Cuando el valor real es cero, incluya el valor "0" en la celda correspondiente;
F14: — | G14: Solamente cuando el valor real or el estimado no esté disponible, trate el dato como no-disponible y deje la celda en blanco.
F16: Nota: Algunas preguntas de este cuestionario se responden marcando la casilla o seleccionando la opción correcta del menú desplegable. Por favor, responda según sea el caso.
F19: ********Por favor no altere este cuestionario añadiendo columnas, filas y/o eliminando preguntas********
C24: Parte 1 - Información de contacto
L25: Código IATA de 3 letras - Si los datos corresponden a más de un aeropuerto,
C26: Nombre del aeropuerto (Por favor llene un formulario/cuestionario por CADA aeropuerto) | L26: liste cada aeropuerto separados con "/" (e.g. XXX/YYY/ZZZ)
C28: Persona de contacto | L28: Número de teléfono
C30: Título | L30: Dirección de E-mail
C35: Parte 2 - Información General
C37: ="El tráfico total para el año calendario 2012"&" "&"("&L27&")" -> El tráfico total para el año calendario 2012 ()
C39: 2.1 | D39: Pasajeros: | J39: 2.5 | K39: Año económico (por favor, seleccione):
C41: 2.2 | D41: Carga (toneladas): | J41: 2.6 | K41: Las cifras financieras presentadas:
C43: 2.3 | D43: Movimientos: | J43: 2.7 | K43: Moneda de Referencia (seleccione):
C45: 2.4 | D45: WLU: | F45: =IF(AND(ISNUMBER(F39), ISNUMBER(F41)), (F39+10*F41), "") | J45: 2.8 | K45: Tipo de cambio sugerido: | N45: 1 USD = | Q45: =IF(ISTEXT(O43), O43, "")
D46: WLU es igual a 1 pasajero o 100 kg de carga
C50: Parte 3.1 - Tamaño de la Infraestructura (Área) | M50: Unidad de medida
M51: (seleccione)
C52: 3.1.1 | D52: Área Total del Aeropuerto
D53: de las cuales:
C54: 3.1.1.1 | D54: Lado aire
C55: 3.1.1.2 | D55: Lado tierra
C57: 3.1.2 | D57: Área total de las terminales de pasajeros
D58: de las cuales:
C59: 3.1.2.1 | D59: Lado aire
C60: 3.1.2.2 | D60: Lado tierra
C62: 3.1.3 | D62: Área total de las terminales de carga
C64: 3.1.4 | D64: Área dedicada a las actividades comerciales
D65: (dentro y fuera de los edificios terminales)
D66: de las cuales:
C67: 3.1.4.1 | D67: Zona de restauración (F&B)
C68: 3.1.4.2 | D68: Área de venta al por menor
D69: de las cuales:
C70: 3.1.4.2.1 | D70: Área de tiendas libres de impuestos
C74: Parte 3.2 - Infraestructura (Unidades)
C76: Por favor, especifique el número de: | J76: Cuenta:
C77: 3.2.1 | D77: Pistas (pistas de aterrizaje pavimentadas)
C78: 3.2.2 | D78: Número de puertas de contacto con pasarela aérea (jet bridge)
C79: 3.2.3 | D79: Número de estacionamientos remotos (B737-800 o equivalente)
C80: 3.2.4 | D80: Terminales de pasajeros
C81: 3.2.5 | D81: Terminales de carga
C82: 3.2.6 | D82: Número de mostradores de facturación
C83: 3.2.7 | D83: Quioscos de autoservicio operados por aeropuerto
C84: 3.2.8 | D84: Número de plazas de estacionamiento de vehículos
C85: 3.2.9 | D85: Tiendas (venta al por menor)
D86: de las cuales:
C87: 3.2.9.1 | D87: Tiendas libres de impuestos (Duty Free)
C88: 3.2.10 | D88: Restaurantes / cafeterías y demás establecimientos de F & B
C92: Parte 4 - Propiedad, Estructura Tarifaria y Regulación Económica
M93: Por favor seleccione:
C94: 4.1 | D94: ¿Qué tipo de regulación tarifaria aplica a su aeropuerto?
C96: 4.2 | D96: ¿Qué forma de vigilancia económica se aplica a su aeropuerto?
C98: 4.3 | D98: ¿Cual es la estructura propietaria del aeropuerto(s) (p.e. propiedad de las acciones)?
C100: 4.4 | D100: Si hay una participación privada en los aeropuertos, por favor indique el tipo:
C102: 4.5 | D102: En su caso, ¿qué es el Costo Promedio Ponderado de Capital (WACC en inglés) | P102: (%)
D103: asignado por los reguladores (o se especifica en los contratos de concesión)?
C104: 4.6 | D104: ¿Tiene el aeropuerto un esquema de incentivos tarifarios?
D105: para atraer a nuevos servicios aéreos o desarrollar los ya existentes?
C109: Parte 5 - Empleo y Operaciones
C110: Por favor seleccione la casilla “Interno” o “Subcontratado” dependiendo de si su organización realiza dicha actividad por sí misma a si está subcontratada.
K113: Número de personal | O113: Trabajadores a
O114: Tiempo Completo
C115: 5.1 | D115: Total de personal empleado por el operador aeroportuario | J115: →
C117: Las actividades realizadas por el operador aeroportuario | K117: de las cuales: | O117: de las cuales:
H118: Interno | I118: Subcontratado
C119: 5.1.1 | D119: Gestión
C120: 5.1.2 | D120: Servicios de asistencia en tierra a aeronaves:
D121: de ellos:
C122: 5.1.2.1 | D122: Asistencia en tierra de pasajeros
C123: 5.1.2.2 | D123: Asistencia en tierra de rampa
C124: 5.1.2.3 | D124: Asistencia en tierra de cargo
C125: 5.1.3 | D125: Bomberos y rescate
C126: 5.1.4 | D126: Aparcamiento de vehículos
C127: 5.1.5 | D127: Servicios de limpieza
C128: 5.1.6 | D128: Servicios de mantenimiento
C129: 5.1.7 | D129: Servicios de control de tráfico aéreo (ATC)
C130: 5.1.8 | D130: Servicios de seguridad de pasajeros
D131: de las cuales:
C132: 5.1.8.1 | D132: Otros servicios de seguridad
C133: 5.1.9 | D133: Servicios comerciales y restauración (F&B)
C134: 5.1.10 | D134: Operaciones de pistas, calles de rodaje, delantal
C135: 5.1.11 | D135: Otros
C138: 5.2 | D138: Número total de personas que trabajan en el aeropuerto
D139: (es decir, contratados por el operador de aeropuertos y otras empresas)
D140: (puede ser estimado por el número de emitida pasa a la seguridad)
C144: Parte 6 - Ingresos Aeroportuarios
K145: 2012 (Año fiscal) | O145: 2011 (Año fiscal anterior)
C146: 6.1 | D146: Ingresos Aeroportuarios Totales (Sum 6.1.1, 6.1.2, 6.1.3) | I146: =IF((SUM(K148,K169,K181))<>K146,(SUM(K148,K169,K181)),"") | K146: =SUM(K148,K169,K181) -> 0 | O146: =SUM(O148,O169,O181) -> 0 | R146: =IF((SUM(O148,O169,O181))<>O146,(SUM(O148,O169,O181)),"")
C148: 6.1.1 | D148: Ingresos Aeronáuticos (Operativos) (sum 6.1.1.1 -6.1.1.12, 6.1.1.13-6.1.1.16) | I148: =IF((SUM(K150:K161,K163:K165,K167))<>K148,(SUM(K150:K161,K163:K165,K167)),"") | K148: =SUM(K150:M161, K163:M165,K167) -> 0 | O148: =SUM(O150:Q161, O163:Q165,O167) -> 0 | R148: =IF((SUM(O150:O161,O163:O165,O167))<>O148,(SUM(O150:O161,O163:O165,O167)),"")
C150: 6.1.1.1 | D150: Tarifas de aterrizaje
C151: 6.1.1.2 | D151: Sobrecargos de iluminación
C152: 6.1.1.3 | D152: Emisiones acústicas y otras tarifas medioambientales
C153: 6.1.1.4 | D153: Tarifas de navegación (Navaid)
...

Sheet glossary
B1: Available in English only
B3: Aircraft Movement – An aircraft take-off or landing at an airport. For
B4: airport traffic purposes one arrival and one departure are counted as
B5: two movements, measured over the course of a year.
B7: Capital Expenditure - (CAPEX) – Funds used by a airport operator to acquire
B8: or upgrade physical assets such as property, industrial buildings or equipment.
B9: This type of outlay is made by companies to maintain or increase the scope of their
B10: operations and allocated for specific time period. These expenditures can include
B11: everything from repairing a roof to building a new terminal building or runway.
B13: Cash – In accounting contexts, cash on hand (e.g., petty cash and cash not yet
B14: deposited to the bank) and demand deposits held in banks and similar accounts
B15: that can be used in payment of obligations.In accounting contexts, cash on hand
... B144: Terminal - the part of an aerodrome used for embarking or disembarking passengers or cargo.
C145: Domestic: terminal used primarily for domestic flights
C146: (i.e. having exclusively domestic stages).
C147: International: terminal used primarily for international flights
C148: (i.e. flights that contain one or more international flight stages).
B150: Total Operating Revenue – The sum of Aeronautical and Nonaeronautical
B151: operating revenue.
B153: Weighted-average cost of capital – A weighted average of the after-tax required rates of
B154: return on a company’s common stock, preferred stock, and long-term debt, where the weights
B155: are the fraction of each source of financing in the company’s target capital structure.

Sheet for internal use
A1: 1 | B1: 1 | C1: 1 | D1: 1 | E1: 1 | F1: 1 | G1: 1 | H1: 1 | I1: 1 | J1: 1 | K1: 1 | L1: 1 | M1: 2 | N1: 2 | O1: 2 | P1: 2 | Q1: 2 | R1: 2 | S1: 2 | T1: 2 | U1: 3.1 | W1: 3.1 | Y1: 3.1 | AA1: 3.1 | AC1: 3.1 | AE1: 3.1 | AG1: 3.1 | AI1: 3.1 | AK1: 3.1 | AM1: 3.1 | AO1: 3.1 | AQ1: 3.2 | AR1: 3.2 | AS1: 3.2 | AT1: 3.2 | AU1: 3.2 | AV1: 3.2 | AW1: 3.2 | AX1: 3.2 | AY1: 3.2 | AZ1: 3.2 | BA1: 3.2 | BB1: 4 | BC1: 4 | BD1: 4 | BE1: 4 | BF1: 4 | BG1: 4 | BH1: 5 | BI1: 5 | BJ1: 5 | BK1: 5 | BL1: 5 | BM1: 5 | BN1: 5 | BO1: 5 | BP1: 5 | BQ1: 5 | BR1: 5 | BS1: 5 | BT1: 5 | BU1: 5 | BV1: 5 | BW1: 5 | BY1: 5 | BZ1: 5 | CA1: 5 | CB1: 5 | CC1: 5 | CD1: 5 | CE1: 5 | CF1: 5 | CG1: 5 | CH1: 5 | CI1: 5 | CJ1: 5 | CK1: 5 | CL1: 5 | CM1: 5 | CN1: 5 | CO1: 5 | CP1: 5 | CQ1: 5 | CR1: 5 | CS1: 5 | CT1: 5 | CU1: 5 | CV1: 5 | CW1: 5 | CX1: 5 | CY1: 5 | CZ1: 5 | DA1: 5 | DB1: 5 | DC1: 5 | DD1: 5 | DE1: 5 | DF1: 5 | DG1: 5 | DH1: 5 | DI1: 5 | DJ1: 5 | DK1: 5 | DL1: 5 | DM1: 5 | DN1: 5 | DO1: 5 | DP1: 5 | DQ1: 5 | DR1: 5 | DS1: 6 | DT1: 6 | DU1: 6 | DV1: 6 | DW1: 6 | DX1: 6 | DY1: 6 | DZ1: 6 | EA1: 6 | EB1: 6 | EC1: 6 | ED1: 6 | EE1: 6 | EF1: 6 | EG1: 6 | EH1: 6 | EI1: 6 | EJ1: 6 | EK1: 6 | EL1: 6 | EM1: 6 | EN1: 6 | EO1: 6 | EP1: 6 | EQ1: 6 | ER1: 6 | ES1: 6 | ET1: 6 | EU1: 6 | EV1: 6 | EW1: 6 | EX1: 6 | EY1: 6 | EZ1: 6 | FA1: 6 | FB1: 6 | FC1: 6 | FD1: 7 | FE1: 7 | FF1: 7 | FG1: 7 | FH1: 7 | FI1: 7 | FJ1: 7 | FK1: 7 | FL1: 7 | FM1: 7 | FN1: 7 | FO1: 7 | FP1: 8 | FQ1: 8 | FR1: 8 | FS1: 8 | FT1: 8 | FU1: 8 | FV1: 8 | FW1: 8 | FX1: 8 | FY1: 8 | FZ1: 8 | GA1: 8 | GB1: 8 | GC1: 8 | GD1: 9 | GE1: 9 | GF1: 9 | GG1: 9 | GH1: 9 | GI1: 9 | GJ1: 9 | GK1: 9 | GL1: 9 | GM1: 9 | GN1: 9 | GO1: 9 | GP1: 10 | GQ1: 10 | GR1: 10 | GS1: 10 | GT1: 10 | GU1: 11 | GV1: 11 | GW1: 11 | GX1: 11 | GY1: 11 | GZ1: 11 | HA1: 11 | HB1: 11 | HC1: 12 | HD1: 12 | HE1: 13 | HF1: 13 | HG1: 13 | HH1: 13 | HI1: 13 | HJ1: 13 | HK1: 13 | HL1: 14 | HM1: 14 | HQ1: 6 (2011) | HR1: 6 (2011) | HS1: 6 (2011) | HT1: 6 (2011) | HU1: 6 (2011) | HV1: 6 (2011) | HW1: 6 (2011) | HX1: 6 (2011) | HY1: 6 (2011) | HZ1: 6 (2011) | IA1: 6 (2011) | IB1: 6 (2011) | IC1: 6 (2011) | ID1: 6 (2011) | IE1: 6 (2011) | IF1: 6 (2011) | IG1: 6 (2011) | IH1: 6 (2011) | II1: 6 (2011) | IJ1: 6 (2011) | IK1: 6 (2011) | IL1: 6 (2011) | IM1: 6 (2011) | IN1: 6 (2011) | IO1: 6 (2011) | IP1: 6 (2011) | IQ1: 6 (2011) | IR1: 6 (2011) | IS1: 6 (2011) | IT1: 6 (2011) | IU1: 6 (2011) | IV1: 6 (2011) | IW1: 6 (2011) | IX1: 6 (2011) | IY1: 6 (2011) | IZ1: 6 (2011) | JA1: 6 (2011) | JB1: 7 (2011) | JC1: 7 (2011) | JD1: 7 (2011) | JE1: 7 (2011) | JF1: 7 (2011) | JG1: 7 (2011) | JH1: 7 (2011) | JI1: 7 (2011) | JJ1: 7 (2011) | JK1: 7 (2011) | JL1: 7 (2011) | JM1: 7 (2011) | JN1: 8 (2011) | JO1: 8 (2011) | JP1: 8 (2011) | JQ1: 8 (2011) | JR1: 8 (2011) | JS1: 8 (2011) | JT1: 8 (2011) | JU1: 8 (2011) | JV1: 8 (2011) | JW1: 8 (2011) | JX1: 8 (2011) | JY1: 8 (2011) | JZ1: 8 (2011) | KA1: 8 (2011) | KB1: 9 (2011) | KC1: 9 (2011) | KD1: 9 (2011) | KE1: 9 (2011) | KF1: 9 (2011) | KG1: 9 (2011) | KH1: 9 (2011) | KI1: 9 (2011) | KJ1: 9 (2011) | KK1: 9 (2011) | KL1: 9 (2011) | KM1: 9 (2011) | KN1: 10 (2011) | KO1: 11 (2011) | KP1: 11 (2011) | KQ1: 11 (2011) | KR1: 11 (2011) | KS1: 11 (2011) | KT1: 11 (2011) | KU1: 11 (2011) | KV1: 11 (2011) | KW1: 12 (2011) | KX1: 12 (2011) | KY1: 13 (2011) | KZ1: 13 (2011) | LA1: 13 (2011) | LB1: 13 (2011) | LC1: 13 (2011) | LD1: 13 (2011) | LE1: 13 (2011) | LF1: 14 (2011) | LG1: 14 (2011)
A2: Region | B2: City | C2: Country | D2: Operator | E2: Size Category | F2: Code | G2: Count | H2: Airport Name | I2: Contact person | J2: Title | K2: Tel. Number | L2: Email Address | M2: 2.1 Passengers: | N2: 2.2 Cargo (metric tons): | O2: 2.3 Movements | P2: 2.4 WLU: | Q2: 2.5 Financial Year (please select): | R2: 2.6 Financial figures submitted in: | S2: 2.7 Reporting Currency (please select): | T2: 2.8 Suggested exchange rate: | U2: 3.1.1 Total Airport Site Area | W2: 3.1.1.1 Airside Area | Y2: 3.1.1.2 Landside area | AA2: 3.1.2 Passenger Terminal(s) Building(s) Area | AC2: 3.1.2.1 Airside Area | AE2: 3.1.2.2 Landside area | AG2: 3.1.3 Cargo Terminal(s) Building(s) Area | AI2: 3.1.4 Commercial Activity Area | AK2: 3.1.4.1 Food & beverage | AM2: 3.1.4.2 Retail Activity Area | AO2: 3.1.4.2.1 Duty Free Area | AQ2: 3.2.1 Runways (paved landing strips) | AR2: 3.2.2 Contact gates with air bridge (jet bridge) | AS2: 3.2.3 Remote stands (B737-800 or equivalent) | AT2: 3.2.4 Passenger terminals | AU2: 3.2.5 Cargo terminals | AV2: 3.2.6 Passenger check-in desks/counters | AW2: 3.2.7 Self service kiosks operated by airport | AX2: 3.2.8 Individual car parking spaces | AY2: 3.2.9 Retail stores / shops / boutiques | AZ2: 3.2.9.1 Duty-Free shops | BA2: 3.2.10 Restaurants / cafés and other F&B outlets | BB2: 4.1 Pricing regulation | BC2: 4.2 Economic Oversigght | BD2: 4.3 Ownership Structure | BE2: 4.4 Private participation | BF2: 4.5 WACC | BG2: 4.6 Incentive scheme | BH2: 5.1 Total personnel employed by airport operator | Headcount | BI2: 5.1 Total personnel employed by airport operator | FTE | BJ2: 5.1.1 Management | Insourced | BK2: 5.1.2 Ground handling services: | Insourced | BL2: 5.1.2.1 Passenger handling services | Insourced | BM2: 5.1.2.2 Ramp handling services | Insourced | BN2: 5.1.2.3 Cargo handling services | Insourced | BO2: 5.1.3 Rescue and fire service | Insourced | BP2: 5.1.4 Car parking services | Insourced | BQ2: 5.1.5 Cleaning services | Insourced | BR2: 5.1.6 Maintenance services | Insourced | BS2: 5.1.7 Air traffic control services | Insourced | BT2: 5.1.8 Passenger security services | Insourced | BU2: 5.1.8.1 Other security (e.g. perimeter and cargo security) | Insourced | BV2: 5.1.10 Concession services (shops, F&B, etc.) | Insourced | BW2: 5.1.11 Runway, taxiway, apron operations |Insourced | BX2: 5.1.12 Other |Insourced | BY2: 5.1.1 Management | Outsourced | BZ2: 5.1.2 Ground handling services: | Outsourced | CA2: 5.1.2.1 Passenger handling services | Outsourced | CB2: 5.1.2.2 Ramp handling services | Outsourced | CC2: 5.1.2.3 Cargo handling services | Outsourced | CD2: 5.1.3 Rescue and fire service | Outsourced | CE2: 5.1.4 Car parking services | Outsourced | CF2: 5.1.5 Cleaning services | Outsourced | CG2: 5.1.6 Maintenance services | Outsourced | CH2: 5.1.7 Air traffic control services | Outsourced | CI2: 5.1.8 Passenger security services | Outsourced | CJ2: 5.1.8.1 Other security (e.g. perimeter and cargo security) | Outsourced | CK2: 5.1.10 Concession services (shops, F&B, etc.) | Outsourced | CL2: 5.1.11 Runway, taxiway, apron operations | Outsourced | CM2: 5.1.12 Other | Outsorced | CN2: 5.1.1 Management | Headcount | CO2: 5.1.2 Ground handling services: | Headcount | CP2: 5.1.2.1 Passenger handling services | Headcount | CQ2: 5.1.2.2 Ramp handling services | Headcount | CR2: 5.1.2.3 Cargo handling services | Headcount | CS2: 5.1.3 Rescue and fire service | Headcount | CT2: 5.1.4 Car parking services | Headcount | CU2: 5.1.5 Cleaning services | Headcount | CV2: 5.1.6 Maintenance services | Headcount | CW2: 5.1.7 Air traffic control services | Headcount | CX2: 5.1.8 Passenger security services | Headcount | CY2: 5.1.8.1 Other security (e.g. perimeter and cargo security) | Headcount | CZ2: 5.1.10 Concession services (shops, F&B, etc.) | Headcount | DA2: 5.1.11 Runway, taxiway, apron operations | Headcount | DB2: 5.1.12 Other | Headcount | DC2: 5.1.1 Management | FTE | DD2: 5.1.2 Ground handling services: | FTE | DE2: 5.1.2.1 Passenger handling services | FTE | DF2: 5.1.2.2 Ramp handling services | FTE | DG2: 5.1.2.3 Cargo handling services | FTE | DH2: 5.1.3 Rescue and fire service | FTE | DI2: 5.1.4 Car parking services | FTE | DJ2: 5.1.5 Cleaning services | FTE | DK2: 5.1.6 Maintenance services | FTE | DL2: 5.1.7 Air traffic control services | FTE | DM2: 5.1.8 Passenger security services | FTE | DN2: 5.1.8.1 Other security (e.g. perimeter and cargo security) | FTE | DO2: 5.1.10 Concession services (shops, F&B, etc.) | FTE | DP2: 5.1.11 Runway, taxiway, apron operations | FTE | DQ2: 5.1.12 Other | FTE | DR2: 5.2 Total number of people working at the airport | DS2: 6.1 Total Airport Revenue (Sum 6.1.1, 6.1.2, 6.1.3) | DT2: 6.1.1 Operating Aeronautical Revenue (sum 6.1.1.1 -6.1.1.12, 6.1.1.13-6.1.1.16) | DU2: 6.1.1.1 Landing charges | DV2: 6.1.1.2 Lighting surcharges | DW2: 6.1.1.3 Noise & other environmental charges | DX2: 6.1.1.4 Navaid charges | DY2: 6.1.1.5 Parking charges | DZ2: 6.1.1.6 Boarding bridge charges | EA2: 6.1.1.7 Passenger charges (excluding AIF or similar) | EB2: 6.1.1.8 Transfer / transit charges | EC2: 6.1.1.9 Security charges | ED2: 6.1.1.10 Cargo (or freight) charges | EE2: 6.1.1.11 Fueling charges | EF2: 6.1.1.12 Ground handling services (excluding fuel charges) | EG2: 6.1.1.12.1 Ground handling infrastructure (if additional to 6.1.1.4) | EH2: 6.1.1.13 Airport improvement fees - AIF (or Passenger facility charge) | EI2: 6.1.1.14 Utility recharges (e.g. water, electricity, etc.) | EJ2: 6.1.1.15 Terminal rentals paid by airlines for space utilization | EK2: 6.1.1.16 Other (please specify in text box below any item >3% of total income) | EL2: 6.1.1.16 Other TEXT | EM2: 6.1.2 Operating Non-Aeronautical Revenue (sum 6.1.2.1 - 6.1.2.7) | EN2: 6.1.2.1 Retail concessions | EO2: 6.1.2.1.1Duty Free concessions | EP2: 6.1.2.2 Food & Beverage | EQ2: 6.1.2.3 Car parking | ER2: 6.1.2.4 Rental car concessions | ES2: 6.1.2.5 Property & real estate income or rent | ET2: 6.1.2.6 Advertising | EU2: 6.1.2.7 Other (please specify in the text box below any item >3%) | EV2: 6.1.2.7 Other TEXT | EW2: 6.1.3 Non-Operating Revenue (sum 6.1.3.1-6.1.3.4) | EX2: 6.1.3.1 Interest income | EY2: 6.1.3.2 Subsidies / Grants | EZ2: 6.1.3.3 Asset Divestments | FA2: 6.1.3.4 Other (please specify in text box any item >3%) | FB2: 6.1.3.4 Other TEXT | FC2: 6.1.4 Comments (please type in the box below): | FD2: 7.1 Total Operating Expenses (sum 7.1.1 - 7.1.9) | FE2: 7.1.1 Personnel expenses (salaries and benefits) | FF2: 7.1.2 Contracted services (cost of services paid to third parties) | FG2: 7.1.3 Materials, equipment, supplies (excluding maintenance/contracted serv.) | FH2: 7.1.4 Communications, utilities, energy & waste | FI2: 7.1.5 Insurance, claims, settlements | FJ2: 7.1.6 Maintenance (excluding contracted services) | FK2: 7.1.7 Lease, rent, concession fee payments | FL2: 7.1.8 General and administrative expenses (excluding personnel) | FM2: 7.1.9 Other - (please specify in text box any item >3% of total expenses): | FN2: 7.1.9 Other TEXT | FO2: 7.2 Comments (please type in the box below): | FP2: 8.1 Total Airport Income | FQ2: 8.1.1 Operating Aeronautical Income | FR2: 8.1.2 Operating Non-Aeronautical Income | FS2: 8.1.3 Non-Operating Income | FT2: 8.2 Total Operating Expenses | FU2: 8.3 Operating Surplus/Deficit (EBITDA) | FV2: 8.4 Capital Costs | FW2: 8.4.1 Interest and dividends paid to third parties | FX2: 8.4.2 Depreciation or/and amortization of property, plant & equipment | FY2: 8.4.3 Other capital costs (please specify below) | FZ2: 8.4.3 Other capital costs TEXT | GA2: 8.5 Taxes & Other Fees | GB2: 8.6 Net Profit / Loss | GC2: 8.7 Comments (please type in the box below): | GD2: 9.1 Total Assets | GE2: 9.1.1 Current Assets | GF2: 9.1.1.1 Cash and equivalent | GG2: 9.1.1.2 Other | GH2: 9.1.2 Non Current Assets | GI2: 9.1.2.1 Fixed assets | GJ2: 9.1.2.2 Other | GK2: 9.2 Total Liabilities | GL2: 9.2.1 Current liabilities | GM2: 9.2.1 Non-current liabilities | GN2: 9.3 Net Assets (9.1 - 9.2) | GO2: 9.4 Accumulated depreciation of fixed assets (9.1.2.1) | GP2: 10.1 Debt outstanding | GQ2: 10.2 What is the credit rating of financial instruments issued by the airport company? Moody's: | GR2: 10.2 What is the credit rating of financial instruments issued by the airport company? S&P: | GS2: 10.2 What is the credit rating of financial instruments issued by the airport company? Fitch: | GT2: 10.2 What is the credit rating of financial instruments issued by the airport company? In words: | GU2: 11.1 Total Operating Expenses (Total corresponds to 7.1) | GV2: 11.1.1 Security | GW2: 11.1.2 Airfield Operations & Maintenance (including firefighting & winter services) | GX2: 11.1.3 Terminal, Landside Operations & Maintenance (including commercial operations) | GY2: 11.1.4 Administration | GZ2: 11.1.5 Sales & Marketing | HA2: 11.1.6 Other - (please specify in text box any item >5% of total operating expenses) | HB2: 11.1.6 Other - TEXT | HC2: 12.1 Taxes levied on passengers | HD2: 12.2 Taxed levied on airlines | HE2: 13.1 Airport Capital Expenditure (CAPEX) | HF2: 13.1.1 Purchase of property, plant & equipment | HG2: 13.1.2 Construction expenses | HH2: 13.1.3 Purchase of other goods & services | HI2: 13.1.4 Other capital expenditure items (please specify below) | HJ2: 13.1.4 Other capital expenditure items TEXT | HK2: 13.2 Comments (please type in the box below): | HL2: 14.1 Return On Invested Capital (ROIC) (%) | HM2: 14.2 Return on Capital Employed (ROCE) (%) | HQ2: 6.1 Total Airport Revenue (Sum 6.1.1, 6.1.2, 6.1.3) | HR2: 6.1.1 Operating Aeronautical Revenue (sum 6.1.1.1 -6.1.1.12, 6.1.1.13-6.1.1.16) | HS2: 6.1.1.1 Landing charges | HT2: 6.1.1.2 Lighting surcharges | HU2: 6.1.1.3 Noise & other environmental charges | HV2: 6.1.1.4 Navaid charges | HW2: 6.1.1.5 Parking charges | HX2: 6.1.1.6 Boarding bridge charges | HY2: 6.1.1.7 Passenger charges (excluding AIF or similar) | HZ2: 6.1.1.8 Transfer / transit charges | IA2: 6.1.1.9 Security charges | IB2: 6.1.1.10 Cargo (or freight) charges | IC2: 6.1.1.11 Fueling charges | ID2: 6.1.1.12 Ground handling services (excluding fuel charges) | IE2: 6.1.1.12.1 Ground handling infrastructure (if additional to 6.1.1.4) | IF2: 6.1.1.13 Airport improvement fees - AIF (or Passenger facility charge) | IG2: 6.1.1.14 Utility recharges (e.g. water, electricity, etc.) | IH2: 6.1.1.15 Terminal rentals paid by airlines for space utilization | II2: 6.1.1.16 Other (please specify in text box below any item >3% of total income) | IJ2: 6.1.1.16 Other TEXT | IK2: 6.1.2 Operating Non-Aeronautical Revenue (sum 6.1.2.1 - 6.1.2.7) | IL2: 6.1.2.1 Retail concessions | IM2: 6.1.2.1.1 of which: Duty Free concessions | IN2: 6.1.2.2 Food & Beverage | IO2: 6.1.2.3 Car parking | IP2: 6.1.2.4 Rental car concessions | IQ2: 6.1.2.5 Property & real estate income or rent | IR2: 6.1.2.6 Advertising | IS2: 6.1.2.7 Other (please specify in the text box below any item >3%) | IT2: 6.1.2.7 Other TEXT | IU2: 6.1.3 Non-Operating Revenue (sum 6.1.3.1-6.1.3.4) | IV2: 6.1.3.1 Interest income | IW2: 6.1.3.2 Subsidies / Grants | IX2: 6.1.3.3 Asset Divestments | IY2: 6.1.3.4 Other (please specify in text box any item >3%) | IZ2: 6.1.3.4 Other TEXT | JA2: 6.1.4 Comments (please type in the box below): | JB2: 7.1 Total Operating Expenses (sum 7.1.1 - 7.1.9) | JC2: 7.1.1 Personnel expenses (salaries and benefits) | JD2: 7.1.2 Contracted services (cost of services paid to third parties) | JE2: 7.1.3 Materials, equipment, supplies (excluding maintenance/contracted serv.) | JF2: 7.1.4 Communications, utilities, energy & waste | JG2: 7.1.5 Insurance, claims, settlements | JH2: 7.1.6 Maintenance (excluding contracted services) | JI2: 7.1.7 Lease, rent, concession fee payments | JJ2: 7.1.8 General and administrative expenses (excluding personnel) | JK2: 7.1.9 Other - (please specify in text box any item >3% of total expenses): | JL2: 7.1.9 Other TEXT | JM2: 7.2 Comments (please type in the box below): | JN2: 8.1 Total Airport Income | JO2: 8.1.1 Operating Aeronautical Income | JP2: 8.1.2 Operating Non-Aeronautical Income | JQ2: 8.1.3 Non-Operating Income | JR2: 8.2 Total Operating Expenses | JS2: 8.3 Operating Surplus/Deficit (EBITDA) | JT2: 8.4 Capital Costs | JU2: 8.4.1 Interest and dividends paid to third parties | JV2: 8.4.2 Depreciation or/and amortization of property, plant & equipment | JW2: 8.4.3 Other capital costs (please specify below) | JX2: 8.4.3 Other capital costs TEXT | JY2: 8.5 Taxes & Other Fees | JZ2: 8.6 Net Profit / Loss | KA2: 8.7 Comments (please type in the box below): | KB2: 9.1 Total Assets | KC2: 9.1.1 Current Assets | KD2: 9.1.1.1 Cash and equivalent | KE2: 9.1.1.2 Other | KF2: 9.1.2 Non Current Assets | KG2: 9.1.2.1 Fixed assets | KH2: 9.1.2.2 Other | KI2: 9.2 Total Liabilities | KJ2: 9.2.1 Current liabilities | KK2: 9.2.1 Non-current liabilities | KL2: 9.3 Net Assets (9.1 - 9.2) | KM2: 9.4 Accumulated depreciation of fixed assets (9.1.2.1) | KN2: 10.1 Debt outstanding | KO2: 11.1 Total Operating Expenses (Total corresponds to 7.1) | KP2: 11.1.1 Security | KQ2: 11.1.2 Airfield Operations & Maintenance (including firefighting & winter services) | KR2: 11.1.3 Terminal, Landside Operations & Maintenance (including commercial operations) | KS2: 11.1.4 Administration | KT2: 11.1.5 Sales & Marketing | KU2: 11.1.6 Other - (please specify in text box any item >5% of total operating expenses) | KV2: 11.1.6 Other - TEXT | KW2: 12.1 Taxes levied on passengers | KX2: 12.2 Taxed levied on airlines | KY2: 13.1 Airport Capital Expenditure (CAPEX) | KZ2: 13.1.1 Purchase of property, plant & equipment | LA2: 13.1.2 Construction expenses | LB2: 13.1.3 Purchase of other goods & services | LC2: 13.1.4 Other capital expenditure items (please specify below) | LD2: 13.1.4 Other capital expenditure items TEXT | LE2: 13.2 Comments (please type in the box below): | LF2: 14.1 Return On Invested Capital (ROIC) (%) | LG2: 14.2 Return on Capital Employed (ROCE) (%)
F3: =IF(ISBLANK(ENGLISH!L27), "", ENGLISH!L27) | G3: =IF(LEN(F3)=3, "1", "") | H3: =IF(ISBLANK(ENGLISH!C27), "", ENGLISH!C27) | I3: =IF(ISBLANK(ENGLISH!C29), "", ENGLISH!C29) | J3: =IF(ISBLANK(ENGLISH!C31), "", ENGLISH!C31) | K3: =IF(ISBLANK(ENGLISH!L29), "", ENGLISH!L29) | L3: =IF(ISBLANK(ENGLISH!L31), "", ENGLISH!L31) | M3: =IF(ISBLANK(ENGLISH!F39), "", ENGLISH!F39) | N3: =IF(ISBLANK(ENGLISH!F41), "", ENGLISH!F41) | O3: =IF(ISBLANK(ENGLISH!F43), "", ENGLISH!F43) | P3: =IF(ISBLANK(ENGLISH!F45), "", ENGLISH!F45) | Q3: =IF(ISBLANK(ENGLISH!O39), "", ENGLISH!O39) | R3: =IF(ISBLANK(ENGLISH!O41), "", ENGLISH!O41) | S3: =IF(ISBLANK(ENGLISH!O43), "", ENGLISH!O43) | T3: =IF(ISBLANK(ENGLISH!O45), "", ENGLISH!O45) | U3: =IF(ISBLANK(ENGLISH!J52), "", ENGLISH!J52) | V3: =IF(ISBLANK(ENGLISH!M52), "", ENGLISH!M52) | W3: =IF(ISBLANK(ENGLISH!J54), "", ENGLISH!J54) | X3: =IF(ISBLANK(ENGLISH!M54), "", ENGLISH!M54) | Y3: =IF(ISBLANK(ENGLISH!J55), "", ENGLISH!J55) | Z3: =IF(ISBLANK(ENGLISH!M55), "", ENGLISH!M55) | AA3: =IF(ISBLANK(ENGLISH!J57), "", ENGLISH!J57) | AB3: =IF(ISBLANK(ENGLISH!M57), "", ENGLISH!M57) | AC3: =IF(ISBLANK(ENGLISH!J59), "", ENGLISH!J59) | AD3: =IF(ISBLANK(ENGLISH!M59), "", ENGLISH!M59) | AE3: =IF(ISBLANK(ENGLISH!J60), "", ENGLISH!J60) | AF3: =IF(ISBLANK(ENGLISH!M60), "", ENGLISH!M60) | AG3: =IF(ISBLANK(ENGLISH!J62), "", ENGLISH!J62) | AH3: =IF(ISBLANK(ENGLISH!M62), "", ENGLISH!M62) | AI3: =IF(ISBLANK(ENGLISH!J64), "", ENGLISH!J64) | AJ3: =IF(ISBLANK(ENGLISH!M64), "", ENGLISH!M64) | AK3: =IF(ISBLANK(ENGLISH!J67), "", ENGLISH!J67) | AL3: =IF(ISBLANK(ENGLISH!M67), "", ENGLISH!M67) | AM3: =IF(ISBLANK(ENGLISH!J68), "", ENGLISH!J68) | AN3: =IF(ISBLANK(ENGLISH!M68), "", ENGLISH!M68) | AO3: =IF(ISBLANK(ENGLISH!J70), "", ENGLISH!J70) | AP3: =IF(ISBLANK(ENGLISH!M70), "", ENGLISH!M70) | AQ3: =IF(ISBLANK(ENGLISH!J77), "", ENGLISH!J77) | AR3: =IF(ISBLANK(ENGLISH!J78), "", ENGLISH!J78) | AS3: =IF(ISBLANK(ENGLISH!J79), "", ENGLISH!J79) | AT3: =IF(ISBLANK(ENGLISH!J80), "", ENGLISH!J80) | AU3: =IF(ISBLANK(ENGLISH!J81), "", ENGLISH!J81) | AV3: =IF(ISBLANK(ENGLISH!J82), "", ENGLISH!J82) | AW3: =IF(ISBLANK(ENGLISH!J83), "", ENGLISH!J83) | AX3: =IF(ISBLANK(ENGLISH!J84), "", ENGLISH!J84) | AY3: =IF(ISBLANK(ENGLISH!J85), "", ENGLISH!J85) | AZ3: =IF(ISBLANK(ENGLISH!J87), "", ENGLISH!J87) | BA3: =IF(ISBLANK(ENGLISH!J88), "", ENGLISH!J88) | BB3: =IF(ISBLANK(ENGLISH!M94), "", ENGLISH!M94) | BC3: =IF(ISBLANK(ENGLISH!M96), "", ENGLISH!M96) | BD3: =IF(ISBLANK(ENGLISH!M98), "", ENGLISH!M98) | BE3: =IF(ISBLANK(ENGLISH!M100), "", ENGLISH!M100) | BF3: =IF(ISBLANK(ENGLISH!M102), "", ENGLISH!M102) | BG3: =IF(ISBLANK(ENGLISH!M104), "", ENGLISH!M104) | BH3: =IF(ISBLANK(ENGLISH!K115), "", ENGLISH!K115) | BI3: =IF(ISBLANK(ENGLISH!O115), "", ENGLISH!O115) | BJ3: FALSE | BK3: FALSE | BL3: FALSE | BM3: FALSE | BN3: FALSE | BO3: FALSE | BP3: FALSE | BQ3: FALSE | BR3: FALSE | BS3: FALSE | BT3: FALSE | BU3: FALSE | BV3: FALSE | BW3: FALSE | BX3: FALSE | BY3: FALSE | BZ3: FALSE | CA3: FALSE | CB3: FALSE | CC3: FALSE | CD3: FALSE | CE3: FALSE | CF3: FALSE | CG3: FALSE | CH3: FALSE | CI3: FALSE | CJ3: FALSE | CK3: FALSE | CL3: FALSE | CM3: FALSE | CN3: =IF(ISBLANK(ENGLISH!K119), "", ENGLISH!K119) | CO3: =IF(ISBLANK(ENGLISH!K120), "", ENGLISH!K120) | CP3: =IF(ISBLANK(ENGLISH!K122), "", ENGLISH!K122) | CQ3: =IF(ISBLANK(ENGLISH!K123), "", ENGLISH!K123) | CR3: =IF(ISBLANK(ENGLISH!K124), "", ENGLISH!K124) | CS3: =IF(ISBLANK(ENGLISH!K125), "", ENGLISH!K125) | CT3: =IF(ISBLANK(ENGLISH!K126), "", ENGLISH!K126) | CU3: =IF(ISBLANK(ENGLISH!K127), "", ENGLISH!K127) | CV3: =IF(ISBLANK(ENGLISH!K128), "", ENGLISH!K128) | CW3: =IF(ISBLANK(ENGLISH!K129), "", ENGLISH!K129) | CX3: =IF(ISBLANK(ENGLISH!K130), "", ENGLISH!K130) | CY3: =IF(ISBLANK(ENGLISH!K132), "", ENGLISH!K132) | CZ3: =IF(ISBLANK(ENGLISH!K133), "", ENGLISH!K133) | DA3: =IF(ISBLANK(ENGLISH!K134), "", ENGLISH!K134) | DB3: =IF(ISBLANK(ENGLISH!K135), "", ENGLISH!K135) | DC3: =IF(ISBLANK(ENGLISH!O119), "", ENGLISH!O119) | DD3: =IF(ISBLANK(ENGLISH!O120), "", ENGLISH!O120) | DE3: =IF(ISBLANK(ENGLISH!O122), "", ENGLISH!O122) | DF3: =IF(ISBLANK(ENGLISH!O123), "", ENGLISH!O123) | DG3: =IF(ISBLANK(ENGLISH!O124), "", ENGLISH!O124) | DH3: =IF(ISBLANK(ENGLISH!O125), "", ENGLISH!O125) | DI3: =IF(ISBLANK(ENGLISH!O126), "", ENGLISH!O126) | DJ3: =IF(ISBLANK(ENGLISH!O127), "", ENGLISH!O127) | DK3: =IF(ISBLANK(ENGLISH!O128), "", ENGLISH!O128) | DL3: =IF(ISBLANK(ENGLISH!O129), "", ENGLISH!O129) | DM3: =IF(ISBLANK(ENGLISH!O130), "", ENGLISH!O130) | DN3: =IF(ISBLANK(ENGLISH!O132), "", ENGLISH!O132) | DO3: =IF(ISBLANK(ENGLISH!O133), "", ENGLISH!O133) | DP3: =IF(ISBLANK(ENGLISH!O134), "", ENGLISH!O134) | DQ3: =IF(ISBLANK(ENGLISH!O135), "", ENGLISH!O135) | DR3: =IF(ISBLANK(ENGLISH!K138), "", ENGLISH!K138) | DS3: =IF(ISBLANK(ENGLISH!K146), "", ENGLISH!K146) -> 0 | DT3: =IF(ISBLANK(ENGLISH!K148), "", ENGLISH!K148) -> 0 | DU3: =IF(ISBLANK(ENGLISH!K150), "", ENGLISH!K150) | DV3: =IF(ISBLANK(ENGLISH!K151), "", ENGLISH!K151) | DW3: =IF(ISBLANK(ENGLISH!K152), "", ENGLISH!K152) | DX3: =IF(ISBLANK(ENGLISH!K153), "", ENGLISH!K153) | DY3: =IF(ISBLANK(ENGLISH!K154), "", ENGLISH!K154) | DZ3: =IF(ISBLANK(ENGLISH!K155), "", ENGLISH!K155) | EA3: =IF(ISBLANK(ENGLISH!K156), "", ENGLISH!K156) | EB3: =IF(ISBLANK(ENGLISH!K157), "", ENGLISH!K157) | EC3: =IF(ISBLANK(ENGLISH!K158), "", ENGLISH!K158) | ED3: =IF(ISBLANK(ENGLISH!K159), "", ENGLISH!K159) | EE3: =IF(ISBLANK(ENGLISH!K160), "", ENGLISH!K160) | EF3: =IF(ISBLANK(ENGLISH!K161), "", ENGLISH!K161) | EG3: =IF(ISBLANK(ENGLISH!K162), "", ENGLISH!K162) | EH3: =IF(ISBLANK(ENGLISH!K163), "", ENGLISH!K163) | EI3: =IF(ISBLANK(ENGLISH!K164), "", ENGLISH!K164) | EJ3: =IF(ISBLANK(ENGLISH!K165), "", ENGLISH!K165) | EK3: =IF(ISBLANK(ENGLISH!K167), "", ENGLISH!K167) | EL3: =IF(ISBLANK(ENGLISH!D167), "", ENGLISH!D167) | EM3: =IF(ISBLANK(ENGLISH!K169), "", ENGLISH!K169) -> 0 | EN3: =IF(ISBLANK(ENGLISH!K171), "", ENGLISH!K171) | EO3: =IF(ISBLANK(ENGLISH!K172), "", ENGLISH!K172) | EP3: =IF(ISBLANK(ENGLISH!K173), "", ENGLISH!K173) | EQ3: =IF(ISBLANK(ENGLISH!K174), "", ENGLISH!K174) | ER3: =IF(ISBLANK(ENGLISH!K175), "", ENGLISH!K175) | ES3: =IF(ISBLANK(ENGLISH!K176), "", ENGLISH!K176) | ET3: =IF(ISBLANK(ENGLISH!K177), "", ENGLISH!K177) | EU3: =IF(ISBLANK(ENGLISH!K179), "", ENGLISH!K179) | EV3: =IF(ISBLANK(ENGLISH!D179), "", ENGLISH!D179) | EW3: =IF(ISBLANK(ENGLISH!K181), "", ENGLISH!K181) -> 0 | EX3: =IF(ISBLANK(ENGLISH!K183), "", ENGLISH!K183) | EY3: =IF(ISBLANK(ENGLISH!K184), "", ENGLISH!K184) | EZ3: =IF(ISBLANK(ENGLISH!K185), "", ENGLISH!K185) | FA3: =IF(ISBLANK(ENGLISH!K187), "", ENGLISH!K187) | FB3: =IF(ISBLANK(ENGLISH!D187), "", ENGLISH!D187) | FC3: =IF(ISBLANK(ENGLISH!D191), "", ENGLISH!D191) | FD3: =IF(ISBLANK(ENGLISH!K199), "", ENGLISH!K199) -> 0 | FE3: =IF(ISBLANK(ENGLISH!K201), "", ENGLISH!K201) | FF3: =IF(ISBLANK(ENGLISH!K202), "", ENGLISH!K202) | FG3: =IF(ISBLANK(ENGLISH!K203), "", ENGLISH!K203) | FH3: =IF(ISBLANK(ENGLISH!K204), "", ENGLISH!K204) | FI3: =IF(ISBLANK(ENGLISH!K205), "", ENGLISH!K205) | FJ3: =IF(ISBLANK(ENGLISH!K206), "", ENGLISH!K206) | FK3: =IF(ISBLANK(ENGLISH!K207), "", ENGLISH!K207) | FL3: =IF(ISBLANK(ENGLISH!K208), "", ENGLISH!K208) | FM3: =IF(ISBLANK(ENGLISH!K210), "", ENGLISH!K210) | FN3: =IF(ISBLANK(ENGLISH!D210), "", ENGLISH!D210) | FO3: =IF(ISBLANK(ENGLISH!D214), "", ENGLISH!D214) | FP3: =IF(ISBLANK(ENGLISH!K222), "", ENGLISH!K222) -> 0 | FQ3: =IF(ISBLANK(ENGLISH!K224), "", ENGLISH!K224) -> 0 | FR3: =IF(ISBLANK(ENGLISH!K225), "", ENGLISH!K225) -> 0 | FS3: =IF(ISBLANK(ENGLISH!K226), "", ENGLISH!K226) -> 0 | FT3: =IF(ISBLANK(ENGLISH!K228), "", ENGLISH!K228) -> 0 | FU3: =IF(ISBLANK(ENGLISH!K230), "", ENGLISH!K230) -> 0 | FV3: =IF(ISBLANK(ENGLISH!K233), "", ENGLISH!K233) -> 0 | FW3: =IF(ISBLANK(ENGLISH!K235), "", ENGLISH!K235) | FX3: =IF(ISBLANK(ENGLISH!K236), "", ENGLISH!K236) | FY3: =IF(ISBLANK(ENGLISH!K238), "", ENGLISH!K238) | FZ3: =IF(ISBLANK(ENGLISH!D238), "", ENGLISH!D238) | GA3: =IF(ISBLANK(ENGLISH!K240), "", ENGLISH!K240) | GB3: =IF(ISBLANK(ENGLISH!K242), "", ENGLISH!K242) -> 0 | GC3: =IF(ISBLANK(ENGLISH!D247), "", ENGLISH!D247) | GD3: =IF(ISBLANK(ENGLISH!K255), "", ENGLISH!K255) -> 0 | GE3: =IF(ISBLANK(ENGLISH!K257), "", ENGLISH!K257) -> 0 | GF3: =IF(ISBLANK(ENGLISH!K258), "", ENGLISH!K258) | GG3: =IF(ISBLANK(ENGLISH!K259), "", ENGLISH!K259) | GH3: =IF(ISBLANK(ENGLISH!K261), "", ENGLISH!K261) -> 0 | GI3: =IF(ISBLANK(ENGLISH!K262), "", ENGLISH!K262) | GJ3: =IF(ISBLANK(ENGLISH!K264),"", ENGLISH!K264) | GK3: =IF(ISBLANK(ENGLISH!K266), "", ENGLISH!K266) -> 0 | GL3: =IF(ISBLANK(ENGLISH!K267), "", ENGLISH!K267) | GM3: =IF(ISBLANK(ENGLISH!K268), "", ENGLISH!K268) | GN3: =IF(ISBLANK(ENGLISH!K270), "", ENGLISH!K270) -> 0 | GO3: =IF(ISBLANK(ENGLISH!K263), "", ENGLISH!K263) | GP3: =IF(ISBLANK(ENGLISH!K276), "", ENGLISH!K276) | GQ3: =IF(ISBLANK(ENGLISH!K279), "", ENGLISH!K279) | GR3: =IF(ISBLANK(ENGLISH!M279), "", ENGLISH!M279) | GS3: =IF(ISBLANK(ENGLISH!O279), "", ENGLISH!O279) | GT3: =IF(ISBLANK(ENGLISH!Q279), "", ENGLISH!Q279) | GU3: =IF(ISBLANK(ENGLISH!K285), "", ENGLISH!K285) -> 0 | GV3: =IF(ISBLANK(ENGLISH!K287),"",ENGLISH!K287) | GW3: =IF(ISBLANK(ENGLISH!K288),"",ENGLISH!K288) | GX3: =IF(ISBLANK(ENGLISH!K289),"",ENGLISH!K289) | GY3: =IF(ISBLANK(ENGLISH!K290),"",ENGLISH!K290) | GZ3: =IF(ISBLANK(ENGLISH!K291),"",ENGLISH!K291) | HA3: =IF(ISBLANK(ENGLISH!K293),"",ENGLISH!K293) | HB3: =IF(ISBLANK(ENGLISH!D293), "", ENGLISH!D293) | HC3: =IF(ISBLANK(ENGLISH!K299), "", ENGLISH!K299) | HD3: =IF(ISBLANK(ENGLISH!K300), "", ENGLISH!K300) | HE3: =IF(ISBLANK(ENGLISH!K306), "", ENGLISH!K306) -> 0 | HF3: =IF(ISBLANK(ENGLISH!K308), "", ENGLISH!K308) | HG3: =IF(ISBLANK(ENGLISH!K309), "", ENGLISH!K309) | HH3: =IF(ISBLANK(ENGLISH!K310), "", ENGLISH!K31) | HI3: =IF(ISBLANK(ENGLISH!K312), "", ENGLISH!K312) | HJ3: =IF(ISBLANK(ENGLISH!D312), "", ENGLISH!D312) | HK3: =IF(ISBLANK(ENGLISH!D316), "", ENGLISH!D316) | HL3: =IF(ISBLANK(ENGLISH!K324), "", ENGLISH!K324) | HM3: =IF(ISBLANK(ENGLISH!K325), "", ENGLISH!K325) | HQ3: =IF(ISBLANK(ENGLISH!O146), "", ENGLISH!O146) -> 0 | HR3: =IF(ISBLANK(ENGLISH!O148), "", ENGLISH!O148) -> 0 | HS3: =IF(ISBLANK(ENGLISH!O150), "", ENGLISH!O150) | HT3: =IF(ISBLANK(ENGLISH!O151), "", ENGLISH!O151) | HU3: =IF(ISBLANK(ENGLISH!O152), "", ENGLISH!O152) | HV3: =IF(ISBLANK(ENGLISH!O153), "", ENGLISH!O153) | HW3: =IF(ISBLANK(ENGLISH!O154), "", ENGLISH!O154) | HX3: =IF(ISBLANK(ENGLISH!O155), "", ENGLISH!O155) | HY3: =IF(ISBLANK(ENGLISH!O156), "", ENGLISH!O156) | HZ3: =IF(ISBLANK(ENGLISH!O157), "", ENGLISH!O157) | IA3: =IF(ISBLANK(ENGLISH!O158), "", ENGLISH!O158) | IB3: =IF(ISBLANK(ENGLISH!O159), "", ENGLISH!O159) | IC3: =IF(ISBLANK(ENGLISH!O160), "", ENGLISH!O160) | ID3: =IF(ISBLANK(ENGLISH!O161), "", ENGLISH!O161) | IE3: =IF(ISBLANK(ENGLISH!O162), "", ENGLISH!O162) | IF3: =IF(ISBLANK(ENGLISH!O163), "", ENGLISH!O163) | IG3: =IF(ISBLANK(ENGLISH!O164), "", ENGLISH!O164) | IH3: =IF(ISBLANK(ENGLISH!O165), "", ENGLISH!O165) | II3: =IF(ISBLANK(ENGLISH!O167), "", ENGLISH!O167) | IJ3: =IF(ISBLANK(ENGLISH!D167), "", ENGLISH!D167) | IK3: =IF(ISBLANK(ENGLISH!O169), "", ENGLISH!O169) -> 0 | IL3: =IF(ISBLANK(ENGLISH!O171), "", ENGLISH!O171) | IM3: =IF(ISBLANK(ENGLISH!O172), "", ENGLISH!O172) | IN3: =IF(ISBLANK(ENGLISH!O173), "", ENGLISH!O173) | IO3: =IF(ISBLANK(ENGLISH!O174), "", ENGLISH!O174) | IP3: =IF(ISBLANK(ENGLISH!O175), "", ENGLISH!O175) | IQ3: =IF(ISBLANK(ENGLISH!O176), "", ENGLISH!O176) | IR3: =IF(ISBLANK(ENGLISH!O177), "", ENGLISH!O177) | IS3: =IF(ISBLANK(ENGLISH!O179), "", ENGLISH!O179) | IT3: =IF(ISBLANK(ENGLISH!D179), "", ENGLISH!D179) | IU3: =IF(ISBLANK(ENGLISH!O181), "", ENGLISH!O181) -> 0 | IV3: =IF(ISBLANK(ENGLISH!O183), "", ENGLISH!O183) | IW3: =IF(ISBLANK(ENGLISH!O184), "", ENGLISH!O184) | IX3: =IF(ISBLANK(ENGLISH!O185), "", ENGLISH!O185) | IY3: =IF(ISBLANK(ENGLISH!O187), "", ENGLISH!O187) | IZ3: =IF(ISBLANK(ENGLISH!DB187), "", ENGLISH!DB187) | JA3: =IF(ISBLANK(ENGLISH!D191), "", ENGLISH!D191) | JB3: =IF(ISBLANK(ENGLISH!O199), "", ENGLISH!O199) -> 0 | JC3: =IF(ISBLANK(ENGLISH!O201), "", ENGLISH!O201) | JD3: =IF(ISBLANK(ENGLISH!O202), "", ENGLISH!O202) | JE3: =IF(ISBLANK(ENGLISH!O203), "", ENGLISH!O203) | JF3: =IF(ISBLANK(ENGLISH!O204), "", ENGLISH!O204) | JG3: =IF(ISBLANK(ENGLISH!O205), "", ENGLISH!O205) | JH3: =IF(ISBLANK(ENGLISH!O206), "", ENGLISH!O206) | JI3: =IF(ISBLANK(ENGLISH!O207), "", ENGLISH!O207) | JJ3: =IF(ISBLANK(ENGLISH!O208), "", ENGLISH!O208) | JK3: =IF(ISBLANK(ENGLISH!O210), "", ENGLISH!O210) | JL3: =IF(ISBLANK(ENGLISH!D210), "", ENGLISH!D210) | JM3: =IF(ISBLANK(ENGLISH!D214), "", ENGLISH!D214) | JN3: =IF(ISBLANK(ENGLISH!O222), "", ENGLISH!O222) -> 0 | JO3: =IF(ISBLANK(ENGLISH!O224), "", ENGLISH!O224) -> 0 | JP3: =IF(ISBLANK(ENGLISH!O225), "", ENGLISH!O225) -> 0 | JQ3: =IF(ISBLANK(ENGLISH!O226), "", ENGLISH!O226) -> 0 | JR3: =IF(ISBLANK(ENGLISH!O228), "", ENGLISH!O228) -> 0 | JS3: =IF(ISBLANK(ENGLISH!O230), "", ENGLISH!O230) -> 0 | JT3: =IF(ISBLANK(ENGLISH!O233), "", ENGLISH!O233) -> 0 | JU3: =IF(ISBLANK(ENGLISH!O235), "", ENGLISH!O235) | JV3: =IF(ISBLANK(ENGLISH!O236), "", ENGLISH!O236) | JW3: =IF(ISBLANK(ENGLISH!O238), "", ENGLISH!O238) | JX3: =IF(ISBLANK(ENGLISH!D238), "", ENGLISH!D238) | JY3: =IF(ISBLANK(ENGLISH!O240), "", ENGLISH!O240) | JZ3: =IF(ISBLANK(ENGLISH!O242), "", ENGLISH!O242) -> 0 | KA3: =IF(ISBLANK(ENGLISH!D247), "", ENGLISH!D247) | KB3: =IF(ISBLANK(ENGLISH!O255), "", ENGLISH!O255) -> 0 | KC3: =IF(ISBLANK(ENGLISH!O257), "", ENGLISH!O257) -> 0 | KD3: =IF(ISBLANK(ENGLISH!O258), "", ENGLISH!O258) | KE3: =IF(ISBLANK(ENGLISH!O259), "", ENGLISH!O259) | KF3: =IF(ISBLANK(ENGLISH!O261), "", ENGLISH!O261) -> 0 | KG3: =IF(ISBLANK(ENGLISH!O262), "", ENGLISH!O262) | KH3: =IF(ISBLANK(ENGLISH!O264),"", ENGLISH!O264) | KI3: =IF(ISBLANK(ENGLISH!O266), "", ENGLISH!O266) -> 0 | KJ3: =IF(ISBLANK(ENGLISH!O267), "", ENGLISH!O267) | KK3: =IF(ISBLANK(ENGLISH!O268), "", ENGLISH!O268) | KL3: =IF(ISBLANK(ENGLISH!O270), "", ENGLISH!O270) -> 0 | KM3: =IF(ISBLANK(ENGLISH!O263), "", ENGLISH!O263) | KN3: =IF(ISBLANK(ENGLISH!O276), "", ENGLISH!O276) | KO3: =IF(ISBLANK(ENGLISH!O285), "", ENGLISH!O285) -> 0 | KP3: =IF(ISBLANK(ENGLISH!O287),"",ENGLISH!O287) | KQ3: =IF(ISBLANK(ENGLISH!O288),"",ENGLISH!O288) | KR3: =IF(ISBLANK(ENGLISH!O289),"",ENGLISH!O289) | KS3: =IF(ISBLANK(ENGLISH!O290),"",ENGLISH!O290) | KT3: =IF(ISBLANK(ENGLISH!O291),"",ENGLISH!O291) | KU3: =IF(ISBLANK(ENGLISH!O293),"",ENGLISH!O293) | KV3: =IF(ISBLANK(ENGLISH!D293), "", ENGLISH!D293) | KW3: =IF(ISBLANK(ENGLISH!O299), "", ENGLISH!O299) | KX3: =IF(ISBLANK(ENGLISH!O300), "", ENGLISH!O300) | KY3: =IF(ISBLANK(ENGLISH!O306), "", ENGLISH!O306) -> 0 | KZ3: =IF(ISBLANK(ENGLISH!O308), "", ENGLISH!O308) | LA3: =IF(ISBLANK(ENGLISH!O309), "", ENGLISH!O309) | LB3: =IF(ISBLANK(ENGLISH!O310), "", ENGLISH!O31) | LC3: =IF(ISBLANK(ENGLISH!O312), "", ENGLISH!O312) | LD3: =IF(ISBLANK(ENGLISH!D312), "", ENGLISH!D312) | LE3: =IF(ISBLANK(ENGLISH!D316), "", ENGLISH!D316) | LF3: =IF(ISBLANK(ENGLISH!O324), "", ENGLISH!O324) | LG3: =IF(ISBLANK(ENGLISH!O325), "", ENGLISH!O325)

Sheet for internal use (FRENCH)
A1: 1 | B1: 1 | C1: 1 | D1: 1 | E1: 1 | F1: 1 | G1: 1 | H1: 1 | I1: 1 | J1: 1 | K1: 1 | L1: 1 | M1: 2 | N1: 2 | O1: 2 | P1: 2 | Q1: 2 | R1: 2 | S1: 2 | T1: 2 | U1: 3.1 | W1: 3.1 | Y1: 3.1 | AA1: 3.1 | AC1: 3.1 | AE1: 3.1 | AG1: 3.1 | AI1: 3.1 | AK1: 3.1 | AM1: 3.1 | AO1: 3.1 | AQ1: 3.2 | AR1: 3.2 | AS1: 3.2 | AT1: 3.2 | AU1: 3.2 | AV1: 3.2 | AW1: 3.2 | AX1: 3.2 | AY1: 3.2 | AZ1: 3.2 | BA1: 3.2 | BB1: 4 | BC1: 4 | BD1: 4 | BE1: 4 | BF1: 4 | BG1: 4 | BH1: 5 | BI1: 5 | BJ1: 5 | BK1: 5 | BL1: 5 | BM1: 5 | BN1: 5 | BO1: 5 | BP1: 5 | BQ1: 5 | BR1: 5 | BS1: 5 | BT1: 5 | BU1: 5 | BV1: 5 | BW1: 5 | BY1: 5 | BZ1: 5 | CA1: 5 | CB1: 5 | CC1: 5 | CD1: 5 | CE1: 5 | CF1: 5 | CG1: 5 | CH1: 5 | CI1: 5 | CJ1: 5 | CK1: 5 | CL1: 5 | CM1: 5 | CN1: 5 | CO1: 5 | CP1: 5 | CQ1: 5 | CR1: 5 | CS1: 5 | CT1: 5 | CU1: 5 | CV1: 5 | CW1: 5 | CX1: 5 | CY1: 5 | CZ1: 5 | DA1: 5 | DB1: 5 | DC1: 5 | DD1: 5 | DE1: 5 | DF1: 5 | DG1: 5 | DH1: 5 | DI1: 5 | DJ1: 5 | DK1: 5 | DL1: 5 | DM1: 5 | DN1: 5 | DO1: 5 | DP1: 5 | DQ1: 5 | DR1: 5 | DS1: 6 | DT1: 6 | DU1: 6 | DV1: 6 | DW1: 6 | DX1: 6 | DY1: 6 | DZ1: 6 | EA1: 6 | EB1: 6 | EC1: 6 | ED1: 6 | EE1: 6 | EF1: 6 | EG1: 6 | EH1: 6 | EI1: 6 | EJ1: 6 | EK1: 6 | EL1: 6 | EM1: 6 | EN1: 6 | EO1: 6 | EP1: 6 | EQ1: 6 | ER1: 6 | ES1: 6 | ET1: 6 | EU1: 6 | EV1: 6 | EW1: 6 | EX1: 6 | EY1: 6 | EZ1: 6 | FA1: 6 | FB1: 6 | FC1: 6 | FD1: 7 | FE1: 7 | FF1: 7 | FG1: 7 | FH1: 7 | FI1: 7 | FJ1: 7 | FK1: 7 | FL1: 7 | FM1: 7 | FN1: 7 | FO1: 7 | FP1: 8 | FQ1: 8 | FR1: 8 | FS1: 8 | FT1: 8 | FU1: 8 | FV1: 8 | FW1: 8 | FX1: 8 | FY1: 8 | FZ1: 8 | GA1: 8 | GB1: 8 | GC1: 8 | GD1: 9 | GE1: 9 | GF1: 9 | GG1: 9 | GH1: 9 | GI1: 9 | GJ1: 9 | GK1: 9 | GL1: 9 | GM1: 9 | GN1: 9 | GO1: 9 | GP1: 10 | GQ1: 10 | GR1: 10 | GS1: 10 | GT1: 10 | GU1: 11 | GV1: 11 | GW1: 11 | GX1: 11 | GY1: 11 | GZ1: 11 | HA1: 11 | HB1: 11 | HC1: 12 | HD1: 12 | HE1: 13 | HF1: 13 | HG1: 13 | HH1: 13 | HI1: 13 | HJ1: 13 | HK1: 13 | HL1: 14 | HM1: 14 | HQ1: 6 (2011) | HR1: 6 (2011) | HS1: 6 (2011) | HT1: 6 (2011) | HU1: 6 (2011) | HV1: 6 (2011) | HW1: 6 (2011) | HX1: 6 (2011) | HY1: 6 (2011) | HZ1: 6 (2011) | IA1: 6 (2011) | IB1: 6 (2011) | IC1: 6 (2011) | ID1: 6 (2011) | IE1: 6 (2011) | IF1: 6 (2011) | IG1: 6 (2011) | IH1: 6 (2011) | II1: 6 (2011) | IJ1: 6 (2011) | IK1: 6 (2011) | IL1: 6 (2011) | IM1: 6 (2011) | IN1: 6 (2011) | IO1: 6 (2011) | IP1: 6 (2011) | IQ1: 6 (2011) | IR1: 6 (2011) | IS1: 6 (2011) | IT1: 6 (2011) | IU1: 6 (2011) | IV1: 6 (2011) | IW1: 6 (2011) | IX1: 6 (2011) | IY1: 6 (2011) | IZ1: 6 (2011) | JA1: 6 (2011) | JB1: 7 (2011) | JC1: 7 (2011) | JD1: 7 (2011) | JE1: 7 (2011) | JF1: 7 (2011) | JG1: 7 (2011) | JH1: 7 (2011) | JI1: 7 (2011) | JJ1: 7 (2011) | JK1: 7 (2011) | JL1: 7 (2011) | JM1: 7 (2011) | JN1: 8 (2011) | JO1: 8 (2011) | JP1: 8 (2011) | JQ1: 8 (2011) | JR1: 8 (2011) | JS1: 8 (2011) | JT1: 8 (2011) | JU1: 8 (2011) | JV1: 8 (2011) | JW1: 8 (2011) | JX1: 8 (2011) | JY1: 8 (2011) | JZ1: 8 (2011) | KA1: 8 (2011) | KB1: 9 (2011) | KC1: 9 (2011) | KD1: 9 (2011) | KE1: 9 (2011) | KF1: 9 (2011) | KG1: 9 (2011) | KH1: 9 (2011) | KI1: 9 (2011) | KJ1: 9 (2011) | KK1: 9 (2011) | KL1: 9 (2011) | KM1: 9 (2011) | KN1: 10 (2011) | KO1: 11 (2011) | KP1: 11 (2011) | KQ1: 11 (2011) | KR1: 11 (2011) | KS1: 11 (2011) | KT1: 11 (2011) | KU1: 11 (2011) | KV1: 11 (2011) | KW1: 12 (2011) | KX1: 12 (2011) | KY1: 13 (2011) | KZ1: 13 (2011) | LA1: 13 (2011) | LB1: 13 (2011) | LC1: 13 (2011) | LD1: 13 (2011) | LE1: 13 (2011) | LF1: 14 (2011) | LG1: 14 (2011)
A2: Region | B2: City | C2: Country | D2: Operator | E2: Size Category | F2: Code | G2: Count | H2: Airport Name | I2: Contact person | J2: Title | K2: Tel. Number | L2: Email Address | M2: 2.1 Passengers: | N2: 2.2 Cargo (metric tons): | O2: 2.3 Movements | P2: 2.4 WLU: | Q2: 2.5 Financial Year (please select): | R2: 2.6 Financial figures submitted in: | S2: 2.7 Reporting Currency (please select): | T2: 2.8 Suggested exchange rate: | U2: 3.1.1 Total Airport Site Area | W2: 3.1.1.1 Airside Area | Y2: 3.1.1.2 Landside area | AA2: 3.1.2 Passenger Terminal(s) Building(s) Area | AC2: 3.1.2.1 Airside Area | AE2: 3.1.2.2 Landside area | AG2: 3.1.3 Cargo Terminal(s) Building(s) Area | AI2: 3.1.4 Commercial Activity Area | AK2: 3.1.4.1 Food & beverage | AM2: 3.1.4.2 Retail Activity Area | AO2: 3.1.4.2.1 Duty Free Area | AQ2: 3.2.1 Runways (paved landing strips) | AR2: 3.2.2 Contact gates with air bridge (jet bridge) | AS2: 3.2.3 Remote stands (B737-800 or equivalent) | AT2: 3.2.4 Passenger terminals | AU2: 3.2.5 Cargo terminals | AV2: 3.2.6 Passenger check-in desks/counters | AW2: 3.2.7 Self service kiosks operated by airport | AX2: 3.2.8 Individual car parking spaces | AY2: 3.2.9 Retail stores / shops / boutiques | AZ2: 3.2.9.1 Duty-Free shops | BA2: 3.2.10 Restaurants / cafés and other F&B outlets | BB2: 4.1 Pricing regulation | BC2: 4.2 Economic Oversigght | BD2: 4.3 Ownership Structure | BE2: 4.4 Private participation | BF2: 4.5 WACC | BG2: 4.6 Incentive scheme | BH2: 5.1 Total personnel employed by airport operator | Headcount | BI2: 5.1 Total personnel employed by airport operator | FTE | BJ2: 5.1.1 Management | Insourced | BK2: 5.1.2 Ground handling services: | Insourced | BL2: 5.1.2.1 Passenger handling services | Insourced | BM2: 5.1.2.2 Ramp handling services | Insourced | BN2: 5.1.2.3 Cargo handling services | Insourced | BO2: 5.1.3 Rescue and fire service | Insourced | BP2: 5.1.4 Car parking services | Insourced | BQ2: 5.1.5 Cleaning services | Insourced | BR2: 5.1.6 Maintenance services | Insourced | BS2: 5.1.7 Air traffic control services | Insourced | BT2: 5.1.8 Passenger security services | Insourced | BU2: 5.1.8.1 Other security (e.g. perimeter and cargo security) | Insourced | BV2: 5.1.10 Concession services (shops, F&B, etc.) | Insourced | BW2: 5.1.11 Runway, taxiway, apron operations |Insourced | BX2: 5.1.12 Other |Insourced | BY2: 5.1.1 Management | Outsourced | BZ2: 5.1.2 Ground handling services: | Outsourced | CA2: 5.1.2.1 Passenger handling services | Outsourced | CB2: 5.1.2.2 Ramp handling services | Outsourced | CC2: 5.1.2.3 Cargo handling services | Outsourced | CD2: 5.1.3 Rescue and fire service | Outsourced | CE2: 5.1.4 Car parking services | Outsourced | CF2: 5.1.5 Cleaning services | Outsourced | CG2: 5.1.6 Maintenance services | Outsourced | CH2: 5.1.7 Air traffic control services | Outsourced | CI2: 5.1.8 Passenger security services | Outsourced | CJ2: 5.1.8.1 Other security (e.g. perimeter and cargo security) | Outsourced | CK2: 5.1.10 Concession services (shops, F&B, etc.) | Outsourced | CL2: 5.1.11 Runway, taxiway, apron operations | Outsourced | CM2: 5.1.12 Other | Outsorced | CN2: 5.1.1 Management | Headcount | CO2: 5.1.2 Ground handling services: | Headcount | CP2: 5.1.2.1 Passenger handling services | Headcount | CQ2: 5.1.2.2 Ramp handling services | Headcount | CR2: 5.1.2.3 Cargo handling services | Headcount | CS2: 5.1.3 Rescue and fire service | Headcount | CT2: 5.1.4 Car parking services | Headcount | CU2: 5.1.5 Cleaning services | Headcount | CV2: 5.1.6 Maintenance services | Headcount | CW2: 5.1.7 Air traffic control services | Headcount | CX2: 5.1.8 Passenger security services | Headcount | CY2: 5.1.8.1 Other security (e.g. perimeter and cargo security) | Headcount | CZ2: 5.1.10 Concession services (shops, F&B, etc.) | Headcount | DA2: 5.1.11 Runway, taxiway, apron operations | Headcount | DB2: 5.1.12 Other | Headcount | DC2: 5.1.1 Management | FTE | DD2: 5.1.2 Ground handling services: | FTE | DE2: 5.1.2.1 Passenger handling services | FTE | DF2: 5.1.2.2 Ramp handling services | FTE | DG2: 5.1.2.3 Cargo handling services | FTE | DH2: 5.1.3 Rescue and fire service | FTE | DI2: 5.1.4 Car parking services | FTE | DJ2: 5.1.5 Cleaning services | FTE | DK2: 5.1.6 Maintenance services | FTE | DL2: 5.1.7 Air traffic control services | FTE | DM2: 5.1.8 Passenger security services | FTE | DN2: 5.1.8.1 Other security (e.g. perimeter and cargo security) | FTE | DO2: 5.1.10 Concession services (shops, F&B, etc.) | FTE | DP2: 5.1.11 Runway, taxiway, apron operations | FTE | DQ2: 5.1.12 Other | FTE | DR2: 5.2 Total number of people working at the airport | DS2: 6.1 Total Airport Revenue (Sum 6.1.1, 6.1.2, 6.1.3) | DT2: 6.1.1 Operating Aeronautical Revenue (sum 6.1.1.1 -6.1.1.12, 6.1.1.13-6.1.1.16) | DU2: 6.1.1.1 Landing charges | DV2: 6.1.1.2 Lighting surcharges | DW2: 6.1.1.3 Noise & other environmental charges | DX2: 6.1.1.4 Navaid charges | DY2: 6.1.1.5 Parking charges | DZ2: 6.1.1.6 Boarding bridge charges | EA2: 6.1.1.7 Passenger charges (excluding AIF or similar) | EB2: 6.1.1.8 Transfer / transit charges | EC2: 6.1.1.9 Security charges | ED2: 6.1.1.10 Cargo (or freight) charges | EE2: 6.1.1.11 Fueling charges | EF2: 6.1.1.12 Ground handling services (excluding fuel charges) | EG2: 6.1.1.12.1 Ground handling infrastructure (if additional to 6.1.1.4) | EH2: 6.1.1.13 Airport improvement fees - AIF (or Passenger facility charge) | EI2: 6.1.1.14 Utility recharges (e.g. water, electricity, etc.) | EJ2: 6.1.1.15 Terminal rentals paid by airlines for space utilization | EK2: 6.1.1.16 Other (please specify in text box below any item >3% of total income) | EL2: 6.1.1.16 Other TEXT | EM2: 6.1.2 Operating Non-Aeronautical Revenue (sum 6.1.2.1 - 6.1.2.7) | EN2: 6.1.2.1 Retail concessions | EO2: 6.1.2.1.1Duty Free concessions | EP2: 6.1.2.2 Food & Beverage | EQ2: 6.1.2.3 Car parking | ER2: 6.1.2.4 Rental car concessions | ES2: 6.1.2.5 Property & real estate income or rent | ET2: 6.1.2.6 Advertising | EU2: 6.1.2.7 Other (please specify in the text box below any item >3%) | EV2: 6.1.2.7 Other TEXT | EW2: 6.1.3 Non-Operating Revenue (sum 6.1.3.1-6.1.3.4) | EX2: 6.1.3.1 Interest income | EY2: 6.1.3.2 Subsidies / Grants | EZ2: 6.1.3.3 Asset Divestments | FA2: 6.1.3.4 Other (please specify in text box any item >3%) | FB2: 6.1.3.4 Other TEXT | FC2: 6.1.4 Comments (please type in the box below): | FD2: 7.1 Total Operating Expenses (sum 7.1.1 - 7.1.9) | FE2: 7.1.1 Personnel expenses (salaries and benefits) | FF2: 7.1.2 Contracted services (cost of services paid to third parties) | FG2: 7.1.3 Materials, equipment, supplies (excluding maintenance/contracted serv.) | FH2: 7.1.4 Communications, utilities, energy & waste | FI2: 7.1.5 Insurance, claims, settlements | FJ2: 7.1.6 Maintenance (excluding contracted services) | FK2: 7.1.7 Lease, rent, concession fee payments | FL2: 7.1.8 General and administrative expenses (excluding personnel) | FM2: 7.1.9 Other - (please specify in text box any item >3% of total expenses): | FN2: 7.1.9 Other TEXT | FO2: 7.2 Comments (please type in the box below): | FP2: 8.1 Total Airport Income | FQ2: 8.1.1 Operating Aeronautical Income | FR2: 8.1.2 Operating Non-Aeronautical Income | FS2: 8.1.3 Non-Operating Income | FT2: 8.2 Total Operating Expenses | FU2: 8.3 Operating Surplus/Deficit (EBITDA) | FV2: 8.4 Capital Costs | FW2: 8.4.1 Interest and dividends paid to third parties | FX2: 8.4.2 Depreciation or/and amortization of property, plant & equipment | FY2: 8.4.3 Other capital costs (please specify below) | FZ2: 8.4.3 Other capital costs TEXT | GA2: 8.5 Taxes & Other Fees | GB2: 8.6 Net Profit / Loss | GC2: 8.7 Comments (please type in the box below): | GD2: 9.1 Total Assets | GE2: 9.1.1 Current Assets | GF2: 9.1.1.1 Cash and equivalent | GG2: 9.1.1.2 Other | GH2: 9.1.2 Non Current Assets | GI2: 9.1.2.1 Fixed assets | GJ2: 9.1.2.2 Other | GK2: 9.2 Total Liabilities | GL2: 9.2.1 Current liabilities | GM2: 9.2.1 Non-current liabilities | GN2: 9.3 Net Assets (9.1 - 9.2) | GO2: 9.4 Accumulated depreciation of fixed assets (9.1.2.1) | GP2: 10.1 Debt outstanding | GQ2: 10.2 What is the credit rating of financial instruments issued by the airport company? Moody's: | GR2: 10.2 What is the credit rating of financial instruments issued by the airport company? S&P: | GS2: 10.2 What is the credit rating of financial instruments issued by the airport company? Fitch: | GT2: 10.2 What is the credit rating of financial instruments issued by the airport company? In words: | GU2: 11.1 Total Operating Expenses (Total corresponds to 7.1) | GV2: 11.1.1 Security | GW2: 11.1.2 Airfield Operations & Maintenance (including firefighting & winter services) | GX2: 11.1.3 Terminal, Landside Operations & Maintenance (including commercial operations) | GY2: 11.1.4 Administration | GZ2: 11.1.5 Sales & Marketing | HA2: 11.1.6 Other - (please specify in text box any item >5% of total operating expenses) | HB2: 11.1.6 Other - TEXT | HC2: 12.1 Taxes levied on passengers | HD2: 12.2 Taxed levied on airlines | HE2: 13.1 Airport Capital Expenditure (CAPEX) | HF2: 13.1.1 Purchase of property, plant & equipment | HG2: 13.1.2 Construction expenses | HH2: 13.1.3 Purchase of other goods & services | HI2: 13.1.4 Other capital expenditure items (please specify below) | HJ2: 13.1.4 Other capital expenditure items TEXT | HK2: 13.2 Comments (please type in the box below): | HL2: 14.1 Return On Invested Capital (ROIC) (%) | HM2: 14.2 Return on Capital Employed (ROCE) (%) | HQ2: 6.1 Total Airport Revenue (Sum 6.1.1, 6.1.2, 6.1.3) | HR2: 6.1.1 Operating Aeronautical Revenue (sum 6.1.1.1 -6.1.1.12, 6.1.1.13-6.1.1.16) | HS2: 6.1.1.1 Landing charges | HT2: 6.1.1.2 Lighting surcharges | HU2: 6.1.1.3 Noise & other environmental charges | HV2: 6.1.1.4 Navaid charges | HW2: 6.1.1.5 Parking charges | HX2: 6.1.1.6 Boarding bridge charges | HY2: 6.1.1.7 Passenger charges (excluding AIF or similar) | HZ2: 6.1.1.8 Transfer / transit charges | IA2: 6.1.1.9 Security charges | IB2: 6.1.1.10 Cargo (or freight) charges | IC2: 6.1.1.11 Fueling charges | ID2: 6.1.1.12 Ground handling services (excluding fuel charges) | IE2: 6.1.1.12.1 Ground handling infrastructure (if additional to 6.1.1.4) | IF2: 6.1.1.13 Airport improvement fees - AIF (or Passenger facility charge) | IG2: 6.1.1.14 Utility recharges (e.g. water, electricity, etc.) | IH2: 6.1.1.15 Terminal rentals paid by airlines for space utilization | II2: 6.1.1.16 Other (please specify in text box below any item >3% of total income) | IJ2: 6.1.1.16 Other TEXT | IK2: 6.1.2 Operating Non-Aeronautical Revenue (sum 6.1.2.1 - 6.1.2.7) | IL2: 6.1.2.1 Retail concessions | IM2: 6.1.2.1.1 of which: Duty Free concessions | IN2: 6.1.2.2 Food & Beverage | IO2: 6.1.2.3 Car parking | IP2: 6.1.2.4 Rental car concessions | IQ2: 6.1.2.5 Property & real estate income or rent | IR2: 6.1.2.6 Advertising | IS2: 6.1.2.7 Other (please specify in the text box below any item >3%) | IT2: 6.1.2.7 Other TEXT | IU2: 6.1.3 Non-Operating Revenue (sum 6.1.3.1-6.1.3.4) | IV2: 6.1.3.1 Interest income | IW2: 6.1.3.2 Subsidies / Grants | IX2: 6.1.3.3 Asset Divestments | IY2: 6.1.3.4 Other (please specify in text box any item >3%) | IZ2: 6.1.3.4 Other TEXT | JA2: 6.1.4 Comments (please type in the box below): | JB2: 7.1 Total Operating Expenses (sum 7.1.1 - 7.1.9) | JC2: 7.1.1 Personnel expenses (salaries and benefits) | JD2: 7.1.2 Contracted services (cost of services paid to third parties) | JE2: 7.1.3 Materials, equipment, supplies (excluding maintenance/contracted serv.) | JF2: 7.1.4 Communications, utilities, energy & waste | JG2: 7.1.5 Insurance, claims, settlements | JH2: 7.1.6 Maintenance (excluding contracted services) | JI2: 7.1.7 Lease, rent, concession fee payments | JJ2: 7.1.8 General and administrative expenses (excluding personnel) | JK2: 7.1.9 Other - (please specify in text box any item >3% of total expenses): | JL2: 7.1.9 Other TEXT | JM2: 7.2 Comments (please type in the box below): | JN2: 8.1 Total Airport Income | JO2: 8.1.1 Operating Aeronautical Income | JP2: 8.1.2 Operating Non-Aeronautical Income | JQ2: 8.1.3 Non-Operating Income | JR2: 8.2 Total Operating Expenses | JS2: 8.3 Operating Surplus/Deficit (EBITDA) | JT2: 8.4 Capital Costs | JU2: 8.4.1 Interest and dividends paid to third parties | JV2: 8.4.2 Depreciation or/and amortization of property, plant & equipment | JW2: 8.4.3 Other capital costs (please specify below) | JX2: 8.4.3 Other capital costs TEXT | JY2: 8.5 Taxes & Other Fees | JZ2: 8.6 Net Profit / Loss | KA2: 8.7 Comments (please type in the box below): | KB2: 9.1 Total Assets | KC2: 9.1.1 Current Assets | KD2: 9.1.1.1 Cash and equivalent | KE2: 9.1.1.2 Other | KF2: 9.1.2 Non Current Assets | KG2: 9.1.2.1 Fixed assets | KH2: 9.1.2.2 Other | KI2: 9.2 Total Liabilities | KJ2: 9.2.1 Current liabilities | KK2: 9.2.1 Non-current liabilities | KL2: 9.3 Net Assets (9.1 - 9.2) | KM2: 9.4 Accumulated depreciation of fixed assets (9.1.2.1) | KN2: 10.1 Debt outstanding | KO2: 11.1 Total Operating Expenses (Total corresponds to 7.1) | KP2: 11.1.1 Security | KQ2: 11.1.2 Airfield Operations & Maintenance (including firefighting & winter services) | KR2: 11.1.3 Terminal, Landside Operations & Maintenance (including commercial operations) | KS2: 11.1.4 Administration | KT2: 11.1.5 Sales & Marketing | KU2: 11.1.6 Other - (please specify in text box any item >5% of total operating expenses) | KV2: 11.1.6 Other - TEXT | KW2: 12.1 Taxes levied on passengers | KX2: 12.2 Taxed levied on airlines | KY2: 13.1 Airport Capital Expenditure (CAPEX) | KZ2: 13.1.1 Purchase of property, plant & equipment | LA2: 13.1.2 Construction expenses | LB2: 13.1.3 Purchase of other goods & services | LC2: 13.1.4 Other capital expenditure items (please specify below) | LD2: 13.1.4 Other capital expenditure items TEXT | LE2: 13.2 Comments (please type in the box below): | LF2: 14.1 Return On Invested Capital (ROIC) (%) | LG2: 14.2 Return on Capital Employed (ROCE) (%)
F3: =IF(ISBLANK(FRANÇAIS!L27), "", FRANÇAIS!L27) | G3: =IF(LEN(F3)=3, "1", "") | H3: =IF(ISBLANK(FRANÇAIS!C27), "", FRANÇAIS!C27) | I3: =IF(ISBLANK(FRANÇAIS!C29), "", FRANÇAIS!C29) | J3: =IF(ISBLANK(FRANÇAIS!C31), "", FRANÇAIS!C31) | K3: =IF(ISBLANK(FRANÇAIS!L29), "", FRANÇAIS!L29) | L3: =IF(ISBLANK(FRANÇAIS!L31), "", FRANÇAIS!L31) | M3: =IF(ISBLANK(FRANÇAIS!F39), "", FRANÇAIS!F39) | N3: =IF(ISBLANK(FRANÇAIS!F41), "", FRANÇAIS!F41) | O3: =IF(ISBLANK(FRANÇAIS!F43), "", FRANÇAIS!F43) | P3: =IF(ISBLANK(FRANÇAIS!F45), "", FRANÇAIS!F45) | Q3: =IF(ISBLANK(FRANÇAIS!O39), "", FRANÇAIS!O39) | R3: =IF(ISBLANK(FRANÇAIS!O41), "", FRANÇAIS!O41) | S3: =IF(ISBLANK(FRANÇAIS!O43), "", FRANÇAIS!O43) | T3: =IF(ISBLANK(FRANÇAIS!O45), "", FRANÇAIS!O45) | U3: =IF(ISBLANK(FRANÇAIS!J52), "", FRANÇAIS!J52) | V3: =IF(ISBLANK(FRANÇAIS!M52), "", FRANÇAIS!M52) | W3: =IF(ISBLANK(FRANÇAIS!J54), "", FRANÇAIS!J54) | X3: =IF(ISBLANK(FRANÇAIS!M54), "", FRANÇAIS!M54) | Y3: =IF(ISBLANK(FRANÇAIS!J55), "", FRANÇAIS!J55) | Z3: =IF(ISBLANK(FRANÇAIS!M55), "", FRANÇAIS!M55) | AA3: =IF(ISBLANK(FRANÇAIS!J57), "", FRANÇAIS!J57) | AB3: =IF(ISBLANK(FRANÇAIS!M57), "", FRANÇAIS!M57) | AC3: =IF(ISBLANK(FRANÇAIS!J59), "", FRANÇAIS!J59) | AD3: =IF(ISBLANK(FRANÇAIS!M59), "", FRANÇAIS!M59) | AE3: =IF(ISBLANK(FRANÇAIS!J60), "", FRANÇAIS!J60) | AF3: =IF(ISBLANK(FRANÇAIS!M60), "", FRANÇAIS!M60) | AG3: =IF(ISBLANK(FRANÇAIS!J62), "", FRANÇAIS!J62) | AH3: =IF(ISBLANK(FRANÇAIS!M62), "", FRANÇAIS!M62) | AI3: =IF(ISBLANK(FRANÇAIS!J64), "", FRANÇAIS!J64) | AJ3: =IF(ISBLANK(FRANÇAIS!M64), "", FRANÇAIS!M64) | AK3: =IF(ISBLANK(FRANÇAIS!J67), "", FRANÇAIS!J67) | AL3: =IF(ISBLANK(FRANÇAIS!M67), "", FRANÇAIS!M67) | AM3: =IF(ISBLANK(FRANÇAIS!J68), "", FRANÇAIS!J68) | AN3: =IF(ISBLANK(FRANÇAIS!M68), "", FRANÇAIS!M68) | AO3: =IF(ISBLANK(FRANÇAIS!J70), "", FRANÇAIS!J70) | AP3: =IF(ISBLANK(FRANÇAIS!M70), "", FRANÇAIS!M70) | AQ3: =IF(ISBLANK(FRANÇAIS!J77), "", FRANÇAIS!J77) | AR3: =IF(ISBLANK(FRANÇAIS!J78), "", FRANÇAIS!J78) | AS3: =IF(ISBLANK(FRANÇAIS!J79), "", FRANÇAIS!J79) | AT3: =IF(ISBLANK(FRANÇAIS!J80), "", FRANÇAIS!J80) | AU3: =IF(ISBLANK(FRANÇAIS!J81), "", FRANÇAIS!J81) | AV3: =IF(ISBLANK(FRANÇAIS!J82), "", FRANÇAIS!J82) | AW3: =IF(ISBLANK(FRANÇAIS!J83), "", FRANÇAIS!J83) | AX3: =IF(ISBLANK(FRANÇAIS!J84), "", FRANÇAIS!J84) | AY3: =IF(ISBLANK(FRANÇAIS!J85), "", FRANÇAIS!J85) | AZ3: =IF(ISBLANK(FRANÇAIS!J87), "", FRANÇAIS!J87) | BA3: =IF(ISBLANK(FRANÇAIS!J88), "", FRANÇAIS!J88) | BB3: =IF(ISBLANK(FRANÇAIS!M94), "", FRANÇAIS!M94) | BC3: =IF(ISBLANK(FRANÇAIS!M96), "", FRANÇAIS!M96) | BD3: =IF(ISBLANK(FRANÇAIS!M98), "", FRANÇAIS!M98) | BE3: =IF(ISBLANK(FRANÇAIS!M100), "", FRANÇAIS!M100) | BF3: =IF(ISBLANK(FRANÇAIS!M102), "", FRANÇAIS!M102) | BG3: =IF(ISBLANK(FRANÇAIS!M104), "", FRANÇAIS!M104) | BH3: =IF(ISBLANK(FRANÇAIS!K115), "", FRANÇAIS!K115) | BI3: =IF(ISBLANK(FRANÇAIS!O115), "", FRANÇAIS!O115) | BJ3: FALSE | BK3: FALSE | BL3: FALSE | BM3: FALSE | BN3: FALSE | BO3: FALSE | BP3: FALSE | BQ3: FALSE | BR3: FALSE | BS3: FALSE | BT3: FALSE | BU3: FALSE | BV3: FALSE | BW3: FALSE | BX3: FALSE | BY3: FALSE | BZ3: FALSE | CA3: FALSE | CB3: FALSE | CC3: FALSE | CD3: FALSE | CE3: FALSE | CF3: FALSE | CG3: FALSE | CH3: FALSE | CI3: FALSE | CJ3: FALSE | CK3: FALSE | CL3: FALSE | CM3: FALSE | CN3: =IF(ISBLANK(FRANÇAIS!K119), "", FRANÇAIS!K119) | CO3: =IF(ISBLANK(FRANÇAIS!K120), "", FRANÇAIS!K120) | CP3: =IF(ISBLANK(FRANÇAIS!K122), "", FRANÇAIS!K122) | CQ3: =IF(ISBLANK(FRANÇAIS!K123), "", FRANÇAIS!K123) | CR3: =IF(ISBLANK(FRANÇAIS!K124), "", FRANÇAIS!K124) | CS3: =IF(ISBLANK(FRANÇAIS!K125), "", FRANÇAIS!K125) | CT3: =IF(ISBLANK(FRANÇAIS!K126), "", FRANÇAIS!K126) | CU3: =IF(ISBLANK(FRANÇAIS!K127), "", FRANÇAIS!K127) | CV3: =IF(ISBLANK(FRANÇAIS!K128), "", FRANÇAIS!K128) | CW3: =IF(ISBLANK(FRANÇAIS!K129), "", FRANÇAIS!K129) | CX3: =IF(ISBLANK(FRANÇAIS!K130), "", FRANÇAIS!K130) | CY3: =IF(ISBLANK(FRANÇAIS!K132), "", FRANÇAIS!K132) | CZ3: =IF(ISBLANK(FRANÇAIS!K133), "", FRANÇAIS!K133) | DA3: =IF(ISBLANK(FRANÇAIS!K134), "", FRANÇAIS!K134) | DB3: =IF(ISBLANK(FRANÇAIS!K135), "", FRANÇAIS!K135) | DC3: =IF(ISBLANK(FRANÇAIS!O119), "", FRANÇAIS!O119) | DD3: =IF(ISBLANK(FRANÇAIS!O120), "", FRANÇAIS!O120) | DE3: =IF(ISBLANK(FRANÇAIS!O122), "", FRANÇAIS!O122) | DF3: =IF(ISBLANK(FRANÇAIS!O123), "", FRANÇAIS!O123) | DG3: =IF(ISBLANK(FRANÇAIS!O124), "", FRANÇAIS!O124) | DH3: =IF(ISBLANK(FRANÇAIS!O125), "", FRANÇAIS!O125) | DI3: =IF(ISBLANK(FRANÇAIS!O126), "", FRANÇAIS!O126) | DJ3: =IF(ISBLANK(FRANÇAIS!O127), "", FRANÇAIS!O127) | DK3: =IF(ISBLANK(FRANÇAIS!O128), "", FRANÇAIS!O128) | DL3: =IF(ISBLANK(FRANÇAIS!O129), "", FRANÇAIS!O129) | DM3: =IF(ISBLANK(FRANÇAIS!O130), "", FRANÇAIS!O130) | DN3: =IF(ISBLANK(FRANÇAIS!O132), "", FRANÇAIS!O132) | DO3: =IF(ISBLANK(FRANÇAIS!O133), "", FRANÇAIS!O133) | DP3: =IF(ISBLANK(FRANÇAIS!O134), "", FRANÇAIS!O134) | DQ3: =IF(ISBLANK(FRANÇAIS!O135), "", FRANÇAIS!O135) | DR3: =IF(ISBLANK(FRANÇAIS!K138), "", FRANÇAIS!K138) | DS3: =IF(ISBLANK(FRANÇAIS!K146), "", FRANÇAIS!K146) -> 0 | DT3: =IF(ISBLANK(FRANÇAIS!K148), "", FRANÇAIS!K148) -> 0 | DU3: =IF(ISBLANK(FRANÇAIS!K150), "", FRANÇAIS!K150) | DV3: =IF(ISBLANK(FRANÇAIS!K151), "", FRANÇAIS!K151) | DW3: =IF(ISBLANK(FRANÇAIS!K152), "", FRANÇAIS!K152) | DX3: =IF(ISBLANK(FRANÇAIS!K153), "", FRANÇAIS!K153) | DY3: =IF(ISBLANK(FRANÇAIS!K154), "", FRANÇAIS!K154) | DZ3: =IF(ISBLANK(FRANÇAIS!K155), "", FRANÇAIS!K155) | EA3: =IF(ISBLANK(FRANÇAIS!K156), "", FRANÇAIS!K156) | EB3: =IF(ISBLANK(FRANÇAIS!K157), "", FRANÇAIS!K157) | EC3: =IF(ISBLANK(FRANÇAIS!K158), "", FRANÇAIS!K158) | ED3: =IF(ISBLANK(FRANÇAIS!K159), "", FRANÇAIS!K159) | EE3: =IF(ISBLANK(FRANÇAIS!K160), "", FRANÇAIS!K160) | EF3: =IF(ISBLANK(FRANÇAIS!K161), "", FRANÇAIS!K161) | EG3: =IF(ISBLANK(FRANÇAIS!K162), "", FRANÇAIS!K162) | EH3: =IF(ISBLANK(FRANÇAIS!K163), "", FRANÇAIS!K163) | EI3: =IF(ISBLANK(FRANÇAIS!K164), "", FRANÇAIS!K164) | EJ3: =IF(ISBLANK(FRANÇAIS!K165), "", FRANÇAIS!K165) | EK3: =IF(ISBLANK(FRANÇAIS!K167), "", FRANÇAIS!K167) | EL3: =IF(ISBLANK(FRANÇAIS!D167), "", FRANÇAIS!D167) | EM3: =IF(ISBLANK(FRANÇAIS!K169), "", FRANÇAIS!K169) -> 0 | EN3: =IF(ISBLANK(FRANÇAIS!K171), "", FRANÇAIS!K171) | EO3: =IF(ISBLANK(FRANÇAIS!K172), "", FRANÇAIS!K172) | EP3: =IF(ISBLANK(FRANÇAIS!K173), "", FRANÇAIS!K173) | EQ3: =IF(ISBLANK(FRANÇAIS!K174), "", FRANÇAIS!K174) | ER3: =IF(ISBLANK(FRANÇAIS!K175), "", FRANÇAIS!K175) | ES3: =IF(ISBLANK(FRANÇAIS!K176), "", FRANÇAIS!K176) | ET3: =IF(ISBLANK(FRANÇAIS!K177), "", FRANÇAIS!K177) | EU3: =IF(ISBLANK(FRANÇAIS!K179), "", FRANÇAIS!K179) | EV3: =IF(ISBLANK(FRANÇAIS!D179), "", FRANÇAIS!D179) | EW3: =IF(ISBLANK(FRANÇAIS!K181), "", FRANÇAIS!K181) -> 0 | EX3: =IF(ISBLANK(FRANÇAIS!K183), "", FRANÇAIS!K183) | EY3: =IF(ISBLANK(FRANÇAIS!K184), "", FRANÇAIS!K184) | EZ3: =IF(ISBLANK(FRANÇAIS!K185), "", FRANÇAIS!K185) | FA3: =IF(ISBLANK(FRANÇAIS!K187), "", FRANÇAIS!K187) | FB3: =IF(ISBLANK(FRANÇAIS!D187), "", FRANÇAIS!D187) | FC3: =IF(ISBLANK(FRANÇAIS!D191), "", FRANÇAIS!D191) | FD3: =IF(ISBLANK(FRANÇAIS!K199), "", FRANÇAIS!K199) -> 0 | FE3: =IF(ISBLANK(FRANÇAIS!K201), "", FRANÇAIS!K201) | FF3: =IF(ISBLANK(FRANÇAIS!K202), "", FRANÇAIS!K202) | FG3: =IF(ISBLANK(FRANÇAIS!K203), "", FRANÇAIS!K203) | FH3: =IF(ISBLANK(FRANÇAIS!K204), "", FRANÇAIS!K204) | FI3: =IF(ISBLANK(FRANÇAIS!K205), "", FRANÇAIS!K205) | FJ3: =IF(ISBLANK(FRANÇAIS!K206), "", FRANÇAIS!K206) | FK3: =IF(ISBLANK(FRANÇAIS!K207), "", FRANÇAIS!K207) | FL3: =IF(ISBLANK(FRANÇAIS!K208), "", FRANÇAIS!K208) | FM3: =IF(ISBLANK(FRANÇAIS!K210), "", FRANÇAIS!K210) | FN3: =IF(ISBLANK(FRANÇAIS!D210), "", FRANÇAIS!D210) | FO3: =IF(ISBLANK(FRANÇAIS!D214), "", FRANÇAIS!D214) | FP3: =IF(ISBLANK(FRANÇAIS!K222), "", FRANÇAIS!K222) -> 0 | FQ3: =IF(ISBLANK(FRANÇAIS!K224), "", FRANÇAIS!K224) -> 0 | FR3: =IF(ISBLANK(FRANÇAIS!K225), "", FRANÇAIS!K225) -> 0 | FS3: =IF(ISBLANK(FRANÇAIS!K226), "", FRANÇAIS!K226) -> 0 | FT3: =IF(ISBLANK(FRANÇAIS!K228), "", FRANÇAIS!K228) -> 0 | FU3: =IF(ISBLANK(FRANÇAIS!K230), "", FRANÇAIS!K230) -> 0 | FV3: =IF(ISBLANK(FRANÇAIS!K233), "", FRANÇAIS!K233) -> 0 | FW3: =IF(ISBLANK(FRANÇAIS!K235), "", FRANÇAIS!K235) | FX3: =IF(ISBLANK(FRANÇAIS!K236), "", FRANÇAIS!K236) | FY3: =IF(ISBLANK(FRANÇAIS!K238), "", FRANÇAIS!K238) | FZ3: =IF(ISBLANK(FRANÇAIS!D238), "", FRANÇAIS!D238) | GA3: =IF(ISBLANK(FRANÇAIS!K240), "", FRANÇAIS!K240) | GB3: =IF(ISBLANK(FRANÇAIS!K242), "", FRANÇAIS!K242) -> 0 | GC3: =IF(ISBLANK(FRANÇAIS!D247), "", FRANÇAIS!D247) | GD3: =IF(ISBLANK(FRANÇAIS!K255), "", FRANÇAIS!K255) -> 0 | GE3: =IF(ISBLANK(FRANÇAIS!K257), "", FRANÇAIS!K257) -> 0 | GF3: =IF(ISBLANK(FRANÇAIS!K258), "", FRANÇAIS!K258) | GG3: =IF(ISBLANK(FRANÇAIS!K259), "", FRANÇAIS!K259) | GH3: =IF(ISBLANK(FRANÇAIS!K261), "", FRANÇAIS!K261) -> 0 | GI3: =IF(ISBLANK(FRANÇAIS!K262), "", FRANÇAIS!K262) | GJ3: =IF(ISBLANK(FRANÇAIS!K264),"", FRANÇAIS!K264) | GK3: =IF(ISBLANK(FRANÇAIS!K266), "", FRANÇAIS!K266) -> 0 | GL3: =IF(ISBLANK(FRANÇAIS!K267), "", FRANÇAIS!K267) | GM3: =IF(ISBLANK(FRANÇAIS!K268), "", FRANÇAIS!K268) | GN3: =IF(ISBLANK(FRANÇAIS!K270), "", FRANÇAIS!K270) -> 0 | GO3: =IF(ISBLANK(FRANÇAIS!K263), "", FRANÇAIS!K263) | GP3: =IF(ISBLANK(FRANÇAIS!K276), "", FRANÇAIS!K276) | GQ3: =IF(ISBLANK(FRANÇAIS!K279), "", FRANÇAIS!K279) | GR3: =IF(ISBLANK(FRANÇAIS!M279), "", FRANÇAIS!M279) | GS3: =IF(ISBLANK(FRANÇAIS!O279), "", FRANÇAIS!O279) | GT3: =IF(ISBLANK(FRANÇAIS!Q279), "", FRANÇAIS!Q279) | GU3: =IF(ISBLANK(FRANÇAIS!K285), "", FRANÇAIS!K285) -> 0 | GV3: =IF(ISBLANK(FRANÇAIS!K287),"",FRANÇAIS!K287) | GW3: =IF(ISBLANK(FRANÇAIS!K288),"",FRANÇAIS!K288) | GX3: =IF(ISBLANK(FRANÇAIS!K289),"",FRANÇAIS!K289) | GY3: =IF(ISBLANK(FRANÇAIS!K290),"",FRANÇAIS!K290) | GZ3: =IF(ISBLANK(FRANÇAIS!K291),"",FRANÇAIS!K291) | HA3: =IF(ISBLANK(FRANÇAIS!K293),"",FRANÇAIS!K293) | HB3: =IF(ISBLANK(FRANÇAIS!D293), "", FRANÇAIS!D293) | HC3: =IF(ISBLANK(FRANÇAIS!K299), "", FRANÇAIS!K299) | HD3: =IF(ISBLANK(FRANÇAIS!K300), "", FRANÇAIS!K300) | HE3: =IF(ISBLANK(FRANÇAIS!K306), "", FRANÇAIS!K306) -> 0 | HF3: =IF(ISBLANK(FRANÇAIS!K308), "", FRANÇAIS!K308) | HG3: =IF(ISBLANK(FRANÇAIS!K309), "", FRANÇAIS!K309) | HH3: =IF(ISBLANK(FRANÇAIS!K310), "", FRANÇAIS!K31) | HI3: =IF(ISBLANK(FRANÇAIS!K312), "", FRANÇAIS!K312) | HJ3: =IF(ISBLANK(FRANÇAIS!D312), "", FRANÇAIS!D312) | HK3: =IF(ISBLANK(FRANÇAIS!D316), "", FRANÇAIS!D316) | HL3: =IF(ISBLANK(FRANÇAIS!K324), "", FRANÇAIS!K324) | HM3: =IF(ISBLANK(FRANÇAIS!K325), "", FRANÇAIS!K325) | HQ3: =IF(ISBLANK(FRANÇAIS!O146), "", FRANÇAIS!O146) -> 0 | HR3: =IF(ISBLANK(FRANÇAIS!O148), "", FRANÇAIS!O148) -> 0 | HS3: =IF(ISBLANK(FRANÇAIS!O150), "", FRANÇAIS!O150) | HT3: =IF(ISBLANK(FRANÇAIS!O151), "", FRANÇAIS!O151) | HU3: =IF(ISBLANK(FRANÇAIS!O152), "", FRANÇAIS!O152) | HV3: =IF(ISBLANK(FRANÇAIS!O153), "", FRANÇAIS!O153) | HW3: =IF(ISBLANK(FRANÇAIS!O154), "", FRANÇAIS!O154) | HX3: =IF(ISBLANK(FRANÇAIS!O155), "", FRANÇAIS!O155) | HY3: =IF(ISBLANK(FRANÇAIS!O156), "", FRANÇAIS!O156) | HZ3: =IF(ISBLANK(FRANÇAIS!O157), "", FRANÇAIS!O157) | IA3: =IF(ISBLANK(FRANÇAIS!O158), "", FRANÇAIS!O158) | IB3: =IF(ISBLANK(FRANÇAIS!O159), "", FRANÇAIS!O159) | IC3: =IF(ISBLANK(FRANÇAIS!O160), "", FRANÇAIS!O160) | ID3: =IF(ISBLANK(FRANÇAIS!O161), "", FRANÇAIS!O161) | IE3: =IF(ISBLANK(FRANÇAIS!O162), "", FRANÇAIS!O162) | IF3: =IF(ISBLANK(FRANÇAIS!O163), "", FRANÇAIS!O163) | IG3: =IF(ISBLANK(FRANÇAIS!O164), "", FRANÇAIS!O164) | IH3: =IF(ISBLANK(FRANÇAIS!O165), "", FRANÇAIS!O165) | II3: =IF(ISBLANK(FRANÇAIS!O167), "", FRANÇAIS!O167) | IJ3: =IF(ISBLANK(FRANÇAIS!D167), "", FRANÇAIS!D167) | IK3: =IF(ISBLANK(FRANÇAIS!O169), "", FRANÇAIS!O169) -> 0 | IL3: =IF(ISBLANK(FRANÇAIS!O171), "", FRANÇAIS!O171) | IM3: =IF(ISBLANK(FRANÇAIS!O172), "", FRANÇAIS!O172) | IN3: =IF(ISBLANK(FRANÇAIS!O173), "", FRANÇAIS!O173) | IO3: =IF(ISBLANK(FRANÇAIS!O174), "", FRANÇAIS!O174) | IP3: =IF(ISBLANK(FRANÇAIS!O175), "", FRANÇAIS!O175) | IQ3: =IF(ISBLANK(FRANÇAIS!O176), "", FRANÇAIS!O176) | IR3: =IF(ISBLANK(FRANÇAIS!O177), "", FRANÇAIS!O177) | IS3: =IF(ISBLANK(FRANÇAIS!O179), "", FRANÇAIS!O179) | IT3: =IF(ISBLANK(FRANÇAIS!D179), "", FRANÇAIS!D179) | IU3: =IF(ISBLANK(FRANÇAIS!O181), "", FRANÇAIS!O181) -> 0 | IV3: =IF(ISBLANK(FRANÇAIS!O183), "", FRANÇAIS!O183) | IW3: =IF(ISBLANK(FRANÇAIS!O184), "", FRANÇAIS!O184) | IX3: =IF(ISBLANK(FRANÇAIS!O185), "", FRANÇAIS!O185) | IY3: =IF(ISBLANK(FRANÇAIS!O187), "", FRANÇAIS!O187) | IZ3: =IF(ISBLANK(FRANÇAIS!DB187), "", FRANÇAIS!DB187) | JA3: =IF(ISBLANK(FRANÇAIS!D191), "", FRANÇAIS!D191) | JB3: =IF(ISBLANK(FRANÇAIS!O199), "", FRANÇAIS!O199) -> 0 | JC3: =IF(ISBLANK(FRANÇAIS!O201), "", FRANÇAIS!O201) | JD3: =IF(ISBLANK(FRANÇAIS!O202), "", FRANÇAIS!O202) | JE3: =IF(ISBLANK(FRANÇAIS!O203), "", FRANÇAIS!O203) | JF3: =IF(ISBLANK(FRANÇAIS!O204), "", FRANÇAIS!O204) | JG3: =IF(ISBLANK(FRANÇAIS!O205), "", FRANÇAIS!O205) | JH3: =IF(ISBLANK(FRANÇAIS!O206), "", FRANÇAIS!O206) | JI3: =IF(ISBLANK(FRANÇAIS!O207), "", FRANÇAIS!O207) | JJ3: =IF(ISBLANK(FRANÇAIS!O208), "", FRANÇAIS!O208) | JK3: =IF(ISBLANK(FRANÇAIS!O210), "", FRANÇAIS!O210) | JL3: =IF(ISBLANK(FRANÇAIS!D210), "", FRANÇAIS!D210) | JM3: =IF(ISBLANK(FRANÇAIS!D214), "", FRANÇAIS!D214) | JN3: =IF(ISBLANK(FRANÇAIS!O222), "", FRANÇAIS!O222) -> 0 | JO3: =IF(ISBLANK(FRANÇAIS!O224), "", FRANÇAIS!O224) -> 0 | JP3: =IF(ISBLANK(FRANÇAIS!O225), "", FRANÇAIS!O225) -> 0 | JQ3: =IF(ISBLANK(FRANÇAIS!O226), "", FRANÇAIS!O226) -> 0 | JR3: =IF(ISBLANK(FRANÇAIS!O228), "", FRANÇAIS!O228) -> 0 | JS3: =IF(ISBLANK(FRANÇAIS!O230), "", FRANÇAIS!O230) -> 0 | JT3: =IF(ISBLANK(FRANÇAIS!O233), "", FRANÇAIS!O233) -> 0 | JU3: =IF(ISBLANK(FRANÇAIS!O235), "", FRANÇAIS!O235) | JV3: =IF(ISBLANK(FRANÇAIS!O236), "", FRANÇAIS!O236) | JW3: =IF(ISBLANK(FRANÇAIS!O238), "", FRANÇAIS!O238) | JX3: =IF(ISBLANK(FRANÇAIS!D238), "", FRANÇAIS!D238) | JY3: =IF(ISBLANK(FRANÇAIS!O240), "", FRANÇAIS!O240) | JZ3: =IF(ISBLANK(FRANÇAIS!O242), "", FRANÇAIS!O242) -> 0 | KA3: =IF(ISBLANK(FRANÇAIS!D247), "", FRANÇAIS!D247) | KB3: =IF(ISBLANK(FRANÇAIS!O255), "", FRANÇAIS!O255) -> 0 | KC3: =IF(ISBLANK(FRANÇAIS!O257), "", FRANÇAIS!O257) -> 0 | KD3: =IF(ISBLANK(FRANÇAIS!O258), "", FRANÇAIS!O258) | KE3: =IF(ISBLANK(FRANÇAIS!O259), "", FRANÇAIS!O259) | KF3: =IF(ISBLANK(FRANÇAIS!O261), "", FRANÇAIS!O261) -> 0 | KG3: =IF(ISBLANK(FRANÇAIS!O262), "", FRANÇAIS!O262) | KH3: =IF(ISBLANK(FRANÇAIS!O264),"", FRANÇAIS!O264) | KI3: =IF(ISBLANK(FRANÇAIS!O266), "", FRANÇAIS!O266) -> 0 | KJ3: =IF(ISBLANK(FRANÇAIS!O267), "", FRANÇAIS!O267) | KK3: =IF(ISBLANK(FRANÇAIS!O268), "", FRANÇAIS!O268) | KL3: =IF(ISBLANK(FRANÇAIS!O270), "", FRANÇAIS!O270) -> 0 | KM3: =IF(ISBLANK(FRANÇAIS!O263), "", FRANÇAIS!O263) | KN3: =IF(ISBLANK(FRANÇAIS!O276), "", FRANÇAIS!O276) | KO3: =IF(ISBLANK(FRANÇAIS!O285), "", FRANÇAIS!O285) -> 0 | KP3: =IF(ISBLANK(FRANÇAIS!O287),"",FRANÇAIS!O287) | KQ3: =IF(ISBLANK(FRANÇAIS!O288),"",FRANÇAIS!O288) | KR3: =IF(ISBLANK(FRANÇAIS!O289),"",FRANÇAIS!O289) | KS3: =IF(ISBLANK(FRANÇAIS!O290),"",FRANÇAIS!O290) | KT3: =IF(ISBLANK(FRANÇAIS!O291),"",FRANÇAIS!O291) | KU3: =IF(ISBLANK(FRANÇAIS!O293),"",FRANÇAIS!O293) | KV3: =IF(ISBLANK(FRANÇAIS!D293), "", FRANÇAIS!D293) | KW3: =IF(ISBLANK(FRANÇAIS!O299), "", FRANÇAIS!O299) | KX3: =IF(ISBLANK(FRANÇAIS!O300), "", FRANÇAIS!O300) | KY3: =IF(ISBLANK(FRANÇAIS!O306), "", FRANÇAIS!O306) -> 0 | KZ3: =IF(ISBLANK(FRANÇAIS!O308), "", FRANÇAIS!O308) | LA3: =IF(ISBLANK(FRANÇAIS!O309), "", FRANÇAIS!O309) | LB3: =IF(ISBLANK(FRANÇAIS!O310), "", FRANÇAIS!O31) | LC3: =IF(ISBLANK(FRANÇAIS!O312), "", FRANÇAIS!O312) | LD3: =IF(ISBLANK(FRANÇAIS!D312), "", FRANÇAIS!D312) | LE3: =IF(ISBLANK(FRANÇAIS!D316), "", FRANÇAIS!D316) | LF3: =IF(ISBLANK(FRANÇAIS!O324), "", FRANÇAIS!O324) | LG3: =IF(ISBLANK(FRANÇAIS!DE325), "", FRANÇAIS!DE325)

Sheet for internal use (SPANISH)
A1: 1 | B1: 1 | C1: 1 | D1: 1 | E1: 1 | F1: 1 | G1: 1 | H1: 1 | I1: 1 | J1: 1 | K1: 1 | L1: 1 | M1: 2 | N1: 2 | O1: 2 | P1: 2 | Q1: 2 | R1: 2 | S1: 2 | T1: 2 | U1: 3.1 | W1: 3.1 | Y1: 3.1 | AA1: 3.1 | AC1: 3.1 | AE1: 3.1 | AG1: 3.1 | AI1: 3.1 | AK1: 3.1 | AM1: 3.1 | AO1: 3.1 | AQ1: 3.2 | AR1: 3.2 | AS1: 3.2 | AT1: 3.2 | AU1: 3.2 | AV1: 3.2 | AW1: 3.2 | AX1: 3.2 | AY1: 3.2 | AZ1: 3.2 | BA1: 3.2 | BB1: 4 | BC1: 4 | BD1: 4 | BE1: 4 | BF1: 4 | BG1: 4 | BH1: 5 | BI1: 5 | BJ1: 5 | BK1: 5 | BL1: 5 | BM1: 5 | BN1: 5 | BO1: 5 | BP1: 5 | BQ1: 5 | BR1: 5 | BS1: 5 | BT1: 5 | BU1: 5 | BV1: 5 | BW1: 5 | BY1: 5 | BZ1: 5 | CA1: 5 | CB1: 5 | CC1: 5 | CD1: 5 | CE1: 5 | CF1: 5 | CG1: 5 | CH1: 5 | CI1: 5 | CJ1: 5 | CK1: 5 | CL1: 5 | CM1: 5 | CN1: 5 | CO1: 5 | CP1: 5 | CQ1: 5 | CR1: 5 | CS1: 5 | CT1: 5 | CU1: 5 | CV1: 5 | CW1: 5 | CX1: 5 | CY1: 5 | CZ1: 5 | DA1: 5 | DB1: 5 | DC1: 5 | DD1: 5 | DE1: 5 | DF1: 5 | DG1: 5 | DH1: 5 | DI1: 5 | DJ1: 5 | DK1: 5 | DL1: 5 | DM1: 5 | DN1: 5 | DO1: 5 | DP1: 5 | DQ1: 5 | DR1: 5 | DS1: 6 | DT1: 6 | DU1: 6 | DV1: 6 | DW1: 6 | DX1: 6 | DY1: 6 | DZ1: 6 | EA1: 6 | EB1: 6 | EC1: 6 | ED1: 6 | EE1: 6 | EF1: 6 | EG1: 6 | EH1: 6 | EI1: 6 | EJ1: 6 | EK1: 6 | EL1: 6 | EM1: 6 | EN1: 6 | EO1: 6 | EP1: 6 | EQ1: 6 | ER1: 6 | ES1: 6 | ET1: 6 | EU1: 6 | EV1: 6 | EW1: 6 | EX1: 6 | EY1: 6 | EZ1: 6 | FA1: 6 | FB1: 6 | FC1: 6 | FD1: 7 | FE1: 7 | FF1: 7 | FG1: 7 | FH1: 7 | FI1: 7 | FJ1: 7 | FK1: 7 | FL1: 7 | FM1: 7 | FN1: 7 | FO1: 7 | FP1: 8 | FQ1: 8 | FR1: 8 | FS1: 8 | FT1: 8 | FU1: 8 | FV1: 8 | FW1: 8 | FX1: 8 | FY1: 8 | FZ1: 8 | GA1: 8 | GB1: 8 | GC1: 8 | GD1: 9 | GE1: 9 | GF1: 9 | GG1: 9 | GH1: 9 | GI1: 9 | GJ1: 9 | GK1: 9 | GL1: 9 | GM1: 9 | GN1: 9 | GO1: 9 | GP1: 10 | GQ1: 10 | GR1: 10 | GS1: 10 | GT1: 10 | GU1: 11 | GV1: 11 | GW1: 11 | GX1: 11 | GY1: 11 | GZ1: 11 | HA1: 11 | HB1: 11 | HC1: 12 | HD1: 12 | HE1: 13 | HF1: 13 | HG1: 13 | HH1: 13 | HI1: 13 | HJ1: 13 | HK1: 13 | HL1: 14 | HM1: 14 | HQ1: 6 (2011) | HR1: 6 (2011) | HS1: 6 (2011) | HT1: 6 (2011) | HU1: 6 (2011) | HV1: 6 (2011) | HW1: 6 (2011) | HX1: 6 (2011) | HY1: 6 (2011) | HZ1: 6 (2011) | IA1: 6 (2011) | IB1: 6 (2011) | IC1: 6 (2011) | ID1: 6 (2011) | IE1: 6 (2011) | IF1: 6 (2011) | IG1: 6 (2011) | IH1: 6 (2011) | II1: 6 (2011) | IJ1: 6 (2011) | IK1: 6 (2011) | IL1: 6 (2011) | IM1: 6 (2011) | IN1: 6 (2011) | IO1: 6 (2011) | IP1: 6 (2011) | IQ1: 6 (2011) | IR1: 6 (2011) | IS1: 6 (2011) | IT1: 6 (2011) | IU1: 6 (2011) | IV1: 6 (2011) | IW1: 6 (2011) | IX1: 6 (2011) | IY1: 6 (2011) | IZ1: 6 (2011) | JA1: 6 (2011) | JB1: 7 (2011) | JC1: 7 (2011) | JD1: 7 (2011) | JE1: 7 (2011) | JF1: 7 (2011) | JG1: 7 (2011) | JH1: 7 (2011) | JI1: 7 (2011) | JJ1: 7 (2011) | JK1: 7 (2011) | JL1: 7 (2011) | JM1: 7 (2011) | JN1: 8 (2011) | JO1: 8 (2011) | JP1: 8 (2011) | JQ1: 8 (2011) | JR1: 8 (2011) | JS1: 8 (2011) | JT1: 8 (2011) | JU1: 8 (2011) | JV1: 8 (2011) | JW1: 8 (2011) | JX1: 8 (2011) | JY1: 8 (2011) | JZ1: 8 (2011) | KA1: 8 (2011) | KB1: 9 (2011) | KC1: 9 (2011) | KD1: 9 (2011) | KE1: 9 (2011) | KF1: 9 (2011) | KG1: 9 (2011) | KH1: 9 (2011) | KI1: 9 (2011) | KJ1: 9 (2011) | KK1: 9 (2011) | KL1: 9 (2011) | KM1: 9 (2011) | KN1: 10 (2011) | KO1: 11 (2011) | KP1: 11 (2011) | KQ1: 11 (2011) | KR1: 11 (2011) | KS1: 11 (2011) | KT1: 11 (2011) | KU1: 11 (2011) | KV1: 11 (2011) | KW1: 12 (2011) | KX1: 12 (2011) | KY1: 13 (2011) | KZ1: 13 (2011) | LA1: 13 (2011) | LB1: 13 (2011) | LC1: 13 (2011) | LD1: 13 (2011) | LE1: 13 (2011) | LF1: 14 (2011) | LG1: 14 (2011)
A2: Region | B2: City | C2: Country | D2: Operator | E2: Size Category | F2: Code | G2: Count | H2: Airport Name | I2: Contact person | J2: Title | K2: Tel. Number | L2: Email Address | M2: 2.1 Passengers: | N2: 2.2 Cargo (metric tons): | O2: 2.3 Movements | P2: 2.4 WLU: | Q2: 2.5 Financial Year (please select): | R2: 2.6 Financial figures submitted in: | S2: 2.7 Reporting Currency (please select): | T2: 2.8 Suggested exchange rate: | U2: 3.1.1 Total Airport Site Area | W2: 3.1.1.1 Airside Area | Y2: 3.1.1.2 Landside area | AA2: 3.1.2 Passenger Terminal(s) Building(s) Area | AC2: 3.1.2.1 Airside Area | AE2: 3.1.2.2 Landside area | AG2: 3.1.3 Cargo Terminal(s) Building(s) Area | AI2: 3.1.4 Commercial Activity Area | AK2: 3.1.4.1 Food & beverage | AM2: 3.1.4.2 Retail Activity Area | AO2: 3.1.4.2.1 Duty Free Area | AQ2: 3.2.1 Runways (paved landing strips) | AR2: 3.2.2 Contact gates with air bridge (jet bridge) | AS2: 3.2.3 Remote stands (B737-800 or equivalent) | AT2: 3.2.4 Passenger terminals | AU2: 3.2.5 Cargo terminals | AV2: 3.2.6 Passenger check-in desks/counters | AW2: 3.2.7 Self service kiosks operated by airport | AX2: 3.2.8 Individual car parking spaces | AY2: 3.2.9 Retail stores / shops / boutiques | AZ2: 3.2.9.1 Duty-Free shops | BA2: 3.2.10 Restaurants / cafés and other F&B outlets | BB2: 4.1 Pricing regulation | BC2: 4.2 Economic Oversigght | BD2: 4.3 Ownership Structure | BE2: 4.4 Private participation | BF2: 4.5 WACC | BG2: 4.6 Incentive scheme | BH2: 5.1 Total personnel employed by airport operator | Headcount | BI2: 5.1 Total personnel employed by airport operator | FTE | BJ2: 5.1.1 Management | Insourced | BK2: 5.1.2 Ground handling services: | Insourced | BL2: 5.1.2.1 Passenger handling services | Insourced | BM2: 5.1.2.2 Ramp handling services | Insourced | BN2: 5.1.2.3 Cargo handling services | Insourced | BO2: 5.1.3 Rescue and fire service | Insourced | BP2: 5.1.4 Car parking services | Insourced | BQ2: 5.1.5 Cleaning services | Insourced | BR2: 5.1.6 Maintenance services | Insourced | BS2: 5.1.7 Air traffic control services | Insourced | BT2: 5.1.8 Passenger security services | Insourced | BU2: 5.1.8.1 Other security (e.g. perimeter and cargo security) | Insourced | BV2: 5.1.10 Concession services (shops, F&B, etc.) | Insourced | BW2: 5.1.11 Runway, taxiway, apron operations |Insourced | BX2: 5.1.12 Other |Insourced | BY2: 5.1.1 Management | Outsourced | BZ2: 5.1.2 Ground handling services: | Outsourced | CA2: 5.1.2.1 Passenger handling services | Outsourced | CB2: 5.1.2.2 Ramp handling services | Outsourced | CC2: 5.1.2.3 Cargo handling services | Outsourced | CD2: 5.1.3 Rescue and fire service | Outsourced | CE2: 5.1.4 Car parking services | Outsourced | CF2: 5.1.5 Cleaning services | Outsourced | CG2: 5.1.6 Maintenance services | Outsourced | CH2: 5.1.7 Air traffic control services | Outsourced | CI2: 5.1.8 Passenger security services | Outsourced | CJ2: 5.1.8.1 Other security (e.g. perimeter and cargo security) | Outsourced | CK2: 5.1.10 Concession services (shops, F&B, etc.) | Outsourced | CL2: 5.1.11 Runway, taxiway, apron operations | Outsourced | CM2: 5.1.12 Other | Outsorced | CN2: 5.1.1 Management | Headcount | CO2: 5.1.2 Ground handling services: | Headcount | CP2: 5.1.2.1 Passenger handling services | Headcount | CQ2: 5.1.2.2 Ramp handling services | Headcount | CR2: 5.1.2.3 Cargo handling services | Headcount | CS2: 5.1.3 Rescue and fire service | Headcount | CT2: 5.1.4 Car parking services | Headcount | CU2: 5.1.5 Cleaning services | Headcount | CV2: 5.1.6 Maintenance services | Headcount | CW2: 5.1.7 Air traffic control services | Headcount | CX2: 5.1.8 Passenger security services | Headcount | CY2: 5.1.8.1 Other security (e.g. perimeter and cargo security) | Headcount | CZ2: 5.1.10 Concession services (shops, F&B, etc.) | Headcount | DA2: 5.1.11 Runway, taxiway, apron operations | Headcount | DB2: 5.1.12 Other | Headcount | DC2: 5.1.1 Management | FTE | DD2: 5.1.2 Ground handling services: | FTE | DE2: 5.1.2.1 Passenger handling services | FTE | DF2: 5.1.2.2 Ramp handling services | FTE | DG2: 5.1.2.3 Cargo handling services | FTE | DH2: 5.1.3 Rescue and fire service | FTE | DI2: 5.1.4 Car parking services | FTE | DJ2: 5.1.5 Cleaning services | FTE | DK2: 5.1.6 Maintenance services | FTE | DL2: 5.1.7 Air traffic control services | FTE | DM2: 5.1.8 Passenger security services | FTE | DN2: 5.1.8.1 Other security (e.g. perimeter and cargo security) | FTE | DO2: 5.1.10 Concession services (shops, F&B, etc.) | FTE | DP2: 5.1.11 Runway, taxiway, apron operations | FTE | DQ2: 5.1.12 Other | FTE | DR2: 5.2 Total number of people working at the airport | DS2: 6.1 Total Airport Revenue (Sum 6.1.1, 6.1.2, 6.1.3) | DT2: 6.1.1 Operating Aeronautical Revenue (sum 6.1.1.1 -6.1.1.12, 6.1.1.13-6.1.1.16) | DU2: 6.1.1.1 Landing charges | DV2: 6.1.1.2 Lighting surcharges | DW2: 6.1.1.3 Noise & other environmental charges | DX2: 6.1.1.4 Navaid charges | DY2: 6.1.1.5 Parking charges | DZ2: 6.1.1.6 Boarding bridge charges | EA2: 6.1.1.7 Passenger charges (excluding AIF or similar) | EB2: 6.1.1.8 Transfer / transit charges | EC2: 6.1.1.9 Security charges | ED2: 6.1.1.10 Cargo (or freight) charges | EE2: 6.1.1.11 Fueling charges | EF2: 6.1.1.12 Ground handling services (excluding fuel charges) | EG2: 6.1.1.12.1 Ground handling infrastructure (if additional to 6.1.1.4) | EH2: 6.1.1.13 Airport improvement fees - AIF (or Passenger facility charge) | EI2: 6.1.1.14 Utility recharges (e.g. water, electricity, etc.) | EJ2: 6.1.1.15 Terminal rentals paid by airlines for space utilization | EK2: 6.1.1.16 Other (please specify in text box below any item >3% of total income) | EL2: 6.1.1.16 Other TEXT | EM2: 6.1.2 Operating Non-Aeronautical Revenue (sum 6.1.2.1 - 6.1.2.7) | EN2: 6.1.2.1 Retail concessions | EO2: 6.1.2.1.1Duty Free concessions | EP2: 6.1.2.2 Food & Beverage | EQ2: 6.1.2.3 Car parking | ER2: 6.1.2.4 Rental car concessions | ES2: 6.1.2.5 Property & real estate income or rent | ET2: 6.1.2.6 Advertising | EU2: 6.1.2.7 Other (please specify in the text box below any item >3%) | EV2: 6.1.2.7 Other TEXT | EW2: 6.1.3 Non-Operating Revenue (sum 6.1.3.1-6.1.3.4) | EX2: 6.1.3.1 Interest income | EY2: 6.1.3.2 Subsidies / Grants | EZ2: 6.1.3.3 Asset Divestments | FA2: 6.1.3.4 Other (please specify in text box any item >3%) | FB2: 6.1.3.4 Other TEXT | FC2: 6.1.4 Comments (please type in the box below): | FD2: 7.1 Total Operating Expenses (sum 7.1.1 - 7.1.9) | FE2: 7.1.1 Personnel expenses (salaries and benefits) | FF2: 7.1.2 Contracted services (cost of services paid to third parties) | FG2: 7.1.3 Materials, equipment, supplies (excluding maintenance/contracted serv.) | FH2: 7.1.4 Communications, utilities, energy & waste | FI2: 7.1.5 Insurance, claims, settlements | FJ2: 7.1.6 Maintenance (excluding contracted services) | FK2: 7.1.7 Lease, rent, concession fee payments | FL2: 7.1.8 General and administrative expenses (excluding personnel) | FM2: 7.1.9 Other - (please specify in text box any item >3% of total expenses): | FN2: 7.1.9 Other TEXT | FO2: 7.2 Comments (please type in the box below): | FP2: 8.1 Total Airport Income | FQ2: 8.1.1 Operating Aeronautical Income | FR2: 8.1.2 Operating Non-Aeronautical Income | FS2: 8.1.3 Non-Operating Income | FT2: 8.2 Total Operating Expenses | FU2: 8.3 Operating Surplus/Deficit (EBITDA) | FV2: 8.4 Capital Costs | FW2: 8.4.1 Interest and dividends paid to third parties | FX2: 8.4.2 Depreciation or/and amortization of property, plant & equipment | FY2: 8.4.3 Other capital costs (please specify below) | FZ2: 8.4.3 Other capital costs TEXT | GA2: 8.5 Taxes & Other Fees | GB2: 8.6 Net Profit / Loss | GC2: 8.7 Comments (please type in the box below): | GD2: 9.1 Total Assets | GE2: 9.1.1 Current Assets | GF2: 9.1.1.1 Cash and equivalent | GG2: 9.1.1.2 Other | GH2: 9.1.2 Non Current Assets | GI2: 9.1.2.1 Fixed assets | GJ2: 9.1.2.2 Other | GK2: 9.2 Total Liabilities | GL2: 9.2.1 Current liabilities | GM2: 9.2.1 Non-current liabilities | GN2: 9.3 Net Assets (9.1 - 9.2) | GO2: 9.4 Accumulated depreciation of fixed assets (9.1.2.1) | GP2: 10.1 Debt outstanding | GQ2: 10.2 What is the credit rating of financial instruments issued by the airport company? Moody's: | GR2: 10.2 What is the credit rating of financial instruments issued by the airport company? S&P: | GS2: 10.2 What is the credit rating of financial instruments issued by the airport company? Fitch: | GT2: 10.2 What is the credit rating of financial instruments issued by the airport company? In words: | GU2: 11.1 Total Operating Expenses (Total corresponds to 7.1) | GV2: 11.1.1 Security | GW2: 11.1.2 Airfield Operations & Maintenance (including firefighting & winter services) | GX2: 11.1.3 Terminal, Landside Operations & Maintenance (including commercial operations) | GY2: 11.1.4 Administration | GZ2: 11.1.5 Sales & Marketing | HA2: 11.1.6 Other - (please specify in text box any item >5% of total operating expenses) | HB2: 11.1.6 Other - TEXT | HC2: 12.1 Taxes levied on passengers | HD2: 12.2 Taxed levied on airlines | HE2: 13.1 Airport Capital Expenditure (CAPEX) | HF2: 13.1.1 Purchase of property, plant & equipment | HG2: 13.1.2 Construction expenses | HH2: 13.1.3 Purchase of other goods & services | HI2: 13.1.4 Other capital expenditure items (please specify below) | HJ2: 13.1.4 Other capital expenditure items TEXT | HK2: 13.2 Comments (please type in the box below): | HL2: 14.1 Return On Invested Capital (ROIC) (%) | HM2: 14.2 Return on Capital Employed (ROCE) (%) | HQ2: 6.1 Total Airport Revenue (Sum 6.1.1, 6.1.2, 6.1.3) | HR2: 6.1.1 Operating Aeronautical Revenue (sum 6.1.1.1 -6.1.1.12, 6.1.1.13-6.1.1.16) | HS2: 6.1.1.1 Landing charges | HT2: 6.1.1.2 Lighting surcharges | HU2: 6.1.1.3 Noise & other environmental charges | HV2: 6.1.1.4 Navaid charges | HW2: 6.1.1.5 Parking charges | HX2: 6.1.1.6 Boarding bridge charges | HY2: 6.1.1.7 Passenger charges (excluding AIF or similar) | HZ2: 6.1.1.8 Transfer / transit charges | IA2: 6.1.1.9 Security charges | IB2: 6.1.1.10 Cargo (or freight) charges | IC2: 6.1.1.11 Fueling charges | ID2: 6.1.1.12 Ground handling services (excluding fuel charges) | IE2: 6.1.1.12.1 Ground handling infrastructure (if additional to 6.1.1.4) | IF2: 6.1.1.13 Airport improvement fees - AIF (or Passenger facility charge) | IG2: 6.1.1.14 Utility recharges (e.g. water, electricity, etc.) | IH2: 6.1.1.15 Terminal rentals paid by airlines for space utilization | II2: 6.1.1.16 Other (please specify in text box below any item >3% of total income) | IJ2: 6.1.1.16 Other TEXT | IK2: 6.1.2 Operating Non-Aeronautical Revenue (sum 6.1.2.1 - 6.1.2.7) | IL2: 6.1.2.1 Retail concessions | IM2: 6.1.2.1.1 of which: Duty Free concessions | IN2: 6.1.2.2 Food & Beverage | IO2: 6.1.2.3 Car parking | IP2: 6.1.2.4 Rental car concessions | IQ2: 6.1.2.5 Property & real estate income or rent | IR2: 6.1.2.6 Advertising | IS2: 6.1.2.7 Other (please specify in the text box below any item >3%) | IT2: 6.1.2.7 Other TEXT | IU2: 6.1.3 Non-Operating Revenue (sum 6.1.3.1-6.1.3.4) | IV2: 6.1.3.1 Interest income | IW2: 6.1.3.2 Subsidies / Grants | IX2: 6.1.3.3 Asset Divestments | IY2: 6.1.3.4 Other (please specify in text box any item >3%) | IZ2: 6.1.3.4 Other TEXT | JA2: 6.1.4 Comments (please type in the box below): | JB2: 7.1 Total Operating Expenses (sum 7.1.1 - 7.1.9) | JC2: 7.1.1 Personnel expenses (salaries and benefits) | JD2: 7.1.2 Contracted services (cost of services paid to third parties) | JE2: 7.1.3 Materials, equipment, supplies (excluding maintenance/contracted serv.) | JF2: 7.1.4 Communications, utilities, energy & waste | JG2: 7.1.5 Insurance, claims, settlements | JH2: 7.1.6 Maintenance (excluding contracted services) | JI2: 7.1.7 Lease, rent, concession fee payments | JJ2: 7.1.8 General and administrative expenses (excluding personnel) | JK2: 7.1.9 Other - (please specify in text box any item >3% of total expenses): | JL2: 7.1.9 Other TEXT | JM2: 7.2 Comments (please type in the box below): | JN2: 8.1 Total Airport Income | JO2: 8.1.1 Operating Aeronautical Income | JP2: 8.1.2 Operating Non-Aeronautical Income | JQ2: 8.1.3 Non-Operating Income | JR2: 8.2 Total Operating Expenses | JS2: 8.3 Operating Surplus/Deficit (EBITDA) | JT2: 8.4 Capital Costs | JU2: 8.4.1 Interest and dividends paid to third parties | JV2: 8.4.2 Depreciation or/and amortization of property, plant & equipment | JW2: 8.4.3 Other capital costs (please specify below) | JX2: 8.4.3 Other capital costs TEXT | JY2: 8.5 Taxes & Other Fees | JZ2: 8.6 Net Profit / Loss | KA2: 8.7 Comments (please type in the box below): | KB2: 9.1 Total Assets | KC2: 9.1.1 Current Assets | KD2: 9.1.1.1 Cash and equivalent | KE2: 9.1.1.2 Other | KF2: 9.1.2 Non Current Assets | KG2: 9.1.2.1 Fixed assets | KH2: 9.1.2.2 Other | KI2: 9.2 Total Liabilities | KJ2: 9.2.1 Current liabilities | KK2: 9.2.1 Non-current liabilities | KL2: 9.3 Net Assets (9.1 - 9.2) | KM2: 9.4 Accumulated depreciation of fixed assets (9.1.2.1) | KN2: 10.1 Debt outstanding | KO2: 11.1 Total Operating Expenses (Total corresponds to 7.1) | KP2: 11.1.1 Security | KQ2: 11.1.2 Airfield Operations & Maintenance (including firefighting & winter services) | KR2: 11.1.3 Terminal, Landside Operations & Maintenance (including commercial operations) | KS2: 11.1.4 Administration | KT2: 11.1.5 Sales & Marketing | KU2: 11.1.6 Other - (please specify in text box any item >5% of total operating expenses) | KV2: 11.1.6 Other - TEXT | KW2: 12.1 Taxes levied on passengers | KX2: 12.2 Taxed levied on airlines | KY2: 13.1 Airport Capital Expenditure (CAPEX) | KZ2: 13.1.1 Purchase of property, plant & equipment | LA2: 13.1.2 Construction expenses | LB2: 13.1.3 Purchase of other goods & services | LC2: 13.1.4 Other capital expenditure items (please specify below) | LD2: 13.1.4 Other capital expenditure items TEXT | LE2: 13.2 Comments (please type in the box below): | LF2: 14.1 Return On Invested Capital (ROIC) (%) | LG2: 14.2 Return on Capital Employed (ROCE) (%)
F3: =IF(ISBLANK(ESPAÑOL!L27), "", ESPAÑOL!L27) | G3: =IF(LEN(F3)=3, "1", "") | H3: =IF(ISBLANK(ESPAÑOL!C27), "", ESPAÑOL!C27) | I3: =IF(ISBLANK(ESPAÑOL!C29), "", ESPAÑOL!C29) | J3: =IF(ISBLANK(ESPAÑOL!C31), "", ESPAÑOL!C31) | K3: =IF(ISBLANK(ESPAÑOL!L29), "", ESPAÑOL!L29) | L3: =IF(ISBLANK(ESPAÑOL!L31), "", ESPAÑOL!L31) | M3: =IF(ISBLANK(ESPAÑOL!F39), "", ESPAÑOL!F39) | N3: =IF(ISBLANK(ESPAÑOL!F41), "", ESPAÑOL!F41) | O3: =IF(ISBLANK(ESPAÑOL!F43), "", ESPAÑOL!F43) | P3: =IF(ISBLANK(ESPAÑOL!F45), "", ESPAÑOL!F45) | Q3: =IF(ISBLANK(ESPAÑOL!O39), "", ESPAÑOL!O39) | R3: =IF(ISBLANK(ESPAÑOL!O41), "", ESPAÑOL!O41) | S3: =IF(ISBLANK(ESPAÑOL!O43), "", ESPAÑOL!O43) | T3: =IF(ISBLANK(ESPAÑOL!O45), "", ESPAÑOL!O45) | U3: =IF(ISBLANK(ESPAÑOL!J52), "", ESPAÑOL!J52) | V3: =IF(ISBLANK(ESPAÑOL!M52), "", ESPAÑOL!M52) | W3: =IF(ISBLANK(ESPAÑOL!J54), "", ESPAÑOL!J54) | X3: =IF(ISBLANK(ESPAÑOL!M54), "", ESPAÑOL!M54) | Y3: =IF(ISBLANK(ESPAÑOL!J55), "", ESPAÑOL!J55) | Z3: =IF(ISBLANK(ESPAÑOL!M55), "", ESPAÑOL!M55) | AA3: =IF(ISBLANK(ESPAÑOL!J57), "", ESPAÑOL!J57) | AB3: =IF(ISBLANK(ESPAÑOL!M57), "", ESPAÑOL!M57) | AC3: =IF(ISBLANK(ESPAÑOL!J59), "", ESPAÑOL!J59) | AD3: =IF(ISBLANK(ESPAÑOL!M59), "", ESPAÑOL!M59) | AE3: =IF(ISBLANK(ESPAÑOL!J60), "", ESPAÑOL!J60) | AF3: =IF(ISBLANK(ESPAÑOL!M60), "", ESPAÑOL!M60) | AG3: =IF(ISBLANK(ESPAÑOL!J62), "", ESPAÑOL!J62) | AH3: =IF(ISBLANK(ESPAÑOL!M62), "", ESPAÑOL!M62) | AI3: =IF(ISBLANK(ESPAÑOL!J64), "", ESPAÑOL!J64) | AJ3: =IF(ISBLANK(ESPAÑOL!M64), "", ESPAÑOL!M64) | AK3: =IF(ISBLANK(ESPAÑOL!J67), "", ESPAÑOL!J67) | AL3: =IF(ISBLANK(ESPAÑOL!M67), "", ESPAÑOL!M67) | AM3: =IF(ISBLANK(ESPAÑOL!J68), "", ESPAÑOL!J68) | AN3: =IF(ISBLANK(ESPAÑOL!M68), "", ESPAÑOL!M68) | AO3: =IF(ISBLANK(ESPAÑOL!J70), "", ESPAÑOL!J70) | AP3: =IF(ISBLANK(ESPAÑOL!M70), "", ESPAÑOL!M70) | AQ3: =IF(ISBLANK(ESPAÑOL!J77), "", ESPAÑOL!J77) | AR3: =IF(ISBLANK(ESPAÑOL!J78), "", ESPAÑOL!J78) | AS3: =IF(ISBLANK(ESPAÑOL!J79), "", ESPAÑOL!J79) | AT3: =IF(ISBLANK(ESPAÑOL!J80), "", ESPAÑOL!J80) | AU3: =IF(ISBLANK(ESPAÑOL!J81), "", ESPAÑOL!J81) | AV3: =IF(ISBLANK(ESPAÑOL!J82), "", ESPAÑOL!J82) | AW3: =IF(ISBLANK(ESPAÑOL!J83), "", ESPAÑOL!J83) | AX3: =IF(ISBLANK(ESPAÑOL!J84), "", ESPAÑOL!J84) | AY3: =IF(ISBLANK(ESPAÑOL!J85), "", ESPAÑOL!J85) | AZ3: =IF(ISBLANK(ESPAÑOL!J87), "", ESPAÑOL!J87) | BA3: =IF(ISBLANK(ESPAÑOL!J88), "", ESPAÑOL!J88) | BB3: =IF(ISBLANK(ESPAÑOL!M94), "", ESPAÑOL!M94) | BC3: =IF(ISBLANK(ESPAÑOL!M96), "", ESPAÑOL!M96) | BD3: =IF(ISBLANK(ESPAÑOL!M98), "", ESPAÑOL!M98) | BE3: =IF(ISBLANK(ESPAÑOL!M100), "", ESPAÑOL!M100) | BF3: =IF(ISBLANK(ESPAÑOL!M102), "", ESPAÑOL!M102) | BG3: =IF(ISBLANK(ESPAÑOL!M104), "", ESPAÑOL!M104) | BH3: =IF(ISBLANK(ESPAÑOL!K115), "", ESPAÑOL!K115) | BI3: =IF(ISBLANK(ESPAÑOL!O115), "", ESPAÑOL!O115) | BJ3: FALSE | BK3: FALSE | BL3: FALSE | BM3: FALSE | BN3: FALSE | BO3: FALSE | BP3: FALSE | BQ3: FALSE | BR3: FALSE | BS3: FALSE | BT3: FALSE | BU3: FALSE | BV3: FALSE | BW3: FALSE | BX3: FALSE | BY3: FALSE | BZ3: FALSE | CA3: FALSE | CB3: FALSE | CC3: FALSE | CD3: FALSE | CE3: FALSE | CF3: FALSE | CG3: FALSE | CH3: FALSE | CI3: FALSE | CJ3: FALSE | CK3: FALSE | CL3: FALSE | CM3: FALSE | CN3: =IF(ISBLANK(ESPAÑOL!K119), "", ESPAÑOL!K119) | CO3: =IF(ISBLANK(ESPAÑOL!K120), "", ESPAÑOL!K120) | CP3: =IF(ISBLANK(ESPAÑOL!K122), "", ESPAÑOL!K122) | CQ3: =IF(ISBLANK(ESPAÑOL!K123), "", ESPAÑOL!K123) | CR3: =IF(ISBLANK(ESPAÑOL!K124), "", ESPAÑOL!K124) | CS3: =IF(ISBLANK(ESPAÑOL!K125), "", ESPAÑOL!K125) | CT3: =IF(ISBLANK(ESPAÑOL!K126), "", ESPAÑOL!K126) | CU3: =IF(ISBLANK(ESPAÑOL!K127), "", ESPAÑOL!K127) | CV3: =IF(ISBLANK(ESPAÑOL!K128), "", ESPAÑOL!K128) | CW3: =IF(ISBLANK(ESPAÑOL!K129), "", ESPAÑOL!K129) | CX3: =IF(ISBLANK(ESPAÑOL!K130), "", ESPAÑOL!K130) | CY3: =IF(ISBLANK(ESPAÑOL!K132), "", ESPAÑOL!K132) | CZ3: =IF(ISBLANK(ESPAÑOL!K133), "", ESPAÑOL!K133) | DA3: =IF(ISBLANK(ESPAÑOL!K134), "", ESPAÑOL!K134) | DB3: =IF(ISBLANK(ESPAÑOL!K135), "", ESPAÑOL!K135) | DC3: =IF(ISBLANK(ESPAÑOL!O119), "", ESPAÑOL!O119) | DD3: =IF(ISBLANK(ESPAÑOL!O120), "", ESPAÑOL!O120) | DE3: =IF(ISBLANK(ESPAÑOL!O122), "", ESPAÑOL!O122) | DF3: =IF(ISBLANK(ESPAÑOL!O123), "", ESPAÑOL!O123) | DG3: =IF(ISBLANK(ESPAÑOL!O124), "", ESPAÑOL!O124) | DH3: =IF(ISBLANK(ESPAÑOL!O125), "", ESPAÑOL!O125) | DI3: =IF(ISBLANK(ESPAÑOL!O126), "", ESPAÑOL!O126) | DJ3: =IF(ISBLANK(ESPAÑOL!O127), "", ESPAÑOL!O127) | DK3: =IF(ISBLANK(ESPAÑOL!O128), "", ESPAÑOL!O128) | DL3: =IF(ISBLANK(ESPAÑOL!O129), "", ESPAÑOL!O129) | DM3: =IF(ISBLANK(ESPAÑOL!O130), "", ESPAÑOL!O130) | DN3: =IF(ISBLANK(ESPAÑOL!O132), "", ESPAÑOL!O132) | DO3: =IF(ISBLANK(ESPAÑOL!O133), "", ESPAÑOL!O133) | DP3: =IF(ISBLANK(ESPAÑOL!O134), "", ESPAÑOL!O134) | DQ3: =IF(ISBLANK(ESPAÑOL!O135), "", ESPAÑOL!O135) | DR3: =IF(ISBLANK(ESPAÑOL!K138), "", ESPAÑOL!K138) | DS3: =IF(ISBLANK(ESPAÑOL!K146), "", ESPAÑOL!K146) -> 0 | DT3: =IF(ISBLANK(ESPAÑOL!K148), "", ESPAÑOL!K148) -> 0 | DU3: =IF(ISBLANK(ESPAÑOL!K150), "", ESPAÑOL!K150) | DV3: =IF(ISBLANK(ESPAÑOL!K151), "", ESPAÑOL!K151) | DW3: =IF(ISBLANK(ESPAÑOL!K152), "", ESPAÑOL!K152) | DX3: =IF(ISBLANK(ESPAÑOL!K153), "", ESPAÑOL!K153) | DY3: =IF(ISBLANK(ESPAÑOL!K154), "", ESPAÑOL!K154) | DZ3: =IF(ISBLANK(ESPAÑOL!K155), "", ESPAÑOL!K155) | EA3: =IF(ISBLANK(ESPAÑOL!K156), "", ESPAÑOL!K156) | EB3: =IF(ISBLANK(ESPAÑOL!K157), "", ESPAÑOL!K157) | EC3: =IF(ISBLANK(ESPAÑOL!K158), "", ESPAÑOL!K158) | ED3: =IF(ISBLANK(ESPAÑOL!K159), "", ESPAÑOL!K159) | EE3: =IF(ISBLANK(ESPAÑOL!K160), "", ESPAÑOL!K160) | EF3: =IF(ISBLANK(ESPAÑOL!K161), "", ESPAÑOL!K161) | EG3: =IF(ISBLANK(ESPAÑOL!K162), "", ESPAÑOL!K162) | EH3: =IF(ISBLANK(ESPAÑOL!K163), "", ESPAÑOL!K163) | EI3: =IF(ISBLANK(ESPAÑOL!K164), "", ESPAÑOL!K164) | EJ3: =IF(ISBLANK(ESPAÑOL!K165), "", ESPAÑOL!K165) | EK3: =IF(ISBLANK(ESPAÑOL!K167), "", ESPAÑOL!K167) | EL3: =IF(ISBLANK(ESPAÑOL!D167), "", ESPAÑOL!D167) | EM3: =IF(ISBLANK(ESPAÑOL!K169), "", ESPAÑOL!K169) -> 0 | EN3: =IF(ISBLANK(ESPAÑOL!K171), "", ESPAÑOL!K171) | EO3: =IF(ISBLANK(ESPAÑOL!K172), "", ESPAÑOL!K172) | EP3: =IF(ISBLANK(ESPAÑOL!K173), "", ESPAÑOL!K173) | EQ3: =IF(ISBLANK(ESPAÑOL!K174), "", ESPAÑOL!K174) | ER3: =IF(ISBLANK(ESPAÑOL!K175), "", ESPAÑOL!K175) | ES3: =IF(ISBLANK(ESPAÑOL!K176), "", ESPAÑOL!K176) | ET3: =IF(ISBLANK(ESPAÑOL!K177), "", ESPAÑOL!K177) | EU3: =IF(ISBLANK(ESPAÑOL!K179), "", ESPAÑOL!K179) | EV3: =IF(ISBLANK(ESPAÑOL!D179), "", ESPAÑOL!D179) | EW3: =IF(ISBLANK(ESPAÑOL!K181), "", ESPAÑOL!K181) -> 0 | EX3: =IF(ISBLANK(ESPAÑOL!K183), "", ESPAÑOL!K183) | EY3: =IF(ISBLANK(ESPAÑOL!K184), "", ESPAÑOL!K184) | EZ3: =IF(ISBLANK(ESPAÑOL!K185), "", ESPAÑOL!K185) | FA3: =IF(ISBLANK(ESPAÑOL!K187), "", ESPAÑOL!K187) | FB3: =IF(ISBLANK(ESPAÑOL!D187), "", ESPAÑOL!D187) | FC3: =IF(ISBLANK(ESPAÑOL!D191), "", ESPAÑOL!D191) | FD3: =IF(ISBLANK(ESPAÑOL!K199), "", ESPAÑOL!K199) -> 0 | FE3: =IF(ISBLANK(ESPAÑOL!K201), "", ESPAÑOL!K201) | FF3: =IF(ISBLANK(ESPAÑOL!K202), "", ESPAÑOL!K202) | FG3: =IF(ISBLANK(ESPAÑOL!K203), "", ESPAÑOL!K203) | FH3: =IF(ISBLANK(ESPAÑOL!K204), "", ESPAÑOL!K204) | FI3: =IF(ISBLANK(ESPAÑOL!K205), "", ESPAÑOL!K205) | FJ3: =IF(ISBLANK(ESPAÑOL!K206), "", ESPAÑOL!K206) | FK3: =IF(ISBLANK(ESPAÑOL!K207), "", ESPAÑOL!K207) | FL3: =IF(ISBLANK(ESPAÑOL!K208), "", ESPAÑOL!K208) | FM3: =IF(ISBLANK(ESPAÑOL!K210), "", ESPAÑOL!K210) | FN3: =IF(ISBLANK(ESPAÑOL!D210), "", ESPAÑOL!D210) | FO3: =IF(ISBLANK(ESPAÑOL!D214), "", ESPAÑOL!D214) | FP3: =IF(ISBLANK(ESPAÑOL!K222), "", ESPAÑOL!K222) -> 0 | FQ3: =IF(ISBLANK(ESPAÑOL!K224), "", ESPAÑOL!K224) -> 0 | FR3: =IF(ISBLANK(ESPAÑOL!K225), "", ESPAÑOL!K225) -> 0 | FS3: =IF(ISBLANK(ESPAÑOL!K226), "", ESPAÑOL!K226) -> 0 | FT3: =IF(ISBLANK(ESPAÑOL!K228), "", ESPAÑOL!K228) -> 0 | FU3: =IF(ISBLANK(ESPAÑOL!K230), "", ESPAÑOL!K230) -> 0 | FV3: =IF(ISBLANK(ESPAÑOL!K233), "", ESPAÑOL!K233) -> 0 | FW3: =IF(ISBLANK(ESPAÑOL!K235), "", ESPAÑOL!K235) | FX3: =IF(ISBLANK(ESPAÑOL!K236), "", ESPAÑOL!K236) | FY3: =IF(ISBLANK(ESPAÑOL!K238), "", ESPAÑOL!K238) | FZ3: =IF(ISBLANK(ESPAÑOL!D238), "", ESPAÑOL!D238) | GA3: =IF(ISBLANK(ESPAÑOL!K240), "", ESPAÑOL!K240) | GB3: =IF(ISBLANK(ESPAÑOL!K242), "", ESPAÑOL!K242) -> 0 | GC3: =IF(ISBLANK(ESPAÑOL!D247), "", ESPAÑOL!D247) | GD3: =IF(ISBLANK(ESPAÑOL!K255), "", ESPAÑOL!K255) -> 0 | GE3: =IF(ISBLANK(ESPAÑOL!K257), "", ESPAÑOL!K257) -> 0 | GF3: =IF(ISBLANK(ESPAÑOL!K258), "", ESPAÑOL!K258) | GG3: =IF(ISBLANK(ESPAÑOL!K259), "", ESPAÑOL!K259) | GH3: =IF(ISBLANK(ESPAÑOL!K261), "", ESPAÑOL!K261) -> 0 | GI3: =IF(ISBLANK(ESPAÑOL!K262), "", ESPAÑOL!K262) | GJ3: =IF(ISBLANK(ESPAÑOL!K264),"", ESPAÑOL!K264) | GK3: =IF(ISBLANK(ESPAÑOL!K266), "", ESPAÑOL!K266) -> 0 | GL3: =IF(ISBLANK(ESPAÑOL!K267), "", ESPAÑOL!K267) | GM3: =IF(ISBLANK(ESPAÑOL!K268), "", ESPAÑOL!K268) | GN3: =IF(ISBLANK(ESPAÑOL!K270), "", ESPAÑOL!K270) -> 0 | GO3: =IF(ISBLANK(ESPAÑOL!K263), "", ESPAÑOL!K263) | GP3: =IF(ISBLANK(ESPAÑOL!K276), "", ESPAÑOL!K276) | GQ3: =IF(ISBLANK(ESPAÑOL!K279), "", ESPAÑOL!K279) | GR3: =IF(ISBLANK(ESPAÑOL!M279), "", ESPAÑOL!M279) | GS3: =IF(ISBLANK(ESPAÑOL!O279), "", ESPAÑOL!O279) | GT3: =IF(ISBLANK(ESPAÑOL!Q279), "", ESPAÑOL!Q279) | GU3: =IF(ISBLANK(ESPAÑOL!K285), "", ESPAÑOL!K285) -> 0 | GV3: =IF(ISBLANK(ESPAÑOL!K287),"",ESPAÑOL!K287) | GW3: =IF(ISBLANK(ESPAÑOL!K288),"",ESPAÑOL!K288) | GX3: =IF(ISBLANK(ESPAÑOL!K289),"",ESPAÑOL!K289) | GY3: =IF(ISBLANK(ESPAÑOL!K290),"",ESPAÑOL!K290) | GZ3: =IF(ISBLANK(ESPAÑOL!K291),"",ESPAÑOL!K291) | HA3: =IF(ISBLANK(ESPAÑOL!K293),"",ESPAÑOL!K293) | HB3: =IF(ISBLANK(ESPAÑOL!D293), "", ESPAÑOL!D293) | HC3: =IF(ISBLANK(ESPAÑOL!K299), "", ESPAÑOL!K299) | HD3: =IF(ISBLANK(ESPAÑOL!K300), "", ESPAÑOL!K300) | HE3: =IF(ISBLANK(ESPAÑOL!K306), "", ESPAÑOL!K306) -> 0 | HF3: =IF(ISBLANK(ESPAÑOL!K308), "", ESPAÑOL!K308) | HG3: =IF(ISBLANK(ESPAÑOL!K309), "", ESPAÑOL!K309) | HH3: =IF(ISBLANK(ESPAÑOL!K310), "", ESPAÑOL!K31) | HI3: =IF(ISBLANK(ESPAÑOL!K312), "", ESPAÑOL!K312) | HJ3: =IF(ISBLANK(ESPAÑOL!D312), "", ESPAÑOL!D312) | HK3: =IF(ISBLANK(ESPAÑOL!D316), "", ESPAÑOL!D316) | HL3: =IF(ISBLANK(ESPAÑOL!K324), "", ESPAÑOL!K324) | HM3: =IF(ISBLANK(ESPAÑOL!K325), "", ESPAÑOL!K325) | HQ3: =IF(ISBLANK(ESPAÑOL!O146), "", ESPAÑOL!O146) -> 0 | HR3: =IF(ISBLANK(ESPAÑOL!O148), "", ESPAÑOL!O148) -> 0 | HS3: =IF(ISBLANK(ESPAÑOL!O150), "", ESPAÑOL!O150) | HT3: =IF(ISBLANK(ESPAÑOL!O151), "", ESPAÑOL!O151) | HU3: =IF(ISBLANK(ESPAÑOL!O152), "", ESPAÑOL!O152) | HV3: =IF(ISBLANK(ESPAÑOL!O153), "", ESPAÑOL!O153) | HW3: =IF(ISBLANK(ESPAÑOL!O154), "", ESPAÑOL!O154) | HX3: =IF(ISBLANK(ESPAÑOL!O155), "", ESPAÑOL!O155) | HY3: =IF(ISBLANK(ESPAÑOL!O156), "", ESPAÑOL!O156) | HZ3: =IF(ISBLANK(ESPAÑOL!O157), "", ESPAÑOL!O157) | IA3: =IF(ISBLANK(ESPAÑOL!O158), "", ESPAÑOL!O158) | IB3: =IF(ISBLANK(ESPAÑOL!O159), "", ESPAÑOL!O159) | IC3: =IF(ISBLANK(ESPAÑOL!O160), "", ESPAÑOL!O160) | ID3: =IF(ISBLANK(ESPAÑOL!O161), "", ESPAÑOL!O161) | IE3: =IF(ISBLANK(ESPAÑOL!O162), "", ESPAÑOL!O162) | IF3: =IF(ISBLANK(ESPAÑOL!O163), "", ESPAÑOL!O163) | IG3: =IF(ISBLANK(ESPAÑOL!O164), "", ESPAÑOL!O164) | IH3: =IF(ISBLANK(ESPAÑOL!O165), "", ESPAÑOL!O165) | II3: =IF(ISBLANK(ESPAÑOL!O167), "", ESPAÑOL!O167) | IJ3: =IF(ISBLANK(ESPAÑOL!D167), "", ESPAÑOL!D167) | IK3: =IF(ISBLANK(ESPAÑOL!O169), "", ESPAÑOL!O169) -> 0 | IL3: =IF(ISBLANK(ESPAÑOL!O171), "", ESPAÑOL!O171) | IM3: =IF(ISBLANK(ESPAÑOL!O172), "", ESPAÑOL!O172) | IN3: =IF(ISBLANK(ESPAÑOL!O173), "", ESPAÑOL!O173) | IO3: =IF(ISBLANK(ESPAÑOL!O174), "", ESPAÑOL!O174) | IP3: =IF(ISBLANK(ESPAÑOL!O175), "", ESPAÑOL!O175) | IQ3: =IF(ISBLANK(ESPAÑOL!O176), "", ESPAÑOL!O176) | IR3: =IF(ISBLANK(ESPAÑOL!O177), "", ESPAÑOL!O177) | IS3: =IF(ISBLANK(ESPAÑOL!O179), "", ESPAÑOL!O179) | IT3: =IF(ISBLANK(ESPAÑOL!D179), "", ESPAÑOL!D179) | IU3: =IF(ISBLANK(ESPAÑOL!O181), "", ESPAÑOL!O181) -> 0 | IV3: =IF(ISBLANK(ESPAÑOL!O183), "", ESPAÑOL!O183) | IW3: =IF(ISBLANK(ESPAÑOL!O184), "", ESPAÑOL!O184) | IX3: =IF(ISBLANK(ESPAÑOL!O185), "", ESPAÑOL!O185) | IY3: =IF(ISBLANK(ESPAÑOL!O187), "", ESPAÑOL!O187) | IZ3: =IF(ISBLANK(ESPAÑOL!DB187), "", ESPAÑOL!DB187) | JA3: =IF(ISBLANK(ESPAÑOL!D191), "", ESPAÑOL!D191) | JB3: =IF(ISBLANK(ESPAÑOL!O199), "", ESPAÑOL!O199) -> 0 | JC3: =IF(ISBLANK(ESPAÑOL!O201), "", ESPAÑOL!O201) | JD3: =IF(ISBLANK(ESPAÑOL!O202), "", ESPAÑOL!O202) | JE3: =IF(ISBLANK(ESPAÑOL!O203), "", ESPAÑOL!O203) | JF3: =IF(ISBLANK(ESPAÑOL!O204), "", ESPAÑOL!O204) | JG3: =IF(ISBLANK(ESPAÑOL!O205), "", ESPAÑOL!O205) | JH3: =IF(ISBLANK(ESPAÑOL!O206), "", ESPAÑOL!O206) | JI3: =IF(ISBLANK(ESPAÑOL!O207), "", ESPAÑOL!O207) | JJ3: =IF(ISBLANK(ESPAÑOL!O208), "", ESPAÑOL!O208) | JK3: =IF(ISBLANK(ESPAÑOL!O210), "", ESPAÑOL!O210) | JL3: =IF(ISBLANK(ESPAÑOL!D210), "", ESPAÑOL!D210) | JM3: =IF(ISBLANK(ESPAÑOL!D214), "", ESPAÑOL!D214) | JN3: =IF(ISBLANK(ESPAÑOL!O222), "", ESPAÑOL!O222) -> 0 | JO3: =IF(ISBLANK(ESPAÑOL!O224), "", ESPAÑOL!O224) -> 0 | JP3: =IF(ISBLANK(ESPAÑOL!O225), "", ESPAÑOL!O225) -> 0 | JQ3: =IF(ISBLANK(ESPAÑOL!O226), "", ESPAÑOL!O226) -> 0 | JR3: =IF(ISBLANK(ESPAÑOL!O228), "", ESPAÑOL!O228) -> 0 | JS3: =IF(ISBLANK(ESPAÑOL!O230), "", ESPAÑOL!O230) -> 0 | JT3: =IF(ISBLANK(ESPAÑOL!O233), "", ESPAÑOL!O233) -> 0 | JU3: =IF(ISBLANK(ESPAÑOL!O235), "", ESPAÑOL!O235) | JV3: =IF(ISBLANK(ESPAÑOL!O236), "", ESPAÑOL!O236) | JW3: =IF(ISBLANK(ESPAÑOL!O238), "", ESPAÑOL!O238) | JX3: =IF(ISBLANK(ESPAÑOL!D238), "", ESPAÑOL!D238) | JY3: =IF(ISBLANK(ESPAÑOL!O240), "", ESPAÑOL!O240) | JZ3: =IF(ISBLANK(ESPAÑOL!O242), "", ESPAÑOL!O242) -> 0 | KA3: =IF(ISBLANK(ESPAÑOL!D247), "", ESPAÑOL!D247) | KB3: =IF(ISBLANK(ESPAÑOL!O255), "", ESPAÑOL!O255) -> 0 | KC3: =IF(ISBLANK(ESPAÑOL!O257), "", ESPAÑOL!O257) -> 0 | KD3: =IF(ISBLANK(ESPAÑOL!O258), "", ESPAÑOL!O258) | KE3: =IF(ISBLANK(ESPAÑOL!O259), "", ESPAÑOL!O259) | KF3: =IF(ISBLANK(ESPAÑOL!O261), "", ESPAÑOL!O261) -> 0 | KG3: =IF(ISBLANK(ESPAÑOL!O262), "", ESPAÑOL!O262) | KH3: =IF(ISBLANK(ESPAÑOL!O264),"", ESPAÑOL!O264) | KI3: =IF(ISBLANK(ESPAÑOL!O266), "", ESPAÑOL!O266) -> 0 | KJ3: =IF(ISBLANK(ESPAÑOL!O267), "", ESPAÑOL!O267) | KK3: =IF(ISBLANK(ESPAÑOL!O268), "", ESPAÑOL!O268) | KL3: =IF(ISBLANK(ESPAÑOL!O270), "", ESPAÑOL!O270) -> 0 | KM3: =IF(ISBLANK(ESPAÑOL!O263), "", ESPAÑOL!O263) | KN3: =IF(ISBLANK(ESPAÑOL!O276), "", ESPAÑOL!O276) | KO3: =IF(ISBLANK(ESPAÑOL!O285), "", ESPAÑOL!O285) -> 0 | KP3: =IF(ISBLANK(ESPAÑOL!O287),"",ESPAÑOL!O287) | KQ3: =IF(ISBLANK(ESPAÑOL!O288),"",ESPAÑOL!O288) | KR3: =IF(ISBLANK(ESPAÑOL!O289),"",ESPAÑOL!O289) | KS3: =IF(ISBLANK(ESPAÑOL!O290),"",ESPAÑOL!O290) | KT3: =IF(ISBLANK(ESPAÑOL!O291),"",ESPAÑOL!O291) | KU3: =IF(ISBLANK(ESPAÑOL!O293),"",ESPAÑOL!O293) | KV3: =IF(ISBLANK(ESPAÑOL!D293), "", ESPAÑOL!D293) | KW3: =IF(ISBLANK(ESPAÑOL!O299), "", ESPAÑOL!O299) | KX3: =IF(ISBLANK(ESPAÑOL!O300), "", ESPAÑOL!O300) | KY3: =IF(ISBLANK(ESPAÑOL!O306), "", ESPAÑOL!O306) -> 0 | KZ3: =IF(ISBLANK(ESPAÑOL!O308), "", ESPAÑOL!O308) | LA3: =IF(ISBLANK(ESPAÑOL!O309), "", ESPAÑOL!O309) | LB3: =IF(ISBLANK(ESPAÑOL!O310), "", ESPAÑOL!O31) | LC3: =IF(ISBLANK(ESPAÑOL!O312), "", ESPAÑOL!O312) | LD3: =IF(ISBLANK(ESPAÑOL!D312), "", ESPAÑOL!D312) | LE3: =IF(ISBLANK(ESPAÑOL!D316), "", ESPAÑOL!D316) | LF3: =IF(ISBLANK(ESPAÑOL!O324), "", ESPAÑOL!O324) | LG3: =IF(ISBLANK(ESPAÑOL!DE325), "", ESPAÑOL!DE325)
