Workbook

Sheet DIRECTIONS
A1: Directions for completing the Straight A Grant Financial Impact Report
A4: Each applicant for a Straight A Fund grant must complete a Straight A Grant Financial Impact Table. The instructions for completing the file can be found below. This file is used for all applicants. If you have multiple applicants, you will need multiple tabs (discussed below). Use the appropriate tab based on your organization type. City, local, exempted village or joint vocational school districts will use the Traditional tab. Educational Service Centers will use the ESC tab. All other applicants will use the Non-Traditional tab.
A7: Instructions for the Traditional Tab
A8: 1. Enter the district's 6-digit IRN in cell B2 of the Traditional tab. Column C of the form will be populated with the October, FY14 five-year forecast figures as submitted to EMIS for the entered district. 2. Enter into Columns D through H (FY16-FY20) the anticipated sustaining costs and cost reductions for each expenditure type impacted by Straight A funds in the years following the grant year (FY15). These numbers are to be based on the anticipated grant award. The purpose of the financial impact table is to show the impact of the grant award. 3. Enter into Column I text explaination regarding the anticipated costs and cost reductions.
A10: Instructions for the Non-Traditional and ESC Tabs
A11: 1. Enter the school or organization name in cell B1 and the IRN (if applicable) in cell B2 of the Non-Traditional or ESC tab. 2. If the applicant is a community school that has submitted a five-year forecast, enter into Column C the data from the five-year forecast as submitted to ODE for the current fiscal year (October, FY14). If the applicant is an organization that has not submitted a five-year forecast to ODE, enter into Column C the current budget information. 3. Enter into Columns D through H (FY16-FY20) the anticipated sustaining costs and cost reductions for each expenditure type impacted by Straight A funds in the years following the grant year (FY15). These numbers are to be based on the anticipated grant award. The purpose of the financial impact table is to show the impact of the grant award. 4. Enter into Column I text explaination regarding the anticipated costs and cost reductions.
A17: Individual Applicants:
A18: A submitted Financial Impact Table for an individual applicant should contain only one tab. 1. After completing the appropriate tab as detailed above, delete the unused tabs from the workbook. 1.a. Right click on the unused tab. 1.b. Select Delete. 2. Save the file with the file name of 'Financial Impact XXXXXX' where XXXXXX is your school's IRN (if applicable) or organization name. 3. Upload the completed file to the CCIP.
A20: Consortium Applicants:
A21: A submitted Financial Impact Table for a consortium should contain one tab for each member of the consortium. 1. Copy the appropriate tab for each member of the consortium based on the organization type. 1.a. Right click on the appropriate tab to be copied (Traditional, ESC or Non-Traditional). Select Move or Copy. 1.b. Select (move to the end) and the Create a copy checkbox. 1.c. Click on OK. A new tab will be created. 1.d. Double-click on the tab title to rename it to the consortium member's IRN (if applicable) or organization name. 2. The first tab after the DIRECTIONS should be the tab for the Lead Applicant. If the Lead Applicant tab is not the first one, click and drag to rearrange the tabs. 3. Enter the appropriate budget and forecast information on each consortium member's tab based on the instructions above. 4. Save the file with the file name of 'Financial Impact XXXXXX' where XXXXXX is the name of the consortium. 5. Upload the completed file to the CCIP.

Sheet Traditional
A1: IRN (6 digits): | I1: APPLICANT:
A2: APPLICANT: | B2: =VLOOKUP(B1,'FYF DATA'!$A$1:$BR$670,2,FALSE) -> #N/A | I2: =B2 -> #N/A
C3: FY14 | D3: FY16 | E3: FY17 | F3: FY18 | G3: FY19 | H3: FY20 | I3: EXPLAINATION
A4: Do not alter any of the shaded cells. | C4: Financial Baseline from the Current Five-Year Forecast | D4: Since FY15 is the grant year, its expenditures are not required in this table. In the FY16-FY20 columns, ADD only the SUSTAINING COSTS to the appropriate line items (refer to Question 15), and SUBTRACT only the SUSTAINING COST REDUCTIONS to the appropriate line items (refer to Questions 16 & 17). | I4: Explaination Provide detailed notes regarding the financial impact on each line affected by the grant funds. These notes are critical to the evaluation of the financial sustainability.
A5: EXPENDITURES - OPERATIONAL | C5: FY14 | D5: FY16 | E5: FY17 | F5: FY18 | G5: FY19 | H5: FY20
A6: 3.010 | B6: Personal Services (Salaries & Wages) | C6: =VLOOKUP(B1,'FYF DATA'!$A$1:$BR$670,20,FALSE) -> #N/A
A7: 3.020 | B7: Fringe Benefits | C7: =VLOOKUP(B1,'FYF DATA'!$A$1:$BR$670,21,FALSE) -> #N/A
A8: 3.030 | B8: Purchased Services | C8: =VLOOKUP(B1,'FYF DATA'!$A$1:$BR$670,22,FALSE) -> #N/A
A9: 3.040 | B9: Supplies and Materials | C9: =VLOOKUP(B1,'FYF DATA'!$A$1:$BR$670,23,FALSE) -> #N/A
A10: 3.050 | B10: Capital Outlay | C10: =VLOOKUP(B1,'FYF DATA'!$A$1:$BR$670,24,FALSE) -> #N/A
A11: 3.060 | B11: Intergovernmental | C11: =VLOOKUP(B1,'FYF DATA'!$A$1:$BR$670,25,FALSE) -> #N/A
B12: Total Expenditures - Operational | C12: =SUM(C6:C11) -> #N/A | D12: =SUM(D6:D11) -> 0 | E12: =SUM(E6:E11) -> 0 | F12: =SUM(F6:F11) -> 0 | G12: =SUM(G6:G11) -> 0 | H12: =SUM(H6:H11) -> 0
A13: EXPENDITURES - DEBT SERVICE | C13: FY14 | D13: FY16 | E13: FY17 | F13: FY18 | G13: FY19 | H13: FY20
A14: 4.010 | B14: Debt Service-Principal-All (Historical Only) | C14: =VLOOKUP(B1,'FYF DATA'!$A$1:$BR$670,26,FALSE) -> #N/A
A15: 4.020 | B15: Debt Service-Principal-Notes | C15: =VLOOKUP($B$1,'FYF DATA'!$A$1:$BR$670,27,FALSE) -> #N/A
A16: 4.030 | B16: Debt Service-Principal-State Loans | C16: =VLOOKUP($B$1,'FYF DATA'!$A$1:$BR$670,28,FALSE) -> #N/A
A17: 4.040 | B17: Debt Service-Principal-State Advances | C17: =VLOOKUP($B$1,'FYF DATA'!$A$1:$BR$670,29,FALSE) -> #N/A
A18: 4.050 | B18: Debt Service-Principal-HB264 Loans | C18: =VLOOKUP($B$1,'FYF DATA'!$A$1:$BR$670,30,FALSE) -> #N/A
A19: 4.055 | B19: Debt Service-Principal-Other | C19: =VLOOKUP($B$1,'FYF DATA'!$A$1:$BR$670,31,FALSE) -> #N/A
A20: 4.060 | B20: Debt Service-Interest and Fiscal Charges | C20: =VLOOKUP($B$1,'FYF DATA'!$A$1:$BR$670,32,FALSE) -> #N/A
A21: 4.300 | B21: Debt Service-Other Objects | C21: =VLOOKUP($B$1,'FYF DATA'!$A$1:$BR$670,33,FALSE) -> #N/A
B22: Total Expenditures - Debt Service | C22: =SUM(C14:C21) -> #N/A | D22: =SUM(D14:D21) -> 0 | E22: =SUM(E14:E21) -> 0 | F22: =SUM(F14:F21) -> 0 | G22: =SUM(G14:G21) -> 0 | H22: =SUM(H14:H21) -> 0
A23: EXPENDITURES - NON-OPERATIONAL | C23: FY14 | D23: FY16 | E23: FY17 | F23: FY18 | G23: FY19 | H23: FY20
A24: 5.010 | B24: Operating Transfers-Out | C24: =VLOOKUP($B$1,'FYF DATA'!$A$1:$BR$670,35,FALSE) -> #N/A
A25: 5.020 | B25: Advances-Out | C25: =VLOOKUP($B$1,'FYF DATA'!$A$1:$BR$670,36,FALSE) -> #N/A
A26: 5.030 | B26: All Other Financing Uses | C26: =VLOOKUP($B$1,'FYF DATA'!$A$1:$BR$670,37,FALSE) -> #N/A
B27: Total Expenditures - Non-operational | C27: =SUM(C24:C26) -> #N/A | D27: =SUM(D24:D26) -> 0 | E27: =SUM(E24:E26) -> 0 | F27: =SUM(F24:F26) -> 0 | G27: =SUM(G24:G26) -> 0 | H27: =SUM(H24:H26) -> 0
A28: SUSTAINABILITY | C28: FY14 | D28: FY16 | E28: FY17 | F28: FY18 | G28: FY19 | H28: FY20
B29: TOTAL EXPENDITURES For FY16-20, total expenditures must be cost neutral (e.g. $0 or less) to prove sustainability. | C29: =(C12+C22+C27) -> #N/A | D29: =(D12+D22+D27) -> 0 | E29: =(E12+E22+E27) -> 0 | F29: =(F12+F22+F27) -> 0 | G29: =(G12+G22+G27) -> 0 | H29: =(H12+H22+H27) -> 0

Sheet Non-Traditional
A1: IRN (if applicable): | I1: APPLICANT:
A2: APPLICANT: | I2: =B2 -> 0
C3: FY14 | D3: FY16 | E3: FY17 | F3: FY18 | G3: FY19 | H3: FY20 | I3: EXPLAINATION
A4: Do not alter any of the shaded cells. | C4: Financial Baseline from the Current Fiscal Year | D4: Since FY15 is the grant year, its expenditures are not required in this table. In the FY16-FY20 columns, ADD only the SUSTAINING COSTS to the appropriate line items (refer to Question 15), and SUBTRACT only the SUSTAINING COST REDUCTIONS to the appropriate line items (refer to Questions 16 & 17). | I4: Explaination Provide detailed notes regarding the financial impact on each line affected by the grant funds. These notes are critical to the evaluation of the financial sustainability.
A5: EXPENDITURES | C5: FY14 | D5: FY16 | E5: FY17 | F5: FY18 | G5: FY19 | H5: FY20
A6: 100 | B6: Salaries and Wages
A7: 200 | B7: Employee Retirement and Insurance Benefits
A8: 400 | B8: Purchased Services
A9: 500 | B9: Supplies and Materials
A10: 600 | B10: Capital Outlay - New
A11: 700 | B11: Capital Outlay - Replacement
A12: 800 | B12: Other Operating Disbursements
A13: SUSTAINABILITY | C13: FY14 | D13: FY16 | E13: FY17 | F13: FY18 | G13: FY19 | H13: FY20
B14: TOTAL EXPENDITURES For FY16-20, total expenditures must be cost neutral (e.g. $0 or less) to prove sustainability. | C14: =SUM(C6:C12) -> 0 | D14: =SUM(D6:D12) -> 0 | E14: =SUM(E6:E12) -> 0 | F14: =SUM(F6:F12) -> 0 | G14: =SUM(G6:G12) -> 0 | H14: =SUM(H6:H12) -> 0

Sheet ESC
A1: IRN (if applicable): | I1: APPLICANT:
A2: APPLICANT: | I2: =B2 -> 0
C3: FY14 | D3: FY16 | E3: FY17 | F3: FY18 | G3: FY19 | H3: FY20 | I3: EXPLAINATION
A4: Do not alter any of the shaded cells. | C4: Financial Baseline from the Current Fiscal Year | D4: Since FY15 is the grant year, its expenditures are not required in this table. In the FY16-FY20 columns, ADD only the SUSTAINING COSTS to the appropriate line items (refer to Question 15), and SUBTRACT only the SUSTAINING COST REDUCTIONS to the appropriate line items (refer to Questions 16 & 17). | I4: Explaination Provide detailed notes regarding the financial impact on each line affected by the grant funds. These notes are critical to the evaluation of the financial sustainability.
A5: EXPENDITURES - OPERATIONAL | C5: FY14 | D5: FY16 | E5: FY17 | F5: FY18 | G5: FY19 | H5: FY20
A6: 3.010 | B6: Personal Services (Salaries & Wages)
A7: 3.020 | B7: Fringe Benefits
A8: 3.030 | B8: Purchased Services
A9: 3.040 | B9: Supplies and Materials
A10: 3.050 | B10: Capital Outlay
A11: 3.060 | B11: Intergovernmental
B12: Total Expenditures - Operational | C12: =SUM(C6:C11) -> 0 | D12: =SUM(D6:D11) -> 0 | E12: =SUM(E6:E11) -> 0 | F12: =SUM(F6:F11) -> 0 | G12: =SUM(G6:G11) -> 0 | H12: =SUM(H6:H11) -> 0
A13: EXPENDITURES - DEBT SERVICE | C13: FY14 | D13: FY16 | E13: FY17 | F13: FY18 | G13: FY19 | H13: FY20
A14: 4.010 | B14: Debt Service-Principal-All (Historical Only)
A15: 4.020 | B15: Debt Service-Principal-Notes
A16: 4.030 | B16: Debt Service-Principal-State Loans
A17: 4.040 | B17: Debt Service-Principal-State Advances
A18: 4.050 | B18: Debt Service-Principal-HB264 Loans
A19: 4.055 | B19: Debt Service-Principal-Other
A20: 4.060 | B20: Debt Service-Interest and Fiscal Charges
A21: 4.300 | B21: Debt Service-Other Objects
B22: Total Expenditures - Debt Service | C22: =SUM(C14:C21) -> 0 | D22: =SUM(D14:D21) -> 0 | E22: =SUM(E14:E21) -> 0 | F22: =SUM(F14:F21) -> 0 | G22: =SUM(G14:G21) -> 0 | H22: =SUM(H14:H21) -> 0
A23: EXPENDITURES - NON-OPERATIONAL | C23: FY14 | D23: FY16 | E23: FY17 | F23: FY18 | G23: FY19 | H23: FY20
A24: 5.010 | B24: Operating Transfers-Out
A25: 5.020 | B25: Advances-Out
A26: 5.030 | B26: All Other Financing Uses
B27: Total Expenditures - Non-operational | C27: =SUM(C24:C26) -> 0 | D27: =SUM(D24:D26) -> 0 | E27: =SUM(E24:E26) -> 0 | F27: =SUM(F24:F26) -> 0 | G27: =SUM(G24:G26) -> 0 | H27: =SUM(H24:H26) -> 0
A28: SUSTAINABILITY | C28: FY14 | D28: FY16 | E28: FY17 | F28: FY18 | G28: FY19 | H28: FY20
B29: TOTAL EXPENDITURES For FY16-20, total expenditures must be cost neutral (e.g. $0 or less) to prove sustainability. | C29: =(C12+C22+C27) -> 0 | D29: =(D12+D22+D27) -> 0 | E29: =(E12+E22+E27) -> 0 | F29: =(F12+F22+F27) -> 0 | G29: =(G12+G22+G27) -> 0 | H29: =(H12+H22+H27) -> 0

Sheet FYF DATA
A1: IRN | B1: DISTRICT | C1: County | D1: 1.01 | E1: 1.02 | F1: 1.03 | G1: 1.035 | H1: 1.04 | I1: 1.045 | J1: 1.05 | K1: 1.06 | L1: 1.07 | M1: 2.01 | N1: 2.02 | O1: 2.04 | P1: 2.05 | Q1: 2.06 | R1: 2.07 | S1: 2.08 | T1: 3.01 | U1: 3.02 | V1: 3.03 | W1: 3.04 | X1: 3.05 | Y1: 3.06 | Z1: 4.01 | AA1: 4.02 | AB1: 4.03 | AC1: 4.04 | AD1: 4.05 | AE1: 4.055 | AF1: 4.06 | AG1: 4.3 | AH1: 4.5 | AI1: 5.01 | AJ1: 5.02 | AK1: 5.03 | AL1: 5.04 | AM1: 5.05 | AN1: 6.01 | AO1: 7.01 | AP1: 7.02 | AQ1: 8.01 | AR1: 9.01 | AS1: 9.02 | AT1: 9.03 | AU1: 9.04 | AV1: 9.045 | AW1: 9.05 | AX1: 9.06 | AY1: 9.07 | AZ1: 9.08 | BA1: 10.01 | BB1: 11.01 | BC1: 11.02 | BD1: 11.3 | BE1: 12.01 | BF1: 13.01 | BG1: 13.02 | BH1: 13.03 | BI1: 14.01 | BJ1: 15.01 | BK1: 20.01 | BL1: 20.015 | BM1: 21.01 | BN1: 21.02 | BO1: 21.03 | BP1: 21.04 | BQ1: 21.05 | BR1: 21.06 | BS1: Grand Total
A2: 000442 | B2: Manchester Local SD | C2: Adams | D2: 2016765 | E2: 5048235 | F2: 0 | G2: 1563539 | H2: 28 | I2: 0 | J2: 2637787 | K2: 747032 | L2: 12013386 | M2: 0 | N2: 0 | O2: 0 | P2: 0 | Q2: 6436 | R2: 6436 | S2: 12019822 | T2: 4735233 | U2: 2157523 | V2: 2323141 | W2: 442627 | X2: 256968 | Y2: 0 | Z2: 0 | AA2: 0 | AB2: 0 | AC2: 0 | AD2: 30000 | AE2: 35793 | AF2: 21805 | AG2: 374534 | AH2: 10377624 | AI2: 2015739 | AJ2: 0 | AK2: 0 | AL2: 2015739 | AM2: 12393363 | AN2: -373541 | AO2: 5166670 | AP2: 4793129 | AQ2: 120000 | AR2: 0 | AS2: 0 | AT2: 0 | AU2: 0 | AV2: 0 | AW2: 0 | AX2: 0 | AY2: 0 | AZ2: 0 | BA2: 4673129 | BB2: 0 | BC2: 0 | BD2: 0 | BE2: 4673129 | BF2: 0 | BG2: 0 | BH2: 0 | BI2: 0 | BJ2: 4673129 | BK2: 0 | BL2: 0 | BM2: 0 | BN2: 0 | BO2: 0 | BP2: 0 | BQ2: 0 | BR2: 0 | BS2: 12393363
A3: 043489 | B3: Akron City SD | C3: Summit | D3: 103384602 | E3: 7465642 | F3: 0 | G3: 160156899 | H3: 3431385 | J3: 20488265 | K3: 11263678 | L3: 306190471 | M3: 0 | N3: 0 | O3: 32000 | R3: 32000 | S3: 306222471 | T3: 146483981 | U3: 64772763 | V3: 72432792 | W3: 9257816 | X3: 5807069 | Z3: 0 | AA3: 0 | AB3: 0 | AC3: 0 | AD3: 0 | AE3: 0 | AF3: 0 | AG3: 3450937 | AH3: 302205358 | AI3: 123500 | AK3: 0 | AM3: 302328858 | AO3: 13609028 | AP3: 17502641 | AQ3: 0 | AT3: 0 | AW3: 0 | AX3: 0 | AY3: 0 | BA3: 17502641 | BB3: 0 | BC3: 0 | BD3: 0 | BE3: 17502641 | BF3: 0 | BI3: 0 | BJ3: 17502641 | BK3: 2310 | BL3: 25009 | BS3: 306222471
A4: 043497 | B4: Alliance City SD | C4: Stark | D4: 6276000 | E4: 0 | F4: 0 | G4: 19330913 | H4: 184975 | I4: 0 | J4: 1072572 | K4: 1000000 | L4: 27864460 | M4: 0 | N4: 0 | O4: 0 | P4: 0 | Q4: 64433 | R4: 64433 | S4: 27928893 | T4: 15700000 | U4: 5700000 | V4: 5024592 | W4: 800000 | X4: 260000 | Y4: 0 | Z4: 165600 | AA4: 0 | AB4: 0 | AC4: 0 | AD4: 0 | AE4: 0 | AF4: 21970 | AG4: 304615 | AH4: 27976777 | AI4: 0 | AJ4: 0 | AK4: 0 | AL4: 0 | AM4: 27976777 | AN4: -47884 | AO4: 4735578 | AP4: 4687694 | AQ4: 0 | AR4: 0 | AS4: 0 | AT4: 0 | AU4: 0 | AV4: 0 | AW4: 0 | AX4: 0 | AY4: 0 | AZ4: 0 | BA4: 4687694 | BB4: 0 | BC4: 0 | BD4: 0 | BE4: 4687694 | BF4: 0 | BG4: 0 | BH4: 0 | BI4: 0 | BJ4: 4687694 | BK4: 238 | BL4: 2646 | BM4: 0 | BN4: 0 | BO4: 0 | BP4: 0 | BQ4: 0 | BR4: 0 | BS4: 27976777
A5: 043505 | B5: Ashland City SD | C5: Ashland | D5: 12974978 | E5: 1009592 | F5: 0 | G5: 10870284 | H5: 155831 | I5: 0 | J5: 3754952 | K5: 953026 | L5: 29718663 | M5: 0 | N5: 0 | O5: 0 | P5: 67423 | Q5: 0 | R5: 67423 | S5: 29786086 | T5: 15918018 | U5: 6856889 | V5: 5058002 | W5: 926966 | X5: 155143 | Y5: 0 | Z5: 0 | AA5: 0 | AB5: 0 | AC5: 0 | AD5: 250000 | AE5: 0 | AF5: 54590 | AG5: 426621 | AH5: 29646229 | AI5: 0 | AJ5: 67423 | AK5: 0 | AL5: 67423 | AM5: 29713652 | AN5: 72434 | AO5: 4539988 | AP5: 4612422 | AQ5: 195000 | AR5: 0 | AS5: 0 | AT5: 0 | AU5: 0 | AV5: 0 | AW5: 0 | AX5: 0 | AY5: 0 | AZ5: 0 | BA5: 4417422 | BB5: 0 | BC5: 0 | BD5: 0 | BE5: 4417422 | BF5: 0 | BG5: 0 | BH5: 0 | BI5: 0 | BJ5: 4417422 | BM5: 0 | BN5: 0 | BO5: 0 | BP5: 0 | BQ5: 0 | BR5: 0 | BS5: 29786086
A6: 043513 | B6: Ashtabula Area City SD | C6: Ashtabula | D6: 7841869 | E6: 1193945 | F6: 0 | G6: 23559062 | H6: 40414 | I6: 0 | J6: 1253343 | K6: 791865 | L6: 34680498 | M6: 0 | N6: 0 | O6: 0 | P6: 48812 | Q6: 25000 | R6: 73812 | S6: 34754310 | T6: 16754138 | U6: 7524351 | V6: 8779688 | W6: 639845 | X6: 8384 | Y6: 0 | Z6: 0 | AA6: 0 | AB6: 0 | AC6: 0 | AD6: 0 | AE6: 0 | AF6: 0 | AG6: 485518 | AH6: 34191924 | AI6: 28000 | AJ6: 350000 | AK6: 0 | AL6: 378000 | AM6: 34569924 | AN6: 184386 | AO6: 1696227 | AP6: 1880613 | AQ6: 250000 | AR6: 0 | AS6: 0 | AT6: 0 | AU6: 0 | AV6: 0 | AW6: 0 | AX6: 0 | AY6: 0 | AZ6: 0 | BA6: 1630613 | BB6: 0 | BC6: 0 | BD6: 0 | BE6: 1630613 | BF6: 0 | BG6: 0 | BH6: 0 | BI6: 0 | BJ6: 1630613 | BM6: 0 | BN6: 0 | BO6: 0 | BP6: 0 | BQ6: 0 | BR6: 0 | BS6: 34754310
A7: 043521 | B7: Athens City SD | C7: Athens | D7: 12044555 | E7: 1586424 | F7: 3598377 | G7: 7964397 | H7: 50034 | I7: 0 | J7: 1487710 | K7: 2901725 | L7: 29633222 | M7: 0 | N7: 0 | O7: 0 | P7: 0 | Q7: 93701 | R7: 93701 | S7: 29726923 | T7: 17491784 | U7: 7711897 | V7: 3463939 | W7: 663286 | X7: 10609 | Y7: 0 | Z7: 0 | AA7: 0 | AB7: 0 | AC7: 0 | AD7: 0 | AE7: 0 | AF7: 0 | AG7: 504631 | AH7: 29846146 | AI7: 10000 | AJ7: 50000 | AK7: 300000 | AL7: 360000 | AM7: 30206146 | AN7: -479223 | AO7: 7653620 | AP7: 7174397 | AQ7: 0 | AR7: 0 | AS7: 0 | AT7: 0 | AU7: 0 | AV7: 0 | AW7: 0 | AX7: 0 | AY7: 0 | AZ7: 0 | BA7: 7174397 | BB7: 0 | BC7: 0 | BD7: 0 | BE7: 7174397 | BF7: 0 | BG7: 0 | BH7: 0 | BI7: 0 | BJ7: 7174397 | BM7: 0 | BN7: 0 | BO7: 0 | BP7: 0 | BQ7: 0 | BR7: 0 | BS7: 30206146
A8: 043539 | B8: Barberton City SD | C8: Summit | D8: 11008889 | E8: 560748 | F8: 0 | G8: 22105032 | H8: 448607 | I8: 0 | J8: 2285107 | K8: 2621538 | L8: 39029921 | M8: 0 | N8: 0 | O8: 0 | P8: 0 | Q8: 250000 | R8: 250000 | S8: 39279921 | T8: 20067331 | U8: 8313788 | V8: 8261402 | W8: 749294 | X8: 56417 | Y8: 0 | Z8: 0 | AA8: 0 | AB8: 0 | AC8: 0 | AD8: 0 | AE8: 0 | AF8: 0 | AG8: 368133 | AH8: 37816365 | AI8: 0 | AJ8: 0 | AK8: 0 | AL8: 0 | AM8: 37816365 | AN8: 1463556 | AO8: 4754414 | AP8: 6217970 | AQ8: 500000 | AR8: 0 | AS8: 0 | AT8: 0 | AU8: 0 | AV8: 0 | AW8: 0 | AX8: 0 | AY8: 0 | AZ8: 0 | BA8: 5717970 | BB8: 0 | BC8: 0 | BD8: 0 | BE8: 5717970 | BF8: 0 | BG8: 0 | BH8: 0 | BI8: 0 | BJ8: 5717970 | BM8: 0 | BN8: 0 | BO8: 0 | BP8: 0 | BQ8: 0 | BR8: 0 | BS8: 39279921
A9: 043547 | B9: Bay Village City SD | C9: Cuyahoga | D9: 21427917 | E9: 819124 | F9: 0 | G9: 4052122 | H9: 139519 | I9: 0 | J9: 3465154 | K9: 357992 | L9: 30261828 | M9: 0 | N9: 0 | O9: 50000 | P9: 0 | Q9: 0 | R9: 50000 | S9: 30311828 | T9: 18744506 | U9: 6421399 | V9: 3094942 | W9: 1062787 | X9: 532354 | Y9: 0 | Z9: 0 | AA9: 159500 | AB9: 0 | AC9: 0 | AD9: 0 | AE9: 0 | AF9: 88162 | AG9: 433292 | AH9: 30536942 | AI9: 0 | AJ9: 0 | AK9: 250000 | AL9: 250000 | AM9: 30786942 | AN9: -475114 | AO9: 9217454 | AP9: 8742340 | AQ9: 200000 | AR9: 0 | AS9: 0 | AT9: 0 | AU9: 0 | AV9: 0 | AW9: 0 | AX9: 0 | AY9: 0 | AZ9: 0 | BA9: 8542340 | BB9: 0 | BC9: 0 | BD9: 0 | BE9: 8542340 | BF9: 0 | BG9: 0 | BH9: 0 | BI9: 0 | BJ9: 8542340 | BM9: 0 | BN9: 0 | BO9: 0 | BP9: 0 | BQ9: 0 | BR9: 0 | BS9: 30786942
A10: 043554 | B10: Beachwood City SD | C10: Cuyahoga | D10: 24715866 | E10: 3846 | F10: 0 | G10: 1037797 | H10: 100000 | I10: 0 | J10: 4248645 | K10: 3113844 | L10: 33219999 | M10: 0 | N10: 0 | O10: 0 | P10: 0 | Q10: 2500 | R10: 2500 | S10: 33222499 | T10: 18353780 | U10: 6299606 | V10: 4730740 | W10: 1078878 | X10: 972741 | Y10: 0 | Z10: 0 | AA10: 0 | AB10: 0 | AC10: 0 | AD10: 0 | AE10: 0 | AF10: 0 | AG10: 546116 | AH10: 31981860 | AI10: 801566 | AJ10: 0 | AK10: 0 | AL10: 801566 | AM10: 32783426 | AN10: 439072 | AO10: 18918953 | AP10: 19358025 | AQ10: 300000 | AR10: 0 | AS10: 0 | AT10: 134873 | AU10: 0 | AW10: 0 | AX10: 0 | AY10: 0 | AZ10: 134873 | BA10: 18923152 | BB10: 0 | BC10: 0 | BD10: 0 | BE10: 18923152 | BF10: 0 | BG10: 0 | BH10: 0 | BI10: 0 | BJ10: 18923152 | BK10: 85 | BL10: 1536 | BS10: 33222499
A11: 043562 | B11: Bedford City SD | C11: Cuyahoga | D11: 24500915 | E11: 2576436 | F11: 0 | G11: 6548130 | H11: 126491 | I11: 0 | J11: 8647318 | K11: 1882156 | L11: 44281446 | M11: 0 | N11: 0 | O11: 0 | P11: 1500000 | Q11: 100000 | R11: 1600000 | S11: 45881446 | T11: 25528989 | U11: 9337008 | V11: 8120005 | W11: 1553994 | X11: 963125 | Y11: 0 | Z11: 0 | AA11: 68644 | AB11: 0 | AC11: 0 | AD11: 230515 | AE11: 102807 | AF11: 96069 | AG11: 792730 | AH11: 46793886 | AI11: 422700 | AJ11: 1000000 | AK11: 0 | AL11: 1422700 | AM11: 48216586 | AN11: -2335140 | AO11: 16019872 | AP11: 13684732 | AQ11: 750000 | AR11: 0 | AS11: 0 | AT11: 0 | AU11: 0 | AV11: 0 | AW11: 0 | AX11: 0 | AY11: 0 | AZ11: 0 | BA11: 12934732 | BB11: 0 | BC11: 0 | BD11: 0 | BE11: 12934732 | BF11: 0 | BG11: 0 | BH11: 0 | BI11: 0 | BJ11: 12934732 | BM11: 0 | BN11: 0 | BO11: 0 | BP11: 0 | BQ11: 0 | BR11: 0 | BS11: 48216586
A12: 043570 | B12: Bellaire Local SD | C12: Belmont | D12: 2110000 | E12: 0 | F12: 0 | G12: 9207000 | H12: 26000 | I12: 0 | J12: 351000 | K12: 1010000 | L12: 12704000 | M12: 0 | N12: 0 | O12: 0 | P12: 0 | Q12: 0 | R12: 0 | S12: 12704000 | T12: 5150000 | U12: 2712000 | V12: 2250000 | W12: 435000 | X12: 300000 | Y12: 0 | Z12: 0 | AA12: 0 | AB12: 0 | AC12: 887500 | AD12: 0 | AE12: 0 | AF12: 0 | AG12: 236640 | AH12: 11971140 | AI12: 0 | AJ12: 0 | AK12: 0 | AL12: 0 | AM12: 11971140 | AN12: 732860 | AO12: 381000 | AP12: 1113860 | AQ12: 150000 | AR12: 0 | AS12: 0 | AT12: 0 | AU12: 0 | AV12: 0 | AW12: 0 | AX12: 0 | AY12: 0 | AZ12: 0 | BA12: 963860 | BB12: 0 | BC12: 0 | BD12: 0 | BE12: 963860 | BF12: 0 | BG12: 0 | BH12: 0 | BI12: 0 | BJ12: 963860 | BK12: 0 | BL12: 0 | BM12: 0 | BN12: 0 | BO12: 0 | BP12: 0 | BQ12: 0 | BR12: 0 | BS12: 12704000
A13: 043588 | B13: Bellefontaine City SD | C13: Logan | D13: 6696000 | E13: 0 | F13: 0 | G13: 13022169 | H13: 42900 | I13: 0 | J13: 1205392 | K13: 1249000 | L13: 22215461 | M13: 0 | N13: 0 | O13: 0 | P13: 0 | Q13: 0 | R13: 0 | S13: 22215461 | T13: 12595348 | U13: 5059216 | V13: 3377355 | W13: 489721 | X13: 123235 | Y13: 0 | Z13: 0 | AA13: 0 | AB13: 0 | AC13: 0 | AD13: 0 | AE13: 0 | AF13: 0 | AG13: 356472 | AH13: 22001347 | AI13: 50000 | AJ13: 0 | AK13: 0 | AL13: 50000 | AM13: 22051347 | AN13: 164114 | AO13: 7422784 | AP13: 7586898 | AQ13: 42000 | AR13: 225904 | AS13: 0 | AT13: 198858 | AU13: 0 | AV13: 0 | AW13: 0 | AX13: 0 | AY13: 0 | AZ13: 424762 | BA13: 7120136 | BB13: 0 | BC13: 0 | BD13: 0 | BE13: 7120136 | BF13: 0 | BG13: 0 | BH13: 0 | BI13: 0 | BJ13: 7120136 | BK13: 213 | BL13: 2430 | BM13: 0 | BN13: 0 | BO13: 0 | BP13: 0 | BQ13: 0 | BR13: 0 | BS13: 22215461
A14: 043596 | B14: Bellevue City SD | C14: Huron | D14: 6475000 | E14: 0 | F14: 1287000 | G14: 9274984 | H14: 110000 | I14: 0 | J14: 1265857 | K14: 609400 | L14: 19022241 | M14: 0 | N14: 0 | O14: 0 | P14: 204241 | Q14: 69355 | R14: 273596 | S14: 19295837 | T14: 10642833 | U14: 3916225 | V14: 3636585 | W14: 812993 | X14: 91340 | Y14: 0 | Z14: 0 | AA14: 0 | AB14: 0 | AC14: 0 | AD14: 69116 | AE14: 0 | AF14: 4090 | AG14: 285255 | AH14: 19458437 | AI14: 10794 | AJ14: 200000 | AK14: 12000 | AL14: 222794 | AM14: 19681231 | AN14: -385394 | AO14: 5406471 | AP14: 5021077 | AQ14: 0 | AR14: 0 | AS14: 0 | AT14: 0 | AU14: 0 | AV14: 0 | AW14: 0 | AX14: 0 | AY14: 0 | AZ14: 0 | BA14: 5021077 | BB14: 0 | BC14: 0 | BD14: 0 | BE14: 5021077 | BF14: 0 | BG14: 0 | BH14: 0 | BI14: 0 | BJ14: 5021077 | BK14: 164 | BL14: 1871 | BM14: 0 | BN14: 0 | BO14: 0 | BP14: 0 | BQ14: 0 | BR14: 0 | BS14: 19681231
A15: 043604 | B15: Belpre City SD | C15: Washington | D15: 3099927 | E15: 244927 | F15: 0 | G15: 2680478 | H15: 1149 | I15: 0 | J15: 2696763 | K15: 650578 | L15: 9373822 | M15: 0 | N15: 0 | O15: 0 | P15: 93266 | Q15: 10000 | R15: 103266 | S15: 9477088 | T15: 4709580 | U15: 2221070 | V15: 2129356 | W15: 389726 | X15: 252448 | Y15: 0 | Z15: 0 | AA15: 0 | AB15: 0 | AC15: 0 | AD15: 0 | AE15: 0 | AF15: 11924 | AG15: 172306 | AH15: 9886410 | AI15: 10000 | AJ15: 3000 | AK15: 0 | AL15: 13000 | AM15: 9899410 | AN15: -422322 | AO15: 1387376 | AP15: 965054 | AQ15: 125000 | AR15: 0 | AS15: 0 | AT15: 299082 | AU15: 0 | AV15: 0 | AW15: 0 | AX15: 0 | AY15: 5944 | AZ15: 305026 | BA15: 535028 | BB15: 0 | BC15: 0 | BD15: 0 | BE15: 535028 | BF15: 0 | BG15: 0 | BH15: 0 | BI15: 0 | BJ15: 535028 | BM15: 0 | BN15: 0 | BO15: 0 | BP15: 0 | BQ15: 0 | BR15: 0 | BS15: 9899410
A16: 043612 | B16: Berea City SD | C16: Cuyahoga | D16: 50974997 | E16: 2395966 | F16: 0 | G16: 8150147 | H16: 141039 | I16: 0 | J16: 14951352 | K16: 4219051 | L16: 80832552 | M16: 0 | N16: 0 | O16: 0 | P16: 160004 | Q16: 0 | R16: 160004 | S16: 80992556 | T16: 44394291 | U16: 22816619 | V16: 9801372 | W16: 2039769 | X16: 276715 | Y16: 0 | Z16: 0 | AA16: 0 | AB16: 0 | AC16: 0 | AD16: 0 | AE16: 525000 | AF16: 1171995 | AG16: 609358 | AH16: 81635119 | AI16: 200000 | AJ16: 160000 | AK16: 0 | AL16: 360000 | AM16: 81995119 | AN16: -1002564 | AO16: 2221730 | AP16: 1219166 | AQ16: 0 | AR16: 0 | AS16: 0 | AT16: 0 | AU16: 0 | AV16: 0 | AW16: 0 | AX16: 0 | AY16: 0 | AZ16: 0 | BA16: 1219166 | BB16: 0 | BC16: 0 | BD16: 0 | BE16: 1219166 | BF16: 0 | BG16: 0 | BH16: 0 | BI16: 0 | BJ16: 1219166 | BM16: 0 | BN16: 0 | BO16: 0 | BP16: 0 | BQ16: 0 | BR16: 0 | BS16: 81995119
A17: 043620 | B17: Bexley City SD | C17: Franklin | D17: 19933000 | E17: 0 | F17: 6300000 | G17: 3950000 | I17: 0 | J17: 2760000 | K17: 280000 | L17: 33223000 | M17: 0 | P17: 38456 | Q17: 20000 | R17: 58456 | T17: 18340000 | U17: 7030000 | V17: 4520000 | W17: 1364000 | X17: 676000 | AG17: 570000 | AH17: 32500000 | AI17: 362921 | AJ17: 50000 | AL17: 414721 | AM17: 32914721 | AN17: 366735 | AO17: 21029924 | AP17: 21396659 | AQ17: 1000000 | AX17: 1900000 | AZ17: 1900000 | BA17: 18496659 | BE17: 18496659 | BJ17: 18496659 | BK17: 163 | BL17: 1992 | BO17: 0 | BP17: 0 | BQ17: 0 | BR17: 0 | BS17: 33223000
A18: 043638 | B18: Bowling Green City SD | C18: Wood | D18: 15469104 | E18: 0 | F18: 2958531 | G18: 6882599 | H18: 167011 | I18: 0 | J18: 3207838 | K18: 443000 | L18: 29128083 | M18: 0 | N18: 0 | O18: 0 | P18: 0 | Q18: 0 | R18: 0 | S18: 29128083 | T18: 16854639 | U18: 6737199 | V18: 3879400 | W18: 1307800 | X18: 210000 | Y18: 0 | Z18: 0 | AA18: 0 | AB18: 0 | AC18: 0 | AD18: 0 | AE18: 0 | AF18: 0 | AG18: 1260450 | AH18: 30249488 | AI18: 301000 | AJ18: 0 | AK18: 0 | AL18: 301000 | AM18: 30550488 | AN18: -1422405 | AO18: 5320157 | AP18: 3897752 | AQ18: 55000 | AR18: 0 | AS18: 0 | AT18: 500000 | AU18: 0 | AV18: 0 | AW18: 0 | AX18: 0 | AY18: 0 | AZ18: 500000 | BA18: 3342752 | BB18: 0 | BC18: 0 | BD18: 0 | BE18: 3342752 | BF18: 0 | BG18: 0 | BH18: 0 | BI18: 0 | BJ18: 3342752 | BM18: 11240 | BN18: 3406 | BO18: 0 | BP18: 0 | BQ18: 0 | BR18: 14646 | BS18: 30550488
A19: 043646 | B19: Brecksville-Broadview Heights City SD | C19: Cuyahoga | D19: 30394054 | E19: 1802360 | F19: 0 | G19: 5223756 | H19: 105262 | I19: 0 | J19: 5751285 | K19: 1577134 | L19: 44853851 | M19: 0 | N19: 0 | O19: 0 | P19: 110000 | Q19: 95521 | R19: 205521 | S19: 45059372 | T19: 29985681 | U19: 9305318 | V19: 4406144 | W19: 1186851 | X19: 257334 | Y19: 0 | Z19: 0 | AA19: 0 | AB19: 0 | AC19: 0 | AD19: 323005 | AE19: 0 | AF19: 3230 | AG19: 815223 | AH19: 46282786 | AI19: 75960 | AJ19: 110000 | AK19: 0 | AL19: 185960 | AM19: 46468746 | AN19: -1409374 | AO19: 10256825 | AP19: 8847451 | AQ19: 272371 | AR19: 0 | AS19: 0 | AT19: 0 | AU19: 0 | AV19: 0 | AW19: 0 | AX19: 0 | AY19: 0 | AZ19: 0 | BA19: 8575080 | BB19: 0 | BC19: 0 | BD19: 0 | BE19: 8575080 | BF19: 0 | BG19: 0 | BH19: 0 | BI19: 0 | BJ19: 8575080 | BM19: 0 | BN19: 0 | BO19: 0 | BP19: 0 | BQ19: 0 | BR19: 0 | BS19: 46468746
A20: 043653 | B20: Brooklyn City SD | C20: Cuyahoga | D20: 9284567 | E20: 900808 | F20: 0 | G20: 760000 | H20: 0 | I20: 0 | J20: 2101607 | K20: 575000 | L20: 13621982 | M20: 0 | N20: 0 | O20: 0 | P20: 351740 | Q20: 0 | R20: 351740 | S20: 13973722 | T20: 9040181 | U20: 2983260 | V20: 2644216 | W20: 245245 | X20: 50000 | Y20: 0 | Z20: 0 | AA20: 0 | AB20: 0 | AC20: 0 | AD20: 0 | AE20: 0 | AF20: 0 | AG20: 400000 | AH20: 15362902 | AI20: 0 | AJ20: 0 | AK20: 0 | AL20: 0 | AM20: 15362902 | AN20: -1389180 | AO20: 2569336 | AP20: 1180156 | AQ20: 0 | AR20: 0 | AS20: 0 | AT20: 0 | AU20: 0 | AV20: 0 | AW20: 0 | AX20: 0 | AY20: 0 | AZ20: 0 | BA20: 1180156 | BB20: 0 | BC20: 1127000 | BD20: 1127000 | BE20: 2307156 | BF20: 0 | BG20: 0 | BH20: 0 | BI20: 0 | BJ20: 2307156 | BM20: 0 | BN20: 0 | BO20: 0 | BP20: 0 | BQ20: 0 | BR20: 0 | BS20: 15362902
A21: 043661 | B21: Brunswick City SD | C21: Medina | D21: 32169823 | E21: 992411 | F21: 0 | G21: 22129000 | H21: 72000 | I21: 102000 | J21: 4928693 | K21: 1212500 | L21: 61606427 | M21: 0 | N21: 0 | O21: 0 | P21: 900000 | Q21: 0 | R21: 900000 | S21: 62506427 | T21: 39600000 | U21: 15648000 | V21: 6036198 | W21: 2732160 | X21: 245270 | Y21: 0 | Z21: 0 | AA21: 0 | AB21: 0 | AC21: 0 | AD21: 0 | AE21: 60865 | AF21: 16263 | AG21: 1098391 | AH21: 65437147 | AI21: 0 | AJ21: 0 | AK21: 0 | AL21: 0 | AM21: 65437146 | AN21: -2930719 | AO21: 4080689 | AP21: 1149970 | AQ21: 922226 | AR21: 0 | AS21: 0 | AT21: 0 | AU21: 0 | AW21: 0 | AX21: 0 | AY21: 0 | AZ21: 0 | BA21: 227744 | BB21: 0 | BC21: 0 | BD21: 0 | BE21: 227744 | BF21: 0 | BG21: 2478000 | BH21: 2478000 | BI21: 0 | BJ21: 2705744 | BS21: 65437147
A22: 043679 | B22: Bryan City SD | C22: Williams | D22: 6400000 | E22: 0 | F22: 2825000 | G22: 5609000 | H22: 38500 | I22: 0 | J22: 2338000 | K22: 1263800 | L22: 18474300 | M22: 0 | N22: 0 | O22: 0 | P22: 0 | Q22: 2000 | R22: 2000 | S22: 18476300 | T22: 11391255 | U22: 4257453 | V22: 2392776 | W22: 500619 | X22: 0 | Y22: 0 | Z22: 0 | AA22: 0 | AB22: 0 | AC22: 0 | AD22: 0 | AE22: 0 | AF22: 0 | AG22: 256465 | AH22: 18798568 | AI22: 157185 | AJ22: 0 | AK22: 0 | AL22: 157185 | AM22: 18955753 | AN22: -479453 | AO22: 9689298 | AP22: 9209845 | AQ22: 100000 | AR22: 0 | AS22: 0 | AT22: 0 | AU22: 0 | AV22: 0 | AW22: 0 | AX22: 0 | AY22: 0 | AZ22: 0 | BA22: 9109845 | BB22: 0 | BC22: 0 | BD22: 0 | BE22: 9109845 | BF22: 0 | BG22: 0 | BH22: 0 | BI22: 0 | BJ22: 9109845 | BK22: 180 | BL22: 1820 | BM22: 0 | BN22: 0 | BO22: 0 | BP22: 0 | BQ22: 0 | BR22: 0 | BS22: 18955753
A23: 043687 | B23: Bucyrus City SD | C23: Crawford | D23: 3441014 | E23: 367687 | F23: 0 | G23: 8941326 | H23: 44074 | I23: 0 | J23: 808315 | K23: 741147 | L23: 14343563 | M23: 0 | N23: 0 | O23: 0 | P23: 0 | Q23: 9700 | R23: 9700 | S23: 14353263 | T23: 7108167 | U23: 3104105 | V23: 3848256 | W23: 218874 | X23: 13430 | Y23: 0 | Z23: 0 | AA23: 0 | AB23: 0 | AC23: 0 | AD23: 0 | AE23: 0 | AF23: 0 | AG23: 224406 | AH23: 14517238 | AI23: 25000 | AJ23: 0 | AK23: 0 | AL23: 25000 | AM23: 14542238 | AN23: -188975 | AO23: 4372247 | AP23: 4183272 | AQ23: 100000 | AR23: 0 | AS23: 0 | AT23: 0 | AU23: 0 | AV23: 0 | AW23: 0 | AX23: 0 | AY23: 0 | AZ23: 0 | BA23: 4083272 | BB23: 0 | BC23: 0 | BD23: 0 | BE23: 4083272 | BF23: 0 | BG23: 0 | BH23: 0 | BI23: 0 | BJ23: 4083272 | BS23: 14542238
A24: 043695 | B24: Cambridge City SD | C24: Guernsey | D24: 4778699 | E24: 738456 | F24: 0 | G24: 13297382 | H24: 24856 | I24: 0 | J24: 841480 | K24: 1026516 | L24: 20707389 | M24: 0 | N24: 0 | O24: 0 | P24: 0 | Q24: 51484 | R24: 51484 | S24: 20758873 | T24: 10565722 | U24: 5141650 | V24: 3921407 | W24: 677263 | X24: 125333 | Y24: 0 | Z24: 0 | AA24: 0 | AB24: 0 | AC24: 0 | AD24: 0 | AE24: 0 | AF24: 0 | AG24: 446520 | AH24: 20877895 | AI24: 0 | AJ24: 0 | AK24: 0 | AL24: 0 | AM24: 20877895 | AN24: -119022 | AO24: 1327072 | AP24: 1208050 | AQ24: 500000 | AR24: 0 | AS24: 0 | AT24: 0 | AU24: 0 | AV24: 0 | AW24: 0 | AX24: 0 | AY24: 0 | AZ24: 0 | BA24: 708050 | BB24: 0 | BC24: 0 | BD24: 0 | BE24: 708050 | BF24: 0 | BG24: 0 | BH24: 0 | BI24: 0 | BJ24: 708050 | BM24: 0 | BN24: 0 | BO24: 0 | BP24: 0 | BQ24: 0 | BR24: 0 | BS24: 20877895
A25: 043703 | B25: Campbell City SD | C25: Mahoning | D25: 1846781 | E25: 0 | F25: 0 | G25: 10706030 | H25: 84256 | I25: 0 | J25: 504346 | K25: 300000 | L25: 13441413 | M25: 0 | N25: 0 | O25: 0 | P25: 39984 | Q25: 0 | R25: 39984 | S25: 13481397 | T25: 7416222 | U25: 2644403 | V25: 2783064 | W25: 303556 | X25: 0 | Y25: 0 | Z25: 0 | AA25: 0 | AB25: 0 | AC25: 0 | AD25: 0 | AE25: 144000 | AF25: 92711 | AG25: 79857 | AH25: 13463813 | AI25: 0 | AJ25: 30000 | AK25: 0 | AL25: 30000 | AM25: 13493813 | AN25: -12416 | AO25: 308684 | AP25: 296268 | AQ25: 20000 | AR25: 0 | AS25: 0 | AT25: 0 | AU25: 0 | AV25: 0 | AW25: 0 | AX25: 0 | AY25: 0 | AZ25: 0 | BA25: 276268 | BB25: 0 | BC25: 0 | BD25: 0 | BE25: 276268 | BF25: 0 | BG25: 0 | BH25: 0 | BI25: 0 | BJ25: 276268 | BK25: 106 | BL25: 1138 | BM25: 0 | BN25: 0 | BO25: 0 | BP25: 0 | BQ25: 0 | BR25: 0 | BS25: 13493813
A26: 043711 | B26: Canton City SD | C26: Stark | D26: 20500000 | E26: 3098350 | F26: 0 | G26: 70844928 | H26: 1067166 | I26: 0 | J26: 6336410 | K26: 1800000 | L26: 103646854 | M26: 0 | N26: 0 | O26: 0 | P26: 0 | Q26: 400000 | R26: 400000 | S26: 104046854 | T26: 59498881 | U26: 22751165 | V26: 22000000 | W26: 3000000 | X26: 1200000 | Y26: 0 | Z26: 0 | AA26: 0 | AB26: 0 | AC26: 0 | AD26: 0 | AE26: 0 | AF26: 0 | AG26: 750000 | AH26: 109200046 | AI26: 1350000 | AJ26: 0 | AK26: 20000 | AL26: 1370000 | AM26: 110570046 | AN26: -6523192 | AO26: 14142407 | AP26: 7619215 | AQ26: 2700000 | AR26: 0 | AS26: 0 | AT26: 0 | AU26: 0 | AV26: 0 | AW26: 0 | AX26: 0 | AY26: 0 | AZ26: 0 | BA26: 4919215 | BB26: 0 | BC26: 0 | BD26: 0 | BE26: 4919215 | BF26: 0 | BG26: 0 | BH26: 0 | BI26: 0 | BJ26: 4919215 | BK26: 0 | BL26: 0 | BM26: 0 | BN26: 0 | BO26: 0 | BP26: 0 | BQ26: 0 | BR26: 0 | BS26: 110570046
A27: 043729 | B27: Celina City SD | C27: Mercer | D27: 10577176 | E27: 302221 | F27: 2296746 | G27: 10313686 | H27: 126075 | I27: 0 | J27: 1629575 | K27: 1645569 | L27: 26891048 | M27: 0 | N27: 0 | O27: 0 | P27: 771500 | Q27: 50000 | R27: 821500 | S27: 27712548 | T27: 14877336 | U27: 7162534 | V27: 3988241 | W27: 940640 | X27: 304806 | Y27: 0 | Z27: 0 | AA27: 0 | AB27: 0 | AC27: 0 | AD27: 0 | AE27: 0 | AF27: 0 | AG27: 452284 | AH27: 27725841 | AI27: 25000 | AJ27: 400000 | AK27: 25000 | AL27: 450000 | AM27: 28175841 | AN27: -463293 | AO27: 6838984 | AP27: 6375691 | AQ27: 0 | AR27: 0 | AS27: 0 | AT27: 0 | AU27: 0 | AV27: 0 | AW27: 0 | AX27: 0 | AY27: 0 | AZ27: 0 | BA27: 6375691 | BB27: 0 | BC27: 0 | BD27: 0 | BE27: 6375691 | BF27: 0 | BG27: 0 | BH27: 0 | BI27: 0 | BJ27: 6375691 | BK27: 196 | BL27: 2469 | BM27: 0 | BN27: 0 | BO27: 0 | BP27: 0 | BQ27: 0 | BR27: 0 | BS27: 28175841
A28: 043737 | B28: Centerville City SD | C28: Montgomery | D28: 55500000 | E28: 2100000 | F28: 0 | G28: 11213500 | H28: 186500 | I28: 261184 | J28: 8000000 | K28: 3400000 | L28: 80661184 | M28: 0 | N28: 0 | O28: 0 | P28: 0 | Q28: 0 | R28: 0 | S28: 80661184 | T28: 52988332 | U28: 24982713 | V28: 4938643 | W28: 2157189 | X28: 66500 | Y28: 0 | Z28: 0 | AA28: 0 | AB28: 0 | AC28: 0 | AD28: 0 | AE28: 0 | AF28: 0 | AG28: 800000 | AH28: 85933377 | AI28: 0 | AJ28: 0 | AK28: 0 | AL28: 0 | AM28: 85933377 | AN28: -5272193 | AO28: 15903864 | AP28: 10631671 | AQ28: 400000 | AR28: 0 | AS28: 0 | AT28: 0 | AU28: 0 | AV28: 0 | AW28: 0 | AX28: 0 | AY28: 0 | AZ28: 0 | BA28: 10231671 | BB28: 0 | BC28: 4631750 | BD28: 4631750 | BE28: 14863421 | BF28: 0 | BG28: 0 | BH28: 0 | BI28: 0 | BJ28: 14863421 | BK28: 0 | BL28: 0 | BM28: 0 | BN28: 0 | BO28: 0 | BP28: 0 | BQ28: 0 | BR28: 0 | BS28: 85933377
A29: 043745 | B29: Chillicothe City SD | C29: Ross | D29: 9851977 | E29: 1100124 | F29: 0 | G29: 11616217 | H29: 0 | I29: 0 | J29: 3824076 | K29: 1533984 | L29: 27926378 | M29: 0 | N29: 0 | O29: 0 | P29: 606 | Q29: 95299 | R29: 95905 | S29: 28022283 | T29: 13014047 | U29: 5820896 | V29: 6373321 | W29: 426348 | X29: 0 | Y29: 0 | Z29: 0 | AA29: 0 | AB29: 0 | AC29: 0 | AD29: 0 | AE29: 0 | AF29: 0 | AG29: 521399 | AH29: 26156011 | AI29: 2000000 | AJ29: 0 | AK29: 0 | AL29: 2000000 | AM29: 28156011 | AN29: -133728 | AO29: 2525688 | AP29: 2391960 | AQ29: 150000 | AR29: 0 | AS29: 0 | AT29: 0 | AU29: 0 | AV29: 0 | AW29: 0 | AX29: 0 | AY29: 0 | AZ29: 0 | BA29: 2241960 | BB29: 0 | BC29: 0 | BD29: 0 | BE29: 2241960 | BF29: 0 | BG29: 0 | BH29: 0 | BI29: 0 | BJ29: 2241960 | BK29: 230 | BL29: 2616 | BM29: 0 | BN29: 0 | BO29: 0 | BP29: 0 | BQ29: 0 | BR29: 0 | BS29: 28156011
A30: 043752 | B30: Cincinnati City SD | C30: Hamilton | D30: 224722049 | E30: 22221945 | F30: 0 | G30: 155346931 | H30: 1082347 | I30: 0 | J30: 35698761 | K30: 10744412 | L30: 449816445 | M30: 0 | N30: 0 | O30: 0 | P30: 24346567 | Q30: 3500000 | R30: 27846567 | S30: 477663012 | T30: 192380454 | U30: 75504424 | V30: 167981228 | W30: 7422292 | X30: 3804847 | Y30: 0 | Z30: 0 | AA30: 0 | AB30: 0 | AC30: 0 | AD30: 2183072 | AE30: 4455000 | AF30: 5435236 | AG30: 6057690 | AH30: 465224243 | AI30: 18085480 | AJ30: 12500000 | AK30: 0 | AL30: 30585480 | AM30: 495809723 | AN30: -18146711 | AO30: 56898627 | AP30: 38751916 | AQ30: 12500000 | AR30: 0 | AS30: 0 | AT30: 0 | AU30: 0 | AV30: 0 | AW30: 0 | AX30: 0 | AY30: 0 | AZ30: 0 | BA30: 26251916 | BB30: 0 | BC30: 0 | BD30: 0 | BE30: 26251916 | BF30: 0 | BG30: 0 | BH30: 0 | BI30: 0 | BJ30: 26251916 | BS30: 495809723
A31: 043760 | B31: Circleville City SD | C31: Pickaway | D31: 7150000 | E31: 615000 | F31: 1575000 | G31: 9475000 | H31: 0 | I31: 0 | J31: 1435000 | K31: 970000 | L31: 21220000 | M31: 0 | N31: 0 | O31: 0 | P31: 449370 | Q31: 107165 | R31: 556535 | S31: 21776535 | T31: 12750000 | U31: 5100000 | V31: 2300000 | W31: 620000 | X31: 2500000 | Y31: 0 | Z31: 0 | AA31: 0 | AB31: 0 | AC31: 0 | AD31: 21000 | AE31: 0 | AF31: 11054 | AG31: 582840 | AH31: 23884894 | AI31: 130000 | AJ31: 250000 | AK31: 120000 | AL31: 500000 | AM31: 24384894 | AN31: -2608359 | AO31: 15265224 | AP31: 12656865 | AQ31: 0 | AR31: 0 | AS31: 0 | AT31: 0 | AU31: 0 | AV31: 0 | AW31: 0 | AX31: 0 | AY31: 0 | AZ31: 0 | BA31: 12656865 | BB31: 0 | BC31: 0 | BD31: 0 | BE31: 12656865 | BF31: 0 | BG31: 0 | BH31: 0 | BI31: 0 | BJ31: 12656865 | BK31: 170 | BL31: 1904 | BM31: 0 | BN31: 0 | BO31: 0 | BP31: 0 | BQ31: 0 | BR31: 0 | BS31: 24384894
A32: 043778 | B32: Claymont City SD | C32: Tuscarawas | D32: 2777660 | E32: 315797 | F32: 0 | G32: 13578260 | H32: 61189 | I32: 0 | J32: 507709 | K32: 1285138 | L32: 18525753 | M32: 0 | N32: 0 | O32: 0 | P32: 10000 | Q32: 0 | R32: 10000 | S32: 18535753 | T32: 10168598 | U32: 4768669 | V32: 2535609 | W32: 530672 | X32: 220296 | Y32: 0 | Z32: 0 | AA32: 0 | AB32: 0 | AC32: 0 | AD32: 0 | AE32: 0 | AF32: 0 | AG32: 138880 | AH32: 18362724 | AI32: 0 | AJ32: 10000 | AK32: 0 | AL32: 10000 | AM32: 18372724 | AN32: 163029 | AO32: 3114120 | AP32: 3277149 | AQ32: 100000 | AR32: 0 | AS32: 0 | AT32: 0 | AU32: 0 | AV32: 0 | AW32: 0 | AX32: 0 | AY32: 0 | AZ32: 0 | BA32: 3177149 | BB32: 0 | BC32: 0 | BD32: 0 | BE32: 3177149 | BF32: 0 | BG32: 0 | BH32: 0 | BI32: 0 | BJ32: 3177149 | BK32: 131 | BL32: 1925 | BM32: 0 | BN32: 0 | BO32: 0 | BP32: 0 | BQ32: 0 | BR32: 0 | BS32: 18535753
A33: 043786 | B33: Cleveland Municipal SD | C33: Cuyahoga | D33: 199907447 | E33: 57169 | F33: 0 | G33: 425495955 | H33: 2877105 | I33: 0 | J33: 32078830 | K33: 33061609 | L33: 693478115 | M33: 0 | N33: 0 | O33: 0 | P33: 9690000 | Q33: 0 | R33: 9690000 | S33: 703168115 | T33: 307476059 | U33: 124535995 | V33: 237681608 | W33: 12330728 | X33: 1540287 | Y33: 0 | Z33: 0 | AA33: 0 | AB33: 0 | AC33: 0 | AD33: 964162 | AE33: 0 | AF33: 272840 | AG33: 6900454 | AH33: 691702133 | AI33: 944394 | AJ33: 0 | AK33: 0 | AL33: 944394 | AM33: 692646527 | AN33: 10521588 | AO33: 69349024 | AP33: 79870613 | AQ33: 12000000 | AR33: 0 | AS33: 0 | AT33: 0 | AU33: 0 | AV33: 0 | AW33: 0 | AX33: 0 | AY33: 0 | AZ33: 0 | BA33: 67870613 | BB33: 0 | BC33: 0 | BD33: 0 | BE33: 67870613 | BF33: 0 | BG33: 0 | BH33: 0 | BI33: 0 | BJ33: 67870613 | BS33: 703168115
A34: 043794 | B34: Cleve. Hts.-Univ. Hts. City SD | C34: Cuyahoga | D34: 68600000 | E34: 0 | F34: 0 | G34: 19000000 | H34: 0 | I34: 0 | J34: 9435000 | K34: 4865000 | L34: 101900000 | M34: 0 | N34: 0 | O34: 0 | P34: 9135000 | Q34: 0 | R34: 9135000 | S34: 111035000 | T34: 55198013 | U34: 22897763 | V34: 15227747 | W34: 2585872 | X34: 2062765 | Y34: 0 | Z34: 0 | AA34: 0 | AB34: 0 | AC34: 0 | AD34: 0 | AE34: 0 | AF34: 0 | AG34: 2175000 | AH34: 100147160 | AI34: 750000 | AJ34: 0 | AK34: 0 | AL34: 750000 | AM34: 100897160 | AN34: 10137840 | AO34: 21711469 | AP34: 31849309 | AQ34: 3295575 | AR34: 0 | AS34: 0 | AT34: 0 | AU34: 0 | AV34: 0 | AW34: 0 | AX34: 0 | AY34: 0 | AZ34: 0 | BA34: 28553734 | BB34: 0 | BC34: 0 | BD34: 0 | BE34: 28553734 | BF34: 0 | BG34: 0 | BH34: 0 | BI34: 0 | BJ34: 28553734 | BM34: 0 | BN34: 0 | BO34: 0 | BP34: 0 | BQ34: 0 | BR34: 0 | BS34: 111035000
A35: 043802 | B35: Columbus City SD | C35: Franklin | D35: 398244352 | E35: 238334 | F35: 0 | G35: 254479868 | H35: 2415583 | I35: 707899 | J35: 61843258 | K35: 15634244 | L35: 733563538 | M35: 0 | N35: 0 | O35: 1515961 | P35: 30000000 | Q35: 150000 | R35: 31665961 | S35: 765229499 | T35: 383141102 | U35: 155896988 | V35: 183389964 | W35: 19267061 | X35: 2332877 | Y35: 0 | Z35: 0 | AA35: 0 | AB35: 0 | AC35: 0 | AD35: 965000 | AE35: 637935 | AF35: 1284977 | AG35: 14417054 | AH35: 761332958 | AI35: 3777141 | AJ35: 30000000 | AK35: 0 | AL35: 33777141 | AM35: 795110099 | AN35: -29880600 | AO35: 120605461 | AP35: 90724861 | AQ35: 8000000 | AR35: 0 | AS35: 0 | AT35: 0 | AU35: 0 | AV35: 0 | AW35: 0 | AX35: 0 | AY35: 0 | AZ35: 0 | BA35: 82724861 | BB35: 0 | BC35: 0 | BD35: 0 | BE35: 82724861 | BF35: 0 | BG35: 0 | BH35: 0 | BI35: 0 | BJ35: 82724861 | BS35: 795110099
A36: 043810 | B36: Conneaut Area City SD | C36: Ashtabula | D36: 3756096 | E36: 222851 | F36: 0 | G36: 11261451 | H36: 38590 | I36: 0 | J36: 577212 | K36: 431698 | L36: 16287898 | M36: 0 | N36: 0 | O36: 0 | P36: 25000 | Q36: 119744 | R36: 144744 | S36: 16432642 | T36: 9223423 | U36: 4191440 | V36: 2733800 | W36: 329605 | X36: 160217 | Y36: 0 | Z36: 0 | AA36: 0 | AB36: 0 | AC36: 0 | AD36: 110000 | AE36: 0 | AF36: 4019 | AG36: 335635 | AH36: 17088139 | AI36: 10000 | AJ36: 25000 | AK36: 0 | AL36: 35000 | AM36: 17123139 | AN36: -690497 | AO36: 2937988 | AP36: 2247491 | AQ36: 150000 | AR36: 0 | AS36: 0 | AT36: 0 | AU36: 0 | AV36: 0 | AW36: 0 | AX36: 0 | AY36: 0 | AZ36: 0 | BA36: 2097491 | BB36: 0 | BC36: 0 | BD36: 0 | BE36: 2097491 | BF36: 0 | BG36: 0 | BH36: 0 | BI36: 0 | BJ36: 2097491 | BK36: 0 | BL36: 0 | BM36: 0 | BN36: 0 | BO36: 0 | BP36: 0 | BQ36: 0 | BR36: 0 | BS36: 17123139
A37: 043828 | B37: Coshocton City SD | C37: Coshocton | D37: 4506394 | E37: 405532 | F37: 0 | G37: 8774161 | H37: 39074 | I37: 0 | J37: 919649 | K37: 1034870 | L37: 15679680 | M37: 0 | N37: 0 | O37: 0 | P37: 0 | Q37: 0 | R37: 0 | S37: 15679680 | T37: 8701337 | U37: 3477100 | V37: 2550675 | W37: 626373 | X37: 88000 | Y37: 0 | Z37: 0 | AA37: 0 | AB37: 0 | AC37: 0 | AD37: 23691 | AE37: 0 | AF37: 12974 | AG37: 256576 | AH37: 15736726 | AI37: 0 | AJ37: 35000 | AK37: 0 | AL37: 35000 | AM37: 15771726 | AN37: -92046 | AO37: 2075025 | AP37: 1982979 | AQ37: 275000 | AR37: 0 | AS37: 0 | AT37: 0 | AU37: 0 | AV37: 0 | AW37: 0 | AX37: 0 | AY37: 0 | AZ37: 0 | BA37: 1707979 | BB37: 0 | BC37: 0 | BD37: 0 | BE37: 1707979 | BF37: 0 | BG37: 0 | BH37: 0 | BI37: 0 | BJ37: 1707979 | BK37: 135 | BL37: 1692 | BM37: 0 | BN37: 0 | BO37: 0 | BP37: 0 | BQ37: 0 | BR37: 0 | BS37: 15771726
A38: 043836 | B38: Cuyahoga Falls City SD | C38: Summit | D38: 27026553 | E38: 253306 | F38: 0 | G38: 12272896 | H38: 546191 | I38: 0 | J38: 4567577 | K38: 3550183 | L38: 48216706 | M38: 0 | N38: 0 | O38: 0 | P38: 0 | Q38: 150493 | R38: 150493 | S38: 48367199 | T38: 26900322 | U38: 10883265 | V38: 7758391 | W38: 740798 | X38: 588641 | Y38: 0 | Z38: 0 | AA38: 0 | AB38: 0 | AC38: 0 | AD38: 0 | AE38: 0 | AF38: 0 | AG38: 786877 | AH38: 47658294 | AI38: 0 | AJ38: 0 | AK38: 150000 | AL38: 150000 | AM38: 47808294 | AN38: 558905 | AO38: 4486602 | AP38: 5045507 | AQ38: 90000 | AR38: 0 | AS38: 0 | AT38: 0 | AU38: 0 | AV38: 0 | AW38: 0 | AX38: 0 | AY38: 0 | AZ38: 0 | BA38: 4955507 | BB38: 0 | BC38: 0 | BD38: 0 | BE38: 4955507 | BF38: 0 | BG38: 0 | BH38: 0 | BI38: 0 | BJ38: 4955507 | BM38: 0 | BN38: 0 | BO38: 0 | BP38: 0 | BQ38: 0 | BR38: 0 | BS38: 48367199
A39: 043844 | B39: Dayton City SD | C39: Montgomery | D39: 50360740 | E39: 5639034 | F39: 0 | G39: 143399691 | H39: 1523125 | I39: 0 | J39: 12742345 | K39: 4301456 | L39: 217966391 | M39: 0 | N39: 0 | O39: 0 | P39: 4483510 | Q39: 75000 | R39: 4558510 | S39: 222524901 | T39: 94872984 | U39: 41733902 | V39: 80627048 | W39: 4963449 | X39: 539472 | Y39: 0 | Z39: 0 | AA39: 0 | AB39: 0 | AC39: 0 | AD39: 0 | AE39: 0 | AF39: 0 | AG39: 2286675 | AH39: 225023530 | AI39: 250000 | AJ39: 2500000 | AK39: 0 | AL39: 2750000 | AM39: 227773530 | AN39: -5248629 | AO39: 11242816 | AP39: 5994187 | AQ39: 0 | AR39: 0 | AS39: 0 | AT39: 0 | AU39: 0 | AV39: 0 | AW39: 0 | AX39: 0 | AY39: 0 | AZ39: 0 | BA39: 5994187 | BB39: 0 | BC39: 0 | BD39: 0 | BE39: 5994187 | BF39: 0 | BG39: 0 | BH39: 0 | BI39: 0 | BJ39: 5994187 | BM39: 0 | BN39: 0 | BO39: 0 | BP39: 0 | BQ39: 0 | BR39: 0 | BS39: 227773530
A40: 043851 | B40: Deer Park Community City SD | C40: Hamilton | D40: 7257844 | E40: 714830 | F40: 0 | G40: 3135407 | H40: 12500 | I40: 0 | J40: 1241494 | K40: 749681 | L40: 13111756 | M40: 0 | N40: 0 | O40: 0 | P40: 128515 | Q40: 31798 | R40: 160313 | S40: 13272069 | T40: 6570014 | U40: 2211871 | V40: 3373467 | W40: 651592 | X40: 39892 | Y40: 0 | Z40: 0 | AA40: 0 | AB40: 0 | AC40: 0 | AD40: 0 | AE40: 0 | AF40: 0 | AG40: 334059 | AH40: 13180895 | AI40: 1406892 | AJ40: 0 | AK40: 0 | AL40: 1406892 | AM40: 14587787 | AN40: -1315718 | AO40: 4853346 | AP40: 3537628 | AQ40: 218067 | AR40: 0 | AS40: 0 | AT40: 0 | AU40: 0 | AV40: 0 | AW40: 0 | AX40: 0 | AY40: 0 | AZ40: 0 | BA40: 3319561 | BB40: 0 | BC40: 0 | BD40: 0 | BE40: 3319561 | BF40: 0 | BG40: 0 | BH40: 0 | BI40: 0 | BJ40: 3319561 | BK40: 0 | BL40: 0 | BM40: 0 | BN40: 0 | BO40: 0 | BP40: 0 | BQ40: 0 | BR40: 0 | BS40: 14587787
A41: 043869 | B41: Defiance City SD | C41: Defiance | D41: 5500000 | E41: 450000 | F41: 1520000 | G41: 13148333 | H41: 105000 | I41: 0 | J41: 1017033 | K41: 1287250 | L41: 23027616 | M41: 0 | N41: 0 | O41: 0 | P41: 20000 | Q41: 145000 | R41: 165000 | S41: 23192616 | T41: 11907344 | U41: 4389939 | V41: 4292080 | W41: 689488 | X41: 452202 | Y41: 0 | Z41: 0 | AA41: 0 | AB41: 0 | AC41: 0 | AD41: 0 | AE41: 0 | AF41: 0 | AG41: 348180 | AH41: 22079233 | AI41: 0 | AJ41: 0 | AK41: 0 | AL41: 0 | AM41: 22079233 | AN41: 1113383 | AO41: 4749832 | AP41: 5863215 | AQ41: 0 | AR41: 0 | AS41: 0 | AT41: 0 | AU41: 0 | AV41: 0 | AW41: 0 | AX41: 0 | AY41: 0 | AZ41: 0 | BA41: 5863215 | BB41: 0 | BC41: 0 | BD41: 0 | BE41: 5863215 | BF41: 0 | BG41: 0 | BH41: 0 | BI41: 0 | BJ41: 5863215 | BK41: 0 | BL41: 0 | BM41: 0 | BN41: 0 | BO41: 0 | BP41: 0 | BQ41: 0 | BR41: 0 | BS41: 23192616
A42: 043877 | B42: Delaware City SD | C42: Delaware | D42: 25947144 | E42: 1653847 | F42: 0 | G42: 13286847 | H42: 22959 | I42: 0 | J42: 4754145 | K42: 1276445 | L42: 46941387 | M42: 0 | N42: 0 | O42: 0 | P42: 0 | Q42: 182459 | R42: 182459 | S42: 47123846 | T42: 27045089 | U42: 10676546 | V42: 5663692 | W42: 1412854 | X42: 83022 | Y42: 0 | Z42: 0 | AA42: 0 | AB42: 0 | AC42: 0 | AD42: 159510 | AE42: 0 | AF42: 68803 | AG42: 1313705 | AH42: 46423221 | AI42: 0 | AJ42: 0 | AK42: 0 | AL42: 0 | AM42: 46423221 | AN42: 700625 | AO42: 5766963 | AP42: 6467588 | AQ42: 300000 | AR42: 0 | AS42: 0 | AT42: 367699 | AU42: 0 | AV42: 0 | AW42: 0 | AX42: 0 | AY42: 0 | AZ42: 367699 | BA42: 5799889 | BB42: 0 | BC42: 0 | BD42: 0 | BE42: 5799889 | BF42: 0 | BG42: 0 | BH42: 0 | BI42: 0 | BJ42: 5799889 | BM42: 0 | BN42: 0 | BO42: 0 | BP42: 0 | BQ42: 0 | BR42: 0 | BS42: 47123846
A43: 043885 | B43: Delphos City SD | C43: Allen | D43: 3745000 | E43: 215809 | F43: 0 | G43: 3109855 | H43: 55741 | I43: 0 | J43: 1036192 | K43: 785000 | L43: 8947597 | M43: 0 | N43: 0 | O43: 0 | P43: 30000 | Q43: 0 | R43: 30000 | S43: 8977597 | T43: 4683222 | U43: 1689377 | V43: 1964616 | W43: 234072 | X43: 29150 | Y43: 0 | Z43: 0 | AA43: 0 | AB43: 0 | AC43: 0 | AD43: 0 | AE43: 0 | AF43: 0 | AG43: 162194 | AH43: 8762631 | AI43: 15000 | AJ43: 30000 | AK43: 67869 | AL43: 112869 | AM43: 8875500 | AN43: 102096 | AO43: 333621 | AP43: 435717 | AQ43: 0 | AR43: 0 | AS43: 0 | AT43: 0 | AU43: 0 | AV43: 0 | AW43: 0 | AX43: 0 | AY43: 0 | AZ43: 0 | BA43: 435717 | BB43: 0 | BC43: 0 | BD43: 0 | BE43: 435717 | BF43: 0 | BG43: 0 | BH43: 0 | BI43: 0 | BJ43: 435717 | BK43: 83 | BL43: 1001 | BM43: 0 | BN43: 0 | BO43: 0 | BP43: 0 | BQ43: 0 | BR43: 0 | BS43: 8977597
A44: 043893 | B44: Dover City SD | C44: Tuscarawas | D44: 11100000 | E44: 0 | F44: 0 | G44: 6300000 | H44: 0 | I44: 0 | J44: 3125321 | K44: 272400 | L44: 20797721 | M44: 0 | N44: 0 | O44: 0 | P44: 202890 | Q44: 0 | R44: 202890 | S44: 21000611 | T44: 13215272 | U44: 5520008 | V44: 1454080 | W44: 811900 | X44: 166500 | Y44: 0 | Z44: 0 | AA44: 0 | AB44: 0 | AC44: 0 | AD44: 0 | AE44: 0 | AF44: 0 | AG44: 672300 | AH44: 21840060 | AI44: 0 | AJ44: 202890 | AK44: 0 | AL44: 202890 | AM44: 22042950 | AN44: -1042339 | AO44: 9108092 | AP44: 8065753 | AQ44: 0 | AR44: 0 | AS44: 0 | AT44: 0 | AU44: 0 | AV44: 0 | AW44: 0 | AX44: 0 | AY44: 0 | AZ44: 0 | BA44: 8065753 | BB44: 0 | BC44: 0 | BD44: 0 | BE44: 8065753 | BF44: 0 | BG44: 0 | BH44: 0 | BI44: 0 | BJ44: 8065753 | BK44: 0 | BL44: 0 | BM44: 0 | BN44: 0 | BO44: 0 | BP44: 0 | BQ44: 0 | BR44: 0 | BS44: 22042950
A45: 043901 | B45: East Cleveland City SD | C45: Cuyahoga | D45: 6857914 | E45: 0 | F45: 0 | G45: 31714780 | H45: 275000 | I45: 0 | J45: 1244848 | K45: 3497500 | L45: 43590042 | M45: 0 | N45: 0 | O45: 0 | P45: 7222498 | Q45: 375000 | R45: 7597498 | S45: 51187540 | T45: 21742181 | U45: 8684420 | V45: 15611552 | W45: 1416632 | X45: 291504 | Y45: 0 | Z45: 0 | AA45: 0 | AB45: 0 | AC45: 0 | AD45: 0 | AE45: 0 | AF45: 0 | AG45: 782900 | AH45: 48529189 | AI45: 250000 | AJ45: 8000000 | AK45: 100000 | AL45: 8350000 | AM45: 56879189 | AN45: -5691650 | AO45: 18209129 | AP45: 12517479 | AQ45: 2200000 | AR45: 0 | AS45: 0 | AT45: 0 | AU45: 0 | AV45: 0 | AW45: 0 | AX45: 0 | AY45: 81931 | AZ45: 81931 | BA45: 10235548 | BB45: 0 | BC45: 0 | BD45: 0 | BE45: 10235548 | BF45: 0 | BG45: 0 | BH45: 0 | BI45: 0 | BJ45: 10235548 | BM45: 0 | BN45: 0 | BO45: 0 | BP45: 0 | BQ45: 0 | BR45: 0 | BS45: 56879189
A46: 043919 | B46: East Liverpool City SD | C46: Columbiana | D46: 3705520 | E46: 0 | F46: 0 | G46: 18557838 | H46: 279390 | I46: 0 | J46: 759183 | K46: 1006000 | L46: 24307931 | M46: 0 | N46: 0 | O46: 0 | P46: 0 | Q46: 60000 | R46: 60000 | S46: 24367931 | T46: 12599061 | U46: 6429912 | V46: 4704120 | W46: 539538 | X46: 239477 | Y46: 0 | Z46: 0 | AA46: 0 | AB46: 0 | AC46: 0 | AD46: 0 | AE46: 0 | AF46: 0 | AG46: 422509 | AH46: 24934617 | AI46: 30000 | AK46: 0 | AL46: 30000 | AM46: 24964617 | AO46: 3915181 | AQ46: 300000 | AR46: 0 | AS46: 0 | AT46: 0 | AU46: 0 | AW46: 0 | AX46: 0 | AY46: 0 | AZ46: 0 | BB46: 0 | BC46: 0 | BD46: 0 | BE46: 3018495 | BF46: 0 | BG46: 0 | BH46: 0 | BI46: 0 | BJ46: 3018495 | BM46: 0 | BN46: 0 | BO46: 0 | BP46: 0 | BQ46: 0 | BR46: 0 | BS46: 24964617
A47: 043927 | B47: East Palestine City SD | C47: Columbiana | D47: 2152000 | E47: 0 | F47: 0 | G47: 7431200 | H47: 55645 | J47: 376458 | K47: 225000 | L47: 10240303 | M47: 0 | N47: 0 | O47: 100000 | P47: 42214 | Q47: 0 | R47: 142214 | S47: 10382517 | T47: 4847039 | U47: 2279607 | V47: 2455263 | W47: 299567 | X47: 23056 | Y47: 0 | Z47: 0 | AA47: 0 | AB47: 0 | AC47: 0 | AD47: 0 | AE47: 0 | AF47: 0 | AG47: 311933 | AH47: 10216465 | AI47: 100000 | AJ47: 0 | AK47: 0 | AL47: 100000 | AM47: 10316465 | AN47: 66052 | AO47: 1375705 | AP47: 1441757 | AQ47: 125000 | AR47: 37321 | AS47: 0 | AT47: 133794 | AU47: 0 | AV47: 0 | AW47: 0 | AX47: 0 | AY47: 0 | AZ47: 171115 | BA47: 1145642 | BB47: 0 | BC47: 0 | BD47: 0 | BE47: 1145642 | BF47: 0 | BG47: 0 | BH47: 0 | BI47: 0 | BJ47: 1145642 | BK47: 85 | BL47: 1214 | BS47: 10382517
A48: 043935 | B48: Eaton Community City SD | C48: Preble | D48: 4786000 | E48: 24 | F48: 4111546 | G48: 8383078 | H48: 45114 | I48: 0 | J48: 927598 | K48: 588873 | L48: 18842233 | M48: 0 | N48: 0 | O48: 746424 | P48: 120000 | Q48: 39006 | R48: 905430 | S48: 19747663 | T48: 9976345 | U48: 3810815 | V48: 2682366 | W48: 843919 | X48: 130532 | Y48: 0 | Z48: 0 | AA48: 0 | AB48: 0 | AC48: 0 | AD48: 135000 | AE48: 0 | AF48: 119953 | AG48: 1423542 | AH48: 19122472 | AI48: 746424 | AJ48: 120000 | AK48: 0 | AL48: 866424 | AM48: 19988896 | AN48: -241233 | AO48: 11888353 | AP48: 11647120 | AQ48: 400000 | AR48: 0 | AS48: 0 | AT48: 0 | AU48: 0 | AV48: 0 | AW48: 0 | AX48: 0 | AY48: 0 | AZ48: 0 | BA48: 11247120 | BB48: 0 | BC48: 0 | BD48: 0 | BE48: 11247120 | BF48: 0 | BG48: 0 | BH48: 0 | BI48: 0 | BJ48: 11247120 | BK48: 0 | BL48: 0 | BM48: 0 | BN48: 0 | BO48: 0 | BP48: 0 | BQ48: 0 | BR48: 0 | BS48: 19988896
A49: 043943 | B49: Elyria City SD | C49: Lorain | D49: 26922832 | E49: 1744984 | F49: 0 | G49: 35489610 | H49: 136298 | I49: 0 | J49: 6629704 | K49: 1975060 | L49: 72898488 | M49: 0 | N49: 0 | O49: 0 | P49: 719212 | Q49: 0 | R49: 719212 | S49: 73617700 | T49: 34913862 | U49: 12202415 | V49: 19942142 | W49: 1131016 | X49: 64858 | Y49: 0 | Z49: 0 | AA49: 0 | AB49: 0 | AC49: 0 | AD49: 385000 | AE49: 70000 | AF49: 150000 | AG49: 839116 | AH49: 69698409 | AI49: 2250000 | AJ49: 225000 | AK49: 0 | AL49: 2475000 | AM49: 72173409 | AN49: 1444291 | AO49: 5925750 | AP49: 7370041 | AQ49: 0 | AR49: 0 | AS49: 0 | AT49: 0 | AU49: 0 | AV49: 0 | AW49: 0 | AX49: 0 | AY49: 0 | AZ49: 0 | BA49: 7370041 | BB49: 0 | BC49: 0 | BD49: 0 | BE49: 7370041 | BF49: 0 | BG49: 0 | BH49: 0 | BI49: 0 | BJ49: 7370041 | BM49: 0 | BN49: 0 | BO49: 0 | BP49: 0 | BQ49: 0 | BR49: 0 | BS49: 73617700
A50: 043950 | B50: Euclid City SD | C50: Cuyahoga | D50: 34698418 | E50: 0 | F50: 6229300 | G50: 21802588 | H50: 750000 | J50: 5956483 | K50: 600000 | L50: 70036789 | M50: 0 | N50: 0 | Q50: 250000 | R50: 250000 | S50: 70286789 | T50: 37904013 | U50: 14884952 | V50: 13000314 | W50: 1575091 | X50: 469865 | Y50: 0 | Z50: 0 | AA50: 0 | AB50: 0 | AC50: 0 | AD50: 364529 | AE50: 0 | AF50: 0 | AG50: 1816119 | AH50: 70014883 | AI50: 0 | AK50: 275000 | AL50: 275000 | AM50: 70289883 | AN50: -3094 | AO50: 1688476 | AP50: 1685382 | AQ50: 1000000 | AR50: 0 | AS50: 0 | AT50: 476510 | AU50: 0 | AV50: 0 | AW50: 0 | AX50: 0 | AY50: 0 | AZ50: 476510 | BA50: 208872 | BB50: 0 | BC50: 0 | BD50: 0 | BE50: 208872 | BF50: 0 | BG50: 0 | BH50: 0 | BI50: 0 | BJ50: 208872 | BK50: 0 | BL50: 0 | BM50: 0 | BN50: 0 | BO50: 0 | BP50: 0 | BQ50: 0 | BR50: 0 | BS50: 70289883
A51: 043968 | B51: Fairborn City SD | C51: Greene | D51: 15626221 | E51: 903704 | F51: 3591089 | G51: 17995857 | H51: 4404 | I51: 0 | J51: 2164602 | K51: 1817692 | L51: 42103569 | M51: 0 | N51: 0 | O51: 0 | P51: 0 | Q51: 261233 | R51: 261233 | S51: 42364802 | T51: 21498970 | U51: 9724236 | V51: 7655518 | W51: 1155892 | X51: 1210973 | Y51: 0 | Z51: 0 | AA51: 0 | AB51: 0 | AC51: 0 | AD51: 0 | AE51: 0 | AF51: 0 | AG51: 554789 | AH51: 41800378 | AI51: 350000 | AJ51: 0 | AK51: 0 | AL51: 350000 | AM51: 42150378 | AN51: 214424 | AO51: 3877616 | AP51: 4092040 | AQ51: 325000 | AR51: 0 | AS51: 0 | AT51: 0 | AU51: 0 | AV51: 0 | AW51: 0 | AX51: 0 | AY51: 0 | AZ51: 0 | BA51: 3767040 | BB51: 0 | BC51: 0 | BD51: 0 | BE51: 3767040 | BF51: 0 | BG51: 0 | BH51: 0 | BI51: 0 | BJ51: 3767040 | BK51: 0 | BL51: 0 | BM51: 0 | BN51: 0 | BO51: 0 | BP51: 0 | BQ51: 0 | BR51: 0 | BS51: 42364802
A52: 043976 | B52: Fairview Park City SD | C52: Cuyahoga | D52: 14887862 | E52: 366996 | F52: 0 | G52: 2144201 | H52: 27802 | I52: 0 | J52: 2482232 | K52: 580816 | L52: 20489909 | M52: 0 | N52: 0 | O52: 0 | P52: 163532 | Q52: 16000 | R52: 179532 | S52: 20669441 | T52: 11468371 | U52: 3964777 | V52: 2268865 | W52: 431436 | X52: 55780 | Y52: 0 | Z52: 0 | AA52: 0 | AB52: 0 | AC52: 0 | AD52: 0 | AE52: 0 | AF52: 0 | AG52: 340713 | AH52: 18529942 | AI52: 935000 | AJ52: 144045 | AK52: 0 | AL52: 1079045 | AM52: 19608987 | AN52: 1060454 | AO52: 15078184 | AP52: 16138638 | AQ52: 0 | AR52: 0 | AS52: 0 | AT52: 364682 | AU52: 0 | AV52: 0 | AW52: 0 | AX52: 0 | AY52: 0 | AZ52: 364682 | BA52: 15773956 | BB52: 0 | BC52: 0 | BD52: 0 | BE52: 15773956 | BF52: 0 | BG52: 0 | BH52: 0 | BI52: 0 | BJ52: 15773956 | BM52: 0 | BN52: 0 | BO52: 0 | BP52: 0 | BQ52: 0 | BR52: 0 | BS52: 20669441
A53: 043984 | B53: Findlay City SD | C53: Hancock | D53: 25810780 | E53: 20000 | F53: 0 | G53: 19338070 | H53: 370430 | I53: 0 | J53: 7142000 | K53: 2606000 | L53: 55287280 | M53: 0 | N53: 0 | O53: 0 | P53: 0 | Q53: 65000 | R53: 65000 | S53: 55352280 | T53: 29879649 | U53: 11006545 | V53: 10552884 | W53: 2117907 | X53: 500000 | Y53: 0 | Z53: 0 | AA53: 0 | AB53: 0 | AC53: 0 | AD53: 0 | AE53: 0 | AF53: 0 | AG53: 960000 | AH53: 55016985 | AI53: 85000 | AJ53: 225000 | AK53: 2500 | AL53: 312500 | AM53: 55329485 | AN53: 22795 | AO53: 11229160 | AP53: 11251955 | AQ53: 1200000 | AR53: 0 | AS53: 0 | AT53: 0 | AU53: 0 | AV53: 0 | AW53: 0 | AX53: 0 | AY53: 0 | AZ53: 0 | BA53: 10051955 | BB53: 0 | BC53: 0 | BD53: 0 | BE53: 10051955 | BF53: 0 | BG53: 0 | BH53: 0 | BI53: 0 | BJ53: 10051955 | BK53: 490 | BL53: 5050 | BM53: 0 | BN53: 0 | BO53: 0 | BP53: 0 | BQ53: 0 | BR53: 0 | BS53: 55352280
A54: 043992 | B54: Fostoria City SD | C54: Seneca | D54: 6282058 | E54: 0 | F54: 0 | G54: 11117777 | H54: 60000 | I54: 0 | J54: 1770295 | K54: 539100 | L54: 19769230 | M54: 0 | N54: 0 | O54: 0 | P54: 10000 | Q54: 0 | R54: 10000 | S54: 19779230 | T54: 9496148 | U54: 4491313 | V54: 5650659 | W54: 700108 | X54: 64600 | Y54: 0 | Z54: 0 | AA54: 0 | AB54: 0 | AC54: 0 | AD54: 0 | AE54: 0 | AF54: 0 | AG54: 245315 | AH54: 20648143 | AI54: 121750 | AJ54: 0 | AK54: 0 | AL54: 121750 | AM54: 20769893 | AN54: -990663 | AO54: 1342854 | AP54: 352191 | AQ54: 0 | AR54: 0 | AS54: 0 | AT54: 0 | AU54: 0 | AV54: 0 | AW54: 0 | AX54: 0 | AY54: 0 | AZ54: 0 | BA54: 352191 | BB54: 0 | BC54: 0 | BD54: 0 | BE54: 352191 | BF54: 0 | BG54: 0 | BH54: 0 | BI54: 0 | BJ54: 352191 | BK54: 0 | BL54: 0 | BM54: 0 | BN54: 0 | BO54: 0 | BP54: 0 | BQ54: 0 | BR54: 0 | BS54: 20769893
A55: 044008 | B55: Franklin City SD | C55: Warren | D55: 10296716 | E55: 1000000 | F55: 0 | G55: 9234221 | H55: 99326 | I55: 0 | J55: 4299901 | K55: 2255121 | L55: 27185285 | M55: 0 | N55: 0 | O55: 0 | P55: 0 | Q55: 0 | R55: 0 | S55: 27185285 | T55: 16041944 | U55: 6054941 | V55: 5290077 | W55: 880972 | X55: 121395 | Y55: 0 | Z55: 0 | AA55: 0 | AB55: 0 | AC55: 0 | AD55: 127867 | AE55: 0 | AF55: 2206 | AG55: 371175 | AH55: 28890577 | AI55: 0 | AJ55: 0 | AK55: 0 | AL55: 0 | AM55: 28890577 | AN55: -1705292 | AO55: 3841286 | AP55: 2135994 | AQ55: 144453 | AR55: 0 | AS55: 0 | AT55: 0 | AU55: 0 | AV55: 0 | AW55: 0 | AX55: 0 | AY55: 0 | AZ55: 0 | BA55: 1991541 | BB55: 0 | BC55: 0 | BD55: 0 | BE55: 1991541 | BF55: 0 | BG55: 0 | BH55: 0 | BI55: 0 | BJ55: 1991541 | BK55: 230 | BL55: 2820 | BM55: 0 | BN55: 0 | BO55: 0 | BP55: 0 | BQ55: 0 | BR55: 0 | BS55: 28890577
A56: 044016 | B56: Fremont City SD | C56: Sandusky | D56: 10556023 | E56: 0 | F56: 6825000 | G56: 13604776 | H56: 24810 | I56: 0 | J56: 3160098 | K56: 1781668 | L56: 35952375 | M56: 0 | N56: 0 | O56: 100000 | P56: 0 | Q56: 0 | R56: 100000 | S56: 36052375 | T56: 21602413 | U56: 7183156 | V56: 6921992 | W56: 1229380 | X56: 384796 | Y56: 0 | Z56: 0 | AA56: 0 | AB56: 0 | AC56: 0 | AD56: 0 | AE56: 0 | AF56: 0 | AG56: 569359 | AH56: 37891096 | AI56: 102407 | AJ56: 0 | AK56: 0 | AL56: 102407 | AM56: 37993502 | AN56: -1941128 | AO56: 11648260 | AP56: 9707133 | AQ56: 255000 | AR56: 0 | AS56: 5283009 | AT56: 0 | AU56: 0 | AV56: 0 | AW56: 0 | AX56: 0 | AY56: 0 | AZ56: 5283009 | BA56: 4169124 | BB56: 0 | BC56: 0 | BD56: 0 | BE56: 4169124 | BF56: 0 | BG56: 0 | BH56: 0 | BI56: 0 | BJ56: 4169124 | BK56: 319 | BL56: 3980 | BM56: 0 | BN56: 0 | BO56: 0 | BP56: 0 | BQ56: 0 | BR56: 0 | BS56: 37993502
A57: 044024 | B57: Galion City SD | C57: Crawford | D57: 3964512 | E57: 118022 | F57: 0 | G57: 10311664 | H57: 7151 | I57: 0 | J57: 1055959 | K57: 725771 | L57: 16183079 | M57: 0 | N57: 0 | O57: 0 | P57: 58593 | Q57: 5000 | R57: 63593 | S57: 16246672 | T57: 8043630 | U57: 3639353 | V57: 3601052 | W57: 408070 | X57: 0 | Y57: 0 | Z57: 0 | AA57: 0 | AB57: 0 | AC57: 0 | AD57: 0 | AE57: 0 | AF57: 0 | AG57: 243300 | AH57: 15935405 | AI57: 415199 | AJ57: 40000 | AK57: 0 | AL57: 455199 | AM57: 16390604 | AN57: -143932 | AO57: 1364408 | AP57: 1220476 | AQ57: 0 | AR57: 0 | AS57: 0 | AT57: 0 | AU57: 0 | AV57: 0 | AW57: 0 | AX57: 0 | AY57: 0 | AZ57: 0 | BA57: 1220476 | BB57: 0 | BC57: 0 | BD57: 0 | BE57: 1220476 | BF57: 0 | BG57: 599671 | BH57: 599671 | BI57: 0 | BJ57: 1820147 | BM57: 0 | BN57: 0 | BO57: 0 | BP57: 0 | BQ57: 0 | BR57: 0 | BS57: 16390604
A58: 044032 | B58: Gallipolis City SD | C58: Gallia | D58: 4607891 | E58: 0 | F58: 51000 | G58: 11761265 | H58: 17940 | I58: 0 | J58: 657369 | K58: 1764107 | L58: 18859572 | M58: 0 | N58: 0 | O58: 0 | P58: 98601 | Q58: 161783 | R58: 260384 | S58: 19119956 | T58: 10374591 | U58: 4574528 | V58: 2643253 | W58: 1245420 | X58: 200000 | Y58: 0 | Z58: 0 | AA58: 0 | AB58: 0 | AC58: 0 | AD58: 0 | AE58: 0 | AF58: 0 | AG58: 182439 | AH58: 19220231 | AI58: 0 | AJ58: 0 | AK58: 0 | AL58: 0 | AM58: 19220231 | AN58: -100275 | AO58: 1799578 | AP58: 1699303 | AQ58: 0 | AR58: 0 | AS58: 0 | AT58: 0 | AU58: 0 | AV58: 0 | AW58: 0 | AX58: 0 | AY58: 0 | AZ58: 0 | BA58: 1699303 | BB58: 0 | BC58: 0 | BD58: 0 | BF58: 0 | BG58: 0 | BH58: 0 | BI58: 0 | BJ58: 1699303 | BK58: 178 | BL58: 1872 | BM58: 0 | BN58: 0 | BO58: 0 | BP58: 0 | BQ58: 0 | BR58: 0 | BS58: 19220231
A59: 044040 | B59: Garfield Heights City SD | C59: Cuyahoga | D59: 13890515 | E59: 578530 | F59: 0 | G59: 17999418 | H59: 41965 | I59: 0 | J59: 2801067 | K59: 962166 | L59: 36273661 | M59: 0 | N59: 0 | O59: 0 | P59: 429300 | Q59: 0 | R59: 429300 | S59: 36702961 | T59: 21143515 | U59: 7473015 | V59: 6104646 | W59: 834423 | X59: 110271 | Y59: 0 | Z59: 0 | AA59: 0 | AB59: 0 | AC59: 0 | AD59: 0 | AE59: 282820 | AF59: 0 | AG59: 577867 | AH59: 36526557 | AI59: 250000 | AJ59: 300000 | AK59: 0 | AL59: 550000 | AM59: 37076557 | AN59: -373596 | AO59: 867082 | AP59: 493486 | AQ59: 0 | AR59: 0 | AS59: 0 | AT59: 0 | AU59: 0 | AV59: 0 | AW59: 0 | AX59: 0 | AY59: 0 | AZ59: 0 | BA59: 493486 | BB59: 0 | BC59: 0 | BD59: 0 | BE59: 493486 | BF59: 0 | BG59: 0 | BH59: 0 | BI59: 0 | BJ59: 493486 | BM59: 0 | BN59: 0 | BO59: 0 | BP59: 0 | BQ59: 0 | BR59: 0 | BS59: 37076557
A60: 044057 | B60: Geneva Schools City SD | C60: Ashtabula | D60: 6532595 | E60: 192 | F60: 0 | G60: 11571577 | H60: 50649 | I60: 0 | J60: 891699 | K60: 1804709 | L60: 20851421 | M60: 0 | N60: 0 | O60: 0 | P60: 0 | Q60: 224039 | R60: 224039 | S60: 21075460 | T60: 11078963 | U60: 4871832 | V60: 3463120 | W60: 750000 | X60: 175000 | Y60: 0 | Z60: 0 | AA60: 0 | AB60: 0 | AC60: 0 | AD60: 0 | AE60: 0 | AF60: 0 | AG60: 268248 | AH60: 20607163 | AI60: 78000 | AJ60: 0 | AK60: 0 | AL60: 78000 | AM60: 20685163 | AN60: 390297 | AO60: 2811838 | AP60: 3202135 | AQ60: 150000 | AR60: 0 | AS60: 0 | AT60: 358077 | AU60: 0 | AV60: 0 | AW60: 0 | AX60: 0 | AY60: 0 | AZ60: 358077 | BA60: 2694058 | BB60: 0 | BC60: 0 | BD60: 0 | BE60: 2694058 | BF60: 0 | BG60: 0 | BH60: 0 | BI60: 0 | BJ60: 2694058 | BK60: 164 | BL60: 2384 | BM60: 0 | BN60: 0 | BO60: 0 | BP60: 0 | BQ60: 0 | BR60: 0 | BS60: 21075460
A61: 044065 | B61: Girard City SD | C61: Trumbull | D61: 3220000 | E61: 419517 | F61: 0 | G61: 8200000 | H61: 79408 | I61: 0 | J61: 631775 | K61: 1233054 | L61: 13783754 | M61: 0 | N61: 0 | O61: 0 | P61: 0 | Q61: 80000 | R61: 80000 | S61: 13863754 | T61: 8480000 | U61: 3250000 | V61: 1850000 | W61: 500000 | X61: 100000 | Y61: 0 | Z61: 0 | AA61: 0 | AB61: 0 | AC61: 0 | AD61: 0 | AE61: 0 | AF61: 0 | AG61: 600000 | AH61: 14780000 | AI61: 0 | AJ61: 0 | AK61: 0 | AL61: 0 | AM61: 14780000 | AN61: -916246 | AO61: 5863737 | AP61: 4947491 | AQ61: 0 | AR61: 0 | AS61: 0 | AT61: 95565 | AU61: 0 | AV61: 0 | AW61: 0 | AX61: 0 | AY61: 0 | AZ61: 95565 | BA61: 4851926 | BB61: 0 | BC61: 0 | BD61: 0 | BE61: 4851926 | BF61: 0 | BG61: 0 | BH61: 0 | BI61: 0 | BJ61: 4851926 | BK61: 124 | BL61: 1625 | BM61: 0 | BN61: 0 | BO61: 0 | BP61: 0 | BQ61: 0 | BR61: 0 | BS61: 14780000
A62: 044073 | B62: Grandview Heights City SD | C62: Franklin | D62: 8967530 | E62: 0 | F62: 0 | G62: 1505153 | H62: 0 | I62: 0 | J62: 2074122 | K62: 874171 | L62: 13420976 | M62: 0 | N62: 0 | O62: 0 | P62: 0 | Q62: 0 | R62: 0 | S62: 13420976 | T62: 10119520 | U62: 3319727 | V62: 2211094 | W62: 292534 | X62: 65865 | Y62: 0 | Z62: 0 | AA62: 0 | AB62: 0 | AC62: 0 | AD62: 0 | AE62: 0 | AF62: 0 | AG62: 273308 | AH62: 16282048 | AI62: 92603 | AJ62: 0 | AK62: 53600 | AL62: 146203 | AM62: 16428251 | AN62: -3007275 | AO62: 7227336 | AP62: 4220061 | AQ62: 391095 | AR62: 0 | AS62: 0 | AT62: 750000 | AU62: 0 | AV62: 0 | AW62: 0 | AX62: 0 | AY62: 0 | AZ62: 750000 | BA62: 3078966 | BB62: 0 | BC62: 0 | BD62: 0 | BE62: 3078966 | BF62: 0 | BG62: 0 | BH62: 0 | BI62: 0 | BJ62: 3078966 | BK62: 64 | BL62: 1017 | BM62: 0 | BN62: 0 | BO62: 0 | BP62: 0 | BQ62: 0 | BR62: 0 | BS62: 16428251
A63: 044081 | B63: Winton Woods City SD | C63: Hamilton | D63: 22210000 | E63: 0 | F63: 0 | G63: 15140000 | H63: 68000 | I63: 0 | J63: 3500900 | K63: 2898600 | L63: 43817500 | M63: 0 | N63: 0 | O63: 0 | P63: 0 | Q63: 108500 | R63: 108500 | S63: 43926000 | T63: 22000000 | U63: 9388500 | V63: 8147000 | W63: 1572600 | X63: 1036000 | Y63: 0 | Z63: 0 | AA63: 0 | AB63: 0 | AC63: 0 | AD63: 0 | AE63: 0 | AF63: 0 | AG63: 765900 | AH63: 42910000 | AI63: 0 | AJ63: 0 | AK63: 0 | AL63: 0 | AM63: 42910000 | AN63: 1016000 | AO63: 10345990 | AP63: 11361990 | AQ63: 100000 | AR63: 0 | AS63: 0 | AT63: 0 | AU63: 0 | AW63: 0 | AX63: 0 | AY63: 0 | AZ63: 0 | BA63: 11261990 | BB63: 0 | BC63: 0 | BD63: 0 | BE63: 11261990 | BF63: 0 | BG63: 0 | BH63: 0 | BI63: 0 | BJ63: 11261990 | BK63: 290 | BL63: 3280 | BM63: 0 | BN63: 0 | BO63: 0 | BP63: 0 | BQ63: 0 | BR63: 0 | BS63: 43926000
A64: 044099 | B64: Greenville City SD | C64: Darke | D64: 8812654 | E64: 602445 | F64: 1970598 | G64: 11591801 | H64: 277515 | I64: 0 | J64: 1849330 | K64: 749032 | L64: 25853375 | M64: 0 | N64: 0 | O64: 0 | P64: 600000 | Q64: 20000 | R64: 620000 | S64: 26473375 | T64: 13844370 | U64: 5553410 | V64: 4881150 | W64: 666992 | X64: 65752 | Y64: 0 | Z64: 0 | AA64: 0 | AB64: 0 | AC64: 0 | AD64: 0 | AE64: 0 | AF64: 0 | AG64: 493959 | AH64: 25505633 | AI64: 205000 | AJ64: 600000 | AK64: 500 | AL64: 805500 | AM64: 26311133 | AN64: 162242 | AO64: 6764438 | AP64: 6926680 | AQ64: 150000 | AR64: 0 | AS64: 0 | AT64: 0 | AU64: 0 | AV64: 0 | AW64: 0 | AX64: 0 | AY64: 0 | AZ64: 0 | BA64: 6776680 | BB64: 0 | BC64: 0 | BD64: 0 | BE64: 6776680 | BF64: 0 | BG64: 0 | BH64: 0 | BI64: 0 | BJ64: 6776680 | BK64: 207 | BL64: 2458 | BM64: 0 | BN64: 0 | BO64: 0 | BP64: 0 | BQ64: 0 | BR64: 0 | BS64: 26473375
A65: 044107 | B65: Hamilton City SD | C65: Butler | D65: 17284049 | E65: 135000 | F65: 0 | H65: 764713 | I65: 0 | J65: 2476709 | K65: 2523082 | L65: 76433862 | M65: 0 | N65: 0 | O65: 0 | P65: 450000 | Q65: 0 | R65: 450000 | S65: 76883862 | T65: 47250000 | U65: 16825646 | V65: 9772340 | W65: 1925282 | X65: 250000 | Y65: 0 | Z65: 0 | AA65: 0 | AB65: 0 | AC65: 0 | AD65: 0 | AE65: 0 | AF65: 0 | AG65: 941454 | AH65: 76964721 | AI65: 200000 | AJ65: 400000 | AK65: 0 | AL65: 600000 | AM65: 77564721 | AO65: 8980276 | AP65: 8299417 | AQ65: 0 | AR65: 0 | AS65: 0 | AT65: 0 | AU65: 0 | AV65: 0 | AW65: 0 | AX65: 0 | AY65: 0 | AZ65: 0 | BA65: 8299417 | BB65: 0 | BC65: 0 | BD65: 0 | BE65: 8299417 | BF65: 0 | BG65: 0 | BH65: 0 | BI65: 0 | BJ65: 8299417 | BK65: 0 | BL65: 0 | BM65: 0 | BN65: 0 | BO65: 0 | BP65: 0 | BQ65: 0 | BR65: 0 | BS65: 77564721
A66: 044115 | B66: Heath City SD | C66: Licking | D66: 6279872 | E66: 324377 | F66: 0 | G66: 4653802 | H66: 29222 | I66: 0 | J66: 1035320 | K66: 989071 | L66: 13311664 | M66: 0 | N66: 0 | O66: 0 | P66: 0 | Q66: 0 | R66: 0 | S66: 13311664 | T66: 7814582 | U66: 3156167 | V66: 2376809 | W66: 363181 | X66: 34022 | Y66: 0 | Z66: 0 | AA66: 0 | AB66: 0 | AC66: 0 | AD66: 0 | AE66: 0 | AF66: 0 | AG66: 851789 | AH66: 14596550 | AI66: 0 | AJ66: 0 | AK66: 0 | AL66: 0 | AM66: 14596550 | AN66: -1284886 | AO66: 1362872 | AP66: 77986 | AQ66: 135000 | AR66: 0 | AS66: 0 | AT66: 77542 | AU66: 0 | AV66: 0 | AW66: 0 | AX66: 0 | AY66: 6628 | AZ66: 84170 | BA66: -141184 | BB66: 0 | BC66: 0 | BD66: 0 | BE66: -141184 | BF66: 0 | BG66: 978033 | BH66: 978033 | BI66: 0 | BJ66: 836849 | BM66: 0 | BN66: 0 | BO66: 0 | BP66: 0 | BQ66: 0 | BR66: 0 | BS66: 14596550
A67: 044123 | B67: Hillsboro City SD | C67: Highland | D67: 5157484 | E67: 0 | F67: 2326962 | G67: 13121979 | H67: 140621 | I67: 0 | J67: 734906 | K67: 1469002 | L67: 22950954 | M67: 0 | N67: 0 | O67: 60000 | P67: 10000 | Q67: 15000 | R67: 85000 | S67: 23035954 | T67: 12453857 | U67: 4588603 | V67: 3110226 | W67: 904150 | X67: 200000 | Y67: 0 | Z67: 0 | AA67: 0 | AB67: 0 | AC67: 0 | AD67: 0 | AE67: 0 | AF67: 55000 | AG67: 285800 | AH67: 21597636 | AI67: 525000 | AJ67: 10000 | AK67: 0 | AL67: 535000 | AM67: 22132636 | AN67: 903318 | AO67: 5155733 | AP67: 6059051 | AQ67: 150000 | AR67: 0 | AS67: 0 | AT67: 0 | AU67: 0 | AV67: 0 | AW67: 0 | AX67: 0 | AY67: 0 | AZ67: 0 | BA67: 5909051 | BB67: 0 | BC67: 0 | BD67: 0 | BE67: 5909051 | BF67: 0 | BG67: 0 | BH67: 0 | BI67: 0 | BJ67: 5909051 | BK67: 195 | BL67: 2548 | BM67: 0 | BN67: 0 | BO67: 0 | BP67: 0 | BQ67: 0 | BR67: 0 | BS67: 23035954
A68: 044131 | B68: Huron City SD | C68: Erie | D68: 8703600 | E68: 0 | F68: 0 | G68: 2353671 | H68: 20000 | I68: 0 | J68: 2248852 | K68: 812064 | L68: 14138187 | M68: 0 | N68: 0 | O68: 440000 | P68: 0 | Q68: 0 | R68: 440000 | S68: 14578187 | T68: 8143496 | U68: 3501874 | V68: 2572730 | W68: 762280 | X68: 75000 | Y68: 0 | Z68: 0 | AA68: 0 | AB68: 0 | AC68: 0 | AD68: 95000 | AE68: 140161 | AF68: 75364 | AG68: 788387 | AH68: 16154292 | AI68: 0 | AJ68: 400000 | AK68: 0 | AL68: 400000 | AM68: 16554292 | AN68: -1976105 | AO68: 5488926 | AP68: 3512821 | AQ68: 225000 | AR68: 0 | AS68: 0 | AT68: 0 | AU68: 0 | AV68: 0 | AW68: 0 | AX68: 0 | AY68: 0 | AZ68: 0 | BA68: 3287821 | BB68: 0 | BC68: 656400 | BD68: 656400 | BE68: 3944221 | BF68: 0 | BG68: 0 | BH68: 0 | BI68: 0 | BJ68: 3944221 | BK68: 84 | BL68: 1388 | BM68: 0 | BN68: 0 | BO68: 0 | BP68: 0 | BQ68: 0 | BR68: 0 | BS68: 16554292
A69: 044149 | B69: Ironton City SD | C69: Lawrence | D69: 2426435 | E69: 75720 | F69: 0 | G69: 8538905 | H69: 55728 | I69: 0 | J69: 434654 | K69: 1403622 | L69: 12935064 | M69: 0 | N69: 0 | O69: 0 | P69: 341313 | Q69: 0 | R69: 341313 | S69: 13276377 | T69: 6776036 | U69: 2850000 | V69: 2146606 | W69: 890950 | X69: 100000 | Y69: 0 | Z69: 0 | AA69: 0 | AB69: 0 | AC69: 0 | AD69: 0 | AE69: 0 | AF69: 0 | AG69: 387316 | AH69: 13150908 | AI69: 0 | AJ69: 75000 | AK69: 0 | AL69: 75000 | AM69: 13225908 | AN69: 50469 | AO69: 1998321 | AP69: 2048790 | AQ69: 95000 | AR69: 0 | AS69: 0 | AT69: 0 | AU69: 0 | AV69: 0 | AW69: 0 | AX69: 0 | AY69: 0 | AZ69: 0 | BA69: 1953790 | BB69: 0 | BC69: 0 | BD69: 0 | BE69: 1953790 | BF69: 0 | BG69: 0 | BH69: 0 | BI69: 0 | BJ69: 1953790 | BK69: 0 | BL69: 0 | BM69: 0 | BN69: 0 | BO69: 0 | BP69: 0 | BQ69: 0 | BR69: 0 | BS69: 13276377
A70: 044156 | B70: Jackson City SD | C70: Jackson | D70: 4202697 | E70: 299408 | F70: 0 | G70: 14508243 | H70: 1309 | I70: 0 | J70: 631236 | K70: 1232086 | L70: 20874979 | M70: 0 | N70: 0 | O70: 0 | P70: 123360 | Q70: 0 | R70: 123360 | S70: 20998339 | T70: 11850027 | U70: 4484425 | V70: 2940867 | W70: 865250 | X70: 11545 | Y70: 0 | Z70: 0 | AA70: 0 | AB70: 0 | AC70: 0 | AD70: 0 | AE70: 0 | AF70: 0 | AG70: 165665 | AH70: 20317779 | AI70: 25000 | AJ70: 125000 | AK70: 0 | AL70: 150000 | AM70: 20467779 | AN70: 530560 | AO70: 6753447 | AP70: 7284007 | AQ70: 0 | AR70: 0 | AS70: 0 | AT70: 0 | AU70: 261129 | AV70: 0 | AW70: 0 | AX70: 0 | AY70: 0 | AZ70: 261129 | BA70: 7022878 | BB70: 0 | BC70: 0 | BD70: 0 | BE70: 7022878 | BF70: 0 | BG70: 0 | BH70: 0 | BI70: 0 | BJ70: 7022878 | BM70: 0 | BN70: 0 | BO70: 0 | BP70: 0 | BQ70: 0 | BR70: 0 | BS70: 20998339
A71: 044164 | B71: Kent City SD | C71: Portage | D71: 21130216 | E71: 1055880 | F71: 0 | G71: 12922150 | H71: 356481 | I71: 0 | J71: 3632156 | K71: 3700496 | L71: 42797379 | M71: 0 | N71: 0 | O71: 0 | P71: 127896 | Q71: 229200 | R71: 357096 | S71: 43154475 | T71: 29296254 | U71: 11197026 | V71: 3147982 | W71: 887615 | X71: 281591 | Y71: 0 | Z71: 0 | AA71: 0 | AB71: 0 | AC71: 0 | AD71: 0 | AE71: 0 | AF71: 0 | AG71: 620759 | AH71: 45431227 | AI71: 605480 | AJ71: 128000 | AK71: 5000 | AL71: 738480 | AM71: 46169707 | AN71: -3015233 | AO71: 13954148 | AP71: 10938915 | AQ71: 500000 | AR71: 0 | AS71: 0 | AT71: 0 | AU71: 0 | AV71: 0 | AW71: 0 | AX71: 0 | AY71: 0 | AZ71: 0 | BA71: 10438915 | BB71: 0 | BC71: 0 | BD71: 0 | BE71: 10438915 | BF71: 0 | BG71: 0 | BH71: 0 | BI71: 0 | BJ71: 10438915 | BK71: 0 | BL71: 0 | BM71: 0 | BN71: 0 | BO71: 0 | BP71: 0 | BQ71: 0 | BR71: 0 | BS71: 46169707
A72: 044172 | B72: Kenton City SD | C72: Hardin | D72: 3750000 | E72: 0 | F72: 2750000 | G72: 8931817 | H72: 74851 | I72: 0 | J72: 1005030 | K72: 1275046 | L72: 17786744 | M72: 0 | N72: 0 | O72: 0 | P72: 0 | Q72: 120000 | R72: 120000 | S72: 17906744 | T72: 9638210 | U72: 3840348 | V72: 2483400 | W72: 503730 | X72: 1000000 | Y72: 0 | Z72: 0 | AA72: 0 | AB72: 0 | AC72: 0 | AD72: 0 | AE72: 0 | AF72: 0 | AG72: 869328 | AH72: 18335016 | AI72: 0 | AJ72: 0 | AK72: 0 | AL72: 0 | AM72: 18335016 | AN72: -428272 | AO72: 4026455 | AP72: 3598183 | AQ72: 100000 | AR72: 0 | AS72: 0 | AT72: 0 | AU72: 0 | AV72: 0 | AW72: 0 | AX72: 0 | AY72: 0 | AZ72: 0 | BA72: 3498183 | BB72: 0 | BC72: 0 | BD72: 0 | BE72: 3498183 | BF72: 0 | BG72: 0 | BH72: 0 | BI72: 0 | BJ72: 3498183 | BM72: 0 | BN72: 0 | BO72: 0 | BP72: 0 | BQ72: 0 | BR72: 0 | BS72: 18335016
A73: 044180 | B73: Kettering City SD | C73: Montgomery | D73: 46253441 | E73: 7201163 | F73: 0 | G73: 12064948 | H73: 359586 | I73: 0 | J73: 12012738 | K73: 1572870 | L73: 79464746 | M73: 0 | N73: 0 | O73: 0 | P73: 0 | Q73: 218105 | R73: 218105 | S73: 79682851 | T73: 49047597 | U73: 21040161 | V73: 8551143 | W73: 2740622 | X73: 456600 | Y73: 0 | Z73: 0 | AA73: 0 | AB73: 0 | AC73: 0 | AD73: 0 | AE73: 0 | AF73: 0 | AG73: 1133083 | AH73: 82969206 | AI73: 29000 | AJ73: 0 | AK73: 0 | AL73: 29000 | AM73: 82998206 | AN73: -3315355 | AO73: 12331520 | AP73: 9016165 | AQ73: 1060936 | AR73: 0 | AS73: 0 | AT73: 0 | AU73: 0 | AV73: 0 | AW73: 0 | AX73: 0 | AY73: 0 | AZ73: 0 | BA73: 7955229 | BB73: 0 | BC73: 0 | BD73: 0 | BE73: 7955229 | BF73: 0 | BG73: 0 | BH73: 0 | BI73: 0 | BJ73: 7955229 | BS73: 82998206
A74: 044198 | B74: Lakewood City SD | C74: Cuyahoga | D74: 40776091 | E74: 0 | F74: 0 | G74: 19103173 | H74: 440929 | I74: 0 | J74: 4960983 | K74: 4749384 | L74: 70030560 | M74: 0 | N74: 0 | O74: 0 | P74: 1784100 | Q74: 25000 | R74: 1809100 | S74: 71839660 | T74: 41985918 | U74: 13410846 | V74: 9704699 | W74: 1265852 | X74: 2661812 | Y74: 0 | Z74: 0 | AA74: 0 | AB74: 0 | AC74: 0 | AD74: 0 | AE74: 0 | AF74: 0 | AG74: 1180919 | AH74: 70210046 | AI74: 20000 | AJ74: 1900000 | AK74: 0 | AL74: 1920000 | AM74: 72130046 | AN74: -290386 | AO74: 18991730 | AP74: 18701344 | AQ74: 300000 | AR74: 0 | AS74: 0 | AT74: 0 | AU74: 0 | AV74: 0 | AW74: 0 | AX74: 0 | AY74: 0 | AZ74: 0 | BA74: 18401344 | BB74: 0 | BC74: 0 | BD74: 0 | BE74: 18401344 | BF74: 0 | BG74: 0 | BH74: 0 | BI74: 0 | BJ74: 18401344 | BS74: 72130046
A75: 044206 | B75: Lancaster City SD | C75: Fairfield | D75: 17283018 | E75: 3110982 | F75: 10605518 | G75: 21426400 | H75: 397835 | I75: 0 | J75: 4049047 | K75: 2408185 | L75: 59280985 | M75: 0 | N75: 0 | O75: 20000 | P75: 200000 | Q75: 225000 | R75: 445000 | S75: 59725985 | T75: 30975500 | U75: 11127618 | V75: 10695252 | W75: 3988072 | X75: 144646 | Y75: 0 | Z75: 0 | AA75: 0 | AB75: 0 | AC75: 0 | AD75: 0 | AE75: 0 | AF75: 0 | AG75: 763877 | AH75: 57694965 | AI75: 50000 | AJ75: 200000 | AK75: 0 | AL75: 250000 | AM75: 57944965 | AN75: 1781020 | AO75: 31776658 | AP75: 33557678 | AQ75: 1675000 | AR75: 0 | AS75: 0 | AT75: 0 | AU75: 0 | AV75: 0 | AW75: 0 | AX75: 0 | AY75: 0 | AZ75: 0 | BA75: 31882678 | BB75: 0 | BC75: 0 | BD75: 0 | BE75: 31882678 | BF75: 0 | BG75: 0 | BH75: 0 | BI75: 0 | BJ75: 31882678 | BM75: 0 | BN75: 0 | BO75: 0 | BP75: 0 | BQ75: 0 | BR75: 0 | BS75: 59725985
A76: 044214 | B76: Lebanon City SD | C76: Warren | D76: 20055340 | E76: 2290180 | F76: 0 | G76: 17862297 | H76: 84710 | I76: 0 | J76: 3173374 | K76: 1348010 | L76: 44813911 | M76: 0 | N76: 0 | O76: 0 | P76: 800000 | Q76: 25000 | R76: 825000 | S76: 45638911 | T76: 24425781 | U76: 10678771 | V76: 6806946 | W76: 1508243 | X76: 105540 | Y76: 0 | Z76: 0 | AA76: 0 | AB76: 0 | AC76: 0 | AD76: 210000 | AE76: 98000 | AF76: 161488 | AG76: 390991 | AH76: 44385760 | AI76: 0 | AJ76: 800000 | AK76: 2000 | AL76: 802000 | AM76: 45187760 | AN76: 451151 | AO76: 8908067 | AP76: 9359218 | AQ76: 600000 | AR76: 0 | AS76: 0 | AT76: 0 | AU76: 0 | AV76: 0 | AW76: 0 | AX76: 0 | AY76: 0 | AZ76: 0 | BA76: 8759218 | BB76: 0 | BC76: 0 | BD76: 0 | BE76: 8759218 | BF76: 0 | BG76: 0 | BH76: 0 | BI76: 0 | BJ76: 8759218 | BM76: 0 | BN76: 0 | BO76: 0 | BP76: 0 | BQ76: 0 | BR76: 0 | BS76: 45638911
A77: 044222 | B77: Lima City SD | C77: Allen | D77: 7436245 | E77: 656981 | F77: 0 | G77: 33796391 | H77: 823787 | I77: 0 | J77: 965909 | K77: 1216441 | L77: 44895754 | M77: 0 | N77: 0 | O77: 0 | P77: 0 | Q77: 0 | R77: 0 | S77: 44895754 | T77: 23140905 | U77: 7498845 | V77: 12759423 | W77: 700204 | X77: 297530 | Y77: 0 | Z77: 0 | AA77: 0 | AB77: 0 | AC77: 0 | AD77: 0 | AE77: 0 | AF77: 0 | AG77: 160879 | AH77: 44557786 | AI77: 60625 | AJ77: 0 | AK77: 0 | AL77: 60625 | AM77: 44618411 | AN77: 277343 | AO77: 2064541 | AP77: 2341884 | AQ77: 0 | AR77: 0 | AS77: 0 | AT77: 0 | AU77: 0 | AV77: 0 | AW77: 0 | AX77: 0 | AY77: 0 | AZ77: 0 | BA77: 2341884 | BB77: 0 | BC77: 0 | BD77: 0 | BE77: 2341884 | BF77: 0 | BG77: 0 | BH77: 0 | BI77: 0 | BJ77: 2341884 | BK77: 340 | BL77: 3469 | BS77: 44895754
A78: 044230 | B78: Lockland Local SD | C78: Hamilton | D78: 2160783 | E78: 335031 | F78: 0 | G78: 2176904 | H78: 9450 | I78: 0 | J78: 1313683 | K78: 485291 | L78: 6481142 | M78: 0 | N78: 0 | O78: 0 | P78: 0 | Q78: 130000 | R78: 130000 | S78: 6611142 | T78: 3145000 | U78: 1134499 | V78: 2043467 | W78: 114769 | X78: 20436 | Y78: 0 | Z78: 0 | AA78: 0 | AB78: 0 | AC78: 0 | AD78: 0 | AE78: 0 | AF78: 0 | AG78: 146384 | AH78: 6604555 | AI78: 500000 | AJ78: 10000 | AK78: 0 | AL78: 510000 | AM78: 7114555 | AN78: -503413 | AO78: 1148588 | AP78: 645175 | AQ78: 75000 | AR78: 0 | AS78: 0 | AT78: 500000 | AU78: 0 | AV78: 0 | AW78: 0 | AX78: 0 | AY78: 0 | AZ78: 500000 | BA78: 70175 | BB78: 0 | BC78: 0 | BD78: 0 | BE78: 70175 | BF78: 0 | BG78: 0 | BH78: 0 | BI78: 0 | BJ78: 70175 | BM78: 0 | BN78: 0 | BO78: 0 | BP78: 0 | BQ78: 0 | BR78: 0 | BS78: 7114555
A79: 044248 | B79: Logan-Hocking Local SD | C79: Hocking | D79: 7691049 | E79: 1261281 | F79: 0 | G79: 20744592 | H79: 161104 | I79: 0 | J79: 1277439 | K79: 1969362 | L79: 33104827 | M79: 0 | N79: 0 | O79: 0 | P79: 162064 | Q79: 0 | R79: 162064 | S79: 33266891 | T79: 19636065 | U79: 9048093 | V79: 3682425 | W79: 860443 | X79: 25000 | Y79: 0 | Z79: 0 | AA79: 0 | AB79: 0 | AC79: 0 | AD79: 0 | AE79: 0 | AF79: 0 | AG79: 404617 | AH79: 33656643 | AI79: 40000 | AJ79: 125000 | AK79: 0 | AL79: 165000 | AM79: 33821643 | AN79: -554752 | AO79: 7595819 | AP79: 7041067 | AQ79: 300000 | AR79: 0 | AS79: 0 | AT79: 0 | AU79: 0 | AV79: 0 | AW79: 0 | AX79: 0 | AY79: 0 | AZ79: 0 | BA79: 6741067 | BB79: 0 | BC79: 0 | BD79: 0 | BE79: 6741067 | BF79: 0 | BG79: 0 | BH79: 0 | BI79: 0 | BJ79: 6741067 | BM79: 0 | BN79: 0 | BO79: 0 | BP79: 0 | BQ79: 0 | BR79: 0 | BS79: 33821643
A80: 044255 | B80: London City SD | C80: Madison | D80: 5668776 | E80: 0 | F80: 3508498 | G80: 7921382 | H80: 31232 | I80: 0 | J80: 866274 | K80: 1176837 | L80: 19172999 | M80: 0 | N80: 0 | O80: 0 | P80: 300000 | Q80: 46000 | R80: 346000 | S80: 19518999 | T80: 9442608 | U80: 3395192 | V80: 3776050 | W80: 555474 | X80: 419000 | Y80: 0 | Z80: 0 | AA80: 0 | AB80: 0 | AC80: 0 | AD80: 15000 | AE80: 0 | AF80: 5000 | AG80: 356706 | AH80: 17965031 | AI80: 300000 | AJ80: 0 | AK80: 0 | AL80: 300000 | AM80: 18265031 | AN80: 1253968 | AO80: 2119520 | AP80: 3373488 | AQ80: 50000 | AR80: 0 | AS80: 0 | AT80: 1000000 | AU80: 0 | AV80: 0 | AW80: 0 | AX80: 0 | AY80: 0 | AZ80: 1000000 | BA80: 2323488 | BB80: 0 | BC80: 0 | BD80: 0 | BE80: 2323488 | BF80: 0 | BG80: 0 | BH80: 0 | BI80: 0 | BJ80: 2323488 | BS80: 19518999
A81: 044263 | B81: Lorain City SD | C81: Lorain | D81: 16950000 | E81: 709795 | F81: 0 | G81: 66757103 | H81: 1714435 | I81: 0 | J81: 2898416 | K81: 1675000 | L81: 90704749 | M81: 0 | N81: 0 | O81: 0 | P81: 1078754 | Q81: 284000 | R81: 1362754 | S81: 92067503 | T81: 40838192 | U81: 13798405 | V81: 33962939 | W81: 1751956 | X81: 209881 | Y81: 0 | Z81: 0 | AA81: 1583838 | AB81: 0 | AC81: 0 | AD81: 0 | AE81: 0 | AF81: 152163 | AG81: 740000 | AH81: 93037374 | AI81: 227120 | AJ81: 750000 | AK81: 0 | AL81: 977120 | AM81: 94014494 | AN81: -1946991 | AO81: 3970421 | AP81: 2023430 | AQ81: 2000000 | AR81: 0 | AS81: 0 | AT81: 0 | AU81: 0 | AV81: 0 | AW81: 0 | AX81: 0 | AY81: 0 | AZ81: 0 | BA81: 23430 | BB81: 0 | BC81: 0 | BD81: 0 | BE81: 23430 | BF81: 0 | BG81: 0 | BH81: 0 | BI81: 0 | BJ81: 23430 | BK81: 719 | BL81: 8871 | BM81: 0 | BN81: 0 | BO81: 0 | BP81: 0 | BQ81: 0 | BR81: 0 | BS81: 94014494
A82: 044271 | B82: Loveland City SD | C82: Hamilton | D82: 24178837 | E82: 822565 | F82: 0 | G82: 11491788 | H82: 108247 | I82: 0 | J82: 3549185 | K82: 911158 | L82: 41061780 | M82: 0 | N82: 0 | O82: 0 | P82: 20175 | Q82: 0 | R82: 20175 | S82: 41081955 | T82: 26380625 | U82: 9785622 | V82: 3215660 | W82: 1411634 | X82: 296458 | Y82: 0 | Z82: 0 | AA82: 0 | AB82: 0 | AC82: 0 | AD82: 0 | AE82: 0 | AF82: 0 | AG82: 891687 | AH82: 41981686 | AI82: 20000 | AJ82: 0 | AK82: 0 | AL82: 20000 | AM82: 42001686 | AN82: -919731 | AO82: 3758530 | AP82: 2838799 | AQ82: 25000 | AR82: 0 | AS82: 0 | AT82: 0 | AU82: 0 | AV82: 0 | AW82: 0 | AX82: 0 | AY82: 0 | AZ82: 0 | BA82: 2813799 | BB82: 0 | BC82: 0 | BD82: 0 | BE82: 2813799 | BF82: 0 | BG82: 0 | BH82: 0 | BI82: 0 | BJ82: 2813799 | BM82: 0 | BN82: 0 | BO82: 0 | BP82: 0 | BQ82: 0 | BR82: 0 | BS82: 42001686
A83: 044289 | B83: Madeira City SD | C83: Hamilton | D83: 11919281 | E83: 491663 | F83: 0 | G83: 2769323 | H83: 10123 | I83: 0 | J83: 1748599 | K83: 369503 | L83: 17308492 | M83: 0 | N83: 0 | O83: 0 | P83: 0 | Q83: 21708 | R83: 21708 | S83: 17330200 | T83: 9600375 | U83: 3025649 | V83: 3360237 | W83: 597489 | X83: 9500 | Y83: 0 | Z83: 0 | AA83: 0 | AB83: 0 | AC83: 0 | AD83: 0 | AE83: 0 | AF83: 0 | AG83: 318045 | AH83: 16911295 | AI83: 300000 | AJ83: 0 | AK83: 0 | AL83: 300000 | AM83: 17211295 | AN83: 118905 | AO83: 7121601 | AP83: 7240506 | AQ83: 0 | AR83: 0 | AS83: 0 | AT83: 0 | AU83: 0 | AV83: 0 | AW83: 0 | AX83: 0 | AY83: 0 | AZ83: 0 | BA83: 7240506 | BB83: 0 | BC83: 0 | BD83: 0 | BE83: 7240506 | BF83: 0 | BG83: 0 | BH83: 0 | BI83: 0 | BJ83: 7240506 | BM83: 0 | BN83: 0 | BO83: 0 | BP83: 0 | BQ83: 0 | BR83: 0 | BS83: 17330200
A84: 044297 | B84: Mansfield City SD | C84: Richland | D84: 9180000 | E84: 950000 | F84: 0 | G84: 31145644 | H84: 496000 | I84: 0 | J84: 1807416 | K84: 2265092 | L84: 45844152 | M84: 0 | N84: 0 | O84: 0 | P84: 0 | Q84: 809000 | R84: 809000 | S84: 46653152 | T84: 26254496 | U84: 11942726 | V84: 15317657 | W84: 961171 | X84: 355009 | Y84: 0 | Z84: 0 | AA84: 210000 | AB84: 0 | AC84: 0 | AD84: 0 | AE84: 0 | AF84: 137731 | AG84: 629066 | AH84: 55807856 | AI84: 0 | AJ84: 0 | AK84: 0 | AL84: 0 | AM84: 55807856 | AN84: -9154704 | AO84: 2986183 | AP84: -6168521 | AQ84: 360000 | AR84: 0 | AS84: 0 | AT84: 0 | AU84: 0 | AV84: 0 | AW84: 0 | AX84: 0 | AY84: 0 | AZ84: 0 | BA84: -6528521 | BB84: 0 | BC84: 0 | BD84: 0 | BE84: -6528521 | BF84: 0 | BG84: 2000000 | BH84: 2000000 | BI84: 0 | BJ84: -4528521 | BK84: 358 | BL84: 3156 | BM84: 0 | BN84: 0 | BO84: 0 | BP84: 0 | BQ84: 0 | BR84: 0 | BS84: 55807856
A85: 044305 | B85: Maple Heights City SD | C85: Cuyahoga | D85: 12600000 | E85: 0 | F85: 0 | G85: 18994827 | H85: 415000 | I85: 0 | J85: 2016177 | K85: 1362601 | L85: 35388605 | M85: 2411000 | N85: 0 | O85: 0 | P85: 0 | Q85: 0 | R85: 2411000 | S85: 37799605 | T85: 19665187 | U85: 7775462 | V85: 6838189 | W85: 703000 | X85: 75000 | Y85: 0 | Z85: 0 | AA85: 2511000 | AB85: 0 | AC85: 0 | AD85: 0 | AE85: 0 | AF85: 31400 | AG85: 457000 | AH85: 38056238 | AI85: 575000 | AJ85: 0 | AK85: 0 | AL85: 575000 | AM85: 38631238 | AN85: -831633 | AO85: 1178072 | AP85: 346439 | AQ85: 50000 | AR85: 0 | AS85: 0 | AT85: 0 | AU85: 0 | AV85: 0 | AW85: 0 | AX85: 0 | AY85: 0 | AZ85: 0 | BA85: 296439 | BB85: 0 | BC85: 0 | BD85: 0 | BE85: 296439 | BF85: 0 | BG85: 0 | BH85: 0 | BI85: 0 | BJ85: 296439 | BK85: 0 | BL85: 0 | BM85: 0 | BN85: 0 | BO85: 0 | BP85: 0 | BQ85: 0 | BR85: 0 | BS85: 38631238
A86: 044313 | B86: Mariemont City SD | C86: Hamilton | D86: 13674496 | E86: 890932 | F86: 0 | G86: 2893867 | H86: 0 | I86: 0 | J86: 2644731 | K86: 200000 | L86: 20304026 | M86: 0 | N86: 0 | O86: 25000 | P86: 0 | Q86: 0 | R86: 25000 | S86: 20329026 | T86: 11838438 | U86: 3733689 | V86: 3828900 | W86: 676671 | X86: 302568 | Y86: 0 | Z86: 0 | AA86: 0 | AB86: 0 | AC86: 0 | AD86: 0 | AE86: 195901 | AF86: 121003 | AG86: 345200 | AH86: 21042370 | AI86: 50000 | AJ86: 0 | AK86: 0 | AL86: 50000 | AM86: 21092370 | AN86: -763344 | AO86: 6733739 | AP86: 5970395 | AQ86: 0 | AR86: 0 | AS86: 0 | AT86: 0 | AU86: 0 | AV86: 0 | AW86: 0 | AX86: 0 | AY86: 0 | AZ86: 0 | BA86: 5970395 | BB86: 0 | BC86: 0 | BD86: 0 | BE86: 5970395 | BF86: 0 | BG86: 0 | BH86: 0 | BI86: 0 | BJ86: 5970395 | BK86: 132 | BL86: 1556 | BM86: 0 | BN86: 0 | BO86: 0 | BP86: 0 | BQ86: 0 | BR86: 0 | BS86: 21092370
A87: 044321 | B87: Marietta City SD | C87: Washington | D87: 11180512 | E87: 895309 | F87: 0 | G87: 8087953 | H87: 24403 | I87: 0 | J87: 1135896 | K87: 1089487 | L87: 22413560 | M87: 0 | N87: 0 | O87: 80000 | P87: 10000 | Q87: 10000 | R87: 100000 | S87: 22513560 | T87: 11989003 | U87: 6025603 | V87: 3314146 | W87: 683547 | X87: 55371 | Y87: 0 | Z87: 0 | AA87: 0 | AB87: 0 | AC87: 0 | AD87: 146000 | AE87: 0 | AF87: 48285 | AG87: 408082 | AH87: 22670037 | AI87: 70000 | AJ87: 10000 | AK87: 5000 | AL87: 85000 | AM87: 22755037 | AN87: -241477 | AO87: 2078194 | AP87: 1836717 | AQ87: 75000 | AR87: 0 | AS87: 0 | AT87: 0 | AU87: 0 | AV87: 0 | AW87: 0 | AX87: 0 | AY87: 0 | AZ87: 0 | BA87: 1761717 | BB87: 0 | BC87: 0 | BD87: 0 | BE87: 1761717 | BF87: 0 | BG87: 0 | BH87: 0 | BI87: 0 | BJ87: 1761717 | BM87: 0 | BN87: 0 | BO87: 0 | BP87: 0 | BQ87: 0 | BR87: 0 | BS87: 22755037
A88: 044339 | B88: Marion City SD | C88: Marion | D88: 7701005 | E88: 0 | F88: 0 | G88: 33141409 | H88: 154808 | I88: 0 | J88: 1200000 | K88: 3429460 | L88: 45626682 | M88: 0 | N88: 0 | O88: 0 | P88: 0 | Q88: 0 | R88: 0 | S88: 45626682 | T88: 23494431 | U88: 9943364 | V88: 11361638 | W88: 1100786 | X88: 588000 | Y88: 0 | Z88: 0 | AA88: 0 | AB88: 0 | AC88: 0 | AD88: 102828 | AE88: 0 | AF88: 63905 | AG88: 1001725 | AH88: 47656677 | AI88: 75000 | AJ88: 0 | AK88: 0 | AL88: 75000 | AM88: 47731677 | AN88: -2104995 | AO88: 14498123 | AP88: 12393128 | AQ88: 800000 | AR88: 0 | AS88: 0 | AT88: 0 | AU88: 0 | AV88: 0 | AW88: 0 | AX88: 0 | AY88: 0 | AZ88: 0 | BA88: 11593128 | BB88: 0 | BC88: 0 | BD88: 0 | BE88: 11593128 | BF88: 0 | BG88: 0 | BH88: 0 | BI88: 0 | BJ88: 11593128 | BK88: 425 | BL88: 4650 | BM88: 0 | BN88: 0 | BO88: 0 | BP88: 0 | BQ88: 0 | BR88: 0 | BS88: 47731677
A89: 044347 | B89: Martins Ferry City SD | C89: Belmont | D89: 2100000 | E89: 0 | F89: 0 | G89: 9133643 | H89: 134658 | I89: 0 | J89: 350000 | K89: 1387661 | L89: 13105962 | M89: 0 | N89: 0 | O89: 0 | P89: 0 | Q89: 76840 | R89: 76840 | S89: 13182802 | T89: 5212167 | U89: 2947982 | V89: 2038300 | W89: 592000 | X89: 278850 | Y89: 0 | Z89: 0 | AA89: 121000 | AB89: 0 | AC89: 0 | AD89: 0 | AE89: 0 | AF89: 119180 | AG89: 149422 | AH89: 11458901 | AI89: 1636030 | AJ89: 0 | AK89: 0 | AL89: 1636030 | AM89: 13094931 | AN89: 87871 | AO89: 1133137 | AP89: 1221008 | AQ89: 40000 | AR89: 0 | AS89: 0 | AT89: 0 | AU89: 0 | AV89: 0 | AW89: 0 | AX89: 0 | AY89: 0 | AZ89: 0 | BA89: 1181008 | BB89: 0 | BC89: 0 | BD89: 0 | BE89: 1181008 | BF89: 0 | BG89: 0 | BH89: 0 | BI89: 0 | BJ89: 1181008 | BK89: 0 | BL89: 0 | BM89: 0 | BN89: 0 | BO89: 0 | BP89: 0 | BQ89: 0 | BR89: 0 | BS89: 13182802
A90: 044354 | B90: Massillon City SD | C90: Stark | D90: 13195846 | E90: 0 | F90: 35760 | G90: 20162831 | H90: 475512 | J90: 2694211 | K90: 2075235 | L90: 38639396 | M90: 0 | N90: 0 | O90: 0 | P90: 101076 | Q90: 257439 | R90: 358515 | S90: 38997910 | T90: 21773435 | U90: 8182486 | V90: 6280686 | W90: 736599 | X90: 253528 | Y90: 0 | Z90: 0 | AA90: 0 | AB90: 0 | AC90: 0 | AD90: 0 | AE90: 0 | AF90: 0 | AG90: 656354 | AH90: 37883089 | AI90: 0 | AJ90: 4852 | AK90: 0 | AL90: 4852 | AM90: 37887941 | AN90: 1109970 | AO90: 4867389 | AP90: 5977358 | AQ90: 0 | AR90: 0 | AS90: 0 | AT90: 0 | AU90: 0 | AW90: 0 | AX90: 0 | AY90: 0 | AZ90: 0 | BA90: 5977358 | BB90: 0 | BC90: 0 | BD90: 0 | BE90: 5977358 | BF90: 0 | BG90: 0 | BH90: 0 | BJ90: 5977358 | BK90: 310 | BL90: 3641 | BS90: 38997910
A91: 044362 | B91: Maumee City SD | C91: Lucas | D91: 18066897 | E91: 660866 | F91: 0 | G91: 4209126 | H91: 15083 | I91: 0 | J91: 4905422 | K91: 535586 | L91: 28392980 | M91: 0 | N91: 0 | O91: 0 | P91: 30000 | Q91: 0 | R91: 30000 | S91: 28422980 | T91: 17445727 | U91: 6464397 | V91: 3299170 | W91: 902083 | X91: 55984 | Y91: 0 | Z91: 0 | AA91: 0 | AB91: 0 | AC91: 0 | AD91: 0 | AE91: 0 | AF91: 0 | AG91: 470345 | AH91: 28637706 | AI91: 442800 | AJ91: 30000 | AK91: 0 | AL91: 472800 | AM91: 29110506 | AN91: -687526 | AO91: 3184813 | AP91: 2497287 | AQ91: 0 | AR91: 0 | AS91: 0 | AT91: 0 | AU91: 0 | AV91: 0 | AW91: 0 | AX91: 0 | AY91: 0 | AZ91: 0 | BA91: 2497287 | BB91: 0 | BC91: 0 | BD91: 0 | BE91: 2497287 | BF91: 0 | BG91: 0 | BH91: 0 | BI91: 0 | BJ91: 2497287 | BM91: 0 | BN91: 0 | BO91: 0 | BP91: 0 | BQ91: 0 | BR91: 0 | BS91: 29110506
A92: 044370 | B92: Mayfield City SD | C92: Cuyahoga | D92: 50147802 | E92: 0 | F92: 0 | G92: 5640295 | H92: 0 | I92: 0 | J92: 5827114 | K92: 2795332 | L92: 64410543 | M92: 0 | N92: 0 | O92: 0 | P92: 460000 | Q92: 0 | R92: 460000 | S92: 64870543 | T92: 34386600 | U92: 13041552 | V92: 10185514 | W92: 2406950 | X92: 282750 | Y92: 0 | Z92: 0 | AA92: 0 | AB92: 0 | AC92: 0 | AD92: 0 | AE92: 0 | AF92: 0 | AG92: 1209599 | AH92: 61512965 | AI92: 475000 | AJ92: 600000 | AK92: 0 | AL92: 1075001 | AM92: 62587966 | AN92: 2282577 | AO92: 25191689 | AP92: 27474267 | AQ92: 2940004 | AR92: 0 | AS92: 0 | AT92: 0 | AU92: 0 | AV92: 0 | AW92: 0 | AX92: 0 | AY92: 0 | AZ92: 0 | BA92: 24534263 | BB92: 0 | BC92: 0 | BD92: 0 | BE92: 24534263 | BF92: 0 | BG92: 0 | BH92: 0 | BI92: 0 | BJ92: 24534263 | BM92: 0 | BN92: 0 | BO92: 0 | BP92: 0 | BQ92: 0 | BR92: 0 | BS92: 64870543
A93: 044388 | B93: Medina City SD | C93: Medina | D93: 39750475 | E93: 1920091 | G93: 16600000 | H93: 31797 | J93: 8528298 | K93: 1400000 | L93: 68230661 | M93: 0 | O93: 0 | P93: 126000 | Q93: 550000 | R93: 676000 | S93: 68906661 | T93: 39792788 | U93: 15603769 | V93: 8938121 | W93: 1832505 | X93: 620000 | AA93: 0 | AF93: 0 | AG93: 1750000 | AH93: 68537183 | AI93: 550000 | AJ93: 50000 | AL93: 600000 | AM93: 69137183 | AN93: -230522 | AO93: 21423295 | AP93: 21192773 | AQ93: 450000 | AT93: 3426859 | BA93: 17315914 | BE93: 17315914 | BJ93: 20622414 | BK93: 579 | BL93: 7335 | BS93: 69137183
A94: 044396 | B94: Miamisburg City SD | C94: Montgomery | D94: 28229935 | E94: 1048600 | F94: 0 | G94: 12197150 | H94: 181540 | I94: 0 | J94: 5268645 | K94: 1560500 | L94: 48486370 | M94: 0 | N94: 0 | O94: 0 | P94: 81500 | Q94: 150000 | R94: 231500 | S94: 48717870 | T94: 28914275 | U94: 10485160 | V94: 6708198 | W94: 1337930 | X94: 0 | Y94: 0 | Z94: 0 | AA94: 0 | AB94: 0 | AC94: 0 | AD94: 0 | AE94: 0 | AF94: 0 | AG94: 1082200 | AH94: 48527763 | AI94: 554000 | AJ94: 40000 | AK94: 0 | AL94: 594000 | AM94: 49121763 | AN94: -403893 | AO94: 7994761 | AP94: 7590868 | AQ94: 700000 | AR94: 0 | AS94: 0 | AT94: 0 | AU94: 0 | AV94: 0 | AW94: 0 | AX94: 0 | AY94: 0 | AZ94: 0 | BA94: 6890868 | BB94: 0 | BC94: 0 | BD94: 0 | BE94: 6890868 | BF94: 0 | BG94: 0 | BH94: 0 | BI94: 0 | BJ94: 6890868 | BM94: 0 | BN94: 0 | BO94: 0 | BP94: 0 | BQ94: 0 | BR94: 0 | BS94: 49121763
A95: 044404 | B95: Middletown City SD | C95: Butler | D95: 27592794 | E95: 0 | F95: 0 | G95: 29674192 | H95: 150000 | I95: 0 | J95: 8314033 | K95: 3132332 | L95: 68863351 | M95: 0 | N95: 0 | O95: 0 | P95: 1500000 | Q95: 0 | R95: 1500000 | S95: 70363351 | T95: 28997574 | U95: 11670361 | V95: 22716580 | W95: 1016870 | X95: 1600000 | Y95: 0 | Z95: 0 | AA95: 0 | AB95: 0 | AC95: 0 | AD95: 160580 | AE95: 0 | AF95: 59121 | AG95: 705227 | AH95: 66926313 | AI95: 700000 | AJ95: 1500000 | AK95: 0 | AL95: 2200000 | AM95: 69126313 | AN95: 1237039 | AO95: 1523219 | AP95: 2760258 | AQ95: 725000 | AR95: 0 | AS95: 0 | AT95: 0 | AU95: 0 | AV95: 0 | AW95: 0 | AX95: 0 | AY95: 0 | AZ95: 0 | BA95: 2035258 | BB95: 0 | BC95: 0 | BD95: 0 | BE95: 2035258 | BF95: 0 | BG95: 0 | BH95: 0 | BI95: 0 | BJ95: 2035258 | BK95: 0 | BL95: 0 | BM95: 0 | BN95: 0 | BO95: 0 | BP95: 0 | BQ95: 0 | BR95: 0 | BS95: 70363351
A96: 044412 | B96: Mt Healthy City SD | C96: Hamilton | D96: 11238753 | E96: 0 | F96: 0 | G96: 21415183 | H96: 185000 | I96: 0 | J96: 1701585 | K96: 970583 | L96: 35511104 | M96: 0 | N96: 0 | O96: 0 | P96: 151071 | Q96: 87261 | R96: 238332 | S96: 35749436 | T96: 14659995 | U96: 5130128 | V96: 13278497 | W96: 1039741 | X96: 117733 | Y96: 0 | Z96: 0 | AA96: 0 | AB96: 0 | AC96: 0 | AD96: 0 | AE96: 0 | AF96: 0 | AG96: 402541 | AH96: 34628635 | AI96: 198175 | AJ96: 170305 | AK96: 13485 | AL96: 381965 | AM96: 35010600 | AN96: 738836 | AO96: 6721309 | AP96: 7460145 | AQ96: 0 | AR96: 0 | AS96: 0 | AT96: 0 | AU96: 0 | AV96: 0 | AW96: 0 | AX96: 0 | AY96: 0 | AZ96: 0 | BA96: 7460145 | BB96: 0 | BC96: 0 | BD96: 0 | BE96: 7460145 | BF96: 0 | BG96: 0 | BH96: 0 | BI96: 0 | BJ96: 7460145 | BK96: 0 | BL96: 0 | BM96: 0 | BN96: 0 | BO96: 0 | BP96: 0 | BQ96: 0 | BR96: 0 | BS96: 35749436
A97: 044420 | B97: Mount Vernon City SD | C97: Knox | D97: 13183444 | E97: 821156 | F97: 0 | G97: 13432286 | H97: 51724 | I97: 0 | J97: 2361309 | K97: 2226908 | L97: 32076827 | M97: 0 | N97: 0 | O97: 0 | P97: 0 | Q97: 200000 | R97: 200000 | S97: 32276827 | T97: 17947009 | U97: 6132774 | V97: 4867840 | W97: 679226 | X97: 62234 | Y97: 0 | Z97: 0 | AA97: 0 | AB97: 0 | AC97: 0 | AD97: 0 | AE97: 0 | AF97: 0 | AG97: 2215427 | AH97: 31904510 | AI97: 92300 | AJ97: 0 | AK97: 0 | AL97: 92300 | AM97: 31996810 | AN97: 280017 | AO97: 1150829 | AP97: 1430846 | AQ97: 60000 | AR97: 0 | AS97: 0 | AT97: 0 | AU97: 0 | AV97: 0 | AW97: 0 | AX97: 0 | AY97: 0 | AZ97: 0 | BA97: 1370846 | BB97: 0 | BC97: 0 | BD97: 0 | BE97: 1370846 | BF97: 0 | BG97: 0 | BH97: 0 | BI97: 0 | BJ97: 1370846 | BM97: 0 | BN97: 0 | BO97: 0 | BP97: 0 | BQ97: 0 | BR97: 0 | BS97: 32276827
A98: 044438 | B98: Napoleon Area City SD | C98: Henry | D98: 7127776 | E98: 276453 | F98: 0 | G98: 8310000 | H98: 40000 | I98: 0 | J98: 3049128 | K98: 1235942 | L98: 20039299 | M98: 0 | N98: 0 | O98: 0 | P98: 55000 | Q98: 65000 | R98: 120000 | S98: 20159299 | T98: 10804549 | U98: 4108012 | V98: 4071166 | W98: 664924 | X98: 1103021 | Y98: 0 | Z98: 0 | AA98: 0 | AB98: 0 | AC98: 0 | AD98: 0 | AE98: 0 | AF98: 0 | AG98: 420542 | AH98: 21172213 | AI98: 240000 | AJ98: 10000 | AK98: 0 | AL98: 250000 | AM98: 21422213 | AN98: -1262914 | AO98: 9242760 | AP98: 7979846 | AQ98: 350000 | AR98: 0 | AS98: 0 | AT98: 252152 | AU98: 0 | AV98: 0 | AW98: 0 | AX98: 0 | AY98: 0 | AZ98: 252152 | BA98: 7377694 | BB98: 0 | BC98: 0 | BD98: 0 | BE98: 7377694 | BF98: 0 | BG98: 0 | BH98: 0 | BI98: 0 | BJ98: 7377694 | BK98: 200 | BL98: 1850 | BM98: 0 | BN98: 0 | BO98: 0 | BP98: 0 | BQ98: 0 | BR98: 0 | BS98: 21422213
A99: 044446 | B99: Nelsonville-York City SD | C99: Athens | D99: 1457196 | E99: 336500 | F99: 0 | G99: 8939039 | H99: 9214 | I99: 0 | J99: 240237 | K99: 773493 | L99: 11755679 | M99: 0 | N99: 0 | O99: 128500 | P99: 0 | Q99: 91996 | R99: 220496 | S99: 11976175 | T99: 6298561 | U99: 2740976 | V99: 1341406 | W99: 630467 | X99: 107469 | Y99: 0 | Z99: 0 | AA99: 103000 | AB99: 0 | AC99: 0 | AD99: 0 | AE99: 0 | AF99: 25517 | AG99: 251453 | AH99: 11498849 | AI99: 163518 | AJ99: 5500 | AK99: 0 | AL99: 169018 | AM99: 11667867 | AN99: 308308 | AO99: 3549519 | AP99: 3857827 | AQ99: 38000 | AR99: 0 | AS99: 20000 | AT99: 0 | AU99: 0 | AV99: 0 | AW99: 0 | AX99: 0 | AY99: 0 | AZ99: 20000 | BA99: 3799827 | BB99: 0 | BC99: 0 | BD99: 0 | BE99: 3799827 | BF99: 0 | BG99: 0 | BH99: 0 | BI99: 0 | BJ99: 3799827 | BM99: 0 | BN99: 0 | BO99: 0 | BP99: 0 | BQ99: 0 | BR99: 0 | BS99: 11976175
A100: 044453 | B100: Newark City SD | C100: Licking | D100: 18431767 | E100: 1124593 | F100: 8211538 | G100: 28259649 | H100: 97789 | J100: 2683521 | K100: 2045228 | L100: 60854085 | M100: 0 | N100: 0 | O100: 250000 | P100: 127476 | Q100: 172893 | R100: 550369 | S100: 61404454 | T100: 34110767 | U100: 12375301 | V100: 12085983 | W100: 2231313 | X100: 0 | Y100: 0 | Z100: 0 | AA100: 0 | AB100: 0 | AC100: 0 | AD100: 0 | AE100: 0 | AF100: 0 | AG100: 664171 | AH100: 61467535 | AI100: 250000 | AJ100: 130000 | AK100: 0 | AL100: 380000 | AM100: 61847535 | AN100: -443081 | AO100: 16033865 | AP100: 15590784 | AQ100: 1500000 | AR100: 0 | AS100: 0 | AT100: 934406 | AU100: 0 | AW100: 0 | AX100: 0 | AY100: 0 | AZ100: 934406 | BA100: 13545741 | BB100: 0 | BC100: 0 | BD100: 0 | BE100: 13545741 | BF100: 0 | BG100: 0 | BH100: 0 | BJ100: 13545741 | BK100: 600 | BL100: 5600 | BS100: 61847535
...
