Workbook

Sheet Summary
B3: Actual 2012 | C3: Projected 2012/13 | F3: 0.92307692
A4: BUDGET DIVISION | B4: BUDGET | C4: SALARIES | D4: ADMIN & SUPPORT | E4: OPERATING | F4: Formula Allocation | G4: 10/11 Expenditure | H4: +/- last year
A6: President | B6: =GETPIVOTDATA("BEGINNING BUDGET",'fy12 budget (2)'!$A$3,"Division","1") -> 1715950 | C6: =Calculations!N8 -> 1015869 | D6: =INDIRECT(ADDRESS(MATCH(A6,Calculations!B:B,0),15,1,1,"Calculations")) -> 0 | E6: =INDIRECT(ADDRESS(MATCH(A6,Calculations!B:B,0),16,1,1,"Calculations")) -> 276744.4 | F6: =INDIRECT(ADDRESS(MATCH(A6,Calculations!B:B,0),17,1,1,"Calculations")) -> 1292613.4 | G6: =GETPIVOTDATA("TOTAL EXPENSE",'FY11 expense (2)'!$A$4,"Division","1") -> 1767758.3 | H6: =F6-B6 -> -423336.6
A7: Provost | B7: =GETPIVOTDATA("BEGINNING BUDGET",'fy12 budget (2)'!$A$3,"Division","2")-(SUM(B12:B33)) -> 4998016 | C7: =Calculations!N9 -> 3900785 | D7: =INDIRECT(ADDRESS(MATCH(A7,Calculations!B:B,0),15,1,1,"Calculations")) -> 0 | E7: =INDIRECT(ADDRESS(MATCH(A7,Calculations!B:B,0),16,1,1,"Calculations")) -> 1062657.1 | F7: =INDIRECT(ADDRESS(MATCH(A7,Calculations!B:B,0),17,1,1,"Calculations")) -> 4963442.1 | G7: =GETPIVOTDATA("TOTAL EXPENSE",'FY11 expense (2)'!$A$4,"Division","2")-(SUM(G12:G33)) -> 6538746.9 | H7: =F7-B7 -> -34573.904
A8: Finance & Aministration | B8: =GETPIVOTDATA("BEGINNING BUDGET",'fy12 budget (2)'!$A$3,"Division","3") -> 11834075 | C8: =Calculations!N10 -> 3762774 | D8: =INDIRECT(ADDRESS(MATCH(A8,Calculations!B:B,0),15,1,1,"Calculations")) -> 0 | E8: =INDIRECT(ADDRESS(MATCH(A8,Calculations!B:B,0),16,1,1,"Calculations")) -> 1025060 | F8: =INDIRECT(ADDRESS(MATCH(A8,Calculations!B:B,0),17,1,1,"Calculations")) -> 4787834 | G8: =GETPIVOTDATA("TOTAL EXPENSE",'FY11 expense (2)'!$A$4,"Division","3") -> 13064220 | H8: =F8-B8 -> -7046241
A9: Strategy, Planning & Policy | B9: =GETPIVOTDATA("BEGINNING BUDGET",'fy12 budget (2)'!$A$3,"Division","4") -> 272144 | C9: =Calculations!N11 -> 0 | D9: =INDIRECT(ADDRESS(MATCH(A9,Calculations!B:B,0),15,1,1,"Calculations")) -> 0 | E9: =INDIRECT(ADDRESS(MATCH(A9,Calculations!B:B,0),16,1,1,"Calculations")) -> 0 | F9: =INDIRECT(ADDRESS(MATCH(A9,Calculations!B:B,0),17,1,1,"Calculations")) -> 0 | G9: =GETPIVOTDATA("TOTAL EXPENSE",'FY11 expense (2)'!$A$4,"Division","4") -> 244753.55 | H9: =F9-B9 -> -272144
A10: Student Services & Enrollment Management | B10: =GETPIVOTDATA("BEGINNING BUDGET",'fy12 budget (2)'!$A$3,"Division","5") -> 2658064 | C10: =Calculations!N12 -> 1895281 | D10: =INDIRECT(ADDRESS(MATCH(A10,Calculations!B:B,0),15,1,1,"Calculations")) -> 84925 | E10: =INDIRECT(ADDRESS(MATCH(A10,Calculations!B:B,0),16,1,1,"Calculations")) -> 516315 | F10: =INDIRECT(ADDRESS(MATCH(A10,Calculations!B:B,0),17,1,1,"Calculations")) -> 2496521 | G10: =GETPIVOTDATA("TOTAL EXPENSE",'FY11 expense (2)'!$A$4,"Division","5") -> 2649386.4 | H10: =F10-B10 -> -161543
A11: Development | B11: =GETPIVOTDATA("BEGINNING BUDGET",'fy12 budget (2)'!$A$3,"Division","6") -> 449832 | C11: =Calculations!N13 -> 427804 | D11: =INDIRECT(ADDRESS(MATCH(A11,Calculations!B:B,0),15,1,1,"Calculations")) -> 0 | E11: =INDIRECT(ADDRESS(MATCH(A11,Calculations!B:B,0),16,1,1,"Calculations")) -> 116542.94 | F11: =INDIRECT(ADDRESS(MATCH(A11,Calculations!B:B,0),17,1,1,"Calculations"))-95000 -> 449346.94 | G11: =GETPIVOTDATA("TOTAL EXPENSE",'FY11 expense (2)'!$A$4,"Division","6") -> 279189.07 | H11: =F11-B11 -> -485.05892
A12: Agriculture | B12: =GETPIVOTDATA("BEGINNING BUDGET",'fy12 budget'!$A$6,"DEPARTMENT","Agriculture") -> 591449 | C12: =INDIRECT(ADDRESS(MATCH(A12,Calculations!B:B,0),14,1,1,"Calculations")) -> 520790.48 | D12: =INDIRECT(ADDRESS(MATCH(A12,Calculations!B:B,0),15,1,1,"Calculations")) -> 92923.575 | E12: =INDIRECT(ADDRESS(MATCH(A12,Calculations!B:B,0),16,1,1,"Calculations")) -> 59116.727 | F12: =INDIRECT(ADDRESS(MATCH(A12,Calculations!B:B,0),17,1,1,"Calculations")) -> 672830.78 | G12: =GETPIVOTDATA("TOTAL EXPENSE",'FY11 expense'!$A$6,"DEPARTMENT","Agriculture") -> 599585.43 | H12: =F12-B12 -> 81381.784
A13: Art & Music | B13: =GETPIVOTDATA("BEGINNING BUDGET",'fy12 budget'!$A$6,"DEPARTMENT","Art and Music") -> 1229055 | C13: =INDIRECT(ADDRESS(MATCH(A13,Calculations!B:B,0),14,1,1,"Calculations")) -> 643983.85 | D13: =INDIRECT(ADDRESS(MATCH(A13,Calculations!B:B,0),15,1,1,"Calculations")) -> 97091.326 | E13: =INDIRECT(ADDRESS(MATCH(A13,Calculations!B:B,0),16,1,1,"Calculations")) -> 89920.186 | F13: =INDIRECT(ADDRESS(MATCH(A13,Calculations!B:B,0),17,1,1,"Calculations")) -> 830995.36 | G13: =GETPIVOTDATA("TOTAL EXPENSE",'FY11 expense'!$A$6,"DEPARTMENT","Art and Music") -> 1225927.7 | H13: =F13-B13 -> -398059.64
A14: Biology | B14: =GETPIVOTDATA("BEGINNING BUDGET",'fy12 budget'!$A$6,"DEPARTMENT","Biology") -> 1108636 | C14: =INDIRECT(ADDRESS(MATCH(A14,Calculations!B:B,0),14,1,1,"Calculations")) -> 953090.97 | D14: =INDIRECT(ADDRESS(MATCH(A14,Calculations!B:B,0),15,1,1,"Calculations")) -> 101174.16 | E14: =INDIRECT(ADDRESS(MATCH(A14,Calculations!B:B,0),16,1,1,"Calculations")) -> 120096.04 | F14: =INDIRECT(ADDRESS(MATCH(A14,Calculations!B:B,0),17,1,1,"Calculations")) -> 1174361.2 | G14: =GETPIVOTDATA("TOTAL EXPENSE",'FY11 expense'!$A$6,"DEPARTMENT","Biology") -> 1165519.6 | H14: =F14-B14 -> 65725.168
A15: Chemistry & Biochemistry | B15: =GETPIVOTDATA("BEGINNING BUDGET",'fy12 budget'!$A$6,"DEPARTMENT","Chemistry and Biochemistry") -> 531545 | C15: =INDIRECT(ADDRESS(MATCH(A15,Calculations!B:B,0),14,1,1,"Calculations")) -> 419992.86 | D15: =INDIRECT(ADDRESS(MATCH(A15,Calculations!B:B,0),15,1,1,"Calculations")) -> 92831.811 | E15: =INDIRECT(ADDRESS(MATCH(A15,Calculations!B:B,0),16,1,1,"Calculations")) -> 58438.505 | F15: =INDIRECT(ADDRESS(MATCH(A15,Calculations!B:B,0),17,1,1,"Calculations")) -> 571263.18 | G15: =GETPIVOTDATA("TOTAL EXPENSE",'FY11 expense'!$A$6,"DEPARTMENT","Chemistry and Biochemistry") -> 595096.85 | H15: =F15-B15 -> 39718.179
A16: Communication, Mass Media, & Theatre | B16: =GETPIVOTDATA("BEGINNING BUDGET",'fy12 budget'!$A$6,"DEPARTMENT","Communication, Mass Media & Theatre") -> 989795 | C16: =INDIRECT(ADDRESS(MATCH(A16,Calculations!B:B,0),14,1,1,"Calculations")) -> 892534.33 | D16: =INDIRECT(ADDRESS(MATCH(A16,Calculations!B:B,0),15,1,1,"Calculations")) -> 99937.394 | E16: =INDIRECT(ADDRESS(MATCH(A16,Calculations!B:B,0),16,1,1,"Calculations")) -> 110955.21 | F16: =INDIRECT(ADDRESS(MATCH(A16,Calculations!B:B,0),17,1,1,"Calculations")) -> 1103426.9 | G16: =GETPIVOTDATA("TOTAL EXPENSE",'FY11 expense'!$A$6,"DEPARTMENT","Communication, Mass Media & Theatre") -> 1256290.9 | H16: =F16-B16 -> 113631.94
A17: English & Modern Langagues | B17: =GETPIVOTDATA("BEGINNING BUDGET",'fy12 budget'!$A$6,"DEPARTMENT","English and Modern Languages") -> 1663079 | C17: =INDIRECT(ADDRESS(MATCH(A17,Calculations!B:B,0),14,1,1,"Calculations")) -> 1370462.8 | D17: =INDIRECT(ADDRESS(MATCH(A17,Calculations!B:B,0),15,1,1,"Calculations")) -> 109647.99 | E17: =INDIRECT(ADDRESS(MATCH(A17,Calculations!B:B,0),16,1,1,"Calculations")) -> 182725.35 | F17: =INDIRECT(ADDRESS(MATCH(A17,Calculations!B:B,0),17,1,1,"Calculations")) -> 1662836.2 | G17: =GETPIVOTDATA("TOTAL EXPENSE",'FY11 expense'!$A$6,"DEPARTMENT","English and Modern languages") -> 1561489.3 | H17: =F17-B17 -> -242.83926
A18: Pol Science | B18: =GETPIVOTDATA("BEGINNING BUDGET",'fy12 budget'!$A$6,"DEPARTMENT","Political Science") -> 462519 | C18: =INDIRECT(ADDRESS(MATCH(A18,Calculations!B:B,0),14,1,1,"Calculations")) -> 329746.23 | D18: =INDIRECT(ADDRESS(MATCH(A18,Calculations!B:B,0),15,1,1,"Calculations")) -> 91112.939 | E18: =INDIRECT(ADDRESS(MATCH(A18,Calculations!B:B,0),16,1,1,"Calculations")) -> 45734.482 | F18: =INDIRECT(ADDRESS(MATCH(A18,Calculations!B:B,0),17,1,1,"Calculations")) -> 466593.65 | G18: =GETPIVOTDATA("TOTAL EXPENSE",'FY11 expense'!$A$6,"DEPARTMENT","Political Science") -> 813960.94 | H18: =F18-B18 -> 4074.6532
A19: History | B19: =GETPIVOTDATA("BEGINNING BUDGET",'fy12 budget'!$A$6,"DEPARTMENT","History") -> 762149 | C19: =INDIRECT(ADDRESS(MATCH(A19,Calculations!B:B,0),14,1,1,"Calculations")) -> 990543.63 | D19: =INDIRECT(ADDRESS(MATCH(A19,Calculations!B:B,0),15,1,1,"Calculations")) -> 103151.89 | E19: =INDIRECT(ADDRESS(MATCH(A19,Calculations!B:B,0),16,1,1,"Calculations")) -> 134713.25 | F19: =INDIRECT(ADDRESS(MATCH(A19,Calculations!B:B,0),17,1,1,"Calculations")) -> 1228408.8 | G19: =GETPIVOTDATA("TOTAL EXPENSE",'FY11 expense'!$A$6,"DEPARTMENT","History") -> 747361.15 | H19: =F19-B19 -> 466259.77
A20: Mathematics & Computer Science | B20: =GETPIVOTDATA("BEGINNING BUDGET",'fy12 budget'!$A$6,"DEPARTMENT","Mathematics and Computer Science") -> 1259999 | C20: =INDIRECT(ADDRESS(MATCH(A20,Calculations!B:B,0),14,1,1,"Calculations")) -> 1061559.7 | D20: =INDIRECT(ADDRESS(MATCH(A20,Calculations!B:B,0),15,1,1,"Calculations")) -> 104980.29 | E20: =INDIRECT(ADDRESS(MATCH(A20,Calculations!B:B,0),16,1,1,"Calculations")) -> 148226.77 | F20: =INDIRECT(ADDRESS(MATCH(A20,Calculations!B:B,0),17,1,1,"Calculations")) -> 1314766.8 | G20: =GETPIVOTDATA("TOTAL EXPENSE",'FY11 expense'!$A$6,"DEPARTMENT","Mathematics and Computer Science") -> 34069.77 | H20: =F20-B20 -> 54767.758
A21: Physics | B21: =GETPIVOTDATA("BEGINNING BUDGET",'fy12 budget'!$A$6,"DEPARTMENT","Physics") -> 810053 | C21: =INDIRECT(ADDRESS(MATCH(A21,Calculations!B:B,0),14,1,1,"Calculations")) -> 593961.47 | D21: =INDIRECT(ADDRESS(MATCH(A21,Calculations!B:B,0),15,1,1,"Calculations")) -> 96146.289 | E21: =INDIRECT(ADDRESS(MATCH(A21,Calculations!B:B,0),16,1,1,"Calculations")) -> 82935.505 | F21: =INDIRECT(ADDRESS(MATCH(A21,Calculations!B:B,0),17,1,1,"Calculations")) -> 773043.26 | G21: =GETPIVOTDATA("TOTAL EXPENSE",'FY11 expense'!$A$6,"DEPARTMENT","Physics") -> 699416.54 | H21: =F21-B21 -> -37009.741
A22: Accounting, Economics, & Finance | B22: =GETPIVOTDATA("BEGINNING BUDGET",'fy12 budget'!$A$6,"DEPARTMENT","Accounting, Economics, and Finance") -> 1066854 | C22: =INDIRECT(ADDRESS(MATCH(A22,Calculations!B:B,0),14,1,1,"Calculations")) -> 748618.19 | D22: =INDIRECT(ADDRESS(MATCH(A22,Calculations!B:B,0),15,1,1,"Calculations")) -> 96931.081 | E22: =INDIRECT(ADDRESS(MATCH(A22,Calculations!B:B,0),16,1,1,"Calculations")) -> 88735.827 | F22: =INDIRECT(ADDRESS(MATCH(A22,Calculations!B:B,0),17,1,1,"Calculations")) -> 934285.1 | G22: =GETPIVOTDATA("TOTAL EXPENSE",'FY11 expense'!$A$6,"DEPARTMENT","Accounting, Economics, and Finance") -> 1233545 | H22: =F22-B22 -> -132568.9
A23: Aerospace Studies | B23: =GETPIVOTDATA("BEGINNING BUDGET",'fy12 budget'!$A$6,"DEPARTMENT","Aerospace Studies") -> 44068 | C23: =INDIRECT(ADDRESS(MATCH(A23,Calculations!B:B,0),14,1,1,"Calculations")) -> 40090.405 | D23: =INDIRECT(ADDRESS(MATCH(A23,Calculations!B:B,0),15,1,1,"Calculations")) -> 85682.399 | E23: =INDIRECT(ADDRESS(MATCH(A23,Calculations!B:B,0),16,1,1,"Calculations")) -> 5597.8682 | F23: =INDIRECT(ADDRESS(MATCH(A23,Calculations!B:B,0),17,1,1,"Calculations")) -> 131370.67 | G23: =GETPIVOTDATA("TOTAL EXPENSE",'FY11 expense'!$A$6,"DEPARTMENT","Aerospace Studies") -> 50559.72 | H23: =F23-B23 -> 87302.673
A24: Management & Marketing | B24: =GETPIVOTDATA("BEGINNING BUDGET",'fy12 budget'!$A$6,"DEPARTMENT","Management and Marketing") -> 1102526 | C24: =INDIRECT(ADDRESS(MATCH(A24,Calculations!B:B,0),14,1,1,"Calculations")) -> 757858.67 | D24: =INDIRECT(ADDRESS(MATCH(A24,Calculations!B:B,0),15,1,1,"Calculations")) -> 95617.616 | E24: =INDIRECT(ADDRESS(MATCH(A24,Calculations!B:B,0),16,1,1,"Calculations")) -> 79028.132 | F24: =INDIRECT(ADDRESS(MATCH(A24,Calculations!B:B,0),17,1,1,"Calculations")) -> 932504.42 | G24: =GETPIVOTDATA("TOTAL EXPENSE",'FY11 expense'!$A$6,"DEPARTMENT","Management and Marketing") -> 1356228.3 | H24: =F24-B24 -> -170021.58
A25: Security Studies & Criminal Justice | B25: =GETPIVOTDATA("BEGINNING BUDGET",'fy12 budget'!$A$6,"DEPARTMENT","Security Studies Criminal Justice") -> 193510 | C25: =INDIRECT(ADDRESS(MATCH(A25,Calculations!B:B,0),14,1,1,"Calculations")) -> 0 | D25: =INDIRECT(ADDRESS(MATCH(A25,Calculations!B:B,0),15,1,1,"Calculations")) -> 84925 | E25: =INDIRECT(ADDRESS(MATCH(A25,Calculations!B:B,0),16,1,1,"Calculations")) -> 0 | F25: =INDIRECT(ADDRESS(MATCH(A25,Calculations!B:B,0),17,1,1,"Calculations")) -> 84925 | H25: =F25-B25 -> -108585
A26: Teacher Education | B26: =GETPIVOTDATA("BEGINNING BUDGET",'fy12 budget'!$A$6,"DEPARTMENT","Teacher Education") -> 763138 | C26: =INDIRECT(ADDRESS(MATCH(A26,Calculations!B:B,0),14,1,1,"Calculations")) -> 714215.95 | D26: =INDIRECT(ADDRESS(MATCH(A26,Calculations!B:B,0),15,1,1,"Calculations")) -> 94913.632 | E26: =INDIRECT(ADDRESS(MATCH(A26,Calculations!B:B,0),16,1,1,"Calculations")) -> 73825.05 | F26: =INDIRECT(ADDRESS(MATCH(A26,Calculations!B:B,0),17,1,1,"Calculations")) -> 882954.63 | G26: =GETPIVOTDATA("TOTAL EXPENSE",'FY11 expense'!$A$6,"DEPARTMENT","Teacher Education") -> 869748.16 | H26: =F26-B26 -> 119816.63
A27: Curriculum & Instruction | B27: =GETPIVOTDATA("BEGINNING BUDGET",'fy12 budget'!$A$6,"DEPARTMENT","Curriculum and Instruction") -> 459814 | C27: =INDIRECT(ADDRESS(MATCH(A27,Calculations!B:B,0),14,1,1,"Calculations")) -> 1598591.7 | D27: =INDIRECT(ADDRESS(MATCH(A27,Calculations!B:B,0),15,1,1,"Calculations")) -> 87131.456 | E27: =INDIRECT(ADDRESS(MATCH(A27,Calculations!B:B,0),16,1,1,"Calculations")) -> 16307.714 | F27: =INDIRECT(ADDRESS(MATCH(A27,Calculations!B:B,0),17,1,1,"Calculations")) -> 1702030.8 | G27: =GETPIVOTDATA("TOTAL EXPENSE",'FY11 expense'!$A$6,"DEPARTMENT","Curriculum and Instruction") -> 927480.14 | H27: =F27-B27 -> 1242216.8
A28: Kinesiology | B28: =GETPIVOTDATA("BEGINNING BUDGET",'fy12 budget'!$A$6,"DEPARTMENT","Kinesiology") -> 538599 | C28: =INDIRECT(ADDRESS(MATCH(A28,Calculations!B:B,0),14,1,1,"Calculations")) -> 580605.43 | D28: =INDIRECT(ADDRESS(MATCH(A28,Calculations!B:B,0),15,1,1,"Calculations")) -> 92931.793 | E28: =INDIRECT(ADDRESS(MATCH(A28,Calculations!B:B,0),16,1,1,"Calculations")) -> 59177.464 | F28: =INDIRECT(ADDRESS(MATCH(A28,Calculations!B:B,0),17,1,1,"Calculations")) -> 732714.69 | G28: =GETPIVOTDATA("TOTAL EXPENSE",'FY11 expense'!$A$6,"DEPARTMENT","Kinesiology") -> 835180.02 | H28: =F28-B28 -> 194115.69
A29: Nursing | B29: =GETPIVOTDATA("BEGINNING BUDGET",'fy12 budget'!$A$6,"DEPARTMENT","Nursing and Rehabilitation Sciences") -> 1951761 | C29: =INDIRECT(ADDRESS(MATCH(A29,Calculations!B:B,0),14,1,1,"Calculations")) -> 1636512.8 | D29: =INDIRECT(ADDRESS(MATCH(A29,Calculations!B:B,0),15,1,1,"Calculations")) -> 101249.49 | E29: =INDIRECT(ADDRESS(MATCH(A29,Calculations!B:B,0),16,1,1,"Calculations")) -> 120652.79 | F29: =INDIRECT(ADDRESS(MATCH(A29,Calculations!B:B,0),17,1,1,"Calculations")) -> 1858415 | G29: =GETPIVOTDATA("TOTAL EXPENSE",'FY11 expense'!$A$6,"DEPARTMENT","Nursing and Rehabilitation Sciences") -> 2186809.8 | H29: =F29-B29 -> -93345.962
A30: Athletic Training | B30: 0 | C30: =INDIRECT(ADDRESS(MATCH(A30,Calculations!B:B,0),14,1,1,"Calculations")) -> 0 | D30: =INDIRECT(ADDRESS(MATCH(A30,Calculations!B:B,0),15,1,1,"Calculations")) -> 84925 | E30: =INDIRECT(ADDRESS(MATCH(A30,Calculations!B:B,0),16,1,1,"Calculations")) -> 0 | F30: =INDIRECT(ADDRESS(MATCH(A30,Calculations!B:B,0),17,1,1,"Calculations")) -> 84925 | G30: 0 | H30: =F30-B30 -> 84925
A31: Physical Therapy | B31: =GETPIVOTDATA("BEGINNING BUDGET",'fy12 budget'!$A$6,"DEPARTMENT","Physical Therapy") -> 980425 | C31: =INDIRECT(ADDRESS(MATCH(A31,Calculations!B:B,0),14,1,1,"Calculations")) -> 143787.87 | D31: =INDIRECT(ADDRESS(MATCH(A31,Calculations!B:B,0),15,1,1,"Calculations")) -> 84925 | E31: =INDIRECT(ADDRESS(MATCH(A31,Calculations!B:B,0),16,1,1,"Calculations")) -> 39170.885 | F31: =INDIRECT(ADDRESS(MATCH(A31,Calculations!B:B,0),17,1,1,"Calculations")) -> 267883.76 | G31: =GETPIVOTDATA("TOTAL EXPENSE",'FY11 expense'!$A$6,"DEPARTMENT","Physical Therapy") -> 1025417.9 | H31: =F31-B31 -> -712541.24
A32: Psychology, Sociology & Social Work | B32: =GETPIVOTDATA("BEGINNING BUDGET",'fy12 budget'!$A$6,"DEPARTMENT","Psychology, Sociology, Social Work") -> 1064457 | C32: =INDIRECT(ADDRESS(MATCH(A32,Calculations!B:B,0),14,1,1,"Calculations")) -> 1355266.5 | D32: =INDIRECT(ADDRESS(MATCH(A32,Calculations!B:B,0),15,1,1,"Calculations")) -> 103269.68 | E32: =INDIRECT(ADDRESS(MATCH(A32,Calculations!B:B,0),16,1,1,"Calculations")) -> 135583.81 | F32: =INDIRECT(ADDRESS(MATCH(A32,Calculations!B:B,0),17,1,1,"Calculations")) -> 1594120 | G32: =GETPIVOTDATA("TOTAL EXPENSE",'FY11 expense'!$A$6,"DEPARTMENT","Psychology, Sociology, Social Work") -> 1228952.8 | H32: =F32-B32 -> 529662.98
A33: Academic Affairs | B33: 1653792 | C33: =INDIRECT(ADDRESS(MATCH(A33,Calculations!B:B,0),14,1,1,"Calculations")) -> 120198.72 | D33: =INDIRECT(ADDRESS(MATCH(A33,Calculations!B:B,0),15,1,1,"Calculations")) -> 87195.828 | E33: =INDIRECT(ADDRESS(MATCH(A33,Calculations!B:B,0),16,1,1,"Calculations")) -> 16783.482 | F33: =INDIRECT(ADDRESS(MATCH(A33,Calculations!B:B,0),17,1,1,"Calculations")) -> 224178.03 | H33: =F33-B33 -> -1429614 | I33: =SUM(H12:H33) -> 1610.1968
A34: Facilities | B34: =GETPIVOTDATA("BEGINNING BUDGET",'fy12 budget (2)'!$A$4,"Division","F") -> 5531857 | C34: =INDIRECT(ADDRESS(MATCH(A34,Calculations!B:B,0),10,1,1,"Calculations")) -> 0 | D34: =INDIRECT(ADDRESS(MATCH(A34,Calculations!B:B,0),15,1,1,"Calculations")) -> 0 | E34: =INDIRECT(ADDRESS(MATCH(A34,Calculations!B:B,0),16,1,1,"Calculations")) -> 0 | F34: =B62*B61 -> 2832527.2 | G34: =GETPIVOTDATA("TOTAL EXPENSE",'FY11 expense (2)'!$A$4,"Division","F") -> 5883187.3 | H34: =F34-B34 -> -2699329.8
A36: Totals | B36: =SUM(B6:B35) -> 46687161 | C36: =SUM(C6:C35) -> 26474926 | D36: =SUM(D6:D35) -> 2173620.6 | E36: =SUM(E6:E35) -> 4665044.4 | F36: =SUM(F6:F35) -> 36051118 | G36: =SUM(G6:G35) -> 48839881
E38: University Expenses | F38: ='University Cost'!D73 -> 10398251
E39: Budget Requirements | F39: =+F36+F38 -> 46449369
E40: Revenue | F40: =Revenue!J62 -> 47056603
E41: Strategic Iniatives | F41: =+F40-F39 -> 607234.18
A43: Variables
A44: Faculty (full time) | B44: 0.85
A45: Faculty (adjunct) | B45: 0.15
A46: Academic Operating | B46: 6750
A47: Required Class Size (UG) | B47: 33
A48: Required Class Size (Grad) | B48: 13
A49: Required UG Faculty Teaching Load | B49: 24
A50: Required Grad Faculty Teaching Load | B50: 18
A51: Required UG Lab (HC) | B51: 20
A52: Required Grad Lab (HC) | B52: 11
A53: FTE/Support Factor | B53: 700
A54: Support Operating | B54: 15300
A55: Headcount Factor | B55: 300
... A64: Student Credit Hour Operating | B64: 800

Sheet Calculations
C5: 2012 | D5: 2012 | G5: Required | H5: Required | I5: Required | J5: Required | K5: Total | L5: 2011/12 UG | M5: 2011/12 Grad | N5: 2011/12 Projected | O5: HeadCount Driven | P5: 2011/12
B6: BUDGET DIVISION | C6: UG SCH | D6: G SCH | E6: UG Lab (HC) | F6: G Lab (HC) | G6: UG Fac. FTE | H6: G Fac. FTE | I6: UG Lab Fac | J6: G Lab Fac | K6: Faculty | L6: Faculty Salaries | M6: Faculty Salaries | N6: SALARIES | O6: ADMIN & SUPPORT | P6: OPERATING | Q6: TOTAL ALLOCATION | R6: HOLD HARMLESS | S6: DIFFERENCE
B8: President | N8: =GETPIVOTDATA("Distribution Budget",'position by div'!$A$3,"Div","1") -> 1015869 | P8: =IF(ISERROR(IF(K8>0,(K8*Summary!$B$46)+((Calculations!C8+D8)/500*Summary!$B$64),Calculations!N8/Summary!$B$59*Summary!$B$54)),"",IF(G8>0,(G8*Summary!$B$46)+(Calculations!C8/500*Summary!$B$64),Calculations!N8/Summary!$B$59*Summary!$B$54)) -> 276744.4 | Q8: =SUM(N8:P8) -> 1292613.4
B9: Provost | N9: =GETPIVOTDATA("Distribution Budget",'position by div'!$A$3,"Div","2") -> 3900785 | P9: =IF(ISERROR(IF(K9>0,(K9*Summary!$B$46)+((Calculations!C9+D9)/500*Summary!$B$64),Calculations!N9/Summary!$B$59*Summary!$B$54)),"",IF(G9>0,(G9*Summary!$B$46)+(Calculations!C9/500*Summary!$B$64),Calculations!N9/Summary!$B$59*Summary!$B$54)) -> 1062657.1 | Q9: =SUM(N9:P9) -> 4963442.1
B10: Finance & Aministration | N10: =GETPIVOTDATA("Distribution Budget",'position by div'!$A$3,"Div","3") -> 3762774 | P10: =IF(ISERROR(IF(K10>0,(K10*Summary!$B$46)+((Calculations!C10+D10)/500*Summary!$B$64),Calculations!N10/Summary!$B$59*Summary!$B$54)),"",IF(G10>0,(G10*Summary!$B$46)+(Calculations!C10/500*Summary!$B$64),Calculations!N10/Summary!$B$59*Summary!$B$54)) -> 1025060 | Q10: =SUM(N10:P10) -> 4787834
B11: Strategy, Planning & Policy | P11: =IF(ISERROR(IF(K11>0,(K11*Summary!$B$46)+((Calculations!C11+D11)/500*Summary!$B$64),Calculations!N11/Summary!$B$59*Summary!$B$54)),"",IF(G11>0,(G11*Summary!$B$46)+(Calculations!C11/500*Summary!$B$64),Calculations!N11/Summary!$B$59*Summary!$B$54)) -> 0 | Q11: =SUM(N11:P11) -> 0
B12: Student Services & Enrollment Management | N12: =GETPIVOTDATA("Distribution Budget",'position by div'!$A$3,"Div","5") -> 1895281 | O12: =IF(ISERROR(Summary!$B$59+Summary!$B$60+((Calculations!C12/30)/Summary!$B$53*Summary!$B$60)),"",Summary!$B$59+Summary!$B$60+((Calculations!C12/30)/Summary!$B$53*Summary!$B$60)) -> 84925 | P12: =IF(ISERROR(IF(K12>0,(K12*Summary!$B$46)+((Calculations!C12+D12)/500*Summary!$B$64),Calculations!N12/Summary!$B$59*Summary!$B$54)),"",IF(G12>0,(G12*Summary!$B$46)+(Calculations!C12/500*Summary!$B$64),Calculations!N12/Summary!$B$59*Summary!$B$54)) -> 516315 | Q12: =SUM(N12:P12) -> 2496521
B13: Development | N13: =GETPIVOTDATA("Distribution Budget",'position by div'!$A$3,"Div","6") -> 427804 | P13: =IF(ISERROR(IF(K13>0,(K13*Summary!$B$46)+((Calculations!C13+D13)/500*Summary!$B$64),Calculations!N13/Summary!$B$59*Summary!$B$54)),"",IF(G13>0,(G13*Summary!$B$46)+(Calculations!C13/500*Summary!$B$64),Calculations!N13/Summary!$B$59*Summary!$B$54)) -> 116542.94 | Q13: =SUM(N13:P13) -> 544346.94
B14: Agriculture | C14: =IF(ISERROR(INDIRECT(ADDRESS(MATCH(B14,Data!B:B,0),5,1,1,"Data"))*INDIRECT(ADDRESS(MATCH(B14,'Cost Factor'!B:B,0),21,1,1,"Cost Factor"))),"",INDIRECT(ADDRESS(MATCH(B14,Data!B:B,0),5,1,1,"Data"))*INDIRECT(ADDRESS(MATCH(B14,'Cost Factor'!B:B,0),21,1,1,"Cost Factor"))) -> 5840 | D14: =IF(ISERROR(INDIRECT(ADDRESS(MATCH(B14,Data!B:B,0),6,1,1,"Data"))*INDIRECT(ADDRESS(MATCH(B14,'Cost Factor'!B:B,0),21,1,1,"Cost Factor"))),"",INDIRECT(ADDRESS(MATCH(B14,Data!B:B,0),6,1,1,"Data"))*INDIRECT(ADDRESS(MATCH(B14,'Cost Factor'!B:B,0),21,1,1,"Cost Factor"))) -> 397 | E14: =IF(ISERROR(INDIRECT(ADDRESS(MATCH(B14,Data!B:B,0),8,1,1,"Data"))*INDIRECT(ADDRESS(MATCH(B14,'Cost Factor'!B:B,0),21,1,1,"Cost Factor"))),"",INDIRECT(ADDRESS(MATCH(B14,Data!B:B,0),8,1,1,"Data"))*INDIRECT(ADDRESS(MATCH(B14,'Cost Factor'!B:B,0),21,1,1,"Cost Factor"))) -> 0 | F14: =IF(ISERROR(INDIRECT(ADDRESS(MATCH(B14,Data!B:B,0),9,1,1,"Data"))*INDIRECT(ADDRESS(MATCH(B14,'Cost Factor'!B:B,0),21,1,1,"Cost Factor"))),"",INDIRECT(ADDRESS(MATCH(B14,Data!B:B,0),9,1,1,"Data"))*INDIRECT(ADDRESS(MATCH(B14,'Cost Factor'!B:B,0),21,1,1,"Cost Factor"))) -> 0 | G14: =IF(ISERROR(C14/(Summary!$B$47*Summary!$B$49)),"",C14/(Summary!$B$47*Summary!$B$49)) -> 7.3737374 | H14: =IF(ISERROR(D14/(Summary!$B$48*Summary!$B$50)),"",D14/(Summary!$B$48*Summary!$B$50)) -> 1.6965812 | I14: =E14/(Summary!$B$51*Summary!$B$49*0.67) -> 0 | J14: =F14/(Summary!$B$50*Summary!$B$52*0.67) -> 0 | K14: =H14+G14+I14+J14 -> 9.0703186 | L14: =IF(ISERROR(((G14+I14)*Summary!$B$44*Summary!$B$57)+((Calculations!G14+I14)*Summary!$B$45*Summary!$B$58)),"",((G14+I14)*Summary!$B$44*Summary!$B$57)+((Calculations!G14+I14)*Summary!$B$45*Summary!$B$58)) -> 423377.88 | M14: =IF(ISERROR(((H14+J14)*Summary!$B$44*Summary!$B$57)+((H14+J14)*Summary!$B$45*Summary!$B$58)),"",((H14+J14)*Summary!$B$44*Summary!$B$57)+((H14+J14)*Summary!$B$45*Summary!$B$58)) -> 97412.603 | N14: =L14+M14 -> 520790.48 | O14: =IF(ISERROR(Summary!$B$59+Summary!$B$60+((Calculations!C14/30)/Summary!$B$53*Summary!$B$60)),"",Summary!$B$59+Summary!$B$60+((Calculations!C14/30)/Summary!$B$53*Summary!$B$60)) -> 92923.575 | P14: =IF(ISERROR(IF(K14>0,(K14*Summary!$B$46)+((Calculations!C14+D14)/500*Summary!$B$64),Calculations!N14/Summary!$B$59*Summary!$B$54)),"",IF(G14>0,(G14*Summary!$B$46)+(Calculations!C14/500*Summary!$B$64),Calculations!N14/Summary!$B$59*Summary!$B$54)) -> 59116.727 | Q14: =SUM(N14:P14) -> 672830.78
B15: Art & Music | C15: =IF(ISERROR(INDIRECT(ADDRESS(MATCH(B15,Data!B:B,0),5,1,1,"Data"))*INDIRECT(ADDRESS(MATCH(B15,'Cost Factor'!B:B,0),21,1,1,"Cost Factor"))),"",INDIRECT(ADDRESS(MATCH(B15,Data!B:B,0),5,1,1,"Data"))*INDIRECT(ADDRESS(MATCH(B15,'Cost Factor'!B:B,0),21,1,1,"Cost Factor"))) -> 8883 | D15: =IF(ISERROR(INDIRECT(ADDRESS(MATCH(B15,Data!B:B,0),6,1,1,"Data"))*INDIRECT(ADDRESS(MATCH(B15,'Cost Factor'!B:B,0),21,1,1,"Cost Factor"))),"",INDIRECT(ADDRESS(MATCH(B15,Data!B:B,0),6,1,1,"Data"))*INDIRECT(ADDRESS(MATCH(B15,'Cost Factor'!B:B,0),21,1,1,"Cost Factor"))) -> 0 | E15: =IF(ISERROR(INDIRECT(ADDRESS(MATCH(B15,Data!B:B,0),8,1,1,"Data"))*INDIRECT(ADDRESS(MATCH(B15,'Cost Factor'!B:B,0),21,1,1,"Cost Factor"))),"",INDIRECT(ADDRESS(MATCH(B15,Data!B:B,0),8,1,1,"Data"))*INDIRECT(ADDRESS(MATCH(B15,'Cost Factor'!B:B,0),21,1,1,"Cost Factor"))) -> 0 | F15: =IF(ISERROR(INDIRECT(ADDRESS(MATCH(B15,Data!B:B,0),9,1,1,"Data"))*INDIRECT(ADDRESS(MATCH(B15,'Cost Factor'!B:B,0),21,1,1,"Cost Factor"))),"",INDIRECT(ADDRESS(MATCH(B15,Data!B:B,0),9,1,1,"Data"))*INDIRECT(ADDRESS(MATCH(B15,'Cost Factor'!B:B,0),21,1,1,"Cost Factor"))) -> 0 | G15: =IF(ISERROR(C15/(Summary!$B$47*Summary!$B$49)),"",C15/(Summary!$B$47*Summary!$B$49)) -> 11.215909 | H15: =IF(ISERROR(D15/(Summary!$B$48*Summary!$B$50)),"",D15/(Summary!$B$48*Summary!$B$50)) -> 0 | I15: =E15/(Summary!$B$51*Summary!$B$49*0.67) -> 0 | J15: =F15/(Summary!$B$50*Summary!$B$52*0.67) -> 0 | K15: =H15+G15+I15+J15 -> 11.215909 | L15: =IF(ISERROR(((G15+I15)*Summary!$B$44*Summary!$B$57)+((Calculations!G15+I15)*Summary!$B$45*Summary!$B$58)),"",((G15+I15)*Summary!$B$44*Summary!$B$57)+((Calculations!G15+I15)*Summary!$B$45*Summary!$B$58)) -> 643983.85 | M15: =IF(ISERROR(((H15+J15)*Summary!$B$44*Summary!$B$57)+((H15+J15)*Summary!$B$45*Summary!$B$58)),"",((H15+J15)*Summary!$B$44*Summary!$B$57)+((H15+J15)*Summary!$B$45*Summary!$B$58)) -> 0 | N15: =L15+M15 -> 643983.85 | O15: =IF(ISERROR(Summary!$B$59+Summary!$B$60+((Calculations!C15/30)/Summary!$B$53*Summary!$B$60)),"",Summary!$B$59+Summary!$B$60+((Calculations!C15/30)/Summary!$B$53*Summary!$B$60)) -> 97091.326 | P15: =IF(ISERROR(IF(K15>0,(K15*Summary!$B$46)+((Calculations!C15+D15)/500*Summary!$B$64),Calculations!N15/Summary!$B$59*Summary!$B$54)),"",IF(G15>0,(G15*Summary!$B$46)+(Calculations!C15/500*Summary!$B$64),Calculations!N15/Summary!$B$59*Summary!$B$54)) -> 89920.186 | Q15: =SUM(N15:P15) -> 830995.36
B16: Biology | C16: =IF(ISERROR(INDIRECT(ADDRESS(MATCH(B16,Data!B:B,0),5,1,1,"Data"))*INDIRECT(ADDRESS(MATCH(B16,'Cost Factor'!B:B,0),21,1,1,"Cost Factor"))),"",INDIRECT(ADDRESS(MATCH(B16,Data!B:B,0),5,1,1,"Data"))*INDIRECT(ADDRESS(MATCH(B16,'Cost Factor'!B:B,0),21,1,1,"Cost Factor"))) -> 11864 | D16: =IF(ISERROR(INDIRECT(ADDRESS(MATCH(B16,Data!B:B,0),6,1,1,"Data"))*INDIRECT(ADDRESS(MATCH(B16,'Cost Factor'!B:B,0),21,1,1,"Cost Factor"))),"",INDIRECT(ADDRESS(MATCH(B16,Data!B:B,0),6,1,1,"Data"))*INDIRECT(ADDRESS(MATCH(B16,'Cost Factor'!B:B,0),21,1,1,"Cost Factor"))) -> 379 | E16: =IF(ISERROR(INDIRECT(ADDRESS(MATCH(B16,Data!B:B,0),8,1,1,"Data"))*INDIRECT(ADDRESS(MATCH(B16,'Cost Factor'!B:B,0),21,1,1,"Cost Factor"))),"",INDIRECT(ADDRESS(MATCH(B16,Data!B:B,0),8,1,1,"Data"))*INDIRECT(ADDRESS(MATCH(B16,'Cost Factor'!B:B,0),21,1,1,"Cost Factor"))) -> 0 | F16: =IF(ISERROR(INDIRECT(ADDRESS(MATCH(B16,Data!B:B,0),9,1,1,"Data"))*INDIRECT(ADDRESS(MATCH(B16,'Cost Factor'!B:B,0),21,1,1,"Cost Factor"))),"",INDIRECT(ADDRESS(MATCH(B16,Data!B:B,0),9,1,1,"Data"))*INDIRECT(ADDRESS(MATCH(B16,'Cost Factor'!B:B,0),21,1,1,"Cost Factor"))) -> 0 | G16: =IF(ISERROR(C16/(Summary!$B$47*Summary!$B$49)),"",C16/(Summary!$B$47*Summary!$B$49)) -> 14.979798 | H16: =IF(ISERROR(D16/(Summary!$B$48*Summary!$B$50)),"",D16/(Summary!$B$48*Summary!$B$50)) -> 1.6196581 | I16: =E16/(Summary!$B$51*Summary!$B$49*0.67) -> 0 | J16: =F16/(Summary!$B$50*Summary!$B$52*0.67) -> 0 | K16: =H16+G16+I16+J16 -> 16.599456 | L16: =IF(ISERROR(((G16+I16)*Summary!$B$44*Summary!$B$57)+((Calculations!G16+I16)*Summary!$B$45*Summary!$B$58)),"",((G16+I16)*Summary!$B$44*Summary!$B$57)+((Calculations!G16+I16)*Summary!$B$45*Summary!$B$58)) -> 860095.06 | M16: =IF(ISERROR(((H16+J16)*Summary!$B$44*Summary!$B$57)+((H16+J16)*Summary!$B$45*Summary!$B$58)),"",((H16+J16)*Summary!$B$44*Summary!$B$57)+((H16+J16)*Summary!$B$45*Summary!$B$58)) -> 92995.91 | N16: =L16+M16 -> 953090.97 | O16: =IF(ISERROR(Summary!$B$59+Summary!$B$60+((Calculations!C16/30)/Summary!$B$53*Summary!$B$60)),"",Summary!$B$59+Summary!$B$60+((Calculations!C16/30)/Summary!$B$53*Summary!$B$60)) -> 101174.16 | P16: =IF(ISERROR(IF(K16>0,(K16*Summary!$B$46)+((Calculations!C16+D16)/500*Summary!$B$64),Calculations!N16/Summary!$B$59*Summary!$B$54)),"",IF(G16>0,(G16*Summary!$B$46)+(Calculations!C16/500*Summary!$B$64),Calculations!N16/Summary!$B$59*Summary!$B$54)) -> 120096.04 | Q16: =SUM(N16:P16) -> 1174361.2
B17: Chemistry & Biochemistry | C17: =IF(ISERROR(INDIRECT(ADDRESS(MATCH(B17,Data!B:B,0),5,1,1,"Data"))*INDIRECT(ADDRESS(MATCH(B17,'Cost Factor'!B:B,0),21,1,1,"Cost Factor"))),"",INDIRECT(ADDRESS(MATCH(B17,Data!B:B,0),5,1,1,"Data"))*INDIRECT(ADDRESS(MATCH(B17,'Cost Factor'!B:B,0),21,1,1,"Cost Factor"))) -> 5773 | D17: =IF(ISERROR(INDIRECT(ADDRESS(MATCH(B17,Data!B:B,0),6,1,1,"Data"))*INDIRECT(ADDRESS(MATCH(B17,'Cost Factor'!B:B,0),21,1,1,"Cost Factor"))),"",INDIRECT(ADDRESS(MATCH(B17,Data!B:B,0),6,1,1,"Data"))*INDIRECT(ADDRESS(MATCH(B17,'Cost Factor'!B:B,0),21,1,1,"Cost Factor"))) -> 6 | E17: =IF(ISERROR(INDIRECT(ADDRESS(MATCH(B17,Data!B:B,0),8,1,1,"Data"))*INDIRECT(ADDRESS(MATCH(B17,'Cost Factor'!B:B,0),21,1,1,"Cost Factor"))),"",INDIRECT(ADDRESS(MATCH(B17,Data!B:B,0),8,1,1,"Data"))*INDIRECT(ADDRESS(MATCH(B17,'Cost Factor'!B:B,0),21,1,1,"Cost Factor"))) -> 0 | F17: =IF(ISERROR(INDIRECT(ADDRESS(MATCH(B17,Data!B:B,0),9,1,1,"Data"))*INDIRECT(ADDRESS(MATCH(B17,'Cost Factor'!B:B,0),21,1,1,"Cost Factor"))),"",INDIRECT(ADDRESS(MATCH(B17,Data!B:B,0),9,1,1,"Data"))*INDIRECT(ADDRESS(MATCH(B17,'Cost Factor'!B:B,0),21,1,1,"Cost Factor"))) -> 0 | G17: =IF(ISERROR(C17/(Summary!$B$47*Summary!$B$49)),"",C17/(Summary!$B$47*Summary!$B$49)) -> 7.2891414 | H17: =IF(ISERROR(D17/(Summary!$B$48*Summary!$B$50)),"",D17/(Summary!$B$48*Summary!$B$50)) -> 0.025641026 | I17: =E17/(Summary!$B$51*Summary!$B$49*0.67) -> 0 | J17: =F17/(Summary!$B$50*Summary!$B$52*0.67) -> 0 | K17: =H17+G17+I17+J17 -> 7.3147824 | L17: =IF(ISERROR(((G17+I17)*Summary!$B$44*Summary!$B$57)+((Calculations!G17+I17)*Summary!$B$45*Summary!$B$58)),"",((G17+I17)*Summary!$B$44*Summary!$B$57)+((Calculations!G17+I17)*Summary!$B$45*Summary!$B$58)) -> 418520.63 | M17: =IF(ISERROR(((H17+J17)*Summary!$B$44*Summary!$B$57)+((H17+J17)*Summary!$B$45*Summary!$B$58)),"",((H17+J17)*Summary!$B$44*Summary!$B$57)+((H17+J17)*Summary!$B$45*Summary!$B$58)) -> 1472.2308 | N17: =L17+M17 -> 419992.86 | O17: =IF(ISERROR(Summary!$B$59+Summary!$B$60+((Calculations!C17/30)/Summary!$B$53*Summary!$B$60)),"",Summary!$B$59+Summary!$B$60+((Calculations!C17/30)/Summary!$B$53*Summary!$B$60)) -> 92831.811 | P17: =IF(ISERROR(IF(K17>0,(K17*Summary!$B$46)+((Calculations!C17+D17)/500*Summary!$B$64),Calculations!N17/Summary!$B$59*Summary!$B$54)),"",IF(G17>0,(G17*Summary!$B$46)+(Calculations!C17/500*Summary!$B$64),Calculations!N17/Summary!$B$59*Summary!$B$54)) -> 58438.505 | Q17: =SUM(N17:P17) -> 571263.18
B18: Communication, Mass Media, & Theatre | C18: =IF(ISERROR(INDIRECT(ADDRESS(MATCH(B18,Data!B:B,0),5,1,1,"Data"))*INDIRECT(ADDRESS(MATCH(B18,'Cost Factor'!B:B,0),21,1,1,"Cost Factor"))),"",INDIRECT(ADDRESS(MATCH(B18,Data!B:B,0),5,1,1,"Data"))*INDIRECT(ADDRESS(MATCH(B18,'Cost Factor'!B:B,0),21,1,1,"Cost Factor"))) -> 10961 | D18: =IF(ISERROR(INDIRECT(ADDRESS(MATCH(B18,Data!B:B,0),6,1,1,"Data"))*INDIRECT(ADDRESS(MATCH(B18,'Cost Factor'!B:B,0),21,1,1,"Cost Factor"))),"",INDIRECT(ADDRESS(MATCH(B18,Data!B:B,0),6,1,1,"Data"))*INDIRECT(ADDRESS(MATCH(B18,'Cost Factor'!B:B,0),21,1,1,"Cost Factor"))) -> 399 | E18: =IF(ISERROR(INDIRECT(ADDRESS(MATCH(B18,Data!B:B,0),8,1,1,"Data"))*INDIRECT(ADDRESS(MATCH(B18,'Cost Factor'!B:B,0),21,1,1,"Cost Factor"))),"",INDIRECT(ADDRESS(MATCH(B18,Data!B:B,0),8,1,1,"Data"))*INDIRECT(ADDRESS(MATCH(B18,'Cost Factor'!B:B,0),21,1,1,"Cost Factor"))) -> 0 | F18: =IF(ISERROR(INDIRECT(ADDRESS(MATCH(B18,Data!B:B,0),9,1,1,"Data"))*INDIRECT(ADDRESS(MATCH(B18,'Cost Factor'!B:B,0),21,1,1,"Cost Factor"))),"",INDIRECT(ADDRESS(MATCH(B18,Data!B:B,0),9,1,1,"Data"))*INDIRECT(ADDRESS(MATCH(B18,'Cost Factor'!B:B,0),21,1,1,"Cost Factor"))) -> 0 | G18: =IF(ISERROR(C18/(Summary!$B$47*Summary!$B$49)),"",C18/(Summary!$B$47*Summary!$B$49)) -> 13.839646 | H18: =IF(ISERROR(D18/(Summary!$B$48*Summary!$B$50)),"",D18/(Summary!$B$48*Summary!$B$50)) -> 1.7051282 | I18: =E18/(Summary!$B$51*Summary!$B$49*0.67) -> 0 | J18: =F18/(Summary!$B$50*Summary!$B$52*0.67) -> 0 | K18: =H18+G18+I18+J18 -> 15.544775 | L18: =IF(ISERROR(((G18+I18)*Summary!$B$44*Summary!$B$57)+((Calculations!G18+I18)*Summary!$B$45*Summary!$B$58)),"",((G18+I18)*Summary!$B$44*Summary!$B$57)+((Calculations!G18+I18)*Summary!$B$45*Summary!$B$58)) -> 794630.98 | M18: =IF(ISERROR(((H18+J18)*Summary!$B$44*Summary!$B$57)+((H18+J18)*Summary!$B$45*Summary!$B$58)),"",((H18+J18)*Summary!$B$44*Summary!$B$57)+((H18+J18)*Summary!$B$45*Summary!$B$58)) -> 97903.346 | N18: =L18+M18 -> 892534.33 | O18: =IF(ISERROR(Summary!$B$59+Summary!$B$60+((Calculations!C18/30)/Summary!$B$53*Summary!$B$60)),"",Summary!$B$59+Summary!$B$60+((Calculations!C18/30)/Summary!$B$53*Summary!$B$60)) -> 99937.394 | P18: =IF(ISERROR(IF(K18>0,(K18*Summary!$B$46)+((Calculations!C18+D18)/500*Summary!$B$64),Calculations!N18/Summary!$B$59*Summary!$B$54)),"",IF(G18>0,(G18*Summary!$B$46)+(Calculations!C18/500*Summary!$B$64),Calculations!N18/Summary!$B$59*Summary!$B$54)) -> 110955.21 | Q18: =SUM(N18:P18) -> 1103426.9
B19: English & Modern Langagues | C19: =IF(ISERROR(INDIRECT(ADDRESS(MATCH(B19,Data!B:B,0),5,1,1,"Data"))*INDIRECT(ADDRESS(MATCH(B19,'Cost Factor'!B:B,0),21,1,1,"Cost Factor"))),"",INDIRECT(ADDRESS(MATCH(B19,Data!B:B,0),5,1,1,"Data"))*INDIRECT(ADDRESS(MATCH(B19,'Cost Factor'!B:B,0),21,1,1,"Cost Factor"))) -> 18051 | D19: =IF(ISERROR(INDIRECT(ADDRESS(MATCH(B19,Data!B:B,0),6,1,1,"Data"))*INDIRECT(ADDRESS(MATCH(B19,'Cost Factor'!B:B,0),21,1,1,"Cost Factor"))),"",INDIRECT(ADDRESS(MATCH(B19,Data!B:B,0),6,1,1,"Data"))*INDIRECT(ADDRESS(MATCH(B19,'Cost Factor'!B:B,0),21,1,1,"Cost Factor"))) -> 252 | E19: =IF(ISERROR(INDIRECT(ADDRESS(MATCH(B19,Data!B:B,0),8,1,1,"Data"))*INDIRECT(ADDRESS(MATCH(B19,'Cost Factor'!B:B,0),21,1,1,"Cost Factor"))),"",INDIRECT(ADDRESS(MATCH(B19,Data!B:B,0),8,1,1,"Data"))*INDIRECT(ADDRESS(MATCH(B19,'Cost Factor'!B:B,0),21,1,1,"Cost Factor"))) -> 0 | F19: =IF(ISERROR(INDIRECT(ADDRESS(MATCH(B19,Data!B:B,0),9,1,1,"Data"))*INDIRECT(ADDRESS(MATCH(B19,'Cost Factor'!B:B,0),21,1,1,"Cost Factor"))),"",INDIRECT(ADDRESS(MATCH(B19,Data!B:B,0),9,1,1,"Data"))*INDIRECT(ADDRESS(MATCH(B19,'Cost Factor'!B:B,0),21,1,1,"Cost Factor"))) -> 0 | G19: =IF(ISERROR(C19/(Summary!$B$47*Summary!$B$49)),"",C19/(Summary!$B$47*Summary!$B$49)) -> 22.791667 | H19: =IF(ISERROR(D19/(Summary!$B$48*Summary!$B$50)),"",D19/(Summary!$B$48*Summary!$B$50)) -> 1.0769231 | I19: =E19/(Summary!$B$51*Summary!$B$49*0.67) -> 0 | J19: =F19/(Summary!$B$50*Summary!$B$52*0.67) -> 0 | K19: =H19+G19+I19+J19 -> 23.86859 | L19: =IF(ISERROR(((G19+I19)*Summary!$B$44*Summary!$B$57)+((Calculations!G19+I19)*Summary!$B$45*Summary!$B$58)),"",((G19+I19)*Summary!$B$44*Summary!$B$57)+((Calculations!G19+I19)*Summary!$B$45*Summary!$B$58)) -> 1308629.1 | M19: =IF(ISERROR(((H19+J19)*Summary!$B$44*Summary!$B$57)+((H19+J19)*Summary!$B$45*Summary!$B$58)),"",((H19+J19)*Summary!$B$44*Summary!$B$57)+((H19+J19)*Summary!$B$45*Summary!$B$58)) -> 61833.692 | N19: =L19+M19 -> 1370462.8 | O19: =IF(ISERROR(Summary!$B$59+Summary!$B$60+((Calculations!C19/30)/Summary!$B$53*Summary!$B$60)),"",Summary!$B$59+Summary!$B$60+((Calculations!C19/30)/Summary!$B$53*Summary!$B$60)) -> 109647.99 | P19: =IF(ISERROR(IF(K19>0,(K19*Summary!$B$46)+((Calculations!C19+D19)/500*Summary!$B$64),Calculations!N19/Summary!$B$59*Summary!$B$54)),"",IF(G19>0,(G19*Summary!$B$46)+(Calculations!C19/500*Summary!$B$64),Calculations!N19/Summary!$B$59*Summary!$B$54)) -> 182725.35 | Q19: =SUM(N19:P19) -> 1662836.2
B20: Pol Science | C20: =IF(ISERROR(INDIRECT(ADDRESS(MATCH(B20,Data!B:B,0),5,1,1,"Data"))*INDIRECT(ADDRESS(MATCH(B20,'Cost Factor'!B:B,0),21,1,1,"Cost Factor"))),"",INDIRECT(ADDRESS(MATCH(B20,Data!B:B,0),5,1,1,"Data"))*INDIRECT(ADDRESS(MATCH(B20,'Cost Factor'!B:B,0),21,1,1,"Cost Factor"))) -> 4518 | D20: =IF(ISERROR(INDIRECT(ADDRESS(MATCH(B20,Data!B:B,0),6,1,1,"Data"))*INDIRECT(ADDRESS(MATCH(B20,'Cost Factor'!B:B,0),21,1,1,"Cost Factor"))),"",INDIRECT(ADDRESS(MATCH(B20,Data!B:B,0),6,1,1,"Data"))*INDIRECT(ADDRESS(MATCH(B20,'Cost Factor'!B:B,0),21,1,1,"Cost Factor"))) -> 9 | E20: =IF(ISERROR(INDIRECT(ADDRESS(MATCH(B20,Data!B:B,0),8,1,1,"Data"))*INDIRECT(ADDRESS(MATCH(B20,'Cost Factor'!B:B,0),21,1,1,"Cost Factor"))),"",INDIRECT(ADDRESS(MATCH(B20,Data!B:B,0),8,1,1,"Data"))*INDIRECT(ADDRESS(MATCH(B20,'Cost Factor'!B:B,0),21,1,1,"Cost Factor"))) -> 0 | F20: =IF(ISERROR(INDIRECT(ADDRESS(MATCH(B20,Data!B:B,0),9,1,1,"Data"))*INDIRECT(ADDRESS(MATCH(B20,'Cost Factor'!B:B,0),21,1,1,"Cost Factor"))),"",INDIRECT(ADDRESS(MATCH(B20,Data!B:B,0),9,1,1,"Data"))*INDIRECT(ADDRESS(MATCH(B20,'Cost Factor'!B:B,0),21,1,1,"Cost Factor"))) -> 0 | G20: =IF(ISERROR(C20/(Summary!$B$47*Summary!$B$49)),"",C20/(Summary!$B$47*Summary!$B$49)) -> 5.7045455 | H20: =IF(ISERROR(D20/(Summary!$B$48*Summary!$B$50)),"",D20/(Summary!$B$48*Summary!$B$50)) -> 0.038461538 | I20: =E20/(Summary!$B$51*Summary!$B$49*0.67) -> 0 | J20: =F20/(Summary!$B$50*Summary!$B$52*0.67) -> 0 | K20: =H20+G20+I20+J20 -> 5.743007 | L20: =IF(ISERROR(((G20+I20)*Summary!$B$44*Summary!$B$57)+((Calculations!G20+I20)*Summary!$B$45*Summary!$B$58)),"",((G20+I20)*Summary!$B$44*Summary!$B$57)+((Calculations!G20+I20)*Summary!$B$45*Summary!$B$58)) -> 327537.89 | M20: =IF(ISERROR(((H20+J20)*Summary!$B$44*Summary!$B$57)+((H20+J20)*Summary!$B$45*Summary!$B$58)),"",((H20+J20)*Summary!$B$44*Summary!$B$57)+((H20+J20)*Summary!$B$45*Summary!$B$58)) -> 2208.3462 | N20: =L20+M20 -> 329746.23 | O20: =IF(ISERROR(Summary!$B$59+Summary!$B$60+((Calculations!C20/30)/Summary!$B$53*Summary!$B$60)),"",Summary!$B$59+Summary!$B$60+((Calculations!C20/30)/Summary!$B$53*Summary!$B$60)) -> 91112.939 | P20: =IF(ISERROR(IF(K20>0,(K20*Summary!$B$46)+((Calculations!C20+D20)/500*Summary!$B$64),Calculations!N20/Summary!$B$59*Summary!$B$54)),"",IF(G20>0,(G20*Summary!$B$46)+(Calculations!C20/500*Summary!$B$64),Calculations!N20/Summary!$B$59*Summary!$B$54)) -> 45734.482 | Q20: =SUM(N20:P20) -> 466593.65
B21: History | C21: =IF(ISERROR(INDIRECT(ADDRESS(MATCH(B21,Data!B:B,0),5,1,1,"Data"))*INDIRECT(ADDRESS(MATCH(B21,'Cost Factor'!B:B,0),21,1,1,"Cost Factor"))),"",INDIRECT(ADDRESS(MATCH(B21,Data!B:B,0),5,1,1,"Data"))*INDIRECT(ADDRESS(MATCH(B21,'Cost Factor'!B:B,0),21,1,1,"Cost Factor"))) -> 13308 | D21: =IF(ISERROR(INDIRECT(ADDRESS(MATCH(B21,Data!B:B,0),6,1,1,"Data"))*INDIRECT(ADDRESS(MATCH(B21,'Cost Factor'!B:B,0),21,1,1,"Cost Factor"))),"",INDIRECT(ADDRESS(MATCH(B21,Data!B:B,0),6,1,1,"Data"))*INDIRECT(ADDRESS(MATCH(B21,'Cost Factor'!B:B,0),21,1,1,"Cost Factor"))) -> 105 | E21: =IF(ISERROR(INDIRECT(ADDRESS(MATCH(B21,Data!B:B,0),8,1,1,"Data"))*INDIRECT(ADDRESS(MATCH(B21,'Cost Factor'!B:B,0),21,1,1,"Cost Factor"))),"",INDIRECT(ADDRESS(MATCH(B21,Data!B:B,0),8,1,1,"Data"))*INDIRECT(ADDRESS(MATCH(B21,'Cost Factor'!B:B,0),21,1,1,"Cost Factor"))) -> 0 | F21: =IF(ISERROR(INDIRECT(ADDRESS(MATCH(B21,Data!B:B,0),9,1,1,"Data"))*INDIRECT(ADDRESS(MATCH(B21,'Cost Factor'!B:B,0),21,1,1,"Cost Factor"))),"",INDIRECT(ADDRESS(MATCH(B21,Data!B:B,0),9,1,1,"Data"))*INDIRECT(ADDRESS(MATCH(B21,'Cost Factor'!B:B,0),21,1,1,"Cost Factor"))) -> 0 | G21: =IF(ISERROR(C21/(Summary!$B$47*Summary!$B$49)),"",C21/(Summary!$B$47*Summary!$B$49)) -> 16.80303 | H21: =IF(ISERROR(D21/(Summary!$B$48*Summary!$B$50)),"",D21/(Summary!$B$48*Summary!$B$50)) -> 0.44871795 | I21: =E21/(Summary!$B$51*Summary!$B$49*0.67) -> 0 | J21: =F21/(Summary!$B$50*Summary!$B$52*0.67) -> 0 | K21: =H21+G21+I21+J21 -> 17.251748 | L21: =IF(ISERROR(((G21+I21)*Summary!$B$44*Summary!$B$57)+((Calculations!G21+I21)*Summary!$B$45*Summary!$B$58)),"",((G21+I21)*Summary!$B$44*Summary!$B$57)+((Calculations!G21+I21)*Summary!$B$45*Summary!$B$58)) -> 964779.59 | M21: =IF(ISERROR(((H21+J21)*Summary!$B$44*Summary!$B$57)+((H21+J21)*Summary!$B$45*Summary!$B$58)),"",((H21+J21)*Summary!$B$44*Summary!$B$57)+((H21+J21)*Summary!$B$45*Summary!$B$58)) -> 25764.038 | N21: =L21+M21 -> 990543.63 | O21: =IF(ISERROR(Summary!$B$59+Summary!$B$60+((Calculations!C21/30)/Summary!$B$53*Summary!$B$60)),"",Summary!$B$59+Summary!$B$60+((Calculations!C21/30)/Summary!$B$53*Summary!$B$60)) -> 103151.89 | P21: =IF(ISERROR(IF(K21>0,(K21*Summary!$B$46)+((Calculations!C21+D21)/500*Summary!$B$64),Calculations!N21/Summary!$B$59*Summary!$B$54)),"",IF(G21>0,(G21*Summary!$B$46)+(Calculations!C21/500*Summary!$B$64),Calculations!N21/Summary!$B$59*Summary!$B$54)) -> 134713.25 | Q21: =SUM(N21:P21) -> 1228408.8
B22: Mathematics & Computer Science | C22: =IF(ISERROR(INDIRECT(ADDRESS(MATCH(B22,Data!B:B,0),5,1,1,"Data"))*INDIRECT(ADDRESS(MATCH(B22,'Cost Factor'!B:B,0),21,1,1,"Cost Factor"))),"",INDIRECT(ADDRESS(MATCH(B22,Data!B:B,0),5,1,1,"Data"))*INDIRECT(ADDRESS(MATCH(B22,'Cost Factor'!B:B,0),21,1,1,"Cost Factor"))) -> 14642.968 | D22: =IF(ISERROR(INDIRECT(ADDRESS(MATCH(B22,Data!B:B,0),6,1,1,"Data"))*INDIRECT(ADDRESS(MATCH(B22,'Cost Factor'!B:B,0),21,1,1,"Cost Factor"))),"",INDIRECT(ADDRESS(MATCH(B22,Data!B:B,0),6,1,1,"Data"))*INDIRECT(ADDRESS(MATCH(B22,'Cost Factor'!B:B,0),21,1,1,"Cost Factor"))) -> 0 | E22: =IF(ISERROR(INDIRECT(ADDRESS(MATCH(B22,Data!B:B,0),8,1,1,"Data"))*INDIRECT(ADDRESS(MATCH(B22,'Cost Factor'!B:B,0),21,1,1,"Cost Factor"))),"",INDIRECT(ADDRESS(MATCH(B22,Data!B:B,0),8,1,1,"Data"))*INDIRECT(ADDRESS(MATCH(B22,'Cost Factor'!B:B,0),21,1,1,"Cost Factor"))) -> 0 | F22: =IF(ISERROR(INDIRECT(ADDRESS(MATCH(B22,Data!B:B,0),9,1,1,"Data"))*INDIRECT(ADDRESS(MATCH(B22,'Cost Factor'!B:B,0),21,1,1,"Cost Factor"))),"",INDIRECT(ADDRESS(MATCH(B22,Data!B:B,0),9,1,1,"Data"))*INDIRECT(ADDRESS(MATCH(B22,'Cost Factor'!B:B,0),21,1,1,"Cost Factor"))) -> 0 | G22: =IF(ISERROR(C22/(Summary!$B$47*Summary!$B$49)),"",C22/(Summary!$B$47*Summary!$B$49)) -> 18.488596 | H22: =IF(ISERROR(D22/(Summary!$B$48*Summary!$B$50)),"",D22/(Summary!$B$48*Summary!$B$50)) -> 0 | I22: =E22/(Summary!$B$51*Summary!$B$49*0.67) -> 0 | J22: =F22/(Summary!$B$50*Summary!$B$52*0.67) -> 0 | K22: =H22+G22+I22+J22 -> 18.488596 | L22: =IF(ISERROR(((G22+I22)*Summary!$B$44*Summary!$B$57)+((Calculations!G22+I22)*Summary!$B$45*Summary!$B$58)),"",((G22+I22)*Summary!$B$44*Summary!$B$57)+((Calculations!G22+I22)*Summary!$B$45*Summary!$B$58)) -> 1061559.7 | M22: =IF(ISERROR(((H22+J22)*Summary!$B$44*Summary!$B$57)+((H22+J22)*Summary!$B$45*Summary!$B$58)),"",((H22+J22)*Summary!$B$44*Summary!$B$57)+((H22+J22)*Summary!$B$45*Summary!$B$58)) -> 0 | N22: =L22+M22 -> 1061559.7 | O22: =IF(ISERROR(Summary!$B$59+Summary!$B$60+((Calculations!C22/30)/Summary!$B$53*Summary!$B$60)),"",Summary!$B$59+Summary!$B$60+((Calculations!C22/30)/Summary!$B$53*Summary!$B$60)) -> 104980.29 | P22: =IF(ISERROR(IF(K22>0,(K22*Summary!$B$46)+((Calculations!C22+D22)/500*Summary!$B$64),Calculations!N22/Summary!$B$59*Summary!$B$54)),"",IF(G22>0,(G22*Summary!$B$46)+(Calculations!C22/500*Summary!$B$64),Calculations!N22/Summary!$B$59*Summary!$B$54)) -> 148226.77 | Q22: =SUM(N22:P22) -> 1314766.8
B23: Physics | C23: =IF(ISERROR(INDIRECT(ADDRESS(MATCH(B23,Data!B:B,0),5,1,1,"Data"))*INDIRECT(ADDRESS(MATCH(B23,'Cost Factor'!B:B,0),21,1,1,"Cost Factor"))),"",INDIRECT(ADDRESS(MATCH(B23,Data!B:B,0),5,1,1,"Data"))*INDIRECT(ADDRESS(MATCH(B23,'Cost Factor'!B:B,0),21,1,1,"Cost Factor"))) -> 8193 | D23: =IF(ISERROR(INDIRECT(ADDRESS(MATCH(B23,Data!B:B,0),6,1,1,"Data"))*INDIRECT(ADDRESS(MATCH(B23,'Cost Factor'!B:B,0),21,1,1,"Cost Factor"))),"",INDIRECT(ADDRESS(MATCH(B23,Data!B:B,0),6,1,1,"Data"))*INDIRECT(ADDRESS(MATCH(B23,'Cost Factor'!B:B,0),21,1,1,"Cost Factor"))) -> 0 | E23: =IF(ISERROR(INDIRECT(ADDRESS(MATCH(B23,Data!B:B,0),8,1,1,"Data"))*INDIRECT(ADDRESS(MATCH(B23,'Cost Factor'!B:B,0),21,1,1,"Cost Factor"))),"",INDIRECT(ADDRESS(MATCH(B23,Data!B:B,0),8,1,1,"Data"))*INDIRECT(ADDRESS(MATCH(B23,'Cost Factor'!B:B,0),21,1,1,"Cost Factor"))) -> 0 | F23: =IF(ISERROR(INDIRECT(ADDRESS(MATCH(B23,Data!B:B,0),9,1,1,"Data"))*INDIRECT(ADDRESS(MATCH(B23,'Cost Factor'!B:B,0),21,1,1,"Cost Factor"))),"",INDIRECT(ADDRESS(MATCH(B23,Data!B:B,0),9,1,1,"Data"))*INDIRECT(ADDRESS(MATCH(B23,'Cost Factor'!B:B,0),21,1,1,"Cost Factor"))) -> 0 | G23: =IF(ISERROR(C23/(Summary!$B$47*Summary!$B$49)),"",C23/(Summary!$B$47*Summary!$B$49)) -> 10.344697 | H23: =IF(ISERROR(D23/(Summary!$B$48*Summary!$B$50)),"",D23/(Summary!$B$48*Summary!$B$50)) -> 0 | I23: =E23/(Summary!$B$51*Summary!$B$49*0.67) -> 0 | J23: =F23/(Summary!$B$50*Summary!$B$52*0.67) -> 0 | K23: =H23+G23+I23+J23 -> 10.344697 | L23: =IF(ISERROR(((G23+I23)*Summary!$B$44*Summary!$B$57)+((Calculations!G23+I23)*Summary!$B$45*Summary!$B$58)),"",((G23+I23)*Summary!$B$44*Summary!$B$57)+((Calculations!G23+I23)*Summary!$B$45*Summary!$B$58)) -> 593961.47 | M23: =IF(ISERROR(((H23+J23)*Summary!$B$44*Summary!$B$57)+((H23+J23)*Summary!$B$45*Summary!$B$58)),"",((H23+J23)*Summary!$B$44*Summary!$B$57)+((H23+J23)*Summary!$B$45*Summary!$B$58)) -> 0 | N23: =L23+M23 -> 593961.47 | O23: =IF(ISERROR(Summary!$B$59+Summary!$B$60+((Calculations!C23/30)/Summary!$B$53*Summary!$B$60)),"",Summary!$B$59+Summary!$B$60+((Calculations!C23/30)/Summary!$B$53*Summary!$B$60)) -> 96146.289 | P23: =IF(ISERROR(IF(K23>0,(K23*Summary!$B$46)+((Calculations!C23+D23)/500*Summary!$B$64),Calculations!N23/Summary!$B$59*Summary!$B$54)),"",IF(G23>0,(G23*Summary!$B$46)+(Calculations!C23/500*Summary!$B$64),Calculations!N23/Summary!$B$59*Summary!$B$54)) -> 82935.505 | Q23: =SUM(N23:P23) -> 773043.26
B24: Accounting, Economics, & Finance | C24: =IF(ISERROR(INDIRECT(ADDRESS(MATCH(B24,Data!B:B,0),5,1,1,"Data"))*INDIRECT(ADDRESS(MATCH(B24,'Cost Factor'!B:B,0),21,1,1,"Cost Factor"))),"",INDIRECT(ADDRESS(MATCH(B24,Data!B:B,0),5,1,1,"Data"))*INDIRECT(ADDRESS(MATCH(B24,'Cost Factor'!B:B,0),21,1,1,"Cost Factor"))) -> 8766 | D24: =IF(ISERROR(INDIRECT(ADDRESS(MATCH(B24,Data!B:B,0),6,1,1,"Data"))*INDIRECT(ADDRESS(MATCH(B24,'Cost Factor'!B:B,0),21,1,1,"Cost Factor"))),"",INDIRECT(ADDRESS(MATCH(B24,Data!B:B,0),6,1,1,"Data"))*INDIRECT(ADDRESS(MATCH(B24,'Cost Factor'!B:B,0),21,1,1,"Cost Factor"))) -> 461 | E24: =IF(ISERROR(INDIRECT(ADDRESS(MATCH(B24,Data!B:B,0),8,1,1,"Data"))*INDIRECT(ADDRESS(MATCH(B24,'Cost Factor'!B:B,0),21,1,1,"Cost Factor"))),"",INDIRECT(ADDRESS(MATCH(B24,Data!B:B,0),8,1,1,"Data"))*INDIRECT(ADDRESS(MATCH(B24,'Cost Factor'!B:B,0),21,1,1,"Cost Factor"))) -> 0 | F24: =IF(ISERROR(INDIRECT(ADDRESS(MATCH(B24,Data!B:B,0),9,1,1,"Data"))*INDIRECT(ADDRESS(MATCH(B24,'Cost Factor'!B:B,0),21,1,1,"Cost Factor"))),"",INDIRECT(ADDRESS(MATCH(B24,Data!B:B,0),9,1,1,"Data"))*INDIRECT(ADDRESS(MATCH(B24,'Cost Factor'!B:B,0),21,1,1,"Cost Factor"))) -> 0 | G24: =IF(ISERROR(C24/(Summary!$B$47*Summary!$B$49)),"",C24/(Summary!$B$47*Summary!$B$49)) -> 11.068182 | H24: =IF(ISERROR(D24/(Summary!$B$48*Summary!$B$50)),"",D24/(Summary!$B$48*Summary!$B$50)) -> 1.9700855 | I24: =E24/(Summary!$B$51*Summary!$B$49*0.67) -> 0 | J24: =F24/(Summary!$B$50*Summary!$B$52*0.67) -> 0 | K24: =H24+G24+I24+J24 -> 13.038267 | L24: =IF(ISERROR(((G24+I24)*Summary!$B$44*Summary!$B$57)+((Calculations!G24+I24)*Summary!$B$45*Summary!$B$58)),"",((G24+I24)*Summary!$B$44*Summary!$B$57)+((Calculations!G24+I24)*Summary!$B$45*Summary!$B$58)) -> 635501.8 | M24: =IF(ISERROR(((H24+J24)*Summary!$B$44*Summary!$B$57)+((H24+J24)*Summary!$B$45*Summary!$B$58)),"",((H24+J24)*Summary!$B$44*Summary!$B$57)+((H24+J24)*Summary!$B$45*Summary!$B$58)) -> 113116.4 | N24: =L24+M24 -> 748618.19 | O24: =IF(ISERROR(Summary!$B$59+Summary!$B$60+((Calculations!C24/30)/Summary!$B$53*Summary!$B$60)),"",Summary!$B$59+Summary!$B$60+((Calculations!C24/30)/Summary!$B$53*Summary!$B$60)) -> 96931.081 | P24: =IF(ISERROR(IF(K24>0,(K24*Summary!$B$46)+((Calculations!C24+D24)/500*Summary!$B$64),Calculations!N24/Summary!$B$59*Summary!$B$54)),"",IF(G24>0,(G24*Summary!$B$46)+(Calculations!C24/500*Summary!$B$64),Calculations!N24/Summary!$B$59*Summary!$B$54)) -> 88735.827 | Q24: =SUM(N24:P24) -> 934285.1
B25: Aerospace Studies | C25: =IF(ISERROR(INDIRECT(ADDRESS(MATCH(B25,Data!B:B,0),5,1,1,"Data"))*INDIRECT(ADDRESS(MATCH(B25,'Cost Factor'!B:B,0),21,1,1,"Cost Factor"))),"",INDIRECT(ADDRESS(MATCH(B25,Data!B:B,0),5,1,1,"Data"))*INDIRECT(ADDRESS(MATCH(B25,'Cost Factor'!B:B,0),21,1,1,"Cost Factor"))) -> 553 | D25: =IF(ISERROR(INDIRECT(ADDRESS(MATCH(B25,Data!B:B,0),6,1,1,"Data"))*INDIRECT(ADDRESS(MATCH(B25,'Cost Factor'!B:B,0),21,1,1,"Cost Factor"))),"",INDIRECT(ADDRESS(MATCH(B25,Data!B:B,0),6,1,1,"Data"))*INDIRECT(ADDRESS(MATCH(B25,'Cost Factor'!B:B,0),21,1,1,"Cost Factor"))) -> 0 | E25: =IF(ISERROR(INDIRECT(ADDRESS(MATCH(B25,Data!B:B,0),8,1,1,"Data"))*INDIRECT(ADDRESS(MATCH(B25,'Cost Factor'!B:B,0),21,1,1,"Cost Factor"))),"",INDIRECT(ADDRESS(MATCH(B25,Data!B:B,0),8,1,1,"Data"))*INDIRECT(ADDRESS(MATCH(B25,'Cost Factor'!B:B,0),21,1,1,"Cost Factor"))) -> 0 | F25: =IF(ISERROR(INDIRECT(ADDRESS(MATCH(B25,Data!B:B,0),9,1,1,"Data"))*INDIRECT(ADDRESS(MATCH(B25,'Cost Factor'!B:B,0),21,1,1,"Cost Factor"))),"",INDIRECT(ADDRESS(MATCH(B25,Data!B:B,0),9,1,1,"Data"))*INDIRECT(ADDRESS(MATCH(B25,'Cost Factor'!B:B,0),21,1,1,"Cost Factor"))) -> 0 | G25: =IF(ISERROR(C25/(Summary!$B$47*Summary!$B$49)),"",C25/(Summary!$B$47*Summary!$B$49)) -> 0.69823232 | H25: =IF(ISERROR(D25/(Summary!$B$48*Summary!$B$50)),"",D25/(Summary!$B$48*Summary!$B$50)) -> 0 | I25: =E25/(Summary!$B$51*Summary!$B$49*0.67) -> 0 | J25: =F25/(Summary!$B$50*Summary!$B$52*0.67) -> 0 | K25: =H25+G25+I25+J25 -> 0.69823232 | L25: =IF(ISERROR(((G25+I25)*Summary!$B$44*Summary!$B$57)+((Calculations!G25+I25)*Summary!$B$45*Summary!$B$58)),"",((G25+I25)*Summary!$B$44*Summary!$B$57)+((Calculations!G25+I25)*Summary!$B$45*Summary!$B$58)) -> 40090.405 | M25: =IF(ISERROR(((H25+J25)*Summary!$B$44*Summary!$B$57)+((H25+J25)*Summary!$B$45*Summary!$B$58)),"",((H25+J25)*Summary!$B$44*Summary!$B$57)+((H25+J25)*Summary!$B$45*Summary!$B$58)) -> 0 | N25: =L25+M25 -> 40090.405 | O25: =IF(ISERROR(Summary!$B$59+Summary!$B$60+((Calculations!C25/30)/Summary!$B$53*Summary!$B$60)),"",Summary!$B$59+Summary!$B$60+((Calculations!C25/30)/Summary!$B$53*Summary!$B$60)) -> 85682.399 | P25: =IF(ISERROR(IF(K25>0,(K25*Summary!$B$46)+((Calculations!C25+D25)/500*Summary!$B$64),Calculations!N25/Summary!$B$59*Summary!$B$54)),"",IF(G25>0,(G25*Summary!$B$46)+(Calculations!C25/500*Summary!$B$64),Calculations!N25/Summary!$B$59*Summary!$B$54)) -> 5597.8682 | Q25: =SUM(N25:P25) -> 131370.67
... B35: Academic Affairs | C35: =IF(ISERROR(INDIRECT(ADDRESS(MATCH(B35,Data!B:B,0),5,1,1,"Data"))*INDIRECT(ADDRESS(MATCH(B35,'Cost Factor'!B:B,0),21,1,1,"Cost Factor"))),"",INDIRECT(ADDRESS(MATCH(B35,Data!B:B,0),5,1,1,"Data"))*INDIRECT(ADDRESS(MATCH(B35,'Cost Factor'!B:B,0),21,1,1,"Cost Factor"))) -> 1658 | D35: =IF(ISERROR(INDIRECT(ADDRESS(MATCH(B35,Data!B:B,0),6,1,1,"Data"))*INDIRECT(ADDRESS(MATCH(B35,'Cost Factor'!B:B,0),21,1,1,"Cost Factor"))),"",INDIRECT(ADDRESS(MATCH(B35,Data!B:B,0),6,1,1,"Data"))*INDIRECT(ADDRESS(MATCH(B35,'Cost Factor'!B:B,0),21,1,1,"Cost Factor"))) -> 0 | E35: =IF(ISERROR(INDIRECT(ADDRESS(MATCH(B35,Data!B:B,0),8,1,1,"Data"))*INDIRECT(ADDRESS(MATCH(B35,'Cost Factor'!B:B,0),21,1,1,"Cost Factor"))),"",INDIRECT(ADDRESS(MATCH(B35,Data!B:B,0),8,1,1,"Data"))*INDIRECT(ADDRESS(MATCH(B35,'Cost Factor'!B:B,0),21,1,1,"Cost Factor"))) -> 0 | F35: =IF(ISERROR(INDIRECT(ADDRESS(MATCH(B35,Data!B:B,0),9,1,1,"Data"))*INDIRECT(ADDRESS(MATCH(B35,'Cost Factor'!B:B,0),21,1,1,"Cost Factor"))),"",INDIRECT(ADDRESS(MATCH(B35,Data!B:B,0),9,1,1,"Data"))*INDIRECT(ADDRESS(MATCH(B35,'Cost Factor'!B:B,0),21,1,1,"Cost Factor"))) -> 0 | G35: =IF(ISERROR(C35/(Summary!$B$47*Summary!$B$49)),"",C35/(Summary!$B$47*Summary!$B$49)) -> 2.0934343 | H35: =IF(ISERROR(D35/(Summary!$B$48*Summary!$B$50)),"",D35/(Summary!$B$48*Summary!$B$50)) -> 0 | I35: =E35/(Summary!$B$51*Summary!$B$49*0.67) -> 0 | J35: =F35/(Summary!$B$50*Summary!$B$52*0.67) -> 0 | K35: =H35+G35+I35+J35 -> 2.0934343 | L35: =IF(ISERROR(((G35+I35)*Summary!$B$44*Summary!$B$57)+((Calculations!G35+I35)*Summary!$B$45*Summary!$B$58)),"",((G35+I35)*Summary!$B$44*Summary!$B$57)+((Calculations!G35+I35)*Summary!$B$45*Summary!$B$58)) -> 120198.72 | M35: =IF(ISERROR(((H35+J35)*Summary!$B$44*Summary!$B$57)+((H35+J35)*Summary!$B$45*Summary!$B$58)),"",((H35+J35)*Summary!$B$44*Summary!$B$57)+((H35+J35)*Summary!$B$45*Summary!$B$58)) -> 0 | N35: =L35+M35 -> 120198.72 | O35: =IF(ISERROR(Summary!$B$59+Summary!$B$60+((Calculations!C35/30)/Summary!$B$53*Summary!$B$60)),"",Summary!$B$59+Summary!$B$60+((Calculations!C35/30)/Summary!$B$53*Summary!$B$60)) -> 87195.828 | P35: =IF(ISERROR(IF(K35>0,(K35*Summary!$B$46)+((Calculations!C35+D35)/500*Summary!$B$64),Calculations!N35/Summary!$B$59*Summary!$B$54)),"",IF(G35>0,(G35*Summary!$B$46)+(Calculations!C35/500*Summary!$B$64),Calculations!N35/Summary!$B$59*Summary!$B$54)) -> 16783.482 | Q35: =SUM(N35:P35) -> 224178.03
B36: Facilities

Sheet Cost Factor
C1: 2010/11
B2: Total Adjusted Revenues | C2: =Revenue!J62 -> 47056603
B3: Administrative $
B4: Facility $ (prior yr facilities allocation) | C4: 4206660
B5: Instructional Funding | C5: =C33 -> 18412640
B6: Inst. Overhead Factor | C6: =(C2-C4-C5)/C5 -> 1.3272026
I7: Not Needed
C9: 2010/11 Expenditures | D9: 2010/11 Instructional Compensation | E9: 2011/12 Total Credits | F9: Instructional Cost per Credit | G9: Departmental Cost per Credit | H9: Institutional Cost per Credit | I9: Departmental Overhead % | J9: Calculated Faculty FTE | K9: Actual Faculty FTE | L9: Faculty Instructional Hours | M9: IH_Cost | N9: Department IH_Cost | O9: Institutional IH_Cost | P9: Revenue per Credit Hour | Q9: Instructional Break-Even Class Size | R9: Departmental Break-Even Class Size | S9: Institutional Break-Even Class Size | T9: Restricted Class Size | U9: Cost Factor
B10: Agriculture | C10: =INDIRECT(ADDRESS(MATCH(B10,Summary!A:A,0),7,1,1,"Summary")) -> 599585.43 | D10: 404624.43 | E10: =INDIRECT(ADDRESS(MATCH(B10,Data!B:B,0),7,1,1,"Data")) -> 6237 | F10: =IF(ISERROR(D10/E10),"",D10/E10) -> 64.874848 | G10: =IF(ISERROR((C10)/E10),"",(C10)/E10) -> 96.133627 | H10: =IF(ISERROR(G10*(1+$C$6)),"",G10*(1+$C$6)) -> 223.72242 | I10: =IF(ISERROR((G10/F10)-1),"",(G10/F10)-1) -> 0.481832 | J10: =INDIRECT(ADDRESS(MATCH(B10,Calculations!B:B,0),11,1,1,"Calculations")) -> 9.0703186 | K10: 8.9672954 | L10: =IF(ISERROR(K10*Summary!$B$49),"",K10*Summary!$B$49) -> 215.21509 | M10: =IF(ISERROR(D10/L10),"",D10/L10) -> 1880.0932 | N10: =IF(ISERROR((C10+D10)/L10),"",(C10+D10)/L10) -> 4666.0755 | O10: =IF(ISERROR(N10*(1+$C$6)),"",N10*(1+$C$6)) -> 10858.903 | P10: =((2425.05+135)/15)+64.99 -> 235.66 | Q10: =IF(ISERROR(M10/P10),"",M10/P10) -> 7.9779904 | R10: =IF(ISERROR(N10/P10),"",N10/P10) -> 19.800032 | S10: =IF(ISERROR(O10/P10),"",O10/P10) -> 46.078685 | U10: =IF(T10>0,Summary!$B$47/T10,IF(S10<Summary!$B$47,'Cost Factor'!S10/Summary!$B$47,1)) -> 1
B11: Art & Music | C11: =INDIRECT(ADDRESS(MATCH(B11,Summary!A:A,0),7,1,1,"Summary")) -> 1225927.7 | D11: 1124676.9 | E11: =INDIRECT(ADDRESS(MATCH(B11,Data!B:B,0),7,1,1,"Data")) -> 8883 | F11: =IF(ISERROR(D11/E11),"",D11/E11) -> 126.61003 | G11: =IF(ISERROR((C11)/E11),"",(C11)/E11) -> 138.0083 | H11: =IF(ISERROR(G11*(1+$C$6)),"",G11*(1+$C$6)) -> 321.17326 | I11: =IF(ISERROR((G11/F11)-1),"",(G11/F11)-1) -> 0.090026538 | J11: =INDIRECT(ADDRESS(MATCH(B11,Calculations!B:B,0),11,1,1,"Calculations")) -> 11.215909 | K11: 12.75708 | L11: =IF(ISERROR(K11*Summary!$B$49),"",K11*Summary!$B$49) -> 306.16991 | M11: =IF(ISERROR(D11/L11),"",D11/L11) -> 3673.3751 | N11: =IF(ISERROR((C11+D11)/L11),"",(C11+D11)/L11) -> 7677.4514 | O11: =IF(ISERROR(N11*(1+$C$6)),"",N11*(1+$C$6)) -> 17866.985 | P11: =((2425.05+135)/15)+64.99 -> 235.66 | Q11: =IF(ISERROR(M11/P11),"",M11/P11) -> 15.587605 | R11: =IF(ISERROR(N11/P11),"",N11/P11) -> 32.578509 | S11: =IF(ISERROR(O11/P11),"",O11/P11) -> 75.816789 | U11: =IF(T11>0,Summary!$B$47/T11,IF(S11<Summary!$B$47,'Cost Factor'!S11/Summary!$B$47,1)) -> 1
B12: Biology | C12: =INDIRECT(ADDRESS(MATCH(B12,Summary!A:A,0),7,1,1,"Summary")) -> 1165519.6 | D12: 996802.07 | E12: =INDIRECT(ADDRESS(MATCH(B12,Data!B:B,0),7,1,1,"Data")) -> 12243 | F12: =IF(ISERROR(D12/E12),"",D12/E12) -> 81.418122 | G12: =IF(ISERROR((C12)/E12),"",(C12)/E12) -> 95.19886 | H12: =IF(ISERROR(G12*(1+$C$6)),"",G12*(1+$C$6)) -> 221.54703 | I12: =IF(ISERROR((G12/F12)-1),"",(G12/F12)-1) -> 0.16925885 | J12: =INDIRECT(ADDRESS(MATCH(B12,Calculations!B:B,0),11,1,1,"Calculations")) -> 16.599456 | K12: 15.933371 | L12: =IF(ISERROR(K12*Summary!$B$49),"",K12*Summary!$B$49) -> 382.40091 | M12: =IF(ISERROR(D12/L12),"",D12/L12) -> 2606.6938 | N12: =IF(ISERROR((C12+D12)/L12),"",(C12+D12)/L12) -> 5654.5936 | O12: =IF(ISERROR(N12*(1+$C$6)),"",N12*(1+$C$6)) -> 13159.385 | P12: =((2425.05+135)/15)+64.99 -> 235.66 | Q12: =IF(ISERROR(M12/P12),"",M12/P12) -> 11.061248 | R12: =IF(ISERROR(N12/P12),"",N12/P12) -> 23.994711 | S12: =IF(ISERROR(O12/P12),"",O12/P12) -> 55.840553 | U12: =IF(T12>0,Summary!$B$47/T12,IF(S12<Summary!$B$47,'Cost Factor'!S12/Summary!$B$47,1)) -> 1
B13: Chemistry & Biochemistry | C13: =INDIRECT(ADDRESS(MATCH(B13,Summary!A:A,0),7,1,1,"Summary")) -> 595096.85 | D13: 514254.34 | E13: =INDIRECT(ADDRESS(MATCH(B13,Data!B:B,0),7,1,1,"Data")) -> 5779 | F13: =IF(ISERROR(D13/E13),"",D13/E13) -> 88.986735 | G13: =IF(ISERROR((C13)/E13),"",(C13)/E13) -> 102.97575 | H13: =IF(ISERROR(G13*(1+$C$6)),"",G13*(1+$C$6)) -> 239.64542 | I13: =IF(ISERROR((G13/F13)-1),"",(G13/F13)-1) -> 0.15720336 | J13: =INDIRECT(ADDRESS(MATCH(B13,Calculations!B:B,0),11,1,1,"Calculations")) -> 7.3147824 | K13: 7.98464 | L13: =IF(ISERROR(K13*Summary!$B$49),"",K13*Summary!$B$49) -> 191.63136 | M13: =IF(ISERROR(D13/L13),"",D13/L13) -> 2683.5605 | N13: =IF(ISERROR((C13+D13)/L13),"",(C13+D13)/L13) -> 5788.9856 | O13: =IF(ISERROR(N13*(1+$C$6)),"",N13*(1+$C$6)) -> 13472.142 | P13: =((2425.05+135)/15)+64.99 -> 235.66 | Q13: =IF(ISERROR(M13/P13),"",M13/P13) -> 11.387424 | R13: =IF(ISERROR(N13/P13),"",N13/P13) -> 24.56499 | S13: =IF(ISERROR(O13/P13),"",O13/P13) -> 57.167708 | U13: =IF(T13>0,Summary!$B$47/T13,IF(S13<Summary!$B$47,'Cost Factor'!S13/Summary!$B$47,1)) -> 1
B14: Communication, Mass Media, & Theatre | C14: =INDIRECT(ADDRESS(MATCH(B14,Summary!A:A,0),7,1,1,"Summary")) -> 1256290.9 | D14: 981628.61 | E14: =INDIRECT(ADDRESS(MATCH(B14,Data!B:B,0),7,1,1,"Data")) -> 11360 | F14: =IF(ISERROR(D14/E14),"",D14/E14) -> 86.410969 | G14: =IF(ISERROR((C14)/E14),"",(C14)/E14) -> 110.58899 | H14: =IF(ISERROR(G14*(1+$C$6)),"",G14*(1+$C$6)) -> 257.36298 | I14: =IF(ISERROR((G14/F14)-1),"",(G14/F14)-1) -> 0.27980267 | J14: =INDIRECT(ADDRESS(MATCH(B14,Calculations!B:B,0),11,1,1,"Calculations")) -> 15.544775 | K14: 14.181245 | L14: =IF(ISERROR(K14*Summary!$B$49),"",K14*Summary!$B$49) -> 340.34988 | M14: =IF(ISERROR(D14/L14),"",D14/L14) -> 2884.175 | N14: =IF(ISERROR((C14+D14)/L14),"",(C14+D14)/L14) -> 6575.3499 | O14: =IF(ISERROR(N14*(1+$C$6)),"",N14*(1+$C$6)) -> 15302.171 | P14: =((2425.05+135)/15)+64.99 -> 235.66 | Q14: =IF(ISERROR(M14/P14),"",M14/P14) -> 12.238713 | R14: =IF(ISERROR(N14/P14),"",N14/P14) -> 27.90185 | S14: =IF(ISERROR(O14/P14),"",O14/P14) -> 64.933256 | U14: =IF(T14>0,Summary!$B$47/T14,IF(S14<Summary!$B$47,'Cost Factor'!S14/Summary!$B$47,1)) -> 1
B15: English & Modern Langagues | C15: =INDIRECT(ADDRESS(MATCH(B15,Summary!A:A,0),7,1,1,"Summary")) -> 1561489.3 | D15: 1878453.3 | E15: =INDIRECT(ADDRESS(MATCH(B15,Data!B:B,0),7,1,1,"Data")) -> 18303 | F15: =IF(ISERROR(D15/E15),"",D15/E15) -> 102.6309 | G15: =IF(ISERROR((C15)/E15),"",(C15)/E15) -> 85.3133 | H15: =IF(ISERROR(G15*(1+$C$6)),"",G15*(1+$C$6)) -> 198.54133 | I15: =IF(ISERROR((G15/F15)-1),"",(G15/F15)-1) -> -0.16873667 | J15: =INDIRECT(ADDRESS(MATCH(B15,Calculations!B:B,0),11,1,1,"Calculations")) -> 23.86859 | K15: 23.102357 | L15: =IF(ISERROR(K15*Summary!$B$49),"",K15*Summary!$B$49) -> 554.45658 | M15: =IF(ISERROR(D15/L15),"",D15/L15) -> 3387.9178 | N15: =IF(ISERROR((C15+D15)/L15),"",(C15+D15)/L15) -> 6204.1696 | O15: =IF(ISERROR(N15*(1+$C$6)),"",N15*(1+$C$6)) -> 14438.359 | P15: =((2425.05+135)/15)+64.99 -> 235.66 | Q15: =IF(ISERROR(M15/P15),"",M15/P15) -> 14.376295 | R15: =IF(ISERROR(N15/P15),"",N15/P15) -> 26.326783 | S15: =IF(ISERROR(O15/P15),"",O15/P15) -> 61.267756 | U15: =IF(T15>0,Summary!$B$47/T15,IF(S15<Summary!$B$47,'Cost Factor'!S15/Summary!$B$47,1)) -> 1
B16: Pol Science | C16: =INDIRECT(ADDRESS(MATCH(B16,Summary!A:A,0),7,1,1,"Summary")) -> 813960.94 | D16: 762164.38 | E16: =INDIRECT(ADDRESS(MATCH(B16,Data!B:B,0),7,1,1,"Data")) -> 4527 | F16: =IF(ISERROR(D16/E16),"",D16/E16) -> 168.3597 | G16: =IF(ISERROR((C16)/E16),"",(C16)/E16) -> 179.8014 | H16: =IF(ISERROR(G16*(1+$C$6)),"",G16*(1+$C$6)) -> 418.43428 | I16: =IF(ISERROR((G16/F16)-1),"",(G16/F16)-1) -> 0.067959828 | J16: =INDIRECT(ADDRESS(MATCH(B16,Calculations!B:B,0),11,1,1,"Calculations")) -> 5.743007 | K16: 4.625 | L16: =IF(ISERROR(K16*Summary!$B$49),"",K16*Summary!$B$49) -> 111 | M16: =IF(ISERROR(D16/L16),"",D16/L16) -> 6866.3458 | N16: =IF(ISERROR((C16+D16)/L16),"",(C16+D16)/L16) -> 14199.327 | O16: =IF(ISERROR(N16*(1+$C$6)),"",N16*(1+$C$6)) -> 33044.711 | P16: =((2425.05+135)/15)+64.99 -> 235.66 | Q16: =IF(ISERROR(M16/P16),"",M16/P16) -> 29.136662 | R16: =IF(ISERROR(N16/P16),"",N16/P16) -> 60.253447 | S16: =IF(ISERROR(O16/P16),"",O16/P16) -> 140.22197 | U16: =IF(T16>0,Summary!$B$47/T16,IF(S16<Summary!$B$47,'Cost Factor'!S16/Summary!$B$47,1)) -> 1
B17: History | C17: =INDIRECT(ADDRESS(MATCH(B17,Summary!A:A,0),7,1,1,"Summary")) -> 747361.15 | D17: 692558.3 | E17: =INDIRECT(ADDRESS(MATCH(B17,Data!B:B,0),7,1,1,"Data")) -> 13413 | F17: =IF(ISERROR(D17/E17),"",D17/E17) -> 51.633363 | G17: =IF(ISERROR((C17)/E17),"",(C17)/E17) -> 55.719164 | H17: =IF(ISERROR(G17*(1+$C$6)),"",G17*(1+$C$6)) -> 129.66978 | I17: =IF(ISERROR((G17/F17)-1),"",(G17/F17)-1) -> 0.079131028 | J17: =INDIRECT(ADDRESS(MATCH(B17,Calculations!B:B,0),11,1,1,"Calculations")) -> 17.251748 | K17: 17.311414 | L17: =IF(ISERROR(K17*Summary!$B$49),"",K17*Summary!$B$49) -> 415.47395 | M17: =IF(ISERROR(D17/L17),"",D17/L17) -> 1666.9115 | N17: =IF(ISERROR((C17+D17)/L17),"",(C17+D17)/L17) -> 3465.7274 | O17: =IF(ISERROR(N17*(1+$C$6)),"",N17*(1+$C$6)) -> 8065.4497 | P17: =((2425.05+135)/15)+64.99 -> 235.66 | Q17: =IF(ISERROR(M17/P17),"",M17/P17) -> 7.0733748 | R17: =IF(ISERROR(N17/P17),"",N17/P17) -> 14.706473 | S17: =IF(ISERROR(O17/P17),"",O17/P17) -> 34.224942 | U17: =IF(T17>0,Summary!$B$47/T17,IF(S17<Summary!$B$47,'Cost Factor'!S17/Summary!$B$47,1)) -> 1
B18: Mathematics & Computer Science | C18: =INDIRECT(ADDRESS(MATCH(B18,Summary!A:A,0),7,1,1,"Summary")) -> 34069.77 | D18: 1448850.5 | E18: =INDIRECT(ADDRESS(MATCH(B18,Data!B:B,0),7,1,1,"Data")) -> 17794 | F18: =IF(ISERROR(D18/E18),"",D18/E18) -> 81.423541 | G18: =IF(ISERROR((C18)/E18),"",(C18)/E18) -> 1.9146774 | H18: =IF(ISERROR(G18*(1+$C$6)),"",G18*(1+$C$6)) -> 4.4558422 | I18: =IF(ISERROR((G18/F18)-1),"",(G18/F18)-1) -> -0.97648496 | J18: =INDIRECT(ADDRESS(MATCH(B18,Calculations!B:B,0),11,1,1,"Calculations")) -> 18.488596 | K18: 22.469086 | L18: =IF(ISERROR(K18*Summary!$B$49),"",K18*Summary!$B$49) -> 539.25806 | M18: =IF(ISERROR(D18/L18),"",D18/L18) -> 2686.7479 | N18: =IF(ISERROR((C18+D18)/L18),"",(C18+D18)/L18) -> 2749.9269 | O18: =IF(ISERROR(N18*(1+$C$6)),"",N18*(1+$C$6)) -> 6399.6369 | P18: =((2425.05+135)/15)+64.99 -> 235.66 | Q18: =IF(ISERROR(M18/P18),"",M18/P18) -> 11.40095 | R18: =IF(ISERROR(N18/P18),"",N18/P18) -> 11.669044 | S18: =IF(ISERROR(O18/P18),"",O18/P18) -> 27.156229 | U18: =IF(T18>0,Summary!$B$47/T18,IF(S18<Summary!$B$47,'Cost Factor'!S18/Summary!$B$47,1)) -> 0.82291603
B19: Physics | C19: =INDIRECT(ADDRESS(MATCH(B19,Summary!A:A,0),7,1,1,"Summary")) -> 699416.54 | D19: 604948.09 | E19: =INDIRECT(ADDRESS(MATCH(B19,Data!B:B,0),7,1,1,"Data")) -> 8193 | F19: =IF(ISERROR(D19/E19),"",D19/E19) -> 73.837189 | G19: =IF(ISERROR((C19)/E19),"",(C19)/E19) -> 85.367575 | H19: =IF(ISERROR(G19*(1+$C$6)),"",G19*(1+$C$6)) -> 198.66764 | I19: =IF(ISERROR((G19/F19)-1),"",(G19/F19)-1) -> 0.1561596 | J19: =INDIRECT(ADDRESS(MATCH(B19,Calculations!B:B,0),11,1,1,"Calculations")) -> 10.344697 | K19: 10.87676 | L19: =IF(ISERROR(K19*Summary!$B$49),"",K19*Summary!$B$49) -> 261.04224 | M19: =IF(ISERROR(D19/L19),"",D19/L19) -> 2317.4337 | N19: =IF(ISERROR((C19+D19)/L19),"",(C19+D19)/L19) -> 4996.757 | O19: =IF(ISERROR(N19*(1+$C$6)),"",N19*(1+$C$6)) -> 11628.466 | P19: =((2425.05+135)/15)+64.99 -> 235.66 | Q19: =IF(ISERROR(M19/P19),"",M19/P19) -> 9.8338019 | R19: =IF(ISERROR(N19/P19),"",N19/P19) -> 21.203246 | S19: =IF(ISERROR(O19/P19),"",O19/P19) -> 49.344249 | U19: =IF(T19>0,Summary!$B$47/T19,IF(S19<Summary!$B$47,'Cost Factor'!S19/Summary!$B$47,1)) -> 1
B20: Accounting, Economics, & Finance | C20: =INDIRECT(ADDRESS(MATCH(B20,Summary!A:A,0),7,1,1,"Summary")) -> 1233545 | D20: 1169666.9 | E20: =INDIRECT(ADDRESS(MATCH(B20,Data!B:B,0),7,1,1,"Data")) -> 9227 | F20: =IF(ISERROR(D20/E20),"",D20/E20) -> 126.76567 | G20: =IF(ISERROR((C20)/E20),"",(C20)/E20) -> 133.68864 | H20: =IF(ISERROR(G20*(1+$C$6)),"",G20*(1+$C$6)) -> 311.12053 | I20: =IF(ISERROR((G20/F20)-1),"",(G20/F20)-1) -> 0.054612285 | J20: =INDIRECT(ADDRESS(MATCH(B20,Calculations!B:B,0),11,1,1,"Calculations")) -> 13.038267 | K20: 12.222705 | L20: =IF(ISERROR(K20*Summary!$B$49),"",K20*Summary!$B$49) -> 293.34491 | M20: =IF(ISERROR(D20/L20),"",D20/L20) -> 3987.3433 | N20: =IF(ISERROR((C20+D20)/L20),"",(C20+D20)/L20) -> 8192.4444 | O20: =IF(ISERROR(N20*(1+$C$6)),"",N20*(1+$C$6)) -> 19065.478 | P20: =((2425.05+135)/15)+64.99 -> 235.66 | Q20: =IF(ISERROR(M20/P20),"",M20/P20) -> 16.919898 | R20: =IF(ISERROR(N20/P20),"",N20/P20) -> 34.763831 | S20: =IF(ISERROR(O20/P20),"",O20/P20) -> 80.902476 | U20: =IF(T20>0,Summary!$B$47/T20,IF(S20<Summary!$B$47,'Cost Factor'!S20/Summary!$B$47,1)) -> 1
B21: Aerospace Studies | C21: =INDIRECT(ADDRESS(MATCH(B21,Summary!A:A,0),7,1,1,"Summary")) -> 50559.72 | E21: =INDIRECT(ADDRESS(MATCH(B21,Data!B:B,0),7,1,1,"Data")) -> 553 | F21: =IF(ISERROR(D21/E21),"",D21/E21) -> 0 | G21: =IF(ISERROR((C21)/E21),"",(C21)/E21) -> 91.428065 | H21: =IF(ISERROR(G21*(1+$C$6)),"",G21*(1+$C$6)) -> 212.77163 | I21: =IF(ISERROR((G21/F21)-1),"",(G21/F21)-1) | J21: =INDIRECT(ADDRESS(MATCH(B21,Calculations!B:B,0),11,1,1,"Calculations")) -> 0.69823232 | K21: 0.37096774 | L21: =IF(ISERROR(K21*Summary!$B$49),"",K21*Summary!$B$49) -> 8.9032258 | M21: =IF(ISERROR(D21/L21),"",D21/L21) -> 0 | N21: =IF(ISERROR((C21+D21)/L21),"",(C21+D21)/L21) -> 5678.8091 | O21: =IF(ISERROR(N21*(1+$C$6)),"",N21*(1+$C$6)) -> 13215.739 | P21: =((2425.05+135)/15)+64.99 -> 235.66 | Q21: =IF(ISERROR(M21/P21),"",M21/P21) -> 0 | R21: =IF(ISERROR(N21/P21),"",N21/P21) -> 24.097467 | S21: =IF(ISERROR(O21/P21),"",O21/P21) -> 56.079687 | U21: =IF(T21>0,Summary!$B$47/T21,IF(S21<Summary!$B$47,'Cost Factor'!S21/Summary!$B$47,1)) -> 1
B22: Management & marketing | C22: =INDIRECT(ADDRESS(MATCH(B22,Summary!A:A,0),7,1,1,"Summary")) -> 1356228.3 | D22: 1279505.9 | E22: =INDIRECT(ADDRESS(MATCH(B22,Data!B:B,0),7,1,1,"Data")) -> 8589 | F22: =IF(ISERROR(D22/E22),"",D22/E22) -> 148.9703 | G22: =IF(ISERROR((C22)/E22),"",(C22)/E22) -> 157.90293 | H22: =IF(ISERROR(G22*(1+$C$6)),"",G22*(1+$C$6)) -> 367.47211 | I22: =IF(ISERROR((G22/F22)-1),"",(G22/F22)-1) -> 0.05996253 | J22: =INDIRECT(ADDRESS(MATCH(B22,Calculations!B:B,0),11,1,1,"Calculations")) -> 13.199204 | K22: 10.480459 | L22: =IF(ISERROR(K22*Summary!$B$49),"",K22*Summary!$B$49) -> 251.53102 | M22: =IF(ISERROR(D22/L22),"",D22/L22) -> 5086.8712 | N22: =IF(ISERROR((C22+D22)/L22),"",(C22+D22)/L22) -> 10478.764 | O22: =IF(ISERROR(N22*(1+$C$6)),"",N22*(1+$C$6)) -> 24386.207 | P22: =((2425.05+135)/15)+64.99 -> 235.66 | Q22: =IF(ISERROR(M22/P22),"",M22/P22) -> 21.585637 | R22: =IF(ISERROR(N22/P22),"",N22/P22) -> 44.465603 | S22: =IF(ISERROR(O22/P22),"",O22/P22) -> 103.48047 | U22: =IF(T22>0,Summary!$B$47/T22,IF(S22<Summary!$B$47,'Cost Factor'!S22/Summary!$B$47,1)) -> 1
B23: Security Studies & Criminal Justice | C23: =INDIRECT(ADDRESS(MATCH(B23,Summary!A:A,0),7,1,1,"Summary")) -> 0 | E23: =INDIRECT(ADDRESS(MATCH(B23,Data!B:B,0),7,1,1,"Data")) -> 4319 | F23: =IF(ISERROR(D23/E23),"",D23/E23) -> 0 | G23: =IF(ISERROR((C23)/E23),"",(C23)/E23) -> 0 | H23: =IF(ISERROR(G23*(1+$C$6)),"",G23*(1+$C$6)) -> 0 | I23: =IF(ISERROR((G23/F23)-1),"",(G23/F23)-1) | J23: =INDIRECT(ADDRESS(MATCH(B23,Calculations!B:B,0),11,1,1,"Calculations")) -> 0 | K23: 6.7570306 | L23: =IF(ISERROR(K23*Summary!$B$49),"",K23*Summary!$B$49) -> 162.16873 | M23: =IF(ISERROR(D23/L23),"",D23/L23) -> 0 | N23: =IF(ISERROR((C23+D23)/L23),"",(C23+D23)/L23) -> 0 | O23: =IF(ISERROR(N23*(1+$C$6)),"",N23*(1+$C$6)) -> 0 | P23: =((2425.05+135)/15)+64.99 -> 235.66 | Q23: =IF(ISERROR(M23/P23),"",M23/P23) -> 0 | R23: =IF(ISERROR(N23/P23),"",N23/P23) -> 0 | S23: =IF(ISERROR(O23/P23),"",O23/P23) -> 0 | U23: =IF(T23>0,Summary!$B$47/T23,IF(S23<Summary!$B$47,'Cost Factor'!S23/Summary!$B$47,1)) -> 0
B24: Teacher Education | C24: =INDIRECT(ADDRESS(MATCH(B24,Summary!A:A,0),7,1,1,"Summary")) -> 869748.16 | D24: 750714.67 | E24: =INDIRECT(ADDRESS(MATCH(B24,Data!B:B,0),7,1,1,"Data")) -> 8049 | F24: =IF(ISERROR(D24/E24),"",D24/E24) -> 93.268067 | G24: =IF(ISERROR((C24)/E24),"",(C24)/E24) -> 108.05667 | H24: =IF(ISERROR(G24*(1+$C$6)),"",G24*(1+$C$6)) -> 251.46977 | I24: =IF(ISERROR((G24/F24)-1),"",(G24/F24)-1) -> 0.15856023 | J24: =INDIRECT(ADDRESS(MATCH(B24,Calculations!B:B,0),11,1,1,"Calculations")) -> 12.439103 | K24: 5.5282258 | L24: =IF(ISERROR(K24*Summary!$B$49),"",K24*Summary!$B$49) -> 132.67742 | M24: =IF(ISERROR(D24/L24),"",D24/L24) -> 5658.1947 | N24: =IF(ISERROR((C24+D24)/L24),"",(C24+D24)/L24) -> 12213.554 | O24: =IF(ISERROR(N24*(1+$C$6)),"",N24*(1+$C$6)) -> 28423.414 | P24: =((2425.05+135)/15)+64.99 -> 235.66 | Q24: =IF(ISERROR(M24/P24),"",M24/P24) -> 24.009992 | R24: =IF(ISERROR(N24/P24),"",N24/P24) -> 51.827014 | S24: =IF(ISERROR(O24/P24),"",O24/P24) -> 120.61196 | U24: =IF(T24>0,Summary!$B$47/T24,IF(S24<Summary!$B$47,'Cost Factor'!S24/Summary!$B$47,1)) -> 1
B25: Curriculum & Instruction | C25: =INDIRECT(ADDRESS(MATCH(B25,Summary!A:A,0),7,1,1,"Summary")) -> 927480.14 | D25: 766315.62 | E25: =INDIRECT(ADDRESS(MATCH(B25,Data!B:B,0),7,1,1,"Data")) -> 7650 | F25: =IF(ISERROR(D25/E25),"",D25/E25) -> 100.17198 | G25: =IF(ISERROR((C25)/E25),"",(C25)/E25) -> 121.23923 | H25: =IF(ISERROR(G25*(1+$C$6)),"",G25*(1+$C$6)) -> 282.14826 | I25: =IF(ISERROR((G25/F25)-1),"",(G25/F25)-1) -> 0.21031089 | J25: =INDIRECT(ADDRESS(MATCH(B25,Calculations!B:B,0),11,1,1,"Calculations")) -> 27.841783 | K25: 17.01799 | L25: =IF(ISERROR(K25*Summary!$B$49),"",K25*Summary!$B$49) -> 408.43176 | M25: =IF(ISERROR(D25/L25),"",D25/L25) -> 1876.239 | N25: =IF(ISERROR((C25+D25)/L25),"",(C25+D25)/L25) -> 4147.0716 | O25: =IF(ISERROR(N25*(1+$C$6)),"",N25*(1+$C$6)) -> 9651.0756 | P25: =((2425.05+135)/15)+64.99 -> 235.66 | Q25: =IF(ISERROR(M25/P25),"",M25/P25) -> 7.9616356 | R25: =IF(ISERROR(N25/P25),"",N25/P25) -> 17.59769 | S25: =IF(ISERROR(O25/P25),"",O25/P25) -> 40.953389 | U25: =IF(T25>0,Summary!$B$47/T25,IF(S25<Summary!$B$47,'Cost Factor'!S25/Summary!$B$47,1)) -> 1
B26: Kinesiology | C26: =INDIRECT(ADDRESS(MATCH(B26,Summary!A:A,0),7,1,1,"Summary")) -> 835180.02 | D26: 759352.23 | E26: =INDIRECT(ADDRESS(MATCH(B26,Data!B:B,0),7,1,1,"Data")) -> 6485 | F26: =IF(ISERROR(D26/E26),"",D26/E26) -> 117.09364 | G26: =IF(ISERROR((C26)/E26),"",(C26)/E26) -> 128.78643 | H26: =IF(ISERROR(G26*(1+$C$6)),"",G26*(1+$C$6)) -> 299.71212 | I26: =IF(ISERROR((G26/F26)-1),"",(G26/F26)-1) -> 0.09985852 | J26: =INDIRECT(ADDRESS(MATCH(B26,Calculations!B:B,0),11,1,1,"Calculations")) -> 10.112082 | K26: 7.7224979 | L26: =IF(ISERROR(K26*Summary!$B$49),"",K26*Summary!$B$49) -> 185.33995 | M26: =IF(ISERROR(D26/L26),"",D26/L26) -> 4097.078 | N26: =IF(ISERROR((C26+D26)/L26),"",(C26+D26)/L26) -> 8603.2841 | O26: =IF(ISERROR(N26*(1+$C$6)),"",N26*(1+$C$6)) -> 20021.585 | P26: =((2425.05+135)/15)+64.99 -> 235.66 | Q26: =IF(ISERROR(M26/P26),"",M26/P26) -> 17.385547 | R26: =IF(ISERROR(N26/P26),"",N26/P26) -> 36.507189 | S26: =IF(ISERROR(O26/P26),"",O26/P26) -> 84.959623 | U26: =IF(T26>0,Summary!$B$47/T26,IF(S26<Summary!$B$47,'Cost Factor'!S26/Summary!$B$47,1)) -> 1
B27: Nursing | C27: =INDIRECT(ADDRESS(MATCH(B27,Summary!A:A,0),7,1,1,"Summary")) -> 2186809.8 | D27: 2006062.1 | E27: =INDIRECT(ADDRESS(MATCH(B27,Data!B:B,0),7,1,1,"Data")) -> 15067 | F27: =IF(ISERROR(D27/E27),"",D27/E27) -> 133.14277 | G27: =IF(ISERROR((C27)/E27),"",(C27)/E27) -> 145.13903 | H27: =IF(ISERROR(G27*(1+$C$6)),"",G27*(1+$C$6)) -> 337.76792 | I27: =IF(ISERROR((G27/F27)-1),"",(G27/F27)-1) -> 0.090100713 | J27: =INDIRECT(ADDRESS(MATCH(B27,Calculations!B:B,0),11,1,1,"Calculations")) -> 28.502234 | K27: 22.69202 | L27: =IF(ISERROR(K27*Summary!$B$49),"",K27*Summary!$B$49) -> 544.60847 | M27: =IF(ISERROR(D27/L27),"",D27/L27) -> 3683.4942 | N27: =IF(ISERROR((C27+D27)/L27),"",(C27+D27)/L27) -> 7698.8738 | O27: =IF(ISERROR(N27*(1+$C$6)),"",N27*(1+$C$6)) -> 17916.839 | P27: =((2425.05+135)/15)+64.99 -> 235.66 | Q27: =IF(ISERROR(M27/P27),"",M27/P27) -> 15.630545 | R27: =IF(ISERROR(N27/P27),"",N27/P27) -> 32.669413 | S27: =IF(ISERROR(O27/P27),"",O27/P27) -> 76.028341 | U27: =IF(T27>0,Summary!$B$47/T27,IF(S27<Summary!$B$47,'Cost Factor'!S27/Summary!$B$47,1)) -> 1
B28: Athletic Training | C28: =INDIRECT(ADDRESS(MATCH(B28,Summary!A:A,0),7,1,1,"Summary")) -> 0 | E28: =INDIRECT(ADDRESS(MATCH(B28,Data!B:B,0),7,1,1,"Data")) -> 0 | F28: =IF(ISERROR(D28/E28),"",D28/E28) | G28: =IF(ISERROR((C28)/E28),"",(C28)/E28) | H28: =IF(ISERROR(G28*(1+$C$6)),"",G28*(1+$C$6)) | I28: =IF(ISERROR((G28/F28)-1),"",(G28/F28)-1) | J28: =INDIRECT(ADDRESS(MATCH(B28,Calculations!B:B,0),11,1,1,"Calculations")) -> 0 | K28: 0 | L28: =IF(ISERROR(K28*Summary!$B$49),"",K28*Summary!$B$49) -> 0 | M28: =IF(ISERROR(D28/L28),"",D28/L28) | N28: =IF(ISERROR((C28+D28)/L28),"",(C28+D28)/L28) | O28: =IF(ISERROR(N28*(1+$C$6)),"",N28*(1+$C$6)) | P28: =((2425.05+135)/15)+64.99 -> 235.66 | Q28: =IF(ISERROR(M28/P28),"",M28/P28) | R28: =IF(ISERROR(N28/P28),"",N28/P28) | S28: =IF(ISERROR(O28/P28),"",O28/P28) | U28: =IF(T28>0,Summary!$B$47/T28,IF(S28<Summary!$B$47,'Cost Factor'!S28/Summary!$B$47,1)) -> 1
B29: Physical Therapy | C29: =INDIRECT(ADDRESS(MATCH(B29,Summary!A:A,0),7,1,1,"Summary")) -> 1025417.9 | D29: 805494.07 | E29: =INDIRECT(ADDRESS(MATCH(B29,Data!B:B,0),7,1,1,"Data")) -> 586 | F29: =IF(ISERROR(D29/E29),"",D29/E29) -> 1374.5633 | G29: =IF(ISERROR((C29)/E29),"",(C29)/E29) -> 1749.8599 | H29: =IF(ISERROR(G29*(1+$C$6)),"",G29*(1+$C$6)) -> 4072.2784 | I29: =IF(ISERROR((G29/F29)-1),"",(G29/F29)-1) -> 0.27302972 | J29: =INDIRECT(ADDRESS(MATCH(B29,Calculations!B:B,0),11,1,1,"Calculations")) -> 2.5042735 | K29: 0 | L29: =IF(ISERROR(K29*Summary!$B$49),"",K29*Summary!$B$49) -> 0 | M29: =IF(ISERROR(D29/L29),"",D29/L29) | N29: =IF(ISERROR((C29+D29)/L29),"",(C29+D29)/L29) | O29: =IF(ISERROR(N29*(1+$C$6)),"",N29*(1+$C$6)) | P29: =((2425.05+135)/15)+64.99 -> 235.66 | Q29: =IF(ISERROR(M29/P29),"",M29/P29) | R29: =IF(ISERROR(N29/P29),"",N29/P29) | S29: =IF(ISERROR(O29/P29),"",O29/P29) | U29: =IF(T29>0,Summary!$B$47/T29,IF(S29<Summary!$B$47,'Cost Factor'!S29/Summary!$B$47,1)) -> 1
B30: Psychology, Sociology & Social Work | C30: =INDIRECT(ADDRESS(MATCH(B30,Summary!A:A,0),7,1,1,"Summary")) -> 1228952.8 | D30: 1074004.9 | E30: =INDIRECT(ADDRESS(MATCH(B30,Data!B:B,0),7,1,1,"Data")) -> 14960 | F30: =IF(ISERROR(D30/E30),"",D30/E30) -> 71.791771 | G30: =IF(ISERROR((C30)/E30),"",(C30)/E30) -> 82.149249 | H30: =IF(ISERROR(G30*(1+$C$6)),"",G30*(1+$C$6)) -> 191.17794 | I30: =IF(ISERROR((G30/F30)-1),"",(G30/F30)-1) -> 0.1442711 | J30: =INDIRECT(ADDRESS(MATCH(B30,Calculations!B:B,0),11,1,1,"Calculations")) -> 23.603924 | K30: 21.251964 | L30: =IF(ISERROR(K30*Summary!$B$49),"",K30*Summary!$B$49) -> 510.04715 | M30: =IF(ISERROR(D30/L30),"",D30/L30) -> 2105.6973 | N30: =IF(ISERROR((C30+D30)/L30),"",(C30+D30)/L30) -> 4515.1858 | O30: =IF(ISERROR(N30*(1+$C$6)),"",N30*(1+$C$6)) -> 10507.752 | P30: =((2425.05+135)/15)+64.99 -> 235.66 | Q30: =IF(ISERROR(M30/P30),"",M30/P30) -> 8.935319 | R30: =IF(ISERROR(N30/P30),"",N30/P30) -> 19.159746 | S30: =IF(ISERROR(O30/P30),"",O30/P30) -> 44.588611 | U30: =IF(T30>0,Summary!$B$47/T30,IF(S30<Summary!$B$47,'Cost Factor'!S30/Summary!$B$47,1)) -> 1
B31: Academic Affairs | C31: =INDIRECT(ADDRESS(MATCH(B31,Summary!A:A,0),7,1,1,"Summary")) -> 0 | D31: 60525 | E31: =INDIRECT(ADDRESS(MATCH(B31,Data!B:B,0),7,1,1,"Data")) -> 1658 | F31: =IF(ISERROR(D31/E31),"",D31/E31) -> 36.504825 | G31: =IF(ISERROR((C31)/E31),"",(C31)/E31) -> 0 | H31: =IF(ISERROR(G31*(1+$C$6)),"",G31*(1+$C$6)) -> 0 | I31: =IF(ISERROR((G31/F31)-1),"",(G31/F31)-1) -> -1 | J31: =INDIRECT(ADDRESS(MATCH(B31,Calculations!B:B,0),11,1,1,"Calculations")) -> 2.0934343 | K31: 2.6129032 | L31: =IF(ISERROR(K31*Summary!$B$49),"",K31*Summary!$B$49) -> 62.709677 | M31: =IF(ISERROR(D31/L31),"",D31/L31) -> 965.16204 | N31: =IF(ISERROR((C31+D31)/L31),"",(C31+D31)/L31) -> 965.16204 | O31: =IF(ISERROR(N31*(1+$C$6)),"",N31*(1+$C$6)) -> 2246.1276 | P31: =((2425.05+135)/15)+64.99 -> 235.66 | Q31: =IF(ISERROR(M31/P31),"",M31/P31) -> 4.09557 | R31: =IF(ISERROR(N31/P31),"",N31/P31) -> 4.09557 | S31: =IF(ISERROR(O31/P31),"",O31/P31) -> 9.5312211 | U31: 1
B33: Total | C33: =SUM(C10:C32) -> 18412640 | D33: =SUM(D10:D32) -> 18080602

Sheet Data
E3: Instructional SCH | H3: Lab SCH
E4: Undergrad | F4: Graduate | H4: Undergrad | I4: Graduate | M4: USTD 1101 is fee based course
B5: Budget Division | C5: 2009-10 Credits | D5: 2010-11 Credits | E5: 2011-12 SCH | F5: 2011-12 SCH | G5: total | H5: 2011-12 HC | I5: 2011-12 HC | K5: Total | M5: USTD 1201 is tuition based
A6: AG | B6: Agriculture | D6: 4578 | E6: =3689+2082+36+33 -> 5840 | F6: =370+27 -> 397 | G6: =E6+F6 -> 6237 | J6: =H6+I6 -> 0 | K6: =J6+G6 -> 6237
A7: AM | B7: Art & Music | D7: 7193 | E7: =1314+7125+45+399 -> 8883 | G7: =E7+F7 -> 8883 | J7: =H7+I7 -> 0 | K7: =J7+G7 -> 8883
A8: BIO | B8: Biology | D8: 10665 | E8: =2303+8708+149+704 -> 11864 | F8: =346+33 -> 379 | G8: =E8+F8 -> 12243 | J8: =H8+I8 -> 0 | K8: =J8+G8 -> 12243
A9: BCHM | B9: Chemistry & Biochemistry | D9: 4606 | E9: =1284+4237+4+248 -> 5773 | F9: 6 | G9: =E9+F9 -> 5779 | J9: =H9+I9 -> 0 | K9: =J9+G9 -> 5779
A10: CMMT | B10: Communication, Mass Media, & Theatre | D10: 9749 | E10: =2952+6914+802+293 -> 10961 | F10: =90+309 -> 399 | G10: =E10+F10 -> 11360 | J10: =H10+I10 -> 0 | K10: =J10+G10 -> 11360
A11: EML | B11: English & Modern Langagues | D11: =1050+12645+3579 -> 17274 | E11: =3000+13473+279+717+108+474 -> 18051 | F11: =219+33 -> 252 | G11: =E11+F11 -> 18303 | J11: =H11+I11 -> 0 | K11: =J11+G11 -> 18303
A12: POLS | B12: Pol Science | D12: 10161 | E12: =507+2925+348+738 -> 4518 | F12: =3+6 -> 9 | G12: =E12+F12 -> 4527 | J12: =H12+I12 -> 0 | K12: =J12+G12 -> 4527
A13: HIP | B13: History | D13: 9732 | E13: =834+3798+1356+6705+147+468 -> 13308 | F13: =54+51 -> 105 | G13: =E13+F13 -> 13413 | J13: =H13+I13 -> 0 | K13: =J13+G13 -> 13413
A14: MCS | B14: Mathematics & Computer Science | D14: =2733+14459 -> 17192 | E14: =58+123+2285+14399+66+863 -> 17794 | G14: =E14+F14 -> 17794 | J14: =H14+I14 -> 0 | K14: =J14+G14 -> 17794
A15: PHYS | B15: Physics | D15: =260+7352 -> 7612 | E15: =1693+5737+255+176+332 -> 8193 | G15: =E15+F15 -> 8193 | J15: =H15+I15 -> 0 | K15: =J15+G15 -> 8193
A16: AEF | B16: Accounting, Economics, & Finance | D16: 8826 | E16: =2778+5022+339+627 -> 8766 | F16: =428+33 -> 461 | G16: =E16+F16 -> 9227 | J16: =H16+I16 -> 0 | K16: =J16+G16 -> 9227
A17: AS | B17: Aerospace Studies | D17: 514 | E17: =199+354 -> 553 | G17: =E17+F17 -> 553 | J17: =H17+I17 -> 0 | K17: =J17+G17 -> 553
A18: MM | B18: Management & marketing | D18: 7130 | E18: =4806+1497+1396+108 -> 7807 | F18: =273+509 -> 782 | G18: =E18+F18 -> 8589 | J18: =H18+I18 -> 0 | K18: =J18+G18 -> 8589
A19: SSCJ | B19: Security Studies & Criminal Justice | E19: =2369+1491 -> 3860 | F19: 459 | G19: =E19+F19 -> 4319 | J19: =H19+I19 -> 0 | K19: =J19+G19 -> 4319
A20: ED | B20: Teacher Education | D20: 7017 | E20: =5388+1488+354+63 -> 7293 | F20: =372+384 -> 756 | G20: =E20+F20 -> 8049 | J20: =H20+I20 -> 0 | K20: =J20+G20 -> 8049
A21: CI | B21: Curriculum & Instruction | D21: 5412 | E21: =1050+501+60 -> 1611 | F21: =4017+2022 -> 6039 | G21: =E21+F21 -> 7650 | J21: =H21+I21 -> 0 | K21: =J21+G21 -> 7650
A22: KIN | B22: Kinesiology | D22: 6400 | E22: =2745+2642+384+75 -> 5846 | F22: =465+174 -> 639 | G22: =E22+F22 -> 6485 | J22: =H22+I22 -> 0 | K22: =J22+G22 -> 6485
A23: NRS | B23: Nursing | D23: 10078 | E23: =3745+6410+662+1102 -> 11919 | F23: =1245+1590+313 -> 3148 | G23: =E23+F23 -> 15067 | J23: =H23+I23 -> 0 | K23: =J23+G23 -> 15067
B24: Athletic Training | G24: =E24+F24 -> 0 | J24: =H24+I24 -> 0 | K24: =J24+G24 -> 0
B25: Physical Therapy | D25: 1101 | F25: 586 | G25: =E25+F25 -> 586 | J25: =H25+I25 -> 0 | K25: =J25+G25 -> 586
A26: PSS | B26: Psychology, Sociology & Social Work | D26: 13689 | E26: =6074+6147+831+342 -> 13394 | F26: =1407+159 -> 1566 | G26: =E26+F26 -> 14960 | J26: =H26+I26 -> 0 | K26: =J26+G26 -> 14960
A27: HONR/USTD | B27: Academic Affairs | D27: =270+1152 -> 1422 | E27: =155+213+25+57+1208 -> 1658 | G27: =E27+F27 -> 1658 | J27: =H27+I27 -> 0 | K27: =J27+G27 -> 1658
B29: Total Credits | C29: =SUM(C6:C27) -> 0 | D29: =SUM(D6:D27) -> 160351 | F29: =SUM(F6:F28) -> 15983 | G29: =SUM(G6:G28) -> 183875 | H29: =SUM(H6:H28) -> 0 | K29: =SUM(K6:K28) -> 183875 | M29: =155274+18366 -> 173640

Sheet Notes
B1: Concerns/Questions | C1: Action/Answer
A2: 1 | B2: Lab hours for Biology seem to be too low | C2: Jeff reran several reports. It appears that some classes offered in Biology combine classroom instruction with a lab making it a 4 hours course. Will discuss in Budget Task Force Group. 4/5 - will do cost factor for heavy lab dependent departments
A3: 2 | B3: Total Expense appears to be lower than total faculty salaries for English Modern Languages | C3: Expense for Modern Languages was downloaded as 'Modern Langauages', corrected to read 'English & Modern Languages' which corrected the problem.
A4: 3 | B4: Should the Writing Center costs be included in English & Modern Languages | C4: Will look at moving these expenses to IE funds. Will also investigate moving Math labs to IE funds.
A5: 4 | B5: Correct Separation of History/Criminal Justice/Security Studies | C5: Done
A6: 5 | B6: No hours for Athletic Training | C6: This will have to be separated by Department Heads. Courses were coded as Kinesiology in FY11
A7: 6 | B7: No hours for Physical Therapy | C7: Courses are coded as NRS
A8: 7 | B8: Instructional Hours on Cost Factor were not correct | C8: Adjusted Cost Factor Tab to calculate from column J not K (cut and pasted J to avoid circular reference)
A9: 8 | B9: Position report downloaded 3/29/12

Sheet Revenue
A1: COA Code | B1: Fund Code | C1: Fund Description | D1: Organization Code | E1: Organization Description | F1: Account Code | G1: Account Description | H1: FY11 Actual | I1: FY12 Budget | J1: FY13 Estimated
A2: A | B2: 0010 | C2: Educational and General | D2: 00010 | E2: Est Income Educ & General | F2: 5010 | G2: Legislative Appropriations | H2: =22470551.85-4388426.85 -> 18082125 | I2: =22921535-3900393-1000000 -> 18021142 | J2: =22939802-3900392-1000000 -> 18039410 | K2: =+J2-I2 -> 18268
A3: A | B3: 0010 | C3: Educational and General | D3: 00010 | E3: Est Income Educ & General | F3: 5016 | G3: Appropriations Supplement Gen Rev | H3: 6000 | I3: 0
A4: A | B4: 0010 | C4: Educational and General | D4: 00010 | E4: Est Income Educ & General | F4: 5050 | G4: Tuition - Fall Semester | H4: 4218937.9 | I4: 4253625 | J4: 4285356 | K4: =+J4-I4 -> 31731
A5: A | B5: 0010 | C5: Educational and General | D5: 00010 | E5: Est Income Educ & General | F5: 5052 | G5: Tuition - Spring Semester | H5: 3762017.4 | I5: 3835725 | J5: 3820089 | K5: =+J5-I5 -> -15636
A6: A | B6: 0010 | C6: Educational and General | D6: 00010 | E6: Est Income Educ & General | F6: 5054 | G6: Tuition - I Summer Semester | H6: 539685 | I6: 487550 | J6: 514243
A7: A | B7: 0010 | C7: Educational and General | D7: 00010 | E7: Est Income Educ & General | F7: 5056 | G7: Tuition - II Summer Semester | H7: 381680 | I7: 378100 | J7: 367316
A8: A | B8: 0010 | C8: Educational and General | D8: 00010 | E8: Est Income Educ & General | F8: 5058 | G8: Tuition Rebate Section 54.0065 | H8: -10000 | I8: -15000 | J8: -15000 | K8: =+J8-I8 -> 0
A9: A | B9: 0010 | C9: Educational and General | D9: 00010 | E9: Est Income Educ & General | F9: 5060 | G9: Transfer TPEG | H9: -1296198.5 | I9: =-1253700-8955 -> -1262655 | J9: -1293028 | K9: =+J9-I9 -> -30373
A10: A | B10: 0010 | C10: Educational and General | D10: 00010 | E10: Est Income Educ & General | F10: 5066 | G10: Grad Tuition - Fall Semester | H10: 189477 | I10: 192533 | J10: 232830 | K10: =+J10-I10 -> 40297
A11: A | B11: 0010 | C11: Educational and General | D11: 00010 | E11: Est Income Educ & General | F11: 5068 | G11: Grad Tuition - Spring Semester | H11: 194431.5 | I11: 170145 | J11: 176414 | K11: =+J11-I11 -> 6269
A12: A | B12: 0010 | C12: Educational and General | D12: 00010 | E12: Est Income Educ & General | F12: 5070 | G12: Grad Tuition - I Summer Semester | H12: 87363 | I12: 107460 | J12: 85073
A13: A | B13: 0010 | C13: Educational and General | D13: 00010 | E13: Est Income Educ & General | F13: 5072 | G13: Grad Tuition - II Summer Semester | H13: 69876 | I13: 62685 | J13: 67163
A14: A | B14: 0010 | C14: Educational and General | D14: 00010 | E14: Est Income Educ & General | F14: 5075 | G14: Doctoral Tuition - Fall Semester | H14: 22950 | I14: 22000 | J14: 39800 | K14: =+J14-I14 -> 17800
A15: A | B15: 0010 | C15: Educational and General | D15: 00010 | E15: Est Income Educ & General | F15: 5076 | G15: Doctoral Tuition - Spring Semester | H15: 24900 | I15: 24000 | J15: 37810 | K15: =+J15-I15 -> 13810
A16: A | B16: 0010 | C16: Educational and General | D16: 00010 | E16: Est Income Educ & General | F16: 5077 | G16: Doctoral Tuition-I Summer Semester | H16: 29300 | I16: 19700 | J16: 29850
A17: A | B17: 0010 | C17: Educational and General | D17: 00010 | E17: Est Income Educ & General | F17: 5078 | G17: Doctoral Tuition-II Summer Semester | H17: 0 | I17: 19700 | J17: 0 | K17: =+J17-I17 -> -19700
A18: A | B18: 0010 | C18: Educational and General | D18: 00010 | E18: Est Income Educ & General | F18: 5863 | G18: Dep Int-Local Funds State Treasury | H18: 41727.62 | I18: 50000 | J18: 30000 | K18: =+J18-I18 -> -20000
A19: A | B19: 0010 | C19: Educational and General | D19: 00010 | E19: Est Income Educ & General | F19: 5970 | G19: Miscellaneous Income | H19: 474.64 | I19: 1000 | J19: 1000 | K19: =+J19-I19 -> 0
A20: A | B20: 0018 | C20: E&G Institutional Enhancement | D20: 00018 | E20: Est Income E&G Inst Enhancement | F20: 5010 | G20: Legislative Appropriations | H20: 5514319 | I20: 3900393 | J20: 3900392 | K20: =+J20-I20 -> -1
A21: A | B21: 0019 | C21: E&G Institutional Enhancement | D21: 00019 | E21: Est Income E&G Inst Enhancement | F21: 5010 | G21: Legislative Appropriations | I21: 1000000 | J21: 1000000 | K21: =+J21-I21 -> 0
A22: A | B22: 0100 | C22: Designated Tuition Fee | D22: 00100 | E22: Est Income Designated Tuition Fee | F22: 5127 | G22: Designated Tuition - Fall | H22: 8347921 | I22: 9500046 | J22: 9784320 | K22: =+J22-I22 -> 284274
A23: A | B23: 0100 | C23: Designated Tuition Fee | D23: 00100 | E23: Est Income Designated Tuition Fee | F23: 5128 | G23: Designated Tuition - Spring | H23: 7448742.7 | I23: 8566708 | J23: 8722022 | K23: =+J23-I23 -> 155314
A24: A | B24: 0100 | D24: 00100 | F24: 5129 | G24: Designated Tuition - I Summer (set-aside) | H24: =1057376.04*0.4 -> 422950.42 | I24: =1088894 -> 1088894 | J24: =1174118 -> 1174118 | K24: =+J24-I24 -> 85224
A25: A | B25: 0100 | D25: 00100 | F25: 5130 | G25: Designated Tuition - II Summer (set-aside) | H25: =745865.26*0.4 -> 298346.1 | I25: =844449 -> 844449 | J25: =838656 -> 838656 | K25: =+J25-I25 -> -5793
A26: A | B26: 0100 | C26: Designated Tuition Fee | D26: 00100 | E26: Est Income Designated Tuition Fee | F26: 5132 | G26: Transfer B on Time Set Aside | H26: -443903.94 | I26: -551956 | J26: -594851 | K26: =+J26-I26 -> -42895
A27: A | B27: 0100 | C27: Designated Tuition Fee | D27: 00100 | E27: Est Income Designated Tuition Fee | F27: 5134 | G27: Transfer Ram Fin Aid Set Aside | H27: -1443881.4 | I27: -1773090 | J27: -1939962 | K27: =+J27-I27 -> -166872
A28: A | B28: 0100 | C28: Designated Tuition Fee | D28: 00100 | E28: Est Income Designated Tuition Fee | F28: 5450 | G28: Endowment Income | H28: 97046.05 | I28: 96400 | J28: 96400 | K28: =+J28-I28 -> 0
A29: A | B29: 0100 | C29: Designated Tuition Fee | D29: 00100 | E29: Est Income Designated Tuition Fee | F29: 5506 | G29: Special Events Merchandise Sales | H29: 729.4 | I29: 500 | J29: 500 | K29: =+J29-I29 -> 0
A30: A | B30: 0100 | C30: Designated Tuition Fee | D30: 00100 | E30: Est Income Designated Tuition Fee | F30: 5507 | G30: Mail Services-Resale | H30: 648.62 | I30: 500 | J30: 500 | K30: =+J30-I30 -> 0
A31: A | B31: 0100 | C31: Designated Tuition Fee | D31: 00100 | E31: Est Income Designated Tuition Fee | F31: 5508 | G31: Mail Services-Postage Sales | H31: 13752.06 | I31: 10000 | J31: 10000 | K31: =+J31-I31 -> 0
A32: A | B32: 0100 | C32: Designated Tuition Fee | D32: 00100 | E32: Est Income Designated Tuition Fee | F32: 5515 | G32: Dinner Theatre | H32: 27433.5 | I32: 28000 | J32: 28000 | K32: =+J32-I32 -> 0
A33: A | B33: 0100 | C33: Designated Tuition Fee | D33: 00100 | E33: Est Income Designated Tuition Fee | F33: 5535 | G33: Ticket Fees | H33: 20279.91 | I33: 10000 | J33: 10000 | K33: =+J33-I33 -> 0
A34: A | B34: 0100 | C34: Designated Tuition Fee | D34: 00100 | E34: Est Income Designated Tuition Fee | F34: 5539 | G34: Junell Center | H34: 72650.1 | I34: 40000 | J34: 40000 | K34: =+J34-I34 -> 0
A35: A | B35: 0100 | C35: Designated Tuition Fee | D35: 00100 | E35: Est Income Designated Tuition Fee | F35: 5540 | G35: Higher One Commission | H35: 13607.46 | I35: 10000 | J35: 12000 | K35: =+J35-I35 -> 2000
A36: A | B36: 0100 | C36: Designated Tuition Fee | D36: 00100 | E36: Est Income Designated Tuition Fee | F36: 5541 | G36: OneCard Replacement Fee | H36: 8505 | I36: 11850 | J36: 8500 | K36: =+J36-I36 -> -3350
A37: A | B37: 0100 | C37: Designated Tuition Fee | D37: 00100 | E37: Est Income Designated Tuition Fee | F37: 5542 | G37: RamBucks | H37: 30904.12 | I37: 35000 | J37: 35000 | K37: =+J37-I37 -> 0
... A40: A | B40: 0100 | C40: Designated Tuition Fee | D40: 00100 | E40: Est Income Designated Tuition Fee | F40: 5869 | G40: Depository Bank Earnings Credit | H40: 2850.28 | I40: 5000 | J40: 1000 | K40: =+J40-I40 -> -4000
A41: A | B41: 0100 | C41: Designated Tuition Fee | D41: 00100 | E41: Est Income Designated Tuition Fee | F41: 5872 | G41: Indirect Costs Revenue | H41: 1256978 | I41: =1247285+175000 -> 1422285 | J41: 1422285 | K41: =+J41-I41 -> 0
A42: A | B42: 0100 | C42: Designated Tuition Fee | D42: 00100 | E42: Est Income Designated Tuition Fee | F42: 5877 | G42: Licensing Royalties | H42: 11201.63 | I42: 10000 | J42: 10000 | K42: =+J42-I42 -> 0
A43: A | B43: 0100 | C43: Designated Tuition Fee | D43: 00100 | E43: Est Income Designated Tuition Fee | F43: 5878 | G43: Lease Revenue | H43: 16728.63 | I43: 15000 | J43: 15000 | K43: =+J43-I43 -> 0
A44: A | B44: 0100 | C44: Designated Tuition Fee | D44: 00100 | E44: Est Income Designated Tuition Fee | F44: 5884 | G44: Mail Services | H44: 102480.25 | I44: 100000 | J44: 100000 | K44: =+J44-I44 -> 0
A45: A | B45: 0100 | C45: Designated Tuition Fee | D45: 00100 | E45: Est Income Designated Tuition Fee | F45: 5935 | G45: Late Registration Fee | H45: 39600 | I45: 50000 | J45: 40000 | K45: =+J45-I45 -> -10000
A46: A | B46: 0100 | C46: Designated Tuition Fee | D46: 00100 | E46: Est Income Designated Tuition Fee | F46: 5970 | G46: Miscellaneous Income | H46: 12995.51 | I46: 0 | J46: 1000 | K46: =+J46-I46 -> 1000
A47: A | B47: 0100 | C47: Designated Tuition Fee | D47: 00100 | E47: Est Income Designated Tuition Fee | F47: 5971 | G47: Interest Income | H47: 9145.16 | I47: 10000 | J47: 5000 | K47: =+J47-I47 -> -5000
A48: A | B48: 0100 | C48: Designated Tuition Fee | D48: 00100 | E48: Est Income Designated Tuition Fee | F48: 5998 | G48: Non-Mandatory Transfer | H48: 211630.94 | I48: 2500 | J48: 2500 | K48: =+J48-I48 -> 0
A49: Less Line Items not transferrable
A50: A | B50: 0010 | D50: 00010 | F50: 5010 | G50: Tuition Revenue Bond Retirement | H50: -4129564 | I50: -4003574 | J50: -3962489 | K50: =+J50-I50 -> 41085
A51: A | B51: 0010 | G51: School-Based Clinic | H51: -46550 | I51: -34912 | J51: -34912 | K51: =+J51-I51 -> 0
G52: Center for Academic Excellence | H52: -415626 | I52: -311720 | J52: -311720 | K52: =+J52-I52 -> 0
G53: Small Business Development | H53: -134270 | I53: -134270 | J53: -134270 | K53: =+J53-I53 -> 0
G54: Center for Fine Arts | H54: -53426 | I54: -40070 | J54: -40070 | K54: =+J54-I54 -> 0
G55: MIR Center | H55: -245992 | I55: -184494 | J55: -184494 | K55: =+J55-I55 -> 0
G56: College of Nursing & Allied Health | I56: -1000000 | J56: -1000000 | K56: =+J56-I56 -> 0
G57: Research Development Fund | I57: -61588 | J57: -61588 | K57: =+J57-I57 -> 0
A58: A | B58: 0117 | D58: 00117 | F58: 5120 | H58: 0 | I58: 754110 | J58: 756000 | K58: =+J58-I58 -> 1890
A59: A | B59: 0117 | D59: 00117 | F59: 5122 | H59: 0 | I59: 680022 | J59: 673920 | K59: =+J59-I59 -> -6102
A60: A | B60: 0117 | D60: 00117 | F60: 5124 | H60: 0 | I60: 86436 | J60: 90720 | K60: =+J60-I60 -> 4284
A61: A | B61: 0117 | D61: 00117 | F61: 5126 | H61: 0 | I61: 67032 | J61: 64800 | K61: =+J61-I61 -> -2232
H62: =SUM(H1:H61) -> 43482822 | I62: =SUM(I1:I61) -> 46687161 | J62: =SUM(J2:J61) -> 47056603 | K62: =+J62-I62 -> 369442
A63: A | B63: 0010 | C63: Educational and General | D63: 00010 | E63: Est Income Educ & General | F63: 5019 | G63: Appropriations Supplement OASI | H63: 1417591.5 | I63: 2145716 | J63: 2073155
A64: A | B64: 0010 | C64: Educational and General | D64: 00010 | E64: Est Income Educ & General | F64: 5031 | G64: Appropriations Supplement ORP | H64: 767624.38 | I64: 1706595 | J64: 1729873
A65: A | B65: 0010 | C65: Educational and General | D65: 00010 | E65: Est Income Educ & General | F65: 5034 | G65: Appropriations Supplement TX Grants | H65: 4076314.5 | I65: 0
A66: A | B66: 0010 | C66: Educational and General | D66: 00010 | E66: Est Income Educ & General | F66: 5300 | G66: Valedictorian | H66: 30350 | J66: 39000
A67: A | B67: 0010 | C67: Educational and General | D67: 00010 | E67: Est Income Educ & General | F67: 5301 | G67: Texas Tomorrow Fund | H67: 172.56 | J67: 100
A68: A | B68: 0010 | C68: Educational and General | D68: 00010 | E68: Est Income Educ & General | F68: 5302 | G68: Veterans | H68: 191053.15 | J68: 125000
A69: A | B69: 0010 | C69: Educational and General | D69: 00010 | E69: Est Income Educ & General | F69: 5304 | G69: Reciprocal Education Exchange | H69: 54050 | J69: 40000
A70: A | B70: 0010 | C70: Educational and General | D70: 00010 | E70: Est Income Educ & General | F70: 5306 | G70: Blind and Deaf | H70: 15385 | J70: 14000
A71: A | B71: 0010 | C71: Educational and General | D71: 00010 | E71: Est Income Educ & General | F71: 5312 | G71: Sr. Citizens | H71: 3162.5 | J71: 3000
A72: A | B72: 0010 | C72: Educational and General | D72: 00010 | E72: Est Income Educ & General | F72: 5314 | G72: Child of Disabled Firemen | H72: 1250 | J72: 2400
A73: A | B73: 0010 | C73: Educational and General | D73: 00010 | E73: Est Income Educ & General | F73: 5319 | G73: Clinical Preceptors | H73: 3450 | J73: 3000
A74: A | B74: 0010 | C74: Educational and General | D74: 00010 | E74: Est Income Educ & General | F74: 5320 | G74: Child of Prof. Nursing Fac/Staff | H74: 7550 | J74: 3000 | K74: =SUM(J66:J74) -> 229500
A75: A | B75: 0010 | C75: Educational and General | D75: 00010 | E75: Est Income Educ & General | F75: 5500 | G75: Ranch Sales | H75: 190966.3 | I75: 120000 | J75: 120000
A76: A | B76: 0012 | C76: E&G Incentive Performance Funding | D76: 00012 | E76: Est Income Incentive Performance Fd | F76: 5351 | G76: Federal Grant Funds (Stimulus) | H76: 294435.8 | I76: 0 | J76: 0
A77: A | B77: 0015 | C77: E&G Nursing and Allied Health ARRA | D77: 00015 | E77: Est Income Nursing Allied Hlth ARRA | F77: 5016 | G77: Appropriations Supplement Gen Rev | H77: 1000000
A78: A | B78: 0015 | C78: E&G Nursing and Allied Health ARRA | D78: 00015 | E78: Est Income Nursing Allied Hlth ARRA | F78: 5351 | G78: Federal Grant Funds (Stimulus) | H78: 1257288.1 | I78: 0 | J78: 0
H79: =SUM(H63:H78) -> 9310643.8 | I79: =SUM(I63:I78) -> 3972311 | J79: =SUM(J63:J78) -> 4152528
A80: A | B80: 0010 | D80: 00010 | F80: 5010 | G80: Tuition Revenue Bond Retirement | H80: =-H50 -> 4129564 | I80: =-I50 -> 4003574 | J80: =-J50 -> 3962489
A81: A | B81: 0010 | G81: School-Based Clinic | H81: =-H51 -> 46550 | I81: =-I51 -> 34912 | J81: =-J51 -> 34912
G82: Center for Academic Excellence | H82: =-H52 -> 415626 | I82: =-I52 -> 311720 | J82: =-J52 -> 311720
G83: Small Business Development | H83: =-H53 -> 134270 | I83: =-I53 -> 134270 | J83: =-J53 -> 134270
G84: Center for Fine Arts | H84: =-H54 -> 53426 | I84: =-I54 -> 40070 | J84: =-J54 -> 40070
G85: MIR Center | H85: =-H55 -> 245992 | I85: =-I55 -> 184494 | J85: =-J55 -> 184494
G86: College of Nursing & Allied Health | H86: =-H56 -> 0 | I86: =-I56 -> 1000000 | J86: =-J56 -> 1000000
G87: Research Development Fund | H87: =-H57 -> 0 | I87: =-I57 -> 61588 | J87: =-J57 -> 61588
G88: Total Non-Transferrable E&G Funds | H88: =SUM(H80:H87) -> 5025428 | I88: =SUM(I80:I87) -> 5770628 | J88: =SUM(J80:J87) -> 5729543
G89: Total Revenue | H89: =+H62+H79+H88 -> 57818894 | I89: =+I62+I79+I88 -> 56430100 | J89: =+J62+J79+J88 -> 56938674
I91: 35240414
I92: 19602086
I93: 1587600
H94: =SUM(H91:H93) -> 0 | I94: =SUM(I91:I93) -> 56430100 | J94: =SUM(J91:J93) -> 0
H96: =+H94-H89 -> -57818894 | I96: =+I94-I89 -> 0 | J96: =+J94-J89 -> -56938674

Sheet position by div
A1: ACCT | B1: (Multiple Items)
A2: PROG | B2: (Multiple Items)
A3: ORGN | B3: (Multiple Items)
A5: Row Labels | B5: Sum of Distribution Budget
A6: 1 | B6: 1015869
A7: 2 | B7: 3900785
A8: 3 | B8: 3762774
A9: 5 | B9: 1895281
A10: 6 | B10: 427804
A11: (blank)
A12: Grand Total | B12: 11002513

Sheet position report
A1: Position Number | B1: FUND | C1: ORGN | D1: DEPT | E1: Div | F1: ORGN Desc | G1: ACCT | H1: PROG | I1: PROG Desc | J1: ACTV | K1: ACTV Desc | L1: Salary Budget | M1: Distribution Budget | N1: Distribution Percent
A2: 999948 | B2: 0010 | C2: 32100 | D2: 1050 | E2: =LEFT(D2,1) -> 1 | F2: Office of the President | G2: 7010 | H2: 6010 | I2: General Administration | J2: 110311 | K2: Departmental Operating Expense | L2: 242046 | M2: 65945 | N2: 27.24
A3: 999743 | B3: 0010 | C3: 33100 | D3: 1400 | E3: =LEFT(D3,1) -> 1 | F3: Communications and Marketing | G3: 7010 | H3: 6020 | I3: General Institutional | J3: 110311 | K3: Departmental Operating Expense | L3: 45000 | M3: 3127 | N3: 6.95
A4: 999454 | B4: 0010 | C4: 33100 | D4: 1400 | E4: =LEFT(D4,1) -> 1 | F4: Communications and Marketing | G4: 7010 | H4: 6020 | I4: General Institutional | J4: 110311 | K4: Departmental Operating Expense | L4: 43649 | M4: 12155 | N4: 27.85
A5: 999877 | B5: 0010 | C5: 33100 | D5: 1400 | E5: =LEFT(D5,1) -> 1 | F5: Communications and Marketing | G5: 7015 | H5: 6020 | I5: General Institutional | J5: 110311 | K5: Departmental Operating Expense | L5: 29117 | M5: 29117 | N5: 100
A6: 998915 | B6: 0010 | C6: 33100 | D6: 1400 | E6: =LEFT(D6,1) -> 1 | F6: Communications and Marketing | G6: 7010 | H6: 6020 | I6: General Institutional | J6: 110311 | K6: Departmental Operating Expense | L6: 39500 | M6: 39500 | N6: 100
A7: 998933 | B7: 0010 | C7: 33100 | D7: 1400 | E7: =LEFT(D7,1) -> 1 | F7: Communications and Marketing | G7: 7010 | H7: 6020 | I7: General Institutional | J7: 110311 | K7: Departmental Operating Expense | L7: 39780 | M7: 39780 | N7: 100
A8: 999180 | B8: 0010 | C8: 33100 | D8: 1400 | E8: =LEFT(D8,1) -> 1 | F8: Communications and Marketing | G8: 7010 | H8: 6020 | I8: General Institutional | J8: 110311 | K8: Departmental Operating Expense | L8: 42799 | M8: 42799 | N8: 100
A9: 999878 | B9: 0010 | C9: 33290 | D9: 3110 | E9: =LEFT(D9,1) -> 3 | F9: Budget and Payroll Services | G9: 7015 | H9: 6020 | I9: General Institutional | J9: 110311 | K9: Departmental Operating Expense | L9: 26000 | M9: 26000 | N9: 100
A10: 999004 | B10: 0010 | C10: 33290 | D10: 3110 | E10: =LEFT(D10,1) -> 3 | F10: Budget and Payroll Services | G10: 7015 | H10: 6020 | I10: General Institutional | J10: 110311 | K10: Departmental Operating Expense | L10: 28000 | M10: 28000 | N10: 100
A11: 999726 | B11: 0010 | C11: 33290 | D11: 3110 | E11: =LEFT(D11,1) -> 3 | F11: Budget and Payroll Services | G11: 7010 | H11: 6020 | I11: General Institutional | J11: 110311 | K11: Departmental Operating Expense | L11: 39776 | M11: 39776 | N11: 100
A12: 999856 | B12: 0010 | C12: 33290 | D12: 3110 | E12: =LEFT(D12,1) -> 3 | F12: Budget and Payroll Services | G12: 7010 | H12: 6020 | I12: General Institutional | J12: 110311 | K12: Departmental Operating Expense | L12: 40000 | M12: 40000 | N12: 100
A13: 999997 | B13: 0010 | C13: 33300 | D13: 3300 | E13: =LEFT(D13,1) -> 3 | F13: Controller's Office | G13: 7015 | H13: 6020 | I13: General Institutional | J13: 110311 | K13: Departmental Operating Expense | L13: 20680 | M13: 20680 | N13: 100
... A444: 999216 | B444: 0018 | C444: 40295 | D444: 2860 | E444: =LEFT(D444,1) -> 2 | F444: Psychology, Sociology & Social Work | G444: 7008 | H444: 1035 | I444: Health and Human Services | J444: 159111 | K444: Institutional Enhancement | L444: 85565 | M444: 85565 | N444: 100
A445: 999836 | B445: 0018 | C445: 40340 | D445: 3810 | E445: =LEFT(D445,1) -> 3 | F445: Information Technology | G445: 7010 | H445: 1040 | I445: Other Instructional & Departmental | J445: 159111 | K445: Institutional Enhancement | L445: 39132 | M445: 3287 | N445: 8.4
A446: 999835 | B446: 0018 | C446: 40340 | D446: 3810 | E446: =LEFT(D446,1) -> 3 | F446: Information Technology | G446: 7010 | H446: 1040 | I446: Other Instructional & Departmental | J446: 159111 | K446: Institutional Enhancement | L446: 46000 | M446: 13928 | N446: 30.28
A447: 999805 | B447: 0018 | C447: 40340 | D447: 3810 | E447: =LEFT(D447,1) -> 3 | F447: Information Technology | G447: 7010 | H447: 1040 | I447: Other Instructional & Departmental | J447: 159111 | K447: Institutional Enhancement | L447: 99554 | M447: 22529 | N447: 22.63
A448: 999826 | B448: 0018 | C448: 40340 | D448: 3810 | E448: =LEFT(D448,1) -> 3 | F448: Information Technology | G448: 7010 | H448: 1040 | I448: Other Instructional & Departmental | J448: 159111 | K448: Institutional Enhancement | L448: 52000 | M448: 24782 | N448: 47.66
A449: 999823 | B449: 0018 | C449: 40340 | D449: 3810 | E449: =LEFT(D449,1) -> 3 | F449: Information Technology | G449: 7010 | H449: 1040 | I449: Other Instructional & Departmental | J449: 159111 | K449: Institutional Enhancement | L449: 66763 | M449: 27173 | N449: 40.7
A450: 999832 | B450: 0018 | C450: 40340 | D450: 3810 | E450: =LEFT(D450,1) -> 3 | F450: Information Technology | G450: 7010 | H450: 1040 | I450: Other Instructional & Departmental | J450: 159111 | K450: Institutional Enhancement | L450: 43099 | M450: 34479 | N450: 80
A451: 999816 | B451: 0018 | C451: 40340 | D451: 3810 | E451: =LEFT(D451,1) -> 3 | F451: Information Technology | G451: 7010 | H451: 1040 | I451: Other Instructional & Departmental | J451: 159111 | K451: Institutional Enhancement | L451: 47390 | M451: 39334 | N451: 83
A452: 999819 | B452: 0018 | C452: 40340 | D452: 3810 | E452: =LEFT(D452,1) -> 3 | F452: Information Technology | G452: 7010 | H452: 1040 | I452: Other Instructional & Departmental | J452: 159111 | K452: Institutional Enhancement | L452: 40000 | M452: 40000 | N452: 100
A453: 998878 | B453: 0018 | C453: 40340 | D453: 3810 | E453: =LEFT(D453,1) -> 3 | F453: Information Technology | G453: 7010 | H453: 1040 | I453: Other Instructional & Departmental | J453: 159111 | K453: Institutional Enhancement | L453: 74000 | M453: 41581 | N453: 56.19
A454: 999828 | B454: 0018 | C454: 40340 | D454: 3810 | E454: =LEFT(D454,1) -> 3 | F454: Information Technology | G454: 7010 | H454: 1040 | I454: Other Instructional & Departmental | J454: 159111 | K454: Institutional Enhancement | L454: 47270 | M454: 43961 | N454: 93
A455: 999160 | B455: 0018 | C455: 40340 | D455: 3810 | E455: =LEFT(D455,1) -> 3 | F455: Information Technology | G455: 7010 | H455: 1040 | I455: Other Instructional & Departmental | J455: 159111 | K455: Institutional Enhancement | L455: 74000 | M455: 51023 | N455: 68.95
A456: 999820 | B456: 0018 | C456: 40340 | D456: 3810 | E456: =LEFT(D456,1) -> 3 | F456: Information Technology | G456: 7010 | H456: 1040 | I456: Other Instructional & Departmental | J456: 159111 | K456: Institutional Enhancement | L456: 56000 | M456: 51643 | N456: 92.22
... A459: 999810 | B459: 0018 | C459: 40340 | D459: 3810 | E459: =LEFT(D459,1) -> 3 | F459: Information Technology | G459: 7010 | H459: 1040 | I459: Other Instructional & Departmental | J459: 159111 | K459: Institutional Enhancement | L459: 73058 | M459: 73058 | N459: 100
A460: 999239 | B460: 0018 | C460: 40480 | D460: 2475 | E460: =LEFT(D460,1) -> 2 | F460: Planetarium | G460: 7010 | H460: 1040 | I460: Other Instructional & Departmental | J460: 159111 | K460: Institutional Enhancement | L460: 74783 | M460: 18696 | N460: 25
A461: 999725 | B461: 0018 | C461: 41300 | D461: 5210 | E461: =LEFT(D461,1) -> 5 | F461: Maintenance Scholastic & Adm Stdrds | G461: 7010 | H461: 4010 | I461: Academic Administration | J461: 159111 | K461: Institutional Enhancement | L461: 35411 | M461: 35411 | N461: 100
A462: 999120 | B462: 0018 | C462: 45000 | D462: 2910 | E462: =LEFT(D462,1) -> 2 | F462: Research Enhancement Reserve | G462: 7010 | H462: 2010 | I462: Research | J462: 159111 | K462: Institutional Enhancement | L462: 90917 | M462: 90917 | N462: 100
A463: 999217 | B463: 0019 | C463: 40285 | D463: 2810 | E463: =LEFT(D463,1) -> 2 | F463: Nursing | G463: 7008 | H463: 1035 | I463: Health and Human Services | J463: 110413 | K463: Stimulus Formula Funding | L463: 106221 | M463: 13662 | N463: 12.86
A464: 999731 | B464: 0019 | C464: 40285 | D464: 2810 | E464: =LEFT(D464,1) -> 2 | F464: Nursing | G464: 7010 | H464: 1035 | I464: Health and Human Services | J464: 110413 | K464: Stimulus Formula Funding | L464: 32428 | M464: 32428 | N464: 100
A465: 998808 | B465: 0019 | C465: 40285 | D465: 2810 | E465: =LEFT(D465,1) -> 2 | F465: Nursing | G465: 7008 | H465: 1035 | I465: Health and Human Services | J465: 110413 | K465: Stimulus Formula Funding | L465: 39068 | M465: 39068 | N465: 100
A466: 998616 | B466: 0019 | C466: 40285 | D466: 2810 | E466: =LEFT(D466,1) -> 2 | F466: Nursing | G466: 7008 | H466: 1035 | I466: Health and Human Services | J466: 110413 | K466: Stimulus Formula Funding | L466: 48953 | M466: 48953 | N466: 100
A467: 999339 | B467: 0019 | C467: 40285 | D467: 2810 | E467: =LEFT(D467,1) -> 2 | F467: Nursing | G467: 7008 | H467: 1035 | I467: Health and Human Services | J467: 110413 | K467: Stimulus Formula Funding | L467: 51817 | M467: 51817 | N467: 100
A468: 998404 | B468: 0019 | C468: 40290 | D468: 2820 | E468: =LEFT(D468,1) -> 2 | F468: Physical Therapy | G468: 7008 | H468: 1035 | I468: Health and Human Services | J468: 110413 | K468: Stimulus Formula Funding | L468: 101673 | M468: 13662 | N468: 13.44
A469: 998779 | B469: 0019 | C469: 40295 | D469: 2860 | E469: =LEFT(D469,1) -> 2 | F469: Psychology, Sociology & Social Work | G469: 7008 | H469: 1035 | I469: Health and Human Services | J469: 110413 | K469: Stimulus Formula Funding | L469: 56817 | M469: 5000 | N469: 8.8
A470: 998581 | B470: 0019 | C470: 41120 | D470: 2800 | E470: =LEFT(D470,1) -> 2 | F470: College Health and Human Services | G470: 7015 | H470: 4010 | I470: Academic Administration | J470: 110413 | K470: Stimulus Formula Funding | L470: 23086 | M470: 1099 | N470: 4.76
A471: 998618 | B471: 0019 | C471: 41120 | D471: 2800 | E471: =LEFT(D471,1) -> 2 | F471: College Health and Human Services | G471: 7015 | H471: 4010 | I471: Academic Administration | J471: 110413 | K471: Stimulus Formula Funding | L471: 23086 | M471: 1099 | N471: 4.76
... A500: 998908 | B500: 0100 | C500: 60080 | D500: 6050 | E500: =LEFT(D500,1) -> 6 | F500: Office VP for Development | G500: 7010 | H500: 6010 | I500: General Administration | J500: DES | K500: Designated Funds | L500: 38000 | M500: 38000 | N500: 100
A501: 998659 | B501: 0100 | C501: 60080 | D501: 6200 | E501: =LEFT(D501,1) -> 6 | F501: Office VP for Development | G501: 7010 | H501: 6010 | I501: General Administration | J501: DES | K501: Designated Funds | L501: 52500 | M501: 52500 | N501: 100
A502: 998784 | B502: 0100 | C502: 60080 | D502: 6050 | E502: =LEFT(D502,1) -> 6 | F502: Office VP for Development | G502: 7010 | H502: 6010 | I502: General Administration | J502: DES | K502: Designated Funds | L502: 60000 | M502: 60000 | N502: 100
A503: 999705 | B503: 0100 | C503: 60080 | D503: 6050 | E503: =LEFT(D503,1) -> 6 | F503: Office VP for Development | G503: 7010 | H503: 6010 | I503: General Administration | J503: DES | K503: Designated Funds | L503: 120000 | M503: 120000 | N503: 100
A504: 999851 | B504: 0100 | C504: 60092 | D504: 5050 | E504: =LEFT(D504,1) -> 5 | F504: Ofc Student Affairs Enrollment Mgmt | G504: 7015 | H504: 6010 | I504: General Administration | J504: DES | K504: Designated Funds | L504: 37000 | M504: 37000 | N504: 100
A505: 998490 | B505: 0100 | C505: 60092 | D505: 5050 | E505: =LEFT(D505,1) -> 5 | F505: Ofc Student Affairs Enrollment Mgmt | G505: 7010 | H505: 6010 | I505: General Administration | J505: DES | K505: Designated Funds | L505: 64000 | M505: 48000 | N505: 75
A506: 998685 | B506: 0100 | C506: 60092 | D506: 5050 | E506: =LEFT(D506,1) -> 5 | F506: Ofc Student Affairs Enrollment Mgmt | G506: 7010 | H506: 6010 | I506: General Administration | J506: DES | K506: Designated Funds | L506: 160000 | M506: 160000 | N506: 100
A507: 998589 | B507: 0100 | C507: 60102 | D507: 1400 | E507: =LEFT(D507,1) -> 1 | F507: Branding and Marketing | G507: 7010 | H507: 6020 | I507: General Institutional | J507: DES | K507: Designated Funds | L507: 32192 | M507: 6438 | N507: 20
A508: 998767 | B508: 0100 | C508: 60103 | D508: 1400 | E508: =LEFT(D508,1) -> 1 | F508: Communications and Marketing | G508: 7010 | H508: 6020 | I508: General Institutional | J508: DES | K508: Designated Funds | L508: 39500 | M508: 39500 | N508: 100
A509: 998886 | B509: 0100 | C509: 60103 | D509: 1400 | E509: =LEFT(D509,1) -> 1 | F509: Communications and Marketing | G509: 7010 | H509: 6020 | I509: General Institutional | J509: DES | K509: Designated Funds | L509: 39500 | M509: 39500 | N509: 100
A510: 998746 | B510: 0100 | C510: 60103 | D510: 1400 | E510: =LEFT(D510,1) -> 1 | F510: Communications and Marketing | G510: 7010 | H510: 6020 | I510: General Institutional | J510: DES | K510: Designated Funds | L510: 59500 | M510: 59500 | N510: 100
A511: 999969 | B511: 0100 | C511: 60103 | D511: 1400 | E511: =LEFT(D511,1) -> 1 | F511: Communications and Marketing | G511: 7010 | H511: 6020 | I511: General Institutional | J511: DES | K511: Designated Funds | L511: 67836 | M511: 61032 | N511: 89.97
A512: 999713 | B512: 0100 | C512: 60103 | D512: 1400 | E512: =LEFT(D512,1) -> 1 | F512: Communications and Marketing | G512: 7010 | H512: 6020 | I512: General Institutional | J512: DES | K512: Designated Funds | L512: 64364 | M512: 64364 | N512: 100
A513: 998582 | B513: 0100 | C513: 60104 | D513: 2080 | E513: =LEFT(D513,1) -> 2 | F513: Inst Research and Accountability | G513: 7015 | H513: 6020 | I513: General Institutional | J513: DES | K513: Designated Funds | L513: 31000 | M513: 31000 | N513: 100
A514: 999899 | B514: 0100 | C514: 60104 | D514: 2080 | E514: =LEFT(D514,1) -> 2 | F514: Inst Research and Accountability | G514: 7015 | H514: 6020 | I514: General Institutional | J514: DES | K514: Designated Funds | L514: 33667 | M514: 33667 | N514: 100
A515: 998928 | B515: 0100 | C515: 60104 | D515: 2080 | E515: =LEFT(D515,1) -> 2 | F515: Inst Research and Accountability | G515: 7010 | H515: 6020 | I515: General Institutional | J515: DES | K515: Designated Funds | L515: 43192 | M515: 43192 | N515: 100
A516: 999966 | B516: 0100 | C516: 60104 | D516: 2080 | E516: =LEFT(D516,1) -> 2 | F516: Inst Research and Accountability | G516: 7010 | H516: 6020 | I516: General Institutional | J516: DES | K516: Designated Funds | L516: 100000 | M516: 100000 | N516: 100
A517: 998978 | B517: 0100 | C517: 60105 | D517: 3810 | E517: =LEFT(D517,1) -> 3 | F517: IT Technology Services | G517: 7010 | H517: 6020 | I517: General Institutional | J517: DES | K517: Designated Funds | L517: 74000 | M517: 3596 | N517: 4.86
A518: 998544 | B518: 0100 | C518: 60105 | D518: 3810 | E518: =LEFT(D518,1) -> 3 | F518: IT Technology Services | G518: 7010 | H518: 6020 | I518: General Institutional | J518: DES | K518: Designated Funds | L518: 64000 | M518: 30976 | N518: 48.4
A519: 999823 | B519: 0100 | C519: 60105 | D519: 3810 | E519: =LEFT(D519,1) -> 3 | F519: IT Technology Services | G519: 7010 | H519: 6020 | I519: General Institutional | J519: DES | K519: Designated Funds | L519: 66763 | M519: 34589 | N519: 51.81
A520: 998917 | B520: 0100 | C520: 60105 | D520: 3810 | E520: =LEFT(D520,1) -> 3 | F520: IT Technology Services | G520: 7010 | H520: 6020 | I520: General Institutional | J520: DES | K520: Designated Funds | L520: 48000 | M520: 45000 | N520: 93.75
A521: 999821 | B521: 0100 | C521: 60105 | D521: 3810 | E521: =LEFT(D521,1) -> 3 | F521: IT Technology Services | G521: 7010 | H521: 6020 | I521: General Institutional | J521: DES | K521: Designated Funds | L521: 63500 | M521: 51873 | N521: 81.69
A522: 999963 | B522: 0100 | C522: 60109 | D522: 2057 | E522: =LEFT(D522,1) -> 2 | F522: Institutional Effectiveness | G522: 7010 | H522: 6020 | I522: General Institutional | J522: DES | K522: Designated Funds | L522: 60000 | M522: 60000 | N522: 100
A523: 998843 | B523: 0100 | C523: 60112 | D523: 2110 | E523: =LEFT(D523,1) -> 2 | F523: Center for Innovation | G523: 7015 | H523: 6020 | I523: General Institutional | J523: DES | K523: Designated Funds | L523: 24186 | M523: 24186 | N523: 100
A524: 998841 | B524: 0100 | C524: 60112 | D524: 2110 | E524: =LEFT(D524,1) -> 2 | F524: Center for Innovation | G524: 7010 | H524: 6020 | I524: General Institutional | J524: DES | K524: Designated Funds | L524: 50000 | M524: 50000 | N524: 100
A525: 998907 | B525: 0100 | C525: 60113 | D525: 2910 | E525: =LEFT(D525,1) -> 2 | F525: Sponsored Projects Office | G525: 7010 | H525: 6020 | I525: General Institutional | J525: DES | K525: Designated Funds | L525: 54000 | M525: 27000 | N525: 50
A526: 998612 | B526: 0100 | C526: 60170 | D526: 3110 | E526: =LEFT(D526,1) -> 3 | F526: Budget Office | G526: 7015 | H526: 6020 | I526: General Institutional | J526: DES | K526: Designated Funds | L526: 37547 | M526: 37547 | N526: 100
A527: 998700 | B527: 0100 | C527: 60170 | D527: 3110 | E527: =LEFT(D527,1) -> 3 | F527: Budget Office | G527: 7010 | H527: 6020 | I527: General Institutional | J527: DES | K527: Designated Funds | L527: 41000 | M527: 41000 | N527: 100
A528: 999003 | B528: 0100 | C528: 60170 | D528: 3110 | E528: =LEFT(D528,1) -> 3 | F528: Budget Office | G528: 7010 | H528: 6020 | I528: General Institutional | J528: DES | K528: Designated Funds | L528: 41000 | M528: 41000 | N528: 100
A529: 998955 | B529: 0100 | C529: 60200 | D529: 3120 | E529: =LEFT(D529,1) -> 3 | F529: Human Resources Office | G529: 7015 | H529: 6020 | I529: General Institutional | J529: DES | K529: Designated Funds | L529: 25131 | M529: 25131 | N529: 100
A530: 998491 | B530: 0100 | C530: 60200 | D530: 3120 | E530: =LEFT(D530,1) -> 3 | F530: Human Resources Office | G530: 7015 | H530: 6020 | I530: General Institutional | J530: DES | K530: Designated Funds | L530: 29265 | M530: 29265 | N530: 100
A531: 998526 | B531: 0100 | C531: 60200 | D531: 3120 | E531: =LEFT(D531,1) -> 3 | F531: Human Resources Office | G531: 7010 | H531: 6020 | I531: General Institutional | J531: DES | K531: Designated Funds | L531: 32192 | M531: 32192 | N531: 100
A532: 998834 | B532: 0100 | C532: 60200 | D532: 3120 | E532: =LEFT(D532,1) -> 3 | F532: Human Resources Office | G532: 7010 | H532: 6020 | I532: General Institutional | J532: DES | K532: Designated Funds | L532: 32192 | M532: 32192 | N532: 100
A533: 999709 | B533: 0100 | C533: 60200 | D533: 3120 | E533: =LEFT(D533,1) -> 3 | F533: Human Resources Office | G533: 7010 | H533: 6020 | I533: General Institutional | J533: DES | K533: Designated Funds | L533: 40000 | M533: 40000 | N533: 100
A534: 999723 | B534: 0100 | C534: 60200 | D534: 3120 | E534: =LEFT(D534,1) -> 3 | F534: Human Resources Office | G534: 7010 | H534: 6020 | I534: General Institutional | J534: DES | K534: Designated Funds | L534: 40000 | M534: 40000 | N534: 100
... A548: 999777 | B548: 0100 | C548: 60220 | D548: 3910 | E548: =LEFT(D548,1) -> 3 | F548: OneCard Operations | G548: 7010 | H548: 6020 | I548: General Institutional | J548: DES | K548: Designated Funds | L548: 57412 | M548: 57412 | N548: 100
A549: 999211 | B549: 0100 | C549: 60222 | D549: 3181 | E549: =LEFT(D549,1) -> 3 | F549: EHS and Risk Management | G549: 7010 | H549: 6020 | I549: General Institutional | J549: DES | K549: Designated Funds | L549: 61000 | M549: 61000 | N549: 100
A550: 999501 | B550: 0100 | C550: 60245 | D550: 3900 | E550: =LEFT(D550,1) -> 3 | F550: University Police | G550: 7015 | H550: 6030 | I550: Campus Police | J550: DES | K550: Designated Funds | L550: 22388 | M550: 22388 | N550: 100
A551: 999503 | B551: 0100 | C551: 60245 | D551: 3900 | E551: =LEFT(D551,1) -> 3 | F551: University Police | G551: 7015 | H551: 6030 | I551: Campus Police | J551: DES | K551: Designated Funds | L551: 22500 | M551: 22500 | N551: 100
A552: 999057 | B552: 0100 | C552: 60245 | D552: 3900 | E552: =LEFT(D552,1) -> 3 | F552: University Police | G552: 7015 | H552: 6030 | I552: Campus Police | J552: DES | K552: Designated Funds | L552: 35411 | M552: 35411 | N552: 100
A553: 999497 | B553: 0100 | C553: 60245 | D553: 3900 | E553: =LEFT(D553,1) -> 3 | F553: University Police | G553: 7015 | H553: 6030 | I553: Campus Police | J553: DES | K553: Designated Funds | L553: 35411 | M553: 35411 | N553: 100
A554: 999498 | B554: 0100 | C554: 60245 | D554: 3900 | E554: =LEFT(D554,1) -> 3 | F554: University Police | G554: 7015 | H554: 6030 | I554: Campus Police | J554: DES | K554: Designated Funds | L554: 35411 | M554: 35411 | N554: 100
A555: 999499 | B555: 0100 | C555: 60245 | D555: 3900 | E555: =LEFT(D555,1) -> 3 | F555: University Police | G555: 7015 | H555: 6030 | I555: Campus Police | J555: DES | K555: Designated Funds | L555: 35411 | M555: 35411 | N555: 100
A556: 999494 | B556: 0100 | C556: 60245 | D556: 3900 | E556: =LEFT(D556,1) -> 3 | F556: University Police | G556: 7015 | H556: 6030 | I556: Campus Police | J556: DES | K556: Designated Funds | L556: 42847 | M556: 42847 | N556: 100
A557: 999495 | B557: 0100 | C557: 60245 | D557: 3900 | E557: =LEFT(D557,1) -> 3 | F557: University Police | G557: 7015 | H557: 6030 | I557: Campus Police | J557: DES | K557: Designated Funds | L557: 42847 | M557: 42847 | N557: 100
A558: 999493 | B558: 0100 | C558: 60245 | D558: 3900 | E558: =LEFT(D558,1) -> 3 | F558: University Police | G558: 7010 | H558: 6030 | I558: Campus Police | J558: DES | K558: Designated Funds | L558: 51845 | M558: 51845 | N558: 100
A559: 999961 | B559: 0100 | C559: 60245 | D559: 3900 | E559: =LEFT(D559,1) -> 3 | F559: University Police | G559: 7010 | H559: 6030 | I559: Campus Police | J559: DES | K559: Designated Funds | L559: 77517 | M559: 77517 | N559: 100
A560: 999771 | B560: 0100 | C560: 60260 | D560: 3210 | E560: =LEFT(D560,1) -> 3 | F560: Junell Center | G560: 7010 | H560: 6020 | I560: General Institutional | J560: DES | K560: Designated Funds | L560: 49048 | M560: 6867 | N560: 14
A561: 998884 | B561: 0100 | C561: 60260 | D561: 3210 | E561: =LEFT(D561,1) -> 3 | F561: Junell Center | G561: 7015 | H561: 6020 | I561: General Institutional | J561: DES | K561: Designated Funds | L561: 31564 | M561: 7891 | N561: 25
... A563: 999097 | B563: 0100 | C563: 60260 | D563: 3210 | E563: =LEFT(D563,1) -> 3 | F563: Junell Center | G563: 7010 | H563: 6020 | I563: General Institutional | J563: DES | K563: Designated Funds | L563: 32192 | M563: 24144 | N563: 75
A564: 998356 | B564: 0100 | C564: 60265 | D564: 6300 | E564: =LEFT(D564,1) -> 6 | F564: Alumni Relations | G564: 7015 | H564: 6020 | I564: General Institutional | J564: DES | K564: Designated Funds | L564: 31000 | M564: 31000 | N564: 100
A565: 998357 | B565: 0100 | C565: 60265 | D565: 6300 | E565: =LEFT(D565,1) -> 6 | F565: Alumni Relations | G565: 7010 | H565: 6020 | I565: General Institutional | J565: DES | K565: Designated Funds | L565: 34000 | M565: 34000 | N565: 100
A566: 998696 | B566: 0100 | C566: 60277 | D566: 3052 | E566: =LEFT(D566,1) -> 3 | F566: Admin. Planning & Special Projects | G566: 7015 | H566: 6020 | I566: General Institutional | J566: DES | K566: Designated Funds | L566: 18750 | M566: 18750 | N566: 100
A567: 999960 | B567: 0100 | C567: 60277 | D567: 3052 | E567: =LEFT(D567,1) -> 3 | F567: Admin. Planning & Special Projects | G567: 7010 | H567: 6020 | I567: General Institutional | J567: DES | K567: Designated Funds | L567: 69838 | M567: 69838 | N567: 100
A568: 999780 | B568: 0100 | C568: 60280 | D568: 3240 | E568: =LEFT(D568,1) -> 3 | F568: Ticket Office | G568: 7010 | H568: 6020 | I568: General Institutional | J568: DES | K568: Designated Funds | L568: 37000 | M568: 37000 | N568: 100
A569: 999855 | B569: 0100 | C569: 60285 | D569: 2140 | E569: =LEFT(D569,1) -> 2 | F569: Quality Enhancement Plan | G569: 7015 | H569: 6020 | I569: General Institutional | J569: DES | K569: Designated Funds | L569: 37519 | M569: 34519 | N569: 92
A570: 998518 | B570: 0100 | C570: 60285 | D570: 2140 | E570: =LEFT(D570,1) -> 2 | F570: Quality Enhancement Plan | G570: 7010 | H570: 6020 | I570: General Institutional | J570: DES | K570: Designated Funds | L570: 97529 | M570: 55506 | N570: 56.91
A571: 998781 | B571: 0100 | C571: 60295 | D571: 5200 | E571: =LEFT(D571,1) -> 5 | F571: Enrollment Management | G571: 7010 | H571: 5010 | I571: Student Services | J571: DES | K571: Designated Funds | L571: 120000 | M571: 120000 | N571: 100
A572: 999740 | B572: 0100 | C572: 60300 | D572: 5230 | E572: =LEFT(D572,1) -> 5 | F572: Financial Aid Office | G572: 7010 | H572: 5010 | I572: Student Services | J572: DES | K572: Designated Funds | L572: 50292 | M572: 50292 | N572: 100
A573: 999741 | B573: 0100 | C573: 60300 | D573: 5230 | E573: =LEFT(D573,1) -> 5 | F573: Financial Aid Office | G573: 7010 | H573: 5010 | I573: Student Services | J573: DES | K573: Designated Funds | L573: 50292 | M573: 50292 | N573: 100
A574: 999964 | B574: 0100 | C574: 60300 | D574: 5230 | E574: =LEFT(D574,1) -> 5 | F574: Financial Aid Office | G574: 7010 | H574: 5010 | I574: Student Services | J574: DES | K574: Designated Funds | L574: 62732 | M574: 62732 | N574: 100
...

Sheet FY11 expense
A1: FSYR | B1: 2011
A2: FUND | B2: (Multiple Items)
A3: DEPT CODE | B3: (Multiple Items)
A4: ORGN CODE | B4: (Multiple Items)
A6: Row Labels | B6: Sum of TOTAL EXPENSE
A7: Accounting, Economics, and Finance | B7: 1233545
A8: Aerospace Studies | B8: 50559.72
A9: Agriculture | B9: 599585.43
A10: Art and Music | B10: 1225927.7
A11: Biology | B11: 1165519.6
A12: Chemistry and Biochemistry | B12: 595096.85
A13: Communication, Mass Media & Theatre | B13: 1256290.9
A14: Computer Science | B14: 513564.52
A15: Curriculum and Instruction | B15: 927480.14
A16: English and Modern Languages | B16: 1561489.3
A17: Kinesiology | B17: 835180.02
A18: Management and Marketing | B18: 1356228.3
... A29: Grand Total | B29: 20618259

Sheet Sheet1
A1: FSYR | B1: DEPARTMENT | C1: DEPT CODE | D1: Division | E1: FUND | F1: FUND CODE | G1: ORGANIZATION | H1: ORGN CODE | I1: MANAGER | J1: ADOPTED BUDGET | K1: PRIOR YR ENC | L1: BEGINNING BUDGET | M1: SALARY | N1: SALARY STUDENTS | O1: BENEFITS | P1: OPERATING EXPENSE | Q1: COMMITMENTS | R1: TOTAL EXPENSE | S1: AVAILABLE BALANCE
A2: 2011 | B2: Maintenance | C2: 3550 | D2: F | E2: Designated Tuition Fee | F2: 0100 | G2: Facilities Maintenance | H2: 61250 | I2: Halbert, Jay S. | J2: 166639.43 | K2: 4476.43 | L2: 162163 | M2: 0 | N2: 6752.97 | O2: 0 | P2: 83817.7 | Q2: 7521.93 | R2: 98092.6 | S2: 57766.07
A3: 2011 | B3: Maintenance | C3: 3550 | D3: F | E3: Designated Tuition Fee | F3: 0100 | G3: Junell Center Plant Operations | H3: 61185 | I3: Halbert, Jay S. | J3: 238417.25 | K3: 8774.25 | L3: 229643 | M3: 38297.71 | N3: 0 | O3: 0 | P3: 181759.72 | Q3: 9999.54 | R3: 230056.97 | S3: 5505.35
A4: 2011 | B4: University Recreation Intramurals | C4: 5500 | D4: F | E4: Designated Tuition Fee | F4: 0100 | G4: Exercise Room | H4: 61175 | I4: Petty, Bradley C. | J4: 8500 | K4: 0.00 | L4: 8500 | M4: 0 | N4: 0 | O4: 0 | P4: 7423.28 | Q4: 0 | R4: 7423.28 | S4: 481.72
A5: 2011 | B5: Facilities Management | C5: 3500 | D5: F | E5: Designated Tuition Fee | F5: 0100 | G5: Bus Operations | H5: 61170 | I5: Halbert, Jay S. | J5: 63058 | K5: 0.00 | L5: 63058 | M5: 2472.76 | N5: 0 | O5: 0 | P5: 14054.4 | Q5: 0 | R5: 16527.16 | S5: 42435.84
A6: 2011 | B6: Infrastructure Services | C6: 3850 | D6: F | E6: Designated Tuition Fee | F6: 0100 | G6: Communications System Maintenance | H6: 61168 | I6: Braden, Brian M. | J6: 48000 | K6: 0.00 | L6: 48000 | M6: 0 | N6: 0 | O6: 0 | P6: 45041.63 | Q6: 0 | R6: 45041.63 | S6: 0
A7: 2011 | B7: EHS and Risk Management | C7: 3181 | D7: F | E7: Designated Tuition Fee | F7: 0100 | G7: Waste Management | H7: 61167 | J7: 16000 | K7: 0.00 | L7: 16000 | M7: 0 | N7: 0 | O7: 0 | P7: 14780.09 | Q7: 415 | R7: 15195.09 | S7: -67.63
A8: 2011 | B8: Facilities Planning Construction | C8: 3600 | D8: F | E8: Designated Tuition Fee | F8: 0100 | G8: Performance Contract Payment | H8: 61166 | I8: Russell, John H. | J8: 799014 | K8: 0.00 | L8: 799014 | M8: 0 | N8: 0 | O8: 0 | P8: 503485.84 | Q8: 0 | R8: 503485.84 | S8: 0.16
A9: 2011 | B9: Facilities Management | C9: 3500 | D9: F | E9: Designated Tuition Fee | F9: 0100 | G9: Plant Renewal | H9: 61165 | I9: Halbert, Jay S. | J9: 241079.65 | K9: 77401.65 | L9: 163678 | M9: 0 | N9: 0 | O9: 0 | P9: 183334.4 | Q9: 0 | R9: 183334.4 | S9: 45387.79
A10: 2011 | B10: Facilities Planning Construction | C10: 3600 | D10: F | E10: Designated Tuition Fee | F10: 0100 | G10: Reidy Building | H10: 61163 | I10: Russell, John H. | J10: 66000 | K10: 0.00 | L10: 66000 | M10: 0 | N10: 0 | O10: 0 | P10: 66000 | Q10: 0 | R10: 66000 | S10: 0
A11: 2011 | B11: Materials Management | C11: 3700 | D11: F | E11: Designated Tuition Fee | F11: 0100 | G11: Materials Management Supplies | H11: 61161 | I11: Flage, Bruce H. | J11: 138046.64 | K11: 38046.64 | L11: 100000 | M11: 0 | N11: 0 | O11: 0 | P11: 14535.24 | Q11: 39321 | R11: 53856.24 | S11: 77190.4
A12: 2011 | B12: Energy Management | C12: 3520 | D12: F | E12: Designated Tuition Fee | F12: 0100 | G12: Purchased Utilities-Sewer | H12: 61159 | I12: Halbert, Jay S. | J12: 47512.52 | K12: 1762.52 | L12: 45750 | M12: 0 | N12: 0 | O12: 0 | P12: 28531.66 | Q12: 0 | R12: 28531.66 | S12: 15778.36
A13: 2011 | B13: Energy Management | C13: 3520 | D13: F | E13: Designated Tuition Fee | F13: 0100 | G13: Purchased Utilities-Water | H13: 61158 | I13: Halbert, Jay S. | J13: 101909.13 | K13: 9209.13 | L13: 92700 | M13: 0 | N13: 0 | O13: 0 | P13: 79384.19 | Q13: 0 | R13: 79384.19 | S13: 16035.94
A14: 2011 | B14: Energy Management | C14: 3520 | D14: F | E14: Designated Tuition Fee | F14: 0100 | G14: Purchased Utilities-Fuel | H14: 61157 | I14: Halbert, Jay S. | J14: 242700 | K14: 2700 | L14: 240000 | M14: 0 | N14: 0 | O14: 0 | P14: 120671.57 | Q14: 0 | R14: 120671.57 | S14: 5228.43
A15: 2011 | B15: Energy Management | C15: 3520 | D15: F | E15: Designated Tuition Fee | F15: 0100 | G15: Purchased Utilities-Electricity | H15: 61156 | I15: Halbert, Jay S. | J15: 357325.66 | K15: 48870.66 | L15: 308455 | M15: 0 | N15: 0 | O15: 0 | P15: 1032767.3 | Q15: 0 | R15: 1032767.3 | S15: 205785.47
A16: 2011 | B16: Energy Management | C16: 3520 | D16: F | E16: Designated Tuition Fee | F16: 0100 | G16: Purchased Utilities | H16: 61155 | I16: Halbert, Jay S. | J16: 273727.34 | K16: 22727.34 | L16: 251000 | M16: 0 | N16: 0 | O16: 0 | P16: 164988.86 | Q16: 0 | R16: 164988.86 | S16: 91168.48
A17: 2011 | B17: Grounds | C17: 3530 | D17: F | E17: Designated Tuition Fee | F17: 0100 | G17: Grounds Maintenance | H17: 61154 | I17: Halbert, Jay S. | J17: 117300.71 | K17: 5900.71 | L17: 111400 | M17: 15390 | N17: 0 | O17: 0 | P17: 105002.37 | Q17: 7424.4 | R17: 127816.77 | S17: 7075.94
A18: 2011 | B18: Custodial | C18: 3510 | D18: F | E18: Designated Tuition Fee | F18: 0100 | G18: Custodial Services | H18: 61152 | I18: Halbert, Jay S. | J18: 695552.03 | K18: 34088.03 | L18: 661464 | M18: 4860 | N18: 0 | O18: 0 | P18: 633937.4 | Q18: 46931.71 | R18: 685729.11 | S18: 882.12
A19: 2011 | B19: Maintenance | C19: 3550 | D19: F | E19: Designated Tuition Fee | F19: 0100 | G19: Building Maintenance | H19: 61150 | I19: Halbert, Jay S. | J19: 907815.03 | K19: 92246.03 | L19: 815569 | M19: 379957.29 | N19: 9356.99 | O19: 900 | P19: 387474.68 | Q19: 38257.08 | R19: 815946.04 | S19: 89775.22
A20: 2011 | B20: Facilities Management | C20: 3500 | D20: F | E20: Designated Tuition Fee | F20: 0100 | G20: Facilities Mgmt Operations | H20: 61148 | I20: Halbert, Jay S. | J20: 98032.76 | K20: 12485.76 | L20: 85547 | M20: 12648.6 | N20: 0 | O20: 0 | P20: 38660.79 | Q20: 11695.73 | R20: 63005.12 | S20: 41687.95
A21: 2011 | B21: Facilities Planning Construction | C21: 3600 | D21: F | E21: Designated Tuition Fee | F21: 0100 | G21: Facilities Services | H21: 61145 | I21: Russell, John H. | J21: 62196.01 | K21: 17196.01 | L21: 45000 | M21: 0 | N21: 0 | O21: 0 | P21: 29274.83 | Q21: 10827.5 | R21: 40102.33 | S21: 18943.68
A22: 2011 | B22: Facilities Planning Construction | C22: 3600 | D22: F | E22: Designated Tuition Fee | F22: 0100 | G22: Construction Management | H22: 61141 | I22: Russell, John H. | J22: 0 | K22: 0.00 | L22: 0 | M22: 0 | N22: 0 | O22: 0 | P22: 0 | Q22: 3006.33 | R22: 3006.33 | S22: 639.67
A23: 2011 | B23: Energy Management | C23: 3520 | D23: F | E23: E&G Institutional Enhancement | F23: 0018 | G23: Purchased Utilities-Electricity | H23: 46510 | I23: Halbert, Jay S. | J23: 498383 | K23: 0.00 | L23: 498383 | M23: 0 | N23: 0 | O23: 0 | P23: 116654.88 | Q23: 0 | R23: 116654.88 | S23: -112725.16
A24: 2011 | B24: Energy Management | C24: 3520 | D24: F | E24: Educational and General | F24: 0010 | G24: Purchased Utilities-Electricity | H24: 46510 | I24: Halbert, Jay S. | J24: 404158.91 | K24: 211.91 | L24: 403947 | M24: 0 | N24: 0 | O24: 0 | P24: -92.37 | Q24: 0 | R24: -92.37 | S24: 304.28
A25: 2011 | B25: Energy Management | C25: 3520 | D25: F | E25: Educational and General | F25: 0010 | G25: Other Utility Costs | H25: 46500 | I25: Halbert, Jay S. | J25: 224171 | K25: 0.00 | L25: 224171 | M25: 190482.33 | N25: 0 | O25: 420 | P25: 17192.19 | Q25: 0 | R25: 208094.52 | S25: 13096.48
A26: 2011 | B26: Grounds | C26: 3530 | D26: F | E26: Educational and General | F26: 0010 | G26: Grounds Maintenance | H26: 46400 | I26: Halbert, Jay S. | J26: 394584 | K26: 0.00 | L26: 394584 | M26: 367778.52 | N26: 12874.59 | O26: 0 | P26: 0 | Q26: 0 | R26: 380653.11 | S26: 1932.85
A27: 2011 | B27: Custodial | C27: 3510 | D27: F | E27: Educational and General | F27: 0010 | G27: Custodial Services | H27: 46300 | I27: Halbert, Jay S. | J27: 91037 | K27: 0.00 | L27: 91037 | M27: 51055.5 | N27: 0 | O27: 900 | P27: 0 | Q27: 0 | R27: 51955.5 | S27: 3522.5
A28: 2011 | B28: Maintenance | C28: 3550 | D28: F | E28: Educational and General | F28: 0010 | G28: Building Maintenance | H28: 46200 | I28: Halbert, Jay S. | J28: 513680 | K28: 0.00 | L28: 513680 | M28: 504117.58 | N28: 0 | O28: 1740 | P28: 0 | Q28: 0 | R28: 505857.58 | S28: 2430.42
A29: 2011 | B29: Facilities Planning Construction | C29: 3600 | D29: F | E29: Educational and General | F29: 0010 | G29: Facilities Planning/Construction | H29: 46115 | I29: Russell, John H. | J29: 20100.7 | K29: 1000.7 | L29: 19100 | M29: 0 | N29: 0 | O29: 0 | P29: 14873.5 | Q29: 285.41 | R29: 15158.91 | S29: 3604.79
A30: 2011 | B30: Facilities Management | C30: 3500 | D30: F | E30: Educational and General | F30: 0010 | G30: Facilities Mgmt Operations | H30: 46100 | I30: Halbert, Jay S. | J30: 7460 | K30: 0.00 | L30: 7460 | M30: 0 | N30: 7108.8 | O30: 0 | P30: 0 | Q30: 0 | R30: 7108.8 | S30: 202
A31: 2011 | B31: Facilities Management | C31: 3500 | D31: F | E31: Educational and General | F31: 0010 | G31: Facilities Mgmt Administration | H31: 46000 | I31: Halbert, Jay S. | J31: 231514 | K31: 15 | L31: 231499 | M31: 189310.55 | N31: 22506.86 | O31: 1320 | P31: 3696.49 | Q31: 0 | R31: 216833.9 | S31: 5120.79

Sheet FY11 expense (2)
A1: FSYR | B1: 2011 | D1: 1= president
A2: ORGN CODE | B2: (All) | D2: 2= Academic Affairs
D3: 3= Finance & Administration
A4: Row Labels | B4: Sum of TOTAL EXPENSE | D4: 4= Strategy & Planning
A5: 1 | B5: 1767758.3 | D5: 5= Student Affairs
A6: 2 | B6: 24951387 | D6: 6= Development
A7: 3 | B7: 13064220 | D7: 9= Non budgeted
A8: 4 | B8: 244753.55 | D8: X= funded by non-transferrable revenue
A9: 5 | B9: 2649386.4 | D9: F= Facilities
A10: 6 | B10: 279189.07
A11: 9 | B11: 931585.65
A12: X | B12: 9132908
A13: F | B13: 5883187.3
A14: Grand Total | B14: 58904375

Sheet fy12 budget
A1: FSYR | B1: 2012
A2: FUND | B2: (Multiple Items)
A3: FUND CODE | B3: (All)
A4: DEPT CODE | B4: (Multiple Items)
A5: ORGN CODE | B5: (Multiple Items)
A7: Row Labels | B7: Sum of BEGINNING BUDGET
A8: Accounting, Economics, and Finance | B8: 1066854
A9: Aerospace Studies | B9: 44068
A10: Agriculture | B10: 591449
A11: Art and Music | B11: 1229055
A12: Biology | B12: 1108636
A13: Chemistry and Biochemistry | B13: 531545
A14: Communication, Mass Media & Theatre | B14: 989795
A15: Curriculum and Instruction | B15: 459814
A16: English and Modern Languages | B16: 1663079
A17: Kinesiology | B17: 538599
A18: Management and Marketing | B18: 1102526
A19: Mathematics and Computer Science | B19: 1259999
... A29: Grand Total | B29: 17573431

Sheet fy12 budget (2)
A1: FSYR | B1: 2012 | D1: 1= president
A2: ORGN CODE | B2: (All) | D2: 2= Academic Affairs
D3: 3= Finance & Administration
A4: Row Labels | B4: Sum of BEGINNING BUDGET | D4: 4= Strategy & Planning
A5: 1 | B5: 1715950 | D5: 5= Student Affairs
A6: 2 | B6: 24225239 | D6: 6= Development
A7: 3 | B7: 11834075 | D7: 9= Non budgeted
A8: 4 | B8: 272144 | D8: X= funded by non-transferrable revenue
A9: 5 | B9: 2658064 | D9: F= Facilities
A10: 6 | B10: 449832
A11: 9 | B11: 0
A12: X | B12: 4890628
A13: F | B13: 5531857
A14: Grand Total | B14: 51577789

Sheet exp&bud data
A1: FSYR | B1: DEPARTMENT | C1: DEPT CODE | D1: Division | E1: FUND | F1: FUND CODE | G1: ORGANIZATION | H1: ORGN CODE | I1: MANAGER | J1: ADOPTED BUDGET | K1: PRIOR YR ENC | L1: BEGINNING BUDGET | M1: SALARY | N1: SALARY STUDENTS | O1: BENEFITS | P1: OPERATING EXPENSE | Q1: COMMITMENTS | R1: TOTAL EXPENSE | S1: AVAILABLE BALANCE
A2: 2011 | B2: President | C2: 1050 | D2: =LEFT(C2:C2,1) -> 1 | E2: Educational and General | F2: 0010 | G2: Office of the President | H2: 32100 | I2: Morales, Adelina C. | J2: 138330 | K2: 0.00 | L2: 138330 | M2: 138250 | N2: 0 | O2: 0 | P2: 0 | Q2: 0 | R2: 138250 | S2: 80
A3: 2012 | B3: President | C3: 1050 | D3: =LEFT(C3:C3,1) -> 1 | E3: Educational and General | F3: 0010 | G3: Office of the President | H3: 32100 | I3: Morales, Adelina C. | J3: 65945 | K3: 0.00 | L3: 65945 | M3: 38747.94 | N3: 0 | O3: 0 | P3: 0 | Q3: 0 | R3: 38747.94 | S3: 27197.06
A4: 2011 | B4: Provost and VPAA | C4: 2050 | D4: =LEFT(C4:C4,1) -> 2 | E4: Educational and General | F4: 0010 | G4: Office Academic Affairs | H4: 32250 | I4: May, Brian J. | J4: 0 | K4: 0.00 | L4: 0 | M4: 146.9 | N4: 0 | O4: 0 | P4: 0 | Q4: 0 | R4: 146.9 | S4: 0
A5: 2011 | B5: Vice Provost for Academic Affairs | C5: 2100 | D5: =LEFT(C5:C5,1) -> 2 | E5: Educational and General | F5: 0010 | G5: Vice Provost Academic Affairs | H5: 32255 | I5: Allen, Nancy G. | J5: 11002.49 | K5: 652.49 | L5: 10350 | M5: 0 | N5: 0 | O5: 0 | P5: 5367.56 | Q5: 0 | R5: 5367.56 | S5: 4910.43
A6: 2011 | B6: Communications and Marketing | C6: 1400 | D6: =LEFT(C6:C6,1) -> 1 | E6: Educational and General | F6: 0010 | G6: Communications and Marketing | H6: 33100 | I6: Lewis, John P. | J6: 401723 | K6: 0.00 | L6: 401723 | M6: 393771.52 | N6: 1370.25 | O6: 0 | P6: 0 | Q6: 0 | R6: 395141.77 | S6: -22812.46
A7: 2012 | B7: Communications and Marketing | C7: 1400 | D7: =LEFT(C7:C7,1) -> 1 | E7: Educational and General | F7: 0010 | G7: Communications and Marketing | H7: 33100 | I7: Lewis, John P. | J7: 168638 | K7: 0.00 | L7: 168638 | M7: 99341.14 | N7: 0 | O7: 0 | P7: 0 | Q7: 0 | R7: 99341.14 | S7: 69209.86
A8: 2011 | B8: Budget Office | C8: 3110 | D8: =LEFT(C8:C8,1) -> 3 | E8: Educational and General | F8: 0010 | G8: Budget and Payroll Services | H8: 33290 | I8: Wright, Angelina W. | J8: 136176 | K8: 0.00 | L8: 136176 | M8: 135346.76 | N8: 0 | O8: 0 | P8: 0 | Q8: 0 | R8: 135346.76 | S8: -10498.76
A9: 2012 | B9: Budget Office | C9: 3110 | D9: =LEFT(C9:C9,1) -> 3 | E9: Educational and General | F9: 0010 | G9: Budget and Payroll Services | H9: 33290 | I9: Wright, Angelina W. | J9: 136656 | K9: 0.00 | L9: 136656 | M9: 77265.64 | N9: 0 | O9: 0 | P9: 0 | Q9: 0 | R9: 77265.64 | S9: 59390.36
A10: 2011 | B10: Controller | C10: 3300 | D10: =LEFT(C10:C10,1) -> 3 | E10: Educational and General | F10: 0010 | G10: Controller's Office | H10: 33300 | I10: Brodnax, Denise H. | J10: 111512 | K10: 0.00 | L10: 111512 | M10: 98195.18 | N10: 0 | O10: 0 | P10: 0 | Q10: 0 | R10: 98195.18 | S10: -6969.79
A11: 2012 | B11: Controller | C11: 3300 | D11: =LEFT(C11:C11,1) -> 3 | E11: Educational and General | F11: 0010 | G11: Controller's Office | H11: 33300 | I11: Brodnax, Denise H. | J11: 446883 | K11: 0.00 | L11: 446883 | M11: 240343.77 | N11: 0 | O11: 0 | P11: 0 | Q11: 0 | R11: 240343.77 | S11: 199698.23
A12: 2011 | B12: Materials Management | C12: 3700 | D12: =LEFT(C12:C12,1) -> 3 | E12: Educational and General | F12: 0010 | G12: Materials Management Office | H12: 33319 | I12: Flage, Bruce H. | J12: 306335 | K12: 0.00 | L12: 306335 | M12: 295555.62 | N12: 2144 | O12: 0 | P12: 0 | Q12: 0 | R12: 297699.62 | S12: -21864.04
A13: 2012 | B13: Materials Management | C13: 3700 | D13: =LEFT(C13:C13,1) -> 3 | E13: Educational and General | F13: 0010 | G13: Materials Management Office | H13: 33319 | I13: Flage, Bruce H. | J13: 295275 | K13: 0.00 | L13: 295275 | M13: 161564.05 | N13: 0 | O13: 0 | P13: 0 | Q13: 0 | R13: 161564.05 | S13: 130702.95
A14: 2011 | B14: Print Shop | C14: 3730 | D14: =LEFT(C14:C14,1) -> 3 | E14: Educational and General | F14: 0010 | G14: Print Shop | H14: 33350 | I14: Begil, Henry H. | J14: 158221.19 | K14: 19950.19 | L14: 138271 | M14: 113536.07 | N14: 0 | O14: 0 | P14: -72464.86 | Q14: 14740.3 | R14: 55811.51 | S14: 58350.02
A15: 2012 | B15: Print Shop | C15: 3730 | D15: =LEFT(C15:C15,1) -> 3 | E15: Educational and General | F15: 0010 | G15: Print Shop | H15: 33350 | I15: Begil, Henry H. | J15: 103011.3 | K15: 14740.3 | L15: 88271 | M15: 49080.04 | N15: 7449.25 | O15: 0 | P15: -69212.24 | Q15: 11814.08 | R15: -868.87 | S15: 103880.17
A16: 2011 | B16: EHS and Risk Management | C16: 3181 | D16: =LEFT(C16:C16,1) -> 3 | E16: Educational and General | F16: 0010 | G16: EHS and Risk Management | H16: 33410 | J16: 64744 | K16: 0.00 | L16: 64744 | M16: 53654.22 | N16: 0 | O16: 0 | P16: 0 | Q16: 0 | R16: 53654.22 | S16: -4110.22
A17: 2011 | B17: VP Finance and Administration | C17: 3050 | D17: =LEFT(C17:C17,1) -> 3 | E17: Educational and General | F17: 0010 | G17: System Office Operations | H17: 33590 | I17: Reid, Michael L. | J17: 120628 | K17: 0.00 | L17: 120628 | M17: 0 | N17: 0 | O17: 0 | P17: 120628 | Q17: 0 | R17: 120628 | S17: 0
A18: 2012 | B18: VP Finance and Administration | C18: 3050 | D18: =LEFT(C18:C18,1) -> 3 | E18: Educational and General | F18: 0010 | G18: System Office Operations | H18: 33590 | I18: Reid, Michael L. | J18: 120628 | K18: 0.00 | L18: 120628 | M18: 0 | N18: 0 | O18: 0 | P18: 120628 | Q18: 0 | R18: 120628 | S18: 0
A19: 2011 | B19: University Police | C19: 3900 | D19: =LEFT(C19:C19,1) -> 3 | E19: Educational and General | F19: 0010 | G19: University Police | H19: 33640 | I19: Adams, James E. | J19: 0 | K19: 0.00 | L19: 0 | M19: 69169.31 | N19: 0 | O19: 0 | P19: 0 | Q19: 0 | R19: 69169.31 | S19: -3175.48
A20: 2011 | B20: Admissions Office | C20: 5210 | D20: =LEFT(C20:C20,1) -> 5 | E20: Educational and General | F20: 0010 | G20: Office of Admissions | H20: 33650 | I20: Loehring, Michael E. | J20: 261421.31 | K20: 1878.31 | L20: 259543 | M20: 177419.94 | N20: 35666.97 | O20: 0 | P20: 1688.67 | Q20: 0 | R20: 214775.58 | S20: 854.89
A21: 2012 | B21: Admissions Office | C21: 5210 | D21: =LEFT(C21:C21,1) -> 5 | E21: Educational and General | F21: 0010 | G21: Office of Admissions | H21: 33650 | I21: Loehring, Michael E. | J21: 0 | K21: 0.00 | L21: 0 | M21: 0 | N21: 145 | O21: 0 | P21: 0 | Q21: 0 | R21: 145 | S21: -145
A22: 2011 | B22: Registrar's Office | C22: 5240 | D22: =LEFT(C22:C22,1) -> 5 | E22: Educational and General | F22: 0010 | G22: Office of the Registrar | H22: 33670 | I22: Weeaks, Cynthia D. | J22: 130598 | K22: 0.00 | L22: 130598 | M22: 125974.87 | N22: 0 | O22: 0 | P22: 0 | Q22: 0 | R22: 125974.87 | S22: -159.79
A23: 2011 | B23: Dean College of Graduate Studies | C23: 2900 | D23: =LEFT(C23:C23,1) -> 2 | E23: Educational and General | F23: 0010 | G23: Pre-Enrollment Advising-Graduate | H23: 33710 | I23: May, Brian J. | J23: 0 | K23: 0.00 | L23: 0 | M23: 1713.24 | N23: 0 | O23: 0 | P23: 0 | Q23: 0 | R23: 1713.24 | S23: -1713.24
A24: 2011 | B24: First Year Experience | C24: 2240 | D24: =LEFT(C24:C24,1) -> 2 | E24: Educational and General | F24: 0010 | G24: First Year Experience | H24: 33715 | I24: Allen, Nancy G. | J24: 0 | K24: 0.00 | L24: 0 | M24: 59448 | N24: 0 | O24: 0 | P24: 0 | Q24: 0 | R24: 59448 | S24: 0
A25: 2012 | B25: First Year Experience | C25: 2240 | D25: =LEFT(C25:C25,1) -> 2 | E25: Educational and General | F25: 0010 | G25: First Year Experience | H25: 33715 | I25: Allen, Nancy G. | J25: 0 | K25: 0.00 | L25: 0 | M25: 56743 | N25: 0 | O25: 0 | P25: 0 | Q25: 0 | R25: 56743 | S25: 3274
A26: 2011 | B26: Financial Aid | C26: 5230 | D26: =LEFT(C26:C26,1) -> 5 | E26: Educational and General | F26: 0010 | G26: Financial Aid | H26: 33730 | I26: Bennett, Michelle A. | J26: 321861 | K26: 0.00 | L26: 321861 | M26: 209753.6 | N26: 10898.78 | O26: 0 | P26: 0 | Q26: 0 | R26: 220652.38 | S26: 12250.01
A27: 2012 | B27: Financial Aid | C27: 5230 | D27: =LEFT(C27:C27,1) -> 5 | E27: Educational and General | F27: 0010 | G27: Financial Aid | H27: 33730 | I27: Bennett, Michelle A. | J27: 242987 | K27: 0.00 | L27: 242987 | M27: 135847.36 | N27: 2789.23 | O27: 0 | P27: 0 | Q27: 0 | R27: 138636.59 | S27: 109038.41
A28: 2011 | B28: Career Development | C28: 5220 | D28: =LEFT(C28:C28,1) -> 5 | E28: Educational and General | F28: 0010 | G28: Career Development | H28: 33765 | I28: Ruthenbeck, Julie J. | J28: 14263 | K28: 0.00 | L28: 14263 | M28: 13115.99 | N28: 0 | O28: 0 | P28: 0 | Q28: 0 | R28: 13115.99 | S28: 3.64
A29: 2012 | B29: Career Development | C29: 5220 | D29: =LEFT(C29:C29,1) -> 5 | E29: Educational and General | F29: 0010 | G29: Career Development | H29: 33765 | I29: Ruthenbeck, Julie J. | J29: 14383 | K29: 0.00 | L29: 14383 | M29: 7779.66 | N29: 0 | O29: 0 | P29: 0 | Q29: 0 | R29: 7779.66 | S29: 6603.34
A30: 2011 | B30: Staff Benefits | C30: 3115 | D30: =LEFT(C30:C30,1) -> 3 | E30: Educational and General | F30: 0010 | G30: Staff Group Insurance Premiums | H30: 33800 | I30: Wright, Angelina W. | J30: 1048198 | K30: 0.00 | L30: 1048198 | M30: 0 | N30: 0 | O30: =4957074-4077985.83 -> 879088.17 | P30: 0 | Q30: 0 | R30: =4957074-4077985.83 -> 879088.17 | S30: -3908876
A31: 2012 | B31: Staff Benefits | C31: 3115 | D31: =LEFT(C31:C31,1) -> 3 | E31: Educational and General | F31: 0010 | G31: Staff Group Insurance Premiums | H31: 33800 | I31: Wright, Angelina W. | J31: 1271290 | K31: 0.00 | L31: 1271290 | M31: 0 | N31: 0 | O31: 658867.43 | P31: 0 | Q31: 0 | R31: 126893.92 | S31: 612422.57
A32: 2011 | B32: Staff Benefits | C32: 3115 | D32: =LEFT(C32:C32,1) -> 3 | E32: Educational and General | F32: 0010 | G32: ORP Fund 001 & Local | H32: 33910 | I32: Wright, Angelina W. | J32: 1854150 | K32: 0.00 | L32: 1854150 | M32: 0 | N32: 0 | O32: =864518.3-737624.38 -> 126893.92 | P32: 0 | Q32: 0 | R32: =864518.3-737624.38 -> 126893.92 | S32: 989631.7
A33: 2012 | B33: Staff Benefits | C33: 3115 | D33: =LEFT(C33:C33,1) -> 3 | E33: Educational and General | F33: 0010 | G33: ORP Fund 001 & Local | H33: 33910 | I33: Wright, Angelina W. | J33: 1706595 | K33: 0.00 | M33: 0 | N33: 0 | O33: 439091.44 | P33: 0 | Q33: 0 | R33: 467922.11 | S33: 926184.56
A34: 2011 | B34: Staff Benefits | C34: 3115 | D34: =LEFT(C34:C34,1) -> 3 | E34: Educational and General | F34: 0010 | G34: ORP Supplement Fund 227 & Local | H34: 33920 | I34: Wright, Angelina W. | J34: 125927 | K34: 0.00 | L34: 125927 | M34: 0 | N34: 0 | O34: 111247.55 | P34: 0 | Q34: 0 | R34: 111247.55 | S34: 14679.45
A35: 2012 | B35: Staff Benefits | C35: 3115 | D35: =LEFT(C35:C35,1) -> 3 | E35: Educational and General | F35: 0010 | G35: ORP Supplement Fund 227 & Local | H35: 33920 | I35: Wright, Angelina W. | J35: 80000 | K35: 0.00 | L35: 80000 | M35: 0 | N35: 0 | O35: 84575.84 | P35: 0 | Q35: 0 | R35: 84575.84 | S35: -4575.84
A36: 2012 | B36: Staff Benefits | C36: 3115 | D36: =LEFT(C36:C36,1) -> 3 | E36: Educational and General | F36: 0010 | G36: ORP Proportional, Fund 227 | H36: 33940 | I36: Wright, Angelina W. | J36: 1035 | K36: 0.00 | L36: 1035 | M36: 0 | N36: 0 | O36: 0 | P36: 0 | Q36: 0 | R36: 0 | S36: 1035
A37: 2011 | B37: Staff Benefits | C37: 3115 | D37: =LEFT(C37:C37,1) -> 3 | E37: Educational and General | F37: 0010 | G37: OASI Fund 001 & Local | H37: 33950 | I37: Wright, Angelina W. | J37: 1976713 | K37: 0.00 | L37: 1976713 | M37: 0 | N37: 0 | O37: =1885513.6-1417591.49 -> 467922.11 | P37: 0 | Q37: 0 | R37: =1885513.6-1417591.49 -> 467922.11 | S37: 91199.4
A38: 2012 | B38: Staff Benefits | C38: 3115 | D38: =LEFT(C38:C38,1) -> 3 | E38: Educational and General | F38: 0010 | G38: OASI Fund 001 & Local | H38: 33950 | I38: Wright, Angelina W. | J38: 2145716 | K38: 0.00 | M38: 0 | N38: 0 | O38: 972230.88 | P38: 0 | Q38: 0 | R38: 972230.88 | S38: 1173485.1
A39: 2011 | B39: Staff Benefits | C39: 3115 | D39: =LEFT(C39:C39,1) -> 3 | E39: Educational and General | F39: 0010 | G39: TRS, Fund 227 and Local | H39: 33980 | I39: Wright, Angelina W. | J39: 0 | K39: 0.00 | L39: 0 | M39: 0 | N39: 0 | O39: 253910.04 | P39: 0 | Q39: 0 | R39: 253910.04 | S39: -73485.02
A40: 2012 | B40: Staff Benefits | C40: 3115 | D40: =LEFT(C40:C40,1) -> 3 | E40: Educational and General | F40: 0010 | G40: TRS, Fund 227 and Local | H40: 33980 | I40: Wright, Angelina W. | J40: 0 | K40: 0.00 | L40: 0 | M40: 0 | N40: 0 | O40: 36444.39 | P40: 0 | Q40: 0 | R40: 36444.39 | S40: 304874.61
A41: 2011 | B41: Staff Benefits | C41: 3115 | D41: =LEFT(C41:C41,1) -> 3 | E41: Educational and General | F41: 0010 | G41: TRS, Fund 001 | H41: 33990 | I41: Wright, Angelina W. | J41: 0 | K41: 0.00 | L41: 0 | M41: 0 | N41: 0 | O41: 244350.18 | P41: 0 | Q41: 0 | R41: 244350.18 | S41: -244350.18
A42: 2011 | B42: Staff Benefits | C42: 3115 | D42: =LEFT(C42:C42,1) -> 3 | E42: Educational and General | F42: 0010 | G42: TRS New Members | H42: 33992 | I42: Wright, Angelina W. | J42: 20000 | K42: 0.00 | L42: 20000 | M42: 0 | N42: 0 | O42: 12007.69 | P42: 0 | Q42: 0 | R42: 12007.69 | S42: 7992.31
A43: 2012 | B43: Staff Benefits | C43: 3115 | D43: =LEFT(C43:C43,1) -> 3 | E43: Educational and General | F43: 0010 | G43: TRS New Members | H43: 33992 | I43: Wright, Angelina W. | J43: 10000 | K43: 0.00 | L43: 10000 | M43: 0 | N43: 0 | O43: 6154.84 | P43: 0 | Q43: 0 | R43: 6154.84 | S43: 3845.16
A44: 2011 | B44: Staff Benefits | C44: 3115 | D44: =LEFT(C44:C44,1) -> 3 | E44: Educational and General | F44: 0010 | G44: TRS Surcharge | H44: 33993 | I44: Wright, Angelina W. | J44: 0 | K44: 0.00 | L44: 0 | M44: 0 | N44: 0 | O44: 22644.27 | P44: 0 | Q44: 0 | R44: 22644.27 | S44: -3069.29
A45: 2012 | B45: Staff Benefits | C45: 3115 | D45: =LEFT(C45:C45,1) -> 3 | E45: Educational and General | F45: 0010 | G45: TRS Surcharge | H45: 33993 | I45: Wright, Angelina W. | J45: 0 | K45: 0.00 | L45: 0 | M45: 0 | N45: 0 | O45: 19003.44 | P45: 0 | Q45: 0 | R45: 19003.44 | S45: -19003.44
A46: 2011 | B46: Staff Benefits | C46: 3115 | D46: =LEFT(C46:C46,1) -> 3 | E46: Educational and General | F46: 0010 | G46: Unemployment Compensation | H46: 33995 | I46: Wright, Angelina W. | J46: 31021 | K46: 0.00 | L46: 31021 | M46: 0 | N46: 0 | O46: 81996.55 | P46: 0 | Q46: 0 | R46: 81996.55 | S46: -50975.55
A47: 2012 | B47: Staff Benefits | C47: 3115 | D47: =LEFT(C47:C47,1) -> 3 | E47: Educational and General | F47: 0010 | G47: Unemployment Compensation | H47: 33995 | I47: Wright, Angelina W. | J47: 10000 | K47: 0.00 | L47: 10000 | M47: 0 | N47: 0 | O47: 25088.45 | P47: 0 | Q47: 0 | R47: 25088.45 | S47: 4911.55
A48: 2011 | B48: EHS and Risk Management | C48: 3181 | D48: =LEFT(C48:C48,1) -> 3 | E48: Educational and General | F48: 0010 | G48: SORM, Fund 001 | H48: 33996 | J48: 60000 | K48: 0.00 | L48: 60000 | M48: 0 | N48: 0 | O48: 0 | P48: 48757.64 | Q48: 0 | R48: 48757.64 | S48: 8139.15
A49: 2012 | B49: EHS and Risk Management | C49: 3181 | D49: =LEFT(C49:C49,1) -> 3 | E49: Educational and General | F49: 0010 | G49: SORM, Fund 001 | H49: 33996 | J49: 50000 | K49: 0.00 | L49: 50000 | M49: 0 | N49: 0 | O49: 0 | P49: 30567.24 | Q49: 0 | R49: 30567.24 | S49: 10189.76
A50: 2011 | B50: EHS and Risk Management | C50: 3181 | D50: =LEFT(C50:C50,1) -> 3 | E50: Educational and General | F50: 0010 | G50: SORM, Fund 227 | H50: 33997 | J50: 17369 | K50: 0.00 | L50: 17369 | M50: 0 | N50: 0 | O50: 0 | P50: 20472.21 | Q50: 0 | R50: 20472.21 | S50: 0
A51: 2012 | B51: EHS and Risk Management | C51: 3181 | D51: =LEFT(C51:C51,1) -> 3 | E51: Educational and General | F51: 0010 | G51: SORM, Fund 227 | H51: 33997 | J51: 10000 | K51: 0.00 | L51: 10000 | M51: 0 | N51: 0 | O51: 0 | P51: 11451.44 | Q51: 0 | R51: 11451.44 | S51: 3817.56
A52: 2012 | B52: Agriculture | C52: 2405 | D52: =LEFT(C52:C52,1) -> 2 | E52: Educational and General | F52: 0010 | G52: Agriculture | H52: 40005 | I52: Engdahl, Gilbert R. | J52: 490373 | K52: 0.00 | L52: 490373 | M52: 342193.03 | N52: 0 | O52: 0 | P52: 0 | Q52: 0 | R52: 342193.03 | S52: 164075.97
A53: 2012 | B53: Agriculture | C53: 2405 | D53: =LEFT(C53:C53,1) -> 2 | E53: Educational and General | F53: 0010 | G53: Agriculture Graduate Program | H53: 40006 | I53: Engdahl, Gilbert R. | J53: 0 | K53: 0.00 | L53: 0 | M53: 0 | N53: 0 | O53: 0 | P53: 2552.7 | Q53: 1215 | R53: 3767.7 | S53: 3732.3
A54: 2011 | B54: Art and Music | C54: 2410 | D54: =LEFT(C54:C54,1) -> 2 | E54: Educational and General | F54: 0010 | G54: Art and Music | H54: 40010 | I54: Scott, David | J54: 569664 | K54: 0.00 | L54: 569664 | M54: 637295.9 | N54: 0 | O54: 0 | P54: 0 | Q54: 0 | R54: 637295.9 | S54: 246.36
A55: 2012 | B55: Art and Music | C55: 2410 | D55: =LEFT(C55:C55,1) -> 2 | E55: Educational and General | F55: 0010 | G55: Art and Music | H55: 40010 | I55: Scott, David | J55: 657365 | K55: 0.00 | L55: 657365 | M55: 533577.85 | N55: 0 | O55: 0 | P55: 0 | Q55: 0 | R55: 533577.85 | S55: 159057.15
A56: 2012 | B56: Biology | C56: 2414 | D56: =LEFT(C56:C56,1) -> 2 | E56: Educational and General | F56: 0010 | G56: Biology | H56: 40013 | I56: Wilke, R. R. | J56: 919532 | K56: 0.00 | L56: 919532 | M56: 721897.17 | N56: 0 | O56: 0 | P56: 0 | Q56: 0 | R56: 721897.17 | S56: 213728.83
A57: 2012 | B57: Biology | C57: 2414 | D57: =LEFT(C57:C57,1) -> 2 | E57: Educational and General | F57: 0010 | G57: Biology Graduate Program | H57: 40014 | I57: Wilke, R. R. | J57: 0 | K57: 0.00 | L57: 0 | M57: 0 | N57: 0 | O57: 0 | P57: 3143.67 | Q57: 1311.25 | R57: 4454.92 | S57: 3870.08
A58: 2012 | B58: Chemistry and Biochemistry | C58: 2418 | D58: =LEFT(C58:C58,1) -> 2 | E58: Educational and General | F58: 0010 | G58: Chemistry and Biochemistry | H58: 40018 | I58: Osterhout, John J. | J58: 487350 | K58: 0.00 | L58: 487350 | M58: 388037.41 | N58: 0 | O58: 0 | P58: 0 | Q58: 0 | R58: 388037.41 | S58: 121058.59
A59: 2011 | B59: Communication, Mass Media & Theatre | C59: 2420 | D59: =LEFT(C59:C59,1) -> 2 | E59: Educational and General | F59: 0010 | G59: Communication, Mass Media & Theatre | H59: 40020 | I59: Wahl, Shawn T. | J59: 834907.43 | K59: 5890.43 | L59: 829017 | M59: 991380.78 | N59: 0 | O59: 0 | P59: 357.27 | Q59: 0 | R59: 991738.05 | S59: 34222.38
A60: 2012 | B60: Communication, Mass Media & Theatre | C60: 2420 | D60: =LEFT(C60:C60,1) -> 2 | E60: Educational and General | F60: 0010 | G60: Communication, Mass Media & Theatre | H60: 40020 | I60: Wahl, Shawn T. | J60: 822047 | K60: 0.00 | L60: 822047 | M60: 656287.72 | N60: 0 | O60: 0 | P60: 0 | Q60: 0 | R60: 656287.72 | S60: 206666.28
A61: 2011 | B61: Communication, Mass Media & Theatre | C61: 2420 | D61: =LEFT(C61:C61,1) -> 2 | E61: Educational and General | F61: 0010 | G61: Comm, Mass Media, Theatre Grad Prog | H61: 40021 | I61: Wahl, Shawn T. | J61: 3241 | K61: 649 | L61: 2592 | M61: 0 | N61: 0 | O61: 0 | P61: 6171.53 | Q61: 0 | R61: 6171.53 | S61: 888.03
A62: 2012 | B62: Communication, Mass Media & Theatre | C62: 2420 | D62: =LEFT(C62:C62,1) -> 2 | E62: Educational and General | F62: 0010 | G62: Comm, Mass Media, Theatre Grad Prog | H62: 40021 | I62: Wahl, Shawn T. | J62: 0 | K62: 0.00 | L62: 0 | M62: 0 | N62: 0 | O62: 0 | P62: 5567.75 | Q62: 1623.33 | R62: 7191.08 | S62: 308.92
A63: 2011 | B63: English and Modern Languages | C63: 2430 | D63: =LEFT(C63:C63,1) -> 2 | E63: Educational and General | F63: 0010 | G63: English and Modern Languages | H63: 40030 | I63: Musgrove, Laurence E. | J63: 693749 | K63: 0.00 | L63: 693749 | M63: 991997.13 | N63: 0 | O63: 0 | P63: 0 | Q63: 0 | R63: 991997.13 | S63: 20.37
A64: 2012 | B64: English and Modern Languages | C64: 2430 | D64: =LEFT(C64:C64,1) -> 2 | E64: Educational and General | F64: 0010 | G64: English and Modern Languages | H64: 40030 | I64: Musgrove, Laurence E. | J64: 1100324 | K64: 0.00 | L64: 1100324 | M64: 934022.28 | N64: 0 | O64: 0 | P64: 0 | Q64: 0 | R64: 934022.28 | S64: 258315.72
A65: 2011 | B65: English and Modern Languages | C65: 2430 | D65: =LEFT(C65:C65,1) -> 2 | E65: Educational and General | F65: 0010 | G65: English and Modern Lang Grad Prog | H65: 40031 | I65: Musgrove, Laurence E. | J65: 3780 | K65: 0.00 | L65: 3780 | M65: 0 | N65: 0 | O65: 0 | P65: 3412.03 | Q65: 0 | R65: 3412.03 | S65: 103.37
A66: 2012 | B66: English and Modern Languages | C66: 2430 | D66: =LEFT(C66:C66,1) -> 2 | E66: Educational and General | F66: 0010 | G66: English and Modern Lang Grad Prog | H66: 40031 | I66: Musgrove, Laurence E. | J66: 0 | K66: 0.00 | L66: 0 | M66: 0 | N66: 0 | O66: 0 | P66: 2051.04 | Q66: 1665.33 | R66: 3716.37 | S66: 783.63
A67: 2011 | B67: Political Science | C67: 2440 | D67: =LEFT(C67:C67,1) -> 2 | E67: Educational and General | F67: 0010 | G67: Political Science | H67: 40040 | I67: Jones, Laurence F. | J67: 316367 | K67: 0.00 | L67: 316367 | M67: 384143.55 | N67: 0 | O67: 0 | P67: 0 | Q67: 0 | R67: 384143.55 | S67: 99.97
A68: 2012 | B68: Political Science | C68: 2440 | D68: =LEFT(C68:C68,1) -> 2 | E68: Educational and General | F68: 0010 | G68: Political Science | H68: 40040 | I68: Jones, Laurence F. | J68: 0 | K68: 0.00 | L68: 462519 | M68: 53395.35 | N68: 0 | O68: 0 | P68: 0 | Q68: 0 | R68: 53395.35 | S68: 35596.65
A69: 2011 | B69: Political Science | C69: 2440 | D69: =LEFT(C69:C69,1) -> 2 | E69: Educational and General | F69: 0010 | G69: Political Science Graduate Program | H69: 40041 | I69: Jones, Laurence F. | J69: 2511 | K69: 0.00 | L69: 2511 | M69: 0 | N69: 0 | O69: 0 | P69: 1003.59 | Q69: 0 | R69: 1003.59 | S69: 1331.64
A70: 2011 | B70: History | C70: 2450 | D70: =LEFT(C70:C70,1) -> 2 | E70: Educational and General | F70: 0010 | G70: History | H70: 40050 | I70: Heineman, Kenneth J. | J70: 407741 | K70: 0.00 | L70: 407741 | M70: 414562.69 | N70: 0 | O70: 0 | P70: 0 | Q70: 0 | R70: 414562.69 | S70: -4189.69
A71: 2012 | B71: History | C71: 2450 | D71: =LEFT(C71:C71,1) -> 2 | E71: Educational and General | F71: 0010 | G71: History | H71: 40050 | I71: Heineman, Kenneth J. | J71: 545499 | K71: 0.00 | L71: =545499-462519 -> 82980 | M71: 388088.69 | N71: 0 | O71: 0 | P71: 0 | Q71: 0 | R71: 388088.69 | S71: 59328.31
A72: 2012 | B72: Mathematics and Computer Science | C72: 2465 | D72: =LEFT(C72:C72,1) -> 2 | E72: Educational and General | F72: 0010 | G72: Mathematics and Computer Science | H72: 40058 | I72: Zarnowski, Roger E. | J72: 952342 | K72: 0.00 | L72: 952342 | M72: 897317.32 | N72: 0 | O72: 0 | P72: 0 | Q72: 0 | R72: 897317.32 | S72: 255840.68
A73: 2011 | B73: Modern Languages | C73: 2460 | D73: =LEFT(C73:C73,1) -> 2 | E73: Educational and General | F73: 0010 | G73: Modern Languages | H73: 40060 | I73: Cody, Karen | J73: 462806 | K73: 0.00 | L73: 462806 | M73: 520996.91 | N73: 0 | O73: 0 | P73: 0 | Q73: 0 | R73: 520996.91 | S73: 900.09
A74: 2012 | B74: Physics | C74: 2475 | D74: =LEFT(C74:C74,1) -> 2 | E74: Educational and General | F74: 0010 | G74: Physics | H74: 40065 | I74: Wallace, Andrew B. | J74: 750779 | K74: 0.00 | L74: 750779 | M74: 516746.93 | N74: 0 | O74: 0 | P74: 0 | Q74: 0 | R74: 516746.93 | S74: 154590.07
A75: 2011 | B75: Psychology, Sociology, Social Work | C75: 2470 | D75: =LEFT(C75:C75,1) -> 2 | E75: Educational and General | F75: 0010 | G75: Psychology, Sociology & Social Work | H75: 40070 | I75: Davidson, William B. | J75: 743961 | K75: 0.00 | L75: 743961 | M75: 855632.48 | N75: 0 | O75: 0 | P75: 0 | Q75: 0 | R75: 855632.48 | S75: 568.52
A76: 2011 | B76: Psychology, Sociology, Social Work | C76: 2470 | D76: =LEFT(C76:C76,1) -> 2 | E76: Educational and General | F76: 0010 | G76: Psychology Graduate Program | H76: 40071 | I76: Davidson, William B. | J76: 19737 | K76: 0.00 | L76: 19737 | M76: 0 | N76: 0 | O76: 0 | P76: 13861.91 | Q76: 0 | R76: 13861.91 | S76: 4493.5
A77: 2011 | B77: Accounting, Economics, and Finance | C77: 2510 | D77: =LEFT(C77:C77,1) -> 2 | E77: Educational and General | F77: 0010 | G77: Accounting, Economics, & Finance | H77: 40090 | I77: Bankston, Thomas A. | J77: 804383 | K77: 0.00 | L77: 804383 | M77: 964208.08 | N77: 0 | O77: 0 | P77: 0 | Q77: 0 | R77: 964208.08 | S77: -79.94
A78: 2012 | B78: Accounting, Economics, and Finance | C78: 2510 | D78: =LEFT(C78:C78,1) -> 2 | E78: Educational and General | F78: 0010 | G78: Accounting, Economics, & Finance | H78: 40090 | I78: Bankston, Thomas A. | J78: 955391 | K78: 0.00 | L78: 955391 | M78: 744129.26 | N78: 0 | O78: 0 | P78: 0 | Q78: 0 | R78: 744129.26 | S78: 241672.74
A79: 2011 | B79: Accounting, Economics, and Finance | C79: 2510 | D79: =LEFT(C79:C79,1) -> 2 | E79: Educational and General | F79: 0010 | G79: Acctg, Eco, Finance Grad Program | H79: 40091 | I79: Bankston, Thomas A. | J79: 7938 | K79: 0.00 | L79: 7938 | M79: 0 | N79: 0 | O79: 0 | P79: 7851.95 | Q79: 0 | R79: 7851.95 | S79: 530.39
A80: 2012 | B80: Accounting, Economics, and Finance | C80: 2510 | D80: =LEFT(C80:C80,1) -> 2 | E80: Educational and General | F80: 0010 | G80: Acctg, Eco, Finance Grad Program | H80: 40091 | I80: Bankston, Thomas A. | J80: 0 | K80: 0.00 | L80: 0 | M80: 0 | N80: 0 | O80: 0 | P80: 1819.39 | Q80: 1980 | R80: 3799.39 | S80: 3700.61
A81: 2011 | B81: Aerospace Studies | C81: 2520 | D81: =LEFT(C81:C81,1) -> 2 | E81: Educational and General | F81: 0010 | G81: Aerospace Studies | H81: 40100 | I81: Magnan, Stephen W. | J81: 32863 | K81: 0.00 | L81: 32863 | M81: 32822.96 | N81: 0 | O81: 0 | P81: 0 | Q81: 0 | R81: 32822.96 | S81: 40.04
A82: 2012 | B82: Aerospace Studies | C82: 2520 | D82: =LEFT(C82:C82,1) -> 2 | E82: Educational and General | F82: 0010 | G82: Aerospace Studies | H82: 40100 | I82: Magnan, Stephen W. | J82: 33103 | K82: 0.00 | L82: 33103 | M82: 17826.09 | N82: 0 | O82: 0 | P82: 0 | Q82: 0 | R82: 17826.09 | S82: 15276.91
A83: 2011 | B83: Management and Marketing | C83: 2530 | D83: =LEFT(C83:C83,1) -> 2 | E83: Educational and General | F83: 0010 | G83: Management and Marketing | H83: 40110 | I83: Badgett, Tommy F. | J83: 1082443 | K83: 0.00 | L83: 1082443 | M83: 1215093.9 | N83: 0 | O83: 0 | P83: 0 | Q83: 0 | R83: 1215093.9 | S83: 120.07
... A89: 2012 | B89: Teacher Education | C89: 2630 | D89: =LEFT(C89:C89,1) -> 2 | E89: Educational and General | F89: 0010 | G89: Teacher Education | H89: 40160 | I89: Lucksinger, Linda N. | J89: 489163 | K89: 0.00 | L89: 489163 | M89: 380966.41 | N89: 0 | O89: 0 | P89: 0 | Q89: 0 | R89: 380966.41 | S89: 117156.59
A90: 2011 | B90: Teacher Education | C90: 2630 | D90: =LEFT(C90:C90,1) -> 2 | E90: Educational and General | F90: 0010 | G90: Teacher Education Graduate Program | H90: 40161 | I90: Miazga, John J. | J90: 15179.41 | K90: 2224.41 | L90: 12955 | M90: 0 | N90: 0 | O90: 0 | P90: 12142.8 | Q90: 0 | R90: 12142.8 | S90: 2549.76
A91: 2012 | B91: Teacher Education | C91: 2630 | D91: =LEFT(C91:C91,1) -> 2 | E91: Educational and General | F91: 0010 | G91: Teacher Education Graduate Program | H91: 40161 | I91: Miazga, John J. | J91: 0 | K91: 0.00 | L91: 0 | M91: 0 | N91: 0 | O91: 0 | P91: 5542.13 | Q91: 5677.35 | R91: 11219.48 | S91: 15780.52
A92: 2011 | B92: Curriculum and Instruction | C92: 2610 | D92: =LEFT(C92:C92,1) -> 2 | E92: Educational and General | F92: 0010 | G92: Curriculum and Instruction | H92: 40165 | I92: Summerlin, James A. | J92: 465780 | K92: 0.00 | L92: 465780 | M92: 690630.58 | N92: 0 | O92: 0 | P92: 0 | Q92: 0 | R92: 690630.58 | S92: -1323.58
A93: 2012 | B93: Curriculum and Instruction | C93: 2610 | D93: =LEFT(C93:C93,1) -> 2 | E93: Educational and General | F93: 0010 | G93: Curriculum and Instruction | H93: 40165 | I93: Summerlin, James A. | J93: 417977 | K93: 0.00 | L93: 417977 | M93: 469381.73 | N93: 0 | O93: 0 | P93: 0 | Q93: 0 | R93: 469381.73 | S93: 140382.27
A94: 2011 | B94: Curriculum and Instruction | C94: 2610 | D94: =LEFT(C94:C94,1) -> 2 | E94: Educational and General | F94: 0010 | G94: Curriculum and Instruction Graduate | H94: 40166 | I94: Miazga, John J. | J94: 11915.9 | K94: 11915.9 | L94: 0 | M94: 3132 | N94: 30809.63 | O94: 0 | P94: 57316.14 | Q94: 0 | R94: 91257.77 | S94: 20885.13
A95: 2012 | B95: Curriculum and Instruction | C95: 2610 | D95: =LEFT(C95:C95,1) -> 2 | E95: Educational and General | F95: 0010 | G95: Curriculum and Instruction Graduate | H95: 40166 | I95: Miazga, John J. | J95: 0 | K95: 0.00 | L95: 0 | M95: 0 | N95: 14271.88 | O95: 0 | P95: 2769.87 | Q95: 6722.75 | R95: 23764.5 | S95: 58735.5
A96: 2011 | B96: Kinesiology | C96: 2620 | D96: =LEFT(C96:C96,1) -> 2 | E96: Educational and General | F96: 0010 | G96: Kinesiology | H96: 40170 | I96: Snowden, Steven R. | J96: 693007 | K96: 0.00 | L96: 693007 | M96: 758382.16 | N96: 0 | O96: 0 | P96: 0 | Q96: 0 | R96: 758382.16 | S96: -533.28
A97: 2011 | B97: Kinesiology | C97: 2620 | D97: =LEFT(C97:C97,1) -> 2 | E97: Educational and General | F97: 0010 | G97: Kinesiology Graduate Program | H97: 40171 | I97: Snowden, Steven R. | J97: 4838.6 | K97: 977.6 | L97: 3861 | M97: 0 | N97: 0 | O97: 0 | P97: 5250.04 | Q97: 0 | R97: 5250.04 | S97: 2318.29
A98: 2011 | B98: Agriculture | C98: 2710 | D98: =LEFT(C98:C98,1) -> 2 | E98: Educational and General | F98: 0010 | G98: Agriculture | H98: 40210 | I98: Engdahl, Gilbert R. | J98: 556025 | K98: 0.00 | L98: 556025 | M98: 480538.92 | N98: 0 | O98: 0 | P98: 0 | Q98: 0 | R98: 480538.92 | S98: -7326.42
A99: 2011 | B99: Agriculture | C99: 2710 | D99: =LEFT(C99:C99,1) -> 2 | E99: Educational and General | F99: 0010 | G99: Agriculture Graduate Program | H99: 40211 | I99: Engdahl, Gilbert R. | J99: 6292 | K99: 154 | L99: 6138 | M99: 0 | N99: 5703.6 | O99: 0 | P99: 15.25 | Q99: 0 | R99: 5718.85 | S99: 164
A100: 2011 | B100: Biology | C100: 2720 | D100: =LEFT(C100:C100,1) -> 2 | E100: Educational and General | F100: 0010 | G100: Biology | H100: 40220 | I100: Wilke, R. R. | J100: 919344 | K100: 0.00 | L100: 919344 | M100: 948404.27 | N100: 0 | O100: 0 | P100: 0 | Q100: 0 | R100: 948404.27 | S100: 19.96
A101: 2011 | B101: Chemistry and Biochemistry | C101: 2730 | D101: =LEFT(C101:C101,1) -> 2 | E101: Educational and General | F101: 0010 | G101: Chemistry and Biochemistry | H101: 40230 | I101: Osterhout, John J. | J101: 494568 | K101: 0.00 | L101: 494568 | M101: 538860.62 | N101: 0 | O101: 0 | P101: 0 | Q101: 0 | R101: 538860.62 | S101: 20.67
A102: 2011 | B102: Computer Science | C102: 2740 | D102: =LEFT(C102:C102,1) -> 2 | E102: Educational and General | F102: 0010 | G102: Computer Science | H102: 40235 | I102: Roden, Timothy E. | J102: 427121 | K102: 0.00 | L102: 427121 | M102: 457511.02 | N102: 0 | O102: 0 | P102: 0 | Q102: 0 | R102: 457511.02 | S102: -40.08
A103: 2011 | B103: Mathematics | C103: 2750 | D103: =LEFT(C103:C103,1) -> 2 | E103: Educational and General | F103: 0010 | G103: Mathematics | H103: 40240 | I103: Zarnowski, Roger E. | J103: 654238 | K103: 0.00 | L103: 654238 | M103: 888190.81 | N103: 0 | O103: 0 | P103: 0 | Q103: 0 | R103: 888190.81 | S103: 59.74
A104: 2011 | B104: Nursing and Rehabilitation Sciences | C104: 2810 | D104: =LEFT(C104:C104,1) -> 2 | E104: Educational and General | F104: 0010 | G104: Nursing Graduate Program | H104: 40266 | I104: Wilkinson, Susan C. | J104: 11574 | K104: 0.00 | L104: 11574 | M104: 0 | N104: 0 | O104: 0 | P104: 9325.03 | Q104: 791.1 | R104: 10116.13 | S104: 647.69
A105: 2012 | B105: Nursing and Rehabilitation Sciences | C105: 2810 | D105: =LEFT(C105:C105,1) -> 2 | E105: Educational and General | F105: 0010 | G105: Nursing Graduate Program | H105: 40266 | I105: Wilkinson, Susan C. | J105: 791.1 | K105: 791.1 | L105: 0 | M105: 0 | N105: 0 | O105: 0 | P105: 0 | Q105: 791.1 | R105: 791.1 | S105: 0
...

Sheet University Cost
A1: University Expenses Supported by E&G and Designated Tuition Fee
A2: Communications & Marketing | B2: 1 | C2: Branding & Marketing | D2: 183708 | E2: 0100-60102
A3: Communications & Marketing | B3: 1 | C3: PR Marketing-ASU Magazine | D3: 74171 | E3: 0100-60102
A4: Communications & Marketing | B4: 1 | C4: Targeted markting-Publications | D4: 76560 | E4: 0100-60102 | G4: =SUM(D2:D4) -> 334439
A5: HR | B5: 3 | C5: Background checks | D5: 8500 | E5: 0100-60200 | F5: C12ABGI1
A6: HR | B6: 3 | C6: EAP | D6: 10000 | E6: 0100-60200 | F6: C12UTHS1
A7: HR | B7: 3 | C7: Recruiting Advertisement | D7: 3000 | E7: 0100-60201 | F7: C12HIGH1
A8: HR | B8: 3 | C8: Recruiting Advertisement | D8: 4600 | E8: 0100-60201 | F8: C12IHED1
A9: HR | B9: 3 | C9: Recruiting Advertisement | D9: 1200 | E9: 0100-60201 | F9: C12LIHE1
A10: HR | B10: 3 | C10: Recruiting Advertisement | D10: 7000 | E10: 0100-60201 | F10: C12CHED
A11: HR | B11: 3 | C11: Applicant Tracking | D11: 17000 | E11: 0100-60201 | F11: C12ADM1
A12: HR | B12: 3 | C12: Salary Data and Training | D12: 7000 | E12: 0100-60200
A13: Controller's | B13: 3 | C13: System Office Operations | D13: 272731 | E13: 0100-60165
A14: Controller's | B14: 3 | C14: Depository Bank Service Charge | D14: =7000-5000 -> 2000 | E14: 0100-60180
A15: Controller's | B15: 3 | C15: Hope Tax Reporting | D15: 12500 | E15: 0100-60190
A16: Controller's | B16: 3 | C16: Credit Card Services | D16: 168000 | E16: 0100-60215
A17: Controller's | B17: 3 | C17: Financial Aid Audit | D17: 30000 | E17: 0100-60299
A18: Postoffice | B18: 3 | C18: Bulk Mail Permits | D18: =630+985 -> 1615 | E18: 0100-
A19: Budget Office | B19: 3 | C19: Print/distribute LAR's & Budgets | D19: 1100 | E19: 0100-60170
A20: Payroll Services | B20: 3 | C20: W-2's | D20: 1100 | E20: 0100-60172
A21: IT | B21: 3 | C21: Banner | D21: =216136.47*0.3333 -> 72038.285 | E21: 0100-60105 (.33)/0120-61460 (.33)/1270-65691 (.33) | F21: P1200191
A22: IT | B22: 3 | C22: Stellen,Captova Support (Imagine) | D22: =19699*0.75 -> 14774.25 | E22: 0100-60105 (.75) 1270-65691 (.25) | F22: P1200165
A23: IT | B23: 3 | C23: Blackboard Mobile | D23: 19110 | E23: 0100-60105 | F23: R1200458
A24: IT | B24: 3 | C24: Time Clock Plus - Data Management | D24: 2901 | E24: 0100-60105 | F24: P1200520
A25: IT | B25: 3 | C25: Microsoft campus license agreement | D25: =39729.24*0.6 -> 23837.544 | E25: 0100-60105 (.60) 0120-61460 (.40) | F25: P1200551
A26: IT | B26: 3 | C26: evsions, Form Fusion and Intellicheck for A/P and payroll | D26: 10368 | E26: 0100-60105 | F26: P1200186
A27: IT | B27: 3 | C27: Cashnet | D27: 39815.27 | E27: 0100-60105
A28: IT | B28: 3 | C28: Panapto Silver Support | D28: 13600
A29: IT | B29: 3 | C29: Cognos Renewal Support | D29: =7185*0.75 -> 5388.75 | E29: 0100-60105 (.75) 0120-65691 (.25) | F29: P1200190
A30: IT | B30: 3 | C30: Oracle maintenance Support | D30: =66049.77*0.4 -> 26419.908 | E30: 0100-60105/0100-60105 (.40) 0120-61460 (.4) 1270-65691 (.20) | F30: P1200553
A31: IT | B31: 3 | C31: Adobe Acrobat Pro | D31: 5759.6 | E31: 0100-60105 | F31: P1200206
A32: IT | B32: 3 | C32: Clean Address 1 year subscription | D32: 4100 | E32: 0100-60105 | F32: P1200192
A33: IT | B33: 3 | C33: Cable TV Service | D33: 3468 | E33: 0100-60105
A34: IT | B34: 3 | C34: Appworx | D34: =11726*0.75 -> 8794.5 | E34: 0100-60105 (.75) 1270-65691 (.75) | F34: 11726
B35: 3 | C35: General Contingency | D35: 250000 | E35: 0100-61265
A36: Risk Management | B36: 3 | C36: Employee Insurance (Bond) | D36: 5585 | E36: 0100-60224
A37: Risk Management | B37: 3 | C37: Property Insurance | D37: 103135 | E37: 0100-60225
A38: Risk Management | B38: 3 | C38: Auto Insurance | D38: 29349 | E38: 0100-60226
A39: Risk Management | B39: 3 | C39: SORM | D39: =42000+48758+20473 -> 111231 | E39: 0100-60390/0010-33996/0010-33997
B40: 3 | C40: Transfer to Other Funds (Athletics) | D40: 1894660 | E40: 0100-61255
B41: 3 | C41: Transfer to Unexpended Plant | E41: 0100-61260
B42: 3 | C42: Temporary Office Debt Service | D42: 75175 | E42: 0100-61267
B43: 3 | C43: Revenue Bond Series 1998 | D43: 645000 | E43: 0100-61270
B44: 3 | C44: Revenue Bond Serires 2002 | D44: 7280 | E44: 0100-61275
B45: 3 | C45: Insurance | D45: 1602015
B46: 3 | C46: OASI | D46: 913262
B47: 3 | C47: Unemployment Comp | D47: 75000
B48: 3 | C48: TRS | D48: 822816
B49: 3 | C49: ORP | D49: 336986 | G49: =SUM(D5:D49) -> 7669215.1
A50: Admissions | B50: 5 | C50: Postage | D50: 94876 | E50: 0100-60304
A51: Admissions | B51: 5 | C51: Student Search | D51: 83000 | E51: 0100-60316
A52: Admissions | B52: 5 | C52: ASU College Days | D52: 22168 | E52: 0100-60340
A53: Admissions | B53: 5 | C53: BRM | D53: 18495
A54: Admissions | B54: 5 | C54: THECB - Apply Texas Fees | D54: 3584
A55: Admissions | B55: 5 | C55: Pitney Bowes | D55: 3280
A56: Admissions | B56: 5 | C56: Zinch Names | D56: 10000
A57: Admissions | B57: 5 | C57: Print Shop | D57: 2000
A58: Admissions | B58: 5 | C58: Texas 4-H Ag Foundation | D58: 877
A59: Admissions | B59: 5 | C59: Vatat Booth Rental FFA Ag | D59: 975
A60: Registrar | B60: 5 | C60: Graduation | D60: =5026+26134 -> 31160
A61: Registrar | B61: 5 | C61: Transcript Paper & Seals | D61: 10300
A62: Registrar | B62: 5 | C62: BOR reports - 20+ bppls 3X a year | D62: 800
A63: Registrar | B63: 5 | C63: Postcards for Bacterial Meningitis | D63: 2500
A64: Student Affairs | B64: 5 | C64: SOAR | D64: =17826+27376 -> 45202
A65: Student Affairs | B65: 5 | C65: ?? ADA | D65: =13898+25149 -> 39047 | G65: =SUM(D50:D65) -> 368264
A66: Utilities | B66: 7 | C66: Purchased Utilities - Electricity | D66: =116654.88+1032767.32 -> 1149422.2 | E66: 46510/61156
A67: Utilities | B67: 7 | C67: Purchased Utilities | D67: 164988.86 | E67: 61155
A68: Utilities | B68: 7 | C68: Purchased Utilies - Fuel | D68: 120671.57 | E68: 61157
A69: Utilities | B69: 7 | C69: Purchased Utilities - Water | D69: 79384.19 | E69: 61158
A70: Utilities | B70: 7 | C70: Purchased Utilities - Sewer | D70: 28531.66 | E70: 61159
A71: Utilities | B71: 7 | C71: Plant Renewal | D71: 183334.4 | E71: 61165 | G71: =SUM(D66:D71) -> 1726332.9
C72: Longevity | D72: 300000 | G72: =SUM(D72) -> 300000
A73: Total University Cost | D73: =SUM(D2:D72) -> 10398251
A76: University Expenses supported by other fees
A77: IT | C77: Blackboard Licensing | D77: 163024.75 | E77: 0115-60601 | F77: R1200458
A78: IT | C78: Turnitin License | D78: 6499.9 | E78: 0101-60105 | F78: P1200181
A79: IT | C79: Adobe Cold Fusion | D79: 1372 | E79: 0120-61460
A80: IT | C80: Respondus | D80: 7735 | E80: 0120-61460
A81: IT | C81: Securexam Brower/Password | D81: 700 | E81: 0120-61460
A84: Denotes that expense is split between other fee revenue
