Workbook

Sheet WFIS Data
B1: U.S. Department of Energy Report of Contractor Expenditures for Employee Supplemental Compensation
B3: DoE Summary for Calendar Year 2009
A4: OP Office: | D4: Sample Operations Office
A5: Facility: | D5: Sample Facility
A6: Contractor: | D6: Sample Contractor
A7: Contract Number:
D9: No. of Employees
A10: Exempt: | D10: 800
A11: Bargaining Unit: | D11: 500
A12: Nonexempt Nonbargaining Unit: | D12: 100
A13: Retiree: | D13: 600
A15: Types of Expenditure | D15: Total
A16: Gross Payroll | D16: 100000000
A17: Annual Base Pay | D17: 94000000
A18: Straight-Time Pay Worked: | D18: 80000000
A19: Paid-Time off: | D19: 14000000
A20: Vacation Pay | D20: 7000000
A21: Vacation Pay in Lieu: | D21: 0
A22: Holiday Pay: | D22: 4000000
A23: Holiday Pay in Lieu: | D23: 0
A24: Sick Leave Pay: | D24: 2000000
A25: Personal Leave Bank: | D25: 1000000
A26: Personal Leave Pay: | D26: 0
A27: Parental Leave: | D27: 0
... A93: TOTAL COMPENSATION | D93: 143500000

Sheet BLS Table Data
A2: December 2009 Bureau of Labor Statistics Table Data
G3: 0.4 | H3: =1-G3 -> 0.6
D4: US Bureau of Labor Statistics Wtd Ave | E4: US Bureau of Labor Statistics Wtd Ave | F4: US Bureau of Labor Statistics Wtd Ave | G4: US Bureau of Labor Statistics Table 5 | H4: US Bureau of Labor Statistics Table 8
D5: Percent of Payroll | E5: Cost per FTE | F5: Cost per hour | G5: Mgmt, professional & related | H5: 500 workers or more
A6: A. | B6: PAYROLL
C7: Total Compensation | D7: =F7/F$8 -> 1.2394897 | E7: =F7*2080 -> 88920 | F7: =ROUND(G$3*G7+H$3*H7,2) -> 42.75 | G7: 48.19 | H7: 39.13
C8: Payroll | D8: =F8/F$8 -> 1 | E8: =F8*2080 -> 71739.2 | F8: =ROUND(G$3*G8+H$3*H8,2) -> 34.49 | G8: =G7-G38-G42 -> 39.82 | H8: =H7-H38-H42 -> 30.94
A10: B. | B10: PAID LEAVE
C11: Vacation | D11: =F11/F$8 -> 0.055088431 | E11: =F11*2080 -> 3952 | F11: =ROUND(G$3*G11+H$3*H11,2) -> 1.9 | G11: 2.09 | H11: 1.78
C12: Holidays | D12: =F12/F$8 -> 0.031893302 | E12: =F12*2080 -> 2288 | F12: =ROUND(G$3*G12+H$3*H12,2) -> 1.1 | G12: 1.26 | H12: 1
C13: Sick and Personal | D13: =F13/F$8 -> 0.018556103 | E13: =F13*2080 -> 1331.2 | F13: =ROUND(G$3*G13+H$3*H13,2) -> 0.64 | G13: =0.53+0.17 -> 0.7 | H13: =0.45+0.15 -> 0.6
C14: TOTAL B | D14: =SUM(D11:D13) -> 0.10553784 | E14: =SUM(E11:E13) -> 7571.2 | F14: =SUM(F11:F13) -> 3.64 | G14: =SUM(G11:G13) -> 4.05 | H14: =SUM(H11:H13) -> 3.38
A16: C. | B16: SUPPLEMENTAL PAY
C17: Overtime and premium | D17: =F17/F$8 -> 0.0089881125 | E17: =F17*2080 -> 644.8 | F17: =ROUND(G$3*G17+H$3*H17,2) -> 0.31 | G17: 0.19 | H17: 0.39
C18: Shift differentials | D18: =F18/F$8 -> 0.0049289649 | E18: =F18*2080 -> 353.6 | F18: =ROUND(G$3*G18+H$3*H18,2) -> 0.17 | G18: 0.13 | H18: 0.2
C19: Nonproduction bonuses | D19: =F19/F$8 -> 0.02928385 | E19: =F19*2080 -> 2100.8 | F19: =ROUND(G$3*G19+H$3*H19,2) -> 1.01 | G19: 1.32 | H19: 0.81
C20: TOTAL C | D20: =SUM(D17:D19) -> 0.043200928 | E20: =SUM(E17:E19) -> 3099.2 | F20: =SUM(F17:F19) -> 1.49 | G20: =SUM(G17:G19) -> 1.64 | H20: =SUM(H17:H19) -> 1.4
A22: D. | B22: INSURANCE
C23: Life | D23: =F23/F$8 -> 0.0020295738 | E23: =F23*2080 -> 145.6 | F23: =ROUND(G$3*G23+H$3*H23,2) -> 0.07 | G23: 0.08 | H23: 0.07
C24: Health | D24: =F24/F$8 -> 0.090750942 | E24: =F24*2080 -> 6510.4 | F24: =ROUND(G$3*G24+H$3*H24,2) -> 3.13 | G24: 2.94 | H24: 3.26
C25: Short-Term Disability | D25: =F25/F$8 -> 0.0028993911 | E25: =F25*2080 -> 208 | F25: =ROUND(G$3*G25+H$3*H25,2) -> 0.1 | G25: 0.09 | H25: 0.1
C26: Long-Term Disability | D26: =F26/F$8 -> 0.002609452 | E26: =F26*2080 -> 187.2 | F26: =ROUND(G$3*G26+H$3*H26,2) -> 0.09 | G26: 0.09 | H26: 0.09
C27: TOTAL D | D27: =SUM(D23:D26) -> 0.098289359 | E27: =SUM(E23:E26) -> 7051.2 | F27: =SUM(F23:F26) -> 3.39 | G27: =SUM(G23:G26) -> 3.2 | H27: =SUM(H23:H26) -> 3.52
A29: E. | B29: RETIREMENT AND SAVINGS
C30: Defined Benefit Pension Plan | D30: =F30/F$8 -> 0.021455494 | E30: =F30*2080 -> 1539.2 | F30: =ROUND(G$3*G30+H$3*H30,2) -> 0.74 | G30: 0.6 | H30: 0.84
C31: Defined Contribution | D31: =F31/F$8 -> 0.031893302 | E31: =F31*2080 -> 2288 | F31: =ROUND(G$3*G31+H$3*H31,2) -> 1.1 | G31: 1.21 | H31: 1.02
C32: TOTAL E | D32: =SUM(D30:D31) -> 0.053348797 | E32: =SUM(E30:E31) -> 3827.2 | F32: =SUM(F30:F31) -> 1.84 | G32: =SUM(G30:G31) -> 1.81 | H32: =SUM(H30:H31) -> 1.86
A34: F. | B34: LEGALLY REQUIRED PAYMENTS:
C35: Social Security and Medicare | D35: =F35/F$8 -> 0.0719049 | E35: =F35*2080 -> 5158.4 | F35: =ROUND(G$3*G35+H$3*H35,2) -> 2.48 | G35: 2.82 | H35: 2.26
C36: Federal and State Unemployment Payments | D36: =F36/F$8 -> 0.0049289649 | E36: =F36*2080 -> 353.6 | F36: =ROUND(G$3*G36+H$3*H36,2) -> 0.17 | G36: =0.03+0.15 -> 0.18 | H36: =0.03+0.13 -> 0.16
C37: Workers' Compensation | D37: =F37/F$8 -> 0.011017686 | E37: =F37*2080 -> 790.4 | F37: =ROUND(G$3*G37+H$3*H37,2) -> 0.38 | G37: 0.36 | H37: 0.39
C38: TOTAL F | D38: =SUM(D35:D37) -> 0.087851551 | E38: =SUM(E35:E37) -> 6302.4 | F38: =SUM(F35:F37) -> 3.03 | G38: =SUM(G35:G37) -> 3.36 | H38: =SUM(H35:H37) -> 2.81
A40: G. | B40: COST STUDY BENEFITS
C41: Paid Leave | D41: =D14 -> 0.10553784 | E41: =E14 -> 7571.2 | F41: =F14 -> 3.64 | G41: =G14 -> 4.05 | H41: =H14 -> 3.38
C42: Insurance plus Retirement and Savings | D42: =D27+D32 -> 0.15163816 | E42: =E27+E32 -> 10878.4 | F42: =F27+F32 -> 5.23 | G42: =G27+G32 -> 5.01 | H42: =H27+H32 -> 5.38
C43: Total G | D43: =SUM(D41:D42) -> 0.25717599 | E43: =SUM(E41:E42) -> 18449.6 | F43: =SUM(F41:F42) -> 8.87 | G43: =SUM(G41:G42) -> 9.06 | H43: =SUM(H41:H42) -> 8.76
A45: H. | B45: COST STUDY PAYROLL AND BENEFITS
C46: Payroll | D46: =D8 -> 1 | E46: =E8 -> 71739.2 | F46: =F8 -> 34.49 | G46: =G8 -> 39.82 | H46: =H8 -> 30.94
C47: Benefits | D47: =D43 -> 0.25717599 | E47: =E43 -> 18449.6 | F47: =F43 -> 8.87 | G47: =G43 -> 9.06 | H47: =H43 -> 8.76
C48: Total H | D48: =SUM(D46:D47) -> 1.257176 | E48: =SUM(E46:E47) -> 90188.8 | F48: =SUM(F46:F47) -> 43.36 | G48: =SUM(G46:G47) -> 48.88 | H48: =SUM(H46:H47) -> 39.7

Sheet Cost Study
A1: ='WFIS Data'!$D$5 -> Sample Facility
A2: ='WFIS Data'!$D$6 -> Sample Contractor
D3: =A1 -> Sample Facility | F3: US Bureau of Labor Statistics Wtd Ave | G3: =D3 -> Sample Facility | J3: US Bureau of Labor Statistics Wtd Ave | K3: =D3 -> Sample Facility | L3: US Bureau of Labor Statistics Wtd Ave
D4: Actual Amount | E4: Percent of Payroll | F4: Percent of Payroll | G4: Percent Above Average | H4: Cost per FTE | I4: Per Capita Cost Ratio | J4: Cost per FTE | K4: Cost per hour | L4: Cost per hour
A5: A. | B5: PAYROLL
C6: Total Compensation | D6: =D7+D37+D41 -> 136500000 | E6: =D6/D$7 -> 1.365 | F6: =L6/L$7 -> 1.2394897 | H6: =K6*2080 -> 97500 | J6: =L6*2080 -> 88920 | K6: =D6/D$46 -> 46.875 | L6: ='BLS Table Data'!F7 -> 42.75
C7: Payroll | D7: ='WFIS Data'!$D$16-'WFIS Data'!$D$33-SUM('WFIS Data'!D42:D43)-'WFIS Data'!$D$47 -> 100000000 | E7: =D7/D$7 -> 1 | F7: =L7/L$7 -> 1 | H7: =K7*2080 -> 71428.571 | J7: =L7*2080 -> 71739.2 | K7: =D7/D$46 -> 34.340659 | L7: ='BLS Table Data'!F8 -> 34.49
A9: B. | B9: PAID LEAVE
C10: Vacation | D10: ='WFIS Data'!$D$20+'WFIS Data'!$D$21 -> 7000000 | E10: =D10/D$7 -> 0.07 | F10: =L10/L$7 -> 0.055088431 | H10: =K10*2080 -> 5000 | J10: =L10*2080 -> 3952 | K10: =D10/D$46 -> 2.4038462 | L10: ='BLS Table Data'!F11 -> 1.9
C11: Holidays | D11: ='WFIS Data'!$D$22+'WFIS Data'!$D$23 -> 4000000 | E11: =D11/D$7 -> 0.04 | F11: =L11/L$7 -> 0.031893302 | H11: =K11*2080 -> 2857.1429 | J11: =L11*2080 -> 2288 | K11: =D11/D$46 -> 1.3736264 | L11: ='BLS Table Data'!F12 -> 1.1
C12: Sick and Personal | D12: =SUM('WFIS Data'!D24:D29) -> 3000000 | E12: =D12/D$7 -> 0.03 | F12: =L12/L$7 -> 0.018556103 | H12: =K12*2080 -> 2142.8571 | J12: =L12*2080 -> 1331.2 | K12: =D12/D$46 -> 1.0302198 | L12: ='BLS Table Data'!F13 -> 0.64
C13: TOTAL B | D13: =SUM(D10:D12) -> 14000000 | E13: =SUM(E10:E12) -> 0.14 | F13: =SUM(F10:F12) -> 0.10553784 | G13: =E13-F13 -> 0.034462163 | H13: =SUM(H10:H12) -> 10000 | I13: =H13/J13 -> 1.3207946 | J13: =SUM(J10:J12) -> 7571.2 | K13: =SUM(K10:K12) -> 4.8076923 | L13: ='BLS Table Data'!F14 -> 3.64
A15: C. | B15: SUPPLEMENTAL PAY
C16: Overtime and premium | D16: ='WFIS Data'!$D$30 -> 3000000 | E16: =D16/D$7 -> 0.03 | F16: =L16/L$7 -> 0.0089881125 | H16: =K16*2080 -> 2142.8571 | J16: =L16*2080 -> 644.8 | K16: =D16/D$46 -> 1.0302198 | L16: ='BLS Table Data'!F17 -> 0.31
C17: Shift differentials | D17: =SUM('WFIS Data'!D35:D36)+SUM('WFIS Data'!D42:D51) -> 500000 | E17: =D17/D$7 -> 0.005 | F17: =L17/L$7 -> 0.0049289649 | H17: =K17*2080 -> 357.14286 | J17: =L17*2080 -> 353.6 | K17: =D17/D$46 -> 0.1717033 | L17: ='BLS Table Data'!F18 -> 0.17
C18: Nonproduction bonuses | D18: =SUM('WFIS Data'!D37:D41) -> 2500000 | E18: =D18/D$7 -> 0.025 | F18: =L18/L$7 -> 0.02928385 | H18: =K18*2080 -> 1785.7143 | J18: =L18*2080 -> 2100.8 | K18: =D18/D$46 -> 0.85851648 | L18: ='BLS Table Data'!F19 -> 1.01
C19: TOTAL C | D19: =SUM(D16:D18) -> 6000000 | E19: =SUM(E16:E18) -> 0.06 | F19: =SUM(F16:F18) -> 0.043200928 | G19: =E19-F19 -> 0.016799072 | H19: =SUM(H16:H18) -> 4285.7143 | I19: =H19/J19 -> 1.3828453 | J19: =SUM(J16:J18) -> 3099.2 | K19: =SUM(K16:K18) -> 2.0604396 | L19: ='BLS Table Data'!F20 -> 1.49
A21: D. | B21: INSURANCE
C22: Life | D22: ='WFIS Data'!$D$64 -> 500000 | E22: =D22/D$7 -> 0.005 | F22: =L22/L$7 -> 0.0020295738 | H22: =K22*2080 -> 357.14286 | J22: =L22*2080 -> 145.6 | K22: =D22/D$46 -> 0.1717033 | L22: ='BLS Table Data'!$F$23 -> 0.07
C23: Health | D23: =SUM('WFIS Data'!D68:D77)+'WFIS Data'!$D$80 -> 11500000 | E23: =D23/D$7 -> 0.115 | F23: =L23/L$7 -> 0.090750942 | H23: =K23*2080 -> 8214.2857 | J23: =L23*2080 -> 6510.4 | K23: =D23/D$46 -> 3.9491758 | L23: ='BLS Table Data'!F24 -> 3.13
C24: Short-Term Disability | D24: ='WFIS Data'!$D$78 -> 250000 | E24: =D24/D$7 -> 0.0025 | F24: =L24/L$7 -> 0.0028993911 | H24: =K24*2080 -> 178.57143 | J24: =L24*2080 -> 208 | K24: =D24/D$46 -> 0.085851648 | L24: ='BLS Table Data'!F25 -> 0.1
C25: Long-Term Disability | D25: ='WFIS Data'!$D$79 -> 250000 | E25: =D25/D$7 -> 0.0025 | F25: =L25/L$7 -> 0.002609452 | H25: =K25*2080 -> 178.57143 | J25: =L25*2080 -> 187.2 | K25: =D25/D$46 -> 0.085851648 | L25: ='BLS Table Data'!F26 -> 0.09
C26: TOTAL D | D26: =SUM(D22:D25) -> 12500000 | E26: =SUM(E22:E25) -> 0.125 | F26: =SUM(F22:F25) -> 0.098289359 | G26: =E26-F26 -> 0.026710641 | H26: =SUM(H22:H25) -> 8928.5714 | I26: =H26/J26 -> 1.2662485 | J26: =SUM(J22:J25) -> 7051.2 | K26: =SUM(K22:K25) -> 4.2925824 | L26: =SUM(L22:L25) -> 3.39
A28: E. | B28: RETIREMENT AND SAVINGS
C29: Defined Benefit | D29: ='WFIS Data'!$D$84 -> 10000000 | E29: =D29/D$7 -> 0.1 | F29: =L29/L$7 -> 0.021455494 | H29: =K29*2080 -> 7142.8571 | J29: =L29*2080 -> 1539.2 | K29: =D29/D$46 -> 3.4340659 | L29: ='BLS Table Data'!F30 -> 0.74
C30: Defined Contribution | D30: =MAX('WFIS Data'!D82:D83)+SUM('WFIS Data'!D85:D86) -> 6000000 | E30: =D30/D$7 -> 0.06 | F30: =L30/L$7 -> 0.031893302 | H30: =K30*2080 -> 4285.7143 | J30: =L30*2080 -> 2288 | K30: =D30/D$46 -> 2.0604396 | L30: ='BLS Table Data'!F31 -> 1.1
C31: TOTAL E | D31: =SUM(D29:D30) -> 16000000 | E31: =SUM(E29:E30) -> 0.16 | F31: =SUM(F29:F30) -> 0.053348797 | G31: =E31-F31 -> 0.1066512 | H31: =SUM(H29:H30) -> 11428.571 | I31: =H31/J31 -> 2.9861443 | J31: =SUM(J29:J30) -> 3827.2 | K31: =SUM(K29:K30) -> 5.4945055 | L31: ='BLS Table Data'!F32 -> 1.84
A33: F. | B33: LEGALLY REQUIRED PAYMENTS:
C34: Social Security and Medicare | D34: =SUM('WFIS Data'!D54:D55) -> 7000000 | E34: =D34/D$7 -> 0.07 | F34: =L34/L$7 -> 0.0719049 | H34: =K34*2080 -> 5000 | J34: =L34*2080 -> 5158.4 | K34: =D34/D$46 -> 2.4038462 | L34: ='BLS Table Data'!F35 -> 2.48
C35: Federal and State Unemployment Payments | D35: ='WFIS Data'!$D$56 -> 400000 | E35: =D35/D$7 -> 0.004 | F35: =L35/L$7 -> 0.0049289649 | H35: =K35*2080 -> 285.71429 | J35: =L35*2080 -> 353.6 | K35: =D35/D$46 -> 0.13736264 | L35: ='BLS Table Data'!F36 -> 0.17
C36: Workers' Compensation | D36: =SUM('WFIS Data'!D60:D63) -> 600000 | E36: =D36/D$7 -> 0.006 | F36: =L36/L$7 -> 0.011017686 | H36: =K36*2080 -> 428.57143 | J36: =L36*2080 -> 790.4 | K36: =D36/D$46 -> 0.20604396 | L36: ='BLS Table Data'!F37 -> 0.38
C37: TOTAL F | D37: =SUM(D34:D36) -> 8000000 | E37: =SUM(E34:E36) -> 0.08 | F37: =SUM(F34:F36) -> 0.087851551 | G37: =E37-F37 -> -0.0078515512 | H37: =SUM(H34:H36) -> 5714.2857 | I37: =H37/J37 -> 0.90668408 | J37: =SUM(J34:J36) -> 6302.4 | K37: =SUM(K34:K36) -> 2.7472527 | L37: ='BLS Table Data'!F38 -> 3.03
A39: G. | B39: COST STUDY RESULTS
C40: Paid Leave | D40: =D13 -> 14000000 | E40: =E13 -> 0.14 | F40: =F13 -> 0.10553784 | G40: =E40-F40 -> 0.034462163 | H40: =H13 -> 10000 | I40: =H40/J40 -> 1.3207946 | J40: =J13 -> 7571.2 | K40: =K13 -> 4.8076923 | L40: ='BLS Table Data'!F41 -> 3.64
C41: Insurance plus Retirement and Savings | D41: =D26+D31 -> 28500000 | E41: =E26+E31 -> 0.285 | F41: =F26+F31 -> 0.15163816 | G41: =E41-F41 -> 0.13336184 | H41: =H26+H31 -> 20357.143 | I41: =H41/J41 -> 1.8713361 | J41: =J26+J31 -> 10878.4 | K41: =K26+K31 -> 9.7870879 | L41: ='BLS Table Data'!F42 -> 5.23
C42: Total G | D42: =SUM(D40:D41) -> 42500000 | E42: =SUM(E40:E41) -> 0.425 | F42: =SUM(F40:F41) -> 0.25717599 | G42: =E42-F42 -> 0.16782401 | H42: =SUM(H40:H41) -> 30357.143 | I42: =H42/J42 -> 1.6454093 | J42: =SUM(J40:J41) -> 18449.6 | K42: =SUM(K40:K41) -> 14.59478 | L42: ='BLS Table Data'!F43 -> 8.87
C45: employees = | D45: =SUM('WFIS Data'!D10:D12) -> 1400
C46: hours worked = | D46: =D45*2080 -> 2912000

Sheet Proposed Cost Study
A1: ='WFIS Data'!$D$5 -> Sample Facility
A2: ='WFIS Data'!$D$6 -> Sample Contractor
D3: =A1 -> Sample Facility | F3: US Bureau of Labor Statistics Wtd Ave | G3: =D3 -> Sample Facility | J3: US Bureau of Labor Statistics Wtd Ave | K3: =D3 -> Sample Facility | L3: US Bureau of Labor Statistics Wtd Ave
D4: Actual Amount | E4: Percent of Payroll | F4: Percent of Payroll | G4: Percent Above Average | H4: Cost per FTE | I4: Per Capita Cost Ratio | J4: Cost per FTE | K4: Cost per hour | L4: Cost per hour
A5: A. | B5: PAYROLL
C6: Total Compensation | D6: =D7+D37+D41 -> 130000000 | E6: =D6/D$7 -> 1.3 | F6: =L6/L$7 -> 1.2394897 | H6: =K6*2080 -> 92857.143 | J6: =L6*2080 -> 88920 | K6: =D6/D$46 -> 44.642857 | L6: ='BLS Table Data'!F7 -> 42.75
C7: Payroll | D7: ='WFIS Data'!$D$16-'WFIS Data'!$D$33-SUM('WFIS Data'!D42:D43)-'WFIS Data'!$D$47 -> 100000000 | E7: =D7/D$7 -> 1 | F7: =L7/L$7 -> 1 | H7: =K7*2080 -> 71428.571 | J7: =L7*2080 -> 71739.2 | K7: =D7/D$46 -> 34.340659 | L7: ='BLS Table Data'!F8 -> 34.49
A9: B. | B9: PAID LEAVE
C10: Vacation | D10: ='WFIS Data'!$D$20+'WFIS Data'!$D$21 -> 7000000 | E10: =D10/D$7 -> 0.07 | F10: =L10/L$7 -> 0.055088431 | H10: =K10*2080 -> 5000 | J10: =L10*2080 -> 3952 | K10: =D10/D$46 -> 2.4038462 | L10: ='BLS Table Data'!F11 -> 1.9
C11: Holidays | D11: ='WFIS Data'!$D$22+'WFIS Data'!$D$23 -> 4000000 | E11: =D11/D$7 -> 0.04 | F11: =L11/L$7 -> 0.031893302 | H11: =K11*2080 -> 2857.1429 | J11: =L11*2080 -> 2288 | K11: =D11/D$46 -> 1.3736264 | L11: ='BLS Table Data'!F12 -> 1.1
C12: Sick and Personal | D12: =SUM('WFIS Data'!D24:D29) -> 3000000 | E12: =D12/D$7 -> 0.03 | F12: =L12/L$7 -> 0.018556103 | H12: =K12*2080 -> 2142.8571 | J12: =L12*2080 -> 1331.2 | K12: =D12/D$46 -> 1.0302198 | L12: ='BLS Table Data'!F13 -> 0.64
C13: TOTAL B | D13: =SUM(D10:D12) -> 14000000 | E13: =SUM(E10:E12) -> 0.14 | F13: =SUM(F10:F12) -> 0.10553784 | G13: =E13-F13 -> 0.034462163 | H13: =SUM(H10:H12) -> 10000 | I13: =H13/J13 -> 1.3207946 | J13: =SUM(J10:J12) -> 7571.2 | K13: =SUM(K10:K12) -> 4.8076923 | L13: ='BLS Table Data'!F14 -> 3.64
A15: C. | B15: SUPPLEMENTAL PAY
C16: Overtime and premium | D16: ='WFIS Data'!$D$30 -> 3000000 | E16: =D16/D$7 -> 0.03 | F16: =L16/L$7 -> 0.0089881125 | H16: =K16*2080 -> 2142.8571 | J16: =L16*2080 -> 644.8 | K16: =D16/D$46 -> 1.0302198 | L16: ='BLS Table Data'!F17 -> 0.31
C17: Shift differentials | D17: =SUM('WFIS Data'!D35:D36)+SUM('WFIS Data'!D42:D51) -> 500000 | E17: =D17/D$7 -> 0.005 | F17: =L17/L$7 -> 0.0049289649 | H17: =K17*2080 -> 357.14286 | J17: =L17*2080 -> 353.6 | K17: =D17/D$46 -> 0.1717033 | L17: ='BLS Table Data'!F18 -> 0.17
C18: Nonproduction bonuses | D18: =SUM('WFIS Data'!D37:D41) -> 2500000 | E18: =D18/D$7 -> 0.025 | F18: =L18/L$7 -> 0.02928385 | H18: =K18*2080 -> 1785.7143 | J18: =L18*2080 -> 2100.8 | K18: =D18/D$46 -> 0.85851648 | L18: ='BLS Table Data'!F19 -> 1.01
C19: TOTAL C | D19: =SUM(D16:D18) -> 6000000 | E19: =SUM(E16:E18) -> 0.06 | F19: =SUM(F16:F18) -> 0.043200928 | G19: =E19-F19 -> 0.016799072 | H19: =SUM(H16:H18) -> 4285.7143 | I19: =H19/J19 -> 1.3828453 | J19: =SUM(J16:J18) -> 3099.2 | K19: =SUM(K16:K18) -> 2.0604396 | L19: ='BLS Table Data'!F20 -> 1.49
A21: D. | B21: INSURANCE
C22: Life | D22: ='WFIS Data'!$D$64 -> 500000 | E22: =D22/D$7 -> 0.005 | F22: =L22/L$7 -> 0.0020295738 | H22: =K22*2080 -> 357.14286 | J22: =L22*2080 -> 145.6 | K22: =D22/D$46 -> 0.1717033 | L22: ='BLS Table Data'!$F$23 -> 0.07
C23: Health - Actives Only | D23: =SUM('WFIS Data'!D68:D72)+'WFIS Data'!$D$80 -> 10000000 | E23: =D23/D$7 -> 0.1 | F23: =L23/L$7 -> 0.090750942 | H23: =K23*2080 -> 7142.8571 | J23: =L23*2080 -> 6510.4 | K23: =D23/D$46 -> 3.4340659 | L23: ='BLS Table Data'!F24 -> 3.13
C24: Short-Term Disability | D24: ='WFIS Data'!$D$78 -> 250000 | E24: =D24/D$7 -> 0.0025 | F24: =L24/L$7 -> 0.0028993911 | H24: =K24*2080 -> 178.57143 | J24: =L24*2080 -> 208 | K24: =D24/D$46 -> 0.085851648 | L24: ='BLS Table Data'!F25 -> 0.1
C25: Long-Term Disability | D25: ='WFIS Data'!$D$79 -> 250000 | E25: =D25/D$7 -> 0.0025 | F25: =L25/L$7 -> 0.002609452 | H25: =K25*2080 -> 178.57143 | J25: =L25*2080 -> 187.2 | K25: =D25/D$46 -> 0.085851648 | L25: ='BLS Table Data'!F26 -> 0.09
C26: TOTAL D | D26: =SUM(D22:D25) -> 11000000 | E26: =SUM(E22:E25) -> 0.11 | F26: =SUM(F22:F25) -> 0.098289359 | G26: =E26-F26 -> 0.011710641 | H26: =SUM(H22:H25) -> 7857.1429 | I26: =H26/J26 -> 1.1142987 | J26: =SUM(J22:J25) -> 7051.2 | K26: =SUM(K22:K25) -> 3.7774725 | L26: =SUM(L22:L25) -> 3.39
A28: E. | B28: RETIREMENT AND SAVINGS
C29: Defined Benefit Normal Cost | D29: 5000000 | E29: =D29/D$7 -> 0.05 | F29: =L29/L$7 -> 0.021455494 | H29: =K29*2080 -> 3571.4286 | J29: =L29*2080 -> 1539.2 | K29: =D29/D$46 -> 1.717033 | L29: ='BLS Table Data'!F30 -> 0.74
C30: Defined Contribution | D30: =MAX('WFIS Data'!D82:D83)+SUM('WFIS Data'!D85:D86) -> 6000000 | E30: =D30/D$7 -> 0.06 | F30: =L30/L$7 -> 0.031893302 | H30: =K30*2080 -> 4285.7143 | J30: =L30*2080 -> 2288 | K30: =D30/D$46 -> 2.0604396 | L30: ='BLS Table Data'!F31 -> 1.1
C31: TOTAL E | D31: =SUM(D29:D30) -> 11000000 | E31: =SUM(E29:E30) -> 0.11 | F31: =SUM(F29:F30) -> 0.053348797 | G31: =E31-F31 -> 0.056651203 | H31: =SUM(H29:H30) -> 7857.1429 | I31: =H31/J31 -> 2.0529742 | J31: =SUM(J29:J30) -> 3827.2 | K31: =SUM(K29:K30) -> 3.7774725 | L31: ='BLS Table Data'!F32 -> 1.84
A33: F. | B33: LEGALLY REQUIRED PAYMENTS:
C34: Social Security and Medicare | D34: =SUM('WFIS Data'!D54:D55) -> 7000000 | E34: =D34/D$7 -> 0.07 | F34: =L34/L$7 -> 0.0719049 | H34: =K34*2080 -> 5000 | J34: =L34*2080 -> 5158.4 | K34: =D34/D$46 -> 2.4038462 | L34: ='BLS Table Data'!F35 -> 2.48
C35: Federal and State Unemployment Payments | D35: ='WFIS Data'!$D$56 -> 400000 | E35: =D35/D$7 -> 0.004 | F35: =L35/L$7 -> 0.0049289649 | H35: =K35*2080 -> 285.71429 | J35: =L35*2080 -> 353.6 | K35: =D35/D$46 -> 0.13736264 | L35: ='BLS Table Data'!F36 -> 0.17
C36: Workers' Compensation | D36: =SUM('WFIS Data'!D60:D63) -> 600000 | E36: =D36/D$7 -> 0.006 | F36: =L36/L$7 -> 0.011017686 | H36: =K36*2080 -> 428.57143 | J36: =L36*2080 -> 790.4 | K36: =D36/D$46 -> 0.20604396 | L36: ='BLS Table Data'!F37 -> 0.38
C37: TOTAL F | D37: =SUM(D34:D36) -> 8000000 | E37: =SUM(E34:E36) -> 0.08 | F37: =SUM(F34:F36) -> 0.087851551 | G37: =E37-F37 -> -0.0078515512 | H37: =SUM(H34:H36) -> 5714.2857 | I37: =H37/J37 -> 0.90668408 | J37: =SUM(J34:J36) -> 6302.4 | K37: =SUM(K34:K36) -> 2.7472527 | L37: ='BLS Table Data'!F38 -> 3.03
A39: G. | B39: PROPOSED COST STUDY RESULTS
C40: Paid Leave | D40: =D13 -> 14000000 | E40: =E13 -> 0.14 | F40: =F13 -> 0.10553784 | G40: =E40-F40 -> 0.034462163 | H40: =H13 -> 10000 | I40: =H40/J40 -> 1.3207946 | J40: =J13 -> 7571.2 | K40: =K13 -> 4.8076923 | L40: ='BLS Table Data'!F41 -> 3.64
C41: Insurance plus Retirement and Savings | D41: =D26+D31 -> 22000000 | E41: =E26+E31 -> 0.22 | F41: =F26+F31 -> 0.15163816 | G41: =E41-F41 -> 0.068361844 | H41: =H26+H31 -> 15714.286 | I41: =H41/J41 -> 1.4445402 | J41: =J26+J31 -> 10878.4 | K41: =K26+K31 -> 7.5549451 | L41: ='BLS Table Data'!F42 -> 5.23
C42: Total G | D42: =SUM(D40:D41) -> 36000000 | E42: =SUM(E40:E41) -> 0.36 | F42: =SUM(F40:F41) -> 0.25717599 | G42: =E42-F42 -> 0.10282401 | H42: =SUM(H40:H41) -> 25714.286 | I42: =H42/J42 -> 1.3937584 | J42: =SUM(J40:J41) -> 18449.6 | K42: =SUM(K40:K41) -> 12.362637 | L42: ='BLS Table Data'!F43 -> 8.87
C45: employees = | D45: =SUM('WFIS Data'!D10:D12) -> 1400
C46: hours worked = | D46: =D45*2080 -> 2912000
