Workbook

Sheet Excess Cost
A1: Excess Cost Worksheet
A2: ` | B2: District | D2: =IF(ISBLANK(C2),"-",VLOOKUP(C2,Data!B2:C307,2,FALSE)) -> - | H2: Year: | I2: 2011-2012
B3: Note: All requested data are from the prior school year (the 2010-2011 school year).
A4: Prior school year total expenditures from all sources less capital outlay and debt service.
E6: Secondary (9-12, NG) | H6: Elementary (PreK-8)
A7: Total Expenditures
B8: State & Local | H8: =IF(ISBLANK(E8),0,Totals!E6-'Excess Cost'!E8) -> 0
B9: Federal | H9: =IF(ISBLANK(E9),0,Totals!E7-'Excess Cost'!E9) -> 0
A10: Total Expenditures from all Sources | F10: =SUM(E8:E9) -> 0 | I10: =SUM(H8:H9) -> 0
A11: Less Capital Outlay & Debt Services
B12: Capital Outlay | H12: =IF(ISBLANK(E12),0,Totals!E10-'Excess Cost'!E12) -> 0
B13: Debt Services | H13: =IF(ISBLANK(E13),0,Totals!E11-'Excess Cost'!E13) -> 0
A14: Total Capital Outlay & Debt Services | F14: =SUM(E12:E13) -> 0 | I14: =SUM(H12:H13) -> 0
A15: Total Expenditures less Capital Outlay
A16: & Debt Services | F16: =F10-F14 -> 0 | I16: =I10-I14 -> 0
A19: Deduct prior Year's Special Education Expenditures.
E20: Secondary (9-12, NG) | H20: Elementary (PreK-8)
A21: Special Education Expenditures
B22: ESEA Title I, Part A | H22: =IF(ISBLANK(E22),0,Totals!E19-'Excess Cost'!E22) -> 0
B23: ESEA Title III, Parts A & B | H23: =IF(ISBLANK(E23),0,Totals!E20-'Excess Cost'!E23) -> 0
B24: State and Local special education funds | H24: =IF(ISBLANK(E24),0,Totals!E21-'Excess Cost'!E24) -> 0
B25: State and local funds for programs under
B26: ESEA Title I, Part A, and ESEA Title III, Parts A & B | H26: =IF(ISBLANK(E26),0,Totals!E23-'Excess Cost'!E26) -> 0
A27: Total special education deductions | F27: =SUM(E22:E26) -> 0 | I27: =SUM(H22:H26) -> 0
A28: Total Expenditures less
A29: Special Education Expenditures | F29: =F16-F27 -> 0 | I29: =I16-I27 -> 0
A31: School enrollments
E32: Secondary (9-12, NG) | H32: Elementary (PreK-8)
A33: Prior year's September 20 count | F33: =IF(ISBLANK(C2),"-",VLOOKUP(C2,Data!B2:Q307,15,FALSE)) -> - | I33: =IF(ISBLANK(C2),"-",Totals!F30-'Excess Cost'!F33) -> -
B37: Please return a copy of the completed Excel file to your Coop/Interlocal Special Education Director.
B38: Do not send a faxed or printed copy.

Sheet Totals
B2: District | C2: ='Excess Cost'!C2 -> 0 | D2: ='Excess Cost'!D2:E2 -> - | H2: Note: The data provided on this tab is informational only and is directly populated from the annual district budgets submitted to KSDE in July. No action is required by district officials on this tab.
E4: Total for District
A5: Total Expenditures
B6: State & Local | E6: =VLOOKUP(C2,Data!B2:P307,3,FALSE) -> #N/A
B7: Federal | E7: =VLOOKUP(C2,Data!B2:P307,4,FALSE) -> #N/A
A8: Total Expenditures from all Sources | F8: =SUM(E6:E7) -> #N/A
A9: Less Capital Outlay & Debt Services
B10: Capital Outlay | E10: =VLOOKUP(C2,Data!B2:P307,5,FALSE) -> #N/A
B11: Debt Services | E11: =VLOOKUP(C2,Data!B2:P307,6,FALSE) -> #N/A
A12: Total Capital Outlay & Debt Services | F12: =SUM(E10:E11) -> #N/A
A13: Total Expenditures less Capital Outlay
A14: & Debt Services | F14: =F8-F12 -> #N/A
E17: Total for District
A18: Special Education Expenditures
B19: ESEA Title I, Part A | E19: =VLOOKUP(C2,Data!B2:Q307,8,FALSE) -> #N/A
B20: ESEA Title III, Parts A & B | E20: =VLOOKUP(C2,Data!B2:Q307,9,FALSE) -> #N/A
B21: State and Local special education funds | E21: =VLOOKUP(C2,Data!B2:Q307,10,FALSE) -> #N/A
B22: State and local funds for programs under
B23: ESEA Title I, Part A, and ESEA Title III, Parts A & B | E23: =VLOOKUP(C2,Data!B2:Q307,13,FALSE) -> #N/A
A24: Total special education deductions | F24: =SUM(E19:E23) -> #N/A
A25: Total Expenditures less
A26: Special Education Expenditures | F26: =F14-F24 -> #N/A
E29: Total for District
A30: Prior year's September 20 count | F30: =VLOOKUP(C2,Data!B2:Q307,14,FALSE)+VLOOKUP(C2,Data!B2:Q307,15,FALSE) -> #N/A

Sheet Data
A1: Coop | B1: USD# | C1: USD_Name | D1: Ln1:Non-Fed Exp | E1: Ln2:Federal Exp (Code 7) | F1: Cap_Outlay | G1: Debt_Service | H1: IDEA_Draw | I1: TitleI_Draw | J1: TitleIII_Draw | K1: Sped Fund | L1: Coop Fund | M1: Sped_Expend | N1: Bil_Expend | O1: PK-8_Hdct | P1: 9-12,NG_Hdct
A2: D0603 | B2: 101 | C2: Erie-Galesburg | D2: 7893998 | E2: 229659 | F2: 1056129 | G2: 1263846 | H2: 0 | I2: 234359 | J2: 0 | K2: 116302 | L2: 0 | M2: 116302 | N2: 1969 | O2: 347 | P2: 197
A3: D0613 | B3: 102 | C3: Cimarron-Ensign | D3: 6346680 | E3: 334944 | F3: 764852 | G3: 395005 | H3: 0 | I3: 122312 | J3: 14377 | K3: 61997 | L3: 0 | M3: 61997 | N3: 259784 | O3: 502 | P3: 217
A4: D0602 | B4: 103 | C4: Cheylin | D4: 2052178 | E4: 129857 | F4: 178431 | G4: 0 | H4: 0 | I4: 50028 | J4: 0 | K4: 49637 | L4: 0 | M4: 49637 | N4: 30490 | O4: 89 | P4: 53
A5: D0602 | B5: 105 | C5: Rawlins County | D5: 3629528 | E5: 132283 | F5: 402826 | G5: 0 | H5: 0 | I5: 96668 | J5: 0 | K5: 170537 | L5: 0 | M5: 170537 | N5: 0 | O5: 200 | P5: 115
A6: D0613 | B6: 106 | C6: Western Plains | D6: 2097730 | E6: 71770 | F6: 50449 | G6: 59001 | H6: 0 | I6: 34098 | J6: 0 | K6: 1102 | L6: 0 | M6: 1102 | N6: 18183 | O6: 122 | P6: 48
A7: D0273 | B7: 107 | C7: Rock Hills | D7: 3703256 | E7: 117063 | F7: 350063 | G7: 52908 | H7: 0 | I7: 102952 | J7: 0 | K7: 20504 | L7: 0 | M7: 20504 | N7: 0 | O7: 171 | P7: 127
A8: D0333 | B8: 108 | C8: Washington Co. Schools | D8: 5711058 | E8: 142453 | F8: 1371943 | G8: 261765 | H8: 0 | I8: 94258 | J8: 0 | K8: 140153 | L8: 0 | M8: 140153 | N8: 0 | O8: 298 | P8: 118
A9: D0333 | B9: 109 | C9: Republic County | D9: 4703569 | E9: 218170 | F9: 221692 | G9: 67320 | H9: 0 | I9: 157312 | J9: 0 | K9: 53406 | L9: 0 | M9: 53406 | N9: 0 | O9: 346 | P9: 163
A10: D0636 | B10: 110 | C10: Thunder Ridge Schools | D10: 3227975 | E10: 105455 | F10: 299807 | G10: 0 | H10: 0 | I10: 54828 | J10: 0 | K10: 440 | L10: 0 | M10: 440 | N10: 0 | O10: 186 | P10: 83
A11: D0616 | B11: 111 | C11: Doniphan West Schools | D11: 5125166 | E11: 80958 | F11: 306258 | G11: 0 | H11: 0 | I11: 49912 | J11: 0 | K11: 6854 | L11: 0 | M11: 6854 | N11: 0 | O11: 236 | P11: 129
A12: D0305 | B12: 112 | C12: Central Plains | D12: 8059964 | E12: 133078 | F12: 516017 | G12: 708875 | H12: 0 | I12: 96897 | J12: 0 | K12: 40632 | L12: 0 | M12: 40632 | N12: 0 | O12: 365 | P12: 254
A13: D0336 | B13: 113 | C13: Prairie Hills | D13: 12575798 | E13: 191344 | F13: 643708 | G13: 561693 | H13: 0 | I13: 169542 | J13: 0 | K13: 282693 | L13: 0 | M13: 282693 | N13: 2000 | O13: 866 | P13: 392
... A16: D0611 | B16: 200 | C16: Greeley County Schools | D16: 2665109 | E16: 53407 | F16: 159854 | G16: 27753 | H16: 0 | I16: 55794 | J16: 0 | K16: 3682 | L16: 0 | M16: 3682 | N16: 59889 | O16: 138 | P16: 63
B17: 202 | C17: Turner-Kansas City | D17: 40618890 | E17: 1849607 | F17: 3767346 | G17: 3761905 | H17: 1129985 | I17: 1457336 | J17: 67046 | K17: 4109176 | L17: 0 | M17: 4109176 | N17: 456154 | O17: 2780 | P17: 1296
A18: D0500 | B18: 203 | C18: Piper-Kansas City | D18: 14975203 | E18: 126433 | F18: 977527 | G18: 1707443 | H18: 0 | I18: 92969 | J18: 0 | K18: 156606 | L18: 0 | M18: 156606 | N18: 0 | O18: 1194 | P18: 524
A19: D0500 | B19: 204 | C19: Bonner Springs | D19: 21118421 | E19: 517728 | F19: 754220 | G19: 3167774 | H19: 0 | I19: 411472 | J19: 22868 | K19: 384374 | L19: 0 | M19: 384374 | N19: 145683 | O19: 1800 | P19: 716
A20: D0490 | B20: 205 | C20: Bluestem | D20: 6504262 | E20: 149584 | F20: 429440 | G20: 608588 | H20: 0 | I20: 120657 | J20: 0 | K20: 32949 | L20: 0 | M20: 32949 | N20: 0 | O20: 323 | P20: 221
A21: D0490 | B21: 206 | C21: Remington-Whitewater | D21: 5410950 | E21: 104250 | F21: 242224 | G21: 436319 | H21: 0 | I21: 83473 | J21: 0 | K21: 80964 | L21: 0 | M21: 80964 | N21: 26284 | O21: 350 | P21: 203
A22: D0453 | B22: 207 | C22: Ft Leavenworth | D22: 16272024 | E22: 94400 | F22: 2254434 | G22: 0 | H22: 0 | I22: 67496 | J22: 0 | K22: 88699 | L22: 0 | M22: 88699 | N22: 174016 | O22: 1905 | P22: 91
A23: D0602 | B23: 208 | C23: Wakeeney | D23: 4551003 | E23: 150004 | F23: 357668 | G23: 207507 | H23: 0 | I23: 119170 | J23: 0 | K23: 504994 | L23: 0 | M23: 504994 | N23: 0 | O23: 270 | P23: 122
A24: D0611 | B24: 209 | C24: Moscow Public Schools | D24: 3059217 | E24: 258073 | F24: 680739 | G24: 0 | H24: 0 | I24: 37185 | J24: 0 | K24: 0 | L24: 0 | M24: 0 | N24: 81496 | O24: 117 | P24: 83
A25: D0611 | B25: 210 | C25: Hugoton Public Schools | D25: 12621278 | E25: 688037 | F25: 2094055 | G25: 1206610 | H25: 0 | I25: 247875 | J25: 23205 | K25: 28176 | L25: 0 | M25: 28176 | N25: 268897 | O25: 774 | P25: 340
A26: D0636 | B26: 211 | C26: Norton Community Schools | D26: 6721102 | E26: 177858 | F26: 539467 | G26: 0 | H26: 0 | I26: 151724 | J26: 0 | K26: 22021 | L26: 0 | M26: 22021 | N26: 0 | O26: 481 | P26: 280
A27: D0636 | B27: 212 | C27: Northern Valley | D27: 3000525 | E27: 56906 | F27: 609499 | G27: 0 | H27: 0 | I27: 58800 | J27: 0 | K27: 14261 | L27: 0 | M27: 14261 | N27: 0 | O27: 150 | P27: 62
A28: D0611 | B28: 214 | C28: Ulysses | D28: 14837976 | E28: 1018855 | F28: 640226 | G28: 1333206 | H28: 0 | I28: 347248 | J28: 43635 | K28: 9130 | L28: 0 | M28: 9130 | N28: 370087 | O28: 1224 | P28: 494
A29: D0611 | B29: 215 | C29: Lakin | D29: 7627396 | E29: 213356 | F29: 547329 | G29: 936175 | H29: 0 | I29: 178782 | J29: 0 | K29: 9462 | L29: 0 | M29: 9462 | N29: 218562 | O29: 464 | P29: 165
... A39: D0613 | B39: 227 | C39: Jetmore | D39: 4164420 | E39: 110532 | F39: 655153 | G39: 345365 | H39: 0 | I39: 61846 | J39: 0 | K39: 2149 | L39: 0 | M39: 2149 | N39: 3543 | O39: 231 | P39: 92
B40: 229 | C40: Blue Valley | D40: 247410819 | E40: 658833 | F40: 14269150 | G40: 41965928 | H40: 5216654 | I40: 340546 | J40: 30806 | K40: 29746139 | L40: 0 | M40: 29746139 | N40: 1505859 | O40: 14768 | P40: 6663
B41: 230 | C41: Spring Hill | D41: 28028186 | E41: 218215 | F41: 430068 | G41: 3810929 | H41: 757820 | I41: 183017 | J41: 0 | K41: 2125599 | L41: 0 | M41: 2125599 | N41: 26137 | O41: 1555 | P41: 2053
B42: 231 | C42: Gardner Edgerton | D42: 57050970 | E42: 1223108 | F42: 3747688 | G42: 11399195 | H42: 1243765 | I42: 412869 | J42: 0 | K42: 7033419 | L42: 0 | M42: 7033419 | N42: 270804 | O42: 3712 | P42: 1330
B43: 232 | C43: De Soto | D43: 70741971 | E43: 360742 | F43: 2210790 | G43: 16010332 | H43: 1620626 | I43: 148872 | J43: 17992 | K43: 6536322 | L43: 0 | M43: 6536322 | N43: 259117 | O43: 4926 | P43: 1742
B44: 233 | C44: Olathe | D44: 280212690 | E44: 4897040 | F44: 3475490 | G44: 42372540 | H44: 9165610 | I44: 2217996 | J44: 138591 | K44: 33953344 | L44: 0 | M44: 33953344 | N44: 2482521 | O44: 19530 | P44: 7835
B45: 234 | C45: Fort Scott | D45: 16714855 | E45: 963216 | F45: 537363 | G45: 1057041 | H45: 630903 | I45: 803285 | J45: 0 | K45: 1335376 | L45: 0 | M45: 1335376 | N45: 9645 | O45: 1406 | P45: 567
A46: D0637 | B46: 235 | C46: Uniontown | D46: 4824177 | E46: 156190 | F46: 446675 | G46: 154070 | H46: 0 | I46: 121343 | J46: 0 | K46: 36029 | L46: 0 | M46: 36029 | N46: 9458 | O46: 318 | P46: 157
A47: D0636 | B47: 237 | C47: Smith Center | D47: 5204512 | E47: 130488 | F47: 1045309 | G47: 0 | H47: 0 | I47: 118879 | J47: 0 | K47: 38745 | L47: 0 | M47: 38745 | N47: 0 | O47: 257 | P47: 172
A48: D0305 | B48: 239 | C48: North Ottawa County | D48: 6167547 | E48: 160941 | F48: 305501 | G48: 354015 | H48: 0 | I48: 95946 | J48: 0 | K48: 202686 | L48: 0 | M48: 202686 | N48: 0 | O48: 397 | P48: 230
A49: D0305 | B49: 240 | C49: Twin Valley | D49: 6524508 | E49: 142998 | F49: 216432 | G49: 522932 | H49: 0 | I49: 86385 | J49: 0 | K49: 98255 | L49: 0 | M49: 98255 | N49: 0 | O49: 427 | P49: 212
A50: D0602 | B50: 241 | C50: Wallace County Schools | D50: 2255334 | E50: 36690 | F50: 146123 | G50: 229218 | H50: 0 | I50: 52577 | J50: 0 | K50: 8 | L50: 0 | M50: 8 | N50: 0 | O50: 141 | P50: 58
A51: D0602 | B51: 242 | C51: Weskan | D51: 1349297 | E51: 53163 | F51: 61759 | G51: 0 | H51: 0 | I51: 29028 | J51: 0 | K51: 0 | L51: 0 | M51: 0 | N51: 20063 | O51: 69 | P51: 44
A52: D0244 | B52: 243 | C52: Lebo-Waverly | D52: 5771267 | E52: 97690 | F52: 185017 | G52: 407488 | H52: 0 | I52: 97690 | J52: 0 | K52: 470525 | L52: 0 | M52: 470525 | N52: 0 | O52: 354 | P52: 181
A53: D0244 | B53: 244 | C53: Burlington | D53: 9779924 | E53: 167715 | F53: 1048278 | G53: 0 | H53: 548995 | I53: 105272 | J53: 0 | K53: 1496515 | L53: 424094 | M53: 1920609 | N53: 0 | O53: 623 | P53: 253
A54: D0244 | B54: 245 | C54: LeRoy-Gridley | D54: 2839411 | E54: 65443 | F54: 1598 | G54: 0 | H54: 0 | I54: 50020 | J54: 0 | K54: 395077 | L54: 0 | M54: 395077 | N54: 0 | O54: 159 | P54: 75
A55: D0637 | B55: 246 | C55: Northeast | D55: 5748362 | E55: 335833 | F55: 81280 | G55: 348378 | H55: 0 | I55: 268559 | J55: 0 | K55: 115615 | L55: 0 | M55: 115615 | N55: 0 | O55: 398 | P55: 171
A56: D0637 | B56: 247 | C56: Cherokee | D56: 7126296 | E56: 944700 | F56: 568960 | G56: 0 | H56: 0 | I56: 222424 | J56: 0 | K56: 210784 | L56: 0 | M56: 210784 | N56: 0 | O56: 518 | P56: 215
A57: D0637 | B57: 248 | C57: Girard | D57: 9810023 | E57: 410712 | F57: 1674722 | G57: 0 | H57: 0 | I57: 256028 | J57: 0 | K57: 78831 | L57: 0 | M57: 78831 | N57: 0 | O57: 719 | P57: 340
... A67: D0603 | B67: 258 | C67: Humboldt | D67: 5626952 | E67: 263785 | F67: 131542 | G67: 787577 | H67: 0 | I67: 128010 | J67: 0 | K67: 5038 | L67: 0 | M67: 5038 | N67: 0 | O67: 388 | P67: 183
B68: 259 | C68: Wichita | D68: 544948840 | E68: 38214883 | F68: 44848559 | G68: 45595357 | H68: 17187209 | I68: 25769412 | J68: 765087 | K68: 70145127 | L68: 0 | M68: 70145127 | N68: 10727995 | O68: 35976 | P68: 13597
B69: 260 | C69: Derby | D69: 60441828 | E69: 1354053 | F69: 5002215 | G69: 3754676 | H69: 1983119 | I69: 1087197 | J69: 69196 | K69: 6968616 | L69: 0 | M69: 6968616 | N69: 836215 | O69: 4872 | P69: 1881
B70: 261 | C70: Haysville | D70: 49117521 | E70: 933460 | F70: 3020936 | G70: 4465218 | H70: 1497993 | I70: 543743 | J70: 13200 | K70: 6509808 | L70: 0 | M70: 6509808 | N70: 183207 | O70: 3607 | P70: 1660
A71: D0618 | B71: 262 | C71: Valley Center Pub Sch | D71: 23776242 | E71: 620085 | F71: 1536358 | G71: 4901345 | H71: 0 | I71: 263346 | J71: 0 | K71: 453807 | L71: 0 | M71: 453807 | N71: 88809 | O71: 1838 | P71: 849
B72: 263 | C72: Mulvane | D72: 17186215 | E72: 375332 | F72: 982829 | G72: 1577705 | H72: 520757 | I72: 254870 | J72: 0 | K72: 1831768 | L72: 0 | M72: 1831768 | N72: 2887 | O72: 1232 | P72: 673
A73: D0618 | B73: 264 | C73: Clearwater | D73: 11613572 | E73: 355608 | F73: 1299687 | G73: 1123869 | H73: 0 | I73: 104534 | J73: 0 | K73: 113224 | L73: 0 | M73: 113224 | N73: 0 | O73: 782 | P73: 520
A74: D0618 | B74: 265 | C74: Goddard | D74: 52623505 | E74: 486013 | F74: 3610923 | G74: 12693150 | H74: 0 | I74: 277552 | J74: 16155 | K74: 284827 | L74: 0 | M74: 284827 | N74: 123756 | O74: 3569 | P74: 1612
A75: D0618 | B75: 266 | C75: Maize | D75: 58279784 | E75: 268552 | F75: 7472307 | G75: 7494635 | H75: 0 | I75: 159945 | J75: 10509 | K75: 485934 | L75: 0 | M75: 485934 | N75: 172518 | O75: 4477 | P75: 2159
A76: D0618 | B76: 267 | C76: Renwick | D76: 16437387 | E76: 192105 | F76: 944728 | G76: 2549196 | H76: 0 | I76: 135031 | J76: 0 | K76: 162480 | L76: 0 | M76: 162480 | N76: 0 | O76: 1338 | P76: 647
A77: D0618 | B77: 268 | C77: Cheney | D77: 7487761 | E77: 80626 | F77: 404461 | G77: 646110 | H77: 0 | I77: 55400 | J77: 0 | K77: 81551 | L77: 0 | M77: 81551 | N77: 0 | O77: 543 | P77: 265
A78: D0636 | B78: 269 | C78: Palco | D78: 2269326 | E78: 89458 | F78: 266696 | G78: 0 | H78: 0 | I78: 42029 | J78: 0 | K78: 37210 | L78: 0 | M78: 37210 | N78: 0 | O78: 97 | P78: 53
A79: D0636 | B79: 270 | C79: Plainville | D79: 4636445 | E79: 128273 | F79: 939955 | G79: 259070 | H79: 0 | I79: 66127 | J79: 0 | K79: 10160 | L79: 0 | M79: 10160 | N79: 0 | O79: 273 | P79: 125
A80: D0636 | B80: 271 | C80: Stockton | D80: 3430958 | E80: 105798 | F80: 406768 | G80: 165101 | H80: 0 | I80: 83131 | J80: 0 | K80: 49254 | L80: 0 | M80: 49254 | N80: 0 | O80: 204 | P80: 89
A81: D0273 | B81: 272 | C81: Waconda | D81: 3703043 | E81: 128725 | F81: 105973 | G81: 0 | H81: 0 | I81: 63365 | J81: 0 | K81: 17847 | L81: 0 | M81: 17847 | N81: 0 | O81: 263 | P81: 145
A82: D0273 | B82: 273 | C82: Beloit | D82: 7604089 | E82: 220266 | F82: 730273 | G82: 0 | H82: 716302 | I82: 169251 | J82: 0 | K82: 0 | L82: 3064292 | M82: 3064292 | N82: 1967 | O82: 564 | P82: 216
A83: D0602 | B83: 274 | C83: Oakley | D83: 4236926 | E83: 92838 | F83: 411188 | G83: 0 | H83: 0 | I83: 68346 | J83: 0 | K83: 118637 | L83: 0 | M83: 118637 | N83: 0 | O83: 255 | P83: 208
A84: D0602 | B84: 275 | C84: Triplains | D84: 1378958 | E84: 40118 | F84: 248856 | G84: 0 | H84: 0 | I84: 34815 | J84: 0 | K84: 83582 | L84: 0 | M84: 83582 | N84: 0 | O84: 63 | P84: 24
... A93: D0614 | B93: 289 | C93: Wellsville | D93: 8358045 | E93: 108921 | F93: 394107 | G93: 759883 | H93: 0 | I93: 84908 | J93: 0 | K93: 78938 | L93: 0 | M93: 78938 | N93: 8616 | O93: 625 | P93: 234
B94: 290 | C94: Ottawa | D94: 24775996 | E94: 1011268 | F94: 1177770 | G94: 2609402 | H94: 796406 | I94: 619264 | J94: 0 | K94: 2504859 | L94: 0 | M94: 2504859 | N94: 47431 | O94: 1798 | P94: 736
A95: D0602 | B95: 291 | C95: Grinnell Public Schools | D95: 939301 | E95: 19332 | F95: 68107 | G95: 0 | H95: 0 | I95: 9064 | J95: 0 | K95: 311 | L95: 0 | M95: 311 | N95: 0 | O95: 51 | P95: 25
A96: D0602 | B96: 292 | C96: Wheatland | D96: 1449550 | E96: 73339 | F96: 98514 | G96: 0 | H96: 0 | I96: 38998 | J96: 0 | K96: 12547 | L96: 0 | M96: 12547 | N96: 0 | O96: 72 | P96: 34
A97: D0602 | B97: 293 | C97: Quinter Public Schools | D97: 3269297 | E97: 78452 | F97: 282743 | G97: 0 | H97: 0 | I97: 33750 | J97: 0 | K97: 263907 | L97: 0 | M97: 263907 | N97: 11000 | O97: 181 | P97: 99
A98: D0602 | B98: 294 | C98: Oberlin | D98: 4063125 | E98: 135057 | F98: 369546 | G98: 0 | H98: 0 | I98: 96078 | J98: 0 | K98: 9530 | L98: 0 | M98: 9530 | N98: 0 | O98: 251 | P98: 113
A99: D0602 | B99: 297 | C99: St Francis Comm Sch | D99: 3270557 | E99: 93921 | F99: 314628 | G99: 0 | H99: 0 | I99: 52990 | J99: 0 | K99: 160784 | L99: 0 | M99: 160784 | N99: 0 | O99: 197 | P99: 103
A100: D0273 | B100: 298 | C100: Lincoln | D100: 3904802 | E100: 117759 | F100: 176163 | G100: 326525 | H100: 0 | I100: 97794 | J100: 0 | K100: 56297 | L100: 0 | M100: 56297 | N100: 0 | O100: 260 | P100: 113
A101: D0273 | B101: 299 | C101: Sylvan Grove | D101: 2476670 | E101: 60373 | F101: 125468 | G101: 0 | H101: 0 | I101: 48538 | J101: 0 | K101: 753 | L101: 0 | M101: 753 | N101: 0 | O101: 160 | P101: 81
A102: D0605 | B102: 300 | C102: Comanche County | D102: 3324408 | E102: 72430 | F102: 106979 | G102: 0 | H102: 0 | I102: 67120 | J102: 0 | K102: 14170 | L102: 0 | M102: 14170 | N102: 0 | O102: 232 | P102: 91
A103: D0613 | B103: 303 | C103: Ness City | D103: 2977142 | E103: 82941 | F103: 378316 | G103: 0 | H103: 0 | I103: 37858 | J103: 0 | K103: 13643 | L103: 0 | M103: 13643 | N103: 0 | O103: 220 | P103: 110
A104: D0305 | B104: 305 | C104: Salina | D104: 66524800 | E104: 8897900 | F104: 4113623 | G104: 7910988 | H104: 4237533 | I104: 1582895 | J104: 37213 | K104: 984005 | L104: 15650407 | M104: 16634412 | N104: 826671 | O104: 5126 | P104: 2220
A105: D0305 | B105: 306 | C105: Southeast Of Saline | D105: 6182800 | E105: 80944 | F105: 624205 | G105: 0 | H105: 0 | I105: 62051 | J105: 0 | K105: 31593 | L105: 0 | M105: 31593 | N105: 0 | O105: 495 | P105: 245
A106: D0305 | B106: 307 | C106: Ell-Saline | D106: 4836371 | E106: 145937 | F106: 293343 | G106: 411650 | H106: 0 | I106: 68344 | J106: 0 | K106: 36547 | L106: 0 | M106: 36547 | N106: 5594 | O106: 326 | P106: 152
B107: 308 | C107: Hutchinson Public Schools | D107: 48598253 | E107: 5680182 | F107: 5327058 | G107: 5196705 | H107: 1771778 | I107: 1991587 | J107: 18224 | K107: 4023654 | L107: 0 | M107: 4023654 | N107: 280939 | O107: 3473 | P107: 1449
A108: D0610 | B108: 309 | C108: Nickerson | D108: 10916478 | E108: 489299 | F108: 744622 | G108: 508803 | H108: 0 | I108: 296698 | J108: 0 | K108: 267919 | L108: 0 | M108: 267919 | N108: 58994 | O108: 897 | P108: 305
A109: D0610 | B109: 310 | C109: Fairfield | D109: 4107543 | E109: 140212 | F109: 684799 | G109: 0 | H109: 0 | I109: 100259 | J109: 0 | K109: 146283 | L109: 0 | M109: 146283 | N109: 11000 | O109: 187 | P109: 103
A110: D0610 | B110: 311 | C110: Pretty Prairie | D110: 2914680 | E110: 67846 | F110: 39411 | G110: 138728 | H110: 0 | I110: 35191 | J110: 0 | K110: 29884 | L110: 0 | M110: 29884 | N110: 0 | O110: 180 | P110: 101
A111: D0610 | B111: 312 | C111: Haven Public Schools | D111: 9538775 | E111: 306236 | F111: 275830 | G111: 674265 | H111: 0 | I111: 229029 | J111: 0 | K111: 95258 | L111: 0 | M111: 95258 | N111: 11234 | O111: 745 | P111: 333
A112: D0610 | B112: 313 | C112: Buhler | D112: 19723443 | E112: 575552 | F112: 1476442 | G112: 1413590 | H112: 0 | I112: 169859 | J112: 0 | K112: 568841 | L112: 0 | M112: 568841 | N112: 51599 | O112: 1616 | P112: 660
A113: D0602 | B113: 314 | C113: Brewster | D113: 1371739 | E113: 42583 | F113: 98164 | G113: 0 | H113: 0 | I113: 14315 | J113: 0 | K113: 52775 | L113: 0 | M113: 52775 | N113: 4271 | O113: 60 | P113: 34
A114: D0602 | B114: 315 | C114: Colby Public Schools | D114: 9412232 | E114: 259479 | F114: 733244 | G114: 534338 | H114: 0 | I114: 142217 | J114: 0 | K114: 962879 | L114: 0 | M114: 962879 | N114: 9290 | O114: 590 | P114: 360
A115: D0602 | B115: 316 | C115: Golden Plains | D115: 2117091 | E115: 46192 | F115: 102740 | G115: 50950 | H115: 0 | I115: 60201 | J115: 0 | K115: 79344 | L115: 0 | M115: 79344 | N115: 18176 | O115: 139 | P115: 77
A116: D0320 | B116: 320 | C116: Wamego | D116: 12057968 | E116: 820287 | F116: 541595 | G116: 1004735 | H116: 743042 | I116: 161914 | J116: 0 | K116: 120827 | L116: 3503425 | M116: 3624252 | N116: 0 | O116: 976 | P116: 448
B117: 321 | C117: Kaw Valley | D117: 13960385 | E117: 283300 | F117: 2441820 | G117: 0 | H117: 452206 | I117: 211179 | J117: 0 | K117: 1659252 | L117: 0 | M117: 1659252 | N117: 0 | O117: 834 | P117: 371
A118: D0336 | B118: 322 | C118: Onaga-Havensville-Wheaton | D118: 3461024 | E118: 107378 | F118: 160310 | G118: 254540 | H118: 0 | I118: 60732 | J118: 0 | K118: 34239 | L118: 0 | M118: 34239 | N118: 0 | O118: 206 | P118: 115
A119: D0320 | B119: 323 | C119: Rock Creek | D119: 8031201 | E119: 166991 | F119: 571747 | G119: 719088 | H119: 0 | I119: 114237 | J119: 0 | K119: 50294 | L119: 0 | M119: 50294 | N119: 0 | O119: 640 | P119: 239
A120: D0636 | B120: 325 | C120: Phillipsburg | D120: 5867614 | E120: 149692 | F120: 400797 | G120: 0 | H120: 0 | I120: 126752 | J120: 0 | K120: 4904 | L120: 0 | M120: 4904 | N120: 0 | O120: 414 | P120: 222
A121: D0636 | B121: 326 | C121: Logan | D121: 2233173 | E121: 76789 | F121: 132296 | G121: 0 | H121: 0 | I121: 57589 | J121: 0 | K121: 695 | L121: 0 | M121: 695 | N121: 0 | O121: 128 | P121: 54
A122: D0305 | B122: 327 | C122: Ellsworth | D122: 6175329 | E122: 99742 | F122: 703066 | G122: 0 | H122: 0 | I122: 106650 | J122: 0 | K122: 33521 | L122: 0 | M122: 33521 | N122: 0 | O122: 449 | P122: 188
A123: D0320 | B123: 329 | C123: Mill Creek Valley | D123: 5289701 | E123: 120184 | F123: 257313 | G123: 546110 | H123: 0 | I123: 63630 | J123: 0 | K123: 35592 | L123: 0 | M123: 35592 | N123: 0 | O123: 349 | P123: 131
B124: 330 | C124: Mission Valley | D124: 6165991 | E124: 163782 | F124: 179184 | G124: 466998 | H124: 167550 | I124: 93237 | J124: 0 | K124: 914085 | L124: 0 | M124: 914085 | N124: 2250 | O124: 345 | P124: 156
A125: D0605 | B125: 331 | C125: Kingman - Norwich | D125: 9846394 | E125: 401422 | F125: 355564 | G125: 966484 | H125: 0 | I125: 268074 | J125: 0 | K125: 99770 | L125: 0 | M125: 99770 | N125: 0 | O125: 738 | P125: 346
A126: D0605 | B126: 332 | C126: Cunningham | D126: 2202784 | E126: 44859 | F126: 106664 | G126: 0 | H126: 0 | I126: 32430 | J126: 0 | K126: 66240 | L126: 0 | M126: 66240 | N126: 0 | O126: 113 | P126: 61
A127: D0333 | B127: 333 | C127: Concordia | D127: 10301476 | E127: 343393 | F127: 415177 | G127: 439361 | H127: 954016 | I127: 289245 | J127: 0 | K127: 53484 | L127: 3959583 | M127: 4013067 | N127: 8000 | O127: 770 | P127: 350
A128: D0379 | B128: 334 | C128: Southern Cloud | D128: 2710386 | E128: 89680 | F128: 216191 | G128: 0 | H128: 0 | I128: 83609 | J128: 0 | K128: 16942 | L128: 0 | M128: 16942 | N128: 0 | O128: 157 | P128: 102
...
