Workbook

Sheet Legend
A2: Legend
D3: Local
D5: State
D7: Federal
D9: Other
A12: Source | B12: Indiana Department of Education
A14: All files are "read only" and based on data collections from the Indiana Department of Education.
A15: The conclusions reached in this document are those of the author(s) and do not necessarily represent those
A16: of Ball State University.

Sheet Figures 1,2,4
A1: Figure 1: District & Charter School Revenues & Enrollments | I1: Figure 2
A2: Indiana (2006-07) | B2: Statewide | F2: Indianapolis | J2: District | K2: Charter | L2: Difference
A3: Per-Pupil Revenue | I3: State | J3: =B4 -> 7046.6145 | K3: =B5 -> 9327.7446 | L3: =B6 -> -2281.13
A4: District | B4: =B14 -> 7046.6145 | F4: =F14 -> 11146.836 | I4: Statewide Weighted
A5: Charter | B5: =C14 -> 9327.7446 | F5: =G14 -> 9835.0698 | I5: Indianapolis | J5: =F4 -> 11146.836 | K5: =F5 -> 9835.0698 | L5: =F6 -> 1311.7665
A6: Difference | B6: =B4-B5 -> -2281.13 | F6: =F4-F5 -> 1311.7665
B7: =B6/B4 -> -0.32372 | F7: =F6/F4 -> 0.11768061
A8: Per-Pupil Revenue by Source | B8: District | C8: Charter | F8: District | G8: Charter
A9: Federal | B9: =Districts!E295/'Figures 1,2,4'!B16:C16 -> 701.31117 | C9: ='Charters State'!E39/'Charters State'!I39 -> 1113.7251 | F9: =Districts!E176/'Figures 1,2,4'!F16:G16 -> 1778.8812 | G9: ='Charters Indy'!E19/'Charters Indy'!I19 -> 995.17289
A10: State | B10: =Districts!D295/'Figures 1,2,4'!B16:C16 -> 3906.4345 | C10: ='Charters State'!D39/'Charters State'!I39 -> 4208.19 | F10: =Districts!D176/'Figures 1,2,4'!F16:G16 -> 5968.2584 | G10: ='Charters Indy'!D19/'Charters Indy'!I19 -> 4031.1984
A11: Local | B11: =Districts!C295/'Figures 1,2,4'!B16:C16 -> 1769.7759 | C11: ='Charters State'!C39/'Charters State'!I39 -> 2339.621 | F11: =Districts!C176/'Figures 1,2,4'!F16:G16 -> 1475.8358 | G11: ='Charters Indy'!C19/'Charters Indy'!I19 -> 2712.1513
A12: Other | B12: =Districts!F295/'Figures 1,2,4'!B16:C16 -> 669.09302 | C12: ='Charters State'!F39/'Charters State'!I39 -> 1666.2084 | F12: =Districts!F176/'Figures 1,2,4'!F16:G16 -> 1923.861 | G12: ='Charters Indy'!F19/'Charters Indy'!I19 -> 2096.5472
A13: Indeterminate
A14: Total | B14: =SUM(B9:B13) -> 7046.6145 | C14: =SUM(C9:C13) -> 9327.7446 | F14: =SUM(F9:F13) -> 11146.836 | G14: =SUM(G9:G13) -> 9835.0698
A15: Enrollment
A16: District | B16: =Districts!I297 -> 1024893 | F16: =Districts!I176 -> 37057
B17: =B16/(B16+B18) -> 0.99128257 | F17: =F16/(F16+F18) -> 0.89570241
A18: Charter | B18: ='Charters State'!I39 -> 9013 | F18: ='Charters Indy'!I19 -> 4315
B19: =B18/(B16+B18) -> 0.0087174269 | F19: =F18/(F16+F18) -> 0.10429759
A20: Number of Charters | B20: 37 | F20: 17
A21: Total Revenue
A22: District | B22: =SUM(Districts!C295:F295) -> 7.2220259e+09 | F22: =SUM(Districts!C176:F176) -> 4.1306831e+08
B23: =B22/B26 -> 0.98849304 | F23: =F22/F26 -> 0.90683269
A24: Charter | B24: =SUM('Charters State'!C39:F39) -> 84070962 | F24: =SUM('Charters Indy'!C19:F19) -> 42438326
B25: =B24/B26 -> 0.01150696 | F25: =F24/F26 -> 0.093167305
A26: Total | B26: =B22+B24 -> 7.3060969e+09 | F26: =F22+F24 -> 4.5550664e+08
A27: Percentage of Revenue by Source | B27: District | C27: Charter | F27: District | G27: Charter | I27: Figure 4
A28: Federal | B28: =B9/B14 -> 0.099524554 | C28: =C9/C14 -> 0.11939919 | F28: =F9/F14 -> 0.15958619 | G28: =G9/G14 -> 0.10118615 | J28: Federal | K28: State | L28: Local | M28: Other | N28: Indeterminate
A29: State | B29: =B10/B14 -> 0.5543704 | C29: =C10/C14 -> 0.45114765 | F29: =F10/F14 -> 0.53542173 | G29: =G10/G14 -> 0.40988 | I29: Statewide District | J29: =B9 -> 701.31117 | K29: =B10 -> 3906.4345 | L29: =B11 -> 1769.7759 | M29: =B12 -> 669.09302 | N29: =B13 -> 0
A30: Local | B30: =B11/B14 -> 0.25115264 | C30: =C11/C14 -> 0.25082387 | F30: =F11/F14 -> 0.13239952 | G30: =G11/G14 -> 0.2757633 | I30: Statewide Charter | J30: =C9 -> 1113.7251 | K30: =C10 -> 4208.19 | L30: =C11 -> 2339.621 | M30: =C12 -> 1666.2084 | N30: =C13 -> 0
A31: Other | B31: =B12/B14 -> 0.094952408 | C31: =C12/C14 -> 0.17862929 | F31: =F12/F14 -> 0.17259256 | G31: =G12/G14 -> 0.21317055 | I31: Statewide Weighted
A32: Change in district school funding if subjected to charter funding structure | I32: Indianapolis District | J32: =F9 -> 1778.8812 | K32: =F10 -> 5968.2584 | L32: =F11 -> 1475.8358 | M32: =F12 -> 1923.861 | N32: =F13 -> 0
B33: $2.2 billion | F33: (48.6 million) | I33: Indianapolis Charter | J33: =G9 -> 995.17289 | K33: =G10 -> 4031.1984 | L33: =G11 -> 2712.1513 | M33: =G12 -> 2096.5472 | N33: =G13 -> 0
B34: =B6*B16 -> -2.3379142e+09 | F34: =F6*F16 -> 48610132
A35: Monument Lighthouse charter school revenues excluded as the school does not list any students for FY07
A36: The following LEA have enrollments but no dollars. Therefore, excluded from analysis
A37: Indiana Department of Corrections
A38: Blue River Special Education Coop
A39: Northwest Indiana Special Education Coop
A40: The following LEA has dollars but no enrollments. Therefore, excluded from analysis
A41: Prairie Town Schools

Sheet archive
A3: Corp | B3: Corporation Name | C3: L062 | D3: L071 | E3: Local Revenue | F3: S062 | G3: S071 | H3: State Revenue | I3: F062 | J3: F071 | K3: Federal Revenue | L3: O062 | M3: O071 | N3: Other Revenue | O3: District/charter
A4: 15 | B4: Adams Central Community Schools | C4: 1381696.7 | D4: 1298899.1 | E4: =SUM(C4:D4) -> 2680595.8 | F4: 2147938.9 | G4: 2008567.6 | H4: =SUM(F4:G4) -> 4156506.5 | I4: 243125.53 | J4: 343162.17 | K4: =SUM(I4:J4) -> 586287.7 | L4: 968547.97 | M4: 42228.66 | N4: =SUM(L4:M4) -> 1010776.6 | O4: District | P4: State
A5: 25 | B5: North Adams Community Schools | C5: 2897178 | D5: 2719609.1 | E5: =SUM(C5:D5) -> 5616787.1 | F5: 4488521.7 | G5: 4036028 | H5: =SUM(F5:G5) -> 8524549.7 | I5: 334800.78 | J5: 499910.74 | K5: =SUM(I5:J5) -> 834711.52 | L5: 43181.08 | M5: 15423.3 | N5: =SUM(L5:M5) -> 58604.38 | O5: District | P5: State
A6: 35 | B6: South Adams Schools | C6: 1510496.5 | D6: 1487835.1 | E6: =SUM(C6:D6) -> 2998331.6 | F6: 3009938.1 | G6: 2764103.9 | H6: =SUM(F6:G6) -> 5774042 | I6: 764214.66 | J6: 625324.17 | K6: =SUM(I6:J6) -> 1389538.8 | L6: 3371.84 | M6: 28019.28 | N6: =SUM(L6:M6) -> 31391.12 | O6: District | P6: State
A7: 125 | B7: M S D Southwest Allen County | C7: 12666607 | D7: 2950903.6 | E7: =SUM(C7:D7) -> 15617511 | F7: 6722083.3 | G7: 6513155.6 | H7: =SUM(F7:G7) -> 13235239 | I7: 1446367.7 | J7: 1516633.3 | K7: =SUM(I7:J7) -> 2963000.9 | L7: 2508013.1 | M7: 2681684.5 | N7: =SUM(L7:M7) -> 5189697.6 | O7: District | P7: State
A8: 225 | B8: Northwest Allen County Schools | C8: 7891483 | D8: 2134056.7 | E8: =SUM(C8:D8) -> 10025540 | F8: 8959306.6 | G8: 8707031.8 | H8: =SUM(F8:G8) -> 17666338 | I8: 429002.4 | J8: 703930.74 | K8: =SUM(I8:J8) -> 1132933.1 | L8: 172880.21 | M8: 66579.65 | N8: =SUM(L8:M8) -> 239459.86 | O8: District | P8: State
A9: 235 | B9: Fort Wayne Community Schools | C9: 32894431 | D9: 9346915.1 | E9: =SUM(C9:D9) -> 42241346 | F9: 69064590 | G9: 63381242 | H9: =SUM(F9:G9) -> 1.3244583e+08 | I9: 14621455 | J9: 16701880 | K9: =SUM(I9:J9) -> 31323336 | L9: 7058316.6 | M9: 1444702.4 | N9: =SUM(L9:M9) -> 8503019.1 | O9: District | P9: State
A10: 255 | B10: East Allen County Schools | C10: 10385601 | D10: 3025155.1 | E10: =SUM(C10:D10) -> 13410756 | F10: 21025558 | G10: 19382272 | H10: =SUM(F10:G10) -> 40407830 | I10: 3253281.9 | J10: 3299733.2 | K10: =SUM(I10:J10) -> 6553015.2 | L10: 5130400.8 | M10: 9046917.4 | N10: =SUM(L10:M10) -> 14177318 | O10: District | P10: State
A11: 365 | B11: Bartholomew Con School Corp | C11: 13448291 | D11: 5952725.1 | E11: =SUM(C11:D11) -> 19401016 | F11: 19130184 | G11: 17862844 | H11: =SUM(F11:G11) -> 36993028 | I11: 5402294.8 | J11: 5298950.2 | K11: =SUM(I11:J11) -> 10701245 | L11: 2110227.5 | M11: 661638.51 | N11: =SUM(L11:M11) -> 2771866 | O11: District | P11: State
A12: 370 | B12: Flat Rock-Hawcreek School Corp | C12: 666613.34 | D12: 183012.16 | E12: =SUM(C12:D12) -> 849625.5 | F12: 2858413.8 | G12: 2455916.3 | H12: =SUM(F12:G12) -> 5314330.1 | I12: 153112.74 | J12: 200413.46 | K12: =SUM(I12:J12) -> 353526.2 | L12: 4619.7 | M12: 22651.84 | N12: =SUM(L12:M12) -> 27271.54 | O12: District | P12: State
A13: 395 | B13: Benton Community School Corp | C13: 3786773.3 | D13: 1117333.8 | E13: =SUM(C13:D13) -> 4904107.1 | F13: 3752329 | G13: 3083276.4 | H13: =SUM(F13:G13) -> 6835605.4 | I13: 114947.71 | J13: 222926.1 | K13: =SUM(I13:J13) -> 337873.81 | L13: 146890.01 | M13: 17295 | N13: =SUM(L13:M13) -> 164185.01 | O13: District | P13: State
A14: 515 | B14: Blackford County Schools | C14: 1935470.9 | D14: 205087.81 | E14: =SUM(C14:D14) -> 2140558.7 | F14: 5389107.3 | G14: 4961684.5 | H14: =SUM(F14:G14) -> 10350792 | I14: 548751.14 | J14: 922084.37 | K14: =SUM(I14:J14) -> 1470835.5 | L14: 48699.09 | M14: 46603.44 | N14: =SUM(L14:M14) -> 95302.53 | O14: District | P14: State
A15: 615 | B15: Western Boone Co Com Sch Dist | C15: 1984149.3 | D15: 517199.45 | E15: =SUM(C15:D15) -> 2501348.8 | F15: 3640846.9 | G15: 3416824.3 | H15: =SUM(F15:G15) -> 7057671.2 | I15: 96683.56 | J15: 195559.25 | K15: =SUM(I15:J15) -> 292242.81 | L15: 9744.83 | M15: 13376.54 | N15: =SUM(L15:M15) -> 23121.37 | O15: District | P15: State
A16: 630 | B16: Zionsville Community Schools | C16: 7910192.3 | D16: 1283513.1 | E16: =SUM(C16:D16) -> 9193705.4 | F16: 7179033.2 | G16: 7006898.7 | H16: =SUM(F16:G16) -> 14185932 | I16: 199767.09 | J16: 188134.53 | K16: =SUM(I16:J16) -> 387901.62 | M16: 325 | N16: =SUM(L16:M16) -> 325 | O16: District | P16: State
A17: 665 | B17: Lebanon Community School Corp | C17: 3449018.9 | D17: 607543.48 | E17: =SUM(C17:D17) -> 4056562.3 | F17: 6093344.5 | G17: 6592757.7 | H17: =SUM(F17:G17) -> 12686102 | I17: 489854.5 | J17: 924894.17 | K17: =SUM(I17:J17) -> 1414748.7 | L17: 454682.25 | M17: 90261.64 | N17: =SUM(L17:M17) -> 544943.89 | O17: District | P17: State
A18: 670 | B18: Brown County School Corporation | C18: 6087341.3 | D18: 490934.53 | E18: =SUM(C18:D18) -> 6578275.9 | F18: 3973281.2 | G18: 3286436.1 | H18: =SUM(F18:G18) -> 7259717.3 | I18: 550260.36 | J18: 879947.09 | K18: =SUM(I18:J18) -> 1430207.4 | L18: 14031.5 | M18: 42161.79 | N18: =SUM(L18:M18) -> 56193.29 | O18: District | P18: State
A19: 750 | B19: Carroll Consolidated Sch Corp | C19: 1467057.7 | D19: 464230.28 | E19: =SUM(C19:D19) -> 1931288 | F19: 2030585.3 | G19: 1842649.4 | H19: =SUM(F19:G19) -> 3873234.6 | I19: 100903.17 | J19: 202262.74 | K19: =SUM(I19:J19) -> 303165.91 | L19: 750000 | M19: 1033173.5 | N19: =SUM(L19:M19) -> 1783173.5 | O19: District | P19: State
A20: 755 | B20: Delphi Community School Corp | C20: 1738957.3 | D20: 586765.74 | E20: =SUM(C20:D20) -> 2325723 | F20: 3432249.3 | G20: 3068378.1 | H20: =SUM(F20:G20) -> 6500627.5 | I20: 320289.89 | J20: 349278.06 | K20: =SUM(I20:J20) -> 669567.95 | L20: 22317.55 | M20: 2217.46 | N20: =SUM(L20:M20) -> 24535.01 | O20: District | P20: State
A21: 775 | B21: Pioneer Regional School Corp | C21: 984792.68 | D21: 334566.16 | E21: =SUM(C21:D21) -> 1319358.8 | F21: 1847121 | G21: 1921376.4 | H21: =SUM(F21:G21) -> 3768497.4 | I21: 119053.5 | J21: 195739.55 | K21: =SUM(I21:J21) -> 314793.05 | L21: 39940.02 | M21: 49124.07 | N21: =SUM(L21:M21) -> 89064.09 | O21: District | P21: State
A22: 815 | B22: Southeastern School Corp | C22: 1722905.5 | D22: 716729.2 | E22: =SUM(C22:D22) -> 2439634.7 | F22: 3361967.5 | G22: 3003140.1 | H22: =SUM(F22:G22) -> 6365107.6 | I22: 288400.05 | J22: 231710.82 | K22: =SUM(I22:J22) -> 520110.87 | L22: 9088.55 | M22: 6664.43 | N22: =SUM(L22:M22) -> 15752.98 | O22: District | P22: State
A23: 875 | B23: Logansport Community Sch Corp | C23: 2892856.1 | D23: 1429205.8 | E23: =SUM(C23:D23) -> 4322061.9 | F23: 10861784 | G23: 10267729 | H23: =SUM(F23:G23) -> 21129512 | I23: 2905086.2 | J23: 3585100.2 | K23: =SUM(I23:J23) -> 6490186.4 | L23: 3990911.5 | M23: 5330534.7 | N23: =SUM(L23:M23) -> 9321446.2 | O23: District | P23: State
A24: 940 | B24: West Clark Community Schools | C24: 5031031.6 | D24: 1523959.5 | E24: =SUM(C24:D24) -> 6554991 | F24: 6635654.1 | G24: 6388404.7 | H24: =SUM(F24:G24) -> 13024059 | I24: 299535.34 | J24: 491165.42 | K24: =SUM(I24:J24) -> 790700.76 | L24: 699446.14 | M24: 69575.09 | N24: =SUM(L24:M24) -> 769021.23 | O24: District | P24: State
A25: 1000 | B25: Clarksville Com School Corp | C25: 2633561.5 | D25: 811586.76 | E25: =SUM(C25:D25) -> 3445148.2 | F25: 3405887.6 | G25: 2931900.5 | H25: =SUM(F25:G25) -> 6337788 | I25: 384646.62 | J25: 378181.11 | K25: =SUM(I25:J25) -> 762827.73 | L25: 106960.16 | M25: 9500.3 | N25: =SUM(L25:M25) -> 116460.46 | O25: District | P25: State
A26: 1010 | B26: Greater Clark County Schools | C26: 13880175 | D26: 5252750.9 | E26: =SUM(C26:D26) -> 19132926 | F26: 24018514 | G26: 22055146 | H26: =SUM(F26:G26) -> 46073660 | I26: 5297135.6 | J26: 4699504.9 | K26: =SUM(I26:J26) -> 9996640.5 | L26: 840109.38 | M26: 1252886.4 | N26: =SUM(L26:M26) -> 2092995.8 | O26: District | P26: State
A27: 1125 | B27: Clay Community Schools | C27: 3763162.9 | D27: 630707.11 | E27: =SUM(C27:D27) -> 4393870 | F27: 10513718 | G27: 9677453.8 | H27: =SUM(F27:G27) -> 20191172 | I27: 1298894.3 | J27: 1646659.8 | K27: =SUM(I27:J27) -> 2945554.1 | L27: 92803.85 | M27: 43167.98 | N27: =SUM(L27:M27) -> 135971.83 | O27: District | P27: State
A28: 1150 | B28: Clinton Central School Corp | C28: 1208514.3 | D28: 420679.94 | E28: =SUM(C28:D28) -> 1629194.3 | F28: 2187142.5 | G28: 1940181.1 | H28: =SUM(F28:G28) -> 4127323.5 | I28: 278931.24 | J28: 255346.76 | K28: =SUM(I28:J28) -> 534278 | L28: 218257.95 | M28: 6112.9 | N28: =SUM(L28:M28) -> 224370.85 | O28: District | P28: State
... A32: 1300 | B32: Crawford Co Com School Corp | C32: 180405.87 | D32: 1298084.2 | E32: =SUM(C32:D32) -> 1478490 | F32: 4794821.7 | G32: 4502700.2 | H32: =SUM(F32:G32) -> 9297521.9 | I32: 721469.62 | J32: 739123.19 | K32: =SUM(I32:J32) -> 1460592.8 | L32: 230601.61 | M32: 107893.97 | N32: =SUM(L32:M32) -> 338495.58 | O32: District | P32: State
A33: 1315 | B33: Barr-Reeve Com Schools Inc | C33: 2340945.7 | D33: 2237871.2 | E33: =SUM(C33:D33) -> 4578817 | H33: =SUM(F33:G33) -> 0 | K33: =SUM(I33:J33) -> 0 | N33: =SUM(L33:M33) -> 0 | O33: District | P33: State
A34: 1375 | B34: North Daviess Com Schools | C34: 1185654.5 | D34: 1258990 | E34: =SUM(C34:D34) -> 2444644.5 | F34: 2375713.3 | G34: 2176942.5 | H34: =SUM(F34:G34) -> 4552655.8 | I34: 344087.99 | J34: 357039.8 | K34: =SUM(I34:J34) -> 701127.79 | L34: 9113.96 | M34: 9424.08 | N34: =SUM(L34:M34) -> 18538.04 | O34: District | P34: State
A35: 1405 | B35: Washington Com Schools Inc | C35: 1848953.3 | D35: 2071056.9 | E35: =SUM(C35:D35) -> 3920010.2 | F35: 5966230 | G35: 5562462 | H35: =SUM(F35:G35) -> 11528692 | I35: 536491 | J35: 639439.61 | K35: =SUM(I35:J35) -> 1175930.6 | L35: 2509313.7 | M35: 20453.83 | N35: =SUM(L35:M35) -> 2529767.6 | O35: District | P35: State
A36: 1560 | B36: Sunman-Dearborn Com Sch Corp | C36: 4723797.9 | D36: 2640034.1 | E36: =SUM(C36:D36) -> 7363832.1 | F36: 8678125.1 | G36: 8158629.9 | H36: =SUM(F36:G36) -> 16836755 | I36: 1551948.4 | J36: 1462156.5 | K36: =SUM(I36:J36) -> 3014104.9 | L36: 2763620.2 | M36: 2458534.1 | N36: =SUM(L36:M36) -> 5222154.3 | O36: District | P36: State
A37: 1600 | B37: South Dearborn Com School Corp | C37: 2710256.8 | D37: 1816592.9 | E37: =SUM(C37:D37) -> 4526849.7 | F37: 6630530.7 | G37: 6181101.4 | H37: =SUM(F37:G37) -> 12811632 | I37: 609089.6 | J37: 500782.32 | K37: =SUM(I37:J37) -> 1109871.9 | L37: 829349.35 | M37: 608138.64 | N37: =SUM(L37:M37) -> 1437488 | O37: District | P37: State
A38: 1620 | B38: Lawrenceburg Com School Corp | C38: 4503409.1 | D38: 2511269.9 | E38: =SUM(C38:D38) -> 7014679 | F38: 183294.12 | G38: 1026075.3 | H38: =SUM(F38:G38) -> 1209369.5 | I38: 306913.53 | J38: 266451.37 | K38: =SUM(I38:J38) -> 573364.9 | L38: 17863.37 | M38: 2635.6 | N38: =SUM(L38:M38) -> 20498.97 | O38: District | P38: State
A39: 1655 | B39: Decatur County Com Schools | C39: 171440.45 | D39: 2861219.8 | E39: =SUM(C39:D39) -> 3032660.3 | F39: 4334069.1 | G39: 4142217.6 | H39: =SUM(F39:G39) -> 8476286.7 | I39: 281833.65 | J39: 390790.2 | K39: =SUM(I39:J39) -> 672623.85 | L39: 22916.71 | M39: 7591.87 | N39: =SUM(L39:M39) -> 30508.58 | O39: District | P39: State
A40: 1730 | B40: Greensburg Community Schools | C40: 2577871.3 | D40: 960102.04 | E40: =SUM(C40:D40) -> 3537973.3 | F40: 4114464.1 | G40: 3771535.1 | H40: =SUM(F40:G40) -> 7885999.2 | I40: 741227.64 | J40: 690155.18 | K40: =SUM(I40:J40) -> 1431382.8 | L40: 249352.5 | M40: 16368.9 | N40: =SUM(L40:M40) -> 265721.4 | O40: District | P40: State
A41: 1805 | B41: DeKalb Co Eastern Com Sch Dist | C41: 2849328.5 | D41: 482114.5 | E41: =SUM(C41:D41) -> 3331443 | F41: 2981750 | G41: 2879892.2 | H41: =SUM(F41:G41) -> 5861642.1 | I41: 4078093 | J41: 963384.42 | K41: =SUM(I41:J41) -> 5041477.5 | L41: 2361486.6 | M41: 922211.16 | N41: =SUM(L41:M41) -> 3283697.8 | O41: District | P41: State
A42: 1820 | B42: Garrett-Keyser-Butler Com | C42: 2690185.8 | D42: 427405.11 | E42: =SUM(C42:D42) -> 3117590.9 | F42: 3556399.7 | G42: 3296367.6 | H42: =SUM(F42:G42) -> 6852767.3 | I42: 1124466.7 | J42: 1307437.9 | K42: =SUM(I42:J42) -> 2431904.5 | L42: 1430461.9 | M42: 725767.24 | N42: =SUM(L42:M42) -> 2156229.2 | O42: District | P42: State
A43: 1835 | B43: DeKalb Co Ctl United Sch Dist | C43: 7311741.9 | D43: 1192385.2 | E43: =SUM(C43:D43) -> 8504127.1 | F43: 7786309.2 | G43: 7121930.4 | H43: =SUM(F43:G43) -> 14908240 | I43: 594609.1 | J43: 787121.45 | K43: =SUM(I43:J43) -> 1381730.5 | L43: 180911.97 | M43: 279275.61 | N43: =SUM(L43:M43) -> 460187.58 | O43: District | P43: State
A44: 1875 | B44: Delaware Community School Corp | C44: 2402772.6 | D44: 614195.96 | E44: =SUM(C44:D44) -> 3016968.6 | F44: 6119270.9 | G44: 5709361.1 | H44: =SUM(F44:G44) -> 11828632 | I44: 645569.52 | J44: 645295 | K44: =SUM(I44:J44) -> 1290864.5 | L44: 23267.39 | M44: 20957.01 | N44: =SUM(L44:M44) -> 44224.4 | O44: District | P44: State
A45: 1885 | B45: Harrison-Wash Com School Corp | C45: 1007048.9 | D45: 243653.12 | E45: =SUM(C45:D45) -> 1250702 | F45: 1717137.5 | G45: 1532241.2 | H45: =SUM(F45:G45) -> 3249378.7 | I45: 158544.52 | J45: 165307 | K45: =SUM(I45:J45) -> 323851.52 | L45: 631524.84 | M45: 470233.38 | N45: =SUM(L45:M45) -> 1101758.2 | O45: District | P45: State
... A50: 1970 | B50: Muncie Community Schools | C50: 8486536.6 | D50: 1985360.6 | E50: =SUM(C50:D50) -> 10471897 | F50: 19771877 | G50: 17787761 | H50: =SUM(F50:G50) -> 37559638 | I50: 7007554.8 | J50: 7245621.7 | K50: =SUM(I50:J50) -> 14253177 | L50: 14827596 | M50: 7382414.6 | N50: =SUM(L50:M50) -> 22210011 | O50: District | P50: State
A51: 2040 | B51: Northeast Dubois Co Sch Corp | C51: 1165847.4 | D51: 1227390.9 | E51: =SUM(C51:D51) -> 2393238.3 | F51: 1728327.5 | G51: 1620685.1 | H51: =SUM(F51:G51) -> 3349012.6 | I51: 65947.65 | J51: 90016.33 | K51: =SUM(I51:J51) -> 155963.98 | L51: 2759.04 | N51: =SUM(L51:M51) -> 2759.04 | O51: District | P51: State
A52: 2100 | B52: Southeast Dubois Co Sch Corp | C52: 1285378.9 | D52: 1326271.7 | E52: =SUM(C52:D52) -> 2611650.7 | F52: 2964787.3 | G52: 2711228.6 | H52: =SUM(F52:G52) -> 5676015.9 | I52: 73440.76 | J52: 142642.06 | K52: =SUM(I52:J52) -> 216082.82 | L52: 43292.98 | M52: 11192.84 | N52: =SUM(L52:M52) -> 54485.82 | O52: District | P52: State
A53: 2110 | B53: Southwest Dubois Co Sch Corp | C53: 1414336.9 | D53: 1542733.1 | E53: =SUM(C53:D53) -> 2957070.1 | F53: 4076893.3 | G53: 3839607.7 | H53: =SUM(F53:G53) -> 7916501 | I53: 1596311.6 | J53: 1327078.9 | K53: =SUM(I53:J53) -> 2923390.6 | L53: 60477.5 | M53: 69390.93 | N53: =SUM(L53:M53) -> 129868.43 | O53: District | P53: State
A54: 2120 | B54: Greater Jasper Con Schs | C54: 4691540.6 | D54: 4833120.7 | E54: =SUM(C54:D54) -> 9524661.3 | F54: 4276143.8 | G54: 3817758.3 | H54: =SUM(F54:G54) -> 8093902.2 | I54: 1783828.8 | J54: 1837830.4 | K54: =SUM(I54:J54) -> 3621659.2 | L54: 1492237.8 | M54: 1781955.1 | N54: =SUM(L54:M54) -> 3274192.8 | O54: District | P54: State
A55: 2155 | B55: Fairfield Community Schools | C55: 2257016.6 | D55: 731377.7 | E55: =SUM(C55:D55) -> 2988394.3 | F55: 3938208.9 | G55: 3738477 | H55: =SUM(F55:G55) -> 7676685.8 | I55: 438540.22 | J55: 386943.58 | K55: =SUM(I55:J55) -> 825483.8 | L55: 164474.51 | M55: 51928.23 | N55: =SUM(L55:M55) -> 216402.74 | O55: District | P55: State
A56: 2260 | B56: Baugo Community Schools | C56: 1951762.5 | D56: 523718.57 | E56: =SUM(C56:D56) -> 2475481.1 | F56: 3760013.8 | G56: 3608796.7 | H56: =SUM(F56:G56) -> 7368810.5 | I56: 297971.54 | J56: 377547.65 | K56: =SUM(I56:J56) -> 675519.19 | L56: 22240.37 | M56: 9612.72 | N56: =SUM(L56:M56) -> 31853.09 | O56: District | P56: State
A57: 2270 | B57: Concord Community Schools | C57: 4580700.7 | D57: 1356231.4 | E57: =SUM(C57:D57) -> 5936932.1 | F57: 8844228.9 | G57: 8448026 | H57: =SUM(F57:G57) -> 17292255 | I57: 1220090.1 | J57: 1505577.3 | K57: =SUM(I57:J57) -> 2725667.5 | L57: 1974294.6 | M57: 1779966.6 | N57: =SUM(L57:M57) -> 3754261.1 | O57: District | P57: State
A58: 2275 | B58: Middlebury Community Schools | C58: 4008551 | D58: 1644167.1 | E58: =SUM(C58:D58) -> 5652718.1 | F58: 6911443.3 | G58: 6772886.2 | H58: =SUM(F58:G58) -> 13684330 | I58: 746145.61 | J58: 845799.66 | K58: =SUM(I58:J58) -> 1591945.3 | L58: 24258.11 | M58: 1092985.3 | N58: =SUM(L58:M58) -> 1117243.4 | O58: District | P58: State
A59: 2285 | B59: Wa-Nee Community Schools | C59: 3928782.2 | D59: 1104024.5 | E59: =SUM(C59:D59) -> 5032806.8 | F59: 5971153 | G59: 5552471.9 | H59: =SUM(F59:G59) -> 11523625 | I59: 900489.98 | J59: 900611.69 | K59: =SUM(I59:J59) -> 1801101.7 | L59: 253075.31 | M59: 29016.8 | N59: =SUM(L59:M59) -> 282092.11 | O59: District | P59: State
A60: 2305 | B60: Elkhart Community Schools | C60: 14243734 | D60: 4407218.9 | E60: =SUM(C60:D60) -> 18650953 | F60: 29797038 | G60: 28314198 | H60: =SUM(F60:G60) -> 58111236 | I60: 5093796 | J60: 7972173.1 | K60: =SUM(I60:J60) -> 13065969 | L60: 3316059.6 | M60: 2196733.9 | N60: =SUM(L60:M60) -> 5512793.5 | O60: District | P60: State
A61: 2315 | B61: Goshen Community Schools | C61: 5670984.5 | D61: 1696801.8 | E61: =SUM(C61:D61) -> 7367786.3 | F61: 13950945 | G61: 13087447 | H61: =SUM(F61:G61) -> 27038392 | I61: 3721540.1 | J61: 4305698 | K61: =SUM(I61:J61) -> 8027238.2 | L61: 6035806 | M61: 5268661.1 | N61: =SUM(L61:M61) -> 11304467 | O61: District | P61: State
A62: 2395 | B62: Fayette County School Corp | C62: 4120425.5 | D62: 860523.88 | E62: =SUM(C62:D62) -> 4980949.4 | F62: 9466275.2 | G62: 8783451.2 | H62: =SUM(F62:G62) -> 18249726 | I62: 2922907.4 | J62: 2743865.1 | K62: =SUM(I62:J62) -> 5666772.5 | L62: 1792255.5 | M62: 1135367 | N62: =SUM(L62:M62) -> 2927622.5 | O62: District | P62: State
A63: 2400 | B63: New Albany-Floyd Co Con Sch | C63: 13326530 | D63: 2986334.7 | E63: =SUM(C63:D63) -> 16312865 | F63: 23614219 | G63: 22385474 | H63: =SUM(F63:G63) -> 45999692 | I63: 4119084.8 | J63: 4457556.5 | K63: =SUM(I63:J63) -> 8576641.3 | L63: 121032.15 | M63: 322953.76 | N63: =SUM(L63:M63) -> 443985.91 | O63: District | P63: State
... A78: 2940 | B78: Eastern Sch Dist of Greene Co | C78: 309097.09 | D78: 443445.46 | E78: =SUM(C78:D78) -> 752542.55 | F78: 2951058.1 | G78: 3508532.3 | H78: =SUM(F78:G78) -> 6459590.4 | I78: 180387.96 | J78: 334435.92 | K78: =SUM(I78:J78) -> 514823.88 | L78: 1092057.2 | M78: 4833348.9 | N78: =SUM(L78:M78) -> 5925406.1 | O78: District | P78: State
A79: 2950 | B79: Linton-Stockton School Corp | C79: 882406.94 | D79: 211947 | E79: =SUM(C79:D79) -> 1094353.9 | F79: 3371997.9 | G79: 3112206 | H79: =SUM(F79:G79) -> 6484203.9 | I79: 207156.31 | J79: 385618.64 | K79: =SUM(I79:J79) -> 592774.95 | L79: 1528 | N79: =SUM(L79:M79) -> 1528 | O79: District | P79: State
A80: 2960 | B80: M S D Shakamak Schools | C80: 479835.94 | D80: 148962.15 | E80: =SUM(C80:D80) -> 628798.09 | F80: 2523519.4 | G80: 2336459.4 | H80: =SUM(F80:G80) -> 4859978.8 | I80: 321872.83 | J80: 374075.53 | K80: =SUM(I80:J80) -> 695948.36 | L80: 4041.94 | M80: 8779.7 | N80: =SUM(L80:M80) -> 12821.64 | O80: District | P80: State
A81: 2980 | B81: White River Valley Sch Dist | C81: 1136536.1 | D81: 458022.67 | E81: =SUM(C81:D81) -> 1594558.8 | F81: 1878205.9 | G81: 1851469.6 | H81: =SUM(F81:G81) -> 3729675.5 | I81: 296267.58 | J81: 449981.78 | K81: =SUM(I81:J81) -> 746249.36 | L81: 827537.95 | M81: 102357.89 | N81: =SUM(L81:M81) -> 929895.84 | O81: District | P81: State
A82: 3005 | B82: Hamilton Southeastern Schools | C82: 24799722 | D82: 9972666.5 | E82: =SUM(C82:D82) -> 34772388 | F82: 17889989 | G82: 18610150 | H82: =SUM(F82:G82) -> 36500139 | I82: 930424.68 | J82: 1021403.7 | K82: =SUM(I82:J82) -> 1951828.3 | L82: 9991.7 | M82: 647632.47 | N82: =SUM(L82:M82) -> 657624.17 | O82: District | P82: State
A83: 3025 | B83: Hamilton Heights School Corp | C83: 2989167.7 | D83: 1299186.4 | E83: =SUM(C83:D83) -> 4288354.1 | F83: 4309299.7 | G83: 4095905 | H83: =SUM(F83:G83) -> 8405204.7 | I83: 174308.11 | J83: 297476.99 | K83: =SUM(I83:J83) -> 471785.1 | L83: 165869.67 | M83: 528830.66 | N83: =SUM(L83:M83) -> 694700.33 | O83: District | P83: State
A84: 3030 | B84: Westfield-Washington Schools | C84: 8872579.9 | D84: 3050937.3 | E84: =SUM(C84:D84) -> 11923517 | F84: 7176719 | G84: 7291914.7 | H84: =SUM(F84:G84) -> 14468634 | I84: 346020.98 | J84: 429152.84 | K84: =SUM(I84:J84) -> 775173.82 | L84: 237960.49 | M84: 320578.22 | N84: =SUM(L84:M84) -> 558538.71 | O84: District | P84: State
A85: 3055 | B85: Sheridan Community Schools | C85: 1259565.5 | D85: 145042.58 | E85: =SUM(C85:D85) -> 1404608.1 | F85: 2298801.1 | G85: 2262516.5 | H85: =SUM(F85:G85) -> 4561317.6 | I85: 131634.43 | J85: 141241.34 | K85: =SUM(I85:J85) -> 272875.77 | L85: 72660.75 | M85: 4302.37 | N85: =SUM(L85:M85) -> 76963.12 | O85: District | P85: State
A86: 3060 | B86: Carmel Clay Schools | C86: 28457946 | D86: 11589187 | E86: =SUM(C86:D86) -> 40047133 | F86: 11182416 | G86: 10387705 | H86: =SUM(F86:G86) -> 21570121 | I86: 5031301.5 | J86: 5219152.7 | K86: =SUM(I86:J86) -> 10250454 | L86: 9028253.8 | M86: 5694439.3 | N86: =SUM(L86:M86) -> 14722693 | O86: District | P86: State
A87: 3070 | B87: Noblesville Schools | C87: 9845340.6 | D87: 4080618.5 | E87: =SUM(C87:D87) -> 13925959 | F87: 12476649 | G87: 12400229 | H87: =SUM(F87:G87) -> 24876878 | I87: 536991.9 | J87: 851988.22 | K87: =SUM(I87:J87) -> 1388980.1 | L87: 262780.28 | M87: 835712.57 | N87: =SUM(L87:M87) -> 1098492.9 | O87: District | P87: State
A88: 3115 | B88: Southern Hancock Co Com Sch Corp | C88: 3541781.3 | D88: 842758.95 | E88: =SUM(C88:D88) -> 4384540.3 | F88: 5761313.8 | G88: 5531696.5 | H88: =SUM(F88:G88) -> 11293010 | I88: 166763.91 | J88: 247699.63 | K88: =SUM(I88:J88) -> 414463.54 | L88: 59002.23 | M88: 47060.26 | N88: =SUM(L88:M88) -> 106062.49 | O88: District | P88: State
A89: 3125 | B89: Greenfield-Central Com Schools | C89: 4733452.3 | D89: 1147000.6 | E89: =SUM(C89:D89) -> 5880453 | F89: 6768397.9 | G89: 7493976.3 | H89: =SUM(F89:G89) -> 14262374 | I89: 2619655.4 | J89: 1817353.9 | K89: =SUM(I89:J89) -> 4437009.3 | L89: 3833993.7 | M89: 3847509.8 | N89: =SUM(L89:M89) -> 7681503.5 | O89: District | P89: State
A90: 3135 | B90: Mt Vernon Community Sch Corp | C90: 4271380.7 | D90: 912184.91 | E90: =SUM(C90:D90) -> 5183565.7 | F90: 4746549.8 | G90: 5525306.9 | H90: =SUM(F90:G90) -> 10271857 | I90: 143834.38 | J90: 239104.12 | K90: =SUM(I90:J90) -> 382938.5 | L90: 61974.97 | M90: 7767.03 | N90: =SUM(L90:M90) -> 69742 | O90: District | P90: State
A91: 3145 | B91: Eastern Hancock Co Com Sch Corp | C91: 1190440.8 | D91: 111109 | E91: =SUM(C91:D91) -> 1301549.8 | F91: 2289210 | G91: 2053090.9 | H91: =SUM(F91:G91) -> 4342300.9 | I91: 56410.73 | J91: 62126.71 | K91: =SUM(I91:J91) -> 118537.44 | L91: 21511.72 | M91: 902806.91 | N91: =SUM(L91:M91) -> 924318.63 | O91: District | P91: State
... A114: 3695 | B114: Brownstown Cnt Com Sch Corp | C114: 1767814.3 | D114: 364593.07 | E114: =SUM(C114:D114) -> 2132407.3 | F114: 3800970.3 | G114: 3625016.2 | H114: =SUM(F114:G114) -> 7425986.5 | I114: 277397.35 | J114: 332022.06 | K114: =SUM(I114:J114) -> 609419.41 | L114: 220769.49 | M114: 273813.15 | N114: =SUM(L114:M114) -> 494582.64 | O114: District | P114: State
A115: 3710 | B115: Crothersville Community Schools | C115: 1363718.4 | D115: 56548.36 | E115: =SUM(C115:D115) -> 1420266.8 | F115: 1421504.8 | G115: 1309263.8 | H115: =SUM(F115:G115) -> 2730768.5 | I115: 103755.87 | J115: 89982.22 | K115: =SUM(I115:J115) -> 193738.09 | L115: 7902.45 | N115: =SUM(L115:M115) -> 7902.45 | O115: District | P115: State
A116: 3785 | B116: Kankakee Valley School Corp | C116: 5356895.3 | D116: 2509318 | E116: =SUM(C116:D116) -> 7866213.3 | F116: 5051218.5 | G116: 4681783 | H116: =SUM(F116:G116) -> 9733001.4 | I116: 496671.17 | J116: 482689.67 | K116: =SUM(I116:J116) -> 979360.84 | L116: 92487.79 | M116: 70196.47 | N116: =SUM(L116:M116) -> 162684.26 | O116: District | P116: State
A117: 3815 | B117: Rensselaer Central School Corp | C117: 2275419.5 | D117: 865452.85 | E117: =SUM(C117:D117) -> 3140872.3 | F117: 3491855.6 | G117: 3206775.7 | H117: =SUM(F117:G117) -> 6698631.3 | I117: 259179.13 | J117: 345607.23 | K117: =SUM(I117:J117) -> 604786.36 | L117: 10551.14 | M117: 30161.5 | N117: =SUM(L117:M117) -> 40712.64 | O117: District | P117: State
A118: 3945 | B118: Jay School Corp | C118: 3158486.8 | D118: 3135379.4 | E118: =SUM(C118:D118) -> 6293866.2 | F118: 9211387.5 | G118: 8391165.9 | H118: =SUM(F118:G118) -> 17602553 | I118: 1142138.1 | J118: 1393083.8 | K118: =SUM(I118:J118) -> 2535221.9 | L118: 2574477.3 | M118: 3049970.3 | N118: =SUM(L118:M118) -> 5624447.6 | O118: District | P118: State
A119: 3995 | B119: Madison Consolidated Schools | C119: 3879163.2 | D119: 453502.82 | E119: =SUM(C119:D119) -> 4332666 | F119: 7436955.2 | G119: 7021010.5 | H119: =SUM(F119:G119) -> 14457966 | I119: 801468.4 | J119: 968726.05 | K119: =SUM(I119:J119) -> 1770194.5 | L119: 1652048 | M119: 1903400.4 | N119: =SUM(L119:M119) -> 3555448.4 | O119: District | P119: State
A120: 4000 | B120: Southwestern-Jefferson Co Con | C120: 1077721.7 | D120: 173681.44 | E120: =SUM(C120:D120) -> 1251403.1 | F120: 3692442 | G120: 3404196.4 | H120: =SUM(F120:G120) -> 7096638.4 | I120: 268946.47 | J120: 481245 | K120: =SUM(I120:J120) -> 750191.47 | L120: 2809.34 | M120: 54196.74 | N120: =SUM(L120:M120) -> 57006.08 | O120: District | P120: State
A121: 4015 | B121: Jennings County Schools | C121: 3479219.8 | D121: 444115.33 | E121: =SUM(C121:D121) -> 3923335.2 | F121: 12956961 | G121: 12374714 | H121: =SUM(F121:G121) -> 25331675 | I121: 1342953.1 | J121: 1804280.1 | K121: =SUM(I121:J121) -> 3147233.2 | L121: 432666.77 | M121: 280324.96 | N121: =SUM(L121:M121) -> 712991.73 | O121: District | P121: State
A122: 4145 | B122: Clark-Pleasant Com School Corp | C122: 4993152.4 | D122: 984519.64 | E122: =SUM(C122:D122) -> 5977672 | F122: 8966373.1 | G122: 9506891.9 | H122: =SUM(F122:G122) -> 18473265 | I122: 404948.91 | J122: 714307.36 | K122: =SUM(I122:J122) -> 1119256.3 | L122: 5752965.7 | M122: 6021503.4 | N122: =SUM(L122:M122) -> 11774469 | O122: District | P122: State
A123: 4205 | B123: Center Grove Com Sch Corp | C123: 10148259 | D123: 1032458.9 | E123: =SUM(C123:D123) -> 11180718 | F123: 10566402 | G123: 9818320.6 | H123: =SUM(F123:G123) -> 20384723 | I123: 369166.65 | J123: 278062.22 | K123: =SUM(I123:J123) -> 647228.87 | L123: 5806 | M123: 1761451.1 | N123: =SUM(L123:M123) -> 1767257.1 | O123: District | P123: State
A124: 4215 | B124: Edinburgh Community Sch Corp | C124: 915284.24 | D124: 221592.77 | E124: =SUM(C124:D124) -> 1136877 | F124: 2418498.4 | G124: 2140793.9 | H124: =SUM(F124:G124) -> 4559292.3 | I124: 261176.72 | J124: 324319.1 | K124: =SUM(I124:J124) -> 585495.82 | L124: 33342.59 | M124: 41568.42 | N124: =SUM(L124:M124) -> 74911.01 | O124: District | P124: State
A125: 4225 | B125: Franklin Community School Corp | C125: 4981225.6 | D125: 797940.36 | E125: =SUM(C125:D125) -> 5779166 | F125: 9216463.1 | G125: 9014312.9 | H125: =SUM(F125:G125) -> 18230776 | I125: 415426.9 | J125: 906153.76 | K125: =SUM(I125:J125) -> 1321580.7 | L125: 1526123.9 | M125: 3319379.8 | N125: =SUM(L125:M125) -> 4845503.8 | O125: District | P125: State
A126: 4245 | B126: Greenwood Community Sch Corp | C126: 4942690.2 | D126: 995411.72 | E126: =SUM(C126:D126) -> 5938102 | F126: 6668196.7 | G126: 6229202.8 | H126: =SUM(F126:G126) -> 12897400 | I126: 512410.43 | J126: 759146.52 | K126: =SUM(I126:J126) -> 1271556.9 | L126: 73810.09 | M126: 40526.13 | N126: =SUM(L126:M126) -> 114336.22 | O126: District | P126: State
A127: 4255 | B127: Nineveh-Hensley-Jackson United | C127: 2186091.2 | D127: 323242.34 | E127: =SUM(C127:D127) -> 2509333.5 | F127: 3092406.4 | G127: 2884115.2 | H127: =SUM(F127:G127) -> 5976521.6 | I127: 143634.72 | J127: 172199.47 | K127: =SUM(I127:J127) -> 315834.19 | L127: 22643.45 | M127: 66248.8 | N127: =SUM(L127:M127) -> 88892.25 | O127: District | P127: State
... A153: 4760 | B153: Whiting School City | C153: 4018641.8 | D153: 879287.75 | E153: =SUM(C153:D153) -> 4897929.5 | F153: 1639489.4 | G153: 1598495.9 | H153: =SUM(F153:G153) -> 3237985.2 | I153: 333817.62 | J153: 385472.26 | K153: =SUM(I153:J153) -> 719289.88 | L153: 12048.21 | M153: 44867.56 | N153: =SUM(L153:M153) -> 56915.77 | O153: District | P153: State
A154: 4770 | B154: Cass Township Schools | C154: 866923.35 | D154: 47625.97 | E154: =SUM(C154:D154) -> 914549.32 | F154: 485921.23 | G154: 419265.02 | H154: =SUM(F154:G154) -> 905186.25 | I154: 54199.85 | J154: 56189.98 | K154: =SUM(I154:J154) -> 110389.83 | M154: 673 | N154: =SUM(L154:M154) -> 673 | O154: District | P154: State
A155: 4790 | B155: Dewey Township Schools | C155: 664602.44 | D155: 120589.28 | E155: =SUM(C155:D155) -> 785191.72 | F155: 423194.86 | G155: 391753.84 | H155: =SUM(F155:G155) -> 814948.7 | K155: =SUM(I155:J155) -> 0 | N155: =SUM(L155:M155) -> 0 | O155: District | P155: State
A156: 4805 | B156: New Prairie United School Corp | C156: 4118872.9 | D156: 266407.59 | E156: =SUM(C156:D156) -> 4385280.5 | F156: 4332199.8 | G156: 4076340.6 | H156: =SUM(F156:G156) -> 8408540.4 | I156: 162785.93 | J156: 262233.94 | K156: =SUM(I156:J156) -> 425019.87 | L156: 2007886.6 | M156: 416561.3 | N156: =SUM(L156:M156) -> 2424447.9 | O156: District | P156: State
A157: 4860 | B157: M S D of New Durham Township | C157: 844386.71 | D157: 100391.17 | E157: =SUM(C157:D157) -> 944777.88 | F157: 1764217.1 | G157: 1800171.2 | H157: =SUM(F157:G157) -> 3564388.3 | I157: 97216.94 | J157: 153199.4 | K157: =SUM(I157:J157) -> 250416.34 | L157: 14385.08 | M157: 9621.42 | N157: =SUM(L157:M157) -> 24006.5 | O157: District | P157: State
A158: 4880 | B158: Prairie Township Schools | C158: 83850.63 | D158: 5887.35 | E158: =SUM(C158:D158) -> 89737.98 | F158: 170591.63 | G158: 180295.69 | H158: =SUM(F158:G158) -> 350887.32 | K158: =SUM(I158:J158) -> 0 | L158: 3468.59 | N158: =SUM(L158:M158) -> 3468.59 | O158: District | P158: State
A159: 4925 | B159: Michigan City Area Schools | C159: 11305507 | D159: 1142335.8 | E159: =SUM(C159:D159) -> 12447843 | F159: 12503519 | G159: 11244198 | H159: =SUM(F159:G159) -> 23747718 | I159: 3143641.2 | J159: 4845311.5 | K159: =SUM(I159:J159) -> 7988952.7 | L159: 3041875.5 | M159: 263373.76 | N159: =SUM(L159:M159) -> 3305249.3 | O159: District | P159: State
A160: 4940 | B160: South Central Com School Corp | C160: 875160.89 | D160: 318790.64 | E160: =SUM(C160:D160) -> 1193951.5 | F160: 1489297.3 | G160: 1394277.5 | H160: =SUM(F160:G160) -> 2883574.8 | I160: 81405.03 | J160: 81174.81 | K160: =SUM(I160:J160) -> 162579.84 | L160: 29806.85 | M160: 27107.24 | N160: =SUM(L160:M160) -> 56914.09 | O160: District | P160: State
A161: 4945 | B161: LaPorte Community School Corp | C161: 6587527.9 | D161: 1010987.6 | E161: =SUM(C161:D161) -> 7598515.5 | F161: 12342229 | G161: 12023544 | H161: =SUM(F161:G161) -> 24365773 | I161: 1995553.3 | J161: 2748553.1 | K161: =SUM(I161:J161) -> 4744106.4 | L161: 6837326.1 | M161: 6678890.3 | N161: =SUM(L161:M161) -> 13516216 | O161: District | P161: State
A162: 5075 | B162: North Lawrence Com Schools | C162: 4285855.5 | D162: 3060286.9 | E162: =SUM(C162:D162) -> 7346142.4 | F162: 12150948 | G162: 11349206 | H162: =SUM(F162:G162) -> 23500154 | I162: 2721600.4 | J162: 2541379.3 | K162: =SUM(I162:J162) -> 5262979.8 | L162: 1676983.2 | M162: 3284553 | N162: =SUM(L162:M162) -> 4961536.3 | O162: District | P162: State
A163: 5085 | B163: Mitchell Community Schools | C163: 1711259 | D163: 860987.11 | E163: =SUM(C163:D163) -> 2572246.1 | F163: 4159505.9 | G163: 4497176.9 | H163: =SUM(F163:G163) -> 8656682.7 | I163: 197959.81 | J163: 396927.88 | K163: =SUM(I163:J163) -> 594887.69 | L163: 295566.03 | M163: 14426.24 | N163: =SUM(L163:M163) -> 309992.27 | O163: District | P163: State
A164: 5245 | B164: Frankton-Lapel Community Schs | C164: 2078551 | D164: 202713.31 | E164: =SUM(C164:D164) -> 2281264.3 | F164: 4742558.3 | G164: 4578412.3 | H164: =SUM(F164:G164) -> 9320970.6 | I164: 258735.36 | J164: 321220.41 | K164: =SUM(I164:J164) -> 579955.77 | L164: 10609.52 | M164: 58535.84 | N164: =SUM(L164:M164) -> 69145.36 | O164: District | P164: State
A165: 5255 | B165: South Madison Com Sch Corp | C165: 3442977.4 | D165: 562464.39 | E165: =SUM(C165:D165) -> 4005441.7 | F165: 7900917.1 | G165: 7819248.7 | H165: =SUM(F165:G165) -> 15720166 | I165: 256235.25 | J165: 229848.71 | K165: =SUM(I165:J165) -> 486083.96 | L165: 2510514.5 | M165: 517357.27 | N165: =SUM(L165:M165) -> 3027871.8 | O165: District | P165: State
A166: 5265 | B166: Alexandria Com School Corp | C166: 1354282.8 | D166: 115289.84 | E166: =SUM(C166:D166) -> 1469572.7 | F166: 4033283.1 | G166: 3747478.8 | H166: =SUM(F166:G166) -> 7780761.9 | I166: 532035.9 | J166: 324917.88 | K166: =SUM(I166:J166) -> 856953.78 | L166: 12312.4 | M166: 994.9 | N166: =SUM(L166:M166) -> 13307.3 | O166: District | P166: State
A167: 5275 | B167: Anderson Community School Corp | C167: 10363322 | D167: 1867476.5 | E167: =SUM(C167:D167) -> 12230798 | F167: 24886332 | G167: 22724083 | H167: =SUM(F167:G167) -> 47610415 | I167: 4739086.5 | J167: 5361334.7 | K167: =SUM(I167:J167) -> 10100421 | L167: 947037.78 | M167: 12853.68 | N167: =SUM(L167:M167) -> 959891.46 | O167: District | P167: State
A168: 5280 | B168: Elwood Community School Corp | C168: 1000401.1 | D168: 138412.6 | E168: =SUM(C168:D168) -> 1138813.7 | F168: 5386274.4 | G168: 4219878.6 | H168: =SUM(F168:G168) -> 9606153 | I168: 1089816.9 | J168: 1188734.7 | K168: =SUM(I168:J168) -> 2278551.6 | L168: 15672.13 | M168: 6670.61 | N168: =SUM(L168:M168) -> 22342.74 | O168: District | P168: State
A169: 5300 | B169: M S D Decatur Township | C169: 4674907 | D169: 2686147.1 | E169: =SUM(C169:D169) -> 7361054.1 | F169: 15959434 | G169: 15134259 | H169: =SUM(F169:G169) -> 31093694 | I169: 1046222.2 | J169: 1586362.8 | K169: =SUM(I169:J169) -> 2632585 | L169: 1844457.8 | M169: 395491.97 | N169: =SUM(L169:M169) -> 2239949.7 | O169: District | P169: State
A170: 5310 | B170: Franklin Township Com Sch Corp | C170: 8501948.8 | D170: 1169126.7 | E170: =SUM(C170:D170) -> 9671075.5 | F170: 15131274 | G170: 15278988 | H170: =SUM(F170:G170) -> 30410262 | I170: 621313.41 | J170: 865656.94 | K170: =SUM(I170:J170) -> 1486970.4 | L170: 16256913 | M170: 2975602.7 | N170: =SUM(L170:M170) -> 19232516 | O170: District | P170: State
...

Sheet Sheet2
A1: 9300 | B1: 666.16
A2: 9315 | B2: 778.6
A3: 9315 | B3: 3689.42
A4: 9320 | B4: 74667.01
A5: 9325 | B5: 17088
A6: 9330 | B6: 48891
A7: 9330 | B7: 563375.4
A8: 9340 | B8: 38015
A9: 9340 | B9: 5685.57
A10: 9350 | B10: 500
A11: 9350 | B11: 3985.94
A12: 9360 | B12: 25
... A60: 9665 | B60: 152565

Sheet Figure 3
A1: State Charter School Policies
A2: Figure 3
A3: State Policies | B3: Yes | C3: No | D3: Partial
A4: Charter schools received their funding directly from the state | B4: X
A5: Charter schools are eligible for local funding | B5: X
A6: Cap on funding a charter school can receive | B6: X
A7: District public school receive differential funding (e.g. more funding for 9-12 vs. K-8 schools) | B7: X
A8: Charter schools receive differential funding | B8: X
A9: State allows districts to withhold funding from charter schools for providing adminstrative services | B9: X
A10: State "holds harmless" ditrict funding for charter enrollment | C10: X
A11: School is considered LEA if authorized by non-district organization | C11: X
A12: School is considered LEA if authorized by district | C12: X
A13: Cap on number of charter schools | B13: X1
A14: Cap on number of charters schools authorized per year | B14: X
A15: Cap on number of studens attending charter schools | C15: X
A16: Charter schools have an open enrollment policy | B16: X
A18: 1. Mayors of consolidated cities may sponsor no more than 20 charter schools as of calendar year 2007 and are limited to sponsoring five in

Sheet Figure 5
A1: Figure 5: School Characteristics
C2: Statewide District | D2: Statewide Charter
A3: Percentage of stuents eligible for free or reduced price lunch | C3: 0.374 | D3: 0.603
A4: Percentage of schools eligible for Title 1 | C4: 0.4 | D4: 0.649
A5: Percent of students by school type
B6: Primary (K-5) | C6: 0.473 | D6: 0.59
B7: Middle (6-8) | C7: 0.201 | D7: 0.033
B8: High (9-12) | C8: 0.305 | D8: 0.075
B9: Other (K-12,K-8, etc.) | C9: 0.022 | D9: 0.302

Sheet Figure 6
B2: Findings | C2: Indiana | E2: Use the following options only
A3: Federal Funding | B3: Charters have access to federal funds according to state statutes (Yes = black, No = white)* | C3: Y | E3: Y
B4: Percentage of federal revenue equals percentage of total enrollment for charter schools (Yes = black, No = white) | C4: > | E4: P
A5: State Funding | B5: Charters have access to state funds according to state statutes (Yes = black, No = white) | C5: Y | E5: N
B6: Percentage of state revenue equals percentage of total enrollment for charter schools (Yes = black, No = white) | C6: >
A7: Local Funding | B7: Charters have access to local funds according to state statutes (Yes = black, No = white) | C7: Y
B8: Percentage of local revenue equals percentage of total enrollment for charter schools (Yes = black, No = white) | C8: >
A9: Facilities Funding | B9: Charters have access to facilities funds according to state statutes (Yes = black, No = white) | C9: Y1
B10: Percentage of facilities revenue equals percentage of total enrollment for charter schools (Yes = black, No = white) | C10: N/A
A11: Data Availability | B11: State provides detailed, public data on federal, state, local and other revenues for district schools (Yes = black, Partial = grey, No = white) | C11: P
B12: State provides detailed, public data on federal, state, local and other revenues for charter schools (Yes = black, Partial = grey, No = white) | C12: P
A13: Funding Formula | B13: Charters are treated as LEAs for funding purposes (Yes = black, Partial = grey, No = white) | C13: P
B14: State funds student (black) or the LEA (grey) | C14: S | E14: S | F14: L | H14: Use these options for the query to the left only (B18)
B15: State funding formula is fair and equitable (Yes = black, No = white | C15: N
A17: * For this finding, No could indicate that the statue is silent or that it denies access.
A19: 1. HB1001, passed in 2005, provides that if the United States Department of Education approves a new competition for states to receive matching funds for charter school facilities, the State Department of Education shall pursue this federal funding; appropriates ten million dollars ($10,000,000) to the department from the common school fund interest balance in the state general fund to provide state matching funds for the federal funding for the benefit of charter schools, beginning July 1, 2005, and ending June 30, 2007.

Sheet Districts
A1: Corp | B1: Corporation Name | C1: Local Revenue | D1: State Revenue | E1: Federal Revenue | F1: Other Revenue | G1: District/charter | K1: CNAME | L1: CORP | M1: PE07PK | N1: PE07TOT | O1: Total Less Pre-K
A2: 15 | B2: Adams Central Community Schools | C2: 2680595.8 | D2: 4156506.5 | E2: 586287.7 | F2: 1010776.6 | G2: District | H2: State | K2: ="Adams Central Community Schools " -> Adams Central Community Schools | L2: ="0015" -> 0015 | M2: 0 | N2: 1163 | O2: =N2-M2 -> 1163
A3: 25 | B3: North Adams Community Schools | C3: 5616787.1 | D3: 8524549.7 | E3: 834711.52 | F3: 58604.38 | G3: District | H3: State | K3: ="North Adams Community Schools " -> North Adams Community Schools | L3: ="0025" -> 0025 | M3: 0 | N3: 2187 | O3: =N3-M3 -> 2187
A4: 35 | B4: South Adams Schools | C4: 2998331.6 | D4: 5774042 | E4: 1389538.8 | F4: 31391.12 | G4: District | H4: State | K4: ="South Adams Schools " -> South Adams Schools | L4: ="0035" -> 0035 | M4: 28 | N4: 1411 | O4: =N4-M4 -> 1383
A5: 125 | B5: M S D Southwest Allen County | C5: 15617511 | D5: 13235239 | E5: 2963000.9 | F5: 5189697.6 | G5: District | H5: State | K5: ="M S D Southwest Allen County " -> M S D Southwest Allen County | L5: ="0125" -> 0125 | M5: 0 | N5: 6612 | O5: =N5-M5 -> 6612
A6: 225 | B6: Northwest Allen County Schools | C6: 10025540 | D6: 17666338 | E6: 1132933.1 | F6: 239459.86 | G6: District | H6: State | K6: ="Northwest Allen County Schools " -> Northwest Allen County Schools | L6: ="0225" -> 0225 | M6: 0 | N6: 6035 | O6: =N6-M6 -> 6035
A7: 235 | B7: Fort Wayne Community Schools | C7: 42241346 | D7: 1.3244583e+08 | E7: 31323336 | F7: 8503019.1 | G7: District | H7: State | K7: ="Fort Wayne Community Schools " -> Fort Wayne Community Schools | L7: ="0235" -> 0235 | M7: 870 | N7: 31884 | O7: =N7-M7 -> 31014
A8: 255 | B8: East Allen County Schools | C8: 13410756 | D8: 40407830 | E8: 6553015.2 | F8: 14177318 | G8: District | H8: State | K8: ="East Allen County Schools " -> East Allen County Schools | L8: ="0255" -> 0255 | M8: 111 | N8: 10228 | O8: =N8-M8 -> 10117
A9: 365 | B9: Bartholomew Con School Corp | C9: 19401016 | D9: 36993028 | E9: 10701245 | F9: 2771866 | G9: District | H9: State | K9: ="Bartholomew Con School Corp " -> Bartholomew Con School Corp | L9: ="0365" -> 0365 | M9: 222 | N9: 11098 | O9: =N9-M9 -> 10876
A10: 370 | B10: Flat Rock-Hawcreek School Corp | C10: 849625.5 | D10: 5314330.1 | E10: 353526.2 | F10: 27271.54 | G10: District | H10: State | K10: ="Flat Rock-Hawcreek School Corp " -> Flat Rock-Hawcreek School Corp | L10: ="0370" -> 0370 | M10: 16 | N10: 1103 | O10: =N10-M10 -> 1087
A11: 395 | B11: Benton Community School Corp | C11: 4904107.1 | D11: 6835605.4 | E11: 337873.81 | F11: 164185.01 | G11: District | H11: State | K11: ="Benton Community School Corp " -> Benton Community School Corp | L11: ="0395" -> 0395 | M11: 0 | N11: 1948 | O11: =N11-M11 -> 1948
A12: 515 | B12: Blackford County Schools | C12: 2140558.7 | D12: 10350792 | E12: 1470835.5 | F12: 95302.53 | G12: District | H12: State | K12: ="Blackford County Schools " -> Blackford County Schools | L12: ="0515" -> 0515 | M12: 6 | N12: 2258 | O12: =N12-M12 -> 2252
A13: 615 | B13: Western Boone Co Com Sch Dist | C13: 2501348.8 | D13: 7057671.2 | E13: 292242.81 | F13: 23121.37 | G13: District | H13: State | K13: ="Western Boone Co Com Sch Dist " -> Western Boone Co Com Sch Dist | L13: ="0615" -> 0615 | M13: 88 | N13: 1916 | O13: =N13-M13 -> 1828
A14: 630 | B14: Zionsville Community Schools | C14: 9193705.4 | D14: 14185932 | E14: 387901.62 | F14: 325 | G14: District | H14: State | K14: ="Zionsville Community Schools " -> Zionsville Community Schools | L14: ="0630" -> 0630 | M14: 37 | N14: 4959 | O14: =N14-M14 -> 4922
A15: 665 | B15: Lebanon Community School Corp | C15: 4056562.3 | D15: 12686102 | E15: 1414748.7 | F15: 544943.89 | G15: District | H15: State | K15: ="Lebanon Community School Corp " -> Lebanon Community School Corp | L15: ="0665" -> 0665 | M15: 24 | N15: 3529 | O15: =N15-M15 -> 3505
A16: 670 | B16: Brown County School Corporation | C16: 6578275.9 | D16: 7259717.3 | E16: 1430207.4 | F16: 56193.29 | G16: District | H16: State | K16: ="Brown County School Corporation " -> Brown County School Corporation | L16: ="0670" -> 0670 | M16: 18 | N16: 2295 | O16: =N16-M16 -> 2277
A17: 750 | B17: Carroll Consolidated Sch Corp | C17: 1931288 | D17: 3873234.6 | E17: 303165.91 | F17: 1783173.5 | G17: District | H17: State | K17: ="Carroll Consolidated Sch Corp " -> Carroll Consolidated Sch Corp | L17: ="0750" -> 0750 | M17: 0 | N17: 1138 | O17: =N17-M17 -> 1138
A18: 755 | B18: Delphi Community School Corp | C18: 2325723 | D18: 6500627.5 | E18: 669567.95 | F18: 24535.01 | G18: District | H18: State | K18: ="Delphi Community School Corp " -> Delphi Community School Corp | L18: ="0755" -> 0755 | M18: 0 | N18: 1649 | O18: =N18-M18 -> 1649
A19: 775 | B19: Pioneer Regional School Corp | C19: 1319358.8 | D19: 3768497.4 | E19: 314793.05 | F19: 89064.09 | G19: District | H19: State | K19: ="Pioneer Regional School Corp " -> Pioneer Regional School Corp | L19: ="0775" -> 0775 | M19: 0 | N19: 1028 | O19: =N19-M19 -> 1028
A20: 815 | B20: Southeastern School Corp | C20: 2439634.7 | D20: 6365107.6 | E20: 520110.87 | F20: 15752.98 | G20: District | H20: State | K20: ="Southeastern School Corp " -> Southeastern School Corp | L20: ="0815" -> 0815 | M20: 0 | N20: 1607 | O20: =N20-M20 -> 1607
A21: 875 | B21: Logansport Community Sch Corp | C21: 4322061.9 | D21: 21129512 | E21: 6490186.4 | F21: 9321446.2 | G21: District | H21: State | K21: ="Logansport Community Sch Corp " -> Logansport Community Sch Corp | L21: ="0875" -> 0875 | M21: 19 | N21: 4310 | O21: =N21-M21 -> 4291
A22: 940 | B22: West Clark Community Schools | C22: 6554991 | D22: 13024059 | E22: 790700.76 | F22: 769021.23 | G22: District | H22: State | K22: ="West Clark Community Schools " -> West Clark Community Schools | L22: ="0940" -> 0940 | M22: 50 | N22: 3796 | O22: =N22-M22 -> 3746
A23: 1000 | B23: Clarksville Com School Corp | C23: 3445148.2 | D23: 6337788 | E23: 762827.73 | F23: 116460.46 | G23: District | H23: State | K23: ="Clarksville Com School Corp " -> Clarksville Com School Corp | L23: ="1000" -> 1000 | M23: 7 | N23: 1459 | O23: =N23-M23 -> 1452
A24: 1010 | B24: Greater Clark County Schools | C24: 19132926 | D24: 46073660 | E24: 9996640.5 | F24: 2092995.8 | G24: District | H24: State | K24: ="Greater Clark County Schools " -> Greater Clark County Schools | L24: ="1010" -> 1010 | M24: 0 | N24: 10768 | O24: =N24-M24 -> 10768
A25: 1125 | B25: Clay Community Schools | C25: 4393870 | D25: 20191172 | E25: 2945554.1 | F25: 135971.83 | G25: District | H25: State | K25: ="Clay Community Schools " -> Clay Community Schools | L25: ="1125" -> 1125 | M25: 0 | N25: 4661 | O25: =N25-M25 -> 4661
A26: 1150 | B26: Clinton Central School Corp | C26: 1629194.3 | D26: 4127323.5 | E26: 534278 | F26: 224370.85 | G26: District | H26: State | K26: ="Clinton Central School Corp " -> Clinton Central School Corp | L26: ="1150" -> 1150 | M26: 0 | N26: 1077 | O26: =N26-M26 -> 1077
A27: 1160 | B27: Clinton Prairie School Corp | C27: 1685131.9 | D27: 3418112.7 | E27: 379505.1 | F27: 274220.09 | G27: District | H27: State | K27: ="Clinton Prairie School Corp " -> Clinton Prairie School Corp | L27: ="1160" -> 1160 | M27: 0 | N27: 1012 | O27: =N27-M27 -> 1012
A28: 1170 | B28: Community Schools of Frankfort | C28: 3069582.3 | D28: 15191121 | E28: 5703189.6 | F28: 4239430.4 | G28: District | H28: State | K28: ="Community Schools of Frankfort " -> Community Schools of Frankfort | L28: ="1170" -> 1170 | M28: 63 | N28: 3320 | O28: =N28-M28 -> 3257
A29: 1180 | B29: Rossville Con School District | C29: 1349687.9 | D29: 3652632.6 | E29: 334237.01 | F29: 22315.77 | G29: District | H29: State | K29: ="Rossville Con School District " -> Rossville Con School District | L29: ="1180" -> 1180 | M29: 0 | N29: 1014 | O29: =N29-M29 -> 1014
A30: 1300 | B30: Crawford Co Com School Corp | C30: 1478490 | D30: 9297521.9 | E30: 1460592.8 | F30: 338495.58 | G30: District | H30: State | K30: ="Crawford Co Com School Corp " -> Crawford Co Com School Corp | L30: ="1300" -> 1300 | M30: 0 | N30: 1809 | O30: =N30-M30 -> 1809
A31: 1315 | B31: Barr-Reeve Com Schools Inc | C31: 4578817 | D31: 0 | E31: 0 | F31: 0 | G31: District | H31: State | K31: ="Barr-Reeve Com Schools Inc " -> Barr-Reeve Com Schools Inc | L31: ="1315" -> 1315 | M31: 0 | N31: 743 | O31: =N31-M31 -> 743
A32: 1375 | B32: North Daviess Com Schools | C32: 2444644.5 | D32: 4552655.8 | E32: 701127.79 | F32: 18538.04 | G32: District | H32: State | K32: ="North Daviess Com Schools " -> North Daviess Com Schools | L32: ="1375" -> 1375 | M32: 0 | N32: 1137 | O32: =N32-M32 -> 1137
A33: 1405 | B33: Washington Com Schools Inc | C33: 3920010.2 | D33: 11528692 | E33: 1175930.6 | F33: 2529767.6 | G33: District | H33: State | K33: ="Washington Com Schools " -> Washington Com Schools | L33: ="1405" -> 1405 | M33: 0 | N33: 2433 | O33: =N33-M33 -> 2433
A34: 1560 | B34: Sunman-Dearborn Com Sch Corp | C34: 7363832.1 | D34: 16836755 | E34: 3014104.9 | F34: 5222154.3 | G34: District | H34: State | K34: ="Sunman-Dearborn Com Sch Corp " -> Sunman-Dearborn Com Sch Corp | L34: ="1560" -> 1560 | M34: 19 | N34: 4422 | O34: =N34-M34 -> 4403
A35: 1600 | B35: South Dearborn Com School Corp | C35: 4526849.7 | D35: 12811632 | E35: 1109871.9 | F35: 1437488 | G35: District | H35: State | K35: ="South Dearborn Com School Corp " -> South Dearborn Com School Corp | L35: ="1600" -> 1600 | M35: 0 | N35: 2984 | O35: =N35-M35 -> 2984
A36: 1620 | B36: Lawrenceburg Com School Corp | C36: 7014679 | D36: 1209369.5 | E36: 573364.9 | F36: 20498.97 | G36: District | H36: State | K36: ="Lawrenceburg Com School Corp " -> Lawrenceburg Com School Corp | L36: ="1620" -> 1620 | M36: 15 | N36: 1628 | O36: =N36-M36 -> 1613
A37: 1655 | B37: Decatur County Com Schools | C37: 3032660.3 | D37: 8476286.7 | E37: 672623.85 | F37: 30508.58 | G37: District | H37: State | K37: ="Decatur County Com Schools " -> Decatur County Com Schools | L37: ="1655" -> 1655 | M37: 14 | N37: 2293 | O37: =N37-M37 -> 2279
A38: 1730 | B38: Greensburg Community Schools | C38: 3537973.3 | D38: 7885999.2 | E38: 1431382.8 | F38: 265721.4 | G38: District | H38: State | K38: ="Greensburg Community Schools " -> Greensburg Community Schools | L38: ="1730" -> 1730 | M38: 22 | N38: 2169 | O38: =N38-M38 -> 2147
A39: 1805 | B39: DeKalb Co Eastern Com Sch Dist | C39: 3331443 | D39: 5861642.1 | E39: 5041477.5 | F39: 3283697.8 | G39: District | H39: State | K39: ="DeKalb Co Eastern Com Sch Dist " -> DeKalb Co Eastern Com Sch Dist | L39: ="1805" -> 1805 | M39: 0 | N39: 1507 | O39: =N39-M39 -> 1507
A40: 1820 | B40: Garrett-Keyser-Butler Com | C40: 3117590.9 | D40: 6852767.3 | E40: 2431904.5 | F40: 2156229.2 | G40: District | H40: State | K40: ="Garrett-Keyser-Butler Com " -> Garrett-Keyser-Butler Com | L40: ="1820" -> 1820 | M40: 0 | N40: 1720 | O40: =N40-M40 -> 1720
A41: 1835 | B41: DeKalb Co Ctl United Sch Dist | C41: 8504127.1 | D41: 14908240 | E41: 1381730.5 | F41: 460187.58 | G41: District | H41: State | K41: ="DeKalb Co Ctl United Sch Dist " -> DeKalb Co Ctl United Sch Dist | L41: ="1835" -> 1835 | M41: 21 | N41: 4153 | O41: =N41-M41 -> 4132
A42: 1875 | B42: Delaware Community School Corp | C42: 3016968.6 | D42: 11828632 | E42: 1290864.5 | F42: 44224.4 | G42: District | H42: State | K42: ="Delaware Community School Corp " -> Delaware Community School Corp | L42: ="1875" -> 1875 | M42: 0 | N42: 2803 | O42: =N42-M42 -> 2803
A43: 1885 | B43: Harrison-Wash Com School Corp | C43: 1250702 | D43: 3249378.7 | E43: 323851.52 | F43: 1101758.2 | G43: District | H43: State | K43: ="Wes-Del Community Schools " -> Wes-Del Community Schools | L43: ="1885" -> 1885 | M43: 0 | N43: 833 | O43: =N43-M43 -> 833
A44: 1895 | B44: Liberty-Perry Com School Corp | C44: 1029135 | D44: 5232683.5 | E44: 669998.97 | F44: 71326.09 | G44: District | H44: State | K44: ="Liberty-Perry Com School Corp " -> Liberty-Perry Com School Corp | L44: ="1895" -> 1895 | M44: 0 | N44: 1204 | O44: =N44-M44 -> 1204
A45: 1900 | B45: Cowan Community School Corp | C45: 843025.53 | D45: 2732117.1 | E45: 267266.96 | F45: 256883.52 | G45: District | H45: State | K45: ="Cowan Community School Corp " -> Cowan Community School Corp | L45: ="1900" -> 1900 | M45: 0 | N45: 687 | O45: =N45-M45 -> 687
A46: 1910 | B46: Mt Pleasant Twp Com Sch Corp | C46: 2898011.2 | D46: 7545142.9 | E46: 667023.17 | F46: 70237.88 | G46: District | H46: State | K46: ="Yorktown Community Schools " -> Yorktown Community Schools | L46: ="1910" -> 1910 | M46: 0 | N46: 2297 | O46: =N46-M46 -> 2297
A47: 1940 | B47: Daleville Community Schools | C47: 857917.19 | D47: 2313784.9 | E47: 225558.43 | F47: 550573.88 | G47: District | H47: State | K47: ="Daleville Community Schools " -> Daleville Community Schools | L47: ="1940" -> 1940 | M47: 0 | N47: 660 | O47: =N47-M47 -> 660
A48: 1970 | B48: Muncie Community Schools | C48: 10471897 | D48: 37559638 | E48: 14253177 | F48: 22210011 | G48: District | H48: State | K48: ="Muncie Community Schools " -> Muncie Community Schools | L48: ="1970" -> 1970 | M48: 169 | N48: 7761 | O48: =N48-M48 -> 7592
A49: 2040 | B49: Northeast Dubois Co Sch Corp | C49: 2393238.3 | D49: 3349012.6 | E49: 155963.98 | F49: 2759.04 | G49: District | H49: State | K49: ="Northeast Dubois Co Sch Corp " -> Northeast Dubois Co Sch Corp | L49: ="2040" -> 2040 | M49: 7 | N49: 979 | O49: =N49-M49 -> 972
A50: 2100 | B50: Southeast Dubois Co Sch Corp | C50: 2611650.7 | D50: 5676015.9 | E50: 216082.82 | F50: 54485.82 | G50: District | H50: State | K50: ="Southeast Dubois Co Sch Corp " -> Southeast Dubois Co Sch Corp | L50: ="2100" -> 2100 | M50: 36 | N50: 1498 | O50: =N50-M50 -> 1462
A51: 2110 | B51: Southwest Dubois Co Sch Corp | C51: 2957070.1 | D51: 7916501 | E51: 2923390.6 | F51: 129868.43 | G51: District | H51: State | K51: ="Southwest Dubois Co Sch Corp " -> Southwest Dubois Co Sch Corp | L51: ="2110" -> 2110 | M51: 12 | N51: 1839 | O51: =N51-M51 -> 1827
A52: 2120 | B52: Greater Jasper Con Schs | C52: 9524661.3 | D52: 8093902.2 | E52: 3621659.2 | F52: 3274192.8 | G52: District | H52: State | K52: ="Greater Jasper Con Schs " -> Greater Jasper Con Schs | L52: ="2120" -> 2120 | M52: 33 | N52: 3183 | O52: =N52-M52 -> 3150
A53: 2155 | B53: Fairfield Community Schools | C53: 2988394.3 | D53: 7676685.8 | E53: 825483.8 | F53: 216402.74 | G53: District | H53: State | K53: ="Fairfield Community Schools " -> Fairfield Community Schools | L53: ="2155" -> 2155 | M53: 0 | N53: 2094 | O53: =N53-M53 -> 2094
A54: 2260 | B54: Baugo Community Schools | C54: 2475481.1 | D54: 7368810.5 | E54: 675519.19 | F54: 31853.09 | G54: District | H54: State | K54: ="Baugo Community Schools " -> Baugo Community Schools | L54: ="2260" -> 2260 | M54: 0 | N54: 1888 | O54: =N54-M54 -> 1888
A55: 2270 | B55: Concord Community Schools | C55: 5936932.1 | D55: 17292255 | E55: 2725667.5 | F55: 3754261.1 | G55: District | H55: State | K55: ="Concord Community Schools " -> Concord Community Schools | L55: ="2270" -> 2270 | M55: 0 | N55: 4764 | O55: =N55-M55 -> 4764
A56: 2275 | B56: Middlebury Community Schools | C56: 5652718.1 | D56: 13684330 | E56: 1591945.3 | F56: 1117243.4 | G56: District | H56: State | K56: ="Middlebury Community Schools " -> Middlebury Community Schools | L56: ="2275" -> 2275 | M56: 29 | N56: 4160 | O56: =N56-M56 -> 4131
A57: 2285 | B57: Wa-Nee Community Schools | C57: 5032806.8 | D57: 11523625 | E57: 1801101.7 | F57: 282092.11 | G57: District | H57: State | K57: ="Wa-Nee Community Schools " -> Wa-Nee Community Schools | L57: ="2285" -> 2285 | M57: 0 | N57: 3311 | O57: =N57-M57 -> 3311
A58: 2305 | B58: Elkhart Community Schools | C58: 18650953 | D58: 58111236 | E58: 13065969 | F58: 5512793.5 | G58: District | H58: State | K58: ="Elkhart Community Schools " -> Elkhart Community Schools | L58: ="2305" -> 2305 | M58: 236 | N58: 13691 | O58: =N58-M58 -> 13455
A59: 2315 | B59: Goshen Community Schools | C59: 7367786.3 | D59: 27038392 | E59: 8027238.2 | F59: 11304467 | G59: District | H59: State | K59: ="Goshen Community Schools " -> Goshen Community Schools | L59: ="2315" -> 2315 | M59: 0 | N59: 6235 | O59: =N59-M59 -> 6235
A60: 2395 | B60: Fayette County School Corp | C60: 4980949.4 | D60: 18249726 | E60: 5666772.5 | F60: 2927622.5 | G60: District | H60: State | K60: ="Fayette County School Corp " -> Fayette County School Corp | L60: ="2395" -> 2395 | M60: 199 | N60: 4187 | O60: =N60-M60 -> 3988
A61: 2400 | B61: New Albany-Floyd Co Con Sch | C61: 16312865 | D61: 45999692 | E61: 8576641.3 | F61: 443985.91 | G61: District | H61: State | K61: ="New Albany-Floyd Co Con Sch " -> New Albany-Floyd Co Con Sch | L61: ="2400" -> 2400 | M61: 134 | N61: 11923 | O61: =N61-M61 -> 11789
A62: 2435 | B62: Attica Consolidated Sch Corp | C62: 1669310.8 | D62: 4123145.1 | E62: 536909.27 | F62: 594839.98 | G62: District | H62: State | K62: ="Attica Consolidated Sch Corp " -> Attica Consolidated Sch Corp | L62: ="2435" -> 2435 | M62: 0 | N62: 956 | O62: =N62-M62 -> 956
A63: 2440 | B63: Covington Community Sch Corp | C63: 1625250.2 | D63: 3807976.1 | E63: 462077.57 | F63: 390420.02 | G63: District | H63: State | K63: ="Covington Community Sch Corp " -> Covington Community Sch Corp | L63: ="2440" -> 2440 | M63: 34 | N63: 997 | O63: =N63-M63 -> 963
A64: 2455 | B64: Southeast Fountain School Corp | C64: 2541765.3 | D64: 5201429.5 | E64: 716779.41 | F64: 216065.99 | G64: District | H64: State | K64: ="Southeast Fountain School Corp " -> Southeast Fountain School Corp | L64: ="2455" -> 2455 | M64: 0 | N64: 1353 | O64: =N64-M64 -> 1353
A65: 2475 | B65: Franklin County Com Sch Corp | C65: 4162083.9 | D65: 12570098 | E65: 1322662.6 | F65: 262657.52 | G65: District | H65: State | K65: ="Franklin County Com Sch Corp " -> Franklin County Com Sch Corp | L65: ="2475" -> 2475 | M65: 67 | N65: 3065 | O65: =N65-M65 -> 2998
A66: 2645 | B66: Rochester Community Sch Corp | C66: 3015866.3 | D66: 6676198 | E66: 766704.84 | F66: 38599.19 | G66: District | H66: State | K66: ="Rochester Community Sch Corp " -> Rochester Community Sch Corp | L66: ="2645" -> 2645 | M66: 23 | N66: 1947 | O66: =N66-M66 -> 1924
A67: 2650 | B67: Caston School Corporation | C67: 1593178.2 | D67: 3042094.7 | E67: 213012.37 | F67: 14689.65 | G67: District | H67: State | K67: ="Caston School Corporation " -> Caston School Corporation | L67: ="2650" -> 2650 | M67: 0 | N67: 825 | O67: =N67-M67 -> 825
A68: 2725 | B68: East Gibson School Corporation | C68: 1407957.1 | D68: 4350823.3 | E68: 393553.74 | F68: 25555.96 | G68: District | H68: State | K68: ="East Gibson School Corporation " -> East Gibson School Corporation | L68: ="2725" -> 2725 | M68: 16 | N68: 1024 | O68: =N68-M68 -> 1008
A69: 2735 | B69: North Gibson School Corp | C69: 2817847 | D69: 8171088.6 | E69: 805193.06 | F69: 330601.21 | G69: District | H69: State | K69: ="North Gibson School Corp " -> North Gibson School Corp | L69: ="2735" -> 2735 | M69: 0 | N69: 2125 | O69: =N69-M69 -> 2125
A70: 2765 | B70: South Gibson School Corp | C70: 2996240.6 | D70: 5040578.9 | E70: 303867.49 | F70: 456042.6 | G70: District | H70: State | K70: ="South Gibson School Corp " -> South Gibson School Corp | L70: ="2765" -> 2765 | M70: 0 | N70: 1971 | O70: =N70-M70 -> 1971
A71: 2815 | B71: Eastbrook Community Sch Corp | C71: 1580732.9 | D71: 7492566.9 | E71: 756158.42 | F71: 5188.16 | G71: District | H71: State | K71: ="Eastbrook Community Sch Corp " -> Eastbrook Community Sch Corp | L71: ="2815" -> 2815 | M71: 10 | N71: 1782 | O71: =N71-M71 -> 1772
A72: 2825 | B72: Madison-Grant United Sch Corp | C72: 1711888.3 | D72: 6590057.7 | E72: 868627.19 | F72: 98687.06 | G72: District | H72: State | K72: ="Madison-Grant United Sch Corp " -> Madison-Grant United Sch Corp | L72: ="2825" -> 2825 | M72: 5 | N72: 1556 | O72: =N72-M72 -> 1551
A73: 2855 | B73: Mississinewa Community School Corp | C73: 1549861.9 | D73: 11023593 | E73: 4158266.3 | F73: 763000.54 | G73: District | H73: State | K73: ="Mississinewa Community School Corp" -> Mississinewa Community School Corp | L73: ="2855" -> 2855 | M73: 43 | N73: 2246 | O73: =N73-M73 -> 2203
A74: 2865 | B74: Marion Community Schools | C74: 9550992.9 | D74: 26539304 | E74: 6113505 | F74: 545472.82 | G74: District | H74: State | K74: ="Marion Community Schools " -> Marion Community Schools | L74: ="2865" -> 2865 | M74: 232 | N74: 5252 | O74: =N74-M74 -> 5020
A75: 2920 | B75: Bloomfield School District | C75: 908214.72 | D75: 4619906.6 | E75: 394716.72 | F75: 18827.12 | G75: District | H75: State | K75: ="Bloomfield School District " -> Bloomfield School District | L75: ="2920" -> 2920 | M75: 0 | N75: 1122 | O75: =N75-M75 -> 1122
A76: 2940 | B76: Eastern Sch Dist of Greene Co | C76: 752542.55 | D76: 6459590.4 | E76: 514823.88 | F76: 5925406.1 | G76: District | H76: State | K76: ="Eastern Greene Schools " -> Eastern Greene Schools | L76: ="2940" -> 2940 | M76: 27 | N76: 1411 | O76: =N76-M76 -> 1384
A77: 2950 | B77: Linton-Stockton School Corp | C77: 1094353.9 | D77: 6484203.9 | E77: 592774.95 | F77: 1528 | G77: District | H77: State | K77: ="Linton-Stockton School Corp " -> Linton-Stockton School Corp | L77: ="2950" -> 2950 | M77: 11 | N77: 1346 | O77: =N77-M77 -> 1335
A78: 2960 | B78: M S D Shakamak Schools | C78: 628798.09 | D78: 4859978.8 | E78: 695948.36 | F78: 12821.64 | G78: District | H78: State | K78: ="M S D Shakamak Schools " -> M S D Shakamak Schools | L78: ="2960" -> 2960 | M78: 13 | N78: 929 | O78: =N78-M78 -> 916
A79: 2980 | B79: White River Valley Sch Dist | C79: 1594558.8 | D79: 3729675.5 | E79: 746249.36 | F79: 929895.84 | G79: District | H79: State | K79: ="White River Valley Sch Dist " -> White River Valley Sch Dist | L79: ="2980" -> 2980 | M79: 0 | N79: 885 | O79: =N79-M79 -> 885
A80: 3005 | B80: Hamilton Southeastern Schools | C80: 34772388 | D80: 36500139 | E80: 1951828.3 | F80: 657624.17 | G80: District | H80: State | K80: ="Hamilton Southeastern Schools " -> Hamilton Southeastern Schools | L80: ="3005" -> 3005 | M80: 0 | N80: 15315 | O80: =N80-M80 -> 15315
A81: 3025 | B81: Hamilton Heights School Corp | C81: 4288354.1 | D81: 8405204.7 | E81: 471785.1 | F81: 694700.33 | G81: District | H81: State | K81: ="Hamilton Heights School Corp " -> Hamilton Heights School Corp | L81: ="3025" -> 3025 | M81: 12 | N81: 2224 | O81: =N81-M81 -> 2212
A82: 3030 | B82: Westfield-Washington Schools | C82: 11923517 | D82: 14468634 | E82: 775173.82 | F82: 558538.71 | G82: District | H82: State | K82: ="Westfield-Washington Schools " -> Westfield-Washington Schools | L82: ="3030" -> 3030 | M82: 52 | N82: 5428 | O82: =N82-M82 -> 5376
A83: 3055 | B83: Sheridan Community Schools | C83: 1404608.1 | D83: 4561317.6 | E83: 272875.77 | F83: 76963.12 | G83: District | H83: State | K83: ="Sheridan Community Schools " -> Sheridan Community Schools | L83: ="3055" -> 3055 | M83: 9 | N83: 1203 | O83: =N83-M83 -> 1194
A84: 3060 | B84: Carmel Clay Schools | C84: 40047133 | D84: 21570121 | E84: 10250454 | F84: 14722693 | G84: District | H84: State | K84: ="Carmel Clay Schools " -> Carmel Clay Schools | L84: ="3060" -> 3060 | M84: 114 | N84: 14680 | O84: =N84-M84 -> 14566
A85: 3070 | B85: Noblesville Schools | C85: 13925959 | D85: 24876878 | E85: 1388980.1 | F85: 1098492.9 | G85: District | H85: State | K85: ="Noblesville Schools " -> Noblesville Schools | L85: ="3070" -> 3070 | M85: 65 | N85: 8334 | O85: =N85-M85 -> 8269
A86: 3115 | B86: Southern Hancock Co Com Sch Corp | C86: 4384540.3 | D86: 11293010 | E86: 414463.54 | F86: 106062.49 | G86: District | H86: State | K86: ="Southern Hancock Co Com Sch Corp " -> Southern Hancock Co Com Sch Corp | L86: ="3115" -> 3115 | M86: 58 | N86: 3385 | O86: =N86-M86 -> 3327
A87: 3125 | B87: Greenfield-Central Com Schools | C87: 5880453 | D87: 14262374 | E87: 4437009.3 | F87: 7681503.5 | G87: District | H87: State | K87: ="Greenfield-Central Com Schools " -> Greenfield-Central Com Schools | L87: ="3125" -> 3125 | M87: 108 | N87: 4655 | O87: =N87-M87 -> 4547
A88: 3135 | B88: Mt Vernon Community Sch Corp | C88: 5183565.7 | D88: 10271857 | E88: 382938.5 | F88: 69742 | G88: District | H88: State | K88: ="Mt Vernon Community Sch Corp " -> Mt Vernon Community Sch Corp | L88: ="3135" -> 3135 | M88: 16 | N88: 3483 | O88: =N88-M88 -> 3467
A89: 3145 | B89: Eastern Hancock Co Com Sch Corp | C89: 1301549.8 | D89: 4342300.9 | E89: 118537.44 | F89: 924318.63 | G89: District | H89: State | K89: ="Eastern Hancock Co Com Sch Corp " -> Eastern Hancock Co Com Sch Corp | L89: ="3145" -> 3145 | M89: 11 | N89: 1116 | O89: =N89-M89 -> 1105
A90: 3160 | B90: Lanesville Community School Corp | C90: 776254.36 | D90: 2184348.9 | E90: 66156.43 | F90: 41116.54 | G90: District | H90: State | K90: ="Lanesville Community School Corp " -> Lanesville Community School Corp | L90: ="3160" -> 3160 | M90: 0 | N90: 647 | O90: =N90-M90 -> 647
A91: 3180 | B91: North Harrison Com School Corp | C91: 1983745.7 | D91: 10490805 | E91: 807779.89 | F91: 945963.14 | G91: District | H91: State | K91: ="North Harrison Com School Corp " -> North Harrison Com School Corp | L91: ="3180" -> 3180 | M91: 0 | N91: 2280 | O91: =N91-M91 -> 2280
A92: 3190 | B92: South Harrison Com Schools | C92: 4193155.3 | D92: 11404272 | E92: 2485471.2 | F92: 3736507 | G92: District | H92: State | K92: ="South Harrison Com Schools " -> South Harrison Com Schools | L92: ="3190" -> 3190 | M92: 32 | N92: 3212 | O92: =N92-M92 -> 3180
A93: 3295 | B93: North West Hendricks Schools | C93: 4020356.2 | D93: 5610973.6 | E93: 542188.67 | F93: 63229.53 | G93: District | H93: State | K93: ="North West Hendricks Schools " -> North West Hendricks Schools | L93: ="3295" -> 3295 | M93: 0 | N93: 1775 | O93: =N93-M93 -> 1775
A94: 3305 | B94: Brownsburg Community Sch Corp | C94: 16230726 | D94: 23335212 | E94: 1672959.4 | F94: 3038480.9 | G94: District | H94: State | K94: ="Brownsburg Community Sch Corp " -> Brownsburg Community Sch Corp | L94: ="3305" -> 3305 | M94: 40 | N94: 6959 | O94: =N94-M94 -> 6919
A95: 3315 | B95: Avon Community School Corp | C95: 18386990 | D95: 25183045 | E95: 2047426.3 | F95: 170213.61 | G95: District | H95: State | K95: ="Avon Community School Corp " -> Avon Community School Corp | L95: ="3315" -> 3315 | M95: 52 | N95: 7785 | O95: =N95-M95 -> 7733
A96: 3325 | B96: Danville Community School Corp | C96: 4866728.3 | D96: 8928533.1 | E96: 562904.2 | F96: 1459835.5 | G96: District | H96: State | K96: ="Danville Community School Corp " -> Danville Community School Corp | L96: ="3325" -> 3325 | M96: 24 | N96: 2567 | O96: =N96-M96 -> 2543
A97: 3330 | B97: Plainfield Community Sch Corp | C97: 9768599.5 | D97: 13092986 | E97: 1167093.8 | F97: 1482922.6 | G97: District | H97: State | K97: ="Plainfield Community Sch Corp " -> Plainfield Community Sch Corp | L97: ="3330" -> 3330 | M97: 24 | N97: 4281 | O97: =N97-M97 -> 4257
A98: 3335 | B98: Mill Creek Community Sch Corp | C98: 3194758.9 | D98: 6130361.7 | E98: 244771.74 | F98: 1939189.1 | G98: District | H98: State | K98: ="Mill Creek Community Sch Corp " -> Mill Creek Community Sch Corp | L98: ="3335" -> 3335 | M98: 18 | N98: 1683 | O98: =N98-M98 -> 1665
A99: 3405 | B99: Blue River Valley Schools | C99: 1413125.8 | D99: 3255044.9 | E99: 321467.55 | F99: 23009.11 | G99: District | H99: State | K99: ="Blue River Valley Schools " -> Blue River Valley Schools | L99: ="3405" -> 3405 | M99: 0 | N99: 815 | O99: =N99-M99 -> 815
A100: 3415 | B100: South Henry School Corp | C100: 1471667.4 | D100: 3504732.3 | E100: 182830.06 | F100: 1227217.7 | G100: District | H100: State | K100: ="South Henry School Corp " -> South Henry School Corp | L100: ="3415" -> 3415 | M100: 0 | N100: 828 | O100: =N100-M100 -> 828
...

Sheet Charters State
A1: Corp | B1: Corporation Name | C1: Local Revenue | D1: State Revenue | E1: Federal Revenue | F1: Other Revenue | G1: District/charter | H1: State/Indy | I1: Enrollment | J1: CNAME | K1: CORP | L1: PE07PK | M1: PE07TOT | N1: Total Less Pre-K
A2: 9300 | B2: Campagna Academy Charter School | C2: 326780.33 | D2: 807114.87 | E2: 101921.09 | F2: 666.16 | G2: Charter | H2: State | I2: 132 | J2: ="Campagna Academy Charter School " -> Campagna Academy Charter School | K2: ="9300" -> 9300 | L2: 0 | M2: 132 | N2: =M2-L2 -> 132
A3: 9310 | B3: Charter School of the Dunes | C3: 1342579.3 | D3: 2681037 | E3: 1028482 | F3: 0 | G3: Charter | H3: State | I3: 490 | J3: ="Charter School of the Dunes " -> Charter School of the Dunes | K3: ="9310" -> 9310 | L3: 0 | M3: 490 | N3: =M3-L3 -> 490
A4: 9315 | B4: Signature Learning Inc | C4: 644456.97 | D4: 1221566.3 | E4: 14193 | F4: 4468.02 | G4: Charter | H4: State | I4: 276 | J4: ="Signature School Inc " -> Signature School Inc | K4: ="9315" -> 9315 | L4: 0 | M4: 276 | N4: =M4-L4 -> 276
A5: 9320 | B5: Community Montessori Inc | C5: 1068842.2 | D5: 1022130.9 | E5: 0 | F5: 74667.01 | G5: Charter | H5: State | I5: 314 | J5: ="Community Montessori Inc " -> Community Montessori Inc | K5: ="9320" -> 9320 | L5: 2 | M5: 316 | N5: =M5-L5 -> 314
A6: 9325 | B6: Options Charter School - Carmel | C6: 225369.48 | D6: 882330.8 | E6: 2691.1 | F6: 17088 | G6: Charter | H6: State | I6: 131 | J6: ="Options Charter School - Carmel " -> Options Charter School - Carmel | K6: ="9325" -> 9325 | L6: 0 | M6: 131 | N6: =M6-L6 -> 131
A7: 9330 | B7: Irvington Community School | C7: 1235976.2 | D7: 1960846.6 | E7: 171365.85 | F7: 612266.4 | G7: Charter | H7: Indianapolis | I7: 460 | J7: ="Irvington Community School " -> Irvington Community School | K7: ="9330" -> 9330 | L7: 0 | M7: 460 | N7: =M7-L7 -> 460
A8: 9340 | B8: New Community School | C8: 203265.69 | D8: 312350.7 | E8: 0 | F8: 43700.57 | G8: Charter | H8: State | I8: 73 | J8: ="New Community School " -> New Community School | K8: ="9340" -> 9340 | L8: 0 | M8: 73 | N8: =M8-L8 -> 73
A9: 9350 | B9: Timothy L Johnson Academy | C9: 245493.83 | D9: 1003857.7 | E9: 294125.31 | F9: 4485.94 | G9: Charter | H9: State | I9: 224 | J9: ="Timothy L Johnson Academy " -> Timothy L Johnson Academy | K9: ="9350" -> 9350 | L9: 0 | M9: 224 | N9: =M9-L9 -> 224
A10: 9360 | B10: Veritas Academy | C10: 278144.53 | D10: 649584.44 | E10: 47855.29 | F10: 1585.26 | G10: Charter | H10: State | I10: 182 | J10: ="Veritas Academy " -> Veritas Academy | K10: ="9360" -> 9360 | L10: 0 | M10: 182 | N10: =M10-L10 -> 182
A11: 9370 | B11: Fall Creek Academy | C11: 711319.8 | D11: 1510339.7 | E11: 224613.1 | F11: 332 | G11: Charter | H11: Indianapolis | I11: 307 | J11: ="Fall Creek Academy " -> Fall Creek Academy | K11: ="9370" -> 9370 | L11: 0 | M11: 307 | N11: =M11-L11 -> 307
A12: 9380 | B12: Christel House Academy | C12: 1949162.6 | D12: 1927108.9 | E12: 522362.81 | F12: 19667.97 | G12: Charter | H12: Indianapolis | I12: 384 | J12: ="Christel House Academy " -> Christel House Academy | K12: ="9380" -> 9380 | L12: 0 | M12: 384 | N12: =M12-L12 -> 384
A13: 9390 | B13: Flanner House Elementary School | C13: 488614.88 | D13: 968099.89 | E13: 157918.97 | F13: 2690.48 | G13: Charter | H13: Indianapolis | I13: 227 | J13: ="Flanner House Elementary School " -> Flanner House Elementary School | K13: ="9390" -> 9390 | L13: 0 | M13: 227 | N13: =M13-L13 -> 227
A14: 9400 | B14: KIPP Indpls College Preparatory | C14: 582873.54 | D14: 917455.33 | E14: 267771.11 | F14: 453004.4 | G14: Charter | H14: Indianapolis | I14: 214 | J14: ="KIPP Indpls College Preparatory " -> KIPP Indpls College Preparatory | K14: ="9400" -> 9400 | L14: 0 | M14: 214 | N14: =M14-L14 -> 214
A15: 9445 | B15: Charles A Tindley Accelerated Sch | C15: 1021456.9 | D15: 1085716.7 | E15: 183916.7 | F15: 334292.08 | G15: Charter | H15: Indianapolis | I15: 245 | J15: ="Charles A Tindley Accelerated Schl" -> Charles A Tindley Accelerated Schl | K15: ="9445" -> 9445 | L15: 0 | M15: 245 | N15: =M15-L15 -> 245
A16: 9460 | B16: Thea Bowman Leadership Academy | C16: 1480101.4 | D16: 2896239.5 | E16: 665169.22 | F16: 0 | G16: Charter | H16: State | I16: 572 | J16: ="Thea Bowman Leadership Academy " -> Thea Bowman Leadership Academy | K16: ="9460" -> 9460 | L16: 0 | M16: 572 | N16: =M16-L16 -> 572
A17: 9465 | B17: Rural Community Schools Inc | C17: 189489.96 | D17: 441988.54 | E17: 43604.74 | F17: 168623.87 | G17: Charter | H17: State | I17: 123 | J17: ="Rural Community Schools Inc " -> Rural Community Schools Inc | K17: ="9465" -> 9465 | L17: 0 | M17: 123 | N17: =M17-L17 -> 123
A18: 9470 | B18: Goodwill Education Initiatives Inc | C18: 441615.17 | D18: 541937.94 | E18: 62221.65 | F18: 143309.69 | G18: Charter | H18: Indianapolis | I18: 122 | J18: Goodwill | K18: ="9470" -> 9470 | L18: 0 | M18: 122 | N18: =M18-L18 -> 122
A19: 9475 | B19: Goodwill Education Initiatives II | C19: 418757.25 | D19: 536218.84 | E19: 50701.99 | F19: 134015.94 | G19: Charter | H19: Indianapolis | I19: 125 | J19: Goodwill | K19: ="9475" -> 9475 | L19: 0 | M19: 125 | N19: =M19-L19 -> 125
A20: 9480 | B20: Fountain Square Academy | C20: 592986.79 | D20: 971940.14 | E20: 281787.1 | F20: 309609 | G20: Charter | H20: Indianapolis | I20: 210 | J20: ="Fountain Square Academy " -> Fountain Square Academy | K20: ="9480" -> 9480 | L20: 0 | M20: 210 | N20: =M20-L20 -> 210
A21: 9485 | B21: SE Neighborhood Sch of Excellence | C21: 396077.36 | D21: 925885.97 | E21: 246204.83 | F21: 214026.16 | G21: Charter | H21: Indianapolis | I21: 235 | J21: ="SE Neighborhood Sch of Excellence " -> SE Neighborhood Sch of Excellence | K21: ="9485" -> 9485 | L21: 0 | M21: 235 | N21: =M21-L21 -> 235
A22: 9495 | B22: Joshua Academy | C22: 570590.5 | D22: 859714.75 | E22: 330169.8 | F22: 51236.52 | G22: Charter | H22: State | I22: 228 | J22: ="Joshua Academy " -> Joshua Academy | K22: ="9495" -> 9495 | L22: 0 | M22: 228 | N22: =M22-L22 -> 228
A23: 9525 | B23: Decatur Discovery Academy Inc | C23: 589468.51 | D23: 516467.81 | E23: 14853 | F23: 549.5 | G23: Charter | H23: Indianapolis | I23: 127 | J23: ="Decatur Discovery Academy Inc " -> Decatur Discovery Academy Inc | K23: ="9525" -> 9525 | L23: 0 | M23: 127 | N23: =M23-L23 -> 127
A24: 9535 | B24: Gary Lighthouse Charter School | C24: 1038409.9 | D24: 2418239.2 | E24: 704490.85 | F24: 1544966.2 | G24: Charter | H24: State | I24: 516 | J24: ="Gary Lighthouse Charter School " -> Gary Lighthouse Charter School | K24: ="9535" -> 9535 | L24: 0 | M24: 516 | N24: =M24-L24 -> 516
A25: 9545 | B25: 21st Century Charter Sch of Gary | C25: 789156.14 | D25: 1727589.4 | E25: 339417.98 | F25: 359002.57 | G25: Charter | H25: State | I25: 304 | J25: ="21st Century Charter Sch of Gary " -> 21st Century Charter Sch of Gary | K25: ="9545" -> 9545 | L25: 0 | M25: 304 | N25: =M25-L25 -> 304
A26: 9555 | B26: East Chicago Urban Enterprise Acad | C26: 482871.96 | D26: 1120056.4 | E26: 386630.92 | F26: 370638 | G26: Charter | H26: State | I26: 284 | J26: ="East Chicago Urban Enterprise Acad" -> East Chicago Urban Enterprise Acad | K26: ="9555" -> 9555 | L26: 0 | M26: 284 | N26: =M26-L26 -> 284
A27: 9565 | B27: Galileo Charter School | C27: 304131.31 | D27: 722823.75 | E27: 286742.13 | F27: 124476 | G27: Charter | H27: State | I27: 179 | J27: ="Galileo Charter School " -> Galileo Charter School | K27: ="9565" -> 9565 | L27: 0 | M27: 179 | N27: =M27-L27 -> 179
A28: 9575 | B28: Indpls Lighthouse Charter School | C28: 553095.98 | D28: 1726107.7 | E28: 587394.15 | F28: 4821076.1 | G28: Charter | H28: Indianapolis | I28: 496 | J28: ="Indpls Lighthouse Charter School " -> Indpls Lighthouse Charter School | K28: ="9575" -> 9575 | L28: 13 | M28: 509 | N28: =M28-L28 -> 496
A29: 9585 | B29: West Gary Lighthouse Charter School | C29: 39946.89 | D29: 938733.64 | E29: 468182.88 | F29: 1853061 | G29: Charter | H29: State | I29: 340 | J29: ="West Gary Lighthouse Charter " -> West Gary Lighthouse Charter | K29: ="9585" -> 9585 | L29: 0 | M29: 340 | N29: =M29-L29 -> 340
A30: 9595 | B30: East Chicago Lighthouse Charter | C30: 17190.06 | D30: 243996.6 | E30: 243811.56 | F30: 428778.38 | G30: Charter | H30: State | I30: 115 | J30: ="East Chicago Lighthouse Charter " -> East Chicago Lighthouse Charter | K30: ="9595" -> 9595 | L30: 0 | M30: 115 | N30: =M30-L30 -> 115
A31: 9615 | B31: Andrew J Brown Academy | C31: 1444803.5 | D31: 2651463.2 | E31: 427758.15 | F31: 0 | G31: Charter | H31: Indianapolis | I31: 609 | J31: ="Andrew J Brown Academy " -> Andrew J Brown Academy | K31: ="9615" -> 9615 | L31: 0 | M31: 609 | N31: =M31-L31 -> 609
A32: 9635 | B32: KIPP Lead College Prep Charter | C32: 53436.8 | D32: 257469.88 | E32: 263633.93 | F32: 429384.7 | G32: Charter | H32: State | I32: 81 | J32: ="KIPP Lead College Prep Charter " -> KIPP Lead College Prep Charter | K32: ="9635" -> 9635 | L32: 0 | M32: 81 | N32: =M32-L32 -> 81
A33: 9640 | B33: Options Charter School - Noblesville | C33: 67836.55 | D33: 255192.61 | E33: 301711.8 | F33: 341541.92 | G33: Charter | H33: State | I33: 109 | J33: ="Options Charter Sch - Noblesville " -> Options Charter Sch - Noblesville | K33: ="9640" -> 9640 | L33: 0 | M33: 109 | N33: =M33-L33 -> 109
A34: 9645 | B34: Challenge Foundation Academy | C34: 440684.18 | D34: 571500.79 | E34: 328509.74 | F34: 921409.12 | G34: Charter | H34: Indianapolis | I34: 257 | J34: ="Challenge Foundation Academy " -> Challenge Foundation Academy | K34: ="9645" -> 9645 | L34: 0 | M34: 257 | N34: =M34-L34 -> 257
A35: 9650 | B35: Herron Charter | C35: 459592.69 | D35: 232176.24 | E35: 383820.84 | F35: 513197.92 | G35: Charter | H35: Indianapolis | I35: 98 | J35: ="Herron Charter " -> Herron Charter | K35: ="9650" -> 9650 | L35: 0 | M35: 98 | N35: =M35-L35 -> 98
A36: 9655 | B36: Hope Academy | C36: 56672.06 | D36: 55666.78 | E36: 269482.03 | F36: 86172.46 | G36: Charter | H36: Indianapolis | I36: 28 | J36: ="Hope Academy " -> Hope Academy | K36: ="9655" -> 9655 | L36: 0 | M36: 28 | N36: =M36-L36 -> 28
A37: 9660 | B37: Stonegate Early Clg HS for Sci/Tec | C37: 319775.4 | D37: 295688.65 | E37: 113489 | F37: 480982 | G37: Charter | H37: Indianapolis | I37: 158 | J37: ="Stonegate Early Clg HS for Sci/Tec" -> Stonegate Early Clg HS for Sci/Tec | K37: ="9660" -> 9660 | L37: 0 | M37: 158 | N37: =M37-L37 -> 158
A38: 9665 | B38: Geist Montessori Academy | C38: 15977.43 | D38: 71778.49 | E38: 221000 | F38: 152565 | G38: Charter | H38: State | I38: 38 | J38: ="Geist Montessori Academy " -> Geist Montessori Academy | K38: ="9665" -> 9665 | L38: 0 | M38: 38 | N38: =M38-L38 -> 38
C39: =SUM(C2:C38) -> 21087004 | D39: =SUM(D2:D38) -> 37928417 | E39: =SUM(E2:E38) -> 10038005 | F39: =SUM(F2:F38) -> 15017536 | I39: =SUM(I2:I38) -> 9013
C40: =C39/I39 -> 2339.621 | D40: =D39/I39 -> 4208.19 | E40: =E39/I39 -> 1113.7251 | F40: =F39/I39 -> 1666.2084 | J40: Not included in analysis as the school did not have enrollment in FY07
A42: 9590 | B42: Monument Lighthouse Charter School | C42: 4240.72 | D42: 0 | E42: 145000 | F42: 56.6 | G42: Charter

Sheet Charters Indy
A1: Corp | B1: Corporation Name | C1: Local Revenue | D1: State Revenue | E1: Federal Revenue | F1: Other Revenue | G1: District/charter | H1: State/Indy | I1: Enrollment
A2: 9330 | B2: Irvington Community School | C2: 1235976.2 | D2: 1960846.6 | E2: 171365.85 | F2: 612266.4 | G2: Charter | H2: Indianapolis | I2: 460
A3: 9370 | B3: Fall Creek Academy | C3: 711319.8 | D3: 1510339.7 | E3: 224613.1 | F3: 332 | G3: Charter | H3: Indianapolis | I3: 307
A4: 9380 | B4: Christel House Academy | C4: 1949162.6 | D4: 1927108.9 | E4: 522362.81 | F4: 19667.97 | G4: Charter | H4: Indianapolis | I4: 384
A5: 9390 | B5: Flanner House Elementary School | C5: 488614.88 | D5: 968099.89 | E5: 157918.97 | F5: 2690.48 | G5: Charter | H5: Indianapolis | I5: 227
A6: 9400 | B6: KIPP Indpls College Preparatory | C6: 582873.54 | D6: 917455.33 | E6: 267771.11 | F6: 453004.4 | G6: Charter | H6: Indianapolis | I6: 214
A7: 9445 | B7: Charles A Tindley Accelerated Sch | C7: 1021456.9 | D7: 1085716.7 | E7: 183916.7 | F7: 334292.08 | G7: Charter | H7: Indianapolis | I7: 245
A8: 9470 | B8: Goodwill Education Initiatives Inc | C8: 441615.17 | D8: 541937.94 | E8: 62221.65 | F8: 143309.69 | G8: Charter | H8: Indianapolis | I8: 122
A9: 9475 | B9: Goodwill Education Initiatives II | C9: 418757.25 | D9: 536218.84 | E9: 50701.99 | F9: 134015.94 | G9: Charter | H9: Indianapolis | I9: 125
A10: 9480 | B10: Fountain Square Academy | C10: 592986.79 | D10: 971940.14 | E10: 281787.1 | F10: 309609 | G10: Charter | H10: Indianapolis | I10: 210
A11: 9485 | B11: SE Neighborhood Sch of Excellence | C11: 396077.36 | D11: 925885.97 | E11: 246204.83 | F11: 214026.16 | G11: Charter | H11: Indianapolis | I11: 235
A12: 9525 | B12: Decatur Discovery Academy Inc | C12: 589468.51 | D12: 516467.81 | E12: 14853 | F12: 549.5 | G12: Charter | H12: Indianapolis | I12: 127
A13: 9575 | B13: Indpls Lighthouse Charter School | C13: 553095.98 | D13: 1726107.7 | E13: 587394.15 | F13: 4821076.1 | G13: Charter | H13: Indianapolis | I13: 509
... A18: 9660 | B18: Stonegate Early Clg HS for Sci/Tec | C18: 319775.4 | D18: 295688.65 | E18: 113489 | F18: 480982 | G18: Charter | H18: Indianapolis | I18: 158
C19: =SUM(C2:C18) -> 11702933 | D19: =SUM(D2:D18) -> 17394621 | E19: =SUM(E2:E18) -> 4294171 | F19: =SUM(F2:F18) -> 9046601.2 | I19: =SUM(I2:I18) -> 4315
