Workbook

Sheet Legend
A2: Legend
D3: Local
D5: State
D7: Federal
D9: Other
D11: Indeterminate
D13: Not Used
D15: Albany
D17: Buffalo
D19: New York City
D21: Focus District
A24: Source | B24: New York Department of Education
A26: All files are "read only" and based on data collections from the New York Department of Education.
A27: The conclusions reached in this document are those of the author(s) and do not necessarily represent those
A28: of Ball State University.

Sheet 1,2,4
A1: Figure 1 | M1: Figure 2
A2: New York (2006-07) | B2: Statewide | D2: Statewide Weighted for Charter Enrollment | F2: Albany | H2: Buffalo | J2: New York City | N2: District | O2: Charter | P2: Difference
A3: Per-Pupil Revenue | M3: State | N3: 19518.393 | O3: 12908.476 | P3: 6609.9172
A4: District | B4: =B14 -> 19518.393 | D4: 19782 | F4: =F14 -> 22761.061 | H4: =H14 -> 18665.733 | J4: =J14 -> 20021.23 | M4: Statewide Weighted | N4: 19782 | O4: 12908 | P4: 6874
A5: Charter | B5: =C14 -> 12908.476 | D5: 12908 | F5: =G14 -> 13261.85 | H5: =I14 -> 11647.269 | J5: =K14 -> 13468.238 | M5: Albany | N5: 22761.061 | O5: 13261.85 | P5: 9499.211
A6: Difference | B6: =B4-B5 -> 6609.9172 | D6: 6874 | F6: =F4-F5 -> 9499.211 | H6: =H4-H5 -> 7018.4643 | J6: =J4-J5 -> 6552.9928 | M6: Buffalo | N6: 18665.733 | O6: 11647.269 | P6: 7018.4643
B7: =B6/B4 -> 0.33865069 | D7: 0.347 | F7: =F6/F4 -> 0.41734483 | H7: =H6/H4 -> 0.37600796 | J7: =J6/J4 -> 0.3273022 | M7: New York City | N7: 20021.23 | O7: 13468.238 | P7: 6552.9928
A8: Per-Pupil Revenue by Source | B8: District | C8: Charter | D8: District | E8: Charter | F8: District | G8: Charter | H8: District | I8: Charter | J8: District | K8: Charter
A9: Federal | B9: ='Dist Work File'!G686 -> 760.54794 | C9: ='Charter Work File'!R98 -> 610.46117 | D9: 1265 | E9: 610.46117 | F9: ='Dist Work File'!G696 -> 1255.6053 | G9: ='Charter Work File'!R198 -> 2015.1528 | H9: ='Dist Work File'!G706 -> 1429.4794 | I9: ='Charter Work File'!R184 -> 551.92395 | J9: ='Dist Work File'!G716 -> 1582.4359 | K9: ='Charter Work File'!R164 -> 343.11588
A10: State | B10: ='Dist Work File'!F686 -> 8856.1444 | C10: ='Charter Work File'!O98 -> 6606.8741 | D10: 10028 | E10: 6606.8741 | F10: ='Dist Work File'!F696 -> 7214.5559 | G10: ='Charter Work File'!O198 -> 4652.9184 | H10: ='Dist Work File'!F706 -> 14085.529 | I10: ='Charter Work File'!O184 -> 8619.6264 | J10: ='Dist Work File'!F716 -> 9741.9882 | K10: ='Charter Work File'!O164 -> 5849.8606
A11: Local | B11: ='Dist Work File'!E686 -> 9756.2939 | C11: ='Charter Work File'!G98 -> 4007.016 | D11: 8401 | E11: 4007.016 | F11: ='Dist Work File'!E696 -> 14241.289 | G11: ='Charter Work File'!G198 -> 5326.9992 | H11: ='Dist Work File'!E706 -> 3031.9092 | I11: ='Charter Work File'!G184 -> 1607.792 | J11: ='Dist Work File'!E716 -> 8659.1841 | K11: ='Charter Work File'!G164 -> 4963.2727
A12: Other | B12: ='Dist Work File'!H686 -> 145.36293 | C12: ='Charter Work File'!Y98 -> 990.72316 | D12: 88 | E12: 990.72316 | F12: ='Dist Work File'!H696 -> 49.610717 | G12: ='Charter Work File'!Y198 -> 763.62924 | H12: ='Dist Work File'!H706 -> 118.81621 | I12: ='Charter Work File'!Y184 -> 294.70288 | J12: ='Dist Work File'!H716 -> 37.500861 | K12: ='Charter Work File'!Y164 -> 1416.0654
A13: Indeterminate | B13: ='Dist Work File'!I686 -> 0.043709732 | C13: ='Charter Work File'!AJ98 -> 693.40121 | D13: - | E13: 693.40121 | F13: ='Dist Work File'!I696 -> 0 | G13: ='Charter Work File'!AJ198 -> 503.15017 | H13: ='Dist Work File'!I706 -> 0 | I13: ='Charter Work File'!AJ184 -> 573.22373 | J13: ='Dist Work File'!I716 -> 0.12142192 | K13: ='Charter Work File'!AJ164 -> 895.92313
A14: Total | B14: =SUM(B9:B13) -> 19518.393 | C14: =SUM(C9:C13) -> 12908.476 | D14: 19782 | E14: 12908.476 | F14: =SUM(F9:F13) -> 22761.061 | G14: =SUM(G9:G13) -> 13261.85 | H14: =SUM(H9:H13) -> 18665.733 | I14: =SUM(I9:I13) -> 11647.269 | J14: =SUM(J9:J13) -> 20021.23 | K14: =SUM(K9:K13) -> 13468.238
A15: Enrollment
A16: District | B16: ='Dist Work File'!C685 -> 2714773 | D16: n/a | F16: ='Dist Work File'!C695 -> 8603 | H16: ='Dist Work File'!C705 -> 34589 | J16: ='Dist Work File'!C715 -> 977270
B17: =B16/(B16+B18) -> 0.99033838 | D17: n/a | F17: =F16/(F16+F18) -> 0.85110803 | H17: =H16/(H16+H18) -> 0.88465178 | J17: =J16/(J16+J18) -> 0.98490995
A18: Charter | B18: ='Charter Work File'!B97 -> 26485 | D18: n/a | F18: ='Charter Work File'!B197 -> 1505 | H18: ='Charter Work File'!B183 -> 4510 | J18: ='Charter Work File'!B163 -> 14973
B19: =B18/(B16+B18) -> 0.0096616225 | D19: n/a | F19: =F18/(F16+F18) -> 0.14889197 | H19: =H18/(H16+H18) -> 0.11534822 | J19: =J18/(J16+J18) -> 0.015090054
A20: Number of Charters | B20: 93 | D20: n/a | F20: 7 | H20: 13 | J20: 58
A21: Total Revenue
A22: District | B22: ='Dist Work File'!J685 -> 52988005852 | D22: n/a | F22: ='Dist Work File'!J695 -> 1.9581341e+08 | H22: ='Dist Work File'!J705 -> 6.4562905e+08 | J22: ='Dist Work File'!J715 -> 1.9566148e+10
B23: =B22/B26 -> 0.99358932 | D23: n/a | F23: =F22/F26 -> 0.9074994 | H23: =H22/H26 -> 0.92476035 | J23: =J22/J26 -> 0.98979857
A24: Charter | B24: ='Charter Work File'!AK97 -> 341880976 | D24: n/a | F24: ='Charter Work File'!AK197 -> 19959084 | H24: ='Charter Work File'!AK183 -> 52529183 | J24: ='Charter Work File'!AK163 -> 201659923
B25: =B24/B26 -> 0.0064106826 | D25: n/a | F25: =F24/F26 -> 0.092500596 | H25: =H24/H26 -> 0.075239653 | J25: =J24/J26 -> 0.010201431
A26: Total | B26: =B22+B24 -> 53329886828 | D26: n/a | F26: =F22+F24 -> 2.1577249e+08 | H26: =H22+H24 -> 6.9815823e+08 | J26: =J22+J24 -> 1.9767808e+10
A27: Percentage of Revenue by Source | B27: District | C27: Charter | D27: District | E27: Charter | F27: District | G27: Charter | H27: District | I27: Charter | J27: District | K27: Charter | M27: Figure 4
A28: Federal | B28: =B9/$B$14 -> 0.038965705 | C28: =C9/$C$14 -> 0.047291499 | D28: 0.063947023 | E28: 0.047291499 | F28: =F9/$F$14 -> 0.055164619 | G28: =G9/$G$14 -> 0.15195111 | H28: =H9/$H$14 -> 0.07658308 | I28: =I9/$I$14 -> 0.047386555 | J28: =J9/$J$14 -> 0.079037895 | K28: =K9/$K$14 -> 0.02547593 | N28: Federal | O28: State | P28: Local | Q28: Other | R28: Indeterminate
A29: State | B29: =B10/$B$14 -> 0.45373328 | C29: =C10/$C$14 -> 0.5118245 | D29: 0.50692549 | E29: 0.5118245 | F29: =F10/$F$14 -> 0.31696923 | G29: =G10/$G$14 -> 0.35084988 | H29: =H10/$H$14 -> 0.75461962 | I29: =I10/$I$14 -> 0.74005558 | J29: =J10/$J$14 -> 0.48658289 | K29: =K10/$K$14 -> 0.43434492 | M29: Statewide District | N29: 760.54794 | O29: 8856.1444 | P29: 9756.2939 | Q29: 145.36293 | R29: 0.043709732
A30: Local | B30: =B11/$B$14 -> 0.49985129 | C30: =C11/$C$14 -> 0.31041744 | D30: 0.424679 | E30: 0.31041744 | F30: =F11/$F$14 -> 0.62568652 | G30: =G11/$G$14 -> 0.40167844 | H30: =H11/$H$14 -> 0.16243183 | I30: =I11/$I$14 -> 0.13804026 | J30: =J11/$J$14 -> 0.4325001 | K30: =K11/$K$14 -> 0.36851686 | M30: Statewide Charter | N30: 610.46117 | O30: 6606.8741 | P30: 4007.016 | Q30: 990.72316 | R30: 693.40121
A31: Other | B31: =B12/$B$14 -> 0.0074474845 | C31: =C12/$C$14 -> 0.076749819 | D31: 0.0044484885 | E31: 0.076749819 | F31: =F12/$F$14 -> 0.0021796311 | G31: =G12/$G$14 -> 0.057580899 | H31: =H12/$H$14 -> 0.0063654726 | I31: =I12/$I$14 -> 0.025302316 | J31: =J12/$J$14 -> 0.0018730547 | K31: =K12/$K$14 -> 0.1051411 | M31: Statewide Weighted | N31: 1265 | O31: 10028 | P31: 8401 | Q31: 88 | R31: -
A32: Change in district school funding if subjected to charter funding structure | M32: Albany District | N32: 1255.6053 | O32: 7214.5559 | P32: 14241.289 | Q32: 49.610717 | R32: 0
B33: ($17.9 billion) | F33: ($81.7 million) | H33: ($242.7 million) | J33: ($6.6 billion) | M33: Albany Charter | N33: 2015.1528 | O33: 4652.9184 | P33: 5326.9992 | Q33: 763.62924 | R33: 503.15017
M34: Buffalo District | N34: 1429.4794 | O34: 14085.529 | P34: 3031.9092 | Q34: 118.81621 | R34: 0
B35: =B6*B16 -> 1.7944425e+10 | F35: =F6*F16 -> 81721713 | H35: =H6*H16 -> 2.4276166e+08 | J35: =J6*J16 -> 6.4040432e+09 | M35: Buffalo Charter | N35: 551.92395 | O35: 8619.6264 | P35: 1607.792 | Q35: 294.70288 | R35: 573.22373
M36: NYC District | N36: 1582.4359 | O36: 9741.9882 | P36: 8659.1841 | Q36: 37.500861 | R36: 0.12142192
M37: NYC Charter | N37: 343.11588 | O37: 5849.8606 | P37: 4963.2727 | Q37: 1416.0654 | R37: 895.92313

Sheet Figure 3
A1: State Charter School Policies
A2: Figure 3
A3: State Policies | B3: Yes | C3: No | D3: Partial
A4: Charter schools received their funding directly from the state | C4: X
A5: Charter schools are eligible for local funding | D5: X
A6: Cap on funding a charter school can receive | C6: X
A7: District public school receive differential funding (e.g. more funding for 9-12 vs. K-8 schools) | B7: X
A8: Charter schools receive differential funding | C8: X
A9: State allows districts to withhold funding from charter schools for providing adminstrative services | C9: X
A10: State "holds harmless" ditrict funding for charter enrollment | C10: X
A11: School is considered LEA if authorized by non-district organization | D11: X
A12: School is considered LEA if authorized by district | D12: X
A13: Cap on number of charter schools | B13: X1
A14: Cap on number of charters schools authorized per year | C14: X
A15: Cap on number of studens attending charter schools | C15: X
A16: Charter schools have an open enrollment policy | B16: X
A18: 1. The State University of New York may authorize 50 charter schools, and the state's Board of Regents may authorize 50. There is no limit on the number of existing district schools that may convert to charter schools. The legislature approved raising the cap to 200 charter schools effective July 1, 2007

Sheet Figure 5
C2: Statewide District | D2: Statewide Charter
A3: Percentage of stuents eligible for free or reduced price lunch | C3: 0.435 | D3: 0.733
A4: Percentage of schools eligible for Title 1 | C4: 0.68 | D4: 0.903
A5: Percent of students by school type
B6: Primary (K-5) | C6: 0.45 | D6: 0.688
B7: Middle (6-8) | C7: 0.195 | D7: 0.102
B8: High (9-12) | C8: 0.306 | D8: 0.029
B9: Other (K-12,K-8, etc.) | C9: 0.048 | D9: 0.18

Sheet Figure 6
A1: Figure 6: State Scorecard
B2: Findings | C2: New York | E2: Use the following options only
A3: Federal Funding | B3: Charters have access to federal funds according to state statutes (Yes = black, No = white) | C3: Y | E3: Y
B4: Percentage of federal revenue equals percentage of total enrollment for charter schools (<, >, or =) | C4: > | E4: P
A5: State Funding | B5: Charters have access to state funds according to state statutes (Yes = black, No = white) | C5: Y | E5: N
B6: Percentage of state revenue equals percentage of total enrollment for charter schools (<, >, or =) | C6: >
A7: Local Funding | B7: Charters have access to local funds according to state statutes (Yes = black, No = white) | C7: N
B8: Percentage of local revenue equals percentage of total enrollment for charter schools (<, >, or =) | C8: >
A9: Facilities Funding | B9: Charters have access to facilities funds according to state statutes (Yes = black, No = white) | C9: Y
B10: Percentage of facilities revenue equals percentage of total enrollment for charter schools (<, >, or =) | C10: NA
A11: Data Availability | B11: State provides detailed, public data on federal, state, local and other revenues for district schools (Yes = black, Partial = grey, No = white) | C11: P
B12: State provides detailed, public data on federal, state, local and other revenues for charter schools (Yes = black, Partial = grey, No = white) | C12: P
A13: Funding Formula | B13: Charters are treated as LEAs for funding purposes (Yes = black, Partial = grey, No = white) | C13: P
B14: State funds student (black) or the LEA (grey) | C14: S | E14: S | F14: L | H14: Use these options for the query to the left only (B18)
B15: State funding formula is fair and equitable (Yes = black, No = white | C15: N
A17: * For this finding, No could indicate that the statue is silent or that it denies access.

Sheet Charter Archive File
B1: New York Charter School Audits | M1: Is this the NY State Stimulus Facility Financing Grant?
B2: FY06-07 | D2: State | E2: Federal | F2: Local | G2: Other | H2: Other | I2: Discard | J2: Other | K2: Indeterminate | L2: Indeterminate | M2: State | N2: Other | O2: Other | P2: Other | Q2: Discard | R2: Local | S2: State | T2: State | U2: Indeterminate | V2: Indeterminate | W2: Other | X2: Indeterminate | Y2: Local | Z2: State | AA2: Federal | AB2: Other | AC2: Indeterminate | AD2: Indeterminate | AE2: State | AF2: Indeterminate | AG2: Indeterminate | AH2: State | AI2: Local | AJ2: Indetemrinate | AK2: Indeterminate | AL2: Federal | AM2: State
C3: District Location | D3: Other State Source | E3: Federal Sources | F3: Local Sources | G3: Private Sources | H3: Contributions | I3: In-Kind Contributions | J3: Other Income | K3: State & Local per pupil Operating | L3: Government Grants and Contracts | M3: Government Grant - Purchase of Land | N3: Benefit Event | O3: Interest Income | P3: Fundraising expenses | Q3: Public School District Revenue/State Aid/NYC Grant | R3: Local Portion Public School District Revenue | S3: State Portion Public School District Revenue | T3: Public School District Sped | U3: Net Assets Released from Restriction | V3: Grants and Other | W3: Revenue from School Operations | X3: Federal, State & Local Grants | Y3: Federal, State & Local Grants | Z3: Federal, State & Local Grants | AA3: Federal, State & Local Grants | AB3: Student Meal Fees | AC3: Various Grants & Honorarius | AD3: Proportionate Share Benefit Agreement | AE3: NYS Stimulus Facility financing grant | AF3: Public Support | AG3: State & City Grants | AH3: State & City Grants | AI3: State & City Grants | AJ3: Other revenue from public school districts | AK3: Federal & State Grants | AL3: Federal & State Grants | AM3: Federal & State Grants | AO3: Total
B4: Brooklyn Excelsior Charter School | C4: NYC | D4: 82544 | E4: 617358 | F4: 44352 | G4: 809841 | Q4: 6318578 | R4: 2964341.8 | S4: 3354236.2 | AO4: =SUM(D4:AN4) -> 14191251
B5: Brooklyn Charter School | C5: NYC | E5: 106924 | H5: 99818 | I5: 462000 | J5: 18475 | Q5: 2376282 | R5: 1114825.5 | S5: 1261456.5 | AO5: =SUM(D5:AN5) -> 5439781
B6: Bronx Preparatory Charter School | C6: NYC | H6: 1103043 | J6: 5988 | L6: 515807 | M6: 350000 | N6: 1250 | O6: 48533 | P6: -66197 | Q6: 5702690 | R6: 2675399.8 | S6: 3027290.2 | AO6: =SUM(D6:AN6) -> 13363804
B7: KIPP Sankofa Charter School | C7: Buffalo | H7: 5200 | J7: 13758 | O7: 68 | Q7: 2181466 | R7: 372538.11 | S7: 1808927.9 | T7: 105425 | U7: 174162 | AO7: =SUM(D7:AN7) -> 4661545
B8: Buffalo Academy of Science Charter School | C8: Buffalo | Q8: 3285894 | R8: 546361.16 | S8: 2739532.8 | V8: 310958 | AO8: =SUM(D8:AN8) -> 6882746
B9: Buffalo United Charter School | C9: Buffalo | D9: 166471 | E9: 620478 | F9: 19292 | Q9: 4445602 | R9: 779070.29 | S9: 3666531.7 | AO9: =SUM(D9:AN9) -> 9697445
B10: Achievement Academy | C10: Albany | D10: 1985 | E10: 169152 | J10: 40088 | Q10: 1318525 | R10: 763500.38 | S10: 555024.62 | T10: 131675 | U10: 157841 | V10: 87500 | AO10: =SUM(D10:AN10) -> 3225291
B11: Achievement First East New York Charter School | C11: NYC | H11: 4000 | J11: 17517 | L11: 398113 | Q11: 2532177 | R11: 1187963.2 | S11: 1344213.8 | AO11: =SUM(D11:AN11) -> 5483984
B12: Achievement First Crown Heights Charter | C12: NYC | H12: 26200 | J12: 40363 | L12: 510760 | Q12: 4291802 | R12: 2013486 | S12: 2278316 | W12: 116972 | AO12: =SUM(D12:AN12) -> 9277899
B13: Achievement First Endeavor Charter School | C13: NYC | H13: 295000 | J13: 650 | O13: 967 | Q13: 846982 | R13: 397359.05 | S13: 449622.95 | X13: 605579 | AB13: 5038 | AD13: brianna call february 12 | AE13: 718-622-4786 | AF13: 18533 ext | AO13: =SUM(D13:AN13) -> 2601198
B14: Westminster Community Charter School | C14: Buffalo | D14: 618210 | E14: 405429 | G14: 504815 | H14: 2133 | J14: 135661 | Q14: 4837511 | R14: 784501.25 | S14: 4053009.7 | T14: 34996 | AO14: =SUM(D14:AN14) -> 11376266
B15: Western New York Maritime Charter | C15: Buffalo | H15: 67084 | J15: 7572 | P15: 13525 | Q15: 2793512 | R15: 482017.54 | S15: 2311494.5 | T15: 450108 | U15: 273172 | AO15: =SUM(D15:AN15) -> 6398485
B16: Williamsburg Collegiate Charter | C16: NYC | H16: 185000 | J16: 17253 | L16: 482069 | Q16: 1431586 | R16: 671624.26 | S16: 759961.74 | AO16: =SUM(D16:AN16) -> 3547494
B17: The Renaissance Charter School | C17: NYC | E17: 279835 | J17: 3961 | Q17: 5291724 | R17: 2482596.4 | S17: 2809127.6 | T17: 415011 | AC17: 198575 | AD17: 9115 | AO17: =SUM(D17:AN17) -> 11489945
B18: Riverhead Charter School | C18: Statewide | L18: 410647 | O18: 898 | Q18: 3796932 | R18: 2148294.4 | S18: 1648637.6 | AO18: =SUM(D18:AN18) -> 8005409
B19: Roosevelt Children's Academy Charter | C19: Statewide | D19: 29466 | E19: 226444 | H19: 5340 | J19: 37672 | O19: 58124 | Q19: 7067201 | R19: 2839171.7 | S19: 4228029.3 | AB19: 176450 | AO19: =SUM(D19:AN19) -> 14667898
B20: Ross Global Academy Charter | C20: NYC | H20: 596250 | I20: 397664 | L20: 290713 | O20: 2930 | Q20: 1734688 | R20: 813823.65 | S20: 920864.35 | AO20: =SUM(D20:AN20) -> 4756933
B21: Sisulu-Walker Charter School of Harlem | C21: NYC | D21: 19246 | E21: 389928 | H21: 34012 | J21: 4891 | O21: 9139 | Q21: 2467850 | R21: 1157784.4 | S21: 1310065.6 | T21: 60209 | AB21: 78604 | AO21: =SUM(D21:AN21) -> 5531729
B22: South Bronx Charter Intl Cultures | C22: NYC | D22: 211167 | E22: 99273 | O22: 17574 | Q22: 2068463 | R22: 970413.18 | S22: 1098049.8 | T22: 7908 | X22: 29311 | AB22: 106761 | AC22: josh - a combination, can't tell off the top of my head. | AD22: 212-786-7900 | AE22: 250000 | AO22: =SUM(D22:AN22) -> 4858920
B23: South Bronx Classical Charter | C23: NYC | H23: 465030 | I23: 70895 | J23: 10993 | Q23: 1307094 | R23: 613219.21 | S23: 693874.79 | X23: 371495 | Y23: 136920 | Z23: 195056 | AA23: 39519 | AC23: Lena | AD23: (718) 860-4340 | AE23: lkonda@southbronxclassical.org Lena | AO23: =SUM(D23:AN23) -> 3904096
B24: South Buffalo Charter | C24: Buffalo | D24: 350000 | E24: 728747 | J24: 36357 | O24: 90737 | Q24: 5964594 | R24: 1056656.5 | S24: 4907937.5 | T24: 316280 | AO24: =SUM(D24:AN24) -> 13451309
B25: Our World Neighborhood Charter | C25: NYC | H25: 66875 | J25: 124624 | L25: 487524 | O25: 44994 | Q25: 7005755 | R25: 3286728.8 | S25: 3719026.2 | AB25: 96854 | AO25: =SUM(D25:AN25) -> 14832381
B26: Peninsula Preparatory Academy Charter | C26: NYC | D26: 19507 | E26: 116508 | H26: 327860 | J26: 23332 | Q26: 2546176 | R26: 1194530.8 | S26: 1351645.2 | T26: 51066 | AB26: 126056 | AO26: =SUM(D26:AN26) -> 5756681
B27: Pinnacle Charter School | C27: Buffalo | E27: 247174 | J27: 9750 | Q27: 3859552 | R27: 726012.01 | S27: 3133540 | T27: 497134 | U27: 6658 | AB27: 131124 | AO27: =SUM(D27:AN27) -> 8610944
B28: King Center Charter School | C28: Buffalo | H28: 1346 | J28: 2142 | O28: 7402 | Q28: 985491 | R28: 159817.5 | S28: 825673.5 | T28: 48646 | U28: 334151 | AO28: =SUM(D28:AN28) -> 2364669
B29: KIPP Academy Charter School | C29: NYC | H29: 2546857 | I29: 3570 | J29: 114929 | L29: 202325 | O29: 116224 | P29: -135463 | Q29: 2688070 | R29: 1261099.9 | S29: 1426970.1 | AO29: =SUM(D29:AN29) -> 8224582
B30: KIPP AMP Academy | C30: NYC | H30: 221632 | I30: 41683 | J30: 38696 | L30: 339570 | O30: 7242 | Q30: 1473829 | R30: 691442.43 | S30: 782386.57 | AO30: =SUM(D30:AN30) -> 3596481
B31: KIPP Infinity Charter | C31: NYC | H31: 220100 | I31: 40197 | J31: 44913 | L31: 302450 | O31: 15088 | Q31: 1687271 | R31: 791578.11 | S31: 895692.89 | AO31: =SUM(D31:AN31) -> 3997290
B32: Family Life Academy Charter | C32: NYC | D32: 267785 | E32: 235903 | I32: 45000 | J32: 22554 | O32: 17689 | Q32: 3156950 | R32: 1482201 | S32: 1674749 | AC32: (718) 410-8100 | AF32: 198029 | AG32: did not want to answer question | AO32: =SUM(D32:AN32) -> 7100860
B33: Ark Community Charter | C33: Statewide | D33: 50000 | E33: 326544 | H33: 7180 | J33: 7278 | O33: 11593 | Q33: 1895827 | R33: 672623.37 | S33: 1223203.6 | AO33: =SUM(D33:AN33) -> 4194249
B34: Carl C. Icahn Charter | C34: NYC | J34: 14116 | O34: 31205 | Q34: 2736898 | R34: 1284007.4 | S34: 1452890.6 | T34: 10815 | V34: 272913 | AO34: =SUM(D34:AN34) -> 5802845
B35: Charter School for Applied Technologies | C35: Statewide | D35: 29909 | E35: 1734293 | J35: 154644 | O35: 386682 | Q35: 13401259 | R35: 2697653.7 | S35: 10703605 | T35: 990404 | U35: 22237 | AO35: =SUM(D35:AN35) -> 30120687
B36: Charter School for Educational Excellence | C36: Statewide | D36: 152247 | E36: 156632 | H36: 5200 | O36: 819 | Q36: 2655696 | R36: 1091870.5 | S36: 1563825.5 | AB36: 86595 | AO36: =SUM(D36:AN36) -> 5712885
B37: New Covenant Charter School | C37: Albany | D37: 27283 | E37: 894921 | J37: 236577 | Q37: 6496868 | R37: 3448538.5 | S37: 3048329.5 | T37: 18394 | U37: 57233 | AO37: =SUM(D37:AN37) -> 14228144
B38: Child Development Center of the Hamptons | C38: Statewide | D38: 21382 | H38: 62667 | J38: 9871 | Q38: 1195807 | T38: 831695 | AO38: =SUM(D38:AN38) -> 2121422
B39: Community Charter School | C39: Buffalo | E39: 179143 | J39: 46040 | Q39: 2610708 | R39: 440496.14 | S39: 2170211.9 | T39: 141520 | AO39: =SUM(D39:AN39) -> 5588119
B40: Community Partnership Charter | C40: NYC | H40: 181687 | J40: 3792 | L40: 215179 | O40: 68381 | Q40: 2937694 | R40: 1378210.3 | S40: 1559483.7 | AO40: =SUM(D40:AN40) -> 6344427
B41: Community Roots Charter School | C41: NYC | E41: 217414 | H41: 417809 | I41: 64984 | O41: 9728 | Q41: 1020822 | R41: 478915.57 | S41: 541906.43 | AC41: (718) 858-1629 | AD41: gar@communityroots.org | AE41: gar | AF41: sent email 12 Feb | AG41: 186527 | AH41: 47115 | AI41: 139412 | AO41: =SUM(D41:AN41) -> 3124633
B42: Brighter Choice Charter School Boys | C42: Albany | D42: 5244 | E42: 222542 | H42: 176387 | J42: 90307 | O42: 21946 | Q42: 1415113 | R42: 811855.11 | S42: 603257.89 | AO42: =SUM(D42:AN42) -> 3346652
B43: Bronx Charter School for Better Learning | C43: NYC | H43: 120265 | J43: 125619 | L43: 162446 | P43: -106991 | Q43: 2322671 | R43: 1089674.1 | S43: 1232996.9 | AO43: =SUM(D43:AN43) -> 4946681
B44: The Bronx Charter School for Children | C44: NYC | H44: 304015 | J44: 5905 | L44: 300740 | O44: 23743 | Q44: 2660639 | R44: 1248230.8 | S44: 1412408.2 | T44: 172546 | AO44: =SUM(D44:AN44) -> 6128227
B45: Bronx Charter School for Excellence | C45: NYC | H45: 334435 | I45: 15186 | J45: 4280 | L45: 68362 | O45: 2617 | P45: -62791 | Q45: 1918323 | R45: 899975.45 | S45: 1018347.5 | AO45: =SUM(D45:AN45) -> 4198735
B46: Bronx Charter School for the Arts | C46: NYC | E46: 187682 | H46: 422776 | J46: 26493 | O46: 22097 | Q46: 3298501 | R46: 1547481.8 | S46: 1751019.2 | AB46: 87823 | AC46: (718) 893-1042 | AD46: sharon johnson ext 145 | AF46: LM 12 Feb | AG46: 214076 | AO46: =SUM(D46:AN46) -> 7557949
B47: Bronx Lighthouse Charter School | C47: NYC | E47: 240744 | I47: 606605 | J47: 11806 | O47: 24338 | Q47: 2790012 | R47: 1308925.7 | S47: 1481086.3 | AC47: (646) 915-0025 | AD47: Reagan Kelly | AE47: LM 12 Feb | AF47: 166815 | AO47: =SUM(D47:AN47) -> 6630332
B48: John V Lindsay Wildcat Charter | C48: NYC | E48: 380274 | H48: 87748 | J48: 7099 | O48: 101475 | Q48: 4333300 | R48: 2032954.6 | S48: 2300345.4 | T48: 859660 | AO48: =SUM(D48:AN48) -> 10102856
B49: Beginning With Children Charter School | C49: NYC | H49: 113676 | L49: 282453 | O49: 57698 | Q49: 4686377 | R49: 2196900.3 | S49: 2489476.7 | AO49: =SUM(D49:AN49) -> 9826581
B50: Achievement First Bushwick Charter | C50: NYC | H50: 255000 | L50: 440884 | O50: 3372 | Q50: 1694371 | R50: 794909.05 | S50: 899461.95 | AB50: 11995 | AO50: =SUM(D50:AN50) -> 4099993
B51: Future Leaders Institute Charter | C51: NYC | H51: 530107 | I51: 77407 | J51: 18558 | Q51: 3280302 | R51: 1538943.8 | S51: 1741358.2 | AC51: (212) 678-2868 | AD51: lmarshall@futureleadersinstitute.org | AF51: sent email 11 Feb | AG51: 321822 | AO51: =SUM(D51:AN51) -> 7508498
A52: NOTE: Review all audit statements above to determine if the audit also includes an "Affliate" agency. | B52: Explore Charter School and Affiliate | C52: NYC | E52: 332895 | H52: 198875 | J52: 7210 | K52: 68739 | O52: 31946 | P52: -9016 | Q52: 3843715 | R52: 1803267.3 | S52: 2040447.7 | AO52: =SUM(D52:AN52) -> 8318079
B53: Opportunity Charter School | C53: NYC | H53: 702032 | J53: 56957 | L53: 390745 | P53: -122043 | Q53: 3819739 | R53: 1792019 | S53: 2027720 | AO53: =SUM(D53:AN53) -> 8667169
B54: Genesee Community Charter School | C54: Statewide | E54: 164547 | H54: 83500 | J54: 50479 | O54: 51505 | Q54: 2047544 | R54: 572500.63 | S54: 1475043.4 | T54: 26756 | AB54: 50037 | AO54: =SUM(D54:AN54) -> 4521912
B55: Girls Preparatory Charter School | C55: NYC | E55: 164594 | H55: 200140 | J55: 46019 | O55: 10813 | Q55: 1394460 | R55: 654206.71 | S55: 740253.29 | AC55: (212) 388-0241 | AG55: 39838 | AO55: =SUM(D55:AN55) -> 3250324
B56: Global Concepts Charter School | C56: Statewide | E56: 520538 | H56: 6500 | J56: 55159 | Q56: 3634166 | R56: 938733.73 | S56: 2695432.3 | T56: 93295 | AO56: =SUM(D56:AN56) -> 7943824
B57: Grand Concourse Academy | C57: NYC | J57: 11025 | L57: 374621 | O57: 11263 | Q57: 2864046 | R57: 1343658.6 | S57: 1520387.4 | AB57: 118434 | AO57: =SUM(D57:AN57) -> 6243435
B58: Democracy Preparatory Charter School | C58: NYC | E58: 228010 | H58: 413946 | I58: 106934 | O58: 12581 | Q58: 1476831 | R58: 692850.81 | S58: 783980.19 | AC58: (212) 281-1248 | AG58: 404079 | AO58: =SUM(D58:AN58) -> 4119212
B59: East NY Preparatory Charter School | C59: NYC | H59: 290500 | J59: 22196 | L59: 363937 | Q59: 1059845 | R59: 497223.09 | S59: 562621.91 | AO59: =SUM(D59:AN59) -> 2796323
B60: Elmwood Village Charter School | C60: Buffalo | D60: 200000 | E60: 209877 | H60: 1300 | J60: 4002 | Q60: 1057881 | R60: 171557.02 | S60: 886323.98 | T60: 25556 | AO60: =SUM(D60:AN60) -> 2556497
B61: Enterprise Charter School | C61: Buffalo | H61: 350 | J61: 49325 | Q61: 5207575 | R61: 893077.04 | S61: 4314498 | T61: 374688 | V61: 1173001 | AJ61: 111420 | AO61: =SUM(D61:AN61) -> 12123934
B62: Eugenio Maria De Hostos Charter | C62: Statewide | J62: 4582 | O62: 29845 | Q62: 2726879 | R62: 657375.75 | S62: 2069503.3 | T62: 80776 | AB62: 171176 | AC62: 585-544-6170 | AD62: Pedro Gomez | AK62: 896561 | AL62: 896561 | AN62: 898561 is all federal, about 95% sure | AO62: =SUM(D62:AN62) -> 7533259
B63: Excellence Charter School of Bedford Stuyvesant | C63: NYC | E63: 137404 | H63: 989184 | J63: 5847 | Q63: 1727664 | R63: 810528.36 | S63: 917135.64 | AC63: (718) 638-1830 | AD63: tsaintsing@excellencecharter.org | AE63: Tim Saintsing | AF63: sent email 11 Feb | AG63: 214076 | AH63: 200000 | AI63: 14076 | AO63: =SUM(D63:AN63) -> 5015915
B64: Southside Academy Charter School | C64: Statewide | D64: 41971 | E64: 641876 | F64: 13792 | G64: 257097 | Q64: 3481545 | R64: 815258.03 | S64: 2666287 | AO64: =SUM(D64:AN64) -> 7917826
B65: Syracuse Academy of Science Charter | C65: Statewide | D65: 3143 | E65: 269634 | J65: 23392 | Q65: 2811637 | R65: 694872.73 | S65: 2116764.3 | T65: 193844 | AO65: =SUM(D65:AN65) -> 6113287
B66: New Heights Academy Charter | C66: NYC | E66: 258026 | H66: 77275 | I66: 25000 | O66: 10066 | Q66: 2166630 | R66: 1016467.9 | S66: 1150162.1 | AC66: (212) 283-5400 | AD66: gene ficsh - LM 110209 | AG66: 531238 | AO66: =SUM(D66:AN66) -> 5234865
B67: New York Center for Autism Charter School | C67: NYC | H67: 120910 | J67: 9311 | Q67: 1074720 | R67: 504201.65 | S67: 570518.35 | AC67: (212) 860-2580 | AF67: LM 12 Feb | AG67: 281567 | AO67: =SUM(D67:AN67) -> 2561228
B68: Oracle Charter School | C68: Buffalo | D68: 309379 | E68: 98329 | H68: 200 | O68: 51738 | Q68: 2300324 | R68: 382995.57 | S68: 1917328.4 | T68: 200105 | AO68: =SUM(D68:AN68) -> 5260399
B69: Tapestry Charter School | C69: Buffalo | H69: 38679 | J69: 44171 | O69: 2230 | Q69: 2542833 | R69: 436749.78 | S69: 2106083.2 | T69: 194904 | V69: 201717 | AB69: 75926 | AO69: =SUM(D69:AN69) -> 5643293
B70: True North Rochester Preparatory Charter | C70: Statewide | H70: 288500 | J70: 4877 | L70: 619158 | Q70: 743071 | R70: 168085.97 | S70: 574985.03 | AO70: =SUM(D70:AN70) -> 2398677
B71: The UFT Charter School | C71: NYC | H71: 473089 | J71: 20128 | L71: 536212 | N71: 31000 | O71: 20127 | Q71: 3637412 | R71: 1709551.9 | S71: 1927860.1 | AO71: =SUM(D71:AN71) -> 8355380
B72: Niagara Charter School | C72: Statewide | H72: 947 | J72: 28005 | Q72: 2278236 | R72: 503021.18 | S72: 1775214.8 | T72: 144899 | V72: 485722 | AJ72: 23822 | AO72: =SUM(D72:AN72) -> 5239867
B73: Urban Choice Charter School | C73: Statewide | E73: 276513 | J73: 11665 | O73: 8873 | Q73: 2509799 | R73: 576456.12 | S73: 1933342.9 | T73: 53436 | AB73: 119446 | AO73: =SUM(D73:AN73) -> 5489531
B74: The Williamsburg Charter High School | C74: NYC | H74: 233643 | J74: 19055 | L74: 281579 | N74: 7075 | P74: -208069 | Q74: 4763457 | R74: 2234761.5 | S74: 2528695.5 | AO74: =SUM(D74:AN74) -> 9860197
B75: Hellenic Classical Charter School | C75: NYC | I75: 534000 | J75: 17823 | Q75: 1831610 | R75: 859294.31 | S75: 972315.69 | AG75: 9688 | AO75: =SUM(D75:AN75) -> 4224731
B76: Hyde Leadership Charter School | C76: NYC | H76: 294174 | I76: 41261 | J76: 29488 | L76: 373297 | Q76: 2009233 | R76: 942625.61 | S76: 1066607.4 | AO76: =SUM(D76:AN76) -> 4756686
B77: International Charter School of Schenectady | C77: Statewide | D77: 36804 | E77: 295026 | J77: 301586 | Q77: 6038794 | R77: 2152750.7 | S77: 3886043.3 | T77: 175995 | U77: 46008 | AO77: =SUM(D77:AN77) -> 12933007
B78: International Leadership Charter School | C78: NYC | H78: 253525 | I78: 100000 | J78: 167 | L78: 372044 | P78: -57032 | Q78: 936224 | R78: 439226.67 | S78: 496997.33 | AO78: =SUM(D78:AN78) -> 2541152
B79: Harlem Children's Zone Promise Academy II | C79: NYC | I79: 852463 | Q79: 1444438 | R79: 677653.73 | S79: 766784.27 | AC79: (917) 492-1481 | AK79: 162644 | AO79: =SUM(D79:AN79) -> 3903983
B80: Harlem Day Charter School | C80: NYC | H80: 1423179 | J80: 91954 | L80: 368279 | Q80: 2504902 | R80: 1175167.2 | S80: 1329734.8 | AO80: =SUM(D80:AN80) -> 6893216
B81: Harlem Link Charter School | C81: NYC | D81: 152922 | E81: 332698 | H81: 142526 | Q81: 1669016 | R81: 783013.83 | S81: 886002.17 | T81: 61288 | AO81: =SUM(D81:AN81) -> 4027466
B82: Harlem Success Academy Charter | C82: NYC | E82: 235602 | H82: 1319156 | I82: 17500 | O82: 653 | Q82: 1532948 | R82: 719177.93 | S82: 813770.07 | AC82: (646) 277-7170 | AG82: 173863 | AO82: =SUM(D82:AN82) -> 4812670
B83: Harlem Village Academy | C83: NYC | E83: 106306 | O83: 2201 | Q83: 2092541 | R83: 981709.3 | S83: 1110831.7 | AG83: 23032 | AO83: =SUM(D83:AN83) -> 4316621
B84: Albany Community Charter School | C84: Albany | D84: 77640 | E84: 409080 | I84: 10596 | J84: 176104 | Q84: 1078927 | R84: 609081.54 | S84: 469845.46 | T84: 26216 | AO84: =SUM(D84:AN84) -> 2857490
B85: Albany Preparatory Charter School | C85: Albany | D85: 108883 | E85: 31334 | J85: 38796 | O85: 3032 | Q85: 1073355 | R85: 613841.16 | S85: 459513.84 | T85: 74619 | AO85: =SUM(D85:AN85) -> 2403374
B86: Amber Charter School | C86: NYC | H86: 206013 | J86: 86734 | L86: 506798 | O86: 314 | Q86: 3533526 | R86: 1657743.1 | S86: 1875782.9 | AO86: =SUM(D86:AN86) -> 7866911
B87: KIPP Star College Prep Charter | C87: NYC | H87: 268959 | I87: 40389 | J87: 17692 | L87: 149435 | O87: 116479 | Q87: 3397806 | R87: 1594070.4 | S87: 1803735.6 | AO87: =SUM(D87:AN87) -> 7388566
B88: KIPP Tech Valley Charter School | C88: Albany | D88: 3773 | E88: 59939 | J88: 63296 | Q88: 1583116 | R88: 895694.65 | S88: 687421.35 | T88: 51703 | U88: 454667 | AO88: =SUM(D88:AN88) -> 3799610
B89: Leadership Preparatory Charter School | C89: NYC | H89: 560075 | J89: 13098 | L89: 472382 | Q89: 1182735 | R89: 554876.56 | S89: 627858.44 | AO89: =SUM(D89:AN89) -> 3411025
B90: Leadership Village Academy Charter | C90: NYC | E90: 53552 | O90: 2352 | Q90: 1148559 | R90: 538842.99 | S90: 609716.01 | AG90: 59595 | AO90: =SUM(D90:AN90) -> 2412617
B91: Manhattan Charter School | C91: NYC | D91: 125406 | E91: 131725 | H91: 2440 | J91: 15805 | Q91: 1194011 | R91: 560166.66 | S91: 633844.34 | AO91: =SUM(D91:AN91) -> 2663398
B92: Merrick Academy-Queens Public Charter | C92: NYC | D92: 39110 | E92: 245300 | L92: 2500 | O92: 24316 | Q92: 4961068 | R92: 2324256.6 | S92: 2636811.4 | T92: 52064 | AB92: 165314 | AO92: =SUM(D92:AN92) -> 10450740
B93: The Harbor Science and Arts Charter School | C93: NYC | H93: 32348 | M93: 227200 | Q93: 2151681 | R93: 1009454.7 | S93: 1142226.3 | AO93: =SUM(D93:AN93) -> 4562910
B94: Harlem Children's Zone Promise Academy | C94: NYC | H94: 15010 | I94: 2735094 | J94: 4110 | Q94: 5436684 | R94: 2550603.9 | S94: 2886080.1 | AB94: 194345 | AC94: (212) 534-0700 | AD94: Jim Adamack - LM 110209 | AK94: 212965 | AO94: =SUM(D94:AN94) -> 14034892
B95: Harriet Tubman Charter School | C95: NYC | H95: 4773 | J95: 14847 | L95: 239950 | Q95: 4229282 | R95: 1984154.9 | S95: 2245127.1 | AO95: =SUM(D95:AN95) -> 8718134

Sheet Charter Work File
A1: New York Charter School Audits
A2: FY06-07 | B2: green = Preschool/PreK enrollment | D2: Local | E2: Local | F2: Local | G2: Local | H2: State | I2: State | J2: State | K2: State | L2: State | M2: State | N2: State | O2: State | P2: Federal | Q2: Federal | R2: Federal | S2: Other | T2: Other | U2: Other | V2: Other | W2: Other | X2: Other | Y2: Other | Z2: Indetemrinate | AA2: Indeterminate | AB2: Indeterminate | AC2: Indeterminate | AD2: Indeterminate | AE2: Indeterminate | AF2: Indeterminate | AG2: Indeterminate | AH2: Indeterminate | AI2: Indeterminate | AJ2: Indeterminate | AN2: Discard | AO2: Discard
B3: Enrollment | C3: District Location | D3: Local Sources | E3: Local Portion Public School District Revenue | F3: State & City Grants | G3: Federal, State & Local Grants | H3: Other State Source | I3: Government Grant - Purchase of Land | J3: State Portion Public School District Revenue | K3: Public School District Sped | L3: NYS Stimulus Facility financing grant | M3: State & City Grants | N3: Federal & State Grants | O3: Federal, State & Local Grants | P3: Federal Sources | Q3: Federal, State & Local Grants | R3: Federal & State Grants | S3: Private Sources | T3: Contributions | U3: Other Income | V3: Benefit Event | W3: Interest Income | X3: Revenue from School Operations | Y3: Student Meal Fees | Z3: Other revenue from public school districts | AA3: State & Local per pupil Operating | AB3: Government Grants and Contracts | AC3: Net Assets Released from Restriction | AD3: Grants and Other | AE3: Federal, State & Local Grants | AF3: Various Grants & Honorarius | AG3: Proportionate Share Benefit Agreement | AH3: Public Support | AI3: State & City Grants | AJ3: Federal & State Grants | AK3: Total | AN3: In-Kind Contributions | AO3: Fundraising expenses
A4: Riverhead Charter School | B4: 306 | C4: Statewide | E4: 2148294.4 | J4: 1648637.6 | W4: 898 | AB4: 410647 | AK4: =SUM(D4:AJ4) -> 4208477
A5: Roosevelt Children's Academy Charter | B5: 499 | C5: Statewide | E5: 2839171.7 | H5: 29466 | J5: 4228029.3 | P5: 226444 | T5: 5340 | U5: 37672 | W5: 58124 | Y5: 176450 | AK5: =SUM(D5:AJ5) -> 7600697 | AN5: 462000
A6: Ark Community Charter | B6: 179 | C6: Statewide | E6: 672623.37 | H6: 50000 | J6: 1223203.6 | P6: 326544 | T6: 7180 | U6: 7278 | W6: 11593 | AK6: =SUM(D6:AJ6) -> 2298422 | AO6: -66197
A7: Charter School for Applied Technologies | B7: 1402 | C7: Statewide | E7: 2697653.7 | H7: 29909 | J7: 10703605 | K7: 990404 | P7: 1734293 | U7: 154644 | W7: 386682 | AC7: 22237 | AK7: =SUM(D7:AJ7) -> 16719428
A8: Charter School for Educational Excellence | B8: 284 | C8: Statewide | E8: 1091870.5 | H8: 152247 | J8: 1563825.5 | P8: 156632 | T8: 5200 | W8: 819 | Y8: 86595 | AK8: =SUM(D8:AJ8) -> 3057189
A9: Child Development Center of the Hamptons | B9: 60 | C9: Statewide | H9: 21382 | K9: 831695 | T9: 62667 | U9: 9871 | AK9: =SUM(D9:AJ9) -> 925615
A10: Genesee Community Charter School | B10: 212 | C10: Statewide | E10: 572500.63 | J10: 1475043.4 | K10: 26756 | P10: 164547 | T10: 83500 | U10: 50479 | W10: 51505 | Y10: 50037 | AK10: =SUM(D10:AJ10) -> 2474368
A11: Global Concepts Charter School | B11: 381 | C11: Statewide | E11: 938733.73 | J11: 2695432.3 | K11: 93295 | P11: 520538 | T11: 6500 | U11: 55159 | AK11: =SUM(D11:AJ11) -> 4309658
A12: Eugenio Maria De Hostos Charter | B12: 290 | C12: Statewide | E12: 657375.75 | J12: 2069503.3 | K12: 80776 | R12: 896561 | U12: 4582 | W12: 29845 | Y12: 171176 | AK12: =SUM(D12:AJ12) -> 3909819
A13: Southside Academy Charter School | B13: 420 | C13: Statewide | D13: 13792 | E13: 815258.03 | H13: 41971 | J13: 2666287 | P13: 641876 | S13: 257097 | AK13: =SUM(D13:AJ13) -> 4436281
A14: Syracuse Academy of Science Charter | B14: 336 | C14: Statewide | E14: 694872.73 | H14: 3143 | J14: 2116764.3 | K14: 193844 | P14: 269634 | U14: 23392 | AK14: =SUM(D14:AJ14) -> 3301650
A15: True North Rochester Preparatory Charter | B15: 81 | C15: Statewide | E15: 168085.97 | J15: 574985.03 | T15: 288500 | U15: 4877 | AB15: 619158 | AK15: =SUM(D15:AJ15) -> 1655606 | AO15: 13525
A16: Niagara Charter School | B16: 245 | C16: Statewide | E16: 503021.18 | J16: 1775214.8 | K16: 144899 | T16: 947 | U16: 28005 | Z16: 23822 | AD16: 485722 | AK16: =SUM(D16:AJ16) -> 2961631
A17: Urban Choice Charter School | B17: 264 | C17: Statewide | E17: 576456.12 | J17: 1933342.9 | K17: 53436 | P17: 276513 | U17: 11665 | W17: 8873 | Y17: 119446 | AK17: =SUM(D17:AJ17) -> 2979732
A18: International Charter School of Schenectady | B18: 538 | C18: Statewide | E18: 2152750.7 | H18: 36804 | J18: 3886043.3 | K18: 175995 | P18: 295026 | U18: 301586 | AC18: 46008 | AK18: =SUM(D18:AJ18) -> 6894213
A19: Brooklyn Excelsior Charter School | B19: 653 | C19: NYC | D19: 44352 | E19: 2964341.8 | H19: 82544 | J19: 3354236.2 | P19: 617358 | S19: 809841 | AK19: =SUM(D19:AJ19) -> 7872673
A20: Brooklyn Charter School | B20: 227 | C20: NYC | E20: 1114825.5 | J20: 1261456.5 | P20: 106924 | T20: 99818 | U20: 18475 | AK20: =SUM(D20:AJ20) -> 2601499 | AN20: 397664
A21: Bronx Preparatory Charter School | B21: 525 | C21: NYC | E21: 2675399.8 | I21: 350000 | J21: 3027290.2 | T21: 1103043 | U21: 5988 | V21: 1250 | W21: 48533 | AB21: 515807 | AK21: =SUM(D21:AJ21) -> 7727311
A22: Achievement First East New York Charter School | B22: 250 | C22: NYC | E22: 1187963.2 | J22: 1344213.8 | T22: 4000 | U22: 17517 | AB22: 398113 | AK22: =SUM(D22:AJ22) -> 2951807
A23: Achievement First Crown Heights Charter | B23: 428 | C23: NYC | E23: 2013486 | J23: 2278316 | T23: 26200 | U23: 40363 | X23: 116972 | AB23: 510760 | AK23: =SUM(D23:AJ23) -> 4986097 | AN23: 70895
A24: Achievement First Endeavor Charter School | B24: 84 | C24: NYC | E24: 397359.05 | J24: 449622.95 | T24: 295000 | U24: 650 | W24: 967 | Y24: 5038 | AE24: 605579 | AK24: =SUM(D24:AJ24) -> 1754216
A25: Williamsburg Collegiate Charter | B25: 139 | C25: NYC | E25: 671624.26 | J25: 759961.74 | T25: 185000 | U25: 17253 | AB25: 482069 | AK25: =SUM(D25:AJ25) -> 2115908
A26: The Renaissance Charter School | B26: 524 | C26: NYC | E26: 2482596.4 | J26: 2809127.6 | K26: 415011 | P26: 279835 | U26: 3961 | AF26: 198575 | AG26: 9115 | AK26: =SUM(D26:AJ26) -> 6198221
A27: Ross Global Academy Charter | B27: 211 | C27: NYC | E27: 813823.65 | J27: 920864.35 | T27: 596250 | W27: 2930 | AB27: 290713 | AK27: =SUM(D27:AJ27) -> 2624581
A28: Sisulu-Walker Charter School of Harlem | B28: 245 | C28: NYC | E28: 1157784.4 | H28: 19246 | J28: 1310065.6 | K28: 60209 | P28: 389928 | T28: 34012 | U28: 4891 | W28: 9139 | Y28: 78604 | AK28: =SUM(D28:AJ28) -> 3063879
A29: South Bronx Charter Intl Cultures | B29: 206 | C29: NYC | E29: 970413.18 | H29: 211167 | J29: 1098049.8 | K29: 7908 | L29: 250000 | P29: 99273 | W29: 17574 | Y29: 106761 | AE29: 29311 | AK29: =SUM(D29:AJ29) -> 2790457 | AN29: 3570 | AO29: -135463
A30: South Bronx Classical Charter | B30: 128 | C30: NYC | E30: 613219.21 | G30: 136920 | J30: 693874.79 | O30: 195056 | Q30: 39519 | T30: 465030 | U30: 10993 | AK30: =SUM(D30:AJ30) -> 2154612 | AN30: 41683
A31: Our World Neighborhood Charter | B31: 677 | C31: NYC | E31: 3286728.8 | J31: 3719026.2 | T31: 66875 | U31: 124624 | W31: 44994 | Y31: 96854 | AB31: 487524 | AK31: =SUM(D31:AJ31) -> 7826626 | AN31: 40197
A32: Peninsula Preparatory Academy Charter | B32: 250 | C32: NYC | E32: 1194530.8 | H32: 19507 | J32: 1351645.2 | K32: 51066 | P32: 116508 | T32: 327860 | U32: 23332 | Y32: 126056 | AK32: =SUM(D32:AJ32) -> 3210505 | AN32: 45000
A33: KIPP Academy Charter School | B33: 248 | C33: NYC | E33: 1261099.9 | J33: 1426970.1 | T33: 2546857 | U33: 114929 | W33: 116224 | AB33: 202325 | AK33: =SUM(D33:AJ33) -> 5668405
A34: KIPP AMP Academy | B34: 136 | C34: NYC | E34: 691442.43 | J34: 782386.57 | T34: 221632 | U34: 38696 | W34: 7242 | AB34: 339570 | AK34: =SUM(D34:AJ34) -> 2080969
A35: KIPP Infinity Charter | B35: 154 | C35: NYC | E35: 791578.11 | J35: 895692.89 | T35: 220100 | U35: 44913 | W35: 15088 | AB35: 302450 | AK35: =SUM(D35:AJ35) -> 2269822
A36: Family Life Academy Charter | B36: 288 | C36: NYC | E36: 1482201 | H36: 267785 | J36: 1674749 | P36: 235903 | U36: 22554 | W36: 17689 | AH36: 198029 | AK36: =SUM(D36:AJ36) -> 3898910
A37: Carl C. Icahn Charter | B37: 278 | C37: NYC | E37: 1284007.4 | J37: 1452890.6 | K37: 10815 | U37: 14116 | W37: 31205 | AD37: 272913 | AK37: =SUM(D37:AJ37) -> 3065947
A38: Community Partnership Charter | B38: 288 | C38: NYC | E38: 1378210.3 | J38: 1559483.7 | T38: 181687 | U38: 3792 | W38: 68381 | AB38: 215179 | AK38: =SUM(D38:AJ38) -> 3406733
A39: Community Roots Charter School | B39: 100 | C39: NYC | E39: 478915.57 | F39: 139412 | J39: 541906.43 | M39: 47115 | P39: 217414 | T39: 417809 | W39: 9728 | AK39: =SUM(D39:AJ39) -> 1852300
A40: Bronx Charter School for Better Learning | B40: 229 | C40: NYC | E40: 1089674.1 | J40: 1232996.9 | T40: 120265 | U40: 125619 | AB40: 162446 | AK40: =SUM(D40:AJ40) -> 2731001
A41: The Bronx Charter School for Children | B41: 262 | C41: NYC | E41: 1248230.8 | J41: 1412408.2 | K41: 172546 | T41: 304015 | U41: 5905 | W41: 23743 | AB41: 300740 | AK41: =SUM(D41:AJ41) -> 3467588 | AN41: 64984
A42: Bronx Charter School for Excellence | B42: 185 | C42: NYC | E42: 899975.45 | J42: 1018347.5 | T42: 334435 | U42: 4280 | W42: 2617 | AB42: 68362 | AK42: =SUM(D42:AJ42) -> 2328017
A43: Bronx Charter School for the Arts | B43: 284 | C43: NYC | E43: 1547481.8 | J43: 1751019.2 | P43: 187682 | T43: 422776 | U43: 26493 | W43: 22097 | Y43: 87823 | AI43: 214076 | AK43: =SUM(D43:AJ43) -> 4259448 | AO43: -106991
A44: Bronx Lighthouse Charter School | B44: 169 | C44: NYC | E44: 1308925.7 | J44: 1481086.3 | P44: 240744 | U44: 11806 | W44: 24338 | AH44: 166815 | AK44: =SUM(D44:AJ44) -> 3233715
A45: John V Lindsay Wildcat Charter | B45: 426 | C45: NYC | E45: 2032954.6 | J45: 2300345.4 | K45: 859660 | P45: 380274 | T45: 87748 | U45: 7099 | W45: 101475 | AK45: =SUM(D45:AJ45) -> 5769556 | AN45: 15186 | AO45: -62791
A46: Beginning With Children Charter School | B46: 443 | C46: NYC | E46: 2196900.3 | J46: 2489476.7 | T46: 113676 | W46: 57698 | AB46: 282453 | AK46: =SUM(D46:AJ46) -> 5140204
A47: Achievement First Bushwick Charter | B47: 163 | C47: NYC | E47: 794909.05 | J47: 899461.95 | T47: 255000 | W47: 3372 | Y47: 11995 | AB47: 440884 | AK47: =SUM(D47:AJ47) -> 2405622 | AN47: 606605
A48: Future Leaders Institute Charter | B48: 294 | C48: NYC | E48: 1538943.8 | J48: 1741358.2 | T48: 530107 | U48: 18558 | AI48: 321822 | AK48: =SUM(D48:AJ48) -> 4150789
A49: Explore Charter School and Affiliate | B49: 382 | C49: NYC | E49: 1803267.3 | J49: 2040447.7 | P49: 332895 | T49: 198875 | U49: 7210 | W49: 31946 | AA49: 68739 | AK49: =SUM(D49:AJ49) -> 4483380
A50: Opportunity Charter School | B50: 218 | C50: NYC | E50: 1792019 | J50: 2027720 | T50: 702032 | U50: 56957 | AB50: 390745 | AK50: =SUM(D50:AJ50) -> 4969473
A51: Girls Preparatory Charter School | B51: 136 | C51: NYC | E51: 654206.71 | J51: 740253.29 | P51: 164594 | T51: 200140 | U51: 46019 | W51: 10813 | AF51: (212) 388-0241 | AI51: 39838 | AK51: =SUM(D51:AJ51) -> 1855864 | AN51: 77407
A52: Grand Concourse Academy | B52: 283 | C52: NYC | E52: 1343658.6 | J52: 1520387.4 | U52: 11025 | W52: 11263 | Y52: 118434 | AB52: 374621 | AK52: =SUM(D52:AJ52) -> 3379389 | AO52: -9016
A53: Democracy Preparatory Charter School | B53: 131 | C53: NYC | E53: 692850.81 | J53: 783980.19 | P53: 228010 | T53: 413946 | W53: 12581 | AF53: (212) 281-1248 | AI53: 404079 | AK53: =SUM(D53:AJ53) -> 2535447 | AO53: -122043
A54: East NY Preparatory Charter School | B54: 108 | C54: NYC | E54: 497223.09 | J54: 562621.91 | T54: 290500 | U54: 22196 | AB54: 363937 | AK54: =SUM(D54:AJ54) -> 1736478
A55: Excellence Charter School of Bedford Stuyvesant | B55: 173 | C55: NYC | E55: 810528.36 | F55: 14076 | J55: 917135.64 | M55: 200000 | P55: 137404 | T55: 989184 | U55: 5847 | AK55: =SUM(D55:AJ55) -> 3074175
A56: New Heights Academy Charter | B56: 192 | C56: NYC | E56: 1016467.9 | J56: 1150162.1 | P56: 258026 | T56: 77275 | W56: 10066 | AI56: 531238 | AK56: =SUM(D56:AJ56) -> 3043235
A57: New York Center for Autism Charter School | B57: 16 | C57: NYC | E57: 504201.65 | J57: 570518.35 | T57: 120910 | U57: 9311 | AI57: 281567 | AK57: =SUM(D57:AJ57) -> 1486508
A58: The UFT Charter School | B58: 355 | C58: NYC | E58: 1709551.9 | J58: 1927860.1 | T58: 473089 | U58: 20128 | V58: 31000 | W58: 20127 | AB58: 536212 | AK58: =SUM(D58:AJ58) -> 4717968 | AN58: 106934
A59: The Williamsburg Charter High School | B59: 465 | C59: NYC | E59: 2234761.5 | J59: 2528695.5 | T59: 233643 | U59: 19055 | V59: 7075 | AB59: 281579 | AK59: =SUM(D59:AJ59) -> 5304809
A60: Hellenic Classical Charter School | B60: 182 | C60: NYC | E60: 859294.31 | J60: 972315.69 | U60: 17823 | AI60: 9688 | AK60: =SUM(D60:AJ60) -> 1859121
A61: Hyde Leadership Charter School | B61: 192 | C61: NYC | E61: 942625.61 | J61: 1066607.4 | T61: 294174 | U61: 29488 | AB61: 373297 | AK61: =SUM(D61:AJ61) -> 2706192
A62: International Leadership Charter School | B62: 84 | C62: NYC | E62: 439226.67 | J62: 496997.33 | T62: 253525 | U62: 167 | AB62: 372044 | AK62: =SUM(D62:AJ62) -> 1561960
A63: Harlem Children's Zone Promise Academy II | B63: 133 | C63: NYC | E63: 677653.73 | J63: 766784.27 | AJ63: 162644 | AK63: =SUM(D63:AJ63) -> 1607082
A64: Harlem Day Charter School | B64: 264 | C64: NYC | E64: 1175167.2 | J64: 1329734.8 | T64: 1423179 | U64: 91954 | AB64: 368279 | AK64: =SUM(D64:AJ64) -> 4388314
A65: Harlem Link Charter School | B65: 162 | C65: NYC | E65: 783013.83 | H65: 152922 | J65: 886002.17 | K65: 61288 | P65: 332698 | T65: 142526 | AK65: =SUM(D65:AJ65) -> 2358450
A66: Harlem Success Academy Charter | B66: 156 | C66: NYC | E66: 719177.93 | J66: 813770.07 | P66: 235602 | T66: 1319156 | W66: 653 | AI66: 173863 | AK66: =SUM(D66:AJ66) -> 3262222 | AN66: 25000
A67: Harlem Village Academy | B67: 200 | C67: NYC | E67: 981709.3 | J67: 1110831.7 | P67: 106306 | W67: 2201 | AI67: 23032 | AK67: =SUM(D67:AJ67) -> 2224080
A68: Amber Charter School | B68: 360 | C68: NYC | E68: 1657743.1 | J68: 1875782.9 | T68: 206013 | U68: 86734 | W68: 314 | AB68: 506798 | AK68: =SUM(D68:AJ68) -> 4333385
A69: KIPP Star College Prep Charter | B69: 313 | C69: NYC | E69: 1594070.4 | J69: 1803735.6 | T69: 268959 | U69: 17692 | W69: 116479 | AB69: 149435 | AK69: =SUM(D69:AJ69) -> 3950371
A70: Leadership Preparatory Charter School | B70: 116 | C70: NYC | E70: 554876.56 | J70: 627858.44 | T70: 560075 | U70: 13098 | AB70: 472382 | AK70: =SUM(D70:AJ70) -> 2228290
A71: Leadership Village Academy Charter | B71: 116 | C71: NYC | E71: 538842.99 | J71: 609716.01 | P71: 53552 | W71: 2352 | AI71: 59595 | AK71: =SUM(D71:AJ71) -> 1264058
A72: Manhattan Charter School | B72: 118 | C72: NYC | E72: 560166.66 | H72: 125406 | J72: 633844.34 | P72: 131725 | T72: 2440 | U72: 15805 | AK72: =SUM(D72:AJ72) -> 1469387
A73: Merrick Academy-Queens Public Charter | B73: 496 | C73: NYC | E73: 2324256.6 | H73: 39110 | J73: 2636811.4 | K73: 52064 | P73: 245300 | W73: 24316 | Y73: 165314 | AB73: 2500 | AK73: =SUM(D73:AJ73) -> 5489672
A74: The Harbor Science and Arts Charter School | B74: 213 | C74: NYC | E74: 1009454.7 | I74: 227200 | J74: 1142226.3 | T74: 32348 | AK74: =SUM(D74:AJ74) -> 2411229 | AO74: -208069
A75: Harlem Children's Zone Promise Academy | B75: 511 | C75: NYC | E75: 2550603.9 | J75: 2886080.1 | T75: 15010 | U75: 4110 | Y75: 194345 | AJ75: 212965 | AK75: =SUM(D75:AJ75) -> 5863114 | AN75: 534000
A76: Harriet Tubman Charter School | B76: 404 | C76: NYC | E76: 1984154.9 | J76: 2245127.1 | T76: 4773 | U76: 14847 | AB76: 239950 | AK76: =SUM(D76:AJ76) -> 4488852 | AN76: 41261
A77: KIPP Sankofa Charter School | B77: 248 | C77: Buffalo | E77: 372538.11 | J77: 1808927.9 | K77: 105425 | T77: 5200 | U77: 13758 | W77: 68 | AC77: 174162 | AK77: =SUM(D77:AJ77) -> 2480079
A78: Buffalo Academy of Science Charter School | B78: 339 | C78: Buffalo | E78: 546361.16 | J78: 2739532.8 | AD78: 310958 | AK78: =SUM(D78:AJ78) -> 3596852 | AN78: 100000 | AO78: -57032
A79: Buffalo United Charter School | B79: 479 | C79: Buffalo | D79: 19292 | E79: 779070.29 | H79: 166471 | J79: 3666531.7 | P79: 620478 | AK79: =SUM(D79:AJ79) -> 5251843 | AN79: 852463
A80: Westminster Community Charter School | B80: 518 | C80: Buffalo | E80: 784501.25 | H80: 618210 | J80: 4053009.7 | K80: 34996 | P80: 405429 | S80: 504815 | T80: 2133 | U80: 135661 | AK80: =SUM(D80:AJ80) -> 6538755
A81: Western New York Maritime Charter | B81: 317 | C81: Buffalo | E81: 482017.54 | J81: 2311494.5 | K81: 450108 | T81: 67084 | U81: 7572 | AC81: 273172 | AK81: =SUM(D81:AJ81) -> 3591448
A82: South Buffalo Charter | B82: 640 | C82: Buffalo | E82: 1056656.5 | H82: 350000 | J82: 4907937.5 | K82: 316280 | P82: 728747 | U82: 36357 | W82: 90737 | AK82: =SUM(D82:AJ82) -> 7486715 | AN82: 17500
A83: Pinnacle Charter School | B83: 405 | C83: Buffalo | E83: 726012.01 | J83: 3133540 | K83: 497134 | P83: 247174 | U83: 9750 | Y83: 131124 | AC83: 6658 | AK83: =SUM(D83:AJ83) -> 4751392
A84: King Center Charter School | B84: 104 | C84: Buffalo | E84: 159817.5 | J84: 825673.5 | K84: 48646 | T84: 1346 | U84: 2142 | W84: 7402 | AC84: 334151 | AK84: =SUM(D84:AJ84) -> 1379178 | AN84: 10596
A85: Community Charter School | B85: 292 | C85: Buffalo | E85: 440496.14 | J85: 2170211.9 | K85: 141520 | P85: 179143 | U85: 46040 | AK85: =SUM(D85:AJ85) -> 2977411
A86: Elmwood Village Charter School | B86: 102 | C86: Buffalo | E86: 171557.02 | H86: 200000 | J86: 886323.98 | K86: 25556 | P86: 209877 | T86: 1300 | U86: 4002 | AK86: =SUM(D86:AJ86) -> 1498616
A87: Enterprise Charter School | B87: 553 | C87: Buffalo | E87: 893077.04 | J87: 4314498 | K87: 374688 | T87: 350 | U87: 49325 | Z87: 111420 | AD87: 1173001 | AK87: =SUM(D87:AJ87) -> 6916359 | AN87: 40389
A88: Oracle Charter School | B88: 244 | C88: Buffalo | E88: 382995.57 | H88: 309379 | J88: 1917328.4 | K88: 200105 | P88: 98329 | T88: 200 | W88: 51738 | AK88: =SUM(D88:AJ88) -> 2960075
A89: Tapestry Charter School | B89: 269 | C89: Buffalo | E89: 436749.78 | J89: 2106083.2 | K89: 194904 | T89: 38679 | U89: 44171 | W89: 2230 | Y89: 75926 | AD89: 201717 | AK89: =SUM(D89:AJ89) -> 3100460
A90: Achievement Academy | B90: 146 | C90: Albany | E90: 763500.38 | H90: 1985 | J90: 555024.62 | K90: 131675 | P90: 169152 | U90: 40088 | AC90: 157841 | AD90: 87500 | AK90: =SUM(D90:AJ90) -> 1906766
A91: New Covenant Charter School | B91: 692 | C91: Albany | E91: 3448538.5 | H91: 27283 | J91: 3048329.5 | K91: 18394 | P91: 894921 | U91: 236577 | AC91: 57233 | AK91: =SUM(D91:AJ91) -> 7731276
A92: Brighter Choice Charter School Boys | B92: 141 | C92: Albany | E92: 811855.11 | H92: 5244 | J92: 603257.89 | P92: 222542 | T92: 176387 | U92: 90307 | W92: 21946 | AK92: =SUM(D92:AJ92) -> 1931539
A93: Brighter Choice Charter School Girls | B93: 144 | C93: Albany | E93: 874622.41 | H93: 12000 | J93: 639834.59 | P93: 1245837 | T93: 174387 | U93: 93618 | W93: 24128 | AK93: =SUM(D93:AJ93) -> 3064427
A94: Albany Community Charter School | B94: 103 | C94: Albany | E94: 609081.54 | H94: 77640 | J94: 469845.46 | K94: 26216 | P94: 409080 | U94: 186700 | AK94: =SUM(D94:AJ94) -> 1778563
A95: Albany Preparatory Charter School | B95: 113 | C95: Albany | E95: 613841.16 | H95: 108883 | J95: 459513.84 | K95: 74619 | P95: 31334 | U95: 38796 | W95: 3032 | AK95: =SUM(D95:AJ95) -> 1330019 | AN95: 2735094
A96: KIPP Tech Valley Charter School | B96: 166 | C96: Albany | E96: 895694.65 | H96: 3773 | J96: 687421.35 | K96: 51703 | P96: 59939 | U96: 63296 | AC96: 454667 | AK96: =SUM(D96:AJ96) -> 2216494
A97: Statewide totals | B97: =SUM(B4:B96) -> 26485 | E97: =SUM(E4:E96) -> 1.0575797e+08 | G97: =SUM(D4:G96) -> 1.0612582e+08 | K97: =SUM(J4:K96) -> 1.7055021e+08 | O97: =SUM(H4:O96) -> 1.7498306e+08 | R97: =SUM(P4:R96) -> 16168064 | Y97: =SUM(S4:Y96) -> 26239303 | AJ97: =SUM(Z4:AJ96) -> 18364731 | AK97: =SUM(AK4:AK96) -> 341880976
G98: =G97/B97 -> 4007.016 | O98: =O97/B97 -> 6606.8741 | R98: =R97/B97 -> 610.46117 | Y98: =Y97/B97 -> 990.72316 | AJ98: =AJ97/B97 -> 693.40121 | AK98: =SUM(G98:AJ98) -> 12908.476
G99: =G97/AK97 -> 0.31041744 | O99: =O97/AK97 -> 0.5118245 | R99: =R97/AK97 -> 0.047291499 | Y99: =Y97/AK97 -> 0.076749819 | AJ99: =AJ97/AK97 -> 0.053716739
A104: New York City Charters
...

Sheet Sending District
A1: Table 6
A2: Formula for Distribution of FY07 Charter Sending District Revenue by Local and State Funds
B3: Sending District | C3: District BEDS | D3: # Pupils | E3: Sending District Funding Formula | F3: Total Sending District Local & State Revenue | G3: % State Revenue | H3: State Revenue | I3: % Local Revenue | J3: Local Revenue | K3: Sending District Total State & Local | L3: State % Total State & Local | M3: Local % Total State & Local | N3: % of pupils | O3: Charter Self Reported Basic Operating Revenues | P3: Local Portion Basic Operating Revenues | Q3: State Portion Basic Operating Revenues
A4: Achievement Academy
B5: Albany | C5: 010100 | D5: 146 | E5: 10176 | F5: 172866321 | G5: =H5/F5 -> 0.42094357 | H5: =F5-J5 -> 72766966 | I5: =J5/F5 -> 0.57905643 | J5: 100099355 | K5: =SUM(H5+J5) -> 172866321 | L5: =H5/K5 -> 0.42094357 | M5: =J5/K5 -> 0.57905643 | N5: =D5/$D$6 -> 1 | O5: 1318525 | P5: =O5*N5*M5 -> 763500.38 | Q5: =O5*N5*L5 -> 555024.62
A6: Total Achievement Academy | D6: =SUM(D5) -> 146 | P6: =SUM(P5) -> 763500.38 | Q6: =SUM(Q5) -> 555024.62
A7: Albany Community
B8: Albany | C8: 010100 | D8: 95 | E8: 10176 | F8: 172866321 | G8: =H8/F8 -> 0.42094357 | H8: =F8-J8 -> 72766966 | I8: =J8/F8 -> 0.57905643 | J8: 100099355 | K8: =SUM(H8+J8) -> 172866321 | L8: =H8/K8 -> 0.42094357 | M8: =J8/K8 -> 0.57905643 | N8: =D8/$D$14 -> 0.9223301 | O8: 1078927 | P8: =O8*N8*M8 -> 576234.6 | Q8: =O8*N8*L8 -> 418892.24
B9: Ravena-Coeymans-Selkirk | C9: 010402 | D9: 1 | E9: 10973 | F9: 39310578 | G9: =H9/F9 -> 0.47995763 | H9: =F9-J9 -> 18867412 | I9: =J9/F9 -> 0.52004237 | J9: 20443166 | K9: =SUM(H9+J9) -> 39310578 | L9: =H9/K9 -> 0.47995763 | M9: =J9/K9 -> 0.52004237 | N9: =D9/$D$14 -> 0.0097087379 | O9: 1078927 | P9: =O9*N9*M9 -> 5447.4539 | Q9: =O9*N9*L9 -> 5027.5655
B10: Watervliet | C10: 011200 | D10: 1 | E10: 8036 | F10: 18681136 | G10: =H10/F10 -> 0.69404532 | H10: =F10-J10 -> 12965555 | I10: =J10/F10 -> 0.30595468 | J10: 5715581 | K10: =SUM(H10+J10) -> 18681136 | L10: =H10/K10 -> 0.69404532 | M10: =J10/K10 -> 0.30595468 | N10: =D10/$D$14 -> 0.0097087379 | O10: 1078927 | P10: =O10*N10*M10 -> 3204.8812 | Q10: =O10*N10*L10 -> 7270.1382
B11: East Greenbush | C11: 490301 | D11: 1 | E11: 10374 | F11: 75113751 | G11: =H11/F11 -> 0.45169729 | H11: =F11-J11 -> 33928678 | I11: =J11/F11 -> 0.54830271 | J11: 41185073 | K11: =SUM(H11+J11) -> 75113751 | L11: =H11/K11 -> 0.45169729 | M11: =J11/K11 -> 0.54830271 | N11: =D11/$D$14 -> 0.0097087379 | O11: 1078927 | P11: =O11*N11*M11 -> 5743.4815 | Q11: =O11*N11*L11 -> 4731.5379
B12: Lansingburgh | C12: 490601 | D12: 1 | E12: 8243 | F12: 31403986 | G12: =H12/F12 -> 0.66721619 | H12: =F12-J12 -> 20953248 | I12: =J12/F12 -> 0.33278381 | J12: 10450738 | K12: =SUM(H12+J12) -> 31403986 | L12: =H12/K12 -> 0.66721619 | M12: =J12/K12 -> 0.33278381 | N12: =D12/$D$14 -> 0.0097087379 | O12: 1078927 | P12: =O12*N12*M12 -> 3485.9168 | Q12: =O12*N12*L12 -> 6989.1026
B13: Troy | C13: 491700 | D13: 4 | E13: 10954 | F13: 81553767 | G13: =H13/F13 -> 0.64283589 | H13: =F13-J13 -> 52425688 | I13: =J13/F13 -> 0.35716411 | J13: 29128079 | K13: =SUM(H13+J13) -> 81553767 | L13: =H13/K13 -> 0.64283589 | M13: =J13/K13 -> 0.35716411 | N13: =D13/$D$14 -> 0.038834951 | O13: 1078927 | P13: =O13*N13*M13 -> 14965.204 | Q13: =O13*N13*L13 -> 26934.874
A14: Total Albany Community | D14: =SUM(D8:D13) -> 103 | P14: =SUM(P8:P13) -> 609081.54 | Q14: =SUM(Q8:Q13) -> 469845.46
A15: Albany Prep
B16: Albany | C16: 010100 | D16: 109 | E16: 10176 | F16: 172866321 | G16: =H16/F16 -> 0.42094357 | H16: =F16-J16 -> 72766966 | I16: =J16/F16 -> 0.57905643 | J16: 100099355 | K16: =SUM(H16+J16) -> 172866321 | L16: =H16/K16 -> 0.42094357 | M16: =J16/K16 -> 0.57905643 | N16: =D16/$D$20 -> 0.96460177 | O16: 1073355 | P16: =O16*N16*M16 -> 599531.94 | Q16: =O16*N16*L16 -> 435828.19
B17: Watervliet | C17: 011200 | D17: 1 | E17: 8036 | F17: 18681136 | G17: =H17/F17 -> 0.69404532 | H17: =F17-J17 -> 12965555 | I17: =J17/F17 -> 0.30595468 | J17: 5715581 | K17: =SUM(H17+J17) -> 18681136 | L17: =H17/K17 -> 0.69404532 | M17: =J17/K17 -> 0.30595468 | N17: =D17/$D$20 -> 0.0088495575 | O17: 1073355 | P17: =O17*N17*M17 -> 2906.1769 | Q17: =O17*N17*L17 -> 6592.5399
B18: Troy | C18: 491700 | D18: 2 | E18: 10954 | F18: 81553767 | G18: =H18/F18 -> 0.64283589 | H18: =F18-J18 -> 52425688 | I18: =J18/F18 -> 0.35716411 | J18: 29128079 | K18: =SUM(H18+J18) -> 81553767 | L18: =H18/K18 -> 0.64283589 | M18: =J18/K18 -> 0.35716411 | N18: =D18/$D$20 -> 0.017699115 | O18: 1073355 | P18: =O18*N18*M18 -> 6785.2016 | Q18: =O18*N18*L18 -> 12212.232
B19: Scotia-Glenville | C19: 530202 | D19: 1 | E19: 9361 | F19: 41910477 | G19: =H19/F19 -> 0.51384605 | H19: =F19-J19 -> 21535533 | I19: =J19/F19 -> 0.48615395 | J19: 20374944 | K19: =SUM(H19+J19) -> 41910477 | L19: =H19/K19 -> 0.51384605 | M19: =J19/K19 -> 0.48615395 | N19: =D19/$D$20 -> 0.0088495575 | O19: 1073355 | P19: =O19*N19*M19 -> 4617.8387 | Q19: =O19*N19*L19 -> 4880.8781
A20: Total Albany Prep | D20: =SUM(D16:D19) -> 113 | P20: =SUM(P16:P19) -> 613841.16 | Q20: =SUM(Q16:Q19) -> 459513.84
A21: Brighter Choice Boys
B22: Albany | C22: 010100 | D22: 137 | E22: 10176 | F22: 172866321 | G22: =H22/F22 -> 0.42094357 | H22: =F22-J22 -> 72766966 | I22: =J22/F22 -> 0.57905643 | J22: 100099355 | K22: =SUM(H22+J22) -> 172866321 | L22: =H22/K22 -> 0.42094357 | M22: =J22/K22 -> 0.57905643 | N22: =D22/$D$27 -> 0.97163121 | O22: 1415113 | P22: =O22*N22*M22 -> 796184.04 | Q22: =O22*N22*L22 -> 578783.92
B23: Ravena-Coeymans-Selkirk | C23: 010402 | D23: 1 | E23: 10973 | F23: 39310578 | G23: =H23/F23 -> 0.47995763 | H23: =F23-J23 -> 18867412 | I23: =J23/F23 -> 0.52004237 | J23: 20443166 | K23: =SUM(H23+J23) -> 39310578 | L23: =H23/K23 -> 0.47995763 | M23: =J23/K23 -> 0.52004237 | N23: =D23/$D$27 -> 0.0070921986 | O23: 1415113 | P23: =O23*N23*M23 -> 5219.2817 | Q23: =O23*N23*L23 -> 4816.9808
B24: Lansingburgh | C24: 490601 | D24: 1 | E24: 8243 | F24: 31403986 | G24: =H24/F24 -> 0.66721619 | H24: =F24-J24 -> 20953248 | I24: =J24/F24 -> 0.33278381 | J24: 10450738 | K24: =SUM(H24+J24) -> 31403986 | L24: =H24/K24 -> 0.66721619 | M24: =J24/K24 -> 0.33278381 | N24: =D24/$D$27 -> 0.0070921986 | O24: 1415113 | P24: =O24*N24*M24 -> 3339.9056 | Q24: =O24*N24*L24 -> 6696.3568
B25: Troy | C25: 491700 | D25: 1 | E25: 10954 | F25: 81553767 | G25: =H25/F25 -> 0.64283589 | H25: =F25-J25 -> 52425688 | I25: =J25/F25 -> 0.35716411 | J25: 29128079 | K25: =SUM(H25+J25) -> 81553767 | L25: =H25/K25 -> 0.64283589 | M25: =J25/K25 -> 0.35716411 | N25: =D25/$D$27 -> 0.0070921986 | O25: 1415113 | P25: =O25*N25*M25 -> 3584.5928 | Q25: =O25*N25*L25 -> 6451.6696
B26: Schenectady | C26: 530600 | D26: 1 | E26: 9112 | F26: 129603734 | G26: =H26/F26 -> 0.64854502 | H26: =F26-J26 -> 84053856 | I26: =J26/F26 -> 0.35145498 | J26: 45549878 | K26: =SUM(H26+J26) -> 129603734 | L26: =H26/K26 -> 0.64854502 | M26: =J26/K26 -> 0.35145498 | N26: =D26/$D$27 -> 0.0070921986 | O26: 1415113 | P26: =O26*N26*M26 -> 3527.2944 | Q26: =O26*N26*L26 -> 6508.968
A27: Total Brighter Choice Boys | D27: =SUM(D22:D26) -> 141 | P27: =SUM(P22:P26) -> 811855.11 | Q27: =SUM(Q22:Q26) -> 603257.89
A28: Brighter Choice Girls
B29: Albany | C29: 010100 | D29: 143 | E29: 10176 | F29: 172866321 | G29: =H29/F29 -> 0.42094357 | H29: =F29-J29 -> 72766966 | I29: =J29/F29 -> 0.57905643 | J29: 100099355 | K29: =SUM(H29+J29) -> 172866321 | L29: =H29/K29 -> 0.42094357 | M29: =J29/K29 -> 0.57905643 | N29: =D29/$D$31 -> 0.99305556 | O29: 1514457 | P29: =O29*N29*M29 -> 870866.09 | Q29: =O29*N29*L29 -> 633073.84
B30: Troy | C30: 491700 | D30: 1 | E30: 10954 | F30: 81553767 | G30: =H30/F30 -> 0.64283589 | H30: =F30-J30 -> 52425688 | I30: =J30/F30 -> 0.35716411 | J30: 29128079 | K30: =SUM(H30+J30) -> 81553767 | L30: =H30/K30 -> 0.64283589 | M30: =J30/K30 -> 0.35716411 | N30: =D30/$D$31 -> 0.0069444444 | O30: 1514457 | P30: =O30*N30*M30 -> 3756.3173 | Q30: =O30*N30*L30 -> 6760.7452
A31: Total Brighter Choice Girls | D31: =SUM(D29:D30) -> 144 | P31: =SUM(P29:P30) -> 874622.41 | Q31: =SUM(Q29:Q30) -> 639834.59
A32: KIPP Tech Valley
B33: Albany | C33: 010100 | D33: 153 | E33: 10176 | F33: 172866321 | G33: =H33/F33 -> 0.42094357 | H33: =F33-J33 -> 72766966 | I33: =J33/F33 -> 0.57905643 | J33: 100099355 | K33: =SUM(H33+J33) -> 172866321 | L33: =H33/K33 -> 0.42094357 | M33: =J33/K33 -> 0.57905643 | N33: =D33/$D$41 -> 0.92168675 | O33: 1583116 | P33: =O33*N33*M33 -> 844922.69 | Q33: =O33*N33*L33 -> 614214.35
B34: Berne-Knox Westerlo | C34: 010201 | D34: 1 | E34: 10026 | F34: 18737733 | G34: =H34/F34 -> 0.53705056 | H34: =F34-J34 -> 10063110 | I34: =J34/F34 -> 0.46294944 | J34: 8674623 | K34: =SUM(H34+J34) -> 18737733 | L34: =H34/K34 -> 0.53705056 | M34: =J34/K34 -> 0.46294944 | N34: =D34/$D$41 -> 0.0060240964 | O34: 1583116 | P34: =O34*N34*M34 -> 4415.0763 | Q34: =O34*N34*L34 -> 5121.7671
B35: Menands | C35: 010615 | D35: 1 | E35: 15215 | F35: 6663188 | G35: =H35/F35 -> 0.12586408 | H35: =F35-J35 -> 838656 | I35: =J35/F35 -> 0.87413592 | J35: 5824532 | K35: =SUM(H35+J35) -> 6663188 | L35: =H35/K35 -> 0.12586408 | M35: =J35/K35 -> 0.87413592 | N35: =D35/$D$41 -> 0.0060240964 | O35: 1583116 | P35: =O35*N35*M35 -> 8336.4974 | Q35: =O35*N35*L35 -> 1200.346
B36: Watervliet | C36: 011200 | D36: 1 | E36: 8036 | F36: 18681136 | G36: =H36/F36 -> 0.69404532 | H36: =F36-J36 -> 12965555 | I36: =J36/F36 -> 0.30595468 | J36: 5715581 | K36: =SUM(H36+J36) -> 18681136 | L36: =H36/K36 -> 0.69404532 | M36: =J36/K36 -> 0.30595468 | N36: =D36/$D$41 -> 0.0060240964 | O36: 1583116 | P36: =O36*N36*M36 -> 2917.8419 | Q36: =O36*N36*L36 -> 6619.0015
B37: Rensselaer | C37: 491200 | D37: 1 | E37: 10992 | F37: 15992771 | G37: =H37/F37 -> 0.58393014 | H37: =F37-J37 -> 9338661 | I37: =J37/F37 -> 0.41606986 | J37: 6654110 | K37: =SUM(H37+J37) -> 15992771 | L37: =H37/K37 -> 0.58393014 | M37: =J37/K37 -> 0.41606986 | N37: =D37/$D$41 -> 0.0060240964 | O37: 1583116 | P37: =O37*N37*M37 -> 3967.9931 | Q37: =O37*N37*L37 -> 5568.8503
B38: Troy | C38: 491700 | D38: 6 | E38: 10954 | F38: 81553767 | G38: =H38/F38 -> 0.64283589 | H38: =F38-J38 -> 52425688 | I38: =J38/F38 -> 0.35716411 | J38: 29128079 | K38: =SUM(H38+J38) -> 81553767 | L38: =H38/K38 -> 0.64283589 | M38: =J38/K38 -> 0.35716411 | N38: =D38/$D$41 -> 0.036144578 | O38: 1583116 | P38: =O38*N38*M38 -> 20437.309 | Q38: =O38*N38*L38 -> 36783.751
B39: Rotterdam-Mohonasen | C39: 530515 | D39: 1 | E39: 7073 | F39: 39235095 | G39: =H39/F39 -> 0.58123445 | H39: =F39-J39 -> 22804789 | I39: =J39/F39 -> 0.41876555 | J39: 16430306 | K39: =SUM(H39+J39) -> 39235095 | L39: =H39/K39 -> 0.58123445 | M39: =J39/K39 -> 0.41876555 | N39: =D39/$D$41 -> 0.0060240964 | O39: 1583116 | P39: =O39*N39*M39 -> 3993.7014 | Q39: =O39*N39*L39 -> 5543.1419
B40: Schenectady | C40: 530600 | D40: 2 | E40: 9112 | F40: 129603734 | G40: =H40/F40 -> 0.64854502 | H40: =F40-J40 -> 84053856 | I40: =J40/F40 -> 0.35145498 | J40: 45549878 | K40: =SUM(H40+J40) -> 129603734 | L40: =H40/K40 -> 0.64854502 | M40: =J40/K40 -> 0.35145498 | N40: =D40/$D$41 -> 0.012048193 | O40: 1583116 | P40: =O40*N40*M40 -> 6703.5422 | Q40: =O40*N40*L40 -> 12370.145
A41: Total Kipp Tech Valley | D41: =SUM(D33:D40) -> 166 | P41: =SUM(P33:P40) -> 895694.65 | Q41: =SUM(Q33:Q40) -> 687421.35
A42: New Covenant Charter School
B43: Albany | C43: 010100 | D43: 529 | E43: 10176 | F43: 172866321 | G43: =H43/F43 -> 0.42094357 | H43: =F43-J43 -> 72766966 | I43: =J43/F43 -> 0.57905643 | J43: 100099355 | K43: =SUM(H43+J43) -> 172866321 | L43: =H43/K43 -> 0.42094357 | M43: =J43/K43 -> 0.57905643 | N43: =D43/$D$53 -> 0.76666667 | O43: 6496868 | P43: =O43*N43*M43 -> 2884240.8 | Q43: =O43*N43*L43 -> 2096691.3
B44: Ravena-Coeymans-Selkirk | C44: 010402 | D44: 1 | E44: 10973 | F44: 39310578 | G44: =H44/F44 -> 0.47995763 | H44: =F44-J44 -> 18867412 | I44: =J44/F44 -> 0.52004237 | J44: 20443166 | K44: =SUM(H44+J44) -> 39310578 | L44: =H44/K44 -> 0.47995763 | M44: =J44/K44 -> 0.52004237 | N44: =D44/$D$53 -> 0.0014492754 | O44: 6496868 | P44: =O44*N44*M44 -> 4896.5893 | Q44: =O44*N44*L44 -> 4519.1614
B45: Cohoes | C45: 010500 | D45: 7 | E45: 9784 | F45: 30197272 | G45: =H45/F45 -> 0.62025894 | H45: =F45-J45 -> 18730128 | I45: =J45/F45 -> 0.37974106 | J45: 11467144 | K45: =SUM(H45+J45) -> 30197272 | L45: =H45/K45 -> 0.62025894 | M45: =J45/K45 -> 0.37974106 | N45: =D45/$D$53 -> 0.010144928 | O45: 6496868 | P45: =O45*N45*M45 -> 25028.83 | Q45: =O45*N45*L45 -> 40881.425
B46: Menands | C46: 010615 | D46: 4 | E46: 15215 | F46: 6663188 | G46: =H46/F46 -> 0.12586408 | H46: =F46-J46 -> 838656 | I46: =J46/F46 -> 0.87413592 | J46: 5824532 | K46: =SUM(H46+J46) -> 6663188 | L46: =H46/K46 -> 0.12586408 | M46: =J46/K46 -> 0.87413592 | N46: =D46/$D$53 -> 0.0057971014 | O46: 6496868 | P46: =O46*N46*M46 -> 32922.584 | Q46: =O46*N46*L46 -> 4740.4191
B47: Guilderland | C47: 010802 | D47: 1 | E47: 9675 | F47: 80598147 | G47: =H47/F47 -> 0.36768657 | H47: =F47-J47 -> 29634856 | I47: =J47/F47 -> 0.63231343 | J47: 50963291 | K47: =SUM(H47+J47) -> 80598147 | L47: =H47/K47 -> 0.36768657 | M47: =J47/K47 -> 0.63231343 | N47: =D47/$D$53 -> 0.0014492754 | O47: 6496868 | P47: =O47*N47*M47 -> 5953.7057 | Q47: =O47*N47*L47 -> 3462.0451
B48: Watervliet | C48: 010615 | D48: 6 | E48: 8036 | F48: 18681136 | G48: =H48/F48 -> 0.69404532 | H48: =F48-J48 -> 12965555 | I48: =J48/F48 -> 0.30595468 | J48: 5715581 | K48: =SUM(H48+J48) -> 18681136 | L48: =H48/K48 -> 0.69404532 | M48: =J48/K48 -> 0.30595468 | N48: =D48/$D$53 -> 0.0086956522 | O48: 6496868 | P48: =O48*N48*M48 -> 17284.758 | Q48: =O48*N48*L48 -> 39209.746
B49: Lansingburg | C49: 011200 | D49: 3 | E49: 8243 | F49: 31403986 | G49: =H49/F49 -> 0.66721619 | H49: =F49-J49 -> 20953248 | I49: =J49/F49 -> 0.33278381 | J49: 10450738 | K49: =SUM(H49+J49) -> 31403986 | L49: =H49/K49 -> 0.66721619 | M49: =J49/K49 -> 0.33278381 | N49: =D49/$D$53 -> 0.0043478261 | O49: 6496868 | P49: =O49*N49*M49 -> 9400.2281 | Q49: =O49*N49*L49 -> 18847.024
B50: Rensselaer | C50: 491200 | D50: 4 | E50: 10992 | F50: 15992771 | G50: =H50/F50 -> 0.58393014 | H50: =F50-J50 -> 9338661 | I50: =J50/F50 -> 0.41606986 | J50: 6654110 | K50: =SUM(H50+J50) -> 15992771 | L50: =H50/K50 -> 0.58393014 | M50: =J50/K50 -> 0.41606986 | N50: =D50/$D$53 -> 0.0057971014 | O50: 6496868 | P50: =O50*N50*M50 -> 15670.44 | Q50: =O50*N50*L50 -> 21992.563
B51: Troy | C51: 491700 | D51: 119 | E51: 10954 | F51: 81553767 | G51: =H51/F51 -> 0.64283589 | H51: =F51-J51 -> 52425688 | I51: =J51/F51 -> 0.35716411 | J51: 29128079 | K51: =SUM(H51+J51) -> 81553767 | L51: =H51/K51 -> 0.64283589 | M51: =J51/K51 -> 0.35716411 | N51: =D51/$D$53 -> 0.17246377 | O51: 6496868 | P51: =O51*N51*M51 -> 400193.22 | Q51: =O51*N51*L51 -> 720281.11
B52: Schenectady | C52: 530600 | D52: 16 | E52: 9112 | F52: 129603734 | G52: =H52/F52 -> 0.64854502 | H52: =F52-J52 -> 84053856 | I52: =J52/F52 -> 0.35145498 | J52: 45549878 | K52: =SUM(H52+J52) -> 129603734 | L52: =H52/K52 -> 0.64854502 | M52: =J52/K52 -> 0.35145498 | N52: =D52/$D$53 -> 0.023188406 | O52: 6496868 | P52: =O52*N52*M52 -> 52947.4 | Q52: =O52*N52*L52 -> 97704.612
A53: Total New Covenant | D53: =SUM(D43:D52) -> 690 | P53: =SUM(P43:P52) -> 3448538.5 | Q53: =SUM(Q43:Q52) -> 3048329.5 | R53: =SUM(P53:Q53) -> 6496868
A54: King Center Charter
B55: Buffalo City School District | C55: 140600 | D55: 104 | E55: 9499 | F55: 654618442 | G55: =H55/F55 -> 0.83782957 | H55: =F55-J55 -> 548458686 | I55: =J55/F55 -> 0.16217043 | J55: 106159756 | K55: =SUM(H55+J55) -> 654618442 | L55: =H55/K55 -> 0.83782957 | M55: =J55/K55 -> 0.16217043 | N55: =D55/D56 -> 1 | O55: ='Charter Archive File'!Q28 -> 985491 | P55: =O55*N55*M55 -> 159817.5 | Q55: =O55*N55*L55 -> 825673.5
A56: Total King Center Charter | D56: =SUM(D55) -> 104 | P56: =SUM(P55) -> 159817.5 | Q56: =SUM(Q55) -> 825673.5
A57: South Buffalo Charter
B58: Buffalo City School District | C58: 140600 | D58: 588 | E58: 9499 | F58: 654618442 | G58: =H58/F58 -> 0.83782957 | H58: =F58-J58 -> 548458686 | I58: =J58/F58 -> 0.16217043 | J58: 106159756 | K58: =SUM(H58+J58) -> 654618442 | L58: =H58/K58 -> 0.83782957 | M58: =J58/K58 -> 0.16217043 | N58: =D58/$D$66 -> 0.92163009 | O58: ='Charter Archive File'!Q24 -> 5964594 | P58: =O58*N58*M58 -> 891475.09 | Q58: =O58*N58*L58 -> 4605674.2
B59: Cheektowaga Central School District | C59: 140701 | D59: 2 | E59: 8622 | F59: 34101719 | G59: =H59/F59 -> 0.41280359 | H59: =F59-J59 -> 14077312 | I59: =J59/F59 -> 0.58719641 | J59: 20024407 | K59: =SUM(H59+J59) -> 34101719 | L59: =H59/K59 -> 0.41280359 | M59: =J59/K59 -> 0.58719641 | N59: =D59/$D$66 -> 0.0031347962 | O59: =$O$58 -> 5964594 | P59: =O59*N59*M59 -> 10979.273 | Q59: =O59*N59*L59 -> 7718.5135
B60: Cheektowaga-Maryvale Union Free School D | C60: 140702 | D60: 1 | E60: 8869 | F60: 32830620 | G60: =H60/F60 -> 0.5325681 | H60: =F60-J60 -> 17484541 | I60: =J60/F60 -> 0.4674319 | J60: 15346079 | K60: =SUM(H60+J60) -> 32830620 | L60: =H60/K60 -> 0.5325681 | M60: =J60/K60 -> 0.4674319 | N60: =D60/$D$66 -> 0.0015673981 | O60: =$O$58 -> 5964594 | P60: =O60*N60*M60 -> 4369.971 | Q60: =O60*N60*L60 -> 4978.9224
B61: Cleveland Hill Union Free School Distric | C61: 140703 | D61: 1 | E61: 7822 | F61: 23280999 | G61: =H61/F61 -> 0.61434456 | H61: =F61-J61 -> 14302555 | I61: =J61/F61 -> 0.38565544 | J61: 8978444 | K61: =SUM(H61+J61) -> 23280999 | L61: =H61/K61 -> 0.61434456 | M61: =J61/K61 -> 0.38565544 | N61: =D61/$D$66 -> 0.0015673981 | O61: =$O$58 -> 5964594 | P61: =O61*N61*M61 -> 3605.4516 | Q61: =O61*N61*L61 -> 5743.4418
B62: Springville-Griffith Institute Central S | C62: 141101 | D62: 1 | E62: 8780 | F62: 32201111 | G62: =H62/F62 -> 0.56220256 | H62: =F62-J62 -> 18103547 | I62: =J62/F62 -> 0.43779744 | J62: 14097564 | K62: =SUM(H62+J62) -> 32201111 | L62: =H62/K62 -> 0.56220256 | M62: =J62/K62 -> 0.43779744 | N62: =D62/$D$66 -> 0.0015673981 | O62: =$O$58 -> 5964594 | P62: =O62*N62*M62 -> 4092.9216 | Q62: =O62*N62*L62 -> 5255.9718
B63: Frontier Central School District | C63: 141604 | D63: 1 | E63: 8027 | F63: 62674392 | G63: =H63/F63 -> 0.50301847 | H63: =F63-J63 -> 31526377 | I63: =J63/F63 -> 0.49698153 | J63: 31148015 | K63: =SUM(H63+J63) -> 62674392 | L63: =H63/K63 -> 0.50301847 | M63: =J63/K63 -> 0.49698153 | N63: =D63/$D$66 -> 0.0015673981 | O63: =$O$58 -> 5964594 | P63: =O63*N63*M63 -> 4646.2273 | Q63: =O63*N63*L63 -> 4702.6661
B64: Lackawanna City School District | C64: 141800 | D64: 29 | E64: 9958 | F64: 34396218 | G64: =H64/F64 -> 0.7332571 | H64: =F64-J64 -> 25221271 | I64: =J64/F64 -> 0.2667429 | J64: 9174947 | K64: =SUM(H64+J64) -> 34396218 | L64: =H64/K64 -> 0.7332571 | M64: =J64/K64 -> 0.2667429 | N64: =D64/$D$66 -> 0.045454545 | O64: =$O$58 -> 5964594 | P64: =O64*N64*M64 -> 72318.778 | Q64: =O64*N64*L64 -> 198799.13
B65: West Seneca Central School District | C65: 142801 | D65: 15 | E65: 8281 | F65: 94634236 | G65: =H65/F65 -> 0.53528345 | H65: =F65-J65 -> 50656140 | I65: =J65/F65 -> 0.46471655 | J65: 43978096 | K65: =SUM(H65+J65) -> 94634236 | L65: =H65/K65 -> 0.53528345 | M65: =J65/K65 -> 0.46471655 | N65: =D65/$D$66 -> 0.023510972 | O65: =$O$58 -> 5964594 | P65: =O65*N65*M65 -> 65168.783 | Q65: =O65*N65*L65 -> 75064.618
A66: Total South Buffalo Charter | D66: =SUM(D58:D65) -> 638 | P66: =SUM(P58:P65) -> 1056656.5 | Q66: =SUM(Q58:Q65) -> 4907937.5
A67: Tapestry Charter
B68: Buffalo City School District | C68: 140600 | D68: 261 | E68: 9499 | F68: 654618442 | G68: =H68/F68 -> 0.83782957 | H68: =F68-J68 -> 548458686 | I68: =J68/F68 -> 0.16217043 | J68: 106159756 | K68: =SUM(H68+J68) -> 654618442 | L68: =H68/K68 -> 0.83782957 | M68: =J68/K68 -> 0.16217043 | N68: =D68/$D$75 -> 0.97026022 | O68: ='Charter Archive File'!Q69 -> 2542833 | P68: =O68*N68*M68 -> 400108.47 | Q68: =O68*N68*L68 -> 2067101.2
B69: Cheektowaga Central School District | C69: 140701 | D69: 1 | E69: 8622 | F69: 34101719 | G69: =H69/F69 -> 0.41280359 | H69: =F69-J69 -> 14077312 | I69: =J69/F69 -> 0.58719641 | J69: 20024407 | K69: =SUM(H69+J69) -> 34101719 | L69: =H69/K69 -> 0.41280359 | M69: =J69/K69 -> 0.58719641 | N69: =D69/$D$75 -> 0.0037174721 | O69: =$O$68 -> 2542833 | P69: =O69*N69*M69 -> 5550.7153 | Q69: =O69*N69*L69 -> 3902.1955
B70: Cleveland Hill Union Free School Distric | C70: 140703 | D70: 1 | E70: 7822 | F70: 23280999 | G70: =H70/F70 -> 0.61434456 | H70: =F70-J70 -> 14302555 | I70: =J70/F70 -> 0.38565544 | J70: 8978444 | K70: =SUM(H70+J70) -> 23280999 | L70: =H70/K70 -> 0.61434456 | M70: =J70/K70 -> 0.38565544 | N70: =D70/$D$75 -> 0.0037174721 | O70: =$O$68 -> 2542833 | P70: =O70*N70*M70 -> 3645.5665 | Q70: =O70*N70*L70 -> 5807.3443
B71: Lackawanna City School District | C71: 141800 | D71: 1 | E71: 9958 | F71: 34396218 | G71: =H71/F71 -> 0.7332571 | H71: =F71-J71 -> 25221271 | I71: =J71/F71 -> 0.2667429 | J71: 9174947 | K71: =SUM(H71+J71) -> 34396218 | L71: =H71/K71 -> 0.7332571 | M71: =J71/K71 -> 0.2667429 | N71: =D71/$D$75 -> 0.0037174721 | O71: =$O$68 -> 2542833 | P71: =O71*N71*M71 -> 2521.4969 | Q71: =O71*N71*L71 -> 6931.4139
B72: Orchard Park Central School District | C72: 142301 | D72: 1 | E72: 9244 | F72: 69118162 | G72: =H72/F72 -> 0.3829844 | H72: =F72-J72 -> 26471178 | I72: =J72/F72 -> 0.6170156 | J72: 42646984 | K72: =SUM(H72+J72) -> 69118162 | L72: =H72/K72 -> 0.3829844 | M72: =J72/K72 -> 0.6170156 | N72: =D72/$D$75 -> 0.0037174721 | O72: =$O$68 -> 2542833 | P72: =O72*N72*M72 -> 5832.5934 | Q72: =O72*N72*L72 -> 3620.3174
B73: Kenmore-Tonawanda Union Free School Dist | C73: 142601 | D73: 3 | E73: 10273 | F73: 125037016 | G73: =H73/F73 -> 0.48171099 | H73: =F73-J73 -> 60231705 | I73: =J73/F73 -> 0.51828901 | J73: 64805311 | K73: =SUM(H73+J73) -> 125037016 | L73: =H73/K73 -> 0.48171099 | M73: =J73/K73 -> 0.51828901 | N73: =D73/$D$75 -> 0.011152416 | O73: =$O$68 -> 2542833 | P73: =O73*N73*M73 -> 14698.019 | Q73: =O73*N73*L73 -> 13660.713
B74: West Seneca Central School District | C74: 142801 | D74: 1 | E74: 8281 | F74: 94634236 | G74: =H74/F74 -> 0.53528345 | H74: =F74-J74 -> 50656140 | I74: =J74/F74 -> 0.46471655 | J74: 43978096 | K74: =SUM(H74+J74) -> 94634236 | L74: =H74/K74 -> 0.53528345 | M74: =J74/K74 -> 0.46471655 | N74: =D74/$D$75 -> 0.0037174721 | O74: =$O$68 -> 2542833 | P74: =O74*N74*M74 -> 4392.9241 | Q74: =O74*N74*L74 -> 5059.9867
A75: Total Tapestry Charter | D75: =SUM(D68:D74) -> 269 | P75: =SUM(P68:P74) -> 436749.78 | Q75: =SUM(Q68:Q74) -> 2106083.2
A76: Community Charter
B77: Buffalo City School District | C77: 140600 | D77: 282 | E77: 9499 | F77: 654618442 | G77: =H77/F77 -> 0.83782957 | H77: =F77-J77 -> 548458686 | I77: =J77/F77 -> 0.16217043 | J77: 106159756 | K77: =SUM(H77+J77) -> 654618442 | L77: =H77/K77 -> 0.83782957 | M77: =J77/K77 -> 0.16217043 | N77: =D77/$D$81 -> 0.97916667 | O77: ='Charter Archive File'!Q39 -> 2610708 | P77: =O77*N77*M77 -> 414559.24 | Q77: =O77*N77*L77 -> 2141759
B78: Cheektowaga Central School District | C78: 140701 | D78: 1 | E78: 8622 | F78: 34101719 | G78: =H78/F78 -> 0.41280359 | H78: =F78-J78 -> 14077312 | I78: =J78/F78 -> 0.58719641 | J78: 20024407 | K78: =SUM(H78+J78) -> 34101719 | L78: =H78/K78 -> 0.41280359 | M78: =J78/K78 -> 0.58719641 | N78: =D78/$D$81 -> 0.0034722222 | O78: =$O$77 -> 2610708 | P78: =O78*N78*M78 -> 5322.911 | Q78: =O78*N78*L78 -> 3742.0473
B79: Cheektowaga-Sloan Union Free School Dist | C79: 140709 | D79: 1 | E79: 9854 | F79: 25951061 | G79: =H79/F79 -> 0.58483613 | H79: =F79-J79 -> 15177118 | I79: =J79/F79 -> 0.41516387 | J79: 10773943 | K79: =SUM(H79+J79) -> 25951061 | L79: =H79/K79 -> 0.58483613 | M79: =J79/K79 -> 0.41516387 | N79: =D79/$D$81 -> 0.0034722222 | O79: =$O$77 -> 2610708 | P79: =O79*N79*M79 -> 3763.4432 | Q79: =O79*N79*L79 -> 5301.5151
B80: West Seneca Central School District | C80: 142801 | D80: 4 | E80: 8281 | F80: 94634236 | G80: =H80/F80 -> 0.53528345 | H80: =F80-J80 -> 50656140 | I80: =J80/F80 -> 0.46471655 | J80: 43978096 | K80: =SUM(H80+J80) -> 94634236 | L80: =H80/K80 -> 0.53528345 | M80: =J80/K80 -> 0.46471655 | N80: =D80/$D$81 -> 0.013888889 | O80: =$O$77 -> 2610708 | P80: =O80*N80*M80 -> 16850.545 | Q80: =O80*N80*L80 -> 19409.289
A81: Total Community Charter | D81: =SUM(D77:D80) -> 288 | P81: =SUM(P77:P80) -> 440496.14 | Q81: =SUM(Q77:Q80) -> 2170211.9
A82: Buffalo United Charter
B83: Sweet Home Central School District | C83: 140207 | D83: 2 | E83: 9698 | F83: 59330003 | G83: =H83/F83 -> 0.41647426 | H83: =F83-J83 -> 24709419 | I83: =J83/F83 -> 0.58352574 | J83: 34620584 | K83: =SUM(H83+J83) -> 59330003 | L83: =H83/K83 -> 0.41647426 | M83: =J83/K83 -> 0.58352574 | N83: =D83/$D$89 -> 0.0041753653 | O83: ='Charter Archive File'!Q9 -> 4445602 | P83: =O83*N83*M83 -> 10831.412 | Q83: =O83*N83*L83 -> 7730.6004
B84: Buffalo City School District | C84: 140600 | D84: 461 | E84: 9499 | F84: 654618442 | G84: =H84/F84 -> 0.83782957 | H84: =F84-J84 -> 548458686 | I84: =J84/F84 -> 0.16217043 | J84: 106159756 | K84: =SUM(H84+J84) -> 654618442 | L84: =H84/K84 -> 0.83782957 | M84: =J84/K84 -> 0.16217043 | N84: =D84/$D$89 -> 0.96242171 | O84: =$O$83 -> 4445602 | P84: =O84*N84*M84 -> 693853.31 | Q84: =O84*N84*L84 -> 3584690.6
B85: Cheektowaga Central School District | C85: 140701 | D85: 6 | E85: 8622 | F85: 34101719 | G85: =H85/F85 -> 0.41280359 | H85: =F85-J85 -> 14077312 | I85: =J85/F85 -> 0.58719641 | J85: 20024407 | K85: =SUM(H85+J85) -> 34101719 | L85: =H85/K85 -> 0.41280359 | M85: =J85/K85 -> 0.58719641 | N85: =D85/$D$89 -> 0.012526096 | O85: =$O$83 -> 4445602 | P85: =O85*N85*M85 -> 32698.641 | Q85: =O85*N85*L85 -> 22987.396
B86: Cleveland Hill Union Free School Distric | C86: 140703 | D86: 4 | E86: 7822 | F86: 23280999 | G86: =H86/F86 -> 0.61434456 | H86: =F86-J86 -> 14302555 | I86: =J86/F86 -> 0.38565544 | J86: 8978444 | K86: =SUM(H86+J86) -> 23280999 | L86: =H86/K86 -> 0.61434456 | M86: =J86/K86 -> 0.38565544 | N86: =D86/$D$89 -> 0.0083507307 | O86: =$O$83 -> 4445602 | P86: =O86*N86*M86 -> 14317.082 | Q86: =O86*N86*L86 -> 22806.943
B87: Kenmore-Tonawanda Union Free School Dist | C87: 142601 | D87: 3 | E87: 10273 | F87: 125037016 | G87: =H87/F87 -> 0.48171099 | H87: =F87-J87 -> 60231705 | I87: =J87/F87 -> 0.51828901 | J87: 64805311 | K87: =SUM(H87+J87) -> 125037016 | L87: =H87/K87 -> 0.48171099 | M87: =J87/K87 -> 0.51828901 | N87: =D87/$D$89 -> 0.006263048 | O87: =$O$83 -> 4445602 | P87: =O87*N87*M87 -> 14430.731 | Q87: =O87*N87*L87 -> 13412.288
B88: West Seneca Central School District | C88: 142801 | D88: 3 | E88: 8281 | F88: 94634236 | G88: =H88/F88 -> 0.53528345 | H88: =F88-J88 -> 50656140 | I88: =J88/F88 -> 0.46471655 | J88: 43978096 | K88: =SUM(H88+J88) -> 94634236 | L88: =H88/K88 -> 0.53528345 | M88: =J88/K88 -> 0.46471655 | N88: =D88/$D$89 -> 0.006263048 | O88: =$O$83 -> 4445602 | P88: =O88*N88*M88 -> 12939.112 | Q88: =O88*N88*L88 -> 14903.907
A89: Total Buffalo United Charter | D89: =SUM(D83:D88) -> 479 | P89: =SUM(P83:P88) -> 779070.29 | Q89: =SUM(Q83:Q88) -> 3666531.7
A90: Pinnacle Charter
B91: Amherst Central School District | C91: 140201 | D91: 1 | E91: 10335 | F91: 38788783 | G91: =H91/F91 -> 0.36065919 | H91: =F91-J91 -> 13989531 | I91: =J91/F91 -> 0.63934081 | J91: 24799252 | K91: =SUM(H91+J91) -> 38788783 | L91: =H91/K91 -> 0.36065919 | M91: =J91/K91 -> 0.63934081 | N91: =D91/$D$101 -> 0.0024691358 | O91: ='Charter Archive File'!Q27 -> 3859552 | P91: =O91*N91*M91 -> 6092.7632 | Q91: =O91*N91*L91 -> 3436.9948
B92: Williamsville Central School District | C92: 140203 | D92: 3 | E92: 9699 | F92: 145327421 | G92: =H92/F92 -> 0.30972277 | H92: =F92-J92 -> 45011211 | I92: =J92/F92 -> 0.69027723 | J92: 100316210 | K92: =SUM(H92+J92) -> 145327421 | L92: =H92/K92 -> 0.30972277 | M92: =J92/K92 -> 0.69027723 | N92: =D92/$D$101 -> 0.0074074074 | O92: =$O$91 -> 3859552 | P92: =O92*N92*M92 -> 19734.525 | Q92: =O92*N92*L92 -> 8854.7491
B93: Sweet Home Central School District | C93: 140207 | D93: 1 | E93: 9698 | F93: 59330003 | G93: =H93/F93 -> 0.41647426 | H93: =F93-J93 -> 24709419 | I93: =J93/F93 -> 0.58352574 | J93: 34620584 | K93: =SUM(H93+J93) -> 59330003 | L93: =H93/K93 -> 0.41647426 | M93: =J93/K93 -> 0.58352574 | N93: =D93/$D$101 -> 0.0024691358 | O93: =$O$91 -> 3859552 | P93: =O93*N93*M93 -> 5560.8591 | Q93: =O93*N93*L93 -> 3968.8989
B94: Buffalo City School District | C94: 140600 | D94: 390 | E94: 9499 | F94: 654618442 | G94: =H94/F94 -> 0.83782957 | H94: =F94-J94 -> 548458686 | I94: =J94/F94 -> 0.16217043 | J94: 106159756 | K94: =SUM(H94+J94) -> 654618442 | L94: =H94/K94 -> 0.83782957 | M94: =J94/K94 -> 0.16217043 | N94: =D94/$D$101 -> 0.96296296 | O94: =$O$91 -> 3859552 | P94: =O94*N94*M94 -> 602723.54 | Q94: =O94*N94*L94 -> 3113882.1
B95: Cheektowaga Central School District | C95: 140701 | D95: 1 | E95: 8622 | F95: 34101719 | G95: =H95/F95 -> 0.41280359 | H95: =F95-J95 -> 14077312 | I95: =J95/F95 -> 0.58719641 | J95: 20024407 | K95: =SUM(H95+J95) -> 34101719 | L95: =H95/K95 -> 0.41280359 | M95: =J95/K95 -> 0.58719641 | N95: =D95/$D$101 -> 0.0024691358 | O95: =$O$91 -> 3859552 | P95: =O95*N95*M95 -> 5595.8397 | Q95: =O95*N95*L95 -> 3933.9183
B96: Cheektowaga-Maryvale Union Free School D | C96: 140702 | D96: 2 | E96: 8869 | F96: 32830620 | G96: =H96/F96 -> 0.5325681 | H96: =F96-J96 -> 17484541 | I96: =J96/F96 -> 0.4674319 | J96: 15346079 | K96: =SUM(H96+J96) -> 32830620 | L96: =H96/K96 -> 0.5325681 | M96: =J96/K96 -> 0.4674319 | N96: =D96/$D$101 -> 0.0049382716 | O96: =$O$91 -> 3859552 | P96: =O96*N96*M96 -> 8909.0258 | Q96: =O96*N96*L96 -> 10150.49
B97: Cleveland Hill Union Free School Distric | C97: 140703 | D97: 4 | E97: 7822 | F97: 23280999 | G97: =H97/F97 -> 0.61434456 | H97: =F97-J97 -> 14302555 | I97: =J97/F97 -> 0.38565544 | J97: 8978444 | K97: =SUM(H97+J97) -> 23280999 | L97: =H97/K97 -> 0.61434456 | M97: =J97/K97 -> 0.38565544 | N97: =D97/$D$101 -> 0.0098765432 | O97: =$O$91 -> 3859552 | P97: =O97*N97*M97 -> 14700.812 | Q97: =O97*N97*L97 -> 23418.22
B98: Depew Union Free School District | C98: 140707 | D98: 1 | E98: 10029 | F98: 2652914 | G98: =H98/F98 -> -4.6185127 | H98: =F98-J98 -> -12252517 | I98: =J98/F98 -> 5.6185127 | J98: 14905431 | K98: =SUM(H98+J98) -> 2652914 | L98: =H98/K98 -> -4.6185127 | M98: =J98/K98 -> 5.6185127 | N98: =D98/$D$101 -> 0.0024691358 | O98: =$O$91 -> 3859552 | P98: =O98*N98*M98 -> 53543.066 | Q98: =O98*N98*L98 -> -44013.308
B99: Hamburg Central School District | C99: 141601 | D99: 1 | E99: 9007 | F99: 47163173 | G99: =H99/F99 -> 0.50440092 | H99: =F99-J99 -> 23789148 | I99: =J99/F99 -> 0.49559908 | J99: 23374025 | K99: =SUM(H99+J99) -> 47163173 | L99: =H99/K99 -> 0.50440092 | M99: =J99/K99 -> 0.49559908 | N99: =D99/$D$101 -> 0.0024691358 | O99: =$O$91 -> 3859552 | P99: =O99*N99*M99 -> 4722.9393 | Q99: =O99*N99*L99 -> 4806.8187
B100: West Seneca Central School District | C100: 142801 | D100: 1 | E100: 8281 | F100: 94634236 | G100: =H100/F100 -> 0.53528345 | H100: =F100-J100 -> 50656140 | I100: =J100/F100 -> 0.46471655 | J100: 43978096 | K100: =SUM(H100+J100) -> 94634236 | L100: =H100/K100 -> 0.53528345 | M100: =J100/K100 -> 0.46471655 | N100: =D100/$D$101 -> 0.0024691358 | O100: =$O$91 -> 3859552 | P100: =O100*N100*M100 -> 4428.6363 | Q100: =O100*N100*L100 -> 5101.1217
...

Sheet District Archive File
A1: District | D1: Year | E1: UFB | F1: STaid | G1: STAR | H1: TOTSTAT | I1: LREV | J1: FEDREV | K1: TOTREV | L1: BDED0607 | M1: CADM0607 | N1: TSAL0607 | O1: PPS0607 | P1: CDS0607 | Q1: BOC0607 | R1: TUI10607 | S1: TUI20607 | T1: OIS0607 | U1: OIEXP0607 | V1: CSER0607 | W1: OPMT0607 | X1: TCHR0607 | Y1: HEAL0607 | Z1: OEB0607 | AA1: OUND0607 | AB1: OTH0607 | AC1: SUBTOT | AD1: TRANS0607 | AE1: DSP0607 | AF1: DSI0607 | AG1: TEXP0506 | AH1: DCAADM | AI1: REV/PUPIL | AJ1: EXP/PUPIL | AK1: AV/TWPU | AL1: INC/TWPU | AM1: CWR | AN1: IE1/TOTAL | AO1: INS FB% | AP1: IE2% | AQ1: IE3/ADJ EXP | AR1: LOC EFF RATE
A2: 010100 | B2: ALBANY | D2: 2006 | E2: 9391660 | F2: 61985001 | G2: 10781965 | H2: 72766966 | I2: 100099355 | J2: 14202125 | K2: 187068446 | L2: 337488 | M2: 1944400 | N2: 52770396 | O2: 5594128 | P2: 4652548 | Q2: 4070123 | R2: 237068 | S2: 6500274 | T2: 16672939 | U2: 22021702 | V2: 1082653 | W2: 11385459 | X2: 5062461 | Y2: 15253020 | Z2: 12100562 | AA2: 3859192 | AB2: 717000 | AC2: 164261413 | AD2: 5921905 | AE2: 7040756 | AF2: 6378739 | AG2: 183602813 | AH2: 10416 | AI2: 17960 | AJ2: 17627 | AK2: 264221 | AL2: 99659 | AM2: 0.754 | AN2: 0.61284016 | AO2: 0.162 | AP2: 0.77484016 | AQ2: 0.8669 | AR2: 24.51
A3: 010201 | B3: BERNE KNOX | D3: 2006 | E3: 1772806 | F3: 8510365 | G3: 1552745 | H3: 10063110 | I3: 8674623 | J3: 738334 | K3: 19476067 | L3: 67838 | M3: 471480 | N3: 5646243 | O3: 0 | P3: 297223 | Q3: 2034555 | R3: 1180 | S3: 350246 | T3: 863681 | U3: 663008 | V3: 0 | W3: 884054 | X3: 526995 | Y3: 2970694 | Z3: 973692 | AA3: 201620 | AB3: 247579 | AC3: 16200088 | AD3: 1606294 | AE3: 703943 | AF3: 250388 | AG3: 18760713 | AH3: 1152 | AI3: 16906 | AJ3: 16285 | AK3: 274364 | AL3: 94667 | AM3: 0.746 | AN3: 0.52536042 | AO3: 0.183 | AP3: 0.70836042 | AQ3: 0.8292 | AR3: 19.72
A4: 010306 | B4: BETHLEHEM | D4: 2006 | E4: 2790327 | F4: 23148376 | G4: 6750166 | H4: 29898542 | I4: 48092263 | J4: 1665041 | K4: 79655846 | L4: 310085 | M4: 903198 | N4: 23631833 | O4: 1731877 | P4: 1927349 | Q4: 2314073 | R4: 991025 | S4: 0 | T4: 6362930 | U4: 2700328 | V4: 0 | W4: 4338334 | X4: 2453424 | Y4: 7810180 | Z4: 4715379 | AA4: 997780 | AB4: 279961 | AC4: 61467756 | AD4: 5199804 | AE4: 4564985 | AF4: 4183369 | AG4: 75415914 | AH4: 4919 | AI4: 16194 | AJ4: 15332 | AK4: 323121 | AL4: 143970 | AM4: 1.013 | AN4: 0.52587594 | AO4: 0.164 | AP4: 0.68987594 | AQ4: 0.8436 | AR4: 19.71
A5: 010402 | B5: RAVENACOEYMAN | D5: 2006 | E5: 2174497 | F5: 15856148 | G5: 3011264 | H5: 18867412 | I5: 20443166 | J5: 1829530 | K5: 41140108 | L5: 205735 | M5: 805983 | N5: 13553561 | O5: 1076869 | P5: 576931 | Q5: 2875915 | R5: 35971 | S5: 964189 | T5: 1609005 | U5: 1617389 | V5: 0 | W5: 2625132 | X5: 1638392 | Y5: 2711402 | Z5: 2162510 | AA5: 602623 | AB5: 215205 | AC5: 33276812 | AD5: 2833969 | AE5: 2532169 | AF5: 1226870 | AG5: 39869820 | AH5: 2254 | AI5: 18252 | AJ5: 17688 | AK5: 298219 | AL5: 89687 | AM5: 0.758 | AN5: 0.55956686 | AO5: 0.134 | AP5: 0.69356686 | AQ5: 0.8358 | AR5: 20.36
A6: 010500 | B6: COHOES | D6: 2006 | E6: 1679645 | F6: 15970615 | G6: 2759513 | H6: 18730128 | I6: 11467144 | J6: 2284729 | K6: 32482001 | L6: 142228 | M6: 780674 | N6: 11284815 | O6: 694296 | P6: 812178 | Q6: 1481549 | R6: 498625 | S6: 76434 | T6: 2097326 | U6: 1412971 | V6: 0 | W6: 2395541 | X6: 1103517 | Y6: 3688568 | Z6: 1799876 | AA6: 599833 | AB6: 76357 | AC6: 28944788 | AD6: 809523 | AE6: 1778764 | AF6: 592341 | AG6: 32125416 | AH6: 2121 | AI6: 15314 | AJ6: 15146 | AK6: 145261 | AL6: 79495 | AM6: 0.516 | AN6: 0.57145389 | AO6: 0.184 | AP6: 0.75545389 | AQ6: 0.8378 | AR6: 24.13
A7: 010601 | B7: SOUTH COLONIE | D7: 2006 | E7: 3179174 | F7: 21034443 | G7: 6989127 | H7: 28023570 | I7: 52765846 | J7: 2204028 | K7: 82993444 | L7: 249073 | M7: 1081181 | N7: 31094392 | O7: 780126 | P7: 1352711 | Q7: 1967720 | R7: 124584 | S7: 1014992 | T7: 7065515 | U7: 4178347 | V7: 371937 | W7: 5021835 | X7: 2989513 | Y7: 7317822 | Z7: 5393145 | AA7: 1585837 | AB7: 0 | AC7: 71588730 | AD7: 3594911 | AE7: 3776865 | AF7: 1847996 | AG7: 80808502 | AH7: 5593 | AI7: 14839 | AJ7: 14448 | AK7: 419464 | AL7: 108496 | AM7: 0.993 | AN7: 0.58877947 | AO7: 0.167 | AP7: 0.75577947 | AQ7: 0.8529 | AR7: 16.42
A8: 010605 | B8: NORTH COLONIE | D8: 2006 | E8: 4139145 | F8: 13407553 | G8: 5153966 | H8: 18561519 | I8: 57007023 | J8: 1292895 | K8: 76861437 | L8: 350374 | M8: 1222494 | N8: 28171984 | O8: 1769369 | P8: 1477306 | Q8: 313800 | R8: 0 | S8: 206829 | T8: 6895235 | U8: 3657553 | V8: 0 | W8: 6212885 | X8: 2791581 | Y8: 5941737 | Z8: 4802011 | AA8: 1387737 | AB8: 1052000 | AC8: 66252895 | AD8: 4715716 | AE8: 3549470 | AF8: 1926284 | AG8: 76444365 | AH8: 5460 | AI8: 14077 | AJ8: 14001 | AK8: 517499 | AL8: 166985 | AM8: 1.362 | AN8: 0.55585622 | AO8: 0.149 | AP8: 0.70485622 | AQ8: 0.8262 | AR8: 15.42
A9: 010615 | B9: MENANDS | D9: 2006 | E9: 848529 | F9: 556367 | G9: 282289 | H9: 838656 | I9: 5824532 | J9: 83593 | K9: 6746781 | L9: 37703 | M9: 342676 | N9: 1638298 | O9: 68661 | P9: 447 | Q9: 356735 | R9: 1341006 | S9: 0 | T9: 99279 | U9: 253522 | V9: 500 | W9: 265946 | X9: 152288 | Y9: 486790 | Z9: 228119 | AA9: 59412 | AB9: 32000 | AC9: 5363382 | AD9: 628820 | AE9: 315000 | AF9: 158805 | AG9: 6466007 | AH9: 378 | AI9: 17849 | AJ9: 17106 | AK9: 730740 | AL9: 251553 | AM9: 1.987 | AN9: 0.58118527 | AO9: 0.108 | AP9: 0.68918527 | AQ9: 0.7742 | AR9: 17.63
A10: 010622 | B10: MAPLEWOOD | D10: 2006 | E10: 105557 | F10: 593116 | G10: 128993 | H10: 722109 | I10: 1732089 | J10: 64148 | K10: 2518346 | L10: 17756 | M10: 148580 | N10: 849340 | O10: 52150 | P10: 0 | Q10: 146480 | R10: 322395 | S10: 108587 | T10: 115466 | U10: 63904 | V10: 0 | W10: 146636 | X10: 87381 | Y10: 198830 | Z10: 112402 | AA10: 53866 | AB10: 0 | AC10: 2423773 | AD10: 73256 | AE10: 20000 | AF10: 11925 | AG10: 2528954 | AH10: 201 | AI10: 12529 | AJ10: 12582 | AK10: 464690 | AL10: 139753 | AM10: 1.18 | AN10: 0.65573435 | AO10: 0.133 | AP10: 0.78873435 | AQ10: 0.7954 | AR10: 28.72
A11: 010701 | B11: GREEN ISLAND | D11: 2006 | E11: 954765 | F11: 1953731 | G11: 412845 | H11: 2366576 | I11: 3153237 | J11: 177335 | K11: 5697148 | L11: 60113 | M11: 211033 | N11: 1577181 | O11: 152803 | P11: 126042 | Q11: 635366 | R11: 0 | S11: 44105 | T11: 259149 | U11: 208401 | V11: 1640 | W11: 339418 | X11: 173890 | Y11: 324573 | Z11: 231216 | AA11: 137663 | AB11: 0 | AC11: 4482593 | AD11: 308525 | AE11: 300741 | AF11: 462187 | AG11: 5554046 | AH11: 332 | AI11: 17160 | AJ11: 16729 | AK11: 176321 | AL11: 87360 | AM11: 0.588 | AN11: 0.54069538 | AO11: 0.112 | AP11: 0.65269538 | AQ11: 0.8081 | AR11: 37.01
A12: 010802 | B12: GUILDERLAND | D12: 2006 | E12: 6203058 | F12: 23250659 | G12: 6384197 | H12: 29634856 | I12: 50963291 | J12: 1460334 | K12: 82058481 | L12: 171747 | M12: 1064380 | N12: 25863701 | O12: 1590613 | P12: 2529249 | Q12: 3485764 | R12: 0 | S12: 1352894 | T12: 6614544 | U12: 2697995 | V12: 0 | W12: 5534844 | X12: 2825418 | Y12: 7687323 | Z12: 4378406 | AA12: 1153535 | AB12: 0 | AC12: 66950413 | AD12: 4238827 | AE12: 4780384 | AF12: 2317955 | AG12: 78287579 | AH12: 5371 | AI12: 15278 | AJ12: 14576 | AK12: 345787 | AL12: 141740 | AM12: 1.033 | AN12: 0.56375175 | AO12: 0.161 | AP12: 0.72475175 | AQ12: 0.8472 | AR12: 17.89
A13: 011003 | B13: VOORHEESVILLE | D13: 2006 | E13: 886657 | F13: 5764070 | G13: 1767447 | H13: 7531517 | I13: 12761920 | J13: 346222 | K13: 20639659 | L13: 165026 | M13: 495240 | N13: 6763106 | O13: 380024 | P13: 364393 | Q13: 1109905 | R13: 11099 | S13: 110638 | T13: 1215832 | U13: 670777 | V13: 28644 | W13: 1362636 | X13: 687917 | Y13: 2547082 | Z13: 1107760 | AA13: 325771 | AB13: 534851 | AC13: 17880701 | AD13: 894939 | AE13: 1343218 | AF13: 723026 | AG13: 20841884 | AH13: 1231 | AI13: 16767 | AJ13: 16931 | AK13: 359379 | AL13: 158232 | AM13: 1.119 | AN13: 0.5098279 | AO13: 0.175 | AP13: 0.6848279 | AQ13: 0.822 | AR13: 18.74
... A678: 680801 | B678: DUNDEE | D678: 2006 | E678: 1398007 | F678: 7234758 | G678: 909846 | H678: 8144604 | I678: 3704917 | J678: 1419336 | K678: 13268857 | L678: 59684 | M678: 342285 | N678: 4687275 | O678: 148534 | P678: 175706 | Q678: 720948 | R678: 12873 | S678: 200 | T678: 921766 | U678: 683970 | V678: 0 | W678: 795694 | X678: 358266 | Y678: 1120627 | Z678: 883663 | AA678: 207925 | AB678: 0 | AC678: 11119416 | AD678: 681800 | AE678: 760000 | AF678: 292257 | AG678: 12853473 | AH678: 945 | AI678: 14041 | AJ678: 13602 | AK678: 215306 | AL678: 57357 | AM678: 0.516 | AN678: 0.57192885 | AO678: 0.156 | AP678: 0.72792885 | AQ678: 0.8418 | AR678: 13.25
A679: 999999 | B679: STATE | D679: 2006 | E679: 1619994566 | F679: 18037704210 | G679: 3553529613 | H679: 21591233823 | I679: 24965812794 | J679: 2739671347 | K679: 49296717964 | L679: 160370576 | M679: 792673793 | N679: 17031940292 | O679: 611843369 | P679: 1118113354 | Q679: 1846045277 | R679: 518070232 | S679: 767917815 | T679: 2961786133 | U679: 3085149569 | V679: 98570011 | W679: 3113401466 | X679: 2506230028 | Y679: 4033668462 | Z679: 3345900549 | AA679: 1012618868 | AB679: 267206592 | AC679: 43271506386 | AD679: 2515971434 | AE679: 1583042758 | AF679: 1196065168 | AG679: 48566585746 | AH679: 2802441 | AI679: 17591 | AJ679: 17330 | AK679: 382200 | AL679: 121800 | AM679: 1 | AN679: 0.57531049 | AO679: 0.18 | AP679: 0.75531049 | AQ679: 0.8502 | AR679: 15.1

Sheet Dist Work File
A1: District | C1: Enrollment | D1: Year | E1: LREV | F1: TOTSTAT | G1: FEDREV | H1: Other | I1: Indeterminate | J1: TOTREV
A2: 010100 | B2: ALBANY | D2: 2006 | E2: 100099355 | F2: 72766966 | G2: 14202125 | J2: 187068446
A3: 010201 | B3: BERNE KNOX | D3: 2006 | E3: 8674623 | F3: 10063110 | G3: 738334 | J3: 19476067
A4: 010306 | B4: BETHLEHEM | D4: 2006 | E4: 48092263 | F4: 29898542 | G4: 1665041 | J4: 79655846
A5: 010402 | B5: RAVENACOEYMAN | D5: 2006 | E5: 20443166 | F5: 18867412 | G5: 1829530 | J5: 41140108
A6: 010500 | B6: COHOES | D6: 2006 | E6: 11467144 | F6: 18730128 | G6: 2284729 | J6: 32482001
A7: 010601 | B7: SOUTH COLONIE | D7: 2006 | E7: 52765846 | F7: 28023570 | G7: 2204028 | J7: 82993444
A8: 010605 | B8: NORTH COLONIE | D8: 2006 | E8: 57007023 | F8: 18561519 | G8: 1292895 | J8: 76861437
A9: 010615 | B9: MENANDS | D9: 2006 | E9: 5824532 | F9: 838656 | G9: 83593 | J9: 6746781
A10: 010622 | B10: MAPLEWOOD | D10: 2006 | E10: 1732089 | F10: 722109 | G10: 64148 | J10: 2518346
A11: 010701 | B11: GREEN ISLAND | D11: 2006 | E11: 3153237 | F11: 2366576 | G11: 177335 | J11: 5697148
A12: 010802 | B12: GUILDERLAND | D12: 2006 | E12: 50963291 | F12: 29634856 | G12: 1460334 | J12: 82058481
A13: 011003 | B13: VOORHEESVILLE | D13: 2006 | E13: 12761920 | F13: 7531517 | G13: 346222 | J13: 20639659
... A678: 680801 | B678: DUNDEE | D678: 2006 | E678: 3704917 | F678: 8144604 | G678: 1419336 | J678: 13268857
B679: State Subtotal | C679: 2714773 | D679: 2006 | E679: 24965812794 | F679: 21591233823 | G679: 2739671347 | J679: 49296717964
B680: Food Service & Capital Revenue | E680: ='Dist Food Sv & Capital'!R21 -> 1626068312 | F680: ='Dist Food Sv & Capital'!R39 -> 3127106016 | G680: ='Dist Food Sv & Capital'!R9 -> 74027060 | H680: ='Dist Food Sv & Capital'!R34 -> 394627352 | I680: ='Dist Food Sv & Capital'!R11 -> 118662 | L680: NIEER Preschool Revenue Data
B681: Total Statewide prior to deductions | E681: =SUM(E679:E680) -> 26591881106 | F681: =SUM(F679:F680) -> 24718339839 | G681: =SUM(G679:G680) -> 2813698407 | H681: =SUM(H679:H680) -> 394627352 | I681: =SUM(I679:I680) -> 118662 | M681: State Preschool | N681: Federal Preschool
B682: Less Preschool/PreK | C682: 40063 | F682: 504413929 | G682: 740979286 | M682: =F682 -> 504413929 | N682: =G682 -> 740979286
B683: Less Charter Passthroughs | E683: ='Charter Work File'!E97 -> 1.0575797e+08 | F683: ='Charter Work File'!K97 -> 1.7055021e+08 | L683: PPR | M683: =M682/C682 -> 12590.518 | N683: =N682/C682 -> 18495.352
B684: Less Adult | F684: =Adult!G24 -> 954009 | G684: =Adult!G59 -> 8004104
B685: Total Statewide After Deductions | C685: =C679 -> 2714773 | E685: =E681-(E682+E683+E684) -> 2.6486123e+10 | F685: =F681-(F682+F683+F684) -> 2.4042422e+10 | G685: =G681-(G682+G683+G684) -> 2064715017 | H685: =H681-(H682+H683+H684) -> 394627352 | I685: =I681-(I682+I683+I684) -> 118662 | J685: =SUM(E685:I685) -> 52988005852 | L685: Note: NIEER reports 84,660 preschool students.
E686: =E685/C685 -> 9756.2939 | F686: =F685/C685 -> 8856.1444 | G686: =G685/C685 -> 760.54794 | H686: =H685/C685 -> 145.36293 | I686: =I685/C685 -> 0.043709732 | L686: However, NIEER only has statewide numbers - none
E687: =E685/J685 -> 0.49985129 | F687: =F685/J685 -> 0.45373328 | G687: =G685/J685 -> 0.038965705 | H687: =H685/J685 -> 0.0074474845 | I687: =I685/J685 -> 2.2394124e-06 | L687: for districts. We used the NYSED report card stats
L688: for that reason as they provide district based numbers
A689: 010100 | B689: ALBANY | D689: 2006 | E689: 100099355 | F689: 72766966 | G689: 14202125 | L689: for pre-K. This results in a higher per pupil than using
B690: Food Service & Capital Revenue | E690: ='Dist Food Sv & Capital'!S21 -> 30435588 | F690: ='Dist Food Sv & Capital'!S39 -> 121389 | G690: ='Dist Food Sv & Capital'!S9 -> 2536855 | H690: ='Dist Food Sv & Capital'!S34 -> 426801 | I690: ='Dist Food Sv & Capital'!S11 -> 0 | L690: the NIEER enrollment but there was no other choice
B691: Total Albany prior to deducations | E691: =SUM(E689:E690) -> 130534943 | F691: =SUM(F689:F690) -> 72888355 | G691: =SUM(G689:G690) -> 16738980 | H691: =SUM(H689:H690) -> 426801 | I691: =SUM(I689:I690) -> 0 | L691: since they do not have district based enrollments.
B692: Less Preschool/PreK | C692: 321 | F692: =M683*C692 -> 4041556.3 | G692: =N683*C692 -> 5937008
B693: Less Charter Passthroughs | E693: ='Charter Work File'!E197 -> 8017133.8 | F693: ='Charter Work File'!K197 -> 6765834.2 | L693: Note: Food Service and Capital Revenue not reported in public documents by the NYSED.
B694: Less Adult | F694: =Adult!L3 -> 14140 | L694: Information provided through the raw data submission by districts to the NYSED except
B695: Total Albany After Deducations | C695: 8603 | E695: =E691-(E692+E693+E694) -> 1.2251781e+08 | F695: =F691-(F692+F693+F694) -> 62066824 | G695: =G691-(G692+G693+G694) -> 10801972 | H695: =H691-(H692+H693+H694) -> 426801 | I695: =I691-(I692+I693+I694) -> 0 | J695: =SUM(E695:I695) -> 1.9581341e+08 | L695: for New York City. NYC data derived from the FY07 audit of the New York City
E696: =E695/C695 -> 14241.289 | F696: =F695/C695 -> 7214.5559 | G696: =G695/C695 -> 1255.6053 | H696: =H695/C695 -> 49.610717 | I696: =I695/C695 -> 0 | L696: School Construction Authority
E697: =E695/J695 -> 0.62568652 | F697: =F695/J695 -> 0.31696923 | G697: =G695/J695 -> 0.055164619 | H697: =H695/J695 -> 0.0021796311 | I697: =I695/J695 -> 0
A699: 140600 | B699: BUFFALO | D699: 2006 | E699: 106159756 | F699: 548458716 | G699: 69637969
B700: Food Service & Capital Revenue | E700: ='Dist Food Sv & Capital'!T21 -> 5942800 | F700: ='Dist Food Sv & Capital'!T39 -> 756078 | G700: ='Dist Food Sv & Capital'!T9 -> 16193712 | H700: ='Dist Food Sv & Capital'!T34 -> 4109734 | I700: ='Dist Food Sv & Capital'!T11 -> 0
B701: Total Buffalo prior to deductions | E701: =SUM(E699:E700) -> 112102556 | F701: =SUM(F699:F700) -> 549214794 | G701: =SUM(G699:G700) -> 85831681 | H701: =SUM(H699:H700) -> 4109734 | I701: =SUM(I699:I700) -> 0
B702: Less Preschool/PreK | C702: 1951 | F702: =M683*C702 -> 24564101 | G702: =N683*C702 -> 36084432
B703: Less Charter Passthroughs | E703: ='Charter Work File'!E183 -> 7231849.9 | F703: ='Charter Work File'!K183 -> 37230455
B704: Less Adult | F704: =Adult!L7 -> 215890 | G704: =Adult!L12 -> 302988
B705: Total Buffalo After Deducations | C705: 34589 | E705: =E701-(E702+E703+E704) -> 1.0487071e+08 | F705: =F701-(F702+F703+F704) -> 4.8720435e+08 | G705: =G701-(G702+G703+G704) -> 49444261 | H705: =H701-(H702+H703+H704) -> 4109734 | I705: =I701-(I702+I703+I704) -> 0 | J705: =SUM(E705:I705) -> 6.4562905e+08
E706: =E705/C705 -> 3031.9092 | F706: =F705/C705 -> 14085.529 | G706: =G705/C705 -> 1429.4794 | H706: =H705/C705 -> 118.81621 | I706: =I705/C705 -> 0
E707: =E705/J705 -> 0.16243183 | F707: =F705/J705 -> 0.75461962 | G707: =G705/J705 -> 0.07658308 | H707: =H705/J705 -> 0.0063654726 | I707: =I705/J705 -> 0
A709: 300000 | B709: NEW YORK CITY | D709: 2006 | E709: 8536341160 | F709: 8073019131 | G709: 1586091039
B710: Food Service & Capital Revenue | E710: ='Dist Food Sv & Capital'!U21 -> 0 | F710: ='Dist Food Sv & Capital'!U39 -> 1772729586 | G710: ='Dist Food Sv & Capital'!U9 -> 317023056 | H710: ='Dist Food Sv & Capital'!U34 -> 36648466 | I710: ='Dist Food Sv & Capital'!U11 -> 118662
B711: Total NYC prior to deductions | E711: =SUM(E709:E710) -> 8536341160 | F711: =SUM(F709:F710) -> 9845748717 | G711: =SUM(G709:G710) -> 1903114095 | H711: =SUM(H709:H710) -> 36648466 | I711: =SUM(I709:I710) -> 118662
B712: Less Preschool/PreK | C712: 19028 | F712: =M683*C712 -> 2.3957238e+08 | G712: =N683*C712 -> 3.5192956e+08
B713: Less Charter Passthroughs | E713: ='Charter Work File'!E163 -> 73980322 | F713: ='Charter Work File'!K163 -> 85402905
B714: Less Adult | F714: =Adult!L15 -> 220647 | G714: =Adult!L21 -> 4717402
B715: Total NYC After Deductions | C715: =956263+21007 -> 977270 | E715: =E711-(E712+E713+E714) -> 8.4623608e+09 | F715: =F711-(F712+F713+F714) -> 9.5205528e+09 | G715: =G711-(G712+G713+G714) -> 1.5464671e+09 | H715: =H711-(H712+H713+H714) -> 36648466 | I715: =I711-(I712+I713+I714) -> 118662 | J715: =SUM(E715:I715) -> 1.9566148e+10 | L715: Note: NYC enrollment gathered from state report cards with exception of District 75 -
E716: =E715/C715 -> 8659.1841 | F716: =F715/C715 -> 9741.9882 | G716: =G715/C715 -> 1582.4359 | H716: =H715/C715 -> 37.500861 | I716: =I715/C715 -> 0.12142192 | J716: =SUM(E716:I716) -> 20021.23 | L716: the special education district, at which enrollments were not reported for 06-07.
E717: =E715/J715 -> 0.4325001 | F717: =F715/J715 -> 0.48658289 | G717: =G715/J715 -> 0.079037895 | H717: =H715/J715 -> 0.0018730547 | I717: =I715/J715 -> 6.0646582e-06

Sheet Dist Food Sv & Capital
A1: District Food Service and Capital Expenditures from the ST-3 Database Download for FY06
S2: 010100 | T2: 140600 | U2: 300000
F3: Downloads | S3: Albany | T3: Buffalo | U3: New York City
B4: ST-3 Revenue Type | C4: DP Code | D4: ST3- Row | E4: Funding Type | F4: ST3-010100-051301 | G4: ST3-051901-120501 | H4: ST3-120701-150901 | I4: ST3-151001-230301 | J4: ST3-230901-280214 | K4: ST3-280215-411603 | L4: ST3-411701-460102 | M4: ST3-460500-512101 | N4: ST3-512201-580211 | O4: ST3-580212-600801 | P4: ST3-600903-660301 | R4: Total
A5: Reimbursement of Medicare Part D Expends | B5: Food Service | C5: 58 | D5: 6 | E5: Federal | F5: 7851 | G5: 8515 | H5: 51310 | I5: 30117 | J5: 5788 | K5: 230945 | L5: 31256 | M5: 63297 | N5: 40565 | O5: 107872 | P5: 6831 | Q5: 26419 | R5: =SUM(F5:Q5) -> 610766
A6: Federal Reimbursement | B6: Food Service | C6: 58 | D6: 11 | E6: Federal | F6: 1624879 | G6: 1534558 | H6: 3351610 | I6: 1360418 | J6: 4260180 | K6: 22021197 | L6: 3259191 | M6: 2209894 | N6: 3718058 | O6: 3349830 | P6: 1382418 | Q6: 1479437 | R6: =SUM(F6:Q6) -> 49551670 | S6: 2449784 | T6: 14761848 | U6: 297023056
A7: Federal Reimbursement Surplus Food Only | B7: Food Service | C7: 58 | D7: 12 | E7: Federal | F7: 270794 | G7: 53619 | H7: 1243078 | I7: 206192 | J7: 376057 | K7: 16616413 | L7: 823220 | M7: 188135 | N7: 72916 | O7: 193806 | P7: 132571 | Q7: 388573 | R7: =SUM(F7:Q7) -> 20565374 | S7: 87071 | T7: 1431864 | U7: 20000000
A8: Federal Sources | B8: Capital | C8: 65 | D8: 6 | E8: Federal | G8: 0 | H8: 0 | I8: 0 | J8: 0 | K8: 0 | L8: 2977873 | M8: 321377 | N8: 0 | O8: 0 | P8: 0 | Q8: 0 | R8: =SUM(F8:Q8) -> 3299250
Q9: Federal | R9: =SUM(R5:R8) -> 74027060 | S9: =SUM(S5:S8) -> 2536855 | T9: =SUM(T5:T8) -> 16193712 | U9: =SUM(U5:U8) -> 317023056
A10: NYC Non-state Capital (manually added item) | B10: Capital | C10: 65 | E10: Indeterminate | K10: =U10 -> 118662 | R10: =SUM(F10:Q10) -> 118662 | U10: 118662
Q11: Indeterminate | R11: =SUM(R10) -> 118662 | S11: =SUM(S10) -> 0 | T11: =SUM(T10) -> 0 | U11: =SUM(U10) -> 118662
A12: Misc. Revenues from Local Sources | B12: Food Service | C12: 58 | D12: 9 | E12: Local | F12: 1913977 | G12: 1579159 | H12: 3925443 | I12: 1244935 | J12: 3781782 | K12: 13816143 | L12: 2668838 | M12: 2230694 | N12: 2447345 | O12: 1764073 | P12: 1883868 | Q12: 1664549 | R12: =SUM(F12:Q12) -> 38920806 | S12: 32588 | T12: 53800
A13: Proceeds Term Bonds | B13: Capital | C13: 65 | D13: 9 | E13: Local | G13: 0 | H13: 0 | I13: 1375000 | J13: 361000 | K13: 0 | L13: 326885 | M13: 0 | N13: 0 | O13: 0 | P13: 6840000 | Q13: 21937517 | R13: =SUM(F13:Q13) -> 30840402
A14: Proceeds Serial Bonds | B14: Capital | C14: 65 | D14: 10 | E14: Local | F14: 169950060 | G14: 31760672 | H14: 70690677 | I14: 73999689 | J14: 106817015 | K14: 106723390 | L14: 186188648 | M14: 94962404 | N14: 152243415 | O14: 220203000 | P14: 79072844 | Q14: 143742767 | R14: =SUM(F14:Q14) -> 1436354581 | S14: 26810000 | T14: 5889000
A15: Proceeds Statutory Installment Bond | B15: Capital | C15: 65 | D15: 11 | E15: Local | F15: 2424522 | G15: 710089 | H15: 718400 | I15: 1489469 | J15: 1007011 | K15: 78475 | L15: 165512 | M15: 1062188 | N15: 442170 | O15: 607412 | P15: 378879 | Q15: 0 | R15: =SUM(F15:Q15) -> 9084127
A16: Proceeds Bond Anticipation Notes | B16: Capital | C16: 65 | D16: 12 | E16: Local | F16: 0 | G16: 275000 | H16: 0 | I16: 91000 | J16: 156784 | K16: 0 | L16: 0 | M16: 10681937 | N16: 0 | O16: 10000000 | P16: 0 | Q16: 0 | R16: =SUM(F16:Q16) -> 21204721
A17: Proceeds Bond Anticipation Notes Redeemed from Appropriations | B17: Capital | C17: 65 | D17: 13 | E17: Local | F17: 7883483 | G17: 2972787 | H17: 8407413 | I17: 2137693 | J17: 1880502 | K17: 451808 | L17: 6445337 | M17: 1723301 | N17: 2905740 | O17: 2133137 | P17: 4434700 | Q17: 486000 | R17: =SUM(F17:Q17) -> 41861901 | S17: 3593000
A18: Proceeds Capital Notes | B18: Capital | C18: 65 | D18: 14 | E18: Local | F18: 0 | G18: 0 | H18: 248581 | I18: 0 | J18: 0 | K18: 0 | L18: 0 | M18: 0 | N18: 0 | O18: 0 | P18: 0 | Q18: 0 | R18: =SUM(F18:Q18) -> 248581
A19: Proceeds Installment Purchase Debt | B19: Capital | C19: 65 | D19: 15 | E19: Local | F19: 1080428 | G19: 541987 | H19: 1481063 | I19: 1865049 | J19: 4407993 | K19: 3680822 | L19: 93452 | M19: 244274 | N19: 3148017 | O19: 597661 | P19: 2158100 | Q19: 2895969 | R19: =SUM(F19:Q19) -> 22194815
A20: Proceeds Other Debt | B20: Capital | C20: 65 | D20: 16 | E20: Local | F20: 176637 | G20: 163327 | H20: 1102070 | I20: 0 | J20: 7636474 | K20: 11164170 | L20: 0 | M20: 3275700 | N20: 40000 | O20: 0 | P20: 1800000 | Q20: 0 | R20: =SUM(F20:Q20) -> 25358378
Q21: Local | R21: =SUM(R12:R20) -> 1626068312 | S21: =SUM(S12:S20) -> 30435588 | T21: =SUM(T12:T20) -> 5942800 | U21: =SUM(U12:U20) -> 0
A22: Sale of Reimbursable Meals | B22: Food Service | C22: 58 | D22: 1 | E22: Other | F22: 9413561 | G22: 7869291 | H22: 15463834 | I22: 7026926 | J22: 21432054 | K22: 37688920 | L22: 19362125 | M22: 13954179 | N22: 16466886 | O22: 18879857 | P22: 9244636 | Q22: 15544080 | R22: =SUM(F22:Q22) -> 192346349 | S22: 353364 | U22: 20045996
A23: Other Cafeteria Sales | B23: Food Service | C23: 58 | D23: 2 | E23: Other | F23: 6358652 | G23: 4400212 | H23: 11448378 | I23: 3191630 | J23: 11158292 | K23: 14325237 | L23: 10033334 | M23: 7175727 | N23: 15253568 | O23: 13913900 | P23: 7449917 | Q23: 7825411 | R23: =SUM(F23:Q23) -> 112534258 | S23: 64956 | T23: 2143926
A24: Interest and Earnings | B24: Food Service | C24: 58 | D24: 3 | E24: Other | F24: 75179 | G24: 169843 | H24: 283392 | I24: 70376 | J24: 343485 | K24: 454010 | L24: 221041 | M24: 232652 | N24: 281449 | O24: 513381 | P24: 157465 | Q24: 316623 | R24: =SUM(F24:Q24) -> 3118896
A25: Sale of Equipment | B25: Food Service | C25: 58 | D25: 4 | E25: Other | F25: 0 | G25: 1200 | H25: 0 | I25: 650 | J25: 0 | K25: 100 | L25: 3617 | M25: 930 | N25: 0 | O25: 0 | P25: 0 | Q25: 0 | R25: =SUM(F25:Q25) -> 6497
A26: Compensation for Loss | B26: Food Service | C26: 58 | D26: 5 | E26: Other | F26: 8069 | G26: 0 | H26: 46495 | I26: 0 | J26: 388 | K26: 56699 | L26: 6894 | M26: 37610 | N26: 5589 | O26: 5327 | P26: 5955 | Q26: 0 | R26: =SUM(F26:Q26) -> 173026
A27: Refunds of Prior Years Expendiutres | B27: Food Service | C27: 58 | D27: 7 | E27: Other | F27: 1000 | G27: 19575 | H27: 0 | I27: 2017 | J27: 2876 | K27: 33 | L27: 36441 | M27: 3880 | N27: 50 | O27: 0 | P27: 0 | Q27: 3940 | R27: =SUM(F27:Q27) -> 69812 | S27: 76
A28: Gifts and Donation | B28: Food Service | C28: 58 | D28: 8 | E28: Other | F28: 684439 | G28: 917648 | H28: 559503 | I28: 415184 | J28: 615100 | K28: 508429 | L28: 584318 | M28: 588777 | N28: 730391 | O28: 753017 | P28: 608132 | Q28: 1135180 | R28: =SUM(F28:Q28) -> 8100118
A29: Summer Food Servic Program for Children | B29: Food Service | C29: 58 | D29: 13 | E29: Other | F29: 1165354 | G29: 326088 | H29: 1257360 | I29: 1518924 | J29: 676541 | K29: 50014454 | L29: 681782 | M29: 128446 | N29: 764693 | O29: 919393 | P29: 770111 | Q29: 1234308 | R29: =SUM(F29:Q29) -> 59457454 | T29: 1186797 | U29: 16602470
A30: Insurance Recoveries | B30: Capital | C30: 65 | D30: 1 | E30: Other | F30: 38035 | G30: 541066 | H30: 0 | I30: 432000 | J30: 58841 | K30: 44581 | L30: 66002 | M30: 175518 | N30: 210883 | O30: 503624 | P30: 0 | Q30: 2949671 | R30: =SUM(F30:Q30) -> 5020221
A31: Gifts and Donations | B31: Capital | C31: 65 | D31: 2 | E31: Other | G31: 67775 | H31: 3500 | I31: 75000 | J31: 2704301 | K31: 50000 | L31: 15000 | M31: 33420 | N31: 32000 | O31: 30000 | P31: 60000 | Q31: 1734565 | R31: =SUM(F31:Q31) -> 4805561
A32: Other Misc | B32: Capital | C32: 65 | D32: 3 | E32: Other | G32: 202562 | H32: 601548 | I32: 390049 | J32: 404674 | K32: 187762 | L32: 121389 | M32: 1228467 | N32: 311589 | O32: 284781 | P32: 226327 | Q32: 624073 | R32: =SUM(F32:Q32) -> 4583221 | S32: 8405 | T32: 185386
A33: Interest and Earnings | B33: Capital | C33: 65 | D33: 17 | E33: Other | F33: 455876 | G33: 198345 | H33: 1406294 | I33: 21104 | J33: 166337 | K33: 667978 | L33: 340968 | M33: 38248 | N33: 296244 | O33: 122524 | P33: 53602 | Q33: 644419 | R33: =SUM(F33:Q33) -> 4411939 | T33: 593625
Q34: Other | R34: =SUM(R22:R33) -> 394627352 | S34: =SUM(S22:S33) -> 426801 | T34: =SUM(T22:T33) -> 4109734 | U34: =SUM(U22:U33) -> 36648466
A35: State Reimbursement | B35: Food Service | C35: 58 | D35: 10 | E35: State | F35: 14998463 | G35: 12905697 | H35: 27667088 | I35: 10384614 | J35: 26939095 | K35: 310258890 | L35: 26679720 | M35: 13774467 | N35: 16368567 | O35: 17548412 | P35: 10101616 | Q35: 13613365 | R35: =SUM(F35:Q35) -> 501239994 | S35: 121389 | T35: 756078 | U35: 12459586
A36: State Sources | B36: Capital | C36: 65 | D36: 4 | E36: State | G36: 0 | H36: 0 | I36: 0 | J36: 0 | K36: 826987804 | L36: 0 | M36: 0 | N36: 0 | O36: 0 | P36: 0 | Q36: 1331482 | R36: =SUM(F36:Q36) -> 828319286
A37: State Sources | B37: Capital | C37: 65 | D37: 5 | E37: State | G37: 182377 | H37: 630930 | I37: 196246 | J37: 33471062 | K37: 1166855 | L37: 352500 | M37: 121435 | N37: 14654 | O37: 387066 | P37: 426585 | Q37: 327026 | R37: =SUM(F37:Q37) -> 37276736
A38: NYC State Capital (EXCEL) (Manually added item) | B38: Capital | C38: 65 | E38: State | K38: =U38 -> 1760270000 | R38: =SUM(F38:Q38) -> 1760270000 | U38: 1760270000
Q39: State | R39: =SUM(R35:R38) -> 3127106016 | S39: =SUM(S35:S38) -> 121389 | T39: =SUM(T35:T38) -> 756078 | U39: =SUM(U35:U38) -> 1772729586
Q42: total | R42: =R9+R11+R21+R34+R39 -> 5221947402
A43: numbers derived from download of ST-3 financial data for all school districts in NYS for 2006-07. Revenue calculations may be incomplete as the New York State Education Department does not require school districts to report data for the Food Service and
A44: the Capital Funds. Capital for New York City School District is not reported through the ST-3 process. Capital numbers included here derived from the audit of the New York City School Construction Authority for FY08 and FY07 http://source.nycsca.org/pdf/PAAA-Report-08.pdf

Sheet Adult
A1: Archive Data | F1: Working Data | K1: City Working Data
A2: BOCES Cayuga-Onondaga | B2: 50000 | C2: Exclude | D2: State | F2: Yonkers City SD | G2: 23449 | H2: Include | I2: State | K2: Albany City SD | L2: 14140 | M2: Include | N2: State
A3: Long Beach City SD | B3: 75000 | C3: Include | D3: State | F3: White Plains City SD | G3: 27821 | H3: Include | I3: State | L3: =SUM(L2) -> 14140
A4: BOCES Schuy-Steub-CHEM | B4: 74941 | C4: Exclude | D4: State | F4: Schenectady City SD | G4: 14604 | H4: Include | I4: State
A5: Buffalo City SD | B5: 149642 | C5: Include | D5: State | F5: Rochester City SD | G5: 143114 | H5: Include | I5: State | K5: Buffalo City SD | L5: 149642 | M5: Include | N5: State
A6: BOCES Franklin-Essex-Ham | B6: 44588 | C6: Exclude | D6: State | F6: Rochester City SD | G6: 36058 | H6: Include | I6: State | K6: Buffalo City SD | L6: 66248 | M6: Include | N6: State
A7: BOCES Oswego | B7: 16548 | C7: Exclude | D7: State | F7: Oneonta City SD | G7: 2326 | H7: Include | I7: State | L7: =SUM(L5:L6) -> 215890
A8: BOCES Madison Oneida | B8: 50594 | C8: Exclude | D8: State | F8: Olean City SD | G8: 3684 | H8: Include | I8: State
F9: Niagara Falls City SD | G9: 96608 | H9: Include | I9: State | K9: Buffalo City SD | L9: 19921 | M9: Include | N9: Federal
A10: BOCES Eastern Suffold | B10: 27717 | C10: Exclude | D10: State | F10: Niagara Falls City SD | G10: 13719 | H10: Include | I10: State | K10: Buffalo City SD | L10: 51379 | M10: Include | N10: Federal
A11: BOCES Sullivan | B11: 7227 | C11: Exclude | D11: State | F11: Mt. Vernon City SD | G11: 10228 | H11: Include | I11: State | K11: Buffalo City SD | L11: 231688 | M11: Include | N11: Federal
A12: BOCES Tomkings | B12: 4885 | C12: Exclude | D12: State | F12: Long Beach City SD | G12: 75000 | H12: Include | I12: State | L12: =SUM(L9:L11) -> 302988
A13: Kingston City SD | B13: 2288 | C13: Include | D13: State | F13: Long Beach City SD | G13: 22061 | H13: Include | I13: State
A14: BOCES Ulster | B14: 11204 | C14: Exclude | D14: State | F14: Kingston City SD | G14: 2288 | H14: Include | I14: State | K14: NYC Alternative & Adult Education | L14: 220647 | M14: Include | N14: State
A15: Yonkers City SD | B15: 23449 | C15: Include | D15: State | F15: Greece CSD | G15: 9969 | H15: Include | I15: State | L15: =SUM(L14) -> 220647
A16: BOCES Westchester | B16: 8870 | C16: Exclude | D16: State | F16: Great Neck UFSD | G16: 12279 | H16: Include | I16: State
A17: BOCES Putnam-Northern | B17: 11372 | C17: Exclude | D17: State | F17: East Bloomfield CSD | G17: 817 | H17: Include | I17: State | K17: NYC Alternative & Adult Education | L17: 1005631 | M17: Include | N17: Federal
A18: White Plains City SD | B18: 27821 | C18: Include | D18: State | F18: Cheektowaga-Maryvale UFSD | G18: 6741 | H18: Include | I18: State | K18: NYC Alternative & Adult Education | L18: 261268 | M18: Include | N18: Federal
A19: Mt. Vernon City SD | B19: 10228 | C19: Include | D19: State | F19: Buffalo City SD | G19: 149642 | H19: Include | I19: State | K19: NYC Alternative & Adult Education | L19: 3085323 | M19: Include | N19: Federal
A20: BOCES Clinton-Essex | B20: 50506 | C20: Exclude | D20: State | F20: Buffalo City SD | G20: 66248 | H20: Include | I20: State | K20: NYC Geog Dist #10 ISC | L20: 365180 | M20: Include | N20: Federal
A21: BOCES Nassau | B21: 134166 | C21: Exclude | D21: State | F21: Albany City SD | G21: 14140 | H21: Include | I21: State | L21: =SUM(L17:L20) -> 4717402
A22: Niagara Falls City SD | B22: 96608 | C22: Include | D22: State | F22: Afton CSD | G22: 2566 | H22: Include | I22: State
A23: BOCES St. Lawrence-Lewis | B23: 45422 | C23: Exclude | D23: State | F23: NYC Alternative & Adult Education | G23: 220647 | H23: Include | I23: State
A24: Rochester City SD | B24: 143114 | C24: Include | D24: State | G24: =SUM(G2:G23) -> 954009
A26: East Bloomfield CSD | B26: 817 | C26: Include | D26: State | F26: Alden CSD | G26: 38950 | H26: Include | I26: Federal
A27: BOCES Wayne-Finger Lakes | B27: 19202 | C27: Exclude | D27: State | F27: Cheektowaga-Maryvale UFSD | G27: 20361 | H27: Include | I27: Federal
A28: BOCES Nassau | B28: 18023 | C28: Exclude | D28: State | F28: Rochester City SD | G28: 55912 | H28: Include | I28: Federal
A29: Long Beach City SD | B29: 22061 | C29: Include | D29: State | F29: Westbury UFSD | G29: 60833 | H29: Include | I29: Federal
A30: Great Neck UFSD | B30: 12279 | C30: Include | D30: State | F30: NYC Geog Dist #10 ISC | G30: 365180 | H30: Include | I30: Federal
A31: BOCES Orange-Ulster | B31: 25393 | C31: Exclude | D31: State | F31: Syracuse City SD | G31: 33527 | H31: Include | I31: Federal
A32: BOCES Oswego | B32: 11490 | C32: Exclude | D32: State | F32: Yonkers City SD | G32: 206767 | H32: Include | I32: Federal
A33: Greece CSD | B33: 9969 | C33: Include | D33: State | F33: Buffalo City SD | G33: 19921 | H33: Include | I33: Federal
A34: Rochester City SD | B34: 36058 | C34: Include | D34: State | F34: Rochester City SD | G34: 38624 | H34: Include | I34: Federal
A35: BOCES Monroe | B35: 6046 | C35: Exclude | D35: State | F35: Afton CSD | G35: 30800 | H35: Include | I35: Federal
A36: BOCES Rockland | B36: 16110 | C36: Exclude | D36: State | F36: Buffalo City SD | G36: 51379 | H36: Include | I36: Federal
A37: BOCES Onondaga | B37: 35767 | C37: Exclude | D37: State | F37: White Plains City SD | G37: 354168 | H37: Include | I37: Federal
... A40: BOCES Wester Suffolk | B40: 31445 | C40: Exclude | D40: State | F40: Smithtown CSD | G40: 97829 | H40: Include | I40: Federal
F41: Yonkers City SD | G41: 321075 | H41: Include | I41: Federal
A42: BOCES Franklin-Essex | B42: 5897 | C42: Exclude | D42: State | F42: Fulton City SD | G42: 50000 | H42: Include | I42: Federal
A43: BOCES Qestar III | B43: 6740 | C43: Exclude | D43: State | F43: Wesbury UFSD | G43: 173622 | H43: Include | I43: Federal
A44: BOCES Schuy-Steub-Chem | B44: 15982 | C44: Exclude | D44: State | F44: Long Beach City SD | G44: 232003 | H44: Include | I44: Federal
A45: BOCES Erie 2 | B45: 14133 | C45: Exclude | D45: State | F45: Hempstead UFSD | G45: 59523 | H45: Include | I45: Federal
A46: BOES Dutchess | B46: 18801 | C46: Exclude | D46: State | F46: Port Washington UFSD | G46: 119415 | H46: Include | I46: Federal
A47: BOCES Hamilton | B47: 6330 | C47: Exclude | D47: State | F47: Rochester City SD | G47: 213170 | H47: Include | I47: Federal
A48: Capital Region BOCES | B48: 3315 | C48: Exclude | D48: State | F48: Afton CSD | G48: 103431 | H48: Include | I48: Federal
A49: BOCES Genesee Valley | B49: 12119 | C49: Exclude | D49: State | F49: Oneonta City SD | G49: 10000 | H49: Include | I49: Federal
A50: BOCES Monroe 2 | B50: 4562 | C50: Exclude | D50: State | F50: Schenectady City SD | G50: 231839 | H50: Include | I50: Federal
A51: BOCES Orleans | B51: 1443 | C51: Exclude | D51: State | F51: Binghampton City SD | G51: 60828 | H51: Include | I51: Federal
A52: BOCES Madison | B52: 21585 | C52: Exclude | D52: State | F52: Cheektowaga-Maryvale UFSD | G52: 89864 | H52: Include | I52: Federal
A53: BOCES Herk | B53: 5348 | C53: Exclude | D53: State | F53: Kenmore-Tonawanda UFSD | G53: 63306 | H53: Include | I53: Federal
... A55: Niagara Falls City SD | B55: 13719 | C55: Include | D55: State | F55: Olean City SD | G55: 45339 | H55: Include | I55: Federal
A56: Alternative & Adult Ed | B56: 220647 | D56: State | F56: NYC Alternative & Adult Education | G56: 1005631 | H56: Include | I56: Federal
F57: NYC Alternative & Adult Education | G57: 261268 | H57: Include | I57: Federal
A58: Schenectady City SD | B58: 14604 | C58: Include | D58: State | F58: NYC Alternative & Adult Education | G58: 3085323 | H58: Include | I58: Federal
A59: Capital Region BOCES | B59: 4308 | C59: Exclude | D59: State | G59: =SUM(G26:G58) -> 8004104
A60: Albany City SD | B60: 14140 | C60: Include | D60: State
A61: BOCES Questar | B61: 3389 | C61: Exclude | D61: State | F61: BOCES Cayuga-Onondaga | G61: 50000 | H61: Exclude | I61: State
A62: Cheektowaga-Maryvale UFSD | B62: 6741 | C62: Include | D62: State | F62: BOCES Schuy-Steub-CHEM | G62: 74941 | H62: Exclude | I62: State
A63: Buffalo City SD | B63: 66248 | C63: Include | D63: State | F63: BOCES Franklin-Essex-Ham | G63: 44588 | H63: Exclude | I63: State
A64: BOCES Erie | B64: 6260 | C64: Exclude | D64: State | F64: BOCES Oswego | G64: 16548 | H64: Exclude | I64: State
A65: Olean City SD | B65: 3684 | C65: Include | D65: State | F65: BOCES Madison Oneida | G65: 50594 | H65: Exclude | I65: State
A66: BOCES Cattar-Alegany | B66: 8973 | C66: Exclude | D66: State | F66: BOCES Eastern Suffold | G66: 27717 | H66: Exclude | I66: State
A67: BOCES Onondaga | B67: 5944 | C67: Exclude | D67: State | F67: BOCES Sullivan | G67: 7227 | H67: Exclude | I67: State
A68: BOCES Cayuga-Onondaga | B68: 6154 | C68: Exclude | D68: State | F68: BOCES Tomkings | G68: 4885 | H68: Exclude | I68: State
A69: Afton CSD | B69: 2566 | C69: Include | D69: State | F69: BOCES Ulster | G69: 11204 | H69: Exclude | I69: State
A70: BOCES Delaw | B70: 5672 | C70: Exclude | D70: State | F70: BOCES Westchester | G70: 8870 | H70: Exclude | I70: State
A71: Oneonta City SD | B71: 2326 | C71: Include | D71: State | F71: BOCES Putnam-Northern | G71: 11372 | H71: Exclude | I71: State
A72: BOCES Clinton-Essex | B72: 8129 | C72: Exclude | D72: State | F72: BOCES Clinton-Essex | G72: 50506 | H72: Exclude | I72: State
F73: BOCES Nassau | G73: 134166 | H73: Exclude | I73: State
A74: Catholic Chartities | B74: 119016 | C74: Exclude | D74: Federal | F74: BOCES St. Lawrence-Lewis | G74: 45422 | H74: Exclude | I74: State
A75: BOCES Hamilton | B75: 11234 | C75: Exclude | D75: Federal | F75: BOCES Wayne-Finger Lakes | G75: 19202 | H75: Exclude | I75: State
F76: BOCES Nassau | G76: 18023 | H76: Exclude | I76: State
A77: BOCES Dutchess | B77: 149882 | C77: Exclude | D77: Federal | F77: BOCES Orange-Ulster | G77: 25393 | H77: Exclude | I77: State
A78: Alden CSD | B78: 38950 | C78: Include | D78: Federal | F78: BOCES Oswego | G78: 11490 | H78: Exclude | I78: State
A79: Cheektowaga-Maryvale UFSD | B79: 20361 | C79: Include | D79: Federal | F79: BOCES Monroe | G79: 6046 | H79: Exclude | I79: State
A80: BOCES Erie 2 | B80: 58021 | C80: Exclude | D80: Federal | F80: BOCES Rockland | G80: 16110 | H80: Exclude | I80: State
A81: BOCES Madison | B81: 143853 | C81: Exclude | D81: Federal | F81: BOCES Onondaga | G81: 35767 | H81: Exclude | I81: State
A82: Rochester City SD | B82: 55912 | C82: Include | D82: Federal | F82: BOCES St. Lawrence | G82: 12129 | H82: Exclude | I82: State
A83: BOCES Monroe 1 | B83: 119024 | C83: Exclude | D83: Federal | F83: BOCES Washing-Sara | G83: 14503 | H83: Exclude | I83: State
A84: CUNY LaGuardia community | B84: 536039 | C84: Exclude | D84: Federal | F84: BOCES Wester Suffolk | G84: 31445 | H84: Exclude | I84: State
A85: BOCES Onondaga | B85: 96714 | C85: Exclude | D85: Federal | F85: BOCES Franklin-Essex | G85: 5897 | H85: Exclude | I85: State
A86: BOCES Onondaga | B86: 46752 | C86: Exclude | D86: Federal | F86: BOCES Qestar III | G86: 6740 | H86: Exclude | I86: State
A87: BOCES St. Lawrence | B87: 70033 | C87: Exclude | D87: Federal | F87: BOCES Schuy-Steub-Chem | G87: 15982 | H87: Exclude | I87: State
A88: BOCES Schuy-Steub | B88: 75000 | C88: Exclude | D88: Federal | F88: BOCES Erie 2 | G88: 14133 | H88: Exclude | I88: State
A89: BOCES Sullivan | B89: 32968 | C89: Exclude | D89: Federal | F89: BOES Dutchess | G89: 18801 | H89: Exclude | I89: State
A90: Alternative & Adult Education | B90: 1005631 | D90: Federal | F90: BOCES Hamilton | G90: 6330 | H90: Exclude | I90: State
A91: BOCES Wayne-Finger Lakes | B91: 176174 | C91: Exclude | D91: Federal | F91: Capital Region BOCES | G91: 3315 | H91: Exclude | I91: State
F92: BOCES Genesee Valley | G92: 12119 | H92: Exclude | I92: State
A93: College of Mt. St. Vincent | B93: 63890 | C93: Exclude | D93: State | F93: BOCES Monroe 2 | G93: 4562 | H93: Exclude | I93: State
A94: Northern Manhattan Improvdment | B94: 88340 | C94: Exclude | D94: State | F94: BOCES Orleans | G94: 1443 | H94: Exclude | I94: State
A95: Brooklyn Public Library | B95: 69836 | C95: Exclude | D95: State | F95: BOCES Madison | G95: 21585 | H95: Exclude | I95: State
A96: Learning Disabilities Assn | B96: 93038 | C96: Exclude | D96: State | F96: BOCES Herk | G96: 5348 | H96: Exclude | I96: State
A97: Union Settlement Assn | B97: 100000 | C97: Exclude | D97: State | F97: BOCES Orleans | G97: 8931 | H97: Exclude | I97: State
A98: Inwood Community Services | B98: 57198 | C98: Exclude | D98: State | F98: Capital Region BOCES | G98: 4308 | H98: Exclude | I98: State
A99: Haitian Americans United | B99: 140717 | C99: Exclude | D99: State | F99: BOCES Questar | G99: 3389 | H99: Exclude | I99: State
A100: Opportunities for a Better | B100: 89101 | C100: Exclude | D100: State | F100: BOCES Erie | G100: 6260 | H100: Exclude | I100: State
A101: Jewish Comm Center | B101: 42097 | C101: Exclude | D101: State | F101: BOCES Cattar-Alegany | G101: 8973 | H101: Exclude | I101: State
A102: Friends of Island Academy | B102: 52279 | C102: Exclude | D102: State | F102: BOCES Onondaga | G102: 5944 | H102: Exclude | I102: State
A103: Learning Disabilities Assn | B103: 12977 | C103: Exclude | D103: State | F103: BOCES Cayuga-Onondaga | G103: 6154 | H103: Exclude | I103: State
A104: Queens Borough Public Library | B104: 118262 | C104: Exclude | D104: State | F104: BOCES Delaw | G104: 5672 | H104: Exclude | I104: State
...

Sheet Sheet1
