Workbook

Sheet Instructions
A1: PLACER COUNTY TRANSIENT OCCUPANCY TAX
A2: REPORTING INSTRUCTIONS FOR PROPERTY MANAGEMENT COMPANIES
A4: GENERAL INFORMATION:
A5: ***This form is to report changes to previously reported Transient Occupancy Tax. ***
A6: The reporting spreadsheet may be filled out electronically using Microsoft Excel or you may print out the form and complete it manually. To access spreadsheet click on the BLUE "TOT Report Page 1" below.
A8: Property Management Companies must complete their business information at the top of the form. The Authorization section must be completed and signed.
A10: The dates for the reporting period must be listed. If amending more than one period, a separate worksheet must be used for each period.
A11: All columns, with the exception of the penalty and interest, must be completed for each certificate. The penalty and interest is to be completed for late filings.
A12: If completing this spreadsheet electronically, the taxable receipts, amount of tax due and total amount due will automatically calculate based on the amounts entered in the other columns. If completing the spreadsheet manually, please enter these calculations.
A13: Remittance address: Placer County Revenue Services, 10810 Justice Center Dr. Ste. 100, Roseville, CA 95678
A16: SPREADSHEET INSTRUCTIONS:
A17: CERT # : | B17: Enter the certificate number assigned to each parcel number.
A18: ACCOUNT # : | B18: Enter the Revenue Services Account Number. This will be listed on the spreadsheet that was sent with the certificates.
A19: GROSS RENTAL INCOME: | B19: Enter the AMENDED amount (what should have been reported) of rental income on the top row. Enter the PREVIOUSLY REPORTED amount of rental income on the second row.
A20: EXEMPT AMOUNT: | B20: Enter the AMENDED amount of any exemption on the first row. Enter the PREVIOUSLY REPORTED amount on the second row.
A21: TAXABLE RECEIPTS: | B21: Enter the amount of taxable income - gross rental income less the exempt amount. AMENDED on the top row and PREVIOUS REPORTING on the second row. **If working in Excel, this column is formulated and will automatically calculate the taxable receipts based on the gross rental income and exempt amounts entered.
A22: TAX RATE: | B22: Enter the tax rate for the rental property - either 8 or 10.
A23: AMOUNT OF TAX DUE: | B23: Enter the amount of taxable receipts multiplied by the tax rate. AMENDED on the top row and PREVIOUS REPORTING on the second row. **If using this spreadsheet in Excel, it will calculate automatically based on the amounts entered in the corresponding columns.
A24: DIFFERENCE | B24: Enter the amount owed, or overpaid for the account listed. If working in Excel, the figures will be calculated.
A25: PLACER COUNTY TRANSIENT OCCUPANCY TAX IS DUE IMMEDIATELY FOLLOWING THE CLOSE OF THE REPORTING PERIOD. PENALTY AND INTEREST ARE DUE FOR DELINQUENT FILINGS. THE DELINQUENCY DATE IS THE LAST DAY OF THE MONTH FOLLOWING THE CLOSE OF THE REPORTING PERIOD.
A26: (Sec.4.16.090 of the Transient Occupancy Tax Code)
A27: PENALTY: | B27: If paid within 30 days after the delinquent date add 10% of the tax due amount. If paid more than 30 days after the delinquent date add 20% of the tax due amount.
A28: INTEREST: | B28: In addition to above penalty, add 1.5% per month, or fraction thereof, of the tax due amount.
A30: TOTAL AMOUNT DUE: | B30: Enter the total of the tax due plus any penalty and interest. AMENDED on the top row and PREVIOUS REPORTING on the second row. **If using this spreadsheet in Excel, it will calculate automatically based on the amounts entered.
A31: DAYS AVAILABLE: | B31: Enter the number of rental units/days available in the reporting period. AMENDED on the top row and PREVIOUS REPORTING on the second row. This number is derived by multiplying the number of units available for rent times the number of days in the reporting period. (i.e. 10 units x 92 days = 920 unit/days available.)
A32: DAYS OCCUPIED: | B32: Enter the number of unit/days occupied in the reporting period. AMENDED on the top row and PREVIOUS REPORTING on the second row. This number requires an auditable record of the number of units actually rented each day during the reporting period.
B33: EXAMPLE: Rental property has 10 units available to rent.
B34: Day 1 - 5 units occupied.
B35: Day 2 - 10 units were occupied.
B36: Day 3 - 7 units were occupied.
B37: Total of unit/days occupied = 22
B38: Continue this method through the end of the reporting period. The unit/days occupied will then be the arithmetical total of the number of units occupied each day.
B39: NOTE: When any unit is occupied more than 1 time each day, then the actual number of times occupied is to be recorded and counted as a separate occupancy.
A42: ADDITIONAL INFORMATION:
A43: CHANGE OF ADDRESS OR OWNERSHIP: | B43: Must be reported immediately to Revenue Services.
A44: IF RENTAL PROPERTY IS DISCONTINUED: | B44: The holder of the certificate must remit the final return and payment immediately to Revenue Services. The certificate must be returned for cancellation with a request to close the certificate. A request form is available on our web site at www.placer.ca.gov Transient Occupancy Tax.
A45: IF RENTAL PROPERTY IS ADDED: | B45: An application for a Transient Occupancy Tax Certificate must be submitted.

Sheet TOT Report Page 1
B1: ***AMENDED*** ***AMENDED*** ***AMENDED***
B2: County of Placer
B3: Transient Occupancy Tax
B4: PROPERTY MANAGEMENT SPREADSHEET FOR AMENDING PREVIOUS REPORTING
B5: Property Management Information: | I5: Authorization
B6: Company Name | I6: By signing this form under the penalty of perjury, I certify that I am authorized to complete this information. This information reported is accurate based on the Transient Occupancy Tax collected by the Property Management Company named on the certificates listed below.
B7: Address
B8: City, State, Zip
B9: Phone | I9: Signature: | K9: Date __________
B10: Fax | I10: Print Name:
B11: Contact | I11: Title:
M12: Amount
E13: **AMENDED** | L13: Page 1 | M13: =L43 -> 0
B14: Reporting Period: | F14: to | L14: Page 2 | M14: ='Page 2'!L50 -> 0
E15: mm-dd-yy | G15: mm-dd-yy | L15: Page 3 | M15: ='Page 3'!L50 -> 0
B16: REASON FOR AMENDMENT: (Please provide supporting documentation.) | L16: Page 4 | M16: ='Page 4'!L50 -> 0
L17: Page 5 | M17: ='Page 5'!L50 -> 0
J18: Total Due | M18: =SUM(M13:M17) -> 0
B22: If amended processing results in a credit balance, a refund will be processed.
B23: Remit check payable to Placer County Revenue Services and send with this report to:
B24: Placer County Administrative Services Department - Revenue Services Division, 10810 Justice Center Drive Ste. 100, Roseville, CA 95678
B25: CERT # | C25: ACCOUNT# | D25: REPORTINGS | E25: GROSS RENTAL INCOME | F25: EXEMPT AMOUNT | G25: TAXABLE RECEIPTS | H25: TAX RATE (%) | I25: AMOUNT OF TAX DUE | J25: PENALTY | K25: INTEREST | L25: TOTAL AMOUNT DUE | M25: DAYS AVAILABLE | N25: DAYS OCCUPIED
A26: 1 | D26: AMENDED | G26: =E26-F26 -> 0 | H26: 0.1 | I26: =G26*H26 -> 0 | L26: =I26+J26+K26 -> 0
A27: 2 | D27: PREVIOUS | G27: =E27-F27 -> 0 | H27: 0.1 | I27: =G27*H27 -> 0 | L27: =I27+J27+K27 -> 0
A28: 3 | D28: DIFFERENCE | E28: =E26-E27 -> 0 | F28: =F26-F27 -> 0 | G28: =E28-F28 -> 0 | H28: 0.1 | I28: =G28*H28 -> 0 | J28: =J26-J27 -> 0 | K28: =K26-K27 -> 0 | L28: =I28+J28+K28 -> 0 | M28: =M26-M27 -> 0 | N28: =N26-N27 -> 0
A30: 4 | D30: AMENDED | G30: =E30-F30 -> 0 | H30: 0.1 | I30: =G30*H30 -> 0 | L30: =I30+J30+K30 -> 0
A31: 5 | D31: PREVIOUS | G31: =E31-F31 -> 0 | H31: 0.1 | I31: =G31*H31 -> 0 | L31: =I31+J31+K31 -> 0
A32: 6 | D32: DIFFERENCE | E32: =E30-E31 -> 0 | F32: =F30-F31 -> 0 | G32: =E32-F32 -> 0 | H32: 0.1 | I32: =G32*H32 -> 0 | J32: =J30-J31 -> 0 | K32: =K30-K31 -> 0 | L32: =I32+J32+K32 -> 0 | M32: =M30-M31 -> 0 | N32: =N30-N31 -> 0
A34: 7 | D34: AMENDED | G34: =E34-F34 -> 0 | H34: 0.1 | I34: =G34*H34 -> 0 | L34: =I34+J34+K34 -> 0
A35: 8 | D35: PREVIOUS | G35: =E35-F35 -> 0 | H35: 0.1 | I35: =G35*H35 -> 0 | L35: =I35+J35+K35 -> 0
A36: 9 | D36: DIFFERENCE | E36: =E34-E35 -> 0 | F36: =F34-F35 -> 0 | G36: =E36-F36 -> 0 | H36: 0.1 | I36: =G36*H36 -> 0 | J36: =J34-J35 -> 0 | K36: =K34-K35 -> 0 | L36: =I36+J36+K36 -> 0 | M36: =M34-M35 -> 0 | N36: =N34-N35 -> 0
A38: 10 | D38: AMENDED | G38: =E38-F38 -> 0 | H38: 0.1 | I38: =G38*H38 -> 0 | L38: =I38+J38+K38 -> 0
A39: 11 | D39: PREVIOUS | G39: =E39-F39 -> 0 | H39: 0.1 | I39: =G39*H39 -> 0 | L39: =I39+J39+K39 -> 0
A40: 12 | D40: DIFFERENCE | E40: =E38-E39 -> 0 | F40: =F38-F39 -> 0 | G40: =E40-F40 -> 0 | H40: 0.1 | I40: =G40*H40 -> 0 | J40: =J38-J39 -> 0 | K40: =K38-K39 -> 0 | L40: =I40+J40+K40 -> 0 | M40: =M38-M39 -> 0 | N40: =N38-N39 -> 0
C43: AMENDED TOTALS page 1 | E43: =E28+E32+E36+E40 -> 0 | F43: =F28+F32+F36+F40 -> 0 | G43: =G28+G32+G36+G40 -> 0 | I43: =I28+I32+I36+I40 -> 0 | J43: =J28+J32+J36+J40 -> 0 | K43: =K28+K32+K36+K40 -> 0 | L43: =L28+L32+L36+L40 -> 0 | M43: =M28+M32+M36+M40 -> 0 | N43: =N28+N32+N36+N40 -> 0

Sheet Page 2
B1: CERT # | C1: ACCOUNT# | D1: REPORTINGS | E1: GROSS RENTAL INCOME | F1: EXEMPT AMOUNT | G1: TAXABLE RECEIPTS | H1: TAX RATE (%) | I1: AMOUNT OF TAX DUE | J1: PENALTY | K1: INTEREST | L1: TOTAL AMOUNT DUE | M1: DAYS AVAILABLE | N1: DAYS OCCUPIED
A2: 1 | D2: AMENDED | G2: =E2-F2 -> 0 | H2: 0.1 | I2: =G2*H2 -> 0 | L2: =I2+J2+K2 -> 0
A3: 2 | D3: PREVIOUS | G3: =E3-F3 -> 0 | H3: 0.1 | I3: =G3*H3 -> 0 | L3: =I3+J3+K3 -> 0
A4: 3 | D4: DIFFERENCE | E4: =E2-E3 -> 0 | F4: =F2-F3 -> 0 | G4: =E4-F4 -> 0 | H4: 0.1 | I4: =G4*H4 -> 0 | J4: =J2-J3 -> 0 | K4: =K2-K3 -> 0 | L4: =I4+J4+K4 -> 0 | M4: =M2-M3 -> 0 | N4: =N2-N3 -> 0
A6: 4 | D6: AMENDED | G6: =E6-F6 -> 0 | H6: 0.1 | I6: =G6*H6 -> 0 | L6: =I6+J6+K6 -> 0
A7: 5 | D7: PREVIOUS | G7: =E7-F7 -> 0 | H7: 0.1 | I7: =G7*H7 -> 0 | L7: =I7+J7+K7 -> 0
A8: 6 | D8: DIFFERENCE | E8: =E6-E7 -> 0 | F8: =F6-F7 -> 0 | G8: =E8-F8 -> 0 | H8: 0.1 | I8: =G8*H8 -> 0 | J8: =J6-J7 -> 0 | K8: =K6-K7 -> 0 | L8: =I8+J8+K8 -> 0 | M8: =M6-M7 -> 0 | N8: =N6-N7 -> 0
A10: 7 | D10: AMENDED | G10: =E10-F10 -> 0 | H10: 0.1 | I10: =G10*H10 -> 0 | L10: =I10+J10+K10 -> 0
A11: 8 | D11: PREVIOUS | G11: =E11-F11 -> 0 | H11: 0.1 | I11: =G11*H11 -> 0 | L11: =I11+J11+K11 -> 0
A12: 9 | D12: DIFFERENCE | E12: =E10-E11 -> 0 | F12: =F10-F11 -> 0 | G12: =E12-F12 -> 0 | H12: 0.1 | I12: =G12*H12 -> 0 | J12: =J10-J11 -> 0 | K12: =K10-K11 -> 0 | L12: =I12+J12+K12 -> 0 | M12: =M10-M11 -> 0 | N12: =N10-N11 -> 0
A14: 10 | D14: AMENDED | G14: =E14-F14 -> 0 | H14: 0.1 | I14: =G14*H14 -> 0 | L14: =I14+J14+K14 -> 0
A15: 11 | D15: PREVIOUS | G15: =E15-F15 -> 0 | H15: 0.1 | I15: =G15*H15 -> 0 | L15: =I15+J15+K15 -> 0
A16: 12 | D16: DIFFERENCE | E16: =E14-E15 -> 0 | F16: =F14-F15 -> 0 | G16: =E16-F16 -> 0 | H16: 0.1 | I16: =G16*H16 -> 0 | J16: =J14-J15 -> 0 | K16: =K14-K15 -> 0 | L16: =I16+J16+K16 -> 0 | M16: =M14-M15 -> 0 | N16: =N14-N15 -> 0
A18: 13 | D18: AMENDED | G18: =E18-F18 -> 0 | H18: 0.1 | I18: =G18*H18 -> 0 | L18: =I18+J18+K18 -> 0
A19: 14 | D19: PREVIOUS | G19: =E19-F19 -> 0 | H19: 0.1 | I19: =G19*H19 -> 0 | L19: =I19+J19+K19 -> 0
A20: 15 | D20: DIFFERENCE | E20: =E18-E19 -> 0 | F20: =F18-F19 -> 0 | G20: =E20-F20 -> 0 | H20: 0.1 | I20: =G20*H20 -> 0 | J20: =J18-J19 -> 0 | K20: =K18-K19 -> 0 | L20: =I20+J20+K20 -> 0 | M20: =M18-M19 -> 0 | N20: =N18-N19 -> 0
A22: 16 | D22: AMENDED | G22: =E22-F22 -> 0 | H22: 0.1 | I22: =G22*H22 -> 0 | L22: =I22+J22+K22 -> 0
A23: 17 | D23: PREVIOUS | G23: =E23-F23 -> 0 | H23: 0.1 | I23: =G23*H23 -> 0 | L23: =I23+J23+K23 -> 0
A24: 18 | D24: DIFFERENCE | E24: =E22-E23 -> 0 | F24: =F22-F23 -> 0 | G24: =E24-F24 -> 0 | H24: 0.1 | I24: =G24*H24 -> 0 | J24: =J22-J23 -> 0 | K24: =K22-K23 -> 0 | L24: =I24+J24+K24 -> 0 | M24: =M22-M23 -> 0 | N24: =N22-N23 -> 0
A26: 19 | D26: AMENDED | G26: =E26-F26 -> 0 | H26: 0.1 | I26: =G26*H26 -> 0 | L26: =I26+J26+K26 -> 0
A27: 20 | D27: PREVIOUS | G27: =E27-F27 -> 0 | H27: 0.1 | I27: =G27*H27 -> 0 | L27: =I27+J27+K27 -> 0
A28: 21 | D28: DIFFERENCE | E28: =E26-E27 -> 0 | F28: =F26-F27 -> 0 | G28: =E28-F28 -> 0 | H28: 0.1 | I28: =G28*H28 -> 0 | J28: =J26-J27 -> 0 | K28: =K26-K27 -> 0 | L28: =I28+J28+K28 -> 0 | M28: =M26-M27 -> 0 | N28: =N26-N27 -> 0
A30: 22 | D30: AMENDED | G30: =E30-F30 -> 0 | H30: 0.1 | I30: =G30*H30 -> 0 | L30: =I30+J30+K30 -> 0
A31: 23 | D31: PREVIOUS | G31: =E31-F31 -> 0 | H31: 0.1 | I31: =G31*H31 -> 0 | L31: =I31+J31+K31 -> 0
A32: 24 | D32: DIFFERENCE | E32: =E30-E31 -> 0 | F32: =F30-F31 -> 0 | G32: =E32-F32 -> 0 | H32: 0.1 | I32: =G32*H32 -> 0 | J32: =J30-J31 -> 0 | K32: =K30-K31 -> 0 | L32: =I32+J32+K32 -> 0 | M32: =M30-M31 -> 0 | N32: =N30-N31 -> 0
A34: 25 | D34: AMENDED | G34: =E34-F34 -> 0 | H34: 0.1 | I34: =G34*H34 -> 0 | L34: =I34+J34+K34 -> 0
A35: 26 | D35: PREVIOUS | G35: =E35-F35 -> 0 | H35: 0.1 | I35: =G35*H35 -> 0 | L35: =I35+J35+K35 -> 0
A36: 27 | D36: DIFFERENCE | E36: =E34-E35 -> 0 | F36: =F34-F35 -> 0 | G36: =E36-F36 -> 0 | H36: 0.1 | I36: =G36*H36 -> 0 | J36: =J34-J35 -> 0 | K36: =K34-K35 -> 0 | L36: =I36+J36+K36 -> 0 | M36: =M34-M35 -> 0 | N36: =N34-N35 -> 0
A38: 28 | D38: AMENDED | G38: =E38-F38 -> 0 | H38: 0.1 | I38: =G38*H38 -> 0 | L38: =I38+J38+K38 -> 0
A39: 29 | D39: PREVIOUS | G39: =E39-F39 -> 0 | H39: 0.1 | I39: =G39*H39 -> 0 | L39: =I39+J39+K39 -> 0
A40: 30 | D40: DIFFERENCE | E40: =E38-E39 -> 0 | F40: =F38-F39 -> 0 | G40: =E40-F40 -> 0 | H40: 0.1 | I40: =G40*H40 -> 0 | J40: =J38-J39 -> 0 | K40: =K38-K39 -> 0 | L40: =I40+J40+K40 -> 0 | M40: =M38-M39 -> 0 | N40: =N38-N39 -> 0
A42: 31 | D42: AMENDED | G42: =E42-F42 -> 0 | H42: 0.1 | I42: =G42*H42 -> 0 | L42: =I42+J42+K42 -> 0
A43: 32 | D43: PREVIOUS | G43: =E43-F43 -> 0 | H43: 0.1 | I43: =G43*H43 -> 0 | L43: =I43+J43+K43 -> 0
A44: 33 | D44: DIFFERENCE | E44: =E42-E43 -> 0 | F44: =F42-F43 -> 0 | G44: =E44-F44 -> 0 | H44: 0.1 | I44: =G44*H44 -> 0 | J44: =J42-J43 -> 0 | K44: =K42-K43 -> 0 | L44: =I44+J44+K44 -> 0 | M44: =M42-M43 -> 0 | N44: =N42-N43 -> 0
A46: 34 | D46: AMENDED | G46: =E46-F46 -> 0 | H46: 0.1 | I46: =G46*H46 -> 0 | L46: =I46+J46+K46 -> 0
A47: 35 | D47: PREVIOUS | G47: =E47-F47 -> 0 | H47: 0.1 | I47: =G47*H47 -> 0 | L47: =I47+J47+K47 -> 0
A48: 36 | D48: DIFFERENCE | E48: =E46-E47 -> 0 | F48: =F46-F47 -> 0 | G48: =E48-F48 -> 0 | H48: 0.1 | I48: =G48*H48 -> 0 | J48: =J46-J47 -> 0 | K48: =K46-K47 -> 0 | L48: =I48+J48+K48 -> 0 | M48: =M46-M47 -> 0 | N48: =N46-N47 -> 0
B50: AMENDED TOTALS page 2 | E50: =E4+E8+E12+E16+E20+E24+E28+E32+E36+E40+E44+E48 -> 0 | F50: =F4+F8+F12+F16+F20+F24+F28+F32+F36+F40+F44+F48 -> 0 | G50: =G4+G8+G12+G16+G20+G24+G28+G32+G36+G40+G44+G48 -> 0 | I50: =I4+I8+I12+I16+I20+I24+I28+I32+I36+I40+I44+I48 -> 0 | J50: =J4+J8+J12+J16+J20+J24+J28+J32+J36+J40+J44+J48 -> 0 | K50: =K4+K8+K12+K16+K20+K24+K28+K32+K36+K40+K44+K48 -> 0 | L50: =L4+L8+L12+L16+L20+L24+L28+L32+L36+L40+L44+L48 -> 0 | M50: =M4+M8+M12+M16+M20+M24+M28+M32+M36+M40+M44+M48 -> 0 | N50: =N4+N8+N12+N16+N20+N24+N28+N32+N36+N40+N44+N48 -> 0
B51: Report period | D51: ='TOT Report Page 1'!E14 -> 0 | E51: to | F51: ='TOT Report Page 1'!G14 -> 0 | H51: ***AMENDED*** | J51: ='TOT Report Page 1'!C6 -> 0

Sheet Page 3
B1: CERT # | C1: ACCOUNT# | D1: REPORTINGS | E1: GROSS RENTAL INCOME | F1: EXEMPT AMOUNT | G1: TAXABLE RECEIPTS | H1: TAX RATE (%) | I1: AMOUNT OF TAX DUE | J1: PENALTY | K1: INTEREST | L1: TOTAL AMOUNT DUE | M1: DAYS AVAILABLE | N1: DAYS OCCUPIED
A2: 1 | D2: AMENDED | G2: =E2-F2 -> 0 | H2: 0.1 | I2: =G2*H2 -> 0 | L2: =I2+J2+K2 -> 0
A3: 2 | D3: PREVIOUS | G3: =E3-F3 -> 0 | H3: 0.1 | I3: =G3*H3 -> 0 | L3: =I3+J3+K3 -> 0
A4: 3 | D4: DIFFERENCE | E4: =E2-E3 -> 0 | F4: =F2-F3 -> 0 | G4: =E4-F4 -> 0 | H4: 0.1 | I4: =G4*H4 -> 0 | J4: =J2-J3 -> 0 | K4: =K2-K3 -> 0 | L4: =I4+J4+K4 -> 0 | M4: =M2-M3 -> 0 | N4: =N2-N3 -> 0
A6: 4 | D6: AMENDED | G6: =E6-F6 -> 0 | H6: 0.1 | I6: =G6*H6 -> 0 | L6: =I6+J6+K6 -> 0
A7: 5 | D7: PREVIOUS | G7: =E7-F7 -> 0 | H7: 0.1 | I7: =G7*H7 -> 0 | L7: =I7+J7+K7 -> 0
A8: 6 | D8: DIFFERENCE | E8: =E6-E7 -> 0 | F8: =F6-F7 -> 0 | G8: =E8-F8 -> 0 | H8: 0.1 | I8: =G8*H8 -> 0 | J8: =J6-J7 -> 0 | K8: =K6-K7 -> 0 | L8: =I8+J8+K8 -> 0 | M8: =M6-M7 -> 0 | N8: =N6-N7 -> 0
A10: 7 | D10: AMENDED | G10: =E10-F10 -> 0 | H10: 0.1 | I10: =G10*H10 -> 0 | L10: =I10+J10+K10 -> 0
A11: 8 | D11: PREVIOUS | G11: =E11-F11 -> 0 | H11: 0.1 | I11: =G11*H11 -> 0 | L11: =I11+J11+K11 -> 0
A12: 9 | D12: DIFFERENCE | E12: =E10-E11 -> 0 | F12: =F10-F11 -> 0 | G12: =E12-F12 -> 0 | H12: 0.1 | I12: =G12*H12 -> 0 | J12: =J10-J11 -> 0 | K12: =K10-K11 -> 0 | L12: =I12+J12+K12 -> 0 | M12: =M10-M11 -> 0 | N12: =N10-N11 -> 0
A14: 10 | D14: AMENDED | G14: =E14-F14 -> 0 | H14: 0.1 | I14: =G14*H14 -> 0 | L14: =I14+J14+K14 -> 0
A15: 11 | D15: PREVIOUS | G15: =E15-F15 -> 0 | H15: 0.1 | I15: =G15*H15 -> 0 | L15: =I15+J15+K15 -> 0
A16: 12 | D16: DIFFERENCE | E16: =E14-E15 -> 0 | F16: =F14-F15 -> 0 | G16: =E16-F16 -> 0 | H16: 0.1 | I16: =G16*H16 -> 0 | J16: =J14-J15 -> 0 | K16: =K14-K15 -> 0 | L16: =I16+J16+K16 -> 0 | M16: =M14-M15 -> 0 | N16: =N14-N15 -> 0
A18: 13 | D18: AMENDED | G18: =E18-F18 -> 0 | H18: 0.1 | I18: =G18*H18 -> 0 | L18: =I18+J18+K18 -> 0
A19: 14 | D19: PREVIOUS | G19: =E19-F19 -> 0 | H19: 0.1 | I19: =G19*H19 -> 0 | L19: =I19+J19+K19 -> 0
A20: 15 | D20: DIFFERENCE | E20: =E18-E19 -> 0 | F20: =F18-F19 -> 0 | G20: =E20-F20 -> 0 | H20: 0.1 | I20: =G20*H20 -> 0 | J20: =J18-J19 -> 0 | K20: =K18-K19 -> 0 | L20: =I20+J20+K20 -> 0 | M20: =M18-M19 -> 0 | N20: =N18-N19 -> 0
A22: 16 | D22: AMENDED | G22: =E22-F22 -> 0 | H22: 0.1 | I22: =G22*H22 -> 0 | L22: =I22+J22+K22 -> 0
A23: 17 | D23: PREVIOUS | G23: =E23-F23 -> 0 | H23: 0.1 | I23: =G23*H23 -> 0 | L23: =I23+J23+K23 -> 0
A24: 18 | D24: DIFFERENCE | E24: =E22-E23 -> 0 | F24: =F22-F23 -> 0 | G24: =E24-F24 -> 0 | H24: 0.1 | I24: =G24*H24 -> 0 | J24: =J22-J23 -> 0 | K24: =K22-K23 -> 0 | L24: =I24+J24+K24 -> 0 | M24: =M22-M23 -> 0 | N24: =N22-N23 -> 0
A26: 19 | D26: AMENDED | G26: =E26-F26 -> 0 | H26: 0.1 | I26: =G26*H26 -> 0 | L26: =I26+J26+K26 -> 0
A27: 20 | D27: PREVIOUS | G27: =E27-F27 -> 0 | H27: 0.1 | I27: =G27*H27 -> 0 | L27: =I27+J27+K27 -> 0
A28: 21 | D28: DIFFERENCE | E28: =E26-E27 -> 0 | F28: =F26-F27 -> 0 | G28: =E28-F28 -> 0 | H28: 0.1 | I28: =G28*H28 -> 0 | J28: =J26-J27 -> 0 | K28: =K26-K27 -> 0 | L28: =I28+J28+K28 -> 0 | M28: =M26-M27 -> 0 | N28: =N26-N27 -> 0
A30: 22 | D30: AMENDED | G30: =E30-F30 -> 0 | H30: 0.1 | I30: =G30*H30 -> 0 | L30: =I30+J30+K30 -> 0
A31: 23 | D31: PREVIOUS | G31: =E31-F31 -> 0 | H31: 0.1 | I31: =G31*H31 -> 0 | L31: =I31+J31+K31 -> 0
A32: 24 | D32: DIFFERENCE | E32: =E30-E31 -> 0 | F32: =F30-F31 -> 0 | G32: =E32-F32 -> 0 | H32: 0.1 | I32: =G32*H32 -> 0 | J32: =J30-J31 -> 0 | K32: =K30-K31 -> 0 | L32: =I32+J32+K32 -> 0 | M32: =M30-M31 -> 0 | N32: =N30-N31 -> 0
A34: 25 | D34: AMENDED | G34: =E34-F34 -> 0 | H34: 0.1 | I34: =G34*H34 -> 0 | L34: =I34+J34+K34 -> 0
A35: 26 | D35: PREVIOUS | G35: =E35-F35 -> 0 | H35: 0.1 | I35: =G35*H35 -> 0 | L35: =I35+J35+K35 -> 0
A36: 27 | D36: DIFFERENCE | E36: =E34-E35 -> 0 | F36: =F34-F35 -> 0 | G36: =E36-F36 -> 0 | H36: 0.1 | I36: =G36*H36 -> 0 | J36: =J34-J35 -> 0 | K36: =K34-K35 -> 0 | L36: =I36+J36+K36 -> 0 | M36: =M34-M35 -> 0 | N36: =N34-N35 -> 0
A38: 28 | D38: AMENDED | G38: =E38-F38 -> 0 | H38: 0.1 | I38: =G38*H38 -> 0 | L38: =I38+J38+K38 -> 0
A39: 29 | D39: PREVIOUS | G39: =E39-F39 -> 0 | H39: 0.1 | I39: =G39*H39 -> 0 | L39: =I39+J39+K39 -> 0
A40: 30 | D40: DIFFERENCE | E40: =E38-E39 -> 0 | F40: =F38-F39 -> 0 | G40: =E40-F40 -> 0 | H40: 0.1 | I40: =G40*H40 -> 0 | J40: =J38-J39 -> 0 | K40: =K38-K39 -> 0 | L40: =I40+J40+K40 -> 0 | M40: =M38-M39 -> 0 | N40: =N38-N39 -> 0
A42: 31 | D42: AMENDED | G42: =E42-F42 -> 0 | H42: 0.1 | I42: =G42*H42 -> 0 | L42: =I42+J42+K42 -> 0
A43: 32 | D43: PREVIOUS | G43: =E43-F43 -> 0 | H43: 0.1 | I43: =G43*H43 -> 0 | L43: =I43+J43+K43 -> 0
A44: 33 | D44: DIFFERENCE | E44: =E42-E43 -> 0 | F44: =F42-F43 -> 0 | G44: =E44-F44 -> 0 | H44: 0.1 | I44: =G44*H44 -> 0 | J44: =J42-J43 -> 0 | K44: =K42-K43 -> 0 | L44: =I44+J44+K44 -> 0 | M44: =M42-M43 -> 0 | N44: =N42-N43 -> 0
A46: 34 | D46: AMENDED | G46: =E46-F46 -> 0 | H46: 0.1 | I46: =G46*H46 -> 0 | L46: =I46+J46+K46 -> 0
A47: 35 | D47: PREVIOUS | G47: =E47-F47 -> 0 | H47: 0.1 | I47: =G47*H47 -> 0 | L47: =I47+J47+K47 -> 0
A48: 36 | D48: DIFFERENCE | E48: =E46-E47 -> 0 | F48: =F46-F47 -> 0 | G48: =E48-F48 -> 0 | H48: 0.1 | I48: =G48*H48 -> 0 | J48: =J46-J47 -> 0 | K48: =K46-K47 -> 0 | L48: =I48+J48+K48 -> 0 | M48: =M46-M47 -> 0 | N48: =N46-N47 -> 0
B50: AMENDED TOTALS page 3 | E50: =E4+E8+E12+E16+E20+E24+E28+E32+E36+E40+E44+E48 -> 0 | F50: =F4+F8+F12+F16+F20+F24+F28+F32+F36+F40+F44+F48 -> 0 | G50: =G4+G8+G12+G16+G20+G24+G28+G32+G36+G40+G44+G48 -> 0 | I50: =I4+I8+I12+I16+I20+I24+I28+I32+I36+I40+I44+I48 -> 0 | J50: =J4+J8+J12+J16+J20+J24+J28+J32+J36+J40+J44+J48 -> 0 | K50: =K4+K8+K12+K16+K20+K24+K28+K32+K36+K40+K44+K48 -> 0 | L50: =L4+L8+L12+L16+L20+L24+L28+L32+L36+L40+L44+L48 -> 0 | M50: =M4+M8+M12+M16+M20+M24+M28+M32+M36+M40+M44+M48 -> 0 | N50: =N4+N8+N12+N16+N20+N24+N28+N32+N36+N40+N44+N48 -> 0
B51: Report period | D51: ='TOT Report Page 1'!E14 -> 0 | E51: to | F51: ='TOT Report Page 1'!G14 -> 0 | H51: ***AMENDED*** | J51: ='TOT Report Page 1'!C6 -> 0

Sheet Page 4
B1: CERT # | C1: ACCOUNT# | D1: REPORTINGS | E1: GROSS RENTAL INCOME | F1: EXEMPT AMOUNT | G1: TAXABLE RECEIPTS | H1: TAX RATE (%) | I1: AMOUNT OF TAX DUE | J1: PENALTY | K1: INTEREST | L1: TOTAL AMOUNT DUE | M1: DAYS AVAILABLE | N1: DAYS OCCUPIED
A2: 1 | D2: AMENDED | G2: =E2-F2 -> 0 | H2: 0.1 | I2: =G2*H2 -> 0 | L2: =I2+J2+K2 -> 0
A3: 2 | D3: PREVIOUS | G3: =E3-F3 -> 0 | H3: 0.1 | I3: =G3*H3 -> 0 | L3: =I3+J3+K3 -> 0
A4: 3 | D4: DIFFERENCE | E4: =E2-E3 -> 0 | F4: =F2-F3 -> 0 | G4: =E4-F4 -> 0 | H4: 0.1 | I4: =G4*H4 -> 0 | J4: =J2-J3 -> 0 | K4: =K2-K3 -> 0 | L4: =I4+J4+K4 -> 0 | M4: =M2-M3 -> 0 | N4: =N2-N3 -> 0
A6: 4 | D6: AMENDED | G6: =E6-F6 -> 0 | H6: 0.1 | I6: =G6*H6 -> 0 | L6: =I6+J6+K6 -> 0
A7: 5 | D7: PREVIOUS | G7: =E7-F7 -> 0 | H7: 0.1 | I7: =G7*H7 -> 0 | L7: =I7+J7+K7 -> 0
A8: 6 | D8: DIFFERENCE | E8: =E6-E7 -> 0 | F8: =F6-F7 -> 0 | G8: =E8-F8 -> 0 | H8: 0.1 | I8: =G8*H8 -> 0 | J8: =J6-J7 -> 0 | K8: =K6-K7 -> 0 | L8: =I8+J8+K8 -> 0 | M8: =M6-M7 -> 0 | N8: =N6-N7 -> 0
A10: 7 | D10: AMENDED | G10: =E10-F10 -> 0 | H10: 0.1 | I10: =G10*H10 -> 0 | L10: =I10+J10+K10 -> 0
A11: 8 | D11: PREVIOUS | G11: =E11-F11 -> 0 | H11: 0.1 | I11: =G11*H11 -> 0 | L11: =I11+J11+K11 -> 0
A12: 9 | D12: DIFFERENCE | E12: =E10-E11 -> 0 | F12: =F10-F11 -> 0 | G12: =E12-F12 -> 0 | H12: 0.1 | I12: =G12*H12 -> 0 | J12: =J10-J11 -> 0 | K12: =K10-K11 -> 0 | L12: =I12+J12+K12 -> 0 | M12: =M10-M11 -> 0 | N12: =N10-N11 -> 0
A14: 10 | D14: AMENDED | G14: =E14-F14 -> 0 | H14: 0.1 | I14: =G14*H14 -> 0 | L14: =I14+J14+K14 -> 0
A15: 11 | D15: PREVIOUS | G15: =E15-F15 -> 0 | H15: 0.1 | I15: =G15*H15 -> 0 | L15: =I15+J15+K15 -> 0
A16: 12 | D16: DIFFERENCE | E16: =E14-E15 -> 0 | F16: =F14-F15 -> 0 | G16: =E16-F16 -> 0 | H16: 0.1 | I16: =G16*H16 -> 0 | J16: =J14-J15 -> 0 | K16: =K14-K15 -> 0 | L16: =I16+J16+K16 -> 0 | M16: =M14-M15 -> 0 | N16: =N14-N15 -> 0
A18: 13 | D18: AMENDED | G18: =E18-F18 -> 0 | H18: 0.1 | I18: =G18*H18 -> 0 | L18: =I18+J18+K18 -> 0
A19: 14 | D19: PREVIOUS | G19: =E19-F19 -> 0 | H19: 0.1 | I19: =G19*H19 -> 0 | L19: =I19+J19+K19 -> 0
A20: 15 | D20: DIFFERENCE | E20: =E18-E19 -> 0 | F20: =F18-F19 -> 0 | G20: =E20-F20 -> 0 | H20: 0.1 | I20: =G20*H20 -> 0 | J20: =J18-J19 -> 0 | K20: =K18-K19 -> 0 | L20: =I20+J20+K20 -> 0 | M20: =M18-M19 -> 0 | N20: =N18-N19 -> 0
A22: 16 | D22: AMENDED | G22: =E22-F22 -> 0 | H22: 0.1 | I22: =G22*H22 -> 0 | L22: =I22+J22+K22 -> 0
A23: 17 | D23: PREVIOUS | G23: =E23-F23 -> 0 | H23: 0.1 | I23: =G23*H23 -> 0 | L23: =I23+J23+K23 -> 0
A24: 18 | D24: DIFFERENCE | E24: =E22-E23 -> 0 | F24: =F22-F23 -> 0 | G24: =E24-F24 -> 0 | H24: 0.1 | I24: =G24*H24 -> 0 | J24: =J22-J23 -> 0 | K24: =K22-K23 -> 0 | L24: =I24+J24+K24 -> 0 | M24: =M22-M23 -> 0 | N24: =N22-N23 -> 0
A26: 19 | D26: AMENDED | G26: =E26-F26 -> 0 | H26: 0.1 | I26: =G26*H26 -> 0 | L26: =I26+J26+K26 -> 0
A27: 20 | D27: PREVIOUS | G27: =E27-F27 -> 0 | H27: 0.1 | I27: =G27*H27 -> 0 | L27: =I27+J27+K27 -> 0
A28: 21 | D28: DIFFERENCE | E28: =E26-E27 -> 0 | F28: =F26-F27 -> 0 | G28: =E28-F28 -> 0 | H28: 0.1 | I28: =G28*H28 -> 0 | J28: =J26-J27 -> 0 | K28: =K26-K27 -> 0 | L28: =I28+J28+K28 -> 0 | M28: =M26-M27 -> 0 | N28: =N26-N27 -> 0
A30: 22 | D30: AMENDED | G30: =E30-F30 -> 0 | H30: 0.1 | I30: =G30*H30 -> 0 | L30: =I30+J30+K30 -> 0
A31: 23 | D31: PREVIOUS | G31: =E31-F31 -> 0 | H31: 0.1 | I31: =G31*H31 -> 0 | L31: =I31+J31+K31 -> 0
A32: 24 | D32: DIFFERENCE | E32: =E30-E31 -> 0 | F32: =F30-F31 -> 0 | G32: =E32-F32 -> 0 | H32: 0.1 | I32: =G32*H32 -> 0 | J32: =J30-J31 -> 0 | K32: =K30-K31 -> 0 | L32: =I32+J32+K32 -> 0 | M32: =M30-M31 -> 0 | N32: =N30-N31 -> 0
A34: 25 | D34: AMENDED | G34: =E34-F34 -> 0 | H34: 0.1 | I34: =G34*H34 -> 0 | L34: =I34+J34+K34 -> 0
A35: 26 | D35: PREVIOUS | G35: =E35-F35 -> 0 | H35: 0.1 | I35: =G35*H35 -> 0 | L35: =I35+J35+K35 -> 0
A36: 27 | D36: DIFFERENCE | E36: =E34-E35 -> 0 | F36: =F34-F35 -> 0 | G36: =E36-F36 -> 0 | H36: 0.1 | I36: =G36*H36 -> 0 | J36: =J34-J35 -> 0 | K36: =K34-K35 -> 0 | L36: =I36+J36+K36 -> 0 | M36: =M34-M35 -> 0 | N36: =N34-N35 -> 0
A38: 28 | D38: AMENDED | G38: =E38-F38 -> 0 | H38: 0.1 | I38: =G38*H38 -> 0 | L38: =I38+J38+K38 -> 0
A39: 29 | D39: PREVIOUS | G39: =E39-F39 -> 0 | H39: 0.1 | I39: =G39*H39 -> 0 | L39: =I39+J39+K39 -> 0
A40: 30 | D40: DIFFERENCE | E40: =E38-E39 -> 0 | F40: =F38-F39 -> 0 | G40: =E40-F40 -> 0 | H40: 0.1 | I40: =G40*H40 -> 0 | J40: =J38-J39 -> 0 | K40: =K38-K39 -> 0 | L40: =I40+J40+K40 -> 0 | M40: =M38-M39 -> 0 | N40: =N38-N39 -> 0
A42: 31 | D42: AMENDED | G42: =E42-F42 -> 0 | H42: 0.1 | I42: =G42*H42 -> 0 | L42: =I42+J42+K42 -> 0
A43: 32 | D43: PREVIOUS | G43: =E43-F43 -> 0 | H43: 0.1 | I43: =G43*H43 -> 0 | L43: =I43+J43+K43 -> 0
A44: 33 | D44: DIFFERENCE | E44: =E42-E43 -> 0 | F44: =F42-F43 -> 0 | G44: =E44-F44 -> 0 | H44: 0.1 | I44: =G44*H44 -> 0 | J44: =J42-J43 -> 0 | K44: =K42-K43 -> 0 | L44: =I44+J44+K44 -> 0 | M44: =M42-M43 -> 0 | N44: =N42-N43 -> 0
A46: 34 | D46: AMENDED | G46: =E46-F46 -> 0 | H46: 0.1 | I46: =G46*H46 -> 0 | L46: =I46+J46+K46 -> 0
A47: 35 | D47: PREVIOUS | G47: =E47-F47 -> 0 | H47: 0.1 | I47: =G47*H47 -> 0 | L47: =I47+J47+K47 -> 0
A48: 36 | D48: DIFFERENCE | E48: =E46-E47 -> 0 | F48: =F46-F47 -> 0 | G48: =E48-F48 -> 0 | H48: 0.1 | I48: =G48*H48 -> 0 | J48: =J46-J47 -> 0 | K48: =K46-K47 -> 0 | L48: =I48+J48+K48 -> 0 | M48: =M46-M47 -> 0 | N48: =N46-N47 -> 0
B50: AMENDED TOTALS page 4 | E50: =E4+E8+E12+E16+E20+E24+E28+E32+E36+E40+E44+E48 -> 0 | F50: =F4+F8+F12+F16+F20+F24+F28+F32+F36+F40+F44+F48 -> 0 | G50: =G4+G8+G12+G16+G20+G24+G28+G32+G36+G40+G44+G48 -> 0 | I50: =I4+I8+I12+I16+I20+I24+I28+I32+I36+I40+I44+I48 -> 0 | J50: =J4+J8+J12+J16+J20+J24+J28+J32+J36+J40+J44+J48 -> 0 | K50: =K4+K8+K12+K16+K20+K24+K28+K32+K36+K40+K44+K48 -> 0 | L50: =L4+L8+L12+L16+L20+L24+L28+L32+L36+L40+L44+L48 -> 0 | M50: =M4+M8+M12+M16+M20+M24+M28+M32+M36+M40+M44+M48 -> 0 | N50: =N4+N8+N12+N16+N20+N24+N28+N32+N36+N40+N44+N48 -> 0
B51: Report period | D51: ='TOT Report Page 1'!E14 -> 0 | E51: to | F51: ='TOT Report Page 1'!G14 -> 0 | H51: ***AMENDED*** | J51: ='TOT Report Page 1'!C6 -> 0

Sheet Page 5
B1: CERT # | C1: ACCOUNT# | D1: REPORTINGS | E1: GROSS RENTAL INCOME | F1: EXEMPT AMOUNT | G1: TAXABLE RECEIPTS | H1: TAX RATE (%) | I1: AMOUNT OF TAX DUE | J1: PENALTY | K1: INTEREST | L1: TOTAL AMOUNT DUE | M1: DAYS AVAILABLE | N1: DAYS OCCUPIED
A2: 1 | D2: AMENDED | G2: =E2-F2 -> 0 | H2: 0.1 | I2: =G2*H2 -> 0 | L2: =I2+J2+K2 -> 0
A3: 2 | D3: PREVIOUS | G3: =E3-F3 -> 0 | H3: 0.1 | I3: =G3*H3 -> 0 | L3: =I3+J3+K3 -> 0
A4: 3 | D4: DIFFERENCE | E4: =E2-E3 -> 0 | F4: =F2-F3 -> 0 | G4: =E4-F4 -> 0 | H4: 0.1 | I4: =G4*H4 -> 0 | J4: =J2-J3 -> 0 | K4: =K2-K3 -> 0 | L4: =I4+J4+K4 -> 0 | M4: =M2-M3 -> 0 | N4: =N2-N3 -> 0
A6: 4 | D6: AMENDED | G6: =E6-F6 -> 0 | H6: 0.1 | I6: =G6*H6 -> 0 | L6: =I6+J6+K6 -> 0
A7: 5 | D7: PREVIOUS | G7: =E7-F7 -> 0 | H7: 0.1 | I7: =G7*H7 -> 0 | L7: =I7+J7+K7 -> 0
A8: 6 | D8: DIFFERENCE | E8: =E6-E7 -> 0 | F8: =F6-F7 -> 0 | G8: =E8-F8 -> 0 | H8: 0.1 | I8: =G8*H8 -> 0 | J8: =J6-J7 -> 0 | K8: =K6-K7 -> 0 | L8: =I8+J8+K8 -> 0 | M8: =M6-M7 -> 0 | N8: =N6-N7 -> 0
A10: 7 | D10: AMENDED | G10: =E10-F10 -> 0 | H10: 0.1 | I10: =G10*H10 -> 0 | L10: =I10+J10+K10 -> 0
A11: 8 | D11: PREVIOUS | G11: =E11-F11 -> 0 | H11: 0.1 | I11: =G11*H11 -> 0 | L11: =I11+J11+K11 -> 0
A12: 9 | D12: DIFFERENCE | E12: =E10-E11 -> 0 | F12: =F10-F11 -> 0 | G12: =E12-F12 -> 0 | H12: 0.1 | I12: =G12*H12 -> 0 | J12: =J10-J11 -> 0 | K12: =K10-K11 -> 0 | L12: =I12+J12+K12 -> 0 | M12: =M10-M11 -> 0 | N12: =N10-N11 -> 0
A14: 10 | D14: AMENDED | G14: =E14-F14 -> 0 | H14: 0.1 | I14: =G14*H14 -> 0 | L14: =I14+J14+K14 -> 0
A15: 11 | D15: PREVIOUS | G15: =E15-F15 -> 0 | H15: 0.1 | I15: =G15*H15 -> 0 | L15: =I15+J15+K15 -> 0
A16: 12 | D16: DIFFERENCE | E16: =E14-E15 -> 0 | F16: =F14-F15 -> 0 | G16: =E16-F16 -> 0 | H16: 0.1 | I16: =G16*H16 -> 0 | J16: =J14-J15 -> 0 | K16: =K14-K15 -> 0 | L16: =I16+J16+K16 -> 0 | M16: =M14-M15 -> 0 | N16: =N14-N15 -> 0
A18: 13 | D18: AMENDED | G18: =E18-F18 -> 0 | H18: 0.1 | I18: =G18*H18 -> 0 | L18: =I18+J18+K18 -> 0
A19: 14 | D19: PREVIOUS | G19: =E19-F19 -> 0 | H19: 0.1 | I19: =G19*H19 -> 0 | L19: =I19+J19+K19 -> 0
A20: 15 | D20: DIFFERENCE | E20: =E18-E19 -> 0 | F20: =F18-F19 -> 0 | G20: =E20-F20 -> 0 | H20: 0.1 | I20: =G20*H20 -> 0 | J20: =J18-J19 -> 0 | K20: =K18-K19 -> 0 | L20: =I20+J20+K20 -> 0 | M20: =M18-M19 -> 0 | N20: =N18-N19 -> 0
A22: 16 | D22: AMENDED | G22: =E22-F22 -> 0 | H22: 0.1 | I22: =G22*H22 -> 0 | L22: =I22+J22+K22 -> 0
A23: 17 | D23: PREVIOUS | G23: =E23-F23 -> 0 | H23: 0.1 | I23: =G23*H23 -> 0 | L23: =I23+J23+K23 -> 0
A24: 18 | D24: DIFFERENCE | E24: =E22-E23 -> 0 | F24: =F22-F23 -> 0 | G24: =E24-F24 -> 0 | H24: 0.1 | I24: =G24*H24 -> 0 | J24: =J22-J23 -> 0 | K24: =K22-K23 -> 0 | L24: =I24+J24+K24 -> 0 | M24: =M22-M23 -> 0 | N24: =N22-N23 -> 0
A26: 19 | D26: AMENDED | G26: =E26-F26 -> 0 | H26: 0.1 | I26: =G26*H26 -> 0 | L26: =I26+J26+K26 -> 0
A27: 20 | D27: PREVIOUS | G27: =E27-F27 -> 0 | H27: 0.1 | I27: =G27*H27 -> 0 | L27: =I27+J27+K27 -> 0
A28: 21 | D28: DIFFERENCE | E28: =E26-E27 -> 0 | F28: =F26-F27 -> 0 | G28: =E28-F28 -> 0 | H28: 0.1 | I28: =G28*H28 -> 0 | J28: =J26-J27 -> 0 | K28: =K26-K27 -> 0 | L28: =I28+J28+K28 -> 0 | M28: =M26-M27 -> 0 | N28: =N26-N27 -> 0
A30: 22 | D30: AMENDED | G30: =E30-F30 -> 0 | H30: 0.1 | I30: =G30*H30 -> 0 | L30: =I30+J30+K30 -> 0
A31: 23 | D31: PREVIOUS | G31: =E31-F31 -> 0 | H31: 0.1 | I31: =G31*H31 -> 0 | L31: =I31+J31+K31 -> 0
A32: 24 | D32: DIFFERENCE | E32: =E30-E31 -> 0 | F32: =F30-F31 -> 0 | G32: =E32-F32 -> 0 | H32: 0.1 | I32: =G32*H32 -> 0 | J32: =J30-J31 -> 0 | K32: =K30-K31 -> 0 | L32: =I32+J32+K32 -> 0 | M32: =M30-M31 -> 0 | N32: =N30-N31 -> 0
A34: 25 | D34: AMENDED | G34: =E34-F34 -> 0 | H34: 0.1 | I34: =G34*H34 -> 0 | L34: =I34+J34+K34 -> 0
A35: 26 | D35: PREVIOUS | G35: =E35-F35 -> 0 | H35: 0.1 | I35: =G35*H35 -> 0 | L35: =I35+J35+K35 -> 0
A36: 27 | D36: DIFFERENCE | E36: =E34-E35 -> 0 | F36: =F34-F35 -> 0 | G36: =E36-F36 -> 0 | H36: 0.1 | I36: =G36*H36 -> 0 | J36: =J34-J35 -> 0 | K36: =K34-K35 -> 0 | L36: =I36+J36+K36 -> 0 | M36: =M34-M35 -> 0 | N36: =N34-N35 -> 0
A38: 28 | D38: AMENDED | G38: =E38-F38 -> 0 | H38: 0.1 | I38: =G38*H38 -> 0 | L38: =I38+J38+K38 -> 0
A39: 29 | D39: PREVIOUS | G39: =E39-F39 -> 0 | H39: 0.1 | I39: =G39*H39 -> 0 | L39: =I39+J39+K39 -> 0
A40: 30 | D40: DIFFERENCE | E40: =E38-E39 -> 0 | F40: =F38-F39 -> 0 | G40: =E40-F40 -> 0 | H40: 0.1 | I40: =G40*H40 -> 0 | J40: =J38-J39 -> 0 | K40: =K38-K39 -> 0 | L40: =I40+J40+K40 -> 0 | M40: =M38-M39 -> 0 | N40: =N38-N39 -> 0
A42: 31 | D42: AMENDED | G42: =E42-F42 -> 0 | H42: 0.1 | I42: =G42*H42 -> 0 | L42: =I42+J42+K42 -> 0
A43: 32 | D43: PREVIOUS | G43: =E43-F43 -> 0 | H43: 0.1 | I43: =G43*H43 -> 0 | L43: =I43+J43+K43 -> 0
A44: 33 | D44: DIFFERENCE | E44: =E42-E43 -> 0 | F44: =F42-F43 -> 0 | G44: =E44-F44 -> 0 | H44: 0.1 | I44: =G44*H44 -> 0 | J44: =J42-J43 -> 0 | K44: =K42-K43 -> 0 | L44: =I44+J44+K44 -> 0 | M44: =M42-M43 -> 0 | N44: =N42-N43 -> 0
A46: 34 | D46: AMENDED | G46: =E46-F46 -> 0 | H46: 0.1 | I46: =G46*H46 -> 0 | L46: =I46+J46+K46 -> 0
A47: 35 | D47: PREVIOUS | G47: =E47-F47 -> 0 | H47: 0.1 | I47: =G47*H47 -> 0 | L47: =I47+J47+K47 -> 0
A48: 36 | D48: DIFFERENCE | E48: =E46-E47 -> 0 | F48: =F46-F47 -> 0 | G48: =E48-F48 -> 0 | H48: 0.1 | I48: =G48*H48 -> 0 | J48: =J46-J47 -> 0 | K48: =K46-K47 -> 0 | L48: =I48+J48+K48 -> 0 | M48: =M46-M47 -> 0 | N48: =N46-N47 -> 0
B50: AMENDED TOTALS page 5 | E50: =E4+E8+E12+E16+E20+E24+E28+E32+E36+E40+E44+E48 -> 0 | F50: =F4+F8+F12+F16+F20+F24+F28+F32+F36+F40+F44+F48 -> 0 | G50: =G4+G8+G12+G16+G20+G24+G28+G32+G36+G40+G44+G48 -> 0 | I50: =I4+I8+I12+I16+I20+I24+I28+I32+I36+I40+I44+I48 -> 0 | J50: =J4+J8+J12+J16+J20+J24+J28+J32+J36+J40+J44+J48 -> 0 | K50: =K4+K8+K12+K16+K20+K24+K28+K32+K36+K40+K44+K48 -> 0 | L50: =L4+L8+L12+L16+L20+L24+L28+L32+L36+L40+L44+L48 -> 0 | M50: =M4+M8+M12+M16+M20+M24+M28+M32+M36+M40+M44+M48 -> 0 | N50: =N4+N8+N12+N16+N20+N24+N28+N32+N36+N40+N44+N48 -> 0
B51: Report period | D51: ='TOT Report Page 1'!E14 -> 0 | E51: to | F51: ='TOT Report Page 1'!G14 -> 0 | H51: ***AMENDED*** | J51: ='TOT Report Page 1'!C6 -> 0

Sheet Sheet1
