Workbook

Sheet Part I Summary
A1: School Name:
A2: Part I Budget Information
A3: Read this before you begin this page: Complete all Sections of Part II, Detail of Budget Information, before returning to this page (to open, click on each worksheet tab at the bottom of this screen). The amounts you enter into Part II will automatically be inserted into this page. Where you see a $0 already inserted in the columns below, a formula has been inserted. Do not delete this formula. This is formatted to automatically draw amounts from corresponding sections within Part II of the application.
A4: Budget Summary
B5: Planning Period (through June 30, 2014) | C5: 1st Operational Year (July 1, 2014-June 30, 2015)
A6: Total Revenues | B6: =Revenue!B6 -> 0 | C6: =Revenue!C6 -> 0
A7: Total Budgeted Expenditures (items A through H) | B7: =SUM(B8:B15) -> 0 | C7: =SUM(C8:C15) -> 0
A8: A. Salaries (100) and Benefits (200) | B8: ='Salaries & Benefits (100-200)'!B6 -> 0 | C8: ='Salaries & Benefits (100-200)'!C6 -> 0
A9: B. Purchased Professional and Technical Services (300) | B9: ='Professional Services (300)'!B6 -> 0 | C9: ='Professional Services (300)'!C6 -> 0
A10: C. Purchased Property Services (400) | B10: ='Property Services (400)'!B6 -> 0 | C10: ='Property Services (400)'!C6 -> 0
A11: D. Other Purchased Services (500) | B11: ='Other (500)'!B6 -> 0 | C11: ='Other (500)'!C6 -> 0
A12: E. Travel (580) | B12: ='Travel (580)'!B6 -> 0 | C12: ='Travel (580)'!C6 -> 0
A13: F. Supplies and Materials (600) | B13: ='Supplies and Materials (600)'!B6 -> 0 | C13: ='Supplies and Materials (600)'!C6 -> 0
A14: G. Property (includes equipment and computer hardware) (700) | B14: ='Property (700)'!B6 -> 0 | C14: ='Property (700)'!C6 -> 0
A15: H. Debt Service and Miscellaneous (800) | B15: ='Misc (800)'!B6 -> 0 | C15: ='Misc (800)'!C6 -> 0
A16: Revenues - Budgeted Expenditures | B16: =B6-B7 -> 0 | C16: =C6-C7 -> 0
A17: Percent of Revenue Budgeted | B17: =B16/B6 -> #DIV/0! | C17: =C16/C6 -> #DIV/0!

Sheet Revenue
A1: ='Part I Summary'!A1 -> School Name:
A2: Part II Budget Detail
A3: List all expected sources of revenue and the expected amount. Indicate if the revenue source is local, state, federal, private, grants, or other. The total is populated for you in the grey cells. Do not delete the formula. If you need extra lines, insert them as needed, but ensure the formula includes any added cells.
A4: Revenue Detail
B5: Planning Period (through June 30, 2014) | C5: 1st Operational Year (July 1, 2014-June 30, 2015)
A6: Description | B6: =SUM(B7:B31) -> 0 | C6: =SUM(C7:C31) -> 0

Sheet Salaries & Benefits (100-200)
A1: ='Part I Summary'!A1 -> School Name:
A2: Part II Budget Detail
A3: Amount paid to employees of the school in permanent and paid positions. Benefits include amounts paid by school on behalf of employees which are over and above salary. The total is populated for you in the grey cells. Do not delete the formula. If you need extra lines, insert them as needed, but ensure the formula includes any added cells.
A4: Salaries (100) and Benefits (200)
B5: Planning Period (through June 30, 2014) | C5: 1st Operational Year (July 1, 2014-June 30, 2015)
A6: Title and number of employees during planning period and 1st operational year | B6: =SUM(B7:B30) -> 0 | C6: =SUM(C7:C30) -> 0

Sheet Professional Services (300)
A1: ='Part I Summary'!A1 -> School Name:
A2: Part II Budget Detail
A3: This will include any purchased services, from individuals or companies with specialized skills, knowledge and services, such as any service provider, accountants, architects, auditors, and consultants. Included in the amount is also any associated expenses paid to the service provider, etc. such as travel, per-diem, and miscellaneous items. The total is populated for you in the grey cells. Do not delete the formula. If you need extra lines, insert them as needed, but ensure the formula includes any added cells.
A4: Purchased Professional and Technical Services (300)
B5: Planning Period (through June 30, 2014) | C5: 1st Operational Year (July 1, 2014-June 30, 2015)
A6: Description (include name or type of company and service provided) | B6: =SUM(B7:B30) -> 0 | C6: =SUM(C7:C30) -> 0

Sheet Property Services (400)
A1: ='Part I Summary'!A1 -> School Name:
A2: Part II Budget Detail
A3: Amounts paid for services, rendered by organizations or personnel not on payroll of the school, to operate, repair, maintain, insure and rent property owned and/or used by the governing board or school. The total is populated for you in the grey cells. Do not delete the formula. If you need extra lines, insert them as needed, but ensure the formula includes any added cells.
A4: Purchased Property Services (400)
B5: Planning Period (through June 30, 2014) | C5: 1st Operational Year (July 1, 2014-June 30, 2015)
A6: Description (include name or type of company and service provided) | B6: =SUM(B7:B32) -> 0 | C6: =SUM(C7:C32) -> 0

Sheet Other (500)
A1: ='Part I Summary'!A1 -> School Name:
A2: Part II Budget Detail
A3: Amounts paid for services rendered by organizations or personnel not on payroll of the school, and other than Professional and Technical Services (300), or Purchased Property Services (400). The total is populated for you in the grey cells. Do not delete the formula. If you need extra lines, insert them as needed, but ensure the formula includes any added cells.
A4: Other Purchased Services (500)
B5: Planning Period (through June 30, 2014) | C5: 1st Operational Year (July 1, 2014-June 30, 2015)
A6: Description (include name or type of company and service provided) | B6: =SUM(B7:B31) -> 0 | C6: =SUM(C7:C31) -> 0

Sheet Travel (580)
A1: ='Part I Summary'!A1 -> School Name:
A2: Part II Budget Detail
A3: Expenditures for transportation, meals, hotel, and other expenses associated with staff (on payroll) and governing board travel for the school. The total is populated for you in the grey cells. Do not delete the formula. If you need extra lines, insert them as needed, but ensure the formula includes any added cells.
A4: Travel (580)
B5: Planning Period (through June 30, 2014) | C5: 1st Operational Year (July 1, 2014-June 30, 2015)
A6: Description | B6: =SUM(B7:B34) -> 0 | C6: =SUM(C7:C34) -> 0

Sheet Supplies and Materials (600)
A1: ='Part I Summary'!A1 -> School Name:
A2: Part II Budget Detail
A3: Amounts paid for items of an expendable nature that are consumed, worn out, or deteriorated in use; or items that lose their identity through fabrication or incorporation into different or more complex units or substances are considered supply expenditures. Amounts paid for non-equipment items and with reasonable care and use may be expected to last for more than one year, are considered material expenditures. Includes computer programs (software). The total is populated for you in the grey cells. Do not delete the formula. If you need extra lines, insert them as needed, but ensure the formula includes any added cells.
A4: Supplies and Materials (600)
B5: Planning Period (through June 30, 2014) | C5: 1st Operational Year (July 1, 2014-June 30, 2015)
A6: Description (include item and quantity) | B6: =SUM(B7:B31) -> 0 | C6: =SUM(C7:C31) -> 0

Sheet Property (700)
A1: ='Part I Summary'!A1 -> School Name:
A2: Part II Budget Detail
A3: Expenditures for the acquisition of fixed assets, including expenditures for land or existing buildings and improvements of grounds; initial equipment; additional equipment; and replacement of equipment. (i.e., machinery, school buses, furniture & fixtures, audiovisual equipment, non-bus vehicles, computer equipment (hardware)). The total is populated for you in the grey cells. Do not delete the formula. If you need extra lines, insert them as needed, but ensure the formula includes any added cells.
A4: Property (700)
B5: Planning Period (through June 30, 2014) | C5: 1st Operational Year (July 1, 2014-June 30, 2015)
A6: Description (include item and quantity) | B6: =SUM(B7:B32) -> 0 | C6: =SUM(C7:C32) -> 0

Sheet Misc (800)
A1: ='Part I Summary'!A1 -> School Name:
A2: Part II Budget Detail
A3: Expenditures for goods and services not otherwise classified above, such as interest, amortization of bond issuance and other debt-related costs, and professional membership dues. The total is populated for you in the grey cells. Do not delete the formula. If you need extra lines, insert them as needed, but ensure the formula includes any added cells.
A4: Debt Service and Miscellaneous (800)
B5: Planning Period (through June 30, 2014) | C5: 1st Operational Year (July 1, 2014-June 30, 2015)
A6: Description | B6: =SUM(B7:B32) -> 0 | C6: =SUM(C7:C32) -> 0
