Workbook

Sheet Pivot
A1: SCC Student Funded Programs
A2: for the period ending June 30, 2013
A4: Account Title | B4: Budget | C4: (Rev)/Exp | D4: Encumbered | E4: Balance
A5: 2221 - SPEC.BLDG FUND-SCC
A6: Carryforward | B6: 0 | C6: -652524.89 | D6: 0 | E6: 652524.89
A7: Revenue | B7: 0 | C7: -304696.93 | D7: 0 | E7: 304696.93
A8: Rev-Fund Transfers - In | B8: 0 | C8: 0 | D8: 0 | E8: 0
A9: Rev-Fund Transfers - Out | B9: 0 | C9: 0 | D9: 0 | E9: 0
A10: Exp-Goods & Services | B10: 0 | C10: 2787.91 | D10: 0 | E10: -2787.91
A11: Exp-Travel | B11: 0 | C11: 0 | D11: 0 | E11: 0
A12: Exp-Equipment | B12: 0 | C12: 0 | D12: 0 | E12: 0
A13: Exp-Computer Equipment | B13: 0 | C13: 0 | D13: 0 | E13: 0
A14: 2221 - SPEC.BLDG FUND-SCC Total | B14: 0 | C14: -954433.91 | D14: 0 | E14: 954433.91
A15: 2222 - SBF-SCC-LAIR FURNISH
A16: Carryforward | B16: 0 | C16: -3339.12 | D16: 0 | E16: 3339.12
A17: 2222 - SBF-SCC-LAIR FURNISH Total | B17: 0 | C17: -3339.12 | D17: 0 | E17: 3339.12
A18: 2309 - IRP CLUB ADVISORS
A19: Exp-Salaries & Wages | B19: 48333 | C19: 48353.89 | D19: 0 | E19: -20.89
A20: Exp-Benefits | B20: 9667 | C20: 8351.01 | D20: 0 | E20: 1315.99
A21: Exp-Goods & Services | B21: 0 | C21: 884.55 | D21: 0 | E21: -884.55
A22: 2309 - IRP CLUB ADVISORS Total | B22: 58000 | C22: 57589.45 | D22: 0 | E22: 410.55
A23: 2310 - IRP-GENERAL FUND
A24: Carryforward | B24: 0 | C24: 179090.33 | D24: 0 | E24: -179090.33
A25: Rev-Intra-Fund Transfer | B25: 0 | C25: -384041.9 | D25: 0 | E25: 384041.9
A26: Exp-Goods & Services | B26: 13893 | C26: 5901.6 | D26: 0 | E26: 7991.4
A27: Exp-Travel | B27: 0 | C27: 148.54 | D27: 0 | E27: -148.54
A28: 2310 - IRP-GENERAL FUND Total | B28: 13893 | C28: -198901.43 | D28: 0 | E28: 212794.43
A29: 2311 - PRES SPEAKER SERIES
A30: Exp-Salaries & Wages | B30: 0 | C30: 0 | D30: 0 | E30: 0
A31: Exp-Benefits | B31: 0 | C31: -0.09 | D31: 0 | E31: 0.09
A32: Exp-Goods & Services | B32: 0 | C32: 0 | D32: 0 | E32: 0
A33: 2311 - PRES SPEAKER SERIES Total | B33: 0 | C33: -0.09 | D33: 0 | E33: 0.09
A34: 2312 - ADA ACCESSIBILITY
A35: Exp-Salaries & Wages | B35: 909 | C35: 636.23 | D35: 0 | E35: 272.77
A36: Exp-Benefits | B36: 91 | C36: 71.57 | D36: 0 | E36: 19.43
A37: Exp-Goods & Services | B37: 0 | C37: 0 | D37: 0 | E37: 0
A38: 2312 - ADA ACCESSIBILITY Total | B38: 1000 | C38: 707.8 | D38: 0 | E38: 292.2
A39: 2313 - HLTH INFO MANAGEMNT
A40: Revenue | B40: 0 | C40: 0 | D40: 0 | E40: 0
A41: Exp-Goods & Services | B41: 2060 | C41: 0 | D41: 0 | E41: 2060
A42: Exp-Travel | B42: 0 | C42: 0 | D42: 0 | E42: 0
A43: Exp-Grants/Scholarships | B43: 0 | C43: 0 | D43: 0 | E43: 0
A44: 2313 - HLTH INFO MANAGEMNT Total | B44: 2060 | C44: 0 | D44: 0 | E44: 2060
A45: 2314 - AMER DESGN DRFTG S A
A46: Revenue | B46: 0 | C46: -73.5 | D46: 0 | E46: 73.5
A47: Rev-Fund Transfers - Out | B47: 0 | C47: 100 | D47: 0 | E47: -100
A48: Exp-Goods & Services | B48: 16295 | C48: 4831.47 | D48: 0 | E48: 11463.53
A49: Exp-Travel | B49: 0 | C49: 5009.71 | D49: 0 | E49: -5009.71
A50: Exp-Equipment | B50: 0 | C50: 6325.62 | D50: 0 | E50: -6325.62
A51: 2314 - AMER DESGN DRFTG S A Total | B51: 16295 | C51: 16193.3 | D51: 0 | E51: 101.7
A52: 2319 - SKILLS USA (VICA)
A53: Revenue | B53: 0 | C53: 0 | D53: 0 | E53: 0
A54: Rev-Intra-Fund Transfer | B54: 0 | C54: 0 | D54: 0 | E54: 0
A55: Exp-Benefits | B55: 0 | C55: 0 | D55: 0 | E55: 0
A56: Exp-Goods & Services | B56: 31563 | C56: 5172.14 | D56: 0 | E56: 26390.86
A57: Exp-Travel | B57: 0 | C57: 22312.15 | D57: 0 | E57: -22312.15
A58: Exp-Computer Equipment | B58: 0 | C58: 2878.35 | D58: 0 | E58: -2878.35
A59: Exp-Grants/Scholarships | B59: 0 | C59: 0 | D59: 0 | E59: 0
A60: 2319 - SKILLS USA (VICA) Total | B60: 31563 | C60: 30362.64 | D60: 0 | E60: 1200.36
A61: 2324 - WRITERS ON THE STORM
A62: Exp-Travel | B62: 0 | C62: 0 | D62: 0 | E62: 0
A63: 2324 - WRITERS ON THE STORM Total | B63: 0 | C63: 0 | D63: 0 | E63: 0
A64: 2330 - MATH CLUB
A65: Exp-Goods & Services | B65: 0 | C65: 0 | D65: 0 | E65: 0
A66: 2330 - MATH CLUB Total | B66: 0 | C66: 0 | D66: 0 | E66: 0
A67: 2343 - SCC AUTOMOTIVE ASSNS
A68: Revenue | B68: 0 | C68: -175 | D68: 0 | E68: 175
A69: Rev-Intra-Fund Transfer | B69: 0 | C69: -4672 | D69: 0 | E69: 4672
A70: Exp-Goods & Services | B70: 4300 | C70: 2485.03 | D70: 0 | E70: 1814.97
A71: Exp-Travel | B71: 0 | C71: 0 | D71: 0 | E71: 0
A72: Exp-Equipment | B72: 0 | C72: 325.01 | D72: 0 | E72: -325.01
A73: 2343 - SCC AUTOMOTIVE ASSNS Total | B73: 4300 | C73: -2036.96 | D73: 0 | E73: 6336.96
A74: 2345 - CULINARY ARTS CLUB
A75: Revenue | B75: 0 | C75: 0 | D75: 0 | E75: 0
A76: Rev-Intra-Fund Transfer | B76: 0 | C76: -132 | D76: 0 | E76: 132
A77: Exp-Goods & Services | B77: 6975 | C77: 280 | D77: 0 | E77: 6695
A78: Exp-Travel | B78: 0 | C78: 0 | D78: 0 | E78: 0
A79: 2345 - CULINARY ARTS CLUB Total | B79: 6975 | C79: 148 | D79: 0 | E79: 6827
A80: 2350 - LEGENDS
A81: Exp-Salaries & Wages | B81: 0 | C81: 0 | D81: 0 | E81: 0
A82: Exp-Benefits | B82: 0 | C82: 0 | D82: 0 | E82: 0
A83: Exp-Goods & Services | B83: 10000 | C83: 5794.87 | D83: 0 | E83: 4205.13
A84: Exp-Equipment | B84: 0 | C84: 4093.97 | D84: 0 | E84: -4093.97
A85: Exp-Grants/Scholarships | B85: 0 | C85: 0 | D85: 0 | E85: 0
A86: 2350 - LEGENDS Total | B86: 10000 | C86: 9888.84 | D86: 0 | E86: 111.16
A87: 2353 - AGRICULTURE
A88: Revenue | B88: 0 | C88: -4231.71 | D88: 0 | E88: 4231.71
A89: Rev-Intra-Fund Transfer | B89: 0 | C89: -5592.75 | D89: 0 | E89: 5592.75
A90: Exp-Goods & Services | B90: 23588 | C90: 8220.39 | D90: 0 | E90: 15367.61
A91: Exp-Travel | B91: 0 | C91: 25263.76 | D91: 0 | E91: -25263.76
A92: 2353 - AGRICULTURE Total | B92: 23588 | C92: 23659.69 | D92: 0 | E92: -71.69
A93: 2354 - CRAFT FAIR
A94: Revenue | B94: 0 | C94: -10329 | D94: 0 | E94: 10329
A95: Rev-Intra-Fund Transfer | B95: 0 | C95: 0 | D95: 0 | E95: 0
A96: Rev-Fund Transfers - Out | B96: 0 | C96: 0 | D96: 0 | E96: 0
A97: Exp-Salaries & Wages | B97: 0 | C97: 0 | D97: 0 | E97: 0
A98: Exp-Benefits | B98: 0 | C98: 0 | D98: 0 | E98: 0
A99: Exp-Goods & Services | B99: 0 | C99: 5370.97 | D99: 0 | E99: -5370.97
A100: Exp-Travel | B100: 0 | C100: 788 | D100: 0 | E100: -788
A101: 2354 - CRAFT FAIR Total | B101: 0 | C101: -4170.03 | D101: 0 | E101: 4170.03
...

Sheet BSPRGORG-T
A1: FYR | B1: Appr | C1: Prg | D1: Org | E1: Title | F1: Sobj | G1: SSObj | H1: Src | I1: SSrc | J1: Category | K1: Budget | L1: Exp/Rev | M1: Encumbered | N1: Balance | O1: Current | P1: Org Title
A2: 1213 | B2: 522 | C2: 264 | D2: 2221 | E2: =D2&" - "&P2 -> 2221 - SPEC.BLDG FUND-SCC | H2: 0401 | J2: =IF(H2="",VLOOKUP(LEFT(F2,1),'Exp-Rev Categories'!A:B,2,FALSE),IF(ISNA(VLOOKUP(H2,'Exp-Rev Categories'!A:B,2,FALSE)),"Revenue",VLOOKUP(H2,'Exp-Rev Categories'!A:B,2,FALSE))) -> Revenue | K2: 0 | L2: -5473.54 | M2: 0 | N2: 5473.54 | O2: -1964.34 | P2: SPEC.BLDG FUND-SCC
A3: 1213 | B3: 522 | C3: 264 | D3: 2221 | E3: =D3&" - "&P3 -> 2221 - SPEC.BLDG FUND-SCC | H3: 0424 | I3: #A | J3: =IF(H3="",VLOOKUP(LEFT(F3,1),'Exp-Rev Categories'!A:B,2,FALSE),IF(ISNA(VLOOKUP(H3,'Exp-Rev Categories'!A:B,2,FALSE)),"Revenue",VLOOKUP(H3,'Exp-Rev Categories'!A:B,2,FALSE))) -> Revenue | K3: 0 | L3: -566.75 | M3: 0 | N3: 566.75 | O3: 0 | P3: SPEC.BLDG FUND-SCC
A4: 1213 | B4: 522 | C4: 264 | D4: 2221 | E4: =D4&" - "&P4 -> 2221 - SPEC.BLDG FUND-SCC | H4: 0424 | I4: #B | J4: =IF(H4="",VLOOKUP(LEFT(F4,1),'Exp-Rev Categories'!A:B,2,FALSE),IF(ISNA(VLOOKUP(H4,'Exp-Rev Categories'!A:B,2,FALSE)),"Revenue",VLOOKUP(H4,'Exp-Rev Categories'!A:B,2,FALSE))) -> Revenue | K4: 0 | L4: -71.91 | M4: 0 | N4: 71.91 | O4: 0 | P4: SPEC.BLDG FUND-SCC
A5: 1213 | B5: 522 | C5: 264 | D5: 2221 | E5: =D5&" - "&P5 -> 2221 - SPEC.BLDG FUND-SCC | H5: 0424 | I5: #G | J5: =IF(H5="",VLOOKUP(LEFT(F5,1),'Exp-Rev Categories'!A:B,2,FALSE),IF(ISNA(VLOOKUP(H5,'Exp-Rev Categories'!A:B,2,FALSE)),"Revenue",VLOOKUP(H5,'Exp-Rev Categories'!A:B,2,FALSE))) -> Revenue | K5: 0 | L5: -1052.07 | M5: 0 | N5: 1052.07 | O5: 0 | P5: SPEC.BLDG FUND-SCC
A6: 1213 | B6: 522 | C6: 264 | D6: 2221 | E6: =D6&" - "&P6 -> 2221 - SPEC.BLDG FUND-SCC | H6: 0424 | I6: #P | J6: =IF(H6="",VLOOKUP(LEFT(F6,1),'Exp-Rev Categories'!A:B,2,FALSE),IF(ISNA(VLOOKUP(H6,'Exp-Rev Categories'!A:B,2,FALSE)),"Revenue",VLOOKUP(H6,'Exp-Rev Categories'!A:B,2,FALSE))) -> Revenue | K6: 0 | L6: -437.51 | M6: 0 | N6: 437.51 | O6: 0 | P6: SPEC.BLDG FUND-SCC
A7: 1213 | B7: 522 | C7: 264 | D7: 2221 | E7: =D7&" - "&P7 -> 2221 - SPEC.BLDG FUND-SCC | H7: 0424 | I7: +1 | J7: =IF(H7="",VLOOKUP(LEFT(F7,1),'Exp-Rev Categories'!A:B,2,FALSE),IF(ISNA(VLOOKUP(H7,'Exp-Rev Categories'!A:B,2,FALSE)),"Revenue",VLOOKUP(H7,'Exp-Rev Categories'!A:B,2,FALSE))) -> Revenue | K7: 0 | L7: -92.92 | M7: 0 | N7: 92.92 | O7: 0 | P7: SPEC.BLDG FUND-SCC
A8: 1213 | B8: 522 | C8: 264 | D8: 2221 | E8: =D8&" - "&P8 -> 2221 - SPEC.BLDG FUND-SCC | H8: 0424 | I8: +2 | J8: =IF(H8="",VLOOKUP(LEFT(F8,1),'Exp-Rev Categories'!A:B,2,FALSE),IF(ISNA(VLOOKUP(H8,'Exp-Rev Categories'!A:B,2,FALSE)),"Revenue",VLOOKUP(H8,'Exp-Rev Categories'!A:B,2,FALSE))) -> Revenue | K8: 0 | L8: -6.21 | M8: 0 | N8: 6.21 | O8: 0 | P8: SPEC.BLDG FUND-SCC
A9: 1213 | B9: 522 | C9: 264 | D9: 2221 | E9: =D9&" - "&P9 -> 2221 - SPEC.BLDG FUND-SCC | H9: 0424 | I9: +A | J9: =IF(H9="",VLOOKUP(LEFT(F9,1),'Exp-Rev Categories'!A:B,2,FALSE),IF(ISNA(VLOOKUP(H9,'Exp-Rev Categories'!A:B,2,FALSE)),"Revenue",VLOOKUP(H9,'Exp-Rev Categories'!A:B,2,FALSE))) -> Revenue | K9: 0 | L9: -19100.76 | M9: 0 | N9: 19100.76 | O9: 0 | P9: SPEC.BLDG FUND-SCC
A10: 1213 | B10: 522 | C10: 264 | D10: 2221 | E10: =D10&" - "&P10 -> 2221 - SPEC.BLDG FUND-SCC | H10: 0424 | I10: +G | J10: =IF(H10="",VLOOKUP(LEFT(F10,1),'Exp-Rev Categories'!A:B,2,FALSE),IF(ISNA(VLOOKUP(H10,'Exp-Rev Categories'!A:B,2,FALSE)),"Revenue",VLOOKUP(H10,'Exp-Rev Categories'!A:B,2,FALSE))) -> Revenue | K10: 0 | L10: -33899.59 | M10: 0 | N10: 33899.59 | O10: 0 | P10: SPEC.BLDG FUND-SCC
A11: 1213 | B11: 522 | C11: 264 | D11: 2221 | E11: =D11&" - "&P11 -> 2221 - SPEC.BLDG FUND-SCC | H11: 0424 | I11: +H | J11: =IF(H11="",VLOOKUP(LEFT(F11,1),'Exp-Rev Categories'!A:B,2,FALSE),IF(ISNA(VLOOKUP(H11,'Exp-Rev Categories'!A:B,2,FALSE)),"Revenue",VLOOKUP(H11,'Exp-Rev Categories'!A:B,2,FALSE))) -> Revenue | K11: 0 | L11: -324.28 | M11: 0 | N11: 324.28 | O11: 0 | P11: SPEC.BLDG FUND-SCC
A12: 1213 | B12: 522 | C12: 264 | D12: 2221 | E12: =D12&" - "&P12 -> 2221 - SPEC.BLDG FUND-SCC | H12: 0424 | I12: +M | J12: =IF(H12="",VLOOKUP(LEFT(F12,1),'Exp-Rev Categories'!A:B,2,FALSE),IF(ISNA(VLOOKUP(H12,'Exp-Rev Categories'!A:B,2,FALSE)),"Revenue",VLOOKUP(H12,'Exp-Rev Categories'!A:B,2,FALSE))) -> Revenue | K12: 0 | L12: -3146.61 | M12: 0 | N12: 3146.61 | O12: 0 | P12: SPEC.BLDG FUND-SCC
A13: 1213 | B13: 522 | C13: 264 | D13: 2221 | E13: =D13&" - "&P13 -> 2221 - SPEC.BLDG FUND-SCC | H13: 0424 | I13: TN | J13: =IF(H13="",VLOOKUP(LEFT(F13,1),'Exp-Rev Categories'!A:B,2,FALSE),IF(ISNA(VLOOKUP(H13,'Exp-Rev Categories'!A:B,2,FALSE)),"Revenue",VLOOKUP(H13,'Exp-Rev Categories'!A:B,2,FALSE))) -> Revenue | K13: 0 | L13: -1736.51 | M13: 0 | N13: 1736.51 | O13: 0 | P13: SPEC.BLDG FUND-SCC
A14: 1213 | B14: 522 | C14: 264 | D14: 2221 | E14: =D14&" - "&P14 -> 2221 - SPEC.BLDG FUND-SCC | H14: 0424 | I14: TR | J14: =IF(H14="",VLOOKUP(LEFT(F14,1),'Exp-Rev Categories'!A:B,2,FALSE),IF(ISNA(VLOOKUP(H14,'Exp-Rev Categories'!A:B,2,FALSE)),"Revenue",VLOOKUP(H14,'Exp-Rev Categories'!A:B,2,FALSE))) -> Revenue | K14: 0 | L14: -238788.27 | M14: 0 | N14: 238788.27 | O14: 0 | P14: SPEC.BLDG FUND-SCC
A15: 1213 | B15: 522 | C15: 264 | D15: 2221 | E15: =D15&" - "&P15 -> 2221 - SPEC.BLDG FUND-SCC | H15: 0621 | J15: =IF(H15="",VLOOKUP(LEFT(F15,1),'Exp-Rev Categories'!A:B,2,FALSE),IF(ISNA(VLOOKUP(H15,'Exp-Rev Categories'!A:B,2,FALSE)),"Revenue",VLOOKUP(H15,'Exp-Rev Categories'!A:B,2,FALSE))) -> Rev-Fund Transfers - In | K15: 0 | L15: 0 | M15: 0 | N15: 0 | O15: 0 | P15: SPEC.BLDG FUND-SCC
A16: 1213 | B16: 522 | C16: 264 | D16: 2221 | E16: =D16&" - "&P16 -> 2221 - SPEC.BLDG FUND-SCC | H16: 0622 | J16: =IF(H16="",VLOOKUP(LEFT(F16,1),'Exp-Rev Categories'!A:B,2,FALSE),IF(ISNA(VLOOKUP(H16,'Exp-Rev Categories'!A:B,2,FALSE)),"Revenue",VLOOKUP(H16,'Exp-Rev Categories'!A:B,2,FALSE))) -> Rev-Fund Transfers - Out | K16: 0 | L16: 0 | M16: 0 | N16: 0 | O16: 0 | P16: SPEC.BLDG FUND-SCC
A17: 1213 | B17: 522 | C17: 264 | D17: 2221 | E17: =D17&" - "&P17 -> 2221 - SPEC.BLDG FUND-SCC | H17: 0999 | J17: =IF(H17="",VLOOKUP(LEFT(F17,1),'Exp-Rev Categories'!A:B,2,FALSE),IF(ISNA(VLOOKUP(H17,'Exp-Rev Categories'!A:B,2,FALSE)),"Revenue",VLOOKUP(H17,'Exp-Rev Categories'!A:B,2,FALSE))) -> Carryforward | K17: 0 | L17: -652524.89 | M17: 0 | N17: 652524.89 | O17: 0 | P17: SPEC.BLDG FUND-SCC
A18: 1213 | B18: 522 | C18: 264 | D18: 2221 | E18: =D18&" - "&P18 -> 2221 - SPEC.BLDG FUND-SCC | F18: E | J18: =IF(H18="",VLOOKUP(LEFT(F18,1),'Exp-Rev Categories'!A:B,2,FALSE),IF(ISNA(VLOOKUP(H18,'Exp-Rev Categories'!A:B,2,FALSE)),"Revenue",VLOOKUP(H18,'Exp-Rev Categories'!A:B,2,FALSE))) -> Exp-Goods & Services | K18: 0 | L18: 0 | M18: 0 | N18: 0 | O18: 0 | P18: SPEC.BLDG FUND-SCC
A19: 1213 | B19: 522 | C19: 264 | D19: 2221 | E19: =D19&" - "&P19 -> 2221 - SPEC.BLDG FUND-SCC | F19: EA | G19: 00 | J19: =IF(H19="",VLOOKUP(LEFT(F19,1),'Exp-Rev Categories'!A:B,2,FALSE),IF(ISNA(VLOOKUP(H19,'Exp-Rev Categories'!A:B,2,FALSE)),"Revenue",VLOOKUP(H19,'Exp-Rev Categories'!A:B,2,FALSE))) -> Exp-Goods & Services | K19: 0 | L19: 2787.91 | M19: 0 | N19: -2787.91 | O19: 0 | P19: SPEC.BLDG FUND-SCC
A20: 1213 | B20: 522 | C20: 264 | D20: 2221 | E20: =D20&" - "&P20 -> 2221 - SPEC.BLDG FUND-SCC | F20: G | J20: =IF(H20="",VLOOKUP(LEFT(F20,1),'Exp-Rev Categories'!A:B,2,FALSE),IF(ISNA(VLOOKUP(H20,'Exp-Rev Categories'!A:B,2,FALSE)),"Revenue",VLOOKUP(H20,'Exp-Rev Categories'!A:B,2,FALSE))) -> Exp-Travel | K20: 0 | L20: 0 | M20: 0 | N20: 0 | O20: 0 | P20: SPEC.BLDG FUND-SCC
A21: 1213 | B21: 522 | C21: 264 | D21: 2221 | E21: =D21&" - "&P21 -> 2221 - SPEC.BLDG FUND-SCC | F21: J | J21: =IF(H21="",VLOOKUP(LEFT(F21,1),'Exp-Rev Categories'!A:B,2,FALSE),IF(ISNA(VLOOKUP(H21,'Exp-Rev Categories'!A:B,2,FALSE)),"Revenue",VLOOKUP(H21,'Exp-Rev Categories'!A:B,2,FALSE))) -> Exp-Equipment | K21: 0 | L21: 0 | M21: 0 | N21: 0 | O21: 0 | P21: SPEC.BLDG FUND-SCC
A22: 1213 | B22: 522 | C22: 264 | D22: 2221 | E22: =D22&" - "&P22 -> 2221 - SPEC.BLDG FUND-SCC | F22: KA | J22: =IF(H22="",VLOOKUP(LEFT(F22,1),'Exp-Rev Categories'!A:B,2,FALSE),IF(ISNA(VLOOKUP(H22,'Exp-Rev Categories'!A:B,2,FALSE)),"Revenue",VLOOKUP(H22,'Exp-Rev Categories'!A:B,2,FALSE))) -> Exp-Computer Equipment | K22: 0 | L22: 0 | M22: 0 | N22: 0 | O22: 0 | P22: SPEC.BLDG FUND-SCC
A23: 1213 | B23: 522 | C23: 264 | D23: 2221 | E23: =D23&" - "&P23 -> 2221 - SPEC.BLDG FUND-SCC | F23: KC | J23: =IF(H23="",VLOOKUP(LEFT(F23,1),'Exp-Rev Categories'!A:B,2,FALSE),IF(ISNA(VLOOKUP(H23,'Exp-Rev Categories'!A:B,2,FALSE)),"Revenue",VLOOKUP(H23,'Exp-Rev Categories'!A:B,2,FALSE))) -> Exp-Computer Equipment | K23: 0 | L23: 0 | M23: 0 | N23: 0 | O23: 0 | P23: SPEC.BLDG FUND-SCC
A24: 1213 | B24: 522 | C24: 264 | D24: 2222 | E24: =D24&" - "&P24 -> 2222 - SBF-SCC-LAIR FURNISH | H24: 0999 | J24: =IF(H24="",VLOOKUP(LEFT(F24,1),'Exp-Rev Categories'!A:B,2,FALSE),IF(ISNA(VLOOKUP(H24,'Exp-Rev Categories'!A:B,2,FALSE)),"Revenue",VLOOKUP(H24,'Exp-Rev Categories'!A:B,2,FALSE))) -> Carryforward | K24: 0 | L24: -3339.12 | M24: 0 | N24: 3339.12 | O24: 0 | P24: SBF-SCC-LAIR FURNISH
A25: 1213 | B25: 522 | C25: 264 | D25: 2309 | E25: =D25&" - "&P25 -> 2309 - IRP CLUB ADVISORS | F25: AC | G25: CA | J25: =IF(H25="",VLOOKUP(LEFT(F25,1),'Exp-Rev Categories'!A:B,2,FALSE),IF(ISNA(VLOOKUP(H25,'Exp-Rev Categories'!A:B,2,FALSE)),"Revenue",VLOOKUP(H25,'Exp-Rev Categories'!A:B,2,FALSE))) -> Exp-Salaries & Wages | K25: 0 | L25: 963 | M25: 0 | N25: -963 | O25: 0 | P25: IRP CLUB ADVISORS
A26: 1213 | B26: 522 | C26: 264 | D26: 2309 | E26: =D26&" - "&P26 -> 2309 - IRP CLUB ADVISORS | F26: AE | G26: CA | J26: =IF(H26="",VLOOKUP(LEFT(F26,1),'Exp-Rev Categories'!A:B,2,FALSE),IF(ISNA(VLOOKUP(H26,'Exp-Rev Categories'!A:B,2,FALSE)),"Revenue",VLOOKUP(H26,'Exp-Rev Categories'!A:B,2,FALSE))) -> Exp-Salaries & Wages | K26: 48333 | L26: 45421.5 | M26: 0 | N26: 2911.5 | O26: 0 | P26: IRP CLUB ADVISORS
A27: 1213 | B27: 522 | C27: 264 | D27: 2309 | E27: =D27&" - "&P27 -> 2309 - IRP CLUB ADVISORS | F27: AE | G27: CP | J27: =IF(H27="",VLOOKUP(LEFT(F27,1),'Exp-Rev Categories'!A:B,2,FALSE),IF(ISNA(VLOOKUP(H27,'Exp-Rev Categories'!A:B,2,FALSE)),"Revenue",VLOOKUP(H27,'Exp-Rev Categories'!A:B,2,FALSE))) -> Exp-Salaries & Wages | K27: 0 | L27: 1765.5 | M27: 0 | N27: -1765.5 | O27: 0 | P27: IRP CLUB ADVISORS
A28: 1213 | B28: 522 | C28: 264 | D28: 2309 | E28: =D28&" - "&P28 -> 2309 - IRP CLUB ADVISORS | F28: AU | G28: 01 | J28: =IF(H28="",VLOOKUP(LEFT(F28,1),'Exp-Rev Categories'!A:B,2,FALSE),IF(ISNA(VLOOKUP(H28,'Exp-Rev Categories'!A:B,2,FALSE)),"Revenue",VLOOKUP(H28,'Exp-Rev Categories'!A:B,2,FALSE))) -> Exp-Salaries & Wages | K28: 0 | L28: 203.89 | M28: 0 | N28: -203.89 | O28: 0 | P28: IRP CLUB ADVISORS
A29: 1213 | B29: 522 | C29: 264 | D29: 2309 | E29: =D29&" - "&P29 -> 2309 - IRP CLUB ADVISORS | F29: B | J29: =IF(H29="",VLOOKUP(LEFT(F29,1),'Exp-Rev Categories'!A:B,2,FALSE),IF(ISNA(VLOOKUP(H29,'Exp-Rev Categories'!A:B,2,FALSE)),"Revenue",VLOOKUP(H29,'Exp-Rev Categories'!A:B,2,FALSE))) -> Exp-Benefits | K29: 9667 | L29: 0 | M29: 0 | N29: 9667 | O29: 0 | P29: IRP CLUB ADVISORS
A30: 1213 | B30: 522 | C30: 264 | D30: 2309 | E30: =D30&" - "&P30 -> 2309 - IRP CLUB ADVISORS | F30: BA | J30: =IF(H30="",VLOOKUP(LEFT(F30,1),'Exp-Rev Categories'!A:B,2,FALSE),IF(ISNA(VLOOKUP(H30,'Exp-Rev Categories'!A:B,2,FALSE)),"Revenue",VLOOKUP(H30,'Exp-Rev Categories'!A:B,2,FALSE))) -> Exp-Benefits | K30: 0 | L30: 3655.48 | M30: 0 | N30: -3655.48 | O30: 0 | P30: IRP CLUB ADVISORS
A31: 1213 | B31: 522 | C31: 264 | D31: 2309 | E31: =D31&" - "&P31 -> 2309 - IRP CLUB ADVISORS | F31: BB | J31: =IF(H31="",VLOOKUP(LEFT(F31,1),'Exp-Rev Categories'!A:B,2,FALSE),IF(ISNA(VLOOKUP(H31,'Exp-Rev Categories'!A:B,2,FALSE)),"Revenue",VLOOKUP(H31,'Exp-Rev Categories'!A:B,2,FALSE))) -> Exp-Benefits | K31: 0 | L31: 4306.86 | M31: 0 | N31: -4306.86 | O31: 0 | P31: IRP CLUB ADVISORS
A32: 1213 | B32: 522 | C32: 264 | D32: 2309 | E32: =D32&" - "&P32 -> 2309 - IRP CLUB ADVISORS | F32: BC | J32: =IF(H32="",VLOOKUP(LEFT(F32,1),'Exp-Rev Categories'!A:B,2,FALSE),IF(ISNA(VLOOKUP(H32,'Exp-Rev Categories'!A:B,2,FALSE)),"Revenue",VLOOKUP(H32,'Exp-Rev Categories'!A:B,2,FALSE))) -> Exp-Benefits | K32: 0 | L32: 2.92 | M32: 0 | N32: -2.92 | O32: 0 | P32: IRP CLUB ADVISORS
A33: 1213 | B33: 522 | C33: 264 | D33: 2309 | E33: =D33&" - "&P33 -> 2309 - IRP CLUB ADVISORS | F33: BD | J33: =IF(H33="",VLOOKUP(LEFT(F33,1),'Exp-Rev Categories'!A:B,2,FALSE),IF(ISNA(VLOOKUP(H33,'Exp-Rev Categories'!A:B,2,FALSE)),"Revenue",VLOOKUP(H33,'Exp-Rev Categories'!A:B,2,FALSE))) -> Exp-Benefits | K33: 0 | L33: 37.6 | M33: 0 | N33: -37.6 | O33: 0 | P33: IRP CLUB ADVISORS
A34: 1213 | B34: 522 | C34: 264 | D34: 2309 | E34: =D34&" - "&P34 -> 2309 - IRP CLUB ADVISORS | F34: BF | J34: =IF(H34="",VLOOKUP(LEFT(F34,1),'Exp-Rev Categories'!A:B,2,FALSE),IF(ISNA(VLOOKUP(H34,'Exp-Rev Categories'!A:B,2,FALSE)),"Revenue",VLOOKUP(H34,'Exp-Rev Categories'!A:B,2,FALSE))) -> Exp-Benefits | K34: 0 | L34: 348.15 | M34: 0 | N34: -348.15 | O34: 0 | P34: IRP CLUB ADVISORS
A35: 1213 | B35: 522 | C35: 264 | D35: 2309 | E35: =D35&" - "&P35 -> 2309 - IRP CLUB ADVISORS | F35: E | J35: =IF(H35="",VLOOKUP(LEFT(F35,1),'Exp-Rev Categories'!A:B,2,FALSE),IF(ISNA(VLOOKUP(H35,'Exp-Rev Categories'!A:B,2,FALSE)),"Revenue",VLOOKUP(H35,'Exp-Rev Categories'!A:B,2,FALSE))) -> Exp-Goods & Services | K35: 0 | L35: 0 | M35: 0 | N35: 0 | O35: 0 | P35: IRP CLUB ADVISORS
A36: 1213 | B36: 522 | C36: 264 | D36: 2309 | E36: =D36&" - "&P36 -> 2309 - IRP CLUB ADVISORS | F36: EN | G36: 06 | J36: =IF(H36="",VLOOKUP(LEFT(F36,1),'Exp-Rev Categories'!A:B,2,FALSE),IF(ISNA(VLOOKUP(H36,'Exp-Rev Categories'!A:B,2,FALSE)),"Revenue",VLOOKUP(H36,'Exp-Rev Categories'!A:B,2,FALSE))) -> Exp-Goods & Services | K36: 0 | L36: 9.67 | M36: 0 | N36: -9.67 | O36: 0 | P36: IRP CLUB ADVISORS
A37: 1213 | B37: 522 | C37: 264 | D37: 2309 | E37: =D37&" - "&P37 -> 2309 - IRP CLUB ADVISORS | F37: EN | G37: 07 | J37: =IF(H37="",VLOOKUP(LEFT(F37,1),'Exp-Rev Categories'!A:B,2,FALSE),IF(ISNA(VLOOKUP(H37,'Exp-Rev Categories'!A:B,2,FALSE)),"Revenue",VLOOKUP(H37,'Exp-Rev Categories'!A:B,2,FALSE))) -> Exp-Goods & Services | K37: 0 | L37: 0.03 | M37: 0 | N37: -0.03 | O37: 0 | P37: IRP CLUB ADVISORS
A38: 1213 | B38: 522 | C38: 264 | D38: 2309 | E38: =D38&" - "&P38 -> 2309 - IRP CLUB ADVISORS | F38: EZ | G38: 30 | J38: =IF(H38="",VLOOKUP(LEFT(F38,1),'Exp-Rev Categories'!A:B,2,FALSE),IF(ISNA(VLOOKUP(H38,'Exp-Rev Categories'!A:B,2,FALSE)),"Revenue",VLOOKUP(H38,'Exp-Rev Categories'!A:B,2,FALSE))) -> Exp-Goods & Services | K38: 0 | L38: 874.85 | M38: 0 | N38: -874.85 | O38: 0 | P38: IRP CLUB ADVISORS
A39: 1213 | B39: 522 | C39: 264 | D39: 2310 | E39: =D39&" - "&P39 -> 2310 - IRP-GENERAL FUND | H39: 0782 | J39: =IF(H39="",VLOOKUP(LEFT(F39,1),'Exp-Rev Categories'!A:B,2,FALSE),IF(ISNA(VLOOKUP(H39,'Exp-Rev Categories'!A:B,2,FALSE)),"Revenue",VLOOKUP(H39,'Exp-Rev Categories'!A:B,2,FALSE))) -> Rev-Intra-Fund Transfer | K39: 0 | L39: -384041.9 | M39: 0 | N39: 384041.9 | O39: -162237 | P39: IRP-GENERAL FUND
A40: 1213 | B40: 522 | C40: 264 | D40: 2310 | E40: =D40&" - "&P40 -> 2310 - IRP-GENERAL FUND | H40: 0999 | J40: =IF(H40="",VLOOKUP(LEFT(F40,1),'Exp-Rev Categories'!A:B,2,FALSE),IF(ISNA(VLOOKUP(H40,'Exp-Rev Categories'!A:B,2,FALSE)),"Revenue",VLOOKUP(H40,'Exp-Rev Categories'!A:B,2,FALSE))) -> Carryforward | K40: 0 | L40: 179090.33 | M40: 0 | N40: -179090.33 | O40: 0 | P40: IRP-GENERAL FUND
A41: 1213 | B41: 522 | C41: 264 | D41: 2310 | E41: =D41&" - "&P41 -> 2310 - IRP-GENERAL FUND | F41: E | J41: =IF(H41="",VLOOKUP(LEFT(F41,1),'Exp-Rev Categories'!A:B,2,FALSE),IF(ISNA(VLOOKUP(H41,'Exp-Rev Categories'!A:B,2,FALSE)),"Revenue",VLOOKUP(H41,'Exp-Rev Categories'!A:B,2,FALSE))) -> Exp-Goods & Services | K41: 13893 | L41: 0 | M41: 0 | N41: 13893 | O41: 0 | P41: IRP-GENERAL FUND
A42: 1213 | B42: 522 | C42: 264 | D42: 2310 | E42: =D42&" - "&P42 -> 2310 - IRP-GENERAL FUND | F42: EA | G42: 00 | J42: =IF(H42="",VLOOKUP(LEFT(F42,1),'Exp-Rev Categories'!A:B,2,FALSE),IF(ISNA(VLOOKUP(H42,'Exp-Rev Categories'!A:B,2,FALSE)),"Revenue",VLOOKUP(H42,'Exp-Rev Categories'!A:B,2,FALSE))) -> Exp-Goods & Services | K42: 0 | L42: 2783.38 | M42: 0 | N42: -2783.38 | O42: 0 | P42: IRP-GENERAL FUND
A43: 1213 | B43: 522 | C43: 264 | D43: 2310 | E43: =D43&" - "&P43 -> 2310 - IRP-GENERAL FUND | F43: EZ | G43: 30 | J43: =IF(H43="",VLOOKUP(LEFT(F43,1),'Exp-Rev Categories'!A:B,2,FALSE),IF(ISNA(VLOOKUP(H43,'Exp-Rev Categories'!A:B,2,FALSE)),"Revenue",VLOOKUP(H43,'Exp-Rev Categories'!A:B,2,FALSE))) -> Exp-Goods & Services | K43: 0 | L43: 3118.22 | M43: 0 | N43: -3118.22 | O43: 0 | P43: IRP-GENERAL FUND
A44: 1213 | B44: 522 | C44: 264 | D44: 2310 | E44: =D44&" - "&P44 -> 2310 - IRP-GENERAL FUND | F44: G | J44: =IF(H44="",VLOOKUP(LEFT(F44,1),'Exp-Rev Categories'!A:B,2,FALSE),IF(ISNA(VLOOKUP(H44,'Exp-Rev Categories'!A:B,2,FALSE)),"Revenue",VLOOKUP(H44,'Exp-Rev Categories'!A:B,2,FALSE))) -> Exp-Travel | K44: 0 | L44: 0 | M44: 0 | N44: 0 | O44: 0 | P44: IRP-GENERAL FUND
A45: 1213 | B45: 522 | C45: 264 | D45: 2310 | E45: =D45&" - "&P45 -> 2310 - IRP-GENERAL FUND | F45: GD | G45: 30 | J45: =IF(H45="",VLOOKUP(LEFT(F45,1),'Exp-Rev Categories'!A:B,2,FALSE),IF(ISNA(VLOOKUP(H45,'Exp-Rev Categories'!A:B,2,FALSE)),"Revenue",VLOOKUP(H45,'Exp-Rev Categories'!A:B,2,FALSE))) -> Exp-Travel | K45: 0 | L45: 138.54 | M45: 0 | N45: -138.54 | O45: 0 | P45: IRP-GENERAL FUND
A46: 1213 | B46: 522 | C46: 264 | D46: 2310 | E46: =D46&" - "&P46 -> 2310 - IRP-GENERAL FUND | F46: GD | G46: 50 | J46: =IF(H46="",VLOOKUP(LEFT(F46,1),'Exp-Rev Categories'!A:B,2,FALSE),IF(ISNA(VLOOKUP(H46,'Exp-Rev Categories'!A:B,2,FALSE)),"Revenue",VLOOKUP(H46,'Exp-Rev Categories'!A:B,2,FALSE))) -> Exp-Travel | K46: 0 | L46: 10 | M46: 0 | N46: -10 | O46: 0 | P46: IRP-GENERAL FUND
A47: 1213 | B47: 522 | C47: 264 | D47: 2311 | E47: =D47&" - "&P47 -> 2311 - PRES SPEAKER SERIES | F47: AU | G47: 01 | J47: =IF(H47="",VLOOKUP(LEFT(F47,1),'Exp-Rev Categories'!A:B,2,FALSE),IF(ISNA(VLOOKUP(H47,'Exp-Rev Categories'!A:B,2,FALSE)),"Revenue",VLOOKUP(H47,'Exp-Rev Categories'!A:B,2,FALSE))) -> Exp-Salaries & Wages | K47: 0 | L47: 0 | M47: 0 | N47: 0 | O47: 0 | P47: PRES SPEAKER SERIES
A48: 1213 | B48: 522 | C48: 264 | D48: 2311 | E48: =D48&" - "&P48 -> 2311 - PRES SPEAKER SERIES | F48: B | J48: =IF(H48="",VLOOKUP(LEFT(F48,1),'Exp-Rev Categories'!A:B,2,FALSE),IF(ISNA(VLOOKUP(H48,'Exp-Rev Categories'!A:B,2,FALSE)),"Revenue",VLOOKUP(H48,'Exp-Rev Categories'!A:B,2,FALSE))) -> Exp-Benefits | K48: 0 | L48: 0 | M48: 0 | N48: 0 | O48: 0 | P48: PRES SPEAKER SERIES
A49: 1213 | B49: 522 | C49: 264 | D49: 2311 | E49: =D49&" - "&P49 -> 2311 - PRES SPEAKER SERIES | F49: BB | J49: =IF(H49="",VLOOKUP(LEFT(F49,1),'Exp-Rev Categories'!A:B,2,FALSE),IF(ISNA(VLOOKUP(H49,'Exp-Rev Categories'!A:B,2,FALSE)),"Revenue",VLOOKUP(H49,'Exp-Rev Categories'!A:B,2,FALSE))) -> Exp-Benefits | K49: 0 | L49: -0.09 | M49: 0 | N49: 0.09 | O49: 0 | P49: PRES SPEAKER SERIES
A50: 1213 | B50: 522 | C50: 264 | D50: 2311 | E50: =D50&" - "&P50 -> 2311 - PRES SPEAKER SERIES | F50: E | J50: =IF(H50="",VLOOKUP(LEFT(F50,1),'Exp-Rev Categories'!A:B,2,FALSE),IF(ISNA(VLOOKUP(H50,'Exp-Rev Categories'!A:B,2,FALSE)),"Revenue",VLOOKUP(H50,'Exp-Rev Categories'!A:B,2,FALSE))) -> Exp-Goods & Services | K50: 0 | L50: 0 | M50: 0 | N50: 0 | O50: 0 | P50: PRES SPEAKER SERIES
A51: 1213 | B51: 522 | C51: 264 | D51: 2312 | E51: =D51&" - "&P51 -> 2312 - ADA ACCESSIBILITY | F51: AD | G51: 05 | J51: =IF(H51="",VLOOKUP(LEFT(F51,1),'Exp-Rev Categories'!A:B,2,FALSE),IF(ISNA(VLOOKUP(H51,'Exp-Rev Categories'!A:B,2,FALSE)),"Revenue",VLOOKUP(H51,'Exp-Rev Categories'!A:B,2,FALSE))) -> Exp-Salaries & Wages | K51: 909 | L51: 636.23 | M51: 0 | N51: 272.77 | O51: 0 | P51: ADA ACCESSIBILITY
A52: 1213 | B52: 522 | C52: 264 | D52: 2312 | E52: =D52&" - "&P52 -> 2312 - ADA ACCESSIBILITY | F52: B | J52: =IF(H52="",VLOOKUP(LEFT(F52,1),'Exp-Rev Categories'!A:B,2,FALSE),IF(ISNA(VLOOKUP(H52,'Exp-Rev Categories'!A:B,2,FALSE)),"Revenue",VLOOKUP(H52,'Exp-Rev Categories'!A:B,2,FALSE))) -> Exp-Benefits | K52: 91 | L52: 0 | M52: 0 | N52: 91 | O52: 0 | P52: ADA ACCESSIBILITY
A53: 1213 | B53: 522 | C53: 264 | D53: 2312 | E53: =D53&" - "&P53 -> 2312 - ADA ACCESSIBILITY | F53: BA | J53: =IF(H53="",VLOOKUP(LEFT(F53,1),'Exp-Rev Categories'!A:B,2,FALSE),IF(ISNA(VLOOKUP(H53,'Exp-Rev Categories'!A:B,2,FALSE)),"Revenue",VLOOKUP(H53,'Exp-Rev Categories'!A:B,2,FALSE))) -> Exp-Benefits | K53: 0 | L53: 48.54 | M53: 0 | N53: -48.54 | O53: 0 | P53: ADA ACCESSIBILITY
A54: 1213 | B54: 522 | C54: 264 | D54: 2312 | E54: =D54&" - "&P54 -> 2312 - ADA ACCESSIBILITY | F54: BB | J54: =IF(H54="",VLOOKUP(LEFT(F54,1),'Exp-Rev Categories'!A:B,2,FALSE),IF(ISNA(VLOOKUP(H54,'Exp-Rev Categories'!A:B,2,FALSE)),"Revenue",VLOOKUP(H54,'Exp-Rev Categories'!A:B,2,FALSE))) -> Exp-Benefits | K54: 0 | L54: 9.15 | M54: 0 | N54: -9.15 | O54: 0 | P54: ADA ACCESSIBILITY
A55: 1213 | B55: 522 | C55: 264 | D55: 2312 | E55: =D55&" - "&P55 -> 2312 - ADA ACCESSIBILITY | F55: BC | J55: =IF(H55="",VLOOKUP(LEFT(F55,1),'Exp-Rev Categories'!A:B,2,FALSE),IF(ISNA(VLOOKUP(H55,'Exp-Rev Categories'!A:B,2,FALSE)),"Revenue",VLOOKUP(H55,'Exp-Rev Categories'!A:B,2,FALSE))) -> Exp-Benefits | K55: 0 | L55: 9.3 | M55: 0 | N55: -9.3 | O55: 0 | P55: ADA ACCESSIBILITY
A56: 1213 | B56: 522 | C56: 264 | D56: 2312 | E56: =D56&" - "&P56 -> 2312 - ADA ACCESSIBILITY | F56: BF | J56: =IF(H56="",VLOOKUP(LEFT(F56,1),'Exp-Rev Categories'!A:B,2,FALSE),IF(ISNA(VLOOKUP(H56,'Exp-Rev Categories'!A:B,2,FALSE)),"Revenue",VLOOKUP(H56,'Exp-Rev Categories'!A:B,2,FALSE))) -> Exp-Benefits | K56: 0 | L56: 4.58 | M56: 0 | N56: -4.58 | O56: 0 | P56: ADA ACCESSIBILITY
A57: 1213 | B57: 522 | C57: 264 | D57: 2312 | E57: =D57&" - "&P57 -> 2312 - ADA ACCESSIBILITY | F57: E | J57: =IF(H57="",VLOOKUP(LEFT(F57,1),'Exp-Rev Categories'!A:B,2,FALSE),IF(ISNA(VLOOKUP(H57,'Exp-Rev Categories'!A:B,2,FALSE)),"Revenue",VLOOKUP(H57,'Exp-Rev Categories'!A:B,2,FALSE))) -> Exp-Goods & Services | K57: 0 | L57: 0 | M57: 0 | N57: 0 | O57: 0 | P57: ADA ACCESSIBILITY
A58: 1213 | B58: 522 | C58: 264 | D58: 2313 | E58: =D58&" - "&P58 -> 2313 - HLTH INFO MANAGEMNT | H58: 0499 | I58: 8I | J58: =IF(H58="",VLOOKUP(LEFT(F58,1),'Exp-Rev Categories'!A:B,2,FALSE),IF(ISNA(VLOOKUP(H58,'Exp-Rev Categories'!A:B,2,FALSE)),"Revenue",VLOOKUP(H58,'Exp-Rev Categories'!A:B,2,FALSE))) -> Revenue | K58: 0 | L58: 0 | M58: 0 | N58: 0 | O58: 0 | P58: HLTH INFO MANAGEMNT
A59: 1213 | B59: 522 | C59: 264 | D59: 2313 | E59: =D59&" - "&P59 -> 2313 - HLTH INFO MANAGEMNT | F59: E | J59: =IF(H59="",VLOOKUP(LEFT(F59,1),'Exp-Rev Categories'!A:B,2,FALSE),IF(ISNA(VLOOKUP(H59,'Exp-Rev Categories'!A:B,2,FALSE)),"Revenue",VLOOKUP(H59,'Exp-Rev Categories'!A:B,2,FALSE))) -> Exp-Goods & Services | K59: 2060 | L59: 0 | M59: 0 | N59: 2060 | O59: 0 | P59: HLTH INFO MANAGEMNT
A60: 1213 | B60: 522 | C60: 264 | D60: 2313 | E60: =D60&" - "&P60 -> 2313 - HLTH INFO MANAGEMNT | F60: G | J60: =IF(H60="",VLOOKUP(LEFT(F60,1),'Exp-Rev Categories'!A:B,2,FALSE),IF(ISNA(VLOOKUP(H60,'Exp-Rev Categories'!A:B,2,FALSE)),"Revenue",VLOOKUP(H60,'Exp-Rev Categories'!A:B,2,FALSE))) -> Exp-Travel | K60: 0 | L60: 0 | M60: 0 | N60: 0 | O60: 0 | P60: HLTH INFO MANAGEMNT
A61: 1213 | B61: 522 | C61: 264 | D61: 2313 | E61: =D61&" - "&P61 -> 2313 - HLTH INFO MANAGEMNT | F61: NB | J61: =IF(H61="",VLOOKUP(LEFT(F61,1),'Exp-Rev Categories'!A:B,2,FALSE),IF(ISNA(VLOOKUP(H61,'Exp-Rev Categories'!A:B,2,FALSE)),"Revenue",VLOOKUP(H61,'Exp-Rev Categories'!A:B,2,FALSE))) -> Exp-Grants/Scholarships | K61: 0 | L61: 0 | M61: 0 | N61: 0 | O61: 0 | P61: HLTH INFO MANAGEMNT
A62: 1213 | B62: 522 | C62: 264 | D62: 2314 | E62: =D62&" - "&P62 -> 2314 - AMER DESGN DRFTG S A | H62: 0499 | I62: 8U | J62: =IF(H62="",VLOOKUP(LEFT(F62,1),'Exp-Rev Categories'!A:B,2,FALSE),IF(ISNA(VLOOKUP(H62,'Exp-Rev Categories'!A:B,2,FALSE)),"Revenue",VLOOKUP(H62,'Exp-Rev Categories'!A:B,2,FALSE))) -> Revenue | K62: 0 | L62: -73.5 | M62: 0 | N62: 73.5 | O62: 0 | P62: AMER DESGN DRFTG S A
A63: 1213 | B63: 522 | C63: 264 | D63: 2314 | E63: =D63&" - "&P63 -> 2314 - AMER DESGN DRFTG S A | H63: 0622 | J63: =IF(H63="",VLOOKUP(LEFT(F63,1),'Exp-Rev Categories'!A:B,2,FALSE),IF(ISNA(VLOOKUP(H63,'Exp-Rev Categories'!A:B,2,FALSE)),"Revenue",VLOOKUP(H63,'Exp-Rev Categories'!A:B,2,FALSE))) -> Rev-Fund Transfers - Out | K63: 0 | L63: 100 | M63: 0 | N63: -100 | O63: 0 | P63: AMER DESGN DRFTG S A
A64: 1213 | B64: 522 | C64: 264 | D64: 2314 | E64: =D64&" - "&P64 -> 2314 - AMER DESGN DRFTG S A | F64: E | J64: =IF(H64="",VLOOKUP(LEFT(F64,1),'Exp-Rev Categories'!A:B,2,FALSE),IF(ISNA(VLOOKUP(H64,'Exp-Rev Categories'!A:B,2,FALSE)),"Revenue",VLOOKUP(H64,'Exp-Rev Categories'!A:B,2,FALSE))) -> Exp-Goods & Services | K64: 16295 | L64: 0 | M64: 0 | N64: 16295 | O64: 0 | P64: AMER DESGN DRFTG S A
A65: 1213 | B65: 522 | C65: 264 | D65: 2314 | E65: =D65&" - "&P65 -> 2314 - AMER DESGN DRFTG S A | F65: EA | G65: 00 | J65: =IF(H65="",VLOOKUP(LEFT(F65,1),'Exp-Rev Categories'!A:B,2,FALSE),IF(ISNA(VLOOKUP(H65,'Exp-Rev Categories'!A:B,2,FALSE)),"Revenue",VLOOKUP(H65,'Exp-Rev Categories'!A:B,2,FALSE))) -> Exp-Goods & Services | K65: 0 | L65: 457.34 | M65: 0 | N65: -457.34 | O65: 0 | P65: AMER DESGN DRFTG S A
A66: 1213 | B66: 522 | C66: 264 | D66: 2314 | E66: =D66&" - "&P66 -> 2314 - AMER DESGN DRFTG S A | F66: EG | G66: 80 | J66: =IF(H66="",VLOOKUP(LEFT(F66,1),'Exp-Rev Categories'!A:B,2,FALSE),IF(ISNA(VLOOKUP(H66,'Exp-Rev Categories'!A:B,2,FALSE)),"Revenue",VLOOKUP(H66,'Exp-Rev Categories'!A:B,2,FALSE))) -> Exp-Goods & Services | K66: 0 | L66: 25 | M66: 0 | N66: -25 | O66: 0 | P66: AMER DESGN DRFTG S A
A67: 1213 | B67: 522 | C67: 264 | D67: 2314 | E67: =D67&" - "&P67 -> 2314 - AMER DESGN DRFTG S A | F67: EG | G67: RG | J67: =IF(H67="",VLOOKUP(LEFT(F67,1),'Exp-Rev Categories'!A:B,2,FALSE),IF(ISNA(VLOOKUP(H67,'Exp-Rev Categories'!A:B,2,FALSE)),"Revenue",VLOOKUP(H67,'Exp-Rev Categories'!A:B,2,FALSE))) -> Exp-Goods & Services | K67: 0 | L67: 3525 | M67: 0 | N67: -3525 | O67: 0 | P67: AMER DESGN DRFTG S A
A68: 1213 | B68: 522 | C68: 264 | D68: 2314 | E68: =D68&" - "&P68 -> 2314 - AMER DESGN DRFTG S A | F68: EY | G68: 00 | J68: =IF(H68="",VLOOKUP(LEFT(F68,1),'Exp-Rev Categories'!A:B,2,FALSE),IF(ISNA(VLOOKUP(H68,'Exp-Rev Categories'!A:B,2,FALSE)),"Revenue",VLOOKUP(H68,'Exp-Rev Categories'!A:B,2,FALSE))) -> Exp-Goods & Services | K68: 0 | L68: 32.6 | M68: 0 | N68: -32.6 | O68: 0 | P68: AMER DESGN DRFTG S A
A69: 1213 | B69: 522 | C69: 264 | D69: 2314 | E69: =D69&" - "&P69 -> 2314 - AMER DESGN DRFTG S A | F69: EZ | G69: 00 | J69: =IF(H69="",VLOOKUP(LEFT(F69,1),'Exp-Rev Categories'!A:B,2,FALSE),IF(ISNA(VLOOKUP(H69,'Exp-Rev Categories'!A:B,2,FALSE)),"Revenue",VLOOKUP(H69,'Exp-Rev Categories'!A:B,2,FALSE))) -> Exp-Goods & Services | K69: 0 | L69: 570 | M69: 0 | N69: -570 | O69: 0 | P69: AMER DESGN DRFTG S A
A70: 1213 | B70: 522 | C70: 264 | D70: 2314 | E70: =D70&" - "&P70 -> 2314 - AMER DESGN DRFTG S A | F70: EZ | G70: 30 | J70: =IF(H70="",VLOOKUP(LEFT(F70,1),'Exp-Rev Categories'!A:B,2,FALSE),IF(ISNA(VLOOKUP(H70,'Exp-Rev Categories'!A:B,2,FALSE)),"Revenue",VLOOKUP(H70,'Exp-Rev Categories'!A:B,2,FALSE))) -> Exp-Goods & Services | K70: 0 | L70: 221.53 | M70: 0 | N70: -221.53 | O70: 0 | P70: AMER DESGN DRFTG S A
A71: 1213 | B71: 522 | C71: 264 | D71: 2314 | E71: =D71&" - "&P71 -> 2314 - AMER DESGN DRFTG S A | F71: G | J71: =IF(H71="",VLOOKUP(LEFT(F71,1),'Exp-Rev Categories'!A:B,2,FALSE),IF(ISNA(VLOOKUP(H71,'Exp-Rev Categories'!A:B,2,FALSE)),"Revenue",VLOOKUP(H71,'Exp-Rev Categories'!A:B,2,FALSE))) -> Exp-Travel | K71: 0 | L71: 0 | M71: 0 | N71: 0 | O71: 0 | P71: AMER DESGN DRFTG S A
A72: 1213 | B72: 522 | C72: 264 | D72: 2314 | E72: =D72&" - "&P72 -> 2314 - AMER DESGN DRFTG S A | F72: GD | G72: 00 | J72: =IF(H72="",VLOOKUP(LEFT(F72,1),'Exp-Rev Categories'!A:B,2,FALSE),IF(ISNA(VLOOKUP(H72,'Exp-Rev Categories'!A:B,2,FALSE)),"Revenue",VLOOKUP(H72,'Exp-Rev Categories'!A:B,2,FALSE))) -> Exp-Travel | K72: 0 | L72: 149.11 | M72: 0 | N72: -149.11 | O72: 0 | P72: AMER DESGN DRFTG S A
A73: 1213 | B73: 522 | C73: 264 | D73: 2314 | E73: =D73&" - "&P73 -> 2314 - AMER DESGN DRFTG S A | F73: GD | G73: 60 | J73: =IF(H73="",VLOOKUP(LEFT(F73,1),'Exp-Rev Categories'!A:B,2,FALSE),IF(ISNA(VLOOKUP(H73,'Exp-Rev Categories'!A:B,2,FALSE)),"Revenue",VLOOKUP(H73,'Exp-Rev Categories'!A:B,2,FALSE))) -> Exp-Travel | K73: 0 | L73: 39.23 | M73: 0 | N73: -39.23 | O73: 0 | P73: AMER DESGN DRFTG S A
A74: 1213 | B74: 522 | C74: 264 | D74: 2314 | E74: =D74&" - "&P74 -> 2314 - AMER DESGN DRFTG S A | F74: GF | G74: 00 | J74: =IF(H74="",VLOOKUP(LEFT(F74,1),'Exp-Rev Categories'!A:B,2,FALSE),IF(ISNA(VLOOKUP(H74,'Exp-Rev Categories'!A:B,2,FALSE)),"Revenue",VLOOKUP(H74,'Exp-Rev Categories'!A:B,2,FALSE))) -> Exp-Travel | K74: 0 | L74: 2603.77 | M74: 0 | N74: -2603.77 | O74: 0 | P74: AMER DESGN DRFTG S A
A75: 1213 | B75: 522 | C75: 264 | D75: 2314 | E75: =D75&" - "&P75 -> 2314 - AMER DESGN DRFTG S A | F75: GG | G75: 00 | J75: =IF(H75="",VLOOKUP(LEFT(F75,1),'Exp-Rev Categories'!A:B,2,FALSE),IF(ISNA(VLOOKUP(H75,'Exp-Rev Categories'!A:B,2,FALSE)),"Revenue",VLOOKUP(H75,'Exp-Rev Categories'!A:B,2,FALSE))) -> Exp-Travel | K75: 0 | L75: 2217.6 | M75: 0 | N75: -2217.6 | O75: 0 | P75: AMER DESGN DRFTG S A
A76: 1213 | B76: 522 | C76: 264 | D76: 2314 | E76: =D76&" - "&P76 -> 2314 - AMER DESGN DRFTG S A | F76: J | J76: =IF(H76="",VLOOKUP(LEFT(F76,1),'Exp-Rev Categories'!A:B,2,FALSE),IF(ISNA(VLOOKUP(H76,'Exp-Rev Categories'!A:B,2,FALSE)),"Revenue",VLOOKUP(H76,'Exp-Rev Categories'!A:B,2,FALSE))) -> Exp-Equipment | K76: 0 | L76: 0 | M76: 0 | N76: 0 | O76: 0 | P76: AMER DESGN DRFTG S A
A77: 1213 | B77: 522 | C77: 264 | D77: 2314 | E77: =D77&" - "&P77 -> 2314 - AMER DESGN DRFTG S A | F77: JA | G77: 00 | J77: =IF(H77="",VLOOKUP(LEFT(F77,1),'Exp-Rev Categories'!A:B,2,FALSE),IF(ISNA(VLOOKUP(H77,'Exp-Rev Categories'!A:B,2,FALSE)),"Revenue",VLOOKUP(H77,'Exp-Rev Categories'!A:B,2,FALSE))) -> Exp-Equipment | K77: 0 | L77: 6325.62 | M77: 0 | N77: -6325.62 | O77: 0 | P77: AMER DESGN DRFTG S A
A78: 1213 | B78: 522 | C78: 264 | D78: 2319 | E78: =D78&" - "&P78 -> 2319 - SKILLS USA (VICA) | H78: 0499 | I78: 6V | J78: =IF(H78="",VLOOKUP(LEFT(F78,1),'Exp-Rev Categories'!A:B,2,FALSE),IF(ISNA(VLOOKUP(H78,'Exp-Rev Categories'!A:B,2,FALSE)),"Revenue",VLOOKUP(H78,'Exp-Rev Categories'!A:B,2,FALSE))) -> Revenue | K78: 0 | L78: 0 | M78: 0 | N78: 0 | O78: 0 | P78: SKILLS USA (VICA)
A79: 1213 | B79: 522 | C79: 264 | D79: 2319 | E79: =D79&" - "&P79 -> 2319 - SKILLS USA (VICA) | H79: 0782 | J79: =IF(H79="",VLOOKUP(LEFT(F79,1),'Exp-Rev Categories'!A:B,2,FALSE),IF(ISNA(VLOOKUP(H79,'Exp-Rev Categories'!A:B,2,FALSE)),"Revenue",VLOOKUP(H79,'Exp-Rev Categories'!A:B,2,FALSE))) -> Rev-Intra-Fund Transfer | K79: 0 | L79: 0 | M79: 0 | N79: 0 | O79: 0 | P79: SKILLS USA (VICA)
A80: 1213 | B80: 522 | C80: 264 | D80: 2319 | E80: =D80&" - "&P80 -> 2319 - SKILLS USA (VICA) | F80: B | J80: =IF(H80="",VLOOKUP(LEFT(F80,1),'Exp-Rev Categories'!A:B,2,FALSE),IF(ISNA(VLOOKUP(H80,'Exp-Rev Categories'!A:B,2,FALSE)),"Revenue",VLOOKUP(H80,'Exp-Rev Categories'!A:B,2,FALSE))) -> Exp-Benefits | K80: 0 | L80: 0 | M80: 0 | N80: 0 | O80: 0 | P80: SKILLS USA (VICA)
A81: 1213 | B81: 522 | C81: 264 | D81: 2319 | E81: =D81&" - "&P81 -> 2319 - SKILLS USA (VICA) | F81: E | J81: =IF(H81="",VLOOKUP(LEFT(F81,1),'Exp-Rev Categories'!A:B,2,FALSE),IF(ISNA(VLOOKUP(H81,'Exp-Rev Categories'!A:B,2,FALSE)),"Revenue",VLOOKUP(H81,'Exp-Rev Categories'!A:B,2,FALSE))) -> Exp-Goods & Services | K81: 31563 | L81: 0 | M81: 0 | N81: 31563 | O81: 0 | P81: SKILLS USA (VICA)
A82: 1213 | B82: 522 | C82: 264 | D82: 2319 | E82: =D82&" - "&P82 -> 2319 - SKILLS USA (VICA) | F82: EA | G82: 00 | J82: =IF(H82="",VLOOKUP(LEFT(F82,1),'Exp-Rev Categories'!A:B,2,FALSE),IF(ISNA(VLOOKUP(H82,'Exp-Rev Categories'!A:B,2,FALSE)),"Revenue",VLOOKUP(H82,'Exp-Rev Categories'!A:B,2,FALSE))) -> Exp-Goods & Services | K82: 0 | L82: 1576.14 | M82: 0 | N82: -1576.14 | O82: 0 | P82: SKILLS USA (VICA)
A83: 1213 | B83: 522 | C83: 264 | D83: 2319 | E83: =D83&" - "&P83 -> 2319 - SKILLS USA (VICA) | F83: EB | G83: 40 | J83: =IF(H83="",VLOOKUP(LEFT(F83,1),'Exp-Rev Categories'!A:B,2,FALSE),IF(ISNA(VLOOKUP(H83,'Exp-Rev Categories'!A:B,2,FALSE)),"Revenue",VLOOKUP(H83,'Exp-Rev Categories'!A:B,2,FALSE))) -> Exp-Goods & Services | K83: 0 | L83: 43.5 | M83: 0 | N83: -43.5 | O83: 0 | P83: SKILLS USA (VICA)
A84: 1213 | B84: 522 | C84: 264 | D84: 2319 | E84: =D84&" - "&P84 -> 2319 - SKILLS USA (VICA) | F84: EG | G84: 70 | J84: =IF(H84="",VLOOKUP(LEFT(F84,1),'Exp-Rev Categories'!A:B,2,FALSE),IF(ISNA(VLOOKUP(H84,'Exp-Rev Categories'!A:B,2,FALSE)),"Revenue",VLOOKUP(H84,'Exp-Rev Categories'!A:B,2,FALSE))) -> Exp-Goods & Services | K84: 0 | L84: 172 | M84: 0 | N84: -172 | O84: 0 | P84: SKILLS USA (VICA)
A85: 1213 | B85: 522 | C85: 264 | D85: 2319 | E85: =D85&" - "&P85 -> 2319 - SKILLS USA (VICA) | F85: EG | G85: RG | J85: =IF(H85="",VLOOKUP(LEFT(F85,1),'Exp-Rev Categories'!A:B,2,FALSE),IF(ISNA(VLOOKUP(H85,'Exp-Rev Categories'!A:B,2,FALSE)),"Revenue",VLOOKUP(H85,'Exp-Rev Categories'!A:B,2,FALSE))) -> Exp-Goods & Services | K85: 0 | L85: 2865 | M85: 0 | N85: -2865 | O85: 0 | P85: SKILLS USA (VICA)
A86: 1213 | B86: 522 | C86: 264 | D86: 2319 | E86: =D86&" - "&P86 -> 2319 - SKILLS USA (VICA) | F86: EZ | G86: 00 | J86: =IF(H86="",VLOOKUP(LEFT(F86,1),'Exp-Rev Categories'!A:B,2,FALSE),IF(ISNA(VLOOKUP(H86,'Exp-Rev Categories'!A:B,2,FALSE)),"Revenue",VLOOKUP(H86,'Exp-Rev Categories'!A:B,2,FALSE))) -> Exp-Goods & Services | K86: 0 | L86: 0 | M86: 0 | N86: 0 | O86: 0 | P86: SKILLS USA (VICA)
A87: 1213 | B87: 522 | C87: 264 | D87: 2319 | E87: =D87&" - "&P87 -> 2319 - SKILLS USA (VICA) | F87: EZ | G87: 20 | J87: =IF(H87="",VLOOKUP(LEFT(F87,1),'Exp-Rev Categories'!A:B,2,FALSE),IF(ISNA(VLOOKUP(H87,'Exp-Rev Categories'!A:B,2,FALSE)),"Revenue",VLOOKUP(H87,'Exp-Rev Categories'!A:B,2,FALSE))) -> Exp-Goods & Services | K87: 0 | L87: 8.48 | M87: 0 | N87: -8.48 | O87: 0 | P87: SKILLS USA (VICA)
A88: 1213 | B88: 522 | C88: 264 | D88: 2319 | E88: =D88&" - "&P88 -> 2319 - SKILLS USA (VICA) | F88: EZ | G88: 30 | J88: =IF(H88="",VLOOKUP(LEFT(F88,1),'Exp-Rev Categories'!A:B,2,FALSE),IF(ISNA(VLOOKUP(H88,'Exp-Rev Categories'!A:B,2,FALSE)),"Revenue",VLOOKUP(H88,'Exp-Rev Categories'!A:B,2,FALSE))) -> Exp-Goods & Services | K88: 0 | L88: 507.02 | M88: 0 | N88: -507.02 | O88: 0 | P88: SKILLS USA (VICA)
A89: 1213 | B89: 522 | C89: 264 | D89: 2319 | E89: =D89&" - "&P89 -> 2319 - SKILLS USA (VICA) | F89: G | J89: =IF(H89="",VLOOKUP(LEFT(F89,1),'Exp-Rev Categories'!A:B,2,FALSE),IF(ISNA(VLOOKUP(H89,'Exp-Rev Categories'!A:B,2,FALSE)),"Revenue",VLOOKUP(H89,'Exp-Rev Categories'!A:B,2,FALSE))) -> Exp-Travel | K89: 0 | L89: 0 | M89: 0 | N89: 0 | O89: 0 | P89: SKILLS USA (VICA)
A90: 1213 | B90: 522 | C90: 264 | D90: 2319 | E90: =D90&" - "&P90 -> 2319 - SKILLS USA (VICA) | F90: GA | G90: 00 | J90: =IF(H90="",VLOOKUP(LEFT(F90,1),'Exp-Rev Categories'!A:B,2,FALSE),IF(ISNA(VLOOKUP(H90,'Exp-Rev Categories'!A:B,2,FALSE)),"Revenue",VLOOKUP(H90,'Exp-Rev Categories'!A:B,2,FALSE))) -> Exp-Travel | K90: 0 | L90: 4429.08 | M90: 0 | N90: -4429.08 | O90: 0 | P90: SKILLS USA (VICA)
A91: 1213 | B91: 522 | C91: 264 | D91: 2319 | E91: =D91&" - "&P91 -> 2319 - SKILLS USA (VICA) | F91: GD | G91: 00 | J91: =IF(H91="",VLOOKUP(LEFT(F91,1),'Exp-Rev Categories'!A:B,2,FALSE),IF(ISNA(VLOOKUP(H91,'Exp-Rev Categories'!A:B,2,FALSE)),"Revenue",VLOOKUP(H91,'Exp-Rev Categories'!A:B,2,FALSE))) -> Exp-Travel | K91: 0 | L91: 647.14 | M91: 0 | N91: -647.14 | O91: 0 | P91: SKILLS USA (VICA)
A92: 1213 | B92: 522 | C92: 264 | D92: 2319 | E92: =D92&" - "&P92 -> 2319 - SKILLS USA (VICA) | F92: GD | G92: 10 | J92: =IF(H92="",VLOOKUP(LEFT(F92,1),'Exp-Rev Categories'!A:B,2,FALSE),IF(ISNA(VLOOKUP(H92,'Exp-Rev Categories'!A:B,2,FALSE)),"Revenue",VLOOKUP(H92,'Exp-Rev Categories'!A:B,2,FALSE))) -> Exp-Travel | K92: 0 | L92: 0 | M92: 0 | N92: 0 | O92: 0 | P92: SKILLS USA (VICA)
A93: 1213 | B93: 522 | C93: 264 | D93: 2319 | E93: =D93&" - "&P93 -> 2319 - SKILLS USA (VICA) | F93: GD | G93: 30 | J93: =IF(H93="",VLOOKUP(LEFT(F93,1),'Exp-Rev Categories'!A:B,2,FALSE),IF(ISNA(VLOOKUP(H93,'Exp-Rev Categories'!A:B,2,FALSE)),"Revenue",VLOOKUP(H93,'Exp-Rev Categories'!A:B,2,FALSE))) -> Exp-Travel | K93: 0 | L93: 1351.05 | M93: 0 | N93: -1351.05 | O93: 0 | P93: SKILLS USA (VICA)
A94: 1213 | B94: 522 | C94: 264 | D94: 2319 | E94: =D94&" - "&P94 -> 2319 - SKILLS USA (VICA) | F94: GD | G94: 50 | J94: =IF(H94="",VLOOKUP(LEFT(F94,1),'Exp-Rev Categories'!A:B,2,FALSE),IF(ISNA(VLOOKUP(H94,'Exp-Rev Categories'!A:B,2,FALSE)),"Revenue",VLOOKUP(H94,'Exp-Rev Categories'!A:B,2,FALSE))) -> Exp-Travel | K94: 0 | L94: 1056.6 | M94: 0 | N94: -1056.6 | O94: 0 | P94: SKILLS USA (VICA)
A95: 1213 | B95: 522 | C95: 264 | D95: 2319 | E95: =D95&" - "&P95 -> 2319 - SKILLS USA (VICA) | F95: GD | G95: 70 | J95: =IF(H95="",VLOOKUP(LEFT(F95,1),'Exp-Rev Categories'!A:B,2,FALSE),IF(ISNA(VLOOKUP(H95,'Exp-Rev Categories'!A:B,2,FALSE)),"Revenue",VLOOKUP(H95,'Exp-Rev Categories'!A:B,2,FALSE))) -> Exp-Travel | K95: 0 | L95: 824.58 | M95: 0 | N95: -824.58 | O95: 0 | P95: SKILLS USA (VICA)
A96: 1213 | B96: 522 | C96: 264 | D96: 2319 | E96: =D96&" - "&P96 -> 2319 - SKILLS USA (VICA) | F96: GF | G96: 00 | J96: =IF(H96="",VLOOKUP(LEFT(F96,1),'Exp-Rev Categories'!A:B,2,FALSE),IF(ISNA(VLOOKUP(H96,'Exp-Rev Categories'!A:B,2,FALSE)),"Revenue",VLOOKUP(H96,'Exp-Rev Categories'!A:B,2,FALSE))) -> Exp-Travel | K96: 0 | L96: 8356 | M96: 0 | N96: -8356 | O96: 0 | P96: SKILLS USA (VICA)
A97: 1213 | B97: 522 | C97: 264 | D97: 2319 | E97: =D97&" - "&P97 -> 2319 - SKILLS USA (VICA) | F97: GG | G97: 00 | J97: =IF(H97="",VLOOKUP(LEFT(F97,1),'Exp-Rev Categories'!A:B,2,FALSE),IF(ISNA(VLOOKUP(H97,'Exp-Rev Categories'!A:B,2,FALSE)),"Revenue",VLOOKUP(H97,'Exp-Rev Categories'!A:B,2,FALSE))) -> Exp-Travel | K97: 0 | L97: 5647.7 | M97: 0 | N97: -5647.7 | O97: 0 | P97: SKILLS USA (VICA)
A98: 1213 | B98: 522 | C98: 264 | D98: 2319 | E98: =D98&" - "&P98 -> 2319 - SKILLS USA (VICA) | F98: KA | J98: =IF(H98="",VLOOKUP(LEFT(F98,1),'Exp-Rev Categories'!A:B,2,FALSE),IF(ISNA(VLOOKUP(H98,'Exp-Rev Categories'!A:B,2,FALSE)),"Revenue",VLOOKUP(H98,'Exp-Rev Categories'!A:B,2,FALSE))) -> Exp-Computer Equipment | K98: 0 | L98: 2878.35 | M98: 0 | N98: -2878.35 | O98: 0 | P98: SKILLS USA (VICA)
A99: 1213 | B99: 522 | C99: 264 | D99: 2319 | E99: =D99&" - "&P99 -> 2319 - SKILLS USA (VICA) | F99: NB | J99: =IF(H99="",VLOOKUP(LEFT(F99,1),'Exp-Rev Categories'!A:B,2,FALSE),IF(ISNA(VLOOKUP(H99,'Exp-Rev Categories'!A:B,2,FALSE)),"Revenue",VLOOKUP(H99,'Exp-Rev Categories'!A:B,2,FALSE))) -> Exp-Grants/Scholarships | K99: 0 | L99: 0 | M99: 0 | N99: 0 | O99: 0 | P99: SKILLS USA (VICA)
A100: 1213 | B100: 522 | C100: 264 | D100: 2324 | E100: =D100&" - "&P100 -> 2324 - WRITERS ON THE STORM | F100: G | J100: =IF(H100="",VLOOKUP(LEFT(F100,1),'Exp-Rev Categories'!A:B,2,FALSE),IF(ISNA(VLOOKUP(H100,'Exp-Rev Categories'!A:B,2,FALSE)),"Revenue",VLOOKUP(H100,'Exp-Rev Categories'!A:B,2,FALSE))) -> Exp-Travel | K100: 0 | L100: 0 | M100: 0 | N100: 0 | O100: 0 | P100: WRITERS ON THE STORM
...

Sheet Exp-Rev Categories
A1: Obj/Src | B1: Title | C1: Line
A2: 0999 | B2: Carryforward | C2: 1
B3: Revenue | C3: 2
A4: 0782 | B4: Rev-Intra-Fund Transfer | C4: 3
A5: 0621 | B5: Rev-Fund Transfers - In | C5: 4
A6: 0622 | B6: Rev-Fund Transfers - Out | C6: 5
A7: A | B7: Exp-Salaries & Wages | C7: 6
A8: B | B8: Exp-Benefits | C8: 7
A9: C | B9: Exp-Personal Service Contracts | C9: 8
A10: E | B10: Exp-Goods & Services | C10: 9
A11: G | B11: Exp-Travel | C11: 10
A12: J | B12: Exp-Equipment | C12: 11
A13: K | B13: Exp-Computer Equipment | C13: 12
A14: N | B14: Exp-Grants/Scholarships | C14: 13
A15: T | B15: Exp-Transfer | C15: 14
