Workbook

Sheet Legend
A2: Legend
D3: Local
D5: State
D7: Federal
D9: Other
D11: Indeterminate
A14: Source | B14: Ohio Department of Education
A16: All files are "read only" and based on data collections from the Ohio Department of Education.
A17: The conclusions reached in this document are those of the author(s) and do not necessarily represent those
A18: of Ball State University.

Sheet Figure 1,2,4
A1: Figure 1 | K1: Figure 2
A2: Ohio (2006-07) | B2: Statewide | D2: Statewide Weighted for Charter Enrollment | F2: Cleveland | H2: Dayton | L2: District | M2: Charter | N2: Difference
A3: Per-Pupil Revenue | K3: State | L3: =B4 -> 9778.6384 | M3: =B5 -> 8190.0097 | N3: =B6 -> 1588.6287
A4: District | B4: =B14 -> 9778.6384 | D4: 10421 | F4: =F14 -> 13016.3 | H4: =H14 -> 13120.806 | K4: Statewide Weighted | L4: =D4 -> 10421 | M4: =D5 -> 8190 | N4: =D6 -> 2231
A5: Charter | B5: =C14 -> 8190.0097 | D5: 8190 | F5: =G14 -> 8931.2491 | H5: =I14 -> 8585.2898 | K5: =F2 -> Cleveland | L5: =F4 -> 13016.3 | M5: =F5 -> 8931.2491 | N5: =F6 -> 4085.0504
A6: Difference | B6: =B4-B5 -> 1588.6287 | D6: 2231 | F6: =F4-F5 -> 4085.0504 | H6: =H4-H5 -> 4535.5164 | K6: =H2 -> Dayton | L6: =H4 -> 13120.806 | M6: =H5 -> 8585.2898 | N6: =H6 -> 4535.5164
B7: =B6/B4 -> 0.16245909 | D7: 0.214 | F7: =F6/F4 -> 0.31384115 | H7: =H6/H4 -> 0.34567361
A8: Per-Pupil Revenue by Source | B8: District | C8: Charter | D8: District | E8: Charter | F8: District | G8: Charter | H8: District | I8: Charter
A9: Federal | B9: ='District Work'!I621/'Figure 1,2,4'!B16:C16 -> 760.30396 | C9: ='Charter Work'!O305 -> 923.29365 | D9: 1046 | E9: =C9 -> 923.29365 | F9: ='District Work'!G37/'Figure 1,2,4'!F16:G16 -> 2290.4939 | G9: ='Charter Work'!O43 -> 1206.8672 | H9: ='District Work'!G43/'Figure 1,2,4'!H16:I16 -> 2128.5719 | I9: ='Charter Work'!O72 -> 812.49115
A10: State | B10: ='District Work'!I1859/'Figure 1,2,4'!B16:C16 -> 4096.8848 | C10: ='Charter Work'!O911 -> 6991.1826 | D10: 4531 | E10: =C10 -> 6991.1826 | F10: ='District Work'!G1275/'Figure 1,2,4'!F16:G16 -> 6686.7822 | G10: ='Charter Work'!O649 -> 7463.7203 | H10: ='District Work'!G1281/'Figure 1,2,4'!H16:I16 -> 5811.1328 | I10: ='Charter Work'!O678 -> 7237.395
A11: Local | B11: ='District Work'!I1240/'Figure 1,2,4'!B16:C16 -> 4921.4497 | C11: 0 | D11: 4843 | E11: =C11 -> 0 | F11: ='District Work'!G656/'Figure 1,2,4'!F16:G16 -> 4039.0234 | G11: 0 | H11: ='District Work'!G662/'Figure 1,2,4'!H16:I16 -> 5181.1015 | I11: 0
A12: Other | B12: 0 | C12: ='Charter Work'!P608 -> 275.5334 | D12: - | E12: =C12 -> 275.5334 | F12: 0 | G12: ='Charter Work'!P346 -> 260.66165 | H12: 0 | I12: ='Charter Work'!P375 -> 535.40364
A13: Indeterminate | B13: 0 | C13: 0 | D13: - | E13: =C13 -> 0 | F13: 0 | G13: 0 | H13: 0 | I13: 0
A14: Total | B14: =SUM(B9:B13) -> 9778.6384 | C14: =SUM(C9:C13) -> 8190.0097 | D14: =D4 -> 10421 | E14: =C14 -> 8190.0097 | F14: =SUM(F9:F13) -> 13016.3 | G14: =SUM(G9:G13) -> 8931.2491 | H14: =SUM(H9:H13) -> 13120.806 | I14: =SUM(I9:I13) -> 8585.2898
A15: Enrollment
A16: District | B16: 1726715 | D16: n/a | F16: 54617 | H16: 15887
B17: =B16/(B16+B18) -> 0.9580986 | D17: n/a | F17: =F16/(F16+F18) -> 0.83953824 | H17: =H16/(H16+H18) -> 0.69952886
A18: Charter | B18: ='Charter Work'!N911 -> 75516 | D18: n/a | F18: ='Charter Work'!O346 -> 10439 | H18: ='Charter Work'!O375 -> 6824
B19: =B18/(B16+B18) -> 0.041901399 | D19: n/a | F19: =F18/(F16+F18) -> 0.16046176 | H19: =H18/(H16+H18) -> 0.30047114
A20: Number of Charters | B20: 303 | D20: n/a | F20: 41 | H20: 29
A21: Total Revenue
A22: District | B22: ='District Work'!I621+'District Work'!I1240+'District Work'!I1859 -> 1.6884922e+10 | D22: n/a | F22: ='District Work'!G37+'District Work'!G656+'District Work'!G1275 -> 7.1091123e+08 | H22: ='District Work'!G1281+'District Work'!G662+'District Work'!G43 -> 2.0845025e+08
B23: =B22/B26 -> 0.96466533 | D23: n/a | F23: =F22/F26 -> 0.88405902 | H23: =H22/H26 -> 0.78060651
A24: Charter | B24: ='Charter Work'!M305+'Charter Work'!N608+'Charter Work'!M911 -> 6.1847677e+08 | D24: n/a | F24: ='Charter Work'!M43+'Charter Work'!N346+'Charter Work'!M649 -> 93233310 | H24: ='Charter Work'!M678+'Charter Work'!N375+'Charter Work'!M72 -> 58586018
B25: =B24/B26 -> 0.035334668 | D25: n/a | F25: =F24/F26 -> 0.11594098 | H25: =H24/H26 -> 0.21939349
A26: Total | B26: =B22+B24 -> 1.7503398e+10 | D26: n/a | F26: =F22+F24 -> 8.0414454e+08 | H26: =H22+H24 -> 2.6703627e+08
A27: Percentage of Revenue by Source | B27: District | C27: Charter | D27: District | E27: Charter | F27: District | G27: Charter | H27: District | I27: Charter | K27: Figure 4
A28: Federal | B28: =B9/B14 -> 0.077751515 | C28: =C9/C14 -> 0.11273413 | D28: =D9/D$14 -> 0.10037424 | E28: =C28 -> 0.11273413 | F28: =F9/F14 -> 0.17597121 | G28: =G9/G14 -> 0.1351286 | H28: =H9/H14 -> 0.16222875 | I28: =I9/I14 -> 0.094637592 | L28: Federal | M28: State | N28: Local | O28: Other | P28: Indeterminate
A29: State | B29: =B10/B14 -> 0.41896271 | C29: =C10/C14 -> 0.85362324 | D29: =D10/D$14 -> 0.43479513 | E29: =C29 -> 0.85362324 | F29: =F10/F14 -> 0.51372375 | G29: =G10/G14 -> 0.83568604 | H29: =H10/H14 -> 0.44289449 | I29: =I10/I14 -> 0.8429995 | K29: Statewide District | L29: =B9 -> 760.30396 | M29: =B10 -> 4096.8848 | N29: =B11 -> 4921.4497 | O29: =B12 -> 0 | P29: =B13 -> 0
A30: Local | B30: =B11/B14 -> 0.50328578 | C30: =C11/C14 -> 0 | D30: =D11/D$14 -> 0.46473467 | E30: =C30 -> 0 | F30: =F11/F14 -> 0.31030504 | G30: =G11/G14 -> 0 | H30: =H11/H14 -> 0.39487677 | I30: =I11/I14 -> 0 | K30: Statewide Charter | L30: =C9 -> 923.29365 | M30: =C10 -> 6991.1826 | N30: =C11 -> 0 | O30: =C12 -> 275.5334 | P30: =C13 -> 0
A31: Other | B31: =B12/B14 -> 0 | C31: =C12/C14 -> 0.033642622 | D31: 0 | E31: =C31 -> 0.033642622 | F31: =F12/F14 -> 0 | G31: =G12/G14 -> 0.029185352 | H31: =H12/H14 -> 0 | I31: =I12/I14 -> 0.062362909 | K31: Statewide Weighted | L31: =D9 -> 1046 | M31: =D10 -> 4531 | N31: =D11 -> 4843 | O31: =D12 -> - | P31: =D13 -> -
A32: Change in district school funding if subjected to charter funding structure | K32: Cleveland District | L32: =F9 -> 2290.4939 | M32: =F10 -> 6686.7822 | N32: =F11 -> 4039.0234 | O32: =F12 -> 0 | P32: =F13 -> 0
B33: ($2.5 billion) | F33: ($214.9 million) | H33: ($64.3 million) | K33: Cleveland Charter | L33: =G9 -> 1206.8672 | M33: =G10 -> 7463.7203 | N33: =G11 -> 0 | O33: =G12 -> 260.66165 | P33: =G13 -> 0
B34: =B6*B16 -> 2.7431091e+09 | F34: =F6*F16 -> 2.231132e+08 | H34: =H6*H16 -> 72055750 | K34: Dayton District | L34: =H9 -> 2128.5719 | M34: =H10 -> 5811.1328 | N34: =H11 -> 5181.1015 | O34: =H12 -> 0 | P34: =H13 -> 0
A35: Removed Promise Academy from the analysis - dollars but no pupils | K35: Dayton Charter | L35: =I9 -> 812.49115 | M35: =I10 -> 7237.395 | N35: =I11 -> 0 | O35: =I12 -> 535.40364 | P35: =I13 -> 0
A36: Conversion charters included in analysis include state funds only

Sheet Figure 3
A1: State Charter School Policies
A2: Figure 3
A3: State Policies | B3: Yes | C3: No | D3: Partial
A4: Charter schools received their funding directly from the state | B4: X
A5: Charter schools are eligible for local funding | C5: X
A6: Cap on funding a charter school can receive | D6: 1
A7: District public school receive differential funding (e.g. more funding for 9-12 vs. K-8 schools) | B7: 2
A8: Charter schools receive differential funding | B8: 3
A9: State allows districts to withhold funding from charter schools for providing adminstrative services | B9: 4
A10: State "holds harmless" ditrict funding for charter enrollment | C10: X
A11: School is considered LEA if authorized by non-district organization | B11: X
A12: School is considered LEA if authorized by district | B12: X
A13: Cap on number of charter schools | B13: 5
A14: Cap on number of charters schools authorized per year | C14: X
A15: Cap on number of studens attending charter schools | C15: X
A16: Charter schools have an open enrollment policy | B16: 6
A19: 1. Internet- or computer-based Community Schools receive only the formula amount and the special education weighted amount
A20: 2. The amount of state funds available to a school is based on a number of variables, including a cost-of-doing business factor for a community, six special education factors, and a Disadvantaged Pupil Impact Aid (DPIA) adjustment factor. Schools receive one-half the funding for kindergarten students.
A21: 3. See two above
A22: 4. The state allows sponsors to charge up to a 3 percent admnistrative fee (of per-pupil funding) to provide sponsorship. Sponsors may also sell additional services to schools.
A23: 5. Ohio law allows 30 start-up charters authorized by non-district entities and 30 start-up charters authorized by districts above the number open as of May 5, 2005. Operators of charter schools with a track record of success are not subject to these restrictions, though. Ohio law also has a moratorium in place on new virtual schools.
A24: 6, There are three open enrollment policies in Ohio. Two are concerned with intradistrict transfers which allow students in low-performing schools to attend different schools within the school district. The third is an interdistrict (voluntary) policy which requires districts to determine whether they will admint nonresident students. "E-schools" are a good example of schools operating under the state's open enrollment policies.

Sheet Figure 5
A1: Figure 5: School Characteristics
C2: Statewide District | D2: Statewide Charter
A3: Percentage of stuents eligible for free or reduced price lunch | C3: 0.334 | D3: 0.432
A4: Percentage of schools eligible for Title 1 | C4: 0.683 | D4: 0.795
A5: Percent of students by school type
B6: Primary (K-5) | C6: 0.45 | D6: 0.426
B7: Middle (6-8) | C7: 0.2 | D7: 0.03
B8: High (9-12) | C8: 0.311 | D8: 0.152
B9: Other (K-12,K-8, etc.) | C9: 0.039 | D9: 0.392

Sheet Figure 6
A1: Figure 6: State Scorecard
B2: Findings | C2: Ohio | E2: Use the following options only
A3: Federal Funding | B3: Charters have access to federal funds according to state statutes (Yes = black, No = white)* | C3: Y | E3: Y
B4: Charters have full access to federal funds in practice (Yes = black, Partial = grey, No = white) | C4: P | E4: P
B5: Percentage of federal revenue equals percentage of total enrollment for charter schools (Yes = black, No = white) | C5: < | E5: N
A6: State Funding | B6: Charters have access to state funds according to state statutes (Yes = black, No = white) | C6: Y
B7: Charters have full access to state funds in practice (Yes = black, Partial = grey, No = white) | C7: Y
B8: Percentage of state revenue equals percentage of total enrollment for charter schools (Yes = black, No = white) | C8: >
A9: Local Funding | B9: Charters have access to local funds according to state statutes (Yes = black, No = white) | C9: N
B10: Charters have full access to local funds in practice (Yes = black, Partial = grey, No = white) | C10: N
B11: Percentage of local revenue equals percentage of total enrollment for charter schools (Yes = black, No = white) | C11: N
A12: Facilities Funding | B12: Charters have access to facilities funds according to state statutes (Yes = black, No = white) | C12: N
B13: Charters have full access to facilities funds in practice (Yes = black, Partial = grey, No = white) | C13: N
B14: Percentage of facilities revenue equals percentage of total enrollment for charter schools (Yes = black, No = white) | C14: N
A15: Data Availability | B15: State provides detailed, public data on federal, state, local and other revenues for district schools (Yes = black, Partial = grey, No = white) | C15: Y
B16: State provides detailed, public data on federal, state, local and other revenues for charter schools (Yes = black, Partial = grey, No = white) | C16: Y
A17: Funding Formula | B17: Charters are treated as LEAs for funding purposes (Yes = black, Partial = grey, No = white) | C17: Y
B18: State funds student (black) or the LEA (grey) | C18: S | E18: S | F18: L | H18: Use these options for the query to the left only (B18)
B19: State funding formula is fair and equitable (Yes = black, No = white | C19: N
A21: * For this finding, No could indicate that the statue is silent or that it denies access.

Sheet District Work
D1: School Year | H1: Charter | K1: County | L1: City | M1: Enrollment
A2: District | C2: Revenue Source | G2: Note: charter revenues are separate and distinct from district revenues. Do not need to back out charter financial eata from the district files as previously told.
A3: 000442 | B3: Manchester Local | C3: Federal Revenue | E3: 13272749 | F3: 0.080527445 | G3: 1068820.6 | H3: District
A4: 000777 | B4: Educational Academy at Linden | C4: Federal Revenue | E4: 204904.7 | F4: 0.73204763 | G4: 150000 | H4: District
A5: 000779 | B5: Educational Academy for Boys & Girls | C5: Federal Revenue | E5: 205403.19 | F5: 0.73027103 | G5: 150000 | H5: District
A6: 000780 | B6: Midnimo Cross Cultural Community School | C6: Federal Revenue | E6: 204907.09 | F6: 0.73203909 | G6: 150000 | H6: District
A7: 043489 | B7: Akron City | C7: Federal Revenue | E7: 3.0791105e+08 | F7: 0.10622273 | G7: 32707152 | H7: District
A8: 043497 | B8: Alliance City | C8: Federal Revenue | E8: 30321614 | F8: 0.13201312 | G8: 4002850.9 | H8: District
A9: 043505 | B9: Ashland City | C9: Federal Revenue | E9: 32742400 | F9: 0.06537838 | G9: 2140645.1 | H9: District
A10: 043513 | B10: Ashtabula Area City | C10: Federal Revenue | E10: 40237485 | F10: 0.1186019 | G10: 4772242.3 | H10: District
A11: 043521 | B11: Athens City | C11: Federal Revenue | E11: 29275566 | F11: 0.076152325 | G11: 2229402.4 | H11: District
A12: 043539 | B12: Barberton City | C12: Federal Revenue | E12: 42958716 | F12: 0.12623936 | G12: 5423080.8 | H12: District
A13: 043547 | B13: Bay Village City | C13: Federal Revenue | E13: 26540939 | F13: 0.037347591 | G13: 991240.16 | H13: District
A14: 043554 | B14: Beachwood City | C14: Federal Revenue | E14: 32237839 | F14: 0.017102645 | G14: 551352.32 | H14: District
... A36: 043778 | B36: Claymont City | C36: Federal Revenue | E36: 18569454 | F36: 0.093773747 | G36: 1741327.3 | H36: District
A37: 043786 | B37: Cleveland Metropolitan City | C37: Federal Revenue | E37: 7.1149149e+08 | F37: 0.17582769 | G37: 1.2509991e+08 | H37: District | L37: Cleveland
A38: 043794 | B38: Cleveland Heights-University Heights City | C38: Federal Revenue | E38: 98409787 | F38: 0.059000842 | G38: 5806260.3 | H38: District
A39: 043802 | B39: Columbus City | C39: Federal Revenue | E39: 6.9664072e+08 | F39: 0.13690076 | G39: 95370641 | H39: District
A40: 043810 | B40: Conneaut Area City | C40: Federal Revenue | E40: 19640706 | F40: 0.1399862 | G40: 2749427.8 | H40: District
A41: 043828 | B41: Coshocton City | C41: Federal Revenue | E41: 16690162 | F41: 0.090898725 | G41: 1517114.4 | H41: District
A42: 043836 | B42: Cuyahoga Falls City | C42: Federal Revenue | E42: 46276612 | F42: 0.023525594 | G42: 1088684.8 | H42: District
A43: 043844 | B43: Dayton City | C43: Federal Revenue | E43: 2.0902574e+08 | F43: 0.16178209 | G43: 33816622 | H43: District | L43: Dayton
A44: 043851 | B44: Deer Park Community City | C44: Federal Revenue | E44: 14444274 | F44: 0.036445204 | G44: 526424.51 | H44: District
A45: 043869 | B45: Defiance City | C45: Federal Revenue | E45: 22578645 | F45: 0.073589053 | G45: 1661541.1 | H45: District
A46: 043877 | B46: Delaware City | C46: Federal Revenue | E46: 40689417 | F46: 0.059497552 | G46: 2420920.7 | H46: District
A47: 043885 | B47: Delphos City | C47: Federal Revenue | E47: 9189823.3 | F47: 0.071652724 | G47: 658475.87 | H47: District
A48: 043893 | B48: Dover City | C48: Federal Revenue | E48: 20473084 | F48: 0.064359535 | G48: 1317638.2 | H48: District
A49: 043901 | B49: East Cleveland City | C49: Federal Revenue | E49: 57785809 | F49: 0.1613687 | G49: 9324821 | H49: District
A50: 043919 | B50: East Liverpool City | C50: Federal Revenue | E50: 25065119 | F50: 0.12549031 | G50: 3145429.6 | H50: District
A51: 043927 | B51: East Palestine City | C51: Federal Revenue | E51: 10582409 | F51: 0.092790759 | G51: 981949.75 | H51: District
A52: 043935 | B52: Eaton Community City | C52: Federal Revenue | E52: 19925241 | F52: 0.054123953 | G52: 1078432.8 | H52: District
A53: 043943 | B53: Elyria City | C53: Federal Revenue | E53: 76055634 | F53: 0.097685357 | G53: 7429521.8 | H53: District
A54: 043950 | B54: Euclid City | C54: Federal Revenue | E54: 75583917 | F54: 0.071132661 | G54: 5376485.2 | H54: District
A55: 043968 | B55: Fairborn City | C55: Federal Revenue | E55: 40189558 | F55: 0.11816503 | G55: 4749000.3 | H55: District
... A619: 069682 | B619: East Guernsey Local | C619: Federal Revenue | E619: 10656779 | F619: 0.10113438 | G619: 1077766.8 | H619: District
A620: 091397 | B620: Tri-County North Local | C620: Federal Revenue | E620: 9036139.3 | F620: 0.053997937 | G620: 487932.88 | H620: District | I620: Total Statewide Federal
A621: 139303 | B621: Monroe Local | C621: Federal Revenue | E621: 15517674 | F621: 0.046199512 | G621: 716908.97 | H621: District | I621: =SUM(G3:G621) -> 1.3128282e+09
A622: 000442 | B622: Manchester Local | C622: Local Revenue | E622: 13272749 | F622: 0.46772579 | G622: 6208007.2 | H622: District
A623: 000777 | B623: Educational Academy at Linden | C623: Local Revenue | E623: 204904.7 | F623: 0 | G623: 0 | H623: District
A624: 000779 | B624: Educational Academy for Boys & Girls | C624: Local Revenue | E624: 205403.19 | F624: 0 | G624: 0 | H624: District
A625: 000780 | B625: Midnimo Cross Cultural Community School | C625: Local Revenue | E625: 204907.09 | F625: 0 | G625: 0 | H625: District
A626: 043489 | B626: Akron City | C626: Local Revenue | E626: 3.0791105e+08 | F626: 0.39008866 | G626: 1.2011261e+08 | H626: District
A627: 043497 | B627: Alliance City | C627: Local Revenue | E627: 30321614 | F627: 0.282754 | G627: 8573557.7 | H627: District
A628: 043505 | B628: Ashland City | C628: Local Revenue | E628: 32742400 | F628: 0.5499565 | G628: 18006896 | H628: District
A629: 043513 | B629: Ashtabula Area City | C629: Local Revenue | E629: 40237485 | F629: 0.30262772 | G629: 12176978 | H629: District
A630: 043521 | B630: Athens City | C630: Local Revenue | E630: 29275566 | F630: 0.58715677 | G630: 17189347 | H630: District
A631: 043539 | B631: Barberton City | C631: Local Revenue | E631: 42958716 | F631: 0.3563278 | G631: 15307385 | H631: District
A632: 043547 | B632: Bay Village City | C632: Local Revenue | E632: 26540939 | F632: 0.7079213 | G632: 18788896 | H632: District
A633: 043554 | B633: Beachwood City | C633: Local Revenue | E633: 32237839 | F633: 0.85624427 | G633: 27603465 | H633: District
... A655: 043778 | B655: Claymont City | C655: Local Revenue | E655: 18569454 | F655: 0.25178847 | G655: 4675574.4 | H655: District
A656: 043786 | B656: Cleveland Metropolitan City | C656: Local Revenue | E656: 7.1149149e+08 | F656: 0.31005197 | G656: 2.2059934e+08 | H656: District | L656: Cleveland
A657: 043794 | B657: Cleveland Heights-University Heights City | C657: Local Revenue | E657: 98409787 | F657: 0.65283649 | G657: 64245500 | H657: District
A658: 043802 | B658: Columbus City | C658: Local Revenue | E658: 6.9664072e+08 | F658: 0.53949388 | G658: 3.7583341e+08 | H658: District
A659: 043810 | B659: Conneaut Area City | C659: Local Revenue | E659: 19640706 | F659: 0.25151964 | G659: 4940023.4 | H659: District
A660: 043828 | B660: Coshocton City | C660: Local Revenue | E660: 16690162 | F660: 0.37029618 | G660: 6180303.1 | H660: District
A661: 043836 | B661: Cuyahoga Falls City | C661: Local Revenue | E661: 46276612 | F661: 0.65536885 | G661: 30328250 | H661: District
A662: 043844 | B662: Dayton City | C662: Local Revenue | E662: 2.0902574e+08 | F662: 0.39378958 | G662: 82312160 | H662: District | L662: Dayton
A663: 043851 | B663: Deer Park Community City | C663: Local Revenue | E663: 14444274 | F663: 0.65159095 | G663: 9411758.2 | H663: District
A664: 043869 | B664: Defiance City | C664: Local Revenue | E664: 22578645 | F664: 0.40662418 | G664: 9181022.8 | H664: District
A665: 043877 | B665: Delaware City | C665: Local Revenue | E665: 40689417 | F665: 0.58622418 | G665: 23853120 | H665: District
A666: 043885 | B666: Delphos City | C666: Local Revenue | E666: 9189823.3 | F666: 0.5822216 | G666: 5350513.7 | H666: District
A667: 043893 | B667: Dover City | C667: Local Revenue | E667: 20473084 | F667: 0.55986736 | G667: 11462211 | H667: District
A668: 043901 | B668: East Cleveland City | C668: Local Revenue | E668: 57785809 | F668: 0.24460833 | G668: 14134890 | H668: District
A669: 043919 | B669: East Liverpool City | C669: Local Revenue | E669: 25065119 | F669: 0.18016359 | G669: 4515821.8 | H669: District
A670: 043927 | B670: East Palestine City | C670: Local Revenue | E670: 10582409 | F670: 0.23710321 | G670: 2509123.1 | H670: District
A671: 043935 | B671: Eaton Community City | C671: Local Revenue | E671: 19925241 | F671: 0.50391984 | G671: 10040724 | H671: District
A672: 043943 | B672: Elyria City | C672: Local Revenue | E672: 76055634 | F672: 0.47586012 | G672: 36191843 | H672: District
A673: 043950 | B673: Euclid City | C673: Local Revenue | E673: 75583917 | F673: 0.54543352 | G673: 41226002 | H673: District
A674: 043968 | B674: Fairborn City | C674: Local Revenue | E674: 40189558 | F674: 0.41956233 | G674: 16862025 | H674: District
... A1238: 069682 | B1238: East Guernsey Local | C1238: Local Revenue | E1238: 10656779 | F1238: 0.280129 | G1238: 2985272.9 | H1238: District
A1239: 091397 | B1239: Tri-County North Local | C1239: Local Revenue | E1239: 9036139.3 | F1239: 0.44866649 | G1239: 4054212.9 | H1239: District | I1239: Total Statewide Local
A1240: 139303 | B1240: Monroe Local | C1240: Local Revenue | E1240: 15517674 | F1240: 0.62199799 | G1240: 9651962.1 | H1240: District | I1240: =SUM(G622:G1240) -> 8.4979409e+09
A1241: 000442 | B1241: Manchester Local | C1241: State Revenue | E1241: 13272749 | F1241: 0.45174677 | G1241: 5995921.7 | H1241: District
A1242: 000777 | B1242: Educational Academy at Linden | C1242: State Revenue | E1242: 204904.7 | F1242: 0.26795237 | G1242: 54904.7 | H1242: District
A1243: 000779 | B1243: Educational Academy for Boys & Girls | C1243: State Revenue | E1243: 205403.19 | F1243: 0.26972897 | G1243: 55403.19 | H1243: District
A1244: 000780 | B1244: Midnimo Cross Cultural Community School | C1244: State Revenue | E1244: 204907.09 | F1244: 0.26796091 | G1244: 54907.09 | H1244: District
A1245: 043489 | B1245: Akron City | C1245: State Revenue | E1245: 3.0791105e+08 | F1245: 0.50368861 | G1245: 1.5509129e+08 | H1245: District
A1246: 043497 | B1246: Alliance City | C1246: State Revenue | E1246: 30321614 | F1246: 0.58523288 | G1246: 17745206 | H1246: District
A1247: 043505 | B1247: Ashland City | C1247: State Revenue | E1247: 32742400 | F1247: 0.38466512 | G1247: 12594859 | H1247: District
A1248: 043513 | B1248: Ashtabula Area City | C1248: State Revenue | E1248: 40237485 | F1248: 0.57877038 | G1248: 23288264 | H1248: District
A1249: 043521 | B1249: Athens City | C1249: State Revenue | E1249: 29275566 | F1249: 0.33669091 | G1249: 9856817 | H1249: District
A1250: 043539 | B1250: Barberton City | C1250: State Revenue | E1250: 42958716 | F1250: 0.51743284 | G1250: 22228250 | H1250: District
A1251: 043547 | B1251: Bay Village City | C1251: State Revenue | E1251: 26540939 | F1251: 0.25473111 | G1251: 6760802.9 | H1251: District
A1252: 043554 | B1252: Beachwood City | C1252: State Revenue | E1252: 32237839 | F1252: 0.12665309 | G1252: 4083021.9 | H1252: District
... A1274: 043778 | B1274: Claymont City | C1274: State Revenue | E1274: 18569454 | F1274: 0.65443778 | G1274: 12152552 | H1274: District
A1275: 043786 | B1275: Cleveland Metropolitan City | C1275: State Revenue | E1275: 7.1149149e+08 | F1275: 0.51412033 | G1275: =365792241.45-580256 -> 3.6521199e+08 | H1275: District | I1275: Cleveland State includes Pre-K Reducation | L1275: Cleveland
A1276: 043794 | B1276: Cleveland Heights-University Heights City | C1276: State Revenue | E1276: 98409787 | F1276: 0.28816267 | G1276: 28358027 | H1276: District
A1277: 043802 | B1277: Columbus City | C1277: State Revenue | E1277: 6.9664072e+08 | F1277: 0.32360536 | G1277: 2.2543667e+08 | H1277: District
A1278: 043810 | B1278: Conneaut Area City | C1278: State Revenue | E1278: 19640706 | F1278: 0.60849416 | G1278: 11951255 | H1278: District
A1279: 043828 | B1279: Coshocton City | C1279: State Revenue | E1279: 16690162 | F1279: 0.53880509 | G1279: 8992744.1 | H1279: District
A1280: 043836 | B1280: Cuyahoga Falls City | C1280: State Revenue | E1280: 46276612 | F1280: 0.32110555 | G1280: 14859677 | H1280: District
A1281: 043844 | B1281: Dayton City | C1281: State Revenue | E1281: 2.0902574e+08 | F1281: 0.44442833 | G1281: =92896961.13-575495 -> 92321466 | H1281: District | I1281: Dayton State includes Pre-K Reduction | L1281: Dayton
A1282: 043851 | B1282: Deer Park Community City | C1282: State Revenue | E1282: 14444274 | F1282: 0.31196385 | G1282: 4506091.3 | H1282: District
A1283: 043869 | B1283: Defiance City | C1283: State Revenue | E1283: 22578645 | F1283: 0.51978677 | G1283: 11736081 | H1283: District
A1284: 043877 | B1284: Delaware City | C1284: State Revenue | E1284: 40689417 | F1284: 0.35427827 | G1284: 14415376 | H1284: District
A1285: 043885 | B1285: Delphos City | C1285: State Revenue | E1285: 9189823.3 | F1285: 0.34612567 | G1285: 3180833.8 | H1285: District
A1286: 043893 | B1286: Dover City | C1286: State Revenue | E1286: 20473084 | F1286: 0.37577311 | G1286: 7693234.4 | H1286: District
A1287: 043901 | B1287: East Cleveland City | C1287: State Revenue | E1287: 57785809 | F1287: 0.59402297 | G1287: 34326097 | H1287: District
A1288: 043919 | B1288: East Liverpool City | C1288: State Revenue | E1288: 25065119 | F1288: 0.69434609 | G1288: 17403867 | H1288: District
A1289: 043927 | B1289: East Palestine City | C1289: State Revenue | E1289: 10582409 | F1289: 0.67010603 | G1289: 7091336 | H1289: District
...

Sheet Charter Work
D1: School Year | H1: Charter | K1: County | L1: City | M1: Enrollment
D2: Metrics | E2: Total Revenue Amount | F2: Revenue Source Pct of Total | G2: Use This Amount | H2: Charter | I2: Conversion | J2: Conversion District | K2: County | L2: City
A3: 000195 | B3: Hope Academy East Campus | C3: Federal Revenue | E3: 3429982.1 | F3: 0.12923064 | G3: 443258.8 | H3: C | K3: Cuyahoga | L3: Cleveland
A4: 000316 | B4: Westpark Community Middle School | C4: Federal Revenue | E4: 865196.41 | F4: 0.27563059 | G4: 238474.6 | H4: C | K4: Cuyahoga | L4: Cleveland
A5: 000319 | B5: Madison Community School | C5: Federal Revenue | E5: 1490755.8 | F5: 0.25866492 | G5: 385606.23 | H5: C | K5: Cuyahoga | L5: Cleveland
A6: 000321 | B6: Old Brooklyn Community Middle School | C6: Federal Revenue | E6: 802536.76 | F6: 0.24571617 | G6: 197196.26 | H6: C | K6: Cuyahoga | L6: Cleveland
A7: 000418 | B7: Greater Heights Academy | C7: Federal Revenue | E7: 7954976.9 | F7: 0.099349158 | G7: 790320.26 | H7: C | K7: Cuyahoga | L7: Cleveland
A8: 000527 | B8: Cleveland Academy for Scholarship Technology and Leadership | C8: Federal Revenue | E8: 2445648.9 | F8: 0.14109789 | G8: 345075.9 | H8: C | K8: Cuyahoga | L8: Cleveland
A9: 000534 | B9: Puritas Community Middle School | C9: Federal Revenue | E9: 479588.19 | F9: 0.47182254 | G9: 226280.52 | H9: C | K9: Cuyahoga | L9: Cleveland
A10: 000541 | B10: Outreach Academy for Children with Disabilities | C10: Federal Revenue | E10: 1689005 | F10: 0.17761937 | G10: 300000 | H10: C | K10: Cuyahoga | L10: Cleveland
A11: 000564 | B11: Virtual Schoolhouse, Inc. | C11: Federal Revenue | E11: 8436970.5 | F11: 0.0521787 | G11: 440230.15 | H11: C | K11: Cuyahoga | L11: Cleveland
A12: 000575 | B12: Hope Academy Northwest Campus | C12: Federal Revenue | E12: 3233072.7 | F12: 0.23784172 | G12: 768959.57 | H12: C | K12: Cuyahoga | L12: Cleveland
A13: 000736 | B13: Phoenix Village Academy Primary 2 | C13: Federal Revenue | E13: 492036.1 | F13: 0.55779653 | G13: 274456.03 | H13: C | K13: Cuyahoga | L13: Cleveland
A14: 000738 | B14: Phoenix Village Academy: Secondary I | C14: Federal Revenue | E14: 393282.73 | F14: 0.57372918 | G14: 225637.78 | H14: C | K14: Cuyahoga | L14: Cleveland
... A39: 143313 | B39: Hope Academy Cuyahoga Campus | C39: Federal Revenue | E39: 4017568.6 | F39: 0.11595871 | G39: 465872.06 | H39: C | K39: Cuyahoga | L39: Cleveland
A40: 143446 | B40: Greater Achievement Community School | C40: Federal Revenue | E40: 0 | F40: -- | G40: 0 | H40: C | K40: Cuyahoga | L40: Cleveland
A41: 143479 | B41: Puritas Community School | C41: Federal Revenue | E41: 1458765.4 | F41: 0.097114022 | G41: 141666.58 | H41: C | K41: Cuyahoga | L41: Cleveland
A42: 151183 | B42: Life Skills Ctr Of Lake Erie | C42: Federal Revenue | E42: 3568958.2 | F42: 0.082010822 | G42: 292693.2 | H42: C | K42: Cuyahoga | L42: Cleveland | M42: Cleveland Charter Totals - Federal
A43: 151209 | B43: Life Skills Of Northeast Ohio | C43: Federal Revenue | E43: 2709131.3 | F43: 0.050943626 | G43: 138012.97 | H43: C | K43: Cuyahoga | L43: Cleveland | M43: =SUM(G3:G43) -> 12598487 | N43: =SUM(M306:M346) -> 10439 | O43: =M43/N43 -> 1206.8672
A44: 000138 | B44: Pathway School of Discovery | C44: Federal Revenue | E44: 0 | F44: -- | H44: C | K44: Montgomery | L44: Dayton
A45: 000297 | B45: Summit Academy Dayton | C45: Federal Revenue | E45: 1407836.6 | F45: 0.059684456 | G45: 84025.96 | H45: C | K45: Montgomery | L45: Dayton
A46: 000427 | B46: Arise Academy | C46: Federal Revenue | E46: 1470515.3 | F46: 0.12967294 | G46: 190686.04 | H46: C | K46: Montgomery | L46: Dayton
A47: 000445 | B47: General Chappie James Leadership Academy | C47: Federal Revenue | E47: 833238.87 | F47: 0.33702075 | G47: 280818.79 | H47: C | K47: Montgomery | L47: Dayton
A48: 000496 | B48: Peterson Entrepreneurial Training Enterprise | C48: Federal Revenue | E48: 1451418.6 | F48: 0.15931945 | G48: 231239.22 | H48: C | K48: Montgomery | L48: Dayton
A49: 000577 | B49: Emerson Academy | C49: Federal Revenue | E49: 0 | F49: -- | G49: 0 | H49: C | K49: Montgomery | L49: Dayton
A50: 000700 | B50: New City School | C50: Federal Revenue | E50: 892186 | F50: 0.41266642 | G50: 368175.2 | H50: C | K50: Montgomery | L50: Dayton
A51: 000808 | B51: Horizon Science Academy-Dayton | C51: Federal Revenue | E51: 1443280.7 | F51: 0.16938231 | G51: 244466.21 | H51: C | K51: Montgomery | L51: Dayton
A52: 000813 | B52: Life Skills Center of Dayton | C52: Federal Revenue | E52: 2707072 | F52: 0.1170392 | G52: 316833.55 | H52: C | K52: Montgomery | L52: Dayton
A53: 000922 | B53: Nu Bethel Center of Excellence | C53: Federal Revenue | E53: 377292.94 | F53: 0.085992253 | G53: 32444.27 | H53: C | K53: Montgomery | L53: Dayton
A54: 008283 | B54: Dayton Technology Design High School | C54: Federal Revenue | E54: 853109.34 | F54: 0.0066539771 | G54: 5676.57 | H54: C | I54: Yes | J54: Dayton | K54: Montgomery | L54: Dayton
A55: 132738 | B55: Colin Powell Leadership Acad | C55: Federal Revenue | E55: 2171897.7 | F55: 0.22343486 | G55: 485277.67 | H55: C | K55: Montgomery | L55: Dayton
A56: 132944 | B56: Miami Valley Academies | C56: Federal Revenue | E56: 1320416 | F56: 0.1027145 | G56: 135625.86 | H56: c | K56: Montgomery | L56: Dayton
A57: 133348 | B57: Richard Allen Preparatory | C57: Federal Revenue | E57: 673623.24 | F57: 0.10794035 | G57: 72711.13 | H57: C | K57: Montgomery | L57: Dayton
A58: 133371 | B58: Omega School Of Excellence | C58: Federal Revenue | E58: 924919.7 | F58: 0.18841253 | G58: 174266.46 | H58: C | K58: Montgomery | L58: Dayton
A59: 133454 | B59: Dayton View Academy | C59: Federal Revenue | E59: 4930062 | F59: 0.11867513 | G59: 585075.72 | H59: C | K59: Montgomery | L59: Dayton
A60: 133736 | B60: Richard Allen Academy | C60: Federal Revenue | E60: 1404805.4 | F60: 0.084365023 | G60: 118516.44 | H60: C | K60: Montgomery | L60: Dayton
A61: 133744 | B61: The ISUS Institute of Construction Technology | C61: Federal Revenue | E61: 4376265 | F61: 0.066322867 | G61: 290246.44 | H61: c | K61: Montgomery | L61: Dayton
A62: 133769 | B62: New Choices Community School | C62: Federal Revenue | E62: 2165529.9 | F62: 0 | G62: 0 | H62: C | K62: Montgomery | L62: Dayton
A63: 133959 | B63: Dayton Academy, The | C63: Federal Revenue | E63: 5661783.1 | F63: 0.10417008 | G63: 589788.41 | H63: C | K63: Montgomery | L63: Dayton
A64: 134247 | B64: City Day Community School | C64: Federal Revenue | E64: 1221188.5 | F64: 0.082518224 | G64: 100770.31 | H64: C | K64: Montgomery | L64: Dayton
A65: 143115 | B65: Mound Street IT Careers Academy | C65: Federal Revenue | E65: 1467825.9 | F65: 0.24709635 | G65: 362694.41 | H65: C | K65: Montgomery | L65: Dayton
A66: 143123 | B66: Mound Street Military Careers Academy | C66: Federal Revenue | E66: 1059969.9 | F66: 0.12486591 | G66: 132354.11 | H66: C | K66: Montgomery | L66: Dayton
... A70: 143388 | B70: East End Community School | C70: Federal Revenue | E70: 1809630.2 | F70: 0.08354827 | G70: 151191.47 | H70: C | K70: Montgomery | L70: Dayton
A71: 143529 | B71: North Dayton School Of Science & Discovery | C71: Federal Revenue | E71: 0 | F71: -- | G71: 0 | H71: c | K71: Montgomery | L71: Dayton | M71: Dayton Charter Totals - Federal
A72: 143560 | B72: Richard Allen Academy II | C72: Federal Revenue | E72: 3404548.4 | F72: 0.10166965 | G72: 346139.23 | H72: C | K72: Montgomery | L72: Dayton | M72: =SUM(G44:G72) -> 5544439.6 | N72: =SUM(M347:M375) -> 6824 | O72: =M72/N72 -> 812.49115
A73: 000302 | B73: Summit Academy Secondary School-Parma | C73: Federal Revenue | E73: 2584058.5 | F73: 0.090184684 | G73: 233042.5 | H73: C | K73: Cuyahoga | L73: Non-CPS
A74: 000523 | B74: Education Alternatives Community School | C74: Federal Revenue | E74: 1901827.3 | F74: 0.20042122 | G74: 381166.56 | H74: C | K74: Cuyahoga | L74: Non-CPS
A75: 000560 | B75: Apex Academy | C75: Federal Revenue | E75: 0 | F75: -- | G75: 0 | H75: C | K75: Cuyahoga | L75: Non-CPS
A76: 000677 | B76: New Day Academy Boarding & Day School | C76: Federal Revenue | E76: 1326737.2 | F76: 0.30365608 | G76: 402871.82 | H76: C | K76: Cuyahoga | L76: Non-CPS
A77: 008061 | B77: Arts and Science Preparatory Academy | C77: Federal Revenue | E77: 161469.61 | F77: 0.16371372 | G77: 26434.79 | H77: C | K77: Cuyahoga | L77: Non-CPS
A78: 008278 | B78: Noble Academy-Cleveland | C78: Federal Revenue | E78: 623733.16 | F78: 0.046777872 | G78: 29176.91 | H78: C | K78: Cuyahoga | L78: Non-CPS
A79: 133256 | B79: Parma Community | C79: Federal Revenue | E79: 2320667.8 | F79: 0.064878307 | G79: 150561 | H79: C | K79: Cuyahoga | L79: Non-CPS
A80: 133587 | B80: Summit Academy Community School for Alt Learners of Akron | C80: Federal Revenue | E80: 1138719.8 | F80: 0.17940728 | G80: 204294.62 | H80: C | K80: Cuyahoga | L80: Non-CPS
A81: 143461 | B81: Marcus Garvey Academy | C81: Federal Revenue | E81: 1114230.3 | F81: 0.16972833 | G81: 189116.45 | H81: C | K81: Cuyahoga | L81: Non-CPS
A82: 143487 | B82: Stockyard Community School | C82: Federal Revenue | E82: 1752311.7 | F82: 0.26695294 | G82: 467784.77 | H82: C | K82: Cuyahoga | L82: Non-CPS
A83: 000125 | B83: Polly Fox Academy Community School | C83: Federal Revenue | E83: 1252639.2 | F83: 0.21746616 | G83: 272406.64 | H83: C
A84: 000130 | B84: Phoenix Academy Community School | C84: Federal Revenue | E84: 7379049.3 | F84: 0.0055225868 | G84: 40751.44 | H84: C
A85: 000131 | B85: Glass City Academy | C85: Federal Revenue | E85: 1296747.6 | F85: 0 | G85: 0 | H85: C
A86: 000139 | B86: Alliance Academy of Cincinnati | C86: Federal Revenue | E86: 0 | F86: -- | H86: C
A87: 000140 | B87: Victory Academy of Toledo | C87: Federal Revenue | E87: 1136684 | F87: 0.30081653 | G87: 341933.34 | H87: C
A88: 000143 | B88: George A. Phillips Academy | C88: Federal Revenue | E88: 1674388.4 | F88: 0.16231337 | G88: 271775.63 | H88: C
A89: 000197 | B89: Hamilton Local Digital Academy | C89: Federal Revenue | E89: 603347.98 | F89: 0.16574208 | G89: 100000.15 | H89: c
A90: 000222 | B90: Wildwood Environmental Academy | C90: Federal Revenue | E90: 1853701.4 | F90: 0.17525233 | G90: 324865.49 | H90: C
A91: 000235 | B91: International College Preparatory Academy | C91: Federal Revenue | E91: 4926715.6 | F91: 0.15964331 | G91: 786517.18 | H91: C
A92: 000236 | B92: Ohio Connections Academy, Inc | C92: Federal Revenue | E92: 7076666.7 | F92: 0.10239663 | G92: 724626.8 | H92: C
A93: 000277 | B93: Scholarts Preparatory and Career Center for Children | C93: Federal Revenue | E93: 842358.61 | F93: 0.28115708 | G93: 236835.09 | H93: C
A94: 000282 | B94: Warren County Virtual Community School | C94: Federal Revenue | E94: 867720.61 | F94: 0.16362759 | G94: 141983.03 | H94: C | I94: Yes | J94: Wayne Local
A95: 000287 | B95: Auglaize County Special Needs School | C95: Federal Revenue | E95: 1082082.8 | F95: 0.26275691 | G95: 284324.72 | H95: C
A96: 000288 | B96: Auglaize County Educational Academy | C96: Federal Revenue | E96: 705727.13 | F96: 0.39696928 | G96: 280151.99 | H96: C
A97: 000296 | B97: Summit Academy Columbus | C97: Federal Revenue | E97: 968241.67 | F97: 0.083965453 | G97: 81298.85 | H97: C
A98: 000298 | B98: Summit Academy Secondary - Akron | C98: Federal Revenue | E98: 954583.08 | F98: 0.052029699 | G98: 49666.67 | H98: C
A99: 000300 | B99: Summit Academy Secondary - Canton | C99: Federal Revenue | E99: 473070.95 | F99: 0.041768851 | G99: 19759.63 | H99: C
A100: 000301 | B100: Summit Academy Secondary - Lorain | C100: Federal Revenue | E100: 461116.57 | F100: 0.044748381 | G100: 20634.22 | H100: C
A101: 000303 | B101: Summit Academy Secondary - Youngstown | C101: Federal Revenue | E101: 1033482.8 | F101: 0.04503508 | G101: 46542.98 | H101: C
A102: 000304 | B102: Summit Academy Community School-Toledo | C102: Federal Revenue | E102: 1832644.5 | F102: 0.10656621 | G102: 195297.97 | H102: C
A103: 000305 | B103: Summit Academy Community School-Warren | C103: Federal Revenue | E103: 1005955.8 | F103: 0.12585982 | G103: 126609.42 | H103: C
A104: 000306 | B104: Summit Academy Cincinnati | C104: Federal Revenue | E104: 1289628 | F104: 0.062070417 | G104: 80047.75 | H104: C
A105: 000318 | B105: Lorain Academy For Gifted Students | C105: Federal Revenue | E105: 689184.34 | F105: 0.036177346 | G105: 24932.86 | H105: C
A106: 000320 | B106: Lorain Community Middle School | C106: Federal Revenue | E106: 967825.37 | F106: 0.24856529 | G106: 240567.79 | H106: C
... A108: 000343 | B108: Chase Academy for Communication Arts | C108: Federal Revenue | E108: 1829347 | F108: 0.18971688 | G108: 347058.01 | H108: C
A109: 000392 | B109: Mansfield Enhancement Academy | C109: Federal Revenue | E109: 694149.71 | F109: 0.27660014 | G109: 192001.91 | H109: C | I109: Yes | J109: Mansfield City
A110: 000402 | B110: Findlay Digital Academy | C110: Federal Revenue | E110: 559227.43 | F110: 0.29847377 | G110: 166914.72 | H110: C | I110: Yes | J110: Findlay
A111: 000417 | B111: Buckeye On-Line School for Success | C111: Federal Revenue | E111: 7399000.7 | F111: 0.055196428 | G111: 408398.41 | H111: C
A112: 000420 | B112: Capitol City Academy | C112: Federal Revenue | E112: 1323872.1 | F112: 0.27800802 | G112: 368047.06 | H112: C
A113: 000461 | B113: Pace Career Central | C113: Federal Revenue | E113: 1037781.3 | F113: 0.19458207 | G113: 201933.64 | H113: c
A114: 000473 | B114: Tech Con Institute | C114: Federal Revenue | E114: 561236.21 | F114: 0.54452255 | G114: 305605.77 | H114: C | K114: Montgomery
A115: 000481 | B115: P.A.C.E. High School | C115: Federal Revenue | E115: 2556579.8 | F115: 0.19872492 | G115: 508056.11 | H115: C
A116: 000502 | B116: Canton Academy, The | C116: Federal Revenue | E116: 879618.34 | F116: 0.3749961 | G116: 329853.45 | H116: C
A117: 000509 | B117: Whitehall Preparatory and Fitness Academy | C117: Federal Revenue | E117: 1848013 | F117: 0 | G117: 0 | H117: C
A118: 000510 | B118: Springfield Preparatory and Fitness Academy | C118: Federal Revenue | E118: 1814426 | F118: 0 | G118: 0 | H118: C
A119: 000511 | B119: Northland Preparatory and Fitness Academy | C119: Federal Revenue | E119: 1697813.2 | F119: 0 | G119: 0 | H119: C
A120: 000525 | B120: Project Rebuild Community School | C120: Federal Revenue | E120: 728694.6 | F120: 0.27895201 | G120: 203270.82 | H120: C
A121: 000543 | B121: Pinnacle Academy | C121: Federal Revenue | E121: 0 | F121: -- | G121: 0 | H121: C
A122: 000546 | B122: Winterfield Venture Academy | C122: Federal Revenue | E122: 0 | F122: -- | G122: 0 | H122: C
A123: 000553 | B123: Columbus Humanities, Arts and Technology Academy | C123: Federal Revenue | E123: 2476348.7 | F123: 0.11932008 | G123: 295478.13 | H123: C
A124: 000556 | B124: A+ Arts Academy | C124: Federal Revenue | E124: 1450154.8 | F124: 0.34439445 | G124: 499425.26 | H124: C
A125: 000557 | B125: Columbus Arts & Technology Academy | C125: Federal Revenue | E125: 4484235.7 | F125: 0.14904684 | G125: 668361.17 | H125: C
A126: 000558 | B126: Columbus Preparatory Academy | C126: Federal Revenue | E126: 3401211.3 | F126: 0.10714961 | G126: 364438.45 | H126: C
A127: 000559 | B127: Orion Academy | C127: Federal Revenue | E127: 0 | F127: -- | G127: 0 | H127: C
A128: 000574 | B128: Arts Academy, The | C128: Federal Revenue | E128: 1974056.5 | F128: 0.063401681 | G128: 125158.5 | H128: C
...

Sheet Charter Master
A1: 133355 | B1: A.B. Miree Fundamental Academy | C1: Local Revenue | E1: 2719630.4 | F1: 0.010789095 | G1: 29342.35 | H1: C | K1: 376
A2: 000556 | B2: A+ Arts Academy | C2: Local Revenue | E2: 1450154.8 | F2: 0.0043871041 | G2: 6361.98 | H2: C | K2: 161
A3: 000912 | B3: Academic Acceleration Academy | C3: Local Revenue | E3: 730744.86 | F3: 0.0086639953 | G3: 6331.17 | H3: C | K3: 82
A4: 007982 | B4: Academy of Arts and Humanities | C4: Local Revenue | E4: 277522.47 | F4: 9.8190247e-05 | G4: 27.25 | H4: C | K4: 128
A5: 008064 | B5: Academy of Arts and Sciences | C5: Local Revenue | E5: 1344443.6 | F5: 0 | G5: 0 | H5: C | K5: 216
A6: 134262 | B6: Academy Of Business & Tech | C6: Local Revenue | E6: 1750555.6 | F6: 0.00052156014 | G6: 913.02 | H6: C | K6: 309
A7: 133900 | B7: Academy of Cleveland | C7: Local Revenue | E7: 1059945.3 | F7: 0.0002142186 | G7: 227.06 | H7: C | I7: Cuyahoga | J7: Cleveland | K7: 147
A8: 000784 | B8: Academy of Columbus | C8: Local Revenue | E8: 2727062.2 | F8: 0 | G8: 0 | H8: C | K8: 473
A9: 133918 | B9: Academy Of Dayton | C9: Local Revenue | E9: 746521.86 | F9: 0.0010595001 | G9: 790.94 | H9: C | I9: Montgomery | K9: 120
A10: 149054 | B10: Akron Digital Academy | C10: Local Revenue | E10: 4063576.7 | F10: 0.021877212 | G10: 88899.73 | H10: C | K10: 539
A11: 000139 | B11: Alliance Academy of Cincinnati | C11: Local Revenue | E11: 0 | F11: -- | H11: C
A12: 143396 | B12: Alternative Education Academy | C12: Local Revenue | E12: 17351899 | F12: 0.060497628 | G12: 1049748.7 | H12: C | K12: 2125
A13: 000560 | B13: Apex Academy | C13: Local Revenue | E13: 0 | F13: -- | H13: C | I13: Cuyahoga | K13: 616
A14: 000427 | B14: Arise Academy | C14: Local Revenue | E14: 1470515.3 | F14: 0 | G14: 0 | H14: C | I14: Montgomery | J14: Dayton | K14: 178
A15: 143610 | B15: Arts & College Preparatory Academy | C15: Local Revenue | E15: 1588994.8 | F15: 0.00026705562 | G15: 424.35 | H15: C | K15: 208
A16: 008068 | B16: Arts Academy West, The | C16: Local Revenue | E16: 657459.05 | F16: 0.0047800087 | G16: 3142.66 | H16: C | I16: Cuyahoga | J16: Cleveland | K16: 74
A17: 000574 | B17: Arts Academy, The | C17: Local Revenue | E17: 1974056.5 | F17: 0.01129149 | G17: 22290.04 | H17: C | K17: 272
A18: 007992 | B18: Arts and Science Academy | C18: Local Revenue | E18: 622949.76 | F18: 6.0197471e-05 | G18: 37.5 | H18: C | K18: 158
A19: 008061 | B19: Arts and Science Preparatory Academy | C19: Local Revenue | E19: 161469.61 | F19: 0 | G19: 0 | H19: C | I19: Cuyahoga | K19: 26
A20: 000288 | B20: Auglaize County Educational Academy | C20: Local Revenue | E20: 705727.13 | F20: 0.016722469 | G20: 11801.5 | H20: C | K20: 56
A21: 000287 | B21: Auglaize County Special Needs School | C21: Local Revenue | E21: 1082082.8 | F21: 0.0098995201 | G21: 10712.1 | H21: C | K21: 35
A22: 134148 | B22: Aurora Academy | C22: Local Revenue | E22: 1380421.7 | F22: 0.010913165 | G22: 15064.77 | H22: C | K22: 159
A23: 000843 | B23: Bennett Venture Academy | C23: Local Revenue | E23: 0 | F23: -- | H23: C | K23: 519
A24: 000417 | B24: Buckeye On-Line School for Success | C24: Local Revenue | E24: 7399000.7 | F24: 0.00097174339 | G24: 7189.93 | H24: C | K24: 1012
A25: 000502 | B25: Canton Academy, The | C25: Local Revenue | E25: 879618.34 | F25: 0.0012297606 | G25: 1081.72 | H25: C | K25: 50
A26: 000859 | B26: Canton Arts Academy | C26: Local Revenue | E26: 1222466.8 | F26: 0.0066802879 | G26: 8166.43 | H26: C | K26: 122
A27: 000420 | B27: Capitol City Academy | C27: Local Revenue | E27: 1323872.1 | F27: 0.038754658 | G27: 51306.21 | H27: C | K27: 159
A28: 000343 | B28: Chase Academy for Communication Arts | C28: Local Revenue | E28: 1829347 | F28: 0.0036094847 | G28: 6603 | H28: C | K28: 221
A29: 133512 | B29: Cincinnati College Preparatory Academy | C29: Local Revenue | E29: 4463813.7 | F29: 0.001022574 | G29: 4564.58 | H29: C | K29: 544
A30: 000953 | B30: Cincinnati Preparatory and Fitness Academy | C30: Local Revenue | E30: 835934 | F30: 0.0011472198 | G30: 959 | H30: C | K30: 79
A31: 000781 | B31: Cincinnati Speech & Reading Intervention Center | C31: Local Revenue | E31: 1357867 | F31: 7.5449214e-05 | G31: 102.45 | H31: C | K31: 180
A32: 133520 | B32: Citizens Academy | C32: Local Revenue | E32: 3812632.9 | F32: 0.085243732 | G32: 325003.06 | H32: C | I32: Cuyahoga | J32: Cleveland | K32: 380
A33: 134247 | B33: City Day Community School | C33: Local Revenue | E33: 1221188.5 | F33: 0.013922404 | G33: 17001.88 | H33: C | I33: Montgomery | J33: Dayton | K33: 169
A34: 000527 | B34: Cleveland Academy for Scholarship Technology and Leadership | C34: Local Revenue | E34: 2445648.9 | F34: 0 | G34: 0 | H34: C | I34: Cuyahoga | J34: Cleveland | K34: 160
A35: 007995 | B35: Cleveland Arts and Social Sciences Academy | C35: Local Revenue | E35: 1189815.7 | F35: 0.00047435076 | G35: 564.39 | H35: C | I35: Cuyahoga | J35: Cleveland | K35: 131
A36: 000930 | B36: Cleveland Entreprenuership Preparatory School | C36: Local Revenue | E36: 1607032.7 | F36: 0.43075697 | G36: 692240.54 | H36: C | I36: Cuyahoga | J36: Cleveland | K36: 123
A37: 000946 | B37: Cleveland Lighthouse Community School | C37: Local Revenue | E37: 2239223.5 | F37: 0.3055538 | G37: 684203.25 | H37: C | I37: Cuyahoga | J37: Cleveland | K37: 166
A38: 132738 | B38: Colin Powell Leadership Acad | C38: Local Revenue | E38: 2171897.7 | F38: 0 | G38: 0 | H38: C | I38: Montgomery | J38: Dayton | K38: 219
A39: 000557 | B39: Columbus Arts & Technology Academy | C39: Local Revenue | E39: 4484235.7 | F39: 0.00050200305 | G39: 2251.1 | H39: C | K39: 598
A40: 000553 | B40: Columbus Humanities, Arts and Technology Academy | C40: Local Revenue | E40: 2476348.7 | F40: 0.0011386159 | G40: 2819.61 | H40: C | K40: 325
A41: 000558 | B41: Columbus Preparatory Academy | C41: Local Revenue | E41: 3401211.3 | F41: 0.00071861458 | G41: 2444.16 | H41: C | K41: 488
A42: 000952 | B42: Columbus Preparatory and Fitness Academy | C42: Local Revenue | E42: 909606 | F42: 0 | G42: 0 | H42: C | K42: 88
A43: 000598 | B43: Coshocton Opportunity School | C43: Local Revenue | E43: 507647 | F43: 0.052460962 | G43: 26631.65 | H43: C | K43: 35
A44: 143412 | B44: Crittenton Community School | C44: Local Revenue | E44: 791513.88 | F44: 0.17240185 | G44: 136458.46 | H44: C | K44: 85
A45: 133959 | B45: Dayton Academy, The | C45: Local Revenue | E45: 5661783.1 | F45: 0.018061978 | G45: 102263 | H45: C | I45: Montgomery | J45: Dayton | K45: 794
A46: 008283 | B46: Dayton Technology Design High School | C46: Local Revenue | E46: 853109.34 | F46: 0.11721827 | G46: 100000 | H46: C | I46: Montgomery | J46: Dayton | K46: 86
A47: 133454 | B47: Dayton View Academy | C47: Local Revenue | E47: 4930062 | F47: 0.025095238 | G47: 123721.08 | H47: C | I47: Montgomery | J47: Dayton | K47: 661
A48: 133264 | B48: Dohn Community | C48: Local Revenue | E48: 949235.02 | F48: 0.020075366 | G48: 19056.24 | H48: C | K48: 98
A49: 143552 | B49: Eagle Academy | C49: Local Revenue | E49: 1355978.3 | F49: 0.0047733875 | G49: 6472.61 | H49: C | K49: 162
A50: 134080 | B50: Eagle Heights Academy | C50: Local Revenue | E50: 8128870.5 | F50: 0.020283367 | G50: 164880.86 | H50: C | K50: 894
A51: 008289 | B51: Eagle Learning Center | C51: Local Revenue | E51: 438809.74 | F51: 0 | G51: 0 | H51: C | K51: 41
A52: 134288 | B52: East End Comm Heritage School | C52: Local Revenue | E52: 1600815.3 | F52: 0.03755307 | G52: 60115.53 | H52: C | K52: 152
A53: 143388 | B53: East End Community School | C53: Local Revenue | E53: 1809630.2 | F53: 0 | G53: 0 | H53: C | I53: Montgomery | J53: Dayton | K53: 221
A54: 133538 | B54: Edge Academy, The | C54: Local Revenue | E54: 2056941.8 | F54: 0.0094495675 | G54: 19437.21 | H54: C | K54: 233
A55: 000523 | B55: Education Alternatives Community School | C55: Local Revenue | E55: 1901827.3 | F55: 0 | G55: 0 | H55: C | I55: Cuyahoga | K55: 339
A56: 133413 | B56: Electronic Classroom Of Tomorrow | C56: Local Revenue | E56: 49974485 | F56: 0.010507981 | G56: 525130.95 | H56: C | K56: 6524
A57: 008067 | B57: Elite Academy of the Arts | C57: Local Revenue | E57: 78367.07 | F57: 0 | G57: 0 | H57: C | K57: 58
A58: 132969 | B58: Elyria Community School | C58: Local Revenue | E58: 1793470.7 | F58: 0.01926637 | G58: 34553.67 | H58: C | K58: 246
A59: 000577 | B59: Emerson Academy | C59: Local Revenue | E59: 0 | F59: -- | H59: C | I59: Montgomery | J59: Dayton | K59: 388
A60: 142976 | B60: Englewood Peace Academy | C60: Local Revenue | E60: 1732192.7 | F60: 0.026788653 | G60: 46403.11 | H60: C | K60: 244
A61: 000585 | B61: FCI Academy | C61: Local Revenue | E61: 4655324.3 | F61: 0.0039895244 | G61: 18572.53 | H61: C | K61: 536
A62: 000402 | B62: Findlay Digital Academy | C62: Local Revenue | E62: 559227.43 | F62: 0.02668088 | G62: 14920.68 | H62: C | K62: 39
A63: 142943 | B63: Focus Learning Academy of Northern Columbus | C63: Local Revenue | E63: 736232.83 | F63: 0 | G63: 0 | H63: C | K63: 183
A64: 142935 | B64: Focus Learning Academy of Southeastern Columbus | C64: Local Revenue | E64: 795520.66 | F64: 0 | G64: 0 | H64: C | K64: 193
A65: 142927 | B65: Focus Learning Academy of Southwest Columbus | C65: Local Revenue | E65: 727034.75 | F65: 0 | G65: 0 | H65: C | K65: 188
A66: 149328 | B66: Foxfire Center For Student Success | C66: Local Revenue | E66: 981473.16 | F66: 0.018604717 | G66: 18260.03 | H66: C | K66: 105
A67: 000445 | B67: General Chappie James Leadership Academy | C67: Local Revenue | E67: 833238.87 | F67: 0.0080378751 | G67: 6697.47 | H67: C | I67: Montgomery | J67: Dayton | K67: 88
A68: 000143 | B68: George A. Phillips Academy | C68: Local Revenue | E68: 1674388.4 | F68: 0.0020729777 | G68: 3470.97 | H68: C | K68: 216
A69: 133967 | B69: George Washington Carver Preparatory Academy | C69: Local Revenue | E69: 1219242.4 | F69: 0 | G69: 0 | H69: C | K69: 194
A70: 000131 | B70: Glass City Academy | C70: Local Revenue | E70: 1296747.6 | F70: 0.087188241 | G70: 113061.14 | H70: C | K70: 180
A71: 133421 | B71: Graham School, The | C71: Local Revenue | E71: 1701855.9 | F71: 0.13101131 | G71: 222962.37 | H71: C | K71: 216
A72: 143370 | B72: Granville T Woods Comm Shule | C72: Local Revenue | E72: 662280.16 | F72: 0.017601947 | G72: 11657.42 | H72: C | K72: 131
A73: 143198 | B73: Great Western Academy | C73: Local Revenue | E73: 3812153 | F73: 0.0030344558 | G73: 11567.81 | H73: C | K73: 535
A74: 143446 | B74: Greater Achievement Community School | C74: Local Revenue | E74: 0 | F74: -- | H74: C | I74: Cuyahoga | J74: Cleveland | K74: 218
A75: 000418 | B75: Greater Heights Academy | C75: Local Revenue | E75: 7954976.9 | F75: 0 | G75: 0 | H75: C | I75: Cuyahoga | J75: Cleveland | K75: 1041
A76: 008287 | B76: Groveport Community School | C76: Local Revenue | E76: 1706352 | F76: 0.0024334428 | G76: 4152.31 | H76: C | K76: 229
A77: 143602 | B77: Hamilton Cnty Math & Science | C77: Local Revenue | E77: 2152877.7 | F77: 0.010811185 | G77: 23275.16 | H77: C | K77: 327
A78: 000197 | B78: Hamilton Local Digital Academy | C78: Local Revenue | E78: 603347.98 | F78: 0.82928566 | G78: 500347.83 | H78: c | K78: 65
A79: 134106 | B79: Harmony Community School | C79: Local Revenue | E79: 4620528.6 | F79: 1 | G79: 4620528.6 | H79: C | K79: 675
A80: 008286 | B80: Harvard Avenue Community School | C80: Local Revenue | E80: 2407551.4 | F80: 4.1535977e-05 | G80: 100 | H80: C | K80: 310
A81: 000613 | B81: Heir Force Community School | C81: Local Revenue | E81: 1782957 | F81: 0.0022338396 | G81: 3982.84 | H81: C | K81: 164
A82: 134189 | B82: Hope Academy Broadway Campus | C82: Local Revenue | E82: 3716277.5 | F82: 0.0063868617 | G82: 23735.35 | H82: C | I82: Cuyahoga | J82: Cleveland | K82: 497
A83: 134221 | B83: Hope Academy Brown St Campus | C83: Local Revenue | E83: 2054278.3 | F83: 0.0037675714 | G83: 7739.64 | H83: C | K83: 250
A84: 133850 | B84: Hope Academy Canton Campus | C84: Local Revenue | E84: 3024077.8 | F84: 0.0044339038 | G84: 13408.47 | H84: C | K84: 376
A85: 134205 | B85: Hope Academy Cathedral Campus | C85: Local Revenue | E85: 3615626.7 | F85: 0.013364289 | G85: 48320.28 | H85: C | I85: Cuyahoga | J85: Cleveland | K85: 460
A86: 134197 | B86: Hope Academy Chapelside Campus | C86: Local Revenue | E86: 3711726.1 | F86: 0.0041771805 | G86: 15504.55 | H86: C | I86: Cuyahoga | J86: Cleveland | K86: 460
A87: 143313 | B87: Hope Academy Cuyahoga Campus | C87: Local Revenue | E87: 4017568.6 | F87: 0.004879384 | G87: 19603.26 | H87: C | I87: Cuyahoga | J87: Cleveland | K87: 510
A88: 000195 | B88: Hope Academy East Campus | C88: Local Revenue | E88: 3429982.1 | F88: 0.0034535982 | G88: 11845.78 | H88: C | I88: Cuyahoga | J88: Cleveland | K88: 440
A89: 008115 | B89: Hope Academy High School - Cleveland Campus | C89: Local Revenue | E89: 2325344.9 | F89: 0.0035050714 | G89: 8150.5 | H89: C | I89: Cuyahoga | J89: Cleveland | K89: 356
A90: 133819 | B90: Hope Academy Lincoln Park | C90: Local Revenue | E90: 1459662.6 | F90: 0.0019847327 | G90: 2897.04 | H90: C | I90: Cuyahoga | J90: Cleveland | K90: 176
A91: 000575 | B91: Hope Academy Northwest Campus | C91: Local Revenue | E91: 3233072.7 | F91: 0.003113487 | G91: 10066.13 | H91: C | I91: Cuyahoga | J91: Cleveland | K91: 352
A92: 134213 | B92: Hope Academy University | C92: Local Revenue | E92: 2793895.7 | F92: 0.0027647238 | G92: 7724.35 | H92: C | K92: 354
A93: 142968 | B93: Hope Northcoast Academy | C93: Local Revenue | E93: 2229418.9 | F93: 0.0044792255 | G93: 9986.07 | H93: C | I93: Cuyahoga | J93: Cleveland | K93: 273
A94: 133629 | B94: Horizon Science Acad Cleveland | C94: Local Revenue | E94: 3308027.6 | F94: 0.050503472 | G94: 167066.88 | H94: C | I94: Cuyahoga | J94: Cleveland | K94: 428
A95: 133660 | B95: Horizon Science Academy Columbus | C95: Local Revenue | E95: 4302445.8 | F95: 0.016633153 | G95: 71563.24 | H95: C | K95: 742
A96: 000338 | B96: Horizon Science Academy Toledo | C96: Local Revenue | E96: 1932182.1 | F96: 0.0045395566 | G96: 8771.25 | H96: C | K96: 283
A97: 000804 | B97: Horizon Science Academy-Cincinnati | C97: Local Revenue | E97: 1527935.8 | F97: 0.0054511386 | G97: 8328.99 | H97: C | K97: 177
A98: 000858 | B98: Horizon Science Academy-Cleveland Middle School | C98: Local Revenue | E98: 967906.27 | F98: 0.040500223 | G98: 39200.42 | H98: C | I98: Cuyahoga | J98: Cleveland | K98: 150
A99: 000808 | B99: Horizon Science Academy-Dayton | C99: Local Revenue | E99: 1443280.7 | F99: 0.0090453162 | G99: 13054.93 | H99: C | I99: Montgomery | J99: Dayton | K99: 220
A100: 000838 | B100: Horizon Science Academy-Denison Middle School | C100: Local Revenue | E100: 1847933.7 | F100: 0.0071149467 | G100: 13147.95 | H100: C | I100: Cuyahoga | J100: Cleveland | K100: 321
...

Sheet Master
D1: School Year | H1: Charter | K1: County | L1: City | M1: Enrollment
D2: Metrics | E2: Total Revenue Amount | F2: Revenue Source Pct of Total | G2: Use This Amount | H2: Charter | I2: Conversion | J2: Conversion District | K2: County | L2: City
A3: District | C3: Revenue Source | G3: Note: charter revenues are separate and distinct from district revenues. Do not need to back out charter financial eata from the district files as previously told.
A4: 000125 | B4: Polly Fox Academy Community School | C4: Local Revenue | E4: 1252639.2 | F4: 0.019529359 | G4: =F4*E4 -> 24463.24 | H4: C | M4: 131
A5: 000125 | B5: Polly Fox Academy Community School | C5: State Revenue | E5: 1252639.2 | F5: 0.76300448 | G5: =F5*E5 -> 955769.31 | H5: C
A6: 000125 | B6: Polly Fox Academy Community School | C6: Federal Revenue | E6: 1252639.2 | F6: 0.21746616 | G6: =F6*E6 -> 272406.64 | H6: C
A7: 000130 | B7: Phoenix Academy Community School | C7: Local Revenue | E7: 7379049.3 | F7: 0.21479738 | G7: =F7*E7 -> 1585000.5 | H7: C | M7: 708
A8: 000130 | B8: Phoenix Academy Community School | C8: State Revenue | E8: 7379049.3 | F8: 0.77968003 | G8: =F8*E8 -> 5753297.3 | H8: C
A9: 000130 | B9: Phoenix Academy Community School | C9: Federal Revenue | E9: 7379049.3 | F9: 0.0055225868 | G9: =F9*E9 -> 40751.44 | H9: C
A10: 000131 | B10: Glass City Academy | C10: Local Revenue | E10: 1296747.6 | F10: 0.087188241 | G10: =F10*E10 -> 113061.14 | H10: C | M10: 180
A11: 000131 | B11: Glass City Academy | C11: State Revenue | E11: 1296747.6 | F11: 0.91281176 | G11: =F11*E11 -> 1183686.4 | H11: C
A12: 000131 | B12: Glass City Academy | C12: Federal Revenue | E12: 1296747.6 | F12: 0 | G12: =F12*E12 -> 0 | H12: C
A13: 000138 | B13: Pathway School of Discovery | C13: Local Revenue | E13: 0 | F13: -- | H13: C | K13: Montgomery | L13: Dayton | M13: 679
A14: 000138 | B14: Pathway School of Discovery | C14: State Revenue | E14: 4188670.2 | F14: -- | G14: 4188670.2 | H14: C | K14: Montgomery | L14: Dayton
A15: 000138 | B15: Pathway School of Discovery | C15: Federal Revenue | E15: 0 | F15: -- | H15: C | K15: Montgomery | L15: Dayton
A16: 000139 | B16: Alliance Academy of Cincinnati | C16: Local Revenue | E16: 0 | F16: -- | H16: C | M16: 505
A17: 000139 | B17: Alliance Academy of Cincinnati | C17: State Revenue | E17: 3161899.6 | F17: -- | G17: 3161899.6 | H17: C
A18: 000139 | B18: Alliance Academy of Cincinnati | C18: Federal Revenue | E18: 0 | F18: -- | H18: C
A19: 000140 | B19: Victory Academy of Toledo | C19: Local Revenue | E19: 1136684 | F19: 0.00050960512 | G19: =F19*E19 -> 579.26 | H19: C | M19: 112
A20: 000140 | B20: Victory Academy of Toledo | C20: State Revenue | E20: 1136684 | F20: 0.69867387 | G20: =F20*E20 -> 794171.43 | H20: C
A21: 000140 | B21: Victory Academy of Toledo | C21: Federal Revenue | E21: 1136684 | F21: 0.30081653 | G21: =F21*E21 -> 341933.34 | H21: C
A22: 000143 | B22: George A. Phillips Academy | C22: Local Revenue | E22: 1674388.4 | F22: 0.0020729777 | G22: =F22*E22 -> 3470.97 | H22: C | M22: 216
A23: 000143 | B23: George A. Phillips Academy | C23: State Revenue | E23: 1674388.4 | F23: 0.83561365 | G23: =F23*E23 -> 1399141.9 | H23: C
A24: 000143 | B24: George A. Phillips Academy | C24: Federal Revenue | E24: 1674388.4 | F24: 0.16231337 | G24: =F24*E24 -> 271775.63 | H24: C
A25: 000195 | B25: Hope Academy East Campus | C25: Local Revenue | E25: 3429982.1 | F25: 0.0034535982 | G25: =F25*E25 -> 11845.78 | H25: C | K25: Cuyahoga | L25: Cleveland | M25: 440
A26: 000195 | B26: Hope Academy East Campus | C26: State Revenue | E26: 3429982.1 | F26: 0.86731576 | G26: =F26*E26 -> 2974877.5 | H26: C | K26: Cuyahoga | L26: Cleveland
A27: 000195 | B27: Hope Academy East Campus | C27: Federal Revenue | E27: 3429982.1 | F27: 0.12923064 | G27: =F27*E27 -> 443258.8 | H27: C | K27: Cuyahoga | L27: Cleveland
A28: 000197 | B28: Hamilton Local Digital Academy | C28: Local Revenue | E28: 603347.98 | F28: 0.82928566 | G28: =F28*E28 -> 500347.83 | H28: c | M28: 65
A29: 000197 | B29: Hamilton Local Digital Academy | C29: State Revenue | E29: 603347.98 | F29: 0.004972255 | G29: =F29*E29 -> 3000 | H29: c
A30: 000197 | B30: Hamilton Local Digital Academy | C30: Federal Revenue | E30: 603347.98 | F30: 0.16574208 | G30: =F30*E30 -> 100000.15 | H30: c
A31: 000222 | B31: Wildwood Environmental Academy | C31: Local Revenue | E31: 1853701.4 | F31: 0.001248939 | G31: =F31*E31 -> 2315.16 | H31: C | M31: 190
A32: 000222 | B32: Wildwood Environmental Academy | C32: State Revenue | E32: 1853701.4 | F32: 0.82349874 | G32: =F32*E32 -> 1526520.8 | H32: C
A33: 000222 | B33: Wildwood Environmental Academy | C33: Federal Revenue | E33: 1853701.4 | F33: 0.17525233 | G33: =F33*E33 -> 324865.49 | H33: C
A34: 000235 | B34: International College Preparatory Academy | C34: Local Revenue | E34: 4926715.6 | F34: 0.013378422 | G34: =F34*E34 -> 65911.68 | H34: C | M34: 639
A35: 000235 | B35: International College Preparatory Academy | C35: State Revenue | E35: 4926715.6 | F35: 0.82697827 | G35: =F35*E35 -> 4074286.7 | H35: C
A36: 000235 | B36: International College Preparatory Academy | C36: Federal Revenue | E36: 4926715.6 | F36: 0.15964331 | G36: =F36*E36 -> 786517.18 | H36: C
A37: 000236 | B37: Ohio Connections Academy, Inc | C37: Local Revenue | E37: 7076666.7 | F37: 0.0051544225 | G37: =F37*E37 -> 36476.13 | H37: C | M37: 912
A38: 000236 | B38: Ohio Connections Academy, Inc | C38: State Revenue | E38: 7076666.7 | F38: 0.89244895 | G38: =F38*E38 -> 6315563.8 | H38: C
A39: 000236 | B39: Ohio Connections Academy, Inc | C39: Federal Revenue | E39: 7076666.7 | F39: 0.10239663 | G39: =F39*E39 -> 724626.8 | H39: C
A40: 000277 | B40: Scholarts Preparatory and Career Center for Children | C40: Local Revenue | E40: 842358.61 | F40: 0.00011871428 | G40: =F40*E40 -> 100 | H40: C | M40: 96
A41: 000277 | B41: Scholarts Preparatory and Career Center for Children | C41: State Revenue | E41: 842358.61 | F41: 0.7187242 | G41: =F41*E41 -> 605423.52 | H41: C
A42: 000277 | B42: Scholarts Preparatory and Career Center for Children | C42: Federal Revenue | E42: 842358.61 | F42: 0.28115708 | G42: =F42*E42 -> 236835.09 | H42: C
A43: 000282 | B43: Warren County Virtual Community School | C43: Local Revenue | E43: 867720.61 | F43: 0.016607189 | G43: =F43*E43 -> 14410.4 | H43: C | I43: Yes | J43: Wayne Local | M43: 90
A44: 000282 | B44: Warren County Virtual Community School | C44: State Revenue | E44: 867720.61 | F44: 0.81976522 | G44: =F44*E44 -> 711327.18 | H44: C | I44: Yes | J44: Wayne Local
A45: 000282 | B45: Warren County Virtual Community School | C45: Federal Revenue | E45: 867720.61 | F45: 0.16362759 | G45: =F45*E45 -> 141983.03 | H45: C | I45: Yes | J45: Wayne Local
A46: 000287 | B46: Auglaize County Special Needs School | C46: Local Revenue | E46: 1082082.8 | F46: 0.0098995201 | G46: =F46*E46 -> 10712.1 | H46: C | M46: 35
A47: 000287 | B47: Auglaize County Special Needs School | C47: State Revenue | E47: 1082082.8 | F47: 0.72734357 | G47: =F47*E47 -> 787045.94 | H47: C
A48: 000287 | B48: Auglaize County Special Needs School | C48: Federal Revenue | E48: 1082082.8 | F48: 0.26275691 | G48: =F48*E48 -> 284324.72 | H48: C
A49: 000288 | B49: Auglaize County Educational Academy | C49: Local Revenue | E49: 705727.13 | F49: 0.016722469 | G49: =F49*E49 -> 11801.5 | H49: C | M49: 56
A50: 000288 | B50: Auglaize County Educational Academy | C50: State Revenue | E50: 705727.13 | F50: 0.58630825 | G50: =F50*E50 -> 413773.64 | H50: C
A51: 000288 | B51: Auglaize County Educational Academy | C51: Federal Revenue | E51: 705727.13 | F51: 0.39696928 | G51: =F51*E51 -> 280151.99 | H51: C
A52: 000296 | B52: Summit Academy Columbus | C52: Local Revenue | E52: 968241.67 | F52: 0.004517271 | G52: =F52*E52 -> 4373.81 | H52: C | M52: 66
A53: 000296 | B53: Summit Academy Columbus | C53: State Revenue | E53: 968241.67 | F53: 0.91151728 | G53: =F53*E53 -> 882569.01 | H53: C
A54: 000296 | B54: Summit Academy Columbus | C54: Federal Revenue | E54: 968241.67 | F54: 0.083965453 | G54: =F54*E54 -> 81298.85 | H54: C
A55: 000297 | B55: Summit Academy Dayton | C55: Local Revenue | E55: 1407836.6 | F55: 0.0037008202 | G55: =F55*E55 -> 5210.15 | H55: C | K55: Montgomery | L55: Dayton | M55: 80
A56: 000297 | B56: Summit Academy Dayton | C56: State Revenue | E56: 1407836.6 | F56: 0.93661472 | G56: =F56*E56 -> 1318600.5 | H56: C | K56: Montgomery | L56: Dayton
A57: 000297 | B57: Summit Academy Dayton | C57: Federal Revenue | E57: 1407836.6 | F57: 0.059684456 | G57: =F57*E57 -> 84025.96 | H57: C | K57: Montgomery | L57: Dayton
A58: 000298 | B58: Summit Academy Secondary - Akron | C58: Local Revenue | E58: 954583.08 | F58: 0.0010778004 | G58: =F58*E58 -> 1028.85 | H58: C | M58: 60
A59: 000298 | B59: Summit Academy Secondary - Akron | C59: State Revenue | E59: 954583.08 | F59: 0.9468925 | G59: =F59*E59 -> 903887.56 | H59: C
A60: 000298 | B60: Summit Academy Secondary - Akron | C60: Federal Revenue | E60: 954583.08 | F60: 0.052029699 | G60: =F60*E60 -> 49666.67 | H60: C
A61: 000300 | B61: Summit Academy Secondary - Canton | C61: Local Revenue | E61: 473070.95 | F61: 0.00089204378 | G61: =F61*E61 -> 422 | H61: C | M61: 33
A62: 000300 | B62: Summit Academy Secondary - Canton | C62: State Revenue | E62: 473070.95 | F62: 0.95733911 | G62: =F62*E62 -> 452889.32 | H62: C
A63: 000300 | B63: Summit Academy Secondary - Canton | C63: Federal Revenue | E63: 473070.95 | F63: 0.041768851 | G63: =F63*E63 -> 19759.63 | H63: C
A64: 000301 | B64: Summit Academy Secondary - Lorain | C64: Local Revenue | E64: 461116.57 | F64: 0.0014404817 | G64: =F64*E64 -> 664.23 | H64: C | M64: 32
A65: 000301 | B65: Summit Academy Secondary - Lorain | C65: State Revenue | E65: 461116.57 | F65: 0.95381114 | G65: =F65*E65 -> 439818.12 | H65: C
A66: 000301 | B66: Summit Academy Secondary - Lorain | C66: Federal Revenue | E66: 461116.57 | F66: 0.044748381 | G66: =F66*E66 -> 20634.22 | H66: C
A67: 000302 | B67: Summit Academy Secondary School-Parma | C67: Local Revenue | E67: 2584058.5 | F67: 0.0034880402 | G67: =F67*E67 -> 9013.3 | H67: C | K67: Cuyahoga | L67: Non-CPS | M67: 158
A68: 000302 | B68: Summit Academy Secondary School-Parma | C68: State Revenue | E68: 2584058.5 | F68: 0.90632728 | G68: =F68*E68 -> 2342002.7 | H68: C | K68: Cuyahoga | L68: Non-CPS
A69: 000302 | B69: Summit Academy Secondary School-Parma | C69: Federal Revenue | E69: 2584058.5 | F69: 0.090184684 | G69: =F69*E69 -> 233042.5 | H69: C | K69: Cuyahoga | L69: Non-CPS
A70: 000303 | B70: Summit Academy Secondary - Youngstown | C70: Local Revenue | E70: 1033482.8 | F70: 0.0023829618 | G70: =F70*E70 -> 2462.75 | H70: C | M70: 65
A71: 000303 | B71: Summit Academy Secondary - Youngstown | C71: State Revenue | E71: 1033482.8 | F71: 0.95258196 | G71: =F71*E71 -> 984477.06 | H71: C
A72: 000303 | B72: Summit Academy Secondary - Youngstown | C72: Federal Revenue | E72: 1033482.8 | F72: 0.04503508 | G72: =F72*E72 -> 46542.98 | H72: C
A73: 000304 | B73: Summit Academy Community School-Toledo | C73: Local Revenue | E73: 1832644.5 | F73: 0.0015615413 | G73: =F73*E73 -> 2861.75 | H73: C | M73: 131
A74: 000304 | B74: Summit Academy Community School-Toledo | C74: State Revenue | E74: 1832644.5 | F74: 0.89187225 | G74: =F74*E74 -> 1634484.7 | H74: C
A75: 000304 | B75: Summit Academy Community School-Toledo | C75: Federal Revenue | E75: 1832644.5 | F75: 0.10656621 | G75: =F75*E75 -> 195297.97 | H75: C
A76: 000305 | B76: Summit Academy Community School-Warren | C76: Local Revenue | E76: 1005955.8 | F76: 0.0046163359 | G76: =F76*E76 -> 4643.83 | H76: C | M76: 63
A77: 000305 | B77: Summit Academy Community School-Warren | C77: State Revenue | E77: 1005955.8 | F77: 0.86952384 | G77: =F77*E77 -> 874702.58 | H77: C
A78: 000305 | B78: Summit Academy Community School-Warren | C78: Federal Revenue | E78: 1005955.8 | F78: 0.12585982 | G78: =F78*E78 -> 126609.42 | H78: C
A79: 000306 | B79: Summit Academy Cincinnati | C79: Local Revenue | E79: 1289628 | F79: 0.002147123 | G79: =F79*E79 -> 2768.99 | H79: C | M79: 72
A80: 000306 | B80: Summit Academy Cincinnati | C80: State Revenue | E80: 1289628 | F80: 0.93578246 | G80: =F80*E80 -> 1206811.3 | H80: C
A81: 000306 | B81: Summit Academy Cincinnati | C81: Federal Revenue | E81: 1289628 | F81: 0.062070417 | G81: =F81*E81 -> 80047.75 | H81: C
A82: 000316 | B82: Westpark Community Middle School | C82: Local Revenue | E82: 865196.41 | F82: 0.018566108 | G82: =F82*E82 -> 16063.33 | H82: C | K82: Cuyahoga | L82: Cleveland | M82: 95
A83: 000316 | B83: Westpark Community Middle School | C83: State Revenue | E83: 865196.41 | F83: 0.7058033 | G83: =F83*E83 -> 610658.48 | H83: C | K83: Cuyahoga | L83: Cleveland
A84: 000316 | B84: Westpark Community Middle School | C84: Federal Revenue | E84: 865196.41 | F84: 0.27563059 | G84: =F84*E84 -> 238474.6 | H84: C | K84: Cuyahoga | L84: Cleveland
A85: 000318 | B85: Lorain Academy For Gifted Students | C85: Local Revenue | E85: 689184.34 | F85: 0.11162224 | G85: =F85*E85 -> 76928.3 | H85: C | M85: 61
A86: 000318 | B86: Lorain Academy For Gifted Students | C86: State Revenue | E86: 689184.34 | F86: 0.85220041 | G86: =F86*E86 -> 587323.18 | H86: C
A87: 000318 | B87: Lorain Academy For Gifted Students | C87: Federal Revenue | E87: 689184.34 | F87: 0.036177346 | G87: =F87*E87 -> 24932.86 | H87: C
A88: 000319 | B88: Madison Community School | C88: Local Revenue | E88: 1490755.8 | F88: 0.0056283262 | G88: =F88*E88 -> 8390.46 | H88: C | K88: Cuyahoga | L88: Cleveland | M88: 153
A89: 000319 | B89: Madison Community School | C89: State Revenue | E89: 1490755.8 | F89: 0.73570676 | G89: =F89*E89 -> 1096759.1 | H89: C | K89: Cuyahoga | L89: Cleveland
A90: 000319 | B90: Madison Community School | C90: Federal Revenue | E90: 1490755.8 | F90: 0.25866492 | G90: =F90*E90 -> 385606.23 | H90: C | K90: Cuyahoga | L90: Cleveland
A91: 000320 | B91: Lorain Community Middle School | C91: Local Revenue | E91: 967825.37 | F91: 0.032354876 | G91: =F91*E91 -> 31313.87 | H91: C | M91: 97
A92: 000320 | B92: Lorain Community Middle School | C92: State Revenue | E92: 967825.37 | F92: 0.71907984 | G92: =F92*E92 -> 695943.71 | H92: C
A93: 000320 | B93: Lorain Community Middle School | C93: Federal Revenue | E93: 967825.37 | F93: 0.24856529 | G93: =F93*E93 -> 240567.79 | H93: C
A94: 000321 | B94: Old Brooklyn Community Middle School | C94: Local Revenue | E94: 802536.76 | F94: 0.014883219 | G94: =F94*E94 -> 11944.33 | H94: C | K94: Cuyahoga | L94: Cleveland | M94: 91
A95: 000321 | B95: Old Brooklyn Community Middle School | C95: State Revenue | E95: 802536.76 | F95: 0.73940061 | G95: =F95*E95 -> 593396.17 | H95: C | K95: Cuyahoga | L95: Cleveland
A96: 000321 | B96: Old Brooklyn Community Middle School | C96: Federal Revenue | E96: 802536.76 | F96: 0.24571617 | G96: =F96*E96 -> 197196.26 | H96: C | K96: Cuyahoga | L96: Cleveland
A97: 000338 | B97: Horizon Science Academy Toledo | C97: Local Revenue | E97: 1932182.1 | F97: 0.0045395566 | G97: =F97*E97 -> 8771.25 | H97: C | M97: 283
A98: 000338 | B98: Horizon Science Academy Toledo | C98: State Revenue | E98: 1932182.1 | F98: 0.87937434 | G98: =F98*E98 -> 1699111.3 | H98: C
A99: 000338 | B99: Horizon Science Academy Toledo | C99: Federal Revenue | E99: 1932182.1 | F99: 0.1160861 | G99: =F99*E99 -> 224299.49 | H99: C
A100: 000343 | B100: Chase Academy for Communication Arts | C100: Local Revenue | E100: 1829347 | F100: 0.0036094847 | G100: =F100*E100 -> 6603 | H100: C | M100: 221
...
