Workbook
Name Rents: 'LIHTCRents 12'!$A$19:$AP$54

Sheet Sources
A1: SOURCES OF FUNDING
A3: Project Name: | E3: Date: | F3: 40909
A5: If mixed use project, see comment | B5: RESIDENTIAL | G5: COMMERCIAL
A6: Funding Source | B6: HOME Match (check) | C6: Committed | D6: Conditional | E6: Tentative | F6: Anticipated or Firm Commitment Date | G6: Commercial | H6: Anticipated or Firm Commitment Date
A8: OHCS GRANTS & EQUITY
A9: LIHTC Equity | E9: ='LIHTC Calculation'!F62 -> 0
A10: Trust Fund
A11: Preservation
A12: LI Weatherization Program
A13: HELP
A14: OTHER ____________________
A15: Total OHCS Grants & Equity | C15: =SUM(C9:C14) -> 0 | D15: =SUM(D9:D14) -> 0 | E15: =SUM(E9:E14) -> 0
A17: OHCS LOANS
A18: Tax Exempt Bonds
A19: Trust Fund
A20: Preservation
A21: ORR
A22: HELP
A23: OTHER ____________________
A24: Total OHCS Loans | C24: =SUM(C18:C23) -> 0 | D24: =SUM(D18:D23) -> 0 | E24: =SUM(E18:E23) -> 0
A26: PHB SOURCES
A27: Tax Increment Financing
A28: HOME
A29: SDC Waivers
A30: Tax Exemptions
A31: OTHER ____________________
A32: Total PHB | C32: =SUM(C27:C31) -> 0 | D32: =SUM(D27:D31) -> 0 | E32: =SUM(E27:E31) -> 0
A34: OTHER LOANS
A35: Permanent Loan (bank name)
A40: Total OTHER Loans | C40: =SUM(C35:C39) -> 0 | D40: =SUM(D35:D39) -> 0 | E40: =SUM(E35:E39) -> 0
A42: OTHER GRANTS
A48: Total OTHER Grants | C48: =SUM(C43:C47) -> 0 | D48: =SUM(D43:D47) -> 0 | E48: =SUM(E43:E47) -> 0
A50: APPLICANT CONTRIBUTIONS
A51: Cash
A52: Deferred Development Fee
A55: Total Applicant Contribution | C55: =SUM(C51:C54) -> 0 | D55: =SUM(D51:D54) -> 0 | E55: =SUM(E51:E54) -> 0
A57: OTHER:
A58: Cashflow During Rehab
A61: Total Other Funds | C61: =SUM(C58:C60) -> 0 | D61: =SUM(D58:D60) -> 0 | E61: =SUM(E58:E60) -> 0
G62: =SUM(G9:G61) -> 0
A63: SUBTOTALS | C63: =C61+C55+C48+C40+C32+C24+C15 -> 0 | D63: =D61+D55+D48+D40+D32+D24+D15 -> 0 | E63: =E61+E55+E48+E40+E32+E24+E15 -> 0
A65: TOTAL FUND SOURCES | C65: =C63+D63+E63 -> 0
A66: Surplus or Gap | C66: =IF(+'Uses of Funds'!E130-C65=0," ",+'Uses of Funds'!E130-C65) | D66: (Note: Total Fund Sources must match "Total Project Cost" from Uses of Funding page.)
A69: Other OHCS non-equity sources:
A70: Oregon Affordable Housing Tax Credit (OAHTC) | E70: =+'OAHTC Calculation'!D9 -> 0 | F70: (loan amount)
A71: GHAP construction bridge loan | F71: (loan amount)
A72: GHAP capitol needs assessment short term loan | F72: (loan amount)
A73: GHAP operating subsidy
A74: Predevelopment Loan | F74: (loan amount)

Sheet Uses of Funds
A1: USES OF FUNDING
A2: Project Name: | C2: =Sources!$B$3 -> 0 | H2: Date: | I2: =Sources!F3 -> 40909
A4: Acq/Rehab
A5: IRS Setaside
A6: Number of Units:
A7: Gross Residential Square Footage:
A8: Net Residential Square Footage (for info only, not used in calcs)
A9: Common Areas: | T9: These two columns are for
A10: Commercial/other | T10: LIHTC APPLICANTS ONLY
A11: Total Square Footage: | C11: =SUM(C7:C10)-C8 -> 0
B13: If mixed use project, see comment | D13: COMMERCIAL | E13: RESIDENTIAL
C14: Total | D14: Commercial | E14: (A) Original Application | F14: Cost per Unit | G14: Cost per Square Foot | H14: Cost as % of Total | I14: (B) Carryover Application | J14: % Diff (B/A) | K14: Cost per Unit | L14: Cost per Square Foot | M14: Cost as % of Total | N14: (C) Final Application | O14: % Diff (C/B) | P14: Cost per Unit | Q14: Cost per Square Foot | R14: Cost as % of Total | S14: Funding Source | T14: Reasonably Expected Basis | U14: Estimated Gross Expended by Carryover Date
A16: Acquisition Costs
B17: Purchase Price:
B18: Land | C18: =D18+E18 -> 0 | F18: =E18/$C$6 -> #DIV/0! | G18: =E18/($C$7+$C$9) -> #DIV/0! | H18: =E18/$E$130 -> #DIV/0! | J18: =(I18/E18)-1 -> #DIV/0! | K18: =I18/$C$6 -> #DIV/0! | L18: =I18/($C$7+$C$9) -> #DIV/0! | M18: =I18/$I$130 -> #DIV/0! | O18: =(N18/I18)-1 -> #DIV/0! | P18: =N18/$C$6 -> #DIV/0! | Q18: =N18/($C$7+$C$9) -> #DIV/0! | R18: =N18/$N$130 -> #DIV/0!
B19: Improvements | C19: =D19+E19 -> 0 | F19: =E19/$C$6 -> #DIV/0! | G19: =E19/($C$7+$C$9) -> #DIV/0! | H19: =E19/$E$130 -> #DIV/0! | J19: =(I19/E19)-1 -> #DIV/0! | K19: =I19/$C$6 -> #DIV/0! | L19: =I19/($C$7+$C$9) -> #DIV/0! | M19: =I19/$I$130 -> #DIV/0! | O19: =(N19/I19)-1 -> #DIV/0! | P19: =N19/$C$6 -> #DIV/0! | Q19: =N19/($C$7+$C$9) -> #DIV/0! | R19: =N19/$N$130 -> #DIV/0! | T19: =E19 -> 0
B20: Liens and Other Taxes | C20: =D20+E20 -> 0 | F20: =E20/$C$6 -> #DIV/0! | G20: =E20/($C$7+$C$9) -> #DIV/0! | H20: =E20/$E$130 -> #DIV/0! | J20: =(I20/E20)-1 -> #DIV/0! | K20: =I20/$C$6 -> #DIV/0! | L20: =I20/($C$7+$C$9) -> #DIV/0! | M20: =I20/$I$130 -> #DIV/0! | O20: =(N20/I20)-1 -> #DIV/0! | P20: =N20/$C$6 -> #DIV/0! | Q20: =N20/($C$7+$C$9) -> #DIV/0! | R20: =N20/$N$130 -> #DIV/0! | T20: =E20 -> 0
B21: Closing/Recording | C21: =D21+E21 -> 0 | F21: =E21/$C$6 -> #DIV/0! | G21: =E21/($C$7+$C$9) -> #DIV/0! | H21: =E21/$E$130 -> #DIV/0! | J21: =(I21/E21)-1 -> #DIV/0! | K21: =I21/$C$6 -> #DIV/0! | L21: =I21/($C$7+$C$9) -> #DIV/0! | M21: =I21/$I$130 -> #DIV/0! | O21: =(N21/I21)-1 -> #DIV/0! | P21: =N21/$C$6 -> #DIV/0! | Q21: =N21/($C$7+$C$9) -> #DIV/0! | R21: =N21/$N$130 -> #DIV/0! | T21: =E21 -> 0
B22: Extension Fees | C22: =D22+E22 -> 0 | F22: =E22/$C$6 -> #DIV/0! | G22: =E22/($C$7+$C$9) -> #DIV/0! | H22: =E22/$E$130 -> #DIV/0! | J22: =(I22/E22)-1 -> #DIV/0! | K22: =I22/$C$6 -> #DIV/0! | L22: =I22/($C$7+$C$9) -> #DIV/0! | M22: =I22/$I$130 -> #DIV/0! | O22: =(N22/I22)-1 -> #DIV/0! | P22: =N22/$C$6 -> #DIV/0! | Q22: =N22/($C$7+$C$9) -> #DIV/0! | R22: =N22/$N$130 -> #DIV/0! | T22: =E22 -> 0
B23: Other: | C23: =D23+E23 -> 0 | F23: =E23/$C$6 -> #DIV/0! | G23: =E23/($C$7+$C$9) -> #DIV/0! | H23: =E23/$E$130 -> #DIV/0! | J23: =(I23/E23)-1 -> #DIV/0! | K23: =I23/$C$6 -> #DIV/0! | L23: =I23/($C$7+$C$9) -> #DIV/0! | M23: =I23/$I$130 -> #DIV/0! | O23: =(N23/I23)-1 -> #DIV/0! | P23: =N23/$C$6 -> #DIV/0! | Q23: =N23/($C$7+$C$9) -> #DIV/0! | R23: =N23/$N$130 -> #DIV/0! | T23: =E23 -> 0
B25: Acquisition Costs Subtotal: | C25: =SUM(C17:C24) -> 0 | D25: =SUM(D17:D24) -> 0 | E25: =SUM(E18:E23) -> 0 | F25: =E25/$C$6 -> #DIV/0! | G25: =E25/($C$7+$C$9) -> #DIV/0! | H25: =E25/$E$130 -> #DIV/0! | I25: =SUM(I18:I24) -> 0 | J25: =(I25/E25)-1 -> #DIV/0! | K25: =I25/$C$6 -> #DIV/0! | L25: =I25/($C$7+$C$9) -> #DIV/0! | M25: =I25/$I$130 -> #DIV/0! | N25: =SUM(N18:N24) -> 0 | O25: =(N25/I25)-1 -> #DIV/0! | P25: =N25/$C$6 -> #DIV/0! | Q25: =N25/($C$7+$C$9) -> #DIV/0! | R25: =N25/$N$130 -> #DIV/0! | T25: =SUM(T18:T23) -> 0 | U25: =SUM(U18:U23) -> 0
A27: Construction Costs
B28: Off-site Work | C28: =D28+E28 -> 0 | F28: =E28/$C$6 -> #DIV/0! | G28: =E28/($C$7+$C$9) -> #DIV/0! | H28: =E28/$E$130 -> #DIV/0! | J28: =(I28/E28)-1 -> #DIV/0! | K28: =I28/$C$6 -> #DIV/0! | L28: =I28/($C$7+$C$9) -> #DIV/0! | M28: =I28/$I$130 -> #DIV/0! | O28: =(N28/I28)-1 -> #DIV/0! | P28: =N28/$C$6 -> #DIV/0! | Q28: =N28/($C$7+$C$9) -> #DIV/0! | R28: =N28/$N$130 -> #DIV/0!
B29: On-site Work | C29: =D29+E29 -> 0 | F29: =E29/$C$6 -> #DIV/0! | G29: =E29/($C$7+$C$9) -> #DIV/0! | H29: =E29/$E$130 -> #DIV/0! | J29: =(I29/E29)-1 -> #DIV/0! | K29: =I29/$C$6 -> #DIV/0! | L29: =I29/($C$7+$C$9) -> #DIV/0! | M29: =I29/$I$130 -> #DIV/0! | O29: =(N29/I29)-1 -> #DIV/0! | P29: =N29/$C$6 -> #DIV/0! | Q29: =N29/($C$7+$C$9) -> #DIV/0! | R29: =N29/$N$130 -> #DIV/0! | T29: =E29 -> 0
B30: Hazardous Materials Abatement | C30: =D30+E30 -> 0 | F30: =E30/$C$6 -> #DIV/0! | G30: =E30/($C$7+$C$9) -> #DIV/0! | H30: =E30/$E$130 -> #DIV/0! | J30: =(I30/E30)-1 -> #DIV/0! | K30: =I30/$C$6 -> #DIV/0! | L30: =I30/($C$7+$C$9) -> #DIV/0! | M30: =I30/$I$130 -> #DIV/0! | O30: =(N30/I30)-1 -> #DIV/0! | P30: =N30/$C$6 -> #DIV/0! | Q30: =N30/($C$7+$C$9) -> #DIV/0! | R30: =N30/$N$130 -> #DIV/0! | T30: =E30 -> 0
B31: Demolition | C31: =D31+E31 -> 0 | F31: =E31/$C$6 -> #DIV/0! | G31: =E31/($C$7+$C$9) -> #DIV/0! | H31: =E31/$E$130 -> #DIV/0! | J31: =(I31/E31)-1 -> #DIV/0! | K31: =I31/$C$6 -> #DIV/0! | L31: =I31/($C$7+$C$9) -> #DIV/0! | M31: =I31/$I$130 -> #DIV/0! | O31: =(N31/I31)-1 -> #DIV/0! | P31: =N31/$C$6 -> #DIV/0! | Q31: =N31/($C$7+$C$9) -> #DIV/0! | R31: =N31/$N$130 -> #DIV/0! | T31: =E31 -> 0
B32: Residential Building | C32: =D32+E32 -> 0 | F32: =E32/$C$6 -> #DIV/0! | G32: =E32/($C$7+$C$9) -> #DIV/0! | H32: =E32/$E$130 -> #DIV/0! | J32: =(I32/E32)-1 -> #DIV/0! | K32: =I32/$C$6 -> #DIV/0! | L32: =I32/($C$7+$C$9) -> #DIV/0! | M32: =I32/$I$130 -> #DIV/0! | O32: =(N32/I32)-1 -> #DIV/0! | P32: =N32/$C$6 -> #DIV/0! | Q32: =N32/($C$7+$C$9) -> #DIV/0! | R32: =N32/$N$130 -> #DIV/0! | T32: =E32 -> 0
B33: Commercial Space/Building | C33: =D33+E33 -> 0 | F33: =E33/$C$6 -> #DIV/0! | G33: =E33/($C$7+$C$9) -> #DIV/0! | H33: =E33/$E$130 -> #DIV/0! | J33: =(I33/E33)-1 -> #DIV/0! | K33: =I33/$C$6 -> #DIV/0! | L33: =I33/($C$7+$C$9) -> #DIV/0! | M33: =I33/$I$130 -> #DIV/0! | O33: =(N33/I33)-1 -> #DIV/0! | P33: =N33/$C$6 -> #DIV/0! | Q33: =N33/($C$7+$C$9) -> #DIV/0! | R33: =N33/$N$130 -> #DIV/0!
B34: Common Use Facilities | C34: =D34+E34 -> 0 | F34: =E34/$C$6 -> #DIV/0! | G34: =E34/($C$7+$C$9) -> #DIV/0! | H34: =E34/$E$130 -> #DIV/0! | J34: =(I34/E34)-1 -> #DIV/0! | K34: =I34/$C$6 -> #DIV/0! | L34: =I34/($C$7+$C$9) -> #DIV/0! | M34: =I34/$I$130 -> #DIV/0! | O34: =(N34/I34)-1 -> #DIV/0! | P34: =N34/$C$6 -> #DIV/0! | Q34: =N34/($C$7+$C$9) -> #DIV/0! | R34: =N34/$N$130 -> #DIV/0! | T34: =E34 -> 0
B35: Elevator | C35: =D35+E35 -> 0 | F35: =E35/$C$6 -> #DIV/0! | G35: =E35/($C$7+$C$9) -> #DIV/0! | H35: =E35/$E$130 -> #DIV/0! | J35: =(I35/E35)-1 -> #DIV/0! | K35: =I35/$C$6 -> #DIV/0! | L35: =I35/($C$7+$C$9) -> #DIV/0! | M35: =I35/$I$130 -> #DIV/0! | O35: =(N35/I35)-1 -> #DIV/0! | P35: =N35/$C$6 -> #DIV/0! | Q35: =N35/($C$7+$C$9) -> #DIV/0! | R35: =N35/$N$130 -> #DIV/0! | T35: =E35 -> 0
B36: Laundry Facilities | C36: =D36+E36 -> 0 | F36: =E36/$C$6 -> #DIV/0! | G36: =E36/($C$7+$C$9) -> #DIV/0! | H36: =E36/$E$130 -> #DIV/0! | J36: =(I36/E36)-1 -> #DIV/0! | K36: =I36/$C$6 -> #DIV/0! | L36: =I36/($C$7+$C$9) -> #DIV/0! | M36: =I36/$I$130 -> #DIV/0! | O36: =(N36/I36)-1 -> #DIV/0! | P36: =N36/$C$6 -> #DIV/0! | Q36: =N36/($C$7+$C$9) -> #DIV/0! | R36: =N36/$N$130 -> #DIV/0! | T36: =E36 -> 0
B37: Storage/Garages | C37: =D37+E37 -> 0 | F37: =E37/$C$6 -> #DIV/0! | G37: =E37/($C$7+$C$9) -> #DIV/0! | H37: =E37/$E$130 -> #DIV/0! | J37: =(I37/E37)-1 -> #DIV/0! | K37: =I37/$C$6 -> #DIV/0! | L37: =I37/($C$7+$C$9) -> #DIV/0! | M37: =I37/$I$130 -> #DIV/0! | O37: =(N37/I37)-1 -> #DIV/0! | P37: =N37/$C$6 -> #DIV/0! | Q37: =N37/($C$7+$C$9) -> #DIV/0! | R37: =N37/$N$130 -> #DIV/0! | T37: =E37 -> 0
B38: Landscaping | C38: =D38+E38 -> 0 | F38: =E38/$C$6 -> #DIV/0! | G38: =E38/($C$7+$C$9) -> #DIV/0! | H38: =E38/$E$130 -> #DIV/0! | J38: =(I38/E38)-1 -> #DIV/0! | K38: =I38/$C$6 -> #DIV/0! | L38: =I38/($C$7+$C$9) -> #DIV/0! | M38: =I38/$I$130 -> #DIV/0! | O38: =(N38/I38)-1 -> #DIV/0! | P38: =N38/$C$6 -> #DIV/0! | Q38: =N38/($C$7+$C$9) -> #DIV/0! | R38: =N38/$N$130 -> #DIV/0! | T38: =E38 -> 0
B39: General Conditions | C39: =D39+E39 -> 0 | F39: =E39/$C$6 -> #DIV/0! | G39: =E39/($C$7+$C$9) -> #DIV/0! | H39: =E39/$E$130 -> #DIV/0! | J39: =(I39/E39)-1 -> #DIV/0! | K39: =I39/$C$6 -> #DIV/0! | L39: =I39/($C$7+$C$9) -> #DIV/0! | M39: =I39/$I$130 -> #DIV/0! | O39: =(N39/I39)-1 -> #DIV/0! | P39: =N39/$C$6 -> #DIV/0! | Q39: =N39/($C$7+$C$9) -> #DIV/0! | R39: =N39/$N$130 -> #DIV/0! | T39: =E39 -> 0
B40: Builder's Risk Insurance | C40: =D40+E40 -> 0 | F40: =E40/$C$6 -> #DIV/0! | G40: =E40/($C$7+$C$9) -> #DIV/0! | H40: =E40/$E$130 -> #DIV/0! | J40: =(I40/E40)-1 -> #DIV/0! | K40: =I40/$C$6 -> #DIV/0! | L40: =I40/($C$7+$C$9) -> #DIV/0! | M40: =I40/$I$130 -> #DIV/0! | O40: =(N40/I40)-1 -> #DIV/0! | P40: =N40/$C$6 -> #DIV/0! | Q40: =N40/($C$7+$C$9) -> #DIV/0! | R40: =N40/$N$130 -> #DIV/0! | T40: =E40 -> 0
B41: Contractor Overhead | C41: =D41+E41 -> 0 | F41: =E41/$C$6 -> #DIV/0! | G41: =E41/($C$7+$C$9) -> #DIV/0! | H41: =E41/$E$130 -> #DIV/0! | J41: =(I41/E41)-1 -> #DIV/0! | K41: =I41/$C$6 -> #DIV/0! | L41: =I41/($C$7+$C$9) -> #DIV/0! | M41: =I41/$I$130 -> #DIV/0! | O41: =(N41/I41)-1 -> #DIV/0! | P41: =N41/$C$6 -> #DIV/0! | Q41: =N41/($C$7+$C$9) -> #DIV/0! | R41: =N41/$N$130 -> #DIV/0! | T41: =E41 -> 0
B42: Contractor Profit | C42: =D42+E42 -> 0 | F42: =E42/$C$6 -> #DIV/0! | G42: =E42/($C$7+$C$9) -> #DIV/0! | H42: =E42/$E$130 -> #DIV/0! | J42: =(I42/E42)-1 -> #DIV/0! | K42: =I42/$C$6 -> #DIV/0! | L42: =I42/($C$7+$C$9) -> #DIV/0! | M42: =I42/$I$130 -> #DIV/0! | O42: =(N42/I42)-1 -> #DIV/0! | P42: =N42/$C$6 -> #DIV/0! | Q42: =N42/($C$7+$C$9) -> #DIV/0! | R42: =N42/$N$130 -> #DIV/0! | T42: =E42 -> 0
B43: Contingency | C43: =D43+E43 -> 0 | F43: =E43/$C$6 -> #DIV/0! | G43: =E43/($C$7+$C$9) -> #DIV/0! | H43: =E43/$E$130 -> #DIV/0! | J43: =(I43/E43)-1 -> #DIV/0! | K43: =I43/$C$6 -> #DIV/0! | L43: =I43/($C$7+$C$9) -> #DIV/0! | M43: =I43/$I$130 -> #DIV/0! | O43: =(N43/I43)-1 -> #DIV/0! | P43: =N43/$C$6 -> #DIV/0! | Q43: =N43/($C$7+$C$9) -> #DIV/0! | R43: =N43/$N$130 -> #DIV/0! | T43: =E43 -> 0
B44: FF&E (Common Area Furnishings) | C44: =D44+E44 -> 0 | F44: =E44/$C$6 -> #DIV/0! | G44: =E44/($C$7+$C$9) -> #DIV/0! | H44: =E44/$E$130 -> #DIV/0! | J44: =(I44/E44)-1 -> #DIV/0! | K44: =I44/$C$6 -> #DIV/0! | L44: =I44/($C$7+$C$9) -> #DIV/0! | M44: =I44/$I$130 -> #DIV/0! | O44: =(N44/I44)-1 -> #DIV/0! | P44: =N44/$C$6 -> #DIV/0! | Q44: =N44/($C$7+$C$9) -> #DIV/0! | R44: =N44/$N$130 -> #DIV/0! | T44: =E44 -> 0
B45: Internet Wiring & Equipment | C45: =D45+E45 -> 0 | F45: =E45/$C$6 -> #DIV/0! | G45: =E45/($C$7+$C$9) -> #DIV/0! | H45: =E45/$E$130 -> #DIV/0! | J45: =(I45/E45)-1 -> #DIV/0! | K45: =I45/$C$6 -> #DIV/0! | L45: =I45/($C$7+$C$9) -> #DIV/0! | M45: =I45/$I$130 -> #DIV/0! | O45: =(N45/I45)-1 -> #DIV/0! | P45: =N45/$C$6 -> #DIV/0! | Q45: =N45/($C$7+$C$9) -> #DIV/0! | R45: =N45/$N$130 -> #DIV/0! | T45: =E45 -> 0
... B48: Other: | C48: =D48+E48 -> 0 | F48: =E48/$C$6 -> #DIV/0! | G48: =E48/($C$7+$C$9) -> #DIV/0! | H48: =E48/$E$130 -> #DIV/0! | J48: =(I48/E48)-1 -> #DIV/0! | K48: =I48/$C$6 -> #DIV/0! | L48: =I48/($C$7+$C$9) -> #DIV/0! | M48: =I48/$I$130 -> #DIV/0! | O48: =(N48/I48)-1 -> #DIV/0! | P48: =N48/$C$6 -> #DIV/0! | Q48: =N48/($C$7+$C$9) -> #DIV/0! | R48: =N48/$N$130 -> #DIV/0! | T48: =E48 -> 0
B50: Construction Costs Subtotal: | C50: =SUM(C28:C49) -> 0 | D50: =SUM(D28:D49) -> 0 | E50: =SUM(E28:E49) -> 0 | F50: =E50/$C$6 -> #DIV/0! | G50: =E50/($C$7+$C$9) -> #DIV/0! | H50: =E50/$E$130 -> #DIV/0! | I50: =SUM(I28:I48) -> 0 | J50: =(I50/E50)-1 -> #DIV/0! | K50: =I50/$C$6 -> #DIV/0! | L50: =I50/($C$7+$C$9) -> #DIV/0! | M50: =I50/$I$130 -> #DIV/0! | N50: =SUM(N28:N48) -> 0 | O50: =(N50/I50)-1 -> #DIV/0! | P50: =N50/$C$6 -> #DIV/0! | Q50: =N50/($C$7+$C$9) -> #DIV/0! | R50: =N50/$N$130 -> #DIV/0! | T50: =SUM(T28:T49) -> 0 | U50: =SUM(U28:U49) -> 0
A52: Development Costs
B53: Land Use Approvals | C53: =D53+E53 -> 0 | F53: =E53/$C$6 -> #DIV/0! | G53: =E53/($C$7+$C$9) -> #DIV/0! | H53: =E53/$E$130 -> #DIV/0! | J53: =(I53/E53)-1 -> #DIV/0! | K53: =I53/$C$6 -> #DIV/0! | L53: =I53/($C$7+$C$9) -> #DIV/0! | M53: =I53/$I$130 -> #DIV/0! | O53: =(N53/I53)-1 -> #DIV/0! | P53: =N53/$C$6 -> #DIV/0! | Q53: =N53/($C$7+$C$9) -> #DIV/0! | R53: =N53/$N$130 -> #DIV/0! | T53: =E53 -> 0
B54: Building Permits/Fees | C54: =D54+E54 -> 0 | F54: =E54/$C$6 -> #DIV/0! | G54: =E54/($C$7+$C$9) -> #DIV/0! | H54: =E54/$E$130 -> #DIV/0! | J54: =(I54/E54)-1 -> #DIV/0! | K54: =I54/$C$6 -> #DIV/0! | L54: =I54/($C$7+$C$9) -> #DIV/0! | M54: =I54/$I$130 -> #DIV/0! | O54: =(N54/I54)-1 -> #DIV/0! | P54: =N54/$C$6 -> #DIV/0! | Q54: =N54/($C$7+$C$9) -> #DIV/0! | R54: =N54/$N$130 -> #DIV/0! | T54: =E54 -> 0
B55: System Development Charges | C55: =D55+E55 -> 0 | F55: =E55/$C$6 -> #DIV/0! | G55: =E55/($C$7+$C$9) -> #DIV/0! | H55: =E55/$E$130 -> #DIV/0! | J55: =(I55/E55)-1 -> #DIV/0! | K55: =I55/$C$6 -> #DIV/0! | L55: =I55/($C$7+$C$9) -> #DIV/0! | M55: =I55/$I$130 -> #DIV/0! | O55: =(N55/I55)-1 -> #DIV/0! | P55: =N55/$C$6 -> #DIV/0! | Q55: =N55/($C$7+$C$9) -> #DIV/0! | R55: =N55/$N$130 -> #DIV/0! | T55: =E55 -> 0
B56: Market Study | C56: =D56+E56 -> 0 | F56: =E56/$C$6 -> #DIV/0! | G56: =E56/($C$7+$C$9) -> #DIV/0! | H56: =E56/$E$130 -> #DIV/0! | J56: =(I56/E56)-1 -> #DIV/0! | K56: =I56/$C$6 -> #DIV/0! | L56: =I56/($C$7+$C$9) -> #DIV/0! | M56: =I56/$I$130 -> #DIV/0! | O56: =(N56/I56)-1 -> #DIV/0! | P56: =N56/$C$6 -> #DIV/0! | Q56: =N56/($C$7+$C$9) -> #DIV/0! | R56: =N56/$N$130 -> #DIV/0! | T56: =E56 -> 0
B57: Environmental Report | C57: =D57+E57 -> 0 | F57: =E57/$C$6 -> #DIV/0! | G57: =E57/($C$7+$C$9) -> #DIV/0! | H57: =E57/$E$130 -> #DIV/0! | J57: =(I57/E57)-1 -> #DIV/0! | K57: =I57/$C$6 -> #DIV/0! | L57: =I57/($C$7+$C$9) -> #DIV/0! | M57: =I57/$I$130 -> #DIV/0! | O57: =(N57/I57)-1 -> #DIV/0! | P57: =N57/$C$6 -> #DIV/0! | Q57: =N57/($C$7+$C$9) -> #DIV/0! | R57: =N57/$N$130 -> #DIV/0! | T57: =E57 -> 0
B58: Lead Based Paint Report | C58: =D58+E58 -> 0 | F58: =E58/$C$6 -> #DIV/0! | G58: =E58/($C$7+$C$9) -> #DIV/0! | H58: =E58/$E$130 -> #DIV/0! | J58: =(I58/E58)-1 -> #DIV/0! | K58: =I58/$C$6 -> #DIV/0! | L58: =I58/($C$7+$C$9) -> #DIV/0! | M58: =I58/$I$130 -> #DIV/0! | O58: =(N58/I58)-1 -> #DIV/0! | P58: =N58/$C$6 -> #DIV/0! | Q58: =N58/($C$7+$C$9) -> #DIV/0! | R58: =N58/$N$130 -> #DIV/0! | T58: =E58 -> 0
B59: Asbestos Report | C59: =D59+E59 -> 0 | F59: =E59/$C$6 -> #DIV/0! | G59: =E59/($C$7+$C$9) -> #DIV/0! | H59: =E59/$E$130 -> #DIV/0! | J59: =(I59/E59)-1 -> #DIV/0! | K59: =I59/$C$6 -> #DIV/0! | L59: =I59/($C$7+$C$9) -> #DIV/0! | M59: =I59/$I$130 -> #DIV/0! | O59: =(N59/I59)-1 -> #DIV/0! | P59: =N59/$C$6 -> #DIV/0! | Q59: =N59/($C$7+$C$9) -> #DIV/0! | R59: =N59/$N$130 -> #DIV/0! | T59: =E59 -> 0
B60: Soils Report (Geotechnical) | C60: =D60+E60 -> 0 | F60: =E60/$C$6 -> #DIV/0! | G60: =E60/($C$7+$C$9) -> #DIV/0! | H60: =E60/$E$130 -> #DIV/0! | J60: =(I60/E60)-1 -> #DIV/0! | K60: =I60/$C$6 -> #DIV/0! | L60: =I60/($C$7+$C$9) -> #DIV/0! | M60: =I60/$I$130 -> #DIV/0! | O60: =(N60/I60)-1 -> #DIV/0! | P60: =N60/$C$6 -> #DIV/0! | Q60: =N60/($C$7+$C$9) -> #DIV/0! | R60: =N60/$N$130 -> #DIV/0! | T60: =E60 -> 0
B61: Survey | C61: =D61+E61 -> 0 | F61: =E61/$C$6 -> #DIV/0! | G61: =E61/($C$7+$C$9) -> #DIV/0! | H61: =E61/$E$130 -> #DIV/0! | J61: =(I61/E61)-1 -> #DIV/0! | K61: =I61/$C$6 -> #DIV/0! | L61: =I61/($C$7+$C$9) -> #DIV/0! | M61: =I61/$I$130 -> #DIV/0! | O61: =(N61/I61)-1 -> #DIV/0! | P61: =N61/$C$6 -> #DIV/0! | Q61: =N61/($C$7+$C$9) -> #DIV/0! | R61: =N61/$N$130 -> #DIV/0! | T61: =E61 -> 0
B62: Marketing/Advertising | C62: =D62+E62 -> 0 | F62: =E62/$C$6 -> #DIV/0! | G62: =E62/($C$7+$C$9) -> #DIV/0! | H62: =E62/$E$130 -> #DIV/0! | J62: =(I62/E62)-1 -> #DIV/0! | K62: =I62/$C$6 -> #DIV/0! | L62: =I62/($C$7+$C$9) -> #DIV/0! | M62: =I62/$I$130 -> #DIV/0! | O62: =(N62/I62)-1 -> #DIV/0! | P62: =N62/$C$6 -> #DIV/0! | Q62: =N62/($C$7+$C$9) -> #DIV/0! | R62: =N62/$N$130 -> #DIV/0!
B63: Insurance | C63: =D63+E63 -> 0 | F63: =E63/$C$6 -> #DIV/0! | G63: =E63/($C$7+$C$9) -> #DIV/0! | H63: =E63/$E$130 -> #DIV/0! | J63: =(I63/E63)-1 -> #DIV/0! | K63: =I63/$C$6 -> #DIV/0! | L63: =I63/($C$7+$C$9) -> #DIV/0! | M63: =I63/$I$130 -> #DIV/0! | O63: =(N63/I63)-1 -> #DIV/0! | P63: =N63/$C$6 -> #DIV/0! | Q63: =N63/($C$7+$C$9) -> #DIV/0! | R63: =N63/$N$130 -> #DIV/0! | T63: =E63 -> 0
B64: OHCS Fees | C64: =D64+E64 -> 0 | F64: =E64/$C$6 -> #DIV/0! | G64: =E64/($C$7+$C$9) -> #DIV/0! | H64: =E64/$E$130 -> #DIV/0! | J64: =(I64/E64)-1 -> #DIV/0! | K64: =I64/$C$6 -> #DIV/0! | L64: =I64/($C$7+$C$9) -> #DIV/0! | M64: =I64/$I$130 -> #DIV/0! | O64: =(N64/I64)-1 -> #DIV/0! | P64: =N64/$C$6 -> #DIV/0! | Q64: =N64/($C$7+$C$9) -> #DIV/0! | R64: =N64/$N$130 -> #DIV/0! | T64: =E64 -> 0
B65: Other: | C65: =D65+E65 -> 0 | F65: =E65/$C$6 -> #DIV/0! | G65: =E65/($C$7+$C$9) -> #DIV/0! | H65: =E65/$E$130 -> #DIV/0! | J65: =(I65/E65)-1 -> #DIV/0! | K65: =I65/$C$6 -> #DIV/0! | L65: =I65/($C$7+$C$9) -> #DIV/0! | M65: =I65/$I$130 -> #DIV/0! | O65: =(N65/I65)-1 -> #DIV/0! | P65: =N65/$C$6 -> #DIV/0! | Q65: =N65/($C$7+$C$9) -> #DIV/0! | R65: =N65/$N$130 -> #DIV/0! | T65: =E65 -> 0
B66: Other: | C66: =D66+E66 -> 0 | F66: =E66/$C$6 -> #DIV/0! | G66: =E66/($C$7+$C$9) -> #DIV/0! | H66: =E66/$E$130 -> #DIV/0! | J66: =(I66/E66)-1 -> #DIV/0! | K66: =I66/$C$6 -> #DIV/0! | L66: =I66/($C$7+$C$9) -> #DIV/0! | M66: =I66/$I$130 -> #DIV/0! | O66: =(N66/I66)-1 -> #DIV/0! | P66: =N66/$C$6 -> #DIV/0! | Q66: =N66/($C$7+$C$9) -> #DIV/0! | R66: =N66/$N$130 -> #DIV/0! | T66: =E66 -> 0
A68: General Fees
B69: Architectural | C69: =D69+E69 -> 0 | F69: =E69/$C$6 -> #DIV/0! | G69: =E69/($C$7+$C$9) -> #DIV/0! | H69: =E69/$E$130 -> #DIV/0! | J69: =(I69/E69)-1 -> #DIV/0! | K69: =I69/$C$6 -> #DIV/0! | L69: =I69/($C$7+$C$9) -> #DIV/0! | M69: =I69/$I$130 -> #DIV/0! | O69: =(N69/I69)-1 -> #DIV/0! | P69: =N69/$C$6 -> #DIV/0! | Q69: =N69/($C$7+$C$9) -> #DIV/0! | R69: =N69/$N$130 -> #DIV/0! | T69: =E69 -> 0
B70: SPD Architectural Review Fee | C70: =D70+E70 -> 0 | F70: =E70/$C$6 -> #DIV/0! | G70: =E70/($C$7+$C$9) -> #DIV/0! | H70: =E70/$E$130 -> #DIV/0! | J70: =(I70/E70)-1 -> #DIV/0! | K70: =I70/$C$6 -> #DIV/0! | L70: =I70/($C$7+$C$9) -> #DIV/0! | M70: =I70/$I$130 -> #DIV/0! | O70: =(N70/I70)-1 -> #DIV/0! | P70: =N70/$C$6 -> #DIV/0! | Q70: =N70/($C$7+$C$9) -> #DIV/0! | R70: =N70/$N$130 -> #DIV/0! | T70: =E70 -> 0
B71: Engineering | C71: =D71+E71 -> 0 | F71: =E71/$C$6 -> #DIV/0! | G71: =E71/($C$7+$C$9) -> #DIV/0! | H71: =E71/$E$130 -> #DIV/0! | J71: =(I71/E71)-1 -> #DIV/0! | K71: =I71/$C$6 -> #DIV/0! | L71: =I71/($C$7+$C$9) -> #DIV/0! | M71: =I71/$I$130 -> #DIV/0! | O71: =(N71/I71)-1 -> #DIV/0! | P71: =N71/$C$6 -> #DIV/0! | Q71: =N71/($C$7+$C$9) -> #DIV/0! | R71: =N71/$N$130 -> #DIV/0! | T71: =E71 -> 0
B72: Legal/Accounting | C72: =D72+E72 -> 0 | F72: =E72/$C$6 -> #DIV/0! | G72: =E72/($C$7+$C$9) -> #DIV/0! | H72: =E72/$E$130 -> #DIV/0! | J72: =(I72/E72)-1 -> #DIV/0! | K72: =I72/$C$6 -> #DIV/0! | L72: =I72/($C$7+$C$9) -> #DIV/0! | M72: =I72/$I$130 -> #DIV/0! | O72: =(N72/I72)-1 -> #DIV/0! | P72: =N72/$C$6 -> #DIV/0! | Q72: =N72/($C$7+$C$9) -> #DIV/0! | R72: =N72/$N$130 -> #DIV/0! | T72: =E72 -> 0
B73: Cost Certification | C73: =D73+E73 -> 0 | F73: =E73/$C$6 -> #DIV/0! | G73: =E73/($C$7+$C$9) -> #DIV/0! | H73: =E73/$E$130 -> #DIV/0! | J73: =(I73/E73)-1 -> #DIV/0! | K73: =I73/$C$6 -> #DIV/0! | L73: =I73/($C$7+$C$9) -> #DIV/0! | M73: =I73/$I$130 -> #DIV/0! | O73: =(N73/I73)-1 -> #DIV/0! | P73: =N73/$C$6 -> #DIV/0! | Q73: =N73/($C$7+$C$9) -> #DIV/0! | R73: =N73/$N$130 -> #DIV/0! | T73: =E73 -> 0
B74: Appraisals | C74: =D74+E74 -> 0 | F74: =E74/$C$6 -> #DIV/0! | G74: =E74/($C$7+$C$9) -> #DIV/0! | H74: =E74/$E$130 -> #DIV/0! | J74: =(I74/E74)-1 -> #DIV/0! | K74: =I74/$C$6 -> #DIV/0! | L74: =I74/($C$7+$C$9) -> #DIV/0! | M74: =I74/$I$130 -> #DIV/0! | O74: =(N74/I74)-1 -> #DIV/0! | P74: =N74/$C$6 -> #DIV/0! | Q74: =N74/($C$7+$C$9) -> #DIV/0! | R74: =N74/$N$130 -> #DIV/0! | T74: =E74 -> 0
B75: Special Inspections/Testing | C75: =D75+E75 -> 0 | F75: =E75/$C$6 -> #DIV/0! | G75: =E75/($C$7+$C$9) -> #DIV/0! | H75: =E75/$E$130 -> #DIV/0! | J75: =(I75/E75)-1 -> #DIV/0! | K75: =I75/$C$6 -> #DIV/0! | L75: =I75/($C$7+$C$9) -> #DIV/0! | M75: =I75/$I$130 -> #DIV/0! | O75: =(N75/I75)-1 -> #DIV/0! | P75: =N75/$C$6 -> #DIV/0! | Q75: =N75/($C$7+$C$9) -> #DIV/0! | R75: =N75/$N$130 -> #DIV/0! | T75: =E75 -> 0
B76: Developer Fee | C76: =D76+E76 -> 0 | F76: =E76/$C$6 -> #DIV/0! | G76: =E76/($C$7+$C$9) -> #DIV/0! | H76: =E76/$E$130 -> #DIV/0! | J76: =(I76/E76)-1 -> #DIV/0! | K76: =I76/$C$6 -> #DIV/0! | L76: =I76/($C$7+$C$9) -> #DIV/0! | M76: =I76/$I$130 -> #DIV/0! | O76: =(N76/I76)-1 -> #DIV/0! | P76: =N76/$C$6 -> #DIV/0! | Q76: =N76/($C$7+$C$9) -> #DIV/0! | R76: =N76/$N$130 -> #DIV/0! | T76: =E76 -> 0
B77: Consultant Fee | C77: =D77+E77 -> 0 | F77: =E77/$C$6 -> #DIV/0! | G77: =E77/($C$7+$C$9) -> #DIV/0! | H77: =E77/$E$130 -> #DIV/0! | J77: =(I77/E77)-1 -> #DIV/0! | K77: =I77/$C$6 -> #DIV/0! | L77: =I77/($C$7+$C$9) -> #DIV/0! | M77: =I77/$I$130 -> #DIV/0! | O77: =(N77/I77)-1 -> #DIV/0! | P77: =N77/$C$6 -> #DIV/0! | Q77: =N77/($C$7+$C$9) -> #DIV/0! | R77: =N77/$N$130 -> #DIV/0! | T77: =E77 -> 0
B78: Lock Rate Fee | C78: =D78+E78 -> 0 | F78: =E78/$C$6 -> #DIV/0! | G78: =E78/($C$7+$C$9) -> #DIV/0! | H78: =E78/$E$130 -> #DIV/0! | J78: =(I78/E78)-1 -> #DIV/0! | K78: =I78/$C$6 -> #DIV/0! | L78: =I78/($C$7+$C$9) -> #DIV/0! | M78: =I78/$I$130 -> #DIV/0! | O78: =(N78/I78)-1 -> #DIV/0! | P78: =N78/$C$6 -> #DIV/0! | Q78: =N78/($C$7+$C$9) -> #DIV/0! | R78: =N78/$N$130 -> #DIV/0! | T78: =E78 -> 0
B79: 3rd Party Constr Inspection Fee | C79: =D79+E79 -> 0 | F79: =E79/$C$6 -> #DIV/0! | G79: =E79/($C$7+$C$9) -> #DIV/0! | H79: =E79/$E$130 -> #DIV/0! | J79: =(I79/E79)-1 -> #DIV/0! | K79: =I79/$C$6 -> #DIV/0! | L79: =I79/($C$7+$C$9) -> #DIV/0! | M79: =I79/$I$130 -> #DIV/0! | O79: =(N79/I79)-1 -> #DIV/0! | P79: =N79/$C$6 -> #DIV/0! | Q79: =N79/($C$7+$C$9) -> #DIV/0! | R79: =N79/$N$130 -> #DIV/0! | T79: =E79 -> 0
B80: OHCS Constr. Analyst review | C80: =D80+E80 -> 0 | F80: =E80/$C$6 -> #DIV/0! | G80: =E80/($C$7+$C$9) -> #DIV/0! | H80: =E80/$E$130 -> #DIV/0! | J80: =(I80/E80)-1 -> #DIV/0! | K80: =I80/$C$6 -> #DIV/0! | L80: =I80/($C$7+$C$9) -> #DIV/0! | M80: =I80/$I$130 -> #DIV/0! | O80: =(N80/I80)-1 -> #DIV/0! | P80: =N80/$C$6 -> #DIV/0! | Q80: =N80/($C$7+$C$9) -> #DIV/0! | R80: =N80/$N$130 -> #DIV/0! | T80: =E80 -> 0
B81: Other: | C81: =D81+E81 -> 0 | F81: =E81/$C$6 -> #DIV/0! | G81: =E81/($C$7+$C$9) -> #DIV/0! | H81: =E81/$E$130 -> #DIV/0! | J81: =(I81/E81)-1 -> #DIV/0! | K81: =I81/$C$6 -> #DIV/0! | L81: =I81/($C$7+$C$9) -> #DIV/0! | M81: =I81/$I$130 -> #DIV/0! | O81: =(N81/I81)-1 -> #DIV/0! | P81: =N81/$C$6 -> #DIV/0! | Q81: =N81/($C$7+$C$9) -> #DIV/0! | R81: =N81/$N$130 -> #DIV/0! | T81: =E81 -> 0
A83: Construction Loan Costs/Fees
B84: Lender Inspection Fees | C84: =D84+E84 -> 0 | F84: =E84/$C$6 -> #DIV/0! | G84: =E84/($C$7+$C$9) -> #DIV/0! | H84: =E84/$E$130 -> #DIV/0! | J84: =(I84/E84)-1 -> #DIV/0! | K84: =I84/$C$6 -> #DIV/0! | L84: =I84/($C$7+$C$9) -> #DIV/0! | M84: =I84/$I$130 -> #DIV/0! | O84: =(N84/I84)-1 -> #DIV/0! | P84: =N84/$C$6 -> #DIV/0! | Q84: =N84/($C$7+$C$9) -> #DIV/0! | R84: =N84/$N$130 -> #DIV/0! | T84: =E84 -> 0
B85: Lender Title Insurance | C85: =D85+E85 -> 0 | F85: =E85/$C$6 -> #DIV/0! | G85: =E85/($C$7+$C$9) -> #DIV/0! | H85: =E85/$E$130 -> #DIV/0! | J85: =(I85/E85)-1 -> #DIV/0! | K85: =I85/$C$6 -> #DIV/0! | L85: =I85/($C$7+$C$9) -> #DIV/0! | M85: =I85/$I$130 -> #DIV/0! | O85: =(N85/I85)-1 -> #DIV/0! | P85: =N85/$C$6 -> #DIV/0! | Q85: =N85/($C$7+$C$9) -> #DIV/0! | R85: =N85/$N$130 -> #DIV/0! | T85: =E85 -> 0
B86: Lender Legal Fees | C86: =D86+E86 -> 0 | F86: =E86/$C$6 -> #DIV/0! | G86: =E86/($C$7+$C$9) -> #DIV/0! | H86: =E86/$E$130 -> #DIV/0! | J86: =(I86/E86)-1 -> #DIV/0! | K86: =I86/$C$6 -> #DIV/0! | L86: =I86/($C$7+$C$9) -> #DIV/0! | M86: =I86/$I$130 -> #DIV/0! | O86: =(N86/I86)-1 -> #DIV/0! | P86: =N86/$C$6 -> #DIV/0! | Q86: =N86/($C$7+$C$9) -> #DIV/0! | R86: =N86/$N$130 -> #DIV/0! | T86: =E86 -> 0
B87: Loan Fees | C87: =D87+E87 -> 0 | F87: =E87/$C$6 -> #DIV/0! | G87: =E87/($C$7+$C$9) -> #DIV/0! | H87: =E87/$E$130 -> #DIV/0! | J87: =(I87/E87)-1 -> #DIV/0! | K87: =I87/$C$6 -> #DIV/0! | L87: =I87/($C$7+$C$9) -> #DIV/0! | M87: =I87/$I$130 -> #DIV/0! | O87: =(N87/I87)-1 -> #DIV/0! | P87: =N87/$C$6 -> #DIV/0! | Q87: =N87/($C$7+$C$9) -> #DIV/0! | R87: =N87/$N$130 -> #DIV/0! | T87: =E87 -> 0
B88: Loan Closing Fees | C88: =D88+E88 -> 0 | F88: =E88/$C$6 -> #DIV/0! | G88: =E88/($C$7+$C$9) -> #DIV/0! | H88: =E88/$E$130 -> #DIV/0! | J88: =(I88/E88)-1 -> #DIV/0! | K88: =I88/$C$6 -> #DIV/0! | L88: =I88/($C$7+$C$9) -> #DIV/0! | M88: =I88/$I$130 -> #DIV/0! | O88: =(N88/I88)-1 -> #DIV/0! | P88: =N88/$C$6 -> #DIV/0! | Q88: =N88/($C$7+$C$9) -> #DIV/0! | R88: =N88/$N$130 -> #DIV/0! | T88: =E88 -> 0
B89: Property Taxes (Constr Period) | C89: =D89+E89 -> 0 | F89: =E89/$C$6 -> #DIV/0! | G89: =E89/($C$7+$C$9) -> #DIV/0! | H89: =E89/$E$130 -> #DIV/0! | J89: =(I89/E89)-1 -> #DIV/0! | K89: =I89/$C$6 -> #DIV/0! | L89: =I89/($C$7+$C$9) -> #DIV/0! | M89: =I89/$I$130 -> #DIV/0! | O89: =(N89/I89)-1 -> #DIV/0! | P89: =N89/$C$6 -> #DIV/0! | Q89: =N89/($C$7+$C$9) -> #DIV/0! | R89: =N89/$N$130 -> #DIV/0! | T89: =E89 -> 0
B90: Insurance | C90: =D90+E90 -> 0 | F90: =E90/$C$6 -> #DIV/0! | G90: =E90/($C$7+$C$9) -> #DIV/0! | H90: =E90/$E$130 -> #DIV/0! | J90: =(I90/E90)-1 -> #DIV/0! | K90: =I90/$C$6 -> #DIV/0! | L90: =I90/($C$7+$C$9) -> #DIV/0! | M90: =I90/$I$130 -> #DIV/0! | O90: =(N90/I90)-1 -> #DIV/0! | P90: =N90/$C$6 -> #DIV/0! | Q90: =N90/($C$7+$C$9) -> #DIV/0! | R90: =N90/$N$130 -> #DIV/0! | T90: =E90 -> 0
A92: Bridge Loan Fees
B93: Bridge Loan Legal | C93: =D93+E93 -> 0 | F93: =E93/$C$6 -> #DIV/0! | G93: =E93/($C$7+$C$9) -> #DIV/0! | H93: =E93/$E$130 -> #DIV/0! | J93: =(I93/E93)-1 -> #DIV/0! | K93: =I93/$C$6 -> #DIV/0! | L93: =I93/($C$7+$C$9) -> #DIV/0! | M93: =I93/$I$130 -> #DIV/0! | O93: =(N93/I93)-1 -> #DIV/0! | P93: =N93/$C$6 -> #DIV/0! | Q93: =N93/($C$7+$C$9) -> #DIV/0! | R93: =N93/$N$130 -> #DIV/0! | T93: =E93 -> 0
B94: Bridge Loan Trustee | C94: =D94+E94 -> 0 | F94: =E94/$C$6 -> #DIV/0! | G94: =E94/($C$7+$C$9) -> #DIV/0! | H94: =E94/$E$130 -> #DIV/0! | J94: =(I94/E94)-1 -> #DIV/0! | K94: =I94/$C$6 -> #DIV/0! | L94: =I94/($C$7+$C$9) -> #DIV/0! | M94: =I94/$I$130 -> #DIV/0! | O94: =(N94/I94)-1 -> #DIV/0! | P94: =N94/$C$6 -> #DIV/0! | Q94: =N94/($C$7+$C$9) -> #DIV/0! | R94: =N94/$N$130 -> #DIV/0! | T94: =E94 -> 0
B95: Bridge Loan Underwriting | C95: =D95+E95 -> 0 | F95: =E95/$C$6 -> #DIV/0! | G95: =E95/($C$7+$C$9) -> #DIV/0! | H95: =E95/$E$130 -> #DIV/0! | J95: =(I95/E95)-1 -> #DIV/0! | K95: =I95/$C$6 -> #DIV/0! | L95: =I95/($C$7+$C$9) -> #DIV/0! | M95: =I95/$I$130 -> #DIV/0! | O95: =(N95/I95)-1 -> #DIV/0! | P95: =N95/$C$6 -> #DIV/0! | Q95: =N95/($C$7+$C$9) -> #DIV/0! | R95: =N95/$N$130 -> #DIV/0! | T95: =E95 -> 0
A97: Permanent Loan Fees
B98: Perm. Loan Fee | C98: =D98+E98 -> 0 | F98: =E98/$C$6 -> #DIV/0! | G98: =E98/($C$7+$C$9) -> #DIV/0! | H98: =E98/$E$130 -> #DIV/0! | J98: =(I98/E98)-1 -> #DIV/0! | K98: =I98/$C$6 -> #DIV/0! | L98: =I98/($C$7+$C$9) -> #DIV/0! | M98: =I98/$I$130 -> #DIV/0! | O98: =(N98/I98)-1 -> #DIV/0! | P98: =N98/$C$6 -> #DIV/0! | Q98: =N98/($C$7+$C$9) -> #DIV/0! | R98: =N98/$N$130 -> #DIV/0!
B99: Perm. Loan Closing Fees | C99: =D99+E99 -> 0 | F99: =E99/$C$6 -> #DIV/0! | G99: =E99/($C$7+$C$9) -> #DIV/0! | H99: =E99/$E$130 -> #DIV/0! | J99: =(I99/E99)-1 -> #DIV/0! | K99: =I99/$C$6 -> #DIV/0! | L99: =I99/($C$7+$C$9) -> #DIV/0! | M99: =I99/$I$130 -> #DIV/0! | O99: =(N99/I99)-1 -> #DIV/0! | P99: =N99/$C$6 -> #DIV/0! | Q99: =N99/($C$7+$C$9) -> #DIV/0! | R99: =N99/$N$130 -> #DIV/0!
A101: Tax Credit Fees
B102: Tax Credit Fee | C102: =D102+E102 -> 0 | F102: =E102/$C$6 -> #DIV/0! | G102: =E102/($C$7+$C$9) -> #DIV/0! | H102: =E102/$E$130 -> #DIV/0! | J102: =(I102/E102)-1 -> #DIV/0! | K102: =I102/$C$6 -> #DIV/0! | L102: =I102/($C$7+$C$9) -> #DIV/0! | M102: =I102/$I$130 -> #DIV/0! | O102: =(N102/I102)-1 -> #DIV/0! | P102: =N102/$C$6 -> #DIV/0! | Q102: =N102/($C$7+$C$9) -> #DIV/0! | R102: =N102/$N$130 -> #DIV/0! | T102: =E102 -> 0
B103: Tax Credit Cost Certification | C103: =D103+E103 -> 0 | F103: =E103/$C$6 -> #DIV/0! | G103: =E103/($C$7+$C$9) -> #DIV/0! | H103: =E103/$E$130 -> #DIV/0! | J103: =(I103/E103)-1 -> #DIV/0! | K103: =I103/$C$6 -> #DIV/0! | L103: =I103/($C$7+$C$9) -> #DIV/0! | M103: =I103/$I$130 -> #DIV/0! | O103: =(N103/I103)-1 -> #DIV/0! | P103: =N103/$C$6 -> #DIV/0! | Q103: =N103/($C$7+$C$9) -> #DIV/0! | R103: =N103/$N$130 -> #DIV/0! | T103: =E103 -> 0
B104: Tax Credit Legal/Advisor Fee | C104: =D104+E104 -> 0 | F104: =E104/$C$6 -> #DIV/0! | G104: =E104/($C$7+$C$9) -> #DIV/0! | H104: =E104/$E$130 -> #DIV/0! | J104: =(I104/E104)-1 -> #DIV/0! | K104: =I104/$C$6 -> #DIV/0! | L104: =I104/($C$7+$C$9) -> #DIV/0! | M104: =I104/$I$130 -> #DIV/0! | O104: =(N104/I104)-1 -> #DIV/0! | P104: =N104/$C$6 -> #DIV/0! | Q104: =N104/($C$7+$C$9) -> #DIV/0! | R104: =N104/$N$130 -> #DIV/0! | T104: =E104 -> 0
A106: Bond Issuance Fees
B107: Cost of Bond Issuance | C107: =D107+E107 -> 0 | F107: =E107/$C$6 -> #DIV/0! | G107: =E107/($C$7+$C$9) -> #DIV/0! | H107: =E107/$E$130 -> #DIV/0! | J107: =(I107/E107)-1 -> #DIV/0! | K107: =I107/$C$6 -> #DIV/0! | L107: =I107/($C$7+$C$9) -> #DIV/0! | M107: =I107/$I$130 -> #DIV/0! | O107: =(N107/I107)-1 -> #DIV/0! | P107: =N107/$C$6 -> #DIV/0! | Q107: =N107/($C$7+$C$9) -> #DIV/0! | R107: =N107/$N$130 -> #DIV/0!
B108: Negative Arbitrage (1.50%) | C108: =D108+E108 -> 0 | F108: =E108/$C$6 -> #DIV/0! | G108: =E108/($C$7+$C$9) -> #DIV/0! | H108: =E108/$E$130 -> #DIV/0! | J108: =(I108/E108)-1 -> #DIV/0! | K108: =I108/$C$6 -> #DIV/0! | L108: =I108/($C$7+$C$9) -> #DIV/0! | M108: =I108/$I$130 -> #DIV/0! | O108: =(N108/I108)-1 -> #DIV/0! | P108: =N108/$C$6 -> #DIV/0! | Q108: =N108/($C$7+$C$9) -> #DIV/0! | R108: =N108/$N$130 -> #DIV/0!
B109: Bond Cost Certification | C109: =D109+E109 -> 0 | F109: =E109/$C$6 -> #DIV/0! | G109: =E109/($C$7+$C$9) -> #DIV/0! | H109: =E109/$E$130 -> #DIV/0! | J109: =(I109/E109)-1 -> #DIV/0! | K109: =I109/$C$6 -> #DIV/0! | L109: =I109/($C$7+$C$9) -> #DIV/0! | M109: =I109/$I$130 -> #DIV/0! | O109: =(N109/I109)-1 -> #DIV/0! | P109: =N109/$C$6 -> #DIV/0! | Q109: =N109/($C$7+$C$9) -> #DIV/0! | R109: =N109/$N$130 -> #DIV/0!
B110: Other: | C110: =D110+E110 -> 0 | F110: =E110/$C$6 -> #DIV/0! | G110: =E110/($C$7+$C$9) -> #DIV/0! | H110: =E110/$E$130 -> #DIV/0! | J110: =(I110/E110)-1 -> #DIV/0! | K110: =I110/$C$6 -> #DIV/0! | L110: =I110/($C$7+$C$9) -> #DIV/0! | M110: =I110/$I$130 -> #DIV/0! | O110: =(N110/I110)-1 -> #DIV/0! | P110: =N110/$C$6 -> #DIV/0! | Q110: =N110/($C$7+$C$9) -> #DIV/0! | R110: =N110/$N$130 -> #DIV/0!
A112: Interest
B113: Construction Period | C113: =D113+E113 -> 0 | F113: =E113/$C$6 -> #DIV/0! | G113: =E113/($C$7+$C$9) -> #DIV/0! | H113: =E113/$E$130 -> #DIV/0! | J113: =(I113/E113)-1 -> #DIV/0! | K113: =I113/$C$6 -> #DIV/0! | L113: =I113/($C$7+$C$9) -> #DIV/0! | M113: =I113/$I$130 -> #DIV/0! | O113: =(N113/I113)-1 -> #DIV/0! | P113: =N113/$C$6 -> #DIV/0! | Q113: =N113/($C$7+$C$9) -> #DIV/0! | R113: =N113/$N$130 -> #DIV/0! | T113: =E113 -> 0
B114: Construction Bridge Loan | C114: =D114+E114 -> 0 | F114: =E114/$C$6 -> #DIV/0! | G114: =E114/($C$7+$C$9) -> #DIV/0! | H114: =E114/$E$130 -> #DIV/0! | J114: =(I114/E114)-1 -> #DIV/0! | K114: =I114/$C$6 -> #DIV/0! | L114: =I114/($C$7+$C$9) -> #DIV/0! | M114: =I114/$I$130 -> #DIV/0! | O114: =(N114/I114)-1 -> #DIV/0! | P114: =N114/$C$6 -> #DIV/0! | Q114: =N114/($C$7+$C$9) -> #DIV/0! | R114: =N114/$N$130 -> #DIV/0!
B115: Other: | C115: =D115+E115 -> 0 | F115: =E115/$C$6 -> #DIV/0! | G115: =E115/($C$7+$C$9) -> #DIV/0! | H115: =E115/$E$130 -> #DIV/0! | J115: =(I115/E115)-1 -> #DIV/0! | K115: =I115/$C$6 -> #DIV/0! | L115: =I115/($C$7+$C$9) -> #DIV/0! | M115: =I115/$I$130 -> #DIV/0! | O115: =(N115/I115)-1 -> #DIV/0! | P115: =N115/$C$6 -> #DIV/0! | Q115: =N115/($C$7+$C$9) -> #DIV/0! | R115: =N115/$N$130 -> #DIV/0! | T115: =E115 -> 0
B116: Other: | C116: =D116+E116 -> 0 | F116: =E116/$C$6 -> #DIV/0! | G116: =E116/($C$7+$C$9) -> #DIV/0! | H116: =E116/$E$130 -> #DIV/0! | J116: =(I116/E116)-1 -> #DIV/0! | K116: =I116/$C$6 -> #DIV/0! | L116: =I116/($C$7+$C$9) -> #DIV/0! | M116: =I116/$I$130 -> #DIV/0! | O116: =(N116/I116)-1 -> #DIV/0! | P116: =N116/$C$6 -> #DIV/0! | Q116: =N116/($C$7+$C$9) -> #DIV/0! | R116: =N116/$N$130 -> #DIV/0! | T116: =E116 -> 0
...

Sheet Income
A1: COMBINED HOUSING/COMMERCIAL OPERATING BUDGET - INCOME
B3: Project Name: | E3: =Sources!$B$3 -> 0
D4: Date: | F4: =Sources!F3 -> 40909
D5: County:
A6: ANNUAL Residential Income: | I6: Annual Inflation Rate Factor: | M6: 0.02
A7: Rents based on:
A8: Unit Size | B8: Unit Type | C8: # of Baths | D8: Square Feet | E8: Median Income % | F8: Gross Monthly Rent Per Unit | H8: Tenant Paid Utility Allow | J8: Net Monthly Rent Per Unit | L8: Number of Units | N8: 1 | O8: 2 | P8: 3 | Q8: 4 | R8: 5 | S8: 6 | T8: 7 | U8: 8 | V8: 9 | W8: 10 | X8: 11 | Y8: 12 | Z8: 13 | AA8: 14 | AB8: 15 | AC8: 16 | AD8: 17 | AE8: 18 | AF8: 19 | AG8: 20 | AH8: 21 | AI8: 22 | AJ8: 23 | AK8: 24 | AL8: 25 | AM8: 26 | AN8: 27 | AO8: 28 | AP8: 29 | AQ8: 30
B10: Bdr | E10: =ROUNDUP(IF(OR(A10="sro",A10=0),+F10/(VLOOKUP($F$5,Rents,26)*2),IF(A10=1,+F10/(VLOOKUP($F$5,Rents,27)*2),IF(A10=2,+F10/(VLOOKUP($F$5,Rents,28)*2),IF(A10=3,+F10/(VLOOKUP($F$5,Rents,29)*2),IF(A10=4,+F10/(VLOOKUP($F$5,Rents,30)*2),IF(A10=5,+F10/(VLOOKUP($F$5,Rents,31)*2),0)))))),3)*100 -> #N/A | G10: - | I10: = | J10: =F10-H10 -> 0 | K10: X 12 | M10: = | N10: =J10*L10*12 -> 0 | O10: =(+N10*$M$6)+N10 -> 0 | P10: =(+O10*$M$6)+O10 -> 0 | Q10: =(+P10*$M$6)+P10 -> 0 | R10: =(+Q10*$M$6)+Q10 -> 0 | S10: =(+R10*$M$6)+R10 -> 0 | T10: =(+S10*$M$6)+S10 -> 0 | U10: =(+T10*$M$6)+T10 -> 0 | V10: =(+U10*$M$6)+U10 -> 0 | ... AQ10: =(+AP10*$M$6)+AP10 -> 0
B11: Bdr | E11: =ROUNDUP(IF(OR(A11="sro",A11=0),+F11/(VLOOKUP($F$5,Rents,26)*2),IF(A11=1,+F11/(VLOOKUP($F$5,Rents,27)*2),IF(A11=2,+F11/(VLOOKUP($F$5,Rents,28)*2),IF(A11=3,+F11/(VLOOKUP($F$5,Rents,29)*2),IF(A11=4,+F11/(VLOOKUP($F$5,Rents,30)*2),IF(A11=5,+F11/(VLOOKUP($F$5,Rents,31)*2),0)))))),3)*100 -> #N/A | G11: - | I11: = | J11: =F11-H11 -> 0 | K11: X 12 | M11: = | N11: =J11*L11*12 -> 0 | O11: =(+N11*$M$6)+N11 -> 0 | P11: =(+O11*$M$6)+O11 -> 0 | Q11: =(+P11*$M$6)+P11 -> 0 | R11: =(+Q11*$M$6)+Q11 -> 0 | S11: =(+R11*$M$6)+R11 -> 0 | T11: =(+S11*$M$6)+S11 -> 0 | U11: =(+T11*$M$6)+T11 -> 0 | V11: =(+U11*$M$6)+U11 -> 0 | ... AQ11: =(+AP11*$M$6)+AP11 -> 0
B12: Bdr | E12: =ROUNDUP(IF(OR(A12="sro",A12=0),+F12/(VLOOKUP($F$5,Rents,26)*2),IF(A12=1,+F12/(VLOOKUP($F$5,Rents,27)*2),IF(A12=2,+F12/(VLOOKUP($F$5,Rents,28)*2),IF(A12=3,+F12/(VLOOKUP($F$5,Rents,29)*2),IF(A12=4,+F12/(VLOOKUP($F$5,Rents,30)*2),IF(A12=5,+F12/(VLOOKUP($F$5,Rents,31)*2),0)))))),3)*100 -> #N/A | G12: - | I12: = | J12: =F12-H12 -> 0 | K12: X 12 | M12: = | N12: =J12*L12*12 -> 0 | O12: =(+N12*$M$6)+N12 -> 0 | P12: =(+O12*$M$6)+O12 -> 0 | Q12: =(+P12*$M$6)+P12 -> 0 | R12: =(+Q12*$M$6)+Q12 -> 0 | S12: =(+R12*$M$6)+R12 -> 0 | T12: =(+S12*$M$6)+S12 -> 0 | U12: =(+T12*$M$6)+T12 -> 0 | V12: =(+U12*$M$6)+U12 -> 0 | ... AQ12: =(+AP12*$M$6)+AP12 -> 0
B13: Bdr | E13: =ROUNDUP(IF(OR(A13="sro",A13=0),+F13/(VLOOKUP($F$5,Rents,26)*2),IF(A13=1,+F13/(VLOOKUP($F$5,Rents,27)*2),IF(A13=2,+F13/(VLOOKUP($F$5,Rents,28)*2),IF(A13=3,+F13/(VLOOKUP($F$5,Rents,29)*2),IF(A13=4,+F13/(VLOOKUP($F$5,Rents,30)*2),IF(A13=5,+F13/(VLOOKUP($F$5,Rents,31)*2),0)))))),3)*100 -> #N/A | G13: - | I13: = | J13: =F13-H13 -> 0 | K13: X 12 | M13: = | N13: =J13*L13*12 -> 0 | O13: =(+N13*$M$6)+N13 -> 0 | P13: =(+O13*$M$6)+O13 -> 0 | Q13: =(+P13*$M$6)+P13 -> 0 | R13: =(+Q13*$M$6)+Q13 -> 0 | S13: =(+R13*$M$6)+R13 -> 0 | T13: =(+S13*$M$6)+S13 -> 0 | U13: =(+T13*$M$6)+T13 -> 0 | V13: =(+U13*$M$6)+U13 -> 0 | ... AQ13: =(+AP13*$M$6)+AP13 -> 0
B14: Bdr | E14: =ROUNDUP(IF(OR(A14="sro",A14=0),+F14/(VLOOKUP($F$5,Rents,26)*2),IF(A14=1,+F14/(VLOOKUP($F$5,Rents,27)*2),IF(A14=2,+F14/(VLOOKUP($F$5,Rents,28)*2),IF(A14=3,+F14/(VLOOKUP($F$5,Rents,29)*2),IF(A14=4,+F14/(VLOOKUP($F$5,Rents,30)*2),IF(A14=5,+F14/(VLOOKUP($F$5,Rents,31)*2),0)))))),3)*100 -> #N/A | G14: - | I14: = | J14: =F14-H14 -> 0 | K14: X 12 | M14: = | N14: =J14*L14*12 -> 0 | O14: =(+N14*$M$6)+N14 -> 0 | P14: =(+O14*$M$6)+O14 -> 0 | Q14: =(+P14*$M$6)+P14 -> 0 | R14: =(+Q14*$M$6)+Q14 -> 0 | S14: =(+R14*$M$6)+R14 -> 0 | T14: =(+S14*$M$6)+S14 -> 0 | U14: =(+T14*$M$6)+T14 -> 0 | V14: =(+U14*$M$6)+U14 -> 0 | ... AQ14: =(+AP14*$M$6)+AP14 -> 0
B15: Bdr | E15: =ROUNDUP(IF(OR(A15="sro",A15=0),+F15/(VLOOKUP($F$5,Rents,26)*2),IF(A15=1,+F15/(VLOOKUP($F$5,Rents,27)*2),IF(A15=2,+F15/(VLOOKUP($F$5,Rents,28)*2),IF(A15=3,+F15/(VLOOKUP($F$5,Rents,29)*2),IF(A15=4,+F15/(VLOOKUP($F$5,Rents,30)*2),IF(A15=5,+F15/(VLOOKUP($F$5,Rents,31)*2),0)))))),3)*100 -> #N/A | G15: - | I15: = | J15: =F15-H15 -> 0 | K15: X 12 | M15: = | N15: =J15*L15*12 -> 0 | O15: =(+N15*$M$6)+N15 -> 0 | P15: =(+O15*$M$6)+O15 -> 0 | Q15: =(+P15*$M$6)+P15 -> 0 | R15: =(+Q15*$M$6)+Q15 -> 0 | S15: =(+R15*$M$6)+R15 -> 0 | T15: =(+S15*$M$6)+S15 -> 0 | U15: =(+T15*$M$6)+T15 -> 0 | V15: =(+U15*$M$6)+U15 -> 0 | ... AQ15: =(+AP15*$M$6)+AP15 -> 0
B16: Bdr | E16: =ROUNDUP(IF(OR(A16="sro",A16=0),+F16/(VLOOKUP($F$5,Rents,26)*2),IF(A16=1,+F16/(VLOOKUP($F$5,Rents,27)*2),IF(A16=2,+F16/(VLOOKUP($F$5,Rents,28)*2),IF(A16=3,+F16/(VLOOKUP($F$5,Rents,29)*2),IF(A16=4,+F16/(VLOOKUP($F$5,Rents,30)*2),IF(A16=5,+F16/(VLOOKUP($F$5,Rents,31)*2),0)))))),3)*100 -> #N/A | G16: - | I16: = | J16: =F16-H16 -> 0 | K16: X 12 | M16: = | N16: =J16*L16*12 -> 0 | O16: =(+N16*$M$6)+N16 -> 0 | P16: =(+O16*$M$6)+O16 -> 0 | Q16: =(+P16*$M$6)+P16 -> 0 | R16: =(+Q16*$M$6)+Q16 -> 0 | S16: =(+R16*$M$6)+R16 -> 0 | T16: =(+S16*$M$6)+S16 -> 0 | U16: =(+T16*$M$6)+T16 -> 0 | V16: =(+U16*$M$6)+U16 -> 0 | ... AQ16: =(+AP16*$M$6)+AP16 -> 0
B17: Bdr | E17: =ROUNDUP(IF(OR(A17="sro",A17=0),+F17/(VLOOKUP($F$5,Rents,26)*2),IF(A17=1,+F17/(VLOOKUP($F$5,Rents,27)*2),IF(A17=2,+F17/(VLOOKUP($F$5,Rents,28)*2),IF(A17=3,+F17/(VLOOKUP($F$5,Rents,29)*2),IF(A17=4,+F17/(VLOOKUP($F$5,Rents,30)*2),IF(A17=5,+F17/(VLOOKUP($F$5,Rents,31)*2),0)))))),3)*100 -> #N/A | G17: - | I17: = | J17: =F17-H17 -> 0 | K17: X 12 | M17: = | N17: =J17*L17*12 -> 0 | O17: =(+N17*$M$6)+N17 -> 0 | P17: =(+O17*$M$6)+O17 -> 0 | Q17: =(+P17*$M$6)+P17 -> 0 | R17: =(+Q17*$M$6)+Q17 -> 0 | S17: =(+R17*$M$6)+R17 -> 0 | T17: =(+S17*$M$6)+S17 -> 0 | U17: =(+T17*$M$6)+T17 -> 0 | V17: =(+U17*$M$6)+U17 -> 0 | ... AQ17: =(+AP17*$M$6)+AP17 -> 0
B18: Bdr | E18: =ROUNDUP(IF(OR(A18="sro",A18=0),+F18/(VLOOKUP($F$5,Rents,26)*2),IF(A18=1,+F18/(VLOOKUP($F$5,Rents,27)*2),IF(A18=2,+F18/(VLOOKUP($F$5,Rents,28)*2),IF(A18=3,+F18/(VLOOKUP($F$5,Rents,29)*2),IF(A18=4,+F18/(VLOOKUP($F$5,Rents,30)*2),IF(A18=5,+F18/(VLOOKUP($F$5,Rents,31)*2),0)))))),3)*100 -> #N/A | G18: - | I18: = | J18: =F18-H18 -> 0 | K18: X 12 | M18: = | N18: =J18*L18*12 -> 0 | O18: =(+N18*$M$6)+N18 -> 0 | P18: =(+O18*$M$6)+O18 -> 0 | Q18: =(+P18*$M$6)+P18 -> 0 | R18: =(+Q18*$M$6)+Q18 -> 0 | S18: =(+R18*$M$6)+R18 -> 0 | T18: =(+S18*$M$6)+S18 -> 0 | U18: =(+T18*$M$6)+T18 -> 0 | V18: =(+U18*$M$6)+U18 -> 0 | ... AQ18: =(+AP18*$M$6)+AP18 -> 0
B19: Bdr | E19: =ROUNDUP(IF(OR(A19="sro",A19=0),+F19/(VLOOKUP($F$5,Rents,26)*2),IF(A19=1,+F19/(VLOOKUP($F$5,Rents,27)*2),IF(A19=2,+F19/(VLOOKUP($F$5,Rents,28)*2),IF(A19=3,+F19/(VLOOKUP($F$5,Rents,29)*2),IF(A19=4,+F19/(VLOOKUP($F$5,Rents,30)*2),IF(A19=5,+F19/(VLOOKUP($F$5,Rents,31)*2),0)))))),3)*100 -> #N/A | G19: - | I19: = | J19: =F19-H19 -> 0 | K19: X 12 | M19: = | N19: =J19*L19*12 -> 0 | O19: =(+N19*$M$6)+N19 -> 0 | P19: =(+O19*$M$6)+O19 -> 0 | Q19: =(+P19*$M$6)+P19 -> 0 | R19: =(+Q19*$M$6)+Q19 -> 0 | S19: =(+R19*$M$6)+R19 -> 0 | T19: =(+S19*$M$6)+S19 -> 0 | U19: =(+T19*$M$6)+T19 -> 0 | V19: =(+U19*$M$6)+U19 -> 0 | ... AQ19: =(+AP19*$M$6)+AP19 -> 0
B20: Bdr | E20: =ROUNDUP(IF(OR(A20="sro",A20=0),+F20/(VLOOKUP($F$5,Rents,26)*2),IF(A20=1,+F20/(VLOOKUP($F$5,Rents,27)*2),IF(A20=2,+F20/(VLOOKUP($F$5,Rents,28)*2),IF(A20=3,+F20/(VLOOKUP($F$5,Rents,29)*2),IF(A20=4,+F20/(VLOOKUP($F$5,Rents,30)*2),IF(A20=5,+F20/(VLOOKUP($F$5,Rents,31)*2),0)))))),3)*100 -> #N/A | G20: - | I20: = | J20: =F20-H20 -> 0 | K20: X 12 | M20: = | N20: =J20*L20*12 -> 0 | O20: =(+N20*$M$6)+N20 -> 0 | P20: =(+O20*$M$6)+O20 -> 0 | Q20: =(+P20*$M$6)+P20 -> 0 | R20: =(+Q20*$M$6)+Q20 -> 0 | S20: =(+R20*$M$6)+R20 -> 0 | T20: =(+S20*$M$6)+S20 -> 0 | U20: =(+T20*$M$6)+T20 -> 0 | V20: =(+U20*$M$6)+U20 -> 0 | ... AQ20: =(+AP20*$M$6)+AP20 -> 0
B21: Bdr | E21: =ROUNDUP(IF(OR(A21="sro",A21=0),+F21/(VLOOKUP($F$5,Rents,26)*2),IF(A21=1,+F21/(VLOOKUP($F$5,Rents,27)*2),IF(A21=2,+F21/(VLOOKUP($F$5,Rents,28)*2),IF(A21=3,+F21/(VLOOKUP($F$5,Rents,29)*2),IF(A21=4,+F21/(VLOOKUP($F$5,Rents,30)*2),IF(A21=5,+F21/(VLOOKUP($F$5,Rents,31)*2),0)))))),3)*100 -> #N/A | G21: - | I21: = | J21: =F21-H21 -> 0 | K21: X 12 | M21: = | N21: =J21*L21*12 -> 0 | O21: =(+N21*$M$6)+N21 -> 0 | P21: =(+O21*$M$6)+O21 -> 0 | Q21: =(+P21*$M$6)+P21 -> 0 | R21: =(+Q21*$M$6)+Q21 -> 0 | S21: =(+R21*$M$6)+R21 -> 0 | T21: =(+S21*$M$6)+S21 -> 0 | U21: =(+T21*$M$6)+T21 -> 0 | V21: =(+U21*$M$6)+U21 -> 0 | ... AQ21: =(+AP21*$M$6)+AP21 -> 0
... B23: Bdr | E23: =ROUNDUP(IF(OR(A23="sro",A23=0),+F23/(VLOOKUP($F$5,Rents,26)*2),IF(A23=1,+F23/(VLOOKUP($F$5,Rents,27)*2),IF(A23=2,+F23/(VLOOKUP($F$5,Rents,28)*2),IF(A23=3,+F23/(VLOOKUP($F$5,Rents,29)*2),IF(A23=4,+F23/(VLOOKUP($F$5,Rents,30)*2),IF(A23=5,+F23/(VLOOKUP($F$5,Rents,31)*2),0)))))),3)*100 -> #N/A | G23: - | I23: = | J23: =F23-H23 -> 0 | K23: X 12 | M23: = | N23: =J23*L23*12 -> 0 | O23: =(+N23*$M$6)+N23 -> 0 | P23: =(+O23*$M$6)+O23 -> 0 | Q23: =(+P23*$M$6)+P23 -> 0 | R23: =(+Q23*$M$6)+Q23 -> 0 | S23: =(+R23*$M$6)+R23 -> 0 | T23: =(+S23*$M$6)+S23 -> 0 | U23: =(+T23*$M$6)+T23 -> 0 | V23: =(+U23*$M$6)+U23 -> 0 | ... AQ23: =(+AP23*$M$6)+AP23 -> 0
A25: SUB-TOTALS | L25: =SUM(L10:L24) -> 0 | M25: = | N25: =SUM(N10:N24) -> 0 | O25: =SUM(O10:O24) -> 0 | P25: =SUM(P10:P24) -> 0 | Q25: =SUM(Q10:Q24) -> 0 | R25: =SUM(R10:R24) -> 0 | S25: =SUM(S10:S24) -> 0 | T25: =SUM(T10:T24) -> 0 | U25: =SUM(U10:U24) -> 0 | ... AQ25: =SUM(AQ10:AQ24) -> 0
A27: Other Revenue:
A29: Laundry | O29: =(+N29*$M$6)+N29 -> 0 | P29: =(+O29*$M$6)+O29 -> 0 | Q29: =(+P29*$M$6)+P29 -> 0 | R29: =(+Q29*$M$6)+Q29 -> 0 | S29: =(+R29*$M$6)+R29 -> 0 | T29: =(+S29*$M$6)+S29 -> 0 | U29: =(+T29*$M$6)+T29 -> 0 | V29: =(+U29*$M$6)+U29 -> 0 | ... AQ29: =(+AP29*$M$6)+AP29 -> 0
A30: Parking | O30: =(+N30*$M$6)+N30 -> 0 | P30: =(+O30*$M$6)+O30 -> 0 | Q30: =(+P30*$M$6)+P30 -> 0 | R30: =(+Q30*$M$6)+Q30 -> 0 | S30: =(+R30*$M$6)+R30 -> 0 | T30: =(+S30*$M$6)+S30 -> 0 | U30: =(+T30*$M$6)+T30 -> 0 | V30: =(+U30*$M$6)+U30 -> 0 | ... AQ30: =(+AP30*$M$6)+AP30 -> 0
A31: Utility Reimbursements | O31: =(+N31*$M$6)+N31 -> 0 | P31: =(+O31*$M$6)+O31 -> 0 | Q31: =(+P31*$M$6)+P31 -> 0 | R31: =(+Q31*$M$6)+Q31 -> 0 | S31: =(+R31*$M$6)+R31 -> 0 | T31: =(+S31*$M$6)+S31 -> 0 | U31: =(+T31*$M$6)+T31 -> 0 | V31: =(+U31*$M$6)+U31 -> 0 | ... AQ31: =(+AP31*$M$6)+AP31 -> 0
A32: Miscellaneous Fees | O32: =(+N32*$M$6)+N32 -> 0 | P32: =(+O32*$M$6)+O32 -> 0 | Q32: =(+P32*$M$6)+P32 -> 0 | R32: =(+Q32*$M$6)+Q32 -> 0 | S32: =(+R32*$M$6)+R32 -> 0 | T32: =(+S32*$M$6)+S32 -> 0 | U32: =(+T32*$M$6)+T32 -> 0 | V32: =(+U32*$M$6)+U32 -> 0 | ... AQ32: =(+AP32*$M$6)+AP32 -> 0
A33: Service Income | O33: =(+N33*$M$6)+N33 -> 0 | P33: =(+O33*$M$6)+O33 -> 0 | Q33: =(+P33*$M$6)+P33 -> 0 | R33: =(+Q33*$M$6)+Q33 -> 0 | S33: =(+R33*$M$6)+R33 -> 0 | T33: =(+S33*$M$6)+S33 -> 0 | U33: =(+T33*$M$6)+T33 -> 0 | V33: =(+U33*$M$6)+U33 -> 0 | ... AQ33: =(+AP33*$M$6)+AP33 -> 0
A34: Other Income | O34: =(+N34*$M$6)+N34 -> 0 | P34: =(+O34*$M$6)+O34 -> 0 | Q34: =(+P34*$M$6)+P34 -> 0 | R34: =(+Q34*$M$6)+Q34 -> 0 | S34: =(+R34*$M$6)+R34 -> 0 | T34: =(+S34*$M$6)+S34 -> 0 | U34: =(+T34*$M$6)+T34 -> 0 | V34: =(+U34*$M$6)+U34 -> 0 | ... AQ34: =(+AP34*$M$6)+AP34 -> 0
A36: SUB-TOTAL OTHER REVENUE | N36: =SUM(N26:N35) -> 0 | O36: =SUM(O26:O35) -> 0 | P36: =SUM(P26:P35) -> 0 | Q36: =SUM(Q26:Q35) -> 0 | R36: =SUM(R26:R35) -> 0 | S36: =SUM(S26:S35) -> 0 | T36: =SUM(T26:T35) -> 0 | U36: =SUM(U26:U35) -> 0 | ... AQ36: =SUM(AQ26:AQ35) -> 0
A38: Gross Income: | N38: =N25+N36 -> 0 | O38: =O25+O36 -> 0 | P38: =P25+P36 -> 0 | Q38: =Q25+Q36 -> 0 | R38: =R25+R36 -> 0 | S38: =S25+S36 -> 0 | T38: =T25+T36 -> 0 | U38: =U25+U36 -> 0 | ... AQ38: =AQ25+AQ36 -> 0
A40: Less Vacancy Rate | E40: 0.05 | N40: =-N38*$E$40 -> 0 | O40: =-O38*$E$40 -> 0 | P40: =-P38*$E$40 -> 0 | Q40: =-Q38*$E$40 -> 0 | R40: =-R38*$E$40 -> 0 | S40: =-S38*$E$40 -> 0 | T40: =-T38*$E$40 -> 0 | U40: =-U38*$E$40 -> 0 | ... AQ40: =-AQ38*$E$40 -> 0
A42: Effective Gross Income (Residential): | N42: =N38+N40 -> 0 | O42: =O38+O40 -> 0 | P42: =P38+P40 -> 0 | Q42: =Q38+Q40 -> 0 | R42: =R38+R40 -> 0 | S42: =S38+S40 -> 0 | T42: =T38+T40 -> 0 | U42: =U38+U40 -> 0 | ... AQ42: =AQ38+AQ40 -> 0
N44: =-N42*$E$44 -> 0 | O44: =-O42*$E$44 -> 0 | P44: =-P42*$E$44 -> 0 | Q44: =-Q42*$E$44 -> 0 | R44: =-R42*$E$44 -> 0 | S44: =-S42*$E$44 -> 0 | T44: =-T42*$E$44 -> 0 | U44: =-U42*$E$44 -> 0 | ... AQ44: =-AQ42*$E$44 -> 0
A45: Commercial:
A46: ANNUAL Commercial Income (Enter on Comm Income Tab, uses escalator on this tab):
A48: Commercial Income: | N48: ='Comm Income'!H11 -> 0 | O48: =(+N48*$M$6)+N48 -> 0 | P48: =(+O48*$M$6)+O48 -> 0 | Q48: =(+P48*$M$6)+P48 -> 0 | R48: =(+Q48*$M$6)+Q48 -> 0 | S48: =(+R48*$M$6)+R48 -> 0 | T48: =(+S48*$M$6)+S48 -> 0 | U48: =(+T48*$M$6)+T48 -> 0 | V48: =(+U48*$M$6)+U48 -> 0 | ... AQ48: =(+AP48*$M$6)+AP48 -> 0
A49: ='Comm Income'!A12 -> Other: | N49: ='Comm Income'!H12 -> 0 | O49: =(+N49*$M$6)+N49 -> 0 | P49: =(+O49*$M$6)+O49 -> 0 | Q49: =(+P49*$M$6)+P49 -> 0 | R49: =(+Q49*$M$6)+Q49 -> 0 | S49: =(+R49*$M$6)+R49 -> 0 | T49: =(+S49*$M$6)+S49 -> 0 | U49: =(+T49*$M$6)+T49 -> 0 | V49: =(+U49*$M$6)+U49 -> 0 | ... AQ49: =(+AP49*$M$6)+AP49 -> 0
A50: ='Comm Income'!A13 -> Other: | N50: ='Comm Income'!H13 -> 0 | O50: =(+N50*$M$6)+N50 -> 0 | P50: =(+O50*$M$6)+O50 -> 0 | Q50: =(+P50*$M$6)+P50 -> 0 | R50: =(+Q50*$M$6)+Q50 -> 0 | S50: =(+R50*$M$6)+R50 -> 0 | T50: =(+S50*$M$6)+S50 -> 0 | U50: =(+T50*$M$6)+T50 -> 0 | V50: =(+U50*$M$6)+U50 -> 0 | ... AQ50: =(+AP50*$M$6)+AP50 -> 0
A51: ='Comm Income'!A14 -> Other: | N51: ='Comm Income'!H14 -> 0 | O51: =(+N51*$M$6)+N51 -> 0 | P51: =(+O51*$M$6)+O51 -> 0 | Q51: =(+P51*$M$6)+P51 -> 0 | R51: =(+Q51*$M$6)+Q51 -> 0 | S51: =(+R51*$M$6)+R51 -> 0 | T51: =(+S51*$M$6)+S51 -> 0 | U51: =(+T51*$M$6)+T51 -> 0 | V51: =(+U51*$M$6)+U51 -> 0 | ... AQ51: =(+AP51*$M$6)+AP51 -> 0
A52: ='Comm Income'!A15 -> Other: | N52: ='Comm Income'!H15 -> 0 | O52: =(+N52*$M$6)+N52 -> 0 | P52: =(+O52*$M$6)+O52 -> 0 | Q52: =(+P52*$M$6)+P52 -> 0 | R52: =(+Q52*$M$6)+Q52 -> 0 | S52: =(+R52*$M$6)+R52 -> 0 | T52: =(+S52*$M$6)+S52 -> 0 | U52: =(+T52*$M$6)+T52 -> 0 | V52: =(+U52*$M$6)+U52 -> 0 | ... AQ52: =(+AP52*$M$6)+AP52 -> 0
A53: ='Comm Income'!A16 -> Other: | N53: ='Comm Income'!H16 -> 0 | O53: =(+N53*$M$6)+N53 -> 0 | P53: =(+O53*$M$6)+O53 -> 0 | Q53: =(+P53*$M$6)+P53 -> 0 | R53: =(+Q53*$M$6)+Q53 -> 0 | S53: =(+R53*$M$6)+R53 -> 0 | T53: =(+S53*$M$6)+S53 -> 0 | U53: =(+T53*$M$6)+T53 -> 0 | V53: =(+U53*$M$6)+U53 -> 0 | ... AQ53: =(+AP53*$M$6)+AP53 -> 0
A54: ='Comm Income'!A17 -> Other: | N54: ='Comm Income'!H17 -> 0 | O54: =(+N54*$M$6)+N54 -> 0 | P54: =(+O54*$M$6)+O54 -> 0 | Q54: =(+P54*$M$6)+P54 -> 0 | R54: =(+Q54*$M$6)+Q54 -> 0 | S54: =(+R54*$M$6)+R54 -> 0 | T54: =(+S54*$M$6)+S54 -> 0 | U54: =(+T54*$M$6)+T54 -> 0 | V54: =(+U54*$M$6)+U54 -> 0 | ... AQ54: =(+AP54*$M$6)+AP54 -> 0
A56: TOTAL COMMERCIAL REVENUE | N56: =SUM(N48:N55) -> 0 | O56: =SUM(O48:O55) -> 0 | P56: =SUM(P48:P55) -> 0 | Q56: =SUM(Q48:Q55) -> 0 | R56: =SUM(R48:R55) -> 0 | S56: =SUM(S48:S55) -> 0 | T56: =SUM(T48:T55) -> 0 | U56: =SUM(U48:U55) -> 0 | ... AQ56: =SUM(AQ48:AQ55) -> 0
A58: Less Vacancy Rate | E58: 0.1 | N58: =N56*$E$58 -> 0 | O58: =O56*$E$58 -> 0 | P58: =P56*$E$58 -> 0 | Q58: =Q56*$E$58 -> 0 | R58: =R56*$E$58 -> 0 | S58: =S56*$E$58 -> 0 | T58: =T56*$E$58 -> 0 | U58: =U56*$E$58 -> 0 | ... AQ58: =AQ56*$E$58 -> 0
A60: Effective Gross Income (Commercial): | N60: =N56-N58 -> 0 | O60: =O56-O58 -> 0 | P60: =P56-P58 -> 0 | Q60: =Q56-Q58 -> 0 | R60: =R56-R58 -> 0 | S60: =S56-S58 -> 0 | T60: =T56-T58 -> 0 | U60: =U56-U58 -> 0 | ... AQ60: =AQ56-AQ58 -> 0
A62: Effective Gross Income (Total Project): | N62: =N42+N60 -> 0 | O62: =O42+O60 -> 0 | P62: =P42+P60 -> 0 | Q62: =Q42+Q60 -> 0 | R62: =R42+R60 -> 0 | S62: =S42+S60 -> 0 | T62: =T42+T60 -> 0 | U62: =U42+U60 -> 0 | ... AQ62: =AQ42+AQ60 -> 0

Sheet Expenses
B2: use purple line items for streamlined compliance reporting only
A3: HOUSING OPERATING BUDGET - EXPENSES
B5: Project Name: | C5: =Sources!$B$3 -> 0
B7: Date: | C7: =Sources!F3 -> 40909 | F7: Annual Inflation Rate Factor: | G7: 0.03
A9: Annual Operating Expenses | D9: Annual per Unit | E9: 1 | F9: 2 | G9: 3 | H9: 4 | I9: 5 | J9: 6 | K9: 7 | L9: 8 | M9: 9 | N9: 10 | O9: 11 | P9: 12 | Q9: 13 | R9: 14 | S9: 15 | T9: 16 | U9: 17 | V9: 18 | W9: 19 | X9: 20 | Y9: 21 | Z9: 22 | AA9: 23 | AB9: 24 | AC9: 25 | AD9: 26 | AE9: 27 | AF9: 28 | AG9: 29 | AH9: 30
A11: Property Management:
B12: On-site | D12: =E12/Income!$L$25 -> #DIV/0! | F12: =(+E12*$G$7)+E12 -> 0 | G12: =(+F12*$G$7)+F12 -> 0 | H12: =(+G12*$G$7)+G12 -> 0 | I12: =(+H12*$G$7)+H12 -> 0 | J12: =(+I12*$G$7)+I12 -> 0 | K12: =(+J12*$G$7)+J12 -> 0 | L12: =(+K12*$G$7)+K12 -> 0 | M12: =(+L12*$G$7)+L12 -> 0 | ... AH12: =(+AG12*$G$7)+AG12 -> 0
B13: On-site (resident mgr/other adm unit) | D13: =E13/Income!$L$25 -> #DIV/0! | F13: =(+E13*$G$7)+E13 -> 0 | G13: =(+F13*$G$7)+F13 -> 0 | H13: =(+G13*$G$7)+G13 -> 0 | I13: =(+H13*$G$7)+H13 -> 0 | J13: =(+I13*$G$7)+I13 -> 0 | K13: =(+J13*$G$7)+J13 -> 0 | L13: =(+K13*$G$7)+K13 -> 0 | M13: =(+L13*$G$7)+L13 -> 0 | ... AH13: =(+AG13*$G$7)+AG13 -> 0
B14: Contracted (Off-Site) | D14: =E14/Income!$L$25 -> #DIV/0! | F14: =(+E14*$G$7)+E14 -> 0 | G14: =(+F14*$G$7)+F14 -> 0 | H14: =(+G14*$G$7)+G14 -> 0 | I14: =(+H14*$G$7)+H14 -> 0 | J14: =(+I14*$G$7)+I14 -> 0 | K14: =(+J14*$G$7)+J14 -> 0 | L14: =(+K14*$G$7)+K14 -> 0 | M14: =(+L14*$G$7)+L14 -> 0 | ... AH14: =(+AG14*$G$7)+AG14 -> 0
A16: Professional Services - Legal/Audit/Accounting | D16: =E16/Income!$L$25 -> #DIV/0! | F16: =(+E16*$G$7)+E16 -> 0 | G16: =(+F16*$G$7)+F16 -> 0 | H16: =(+G16*$G$7)+G16 -> 0 | I16: =(+H16*$G$7)+H16 -> 0 | J16: =(+I16*$G$7)+I16 -> 0 | K16: =(+J16*$G$7)+J16 -> 0 | L16: =(+K16*$G$7)+K16 -> 0 | M16: =(+L16*$G$7)+L16 -> 0 | ... AH16: =(+AG16*$G$7)+AG16 -> 0
A18: Office & Administration | D18: =E18/Income!$L$25 -> #DIV/0! | F18: =(+E18*$G$7)+E18 -> 0 | G18: =(+F18*$G$7)+F18 -> 0 | H18: =(+G18*$G$7)+G18 -> 0 | I18: =(+H18*$G$7)+H18 -> 0 | J18: =(+I18*$G$7)+I18 -> 0 | K18: =(+J18*$G$7)+J18 -> 0 | L18: =(+K18*$G$7)+K18 -> 0 | M18: =(+L18*$G$7)+L18 -> 0 | ... AH18: =(+AG18*$G$7)+AG18 -> 0
A20: Advertising/Marketing & Promotion | D20: =E20/Income!$L$25 -> #DIV/0! | F20: =(+E20*$G$7)+E20 -> 0 | G20: =(+F20*$G$7)+F20 -> 0 | H20: =(+G20*$G$7)+G20 -> 0 | I20: =(+H20*$G$7)+H20 -> 0 | J20: =(+I20*$G$7)+I20 -> 0 | K20: =(+J20*$G$7)+J20 -> 0 | L20: =(+K20*$G$7)+K20 -> 0 | M20: =(+L20*$G$7)+L20 -> 0 | ... AH20: =(+AG20*$G$7)+AG20 -> 0
A22: Residential Bad Debt | D22: =E22/Income!$L$25 -> #DIV/0! | F22: =(+E22*$G$7)+E22 -> 0 | G22: =(+F22*$G$7)+F22 -> 0 | H22: =(+G22*$G$7)+G22 -> 0 | I22: =(+H22*$G$7)+H22 -> 0 | J22: =(+I22*$G$7)+I22 -> 0 | K22: =(+J22*$G$7)+J22 -> 0 | L22: =(+K22*$G$7)+K22 -> 0 | M22: =(+L22*$G$7)+L22 -> 0 | ... AH22: =(+AG22*$G$7)+AG22 -> 0
A24: Commercial Bad Debt | D24: =E24/Income!$L$25 -> #DIV/0! | F24: =(+E24*$G$7)+E24 -> 0 | G24: =(+F24*$G$7)+F24 -> 0 | H24: =(+G24*$G$7)+G24 -> 0 | I24: =(+H24*$G$7)+H24 -> 0 | J24: =(+I24*$G$7)+I24 -> 0 | K24: =(+J24*$G$7)+J24 -> 0 | L24: =(+K24*$G$7)+K24 -> 0 | M24: =(+L24*$G$7)+L24 -> 0 | ... AH24: =(+AG24*$G$7)+AG24 -> 0
A26: Security | D26: =E26/Income!$L$25 -> #DIV/0! | F26: =(+E26*$G$7)+E26 -> 0 | G26: =(+F26*$G$7)+F26 -> 0 | H26: =(+G26*$G$7)+G26 -> 0 | I26: =(+H26*$G$7)+H26 -> 0 | J26: =(+I26*$G$7)+I26 -> 0 | K26: =(+J26*$G$7)+J26 -> 0 | L26: =(+K26*$G$7)+K26 -> 0 | M26: =(+L26*$G$7)+L26 -> 0 | ... AH26: =(+AG26*$G$7)+AG26 -> 0
A28: Repairs:
B29: Repairs & Maint performed under contract | D29: =E29/Income!$L$25 -> #DIV/0! | F29: =(+E29*$G$7)+E29 -> 0 | G29: =(+F29*$G$7)+F29 -> 0 | H29: =(+G29*$G$7)+G29 -> 0 | I29: =(+H29*$G$7)+H29 -> 0 | J29: =(+I29*$G$7)+I29 -> 0 | K29: =(+J29*$G$7)+J29 -> 0 | L29: =(+K29*$G$7)+K29 -> 0 | M29: =(+L29*$G$7)+L29 -> 0 | ... AH29: =(+AG29*$G$7)+AG29 -> 0
B30: Repairs & Maint performed by property mgmt staff | D30: =E30/Income!$L$25 -> #DIV/0! | F30: =(+E30*$G$7)+E30 -> 0 | G30: =(+F30*$G$7)+F30 -> 0 | H30: =(+G30*$G$7)+G30 -> 0 | I30: =(+H30*$G$7)+H30 -> 0 | J30: =(+I30*$G$7)+I30 -> 0 | K30: =(+J30*$G$7)+J30 -> 0 | L30: =(+K30*$G$7)+K30 -> 0 | M30: =(+L30*$G$7)+L30 -> 0 | ... AH30: =(+AG30*$G$7)+AG30 -> 0
A32: Unit Turnover:
B33: Turnover performed under contract | D33: =E33/Income!$L$25 -> #DIV/0! | F33: =(+E33*$G$7)+E33 -> 0 | G33: =(+F33*$G$7)+F33 -> 0 | H33: =(+G33*$G$7)+G33 -> 0 | I33: =(+H33*$G$7)+H33 -> 0 | J33: =(+I33*$G$7)+I33 -> 0 | K33: =(+J33*$G$7)+J33 -> 0 | L33: =(+K33*$G$7)+K33 -> 0 | M33: =(+L33*$G$7)+L33 -> 0 | ... AH33: =(+AG33*$G$7)+AG33 -> 0
B34: Turnover performed by property mgmt staff | D34: =E34/Income!$L$25 -> #DIV/0! | F34: =(+E34*$G$7)+E34 -> 0 | G34: =(+F34*$G$7)+F34 -> 0 | H34: =(+G34*$G$7)+G34 -> 0 | I34: =(+H34*$G$7)+H34 -> 0 | J34: =(+I34*$G$7)+I34 -> 0 | K34: =(+J34*$G$7)+J34 -> 0 | L34: =(+K34*$G$7)+K34 -> 0 | M34: =(+L34*$G$7)+L34 -> 0 | ... AH34: =(+AG34*$G$7)+AG34 -> 0
A36: Elevator | D36: =E36/Income!$L$25 -> #DIV/0! | F36: =(+E36*$G$7)+E36 -> 0 | G36: =(+F36*$G$7)+F36 -> 0 | H36: =(+G36*$G$7)+G36 -> 0 | I36: =(+H36*$G$7)+H36 -> 0 | J36: =(+I36*$G$7)+I36 -> 0 | K36: =(+J36*$G$7)+J36 -> 0 | L36: =(+K36*$G$7)+K36 -> 0 | M36: =(+L36*$G$7)+L36 -> 0 | ... AH36: =(+AG36*$G$7)+AG36 -> 0
A38: Landscaping | D38: =E38/Income!$L$25 -> #DIV/0! | F38: =(+E38*$G$7)+E38 -> 0 | G38: =(+F38*$G$7)+F38 -> 0 | H38: =(+G38*$G$7)+G38 -> 0 | I38: =(+H38*$G$7)+H38 -> 0 | J38: =(+I38*$G$7)+I38 -> 0 | K38: =(+J38*$G$7)+J38 -> 0 | L38: =(+K38*$G$7)+K38 -> 0 | M38: =(+L38*$G$7)+L38 -> 0 | ... AH38: =(+AG38*$G$7)+AG38 -> 0
A40: Utilities:
B41: Electric | D41: =E41/Income!$L$25 -> #DIV/0! | F41: =(+E41*$G$7)+E41 -> 0 | G41: =(+F41*$G$7)+F41 -> 0 | H41: =(+G41*$G$7)+G41 -> 0 | I41: =(+H41*$G$7)+H41 -> 0 | J41: =(+I41*$G$7)+I41 -> 0 | K41: =(+J41*$G$7)+J41 -> 0 | L41: =(+K41*$G$7)+K41 -> 0 | M41: =(+L41*$G$7)+L41 -> 0 | ... AH41: =(+AG41*$G$7)+AG41 -> 0
B42: Natural Gas | D42: =E42/Income!$L$25 -> #DIV/0! | F42: =(+E42*$G$7)+E42 -> 0 | G42: =(+F42*$G$7)+F42 -> 0 | H42: =(+G42*$G$7)+G42 -> 0 | I42: =(+H42*$G$7)+H42 -> 0 | J42: =(+I42*$G$7)+I42 -> 0 | K42: =(+J42*$G$7)+J42 -> 0 | L42: =(+K42*$G$7)+K42 -> 0 | M42: =(+L42*$G$7)+L42 -> 0 | ... AH42: =(+AG42*$G$7)+AG42 -> 0
B43: Water & Sewer | D43: =E43/Income!$L$25 -> #DIV/0! | F43: =(+E43*$G$7)+E43 -> 0 | G43: =(+F43*$G$7)+F43 -> 0 | H43: =(+G43*$G$7)+G43 -> 0 | I43: =(+H43*$G$7)+H43 -> 0 | J43: =(+I43*$G$7)+I43 -> 0 | K43: =(+J43*$G$7)+J43 -> 0 | L43: =(+K43*$G$7)+K43 -> 0 | M43: =(+L43*$G$7)+L43 -> 0 | ... AH43: =(+AG43*$G$7)+AG43 -> 0
B44: Garbage Removal | D44: =E44/Income!$L$25 -> #DIV/0! | F44: =(+E44*$G$7)+E44 -> 0 | G44: =(+F44*$G$7)+F44 -> 0 | H44: =(+G44*$G$7)+G44 -> 0 | I44: =(+H44*$G$7)+H44 -> 0 | J44: =(+I44*$G$7)+I44 -> 0 | K44: =(+J44*$G$7)+J44 -> 0 | L44: =(+K44*$G$7)+K44 -> 0 | M44: =(+L44*$G$7)+L44 -> 0 | ... AH44: =(+AG44*$G$7)+AG44 -> 0
B45: Other Utilities: | D45: =E45/Income!$L$25 -> #DIV/0! | F45: =(+E45*$G$7)+E45 -> 0 | G45: =(+F45*$G$7)+F45 -> 0 | H45: =(+G45*$G$7)+G45 -> 0 | I45: =(+H45*$G$7)+H45 -> 0 | J45: =(+I45*$G$7)+I45 -> 0 | K45: =(+J45*$G$7)+J45 -> 0 | L45: =(+K45*$G$7)+K45 -> 0 | M45: =(+L45*$G$7)+L45 -> 0 | ... AH45: =(+AG45*$G$7)+AG45 -> 0
A47: Real Estate Taxes | D47: =E47/Income!$L$25 -> #DIV/0! | F47: =(+E47*$G$7)+E47 -> 0 | G47: =(+F47*$G$7)+F47 -> 0 | H47: =(+G47*$G$7)+G47 -> 0 | I47: =(+H47*$G$7)+H47 -> 0 | J47: =(+I47*$G$7)+I47 -> 0 | K47: =(+J47*$G$7)+J47 -> 0 | L47: =(+K47*$G$7)+K47 -> 0 | M47: =(+L47*$G$7)+L47 -> 0 | ... AH47: =(+AG47*$G$7)+AG47 -> 0
A49: Insurance | D49: =E49/Income!$L$25 -> #DIV/0! | F49: =(+E49*$G$7)+E49 -> 0 | G49: =(+F49*$G$7)+F49 -> 0 | H49: =(+G49*$G$7)+G49 -> 0 | I49: =(+H49*$G$7)+H49 -> 0 | J49: =(+I49*$G$7)+I49 -> 0 | K49: =(+J49*$G$7)+J49 -> 0 | L49: =(+K49*$G$7)+K49 -> 0 | M49: =(+L49*$G$7)+L49 -> 0 | ... AH49: =(+AG49*$G$7)+AG49 -> 0
A51: Compliance Monitoring Fees | D51: =E51/Income!$L$25 -> #DIV/0! | F51: =(+E51*$G$7)+E51 -> 0 | G51: =(+F51*$G$7)+F51 -> 0 | H51: =(+G51*$G$7)+G51 -> 0 | I51: =(+H51*$G$7)+H51 -> 0 | J51: =(+I51*$G$7)+I51 -> 0 | K51: =(+J51*$G$7)+J51 -> 0 | L51: =(+K51*$G$7)+K51 -> 0 | M51: =(+L51*$G$7)+L51 -> 0 | ... AH51: =(+AG51*$G$7)+AG51 -> 0
A53: Asset Management Fees | D53: =E53/Income!$L$25 -> #DIV/0! | F53: =(+E53*$G$7)+E53 -> 0 | G53: =(+F53*$G$7)+F53 -> 0 | H53: =(+G53*$G$7)+G53 -> 0 | I53: =(+H53*$G$7)+H53 -> 0 | J53: =(+I53*$G$7)+I53 -> 0 | K53: =(+J53*$G$7)+J53 -> 0 | L53: =(+K53*$G$7)+K53 -> 0 | M53: =(+L53*$G$7)+L53 -> 0 | ... AH53: =(+AG53*$G$7)+AG53 -> 0
A55: Resident Services | D55: =E55/Income!$L$25 -> #DIV/0! | F55: =(+E55*$G$7)+E55 -> 0 | G55: =(+F55*$G$7)+F55 -> 0 | H55: =(+G55*$G$7)+G55 -> 0 | I55: =(+H55*$G$7)+H55 -> 0 | J55: =(+I55*$G$7)+I55 -> 0 | K55: =(+J55*$G$7)+J55 -> 0 | L55: =(+K55*$G$7)+K55 -> 0 | M55: =(+L55*$G$7)+L55 -> 0 | ... AH55: =(+AG55*$G$7)+AG55 -> 0
A57: Gross Replacement Reserve Deposits | D57: =E57/Income!$L$25 -> #DIV/0! | F57: =(+E57*$G$7)+E57 -> 0 | G57: =(+F57*$G$7)+F57 -> 0 | H57: =(+G57*$G$7)+G57 -> 0 | I57: =(+H57*$G$7)+H57 -> 0 | J57: =(+I57*$G$7)+I57 -> 0 | K57: =(+J57*$G$7)+J57 -> 0 | L57: =(+K57*$G$7)+K57 -> 0 | M57: =(+L57*$G$7)+L57 -> 0 | ... AH57: =(+AG57*$G$7)+AG57 -> 0
A59: Commercial Expense (See Comment): | D59: 0 | F59: =(+E59*$G$7)+E59 -> 0 | G59: =(+F59*$G$7)+F59 -> 0 | H59: =(+G59*$G$7)+G59 -> 0 | I59: =(+H59*$G$7)+H59 -> 0 | J59: =(+I59*$G$7)+I59 -> 0 | K59: =(+J59*$G$7)+J59 -> 0 | L59: =(+K59*$G$7)+K59 -> 0 | M59: =(+L59*$G$7)+L59 -> 0 | ... AH59: =(+AG59*$G$7)+AG59 -> 0
A61: Other: | D61: =E61/Income!$L$25 -> #DIV/0! | F61: =(+E61*$G$7)+E61 -> 0 | G61: =(+F61*$G$7)+F61 -> 0 | H61: =(+G61*$G$7)+G61 -> 0 | I61: =(+H61*$G$7)+H61 -> 0 | J61: =(+I61*$G$7)+I61 -> 0 | K61: =(+J61*$G$7)+J61 -> 0 | L61: =(+K61*$G$7)+K61 -> 0 | M61: =(+L61*$G$7)+L61 -> 0 | ... AH61: =(+AG61*$G$7)+AG61 -> 0
A64: Total Annual Operating Expenses: | D64: =SUM(D45:D63) -> #DIV/0! | E64: =SUM(E45:E63) -> 0 | F64: =SUM(F45:F63) -> 0 | G64: =SUM(G45:G63) -> 0 | H64: =SUM(H45:H63) -> 0 | I64: =SUM(I45:I63) -> 0 | J64: =SUM(J45:J63) -> 0 | K64: =SUM(K45:K63) -> 0 | ... AH64: =SUM(AH45:AH63) -> 0
A66: Less Debt Service:
A68: Must Pay Debt (Complete for Annual Reporting): | C68: Lender:
A69: First Position Loan Principal
A70: First Position Loan Interest
A71: Subordinate Loan Principal
A72: Subordinate Loan Interest
A73: Other Hard Debt Principal
A74: Other Hard Debt Interest
A75: Total Must Pay Debt
A77: Cash Flow Based Pmts (Priority Order): | C77: Recipient:
A78: Priority Payment 1
A79: Priority Payment 2
A80: Priority Payment 3
A81: Priority Payment 4
A82: Priority Payment 5
A83: Priority Payment 6
A86: Debt Service:
A88: Permanent loan
A89: Rate | B89: Term (Years) | C89: Loan Amount
D90: =(PMT($A$90/12,$B$90*12,-$C$90,0,0)*12)/Income!$L$25 -> #DIV/0! | E90: =IF($B$90>=E9,PMT($A$90/12,$B$90*12,-$C$90,0,0)*12,0) -> 0 | F90: =IF($B$90>=F9,PMT($A$90/12,$B$90*12,-$C$90,0,0)*12,0) -> 0 | G90: =IF($B$90>=G9,PMT($A$90/12,$B$90*12,-$C$90,0,0)*12,0) -> 0 | H90: =IF($B$90>=H9,PMT($A$90/12,$B$90*12,-$C$90,0,0)*12,0) -> 0 | I90: =IF($B$90>=I9,PMT($A$90/12,$B$90*12,-$C$90,0,0)*12,0) -> 0 | J90: =IF($B$90>=J9,PMT($A$90/12,$B$90*12,-$C$90,0,0)*12,0) -> 0 | K90: =IF($B$90>=K9,PMT($A$90/12,$B$90*12,-$C$90,0,0)*12,0) -> 0 | L90: =IF($B$90>=L9,PMT($A$90/12,$B$90*12,-$C$90,0,0)*12,0) -> 0 | ... AH90: =IF($B$90>=AH9,PMT($A$90/12,$B$90*12,-$C$90,0,0)*12,0) -> 0
A91: OAHTC Permanent loan
A92: Rate | B92: Term (Years) | C92: Loan Amount
A93: =+'OAHTC Calculation'!D10 -> -0.04 | B93: ='OAHTC Calculation'!D11 -> 1 | C93: ='OAHTC Calculation'!F9 -> 0 | D93: =(PMT($A$93/12,$B$93*12,-$C$93,0,0)*12/Income!$L$25) -> #DIV/0! | E93: =IF('OAHTC Calculation'!$F$12>=E9,PMT($A$93/12,$B$93*12,-$C$93,0,0)*12,0) -> 0 | F93: =IF('OAHTC Calculation'!$F$12>=F9,PMT($A$93/12,$B$93*12,-$C$93,0,0)*12,0) -> 0 | G93: =IF('OAHTC Calculation'!$F$12>=G9,PMT($A$93/12,$B$93*12,-$C$93,0,0)*12,0) -> 0 | H93: =IF('OAHTC Calculation'!$F$12>=H9,PMT($A$93/12,$B$93*12,-$C$93,0,0)*12,0) -> 0 | I93: =IF('OAHTC Calculation'!$F$12>=I9,PMT($A$93/12,$B$93*12,-$C$93,0,0)*12,0) -> 0 | J93: =IF('OAHTC Calculation'!$F$12>=J9,PMT($A$93/12,$B$93*12,-$C$93,0,0)*12,0) -> 0 | K93: =IF('OAHTC Calculation'!$F$12>=K9,PMT($A$93/12,$B$93*12,-$C$93,0,0)*12,0) -> 0 | L93: =IF('OAHTC Calculation'!$F$12>=L9,PMT($A$93/12,$B$93*12,-$C$93,0,0)*12,0) -> 0 | ... AH93: =IF('OAHTC Calculation'!$F$12>=AH9,PMT($A$93/12,$B$93*12,-$C$93,0,0)*12,0) -> 0
A95: Portion of perm loan w/o OAHTC (if applicable)
B96: 1 | D96: =(PMT($A$96/12,$B$96*12,-$C$96,0,0)*12)/Income!$L$25 -> #DIV/0! | E96: =IF($B$96>=E9,PMT($A$96/12,$B$96*12,-$C$96,0,0)*12,0) -> 0 | F96: =IF($B$96>=F9,PMT($A$96/12,$B$96*12,-$C$96,0,0)*12,0) -> 0 | G96: =IF($B$96>=G9,PMT($A$96/12,$B$96*12,-$C$96,0,0)*12,0) -> 0 | H96: =IF($B$96>=H9,PMT($A$96/12,$B$96*12,-$C$96,0,0)*12,0) -> 0 | I96: =IF($B$96>=I9,PMT($A$96/12,$B$96*12,-$C$96,0,0)*12,0) -> 0 | J96: =IF($B$96>=J9,PMT($A$96/12,$B$96*12,-$C$96,0,0)*12,0) -> 0 | K96: =IF($B$96>=K9,PMT($A$96/12,$B$96*12,-$C$96,0,0)*12,0) -> 0 | L96: =IF($B$96>=L9,PMT($A$96/12,$B$96*12,-$C$96,0,0)*12,0) -> 0 | ... AH96: =IF($B$96>=AH9,PMT($A$96/12,$B$96*12,-$C$96,0,0)*12,0) -> 0
A97: Deferred Developer Fee
A98: Rate | B98: Term (Years) | C98: Loan Amount
B99: 1 | D99: =(PMT($A$99/12,$B$99*12,-$C$99,0,0)*12/Income!$L$25) -> #DIV/0! | E99: =IF($B$99>=E9,PMT($A$99/12,$B$99*12,-$C$99,0,0)*12,0) -> 0 | F99: =IF($B$99>=F9,PMT($A$99/12,$B$99*12,-$C$99,0,0)*12,0) -> 0 | G99: =IF($B$99>=G9,PMT($A$99/12,$B$99*12,-$C$99,0,0)*12,0) -> 0 | H99: =IF($B$99>=H9,PMT($A$99/12,$B$99*12,-$C$99,0,0)*12,0) -> 0 | I99: =IF($B$99>=I9,PMT($A$99/12,$B$99*12,-$C$99,0,0)*12,0) -> 0 | J99: =IF($B$99>=J9,PMT($A$99/12,$B$99*12,-$C$99,0,0)*12,0) -> 0 | K99: =IF($B$99>=K9,PMT($A$99/12,$B$99*12,-$C$99,0,0)*12,0) -> 0 | L99: =IF($B$99>=L9,PMT($A$99/12,$B$99*12,-$C$99,0,0)*12,0) -> 0 | ... AH99: =IF($B$99>=AH9,PMT($A$99/12,$B$99*12,-$C$99,0,0)*12,0) -> 0
A100: Amortized Debt (HOME Loan, Partnership Loans, etc.) & Cashflow Loans
A101: Rate | B101: Term (Years) | C101: Loan Amount
B102: 1 | D102: =(PMT($A$102/12,$B$102*12,-$C$102,0,0)*12/Income!$L$25) -> #DIV/0! | E102: =IF($B$102>=E9,PMT($A$102/12,$B$102*12,-$C$102,0,0)*12,0) -> 0 | F102: =IF($B$102>=F9,PMT($A$102/12,$B$102*12,-$C$102,0,0)*12,0) -> 0 | G102: =IF($B$102>=G9,PMT($A$102/12,$B$102*12,-$C$102,0,0)*12,0) -> 0 | H102: =IF($B$102>=H9,PMT($A$102/12,$B$102*12,-$C$102,0,0)*12,0) -> 0 | I102: =IF($B$102>=I9,PMT($A$102/12,$B$102*12,-$C$102,0,0)*12,0) -> 0 | J102: =IF($B$102>=J9,PMT($A$102/12,$B$102*12,-$C$102,0,0)*12,0) -> 0 | K102: =IF($B$102>=K9,PMT($A$102/12,$B$102*12,-$C$102,0,0)*12,0) -> 0 | L102: =IF($B$102>=L9,PMT($A$102/12,$B$102*12,-$C$102,0,0)*12,0) -> 0 | ... AH102: =IF($B$102>=AH9,PMT($A$102/12,$B$102*12,-$C$102,0,0)*12,0) -> 0
B103: 1 | D103: =(PMT($A$103/12,$B$103*12,-$C$103,0,0)*12/Income!$L$25) -> #DIV/0! | E103: =IF($B$103>=E9,PMT($A$103/12,$B$103*12,-$C$103,0,0)*12,0) -> 0 | F103: =IF($B$103>=F9,PMT($A$103/12,$B$103*12,-$C$103,0,0)*12,0) -> 0 | G103: =IF($B$103>=G9,PMT($A$103/12,$B$103*12,-$C$103,0,0)*12,0) -> 0 | H103: =IF($B$103>=H9,PMT($A$103/12,$B$103*12,-$C$103,0,0)*12,0) -> 0 | I103: =IF($B$103>=I9,PMT($A$103/12,$B$103*12,-$C$103,0,0)*12,0) -> 0 | J103: =IF($B$103>=J9,PMT($A$103/12,$B$103*12,-$C$103,0,0)*12,0) -> 0 | K103: =IF($B$103>=K9,PMT($A$103/12,$B$103*12,-$C$103,0,0)*12,0) -> 0 | L103: =IF($B$103>=L9,PMT($A$103/12,$B$103*12,-$C$103,0,0)*12,0) -> 0 | ... AH103: =IF($B$103>=AH9,PMT($A$103/12,$B$103*12,-$C$103,0,0)*12,0) -> 0
B104: 1 | D104: =(PMT($A$104/12,$B$104*12,-$C$104,0,0)*12/Income!$L$25) -> #DIV/0! | E104: =IF($B$104>=E10,PMT($A$104/12,$B$104*12,-$C$104,0,0)*12,0) -> 0 | F104: =IF($B$104>=F10,PMT($A$104/12,$B$104*12,-$C$104,0,0)*12,0) -> 0 | G104: =IF($B$104>=G10,PMT($A$104/12,$B$104*12,-$C$104,0,0)*12,0) -> 0 | H104: =IF($B$104>=H10,PMT($A$104/12,$B$104*12,-$C$104,0,0)*12,0) -> 0 | I104: =IF($B$104>=I10,PMT($A$104/12,$B$104*12,-$C$104,0,0)*12,0) -> 0 | J104: =IF($B$104>=J10,PMT($A$104/12,$B$104*12,-$C$104,0,0)*12,0) -> 0 | K104: =IF($B$104>=K10,PMT($A$104/12,$B$104*12,-$C$104,0,0)*12,0) -> 0 | L104: =IF($B$104>=L10,PMT($A$104/12,$B$104*12,-$C$104,0,0)*12,0) -> 0 | ... AH104: =IF($B$104>=AH10,PMT($A$104/12,$B$104*12,-$C$104,0,0)*12,0) -> 0
A106: WITHOUT OAHTC
A107: Effective Gross Income: | D107: =Income!N42/Income!L25 -> #DIV/0! | E107: =Income!N42 -> 0 | F107: =Income!O42 -> 0 | G107: =Income!P42 -> 0 | H107: =Income!Q42 -> 0 | I107: =Income!R42 -> 0 | J107: =Income!S42 -> 0 | K107: =Income!T42 -> 0 | L107: =Income!U42 -> 0 | ... AH107: =Income!AQ42 -> 0
A108: Total Annual Operating Expenses: | D108: =D64 -> #DIV/0! | E108: =E64 -> 0 | F108: =F64 -> 0 | G108: =G64 -> 0 | H108: =H64 -> 0 | I108: =I64 -> 0 | J108: =J64 -> 0 | K108: =K64 -> 0 | ... AH108: =AH64 -> 0
A109: Net Operating Income: | D109: =D107-D108 -> #DIV/0! | E109: =E107-E108 -> 0 | F109: =F107-F108 -> 0 | G109: =G107-G108 -> 0 | H109: =H107-H108 -> 0 | I109: =I107-I108 -> 0 | J109: =J107-J108 -> 0 | K109: =K107-K108 -> 0 | ... AH109: =AH107-AH108 -> 0
A110: Primary Debt Service | D110: =D90 -> #DIV/0! | E110: =E90 -> 0 | F110: =F90 -> 0 | G110: =G90 -> 0 | H110: =H90 -> 0 | I110: =I90 -> 0 | J110: =J90 -> 0 | K110: =K90 -> 0 | ... AH110: =AH90 -> 0
A111: Total Debt Service | D111: =SUM(D102:D105)+D90+D99 -> #DIV/0! | E111: =SUM(E102:E105)+E90+E99 -> 0 | F111: =SUM(F102:F105)+F90+F99 -> 0 | G111: =SUM(G102:G105)+G90+G99 -> 0 | H111: =SUM(H102:H105)+H90+H99 -> 0 | I111: =SUM(I102:I105)+I90+I99 -> 0 | J111: =SUM(J102:J105)+J90+J99 -> 0 | K111: =SUM(K102:K105)+K90+K99 -> 0 | ... AH111: =SUM(AH102:AH105)+AH90+AH99 -> 0
A112: Cash Flow Per Year | D112: =D109-D111 -> #DIV/0! | E112: =E109-E111 -> 0 | F112: =F109-F111 -> 0 | G112: =G109-G111 -> 0 | H112: =H109-H111 -> 0 | I112: =I109-I111 -> 0 | J112: =J109-J111 -> 0 | K112: =K109-K111 -> 0 | ... AH112: =AH109-AH111 -> 0
A113: Primary Debt Coverage Ratio | D113: =D109/D110 -> #DIV/0! | E113: =E109/E110 -> #DIV/0! | F113: =F109/F110 -> #DIV/0! | G113: =G109/G110 -> #DIV/0! | H113: =H109/H110 -> #DIV/0! | I113: =I109/I110 -> #DIV/0! | J113: =J109/J110 -> #DIV/0! | K113: =K109/K110 -> #DIV/0! | ... AH113: =AH109/AH110 -> #DIV/0!
A114: Total Debt Coverage Ratio | D114: =D109/D111 -> #DIV/0! | E114: =E109/E111 -> #DIV/0! | F114: =F109/F111 -> #DIV/0! | G114: =G109/G111 -> #DIV/0! | H114: =H109/H111 -> #DIV/0! | I114: =I109/I111 -> #DIV/0! | J114: =J109/J111 -> #DIV/0! | K114: =K109/K111 -> #DIV/0! | ... AH114: =AH109/AH111 -> #DIV/0!
A116: WITH OAHTC
A117: Effective Gross Income: | D117: ='Income with OAHTC'!N50/'Income with OAHTC'!L25 -> #DIV/0! | E117: ='Income with OAHTC'!N50 -> 0 | F117: ='Income with OAHTC'!O50 -> 0 | G117: ='Income with OAHTC'!P50 -> 0 | H117: ='Income with OAHTC'!Q50 -> 0 | I117: ='Income with OAHTC'!R50 -> 0 | J117: ='Income with OAHTC'!S50 -> 0 | K117: ='Income with OAHTC'!T50 -> 0 | L117: ='Income with OAHTC'!U50 -> 0 | ... AH117: ='Income with OAHTC'!AQ50 -> 0
A118: Total Annual Operating Expenses: | D118: =D64 -> #DIV/0! | E118: =E64 -> 0 | F118: =F64 -> 0 | G118: =G64 -> 0 | H118: =H64 -> 0 | I118: =I64 -> 0 | J118: =J64 -> 0 | K118: =K64 -> 0 | ... AH118: =AH64 -> 0
A119: Net Operating Income: | D119: =D117-D118 -> #DIV/0! | E119: =E117-E118 -> 0 | F119: =F117-F118 -> 0 | G119: =G117-G118 -> 0 | H119: =H117-H118 -> 0 | I119: =I117-I118 -> 0 | J119: =J117-J118 -> 0 | K119: =K117-K118 -> 0 | ... AH119: =AH117-AH118 -> 0
A120: Primary Debt Service | D120: =D93+D96 -> #DIV/0! | E120: =E93+E96 -> 0 | F120: =F93+F96 -> 0 | G120: =G93+G96 -> 0 | H120: =H93+H96 -> 0 | I120: =I93+I96 -> 0 | J120: =J93+J96 -> 0 | K120: =K93+K96 -> 0 | ... AH120: =AH93+AH96 -> 0
A121: Total Debt Service: | D121: =SUM(D102:D105)+D93+D96+D99 -> #DIV/0! | E121: =SUM(E102:E105)+E93+E96+E99 -> 0 | F121: =SUM(F102:F105)+F93+F96+F99 -> 0 | G121: =SUM(G102:G105)+G93+G96+G99 -> 0 | H121: =SUM(H102:H105)+H93+H96+H99 -> 0 | I121: =SUM(I102:I105)+I93+I96+I99 -> 0 | J121: =SUM(J102:J105)+J93+J96+J99 -> 0 | K121: =SUM(K102:K105)+K93+K96+K99 -> 0 | ... AH121: =SUM(AH102:AH105)+AH93+AH96+AH99 -> 0
A122: Cash Flow Per Year: | D122: =D119-D121 -> #DIV/0! | E122: =E119-E121 -> 0 | F122: =F119-F121 -> 0 | G122: =G119-G121 -> 0 | H122: =H119-H121 -> 0 | I122: =I119-I121 -> 0 | J122: =J119-J121 -> 0 | K122: =K119-K121 -> 0 | ... AH122: =AH119-AH121 -> 0
A123: Primary Debt Coverage Ratio: | D123: =D119/D120 -> #DIV/0! | E123: =E119/E120 -> #DIV/0! | F123: =F119/F120 -> #DIV/0! | G123: =G119/G120 -> #DIV/0! | H123: =H119/H120 -> #DIV/0! | I123: =I119/I120 -> #DIV/0! | J123: =J119/J120 -> #DIV/0! | K123: =K119/K120 -> #DIV/0! | ... AH123: =AH119/AH120 -> #DIV/0!
A124: Total Debt Coverage Ratio: | D124: =D119/D121 -> #DIV/0! | E124: =E119/E121 -> #DIV/0! | F124: =F119/F121 -> #DIV/0! | G124: =G119/G121 -> #DIV/0! | H124: =H119/H121 -> #DIV/0! | I124: =I119/I121 -> #DIV/0! | J124: =J119/J121 -> #DIV/0! | K124: =K119/K121 -> #DIV/0! | ... AH124: =AH119/AH121 -> #DIV/0!

Sheet Utility Allowance
A1: UTILITY ALLOWANCE INFORMATION
B3: Project Name: | C3: =Sources!$B$3 -> 0 | E3: Date: | F3: =Sources!F3 -> 40909
A5: UTILITIES | B5: TYPE OF UTILITY (Gas, elec., Oil,etc.) | C5: OWNER PAYS | D5: TENANT PAYS | E5: 0 BDRM | F5: 1 BDRM | G5: 2 BDRM | H5: 3 BDRM | I5: 4 BDRM
A7: Heating
A8: Lighting
A9: Air Conditioning
A10: Cooking
A11: Hot Water
A12: Water
A13: Sewer
A14: Trash Removal
A16: TOTAL UTILITY ALLOWANCE | E16: =SUM(E7:E15) -> 0 | F16: =SUM(F7:F15) -> 0 | G16: =SUM(G7:G15) -> 0 | H16: =SUM(H7:H15) -> 0 | I16: =SUM(I7:I15) -> 0
A19: Source of Utility Allowance Calculation: (Attach a Copy)
B21: Local Housing Authority
B22: Utility Company
B23: Other
A25: If allowances are calculated by other methods, attach the appropriate schedule and include
A26: unit rents, number of bedrooms, and allowances

Sheet Comm Income
A1: COMMERCIAL OPERATING BUDGET - INCOME
B3: Project Name: | E3: =Sources!$B$3 -> 0
D4: Date: | E4: =Sources!F3 -> 40909
D6: Annual Inflation Rate Factor: | E6: 0.02
A8: ANNUAL Commercial Income:
H9: 1 | I9: 2 | J9: 3 | K9: 4 | L9: 5 | M9: 6 | N9: 7 | O9: 8 | P9: 9 | Q9: 10 | R9: 11 | S9: 12 | T9: 13 | U9: 14 | V9: 15 | W9: 16 | X9: 17 | Y9: 18 | Z9: 19 | AA9: 20 | AB9: 21 | AC9: 22 | AD9: 23 | AE9: 24 | AF9: 25 | AG9: 26 | AH9: 27 | AI9: 28 | AJ9: 29 | AK9: 30
A11: Commercial Income: | I11: =(+H11*$E$6)+H11 -> 0 | J11: =(+I11*$E$6)+I11 -> 0 | K11: =(+J11*$E$6)+J11 -> 0 | L11: =(+K11*$E$6)+K11 -> 0 | M11: =(+L11*$E$6)+L11 -> 0 | N11: =(+M11*$E$6)+M11 -> 0 | O11: =(+N11*$E$6)+N11 -> 0 | P11: =(+O11*$E$6)+O11 -> 0 | ... AK11: =(+AJ11*$E$6)+AJ11 -> 0
A12: Other: | I12: =(+H12*$E$6)+H12 -> 0 | J12: =(+I12*$E$6)+I12 -> 0 | K12: =(+J12*$E$6)+J12 -> 0 | L12: =(+K12*$E$6)+K12 -> 0 | M12: =(+L12*$E$6)+L12 -> 0 | N12: =(+M12*$E$6)+M12 -> 0 | O12: =(+N12*$E$6)+N12 -> 0 | P12: =(+O12*$E$6)+O12 -> 0 | ... AK12: =(+AJ12*$E$6)+AJ12 -> 0
A13: Other: | I13: =(+H13*$E$6)+H13 -> 0 | J13: =(+I13*$E$6)+I13 -> 0 | K13: =(+J13*$E$6)+J13 -> 0 | L13: =(+K13*$E$6)+K13 -> 0 | M13: =(+L13*$E$6)+L13 -> 0 | N13: =(+M13*$E$6)+M13 -> 0 | O13: =(+N13*$E$6)+N13 -> 0 | P13: =(+O13*$E$6)+O13 -> 0 | ... AK13: =(+AJ13*$E$6)+AJ13 -> 0
A14: Other: | I14: =(+H14*$E$6)+H14 -> 0 | J14: =(+I14*$E$6)+I14 -> 0 | K14: =(+J14*$E$6)+J14 -> 0 | L14: =(+K14*$E$6)+K14 -> 0 | M14: =(+L14*$E$6)+L14 -> 0 | N14: =(+M14*$E$6)+M14 -> 0 | O14: =(+N14*$E$6)+N14 -> 0 | P14: =(+O14*$E$6)+O14 -> 0 | ... AK14: =(+AJ14*$E$6)+AJ14 -> 0
A15: Other: | I15: =(+H15*$E$6)+H15 -> 0 | J15: =(+I15*$E$6)+I15 -> 0 | K15: =(+J15*$E$6)+J15 -> 0 | L15: =(+K15*$E$6)+K15 -> 0 | M15: =(+L15*$E$6)+L15 -> 0 | N15: =(+M15*$E$6)+M15 -> 0 | O15: =(+N15*$E$6)+N15 -> 0 | P15: =(+O15*$E$6)+O15 -> 0 | ... AK15: =(+AJ15*$E$6)+AJ15 -> 0
A16: Other: | I16: =(+H16*$E$6)+H16 -> 0 | J16: =(+I16*$E$6)+I16 -> 0 | K16: =(+J16*$E$6)+J16 -> 0 | L16: =(+K16*$E$6)+K16 -> 0 | M16: =(+L16*$E$6)+L16 -> 0 | N16: =(+M16*$E$6)+M16 -> 0 | O16: =(+N16*$E$6)+N16 -> 0 | P16: =(+O16*$E$6)+O16 -> 0 | ... AK16: =(+AJ16*$E$6)+AJ16 -> 0
A17: Other: | I17: =(+H17*$E$6)+H17 -> 0 | J17: =(+I17*$E$6)+I17 -> 0 | K17: =(+J17*$E$6)+J17 -> 0 | L17: =(+K17*$E$6)+K17 -> 0 | M17: =(+L17*$E$6)+L17 -> 0 | N17: =(+M17*$E$6)+M17 -> 0 | O17: =(+N17*$E$6)+N17 -> 0 | P17: =(+O17*$E$6)+O17 -> 0 | ... AK17: =(+AJ17*$E$6)+AJ17 -> 0
A19: TOTAL COMMERCIAL REVENUE | H19: =SUM(H11:H18) -> 0 | I19: =SUM(I11:I18) -> 0 | J19: =SUM(J11:J18) -> 0 | K19: =SUM(K11:K18) -> 0 | L19: =SUM(L11:L18) -> 0 | M19: =SUM(M11:M18) -> 0 | N19: =SUM(N11:N18) -> 0 | O19: =SUM(O11:O18) -> 0 | ... AK19: =SUM(AK11:AK18) -> 0
A21: Less Vacancy Rate | E21: 0.1 | H21: =H19*$E$21 -> 0 | I21: =I19*$E$21 -> 0 | J21: =J19*$E$21 -> 0 | K21: =K19*$E$21 -> 0 | L21: =L19*$E$21 -> 0 | M21: =M19*$E$21 -> 0 | N21: =N19*$E$21 -> 0 | O21: =O19*$E$21 -> 0 | ... AK21: =AK19*$E$21 -> 0
A23: Effective Gross Income: | H23: =H19-H21 -> 0 | I23: =I19-I21 -> 0 | J23: =J19-J21 -> 0 | K23: =K19-K21 -> 0 | L23: =L19-L21 -> 0 | M23: =M19-M21 -> 0 | N23: =N19-N21 -> 0 | O23: =O19-O21 -> 0 | ... AK23: =AK19-AK21 -> 0

Sheet Com Expense
A3: COMMERCIAL OPERATING BUDGET - EXPENSES
B5: Project Name: | C5: =Sources!$B$3 -> 0
B7: Date: | C7: =Sources!F3 -> 40909 | E7: Annual Inflation Rate Factor: | F7: 0.03
A9: ANNUAL Operating Expenses | D9: 1 | E9: 2 | F9: 3 | G9: 4 | H9: 5 | I9: 6 | J9: 7 | K9: 8 | L9: 9 | M9: 10 | N9: 11 | O9: 12 | P9: 13 | Q9: 14 | R9: 15 | S9: 16 | T9: 17 | U9: 18 | V9: 19 | W9: 20 | X9: 21 | Y9: 22 | Z9: 23 | AA9: 24 | AB9: 25 | AC9: 26 | AD9: 27 | AE9: 28 | AF9: 29 | AG9: 30
A11: Insurance | E11: =(+D11*$F$7)+D11 -> 0 | F11: =(+E11*$F$7)+E11 -> 0 | G11: =(+F11*$F$7)+F11 -> 0 | H11: =(+G11*$F$7)+G11 -> 0 | I11: =(+H11*$F$7)+H11 -> 0 | J11: =(+I11*$F$7)+I11 -> 0 | K11: =(+J11*$F$7)+J11 -> 0 | L11: =(+K11*$F$7)+K11 -> 0 | ... AG11: =(+AF11*$F$7)+AF11 -> 0
A13: Utilities:(common areas)
B14: Gas/Oil | E14: =(+D14*$F$7)+D14 -> 0 | F14: =(+E14*$F$7)+E14 -> 0 | G14: =(+F14*$F$7)+F14 -> 0 | H14: =(+G14*$F$7)+G14 -> 0 | I14: =(+H14*$F$7)+H14 -> 0 | J14: =(+I14*$F$7)+I14 -> 0 | K14: =(+J14*$F$7)+J14 -> 0 | L14: =(+K14*$F$7)+K14 -> 0 | ... AG14: =(+AF14*$F$7)+AF14 -> 0
B15: Electric | E15: =(+D15*$F$7)+D15 -> 0 | F15: =(+E15*$F$7)+E15 -> 0 | G15: =(+F15*$F$7)+F15 -> 0 | H15: =(+G15*$F$7)+G15 -> 0 | I15: =(+H15*$F$7)+H15 -> 0 | J15: =(+I15*$F$7)+I15 -> 0 | K15: =(+J15*$F$7)+J15 -> 0 | L15: =(+K15*$F$7)+K15 -> 0 | ... AG15: =(+AF15*$F$7)+AF15 -> 0
B16: Water & Sewer | E16: =(+D16*$F$7)+D16 -> 0 | F16: =(+E16*$F$7)+E16 -> 0 | G16: =(+F16*$F$7)+F16 -> 0 | H16: =(+G16*$F$7)+G16 -> 0 | I16: =(+H16*$F$7)+H16 -> 0 | J16: =(+I16*$F$7)+I16 -> 0 | K16: =(+J16*$F$7)+J16 -> 0 | L16: =(+K16*$F$7)+K16 -> 0 | ... AG16: =(+AF16*$F$7)+AF16 -> 0
B17: Garbage Removal | E17: =(+D17*$F$7)+D17 -> 0 | F17: =(+E17*$F$7)+E17 -> 0 | G17: =(+F17*$F$7)+F17 -> 0 | H17: =(+G17*$F$7)+G17 -> 0 | I17: =(+H17*$F$7)+H17 -> 0 | J17: =(+I17*$F$7)+I17 -> 0 | K17: =(+J17*$F$7)+J17 -> 0 | L17: =(+K17*$F$7)+K17 -> 0 | ... AG17: =(+AF17*$F$7)+AF17 -> 0
A19: Repairs | E19: =(+D19*$F$7)+D19 -> 0 | F19: =(+E19*$F$7)+E19 -> 0 | G19: =(+F19*$F$7)+F19 -> 0 | H19: =(+G19*$F$7)+G19 -> 0 | I19: =(+H19*$F$7)+H19 -> 0 | J19: =(+I19*$F$7)+I19 -> 0 | K19: =(+J19*$F$7)+J19 -> 0 | L19: =(+K19*$F$7)+K19 -> 0 | ... AG19: =(+AF19*$F$7)+AF19 -> 0
A20: General Maintenance | E20: =(+D20*$F$7)+D20 -> 0 | F20: =(+E20*$F$7)+E20 -> 0 | G20: =(+F20*$F$7)+F20 -> 0 | H20: =(+G20*$F$7)+G20 -> 0 | I20: =(+H20*$F$7)+H20 -> 0 | J20: =(+I20*$F$7)+I20 -> 0 | K20: =(+J20*$F$7)+J20 -> 0 | L20: =(+K20*$F$7)+K20 -> 0 | ... AG20: =(+AF20*$F$7)+AF20 -> 0
A21: Landscape Maintenance | E21: =(+D21*$F$7)+D21 -> 0 | F21: =(+E21*$F$7)+E21 -> 0 | G21: =(+F21*$F$7)+F21 -> 0 | H21: =(+G21*$F$7)+G21 -> 0 | I21: =(+H21*$F$7)+H21 -> 0 | J21: =(+I21*$F$7)+I21 -> 0 | K21: =(+J21*$F$7)+J21 -> 0 | L21: =(+K21*$F$7)+K21 -> 0 | ... AG21: =(+AF21*$F$7)+AF21 -> 0
A22: Replacement Reserve | E22: =(+D22*$F$7)+D22 -> 0 | F22: =(+E22*$F$7)+E22 -> 0 | G22: =(+F22*$F$7)+F22 -> 0 | H22: =(+G22*$F$7)+G22 -> 0 | I22: =(+H22*$F$7)+H22 -> 0 | J22: =(+I22*$F$7)+I22 -> 0 | K22: =(+J22*$F$7)+J22 -> 0 | L22: =(+K22*$F$7)+K22 -> 0 | ... AG22: =(+AF22*$F$7)+AF22 -> 0
A24: Property Management:
B25: On-site | E25: =(+D25*$F$7)+D25 -> 0 | F25: =(+E25*$F$7)+E25 -> 0 | G25: =(+F25*$F$7)+F25 -> 0 | H25: =(+G25*$F$7)+G25 -> 0 | I25: =(+H25*$F$7)+H25 -> 0 | J25: =(+I25*$F$7)+I25 -> 0 | K25: =(+J25*$F$7)+J25 -> 0 | L25: =(+K25*$F$7)+K25 -> 0 | ... AG25: =(+AF25*$F$7)+AF25 -> 0
B26: Contracted (Off-Site) | E26: =(+D26*$F$7)+D26 -> 0 | F26: =(+E26*$F$7)+E26 -> 0 | G26: =(+F26*$F$7)+F26 -> 0 | H26: =(+G26*$F$7)+G26 -> 0 | I26: =(+H26*$F$7)+H26 -> 0 | J26: =(+I26*$F$7)+I26 -> 0 | K26: =(+J26*$F$7)+J26 -> 0 | L26: =(+K26*$F$7)+K26 -> 0 | ... AG26: =(+AF26*$F$7)+AF26 -> 0
A28: Professional Services:
B29: Legal | E29: =(+D29*$F$7)+D29 -> 0 | F29: =(+E29*$F$7)+E29 -> 0 | G29: =(+F29*$F$7)+F29 -> 0 | H29: =(+G29*$F$7)+G29 -> 0 | I29: =(+H29*$F$7)+H29 -> 0 | J29: =(+I29*$F$7)+I29 -> 0 | K29: =(+J29*$F$7)+J29 -> 0 | L29: =(+K29*$F$7)+K29 -> 0 | ... AG29: =(+AF29*$F$7)+AF29 -> 0
B30: Accounting | E30: =(+D30*$F$7)+D30 -> 0 | F30: =(+E30*$F$7)+E30 -> 0 | G30: =(+F30*$F$7)+F30 -> 0 | H30: =(+G30*$F$7)+G30 -> 0 | I30: =(+H30*$F$7)+H30 -> 0 | J30: =(+I30*$F$7)+I30 -> 0 | K30: =(+J30*$F$7)+J30 -> 0 | L30: =(+K30*$F$7)+K30 -> 0 | ... AG30: =(+AF30*$F$7)+AF30 -> 0
A32: Office & Administration | E32: =(+D32*$F$7)+D32 -> 0 | F32: =(+E32*$F$7)+E32 -> 0 | G32: =(+F32*$F$7)+F32 -> 0 | H32: =(+G32*$F$7)+G32 -> 0 | I32: =(+H32*$F$7)+H32 -> 0 | J32: =(+I32*$F$7)+I32 -> 0 | K32: =(+J32*$F$7)+J32 -> 0 | L32: =(+K32*$F$7)+K32 -> 0 | ... AG32: =(+AF32*$F$7)+AF32 -> 0
A33: Advertising/Marketing & Promotion | E33: =(+D33*$F$7)+D33 -> 0 | F33: =(+E33*$F$7)+E33 -> 0 | G33: =(+F33*$F$7)+F33 -> 0 | H33: =(+G33*$F$7)+G33 -> 0 | I33: =(+H33*$F$7)+H33 -> 0 | J33: =(+I33*$F$7)+I33 -> 0 | K33: =(+J33*$F$7)+J33 -> 0 | L33: =(+K33*$F$7)+K33 -> 0 | ... AG33: =(+AF33*$F$7)+AF33 -> 0
A34: Turnover | E34: =(+D34*$F$7)+D34 -> 0 | F34: =(+E34*$F$7)+E34 -> 0 | G34: =(+F34*$F$7)+F34 -> 0 | H34: =(+G34*$F$7)+G34 -> 0 | I34: =(+H34*$F$7)+H34 -> 0 | J34: =(+I34*$F$7)+I34 -> 0 | K34: =(+J34*$F$7)+J34 -> 0 | L34: =(+K34*$F$7)+K34 -> 0 | ... AG34: =(+AF34*$F$7)+AF34 -> 0
A35: Taxes(non-real estate) | E35: =(+D35*$F$7)+D35 -> 0 | F35: =(+E35*$F$7)+E35 -> 0 | G35: =(+F35*$F$7)+F35 -> 0 | H35: =(+G35*$F$7)+G35 -> 0 | I35: =(+H35*$F$7)+H35 -> 0 | J35: =(+I35*$F$7)+I35 -> 0 | K35: =(+J35*$F$7)+J35 -> 0 | L35: =(+K35*$F$7)+K35 -> 0 | ... AG35: =(+AF35*$F$7)+AF35 -> 0
A36: Real Estate Taxes | E36: =(+D36*$F$7)+D36 -> 0 | F36: =(+E36*$F$7)+E36 -> 0 | G36: =(+F36*$F$7)+F36 -> 0 | H36: =(+G36*$F$7)+G36 -> 0 | I36: =(+H36*$F$7)+H36 -> 0 | J36: =(+I36*$F$7)+I36 -> 0 | K36: =(+J36*$F$7)+J36 -> 0 | L36: =(+K36*$F$7)+K36 -> 0 | ... AG36: =(+AF36*$F$7)+AF36 -> 0
A37: Payroll Taxes | E37: =(+D37*$F$7)+D37 -> 0 | F37: =(+E37*$F$7)+E37 -> 0 | G37: =(+F37*$F$7)+F37 -> 0 | H37: =(+G37*$F$7)+G37 -> 0 | I37: =(+H37*$F$7)+H37 -> 0 | J37: =(+I37*$F$7)+I37 -> 0 | K37: =(+J37*$F$7)+J37 -> 0 | L37: =(+K37*$F$7)+K37 -> 0 | ... AG37: =(+AF37*$F$7)+AF37 -> 0
A38: Other: | E38: =(+D38*$F$7)+D38 -> 0 | F38: =(+E38*$F$7)+E38 -> 0 | G38: =(+F38*$F$7)+F38 -> 0 | H38: =(+G38*$F$7)+G38 -> 0 | I38: =(+H38*$F$7)+H38 -> 0 | J38: =(+I38*$F$7)+I38 -> 0 | K38: =(+J38*$F$7)+J38 -> 0 | L38: =(+K38*$F$7)+K38 -> 0 | ... AG38: =(+AF38*$F$7)+AF38 -> 0
A39: Other: | E39: =(+D39*$F$7)+D39 -> 0 | F39: =(+E39*$F$7)+E39 -> 0 | G39: =(+F39*$F$7)+F39 -> 0 | H39: =(+G39*$F$7)+G39 -> 0 | I39: =(+H39*$F$7)+H39 -> 0 | J39: =(+I39*$F$7)+I39 -> 0 | K39: =(+J39*$F$7)+J39 -> 0 | L39: =(+K39*$F$7)+K39 -> 0 | ... AG39: =(+AF39*$F$7)+AF39 -> 0
A41: Total Annual Operating Expenses: | D41: =SUM(D11:D40) -> 0 | E41: =SUM(E11:E40) -> 0 | F41: =SUM(F11:F40) -> 0 | G41: =SUM(G11:G40) -> 0 | H41: =SUM(H11:H40) -> 0 | I41: =SUM(I11:I40) -> 0 | J41: =SUM(J11:J40) -> 0 | K41: =SUM(K11:K40) -> 0 | ... AG41: =SUM(AG11:AG40) -> 0
A43: Less Debt Service:
A45: Permanent loan
A46: Rate | B46: Term (Years) | C46: Loan Amount
B47: 1 | D47: =IF($B$47>=D9,PMT($A$47/12,$B$47*12,-$C$47,0,0)*12,0) -> 0 | E47: =IF($B$47>=E9,PMT($A$47/12,$B$47*12,-$C$47,0,0)*12,0) -> 0 | F47: =IF($B$47>=F9,PMT($A$47/12,$B$47*12,-$C$47,0,0)*12,0) -> 0 | G47: =IF($B$47>=G9,PMT($A$47/12,$B$47*12,-$C$47,0,0)*12,0) -> 0 | H47: =IF($B$47>=H9,PMT($A$47/12,$B$47*12,-$C$47,0,0)*12,0) -> 0 | I47: =IF($B$47>=I9,PMT($A$47/12,$B$47*12,-$C$47,0,0)*12,0) -> 0 | J47: =IF($B$47>=J9,PMT($A$47/12,$B$47*12,-$C$47,0,0)*12,0) -> 0 | K47: =IF($B$47>=K9,PMT($A$47/12,$B$47*12,-$C$47,0,0)*12,0) -> 0 | ... AG47: =IF($B$47>=AG9,PMT($A$47/12,$B$47*12,-$C$47,0,0)*12,0) -> 0
A48: Deferred Developer Fee
A49: Rate | B49: Term (Years) | C49: Loan Amount
B50: 1 | D50: =IF($B$50>=D9,PMT($A$50/12,$B$50*12,-$C$50,0,0)*12,0) -> 0 | E50: =IF($B$50>=E9,PMT($A$50/12,$B$50*12,-$C$50,0,0)*12,0) -> 0 | F50: =IF($B$50>=F9,PMT($A$50/12,$B$50*12,-$C$50,0,0)*12,0) -> 0 | G50: =IF($B$50>=G9,PMT($A$50/12,$B$50*12,-$C$50,0,0)*12,0) -> 0 | H50: =IF($B$50>=H9,PMT($A$50/12,$B$50*12,-$C$50,0,0)*12,0) -> 0 | I50: =IF($B$50>=I9,PMT($A$50/12,$B$50*12,-$C$50,0,0)*12,0) -> 0 | J50: =IF($B$50>=J9,PMT($A$50/12,$B$50*12,-$C$50,0,0)*12,0) -> 0 | K50: =IF($B$50>=K9,PMT($A$50/12,$B$50*12,-$C$50,0,0)*12,0) -> 0 | ... AG50: =IF($B$50>=AG9,PMT($A$50/12,$B$50*12,-$C$50,0,0)*12,0) -> 0
A51: Amortized Debt (HOME Loan, , Partnership Loans,etc.) & Cashflow Loans
A53: Rate | B53: Term (Years) | C53: Loan Amount
B54: 1 | D54: =IF($B$54>=D9,PMT($A$54/12,$B$54*12,-$C$54,0,0)*12,0) -> 0 | E54: =IF($B$54>=E9,PMT($A$54/12,$B$54*12,-$C$54,0,0)*12,0) -> 0 | F54: =IF($B$54>=F9,PMT($A$54/12,$B$54*12,-$C$54,0,0)*12,0) -> 0 | G54: =IF($B$54>=G9,PMT($A$54/12,$B$54*12,-$C$54,0,0)*12,0) -> 0 | H54: =IF($B$54>=H9,PMT($A$54/12,$B$54*12,-$C$54,0,0)*12,0) -> 0 | I54: =IF($B$54>=I9,PMT($A$54/12,$B$54*12,-$C$54,0,0)*12,0) -> 0 | J54: =IF($B$54>=J9,PMT($A$54/12,$B$54*12,-$C$54,0,0)*12,0) -> 0 | K54: =IF($B$54>=K9,PMT($A$54/12,$B$54*12,-$C$54,0,0)*12,0) -> 0 | ... AG54: =IF($B$54>=AG9,PMT($A$54/12,$B$54*12,-$C$54,0,0)*12,0) -> 0
B55: 1 | D55: =IF($B$55>=D9,PMT($A$55/12,$B$55*12,-$C$55,0,0)*12,0) -> 0 | E55: =IF($B$55>=E9,PMT($A$55/12,$B$55*12,-$C$55,0,0)*12,0) -> 0 | F55: =IF($B$55>=F9,PMT($A$55/12,$B$55*12,-$C$55,0,0)*12,0) -> 0 | G55: =IF($B$55>=G9,PMT($A$55/12,$B$55*12,-$C$55,0,0)*12,0) -> 0 | H55: =IF($B$55>=H9,PMT($A$55/12,$B$55*12,-$C$55,0,0)*12,0) -> 0 | I55: =IF($B$55>=I9,PMT($A$55/12,$B$55*12,-$C$55,0,0)*12,0) -> 0 | J55: =IF($B$55>=J9,PMT($A$55/12,$B$55*12,-$C$55,0,0)*12,0) -> 0 | K55: =IF($B$55>=K9,PMT($A$55/12,$B$55*12,-$C$55,0,0)*12,0) -> 0 | ... AG55: =IF($B$55>=AG9,PMT($A$55/12,$B$55*12,-$C$55,0,0)*12,0) -> 0
B56: 1 | D56: =IF($B$56>=D10,PMT($A$56/12,$B$56*12,-$C$56,0,0)*12,0) -> 0 | E56: =IF($B$56>=E10,PMT($A$56/12,$B$56*12,-$C$56,0,0)*12,0) -> 0 | F56: =IF($B$56>=F10,PMT($A$56/12,$B$56*12,-$C$56,0,0)*12,0) -> 0 | G56: =IF($B$56>=G10,PMT($A$56/12,$B$56*12,-$C$56,0,0)*12,0) -> 0 | H56: =IF($B$56>=H10,PMT($A$56/12,$B$56*12,-$C$56,0,0)*12,0) -> 0 | I56: =IF($B$56>=I10,PMT($A$56/12,$B$56*12,-$C$56,0,0)*12,0) -> 0 | J56: =IF($B$56>=J10,PMT($A$56/12,$B$56*12,-$C$56,0,0)*12,0) -> 0 | K56: =IF($B$56>=K10,PMT($A$56/12,$B$56*12,-$C$56,0,0)*12,0) -> 0 | ... AG56: =IF($B$56>=AG10,PMT($A$56/12,$B$56*12,-$C$56,0,0)*12,0) -> 0
A59: Effective Gross Income: | D59: ='Comm Income'!H23 -> 0 | E59: ='Comm Income'!I23 -> 0 | F59: ='Comm Income'!J23 -> 0 | G59: ='Comm Income'!K23 -> 0 | H59: ='Comm Income'!L23 -> 0 | I59: ='Comm Income'!M23 -> 0 | J59: ='Comm Income'!N23 -> 0 | K59: ='Comm Income'!O23 -> 0 | ... AG59: ='Comm Income'!AK23 -> 0
A60: Total Annual Operating Expenses: | D60: =D41 -> 0 | E60: =E41 -> 0 | F60: =F41 -> 0 | G60: =G41 -> 0 | H60: =H41 -> 0 | I60: =I41 -> 0 | J60: =J41 -> 0 | K60: =K41 -> 0 | ... AG60: =AG41 -> 0
A61: Net Operating Income: | D61: =D59-D60 -> 0 | E61: =E59-E60 -> 0 | F61: =F59-F60 -> 0 | G61: =G59-G60 -> 0 | H61: =H59-H60 -> 0 | I61: =I59-I60 -> 0 | J61: =J59-J60 -> 0 | K61: =K59-K60 -> 0 | ... AG61: =AG59-AG60 -> 0
A62: Primary Debt Service | D62: =D47 -> 0 | E62: =E47 -> 0 | F62: =F47 -> 0 | G62: =G47 -> 0 | H62: =H47 -> 0 | I62: =I47 -> 0 | J62: =J47 -> 0 | K62: =K47 -> 0 | ... AG62: =AG47 -> 0
A63: Total Debt Service | D63: =SUM(D54:D57)+D47+D50 -> 0 | E63: =SUM(E54:E57)+E47+E50 -> 0 | F63: =SUM(F54:F57)+F47+F50 -> 0 | G63: =SUM(G54:G57)+G47+G50 -> 0 | H63: =SUM(H54:H57)+H47+H50 -> 0 | I63: =SUM(I54:I57)+I47+I50 -> 0 | J63: =SUM(J54:J57)+J47+J50 -> 0 | K63: =SUM(K54:K57)+K47+K50 -> 0 | ... AG63: =SUM(AG54:AG57)+AG47+AG50 -> 0
A64: Cash Flow Per Year | D64: =D61-D63 -> 0 | E64: =E61-E63 -> 0 | F64: =F61-F63 -> 0 | G64: =G61-G63 -> 0 | H64: =H61-H63 -> 0 | I64: =I61-I63 -> 0 | J64: =J61-J63 -> 0 | K64: =K61-K63 -> 0 | ... AG64: =AG61-AG63 -> 0
A65: Primary Debt Coverage Ratio | D65: =D61/D62 -> #DIV/0! | E65: =E61/E62 -> #DIV/0! | F65: =F61/F62 -> #DIV/0! | G65: =G61/G62 -> #DIV/0! | H65: =H61/H62 -> #DIV/0! | I65: =I61/I62 -> #DIV/0! | J65: =J61/J62 -> #DIV/0! | K65: =K61/K62 -> #DIV/0! | ... AG65: =AG61/AG62 -> #DIV/0!
A66: Total Debt Coverage Ratio | D66: =D61/D63 -> #DIV/0! | E66: =E61/E63 -> #DIV/0! | F66: =F61/F63 -> #DIV/0! | G66: =G61/G63 -> #DIV/0! | H66: =H61/H63 -> #DIV/0! | I66: =I61/I63 -> #DIV/0! | J66: =J61/J63 -> #DIV/0! | K66: =K61/K63 -> #DIV/0! | ... AG66: =AG61/AG63 -> #DIV/0!

Sheet Pro forma Summary
A1: Pro Forma Summary
A3: Project Name: | B3: =Sources!B3 -> 0 | D3: Date: | E3: =Sources!F3 -> 40909
A5: Number of Units: | B5: ='Uses of Funds'!C6 -> 0
A6: Square Footage: | C6: % of Total Sq. Foot
A7: Residential: | B7: ='Uses of Funds'!C7 -> 0 | C7: =B7/$B$10 -> #DIV/0!
A8: Common Areas: | B8: ='Uses of Funds'!C9 -> 0 | C8: =B8/$B$10 -> #DIV/0!
A9: Commercial/Other: | B9: ='Uses of Funds'!C10 -> 0 | C9: =B9/$B$10 -> #DIV/0!
A10: Total Square Footage: | B10: ='Uses of Funds'!C11 -> 0 | C10: =B10/$B$10 -> #DIV/0!
A12: Total Residential Project Cost:
B13: Total in Dollars | C13: Percent of Total Project Costs | D13: Total Cost Per Unit | E13: Total Cost Per Sq. Foot
A14: Acquisition Costs: | B14: ='Uses of Funds'!E25 -> 0 | C14: =B14/$B$17 -> #DIV/0! | D14: =B14/$B$5 -> #DIV/0! | E14: =B14/($B$7+$B$8) -> #DIV/0!
A15: Construction Costs: | B15: ='Uses of Funds'!E50 -> 0 | C15: =B15/$B$17 -> #DIV/0! | D15: =B15/$B$5 -> #DIV/0! | E15: =B15/($B$7+$B$8) -> #DIV/0!
A16: Development Costs: | B16: ='Uses of Funds'!E128 -> 0 | C16: =B16/$B$17 -> #DIV/0! | D16: =B16/$B$5 -> #DIV/0! | E16: =B16/($B$7+$B$8) -> #DIV/0!
A17: Total Project Costs : | B17: ='Uses of Funds'!E130 -> 0 | C17: =B17/$B$17 -> #DIV/0! | D17: =B17/$B$5 -> #DIV/0! | E17: =B17/($B$7+$B$8) -> #DIV/0!
A18: Construction:
C19: Percent of Construction | D19: Per Unit | E19: Per Sq. Foot
A20: Builder General Conditions | B20: ='Uses of Funds'!E39 -> 0 | C20: =B20/($B$15-$B$20) -> #DIV/0! | D20: =B20/$B$5 -> #DIV/0! | E20: =B20/($B$7+$B$8) -> #DIV/0!
A21: Builder Overhead | B21: ='Uses of Funds'!E41 -> 0 | C21: =B21/($B$15-$B$21) -> #DIV/0! | D21: =B21/$B$5 -> #DIV/0! | E21: =B21/($B$7+$B$8) -> #DIV/0!
A22: Builder Profit | B22: ='Uses of Funds'!E42 -> 0 | C22: =B22/($B$15-$B$22) -> #DIV/0! | D22: =B22/$B$5 -> #DIV/0! | E22: =B22/($B$7+$B$8) -> #DIV/0!
A23: Total Builder GC/O/P | B23: =SUM(B20:B22) -> 0 | C23: =B23/($B$15-$B$23) -> #DIV/0! | D23: =B23/$B$5 -> #DIV/0! | E23: =B23/($B$7+$B$8) -> #DIV/0!
A25: Construction Contingency | B25: ='Uses of Funds'!E43 -> 0 | C25: =B25/($B$15-$B$25) -> #DIV/0! | D25: =B25/$B$5 -> #DIV/0! | E25: =B25/($B$7+$B$8) -> #DIV/0!
A27: Architect's Fee | B27: ='Uses of Funds'!E69 -> 0 | C27: =B27/($B$15-$B$27) -> #DIV/0!
A28: Development Cost:
C29: Percent of Development | D29: Per Unit | E29: Per Sq. Foot
A30: Development Contingency | B30: ='Uses of Funds'!E121 -> 0 | C30: =B30/($B$16-$B$30) -> #DIV/0! | D30: =B30/$B$5 -> #DIV/0! | E30: =B30/($B$7+$B$8) -> #DIV/0!
B32: Total in Dollars | C32: Percent of Total Project Costs
A33: 5 % Max for Acquisition: | B33: =IF('Uses of Funds'!C4="x",('Uses of Funds'!E18+'Uses of Funds'!E19)*0.05, ) -> 0 | C33: =B33/(($B$17+(B33-$B$40)-B33)-'Uses of Funds'!E119-'Uses of Funds'!E120-'Uses of Funds'!E123) -> #DIV/0! | D33: =B33/$B$5 -> #DIV/0! | E33: =B33/($B$7+$B$8) -> #DIV/0!
A34: Max New Const/Rehab: | B34: =B35-B33 -> 0 | C34: =B34/(($B$17+(B34-$B$40)-B34-'Uses of Funds'!E119-'Uses of Funds'!E120-'Uses of Funds'!E123)) -> #DIV/0! | D34: =B34/$B$5 -> #DIV/0! | E34: =B34/($B$7+$B$8) -> #DIV/0!
A35: 15% Max Developer Fee: | B35: =('Uses of Funds'!E130-'Pro forma Summary'!B40-'Uses of Funds'!E76-'Uses of Funds'!E77-'Uses of Funds'!E119-'Uses of Funds'!E120-'Uses of Funds'!E123)*0.15 -> 0 | C35: =B35/(($B$17+(B35-$B$40)-B35-'Uses of Funds'!E119-'Uses of Funds'!E120-'Uses of Funds'!E123)) -> #DIV/0!
A37: Developer Fee: | B37: ='Uses of Funds'!E76 -> 0 | C37: =B37/($B$17-$B$40-'Uses of Funds'!E119-'Uses of Funds'!E120-'Uses of Funds'!E123) -> #DIV/0! | D37: =B37/$B$5 -> #DIV/0! | E37: =B37/($B$7+$B$8) -> #DIV/0!
A38: Consultant Fee | B38: ='Uses of Funds'!E77 -> 0 | C38: =B38/($B$17-$B$40-'Uses of Funds'!E119-'Uses of Funds'!E120-'Uses of Funds'!E123) -> #DIV/0! | D38: =B38/$B$5 -> #DIV/0! | E38: =B38/($B$7+$B$8) -> #DIV/0!
A39: Minimum Required Non-Profit Share of Developer Fee: (If Applicable) | B39: =B40*0.25 -> 0 | C39: =B39/($B$17-$B$40-'Uses of Funds'!E119-'Uses of Funds'!E120-'Uses of Funds'!E123) -> #DIV/0! | D39: =B39/$B$5 -> #DIV/0! | E39: =B39/($B$7+$B$8) -> #DIV/0!
A40: Total Developer Fee | B40: =B37+B38 -> 0 | C40: =B40/($B$17-$B$40-'Uses of Funds'!E119-'Uses of Funds'!E120-'Uses of Funds'!E123) -> #DIV/0! | D40: =B40/$B$5 -> #DIV/0! | E40: =B40/($B$7+$B$8) -> #DIV/0!
A41: Total Deferred Fee | B41: =Sources!$C$52+Sources!$D$52+Sources!$E$52 -> 0 | C41: =B41/($B$17-B40-'Uses of Funds'!E119-'Uses of Funds'!E120-'Uses of Funds'!E123) -> #DIV/0! | D41: =B41/$B$5 -> #DIV/0! | E41: =B41/($B$7+$B$8) -> #DIV/0!
A42: Total Cash Developer Fee: | B42: =B40-B41 -> 0 | C42: =B42/($B$17-$B$40-'Uses of Funds'!E119-'Uses of Funds'!E120-'Uses of Funds'!E123) -> #DIV/0! | D42: =B42/$B$5 -> #DIV/0! | E42: =B42/($B$7+$B$8) -> #DIV/0!
A44: Operating Income & Expense:
A45: Income: | C45: Percent of EGI | D45: Per Unit | E45: Per Sq. Foot
A46: EGI without OAHTC | B46: =Income!N42 -> 0 | D46: =B46/$B$5 -> #DIV/0! | E46: =B46/($B$7+$B$8) -> #DIV/0!
A47: EGI with OAHTC | B47: ='Income with OAHTC'!N50 -> 0 | D47: =B47/$B$5 -> #DIV/0! | E47: =B47/($B$7+$B$8) -> #DIV/0!
A49: Cash Flow without OAHTC | B49: =Expenses!E112 -> 0 | C49: =B49/B46 -> #DIV/0! | D49: =B49/$B$5 -> #DIV/0! | E49: =B49/($B$7+$B$8) -> #DIV/0!
A50: Cash Flow with OAHTC | B50: =Expenses!$E$122 -> 0 | C50: =B50/B47 -> #DIV/0! | D50: =B50/$B$5 -> #DIV/0! | E50: =B50/($B$7+$B$8) -> #DIV/0!
A52: Expenses:
A53: Total Op Expenses/Unit | B53: =Expenses!$D$64 -> #DIV/0! | C53: =B53/Income!N42 -> #DIV/0! | D53: =Expenses!$D$64 -> #DIV/0! | E53: =B53/($B$7+$B$8) -> #DIV/0!
A54: Less property tax | B54: =Expenses!D47 -> #DIV/0! | C54: =B54/Income!N42 -> #DIV/0! | D54: =Expenses!D47 -> #DIV/0! | E54: =B54/($B$7+$B$8) -> #DIV/0!
A55: Less resident services | B55: =Expenses!D55 -> #DIV/0! | C55: =B55/Income!N42 -> #DIV/0! | D55: =Expenses!D55 -> #DIV/0! | E55: =B55/($B$7+$B$8) -> #DIV/0!
A56: Net Op Exp/Unit | B56: =B53-(B54+B55) -> #DIV/0! | C56: =B56/Income!N42 -> #DIV/0! | D56: =B56/B5 -> #DIV/0! | E56: =B56/($B$7+$B$8) -> #DIV/0!
C58: Percent EGI w/o OAHTC | D58: Percent EGI w OAHTC
A60: On Site Mgmt Fee/Unit | B60: =Expenses!$D$60 -> 0 | C60: =B60/$B$46 -> #DIV/0! | D60: =B60/$B$47 -> #DIV/0!
A61: Off Site Mgmt Fee/Unit | B61: =Expenses!$D$61 -> #DIV/0! | C61: =B61/$B$46 -> #DIV/0! | D61: =B61/$B$47 -> #DIV/0!
A62: Total Mgmt Fee/Unit | B62: =B60+B61 -> #DIV/0! | C62: =B62/$B$46 -> #DIV/0! | D62: =B62/$B$47 -> #DIV/0!
A64: Repairs/Unit | B64: =Expenses!$D$54 -> 0 | C64: =B64/$B$46 -> #DIV/0! | D64: =B64/$B$47 -> #DIV/0!
A65: Maintenance/Unit | B65: =Expenses!$D$55 -> #DIV/0! | C65: =B65/$B$46 -> #DIV/0! | D65: =B65/$B$47 -> #DIV/0!
A66: Total Repairs and Maint/Unit | B66: =B64+B65 -> #DIV/0! | C66: =B66/$B$46 -> #DIV/0! | D66: =B66/$B$47 -> #DIV/0!
A67: Replacement Reserve | B67: =Expenses!D57 -> #DIV/0! | C67: =B67/$B$46 -> #DIV/0! | D67: =B67/$B$47 -> #DIV/0!
A70: LIHTC:
D71: Per Unit | E71: Per Sq. Foot
A72: Total Qualified Basis: | B72: ='LIHTC Calculation'!D46+'LIHTC Calculation'!E46 -> 0 | D72: =B72/$B$5 -> #DIV/0! | E72: =B72/($B$7+$B$8) -> #DIV/0!
A73: Total Amount Of Credit Requested: | B73: ='LIHTC Calculation'!D52+'LIHTC Calculation'!E52 -> 0 | D73: =B73/$B$5 -> #DIV/0! | E73: =B73/($B$7+$B$8) -> #DIV/0!
A74: Total Amount of Credit Allowable: | B74: ='LIHTC Calculation'!E50+'LIHTC Calculation'!D50 -> 0 | D74: =B74/$B$5 -> #DIV/0! | E74: =B74/($B$7+$B$8) -> #DIV/0!
A75: Net Tax Credit Investor Proceeds: | B75: ='LIHTC Calculation'!D58+'LIHTC Calculation'!E58 -> 0 | D75: =B75/$B$5 -> #DIV/0! | E75: =B75/($B$7+$B$8) -> #DIV/0!
B76: Uses Page | C76: Tax Credit Calc Page | D76: Difference
A77: LIHTC Ineligible Costs | B77: ='Uses of Funds'!$C$130-'Uses of Funds'!$T$130 -> 0 | C77: ='LIHTC Calculation'!$E$27+'LIHTC Calculation'!$D$27 -> 0 | D77: =B77-C77 -> 0
A80: OAHTC:
C81: Annual Per Unit | D81: Per Unit | E81: Per Sq. Foot
A82: Annual Passthrough: | B82: ='OAHTC Calculation'!E21 -> 0 | C82: ='OAHTC Calculation'!D17 -> 0 | D82: =B82/$B$5 -> #DIV/0! | E82: =B82/($B$7+$B$8) -> #DIV/0!
A83: Actual Passthrough: | B83: ='OAHTC Calculation'!E22 -> 0 | C83: ='OAHTC Calculation'!D22 -> 0 | D83: =B83/$B$5 -> #DIV/0! | E83: =B83/($B$7+$B$8) -> #DIV/0!
A84: Over/Under: | B84: =B83-B82 -> 0 | C84: =C83-C82 -> 0 | D84: =D83-D82 -> #DIV/0! | E84: =E83-E82 -> #DIV/0!
A87: Snapshot:
A88: Construction Costs/Sq Ft: | B88: =E15 -> #DIV/0!
A89: Development Costs % of Project Costs: | B89: =C16 -> #DIV/0!
A90: Total Builder GC/O&P %: | B90: =C23 -> #DIV/0!
A91: Construction Contigency %: | B91: =C25 -> #DIV/0!
A92: Architect Fee %: | B92: =C27 -> #DIV/0!
A93: Development Contingency %: | B93: =C30 -> #DIV/0!
A94: Total Developer Fee %: | B94: =C40 -> #DIV/0!
A95: Total Cash Developers Fee %: | B95: =C42 -> #DIV/0!
A96: Cash Flow without OAHTC %: | B96: =C49 -> #DIV/0!
A97: Cash Flow with OAHTC %: | B97: =C50 -> #DIV/0!
A98: Net Op Exp/Unit: | B98: =D56 -> #DIV/0!
A99: Total Mgmt Fee/Unit: | B99: =B62 -> #DIV/0!
A100: Total Repairs and Maint/Unit: | B100: =B66 -> #DIV/0!
A101: Replacement Reserve: | B101: =B67 -> #DIV/0!

Sheet Project Summary
A1: PROJECT SUMMARY
A3: Project Name: | B3: =Sources!B3 -> 0
A5: Date: | B5: =Sources!F3 -> 40909
A6: County | B6: =Income!F5 -> 0
A8: SOURCES
A10: OHCS Grants & Equity | B10: =Sources!C15+Sources!D15+Sources!E15 -> 0
A11: OHCS Loans | B11: =Sources!C24+Sources!D24+Sources!E24 -> 0
A12: PHB Sources | B12: =Sources!C32+Sources!D32+Sources!E32 -> 0
A13: Other Loans | B13: =Sources!C40+Sources!D40+Sources!E40 -> 0
A14: Other Grants | B14: =Sources!C48+Sources!D48+Sources!E48 -> 0
A15: Applicant Contributions | B15: =Sources!C55+Sources!D55+Sources!E55 -> 0
A16: Other Funds | B16: =Sources!C61+Sources!D61+Sources!E61 -> 0
A18: TOTAL FUNDING SOURCE | B18: =B16+B15+B14+B13+B12+B11+B10 -> 0
A19: =IF(Sources!C64+Sources!D64+Sources!E64>0,Sources!A64," ")
A20: USES
A22: Acquisition | B22: ='Uses of Funds'!E25 -> 0
A23: Construction/Rehab | B23: ='Uses of Funds'!E50 -> 0
A24: Development Costs | B24: ='Uses of Funds'!E128 -> 0
A26: Total | B26: ='Uses of Funds'!E130 -> 0
A28: FIRST YEAR INCOME & EXPENSES
B30: Without OAHTC | C30: With OAHTC
A32: Rental Income | B32: =Income!N25 -> 0 | C32: ='Income with OAHTC'!N25 -> 0
A33: Other Income | B33: =Income!N40 -> 0 | C33: ='Income with OAHTC'!N44 -> 0
A34: Gross Potential Income | B34: =Income!N42 -> 0 | C34: ='Income with OAHTC'!N46 -> 0
A35: Less Vacancy | B35: =Income!N44 -> 0 | C35: ='Income with OAHTC'!N48 -> 0
A36: Effective Gross Income | B36: =Income!N42 -> 0 | C36: ='Income with OAHTC'!N50 -> 0
A37: Annual Operating Expenses | B37: =Expenses!E64 -> 0 | C37: =Expenses!E118 -> 0
A38: Net Operating Income | B38: =Expenses!E109 -> 0 | C38: =Expenses!E119 -> 0
A39: Annual Debt Service | B39: =Expenses!E110 -> 0 | C39: =Expenses!E120 -> 0
A40: Primary Debt Coverage | B40: =Expenses!E113 -> #DIV/0! | C40: =Expenses!E123 -> #DIV/0!

Sheet LIHTC Calculation
A2: CALCULATION OF TAX CREDIT
B4: Project Name: | C4: =Sources!$B$3 -> 0
B5: Date: | C5: =Sources!F3 -> 40909
A7: Tax credits are calculated on an annual basis. The total tax credit receive is equal to 10 times the annual credit
D9: Yes | E9: No
A11: Qualified Census Tract (QCT) or Difficult to Develop Area (DDA) ?
B13: Enter QCT number
B14: Enter DDA area
A17: Indicate whether your project is qualified for:
A19: 30% Net Present Value | C19: (Place X under "Yes" if applicable)
A20: 70% Net Present Value | C20: (Place X under "Yes" if applicable)
A21: Both 30% & 70% | C21: (Place X under "Yes" if applicable)
D23: 0.3 | E23: 0.7 | F23: Total
A25: Total Project Costs | C25: Use applicable column (30%, 70% or both) for data entry | D25: ='Uses of Funds'!E130 -> 0 | E25: ='Uses of Funds'!E130 -> 0
B27: Less land; amortized and other ineligible costs * | D27: ='Uses of Funds'!$E$130-'Uses of Funds'!$T$130 -> 0 | E27: ='Uses of Funds'!$E$130-'Uses of Funds'!$T$130 -> 0
A29: Eligible Basis
B31: Less portion of federal grant used to finance qualifying developments
B32: Less amounts of nonqualified nonrecourse financing
B33: Less nonqualifying costs or units of higher quality
B34: Less Section 48 Rehabilitation Tax Credit
B35: Less Historic Tax Credit (Rresidential Portion Only)
A38: Total Eligible Basis | D38: =D25-D27-D31-D32-D33-D34-D35-D36 -> 0 | E38: =E25-E27-E31-E32-E33-E34-E35-E36 -> 0
B40: (Change to 130% if high cost or qualified census tract) | D40: 1 | E40: 1
A42: Adjusted Eligible Basis | D42: =D40*D38 -> 0 | E42: =E40*E38 -> 0
B44: Multiplied by the applicable fraction | D44: 1 | E44: 1
A46: Total Qualified Basis | D46: =D42*D44 -> 0 | E46: =E42*E44 -> 0
B48: Multiplied by the applicable percentage (Month/Year used? 0/0)
A50: Total Amount Of Tax Credit Allowable | D50: =D46*D48 -> 0 | E50: =E46*E48 -> 0
A52: Total Amount Of Tax Credit Requested | F52: =D52+E52 -> 0
A54: Total Tax Credits for 10 Years | D54: =D52*10 -> 0 | E54: =E52*10 -> 0
A56: Tax Credit Yield
A58: Tax Credit Equity | D58: =D54*D56 -> 0 | E58: =E54*E56 -> 0 | F58: =D58+E58 -> 0
B60: Percentage of Limited Partnership proceeds
A62: Net Tax Credit Investor Proceeds | D62: =D58*D60 -> 0 | E62: =E58*E60 -> 0 | F62: =D62+E62 -> 0
A64: * If total ineligible costs does not equal total costs less reasonable basis from Uses of Funding form, explain here.

Sheet Income with OAHTC
A1: HOUSING OPERATING BUDGET - INCOME WITH OAHTC
B3: Project Name: | E3: =Sources!$B$3 -> 0
D4: Date: | F4: =Sources!F3 -> 40909
D5: County: | F5: =Income!F5 -> 0
A6: ANNUAL Residential Income: | I6: Annual Inflation Rate Factor: | M6: =+Income!M6 -> 0.02
A7: LIHTC Rents based on: | F7: Actual Multifamily Tax Subsidy Incomes or | N7: National Non-Metropolitan Income Limits
A8: Unit Size | B8: Unit Type | C8: # of Baths | D8: Square Feet | E8: Median Income % | F8: Gross Monthly Rent Per Unit | H8: Tenant Paid Utility Allow | J8: Net Monthly Rent Per Unit | L8: Number of Units | N8: 1 | O8: 2 | P8: 3 | Q8: 4 | R8: 5 | S8: 6 | T8: 7 | U8: 8 | V8: 9 | W8: 10 | X8: 11 | Y8: 12 | Z8: 13 | AA8: 14 | AB8: 15 | AC8: 16 | AD8: 17 | AE8: 18 | AF8: 19 | AG8: 20 | AH8: 21 | AI8: 22 | AJ8: 23 | AK8: 24 | AL8: 25 | AM8: 26 | AN8: 27 | AO8: 28 | AP8: 29 | AQ8: 30
B10: Bdr | E10: =ROUNDUP(IF(OR(A10="sro",A10=0),+F10/(VLOOKUP($F$5,Rents,26)*2),IF(A10=1,+F10/(VLOOKUP($F$5,Rents,27)*2),IF(A10=2,+F10/(VLOOKUP($F$5,Rents,28)*2),IF(A10=3,+F10/(VLOOKUP($F$5,Rents,29)*2),IF(A10=4,+F10/(VLOOKUP($F$5,Rents,30)*2),IF(A10=5,+F10/(VLOOKUP($F$5,Rents,31)*2),0)))))),3)*100 -> #N/A | G10: - | I10: = | J10: =F10-H10 -> 0 | K10: X 12 | M10: = | N10: =J10*L10*12 -> 0 | O10: =(+N10*$M$6)+N10 -> 0 | P10: =(+O10*$M$6)+O10 -> 0 | Q10: =(+P10*$M$6)+P10 -> 0 | R10: =(+Q10*$M$6)+Q10 -> 0 | S10: =(+R10*$M$6)+R10 -> 0 | T10: =(+S10*$M$6)+S10 -> 0 | U10: =(+T10*$M$6)+T10 -> 0 | V10: =(+U10*$M$6)+U10 -> 0 | ... AQ10: =(+AP10*$M$6)+AP10 -> 0
B11: Bdr | E11: =ROUNDUP(IF(OR(A11="sro",A11=0),+F11/(VLOOKUP($F$5,Rents,26)*2),IF(A11=1,+F11/(VLOOKUP($F$5,Rents,27)*2),IF(A11=2,+F11/(VLOOKUP($F$5,Rents,28)*2),IF(A11=3,+F11/(VLOOKUP($F$5,Rents,29)*2),IF(A11=4,+F11/(VLOOKUP($F$5,Rents,30)*2),IF(A11=5,+F11/(VLOOKUP($F$5,Rents,31)*2),0)))))),3)*100 -> #N/A | G11: - | I11: = | J11: =F11-H11 -> 0 | K11: X 12 | M11: = | N11: =J11*L11*12 -> 0 | O11: =(+N11*$M$6)+N11 -> 0 | P11: =(+O11*$M$6)+O11 -> 0 | Q11: =(+P11*$M$6)+P11 -> 0 | R11: =(+Q11*$M$6)+Q11 -> 0 | S11: =(+R11*$M$6)+R11 -> 0 | T11: =(+S11*$M$6)+S11 -> 0 | U11: =(+T11*$M$6)+T11 -> 0 | V11: =(+U11*$M$6)+U11 -> 0 | ... AQ11: =(+AP11*$M$6)+AP11 -> 0
B12: Bdr | E12: =ROUNDUP(IF(OR(A12="sro",A12=0),+F12/(VLOOKUP($F$5,Rents,26)*2),IF(A12=1,+F12/(VLOOKUP($F$5,Rents,27)*2),IF(A12=2,+F12/(VLOOKUP($F$5,Rents,28)*2),IF(A12=3,+F12/(VLOOKUP($F$5,Rents,29)*2),IF(A12=4,+F12/(VLOOKUP($F$5,Rents,30)*2),IF(A12=5,+F12/(VLOOKUP($F$5,Rents,31)*2),0)))))),3)*100 -> #N/A | G12: - | I12: = | J12: =F12-H12 -> 0 | K12: X 12 | M12: = | N12: =J12*L12*12 -> 0 | O12: =(+N12*$M$6)+N12 -> 0 | P12: =(+O12*$M$6)+O12 -> 0 | Q12: =(+P12*$M$6)+P12 -> 0 | R12: =(+Q12*$M$6)+Q12 -> 0 | S12: =(+R12*$M$6)+R12 -> 0 | T12: =(+S12*$M$6)+S12 -> 0 | U12: =(+T12*$M$6)+T12 -> 0 | V12: =(+U12*$M$6)+U12 -> 0 | ... AQ12: =(+AP12*$M$6)+AP12 -> 0
B13: Bdr | E13: =ROUNDUP(IF(OR(A13="sro",A13=0),+F13/(VLOOKUP($F$5,Rents,26)*2),IF(A13=1,+F13/(VLOOKUP($F$5,Rents,27)*2),IF(A13=2,+F13/(VLOOKUP($F$5,Rents,28)*2),IF(A13=3,+F13/(VLOOKUP($F$5,Rents,29)*2),IF(A13=4,+F13/(VLOOKUP($F$5,Rents,30)*2),IF(A13=5,+F13/(VLOOKUP($F$5,Rents,31)*2),0)))))),3)*100 -> #N/A | G13: - | I13: = | J13: =F13-H13 -> 0 | K13: X 12 | M13: = | N13: =J13*L13*12 -> 0 | O13: =(+N13*$M$6)+N13 -> 0 | P13: =(+O13*$M$6)+O13 -> 0 | Q13: =(+P13*$M$6)+P13 -> 0 | R13: =(+Q13*$M$6)+Q13 -> 0 | S13: =(+R13*$M$6)+R13 -> 0 | T13: =(+S13*$M$6)+S13 -> 0 | U13: =(+T13*$M$6)+T13 -> 0 | V13: =(+U13*$M$6)+U13 -> 0 | ... AQ13: =(+AP13*$M$6)+AP13 -> 0
B14: Bdr | E14: =ROUNDUP(IF(OR(A14="sro",A14=0),+F14/(VLOOKUP($F$5,Rents,26)*2),IF(A14=1,+F14/(VLOOKUP($F$5,Rents,27)*2),IF(A14=2,+F14/(VLOOKUP($F$5,Rents,28)*2),IF(A14=3,+F14/(VLOOKUP($F$5,Rents,29)*2),IF(A14=4,+F14/(VLOOKUP($F$5,Rents,30)*2),IF(A14=5,+F14/(VLOOKUP($F$5,Rents,31)*2),0)))))),3)*100 -> #N/A | G14: - | I14: = | J14: =F14-H14 -> 0 | K14: X 12 | M14: = | N14: =J14*L14*12 -> 0 | O14: =(+N14*$M$6)+N14 -> 0 | P14: =(+O14*$M$6)+O14 -> 0 | Q14: =(+P14*$M$6)+P14 -> 0 | R14: =(+Q14*$M$6)+Q14 -> 0 | S14: =(+R14*$M$6)+R14 -> 0 | T14: =(+S14*$M$6)+S14 -> 0 | U14: =(+T14*$M$6)+T14 -> 0 | V14: =(+U14*$M$6)+U14 -> 0 | ... AQ14: =(+AP14*$M$6)+AP14 -> 0
B15: Bdr | E15: =ROUNDUP(IF(OR(A15="sro",A15=0),+F15/(VLOOKUP($F$5,Rents,26)*2),IF(A15=1,+F15/(VLOOKUP($F$5,Rents,27)*2),IF(A15=2,+F15/(VLOOKUP($F$5,Rents,28)*2),IF(A15=3,+F15/(VLOOKUP($F$5,Rents,29)*2),IF(A15=4,+F15/(VLOOKUP($F$5,Rents,30)*2),IF(A15=5,+F15/(VLOOKUP($F$5,Rents,31)*2),0)))))),3)*100 -> #N/A | G15: - | I15: = | J15: =F15-H15 -> 0 | K15: X 12 | M15: = | N15: =J15*L15*12 -> 0 | O15: =(+N15*$M$6)+N15 -> 0 | P15: =(+O15*$M$6)+O15 -> 0 | Q15: =(+P15*$M$6)+P15 -> 0 | R15: =(+Q15*$M$6)+Q15 -> 0 | S15: =(+R15*$M$6)+R15 -> 0 | T15: =(+S15*$M$6)+S15 -> 0 | U15: =(+T15*$M$6)+T15 -> 0 | V15: =(+U15*$M$6)+U15 -> 0 | ... AQ15: =(+AP15*$M$6)+AP15 -> 0
B16: Bdr | E16: =ROUNDUP(IF(OR(A16="sro",A16=0),+F16/(VLOOKUP($F$5,Rents,26)*2),IF(A16=1,+F16/(VLOOKUP($F$5,Rents,27)*2),IF(A16=2,+F16/(VLOOKUP($F$5,Rents,28)*2),IF(A16=3,+F16/(VLOOKUP($F$5,Rents,29)*2),IF(A16=4,+F16/(VLOOKUP($F$5,Rents,30)*2),IF(A16=5,+F16/(VLOOKUP($F$5,Rents,31)*2),0)))))),3)*100 -> #N/A | G16: - | I16: = | J16: =F16-H16 -> 0 | K16: X 12 | M16: = | N16: =J16*L16*12 -> 0 | O16: =(+N16*$M$6)+N16 -> 0 | P16: =(+O16*$M$6)+O16 -> 0 | Q16: =(+P16*$M$6)+P16 -> 0 | R16: =(+Q16*$M$6)+Q16 -> 0 | S16: =(+R16*$M$6)+R16 -> 0 | T16: =(+S16*$M$6)+S16 -> 0 | U16: =(+T16*$M$6)+T16 -> 0 | V16: =(+U16*$M$6)+U16 -> 0 | ... AQ16: =(+AP16*$M$6)+AP16 -> 0
B17: Bdr | E17: =ROUNDUP(IF(OR(A17="sro",A17=0),+F17/(VLOOKUP($F$5,Rents,26)*2),IF(A17=1,+F17/(VLOOKUP($F$5,Rents,27)*2),IF(A17=2,+F17/(VLOOKUP($F$5,Rents,28)*2),IF(A17=3,+F17/(VLOOKUP($F$5,Rents,29)*2),IF(A17=4,+F17/(VLOOKUP($F$5,Rents,30)*2),IF(A17=5,+F17/(VLOOKUP($F$5,Rents,31)*2),0)))))),3)*100 -> #N/A | G17: - | I17: = | J17: =F17-H17 -> 0 | K17: X 12 | M17: = | N17: =J17*L17*12 -> 0 | O17: =(+N17*$M$6)+N17 -> 0 | P17: =(+O17*$M$6)+O17 -> 0 | Q17: =(+P17*$M$6)+P17 -> 0 | R17: =(+Q17*$M$6)+Q17 -> 0 | S17: =(+R17*$M$6)+R17 -> 0 | T17: =(+S17*$M$6)+S17 -> 0 | U17: =(+T17*$M$6)+T17 -> 0 | V17: =(+U17*$M$6)+U17 -> 0 | ... AQ17: =(+AP17*$M$6)+AP17 -> 0
B18: Bdr | E18: =ROUNDUP(IF(OR(A18="sro",A18=0),+F18/(VLOOKUP($F$5,Rents,26)*2),IF(A18=1,+F18/(VLOOKUP($F$5,Rents,27)*2),IF(A18=2,+F18/(VLOOKUP($F$5,Rents,28)*2),IF(A18=3,+F18/(VLOOKUP($F$5,Rents,29)*2),IF(A18=4,+F18/(VLOOKUP($F$5,Rents,30)*2),IF(A18=5,+F18/(VLOOKUP($F$5,Rents,31)*2),0)))))),3)*100 -> #N/A | G18: - | I18: = | J18: =F18-H18 -> 0 | K18: X 12 | M18: = | N18: =J18*L18*12 -> 0 | O18: =(+N18*$M$6)+N18 -> 0 | P18: =(+O18*$M$6)+O18 -> 0 | Q18: =(+P18*$M$6)+P18 -> 0 | R18: =(+Q18*$M$6)+Q18 -> 0 | S18: =(+R18*$M$6)+R18 -> 0 | T18: =(+S18*$M$6)+S18 -> 0 | U18: =(+T18*$M$6)+T18 -> 0 | V18: =(+U18*$M$6)+U18 -> 0 | ... AQ18: =(+AP18*$M$6)+AP18 -> 0
B19: Bdr | E19: =ROUNDUP(IF(OR(A19="sro",A19=0),+F19/(VLOOKUP($F$5,Rents,26)*2),IF(A19=1,+F19/(VLOOKUP($F$5,Rents,27)*2),IF(A19=2,+F19/(VLOOKUP($F$5,Rents,28)*2),IF(A19=3,+F19/(VLOOKUP($F$5,Rents,29)*2),IF(A19=4,+F19/(VLOOKUP($F$5,Rents,30)*2),IF(A19=5,+F19/(VLOOKUP($F$5,Rents,31)*2),0)))))),3)*100 -> #N/A | G19: - | I19: = | J19: =F19-H19 -> 0 | K19: X 12 | M19: = | N19: =J19*L19*12 -> 0 | O19: =(+N19*$M$6)+N19 -> 0 | P19: =(+O19*$M$6)+O19 -> 0 | Q19: =(+P19*$M$6)+P19 -> 0 | R19: =(+Q19*$M$6)+Q19 -> 0 | S19: =(+R19*$M$6)+R19 -> 0 | T19: =(+S19*$M$6)+S19 -> 0 | U19: =(+T19*$M$6)+T19 -> 0 | V19: =(+U19*$M$6)+U19 -> 0 | ... AQ19: =(+AP19*$M$6)+AP19 -> 0
B20: Bdr | E20: =ROUNDUP(IF(OR(A20="sro",A20=0),+F20/(VLOOKUP($F$5,Rents,26)*2),IF(A20=1,+F20/(VLOOKUP($F$5,Rents,27)*2),IF(A20=2,+F20/(VLOOKUP($F$5,Rents,28)*2),IF(A20=3,+F20/(VLOOKUP($F$5,Rents,29)*2),IF(A20=4,+F20/(VLOOKUP($F$5,Rents,30)*2),IF(A20=5,+F20/(VLOOKUP($F$5,Rents,31)*2),0)))))),3)*100 -> #N/A | G20: - | I20: = | J20: =F20-H20 -> 0 | K20: X 12 | M20: = | N20: =J20*L20*12 -> 0 | O20: =(+N20*$M$6)+N20 -> 0 | P20: =(+O20*$M$6)+O20 -> 0 | Q20: =(+P20*$M$6)+P20 -> 0 | R20: =(+Q20*$M$6)+Q20 -> 0 | S20: =(+R20*$M$6)+R20 -> 0 | T20: =(+S20*$M$6)+S20 -> 0 | U20: =(+T20*$M$6)+T20 -> 0 | V20: =(+U20*$M$6)+U20 -> 0 | ... AQ20: =(+AP20*$M$6)+AP20 -> 0
B21: Bdr | E21: =ROUNDUP(IF(OR(A21="sro",A21=0),+F21/(VLOOKUP($F$5,Rents,26)*2),IF(A21=1,+F21/(VLOOKUP($F$5,Rents,27)*2),IF(A21=2,+F21/(VLOOKUP($F$5,Rents,28)*2),IF(A21=3,+F21/(VLOOKUP($F$5,Rents,29)*2),IF(A21=4,+F21/(VLOOKUP($F$5,Rents,30)*2),IF(A21=5,+F21/(VLOOKUP($F$5,Rents,31)*2),0)))))),3)*100 -> #N/A | G21: - | I21: = | J21: =F21-H21 -> 0 | K21: X 12 | M21: = | N21: =J21*L21*12 -> 0 | O21: =(+N21*$M$6)+N21 -> 0 | P21: =(+O21*$M$6)+O21 -> 0 | Q21: =(+P21*$M$6)+P21 -> 0 | R21: =(+Q21*$M$6)+Q21 -> 0 | S21: =(+R21*$M$6)+R21 -> 0 | T21: =(+S21*$M$6)+S21 -> 0 | U21: =(+T21*$M$6)+T21 -> 0 | V21: =(+U21*$M$6)+U21 -> 0 | ... AQ21: =(+AP21*$M$6)+AP21 -> 0
... B23: Bdr | E23: =ROUNDUP(IF(OR(A23="sro",A23=0),+F23/(VLOOKUP($F$5,Rents,26)*2),IF(A23=1,+F23/(VLOOKUP($F$5,Rents,27)*2),IF(A23=2,+F23/(VLOOKUP($F$5,Rents,28)*2),IF(A23=3,+F23/(VLOOKUP($F$5,Rents,29)*2),IF(A23=4,+F23/(VLOOKUP($F$5,Rents,30)*2),IF(A23=5,+F23/(VLOOKUP($F$5,Rents,31)*2),0)))))),3)*100 -> #N/A | G23: - | I23: = | J23: =F23-H23 -> 0 | K23: X 12 | M23: = | N23: =J23*L23*12 -> 0 | O23: =(+N23*$M$6)+N23 -> 0 | P23: =(+O23*$M$6)+O23 -> 0 | Q23: =(+P23*$M$6)+P23 -> 0 | R23: =(+Q23*$M$6)+Q23 -> 0 | S23: =(+R23*$M$6)+R23 -> 0 | T23: =(+S23*$M$6)+S23 -> 0 | U23: =(+T23*$M$6)+T23 -> 0 | V23: =(+U23*$M$6)+U23 -> 0 | ... AQ23: =(+AP23*$M$6)+AP23 -> 0
A25: SUB-TOTALS | L25: =SUM(L10:L24) -> 0 | M25: = | N25: =SUM(N10:N24) -> 0 | O25: =SUM(O10:O24) -> 0 | P25: =SUM(P10:P24) -> 0 | Q25: =SUM(Q10:Q24) -> 0 | R25: =SUM(R10:R24) -> 0 | S25: =SUM(S10:S24) -> 0 | T25: =SUM(T10:T24) -> 0 | U25: =SUM(U10:U24) -> 0 | ... AQ25: =SUM(AQ10:AQ24) -> 0
A27: Service Revenue: | N27: Total Annual Income
A29: Medicaid-Resident Services (Averaged) | O29: =(+N29*$M$6)+N29 -> 0 | P29: =(+O29*$M$6)+O29 -> 0 | Q29: =(+P29*$M$6)+P29 -> 0 | R29: =(+Q29*$M$6)+Q29 -> 0 | S29: =(+R29*$M$6)+R29 -> 0 | T29: =(+S29*$M$6)+S29 -> 0 | U29: =(+T29*$M$6)+T29 -> 0 | V29: =(+U29*$M$6)+U29 -> 0 | ... AQ29: =(+AP29*$M$6)+AP29 -> 0
A30: Private-Resident Services (Averaged) | O30: =(+N30*$M$6)+N30 -> 0 | P30: =(+O30*$M$6)+O30 -> 0 | Q30: =(+P30*$M$6)+P30 -> 0 | R30: =(+Q30*$M$6)+Q30 -> 0 | S30: =(+R30*$M$6)+R30 -> 0 | T30: =(+S30*$M$6)+S30 -> 0 | U30: =(+T30*$M$6)+T30 -> 0 | V30: =(+U30*$M$6)+U30 -> 0 | ... AQ30: =(+AP30*$M$6)+AP30 -> 0
A31: Other: | O31: =(+N31*$M$6)+N31 -> 0 | P31: =(+O31*$M$6)+O31 -> 0 | Q31: =(+P31*$M$6)+P31 -> 0 | R31: =(+Q31*$M$6)+Q31 -> 0 | S31: =(+R31*$M$6)+R31 -> 0 | T31: =(+S31*$M$6)+S31 -> 0 | U31: =(+T31*$M$6)+T31 -> 0 | V31: =(+U31*$M$6)+U31 -> 0 | ... AQ31: =(+AP31*$M$6)+AP31 -> 0
A32: Other: | O32: =(+N32*$M$6)+N32 -> 0 | P32: =(+O32*$M$6)+O32 -> 0 | Q32: =(+P32*$M$6)+P32 -> 0 | R32: =(+Q32*$M$6)+Q32 -> 0 | S32: =(+R32*$M$6)+R32 -> 0 | T32: =(+S32*$M$6)+S32 -> 0 | U32: =(+T32*$M$6)+T32 -> 0 | V32: =(+U32*$M$6)+U32 -> 0 | ... AQ32: =(+AP32*$M$6)+AP32 -> 0
A34: Other Revenue:
A36: Laundry | O36: =(+N36*$M$6)+N36 -> 0 | P36: =(+O36*$M$6)+O36 -> 0 | Q36: =(+P36*$M$6)+P36 -> 0 | R36: =(+Q36*$M$6)+Q36 -> 0 | S36: =(+R36*$M$6)+R36 -> 0 | T36: =(+S36*$M$6)+S36 -> 0 | U36: =(+T36*$M$6)+T36 -> 0 | V36: =(+U36*$M$6)+U36 -> 0 | ... AQ36: =(+AP36*$M$6)+AP36 -> 0
A37: Parking | O37: =(+N37*$M$6)+N37 -> 0 | P37: =(+O37*$M$6)+O37 -> 0 | Q37: =(+P37*$M$6)+P37 -> 0 | R37: =(+Q37*$M$6)+Q37 -> 0 | S37: =(+R37*$M$6)+R37 -> 0 | T37: =(+S37*$M$6)+S37 -> 0 | U37: =(+T37*$M$6)+T37 -> 0 | V37: =(+U37*$M$6)+U37 -> 0 | ... AQ37: =(+AP37*$M$6)+AP37 -> 0
A38: Utility Reimbursements | O38: =(+N38*$M$6)+N38 -> 0 | P38: =(+O38*$M$6)+O38 -> 0 | Q38: =(+P38*$M$6)+P38 -> 0 | R38: =(+Q38*$M$6)+Q38 -> 0 | S38: =(+R38*$M$6)+R38 -> 0 | T38: =(+S38*$M$6)+S38 -> 0 | U38: =(+T38*$M$6)+T38 -> 0 | V38: =(+U38*$M$6)+U38 -> 0 | ... AQ38: =(+AP38*$M$6)+AP38 -> 0
A39: Miscellaneous Fees | O39: =(+N39*$M$6)+N39 -> 0 | P39: =(+O39*$M$6)+O39 -> 0 | Q39: =(+P39*$M$6)+P39 -> 0 | R39: =(+Q39*$M$6)+Q39 -> 0 | S39: =(+R39*$M$6)+R39 -> 0 | T39: =(+S39*$M$6)+S39 -> 0 | U39: =(+T39*$M$6)+T39 -> 0 | V39: =(+U39*$M$6)+U39 -> 0 | ... AQ39: =(+AP39*$M$6)+AP39 -> 0
A40: Service Income | O40: =(+N40*$M$6)+N40 -> 0 | P40: =(+O40*$M$6)+O40 -> 0 | Q40: =(+P40*$M$6)+P40 -> 0 | R40: =(+Q40*$M$6)+Q40 -> 0 | S40: =(+R40*$M$6)+R40 -> 0 | T40: =(+S40*$M$6)+S40 -> 0 | U40: =(+T40*$M$6)+T40 -> 0 | V40: =(+U40*$M$6)+U40 -> 0 | ... AQ40: =(+AP40*$M$6)+AP40 -> 0
A41: Other Income | O41: =(+N41*$M$6)+N41 -> 0 | P41: =(+O41*$M$6)+O41 -> 0 | Q41: =(+P41*$M$6)+P41 -> 0 | R41: =(+Q41*$M$6)+Q41 -> 0 | S41: =(+R41*$M$6)+R41 -> 0 | T41: =(+S41*$M$6)+S41 -> 0 | U41: =(+T41*$M$6)+T41 -> 0 | V41: =(+U41*$M$6)+U41 -> 0 | ... AQ41: =(+AP41*$M$6)+AP41 -> 0
A44: SUB-TOTAL OTHER REVENUE | N44: =SUM(N29:N43) -> 0 | O44: =SUM(O29:O43) -> 0 | P44: =SUM(P29:P43) -> 0 | Q44: =SUM(Q29:Q43) -> 0 | R44: =SUM(R29:R43) -> 0 | S44: =SUM(S29:S43) -> 0 | T44: =SUM(T29:T43) -> 0 | U44: =SUM(U29:U43) -> 0 | ... AQ44: =SUM(AQ29:AQ43) -> 0
A46: Gross Income: | N46: =N25+N44 -> 0 | O46: =O25+O44 -> 0 | P46: =P25+P44 -> 0 | Q46: =Q25+Q44 -> 0 | R46: =R25+R44 -> 0 | S46: =S25+S44 -> 0 | T46: =T25+T44 -> 0 | U46: =U25+U44 -> 0 | ... AQ46: =AQ25+AQ44 -> 0
A48: Less Vacancy Rate | E48: 0.05 | N48: =-N46*$E$48 -> 0 | O48: =-O46*$E$48 -> 0 | P48: =-P46*$E$48 -> 0 | Q48: =-Q46*$E$48 -> 0 | R48: =-R46*$E$48 -> 0 | S48: =-S46*$E$48 -> 0 | T48: =-T46*$E$48 -> 0 | U48: =-U46*$E$48 -> 0 | ... AQ48: =-AQ46*$E$48 -> 0
A50: Effective Gross Income: | N50: =N46+N48 -> 0 | O50: =O46+O48 -> 0 | P50: =P46+P48 -> 0 | Q50: =Q46+Q48 -> 0 | R50: =R46+R48 -> 0 | S50: =S46+S48 -> 0 | T50: =T46+T48 -> 0 | U50: =U46+U48 -> 0 | ... AQ50: =AQ46+AQ48 -> 0
A52: Note: Projects that provide care services (e.g., Assisted Living Facilities) need to delineate the service levels and
A53: anticipated revenue as well as the basic monthly rents on a separate page.

Sheet OAHTC Calculation
A1: PAYMENTS COMPUTED ANNUALLY
A2: OAHTC RENT REDUCTION CALCULATION
A4: Project Name: | B4: =Sources!$B$3 -> 0
A5: Date: | B5: =Sources!F3 -> 40909
D7: WITH OAHTC | F7: W/O OAHTC
A9: LOAN AMOUNT: | D9: =F9 -> 0
A10: INTEREST RATE: | D10: =F10-D14 -> -0.04
A11: NUMBER OF YEARS TO AMORTIZE: | D11: =F11 -> 1 | F11: 1
A12: NUMBER OF YEARS TAX CREDITS TAKEN: | D12: =F12 -> 1 | F12: 1
A13: MONTHLY PAYMENT AMOUNT: | D13: =PMT(D10/12,12*D11,-D9) -> 0 | F13: =PMT(F10/12,12*F11,-F9) -> 0
A14: INTEREST RATE REDUCTION: | D14: 0.04
A15: TOTAL TAX CREDIT ALLOWED: | D15: =SUM(I32:I32:I51) -> 0
A16: NUMBER OF UNITS: | D16: 1
A17: RENT REDUCTION UNIT/MONTH: | D17: =ROUNDUP(((+D15/D16)/D12)/12,0) -> 0
A18: ANNUAL RENT PASS THROUGH: | D18: =D17*12*D16 -> 0
A21: Required OAHTC Annual Pass Through | D21: ='OAHTC Calculation'!D17 -> 0 | E21: ='OAHTC Calculation'!$D$18 -> 0
A22: Actual OAHTC Annual Pass Through | D22: =ROUNDUP(((+Income!$N$25-'Income with OAHTC'!$N$25)/12)/$D$16,0) -> 0 | E22: =Income!N25-'Income with OAHTC'!N25 -> 0
A23: Amount over/under required pass through | D23: =D22-D21 -> 0 | E23: =+E22-E21 -> 0
B26: LOAN AMORTIZATION | E26: MAXIMUM ANNUAL TAX CREDIT
D28: ENDING | F28: PRINCIPAL | G28: AVERAGE | H28: AVERAGE | I28: TAX
A29: YEAR | B29: INTEREST | C29: PRINCIPAL | D29: BALANCE | E29: =A29 -> YEAR | F29: REDUCTION | G29: INTEREST | H29: BALANCE | I29: CREDIT
C31: =IF(A31>=1,-PPMT(Sources!$D$9/12,A31*12,Sources!#REF!*12,Sources!$D$7)*12,"")
A32: 1 | B32: =IF(A32>=1,-IPMT($D$10/12,A32*12,$D$11*12,$D$9,0,0)*12,"") -> 0 | C32: =IF(A32>=1,-PPMT($D$10/12,A32*12,$D$11*12,$D$9,0,0)*12,"") -> 0 | D32: =IF(A32>=1,+D9-C32,"") -> 0 | E32: =A32 -> 1 | F32: =IF(A32>=1,+$D$9-D32,"") -> 0 | G32: =IF(A32>=1,+$D$13*12-F32,"") -> 0 | H32: =IF(A32>=1,+G32/$D$10,"") -> 0 | I32: =IF(A32>=1,+H32*$D$14,"") -> 0
A33: =IF($D$12>A32,IF(A32>0,A32+1,0),0) -> 0 | B33: =IF(A33>=1,-IPMT($D$10/12,A33*12,$D$11*12,$D$9,0,0)*12,"") | C33: =IF(A33>=1,-PPMT($D$10/12,A33*12,$D$11*12,$D$9,0,0)*12,"") | D33: =IF(A33>=1,+D32-C33,"") | E33: =A33 -> 0 | F33: =IF(A33>=1,+D32-D33,"") | G33: =IF(A33>=1,+$D$13*12-F33,"") | H33: =IF(A33>=1,+G33/$D$10,"") | I33: =IF(A33>=1,+H33*$D$14,"")
A34: =IF($D$12>A33,IF(A33>0,A33+1,0),0) -> 0 | B34: =IF(A34>=1,-IPMT($D$10/12,A34*12,$D$11*12,$D$9,0,0)*12,"") | C34: =IF(A34>=1,-PPMT($D$10/12,A34*12,$D$11*12,$D$9,0,0)*12,"") | D34: =IF(A34>=1,+D33-C34,"") | E34: =A34 -> 0 | F34: =IF(A34>=1,+D33-D34,"") | G34: =IF(A34>=1,+$D$13*12-F34,"") | H34: =IF(A34>=1,+G34/$D$10,"") | I34: =IF(A34>=1,+H34*$D$14,"")
A35: =IF($D$12>A34,IF(A34>0,A34+1,0),0) -> 0 | B35: =IF(A35>=1,-IPMT($D$10/12,A35*12,$D$11*12,$D$9,0,0)*12,"") | C35: =IF(A35>=1,-PPMT($D$10/12,A35*12,$D$11*12,$D$9,0,0)*12,"") | D35: =IF(A35>=1,+D34-C35,"") | E35: =A35 -> 0 | F35: =IF(A35>=1,+D34-D35,"") | G35: =IF(A35>=1,+$D$13*12-F35,"") | H35: =IF(A35>=1,+G35/$D$10,"") | I35: =IF(A35>=1,+H35*$D$14,"")
A36: =IF($D$12>A35,IF(A35>0,A35+1,0),0) -> 0 | B36: =IF(A36>=1,-IPMT($D$10/12,A36*12,$D$11*12,$D$9,0,0)*12,"") | C36: =IF(A36>=1,-PPMT($D$10/12,A36*12,$D$11*12,$D$9,0,0)*12,"") | D36: =IF(A36>=1,+D35-C36,"") | E36: =A36 -> 0 | F36: =IF(A36>=1,+D35-D36,"") | G36: =IF(A36>=1,+$D$13*12-F36,"") | H36: =IF(A36>=1,+G36/$D$10,"") | I36: =IF(A36>=1,+H36*$D$14,"")
A37: =IF($D$12>A36,IF(A36>0,A36+1,0),0) -> 0 | B37: =IF(A37>=1,-IPMT($D$10/12,A37*12,$D$11*12,$D$9,0,0)*12,"") | C37: =IF(A37>=1,-PPMT($D$10/12,A37*12,$D$11*12,$D$9,0,0)*12,"") | D37: =IF(A37>=1,+D36-C37,"") | E37: =A37 -> 0 | F37: =IF(A37>=1,+D36-D37,"") | G37: =IF(A37>=1,+$D$13*12-F37,"") | H37: =IF(A37>=1,+G37/$D$10,"") | I37: =IF(A37>=1,+H37*$D$14,"")
A38: =IF($D$12>A37,IF(A37>0,A37+1,0),0) -> 0 | B38: =IF(A38>=1,-IPMT($D$10/12,A38*12,$D$11*12,$D$9,0,0)*12,"") | C38: =IF(A38>=1,-PPMT($D$10/12,A38*12,$D$11*12,$D$9,0,0)*12,"") | D38: =IF(A38>=1,+D37-C38,"") | E38: =A38 -> 0 | F38: =IF(A38>=1,+D37-D38,"") | G38: =IF(A38>=1,+$D$13*12-F38,"") | H38: =IF(A38>=1,+G38/$D$10,"") | I38: =IF(A38>=1,+H38*$D$14,"")
A39: =IF($D$12>A38,IF(A38>0,A38+1,0),0) -> 0 | B39: =IF(A39>=1,-IPMT($D$10/12,A39*12,$D$11*12,$D$9,0,0)*12,"") | C39: =IF(A39>=1,-PPMT($D$10/12,A39*12,$D$11*12,$D$9,0,0)*12,"") | D39: =IF(A39>=1,+D38-C39,"") | E39: =A39 -> 0 | F39: =IF(A39>=1,+D38-D39,"") | G39: =IF(A39>=1,+$D$13*12-F39,"") | H39: =IF(A39>=1,+G39/$D$10,"") | I39: =IF(A39>=1,+H39*$D$14,"")
A40: =IF($D$12>A39,IF(A39>0,A39+1,0),0) -> 0 | B40: =IF(A40>=1,-IPMT($D$10/12,A40*12,$D$11*12,$D$9,0,0)*12,"") | C40: =IF(A40>=1,-PPMT($D$10/12,A40*12,$D$11*12,$D$9,0,0)*12,"") | D40: =IF(A40>=1,+D39-C40,"") | E40: =A40 -> 0 | F40: =IF(A40>=1,+D39-D40,"") | G40: =IF(A40>=1,+$D$13*12-F40,"") | H40: =IF(A40>=1,+G40/$D$10,"") | I40: =IF(A40>=1,+H40*$D$14,"")
A41: =IF($D$12>A40,IF(A40>0,A40+1,0),0) -> 0 | B41: =IF(A41>=1,-IPMT($D$10/12,A41*12,$D$11*12,$D$9,0,0)*12,"") | C41: =IF(A41>=1,-PPMT($D$10/12,A41*12,$D$11*12,$D$9,0,0)*12,"") | D41: =IF(A41>=1,+D40-C41,"") | E41: =A41 -> 0 | F41: =IF(A41>=1,+D40-D41,"") | G41: =IF(A41>=1,+$D$13*12-F41,"") | H41: =IF(A41>=1,+G41/$D$10,"") | I41: =IF(A41>=1,+H41*$D$14,"")
A42: =IF($D$12>A41,IF(A41>0,A41+1,0),0) -> 0 | B42: =IF(A42>=1,-IPMT($D$10/12,A42*12,$D$11*12,$D$9,0,0)*12,"") | C42: =IF(A42>=1,-PPMT($D$10/12,A42*12,$D$11*12,$D$9,0,0)*12,"") | D42: =IF(A42>=1,+D41-C42,"") | E42: =A42 -> 0 | F42: =IF(A42>=1,+D41-D42,"") | G42: =IF(A42>=1,+$D$13*12-F42,"") | H42: =IF(A42>=1,+G42/$D$10,"") | I42: =IF(A42>=1,+H42*$D$14,"")
A43: =IF($D$12>A42,IF(A42>0,A42+1,0),0) -> 0 | B43: =IF(A43>=1,-IPMT($D$10/12,A43*12,$D$11*12,$D$9,0,0)*12,"") | C43: =IF(A43>=1,-PPMT($D$10/12,A43*12,$D$11*12,$D$9,0,0)*12,"") | D43: =IF(A43>=1,+D42-C43,"") | E43: =A43 -> 0 | F43: =IF(A43>=1,+D42-D43,"") | G43: =IF(A43>=1,+$D$13*12-F43,"") | H43: =IF(A43>=1,+G43/$D$10,"") | I43: =IF(A43>=1,+H43*$D$14,"")
A44: =IF($D$12>A43,IF(A43>0,A43+1,0),0) -> 0 | B44: =IF(A44>=1,-IPMT($D$10/12,A44*12,$D$11*12,$D$9,0,0)*12,"") | C44: =IF(A44>=1,-PPMT($D$10/12,A44*12,$D$11*12,$D$9,0,0)*12,"") | D44: =IF(A44>=1,+D43-C44,"") | E44: =A44 -> 0 | F44: =IF(A44>=1,+D43-D44,"") | G44: =IF(A44>=1,+$D$13*12-F44,"") | H44: =IF(A44>=1,+G44/$D$10,"") | I44: =IF(A44>=1,+H44*$D$14,"")
... A51: =IF($D$12>A50,IF(A50>0,A50+1,0),0) -> 0 | B51: =IF(A51>=1,-IPMT($D$10/12,A51*12,$D$11*12,$D$9,0,0)*12,"") | C51: =IF(A51>=1,-PPMT($D$10/12,A51*12,$D$11*12,$D$9,0,0)*12,"") | D51: =IF(A51>=1,+D50-C51,"") | E51: =A51 -> 0 | F51: =IF(A51>=1,+D50-D51,"") | G51: =IF(A51>=1,+$D$13*12-F51,"") | H51: =IF(A51>=1,+G51/$D$10,"") | I51: =IF(A51>=1,+H51*$D$14,"")
D86: =IF(B86>=1,-PPMT($D$10/12,B86*12,$D$11*12,$D$9)*12,"")
D87: =IF(B87>=1,-PPMT($D$10/12,B87*12,$D$11*12,$D$9)*12,"")
D88: =IF(B88>=1,-PPMT($D$10/12,B88*12,$D$11*12,$D$9)*12,"")
D89: =IF(B89>=1,-PPMT($D$10/12,B89*12,$D$11*12,$D$9)*12,"")

Sheet LIHTCRents 12
A1: OREGON HOUSING AND COMMUNITY SERVICES
A2: 2012 RENTS FOR LIHTC & BOND FINANCING
B4: Low-income rents by county or MSA as of December 1, 2011
B5: Based on HUD's published Multifamily Tax Subsidy Income Limits
B6: Using 1 person for 0 bedroom and 1.5 persons per bedroom for 1-4 bedroom units
B7: Deduct utility allowances from these rents to get gross allowable rents
B8: Consult tax advisor to assure your management plan's compliance with program
B9: Income limits by county (or non-PMSA average if greater)
B10: Affordable rents are defined as 30% of income, including tenant paid utilities
B12: If your project is located in a rural area as defined by USDA RHS*, you qualify to use national non-metropolitan income limits, available at OHCS website**.
B13: *USDA RHS: | C13: http://eligibility.sc.egov.usda.gov/eligibility/welcomeAction.do?pageAction=sfp&NavKey=property@12
B14: **OHCS: | C14: http://www.ohcs.oregon.gov/OHCS/HPM_income_rent_limits_2012.shtml
B16: 30% MEDIAN INCOME RENTS | H16: 35% MEDIAN INCOME RENTS | N16: 40% MEDIAN INCOME RENTS | T16: 45% MEDIAN INCOME RENTS | Z16: 50% MEDIAN INCOME RENTS | AF16: 55% MEDIAN INCOME RENTS | AL16: 60% MEDIAN INCOME RENTS
A17: COUNTY | B17: 0 BDR | C17: 1 BDR | D17: 2 BDR | E17: 3 BDR | F17: 4 BDR | G17: 5 BDR | H17: 0 BDR | I17: 1 BDR | J17: 2 BDR | K17: 3 BDR | L17: 4 BDR | M17: 5 BDR | N17: 0 BDR | O17: 1 BDR | P17: 2 BDR | Q17: 3 BDR | R17: 4 BDR | S17: 5 BDR | T17: 0 BDR | U17: 1 BDR | V17: 2 BDR | W17: 3 BDR | X17: 4 BDR | Y17: 5 BDR | Z17: 0 BDR | AA17: 1 BDR | AB17: 2 BDR | AC17: 3 BDR | AD17: 4 BDR | AE17: 5 BDR | AF17: 0 BDR | AG17: 1 BDR | AH17: 2 BDR | AI17: 3 BDR | AJ17: 4 BDR | AK17: 5 BDR | AL17: 0 BDR | AM17: 1 BDR | AN17: 2 BDR | AO17: 3 BDR | AP17: 4 BDR | AQ17: 5 BDR
A19: BAKER | B19: 280 | C19: 300 | D19: 360 | E19: 416 | F19: 465 | G19: 513 | H19: 327 | I19: 350 | J19: 420 | K19: 486 | L19: 542 | M19: 598 | N19: 374 | O19: 401 | P19: 481 | Q19: 555 | R19: 620 | S19: 684 | T19: 420 | U19: 451 | V19: 541 | W19: 624 | X19: 697 | Y19: 769 | Z19: 467 | AA19: 501 | AB19: 601 | AC19: 694 | AD19: 775 | AE19: 855 | AF19: 514 | AG19: 551 | AH19: 661 | AI19: 763 | AJ19: 852 | AK19: 940 | AL19: 561 | AM19: 601 | AN19: 721 | AO19: 833 | AP19: 930 | AQ19: 1026
A20: BENTON | B20: 390 | C20: 417 | D20: 501 | E20: 579 | F20: 645 | G20: 712 | H20: 455 | I20: 487 | J20: 584 | K20: 675 | L20: 753 | M20: 831 | N20: 520 | O20: 557 | P20: 668 | Q20: 772 | R20: 861 | S20: 950 | T20: 585 | U20: 626 | V20: 751 | W20: 868 | X20: 968 | Y20: 1069 | Z20: 650 | AA20: 696 | AB20: 835 | AC20: 965 | AD20: 1076 | AE20: 1188 | AF20: 715 | AG20: 765 | AH20: 918 | AI20: 1061 | AJ20: 1183 | AK20: 1306 | AL20: 780 | AM20: 835 | AN20: 1002 | AO20: 1158 | AP20: 1291 | AQ20: 1425
A21: CLACKAMAS | B21: 383 | C21: 410 | D21: 492 | E21: 569 | F21: 635 | G21: 701 | H21: 447 | I21: 479 | J21: 574 | K21: 664 | L21: 741 | M21: 818 | N21: 511 | O21: 547 | P21: 657 | Q21: 759 | R21: 847 | S21: 935 | T21: 574 | U21: 615 | V21: 739 | W21: 854 | X21: 952 | Y21: 1051 | Z21: 638 | AA21: 684 | AB21: 821 | AC21: 949 | AD21: 1058 | AE21: 1168 | AF21: 702 | AG21: 752 | AH21: 903 | AI21: 1044 | AJ21: 1164 | AK21: 1285 | AL21: 766 | AM21: 821 | AN21: 985 | AO21: 1139 | AP21: 1270 | AQ21: 1402
A22: CLATSOP | B22: 297 | C22: 319 | D22: 383 | E22: 442 | F22: 493 | G22: 544 | H22: 347 | I22: 372 | J22: 447 | K22: 516 | L22: 575 | M22: 635 | N22: 397 | O22: 425 | P22: 511 | Q22: 590 | R22: 658 | S22: 726 | T22: 446 | U22: 478 | V22: 574 | W22: 663 | X22: 740 | Y22: 817 | Z22: 496 | AA22: 531 | AB22: 638 | AC22: 737 | AD22: 822 | AE22: 908 | AF22: 545 | AG22: 585 | AH22: 702 | AI22: 811 | AJ22: 904 | AK22: 998 | AL22: 595 | AM22: 638 | AN22: 766 | AO22: 885 | AP22: 987 | AQ22: 1089
A23: COLUMBIA | B23: 383 | C23: 410 | D23: 492 | E23: 569 | F23: 635 | G23: 701 | H23: 447 | I23: 479 | J23: 574 | K23: 664 | L23: 741 | M23: 818 | N23: 511 | O23: 547 | P23: 657 | Q23: 759 | R23: 847 | S23: 935 | T23: 574 | U23: 615 | V23: 739 | W23: 854 | X23: 952 | Y23: 1051 | Z23: 638 | AA23: 684 | AB23: 821 | AC23: 949 | AD23: 1058 | AE23: 1168 | AF23: 702 | AG23: 752 | AH23: 903 | AI23: 1044 | AJ23: 1164 | AK23: 1285 | AL23: 766 | AM23: 821 | AN23: 985 | AO23: 1139 | AP23: 1270 | AQ23: 1402
A24: COOS | B24: 280 | C24: 300 | D24: 360 | E24: 416 | F24: 465 | G24: 513 | H24: 327 | I24: 350 | J24: 420 | K24: 486 | L24: 542 | M24: 598 | N24: 374 | O24: 401 | P24: 481 | Q24: 555 | R24: 620 | S24: 684 | T24: 420 | U24: 451 | V24: 541 | W24: 624 | X24: 697 | Y24: 769 | Z24: 467 | AA24: 501 | AB24: 601 | AC24: 694 | AD24: 775 | AE24: 855 | AF24: 514 | AG24: 551 | AH24: 661 | AI24: 763 | AJ24: 852 | AK24: 940 | AL24: 561 | AM24: 601 | AN24: 721 | AO24: 833 | AP24: 930 | AQ24: 1026
A25: CROOK | B25: 296 | C25: 317 | D25: 380 | E25: 439 | F25: 490 | G25: 541 | H25: 345 | I25: 370 | J25: 443 | K25: 512 | L25: 572 | M25: 631 | N25: 395 | O25: 423 | P25: 507 | Q25: 586 | R25: 654 | S25: 721 | T25: 444 | U25: 475 | V25: 570 | W25: 659 | X25: 735 | Y25: 811 | Z25: 493 | AA25: 528 | AB25: 633 | AC25: 732 | AD25: 817 | AE25: 901 | AF25: 543 | AG25: 581 | AH25: 697 | AI25: 805 | AJ25: 899 | AK25: 992 | AL25: 592 | AM25: 634 | AN25: 760 | AO25: 879 | AP25: 981 | AQ25: 1082
A26: CURRY | B26: 285 | C26: 306 | D26: 367 | E26: 424 | F26: 474 | G26: 522 | H26: 333 | I26: 357 | J26: 428 | K26: 495 | L26: 553 | M26: 609 | N26: 381 | O26: 408 | P26: 490 | Q26: 566 | R26: 632 | S26: 697 | T26: 428 | U26: 459 | V26: 551 | W26: 636 | X26: 711 | Y26: 784 | Z26: 476 | AA26: 510 | AB26: 612 | AC26: 707 | AD26: 790 | AE26: 871 | AF26: 523 | AG26: 561 | AH26: 673 | AI26: 778 | AJ26: 869 | AK26: 958 | AL26: 571 | AM26: 612 | AN26: 735 | AO26: 849 | AP26: 948 | AQ26: 1045
A27: DESCHUTES | B27: 348 | C27: 373 | D27: 448 | E27: 518 | F27: 578 | G27: 637 | H27: 406 | I27: 436 | J27: 523 | K27: 604 | L27: 674 | M27: 744 | N27: 465 | O27: 498 | P27: 598 | Q27: 691 | R27: 771 | S27: 850 | T27: 523 | U27: 560 | V27: 672 | W27: 777 | X27: 867 | Y27: 956 | Z27: 581 | AA27: 623 | AB27: 747 | AC27: 863 | AD27: 963 | AE27: 1063 | AF27: 639 | AG27: 685 | AH27: 822 | AI27: 950 | AJ27: 1060 | AK27: 1169 | AL27: 697 | AM27: 747 | AN27: 897 | AO27: 1036 | AP27: 1156 | AQ27: 1275
A28: DOUGLAS | B28: 280 | C28: 300 | D28: 360 | E28: 416 | F28: 465 | G28: 513 | H28: 327 | I28: 350 | J28: 420 | K28: 486 | L28: 542 | M28: 598 | N28: 374 | O28: 401 | P28: 481 | Q28: 555 | R28: 620 | S28: 684 | T28: 420 | U28: 451 | V28: 541 | W28: 624 | X28: 697 | Y28: 769 | Z28: 467 | AA28: 501 | AB28: 601 | AC28: 694 | AD28: 775 | AE28: 855 | AF28: 514 | AG28: 551 | AH28: 661 | AI28: 763 | AJ28: 852 | AK28: 940 | AL28: 561 | AM28: 601 | AN28: 721 | AO28: 833 | AP28: 930 | AQ28: 1026
A29: GILLIAM | B29: 287 | C29: 307 | D29: 369 | E29: 426 | F29: 475 | G29: 524 | H29: 335 | I29: 358 | J29: 430 | K29: 497 | L29: 554 | M29: 612 | N29: 383 | O29: 410 | P29: 492 | Q29: 568 | R29: 634 | S29: 699 | T29: 430 | U29: 461 | V29: 553 | W29: 639 | X29: 713 | Y29: 786 | Z29: 478 | AA29: 512 | AB29: 615 | AC29: 710 | AD29: 792 | AE29: 874 | AF29: 526 | AG29: 563 | AH29: 676 | AI29: 781 | AJ29: 871 | AK29: 961 | AL29: 574 | AM29: 615 | AN29: 738 | AO29: 852 | AP29: 951 | AQ29: 1049
A30: GRANT | B30: 280 | C30: 300 | D30: 360 | E30: 416 | F30: 465 | G30: 513 | H30: 327 | I30: 350 | J30: 420 | K30: 486 | L30: 542 | M30: 598 | N30: 374 | O30: 401 | P30: 481 | Q30: 555 | R30: 620 | S30: 684 | T30: 420 | U30: 451 | V30: 541 | W30: 624 | X30: 697 | Y30: 769 | Z30: 467 | AA30: 501 | AB30: 601 | AC30: 694 | AD30: 775 | AE30: 855 | AF30: 514 | AG30: 551 | AH30: 661 | AI30: 763 | AJ30: 852 | AK30: 940 | AL30: 561 | AM30: 601 | AN30: 721 | AO30: 833 | AP30: 930 | AQ30: 1026
... A54: YAMHILL | B54: 383 | C54: 410 | D54: 492 | E54: 569 | F54: 635 | G54: 701 | H54: 447 | I54: 479 | J54: 574 | K54: 664 | L54: 741 | M54: 818 | N54: 511 | O54: 547 | P54: 657 | Q54: 759 | R54: 847 | S54: 935 | T54: 574 | U54: 615 | V54: 739 | W54: 854 | X54: 952 | Y54: 1051 | Z54: 638 | AA54: 684 | AB54: 821 | AC54: 949 | AD54: 1058 | AE54: 1168 | AF54: 702 | AG54: 752 | AH54: 903 | AI54: 1044 | AJ54: 1164 | AK54: 1285 | AL54: 766 | AM54: 821 | AN54: 985 | AO54: 1139 | AP54: 1270 | AQ54: 1402

Sheet LIHTCIncomes12
F1: OREGON HOUSING AND COMMUNITY SERVICES
F2: 2012 INCOME LIMITS
F3: for the LIHTC PROGRAM
B5: Based on HUD's published Section 8 (and Multifamily Tax Subsidy) income limits
B6: Median incomes by county (effective: December 1, 2011)
B7: Income limits by county (or non-PMSA average if greater)
B9: If your project is located in a rural area as defined by USDA RHS*, you qualify to use
B10: national non-metropolitan income limits, available at OHCS website**.
A11: *USDA RHS: | B11: http://eligibility.sc.egov.usda.gov/eligibility/welcomeAction.do?NavKey=home@1
A12: **OHCS: | B12: http://www.ohcs.oregon.gov/OHCS/HPM_income_rent_limits_2012.shtml
A14: MSA / County | B14: % MFI | C14: 1 Pers | D14: 2 Pers | E14: 3 Pers | F14: 4 Pers | G14: 5 Pers | H14: 6 Pers | I14: 7 Pers | J14: 8 Pers
A16: Deschutes | B16: 0.3 | C16: =+C18*0.6 -> 13950 | D16: =+D18*0.6 -> 15960 | E16: =+E18*0.6 -> 17940 | F16: =+F18*0.6 -> 19920 | G16: =+G18*0.6 -> 21540 | H16: =+H18*0.6 -> 23130 | I16: =+I18*0.6 -> 24720 | J16: =+J18*0.6 -> 26310
B17: 0.4 | C17: =+C18*0.8 -> 18600 | D17: =+D18*0.8 -> 21280 | E17: =+E18*0.8 -> 23920 | F17: =+F18*0.8 -> 26560 | G17: =+G18*0.8 -> 28720 | H17: =+H18*0.8 -> 30840 | I17: =+I18*0.8 -> 32960 | J17: =+J18*0.8 -> 35080
B18: 0.5 | C18: 23250 | D18: 26600 | E18: 29900 | F18: 33200 | G18: 35900 | H18: 38550 | I18: 41200 | J18: 43850
B19: 0.6 | C19: =+C18*1.2 -> 27900 | D19: =+D18*1.2 -> 31920 | E19: =+E18*1.2 -> 35880 | F19: =+F18*1.2 -> 39840 | G19: =+G18*1.2 -> 43080 | H19: =+H18*1.2 -> 46260 | I19: =+I18*1.2 -> 49440 | J19: =+J18*1.2 -> 52620
B20: 0.8 | C20: =+C18*1.6 -> 37200 | D20: =+D18*1.6 -> 42560 | E20: =+E18*1.6 -> 47840 | F20: =+F18*1.6 -> 53120 | G20: =+G18*1.6 -> 57440 | H20: =+H18*1.6 -> 61680 | I20: =+I18*1.6 -> 65920 | J20: =+J18*1.6 -> 70160
A22: Benton | B22: 0.3 | C22: =+C24*0.6 -> 15600 | D22: =+D24*0.6 -> 17820 | E22: =+E24*0.6 -> 20040 | F22: =+F24*0.6 -> 22260 | G22: =+G24*0.6 -> 24060 | H22: =+H24*0.6 -> 25830 | I22: =+I24*0.6 -> 27630 | J22: =+J24*0.6 -> 29400
B23: 0.4 | C23: =+C24*0.8 -> 20800 | D23: =+D24*0.8 -> 23760 | E23: =+E24*0.8 -> 26720 | F23: =+F24*0.8 -> 29680 | G23: =+G24*0.8 -> 32080 | H23: =+H24*0.8 -> 34440 | I23: =+I24*0.8 -> 36840 | J23: =+J24*0.8 -> 39200
B24: 0.5 | C24: 26000 | D24: 29700 | E24: 33400 | F24: 37100 | G24: 40100 | H24: 43050 | I24: 46050 | J24: 49000
B25: 0.6 | C25: =+C24*1.2 -> 31200 | D25: =+D24*1.2 -> 35640 | E25: =+E24*1.2 -> 40080 | F25: =+F24*1.2 -> 44520 | G25: =+G24*1.2 -> 48120 | H25: =+H24*1.2 -> 51660 | I25: =+I24*1.2 -> 55260 | J25: =+J24*1.2 -> 58800
B26: 0.8 | C26: =+C24*1.6 -> 41600 | D26: =+D24*1.6 -> 47520 | E26: =+E24*1.6 -> 53440 | F26: =+F24*1.6 -> 59360 | G26: =+G24*1.6 -> 64160 | H26: =+H24*1.6 -> 68880 | I26: =+I24*1.6 -> 73680 | J26: =+J24*1.6 -> 78400
A28: Lane | B28: 0.3 | C28: =+C30*0.6 -> 12450 | D28: =+D30*0.6 -> 14220 | E28: =+E30*0.6 -> 15990 | F28: =+F30*0.6 -> 17760 | G28: =+G30*0.6 -> 19200 | H28: =+H30*0.6 -> 20610 | I28: =+I30*0.6 -> 22050 | J28: =+J30*0.6 -> 23460
B29: 0.4 | C29: =+C30*0.8 -> 16600 | D29: =+D30*0.8 -> 18960 | E29: =+E30*0.8 -> 21320 | F29: =+F30*0.8 -> 23680 | G29: =+G30*0.8 -> 25600 | H29: =+H30*0.8 -> 27480 | I29: =+I30*0.8 -> 29400 | J29: =+J30*0.8 -> 31280
B30: 0.5 | C30: 20750 | D30: 23700 | E30: 26650 | F30: 29600 | G30: 32000 | H30: 34350 | I30: 36750 | J30: 39100
B31: 0.6 | C31: =+C30*1.2 -> 24900 | D31: =+D30*1.2 -> 28440 | E31: =+E30*1.2 -> 31980 | F31: =+F30*1.2 -> 35520 | G31: =+G30*1.2 -> 38400 | H31: =+H30*1.2 -> 41220 | I31: =+I30*1.2 -> 44100 | J31: =+J30*1.2 -> 46920
B32: 0.8 | C32: =+C30*1.6 -> 33200 | D32: =+D30*1.6 -> 37920 | E32: =+E30*1.6 -> 42640 | F32: =+F30*1.6 -> 47360 | G32: =+G30*1.6 -> 51200 | H32: =+H30*1.6 -> 54960 | I32: =+I30*1.6 -> 58800 | J32: =+J30*1.6 -> 62560
A34: Jackson | B34: 0.3 | C34: =+C36*0.6 -> 12300 | D34: =+D36*0.6 -> 14040 | E34: =+E36*0.6 -> 15810 | F34: =+F36*0.6 -> 17550 | G34: =+G36*0.6 -> 18960 | H34: =+H36*0.6 -> 20370 | I34: =+I36*0.6 -> 21780 | J34: =+J36*0.6 -> 23190
B35: 0.4 | C35: =+C36*0.8 -> 16400 | D35: =+D36*0.8 -> 18720 | E35: =+E36*0.8 -> 21080 | F35: =+F36*0.8 -> 23400 | G35: =+G36*0.8 -> 25280 | H35: =+H36*0.8 -> 27160 | I35: =+I36*0.8 -> 29040 | J35: =+J36*0.8 -> 30920
B36: 0.5 | C36: 20500 | D36: 23400 | E36: 26350 | F36: 29250 | G36: 31600 | H36: 33950 | I36: 36300 | J36: 38650
B37: 0.6 | C37: =+C36*1.2 -> 24600 | D37: =+D36*1.2 -> 28080 | E37: =+E36*1.2 -> 31620 | F37: =+F36*1.2 -> 35100 | G37: =+G36*1.2 -> 37920 | H37: =+H36*1.2 -> 40740 | I37: =+I36*1.2 -> 43560 | J37: =+J36*1.2 -> 46380
B38: 0.8 | C38: =+C36*1.6 -> 32800 | D38: =+D36*1.6 -> 37440 | E38: =+E36*1.6 -> 42160 | F38: =+F36*1.6 -> 46800 | G38: =+G36*1.6 -> 50560 | H38: =+H36*1.6 -> 54320 | I38: =+I36*1.6 -> 58080 | J38: =+J36*1.6 -> 61840
A40: Clackamas | B40: 0.3 | C40: =+C42*0.6 -> 15330 | D40: =+D42*0.6 -> 17520 | E40: =+E42*0.6 -> 19710 | F40: =+F42*0.6 -> 21900 | G40: =+G42*0.6 -> 23670 | H40: =+H42*0.6 -> 25410 | I40: =+I42*0.6 -> 27180 | J40: =+J42*0.6 -> 28920
A41: Columbia | B41: 0.4 | C41: =+C42*0.8 -> 20440 | D41: =+D42*0.8 -> 23360 | E41: =+E42*0.8 -> 26280 | F41: =+F42*0.8 -> 29200 | G41: =+G42*0.8 -> 31560 | H41: =+H42*0.8 -> 33880 | I41: =+I42*0.8 -> 36240 | J41: =+J42*0.8 -> 38560
A42: Multnomah | B42: 0.5 | C42: 25550 | D42: 29200 | E42: 32850 | F42: 36500 | G42: 39450 | H42: 42350 | I42: 45300 | J42: 48200
A43: Washington | B43: 0.6 | C43: =+C42*1.2 -> 30660 | D43: =+D42*1.2 -> 35040 | E43: =+E42*1.2 -> 39420 | F43: =+F42*1.2 -> 43800 | G43: =+G42*1.2 -> 47340 | H43: =+H42*1.2 -> 50820 | I43: =+I42*1.2 -> 54360 | J43: =+J42*1.2 -> 57840
A44: & Yamhill | B44: 0.8 | C44: =+C42*1.6 -> 40880 | D44: =+D42*1.6 -> 46720 | E44: =+E42*1.6 -> 52560 | F44: =+F42*1.6 -> 58400 | G44: =+G42*1.6 -> 63120 | H44: =+H42*1.6 -> 67760 | I44: =+I42*1.6 -> 72480 | J44: =+J42*1.6 -> 77120
A46: Marion & Polk | B46: 0.3 | C46: =+C48*0.6 -> 12600 | D46: =+D48*0.6 -> 14400 | E46: =+E48*0.6 -> 16200 | F46: =+F48*0.6 -> 18000 | G46: =+G48*0.6 -> 19440 | H46: =+H48*0.6 -> 20880 | I46: =+I48*0.6 -> 22320 | J46: =+J48*0.6 -> 23760
B47: 0.4 | C47: =+C48*0.8 -> 16800 | D47: =+D48*0.8 -> 19200 | E47: =+E48*0.8 -> 21600 | F47: =+F48*0.8 -> 24000 | G47: =+G48*0.8 -> 25920 | H47: =+H48*0.8 -> 27840 | I47: =+I48*0.8 -> 29760 | J47: =+J48*0.8 -> 31680
B48: 0.5 | C48: 21000 | D48: 24000 | E48: 27000 | F48: 30000 | G48: 32400 | H48: 34800 | I48: 37200 | J48: 39600
B49: 0.6 | C49: =+C48*1.2 -> 25200 | D49: =+D48*1.2 -> 28800 | E49: =+E48*1.2 -> 32400 | F49: =+F48*1.2 -> 36000 | G49: =+G48*1.2 -> 38880 | H49: =+H48*1.2 -> 41760 | I49: =+I48*1.2 -> 44640 | J49: =+J48*1.2 -> 47520
B50: 0.8 | C50: =+C48*1.6 -> 33600 | D50: =+D48*1.6 -> 38400 | E50: =+E48*1.6 -> 43200 | F50: =+F48*1.6 -> 48000 | G50: =+G48*1.6 -> 51840 | H50: =+H48*1.6 -> 55680 | I50: =+I48*1.6 -> 59520 | J50: =+J48*1.6 -> 63360
A52: Baker | B52: 0.3 | C52: =+C54*0.6 -> 11220 | D52: =+D54*0.6 -> 12840 | E52: =+E54*0.6 -> 14430 | F52: =+F54*0.6 -> 16020 | G52: =+G54*0.6 -> 17310 | H52: =+H54*0.6 -> 18600 | I52: =+I54*0.6 -> 19890 | J52: =+J54*0.6 -> 21150
B53: 0.4 | C53: =+C54*0.8 -> 14960 | D53: =+D54*0.8 -> 17120 | E53: =+E54*0.8 -> 19240 | F53: =+F54*0.8 -> 21360 | G53: =+G54*0.8 -> 23080 | H53: =+H54*0.8 -> 24800 | I53: =+I54*0.8 -> 26520 | J53: =+J54*0.8 -> 28200
B54: 0.5 | C54: 18700 | D54: 21400 | E54: 24050 | F54: 26700 | G54: 28850 | H54: 31000 | I54: 33150 | J54: 35250
B55: 0.6 | C55: =+C54*1.2 -> 22440 | D55: =+D54*1.2 -> 25680 | E55: =+E54*1.2 -> 28860 | F55: =+F54*1.2 -> 32040 | G55: =+G54*1.2 -> 34620 | H55: =+H54*1.2 -> 37200 | I55: =+I54*1.2 -> 39780 | J55: =+J54*1.2 -> 42300
B56: 0.8 | C56: =+C54*1.6 -> 29920 | D56: =+D54*1.6 -> 34240 | E56: =+E54*1.6 -> 38480 | F56: =+F54*1.6 -> 42720 | G56: =+G54*1.6 -> 46160 | H56: =+H54*1.6 -> 49600 | I56: =+I54*1.6 -> 53040 | J56: =+J54*1.6 -> 56400
A58: MSA / County | B58: % of MFI | C58: 1 Pers | D58: 2 Pers | E58: 3 Pers | F58: 4 Pers | G58: 5 Pers | H58: 6 Pers | I58: 7 Pers | J58: 8 Pers
A60: Clatsop | B60: 0.3 | C60: =+C62*0.6 -> 11910 | D60: =+D62*0.6 -> 13620 | E60: =+E62*0.6 -> 15330 | F60: =+F62*0.6 -> 17010 | G60: =+G62*0.6 -> 18390 | H60: =+H62*0.6 -> 19740 | I60: =+I62*0.6 -> 21120 | J60: =+J62*0.6 -> 22470
B61: 0.4 | C61: =+C62*0.8 -> 15880 | D61: =+D62*0.8 -> 18160 | E61: =+E62*0.8 -> 20440 | F61: =+F62*0.8 -> 22680 | G61: =+G62*0.8 -> 24520 | H61: =+H62*0.8 -> 26320 | I61: =+I62*0.8 -> 28160 | J61: =+J62*0.8 -> 29960
B62: 0.5 | C62: 19850 | D62: 22700 | E62: 25550 | F62: 28350 | G62: 30650 | H62: 32900 | I62: 35200 | J62: 37450
B63: 0.6 | C63: =+C62*1.2 -> 23820 | D63: =+D62*1.2 -> 27240 | E63: =+E62*1.2 -> 30660 | F63: =+F62*1.2 -> 34020 | G63: =+G62*1.2 -> 36780 | H63: =+H62*1.2 -> 39480 | I63: =+I62*1.2 -> 42240 | J63: =+J62*1.2 -> 44940
B64: 0.8 | C64: =+C62*1.6 -> 31760 | D64: =+D62*1.6 -> 36320 | E64: =+E62*1.6 -> 40880 | F64: =+F62*1.6 -> 45360 | G64: =+G62*1.6 -> 49040 | H64: =+H62*1.6 -> 52640 | I64: =+I62*1.6 -> 56320 | J64: =+J62*1.6 -> 59920
A66: Coos | B66: 0.3 | C66: =+C68*0.6 -> 11220 | D66: =+D68*0.6 -> 12840 | E66: =+E68*0.6 -> 14430 | F66: =+F68*0.6 -> 16020 | G66: =+G68*0.6 -> 17310 | H66: =+H68*0.6 -> 18600 | I66: =+I68*0.6 -> 19890 | J66: =+J68*0.6 -> 21150
B67: 0.4 | C67: =+C68*0.8 -> 14960 | D67: =+D68*0.8 -> 17120 | E67: =+E68*0.8 -> 19240 | F67: =+F68*0.8 -> 21360 | G67: =+G68*0.8 -> 23080 | H67: =+H68*0.8 -> 24800 | I67: =+I68*0.8 -> 26520 | J67: =+J68*0.8 -> 28200
B68: 0.5 | C68: 18700 | D68: 21400 | E68: 24050 | F68: 26700 | G68: 28850 | H68: 31000 | I68: 33150 | J68: 35250
B69: 0.6 | C69: =+C68*1.2 -> 22440 | D69: =+D68*1.2 -> 25680 | E69: =+E68*1.2 -> 28860 | F69: =+F68*1.2 -> 32040 | G69: =+G68*1.2 -> 34620 | H69: =+H68*1.2 -> 37200 | I69: =+I68*1.2 -> 39780 | J69: =+J68*1.2 -> 42300
B70: 0.8 | C70: =+C68*1.6 -> 29920 | D70: =+D68*1.6 -> 34240 | E70: =+E68*1.6 -> 38480 | F70: =+F68*1.6 -> 42720 | G70: =+G68*1.6 -> 46160 | H70: =+H68*1.6 -> 49600 | I70: =+I68*1.6 -> 53040 | J70: =+J68*1.6 -> 56400
A72: Crook | B72: 0.3 | C72: =+C74*0.6 -> 11850 | D72: =+D74*0.6 -> 13530 | E72: =+E74*0.6 -> 15210 | F72: =+F74*0.6 -> 16890 | G72: =+G74*0.6 -> 18270 | H72: =+H74*0.6 -> 19620 | I72: =+I74*0.6 -> 20970 | J72: =+J74*0.6 -> 22320
B73: 0.4 | C73: =+C74*0.8 -> 15800 | D73: =+D74*0.8 -> 18040 | E73: =+E74*0.8 -> 20280 | F73: =+F74*0.8 -> 22520 | G73: =+G74*0.8 -> 24360 | H73: =+H74*0.8 -> 26160 | I73: =+I74*0.8 -> 27960 | J73: =+J74*0.8 -> 29760
B74: 0.5 | C74: 19750 | D74: 22550 | E74: 25350 | F74: 28150 | G74: 30450 | H74: 32700 | I74: 34950 | J74: 37200
B75: 0.6 | C75: =+C74*1.2 -> 23700 | D75: =+D74*1.2 -> 27060 | E75: =+E74*1.2 -> 30420 | F75: =+F74*1.2 -> 33780 | G75: =+G74*1.2 -> 36540 | H75: =+H74*1.2 -> 39240 | I75: =+I74*1.2 -> 41940 | J75: =+J74*1.2 -> 44640
B76: 0.8 | C76: =+C74*1.6 -> 31600 | D76: =+D74*1.6 -> 36080 | E76: =+E74*1.6 -> 40560 | F76: =+F74*1.6 -> 45040 | G76: =+G74*1.6 -> 48720 | H76: =+H74*1.6 -> 52320 | I76: =+I74*1.6 -> 55920 | J76: =+J74*1.6 -> 59520
A78: Curry | B78: 0.3 | C78: =+C80*0.6 -> 11430 | D78: =+D80*0.6 -> 13080 | E78: =+E80*0.6 -> 14700 | F78: =+F80*0.6 -> 16320 | G78: =+G80*0.6 -> 17640 | H78: =+H80*0.6 -> 18960 | I78: =+I80*0.6 -> 20250 | J78: =+J80*0.6 -> 21570
B79: 0.4 | C79: =+C80*0.8 -> 15240 | D79: =+D80*0.8 -> 17440 | E79: =+E80*0.8 -> 19600 | F79: =+F80*0.8 -> 21760 | G79: =+G80*0.8 -> 23520 | H79: =+H80*0.8 -> 25280 | I79: =+I80*0.8 -> 27000 | J79: =+J80*0.8 -> 28760
B80: 0.5 | C80: 19050 | D80: 21800 | E80: 24500 | F80: 27200 | G80: 29400 | H80: 31600 | I80: 33750 | J80: 35950
B81: 0.6 | C81: =+C80*1.2 -> 22860 | D81: =+D80*1.2 -> 26160 | E81: =+E80*1.2 -> 29400 | F81: =+F80*1.2 -> 32640 | G81: =+G80*1.2 -> 35280 | H81: =+H80*1.2 -> 37920 | I81: =+I80*1.2 -> 40500 | J81: =+J80*1.2 -> 43140
B82: 0.8 | C82: =+C80*1.6 -> 30480 | D82: =+D80*1.6 -> 34880 | E82: =+E80*1.6 -> 39200 | F82: =+F80*1.6 -> 43520 | G82: =+G80*1.6 -> 47040 | H82: =+H80*1.6 -> 50560 | I82: =+I80*1.6 -> 54000 | J82: =+J80*1.6 -> 57520
A84: Douglas | B84: 0.3 | C84: =+C86*0.6 -> 11220 | D84: =+D86*0.6 -> 12840 | E84: =+E86*0.6 -> 14430 | F84: =+F86*0.6 -> 16020 | G84: =+G86*0.6 -> 17310 | H84: =+H86*0.6 -> 18600 | I84: =+I86*0.6 -> 19890 | J84: =+J86*0.6 -> 21150
B85: 0.4 | C85: =+C86*0.8 -> 14960 | D85: =+D86*0.8 -> 17120 | E85: =+E86*0.8 -> 19240 | F85: =+F86*0.8 -> 21360 | G85: =+G86*0.8 -> 23080 | H85: =+H86*0.8 -> 24800 | I85: =+I86*0.8 -> 26520 | J85: =+J86*0.8 -> 28200
B86: 0.5 | C86: 18700 | D86: 21400 | E86: 24050 | F86: 26700 | G86: 28850 | H86: 31000 | I86: 33150 | J86: 35250
B87: 0.6 | C87: =+C86*1.2 -> 22440 | D87: =+D86*1.2 -> 25680 | E87: =+E86*1.2 -> 28860 | F87: =+F86*1.2 -> 32040 | G87: =+G86*1.2 -> 34620 | H87: =+H86*1.2 -> 37200 | I87: =+I86*1.2 -> 39780 | J87: =+J86*1.2 -> 42300
B88: 0.8 | C88: =+C86*1.6 -> 29920 | D88: =+D86*1.6 -> 34240 | E88: =+E86*1.6 -> 38480 | F88: =+F86*1.6 -> 42720 | G88: =+G86*1.6 -> 46160 | H88: =+H86*1.6 -> 49600 | I88: =+I86*1.6 -> 53040 | J88: =+J86*1.6 -> 56400
A90: Gilliam | B90: 0.3 | C90: =+C92*0.6 -> 11490 | D90: =+D92*0.6 -> 13110 | E90: =+E92*0.6 -> 14760 | F90: =+F92*0.6 -> 16380 | G90: =+G92*0.6 -> 17700 | H90: =+H92*0.6 -> 19020 | I90: =+I92*0.6 -> 20340 | J90: =+J92*0.6 -> 21630
B91: 0.4 | C91: =+C92*0.8 -> 15320 | D91: =+D92*0.8 -> 17480 | E91: =+E92*0.8 -> 19680 | F91: =+F92*0.8 -> 21840 | G91: =+G92*0.8 -> 23600 | H91: =+H92*0.8 -> 25360 | I91: =+I92*0.8 -> 27120 | J91: =+J92*0.8 -> 28840
B92: 0.5 | C92: 19150 | D92: 21850 | E92: 24600 | F92: 27300 | G92: 29500 | H92: 31700 | I92: 33900 | J92: 36050
B93: 0.6 | C93: =+C92*1.2 -> 22980 | D93: =+D92*1.2 -> 26220 | E93: =+E92*1.2 -> 29520 | F93: =+F92*1.2 -> 32760 | G93: =+G92*1.2 -> 35400 | H93: =+H92*1.2 -> 38040 | I93: =+I92*1.2 -> 40680 | J93: =+J92*1.2 -> 43260
B94: 0.8 | C94: =+C92*1.6 -> 30640 | D94: =+D92*1.6 -> 34960 | E94: =+E92*1.6 -> 39360 | F94: =+F92*1.6 -> 43680 | G94: =+G92*1.6 -> 47200 | H94: =+H92*1.6 -> 50720 | I94: =+I92*1.6 -> 54240 | J94: =+J92*1.6 -> 57680
A96: Grant | B96: 0.3 | C96: =+C98*0.6 -> 11220 | D96: =+D98*0.6 -> 12840 | E96: =+E98*0.6 -> 14430 | F96: =+F98*0.6 -> 16020 | G96: =+G98*0.6 -> 17310 | H96: =+H98*0.6 -> 18600 | I96: =+I98*0.6 -> 19890 | J96: =+J98*0.6 -> 21150
B97: 0.4 | C97: =+C98*0.8 -> 14960 | D97: =+D98*0.8 -> 17120 | E97: =+E98*0.8 -> 19240 | F97: =+F98*0.8 -> 21360 | G97: =+G98*0.8 -> 23080 | H97: =+H98*0.8 -> 24800 | I97: =+I98*0.8 -> 26520 | J97: =+J98*0.8 -> 28200
B98: 0.5 | C98: 18700 | D98: 21400 | E98: 24050 | F98: 26700 | G98: 28850 | H98: 31000 | I98: 33150 | J98: 35250
B99: 0.6 | C99: =+C98*1.2 -> 22440 | D99: =+D98*1.2 -> 25680 | E99: =+E98*1.2 -> 28860 | F99: =+F98*1.2 -> 32040 | G99: =+G98*1.2 -> 34620 | H99: =+H98*1.2 -> 37200 | I99: =+I98*1.2 -> 39780 | J99: =+J98*1.2 -> 42300
B100: 0.8 | C100: =+C98*1.6 -> 29920 | D100: =+D98*1.6 -> 34240 | E100: =+E98*1.6 -> 38480 | F100: =+F98*1.6 -> 42720 | G100: =+G98*1.6 -> 46160 | H100: =+H98*1.6 -> 49600 | I100: =+I98*1.6 -> 53040 | J100: =+J98*1.6 -> 56400
A102: Harney | B102: 0.3 | C102: =+C104*0.6 -> 11220 | D102: =+D104*0.6 -> 12840 | E102: =+E104*0.6 -> 14430 | F102: =+F104*0.6 -> 16020 | G102: =+G104*0.6 -> 17310 | H102: =+H104*0.6 -> 18600 | I102: =+I104*0.6 -> 19890 | J102: =+J104*0.6 -> 21150
B103: 0.4 | C103: =+C104*0.8 -> 14960 | D103: =+D104*0.8 -> 17120 | E103: =+E104*0.8 -> 19240 | F103: =+F104*0.8 -> 21360 | G103: =+G104*0.8 -> 23080 | H103: =+H104*0.8 -> 24800 | I103: =+I104*0.8 -> 26520 | J103: =+J104*0.8 -> 28200
B104: 0.5 | C104: 18700 | D104: 21400 | E104: 24050 | F104: 26700 | G104: 28850 | H104: 31000 | I104: 33150 | J104: 35250
B105: 0.6 | C105: =+C104*1.2 -> 22440 | D105: =+D104*1.2 -> 25680 | E105: =+E104*1.2 -> 28860 | F105: =+F104*1.2 -> 32040 | G105: =+G104*1.2 -> 34620 | H105: =+H104*1.2 -> 37200 | I105: =+I104*1.2 -> 39780 | J105: =+J104*1.2 -> 42300
B106: 0.8 | C106: =+C104*1.6 -> 29920 | D106: =+D104*1.6 -> 34240 | E106: =+E104*1.6 -> 38480 | F106: =+F104*1.6 -> 42720 | G106: =+G104*1.6 -> 46160 | H106: =+H104*1.6 -> 49600 | I106: =+I104*1.6 -> 53040 | J106: =+J104*1.6 -> 56400
A108: Hood River | B108: 0.3 | C108: =+C110*0.6 -> 12180 | D108: =+D110*0.6 -> 13920 | E108: =+E110*0.6 -> 15660 | F108: =+F110*0.6 -> 17370 | G108: =+G110*0.6 -> 18780 | H108: =+H110*0.6 -> 20160 | I108: =+I110*0.6 -> 21540 | J108: =+J110*0.6 -> 22950
B109: 0.4 | C109: =+C110*0.8 -> 16240 | D109: =+D110*0.8 -> 18560 | E109: =+E110*0.8 -> 20880 | F109: =+F110*0.8 -> 23160 | G109: =+G110*0.8 -> 25040 | H109: =+H110*0.8 -> 26880 | I109: =+I110*0.8 -> 28720 | J109: =+J110*0.8 -> 30600
B110: 0.5 | C110: 20300 | D110: 23200 | E110: 26100 | F110: 28950 | G110: 31300 | H110: 33600 | I110: 35900 | J110: 38250
B111: 0.6 | C111: =+C110*1.2 -> 24360 | D111: =+D110*1.2 -> 27840 | E111: =+E110*1.2 -> 31320 | F111: =+F110*1.2 -> 34740 | G111: =+G110*1.2 -> 37560 | H111: =+H110*1.2 -> 40320 | I111: =+I110*1.2 -> 43080 | J111: =+J110*1.2 -> 45900
B112: 0.8 | C112: =+C110*1.6 -> 32480 | D112: =+D110*1.6 -> 37120 | E112: =+E110*1.6 -> 41760 | F112: =+F110*1.6 -> 46320 | G112: =+G110*1.6 -> 50080 | H112: =+H110*1.6 -> 53760 | I112: =+I110*1.6 -> 57440 | J112: =+J110*1.6 -> 61200
A114: MSA / County | B114: % of MFI | C114: 1 Pers | D114: 2 Pers | E114: 3 Pers | F114: 4 Pers | G114: 5 Pers | H114: 6 Pers | I114: 7 Pers | J114: 8 Pers
A116: Jefferson | B116: 0.3 | C116: =+C118*0.6 -> 11220 | D116: =+D118*0.6 -> 12840 | E116: =+E118*0.6 -> 14430 | F116: =+F118*0.6 -> 16020 | G116: =+G118*0.6 -> 17310 | H116: =+H118*0.6 -> 18600 | I116: =+I118*0.6 -> 19890 | J116: =+J118*0.6 -> 21150
B117: 0.4 | C117: =+C118*0.8 -> 14960 | D117: =+D118*0.8 -> 17120 | E117: =+E118*0.8 -> 19240 | F117: =+F118*0.8 -> 21360 | G117: =+G118*0.8 -> 23080 | H117: =+H118*0.8 -> 24800 | I117: =+I118*0.8 -> 26520 | J117: =+J118*0.8 -> 28200
B118: 0.5 | C118: 18700 | D118: 21400 | E118: 24050 | F118: 26700 | G118: 28850 | H118: 31000 | I118: 33150 | J118: 35250
B119: 0.6 | C119: =+C118*1.2 -> 22440 | D119: =+D118*1.2 -> 25680 | E119: =+E118*1.2 -> 28860 | F119: =+F118*1.2 -> 32040 | G119: =+G118*1.2 -> 34620 | H119: =+H118*1.2 -> 37200 | I119: =+I118*1.2 -> 39780 | J119: =+J118*1.2 -> 42300
B120: 0.8 | C120: =+C118*1.6 -> 29920 | D120: =+D118*1.6 -> 34240 | E120: =+E118*1.6 -> 38480 | F120: =+F118*1.6 -> 42720 | G120: =+G118*1.6 -> 46160 | H120: =+H118*1.6 -> 49600 | I120: =+I118*1.6 -> 53040 | J120: =+J118*1.6 -> 56400
A122: Josephine | B122: 0.3 | C122: =+C124*0.6 -> 11220 | D122: =+D124*0.6 -> 12840 | E122: =+E124*0.6 -> 14430 | F122: =+F124*0.6 -> 16020 | G122: =+G124*0.6 -> 17310 | H122: =+H124*0.6 -> 18600 | I122: =+I124*0.6 -> 19890 | J122: =+J124*0.6 -> 21150
B123: 0.4 | C123: =+C124*0.8 -> 14960 | D123: =+D124*0.8 -> 17120 | E123: =+E124*0.8 -> 19240 | F123: =+F124*0.8 -> 21360 | G123: =+G124*0.8 -> 23080 | H123: =+H124*0.8 -> 24800 | I123: =+I124*0.8 -> 26520 | J123: =+J124*0.8 -> 28200
...

Sheet HOME Rents 11
A1: OREGON HOUSING AND COMMUNITY SERVICES
A2: HOME PROGRAM RENTS
B4: FY 2012 Fair Market and HOME Rents as of February 9, 2012 for Portland MSA ONLY
B5: (All MSA's 2011 rents)
A7: MSA / County | C7: Studio | D7: 1 Bdrm | E7: 2 Bdrm | F7: 3 Bdrm | G7: 4 Bdrm | H7: 5 Bdrm | I7: 6 Bdrm
A9: Bend | B9: FMR | C9: 572 | D9: 664 | E9: 792 | F9: 1154 | G9: 1190 | H9: 1369 | I9: 1547
A10: Deschutes | B10: LOW | C10: 572 | D10: 614 | E10: 737 | F10: 851 | G10: 950 | H10: 1048 | I10: 1146
B11: HIGH | C11: 572 | D11: 664 | E11: 792 | F11: 1074 | G11: 1179 | H11: 1282 | I11: 1385
A13: Corvallis | B13: FMR | C13: 537 | D13: 651 | E13: 811 | F13: 1178 | G13: 1355 | H13: 1558 | I13: 1762
A14: Benton | B14: LOW | C14: 537 | D14: 651 | E14: 811 | F14: 951 | G14: 1062 | H14: 1171 | I14: 1281
B15: HIGH | C15: 537 | D15: 651 | E15: 811 | F15: 1178 | G15: 1324 | H15: 1442 | I15: 1560
A17: Eugene-Springfield | B17: FMR | C17: 523 | D17: 634 | E17: 803 | F17: 1123 | G17: 1250 | H17: 1438 | I17: 1625
A18: Lane | B18: LOW | C18: 511 | D18: 548 | E18: 657 | F18: 759 | G18: 847 | H18: 935 | I18: 1022
B19: HIGH | C19: 523 | D19: 634 | E19: 803 | F19: 953 | G19: 1044 | H19: 1133 | I19: 1222
A21: Medford-Ashland | B21: FMR | C21: 529 | D21: 629 | E21: 790 | F21: 1149 | G21: 1183 | H21: 1360 | I21: 1538
A22: Jackson | B22: LOW | C22: 505 | D22: 541 | E22: 650 | F22: 750 | G22: 837 | H22: 923 | I22: 1009
B23: HIGH | C23: 529 | D23: 629 | E23: 790 | F23: 941 | G23: 1030 | H23: 1118 | I23: 1207
A25: Portland-Vancouver | B25: FMR | C25: 665 | D25: 771 | E25: 891 | F25: 1297 | G25: 1558 | H25: 1792 | I25: 2025
A26: Clackamas, Columbia, | B26: LOW | C26: 638 | D26: 684 | E26: 821 | F26: 949 | G26: 1058 | H26: 1168 | I26: 1277
A27: Multnomah, Washington | B27: HIGH | C27: 675 | D27: 783 | E27: 905 | F27: 1200 | G27: 1319 | H27: 1437 | I27: 1555
A28: Yamhill
A30: Salem | B30: FMR | C30: 536 | D30: 595 | E30: 712 | F30: 1035 | G30: 1248 | H30: 1435 | I30: 1622
A31: Marion, Polk | B31: LOW | C31: 518 | D31: 555 | E31: 666 | F31: 770 | G31: 858 | H31: 948 | I31: 1036
B32: HIGH | C32: 536 | D32: 595 | E32: 712 | F32: 967 | G32: 1060 | H32: 1151 | I32: 1242
A34: Baker | B34: FMR | C34: 419 | D34: 488 | E34: 644 | F34: 937 | G34: 965 | H34: 1110 | I34: 1255
B35: LOW | C35: 419 | D35: 488 | E35: 593 | F35: 685 | G35: 765 | H35: 843 | I35: 922
B36: HIGH | C36: 419 | D36: 488 | E36: 644 | F36: 857 | G36: 936 | H36: 1015 | I36: 1093
A38: Clatsop | B38: FMR | C38: 474 | D38: 589 | E38: 728 | F38: 1053 | G38: 1086 | H38: 1249 | I38: 1412
B39: LOW | C39: 474 | D39: 531 | E39: 637 | F39: 736 | G39: 821 | H39: 906 | I39: 990
B40: HIGH | C40: 474 | D40: 589 | E40: 728 | F40: 923 | G40: 1010 | H40: 1096 | I40: 1182
A42: Coos | B42: FMR | C42: 458 | D42: 555 | E42: 704 | F42: 934 | G42: 1076 | H42: 1237 | I42: 1399
B43: LOW | C43: 458 | D43: 494 | E43: 593 | F43: 685 | G43: 765 | H43: 843 | I43: 922
B44: HIGH | C44: 458 | D44: 555 | E44: 704 | F44: 857 | G44: 936 | H44: 1015 | I44: 1093
A46: Crook | B46: FMR | C46: 451 | D46: 580 | E46: 694 | F46: 939 | G46: 1099 | H46: 1264 | I46: 1429
B47: LOW | C47: 451 | D47: 508 | E47: 610 | F47: 705 | G47: 786 | H47: 868 | I47: 948
B48: HIGH | C48: 451 | D48: 580 | E48: 694 | F48: 883 | G48: 965 | H48: 1047 | I48: 1128
A50: Curry | B50: FMR | C50: 517 | D50: 595 | E50: 702 | F50: 1026 | G50: 1238 | H50: 1424 | I50: 1609
B51: LOW | C51: 465 | D51: 498 | E51: 597 | F51: 690 | G51: 770 | H51: 850 | I51: 929
B52: HIGH | C52: 517 | D52: 595 | E52: 702 | F52: 864 | G52: 944 | H52: 1022 | I52: 1102
A54: Douglas | B54: FMR | C54: 447 | D54: 532 | E54: 687 | F54: 932 | G54: 1153 | H54: 1326 | I54: 1499
B55: LOW | C55: 447 | D55: 494 | E55: 593 | F55: 685 | G55: 765 | H55: 843 | I55: 922
B56: HIGH | C56: 447 | D56: 532 | E56: 687 | F56: 857 | G56: 936 | H56: 1015 | I56: 1093
A58: Gilliam | B58: FMR | C58: 485 | D58: 568 | E58: 686 | F58: 930 | G58: 1087 | H58: 1250 | I58: 1413
B59: LOW | C59: 471 | D59: 505 | E59: 606 | F59: 700 | G59: 781 | H59: 861 | I59: 941
B60: HIGH | C60: 485 | D60: 568 | E60: 686 | F60: 875 | G60: 956 | H60: 1037 | I60: 1117
A62: Grant | B62: FMR | C62: 485 | D62: 568 | E62: 686 | F62: 930 | G62: 1087 | H62: 1250 | I62: 1413
B63: LOW | C63: 461 | D63: 494 | E63: 593 | F63: 685 | G63: 765 | H63: 843 | I63: 922
B64: HIGH | C64: 485 | D64: 568 | E64: 686 | F64: 857 | G64: 936 | H64: 1015 | I64: 1093
A66: Harney | B66: FMR | C66: 434 | D66: 505 | E66: 635 | F66: 878 | G66: 933 | H66: 1073 | I66: 1213
B67: LOW | C67: 434 | D67: 494 | E67: 593 | F67: 685 | G67: 765 | H67: 843 | I67: 922
B68: HIGH | C68: 434 | D68: 505 | E68: 635 | F68: 857 | G68: 933 | H68: 1015 | I68: 1093
A70: Hood River | B70: FMR | C70: 487 | D70: 602 | E70: 750 | F70: 1067 | G70: 1101 | H70: 1266 | I70: 1431
B71: LOW | C71: 483 | D71: 518 | E71: 621 | F71: 718 | G71: 801 | H71: 883 | I71: 966
B72: HIGH | C72: 487 | D72: 602 | E72: 750 | F72: 900 | G72: 984 | H72: 1067 | I72: 1151
A74: Jefferson | B74: FMR | C74: 538 | D74: 573 | E74: 649 | F74: 944 | G74: 1062 | H74: 1221 | I74: 1381
B75: LOW | C75: 461 | D75: 494 | E75: 593 | F75: 685 | G75: 765 | H75: 843 | I75: 922
B76: HIGH | C76: 538 | D76: 573 | E76: 649 | F76: 857 | G76: 936 | H76: 1015 | I76: 1093
A78: Josephine | B78: FMR | C78: 521 | D78: 597 | E78: 722 | F78: 1027 | G78: 1139 | H78: 1310 | I78: 1481
B79: LOW | C79: 461 | D79: 494 | E79: 593 | F79: 685 | G79: 765 | H79: 843 | I79: 922
B80: HIGH | C80: 521 | D80: 597 | E80: 722 | F80: 857 | G80: 936 | H80: 1015 | I80: 1093
A82: Klamath | B82: FMR | C82: 432 | D82: 506 | E82: 645 | F82: 902 | G82: 1002 | H82: 1152 | I82: 1303
B83: LOW | C83: 432 | D83: 503 | E83: 603 | F83: 696 | G83: 777 | H83: 858 | I83: 938
B84: HIGH | C84: 432 | D84: 506 | E84: 645 | F84: 872 | G84: 954 | H84: 1034 | I84: 1114
A86: Lake | B86: FMR | C86: 434 | D86: 505 | E86: 635 | F86: 878 | G86: 933 | H86: 1073 | I86: 1213
B87: LOW | C87: 434 | D87: 494 | E87: 593 | F87: 685 | G87: 765 | H87: 843 | I87: 922
B88: HIGH | C88: 434 | D88: 505 | E88: 635 | F88: 857 | G88: 933 | H88: 1015 | I88: 1093
A90: Lincoln | B90: FMR | C90: 538 | D90: 614 | E90: 783 | F90: 1085 | G90: 1225 | H90: 1409 | I90: 1593
B91: LOW | C91: 465 | D91: 498 | E91: 597 | F91: 690 | G91: 770 | H91: 850 | I91: 929
B92: HIGH | C92: 538 | D92: 614 | E92: 754 | F92: 864 | G92: 944 | H92: 1022 | I92: 1102
A94: Linn | B94: FMR | C94: 514 | D94: 623 | E94: 777 | F94: 1071 | G94: 1326 | H94: 1525 | I94: 1724
B95: LOW | C95: 507 | D95: 543 | E95: 652 | F95: 753 | G95: 840 | H95: 926 | I95: 1013
B96: HIGH | C96: 514 | D96: 623 | E96: 777 | F96: 945 | G96: 1035 | H96: 1123 | I96: 1212
A98: Malheur | B98: FMR | C98: 459 | D98: 524 | E98: 638 | F98: 923 | G98: 949 | H98: 1091 | I98: 1234
B99: LOW | C99: 459 | D99: 494 | E99: 593 | F99: 685 | G99: 765 | H99: 843 | I99: 922
B100: HIGH | C100: 459 | D100: 524 | E100: 638 | F100: 857 | G100: 936 | H100: 1015 | I100: 1093
A102: Morrow | B102: FMR | C102: 485 | D102: 568 | E102: 686 | F102: 930 | G102: 1087 | H102: 1250 | I102: 1413
B103: LOW | C103: 461 | D103: 494 | E103: 593 | F103: 685 | G103: 765 | H103: 843 | I103: 922
B104: HIGH | C104: 485 | D104: 568 | E104: 686 | F104: 857 | G104: 936 | H104: 1015 | I104: 1093
A106: Sherman | B106: FMR | C106: 485 | D106: 568 | E106: 686 | F106: 930 | G106: 1087 | H106: 1250 | I106: 1413
B107: LOW | C107: 470 | D107: 506 | E107: 607 | F107: 701 | G107: 782 | H107: 863 | I107: 943
B108: HIGH | C108: 485 | D108: 568 | E108: 686 | F108: 878 | G108: 960 | H108: 1041 | I108: 1121
A110: Tillamook | B110: FMR | C110: 498 | D110: 595 | E110: 765 | F110: 1069 | G110: 1102 | H110: 1267 | I110: 1433
B111: LOW | C111: 468 | D111: 501 | E111: 602 | F111: 695 | G111: 776 | H111: 856 | I111: 936
B112: HIGH | C112: 498 | D112: 595 | E112: 762 | F112: 871 | G112: 953 | H112: 1032 | I112: 1112
A114: Umatilla | B114: FMR | C114: 450 | D114: 513 | E114: 656 | F114: 921 | G114: 1027 | H114: 1181 | I114: 1335
B115: LOW | C115: 450 | D115: 510 | E115: 612 | F115: 707 | G115: 790 | H115: 871 | I115: 952
B116: HIGH | C116: 450 | D116: 513 | E116: 656 | F116: 885 | G116: 969 | H116: 1050 | I116: 1131
A118: Union | B118: FMR | C118: 430 | D118: 501 | E118: 661 | F118: 964 | G118: 992 | H118: 1141 | I118: 1290
B119: LOW | C119: 430 | D119: 501 | E119: 625 | F119: 721 | G119: 805 | H119: 888 | I119: 971
B120: HIGH | C120: 430 | D120: 501 | E120: 661 | F120: 905 | G120: 990 | H120: 1074 | I120: 1158
A122: Wallowa | B122: FMR | C122: 426 | D122: 496 | E122: 655 | F122: 937 | G122: 1007 | H122: 1158 | I122: 1309
B123: LOW | C123: 426 | D123: 496 | E123: 597 | F123: 690 | G123: 770 | H123: 850 | I123: 929
B124: HIGH | C124: 426 | D124: 496 | E124: 655 | F124: 864 | G124: 944 | H124: 1022 | I124: 1102
A126: Wasco | B126: FMR | C126: 499 | D126: 559 | E126: 696 | F126: 989 | G126: 1224 | H126: 1408 | I126: 1591
B127: LOW | C127: 470 | D127: 503 | E127: 603 | F127: 696 | G127: 777 | H127: 858 | I127: 938
B128: HIGH | C128: 499 | D128: 559 | E128: 696 | F128: 872 | G128: 954 | H128: 1034 | I128: 1114
A130: Wheeler | B130: FMR | C130: 485 | D130: 568 | E130: 686 | F130: 930 | G130: 1087 | H130: 1250 | I130: 1413
B131: LOW | C131: 461 | D131: 494 | E131: 593 | F131: 685 | G131: 765 | H131: 843 | I131: 922
B132: HIGH | C132: 485 | D132: 568 | E132: 686 | F132: 857 | G132: 936 | H132: 1015 | I132: 1093

Sheet HOMEIncomes11
A1: OREGON HOUSING AND COMMUNITY SERVICES
A2: 2011 INCOME LIMITS
A3: for the HOME Investment Partnership Program
B5: Based on HUD's published Section 8 income limits
B6: Median incomes by county (effective: May 31, 2011)
B7: Section 8 income limits by county (or non-PMSA average if greater)
A9: MSA / County | B9: % MFI | C9: 1 Pers | D9: 2 Pers | E9: 3 Pers | F9: 4 Pers | G9: 5 Pers | H9: 6 Pers | I9: 7 Pers | J9: 8 Pers
A11: Deschutes | B11: 0.3 | C11: 13800 | D11: 15750 | E11: 17700 | F11: 19650 | G11: 21250 | H11: 22800 | I11: 24400 | J11: 25950
B12: 0.4 | C12: =(+C13*2)*0.4 -> 18360 | D12: =(+D13*2)*0.4 -> 20960 | E12: =(+E13*2)*0.4 -> 23600 | F12: =(+F13*2)*0.4 -> 26200 | G12: =(+G13*2)*0.4 -> 28320 | H12: =(+H13*2)*0.4 -> 30400 | I12: =(+I13*2)*0.4 -> 32520 | J12: =(+J13*2)*0.4 -> 34600
B13: 0.5 | C13: 22950 | D13: 26200 | E13: 29500 | F13: 32750 | G13: 35400 | H13: 38000 | I13: 40650 | J13: 43250
B14: 0.6 | C14: =(+C13*2)*0.6 -> 27540 | D14: =(+D13*2)*0.6 -> 31440 | E14: =(+E13*2)*0.6 -> 35400 | F14: =(+F13*2)*0.6 -> 39300 | G14: =(+G13*2)*0.6 -> 42480 | H14: =(+H13*2)*0.6 -> 45600 | I14: =(+I13*2)*0.6 -> 48780 | J14: =(+J13*2)*0.6 -> 51900
B15: 0.8 | C15: 36700 | D15: 41950 | E15: 47200 | F15: 52400 | G15: 56600 | H15: 60800 | I15: 65000 | J15: 69200
A17: Benton | B17: 0.3 | C17: 15400 | D17: 17600 | E17: 19800 | F17: 21950 | G17: 23750 | H17: 25500 | I17: 27250 | J17: 29000
B18: 0.4 | C18: =(+C19*2)*0.4 -> 20520 | D18: =(+D19*2)*0.4 -> 23440 | E18: =(+E19*2)*0.4 -> 26360 | F18: =(+F19*2)*0.4 -> 29280 | G18: =(+G19*2)*0.4 -> 31640 | H18: =(+H19*2)*0.4 -> 34000 | I18: =(+I19*2)*0.4 -> 36320 | J18: =(+J19*2)*0.4 -> 38680
B19: 0.5 | C19: 25650 | D19: 29300 | E19: 32950 | F19: 36600 | G19: 39550 | H19: 42500 | I19: 45400 | J19: 48350
B20: 0.6 | C20: =(+C19*2)*0.6 -> 30780 | D20: =(+D19*2)*0.6 -> 35160 | E20: =(+E19*2)*0.6 -> 39540 | F20: =(+F19*2)*0.6 -> 43920 | G20: =(+G19*2)*0.6 -> 47460 | H20: =(+H19*2)*0.6 -> 51000 | I20: =(+I19*2)*0.6 -> 54480 | J20: =(+J19*2)*0.6 -> 58020
B21: 0.8 | C21: 41000 | D21: 46850 | E21: 52700 | F21: 58550 | G21: 63250 | H21: 67950 | I21: 72650 | J21: 77300
A23: Lane | B23: 0.3 | C23: 12250 | D23: 14000 | E23: 15750 | F23: 17500 | G23: 18900 | H23: 20300 | I23: 21700 | J23: 23100
B24: 0.4 | C24: =(+C25*2)*0.4 -> 16360 | D24: =(+D25*2)*0.4 -> 18720 | E24: =(+E25*2)*0.4 -> 21040 | F24: =(+F25*2)*0.4 -> 23360 | G24: =(+G25*2)*0.4 -> 25240 | H24: =(+H25*2)*0.4 -> 27120 | I24: =(+I25*2)*0.4 -> 29000 | J24: =(+J25*2)*0.4 -> 30840
B25: 0.5 | C25: 20450 | D25: 23400 | E25: 26300 | F25: 29200 | G25: 31550 | H25: 33900 | I25: 36250 | J25: 38550
B26: 0.6 | C26: =(+C25*2)*0.6 -> 24540 | D26: =(+D25*2)*0.6 -> 28080 | E26: =(+E25*2)*0.6 -> 31560 | F26: =(+F25*2)*0.6 -> 35040 | G26: =(+G25*2)*0.6 -> 37860 | H26: =(+H25*2)*0.6 -> 40680 | I26: =(+I25*2)*0.6 -> 43500 | J26: =(+J25*2)*0.6 -> 46260
B27: 0.8 | C27: 32700 | D27: 37400 | E27: 42050 | F27: 46700 | G27: 50450 | H27: 54200 | I27: 57950 | J27: 61650
A29: Jackson | B29: 0.3 | C29: 12150 | D29: 13850 | E29: 15600 | F29: 17300 | G29: 18700 | H29: 20100 | I29: 21500 | J29: 22850
B30: 0.4 | C30: =(+C31*2)*0.4 -> 16160 | D30: =(+D31*2)*0.4 -> 18480 | E30: =(+E31*2)*0.4 -> 20800 | F30: =(+F31*2)*0.4 -> 23080 | G30: =(+G31*2)*0.4 -> 24960 | H30: =(+H31*2)*0.4 -> 26800 | I30: =(+I31*2)*0.4 -> 28640 | J30: =(+J31*2)*0.4 -> 30480
B31: 0.5 | C31: 20200 | D31: 23100 | E31: 26000 | F31: 28850 | G31: 31200 | H31: 33500 | I31: 35800 | J31: 38100
B32: 0.6 | C32: =(+C31*2)*0.6 -> 24240 | D32: =(+D31*2)*0.6 -> 27720 | E32: =(+E31*2)*0.6 -> 31200 | F32: =(+F31*2)*0.6 -> 34620 | G32: =(+G31*2)*0.6 -> 37440 | H32: =(+H31*2)*0.6 -> 40200 | I32: =(+I31*2)*0.6 -> 42960 | J32: =(+J31*2)*0.6 -> 45720
B33: 0.8 | C33: 32350 | D33: 36950 | E33: 41550 | F33: 46150 | G33: 49850 | H33: 53550 | I33: 57250 | J33: 60950
A35: Clackamas | B35: 0.3 | C35: 15150 | D35: 17300 | E35: 19450 | F35: 21600 | G35: 23350 | H35: 25100 | I35: 26800 | J35: 28550
A36: Columbia | B36: 0.4 | C36: =(+C37*2)*0.4 -> 20160 | D36: =(+D37*2)*0.4 -> 23040 | E36: =(+E37*2)*0.4 -> 25920 | F36: =(+F37*2)*0.4 -> 28800 | G36: =(+G37*2)*0.4 -> 31120 | H36: =(+H37*2)*0.4 -> 33440 | I36: =(+I37*2)*0.4 -> 35720 | J36: =(+J37*2)*0.4 -> 38040
A37: Multnomah | B37: 0.5 | C37: 25200 | D37: 28800 | E37: 32400 | F37: 36000 | G37: 38900 | H37: 41800 | I37: 44650 | J37: 47550
A38: Washington | B38: 0.6 | C38: =(+C37*2)*0.6 -> 30240 | D38: =(+D37*2)*0.6 -> 34560 | E38: =(+E37*2)*0.6 -> 38880 | F38: =(+F37*2)*0.6 -> 43200 | G38: =(+G37*2)*0.6 -> 46680 | H38: =(+H37*2)*0.6 -> 50160 | I38: =(+I37*2)*0.6 -> 53580 | J38: =(+J37*2)*0.6 -> 57060
A39: & Yamhill | B39: 0.8 | C39: 40350 | D39: 46100 | E39: 51850 | F39: 57600 | G39: 62250 | H39: 66850 | I39: 71450 | J39: 76050
A41: Marion & Polk | B41: 0.3 | C41: 12450 | D41: 14200 | E41: 16000 | F41: 17750 | G41: 19200 | H41: 20600 | I41: 22050 | J41: 23450
B42: 0.4 | C42: =(+C43*2)*0.4 -> 16600 | D42: =(+D43*2)*0.4 -> 18960 | E42: =(+E43*2)*0.4 -> 21320 | F42: =(+F43*2)*0.4 -> 23680 | G42: =(+G43*2)*0.4 -> 25600 | H42: =(+H43*2)*0.4 -> 27480 | I42: =(+I43*2)*0.4 -> 29400 | J42: =(+J43*2)*0.4 -> 31280
B43: 0.5 | C43: 20750 | D43: 23700 | E43: 26650 | F43: 29600 | G43: 32000 | H43: 34350 | I43: 36750 | J43: 39100
B44: 0.6 | C44: =(+C43*2)*0.6 -> 24900 | D44: =(+D43*2)*0.6 -> 28440 | E44: =(+E43*2)*0.6 -> 31980 | F44: =(+F43*2)*0.6 -> 35520 | G44: =(+G43*2)*0.6 -> 38400 | H44: =(+H43*2)*0.6 -> 41220 | I44: =(+I43*2)*0.6 -> 44100 | J44: =(+J43*2)*0.6 -> 46920
B45: 0.8 | C45: 33150 | D45: 37900 | E45: 42650 | F45: 47350 | G45: 51150 | H45: 54950 | I45: 58750 | J45: 62550
A47: Baker | B47: 0.3 | C47: 11100 | D47: 12650 | E47: 14250 | F47: 15800 | G47: 17100 | H47: 18350 | I47: 19600 | J47: 20900
B48: 0.4 | C48: =(+C49*2)*0.4 -> 14760 | D48: =(+D49*2)*0.4 -> 16880 | E48: =(+E49*2)*0.4 -> 19000 | F48: =(+F49*2)*0.4 -> 21080 | G48: =(+G49*2)*0.4 -> 22800 | H48: =(+H49*2)*0.4 -> 24480 | I48: =(+I49*2)*0.4 -> 26160 | J48: =(+J49*2)*0.4 -> 27840
B49: 0.5 | C49: 18450 | D49: 21100 | E49: 23750 | F49: 26350 | G49: 28500 | H49: 30600 | I49: 32700 | J49: 34800
B50: 0.6 | C50: =(+C49*2)*0.6 -> 22140 | D50: =(+D49*2)*0.6 -> 25320 | E50: =(+E49*2)*0.6 -> 28500 | F50: =(+F49*2)*0.6 -> 31620 | G50: =(+G49*2)*0.6 -> 34200 | H50: =(+H49*2)*0.6 -> 36720 | I50: =(+I49*2)*0.6 -> 39240 | J50: =(+J49*2)*0.6 -> 41760
B51: 0.8 | C51: 29550 | D51: 33750 | E51: 37950 | F51: 42150 | G51: 45550 | H51: 48900 | I51: 52300 | J51: 55650
A53: MSA / County | B53: % of MFI | C53: 1 Pers | D53: 2 Pers | E53: 3 Pers | F53: 4 Pers | G53: 5 Pers | H53: 6 Pers | I53: 7 Pers | J53: 8 Pers
A55: Clatsop | B55: 0.3 | C55: 11750 | D55: 13400 | E55: 15100 | F55: 16750 | G55: 18100 | H55: 19450 | I55: 20800 | J55: 22150
B56: 0.4 | C56: =(+C57*2)*0.4 -> 15680 | D56: =(+D57*2)*0.4 -> 17920 | E56: =(+E57*2)*0.4 -> 20160 | F56: =(+F57*2)*0.4 -> 22360 | G56: =(+G57*2)*0.4 -> 24160 | H56: =(+H57*2)*0.4 -> 25960 | I56: =(+I57*2)*0.4 -> 27760 | J56: =(+J57*2)*0.4 -> 29520
B57: 0.5 | C57: 19600 | D57: 22400 | E57: 25200 | F57: 27950 | G57: 30200 | H57: 32450 | I57: 34700 | J57: 36900
B58: 0.6 | C58: =(+C57*2)*0.6 -> 23520 | D58: =(+D57*2)*0.6 -> 26880 | E58: =(+E57*2)*0.6 -> 30240 | F58: =(+F57*2)*0.6 -> 33540 | G58: =(+G57*2)*0.6 -> 36240 | H58: =(+H57*2)*0.6 -> 38940 | I58: =(+I57*2)*0.6 -> 41640 | J58: =(+J57*2)*0.6 -> 44280
B59: 0.8 | C59: 31300 | D59: 35800 | E59: 40250 | F59: 44700 | G59: 48300 | H59: 51900 | I59: 55450 | J59: 59050
A61: Coos | B61: 0.3 | C61: 11100 | D61: 12650 | E61: 14250 | F61: 15800 | G61: 17100 | H61: 18350 | I61: 19600 | J61: 20900
B62: 0.4 | C62: =(+C63*2)*0.4 -> 14760 | D62: =(+D63*2)*0.4 -> 16880 | E62: =(+E63*2)*0.4 -> 19000 | F62: =(+F63*2)*0.4 -> 21080 | G62: =(+G63*2)*0.4 -> 22800 | H62: =(+H63*2)*0.4 -> 24480 | I62: =(+I63*2)*0.4 -> 26160 | J62: =(+J63*2)*0.4 -> 27840
B63: 0.5 | C63: 18450 | D63: 21100 | E63: 23750 | F63: 26350 | G63: 28500 | H63: 30600 | I63: 32700 | J63: 34800
B64: 0.6 | C64: =(+C63*2)*0.6 -> 22140 | D64: =(+D63*2)*0.6 -> 25320 | E64: =(+E63*2)*0.6 -> 28500 | F64: =(+F63*2)*0.6 -> 31620 | G64: =(+G63*2)*0.6 -> 34200 | H64: =(+H63*2)*0.6 -> 36720 | I64: =(+I63*2)*0.6 -> 39240 | J64: =(+J63*2)*0.6 -> 41760
B65: 0.8 | C65: 29550 | D65: 33750 | E65: 37950 | F65: 42150 | G65: 45550 | H65: 48900 | I65: 52300 | J65: 55650
A67: Crook | B67: 0.3 | C67: 11400 | D67: 13000 | E67: 14650 | F67: 16250 | G67: 17550 | H67: 18850 | I67: 20150 | J67: 21450
B68: 0.4 | C68: =(+C69*2)*0.4 -> 15200 | D68: =(+D69*2)*0.4 -> 17360 | E68: =(+E69*2)*0.4 -> 19520 | F68: =(+F69*2)*0.4 -> 21680 | G68: =(+G69*2)*0.4 -> 23440 | H68: =(+H69*2)*0.4 -> 25160 | I68: =(+I69*2)*0.4 -> 26920 | J68: =(+J69*2)*0.4 -> 28640
B69: 0.5 | C69: 19000 | D69: 21700 | E69: 24400 | F69: 27100 | G69: 29300 | H69: 31450 | I69: 33650 | J69: 35800
B70: 0.6 | C70: =(+C69*2)*0.6 -> 22800 | D70: =(+D69*2)*0.6 -> 26040 | E70: =(+E69*2)*0.6 -> 29280 | F70: =(+F69*2)*0.6 -> 32520 | G70: =(+G69*2)*0.6 -> 35160 | H70: =(+H69*2)*0.6 -> 37740 | I70: =(+I69*2)*0.6 -> 40380 | J70: =(+J69*2)*0.6 -> 42960
B71: 0.8 | C71: 30350 | D71: 34700 | E71: 39050 | F71: 43350 | G71: 46850 | H71: 50300 | I71: 53800 | J71: 57250
A73: Curry | B73: 0.3 | C73: 11200 | D73: 12800 | E73: 14400 | F73: 15950 | G73: 17250 | H73: 18550 | I73: 19800 | J73: 21100
B74: 0.4 | C74: =(+C75*2)*0.4 -> 14880 | D74: =(+D75*2)*0.4 -> 17000 | E74: =(+E75*2)*0.4 -> 19120 | F74: =(+F75*2)*0.4 -> 21240 | G74: =(+G75*2)*0.4 -> 22960 | H74: =(+H75*2)*0.4 -> 24640 | I74: =(+I75*2)*0.4 -> 26360 | J74: =(+J75*2)*0.4 -> 28040
B75: 0.5 | C75: 18600 | D75: 21250 | E75: 23900 | F75: 26550 | G75: 28700 | H75: 30800 | I75: 32950 | J75: 35050
B76: 0.6 | C76: =(+C75*2)*0.6 -> 22320 | D76: =(+D75*2)*0.6 -> 25500 | E76: =(+E75*2)*0.6 -> 28680 | F76: =(+F75*2)*0.6 -> 31860 | G76: =(+G75*2)*0.6 -> 34440 | H76: =(+H75*2)*0.6 -> 36960 | I76: =(+I75*2)*0.6 -> 39540 | J76: =(+J75*2)*0.6 -> 42060
B77: 0.8 | C77: 29750 | D77: 34000 | E77: 38250 | F77: 42500 | G77: 45900 | H77: 49300 | I77: 52700 | J77: 56100
A79: Douglas | B79: 0.3 | C79: 11100 | D79: 12650 | E79: 14250 | F79: 15800 | G79: 17100 | H79: 18350 | I79: 19600 | J79: 20900
B80: 0.4 | C80: =(+C81*2)*0.4 -> 14760 | D80: =(+D81*2)*0.4 -> 16880 | E80: =(+E81*2)*0.4 -> 19000 | F80: =(+F81*2)*0.4 -> 21080 | G80: =(+G81*2)*0.4 -> 22800 | H80: =(+H81*2)*0.4 -> 24480 | I80: =(+I81*2)*0.4 -> 26160 | J80: =(+J81*2)*0.4 -> 27840
B81: 0.5 | C81: 18450 | D81: 21100 | E81: 23750 | F81: 26350 | G81: 28500 | H81: 30600 | I81: 32700 | J81: 34800
B82: 0.6 | C82: =(+C81*2)*0.6 -> 22140 | D82: =(+D81*2)*0.6 -> 25320 | E82: =(+E81*2)*0.6 -> 28500 | F82: =(+F81*2)*0.6 -> 31620 | G82: =(+G81*2)*0.6 -> 34200 | H82: =(+H81*2)*0.6 -> 36720 | I82: =(+I81*2)*0.6 -> 39240 | J82: =(+J81*2)*0.6 -> 41760
B83: 0.8 | C83: 29550 | D83: 33750 | E83: 37950 | F83: 42150 | G83: 45550 | H83: 48900 | I83: 52300 | J83: 55650
A85: Gilliam | B85: 0.3 | C85: 11350 | D85: 12950 | E85: 14550 | F85: 16150 | G85: 17450 | H85: 18750 | I85: 20050 | J85: 21350
B86: 0.4 | C86: =(+C87*2)*0.4 -> 15080 | D86: =(+D87*2)*0.4 -> 17240 | E86: =(+E87*2)*0.4 -> 19400 | F86: =(+F87*2)*0.4 -> 21520 | G86: =(+G87*2)*0.4 -> 23280 | H86: =(+H87*2)*0.4 -> 25000 | I86: =(+I87*2)*0.4 -> 26720 | J86: =(+J87*2)*0.4 -> 28440
B87: 0.5 | C87: 18850 | D87: 21550 | E87: 24250 | F87: 26900 | G87: 29100 | H87: 31250 | I87: 33400 | J87: 35550
B88: 0.6 | C88: =(+C87*2)*0.6 -> 22620 | D88: =(+D87*2)*0.6 -> 25860 | E88: =(+E87*2)*0.6 -> 29100 | F88: =(+F87*2)*0.6 -> 32280 | G88: =(+G87*2)*0.6 -> 34920 | H88: =(+H87*2)*0.6 -> 37500 | I88: =(+I87*2)*0.6 -> 40080 | J88: =(+J87*2)*0.6 -> 42660
B89: 0.8 | C89: 30150 | D89: 34450 | E89: 38750 | F89: 43050 | G89: 46500 | H89: 49950 | I89: 53400 | J89: 56850
A91: Grant | B91: 0.3 | C91: 11100 | D91: 12650 | E91: 14250 | F91: 15800 | G91: 17100 | H91: 18350 | I91: 19600 | J91: 20900
B92: 0.4 | C92: =(+C93*2)*0.4 -> 14760 | D92: =(+D93*2)*0.4 -> 16880 | E92: =(+E93*2)*0.4 -> 19000 | F92: =(+F93*2)*0.4 -> 21080 | G92: =(+G93*2)*0.4 -> 22800 | H92: =(+H93*2)*0.4 -> 24480 | I92: =(+I93*2)*0.4 -> 26160 | J92: =(+J93*2)*0.4 -> 27840
B93: 0.5 | C93: 18450 | D93: 21100 | E93: 23750 | F93: 26350 | G93: 28500 | H93: 30600 | I93: 32700 | J93: 34800
B94: 0.6 | C94: =(+C93*2)*0.6 -> 22140 | D94: =(+D93*2)*0.6 -> 25320 | E94: =(+E93*2)*0.6 -> 28500 | F94: =(+F93*2)*0.6 -> 31620 | G94: =(+G93*2)*0.6 -> 34200 | H94: =(+H93*2)*0.6 -> 36720 | I94: =(+I93*2)*0.6 -> 39240 | J94: =(+J93*2)*0.6 -> 41760
B95: 0.8 | C95: 29550 | D95: 33750 | E95: 37950 | F95: 42150 | G95: 45550 | H95: 48900 | I95: 52300 | J95: 55650
A97: Harney | B97: 0.3 | C97: 11100 | D97: 12650 | E97: 14250 | F97: 15800 | G97: 17100 | H97: 18350 | I97: 19600 | J97: 20900
B98: 0.4 | C98: =(+C99*2)*0.4 -> 14760 | D98: =(+D99*2)*0.4 -> 16880 | E98: =(+E99*2)*0.4 -> 19000 | F98: =(+F99*2)*0.4 -> 21080 | G98: =(+G99*2)*0.4 -> 22800 | H98: =(+H99*2)*0.4 -> 24480 | I98: =(+I99*2)*0.4 -> 26160 | J98: =(+J99*2)*0.4 -> 27840
B99: 0.5 | C99: 18450 | D99: 21100 | E99: 23750 | F99: 26350 | G99: 28500 | H99: 30600 | I99: 32700 | J99: 34800
B100: 0.6 | C100: =(+C99*2)*0.6 -> 22140 | D100: =(+D99*2)*0.6 -> 25320 | E100: =(+E99*2)*0.6 -> 28500 | F100: =(+F99*2)*0.6 -> 31620 | G100: =(+G99*2)*0.6 -> 34200 | H100: =(+H99*2)*0.6 -> 36720 | I100: =(+I99*2)*0.6 -> 39240 | J100: =(+J99*2)*0.6 -> 41760
B101: 0.8 | C101: 29550 | D101: 33750 | E101: 37950 | F101: 42150 | G101: 45550 | H101: 48900 | I101: 52300 | J101: 55650
A104: MSA / County | B104: % of MFI | C104: 1 Pers | D104: 2 Pers | E104: 3 Pers | F104: 4 Pers | G104: 5 Pers | H104: 6 Pers | I104: 7 Pers | J104: 8 Pers
A106: Hood River | B106: 0.3 | C106: 11600 | D106: 13250 | E106: 14900 | F106: 16550 | G106: 17900 | H106: 19200 | I106: 20550 | J106: 21850
B107: 0.4 | C107: =(+C108*2)*0.4 -> 15480 | D107: =(+D108*2)*0.4 -> 17680 | E107: =(+E108*2)*0.4 -> 19880 | F107: =(+F108*2)*0.4 -> 22080 | G107: =(+G108*2)*0.4 -> 23880 | H107: =(+H108*2)*0.4 -> 25640 | I107: =(+I108*2)*0.4 -> 27400 | J107: =(+J108*2)*0.4 -> 29160
B108: 0.5 | C108: 19350 | D108: 22100 | E108: 24850 | F108: 27600 | G108: 29850 | H108: 32050 | I108: 34250 | J108: 36450
B109: 0.6 | C109: =(+C108*2)*0.6 -> 23220 | D109: =(+D108*2)*0.6 -> 26520 | E109: =(+E108*2)*0.6 -> 29820 | F109: =(+F108*2)*0.6 -> 33120 | G109: =(+G108*2)*0.6 -> 35820 | H109: =(+H108*2)*0.6 -> 38460 | I109: =(+I108*2)*0.6 -> 41100 | J109: =(+J108*2)*0.6 -> 43740
B110: 0.8 | C110: 30950 | D110: 35350 | E110: 39750 | F110: 44150 | G110: 47700 | H110: 51250 | I110: 54750 | J110: 58300
A112: Jefferson | B112: 0.3 | C112: 11100 | D112: 12650 | E112: 14250 | F112: 15800 | G112: 17100 | H112: 18350 | I112: 19600 | J112: 20900
B113: 0.4 | C113: =(+C114*2)*0.4 -> 14760 | D113: =(+D114*2)*0.4 -> 16880 | E113: =(+E114*2)*0.4 -> 19000 | F113: =(+F114*2)*0.4 -> 21080 | G113: =(+G114*2)*0.4 -> 22800 | H113: =(+H114*2)*0.4 -> 24480 | I113: =(+I114*2)*0.4 -> 26160 | J113: =(+J114*2)*0.4 -> 27840
B114: 0.5 | C114: 18450 | D114: 21100 | E114: 23750 | F114: 26350 | G114: 28500 | H114: 30600 | I114: 32700 | J114: 34800
B115: 0.6 | C115: =(+C114*2)*0.6 -> 22140 | D115: =(+D114*2)*0.6 -> 25320 | E115: =(+E114*2)*0.6 -> 28500 | F115: =(+F114*2)*0.6 -> 31620 | G115: =(+G114*2)*0.6 -> 34200 | H115: =(+H114*2)*0.6 -> 36720 | I115: =(+I114*2)*0.6 -> 39240 | J115: =(+J114*2)*0.6 -> 41760
B116: 0.8 | C116: 29550 | D116: 33750 | E116: 37950 | F116: 42150 | G116: 45550 | H116: 48900 | I116: 52300 | J116: 55650
A118: Josephine | B118: 0.3 | C118: 11100 | D118: 12650 | E118: 14250 | F118: 15800 | G118: 17100 | H118: 18350 | I118: 19600 | J118: 20900
B119: 0.4 | C119: =(+C120*2)*0.4 -> 14760 | D119: =(+D120*2)*0.4 -> 16880 | E119: =(+E120*2)*0.4 -> 19000 | F119: =(+F120*2)*0.4 -> 21080 | G119: =(+G120*2)*0.4 -> 22800 | H119: =(+H120*2)*0.4 -> 24480 | I119: =(+I120*2)*0.4 -> 26160 | J119: =(+J120*2)*0.4 -> 27840
B120: 0.5 | C120: 18450 | D120: 21100 | E120: 23750 | F120: 26350 | G120: 28500 | H120: 30600 | I120: 32700 | J120: 34800
B121: 0.6 | C121: =(+C120*2)*0.6 -> 22140 | D121: =(+D120*2)*0.6 -> 25320 | E121: =(+E120*2)*0.6 -> 28500 | F121: =(+F120*2)*0.6 -> 31620 | G121: =(+G120*2)*0.6 -> 34200 | H121: =(+H120*2)*0.6 -> 36720 | I121: =(+I120*2)*0.6 -> 39240 | J121: =(+J120*2)*0.6 -> 41760
B122: 0.8 | C122: 29550 | D122: 33750 | E122: 37950 | F122: 42150 | G122: 45550 | H122: 48900 | I122: 52300 | J122: 55650
A124: Klamath | B124: 0.3 | C124: 11300 | D124: 12900 | E124: 14500 | F124: 16100 | G124: 17400 | H124: 18700 | I124: 20000 | J124: 21300
...
