Workbook

Sheet Worksheet Instructions
B2: Charter School Funding -- Inequity Persists
B3: May 2010
B5: Supporting Excel Spreadsheet
B6: Worksheet Legend and Instructions
B7: South Carolina
B9: Data Source:
B10: District revenue data (inclusive of inseparable charter school revenue data) was downloaded from the South Carolina Department of Education (SCDE) FTP site – the download file name: “07-distrev.xls.” This file contains sufficient revenue account coding to identify sources of revenues. Charter school revenue data was not available from SCDE. Charter school revenue data was obtained from audited Annual Financial Reports, which were downloaded from school district web sites (these are also available in paper at SCDE). Charter revenue data were subtracted from the “district” revenue data to arrive at comparable revenue data for district schools and charter schools. A “district” enrollment file was also downloaded – this file included inseparable district school and charter school enrollment. SCDE also provided an enrollment file just for charter schools. The charter school enrollments were subtracted from the “district” enrollment file in order to obtain separate district and charter school enrollment counts. Charter school revenue data could not be obtained for some charter schools, representing 24.8 percent of the total population of charter school students. An estimate was made of total statewide charter school revenues by taking the actual per pupil revenue amount from charter schools representing 76.2 percent of charter students, and applying that per pupil amount to the 24.8 percent of students with no associated revenue data, then adding the actual and extrapolated amounts together. The Meyer Center for Special Children, a Greenville charter school, was eliminated from the Greenville and statewide presentation of this analysis because it would distort the analysis. The Meyer Center, established in 1954, receives 83.4 percent of its funding through private contributions and donations, and has a per pupil revenue amount of $410,250.
B12: Disclaimer:
B13: This is a "read only" file containing data collections from the South Carolina Department of Education. The conclusions reached in this document are those of the author(s) and do not necessarily represent those of Ball State University.
B15: File Management:
B16: This is a "Final (Read-Only)" Excel file. This means you will not be able to edit this file, but you can copy whole worksheets, paste them into a new file (workbook), and then save that file under a different name. No "Protection" has been set for this file.
B18: Cautions:
B19: This spreadsheet was designed for use by the author/researcher, not for third-party use. Some of the data in this spreadsheet may be useful to third-parties, but any interpretations or additional analysis by third-parties is done so at their own risk.

Sheet Template
A1: Figure 1 | I1: Figure 2 | S1: TEMPLATE
A2: South Carolina 2006-2007 | B2: Statewide | D2: Greenville | F2: N/A
A3: Per-Pupil Revenue
A4: District | B4: =B22/B16 -> 10164.628 | D4: =D22/D16 -> 9331.7805
A5: Charter | B5: =C24/B18 -> 8396.0204 | D5: =D24/D18 -> 7464.5999
A6: Difference | B6: =B4-B5 -> 1768.6078 | D6: =D4-D5 -> 1867.1805
B7: =B6/B4 -> 0.17399631 | D7: =D6/D4 -> 0.20008835
A8: Per-Pupil Revenue by Source | B8: District | C8: Charter | D8: District | E8: Charter (3) | R8: PROOF
A9: Federal | B9: ='4-Districts Less Charters'!DI229/B16 -> 1014.4325 | C9: N/A (1) | D9: ='4-Districts Less Charters'!AY232/D16 -> 796.18153 | E9: ='5-Charters'!H101/D18 -> 918.71353 | R9: =SUM(B9:G9) -> 2729.3275
A10: State | B10: ='4-Districts Less Charters'!DI187/B16 -> 4295.0403 | C10: N/A (1) | D10: ='4-Districts Less Charters'!AY190/D16 -> 4078.1773 | E10: ='5-Charters'!H100/D18 -> 6025.4518 | R10: =SUM(B10:G10) -> 14398.669
A11: Local | B11: ='4-Districts Less Charters'!DI16/B16 -> 3922.8877 | C11: N/A (1) | D11: ='4-Districts Less Charters'!AY19/D16 -> 3430.5143 | E11: ='5-Charters'!H99/D18 -> 0 | R11: =SUM(B11:G11) -> 7353.4021
A12: Other | B12: ='4-Districts Less Charters'!DI58/B16 -> 932.26766 | C12: N/A (1) | D12: ='4-Districts Less Charters'!AY61/D16 -> 1026.9073 | E12: ='5-Charters'!H102/D18 -> 520.43464 | R12: =SUM(B12:G12) -> 2479.6096
A13: Indeterminate | B13: 0 | C13: N/A (1) | D13: ='4-Districts Less Charters'!AY235/D16 -> 0 | E13: 0 | R13: =SUM(B13:G13) -> 0
A14: Total | B14: =SUM(B9:B13) -> 10164.628 | C14: Est'd.(2) $8,396 | D14: =SUM(D9:D13) -> 9331.7805 | E14: =SUM(E9:E13) -> 7464.5999
A15: Enrollment
A16: District | B16: ='6-Enrollment'!P104 -> 676773.43 | D16: ='6-Enrollment'!R47 -> 65411.5
B17: =B16/(B16+B18) -> 0.99266054 | D17: =D16/(D16+D18) -> 0.98770851 | J17: District | K17: Charter | L17: Difference
A18: Charter | B18: ='5-Charters'!M34 -> 5003.88 | D18: ='5-Charters'!B98 -> 814.01 | I18: South Carolina | J18: =B4 -> 10164.628 | K18: =B5 -> 8396.0204 | L18: =B6 -> 1768.6078
B19: =B18/(B16+B18) -> 0.007339464 | D19: =D18/(D16+D18) -> 0.012291487 | I19: Greenville | J19: =D4 -> 9331.7805 | K19: =D5 -> 7464.5999 | L19: =D6 -> 1867.1805
A20: Number of Charters | B20: ='5-Charters'!L34 -> 28 | D20: 6
A21: Total Revenue
A22: District | B22: ='4-Districts Less Charters'!DI237 -> 6.8791503e+09 | D22: ='4-Districts Less Charters'!AY240 -> 610405757
B23: =B22/B26 -> 0.99392982 | D23: =D22/D26 -> 0.99014366
A24: Charter | B24: Est'd.(2) | C24: ='5-Charters'!Q34 -> 42012678 | D24: ='5-Charters'!I104 -> 6076259
B25: =C24/B26 -> 0.0060701762 | D25: =D24/D26 -> 0.0098563443
A26: Total | B26: =C24+B22 -> 6921162935 | D26: =D24+D22 -> 616482016
A27: Percentage of Revenue by Source | B27: District | C27: Charter | D27: District | E27: Charter | I27: Figure 4
A28: Federal | B28: =B9/B$14 -> 0.099800253 | C28: N/A (1) | D28: =D9/D$14 -> 0.085319359 | E28: =E9/E$14 -> 0.12307606
A29: State | B29: =B10/B$14 -> 0.4225477 | C29: N/A (1) | D29: =D10/D$14 -> 0.43702028 | E29: =E10/E$14 -> 0.80720358
A30: Local | B30: =B11/B$14 -> 0.38593519 | C30: N/A (1) | D30: =D11/D$14 -> 0.36761627 | E30: =E11/E$14 -> 0
A31: Other | B31: =B12/B$14 -> 0.091716848 | C31: N/A (1) | D31: =D12/D$14 -> 0.11004409 | E31: =E12/E$14 -> 0.069720366
A32: Indeterminate | B32: =B13/B$14 -> 0 | C32: N/A (1) | D32: =D13/D$14 -> 0 | E32: =E13/E$14 -> 0
A33: Change in district school funding if subjected to charter funding structure
B34: =B6*B16 -> 1.1969468e+09 | D34: =D6*D16 -> 1.2213508e+08
A36: PROOF | B36: =SUM(B28:B32) -> 1 | C36: =SUM(C28:C32) -> 0 | D36: =SUM(D28:D32) -> 1 | E36: =SUM(E28:E32) -> 1 | F36: =SUM(F28:F32) -> 0 | G36: =SUM(G28:G32) -> 0
A38: See other NOTES on tab #5-Charters.
J56: Federal | K56: State | L56: Local | M56: Other | N56: Indeterminate | R56: PROOF
I57: Statewide-District | J57: =B9 -> 1014.4325 | K57: =B10 -> 4295.0403 | L57: =B11 -> 3922.8877 | M57: =B12 -> 932.26766 | N57: =B13 -> 0 | R57: =SUM(J57:O57) -> 10164.628
I58: Statewide-Charter | J58: =C9 -> N/A (1) | K58: =C10 -> N/A (1) | L58: =C11 -> N/A (1) | M58: =C12 -> N/A (1) | N58: =C13 -> N/A (1) | R58: =SUM(J58:O58) -> 0
I59: Greenville District | J59: =D9 -> 796.18153 | K59: =D10 -> 4078.1773 | L59: =D11 -> 3430.5143 | M59: =D12 -> 1026.9073 | N59: =D13 -> 0 | R59: =SUM(J59:O59) -> 9331.7805
I60: Greenville Charter | J60: =E9 -> 918.71353 | K60: =E10 -> 6025.4518 | L60: =E11 -> 0 | M60: =E12 -> 520.43464 | N60: =E13 -> 0 | R60: =SUM(J60:O60) -> 7464.5999
I64: PROOF | J64: =SUM(J57:J63) -> 2729.3275 | K64: =SUM(K57:K63) -> 14398.669 | L64: =SUM(L57:L63) -> 7353.4021 | M64: =SUM(M57:M63) -> 2479.6096 | N64: =SUM(N57:N62) -> 0

Sheet Figures 1,2,4-Weighted
A1: Figure 1 | K1: Figure 2 | U1: TEMPLATE
A2: South Carolina 2006-2007 | B2: Statewide | D2: Statewide Weighted for Charter Enrollment | F2: Greenville | H2: N/A
A3: Per-Pupil Revenue
A4: District | B4: =B22/B16 -> 10164.628 | D4: 10104 | F4: =F22/F16 -> 9331.7805
A5: Charter | B5: =42012678.339/B18 -> 8396.0204 | D5: 8396 | F5: =F24/F18 -> 7464.5999
A6: Difference | B6: =B4-B5 -> 1768.6078 | D6: 1708 | F6: =F4-F5 -> 1867.1805
B7: =B6/B4 -> 0.17399631 | D7: 0.169 | F7: =F6/F4 -> 0.20008835
A8: Per-Pupil Revenue by Source | B8: District | C8: Charter | D8: District | E8: Charter | F8: District | G8: Charter (3) | T8: PROOF
A9: Federal | B9: ='[2]4-Districts Less Charters'!DI229/B16 -> 1014.4325 | C9: * | D9: 998 | E9: =C9 -> * | F9: ='[2]4-Districts Less Charters'!AY232/F16 -> 796.18153 | G9: ='[2]5-Charters'!H101/F18 -> 918.71353 | T9: =SUM(B9:I9) -> 3727.3275
A10: State | B10: ='[2]4-Districts Less Charters'!DI187/B16 -> 4295.0403 | C10: * | D10: 4279 | E10: =C10 -> * | F10: ='[2]4-Districts Less Charters'!AY190/F16 -> 4078.1773 | G10: ='[2]5-Charters'!H100/F18 -> 6025.4518 | T10: =SUM(B10:I10) -> 18677.669
A11: Local | B11: ='[2]4-Districts Less Charters'!DI16/B16 -> 3922.8877 | C11: * | D11: 3887 | E11: =C11 -> * | F11: ='[2]4-Districts Less Charters'!AY19/F16 -> 3430.5143 | G11: ='[2]5-Charters'!H99/F18 -> 0 | T11: =SUM(B11:I11) -> 11240.402
A12: Other | B12: ='[2]4-Districts Less Charters'!DI58/B16 -> 932.26766 | C12: * | D12: 939 | E12: =C12 -> * | F12: ='[2]4-Districts Less Charters'!AY61/F16 -> 1026.9073 | G12: ='[2]5-Charters'!H102/F18 -> 520.43464 | T12: =SUM(B12:I12) -> 3418.6096
A13: Indeterminate | B13: 0 | C13: * | D13: 0 | E13: =C13 -> * | F13: ='[2]4-Districts Less Charters'!AY235/F16 -> 0 | G13: 0 | T13: =SUM(B13:I13) -> 0
A14: Total | B14: =SUM(B9:B13) -> 10164.628 | C14: $8,396** | D14: =D4 -> 10104 | E14: =C14 -> $8,396** | F14: =SUM(F9:F13) -> 9331.7805 | G14: =SUM(G9:G13) -> 7464.5999
A15: Enrollment
A16: District | B16: ='[2]6-Enrollment'!P104 -> 676773.43 | D16: n/a | F16: ='[2]6-Enrollment'!R47 -> 65411.5
B17: =B16/(B16+B18) -> 0.99266054 | D17: n/a | F17: =F16/(F16+F18) -> 0.98770851 | L17: District | M17: Charter | N17: Difference
A18: Charter | B18: ='[2]5-Charters'!M34 -> 5003.88 | D18: n/a | F18: ='[2]5-Charters'!B98 -> 814.01 | K18: South Carolina | L18: =B4 -> 10164.628 | M18: =B5 -> 8396.0204 | N18: =B6 -> 1768.6078
B19: =B18/(B16+B18) -> 0.007339464 | D19: n/a | F19: =F18/(F16+F18) -> 0.012291487 | K19: South Carolina Weighted | L19: =D4 -> 10104 | M19: =D5 -> 8396 | N19: =D6 -> 1708
A20: Number of Charters | B20: ='[2]5-Charters'!L34 -> 28 | D20: n/a | F20: 6 | K20: Greenville | L20: =F4 -> 9331.7805 | M20: =F5 -> 7464.5999 | N20: =F6 -> 1867.1805
A21: Total Revenue
A22: District | B22: ='[2]4-Districts Less Charters'!DI237 -> 6.8791503e+09 | D22: n/a | F22: ='[2]4-Districts Less Charters'!AY240 -> 610405757
B23: =B22/B26 -> 0.99392982 | D23: n/a | F23: =F22/F26 -> 0.99014366
A24: Charter | B24: $ | C24: 42,012,678** | D24: n/a | F24: ='[2]5-Charters'!I104 -> 6076259
B25: =42012678.339/B26 -> 0.0060701762 | D25: n/a | F25: =F24/F26 -> 0.0098563443
A26: Total | B26: 6921162935 | D26: n/a | F26: =F24+F22 -> 616482016
A27: Percentage of Revenue by Source | B27: District | C27: Charter | D27: District | E27: Charter | F27: District | G27: Charter | K27: Figure 4
A28: Federal | B28: =B9/B$14 -> 0.099800253 | C28: * | D28: =D9/$D$14 -> 0.098772763 | E28: =C28 -> * | F28: =F9/F$14 -> 0.085319359 | G28: =G9/G$14 -> 0.12307606
A29: State | B29: =B10/B$14 -> 0.4225477 | C29: * | D29: =D10/$D$14 -> 0.42349565 | E29: =C29 -> * | F29: =F10/F$14 -> 0.43702028 | G29: =G10/G$14 -> 0.80720358
A30: Local | B30: =B11/B$14 -> 0.38593519 | C30: * | D30: =D11/$D$14 -> 0.38469913 | E30: =C30 -> * | F30: =F11/F$14 -> 0.36761627 | G30: =G11/G$14 -> 0
A31: Other | B31: =B12/B$14 -> 0.091716848 | C31: * | D31: =D12/$D$14 -> 0.092933492 | E31: =C31 -> * | F31: =F12/F$14 -> 0.11004409 | G31: =G12/G$14 -> 0.069720366
A32: Indeterminate | B32: =B13/B$14 -> 0 | C32: * | D32: =D13/$D$14 -> 0 | E32: =C32 -> * | F32: =F13/F$14 -> 0 | G32: =G13/G$14 -> 0
A33: Change in district school funding if subjected to charter funding structure
B34: ($1.2 billion) | F34: ($122.1 million)
A36: 42012678 | B36: =(B$16*B$5)-B$22 -> -1.1969468e+09 | F36: =(F$16*F$5)-F$22 -> -1.2213508e+08 | H36: =SUM(H28:H32) -> 0 | I36: =SUM(I28:I32) -> 0
A37: PROOF | B37: =SUM(B28:B32) -> 1 | C37: =SUM(C28:C32) -> 0 | F37: =SUM(F28:F32) -> 1 | G37: =SUM(G28:G32) -> 1
A38: See other NOTES on tab #5-Charters.
L60: Federal | M60: State | N60: Local | O60: Other | P60: Indeterminate | T60: PROOF
K61: Statewide District | L61: =B9 -> 1014.4325 | M61: =B10 -> 4295.0403 | N61: =B11 -> 3922.8877 | O61: =B12 -> 932.26766 | P61: =B13 -> 0 | T61: =SUM(L61:Q61) -> 10164.628
K62: Statewide Weighted | L62: =D9 -> 998 | M62: =D10 -> 4279 | N62: =D11 -> 3887 | O62: =D12 -> 939 | P62: =D13 -> 0
K63: Statewide Charter | L63: =C9 -> * | M63: =C10 -> * | N63: =C11 -> * | O63: =C12 -> * | P63: =C13 -> * | T63: =SUM(L63:Q63) -> 0
K64: Greenville District | L64: =F9 -> 796.18153 | M64: =F10 -> 4078.1773 | N64: =F11 -> 3430.5143 | O64: =F12 -> 1026.9073 | P64: =F13 -> 0 | T64: =SUM(L64:Q64) -> 9331.7805
K65: Greenville Charter | L65: =G9 -> 918.71353 | M65: =G10 -> 6025.4518 | N65: =G11 -> 0 | O65: =G12 -> 520.43464 | P65: =G13 -> 0 | T65: =SUM(L65:Q65) -> 7464.5999
K69: PROOF | L69: =SUM(L61:L68) -> 3727.3275 | M69: =SUM(M61:M68) -> 18677.669 | N69: =SUM(N61:N68) -> 11240.402 | O69: =SUM(O61:O68) -> 3418.6096 | P69: =SUM(P61:P67) -> 0

Sheet Report Figures 1,3,5,6
B3: Figure 1
B4: South Carolina (2006-07) | C4: Statewide | E4: Statewide Weighted for Charter Enrollment | G4: Greenville
B5: Per-Pupil Revenue
B6: District | C6: 10164.628 | E6: 10104 | G6: 9331.7805
B7: Charter | C7: est. $8,396 | E7: est. $8,396 | G7: 7464.5999
B8: Difference | C8: est. ($1,769) | E8: est. ($1,708) | G8: -1867.1805
C9: est. (17.4%) | E9: est. (16.9%) | G9: (20.0%)
B10: Per-Pupil Revenue by Source | C10: District | D10: Charter | E10: District | F10: Charter | G10: District | H10: Charter
B11: Federal | C11: 1014.4325 | D11: N/A | E11: 998 | F11: N/A | G11: 796.18153 | H11: 918.71353
B12: State | C12: 4295.0403 | D12: N/A | E12: 4279 | F12: N/A | G12: 4078.1773 | H12: 6025.4518
B13: Local | C13: 3922.8877 | D13: N/A | E13: 3887 | F13: N/A | G13: 3430.5143 | H13: 0
B14: Other | C14: 932.26766 | D14: N/A | E14: 939 | F14: N/A | G14: 1026.9073 | H14: 520.43464
B15: Indeterminate | C15: 0 | D15: N/A | E15: 0 | F15: N/A | G15: 0 | H15: 0
B16: Total | C16: 10164.628 | D16: est. $8,396 | E16: 10104 | F16: est. $8,396 | G16: 9331.7805 | H16: 7464.5999
B17: Enrollment
B18: District | C18: 676773.43 | E18: N/A | G18: 65411.5
C19: 0.99266054 | E19: N/A | G19: 0.98770851
B20: Charter | C20: 5003.88 | E20: N/A | G20: 814.01
C21: 0.007339464 | E21: N/A | G21: 0.012291487
B22: Number of Charters | C22: 28 | E22: N/A | G22: 6
B23: Total Revenue
B24: District | C24: 6.8791503e+09 | E24: N/A | G24: 610405757
C25: 0.99392982 | E25: N/A | G25: 0.99014366
B26: Charter | C26: est. $42,012,678 | E26: N/A | G26: 6076259
C27: 0.0060701762 | E27: N/A | G27: 0.0098563443
B28: Total | C28: est. $6,921,162,935 | E28: N/A | G28: 616482016
B29: Percentage of Revenue by Source | C29: District | D29: Charter | E29: District | F29: Charter | G29: District | H29: Charter
B30: Federal | C30: 0.099800253 | D30: N/A | E30: 0.098772763 | F30: N/A | G30: 0.085319359 | H30: 0.12307606
B31: State | C31: 0.4225477 | D31: N/A | E31: 0.42349565 | F31: N/A | G31: 0.43702028 | H31: 0.80720358
B32: Local | C32: 0.38593519 | D32: N/A | E32: 0.38469913 | F32: N/A | G32: 0.36761627 | H32: 0
B33: Other | C33: 0.091716848 | D33: N/A | E33: 0.092933492 | F33: N/A | G33: 0.11004409 | H33: 0.069720366
B34: Indeterminate | C34: 0 | D34: N/A | E34: 0 | F34: N/A | G34: 0 | H34: 0
B35: Change in district school funding if subjected to charter funding structure
C36: ($1.2 billion) | G36: ($122.1 million)
J39: Figure 3
J40: State Policies | K40: Yes | L40: No | M40: Partial
J41: Charter schools receive their funding directly from the state | L41: X3
J42: Charter schools are eligible for local funding | K42: X4
J43: Cap on funding a charter school can receive | L43: X
J44: District public schools receive differential funding (e.g. more funding for 9-12 vs. K-8 schools) | K44: X
J45: Charter schools receive differential funding | K45: X
J46: State allows district to withhold funding from charter schools for providing administrative services | K46: X5
J47: State "holds harmless" district funding for charter enrollment | L47: X
J48: School is considered LEA if authorized by non-district organization | L48: X
J49: School is considered LEA if authorized by district | L49: X
J50: Cap on number of charter schools | L50: X
J51: Cap on number of charter schools authorized per year | L51: X
J52: Cap on number of students attending charter schools | L52: X
J53: Charter schools have an open enrollment policy | K53: X6
E56: 3 | F56: Charter schools can be authorized by local school boards; and by the South Carolina Public Charter School District (SCPCSD) for new starts only. Revenues pass through the hosting local school district. The general rule is that charter schools report financial data as a component unit of the hosting school district in annual audits -- that reporting is incomplete as to sources of revenue, and on occasion not included in district annual audits.
E57: 4 | F57: Charter schools authorized by SCPCSD (the state) receive only state and federal funds. Charter schools authorized by local school districts receive local revenues.
E58: 5 | F58: Language in the charter law permits the district to negotiate a variety of services with charters.
E59: 6 | F59: A charter school may give enrollment priority to a sibling of a pupil already enrolled, children of a charter school employee and children of the charter committee, provided their enrollment does not constitute more than twenty percent of the enrollment of the charter school. A charter school must give priority to in-district children versus out-of-district children, and the out-of-district enrollment shall not exceed twenty percent of the total enrollment of the charter school without the approval of the sponsoring local school board and the sending local school board. A converted charter school must give priority in enrollment to students enrolled in the school at the time of conversion.
O60: Figure 5
O61: South Carolina (2006-07) | P61: Statewide District | Q61: Statewide Charters
O62: Percentage of students eligible for free or reduced price lunch | P62: 0.51481289 | Q62: 0.30594679
O63: Percentage of schools eligible for Title I | P63: 0.42060086 | Q63: 0.26666667
O64: Percentage of students by school type:
O65: Primary (K-5) | P65: 0.47810839 | Q65: 0.4149061
O66: Middle (6-8) | P66: 0.22380864 | Q66: 0.060054773
O67: High (9-12) | P67: 0.27996997 | Q67: 0.50058685
O68: Other (K-12, K-8, etc.) | P68: 0.018112999 | Q68: 0.024452269
S71: Figure 6
T72: Findings | U72: SC
S73: Federal Funding | T73: Charters have access to federal funds according to state statutes (Yes = black, No = white) | U73: Y
T74: Percentage of federal revenue is greater than (>; black), equal to (=; black), or is less than (<; white) that of total enrollment for charter schools | U74: N/A7
S75: State Funding | T75: Charters have access to state funds according to state statutes (Yes = black, No = white) | U75: Y
T76: Percentage of state revenue is greater than (>; black), equal to (=; black), or is less than (<; white) that of total enrollment for charter schools | U76: N/A7
S77: Local Funding | T77: Charters have access to local funds according to state statutes (Yes = black, No = white) | U77: Y
T78: Percentage of local revenue is greater than (>; black), equal to (=; black), or is less than (<; white) that of total enrollment for charter schools | U78: N/A7
S79: Facilities Funding | T79: Charters have access to facilities funds according to state statutes (Yes = black, No = white) | U79: N
T80: Percentage of facilities revenue is greater than (>; black), equal to (=; black), or is less than (<; white) that of total enrollment for charter schools | U80: N/A7
S81: Data Availability | T81: State provides detailed, public data on federal, state, local, and other revenues for district schools (Yes = black, Partial = grey, No = white) | U81: Y
T82: State provides detailed, public data on federal, state, local and other revenues for charter schools (Yes = black, Partial = grey, No = white) | U82: N
S83: Funding Formula | T83: Charters are treated as LEAs for funding purposes (Yes = black, Partial = grey, No = white) | U83: N
T84: State funds student (black) or the LEA (grey) | U84: L
T85: State funding formula is fair and equitable (Yes = black, No = white) | U85: N
N88: 7 | O88: The state does not track charter school revenue by source. The only source of charter school revenue data is from Annual Financial Reports (AFR) of sponsoring local school districts. Generally, sponsoring district AFRs report charter schools as separate component units. However, the AFRs do not consistently report sources of revenue data for charter schools. Therefore, on a statewide basis the sources of revenues for charter schools could not be determined.

Sheet 1-Download
A1: File Name: "07-distrev.xls" -- Download of Excel 2006/2007 Revenue File
A2: SOURCE: SC DOE Web Site; Confirmed as to Content by Mellanie Jinnette, Financial Systems Manager, SC Department of Education (DOE) | O2: See other NOTES on tab #5-Charters.
A3: Notes: Includes revenue for traditional district schools and charter schools by district; all revenues sources (some non-study revenue items to be deleted)
C5: | | D5: ABBEVILLE | E5: | | F5: AIKEN | G5: | | H5: ALLENDALE | I5: | | J5: ANDERSON CTY BD | K5: | | L5: ANDERSON 01 | M5: | | N5: ANDERSON 02 | O5: | | P5: ANDERSON 03 | Q5: | | R5: ANDERSON 04 | S5: | | T5: ANDERSON 05 | U5: | | V5: ANDERSON ALT SCHOOL | W5: | | X5: ANDERSON 1&2 CC | Y5: | | Z5: BAMBERG 01 | AA5: | | AB5: BAMBERG 02 | AC5: | | AD5: BARNWELL 19 | AE5: | | AF5: BARNWELL 29 | AG5: | | AH5: BARNWELL 45 | AI5: | | AJ5: BARNWELL VOC CEN | AK5: | | AL5: BEAUFORT | AM5: | | AN5: BEAUFORT-JASPER CEC | AO5: | | AP5: BERKELEY | AQ5: | | AR5: CALHOUN | AS5: | | AT5: CHARLESTON | AU5: | | AV5: CHEROKEE | AW5: | | AX5: CHESTER | AY5: | | AZ5: CHESTERFIELD | BA5: | | BB5: CLARENDON 01 | BC5: | | BD5: CLARENDON 02 | BE5: | | BF5: CLARENDON 03 | BG5: | | BH5: F.E. DUBOSE CC | BI5: | | BJ5: COLLETON | BK5: | | BL5: DARLINGTON | BM5: | | BN5: DILLON CTY BD | BO5: | | BP5: DILLON 01 | BQ5: | | BR5: DILLON 02 | BS5: | | BT5: DILLON 03 | BU5: | | BV5: DILLON ATC | BW5: | | BX5: DORCHESTER 02 | BY5: | | BZ5: DORCHESTER 04 | CA5: | | CB5: DORCHESTER CAR SCH | CC5: | | CD5: EDGEFIELD | CE5: | | CF5: FAIRFIELD | CG5: | | CH5: FLORENCE 01 | CI5: | | CJ5: FLORENCE 02 | CK5: | | CL5: FLORENCE 03 | CM5: | | CN5: FLORENCE 04 | CO5: | | CP5: FLORENCE 05 | CQ5: | | CR5: GEORGETOWN | CS5: | | CT5: GREENVILLE | CU5: | | CV5: GREENWOOD 50 | CW5: | | CX5: GREENWOOD 51 | CY5: | | CZ5: GREENWOOD 52 | DA5: | | DB5: GREENWOOD VOC FAC | DC5: | | DD5: HAMPTON 01 | DE5: | | DF5: HAMPTON 02 | DG5: | | DH5: HORRY | DI5: | | DJ5: JASPER | DK5: | | DL5: KERSHAW | DM5: | | DN5: LANCASTER | DO5: | | DP5: LAURENS 55 | DQ5: | | DR5: LAURENS 56 | DS5: | | DT5: LEE | DU5: | | DV5: LEXINGTON 01 | DW5: | | DX5: LEXINGTON 02 | DY5: | | DZ5: LEXINGTON 03 | EA5: | | EB5: LEXINGTON 04 | EC5: | | ED5: LEXINGTON 05 | EE5: | | EF5: MCCORMICK | EG5: | | EH5: MARION CTY BD | EI5: | | EJ5: MARION 01 | EK5: | | EL5: MARION 02 | EM5: | | EN5: MARION 07 | EO5: | | EP5: MARION VOC CTR | EQ5: | | ER5: MARLBORO | ES5: | | ET5: NEWBERRY | EU5: | | EV5: OCONEE | EW5: | | EX5: ORANGEBURG CTY BD | EY5: | | EZ5: ORANGEBURG 03 | FA5: | | FB5: ORANGEBURG 04 | FC5: | | FD5: ORANGEBURG 05 | FE5: | | FF5: COPE AVC | FG5: | | FH5: PICKENS | FI5: | | FJ5: RICHLAND 01 | FK5: | | FL5: RICHLAND 02 | FM5: | | FN5: SALUDA | FO5: | | FP5: SPARTANBURG 01 | FQ5: | | FR5: SPARTANBURG 02 | FS5: | | FT5: SPARTANBURG 03 | FU5: | | FV5: SPARTANBURG 04 | FW5: | | FX5: SPARTANBURG 05 | FY5: | | FZ5: SPARTANBURG 06 | GA5: | | GB5: SPARTANBURG 07 | GC5: | | GD5: DAN MORGAN VOC CEN | GE5: | | GF5: R.D. ANDERSON ATC | GG5: | | GH5: H.B. SWOFFORD CC | GI5: | | GJ5: SUMTER 02 | GK5: | | GL5: SUMTER 17 | GM5: | | GN5: SUMTER CC | GO5: | | GP5: UNION | GQ5: | | GR5: WILLIAMSBURG | GS5: | | GT5: YORK 01 | GU5: | | GV5: YORK 02 | GW5: | | GX5: YORK 03 | GY5: | | GZ5: YORK 04 | HA5: | | HB5: JUVENILE JUSTICE | HC5: | | HD5: PALMETTO UNIFIED | HE5: | | HF5: REGULAR DIST.TOTALS | HG5: | | HH5: SPECIAL DIST.TOTALS | HI5: | | HJ5: STATE TOTALS | HK5: |
C6: | | E6: | | G6: | | I6: | | K6: | | M6: | | O6: | | Q6: | | S6: | | U6: | | W6: | | Y6: | | AA6: | | AC6: | | AE6: | | AG6: | | AI6: | | AK6: | | AM6: | | AO6: | | AQ6: | | AS6: | | AU6: | | AW6: | | AY6: | | BA6: | | BC6: | | BE6: | | BG6: | | BI6: | | BK6: | | BM6: | | BO6: | | BQ6: | | BS6: | | BU6: | | BW6: | | BY6: | | CA6: | | CC6: | | CE6: | | CG6: | | CI6: | | CK6: | | CM6: | | CO6: | | CQ6: | | CS6: | | CU6: | | CW6: | | CY6: | | DA6: | | DC6: | | DE6: | | DG6: | | DI6: | | DK6: | | DM6: | | DO6: | | DQ6: | | DS6: | | DU6: | | DW6: | | DY6: | | EA6: | | EC6: | | EE6: | | EG6: | | EI6: | | EK6: | | EM6: | | EO6: | | EQ6: | | ES6: | | EU6: | | EW6: | | EY6: | | FA6: | | FC6: | | FE6: | | FG6: | | FI6: | | FK6: | | FM6: | | FO6: | | FQ6: | | FS6: | | FU6: | | FW6: | | FY6: | | GA6: | | GC6: | | GE6: | | GG6: | | GI6: | | GK6: | | GM6: | | GO6: | | GQ6: | | GS6: | | GU6: | | GW6: | | GY6: | | HA6: | | HC6: | | HE6: | | HG6: | | HI6: | | HK6: |
A7: 1000 | B7: REVENUE FROM LOCAL SOURCES: | C7: | | E7: | | G7: | | I7: | | K7: | | M7: | | O7: | | Q7: | | S7: | | U7: | | W7: | | Y7: | | AA7: | | AC7: | | AE7: | | AG7: | | AI7: | | AK7: | | AM7: | | AO7: | | AQ7: | | AS7: | | AU7: | | AW7: | | AY7: | | BA7: | | BC7: | | BE7: | | BG7: | | BI7: | | BK7: | | BM7: | | BO7: | | BQ7: | | BS7: | | BU7: | | BW7: | | BY7: | | CA7: | | CC7: | | CE7: | | CG7: | | CI7: | | CK7: | | CM7: | | CO7: | | CQ7: | | CS7: | | CU7: | | CW7: | | CY7: | | DA7: | | DC7: | | DE7: | | DG7: | | DI7: | | DK7: | | DM7: | | DO7: | | DQ7: | | DS7: | | DU7: | | DW7: | | DY7: | | EA7: | | EC7: | | EE7: | | EG7: | | EI7: | | EK7: | | EM7: | | EO7: | | EQ7: | | ES7: | | EU7: | | EW7: | | EY7: | | FA7: | | FC7: | | FE7: | | FG7: | | FI7: | | FK7: | | FM7: | | FO7: | | FQ7: | | FS7: | | FU7: | | FW7: | | FY7: | | GA7: | | GC7: | | GE7: | | GG7: | | GI7: | | GK7: | | GM7: | | GO7: | | GQ7: | | GS7: | | GU7: | | GW7: | | GY7: | | HA7: | | HC7: | | HE7: | | HG7: | | HI7: | | HK7: |
A8: 1100 | B8: TAXES ASSESSED/LEVIED BY LEA: | C8: | | E8: | | G8: | | I8: | | K8: | | M8: | | O8: | | Q8: | | S8: | | U8: | | W8: | | Y8: | | AA8: | | AC8: | | AE8: | | AG8: | | AI8: | | AK8: | | AM8: | | AO8: | | AQ8: | | AS8: | | AU8: | | AW8: | | AY8: | | BA8: | | BC8: | | BE8: | | BG8: | | BI8: | | BK8: | | BM8: | | BO8: | | BQ8: | | BS8: | | BU8: | | BW8: | | BY8: | | CA8: | | CC8: | | CE8: | | CG8: | | CI8: | | CK8: | | CM8: | | CO8: | | CQ8: | | CS8: | | CU8: | | CW8: | | CY8: | | DA8: | | DC8: | | DE8: | | DG8: | | DI8: | | DK8: | | DM8: | | DO8: | | DQ8: | | DS8: | | DU8: | | DW8: | | DY8: | | EA8: | | EC8: | | EE8: | | EG8: | | EI8: | | EK8: | | EM8: | | EO8: | | EQ8: | | ES8: | | EU8: | | EW8: | | EY8: | | FA8: | | FC8: | | FE8: | | FG8: | | FI8: | | FK8: | | FM8: | | FO8: | | FQ8: | | FS8: | | FU8: | | FW8: | | FY8: | | GA8: | | GC8: | | GE8: | | GG8: | | GI8: | | GK8: | | GM8: | | GO8: | | GQ8: | | GS8: | | GU8: | | GW8: | | GY8: | | HA8: | | HC8: | | HE8: | | HG8: | | HI8: | | HK8: |
A9: 1110 | B9: AD VALOREM TAXES (FISC INDEPEN) | C9: | | D9: 1520764 | E9: | | F9: 60312472 | G9: | | H9: 4709102 | I9: | | K9: | | M9: | | O9: | | Q9: | | S9: | | U9: | | W9: | | Y9: | | Z9: 3518785 | AA9: | | AC9: | | AD9: 1608309 | AE9: | | AF9: 1694415 | AG9: | | AH9: 4983807 | AI9: | | AK9: | | AM9: | | AO9: | | AP9: 81057233 | AQ9: | | AS9: | | AT9: 237617163 | AU9: | | AV9: 20857424 | AW9: | | AX9: 15774043 | AY9: | | AZ9: 13611432 | BA9: | | BC9: | | BE9: | | BG9: | | BI9: | | BJ9: 3633589 | BK9: | | BL9: 31643785 | BM9: | | BN9: 1164045 | BO9: | | BQ9: | | BS9: | | BT9: 1669444 | BU9: | | BV9: 773207 | BW9: | | BX9: 47974404 | BY9: | | BZ9: 9991137 | CA9: | | CC9: | | CD9: 9211573 | CE9: | | CG9: | | CI9: | | CK9: | | CL9: 6118718 | CM9: | | CN9: 2340676 | CO9: | | CQ9: | | CR9: 53912753 | CS9: | | CT9: 209875704 | CU9: | | CW9: | | CY9: | | DA9: | | DC9: | | DE9: | | DG9: | | DH9: 189882593 | DI9: | | DK9: | | DM9: | | DN9: 27833046 | DO9: | | DP9: 12598542 | DQ9: | | DR9: 4931133 | DS9: | | DU9: | | DV9: 54022433 | DW9: | | DX9: 28570445 | DY9: | | DZ9: 8785696 | EA9: | | EB9: 6370433 | EC9: | | ED9: 75156901 | EE9: | | EG9: | | EH9: 1031638 | EI9: | | EK9: | | EM9: | | EO9: | | EP9: 829221 | EQ9: | | ER9: 7589855 | ES9: | | ET9: 21368223 | EU9: | | EW9: | | EY9: | | EZ9: 8411421 | FA9: | | FB9: 9864404 | FC9: | | FD9: 22697920 | FE9: | | FG9: | | FH9: 41771782 | FI9: | | FK9: | | FM9: | | FO9: | | FP9: 15002986 | FQ9: | | FR9: 19399837 | FS9: | | FT9: 10606763 | FU9: | | FV9: 6064849 | FW9: | | FX9: 27007132 | FY9: | | FZ9: 34914489 | GA9: | | GB9: 35418636 | GC9: | | GD9: 1220480 | GE9: | | GF9: 1790126 | GG9: | | GI9: | | GK9: | | GM9: | | GO9: | | GP9: 7548390 | GQ9: | | GR9: 6863244 | GS9: | | GT9: 8885582 | GU9: | | GV9: 37156040 | GW9: | | GX9: 51613941 | GY9: | | GZ9: 34135864 | HA9: | | HC9: | | HE9: | | HF9: 1644918029 | HG9: | | HI9: | | HJ9: 1644918029 | HK9: |
A10: 1140 | B10: PENALTY/INT ON TAX (FISC INDEP) | C10: | | D10: 132769 | E10: | | F10: 2319640 | G10: | | H10: 10538 | I10: | | K10: | | M10: | | O10: | | Q10: | | S10: | | U10: | | W10: | | Y10: | | AA10: | | AC10: | | AD10: 22174 | AE10: | | AF10: 315835 | AG10: | | AI10: | | AK10: | | AM10: | | AO10: | | AP10: 283069 | AQ10: | | AS10: | | AT10: 7206803 | AU10: | | AW10: | | AY10: | | AZ10: 69856 | BA10: | | BC10: | | BE10: | | BG10: | | BI10: | | BK10: | | BL10: 149802 | BM10: | | BO10: | | BQ10: | | BS10: | | BT10: 16783 | BU10: | | BV10: 7569 | BW10: | | BY10: | | CA10: | | CC10: | | CD10: 63329 | CE10: | | CG10: | | CI10: | | CK10: | | CL10: 24835 | CM10: | | CN10: 7929 | CO10: | | CQ10: | | CR10: 338274 | CS10: | | CU10: | | CW10: | | CY10: | | DA10: | | DC10: | | DE10: | | DG10: | | DH10: 1847104 | DI10: | | DK10: | | DM10: | | DN10: 306014 | DO10: | | DP10: 39250 | DQ10: | | DR10: 352047 | DS10: | | DU10: | | DV10: 2948414 | DW10: | | DX10: 168908 | DY10: | | DZ10: 123038 | EA10: | | EB10: 60715 | EC10: | | ED10: 401443 | EE10: | | EG10: | | EH10: 13774 | EI10: | | EK10: | | EM10: | | EO10: | | EP10: 11472 | EQ10: | | ER10: 98476 | ES10: | | ET10: 382847 | EU10: | | EW10: | | EY10: | | EZ10: 158859 | FA10: | | FB10: 92320 | FC10: | | FD10: 302645 | FE10: | | FG10: | | FH10: 356908 | FI10: | | FK10: | | FM10: | | FO10: | | FQ10: | | FS10: | | FU10: | | FW10: | | FY10: | | FZ10: 53219 | GA10: | | GC10: | | GE10: | | GF10: 118918 | GG10: | | GI10: | | GK10: | | GM10: | | GO10: | | GP10: 623388 | GQ10: | | GS10: | | GT10: 436515 | GU10: | | GV10: 765865 | GW10: | | GX10: 436456 | GY10: | | GZ10: 117338 | HA10: | | HC10: | | HE10: | | HF10: 21185138 | HG10: | | HI10: | | HJ10: 21185138 | HK10: |
A11: 1190 | B11: OTHER TAXES (FISCALLY INDEPEN) | C11: | | E11: | | G11: | | I11: | | K11: | | M11: | | O11: | | Q11: | | S11: | | U11: | | W11: | | Y11: | | AA11: | | AC11: | | AE11: | | AG11: | | AI11: | | AK11: | | AM11: | | AO11: | | AQ11: | | AS11: | | AU11: | | AV11: 5051631 | AW11: | | AY11: | | BA11: | | BC11: | | BE11: | | BG11: | | BI11: | | BK11: | | BM11: | | BN11: 62076 | BO11: | | BQ11: | | BS11: | | BT11: 347531 | BU11: | | BV11: 162535 | BW11: | | BY11: | | CA11: | | CC11: | | CE11: | | CG11: | | CI11: | | CK11: | | CM11: | | CO11: | | CQ11: | | CS11: | | CU11: | | CW11: | | CY11: | | DA11: | | DC11: | | DE11: | | DG11: | | DI11: | | DK11: | | DM11: | | DO11: | | DQ11: | | DS11: | | DU11: | | DV11: 25525556 | DW11: | | DY11: | | EA11: | | EC11: | | EE11: | | EG11: | | EI11: | | EK11: | | EM11: | | EO11: | | EQ11: | | ER11: 8497 | ES11: | | EU11: | | EW11: | | EY11: | | FA11: | | FC11: | | FE11: | | FG11: | | FH11: 5595 | FI11: | | FK11: | | FM11: | | FO11: | | FQ11: | | FS11: | | FU11: | | FW11: | | FX11: 1781081 | FY11: | | GA11: | | GC11: | | GE11: | | GG11: | | GI11: | | GK11: | | GM11: | | GO11: | | GQ11: | | GS11: | | GU11: | | GW11: | | GY11: | | HA11: | | HC11: | | HE11: | | HF11: 32944502 | HG11: | | HI11: | | HJ11: 32944502 | HK11: |
A12: 1200 | B12: REV FR LOC GOV UNIT OTH THAN LEA: | C12: | | E12: | | G12: | | I12: | | K12: | | M12: | | O12: | | Q12: | | S12: | | U12: | | W12: | | Y12: | | AA12: | | AC12: | | AE12: | | AG12: | | AI12: | | AK12: | | AM12: | | AO12: | | AQ12: | | AS12: | | AU12: | | AW12: | | AY12: | | BA12: | | BC12: | | BE12: | | BG12: | | BI12: | | BK12: | | BM12: | | BO12: | | BQ12: | | BS12: | | BU12: | | BW12: | | BY12: | | CA12: | | CC12: | | CE12: | | CG12: | | CI12: | | CK12: | | CM12: | | CO12: | | CQ12: | | CS12: | | CU12: | | CW12: | | CY12: | | DA12: | | DC12: | | DE12: | | DG12: | | DI12: | | DK12: | | DM12: | | DO12: | | DQ12: | | DS12: | | DU12: | | DW12: | | DY12: | | EA12: | | EC12: | | EE12: | | EG12: | | EI12: | | EK12: | | EM12: | | EO12: | | EQ12: | | ES12: | | EU12: | | EW12: | | EY12: | | FA12: | | FC12: | | FE12: | | FG12: | | FI12: | | FK12: | | FM12: | | FO12: | | FQ12: | | FS12: | | FU12: | | FW12: | | FY12: | | GA12: | | GC12: | | GE12: | | GG12: | | GI12: | | GK12: | | GM12: | | GO12: | | GQ12: | | GS12: | | GU12: | | GW12: | | GY12: | | HA12: | | HC12: | | HE12: | | HG12: | | HI12: | | HK12: |
A13: 1210 | B13: AD VALOREM TAX (FISC DEPENDENT) | C13: | | D13: 6245819 | E13: | | G13: | | I13: | | J13: 433216 | K13: | | L13: 16421598 | M13: | | N13: 7017799 | O13: | | P13: 5213455 | Q13: | | R13: 12347769 | S13: | | T13: 33664427 | U13: | | V13: 868614 | W13: | | X13: 2138478 | Y13: | | AA13: | | AB13: 2593235 | AC13: | | AE13: | | AG13: | | AI13: | | AJ13: 1111614 | AK13: | | AL13: 153402920 | AM13: | | AO13: | | AQ13: | | AR13: 5828627 | AS13: | | AU13: | | AW13: | | AY13: | | BA13: | | BB13: 3254202 | BC13: | | BD13: 3919418 | BE13: | | BF13: 1414172 | BG13: | | BH13: 195242 | BI13: | | BJ13: 13693942 | BK13: | | BM13: | | BO13: | | BP13: 797062 | BQ13: | | BR13: 3812551 | BS13: | | BU13: | | BW13: | | BY13: | | CA13: | | CB13: 2977217 | CC13: | | CD13: 1735984 | CE13: | | CF13: 21351124 | CG13: | | CH13: 46691201 | CI13: | | CJ13: 2458856 | CK13: | | CM13: | | CO13: | | CP13: 2852068 | CQ13: | | CS13: | | CU13: | | CV13: 30220203 | CW13: | | CX13: 2691050 | CY13: | | CZ13: 7425961 | DA13: | | DB13: 1147565 | DC13: | | DD13: 5106272 | DE13: | | DF13: 3216142 | DG13: | | DI13: | | DJ13: 9192444 | DK13: | | DL13: 24813543 | DM13: | | DO13: | | DQ13: | | DR13: 976985 | DS13: | | DT13: 4809755 | DU13: | | DW13: | | DY13: | | EA13: | | EC13: | | EE13: | | EF13: 4962701 | EG13: | | EI13: | | EJ13: 3857014 | EK13: | | EL13: 2488097 | EM13: | | EN13: 1333045 | EO13: | | EQ13: | | ES13: | | EU13: | | EV13: 54253011 | EW13: | | EY13: | | EZ13: 1874414 | FA13: | | FB13: 604807 | FC13: | | FD13: 3222083 | FE13: | | FG13: | | FI13: | | FJ13: 158166933 | FK13: | | FL13: 97862726 | FM13: | | FN13: 5417651 | FO13: | | FQ13: | | FS13: | | FU13: | | FW13: | | FY13: | | GA13: | | GC13: | | GE13: | | GG13: | | GH13: 1742817 | GI13: | | GJ13: 18310585 | GK13: | | GL13: 18715981 | GM13: | | GO13: | | GQ13: | | GS13: | | GT13: 5888294 | GU13: | | GV13: 3131088 | GW13: | | GX13: 9576458 | GY13: | | HA13: | | HC13: | | HE13: | | HF13: 833448235 | HG13: | | HI13: | | HJ13: 833448235 | HK13: |
A14: 1240 | B14: PENALTY/INT ON TAX (FISC DEPEN) | C14: | | D14: 597511 | E14: | | G14: | | I14: | | K14: | | L14: 880175 | M14: | | N14: 621538 | O14: | | Q14: | | S14: | | T14: 1894677 | U14: | | W14: | | X14: 154664 | Y14: | | AA14: | | AB14: 263749 | AC14: | | AE14: | | AG14: | | AI14: | | AJ14: 7827 | AK14: | | AL14: 1108823 | AM14: | | AO14: | | AQ14: | | AR14: 314398 | AS14: | | AU14: | | AW14: | | AY14: | | BA14: | | BB14: 20715 | BC14: | | BD14: 58335 | BE14: | | BF14: 14132 | BG14: | | BI14: | | BK14: | | BM14: | | BO14: | | BP14: 10867 | BQ14: | | BR14: 45178 | BS14: | | BU14: | | BW14: | | BY14: | | CA14: | | CC14: | | CE14: | | CF14: 128917 | CG14: | | CH14: 94545 | CI14: | | CJ14: 8145 | CK14: | | CM14: | | CO14: | | CP14: 8204 | CQ14: | | CS14: | | CU14: | | CV14: 3144240 | CW14: | | CX14: 28733 | CY14: | | CZ14: 20006 | DA14: | | DB14: 101865 | DC14: | | DD14: 36588 | DE14: | | DF14: 44176 | DG14: | | DI14: | | DJ14: 147877 | DK14: | | DL14: 381137 | DM14: | | DO14: | | DQ14: | | DS14: | | DT14: 41064 | DU14: | | DW14: | | DY14: | | EA14: | | EC14: | | EE14: | | EG14: | | EI14: | | EJ14: 56050 | EK14: | | EL14: 36677 | EM14: | | EN14: 121914 | EO14: | | EQ14: | | ES14: | | EU14: | | EV14: 172869 | EW14: | | EY14: | | FA14: | | FC14: | | FE14: | | FG14: | | FI14: | | FJ14: 1748 | FK14: | | FL14: 1202011 | FM14: | | FO14: | | FQ14: | | FS14: | | FU14: | | FW14: | | FY14: | | GA14: | | GC14: | | GE14: | | GG14: | | GI14: | | GK14: | | GM14: | | GO14: | | GQ14: | | GS14: | | GT14: 233092 | GU14: | | GV14: 89758 | GW14: | | GY14: | | HA14: | | HC14: | | HE14: | | HF14: 12092205 | HG14: | | HI14: | | HJ14: 12092205 | HK14: |
A15: 1280 | B15: REV IN LIEU OF TAX (INDEP & DEP) | C15: | | D15: 248250 | E15: | | F15: 3228180 | G15: | | H15: 30934 | I15: | | J15: 16195 | K15: | | L15: 281920 | M15: | | N15: 110149 | O15: | | P15: 663826 | Q15: | | R15: 987719 | S15: | | T15: 705878 | U15: | | V15: 32380 | W15: | | X15: 37121 | Y15: | | AA15: | | AB15: 58802 | AC15: | | AD15: 337725 | AE15: | | AG15: | | AI15: | | AK15: | | AL15: 72555 | AM15: | | AO15: | | AP15: 11717128 | AQ15: | | AR15: 1501169 | AS15: | | AU15: | | AV15: 3487340 | AW15: | | AX15: 1808893 | AY15: | | AZ15: 1012904 | BA15: | | BC15: | | BE15: | | BG15: | | BI15: | | BK15: | | BL15: 2270051 | BM15: | | BO15: | | BQ15: | | BS15: | | BU15: | | BW15: | | BX15: 2558555 | BY15: | | BZ15: 136438 | CA15: | | CC15: | | CE15: | | CF15: 81935 | CG15: | | CH15: 1352744 | CI15: | | CJ15: 18213 | CK15: | | CL15: 512915 | CM15: | | CN15: 778498 | CO15: | | CP15: 75913 | CQ15: | | CR15: 260827 | CS15: | | CT15: 14519384 | CU15: | | CW15: | | CX15: 239598 | CY15: | | DA15: | | DC15: | | DD15: 175 | DE15: | | DG15: | | DH15: 3339957 | DI15: | | DJ15: 424974 | DK15: | | DL15: 2160178 | DM15: | | DN15: 1429643 | DO15: | | DP15: 262951 | DQ15: | | DR15: 635032 | DS15: | | DT15: 151497 | DU15: | | DV15: 3660322 | DW15: | | DX15: 1228103 | DY15: | | DZ15: 9708 | EA15: | | EB15: 449301 | EC15: | | ED15: 78278 | EE15: | | EF15: 138537 | EG15: | | EI15: | | EJ15: 107735 | EK15: | | EL15: 66565 | EM15: | | EO15: | | EQ15: | | ER15: 2473128 | ES15: | | ET15: 1173323 | EU15: | | EV15: 1913859 | EW15: | | EY15: | | EZ15: 983273 | FA15: | | FB15: 164336 | FC15: | | FD15: 1488642 | FE15: | | FG15: | | FH15: 57293 | FI15: | | FJ15: 6147665 | FK15: | | FL15: 955039 | FM15: | | FO15: | | FQ15: | | FR15: 66554 | FS15: | | FT15: 1296281 | FU15: | | FV15: 126483 | FW15: | | FX15: 4902610 | FY15: | | FZ15: 1833006 | GA15: | | GB15: 42550 | GC15: | | GD15: 2821 | GE15: | | GF15: 11374 | GG15: | | GI15: | | GJ15: 286707 | GK15: | | GM15: | | GO15: | | GQ15: | | GR15: 3398472 | GS15: | | GU15: | | GV15: 194008 | GW15: | | GY15: | | GZ15: 2423424 | HA15: | | HC15: | | HE15: | | HF15: 93227943 | HG15: | | HI15: | | HJ15: 93227943 | HK15: |
A16: 1290 | B16: OTHER TAXES (FISCALLY DEPENDENT) | C16: | | D16: -185981 | E16: | | G16: | | I16: | | K16: | | L16: 2529411 | M16: | | N16: 1058039 | O16: | | Q16: | | S16: | | T16: 3578859 | U16: | | W16: | | Y16: | | AA16: | | AC16: | | AE16: | | AG16: | | AI16: | | AK16: | | AM16: | | AO16: | | AQ16: | | AS16: | | AU16: | | AW16: | | AY16: | | AZ16: 2678003 | BA16: | | BB16: 498106 | BC16: | | BE16: | | BF16: 592984 | BG16: | | BI16: | | BK16: | | BM16: | | BO16: | | BP16: 191741 | BQ16: | | BR16: 693689 | BS16: | | BU16: | | BW16: | | BY16: | | CA16: | | CC16: | | CE16: | | CG16: | | CI16: | | CK16: | | CM16: | | CO16: | | CQ16: | | CS16: | | CU16: | | CW16: | | CY16: | | DA16: | | DC16: | | DE16: | | DG16: | | DI16: | | DK16: | | DM16: | | DO16: | | DQ16: | | DS16: | | DT16: 162622 | DU16: | | DW16: | | DY16: | | EA16: | | EC16: | | EE16: | | EG16: | | EI16: | | EK16: | | EM16: | | EO16: | | EQ16: | | ES16: | | EU16: | | EW16: | | EY16: | | FA16: | | FB16: 2395955 | FC16: | | FE16: | | FG16: | | FI16: | | FK16: | | FM16: | | FO16: | | FQ16: | | FR16: 2896709 | FS16: | | FU16: | | FW16: | | FY16: | | GA16: | | GC16: | | GE16: | | GG16: | | GI16: | | GK16: | | GM16: | | GO16: | | GQ16: | | GS16: | | GU16: | | GW16: | | GY16: | | HA16: | | HC16: | | HE16: | | HF16: 17090137 | HG16: | | HI16: | | HJ16: 17090137 | HK16: |
A17: 1300 | B17: TUITION: | C17: | | E17: | | G17: | | I17: | | K17: | | M17: | | O17: | | Q17: | | S17: | | U17: | | W17: | | Y17: | | AA17: | | AC17: | | AE17: | | AG17: | | AI17: | | AK17: | | AM17: | | AO17: | | AQ17: | | AS17: | | AU17: | | AW17: | | AY17: | | BA17: | | BC17: | | BE17: | | BG17: | | BI17: | | BK17: | | BM17: | | BO17: | | BQ17: | | BS17: | | BU17: | | BW17: | | BY17: | | CA17: | | CC17: | | CE17: | | CG17: | | CI17: | | CK17: | | CM17: | | CO17: | | CQ17: | | CS17: | | CU17: | | CW17: | | CY17: | | DA17: | | DC17: | | DE17: | | DG17: | | DI17: | | DK17: | | DM17: | | DO17: | | DQ17: | | DS17: | | DU17: | | DW17: | | DY17: | | EA17: | | EC17: | | EE17: | | EG17: | | EI17: | | EK17: | | EM17: | | EO17: | | EQ17: | | ES17: | | EU17: | | EW17: | | EY17: | | FA17: | | FC17: | | FE17: | | FG17: | | FI17: | | FK17: | | FM17: | | FO17: | | FQ17: | | FS17: | | FU17: | | FW17: | | FY17: | | GA17: | | GC17: | | GE17: | | GG17: | | GI17: | | GK17: | | GM17: | | GO17: | | GQ17: | | GS17: | | GU17: | | GW17: | | GY17: | | HA17: | | HC17: | | HE17: | | HG17: | | HI17: | | HK17: |
A18: 1310 | B18: REGULAR DAY SCHOOL FRM PATRONS | C18: | | D18: 4600 | E18: | | F18: 19069 | G18: | | I18: | | K18: | | L18: 29796 | M18: | | N18: 13270 | O18: | | P18: 6586 | Q18: | | R18: 9507 | S18: | | U18: | | W18: | | Y18: | | Z18: 44039 | AA18: | | AC18: | | AE18: | | AG18: | | AI18: | | AK18: | | AL18: 40379 | AM18: | | AO18: | | AP18: 2424119 | AQ18: | | AS18: | | AT18: 29275 | AU18: | | AW18: | | AX18: 1517 | AY18: | | AZ18: 61794 | BA18: | | BC18: | | BD18: 6214 | BE18: | | BF18: 100565 | BG18: | | BH18: 4201 | BI18: | | BK18: | | BM18: | | BO18: | | BQ18: | | BS18: | | BU18: | | BW18: | | BY18: | | CA18: | | CB18: 7752 | CC18: | | CD18: 11617 | CE18: | | CF18: 1068 | CG18: | | CH18: 102253 | CI18: | | CK18: | | CL18: 7970 | CM18: | | CO18: | | CP18: 55215 | CQ18: | | CR18: 25358 | CS18: | | CT18: 495128 | CU18: | | CV18: 5400 | CW18: | | CX18: 7750 | CY18: | | CZ18: 9080 | DA18: | | DC18: | | DD18: 28003 | DE18: | | DG18: | | DH18: 59417 | DI18: | | DK18: | | DM18: | | DN18: 37589 | DO18: | | DQ18: | | DR18: 4776 | DS18: | | DU18: | | DV18: 33968 | DW18: | | DX18: 33500 | DY18: | | DZ18: 83297 | EA18: | | EB18: 36675 | EC18: | | ED18: 287505 | EE18: | | EG18: | | EI18: | | EK18: | | EL18: 16296 | EM18: | | EO18: | | EP18: 35090 | EQ18: | | ES18: | | ET18: 1700 | EU18: | | EV18: 103074 | EW18: | | EY18: | | FA18: | | FB18: 25225 | FC18: | | FD18: 77335 | FE18: | | FG18: | | FH18: 240398 | FI18: | | FJ18: 72550 | FK18: | | FL18: 90318 | FM18: | | FO18: | | FP18: 5112 | FQ18: | | FR18: 6335 | FS18: | | FT18: 42214 | FU18: | | FV18: 3550 | FW18: | | FX18: 3815 | FY18: | | FZ18: 29962 | GA18: | | GB18: 47447 | GC18: | | GE18: | | GG18: | | GI18: | | GJ18: 1139 | GK18: | | GL18: 551267 | GM18: | | GO18: | | GQ18: | | GS18: | | GU18: | | GV18: 6218 | GW18: | | GX18: 280631 | GY18: | | GZ18: 139833 | HA18: | | HC18: | | HE18: | | HF18: 5907761 | HG18: | | HI18: | | HJ18: 5907761 | HK18: |
A19: 1320 | B19: REG DAY SCHL FROM OTHER LEA'S | C19: | | E19: | | F19: 12820 | G19: | | H19: 47341 | I19: | | K19: | | L19: 17317 | M19: | | O19: | | Q19: | | S19: | | T19: 76940 | U19: | | W19: | | X19: 1221292 | Y19: | | AA19: | | AC19: | | AE19: | | AG19: | | AH19: 90802 | AI19: | | AJ19: 181167 | AK19: | | AM19: | | AN19: 2431388 | AO19: | | AP19: 56192 | AQ19: | | AS19: | | AU19: | | AW19: | | AX19: 50000 | AY19: | | AZ19: 16318 | BA19: | | BC19: | | BE19: | | BG19: | | BH19: 750617 | BI19: | | BJ19: 11183 | BK19: | | BM19: | | BO19: | | BQ19: | | BS19: | | BU19: | | BW19: | | BY19: | | BZ19: 14134 | CA19: | | CC19: | | CE19: | | CG19: | | CH19: 78083 | CI19: | | CK19: | | CL19: 11617 | CM19: | | CN19: 3122 | CO19: | | CQ19: | | CS19: | | CU19: | | CW19: | | CY19: | | DA19: | | DC19: | | DE19: | | DG19: | | DI19: | | DK19: | | DL19: 24318 | DM19: | | DN19: 21353 | DO19: | | DQ19: | | DR19: 5787 | DS19: | | DU19: | | DV19: 197914 | DW19: | | DX19: 668225 | DY19: | | EA19: | | EC19: | | EE19: | | EG19: | | EH19: 375077 | EI19: | | EK19: | | EM19: | | EO19: | | EP19: 329502 | EQ19: | | ES19: | | ET19: 13989 | EU19: | | EV19: 21750 | EW19: | | EY19: | | FA19: | | FB19: 6195 | FC19: | | FD19: 24622 | FE19: | | FF19: 759620 | FG19: | | FH19: 63211 | FI19: | | FJ19: 396184 | FK19: | | FL19: 882 | FM19: | | FO19: | | FQ19: | | FR19: 81313 | FS19: | | FU19: | | FW19: | | FY19: | | FZ19: 31574 | GA19: | | GB19: 663166 | GC19: | | GD19: 407619 | GE19: | | GF19: 619986 | GG19: | | GH19: 544539 | GI19: | | GJ19: 995368 | GK19: | | GM19: | | GO19: | | GQ19: | | GR19: 22786 | GS19: | | GU19: | | GW19: | | GX19: 15962 | GY19: | | HA19: | | HC19: | | HE19: | | HF19: 11361275 | HG19: | | HI19: | | HJ19: 11361275 | HK19: |
A20: 1330 | B20: ADULT/CONT ED FROM PATRONS | C20: | | E20: | | F20: 12354 | G20: | | I20: | | K20: | | M20: | | O20: | | Q20: | | S20: | | U20: | | W20: | | X20: 29659 | Y20: | | AA20: | | AC20: | | AD20: 1267 | AE20: | | AG20: | | AI20: | | AK20: | | AM20: | | AO20: | | AQ20: | | AR20: 12856 | AS20: | | AU20: | | AV20: 11021 | AW20: | | AY20: | | AZ20: 18550 | BA20: | | BC20: | | BE20: | | BG20: | | BH20: 15692 | BI20: | | BK20: | | BM20: | | BO20: | | BQ20: | | BR20: 3490 | BS20: | | BU20: | | BW20: | | BX20: 105071 | BY20: | | CA20: | | CC20: | | CE20: | | CF20: 141 | CG20: | | CH20: 146348 | CI20: | | CK20: | | CM20: | | CO20: | | CQ20: | | CS20: | | CT20: 509383 | CU20: | | CV20: 20362 | CW20: | | CY20: | | DA20: | | DC20: | | DE20: | | DG20: | | DH20: 15248 | DI20: | | DK20: | | DM20: | | DN20: 20604 | DO20: | | DQ20: | | DS20: | | DU20: | | DW20: | | DX20: 100 | DY20: | | EA20: | | EC20: | | EE20: | | EG20: | | EI20: | | EK20: | | EM20: | | EO20: | | EP20: 520 | EQ20: | | ES20: | | EU20: | | EV20: 6002 | EW20: | | EY20: | | FA20: | | FC20: | | FE20: | | FG20: | | FI20: | | FJ20: 66956 | FK20: | | FM20: | | FO20: | | FQ20: | | FS20: | | FU20: | | FW20: | | FY20: | | GA20: | | GB20: 13313 | GC20: | | GE20: | | GG20: | | GI20: | | GK20: | | GL20: 7190 | GM20: | | GO20: | | GQ20: | | GR20: 41319 | GS20: | | GU20: | | GW20: | | GY20: | | HA20: | | HC20: | | HE20: | | HF20: 1057446 | HG20: | | HI20: | | HJ20: 1057446 | HK20: |
A21: 1340 | B21: ADULT/CONT ED FROM OTHER LEA'S | C21: | | E21: | | G21: | | I21: | | K21: | | M21: | | O21: | | Q21: | | S21: | | U21: | | W21: | | Y21: | | AA21: | | AC21: | | AE21: | | AG21: | | AI21: | | AK21: | | AM21: | | AO21: | | AQ21: | | AS21: | | AU21: | | AW21: | | AY21: | | BA21: | | BC21: | | BE21: | | BG21: | | BH21: 12000 | BI21: | | BK21: | | BM21: | | BO21: | | BQ21: | | BS21: | | BU21: | | BW21: | | BY21: | | CA21: | | CC21: | | CE21: | | CG21: | | CI21: | | CK21: | | CM21: | | CO21: | | CQ21: | | CS21: | | CU21: | | CW21: | | CY21: | | DA21: | | DC21: | | DE21: | | DG21: | | DI21: | | DK21: | | DM21: | | DO21: | | DQ21: | | DS21: | | DU21: | | DW21: | | DY21: | | EA21: | | EC21: | | EE21: | | EG21: | | EI21: | | EK21: | | EM21: | | EO21: | | EQ21: | | ES21: | | EU21: | | EV21: 3960 | EW21: | | EY21: | | FA21: | | FC21: | | FE21: | | FG21: | | FI21: | | FK21: | | FM21: | | FO21: | | FQ21: | | FS21: | | FU21: | | FW21: | | FY21: | | GA21: | | GC21: | | GE21: | | GG21: | | GI21: | | GK21: | | GM21: | | GO21: | | GQ21: | | GS21: | | GU21: | | GW21: | | GY21: | | HA21: | | HC21: | | HE21: | | HF21: 15960 | HG21: | | HI21: | | HJ21: 15960 | HK21: |
A22: 1350 | B22: SUMMER SCHOOL FROM PATRONS | C22: | | D22: 2400 | E22: | | G22: | | I22: | | K22: | | L22: 52183 | M22: | | N22: 16242 | O22: | | P22: 7992 | Q22: | | S22: | | U22: | | W22: | | Y22: | | AA22: | | AB22: 250 | AC22: | | AE22: | | AG22: | | AH22: 29544 | AI22: | | AK22: | | AM22: | | AN22: 780636 | AO22: | | AQ22: | | AS22: | | AU22: | | AV22: 22803 | AW22: | | AY22: | | AZ22: 18050 | BA22: | | BC22: | | BE22: | | BG22: | | BI22: | | BK22: | | BM22: | | BO22: | | BP22: 900 | BQ22: | | BR22: 5150 | BS22: | | BU22: | | BW22: | | BX22: 184486 | BY22: | | BZ22: 12995 | CA22: | | CB22: 2925 | CC22: | | CE22: | | CG22: | | CI22: | | CK22: | | CM22: | | CN22: 460 | CO22: | | CQ22: | | CR22: 20638 | CS22: | | CT22: 278417 | CU22: | | CW22: | | CX22: 7390 | CY22: | | CZ22: 200 | DA22: | | DC22: | | DE22: | | DG22: | | DH22: 147814 | DI22: | | DJ22: 8294 | DK22: | | DM22: | | DN22: 11420 | DO22: | | DQ22: | | DS22: | | DT22: 11980 | DU22: | | DW22: | | DX22: 38629 | DY22: | | EA22: | | EC22: | | ED22: 75910 | EE22: | | EG22: | | EI22: | | EJ22: 15033 | EK22: | | EL22: 3040 | EM22: | | EO22: | | EQ22: | | ES22: | | ET22: 6250 | EU22: | | EV22: 75695 | EW22: | | EY22: | | EZ22: 74383 | FA22: | | FB22: 33386 | FC22: | | FD22: 16724 | FE22: | | FG22: | | FH22: 45210 | FI22: | | FJ22: 61125 | FK22: | | FL22: 90223 | FM22: | | FO22: | | FP22: 3400 | FQ22: | | FR22: 3050 | FS22: | | FU22: | | FW22: | | FX22: 3575 | FY22: | | FZ22: 1000 | GA22: | | GB22: 22365 | GC22: | | GE22: | | GG22: | | GI22: | | GJ22: 6942 | GK22: | | GL22: 11978 | GM22: | | GO22: | | GQ22: | | GS22: | | GU22: | | GW22: | | GX22: 123250 | GY22: | | GZ22: 20749 | HA22: | | HC22: | | HE22: | | HF22: 2355086 | HG22: | | HI22: | | HJ22: 2355086 | HK22: |
A23: 1360 | B23: SUMMER SCHOOL FROM OTHER LEA'S | C23: | | E23: | | G23: | | I23: | | K23: | | M23: | | O23: | | Q23: | | S23: | | U23: | | W23: | | Y23: | | AA23: | | AC23: | | AE23: | | AG23: | | AI23: | | AK23: | | AM23: | | AO23: | | AQ23: | | AS23: | | AU23: | | AW23: | | AY23: | | BA23: | | BC23: | | BE23: | | BG23: | | BI23: | | BK23: | | BM23: | | BO23: | | BQ23: | | BS23: | | BU23: | | BW23: | | BY23: | | CA23: | | CC23: | | CE23: | | CG23: | | CI23: | | CK23: | | CM23: | | CO23: | | CQ23: | | CS23: | | CU23: | | CW23: | | CY23: | | DA23: | | DC23: | | DE23: | | DG23: | | DH23: 400 | DI23: | | DK23: | | DM23: | | DO23: | | DQ23: | | DS23: | | DU23: | | DW23: | | DY23: | | EA23: | | EC23: | | EE23: | | EG23: | | EI23: | | EK23: | | EM23: | | EO23: | | EQ23: | | ES23: | | EU23: | | EW23: | | EY23: | | FA23: | | FC23: | | FE23: | | FG23: | | FI23: | | FK23: | | FL23: 104200 | FM23: | | FO23: | | FQ23: | | FS23: | | FU23: | | FW23: | | FY23: | | GA23: | | GC23: | | GE23: | | GG23: | | GI23: | | GK23: | | GM23: | | GO23: | | GQ23: | | GS23: | | GU23: | | GW23: | | GY23: | | HA23: | | HC23: | | HE23: | | HF23: 104600 | HG23: | | HI23: | | HJ23: 104600 | HK23: |
A24: 1400 | B24: TRANSPORTATION FEES: | C24: | | E24: | | G24: | | I24: | | K24: | | M24: | | O24: | | Q24: | | S24: | | U24: | | W24: | | Y24: | | AA24: | | AC24: | | AE24: | | AG24: | | AI24: | | AK24: | | AM24: | | AO24: | | AQ24: | | AS24: | | AU24: | | AW24: | | AY24: | | BA24: | | BC24: | | BE24: | | BG24: | | BI24: | | BK24: | | BM24: | | BO24: | | BQ24: | | BS24: | | BU24: | | BW24: | | BY24: | | CA24: | | CC24: | | CE24: | | CG24: | | CI24: | | CK24: | | CM24: | | CO24: | | CQ24: | | CS24: | | CU24: | | CW24: | | CY24: | | DA24: | | DC24: | | DE24: | | DG24: | | DI24: | | DK24: | | DM24: | | DO24: | | DQ24: | | DS24: | | DU24: | | DW24: | | DY24: | | EA24: | | EC24: | | EE24: | | EG24: | | EI24: | | EK24: | | EM24: | | EO24: | | EQ24: | | ES24: | | EU24: | | EW24: | | EY24: | | FA24: | | FC24: | | FE24: | | FG24: | | FI24: | | FK24: | | FM24: | | FO24: | | FQ24: | | FS24: | | FU24: | | FW24: | | FY24: | | GA24: | | GC24: | | GE24: | | GG24: | | GI24: | | GK24: | | GM24: | | GO24: | | GQ24: | | GS24: | | GU24: | | GW24: | | GY24: | | HA24: | | HC24: | | HE24: | | HG24: | | HI24: | | HK24: |
A25: 1410 | B25: REGULAR DAY SCHOOL FRM PATRONS | C25: | | E25: | | G25: | | I25: | | K25: | | L25: 107802 | M25: | | O25: | | Q25: | | S25: | | U25: | | W25: | | Y25: | | AA25: | | AC25: | | AE25: | | AG25: | | AI25: | | AK25: | | AM25: | | AO25: | | AQ25: | | AS25: | | AU25: | | AW25: | | AY25: | | BA25: | | BC25: | | BE25: | | BG25: | | BI25: | | BK25: | | BM25: | | BO25: | | BQ25: | | BS25: | | BU25: | | BW25: | | BY25: | | CA25: | | CC25: | | CE25: | | CG25: | | CI25: | | CK25: | | CM25: | | CO25: | | CQ25: | | CS25: | | CU25: | | CW25: | | CY25: | | DA25: | | DC25: | | DE25: | | DG25: | | DI25: | | DK25: | | DM25: | | DO25: | | DP25: 40077 | DQ25: | | DS25: | | DU25: | | DW25: | | DY25: | | EA25: | | EC25: | | EE25: | | EG25: | | EI25: | | EK25: | | EM25: | | EN25: 3750 | EO25: | | EQ25: | | ES25: | | EU25: | | EV25: 157696 | EW25: | | EY25: | | FA25: | | FC25: | | FE25: | | FG25: | | FI25: | | FJ25: 85349 | FK25: | | FM25: | | FO25: | | FQ25: | | FS25: | | FU25: | | FW25: | | FY25: | | FZ25: 105 | GA25: | | GC25: | | GE25: | | GG25: | | GI25: | | GK25: | | GM25: | | GO25: | | GQ25: | | GS25: | | GU25: | | GW25: | | GY25: | | HA25: | | HC25: | | HE25: | | HF25: 394779 | HG25: | | HI25: | | HJ25: 394779 | HK25: |
A26: 1415 | B26: REGULAR DAY SCHL FRM OTH LEA'S | C26: | | E26: | | G26: | | I26: | | K26: | | L26: 28632 | M26: | | O26: | | Q26: | | S26: | | U26: | | W26: | | Y26: | | AA26: | | AC26: | | AE26: | | AG26: | | AH26: 14420 | AI26: | | AK26: | | AM26: | | AO26: | | AQ26: | | AS26: | | AU26: | | AW26: | | AY26: | | BA26: | | BC26: | | BE26: | | BG26: | | BI26: | | BK26: | | BM26: | | BO26: | | BQ26: | | BS26: | | BU26: | | BW26: | | BY26: | | CA26: | | CC26: | | CE26: | | CG26: | | CI26: | | CK26: | | CM26: | | CO26: | | CQ26: | | CS26: | | CU26: | | CW26: | | CY26: | | DA26: | | DC26: | | DE26: | | DG26: | | DI26: | | DK26: | | DM26: | | DO26: | | DQ26: | | DS26: | | DU26: | | DW26: | | DY26: | | EA26: | | EC26: | | EE26: | | EG26: | | EI26: | | EK26: | | EM26: | | EO26: | | EQ26: | | ES26: | | EU26: | | EW26: | | EY26: | | FA26: | | FC26: | | FE26: | | FG26: | | FI26: | | FK26: | | FM26: | | FO26: | | FQ26: | | FS26: | | FU26: | | FW26: | | FY26: | | GA26: | | GC26: | | GE26: | | GG26: | | GI26: | | GK26: | | GM26: | | GO26: | | GQ26: | | GS26: | | GU26: | | GW26: | | GY26: | | HA26: | | HC26: | | HE26: | | HF26: 43052 | HG26: | | HI26: | | HJ26: 43052 | HK26: |
A27: 1420 | B27: SUMMER SCHOOL FRM PATRONS | C27: | | E27: | | G27: | | I27: | | K27: | | M27: | | O27: | | Q27: | | S27: | | U27: | | W27: | | Y27: | | AA27: | | AC27: | | AE27: | | AG27: | | AI27: | | AK27: | | AM27: | | AO27: | | AQ27: | | AS27: | | AU27: | | AW27: | | AY27: | | BA27: | | BC27: | | BE27: | | BG27: | | BI27: | | BK27: | | BM27: | | BO27: | | BQ27: | | BS27: | | BU27: | | BW27: | | BY27: | | CA27: | | CC27: | | CE27: | | CG27: | | CI27: | | CK27: | | CM27: | | CO27: | | CQ27: | | CS27: | | CU27: | | CW27: | | CY27: | | DA27: | | DC27: | | DE27: | | DG27: | | DI27: | | DK27: | | DM27: | | DO27: | | DQ27: | | DS27: | | DU27: | | DW27: | | DY27: | | EA27: | | EC27: | | EE27: | | EG27: | | EI27: | | EK27: | | EM27: | | EO27: | | EQ27: | | ES27: | | EU27: | | EW27: | | EY27: | | FA27: | | FC27: | | FE27: | | FG27: | | FI27: | | FK27: | | FM27: | | FO27: | | FQ27: | | FS27: | | FU27: | | FW27: | | FY27: | | GA27: | | GC27: | | GE27: | | GG27: | | GI27: | | GK27: | | GM27: | | GO27: | | GQ27: | | GS27: | | GU27: | | GW27: | | GY27: | | HA27: | | HC27: | | HE27: | | HG27: | | HI27: | | HK27: |
A28: 1425 | B28: SUMMER SCHOOL FROM OTHER LEA'S | C28: | | E28: | | G28: | | I28: | | K28: | | M28: | | O28: | | Q28: | | S28: | | U28: | | W28: | | Y28: | | AA28: | | AC28: | | AE28: | | AG28: | | AI28: | | AK28: | | AM28: | | AO28: | | AQ28: | | AS28: | | AU28: | | AW28: | | AY28: | | BA28: | | BC28: | | BE28: | | BG28: | | BI28: | | BK28: | | BM28: | | BO28: | | BQ28: | | BS28: | | BU28: | | BW28: | | BY28: | | CA28: | | CC28: | | CE28: | | CG28: | | CI28: | | CK28: | | CM28: | | CO28: | | CQ28: | | CS28: | | CU28: | | CW28: | | CY28: | | DA28: | | DC28: | | DE28: | | DG28: | | DI28: | | DK28: | | DM28: | | DO28: | | DQ28: | | DS28: | | DU28: | | DW28: | | DY28: | | EA28: | | EC28: | | EE28: | | EG28: | | EI28: | | EK28: | | EM28: | | EO28: | | EQ28: | | ES28: | | EU28: | | EW28: | | EY28: | | FA28: | | FC28: | | FE28: | | FG28: | | FI28: | | FK28: | | FM28: | | FO28: | | FQ28: | | FS28: | | FU28: | | FW28: | | FY28: | | GA28: | | GC28: | | GE28: | | GG28: | | GI28: | | GK28: | | GM28: | | GO28: | | GQ28: | | GS28: | | GU28: | | GW28: | | GY28: | | HA28: | | HC28: | | HE28: | | HG28: | | HI28: | | HK28: |
A29: 1500 | B29: EARNINGS ON INVESTMENTS: | C29: | | E29: | | G29: | | I29: | | K29: | | M29: | | O29: | | Q29: | | S29: | | U29: | | W29: | | Y29: | | AA29: | | AC29: | | AE29: | | AG29: | | AI29: | | AK29: | | AM29: | | AO29: | | AQ29: | | AS29: | | AU29: | | AW29: | | AY29: | | BA29: | | BC29: | | BE29: | | BG29: | | BI29: | | BK29: | | BM29: | | BO29: | | BQ29: | | BS29: | | BU29: | | BW29: | | BY29: | | CA29: | | CC29: | | CE29: | | CG29: | | CI29: | | CK29: | | CM29: | | CO29: | | CQ29: | | CS29: | | CU29: | | CW29: | | CY29: | | DA29: | | DC29: | | DE29: | | DG29: | | DI29: | | DK29: | | DM29: | | DO29: | | DQ29: | | DS29: | | DU29: | | DW29: | | DY29: | | EA29: | | EC29: | | EE29: | | EG29: | | EI29: | | EK29: | | EM29: | | EO29: | | EQ29: | | ES29: | | EU29: | | EW29: | | EY29: | | FA29: | | FC29: | | FE29: | | FG29: | | FI29: | | FK29: | | FM29: | | FO29: | | FQ29: | | FS29: | | FU29: | | FW29: | | FY29: | | GA29: | | GC29: | | GE29: | | GG29: | | GI29: | | GK29: | | GM29: | | GO29: | | GQ29: | | GS29: | | GU29: | | GW29: | | GY29: | | HA29: | | HC29: | | HE29: | | HG29: | | HI29: | | HK29: |
A30: 1510 | B30: INTEREST ON INVESTMENTS | C30: | | D30: 134656 | E30: | | F30: 1019518 | G30: | | H30: 26508 | I30: | | J30: 14227 | K30: | | L30: 382520 | M30: | | N30: 175851 | O30: | | P30: 593746 | Q30: | | R30: 1393711 | S30: | | T30: 995816 | U30: | | V30: 24583 | W30: | | X30: 101910 | Y30: | | Z30: 86610 | AA30: | | AB30: 31703 | AC30: | | AD30: 33738 | AE30: | | AF30: 51617 | AG30: | | AH30: 283442 | AI30: | | AJ30: 3750 | AK30: | | AL30: 6091855 | AM30: | | AN30: 17315 | AO30: | | AP30: 9966532 | AQ30: | | AR30: 1039571 | AS30: | | AT30: 31663984 | AU30: | | AV30: 2551948 | AW30: | | AX30: 657255 | AY30: | | AZ30: 775806 | BA30: | | BB30: 480114 | BC30: | | BD30: 157046 | BE30: | | BF30: 95143 | BG30: | | BH30: 77 | BI30: | | BJ30: 2944533 | BK30: | | BL30: 2511589 | BM30: | | BN30: 61978 | BO30: | | BP30: 25012 | BQ30: | | BR30: 213591 | BS30: | | BT30: 146640 | BU30: | | BV30: 10776 | BW30: | | BX30: 6061613 | BY30: | | BZ30: 328116 | CA30: | | CB30: 70250 | CC30: | | CD30: 263705 | CE30: | | CF30: 455917 | CG30: | | CH30: 2392922 | CI30: | | CJ30: 22739 | CK30: | | CL30: 447808 | CM30: | | CN30: 65072 | CO30: | | CP30: 173768 | CQ30: | | CR30: 1222449 | CS30: | | CT30: 26367262 | CU30: | | CV30: 3868814 | CW30: | | CX30: 140798 | CY30: | | CZ30: 148978 | DA30: | | DB30: 15150 | DC30: | | DD30: 78885 | DE30: | | DF30: 99706 | DG30: | | DH30: 9414516 | DI30: | | DJ30: 858451 | DK30: | | DL30: 6396413 | DM30: | | DN30: 2710836 | DO30: | | DP30: 891984 | DQ30: | | DR30: 1098339 | DS30: | | DT30: 256399 | DU30: | | DV30: 8581616 | DW30: | | DX30: 1636238 | DY30: | | DZ30: 159922 | EA30: | | EB30: 414131 | EC30: | | ED30: 1932695 | EE30: | | EF30: 121817 | EG30: | | EH30: 88904 | EI30: | | EJ30: 317612 | EK30: | | EL30: 295666 | EM30: | | EN30: 93279 | EO30: | | EP30: 50194 | EQ30: | | ER30: 125350 | ES30: | | ET30: 3580991 | EU30: | | EV30: 1454347 | EW30: | | EY30: | | EZ30: 412277 | FA30: | | FB30: 386574 | FC30: | | FD30: 1137980 | FE30: | | FF30: 2297 | FG30: | | FH30: 9208926 | FI30: | | FJ30: 7846289 | FK30: | | FL30: 5121247 | FM30: | | FN30: 159958 | FO30: | | FP30: 1053150 | FQ30: | | FR30: 1413118 | FS30: | | FT30: 802732 | FU30: | | FV30: 520570 | FW30: | | FX30: 3698436 | FY30: | | FZ30: 1076282 | GA30: | | GB30: 1152244 | GC30: | | GD30: 3680 | GE30: | | GF30: 21482 | GG30: | | GH30: 19850 | GI30: | | GJ30: 2016865 | GK30: | | GL30: 1476955 | GM30: | | GO30: | | GP30: 1460897 | GQ30: | | GR30: 721203 | GS30: | | GT30: 760084 | GU30: | | GV30: 1333915 | GW30: | | GX30: 3715398 | GY30: | | GZ30: 3658618 | HA30: | | HC30: | | HE30: | | HF30: 196649350 | HG30: | | HI30: | | HJ30: 196649350 | HK30: |
A31: 1520 | B31: DIVIDENDS ON INVESTMENTS | C31: | | E31: | | F31: 156526 | G31: | | I31: | | K31: | | M31: | | O31: | | Q31: | | S31: | | U31: | | W31: | | Y31: | | AA31: | | AC31: | | AE31: | | AG31: | | AI31: | | AK31: | | AM31: | | AO31: | | AQ31: | | AS31: | | AU31: | | AW31: | | AY31: | | BA31: | | BC31: | | BE31: | | BG31: | | BI31: | | BK31: | | BM31: | | BO31: | | BQ31: | | BS31: | | BU31: | | BW31: | | BY31: | | CA31: | | CC31: | | CE31: | | CG31: | | CI31: | | CK31: | | CM31: | | CO31: | | CQ31: | | CS31: | | CU31: | | CW31: | | CY31: | | DA31: | | DC31: | | DE31: | | DG31: | | DI31: | | DK31: | | DM31: | | DO31: | | DQ31: | | DS31: | | DU31: | | DW31: | | DY31: | | EA31: | | EC31: | | EE31: | | EG31: | | EI31: | | EK31: | | EM31: | | EO31: | | EQ31: | | ES31: | | EU31: | | EW31: | | EY31: | | FA31: | | FC31: | | FE31: | | FG31: | | FI31: | | FK31: | | FM31: | | FO31: | | FQ31: | | FS31: | | FU31: | | FW31: | | FY31: | | GA31: | | GC31: | | GE31: | | GG31: | | GI31: | | GK31: | | GM31: | | GO31: | | GQ31: | | GS31: | | GU31: | | GW31: | | GY31: | | HA31: | | HC31: | | HE31: | | HF31: 156526 | HG31: | | HI31: | | HJ31: 156526 | HK31: |
A32: 1530 | B32: GAIN/LOSS ON SALE OF INVEST | C32: | | E32: | | G32: | | I32: | | K32: | | M32: | | O32: | | Q32: | | S32: | | U32: | | W32: | | Y32: | | AA32: | | AC32: | | AE32: | | AG32: | | AI32: | | AK32: | | AM32: | | AO32: | | AQ32: | | AS32: | | AU32: | | AV32: 22159 | AW32: | | AY32: | | BA32: | | BC32: | | BE32: | | BG32: | | BI32: | | BK32: | | BM32: | | BO32: | | BQ32: | | BS32: | | BU32: | | BW32: | | BY32: | | CA32: | | CC32: | | CE32: | | CG32: | | CI32: | | CK32: | | CM32: | | CO32: | | CQ32: | | CS32: | | CT32: 123830 | CU32: | | CW32: | | CY32: | | DA32: | | DC32: | | DE32: | | DG32: | | DI32: | | DK32: | | DM32: | | DO32: | | DQ32: | | DS32: | | DU32: | | DW32: | | DY32: | | EA32: | | EC32: | | EE32: | | EG32: | | EI32: | | EK32: | | EM32: | | EO32: | | EQ32: | | ES32: | | EU32: | | EW32: | | EY32: | | FA32: | | FC32: | | FE32: | | FG32: | | FI32: | | FJ32: 31128 | FK32: | | FM32: | | FO32: | | FQ32: | | FS32: | | FU32: | | FW32: | | FY32: | | GA32: | | GC32: | | GE32: | | GG32: | | GI32: | | GK32: | | GM32: | | GO32: | | GQ32: | | GS32: | | GU32: | | GW32: | | GY32: | | HA32: | | HC32: | | HE32: | | HF32: 177117 | HG32: | | HI32: | | HJ32: 177117 | HK32: |
A33: 1600 | B33: FOOD SERVICE: | C33: | | E33: | | G33: | | I33: | | K33: | | M33: | | O33: | | Q33: | | S33: | | U33: | | W33: | | Y33: | | AA33: | | AC33: | | AE33: | | AG33: | | AI33: | | AK33: | | AM33: | | AO33: | | AQ33: | | AS33: | | AU33: | | AW33: | | AY33: | | BA33: | | BC33: | | BE33: | | BG33: | | BI33: | | BK33: | | BM33: | | BO33: | | BQ33: | | BS33: | | BU33: | | BW33: | | BY33: | | CA33: | | CC33: | | CE33: | | CG33: | | CI33: | | CK33: | | CM33: | | CO33: | | CQ33: | | CS33: | | CU33: | | CW33: | | CY33: | | DA33: | | DC33: | | DE33: | | DG33: | | DI33: | | DK33: | | DM33: | | DO33: | | DQ33: | | DS33: | | DU33: | | DW33: | | DY33: | | EA33: | | EC33: | | EE33: | | EG33: | | EI33: | | EK33: | | EM33: | | EO33: | | EQ33: | | ES33: | | EU33: | | EW33: | | EY33: | | FA33: | | FC33: | | FE33: | | FG33: | | FI33: | | FK33: | | FM33: | | FO33: | | FQ33: | | FS33: | | FU33: | | FW33: | | FY33: | | GA33: | | GC33: | | GE33: | | GG33: | | GI33: | | GK33: | | GM33: | | GO33: | | GQ33: | | GS33: | | GU33: | | GW33: | | GY33: | | HA33: | | HC33: | | HE33: | | HG33: | | HI33: | | HK33: |
A34: 1610 | B34: LUNCH SALES TO PUPILS | C34: | | D34: 246083 | E34: | | F34: 1413480 | G34: | | H34: 30345 | I34: | | K34: | | L34: 852482 | M34: | | N34: 366676 | O34: | | P34: 201824 | Q34: | | R34: 286322 | S34: | | T34: 873370 | U34: | | V34: 11557 | W34: | | Y34: | | Z34: 69734 | AA34: | | AB34: 12316 | AC34: | | AD34: 24769 | AE34: | | AF34: 62933 | AG34: | | AH34: 100630 | AI34: | | AK34: | | AL34: 1239577 | AM34: | | AO34: | | AP34: 2238786 | AQ34: | | AR34: 48354 | AS34: | | AT34: 1844001 | AU34: | | AV34: 628479 | AW34: | | AX34: 232350 | AY34: | | AZ34: 446789 | BA34: | | BB34: 39 | BC34: | | BD34: 82123 | BE34: | | BF34: 39445 | BG34: | | BI34: | | BJ34: 188805 | BK34: | | BL34: 521901 | BM34: | | BO34: | | BP34: 40199 | BQ34: | | BR34: 97296 | BS34: | | BT34: 70674 | BU34: | | BW34: | | BX34: 1477132 | BY34: | | BZ34: 75687 | CA34: | | CC34: | | CD34: 218188 | CE34: | | CF34: 132328 | CG34: | | CH34: 1002764 | CI34: | | CJ34: 73929 | CK34: | | CL34: 51994 | CM34: | | CN34: 9318 | CO34: | | CP34: 116700 | CQ34: | | CR34: 589941 | CS34: | | CT34: 5450673 | CU34: | | CV34: 471484 | CW34: | | CX34: 85914 | CY34: | | CZ34: 169699 | DA34: | | DC34: | | DD34: 144530 | DE34: | | DF34: 16626 | DG34: | | DH34: 3925632 | DI34: | | DJ34: 67003 | DK34: | | DL34: 1154336 | DM34: | | DN34: 776698 | DO34: | | DP34: 432990 | DQ34: | | DR34: 234124 | DS34: | | DT34: 31658 | DU34: | | DV34: 2337800 | DW34: | | DX34: 642393 | DY34: | | DZ34: 205793 | EA34: | | EB34: 256088 | EC34: | | ED34: 2293609 | EE34: | | EF34: 28336 | EG34: | | EI34: | | EJ34: 47668 | EK34: | | EL34: 50276 | EM34: | | EN34: 12527 | EO34: | | EQ34: | | ER34: 153858 | ES34: | | ET34: 532300 | EU34: | | EV34: 1184438 | EW34: | | EY34: | | EZ34: 70177 | FA34: | | FB34: 273553 | FC34: | | FD34: 183112 | FE34: | | FG34: | | FH34: 1576485 | FI34: | | FJ34: 1135626 | FK34: | | FL34: 2203713 | FM34: | | FN34: 78426 | FO34: | | FP34: 438070 | FQ34: | | FR34: 955997 | FS34: | | FT34: 296238 | FU34: | | FV34: 305564 | FW34: | | FX34: 653776 | FY34: | | FZ34: 732955 | GA34: | | GB34: 481303 | GC34: | | GE34: | | GG34: | | GI34: | | GJ34: 365772 | GK34: | | GL34: 379982 | GM34: | | GO34: | | GP34: 276492 | GQ34: | | GR34: 80504 | GS34: | | GT34: 367069 | GU34: | | GV34: 781941 | GW34: | | GX34: 1216703 | GY34: | | GZ34: 1067064 | HA34: | | HC34: | | HE34: | | HF34: 50646295 | HG34: | | HI34: | | HJ34: 50646295 | HK34: |
A35: 1620 | B35: BREAKFAST SALES TO PUPILS | C35: | | D35: 953 | E35: | | F35: 6381 | G35: | | I35: | | K35: | | L35: 86755 | M35: | | N35: 24708 | O35: | | Q35: | | S35: | | T35: 4743 | U35: | | W35: | | Y35: | | Z35: 11556 | AA35: | | AB35: 3477 | AC35: | | AD35: 9875 | AE35: | | AF35: 2866 | AG35: | | AH35: 17387 | AI35: | | AK35: | | AL35: 79818 | AM35: | | AO35: | | AP35: 42732 | AQ35: | | AR35: 8161 | AS35: | | AT35: 80564 | AU35: | | AV35: 18927 | AW35: | | AX35: 59270 | AY35: | | AZ35: 2 | BA35: | | BC35: | | BE35: | | BF35: 5024 | BG35: | | BI35: | | BJ35: 1000 | BK35: | | BL35: 28881 | BM35: | | BO35: | | BQ35: | | BR35: 235 | BS35: | | BT35: 250 | BU35: | | BW35: | | BX35: 128196 | BY35: | | CA35: | | CC35: | | CD35: 1575 | CE35: | | CG35: | | CH35: 15230 | CI35: | | CJ35: 869 | CK35: | | CM35: | | CN35: 1258 | CO35: | | CP35: 18937 | CQ35: | | CR35: 22260 | CS35: | | CT35: 342432 | CU35: | | CV35: 26906 | CW35: | | CX35: 5244 | CY35: | | CZ35: 14683 | DA35: | | DC35: | | DD35: 18499 | DE35: | | DF35: 7722 | DG35: | | DH35: 28367 | DI35: | | DJ35: 2570 | DK35: | | DL35: 154734 | DM35: | | DN35: 81645 | DO35: | | DP35: 291 | DQ35: | | DR35: 1663 | DS35: | | DT35: 77 | DU35: | | DV35: 199816 | DW35: | | DX35: 66419 | DY35: | | DZ35: 5050 | EA35: | | EB35: 2974 | EC35: | | ED35: 117514 | EE35: | | EF35: 7293 | EG35: | | EI35: | | EJ35: 14032 | EK35: | | EL35: 1145 | EM35: | | EO35: | | EQ35: | | ER35: 93 | ES35: | | ET35: 21885 | EU35: | | EV35: 13501 | EW35: | | EY35: | | EZ35: 12746 | FA35: | | FB35: 10695 | FC35: | | FD35: 23237 | FE35: | | FG35: | | FH35: 232536 | FI35: | | FJ35: 9107 | FK35: | | FL35: 173475 | FM35: | | FN35: 86369 | FO35: | | FP35: 1314 | FQ35: | | FR35: 88332 | FS35: | | FU35: | | FV35: 23425 | FW35: | | FX35: 53962 | FY35: | | FZ35: 54777 | GA35: | | GC35: | | GE35: | | GG35: | | GI35: | | GJ35: 224 | GK35: | | GM35: | | GO35: | | GP35: 12991 | GQ35: | | GR35: 9281 | GS35: | | GT35: 22029 | GU35: | | GV35: 39243 | GW35: | | GX35: 283905 | GY35: | | GZ35: 42476 | HA35: | | HC35: | | HE35: | | HF35: 2996569 | HG35: | | HI35: | | HJ35: 2996569 | HK35: |
A36: 1630 | B36: SPECIAL SALES TO PUPILS | C36: | | D36: 39142 | E36: | | F36: 161805 | G36: | | H36: 20436 | I36: | | K36: | | L36: 614736 | M36: | | N36: 114919 | O36: | | P36: 156186 | Q36: | | R36: 91170 | S36: | | T36: 437833 | U36: | | W36: | | Y36: | | Z36: 91768 | AA36: | | AB36: 27950 | AC36: | | AD36: 15288 | AE36: | | AF36: 475 | AG36: | | AH36: 74594 | AI36: | | AK36: | | AL36: 537023 | AM36: | | AO36: | | AP36: 399631 | AQ36: | | AR36: 47168 | AS36: | | AT36: 3296713 | AU36: | | AV36: 307255 | AW36: | | AX36: 49626 | AY36: | | AZ36: 102661 | BA36: | | BB36: 15349 | BC36: | | BD36: 69727 | BE36: | | BF36: 150732 | BG36: | | BI36: | | BJ36: 88032 | BK36: | | BL36: 96330 | BM36: | | BO36: | | BP36: 16053 | BQ36: | | BR36: 51708 | BS36: | | BT36: 874 | BU36: | | BW36: | | BX36: 1106909 | BY36: | | BZ36: 56477 | CA36: | | CC36: | | CD36: 172122 | CE36: | | CF36: 68701 | CG36: | | CH36: 556005 | CI36: | | CJ36: 4646 | CK36: | | CL36: 30763 | CM36: | | CN36: 26775 | CO36: | | CP36: 72411 | CQ36: | | CR36: 260941 | CS36: | | CT36: 5214333 | CU36: | | CV36: 600750 | CW36: | | CX36: 51740 | CY36: | | CZ36: 25847 | DA36: | | DC36: | | DD36: 41896 | DE36: | | DF36: 2269 | DG36: | | DH36: 1379077 | DI36: | | DJ36: 7482 | DK36: | | DL36: 173723 | DM36: | | DN36: 354227 | DO36: | | DP36: 118897 | DQ36: | | DR36: 88300 | DS36: | | DT36: 25014 | DU36: | | DV36: 2463539 | DW36: | | DX36: 232856 | DY36: | | DZ36: 81663 | EA36: | | EB36: 13529 | EC36: | | ED36: 1935871 | EE36: | | EF36: 2190 | EG36: | | EI36: | | EJ36: 44455 | EK36: | | EL36: 27624 | EM36: | | EO36: | | EQ36: | | ER36: 41249 | ES36: | | ET36: 250718 | EU36: | | EV36: 200255 | EW36: | | EY36: | | EZ36: 23878 | FA36: | | FB36: 31409 | FC36: | | FD36: 104242 | FE36: | | FG36: | | FH36: 310314 | FI36: | | FJ36: 565404 | FK36: | | FL36: 277437 | FM36: | | FN36: 64644 | FO36: | | FP36: 260928 | FQ36: | | FR36: 275690 | FS36: | | FT36: 108205 | FU36: | | FV36: 40571 | FW36: | | FX36: 376169 | FY36: | | FZ36: 433053 | GA36: | | GC36: | | GE36: | | GG36: | | GI36: | | GJ36: 273036 | GK36: | | GL36: 490225 | GM36: | | GO36: | | GP36: 133041 | GQ36: | | GR36: 33866 | GS36: | | GT36: 347649 | GU36: | | GV36: 399735 | GW36: | | GX36: 515229 | GY36: | | GZ36: 685028 | HA36: | | HC36: | | HE36: | | HF36: 28558191 | HG36: | | HI36: | | HJ36: 28558191 | HK36: |
A37: 1640 | B37: LUNCH SALES TO ADULTS | C37: | | D37: 58681 | E37: | | F37: 240995 | G37: | | H37: 40720 | I37: | | K37: | | L37: 53286 | M37: | | N37: 49161 | O37: | | P37: 50977 | Q37: | | R37: 36317 | S37: | | T37: 144626 | U37: | | W37: | | Y37: | | Z37: 13859 | AA37: | | AB37: 16079 | AC37: | | AD37: 25639 | AE37: | | AF37: 17763 | AG37: | | AH37: 36528 | AI37: | | AK37: | | AL37: 98847 | AM37: | | AO37: | | AP37: 252145 | AQ37: | | AR37: 19872 | AS37: | | AT37: 257485 | AU37: | | AV37: 159550 | AW37: | | AX37: 60745 | AY37: | | AZ37: 100929 | BA37: | | BB37: 9964 | BC37: | | BD37: 49068 | BE37: | | BF37: 4464 | BG37: | | BI37: | | BJ37: 80694 | BK37: | | BL37: 120792 | BM37: | | BO37: | | BP37: 25030 | BQ37: | | BR37: 52554 | BS37: | | BT37: 16560 | BU37: | | BW37: | | BX37: 84307 | BY37: | | BZ37: 45033 | CA37: | | CC37: | | CD37: 63217 | CE37: | | CF37: 71395 | CG37: | | CH37: 243331 | CI37: | | CJ37: 15392 | CK37: | | CL37: 33589 | CM37: | | CN37: 7361 | CO37: | | CP37: 20628 | CQ37: | | CR37: 139036 | CS37: | | CT37: 655456 | CU37: | | CV37: 96833 | CW37: | | CX37: 14979 | CY37: | | CZ37: 22311 | DA37: | | DC37: | | DD37: 47637 | DE37: | | DF37: 21611 | DG37: | | DH37: 422376 | DI37: | | DJ37: 14777 | DK37: | | DL37: 165170 | DM37: | | DN37: 106614 | DO37: | | DP37: 73788 | DQ37: | | DR37: 71074 | DS37: | | DT37: 24029 | DU37: | | DV37: 276763 | DW37: | | DX37: 111699 | DY37: | | DZ37: 32955 | EA37: | | EB37: 47293 | EC37: | | ED37: 181136 | EE37: | | EF37: 11792 | EG37: | | EI37: | | EJ37: 31004 | EK37: | | EL37: 35322 | EM37: | | EN37: 9726 | EO37: | | EQ37: | | ER37: 45277 | ES37: | | ET37: 106335 | EU37: | | EV37: 147078 | EW37: | | EY37: | | EZ37: 33327 | FA37: | | FB37: 61989 | FC37: | | FD37: 144208 | FE37: | | FG37: | | FH37: 142647 | FI37: | | FJ37: 172337 | FK37: | | FL37: 351935 | FM37: | | FN37: 48275 | FO37: | | FP37: 56555 | FQ37: | | FR37: 103133 | FS37: | | FT37: 38948 | FU37: | | FV37: 50452 | FW37: | | FX37: 71266 | FY37: | | FZ37: 107062 | GA37: | | GB37: 126637 | GC37: | | GE37: | | GG37: | | GI37: | | GJ37: 110134 | GK37: | | GL37: 79995 | GM37: | | GO37: | | GP37: 61243 | GQ37: | | GR37: 93724 | GS37: | | GT37: 23081 | GU37: | | GV37: 39875 | GW37: | | GX37: 73833 | GY37: | | GZ37: 78109 | HA37: | | HC37: | | HE37: | | HF37: 7658419 | HG37: | | HI37: | | HJ37: 7658419 | HK37: |
A38: 1650 | B38: BREAKFAST SALES TO ADULTS | C38: | | D38: 137 | E38: | | F38: 1959 | G38: | | H38: 834 | I38: | | K38: | | L38: 2977 | M38: | | N38: 410 | O38: | | Q38: | | S38: | | T38: 525 | U38: | | W38: | | Y38: | | Z38: 1368 | AA38: | | AB38: 687 | AC38: | | AD38: 2410 | AE38: | | AF38: 687 | AG38: | | AH38: 718 | AI38: | | AK38: | | AL38: 5538 | AM38: | | AO38: | | AP38: 3272 | AQ38: | | AR38: 1603 | AS38: | | AT38: 12018 | AU38: | | AV38: 3033 | AW38: | | AX38: 2339 | AY38: | | AZ38: 1263 | BA38: | | BB38: 153 | BC38: | | BD38: 1565 | BE38: | | BG38: | | BI38: | | BJ38: 458 | BK38: | | BL38: 2017 | BM38: | | BO38: | | BP38: 767 | BQ38: | | BR38: 1034 | BS38: | | BT38: 665 | BU38: | | BW38: | | BX38: 4455 | BY38: | | BZ38: 4596 | CA38: | | CC38: | | CD38: 1799 | CE38: | | CF38: 7546 | CG38: | | CH38: 6385 | CI38: | | CJ38: 24 | CK38: | | CL38: 6158 | CM38: | | CN38: 922 | CO38: | | CP38: 1536 | CQ38: | | CR38: 3521 | CS38: | | CT38: 20763 | CU38: | | CV38: 4017 | CW38: | | CX38: 119 | CY38: | | CZ38: 450 | DA38: | | DC38: | | DD38: 2080 | DE38: | | DF38: 648 | DG38: | | DH38: 4952 | DI38: | | DJ38: 150 | DK38: | | DL38: 9715 | DM38: | | DN38: 7877 | DO38: | | DP38: 10630 | DQ38: | | DR38: 424 | DS38: | | DT38: 2486 | DU38: | | DV38: 9683 | DW38: | | DX38: 9108 | DY38: | | DZ38: 493 | EA38: | | EB38: 1620 | EC38: | | ED38: 3581 | EE38: | | EG38: | | EI38: | | EJ38: 4040 | EK38: | | EL38: 340 | EM38: | | EN38: 9150 | EO38: | | EQ38: | | ER38: 863 | ES38: | | ET38: 4320 | EU38: | | EV38: 5030 | EW38: | | EY38: | | EZ38: 1999 | FA38: | | FB38: 234 | FC38: | | FD38: 11600 | FE38: | | FG38: | | FH38: 3128 | FI38: | | FJ38: 1907 | FK38: | | FL38: 6131 | FM38: | | FN38: 1781 | FO38: | | FP38: 1243 | FQ38: | | FS38: | | FU38: | | FV38: 788 | FW38: | | FX38: 1074 | FY38: | | FZ38: 4296 | GA38: | | GC38: | | GE38: | | GG38: | | GI38: | | GJ38: 5959 | GK38: | | GL38: 1752 | GM38: | | GO38: | | GP38: 286 | GQ38: | | GR38: 7368 | GS38: | | GT38: 648 | GU38: | | GV38: 1859 | GW38: | | GX38: 10025 | GY38: | | GZ38: 1688 | HA38: | | HC38: | | HE38: | | HF38: 261684 | HG38: | | HI38: | | HJ38: 261684 | HK38: |
A39: 1660 | B39: SPECIAL SALES TO ADULTS | C39: | | D39: 4170 | E39: | | F39: 10071 | G39: | | H39: 25422 | I39: | | K39: | | L39: 28845 | M39: | | N39: 8908 | O39: | | P39: 10678 | Q39: | | R39: 6664 | S39: | | T39: 14790 | U39: | | W39: | | Y39: | | Z39: 28963 | AA39: | | AB39: 4771 | AC39: | | AD39: 13979 | AE39: | | AF39: 1672 | AG39: | | AH39: 27080 | AI39: | | AK39: | | AL39: 24112 | AM39: | | AO39: | | AP39: 58212 | AQ39: | | AR39: 10663 | AS39: | | AT39: 286955 | AU39: | | AV39: 14390 | AW39: | | AX39: 19534 | AY39: | | AZ39: 9752 | BA39: | | BB39: 3196 | BC39: | | BD39: 122458 | BE39: | | BF39: 27298 | BG39: | | BI39: | | BJ39: 15756 | BK39: | | BL39: 65156 | BM39: | | BO39: | | BP39: 2454 | BQ39: | | BR39: 17481 | BS39: | | BT39: 1628 | BU39: | | BW39: | | BX39: 150670 | BY39: | | BZ39: 6289 | CA39: | | CC39: | | CD39: 12236 | CE39: | | CF39: 21957 | CG39: | | CH39: 22446 | CI39: | | CJ39: 3478 | CK39: | | CL39: 18795 | CM39: | | CO39: | | CP39: 7471 | CQ39: | | CR39: 28990 | CS39: | | CT39: 188422 | CU39: | | CV39: 66074 | CW39: | | CX39: 6034 | CY39: | | CZ39: 11703 | DA39: | | DC39: | | DD39: 3564 | DE39: | | DF39: 5995 | DG39: | | DH39: 42076 | DI39: | | DJ39: 14136 | DK39: | | DL39: 10209 | DM39: | | DN39: 60618 | DO39: | | DP39: 7162 | DQ39: | | DR39: 1906 | DS39: | | DT39: 16601 | DU39: | | DV39: 114697 | DW39: | | DX39: 23636 | DY39: | | DZ39: 12324 | EA39: | | EB39: 430 | EC39: | | ED39: 125116 | EE39: | | EF39: 1947 | EG39: | | EI39: | | EJ39: 1836 | EK39: | | EL39: 3827 | EM39: | | EO39: | | EQ39: | | ER39: 12935 | ES39: | | ET39: 19113 | EU39: | | EV39: 21305 | EW39: | | EY39: | | EZ39: 5644 | FA39: | | FB39: 7883 | FC39: | | FD39: 96460 | FE39: | | FG39: | | FH39: 31407 | FI39: | | FJ39: 8771 | FK39: | | FL39: 33581 | FM39: | | FN39: 10752 | FO39: | | FP39: 6900 | FQ39: | | FR39: 6930 | FS39: | | FT39: 7065 | FU39: | | FV39: 6322 | FW39: | | FX39: 14618 | FY39: | | FZ39: 13896 | GA39: | | GC39: | | GE39: | | GG39: | | GI39: | | GJ39: 50801 | GK39: | | GL39: 167125 | GM39: | | GO39: | | GP39: 23360 | GQ39: | | GR39: 57699 | GS39: | | GT39: 13496 | GU39: | | GV39: 26246 | GW39: | | GX39: 221941 | GY39: | | GZ39: 16943 | HA39: | | HC39: | | HE39: | | HF39: 2736896 | HG39: | | HI39: | | HJ39: 2736896 | HK39: |
A40: 1700 | B40: PUPIL ACTIVITIES: | C40: | | E40: | | G40: | | I40: | | K40: | | M40: | | O40: | | Q40: | | S40: | | U40: | | W40: | | Y40: | | AA40: | | AC40: | | AE40: | | AG40: | | AI40: | | AK40: | | AM40: | | AO40: | | AQ40: | | AS40: | | AU40: | | AW40: | | AY40: | | BA40: | | BC40: | | BE40: | | BG40: | | BI40: | | BK40: | | BM40: | | BO40: | | BQ40: | | BS40: | | BU40: | | BW40: | | BY40: | | CA40: | | CC40: | | CE40: | | CG40: | | CI40: | | CK40: | | CM40: | | CO40: | | CQ40: | | CS40: | | CU40: | | CW40: | | CY40: | | DA40: | | DC40: | | DE40: | | DG40: | | DI40: | | DK40: | | DM40: | | DO40: | | DQ40: | | DS40: | | DU40: | | DW40: | | DY40: | | EA40: | | EC40: | | EE40: | | EG40: | | EI40: | | EK40: | | EM40: | | EO40: | | EQ40: | | ES40: | | EU40: | | EW40: | | EY40: | | FA40: | | FC40: | | FE40: | | FG40: | | FI40: | | FK40: | | FM40: | | FO40: | | FQ40: | | FS40: | | FU40: | | FW40: | | FY40: | | GA40: | | GC40: | | GE40: | | GG40: | | GI40: | | GK40: | | GM40: | | GO40: | | GQ40: | | GS40: | | GU40: | | GW40: | | GY40: | | HA40: | | HC40: | | HE40: | | HG40: | | HI40: | | HK40: |
A41: 1710 | B41: ADMISSIONS | C41: | | D41: 380923 | E41: | | F41: 799643 | G41: | | H41: 56234 | I41: | | K41: | | L41: 700203 | M41: | | N41: 156233 | O41: | | P41: 107447 | Q41: | | R41: 214246 | S41: | | T41: 629657 | U41: | | W41: | | Y41: | | Z41: 98026 | AA41: | | AB41: 29797 | AC41: | | AD41: 57140 | AE41: | | AF41: 41315 | AG41: | | AH41: 90107 | AI41: | | AK41: | | AM41: | | AO41: | | AP41: 588838 | AQ41: | | AS41: | | AT41: 1522350 | AU41: | | AV41: 446424 | AW41: | | AX41: 160539 | AY41: | | BA41: | | BB41: 25868 | BC41: | | BD41: 147973 | BE41: | | BF41: 93575 | BG41: | | BI41: | | BJ41: 167504 | BK41: | | BM41: | | BO41: | | BP41: 68378 | BQ41: | | BR41: 111443 | BS41: | | BT41: 61497 | BU41: | | BW41: | | BX41: 306881 | BY41: | | BZ41: 33979 | CA41: | | CC41: | | CE41: | | CF41: 90771 | CG41: | | CH41: 85299 | CI41: | | CJ41: 9910 | CK41: | | CL41: 54968 | CM41: | | CN41: 39610 | CO41: | | CP41: 98288 | CQ41: | | CR41: 338404 | CS41: | | CT41: 1472719 | CU41: | | CV41: 351482 | CW41: | | CX41: 68973 | CY41: | | DA41: | | DC41: | | DE41: | | DF41: 34358 | DG41: | | DH41: 710214 | DI41: | | DJ41: 55913 | DK41: | | DL41: 205922 | DM41: | | DN41: 307732 | DO41: | | DP41: 13011 | DQ41: | | DR41: 209188 | DS41: | | DT41: 72706 | DU41: | | DV41: 601218 | DW41: | | DX41: 165423 | DY41: | | EA41: | | EC41: | | ED41: 394217 | EE41: | | EF41: 41924 | EG41: | | EI41: | | EJ41: 56996 | EK41: | | EL41: 63691 | EM41: | | EN41: 9444 | EO41: | | EQ41: | | ER41: 163408 | ES41: | | ET41: 259715 | EU41: | | EV41: 336641 | EW41: | | EY41: | | EZ41: 85290 | FA41: | | FB41: 24571 | FC41: | | FD41: 189793 | FE41: | | FG41: | | FH41: 1138826 | FI41: | | FJ41: 319461 | FK41: | | FL41: 15761 | FM41: | | FN41: 153568 | FO41: | | FP41: 162837 | FQ41: | | FR41: 352363 | FS41: | | FT41: 103203 | FU41: | | FV41: 161129 | FW41: | | FX41: 539544 | FY41: | | FZ41: 325492 | GA41: | | GB41: 185560 | GC41: | | GE41: | | GG41: | | GI41: | | GJ41: 165548 | GK41: | | GL41: 122774 | GM41: | | GO41: | | GP41: 244711 | GQ41: | | GR41: 158075 | GS41: | | GT41: 21311 | GU41: | | GV41: 156102 | GW41: | | GX41: 124577 | GY41: | | GZ41: 251927 | HA41: | | HC41: | | HE41: | | HF41: 18410788 | HG41: | | HI41: | | HJ41: 18410788 | HK41: |
A42: 1720 | B42: BOOKSTORE SALES | C42: | | D42: 54809 | E42: | | F42: 21105 | G42: | | I42: | | K42: | | L42: 226616 | M42: | | N42: 9050 | O42: | | P42: 38584 | Q42: | | R42: 3733 | S42: | | T42: 10530 | U42: | | W42: | | Y42: | | AA42: | | AC42: | | AE42: | | AF42: 8442 | AG42: | | AH42: 1892 | AI42: | | AK42: | | AM42: | | AO42: | | AP42: 110612 | AQ42: | | AS42: | | AT42: 228887 | AU42: | | AV42: 37075 | AW42: | | AX42: 22427 | AY42: | | BA42: | | BB42: 2501 | BC42: | | BD42: 1310 | BE42: | | BF42: 113570 | BG42: | | BI42: | | BJ42: 4638 | BK42: | | BM42: | | BO42: | | BP42: 10 | BQ42: | | BS42: | | BU42: | | BW42: | | BY42: | | CA42: | | CB42: 549 | CC42: | | CE42: | | CF42: 1442 | CG42: | | CI42: | | CK42: | | CM42: | | CO42: | | CP42: 279062 | CQ42: | | CR42: 15273 | CS42: | | CT42: 22623 | CU42: | | CV42: 13972 | CW42: | | CX42: 10386 | CY42: | | DA42: | | DC42: | | DD42: 1944 | DE42: | | DG42: | | DH42: 629173 | DI42: | | DJ42: 17593 | DK42: | | DL42: 49506 | DM42: | | DN42: 1309254 | DO42: | | DP42: 396066 | DQ42: | | DR42: 123568 | DS42: | | DU42: | | DW42: | | DX42: 2863 | DY42: | | EA42: | | EC42: | | ED42: 42789 | EE42: | | EF42: 1712 | EG42: | | EI42: | | EK42: | | EM42: | | EN42: 43405 | EO42: | | EP42: 29304 | EQ42: | | ES42: | | ET42: 39059 | EU42: | | EV42: 1029363 | EW42: | | EY42: | | FA42: | | FB42: 137260 | FC42: | | FD42: 1119 | FE42: | | FG42: | | FH42: 198 | FI42: | | FJ42: 704820 | FK42: | | FL42: 290263 | FM42: | | FN42: 22759 | FO42: | | FP42: 18295 | FQ42: | | FR42: 6489 | FS42: | | FT42: 20526 | FU42: | | FV42: 6290 | FW42: | | FX42: 40815 | FY42: | | FZ42: 472477 | GA42: | | GB42: 22276 | GC42: | | GE42: | | GG42: | | GI42: | | GJ42: 1137 | GK42: | | GL42: 5431 | GM42: | | GO42: | | GP42: 292651 | GQ42: | | GS42: | | GT42: 43210 | GU42: | | GV42: 19474 | GW42: | | GX42: 807 | GY42: | | HA42: | | HC42: | | HE42: | | HF42: 7060994 | HG42: | | HI42: | | HJ42: 7060994 | HK42: |
A43: 1730 | B43: PUPIL ORGANIZATION MEMBER DUES | C43: | | D43: 256402 | E43: | | F43: 509151 | G43: | | H43: 4616 | I43: | | K43: | | L43: 1160731 | M43: | | N43: 139673 | O43: | | P43: 8181 | Q43: | | R43: 33612 | S43: | | T43: 194997 | U43: | | W43: | | Y43: | | AA43: | | AC43: | | AD43: 6498 | AE43: | | AF43: 38834 | AG43: | | AH43: 2782 | AI43: | | AJ43: 21107 | AK43: | | AL43: 188871 | AM43: | | AN43: 131286 | AO43: | | AP43: 640 | AQ43: | | AR43: 15877 | AS43: | | AT43: 53843 | AU43: | | AV43: 318128 | AW43: | | AX43: 10855 | AY43: | | BA43: | | BC43: | | BD43: 93743 | BE43: | | BF43: 133436 | BG43: | | BH43: 23564 | BI43: | | BK43: | | BM43: | | BO43: | | BP43: 2242 | BQ43: | | BS43: | | BT43: 1995 | BU43: | | BV43: 28207 | BW43: | | BX43: 14549 | BY43: | | BZ43: 1245 | CA43: | | CC43: | | CE43: | | CF43: 491 | CG43: | | CI43: | | CJ43: 17060 | CK43: | | CL43: 104735 | CM43: | | CN43: 6454 | CO43: | | CP43: 167611 | CQ43: | | CR43: 6576 | CS43: | | CT43: 277552 | CU43: | | CV43: 18113 | CW43: | | CX43: 2184 | CY43: | | DA43: | | DC43: | | DD43: 125004 | DE43: | | DF43: 391 | DG43: | | DH43: 26372 | DI43: | | DJ43: 7027 | DK43: | | DL43: 167866 | DM43: | | DN43: 618829 | DO43: | | DP43: 4176 | DQ43: | | DR43: 250609 | DS43: | | DT43: 2814 | DU43: | | DW43: | | DX43: 2427 | DY43: | | EA43: | | EB43: 13005 | EC43: | | EE43: | | EF43: 420 | EG43: | | EI43: | | EK43: | | EM43: | | EN43: 22669 | EO43: | | EP43: 11274 | EQ43: | | ER43: 110409 | ES43: | | ET43: 12398 | EU43: | | EV43: 20149 | EW43: | | EY43: | | FA43: | | FB43: 283605 | FC43: | | FD43: 323615 | FE43: | | FG43: | | FH43: 560613 | FI43: | | FJ43: 53439 | FK43: | | FL43: 4028 | FM43: | | FN43: 41772 | FO43: | | FP43: 1708 | FQ43: | | FR43: 205193 | FS43: | | FT43: 6469 | FU43: | | FW43: | | FX43: 60338 | FY43: | | FZ43: 79818 | GA43: | | GB43: 91099 | GC43: | | GE43: | | GF43: 231 | GG43: | | GI43: | | GJ43: 119345 | GK43: | | GL43: 248365 | GM43: | | GO43: | | GP43: 12678 | GQ43: | | GR43: 175411 | GS43: | | GT43: 111553 | GU43: | | GW43: | | GX43: 4893 | GY43: | | GZ43: 9982 | HA43: | | HC43: | | HE43: | | HF43: 7785835 | HG43: | | HI43: | | HJ43: 7785835 | HK43: |
A44: 1740 | B44: STUDENT FEES | C44: | | E44: | | F44: 1241725 | G44: | | H44: 486 | I44: | | K44: | | L44: 346995 | M44: | | N44: 180356 | O44: | | P44: 51582 | Q44: | | S44: | | T44: 1111058 | U44: | | W44: | | Y44: | | Z44: 66471 | AA44: | | AC44: | | AD44: 12765 | AE44: | | AG44: | | AH44: 33748 | AI44: | | AJ44: 58181 | AK44: | | AM44: | | AO44: | | AP44: 161000 | AQ44: | | AR44: 28299 | AS44: | | AT44: 1599955 | AU44: | | AV44: 883516 | AW44: | | AX44: 328914 | AY44: | | BA44: | | BB44: 6146 | BC44: | | BD44: 70159 | BE44: | | BG44: | | BI44: | | BK44: | | BM44: | | BO44: | | BQ44: | | BS44: | | BT44: 350 | BU44: | | BW44: | | BX44: 353160 | BY44: | | BZ44: 26748 | CA44: | | CC44: | | CE44: | | CF44: 64659 | CG44: | | CI44: | | CJ44: 68945 | CK44: | | CL44: 16039 | CM44: | | CN44: 11112 | CO44: | | CP44: 445 | CQ44: | | CR44: 25713 | CS44: | | CT44: 162716 | CU44: | | CV44: 141104 | CW44: | | CX44: 10376 | CY44: | | DA44: | | DC44: | | DD44: 158758 | DE44: | | DG44: | | DH44: 2141 | DI44: | | DJ44: 13075 | DK44: | | DM44: | | DN44: 55369 | DO44: | | DP44: 52846 | DQ44: | | DS44: | | DT44: 262 | DU44: | | DV44: 884307 | DW44: | | DX44: 1963 | DY44: | | EA44: | | EB44: 73043 | EC44: | | ED44: 1665183 | EE44: | | EF44: 2517 | EG44: | | EI44: | | EJ44: 41428 | EK44: | | EL44: 2549 | EM44: | | EN44: 8089 | EO44: | | EQ44: | | ER44: 62095 | ES44: | | ET44: 186270 | EU44: | | EV44: 96511 | EW44: | | EY44: | | EZ44: 1309 | FA44: | | FC44: | | FD44: 21777 | FE44: | | FG44: | | FH44: 937186 | FI44: | | FJ44: 1557 | FK44: | | FL44: 3065346 | FM44: | | FN44: 153720 | FO44: | | FP44: 96344 | FQ44: | | FR44: 390416 | FS44: | | FT44: 120300 | FU44: | | FV44: 90964 | FW44: | | FX44: 377276 | FY44: | | FZ44: 293691 | GA44: | | GB44: 18731 | GC44: | | GE44: | | GF44: 9647 | GG44: | | GI44: | | GJ44: 61195 | GK44: | | GL44: 65077 | GM44: | | GO44: | | GP44: 51744 | GQ44: | | GR44: 77164 | GS44: | | GT44: 46119 | GU44: | | GV44: 237128 | GW44: | | GX44: 6316 | GY44: | | GZ44: 191211 | HA44: | | HC44: | | HE44: | | HF44: 16683347 | HG44: | | HI44: | | HJ44: 16683347 | HK44: |
A45: 1790 | B45: OTHER PUPIL ACTIVITY | C45: | | D45: 274541 | E45: | | F45: 2384416 | G45: | | H45: 167916 | I45: | | K45: | | L45: 783691 | M45: | | N45: 657967 | O45: | | P45: 417239 | Q45: | | R45: 648494 | S45: | | T45: 1083532 | U45: | | V45: 7174 | W45: | | Y45: | | Z45: 150316 | AA45: | | AB45: 71099 | AC45: | | AD45: 158173 | AE45: | | AF45: 161077 | AG45: | | AH45: 303987 | AI45: | | AJ45: 2163 | AK45: | | AM45: | | AN45: 111 | AO45: | | AP45: 2867929 | AQ45: | | AR45: 245864 | AS45: | | AT45: 4620878 | AU45: | | AV45: 841765 | AW45: | | AX45: 963951 | AY45: | | AZ45: 2485583 | BA45: | | BB45: 60815 | BC45: | | BD45: 530867 | BE45: | | BF45: 57148 | BG45: | | BH45: 7137 | BI45: | | BJ45: 714386 | BK45: | | BL45: 1936739 | BM45: | | BO45: | | BP45: 171566 | BQ45: | | BR45: 203924 | BS45: | | BT45: 310975 | BU45: | | BV45: 23845 | BW45: | | BX45: 1449698 | BY45: | | BZ45: 270535 | CA45: | | CB45: 43652 | CC45: | | CD45: 1134290 | CE45: | | CF45: 288034 | CG45: | | CH45: 2206041 | CI45: | | CJ45: 181662 | CK45: | | CL45: 509743 | CM45: | | CN45: 106777 | CO45: | | CP45: 15090 | CQ45: | | CR45: 1109345 | CS45: | | CT45: 14938652 | CU45: | | CV45: 2086170 | CW45: | | CX45: 174515 | CY45: | | CZ45: 510241 | DA45: | | DB45: 113673 | DC45: | | DD45: 700795 | DE45: | | DF45: 61536 | DG45: | | DH45: 5414834 | DI45: | | DJ45: 117856 | DK45: | | DL45: 1123061 | DM45: | | DN45: 1761 | DO45: | | DP45: 395462 | DQ45: | | DR45: 53626 | DS45: | | DT45: 184128 | DU45: | | DV45: 3590996 | DW45: | | DX45: 1607261 | DY45: | | DZ45: 956641 | EA45: | | EB45: 729275 | EC45: | | ED45: 4274675 | EE45: | | EF45: 79473 | EG45: | | EI45: | | EJ45: 239985 | EK45: | | EL45: 118335 | EM45: | | EN45: 31826 | EO45: | | EP45: 117076 | EQ45: | | ER45: 343939 | ES45: | | ET45: 503629 | EU45: | | EV45: 794856 | EW45: | | EY45: | | EZ45: 526801 | FA45: | | FB45: 490522 | FC45: | | FD45: 256965 | FE45: | | FF45: 28697 | FG45: | | FH45: 1783443 | FI45: | | FJ45: 2337707 | FK45: | | FL45: 4204176 | FM45: | | FN45: 381580 | FO45: | | FP45: 728556 | FQ45: | | FR45: 1565510 | FS45: | | FT45: 475228 | FU45: | | FV45: 493432 | FW45: | | FX45: 1164826 | FY45: | | FZ45: 592774 | GA45: | | GB45: 690193 | GC45: | | GD45: 53806 | GE45: | | GG45: | | GH45: 215400 | GI45: | | GJ45: 772672 | GK45: | | GL45: 618226 | GM45: | | GO45: | | GP45: 7578 | GQ45: | | GR45: 552384 | GS45: | | GT45: 771660 | GU45: | | GV45: 638031 | GW45: | | GX45: 2927230 | GY45: | | GZ45: 947352 | HA45: | | HC45: | | HE45: | | HF45: 93119161 | HG45: | | HI45: | | HJ45: 93119161 | HK45: |
A46: 1900 | B46: OTHER REVENUE FROM LOCAL SOURCES | C46: | | E46: | | G46: | | I46: | | K46: | | M46: | | O46: | | Q46: | | S46: | | U46: | | W46: | | Y46: | | AA46: | | AC46: | | AE46: | | AG46: | | AI46: | | AK46: | | AM46: | | AO46: | | AQ46: | | AS46: | | AU46: | | AW46: | | AY46: | | BA46: | | BC46: | | BE46: | | BG46: | | BI46: | | BK46: | | BM46: | | BO46: | | BQ46: | | BS46: | | BU46: | | BW46: | | BY46: | | CA46: | | CC46: | | CE46: | | CG46: | | CI46: | | CK46: | | CM46: | | CO46: | | CQ46: | | CS46: | | CU46: | | CW46: | | CY46: | | DA46: | | DC46: | | DE46: | | DG46: | | DI46: | | DK46: | | DM46: | | DO46: | | DQ46: | | DS46: | | DU46: | | DW46: | | DY46: | | EA46: | | EC46: | | EE46: | | EG46: | | EI46: | | EK46: | | EM46: | | EO46: | | EQ46: | | ES46: | | EU46: | | EW46: | | EY46: | | FA46: | | FC46: | | FE46: | | FG46: | | FI46: | | FK46: | | FM46: | | FO46: | | FQ46: | | FS46: | | FU46: | | FW46: | | FY46: | | GA46: | | GC46: | | GE46: | | GG46: | | GI46: | | GK46: | | GM46: | | GO46: | | GQ46: | | GS46: | | GU46: | | GW46: | | GY46: | | HA46: | | HC46: | | HE46: | | HG46: | | HI46: | | HK46: |
A47: 1910 | B47: RENTALS | C47: | | E47: | | F47: 39477 | G47: | | H47: 5515 | I47: | | K47: | | L47: 10850 | M47: | | N47: 5098 | O47: | | Q47: | | S47: | | T47: 37893 | U47: | | W47: | | Y47: | | Z47: 540 | AA47: | | AB47: 3690 | AC47: | | AE47: | | AG47: | | AH47: 1130 | AI47: | | AK47: | | AL47: 1555 | AM47: | | AN47: 18392 | AO47: | | AP47: 302338 | AQ47: | | AS47: | | AT47: 411122 | AU47: | | AV47: 6735 | AW47: | | AX47: 22796 | AY47: | | AZ47: 4086 | BA47: | | BB47: 20409 | BC47: | | BD47: 14936 | BE47: | | BF47: 825 | BG47: | | BI47: | | BK47: | | BL47: 7661 | BM47: | | BO47: | | BQ47: | | BR47: 3000 | BS47: | | BT47: 150 | BU47: | | BW47: | | BX47: 12265 | BY47: | | BZ47: 12515 | CA47: | | CC47: | | CD47: 800 | CE47: | | CF47: 2358 | CG47: | | CH47: 43709 | CI47: | | CK47: | | CL47: 16326 | CM47: | | CO47: | | CP47: 560 | CQ47: | | CR47: 35970 | CS47: | | CT47: 33981 | CU47: | | CV47: 14770 | CW47: | | CY47: | | DA47: | | DC47: | | DD47: 760 | DE47: | | DF47: 8412 | DG47: | | DH47: 109152 | DI47: | | DK47: | | DL47: 25933 | DM47: | | DN47: 46588 | DO47: | | DQ47: | | DR47: 683 | DS47: | | DU47: | | DV47: 225915 | DW47: | | DY47: | | DZ47: 50098 | EA47: | | EB47: 17870 | EC47: | | ED47: 55418 | EE47: | | EF47: 11519 | EG47: | | EH47: 2700 | EI47: | | EJ47: 14942 | EK47: | | EL47: 19660 | EM47: | | EN47: 3616 | EO47: | | EP47: 1550 | EQ47: | | ER47: 5341 | ES47: | | ET47: 5854 | EU47: | | EV47: 15836 | EW47: | | EY47: | | EZ47: 20041 | FA47: | | FB47: 51510 | FC47: | | FD47: 20553 | FE47: | | FG47: | | FH47: 34581 | FI47: | | FJ47: 44289 | FK47: | | FL47: 138410 | FM47: | | FO47: | | FQ47: | | FR47: 4000 | FS47: | | FU47: | | FV47: 3022 | FW47: | | FX47: 18175 | FY47: | | FZ47: 86090 | GA47: | | GB47: 52928 | GC47: | | GE47: | | GG47: | | GI47: | | GJ47: 35725 | GK47: | | GL47: 60065 | GM47: | | GO47: | | GP47: 4581 | GQ47: | | GR47: 140 | GS47: | | GT47: 1400 | GU47: | | GV47: 25390 | GW47: | | GX47: 49843 | GY47: | | GZ47: 28610 | HA47: | | HC47: | | HE47: | | HF47: 2392652 | HG47: | | HI47: | | HJ47: 2392652 | HK47: |
A48: 1920 | B48: CONTRIB/DONAT FRM PRIV SOURCE | C48: | | D48: 10351 | E48: | | F48: 430471 | G48: | | H48: 5483 | I48: | | J48: 300000 | K48: | | L48: 123801 | M48: | | N48: 187152 | O48: | | Q48: | | R48: 27106 | S48: | | T48: 114319 | U48: | | V48: 8178 | W48: | | Y48: | | Z48: 11725 | AA48: | | AB48: 86618 | AC48: | | AE48: | | AF48: 536 | AG48: | | AH48: 21130 | AI48: | | AK48: | | AL48: 18622 | AM48: | | AO48: | | AP48: 492671 | AQ48: | | AR48: 1200 | AS48: | | AT48: 586189 | AU48: | | AV48: 21535 | AW48: | | AX48: 44768 | AY48: | | BA48: | | BC48: | | BD48: 49394 | BE48: | | BF48: 16342 | BG48: | | BI48: | | BK48: | | BL48: 739569 | BM48: | | BO48: | | BP48: 4227 | BQ48: | | BR48: 13714 | BS48: | | BT48: 13586 | BU48: | | BV48: 14750 | BW48: | | BX48: 117372 | BY48: | | CA48: | | CC48: | | CE48: | | CF48: 57941 | CG48: | | CH48: 400167 | CI48: | | CK48: | | CL48: 4537 | CM48: | | CN48: 2250 | CO48: | | CQ48: | | CR48: 289173 | CS48: | | CT48: 5957518 | CU48: | | CV48: 1150 | CW48: | | CY48: | | CZ48: 26666 | DA48: | | DC48: | | DD48: 51858 | DE48: | | DF48: 14485 | DG48: | | DH48: 233344 | DI48: | | DK48: | | DL48: 147765 | DM48: | | DN48: 1268855 | DO48: | | DP48: 13127 | DQ48: | | DR48: 11908 | DS48: | | DT48: 24855 | DU48: | | DW48: | | DX48: 3000 | DY48: | | EA48: | | EB48: 648726 | EC48: | | ED48: 144917 | EE48: | | EF48: 1387 | EG48: | | EH48: 250 | EI48: | | EJ48: 82306 | EK48: | | EL48: 3891 | EM48: | | EN48: 8209 | EO48: | | EP48: 25969 | EQ48: | | ER48: 181435 | ES48: | | ET48: 106848 | EU48: | | EV48: 312479 | EW48: | | EY48: | | EZ48: 5500 | FA48: | | FB48: 9255 | FC48: | | FD48: 16806 | FE48: | | FG48: | | FH48: 205995 | FI48: | | FJ48: 12379 | FK48: | | FL48: 80191 | FM48: | | FO48: | | FP48: 92854 | FQ48: | | FR48: 14168 | FS48: | | FT48: 26039 | FU48: | | FV48: 2374512 | FW48: | | FX48: 5748 | FY48: | | FZ48: 202887 | GA48: | | GB48: 269579 | GC48: | | GD48: 33832 | GE48: | | GG48: | | GI48: | | GJ48: 85609 | GK48: | | GL48: 13080 | GM48: | | GO48: | | GP48: 9636 | GQ48: | | GR48: 2050 | GS48: | | GT48: 23131 | GU48: | | GV48: 2200 | GW48: | | GX48: 38076 | GY48: | | GZ48: 113516 | HA48: | | HC48: | | HE48: | | HF48: 17122868 | HG48: | | HI48: | | HJ48: 17122868 | HK48: |
C49: | | D49: ABBEVILLE | E49: | | F49: AIKEN | G49: | | H49: ALLENDALE | I49: | | J49: ANDERSON CTY BD | K49: | | L49: ANDERSON 01 | M49: | | N49: ANDERSON 02 | O49: | | P49: ANDERSON 03 | Q49: | | R49: ANDERSON 04 | S49: | | T49: ANDERSON 05 | U49: | | V49: ANDERSON ALT SCHOOL | W49: | | X49: ANDERSON 1&2 CC | Y49: | | Z49: BAMBERG 01 | AA49: | | AB49: BAMBERG 02 | AC49: | | AD49: BARNWELL 19 | AE49: | | AF49: BARNWELL 29 | AG49: | | AH49: BARNWELL 45 | AI49: | | AJ49: BARNWELL VOC CEN | AK49: | | AL49: BEAUFORT | AM49: | | AN49: BEAUFORT-JASPER CEC | AO49: | | AP49: BERKELEY | AQ49: | | AR49: CALHOUN | AS49: | | AT49: CHARLESTON | AU49: | | AV49: CHEROKEE | AW49: | | AX49: CHESTER | AY49: | | AZ49: CHESTERFIELD | BA49: | | BB49: CLARENDON 01 | BC49: | | BD49: CLARENDON 02 | BE49: | | BF49: CLARENDON 03 | BG49: | | BH49: F.E. DUBOSE CC | BI49: | | BJ49: COLLETON | BK49: | | BL49: DARLINGTON | BM49: | | BN49: DILLON CTY BD | BO49: | | BP49: DILLON 01 | BQ49: | | BR49: DILLON 02 | BS49: | | BT49: DILLON 03 | BU49: | | BV49: DILLON ATC | BW49: | | BX49: DORCHESTER 02 | BY49: | | BZ49: DORCHESTER 04 | CA49: | | CB49: DORCHESTER CAR SCH | CC49: | | CD49: EDGEFIELD | CE49: | | CF49: FAIRFIELD | CG49: | | CH49: FLORENCE 01 | CI49: | | CJ49: FLORENCE 02 | CK49: | | CL49: FLORENCE 03 | CM49: | | CN49: FLORENCE 04 | CO49: | | CP49: FLORENCE 05 | CQ49: | | CR49: GEORGETOWN | CS49: | | CT49: GREENVILLE | CU49: | | CV49: GREENWOOD 50 | CW49: | | CX49: GREENWOOD 51 | CY49: | | CZ49: GREENWOOD 52 | DA49: | | DB49: GREENWOOD VOC FAC | DC49: | | DD49: HAMPTON 01 | DE49: | | DF49: HAMPTON 02 | DG49: | | DH49: HORRY | DI49: | | DJ49: JASPER | DK49: | | DL49: KERSHAW | DM49: | | DN49: LANCASTER | DO49: | | DP49: LAURENS 55 | DQ49: | | DR49: LAURENS 56 | DS49: | | DT49: LEE | DU49: | | DV49: LEXINGTON 01 | DW49: | | DX49: LEXINGTON 02 | DY49: | | DZ49: LEXINGTON 03 | EA49: | | EB49: LEXINGTON 04 | EC49: | | ED49: LEXINGTON 05 | EE49: | | EF49: MCCORMICK | EG49: | | EH49: MARION CTY BD | EI49: | | EJ49: MARION 01 | EK49: | | EL49: MARION 02 | EM49: | | EN49: MARION 07 | EO49: | | EP49: MARION VOC CTR | EQ49: | | ER49: MARLBORO | ES49: | | ET49: NEWBERRY | EU49: | | EV49: OCONEE | EW49: | | EX49: ORANGEBURG CTY BD | EY49: | | EZ49: ORANGEBURG 03 | FA49: | | FB49: ORANGEBURG 04 | FC49: | | FD49: ORANGEBURG 05 | FE49: | | FF49: COPE AVC | FG49: | | FH49: PICKENS | FI49: | | FJ49: RICHLAND 01 | FK49: | | FL49: RICHLAND 02 | FM49: | | FN49: SALUDA | FO49: | | FP49: SPARTANBURG 01 | FQ49: | | FR49: SPARTANBURG 02 | FS49: | | FT49: SPARTANBURG 03 | FU49: | | FV49: SPARTANBURG 04 | FW49: | | FX49: SPARTANBURG 05 | FY49: | | FZ49: SPARTANBURG 06 | GA49: | | GB49: SPARTANBURG 07 | GC49: | | GD49: DAN MORGAN VOC CEN | GE49: | | GF49: R.D. ANDERSON ATC | GG49: | | GH49: H.B. SWOFFORD CC | GI49: | | GJ49: SUMTER 02 | GK49: | | GL49: SUMTER 17 | GM49: | | GN49: SUMTER CC | GO49: | | GP49: UNION | GQ49: | | GR49: WILLIAMSBURG | GS49: | | GT49: YORK 01 | GU49: | | GV49: YORK 02 | GW49: | | GX49: YORK 03 | GY49: | | GZ49: YORK 04 | HA49: | | HB49: JUVENILE JUSTICE | HC49: | | HD49: PALMETTO UNIFIED | HE49: | | HF49: REGULAR DIST.TOTALS | HG49: | | HH49: SPECIAL DIST.TOTALS | HI49: | | HJ49: STATE TOTALS | HK49: |
C50: | | E50: | | G50: | | I50: | | K50: | | M50: | | O50: | | Q50: | | S50: | | U50: | | W50: | | Y50: | | AA50: | | AC50: | | AE50: | | AG50: | | AI50: | | AK50: | | AM50: | | AO50: | | AQ50: | | AS50: | | AU50: | | AW50: | | AY50: | | BA50: | | BC50: | | BE50: | | BG50: | | BI50: | | BK50: | | BM50: | | BO50: | | BQ50: | | BS50: | | BU50: | | BW50: | | BY50: | | CA50: | | CC50: | | CE50: | | CG50: | | CI50: | | CK50: | | CM50: | | CO50: | | CQ50: | | CS50: | | CU50: | | CW50: | | CY50: | | DA50: | | DC50: | | DE50: | | DG50: | | DI50: | | DK50: | | DM50: | | DO50: | | DQ50: | | DS50: | | DU50: | | DW50: | | DY50: | | EA50: | | EC50: | | EE50: | | EG50: | | EI50: | | EK50: | | EM50: | | EO50: | | EQ50: | | ES50: | | EU50: | | EW50: | | EY50: | | FA50: | | FC50: | | FE50: | | FG50: | | FI50: | | FK50: | | FM50: | | FO50: | | FQ50: | | FS50: | | FU50: | | FW50: | | FY50: | | GA50: | | GC50: | | GE50: | | GG50: | | GI50: | | GK50: | | GM50: | | GO50: | | GQ50: | | GS50: | | GU50: | | GW50: | | GY50: | | HA50: | | HC50: | | HE50: | | HG50: | | HI50: | | HK50: |
A51: 1930 | B51: MEDICAID RECEIPTS | C51: | | D51: 238093 | E51: | | F51: 783662 | G51: | | H51: 123308 | I51: | | K51: | | L51: 250322 | M51: | | N51: 339304 | O51: | | P51: 348809 | Q51: | | R51: 197903 | S51: | | T51: 1024193 | U51: | | W51: | | Y51: | | Z51: 118057 | AA51: | | AB51: 233135 | AC51: | | AD51: 35406 | AE51: | | AF51: 89694 | AG51: | | AH51: 274088 | AI51: | | AK51: | | AL51: 589615 | AM51: | | AO51: | | AP51: 1853575 | AQ51: | | AR51: 393959 | AS51: | | AT51: 2350405 | AU51: | | AV51: 808773 | AW51: | | AX51: 678057 | AY51: | | AZ51: 418531 | BA51: | | BB51: 48749 | BC51: | | BD51: 528029 | BE51: | | BF51: 47717 | BG51: | | BI51: | | BJ51: 590638 | BK51: | | BL51: 698851 | BM51: | | BO51: | | BP51: 93836 | BQ51: | | BR51: 145610 | BS51: | | BT51: 72044 | BU51: | | BW51: | | BX51: 396232 | BY51: | | BZ51: 514672 | CA51: | | CC51: | | CD51: 204151 | CE51: | | CF51: 513930 | CG51: | | CH51: 1453990 | CI51: | | CJ51: 550350 | CK51: | | CL51: 294671 | CM51: | | CN51: 86627 | CO51: | | CP51: 1740184 | CQ51: | | CR51: 1333471 | CS51: | | CT51: 3496993 | CU51: | | CV51: 191334 | CW51: | | CX51: 128742 | CY51: | | CZ51: 16760 | DA51: | | DC51: | | DD51: 170077 | DE51: | | DF51: 70043 | DG51: | | DH51: 4472998 | DI51: | | DJ51: 499539 | DK51: | | DL51: 451070 | DM51: | | DN51: 567769 | DO51: | | DP51: 540947 | DQ51: | | DR51: 794363 | DS51: | | DT51: 300706 | DU51: | | DV51: 360538 | DW51: | | DX51: 429272 | DY51: | | DZ51: 253791 | EA51: | | EB51: 193043 | EC51: | | ED51: 417085 | EE51: | | EF51: 12552 | EG51: | | EI51: | | EJ51: 1312128 | EK51: | | EL51: 1509980 | EM51: | | EN51: 106564 | EO51: | | EQ51: | | ER51: 171 | ES51: | | ET51: 554201 | EU51: | | EV51: 1594002 | EW51: | | EY51: | | EZ51: 911362 | FA51: | | FB51: 114493 | FC51: | | FD51: 704507 | FE51: | | FG51: | | FH51: 1443111 | FI51: | | FJ51: 100898 | FK51: | | FL51: 8227 | FM51: | | FN51: 87864 | FO51: | | FP51: 589137 | FQ51: | | FR51: 374281 | FS51: | | FT51: 256458 | FU51: | | FV51: 199092 | FW51: | | FX51: 268419 | FY51: | | FZ51: 637906 | GA51: | | GB51: 3879610 | GC51: | | GE51: | | GG51: | | GI51: | | GJ51: 398887 | GK51: | | GL51: 667104 | GM51: | | GO51: | | GP51: 330357 | GQ51: | | GR51: 1948021 | GS51: | | GT51: 471917 | GU51: | | GV51: 295421 | GW51: | | GX51: 447408 | GY51: | | GZ51: 298026 | HA51: | | HC51: | | HE51: | | HF51: 53339815 | HG51: | | HI51: | | HJ51: 53339815 | HK51: |
A52: 1931 | B52: MEDICAID THERAPY ADJUSTMENT | C52: | | E52: | | G52: | | H52: 51175 | I52: | | K52: | | M52: | | O52: | | Q52: | | S52: | | U52: | | W52: | | Y52: | | AA52: | | AC52: | | AE52: | | AG52: | | AI52: | | AK52: | | AM52: | | AO52: | | AQ52: | | AS52: | | AU52: | | AW52: | | AY52: | | BA52: | | BC52: | | BE52: | | BG52: | | BI52: | | BK52: | | BM52: | | BO52: | | BQ52: | | BS52: | | BU52: | | BW52: | | BY52: | | CA52: | | CC52: | | CE52: | | CG52: | | CI52: | | CK52: | | CM52: | | CO52: | | CQ52: | | CS52: | | CT52: 29570 | CU52: | | CW52: | | CY52: | | DA52: | | DC52: | | DE52: | | DG52: | | DI52: | | DK52: | | DM52: | | DO52: | | DP52: 56951 | DQ52: | | DS52: | | DU52: | | DW52: | | DY52: | | EA52: | | EC52: | | EE52: | | EG52: | | EI52: | | EK52: | | EM52: | | EO52: | | EQ52: | | ES52: | | EU52: | | EW52: | | EY52: | | FA52: | | FC52: | | FE52: | | FG52: | | FI52: | | FK52: | | FM52: | | FO52: | | FQ52: | | FS52: | | FU52: | | FW52: | | FY52: | | GA52: | | GC52: | | GE52: | | GG52: | | GI52: | | GK52: | | GM52: | | GO52: | | GQ52: | | GS52: | | GU52: | | GW52: | | GY52: | | HA52: | | HC52: | | HE52: | | HF52: 137696 | HG52: | | HI52: | | HJ52: 137696 | HK52: |
A53: 1950 | B53: REFUND-PRIOR YR'S EXPENDITURES | C53: | | D53: 47505 | E53: | | F53: 62260 | G53: | | I53: | | K53: | | L53: 21081 | M53: | | O53: | | Q53: | | S53: | | T53: 42532 | U53: | | W53: | | X53: 4056 | Y53: | | AA53: | | AB53: 2818 | AC53: | | AE53: | | AG53: | | AI53: | | AK53: | | AL53: 8567 | AM53: | | AO53: | | AQ53: | | AR53: 47560 | AS53: | | AT53: 921293 | AU53: | | AV53: 20732 | AW53: | | AX53: 711 | AY53: | | AZ53: 3383 | BA53: | | BC53: | | BD53: 18061 | BE53: | | BG53: | | BI53: | | BK53: | | BM53: | | BO53: | | BP53: 549 | BQ53: | | BR53: 11146 | BS53: | | BT53: 5722 | BU53: | | BW53: | | BY53: | | BZ53: 67201 | CA53: | | CC53: | | CE53: | | CF53: 25032 | CG53: | | CH53: 2256 | CI53: | | CK53: | | CL53: 340 | CM53: | | CO53: | | CQ53: | | CR53: 1715 | CS53: | | CU53: | | CW53: | | CX53: 2452 | CY53: | | DA53: | | DC53: | | DD53: 17886 | DE53: | | DF53: 52780 | DG53: | | DH53: 68530 | DI53: | | DJ53: 2500 | DK53: | | DM53: | | DO53: | | DP53: 39572 | DQ53: | | DR53: 5359 | DS53: | | DT53: 135 | DU53: | | DV53: 12858 | DW53: | | DX53: 13675 | DY53: | | EA53: | | EC53: | | ED53: -4752 | EE53: | | EF53: 18046 | EG53: | | EH53: 60 | EI53: | | EJ53: 1107 | EK53: | | EL53: 27202 | EM53: | | EN53: 848 | EO53: | | EQ53: | | ER53: 1807 | ES53: | | ET53: 2683 | EU53: | | EV53: 40326 | EW53: | | EY53: | | FA53: | | FB53: 98077 | FC53: | | FE53: | | FG53: | | FI53: | | FJ53: -131013 | FK53: | | FL53: 573614 | FM53: | | FO53: | | FP53: 1022 | FQ53: | | FS53: | | FU53: | | FW53: | | FX53: 65 | FY53: | | FZ53: 1829 | GA53: | | GB53: 40018 | GC53: | | GE53: | | GG53: | | GI53: | | GJ53: 44311 | GK53: | | GL53: 92730 | GM53: | | GO53: | | GP53: 1140 | GQ53: | | GR53: 3475 | GS53: | | GU53: | | GW53: | | GY53: | | GZ53: 522 | HA53: | | HC53: | | HE53: | | HF53: 2343384 | HG53: | | HI53: | | HJ53: 2343384 | HK53: |
A54: 1990 | B54: MISCELLANEOUS LOCAL REVENUE: | C54: | | E54: | | G54: | | I54: | | K54: | | M54: | | O54: | | Q54: | | S54: | | U54: | | W54: | | Y54: | | AA54: | | AC54: | | AE54: | | AG54: | | AI54: | | AK54: | | AM54: | | AO54: | | AQ54: | | AS54: | | AU54: | | AW54: | | AY54: | | BA54: | | BC54: | | BE54: | | BG54: | | BI54: | | BK54: | | BM54: | | BO54: | | BQ54: | | BS54: | | BU54: | | BW54: | | BY54: | | CA54: | | CC54: | | CE54: | | CG54: | | CI54: | | CK54: | | CM54: | | CO54: | | CQ54: | | CS54: | | CU54: | | CW54: | | CY54: | | DA54: | | DC54: | | DE54: | | DG54: | | DI54: | | DK54: | | DM54: | | DO54: | | DQ54: | | DS54: | | DU54: | | DW54: | | DY54: | | EA54: | | EC54: | | EE54: | | EG54: | | EI54: | | EK54: | | EM54: | | EO54: | | EQ54: | | ES54: | | EU54: | | EW54: | | EY54: | | FA54: | | FC54: | | FE54: | | FG54: | | FI54: | | FK54: | | FM54: | | FO54: | | FQ54: | | FS54: | | FU54: | | FW54: | | FY54: | | GA54: | | GC54: | | GE54: | | GG54: | | GI54: | | GK54: | | GM54: | | GO54: | | GQ54: | | GS54: | | GU54: | | GW54: | | GY54: | | HA54: | | HC54: | | HE54: | | HG54: | | HI54: | | HK54: |
A55: 1992 | B55: CANTEEN OPERATIONS | C55: | | E55: | | G55: | | I55: | | K55: | | L55: 34546 | M55: | | O55: | | Q55: | | S55: | | U55: | | V55: 9932 | W55: | | Y55: | | AA55: | | AC55: | | AE55: | | AG55: | | AI55: | | AK55: | | AM55: | | AO55: | | AQ55: | | AS55: | | AT55: 422227 | AU55: | | AW55: | | AY55: | | BA55: | | BC55: | | BE55: | | BG55: | | BI55: | | BK55: | | BM55: | | BO55: | | BQ55: | | BS55: | | BU55: | | BW55: | | BY55: | | CA55: | | CC55: | | CE55: | | CG55: | | CI55: | | CK55: | | CM55: | | CO55: | | CQ55: | | CS55: | | CT55: 8047 | CU55: | | CW55: | | CY55: | | DA55: | | DC55: | | DE55: | | DG55: | | DI55: | | DK55: | | DM55: | | DO55: | | DQ55: | | DS55: | | DU55: | | DW55: | | DY55: | | EA55: | | EB55: 4565 | EC55: | | EE55: | | EG55: | | EI55: | | EK55: | | EM55: | | EO55: | | EQ55: | | ES55: | | EU55: | | EW55: | | EY55: | | FA55: | | FC55: | | FE55: | | FG55: | | FI55: | | FK55: | | FM55: | | FO55: | | FQ55: | | FS55: | | FU55: | | FW55: | | FY55: | | GA55: | | GC55: | | GE55: | | GG55: | | GI55: | | GK55: | | GL55: 37 | GM55: | | GO55: | | GQ55: | | GS55: | | GU55: | | GV55: 17139 | GW55: | | GY55: | | HA55: | | HC55: | | HE55: | | HF55: 496493 | HG55: | | HI55: | | HJ55: 496493 | HK55: |
A56: 1993 | B56: RECEIPT OF INSURANCE PROCEEDS | C56: | | D56: 40028 | E56: | | F56: 4960 | G56: | | I56: | | K56: | | L56: 6657 | M56: | | O56: | | P56: 2150 | Q56: | | S56: | | T56: 9720 | U56: | | W56: | | Y56: | | Z56: 326 | AA56: | | AC56: | | AE56: | | AG56: | | AI56: | | AK56: | | AL56: 34855 | AM56: | | AO56: | | AP56: 102357 | AQ56: | | AS56: | | AT56: 609444 | AU56: | | AV56: 1020 | AW56: | | AY56: | | BA56: | | BC56: | | BD56: 16017 | BE56: | | BG56: | | BI56: | | BK56: | | BM56: | | BO56: | | BP56: 23908 | BQ56: | | BR56: 15490 | BS56: | | BU56: | | BW56: | | BX56: 103196 | BY56: | | BZ56: 50386 | CA56: | | CC56: | | CE56: | | CG56: | | CH56: 10517 | CI56: | | CK56: | | CM56: | | CO56: | | CQ56: | | CR56: 17222 | CS56: | | CT56: 88248 | CU56: | | CV56: 32120 | CW56: | | CX56: 3412 | CY56: | | DA56: | | DC56: | | DD56: 920 | DE56: | | DF56: 1508 | DG56: | | DH56: 66724 | DI56: | | DJ56: 8155 | DK56: | | DM56: | | DN56: 45600 | DO56: | | DQ56: | | DR56: 55899 | DS56: | | DU56: | | DV56: 269811 | DW56: | | DX56: 5593 | DY56: | | EA56: | | EB56: 24296 | EC56: | | EE56: | | EF56: 73876 | EG56: | | EH56: 11003 | EI56: | | EK56: | | EM56: | | EN56: 126631 | EO56: | | EQ56: | | ER56: 22594 | ES56: | | ET56: 25261 | EU56: | | EV56: 40336 | EW56: | | EY56: | | EZ56: 1009 | FA56: | | FC56: | | FD56: 806867 | FE56: | | FG56: | | FI56: | | FJ56: 109350 | FK56: | | FL56: 7108 | FM56: | | FO56: | | FP56: 12796 | FQ56: | | FS56: | | FT56: 23866 | FU56: | | FW56: | | FX56: 52248 | FY56: | | FZ56: 4207 | GA56: | | GB56: 23014 | GC56: | | GE56: | | GG56: | | GI56: | | GJ56: 28539 | GK56: | | GL56: 316 | GM56: | | GO56: | | GP56: 294231 | GQ56: | | GS56: | | GU56: | | GW56: | | GX56: 24663 | GY56: | | GZ56: 62115 | HA56: | | HC56: | | HE56: | | HF56: 3400569 | HG56: | | HI56: | | HJ56: 3400569 | HK56: |
A57: 1994 | B57: RECEIPT OF LEGAL SETTLEMENTS | C57: | | E57: | | G57: | | I57: | | K57: | | M57: | | O57: | | Q57: | | S57: | | U57: | | W57: | | Y57: | | AA57: | | AC57: | | AE57: | | AG57: | | AI57: | | AK57: | | AM57: | | AO57: | | AP57: 4130 | AQ57: | | AS57: | | AU57: | | AW57: | | AY57: | | AZ57: 99089 | BA57: | | BC57: | | BE57: | | BG57: | | BI57: | | BK57: | | BM57: | | BO57: | | BQ57: | | BS57: | | BU57: | | BW57: | | BY57: | | CA57: | | CC57: | | CE57: | | CG57: | | CH57: 271790 | CI57: | | CK57: | | CM57: | | CO57: | | CQ57: | | CS57: | | CU57: | | CW57: | | CY57: | | DA57: | | DC57: | | DE57: | | DF57: 128105 | DG57: | | DH57: 53091 | DI57: | | DK57: | | DL57: 150000 | DM57: | | DO57: | | DQ57: | | DR57: 40 | DS57: | | DU57: | | DW57: | | DY57: | | EA57: | | EC57: | | EE57: | | EG57: | | EI57: | | EK57: | | EM57: | | EO57: | | EQ57: | | ES57: | | EU57: | | EW57: | | EY57: | | FA57: | | FC57: | | FE57: | | FG57: | | FI57: | | FK57: | | FM57: | | FO57: | | FQ57: | | FS57: | | FU57: | | FW57: | | FY57: | | GA57: | | GC57: | | GE57: | | GG57: | | GI57: | | GK57: | | GL57: 83782 | GM57: | | GO57: | | GQ57: | | GS57: | | GU57: | | GW57: | | GX57: 799051 | GY57: | | HA57: | | HC57: | | HE57: | | HF57: 1589078 | HG57: | | HI57: | | HJ57: 1589078 | HK57: |
A58: 1999 | B58: REVENUES FRM OTH LOCAL SOURCES | C58: | | D58: 122035 | E58: | | F58: 469459 | G58: | | H58: 145772 | I58: | | J58: 21532 | K58: | | L58: 122757 | M58: | | N58: 167828 | O58: | | P58: 178729 | Q58: | | R58: 231764 | S58: | | T58: 294441 | U58: | | V58: 85590 | W58: | | X58: 224824 | Y58: | | Z58: 48399 | AA58: | | AB58: 28544 | AC58: | | AD58: 56311 | AE58: | | AF58: 350217 | AG58: | | AH58: 74260 | AI58: | | AJ58: 5213 | AK58: | | AL58: 4116544 | AM58: | | AN58: 451165 | AO58: | | AP58: 2094179 | AQ58: | | AR58: 93015 | AS58: | | AT58: 8579224 | AU58: | | AV58: 327087 | AW58: | | AX58: 534728 | AY58: | | AZ58: 627432 | BA58: | | BB58: 351644 | BC58: | | BD58: 155508 | BE58: | | BF58: 113636 | BG58: | | BH58: 48590 | BI58: | | BJ58: 642474 | BK58: | | BL58: 7213033 | BM58: | | BN58: 27 | BO58: | | BP58: 350 | BQ58: | | BR58: 1990 | BS58: | | BT58: 84227 | BU58: | | BW58: | | BX58: 4263449 | BY58: | | BZ58: 10818 | CA58: | | CB58: 210 | CC58: | | CD58: 108138 | CE58: | | CF58: 421925 | CG58: | | CH58: 785497 | CI58: | | CJ58: 475219 | CK58: | | CL58: 110565 | CM58: | | CN58: 55986 | CO58: | | CP58: 497992 | CQ58: | | CR58: 409361 | CS58: | | CT58: 2481594 | CU58: | | CV58: 156617 | CW58: | | CX58: 60474 | CY58: | | CZ58: 7074 | DA58: | | DC58: | | DD58: 92322 | DE58: | | DF58: 100019 | DG58: | | DH58: 2396192 | DI58: | | DJ58: 76560 | DK58: | | DL58: 1176409 | DM58: | | DN58: 531063 | DO58: | | DP58: 382188 | DQ58: | | DR58: 132842 | DS58: | | DT58: 374077 | DU58: | | DV58: 757069 | DW58: | | DX58: 657938 | DY58: | | DZ58: 80009 | EA58: | | EB58: 47183 | EC58: | | ED58: 214746 | EE58: | | EF58: 315631 | EG58: | | EH58: 8123 | EI58: | | EJ58: 71812 | EK58: | | EL58: 16430 | EM58: | | EN58: 56788 | EO58: | | EP58: 7512 | EQ58: | | ER58: 90302 | ES58: | | ET58: 1392143 | EU58: | | EV58: 431816 | EW58: | | EY58: | | EZ58: 770250 | FA58: | | FB58: 25330 | FC58: | | FD58: 629660 | FE58: | | FG58: | | FH58: 308367 | FI58: | | FJ58: 2476342 | FK58: | | FL58: 3011905 | FM58: | | FN58: 120400 | FO58: | | FP58: 867224 | FQ58: | | FR58: 356390 | FS58: | | FT58: 237330 | FU58: | | FV58: 44749 | FW58: | | FX58: 28851 | FY58: | | FZ58: 296194 | GA58: | | GB58: 573294 | GC58: | | GD58: 17585 | GE58: | | GF58: 154865 | GG58: | | GH58: 25308 | GI58: | | GJ58: 543418 | GK58: | | GL58: 299589 | GM58: | | GO58: | | GP58: 425001 | GQ58: | | GR58: 388582 | GS58: | | GT58: 185690 | GU58: | | GV58: 202095 | GW58: | | GX58: 1958425 | GY58: | | GZ58: 4007184 | HA58: | | HB58: 12497 | HC58: | | HE58: | | HF58: 65270649 | HG58: | | HH58: 12497 | HI58: | | HJ58: 65283146 | HK58: |
C59: | | E59: | | G59: | | I59: | | K59: | | M59: | | O59: | | Q59: | | S59: | | U59: | | W59: | | Y59: | | AA59: | | AC59: | | AE59: | | AG59: | | AI59: | | AK59: | | AM59: | | AO59: | | AQ59: | | AS59: | | AU59: | | AW59: | | AY59: | | BA59: | | BC59: | | BE59: | | BG59: | | BI59: | | BK59: | | BM59: | | BO59: | | BQ59: | | BS59: | | BU59: | | BW59: | | BY59: | | CA59: | | CC59: | | CE59: | | CG59: | | CI59: | | CK59: | | CM59: | | CO59: | | CQ59: | | CS59: | | CU59: | | CW59: | | CY59: | | DA59: | | DC59: | | DE59: | | DG59: | | DI59: | | DK59: | | DM59: | | DO59: | | DQ59: | | DS59: | | DU59: | | DW59: | | DY59: | | EA59: | | EC59: | | EE59: | | EG59: | | EI59: | | EK59: | | EM59: | | EO59: | | EQ59: | | ES59: | | EU59: | | EW59: | | EY59: | | FA59: | | FC59: | | FE59: | | FG59: | | FI59: | | FK59: | | FM59: | | FO59: | | FQ59: | | FS59: | | FU59: | | FW59: | | FY59: | | GA59: | | GC59: | | GE59: | | GG59: | | GI59: | | GK59: | | GM59: | | GO59: | | GQ59: | | GS59: | | GU59: | | GW59: | | GY59: | | HA59: | | HC59: | | HE59: | | HG59: | | HI59: | | HK59: |
A60: ***** | B60: TOTAL REVENUE LOCAL SOURCES: | C60: | | D60: 10474641 | E60: | | F60: 75661599 | G60: | | H60: 5502685 | I60: | | J60: 785170 | K60: | | L60: 26158685 | M60: | | N60: 11420331 | O60: | | P60: 8057991 | Q60: | | R60: 16516037 | S60: | | T60: 46945356 | U60: | | V60: 1048008 | W60: | | X60: 3912004 | Y60: | | Z60: 4360542 | AA60: | | AB60: 3468720 | AC60: | | AD60: 2421466 | AE60: | | AF60: 2838378 | AG60: | | AH60: 6462076 | AI60: | | AJ60: 1391022 | AK60: | | AL60: 167660076 | AM60: | | AN60: 3830293 | AO60: | | AP60: 117077320 | AQ60: | | AR60: 9658216 | AS60: | | AT60: 304200778 | AU60: | | AV60: 36848750 | AW60: | | AX60: 21483318 | AY60: | | AZ60: 22562213 | BA60: | | BB60: 4797970 | BC60: | | BD60: 6091951 | BE60: | | BF60: 3020208 | BG60: | | BH60: 1057120 | BI60: | | BJ60: 22777632 | BK60: | | BL60: 48006157 | BM60: | | BN60: 1288126 | BO60: | | BP60: 1475151 | BQ60: | | BR60: 5500274 | BS60: | | BT60: 2821595 | BU60: | | BV60: 1020889 | BW60: | | BX60: 66852600 | BY60: | | BZ60: 11659001 | CA60: | | CB60: 3102555 | CC60: | | CD60: 13202724 | CE60: | | CF60: 23787612 | CG60: | | CH60: 57963523 | CI60: | | CJ60: 3909437 | CK60: | | CL60: 8377086 | CM60: | | CN60: 3550207 | CO60: | | CP60: 6202083 | CQ60: | | CR60: 60407211 | CS60: | | CT60: 293011400 | CU60: | | CV60: 41531915 | CW60: | | CX60: 3740863 | CY60: | | CZ60: 8409659 | DA60: | | DB60: 1378253 | DC60: | | DD60: 6828453 | DE60: | | DF60: 3886532 | DG60: | | DH60: 224692294 | DI60: | | DJ60: 11536376 | DK60: | | DL60: 38941008 | DM60: | | DN60: 38511004 | DO60: | | DP60: 16370908 | DQ60: | | DR60: 10039675 | DS60: | | DT60: 6492865 | DU60: | | DV60: 107075233 | DW60: | | DX60: 36319674 | DY60: | | DZ60: 10840478 | EA60: | | EB60: 9404195 | EC60: | | ED60: 89793837 | EE60: | | EF60: 5833670 | EG60: | | EH60: 1531529 | EI60: | | EJ60: 6317183 | EK60: | | EL60: 4786613 | EM60: | | EN60: 2001480 | EO60: | | EP60: 1448684 | EQ60: | | ER60: 11531082 | ES60: | | ET60: 30550055 | EU60: | | EV60: 64446185 | EW60: | | EY60: | | EZ60: 14383960 | FA60: | | FB60: 15193588 | FC60: | | FD60: 32502472 | FE60: | | FF60: 790614 | FG60: | | FH60: 60458160 | FI60: | | FJ60: 180798308 | FK60: | | FL60: 119871947 | FM60: | | FN60: 6829519 | FO60: | | FP60: 19400431 | FQ60: | | FR60: 28565808 | FS60: | | FT60: 14467865 | FU60: | | FV60: 10515764 | FW60: | | FX60: 41123819 | FY60: | | FZ60: 42279041 | GA60: | | GB60: 43813963 | GC60: | | GD60: 1739823 | GE60: | | GF60: 2726629 | GG60: | | GH60: 2547914 | GI60: | | GJ60: 24679918 | GK60: | | GL60: 24159026 | GM60: | | GO60: | | GP60: 11814396 | GQ60: | | GR60: 14634768 | GS60: | | GT60: 18653530 | GU60: | | GV60: 45558771 | GW60: | | GX60: 74465021 | GY60: | | GZ60: 48297579 | HA60: | | HB60: 12497 | HC60: | | HE60: | | HF60: 3255140524 | HG60: | | HH60: 12497 | HI60: | | HJ60: 3255153021 | HK60: |
C61: | | E61: | | G61: | | I61: | | K61: | | M61: | | O61: | | Q61: | | S61: | | U61: | | W61: | | Y61: | | AA61: | | AC61: | | AE61: | | AG61: | | AI61: | | AK61: | | AM61: | | AO61: | | AQ61: | | AS61: | | AU61: | | AW61: | | AY61: | | BA61: | | BC61: | | BE61: | | BG61: | | BI61: | | BK61: | | BM61: | | BO61: | | BQ61: | | BS61: | | BU61: | | BW61: | | BY61: | | CA61: | | CC61: | | CE61: | | CG61: | | CI61: | | CK61: | | CM61: | | CO61: | | CQ61: | | CS61: | | CU61: | | CW61: | | CY61: | | DA61: | | DC61: | | DE61: | | DG61: | | DI61: | | DK61: | | DM61: | | DO61: | | DQ61: | | DS61: | | DU61: | | DW61: | | DY61: | | EA61: | | EC61: | | EE61: | | EG61: | | EI61: | | EK61: | | EM61: | | EO61: | | EQ61: | | ES61: | | EU61: | | EW61: | | EY61: | | FA61: | | FC61: | | FE61: | | FG61: | | FI61: | | FK61: | | FM61: | | FO61: | | FQ61: | | FS61: | | FU61: | | FW61: | | FY61: | | GA61: | | GC61: | | GE61: | | GG61: | | GI61: | | GK61: | | GM61: | | GO61: | | GQ61: | | GS61: | | GU61: | | GW61: | | GY61: | | HA61: | | HC61: | | HE61: | | HG61: | | HI61: | | HK61: |
A62: 2000 | B62: INTERGOVERNMENTAL REVENUES: | C62: | | E62: | | G62: | | I62: | | K62: | | M62: | | O62: | | Q62: | | S62: | | U62: | | W62: | | Y62: | | AA62: | | AC62: | | AE62: | | AG62: | | AI62: | | AK62: | | AM62: | | AO62: | | AQ62: | | AS62: | | AU62: | | AW62: | | AY62: | | BA62: | | BC62: | | BE62: | | BG62: | | BI62: | | BK62: | | BM62: | | BO62: | | BQ62: | | BS62: | | BU62: | | BW62: | | BY62: | | CA62: | | CC62: | | CE62: | | CG62: | | CI62: | | CK62: | | CM62: | | CO62: | | CQ62: | | CS62: | | CU62: | | CW62: | | CY62: | | DA62: | | DC62: | | DE62: | | DG62: | | DI62: | | DK62: | | DM62: | | DO62: | | DQ62: | | DS62: | | DU62: | | DW62: | | DY62: | | EA62: | | EC62: | | EE62: | | EG62: | | EI62: | | EK62: | | EM62: | | EO62: | | EQ62: | | ES62: | | EU62: | | EW62: | | EY62: | | FA62: | | FC62: | | FE62: | | FG62: | | FI62: | | FK62: | | FM62: | | FO62: | | FQ62: | | FS62: | | FU62: | | FW62: | | FY62: | | GA62: | | GC62: | | GE62: | | GG62: | | GI62: | | GK62: | | GM62: | | GO62: | | GQ62: | | GS62: | | GU62: | | GW62: | | GY62: | | HA62: | | HC62: | | HE62: | | HG62: | | HI62: | | HK62: |
A63: 2100 | B63: PAYMENTS FROM OTHER GOVERNMENTAL UN | C63: | | E63: | | F63: 964440 | G63: | | I63: | | K63: | | M63: | | O63: | | Q63: | | S63: | | T63: 77771 | U63: | | W63: | | Y63: | | Z63: 22619 | AA63: | | AB63: 37338 | AC63: | | AD63: 58067 | AE63: | | AG63: | | AH63: 52650 | AI63: | | AK63: | | AM63: | | AO63: | | AP63: 56180 | AQ63: | | AS63: | | AT63: 123510 | AU63: | | AV63: 4099 | AW63: | | AX63: 1803083 | AY63: | | AZ63: 201369 | BA63: | | BC63: | | BE63: | | BG63: | | BI63: | | BJ63: 49449 | BK63: | | BM63: | | BN63: 2213625 | BO63: | | BP63: 823890 | BQ63: | | BR63: 1366477 | BS63: | | BT63: 588894 | BU63: | | BV63: 218419 | BW63: | | BX63: 1032712 | BY63: | | BZ63: 30000 | CA63: | | CC63: | | CD63: 93179 | CE63: | | CF63: 26147 | CG63: | | CH63: 39442 | CI63: | | CK63: | | CL63: 129222 | CM63: | | CO63: | | CP63: 1816 | CQ63: | | CR63: 2808 | CS63: | | CT63: 4329237 | CU63: | | CW63: | | CX63: 7494 | CY63: | | DA63: | | DB63: 502407 | DC63: | | DD63: 60084 | DE63: | | DG63: | | DH63: 1043570 | DI63: | | DJ63: 3191079 | DK63: | | DM63: | | DN63: 571822 | DO63: | | DQ63: | | DS63: | | DT63: 393332 | DU63: | | DW63: | | DX63: 33542 | DY63: | | DZ63: 81374 | EA63: | | EC63: | | EE63: | | EG63: | | EH63: 147988 | EI63: | | EJ63: 133499 | EK63: | | EL63: 63012 | EM63: | | EN63: 371960 | EO63: | | EP63: 151762 | EQ63: | | ER63: 195526 | ES63: | | EU63: | | EV63: 323976 | EW63: | | EY63: | | EZ63: 800000 | FA63: | | FB63: 64101 | FC63: | | FD63: 79843 | FE63: | | FG63: | | FH63: 11578 | FI63: | | FK63: | | FM63: | | FO63: | | FQ63: | | FS63: | | FT63: 61003 | FU63: | | FV63: 146432 | FW63: | | FX63: 281112 | FY63: | | FZ63: 640668 | GA63: | | GB63: 332265 | GC63: | | GE63: | | GG63: | | GI63: | | GJ63: 196966 | GK63: | | GL63: 10942 | GM63: | | GO63: | | GQ63: | | GS63: | | GT63: 73719 | GU63: | | GW63: | | GX63: 274549 | GY63: | | GZ63: 20193 | HA63: | | HB63: 2527750 | HC63: | | HD63: 4375941 | HE63: | | HF63: 24612241 | HG63: | | HH63: 6903691 | HI63: | | HJ63: 31515932 | HK63: |
A64: 2200 | B64: PAYMENTS FROM PUB CHARTER SCHOOL | C64: | | E64: | | G64: | | I64: | | K64: | | M64: | | O64: | | Q64: | | S64: | | U64: | | W64: | | Y64: | | AA64: | | AC64: | | AE64: | | AG64: | | AI64: | | AK64: | | AM64: | | AO64: | | AQ64: | | AS64: | | AU64: | | AW64: | | AX64: 360617 | AY64: | | BA64: | | BC64: | | BE64: | | BG64: | | BI64: | | BK64: | | BM64: | | BO64: | | BQ64: | | BS64: | | BU64: | | BW64: | | BY64: | | CA64: | | CC64: | | CD64: 1200 | CE64: | | CG64: | | CI64: | | CK64: | | CM64: | | CO64: | | CQ64: | | CS64: | | CU64: | | CW64: | | CY64: | | DA64: | | DC64: | | DE64: | | DG64: | | DI64: | | DK64: | | DM64: | | DO64: | | DQ64: | | DS64: | | DU64: | | DW64: | | DY64: | | EA64: | | EC64: | | EE64: | | EG64: | | EI64: | | EK64: | | EM64: | | EO64: | | EQ64: | | ES64: | | EU64: | | EW64: | | EY64: | | FA64: | | FC64: | | FE64: | | FG64: | | FI64: | | FK64: | | FM64: | | FO64: | | FQ64: | | FS64: | | FU64: | | FW64: | | FY64: | | GA64: | | GC64: | | GE64: | | GG64: | | GI64: | | GK64: | | GM64: | | GO64: | | GQ64: | | GS64: | | GU64: | | GW64: | | GY64: | | HA64: | | HC64: | | HE64: | | HF64: 361817 | HG64: | | HI64: | | HJ64: 361817 | HK64: |
A65: 2300 | B65: PAYMENT FROM NON-PROFIT ENTITIES (F | C65: | | D65: 182004 | E65: | | G65: | | I65: | | K65: | | M65: | | O65: | | Q65: | | S65: | | U65: | | W65: | | Y65: | | Z65: 107536 | AA65: | | AC65: | | AD65: 122094 | AE65: | | AF65: 20214 | AG65: | | AI65: | | AK65: | | AM65: | | AO65: | | AQ65: | | AR65: 183963 | AS65: | | AU65: | | AV65: 9862 | AW65: | | AX65: 129315 | AY65: | | AZ65: 104676 | BA65: | | BC65: | | BD65: 46464 | BE65: | | BF65: 33766 | BG65: | | BI65: | | BK65: | | BM65: | | BO65: | | BQ65: | | BS65: | | BT65: 107812 | BU65: | | BW65: | | BX65: 98200 | BY65: | | BZ65: 93344 | CA65: | | CC65: | | CE65: | | CF65: 94042 | CG65: | | CH65: 189533 | CI65: | | CJ65: 22453 | CK65: | | CL65: 25000 | CM65: | | CN65: 43267 | CO65: | | CQ65: | | CS65: | | CU65: | | CW65: | | CX65: 34706 | CY65: | | DA65: | | DC65: | | DE65: | | DG65: | | DI65: | | DJ65: 112841 | DK65: | | DM65: | | DO65: | | DQ65: | | DR65: 91758 | DS65: | | DU65: | | DV65: 151695 | DW65: | | DY65: | | DZ65: 270559 | EA65: | | EC65: | | EE65: | | EG65: | | EI65: | | EK65: | | EM65: | | EO65: | | EQ65: | | ER65: 66665 | ES65: | | ET65: 51800 | EU65: | | EW65: | | EY65: | | FA65: | | FC65: | | FE65: | | FG65: | | FH65: 272969 | FI65: | | FK65: | | FM65: | | FO65: | | FP65: 571818 | FQ65: | | FS65: | | FU65: | | FV65: 72450 | FW65: | | FX65: 1344213 | FY65: | | GA65: | | GB65: 582103 | GC65: | | GE65: | | GG65: | | GI65: | | GJ65: 116313 | GK65: | | GL65: 100584 | GM65: | | GO65: | | GP65: 162552 | GQ65: | | GR65: 187908 | GS65: | | GT65: 33750 | GU65: | | GW65: | | GX65: 58103 | GY65: | | GZ65: 25750 | HA65: | | HC65: | | HE65: | | HF65: 5922082 | HG65: | | HI65: | | HJ65: 5922082 | HK65: |
A66: 2310 | B66: PAYMENTS FROM NON-PROFIT ENTITIES | C66: | | E66: | | G66: | | I66: | | K66: | | M66: | | O66: | | Q66: | | S66: | | U66: | | W66: | | Y66: | | AA66: | | AC66: | | AE66: | | AG66: | | AI66: | | AK66: | | AM66: | | AO66: | | AQ66: | | AS66: | | AU66: | | AW66: | | AY66: | | BA66: | | BC66: | | BD66: 465192 | BE66: | | BG66: | | BI66: | | BK66: | | BM66: | | BO66: | | BQ66: | | BS66: | | BU66: | | BW66: | | BY66: | | CA66: | | CC66: | | CE66: | | CG66: | | CH66: 984917 | CI66: | | CK66: | | CM66: | | CO66: | | CQ66: | | CS66: | | CU66: | | CW66: | | CY66: | | DA66: | | DC66: | | DE66: | | DG66: | | DI66: | | DK66: | | DM66: | | DO66: | | DQ66: | | DS66: | | DU66: | | DW66: | | DY66: | | EA66: | | EC66: | | EE66: | | EG66: | | EI66: | | EK66: | | EM66: | | EO66: | | EQ66: | | ES66: | | EU66: | | EV66: 135415 | EW66: | | EY66: | | FA66: | | FC66: | | FE66: | | FG66: | | FI66: | | FK66: | | FM66: | | FO66: | | FQ66: | | FR66: 18243 | FS66: | | FU66: | | FV66: 89899 | FW66: | | FY66: | | GA66: | | GC66: | | GE66: | | GG66: | | GI66: | | GK66: | | GM66: | | GO66: | | GQ66: | | GS66: | | GU66: | | GW66: | | GY66: | | GZ66: 37178 | HA66: | | HC66: | | HE66: | | HF66: 1730844 | HG66: | | HI66: | | HJ66: 1730844 | HK66: |
C67: | | E67: | | G67: | | I67: | | K67: | | M67: | | O67: | | Q67: | | S67: | | U67: | | W67: | | Y67: | | AA67: | | AC67: | | AE67: | | AG67: | | AI67: | | AK67: | | AM67: | | AO67: | | AQ67: | | AS67: | | AU67: | | AW67: | | AY67: | | BA67: | | BC67: | | BE67: | | BG67: | | BI67: | | BK67: | | BM67: | | BO67: | | BQ67: | | BS67: | | BU67: | | BW67: | | BY67: | | CA67: | | CC67: | | CE67: | | CG67: | | CI67: | | CK67: | | CM67: | | CO67: | | CQ67: | | CS67: | | CU67: | | CW67: | | CY67: | | DA67: | | DC67: | | DE67: | | DG67: | | DI67: | | DK67: | | DM67: | | DO67: | | DQ67: | | DS67: | | DU67: | | DW67: | | DY67: | | EA67: | | EC67: | | EE67: | | EG67: | | EI67: | | EK67: | | EM67: | | EO67: | | EQ67: | | ES67: | | EU67: | | EW67: | | EY67: | | FA67: | | FC67: | | FE67: | | FG67: | | FI67: | | FK67: | | FM67: | | FO67: | | FQ67: | | FS67: | | FU67: | | FW67: | | FY67: | | GA67: | | GC67: | | GE67: | | GG67: | | GI67: | | GK67: | | GM67: | | GO67: | | GQ67: | | GS67: | | GU67: | | GW67: | | GY67: | | HA67: | | HC67: | | HE67: | | HG67: | | HI67: | | HK67: |
A68: ***** | B68: TOTAL INTERGOVERNMENTAL REVENUE: | C68: | | D68: 182004 | E68: | | F68: 964440 | G68: | | I68: | | K68: | | M68: | | O68: | | Q68: | | S68: | | T68: 77771 | U68: | | W68: | | Y68: | | Z68: 130155 | AA68: | | AB68: 37338 | AC68: | | AD68: 180161 | AE68: | | AF68: 20214 | AG68: | | AH68: 52650 | AI68: | | AK68: | | AM68: | | AO68: | | AP68: 56180 | AQ68: | | AR68: 183963 | AS68: | | AT68: 123510 | AU68: | | AV68: 13961 | AW68: | | AX68: 2293015 | AY68: | | AZ68: 306045 | BA68: | | BC68: | | BD68: 511656 | BE68: | | BF68: 33766 | BG68: | | BI68: | | BJ68: 49449 | BK68: | | BM68: | | BN68: 2213625 | BO68: | | BP68: 823890 | BQ68: | | BR68: 1366477 | BS68: | | BT68: 696706 | BU68: | | BV68: 218419 | BW68: | | BX68: 1130912 | BY68: | | BZ68: 123344 | CA68: | | CC68: | | CD68: 94379 | CE68: | | CF68: 120189 | CG68: | | CH68: 1213892 | CI68: | | CJ68: 22453 | CK68: | | CL68: 154222 | CM68: | | CN68: 43267 | CO68: | | CP68: 1816 | CQ68: | | CR68: 2808 | CS68: | | CT68: 4329237 | CU68: | | CW68: | | CX68: 42200 | CY68: | | DA68: | | DB68: 502407 | DC68: | | DD68: 60084 | DE68: | | DG68: | | DH68: 1043570 | DI68: | | DJ68: 3303920 | DK68: | | DM68: | | DN68: 571822 | DO68: | | DQ68: | | DR68: 91758 | DS68: | | DT68: 393332 | DU68: | | DV68: 151695 | DW68: | | DX68: 33542 | DY68: | | DZ68: 351933 | EA68: | | EC68: | | EE68: | | EG68: | | EH68: 147988 | EI68: | | EJ68: 133499 | EK68: | | EL68: 63012 | EM68: | | EN68: 371960 | EO68: | | EP68: 151762 | EQ68: | | ER68: 262191 | ES68: | | ET68: 51800 | EU68: | | EV68: 459391 | EW68: | | EY68: | | EZ68: 800000 | FA68: | | FB68: 64101 | FC68: | | FD68: 79843 | FE68: | | FG68: | | FH68: 284547 | FI68: | | FK68: | | FM68: | | FO68: | | FP68: 571818 | FQ68: | | FR68: 18243 | FS68: | | FT68: 61003 | FU68: | | FV68: 308781 | FW68: | | FX68: 1625325 | FY68: | | FZ68: 640668 | GA68: | | GB68: 914368 | GC68: | | GE68: | | GG68: | | GI68: | | GJ68: 313279 | GK68: | | GL68: 111526 | GM68: | | GO68: | | GP68: 162552 | GQ68: | | GR68: 187908 | GS68: | | GT68: 107469 | GU68: | | GW68: | | GX68: 332652 | GY68: | | GZ68: 83121 | HA68: | | HB68: 2527750 | HC68: | | HD68: 4375941 | HE68: | | HF68: 32626984 | HG68: | | HH68: 6903691 | HI68: | | HJ68: 39530675 | HK68: |
C69: | | E69: | | G69: | | I69: | | K69: | | M69: | | O69: | | Q69: | | S69: | | U69: | | W69: | | Y69: | | AA69: | | AC69: | | AE69: | | AG69: | | AI69: | | AK69: | | AM69: | | AO69: | | AQ69: | | AS69: | | AU69: | | AW69: | | AY69: | | BA69: | | BC69: | | BE69: | | BG69: | | BI69: | | BK69: | | BM69: | | BO69: | | BQ69: | | BS69: | | BU69: | | BW69: | | BY69: | | CA69: | | CC69: | | CE69: | | CG69: | | CI69: | | CK69: | | CM69: | | CO69: | | CQ69: | | CS69: | | CU69: | | CW69: | | CY69: | | DA69: | | DC69: | | DE69: | | DG69: | | DI69: | | DK69: | | DM69: | | DO69: | | DQ69: | | DS69: | | DU69: | | DW69: | | DY69: | | EA69: | | EC69: | | EE69: | | EG69: | | EI69: | | EK69: | | EM69: | | EO69: | | EQ69: | | ES69: | | EU69: | | EW69: | | EY69: | | FA69: | | FC69: | | FE69: | | FG69: | | FI69: | | FK69: | | FM69: | | FO69: | | FQ69: | | FS69: | | FU69: | | FW69: | | FY69: | | GA69: | | GC69: | | GE69: | | GG69: | | GI69: | | GK69: | | GM69: | | GO69: | | GQ69: | | GS69: | | GU69: | | GW69: | | GY69: | | HA69: | | HC69: | | HE69: | | HG69: | | HI69: | | HK69: |
A70: 3000 | B70: REVENUE FROM STATE SOURCES: | C70: | | E70: | | G70: | | I70: | | K70: | | M70: | | O70: | | Q70: | | S70: | | U70: | | W70: | | Y70: | | AA70: | | AC70: | | AE70: | | AG70: | | AI70: | | AK70: | | AM70: | | AO70: | | AQ70: | | AS70: | | AU70: | | AW70: | | AY70: | | BA70: | | BC70: | | BE70: | | BG70: | | BI70: | | BK70: | | BM70: | | BO70: | | BQ70: | | BS70: | | BU70: | | BW70: | | BY70: | | CA70: | | CC70: | | CE70: | | CG70: | | CI70: | | CK70: | | CM70: | | CO70: | | CQ70: | | CS70: | | CU70: | | CW70: | | CY70: | | DA70: | | DC70: | | DE70: | | DG70: | | DI70: | | DK70: | | DM70: | | DO70: | | DQ70: | | DS70: | | DU70: | | DW70: | | DY70: | | EA70: | | EC70: | | EE70: | | EG70: | | EI70: | | EK70: | | EM70: | | EO70: | | EQ70: | | ES70: | | EU70: | | EW70: | | EY70: | | FA70: | | FC70: | | FE70: | | FG70: | | FI70: | | FK70: | | FM70: | | FO70: | | FQ70: | | FS70: | | FU70: | | FW70: | | FY70: | | GA70: | | GC70: | | GE70: | | GG70: | | GI70: | | GK70: | | GM70: | | GO70: | | GQ70: | | GS70: | | GU70: | | GW70: | | GY70: | | HA70: | | HC70: | | HE70: | | HG70: | | HI70: | | HK70: |
A71: 3100 | B71: RESTRICTED STATE GRANTS: | C71: | | E71: | | G71: | | I71: | | K71: | | M71: | | O71: | | Q71: | | S71: | | U71: | | W71: | | Y71: | | AA71: | | AC71: | | AE71: | | AG71: | | AI71: | | AK71: | | AM71: | | AO71: | | AQ71: | | AS71: | | AU71: | | AW71: | | AY71: | | BA71: | | BC71: | | BE71: | | BG71: | | BI71: | | BK71: | | BM71: | | BO71: | | BQ71: | | BS71: | | BU71: | | BW71: | | BY71: | | CA71: | | CC71: | | CE71: | | CG71: | | CI71: | | CK71: | | CM71: | | CO71: | | CQ71: | | CS71: | | CU71: | | CW71: | | CY71: | | DA71: | | DC71: | | DE71: | | DG71: | | DI71: | | DK71: | | DM71: | | DO71: | | DQ71: | | DS71: | | DU71: | | DW71: | | DY71: | | EA71: | | EC71: | | EE71: | | EG71: | | EI71: | | EK71: | | EM71: | | EO71: | | EQ71: | | ES71: | | EU71: | | EW71: | | EY71: | | FA71: | | FC71: | | FE71: | | FG71: | | FI71: | | FK71: | | FM71: | | FO71: | | FQ71: | | FS71: | | FU71: | | FW71: | | FY71: | | GA71: | | GC71: | | GE71: | | GG71: | | GI71: | | GK71: | | GM71: | | GO71: | | GQ71: | | GS71: | | GU71: | | GW71: | | GY71: | | HA71: | | HC71: | | HE71: | | HG71: | | HI71: | | HK71: |
A72: 3110 | B72: OCCUPATIONAL EDUCATION: | C72: | | E72: | | G72: | | I72: | | K72: | | M72: | | O72: | | Q72: | | S72: | | U72: | | W72: | | Y72: | | AA72: | | AC72: | | AE72: | | AG72: | | AI72: | | AK72: | | AM72: | | AO72: | | AQ72: | | AS72: | | AU72: | | AW72: | | AY72: | | BA72: | | BC72: | | BE72: | | BG72: | | BI72: | | BK72: | | BM72: | | BO72: | | BQ72: | | BS72: | | BU72: | | BW72: | | BY72: | | CA72: | | CC72: | | CE72: | | CG72: | | CI72: | | CK72: | | CM72: | | CO72: | | CQ72: | | CS72: | | CU72: | | CW72: | | CY72: | | DA72: | | DC72: | | DE72: | | DG72: | | DI72: | | DK72: | | DM72: | | DO72: | | DQ72: | | DS72: | | DU72: | | DW72: | | DY72: | | EA72: | | EC72: | | EE72: | | EG72: | | EI72: | | EK72: | | EM72: | | EO72: | | EQ72: | | ES72: | | EU72: | | EW72: | | EY72: | | FA72: | | FC72: | | FE72: | | FG72: | | FI72: | | FK72: | | FM72: | | FO72: | | FQ72: | | FS72: | | FU72: | | FW72: | | FY72: | | GA72: | | GC72: | | GE72: | | GG72: | | GI72: | | GK72: | | GM72: | | GO72: | | GQ72: | | GS72: | | GU72: | | GW72: | | GY72: | | HA72: | | HC72: | | HE72: | | HG72: | | HI72: | | HK72: |
A73: 3112 | B73: NURSING PROGRAM | C73: | | E73: | | G73: | | I73: | | K73: | | M73: | | O73: | | Q73: | | S73: | | U73: | | W73: | | Y73: | | AA73: | | AC73: | | AE73: | | AG73: | | AI73: | | AK73: | | AM73: | | AO73: | | AQ73: | | AS73: | | AU73: | | AV73: 38919 | AW73: | | AY73: | | BA73: | | BC73: | | BE73: | | BG73: | | BI73: | | BK73: | | BM73: | | BO73: | | BQ73: | | BS73: | | BU73: | | BW73: | | BY73: | | CA73: | | CC73: | | CE73: | | CG73: | | CI73: | | CK73: | | CM73: | | CO73: | | CQ73: | | CS73: | | CU73: | | CW73: | | CY73: | | DA73: | | DC73: | | DE73: | | DG73: | | DI73: | | DK73: | | DL73: 46307 | DM73: | | DO73: | | DQ73: | | DS73: | | DT73: 1721 | DU73: | | DW73: | | DY73: | | EA73: | | EC73: | | EE73: | | EG73: | | EI73: | | EK73: | | EM73: | | EO73: | | EQ73: | | ES73: | | EU73: | | EV73: 69721 | EW73: | | EY73: | | FA73: | | FC73: | | FE73: | | FG73: | | FI73: | | FK73: | | FM73: | | FO73: | | FQ73: | | FS73: | | FU73: | | FW73: | | FY73: | | GA73: | | GC73: | | GE73: | | GG73: | | GI73: | | GK73: | | GM73: | | GO73: | | GQ73: | | GS73: | | GU73: | | GW73: | | GY73: | | HA73: | | HC73: | | HE73: | | HF73: 156668 | HG73: | | HI73: | | HJ73: 156668 | HK73: |
A74: 3113 | B74: 12-MONTH AGRICULTURE PROGRAM | C74: | | D74: 40261 | E74: | | F74: 52274 | G74: | | I74: | | K74: | | M74: | | N74: 10147 | O74: | | P74: 14552 | Q74: | | R74: 5597 | S74: | | T74: 10106 | U74: | | W74: | | Y74: | | AA74: | | AC74: | | AE74: | | AG74: | | AI74: | | AJ74: 7906 | AK74: | | AM74: | | AO74: | | AQ74: | | AS74: | | AU74: | | AV74: 18139 | AW74: | | AX74: 4730 | AY74: | | AZ74: 35428 | BA74: | | BC74: | | BE74: | | BG74: | | BH74: 10192 | BI74: | | BK74: | | BL74: 17217 | BM74: | | BO74: | | BQ74: | | BS74: | | BU74: | | BW74: | | BY74: | | CA74: | | CC74: | | CD74: 20498 | CE74: | | CF74: 6959 | CG74: | | CI74: | | CK74: | | CM74: | | CO74: | | CP74: 12214 | CQ74: | | CR74: 11732 | CS74: | | CU74: | | CW74: | | CY74: | | DA74: | | DC74: | | DE74: | | DF74: 10039 | DG74: | | DH74: 37832 | DI74: | | DK74: | | DM74: | | DN74: 12085 | DO74: | | DQ74: | | DS74: | | DU74: | | DW74: | | DY74: | | EA74: | | EC74: | | EE74: | | EG74: | | EI74: | | EK74: | | EM74: | | EO74: | | EP74: 11837 | EQ74: | | ER74: 12447 | ES74: | | EU74: | | EV74: 12355 | EW74: | | EY74: | | EZ74: 9755 | FA74: | | FC74: | | FE74: | | FG74: | | FI74: | | FK74: | | FM74: | | FO74: | | FQ74: | | FS74: | | FU74: | | FW74: | | FY74: | | GA74: | | GC74: | | GE74: | | GG74: | | GI74: | | GJ74: 21552 | GK74: | | GM74: | | GO74: | | GP74: 12099 | GQ74: | | GS74: | | GT74: 10125 | GU74: | | GW74: | | GY74: | | GZ74: 11116 | HA74: | | HC74: | | HE74: | | HF74: 439194 | HG74: | | HI74: | | HJ74: 439194 | HK74: |
A75: 3117 | B75: EEDA 8TH GRADE AWARENESS | C75: | | E75: | | F75: 14229 | G75: | | H75: 921 | I75: | | K75: | | M75: | | O75: | | Q75: | | R75: 1107 | S75: | | U75: | | W75: | | Y75: | | Z75: 982 | AA75: | | AB75: 533 | AC75: | | AD75: 516 | AE75: | | AF75: 593 | AG75: | | AI75: | | AK75: | | AM75: | | AO75: | | AP75: 15061 | AQ75: | | AR75: 815 | AS75: | | AU75: | | AV75: 5192 | AW75: | | AX75: 3415 | AY75: | | AZ75: 1498 | BA75: | | BC75: | | BE75: | | BF75: 843 | BG75: | | BI75: | | BK75: | | BM75: | | BO75: | | BQ75: | | BS75: | | BT75: 1011 | BU75: | | BW75: | | BX75: 11316 | BY75: | | BZ75: 302 | CA75: | | CC75: | | CE75: | | CG75: | | CH75: 9240 | CI75: | | CJ75: 719 | CK75: | | CM75: | | CO75: | | CP75: 963 | CQ75: | | CS75: | | CT75: 34171 | CU75: | | CV75: 4936 | CW75: | | CX75: 832 | CY75: | | DA75: | | DC75: | | DD75: 1538 | DE75: | | DF75: 840 | DG75: | | DH75: 16440 | DI75: | | DJ75: 1776 | DK75: | | DL75: 5955 | DM75: | | DN75: 1298 | DO75: | | DQ75: | | DR75: 2024 | DS75: | | DT75: 39815 | DU75: | | DV75: 11654 | DW75: | | DY75: | | EA75: | | EB75: 2053 | EC75: | | EE75: | | EF75: 383 | EG75: | | EI75: | | EJ75: 1825 | EK75: | | EL75: 1044 | EM75: | | EN75: 528 | EO75: | | EQ75: | | ES75: | | EU75: | | EW75: | | EY75: | | EZ75: 2046 | FA75: | | FB75: 1575 | FC75: | | FE75: | | FG75: | | FI75: | | FK75: | | FL75: 9288 | FM75: | | FN75: 1381 | FO75: | | FP75: 1183 | FQ75: | | FR75: 4889 | FS75: | | FT75: 1778 | FU75: | | FW75: | | FY75: | | FZ75: 2588 | GA75: | | GC75: | | GE75: | | GG75: | | GI75: | | GK75: | | GM75: | | GO75: | | GP75: 1550 | GQ75: | | GR75: 1067 | GS75: | | GT75: 2869 | GU75: | | GV75: 3503 | GW75: | | GY75: | | GZ75: 4137 | HA75: | | HB75: 1176 | HC75: | | HE75: | | HF75: 234222 | HG75: | | HH75: 1176 | HI75: | | HJ75: 235398 | HK75: |
A76: 3118 | B76: EEDA CAREER SPECIALISTS | C76: | | D76: 39117 | E76: | | F76: 295744 | G76: | | H76: 35842 | I76: | | K76: | | L76: 79630 | M76: | | N76: 79630 | O76: | | P76: 39597 | Q76: | | R76: 39815 | S76: | | T76: 159259 | U76: | | W76: | | Y76: | | Z76: 39815 | AA76: | | AC76: | | AE76: | | AG76: | | AH76: 62622 | AI76: | | AK76: | | AL76: 287280 | AM76: | | AO76: | | AP76: 398148 | AQ76: | | AR76: 32557 | AS76: | | AT76: 361807 | AU76: | | AV76: 79630 | AW76: | | AX76: 79630 | AY76: | | AZ76: 153694 | BA76: | | BC76: | | BD76: 25751 | BE76: | | BF76: 39535 | BG76: | | BI76: | | BJ76: 111013 | BK76: | | BL76: 77231 | BM76: | | BO76: | | BP76: 33996 | BQ76: | | BR76: 39815 | BS76: | | BT76: 39815 | BU76: | | BW76: | | BX76: 238889 | BY76: | | BZ76: 39815 | CA76: | | CC76: | | CD76: 39815 | CE76: | | CG76: | | CH76: 259562 | CI76: | | CK76: | | CL76: 78169 | CM76: | | CO76: | | CP76: 39815 | CQ76: | | CR76: 67701 | CS76: | | CT76: 796296 | CU76: | | CV76: 119444 | CW76: | | CX76: 39815 | CY76: | | CZ76: 39815 | DA76: | | DC76: | | DD76: 79630 | DE76: | | DF76: 27194 | DG76: | | DH76: 398148 | DI76: | | DJ76: 39815 | DK76: | | DL76: 79630 | DM76: | | DN76: 159259 | DO76: | | DP76: 119444 | DQ76: | | DR76: 39815 | DS76: | | DU76: | | DV76: 278704 | DW76: | | DX76: 159259 | DY76: | | EA76: | | EB76: 33576 | EC76: | | ED76: 154767 | EE76: | | EG76: | | EI76: | | EJ76: 37113 | EK76: | | EL76: 39815 | EM76: | | EO76: | | EQ76: | | ER76: 39815 | ES76: | | ET76: 39815 | EU76: | | EV76: 159259 | EW76: | | EY76: | | EZ76: 39101 | FA76: | | FB76: 104011 | FC76: | | FD76: 110744 | FE76: | | FG76: | | FH76: 199486 | FI76: | | FJ76: 318518 | FK76: | | FL76: 207312 | FM76: | | FN76: 39815 | FO76: | | FP76: 79630 | FQ76: | | FR76: 34391 | FS76: | | FT76: 39815 | FU76: | | FV76: 39815 | FW76: | | FX76: 79630 | FY76: | | FZ76: 119444 | GA76: | | GB76: 139883 | GC76: | | GE76: | | GG76: | | GI76: | | GJ76: 77387 | GK76: | | GL76: 119444 | GM76: | | GO76: | | GP76: 79630 | GQ76: | | GR76: 159259 | GS76: | | GT76: 39815 | GU76: | | GV76: 119444 | GW76: | | GX76: 159861 | GY76: | | GZ76: 119444 | HA76: | | HB76: 119444 | HC76: | | HE76: | | HF76: 8701046 | HG76: | | HH76: 119444 | HI76: | | HJ76: 8820490 | HK76: |
A77: 3120 | B77: GENERAL EDUCATION: | C77: | | E77: | | G77: | | I77: | | K77: | | M77: | | O77: | | Q77: | | S77: | | U77: | | W77: | | Y77: | | AA77: | | AC77: | | AE77: | | AG77: | | AI77: | | AK77: | | AM77: | | AO77: | | AQ77: | | AS77: | | AU77: | | AW77: | | AY77: | | BA77: | | BC77: | | BE77: | | BG77: | | BI77: | | BK77: | | BM77: | | BO77: | | BQ77: | | BS77: | | BU77: | | BW77: | | BY77: | | CA77: | | CC77: | | CE77: | | CG77: | | CI77: | | CK77: | | CM77: | | CO77: | | CQ77: | | CS77: | | CU77: | | CW77: | | CY77: | | DA77: | | DC77: | | DE77: | | DG77: | | DI77: | | DK77: | | DM77: | | DO77: | | DQ77: | | DS77: | | DU77: | | DW77: | | DY77: | | EA77: | | EC77: | | EE77: | | EG77: | | EI77: | | EK77: | | EM77: | | EO77: | | EQ77: | | ES77: | | EU77: | | EW77: | | EY77: | | FA77: | | FC77: | | FE77: | | FG77: | | FI77: | | FK77: | | FM77: | | FO77: | | FQ77: | | FS77: | | FU77: | | FW77: | | FY77: | | GA77: | | GC77: | | GE77: | | GG77: | | GI77: | | GK77: | | GM77: | | GO77: | | GQ77: | | GS77: | | GU77: | | GW77: | | GY77: | | HA77: | | HC77: | | HE77: | | HG77: | | HI77: | | HK77: |
A78: 3121 | B78: COMPREHENSIVE REMEDIATION SUMMER SC | C78: | | E78: | | G78: | | I78: | | K78: | | M78: | | O78: | | Q78: | | S78: | | U78: | | W78: | | Y78: | | AA78: | | AC78: | | AE78: | | AF78: 4457 | AG78: | | AI78: | | AK78: | | AM78: | | AO78: | | AQ78: | | AS78: | | AU78: | | AW78: | | AY78: | | BA78: | | BC78: | | BE78: | | BG78: | | BI78: | | BK78: | | BL78: 191095 | BM78: | | BO78: | | BQ78: | | BR78: 9580 | BS78: | | BU78: | | BW78: | | BY78: | | CA78: | | CC78: | | CE78: | | CG78: | | CI78: | | CK78: | | CM78: | | CO78: | | CQ78: | | CS78: | | CU78: | | CW78: | | CY78: | | DA78: | | DC78: | | DE78: | | DG78: | | DI78: | | DK78: | | DM78: | | DO78: | | DQ78: | | DS78: | | DU78: | | DW78: | | DY78: | | EA78: | | EC78: | | EE78: | | EG78: | | EI78: | | EK78: | | EM78: | | EO78: | | EQ78: | | ES78: | | EU78: | | EW78: | | EY78: | | FA78: | | FC78: | | FE78: | | FG78: | | FI78: | | FK78: | | FM78: | | FO78: | | FQ78: | | FS78: | | FU78: | | FW78: | | FY78: | | FZ78: 22616 | GA78: | | GC78: | | GE78: | | GG78: | | GI78: | | GK78: | | GM78: | | GO78: | | GQ78: | | GS78: | | GU78: | | GW78: | | GY78: | | HA78: | | HC78: | | HE78: | | HF78: 227748 | HG78: | | HI78: | | HJ78: 227748 | HK78: |
A79: 3122 | B79: INCREASE HIGH SCHOOL DIPLOMA CREDIT | C79: | | E79: | | G79: | | I79: | | K79: | | M79: | | O79: | | Q79: | | S79: | | U79: | | W79: | | Y79: | | AA79: | | AC79: | | AE79: | | AG79: | | AI79: | | AK79: | | AM79: | | AO79: | | AQ79: | | AS79: | | AU79: | | AW79: | | AY79: | | BA79: | | BC79: | | BE79: | | BG79: | | BI79: | | BK79: | | BM79: | | BO79: | | BQ79: | | BS79: | | BU79: | | BW79: | | BY79: | | CA79: | | CC79: | | CE79: | | CG79: | | CI79: | | CK79: | | CM79: | | CO79: | | CQ79: | | CS79: | | CU79: | | CW79: | | CY79: | | DA79: | | DC79: | | DE79: | | DG79: | | DI79: | | DK79: | | DM79: | | DO79: | | DQ79: | | DS79: | | DU79: | | DW79: | | DY79: | | EA79: | | EC79: | | EE79: | | EG79: | | EI79: | | EK79: | | EM79: | | EO79: | | EQ79: | | ES79: | | EU79: | | EW79: | | EY79: | | FA79: | | FC79: | | FE79: | | FG79: | | FI79: | | FK79: | | FL79: 523508 | FM79: | | FO79: | | FQ79: | | FS79: | | FU79: | | FW79: | | FY79: | | GA79: | | GB79: 2301 | GC79: | | GE79: | | GG79: | | GI79: | | GK79: | | GM79: | | GO79: | | GQ79: | | GS79: | | GU79: | | GW79: | | GY79: | | HA79: | | HC79: | | HE79: | | HF79: 525809 | HG79: | | HI79: | | HJ79: 525809 | HK79: |
A80: 3123 | B80: EAA ALTERNATIVE SCHOOLS GRANT | C80: | | E80: | | G80: | | I80: | | K80: | | M80: | | O80: | | Q80: | | S80: | | U80: | | V80: 100000 | W80: | | Y80: | | AA80: | | AC80: | | AE80: | | AG80: | | AI80: | | AK80: | | AM80: | | AO80: | | AQ80: | | AS80: | | AU80: | | AW80: | | AY80: | | BA80: | | BC80: | | BE80: | | BG80: | | BI80: | | BK80: | | BM80: | | BO80: | | BQ80: | | BR80: 25781 | BS80: | | BU80: | | BW80: | | BY80: | | CA80: | | CC80: | | CE80: | | CG80: | | CI80: | | CK80: | | CM80: | | CO80: | | CQ80: | | CS80: | | CU80: | | CW80: | | CY80: | | DA80: | | DC80: | | DE80: | | DG80: | | DI80: | | DK80: | | DM80: | | DO80: | | DQ80: | | DS80: | | DU80: | | DW80: | | DY80: | | EA80: | | EC80: | | EE80: | | EG80: | | EI80: | | EK80: | | EM80: | | EO80: | | EQ80: | | ES80: | | EU80: | | EW80: | | EY80: | | FA80: | | FC80: | | FE80: | | FG80: | | FI80: | | FK80: | | FM80: | | FO80: | | FQ80: | | FS80: | | FU80: | | FW80: | | FY80: | | GA80: | | GB80: 73827 | GC80: | | GE80: | | GG80: | | GI80: | | GK80: | | GM80: | | GO80: | | GQ80: | | GS80: | | GU80: | | GW80: | | GY80: | | HA80: | | HC80: | | HE80: | | HF80: 199608 | HG80: | | HI80: | | HJ80: 199608 | HK80: |
A81: 3124 | B81: CTE TECHNOLOGY INITIATIVE | C81: | | E81: | | G81: | | I81: | | K81: | | M81: | | O81: | | Q81: | | S81: | | U81: | | W81: | | Y81: | | AA81: | | AC81: | | AE81: | | AG81: | | AI81: | | AK81: | | AM81: | | AO81: | | AQ81: | | AR81: 226 | AS81: | | AU81: | | AW81: | | AY81: | | BA81: | | BC81: | | BE81: | | BG81: | | BI81: | | BK81: | | BM81: | | BO81: | | BQ81: | | BS81: | | BU81: | | BW81: | | BY81: | | CA81: | | CC81: | | CE81: | | CG81: | | CI81: | | CK81: | | CM81: | | CO81: | | CQ81: | | CS81: | | CU81: | | CW81: | | CY81: | | DA81: | | DC81: | | DE81: | | DG81: | | DI81: | | DK81: | | DM81: | | DO81: | | DQ81: | | DS81: | | DU81: | | DW81: | | DY81: | | EA81: | | EC81: | | EE81: | | EG81: | | EI81: | | EK81: | | EM81: | | EO81: | | EQ81: | | ES81: | | EU81: | | EW81: | | EY81: | | FA81: | | FC81: | | FE81: | | FG81: | | FI81: | | FK81: | | FM81: | | FO81: | | FQ81: | | FS81: | | FU81: | | FW81: | | FY81: | | GA81: | | GC81: | | GE81: | | GG81: | | GI81: | | GK81: | | GM81: | | GO81: | | GQ81: | | GS81: | | GU81: | | GW81: | | GY81: | | HA81: | | HC81: | | HE81: | | HF81: 226 | HG81: | | HI81: | | HJ81: 226 | HK81: |
A82: 3125 | B82: CAREER & TECHNOLOGY EDUC EQUIPMENT | C82: | | E82: | | F82: 244281 | G82: | | H82: 6149 | I82: | | K82: | | L82: 93599 | M82: | | O82: | | P82: 39507 | Q82: | | R82: 32362 | S82: | | T82: 120924 | U82: | | W82: | | X82: 62667 | Y82: | | Z82: 36514 | AA82: | | AB82: 10573 | AC82: | | AD82: 29412 | AE82: | | AF82: 24584 | AG82: | | AH82: 19336 | AI82: | | AJ82: 39202 | AK82: | | AM82: | | AO82: | | AP82: 332932 | AQ82: | | AR82: 37866 | AS82: | | AT82: 374106 | AU82: | | AV82: 81121 | AW82: | | AX82: 72691 | AY82: | | AZ82: 105199 | BA82: | | BC82: | | BD82: 20976 | BE82: | | BF82: 24022 | BG82: | | BI82: | | BJ82: 86042 | BK82: | | BL82: 101159 | BM82: | | BO82: | | BP82: 5699 | BQ82: | | BR82: 36749 | BS82: | | BT82: 30698 | BU82: | | BV82: 38327 | BW82: | | BX82: 162886 | BY82: | | BZ82: 33412 | CA82: | | CB82: 45791 | CC82: | | CD82: 46288 | CE82: | | CF82: 71845 | CG82: | | CH82: 164296 | CI82: | | CJ82: 31527 | CK82: | | CL82: 46490 | CM82: | | CN82: 38170 | CO82: | | CQ82: | | CR82: 109889 | CS82: | | CU82: | | CW82: | | CX82: 33269 | CY82: | | CZ82: 22885 | DA82: | | DB82: 234989 | DC82: | | DD82: 47124 | DE82: | | DF82: 63678 | DG82: | | DH82: 284940 | DI82: | | DJ82: 42183 | DK82: | | DL82: 78388 | DM82: | | DO82: | | DQ82: | | DS82: | | DU82: | | DW82: | | DY82: | | EA82: | | EC82: | | EE82: | | EG82: | | EI82: | | EK82: | | EM82: | | EO82: | | EQ82: | | ES82: | | EU82: | | EW82: | | EY82: | | FA82: | | FC82: | | FE82: | | FG82: | | FI82: | | FK82: | | FM82: | | FO82: | | FQ82: | | FS82: | | FT82: 16131 | FU82: | | FW82: | | FY82: | | GA82: | | GC82: | | GE82: | | GG82: | | GI82: | | GK82: | | GM82: | | GO82: | | GQ82: | | GS82: | | GU82: | | GW82: | | GY82: | | HA82: | | HC82: | | HE82: | | HF82: 3680878 | HG82: | | HI82: | | HJ82: 3680878 | HK82: |
A83: 3126 | B83: REFURBISH SCIENCE KITS | C83: | | D83: 12754 | E83: | | F83: 9472 | G83: | | I83: | | K83: | | L83: 35500 | M83: | | N83: 17116 | O83: | | P83: 12374 | Q83: | | R83: 12799 | S83: | | T83: 56087 | U83: | | W83: | | Y83: | | Z83: 6985 | AA83: | | AC83: | | AE83: | | AF83: 2511 | AG83: | | AH83: 11782 | AI83: | | AK83: | | AL83: 65272 | AM83: | | AO83: | | AP83: 118313 | AQ83: | | AR83: 6494 | AS83: | | AT83: 136305 | AU83: | | AV83: 37020 | AW83: | | AX83: 27326 | AY83: | | AZ83: 24507 | BA83: | | BB83: 4506 | BC83: | | BD83: 7041 | BE83: | | BF83: 4980 | BG83: | | BI83: | | BJ83: 28066 | BK83: | | BL83: 31188 | BM83: | | BO83: | | BP83: 3720 | BQ83: | | BR83: 6147 | BS83: | | BU83: | | BW83: | | BX83: 9772 | BY83: | | BZ83: 10084 | CA83: | | CC83: | | CD83: 18900 | CE83: | | CG83: | | CH83: 68135 | CI83: | | CJ83: 5440 | CK83: | | CL83: 17555 | CM83: | | CN83: 4552 | CO83: | | CP83: 8077 | CQ83: | | CR83: 23212 | CS83: | | CT83: 301844 | CU83: | | CV83: 20935 | CW83: | | CX83: 5416 | CY83: | | CZ83: 7529 | DA83: | | DC83: | | DD83: 20757 | DE83: | | DG83: | | DH83: 155897 | DI83: | | DK83: | | DL83: 47166 | DM83: | | DN83: 50631 | DO83: | | DP83: 16764 | DQ83: | | DS83: | | DT83: 11286 | DU83: | | DV83: 90099 | DW83: | | DX83: 30908 | DY83: | | DZ83: 9666 | EA83: | | EB83: 18554 | EC83: | | ED83: 69629 | EE83: | | EG83: | | EI83: | | EJ83: 11765 | EK83: | | EL83: 8735 | EM83: | | EN83: 3777 | EO83: | | EQ83: | | ER83: 22750 | ES83: | | ET83: 32098 | EU83: | | EV83: 49064 | EW83: | | EY83: | | FA83: | | FB83: 18786 | FC83: | | FD83: 31189 | FE83: | | FG83: | | FH83: 75881 | FI83: | | FJ83: 177501 | FK83: | | FL83: 96569 | FM83: | | FN83: 10169 | FO83: | | FP83: 21229 | FQ83: | | FR83: 30844 | FS83: | | FT83: 14155 | FU83: | | FV83: 11697 | FW83: | | FX83: 30813 | FY83: | | FZ83: 43448 | GA83: | | GB83: 35848 | GC83: | | GE83: | | GG83: | | GI83: | | GJ83: 40824 | GK83: | | GL83: 35691 | GM83: | | GO83: | | GP83: 21889 | GQ83: | | GR83: 10322 | GS83: | | GT83: 22264 | GU83: | | GV83: 24808 | GW83: | | GX83: 74494 | GY83: | | GZ83: 33167 | HA83: | | HC83: | | HE83: | | HF83: 2690850 | HG83: | | HI83: | | HJ83: 2690850 | HK83: |
A84: 3127 | B84: STUDENT HEALTH AND FITNESS | C84: | | E84: | | F84: 37422 | G84: | | I84: | | K84: | | L84: 37532 | M84: | | N84: 17687 | O84: | | Q84: | | R84: 12851 | S84: | | T84: 35619 | U84: | | W84: | | Y84: | | Z84: 6814 | AA84: | | AC84: | | AD84: 3894 | AE84: | | AG84: | | AH84: 11792 | AI84: | | AK84: | | AL84: 8535 | AM84: | | AO84: | | AP84: 119566 | AQ84: | | AR84: 8125 | AS84: | | AT84: 190363 | AU84: | | AV84: 41018 | AW84: | | AX84: 26980 | AY84: | | AZ84: 35216 | BA84: | | BB84: 678 | BC84: | | BE84: | | BF84: 5565 | BG84: | | BI84: | | BK84: | | BL84: 5392 | BM84: | | BO84: | | BP84: 3391 | BQ84: | | BR84: 17320 | BS84: | | BT84: 7090 | BU84: | | BW84: | | BX84: 56314 | BY84: | | BZ84: 1324 | CA84: | | CC84: | | CD84: 18334 | CE84: | | CG84: | | CH84: 61327 | CI84: | | CJ84: 5285 | CK84: | | CM84: | | CN84: 245 | CO84: | | CP84: 6633 | CQ84: | | CR84: 44574 | CS84: | | CT84: 284016 | CU84: | | CV84: 42142 | CW84: | | CX84: 5215 | CY84: | | DA84: | | DC84: | | DD84: 12385 | DE84: | | DF84: 5939 | DG84: | | DH84: 861 | DI84: | | DJ84: 14439 | DK84: | | DL84: 45682 | DM84: | | DN84: 43560 | DO84: | | DP84: 13893 | DQ84: | | DR84: 13862 | DS84: | | DT84: 12204 | DU84: | | DV84: 28555 | DW84: | | DX84: 39521 | DY84: | | DZ84: 9552 | EA84: | | EB84: 15241 | EC84: | | ED84: 1231 | EE84: | | EF84: 2520 | EG84: | | EI84: | | EJ84: 13536 | EK84: | | EL84: 9164 | EM84: | | EN84: 3660 | EO84: | | EQ84: | | ER84: 22143 | ES84: | | ET84: 26663 | EU84: | | EV84: 47210 | EW84: | | EY84: | | EZ84: 14188 | FA84: | | FB84: 18418 | FC84: | | FD84: 31681 | FE84: | | FG84: | | FH84: 74139 | FI84: | | FJ84: 62100 | FK84: | | FL84: 29620 | FM84: | | FN84: 10121 | FO84: | | FP84: 21045 | FQ84: | | FR84: 9338 | FS84: | | FT84: 13663 | FU84: | | FV84: 13436 | FW84: | | FX84: 29152 | FY84: | | FZ84: 41537 | GA84: | | GB84: 33881 | GC84: | | GE84: | | GG84: | | GI84: | | GJ84: 36711 | GK84: | | GL84: 32253 | GM84: | | GO84: | | GP84: 22145 | GQ84: | | GR84: 22427 | GS84: | | GT84: 22740 | GU84: | | GV84: 22555 | GW84: | | GX84: 69844 | GY84: | | GZ84: 29823 | HA84: | | HC84: | | HE84: | | HF84: 2200897 | HG84: | | HI84: | | HJ84: 2200897 | HK84: |
A85: 3128 | B85: EEDA CAREER SPECIALISTS | C85: | | D85: 7201 | E85: | | G85: | | I85: | | K85: | | L85: 3233 | M85: | | O85: | | Q85: | | S85: | | U85: | | W85: | | Y85: | | AA85: | | AC85: | | AE85: | | AG85: | | AI85: | | AK85: | | AM85: | | AO85: | | AP85: 109208 | AQ85: | | AR85: 2900 | AS85: | | AT85: 49346 | AU85: | | AW85: | | AX85: 7109 | AY85: | | BA85: | | BB85: 12000 | BC85: | | BE85: | | BG85: | | BI85: | | BK85: | | BM85: | | BO85: | | BQ85: | | BS85: | | BU85: | | BW85: | | BY85: | | CA85: | | CC85: | | CE85: | | CG85: | | CH85: 29843 | CI85: | | CK85: | | CM85: | | CO85: | | CQ85: | | CS85: | | CT85: 7000 | CU85: | | CW85: | | CY85: | | DA85: | | DC85: | | DE85: | | DG85: | | DH85: 4512 | DI85: | | DK85: | | DM85: | | DN85: 7827 | DO85: | | DQ85: | | DR85: 887 | DS85: | | DU85: | | DV85: 22396 | DW85: | | DY85: | | EA85: | | EC85: | | EE85: | | EG85: | | EI85: | | EK85: | | EM85: | | EO85: | | EQ85: | | ES85: | | ET85: 7938 | EU85: | | EV85: 34909 | EW85: | | EY85: | | EZ85: 10214 | FA85: | | FC85: | | FE85: | | FG85: | | FH85: 2390 | FI85: | | FJ85: 21201 | FK85: | | FM85: | | FO85: | | FQ85: | | FS85: | | FT85: 15800 | FU85: | | FW85: | | FY85: | | GA85: | | GC85: | | GE85: | | GG85: | | GI85: | | GK85: | | GL85: 14789 | GM85: | | GO85: | | GQ85: | | GR85: 26208 | GS85: | | GT85: 1798 | GU85: | | GV85: 3087 | GW85: | | GX85: 6099 | GY85: | | GZ85: 27800 | HA85: | | HC85: | | HE85: | | HF85: 435695 | HG85: | | HI85: | | HJ85: 435695 | HK85: |
A86: 3129 | B86: EAA REDUCE CLASS SIZE GRADES 1-3 | C86: | | E86: | | G86: | | I86: | | K86: | | M86: | | O86: | | Q86: | | S86: | | U86: | | W86: | | Y86: | | AA86: | | AC86: | | AE86: | | AG86: | | AI86: | | AK86: | | AM86: | | AO86: | | AQ86: | | AS86: | | AU86: | | AW86: | | AY86: | | BA86: | | BC86: | | BE86: | | BG86: | | BI86: | | BK86: | | BM86: | | BO86: | | BQ86: | | BS86: | | BU86: | | BW86: | | BY86: | | CA86: | | CC86: | | CE86: | | CG86: | | CI86: | | CK86: | | CM86: | | CO86: | | CQ86: | | CS86: | | CU86: | | CW86: | | CY86: | | DA86: | | DC86: | | DE86: | | DG86: | | DI86: | | DK86: | | DM86: | | DO86: | | DQ86: | | DS86: | | DU86: | | DW86: | | DY86: | | EA86: | | EC86: | | EE86: | | EG86: | | EI86: | | EK86: | | EM86: | | EO86: | | EQ86: | | ES86: | | EU86: | | EW86: | | EY86: | | FA86: | | FC86: | | FE86: | | FG86: | | FI86: | | FK86: | | FM86: | | FO86: | | FQ86: | | FS86: | | FU86: | | FW86: | | FY86: | | GA86: | | GC86: | | GE86: | | GG86: | | GI86: | | GK86: | | GM86: | | GO86: | | GQ86: | | GS86: | | GU86: | | GW86: | | GY86: | | HA86: | | HC86: | | HE86: | | HG86: | | HI86: | | HK86: |
A87: 3130 | B87: SPECIAL PROGRAMS: | C87: | | E87: | | G87: | | I87: | | K87: | | M87: | | O87: | | Q87: | | S87: | | U87: | | W87: | | Y87: | | AA87: | | AC87: | | AE87: | | AG87: | | AI87: | | AK87: | | AM87: | | AO87: | | AQ87: | | AS87: | | AU87: | | AW87: | | AY87: | | BA87: | | BC87: | | BE87: | | BG87: | | BI87: | | BK87: | | BM87: | | BO87: | | BQ87: | | BS87: | | BU87: | | BW87: | | BY87: | | CA87: | | CC87: | | CE87: | | CG87: | | CI87: | | CK87: | | CM87: | | CO87: | | CQ87: | | CS87: | | CU87: | | CW87: | | CY87: | | DA87: | | DC87: | | DE87: | | DG87: | | DI87: | | DK87: | | DM87: | | DO87: | | DQ87: | | DS87: | | DU87: | | DW87: | | DY87: | | EA87: | | EC87: | | EE87: | | EG87: | | EI87: | | EK87: | | EM87: | | EO87: | | EQ87: | | ES87: | | EU87: | | EW87: | | EY87: | | FA87: | | FC87: | | FE87: | | FG87: | | FI87: | | FK87: | | FM87: | | FO87: | | FQ87: | | FS87: | | FU87: | | FW87: | | FY87: | | GA87: | | GC87: | | GE87: | | GG87: | | GI87: | | GK87: | | GM87: | | GO87: | | GQ87: | | GS87: | | GU87: | | GW87: | | GY87: | | HA87: | | HC87: | | HE87: | | HG87: | | HI87: | | HK87: |
A88: 3131 | B88: HANDICAP TRANSPORTATION | C88: | | D88: 764 | E88: | | F88: 9534 | G88: | | H88: 764 | I88: | | K88: | | L88: 859 | M88: | | N88: 5980 | O88: | | P88: 859 | Q88: | | R88: 859 | S88: | | T88: 5183 | U88: | | W88: | | Y88: | | Z88: 764 | AA88: | | AB88: 764 | AC88: | | AD88: 4146 | AE88: | | AF88: 764 | AG88: | | AH88: 764 | AI88: | | AK88: | | AL88: 3437 | AM88: | | AO88: | | AP88: 10378 | AQ88: | | AR88: 21019 | AS88: | | AT88: 22083 | AU88: | | AV88: 1719 | AW88: | | AX88: 18326 | AY88: | | AZ88: 15108 | BA88: | | BB88: 764 | BC88: | | BD88: 764 | BE88: | | BF88: 764 | BG88: | | BI88: | | BJ88: 1719 | BK88: | | BL88: 4496 | BM88: | | BO88: | | BP88: 764 | BQ88: | | BR88: 4847 | BS88: | | BT88: 764 | BU88: | | BW88: | | BX88: 12606 | BY88: | | BZ88: 7633 | CA88: | | CC88: | | CD88: 764 | CE88: | | CF88: 5525 | CG88: | | CH88: 4498 | CI88: | | CJ88: 764 | CK88: | | CL88: 3099 | CM88: | | CN88: 764 | CO88: | | CP88: 764 | CQ88: | | CR88: 3899 | CS88: | | CT88: 160603 | CU88: | | CV88: 3280 | CW88: | | CX88: 5274 | CY88: | | CZ88: 764 | DA88: | | DC88: | | DD88: 5249 | DE88: | | DF88: 5070 | DG88: | | DH88: 10232 | DI88: | | DJ88: 3970 | DK88: | | DL88: 15496 | DM88: | | DN88: 11339 | DO88: | | DP88: 29362 | DQ88: | | DR88: 764 | DS88: | | DT88: 859 | DU88: | | DV88: 98145 | DW88: | | DX88: 5257 | DY88: | | DZ88: 764 | EA88: | | EB88: 10952 | EC88: | | ED88: 2578 | EE88: | | EF88: 764 | EG88: | | EI88: | | EJ88: 764 | EK88: | | EM88: | | EN88: 764 | EO88: | | EQ88: | | ER88: 859 | ES88: | | ET88: 859 | EU88: | | EV88: 2731 | EW88: | | EY88: | | EZ88: 764 | FA88: | | FB88: 859 | FC88: | | FD88: 2578 | FE88: | | FG88: | | FH88: 26157 | FI88: | | FJ88: 7734 | FK88: | | FL88: 44131 | FM88: | | FN88: 765 | FO88: | | FP88: 859 | FQ88: | | FR88: 1617 | FS88: | | FT88: 18575 | FU88: | | FV88: 764 | FW88: | | FX88: 764 | FY88: | | FZ88: 8874 | GA88: | | GB88: 5156 | GC88: | | GE88: | | GG88: | | GI88: | | GJ88: 26473 | GK88: | | GL88: 1719 | GM88: | | GO88: | | GP88: 23967 | GQ88: | | GR88: 5329 | GS88: | | GT88: 8962 | GU88: | | GV88: 764 | GW88: | | GX88: 8080 | GY88: | | GZ88: 859 | HA88: | | HC88: | | HE88: | | HF88: 751721 | HG88: | | HI88: | | HJ88: 751721 | HK88: |
A89: 3132 | B89: HOME SCHOOLING | C89: | | D89: 1184 | E89: | | G89: | | I89: | | K89: | | M89: | | O89: | | Q89: | | S89: | | U89: | | W89: | | Y89: | | Z89: 1775 | AA89: | | AC89: | | AE89: | | AG89: | | AI89: | | AK89: | | AL89: 9468 | AM89: | | AO89: | | AP89: 592 | AQ89: | | AR89: 7101 | AS89: | | AT89: 8285 | AU89: | | AV89: 1184 | AW89: | | AY89: | | BA89: | | BC89: | | BE89: | | BG89: | | BI89: | | BK89: | | BM89: | | BO89: | | BQ89: | | BS89: | | BU89: | | BW89: | | BX89: 2368 | BY89: | | CA89: | | CC89: | | CD89: 7693 | CE89: | | CF89: 4734 | CG89: | | CH89: 3551 | CI89: | | CK89: | | CM89: | | CN89: 592 | CO89: | | CQ89: | | CS89: | | CT89: 129002 | CU89: | | CV89: 592 | CW89: | | CY89: | | DA89: | | DC89: | | DE89: | | DG89: | | DH89: 17161 | DI89: | | DK89: | | DM89: | | DO89: | | DP89: 3551 | DQ89: | | DS89: | | DT89: 1775 | DU89: | | DV89: 117160 | DW89: | | DY89: | | EA89: | | EB89: 1184 | EC89: | | ED89: 6509 | EE89: | | EG89: | | EI89: | | EK89: | | EM89: | | EO89: | | EQ89: | | ER89: 2367 | ES89: | | EU89: | | EV89: 7693 | EW89: | | EY89: | | FA89: | | FB89: 7101 | FC89: | | FE89: | | FG89: | | FH89: 2367 | FI89: | | FJ89: 10652 | FK89: | | FL89: 2367 | FM89: | | FO89: | | FQ89: | | FS89: | | FU89: | | FV89: 592 | FW89: | | FX89: 2367 | FY89: | | GA89: | | GB89: 2959 | GC89: | | GE89: | | GG89: | | GI89: | | GJ89: 4734 | GK89: | | GL89: 4142 | GM89: | | GO89: | | GP89: 1184 | GQ89: | | GS89: | | GT89: 3551 | GU89: | | GV89: 592 | GW89: | | GY89: | | GZ89: 3551 | HA89: | | HC89: | | HE89: | | HF89: 381680 | HG89: | | HI89: | | HJ89: 381680 | HK89: |
A90: 3134 | B90: CHILD DEVELOP. EDUCATION PILOT PROGRAM | C90: | | D90: 325933 | E90: | | G90: | | H90: 271132 | I90: | | K90: | | M90: | | O90: | | Q90: | | S90: | | U90: | | W90: | | Y90: | | Z90: 170 | AA90: | | AB90: 128866 | AC90: | | AD90: 73025 | AE90: | | AF90: 98 | AG90: | | AI90: | | AK90: | | AM90: | | AO90: | | AP90: 782131 | AQ90: | | AS90: | | AU90: | | AW90: | | AY90: | | BA90: | | BB90: 97835 | BC90: | | BD90: 320397 | BE90: | | BF90: 159451 | BG90: | | BI90: | | BK90: | | BM90: | | BO90: | | BP90: 139267 | BQ90: | | BR90: 529349 | BS90: | | BT90: 284952 | BU90: | | BW90: | | BY90: | | CA90: | | CC90: | | CE90: | | CG90: | | CH90: 327807 | CI90: | | CJ90: 235431 | CK90: | | CL90: 156175 | CM90: | | CN90: 202747 | CO90: | | CP90: 180937 | CQ90: | | CS90: | | CU90: | | CW90: | | CY90: | | DA90: | | DC90: | | DD90: 350710 | DE90: | | DF90: 128049 | DG90: | | DI90: | | DJ90: 378766 | DK90: | | DM90: | | DO90: | | DP90: 520638 | DQ90: | | DR90: 239179 | DS90: | | DT90: 359205 | DU90: | | DW90: | | DY90: | | EA90: | | EB90: 493170 | EC90: | | EE90: | | EG90: | | EI90: | | EK90: | | EL90: 387437 | EM90: | | EN90: 201557 | EO90: | | EQ90: | | ES90: | | EU90: | | EW90: | | EY90: | | EZ90: 595408 | FA90: | | FB90: 499007 | FC90: | | FD90: 1033133 | FE90: | | FG90: | | FI90: | | FK90: | | FM90: | | FO90: | | FQ90: | | FS90: | | FU90: | | FW90: | | FY90: | | GA90: | | GC90: | | GE90: | | GG90: | | GI90: | | GK90: | | GM90: | | GO90: | | GQ90: | | GR90: 806192 | GS90: | | GU90: | | GW90: | | GY90: | | HA90: | | HC90: | | HE90: | | HF90: 10208154 | HG90: | | HI90: | | HJ90: 10208154 | HK90: |
A91: 3135 | B91: PRESCH PRO FOR CHLDRN W/DISABIL | C91: | | E91: | | G91: | | I91: | | K91: | | M91: | | O91: | | Q91: | | S91: | | U91: | | W91: | | Y91: | | AA91: | | AC91: | | AE91: | | AG91: | | AI91: | | AK91: | | AM91: | | AO91: | | AQ91: | | AS91: | | AU91: | | AW91: | | AY91: | | BA91: | | BC91: | | BE91: | | BG91: | | BI91: | | BK91: | | BM91: | | BO91: | | BQ91: | | BS91: | | BU91: | | BW91: | | BY91: | | CA91: | | CC91: | | CE91: | | CG91: | | CI91: | | CK91: | | CM91: | | CO91: | | CQ91: | | CS91: | | CU91: | | CW91: | | CY91: | | DA91: | | DC91: | | DE91: | | DG91: | | DI91: | | DK91: | | DM91: | | DO91: | | DQ91: | | DS91: | | DU91: | | DW91: | | DY91: | | EA91: | | EC91: | | EE91: | | EG91: | | EI91: | | EK91: | | EM91: | | EO91: | | EQ91: | | ES91: | | EU91: | | EW91: | | EY91: | | FA91: | | FC91: | | FE91: | | FG91: | | FI91: | | FK91: | | FM91: | | FO91: | | FQ91: | | FS91: | | FU91: | | FW91: | | FY91: | | GA91: | | GC91: | | GE91: | | GG91: | | GI91: | | GK91: | | GL91: 16821 | GM91: | | GO91: | | GQ91: | | GS91: | | GU91: | | GW91: | | GY91: | | HA91: | | HC91: | | HE91: | | HF91: 16821 | HG91: | | HI91: | | HJ91: 16821 | HK91: |
A92: 3140 | B92: SCHOOL LUNCH: | C92: | | E92: | | G92: | | I92: | | K92: | | M92: | | O92: | | Q92: | | S92: | | U92: | | W92: | | Y92: | | AA92: | | AC92: | | AE92: | | AG92: | | AI92: | | AK92: | | AM92: | | AO92: | | AQ92: | | AS92: | | AU92: | | AW92: | | AY92: | | BA92: | | BC92: | | BE92: | | BG92: | | BI92: | | BK92: | | BM92: | | BO92: | | BQ92: | | BS92: | | BU92: | | BW92: | | BY92: | | CA92: | | CC92: | | CE92: | | CG92: | | CI92: | | CK92: | | CM92: | | CO92: | | CQ92: | | CS92: | | CU92: | | CW92: | | CY92: | | DA92: | | DC92: | | DE92: | | DG92: | | DI92: | | DK92: | | DM92: | | DO92: | | DQ92: | | DS92: | | DU92: | | DW92: | | DY92: | | EA92: | | EC92: | | EE92: | | EG92: | | EI92: | | EK92: | | EM92: | | EO92: | | EQ92: | | ES92: | | EU92: | | EW92: | | EY92: | | FA92: | | FC92: | | FE92: | | FG92: | | FI92: | | FK92: | | FM92: | | FO92: | | FQ92: | | FS92: | | FU92: | | FW92: | | FY92: | | GA92: | | GC92: | | GE92: | | GG92: | | GI92: | | GK92: | | GM92: | | GO92: | | GQ92: | | GS92: | | GU92: | | GW92: | | GY92: | | HA92: | | HC92: | | HE92: | | HG92: | | HI92: | | HK92: |
C93: | | D93: ABBEVILLE | E93: | | F93: AIKEN | G93: | | H93: ALLENDALE | I93: | | J93: ANDERSON CTY BD | K93: | | L93: ANDERSON 01 | M93: | | N93: ANDERSON 02 | O93: | | P93: ANDERSON 03 | Q93: | | R93: ANDERSON 04 | S93: | | T93: ANDERSON 05 | U93: | | V93: ANDERSON ALT SCHOOL | W93: | | X93: ANDERSON 1&2 CC | Y93: | | Z93: BAMBERG 01 | AA93: | | AB93: BAMBERG 02 | AC93: | | AD93: BARNWELL 19 | AE93: | | AF93: BARNWELL 29 | AG93: | | AH93: BARNWELL 45 | AI93: | | AJ93: BARNWELL VOC CEN | AK93: | | AL93: BEAUFORT | AM93: | | AN93: BEAUFORT-JASPER CEC | AO93: | | AP93: BERKELEY | AQ93: | | AR93: CALHOUN | AS93: | | AT93: CHARLESTON | AU93: | | AV93: CHEROKEE | AW93: | | AX93: CHESTER | AY93: | | AZ93: CHESTERFIELD | BA93: | | BB93: CLARENDON 01 | BC93: | | BD93: CLARENDON 02 | BE93: | | BF93: CLARENDON 03 | BG93: | | BH93: F.E. DUBOSE CC | BI93: | | BJ93: COLLETON | BK93: | | BL93: DARLINGTON | BM93: | | BN93: DILLON CTY BD | BO93: | | BP93: DILLON 01 | BQ93: | | BR93: DILLON 02 | BS93: | | BT93: DILLON 03 | BU93: | | BV93: DILLON ATC | BW93: | | BX93: DORCHESTER 02 | BY93: | | BZ93: DORCHESTER 04 | CA93: | | CB93: DORCHESTER CAR SCH | CC93: | | CD93: EDGEFIELD | CE93: | | CF93: FAIRFIELD | CG93: | | CH93: FLORENCE 01 | CI93: | | CJ93: FLORENCE 02 | CK93: | | CL93: FLORENCE 03 | CM93: | | CN93: FLORENCE 04 | CO93: | | CP93: FLORENCE 05 | CQ93: | | CR93: GEORGETOWN | CS93: | | CT93: GREENVILLE | CU93: | | CV93: GREENWOOD 50 | CW93: | | CX93: GREENWOOD 51 | CY93: | | CZ93: GREENWOOD 52 | DA93: | | DB93: GREENWOOD VOC FAC | DC93: | | DD93: HAMPTON 01 | DE93: | | DF93: HAMPTON 02 | DG93: | | DH93: HORRY | DI93: | | DJ93: JASPER | DK93: | | DL93: KERSHAW | DM93: | | DN93: LANCASTER | DO93: | | DP93: LAURENS 55 | DQ93: | | DR93: LAURENS 56 | DS93: | | DT93: LEE | DU93: | | DV93: LEXINGTON 01 | DW93: | | DX93: LEXINGTON 02 | DY93: | | DZ93: LEXINGTON 03 | EA93: | | EB93: LEXINGTON 04 | EC93: | | ED93: LEXINGTON 05 | EE93: | | EF93: MCCORMICK | EG93: | | EH93: MARION CTY BD | EI93: | | EJ93: MARION 01 | EK93: | | EL93: MARION 02 | EM93: | | EN93: MARION 07 | EO93: | | EP93: MARION VOC CTR | EQ93: | | ER93: MARLBORO | ES93: | | ET93: NEWBERRY | EU93: | | EV93: OCONEE | EW93: | | EX93: ORANGEBURG CTY BD | EY93: | | EZ93: ORANGEBURG 03 | FA93: | | FB93: ORANGEBURG 04 | FC93: | | FD93: ORANGEBURG 05 | FE93: | | FF93: COPE AVC | FG93: | | FH93: PICKENS | FI93: | | FJ93: RICHLAND 01 | FK93: | | FL93: RICHLAND 02 | FM93: | | FN93: SALUDA | FO93: | | FP93: SPARTANBURG 01 | FQ93: | | FR93: SPARTANBURG 02 | FS93: | | FT93: SPARTANBURG 03 | FU93: | | FV93: SPARTANBURG 04 | FW93: | | FX93: SPARTANBURG 05 | FY93: | | FZ93: SPARTANBURG 06 | GA93: | | GB93: SPARTANBURG 07 | GC93: | | GD93: DAN MORGAN VOC CEN | GE93: | | GF93: R.D. ANDERSON ATC | GG93: | | GH93: H.B. SWOFFORD CC | GI93: | | GJ93: SUMTER 02 | GK93: | | GL93: SUMTER 17 | GM93: | | GN93: SUMTER CC | GO93: | | GP93: UNION | GQ93: | | GR93: WILLIAMSBURG | GS93: | | GT93: YORK 01 | GU93: | | GV93: YORK 02 | GW93: | | GX93: YORK 03 | GY93: | | GZ93: YORK 04 | HA93: | | HB93: JUVENILE JUSTICE | HC93: | | HD93: PALMETTO UNIFIED | HE93: | | HF93: REGULAR DIST.TOTALS | HG93: | | HH93: SPECIAL DIST.TOTALS | HI93: | | HJ93: STATE TOTALS | HK93: |
C94: | | E94: | | G94: | | I94: | | K94: | | M94: | | O94: | | Q94: | | S94: | | U94: | | W94: | | Y94: | | AA94: | | AC94: | | AE94: | | AG94: | | AI94: | | AK94: | | AM94: | | AO94: | | AQ94: | | AS94: | | AU94: | | AW94: | | AY94: | | BA94: | | BC94: | | BE94: | | BG94: | | BI94: | | BK94: | | BM94: | | BO94: | | BQ94: | | BS94: | | BU94: | | BW94: | | BY94: | | CA94: | | CC94: | | CE94: | | CG94: | | CI94: | | CK94: | | CM94: | | CO94: | | CQ94: | | CS94: | | CU94: | | CW94: | | CY94: | | DA94: | | DC94: | | DE94: | | DG94: | | DI94: | | DK94: | | DM94: | | DO94: | | DQ94: | | DS94: | | DU94: | | DW94: | | DY94: | | EA94: | | EC94: | | EE94: | | EG94: | | EI94: | | EK94: | | EM94: | | EO94: | | EQ94: | | ES94: | | EU94: | | EW94: | | EY94: | | FA94: | | FC94: | | FE94: | | FG94: | | FI94: | | FK94: | | FM94: | | FO94: | | FQ94: | | FS94: | | FU94: | | FW94: | | FY94: | | GA94: | | GC94: | | GE94: | | GG94: | | GI94: | | GK94: | | GM94: | | GO94: | | GQ94: | | GS94: | | GU94: | | GW94: | | GY94: | | HA94: | | HC94: | | HE94: | | HG94: | | HI94: | | HK94: |
A95: 3141 | B95: SUPERVISOR'S SALARY | C95: | | E95: | | G95: | | I95: | | K95: | | M95: | | O95: | | Q95: | | S95: | | U95: | | W95: | | Y95: | | AA95: | | AC95: | | AE95: | | AG95: | | AI95: | | AK95: | | AM95: | | AO95: | | AQ95: | | AS95: | | AU95: | | AW95: | | AY95: | | BA95: | | BC95: | | BE95: | | BG95: | | BI95: | | BK95: | | BM95: | | BO95: | | BQ95: | | BS95: | | BU95: | | BW95: | | BY95: | | CA95: | | CC95: | | CE95: | | CG95: | | CI95: | | CK95: | | CM95: | | CO95: | | CQ95: | | CS95: | | CU95: | | CW95: | | CY95: | | DA95: | | DC95: | | DE95: | | DG95: | | DI95: | | DK95: | | DM95: | | DO95: | | DQ95: | | DS95: | | DU95: | | DW95: | | DY95: | | EA95: | | EC95: | | EE95: | | EG95: | | EI95: | | EK95: | | EM95: | | EO95: | | EQ95: | | ES95: | | EU95: | | EW95: | | EY95: | | FA95: | | FC95: | | FE95: | | FG95: | | FI95: | | FK95: | | FM95: | | FO95: | | FQ95: | | FS95: | | FU95: | | FW95: | | FY95: | | GA95: | | GC95: | | GE95: | | GG95: | | GI95: | | GK95: | | GM95: | | GO95: | | GQ95: | | GS95: | | GU95: | | GW95: | | GY95: | | HA95: | | HC95: | | HE95: | | HG95: | | HI95: | | HK95: |
A96: 3142 | B96: PROGRAM AID | C96: | | D96: 3502 | E96: | | F96: 14786 | G96: | | H96: 1556 | I96: | | J96: 17898 | K96: | | M96: | | O96: | | Q96: | | S96: | | U96: | | W96: | | Y96: | | Z96: 1556 | AA96: | | AB96: 1167 | AC96: | | AD96: 778 | AE96: | | AF96: 778 | AG96: | | AH96: 1556 | AI96: | | AK96: | | AL96: 10895 | AM96: | | AO96: | | AP96: 12840 | AQ96: | | AR96: 1556 | AS96: | | AT96: 29571 | AU96: | | AV96: 7393 | AW96: | | AX96: 3502 | AY96: | | AZ96: 6225 | BA96: | | BB96: 1167 | BC96: | | BD96: 1945 | BE96: | | BF96: 778 | BG96: | | BI96: | | BJ96: 3891 | BK96: | | BL96: 7393 | BM96: | | BO96: | | BP96: 778 | BQ96: | | BR96: 2335 | BS96: | | BU96: | | BW96: | | BX96: 5447 | BY96: | | BZ96: 1946 | CA96: | | CC96: | | CD96: 2724 | CE96: | | CF96: 2724 | CG96: | | CH96: 7393 | CI96: | | CJ96: 778 | CK96: | | CL96: 3502 | CM96: | | CN96: 389 | CO96: | | CP96: 1167 | CQ96: | | CR96: 6615 | CS96: | | CT96: 33462 | CU96: | | CV96: 5836 | CW96: | | CX96: 1167 | CY96: | | CZ96: 1556 | DA96: | | DC96: | | DD96: 2724 | DE96: | | DF96: 1167 | DG96: | | DH96: 16731 | DI96: | | DJ96: 1167 | DK96: | | DL96: 7004 | DM96: | | DN96: 7004 | DO96: | | DP96: 3891 | DQ96: | | DR96: 2724 | DS96: | | DT96: 2335 | DU96: | | DV96: 7393 | DW96: | | DX96: 6225 | DY96: | | DZ96: 1556 | EA96: | | EB96: 1945 | EC96: | | EE96: | | EF96: 778 | EG96: | | EI96: | | EJ96: 1945 | EK96: | | EL96: 2335 | EM96: | | EN96: 1167 | EO96: | | EQ96: | | ER96: 3502 | ES96: | | ET96: 4280 | EU96: | | EV96: 7393 | EW96: | | EY96: | | EZ96: 2335 | FA96: | | FB96: 2335 | FC96: | | FD96: 4669 | FE96: | | FG96: | | FH96: 10116 | FI96: | | FJ96: 18677 | FK96: | | FL96: 9338 | FM96: | | FN96: 1556 | FO96: | | FP96: 2724 | FQ96: | | FR96: 5058 | FS96: | | FT96: 2724 | FU96: | | FV96: 1556 | FW96: | | FX96: 3502 | FY96: | | FZ96: 5836 | GA96: | | GB96: 5447 | GC96: | | GE96: | | GG96: | | GI96: | | GJ96: 5836 | GK96: | | GL96: 4280 | GM96: | | GO96: | | GP96: 3502 | GQ96: | | GR96: 4669 | GS96: | | GT96: 3113 | GU96: | | GV96: 3113 | GW96: | | GX96: 8949 | GY96: | | GZ96: 3113 | HA96: | | HC96: | | HE96: | | HF96: 404266 | HG96: | | HI96: | | HJ96: 404266 | HK96: |
A97: 3150 | B97: ADULT EDUCATION: | C97: | | E97: | | G97: | | I97: | | K97: | | M97: | | O97: | | Q97: | | S97: | | U97: | | W97: | | Y97: | | AA97: | | AC97: | | AE97: | | AG97: | | AI97: | | AK97: | | AM97: | | AO97: | | AQ97: | | AS97: | | AU97: | | AW97: | | AY97: | | BA97: | | BC97: | | BE97: | | BG97: | | BI97: | | BK97: | | BM97: | | BO97: | | BQ97: | | BS97: | | BU97: | | BW97: | | BY97: | | CA97: | | CC97: | | CE97: | | CG97: | | CI97: | | CK97: | | CM97: | | CO97: | | CQ97: | | CS97: | | CU97: | | CW97: | | CY97: | | DA97: | | DC97: | | DE97: | | DG97: | | DI97: | | DK97: | | DM97: | | DO97: | | DQ97: | | DS97: | | DU97: | | DW97: | | DY97: | | EA97: | | EC97: | | EE97: | | EG97: | | EI97: | | EK97: | | EM97: | | EO97: | | EQ97: | | ES97: | | EU97: | | EW97: | | EY97: | | FA97: | | FC97: | | FE97: | | FG97: | | FI97: | | FK97: | | FM97: | | FO97: | | FQ97: | | FS97: | | FU97: | | FW97: | | FY97: | | GA97: | | GC97: | | GE97: | | GG97: | | GI97: | | GK97: | | GM97: | | GO97: | | GQ97: | | GS97: | | GU97: | | GW97: | | GY97: | | HA97: | | HC97: | | HE97: | | HG97: | | HI97: | | HK97: |
A98: 3151 | B98: BASIC | C98: | | E98: | | F98: 9409 | G98: | | H98: 3043 | I98: | | K98: | | M98: | | O98: | | Q98: | | S98: | | T98: 12480 | U98: | | W98: | | X98: 9892 | Y98: | | AA98: | | AC98: | | AE98: | | AG98: | | AI98: | | AK98: | | AL98: 9409 | AM98: | | AO98: | | AQ98: | | AR98: 10340 | AS98: | | AT98: 22480 | AU98: | | AV98: 13025 | AW98: | | AY98: | | BA98: | | BC98: | | BE98: | | BG98: | | BH98: 166948 | BI98: | | BJ98: 12480 | BK98: | | BL98: 12237 | BM98: | | BO98: | | BQ98: | | BS98: | | BU98: | | BW98: | | BX98: 12480 | BY98: | | CA98: | | CC98: | | CE98: | | CG98: | | CH98: 10712 | CI98: | | CK98: | | CM98: | | CO98: | | CQ98: | | CS98: | | CT98: 129120 | CU98: | | CV98: 9409 | CW98: | | CY98: | | DA98: | | DC98: | | DE98: | | DG98: | | DH98: 9469 | DI98: | | DK98: | | DL98: 8840 | DM98: | | DN98: 18273 | DO98: | | DP98: 5425 | DQ98: | | DS98: | | DU98: | | DW98: | | DX98: 10819 | DY98: | | EA98: | | EC98: | | EE98: | | EG98: | | EH98: 14703 | EI98: | | EK98: | | EM98: | | EO98: | | EQ98: | | ES98: | | EU98: | | EV98: 9409 | EW98: | | EY98: | | FA98: | | FC98: | | FE98: | | FG98: | | FH98: 1620 | FI98: | | FJ98: 12480 | FK98: | | FM98: | | FO98: | | FQ98: | | FS98: | | FU98: | | FW98: | | FY98: | | GA98: | | GB98: 9717 | GC98: | | GE98: | | GG98: | | GI98: | | GK98: | | GL98: 23230 | GM98: | | GO98: | | GP98: 3071 | GQ98: | | GS98: | | GU98: | | GW98: | | GX98: 14164 | GY98: | | HA98: | | HC98: | | HD98: 111656 | HE98: | | HF98: 584684 | HG98: | | HH98: 111656 | HI98: | | HJ98: 696340 | HK98: |
A99: 3152 | B99: ADULT ED - LITERACY | C99: | | E99: | | G99: | | I99: | | K99: | | M99: | | O99: | | Q99: | | S99: | | U99: | | W99: | | Y99: | | AA99: | | AC99: | | AE99: | | AG99: | | AI99: | | AK99: | | AM99: | | AO99: | | AQ99: | | AS99: | | AU99: | | AW99: | | AY99: | | BA99: | | BC99: | | BE99: | | BG99: | | BH99: 50000 | BI99: | | BK99: | | BM99: | | BO99: | | BQ99: | | BR99: 4715 | BS99: | | BU99: | | BW99: | | BY99: | | CA99: | | CC99: | | CE99: | | CG99: | | CI99: | | CK99: | | CM99: | | CO99: | | CQ99: | | CS99: | | CU99: | | CW99: | | CY99: | | DA99: | | DC99: | | DE99: | | DG99: | | DI99: | | DK99: | | DM99: | | DO99: | | DQ99: | | DS99: | | DU99: | | DW99: | | DY99: | | EA99: | | EC99: | | EE99: | | EG99: | | EI99: | | EK99: | | EM99: | | EO99: | | EQ99: | | ES99: | | EU99: | | EW99: | | EY99: | | FA99: | | FC99: | | FE99: | | FG99: | | FI99: | | FK99: | | FM99: | | FO99: | | FQ99: | | FS99: | | FU99: | | FW99: | | FY99: | | GA99: | | GC99: | | GE99: | | GG99: | | GI99: | | GK99: | | GM99: | | GO99: | | GQ99: | | GS99: | | GU99: | | GW99: | | GY99: | | HA99: | | HC99: | | HE99: | | HF99: 54715 | HG99: | | HI99: | | HJ99: 54715 | HK99: |
A100: 3153 | B100: VEHICLE TITLE TRANSFER FEE - ADULT | C100: | | E100: | | G100: | | I100: | | K100: | | M100: | | O100: | | Q100: | | S100: | | U100: | | W100: | | Y100: | | AA100: | | AC100: | | AE100: | | AG100: | | AI100: | | AK100: | | AM100: | | AO100: | | AQ100: | | AS100: | | AU100: | | AW100: | | AY100: | | BA100: | | BC100: | | BE100: | | BG100: | | BI100: | | BK100: | | BM100: | | BO100: | | BQ100: | | BS100: | | BU100: | | BW100: | | BY100: | | CA100: | | CC100: | | CE100: | | CG100: | | CI100: | | CK100: | | CM100: | | CO100: | | CQ100: | | CS100: | | CU100: | | CW100: | | CY100: | | DA100: | | DC100: | | DE100: | | DG100: | | DI100: | | DK100: | | DM100: | | DO100: | | DQ100: | | DS100: | | DU100: | | DW100: | | DY100: | | EA100: | | EC100: | | EE100: | | EG100: | | EI100: | | EK100: | | EM100: | | EO100: | | EQ100: | | ES100: | | EU100: | | EW100: | | EY100: | | FA100: | | FC100: | | FE100: | | FG100: | | FI100: | | FK100: | | FM100: | | FO100: | | FQ100: | | FS100: | | FU100: | | FW100: | | FY100: | | GA100: | | GC100: | | GE100: | | GG100: | | GI100: | | GK100: | | GM100: | | GO100: | | GQ100: | | GS100: | | GU100: | | GW100: | | GY100: | | HA100: | | HC100: | | HE100: | | HG100: | | HI100: | | HK100: |
A101: 3154 | B101: YOUNG ADULT POPULATION - ADULT ED | C101: | | E101: | | G101: | | I101: | | K101: | | M101: | | O101: | | Q101: | | S101: | | U101: | | W101: | | Y101: | | AA101: | | AC101: | | AE101: | | AG101: | | AI101: | | AK101: | | AM101: | | AO101: | | AQ101: | | AS101: | | AU101: | | AW101: | | AY101: | | BA101: | | BC101: | | BE101: | | BG101: | | BI101: | | BK101: | | BM101: | | BO101: | | BQ101: | | BS101: | | BU101: | | BW101: | | BY101: | | CA101: | | CC101: | | CE101: | | CG101: | | CI101: | | CK101: | | CM101: | | CO101: | | CQ101: | | CS101: | | CU101: | | CV101: 5947 | CW101: | | CY101: | | DA101: | | DC101: | | DD101: 8342 | DE101: | | DG101: | | DH101: 47347 | DI101: | | DK101: | | DL101: 28956 | DM101: | | DN101: 28318 | DO101: | | DP101: 23251 | DQ101: | | DS101: | | DU101: | | DV101: 64352 | DW101: | | DX101: 29384 | DY101: | | DZ101: 10606 | EA101: | | EC101: | | ED101: 20332 | EE101: | | EF101: 10893 | EG101: | | EH101: 19413 | EI101: | | EK101: | | EM101: | | EO101: | | EQ101: | | ER101: 15163 | ES101: | | ET101: 28500 | EU101: | | EV101: 29701 | EW101: | | EY101: | | FA101: | | FC101: | | FE101: | | FG101: | | FH101: 87592 | FI101: | | FJ101: 197676 | FK101: | | FL101: 36169 | FM101: | | FN101: 13511 | FO101: | | FQ101: | | FS101: | | FU101: | | FW101: | | FY101: | | GA101: | | GB101: 90551 | GC101: | | GE101: | | GG101: | | GI101: | | GK101: | | GL101: 177115 | GM101: | | GO101: | | GP101: 9301 | GQ101: | | GR101: 23688 | GS101: | | GU101: | | GV101: 43070 | GW101: | | GX101: 32978 | GY101: | | HA101: | | HC101: | | HE101: | | HF101: 1082156 | HG101: | | HI101: | | HJ101: 1082156 | HK101: |
...

Sheet 2-ID Study Revenues
A1: Evaluation of Download File (Step 1); Restructured to Extend all Districts across Columns
A2: Revenue Study / Row Codes: H=Row Heading, or Blank Row; F=Federal Revenue; S=State Revenue; L=Local Revenue; O=Other Revenue; X=Not a Study Revenue (Adult Ed, Non-SpEd PreSchool, Non-Revenue Item) | S2: See other NOTES on tab #5-Charters.
A3: Legend | B3: Green Highlight: Rows to be Removed
A4: Notes: Includes revenue for traditional district schools and charter schools by district; all revenues sources (some non-study revenue items to be deleted)
A6: Row
A7: Codes | D7: | | E7: ABBEVILLE | F7: | | G7: AIKEN | H7: | | I7: ALLENDALE | J7: | | K7: ANDERSON CTY BD | L7: | | M7: ANDERSON 01 | N7: | | O7: ANDERSON 02 | P7: | | Q7: ANDERSON 03 | R7: | | S7: ANDERSON 04 | T7: | | U7: ANDERSON 05 | V7: | | W7: ANDERSON ALT SCHOOL | X7: | | Y7: ANDERSON 1&2 CC | Z7: | | AA7: BAMBERG 01 | AB7: | | AC7: BAMBERG 02 | AD7: | | AE7: BARNWELL 19 | AF7: | | AG7: BARNWELL 29 | AH7: | | AI7: BARNWELL 45 | AJ7: | | AK7: BARNWELL VOC CEN | AL7: | | AM7: BEAUFORT | AN7: | | AO7: BEAUFORT-JASPER CEC | AP7: | | AQ7: BERKELEY | AR7: | | AS7: CALHOUN | AT7: | | AU7: CHARLESTON | AV7: | | AW7: CHEROKEE | AX7: | | AY7: CHESTER | AZ7: | | BA7: CHESTERFIELD | BB7: | | BC7: CLARENDON 01 | BD7: | | BE7: CLARENDON 02 | BF7: | | BG7: CLARENDON 03 | BH7: | | BI7: F.E. DUBOSE CC | BJ7: | | BK7: COLLETON | BL7: | | BM7: DARLINGTON | BN7: | | BO7: DILLON CTY BD | BP7: | | BQ7: DILLON 01 | BR7: | | BS7: DILLON 02 | BT7: | | BU7: DILLON 03 | BV7: | | BW7: DILLON ATC | BX7: | | BY7: DORCHESTER 02 | BZ7: | | CA7: DORCHESTER 04 | CB7: | | CC7: DORCHESTER CAR SCH | CD7: | | CE7: EDGEFIELD | CF7: | | CG7: FAIRFIELD | CH7: | | CI7: FLORENCE 01 | CJ7: | | CK7: FLORENCE 02 | CL7: | | CM7: FLORENCE 03 | CN7: | | CO7: FLORENCE 04 | CP7: | | CQ7: FLORENCE 05 | CR7: | | CS7: GEORGETOWN | CT7: | | CU7: GREENVILLE | CV7: | | CW7: GREENWOOD 50 | CX7: | | CY7: GREENWOOD 51 | CZ7: | | DA7: GREENWOOD 52 | DB7: | | DC7: GREENWOOD VOC FAC | DD7: | | DE7: HAMPTON 01 | DF7: | | DG7: HAMPTON 02 | DH7: | | DI7: HORRY | DJ7: | | DK7: JASPER | DL7: | | DM7: KERSHAW | DN7: | | DO7: LANCASTER | DP7: | | DQ7: LAURENS 55 | DR7: | | DS7: LAURENS 56 | DT7: | | DU7: LEE | DV7: | | DW7: LEXINGTON 01 | DX7: | | DY7: LEXINGTON 02 | DZ7: | | EA7: LEXINGTON 03 | EB7: | | EC7: LEXINGTON 04 | ED7: | | EE7: LEXINGTON 05 | EF7: | | EG7: MCCORMICK | EH7: | | EI7: MARION CTY BD | EJ7: | | EK7: MARION 01 | EL7: | | EM7: MARION 02 | EN7: | | EO7: MARION 07 | EP7: | | EQ7: MARION VOC CTR | ER7: | | ES7: MARLBORO | ET7: | | EU7: NEWBERRY | EV7: | | EW7: OCONEE | EX7: | | EY7: ORANGEBURG CTY BD | EZ7: | | FA7: ORANGEBURG 03 | FB7: | | FC7: ORANGEBURG 04 | FD7: | | FE7: ORANGEBURG 05 | FF7: | | FG7: COPE AVC | FH7: | | FI7: PICKENS | FJ7: | | FK7: RICHLAND 01 | FL7: | | FM7: RICHLAND 02 | FN7: | | FO7: SALUDA | FP7: | | FQ7: SPARTANBURG 01 | FR7: | | FS7: SPARTANBURG 02 | FT7: | | FU7: SPARTANBURG 03 | FV7: | | FW7: SPARTANBURG 04 | FX7: | | FY7: SPARTANBURG 05 | FZ7: | | GA7: SPARTANBURG 06 | GB7: | | GC7: SPARTANBURG 07 | GD7: | | GE7: DAN MORGAN VOC CEN | GF7: | | GG7: R.D. ANDERSON ATC | GH7: | | GI7: H.B. SWOFFORD CC | GJ7: | | GK7: SUMTER 02 | GL7: | | GM7: SUMTER 17 | GN7: | | GO7: SUMTER CC | GP7: | | GQ7: UNION | GR7: | | GS7: WILLIAMSBURG | GT7: | | GU7: YORK 01 | GV7: | | GW7: YORK 02 | GX7: | | GY7: YORK 03 | GZ7: | | HA7: YORK 04 | HB7: | | HC7: JUVENILE JUSTICE | HD7: | | HE7: PALMETTO UNIFIED | HF7: | | HG7: REGULAR DIST.TOTALS | HH7: | | HI7: SPECIAL DIST.TOTALS | HJ7: | | HK7: STATE TOTALS | HL7: |
D8: | | F8: | | H8: | | J8: | | L8: | | N8: | | P8: | | R8: | | T8: | | V8: | | X8: | | Z8: | | AB8: | | AD8: | | AF8: | | AH8: | | AJ8: | | AL8: | | AN8: | | AP8: | | AR8: | | AT8: | | AV8: | | AX8: | | AZ8: | | BB8: | | BD8: | | BF8: | | BH8: | | BJ8: | | BL8: | | BN8: | | BP8: | | BR8: | | BT8: | | BV8: | | BX8: | | BZ8: | | CB8: | | CD8: | | CF8: | | CH8: | | CJ8: | | CL8: | | CN8: | | CP8: | | CR8: | | CT8: | | CV8: | | CX8: | | CZ8: | | DB8: | | DD8: | | DF8: | | DH8: | | DJ8: | | DL8: | | DN8: | | DP8: | | DR8: | | DT8: | | DV8: | | DX8: | | DZ8: | | EB8: | | ED8: | | EF8: | | EH8: | | EJ8: | | EL8: | | EN8: | | EP8: | | ER8: | | ET8: | | EV8: | | EX8: | | EZ8: | | FB8: | | FD8: | | FF8: | | FH8: | | FJ8: | | FL8: | | FN8: | | FP8: | | FR8: | | FT8: | | FV8: | | FX8: | | FZ8: | | GB8: | | GD8: | | GF8: | | GH8: | | GJ8: | | GL8: | | GN8: | | GP8: | | GR8: | | GT8: | | GV8: | | GX8: | | GZ8: | | HB8: | | HD8: | | HF8: | | HH8: | | HJ8: | | HL8: |
A9: H | B9: 1000 | C9: REVENUE FROM LOCAL SOURCES: | D9: | | F9: | | H9: | | J9: | | L9: | | N9: | | P9: | | R9: | | T9: | | V9: | | X9: | | Z9: | | AB9: | | AD9: | | AF9: | | AH9: | | AJ9: | | AL9: | | AN9: | | AP9: | | AR9: | | AT9: | | AV9: | | AX9: | | AZ9: | | BB9: | | BD9: | | BF9: | | BH9: | | BJ9: | | BL9: | | BN9: | | BP9: | | BR9: | | BT9: | | BV9: | | BX9: | | BZ9: | | CB9: | | CD9: | | CF9: | | CH9: | | CJ9: | | CL9: | | CN9: | | CP9: | | CR9: | | CT9: | | CV9: | | CX9: | | CZ9: | | DB9: | | DD9: | | DF9: | | DH9: | | DJ9: | | DL9: | | DN9: | | DP9: | | DR9: | | DT9: | | DV9: | | DX9: | | DZ9: | | EB9: | | ED9: | | EF9: | | EH9: | | EJ9: | | EL9: | | EN9: | | EP9: | | ER9: | | ET9: | | EV9: | | EX9: | | EZ9: | | FB9: | | FD9: | | FF9: | | FH9: | | FJ9: | | FL9: | | FN9: | | FP9: | | FR9: | | FT9: | | FV9: | | FX9: | | FZ9: | | GB9: | | GD9: | | GF9: | | GH9: | | GJ9: | | GL9: | | GN9: | | GP9: | | GR9: | | GT9: | | GV9: | | GX9: | | GZ9: | | HB9: | | HD9: | | HF9: | | HH9: | | HJ9: | | HL9: |
A10: H | B10: 1100 | C10: TAXES ASSESSED/LEVIED BY LEA: | D10: | | F10: | | H10: | | J10: | | L10: | | N10: | | P10: | | R10: | | T10: | | V10: | | X10: | | Z10: | | AB10: | | AD10: | | AF10: | | AH10: | | AJ10: | | AL10: | | AN10: | | AP10: | | AR10: | | AT10: | | AV10: | | AX10: | | AZ10: | | BB10: | | BD10: | | BF10: | | BH10: | | BJ10: | | BL10: | | BN10: | | BP10: | | BR10: | | BT10: | | BV10: | | BX10: | | BZ10: | | CB10: | | CD10: | | CF10: | | CH10: | | CJ10: | | CL10: | | CN10: | | CP10: | | CR10: | | CT10: | | CV10: | | CX10: | | CZ10: | | DB10: | | DD10: | | DF10: | | DH10: | | DJ10: | | DL10: | | DN10: | | DP10: | | DR10: | | DT10: | | DV10: | | DX10: | | DZ10: | | EB10: | | ED10: | | EF10: | | EH10: | | EJ10: | | EL10: | | EN10: | | EP10: | | ER10: | | ET10: | | EV10: | | EX10: | | EZ10: | | FB10: | | FD10: | | FF10: | | FH10: | | FJ10: | | FL10: | | FN10: | | FP10: | | FR10: | | FT10: | | FV10: | | FX10: | | FZ10: | | GB10: | | GD10: | | GF10: | | GH10: | | GJ10: | | GL10: | | GN10: | | GP10: | | GR10: | | GT10: | | GV10: | | GX10: | | GZ10: | | HB10: | | HD10: | | HF10: | | HH10: | | HJ10: | | HL10: |
A11: L | B11: 1110 | C11: AD VALOREM TAXES (FISC INDEPEN) | D11: | | E11: 1520764 | F11: | | G11: 60312472 | H11: | | I11: 4709102 | J11: | | L11: | | N11: | | P11: | | R11: | | T11: | | V11: | | X11: | | Z11: | | AA11: 3518785 | AB11: | | AD11: | | AE11: 1608309 | AF11: | | AG11: 1694415 | AH11: | | AI11: 4983807 | AJ11: | | AL11: | | AN11: | | AP11: | | AQ11: 81057233 | AR11: | | AT11: | | AU11: 237617163 | AV11: | | AW11: 20857424 | AX11: | | AY11: 15774043 | AZ11: | | BA11: 13611432 | BB11: | | BD11: | | BF11: | | BH11: | | BJ11: | | BK11: 3633589 | BL11: | | BM11: 31643785 | BN11: | | BO11: 1164045 | BP11: | | BR11: | | BT11: | | BU11: 1669444 | BV11: | | BW11: 773207 | BX11: | | BY11: 47974404 | BZ11: | | CA11: 9991137 | CB11: | | CD11: | | CE11: 9211573 | CF11: | | CH11: | | CJ11: | | CL11: | | CM11: 6118718 | CN11: | | CO11: 2340676 | CP11: | | CR11: | | CS11: 53912753 | CT11: | | CU11: 209875704 | CV11: | | CX11: | | CZ11: | | DB11: | | DD11: | | DF11: | | DH11: | | DI11: 189882593 | DJ11: | | DL11: | | DN11: | | DO11: 27833046 | DP11: | | DQ11: 12598542 | DR11: | | DS11: 4931133 | DT11: | | DV11: | | DW11: 54022433 | DX11: | | DY11: 28570445 | DZ11: | | EA11: 8785696 | EB11: | | EC11: 6370433 | ED11: | | EE11: 75156901 | EF11: | | EH11: | | EI11: 1031638 | EJ11: | | EL11: | | EN11: | | EP11: | | EQ11: 829221 | ER11: | | ES11: 7589855 | ET11: | | EU11: 21368223 | EV11: | | EX11: | | EZ11: | | FA11: 8411421 | FB11: | | FC11: 9864404 | FD11: | | FE11: 22697920 | FF11: | | FH11: | | FI11: 41771782 | FJ11: | | FL11: | | FN11: | | FP11: | | FQ11: 15002986 | FR11: | | FS11: 19399837 | FT11: | | FU11: 10606763 | FV11: | | FW11: 6064849 | FX11: | | FY11: 27007132 | FZ11: | | GA11: 34914489 | GB11: | | GC11: 35418636 | GD11: | | GE11: 1220480 | GF11: | | GG11: 1790126 | GH11: | | GJ11: | | GL11: | | GN11: | | GP11: | | GQ11: 7548390 | GR11: | | GS11: 6863244 | GT11: | | GU11: 8885582 | GV11: | | GW11: 37156040 | GX11: | | GY11: 51613941 | GZ11: | | HA11: 34135864 | HB11: | | HD11: | | HF11: | | HG11: 1644918029 | HH11: | | HJ11: | | HK11: 1644918029 | HL11: |
A12: L | B12: 1140 | C12: PENALTY/INT ON TAX (FISC INDEP) | D12: | | E12: 132769 | F12: | | G12: 2319640 | H12: | | I12: 10538 | J12: | | L12: | | N12: | | P12: | | R12: | | T12: | | V12: | | X12: | | Z12: | | AB12: | | AD12: | | AE12: 22174 | AF12: | | AG12: 315835 | AH12: | | AJ12: | | AL12: | | AN12: | | AP12: | | AQ12: 283069 | AR12: | | AT12: | | AU12: 7206803 | AV12: | | AX12: | | AZ12: | | BA12: 69856 | BB12: | | BD12: | | BF12: | | BH12: | | BJ12: | | BL12: | | BM12: 149802 | BN12: | | BP12: | | BR12: | | BT12: | | BU12: 16783 | BV12: | | BW12: 7569 | BX12: | | BZ12: | | CB12: | | CD12: | | CE12: 63329 | CF12: | | CH12: | | CJ12: | | CL12: | | CM12: 24835 | CN12: | | CO12: 7929 | CP12: | | CR12: | | CS12: 338274 | CT12: | | CV12: | | CX12: | | CZ12: | | DB12: | | DD12: | | DF12: | | DH12: | | DI12: 1847104 | DJ12: | | DL12: | | DN12: | | DO12: 306014 | DP12: | | DQ12: 39250 | DR12: | | DS12: 352047 | DT12: | | DV12: | | DW12: 2948414 | DX12: | | DY12: 168908 | DZ12: | | EA12: 123038 | EB12: | | EC12: 60715 | ED12: | | EE12: 401443 | EF12: | | EH12: | | EI12: 13774 | EJ12: | | EL12: | | EN12: | | EP12: | | EQ12: 11472 | ER12: | | ES12: 98476 | ET12: | | EU12: 382847 | EV12: | | EX12: | | EZ12: | | FA12: 158859 | FB12: | | FC12: 92320 | FD12: | | FE12: 302645 | FF12: | | FH12: | | FI12: 356908 | FJ12: | | FL12: | | FN12: | | FP12: | | FR12: | | FT12: | | FV12: | | FX12: | | FZ12: | | GA12: 53219 | GB12: | | GD12: | | GF12: | | GG12: 118918 | GH12: | | GJ12: | | GL12: | | GN12: | | GP12: | | GQ12: 623388 | GR12: | | GT12: | | GU12: 436515 | GV12: | | GW12: 765865 | GX12: | | GY12: 436456 | GZ12: | | HA12: 117338 | HB12: | | HD12: | | HF12: | | HG12: 21185138 | HH12: | | HJ12: | | HK12: 21185138 | HL12: |
A13: L | B13: 1190 | C13: OTHER TAXES (FISCALLY INDEPEN) | D13: | | F13: | | H13: | | J13: | | L13: | | N13: | | P13: | | R13: | | T13: | | V13: | | X13: | | Z13: | | AB13: | | AD13: | | AF13: | | AH13: | | AJ13: | | AL13: | | AN13: | | AP13: | | AR13: | | AT13: | | AV13: | | AW13: 5051631 | AX13: | | AZ13: | | BB13: | | BD13: | | BF13: | | BH13: | | BJ13: | | BL13: | | BN13: | | BO13: 62076 | BP13: | | BR13: | | BT13: | | BU13: 347531 | BV13: | | BW13: 162535 | BX13: | | BZ13: | | CB13: | | CD13: | | CF13: | | CH13: | | CJ13: | | CL13: | | CN13: | | CP13: | | CR13: | | CT13: | | CV13: | | CX13: | | CZ13: | | DB13: | | DD13: | | DF13: | | DH13: | | DJ13: | | DL13: | | DN13: | | DP13: | | DR13: | | DT13: | | DV13: | | DW13: 25525556 | DX13: | | DZ13: | | EB13: | | ED13: | | EF13: | | EH13: | | EJ13: | | EL13: | | EN13: | | EP13: | | ER13: | | ES13: 8497 | ET13: | | EV13: | | EX13: | | EZ13: | | FB13: | | FD13: | | FF13: | | FH13: | | FI13: 5595 | FJ13: | | FL13: | | FN13: | | FP13: | | FR13: | | FT13: | | FV13: | | FX13: | | FY13: 1781081 | FZ13: | | GB13: | | GD13: | | GF13: | | GH13: | | GJ13: | | GL13: | | GN13: | | GP13: | | GR13: | | GT13: | | GV13: | | GX13: | | GZ13: | | HB13: | | HD13: | | HF13: | | HG13: 32944502 | HH13: | | HJ13: | | HK13: 32944502 | HL13: |
A14: H | B14: 1200 | C14: REV FR LOC GOV UNIT OTH THAN LEA: | D14: | | F14: | | H14: | | J14: | | L14: | | N14: | | P14: | | R14: | | T14: | | V14: | | X14: | | Z14: | | AB14: | | AD14: | | AF14: | | AH14: | | AJ14: | | AL14: | | AN14: | | AP14: | | AR14: | | AT14: | | AV14: | | AX14: | | AZ14: | | BB14: | | BD14: | | BF14: | | BH14: | | BJ14: | | BL14: | | BN14: | | BP14: | | BR14: | | BT14: | | BV14: | | BX14: | | BZ14: | | CB14: | | CD14: | | CF14: | | CH14: | | CJ14: | | CL14: | | CN14: | | CP14: | | CR14: | | CT14: | | CV14: | | CX14: | | CZ14: | | DB14: | | DD14: | | DF14: | | DH14: | | DJ14: | | DL14: | | DN14: | | DP14: | | DR14: | | DT14: | | DV14: | | DX14: | | DZ14: | | EB14: | | ED14: | | EF14: | | EH14: | | EJ14: | | EL14: | | EN14: | | EP14: | | ER14: | | ET14: | | EV14: | | EX14: | | EZ14: | | FB14: | | FD14: | | FF14: | | FH14: | | FJ14: | | FL14: | | FN14: | | FP14: | | FR14: | | FT14: | | FV14: | | FX14: | | FZ14: | | GB14: | | GD14: | | GF14: | | GH14: | | GJ14: | | GL14: | | GN14: | | GP14: | | GR14: | | GT14: | | GV14: | | GX14: | | GZ14: | | HB14: | | HD14: | | HF14: | | HH14: | | HJ14: | | HL14: |
A15: L | B15: 1210 | C15: AD VALOREM TAX (FISC DEPENDENT) | D15: | | E15: 6245819 | F15: | | H15: | | J15: | | K15: 433216 | L15: | | M15: 16421598 | N15: | | O15: 7017799 | P15: | | Q15: 5213455 | R15: | | S15: 12347769 | T15: | | U15: 33664427 | V15: | | W15: 868614 | X15: | | Y15: 2138478 | Z15: | | AB15: | | AC15: 2593235 | AD15: | | AF15: | | AH15: | | AJ15: | | AK15: 1111614 | AL15: | | AM15: 153402920 | AN15: | | AP15: | | AR15: | | AS15: 5828627 | AT15: | | AV15: | | AX15: | | AZ15: | | BB15: | | BC15: 3254202 | BD15: | | BE15: 3919418 | BF15: | | BG15: 1414172 | BH15: | | BI15: 195242 | BJ15: | | BK15: 13693942 | BL15: | | BN15: | | BP15: | | BQ15: 797062 | BR15: | | BS15: 3812551 | BT15: | | BV15: | | BX15: | | BZ15: | | CB15: | | CC15: 2977217 | CD15: | | CE15: 1735984 | CF15: | | CG15: 21351124 | CH15: | | CI15: 46691201 | CJ15: | | CK15: 2458856 | CL15: | | CN15: | | CP15: | | CQ15: 2852068 | CR15: | | CT15: | | CV15: | | CW15: 30220203 | CX15: | | CY15: 2691050 | CZ15: | | DA15: 7425961 | DB15: | | DC15: 1147565 | DD15: | | DE15: 5106272 | DF15: | | DG15: 3216142 | DH15: | | DJ15: | | DK15: 9192444 | DL15: | | DM15: 24813543 | DN15: | | DP15: | | DR15: | | DS15: 976985 | DT15: | | DU15: 4809755 | DV15: | | DX15: | | DZ15: | | EB15: | | ED15: | | EF15: | | EG15: 4962701 | EH15: | | EJ15: | | EK15: 3857014 | EL15: | | EM15: 2488097 | EN15: | | EO15: 1333045 | EP15: | | ER15: | | ET15: | | EV15: | | EW15: 54253011 | EX15: | | EZ15: | | FA15: 1874414 | FB15: | | FC15: 604807 | FD15: | | FE15: 3222083 | FF15: | | FH15: | | FJ15: | | FK15: 158166933 | FL15: | | FM15: 97862726 | FN15: | | FO15: 5417651 | FP15: | | FR15: | | FT15: | | FV15: | | FX15: | | FZ15: | | GB15: | | GD15: | | GF15: | | GH15: | | GI15: 1742817 | GJ15: | | GK15: 18310585 | GL15: | | GM15: 18715981 | GN15: | | GP15: | | GR15: | | GT15: | | GU15: 5888294 | GV15: | | GW15: 3131088 | GX15: | | GY15: 9576458 | GZ15: | | HB15: | | HD15: | | HF15: | | HG15: 833448235 | HH15: | | HJ15: | | HK15: 833448235 | HL15: |
A16: L | B16: 1240 | C16: PENALTY/INT ON TAX (FISC DEPEN) | D16: | | E16: 597511 | F16: | | H16: | | J16: | | L16: | | M16: 880175 | N16: | | O16: 621538 | P16: | | R16: | | T16: | | U16: 1894677 | V16: | | X16: | | Y16: 154664 | Z16: | | AB16: | | AC16: 263749 | AD16: | | AF16: | | AH16: | | AJ16: | | AK16: 7827 | AL16: | | AM16: 1108823 | AN16: | | AP16: | | AR16: | | AS16: 314398 | AT16: | | AV16: | | AX16: | | AZ16: | | BB16: | | BC16: 20715 | BD16: | | BE16: 58335 | BF16: | | BG16: 14132 | BH16: | | BJ16: | | BL16: | | BN16: | | BP16: | | BQ16: 10867 | BR16: | | BS16: 45178 | BT16: | | BV16: | | BX16: | | BZ16: | | CB16: | | CD16: | | CF16: | | CG16: 128917 | CH16: | | CI16: 94545 | CJ16: | | CK16: 8145 | CL16: | | CN16: | | CP16: | | CQ16: 8204 | CR16: | | CT16: | | CV16: | | CW16: 3144240 | CX16: | | CY16: 28733 | CZ16: | | DA16: 20006 | DB16: | | DC16: 101865 | DD16: | | DE16: 36588 | DF16: | | DG16: 44176 | DH16: | | DJ16: | | DK16: 147877 | DL16: | | DM16: 381137 | DN16: | | DP16: | | DR16: | | DT16: | | DU16: 41064 | DV16: | | DX16: | | DZ16: | | EB16: | | ED16: | | EF16: | | EH16: | | EJ16: | | EK16: 56050 | EL16: | | EM16: 36677 | EN16: | | EO16: 121914 | EP16: | | ER16: | | ET16: | | EV16: | | EW16: 172869 | EX16: | | EZ16: | | FB16: | | FD16: | | FF16: | | FH16: | | FJ16: | | FK16: 1748 | FL16: | | FM16: 1202011 | FN16: | | FP16: | | FR16: | | FT16: | | FV16: | | FX16: | | FZ16: | | GB16: | | GD16: | | GF16: | | GH16: | | GJ16: | | GL16: | | GN16: | | GP16: | | GR16: | | GT16: | | GU16: 233092 | GV16: | | GW16: 89758 | GX16: | | GZ16: | | HB16: | | HD16: | | HF16: | | HG16: 12092205 | HH16: | | HJ16: | | HK16: 12092205 | HL16: |
A17: L | B17: 1280 | C17: REV IN LIEU OF TAX (INDEP & DEP) | D17: | | E17: 248250 | F17: | | G17: 3228180 | H17: | | I17: 30934 | J17: | | K17: 16195 | L17: | | M17: 281920 | N17: | | O17: 110149 | P17: | | Q17: 663826 | R17: | | S17: 987719 | T17: | | U17: 705878 | V17: | | W17: 32380 | X17: | | Y17: 37121 | Z17: | | AB17: | | AC17: 58802 | AD17: | | AE17: 337725 | AF17: | | AH17: | | AJ17: | | AL17: | | AM17: 72555 | AN17: | | AP17: | | AQ17: 11717128 | AR17: | | AS17: 1501169 | AT17: | | AV17: | | AW17: 3487340 | AX17: | | AY17: 1808893 | AZ17: | | BA17: 1012904 | BB17: | | BD17: | | BF17: | | BH17: | | BJ17: | | BL17: | | BM17: 2270051 | BN17: | | BP17: | | BR17: | | BT17: | | BV17: | | BX17: | | BY17: 2558555 | BZ17: | | CA17: 136438 | CB17: | | CD17: | | CF17: | | CG17: 81935 | CH17: | | CI17: 1352744 | CJ17: | | CK17: 18213 | CL17: | | CM17: 512915 | CN17: | | CO17: 778498 | CP17: | | CQ17: 75913 | CR17: | | CS17: 260827 | CT17: | | CU17: 14519384 | CV17: | | CX17: | | CY17: 239598 | CZ17: | | DB17: | | DD17: | | DE17: 175 | DF17: | | DH17: | | DI17: 3339957 | DJ17: | | DK17: 424974 | DL17: | | DM17: 2160178 | DN17: | | DO17: 1429643 | DP17: | | DQ17: 262951 | DR17: | | DS17: 635032 | DT17: | | DU17: 151497 | DV17: | | DW17: 3660322 | DX17: | | DY17: 1228103 | DZ17: | | EA17: 9708 | EB17: | | EC17: 449301 | ED17: | | EE17: 78278 | EF17: | | EG17: 138537 | EH17: | | EJ17: | | EK17: 107735 | EL17: | | EM17: 66565 | EN17: | | EP17: | | ER17: | | ES17: 2473128 | ET17: | | EU17: 1173323 | EV17: | | EW17: 1913859 | EX17: | | EZ17: | | FA17: 983273 | FB17: | | FC17: 164336 | FD17: | | FE17: 1488642 | FF17: | | FH17: | | FI17: 57293 | FJ17: | | FK17: 6147665 | FL17: | | FM17: 955039 | FN17: | | FP17: | | FR17: | | FS17: 66554 | FT17: | | FU17: 1296281 | FV17: | | FW17: 126483 | FX17: | | FY17: 4902610 | FZ17: | | GA17: 1833006 | GB17: | | GC17: 42550 | GD17: | | GE17: 2821 | GF17: | | GG17: 11374 | GH17: | | GJ17: | | GK17: 286707 | GL17: | | GN17: | | GP17: | | GR17: | | GS17: 3398472 | GT17: | | GV17: | | GW17: 194008 | GX17: | | GZ17: | | HA17: 2423424 | HB17: | | HD17: | | HF17: | | HG17: 93227943 | HH17: | | HJ17: | | HK17: 93227943 | HL17: |
A18: L | B18: 1290 | C18: OTHER TAXES (FISCALLY DEPENDENT) | D18: | | E18: -185981 | F18: | | H18: | | J18: | | L18: | | M18: 2529411 | N18: | | O18: 1058039 | P18: | | R18: | | T18: | | U18: 3578859 | V18: | | X18: | | Z18: | | AB18: | | AD18: | | AF18: | | AH18: | | AJ18: | | AL18: | | AN18: | | AP18: | | AR18: | | AT18: | | AV18: | | AX18: | | AZ18: | | BA18: 2678003 | BB18: | | BC18: 498106 | BD18: | | BF18: | | BG18: 592984 | BH18: | | BJ18: | | BL18: | | BN18: | | BP18: | | BQ18: 191741 | BR18: | | BS18: 693689 | BT18: | | BV18: | | BX18: | | BZ18: | | CB18: | | CD18: | | CF18: | | CH18: | | CJ18: | | CL18: | | CN18: | | CP18: | | CR18: | | CT18: | | CV18: | | CX18: | | CZ18: | | DB18: | | DD18: | | DF18: | | DH18: | | DJ18: | | DL18: | | DN18: | | DP18: | | DR18: | | DT18: | | DU18: 162622 | DV18: | | DX18: | | DZ18: | | EB18: | | ED18: | | EF18: | | EH18: | | EJ18: | | EL18: | | EN18: | | EP18: | | ER18: | | ET18: | | EV18: | | EX18: | | EZ18: | | FB18: | | FC18: 2395955 | FD18: | | FF18: | | FH18: | | FJ18: | | FL18: | | FN18: | | FP18: | | FR18: | | FS18: 2896709 | FT18: | | FV18: | | FX18: | | FZ18: | | GB18: | | GD18: | | GF18: | | GH18: | | GJ18: | | GL18: | | GN18: | | GP18: | | GR18: | | GT18: | | GV18: | | GX18: | | GZ18: | | HB18: | | HD18: | | HF18: | | HG18: 17090137 | HH18: | | HJ18: | | HK18: 17090137 | HL18: |
A19: H | B19: 1300 | C19: TUITION: | D19: | | F19: | | H19: | | J19: | | L19: | | N19: | | P19: | | R19: | | T19: | | V19: | | X19: | | Z19: | | AB19: | | AD19: | | AF19: | | AH19: | | AJ19: | | AL19: | | AN19: | | AP19: | | AR19: | | AT19: | | AV19: | | AX19: | | AZ19: | | BB19: | | BD19: | | BF19: | | BH19: | | BJ19: | | BL19: | | BN19: | | BP19: | | BR19: | | BT19: | | BV19: | | BX19: | | BZ19: | | CB19: | | CD19: | | CF19: | | CH19: | | CJ19: | | CL19: | | CN19: | | CP19: | | CR19: | | CT19: | | CV19: | | CX19: | | CZ19: | | DB19: | | DD19: | | DF19: | | DH19: | | DJ19: | | DL19: | | DN19: | | DP19: | | DR19: | | DT19: | | DV19: | | DX19: | | DZ19: | | EB19: | | ED19: | | EF19: | | EH19: | | EJ19: | | EL19: | | EN19: | | EP19: | | ER19: | | ET19: | | EV19: | | EX19: | | EZ19: | | FB19: | | FD19: | | FF19: | | FH19: | | FJ19: | | FL19: | | FN19: | | FP19: | | FR19: | | FT19: | | FV19: | | FX19: | | FZ19: | | GB19: | | GD19: | | GF19: | | GH19: | | GJ19: | | GL19: | | GN19: | | GP19: | | GR19: | | GT19: | | GV19: | | GX19: | | GZ19: | | HB19: | | HD19: | | HF19: | | HH19: | | HJ19: | | HL19: |
