Workbook
Name BudgetCategory: BudgetCategoryLookup[Budget Category Lookup]
Name ConstructionCategory: [1]!BudgetCategoryLookup[Budget Category Lookup]

Sheet Budget Report
A2: Attention: | D2: MAI Representative:
A3: Title: | D3: Project Title:
A4: Company Name: | D4: Quote Number:
A5: Address: | D5: Date:
A8: Cost Analysis
B10: Rentable SF | C10: Costs | D10: Total | E10: Per SF
C11: Construction | D11: =SUMIF('Budget Details'!A:A,"Construction",'Budget Details'!F:F) -> 0 | E11: =Table4[[#This Row],[Total]]/B11 -> #DIV/0!
C12: MAI Package | D12: =SUMIF('Budget Details'!A:A, "Systems",'Budget Details'!F:F)+SUMIF('Budget Details'!A:A,"Lateral Files",'Budget Details'!F:F)+SUMIF('Budget Details'!A:A,"Seating",'Budget Details'!F:F)+SUMIF('Budget Details'!A:A,"Tables",'Budget Details'!F:F)+SUMIF('Budget Details'!A:A,"Private Offices",'Budget Details'!F:F)+SUMIF('Budget Details'!A:A,"Sound Masking", 'Budget Details'!F:F)+SUMIF('Budget Details'!A:A,"Walls",'Budget Details'!F:F)+SUMIF('Budget Details'!A:A,"Carpet",'Budget Details'!F:F)+SUMIF('Budget Details'!A:A,"Cabling",'Budget Details'!F:F) -> 0 | E12: =Table4[[#This Row],[Total]]/B11 -> #DIV/0!
C13: Total | D13: =SUM(D11:D12) -> 0 | E13: =SUM(E11:E12) -> #DIV/0!
C15: Breakdown
B16: Categories | C16: Cost | D16: $ per SF | E16: % Total

Sheet Budget Details
A1: Category | B1: List Price | C1: Installation | D1: Discount | E1: Markup | F1: Sale Price | G1: $/sf | H1: % of Total
F2: =(BudgetDetails[[#This Row],[List Price]]*(1-BudgetDetails[[#This Row],[Discount]]))*(1+BudgetDetails[[#This Row],[Markup]])+BudgetDetails[[#This Row],[Installation]] -> 0 | G2: =BudgetDetails[[#This Row],[Sale Price]]/'Budget Report'!B11 -> #DIV/0! | H2: =BudgetDetails[$/sf]/SUM(G:G) -> #DIV/0!
F3: =(BudgetDetails[[#This Row],[List Price]]*(1-BudgetDetails[[#This Row],[Discount]]))*(1+BudgetDetails[[#This Row],[Markup]])+BudgetDetails[[#This Row],[Installation]] -> 0 | G3: =BudgetDetails[[#This Row],[Sale Price]]/'Budget Report'!B11 -> #DIV/0! | H3: =BudgetDetails[$/sf]/SUM(G:G) -> #DIV/0!
F4: =(BudgetDetails[[#This Row],[List Price]]*(1-BudgetDetails[[#This Row],[Discount]]))*(1+BudgetDetails[[#This Row],[Markup]])+BudgetDetails[[#This Row],[Installation]] -> 0 | G4: =BudgetDetails[[#This Row],[Sale Price]]/'Budget Report'!B11 -> #DIV/0! | H4: =BudgetDetails[$/sf]/SUM(G:G) -> #DIV/0!
F5: =(BudgetDetails[[#This Row],[List Price]]*(1-BudgetDetails[[#This Row],[Discount]]))*(1+BudgetDetails[[#This Row],[Markup]])+BudgetDetails[[#This Row],[Installation]] -> 0 | G5: =BudgetDetails[[#This Row],[Sale Price]]/'Budget Report'!B11 -> #DIV/0! | H5: =BudgetDetails[$/sf]/SUM(G:G) -> #DIV/0!
F6: =(BudgetDetails[[#This Row],[List Price]]*(1-BudgetDetails[[#This Row],[Discount]]))*(1+BudgetDetails[[#This Row],[Markup]])+BudgetDetails[[#This Row],[Installation]] -> 0 | G6: =BudgetDetails[[#This Row],[Sale Price]]/'Budget Report'!B11 -> #DIV/0! | H6: =BudgetDetails[$/sf]/SUM(G:G) -> #DIV/0!
F7: =(BudgetDetails[[#This Row],[List Price]]*(1-BudgetDetails[[#This Row],[Discount]]))*(1+BudgetDetails[[#This Row],[Markup]])+BudgetDetails[[#This Row],[Installation]] -> 0 | G7: =BudgetDetails[[#This Row],[Sale Price]]/'Budget Report'!B11 -> #DIV/0! | H7: =BudgetDetails[$/sf]/SUM(G:G) -> #DIV/0!
F8: =(BudgetDetails[[#This Row],[List Price]]*(1-BudgetDetails[[#This Row],[Discount]]))*(1+BudgetDetails[[#This Row],[Markup]])+BudgetDetails[[#This Row],[Installation]] -> 0 | G8: =BudgetDetails[[#This Row],[Sale Price]]/'Budget Report'!B11 -> #DIV/0! | H8: =BudgetDetails[$/sf]/SUM(G:G) -> #DIV/0!
F9: =(BudgetDetails[[#This Row],[List Price]]*(1-BudgetDetails[[#This Row],[Discount]]))*(1+BudgetDetails[[#This Row],[Markup]])+BudgetDetails[[#This Row],[Installation]] -> 0 | G9: =BudgetDetails[[#This Row],[Sale Price]]/'Budget Report'!B11 -> #DIV/0! | H9: =BudgetDetails[$/sf]/SUM(G:G) -> #DIV/0!
F10: =(BudgetDetails[[#This Row],[List Price]]*(1-BudgetDetails[[#This Row],[Discount]]))*(1+BudgetDetails[[#This Row],[Markup]])+BudgetDetails[[#This Row],[Installation]] -> 0 | G10: =BudgetDetails[[#This Row],[Sale Price]]/'Budget Report'!B11 -> #DIV/0! | H10: =BudgetDetails[$/sf]/SUM(G:G) -> #DIV/0!
F11: =(BudgetDetails[[#This Row],[List Price]]*(1-BudgetDetails[[#This Row],[Discount]]))*(1+BudgetDetails[[#This Row],[Markup]])+BudgetDetails[[#This Row],[Installation]] -> 0 | G11: =BudgetDetails[[#This Row],[Sale Price]]/'Budget Report'!B11 -> #DIV/0! | H11: =BudgetDetails[$/sf]/SUM(G:G) -> #DIV/0!
F12: =(BudgetDetails[[#This Row],[List Price]]*(1-BudgetDetails[[#This Row],[Discount]]))*(1+BudgetDetails[[#This Row],[Markup]])+BudgetDetails[[#This Row],[Installation]] -> 0 | G12: =BudgetDetails[[#This Row],[Sale Price]]/'Budget Report'!B11 -> #DIV/0! | H12: =BudgetDetails[$/sf]/SUM(G:G) -> #DIV/0!
F13: =(BudgetDetails[[#This Row],[List Price]]*(1-BudgetDetails[[#This Row],[Discount]]))*(1+BudgetDetails[[#This Row],[Markup]])+BudgetDetails[[#This Row],[Installation]] -> 0 | G13: =BudgetDetails[[#This Row],[Sale Price]]/'Budget Report'!B11 -> #DIV/0! | H13: =BudgetDetails[$/sf]/SUM(G:G) -> #DIV/0!
F14: =(BudgetDetails[[#This Row],[List Price]]*(1-BudgetDetails[[#This Row],[Discount]]))*(1+BudgetDetails[[#This Row],[Markup]])+BudgetDetails[[#This Row],[Installation]] -> 0 | G14: =BudgetDetails[[#This Row],[Sale Price]]/'Budget Report'!B11 -> #DIV/0! | H14: =BudgetDetails[$/sf]/SUM(G:G) -> #DIV/0!
F15: =(BudgetDetails[[#This Row],[List Price]]*(1-BudgetDetails[[#This Row],[Discount]]))*(1+BudgetDetails[[#This Row],[Markup]])+BudgetDetails[[#This Row],[Installation]] -> 0 | G15: =BudgetDetails[[#This Row],[Sale Price]]/'Budget Report'!B11 -> #DIV/0! | H15: =BudgetDetails[$/sf]/SUM(G:G) -> #DIV/0!
F16: =(BudgetDetails[[#This Row],[List Price]]*(1-BudgetDetails[[#This Row],[Discount]]))*(1+BudgetDetails[[#This Row],[Markup]])+BudgetDetails[[#This Row],[Installation]] -> 0 | G16: =BudgetDetails[[#This Row],[Sale Price]]/'Budget Report'!B11 -> #DIV/0! | H16: =BudgetDetails[$/sf]/SUM(G:G) -> #DIV/0!
F17: =(BudgetDetails[[#This Row],[List Price]]*(1-BudgetDetails[[#This Row],[Discount]]))*(1+BudgetDetails[[#This Row],[Markup]])+BudgetDetails[[#This Row],[Installation]] -> 0 | G17: =BudgetDetails[[#This Row],[Sale Price]]/'Budget Report'!B11 -> #DIV/0! | H17: =BudgetDetails[$/sf]/SUM(G:G) -> #DIV/0!
F18: =(BudgetDetails[[#This Row],[List Price]]*(1-BudgetDetails[[#This Row],[Discount]]))*(1+BudgetDetails[[#This Row],[Markup]])+BudgetDetails[[#This Row],[Installation]] -> 0 | G18: =BudgetDetails[[#This Row],[Sale Price]]/'Budget Report'!B11 -> #DIV/0! | H18: =BudgetDetails[$/sf]/SUM(G:G) -> #DIV/0!
F19: =(BudgetDetails[[#This Row],[List Price]]*(1-BudgetDetails[[#This Row],[Discount]]))*(1+BudgetDetails[[#This Row],[Markup]])+BudgetDetails[[#This Row],[Installation]] -> 0 | G19: =BudgetDetails[[#This Row],[Sale Price]]/'Budget Report'!B11 -> #DIV/0! | H19: =BudgetDetails[$/sf]/SUM(G:G) -> #DIV/0!
F20: =(BudgetDetails[[#This Row],[List Price]]*(1-BudgetDetails[[#This Row],[Discount]]))*(1+BudgetDetails[[#This Row],[Markup]])+BudgetDetails[[#This Row],[Installation]] -> 0 | G20: =BudgetDetails[[#This Row],[Sale Price]]/'Budget Report'!B11 -> #DIV/0! | H20: =BudgetDetails[$/sf]/SUM(G:G) -> #DIV/0!
F21: =(BudgetDetails[[#This Row],[List Price]]*(1-BudgetDetails[[#This Row],[Discount]]))*(1+BudgetDetails[[#This Row],[Markup]])+BudgetDetails[[#This Row],[Installation]] -> 0 | G21: =BudgetDetails[[#This Row],[Sale Price]]/'Budget Report'!B11 -> #DIV/0! | H21: =BudgetDetails[$/sf]/SUM(G:G) -> #DIV/0!
F22: =(BudgetDetails[[#This Row],[List Price]]*(1-BudgetDetails[[#This Row],[Discount]]))*(1+BudgetDetails[[#This Row],[Markup]])+BudgetDetails[[#This Row],[Installation]] -> 0 | G22: =BudgetDetails[[#This Row],[Sale Price]]/'Budget Report'!B11 -> #DIV/0! | H22: =BudgetDetails[$/sf]/SUM(G:G) -> #DIV/0!
F23: =(BudgetDetails[[#This Row],[List Price]]*(1-BudgetDetails[[#This Row],[Discount]]))*(1+BudgetDetails[[#This Row],[Markup]])+BudgetDetails[[#This Row],[Installation]] -> 0 | G23: =BudgetDetails[[#This Row],[Sale Price]]/'Budget Report'!B11 -> #DIV/0! | H23: =BudgetDetails[$/sf]/SUM(G:G) -> #DIV/0!
F24: =(BudgetDetails[[#This Row],[List Price]]*(1-BudgetDetails[[#This Row],[Discount]]))*(1+BudgetDetails[[#This Row],[Markup]])+BudgetDetails[[#This Row],[Installation]] -> 0 | G24: =BudgetDetails[[#This Row],[Sale Price]]/'Budget Report'!B11 -> #DIV/0! | H24: =BudgetDetails[$/sf]/SUM(G:G) -> #DIV/0!
F25: =(BudgetDetails[[#This Row],[List Price]]*(1-BudgetDetails[[#This Row],[Discount]]))*(1+BudgetDetails[[#This Row],[Markup]])+BudgetDetails[[#This Row],[Installation]] -> 0 | G25: =BudgetDetails[[#This Row],[Sale Price]]/'Budget Report'!B11 -> #DIV/0! | H25: =BudgetDetails[$/sf]/SUM(G:G) -> #DIV/0!
F26: =(BudgetDetails[[#This Row],[List Price]]*(1-BudgetDetails[[#This Row],[Discount]]))*(1+BudgetDetails[[#This Row],[Markup]])+BudgetDetails[[#This Row],[Installation]] -> 0 | G26: =BudgetDetails[[#This Row],[Sale Price]]/'Budget Report'!B11 -> #DIV/0! | H26: =BudgetDetails[$/sf]/SUM(G:G) -> #DIV/0!
F27: =(BudgetDetails[[#This Row],[List Price]]*(1-BudgetDetails[[#This Row],[Discount]]))*(1+BudgetDetails[[#This Row],[Markup]])+BudgetDetails[[#This Row],[Installation]] -> 0 | G27: =BudgetDetails[[#This Row],[Sale Price]]/'Budget Report'!B11 -> #DIV/0! | H27: =BudgetDetails[$/sf]/SUM(G:G) -> #DIV/0!
F28: =(BudgetDetails[[#This Row],[List Price]]*(1-BudgetDetails[[#This Row],[Discount]]))*(1+BudgetDetails[[#This Row],[Markup]])+BudgetDetails[[#This Row],[Installation]] -> 0 | G28: =BudgetDetails[[#This Row],[Sale Price]]/'Budget Report'!B11 -> #DIV/0! | H28: =BudgetDetails[$/sf]/SUM(G:G) -> #DIV/0!
F29: =(BudgetDetails[[#This Row],[List Price]]*(1-BudgetDetails[[#This Row],[Discount]]))*(1+BudgetDetails[[#This Row],[Markup]])+BudgetDetails[[#This Row],[Installation]] -> 0 | G29: =BudgetDetails[[#This Row],[Sale Price]]/'Budget Report'!B11 -> #DIV/0! | H29: =BudgetDetails[$/sf]/SUM(G:G) -> #DIV/0!
F30: =(BudgetDetails[[#This Row],[List Price]]*(1-BudgetDetails[[#This Row],[Discount]]))*(1+BudgetDetails[[#This Row],[Markup]])+BudgetDetails[[#This Row],[Installation]] -> 0 | G30: =BudgetDetails[[#This Row],[Sale Price]]/'Budget Report'!B11 -> #DIV/0! | H30: =BudgetDetails[$/sf]/SUM(G:G) -> #DIV/0!
F31: =(BudgetDetails[[#This Row],[List Price]]*(1-BudgetDetails[[#This Row],[Discount]]))*(1+BudgetDetails[[#This Row],[Markup]])+BudgetDetails[[#This Row],[Installation]] -> 0 | G31: =BudgetDetails[[#This Row],[Sale Price]]/'Budget Report'!B11 -> #DIV/0! | H31: =BudgetDetails[$/sf]/SUM(G:G) -> #DIV/0!
F32: =(BudgetDetails[[#This Row],[List Price]]*(1-BudgetDetails[[#This Row],[Discount]]))*(1+BudgetDetails[[#This Row],[Markup]])+BudgetDetails[[#This Row],[Installation]] -> 0 | G32: =BudgetDetails[[#This Row],[Sale Price]]/'Budget Report'!B11 -> #DIV/0! | H32: =BudgetDetails[$/sf]/SUM(G:G) -> #DIV/0!

Sheet Lookup Lists
A1: Budget Category Lookup
A2: Cabling
A3: Carpet
A4: Construction
A5: Lateral Files
A6: Private Offices
A7: Seating
A8: Sound Masking
A9: Systems
A10: Tables
A11: Walls
