Workbook
Name _Rev07: Master!$A$1:$EJ$666

Sheet Legend
A2: Legend
D3: Local
D5: State
D7: Federal
D9: Other
D11: Indeterminate
D13: Pre K Enrollments
D15: Not Used
A18: Source | B18: New Jersey Department of Education
A20: All files are "read only" and based on data collections from the New Jersey Department of Education.
A21: The conclusions reached in this document are those of the author(s) and do not necessarily represent those
A22: of Ball State University.

Sheet Figures 1,2,4
A1: Figure 1 | M1: Figure 2
A2: New Jersey (2006-07) | B2: Statewide | D2: Statewide Weighted for Charter Enrollment | F2: Jersey City | H2: Newark | J2: Trenton | N2: District | O2: Charter | P2: Difference | R2: Trenton charter numbers reflect a significant drop from the FY03 analysis.
A3: Per-Pupil Revenue | M3: State | N3: 17110.216 | O3: 12441.618 | P3: 4668.5987 | R3: Compared the files. It appears that Granville Charter School did not operate in FY07 -
A4: District | B4: ='[1]State Dist'!$CL$618 -> 17110.216 | D4: 19837 | F4: ='[1]State Dist'!$CL$625 -> 21951.563 | H4: ='[1]State Dist'!$CL$632 -> 23594.054 | J4: ='[1]State Dist'!$CL$639 -> 23655.25 | M4: Statewide Weighted | N4: 19837 | O4: 12442 | P4: 7395
A5: Charter | B5: ='[1]State Chart'!$CL$58 -> 12441.618 | D5: 12442 | F5: ='[1]State Chart'!$CL$69 -> 11886.06 | H5: ='[1]State Chart'!$CL$83 -> 11677.314 | J5: ='[1]State Chart'!$CL$90 -> 12648.808 | M5: Jersey City | N5: 21951.563 | O5: 11886.06 | P5: 10065.503 | R5: - it was by far the largest charter school in the city with 1188 pupils in FY03.
A6: Difference | B6: =B4-B5 -> 4668.5987 | D6: 7395 | F6: =F4-F5 -> 10065.503 | H6: =H4-H5 -> 11916.741 | J6: =J4-J5 -> 11006.442 | M6: Newark | N6: 23594.054 | O6: 11677.314 | P6: 11916.741 | R6: The closing of that school would affect significantly the numbers presented in FY07.
B7: =B6/B4 -> 0.27285445 | D7: 0.373 | F7: =F6/F4 -> 0.45853241 | H7: =H6/H4 -> 0.50507388 | J7: =J6/J4 -> 0.46528536 | M7: Trenton | N7: 23655.25 | O7: 12648.808 | P7: 11006.442 | R7: Confirmed on SDE website that Granville is not operational in FY07
A8: Per-Pupil Revenue by Source | B8: District | C8: Charter | D8: District | E8: Charter | F8: District | G8: Charter | H8: District | I8: Charter | J8: District | K8: Charter | M8: Figure 2: Per Pupil Revenue for New Jersey District & Charter Schools, FY 2006-07
A9: Federal | B9: ='[1]State Dist'!$BF$618 -> 549.52683 | C9: ='[1]State Chart'!$BF$58 -> 1140.7799 | D9: 963 | E9: 1140.7799 | F9: ='[1]State Dist'!$BF$625 -> 1314.3847 | G9: ='[1]State Chart'!$BF$69 -> 1139.3091 | H9: ='[1]State Dist'!$BF$632 -> 1625.7832 | I9: ='[1]State Chart'!$BF$83 -> 1217.9403 | J9: ='[1]State Dist'!$BF$639 -> 1251.6225 | K9: ='[1]State Chart'!$BF$90 -> 1239.0861
A10: State | B10: ='[1]State Dist'!$AV$618 -> 6503.1246 | C10: ='[1]State Chart'!$AV$58 -> 8911.6816 | D10: 11898 | E10: 8911.6816 | F10: ='[1]State Dist'!$AV$625 -> 17347.826 | G10: ='[1]State Chart'!$AV$69 -> 8585.1296 | H10: ='[1]State Dist'!$AV$632 -> 17448.688 | I10: ='[1]State Chart'!$AV$83 -> 9114.2904 | J10: ='[1]State Dist'!$AV$639 -> 21332.867 | K10: ='[1]State Chart'!$AV$90 -> 9491.2024
A11: Local | B11: ='[1]State Dist'!$O$618 -> 9080.4845 | C11: ='[1]State Chart'!$N$58 -> 2314.9006 | D11: 5959 | E11: 2314.9006 | F11: ='[1]State Dist'!$O$625 -> 3152.3881 | G11: ='[1]State Chart'!$N$69 -> 2083.2195 | H11: ='[1]State Dist'!$O$632 -> 2254.5849 | I11: ='[1]State Chart'!$N$83 -> 1332.5719 | J11: ='[1]State Dist'!$O$639 -> 956.70679 | K11: ='[1]State Chart'!$N$90 -> 1918.5199
A12: Other | B12: ='[1]State Dist'!$CC$618 -> 541.00187 | C12: ='[1]State Chart'!$CC$58 -> 63.305208 | D12: 781 | E12: 63.305208 | F12: ='[1]State Dist'!$CC$625 -> 136.96403 | G12: ='[1]State Chart'!$CC$69 -> 78.401425 | H12: ='[1]State Dist'!$CC$632 -> 2252.0969 | I12: ='[1]State Chart'!$CC$83 -> 12.511356 | J12: ='[1]State Dist'!$CC$639 -> 114.05395 | K12: ='[1]State Chart'!$CC$90 -> 0
A13: Indeterminate | B13: ='[1]State Dist'!$CK$618 -> 436.07851 | C13: ='[1]State Chart'!$CK$58 -> 10.950263 | D13: 236 | E13: 10.950263 | F13: ='[1]State Dist'!$CK$625 -> 0 | G13: ='[1]State Chart'!$CK$69 -> 0 | H13: ='[1]State Dist'!$CK$632 -> 12.901808 | I13: ='[1]State Chart'!$CK$83 -> 0 | J13: ='[1]State Dist'!$CK$639 -> 0 | K13: ='[1]State Chart'!$CK$90 -> 0
A14: Total | B14: =SUM(B9:B13) -> 17110.216 | C14: =SUM(C9:C13) -> 12441.618 | D14: 19837 | E14: 12441.618 | F14: =SUM(F9:F13) -> 21951.563 | G14: =SUM(G9:G13) -> 11886.06 | H14: =SUM(H9:H13) -> 23594.054 | I14: =SUM(I9:I13) -> 11677.314 | J14: =SUM(J9:J13) -> 23655.25 | K14: =SUM(K9:K13) -> 12648.808
A15: Enrollment
A16: District | B16: ='[1]State Dist'!$F$617 -> 1331638 | D16: n/a | F16: ='[1]State Dist'!$F$622 -> 28910 | H16: ='[1]State Dist'!$F$629 -> 41266 | J16: ='[1]State Dist'!$F$636 -> 12047.5
B17: =B16/(B16+B18) -> 0.98831893 | D17: n/a | F17: =F16/(F16+F18) -> 0.90749286 | H17: =H16/(H16+H18) -> 0.92271641 | J17: =J16/(J16+J18) -> 0.89439495
A18: Charter | B18: ='[1]State Chart'!$F$57 -> 15738.8 | D18: n/a | F18: ='[1]State Chart'!$F$68 -> 2947 | H18: ='[1]State Chart'!$F$82 -> 3456.3 | J18: ='[1]State Chart'!$F$89 -> 1422.5
B19: =B18/(B16+B18) -> 0.011681068 | D19: n/a | F19: =F18/(F16+F18) -> 0.092507141 | H19: =H18/(H16+H18) -> 0.077283592 | J19: =J18/(J16+J18) -> 0.10560505
A20: Number of Charters | B20: 53 | D20: n/a | F20: 8 | H20: 11 | J20: 4
A21: Total Revenue
A22: District | B22: ='[1]State Dist'!$CL$617 -> 22784614225 | D22: n/a | F22: ='[1]State Dist'!$CL$624 -> 634619678 | H22: ='[1]State Dist'!$CL$631 -> 973632249 | J22: ='[1]State Dist'!$CL$638 -> 284986624
B23: =B22/B26 -> 0.99147901 | D23: n/a | F23: =F22/F26 -> 0.94769159 | H23: =H22/H26 -> 0.96019665 | J23: =J22/J26 -> 0.94061339
A24: Charter | B24: ='[1]State Chart'!$CL$57 -> 1.9581613e+08 | D24: n/a | F24: ='[1]State Chart'!$CL$68 -> 35028218 | H24: ='[1]State Chart'!$CL$82 -> 40360300 | J24: ='[1]State Chart'!$CL$89 -> 17992930
B25: =B24/B26 -> 0.008520995 | D25: n/a | F25: =F24/F26 -> 0.052308412 | H25: =H24/H26 -> 0.03980335 | J25: =J24/J26 -> 0.059386615
A26: Total | B26: =B22+B24 -> 2.298043e+10 | D26: n/a | F26: =F22+F24 -> 669647896 | H26: =H22+H24 -> 1013992549 | J26: =J22+J24 -> 302979554
A27: Percentage of Revenue by Source | B27: District | C27: Charter | D27: District | E27: Charter | F27: District | G27: Charter | H27: District | I27: Charter | J27: District | K27: Charter | M27: Figure 4
A28: Federal | B28: =B9/$B$14 -> 0.032116884 | C28: =C9/$C$14 -> 0.091690643 | D28: 0.048545647 | E28: 0.091690643 | F28: =F9/$F$14 -> 0.059876588 | G28: =G9/$G$14 -> 0.09585255 | H28: =H9/$H$14 -> 0.068906479 | I28: =I9/$I$14 -> 0.1042997 | J28: =J9/$J$14 -> 0.052910982 | K28: =K9/$K$14 -> 0.097960699 | N28: Federal | O28: State | P28: Local | Q28: Other | R28: Indeterminate
A29: State | B29: =B10/$B$14 -> 0.38007261 | C29: =C10/$C$14 -> 0.71627998 | D29: 0.59978827 | E29: 0.71627998 | F29: =F10/$F$14 -> 0.79027749 | G29: =G10/$G$14 -> 0.72228559 | H29: =H10/$H$14 -> 0.73953748 | I29: =I10/$I$14 -> 0.78051258 | J29: =J10/$J$14 -> 0.90182377 | K29: =K10/$K$14 -> 0.75036336 | M29: Statewide District | N29: 549.52683 | O29: 6503.1246 | P29: 9080.4845 | Q29: 541.00187 | R29: 436.07851
A30: Local | B30: =B11/$B$14 -> 0.53070542 | C30: =C11/$C$14 -> 0.18606106 | D30: 0.30039825 | E30: 0.18606106 | F30: =F11/$F$14 -> 0.14360654 | G30: =G11/$G$14 -> 0.17526578 | H30: =H11/$H$14 -> 0.095557331 | I30: =I11/$I$14 -> 0.1141163 | J30: =J11/$J$14 -> 0.04044374 | K30: =K11/$K$14 -> 0.15167594 | M30: Statewide Charter | N30: 1140.7799 | O30: 8911.6816 | P30: 2314.9006 | Q30: 63.305208 | R30: 10.950263
A31: Other | B31: =B12/$B$14 -> 0.031618646 | C31: =C12/$C$14 -> 0.0050881814 | D31: 0.039370873 | E31: 0.0050881814 | F31: =F12/$F$14 -> 0.0062393748 | G31: =G12/$G$14 -> 0.0065960821 | H31: =H12/$H$14 -> 0.095451883 | I31: =I12/$I$14 -> 0.0010714241 | J31: =J12/$J$14 -> 0.004821507 | K31: =K12/$K$14 -> 0 | M31: Statewide Weighted | N31: 963 | O31: 11898 | P31: 5959 | Q31: 781 | R31: 236
A32: Change in district school funding if subjected to charter funding structure | M32: Jersey City District | N32: 1314.3847 | O32: 17347.826 | P32: 3152.3881 | Q32: 136.96403 | R32: 0
B33: ($5.9 billion) | F33: ($360 million) | H33: ($614 million) | J33: ($168 million) | M33: Jersey City Charter | N33: 1139.3091 | O33: 8585.1296 | P33: 2083.2195 | Q33: 78.401425 | R33: 0
M34: Newark District | N34: 1625.7832 | O34: 17448.688 | P34: 2254.5849 | Q34: 2252.0969 | R34: 12.901808
M35: Newark Charter | N35: 1217.9403 | O35: 9114.2904 | P35: 1332.5719 | Q35: 12.511356 | R35: 0
M36: Trenton District | N36: 1251.6225 | O36: 21332.867 | P36: 956.70679 | Q36: 114.05395 | R36: 0
M37: Trenton Charter | N37: 1239.0861 | O37: 9491.2024 | P37: 1918.5199 | Q37: 0 | R37: 0

Sheet Figure 3 Policies
A1: State Charter School Policies
A2: Figure 3
A3: State Policies | B3: Yes | C3: No | D3: Partial
A4: Charter schools received their funding directly from the state | D4: X₁
A5: Charter schools are eligible for local funding | B5: X
A6: Cap on funding a charter school can receive | C6: X
A7: District public school receive differential funding (e.g. more funding for 9-12 vs. K-8 schools) | B7: X
A8: Charter schools receive differential funding | B8: X
A9: State allows districts to withhold funding from charter schools for providing adminstrative services | B9: X₂
A10: State "holds harmless" district funding for charter enrollment | C10: X
A11: School is considered LEA if authorized by non-district organization | B11: X
A12: School is considered LEA if authorized by district | C12: X
A13: Cap on number of charter schools | C13: X
A14: Cap on number of charters schools authorized per year | C14: X
A15: Cap on number of students attending charter schools | C15: X
A16: Charter schools have an open enrollment policy | B16: X
A19: 1. State funding generally flows from the school district to the charter school for any revenue related to
A20: core funding. However, charters do receive some revenue directly from the state, such as the Abbott
A21: Kindergarten funding provided to charters within Abbott districts that run kindergarten programs.
A22: 2. Districts must provide charters 90 percent of the state mandated per pupil minimum.
A24: Note for chapter: the state passed funding reform legislation in 2008 to provide more equitable distribution of funds to charter schools - the School Funding Reform Act of 2008

Sheet Figure 5 Characteristics
A1: Figure 5: School Characteristics
C2: Statewide District | D2: Statewide Charter
A3: Percentage of students eligible for free or reduced price lunch | C3: 0.269 | D3: 0.653
A4: Percentage of schools eligible for Title 1 | C4: 0.507 | D4: 0.906
A5: Percent of students by school type
B6: Primary (K-5) | C6: 0.477 | D6: 0.634
B7: Middle (6-8) | C7: 0.204 | D7: 0.113
B8: High (9-12) | C8: 0.303 | D8: 0.112
B9: Other (K-12,K-8, etc.) | C9: 0.016 | D9: 0.141

Sheet Figure 6 Findings
A1: Figure 6: State Scorecard
B2: Findings | C2: New Jersey | E2: Use the following options only
A3: Federal Funding | B3: Charters have access to federal funds according to state statutes (Yes = black, No = white)* | C3: Y | E3: Y
B4: Percentage of federal revenue equals percentage of total enrollment for charter schools (<, >, or =) | C4: > | E4: P
A5: State Funding | B5: Charters have access to state funds according to state statutes (Yes = black, No = white) | C5: N | E5: N
B6: Percentage of state revenue equals percentage of total enrollment for charter schools (<, >, or =) | C6: >
A7: Local Funding | B7: Charters have access to local funds according to state statutes (Yes = black, No = white) | C7: Y
B8: Percentage of local revenue equals percentage of total enrollment for charter schools (<, >, or =) | C8: >
A9: Facilities Funding | B9: Charters have access to facilities funds according to state statutes (Yes = black, No = white) | C9: N
B10: Percentage of facilities revenue equals percentage of total enrollment for charter schools (<, >, or =) | C10: N
A11: Data Availability | B11: State provides detailed, public data on federal, state, local and other revenues for district schools (Yes = black, Partial = grey, No = white) | C11: Y
B12: State provides detailed, public data on federal, state, local and other revenues for charter schools (Yes = black, Partial = grey, No = white) | C12: Y
A13: Funding Formula | B13: Charters are treated as LEAs for funding purposes (Yes = black, Partial = grey, No = white) | C13: Y
B14: State funds student (black) or the LEA (grey) | C14: S | E14: S | F14: L | H14: Use these options for the query to the left only (B18)
B15: State funding formula is fair and equitable (Yes = black, No = white | C15: N
A17: * For this finding, No one could indicate that the statue is silent or that it denies access.

Sheet enr send dist
A1: Table 6 | B1: Students Originating from Districts that Receive a Higher Percentage of State Funding in their Aid Formula
A2: Formula for Distribution of FY07 New Jersey Charter State and Local Revenue Sending District
A3: Sending District by Charter School | B3: Charter Location | C3: BEDS | D3: # Pupils | E3: Sending District Funding Formula | F3: Total Sending District Local & State Revenue | G3: % state | H3: State Revenue | I3: % Local Revenue | J3: Local Revenue | K3: Sending District Total State & Local | L3: State % Total State & Local | M3: Local % Total State & Local | N3: % of pupils | O3: Charter Self Reported Local Revenues | P3: Local Portion Local Revenues | Q3: State Portion Local Revenues
A4: Academy Charter High
A5: Asbury Park City | D5: 162.7 | F5: =H5+J5 -> 33272858 | G5: =H5/F5 -> 0.825037 | H5: ='rev send dist only'!O359 -> 27451339 | I5: =J5/F5 -> 0.174963 | J5: ='rev send dist only'!J359 -> 5821519 | K5: =SUM(H5+J5) -> 33272858 | L5: =H5/K5 -> 0.825037 | M5: =J5/K5 -> 0.174963 | N5: =D5/$D$11 -> 0.83265097 | O5: 2330133 | P5: =O5*N5*M5 -> 339461.02 | Q5: =O5*N5*L5 -> 1600726.5
A6: Bradley Beach Boro | D6: 6 | F6: =H6+J6 -> 5083808 | G6: =H6/F6 -> 0 | H6: ='rev send dist only'!O364 -> 0 | I6: =J6/F6 -> 1 | J6: ='rev send dist only'!J364 -> 5083808 | K6: =SUM(H6+J6) -> 5083808 | L6: =H6/K6 -> 0 | M6: =J6/K6 -> 1 | N6: =D6/$D$11 -> 0.030706244 | O6: 2330133 | P6: =O6*N6*M6 -> 71549.632 | Q6: =O6*N6*L6 -> 0
A7: Neptune Twp | D7: 23.7 | F7: =H7+J7 -> 38370256 | G7: =H7/F7 -> 0.22188721 | H7: ='rev send dist only'!O394 -> 8513869 | I7: =J7/F7 -> 0.77811279 | J7: ='rev send dist only'!J394 -> 29856387 | K7: =SUM(H7+J7) -> 38370256 | L7: =H7/K7 -> 0.22188721 | M7: =J7/K7 -> 0.77811279 | N7: =D7/$D$11 -> 0.12128966 | O7: 2330133 | P7: =O7*N7*M7 -> 219911.05 | Q7: =O7*N7*L7 -> 62709.995
A8: Ocean Twp | D8: 1 | F8: =H8+J8 -> 53077484 | G8: =H8/F8 -> 0.093194489 | H8: ='rev send dist only'!O395 -> 4946529 | I8: =J8/F8 -> 0.90680551 | J8: ='rev send dist only'!J395 -> 48130955 | K8: =SUM(H8+J8) -> 53077484 | L8: =H8/K8 -> 0.093194489 | M8: =J8/K8 -> 0.90680551 | N8: =D8/$D$11 -> 0.0051177073 | O8: 2330133 | P8: =O8*N8*M8 -> 10813.6 | Q8: =O8*N8*L8 -> 1111.3386
A9: Lake Como | D9: 1 | F9: =H9+J9 -> 2785974 | G9: =H9/F9 -> 0.11371714 | H9: ='rev send dist only'!O405 -> 316813 | I9: =J9/F9 -> 0.88628286 | J9: ='rev send dist only'!J405 -> 2469161 | K9: =SUM(H9+J9) -> 2785974 | L9: =H9/K9 -> 0.11371714 | M9: =J9/K9 -> 0.88628286 | N9: =D9/$D$11 -> 0.0051177073 | O9: 2330133 | P9: =O9*N9*M9 -> 10568.869 | Q9: =O9*N9*L9 -> 1356.0699
A10: Wall Twp | D10: 1 | F10: =H10+J10 -> 49984614 | G10: =H10/F10 -> 0.013914002 | H10: ='rev send dist only'!O411 -> 695486 | I10: =J10/F10 -> 0.986086 | J10: ='rev send dist only'!J411 -> 49289128 | K10: =SUM(H10+J10) -> 49984614 | L10: =H10/K10 -> 0.013914002 | M10: =J10/K10 -> 0.986086 | N10: =D10/$D$11 -> 0.0051177073 | O10: 2330133 | P10: =O10*N10*M10 -> 11759.015 | Q10: =O10*N10*L10 -> 165.92361
A11: Benchmark Charter | D11: =SUM(D5:D10) -> 195.4 | P11: =SUM(P5:P10) -> 664063.19 | Q11: =SUM(Q5:Q10) -> 1666069.8
A12: Absecon City | D12: 0.8 | F12: =H12+J12 -> 8588416 | G12: =H12/F12 -> 0.040100177 | H12: ='rev send dist only'!O4 -> 344397 | I12: =J12/F12 -> 0.95989982 | J12: ='rev send dist only'!J4 -> 8244019 | K12: =SUM(H12+J12) -> 8588416 | L12: =H12/K12 -> 0.040100177 | M12: =J12/K12 -> 0.95989982 | N12: =D12/$D$26 -> 0.049382716 | P12: =O12*N12*M12 -> 0 | Q12: =O12*N12*L12 -> 0
A13: Atlantic City | D13: 0.8 | F13: =H13+J13 -> 95516913 | G13: =H13/F13 -> 0 | H13: ='rev send dist only'!O5 -> 0 | I13: =J13/F13 -> 1 | J13: ='rev send dist only'!J5 -> 95516913 | K13: =SUM(H13+J13) -> 95516913 | L13: =H13/K13 -> 0 | M13: =J13/K13 -> 1 | N13: =D13/$D$26 -> 0.049382716 | P13: =O13*N13*M13 -> 0 | Q13: =O13*N13*L13 -> 0
A14: Buena Regional | D14: 0.4 | F14: =H14+J14 -> 20836651 | G14: =H14/F14 -> 0.45071264 | H14: ='rev send dist only'!O9 -> 9391342 | I14: =J14/F14 -> 0.54928736 | J14: ='rev send dist only'!J9 -> 11445309 | K14: =SUM(H14+J14) -> 20836651 | L14: =H14/K14 -> 0.45071264 | M14: =J14/K14 -> 0.54928736 | N14: =D14/$D$26 -> 0.024691358 | P14: =O14*N14*M14 -> 0 | Q14: =O14*N14*L14 -> 0
A15: Corbin City | D15: 0.2 | F15: =H15+J15 -> 1186799 | G15: =H15/F15 -> 0.35255422 | H15: ='rev send dist only'!O10 -> 418411 | I15: =J15/F15 -> 0.64744578 | J15: ='rev send dist only'!J10 -> 768388 | K15: =SUM(H15+J15) -> 1186799 | L15: =H15/K15 -> 0.35255422 | M15: =J15/K15 -> 0.64744578 | N15: =D15/$D$26 -> 0.012345679 | P15: =O15*N15*M15 -> 0 | Q15: =O15*N15*L15 -> 0
A16: Egg Harbor Twp | D16: 0.6 | F16: =H16+J16 -> 72401641 | G16: =H16/F16 -> 0.28095243 | H16: ='rev send dist only'!O12 -> 20341417 | I16: =J16/F16 -> 0.71904757 | J16: ='rev send dist only'!J12 -> 52060224 | K16: =SUM(H16+J16) -> 72401641 | L16: =H16/K16 -> 0.28095243 | M16: =J16/K16 -> 0.71904757 | N16: =D16/$D$26 -> 0.037037037 | P16: =O16*N16*M16 -> 0 | Q16: =O16*N16*L16 -> 0
A17: Estell Manor City | D17: 0.8 | F17: =H17+J17 -> 3443757 | G17: =H17/F17 -> 0.43170816 | H17: ='rev send dist only'!O13 -> 1486698 | I17: =J17/F17 -> 0.56829184 | J17: ='rev send dist only'!J13 -> 1957059 | K17: =SUM(H17+J17) -> 3443757 | L17: =H17/K17 -> 0.43170816 | M17: =J17/K17 -> 0.56829184 | N17: =D17/$D$26 -> 0.049382716 | P17: =O17*N17*M17 -> 0 | Q17: =O17*N17*L17 -> 0
A18: Greater Egg Harbor Reg | D18: 1.7 | F18: =H18+J18 -> 44291276 | G18: =H18/F18 -> 0.40463217 | H18: ='rev send dist only'!O16 -> 17921675 | I18: =J18/F18 -> 0.59536783 | J18: ='rev send dist only'!J16 -> 26369601 | K18: =SUM(H18+J18) -> 44291276 | L18: =H18/K18 -> 0.40463217 | M18: =J18/K18 -> 0.59536783 | N18: =D18/$D$26 -> 0.10493827 | P18: =O18*N18*M18 -> 0 | Q18: =O18*N18*L18 -> 0
A19: Pleasantville City | D19: 7.5 | F19: =H19+J19 -> 34151238 | G19: =H19/F19 -> 0.80709888 | H19: ='rev send dist only'!O25 -> 27563426 | I19: =J19/F19 -> 0.19290112 | J19: ='rev send dist only'!J25 -> 6587812 | K19: =SUM(H19+J19) -> 34151238 | L19: =H19/K19 -> 0.80709888 | M19: =J19/K19 -> 0.19290112 | N19: =D19/$D$26 -> 0.46296296 | P19: =O19*N19*M19 -> 0 | Q19: =O19*N19*L19 -> 0
A20: Ventnor City | D20: 0.2 | F20: =H20+J20 -> 15801226 | G20: =H20/F20 -> 0.0063286229 | H20: ='rev send dist only'!O28 -> 100000 | I20: =J20/F20 -> 0.99367138 | J20: ='rev send dist only'!J28 -> 15701226 | K20: =SUM(H20+J20) -> 15801226 | L20: =H20/K20 -> 0.0063286229 | M20: =J20/K20 -> 0.99367138 | N20: =D20/$D$26 -> 0.012345679 | P20: =O20*N20*M20 -> 0 | Q20: =O20*N20*L20 -> 0
A21: Weymouth Twp | D21: 0.6 | F21: =H21+J21 -> 3202984 | G21: =H21/F21 -> 0.49066277 | H21: ='rev send dist only'!O29 -> 1571585 | I21: =J21/F21 -> 0.50933723 | J21: ='rev send dist only'!J29 -> 1631399 | K21: =SUM(H21+J21) -> 3202984 | L21: =H21/K21 -> 0.49066277 | M21: =J21/K21 -> 0.50933723 | N21: =D21/$D$26 -> 0.037037037 | P21: =O21*N21*M21 -> 0 | Q21: =O21*N21*L21 -> 0
A22: Dennis Twp | D22: 0.8 | F22: =H22+J22 -> 11557417 | G22: =H22/F22 -> 0.38452909 | H22: ='rev send dist only'!O195 -> 4444163 | I22: =J22/F22 -> 0.61547091 | J22: ='rev send dist only'!J195 -> 7113254 | K22: =SUM(H22+J22) -> 11557417 | L22: =H22/K22 -> 0.38452909 | M22: =J22/K22 -> 0.61547091 | N22: =D22/$D$26 -> 0.049382716 | P22: =O22*N22*M22 -> 0 | Q22: =O22*N22*L22 -> 0
A23: Upper Twp | D23: 1.2 | F23: =H23+J23 -> 26859440 | G23: =H23/F23 -> 0.25367204 | H23: ='rev send dist only'!O203 -> 6813489 | I23: =J23/F23 -> 0.74632796 | J23: ='rev send dist only'!J203 -> 20045951 | K23: =SUM(H23+J23) -> 26859440 | L23: =H23/K23 -> 0.25367204 | M23: =J23/K23 -> 0.74632796 | N23: =D23/$D$26 -> 0.074074074 | P23: =O23*N23*M23 -> 0 | Q23: =O23*N23*L23 -> 0
A24: Woodbine Boro | D24: 0.4 | F24: =H24+J24 -> 3007432 | G24: =H24/F24 -> 0.65751179 | H24: ='rev send dist only'!O208 -> 1977422 | I24: =J24/F24 -> 0.34248821 | J24: ='rev send dist only'!J208 -> 1030010 | K24: =SUM(H24+J24) -> 3007432 | L24: =H24/K24 -> 0.65751179 | M24: =J24/K24 -> 0.34248821 | N24: =D24/$D$26 -> 0.024691358 | P24: =O24*N24*M24 -> 0 | Q24: =O24*N24*L24 -> 0
A25: Commercial Twp | D25: 0.2 | F25: =H25+J25 -> 7519706 | G25: =H25/F25 -> 0.75021484 | H25: ='rev send dist only'!O210 -> 5641395 | I25: =J25/F25 -> 0.24978516 | J25: ='rev send dist only'!J210 -> 1878311 | K25: =SUM(H25+J25) -> 7519706 | L25: =H25/K25 -> 0.75021484 | M25: =J25/K25 -> 0.24978516 | N25: =D25/$D$26 -> 0.012345679 | P25: =O25*N25*M25 -> 0 | Q25: =O25*N25*L25 -> 0
A26: Central Jersey Prep | D26: =SUM(D12:D25) -> 16.2 | P26: =SUM(P12:P13) -> 0 | Q26: =SUM(Q12:Q13) -> 0
A27: Hamilton Twp | B27: Albany | C27: 010100 | D27: 1 | F27: =H27+J27 -> 125290913 | G27: =H27/F27 -> 0.25425071 | H27: ='rev send dist only'!O323 -> 31855304 | I27: =J27/F27 -> 0.74574929 | J27: ='rev send dist only'!J323 -> 93435609 | K27: =SUM(H27+J27) -> 125290913 | L27: =H27/K27 -> 0.25425071 | M27: =J27/K27 -> 0.74574929 | N27: =D27/$D$38 -> 0.006097561 | O27: 954474 | P27: =O27*N27*M27 -> 4340.2336 | Q27: =O27*N27*L27 -> 1479.7298
A28: Highland Park Boro | D28: 1 | F28: =H28+J28 -> 18671955 | G28: =H28/F28 -> 0.047495402 | H28: ='rev send dist only'!O338 -> 886832 | I28: =J28/F28 -> 0.9525046 | J28: ='rev send dist only'!J338 -> 17785123 | K28: =SUM(H28+J28) -> 18671955 | L28: =H28/K28 -> 0.047495402 | M28: =J28/K28 -> 0.9525046 | N28: =D28/$D$38 -> 0.006097561 | O28: 954474 | P28: =O28*N28*M28 -> 5543.5419 | Q28: =O28*N28*L28 -> 276.4215
A29: New Brunswick City | D29: 71.1 | F29: =H29+J29 -> 57383607 | G29: =H29/F29 -> 0.52198012 | H29: ='rev send dist only'!O346 -> 29953102 | I29: =J29/F29 -> 0.47801988 | J29: ='rev send dist only'!J346 -> 27430505 | K29: =SUM(H29+J29) -> 57383607 | L29: =H29/K29 -> 0.52198012 | M29: =J29/K29 -> 0.47801988 | N29: =D29/$D$38 -> 0.43353659 | O29: 954474 | P29: =O29*N29*M29 -> 197804.34 | Q29: =O29*N29*L29 -> 215995.06
A30: North Brunswick Twp | D30: 13.7 | F30: =H30+J30 -> 63170430 | G30: =H30/F30 -> 0.033034064 | H30: ='rev send dist only'!O347 -> 2086776 | I30: =J30/F30 -> 0.96696594 | J30: ='rev send dist only'!J347 -> 61083654 | K30: =SUM(H30+J30) -> 63170430 | L30: =H30/K30 -> 0.033034064 | M30: =J30/K30 -> 0.96696594 | N30: =D30/$D$38 -> 0.083536585 | O30: 954474 | P30: =O30*N30*M30 -> 77099.577 | Q30: =O30*N30*L30 -> 2633.9215
A31: Piscataway Twp | D31: 1 | F31: =H31+J31 -> 74430231 | G31: =H31/F31 -> 0.050648976 | H31: ='rev send dist only'!O350 -> 3769815 | I31: =J31/F31 -> 0.94935102 | J31: ='rev send dist only'!J350 -> 70660416 | K31: =SUM(H31+J31) -> 74430231 | L31: =H31/K31 -> 0.050648976 | M31: =J31/K31 -> 0.94935102 | N31: =D31/$D$38 -> 0.006097561 | O31: 954474 | P31: =O31*N31*M31 -> 5525.1882 | Q31: =O31*N31*L31 -> 294.77519
A32: South Brunswick Twp | D32: 1 | F32: =H32+J32 -> 101877504 | G32: =H32/F32 -> 0.10543046 | H32: ='rev send dist only'!O353 -> 10740992 | I32: =J32/F32 -> 0.89456954 | J32: ='rev send dist only'!J353 -> 91136512 | K32: =SUM(H32+J32) -> 101877504 | L32: =H32/K32 -> 0.10543046 | M32: =J32/K32 -> 0.89456954 | N32: =D32/$D$38 -> 0.006097561 | O32: 954474 | P32: =O32*N32*M32 -> 5206.362 | Q32: =O32*N32*L32 -> 613.60141
A33: South River Boro | D33: 1 | F33: =H33+J33 -> 17187343 | G33: =H33/F33 -> 0.31843107 | H33: ='rev send dist only'!O355 -> 5472984 | I33: =J33/F33 -> 0.68156893 | J33: ='rev send dist only'!J355 -> 11714359 | K33: =SUM(H33+J33) -> 17187343 | L33: =H33/K33 -> 0.31843107 | M33: =J33/K33 -> 0.68156893 | N33: =D33/$D$38 -> 0.006097561 | O33: 954474 | P33: =O33*N33*M33 -> 3966.7062 | Q33: =O33*N33*L33 -> 1853.2572
A34: Bound Brook Boro | D34: 2.5 | F34: =H34+J34 -> 14987214 | G34: =H34/F34 -> 0.15880697 | H34: ='rev send dist only'!O522 -> 2380074 | I34: =J34/F34 -> 0.84119303 | J34: ='rev send dist only'!J522 -> 12607140 | K34: =SUM(H34+J34) -> 14987214 | L34: =H34/K34 -> 0.15880697 | M34: =J34/K34 -> 0.84119303 | N34: =D34/$D$38 -> 0.015243902 | O34: 954474 | P34: =O34*N34*M34 -> 12239.282 | Q34: =O34*N34*L34 -> 2310.6268
A35: Franklin Twp | D35: 62.3 | F35: =H35+J35 -> 97929722 | G35: =H35/F35 -> 0 | H35: ='rev send dist only'!O525 -> 0 | I35: =J35/F35 -> 1 | J35: ='rev send dist only'!J525 -> 97929722 | K35: =SUM(H35+J35) -> 97929722 | L35: =H35/K35 -> 0 | M35: =J35/K35 -> 1 | N35: =D35/$D$38 -> 0.37987805 | O35: 954474 | P35: =O35*N35*M35 -> 362583.72 | Q35: =O35*N35*L35 -> 0
A36: Somerville Boro | D36: 1 | F36: =H36+J36 -> 19801225 | G36: =H36/F36 -> 0.096690836 | H36: ='rev send dist only'!O536 -> 1914597 | I36: =J36/F36 -> 0.90330916 | J36: ='rev send dist only'!J536 -> 17886628 | K36: =SUM(H36+J36) -> 19801225 | L36: =H36/K36 -> 0.096690836 | M36: =J36/K36 -> 0.90330916 | N36: =D36/$D$38 -> 0.006097561 | O36: 954474 | P36: =O36*N36*M36 -> 5257.2263 | Q36: =O36*N36*L36 -> 562.73713
A37: Plainfield City | D37: 8.4 | F37: =H37+J37 -> 62723780 | G37: =H37/F37 -> 0.71806696 | H37: ='rev send dist only'!O579 -> 45039874 | I37: =J37/F37 -> 0.28193304 | J37: ='rev send dist only'!J579 -> 17683906 | K37: =SUM(H37+J37) -> 62723780 | L37: =H37/K37 -> 0.71806696 | M37: =J37/K37 -> 0.28193304 | N37: =D37/$D$38 -> 0.051219512 | O37: 954474 | P37: =O37*N37*M37 -> 13783.056 | Q37: =O37*N37*L37 -> 35104.637
A38: Camden Academy Charter | D38: =SUM(D27:D37) -> 164 | P38: =SUM(P27:P37) -> 693349.23 | Q38: =SUM(Q27:Q37) -> 261124.77
A39: Camden City | B39: Albany | C39: 010100 | D39: 399 | F39: =H39+J39 -> 142607869 | G39: =H39/F39 -> 0.93287844 | H39: ='rev send dist only'!O158 -> 133035807 | I39: =J39/F39 -> 0.067121556 | J39: ='rev send dist only'!J158 -> 9572062 | K39: =SUM(H39+J39) -> 142607869 | L39: =H39/K39 -> 0.93287844 | M39: =J39/K39 -> 0.067121556 | N39: =D39/$D$41 -> 0.99007444 | O39: 615928 | P39: =O39*N39*M39 -> 40931.703 | Q39: =O39*N39*L39 -> 568882.87
A40: Pennsauken Twp | D40: 4 | F40: =H40+J40 -> 55109391 | G40: =H40/F40 -> 0.37803192 | H40: ='rev send dist only'!O180 -> 20833109 | I40: =J40/F40 -> 0.62196808 | J40: ='rev send dist only'!J180 -> 34276282 | K40: =SUM(H40+J40) -> 55109391 | L40: =H40/K40 -> 0.37803192 | M40: =J40/K40 -> 0.62196808 | N40: =D40/$D$41 -> 0.0099255583 | O40: 615928 | P40: =O40*N40*M40 -> 3802.3579 | Q40: =O40*N40*L40 -> 2311.0714
A41: Camden's Promise | D41: =SUM(D39:D40) -> 403 | P41: =SUM(P39:P40) -> 44734.06 | Q41: =SUM(Q39:Q40) -> 571193.94
A42: Camden City | D42: 378.5 | F42: =H42+J42 -> 142607869 | G42: =H42/F42 -> 0.93287844 | H42: =$H$39 -> 133035807 | I42: =J42/F42 -> 0.067121556 | J42: =$J$39 -> 9572062 | K42: =SUM(H42+J42) -> 142607869 | L42: =H42/K42 -> 0.93287844 | M42: =J42/K42 -> 0.067121556 | N42: =D42/$D$45 -> 0.97501288 | O42: 1705932 | P42: =O42*N42*M42 -> 111643.66 | Q42: =O42*N42*L42 -> 1551662
A43: Pennsauken Twp | D43: 9 | F43: =H43+J43 -> 55109391 | G43: =H43/F43 -> 0.37803192 | H43: =$H$40 -> 20833109 | I43: =J43/F43 -> 0.62196808 | J43: =$J$40 -> 34276282 | K43: =SUM(H43+J43) -> 55109391 | L43: =H43/K43 -> 0.37803192 | M43: =J43/K43 -> 0.62196808 | N43: =D43/$D$45 -> 0.023183926 | O43: 1705932 | P43: =O43*N43*M43 -> 24598.962 | Q43: =O43*N43*L43 -> 14951.238
A44: Winslow Twp | D44: 0.7 | F44: =H44+J44 -> 62017064 | G44: =H44/F44 -> 0.41221916 | H44: ='rev send dist only'!O188 -> 25564622 | I44: =J44/F44 -> 0.58778084 | J44: ='rev send dist only'!J188 -> 36452442 | K44: =SUM(H44+J44) -> 62017064 | L44: =H44/K44 -> 0.41221916 | M44: =J44/K44 -> 0.58778084 | N44: =D44/$D$45 -> 0.0018031942 | O44: 1705932 | P44: =O44*N44*M44 -> 1808.0884 | Q44: =O44*N44*L44 -> 1268.0384
A45: Central Jersey Arts Charter | D45: =SUM(D42:D44) -> 388.2 | P45: =SUM(P42:P44) -> 138050.71 | Q45: =SUM(Q42:Q44) -> 1567881.3
A46: Newark City | B46: Albany | C46: 010100 | D46: 1 | F46: =H46+J46 -> 381732222 | G46: =H46/F46 -> 0.75741087 | H46: ='rev send dist only'!O239 -> 289128135 | I46: =J46/F46 -> 0.24258913 | J46: ='rev send dist only'!J239 -> 92604087 | K46: =SUM(H46+J46) -> 381732222 | L46: =H46/K46 -> 0.75741087 | M46: =J46/K46 -> 0.24258913 | N46: =D46/$D$56 -> 0.0044843049 | O46: 437739 | P46: =O46*N46*M46 -> 476.19158 | Q46: =O46*N46*L46 -> 1486.7636
A47: Edison Twp | B47: Albany | C47: 010615 | D47: 0.1 | F47: =H47+J47 -> 159130899 | G47: =H47/F47 -> 0.0011607802 | H47: ='rev send dist only'!O336 -> 184716 | I47: =J47/F47 -> 0.99883922 | J47: ='rev send dist only'!J336 -> 158946183 | K47: =SUM(H47+J47) -> 159130899 | L47: =H47/K47 -> 0.0011607802 | M47: =J47/K47 -> 0.99883922 | N47: =D47/$D$56 -> 0.00044843049 | O47: 437739 | P47: =O47*N47*M47 -> 196.06766 | Q47: =O47*N47*L47 -> 0.22785595
A48: Piscataway Twp | B48: Albany | C48: 011200 | D48: 1 | F48: =H48+J48 -> 74430231 | G48: =H48/F48 -> 0.050648976 | H48: =$H$31 -> 3769815 | I48: =J48/F48 -> 0.94935102 | J48: =$J$31 -> 70660416 | K48: =SUM(H48+J48) -> 74430231 | L48: =H48/K48 -> 0.050648976 | M48: =J48/K48 -> 0.94935102 | N48: =D48/$D$56 -> 0.0044843049 | O48: 437739 | P48: =O48*N48*M48 -> 1863.5335 | Q48: =O48*N48*L48 -> 99.421669
A49: South Plainfield Boro | B49: Albany | C49: 491700 | D49: 1 | F49: =H49+J49 -> 43178619 | G49: =H49/F49 -> 0.10620312 | H49: ='rev send dist only'!O354 -> 4585704 | I49: =J49/F49 -> 0.89379688 | J49: ='rev send dist only'!J354 -> 38592915 | K49: =SUM(H49+J49) -> 43178619 | L49: =H49/K49 -> 0.10620312 | M49: =J49/K49 -> 0.89379688 | N49: =D49/$D$56 -> 0.0044843049 | O49: 437739 | P49: =O49*N49*M49 -> 1754.4832 | Q49: =O49*N49*L49 -> 208.47196
A50: Franklin Twp | D50: 1.9 | F50: =H50+J50 -> 97929722 | G50: =H50/F50 -> 0 | H50: =H35 -> 0 | I50: =J50/F50 -> 1 | J50: =J35 -> 97929722 | K50: =SUM(H50+J50) -> 97929722 | L50: =H50/K50 -> 0 | M50: =J50/K50 -> 1 | N50: =D50/$D$56 -> 0.0085201794 | O50: 437739 | P50: =O50*N50*M50 -> 3729.6148 | Q50: =O50*N50*L50 -> 0
A51: North Plainfield Boro | D51: 2 | F51: =H51+J51 -> 37628562 | G51: =H51/F51 -> 0.31056635 | H51: ='rev send dist only'!O531 -> 11686165 | I51: =J51/F51 -> 0.68943365 | J51: ='rev send dist only'!J531 -> 25942397 | K51: =SUM(H51+J51) -> 37628562 | L51: =H51/K51 -> 0.31056635 | M51: =J51/K51 -> 0.68943365 | N51: =D51/$D$56 -> 0.0089686099 | O51: 437739 | P51: =O51*N51*M51 -> 2706.6547 | Q51: =O51*N51*L51 -> 1219.2556
A52: Plainfield City | D52: 211 | F52: =H52+J52 -> 62723780 | G52: =H52/F52 -> 0.71806696 | H52: =$H$37 -> 45039874 | I52: =J52/F52 -> 0.28193304 | J52: =$J$37 -> 17683906 | K52: =SUM(H52+J52) -> 62723780 | L52: =H52/K52 -> 0.71806696 | M52: =J52/K52 -> 0.28193304 | N52: =D52/$D$56 -> 0.94618834 | O52: 437739 | P52: =O52*N52*M52 -> 116772.02 | Q52: =O52*N52*L52 -> 297411.51
A53: Roselle Boro | D53: 2 | F53: =H53+J53 -> 33097510 | G53: =H53/F53 -> 0.3301148 | H53: ='rev send dist only'!O581 -> 10925978 | I53: =J53/F53 -> 0.6698852 | J53: ='rev send dist only'!J581 -> 22171532 | K53: =SUM(H53+J53) -> 33097510 | L53: =H53/K53 -> 0.3301148 | M53: =J53/K53 -> 0.6698852 | N53: =D53/$D$56 -> 0.0089686099 | O53: 437739 | P53: =O53*N53*M53 -> 2629.9092 | Q53: =O53*N53*L53 -> 1296.0011
A54: Scotch Plains - Fanwood | B54: Albany | C54: 530600 | D54: 2 | F54: =H54+J54 -> 62641766 | G54: =H54/F54 -> 0 | H54: ='rev send dist only'!O583 -> 0 | I54: =J54/F54 -> 1 | J54: ='rev send dist only'!J583 -> 62641766 | K54: =SUM(H54+J54) -> 62641766 | L54: =H54/K54 -> 0 | M54: =J54/K54 -> 1 | N54: =D54/$D$56 -> 0.0089686099 | O54: 437739 | P54: =O54*N54*M54 -> 3925.9103 | Q54: =O54*N54*L54 -> 0
A55: Union Twp | D55: 1 | F55: =H55+J55 -> 84390302 | G55: =H55/F55 -> 0.16589154 | H55: ='rev send dist only'!O588 -> 13999637 | I55: =J55/F55 -> 0.83410846 | J55: ='rev send dist only'!J588 -> 70390665 | K55: =SUM(H55+J55) -> 84390302 | L55: =H55/K55 -> 0.16589154 | M55: =J55/K55 -> 0.83410846 | N55: =D55/$D$56 -> 0.0044843049 | O55: 437739 | P55: =O55*N55*M55 -> 1637.3175 | Q55: =O55*N55*L55 -> 325.63765
A56: CREATE | D56: =SUM(D46:D55) -> 223 | P56: =SUM(P46:P55) -> 135691.71 | Q56: =SUM(Q46:Q55) -> 302047.29
A57: Jersey City | B57: Albany | C57: 010100 | D57: 399.8 | F57: =H57+J57 -> 259769100 | G57: =H57/F57 -> 0.68623093 | H57: ='rev send dist only'!O283 -> 178261592 | I57: =J57/F57 -> 0.31376907 | J57: ='rev send dist only'!J283 -> 81507508 | K57: =SUM(H57+J57) -> 259769100 | L57: =H57/K57 -> 0.68623093 | M57: =J57/K57 -> 0.31376907 | N57: =D57/$D$58 -> 1 | O57: 1115833 | P57: =O57*N57*M57 -> 350113.88 | Q57: =O57*N57*L57 -> 765719.12
A58: Classical Academy | D58: =SUM(D57) -> 399.8 | P58: =SUM(P57) -> 350113.88 | Q58: =SUM(Q57) -> 765719.12
A59: Garfield City | B59: Albany | C59: 010100 | D59: 1 | F59: =H59+J59 -> 34791931 | G59: =H59/F59 -> 0.39053627 | H59: ='rev send dist only'!O53 -> 13587511 | I59: =J59/F59 -> 0.60946373 | J59: ='rev send dist only'!J53 -> 21204420 | K59: =SUM(H59+J59) -> 34791931 | L59: =H59/K59 -> 0.39053627 | M59: =J59/K59 -> 0.60946373 | N59: =D59/$D$65 -> 0.009765625 | O59: 885543 | P59: =O59*N59*M59 -> 5270.5697 | Q59: =O59*N59*L59 -> 3377.3111
A60: Cedar Grove Twp | D60: 0.7 | F60: =H60+J60 -> 19647375 | G60: =H60/F60 -> 0 | H60: ='rev send dist only'!O228 -> 0 | I60: =J60/F60 -> 1 | J60: ='rev send dist only'!J228 -> 19647375 | K60: =SUM(H60+J60) -> 19647375 | L60: =H60/K60 -> 0 | M60: =J60/K60 -> 1 | N60: =D60/$D$65 -> 0.0068359375 | O60: 885543 | P60: =O60*N60*M60 -> 6053.5166 | Q60: =O60*N60*L60 -> 0
A61: Clifton City | D61: 95.7 | F61: =H61+J61 -> 105627636 | G61: =H61/F61 -> 0.040848732 | H61: ='rev send dist only'!O485 -> 4314755 | I61: =J61/F61 -> 0.95915127 | J61: ='rev send dist only'!J485 -> 101312881 | K61: =SUM(H61+J61) -> 105627636 | L61: =H61/K61 -> 0.040848732 | M61: =J61/K61 -> 0.95915127 | N61: =D61/$D$65 -> 0.93457031 | O61: 885543 | P61: =O61*N61*M61 -> 793795.7 | Q61: =O61*N61*L61 -> 33806.5
A62: Passaic City | D62: 3 | F62: =H62+J62 -> 89777526 | G62: =H62/F62 -> 0.82009587 | H62: ='rev send dist only'!O491 -> 73626178 | I62: =J62/F62 -> 0.17990413 | J62: ='rev send dist only'!J491 -> 16151348 | K62: =SUM(H62+J62) -> 89777526 | L62: =H62/K62 -> 0.82009587 | M62: =J62/K62 -> 0.17990413 | N62: =D62/$D$65 -> 0.029296875 | O62: 885543 | P62: =O62*N62*M62 -> 4667.3685 | Q62: =O62*N62*L62 -> 21276.274
A63: Paterson City | D63: 1 | F63: =H63+J63 -> 212827949 | G63: =H63/F63 -> 0.80920356 | H63: ='rev send dist only'!O496 -> 172221134 | I63: =J63/F63 -> 0.19079644 | J63: ='rev send dist only'!J496 -> 40606815 | K63: =SUM(H63+J63) -> 212827949 | L63: =H63/K63 -> 0.80920356 | M63: =J63/K63 -> 0.19079644 | N63: =D63/$D$65 -> 0.009765625 | O63: 885543 | P63: =O63*N63*M63 -> 1649.9849 | Q63: =O63*N63*L63 -> 6997.896
A64: Wayne Twp | D64: 1 | F64: =H64+J64 -> 107253154 | G64: =H64/F64 -> 0 | H64: ='rev send dist only'!O502 -> 0 | I64: =J64/F64 -> 1 | J64: ='rev send dist only'!J502 -> 107253154 | K64: =SUM(H64+J64) -> 107253154 | L64: =H64/K64 -> 0 | M64: =J64/K64 -> 1 | N64: =D64/$D$65 -> 0.009765625 | O64: 885543 | P64: =O64*N64*M64 -> 8647.8809 | Q64: =O64*N64*L64 -> 0
A65: Environment Community Opportunity Charter | D65: =SUM(D59:D64) -> 102.4 | P65: =SUM(P59:P64) -> 820085.02 | Q65: =SUM(Q59:Q64) -> 65457.982
A66: Camden City | B66: Albany | C66: 010100 | D66: 179.6 | F66: =H66+J66 -> 142607869 | G66: =H66/F66 -> 0.93287844 | H66: =$H$39 -> 133035807 | I66: =J66/F66 -> 0.067121556 | J66: =$J$39 -> 9572062 | K66: =SUM(H66+J66) -> 142607869 | L66: =H66/K66 -> 0.93287844 | M66: =J66/K66 -> 0.067121556 | N66: =D66/$D$71 -> 0.97821351 | O66: 298384 | P66: =O66*N66*M66 -> 19591.658 | Q66: =O66*N66*L66 -> 272291.6
A67: Lindenwold Boro | D67: 1 | F67: =H67+J67 -> 25206777 | G67: =H67/F67 -> 0.45348773 | H67: ='rev send dist only'!O175 -> 11430964 | I67: =J67/F67 -> 0.54651227 | J67: ='rev send dist only'!J175 -> 13775813 | K67: =SUM(H67+J67) -> 25206777 | L67: =H67/K67 -> 0.45348773 | M67: =J67/K67 -> 0.54651227 | N67: =D67/$D$71 -> 0.0054466231 | O67: 298384 | P67: =O67*N67*M67 -> 888.18365 | Q67: =O67*N67*L67 -> 737.00154
A68: Pennsauken Twp | D68: 1 | F68: =H68+J68 -> 55109391 | G68: =H68/F68 -> 0.37803192 | H68: =$H$40 -> 20833109 | I68: =J68/F68 -> 0.62196808 | J68: =$J$40 -> 34276282 | K68: =SUM(H68+J68) -> 55109391 | L68: =H68/K68 -> 0.37803192 | M68: =J68/K68 -> 0.62196808 | N68: =D68/$D$71 -> 0.0054466231 | O68: 298384 | P68: =O68*N68*M68 -> 1010.8133 | Q68: =O68*N68*L68 -> 614.37188
A69: Woodlynne Boro | D69: 1 | F69: =H69+J69 -> 5064432 | G69: =H69/F69 -> 0.6557608 | H69: ='rev send dist only'!O189 -> 3321056 | I69: =J69/F69 -> 0.3442392 | J69: ='rev send dist only'!J189 -> 1743376 | K69: =SUM(H69+J69) -> 5064432 | L69: =H69/K69 -> 0.6557608 | M69: =J69/K69 -> 0.3442392 | N69: =D69/$D$71 -> 0.0054466231 | O69: 298384 | P69: =O69*N69*M69 -> 559.45244 | Q69: =O69*N69*L69 -> 1065.7327
A70: West Deptford Twp | D70: 1 | F70: =H70+J70 -> 30311084 | G70: =H70/F70 -> 0.18210246 | H70: ='rev send dist only'!O273 -> 5519723 | I70: =J70/F70 -> 0.81789754 | J70: ='rev send dist only'!J273 -> 24791361 | K70: =SUM(H70+J70) -> 30311084 | L70: =H70/K70 -> 0.18210246 | M70: =J70/K70 -> 0.81789754 | N70: =D70/$D$71 -> 0.0054466231 | O70: 298384 | P70: =O70*N70*M70 -> 1329.235 | Q70: =O70*N70*L70 -> 295.95022
A71: Liberty Academy Charter | D71: =SUM(D66:D70) -> 183.6 | P71: =SUM(P66:P70) -> 23379.343 | Q71: =SUM(Q66:Q70) -> 275004.66
A72: Newark City | B72: Albany | C72: 010100 | D72: 0.6 | F72: =H72+J72 -> 381732222 | G72: =H72/F72 -> 0.75741087 | H72: =$H$46 -> 289128135 | I72: =J72/F72 -> 0.24258913 | J72: =$J$46 -> 92604087 | K72: =SUM(H72+J72) -> 381732222 | L72: =H72/K72 -> 0.75741087 | M72: =J72/K72 -> 0.24258913 | N72: =D72/$D$76 -> 0.0018039687 | O72: 858172 | P72: =O72*N72*M72 -> 375.55598 | Q72: =O72*N72*L72 -> 1172.5595
A73: Bayonne City | D73: 2.5 | F73: =H73+J73 -> 74696754 | G73: =H73/F73 -> 0.25820892 | H73: ='rev send dist only'!O277 -> 19287368 | I73: =J73/F73 -> 0.74179108 | J73: ='rev send dist only'!J277 -> 55409386 | K73: =SUM(H73+J73) -> 74696754 | L73: =H73/K73 -> 0.25820892 | M73: =J73/K73 -> 0.74179108 | N73: =D73/$D$76 -> 0.0075165364 | O73: 858172 | P73: =O73*N73*M73 -> 4784.9093 | Q73: =O73*N73*L73 -> 1665.5717
A74: Jersey City | D74: 328.5 | F74: =H74+J74 -> 259769100 | G74: =H74/F74 -> 0.68623093 | H74: =$H$57 -> 178261592 | I74: =J74/F74 -> 0.31376907 | J74: =$J$57 -> 81507508 | K74: =SUM(H74+J74) -> 259769100 | L74: =H74/K74 -> 0.68623093 | M74: =J74/K74 -> 0.31376907 | N74: =D74/$D$76 -> 0.98767288 | O74: 858172 | P74: =O74*N74*M74 -> 265948.53 | Q74: =O74*N74*L74 -> 581644.68
A75: Union Twp | D75: 1 | F75: =H75+J75 -> 84390302 | G75: =H75/F75 -> 0.16589154 | H75: ='rev send dist only'!O588 -> 13999637 | I75: =J75/F75 -> 0.83410846 | J75: ='rev send dist only'!J588 -> 70390665 | K75: =SUM(H75+J75) -> 84390302 | L75: =H75/K75 -> 0.16589154 | M75: =J75/K75 -> 0.83410846 | N75: =D75/$D$76 -> 0.0030066146 | O75: 858172 | P75: =O75*N75*M75 -> 2152.1603 | Q75: =O75*N75*L75 -> 428.03209
A76: Freedom Academy Charter | D76: =SUM(D72:D75) -> 332.6 | P76: =SUM(P72:P75) -> 273261.16 | Q76: =SUM(Q72:Q75) -> 584910.84
A77: Mount Laurel Twp | B77: Albany | C77: 010100 | D77: 0.2 | F77: =H77+J77 -> 46608839 | G77: =H77/F77 -> 0 | H77: ='rev send dist only'!O132 -> 0 | I77: =J77/F77 -> 1 | J77: ='rev send dist only'!J132 -> 46608839 | K77: =SUM(H77+J77) -> 46608839 | L77: =H77/K77 -> 0 | M77: =J77/K77 -> 1 | N77: =D77/$D$81 -> 0.00091365921 | O77: 312016 | P77: =O77*N77*M77 -> 285.07629 | Q77: =O77*N77*L77 -> 0
A78: Camden City | D78: 216.3 | F78: =H78+J78 -> 142607869 | G78: =H78/F78 -> 0.93287844 | H78: =$H$39 -> 133035807 | I78: =J78/F78 -> 0.067121556 | J78: =$J$39 -> 9572062 | K78: =SUM(H78+J78) -> 142607869 | L78: =H78/K78 -> 0.93287844 | M78: =J78/K78 -> 0.067121556 | N78: =D78/$D$81 -> 0.98812243 | O78: 312016 | P78: =O78*N78*M78 -> 20694.247 | Q78: =O78*N78*L78 -> 287615.76
A79: Collingswood Boro | D79: 0.4 | F79: =H79+J79 -> 19550231 | G79: =H79/F79 -> 0.37506631 | H79: ='rev send dist only'!O164 -> 7332633 | I79: =J79/F79 -> 0.62493369 | J79: ='rev send dist only'!J164 -> 12217598 | K79: =SUM(H79+J79) -> 19550231 | L79: =H79/K79 -> 0.37506631 | M79: =J79/K79 -> 0.62493369 | N79: =D79/$D$81 -> 0.0018273184 | O79: 312016 | P79: =O79*N79*M79 -> 356.30756 | Q79: =O79*N79*L79 -> 213.84502
A80: Winslow Twp | D80: 2 | F80: =H80+J80 -> 62017064 | G80: =H80/F80 -> 0.41221916 | H80: =$H$44 -> 25564622 | I80: =J80/F80 -> 0.58778084 | J80: =$J$44 -> 36452442 | K80: =SUM(H80+J80) -> 62017064 | L80: =H80/K80 -> 0.41221916 | M80: =J80/K80 -> 0.58778084 | N80: =D80/$D$81 -> 0.0091365921 | O80: 312016 | P80: =O80*N80*M80 -> 1675.6238 | Q80: =O80*N80*L80 -> 1175.1391
A81: Discovery Charter | D81: =SUM(D77:D80) -> 218.9 | P81: =SUM(P77:P80) -> 23011.255 | Q81: =SUM(Q77:Q80) -> 289004.74
A82: Newark City | B82: Albany | C82: 010100 | D82: 75 | F82: =H82+J82 -> 381732222 | G82: =H82/F82 -> 0.75741087 | H82: =$H$46 -> 289128135 | I82: =J82/F82 -> 0.24258913 | J82: =$J$46 -> 92604087 | K82: =SUM(H82+J82) -> 381732222 | L82: =H82/K82 -> 0.75741087 | M82: =J82/K82 -> 0.24258913 | N82: =D82/$D$83 -> 1 | O82: 137802 | P82: =O82*N82*M82 -> 33429.267 | Q82: =O82*N82*L82 -> 104372.73
A83: D. U. E. Season Charter | D83: =SUM(D82) -> 75 | P83: =SUM(P82) -> 33429.267 | Q83: =SUM(Q82) -> 104372.73
A84: Camden City | B84: Albany | C84: 010100 | D84: 317.8 | F84: =H84+J84 -> 142607869 | G84: =H84/F84 -> 0.93287844 | H84: =$H$39 -> 133035807 | I84: =J84/F84 -> 0.067121556 | J84: =$J$39 -> 9572062 | K84: =SUM(H84+J84) -> 142607869 | L84: =H84/K84 -> 0.93287844 | M84: =J84/K84 -> 0.067121556 | N84: =D84/$D$90 -> 0.97844828 | O84: 471665 | P84: =O84*N84*M84 -> 30976.585 | Q84: =O84*N84*L84 -> 430523.22
A85: Cherry Hill Twp | D85: 1 | F85: =H85+J85 -> 140289607 | G85: =H85/F85 -> 0.014410397 | H85: ='rev send dist only'!O161 -> 2021629 | I85: =J85/F85 -> 0.9855896 | J85: ='rev send dist only'!J161 -> 138267978 | K85: =SUM(H85+J85) -> 140289607 | L85: =H85/K85 -> 0.014410397 | M85: =J85/K85 -> 0.9855896 | N85: =D85/$D$90 -> 0.0030788177 | O85: 471665 | P85: =O85*N85*M85 -> 1431.2442 | Q85: =O85*N85*L85 -> 20.926355
A86: Collingswood Boro | D86: 1 | F86: =H86+J86 -> 19550231 | G86: =H86/F86 -> 0.37506631 | H86: =H79 -> 7332633 | I86: =J86/F86 -> 0.62493369 | J86: =J79 -> 12217598 | K86: =SUM(H86+J86) -> 19550231 | L86: =H86/K86 -> 0.37506631 | M86: =J86/K86 -> 0.62493369 | N86: =D86/$D$90 -> 0.0030788177 | O86: 471665 | P86: =O86*N86*M86 -> 907.51031 | Q86: =O86*N86*L86 -> 544.66026
A87: Lindenwold Boro | D87: 1 | F87: =H87+J87 -> 25206777 | G87: =H87/F87 -> 0.45348773 | H87: =H67 -> 11430964 | I87: =J87/F87 -> 0.54651227 | J87: =J67 -> 13775813 | K87: =SUM(H87+J87) -> 25206777 | L87: =H87/K87 -> 0.45348773 | M87: =J87/K87 -> 0.54651227 | N87: =D87/$D$90 -> 0.0030788177 | O87: 471665 | P87: =O87*N87*M87 -> 793.62904 | Q87: =O87*N87*L87 -> 658.54153
A88: Pennsauken Twp | D88: 1 | F88: =H88+J88 -> 55109391 | G88: =H88/F88 -> 0.37803192 | H88: =$H$40 -> 20833109 | I88: =J88/F88 -> 0.62196808 | J88: =$J$40 -> 34276282 | K88: =SUM(H88+J88) -> 55109391 | L88: =H88/K88 -> 0.37803192 | M88: =J88/K88 -> 0.62196808 | N88: =D88/$D$90 -> 0.0030788177 | O88: 471665 | P88: =O88*N88*M88 -> 903.20374 | Q88: =O88*N88*L88 -> 548.96683
A89: Woodlynne Boro | D89: 3 | F89: =H89+J89 -> 5064432 | G89: =H89/F89 -> 0.6557608 | H89: =H69 -> 3321056 | I89: =J89/F89 -> 0.3442392 | J89: =J69 -> 1743376 | K89: =SUM(H89+J89) -> 5064432 | L89: =H89/K89 -> 0.6557608 | M89: =J89/K89 -> 0.3442392 | N89: =D89/$D$90 -> 0.0092364532 | O89: 471665 | P89: =O89*N89*M89 -> 1499.6821 | Q89: =O89*N89*L89 -> 2856.8296
A90: East Orange Community Charter | D90: =SUM(D84:D89) -> 324.8 | P90: =SUM(P84:P89) -> 36511.854 | Q90: =SUM(Q84:Q89) -> 435153.15
A91: Belleville Town | B91: Albany | C91: 010100 | D91: 1 | F91: =H91+J91 -> 43915306 | G91: =H91/F91 -> 0.29037593 | H91: ='rev send dist only'!O225 -> 12751948 | I91: =J91/F91 -> 0.70962407 | J91: ='rev send dist only'!J225 -> 31163358 | K91: =SUM(H91+J91) -> 43915306 | L91: =H91/K91 -> 0.29037593 | M91: =J91/K91 -> 0.70962407 | N91: =D91/$D$102 -> 0.0020512821 | O91: 909109 | P91: =O91*N91*M91 -> 1323.3346 | Q91: =O91*N91*L91 -> 541.50436
A92: Bloomfield Twp | D92: 1.9 | F92: =H92+J92 -> 56381700 | G92: =H92/F92 -> 0.14228755 | H92: ='rev send dist only'!O226 -> 8022414 | I92: =J92/F92 -> 0.85771245 | J92: ='rev send dist only'!J226 -> 48359286 | K92: =SUM(H92+J92) -> 56381700 | L92: =H92/K92 -> 0.14228755 | M92: =J92/K92 -> 0.85771245 | N92: =D92/$D$102 -> 0.0038974359 | O92: 909109 | P92: =O92*N92*M92 -> 3039.0416 | Q92: =O92*N92*L92 -> 504.1524
A93: East Orange | D93: 428.3 | F93: =H93+J93 -> 103873744 | G93: =H93/F93 -> 0.80026648 | H93: ='rev send dist only'!O229 -> 83126675 | I93: =J93/F93 -> 0.19973352 | J93: ='rev send dist only'!J229 -> 20747069 | K93: =SUM(H93+J93) -> 103873744 | L93: =H93/K93 -> 0.80026648 | M93: =J93/K93 -> 0.19973352 | N93: =D93/$D$102 -> 0.8785641 | O93: 909109 | P93: =O93*N93*M93 -> 159529.27 | Q93: =O93*N93*L93 -> 639181.26
A94: Irvington Twp | D94: 8.5 | F94: =H94+J94 -> 69459286 | G94: =H94/F94 -> 0.7486365 | H94: ='rev send dist only'!O235 -> 51999757 | I94: =J94/F94 -> 0.2513635 | J94: ='rev send dist only'!J235 -> 17459529 | K94: =SUM(H94+J94) -> 69459286 | L94: =H94/K94 -> 0.7486365 | M94: =J94/K94 -> 0.2513635 | N94: =D94/$D$102 -> 0.017435897 | O94: 909109 | P94: =O94*N94*M94 -> 3984.3958 | Q94: =O94*N94*L94 -> 11866.735
A95: Newark City | D95: 26 | F95: =H95+J95 -> 381732222 | G95: =H95/F95 -> 0.75741087 | H95: =$H$46 -> 289128135 | I95: =J95/F95 -> 0.24258913 | J95: =$J$46 -> 92604087 | K95: =SUM(H95+J95) -> 381732222 | L95: =H95/K95 -> 0.75741087 | M95: =J95/K95 -> 0.24258913 | N95: =D95/$D$102 -> 0.053333333 | O95: 909109 | P95: =O95*N95*M95 -> 11762.131 | Q95: =O95*N95*L95 -> 36723.682
A96: City of Orange Twp | D96: 17.2 | F96: =H96+J96 -> 39282621 | G96: =H96/F96 -> 0.76110879 | H96: ='rev send dist only'!O242 -> 29898348 | I96: =J96/F96 -> 0.23889121 | J96: ='rev send dist only'!J242 -> 9384273 | K96: =SUM(H96+J96) -> 39282621 | L96: =H96/K96 -> 0.76110879 | M96: =J96/K96 -> 0.23889121 | N96: =D96/$D$102 -> 0.035282051 | O96: 909109 | P96: =O96*N96*M96 -> 7662.4907 | Q96: =O96*N96*L96 -> 24412.74
A97: West Orange Twp | D97: 1 | F97: =H97+J97 -> 95712705 | G97: =H97/F97 -> 0 | H97: ='rev send dist only'!O247 -> 0 | I97: =J97/F97 -> 1 | J97: ='rev send dist only'!J247 -> 95712705 | K97: =SUM(H97+J97) -> 95712705 | L97: =H97/K97 -> 0 | M97: =J97/K97 -> 1 | N97: =D97/$D$102 -> 0.0020512821 | O97: 909109 | P97: =O97*N97*M97 -> 1864.839 | Q97: =O97*N97*L97 -> 0
A98: Jersey City | D98: 1 | F98: =H98+J98 -> 259769100 | G98: =H98/F98 -> 0.68623093 | H98: =$H$57 -> 178261592 | I98: =J98/F98 -> 0.31376907 | J98: =$J$57 -> 81507508 | K98: =SUM(H98+J98) -> 259769100 | L98: =H98/K98 -> 0.68623093 | M98: =J98/K98 -> 0.31376907 | N98: =D98/$D$102 -> 0.0020512821 | O98: 909109 | P98: =O98*N98*M98 -> 585.12878 | Q98: =O98*N98*L98 -> 1279.7102
A99: Perth Amboy City | D99: 1 | F99: =H99+J99 -> 73322922 | G99: =H99/F99 -> 0.75020372 | H99: ='rev send dist only'!O349 -> 55007129 | I99: =J99/F99 -> 0.24979628 | J99: ='rev send dist only'!J349 -> 18315793 | K99: =SUM(H99+J99) -> 73322922 | L99: =H99/K99 -> 0.75020372 | M99: =J99/K99 -> 0.24979628 | N99: =D99/$D$102 -> 0.0020512821 | O99: 909109 | P99: =O99*N99*M99 -> 465.82983 | Q99: =O99*N99*L99 -> 1399.0091
A100: Passaic City | D100: 0.9 | F100: =H100+J100 -> 89777526 | G100: =H100/F100 -> 0.82009587 | H100: =H62 -> 73626178 | I100: =J100/F100 -> 0.17990413 | J100: =J62 -> 16151348 | K100: =SUM(H100+J100) -> 89777526 | L100: =H100/K100 -> 0.82009587 | M100: =J100/K100 -> 0.17990413 | N100: =D100/$D$102 -> 0.0018461538 | O100: 909109 | P100: =O100*N100*M100 -> 301.94302 | Q100: =O100*N100*L100 -> 1376.4121
...

Sheet State Chart
G1: Local | H1: Local | I1: Local | J1: Local | K1: Local | L1: Local | M1: Local | O1: State | P1: State | Q1: State | R1: State | S1: State | T1: State | U1: State | V1: State | W1: State | X1: State | Y1: State | Z1: State | AA1: State | AB1: State | AC1: State | AD1: State | AE1: State | AF1: State | AG1: State | AH1: State | AI1: State | AJ1: State | AK1: State | AL1: State | AM1: State | AN1: State | AO1: State | AP1: State | AQ1: State | AR1: State | AS1: State | AT1: State | AU1: State Revenue - Special Revenue Funds | AW1: Federal | AX1: Federal | AY1: Federal | AZ1: Federal | BA1: Federal | BB1: Federal | BC1: Federal Revenue | BD1: Federal Revenue | BE1: Federal Revenue | BG1: Other | BH1: Other | BI1: Other | BJ1: Other | BK1: Other | BL1: Other | BM1: Other | BN1: Other | BO1: Other | BP1: Other | BR1: Other | BS1: Other | BT1: Other | BU1: Other | BV1: Other | BW1: Other | BX1: Other | BY1: Other | BZ1: Other | CA1: Other | CB1: Other | CD1: Indeterminate | CE1: Indeterminate | CF1: Indeterminate | CG1: Indeterminate | CI1: Intermediate | CJ1: Intermediate | CM1: Capital Projects Fund | CN1: Capital Projects | CO1: State | CP1: State | CQ1: State | CR1: Federal | CS1: Federal | CT1: State | CU1: State | CV1: Indeterminate
A2: CO | B2: DIST | C2: CONAME | D2: DISTNAME | F2: Enrollment | G2: Local Tax Levy & Unrestricted Misc Revenues | H2: County Tax Levy | I2: Other Local Govt Units - Unrestricted | J2: Other Local Govt Units - Restricted | K2: Other Revenue from Local Sources | L2: Local Tax Levy | M2: Municipal Surplus | N2: Total Local | O2: Core Curriculum Standards Aid | P2: Supplemental Core Curriculum Standards Aid | Q2: Local Tax Levy & Unrestricted Misc Revenues | R2: School Choice Aid | S2: Education Opportunity Aid | T2: Discretionary Education Opportunity Aid | U2: Abbott-bordered district aid | V2: Transportation Aid | W2: Special Education Aid | X2: Bilingual Education | Y2: Stabilization Aid | Z2: Supplemental Stabilization Aid | AA2: County Vocational Education Program Aid | AB2: Academic Achievement Reward Program | AC2: Extraordinary Aid | AD2: Consolidated Aid | AE2: Additional Formula Aid | AF2: Other State Aids - Out of Cap | AG2: TPAF Pension (On Behalf) | AH2: TPAF Social Security (Reimbursed) | AI2: Other State Aids | AJ2: Demonstrably Effective Program Aid - Prior Year Carryover | AK2: Distance Learning Network Aid - Prior Year Carryover | AL2: Instructional Supplement Ad - Prior Yr Carryover | AM2: Demontrably Effective Program Aid | AN2: Distance Learning Network Aid | AO2: Instructional Supplemental Aid | AP2: Debt Service Aid Type II | AQ2: Addtl State School Bldg Aid - Chap 177 | AR2: Addtl State School Bldg Aid - Chap 10 | AS2: Addt State School Building Aid-Chapter 74 | AT2: Addtl State School Building Aid - EDA Grant | AU2: Other Restricted Entitlements | AW2: Medicaid Reimbursement | AX2: Title VI | AY2: Schoolwide Programs | AZ2: JTPA | BA2: PL 81.874 (Impact) | BB2: Vocational Education | BC2: Title I | BD2: IDEA | BE2: Other Federal | BG2: Other Financing Sources - Capital Leases | BH2: Other Financing Sources | BI2: Tuition from Individuals | BJ2: Tuition from Other Sources | BK2: Tuition from Summer School | BL2: Non-Resident Fees | BM2: Transportation Fees from Individuals | BN2: Transportation Fees Other LEAs | BO2: Interest Earned on Capital Reserve Funds | BP2: Other Restricted Misc | BR2: Rents & Royalties | BS2: Sale of Property | BT2: Fines and Forfeits | BU2: Private Contributions | BV2: Tetbook Sales & Rentals | BW2: Interest on Investments | BX2: Other Financing Sources | BY2: Interest on Investments | BZ2: Other Misc | CA2: Earnings on Investments | CB2: Other Financing Sources | CD2: Tuition Other LEAs in State | CE2: Tuition from Other LEAs Outside the State | CF2: Tuition from LEAs | CG2: Other Tuition | CI2: Restricted Rev from Intermediate Sources | CJ2: Unrestricted Rev from Intermediate Sources | CM2: Bond Principal | CN2: Bond Premium | CO2: Aid for Adult & Post Graduate Programs | CP2: Post-Secondary Vocational Program Aid | CQ2: Early Childhood Program Aid - Prior Year Carryover | CR2: Adult Basic Ed | CS2: Interest earnd on Early Childhood Cap. Res. Fund | CT2: Early Childhood Program | CU2: Preschool Expansion Aid | CV2: Total Special Revenue
G3: L150/L253 | H3: L160 | I3: L191 | J3: L192 | K3: L419 | L3: L550 | M3: L642 | O3: L280 | P3: L281 | Q3: L150/L253 | R3: L285 | S3: L286 | T3: L287 | U3: L288 | V3: L300 | W3: L310 | X3: L320 | Y3: L340 | Z3: L341 | AA3: L350 | AB3: L353 | AC3: L354 | AD3: L355 | AE3: L356 | AF3: L360 | AG3: L361 | AH3: L362 | AI3: L365 | AJ3: L422 | AK3: L423 | AL3: L424 | AM3: L426 | AN3: L427 | AO3: L428 | AP3: L580 | AQ3: L600 | AR3: L610 | AS3: L620 | AT3: L641 | AU3: L430 | AV3: Total State | AW3: L390 | AX3: L450 | AY3: L455 | AZ3: L490 | BA3: L380 | BB3: L470 | BC3: L440 | BD3: L460 | BE3: L500 | BF3: Total Federal | BG3: L141 | BH3: L142 | BI3: L195 | BJ3: L198 | BK3: L199 | BL3: L230 | BM3: L241 | BN3: L242 | BO3: L251 | BP3: L252 | BR3: L254 | BS3: L255 | BT3: L256 | BU3: L257 | BV3: L258 | BW3: L418 | BX3: L541 | BY3: L551 | BZ3: L552 | CA3: L643 | CB3: L647 | CC3: Total Other | CD3: L196 | CE3: L197 | CF3: L210 | CG3: L220 | CI3: L271 | CJ3: L272 | CK3: Total Indeterminate | CM3: L644 | CN3: L645 | CO3: L351 | CP3: L352 | CQ3: L421 | CR3: L480 | CS3: L512 | CT3: L425 | CU3: L429 | CV3: L520
A4: 80 | B4: 6010 | C4: Lake Como | D4: Academy Charter High School | F4: 202 | G4: 664063.19 | N4: =SUM(G4:M4) -> 664063.19 | P4: 55117 | Q4: 1666069.8 | W4: 112833 | X4: 1400 | AH4: 82076 | AV4: =SUM(O4:AU4) -> 1917495.8 | AX4: 40755 | BC4: 97563 | BF4: =SUM(AW4:BE4) -> 138318 | CC4: =SUM(BG4:CB4) -> 0 | CK4: =SUM(CD4:CJ4) -> 0 | CV4: 138318
A5: 80 | B5: 6018 | C5: SOMERSET | D5: Central Jersey College Prep | F5: 164 | G5: 693349.23 | N5: =SUM(G5:M5) -> 693349.23 | Q5: 261124.77 | W5: 78081 | AF5: 684744 | AH5: 52147 | AU5: 3000 | AV5: =SUM(O5:AU5) -> 1079096.8 | BC5: 27840 | BE5: 319041 | BF5: =SUM(AW5:BE5) -> 346881 | BU5: 61045 | CC5: =SUM(BG5:CB5) -> 61045 | CK5: =SUM(CD5:CJ5) -> 0 | CV5: 349881
A6: 80 | B6: 6212 | C6: Camden | D6: Camden Academy Charter High School | F6: 406 | G6: 44734.06 | N6: =SUM(G6:M6) -> 44734.06 | O6: 3079797 | Q6: 571193.94 | R6: 183466 | W6: 173091 | AG6: 127894 | AH6: 144787 | AI6: 353634 | AU6: 251 | AV6: =SUM(O6:AU6) -> 4634113.9 | BC6: 414688 | BD6: 92081 | BE6: 42244 | BF6: =SUM(AW6:BE6) -> 549013 | CC6: =SUM(BG6:CB6) -> 0 | CK6: =SUM(CD6:CJ6) -> 0 | CV6: 549264
A7: 80 | B7: 6215 | C7: Camden | D7: Camden's Promise Charter | F7: 391 | G7: 138050.71 | N7: =SUM(G7:M7) -> 138050.71 | O7: 2793192 | Q7: 1567881.3 | W7: 225245 | AG7: 115668 | AH7: 157364 | AV7: =SUM(O7:AU7) -> 4859350.3 | BC7: 361407 | BD7: 82539 | BE7: 616263 | BF7: =SUM(AW7:BE7) -> 1060209 | CC7: =SUM(BG7:CB7) -> 0 | CJ7: 172344 | CK7: =SUM(CD7:CJ7) -> 172344 | CV7: 1060209
A8: 80 | B8: 6217 | C8: Plainfield | D8: Central Jersey Arts | F8: 222 | G8: 135691.71 | N8: =SUM(G8:M8) -> 135691.71 | Q8: 302047.29 | W8: 34375 | AH8: 58427 | AI8: 1728752 | AU8: 565634 | AV8: =SUM(O8:AU8) -> 2689235.3 | BC8: 22427 | BE8: 650 | BF8: =SUM(AW8:BE8) -> 23077 | CC8: =SUM(BG8:CB8) -> 0 | CK8: =SUM(CD8:CJ8) -> 0 | CV8: 588711
A9: 80 | B9: 6220 | C9: Jersey City | D9: CREATE | F9: 518 | G9: 350113.88 | I9: 2299440 | N9: =SUM(G9:M9) -> 2649553.9 | Q9: 765719.12 | W9: 401004 | AH9: 136909 | AM9: 130654 | AN9: 112475 | AU9: 359020 | AV9: =SUM(O9:AU9) -> 1905781.1 | BC9: 264127 | BD9: 89487 | BE9: 175429 | BF9: =SUM(AW9:BE9) -> 529043 | BR9: 101343 | CC9: =SUM(BG9:CB9) -> 101343 | CK9: =SUM(CD9:CJ9) -> 0 | CV9: 1131192
A10: 80 | B10: 6230 | C10: Clifton | D10: Classical Academy Charter | F10: 104 | G10: 820085.02 | K10: 6053 | N10: =SUM(G10:M10) -> 826138.02 | Q10: 65457.982 | AF10: 66314 | AH10: 29116 | AU10: 4000 | AV10: =SUM(O10:AU10) -> 164887.98 | BC10: 2418 | BD10: 2025 | BE10: 3859 | BF10: =SUM(AW10:BE10) -> 8302 | CC10: =SUM(BG10:CB10) -> 0 | CK10: =SUM(CD10:CJ10) -> 0 | CV10: 18355
A11: 80 | B11: 6232 | C11: Camden | D11: Environment Community Opportunity Charter School (ECO Charter School) | F11: 198 | G11: 23379.343 | N11: =SUM(G11:M11) -> 23379.343 | O11: 1157758 | Q11: 275004.66 | W11: 21623 | AF11: 259401 | AH11: 52275 | AM11: 80195 | AV11: =SUM(O11:AU11) -> 1846256.7 | AX11: 4384 | BC11: 200514 | BD11: 10593 | BE11: 206552 | BF11: =SUM(AW11:BE11) -> 422043 | CC11: =SUM(BG11:CB11) -> 0 | CK11: =SUM(CD11:CJ11) -> 0 | CT11: 141128 | CV11: 643366
A12: 80 | B12: 6235 | C12: Jersey City | D12: Liberty Academy Charter School | F12: 337 | G12: 273261.16 | N12: =SUM(G12:M12) -> 273261.16 | Q12: 584910.84 | W12: 153008 | X12: 5840 | AF12: 2484819 | AH12: 76818 | AV12: =SUM(O12:AU12) -> 3305395.8 | BC12: 297746 | BD12: 49919 | BE12: 53825 | BF12: =SUM(AW12:BE12) -> 401490 | CC12: =SUM(BG12:CB12) -> 0 | CK12: =SUM(CD12:CJ12) -> 0 | CV12: 401490
A13: 80 | B13: 6240 | C13: Camden | D13: Freedom Academy Charter School | F13: 215 | G13: 23011.255 | K13: 132750 | N13: =SUM(G13:M13) -> 155761.26 | O13: 1595913 | Q13: 289004.74 | W13: 160308 | AF13: 235387 | AH13: 34566 | AV13: =SUM(O13:AU13) -> 2315178.7 | BC13: 198674 | BE13: 43101 | BF13: =SUM(AW13:BE13) -> 241775 | BU13: 28933 | CC13: =SUM(BG13:CB13) -> 28933 | CK13: =SUM(CD13:CJ13) -> 0 | CV13: 374525
A14: 80 | B14: 6320 | C14: Newark | D14: Discovery Charter | F14: 75 | G14: 33429.267 | K14: 53000 | N14: =SUM(G14:M14) -> 86429.267 | Q14: 104372.73 | W14: 53080 | AF14: 563805 | AH14: 21326 | AV14: =SUM(O14:AU14) -> 742583.73 | BC14: 43088 | BD14: 10660 | BE14: 287792 | BF14: =SUM(AW14:BE14) -> 341540 | CC14: =SUM(BG14:CB14) -> 0 | CK14: =SUM(CD14:CJ14) -> 0 | CV14: 394540
A15: 80 | B15: 6325 | C15: Camden | D15: D.U.E. Season Charter | F15: 329 | G15: 36511.854 | N15: =SUM(G15:M15) -> 36511.854 | Q15: 435153.15 | W15: 78128 | AF15: 2900896 | AH15: 82597 | AU15: 223254 | AV15: =SUM(O15:AU15) -> 3720028.1 | BC15: 166396 | BD15: 34813 | BE15: 6736 | BF15: =SUM(AW15:BE15) -> 207945 | CC15: =SUM(BG15:CB15) -> 0 | CK15: =SUM(CD15:CJ15) -> 0 | CV15: 431199
A16: 80 | B16: 6410 | C16: East Orange | D16: East Orange Community Charter | F16: 501 | G16: 191481.34 | N16: =SUM(G16:M16) -> 191481.34 | O16: 2787424 | Q16: 717627.66 | W16: 103880 | AF16: 1255101 | AH16: 118791 | AV16: =SUM(O16:AU16) -> 4982823.7 | BC16: 425588 | BD16: 105509 | BE16: 256157 | BF16: =SUM(AW16:BE16) -> 787254 | CC16: =SUM(BG16:CB16) -> 0 | CK16: =SUM(CD16:CJ16) -> 0 | CV16: 787254
A17: 80 | B17: 6420 | C17: Hoboken | D17: Elysian Charter | F17: 279 | G17: 709741.84 | I17: 2248197 | N17: =SUM(G17:M17) -> 2957938.8 | Q17: 320838.16 | W17: 189487 | AF17: 160769 | AG17: 111623 | AV17: =SUM(O17:AU17) -> 782717.16 | BC17: 64068 | BD17: 39671 | BE17: 13350 | BF17: =SUM(AW17:BE17) -> 117089 | CC17: =SUM(BG17:CB17) -> 0 | CK17: =SUM(CD17:CJ17) -> 0 | CV17: 117089
A18: 80 | B18: 6425 | C18: Trenton | D18: Emily Fisher Charter | F18: 352 | G18: 111698.87 | N18: =SUM(G18:M18) -> 111698.87 | Q18: 512356.13 | W18: 1462240 | X18: 7290 | AF18: 2873003 | AH18: 99491 | AV18: =SUM(O18:AU18) -> 4954380.1 | BC18: 321978 | BD18: 63559 | BE18: 48003 | BF18: =SUM(AW18:BE18) -> 433540 | CC18: =SUM(BG18:CB18) -> 0 | CK18: =SUM(CD18:CJ18) -> 0 | CV18: 433540
A19: 80 | B19: 6430 | C19: Englewood | D19: Englewood on the Palisades Charter School | F19: 182 | G19: 1396669.3 | N19: =SUM(G19:M19) -> 1396669.3 | O19: 722193 | Q19: 43903.683 | W19: 55463 | X19: 294 | AF19: 325 | AH19: 70378 | AM19: 68279 | AO19: 1297 | AV19: =SUM(O19:AU19) -> 962132.68 | AX19: 14483 | BA19: 475 | BC19: 121191 | BD19: 27351 | BE19: 2900 | BF19: =SUM(AW19:BE19) -> 166400 | CC19: =SUM(BG19:CB19) -> 0 | CK19: =SUM(CD19:CJ19) -> 0 | CT19: 118130 | CV19: 353631
A20: 80 | B20: 6612 | C20: Galloway Township | D20: Galloway Community Charter School | F20: 270 | G20: 1220410.9 | N20: =SUM(G20:M20) -> 1220410.9 | Q20: 888874.15 | W20: 44841 | AF20: 219768 | AH20: 104580 | AU20: 191677 | AV20: =SUM(O20:AU20) -> 1449740.1 | BC20: 103503 | BD20: 56606 | BE20: 7843 | BF20: =SUM(AW20:BE20) -> 167952 | BX20: 237370 | CC20: =SUM(BG20:CB20) -> 237370 | CK20: =SUM(CD20:CJ20) -> 0 | CV20: 359629
A21: 80 | B21: 6635 | C21: New Brunswick | D21: Greater Brunswick Charter School | F21: 219 | G21: 556779.22 | N21: =SUM(G21:M21) -> 556779.22 | O21: 587519 | Q21: 398661.78 | W21: 92829 | X21: 32704 | AF21: 437901 | AG21: 13925 | AH21: 69545 | AU21: 132180 | AV21: =SUM(O21:AU21) -> 1765264.8 | AY21: 32186 | BC21: 90866 | BE21: 1575 | BF21: =SUM(AW21:BE21) -> 124627 | CC21: =SUM(BG21:CB21) -> 0 | CK21: =SUM(CD21:CJ21) -> 0 | CV21: 256807
A22: 80 | B22: 6665 | C22: Newark | D22: Gray Charter School | F22: 306 | G22: 140740.99 | N22: =SUM(G22:M22) -> 140740.99 | Q22: 439421.01 | AF22: 2443362 | AH22: 74931 | AU22: 4000 | AV22: =SUM(O22:AU22) -> 2961714 | BC22: 234750 | BE22: 30398 | BF22: =SUM(AW22:BE22) -> 265148 | CC22: =SUM(BG22:CB22) -> 0 | CK22: =SUM(CD22:CJ22) -> 0 | CL22: =SUM(N22+AV22+BF22+CC23+CK23) -> 3367603 | CV22: 269148
A23: 80 | B23: 6720 | C23: Hoboken | D23: Hoboken Charter School | F23: 251 | G23: 1482388 | K23: 40291 | N23: =SUM(G23:M23) -> 1522679 | O23: 1401520 | Q23: 617445.01 | W23: 228146 | AF23: 204519 | AH23: 115239 | AV23: =SUM(O23:AU23) -> 2566869 | BC23: 64795 | BD23: 42401 | BE23: 18238 | BF23: =SUM(AW23:BE23) -> 125434 | CC23: =SUM(BG23:CB23) -> 0 | CK23: =SUM(CD23:CJ23) -> 0 | CV23: 165725
A24: 80 | B24: 6740 | C24: Asbury Park | D24: Hope Academy Charter School | F24: 135 | G24: 76802.086 | N24: =SUM(G24:M24) -> 76802.086 | Q24: 239338.91 | AF24: 1296566 | AH24: 69043 | AV24: =SUM(O24:AU24) -> 1604947.9 | BC24: 110972 | BD24: 34603 | BE24: 11178 | BF24: =SUM(AW24:BE24) -> 156753 | CC24: =SUM(BG24:CB24) -> 0 | CK24: =SUM(CD24:CJ24) -> 0 | CV24: 156753
A25: 80 | B25: 6810 | C25: Trenton | D25: International Charter School of Trenton | F25: 94.5 | G25: 29309.455 | N25: =SUM(G25:M25) -> 29309.455 | Q25: 134735.55 | W25: 50525 | AF25: 753481 | AH25: 35679 | AU25: 1638 | AV25: =SUM(O25:AU25) -> 976058.55 | BC25: 72658 | BD25: 26141 | BE25: 26029 | BF25: =SUM(AW25:BE25) -> 124828 | CC25: =SUM(BG25:CB25) -> 0 | CK25: =SUM(CD25:CJ25) -> 0 | CL25: =SUM(N25+AV25+BF25+CC26+CK26) -> 1259902 | CV25: 126466
A26: 80 | B26: 6910 | C26: Jersey City | D26: Jersey City Community Charter School | F26: 505 | G26: 348970.78 | N26: =SUM(G26:M26) -> 348970.78 | O26: 2276775 | Q26: 743587.22 | W26: 60091 | AF26: 1305249 | AH26: 132000 | AV26: =SUM(O26:AU26) -> 4517702.2 | BC26: 670116 | BD26: 85170 | BE26: 48289 | BF26: =SUM(AW26:BE26) -> 803575 | BO26: 65022 | BP26: 64684 | CC26: =SUM(BG26:CB26) -> 129706 | CK26: =SUM(CD26:CJ26) -> 0 | CV26: 803575
A27: 80 | B27: 6915 | C27: Jersey City | D27: Jersey City Golden Door Charter School | F27: 494 | G27: 368589.86 | N27: =SUM(G27:M27) -> 368589.86 | Q27: 806127.14 | W27: 132810 | AF27: 3753870 | AH27: 161209 | AU27: 1892 | AV27: =SUM(O27:AU27) -> 4855908.1 | BC27: 300676 | BD27: 96131 | BE27: 70581 | BF27: =SUM(AW27:BE27) -> 467388 | CC27: =SUM(BG27:CB27) -> 0 | CK27: =SUM(CD27:CJ27) -> 0 | CV27: 469280
A28: 80 | B28: 7100 | C28: Newark | D28: Lady Liberty Academy Charter School | F28: 443 | G28: 185215.1 | N28: =SUM(G28:M28) -> 185215.1 | Q28: 577992.9 | AF28: 3620192 | AH28: 161510 | AV28: =SUM(O28:AU28) -> 4359694.9 | BC28: 325286 | BD28: 96705 | BE28: 44518 | BF28: =SUM(AW28:BE28) -> 466509 | CC28: =SUM(BG28:CB28) -> 0 | CK28: =SUM(CD28:CJ28) -> 0 | CV28: 466509
A29: 80 | B29: 7109 | C29: Camden | D29: LEAP Academy University Charter School | F29: 774 | G29: 264692.66 | N29: =SUM(G29:M29) -> 264692.66 | O29: 5075202 | Q29: 1540066.3 | W29: 167020 | X29: 20907 | AF29: 554157 | AG29: 215266 | AH29: 260176 | AM29: 327061 | AV29: =SUM(O29:AU29) -> 8159855.3 | BC29: 577652 | BD29: 151589 | BE29: 496172 | BF29: =SUM(AW29:BE29) -> 1225413 | BH29: 362413 | CC29: =SUM(BG29:CB29) -> 362413 | CK29: =SUM(CD29:CJ29) -> 0 | CT29: 582624 | CV29: 2135098
A30: 80 | B30: 7115 | C30: Jersey City | D30: Learning Community Charter School | F30: 322 | G30: 266399.35 | I30: 1613923 | K30: 88637 | N30: =SUM(G30:M30) -> 1968959.4 | Q30: 582630.65 | U30: 122868 | W30: 150221 | X30: 2336 | AF30: 562084 | AG30: 118066 | AV30: =SUM(O30:AU30) -> 1538205.6 | BC30: 125760 | BD30: 48427 | BF30: =SUM(AW30:BE30) -> 174187 | CC30: =SUM(BG30:CB30) -> 0 | CK30: =SUM(CD30:CJ30) -> 0 | CV30: 262824
A31: 80 | B31: 7210 | C31: Newark | D31: Marion P. Thomas Charter School | F31: 359 | G31: 153396.63 | N31: =SUM(G31:M31) -> 153396.63 | Q31: 478934.37 | AF31: 2939449 | AH31: 20004 | AV31: =SUM(O31:AU31) -> 3438387.4 | BC31: 350177 | BE31: 100700 | BF31: =SUM(AW31:BE31) -> 450877 | BU31: 27893 | CC31: =SUM(BG31:CB31) -> 27893 | CK31: =SUM(CD31:CJ31) -> 0 | CV31: 450877
A32: 80 | B32: 7280 | C32: Newark | D32: Greater Newark Charter School (formerly Newark, Greater Newark Academy Charter School | F32: 171.3 | G32: 83509.124 | K32: 10000 | N32: =SUM(G32:M32) -> 93509.124 | O32: 1056725 | Q32: 260731.88 | W32: 49386 | AD32: 162776 | AF32: 79312 | AH32: 61517 | AV32: =SUM(O32:AU32) -> 1670447.9 | AZ32: 11663 | BC32: 139803 | BD32: 29249 | BF32: =SUM(AW32:BE32) -> 180715 | BU32: 11176 | CC32: =SUM(BG32:CB32) -> 11176 | CK32: =SUM(CD32:CJ32) -> 0 | CV32: 190715
A33: 80 | B33: 7290 | C33: Newark | D33: New Horizons Community Charter School | F33: 508 | G33: 181243.19 | N33: =SUM(G33:M33) -> 181243.19 | Q33: 565876.81 | AF33: 3775494 | AH33: 144177 | AV33: =SUM(O33:AU33) -> 4485547.8 | BC33: 540738 | BD33: 80906 | BE33: 103550 | BF33: =SUM(AW33:BE33) -> 725194 | BH33: 4174 | CC33: =SUM(BG33:CB33) -> 4174 | CK33: =SUM(CD33:CJ33) -> 0 | CV33: 725194
A34: 80 | B34: 7320 | C34: Newark | D34: North Star Academy Charter School of Newark | F34: 451 | G34: 267018.1 | N34: =SUM(G34:M34) -> 267018.1 | Q34: 833682.9 | AF34: 3761939 | AH34: 212193 | AU34: 90688 | AV34: =SUM(O34:AU34) -> 4898502.9 | BC34: 402521 | BD34: 65204 | BE34: 239596 | BF34: =SUM(AW34:BE34) -> 707321 | CC34: =SUM(BG34:CB34) -> 0 | CK34: =SUM(CD34:CJ34) -> 0 | CV34: 798009
A35: 80 | B35: 7325 | C35: Newark | D35: TEAM Academy Charter School | F35: 467 | G35: 274966.61 | I35: 2699210 | K35: 192750 | N35: =SUM(G35:M35) -> 3166926.6 | Q35: 860282.39 | W35: 129781 | AF35: 634003 | AH35: 124814 | AV35: =SUM(O35:AU35) -> 1748880.4 | BC35: 317673 | BD35: 70308 | BE35: 22954 | BF35: =SUM(AW35:BE35) -> 410935 | CC35: =SUM(BG35:CB35) -> 0 | CK35: =SUM(CD35:CJ35) -> 0 | CV35: 603685
A36: 80 | B36: 7410 | C36: Somers Point | D36: Charter Tech High School | F36: 251 | G36: 1178176.4 | N36: =SUM(G36:M36) -> 1178176.4 | O36: 701118 | Q36: 500183.59 | W36: 159612 | AF36: 194093 | AH36: 92893 | AM36: 46794 | AV36: =SUM(O36:AU36) -> 1694693.6 | AX36: 1000 | BB36: 36052 | BC36: 82902 | BD36: 34529 | BE36: 2585 | BF36: =SUM(AW36:BE36) -> 157068 | CC36: =SUM(BG36:CB36) -> 0 | CK36: =SUM(CD36:CJ36) -> 0 | CV36: 203862
A37: 80 | B37: 7420 | C37: Atlantic City | D37: Oceanside Charter School | F37: 354 | G37: 2605924.2 | N37: =SUM(G37:M37) -> 2605924.2 | Q37: 127850.8 | W37: 195844 | AF37: 1367428 | AG37: 153924 | AH37: 146793 | AV37: =SUM(O37:AU37) -> 1991839.8 | BC37: 282375 | BD37: 76095 | BE37: 43969 | BF37: =SUM(AW37:BE37) -> 402439 | CC37: =SUM(BG37:CB37) -> 0 | CK37: =SUM(CD37:CJ37) -> 0 | CV37: 402439
A38: 80 | B38: 7500 | C38: Hamilton Township | D38: PACE Charter School of Hamilton | F38: 106 | G38: 59449.551 | N38: =SUM(G38:M38) -> 59449.551 | Q38: 172862.45 | AF38: 759274 | AH38: 30272 | AV38: =SUM(O38:AU38) -> 962408.45 | BF38: =SUM(AW38:BE38) -> 0 | CC38: =SUM(BG38:CB38) -> 0 | CK38: =SUM(CD38:CJ38) -> 0
A39: 80 | B39: 7503 | C39: Paterson | D39: Paterson Charter School for Science and Technology | F39: 397 | G39: 197178.29 | N39: =SUM(G39:M39) -> 197178.29 | Q39: 617858.71 | X39: 21258 | AH39: 109658 | AI39: 3238838 | AU39: 2125 | AV39: =SUM(O39:AU39) -> 3989737.7 | BC39: 171638 | BD39: 51728 | BE39: 80825 | BF39: =SUM(AW39:BE39) -> 304191 | CC39: =SUM(BG39:CB39) -> 0 | CK39: =SUM(CD39:CJ39) -> 0 | CV39: 306316
A40: 80 | B40: 7520 | C40: Pleasantville | D40: PleasanTech Academy Charter School | F40: 555 | G40: 623956.68 | N40: =SUM(G40:M40) -> 623956.68 | Q40: 1075634.3 | W40: 171189 | AF40: 3877698 | AH40: 173391 | AU40: 3993 | AV40: =SUM(O40:AU40) -> 5301905.3 | BC40: 274711 | BD40: 156027 | BE40: 154934 | BF40: =SUM(AW40:BE40) -> 585672 | CC40: =SUM(BG40:CB40) -> 0 | CK40: =SUM(CD40:CJ40) -> 0 | CV40: 589665
A41: 80 | B41: 7540 | C41: Princeton | D41: Princeton Charter School | F41: 290 | G41: 2411356.8 | N41: =SUM(G41:M41) -> 2411356.8 | Q41: 80.164959 | W41: 38575 | AF41: 1619154 | AH41: 105722 | AU41: 768 | AV41: =SUM(O41:AU41) -> 1764299.2 | BC41: 10816 | BD41: 35746 | BE41: 6331 | BF41: =SUM(AW41:BE41) -> 52893 | BO41: 26739 | CC41: =SUM(BG41:CB41) -> 26739 | CK41: =SUM(CD41:CJ41) -> 0 | CV41: 53661
A42: 80 | B42: 7600 | C42: Plainfield | D42: Queen City Academy Charter School | F42: 242 | G42: 155198.12 | N42: =SUM(G42:M42) -> 155198.12 | Q42: 388779.88 | W42: 34535 | AF42: 1884177 | AH42: 68339 | AU42: 13235 | AV42: =SUM(O42:AU42) -> 2389065.9 | BC42: 115184 | BD42: 63799 | BE42: 606768 | BF42: =SUM(AW42:BE42) -> 785751 | CC42: =SUM(BG42:CB42) -> 0 | CK42: =SUM(CD42:CJ42) -> 0 | CV42: 798986
A43: 80 | B43: 7720 | C43: Red Bank | D43: Red Bank Charter School | F43: 156 | G43: 1315952 | K43: 58357 | N43: =SUM(G43:M43) -> 1374309 | Q43: 0 | W43: 272488 | X43: 30602 | AF43: 647532 | AG43: 60459 | AH43: 70045 | AM43: 51176 | AU43: 25000 | AV43: =SUM(O43:AU43) -> 1157302 | BC43: 91820 | BD43: 27583 | BE43: 8795 | BF43: =SUM(AW43:BE43) -> 128198 | CC43: =SUM(BG43:CB43) -> 0 | CK43: =SUM(CD43:CJ43) -> 0 | CT43: 79189 | CV43: 341920
A44: 80 | B44: 7727 | C44: Blairstown | D44: Ridge and Valley Charter School | F44: 100 | G44: 660091.25 | K44: 16495 | N44: =SUM(G44:M44) -> 676586.25 | Q44: 171661.75 | AH44: 30350 | AI44: 153002 | AU44: 1645 | AV44: =SUM(O44:AU44) -> 356658.75 | BD44: 18973 | BE44: 2390 | BF44: =SUM(AW44:BE44) -> 21363 | CC44: =SUM(BG44:CB44) -> 0 | CK44: =SUM(CD44:CJ44) -> 0 | CV44: 39503
A45: 80 | B45: 7730 | C45: Newark | D45: Robert Treat Academy Charter School | F45: 450 | G45: 213881.86 | K45: 25000 | N45: =SUM(G45:M45) -> 238881.86 | O45: 2505594 | Q45: 667781.14 | W45: 86079 | X45: 4672 | AF45: 580524 | AG45: 160867 | AH45: 141191 | AM45: 206868 | AV45: =SUM(O45:AU45) -> 4353576.1 | BC45: 237658 | BD45: 80521 | BE45: 136716 | BF45: =SUM(AW45:BE45) -> 454895 | CC45: =SUM(BG45:CB45) -> 0 | CK45: =SUM(CD45:CJ45) -> 0 | CT45: 365036 | CV45: 1051799
A46: 80 | B46: 7735 | C46: Newark | D46: Maria L. Varisco-Rogers Charter School | F46: 112 | G46: 53034.107 | N46: =SUM(G46:M46) -> 53034.107 | P46: 666580 | Q46: 165582.89 | AF46: 205885 | AH46: 24171 | AM46: 50884 | AO46: 32507 | AV46: =SUM(O46:AU46) -> 1145609.9 | AX46: 163911 | BF46: =SUM(AW46:BE46) -> 163911 | CC46: =SUM(BG46:CB46) -> 0 | CK46: =SUM(CD46:CJ46) -> 0 | CV46: 247302
A47: 80 | B47: 7820 | C47: Jersey City | D47: Schomburg Charter School | F47: 165 | G47: 12769.284 | N47: =SUM(G47:M47) -> 12769.284 | O47: 2267098 | Q47: 27583.716 | W47: 119103 | AF47: 830064 | AH47: 25762 | AV47: =SUM(O47:AU47) -> 3269610.7 | BC47: 451349 | BD47: 110363 | BE47: 60496 | BF47: =SUM(AW47:BE47) -> 622208 | CC47: =SUM(BG47:CB47) -> 0 | CK47: =SUM(CD47:CJ47) -> 0 | CV47: 622208
A48: 80 | B48: 7830 | C48: Jersey City | D48: Soaring Heights Charter School | F48: 201 | G48: 157492.93 | N48: =SUM(G48:M48) -> 157492.93 | Q48: 344446.07 | W48: 65649 | AF48: 1511178 | AH48: 63139 | AI48: 917 | AV48: =SUM(O48:AU48) -> 1985329.1 | BC48: 147039 | BD48: 48074 | BE48: 20875 | BF48: =SUM(AW48:BE48) -> 215988 | CC48: =SUM(BG48:CB48) -> 0 | CK48: =SUM(CD48:CJ48) -> 0 | CV48: 215988
A49: 80 | B49: 7850 | C49: Sparta | D49: Sussex County Charter School of Technology | F49: 100 | G49: 475805.78 | N49: =SUM(G49:M49) -> 475805.78 | Q49: 175423.22 | W49: 99957 | AF49: 312021 | AG49: 36283 | AH49: 43372 | AV49: =SUM(O49:AU49) -> 667056.22 | BC49: 16745 | BD49: 18549 | BE49: 26437 | BF49: =SUM(AW49:BE49) -> 61731 | BP49: 5556 | CC49: =SUM(BG49:CB49) -> 5556 | CK49: =SUM(CD49:CJ49) -> 0 | CV49: 61731
A50: 80 | B50: 7890 | C50: Teaneck | D50: Teaneck Community Charter School | F50: 240 | G50: 2009263.6 | K50: 500 | N50: =SUM(G50:M50) -> 2009763.6 | Q50: 2588.3595 | W50: 134863 | AF50: 1299893 | AH50: 112791 | AV50: =SUM(O50:AU50) -> 1550135.4 | BC50: 35124 | BD50: 33405 | BE50: 8312 | BF50: =SUM(AW50:BE50) -> 76841 | CC50: =SUM(BG50:CB50) -> 0 | CK50: =SUM(CD50:CJ50) -> 0 | CV50: 77341
A51: 80 | B51: 7901 | C51: Trenton | D51: Trenton Community Charter School (consolidated school in 2001) | F51: 621 | G51: 166017.53 | N51: =SUM(G51:M51) -> 166017.53 | Q51: 763182.47 | W51: 206107 | X51: 2336 | AF51: 5005974 | AH51: 201848 | AU51: 847 | AV51: =SUM(O51:AU51) -> 6180294.5 | BC51: 566517 | BD51: 153456 | BE51: 103731 | BF51: =SUM(AW51:BE51) -> 823704 | CC51: =SUM(BG51:CB51) -> 0 | CK51: =SUM(CD51:CJ51) -> 0 | CV51: 824551
A52: 80 | B52: 8010 | C52: Plainfield | D52: Union County TEAMS (Technology, Engineering, Architecture, Math&Science) Charter School | F52: 178 | G52: 129312.25 | N52: =SUM(G52:M52) -> 129312.25 | Q52: 329350.75 | W52: 51318 | AF52: 1396588 | AH52: 48620 | AU52: 252002 | AV52: =SUM(O52:AU52) -> 2077878.7 | AX52: 1349 | BC52: 133422 | BD52: 22860 | BE52: 3680 | BF52: =SUM(AW52:BE52) -> 161311 | CC52: =SUM(BG52:CB52) -> 0 | CK52: =SUM(CD52:CJ52) -> 0 | CV52: 413313
A53: 80 | B53: 8050 | C53: Morristown | D53: Unity Charter School | F53: 102 | G53: 116855.1 | K53: 40642 | N53: =SUM(G53:M53) -> 157497.1 | Q53: 17371.005 | W53: 98441 | AF53: 386556 | AH53: 49971 | AU53: 526 | AV53: =SUM(O53:AU53) -> 552865.01 | BD53: 18853 | BF53: =SUM(AW53:BE53) -> 18853 | CC53: =SUM(BG53:CB53) -> 0 | CK53: =SUM(CD53:CJ53) -> 0 | CV53: 60021
A54: 80 | B54: 8060 | C54: Jersey City | D54: University Academy Charter High School | F54: 405 | G54: 354483.74 | K54: 5167 | N54: =SUM(G54:M54) -> 359650.74 | Q54: 775276.26 | W54: 135570 | AF54: 2847849 | AH54: 158898 | AU54: 4851 | AV54: =SUM(O54:AU54) -> 3922444.3 | BC54: 81743 | BD54: 54552 | BE54: 7370 | BF54: =SUM(AW54:BE54) -> 143665 | CC54: =SUM(BG54:CB54) -> 0 | CK54: =SUM(CD54:CJ54) -> 0 | CV54: 153683
A55: 80 | B55: 8065 | C55: Newark | D55: University Heights Charter School | F55: 114 | G55: 39373.186 | N55: =SUM(G55:M55) -> 39373.186 | Q55: 122930.81 | W55: 10043 | X55: 1051 | AF55: 962386 | AH55: 21150 | AU55: 579216 | AV55: =SUM(O55:AU55) -> 1696776.8 | BE55: 42522 | BF55: =SUM(AW55:BE55) -> 42522 | CC55: =SUM(BG55:CB55) -> 0 | CK55: =SUM(CD55:CJ55) -> 0 | CV55: 621738
A56: 80 | B56: 8140 | C56: Trenton | D56: Village Charter School | F56: 355 | G56: 113463.69 | I56: 2298132 | K56: 10473 | N56: =SUM(G56:M56) -> 2422068.7 | Q56: 513902.31 | W56: 42549 | AH56: 143801 | AI56: 687421 | AU56: 2829 | AV56: =SUM(O56:AU56) -> 1390502.3 | BC56: 245837 | BD56: 73568 | BE56: 61123 | BF56: =SUM(AW56:BE56) -> 380528 | CC56: =SUM(BG56:CB56) -> 0 | CK56: =SUM(CD56:CJ56) -> 0 | CV56: 393830
D57: TOTAL DOLLARS | F57: =SUM(F4:F56) -> 15738.8 | N57: =SUM(N4:N56) -> 36433757 | AV57: =SUM(AV4:AV56) -> 1.4025917e+08 | BF57: =SUM(BF4:BF56) -> 17954507 | CC57: =SUM(CC4:CC56) -> 996348 | CK57: =SUM(CK4:CK56) -> 172344 | CL57: =SUM(N57:CK57) -> 1.9581613e+08
D58: PER PUPIL REVENUE | N58: =N57/$F$57 -> 2314.9006 | AV58: =AV57/$F$57 -> 8911.6816 | BF58: =BF57/$F$57 -> 1140.7799 | CC58: =CC57/$F$57 -> 63.305208 | CK58: =CK57/$F$57 -> 10.950263 | CL58: =SUM(N58:CK58) -> 12441.618
A60: 80 | B60: 6220 | C60: Jersey City | D60: CREATE | F60: 518 | G60: 350113.88 | I60: 2299440 | N60: =SUM(G60:M60) -> 2649553.9 | Q60: 765719.12 | W60: 401004 | AH60: 136909 | AM60: 130654 | AN60: 112475 | AU60: 359020 | AV60: =SUM(O60:AU60) -> 1905781.1 | BC60: 264127 | BD60: 89487 | BE60: 175429 | BF60: =SUM(AW60:BE60) -> 529043 | BR60: 101343 | CC60: =SUM(BG60:CB60) -> 101343 | CK60: =SUM(CD60:CJ60) -> 0 | CV60: 1131192
A61: 80 | B61: 6235 | C61: Jersey City | D61: Liberty Academy Charter School | F61: 337 | G61: 273261.16 | N61: =SUM(G61:M61) -> 273261.16 | Q61: 584910.84 | W61: 153008 | X61: 5840 | AF61: 2484819 | AH61: 76818 | AV61: =SUM(O61:AU61) -> 3305395.8 | BC61: 297746 | BD61: 49919 | BE61: 53825 | BF61: =SUM(AW61:BE61) -> 401490 | CC61: =SUM(BG61:CB61) -> 0 | CK61: =SUM(CD61:CJ61) -> 0 | CV61: 401490
A62: 80 | B62: 6910 | C62: Jersey City | D62: Jersey City Community Charter School | F62: 505 | G62: 348970.78 | N62: =SUM(G62:M62) -> 348970.78 | O62: 2276775 | Q62: 743587.22 | W62: 60091 | AF62: 1305249 | AH62: 132000 | AV62: =SUM(O62:AU62) -> 4517702.2 | BC62: 670116 | BD62: 85170 | BE62: 48289 | BF62: =SUM(AW62:BE62) -> 803575 | BO62: 65022 | BP62: 64684 | CC62: =SUM(BG62:CB62) -> 129706 | CK62: =SUM(CD62:CJ62) -> 0 | CV62: 803575
A63: 80 | B63: 6915 | C63: Jersey City | D63: Jersey City Golden Door Charter School | F63: 494 | G63: 368589.86 | N63: =SUM(G63:M63) -> 368589.86 | Q63: 806127.14 | W63: 132810 | AF63: 3753870 | AH63: 161209 | AU63: 1892 | AV63: =SUM(O63:AU63) -> 4855908.1 | BC63: 300676 | BD63: 96131 | BE63: 70581 | BF63: =SUM(AW63:BE63) -> 467388 | CC63: =SUM(BG63:CB63) -> 0 | CK63: =SUM(CD63:CJ63) -> 0 | CV63: 469280
A64: 80 | B64: 7115 | C64: Jersey City | D64: Learning Community Charter School | F64: 322 | G64: 266399.35 | I64: 1613923 | K64: 88637 | N64: =SUM(G64:M64) -> 1968959.4 | Q64: 582630.65 | U64: 122868 | W64: 150221 | X64: 2336 | AF64: 562084 | AG64: 118066 | AV64: =SUM(O64:AU64) -> 1538205.6 | BC64: 125760 | BD64: 48427 | BF64: =SUM(AW64:BE64) -> 174187 | CC64: =SUM(BG64:CB64) -> 0 | CK64: =SUM(CD64:CJ64) -> 0 | CV64: 262824
A65: 80 | B65: 7820 | C65: Jersey City | D65: Schomburg Charter School | F65: 165 | G65: 12769.284 | N65: =SUM(G65:M65) -> 12769.284 | O65: 2267098 | Q65: 27583.716 | W65: 119103 | AF65: 830064 | AH65: 25762 | AV65: =SUM(O65:AU65) -> 3269610.7 | BC65: 451349 | BD65: 110363 | BE65: 60496 | BF65: =SUM(AW65:BE65) -> 622208 | CC65: =SUM(BG65:CB65) -> 0 | CK65: =SUM(CD65:CJ65) -> 0 | CV65: 622208
A66: 80 | B66: 7830 | C66: Jersey City | D66: Soaring Heights Charter School | F66: 201 | G66: 157492.93 | N66: =SUM(G66:M66) -> 157492.93 | Q66: 344446.07 | W66: 65649 | AF66: 1511178 | AH66: 63139 | AI66: 917 | AV66: =SUM(O66:AU66) -> 1985329.1 | BC66: 147039 | BD66: 48074 | BE66: 20875 | BF66: =SUM(AW66:BE66) -> 215988 | CC66: =SUM(BG66:CB66) -> 0 | CK66: =SUM(CD66:CJ66) -> 0 | CV66: 215988
A67: 80 | B67: 8060 | C67: Jersey City | D67: University Academy Charter High School | F67: 405 | G67: 354483.74 | K67: 5167 | N67: =SUM(G67:M67) -> 359650.74 | Q67: 775276.26 | W67: 135570 | AF67: 2847849 | AH67: 158898 | AU67: 4851 | AV67: =SUM(O67:AU67) -> 3922444.3 | BC67: 81743 | BD67: 54552 | BE67: 7370 | BF67: =SUM(AW67:BE67) -> 143665 | CC67: =SUM(BG67:CB67) -> 0 | CK67: =SUM(CD67:CJ67) -> 0 | CV67: 153683
D68: TOTAL DOLLARS | F68: =SUM(F60:F67) -> 2947 | N68: =SUM(N60:N67) -> 6139248 | AV68: =SUM(AV60:AV67) -> 25300377 | BF68: =SUM(BF60:BF67) -> 3357544 | CC68: =SUM(CC60:CC67) -> 231049 | CK68: =SUM(CK60:CK67) -> 0 | CL68: =SUM(N68:CK68) -> 35028218
D69: PER PUPIL REVENUE | N69: =N68/$F$68 -> 2083.2195 | AV69: =AV68/$F$68 -> 8585.1296 | BF69: =BF68/$F$68 -> 1139.3091 | CC69: =CC68/$F$68 -> 78.401425 | CK69: =CK68/$F$68 -> 0 | CL69: =SUM(N69:CK69) -> 11886.06
A71: 80 | B71: 6320 | C71: Newark | D71: Discovery Charter | F71: 75 | G71: 33429.267 | K71: 53000 | N71: =SUM(G71:M71) -> 86429.267 | Q71: 104372.73 | W71: 53080 | AF71: 563805 | AH71: 21326 | AV71: =SUM(O71:AU71) -> 742583.73 | BC71: 43088 | BD71: 10660 | BE71: 287792 | BF71: =SUM(AW71:BE71) -> 341540 | CC71: =SUM(BG71:CB71) -> 0 | CK71: =SUM(CD71:CJ71) -> 0 | CV71: 394540
A72: 80 | B72: 6665 | C72: Newark | D72: Gray Charter School | F72: 306 | G72: 140740.99 | N72: =SUM(G72:M72) -> 140740.99 | Q72: 439421.01 | AF72: 2443362 | AH72: 74931 | AU72: 4000 | AV72: =SUM(O72:AU72) -> 2961714 | BC72: 234750 | BE72: 30398 | BF72: =SUM(AW72:BE72) -> 265148 | CC72: =SUM(BG72:CB72) -> 0 | CK72: =SUM(CD72:CJ72) -> 0 | CV72: 269148
A73: 80 | B73: 7100 | C73: Newark | D73: Lady Liberty Academy Charter School | F73: 443 | G73: 185215.1 | N73: =SUM(G73:M73) -> 185215.1 | Q73: 577992.9 | AF73: 3620192 | AH73: 161510 | AV73: =SUM(O73:AU73) -> 4359694.9 | BC73: 325286 | BD73: 96705 | BE73: 44518 | BF73: =SUM(AW73:BE73) -> 466509 | CC73: =SUM(BG73:CB73) -> 0 | CK73: =SUM(CD73:CJ73) -> 0 | CV73: 466509
A74: 80 | B74: 7210 | C74: Newark | D74: Marion P. Thomas Charter School | F74: 359 | G74: 153396.63 | N74: =SUM(G74:M74) -> 153396.63 | Q74: 478934.37 | AF74: 2939449 | AH74: 20004 | AV74: =SUM(O74:AU74) -> 3438387.4 | BC74: 350177 | BE74: 100700 | BF74: =SUM(AW74:BE74) -> 450877 | BU74: 27893 | CC74: =SUM(BG74:CB74) -> 27893 | CK74: =SUM(CD74:CJ74) -> 0 | CV74: 450877
A75: 80 | B75: 7280 | C75: Newark | D75: Greater Newark Charter School (formerly Newark, Greater Newark Academy Charter School | F75: 171.3 | G75: 83509.124 | K75: 10000 | N75: =SUM(G75:M75) -> 93509.124 | O75: 1056725 | Q75: 260731.88 | W75: 49386 | AD75: 162776 | AF75: 79312 | AH75: 61517 | AV75: =SUM(O75:AU75) -> 1670447.9 | AZ75: 11663 | BC75: 139803 | BD75: 29249 | BF75: =SUM(AW75:BE75) -> 180715 | BU75: 11176 | CC75: =SUM(BG75:CB75) -> 11176 | CK75: =SUM(CD75:CJ75) -> 0 | CV75: 190715
A76: 80 | B76: 7290 | C76: Newark | D76: New Horizons Community Charter School | F76: 508 | G76: 181243.19 | N76: =SUM(G76:M76) -> 181243.19 | Q76: 565876.81 | AF76: 3775494 | AH76: 144177 | AV76: =SUM(O76:AU76) -> 4485547.8 | BC76: 540738 | BD76: 80906 | BE76: 103550 | BF76: =SUM(AW76:BE76) -> 725194 | BH76: 4174 | CC76: =SUM(BG76:CB76) -> 4174 | CK76: =SUM(CD76:CJ76) -> 0 | CV76: 725194
A77: 80 | B77: 7320 | C77: Newark | D77: North Star Academy Charter School of Newark | F77: 451 | G77: 267018.1 | N77: =SUM(G77:M77) -> 267018.1 | Q77: 833682.9 | AF77: 3761939 | AH77: 212193 | AU77: 90688 | AV77: =SUM(O77:AU77) -> 4898502.9 | BC77: 402521 | BD77: 65204 | BE77: 239596 | BF77: =SUM(AW77:BE77) -> 707321 | CC77: =SUM(BG77:CB77) -> 0 | CK77: =SUM(CD77:CJ77) -> 0 | CV77: 798009
A78: 80 | B78: 7325 | C78: Newark | D78: TEAM Academy Charter School | F78: 467 | G78: 274966.61 | I78: 2699210 | K78: 192750 | N78: =SUM(G78:M78) -> 3166926.6 | Q78: 860282.39 | W78: 129781 | AF78: 634003 | AH78: 124814 | AV78: =SUM(O78:AU78) -> 1748880.4 | BC78: 317673 | BD78: 70308 | BE78: 22954 | BF78: =SUM(AW78:BE78) -> 410935 | CC78: =SUM(BG78:CB78) -> 0 | CK78: =SUM(CD78:CJ78) -> 0 | CV78: 603685
A79: 80 | B79: 7730 | C79: Newark | D79: Robert Treat Academy Charter School | F79: 450 | G79: 213881.86 | K79: 25000 | N79: =SUM(G79:M79) -> 238881.86 | O79: 2505594 | Q79: 667781.14 | W79: 86079 | X79: 4672 | AF79: 580524 | AG79: 160867 | AH79: 141191 | AM79: 206868 | AV79: =SUM(O79:AU79) -> 4353576.1 | BC79: 237658 | BD79: 80521 | BE79: 136716 | BF79: =SUM(AW79:BE79) -> 454895 | CC79: =SUM(BG79:CB79) -> 0 | CK79: =SUM(CD79:CJ79) -> 0 | CT79: 365036 | CV79: 1051799
A80: 80 | B80: 7735 | C80: Newark | D80: Maria L. Varisco-Rogers Charter School | F80: 112 | G80: 53034.107 | N80: =SUM(G80:M80) -> 53034.107 | P80: 666580 | Q80: 165582.89 | AF80: 205885 | AH80: 24171 | AM80: 50884 | AO80: 32507 | AV80: =SUM(O80:AU80) -> 1145609.9 | AX80: 163911 | BF80: =SUM(AW80:BE80) -> 163911 | CC80: =SUM(BG80:CB80) -> 0 | CK80: =SUM(CD80:CJ80) -> 0 | CV80: 247302
A81: 80 | B81: 8065 | C81: Newark | D81: University Heights Charter School | F81: 114 | G81: 39373.186 | N81: =SUM(G81:M81) -> 39373.186 | Q81: 122930.81 | W81: 10043 | X81: 1051 | AF81: 962386 | AH81: 21150 | AU81: 579216 | AV81: =SUM(O81:AU81) -> 1696776.8 | BE81: 42522 | BF81: =SUM(AW81:BE81) -> 42522 | CC81: =SUM(BG81:CB81) -> 0 | CK81: =SUM(CD81:CJ81) -> 0 | CV81: 621738
D82: TOTAL DOLLARS | F82: =SUM(F71:F81) -> 3456.3 | N82: =SUM(N71:N81) -> 4605768.2 | AV82: =SUM(AV71:AV81) -> 31501722 | BF82: =SUM(BF71:BF81) -> 4209567 | CC82: =SUM(CC71:CC81) -> 43243 | CK82: =SUM(CK71:CK81) -> 0 | CL82: =SUM(N82:CK82) -> 40360300
D83: PER PUPIL REVENUE | N83: =N82/$F$82 -> 1332.5719 | AV83: =AV82/$F$82 -> 9114.2904 | BF83: =BF82/$F$82 -> 1217.9403 | CC83: =CC82/$F$82 -> 12.511356 | CK83: =CK82/$F$82 -> 0 | CL83: =SUM(N83:CK83) -> 11677.314
A85: 80 | B85: 6425 | C85: Trenton | D85: Emily Fisher Charter | F85: 352 | G85: 111698.87 | N85: =SUM(G85:M85) -> 111698.87 | Q85: 512356.13 | W85: 1462240 | X85: 7290 | AF85: 2873003 | AH85: 99491 | AV85: =SUM(O85:AU85) -> 4954380.1 | BC85: 321978 | BD85: 63559 | BE85: 48003 | BF85: =SUM(AW85:BE85) -> 433540 | CC85: =SUM(BG85:CB85) -> 0 | CK85: =SUM(CD85:CJ85) -> 0 | CL85: =SUM(N85+AV85+BF85+CC85+CK85) -> 5499619 | CV85: 433540
A86: 80 | B86: 6810 | C86: Trenton | D86: International Charter School of Trenton | F86: 94.5 | G86: 29309.455 | N86: =SUM(G86:M86) -> 29309.455 | Q86: 134735.55 | W86: 50525 | AF86: 753481 | AH86: 35679 | AU86: 1638 | AV86: =SUM(O86:AU86) -> 976058.55 | BC86: 72658 | BD86: 26141 | BE86: 26029 | BF86: =SUM(AW86:BE86) -> 124828 | CC86: =SUM(BG86:CB86) -> 0 | CK86: =SUM(CD86:CJ86) -> 0 | CL86: =SUM(N86+AV86+BF86+CC86+CK86) -> 1130196 | CV86: 126466
A87: 80 | B87: 7901 | C87: Trenton | D87: Trenton Community Charter School (consolidated school in 2001) | F87: 621 | G87: 166017.53 | N87: =SUM(G87:M87) -> 166017.53 | Q87: 763182.47 | W87: 206107 | X87: 2336 | AF87: 5005974 | AH87: 201848 | AU87: 847 | AV87: =SUM(O87:AU87) -> 6180294.5 | BC87: 566517 | BD87: 153456 | BE87: 103731 | BF87: =SUM(AW87:BE87) -> 823704 | CC87: =SUM(BG87:CB87) -> 0 | CK87: =SUM(CD87:CJ87) -> 0 | CL87: =SUM(N87+AV87+BF87+CC87+CK87) -> 7170016 | CV87: 824551
A88: 80 | B88: 8140 | C88: Trenton | D88: Village Charter School | F88: 355 | G88: 113463.69 | I88: 2298132 | K88: 10473 | N88: =SUM(G88:M88) -> 2422068.7 | Q88: 513902.31 | W88: 42549 | AH88: 143801 | AI88: 687421 | AU88: 2829 | AV88: =SUM(O88:AU88) -> 1390502.3 | BC88: 245837 | BD88: 73568 | BE88: 61123 | BF88: =SUM(AW88:BE88) -> 380528 | CC88: =SUM(BG88:CB88) -> 0 | CK88: =SUM(CD88:CJ88) -> 0 | CL88: =SUM(N88+AV88+BF88+CC88+CK88) -> 4193099 | CV88: 393830
D89: TOTAL DOLLARS | F89: =SUM(F85:F88) -> 1422.5 | N89: =SUM(N85:N88) -> 2729094.5 | AV89: =SUM(AV85:AV88) -> 13501235 | BF89: =SUM(BF85:BF88) -> 1762600 | CC89: =SUM(CC85:CC88) -> 0 | CK89: =SUM(CK85:CK88) -> 0 | CL89: =SUM(N89:CK89) -> 17992930
D90: PER PUPIL REVENUE | N90: =N89/$F$89 -> 1918.5199 | AV90: =AV89/$F$89 -> 9491.2024 | BF90: =BF89/$F$89 -> 1239.0861 | CC90: =CC89/$F$89 -> 0 | CK90: =CK89/$F$89 -> 0 | CL90: =SUM(N90:CK90) -> 12648.808
C138: district aligned properly
C139: don't know if district is aligned properly | F139: Missing enrollment data from state web file. Enrollment data used for these charters originates from the FY2006-07 Enrollments and State Aid Payments to Charter Schools Based on Final Enrollment
C140: If white, need to determine if in an Abbott district

Sheet rev send dist only
G1: Revenue Local | H1: Local | I1: Revenue Local | J1: Total Local Revenues for Charter Distribution Calculation | L1: Revenue State | M1: State | N1: State | O1: Total State Revenue for Charter Distribution Calculation only
A2: CO | B2: DIST | C2: CONAME | D2: DISTNAME | F2: Enrollment | G2: Local Tax Levy | H2: County Tax Levy | I2: Unrestricted Misc Revenues | L2: Core Curriculum Standards Aid | M2: Supplemental Core Curriculum Standards Aid | N2: Stabilization Aid
G3: L150 | H3: L160 | I3: L253 | J3: L273 | L3: L280 | M3: L281 | N3: L340
A4: 1 | B4: 10 | C4: ATLANTIC | D4: ABSECON CITY | E4: 0010-ABSECON CITY | F4: 847 | G4: 8172525 | I4: 71494 | J4: =SUM(G4:I4) -> 8244019 | L4: 344397 | O4: =SUM(L4:N4) -> 344397
A5: 1 | B5: 110 | C5: ATLANTIC | D5: ATLANTIC CITY | E5: 0110-ATLANTIC CITY | F5: 6974 | G5: 93056124 | I5: 2460789 | J5: =SUM(G5:I5) -> 95516913 | O5: =SUM(L5:N5) -> 0
A6: 1 | B6: 120 | C6: ATLANTIC | D6: ATLANTIC CO VOCATIONAL | E6: 0120-ATLANTIC CO VOCATIONAL | F6: 532.5 | H6: 3624000 | I6: 339613 | J6: =SUM(G6:I6) -> 3963613 | L6: 1094318 | N6: 1928 | O6: =SUM(L6:N6) -> 1096246
A7: 1 | B7: 125 | C7: ATLANTIC | D7: ATLANTIC CO SPECIAL SERV | E7: 0125-ATLANTIC CO SPECIAL SERV | F7: 464 | H7: 1854000 | I7: 217626 | J7: =SUM(G7:I7) -> 2071626 | O7: =SUM(L7:N7) -> 0
A8: 1 | B8: 570 | C8: ATLANTIC | D8: BRIGANTINE CITY | E8: 0570-BRIGANTINE CITY | F8: 885 | G8: 13665336 | I8: 189857 | J8: =SUM(G8:I8) -> 13855193 | O8: =SUM(L8:N8) -> 0
A9: 1 | B9: 590 | C9: ATLANTIC | D9: BUENA REGIONAL | E9: 0590-BUENA REGIONAL | F9: 2594 | G9: 11204236 | I9: 241073 | J9: =SUM(G9:I9) -> 11445309 | L9: 9091917 | N9: 299425 | O9: =SUM(L9:N9) -> 9391342
A10: 1 | B10: 960 | C10: ATLANTIC | D10: CORBIN CITY | G10: 763006 | I10: 5382 | J10: =SUM(G10:I10) -> 768388 | L10: 418411 | O10: =SUM(L10:N10) -> 418411
A11: 1 | B11: 1300 | C11: ATLANTIC | D11: EGG HARBOR CITY | E11: 1300-EGG HARBOR CITY | F11: 520 | G11: 1810936 | I11: 72013 | J11: =SUM(G11:I11) -> 1882949 | L11: 2389741 | M11: 394444 | N11: 161942 | O11: =SUM(L11:N11) -> 2946127
A12: 1 | B12: 1310 | C12: ATLANTIC | D12: EGG HARBOR TWP | E12: 1310-EGG HARBOR TWP | F12: 7484 | G12: 50843214 | I12: 1217010 | J12: =SUM(G12:I12) -> 52060224 | L12: 20341417 | O12: =SUM(L12:N12) -> 20341417
A13: 1 | B13: 1410 | C13: ATLANTIC | D13: ESTELL MANOR CITY | E13: 1410-ESTELL MANOR CITY | F13: 218 | G13: 1934320 | I13: 22739 | J13: =SUM(G13:I13) -> 1957059 | L13: 1486698 | O13: =SUM(L13:N13) -> 1486698
A14: 1 | B14: 1540 | C14: ATLANTIC | D14: FOLSOM BORO | E14: 1540-FOLSOM BORO | F14: 392 | G14: 1258908 | I14: 109391 | J14: =SUM(G14:I14) -> 1368299 | L14: 1033381 | N14: 396365 | O14: =SUM(L14:N14) -> 1429746
A15: 1 | B15: 1690 | C15: ATLANTIC | D15: GALLOWAY TWP | E15: 1690-GALLOWAY TWP | F15: 3791 | G15: 26335007 | I15: 354991 | J15: =SUM(G15:I15) -> 26689998 | L15: 13410623 | N15: 446658 | O15: =SUM(L15:N15) -> 13857281
A16: 1 | B16: 1790 | C16: ATLANTIC | D16: GREATER EGG HARBOR REG | E16: 1790-GREATER EGG HARBOR REG | F16: 3913.5 | G16: 25657864 | I16: 711737 | J16: =SUM(G16:I16) -> 26369601 | L16: 17921675 | O16: =SUM(L16:N16) -> 17921675
A17: 1 | B17: 1940 | C17: ATLANTIC | D17: HAMILTON TWP | E17: 1940-HAMILTON TWP | F17: 3225 | G17: 15007035 | I17: 431583 | J17: =SUM(G17:I17) -> 15438618 | L17: 9647111 | O17: =SUM(L17:N17) -> 9647111
A18: 1 | B18: 1960 | C18: ATLANTIC | D18: HAMMONTON TOWN | E18: 1960-HAMMONTON TOWN | F18: 3325.5 | G18: 14521766 | J18: =SUM(G18:I18) -> 14521766 | L18: 4337255 | O18: =SUM(L18:N18) -> 4337255
A19: 1 | B19: 2680 | C19: ATLANTIC | D19: LINWOOD CITY | E19: 2680-LINWOOD CITY | F19: 998 | G19: 9157885 | I19: 143739 | J19: =SUM(G19:I19) -> 9301624 | L19: 969200 | O19: =SUM(L19:N19) -> 969200
A20: 1 | B20: 2780 | C20: ATLANTIC | D20: LONGPORT | G20: 968994 | J20: =SUM(G20:I20) -> 968994 | N20: 71301 | O20: =SUM(L20:N20) -> 71301
A21: 1 | B21: 2910 | C21: ATLANTIC | D21: MAINLAND REGIONAL | E21: 2910-MAINLAND REGIONAL | F21: 1621.5 | G21: 13953238 | I21: 351148 | J21: =SUM(G21:I21) -> 14304386 | L21: 4640595 | O21: =SUM(L21:N21) -> 4640595
A22: 1 | B22: 3020 | C22: ATLANTIC | D22: MARGATE CITY | E22: 3020-MARGATE CITY | F22: 593 | G22: 10173118 | I22: 242872 | J22: =SUM(G22:I22) -> 10415990 | O22: =SUM(L22:N22) -> 0
A23: 1 | B23: 3480 | C23: ATLANTIC | D23: MULLICA TWP | E23: 3480-MULLICA TWP | F23: 744 | G23: 3085814 | I23: 34891 | J23: =SUM(G23:I23) -> 3120705 | L23: 3250225 | O23: =SUM(L23:N23) -> 3250225
A24: 1 | B24: 3720 | C24: ATLANTIC | D24: NORTHFIELD CITY | E24: 3720-NORTHFIELD CITY | F24: 1078 | G24: 7194807 | I24: 89378 | J24: =SUM(G24:I24) -> 7284185 | L24: 1852131 | O24: =SUM(L24:N24) -> 1852131
A25: 1 | B25: 4180 | C25: ATLANTIC | D25: PLEASANTVILLE CITY | E25: 4180-PLEASANTVILLE CITY | F25: 3423 | G25: 6220639 | I25: 367173 | J25: =SUM(G25:I25) -> 6587812 | L25: 25501280 | M25: 2062146 | O25: =SUM(L25:N25) -> 27563426
A26: 1 | B26: 4240 | C26: ATLANTIC | D26: PORT REPUBLIC CITY | E26: 4240-PORT REPUBLIC CITY | F26: 134 | G26: 1229445 | J26: =SUM(G26:I26) -> 1229445 | N26: 771685 | O26: =SUM(L26:N26) -> 771685
A27: 1 | B27: 4800 | C27: ATLANTIC | D27: SOMERS POINT CITY | E27: 4800-SOMERS POINT CITY | F27: 1124 | G27: 7861264 | I27: 126375 | J27: =SUM(G27:I27) -> 7987639 | L27: 1865875 | N27: 495568 | O27: =SUM(L27:N27) -> 2361443
A28: 1 | B28: 5350 | C28: ATLANTIC | D28: VENTNOR CITY | E28: 5350-VENTNOR CITY | F28: 947 | G28: 15597115 | I28: 104111 | J28: =SUM(G28:I28) -> 15701226 | N28: 100000 | O28: =SUM(L28:N28) -> 100000
A29: 1 | B29: 5760 | C29: ATLANTIC | D29: WEYMOUTH TWP | E29: 5760-WEYMOUTH TWP | F29: 258 | G29: 1631399 | J29: =SUM(G29:I29) -> 1631399 | L29: 1422519 | N29: 149066 | O29: =SUM(L29:N29) -> 1571585
A30: 3 | B30: 40 | C30: BERGEN | D30: ALLENDALE BORO | E30: 0040-ALLENDALE BORO | F30: 1032 | G30: 12025265 | J30: =SUM(G30:I30) -> 12025265 | O30: =SUM(L30:N30) -> 0
A31: 3 | B31: 80 | C31: BERGEN | D31: ALPINE BORO | E31: 0080-ALPINE BORO | F31: 136 | G31: 4660644 | I31: 155383 | J31: =SUM(G31:I31) -> 4816027 | O31: =SUM(L31:N31) -> 0
A32: 3 | B32: 285 | C32: BERGEN | D32: BERGEN CO SPECIAL SERVICE | E32: 0285-BERGEN CO SPECIAL SERVICE | F32: 1025 | H32: 5766582 | I32: 928679 | J32: =SUM(G32:I32) -> 6695261 | O32: =SUM(L32:N32) -> 0
A33: 3 | B33: 290 | C33: BERGEN | D33: BERGEN COUNTY VOCATIONAL | E33: 0290-BERGEN COUNTY VOCATIONAL | F33: 2089 | H33: 22567423 | I33: 658561 | J33: =SUM(G33:I33) -> 23225984 | O33: =SUM(L33:N33) -> 0
A34: 3 | B34: 300 | C34: BERGEN | D34: BERGENFIELD BORO | E34: 0300-BERGENFIELD BORO | F34: 3619 | G34: 39876425 | I34: 160847 | J34: =SUM(G34:I34) -> 40037272 | L34: 4868281 | O34: =SUM(L34:N34) -> 4868281
A35: 3 | B35: 440 | C35: BERGEN | D35: BOGOTA BORO | E35: 0440-BOGOTA BORO | F35: 1182 | G35: 10238743 | I35: 15478 | J35: =SUM(G35:I35) -> 10254221 | L35: 2138184 | N35: 848968 | O35: =SUM(L35:N35) -> 2987152
A36: 3 | B36: 740 | C36: BERGEN | D36: CARLSTADT BORO | E36: 0740-CARLSTADT BORO | F36: 549.5 | G36: 7349150 | I36: 51799 | J36: =SUM(G36:I36) -> 7400949 | O36: =SUM(L36:N36) -> 0
A37: 3 | B37: 745 | C37: BERGEN | D37: CARLSTADT-EAST RUTHERFORD | E37: 0745-CARLSTADT-EAST RUTHERFORD | F37: 522.5 | G37: 9850324 | I37: 208302 | J37: =SUM(G37:I37) -> 10058626 | N37: 130865 | O37: =SUM(L37:N37) -> 130865
A38: 3 | B38: 890 | C38: BERGEN | D38: CLIFFSIDE PARK BORO | E38: 0890-CLIFFSIDE PARK BORO | F38: 2617 | G38: 23525325 | J38: =SUM(G38:I38) -> 23525325 | O38: =SUM(L38:N38) -> 0
A39: 3 | B39: 930 | C39: BERGEN | D39: CLOSTER BORO | E39: 0930-CLOSTER BORO | F39: 1183 | G39: 13720585 | I39: 99983 | J39: =SUM(G39:I39) -> 13820568 | O39: =SUM(L39:N39) -> 0
A40: 3 | B40: 990 | C40: BERGEN | D40: CRESSKILL BORO | E40: 0990-CRESSKILL BORO | F40: 1741 | G40: 18521666 | I40: 127890 | J40: =SUM(G40:I40) -> 18649556 | O40: =SUM(L40:N40) -> 0
A41: 3 | B41: 1070 | C41: BERGEN | D41: DEMAREST BORO | E41: 1070-DEMAREST BORO | F41: 708 | G41: 9893854 | I41: 167411 | J41: =SUM(G41:I41) -> 10061265 | O41: =SUM(L41:N41) -> 0
A42: 3 | B42: 1130 | C42: BERGEN | D42: DUMONT BORO | E42: 1130-DUMONT BORO | F42: 2678.5 | G42: 27173953 | I42: 322978 | J42: =SUM(G42:I42) -> 27496931 | L42: 4728390 | O42: =SUM(L42:N42) -> 4728390
A43: 3 | B43: 1230 | C43: BERGEN | D43: EAST RUTHERFORD BORO | E43: 1230-EAST RUTHERFORD BORO | F43: 730 | G43: 10337154 | I43: 120348 | J43: =SUM(G43:I43) -> 10457502 | O43: =SUM(L43:N43) -> 0
A44: 3 | B44: 1270 | C44: BERGEN | D44: EDGEWATER BORO | E44: 1270-EDGEWATER BORO | F44: 424 | G44: 10863869 | I44: 71497 | J44: =SUM(G44:I44) -> 10935366 | O44: =SUM(L44:N44) -> 0
A45: 3 | B45: 1345 | C45: BERGEN | D45: ELMWOOD PARK | E45: 1345-ELMWOOD PARK | F45: 2142 | G45: 23573986 | I45: 250916 | J45: =SUM(G45:I45) -> 23824902 | O45: =SUM(L45:N45) -> 0
A46: 3 | B46: 1360 | C46: BERGEN | D46: EMERSON BORO | E46: 1360-EMERSON BORO | F46: 1168 | G46: 13943163 | I46: 430504 | J46: =SUM(G46:I46) -> 14373667 | O46: =SUM(L46:N46) -> 0
A47: 3 | B47: 1370 | C47: BERGEN | D47: ENGLEWOOD CITY | E47: 1370-ENGLEWOOD CITY | F47: 2693.5 | G47: 40600443 | I47: 2691799 | J47: =SUM(G47:I47) -> 43292242 | N47: 103107 | O47: =SUM(L47:N47) -> 103107
A48: 3 | B48: 1380 | C48: BERGEN | D48: ENGLEWOOD CLIFFS BORO | E48: 1380-ENGLEWOOD CLIFFS BORO | F48: 421 | G48: 8376177 | I48: 88602 | J48: =SUM(G48:I48) -> 8464779 | N48: 10497 | O48: =SUM(L48:N48) -> 10497
A49: 3 | B49: 1450 | C49: BERGEN | D49: FAIR LAWN BORO | E49: 1450-FAIR LAWN BORO | F49: 4732.5 | G49: 61516737 | J49: =SUM(G49:I49) -> 61516737 | O49: =SUM(L49:N49) -> 0
A50: 3 | B50: 1470 | C50: BERGEN | D50: FAIRVIEW BORO | E50: 1470-FAIRVIEW BORO | F50: 1028 | G50: 11056569 | I50: 218588 | J50: =SUM(G50:I50) -> 11275157 | L50: 2026323 | N50: 918394 | O50: =SUM(L50:N50) -> 2944717
A51: 3 | B51: 1550 | C51: BERGEN | D51: FORT LEE BORO | E51: 1550-FORT LEE BORO | F51: 3454 | G51: 42581845 | I51: 451452 | J51: =SUM(G51:I51) -> 43033297 | O51: =SUM(L51:N51) -> 0
A52: 3 | B52: 1580 | C52: BERGEN | D52: FRANKLIN LAKES BORO | E52: 1580-FRANKLIN LAKES BORO | F52: 1501 | G52: 20267099 | I52: 131258 | J52: =SUM(G52:I52) -> 20398357 | O52: =SUM(L52:N52) -> 0
A53: 3 | B53: 1700 | C53: BERGEN | D53: GARFIELD CITY | E53: 1700-GARFIELD CITY | F53: 4591 | G53: 20348191 | I53: 856229 | J53: =SUM(G53:I53) -> 21204420 | L53: 13587511 | O53: =SUM(L53:N53) -> 13587511
A54: 3 | B54: 1760 | C54: BERGEN | D54: GLEN ROCK BORO | E54: 1760-GLEN ROCK BORO | F54: 2473 | G54: 33730381 | I54: 318594 | J54: =SUM(G54:I54) -> 34048975 | N54: 162279 | O54: =SUM(L54:N54) -> 162279
A55: 3 | B55: 1860 | C55: BERGEN | D55: HACKENSACK CITY | E55: 1860-HACKENSACK CITY | F55: 4881 | G55: 53452727 | I55: 874143 | J55: =SUM(G55:I55) -> 54326870 | N55: 1689 | O55: =SUM(L55:N55) -> 1689
A56: 3 | B56: 2050 | C56: BERGEN | D56: HARRINGTON PARK BORO | E56: 2050-HARRINGTON PARK BORO | F56: 704 | G56: 8245695 | I56: 60122 | J56: =SUM(G56:I56) -> 8305817 | O56: =SUM(L56:N56) -> 0
A57: 3 | B57: 2080 | C57: BERGEN | D57: HASBROUCK HEIGHTS BORO | E57: 2080-HASBROUCK HEIGHTS BORO | F57: 1556 | G57: 18764451 | I57: 114387 | J57: =SUM(G57:I57) -> 18878838 | O57: =SUM(L57:N57) -> 0
A58: 3 | B58: 2090 | C58: BERGEN | D58: HAWORTH BORO | E58: 2090-HAWORTH BORO | F58: 528 | G58: 6249910 | I58: 42429 | J58: =SUM(G58:I58) -> 6292339 | N58: 63041 | O58: =SUM(L58:N58) -> 63041
A59: 3 | B59: 2180 | C59: BERGEN | D59: HILLSDALE BORO | E59: 2180-HILLSDALE BORO | F59: 1455 | G59: 14542646 | I59: 71542 | J59: =SUM(G59:I59) -> 14614188 | O59: =SUM(L59:N59) -> 0
A60: 3 | B60: 2200 | C60: BERGEN | D60: HO HO KUS BORO | E60: 2200-HO HO KUS BORO | F60: 670 | G60: 9458497 | I60: 124762 | J60: =SUM(G60:I60) -> 9583259 | O60: =SUM(L60:N60) -> 0
A61: 3 | B61: 2620 | C61: BERGEN | D61: LEONIA BORO | E61: 2620-LEONIA BORO | F61: 1731.5 | G61: 14333093 | I61: 51765 | J61: =SUM(G61:I61) -> 14384858 | L61: 1395172 | O61: =SUM(L61:N61) -> 1395172
A62: 3 | B62: 2710 | C62: BERGEN | D62: LITTLE FERRY BORO | E62: 2710-LITTLE FERRY BORO | F62: 975 | G62: 13285276 | I62: 179812 | J62: =SUM(G62:I62) -> 13465088 | O62: =SUM(L62:N62) -> 0
A63: 3 | B63: 2740 | C63: BERGEN | D63: LODI BOROUGH | E63: 2740-LODI BOROUGH | F63: 3168.5 | G63: 30866646 | I63: 485896 | J63: =SUM(G63:I63) -> 31352542 | L63: 5210513 | O63: =SUM(L63:N63) -> 5210513
A64: 3 | B64: 2860 | C64: BERGEN | D64: LYNDHURST TWP | E64: 2860-LYNDHURST TWP | F64: 2205.5 | G64: 25756895 | I64: 218770 | J64: =SUM(G64:I64) -> 25975665 | N64: 69889 | O64: =SUM(L64:N64) -> 69889
A65: 3 | B65: 2900 | C65: BERGEN | D65: MAHWAH TWP | E65: 2900-MAHWAH TWP | F65: 3394.5 | G65: 45107181 | I65: 572439 | J65: =SUM(G65:I65) -> 45679620 | O65: =SUM(L65:N65) -> 0
A66: 3 | B66: 3060 | C66: BERGEN | D66: MAYWOOD BORO | E66: 3060-MAYWOOD BORO | F66: 860 | G66: 13037857 | J66: =SUM(G66:I66) -> 13037857 | O66: =SUM(L66:N66) -> 0
A67: 3 | B67: 3170 | C67: BERGEN | D67: MIDLAND PARK BORO | E67: 3170-MIDLAND PARK BORO | F67: 1131 | G67: 14448910 | I67: 164665 | J67: =SUM(G67:I67) -> 14613575 | O67: =SUM(L67:N67) -> 0
A68: 3 | B68: 3330 | C68: BERGEN | D68: MONTVALE BORO | E68: 3330-MONTVALE BORO | F68: 1007 | G68: 11418991 | I68: 133721 | J68: =SUM(G68:I68) -> 11552712 | O68: =SUM(L68:N68) -> 0
A69: 3 | B69: 3350 | C69: BERGEN | D69: MOONACHIE BORO | E69: 3350-MOONACHIE BORO | F69: 264 | G69: 5527255 | J69: =SUM(G69:I69) -> 5527255 | O69: =SUM(L69:N69) -> 0
A70: 3 | B70: 3550 | C70: BERGEN | D70: NEW MILFORD BORO | E70: 3550-NEW MILFORD BORO | F70: 1989.5 | G70: 22156722 | I70: 195304 | J70: =SUM(G70:I70) -> 22352026 | O70: =SUM(L70:N70) -> 0
A71: 3 | B71: 3600 | C71: BERGEN | D71: NORTH ARLINGTON BORO | E71: 3600-NORTH ARLINGTON BORO | F71: 1577 | G71: 17526121 | I71: 213745 | J71: =SUM(G71:I71) -> 17739866 | O71: =SUM(L71:N71) -> 0
A72: 3 | B72: 3700 | C72: BERGEN | D72: NORTHERN HIGHLANDS REG | E72: 3700-NORTHERN HIGHLANDS REG | F72: 1268.5 | G72: 16298379 | I72: 251891 | J72: =SUM(G72:I72) -> 16550270 | O72: =SUM(L72:N72) -> 0
A73: 3 | B73: 3710 | C73: BERGEN | D73: NORTHERN VALLEY REGIONAL | E73: 3710-NORTHERN VALLEY REGIONAL | F73: 2453 | G73: 37517322 | I73: 953541 | J73: =SUM(G73:I73) -> 38470863 | N73: 35026 | O73: =SUM(L73:N73) -> 35026
A74: 3 | B74: 3730 | C74: BERGEN | D74: NORTHVALE BORO | E74: 3730-NORTHVALE BORO | F74: 577 | G74: 6362000 | I74: 30478 | J74: =SUM(G74:I74) -> 6392478 | N74: 47315 | O74: =SUM(L74:N74) -> 47315
A75: 3 | B75: 3740 | C75: BERGEN | D75: NORWOOD BORO | E75: 3740-NORWOOD BORO | F75: 641 | G75: 7119914 | I75: 36675 | J75: =SUM(G75:I75) -> 7156589 | N75: 61099 | O75: =SUM(L75:N75) -> 61099
A76: 3 | B76: 3760 | C76: BERGEN | D76: OAKLAND BORO | E76: 3760-OAKLAND BORO | F76: 1722 | G76: 21459443 | J76: =SUM(G76:I76) -> 21459443 | O76: =SUM(L76:N76) -> 0
A77: 3 | B77: 3850 | C77: BERGEN | D77: OLD TAPPAN BORO | E77: 3850-OLD TAPPAN BORO | F77: 869 | G77: 10284928 | I77: 190333 | J77: =SUM(G77:I77) -> 10475261 | N77: 360438 | O77: =SUM(L77:N77) -> 360438
A78: 3 | B78: 3870 | C78: BERGEN | D78: ORADELL BORO | E78: 3870-ORADELL BORO | F78: 791 | G78: 7681644 | I78: 45889 | J78: =SUM(G78:I78) -> 7727533 | O78: =SUM(L78:N78) -> 0
A79: 3 | B79: 3910 | C79: BERGEN | D79: PALISADES PARK | E79: 3910-PALISADES PARK | F79: 1518 | G79: 16269671 | I79: 225358 | J79: =SUM(G79:I79) -> 16495029 | N79: 176935 | O79: =SUM(L79:N79) -> 176935
A80: 3 | B80: 3930 | C80: BERGEN | D80: PARAMUS BORO | E80: 3930-PARAMUS BORO | F80: 4292.5 | G80: 57512840 | I80: 1221599 | J80: =SUM(G80:I80) -> 58734439 | O80: =SUM(L80:N80) -> 0
A81: 3 | B81: 3940 | C81: BERGEN | D81: PARK RIDGE BORO | E81: 3940-PARK RIDGE BORO | F81: 1352.5 | G81: 18869664 | I81: 214915 | J81: =SUM(G81:I81) -> 19084579 | O81: =SUM(L81:N81) -> 0
A82: 3 | B82: 3960 | C82: BERGEN | D82: PASCACK VALLEY REGIONAL | E82: 3960-PASCACK VALLEY REGIONAL | F82: 1831.5 | G82: 31336279 | I82: 276587 | J82: =SUM(G82:I82) -> 31612866 | O82: =SUM(L82:N82) -> 0
A83: 3 | B83: 4300 | C83: BERGEN | D83: RAMAPO-INDIAN HILL REG | E83: 4300-RAMAPO-INDIAN HILL REG | F83: 2282 | G83: 38678558 | I83: 374824 | J83: =SUM(G83:I83) -> 39053382 | O83: =SUM(L83:N83) -> 0
A84: 3 | B84: 4310 | C84: BERGEN | D84: RAMSEY BORO | E84: 4310-RAMSEY BORO | F84: 3097 | G84: 39011486 | I84: 270321 | J84: =SUM(G84:I84) -> 39281807 | O84: =SUM(L84:N84) -> 0
A85: 3 | B85: 4370 | C85: BERGEN | D85: RIDGEFIELD BORO | E85: 4370-RIDGEFIELD BORO | F85: 2045 | G85: 12826957 | I85: 330695 | J85: =SUM(G85:I85) -> 13157652 | L85: 911179 | O85: =SUM(L85:N85) -> 911179
A86: 3 | B86: 4380 | C86: BERGEN | D86: RIDGEFIELD PARK TWP | E86: 4380-RIDGEFIELD PARK TWP | F86: 2078 | G86: 19431797 | I86: 287944 | J86: =SUM(G86:I86) -> 19719741 | L86: 328787 | N86: 1357673 | O86: =SUM(L86:N86) -> 1686460
A87: 3 | B87: 4390 | C87: BERGEN | D87: RIDGEWOOD VILLAGE | E87: 4390-RIDGEWOOD VILLAGE | F87: 5625.5 | G87: 67994062 | I87: 956061 | J87: =SUM(G87:I87) -> 68950123 | O87: =SUM(L87:N87) -> 0
A88: 3 | B88: 4405 | C88: BERGEN | D88: RIVER DELL REGIONAL | E88: 4405-RIVER DELL REGIONAL | F88: 1493 | G88: 20393526 | I88: 339696 | J88: =SUM(G88:I88) -> 20733222 | N88: 81024 | O88: =SUM(L88:N88) -> 81024
A89: 3 | B89: 4410 | C89: BERGEN | D89: RIVER EDGE BORO | E89: 4410-RIVER EDGE BORO | F89: 1126 | G89: 10462823 | I89: 161604 | J89: =SUM(G89:I89) -> 10624427 | O89: =SUM(L89:N89) -> 0
A90: 3 | B90: 4430 | C90: BERGEN | D90: RIVER VALE TWP | E90: 4430-RIVER VALE TWP | F90: 1357 | G90: 15429737 | J90: =SUM(G90:I90) -> 15429737 | O90: =SUM(L90:N90) -> 0
A91: 3 | B91: 4470 | C91: BERGEN | D91: ROCHELLE PARK TWP | E91: 4470-ROCHELLE PARK TWP | F91: 480 | G91: 8441799 | I91: 68848 | J91: =SUM(G91:I91) -> 8510647 | O91: =SUM(L91:N91) -> 0
A92: 3 | B92: 4500 | C92: BERGEN | D92: ROCKLEIGH | G92: 391267 | J92: =SUM(G92:I92) -> 391267 | O92: =SUM(L92:N92) -> 0
A93: 3 | B93: 4600 | C93: BERGEN | D93: RUTHERFORD BORO | E93: 4600-RUTHERFORD BORO | F93: 2456 | G93: 30302192 | I93: 163295 | J93: =SUM(G93:I93) -> 30465487 | N93: 812880 | O93: =SUM(L93:N93) -> 812880
A94: 3 | B94: 4610 | C94: BERGEN | D94: SADDLE BROOK TWP | E94: 4610-SADDLE BROOK TWP | F94: 1593 | G94: 20753135 | J94: =SUM(G94:I94) -> 20753135 | O94: =SUM(L94:N94) -> 0
A95: 3 | B95: 4620 | C95: BERGEN | D95: SADDLE RIVER BORO | E95: 4620-SADDLE RIVER BORO | F95: 224 | G95: 6289800 | I95: 6391 | J95: =SUM(G95:I95) -> 6296191 | O95: =SUM(L95:N95) -> 0
A96: 3 | B96: 4845 | C96: BERGEN | D96: SOUTH BERGEN JOINTURE COM | E96: 4845-SOUTH BERGEN JOINTURE COM | F96: 321 | I96: 2809514 | J96: =SUM(G96:I96) -> 2809514 | O96: =SUM(L96:N96) -> 0
A97: 3 | B97: 4870 | C97: BERGEN | D97: SOUTH HACKENSACK TWP | E97: 4870-SOUTH HACKENSACK TWP | F97: 233 | G97: 5091935 | I97: 160118 | J97: =SUM(G97:I97) -> 5252053 | O97: =SUM(L97:N97) -> 0
A98: 3 | B98: 5150 | C98: BERGEN | D98: TEANECK TWP | E98: 5150-TEANECK TWP | F98: 4148 | G98: 71386061 | I98: 450724 | J98: =SUM(G98:I98) -> 71836785 | O98: =SUM(L98:N98) -> 0
A99: 3 | B99: 5160 | C99: BERGEN | D99: TENAFLY BORO | E99: 5160-TENAFLY BORO | F99: 3394 | G99: 43105141 | I99: 655011 | J99: =SUM(G99:I99) -> 43760152 | O99: =SUM(L99:N99) -> 0
A100: 3 | B100: 5170 | C100: BERGEN | D100: TETERBORO | G100: 95316 | J100: =SUM(G100:I100) -> 95316 | N100: 580 | O100: =SUM(L100:N100) -> 580
...

Sheet Master
A1: CO | B1: DIST | C1: CONAME | D1: DISTNAME | E1: L16 | F1: L20 | G1: L24 | H1: L25 | I1: L50 | J1: L60 | K1: L70 | L1: L75 | M1: L80 | N1: L90 | O1: L100 | P1: L140 | Q1: L150 | R1: L196 | S1: L200 | T1: L242 | U1: L251 | V1: L253 | W1: L260 | X1: L280 | Y1: L300 | Z1: L310 | AA1: L320 | AB1: L354 | AC1: L355 | AD1: L361 | AE1: L362 | AF1: L365 | AG1: L370 | AH1: L410 | AI1: L428 | AJ1: L430 | AK1: L431 | AL1: L440 | AM1: L460 | AN1: L500 | AO1: L510 | AP1: L520 | AQ1: L550 | AR1: L551 | AS1: L560 | AT1: L570 | AU1: L580 | AV1: L590 | AW1: L640 | AX1: L643 | AY1: L646 | AZ1: L661 | BA1: L10 | BB1: L45 | BC1: L195 | BD1: L351 | BE1: L356 | BF1: L360 | BG1: L380 | BH1: L400 | BI1: L425 | BJ1: L426 | BK1: L470 | BL1: L540 | BM1: L541 | BN1: L160 | BO1: L210 | BP1: L220 | BQ1: L252 | BR1: L340 | BS1: L350 | BT1: L352 | BU1: L419 | BV1: L420 | BW1: L480 | BX1: L644 | BY1: L648 | BZ1: L230 | CA1: L390 | CB1: L198 | CC1: L647 | CD1: L15 | CE1: L254 | CF1: L281 | CG1: L141 | CH1: L285 | CI1: L641 | CJ1: L121 | CK1: L132 | CL1: L30 | CM1: L353 | CN1: L21 | CO1: L286 | CP1: L429 | CQ1: L511 | CR1: L620 | CS1: L630 | CT1: L427 | CU1: L422 | CV1: L40 | CW1: L421 | CX1: L142 | CY1: L192 | CZ1: L241 | DA1: L17 | DB1: L122 | DC1: L552 | DD1: L287 | DE1: L450 | DF1: L645 | DG1: L490 | DH1: L642 | DI1: L199 | DJ1: L256 | DK1: L258 | DL1: L130 | DM1: L418 | DN1: L191 | DO1: L341 | DP1: L423 | DQ1: L424 | DR1: L22 | DS1: L197 | DT1: L255 | DU1: L271 | DV1: L273 | DW1: L288 | DX1: L135 | DY1: L610 | DZ1: L257 | EA1: L545 | EB1: L123 | EC1: L600 | ED1: L272 | EE1: L455 | EF1: L131 | EG1: L133 | EH1: L134 | EI1: L512 | EJ1: L513
A2: 1 | B2: 10 | C2: ATLANTIC | D2: ABSECON CITY | E2: 35200 | F2: 800 | G2: 22986 | H2: 145750 | I2: 515706 | J2: 720442 | K2: 186685 | L2: 32594 | M2: 38022 | N2: 841 | O2: 258142 | P2: 341 | Q2: 8172525 | R2: 52188 | S2: 52188 | T2: 5834 | U2: 25895 | V2: 71494 | W2: 8327936 | X2: 344397 | Y2: 139638 | Z2: 656131 | AA2: 54842 | AB2: 9607 | AC2: 147092 | AD2: 860745 | AE2: 371687 | AF2: 5397 | AG2: 2589536 | AH2: 10917813 | AI2: 35811 | AJ2: 406322 | AK2: 442133 | AL2: 144655 | AM2: 244547 | AN2: 59446 | AO2: 448648 | AP2: 890781 | AQ2: 1134135 | AR2: 1817 | AS2: 1817 | AT2: 1135952 | AU2: 91394 | AV2: 1227346 | AW2: 1227346 | AX2: 341 | AY2: -341 | AZ2: 14014524
A3: 1 | B3: 110 | C3: ATLANTIC | D3: ATLANTIC CITY | F3: 3780064 | G3: 5258723 | H3: 3595885 | I3: 505000 | J3: 14840068 | K3: 2682970 | M3: 737864 | N3: 30041 | O3: 3450875 | Q3: 93056124 | S3: 11635011 | V3: 2460789 | W3: 107151924 | Y3: 1042992 | Z3: 5304073 | AA3: 910558 | AB3: 202806 | AC3: 749710 | AD3: 6726159 | AE3: 3691269 | AG3: 19698097 | AH3: 126878654 | AJ3: 229570 | AK3: 9461606 | AL3: 3730927 | AM3: 2312622 | AN3: 3125142 | AO3: 9266420 | AP3: 18728026 | AQ3: 11534220 | AT3: 11534220 | AU3: 1034431 | AV3: 12581503 | AW3: 12581503 | AZ3: 176479126 | BA3: 1643557 | BB3: 56839 | BC3: 11635011 | BD3: 34678 | BE3: 525813 | BF3: 510039 | BG3: 28633 | BH3: 28633 | BI3: 5952147 | BJ3: 3279889 | BK3: 97729 | BL3: 3080 | BM3: 9772
A4: 1 | B4: 120 | C4: ATLANTIC | D4: ATLANTIC CO VOCATIONAL | F4: 467596 | G4: 261575 | H4: 477914 | J4: 1207085 | K4: 520694 | L4: 149811 | O4: 670505 | V4: 339613 | W4: 6514876 | X4: 1094318 | Z4: 469855 | AC4: 20527 | AD4: 513045 | AE4: 280300 | AG4: 3750845 | AH4: 10265721 | AJ4: 99216 | AK4: 494426 | AL4: 123727 | AN4: 104821 | AO4: 564317 | AP4: 1282453 | AZ4: 14986022 | BD4: 208499 | BE4: 97652 | BJ4: 395210 | BK4: 260628 | BN4: 3624000 | BO4: 1907500 | BP4: 497926 | BQ4: 145837 | BR4: 1928 | BS4: 878471 | BT4: 186250 | BU4: 223710 | BV4: 223710 | BW4: 75141 | BX4: 1560258 | BY4: 1560258
A5: 1 | B5: 125 | C5: ATLANTIC | D5: ATLANTIC CO SPECIAL SERV | F5: 35722 | I5: 28418 | J5: 64140 | K5: 2413589 | L5: 675000 | M5: 216792 | O5: 3305381 | V5: 217626 | W5: 18544306 | AD5: 776303 | AE5: 559221 | AG5: 1335524 | AH5: 20016499 | AJ5: 201282 | AK5: 201282 | AM5: 27450 | AO5: 27450 | AP5: 267387 | AZ5: 23653407 | BH5: 136669 | BN5: 1854000 | BO5: 15458793 | BP5: 861740 | BU5: 38655 | BV5: 38655 | BZ5: 152147 | CA5: 136669
A6: 1 | B6: 570 | C6: ATLANTIC | D6: BRIGANTINE CITY | G6: 1412365 | H6: 1040602 | I6: 1 | J6: 2452968 | K6: 300627 | O6: 300627 | Q6: 13665336 | V6: 189857 | W6: 13855193 | Y6: 570923 | Z6: 1168580 | AA6: 39048 | AC6: 152382 | AD6: 808384 | AE6: 455929 | AF6: 928 | AG6: 3253000 | AH6: 17108193 | AJ6: 2440 | AK6: 1054983 | AL6: 264884 | AM6: 289968 | AN6: 81077 | AO6: 635929 | AP6: 1703941 | AZ6: 21576929 | BE6: 56826 | BI6: 605498 | BJ6: 447045 | BU6: 13029 | BV6: 13029 | BX6: 11200 | BY6: 11200
A7: 1 | B7: 590 | C7: ATLANTIC | D7: BUENA REGIONAL | F7: 340556 | G7: 445245 | I7: 30742 | J7: 816543 | K7: 587426 | L7: 100000 | M7: 9880899 | N7: 126447 | O7: 10694772 | Q7: 11204236 | R7: 4026996 | S7: 4086377 | T7: 371163 | U7: 1000 | V7: 241073 | W7: 15903849 | X7: 9091917 | Y7: 964459 | Z7: 1451707 | AA7: 66540 | AB7: 31772 | AC7: 230631 | AD7: 2272723 | AE7: 1101103 | AF7: 176033 | AG7: 16112737 | AH7: 32075085 | AJ7: 359797 | AK7: 2591692 | AL7: 899513 | AM7: 930500 | AN7: 1201979 | AO7: 3031992 | AP7: 5624363 | AQ7: 816593 | AT7: 816593 | AU7: 378926 | AV7: 1815313 | AW7: 1815313 | AZ7: 51030320 | BE7: 426427 | BH7: 58499 | BI7: 1292661 | BJ7: 939234 | BL7: 619794 | BR7: 299425 | BU7: 679 | BV7: 679 | BY7: 4244 | CA7: 58499 | CB7: 59381 | CC7: 4244
A8: 1 | B8: 960 | C8: ATLANTIC | D8: CORBIN CITY | G8: 31243 | J8: 134348 | K8: 100000 | L8: 135807 | O8: 235807 | Q8: 763006 | V8: 5382 | W8: 858388 | X8: 418411 | Y8: 99415 | Z8: 159276 | AC8: 14483 | AD8: 24067 | AG8: 736400 | AH8: 1594788 | AZ8: 1964943 | BE8: 20748 | CD8: 103105 | CE8: 90000
A9: 1 | B9: 1300 | C9: ATLANTIC | D9: EGG HARBOR CITY | F9: 46477 | G9: 356691 | H9: 184009 | I9: 22501 | J9: 759171 | K9: 123672 | N9: 2 | O9: 123674 | Q9: 1810936 | R9: 35345 | S9: 35345 | U9: 3902 | V9: 72013 | W9: 1922196 | X9: 2389741 | Y9: 62692 | Z9: 471258 | AA9: 14052 | AB9: 5724 | AC9: 59249 | AD9: 525270 | AE9: 268265 | AG9: 4526911 | AH9: 6451156 | AJ9: 210171 | AK9: 973029 | AL9: 362190 | AM9: 173141 | AN9: 877377 | AO9: 1412708 | AP9: 2385737 | AZ9: 9719738 | BA9: 149493 | BE9: 127797 | BF9: 46477 | BH9: 2049 | BI9: 498381 | BJ9: 264477 | BR9: 161942 | CA9: 2049 | CF9: 394444
A10: 1 | B10: 1310 | C10: ATLANTIC | D10: EGG HARBOR TWP | F10: 1126727 | G10: 3250080 | H10: 2481057 | I10: 742211 | J10: 7605303 | K10: 2250739 | L10: 1905047 | M10: 24790608 | N10: 64370 | O10: 29010764 | Q10: 50843214 | S10: 54619 | V10: 1217010 | W10: 52114843 | X10: 20341417 | Y10: 2516475 | Z10: 4028682 | AA10: 105426 | AC10: 749168 | AD10: 4426169 | AE10: 2890602 | AG10: 37234397 | AH10: 91003659 | AI10: 333900 | AJ10: 352277 | AK10: 923816 | AL10: 596828 | AM10: 1547033 | AN10: 274331 | AO10: 2442134 | AP10: 3375797 | AQ10: 4222368 | AT10: 4222368 | AU10: 3143213 | AV10: 7365581 | AW10: 7365581 | AY10: 3057611 | AZ10: 142204715 | BA10: 5228 | BC10: 54619 | BE10: 849381 | BF10: 1327077 | BH10: 9037 | BJ10: 237639 | BK10: 23942 | BU10: 9847 | BV10: 9847 | BY10: 3843611 | CA10: 9037 | CC10: 786000 | CG10: 1645382
A11: 1 | B11: 1410 | C11: ATLANTIC | D11: ESTELL MANOR CITY | F11: 25287 | G11: 37697 | H11: 21081 | I11: 112696 | J11: 196761 | K11: 100000 | L11: 50000 | M11: 89042 | N11: 3755 | O11: 242797 | P11: 887 | Q11: 1934320 | U11: 4696 | V11: 22739 | W11: 1961755 | X11: 1486698 | Y11: 142144 | Z11: 214603 | AC11: 35549 | AD11: 199475 | AE11: 107599 | AG11: 2242946 | AH11: 4205588 | AI11: 19128 | AK11: 19128 | AL11: 20070 | AM11: 73136 | AN11: 35431 | AO11: 128637 | AP11: 147765 | AQ11: 152371 | AT11: 152371 | AU11: 97530 | AV11: 249901 | AW11: 249901 | AY11: 50000 | AZ11: 5092812 | BE11: 56878 | BY11: 50000
A12: 1 | B12: 1540 | C12: ATLANTIC | D12: FOLSOM BORO | F12: 345800 | G12: 393916 | H12: 306282 | I12: 131540 | J12: 1272538 | K12: 100000 | L12: 70000 | M12: 962159 | N12: 16493 | O12: 1148652 | P12: 11766 | Q12: 1258908 | V12: 109391 | W12: 1368299 | X12: 1033381 | Y12: 205587 | Z12: 237486 | AB12: 2689 | AC12: 52446 | AD12: 290001 | AE12: 153302 | AG12: 3773112 | AH12: 5153177 | AI12: 3993 | AJ12: 1237 | AK12: 208131 | AL12: 74182 | AM12: 106314 | AN12: 33297 | AO12: 213793 | AP12: 421924 | AQ12: 228216 | AT12: 228216 | AV12: 228216 | AW12: 228216 | AY12: 163175 | AZ12: 8861887 | BB12: 95000 | BE12: 95963 | BF12: 103116 | BI12: 128018 | BJ12: 74883 | BR12: 396365 | BY12: 637380 | CH12: 1202776 | CI12: 474205
A13: 1 | B13: 1690 | C13: ATLANTIC | D13: GALLOWAY TWP | F13: 29819 | G13: 630906 | H13: 1350803 | I13: 510942 | J13: 2543714 | K13: 906382 | L13: 617326 | M13: 202679 | N13: 71001 | O13: 1797388 | P13: 166392 | Q13: 26335007 | R13: 67647 | S13: 67647 | U13: 10876 | V13: 354991 | W13: 26768521 | X13: 13410623 | Y13: 1107364 | Z13: 2223740 | AA13: 233940 | AB13: 70191 | AC13: 456764 | AD13: 2446616 | AE13: 1625712 | AF13: 41187 | AG13: 22605935 | AH13: 49545515 | AI13: 207522 | AJ13: 434300 | AK13: 659891 | AL13: 430365 | AM13: 790131 | AN13: 179128 | AO13: 1399624 | AP13: 2076754 | AQ13: 1644990 | AT13: 1644990 | AU13: 1400447 | AV13: 3045437 | AW13: 3045437 | AY13: 271390 | AZ13: 59282523 | BA13: 21244 | BE13: 543140 | BH13: 4667 | BJ13: 18069 | BR13: 446658 | BU13: 17239 | BV13: 17239 | BY13: 273715 | CA13: 4667 | CC13: 2325 | CJ13: 2268129 | CK13: 300000
A14: 1 | B14: 1790 | C14: ATLANTIC | D14: GREATER EGG HARBOR REG | F14: 263189 | G14: 3156329 | H14: 2197469 | I14: 14926 | J14: 5631913 | K14: 1052462 | L14: 320600 | M14: 365725 | N14: 40515 | O14: 1779302 | Q14: 25657864 | R14: 768171 | S14: 768171 | U14: 746 | V14: 711737 | W14: 27138518 | X14: 17921675 | Y14: 1381334 | Z14: 3012677 | AA14: 68552 | AB14: 132882 | AC14: 408378 | AD14: 2964023 | AE14: 1509445 | AF14: 1019919 | AG14: 28418885 | AH14: 55557403 | AI14: 163980 | AJ14: 50882 | AK14: 214862 | AL14: 213644 | AM14: 754208 | AN14: 94838 | AO14: 1075014 | AP14: 1305970 | AQ14: 550208 | AT14: 550208 | AU14: 768616 | AV14: 1373817 | AW14: 1373817 | AX14: 54993 | AY14: -54993 | AZ14: 65648405 | BK14: 12324 | BL14: 54993 | BU14: 16094 | BV14: 16094
A15: 1 | B15: 1940 | C15: ATLANTIC | D15: HAMILTON TWP | F15: 28315 | H15: 383737 | I15: 397321 | J15: 1374554 | K15: 493394 | L15: 250000 | M15: 62223 | N15: 1 | O15: 805618 | P15: 20000 | Q15: 15007035 | R15: 37551 | S15: 37551 | U15: 19539 | V15: 431583 | W15: 15495708 | X15: 9647111 | Y15: 1195764 | Z15: 2588474 | AA15: 85102 | AB15: 58163 | AC15: 318846 | AD15: 1645769 | AE15: 1191425 | AF15: 13911 | AG15: 17228296 | AH15: 32893329 | AJ15: 167856 | AK15: 2462056 | AL15: 634548 | AM15: 711678 | AN15: 213655 | AO15: 1559881 | AP15: 4021937 | AQ15: 2800921 | AT15: 2800921 | AU15: 1672760 | AV15: 4473681 | AW15: 4473681 | AY15: 30797 | AZ15: 43599916 | BE15: 483731 | BH15: 37787 | BI15: 1427282 | BJ15: 866918 | BY15: 30797 | CA15: 37787 | CG15: 111538 | CL15: 565181
A16: 1 | B16: 1960 | C16: ATLANTIC | D16: HAMMONTON TOWN | I16: 1213 | J16: 1213 | K16: -2187609 | M16: 1709176 | N16: 18835 | O16: -459598 | Q16: 14521766 | R16: 6734504 | S16: 6734504 | U16: 77 | W16: 22916492 | X16: 4337255 | Y16: 359182 | Z16: 1793188 | AA16: 102820 | AB16: 36942 | AC16: 249064 | AD16: 2238589 | AE16: 1265095 | AG16: 10777222 | AH16: 33722214 | AJ16: 427475 | AK16: 2210726 | AL16: 679112 | AM16: 625973 | AN16: 150046 | AO16: 1474560 | AP16: 3685286 | AQ16: 1531726 | AT16: 1531726 | AU16: 5597 | AV16: 1621610 | AW16: 1621610 | AX16: 84287 | AY16: -84287 | AZ16: 38570725 | BE16: 258745 | BF16: 5104 | BI16: 1265056 | BJ16: 518195 | BK16: 19429 | BL16: 84287 | BQ16: 1660145 | CG16: 28500 | CM16: 131238
A17: 1 | B17: 2680 | C17: ATLANTIC | D17: LINWOOD CITY | F17: 28772 | G17: 453670 | H17: 529280 | I17: 243273 | J17: 1254995 | K17: 227182 | L17: 185000 | M17: 505459 | O17: 917641 | Q17: 9157885 | V17: 143739 | W17: 9301624 | X17: 969200 | Y17: 89582 | Z17: 719219 | AA17: 6990 | AB17: 11010 | AC17: 111914 | AD17: 866075 | AE17: 433211 | AG17: 3265775 | AH17: 12567399 | AL17: 18339 | AM17: 196563 | AN17: 25114 | AO17: 240016 | AP17: 296663 | AZ17: 15036698 | BE17: 56907 | BF17: 1667 | BU17: 56647 | BV17: 56647
A18: 1 | B18: 2780 | C18: ATLANTIC | D18: LONGPORT | K18: 21479 | O18: 21479 | Q18: 968994 | W18: 982338 | Y18: 10048 | Z18: 10922 | AC18: 5267 | AE18: 319 | AG18: 108407 | AH18: 1090745 | AZ18: 1112224 | BE18: 2926 | BF18: 7624 | BQ18: 13344 | BR18: 71301
A19: 1 | B19: 2910 | C19: ATLANTIC | D19: MAINLAND REGIONAL | F19: 527609 | G19: 590476 | H19: 312750 | J19: 1430835 | K19: 421625 | L19: 432869 | M19: 12599 | N19: 28099 | O19: 895192 | Q19: 13953238 | T19: 109989 | V19: 351148 | W19: 14414375 | X19: 4640595 | Y19: 267605 | Z19: 759228 | AA19: 22254 | AB19: 33727 | AC19: 187841 | AD19: 1346139 | AE19: 781598 | AF19: 88865 | AG19: 8305301 | AH19: 23040688 | AI19: 37457 | AJ19: 3000 | AK19: 40457 | AL19: 49629 | AM19: 277679 | AN19: 20393 | AO19: 355799 | AP19: 396256 | AQ19: 785123 | AT19: 785123 | AU19: 275591 | AV19: 1064277 | AW19: 1064277 | AY19: -3563 | AZ19: 26827248 | BE19: 177449 | BK19: 8098 | BL19: 3563 | CC19: 3563 | CG19: 321012
A20: 1 | B20: 3020 | C20: ATLANTIC | D20: MARGATE CITY | F20: 45430 | G20: 926429 | H20: 484084 | J20: 1456297 | K20: 239403 | L20: 81475 | O20: 320878 | Q20: 10173118 | R20: 734759 | S20: 791419 | V20: 242872 | W20: 11207409 | Y20: 112437 | Z20: 643606 | AA20: 10530 | AB20: 7656 | AC20: 79108 | AD20: 686231 | AE20: 331567 | AG20: 1902405 | AH20: 13109814 | AI20: 22170 | AJ20: 69505 | AK20: 91675 | AL20: 53328 | AM20: 196003 | AN20: 22880 | AO20: 272211 | AP20: 419529 | AZ20: 15306518 | BA20: 354 | BC20: 56660 | BE20: 26036 | BF20: 5234 | BU20: 55643 | BV20: 55643
A21: 1 | B21: 3480 | C21: ATLANTIC | D21: MULLICA TWP | F21: 428221 | J21: 552790 | K21: 87261 | L21: 75525 | M21: 150965 | O21: 313751 | P21: 1024 | Q21: 3085814 | R21: 1861 | S21: 1861 | V21: 34891 | W21: 3122566 | X21: 3250225 | Y21: 288968 | Z21: 713718 | AA21: 24510 | AC21: 81114 | AD21: 644108 | AE21: 348414 | AG21: 5528054 | AH21: 8657911 | AJ21: 27228 | AK21: 715823 | AL21: 207484 | AM21: 171601 | AN21: 209147 | AO21: 588232 | AP21: 1304055 | AQ21: 428248 | AT21: 428248 | AU21: 173482 | AV21: 601730 | AW21: 601730 | AZ21: 11430237 | BE21: 115947 | BF21: 61050 | BH21: 6267 | BI21: 418670 | BJ21: 269925 | CA21: 6267 | CL21: 124569
A22: 1 | B22: 3720 | C22: ATLANTIC | D22: NORTHFIELD CITY | F22: 146347 | G22: 376665 | H22: 371256 | I22: 284803 | J22: 1229071 | K22: 192789 | N22: -140326 | O22: 52463 | Q22: 7194807 | S22: 7820 | V22: 89378 | W22: 7292005 | X22: 1852131 | Y22: 77066 | Z22: 774067 | AA22: 15220 | AB22: 2732 | AC22: 125520 | AD22: 868975 | AE22: 415642 | AG22: 4222968 | AH22: 11514973 | AI22: 17088 | AJ22: 16291 | AK22: 33379 | AL22: 83672 | AM22: 208359 | AN22: 41523 | AO22: 333554 | AP22: 367854 | AQ22: 1093305 | AT22: 1093305 | AU22: 504684 | AV22: 1597989 | AW22: 1597989 | AZ22: 14762350 | BB22: 50000 | BC22: 7820 | BE22: 85833 | BF22: 5782 | BU22: 921 | BV22: 921
A23: 1 | B23: 4180 | C23: ATLANTIC | D23: PLEASANTVILLE CITY | F23: 19873 | G23: 2012771 | I23: 1 | J23: 2032645 | K23: 1536534 | L23: 1962613 | M23: 11979533 | N23: -118716 | O23: 15359964 | Q23: 6220639 | S23: 212378 | V23: 367173 | W23: 6800190 | X23: 25501280 | Y23: 623617 | Z23: 3575208 | AA23: 205140 | AB23: 17354 | AC23: 447987 | AD23: 3461190 | AE23: 2071333 | AG23: 65823048 | AH23: 72660664 | AJ23: 110506 | AK23: 7081127 | AL23: 2395104 | AM23: 756929 | AN23: 1241904 | AO23: 4496370 | AP23: 12011586 | AQ23: 973100 | AT23: 973100 | AU23: 2825822 | AV23: 3798922 | AW23: 3844440 | AX23: 12034 | AZ23: 105921333 | BC23: 212378 | BF23: 12562 | BH23: 37426 | BI23: 3469509 | BJ23: 1644468 | BK23: 17900 | BU23: 2800 | BV23: 2800 | BW23: 84533 | BY23: 12034 | CA23: 37426 | CF23: 2062146 | CN23: 136279 | CO23: 27845231 | CP23: 1856644 | CQ23: 431289 | CR23: 45518 | CS23: 45518
A24: 1 | B24: 4240 | C24: ATLANTIC | D24: PORT REPUBLIC CITY | F24: 38911 | H24: 41215 | I24: 529 | J24: 80655 | K24: 85514 | O24: 85514 | Q24: 1229445 | S24: 4010 | U24: 13 | W24: 1258685 | Y24: 40319 | Z24: 94368 | AC24: 16568 | AD24: 138067 | AE24: 61914 | AG24: 1150675 | AH24: 2409360 | AI24: 5904 | AJ24: 4000 | AK24: 9904 | AM24: 35301 | AN24: 20344 | AO24: 55645 | AP24: 65549 | AZ24: 2641078 | BC24: 4010 | BE24: 27754 | BQ24: 25217 | BR24: 771685
A25: 1 | B25: 4800 | C25: ATLANTIC | D25: SOMERS POINT CITY | F25: 271466 | G25: 47420 | I25: 100 | J25: 318986 | K25: 223582 | L25: 335000 | M25: 9910 | N25: 30736 | O25: 599228 | Q25: 7861264 | R25: 9163 | S25: 9163 | V25: 126375 | W25: 7996802 | X25: 1865875 | Y25: 104766 | Z25: 995247 | AA25: 10602 | AC25: 130554 | AD25: 661108 | AE25: 478014 | AG25: 4742980 | AH25: 12768955 | AJ25: 280061 | AK25: 1014957 | AL25: 373936 | AM25: 332863 | AN25: 91519 | AO25: 798318 | AP25: 1813275 | AQ25: 813791 | AT25: 813791 | AU25: 228558 | AV25: 1042700 | AW25: 1042700 | AX25: 351 | AY25: -351 | AZ25: 16543144 | BF25: 1246 | BH25: 29173 | BI25: 588316 | BJ25: 146580 | BL25: 351 | BR25: 495568 | CA25: 29173
A26: 1 | B26: 5350 | C26: ATLANTIC | D26: VENTNOR CITY | F26: 4355 | G26: 410096 | H26: 50296 | J26: 480318 | K26: 335319 | L26: 87255 | M26: 179447 | O26: 602021 | Q26: 15597115 | T26: 202611 | V26: 104111 | W26: 15903837 | Y26: 364427 | Z26: 608896 | AA26: 92670 | AB26: 7724 | AC26: 160233 | AD26: 860391 | AE26: 487513 | AG26: 2855229 | AH26: 18909986 | AJ26: 87075 | AK26: 992788 | AL26: 439488 | AM26: 307288 | AN26: 674368 | AO26: 1421144 | AP26: 2413932 | AZ26: 22406257 | BA26: 15571 | BE26: 51228 | BF26: 122147 | BH26: 6327 | BI26: 553471 | BJ26: 351801 | BR26: 100000 | CA26: 6327 | CG26: 144593 | CT26: 441
A27: 1 | B27: 5760 | C27: ATLANTIC | D27: WEYMOUTH TWP | F27: 49286 | G27: 116648 | H27: 13470 | I27: 51271 | J27: 280675 | K27: 100000 | L27: 34338 | M27: 35040 | O27: 169378 | Q27: 1631399 | U27: 2358 | W27: 1672026 | X27: 1422519 | Y27: 189150 | Z27: 204252 | AA27: 2336 | AC27: 39389 | AD27: 183426 | AE27: 104043 | AG27: 2388583 | AH27: 4060609 | AK27: 172178 | AL27: 46174 | AM27: 86518 | AN27: 52849 | AO27: 185541 | AP27: 357719 | AQ27: 63946 | AT27: 63946 | AU27: 70360 | AV27: 134306 | AW27: 134306 | AZ27: 5002687 | BA27: 50000 | BE27: 65023 | BF27: 29379 | BI27: 106502 | BJ27: 65676 | BQ27: 38269 | BR27: 149066
A28: 3 | B28: 40 | C28: BERGEN | D28: ALLENDALE BORO | F28: 172253 | G28: 477698 | H28: 45784 | I28: 320548 | J28: 1244486 | K28: 372692 | L28: 136382 | M28: 4455111 | N28: 128709 | O28: 5092894 | Q28: 12025265 | S28: 203476 | U28: 96334 | W28: 12367879 | Z28: 526449 | AB28: 162846 | AC28: 72221 | AD28: 939402 | AE28: 455185 | AG28: 2174063 | AH28: 14541942 | AM28: 166055 | AN28: 39362 | AO28: 205417 | AP28: 205417 | AQ28: 847316 | AT28: 847316 | AU28: 142845 | AV28: 1174257 | AW28: 1174257 | AX28: 184096 | AY28: -184096 | AZ28: 22258996 | BA28: 2647 | BC28: 203476 | BE28: 17960 | BL28: 184096 | BQ28: 42804 | CL28: 225556
A29: 3 | B29: 80 | C29: BERGEN | D29: ALPINE BORO | F29: 76843 | I29: 184405 | J29: 261248 | K29: 75240 | L29: 499574 | O29: 574814 | Q29: 4660644 | S29: 65000 | U29: 8791 | V29: 155383 | W29: 4889818 | Y29: 96713 | Z29: 123868 | AA29: 5822 | AB29: 45117 | AC29: 10419 | AD29: 118188 | AE29: 261834 | AF29: 4654 | AG29: 673720 | AH29: 5563538 | AM29: 49553 | AN29: 6462 | AO29: 56015 | AP29: 56015 | AZ29: 6455615 | BC29: 65000 | BE29: 7105
A30: 3 | B30: 285 | C30: BERGEN | D30: BERGEN CO SPECIAL SERVICE | F30: 777052 | I30: 1 | J30: 1593723 | K30: 639897 | M30: -3902824 | O30: -3262927 | P30: 500000 | V30: 928679 | W30: 45783020 | AD30: 2430667 | AE30: 1996751 | AG30: 4427418 | AH30: 50999569 | AJ30: 8621435 | AK30: 8621435 | AN30: 149901 | AO30: 149901 | AP30: 8771336 | AZ30: 61235749 | BH30: 289131 | BN30: 5766582 | BO30: 37970599 | BY30: 3134048 | BZ30: 1117160 | CA30: 289131 | CC30: 2421390 | CI30: 712658 | CL30: 816670
A31: 3 | B31: 290 | C31: BERGEN | D31: BERGEN COUNTY VOCATIONAL | F31: 627887 | I31: 1 | J31: 9571603 | K31: 521291 | M31: -13882839 | O31: -13361548 | P31: 200000 | V31: 658561 | W31: 42646447 | Z31: 1994976 | AC31: 254112 | AD31: 2839675 | AE31: 1538392 | AG31: 10919543 | AH31: 53767554 | AI31: 50546 | AJ31: 2296065 | AK31: 2424223 | AL31: 109066 | AM31: 449358 | AN31: 6400215 | AO31: 7664599 | AP31: 10122209 | AZ31: 67716456 | BE31: 191334 | BF31: 114052 | BH31: 1564 | BJ31: 65024 | BN31: 22567423 | BO31: 19420463 | BS31: 3987002 | BU31: 33387 | BV31: 33387 | BW31: 705960 | BY31: 7616638 | CA31: 1564 | CC31: 6349545 | CI31: 1267093 | CL31: 8943715 | CU31: 12588
A32: 3 | B32: 300 | C32: BERGEN | D32: BERGENFIELD BORO | F32: 875958 | H32: 125821 | J32: 1223128 | K32: 1330132 | L32: 255208 | M32: 116389 | N32: 30718 | O32: 1732447 | P32: 116389 | Q32: 39876425 | R32: 446821 | S32: 446821 | T32: 37909 | V32: 160847 | W32: 40522002 | X32: 4868281 | Y32: 536398 | Z32: 4311809 | AA32: 256852 | AB32: 546454 | AC32: 443255 | AD32: 3890150 | AE32: 1703206 | AG32: 16560955 | AH32: 57199346 | AI32: 16999 | AJ32: 207490 | AK32: 331816 | AL32: 157200 | AM32: 840891 | AN32: 591920 | AO32: 1590011 | AP32: 1937654 | AY32: -116389 | AZ32: 61976186 | BA32: 2608 | BB32: 141520 | BF32: 4550 | BJ32: 107327 | BU32: 15827 | BV32: 15827 | BY32: -116389 | CV32: 77221
A33: 3 | B33: 440 | C33: BERGEN | D33: BOGOTA BORO | F33: 161128 | I33: 102164 | J33: 296724 | K33: 137626 | M33: 19445 | N33: 153504 | O33: 310575 | P33: 2917 | Q33: 10238743 | R33: 153063 | S33: 153063 | U33: 3288 | V33: 15478 | W33: 10487236 | X33: 2138184 | Y33: 93884 | Z33: 746584 | AA33: 64168 | AB33: 81967 | AC33: 120692 | AD33: 1001031 | AE33: 493396 | AG33: 5711832 | AH33: 16201985 | AI33: 42780 | AJ33: 136148 | AK33: 178928 | AL33: 204753 | AM33: 273462 | AN33: 52104 | AO33: 530319 | AP33: 709247 | AQ33: 576161 | AT33: 576161 | AU33: 13229 | AV33: 589390 | AW33: 589390 | AZ33: 18156179 | BE33: 121658 | BF33: 1300 | BQ33: 76664 | BR33: 848968 | BY33: 48258 | CI33: 48258 | CL33: 33432
A34: 3 | B34: 740 | C34: BERGEN | D34: CARLSTADT BORO | F34: 23924 | G34: 621722 | I34: 11001 | J34: 656647 | K34: 150823 | M34: 8668712 | N34: 151356 | O34: 8970891 | P34: 192846 | Q34: 7349150 | V34: 51799 | W34: 7400949 | Y34: 42654 | Z34: 277899 | AA34: 34896 | AB34: 15795 | AC34: 53873 | AD34: 570464 | AE34: 301675 | AG34: 1309536 | AH34: 8975463 | AJ34: 2162 | AK34: 2162 | AL34: 25722 | AM34: 126210 | AN34: 18893 | AO34: 170825 | AP34: 178899 | AQ34: 1533835 | AT34: 1533835 | AV34: 1533835 | AW34: 1533835 | AX34: 192846 | AY34: -192846 | AZ34: 24477451 | BE34: 12280 | BU34: 5912 | BV34: 5912 | BY34: 4161716 | CG34: 72132 | CI34: 4161716
A35: 3 | B35: 745 | C35: BERGEN | D35: CARLSTADT-EAST RUTHERFORD | F35: 104027 | G35: 189415 | H35: 96496 | I35: 37235 | J35: 427173 | K35: 222784 | L35: 13443 | M35: 1149309 | N35: 26147 | O35: 1411683 | Q35: 9850324 | U35: 1819 | V35: 208302 | W35: 10065732 | Y35: 79978 | Z35: 155683 | AA35: 43144 | AB35: 38250 | AC35: 60127 | AD35: 635576 | AE35: 300644 | AG35: 1495031 | AH35: 11560763 | AI35: 5355 | AK35: 5355 | AL35: 63360 | AM35: 109403 | AN35: 28203 | AO35: 200966 | AP35: 206321 | AV35: 44396 | AW35: 44396 | AX35: 44396 | AY35: -44396 | AZ35: 13650336 | BE35: 14180 | BF35: 36584 | BL35: 44396 | BQ35: 5287 | BR35: 130865
A36: 3 | B36: 890 | C36: BERGEN | D36: CLIFFSIDE PARK BORO | F36: 70000 | G36: 178387 | J36: 248387 | K36: 656073 | L36: 113242 | M36: 84587 | N36: 10 | O36: 853912 | Q36: 23525325 | S36: 4993919 | T36: 16200 | U36: 188266 | W36: 29116737 | Y36: 137025 | Z36: 1172210 | AA36: 405044 | AB36: 89578 | AC36: 237544 | AD36: 2136593 | AE36: 1148715 | AG36: 5754302 | AH36: 35037712 | AJ36: 151704 | AK36: 1976828 | AL36: 412083 | AM36: 524366 | AN36: 709642 | AO36: 1646091 | AP36: 3622919 | AQ36: 441357 | AT36: 441357 | AU36: 5667 | AV36: 542884 | AW36: 542884 | AZ36: 40305814 | BC36: 4993919 | BE36: 110346 | BF36: 317247 | BI36: 1226989 | BJ36: 499388 | BM36: 95860 | BQ36: 393027 | CG36: 166673 | CU36: 88195 | CW36: 10552
A37: 3 | B37: 930 | C37: BERGEN | D37: CLOSTER BORO | F37: 145924 | G37: 188128 | H37: 105069 | I37: 84560 | J37: 633979 | K37: 331473 | L37: 29475 | M37: 2444 | N37: 38379 | O37: 401771 | P37: 54665 | Q37: 13720585 | R37: 75673 | S37: 75673 | U37: 4463 | V37: 99983 | W37: 13900704 | Z37: 560979 | AB37: 64189 | AC37: 75446 | AD37: 1100971 | AE37: 612178 | AG37: 2442263 | AH37: 16397632 | AJ37: 31530 | AK37: 31530 | AM37: 232295 | AO37: 232295 | AP37: 266313 | AQ37: 1022877 | AT37: 1022877 | AV37: 1025103 | AW37: 1025103 | AX37: 2226 | AY37: -56891 | AZ37: 18686910 | BE37: 19093 | BF37: 9407 | BL37: 2226 | BU37: 2488 | BV37: 2488 | BY37: -37888 | CI37: 16777 | CL37: 110298
A38: 3 | B38: 990 | C38: BERGEN | D38: CRESSKILL BORO | F38: 16038 | G38: 348217 | H38: 260346 | I38: 132729 | J38: 757330 | K38: 476119 | L38: 26796 | M38: 18139066 | N38: 22221 | O38: 18664202 | P38: 544349 | Q38: 18521666 | R38: 85949 | S38: 292449 | U38: 7000 | V38: 127890 | W38: 18953313 | Z38: 803849 | AB38: 78920 | AC38: 97137 | AD38: 1424359 | AE38: 811488 | AG38: 3359760 | AH38: 23137445 | AJ38: 81572 | AK38: 81572 | AM38: 289457 | AN38: 51222 | AO38: 340679 | AP38: 609130 | AQ38: 1623773 | AT38: 1623773 | AU38: 43946 | AV38: 1667719 | AW38: 1667719 | AX38: 544349 | AY38: -544349 | AZ38: 54271369 | BC38: 206500 | BE38: 27030 | BF38: 116977 | BU38: 186879 | BV38: 186879 | BY38: 9435543 | CE38: 4308 | CG38: 280023 | CI38: 9435543
A39: 3 | B39: 1070 | C39: BERGEN | D39: DEMAREST BORO | F39: 24956 | H39: 441403 | I39: 16594 | J39: 482953 | K39: 245157 | L39: 177438 | M39: 186836 | O39: 609431 | P39: 8490 | Q39: 9893854 | R39: 56662 | S39: 56662 | V39: 167411 | W39: 10117927 | Z39: 463656 | AB39: 47131 | AC39: 48318 | AD39: 582754 | AE39: 338624 | AG39: 1499773 | AH39: 11626190 | AJ39: 95513 | AK39: 95513 | AM39: 233493 | AO39: 233493 | AP39: 329006 | AQ39: 649950 | AT39: 649950 | AV39: 649950 | AW39: 649950 | AY39: 136319 | AZ39: 13833849 | BE39: 15359 | BF39: 3931 | BY39: 136319
A40: 3 | B40: 1130 | C40: BERGEN | D40: DUMONT BORO | F40: 293155 | I40: 1 | J40: 11968480 | K40: 695893 | L40: 1 | M40: 1915363 | N40: 212971 | O40: 2824228 | P40: 15726 | Q40: 27173953 | S40: 18433 | V40: 322978 | W40: 27515364 | X40: 4728390 | Y40: 246326 | Z40: 1467804 | AA40: 134176 | AB40: 173399 | AC40: 304583 | AD40: 2764116 | AE40: 1381865 | AG40: 11411322 | AH40: 39063159 | AL40: 75238 | AM40: 521027 | AN40: 109524 | AO40: 705789 | AP40: 705789 | AQ40: 1397488 | AT40: 1397488 | AV40: 1540657 | AW40: 1540657 | AY40: 56353 | AZ40: 56158666 | BA40: 6677 | BC40: 18433 | BE40: 206438 | BF40: 4225 | BL40: 143169 | BY40: 56353 | CG40: 120747 | CL40: 11668647
A41: 3 | B41: 1230 | C41: BERGEN | D41: EAST RUTHERFORD BORO | F41: 1062278 | I41: 392023 | J41: 1454301 | K41: 134918 | M41: 65249 | N41: 218 | O41: 200385 | Q41: 10337154 | V41: 120348 | W41: 10457502 | Y41: 53200 | Z41: 473935 | AA41: 70873 | AB41: 14583 | AC41: 78779 | AD41: 757665 | AE41: 483932 | AG41: 1955895 | AH41: 12413397 | AI41: 24117 | AJ41: 125477 | AK41: 212966 | AL41: 136359 | AM41: 192525 | AN41: 77847 | AO41: 406731 | AP41: 621440 | AQ41: 661590 | AT41: 661590 | AV41: 661590 | AW41: 661590 | AX41: 12204 | AZ41: 15411581 | BE41: 22928 | BJ41: 63372 | BU41: 1743 | BV41: 1743 | BY41: 60468 | CC41: 48264
A42: 3 | B42: 1270 | C42: BERGEN | D42: EDGEWATER BORO | F42: 276161 | G42: 422619 | H42: 316097 | I42: 456711 | J42: 1485409 | K42: 300481 | L42: 84439 | M42: 101713 | O42: 486633 | Q42: 10863869 | U42: 22829 | V42: 71497 | W42: 10958195 | Y42: 156041 | Z42: 426795 | AA42: 96584 | AB42: 102244 | AC42: 69782 | AD42: 382102 | AE42: 218033 | AG42: 1533898 | AH42: 12524133 | AJ42: 20583 | AK42: 291480 | AL42: 95651 | AM42: 104604 | AN42: 36206 | AO42: 236461 | AP42: 527941 | AQ42: 695876 | AT42: 695876 | AV42: 695876 | AW42: 695876 | AX42: 60875 | AY42: -60875 | AZ42: 15719992 | BE42: 30853 | BF42: 51464 | BI42: 158498 | BJ42: 112399 | CL42: 13821 | CX42: 32040
A43: 3 | B43: 1345 | C43: BERGEN | D43: ELMWOOD PARK | F43: 408749 | I43: 305694 | J43: 714443 | K43: 306324 | L43: 1400000 | M43: 22606697 | N43: 559930 | O43: 24872951 | P43: 96976 | Q43: 23573986 | V43: 250916 | W43: 23824902 | Z43: 1670708 | AA43: 44742 | AB43: 164008 | AC43: 233813 | AD43: 1790711 | AE43: 704203 | AG43: 4695066 | AH43: 28616944 | AI43: 99740 | AJ43: 317417 | AK43: 417157 | AL43: 281717 | AM43: 538274 | AN43: 103195 | AO43: 923186 | AP43: 1340785 | AQ43: 1462374 | AT43: 1462374 | AV43: 1462374 | AW43: 1462374 | AX43: 96976 | AY43: 1208717 | AZ43: 58313190 | BE43: 61470 | BF43: 25411 | BU43: 442 | BV43: 442 | BY43: 1305693
A44: 3 | B44: 1360 | C44: BERGEN | D44: EMERSON BORO | F44: 115000 | I44: 447058 | J44: 608266 | K44: 442711 | L44: 175000 | N44: 2 | O44: 617713 | Q44: 13943163 | R44: 206773 | S44: 206773 | V44: 430504 | W44: 14896292 | Z44: 678512 | AA44: 9200 | AB44: 134187 | AD44: 1204110 | AE44: 486497 | AG44: 2512506 | AH44: 17408798 | AJ44: 63269 | AK44: 63269 | AM44: 222247 | AN44: 43417 | AO44: 265664 | AP44: 328933 | AQ44: 541898 | AT44: 541898 | AV44: 541898 | AW44: 541898 | AZ44: 19505608 | BA44: 46208 | CY44: 315852
A45: 3 | B45: 1370 | C45: BERGEN | D45: ENGLEWOOD CITY | F45: 213930 | G45: 533966 | J45: 747896 | K45: 1033844 | L45: 2639563 | M45: 22646939 | N45: 1704 | O45: 26322050 | P45: 803945 | Q45: 40600443 | R45: 82692 | S45: 82692 | V45: 2691799 | W45: 43488822 | Y45: 736241 | Z45: 2503994 | AA45: 295918 | AB45: 261295 | AC45: 314787 | AD45: 3158978 | AE45: 1590886 | AG45: 15852840 | AH45: 60145607 | AJ45: 676697 | AK45: 3909873 | AL45: 686694 | AM45: 973034 | AN45: 2169893 | AO45: 3829621 | AP45: 7753567 | AQ45: 2358026 | AT45: 2358026 | AV45: 2358026 | AW45: 2358026 | AX45: 803945 | AY45: 1535618 | AZ45: 101005553 | BE45: 249444 | BF45: 4264290 | BI45: 2167999 | BJ45: 1057576 | BR45: 103107 | BU45: 14073 | BV45: 14073 | BY45: 3678407 | CE45: 113888 | CH45: 2373900 | CI45: 1338844 | CU45: 2102 | CW45: 5499
A46: 3 | B46: 1380 | C46: BERGEN | D46: ENGLEWOOD CLIFFS BORO | F46: 327327 | G46: 284524 | I46: 1 | J46: 611852 | K46: 228965 | M46: 533841 | O46: 762806 | Q46: 8376177 | R46: 82100 | S46: 82100 | V46: 88602 | W46: 8546879 | Y46: 156312 | Z46: 334186 | AA46: 35058 | AB46: 50691 | AC46: 25428 | AD46: 688094 | AE46: 248129 | AG46: 1574603 | AH46: 10121482 | AM46: 88457 | AN46: 34972 | AO46: 123429 | AP46: 123429 | AQ46: 99000 | AT46: 99000 | AV46: 210386 | AW46: 210386 | AX46: 111386 | AY46: -111386 | AZ46: 15785955 | BE46: 16844 | BF46: 9364 | BL46: 111386 | BR46: 10497 | BX46: 3956000 | BY46: 3956000
A47: 3 | B47: 1450 | C47: BERGEN | D47: FAIR LAWN BORO | F47: 1517501 | G47: 98868 | I47: 122368 | J47: 8411353 | K47: 1988149 | M47: 2605139 | N47: 473708 | O47: 5066996 | Q47: 61516737 | S47: 490375 | U47: 5939 | W47: 64701885 | Y47: 379972 | Z47: 3777675 | AA47: 305260 | AB47: 548191 | AC47: 531374 | AD47: 5011570 | AE47: 2305500 | AG47: 13057866 | AH47: 77759751 | AJ47: 695894 | AK47: 695894 | AL47: 167043 | AM47: 1029380 | AN47: 173212 | AO47: 1369635 | AP47: 2082913 | AQ47: 1758531 | AT47: 1758531 | AV47: 1916307 | AW47: 1916307 | AZ47: 95237320 | BC47: 490375 | BE47: 149828 | BF47: 48496 | BL47: 157776 | BQ47: 2652157 | BU47: 17384 | BV47: 17384 | CL47: 6672616 | CZ47: 36677
A48: 3 | B48: 1470 | C48: BERGEN | D48: FAIRVIEW BORO | E48: 200000 | F48: 379798 | G48: 72406 | H48: 45166 | J48: 1247370 | K48: 410172 | L48: 158861 | N48: 2 | O48: 569035 | Q48: 11056569 | V48: 218588 | W48: 11275157 | X48: 2026323 | Y48: 151808 | Z48: 802397 | AA48: 189162 | AB48: 54407 | AC48: 142737 | AD48: 628606 | AE48: 421071 | AG48: 5546591 | AH48: 16865080 | AJ48: 121104 | AK48: 991584 | AL48: 587765 | AM48: 367113 | AN48: 113195 | AO48: 1068073 | AP48: 2059657 | AQ48: 276896 | AT48: 276896 | AU48: 58155 | AV48: 335051 | AW48: 335051 | AZ48: 21076193 | BE48: 97174 | BF48: 114512 | BI48: 476213 | BJ48: 394267 | BR48: 918394 | CD48: 350000 | CG48: 43332 | DA48: 200000
A49: 3 | B49: 1550 | C49: BERGEN | D49: FORT LEE BORO | F49: 961257 | G49: 183028 | H49: 56337 | I49: 1103890 | J49: 2304512 | K49: 1071306 | M49: 1042756 | O49: 2114062 | Q49: 42581845 | U49: 53422 | V49: 451452 | W49: 43137529 | Y49: 234506 | Z49: 1892463 | AA49: 483210 | AB49: 184414 | AC49: 388189 | AD49: 3203089 | AE49: 1659219 | AG49: 8164764 | AH49: 51302293 | AJ49: 147760 | AK49: 147760 | AL49: 665539 | AM49: 739555 | AN49: 494676 | AO49: 1899770 | AP49: 3876310 | AZ49: 59610828 | BE49: 89951 | BF49: 29723 | BQ49: 50810 | BU49: 1828780 | BV49: 1828780 | BY49: 13651 | CI49: 13651 | CK49: 207920 | DB49: 30000
A50: 3 | B50: 1580 | C50: BERGEN | D50: FRANKLIN LAKES BORO | F50: 171123 | G50: 49766 | I50: 52288 | J50: 284357 | K50: 511126 | M50: -150779 | N50: 329 | O50: 360676 | P50: 1319 | Q50: 20267099 | R50: 1392942 | S50: 1392942 | V50: 131258 | W50: 21955099 | Y50: 353045 | Z50: 739427 | AB50: 44431 | AC50: 89911 | AD50: 1506439 | AE50: 885247 | AG50: 3737193 | AH50: 25693611 | AJ50: 127437 | AK50: 127437 | AM50: 312026 | AN50: 42296 | AO50: 354322 | AP50: 545032 | AQ50: 2287311 | AS50: 20961 | AT50: 2308272 | AV50: 2308272 | AW50: 2308272 | AX50: 1319 | AY50: -1319 | AZ50: 29453931 | BE50: 35471 | BF50: 83222 | BU50: 63273 | BV50: 63273 | BY50: 261983 | CC50: 2979 | CI50: 259004 | CL50: 11180 | CZ50: 163800 | DC50: 20961
A51: 3 | B51: 1700 | C51: BERGEN | D51: GARFIELD CITY | F51: 7734 | I51: 1 | J51: 823980 | K51: -200182 | L51: 700000 | M51: 467115 | N51: 27361 | O51: 994294 | Q51: 20348191 | V51: 856229 | W51: 21204420 | X51: 13587511 | Y51: 664602 | Z51: 2879851 | AA51: 618754 | AB51: 171284 | AC51: 453802 | AD51: 3331260 | AE51: 2125415 | AG51: 41411875 | AH51: 62956133 | AJ51: 347577 | AK51: 6678664 | AL51: 794521 | AM51: 1170835 | AN51: 384841 | AO51: 2350197 | AP51: 9985888 | AQ51: 507892 | AT51: 507892 | AU51: 395103 | AV51: 928278 | AW51: 928278 | AX51: 25283 | AY51: -25283 | AZ51: 89196040 | BA51: 816245 | BH51: 15359 | BI51: 2095651 | BJ51: 1330142 | BL51: 25283 | BU51: 9942 | BV51: 9942 | BY51: 13507467 | CA51: 15359 | CG51: 324479 | CI51: 13507467 | CO51: 16327786 | CP51: 2905294 | CQ51: 947085 | DD51: 1251610
A52: 3 | B52: 1760 | C52: BERGEN | D52: GLEN ROCK BORO | F52: 464334 | G52: 250098 | H52: 365085 | I52: 200765 | J52: 1280282 | K52: 817156 | L52: 217318 | M52: 143582 | N52: 1 | O52: 1178057 | Q52: 33730381 | S52: 269546 | V52: 318594 | W52: 34318521 | Y52: 76355 | Z52: 1209911 | AA52: 110582 | AB52: 152077 | AC52: 150896 | AD52: 2308442 | AE52: 1224144 | AG52: 5445987 | AH52: 39764508 | AJ52: 207768 | AK52: 207768 | AM52: 502797 | AN52: 72843 | AO52: 580947 | AP52: 788715 | AQ52: 1131604 | AT52: 1131604 | AV52: 1131604 | AW52: 1131604 | AY52: 182402 | AZ52: 44325568 | BC52: 269546 | BE52: 51301 | BR52: 162279 | BY52: 182402 | CK52: 182402 | DE52: 5307
A53: 3 | B53: 1860 | C53: BERGEN | D53: HACKENSACK CITY | F53: 1470267 | G53: 2712494 | H53: 3180087 | I53: 2226188 | J53: 9589036 | K53: 1543418 | L53: 517137 | M53: 2454283 | N53: 299230 | O53: 4814068 | P53: -2116899 | Q53: 53452727 | R53: 5273917 | S53: 5273917 | U53: 110654 | V53: 874143 | W53: 59711441 | Y53: 580033 | Z53: 4004188 | AA53: 472986 | AB53: 275791 | AC53: 514697 | AD53: 2687426 | AE53: 5445973 | AG53: 14649447 | AH53: 72244750 | AJ53: 580007 | AK53: 5114650 | AL53: 1020766 | AM53: 1170013 | AN53: 3117083 | AO53: 5308097 | AP53: 10456274 | AQ53: 1053774 | AT53: 1053774 | AV53: 1151585 | AW53: 1151585 | AY53: 2116899 | AZ53: 100372612 | BE53: 298852 | BF53: 367812 | BH53: 761 | BI53: 2435922 | BJ53: 2098721 | BK53: 235 | BM53: 97811 | BR53: 1689 | BU53: 33527 | BV53: 33527 | BY53: 2116899 | CA53: 761
A54: 3 | B54: 2050 | C54: BERGEN | D54: HARRINGTON PARK BORO | F54: 510247 | G54: 59550 | H54: 62812 | I54: 1 | J54: 632610 | K54: 159321 | M54: 5528 | N54: 12411 | O54: 177260 | Q54: 8245695 | V54: 60122 | W54: 8305817 | Y54: 26681 | Z54: 301878 | AA54: 20862 | AB54: 36778 | AC54: 39485 | AD54: 592275 | AE54: 296128 | AG54: 1369500 | AH54: 9675317 | AJ54: 3000 | AK54: 3000 | AM54: 100000 | AN54: 8829 | AO54: 108829 | AP54: 112511 | AQ54: 327097 | AT54: 327097 | AV54: 327097 | AW54: 327097 | AZ54: 10924795 | BE54: 11667 | BF54: 43746 | BU54: 682 | BV54: 682
A55: 3 | B55: 2080 | C55: BERGEN | D55: HASBROUCK HEIGHTS BORO | F55: 57302 | I55: 1 | J55: 57303 | K55: 438583 | N55: 30937 | O55: 469520 | Q55: 18764451 | S55: 250115 | V55: 114387 | W55: 19128953 | Y55: 132137 | Z55: 1121956 | AA55: 36172 | AB55: 111593 | AC55: 177308 | AD55: 1296758 | AE55: 755362 | AG55: 3676973 | AH55: 22908046 | AJ55: 218157 | AK55: 218157 | AM55: 358687 | AN55: 98098 | AO55: 456785 | AP55: 682942 | AQ55: 550690 | AT55: 550690 | AU55: 210587 | AV55: 761277 | AW55: 761277 | AZ55: 24879088 | BC55: 250115 | BE55: 44027 | BF55: 1660 | BU55: 8000 | BV55: 8000 | CG55: 102120
A56: 3 | B56: 2090 | C56: BERGEN | D56: HAWORTH BORO | F56: 25289 | G56: 232566 | I56: 29544 | J56: 287399 | K56: 135664 | L56: 365068 | M56: 709594 | N56: 58084 | O56: 1268410 | Q56: 6249910 | S56: 115637 | V56: 42429 | W56: 6407976 | Y56: 55451 | Z56: 165993 | AA56: 8248 | AC56: 29815 | AD56: 414183 | AE56: 237047 | AG56: 1018462 | AH56: 7427804 | AM56: 92849 | AN56: 5446 | AO56: 98295 | AP56: 100682 | AQ56: 489050 | AT56: 489050 | AU56: 101874 | AV56: 616963 | AW56: 616963 | AZ56: 9701258 | BC56: 115637 | BE56: 9676 | BF56: 35008 | BH56: 1366 | BL56: 26039 | BR56: 63041 | BU56: 2387 | BV56: 2387 | CA56: 1366
A57: 3 | B57: 2180 | C57: BERGEN | D57: HILLSDALE BORO | F57: 107533 | I57: 81441 | J57: 188974 | K57: 271270 | L57: 100000 | M57: 81076 | N57: 1 | O57: 452347 | P57: 7968 | Q57: 14542646 | S57: 90001 | V57: 71542 | W57: 14704189 | Z57: 710226 | AB57: 41502 | AC57: 148122 | AD57: 1266343 | AE57: 606178 | AG57: 2887926 | AH57: 17600083 | AJ57: 232989 | AK57: 232989 | AL57: 28153 | AM57: 339368 | AN57: 96048 | AO57: 463569 | AP57: 699714 | AQ57: 810828 | AT57: 810828 | AU57: 6899 | AV57: 817727 | AW57: 817727 | AX57: 7968 | AY57: -7968 | AZ57: 19758845 | BC57: 90001 | BE57: 25750 | BF57: 89805 | BU57: 3156 | BV57: 3156
A58: 3 | B58: 2200 | C58: BERGEN | D58: HO HO KUS BORO | F58: 129667 | G58: 13508 | H58: 26265 | I58: 157641 | J58: 327081 | K58: 231943 | L58: 109431 | M58: 161872 | O58: 503246 | Q58: 9458497 | R58: 418495 | S58: 455322 | U58: 2200 | V58: 124762 | W58: 10040781 | Z58: 578839 | AB58: 11903 | AC58: 44046 | AD58: 591611 | AE58: 315960 | AF58: 4993 | AG58: 1566039 | AH58: 11606820 | AJ58: 1156 | AK58: 1156 | AM58: 149256 | AN58: 10986 | AO58: 160242 | AP58: 175979 | AQ58: 781411 | AT58: 781411 | AU58: 86513 | AV58: 869348 | AW58: 869348 | AZ58: 13482474 | BC58: 36827 | BE58: 18687 | BL58: 1424 | BU58: 14581 | BV58: 14581 | CJ58: 135696
A59: 3 | B59: 2620 | C59: BERGEN | D59: LEONIA BORO | F59: 129408 | H59: 26338 | J59: 155746 | K59: 427217 | L59: 458518 | M59: 3350370 | N59: 154489 | O59: 4390594 | Q59: 14333093 | R59: 4975907 | S59: 4975907 | V59: 51765 | W59: 19360765 | X59: 1395172 | Y59: 97614 | Z59: 1105766 | AA59: 253886 | AB59: 21167 | AC59: 96686 | AD59: 1642096 | AE59: 889386 | AG59: 5628804 | AH59: 24989569 | AJ59: 103336 | AK59: 103336 | AL59: 84006 | AM59: 252659 | AN59: 95104 | AO59: 432109 | AP59: 535445 | AQ59: 1260323 | AR59: 116827 | AS59: 116827 | AT59: 1377150 | AU59: 48812 | AV59: 1425962 | AW59: 1425962 | AZ59: 31497316 | BE59: 88797 | BF59: 38234 | DE59: 340
A60: 3 | B60: 2710 | C60: BERGEN | D60: LITTLE FERRY BORO | E60: 150000 | F60: 222599 | G60: 94619 | H60: 189759 | I60: 96253 | J60: 753230 | K60: 307988 | L60: 929 | M60: 45515 | O60: 354432 | Q60: 13285276 | S60: 58273 | U60: 5079 | V60: 179812 | W60: 13528440 | Y60: 279789 | Z60: 790392 | AA60: 167706 | AB60: 45936 | AC60: 127824 | AD60: 557239 | AE60: 76249 | AG60: 2095734 | AH60: 15624174 | AK60: 90000 | AL60: 100061 | AM60: 245808 | AN60: 81237 | AO60: 430208 | AP60: 520208 | AU60: 478400 | AV60: 478400 | AW60: 478400 | AZ60: 17730444 | BC60: 58273 | BE60: 40971 | BF60: 9628 | BI60: 90000 | DE60: 3102
A61: 3 | B61: 2740 | C61: BERGEN | D61: LODI BOROUGH | F61: 210867 | G61: 1067419 | H61: 522039 | I61: 9257 | J61: 1882243 | K61: 905460 | L61: 616278 | M61: 1105 | N61: 1699 | O61: 1524542 | Q61: 30866646 | R61: 15170 | S61: 15170 | U61: 104 | V61: 485896 | W61: 31367816 | X61: 5210513 | Y61: 416900 | Z61: 1999480 | AA61: 331208 | AB61: 137767 | AC61: 343533 | AD61: 2740444 | AE61: 1362966 | AG61: 12862908 | AH61: 44241026 | AJ61: 84484 | AK61: 2184097 | AL61: 404860 | AM61: 722228 | AN61: 193036 | AO61: 1320124 | AP61: 3504221 | AQ61: 812481 | AT61: 812481 | AU61: 112708 | AV61: 925189 | AW61: 925189 | AX61: 331 | AZ61: 52077552 | BA61: 72661 | BE61: 313655 | BF61: 6442 | BH61: 10302 | BI61: 1490447 | BJ61: 609166 | BY61: 331 | CA61: 10302
A62: 3 | B62: 2860 | C62: BERGEN | D62: LYNDHURST TWP | F62: 299950 | J62: 299950 | K62: 327477 | L62: 700199 | N62: 284 | O62: 1027960 | Q62: 25756895 | R62: 12006 | S62: 12006 | V62: 218770 | W62: 25987671 | Y62: 272818 | Z62: 1300792 | AA62: 31824 | AB62: 86139 | AC62: 230631 | AD62: 2052735 | AE62: 1029913 | AG62: 5136914 | AH62: 31127518 | AI62: 70928 | AJ62: 133985 | AK62: 204913 | AL62: 184872 | AM62: 569830 | AN62: 88046 | AO62: 842748 | AP62: 1047661 | AQ62: 769000 | AT62: 769000 | AV62: 769000 | AW62: 769000 | AZ62: 34272089 | BE62: 59306 | BF62: 2867 | BH62: 2933 | BR62: 69889 | CA62: 2933
A63: 3 | B63: 2900 | C63: BERGEN | D63: MAHWAH TWP | F63: 814532 | G63: 926083 | H63: 712560 | I63: 999981 | J63: 3453156 | K63: 1136071 | L63: 597440 | M63: 1614457 | N63: 60457 | O63: 3408425 | Q63: 45107181 | S63: 6950 | T63: 34258 | U63: 60145 | V63: 572439 | W63: 45780973 | Y63: 756729 | Z63: 2519918 | AA63: 49128 | AB63: 203801 | AC63: 135321 | AD63: 2916813 | AE63: 1664800 | AG63: 8389950 | AH63: 54170923 | AJ63: 58642 | AK63: 58642 | AL63: 132248 | AM63: 639808 | AN63: 164346 | AO63: 936402 | AP63: 995044 | AQ63: 2844069 | AT63: 2844069 | AV63: 2851682 | AW63: 2851682 | AY63: 1281517 | AZ63: 66160747 | BC63: 6950 | BE63: 103833 | BF63: 39607 | BL63: 7613 | BY63: 1281517 | CJ63: 1060000 | DB63: 250000
A64: 3 | B64: 3060 | C64: BERGEN | D64: MAYWOOD BORO | E64: 261000 | F64: 42630 | G64: 624388 | H64: 385000 | I64: 53615 | J64: 16937033 | K64: 338251 | L64: 113806 | M64: -5631591 | N64: 311477 | O64: -4868057 | P64: 304593 | Q64: 13037857 | U64: 274395 | W64: 13405244 | Z64: 972595 | AA64: 4874 | AB64: 69167 | AC64: 123106 | AD64: 734197 | AE64: 372924 | AG64: 2319900 | AH64: 16029737 | AI64: 9357 | AJ64: 16326 | AK64: 25683 | AL64: 67732 | AM64: 239985 | AN64: 37358 | AO64: 345075 | AP64: 371758 | AQ64: 642041 | AT64: 642041 | AV64: 642041 | AW64: 642041 | AX64: 302344 | AY64: -304593 | AZ64: 36172652 | BE64: 33298 | BF64: 9739 | BQ64: 92992 | BU64: 1000 | BV64: 1000 | BX64: 2249 | BY64: 7060140 | CD64: 263000 | CI64: 5018140 | CL64: 15057400 | DA64: 250000 | DF64: 2042000
A65: 3 | B65: 3170 | C65: BERGEN | D65: MIDLAND PARK BORO | G65: 112719 | H65: 36046 | I65: 128532 | J65: 555318 | K65: 413940 | L65: 189707 | M65: -10478 | O65: 593169 | P65: 51 | Q65: 14448910 | R65: 63395 | S65: 63395 | U65: 4637 | V65: 164665 | W65: 16032778 | Z65: 857702 | AB65: 86138 | AC65: 124203 | AD65: 1075650 | AE65: 604059 | AG65: 2779426 | AH65: 18812255 | AJ65: 165493 | AK65: 165493 | AL65: 30940 | AM65: 285512 | AN65: 50870 | AO65: 367322 | AP65: 532815 | AQ65: 450590 | AT65: 450590 | AV65: 450590 | AW65: 450590 | AX65: 51 | AY65: -51 | AZ65: 20945125 | BE65: 29457 | BF65: 2217 | BQ65: 1351171 | BY65: 978 | CI65: 978 | CL65: 115750 | CV65: 162271
A66: 3 | B66: 3330 | C66: BERGEN | D66: MONTVALE BORO | F66: 45030 | G66: 329093 | H66: 345101 | I66: 83869 | J66: 803093 | K66: 292016 | L66: 100000 | M66: 1280043 | N66: 25020 | O66: 1697079 | Q66: 11418991 | S66: 56 | U66: 4035 | V66: 133721 | W66: 11594770 | Z66: 610682 | AB66: 37875 | AC66: 60967 | AD66: 991490 | AE66: 510958 | AG66: 2286031 | AH66: 13881645 | AK66: 1892 | AM66: 183529 | AN66: 26298 | AO66: 209827 | AP66: 215545 | AQ66: 547552 | AT66: 547552 | AV66: 590496 | AW66: 590496 | AZ66: 19558858 | BC66: 56 | BE66: 20149 | BF66: 53910 | BI66: 1892 | BL66: 42944 | BU66: 3826 | BV66: 3826 | BY66: 2371000 | CC66: 2371000 | CX66: 844 | CZ66: 37967
A67: 3 | B67: 3350 | C67: BERGEN | D67: MOONACHIE BORO | E67: 12000 | F67: 186746 | G67: 9160 | H67: 116138 | I67: 5252 | J67: 419296 | K67: 136962 | L67: 203814 | M67: 345 | N67: 1 | O67: 341122 | Q67: 5527255 | R67: 243997 | S67: 243997 | U67: 41074 | W67: 5919537 | Y67: 107383 | Z67: 362968 | AA67: 14016 | AB67: 12931 | AC67: 40158 | AD67: 136369 | AE67: 171797 | AG67: 864064 | AH67: 6783946 | AI67: 12891 | AJ67: 4500 | AK67: 17391 | AL67: 50558 | AM67: 92421 | AN67: 13538 | AO67: 156517 | AP67: 173908 | AQ67: 362116 | AT67: 362116 | AV67: 362116 | AW67: 362116 | AY67: -345 | AZ67: 8080043 | BE67: 16122 | BF67: 2320 | BQ67: 107211 | BY67: -345 | CX67: 345 | DA67: 90000
A68: 3 | B68: 3550 | C68: BERGEN | D68: NEW MILFORD BORO | F68: 775465 | G68: 231227 | H68: 618841 | I68: 459315 | J68: 2150386 | K68: 467926 | M68: 74163 | O68: 542089 | P68: 3809 | Q68: 22156722 | S68: 7549 | U68: 23321 | V68: 195304 | W68: 22391286 | Y68: 126397 | Z68: 1387088 | AA68: 69074 | AB68: 127019 | AC68: 215271 | AD68: 1955709 | AE68: 789590 | AF68: 13548 | AG68: 4738373 | AH68: 27296468 | AI68: 24734 | AJ68: 500445 | AK68: 525179 | AL68: 87309 | AM68: 741940 | AN68: 65800 | AO68: 895049 | AP68: 1420228 | AQ68: 539088 | AT68: 539088 | AV68: 539088 | AW68: 539088 | AX68: 3809 | AY68: -3809 | AZ68: 31957409 | BB68: 65538 | BC68: 7549 | BE68: 54677 | BQ68: 3887 | BY68: 9150 | CG68: 163000 | CI68: 9150 | CZ68: 4503
A69: 3 | B69: 3600 | C69: BERGEN | D69: NORTH ARLINGTON BORO | F69: 551309 | G69: 327763 | H69: 140803 | I69: 1861998 | J69: 3065343 | K69: 369122 | L69: 65648 | M69: 2383 | N69: 3 | O69: 437156 | Q69: 17526121 | U69: 100963 | V69: 213745 | W69: 17840829 | Y69: 134920 | Z69: 1194232 | AA69: 120304 | AB69: 60581 | AC69: 160411 | AD69: 1351412 | AE69: 617441 | AG69: 3692934 | AH69: 21649096 | AI69: 40929 | AJ69: 389948 | AK69: 430877 | AL69: 92771 | AM69: 467136 | AN69: 93682 | AO69: 723491 | AP69: 1165538 | AQ69: 1009797 | AT69: 1009797 | AV69: 1009797 | AW69: 1009797 | AY69: 12850 | AZ69: 27574341 | BE69: 49524 | BF69: 4109 | BU69: 11170 | BV69: 11170 | BY69: 247411 | CG69: 115333 | CI69: 234561 | CL69: 183470 | DG69: 69902
A70: 3 | B70: 3700 | C70: BERGEN | D70: NORTHERN HIGHLANDS REG | F70: 923701 | G70: 874777 | H70: 633928 | I70: 88672 | J70: 2574425 | K70: 502636 | L70: 153347 | M70: 1079149 | O70: 1735132 | P70: 66209 | Q70: 16298379 | R70: 3288700 | S70: 3288700 | U70: 4883 | V70: 251891 | W70: 19843853 | Y70: 260888 | Z70: 318012 | AA70: 13962 | AB70: 69274 | AC70: 74019 | AD70: 1452064 | AE70: 745206 | AF70: 7322 | AG70: 3086523 | AH70: 22996585 | AM70: 159173 | AN70: 20195 | AO70: 179368 | AP70: 179368 | AQ70: 1441219 | AT70: 1441219 | AV70: 1441219 | AW70: 1441219 | AZ70: 28926729 | BA70: 53347 | BE70: 20006 | BF70: 125770 | CJ70: 787275
A71: 3 | B71: 3710 | C71: BERGEN | D71: NORTHERN VALLEY REGIONAL | F71: 619636 | I71: 513344 | J71: 1678105 | K71: 790385 | L71: 1000000 | M71: 2176353 | N71: 510303 | O71: 4477041 | P71: -3140 | Q71: 37517322 | S71: 423047 | U71: 34578 | V71: 953541 | W71: 38928488 | Y71: 273847 | Z71: 1232560 | AA71: 25984 | AB71: 171728 | AC71: 183891 | AD71: 3247706 | AE71: 1744936 | AG71: 7111575 | AH71: 46036923 | AJ71: 120116 | AK71: 120116 | AL71: 68545 | AM71: 269284 | AN71: 340018 | AO71: 677847 | AP71: 797963 | AQ71: 1117715 | AT71: 1117715 | AV71: 1312989 | AW71: 1312989 | AX71: 2051374 | AZ71: 56354395 | BC71: 423047 | BE71: 52539 | BF71: 143358 | BL71: 195274 | BR71: 35026 | BY71: 2051374 | CL71: 545125
A72: 3 | B72: 3730 | C72: BERGEN | D72: NORTHVALE BORO | F72: 15515 | H72: 28770 | J72: 676643 | K72: 188928 | M72: 298621 | O72: 487549 | P72: 14278 | Q72: 6362000 | R72: 186288 | S72: 186288 | V72: 30478 | W72: 6578766 | Y72: 7781 | Z72: 204920 | AA72: 22210 | AB72: 57800 | AC72: 61882 | AD72: 581317 | AE72: 255326 | AG72: 1275735 | AH72: 7868779 | AM72: 110156 | AN72: 33072 | AO72: 143228 | AP72: 180603 | AQ72: 445807 | AT72: 445807 | AV72: 445807 | AW72: 445807 | AX72: 14143 | AY72: -14143 | AZ72: 9662242 | BE72: 10323 | BF72: 26861 | BR72: 47315 | BU72: 37375 | BV72: 37375 | BY72: 2861 | CL72: 632358 | DH72: 2861
A73: 3 | B73: 3740 | C73: BERGEN | D73: NORWOOD BORO | G73: 7563 | H73: 47231 | I73: 3718 | J73: 58512 | K73: 229207 | M73: 4980437 | N73: 218049 | O73: 5427693 | Q73: 7119914 | R73: 14550 | S73: 14550 | U73: 3730 | V73: 36675 | W73: 7174869 | Y73: 55490 | Z73: 457301 | AB73: 59974 | AC73: 42770 | AD73: 541711 | AE73: 264601 | AG73: 1506648 | AH73: 8681517 | AJ73: 125052 | AK73: 125052 | AM73: 172344 | AO73: 172344 | AP73: 297396 | AQ73: 428632 | AT73: 428632 | AV73: 667046 | AW73: 667046 | AX73: 238414 | AY73: -238414 | AZ73: 16208413 | BE73: 18500 | BF73: 5202 | BL73: 238414 | BR73: 61099 | BY73: 1076249 | CI73: 1076249
A74: 3 | B74: 3760 | C74: BERGEN | D74: OAKLAND BORO | F74: 787634 | G74: 153782 | H74: 93165 | I74: 168545 | J74: 1203126 | K74: 434141 | M74: -70472 | O74: 363669 | Q74: 21459443 | T74: 84313 | W74: 21724481 | Z74: 892731 | AB74: 87224 | AC74: 98574 | AD74: 1945335 | AE74: 787246 | AG74: 3850131 | AH74: 25574612 | AJ74: 143804 | AK74: 143804 | AM74: 371324 | AN74: 36339 | AO74: 407663 | AP74: 551467 | AV74: 64131 | AW74: 64131 | AX74: 64131 | AY74: -64131 | AZ74: 30490005 | BE74: 29739 | BF74: 9282 | BL74: 64131 | BQ74: 180725 | BX74: 2733000 | BY74: 2733000
A75: 3 | B75: 3850 | C75: BERGEN | D75: OLD TAPPAN BORO | F75: 25423 | G75: 1134496 | H75: 675732 | I75: 25000 | J75: 2239804 | K75: 235538 | M75: -151676 | N75: 39731 | O75: 123593 | Q75: 10284928 | R75: 22529 | S75: 22529 | V75: 190333 | W75: 10497790 | Y75: 88321 | Z75: 82197 | AA75: 72 | AB75: 42523 | AC75: 49055 | AD75: 684152 | AE75: 354270 | AG75: 1692782 | AH75: 12190572 | AJ75: 5000 | AK75: 5000 | AM75: 147568 | AN75: 4556 | AO75: 152124 | AP75: 184649 | AQ75: 702834 | AT75: 702834 | AU75: 210789 | AV75: 913640 | AW75: 913640 | AX75: 17 | AY75: -17 | AZ75: 15803910 | BE75: 17402 | BF75: 14352 | BL75: 17 | BR75: 360438 | BU75: 27525 | BV75: 27525 | BY75: 151652 | CI75: 151652 | CL75: 379153
A76: 3 | B76: 3870 | C76: BERGEN | D76: ORADELL BORO | F76: 53810 | G76: 250122 | H76: 265253 | I76: 112 | J76: 569297 | K76: 208674 | L76: 200000 | M76: 6035380 | N76: 4733 | O76: 6448787 | P76: 117418 | Q76: 7681644 | R76: 36942 | S76: 36942 | U76: 3 | V76: 45889 | W76: 7764478 | Y76: 19263 | Z76: 404414 | AA76: 19856 | AB76: 32894 | AC76: 29289 | AD76: 521165 | AE76: 306076 | AG76: 1384762 | AH76: 9266658 | AJ76: 126385 | AK76: 126385 | AM76: 194029 | AN76: 26494 | AO76: 220523 | AP76: 346908 | AQ76: 1331741 | AT76: 1331741 | AV76: 1331741 | AW76: 1331741 | AX76: 117418 | AY76: -117418 | AZ76: 20160959 | BE76: 14185 | BF76: 37620 | BY76: 2197568 | CI76: 2197568
A77: 3 | B77: 3910 | C77: BERGEN | D77: PALISADES PARK | F77: 383099 | G77: 182416 | H77: 30083 | I77: 49019 | J77: 934617 | K77: 423571 | L77: 574203 | M77: 117349 | N77: -8964 | O77: 1106159 | Q77: 16269671 | S77: 18000 | U77: 4946 | V77: 225358 | W77: 16517975 | Y77: 60899 | Z77: 830472 | AA77: 287436 | AB77: 74646 | AC77: 158050 | AD77: 1350234 | AE77: 668646 | AG77: 3659599 | AH77: 20177574 | AI77: 11034 | AJ77: 102515 | AK77: 249859 | AL77: 228197 | AM77: 311841 | AN77: 159995 | AO77: 700033 | AP77: 949892 | AQ77: 551878 | AT77: 551878 | AV77: 595883 | AW77: 595883 | AX77: 44005 | AY77: 150000 | AZ77: 23958130 | BC77: 18000 | BE77: 44713 | BF77: 7568 | BJ77: 136310 | BL77: 44005 | BR77: 176935 | BY77: 194005 | CJ77: 257030 | CL77: 290000
A78: 3 | B78: 3930 | C78: BERGEN | D78: PARAMUS BORO | F78: 619544 | G78: 200000 | H78: 599679 | I78: 45450 | J78: 1464673 | K78: 1355247 | L78: 552670 | M78: 15715529 | N78: -455824 | O78: 17167622 | P78: 491391 | Q78: 57512840 | R78: 134744 | S78: 153841 | V78: 1221599 | W78: 59142064 | Y78: 14258 | Z78: 2612975 | AA78: 249718 | AB78: 128462 | AC78: 477611 | AD78: 4684736 | AE78: 2051862 | AG78: 10352782 | AH78: 69986237 | AJ78: 1213276 | AK78: 1213276 | AL78: 293118 | AM78: 1304399 | AN78: 262337 | AO78: 1859854 | AP78: 3125364 | AQ78: 3331654 | AT78: 3331654 | AU78: 230235 | AV78: 3561889 | AW78: 3561889 | AX78: 491391 | AY78: -491391 | AZ78: 108532912 | BC78: 19097 | BE78: 100637 | BF78: 32523 | BQ78: 253784 | BU78: 52234 | BV78: 52234 | BY78: 13227127 | CC78: 3149861 | CI78: 10077266
A79: 3 | B79: 3940 | C79: BERGEN | D79: PARK RIDGE BORO | F79: 436399 | I79: 1 | J79: 436400 | K79: 492574 | L79: 175000 | M79: 16732 | N79: 1 | O79: 684307 | P79: 125000 | Q79: 18869664 | R79: 55079 | S79: 55079 | V79: 214915 | W79: 19139658 | Z79: 671137 | AB79: 112567 | AC79: 78444 | AD79: 1531491 | AE79: 638601 | AG79: 3054727 | AH79: 22319385 | AJ79: 92891 | AK79: 92891 | AM79: 312311 | AN79: 35596 | AO79: 347907 | AP79: 454582 | AQ79: 244215 | AT79: 244215 | AV79: 244215 | AW79: 244215 | AX79: 10186 | AZ79: 24149075 | BE79: 22487 | BU79: 13784 | BV79: 13784 | BY79: 10186
A80: 3 | B80: 3960 | C80: BERGEN | D80: PASCACK VALLEY REGIONAL | F80: 479720 | H80: 1264806 | I80: 1 | J80: 1744527 | K80: 698991 | L80: 1016605 | M80: 20482646 | N80: 1 | O80: 22198243 | P80: 355120 | Q80: 31336279 | R80: 124758 | S80: 124758 | V80: 276587 | W80: 31737624 | Y80: 386632 | Z80: 968056 | AA80: 2336 | AB80: 60594 | AC80: 123610 | AD80: 2610879 | AE80: 1103378 | AG80: 5427807 | AH80: 37520551 | AJ80: 233530 | AK80: 233530 | AL80: 39504 | AN80: 409304 | AO80: 448808 | AP80: 682338 | AQ80: 1793563 | AT80: 1793563 | AV80: 1793563 | AW80: 1793563 | AX80: 355120 | AY80: -355120 | AZ80: 63939222 | BE80: 44419 | BF80: 127903
A81: 3 | B81: 4300 | C81: BERGEN | D81: RAMAPO-INDIAN HILL REG | F81: 452880 | G81: 599118 | H81: 174002 | I81: 327406 | J81: 2083557 | K81: 952944 | L81: 333458 | M81: -26919 | N81: 89783 | O81: 1349266 | Q81: 38678558 | R81: 70905 | S81: 70905 | U81: 73329 | V81: 374824 | W81: 39494147 | Y81: 366335 | Z81: 1250247 | AA81: 7044 | AB81: 125592 | AC81: 133385 | AD81: 2926732 | AE81: 1170571 | AG81: 6177115 | AH81: 45671262 | AJ81: 47080 | AK81: 47080 | AL81: 66721 | AM81: 398846 | AN81: 21516 | AO81: 487083 | AP81: 581383 | AQ81: 1667375 | AT81: 1667375 | AV81: 1667375 | AW81: 1667375 | AZ81: 51567522 | BA81: 91369 | BE81: 52710 | BF81: 144499 | BQ81: 274983 | BU81: 47220 | BV81: 47220 | BY81: 214679 | CI81: 214679 | CL81: 438782 | CZ81: 21548
A82: 3 | B82: 4310 | C82: BERGEN | D82: RAMSEY BORO | G82: 234030 | H82: 629177 | I82: 311017 | J82: 1174224 | K82: 1076832 | L82: 134448 | M82: 5700341 | N82: 577233 | O82: 7488854 | Q82: 39011486 | R82: 1667528 | S82: 1667528 | V82: 270321 | W82: 40977364 | Y82: 113807 | Z82: 1602397 | AA82: 49020 | AB82: 222166 | AC82: 186957 | AD82: 3304358 | AE82: 1561093 | AG82: 7239281 | AH82: 48218781 | AJ82: 314685 | AK82: 314685 | AM82: 683223 | AN82: 71396 | AO82: 754619 | AP82: 1069304 | AQ82: 2190293 | AT82: 2190293 | AV82: 2475452 | AW82: 2475452 | AX82: 285159 | AY82: -84585 | AZ82: 60725305 | BE82: 58565 | BF82: 140918 | BH82: 2136 | BL82: 285159 | BQ82: 14728 | BY82: 298690 | CA82: 2136 | CC82: 98116 | CZ82: 13301
A83: 3 | B83: 4370 | C83: BERGEN | D83: RIDGEFIELD BORO | F83: 185658 | G83: 260751 | I83: 1 | J83: 3438653 | K83: 564834 | M83: -2246754 | O83: -1681920 | P83: 43004 | Q83: 12826957 | R83: 13711452 | S83: 13711452 | V83: 330695 | W83: 28180273 | X83: 911179 | Y83: 37368 | Z83: 795291 | AA83: 143502 | AB83: 5052 | AC83: 203311 | AD83: 1751049 | AE83: 1067114 | AG83: 5057918 | AH83: 33281195 | AI83: 70950 | AJ83: 99267 | AK83: 258471 | AL83: 210750 | AM83: 239412 | AN83: 117560 | AO83: 567722 | AP83: 847989 | AV83: 4242 | AW83: 4242 | AX83: 32702 | AY83: -32023 | AZ83: 44298838 | BA83: 155243 | BE83: 67496 | BF83: 76556 | BJ83: 88254 | BL83: 4242 | BQ83: 1311169 | BU83: 21796 | BV83: 21796 | BX83: 8408000 | BY83: 8408679 | CD83: 511000 | CL83: 2326000
A84: 3 | B84: 4380 | C84: BERGEN | D84: RIDGEFIELD PARK TWP | G84: 426951 | H84: 102926 | I84: 102 | J84: 529979 | K84: 696025 | L84: 196470 | N84: 468 | O84: 892963 | Q84: 19431797 | R84: 3619159 | S84: 3619159 | U84: 2 | V84: 287944 | W84: 23338902 | X84: 328787 | Y84: 261054 | Z84: 1203765 | AA84: 108696 | AB84: 77739 | AC84: 191242 | AD84: 1878888 | AE84: 1000977 | AG84: 6653543 | AH84: 29992445 | AI84: 81879 | AJ84: 182685 | AK84: 318739 | AL84: 347920 | AM84: 537985 | AN84: 181569 | AO84: 1067474 | AP84: 1386213 | AQ84: 416161 | AT84: 416161 | AU84: 217200 | AV84: 633361 | AW84: 633361 | AZ84: 33434961 | BE84: 107618 | BF84: 137104 | BJ84: 54175 | BR84: 1357673
A85: 3 | B85: 4390 | C85: BERGEN | D85: RIDGEWOOD VILLAGE | F85: 512093 | G85: 1526711 | H85: 1650875 | I85: 262494 | J85: 5563718 | K85: 1814300 | L85: 16150 | M85: 6967 | N85: 11023 | O85: 1848440 | Q85: 67994062 | R85: 322482 | S85: 570751 | U85: 13709 | V85: 956061 | W85: 71151787 | Z85: 2551192 | AA85: 137922 | AB85: 393046 | AC85: 366139 | AD85: 5812214 | AE85: 2805090 | AG85: 12246682 | AH85: 84017074 | AJ85: 2025 | AK85: 2025 | AL85: 177746 | AM85: 876476 | AN85: 176173 | AO85: 1230395 | AP85: 1648552 | AQ85: 1381771 | AT85: 1381771 | AU85: 517670 | AV85: 1899441 | AW85: 1899441 | AZ85: 94977225 | BA85: 1607455 | BC85: 142580 | BE85: 91658 | BF85: 89421 | BQ85: 1114975 | BU85: 416132 | BV85: 416132 | CE85: 440324 | CG85: 618605 | CL85: 4090 | CY85: 15417 | CZ85: 1066 | DI85: 105689 | DJ85: 35720 | DK85: 9702
A86: 3 | B86: 4405 | C86: BERGEN | D86: RIVER DELL REGIONAL | F86: 177058 | G86: 1039365 | H86: 242879 | I86: 107612 | J86: 11640565 | K86: 505717 | M86: 1148042 | N86: 17890 | O86: 1671649 | P86: 26548 | Q86: 20393526 | R86: 269577 | S86: 269577 | U86: 1346 | V86: 339696 | W86: 21061163 | Y86: 125173 | Z86: 615366 | AA86: 53674 | AB86: 101578 | AC86: 101699 | AD86: 1886917 | AE86: 833617 | AG86: 3842650 | AH86: 25748395 | AJ86: 266911 | AK86: 266911 | AM86: 341753 | AN86: 83654 | AO86: 425407 | AP86: 700818 | AQ86: 2198091 | AT86: 2198091 | AV86: 2198091 | AW86: 2198091 | AX86: 26548 | AY86: -26548 | AZ86: 41959518 | BF86: 43602 | BQ86: 57018 | BR86: 81024 | BU86: 8500 | BV86: 8500 | CG86: 818034 | CL86: 10073651 | DL86: 107428
A87: 3 | B87: 4410 | C87: BERGEN | D87: RIVER EDGE BORO | F87: 62837 | G87: 418946 | H87: 106617 | I87: 1 | J87: 14517448 | K87: 251761 | M87: -5271002 | N87: 190331 | O87: -4828910 | Q87: 10462823 | S87: 8000 | V87: 161604 | W87: 10682202 | Y87: 35444 | Z87: 335553 | AA87: 72254 | AB87: 48050 | AC87: 112573 | AD87: 860910 | AE87: 435598 | AG87: 1999289 | AH87: 12681491 | AJ87: 384617 | AK87: 384617 | AM87: 319219 | AN87: 60960 | AO87: 380179 | AP87: 764796 | AQ87: 996710 | AT87: 996710 | AV87: 1537994 | AW87: 1537994 | AX87: 530503 | AY87: -541284 | AZ87: 33535592 | BC87: 8000 | BE87: 16675 | BF87: 82232 | BL87: 541284 | BQ87: 49775 | BY87: 8862773 | CC87: 8865781 | CL87: 13929047 | DH87: 7773
A88: 3 | B88: 4430 | C88: BERGEN | D88: RIVER VALE TWP | F88: 302945 | G88: 191263 | H88: 123401 | I88: 205507 | J88: 1431809 | K88: 346068 | M88: 192773 | N88: 1 | O88: 538842 | P88: 20298 | Q88: 15429737 | S88: 15087 | U88: 101171 | W88: 15582011 | Y88: 101086 | Z88: 440480 | AA88: 23324 | AB88: 58666 | AC88: 74496 | AD88: 1323409 | AE88: 630492 | AG88: 2676558 | AH88: 18278867 | AJ88: 4000 | AK88: 4000 | AM88: 230762 | AN88: 29326 | AO88: 260088 | AP88: 265241 | AQ88: 984356 | AT88: 984356 | AV88: 984356 | AW88: 984356 | AX88: 30149 | AY88: -20298 | AZ88: 21508966 | BC88: 15087 | BE88: 19182 | BF88: 5423 | BQ88: 36016 | BV88: 1153 | BY88: 9851 | CL88: 608693 | DM88: 1153
A89: 3 | B89: 4470 | C89: BERGEN | D89: ROCHELLE PARK TWP | F89: 4000 | G89: 179082 | H89: 42602 | I89: 39806 | J89: 265490 | K89: 240345 | M89: 63828 | N89: 4758 | O89: 308931 | Q89: 8441799 | R89: 12810 | S89: 12810 | U89: 2011 | V89: 68848 | W89: 8525468 | Y89: 220066 | Z89: 297023 | AA89: 12866 | AB89: 37559 | AC89: 70550 | AD89: 534683 | AE89: 260936 | AG89: 1452294 | AH89: 9977762 | AI89: 19454 | AK89: 19454 | AL89: 23520 | AM89: 120093 | AN89: 7121 | AO89: 150734 | AP89: 210688 | AQ89: 277229 | AS89: 3708 | AT89: 280937 | AV89: 280937 | AW89: 280937 | AZ89: 11043808 | BE89: 18611 | BU89: 40500 | BV89: 40500 | DC89: 3708
A90: 3 | B90: 4500 | C90: BERGEN | D90: ROCKLEIGH | G90: 100959 | H90: 113409 | J90: 214368 | K90: 107689 | L90: 915 | O90: 108604 | Q90: 391267 | W90: 402385 | Y90: 12961 | Z90: 10251 | AB90: 8916 | AC90: 1975 | AE90: 1102 | AG90: 37701 | AH90: 440086 | AZ90: 763058 | BE90: 756 | BF90: 1740 | BQ90: 11118
A91: 3 | B91: 4600 | C91: BERGEN | D91: RUTHERFORD BORO | F91: 543947 | G91: 207886 | I91: 189487 | J91: 941320 | K91: 633925 | L91: 170531 | M91: 907895 | N91: 107509 | O91: 1819860 | P91: 115906 | Q91: 30302192 | R91: 9462 | S91: 9462 | U91: 7579 | V91: 163295 | W91: 30482528 | Y91: 160785 | Z91: 1463029 | AA91: 38778 | AB91: 86411 | AC91: 261792 | AD91: 2336320 | AE91: 1243641 | AG91: 6485754 | AH91: 37303568 | AJ91: 192754 | AK91: 192754 | AM91: 472709 | AN91: 82294 | AO91: 555003 | AP91: 747757 | AQ91: 1855225 | AT91: 1855225 | AV91: 1888682 | AW91: 1888682 | AX91: 165063 | AZ91: 42866250 | BE91: 82118 | BL91: 33457 | BR91: 812880 | BY91: 165063 | CG91: 219380
A92: 3 | B92: 4610 | C92: BERGEN | D92: SADDLE BROOK TWP | F92: 203138 | J92: 361761 | K92: 532589 | L92: 100000 | M92: 508342 | O92: 1140931 | P92: 40118 | Q92: 20753135 | R92: 428179 | S92: 428179 | W92: 21295737 | Y92: 170310 | Z92: 1256342 | AA92: 37412 | AB92: 183772 | AC92: 190035 | AD92: 1685832 | AE92: 752488 | AG92: 4345104 | AH92: 25680959 | AJ92: 18626 | AK92: 18626 | AL92: 91535 | AM92: 349857 | AN92: 70659 | AO92: 512051 | AP92: 534333 | AQ92: 1766865 | AT92: 1766865 | AV92: 1766865 | AW92: 1766865 | AX92: 40118 | AY92: -40118 | AZ92: 29618405 | BE92: 49623 | BF92: 19290 | BQ92: 114423 | BU92: 3656 | BV92: 3656 | BY92: 133556 | CI92: 133556 | CL92: 158623
A93: 3 | B93: 4620 | C93: BERGEN | D93: SADDLE RIVER BORO | F93: 210010 | G93: 393783 | H93: 81016 | I93: 344836 | J93: 1921038 | K93: 164745 | L93: 542842 | M93: 125188 | N93: 2934 | O93: 835709 | P93: 16460 | Q93: 6289800 | R93: 75188 | S93: 75188 | U93: 17190 | V93: 6391 | W93: 6491131 | Y93: 83420 | Z93: 226624 | AA93: 4654 | AB93: 42696 | AC93: 17341 | AD93: 275902 | AE93: 145403 | AG93: 814971 | AH93: 7322562 | AJ93: 38728 | AK93: 38728 | AM93: 110050 | AN93: 10877 | AO93: 120927 | AP93: 196459 | AQ93: 127170 | AT93: 127170 | AV93: 127170 | AW93: 127170 | AX93: 16460 | AY93: -16460 | AZ93: 10620247 | BB93: 42500 | BE93: 9961 | BF93: 8970 | BQ93: 102562 | BU93: 36804 | BV93: 36804 | BY93: 217309 | CI93: 217309 | CL93: 848893
A94: 3 | B94: 4845 | C94: BERGEN | D94: SOUTH BERGEN JOINTURE COM | F94: 127308 | J94: 127308 | K94: 3136408 | O94: 3136408 | S94: 12294442 | T94: 19331492 | V94: 2809514 | W94: 34612149 | AD94: 509239 | AE94: 550383 | AG94: 1059622 | AH94: 35671771 | AZ94: 38935487 | BC94: 12294442 | BQ94: 176701
A95: 3 | B95: 4870 | C95: BERGEN | D95: SOUTH HACKENSACK TWP | G95: 100282 | J95: 100282 | K95: 132309 | L95: 76418 | M95: 1551178 | N95: 161531 | O95: 1921436 | Q95: 5091935 | R95: 73470 | S95: 73470 | V95: 160118 | W95: 5325523 | Y95: 14640 | Z95: 324441 | AA95: 26720 | AB95: 35117 | AC95: 32038 | AD95: 242865 | AE95: 107802 | AG95: 795911 | AH95: 6121644 | AI95: 11760 | AK95: 11760 | AL95: 22656 | AM95: 62770 | AN95: 114062 | AO95: 199488 | AP95: 211248 | AQ95: 527830 | AS95: 240588 | AT95: 768418 | AV95: 768418 | AW95: 768418 | AZ95: 9123028 | BE95: 12288 | BH95: 210 | CA95: 210 | DC95: 240588
A96: 3 | B96: 5150 | C96: BERGEN | D96: TEANECK TWP | F96: 1163385 | G96: 1972989 | H96: 1119006 | I96: 534661 | J96: 6380837 | K96: 2015505 | L96: 480686 | M96: 595486 | O96: 3091677 | P96: -450000 | Q96: 71386061 | R96: 192172 | S96: 204637 | T96: 30231 | U96: 53060 | V96: 450724 | W96: 72124713 | Y96: 1351777 | Z96: 3431277 | AA96: 111104 | AB96: 356965 | AC96: 506682 | AD96: 5308816 | AE96: 2371489 | AG96: 13715456 | AH96: 85390169 | AI96: 174894 | AJ96: 516864 | AK96: 691758 | AL96: 278537 | AM96: 962509 | AN96: 188410 | AO96: 1429456 | AP96: 2352460 | AQ96: 1770877 | AT96: 1770877 | AV96: 1770877 | AW96: 1770877 | AX96: 2078 | AZ96: 99906288 | BC96: 12465 | BE96: 150527 | BF96: 126819 | BU96: 231246 | BV96: 231246 | BY96: 920268 | CC96: 450000 | CI96: 468190 | CL96: 1590796
A97: 3 | B97: 5160 | C97: BERGEN | D97: TENAFLY BORO | F97: 28511 | G97: 345644 | H97: 57027 | I97: 363360 | J97: 833042 | K97: 1214246 | M97: 23991530 | N97: 613583 | O97: 25819359 | Q97: 43105141 | R97: 967893 | S97: 1057457 | U97: 18177 | V97: 655011 | W97: 44835786 | Y97: 176208 | Z97: 1415475 | AA97: 223196 | AB97: 355434 | AC97: 215130 | AD97: 3238229 | AE97: 1739574 | AG97: 7610899 | AH97: 52446685 | AJ97: 117786 | AK97: 117786 | AM97: 739768 | AN97: 191726 | AO97: 931494 | AP97: 1315834 | AQ97: 1836220 | AT97: 1836220 | AV97: 3005692 | AW97: 3005692 | AX97: 1169418 | AY97: -1169472 | AZ97: 90931612 | BC97: 89564 | BE97: 60900 | BF97: 186753 | BL97: 1169472 | BU97: 266554 | BV97: 266554 | BX97: 7511000 | BY97: 7511000 | CL97: 38500 | DF97: 54
A98: 3 | B98: 5170 | C98: BERGEN | D98: TETERBORO | G98: 91188 | H98: 162826 | J98: 254014 | K98: 100000 | O98: 100000 | Q98: 95316 | W98: 111125 | AC98: 2085 | AG98: 2745 | AH98: 113870 | AZ98: 467884 | BE98: 80 | BQ98: 15809 | BR98: 580
A99: 3 | B99: 5330 | C99: BERGEN | D99: UPPER SADDLE RIVER BORO | F99: 175475 | G99: 473474 | H99: 253186 | I99: 366676 | J99: 1269811 | K99: 437069 | L99: 88100 | M99: 112452 | N99: 21503 | O99: 659124 | Q99: 16723037 | R99: 112785 | S99: 112785 | U99: 13691 | V99: 144004 | W99: 16993517 | Y99: 71715 | Z99: 645244 | AA99: 24456 | AB99: 92820 | AC99: 77418 | AD99: 1211759 | AE99: 641135 | AG99: 2797739 | AH99: 19866497 | AJ99: 1988 | AK99: 1988 | AM99: 239522 | AN99: 22577 | AO99: 262099 | AP99: 264087 | AQ99: 737134 | AT99: 737134 | AU99: 293149 | AV99: 1030283 | AW99: 1030283 | AX99: 328 | AZ99: 23090130 | BE99: 24565 | BF99: 8627 | BY99: 328 | CG99: 75241 | CL99: 1000
A100: 3 | B100: 5410 | C100: BERGEN | D100: WALDWICK BORO | F100: 79829 | G100: 872407 | H100: 173651 | I100: 1 | J100: 1710315 | K100: 503385 | M100: 367990 | N100: 2041 | O100: 873416 | P100: -521656 | Q100: 20796714 | S100: 17000 | V100: 230477 | W100: 21044191 | Y100: 148593 | Z100: 918126 | AA100: 81436 | AB100: 105163 | AC100: 172370 | AD100: 1823248 | AE100: 749773 | AG100: 4044662 | AH100: 24632724 | AJ100: 140986 | AK100: 140986 | AM100: 336360 | AN100: 86549 | AO100: 422909 | AP100: 563895 | AQ100: 674742 | AT100: 674742 | AV100: 674742 | AW100: 674742 | AX100: 28344 | AY100: 521656 | AZ100: 29005092 | BC100: 17000 | BE100: 39616 | BF100: 6337 | BY100: 550000 | CG100: 65527 | CL100: 584427
...

Sheet State Dist
G1: Local | H1: Local | I1: Local | J1: Local | K1: Local | L1: Local | M1: Local | N1: Local | P1: State | Q1: State | R1: State | S1: State | T1: State | U1: State | V1: State | W1: State | X1: State | Y1: State | Z1: State | AA1: State | AB1: State | AC1: State | AD1: State | AE1: State | AF1: State | AG1: State | AH1: State | AI1: State | AJ1: State | AK1: State | AL1: State | AM1: State | AN1: State | AO1: State | AP1: State | AQ1: State | AR1: State | AS1: State | AT1: State | AU1: State Revenue - Special Revenue Funds | AW1: Federal | AX1: Federal | AY1: Federal | AZ1: Federal | BA1: Federal | BB1: Federal | BC1: Federal Revenue | BD1: Federal Revenue | BE1: Federal Revenue | BG1: Other | BH1: Other | BI1: Other | BJ1: Other | BK1: Other | BL1: Other | BM1: Other | BN1: Other | BO1: Other | BP1: Other | BR1: Other | BS1: Other | BT1: Other | BU1: Other | BV1: Other | BW1: Other | BX1: Other | BY1: Other | BZ1: Other | CA1: Other | CB1: Other | CD1: Indeterminate | CE1: Indeterminate | CF1: Indeterminate | CG1: Indeterminate | CI1: Intermediate | CJ1: Intermediate | CM1: Capital Projects Fund | CN1: Capital Projects | CO1: State | CP1: State | CQ1: State | CR1: Federal | CS1: Federal | CT1: State | CU1: State | CV1: Indeterminate
A2: CO | B2: DIST | C2: CONAME | D2: DISTNAME | F2: Enrollment | G2: Local Tax Levy | H2: Unrestricted Misc Revenues | I2: County Tax Levy | J2: Other Local Govt Units - Unrestricted | K2: Other Local Govt Units - Restricted | L2: Other Revenue from Local Sources | M2: Local Tax Levy | N2: Municipal Surplus | O2: Total Local | P2: Core Curriculum Standards Aid | Q2: Supplemental Core Curriculum Standards Aid | R2: School Choice Aid | S2: Education Opportunity Aid | T2: Discretionary Education Opportunity Aid | U2: Abbott-bordered district aid | V2: Transportation Aid | W2: Special Education Aid | X2: Bilingual Education | Y2: Stabilization Aid | Z2: Supplemental Stabilization Aid | AA2: County Vocational Education Program Aid | AB2: Academic Achievement Reward Program | AC2: Extraordinary Aid | AD2: Consolidated Aid | AE2: Additional Formula Aid | AF2: Other State Aids - Out of Cap | AG2: TPAF Pension (On Behalf) | AH2: TPAF Social Security (Reimbursed) | AI2: Other State Aids | AJ2: Demonstrably Effective Program Aid - Prior Year Carryover | AK2: Distance Learning Network Aid - Prior Year Carryover | AL2: Instructional Supplement Ad - Prior Yr Carryover | AM2: Demontrably Effective Program Aid | AN2: Distance Learning Network Aid | AO2: Instructional Supplemental Aid | AP2: Debt Service Aid Type II | AQ2: Addtl State School Bldg Aid - Chap 177 | AR2: Addtl State School Bldg Aid - Chap 10 | AS2: Addt State School Building Aid-Chapter 74 | AT2: Addtl State School Building Aid - EDA Grant | AU2: Other Restricted Entitlements | AW2: Medicaid Reimbursement | AX2: Title VI | AY2: Schoolwide Programs | AZ2: JTPA | BA2: PL 81.874 (Impact) | BB2: Vocational Education | BC2: Title I | BD2: IDEA | BE2: Other Federal | BG2: Other Financing Sources - Capital Leases | BH2: Other Financing Sources | BI2: Tuition from Individuals | BJ2: Tuition from Other Sources | BK2: Tuition from Summer School | BL2: Non-Resident Fees | BM2: Transportation Fees from Individuals | BN2: Transportation Fees Other LEAs | BO2: Interest Earned on Capital Reserve Funds | BP2: Other Restricted Misc | BR2: Rents & Royalties | BS2: Sale of Property | BT2: Fines and Forfeits | BU2: Private Contributions | BV2: Tetbook Sales & Rentals | BW2: Interest on Investments | BX2: Other Financing Sources | BY2: Interest on Investments | BZ2: Other Misc | CA2: Earnings on Investments | CB2: Other Financing Sources | CD2: Tuition Other LEAs in State | CE2: Tuition from Other LEAs Outside the State | CF2: Tuition from LEAs | CG2: Other Tuition | CI2: Restricted Rev from Intermediate Sources | CJ2: Unrestricted Rev from Intermediate Sources | CM2: Bond Principal | CN2: Bond Premium | CO2: Aid for Adult & Post Graduate Programs | CP2: Post-Secondary Vocational Program Aid | CQ2: Early Childhood Program Aid - Prior Year Carryover | CR2: Adult Basic Ed | CS2: Interest earnd on Early Childhood Cap. Res. Fund | CT2: Early Childhood Program | CU2: Preschool Expansion Aid | CV2: Total Special Revenue
G3: L150 | H3: L253 | I3: L160 | J3: L191 | K3: L192 | L3: L419 | M3: L550 | N3: L642 | P3: L280 | Q3: L281 | R3: L285 | S3: L286 | T3: L287 | U3: L288 | V3: L300 | W3: L310 | X3: L320 | Y3: L340 | Z3: L341 | AA3: L350 | AB3: L353 | AC3: L354 | AD3: L355 | AE3: L356 | AF3: L360 | AG3: L361 | AH3: L362 | AI3: L365 | AJ3: L422 | AK3: L423 | AL3: L424 | AM3: L426 | AN3: L427 | AO3: L428 | AP3: L580 | AQ3: L600 | AR3: L610 | AS3: L620 | AT3: L641 | AU3: L430 | AV3: Total State | AW3: L390 | AX3: L450 | AY3: L455 | AZ3: L490 | BA3: L380 | BB3: L470 | BC3: L440 | BD3: L460 | BE3: L500 | BF3: Total Federal | BG3: L141 | BH3: L142 | BI3: L195 | BJ3: L198 | BK3: L199 | BL3: L230 | BM3: L241 | BN3: L242 | BO3: L251 | BP3: L252 | BR3: L254 | BS3: L255 | BT3: L256 | BU3: L257 | BV3: L258 | BW3: L418 | BX3: L541 | BY3: L551 | BZ3: L552 | CA3: L643 | CB3: L647 | CC3: Total Other | CD3: L196 | CE3: L197 | CF3: L210 | CG3: L220 | CI3: L271 | CJ3: L272 | CK3: Total Indeterminate | CM3: L644 | CN3: L645 | CO3: L351 | CP3: L352 | CQ3: L421 | CR3: L480 | CS3: L512 | CT3: L425 | CU3: L429 | CV3: L520
A4: 1 | B4: 10 | C4: ATLANTIC | D4: ABSECON CITY | E4: 0010-ABSECON CITY | F4: 847 | G4: 8172525 | H4: 71494 | M4: 1134135 | O4: =SUM(G4:N4) -> 9378154 | P4: 344397 | V4: 139638 | W4: 656131 | X4: 54842 | AC4: 9607 | AD4: 147092 | AG4: 860745 | AH4: 371687 | AI4: 5397 | AO4: 35811 | AP4: 91394 | AU4: 406322 | AV4: =SUM(P4:AU4) -> 3123063 | BC4: 144655 | BD4: 244547 | BE4: 59446 | BF4: =SUM(AW4:BE4) -> 448648 | BN4: 5834 | BO4: 25895 | BY4: 1817 | CA4: 341 | CC4: =SUM(BG4:CB4) -> 33887 | CD4: 52188 | CK4: =SUM(CD4:CJ4) -> 52188 | CV4: 890781
A5: 1 | B5: 110 | C5: ATLANTIC | D5: ATLANTIC CITY | E5: 0110-ATLANTIC CITY | F5: 6974 | G5: 93056124 | H5: 2460789 | M5: 11534220 | O5: =SUM(G5:N5) -> 107051133 | V5: 1042992 | W5: 5304073 | X5: 910558 | AC5: 202806 | AD5: 749710 | AE5: 525813 | AF5: 510039 | AG5: 6726159 | AH5: 3691269 | AM5: 3279889 | AP5: 1034431 | AU5: 229570 | AV5: =SUM(P5:AU5) -> 24207309 | BA5: 28633 | BB5: 97729 | BC5: 3730927 | BD5: 2312622 | BE5: 3125142 | BF5: =SUM(AW5:BE5) -> 9295053 | BI5: 11635011 | BX5: 9772 | CC5: =SUM(BG5:CB5) -> 11644783 | CK5: =SUM(CD5:CJ5) -> 0 | CO5: 34678 | CT5: 5952147 | CV5: 18728026
A6: 1 | B6: 120 | C6: ATLANTIC | D6: ATLANTIC CO VOCATIONAL | E6: 0120-ATLANTIC CO VOCATIONAL | F6: 532.5 | H6: 339613 | I6: 3624000 | L6: 223710 | O6: =SUM(G6:N6) -> 4187323 | P6: 1094318 | W6: 469855 | Y6: 1928 | AA6: 878471 | AD6: 20527 | AE6: 97652 | AG6: 513045 | AH6: 280300 | AM6: 395210 | AU6: 99216 | AV6: =SUM(P6:AU6) -> 3850522 | BB6: 260628 | BC6: 123727 | BE6: 104821 | BF6: =SUM(AW6:BE6) -> 489176 | BP6: 145837 | CC6: =SUM(BG6:CB6) -> 145837 | CF6: 1907500 | CG6: 497926 | CK6: =SUM(CD6:CJ6) -> 2405426 | CM6: 1560258 | CO6: 208499 | CP6: 186250 | CR6: 75141 | CV6: 1282453
A7: 1 | B7: 125 | C7: ATLANTIC | D7: ATLANTIC CO SPECIAL SERV | E7: 0125-ATLANTIC CO SPECIAL SERV | F7: 464 | H7: 217626 | I7: 1854000 | L7: 38655 | O7: =SUM(G7:N7) -> 2110281 | AG7: 776303 | AH7: 559221 | AU7: 201282 | AV7: =SUM(P7:AU7) -> 1536806 | AW7: 136669 | BD7: 27450 | BF7: =SUM(AW7:BE7) -> 164119 | BL7: 152147 | CC7: =SUM(BG7:CB7) -> 152147 | CF7: 15458793 | CG7: 861740 | CK7: =SUM(CD7:CJ7) -> 16320533 | CV7: 267387
A8: 1 | B8: 570 | C8: ATLANTIC | D8: BRIGANTINE CITY | E8: 0570-BRIGANTINE CITY | F8: 885 | G8: 13665336 | H8: 189857 | L8: 13029 | O8: =SUM(G8:N8) -> 13868222 | V8: 570923 | W8: 1168580 | X8: 39048 | AD8: 152382 | AE8: 56826 | AG8: 808384 | AH8: 455929 | AI8: 928 | AM8: 447045 | AU8: 2440 | AV8: =SUM(P8:AU8) -> 3702485 | BC8: 264884 | BD8: 289968 | BE8: 81077 | BF8: =SUM(AW8:BE8) -> 635929 | CC8: =SUM(BG8:CB8) -> 0 | CK8: =SUM(CD8:CJ8) -> 0 | CM8: 11200 | CT8: 605498 | CV8: 1703941
A9: 1 | B9: 590 | C9: ATLANTIC | D9: BUENA REGIONAL | E9: 0590-BUENA REGIONAL | F9: 2594 | G9: 11204236 | H9: 241073 | L9: 679 | M9: 816593 | O9: =SUM(G9:N9) -> 12262581 | P9: 9091917 | V9: 964459 | W9: 1451707 | X9: 66540 | Y9: 299425 | AC9: 31772 | AD9: 230631 | AE9: 426427 | AG9: 2272723 | AH9: 1101103 | AI9: 176033 | AM9: 939234 | AP9: 378926 | AU9: 359797 | AV9: =SUM(P9:AU9) -> 17790694 | AW9: 58499 | BC9: 899513 | BD9: 930500 | BE9: 1201979 | BF9: =SUM(AW9:BE9) -> 3090491 | BJ9: 59381 | BN9: 371163 | BO9: 1000 | CB9: 4244 | CC9: =SUM(BG9:CB9) -> 435788 | CD9: 4026996 | CK9: =SUM(CD9:CJ9) -> 4026996 | CT9: 1292661 | CV9: 5624363
A10: 1 | B10: 960 | C10: ATLANTIC | D10: CORBIN CITY | G10: 763006 | H10: 5382 | O10: =SUM(G10:N10) -> 768388 | P10: 418411 | V10: 99415 | W10: 159276 | AD10: 14483 | AE10: 20748 | AG10: 24067 | AV10: =SUM(P10:AU10) -> 736400 | BF10: =SUM(AW10:BE10) -> 0 | BR10: 90000 | CC10: =SUM(BG10:CB10) -> 90000 | CK10: =SUM(CD10:CJ10) -> 0
A11: 1 | B11: 1300 | C11: ATLANTIC | D11: EGG HARBOR CITY | E11: 1300-EGG HARBOR CITY | F11: 520 | G11: 1810936 | H11: 72013 | O11: =SUM(G11:N11) -> 1882949 | P11: 2389741 | Q11: 394444 | V11: 62692 | W11: 471258 | X11: 14052 | Y11: 161942 | AC11: 5724 | AD11: 59249 | AE11: 127797 | AF11: 46477 | AG11: 525270 | AH11: 268265 | AM11: 264477 | AU11: 210171 | AV11: =SUM(P11:AU11) -> 5001559 | AW11: 2049 | BC11: 362190 | BD11: 173141 | BE11: 877377 | BF11: =SUM(AW11:BE11) -> 1414757 | BO11: 3902 | CC11: =SUM(BG11:CB11) -> 3902 | CD11: 35345 | CK11: =SUM(CD11:CJ11) -> 35345 | CT11: 498381 | CV11: 2385737
A12: 1 | B12: 1310 | C12: ATLANTIC | D12: EGG HARBOR TWP | E12: 1310-EGG HARBOR TWP | F12: 7484 | G12: 50843214 | H12: 1217010 | L12: 9847 | M12: 4222368 | O12: =SUM(G12:N12) -> 56292439 | P12: 20341417 | V12: 2516475 | W12: 4028682 | X12: 105426 | AD12: 749168 | AE12: 849381 | AF12: 1327077 | AG12: 4426169 | AH12: 2890602 | AM12: 237639 | AO12: 333900 | AP12: 3143213 | AU12: 352277 | AV12: =SUM(P12:AU12) -> 41301426 | AW12: 9037 | BB12: 23942 | BC12: 596828 | BD12: 1547033 | BE12: 274331 | BF12: =SUM(AW12:BE12) -> 2451171 | BG12: 1645382 | BI12: 54619 | CB12: 786000 | CC12: =SUM(BG12:CB12) -> 2486001 | CK12: =SUM(CD12:CJ12) -> 0 | CV12: 3375797
A13: 1 | B13: 1410 | C13: ATLANTIC | D13: ESTELL MANOR CITY | E13: 1410-ESTELL MANOR CITY | F13: 218 | G13: 1934320 | H13: 22739 | M13: 152371 | O13: =SUM(G13:N13) -> 2109430 | P13: 1486698 | V13: 142144 | W13: 214603 | AD13: 35549 | AE13: 56878 | AG13: 199475 | AH13: 107599 | AO13: 19128 | AP13: 97530 | AV13: =SUM(P13:AU13) -> 2359604 | BC13: 20070 | BD13: 73136 | BE13: 35431 | BF13: =SUM(AW13:BE13) -> 128637 | BO13: 4696 | CC13: =SUM(BG13:CB13) -> 4696 | CK13: =SUM(CD13:CJ13) -> 0 | CV13: 147765
A14: 1 | B14: 1540 | C14: ATLANTIC | D14: FOLSOM BORO | E14: 1540-FOLSOM BORO | F14: 392 | G14: 1258908 | H14: 109391 | M14: 228216 | O14: =SUM(G14:N14) -> 1596515 | P14: 1033381 | R14: 1202776 | V14: 205587 | W14: 237486 | Y14: 396365 | AC14: 2689 | AD14: 52446 | AE14: 95963 | AF14: 103116 | AG14: 290001 | AH14: 153302 | AM14: 74883 | AO14: 3993 | AT14: 474205 | AU14: 1237 | AV14: =SUM(P14:AU14) -> 4327430 | BC14: 74182 | BD14: 106314 | BE14: 33297 | BF14: =SUM(AW14:BE14) -> 213793 | CC14: =SUM(BG14:CB14) -> 0 | CK14: =SUM(CD14:CJ14) -> 0 | CT14: 128018 | CV14: 421924
A15: 1 | B15: 1690 | C15: ATLANTIC | D15: GALLOWAY TWP | E15: 1690-GALLOWAY TWP | F15: 3791 | G15: 26335007 | H15: 354991 | L15: 17239 | M15: 1644990 | O15: =SUM(G15:N15) -> 28352227 | P15: 13410623 | V15: 1107364 | W15: 2223740 | X15: 233940 | Y15: 446658 | AC15: 70191 | AD15: 456764 | AE15: 543140 | AG15: 2446616 | AH15: 1625712 | AI15: 41187 | AM15: 18069 | AO15: 207522 | AP15: 1400447 | AU15: 434300 | AV15: =SUM(P15:AU15) -> 24666273 | AW15: 4667 | BC15: 430365 | BD15: 790131 | BE15: 179128 | BF15: =SUM(AW15:BE15) -> 1404291 | BO15: 10876 | CB15: 2325 | CC15: =SUM(BG15:CB15) -> 13201 | CD15: 67647 | CK15: =SUM(CD15:CJ15) -> 67647 | CV15: 2076754
A16: 1 | B16: 1790 | C16: ATLANTIC | D16: GREATER EGG HARBOR REG | E16: 1790-GREATER EGG HARBOR REG | F16: 3913.5 | G16: 25657864 | H16: 711737 | L16: 16094 | M16: 550208 | O16: =SUM(G16:N16) -> 26935903 | P16: 17921675 | V16: 1381334 | W16: 3012677 | X16: 68552 | AC16: 132882 | AD16: 408378 | AG16: 2964023 | AH16: 1509445 | AI16: 1019919 | AO16: 163980 | AP16: 768616 | AU16: 50882 | AV16: =SUM(P16:AU16) -> 29402363 | BB16: 12324 | BC16: 213644 | BD16: 754208 | BE16: 94838 | BF16: =SUM(AW16:BE16) -> 1075014 | BO16: 746 | CA16: 54993 | CC16: =SUM(BG16:CB16) -> 55739 | CD16: 768171 | CK16: =SUM(CD16:CJ16) -> 768171 | CV16: 1305970
A17: 1 | B17: 1940 | C17: ATLANTIC | D17: HAMILTON TWP | E17: 1940-HAMILTON TWP | F17: 3225 | G17: 15007035 | H17: 431583 | M17: 2800921 | O17: =SUM(G17:N17) -> 18239539 | P17: 9647111 | V17: 1195764 | W17: 2588474 | X17: 85102 | AC17: 58163 | AD17: 318846 | AE17: 483731 | AG17: 1645769 | AH17: 1191425 | AI17: 13911 | AM17: 866918 | AP17: 1672760 | AU17: 167856 | AV17: =SUM(P17:AU17) -> 19935830 | AW17: 37787 | BC17: 634548 | BD17: 711678 | BE17: 213655 | BF17: =SUM(AW17:BE17) -> 1597668 | BG17: 111538 | BO17: 19539 | CC17: =SUM(BG17:CB17) -> 131077 | CD17: 37551 | CK17: =SUM(CD17:CJ17) -> 37551 | CT17: 1427282 | CV17: 4021937
A18: 1 | B18: 1960 | C18: ATLANTIC | D18: HAMMONTON TOWN | E18: 1960-HAMMONTON TOWN | F18: 3325.5 | G18: 14521766 | M18: 1531726 | O18: =SUM(G18:N18) -> 16053492 | P18: 4337255 | V18: 359182 | W18: 1793188 | X18: 102820 | AB18: 131238 | AC18: 36942 | AD18: 249064 | AE18: 258745 | AF18: 5104 | AG18: 2238589 | AH18: 1265095 | AM18: 518195 | AP18: 5597 | AU18: 427475 | AV18: =SUM(P18:AU18) -> 11728489 | BB18: 19429 | BC18: 679112 | BD18: 625973 | BE18: 150046 | BF18: =SUM(AW18:BE18) -> 1474560 | BG18: 28500 | BO18: 77 | BP18: 1660145 | CA18: 84287 | CC18: =SUM(BG18:CB18) -> 1773009 | CD18: 6734504 | CK18: =SUM(CD18:CJ18) -> 6734504 | CT18: 1265056 | CV18: 3685286
A19: 1 | B19: 2680 | C19: ATLANTIC | D19: LINWOOD CITY | E19: 2680-LINWOOD CITY | F19: 998 | G19: 9157885 | H19: 143739 | L19: 56647 | O19: =SUM(G19:N19) -> 9358271 | P19: 969200 | V19: 89582 | W19: 719219 | X19: 6990 | AC19: 11010 | AD19: 111914 | AE19: 56907 | AF19: 1667 | AG19: 866075 | AH19: 433211 | AV19: =SUM(P19:AU19) -> 3265775 | BC19: 18339 | BD19: 196563 | BE19: 25114 | BF19: =SUM(AW19:BE19) -> 240016 | CC19: =SUM(BG19:CB19) -> 0 | CK19: =SUM(CD19:CJ19) -> 0 | CV19: 296663
A20: 1 | B20: 2780 | C20: ATLANTIC | D20: LONGPORT | G20: 968994 | O20: =SUM(G20:N20) -> 968994 | V20: 10048 | W20: 10922 | Y20: 71301 | AD20: 5267 | AE20: 2926 | AF20: 7624 | AH20: 319 | AV20: =SUM(P20:AU20) -> 108407 | BF20: =SUM(AW20:BE20) -> 0 | BP20: 13344 | CC20: =SUM(BG20:CB20) -> 13344 | CK20: =SUM(CD20:CJ20) -> 0
A21: 1 | B21: 2910 | C21: ATLANTIC | D21: MAINLAND REGIONAL | E21: 2910-MAINLAND REGIONAL | F21: 1621.5 | G21: 13953238 | H21: 351148 | M21: 785123 | O21: =SUM(G21:N21) -> 15089509 | P21: 4640595 | V21: 267605 | W21: 759228 | X21: 22254 | AC21: 33727 | AD21: 187841 | AE21: 177449 | AG21: 1346139 | AH21: 781598 | AI21: 88865 | AO21: 37457 | AP21: 275591 | AU21: 3000 | AV21: =SUM(P21:AU21) -> 8621349 | BB21: 8098 | BC21: 49629 | BD21: 277679 | BE21: 20393 | BF21: =SUM(AW21:BE21) -> 355799 | BG21: 321012 | BN21: 109989 | CB21: 3563 | CC21: =SUM(BG21:CB21) -> 434564 | CK21: =SUM(CD21:CJ21) -> 0 | CV21: 396256
A22: 1 | B22: 3020 | C22: ATLANTIC | D22: MARGATE CITY | E22: 3020-MARGATE CITY | F22: 593 | G22: 10173118 | H22: 242872 | L22: 55643 | O22: =SUM(G22:N22) -> 10471633 | V22: 112437 | W22: 643606 | X22: 10530 | AC22: 7656 | AD22: 79108 | AE22: 26036 | AF22: 5234 | AG22: 686231 | AH22: 331567 | AO22: 22170 | AU22: 69505 | AV22: =SUM(P22:AU22) -> 1994080 | BC22: 53328 | BD22: 196003 | BE22: 22880 | BF22: =SUM(AW22:BE22) -> 272211 | BI22: 56660 | CC22: =SUM(BG22:CB22) -> 56660 | CD22: 734759 | CK22: =SUM(CD22:CJ22) -> 734759 | CV22: 419529
A23: 1 | B23: 3480 | C23: ATLANTIC | D23: MULLICA TWP | E23: 3480-MULLICA TWP | F23: 744 | G23: 3085814 | H23: 34891 | M23: 428248 | O23: =SUM(G23:N23) -> 3548953 | P23: 3250225 | V23: 288968 | W23: 713718 | X23: 24510 | AD23: 81114 | AE23: 115947 | AF23: 61050 | AG23: 644108 | AH23: 348414 | AM23: 269925 | AP23: 173482 | AU23: 27228 | AV23: =SUM(P23:AU23) -> 5998689 | AW23: 6267 | BC23: 207484 | BD23: 171601 | BE23: 209147 | BF23: =SUM(AW23:BE23) -> 594499 | CC23: =SUM(BG23:CB23) -> 0 | CD23: 1861 | CK23: =SUM(CD23:CJ23) -> 1861 | CT23: 418670 | CV23: 1304055
A24: 1 | B24: 3720 | C24: ATLANTIC | D24: NORTHFIELD CITY | E24: 3720-NORTHFIELD CITY | F24: 1078 | G24: 7194807 | H24: 89378 | L24: 921 | M24: 1093305 | O24: =SUM(G24:N24) -> 8378411 | P24: 1852131 | V24: 77066 | W24: 774067 | X24: 15220 | AC24: 2732 | AD24: 125520 | AE24: 85833 | AF24: 5782 | AG24: 868975 | AH24: 415642 | AO24: 17088 | AP24: 504684 | AU24: 16291 | AV24: =SUM(P24:AU24) -> 4761031 | BC24: 83672 | BD24: 208359 | BE24: 41523 | BF24: =SUM(AW24:BE24) -> 333554 | BI24: 7820 | CC24: =SUM(BG24:CB24) -> 7820 | CK24: =SUM(CD24:CJ24) -> 0 | CV24: 367854
A25: 1 | B25: 4180 | C25: ATLANTIC | D25: PLEASANTVILLE CITY | E25: 4180-PLEASANTVILLE CITY | F25: 3423 | G25: 6220639 | H25: 367173 | L25: 2800 | M25: 973100 | O25: =SUM(G25:N25) -> 7563712 | P25: 25501280 | Q25: 2062146 | S25: 27845231 | V25: 623617 | W25: 3575208 | X25: 205140 | AC25: 17354 | AD25: 447987 | AF25: 12562 | AG25: 3461190 | AH25: 2071333 | AM25: 1644468 | AP25: 2825822 | AS25: 45518 | AU25: 110506 | AV25: =SUM(P25:AU25) -> 70449362 | AW25: 37426 | BB25: 17900 | BC25: 2395104 | BD25: 756929 | BE25: 1241904 | BF25: =SUM(AW25:BE25) -> 4449263 | BI25: 212378 | CA25: 12034 | CC25: =SUM(BG25:CB25) -> 224412 | CK25: =SUM(CD25:CJ25) -> 0 | CR25: 84533 | CT25: 3469509 | CU25: 1856644 | CV25: 12011586
A26: 1 | B26: 4240 | C26: ATLANTIC | D26: PORT REPUBLIC CITY | E26: 4240-PORT REPUBLIC CITY | F26: 134 | G26: 1229445 | O26: =SUM(G26:N26) -> 1229445 | V26: 40319 | W26: 94368 | Y26: 771685 | AD26: 16568 | AE26: 27754 | AG26: 138067 | AH26: 61914 | AO26: 5904 | AU26: 4000 | AV26: =SUM(P26:AU26) -> 1160579 | BD26: 35301 | BE26: 20344 | BF26: =SUM(AW26:BE26) -> 55645 | BI26: 4010 | BO26: 13 | BP26: 25217 | CC26: =SUM(BG26:CB26) -> 29240 | CK26: =SUM(CD26:CJ26) -> 0 | CV26: 65549
A27: 1 | B27: 4800 | C27: ATLANTIC | D27: SOMERS POINT CITY | E27: 4800-SOMERS POINT CITY | F27: 1124 | G27: 7861264 | H27: 126375 | M27: 813791 | O27: =SUM(G27:N27) -> 8801430 | P27: 1865875 | V27: 104766 | W27: 995247 | X27: 10602 | Y27: 495568 | AD27: 130554 | AF27: 1246 | AG27: 661108 | AH27: 478014 | AM27: 146580 | AP27: 228558 | AU27: 280061 | AV27: =SUM(P27:AU27) -> 5398179 | AW27: 29173 | BC27: 373936 | BD27: 332863 | BE27: 91519 | BF27: =SUM(AW27:BE27) -> 827491 | CA27: 351 | CC27: =SUM(BG27:CB27) -> 351 | CD27: 9163 | CK27: =SUM(CD27:CJ27) -> 9163 | CT27: 588316 | CV27: 1813275
A28: 1 | B28: 5350 | C28: ATLANTIC | D28: VENTNOR CITY | E28: 5350-VENTNOR CITY | F28: 947 | G28: 15597115 | H28: 104111 | O28: =SUM(G28:N28) -> 15701226 | V28: 364427 | W28: 608896 | X28: 92670 | Y28: 100000 | AC28: 7724 | AD28: 160233 | AE28: 51228 | AF28: 122147 | AG28: 860391 | AH28: 487513 | AM28: 351801 | AN28: 441 | AU28: 87075 | AV28: =SUM(P28:AU28) -> 3294546 | AW28: 6327 | BC28: 439488 | BD28: 307288 | BE28: 674368 | BF28: =SUM(AW28:BE28) -> 1427471 | BG28: 144593 | BN28: 202611 | CC28: =SUM(BG28:CB28) -> 347204 | CK28: =SUM(CD28:CJ28) -> 0 | CT28: 553471 | CV28: 2413932
A29: 1 | B29: 5760 | C29: ATLANTIC | D29: WEYMOUTH TWP | E29: 5760-WEYMOUTH TWP | F29: 258 | G29: 1631399 | M29: 63946 | O29: =SUM(G29:N29) -> 1695345 | P29: 1422519 | V29: 189150 | W29: 204252 | X29: 2336 | Y29: 149066 | AD29: 39389 | AE29: 65023 | AF29: 29379 | AG29: 183426 | AH29: 104043 | AM29: 65676 | AP29: 70360 | AV29: =SUM(P29:AU29) -> 2524619 | BC29: 46174 | BD29: 86518 | BE29: 52849 | BF29: =SUM(AW29:BE29) -> 185541 | BO29: 2358 | BP29: 38269 | CC29: =SUM(BG29:CB29) -> 40627 | CK29: =SUM(CD29:CJ29) -> 0 | CT29: 106502 | CV29: 357719
A30: 3 | B30: 40 | C30: BERGEN | D30: ALLENDALE BORO | E30: 0040-ALLENDALE BORO | F30: 1032 | G30: 12025265 | M30: 847316 | O30: =SUM(G30:N30) -> 12872581 | W30: 526449 | AC30: 162846 | AD30: 72221 | AE30: 17960 | AG30: 939402 | AH30: 455185 | AP30: 142845 | AV30: =SUM(P30:AU30) -> 2316908 | BD30: 166055 | BE30: 39362 | BF30: =SUM(AW30:BE30) -> 205417 | BI30: 203476 | BO30: 96334 | BP30: 42804 | CA30: 184096 | CC30: =SUM(BG30:CB30) -> 526710 | CK30: =SUM(CD30:CJ30) -> 0 | CV30: 205417
A31: 3 | B31: 80 | C31: BERGEN | D31: ALPINE BORO | E31: 0080-ALPINE BORO | F31: 136 | G31: 4660644 | H31: 155383 | O31: =SUM(G31:N31) -> 4816027 | V31: 96713 | W31: 123868 | X31: 5822 | AC31: 45117 | AD31: 10419 | AE31: 7105 | AG31: 118188 | AH31: 261834 | AI31: 4654 | AV31: =SUM(P31:AU31) -> 673720 | BD31: 49553 | BE31: 6462 | BF31: =SUM(AW31:BE31) -> 56015 | BI31: 65000 | BO31: 8791 | CC31: =SUM(BG31:CB31) -> 73791 | CK31: =SUM(CD31:CJ31) -> 0 | CV31: 56015
A32: 3 | B32: 285 | C32: BERGEN | D32: BERGEN CO SPECIAL SERVICE | E32: 0285-BERGEN CO SPECIAL SERVICE | F32: 1025 | H32: 928679 | I32: 5766582 | O32: =SUM(G32:N32) -> 6695261 | AG32: 2430667 | AH32: 1996751 | AT32: 712658 | AU32: 8621435 | AV32: =SUM(P32:AU32) -> 13761511 | AW32: 289131 | BE32: 149901 | BF32: =SUM(AW32:BE32) -> 439032 | BL32: 1117160 | CB32: 2421390 | CC32: =SUM(BG32:CB32) -> 3538550 | CF32: 37970599 | CK32: =SUM(CD32:CJ32) -> 37970599 | CV32: 8771336
A33: 3 | B33: 290 | C33: BERGEN | D33: BERGEN COUNTY VOCATIONAL | E33: 0290-BERGEN COUNTY VOCATIONAL | F33: 2089 | H33: 658561 | I33: 22567423 | L33: 33387 | O33: =SUM(G33:N33) -> 23259371 | W33: 1994976 | AA33: 3987002 | AD33: 254112 | AE33: 191334 | AF33: 114052 | AG33: 2839675 | AH33: 1538392 | AJ33: 12588 | AM33: 65024 | AO33: 50546 | AT33: 1267093 | AU33: 2296065 | AV33: =SUM(P33:AU33) -> 14610859 | AW33: 1564 | BC33: 109066 | BD33: 449358 | BE33: 6400215 | BF33: =SUM(AW33:BE33) -> 6960203 | CB33: 6349545 | CC33: =SUM(BG33:CB33) -> 6349545 | CF33: 19420463 | CK33: =SUM(CD33:CJ33) -> 19420463 | CR33: 705960 | CV33: 10122209
A34: 3 | B34: 300 | C34: BERGEN | D34: BERGENFIELD BORO | E34: 0300-BERGENFIELD BORO | F34: 3619 | G34: 39876425 | H34: 160847 | L34: 15827 | O34: =SUM(G34:N34) -> 40053099 | P34: 4868281 | V34: 536398 | W34: 4311809 | X34: 256852 | AC34: 546454 | AD34: 443255 | AF34: 4550 | AG34: 3890150 | AH34: 1703206 | AM34: 107327 | AO34: 16999 | AU34: 207490 | AV34: =SUM(P34:AU34) -> 16892771 | BC34: 157200 | BD34: 840891 | BE34: 591920 | BF34: =SUM(AW34:BE34) -> 1590011 | BN34: 37909 | CC34: =SUM(BG34:CB34) -> 37909 | CD34: 446821 | CK34: =SUM(CD34:CJ34) -> 446821 | CV34: 1937654
A35: 3 | B35: 440 | C35: BERGEN | D35: BOGOTA BORO | E35: 0440-BOGOTA BORO | F35: 1182 | G35: 10238743 | H35: 15478 | M35: 576161 | O35: =SUM(G35:N35) -> 10830382 | P35: 2138184 | V35: 93884 | W35: 746584 | X35: 64168 | Y35: 848968 | AC35: 81967 | AD35: 120692 | AE35: 121658 | AF35: 1300 | AG35: 1001031 | AH35: 493396 | AO35: 42780 | AP35: 13229 | AT35: 48258 | AU35: 136148 | AV35: =SUM(P35:AU35) -> 5952247 | BC35: 204753 | BD35: 273462 | BE35: 52104 | BF35: =SUM(AW35:BE35) -> 530319 | BO35: 3288 | BP35: 76664 | CC35: =SUM(BG35:CB35) -> 79952 | CD35: 153063 | CK35: =SUM(CD35:CJ35) -> 153063 | CV35: 709247
A36: 3 | B36: 740 | C36: BERGEN | D36: CARLSTADT BORO | E36: 0740-CARLSTADT BORO | F36: 549.5 | G36: 7349150 | H36: 51799 | L36: 5912 | M36: 1533835 | O36: =SUM(G36:N36) -> 8940696 | V36: 42654 | W36: 277899 | X36: 34896 | AC36: 15795 | AD36: 53873 | AE36: 12280 | AG36: 570464 | AH36: 301675 | AT36: 4161716 | AU36: 2162 | AV36: =SUM(P36:AU36) -> 5473414 | BC36: 25722 | BD36: 126210 | BE36: 18893 | BF36: =SUM(AW36:BE36) -> 170825 | BG36: 72132 | CA36: 192846 | CC36: =SUM(BG36:CB36) -> 264978 | CK36: =SUM(CD36:CJ36) -> 0 | CV36: 178899
A37: 3 | B37: 745 | C37: BERGEN | D37: CARLSTADT-EAST RUTHERFORD | E37: 0745-CARLSTADT-EAST RUTHERFORD | F37: 522.5 | G37: 9850324 | H37: 208302 | O37: =SUM(G37:N37) -> 10058626 | V37: 79978 | W37: 155683 | X37: 43144 | Y37: 130865 | AC37: 38250 | AD37: 60127 | AE37: 14180 | AF37: 36584 | AG37: 635576 | AH37: 300644 | AO37: 5355 | AV37: =SUM(P37:AU37) -> 1500386 | BC37: 63360 | BD37: 109403 | BE37: 28203 | BF37: =SUM(AW37:BE37) -> 200966 | BO37: 1819 | BP37: 5287 | CA37: 44396 | CC37: =SUM(BG37:CB37) -> 51502 | CK37: =SUM(CD37:CJ37) -> 0 | CV37: 206321
A38: 3 | B38: 890 | C38: BERGEN | D38: CLIFFSIDE PARK BORO | E38: 0890-CLIFFSIDE PARK BORO | F38: 2617 | G38: 23525325 | M38: 441357 | O38: =SUM(G38:N38) -> 23966682 | V38: 137025 | W38: 1172210 | X38: 405044 | AC38: 89578 | AD38: 237544 | AE38: 110346 | AF38: 317247 | AG38: 2136593 | AH38: 1148715 | AJ38: 88195 | AM38: 499388 | AP38: 5667 | AU38: 151704 | AV38: =SUM(P38:AU38) -> 6499256 | BC38: 412083 | BD38: 524366 | BE38: 709642 | BF38: =SUM(AW38:BE38) -> 1646091 | BG38: 166673 | BI38: 4993919 | BN38: 16200 | BO38: 188266 | BP38: 393027 | BX38: 95860 | CC38: =SUM(BG38:CB38) -> 5853945 | CK38: =SUM(CD38:CJ38) -> 0 | CQ38: 10552 | CT38: 1226989 | CV38: 3622919
A39: 3 | B39: 930 | C39: BERGEN | D39: CLOSTER BORO | E39: 0930-CLOSTER BORO | F39: 1183 | G39: 13720585 | H39: 99983 | L39: 2488 | M39: 1022877 | O39: =SUM(G39:N39) -> 14845933 | W39: 560979 | AC39: 64189 | AD39: 75446 | AE39: 19093 | AF39: 9407 | AG39: 1100971 | AH39: 612178 | AT39: 16777 | AU39: 31530 | AV39: =SUM(P39:AU39) -> 2490570 | BD39: 232295 | BF39: =SUM(AW39:BE39) -> 232295 | BO39: 4463 | CA39: 2226 | CC39: =SUM(BG39:CB39) -> 6689 | CD39: 75673 | CK39: =SUM(CD39:CJ39) -> 75673 | CV39: 266313
A40: 3 | B40: 990 | C40: BERGEN | D40: CRESSKILL BORO | E40: 0990-CRESSKILL BORO | F40: 1741 | G40: 18521666 | H40: 127890 | L40: 186879 | M40: 1623773 | O40: =SUM(G40:N40) -> 20460208 | W40: 803849 | AC40: 78920 | AD40: 97137 | AE40: 27030 | AF40: 116977 | AG40: 1424359 | AH40: 811488 | AP40: 43946 | AT40: 9435543 | AU40: 81572 | AV40: =SUM(P40:AU40) -> 12920821 | BD40: 289457 | BE40: 51222 | BF40: =SUM(AW40:BE40) -> 340679 | BG40: 280023 | BI40: 206500 | BO40: 7000 | BR40: 4308 | CA40: 544349 | CC40: =SUM(BG40:CB40) -> 1042180 | CD40: 85949 | CK40: =SUM(CD40:CJ40) -> 85949 | CV40: 609130
A41: 3 | B41: 1070 | C41: BERGEN | D41: DEMAREST BORO | E41: 1070-DEMAREST BORO | F41: 708 | G41: 9893854 | H41: 167411 | M41: 649950 | O41: =SUM(G41:N41) -> 10711215 | W41: 463656 | AC41: 47131 | AD41: 48318 | AE41: 15359 | AF41: 3931 | AG41: 582754 | AH41: 338624 | AU41: 95513 | AV41: =SUM(P41:AU41) -> 1595286 | BD41: 233493 | BF41: =SUM(AW41:BE41) -> 233493 | CC41: =SUM(BG41:CB41) -> 0 | CD41: 56662 | CK41: =SUM(CD41:CJ41) -> 56662 | CV41: 329006
A42: 3 | B42: 1130 | C42: BERGEN | D42: DUMONT BORO | E42: 1130-DUMONT BORO | F42: 2678.5 | G42: 27173953 | H42: 322978 | M42: 1397488 | O42: =SUM(G42:N42) -> 28894419 | P42: 4728390 | V42: 246326 | W42: 1467804 | X42: 134176 | AC42: 173399 | AD42: 304583 | AE42: 206438 | AF42: 4225 | AG42: 2764116 | AH42: 1381865 | AV42: =SUM(P42:AU42) -> 11411322 | BC42: 75238 | BD42: 521027 | BE42: 109524 | BF42: =SUM(AW42:BE42) -> 705789 | BG42: 120747 | BI42: 18433 | CC42: =SUM(BG42:CB42) -> 139180 | CK42: =SUM(CD42:CJ42) -> 0 | CV42: 705789
