Workbook
Name Check1: 'Page 1'!#REF!
Name Check1: 'Page 2'!#REF!
Name Check1: 'Page 3'!#REF!
Name Text11: 'Page 1'!#REF!
Name Text11: 'Page 2'!#REF!
Name Text11: 'Page 3'!#REF!
Name Text16: 'Page 1'!#REF!
Name Text16: 'Page 2'!#REF!
Name Text16: 'Page 3'!#REF!
Name Text2: 'Page 1'!$K$33
Name Text2: 'Page 2'!$K$33
Name Text2: 'Page 3'!$K$33
Name Text4: 'Page 1'!$A$4
Name Text4: 'Page 2'!$A$4
Name Text4: 'Page 3'!$A$4
Name Text5: 'Page 1'!#REF!
Name Text5: 'Page 2'!#REF!
Name Text5: 'Page 3'!#REF!
Name Text6: 'Page 1'!$K$35
Name Text6: 'Page 2'!$K$35
Name Text6: 'Page 3'!$K$35
Name Text7: 'Page 1'!#REF!
Name Text7: 'Page 2'!#REF!
Name Text7: 'Page 3'!#REF!
Name Text8: 'Page 1'!#REF!
Name Text8: 'Page 2'!#REF!
Name Text8: 'Page 3'!#REF!
Name Text9: 'Page 1'!#REF!
Name Text9: 'Page 2'!#REF!
Name Text9: 'Page 3'!#REF!

Sheet Page 1
C1: Purchasing Card Cycle Transaction Log
A2: PURCHASING SERVICES | K2: Page 1
A4: [1] Cardholder: | C4: [2] Dept/Unit: | D4: [3] Card Number: xxxx-xxxx-xxxx- | I4: [4] Purchasing Cycle Date:
A5: [5] | B5: [6] | C5: [7] | D5: [8] | E5: [9] | F5: [10] | G5: [11] | H5: [12] | I5: [13] | J5: [14] | K5: [15]
A6: Trans Date | B6: Supplier/Vendor | C6: Description Goods/Services Ordered | D6: Sub-Total | E6: Cost of Goods (Use Tax applicable) | F6: Use/ | G6: Sales Tax | H6: Use Tax | I6: Shipping Costs | J6: Total Cost | K6: Travel TA/TP Document Number
C7: /Public Purpose : | F7: Sales Tax | H7: Rate: 5.6%
F8: Exempt
E10: =IF($H10>0,($D10),"") | H10: =IF($F10="exempt",0,(IF($G10="",(0.056*D10),0))) -> 0 | J10: =D10+G10+I10 -> 0
E11: =IF($H11>0,($D11),"") | H11: =IF($F11="exempt",0,(IF($G11="",(0.056*D11),0))) -> 0 | J11: =D11+G11+I11 -> 0
E12: =IF($H12>0,($D12),"") | H12: =IF($F12="exempt",0,(IF($G12="",(0.056*D12),0))) -> 0 | J12: =D12+G12+I12 -> 0
E13: =IF($H13>0,($D13),"") | H13: =IF($F13="exempt",0,(IF($G13="",(0.056*D13),0))) -> 0 | J13: =D13+G13+I13 -> 0
E14: =IF($H14>0,($D14),"") | H14: =IF($F14="exempt",0,(IF($G14="",(0.056*D14),0))) -> 0 | J14: =D14+G14+I14 -> 0
E15: =IF($H15>0,($D15),"") | H15: =IF($F15="exempt",0,(IF($G15="",(0.056*D15),0))) -> 0 | J15: =D15+G15+I15 -> 0
E16: =IF($H16>0,($D16),"") | H16: =IF($F16="exempt",0,(IF($G16="",(0.056*D16),0))) -> 0 | J16: =D16+G16+I16 -> 0
E17: =IF($H17>0,($D17),"") | H17: =IF($F17="exempt",0,(IF($G17="",(0.056*D17),0))) -> 0 | J17: =D17+G17+I17 -> 0
E18: =IF($H18>0,($D18),"") | H18: =IF($F18="exempt",0,(IF($G18="",(0.056*D18),0))) -> 0 | J18: =D18+G18+I18 -> 0
E19: =IF($H19>0,($D19),"") | H19: =IF($F19="exempt",0,(IF($G19="",(0.056*D19),0))) -> 0 | J19: =D19+G19+I19 -> 0
E20: =IF($H20>0,($D20),"") | H20: =IF($F20="exempt",0,(IF($G20="",(0.056*D20),0))) -> 0 | J20: =D20+G20+I20 -> 0
E21: =IF($H21>0,($D21),"") | H21: =IF($F21="exempt",0,(IF($G21="",(0.056*D21),0))) -> 0 | J21: =D21+G21+I21 -> 0
... E30: =IF($H30>0,($D30),"") | H30: =IF($F30="exempt",0,(IF($G30="",(0.056*D30),0))) -> 0 | J30: =D30+G30+I30 -> 0
C31: Purchasing Card Transaction Totals: | D31: =IF('Page 2'!$A$10="",(SUM(D10:D30)+SUM('Page 2'!D10:D30)+SUM('Page 3'!D10:D30)),"XXX") -> 0 | E31: =IF('Page 2'!$A$10="",(SUM(E10:E30)+SUM('Page 2'!E10:E30)+SUM('Page 3'!E10:E30)),"XXX") -> 0 | F31: =IF('Page 2'!$A$10="",(SUM(F10:F30)+SUM('Page 2'!F10:F30)+SUM('Page 3'!F10:F30)),"XXX") -> 0 | G31: =IF('Page 2'!$A$10="",(SUM(G10:G30)+SUM('Page 2'!G10:G30)+SUM('Page 3'!G10:G30)),"XXX") -> 0 | H31: =IF('Page 2'!$A$10="",(SUM(H10:H30)+SUM('Page 2'!H10:H30)+SUM('Page 3'!H10:H30)),"XXX") -> 0 | I31: =IF('Page 2'!$A$10="",(SUM(I10:I30)+SUM('Page 2'!I10:I30)+SUM('Page 3'!I10:I30)),"XXX") -> 0 | J31: =IF('Page 2'!$A$10="",(SUM(J10:J30)+SUM('Page 2'!J10:J30)+SUM('Page 3'!J10:J30)),"XXX") -> 0
A32: With my signature below, I certify that I, as the cardholder, personally made all purchases identified on this Purchasing Card Cycle Transaction Log, have not received or requested reimbursement for these same transactions, that they serve the public purpose indicated to further the goals of the University, were conducted in accordance with the policies and procedures set forth by the University and the Arizona Board of Regents and I acknowledge understanding of ARS §35-301, specifically, that a public officer or other person, including justices of the peace and constables, charged with the receipt, safekeeping, transfer or disbursement of public money is guilty of a class 4 felony who without authority of law, appropriates it, or any portion thereof, to his own use, or to the use of another.
A33: [16] Cardholder Signature: | K33: Date:
A34: With my signature below, I certify that, to the best of my knowledge, the items purchased on this claim are correct, serve a public purpose and that no duplicate reimbursement payments have been made.
A35: [17] Dept/Unit Fiscal Liaison Signature: *Approval and reconciliation shall not be completed by the Cardholder. | K35: Date:

Sheet Page 2
C1: Purchasing Card Cycle Transaction Log
A2: PURCHASING SERVICES | K2: Page 2
A4: [1] Cardholder: | C4: [2] Dept/Unit: | D4: [3] Card Number: xxxx-xxxx-xxxx- | I4: [4] Purchasing Cycle Date:
A5: [5] | B5: [6] | C5: [7] | D5: [8] | E5: [9] | F5: [10] | G5: [11] | H5: [12] | I5: [13] | J5: [14] | K5: [15]
A6: Trans Date | B6: Supplier/Vendor | C6: Description Goods/Services Ordered | D6: Sub-Total | E6: Cost of Goods (Use Tax applicable) | F6: Use/ | G6: Sales Tax | H6: Use Tax | I6: Shipping Costs | J6: Total Cost | K6: Travel TA/TP Document Number
C7: /Public Purpose : | F7: Sales Tax | H7: Rate: 5.6%
F8: Exempt
E10: =IF($H10>0,($D10),"") | H10: =IF($F10="exempt",0,(IF($G10="",(0.056*D10),0))) -> 0 | J10: =D10+G10+I10 -> 0
E11: =IF($H11>0,($D11),"") | H11: =IF($F11="exempt",0,(IF($G11="",(0.056*D11),0))) -> 0 | J11: =D11+G11+I11 -> 0
E12: =IF($H12>0,($D12),"") | H12: =IF($F12="exempt",0,(IF($G12="",(0.056*D12),0))) -> 0 | J12: =D12+G12+I12 -> 0
E13: =IF($H13>0,($D13),"") | H13: =IF($F13="exempt",0,(IF($G13="",(0.056*D13),0))) -> 0 | J13: =D13+G13+I13 -> 0
E14: =IF($H14>0,($D14),"") | H14: =IF($F14="exempt",0,(IF($G14="",(0.056*D14),0))) -> 0 | J14: =D14+G14+I14 -> 0
E15: =IF($H15>0,($D15),"") | H15: =IF($F15="exempt",0,(IF($G15="",(0.056*D15),0))) -> 0 | J15: =D15+G15+I15 -> 0
E16: =IF($H16>0,($D16),"") | H16: =IF($F16="exempt",0,(IF($G16="",(0.056*D16),0))) -> 0 | J16: =D16+G16+I16 -> 0
E17: =IF($H17>0,($D17),"") | H17: =IF($F17="exempt",0,(IF($G17="",(0.056*D17),0))) -> 0 | J17: =D17+G17+I17 -> 0
E18: =IF($H18>0,($D18),"") | H18: =IF($F18="exempt",0,(IF($G18="",(0.056*D18),0))) -> 0 | J18: =D18+G18+I18 -> 0
E19: =IF($H19>0,($D19),"") | H19: =IF($F19="exempt",0,(IF($G19="",(0.056*D19),0))) -> 0 | J19: =D19+G19+I19 -> 0
E20: =IF($H20>0,($D20),"") | H20: =IF($F20="exempt",0,(IF($G20="",(0.056*D20),0))) -> 0 | J20: =D20+G20+I20 -> 0
E21: =IF($H21>0,($D21),"") | H21: =IF($F21="exempt",0,(IF($G21="",(0.056*D21),0))) -> 0 | J21: =D21+G21+I21 -> 0
... E30: =IF($H30>0,($D30),"") | H30: =IF($F30="exempt",0,(IF($G30="",(0.056*D30),0))) -> 0 | J30: =D30+G30+I30 -> 0
C31: Purchasing Card Transaction Totals: | D31: =IF('Page 3'!$A$10="",(SUM(D10:D30)+SUM('Page 1'!D10:D30)+SUM('Page 3'!D10:D30)),"XXX") -> 0 | E31: =IF('Page 3'!$A$10="",(SUM(E10:E30)+SUM('Page 1'!E10:E30)+SUM('Page 3'!E10:E30)),"XXX") -> 0 | F31: =IF('Page 3'!$A$10="",(SUM(F10:F30)+SUM('Page 1'!F10:F30)+SUM('Page 3'!F10:F30)),"XXX") -> 0 | G31: =IF('Page 3'!$A$10="",(SUM(G10:G30)+SUM('Page 1'!G10:G30)+SUM('Page 3'!G10:G30)),"XXX") -> 0 | H31: =IF('Page 3'!$A$10="",(SUM(H10:H30)+SUM('Page 1'!H10:H30)+SUM('Page 3'!H10:H30)),"XXX") -> 0 | I31: =IF('Page 3'!$A$10="",(SUM(I10:I30)+SUM('Page 1'!I10:I30)+SUM('Page 3'!I10:I30)),"XXX") -> 0 | J31: =IF('Page 3'!$A$10="",(SUM(J10:J30)+SUM('Page 1'!J10:J30)+SUM('Page 3'!J10:J30)),"XXX") -> 0
A32: With my signature below, I certify that I, as the cardholder, personally made all purchases identified on this Purchasing Card Cycle Transaction Log, have not received or requested reimbursement for these same transactions, that they serve the public purpose indicated to further the goals of the University, were conducted in accordance with the policies and procedures set forth by the University and the Arizona Board of Regents and I acknowledge understanding of ARS §35-301, specifically, that a public officer or other person, including justices of the peace and constables, charged with the receipt, safekeeping, transfer or disbursement of public money is guilty of a class 4 felony who without authority of law, appropriates it, or any portion thereof, to his own use, or to the use of another.
A33: [16] Cardholder Signature: | K33: Date:
A34: With my signature below, I certify that, to the best of my knowledge, the items purchased on this claim are correct, serve a public purpose and that no duplicate reimbursement payments have been made.
A35: [17] Dept/Unit Fiscal Liaison Signature: *Approval and reconciliation shall not be completed by the Cardholder. | K35: Date:

Sheet Page 3
C1: Purchasing Card Cycle Transaction Log
A2: PURCHASING SERVICES | K2: Page 3
A4: [1] Cardholder: | C4: [2] Dept/Unit: | D4: [3] Card Number: xxxx-xxxx-xxxx- | I4: [4] Purchasing Cycle Date:
A5: [5] | B5: [6] | C5: [7] | D5: [8] | E5: [9] | F5: [10] | G5: [11] | H5: [12] | I5: [13] | J5: [14] | K5: [15]
A6: Trans Date | B6: Supplier/Vendor | C6: Description Goods/Services Ordered | D6: Sub-Total | E6: Cost of Goods (Use Tax applicable) | F6: Use/ | G6: Sales Tax | H6: Use Tax | I6: Shipping Costs | J6: Total Cost | K6: Travel TA/TP Document Number
C7: /Public Purpose : | F7: Sales Tax | H7: Rate: 5.6%
F8: Exempt
E10: =IF($H10>0,($D10),"") | H10: =IF($F10="exempt",0,(IF($G10="",(0.056*D10),0))) -> 0 | J10: =D10+G10+I10 -> 0
E11: =IF($H11>0,($D11),"") | H11: =IF($F11="exempt",0,(IF($G11="",(0.056*D11),0))) -> 0 | J11: =D11+G11+I11 -> 0
E12: =IF($H12>0,($D12),"") | H12: =IF($F12="exempt",0,(IF($G12="",(0.056*D12),0))) -> 0 | J12: =D12+G12+I12 -> 0
E13: =IF($H13>0,($D13),"") | H13: =IF($F13="exempt",0,(IF($G13="",(0.056*D13),0))) -> 0 | J13: =D13+G13+I13 -> 0
E14: =IF($H14>0,($D14),"") | H14: =IF($F14="exempt",0,(IF($G14="",(0.056*D14),0))) -> 0 | J14: =D14+G14+I14 -> 0
E15: =IF($H15>0,($D15),"") | H15: =IF($F15="exempt",0,(IF($G15="",(0.056*D15),0))) -> 0 | J15: =D15+G15+I15 -> 0
E16: =IF($H16>0,($D16),"") | H16: =IF($F16="exempt",0,(IF($G16="",(0.056*D16),0))) -> 0 | J16: =D16+G16+I16 -> 0
E17: =IF($H17>0,($D17),"") | H17: =IF($F17="exempt",0,(IF($G17="",(0.056*D17),0))) -> 0 | J17: =D17+G17+I17 -> 0
E18: =IF($H18>0,($D18),"") | H18: =IF($F18="exempt",0,(IF($G18="",(0.056*D18),0))) -> 0 | J18: =D18+G18+I18 -> 0
E19: =IF($H19>0,($D19),"") | H19: =IF($F19="exempt",0,(IF($G19="",(0.056*D19),0))) -> 0 | J19: =D19+G19+I19 -> 0
E20: =IF($H20>0,($D20),"") | H20: =IF($F20="exempt",0,(IF($G20="",(0.056*D20),0))) -> 0 | J20: =D20+G20+I20 -> 0
E21: =IF($H21>0,($D21),"") | H21: =IF($F21="exempt",0,(IF($G21="",(0.056*D21),0))) -> 0 | J21: =D21+G21+I21 -> 0
... E30: =IF($H30>0,($D30),"") | H30: =IF($F30="exempt",0,(IF($G30="",(0.056*D30),0))) -> 0 | J30: =D30+G30+I30 -> 0
C31: Purchasing Card Transaction Totals: | D31: =SUM(D10:D30)+SUM('Page 1'!D10:D30)+SUM('Page 2'!D10:D30) -> 0 | E31: =SUM(E10:E30)+SUM('Page 1'!E10:E30)+SUM('Page 2'!E10:E30) -> 0 | F31: =SUM(F10:F30)+SUM('Page 1'!F10:F30)+SUM('Page 2'!F10:F30) -> 0 | G31: =SUM(G10:G30)+SUM('Page 1'!G10:G30)+SUM('Page 2'!G10:G30) -> 0 | H31: =SUM(H10:H30)+SUM('Page 1'!H10:H30)+SUM('Page 2'!H10:H30) -> 0 | I31: =SUM(I10:I30)+SUM('Page 1'!I10:I30)+SUM('Page 2'!I10:I30) -> 0 | J31: =SUM(J10:J30)+SUM('Page 1'!J10:J30)+SUM('Page 2'!J10:J30) -> 0
A32: With my signature below, I certify that I, as the cardholder, personally made all purchases identified on this Purchasing Card Cycle Transaction Log, have not received or requested reimbursement for these same transactions, that they serve the public purpose indicated to further the goals of the University, were conducted in accordance with the policies and procedures set forth by the University and the Arizona Board of Regents and I acknowledge understanding of ARS §35-301, specifically, that a public officer or other person, including justices of the peace and constables, charged with the receipt, safekeeping, transfer or disbursement of public money is guilty of a class 4 felony who without authority of law, appropriates it, or any portion thereof, to his own use, or to the use of another.
A33: [16] Cardholder Signature: | K33: Date:
A34: With my signature below, I certify that, to the best of my knowledge, the items purchased on this claim are correct, serve a public purpose and that no duplicate reimbursement payments have been made.
A35: [17] Dept/Unit Fiscal Liaison Signature: *Approval and reconciliation shall not be completed by the Cardholder. | K35: Date:
