Workbook
Name access_distances: Stat!$B$54:$B$59
Name Canada: Calc2!$K$136:$K$148
Name Country: EF!$A$3:$A$157
Name distance_train: Stat!$B$61:$B$67
Name N_A: Calc2!$K$149

Sheet Intro
A1: ACERT v1.0 INTRODUCTION and INSTRUCTIONS
A2: Do-It-Yourself Airport Greenhouse Gas Emissions Inventory Tool
A37: Key to inputs | C37: Data input required - text, number, percentage or select from pull down menu
C38: (Some cells already have sample data. Modify or use this data as default)
C39: Information feedback (no input required)
C40: Notes to help explain data input
C42: Banner indicating Airport Owned and Controlled Sources
C43: Banner indicating Non-Airport, Tenant, or Airline Sources

Sheet Input
A1: Airport Carbon and Emissions Reporting Tool ACERT v1.0 | J1: =C5 -> XYZ | K1: =J6 -> 2011
A2: STEP 1 - GENERAL AIRPORT INFORMATION
B4: Airport Name: | G4: Airport Operator:
B5: IATA Identifier: | C5: XYZ | D5: (3 letters) | E5: ICAO Identifier: | F5: WXYZ | G5: (4 letters) | I5: Date of Report (DD/MM/YYYY): | J5: 41153 | O5: January
I6: Year of Inventory: | J6: 2011 | O6: February
B7: City: | I7: First month of year: | J7: January | O7: March
B8: Country: | C8: Albania | E8: ACI Region: | F8: Select One | O8: April
B9: Province: | C9: n/a | D9: (Canada only, otherwise select n/a) | I9: Aircraft movements in inventory year | J9: 100 | K9: movements | O9: May
I10: Passengers Movements in Inventory year | J10: 100 | K10: movements | O10: June
B11: Inventory compiled by: | C11: name | I11: Cargo in inventory year | J11: 10 | K11: tonnes | O11: July
B12: Position: | H12: Note: 1 landing and 1 take-off (LTO) = 2 movements | O12: August
B13: email: | O13: September
O14: October
D15: Permission: This data is made available to ACI | E15: unconditionally | I15: Unit System: | J15: Metric (e.g. metres, litres, kg) | O15: November
D16: Have you ever conducted a more detailed GHG inventory? | E16: No | O16: December
D17: If yes, will you submit it to ACI with this inventory? | E17: No | F17: Most recent year | I17: Reminder:Save file under a new name eg LHR2012
B18: Note: - Make sure you can see Columns A through K
A20: STEP 2 - AIRSIDE VEHICLES, MACHINERY, GSE, FIRE TRAINING, GLYCOL
B22: Fuel used in vehicles, including airside transport, machinery, ground service equipment
C23: Total Fuel used in Vehicles | D23: Airport Owned Vehicles | E23: Non-Airport, Tenant, or Airline Vehicles | F23: Unit | H23: Tenants include all airlines, government bureaus, concessionaires, freight companies, maintenance, contractors, and other companies based at the airport
C24: Gasoline | D24: 5 | F24: litre
C25: Diesel | F25: litre
C26: Natural Gas | F26: kg
C27: Propane | F27: litre
B29: Fuel used for fire training
C30: Fuel | D30: Airport Owned Fire Services | E30: Non-Airport Owned Fire Services | F30: Unit
C31: Kerosene | F31: litre
C32: Butane | F32: litre
C33: Propane | F33: kg
C34: Jet A | F34: litre
C35: Jet B | F35: litre
C36: Wood | F36: kg
I37: Reminder: Save your data. Menu "File"-> "Save"
B38: Fuel used for Stationary Emergency Power Generation Units
C39: Fuel | D39: Airport Owned Equipment | E39: Tenant Owned Equipment | F39: Unit
C40: Diesel or Jet A | F40: litre
B42: Glycol usage for surface and aircraft de-icing
C43: Glycol usage | D43: Airport Operation | E43: Non-Airport, Contactor or Airline Operation | F43: Unit
C44: Movement Surfaces | F44: litre
C45: Other/Aircraft | F45: litre | G45: Note: Calculation is based on 50-50 dilluted glycol
I46: Reminder: Save your data. Menu "File"-> "Save"
A47: STEP 3 - FUEL USED FOR ELECTRICITY GENERATION AND HEATING BUILDINGS
B49: Annual fuel used for electricity and heat generation in AIRPORT OWNED BUILDINGS
B50: Airport Owned and Operated Buildings and Power/Heat Generation Plant
B51: Building Name | C51: Natural Gas | D51: Unit (Choose kg, m3 or GJ) | E51: Fuel Oil | F51: Unit | G51: Coal | H51: Unit
B52: eg Heating plant | C52: 10 | D52: m3 | F52: litre | H52: kg
B53: Power plant | D53: =D$52 -> m3 | F53: litre | H53: kg
D54: =D$52 -> m3 | F54: litre | H54: kg | I54: Note: Do not include Electricity Purchased
D55: =D$52 -> m3 | F55: litre | H55: kg | I55: Note: Combine data if necessary.
B56: Total | C56: =SUM(C52:C55) -> 10 | D56: =D$52 -> m3 | E56: =SUM(E52:E55) -> 0 | F56: litre | G56: =SUM(G52:G55) -> 0 | H56: kg | I56: Note: Only totals matter
B58: Annual fuel used for electricity and heat generation in NON-AIRPORT OWNED BUILDINGS
B59: Non-Airport Owned and Operated Buildings
B60: Building Name | C60: Natural Gas | D60: Unit (Choose) | E60: Fuel Oil | F60: Unit | G60: Coal | H60: Unit
B61: eg Airline office | D61: m3 | F61: litre | H61: kg
B62: Airline Mtce Bldg | D62: =D$61 -> m3 | F62: litre | H62: kg
B63: Airline Hangar | D63: =D$61 -> m3 | F63: litre | H63: kg | I63: Note: Do not include Electricity Purchased
B64: Caterer | D64: =D$61 -> m3 | F64: litre | H64: kg | I64: Note: Combine data if necessary.
B65: Total | C65: =SUM(C61:C64) -> 0 | D65: =D$61 -> m3 | E65: =SUM(E61:E64) -> 0 | F65: litre | G65: =SUM(G61:G64) -> 0 | H65: kg | I65: Note: Only totals matter
A67: STEP 4 - ELECTRICITY PURCHASED FROM OFF-SITE GENERATION
B69: Total annual Electricity purchased by airport from off-site supplier: | F69: 5 | G69: kWh | H69: Data should be available from electricity bills.
F70: =IF(F69<F71,"Warning: Sold amount higher than bought amount! Amend"," ")
B71: Total annual Electricity purchased then resold to tenants: | G71: kWh | H71: Data should be available from invoices to tenants.
B73: Total annual Electricity generated by airport and sold to tenants | G73: kWh | H73: These emissions are counted as Airport Scope 1 in Step 1-2
B75: Total annual Electricity purchased by tenants directly from off-site | G75: kWh | H75: Need data from tenants if available
B77: Your country is | C77: =+IF(C8="(Select One)","You must select one at Line 9", C8) -> Albania | E77: Default EF is | F77: =VLOOKUP(C77,EF!$A$4:$B$158,2) -> 34.4395 | G77: g CO2/kWh | H77: Emission Factor for electricity purchased from the national grid
B78: Input your actual emissions factor, if you know it (if not, leave blank) | G78: g CO2/kWh | H78: This will take zero emissions sources (eg hydro) into account.
H79: To see US data click here
A80: STEP 5 - HEAT (Steam or Hot water) PURCHASED FROM OFF-SITE GENERATION
H81: (select units - kWh or GJ)
B82: Total annual Heat purchased by airport (eg hot water or steam) | G82: kWh | H82: Data should be available from heating bills.
F83: =IF(F82<F84,"Warning: Sold amount higher than bought amount! Amend"," ")
B84: Total annual Heat purchased then resold to tenants | G84: =+G82 -> kWh | H84: Data should be available from invoices to tenants.
B86: Total annual Heat generated by airport and sold to tenants | G86: =+G82 -> kWh | H86: Data should be available from invoices to tenants.
B88: Total annual Heat purchased by tenants directly from off-site | G88: =+G82 -> kWh | H88: Need data from tenants if available
B90: Fuel used by the off-site Heat producer: | F90: Natural Gas | H90: Select from pull-down menu
A92: STEP 6 - AIRCRAFT ACTIVITY
B93: (including airlines, government, concessionaires, aircraft operators, fixed-based operators, etc.)
D95: Select Type of Aircraft you are able to input | E95: Generic aircraft data (Good) | H95: =IF(E95="No aircraft data",0,+IF(E95="Generic aircraft data (Good)",1,2)) -> 1
B97: =IF($H$95=0,"No data available. Skip Input of Annual Aircraft Movements",+IF($H$95=1,"Input Generic aircraft data here","Input Detailed aircraft data in next section below")) -> Input Generic aircraft data here
B98: Generic Aircraft Type | D98: Annual Mvmts | E98: Example Aircraft
B99: Large: 2-aisle, long-haul | E99: A340, B747 | G99: Note: 1 landing and 1 take-off (LTO) = 2 movements
B100: Medium: 2-aisle, medium-haul | D100: 100 | E100: A330, B767
B101: Small: 1-aisle, small/medium haul | E101: A320, B737
B102: Regional: 1-aisle, short-haul | E102: EMB170/190, CRJ70/90 | H102: Sum of Aircraft Movements Input: | I102: =+SUM(D99:D107) -> 100
B103: Business: 2-eng biz jets | E103: C525, F90, etc | H103: Declared Movements: | I103: =+J9 -> 100 | J103: This was input in CellJ10
B104: Turboprop (all engines) | G104: =+IF($H$95=0,"No data required here",+IF($H$95=1,"These numbers should match as closely as possible","No data required here")) -> These numbers should match as closely as possible
B105: Piston (all engines) | G105: Movements input | H105: =+I102/I103 -> 1 | I105: of Declared Movements
B106: Heli small (1 engine/turbine) | G106: =+IF(OR($H$95=0,$H$95=2),"No data required here",IF(H105<90%,"Continue to input more aircraft movements",IF(H105>110%,"Too many movements input, reduce or review CellJ10","Acceptable. Input movements within 10% of declared"))) -> Acceptable. Input movements within 10% of declared
B107: Heli large (2 engine/turbine)
B109: =IF($H$95=0,"No data available. Skip Input of Annual Aircraft Movements",+IF($H$95=1,"Input Generic aircraft data above","Input Detailed aircraft data here")) -> Input Generic aircraft data above | G109: Note: 1 landing and 1 take-off (LTO) = 2 movements
G110: Note: For aircraft not listed use a similarly sized substitute.
B111: Aircraft Type | C111: Annual Mvmts | D111: Aircraft Type | E111: Annual Mvmts | F111: Aircraft Type | G111: Annual Mvmts | H111: Aircraft Type | I111: Annual Mvmts
B112: A109 | D112: Boeing 777 | F112: EMB 135/145 | H112: Piaggio P180
B113: A119 | D113: Boeing 787 | F113: EMB 170 | H113: Pilatus PC-12
B114: Airbus 300 | D114: C-130 Hercules | F114: EMB 190 | H114: Pilatus PC-21
B115: Airbus 310 | D115: C-27 Spartan | F115: EMB 314 | H115: Pilatus PC-9
B116: Airbus 319 | D116: Canadair Challenger | F116: EMB Legacy | H116: Piper PA31 Cheyenne
B117: Airbus 320 | D117: Casa C-212 | F117: Eurocopter AS332 | H117: Piper PA32 Saratoga
B118: Airbus 321 | D118: Casa CN-235 | F118: Eurocopter AS350 | H118: Piper PA34 Seneca
B119: Airbus 330 | D119: Cessna 172 | F119: Eurocopter AS365 | H119: Piper PA46 Malibu
...

Sheet Output
B1: Airport Carbon and Emissions Reporting Tool ACERT v1.0 | G1: =+Calc1!C6 -> XYZ | H1: =Calc1!J8 -> 2011
B2: Airport: | C2: =Calc1!C4 -> 0 | G2: Country: | H2: =+Calc1!C10 -> Albania | K2: Aircraft mvmts: | L2: =+Calc1!J10 -> 100
B3: Report Date: | C3: =Calc1!J6 -> 41153 | G3: Default Ems Factor: | H3: =+Calc1!F95 -> 34.4395 | I3: g CO2/kWh | K3: Passengers: | L3: =+Calc1!J11 -> 100
B4: Operator: | C4: =+Calc1!H4 -> 0 | G4: EF Used: | H4: =+Calc2!E143 -> 34.4395 | I4: g CO2/kWh | K4: Traffic units: | L4: =Calc1!J11+(Calc1!J12*10) -> 200
G5: Greenhouse Gases (t)
B6: Entity | C6: Source | F6: Scope | G6: CO2 | H6: CH4 | I6: N2O | J6: CO2e | K6: CO2e %
B7: Airport Operator | C7: Airport | D7: Airside Vehicles | F7: 1 | G7: =Calc2!E41 -> 0.011445 | H7: =Calc2!F41 -> 2.51e-06 | I7: =Calc2!G41 -> 1e-06 | J7: =G7+H7*21+I7*310 -> 0.01180771 | K7: =J7/$J$33 -> 2.1727371e-06
C8: Airport | D8: Buildings (gas/oil/coal) | F8: 1 | G8: =+Calc2!C80 -> 0.018677934 | H8: =+Calc2!D80 -> 3.3294e-07 | I8: =+Calc2!E80 -> 3.3294e-08 | J8: =G8+H8*21+I8*310 -> 0.018695247 | K8: =J8/$J$33 -> 3.4401129e-06
C9: Airport | D9: Fire Training | F9: 1 | G9: =Calc2!E99 -> 0 | H9: =Calc2!F99 -> 0 | I9: =Calc2!G99 -> 0 | J9: =G9+H9*21+I9*310 -> 0 | K9: =J9/$J$33 -> 0
C10: Airport | D10: Emergency Generator | F10: 1 | G10: =Calc2!D117 -> 0 | H10: =Calc2!E117 -> 0 | I10: =Calc2!F117 -> 0 | J10: =G10+H10*21+I10*310 -> 0 | K10: =J10/$J$33 -> 0
C11: Airport | D11: Glycol | F11: 1 | G11: =Calc2!D129 -> 0 | J11: =G11+H11*21+I11*310 -> 0 | K11: =J11/$J$33 -> 0
C12: Airport | D12: Electricity Purchase | F12: 2 | G12: =Calc2!C142 -> 0.0001721975 | J12: =G12+H12*21+I12*310 -> 0.0001721975 | K12: =G12/$J$33 -> 3.1686067e-08 | L12: =+IF(Input!F71>Input!F69,"Error Step 4","")
C13: Airport | D13: Heat Purchase | F13: 2 | G13: =Calc2!C173 -> 0 | H13: =Calc2!D173 -> 0 | I13: =Calc2!E173 -> 0 | J13: =G13+H13*21+I13*310 -> 0 | K13: =J13/$J$33 -> 0 | L13: =+IF(Input!F84>Input!F82,"Error Step 5","")
I14: Airport Operator Sub-total | J14: =+SUM(J7:J13) -> 0.030675154 | K14: =J14/$J$33 -> 5.644536e-06
B15: Tenants (including airlines, government, shops etc.) and Employees | C15: Tenant | D15: Aircraft (LTO & taxi) | F15: 3 | G15: =Calc2!O324 -> 297.97173 | H15: =Calc2!G334 -> 0.0093648258 | I15: =Calc2!G335 -> 0.026959347 | J15: =G15+H15*21+I15*310 -> 306.52579 | K15: =J15/$J$33 -> 0.056403819
C16: Tenant | D16: Aircraft APU | F16: 3 | G16: =+Calc2!W324 -> 28.35 | H16: =+Calc2!G345 -> 0.000891 | I16: =+Calc2!G346 -> 0.002565 | J16: =G16+H16*21+I16*310 -> 29.163861 | K16: =J16/$J$33 -> 0.0053664429
C17: Tenant | D17: Aircraft Engine Run-ups | F17: 3 | G17: =Calc2!C513 -> 0.00471 | H17: =Calc2!D513 -> 4.437e-06 | I17: =Calc2!E513 -> 4.1325e-07 | J17: =G17+H17*21+I17*310 -> 0.0049312845 | K17: =J17/$J$33 -> 9.074058e-07
C18: Tenant | D18: Aircraft De-icing | F18: 3 | G18: =Calc2!D526 -> 0 | J18: =G18+H18*21+I18*310 -> 0 | K18: =J18/$J$33 -> 0
C19: Tenant | D19: Airside Vehicles | F19: 3 | G19: =Calc2!E384 -> 0 | H19: =Calc2!F384 -> 0 | I19: =Calc2!G384 -> 0 | J19: =G19+H19*21+I19*310 -> 0 | K19: =J19/$J$33 -> 0
C20: Tenant | D20: Buildings (gas/oil/coal) | F20: 3 | G20: =+Calc2!C430 -> 0 | H20: =+Calc2!D430 -> 0 | I20: =+Calc2!E430 -> 0 | J20: =G20+H20*21+I20*310 -> 0 | K20: =J20/$J$33 -> 0
C21: Tenant | D21: Electricity Purchase | F21: 3 | G21: =Calc2!C435 -> 0 | J21: =G21+H21*21+I21*310 -> 0 | K21: =J21/$J$33 -> 0
C22: Tenant | D22: Heat Purchase | F22: 3 | G22: =Calc2!C460 -> 0 | H22: =Calc2!D460 -> 0 | I22: =Calc2!E460 -> 0 | J22: =G22+H22*21+I22*310 -> 0 | K22: =J22/$J$33 -> 0
C23: Tenant | D23: Fire Training | F23: 3 | G23: =Calc2!E478 -> 0 | H23: =Calc2!F478 -> 0 | I23: =Calc2!G478 -> 0 | J23: =G23+H23*21+I23*310 -> 0 | K23: =J23/$J$33 -> 0
C24: Tenant | D24: Emergency Generator | F24: 3 | G24: =Calc2!D495 -> 0 | H24: =Calc2!E495 -> 0 | I24: =Calc2!F495 -> 0 | J24: =G24+H24*21+I24*310 -> 0 | K24: =J24/$J$33 -> 0
C25: Tenant | D25: Landside Vehicles | F25: 3 | G25: =Calc2!C922 -> 4467.6149 | H25: =Calc2!D922 -> 0.91997033 | I25: =Calc2!E922 -> 0.38634493 | J25: =G25+H25*21+I25*310 -> 4606.7012 | K25: =J25/$J$33 -> 0.84767922
C26: Airport | D26: Employee Vehicles | F26: 3 | G26: =Calc2!C908 -> 436.60656 | H26: =Calc2!D908 -> 0.090361954 | I26: =Calc2!E908 -> 0.037370466 | J26: =G26+H26*21+I26*310 -> 450.08901 | K26: =J26/$J$33 -> 0.082820891
I27: Tenant Sub-total | J27: =SUM(J15:J26) -> 5392.4848 | K27: =J27/$J$33 -> 0.99227128
B28: Public (including Passengers) | C28: Ground Access Vehicles | D28: Cars, taxi | F28: 3 | G28: =Calc2!C928 -> 0.4298587 | H28: =Calc2!D928 -> 8.0237082e-05 | I28: =Calc2!E928 -> 3.6823126e-05 | J28: =G28+H28*21+I28*310 -> 0.44295885 | K28: =J28/$J$33 -> 8.1508871e-05
D29: Bus, shuttles | F29: 3 | G29: =Calc2!C929 -> 38.317444 | H29: =Calc2!D929 -> 0.0012092152 | I29: =Calc2!E929 -> 0.0030314 | J29: =G29+H29*21+I29*310 -> 39.282571 | K29: =J29/$J$33 -> 0.0072283871
D30: Rail | F30: 3 | G30: =Calc2!C930 -> 2.2453959 | H30: =Calc2!D930 -> 0 | I30: =Calc2!E930 -> 0 | J30: =G30+H30*21+I30*310 -> 2.2453959 | K30: =J30/$J$33 -> 0.00041317536
I31: Public Sub-total | J31: =SUM(J28:J30) -> 41.970926 | K31: =J31/$J$33 -> 0.0077230713
B32: TOTAL | C32: Total emissions (tonne) | G32: =SUM(G7:G31) -> 5271.5709 | H32: =SUM(H7:H31) -> 1.0218848 | I32: =SUM(I7:I31) -> 0.45630941 | J32: =G32+H32*21+I32*310 -> 5434.4864
B33: Summary | C33: t CO2e | D33: CO2e % | H33: Total CO2e Emissions (t) | J33: =J14+J27+J31 -> 5434.4864 | K33: =K14+K27+K31 -> 1
B34: Airport Scope 1 | C34: =+SUM(J7:J11) -> 0.030502957 | D34: =+SUM(K7:K11) -> 5.61285e-06 | I34: The aircraft emissions calculations were | J34: =IF(Input!H95=0,"not included in this calculation.",+IF(Input!H95=1, "based on generic aircraft data.", "based on detailed aircraft data.")) -> based on generic aircraft data.
B35: Airport Scope 2 | C35: =+SUM(J12:J13) -> 0.0001721975 | D35: =+SUM(K12:K13) -> 3.1686067e-08 | I35: The landside traffic calculations were | J35: =IF(Calc1!E279="None","not included in this calculation.",+IF(Calc1!E279="No.", "based on estimated traffic data.", "based on a detailed traffic survey.")) -> based on estimated traffic data.
B36: Airport Scope 3 | C36: =+J27+J31 -> 5434.4557 | D36: =+K27+K31 -> 0.99999436 | J36: A more detailed separate GHG inventory is also available for Year: | K36: =+IF(AND(Calc1!E19="Yes",Calc1!E18="Yes"),Calc1!G19,"N/A") -> N/A
B70: Check List for Review of Input
A72: 1 | B72: Check Total Fuel dispensed to airside vehicles should not be zero | G72: Airport | H72: =+SUM(Calc1!C28:C31) -> 5 | I72: litres or kg
G73: Tenants | H73: =+SUM(Calc1!C179:C182) -> 0 | I73: litres or kg
A75: 2 | B75: Check Total Fuel (airport and tenants) for electricity or heat | G75: Nat Gas | H75: =+Input!C56+Input!C65 -> 10 | I75: =+Input!D52 -> m3
G76: Fuel Oil | H76: =+Input!E56+Input!E65 -> 0 | I76: litre
G77: Coal | H77: =+Input!G56+Input!G65 -> 0 | I77: kg
A79: 3 | B79: Check Total Electricity purchases are not zero | G79: by airport | H79: =+Input!F69/1000 -> 0.005 | I79: MWh
G80: by tenants | H80: =+(Input!F71+Input!F73+Input!F75)/1000 -> 0 | I80: MWh
A81: 4 | B81: Check that electricty resold to tenants not greater than purchased by airport | H81: =+IF(Input!F71<=Input!F69,"OK","Not OK") -> OK
A83: 5 | B83: Check that the entered number of aircraft movements is appropriate
G84: Your choice was to enter | H84: =+IF(Input!H95=0," no aircraft data.",+IF(Input!H95=1," generic aircraft data."," detailed aircraft data.")) -> generic aircraft data.
G85: Total aircraft movements declared | H85: =+L2 -> 100 | I85: mvmts
G86: Aircraft movements used in calc | H86: =+Calc1!I153 -> 100 | I86: mvmts
H87: =+IF(Input!H95=0,"OK. No aircraft data required.",+IF(K193<90%,"Too few aircraft movements entered.",+IF(K193>110%,"Too many aircraft movements entered.","OK - number entered is within in 10%"))) -> OK - number entered is within in 10%
A89: 6 | B89: Check staff numbers at airport | G89: Airport Employees | H89: =IF(Input!$I$169="No.",+Input!E186,"Not required") -> 100
G90: Tenant/Airline Employees | H90: =IF(Input!$I$169="No.",+Input!E187,"Not required") -> 1000
A92: 7 | B92: Check daily number visitors/deliveries at airport | H92: =IF(Input!$I$169="No.",+Input!E196*Input!E197,"Not required") -> 40
A94: 8 | B94: Distance used for car trips to and from airport | F94: =IF(Input!$I$169="No.",Input!G175,"Not required") -> 30 | G94: km
B95: This distance was calculated using: | F95: =IF(Input!$I$169="No.",Input!G178,"Not required") -> How I chose the vehicle travel distance?
A97: 9 | B97: According to the Input Page, the Airport has granted the following permission to ACI:
E98: Permission: This data is made available to ACI | F98: =+Calc1!E17 -> unconditionally
C175: PLOT DATA
C177: AIRPORT SCOPE 1 AND 2 GHG INVENTORY | G177: AIRPORT SCOPE 1/2/3 GHG INVENTORY
D178: tCO2e | J178: tCO2e
C179: Airport Airside Vehicles | D179: =+J7 -> 0.01180771 | I179: Airport Scope1 | J179: =+SUM(D179:D183) -> 0.030502957
C180: Airport Buildings (gas/oil/coal) | D180: =+J8 -> 0.018695247 | I180: Airport Scope2 | J180: =+SUM(D184:D185) -> 0.0001721975 | K180: Sc1+2 | L180: =+SUM(J179:J180) -> 0.030675154
C181: Airport Fire Training | D181: =+J9 -> 0 | I181: Aircraft (LTO & taxi) | J181: =+D189 -> 306.52579
C182: Airport Emergency Generator | D182: =+J10 -> 0 | I182: Aircraft (other) | J182: =SUM(D190:D192) -> 29.168792
C183: Airport Glycol | D183: =+J11 -> 0 | I183: Tenant Airside Vehicles | J183: =+D193 -> 0
C184: Airport Electricity Purchase (Sc2) | D184: =+J12 -> 0.0001721975 | I184: Tenant Elect./Heat/Fuel | J184: =+SUM(D194:D196) -> 0
C185: Airport Heat Purchase (Sc2) | D185: =+J13 -> 0 | I185: Tenant Landside Vehicles | J185: =+D199 -> 4606.7012
I186: Employee Vehicles | J186: =+D200 -> 450.08901
I187: Public Landside Vehicles | J187: =+SUM(D201:D203) -> 41.970926 | K187: Sc123 | L187: =+SUM(J179:J187) -> 5434.4864
C188: Scope 3 data
C189: =+D15 -> Aircraft (LTO & taxi) | D189: =+J15 -> 306.52579
C190: =+D16 -> Aircraft APU | D190: =+J16 -> 29.163861
C191: =+D17 -> Aircraft Engine Run-ups | D191: =+J17 -> 0.0049312845
C192: =+D18 -> Aircraft De-icing | D192: =+J18 -> 0
C193: =+D19 -> Airside Vehicles | D193: =+J19 -> 0 | J193: Used for check list | K193: =H86/H85 -> 1
C194: =+D20 -> Buildings (gas/oil/coal) | D194: =+J20 -> 0
C195: =+D21 -> Electricity Purchase | D195: =+J21 -> 0
C196: =+D22 -> Heat Purchase | D196: =+J22 -> 0
C197: =+D23 -> Fire Training | D197: =+J23 -> 0
C198: =+D24 -> Emergency Generator | D198: =+J24 -> 0
C199: =+D25 -> Landside Vehicles | D199: =+J25 -> 4606.7012
C200: =+D26 -> Employee Vehicles | D200: =+J26 -> 450.08901
C201: Public Landside Vehicles | D201: =+J28 -> 0.44295885
C202: Bus | D202: =+J29 -> 39.282571
C203: Train | D203: =+J30 -> 2.2453959

Sheet Acronyms
A1: Acronyms & Abbreviations
A2: ACERT | B2: Airport Carbon and Emissions Reporting Tool
A3: ACU | B3: Air Conditioning Unit
A4: AMO | B4: Aircraft Maintenance Organization
A5: AO | B5: Airport Operators
A6: APU | B6: Auxiliary Power Unit
A7: CAC | B7: Common Air Contaminants
A8: CH4 | B8: Methane
A9: CNG | B9: Compressed Natural Gas
A10: CO | B10: Carbon Monoxide
A11: CO2 | B11: Carbon Dioxide
A12: CO2e | B12: Carbon Dioxide Equivalent
A13: DA | B13: Double Aisle
... A43: WRI | B43: World Reporting Institute

Sheet EF
A1: CO2 Emission Factors for Electricity for Countries and US States
A2: Country | B2: Emissions factor | C2: (spot checks) | D2: Unit | F2: Emissions Factors for US States | H2: g CO2/kWh
A3: (Select One) | F3: NY, CT, RI, MA, VT, NH, ME | H3: 466
A4: Albania | B4: 34.4395 | D4: g CO2/kWh | F4: NJ, DE, PA, ML, WV,OH, IN, MI | H4: 782
A5: Algeria | B5: 670.9448 | D5: g CO2/kWh | F5: IL, WI | H5: 638
A6: Angola | B6: 342.7467 | D6: g CO2/kWh | F6: MO, KY, VI, AR, TN, NC, SC, LA, MI, AL, GA | H6: 690
A7: Argentina | B7: 306.4495 | D7: g CO2/kWh | F7: FA | H7: 678
A8: Armenia | B8: 138.329 | D8: g CO2/kWh | F8: TX | H8: 730
A9: Australia | B9: 873.31 | C9: 924 | D9: g CO2/kWh | F9: OK, KN | H9: 867
A10: Austria | B10: 224.87 | D10: g CO2/kWh | F10: ND, SD, NB, MN, IO | H10: 875
A11: Azerbaijan | B11: 504.8522 | D11: g CO2/kWh | F11: CO, UT, NV, WY, MT | H11: 909
A12: Bahrain | B12: 890.1022 | D12: g CO2/kWh | F12: NM, AZ | H12: 658
A13: Bangladesh | B13: 556.8777 | D13: g CO2/kWh | F13: OR, WA, ID | H13: 147
A14: Belarus | B14: 298.834 | D14: g CO2/kWh | F14: CA | H14: 350
A15: Belgium | B15: 267.959 | D15: g CO2/kWh | F15: HA | H15: 858
A16: Benin | B16: 709.9346 | D16: g CO2/kWh | F16: AL | H16: 749
A17: Bolivia | B17: 481.352 | D17: g CO2/kWh | F17: US TERRITORIES | H17: 858
A18: Bosnia-Herzegovina | B18: 618.6506 | D18: g CO2/kWh | F18: US AVERAGE | H18: 676
A19: Botswana | B19: 1847.6941 | D19: g CO2/kWh
A20: Brazil | B20: 84.2192 | C20: 93 | D20: g CO2/kWh | F20: Source Dept of Energy For EIA-1605 (2007)
A21: Brunei Darussalam | B21: 788.8284 | D21: g CO2/kWh | F21: For period 1999-2002
A22: Bulgaria | B22: 448.0035 | D22: g CO2/kWh
A23: Cambodia | B23: 1205.9307 | D23: g CO2/kWh
A24: Cameroon | B24: 39.0982 | C24: 16 | D24: g CO2/kWh
A25: Canada | B25: 198.664 | C25: 223 | D25: g CO2/kWh
A26: Chile | B26: 357.4757 | D26: g CO2/kWh
A27: People's Republic of China | B27: 787.8678 | D27: g CO2/kWh
A28: China (including Hong Kong) | B28: 788.1334 | D28: g CO2/kWh
A29: Chinese Taipei | B29: 631.6822 | D29: g CO2/kWh
A30: Colombia | B30: 163.1909 | D30: g CO2/kWh
A31: Congo | B31: 643 | C31: 683 | D31: g CO2/kWh
A32: Democratic Republic of Congo | B32: 2.9579 | C32: 4 | D32: g CO2/kWh
A33: Costa Rica | B33: 26.8938 | C33: 15 | D33: g CO2/kWh
A34: Côte d'Ivoire | B34: 518.1223 | D34: g CO2/kWh
A35: Croatia | B35: 311.3264 | D35: g CO2/kWh
A36: Cuba | B36: 987.4434 | D36: g CO2/kWh
A37: Cyprus | B37: 792.3237 | D37: g CO2/kWh
A38: Czech Republic | B38: 515.573 | D38: g CO2/kWh
A39: Denmark | B39: 283.582 | D39: g CO2/kWh
A40: Dominican Republic | B40: 573.9929 | D40: g CO2/kWh
A41: Ecuador | B41: 369.0944 | D41: g CO2/kWh
A42: Egypt | B42: 471.4438 | D42: g CO2/kWh
A43: El Salvador | B43: 263.4097 | D43: g CO2/kWh
A44: Eritrea | B44: 696.1661 | D44: g CO2/kWh
A45: Estonia | B45: 664.9089 | D45: g CO2/kWh
A46: Ethiopia | B46: 6.6382 | C46: 11 | D46: g CO2/kWh
A47: Finland | B47: 193.551 | D47: g CO2/kWh
A48: France | B48: 90.859 | C48: 83 | D48: g CO2/kWh
A49: Gabon | B49: 368.3352 | D49: g CO2/kWh
A50: Georgia | B50: 89.2311 | D50: g CO2/kWh
A51: Germany | B51: 349.232 | D51: g CO2/kWh
A52: Ghana | B52: 203.7662 | D52: g CO2/kWh
A53: Gibraltar | B53: 743.0897 | D53: g CO2/kWh
A54: Greece | B54: 776.493 | D54: g CO2/kWh
A55: Guatemala | B55: 383.7588 | D55: g CO2/kWh
A56: Haiti | B56: 307.3561 | D56: g CO2/kWh
A57: Honduras | B57: 410.7127 | D57: g CO2/kWh
A58: Hong Kong, China | B58: 809.7809 | D58: g CO2/kWh
A59: Hungary | B59: 338.703 | D59: g CO2/kWh
A60: Iceland | B60: 0.619 | D60: g CO2/kWh
... A88: Morocco | B88: 777.5021 | D88: g CO2/kWh
A89: Mozambique | B89: 683 | C89: 683 (it was 1) | D89: g CO2/kWh
A90: Myanmar | B90: 364.8027 | D90: g CO2/kWh
A91: Namibia | B91: 683 | C91: 683 (it was 26) | D91: g CO2/kWh
A92: Nepal | B92: 13 | C92: 13( it was 1) | D92: g CO2/kWh
A93: Netherlands | B93: 386.667 | D93: g CO2/kWh
A94: Netherlands Antilles | B94: 717.8293 | D94: g CO2/kWh
A95: New Zealand | B95: 275.422 | D95: g CO2/kWh
A96: Nicaragua | B96: 538.7694 | D96: g CO2/kWh
A97: Nigeria | B97: 402.963 | D97: g CO2/kWh
A98: Norway | B98: 5.502 | C98: 5 | D98: g CO2/kWh
A99: Oman | B99: 854.5383 | D99: g CO2/kWh
A100: Pakistan | B100: 379.5676 | D100: g CO2/kWh
A101: Panama | B101: 276.8361 | D101: g CO2/kWh
A102: Paraguay | B102: 0 | D102: g CO2/kWh
A103: Peru | B103: 197.8384 | D103: g CO2/kWh
A104: Philippines | B104: 495.1494 | D104: g CO2/kWh
A105: Poland | B105: 658.899 | D105: g CO2/kWh
A106: Portugal | B106: 498.223 | D106: g CO2/kWh
A107: Qatar | B107: 617.9696 | D107: g CO2/kWh
A108: Romania | B108: 394.1358 | D108: g CO2/kWh
A109: Russia | B109: 337.9606 | D109: g CO2/kWh
A110: Saudi Arabia | B110: 747.6115 | D110: g CO2/kWh
... A133: United Kingdom | B133: 472.514 | D133: g CO2/kWh
A134: United States | B134: 572.934 | C134: 676 | D134: g CO2/kWh
A135: Uruguay | B135: 102.7396 | D135: g CO2/kWh
A136: Uzbekistan | B136: 443.0373 | D136: g CO2/kWh
A137: Venezuela | B137: 225.2232 | D137: g CO2/kWh
A138: Vietnam | B138: 405.5964 | D138: g CO2/kWh
A139: Yemen | B139: 845.4729 | D139: g CO2/kWh
A140: Zambia | B140: 6.8391 | D140: g CO2/kWh
A141: Zimbabwe | B141: 572.3375 | D141: g CO2/kWh
A142: Other Africa | B142: 420.1425 | D142: g CO2/kWh
A143: Other Latin America | B143: 518.2661 | D143: g CO2/kWh
A144: Other Asia | B144: 360.8507 | D144: g CO2/kWh
A145: European Union -27 | B145: 340.861 | D145: g CO2/kWh
A146: Former Yugoslavia | B146: 576.5181 | D146: g CO2/kWh
... A157: Asia (excluding China) | B157: 728.3018 | D157: g CO2/kWh
B158: U100319:
B159: GHG Protocol Worksheet; data for 2006 | C159: From US dept Energy (1999-2002)

Sheet LAQ
A1: Airport Carbon and Emissions Reporting Tool ACERT v1.0 - Approximate LAQ Emissions data | G1: =+Calc1!C6 -> XYZ | H1: =Calc1!J8 -> 2011
B2: Airport: | C2: =Calc1!C4 -> 0 | F2: Country: | G2: =+Calc1!C10 -> Albania | I2: Aircraft mvmts: | J2: =+Calc1!I153 -> 100
B3: Date: | C3: =Calc1!J6 -> 41153 | I3: Passengers: | J3: =+Calc1!J11 -> 100
B4: Operator: | C4: =+Calc1!H4 -> 0 | I4: Traffic units: | J4: =Calc1!J11+(Calc1!J12*10) -> 200
F5: Local Air Quality Pollutants (t)
B6: Entity | C6: Source | F6: NOx | G6: VOC | H6: CO | I6: PM | J6: SOx
B7: Airport Operator | C7: Airport | D7: Airside Vehicles | F7: =Calc2!H41 -> 5.986e-05 | G7: =Calc2!I41 -> 5.11e-05 | H7: =Calc2!J41 -> 0.00049859 | I7: =Calc2!K41 -> 1.2994e-07 | J7: =Calc2!L41 -> 1.46e-07
C8: Airport | D8: Buildings (gas/oil/coal) | F8: =+Calc2!F80 -> 2.33058e-05 | G8: =+Calc2!G80 -> 9.9882e-07 | H8: =+Calc2!H80 -> 9.9882e-06 | I8: =+Calc2!I80 -> 1.6647e-07 | J8: =+Calc2!J80 -> 1.6647e-07
C9: Airport | D9: Fire Training | F9: =Calc2!H99 -> 0 | G9: =Calc2!I99 -> 0 | H9: =Calc2!J99 -> 0 | I9: =Calc2!K99 -> 0 | J9: =Calc2!L99 -> 0
C10: Airport | D10: Emergency Generator | F10: =Calc2!G117 -> 0 | G10: =Calc2!H117 -> 0 | H10: =Calc2!I117 -> 0 | I10: =Calc2!J117 -> 0 | J10: =Calc2!K117 -> 0
C11: Airport | D11: Glycol | G11: =Calc2!H129 -> 0
C12: Airport | D12: Electricity Purchase | K12: LAQ not calculated
C13: Airport | D13: Heat Purchase | F13: =Calc2!F173 -> 0 | G13: =Calc2!G173 -> 0 | H13: =Calc2!H173 -> 0 | I13: =Calc2!I173 -> 0 | J13: =Calc2!J173 -> 0
B14: Airport Operator Sub-total | F14: =SUM(F7:F13) -> 8.31658e-05 | G14: =SUM(G7:G13) -> 5.209882e-05 | H14: =SUM(H7:H13) -> 0.0005085782 | I14: =SUM(I7:I13) -> 2.9641e-07 | J14: =SUM(J7:J13) -> 3.1247e-07
B15: Tenants (incl. airlines, governm't shops etc.) | C15: Tenant | D15: Aircraft (LTO & taxi) | F15: =Calc2!E324 -> 1.3223156 | G15: =Calc2!G324 -> 0.047620365 | H15: =Calc2!I324 -> 0.65646467 | I15: =Calc2!K324 -> 0.0041718604 | J15: =Calc2!M324 -> 0.0472971
C16: Tenant | D16: Aircraft APU | F16: =+Calc2!R324 -> 0.072 | G16: =Calc2!S324 -> 0.0048 | H16: =+Calc2!T324 -> 0.0063 | I16: =+Calc2!U324 -> 0.0012 | J16: =+Calc2!V324 -> 0.0045
C17: Tenant | D17: Aircraft Engine Run-ups | F17: =Calc2!F513 -> 1.5e-06 | G17: =Calc2!G513 -> 6.84e-05 | H17: =Calc2!H513 -> 0.0015 | I17: =Calc2!I513 -> 7.5e-08 | J17: =Calc2!J513 -> 7.5e-07
C18: Tenant | D18: Aircraft De-icing | G18: =Calc2!H526 -> 0
C19: Tenant | D19: Airside Vehicles | F19: =Calc2!H384 -> 0 | G19: =Calc2!I384 -> 0 | H19: =Calc2!J384 -> 0 | I19: =Calc2!K384 -> 0 | J19: =Calc2!L384 -> 0
C20: Tenant | D20: Buildings (gas/oil/coal) | F20: =+Calc2!F430 -> 0 | G20: =+Calc2!G430 -> 0 | H20: =+Calc2!H430 -> 0 | I20: =+Calc2!I430 -> 0 | J20: =+Calc2!J430 -> 0
C21: Tenant | D21: Electricity Purchase | K21: LAQ not calculated
C22: Tenant | D22: Heat Purchase | F22: =Calc2!F460 -> 0 | G22: =Calc2!G460 -> 0 | H22: =Calc2!H460 -> 0 | I22: =Calc2!I460 -> 0 | J22: =Calc2!J460 -> 0
C23: Tenant | D23: Fire Training | F23: =Calc2!H478 -> 0 | G23: =Calc2!I478 -> 0 | H23: =Calc2!J478 -> 0 | I23: =Calc2!K478 -> 0 | J23: =Calc2!L478 -> 0
C24: Tenant | D24: Emergency Generator | F24: =Calc2!G495 -> 0 | G24: =Calc2!H495 -> 0 | H24: =Calc2!I495 -> 0 | I24: =Calc2!J495 -> 0 | J24: =Calc2!K495 -> 0
C25: Tenant | D25: Landside Vehicles | F25: =Calc2!F922 -> 20.266524 | G25: =Calc2!G922 -> 18.100459 | H25: =Calc2!H922 -> 170.0067 | I25: =Calc2!I922 -> 0.30962479 | J25: =Calc2!J922 -> 0.05236512
C26: Airport | D26: Employee Vehicles | F26: =Calc2!F908 -> 1.951164 | G26: =Calc2!G908 -> 1.7700912 | H26: =Calc2!H908 -> 16.621646 | I26: =Calc2!I908 -> 0.024961752 | J26: =Calc2!J908 -> 0.005115456
B27: Tenant Sub-total | F27: =SUM(F15:F26) -> 23.612005 | G27: =SUM(G15:G26) -> 19.923039 | H27: =SUM(H15:H26) -> 187.29261 | I27: =SUM(I15:I26) -> 0.33995848 | J27: =SUM(J15:J26) -> 0.10927843
B28: Public | C28: Ground Access Vehicles | D28: Cars, taxi | F28: =Calc2!F928 -> 0.0019813626 | G28: =Calc2!G928 -> 0.0016208321 | H28: =Calc2!H928 -> 0.015243828 | I28: =Calc2!I928 -> 5.6526263e-05 | J28: =Calc2!J928 -> 4.7187168e-06
D29: Bus, shuttles | F29: =Calc2!F929 -> 0.3873672 | G29: =Calc2!G929 -> 0.05586836 | H29: =Calc2!H929 -> 0.5344038 | I29: =Calc2!I929 -> 0.01099891 | J29: =Calc2!J929 -> 0.0001893328
D30: Rail | F30: =Calc2!F930 -> 0 | G30: =Calc2!G930 -> 0 | H30: =Calc2!H930 -> 0 | I30: =Calc2!I930 -> 0 | J30: =Calc2!J930 -> 0
B31: Public Sub-total | F31: =SUM(F28:F30) -> 0.38934856 | G31: =SUM(G28:G30) -> 0.057489192 | H31: =SUM(H28:H30) -> 0.54964763 | I31: =SUM(I28:I30) -> 0.011055436 | J31: =SUM(J28:J30) -> 0.00019405152
B33: APPROXIMATE LAQ EMISSIONS | F33: =+F14+F27+F31 -> 24.001437 | G33: =+G14+G27+G31 -> 19.98058 | H33: =+H14+H27+H31 -> 187.84277 | I33: =+I14+I27+I31 -> 0.35101421 | J33: =+J14+J27+J31 -> 0.10947279 | K33: tonnes
E35: The landside traffic calculations for this inventory were based on: | J35: =IF(Calc1!E279="No.", "estimated traffic data", "a detailed traffic survey") -> estimated traffic data

Sheet xfer
A1: Notes: This page is for tranfer of the main data to an ACI database. | AU1: Onsite Elect generation? | BS1: Infrastructure for alternative fuel | CE1: Terminal Gates APU replacement | CU1: Outputs (tonnes per year)
CU2: Airport CO2e | DB2: Tenant/Staff CO2e | DW2: Airport LAQ | EB2: Tenant LAQ | EG2: GAV LAQ
A3: Airport code | B3: Airport Name: | C3: City: | D3: Airport Operator: | E3: ICAO Identifier: | F3: Country: | G3: Contact | H3: Position: | I3: email: | J3: date | K3: inventory yr | L3: AC mvt | M3: PAX | N3: Cargo | O3: Permission | P3: Prev GHG inventory | Q3: Send to ACI | R3: Other year | S3: Electricity Purchase | T3: El onsold | U3: Nat EF gCO2/kWh | V3: Actual EF | W3: Heat purch | X3: Heat purchase unit | Y3: Heat source | Z3: Heat onsold | AA3: Annual movements declared | AB3: Average Taxi Time | AC3: APU sm-med | AD3: APU Large aircraft | AE3: Traff study? | AF3: trip distance | AG3: Tirp distance method | AH3: % PAX connecting | AI3: % pax on Public Transport: | AJ3: Train # of service | AK3: distance | AL3: Subway # services | AM3: distance | AN3: # Apt emplees | AO3: #Tenant emplees | AP3: #Tenant visitors/day | AQ3: Equiv full time env staff | AR3: Environmental Report | AU3: Solar/PV | AV3: kW | AW3: MWh/yr | AX3: Comment | AY3: Solar hot water | AZ3: kW | BA3: MWh/yr | BB3: Comment | BC3: Wind turbine | BD3: kW | BE3: MWh/yr | BF3: Comment | BG3: Geothermal | BH3: kW | BI3: MWh/yr | BJ3: Comment | BK3: Hydroelectricity | BL3: kW | BM3: MWh/yr | BN3: Comment | BO3: Other | BP3: kW | BQ3: MWh/yr | BR3: Comment | BS3: CNG for vehicles | BU3: LPG for vehicles | BW3: Biofuels | BY3: Liquid Hydrogen | CA3: Electric veh recharge station | CC3: Other | CE3: # of bridges or contact gates | CG3: # with FEGP | CI3: # with PCA | CK3: # remote stands | CM3: # with FEGP | CO3: # with PCA | CQ3: # GPU available | CS3: # ACU available | CU3: Apt Veh airside | CV3: bldgs | CW3: fire training | CX3: em gens | CY3: glycol | CZ3: el purchase | DA3: heat purch | DB3: Ten LTO | DC3: APU | DD3: Eng runup | DE3: AC deice | DF3: Aside veh | DG3: Ten blds | DH3: El purch | DI3: heat purch | DJ3: fire tenant | DK3: em gen | DL3: landside veh | DM3: apt empl veh | DN3: GAV Cars | DO3: GAV Buses | DP3: GAV Trains | DQ3: GAV | DR3: Total Co2e | DS3: Apt sc1 | DT3: Apt sc2 | DU3: Apt sc3 | DV3: kg CO2e/traffic unit/year | DW3: Apt NOx | DX3: VOC | DY3: CO | DZ3: PM | EA3: SOx | EB3: Tenant NOx | EC3: VOC | ED3: CO | EE3: PM | EF3: SOx | EG3: GAV NOx | EH3: VOC | EI3: CO | EJ3: PM | EK3: SOx
A4: =Calc1!C6 -> XYZ | B4: =Calc1!C4 -> 0 | C4: =Calc1!C8 -> 0 | D4: =Calc1!H4 -> 0 | E4: =Calc1!F6 -> WXYZ | F4: =Calc1!C10 -> Albania | G4: =Calc1!C13 -> name | H4: =Calc1!C14 -> 0 | I4: =Calc1!C15 -> 0 | J4: =Calc1!J6 -> 41153 | K4: =Calc1!J8 -> 2011 | L4: =Calc1!J10 -> 100 | M4: =Calc1!J11 -> 100 | N4: =Calc1!J12 -> 10 | O4: =Calc1!E17 -> unconditionally | P4: =Calc1!E18 -> No | Q4: =Calc1!E19 -> No | R4: =Calc1!G19 -> 0 | S4: =Calc1!F91 -> 5 | T4: =Calc1!F93 -> 0 | U4: =Calc1!F95 -> 34.4395 | V4: =Calc1!W6 -> 0 | W4: =+Calc1!F101 -> 0 | X4: =+Calc1!G101 -> kWh | Y4: =+Calc1!F103 -> Natural Gas | Z4: =+Calc1!F105 -> not used | AA4: =Calc1!I153 -> 100 | AB4: =Calc1!C168 -> 26 | AC4: =Calc1!C172 -> 15 | AD4: =Calc1!C173 -> 45 | AE4: =+Calc1!E279 -> No. | AF4: =Calc1!G285 -> 30 | AG4: =+Calc1!G288 -> How I chose the vehicle travel distance? | AH4: =Calc1!F292 -> 0.3 | AI4: =Calc1!E296 -> 0.2 | AJ4: =+Calc1!F345 -> 1 | AK4: =+Calc1!G345 -> 5 | AL4: =+Calc1!F346 -> 1 | AM4: =+Calc1!G346 -> 5 | AN4: =+Calc1!E361 -> 100 | AO4: =+Calc1!E380 -> 1000 | AP4: =+Calc1!I400 -> 40 | AQ4: =+Calc1!D468 -> 1 | AR4: =+Calc1!D472 -> no | AS4: =+Calc1!E472 -> 2000 | AT4: =+Calc1!I472 -> 0 | AU4: =+Calc1!D517 -> yes | AV4: =+Calc1!I517 -> 0 | AW4: 0 | AX4: =+Calc1!I517 -> 0 | AY4: =+Calc1!D518 -> no | AZ4: =+Calc1!E518 -> 0 | BA4: 0 | BB4: =+Calc1!I518 -> 0 | BC4: =+Calc1!D519 -> no | BD4: =+Calc1!E519 -> 0 | BE4: 0 | BF4: =+Calc1!I519 -> 0 | BG4: =+Calc1!D520 -> no | BH4: =+Calc1!E520 -> 0 | BI4: 0 | BJ4: =+Calc1!I520 -> 0 | BK4: =+Calc1!D521 -> no | BL4: =+Calc1!E521 -> 0 | BM4: 0 | BN4: =+Calc1!I521 -> 0 | BO4: =+Calc1!D522 -> no | BP4: =+Calc1!E522 -> 0 | BQ4: 0 | BR4: =+Calc1!I522 -> 0 | BS4: =+Calc1!D539 -> no | BT4: =+Calc1!I539 -> 0 | BU4: =+Calc1!D540 -> no | BV4: =+Calc1!I540 -> 0 | BW4: =+Calc1!D541 -> no | BX4: =+Calc1!I541 -> 0 | BY4: =+Calc1!D542 -> no | BZ4: =+Calc1!I542 -> 0 | CA4: =+Calc1!D543 -> no | CB4: =+Calc1!I543 -> 0 | CC4: =+Calc1!D544 -> no | CD4: =+Calc1!I544 -> 0 | CE4: =+Calc1!D547 -> 99 | CF4: =+Calc1!I547 -> 0 | CG4: =+Calc1!D548 -> 99 | CH4: =+Calc1!I548 -> 0 | CI4: =+Calc1!D549 -> 99 | CJ4: =+Calc1!I549 -> 0 | CK4: =+Calc1!D551 -> 99 | CL4: =+Calc1!I551 -> 0 | CM4: =+Calc1!D552 -> 99 | CN4: =+Calc1!I552 -> 0 | CO4: =+Calc1!D553 -> 99 | CP4: =+Calc1!I553 -> 0 | CQ4: =+Calc1!D554 -> 99 | CR4: =+Calc1!I554 -> 0 | CS4: =+Calc1!D555 -> 99 | CT4: =+Calc1!I555 -> 0 | CU4: =+Output!J7 -> 0.01180771 | CV4: =+Output!J8 -> 0.018695247 | CW4: =+Output!J9 -> 0 | CX4: =+Output!J10 -> 0 | CY4: =+Output!J11 -> 0 | CZ4: =+Output!J12 -> 0.0001721975 | DA4: =+Output!J13 -> 0 | DB4: =+Output!J15 -> 306.52579 | DC4: =+Output!J16 -> 29.163861 | DD4: =+Output!J17 -> 0.0049312845 | DE4: =+Output!J18 -> 0 | DF4: =+Output!J19 -> 0 | DG4: =+Output!J20 -> 0 | DH4: =+Output!J21 -> 0 | DI4: =+Output!J22 -> 0 | DJ4: =+Output!J23 -> 0 | DK4: =+Output!J24 -> 0 | DL4: =+Output!J25 -> 4606.7012 | DM4: =+Output!J26 -> 450.08901 | DN4: =+Output!J25 -> 4606.7012 | DO4: =+Output!J26 -> 450.08901 | DP4: =+Output!J27 -> 5392.4848 | DQ4: =+Output!J28 -> 0.44295885 | DR4: =+Output!J32 -> 5434.4864 | DS4: =+Output!C34 -> 0.030502957 | DT4: =+Output!C35 -> 0.0001721975 | DU4: =+Output!C36 -> 5434.4557 | DV4: =+Output!J38 -> 0 | DW4: =+LAQ!F14 -> 8.31658e-05 | DX4: =+LAQ!G14 -> 5.209882e-05 | DY4: =+LAQ!H14 -> 0.0005085782 | DZ4: =+LAQ!I14 -> 2.9641e-07 | EA4: =+LAQ!J14 -> 3.1247e-07 | EB4: =+LAQ!F27 -> 23.612005 | EC4: =+LAQ!G27 -> 19.923039 | ED4: =+LAQ!H27 -> 187.29261 | EE4: =+LAQ!I27 -> 0.33995848 | EF4: =+LAQ!J27 -> 0.10927843 | EG4: =+LAQ!F31 -> 0.38934856 | EH4: =+LAQ!G31 -> 0.057489192 | EI4: =+LAQ!H31 -> 0.54964763 | EJ4: =+LAQ!I31 -> 0.011055436 | EK4: =+LAQ!J31 -> 0.00019405152
A7: Short Summary
B8: Airport Name: | C8: =+L3 -> AC mvt | D8: Pax | E8: Traff units | F8: =+K3 -> inventory yr | G8: Scope 1 | H8: Scope 2 | I8: Scope 3 | J8: Total | K8: Total/TU | L8: Sc1&2/TU | M8: Nat'l EF | N8: EF Used
A9: =+A4 -> XYZ | B9: =+B4 -> 0 | C9: =+Output!L2 -> 100 | D9: =+Output!L3 -> 100 | E9: =+Output!L4 -> 200 | F9: =+K4 -> 2011 | G9: =+Output!C34 -> 0.030502957 | H9: =+Output!C35 -> 0.0001721975 | I9: =+Output!C36 -> 5434.4557 | J9: =+Output!J33 -> 5434.4864 | K9: =+J9/E9*1000 -> 27172.432 | L9: =+(G9+H9)/E9*1000 -> 0.15337577 | M9: =+Output!H3 -> 34.4395 | N9: =+Output!H4 -> 34.4395

Sheet Calc1
A1: Calc 1 - Data processing page. | J1: =C4 -> 0 | K1: =J8 -> 2011
A2: GENERAL AIRPORT INFORMATION
A4: Mirror | B4: Airport Name: | C4: =+Input!C4 -> 0 | G4: Airport Operator: | H4: =+Input!H4 -> 0
A5: Input
A6: Page | B6: IATA Identifier: | C6: =+Input!C5 -> XYZ | D6: (3 letters) | E6: ICAO Identifier: | F6: =+Input!F5 -> WXYZ | G6: (4 letters) | I6: Date of Report (DD/MM/YYYY): | J6: =+Input!J5 -> 41153
B8: City: | C8: =+Input!C7 -> 0 | D8: =+Input!D7 -> 0 | E8: =+Input!E7 -> 0 | F8: =+Input!F7 -> 0 | I8: Calendar Year of Inventory: | J8: =+Input!J6 -> 2011
B10: Country: | C10: =+Input!C8 -> Albania | E10: ACI Region: | F10: =+Input!F8 -> Select One | I10: Aircraft movements in inventory year | J10: =+Input!J9 -> 100 | K10: movements
B11: Province: | C11: =+Input!C9 -> n/a | D11: (Canada only, otherwise select n/a) | I11: Passengers Movements in Inventory year | J11: =+Input!J10 -> 100 | K11: movements
I12: Cargo in inventory year | J12: =+Input!J11 -> 10 | K12: tonnes
B13: Inventory compiled by: | C13: =+Input!C11 -> name
B14: Position: | C14: =+Input!C12 -> 0
B15: email: | C15: =+Input!C13 -> 0
D17: Permission: This data is made available to ACI | E17: =+Input!E15 -> unconditionally | I17: Unit System: | J17: Metric (e.g. metres, litres, kg)
D18: Have you ever conducted a more detailed GHG inventory? | E18: =+Input!E16 -> No
D19: If yes, will you submit it to ACI with this inventory? | E19: =+Input!E17 -> No | F19: Most recent year? | G19: =+Input!G17 -> 0 | I19: Reminder: Save file under a new name eg LHR2012
B20: Note: - Make sure you can see Columns A through K
A22: SCOPE 1 - DIRECT EMISSIONS FROM SOURCES THAT ARE OWNED AND CONTROLLED BY THE AIRPORT OPERATOR
A24: Step 1-1: Input information for AIRPORT OPERATOR FLEET VEHICLES (vehicles, machinery and GSE)
A26: Mirror | B26: 1) Input total annual fuel usage for Airport Fleet | K26: Beta version - You can type comments here>>>>
A27: Input | B27: Fuel | C27: Volume | D27: Unit | E27: Note: Do not include ACU or GPU fuel. This is below.
A28: Page | B28: Gasoline | C28: =Input!D24 -> 5 | D28: litre | E28: Note: Include only fuel for airport owned vehicles.
B29: Diesel | C29: =Input!D25 -> 0 | D29: litre
B30: Natural Gas | C30: =Input!D26 -> 0 | D30: kg
B31: Propane | C31: =Input!D27 -> 0 | D31: litre
F32: Note: This table requires estimating the proportions of the fuel going into vehicles of different sizes.
B33: 1a) Input approximate percentages of fuel use in different vehicles | F33: Note: This data is for the Local Air Quality calculations, not for CO2
D34: Gasoline | E34: Diesel | F34: Note: Leave default values if estimates cannot be made. | J34: Gasoline (litre) | K34: Diesel (litre)
A35: Not on | B35: Passenger cars | D35: 0.8 | E35: 0.1 | F35: - cars and vehicles <2 tonnes | J35: =$C$28*D35 -> 4 | K35: =$C$29*E35 -> 0
A36: Input page | B36: Light-duty vehicles | D36: 0.2 | E36: 0.4 | F36: - vans and small buses typically <20 seats or 2-3.5 tonnes | J36: =$C$28*D36 -> 1 | K36: =$C$29*E36 -> 0
B37: Heavy-duty vehicles | D37: 0 | E37: 0.5 | F37: - buses, trucks, machinery > 20 seats or >3.5 tonnes | J37: =$C$28*D37 -> 0 | K37: =$C$29*E37 -> 0
D38: =+SUM(D35:D37) -> 1 | E38: =+SUM(E35:E37) -> 1
D39: =IF(SUM(D35:D37)>1, "> 100%, revise!", IF(SUM(D35:D37)<1, "< 100%, revise!", "Total % is OK.")) -> Total % is OK. | E39: =IF(SUM(E35:E37)>1, "> 100%, revise!", IF(SUM(E35:E37)<1, "< 100%, revise!", "Total % is OK.")) -> Total % is OK. | F39: Note: Percentages must add to 100%. Use whole numbers, no decimals.
B41: 2) Input total annual fuel usage for mobile equipment - Airport owned
E42: Gasoline | F42: Diesel | G42: Unit
B43: Mobile Air Conditioning Units (ACU) - Airport owned | E43: 0 | G43: litre | H43: This is included above
B44: Ground Power Units (GPU) - Airport owned | E44: 0 | G44: litre
A46: Step 1-2: Input information for AIRPORT OWNED AND OPERATED buildings (e.g. Power/electricity generation, heating/cooling plant, ATB, maintenance garage, etc.)
B48: 1) For buildings with metered fuel usage, input annual total usage: | F48: Note: Do not include Electricity - See Step 2
B49: Building Name | C49: Natural Gas | D49: Unit (Choose kg, m3 or GJ) | E49: Fuel Oil | F49: Unit | G49: Coal | H49: Unit
A50: Mirror | B50: =+Input!B52 -> eg Heating plant | C50: =+Input!C52 -> 10 | D50: =+Input!D52 -> m3 | E50: =+Input!E52 -> 0 | F50: litre | G50: =+Input!G52 -> 0 | H50: kg
A51: Input | B51: =+Input!B53 -> Power plant | C51: =+Input!C53 -> 0 | D51: =D$50 -> m3 | E51: =+Input!E53 -> 0 | F51: litre | G51: =+Input!G53 -> 0 | H51: kg
A52: Page | B52: =+Input!B54 -> 0 | C52: =+Input!C54 -> 0 | D52: =D$50 -> m3 | E52: =+Input!E54 -> 0 | F52: litre | G52: =+Input!G54 -> 0 | H52: kg
B53: =+Input!B55 -> 0 | C53: =+Input!C55 -> 0 | D53: =D$50 -> m3 | E53: =+Input!E55 -> 0 | F53: litre | G53: =+Input!G55 -> 0 | H53: kg
D54: =D$50 -> m3 | F54: litre | H54: kg
D55: =D$50 -> m3 | F55: litre | H55: kg
D56: =D$50 -> m3 | F56: litre | H56: kg | I56: You can add a row:
D57: =D$50 -> m3 | F57: litre | H57: kg | I57: 1. Select a cell in white;
D58: =D$50 -> m3 | F58: litre | H58: kg | I58: 2. Menu "Home" ->"Insert" -> "Rows".
B59: Total | C59: =SUM(C50:C58) -> 10 | D59: =D$50 -> m3 | E59: =SUM(E50:E58) -> 0 | F59: litre | G59: =SUM(G50:G58) -> 0 | H59: kg
A61: Step 1-3: Input the annual fuel usage for fire training (conducted by the Airport Operator Fire Services)
B63: Fuel | C63: Volume | D63: Unit
A64: Mirror | B64: Kerosene | C64: =+Input!D31 -> 0 | D64: litre
A65: Input | B65: Butane | C65: =+Input!D32 -> 0 | D65: litre
A66: Page | B66: Propane | C66: =+Input!D33 -> 0 | D66: kg
B67: Jet A | C67: =+Input!D34 -> 0 | D67: litre
B68: Jet B | C68: =+Input!D35 -> 0 | D68: litre
B69: Wood | C69: =+Input!D36 -> 0 | D69: kg | I69: Reminder: Save your data. Menu "File"-> "Save"
K70: Beta version - You can type comments here>>>>
A71: Step 1-4: Input the annual fuel flow for Stationary Emergency Power Generation Units, owned by the Airport Operator
B73: Generator Name | C73: Diesel | D73: Jet A | E73: Unit
E74: litre
E75: litre
E76: litre
E77: litre
B78: Total | C78: =+Input!D40 -> 0 | E78: litre | F78: Totals only. JetA not separate
A80: Step 1-5: Input annual glycol usage for de-icing by Airport Operator
B82: Glycol usage | C82: Volume | D82: Unit
B83: Movement Surfaces | C83: =+Input!D44 -> 0 | D83: litre
B84: Other | C84: =+Input!D45 -> 0 | D84: litre | F84: Note: Calculation is based on 50-50 dilluted glycol
I85: Reminder: Save your data. Menu "File"-> "Save"
A87: SCOPE 2 - INDIRECT EMISSIONS FROM THE GENERATION OF PURCHASED ELECTRICITY / HEAT CONSUMED BY AIRPORT
A88: Mirror
A89: Input | B89: Electricity Purchase
A90: Page
A91: Step 2-1 | B91: Input annual total Electricity purchased by airport from off-site supplier: | F91: =+Input!F69 -> 5 | G91: kWh | H91: Data should be available from electricity bills.
A93: Step 2-2 | B93: Input annual total Electricity resold to tenants: | F93: =+Input!F71 -> 0 | G93: kWh | H93: =IF(F91<F93,"Warning: Sold amount higher than bought amount!"," ")
A95: Step 2-3 | B95: Your country is | C95: =+IF(C10="(Select One)","You must select one at Line 9", C10) -> Albania | E95: Default EF is | F95: =VLOOKUP(C95,EF!$A$4:$B$158,2) -> 34.4395 | G95: g CO2/kWh Emission Factor for electricity purchased from the national grid
B97: Input your actual emissions factor, if you know it (if not, leave blank) | F97: =+Input!F78 -> 0 | G97: g CO2/kWh | H97: This will take zero emissions sources (eg hydro) into account.
A98: Mirror | H98: To see US data click here
A99: Input | B99: Heat (eg Hot water or Steam) Purchase
A100: Page
A101: Step 2-4 | B101: Input annual total Heat purchased by airport (eg hot water or steam) | F101: =+Input!F82 -> 0 | G101: =+Input!G82 -> kWh | H101: (select units - kWh or GJ)
H102: Data should be available from heating bills.
A103: Step 2-5 | B103: Input Fuel used by the off-site Heat producer: | F103: =+Input!F90 -> Natural Gas
H104: Heat used:
A105: Step 2-6 | B105: Input percentage of total Heat purchased which is then sold to Tenants: | F105: not used | H105: - by Airport: | I105: =+Input!F82-Input!F84 -> 0 | J105: =G101 -> kWh
H106: - byTenants: | I106: =+Input!F84 -> 0 | J106: =G101 -> kWh
H107: (This used in Step 3.5)
A109: SCOPE 3 - DIRECT AND INDIRECT EMISSIONS GENERATED BY TENANTS AND PASSENGERS
B110: (including airlines, government, concessionaires, aircraft operators, fixed-based operators, etc.)
H111: Note: 1 landing and 1 take-off (LTO) = 2 movements
A112: Step 3-1 Input Annual Aircraft Movements | H112: Note: For aircraft not listed use a similarly sized substitute.
H113: Note: In this calculation only aircraft LTO emissions are included.
B114: Aircraft Type | C114: Annual Movements | E114: Aircraft Type | F114: Annual Movements | H114: Aircraft Type | I114: Annual Movements
A115: Mirror | B115: A109 | C115: =+IF(Input!$H$95=2,Input!C112,+IF(Input!$H$95=0,0,0)) -> 0 | E115: CH-47 | F115: =+IF(Input!$H$95=2,Input!E128,+IF(Input!$H$95=0,0,0)) -> 0 | H115: MD83 (80-87) | I115: =+IF(Input!$H$95=2,Input!G144,+IF(Input!$H$95=0,0,0)) -> 0
A116: Input | B116: A119 | C116: =+IF(Input!$H$95=2,Input!C113,+IF(Input!$H$95=0,0,0)) -> 0 | E116: Cirrus SR22 | F116: =+IF(Input!$H$95=2,Input!E129,+IF(Input!$H$95=0,0,0)) -> 0 | H116: MD95 | I116: =+IF(Input!$H$95=2,Input!G145,+IF(Input!$H$95=0,0,0)) -> 0
A117: Page | B117: Airbus 300 | C117: =+IF(Input!$H$95=2,Input!C114,+IF(Input!$H$95=0,0,0)) -> 0 | E117: CL300 | F117: =+IF(Input!$H$95=2,Input!E130,+IF(Input!$H$95=0,0,0)) -> 0 | H117: Piaggio P180 | I117: =+IF(Input!$H$95=2,Input!I112,+IF(Input!$H$95=0,0,0)) -> 0
B118: Airbus 310 | C118: =+IF(Input!$H$95=2,Input!C115,+IF(Input!$H$95=0,0,0)) -> 0 | E118: CL415 | F118: =+IF(Input!$H$95=2,Input!E131,+IF(Input!$H$95=0,0,0)) -> 0 | H118: Pilatus PC-12 | I118: =+IF(Input!$H$95=2,Input!I113,+IF(Input!$H$95=0,0,0)) -> 0
B119: Airbus 319 | C119: =+IF(Input!$H$95=2,Input!C116,+IF(Input!$H$95=0,0,0)) -> 0 | E119: CL604 | F119: =+IF(Input!$H$95=2,Input!E132,+IF(Input!$H$95=0,0,0)) -> 0 | H119: Pilatus PC-21 | I119: =+IF(Input!$H$95=2,Input!I114,+IF(Input!$H$95=0,0,0)) -> 0
B120: Airbus 320 | C120: =+IF(Input!$H$95=2,Input!C117,+IF(Input!$H$95=0,0,Input!D101/2)) -> 0 | E120: CRJ200 | F120: =+IF(Input!$H$95=2,Input!E133,+IF(Input!$H$95=0,0,0)) -> 0 | H120: Pilatus PC-9 | I120: =+IF(Input!$H$95=2,Input!I115,+IF(Input!$H$95=0,0,0)) -> 0
...

Sheet Calc2
A1: Calculation Page 2
B4: =Calc1!A22 -> SCOPE 1 - DIRECT EMISSIONS FROM SOURCES THAT ARE OWNED AND CONTROLLED BY THE AIRPORT OPERATOR
A6: Step 1-1 | B6: Airside Vehicle Emission Calculation (Ton):
B8: Vehicle Type | C8: Volume (Liter) | E8: CO2 | F8: CH4 | G8: N2O | H8: NOx | I8: VOC | J8: CO | K8: PM | L8: SOx | M8: co2
B9: Light Gas Vehicle | C9: =Calc1!J35 -> 4 | D9: Gas EF (kg/L) | E9: 2.289 | F9: 0.00052 | G9: 0.0002 | H9: =14.5*730/1000/1000 -> 0.010585 | I9: =14*730/1000/1000 -> 0.01022 | J9: =132*730/1000/1000 -> 0.09636 | K9: =0.037*730/1000/1000 -> 2.701e-05 | L9: =0.04*730/1000/1000 -> 2.92e-05 | M9: =3180*730/1000/1000 -> 2.3214
B10: Light Gas Truck | C10: =Calc1!J36 -> 1 | D10: Gas EF (kg/L) | E10: 2.289 | F10: 0.00043 | G10: 0.0002 | H10: =24*730/1000/1000 -> 0.01752 | I10: =14*730/1000/1000 -> 0.01022 | J10: =155*730/1000/1000 -> 0.11315 | K10: =0.03*730/1000/1000 -> 2.19e-05 | L10: =0.04*730/1000/1000 -> 2.92e-05 | M10: =3180*730/1000/1000 -> 2.3214
B11: Heavy Gas Vehicle | C11: =Calc1!J37 -> 0 | D11: Gas EF (kg/L) | E11: 2.289 | F11: 0.00068 | G11: 0.0002 | H11: =Stat!H21*730/1000/1000 -> 0.027220339 | I11: =Stat!I21*730/1000/1000 -> 0.021652542 | J11: =Stat!J21*730/1000/1000 -> 0.24539548 | K11: =Stat!K21*730/1000/1000 -> 0 | L11: =Stat!M21*730/1000/1000 -> 2.92e-05
B13: Light Diesel Vehicle | C13: =Calc1!K35 -> 0 | D13: Diesel EF (kg/L) | E13: 2.663 | F13: 6.8e-05 | G13: 0.00021 | H13: =11*840/1000/1000 -> 0.00924 | I13: =1.1*840/1000/1000 -> 0.000924 | J13: =4.7*840/1000/1000 -> 0.003948 | K13: =1.7*840/1000/1000 -> 0.001428 | L13: =0.008*840/1000/1000 -> 6.72e-06 | M13: =3140*840/1000/1000 -> 2.6376
B14: Light Diesel Truck | C14: =Calc1!K36 -> 0 | D14: Diesel EF (kg/L) | E14: 2.663 | F14: 6.8e-05 | G14: 0.00021 | H14: =15*840/1000/1000 -> 0.0126 | I14: =1.75*840/1000/1000 -> 0.00147 | J14: =11*840/1000/1000 -> 0.00924 | K14: =2.8*840/1000/1000 -> 0.002352 | L14: =0.008*840/1000/1000 -> 6.72e-06
B15: Heavy Diesel Vehicle | C15: =Calc1!K37 -> 0 | D15: Diesel EF (kg/L) | E15: 2.663 | F15: 0.00014 | G15: 8.2e-05 | H15: =37*840/1000/1000 -> 0.03108 | I15: =1.6*840/1000/1000 -> 0.001344 | J15: =8*840/1000/1000 -> 0.00672 | K15: =1.2*840/1000/1000 -> 0.001008 | L15: =0.008*840/1000/1000 -> 6.72e-06
N16: co2e | O16: check - i.e. should = output total for both fuel types next sheet
D17: Gas Em | E17: =SUMPRODUCT($C$9:$C$11,E9:E11)/1000 -> 0.011445 | F17: =SUMPRODUCT($C$9:$C$11,F9:F11)/1000 -> 2.51e-06 | G17: =SUMPRODUCT($C$9:$C$11,G9:G11)/1000 -> 1e-06 | H17: =SUMPRODUCT($C$9:$C$11,H9:H11)/1000 -> 5.986e-05 | I17: =SUMPRODUCT($C$9:$C$11,I9:I11)/1000 -> 5.11e-05 | J17: =SUMPRODUCT($C$9:$C$11,J9:J11)/1000 -> 0.00049859 | K17: =SUMPRODUCT($C$9:$C$11,K9:K11)/1000 -> 1.2994e-07 | L17: =SUMPRODUCT($C$9:$C$11,L9:L11)/1000 -> 1.46e-07 | N17: =E17+F17*21+G17*310 -> 0.01180771
D18: Diesel Em | E18: =SUMPRODUCT($C$13:$C$15,E13:E15)/1000 -> 0 | F18: =SUMPRODUCT($C$13:$C$15,F13:F15)/1000 -> 0 | G18: =SUMPRODUCT($C$13:$C$15,G13:G15)/1000 -> 0 | H18: =SUMPRODUCT($C$13:$C$15,H13:H15)/1000 -> 0 | I18: =SUMPRODUCT($C$13:$C$15,I13:I15)/1000 -> 0 | J18: =SUMPRODUCT($C$13:$C$15,J13:J15)/1000 -> 0 | K18: =SUMPRODUCT($C$13:$C$15,K13:K15)/1000 -> 0 | L18: =SUMPRODUCT($C$13:$C$15,L13:L15)/1000 -> 0 | N18: =E18+F18*21+G18*310 -> 0 | O18: =SUM(N17:N18) -> 0.01180771
D20: Subtotal (t) | E20: =SUM(E17:E18) -> 0.011445 | F20: =SUM(F17:F18) -> 2.51e-06 | G20: =SUM(G17:G18) -> 1e-06 | H20: =SUM(H17:H18) -> 5.986e-05 | I20: =SUM(I17:I18) -> 5.11e-05 | J20: =SUM(J17:J18) -> 0.00049859 | K20: =SUM(K17:K18) -> 1.2994e-07 | L20: =SUM(L17:L18) -> 1.46e-07
B22: Vehicle Type | C22: units | E22: CO2 | F22: CH4 | G22: N2O | H22: NOx | I22: VOC | J22: CO | K22: PM | L22: SOx
B23: Natural Gas Vehicle | C23: =Calc1!C30/1000 -> 0 | D23: CNG EF | E23: 148 | F23: =1000*0.000009 -> 0.009 | G23: =1000*0.00000006 -> 6e-05 | H23: 0.056 | I23: 0.015 | J23: 0.395 | K23: 0.002 | L23: 0
B24: Propane Vehicle | C24: =Calc1!C31/1000 -> 0 | D24: Propane EF (kg/m3) | E24: =1000*1.51 -> 1510 | F24: =1000*0.00064 -> 0.64 | G24: =1000*0.000028 -> 0.028 | H24: =15.5*510/1000 -> 7.905 | I24: =10*510/1000 -> 5.1 | J24: =68*510/1000 -> 34.68 | K24: 0 | L24: 0
D26: CNG Em (tonne) | E26: =$C$23*1000/50*E23/1000/1000 -> 0 | F26: =$C$23/0.714*F23/1000 -> 0 | G26: =$C$23/0.714*G23/1000 -> 0 | H26: =$C$23*1000/50*H23/1000/1000 -> 0 | I26: =$C$23*1000/50*I23/1000/1000 -> 0 | J26: =$C$23*1000/50*J23/1000/1000 -> 0 | K26: =$C$23*1000/50*K23/1000/1000 -> 0 | L26: =$C$23*1000/50*L23/1000/1000 -> 0
D27: Propane em (tonne) | E27: =$C$24*E24/1000 -> 0 | F27: =$C$24*F24/1000 -> 0 | G27: =$C$24*G24/1000 -> 0 | H27: =$C$24*H24/1000 -> 0 | I27: =$C$24*I24/1000 -> 0 | J27: =$C$24*J24/1000 -> 0 | K27: =$C$24*K24/1000 -> 0 | L27: =$C$24*L24/1000 -> 0
D29: Subtotal | E29: =SUM(E26:E27) -> 0 | F29: =SUM(F26:F27) -> 0 | G29: =SUM(G26:G27) -> 0 | H29: =SUM(H26:H27) -> 0 | I29: =SUM(I26:I27) -> 0 | J29: =SUM(J26:J27) -> 0 | K29: =SUM(K26:K27) -> 0 | L29: =SUM(L26:L27) -> 0
B31: ACU | C31: Volume (L) | E31: CO2 | F31: CH4 | G31: N2O | H31: NOx | I31: VOC | J31: CO | K31: PM | L31: SOx
B32: Gasoline | C32: =Calc1!E43 -> 0 | D32: Gas EF (kg/L) | E32: 2.289 | F32: 0.00052 | G32: 0.0002 | H32: =14.5*730/1000/1000 -> 0.010585 | I32: =14*730/1000/1000 -> 0.01022 | J32: =132*730/1000/1000 -> 0.09636 | K32: =0.037*730/1000/1000 -> 2.701e-05 | L32: =0.04*730/1000/1000 -> 2.92e-05
B33: Diesel | C33: =Calc1!F43 -> 0 | D33: Diesel EF (kg/L) | E33: 2.663 | F33: 6.8e-05 | G33: 0.00021 | H33: =11*840/1000/1000 -> 0.00924 | I33: =1.1*840/1000/1000 -> 0.000924 | J33: =4.7*840/1000/1000 -> 0.003948 | K33: =1.7*840/1000/1000 -> 0.001428 | L33: =0.008*840/1000/1000 -> 6.72e-06
D34: Subtotal | E34: =SUMPRODUCT($C$32:$C$33,E32:E33)/1000 -> 0 | F34: =SUMPRODUCT($C$32:$C$33,F32:F33)/1000 -> 0 | G34: =SUMPRODUCT($C$32:$C$33,G32:G33)/1000 -> 0 | H34: =SUMPRODUCT($C$32:$C$33,H32:H33)/1000 -> 0 | I34: =SUMPRODUCT($C$32:$C$33,I32:I33)/1000 -> 0 | J34: =SUMPRODUCT($C$32:$C$33,J32:J33)/1000 -> 0 | K34: =SUMPRODUCT($C$32:$C$33,K32:K33)/1000 -> 0 | L34: =SUMPRODUCT($C$32:$C$33,L32:L33)/1000 -> 0
B36: GPU | E36: CO2 | F36: CH4 | G36: N2O | H36: NOx | I36: VOC | J36: CO | K36: PM | L36: SOx
B37: Gasoline | C37: =Calc1!E44 -> 0 | D37: Gas EF (kg/L) | E37: 2.289 | F37: 0.00052 | G37: 0.0002 | H37: =14.5*730/1000/1000 -> 0.010585 | I37: =14*730/1000/1000 -> 0.01022 | J37: =132*730/1000/1000 -> 0.09636 | K37: =0.037*730/1000/1000 -> 2.701e-05 | L37: =0.04*730/1000/1000 -> 2.92e-05
B38: Diesel | C38: =Calc1!F44 -> 0 | D38: Diesel EF (kg/L) | E38: 2.663 | F38: 6.8e-05 | G38: 0.00021 | H38: =11*840/1000/1000 -> 0.00924 | I38: =1.1*840/1000/1000 -> 0.000924 | J38: =4.7*840/1000/1000 -> 0.003948 | K38: =1.7*840/1000/1000 -> 0.001428 | L38: =0.008*840/1000/1000 -> 6.72e-06
D39: Subtotal | E39: =SUMPRODUCT($C$37:$C$38,E37:E38)/1000 -> 0 | F39: =SUMPRODUCT($C$37:$C$38,F37:F38)/1000 -> 0 | G39: =SUMPRODUCT($C$37:$C$38,G37:G38)/1000 -> 0 | H39: =SUMPRODUCT($C$37:$C$38,H37:H38)/1000 -> 0 | I39: =SUMPRODUCT($C$37:$C$38,I37:I38)/1000 -> 0 | J39: =SUMPRODUCT($C$37:$C$38,J37:J38)/1000 -> 0 | K39: =SUMPRODUCT($C$37:$C$38,K37:K38)/1000 -> 0 | L39: =SUMPRODUCT($C$37:$C$38,L37:L38)/1000 -> 0
D41: Airside Vehicle Subtotal | E41: =E20+E29+E34+E39 -> 0.011445 | F41: =F20+F29+F34+F39 -> 2.51e-06 | G41: =G20+G29+G34+G39 -> 1e-06 | H41: =H20+H29+H34+H39 -> 5.986e-05 | I41: =I20+I29+I34+I39 -> 5.11e-05 | J41: =J20+J29+J34+J39 -> 0.00049859 | K41: =K20+K29+K34+K39 -> 1.2994e-07 | L41: =L20+L29+L34+L39 -> 1.46e-07
B43: Note:
B44: Source: Environment Canada, "National Inventory Report 1990 - 2006", Annex 12 Table 12-7: Emission Factors for Energy Combustion Sources.
B45: Gasoline Vehicles: Light vehicle-Oxidation Catalyst; light truck-Oxidation Catalyst; heavy vehicle-three way catalyst.
B46: Diesel Vehicles: Moderate Control.
A48: Step 1-2 | B48: Building Emission Calculation (Ton)
B49: 1) Natural Gas
B50: Building | C50: Square Meter | D50: GJ/Annum | E50: Estimated NG (GJ)
F52: =SUM(E51:E52) -> 0
E53: =SUM(E51:E52) -> 0 | F53: GJ
E54: qty & unit as input
B55: Known NG total | E55: =Calc1!C59 -> 10 | F55: =Calc1!D59 -> m3
B56: Convert Known NG | E56: =IF(F55="GJ",E55,IF(F55="kg",E55*46.5/1000,E55*0.716*46.5/1000)) -> 0.33294 | F56: GJ
B59: Total NG (GJ) | E59: =E56+E53 -> 0.33294
C61: CO2 | D61: CH4 | E61: N2O | F61: NOx | G61: VOC | H61: CO | I61: PM | J61: SOx
B62: EF (T/GJ) | C62: 0.0561 | D62: 1e-06 | E62: 1e-07 | F62: =70/1000/1000 -> 7e-05 | G62: =3/1000/1000 -> 3e-06 | H62: =30/1000/1000 -> 3e-05 | I62: =0.5/1000/1000 -> 5e-07 | J62: =0.5/1000/1000 -> 5e-07
B63: Emission (Ton) | C63: =$E$59*C62 -> 0.018677934 | D63: =$E$59*D62 -> 3.3294e-07 | E63: =$E$59*E62 -> 3.3294e-08 | F63: =$E$59*F62 -> 2.33058e-05 | G63: =$E$59*G62 -> 9.9882e-07 | H63: =$E$59*H62 -> 9.9882e-06 | I63: =$E$59*I62 -> 1.6647e-07 | J63: =$E$59*J62 -> 1.6647e-07
B64: Source: 2006 IPCC Guidelines for National GHG Inventories, Volume 2, Table 2.2
B66: 3) Fuel Oil
B67: Annual Fuel Oil (L) | C67: =Calc1!E59 -> 0 | D67: Input in Litres
B68: GHG | C68: CO2 | D68: CH4 | E68: N2O | F68: NOx | G68: VOC | H68: CO | I68: PM | J68: SOx
B69: EF (T/L) | C69: 0.002725 | D69: 2.6e-08 | E69: 3.1e-08 | F69: =398*42.6*0.845/1000/1000/1000 -> 1.4326806e-05 | G69: =0.19*42.6*0.845/1000/1000/1000 -> 6.83943e-09 | H69: =1.49*42.6*0.845/1000/1000/1000 -> 5.363553e-08 | I69: =3*42.6*0.845/1000/1000/1000 -> 1.07991e-07 | J69: =46.1*42.6*0.845/1000/1000/1000 -> 1.6594617e-06
B70: Emission (Ton) | C70: =$C$67*C69 -> 0 | D70: =$C$67*D69 -> 0 | E70: =$C$67*E69 -> 0 | F70: =$C$67*F69 -> 0 | G70: =$C$67*G69 -> 0 | H70: =$C$67*H69 -> 0 | I70: =$C$67*I69 -> 0 | J70: =$C$67*J69 -> 0
B71: Source: Environment Canada, "National Inventory Report 1990 - 2006", Annex 12 Table 12-2, Light Fuel Oil for Commercial/Institutional.
B73: 2) Coal
B74: Annual Coal (GJ) | C74: =Calc1!G59*28.1/1000 -> 0 | D74: Input in kg converted here to GJ
B75: GHG | C75: CO2 | D75: CH4 | E75: N2O | F75: NOx | G75: VOC | H75: CO | I75: PM | J75: SOx
B76: EF (g/GJ) | C76: 94000 | D76: 10 | E76: 1.5 | F76: 160 | G76: 200 | H76: 2000 | I76: 190 | J76: 900
B77: Emission (Ton) | C77: =$C$74*C76/1000/1000 -> 0 | D77: =$C$74*D76/1000/1000 -> 0 | E77: =$C$74*E76/1000/1000 -> 0 | F77: =$C$74*F76/1000/1000 -> 0 | G77: =$C$74*G76/1000/1000 -> 0 | H77: =$C$74*H76/1000/1000 -> 0 | I77: =$C$74*I76/1000/1000 -> 0 | J77: =$C$74*J76/1000/1000 -> 0
B78: Source: 2006 IPCC Guidelines for National GHG Inventories, Volume 2, Table 2.4
B80: Sum Gas/Oil/Coal | C80: =+C63+C70+C77 -> 0.018677934 | D80: =+D63+D70+D77 -> 3.3294e-07 | E80: =+E63+E70+E77 -> 3.3294e-08 | F80: =+F63+F70+F77 -> 2.33058e-05 | G80: =+G63+G70+G77 -> 9.9882e-07 | H80: =+H63+H70+H77 -> 9.9882e-06 | I80: =+I63+I70+I77 -> 1.6647e-07 | J80: =+J63+J70+J77 -> 1.6647e-07
A83: Step 1-3 | B83: Fire Training Emission Calculation (Ton):
C85: Volume (Liter) | E85: CO2 | F85: CH4 | G85: N2O | H85: NOx | I85: VOC | J85: CO | K85: PM | L85: SOx
B86: Kerosene | C86: =Calc1!C64 -> 0 | D86: Kerosene EF (kg/L) | E86: 3.15 | F86: 0.0075 | G86: 0.0388 | H86: =5.04*0.8/1000 -> 0.004032 | I86: =20.22*0.8/1000 -> 0.016176 | J86: =672.08*0.8/1000 -> 0.537664 | K86: =151.88*0.8/1000 -> 0.121504 | L86: =1.02*0.8/1000 -> 0.000816
D87: Emission (Ton) | E87: =$C$86*E86/1000 -> 0 | F87: =$C$86*F86/1000 -> 0 | G87: =$C$86*G86/1000 -> 0 | H87: =$C$86*H86/1000 -> 0 | I87: =$C$86*I86/1000 -> 0 | J87: =$C$86*J86/1000 -> 0 | K87: =$C$86*K86/1000 -> 0 | L87: =$C$86*L86/1000 -> 0
B88: Butane | C88: =Calc1!C65 -> 0 | D88: Butane EF (kg/L) | E88: 1.73 | F88: 2.4e-05 | G88: 0.000108 | H88: =H90 -> 1.32 | I88: =I90 -> 6.57 | J88: =J90 -> 7.19 | K88: =K90 -> 24.21 | L88: =L90 -> 0
D89: Emission (Ton) | E89: =$C$88*E88/1000 -> 0 | F89: =$C$88*F88/1000 -> 0 | G89: =$C$88*G88/1000 -> 0
B90: Propane | C90: =Calc1!C66 -> 0 | D90: Propane EF (g/kg) | E90: 3030 | F90: 0.053 | G90: 0.2112 | H90: 1.32 | I90: 6.57 | J90: 7.19 | K90: 24.21 | L90: 0 | M90: <<<emission factor, converted from table
D91: Emission (Ton) | E91: =$C$90*E90/1000/1000 -> 0 | F91: =$C$90*F90/1000/1000 -> 0 | G91: =$C$90*G90/1000/1000 -> 0 | H91: =$C$90*H90/1000/1000 -> 0 | I91: =$C$90*I90/1000/1000 -> 0 | J91: =$C$90*J90/1000/1000 -> 0 | K91: =$C$90*K90/1000/1000 -> 0 | L91: =$C$90*L90/1000/1000 -> 0 | N91: Emission Index (lbs/10^3 gallon) US EPA Appendix H pg 16
B92: Jet A | C92: =Calc1!C67 -> 0 | D92: Jet A EF (kg/L) | E92: 2.534 | F92: 8e-05 | G92: 0.00023 | H92: =$P$95/10^3*0.1198 -> 0.00403127 | I92: =$R$95/10^3*0.1198 -> 0.016173 | J92: =$N$95/10^3*0.1198 -> 0.5375426 | K92: =$O$95/10^3*0.1198 -> 0.1214772 | L92: =$Q$95/10^3*0.1198 -> 0.00081464 | M92: Fuel | N92: CO | O92: PM | P92: Nox | Q92: SO2 | R92: VOC
D93: Emission (Ton) | E93: =$C$92*E92/1000 -> 0 | F93: =$C$92*F92/1000 -> 0 | G93: =$C$92*G92/1000 -> 0 | H93: =$C$92*H92/1000 -> 0 | I93: =$C$92*I92/1000 -> 0 | J93: =$C$92*J92/1000 -> 0 | K93: =$C$92*K92/1000 -> 0 | L93: =$C$92*L92/1000 -> 0 | M93: propane | N93: 34.8 | O93: 117.2 | P93: 6.4 | Q93: 0.02 | R93: 31.8
B94: Jet B | C94: =Calc1!C68 -> 0 | D94: Jet B EF (kg/L) | E94: 2.534 | F94: 8e-05 | G94: 0.00023 | H94: =$P$94/10^3*0.1198 -> 0.003220224 | I94: =$R$94/10^3*0.1198 -> 0.0153344 | J94: =$N$94/10^3*0.1198 -> 0.4293632 | K94: =$O$94/10^3*0.1198 -> 0.115008 | L94: =$Q$94/10^3*0.1198 -> 0.00045524 | M94: JP-4 (Jet B) | N94: 3584 | O94: 960 | P94: 26.88 | Q94: 3.8 | R94: 128
D95: Emission (Ton) | E95: =$C$94*E94/1000 -> 0 | F95: =$C$94*F94/1000 -> 0 | G95: =$C$94*G94/1000 -> 0 | H95: =$C$94*H94/1000 -> 0 | I95: =$C$94*I94/1000 -> 0 | J95: =$C$94*J94/1000 -> 0 | K95: =$C$94*K94/1000 -> 0 | L95: =$C$94*L94/1000 -> 0 | M95: JP-8 (Jet A) | N95: 4487 | O95: 1014 | P95: 33.65 | Q95: 6.8 | R95: 135
B96: Wood | C96: =Calc1!C69 -> 0 | D96: wood EF (g/kg) | E96: 950 | F96: 0.05 | G96: 0.02 | H96: 1.72 | I96: 4.98 | J96: 104 | K96: 18.8
D97: Emission (Ton) | E97: =$C$96*E96/1000/1000 -> 0 | F97: =$C$96*F96/1000/1000 -> 0 | G97: =$C$96*G96/1000/1000 -> 0 | H97: =$C$96*H96/1000/1000 -> 0 | I97: =$C$96*I96/1000/1000 -> 0 | J97: =$C$96*J96/1000/1000 -> 0 | K97: =$C$96*K96/1000/1000 -> 0 | L97: =$C$96*L96/1000/1000 -> 0
D99: Subtotal | E99: =+E87+E89+E91+E93+E95+E97 -> 0 | F99: =+F87+F89+F91+F93+F95+F97 -> 0 | G99: =+G87+G89+G91+G93+G95+G97 -> 0 | H99: =+H87+H89+H91+H93+H95+H97 -> 0 | I99: =+I87+I89+I91+I93+I95+I97 -> 0 | J99: =+J87+J89+J91+J93+J95+J97 -> 0 | K99: =+K87+K89+K91+K93+K95+K97 -> 0 | L99: =+L87+L89+L91+L93+L95+L97 -> 0
B100: Note:
B101: Source: Environment Canada, "National Inventory Report 1990 - 2006", Annex 12 Table 12-7: Emission Factors for Energy Mobile Combustion Sources.
B102: Propane CH4, N2O, Butane Source: Environment Canada, "National Inventory Report 1990 - 2008", Table A8-3: Emission Factors for Natual Gas Liquids.
B103: Kerosene Source: Environment Canada, "National Inventory Report 1990 - 2008", Table A8-4: Emission Factors for Refined Petroleum Products.
B104: Jet A/B Source: Environment Canada, "National Inventory Report 1990 - 2008", Table A8-11: Emission Factors for Energy Mobile Combustion Sources.
B105: Wood Source: Environment Canada, "National Inventory Report 1990 - 2008", Table A8-25: Emission Factors for Biomass.
A108: Step 1-4 | B108: Stationary Emergency Power Generator Calculation (Ton):
B110: Volume (Liter) | D110: CO2 | E110: CH4 | F110: N2O | G110: NOx | H110: VOC | I110: CO | J110: PM | K110: SOx
B111: =Calc1!C78 -> 0 | C111: Diesel EF (kg/L) | D111: 2.663 | E111: 0.000133 | F111: 0.0004 | G111: =1400*42.7*0.83/1000/1000 -> 0.0496174 | H111: =70*42.7*0.83/1000/1000 -> 0.00248087 | I111: =210*42.7*0.83/1000/1000 -> 0.00744261 | J111: =30*42.7*0.83/1000/1000 -> 0.00106323 | K111: =65*42.7*0.83/1000/1000 -> 0.002303665
C112: Diesel Em (ton) | D112: =$B111*D111/1000 -> 0 | E112: =$B111*E111/1000 -> 0 | F112: =$B111*F111/1000 -> 0 | G112: =$B111*G111/1000 -> 0 | H112: =$B111*H111/1000 -> 0 | I112: =$B111*I111/1000 -> 0 | J112: =$B111*J111/1000 -> 0 | K112: =$B111*K111/1000 -> 0
B114: =Calc1!D78 -> 0 | C114: Jet A EF (kg/L) | D114: 2.534 | E114: 8e-05 | F114: 0.00023 | G114: =469/10^3*0.1198 -> 0.0561862 | H114: =32.1/10^3*0.1198 -> 0.00384558 | I114: =102/10^3*0.1198 -> 0.0122196 | J114: =33.5/10^3*0.1198 -> 0.0040133 | K114: =128/10^3*0.1198 -> 0.0153344
C115: Jet A Em | D115: =$B114*D114/1000 -> 0 | E115: =$B114*E114/1000 -> 0 | F115: =$B114*F114/1000 -> 0 | G115: =$B114*G114/1000 -> 0 | H115: =$B114*H114/1000 -> 0 | I115: =$B114*I114/1000 -> 0 | J115: =$B114*J114/1000 -> 0 | K115: =$B114*K114/1000 -> 0 | L115: =$B114*L114/1000 -> 0
C117: Subtotal | D117: =D112+D115 -> 0 | E117: =E112+E115 -> 0 | F117: =F112+F115 -> 0 | G117: =G112+G115 -> 0 | H117: =H112+H115 -> 0 | I117: =I112+I115 -> 0 | J117: =J112+J115 -> 0 | K117: =K112+K115 -> 0
B119: Note:
B120: Source: Environment Canada, "National Inventory Report 1990 - 2006", Annex 12 Table 12-2 and 12-7.
A122: Step 1-5 | B122: Deicing/Anti-icing Fluid Emission Calculation (Ton):
B124: Volume (Litre) | D124: CO2 | E124: CH4 | F124: N2O | G124: NOx | H124: VOC | I124: CO | J124: PM | K124: SOx
B125: =+Calc1!C83 -> 0 | C125: Aircraft EF | D125: =1.736/2 -> 0.868 | E125: 0 | F125: 0 | H125: 0.11
C126: aircraft Em | D126: =$B125*D125/1000 -> 0 | E126: =$B125*E125/1000 -> 0 | F126: =$B125*F125/1000 -> 0 | H126: =$B125/1000*2*H125/1000 -> 0
B127: =+Calc1!C84 -> 0 | C127: Surface EF | D127: =1.736/2 -> 0.868 | E127: 0 | F127: 0 | H127: 0.11
C128: surface Em | D128: =D127*$B127/1000 -> 0 | E128: =E127*$B$524/1000 -> 0 | F128: =F127*$B$524/1000 -> 0 | H128: =$B127/1000*2*H127/1000 -> 0
C129: Subtotal (ton) | D129: =D126+D128 -> 0 | E129: =E126+E128 -> 0 | F129: =F126+F128 -> 0 | G129: =G126+G128 -> 0 | H129: =H126+H128 -> 0 | J129: =J126+J128 -> 0 | K129: =K126+K128 -> 0
B131: Note: CO2 EF: 1.736 kg/L for pure glycol, so 0.868 kg/L for 50-50 diluted glycol.
B134: =Calc1!A87 -> SCOPE 2 - INDIRECT EMISSIONS FROM THE GENERATION OF PURCHASED ELECTRICITY / HEAT CONSUMED BY AIRPORT | K134: Provincial Electricity Emission Factors
K135: Province | L135: t CO2-e/Kwh
B136: Electricity | K136: AB | L136: 0.000924
...

Sheet Acraft
A1: Data: Emission Factors for Aircraft
A2: Aircraft type | B2: #/Eng | C2: Typical engine | D2: Data | E2: Fuel (kg/LTO*) | F2: NOx (kg/ LTO*) | G2: HC (kg/ LTO*) | H2: CO (kg/ LTO*) | I2: PM (kg/ LTO*) | J2: SOx (kg/ LTO*) | K2: CO2 (kg/ LTO*) | L2: Fuel (g/min taxi) | M2: NOx (g/min taxi) | N2: HC (g/min taxi) | O2: CO (g/min taxi) | P2: PM (g/min taxi) | Q2: SOx (g/min taxi) | R2: CO2 (g/min taxi) | S2: FB (kg/min) | T2: Nox (g/min) | U2: HC (g/min) | V2: CO (g/min) | W2: PM (g/min) | X2: Sox (g/min) | Y2: CO2 (g/min)
A3: A109 | B3: 2H | C3: PW206C | D3: LSZH-H650 | E3: 69.888 | F3: 0.3214536 | G3: 1.3146354 | H3: 2.3507406 | I3: 0.00451832 | J3: 0.034944 | K3: 220.1472
A4: A119 | B4: 2H | C4: PT6B-37A | D4: LSZH-H900 | E4: 114.66 | F4: 0.8468148 | G4: 1.0201152 | H4: 1.3058838 | I4: 0.00738252 | J4: 0.05733 | K4: 361.179
A5: Airbus 300 | B5: 2J | C5: CF6-50A | D5: ICAO-3GE069 | E5: 973.44 | F5: 18.908528 | G5: 0.23956752 | H5: 2.0846969 | I5: 0.056265003 | J5: 0.48672 | K5: 3066.336 | L5: 19560 | M5: 66.504 | N5: 53.2032 | O5: 470.2224 | P5: 1.4568535 | Q5: 9.78 | R5: 61614 | S5: 4 | T5: 32 | U5: 2.1333333 | V5: 2.8 | W5: 0.53333333 | X5: 2 | Y5: 12600
A6: Airbus 310 | B6: 2J | C6: CF6-80A | D6: ICAO-1GE010 | E6: 967.26 | F6: 20.602452 | G6: 0.4416414 | H6: 2.124168 | I6: 0.060675899 | J6: 0.48363 | K6: 3046.869 | L6: 18000 | M6: 61.2 | N6: 113.22 | O6: 507.6 | P6: 1.8241209 | Q6: 9 | R6: 56700 | S6: 4 | T6: 32 | U6: 2.1333333 | V6: 2.8 | W6: 0.53333333 | X6: 2 | Y6: 12600
A7: Airbus 319 | B7: 2J | C7: CFM56-5B5P | D7: ICAO-3CM027 | E7: 406.812 | F7: 6.3916356 | G7: 0.2114424 | H7: 1.0259676 | I7: 0.017344058 | J7: 0.203406 | K7: 1281.4578 | L7: 11280 | M7: 42.864 | N7: 69.936 | O7: 338.4 | P7: 1.1018015 | Q7: 5.64 | R7: 35532 | S7: 1.7777778 | T7: 15.555556 | U7: 0.66666667 | V7: 6.8888889 | W7: 0.55555556 | X7: 0.88888889 | Y7: 5600
A8: Airbus 320 | B8: 2J | C8: CFM56-5B4P | D8: ICAO-3CM026 | E8: 504.168 | F8: 9.940416 | G8: 0.2006736 | H8: 0.9442152 | I8: 0.02194725 | J8: 0.252084 | K8: 1588.1292 | L8: 12480 | M8: 53.664 | N8: 57.408 | O8: 292.032 | P8: 1.0958119 | Q8: 6.24 | R8: 39312 | S8: 1.7777778 | T8: 15.555556 | U8: 0.66666667 | V8: 6.8888889 | W8: 0.55555556 | X8: 0.88888889 | Y8: 5600
A9: Airbus 321 | B9: 2J | C9: CFM56-5B1P | D9: ICAO-3CM023 | E9: 566.892 | F9: 12.739034 | G9: 0.1983804 | H9: 0.9418428 | I9: 0.023201222 | J9: 0.283446 | K9: 1785.7098 | L9: 13200 | M9: 59.4 | N9: 48.84 | O9: 261.36 | P9: 1.0857322 | Q9: 6.6 | R9: 41580 | S9: 1.7777778 | T9: 15.555556 | U9: 0.66666667 | V9: 6.8888889 | W9: 0.55555556 | X9: 0.88888889 | Y9: 5600
A10: Airbus 330 | B10: 2J | C10: PW4168 | D10: ICAO-9PW094 | E10: 1302.66 | F10: 26.543941 | G10: 0.04836 | H10: 1.0975669 | I10: 0.045550932 | J10: 0.65133 | K10: 4103.379 | L10: 30240 | M10: 123.3792 | N10: 28.728 | O10: 446.9472 | P10: 1.6578022 | Q10: 15.12 | R10: 95256 | S10: 4 | T10: 32 | U10: 2.1333333 | V10: 2.8 | W10: 0.53333333 | X10: 2 | Y10: 12600
A11: Airbus 340 | B11: 4J | C11: CFM56-5C4/1P | D11: ICAO-7CM047 | E11: 1220.664 | F11: 27.734873 | G11: 0.138 | H11: 2.0504208 | I11: 0.062235344 | J11: 0.610332 | K11: 3845.0916 | L11: 27600 | M11: 113.16 | N11: 138 | O11: 872.16 | P11: 2.9808 | Q11: 13.8 | R11: 86940 | S11: 4 | T11: 32 | U11: 2.1333333 | V11: 2.8 | W11: 0.53333333 | X11: 2 | Y11: 12600
A12: Airbus 380 | B12: 4J | C12: RR Trent 970 | D12: ICAO-8RR048 | E12: 2342.4 | F12: 58.07952 | G12: 0.0144 | H12: 2.43504 | I12: 0.075429778 | J12: 1.1712 | K12: 7378.56 | L12: 72000 | M12: 367.2 | N12: 14.4 | O12: 1087.2 | P12: 3.8814635 | Q12: 36 | R12: 226800 | S12: 4 | T12: 32 | U12: 2.1333333 | V12: 2.8 | W12: 0.53333333 | X12: 2 | Y12: 12600
A13: An-128 | B13: 4J | C13: D18T | D13: FOCA-J357 | E13: 2176.092 | F13: 45.257227 | G13: 1.1717208 | H13: 4.4182584 | I13: 0.10752268 | J13: 1.088046 | K13: 6854.6898 | L13: 56880 | M13: 170.64 | N13: 682.56 | O13: 3014.64 | P13: 7.9628987 | Q13: 28.44 | R13: 179172 | S13: 4 | T13: 32 | U13: 2.1333333 | V13: 2.8 | W13: 0.53333333 | X13: 2 | Y13: 12600
A14: An-70 | B14: 4T | C14: ZMKB D27 | D14: FAEED135 | E14: 375.612 | F14: 3.0774257 | G14: 0.78690708 | H14: 2.0163804 | I14: 0.027777304 | J14: 0.187806 | K14: 1183.1778 | L14: 18456 | M14: 64.96512 | N14: 325.01016 | O14: 804.6816 | P14: 3.6912 | Q14: 9.228 | R14: 58136.4 | S14: 4 | T14: 32 | U14: 2.1333333 | V14: 2.8 | W14: 0.53333333 | X14: 2 | Y14: 12600
A15: AN-72/74 | B15: 2J | C15: D-36 | D15: ICAO-1ZM001 | E15: 307.248 | F15: 5.45784 | G15: 0.0648 | H15: 0.6047688 | I15: 0.016527997 | J15: 0.153624 | K15: 967.8312 | L15: 12000 | M15: 66 | N15: 64.8 | O15: 248.4 | P15: 1.4230332 | Q15: 6 | R15: 37800 | S15: 1.7777778 | T15: 15.555556 | U15: 0.66666667 | V15: 6.8888889 | W15: 0.55555556 | X15: 0.88888889 | Y15: 5600
A16: ATR-42-300 | B16: 2T | C16: PW127E | D16: AIA-127B | E16: 103.5 | F16: 1.352706 | G16: 0 | H16: 0.311436 | I16: 0.00706652 | J16: 0.05175 | K16: 326.025 | L16: 6120 | M16: 42.228 | N16: 0 | O16: 56.304 | P16: 1.224 | Q16: 3.06 | R16: 19278
A17: ATR-72-200 | B17: 2T | C17: PW127F | D17: AIA-127B | E17: 103.5 | F17: 1.352706 | G17: 0 | H17: 0.311436 | I17: 0.00706652 | J17: 0.05175 | K17: 326.025 | L17: 6120 | M17: 42.228 | N17: 0 | O17: 56.304 | P17: 1.224 | Q17: 3.06 | R17: 19278
A18: BAe 146-300 | B18: 4J | C18: LF507 | D18: ICAO-1TL004 | E18: 331.2912 | F18: 3.4520351 | G18: 0.065956512 | H18: 0.93079032 | I18: 0.015178097 | J18: 0.1656456 | K18: 1043.5673 | L18: 10872 | M18: 35.66016 | N18: 51.31584 | O18: 411.28776 | P18: 1.516884 | Q18: 5.436 | R18: 34246.8 | S18: 1.7777778 | T18: 15.555556 | U18: 0.66666667 | V18: 6.8888889 | W18: 0.55555556 | X18: 0.88888889 | Y18: 5600
A19: BAe ATP | B19: 2T | C19: PW124 | D19: AIA-127B | E19: 103.5 | F19: 1.352706 | G19: 0 | H19: 0.311436 | I19: 0.00706652 | J19: 0.05175 | K19: 326.025 | L19: 6120 | M19: 42.228 | N19: 0 | O19: 56.304 | P19: 1.224 | Q19: 3.06 | R19: 19278
A20: BAe Jetstream 41 | B20: 2T | C20: TPE331-14GR | D20: FAEED136 | E20: 37.614 | F20: 0.39960564 | G20: 0.14743884 | H20: 0.2413476 | I20: 0.00263352 | J20: 0.018807 | K20: 11.84841 | L20: 1692 | M20: 4.83912 | N20: 133.85412 | O20: 104.058 | P20: 0.3384 | Q20: 0.846 | R20: 532.98
A21: Beech 1900D | B21: 2T | C21: PT6A-67D | D21: AIA-67D | E21: 47.76 | F21: 0.290748 | G21: 0.07623 | H21: 0.593394 | I21: 0.00349332 | J21: 0.02388 | K21: 150.444 | L21: 1800 | M21: 5.58 | N21: 31.68 | O21: 102.24 | P21: 0.36 | Q21: 0.9 | R21: 5670
A22: Beech 300 | B22: 2J | C22: FJ44-2A | D22: LSZH-FJ442A | E22: 27.996 | F22: 0.3215868 | G22: 0.023133 | H22: 0.1810812 | I22: 0.0038255017 | J22: 0.013998 | K22: 88.1874 | L22: 2520 | M22: 6.048 | N22: 5.7456 | O22: 80.892 | P22: 0.16212035 | Q22: 1.26 | R22: 7938 | S22: 1.7777778 | T22: 15.555556 | U22: 0.66666667 | V22: 6.8888889 | W22: 0.55555556 | X22: 0.88888889 | Y22: 5600
A23: Beech Super King 200B | B23: 2T | C23: PT6A-42 | D23: AIA-42 | E23: 45.516 | F23: 0.305871 | G23: 0.032184 | H23: 0.2539674 | I23: 0.003223572 | J23: 0.022758 | K23: 143.3754 | L23: 2160 | M23: 6.912 | N23: 32.184 | O23: 83.592 | P23: 0.432 | Q23: 1.08 | R23: 6804
A24: Beech Super King 350 | B24: 2T | C24: PT6A-60A | D24: AIA-67D | E24: 47.76 | F24: 0.290748 | G24: 0.07623 | H24: 0.593394 | I24: 0.00349332 | J24: 0.02388 | K24: 150.444 | L24: 1800 | M24: 5.58 | N24: 31.68 | O24: 102.24 | P24: 0.36 | Q24: 0.9 | R24: 5670
A25: Beech T-6A Texan | B25: 1T | C25: PT6A-68 | D25: AIA-67D | E25: 47.76 | F25: 0.290748 | G25: 0.07623 | H25: 0.593394 | I25: 0.00349332 | J25: 0.02388 | K25: 150.444 | L25: 1800 | M25: 5.58 | N25: 31.68 | O25: 102.24 | P25: 0.36 | Q25: 0.9 | R25: 5670
A26: Bell 206B | B26: 1H | C26: Allison 250-C20J | D26: LSZH-H650 | E26: 34.95 | F26: 0.1427598 | G26: 0.6153204 | H26: 1.0930386 | I26: 0.00227226 | J26: 0.017475 | K26: 110.0925
A27: Bell 230 | B27: 2H | C27: Allison 250-C30G2 | D27: LSZH-H650 | E27: 69.9 | F27: 0.2855196 | G27: 1.2306408 | H27: 2.1860772 | I27: 0.00454452 | J27: 0.03495 | K27: 220.185
A28: Bell 407/MDD 600N | B28: 1H | C28: Allison 250-C47 | D28: LSZH-H650 | E28: 34.95 | F28: 0.1427598 | G28: 0.6153204 | H28: 1.0930386 | I28: 0.00227226 | J28: 0.017475 | K28: 110.0925
A29: Bell 430 | B29: 2H | C29: Allison 250-C40B | D29: LSZH-H650 | E29: 69.9 | F29: 0.2855196 | G29: 1.2306408 | H29: 2.1860772 | I29: 0.00454452 | J29: 0.03495 | K29: 220.185
A30: Bell AB119 | B30: 2H | C30: PT6C-67C | D30: LSZH-H900 | E30: 114.66 | F30: 0.8468148 | G30: 1.0201152 | H30: 1.3058838 | I30: 0.00738252 | J30: 0.05733 | K30: 361.179
A31: Boeing 717 | B31: 2J | C31: BR715 | D31: ICAO-4BR002 | E31: 381.504 | F31: 6.4583597 | G31: 0.0072384 | H31: 0.82100112 | I31: 0.010983716 | J31: 0.190752 | K31: 1201.7376 | L31: 11520 | M31: 61.8624 | N31: 2.4192 | O31: 187.4304 | P31: 0.63810761 | Q31: 5.76 | R31: 36288 | S31: 1.7777778 | T31: 15.555556 | U31: 0.66666667 | V31: 6.8888889 | W31: 0.55555556 | X31: 0.88888889 | Y31: 5600
A32: Boeing 737 (300-500) | B32: 2J | C32: CFM56-3B1 | D32: ICAO-1CM004 | E32: 441.432 | F32: 5.8560888 | G32: 0.05595936 | H32: 1.2697032 | I32: 0.013520494 | J32: 0.220716 | K32: 1390.5108 | L32: 13680 | M32: 53.352 | N32: 31.1904 | O32: 470.592 | P32: 1.0710359 | Q32: 6.84 | R32: 43092 | S32: 1.7777778 | T32: 15.555556 | U32: 0.66666667 | V32: 6.8888889 | W32: 0.55555556 | X32: 0.88888889 | Y32: 5600
A33: Boeing 737 (600-900) | B33: 2J | C33: CFM56-7B24 | D33: ICAO-3CM032 | E33: 497.652 | F33: 8.8585356 | G33: 0.0824652 | H33: 0.8026608 | I33: 0.027860512 | J33: 0.248826 | K33: 1567.6038 | L33: 13080 | M33: 57.552 | N33: 34.008 | O33: 287.76 | P33: 1.2395989 | Q33: 6.54 | R33: 41202 | S33: 1.7777778 | T33: 15.555556 | U33: 0.66666667 | V33: 6.8888889 | W33: 0.55555556 | X33: 0.88888889 | Y33: 5600
A34: Boeing 747 (400) | B34: 4J | C34: CF6-80C2B4 | D34: ICAO-2GE043 | E34: 2105.832 | F34: 39.258727 | G34: 0.2226564 | H34: 2.319522 | I34: 0.08070063 | J34: 1.052916 | K34: 6633.3708 | L34: 48240 | M34: 225.7632 | N34: 76.7016 | O34: 953.2224 | P34: 2.8350793 | Q34: 24.12 | R34: 151956 | S34: 4 | T34: 32 | U34: 2.1333333 | V34: 2.8 | W34: 0.53333333 | X34: 2 | Y34: 12600
A35: Boeing 757 | B35: 2J | C35: RB211-535C | D35: ICAO-1RR012 | E35: 822.48 | F35: 16.489927 | G35: 0.2407392 | H35: 0.7859976 | I35: 0.040035543 | J35: 0.41124 | K35: 2590.812 | L35: 24000 | M35: 82.56 | N35: 34.56 | O35: 450.96 | P35: 1.7961481 | Q35: 12 | R35: 75600 | S35: 1.7777778 | T35: 15.555556 | U35: 0.66666667 | V35: 6.8888889 | W35: 0.55555556 | X35: 0.88888889 | Y35: 5600
A36: Boeing 767-300 | B36: 2J | C36: CF6-80C2 | D36: ICAO-2GE036 | E36: 1067.748 | F36: 20.205902 | G36: 0.1124058 | H36: 1.1485016 | I36: 0.041364598 | J36: 0.533874 | K36: 3363.4062 | L36: 24120 | M36: 112.8816 | N36: 38.3508 | O36: 476.6112 | P36: 1.4175396 | Q36: 12.06 | R36: 75978 | S36: 4 | T36: 32 | U36: 2.1333333 | V36: 2.8 | W36: 0.53333333 | X36: 2 | Y36: 12600
A37: Boeing 777 | B37: 2J | C37: RR Trent 892 | D37: ICAO-2RR027 | E37: 1662.84 | F37: 48.012708 | G37: 0.02861424 | H37: 0.9997632 | I37: 0.058148729 | J37: 0.83142 | K37: 5237.946 | L37: 36000 | M37: 191.88 | N37: 25.2 | O37: 470.52 | P37: 2.2861386 | Q37: 18 | R37: 113400 | S37: 4 | T37: 32 | U37: 2.1333333 | V37: 2.8 | W37: 0.53333333 | X37: 2 | Y37: 12600
A38: Boeing 787 | B38: 2J | C38: RR Trent 1000 | D38: ICAO | S38: 4 | T38: 32 | U38: 2.1333333 | V38: 2.8 | W38: 0.53333333 | X38: 2 | Y38: 12600
A39: C-130 Hercules | B39: 4T | C39: Allison AE2100 | D39: FOCA-T201 | E39: 282.984 | F39: 2.6284016 | G39: 0.027784728 | H39: 1.0931473 | I39: 0.021129944 | J39: 0.141492 | K39: 891.3996 | L39: 12504 | M39: 30.147144 | N39: 14.217048 | O39: 215.79403 | P39: 2.5008 | Q39: 6.252 | R39: 39387.6
A40: C-27 Spartan | B40: 2T | C40: Allison AE2100 | D40: FOCA-T201 | E40: 141.492 | F40: 1.3142008 | G40: 0.013892364 | H40: 0.54657367 | I40: 0.010564972 | J40: 0.070746 | K40: 445.6998 | L40: 6252 | M40: 15.073572 | N40: 7.108524 | O40: 107.89702 | P40: 1.2504 | Q40: 3.126 | R40: 19693.8
A41: Canadair Challenger | B41: 2J | C41: LF502-L | D41: ICAO-1TL001 | E41: 181.002 | F41: 1.8621863 | G41: 0.050996179 | H41: 0.5235882 | I41: 0.0085913211 | J41: 0.090501 | K41: 570.1563 | L41: 5724 | M41: 19.34712 | N41: 38.0646 | O41: 261.18612 | P41: 0.63797161 | Q41: 2.862 | R41: 18030.6 | S41: 1.7777778 | T41: 15.555556 | U41: 0.66666667 | V41: 6.8888889 | W41: 0.55555556 | X41: 0.88888889 | Y41: 5600
A42: Casa C-212 | B42: 2T | C42: TPE331-12J | D42: FAEED136 | E42: 37.614 | F42: 0.39960564 | G42: 0.14743884 | H42: 0.2413476 | I42: 0.00263352 | J42: 0.018807 | K42: 11.84841 | L42: 1692 | M42: 4.83912 | N42: 133.85412 | O42: 104.058 | P42: 0.3384 | Q42: 0.846 | R42: 532.98
A43: Casa CN-235 | B43: 2T | C43: CT7-9C | D43: FOCA-T053 | E43: 62.184 | F43: 0.667533 | G43: 0.1075266 | H43: 0.75402402 | I43: 0.004571972 | J43: 0.031092 | K43: 195.8796 | L43: 3096 | M43: 8.85456 | N43: 14.33448 | O43: 149.382 | P43: 0.6192 | Q43: 1.548 | R43: 9752.4
A44: Cessna 172 | B44: 1P | C44: IO-360-L2A | D44: FOCA-PF03 | E44: 5.7408 | F44: 0.007717344 | G44: 0.10686761 | H44: 7.606644 | I44: 0.00021196 | J44: 0.0028704 | K44: 18.026112 | L44: 84 | M44: 0.18396 | N44: 4.05804 | O44: 91.959 | P44: 0.0084 | Q44: 0.042 | R44: 263.76
A45: Cessna 182 | B45: 1P | C45: IO-540-AB1A5 | D45: FOCA-PF12 | E45: 7.5546 | F45: 0.0303558 | G45: 0.11660154 | H45: 6.977742 | I45: 0.0001626566 | J45: 0.0037773 | K45: 23.721444 | L45: 150 | M45: 0.15 | N45: 6.84 | O45: 150 | P45: 0.0075 | Q45: 0.075 | R45: 471
A46: Cessna 208B | B46: 1T | C46: PT6A-114D | D46: AIA-112 | E46: 26.472 | F46: 0.105144 | G46: 0.551652 | H46: 0.592296 | I46: 0.00190452 | J46: 0.013236 | K46: 83.3868 | L46: 1512 | M46: 3.024 | N46: 152.712 | O46: 102.816 | P46: 0.3024 | Q46: 0.756 | R46: 4762.8
A47: Cessna 402 | B47: 2P | C47: TSIO-520E | D47: FOCA-PF07 | E47: 25.584 | F47: 0.046104 | G47: 0.335148 | H47: 30.333 | I47: 0.000518332 | J47: 0.012792 | K47: 80.33376 | L47: 732 | M47: 2.59128 | N47: 6.0024 | O47: 338.184 | P47: 0.0366 | Q47: 0.366 | R47: 2298.48
A48: Cessna 525 | B48: 2J | C48: FJ44-1A | D48: LSZH-FJ441A | E48: 19.512 | F48: 0.1669464 | G48: 0.00299544 | H48: 0.174648 | I48: 0.0033528842 | J48: 0.009756 | K48: 61.4628 | L48: 1680 | M48: 3.696 | N48: 2.604 | O48: 76.44 | P48: 0.10144833 | Q48: 0.84 | R48: 5292 | S48: 1.7777778 | T48: 15.555556 | U48: 0.66666667 | V48: 6.8888889 | W48: 0.55555556 | X48: 0.88888889 | Y48: 5600
A49: Cessna 560XL | B49: 2J | C49: PW545A | D49: FOCA-B004 | E49: 38.0796 | F49: 0.19751093 | G49: 0.23317813 | H49: 0.69013943 | I49: 0.016468633 | J49: 0.0190398 | K49: 119.95074 | L49: 3744 | M49: 4.15584 | N49: 99.4032 | O49: 250.96032 | P49: 0.26208 | Q49: 1.872 | R49: 11793.6 | S49: 1.7777778 | T49: 15.555556 | U49: 0.66666667 | V49: 6.8888889 | W49: 0.55555556 | X49: 0.88888889 | Y49: 5600
A50: Cessna 680 | B50: 2J | C50: PW306C | D50: ICAO-7PW078 | E50: 148.1748 | F50: 2.4542312 | G50: 0.02207904 | H50: 0.75195097 | I50: 0.0084257051 | J50: 0.0740874 | K50: 466.75062 | L50: 5064 | M50: 21.57264 | N50: 22.07904 | O50: 184.0764 | P50: 0.57752077 | Q50: 2.532 | R50: 15951.6 | S50: 1.7777778 | T50: 15.555556 | U50: 0.66666667 | V50: 6.8888889 | W50: 0.55555556 | X50: 0.88888889 | Y50: 5600
A51: Cessna 750 | B51: 2J | C51: GMA 3007C | D51: ICAO-8AL025 | E51: 141.7848 | F51: 1.72089 | G51: 0.079746677 | H51: 0.41395541 | I51: 0.0055421235 | J51: 0.0708924 | K51: 446.62212 | L51: 4524 | M51: 15.20064 | N51: 22.407372 | O51: 119.07168 | P51: 0.36029452 | Q51: 2.262 | R51: 14250.6 | S51: 1.7777778 | T51: 15.555556 | U51: 0.66666667 | V51: 6.8888889 | W51: 0.55555556 | X51: 0.88888889 | Y51: 5600
A52: Cessna Citation | B52: 2J | C52: JT15D-1A | D52: ICAO-1PW035 | E52: 27.096 | F52: 0.14287368 | G52: 0.182904 | H52: 0.8057616 | I52: 0.00654852 | J52: 0.013548 | K52: 85.3524 | L52: 2760 | M52: 4.83 | N52: 139.38 | O52: 364.32 | P52: 0.552 | Q52: 1.38 | R52: 8694 | S52: 1.7777778 | T52: 15.555556 | U52: 0.66666667 | V52: 6.8888889 | W52: 0.55555556 | X52: 0.88888889 | Y52: 5600
A53: CH-47 | B53: 2H | C53: T55-714A | D53: FOCA-HF30 | E53: 161.31 | F53: 0.8109714 | G53: 0.1076148 | H53: 1.0661532 | I53: 0.009704492 | J53: 0.080655 | K53: 508.1265
A54: Cirrus SR22 | B54: 1P | C54: IO-550-N | D54: FOCA-PF01 | E54: 9.4836 | F54: 0.051293424 | G54: 0.12103206 | H54: 8.5852392 | I54: 0.0001851926 | J54: 0.0047418 | K54: 29.778504 | L54: 228 | M54: 0.11856 | N54: 9.71736 | O54: 265.25292 | P54: 0.0114 | Q54: 0.114 | R54: 715.92
A55: CL300 | B55: 2J | C55: AS907 | D55: ICAO-1PW035 | E55: 27.096 | F55: 0.1428792 | G55: 0.18289421 | H55: 0.80585952 | I55: 0.00654852 | J55: 0.013548 | K55: 85.3524 | L55: 2760 | M55: 4.83552 | N55: 139.38 | O55: 364.32 | P55: 0.552 | Q55: 1.38 | R55: 8694 | S55: 1.7777778 | T55: 15.555556 | U55: 0.66666667 | V55: 6.8888889 | W55: 0.55555556 | X55: 0.88888889 | Y55: 5600
A56: CL415 | B56: 2T | C56: PW123-AF | D56: AIA-127B | E56: 103.5 | F56: 1.352706 | G56: 0 | H56: 0.311436 | I56: 0.00706652 | J56: 0.05175 | K56: 326.025 | L56: 6120 | M56: 42.228 | N56: 0 | O56: 56.304 | P56: 1.224 | Q56: 3.06 | R56: 19278
A57: CL604 | B57: 2J | C57: CF34-3B1 | D57: ICAO-5GE084 | E57: 181.8756 | F57: 1.6093976 | G57: 0.041110944 | H57: 0.38393652 | I57: 0.010785835 | J57: 0.0909378 | K57: 572.90814 | L57: 5868 | M57: 21.82896 | N57: 27.52092 | O57: 279.25812 | P57: 0.5938627 | Q57: 2.934 | R57: 18484.2 | S57: 1.7777778 | T57: 15.555556 | U57: 0.66666667 | V57: 6.8888889 | W57: 0.55555556 | X57: 0.88888889 | Y57: 5600
A58: CRJ200 | B58: 2J | C58: CF34-3B1 | D58: ICAO-5GE084 | E58: 181.8756 | F58: 1.6093976 | G58: 0.041110944 | H58: 0.38393652 | I58: 0.010785835 | J58: 0.0909378 | K58: 572.90814 | L58: 5868 | M58: 21.82896 | N58: 27.52092 | O58: 279.25812 | P58: 0.5938627 | Q58: 2.934 | R58: 18484.2 | S58: 1.7777778 | T58: 15.555556 | U58: 0.66666667 | V58: 6.8888889 | W58: 0.55555556 | X58: 0.88888889 | Y58: 5600
A59: CRJ700 | B59: 2J | C59: CF34-8C1 | D59: ICAO-5GE083 | E59: 270.139 | F59: 3.3478843 | G59: 0.0091264543 | H59: 0.52720636 | I59: 0.0084174374 | J59: 0.1350695 | K59: 850.93784 | L59: 8276.28 | M59: 35.670767 | N59: 0.6621024 | O59: 206.41042 | P59: 0.40929184 | Q59: 4.13814 | R59: 26070.282 | S59: 1.7777778 | T59: 15.555556 | U59: 0.66666667 | V59: 6.8888889 | W59: 0.55555556 | X59: 0.88888889 | Y59: 5600
A60: CRJ900 | B60: 2J | C60: CF34-8C5 | D60: ICAO-8GE110 | E60: 287.952 | F60: 3.5215661 | G60: 0.01004064 | H60: 0.61905168 | I60: 0.010305269 | J60: 0.143976 | K60: 907.0488 | L60: 7680 | M60: 35.328 | N60: 0.9984 | O60: 140.16 | P60: 0.38217293 | Q60: 3.84 | R60: 24192 | S60: 1.7777778 | T60: 15.555556 | U60: 0.66666667 | V60: 6.8888889 | W60: 0.55555556 | X60: 0.88888889 | Y60: 5600
A61: Dash 7 | B61: 2T | C61: PT6A-50 | D61: AIA-67D | E61: 47.76 | F61: 0.290748 | G61: 0.07623 | H61: 0.593394 | I61: 0.00349332 | J61: 0.02388 | K61: 150.444 | L61: 1800 | M61: 5.58 | N61: 31.68 | O61: 102.24 | P61: 0.36 | Q61: 0.9 | R61: 5670
A62: Dash 8-400 | B62: 2T | C62: PW150 | D62: AIA-127B | E62: 103.5 | F62: 1.352706 | G62: 0 | H62: 0.311436 | I62: 0.00706652 | J62: 0.05175 | K62: 326.025 | L62: 6120 | M62: 42.228 | N62: 0 | O62: 56.304 | P62: 1.224 | Q62: 3.06 | R62: 19278
A63: DHC-6 Twin Otter | B63: 2T | C63: PT6A-27 | D63: AIA-42 | E63: 45.516 | F63: 0.305871 | G63: 0.032184 | H63: 0.2539674 | I63: 0.003223572 | J63: 0.022758 | K63: 143.3754 | L63: 2160 | M63: 6.912 | N63: 32.184 | O63: 83.592 | P63: 0.432 | Q63: 1.08 | R63: 6804
A64: Diamond DA-42 | B64: 2T | C64: TAE (135hp) | D64: FOCA-PF10 | E64: 5.1264 | F64: 0.12345386 | G64: 0.010341 | H64: 0.051880104 | I64: 0.000119852 | J64: 0.0025632 | K64: 16.096896 | L64: 36 | M64: 0.60876 | N64: 0.35208 | O64: 0.8928 | P64: 0.0018 | Q64: 0.018 | R64: 113.04
A65: Dornier 228 | B65: 2T | C65: TPE-331-5 | D65: FAEED136 | E65: 37.614 | F65: 0.39960564 | G65: 0.14743884 | H65: 0.2413476 | I65: 0.00263352 | J65: 0.018807 | K65: 11.84841 | L65: 1692 | M65: 4.83912 | N65: 133.85412 | O65: 104.058 | P65: 0.3384 | Q65: 0.846 | R65: 532.98
A66: Dornier 328 (Jet) | B66: 2J | C66: PW306B | D66: ICAO-7PW078 | E66: 148.1748 | F66: 2.4542312 | G66: 0.02207904 | H66: 0.75195097 | I66: 0.0084257051 | J66: 0.0740874 | K66: 466.75062 | L66: 5064 | M66: 21.57264 | N66: 22.07904 | O66: 184.0764 | P66: 0.57752077 | Q66: 2.532 | R66: 15951.6 | S66: 1.7777778 | T66: 15.555556 | U66: 0.66666667 | V66: 6.8888889 | W66: 0.55555556 | X66: 0.88888889 | Y66: 5600
A67: Dornier 328 (TP) | B67: 2T | C67: PW119B | D67: AIA-119B | E67: 94.512 | F67: 1.1380104 | G67: 0 | H67: 0.3114456 | I67: 0.00622332 | J67: 0.047256 | K67: 297.7128 | L67: 6672 | M67: 48.0384 | N67: 0 | O67: 55.3776 | P67: 1.3344 | Q67: 3.336 | R67: 21016.8
A68: Eclipse 500 | B68: 2J | C68: EJ22 | D68: ICAO-1PW035 | E68: 27.096 | F68: 0.1428792 | G68: 0.18289421 | H68: 0.80585952 | I68: 0.00654852 | J68: 0.013548 | K68: 85.3524 | L68: 2760 | M68: 4.83552 | N68: 139.38 | O68: 364.32 | P68: 0.552 | Q68: 1.38 | R68: 8694
A69: EH 101 | B69: 3H | C69: T700-GE-T6A | D69: FOCA-HF30 | E69: 241.965 | F69: 1.2164571 | G69: 0.1614222 | H69: 1.5992298 | I69: 0.014556738 | J69: 0.1209825 | K69: 762.18975
A70: EMB 120 | B70: 2T | C70: PW118A | D70: AIA-119B | E70: 94.512 | F70: 1.1380104 | G70: 0 | H70: 0.3114456 | I70: 0.00622332 | J70: 0.047256 | K70: 297.7128 | L70: 6672 | M70: 48.0384 | N70: 0 | O70: 55.3776 | P70: 1.3344 | Q70: 3.336 | R70: 21016.8
A71: EMB 135/145 | B71: 2J | C71: AE3007A | D71: ICAO-4AL003 | E71: 176.868 | F71: 2.5632727 | G71: 0.0827346 | H71: 0.386481 | I71: 0.0069050717 | J71: 0.088434 | K71: 557.1342 | L71: 5880 | M71: 22.5204 | N71: 14.7588 | O71: 102.018 | P71: 0.3789466 | Q71: 2.94 | R71: 18522 | S71: 1.7777778 | T71: 15.555556 | U71: 0.66666667 | V71: 6.8888889 | W71: 0.55555556 | X71: 0.88888889 | Y71: 5600
A72: EMB 170 | B72: 2J | C72: CF34-8E | D72: ICAO-8GE113 | E72: 265.764 | F72: 3.0514848 | G72: 0.01166928 | H72: 0.61692036 | I72: 0.0079249754 | J72: 0.132882 | K72: 837.1566 | L72: 7440 | M72: 33.108 | N72: 1.1904 | O72: 148.8744 | P72: 0.37160717 | Q72: 3.72 | R72: 23436 | S72: 1.7777778 | T72: 15.555556 | U72: 0.66666667 | V72: 6.8888889 | W72: 0.55555556 | X72: 0.88888889 | Y72: 5600
A73: EMB 190 | B73: 2J | C73: CF34-10E | D73: ICAO-8GE114 | E73: 350.196 | F73: 4.5897689 | G73: 0.07652304 | H73: 1.0781116 | I73: 0.010669395 | J73: 0.175098 | K73: 1103.1174 | L73: 10080 | M73: 35.8848 | N73: 54.8352 | O73: 512.1648 | P73: 0.87943787 | Q73: 5.04 | R73: 31752 | S73: 1.7777778 | T73: 15.555556 | U73: 0.66666667 | V73: 6.8888889 | W73: 0.55555556 | X73: 0.88888889 | Y73: 5600
A74: EMB 314 | B74: 1T | C74: PT6A-68 | D74: AIA-67D | E74: 47.76 | F74: 0.290748 | G74: 0.07623 | H74: 0.593394 | I74: 0.00349332 | J74: 0.02388 | K74: 150.444 | L74: 1800 | M74: 5.58 | N74: 31.68 | O74: 102.24 | P74: 0.36 | Q74: 0.9 | R74: 5670
A75: EMB Legacy | B75: 2J | C75: AE3007-A1P | D75: ICAO-6AL015 | E75: 175.0416 | F75: 2.693909 | G75: 0.03820032 | H75: 0.26200608 | I75: 0.0041121183 | J75: 0.0875208 | K75: 551.38104 | L75: 5520 | M75: 17.6088 | N75: 27.9312 | O75: 180.3936 | P75: 0.44321478 | Q75: 2.76 | R75: 17388 | S75: 1.7777778 | T75: 15.555556 | U75: 0.66666667 | V75: 6.8888889 | W75: 0.55555556 | X75: 0.88888889 | Y75: 5600
A76: Eurocopter AS332 | B76: 2H | C76: Makila 1A2 | D76: FOCA-HF30 | E76: 161.31 | F76: 0.8109714 | G76: 0.1076148 | H76: 1.0661532 | I76: 0.009704492 | J76: 0.080655 | K76: 508.1265
A77: Eurocopter AS350 | B77: 1H | C77: Arriel 1D1 | D77: LSZH-H650 | E77: 34.95 | F77: 0.1427598 | G77: 0.6153204 | H77: 1.0930386 | I77: 0.00227226 | J77: 0.017475 | K77: 110.0925
A78: Eurocopter AS365 | B78: 2H | C78: Arriel 1C2 | D78: LSZH-H650 | E78: 69.9 | F78: 0.2855196 | G78: 1.2306408 | H78: 2.1860772 | I78: 0.00454452 | J78: 0.03495 | K78: 220.185
A79: Eurocopter EC130/135 | B79: 2H | C79: Arrius 2B | D79: LSZH-H650 | E79: 69.9 | F79: 0.2855196 | G79: 1.2306408 | H79: 2.1860772 | I79: 0.00454452 | J79: 0.03495 | K79: 220.185
A80: Eurocopter EC145/155 | B80: 2H | C80: Arrius 2C | D80: LSZH-H650 | E80: 69.9 | F80: 0.2855196 | G80: 1.2306408 | H80: 2.1860772 | I80: 0.00454452 | J80: 0.03495 | K80: 220.185
A81: Falcon 2000 | B81: 2J | C81: CFE738-1-1B/TFE731-3 | D81: ICAO-1AS002 | E81: 38.904 | F81: 0.49287168 | G81: 0.04916976 | H81: 0.39420864 | I81: 0.00989292 | J81: 0.019452 | K81: 122.5476 | L81: 3120 | M81: 11.6064 | N81: 28.2048 | O81: 148.824 | P81: 0.624 | Q81: 1.56 | R81: 9828 | S81: 1.7777778 | T81: 15.555556 | U81: 0.66666667 | V81: 6.8888889 | W81: 0.55555556 | X81: 0.88888889 | Y81: 5600
A82: Falcon 50 | B82: 2J | C82: TFE731-40 | D82: ICAO-1AS002 | E82: 38.904 | F82: 0.49287168 | G82: 0.04916976 | H82: 0.39420864 | I82: 0.00989292 | J82: 0.019452 | K82: 122.5476 | L82: 3120 | M82: 11.6064 | N82: 28.2048 | O82: 148.824 | P82: 0.624 | Q82: 1.56 | R82: 9828 | S82: 1.7777778 | T82: 15.555556 | U82: 0.66666667 | V82: 6.8888889 | W82: 0.55555556 | X82: 0.88888889 | Y82: 5600
A83: Falcon 900EX | B83: 3J | C83: TFE731-60 | D83: ICAO-1AS002 | E83: 38.904 | F83: 0.49287168 | G83: 0.04916976 | H83: 0.39420864 | I83: 0.00989292 | J83: 0.019452 | K83: 122.5476 | L83: 3120 | M83: 11.6064 | N83: 28.2048 | O83: 148.824 | P83: 0.624 | Q83: 1.56 | R83: 9828 | S83: 1.7777778 | T83: 15.555556 | U83: 0.66666667 | V83: 6.8888889 | W83: 0.55555556 | X83: 0.88888889 | Y83: 5600
A84: Fokker F100 | B84: 2J | C84: Tay 620-15 | D84: ICAO-1RR020 | E84: 353.76 | F84: 4.80348 | G84: 0.245208 | H84: 0.926424 | I84: 0.089125904 | J84: 0.17688 | K84: 1114.344 | L84: 13200 | M84: 33 | N84: 44.88 | O84: 318.12 | P84: 3.9037912 | Q84: 6.6 | R84: 41580 | S84: 1.7777778 | T84: 15.555556 | U84: 0.66666667 | V84: 6.8888889 | W84: 0.55555556 | X84: 0.88888889 | Y84: 5600
A85: Fokker F27 | B85: 2T | C85: RR Dart 528 | D85: FAEED226 | E85: 107.94 | F85: 0.3156612 | G85: 0.3426336 | H85: 2.2298064 | I85: 0.008072572 | J85: 0.05397 | K85: 340.011 | L85: 6204 | M85: 4.3428 | N85: 148.2756 | O85: 567.0456 | P85: 1.2408 | Q85: 3.102 | R85: 19542.6
A86: Fokker F28 | B86: 2J | C86: Spey 555-15 | D86: ICAO-4RR035 | E86: 335.94 | F86: 3.676024 | G86: 0.11815572 | H86: 1.394309 | I86: 0.058223205 | J86: 0.16797 | K86: 1058.211 | L86: 11568 | M86: 25.79664 | N86: 39.44688 | O86: 360.45888 | P86: 2.6449633 | Q86: 5.784 | R86: 36439.2 | S86: 1.7777778 | T86: 15.555556 | U86: 0.66666667 | V86: 6.8888889 | W86: 0.55555556 | X86: 0.88888889 | Y86: 5600
A87: Fokker F50 | B87: 2T | C87: PW125B | D87: AIA-127B | E87: 103.5 | F87: 1.352706 | G87: 0 | H87: 0.311436 | I87: 0.00706652 | J87: 0.05175 | K87: 326.025 | L87: 6120 | M87: 42.228 | N87: 0 | O87: 56.304 | P87: 1.224 | Q87: 3.06 | R87: 19278
A88: Fokker F70 | B88: 2J | C88: Tay 620-15 | D88: ICAO-1RR020 | E88: 353.76 | F88: 4.80348 | G88: 0.245208 | H88: 0.926424 | I88: 0.089125904 | J88: 0.17688 | K88: 1114.344 | L88: 13200 | M88: 33 | N88: 44.88 | O88: 318.12 | P88: 3.9037912 | Q88: 6.6 | R88: 41580 | S88: 1.7777778 | T88: 15.555556 | U88: 0.66666667 | V88: 6.8888889 | W88: 0.55555556 | X88: 0.88888889 | Y88: 5600
A89: Galaxy | B89: 2J | C89: PW306A | D89: ICAO-7PW077 | E89: 148.1748 | F89: 2.4542312 | G89: 0.02207904 | H89: 0.75195097 | I89: 0.0084257051 | J89: 0.0740874 | K89: 466.75062 | L89: 5064 | M89: 21.57264 | N89: 22.07904 | O89: 184.0764 | P89: 0.57752077 | Q89: 2.532 | R89: 15951.6 | S89: 1.7777778 | T89: 15.555556 | U89: 0.66666667 | V89: 6.8888889 | W89: 0.55555556 | X89: 0.88888889 | Y89: 5600
A90: GLEX | B90: 2J | C90: BR710-48 | D90: ICAO-4BR009 | E90: 330.456 | F90: 4.3220009 | G90: 0.02143872 | H90: 1.0015826 | I90: 0.017770283 | J90: 0.165228 | K90: 1040.9364 | L90: 10680 | M90: 49.8756 | N90: 11.9616 | O90: 299.04 | P90: 0.627489 | Q90: 5.34 | R90: 33642 | S90: 1.7777778 | T90: 15.555556 | U90: 0.66666667 | V90: 6.8888889 | W90: 0.55555556 | X90: 0.88888889 | Y90: 5600
A91: Global 5000 | B91: 2J | C91: BR710-48A2 | D91: ICAO-4BR009 | E91: 330.456 | F91: 4.3220009 | G91: 0.02143872 | H91: 1.0015826 | I91: 0.017770283 | J91: 0.165228 | K91: 1040.9364 | L91: 10680 | M91: 49.8756 | N91: 11.9616 | O91: 299.04 | P91: 0.627489 | Q91: 5.34 | R91: 33642 | S91: 1.7777778 | T91: 15.555556 | U91: 0.66666667 | V91: 6.8888889 | W91: 0.55555556 | X91: 0.88888889 | Y91: 5600
A92: Gulfstream G200 | B92: 2J | C92: PW306A | D92: ICAO-7PW077 | E92: 148.1748 | F92: 2.4542312 | G92: 0.02207904 | H92: 0.75195097 | I92: 0.0084257051 | J92: 0.0740874 | K92: 466.75062 | L92: 5064 | M92: 21.57264 | N92: 22.07904 | O92: 184.0764 | P92: 0.57752077 | Q92: 2.532 | R92: 15951.6 | S92: 1.7777778 | T92: 15.555556 | U92: 0.66666667 | V92: 6.8888889 | W92: 0.55555556 | X92: 0.88888889 | Y92: 5600
A93: Gulfstream V | B93: 2J | C93: BR710-48 | D93: ICAO-4BR009 | E93: 330.456 | F93: 4.3220009 | G93: 0.02143872 | H93: 1.0015826 | I93: 0.017770283 | J93: 0.165228 | K93: 1040.9364 | L93: 10680 | M93: 49.8756 | N93: 11.9616 | O93: 299.04 | P93: 0.627489 | Q93: 5.34 | R93: 33642 | S93: 1.7777778 | T93: 15.555556 | U93: 0.66666667 | V93: 6.8888889 | W93: 0.55555556 | X93: 0.88888889 | Y93: 5600
A94: Hawker 800 | B94: 2J | C94: TFE731-5BR | D94: ICAO-1AS002 | E94: 38.904 | F94: 0.49287168 | G94: 0.04916976 | H94: 0.39420864 | I94: 0.00989292 | J94: 0.019452 | K94: 122.5476 | L94: 3120 | M94: 11.6064 | N94: 28.2048 | O94: 148.824 | P94: 0.624 | Q94: 1.56 | R94: 9828 | S94: 1.7777778 | T94: 15.555556 | U94: 0.66666667 | V94: 6.8888889 | W94: 0.55555556 | X94: 0.88888889 | Y94: 5600
A95: Hawker Horizon | B95: 2J | C95: PW308A | D95: ICAO-7PW079 | E95: 173.856 | F95: 2.1125008 | G95: 0.0365364 | H95: 0.55473103 | I95: 0.031869719 | J95: 0.086928 | K95: 547.6464 | L95: 5340 | M95: 19.491 | N95: 35.3508 | O95: 204.0414 | P95: 1.4845714 | Q95: 2.67 | R95: 16821 | S95: 1.7777778 | T95: 15.555556 | U95: 0.66666667 | V95: 6.8888889 | W95: 0.55555556 | X95: 0.88888889 | Y95: 5600
A96: HS125-700 | B96: 2J | C96: TFE731-3 | D96: ICAO-1AS002 | E96: 38.904 | F96: 0.49287168 | G96: 0.04916976 | H96: 0.39420864 | I96: 0.00989292 | J96: 0.019452 | K96: 122.5476 | L96: 3120 | M96: 11.6064 | N96: 28.2048 | O96: 148.824 | P96: 0.624 | Q96: 1.56 | R96: 9828 | S96: 1.7777778 | T96: 15.555556 | U96: 0.66666667 | V96: 6.8888889 | W96: 0.55555556 | X96: 0.88888889 | Y96: 5600
A97: IL76 | B97: 4J | C97: PS-90A | D97: ICAO-1AA005 | E97: 1559.88 | F97: 40.397184 | G97: 0.2324304 | H97: 1.1217444 | I97: 0.32617332 | J97: 0.77994 | K97: 4913.622 | L97: 42720 | M97: 247.776 | N97: 12.816 | O97: 294.768 | P97: 10.031221 | Q97: 21.36 | R97: 134568 | S97: 4 | T97: 32 | U97: 2.1333333 | V97: 2.8 | W97: 0.53333333 | X97: 2 | Y97: 12600
A98: Learjet 45 | B98: 2J | C98: TEF331-20 | D98: ICAO-1AS001 | E98: 35.964 | F98: 0.3698496 | G98: 0.11496624 | H98: 0.49141332 | I98: 0.00909892 | J98: 0.017982 | K98: 113.2866 | L98: 2880 | M98: 8.1216 | N98: 57.7152 | O98: 168.768 | P98: 0.576 | Q98: 1.44 | R98: 9072 | S98: 1.7777778 | T98: 15.555556 | U98: 0.66666667 | V98: 6.8888889 | W98: 0.55555556 | X98: 0.88888889 | Y98: 5600
A99: Learjet 60 | B99: 2J | C99: PW305A | D99: PW-305 | E99: 45.048 | F99: 0.52581768 | G99: 0.03015384 | H99: 0.4125468 | I99: 0.01126532 | J99: 0.022524 | K99: 141.9012 | L99: 4080 | M99: 17.748 | N99: 21.0936 | O99: 185.1504 | P99: 0.816 | Q99: 2.04 | R99: 12852 | S99: 1.7777778 | T99: 15.555556 | U99: 0.66666667 | V99: 6.8888889 | W99: 0.55555556 | X99: 0.88888889 | Y99: 5600
A100: MBB BK117 | B100: 2H | C100: LTS101-750B-1 | D100: LSZH-H650 | E100: 69.9 | F100: 0.2855196 | G100: 1.2306408 | H100: 2.1860772 | I100: 0.00454452 | J100: 0.03495 | K100: 220.185
...

Sheet Stat
A1: Data: Emission Factors for Stationary Sources and Others
A2: Emission source | B2: Carburant | C2: Data Source/Reference | D2: Input metric | E2: Conversion unit | F2: Conversion value | G2: EI units | H2: EI NOx | I2: EI VOC | J2: EI CO | K2: EI PM | L2: EI CO2 | M2: EI SOx | N2: Extra comment
A3: Stationary sources
A4: Building Heating (50kW-1MW) | B4: Coal | C4: CORINAIR, 2009, 1.A.4.a.i | D4: kg coal | E4: MJ/kg carburant | F4: 28.1 | G4: g/GJ | H4: 160 | I4: 200 | J4: 2000 | K4: 190 | L4: 94000 | M4: 900
A5: Building Heating (50kW-1MW) | B5: Natural Gas | C5: CORINAIR, 2009, 1.A.4.a.i | D5: kg natural gas | E5: MJ/kg carburant | F5: 46.5 | G5: g/GJ | H5: 70 | I5: 3 | J5: 30 | K5: 0.5 | L5: 55000 | M5: 0.5
A6: Building Heating | B6: Light Oil | C6: CORINAIR, 2009, 1.A.4.a.i | D6: kg light/gas oil | E6: MJ/kg carburant | F6: 42.6 | G6: g/GJ | H6: 398 | I6: 0.19 | J6: 1.49 | K6: 3 | L6: 73700 | M6: 46.1
A7: Emergency Generator | B7: Diesel | C7: CORINAIR, 1990 | D7: kg diesel | E7: MJ/kg carburant | F7: 42.7 | G7: g/GJ | H7: 1400 | I7: 70 | J7: 210 | K7: 30 | L7: 73000 | M7: 65
A8: Fire training | B8: Kerosene | C8: US FAA (EDMS 4.2, App. H) | D8: kg kerosene | G8: g/kg | H8: 5.04 | I8: 20.22 | J8: 672.08 | K8: 151.88 | L8: 3150 | M8: 1.02
A9: Fire training | B9: Propane | C9: US FAA (EDMS 4.2, App. H) | D9: kg propane | G9: g/kg | H9: 1.32 | I9: 6.57 | J9: 7.19 | K9: 24.21 | L9: 3030 | M9: 0
A10: Fire training | B10: Wood | C10: http://www.atmos-chem-phys-discuss.net/10/27523/2010/acpd-10-27523-2010-print.pdf | D10: kg wood | G10: g/kg | H10: 1.72 | I10: 4.98 | J10: 104 | K10: 18.8 | L10: 1598 | M10: 0
A12: Vehicles landside
A13: Passenger Cars | B13: Gasoline | C13: CORINAIR, 2009, 1.A.3.b | D13: km estimate | E13: g fuel/km | F13: 70 | G13: g/kg | H13: 14.5 | I13: 14 | J13: 132 | K13: 0.037 | L13: 3180 | M13: 0.04
A14: Passenger Cars | B14: Diesel | C14: CORINAIR, 2009, 1.A.3.b | D14: km estimate | E14: g fuel/km | F14: 60 | G14: g/kg | H14: 11 | I14: 1.1 | J14: 4.7 | K14: 1.7 | L14: 3140 | M14: 0.008
A15: Passenger Cars | B15: LPG | C15: CORINAIR, 2009, 1.A.3.b | D15: km estimate | E15: g fuel/km | F15: 57.5 | G15: g/kg | H15: 15.5 | I15: 10 | J15: 68 | K15: 0 | L15: 3017 | M15: 0
A16: LDV | B16: Gasoline | C16: CORINAIR, 2009, 1.A.3.b | D16: km estimate | E16: g fuel/km | F16: 100 | G16: g/kg | H16: 24 | I16: 14 | J16: 155 | K16: 0.03 | L16: 3180 | M16: 0.04
A17: LDV | B17: Diesel | C17: CORINAIR, 2009, 1.A.3.b | D17: km estimate | E17: g fuel/km | F17: 80 | G17: g/kg | H17: 15 | I17: 1.75 | J17: 11 | K17: 2.8 | L17: 3140 | M17: 0.008
A18: HDV | B18: Diesel | C18: CORINAIR, 2009, 1.A.3.b | D18: km estimate | E18: g fuel/km | F18: 240 | G18: g/kg | H18: 37 | I18: 1.6 | J18: 8 | K18: 1.2 | L18: 3140 | M18: 0.008
A19: HDV | B19: CNG | C19: CORINAIR, 2009, 1.A.3.b | D19: km estimate | E19: g fuel/km | F19: 500 | G19: g/kg | H19: 13 | I19: 0.26 | J19: 5.7 | K19: 0.02 | L19: 2750 | M19: 0.008
A20: Motorbikes | B20: Gasoline | C20: CORINAIR, 2009, 1.A.3.b | D20: km estimate | E20: g fuel/km | F20: 35 | G20: g/kg | H20: 9.5 | I20: 114 | J20: 490 | K20: 2.7 | L20: 3180 | M20: 0.04
A21: HDV | B21: Gasoline | C21: CORINAIR, 2009, 1.A.3.b | D21: km estimate | E21: g fuel/km | F21: 177 | G21: g/kg | H21: =6.6/($F$21/1000) -> 37.288136 | I21: =5.25/($F$21/1000) -> 29.661017 | J21: =59.5/($F$21/1000) -> 336.15819 | K21: =0/($F$21/1000) -> 0 | L21: 3180 | M21: 0.04 | N21: NOX, VOC, CO, PM: Table3-19, 20
A23: Passenger Cars | B23: CNG | C23: Swiss EPA, 2010 (Nr.102, table 22) | D23: km estimate | G23: g/km | H23: 0.056 | I23: 0.015 | J23: 0.395 | K23: 0.002 | L23: 148 | M23: 0
A25: Vehicles/machinery airside
A26: Offroad machinery | B26: Diesel | C26: Swiss Offroad Database, 2000 | D26: kg diesel | G26: g/kg | H26: 36.71 | I26: 21.24 | J26: 151.37 | K26: 3.1 | L26: 3150 | M26: 0.54
A29: Older or alternative emission factors
A30: Building Heating | B30: Coke | C30: CORINAIR, 1990 | D30: kg coke | E30: MJ/kg carburant | F30: 28.05 | G30: g/GJ | H30: 200 | I30: 18 | J30: 178 | K30: 64 | L30: 98000 | M30: 500
A31: Building Heating | B31: Light Oil | C31: CORINAIR, 1990 | D31: kg light oil | E31: MJ/kg carburant | F31: 41 | G31: g/GJ | H31: 133 | I31: 8 | J31: 15 | K31: 24 | L31: 76000 | M31: 440
A32: Fire training | B32: Wood | C32: CORINAIR | D32: kg wood | E32: MJ/kg carburant | F32: 14.5 | G32: g/GJ | H32: 140 | I32: 28 | J32: 650 | K32: 80 | L32: 0 | M32: 0
A33: Fire training | B33: Wood | C33: AP-42, 2.5 | D33: kg forest residues | G33: g/kg | H33: 2000 | I33: 11.8 | J33: 70 | K33: 8 | L33: 0 | M33: 0
A34: Fire training | B34: Wood | C34: USDA-FS, 2003 | D34: kg pine pile | G34: g/kg | H34: 0.1 | I34: 11.8 | J34: 86.2 | K34: 12.7 | L34: 1634 | M34: 0
A36: Airside circulating cars | B36: All types | C36: HBEFA 2.1 (Swiss EPA), 2010 | D36: km estimate | G36: g/km | H36: 0.188 | I36: 0.046 | J36: 0.659 | K36: 0.005 | M36: 0.001 | N36: Swiss average, all fuel types, low speed
A37: Airside circulating light duty vehicles | B37: All types | C37: HBEFA 2.1 (Swiss EPA), 2010 | D37: km estimate | G37: g/km | H37: 0.642 | I37: 0.123 | J37: 1.218 | K37: 0.039 | M37: 0.001 | N37: Swiss average, all fuel types, low speed
A38: Airside circulating heavy duty vehicles | B38: All types | C38: HBEFA 2.1 (Swiss EPA), 2010 | D38: km estimate | G38: g/km | H38: 10.195 | I38: 1.09 | J38: 2.93 | K38: 0.288 | M38: 0.007 | N38: Swiss average, all fuel types, low speed
A42: Engine Runups
A43: Aircraft with aviation gasoline | B43: AVGAS | C43: 10min-idle-C182 | G43: kg/runup | H43: 0.0015 | I43: 0.0684 | J43: 1.5 | K43: 7.5e-05 | L43: 4.71 | M43: 0.00075
A44: Single-aisle aircraft with kerosene | B44: Jet-A1 | C44: 30min-idle-B737 | G44: kg/runup | H44: 4.3 | I44: 1.02024 | J44: 7 | K44: 0.037187967 | L44: 1236.06 | M44: 0.1962
A45: Double-aisle aircraft with kerosene | B45: Jet-A1 | C45: 30min-idle-A330 | G45: kg/runup | H45: 6.8 | I45: 0.73584 | J45: 9.04176 | K45: 0.038468934 | L45: 1575 | M45: 0.25
A47: Train emission factors | H47: EI MJ | I47: EI kWh/km
A48: Energy use per light rail wagon | B48: Electricity | C48: Murdoch Univ, Murdoch, WA, AU, 1995 | D48: km | E48: kWh/MJ | F48: 0.2778 | G48: MJ/km | H48: 15.3 | I48: =F48*H48 -> 4.25034
A49: Energy use per suburban rail wagon | B49: Electricity | C49: Murdoch Univ, Murdoch, WA, AU, 1995 | D49: km | E49: kWh/MJ | F49: 0.2778 | G49: MJ/km | H49: 49 | I49: =F49*H49 -> 13.6122
A50: Energy user per light rail pass.-km | B50: Electricity | C50: Murdoch Univ, Murdoch, WA, AU, 1995 | E50: kWh/MJ | F50: 0.2778 | G50: MJ/pkm | H50: 0.5
A51: Energy use per suburban rail pass.-km | B51: Electricity | C51: Murdoch Univ, Murdoch, WA, AU, 1995 | E51: kWh/MJ | F51: 0.2778 | G51: MJ/pkm | H51: 0.9
A53: Drop-down selection landside traffic access distances
A54: Q 3.11 | B54: How I chose the vehicle travel distance?
B55: Default 15 km (not recommended)
B56: Distance from airport to city centre (recommended)
B57: Radius of circle covering 80-90% of city (2nd recommend'n)
B58: Survey data
B59: Best estimate
A61: Q3.11 2 d) Trains | B61: How I chose train distance?
B62: Not applicable
B63: Default distances (not recommended)
B64: Distance from airport to city centre
B65: Distance from airport to next train stations (recommended)
B66: Survey data incl passenger travel distances
B67: Best estimate
