Workbook
Name Disability_Type: options!$A$7:$A$20
Name dist: data!$A$2:$A$616
Name Inclusion: options!$A$32:$A$34
Name Options: options!$A$2:$A$4
Name Placement: options!$A$23:$A$29

Sheet SF-6 Form per Capita
O4: =NOW() -> 41283.613
L9: Quality School Choice and Funding
L10: Finance Program Services
L11: SF-6
L12: School Age Form
L13: for Per Capita Calculation
L14: Report To Certify the Excess Cost For School District School-Age Pupils
L15: Who Were Provided Special Education and Related Services
L16: To be filed by educating district (3323.14 O.R.C.) for school year 2011-12
C18: Section I.
E19: Educating District - City, Exempted Village or Local
F20: Please select a district.
C23: Section II. Salaries, Benefits, and General Student Costs (General Fund) | N23: Actual Costs | O23: Students with disabilities (excluding speech 05) counted in EFM ADM | P23: Cost per FTE (Column N/ Column O)
D24: 1. | E24: Special Education Salaries and Benefits
D25: A. | E25: Special Education teacher salaries and benefits by district (Functions 1220, 1230 and 1240 and objects 11x, 12x, 131, 21x, 24x, 261)) | N25: =IF(F$20<>"Please select a district.",VLOOKUP(F$20,data!A$3:Q$616,5,FALSE),"") | O25: =IF(F$20<>"Please select a district.",VLOOKUP(F$20,data!A$3:Q$616,4,FALSE),"") | P25: =IF(F$20<>"Please select a district.",N25/O25,"")
D26: 2. | E26: Instructional Salaries and Benefits by districts | N26: Reported Costs | O26: EFM ADM | P26: Cost per FTE (Column N/ Column O)
E27: Teacher salaries and benefits by district (functions 11xx, objects 11x, 12x, 131, 21x, 24x, 261)) | N27: =IF(F$20<>"Please select a district.",VLOOKUP(F$20,data!A$3:Q$616,6,FALSE),"") | O27: =IF(F$20<>"Please select a district.",VLOOKUP(F$20,data!A$3:Q$616,17,FALSE),"") | P27: =IF(F$20<>"Please select a district.",N27/O27,"")
C28: Section III. General Student Costs (General Fund) | N28: Reported Costs | O28: EFM ADM | P28: Cost per FTE (Column N/ Column O)
D29: 3. Instructional Supplies and Materials By District
D30: Instructional Supplies and Materials (Func 1XXX - Obj 5XX) | N30: =IF(F$20<>"Please select a district.",VLOOKUP(F$20,data!A$3:Q$616,7,FALSE),"") | O30: =IF(F$20<>"Please select a district.",VLOOKUP(F$20,data!A$3:Q$616,17,FALSE),"") | P30: =IF(F$20<>"Please select a district.",N30/O30,"")
D31: 4. Instructional Equipment
D32: Instructional Equipment (Func 1XXX - Obj 6XX, Obj 7XX) | N32: =IF(F$20<>"Please select a district.",VLOOKUP(F$20,data!A$3:Q$616,8,FALSE),"") | O32: =IF(F$20<>"Please select a district.",VLOOKUP(F$20,data!A$3:Q$616,17,FALSE),"") | P32: =IF(F$20<>"Please select a district.",N32/O32,"")
D33: 5. Administration Costs - By District from EFM Report | N33: =IF(F$20<>"Please select a district.",VLOOKUP(F$20,data!A$3:Q$616,9,FALSE),"") | O33: =IF(F$20<>"Please select a district.",VLOOKUP(F$20,data!A$3:Q$616,17,FALSE),"") | P33: =IF(F$20<>"Please select a district.",N33/O33,"")
D34: 6. Operations Support Costs - By District from EFM Report | N34: =IF(F$20<>"Please select a district.",VLOOKUP(F$20,data!A$3:Q$616,10,FALSE),"") | O34: =IF(F$20<>"Please select a district.",VLOOKUP(F$20,data!A$3:Q$616,17,FALSE),"") | P34: =IF(F$20<>"Please select a district.",N34/O34,"")
D35: 7. Staff Support Costs - By District from EFM Report | N35: =IF(F$20<>"Please select a district.",VLOOKUP(F$20,data!A$3:Q$616,11,FALSE),"") | O35: =IF(F$20<>"Please select a district.",VLOOKUP(F$20,data!A$3:Q$616,17,FALSE),"") | P35: =IF(F$20<>"Please select a district.",N35/O35,"")
D36: 8. Pupil Support Costs - By District from EFM Report | N36: =IF(F$20<>"Please select a district.",VLOOKUP(F$20,data!A$3:Q$616,12,FALSE),"") | O36: =IF(F$20<>"Please select a district.",VLOOKUP(F$20,data!A$3:Q$616,17,FALSE),"") | P36: =IF(F$20<>"Please select a district.",N36/O36,"")
C38: Section V. Totals
D39: 9. | E39: Total Cost per FTE | P39: =IF(F$20<>"Please select a district.",SUM(P30:P36,P27,P25),"")
D45: City, Exempted Village or Local Superintendent Signature | M45: Treasurer Signature

Sheet SF-6 Form Specific Student
P1: =NOW() -> 41283.613
L6: Quality School Choice and Funding
L7: Finance Program Services
L8: SF-6
L9: School Age Form
L10: for Specific Student Calculation
L11: Report To Certify the Excess Cost For School District School-Age Pupils
L12: Who Were Provided Special Education and Related Services
L13: To be filed by educating district (3323.14 O.R.C.) for school year 2011-12
C15: Please make selections and type data only in those cells highlighted in blue.
C16: Section I.
D17: A. | E17: Educating District - City, Exempted Village or Local
F18: Please select a district.
D20: B. | E20: Resident District - City, Exempted Village or Local
F21: Please select a district.
D23: C. | E23: Student disability condition
F24: Please select a disability condition.
D26: D. | E26: Method of placement (EMIS status code).
F27: Please select a placement explanation.
D29: E. | E29: Percent of time in regular classroom (0 to 100)
F30: 0 | H30: %
C32: Section II. Salaries, Benefits, and General Student Costs (General Fund) | N32: Actual Costs | O32: Served student FTE by Disability | P32: FTE Percent | Q32: Cost per FTE (Column N/ Column O*Column P)
D33: 1. | E33: Special Education Salaries and Benefits
D34: A. | E34: Specific teacher(s) salary | P34: =IF(AND(F$18<>"Please select a district.",F30=100),1,IF(AND(F$18<>"Please select a district.",F$30<>100),(100-F30)/100,"")) | Q34: =IF(AND(O34<>"",F$18<>"Please select a district."),(N34/O34)*P34,"")
E35: Specific teacher(s) benefits | O35: =IF(AND(F18<>"Please select a district.",O34<>""),O34,"") | P35: =IF(AND(F$18<>"Please select a district.",F30=100),1,IF(AND(F$18<>"Please select a district.",F$30<>100),(100-F30)/100,"")) | Q35: =IF(AND(O35<>"",F$18<>"Please select a district."),(N35/O35)*P35,"")
D36: 2. | E36: Instructional Salaries and Benefits by districts | O36: EFM ADM
E37: Teacher salaries and benefits by district (functions 11xx, objects 11x, 12x, 131, 21x, 24x, 261)) | N37: =IF(AND(N50="",F$18<>"Please select a district."),VLOOKUP(F$18,data!A$3:Q$616,6,FALSE),"") | O37: =IF(F$18<>"Please select a district.",VLOOKUP(F$18,data!A$3:Q$616,17,FALSE),"") | P37: =IF(F18<>"Please select a district.",F$30/100,"") | Q37: =IF(AND(F$18<>"Please select a district.", P37<>0),(N37/O37)*P37,"")
C38: Section III. General Student Costs (General Fund) | N38: Reported Costs | O38: EFM ADM | Q38: Cost per FTE (Column N/ Column O)
D39: 3. Instructional Supplies and Materials By District
D40: Instructional Supplies and Materials (Func 1XXX - Obj 5XX) | N40: =IF(AND(N50="",F$18<>"Please select a district."),VLOOKUP(F$18,data!A$3:Q$616,7,FALSE),"") | O40: =IF(F$18<>"Please select a district.",VLOOKUP(F$18,data!A$3:Q$616,17,FALSE),"") | Q40: =IF(AND(F$18<>"Please select a district.",N40<>""),N40/O40,"")
D41: 4. Instructional Equipment
D42: Instructional Equipment (Func 1XXX - Obj 6XX, Obj 7XX) | N42: =IF(AND(N50="",F$18<>"Please select a district."),VLOOKUP(F$18,data!A$3:Q$616,8,FALSE),"") | O42: =IF(F$18<>"Please select a district.",VLOOKUP(F$18,data!A$3:Q$616,17,FALSE),"") | Q42: =IF(AND(F$18<>"Please select a district.",N42<>""),N42/O42,"")
D43: 5. Administration Costs - By District from EFM Report | N43: =IF(F$18<>"Please select a district.",VLOOKUP(F$18,data!A$3:Q$616,9,FALSE),"") | O43: =IF(F$18<>"Please select a district.",VLOOKUP(F$18,data!A$3:Q$616,17,FALSE),"") | Q43: =IF(AND(F$18<>"Please select a district.",N43<>""),N43/O43,"")
D44: 6. Operations Support Costs - By District from EFM Report | N44: =IF(AND(N50="",F$18<>"Please select a district."),VLOOKUP(F$18,data!A$3:Q$616,10,FALSE),"") | O44: =IF(F$18<>"Please select a district.",VLOOKUP(F$18,data!A$3:Q$616,17,FALSE),"") | Q44: =IF(AND(N44<>"",F$18<>"Please select a district."),N44/O44,"")
D45: 7. Staff Support Costs - By District from EFM Report | N45: =IF(AND(N50="",F$18<>"Please select a district."),VLOOKUP(F$18,data!A$3:Q$616,11,FALSE),"") | O45: =IF(F$18<>"Please select a district.",VLOOKUP(F$18,data!A$3:Q$616,17,FALSE),"") | Q45: =IF(AND(N45<>"",F$18<>"Please select a district."),N45/O45,"")
D46: 8. Pupil Support Costs - By District from EFM Report | N46: =IF(AND(N50="",F$18<>"Please select a district."),VLOOKUP(F$18,data!A$3:Q$616,12,FALSE),"") | O46: =IF(F$18<>"Please select a district.",VLOOKUP(F$18,data!A$3:Q$616,17,FALSE),"") | Q46: =IF(AND(N46<>"",F$18<>"Please select a district."),N46/O46,"")
C48: Section IV. Specific Student Costs and Related Services (General Fund). Completing these fields will replace some items automatically calculated above. | N48: Actual Costs | O48: Served student FTE by Disability | Q48: Cost per FTE (Column N/ Column O)
D49: 9. Provide itemized costs directly tied to a specific student(s).
D50: A. | E50: Contract services (include this item instead of Lines 3,4, 6, 7, and 8 above) | Q50: =IF(AND(F$18<>"Please select a district.",O50<>""),N50/O50,"")
D51: B. | E51: Supplies for specific students | Q51: =IF(AND(F$18<>"Please select a district.",O51<>""),N51/O51,"")
D52: C. | E52: Equipment for specific students | Q52: =IF(AND(F$18<>"Please select a district.",O52<>""),N52/O52,"")
D53: D. | E53: Special transportation cost required by IEP | Q53: =IF(AND(F$18<>"Please select a district.",O53<>""),N53/O53,"")
D54: E. | E54: Aide | Q54: =IF(AND(F$18<>"Please select a district.",O54<>""),N54/O54,"")
D55: F. | E55: Related services (complete worksheet) | Q55: =IF(AND(F$18<>"Please select a district.",O55<>""),N55/O55,"")
C57: Section V. Totals
D58: 10. | E58: Total Salaries and Benefits (Section II) | Q58: =IF(F18<>"Please select a district.",SUM(Q34:Q35,Q37),"")
D59: 11. | E59: Total General Student Costs (Section III) | Q59: =IF(F18<>"Please select a district.",SUM(Q40,Q42:Q46),"")
D60: 12. | E60: Total Specific Students Costs (Section IV) | Q60: =IF(F18<>"Please select a district.",SUM(Q50:Q55),"")
D61: 14. | E61: Total Costs | Q61: =IF(F18<>"Please select a district.",SUM(Q58:Q60),"")
D67: City, Exempted Village or Local Superintendent Signature | N67: Treasurer Signature

Sheet data
A1: dist | B1: SCHOOL_YEAR | C1: DIST_IRN | D1: disadm_nospch | E1: DISABILITY_SALBEN | F1: reg_salben | G1: INSTR_SUP | H1: INSTR_EQ | I1: admin_gf_total | J1: ops_gf_total | K1: staff_gf_total | L1: pupil_gf_total | M1: admin_EFM_GF | N1: ops_EFM_gf | O1: staff_EFM_gf | P1: pupil_EFM_gf | Q1: adm1
A2: Please select a district.
A3: Ada Ex Vill SD (045187, Hardin County) | B3: 2012 | C3: 045187 | D3: 83.342768 | E3: 241158.23 | F3: 3283118.5 | G3: 46243.78 | H3: 6987.05 | I3: 978016.58 | J3: 1023476 | K3: 125338.71 | L3: 672121.96 | M3: 1097.8589 | N3: 1148.8887 | O3: 140.69722 | P3: 754.48112 | Q3: 890.84
A4: Adams County/Ohio Valley Local (061903, Adams County) | B4: 2012 | C4: 061903 | D4: 640.58983 | E4: 2440189.1 | F4: 12132096 | G4: 516034.77 | H4: 264156.54 | I4: 3193564.9 | J4: 4280071.7 | K4: 775393.4 | L4: 1889426.5 | M4: 807.35283 | N4: 1082.0284 | O4: 196.02422 | P4: 477.65863 | Q4: 3955.6
A5: Adena Local SD (049494, Ross County) | B5: 2012 | C5: 049494 | D5: 149.84561 | E5: 361572.64 | F5: 4250359.5 | G5: 77622.32 | H5: 45103.89 | I5: 1399382.7 | J5: 1767702.5 | K5: 6682.9 | L5: 971642.91 | M5: 1125.2947 | N5: 1421.4741 | O5: 5.3739637 | P5: 781.33351 | Q5: 1243.57
A6: Akron City SD (043489, Summit County) | B6: 2012 | C6: 043489 | D6: 3756.1113 | E6: 24916669 | F6: 97749395 | G6: 3683579.4 | H6: 255709.47 | I6: 22662924 | J6: 45233608 | K6: 7542895 | L6: 24915316 | M6: 1030.8976 | N6: 2057.5995 | O6: 343.11339 | P6: 1133.3551 | Q6: 21983.68
A7: Alexander Local SD (045906, Athens County) | B7: 2012 | C7: 045906 | D7: 264.38097 | E7: 563144.99 | F7: 2597175 | G7: 110029.41 | H7: 97139.52 | I7: 1598831 | J7: 2674184.9 | K7: 221484.5 | L7: 928563.87 | M7: 1002.0626 | N7: 1676.0375 | O7: 138.81476 | P7: 581.97467 | Q7: 1595.54
A8: Allen East Local SD (045757, Allen County) | B8: 2012 | C8: 045757 | D8: 95.429838 | E8: 283656.03 | F8: 3935205.9 | G8: 44930.19 | H8: 649.97 | I8: 943196.48 | J8: 1102114.3 | K8: 24788.43 | L8: 673712.64 | M8: 836.47113 | N8: 977.40696 | O8: 21.983549 | P8: 597.48015 | Q8: 1127.59
A9: Alliance City SD (043497, Stark County) | B9: 2012 | C9: 043497 | D9: 496.21148 | E9: 2859206.5 | F9: 9552744.2 | G9: 495112.81 | H9: 73968.28 | I9: 2592951.2 | J9: 3939978.6 | K9: 129922.75 | L9: 1960405.3 | M9: 912.22726 | N9: 1386.1255 | O9: 45.708177 | P9: 689.69102 | Q9: 2842.44
A10: Amanda-Clearcreek Local SD (046847, Fairfield County) | B10: 2012 | C10: 046847 | D10: 168.16475 | E10: 729481.28 | F10: 3804393.1 | G10: 181138.85 | H10: 142471.21 | I10: 1520971 | J10: 2495103.6 | K10: 51814.69 | L10: 777150.35 | M10: 894.83095 | N10: 1467.9411 | O10: 30.484071 | P10: 457.21988 | Q10: 1699.73
A11: Amherst Ex Vill SD (045195, Lorain County) | B11: 2012 | C11: 045195 | D11: 597.38915 | E11: 1974216.9 | F11: 14248397 | G11: 466062.1 | H11: 610 | I11: 3887479.7 | J11: 4461831.7 | K11: 739498.51 | L11: 3069947.4 | M11: 979.03401 | N11: 1123.6805 | O11: 186.23742 | P11: 773.14432 | Q11: 3970.73
A12: Anna Local SD (049759, Shelby County) | B12: 2012 | C12: 049759 | D12: 90.988764 | E12: 182243.78 | F12: 4049237.4 | G12: 214918.87 | H12: 1255.6 | I12: 1067808.9 | J12: 1717671.6 | K12: 72788.65 | L12: 886547.41 | M12: 879.48485 | N12: 1414.7345 | O12: 59.951282 | P12: 730.1915 | Q12: 1214.13
A13: Ansonia Local SD (046623, Darke County) | B13: 2012 | C13: 046623 | D13: 79.314253 | E13: 528335.17 | F13: 2389226.8 | G13: 71714.89 | H13: 2202.96 | I13: 717700.92 | J13: 931651.96 | K13: 61507.05 | L13: 644254.94 | M13: 1056.4057 | N13: 1371.3267 | O13: 90.53409 | P13: 948.29836 | Q13: 679.38
A14: Anthony Wayne Local SD (048207, Lucas County) | B14: 2012 | C14: 048207 | D14: 333.04918 | E14: 1391264.1 | F14: 16139592 | G14: 341668.53 | H14: 0 | I14: 4148007.1 | J14: 5631071.4 | K14: 482753.39 | L14: 2427090.7 | M14: 1012.744 | N14: 1374.8371 | O14: 117.86518 | P14: 592.57892 | Q14: 4095.81
... A342: Miamisburg City SD (044396, Montgomery County) | B342: 2012 | C342: 044396 | D342: 708.21679 | E342: 3133127.8 | F342: 18770188 | G342: 230109.41 | H342: 0 | I342: 4444521.7 | J342: 6161101.8 | K342: 353029.69 | L342: 4909423.4 | M342: 838.5083 | N342: 1162.3602 | O342: 66.602967 | P342: 926.21717 | Q342: 5300.51
A343: Middle Bass Local SD (048959, Ottawa County) | B343: 2012 | C343: 048959 | D343: 0 | E343: 0 | F343: 0 | G343: 0 | H343: 0 | I343: 25460.87 | J343: 4894.71 | K343: 0 | L343: 0 | M343: #DIV/0! | N343: #DIV/0! | O343: #DIV/0! | P343: #DIV/0! | Q343: 0
A344: Middletown City SD (044404, Butler County) | B344: 2012 | C344: 044404 | D344: 926.0177 | E344: 5166091.7 | F344: 25555137 | G344: 360564.6 | H344: 0 | I344: 8948248.4 | J344: 8979936.8 | K344: 2070418.6 | L344: 4055163.7 | M344: 1439.9493 | N344: 1445.0486 | O344: 333.17112 | P344: 652.55568 | Q344: 6214.28
A345: Midview Local SD (048173, Lorain County) | B345: 2012 | C345: 048173 | D345: 322.95416 | E345: 889340.72 | F345: 10693019 | G345: 169087.67 | H345: 65634.84 | I345: 3541990.5 | J345: 4108237.6 | K345: 55322.71 | L345: 2467159.3 | M345: 1115.145 | N345: 1293.4198 | O345: 17.417563 | P345: 776.74978 | Q345: 3176.26
A346: Milford Ex Vill SD (045500, Clermont County) | B346: 2012 | C346: 045500 | D346: 719.43354 | E346: 3234837.8 | F346: 22764052 | G346: 1121087.6 | H346: 782253.75 | I346: 5171503.8 | J346: 9949618.2 | K346: 2871000.1 | L346: 3487259.6 | M346: 833.07889 | N346: 1602.7866 | O346: 462.49015 | P346: 561.76355 | Q346: 6207.7
A347: Millcreek-West Unity Local SD (050633, Williams County) | B347: 2012 | C347: 050633 | D347: 68.591185 | E347: 202695.4 | F347: 2319669.3 | G347: 36917.91 | H347: 8807.25 | I347: 872263.69 | J347: 889623.29 | K347: 36130.54 | L347: 473791.94 | M347: 1426.9696 | N347: 1455.3688 | O347: 59.107334 | P347: 775.09438 | Q347: 611.27
A348: Miller City-New Cleveland Loca (049361, Putnam County) | B348: 2012 | C348: 049361 | D348: 34.733954 | E348: 136956.96 | F348: 1943276.3 | G348: 76396.79 | H348: 0 | I348: 555199.41 | J348: 729907.15 | K348: 19898.6 | L348: 314172.52 | M348: 1195.5456 | N348: 1571.7547 | O348: 42.848899 | P348: 676.52732 | Q348: 464.39
A349: Milton-Union Ex Vill SD (045518, Miami County) | B349: 2012 | C349: 045518 | D349: 210.60354 | E349: 805332.34 | F349: 5579370.6 | G349: 100054.31 | H349: 52644.19 | I349: 1902121.9 | J349: 1537068.3 | K349: 247532.91 | L349: 818053.21 | M349: 1200.6223 | N349: 970.19988 | O349: 156.24316 | P349: 516.35646 | Q349: 1584.28
A350: Minerva Local SD (049890, Stark County) | B350: 2012 | C350: 049890 | D350: 286.40657 | E350: 825543.65 | F350: 6156114.2 | G350: 199018.18 | H350: 8391.39 | I350: 2085459.4 | J350: 2238579.1 | K350: 43987.13 | L350: 2218332.2 | M350: 953.51853 | N350: 1023.5283 | O350: 20.111896 | P350: 1014.2709 | Q350: 2187.12
A351: Minford Local SD (049627, Scioto County) | B351: 2012 | C351: 049627 | D351: 166.42266 | E351: 577029.8 | F351: 5181701.5 | G351: 60383.98 | H351: 14004.1 | I351: 1293812.5 | J351: 2208184 | K351: 173067.71 | L351: 767254.04 | M351: 867.3235 | N351: 1480.284 | O351: 116.01812 | P351: 514.33841 | Q351: 1491.73
A352: Minster Local SD (045948, Auglaize County) | B352: 2012 | C352: 045948 | D352: 74.154704 | E352: 327502.95 | F352: 3597057.3 | G352: 49105.11 | H352: 71875.17 | I352: 798342.26 | J352: 1109236.9 | K352: 52042.76 | L352: 517737.23 | M352: 990.14283 | N352: 1375.7295 | O352: 64.545957 | P352: 642.12285 | Q352: 806.29
A353: Mississinawa Valley Local SD (046672, Darke County) | B353: 2012 | C353: 046672 | D353: 111.81619 | E353: 524861.96 | F353: 2430120 | G353: 130218.58 | H353: 1769.95 | I353: 766512.72 | J353: 1005687.8 | K353: 109887.47 | L353: 716191.78 | M353: 1111.2745 | N353: 1458.0257 | O353: 159.31262 | P353: 1038.3203 | Q353: 689.76
A354: Mogadore Local SD (050039, Summit County) | B354: 2012 | C354: 050039 | D354: 90.290779 | E354: 286008.18 | F354: 4137211.7 | G354: 73741.74 | H354: 2033.46 | I354: 1197162.8 | J354: 1057600 | K354: 28493.91 | L354: 819119.36 | M354: 1320.2205 | N354: 1166.3119 | O354: 31.422832 | P354: 903.31759 | Q354: 906.79
A355: Mohawk Local SD (050740, Wyandot County) | B355: 2012 | C355: 050740 | D355: 88.0625 | E355: 337266.85 | F355: 2958036.9 | G355: 164645.07 | H355: 11835.91 | I355: 887861.2 | J355: 1625351.6 | K355: 186968.3 | L355: 940735.69 | M355: 956.59236 | N355: 1751.1735 | O355: 201.4419 | P355: 1013.56 | Q355: 928.15
... A385: North Baltimore Local SD (050708, Wood County) | B385: 2012 | C385: 050708 | D385: 124.282 | E385: 318114.2 | F385: 2545729.1 | G385: 21656.32 | H385: 0 | I385: 1092320.4 | J385: 899133.21 | K385: 38005.27 | L385: -624575.96 | M385: 1551.9442 | N385: 1277.4682 | O385: 53.997031 | P385: -887.38344 | Q385: 703.84
A386: North Bass Local SD (048967, Ottawa County) | B386: 2012 | C386: 048967 | D386: 0 | E386: 0 | F386: 22.41 | G386: 0 | H386: 0 | I386: 11251.29 | J386: 20775.2 | K386: 0 | L386: 0 | M386: #DIV/0! | N386: #DIV/0! | O386: #DIV/0! | P386: #DIV/0! | Q386: 0
A387: North Canton City SD (044503, Stark County) | B387: 2012 | C387: 044503 | D387: 470.95474 | E387: 2003182.7 | F387: 17644274 | G387: 197029 | H387: 224079.43 | I387: 4007099.5 | J387: 6845804.3 | K387: 758539.7 | L387: 4626003.5 | M387: 889.76859 | N387: 1520.0974 | O387: 168.43225 | P387: 1027.195 | Q387: 4503.53
A388: North Central Local SD (050641, Williams County) | B388: 2012 | C388: 050641 | D388: 80.050852 | E388: 303305.27 | F388: 2565879.8 | G388: 105833.98 | H388: 1705.58 | I388: 831007.24 | J388: 863427.7 | K388: 129788.23 | L388: 719397.91 | M388: 1333.3022 | N388: 1385.3189 | O388: 208.23757 | P388: 1154.2316 | Q388: 623.27
A389: North College Hill City SD (044511, Hamilton County) | B389: 2012 | C389: 044511 | D389: 271.12522 | E389: 0 | F389: 4427251.7 | G389: 115102.77 | H389: 0 | I389: 1340104.3 | J389: 1214568.3 | K389: 332430.95 | L389: 1537586.2 | M389: 822.44252 | N389: 745.39916 | O389: 204.01796 | P389: 943.64017 | Q389: 1629.42
A390: North Fork Local SD (048025, Licking County) | B390: 2012 | C390: 048025 | D390: 258.34259 | E390: 914661.15 | F390: 5167378.7 | G390: 129727.18 | H390: 24018.26 | I390: 2156751.4 | J390: 2651318.3 | K390: 787595.3 | L390: 904625.61 | M390: 1240.9958 | N390: 1525.5698 | O390: 453.18271 | P390: 520.52201 | Q390: 1737.92
A391: North Olmsted City SD (044529, Cuyahoga County) | B391: 2012 | C391: 044529 | D391: 537.98139 | E391: 4170436.4 | F391: 20044900 | G391: 270572.51 | H391: 17658.42 | I391: 5559998.9 | J391: 7617504.9 | K391: 137948.16 | L391: 5666501 | M391: 1416.2752 | N391: 1940.375 | O391: 35.138955 | P391: 1443.404 | Q391: 3925.79
A392: North Ridgeville City SD (044537, Lorain County) | B392: 2012 | C392: 044537 | D392: 470.49371 | E392: 2129025.6 | F392: 12822289 | G392: 178888.83 | H392: 19137.45 | I392: 3273744.6 | J392: 4595618 | K392: 1613657.5 | L392: 2830737.5 | M392: 865.28027 | N392: 1214.6633 | O392: 426.50424 | P392: 748.18948 | Q392: 3783.45
A393: North Royalton City SD (044545, Cuyahoga County) | B393: 2012 | C393: 044545 | D393: 415.47638 | E393: 2430673.9 | F393: 21070386 | G393: 495468.96 | H393: 29822.15 | I393: 5111093.6 | J393: 6826615.2 | K393: 570209.52 | L393: 4967966.1 | M393: 1116.3347 | N393: 1491.0287 | O393: 124.54177 | P393: 1085.0736 | Q393: 4578.46
A394: North Union Local SD (050336, Union County) | B394: 2012 | C394: 050336 | D394: 195.38033 | E394: 806574.05 | F394: 5193455.8 | G394: 220489.85 | H394: 565627.85 | I394: 1563698.8 | J394: 2804682.4 | K394: 447546.48 | L394: 1173740.9 | M394: 1049.5961 | N394: 1882.5773 | O394: 300.40507 | P394: 787.84603 | Q394: 1489.81
A395: Northeastern Local SD (046250, Clark County) | B395: 2012 | C395: 046250 | D395: 271.03491 | E395: 1419964.8 | F395: 12142873 | G395: 364072.06 | H395: 114447.13 | I395: 3558371 | J395: 4836895.8 | K395: 388251.58 | L395: 3409456.9 | M395: 1003.4208 | N395: 1363.9505 | O395: 109.4826 | P395: 961.42869 | Q395: 3546.24
A396: Northeastern Local SD (046722, Defiance County) | B396: 2012 | C396: 046722 | D396: 108.14073 | E396: 398038.21 | F396: 3994677 | G396: 90776.45 | H396: 1774.8 | I396: 1280139.5 | J396: 1403601.9 | K396: 70246.46 | L396: 1118419.6 | M396: 1136.77 | N396: 1246.4053 | O396: 62.379196 | P396: 993.16204 | Q396: 1126.12
A397: Northern Local SD (049056, Perry County) | B397: 2012 | C397: 049056 | D397: 253.54607 | E397: 974205.21 | F397: 7223733 | G397: 134236.67 | H397: 0 | I397: 3006767.1 | J397: 3243196.9 | K397: 234820.84 | L397: 1588558.7 | M397: 1371.4813 | N397: 1479.3244 | O397: 107.10919 | P397: 724.59174 | Q397: 2192.35
A398: Northmont City SD (048728, Montgomery County) | B398: 2012 | C398: 048728 | D398: 652.30445 | E398: 3818094.4 | F398: 19585067 | G398: 680268.58 | H398: 428513.74 | I398: 4897490.5 | J398: 6297778.7 | K398: 197000.86 | L398: 4692951.2 | M398: 938.32263 | N398: 1206.6074 | O398: 37.743894 | P398: 899.13443 | Q398: 5219.41
... A465: River View Local SD (046482, Coshocton County) | B465: 2012 | C465: 046482 | D465: 349.10693 | E465: 1380367.7 | F465: 7663167.5 | G465: 206231.31 | H465: 59263.86 | I465: 2355350.7 | J465: 3337899.6 | K465: 426977.33 | L465: 1189661.4 | M465: 1112.4838 | N465: 1576.5632 | O465: 201.67076 | P465: 561.90318 | Q465: 2117.2
A466: Riverdale Local SD (047514, Hardin County) | B466: 2012 | C466: 047514 | D466: 120.32418 | E466: 0 | F466: 0 | G466: 0 | H466: 0 | I466: 0 | J466: 0 | K466: 0 | L466: 0 | M466: 0 | N466: 0 | O466: 0 | P466: 0 | Q466: #N/A
A467: Riverside Local Local SD (047894, Lake County) | B467: 2012 | C467: 047894 | D467: 455.46953 | E467: 1909725.2 | F467: 15775472 | G467: 488518.41 | H467: 65211.25 | I467: 5131860 | J467: 6712987.3 | K467: 829638.47 | L467: 2298587 | M467: 1102.8005 | N467: 1442.5736 | O467: 178.28345 | P467: 493.95011 | Q467: 4653.48
A468: Riverside Local SD (048090, Logan County) | B468: 2012 | C468: 048090 | D468: 83.488764 | E468: 428149.31 | F468: 2613223.3 | G468: 23201.05 | H468: 0 | I468: 810585.99 | J468: 1131760.2 | K468: 164650.99 | L468: 394904.95 | M468: 1152.5466 | N468: 1609.214 | O468: 234.11203 | P468: 561.50284 | Q468: 703.3
A469: Rock Hill Local SD (047944, Lawrence County) | B469: 2012 | C469: 047944 | D469: 221.96377 | E469: 1078962.9 | F469: 5202220.2 | G469: 106191.13 | H469: 0 | I469: 1830954.1 | J469: 3266736.7 | K469: 0 | L469: 1169832.1 | M469: 1245.1066 | N469: 2221.484 | O469: 0 | P469: 795.52275 | Q469: 1470.52
A470: Rocky River City SD (044701, Cuyahoga County) | B470: 2012 | C470: 044701 | D470: 210.93251 | E470: 2181071.6 | F470: 13188327 | G470: 200758.13 | H470: 297882.23 | I470: 3847525.6 | J470: 5116716.7 | K470: 937025.7 | L470: 3157144.5 | M470: 1522.9221 | N470: 2025.2915 | O470: 370.89218 | P470: 1249.6564 | Q470: 2526.41
A471: Rolling Hills Local SD (047308, Guernsey County) | B471: 2012 | C471: 047308 | D471: 251.07009 | E471: 893988.96 | F471: 6172058.9 | G471: 225011.07 | H471: 132089.13 | I471: 2025417.2 | J471: 2504866.7 | K471: 287634.08 | L471: 606262.1 | M471: 1100.8241 | N471: 1361.4072 | O471: 156.33052 | P471: 329.50639 | Q471: 1839.91
A472: Rootstown Local SD (049213, Portage County) | B472: 2012 | C472: 049213 | D472: 153.23697 | E472: 313396.12 | F472: 4330834.6 | G472: 103130.75 | H472: 4241.06 | I472: 1203070.6 | J472: 1622852 | K472: 230111.94 | L472: 936649.59 | M472: 968.43753 | N472: 1306.3496 | O472: 185.23355 | P472: 753.97623 | Q472: 1242.28
A473: Ross Local SD (046144, Butler County) | B473: 2012 | C473: 046144 | D473: 240.32877 | E473: 1120800.4 | F473: 10311555 | G473: 160630.41 | H473: 121656.22 | I473: 1876924.1 | J473: 3318140 | K473: 169006 | L473: 2058223.2 | M473: 676.86908 | N473: 1196.6101 | O473: 60.948088 | P473: 742.25038 | Q473: 2772.95
A474: Rossford Ex Vill SD (045609, Wood County) | B474: 2012 | C474: 045609 | D474: 176.63234 | E474: 1439834.8 | F474: 9886223.1 | G474: 296645.04 | H474: 0 | I474: 2896222 | J474: 3076971.5 | K474: 720802.87 | L474: 2476864.9 | M474: 1837.5644 | N474: 1952.2444 | O474: 457.32741 | P474: 1571.4951 | Q474: 1576.12
A475: Russia Local SD (049817, Shelby County) | B475: 2012 | C475: 049817 | D475: 30.258225 | E475: 125145.51 | F475: 1667420.1 | G475: 65319.44 | H475: 23487.76 | I475: 587242.64 | J475: 546403.97 | K475: 7557.37 | L475: 242402.34 | M475: 1260.2314 | N475: 1172.591 | O475: 16.218228 | P475: 520.19902 | Q475: 465.98
A476: Salem City SD (044735, Columbiana County) | B476: 2012 | C476: 044735 | D476: 212.48912 | E476: 857747.7 | F476: 7288746 | G476: 293699.65 | H476: 0 | I476: 2369600.5 | J476: 2253248.9 | K476: 89561.03 | L476: 1802876.4 | M476: 1130.6694 | N476: 1075.1516 | O476: 42.734596 | P476: 860.25355 | Q476: 2095.75
A477: Sandusky City SD (044743, Erie County) | B477: 2012 | C477: 044743 | D477: 476.51661 | E477: 3230694.2 | F477: 13485953 | G477: 188609.31 | H477: 14048.02 | I477: 3697169.1 | J477: 4638212.7 | K477: 1500267.5 | L477: 2879354.6 | M477: 1141.824 | N477: 1432.4535 | O477: 463.3387 | P477: 889.25235 | Q477: 3237.95
A478: Sandy Valley Local SD (049940, Stark County) | B478: 2012 | C478: 049940 | D478: 239.39917 | E478: 700434.43 | F478: 4299069.1 | G478: 155650.83 | H478: 0 | I478: 1459964 | J478: 1780218.4 | K478: 48864.25 | L478: 1418087.1 | M478: 1025.9978 | N478: 1251.0583 | O478: 34.339621 | P478: 996.56851 | Q478: 1422.97
... A521: Swanton Local SD (047092, Fulton County) | B521: 2012 | C521: 047092 | D521: 161.241 | E521: 621727.35 | F521: 4700430.5 | G521: 138987.29 | H521: 5620.42 | I521: 1778747 | J521: 2003676.6 | K521: 281614.1 | L521: 1472074.9 | M521: 1376.7392 | N521: 1550.8333 | O521: 217.96757 | P521: 1139.3769 | Q521: 1292
A522: Switzerland of Ohio Local SD (048652, Monroe County) | B522: 2012 | C522: 048652 | D522: 394.44852 | E522: 1249812.1 | F522: 8890108.2 | G522: 380372.62 | H522: 60599.13 | I522: 2822296.4 | J522: 4959358 | K522: 70305.68 | L522: 1747123.6 | M522: #DIV/0! | N522: #DIV/0! | O522: #DIV/0! | P522: #DIV/0! | Q522: 0
A523: Sycamore Community City SD (044867, Hamilton County) | B523: 2012 | C523: 044867 | D523: 509.48074 | E523: 4673816 | F523: 30438767 | G523: 703881.36 | H523: 170784.43 | I523: 8754565.6 | J523: 11467002 | K523: 3016032.2 | L523: 6455161.6 | M523: 1682.6998 | N523: 2204.0524 | O523: 579.7063 | P523: 1240.7354 | Q523: 5202.69
A524: Sylvania City SD (044875, Lucas County) | B524: 2012 | C524: 044875 | D524: 976.14444 | E524: 5635260.5 | F524: 31272536 | G524: 872527.97 | H524: 5499 | I524: 9962722.2 | J524: 12736837 | K524: 1388480.4 | L524: 7748326.7 | M524: 1344.7274 | N524: 1719.166 | O524: 187.41139 | P524: 1045.8374 | Q524: 7408.73
A525: Symmes Valley Local SD (047969, Lawrence County) | B525: 2012 | C525: 047969 | D525: 127.51987 | E525: 514779 | F525: 2826576.1 | G525: 98397.59 | H525: 1551.68 | I525: 1059287.8 | J525: 1809330.5 | K525: 16025.33 | L525: 684541.37 | M525: 1340.1582 | N525: 2289.0748 | O525: 20.274449 | P525: 866.04763 | Q525: 790.42
A526: Talawanda City SD (046151, Butler County) | B526: 2012 | C526: 046151 | D526: 268.53709 | E526: 1279079.4 | F526: 12767862 | G526: 147877.29 | H526: 65580.58 | I526: 3672400.9 | J526: 4913442 | K526: 899756 | L526: 3215151.7 | M526: 1201.0416 | N526: 1606.9183 | O526: 294.26101 | P526: 1051.5004 | Q526: 3057.68
A527: Tallmadge City SD (044883, Summit County) | B527: 2012 | C527: 044883 | D527: 271.23233 | E527: 1685373.5 | F527: 10109323 | G527: 82213.7 | H527: 365840.85 | I527: 2714064.3 | J527: 3533364.8 | K527: 63985.07 | L527: 2282266 | M527: 1076.9669 | N527: 1402.0732 | O527: 25.389893 | P527: 905.62519 | Q527: 2520.1
A528: Teays Valley Local SD (049098, Pickaway County) | B528: 2012 | C528: 049098 | D528: 375.90328 | E528: 2219762.5 | F528: 12527958 | G528: 275897.56 | H528: 0 | I528: 4086788.1 | J528: 4949636 | K528: 539955.99 | L528: 2287609.6 | M528: 1141.6247 | N528: 1382.6571 | O528: 150.83412 | P528: 639.03281 | Q528: 3579.8
A529: Tecumseh Local SD (046243, Clark County) | B529: 2012 | C529: 046243 | D529: 408.72072 | E529: 1977486 | F529: 11067311 | G529: 305151.22 | H529: 65283.66 | I529: 3045270.4 | J529: 4321447.7 | K529: 237258.24 | L529: 2252329.2 | M529: 986.5141 | N529: 1399.9312 | O529: 76.85971 | P529: 729.64114 | Q529: 3086.9
A530: Three Rivers Local SD (047399, Hamilton County) | B530: 2012 | C530: 047399 | D530: 240.88214 | E530: 832565.88 | F530: 7757463.2 | G530: 62427.25 | H530: 15965.32 | I530: 2330986.4 | J530: 2812399.4 | K530: 121546.24 | L530: 2092668.9 | M530: 1271.6159 | N530: 1534.2397 | O530: 66.30675 | P530: 1141.6073 | Q530: 1833.09
A531: Tiffin City SD (044891, Seneca County) | B531: 2012 | C531: 044891 | D531: 412.01622 | E531: 1376040 | F531: 8160962.1 | G531: 98470.75 | H531: 5170.18 | I531: 2666765.4 | J531: 2989950.6 | K531: 116083.6 | L531: 1910232.2 | M531: 965.84841 | N531: 1082.8996 | O531: 42.043128 | P531: 691.84741 | Q531: 2761.06
A532: Tipp City Ex Vill SD (045617, Miami County) | B532: 2012 | C532: 045617 | D532: 303.2579 | E532: 521862.27 | F532: 9972023.2 | G532: 145915.01 | H532: 23052.21 | I532: 2600735 | J532: 3064986.8 | K532: 221171.98 | L532: 2390517.7 | M532: 1042.0947 | N532: 1228.1169 | O532: 88.621931 | P532: 957.86228 | Q532: 2495.68
A533: Toledo City SD (044909, Lucas County) | B533: 2012 | C533: 044909 | D533: 3646.622 | E533: 24154044 | F533: 74674249 | G533: 3317045.2 | H533: 687881.26 | I533: 27516085 | J533: 38061255 | K533: 2167063.9 | L533: 25422078 | M533: 1271.4459 | N533: 1758.7104 | O533: 100.13432 | P533: 1174.6873 | Q533: 21641.57
A534: Toronto City SD (044917, Jefferson County) | B534: 2012 | C534: 044917 | D534: 104.01117 | E534: 448057.74 | F534: 2717554.3 | G534: 62422.63 | H534: 6828 | I534: 1239185.8 | J534: 967873.13 | K534: 38737.74 | L534: 656574.03 | M534: 1585.549 | N534: 1238.4021 | O534: 49.565274 | P534: 840.09216 | Q534: 781.55
... A616: Zanesville City SD (045179, Muskingum County) | B616: 2012 | C616: 045179 | D616: 622.06283 | E616: 3171024.6 | F616: 9321143.9 | G616: 181404.94 | H616: 32651 | I616: 3142088.4 | J616: 4509279.8 | K616: 441765.31 | L616: 3154026 | M616: 925.81284 | N616: 1328.6543 | O616: 130.16565 | P616: 929.33024 | Q616: 3393.87

Sheet Data Notes
A3: Sheet Name | B3: Cell | C3: Description
A4: SF-6 Form Per Capita | B4: N25 | C4: FY 2012 expenditure reported to funds 001, 494, 016, and 532 and functions 122X, 123X, 124X and object codes 11X, 12X, 21X, 24X, 131 and 261
A5: SF-6 Form Per Capita | B5: N27 | C5: FY 2012 expenditure reported to funds 001, 494, 016, and 532 and function 11XX and object codes 11X, 12X, 21X, 24X, 131 and 261
A6: SF-6 Form Per Capita | B6: N30 | C6: FY 2012 expenditure reported to funds 001, 494, 016, and 532 and function 1XXX and object codes 5XX
A7: SF-6 Form Per Capita | B7: N32 | C7: FY 2012 expenditure reported to funds 001, 494, 016, and 532 and function 1XXX and object codes 6XX and 7XX
A8: SF-6 Form Per Capita | B8: N33 | C8: FY 2012 EFM General Fund administrative expenditure total
A9: SF-6 Form Per Capita | B9: N34 | C9: FY 2012 EFM General Fund operations expenditure total
A10: SF-6 Form Per Capita | B10: N35 | C10: FY 2012 EFM General Fund staff support expenditure total
A11: SF-6 Form Per Capita | B11: N36 | C11: FY 2012 EFM General Fund pupil support expenditure total
A12: SF-6 Form Per Capita | B12: O25 | C12: FY 2012 EFM ADM of those student with a disability condition excluding Speech and lanaguage (05)
A13: SF-6 Form Per Capita | B13: O27-O36 | C13: FY 2012 EFM ADM total
A14: SF-6 Form Specific Student | B14: N34-N35 | C14: District submitted FY 2012 data
... A28: SF-6 Form Specific Student | B28: O37-O46 | C28: FY 2012 EFM ADM total

Sheet options
A1: Options
A2: Please select a calculation option.
A3: I would like Excess Cost for my district to be calculated on a per capita basis.
A4: I would like Excess Cost for my district to be calculated on an individual student basis.
A6: Disability Type
A7: Please select a disability condition.
A8: Category 1. Speech (Disability condition 05)
A9: Category 2. Learning Disabilities (Disability condition 10)
A10: Category 2. Cognitive Disabilities (formerly Developmentally Handicapped) (Disability condition 09)
A11: Category 2. Other Health Impairment, Minor (Disability condition 15)
A12: Category 3. Hearing Impairment (Disability condition 03)
A13: Category 3. Emotional Disturbance (SBH) (Disability condition 08)
... A29: Non-resident student attending special ed program (including coop) (How Received Code=B)
