Workbook
Name Aid: 'Aid Adjust'!$A$10:$H$346
Name Ideas: Credits!$A$8:$C$344
Name Ideas: Levy!$A$8:$C$344
Name Ideas: Ideas!$A$9:$H$345
Name Query_from_Databridge: Query1!$A$3:$F$146
Name Query_from_Databridge: Query4!$A$3:$F$138
Name Shift05: Receipts!$A$8:$K$344
Name ShiftCY: Shift11!$A$8:$O$344
Name ShiftPY: Shift10!$A$8:$O$344

Sheet Instructions
A1: PROPERTY TAX SHIFT | M1: =Report!I1 -> 41115 | O1: 2012 | P1: Pay 2012 | Q1: 11 Pay 12 | R1: FY 2013
P2: Pay 2011 | Q2: 10 Pay 11 | R2: FY 2012 | S2: 06/30/12 | T2: 07/01/2011 to 06/30/2012
P3: Pay 2010 | R3: FY 2011 | S3: 06/30/11 | T3: 07/01/2011 to 04/30/2012
P4: Pay 2009 | T4: 05/01/2012 to 06/30/2012
A5: ="The property tax shift is an accounting entry that takes a portion of the school district's property tax revenue and moves it forward one fiscal year, i.e., taxes that would otherwise be revenue for fiscal year "&RIGHT(R1,4)&" are shifted into fiscal year "&RIGHT(R2,4)&". The property tax shift requirement is in Minnesota Statutes, section 123B.75, subdivision 5." -> The property tax shift is an accounting entry that takes a portion of the school district's property tax revenue and moves it forward one fiscal year, i.e., taxes that would otherwise be revenue for fiscal year 2013 are shifted into fiscal year 2012. The property tax shift requirement is in Minnesota Statutes, section 123B.75, subdivision 5. | P5: Pay 2008
P6: Pay 2007
P7: Pay 2006
A8: Notes: | P8: Pay 2005
A10: ="For the June 30, "&RIGHT(R2,4)&", tax shift this spreadsheet is using the payable "&RIGHT(P1,4)&" final certified levies plus/minus county auditor adjustments." -> For the June 30, 2012, tax shift this spreadsheet is using the payable 2012 final certified levies plus/minus county auditor adjustments.
A13: ="Preliminary payable "&RIGHT(P1,4)&" credits are used in this spreadsheet. The spreadsheet will be updated to use final payable "&RIGHT(P1,4)&" credits when that data is available." -> Preliminary payable 2012 credits are used in this spreadsheet. The spreadsheet will be updated to use final payable 2012 credits when that data is available.
A15: ="Tax receipts for May-July "&RIGHT(R2,4)&" for the general fund and community service fund have been estimated on the Receipts tab. Preliminary payable "&RIGHT(P1,4)&" credits from the Department of Revenue are used in computing estimated tax receipts. These estimates are carried over to cells E89 and F89 of the Report tab. Districts should override these estimates when actual tax receipts are determined." -> Tax receipts for May-July 2012 for the general fund and community service fund have been estimated on the Receipts tab. Preliminary payable 2012 credits from the Department of Revenue are used in computing estimated tax receipts. These estimates are carried over to cells E89 and F89 of the Report tab. Districts should override these estimates when actual tax receipts are determined.
A19: Early Recognition Levies
A20: Certain levies have been--and will continue to be--shifted 100% with no aid reduction. Recognizing these levies early gets the revenue into the same fiscal year as the related expenditures. There is no state aid adjustment for this portion of the shift.
A23: Other Levies
A24: Starting in fiscal year 2004, the shift was expanded to include all other general and community service fund levies, net of tax credits. There is a corresponding state aid adjustment for this portion of the property tax shift, making this portion of the shift revenue neutral to school districts each year. If the shift at the end of the current year is larger than the shift at the end of the previous year, state aid for the current year is reduced for the net increase in the shift. If the shift at the end of the current year is less than the shift at the end of the previous year, state aid for the current year is increased for the net decrease in the shift.
A29: Starting in fiscal year 2006, the shift percentage for other levies was set to zero percent.
A30: Starting in fiscal year 2011, the shift percentage for other levies was set to 48.6 percent, and based on gross levies (before subtraction of credits).
A33: The "Reports" tab shows the property tax shift report for a selected school district.
B34: To select a specific district, type the district number in cell A3 (use 1.2 for Minneapolis) and press enter. Information for the selected district will then appear in the report. Running a macro is not required.
B37: The first section shows the property tax shift report for the school district, with a definition for each tax shift category.
C38: ="Column 1 is the amount of payable "&RIGHT(P1,4)&" levy to be recognized in fiscal year "&RIGHT(R2,4)&"." -> Column 1 is the amount of payable 2012 levy to be recognized in fiscal year 2012.
C39: ="Column 2 is the amount of payable "&RIGHT(P2,4)&" levy that was recognized in fiscal year "&RIGHT(R3,4)&"." -> Column 2 is the amount of payable 2011 levy that was recognized in fiscal year 2011.
C40: Column 3 is the revenue change to be recognized as a result of the levies shifted with with no aid reduction (net of column 1 and column 2 for these categories).
C41: Column 4 is the net shift amount to be recognized as a result of levies shifted with an aid reduction. A negative amount in this column represents a debit balance in source 020 and related crebit balance in source 299.
C43: Column 5 is the state aid payment (reduction) that is being made in the current year for the property tax shift.
C44: Column 6 represents the state aid payment (reduction) that will be made next year, for this year's tax shift. Column 4 plus column 5 plus column 6 should equal zero.
B47: The second section discusses the assumptions that have been made in generating the entries to record the tax shift. Also review the Accounts tab and Entries tab.
B49: ="In the third section, estimated tax receipts for May, June and July "&RIGHT(R2,4)&" have been computed. See blue highlighted area. Override these estimates with actual tax settlement receipts for May, June and July "&RIGHT(R2,4)&" when this data is available. If the gross shift amount is greater than May, June and July tax receipts, the district will recognize fiscal year "&RIGHT(R1,4)&" general education aid early in an amount equal to the difference between tax receipts and the gross shift." -> In the third section, estimated tax receipts for May, June and July 2012 have been computed. See blue highlighted area. Override these estimates with actual tax settlement receipts for May, June and July 2012 when this data is available. If the gross shift amount is greater than May, June and July tax receipts, the district will recognize fiscal year 2013 general education aid early in an amount equal to the difference between tax receipts and the gross shift.
B53: ="The fourth section provides information to make the year-end accounting entries for the fiscal year "&RIGHT(R2,4)&" property tax shift. The entry will include any general education aid to be recognized early if tax settlement receipts entered in section three are less than the gross shift amount." -> The fourth section provides information to make the year-end accounting entries for the fiscal year 2012 property tax shift. The entry will include any general education aid to be recognized early if tax settlement receipts entered in section three are less than the gross shift amount.
A56: Enter data on the Funds tab if you want to use the reconciliation feature in the Accounts tab.
B57: ="Enter certified levy by fund for payable "&RIGHT(P8,4)&" through "&RIGHT(P1,4)&" in the yellow highlighted section. Verify total certified levy. This data is used in the Accounts tab to automatically enter the certifed levy and to allocate abatements and adjustments." -> Enter certified levy by fund for payable 2005 through 2012 in the yellow highlighted section. Verify total certified levy. This data is used in the Accounts tab to automatically enter the certifed levy and to allocate abatements and adjustments.
B60: ="Enter tax settlements received during fiscal year "&RIGHT(R2,4)&" in the green highlighted section. The green outlined section below will then show each settlement allocated by fund. This data carries over as settlements received in the Accounts tab." -> Enter tax settlements received during fiscal year 2012 in the green highlighted section. The green outlined section below will then show each settlement allocated by fund. This data carries over as settlements received in the Accounts tab.
A63: The Accounts tab provides a year-end reconciliation for each tax-related account.
B64: This section shows how to determine the balance to be reflected in each account at year-end after all tax entries (including the property tax shift entries) have been made. Balance sheet accounts are listed first and then revenue source codes. Also shown is the source document where the data for each step of the reconcilation can be obtained.
B68: This tab can serve as a year-end reconcilation tool. Enter data in the highlighted fields on this tab and in the Funds tab. All other fields in this tab will automatically be computed.
A71: The Entries tab shows standard accounting entries for recording property taxes.
B72: The entries start with the levy being certified by the school board and work through a full year of accounting entries.
A74: The other tabs in this spreadsheet provide the data that is used to create the tax shift report shown in the Reports tab.
A76: If you have questions about the property tax shift or about using this spreadsheet, contact Terri Yetter by phone at 651-582-8868 or by e-mail at terri.yetter@state.mn.us.

Sheet Report
D1: PROPERTY TAX SHIFT YEAR-END RECONCILIATION | I1: 41115
D2: =Instructions!S2 -> 06/30/12
A3: 1.2 | B3: Enter District Number
B5: =VLOOKUP(A3,ShiftCY,3) -> MINNEAPOLIS
C6: 1 | D6: 2 | E6: 3 | F6: 4 | H6: 5 | I6: 6
C7: ="Gross Shift Amount "&Instructions!Q1 -> Gross Shift Amount 11 Pay 12 | D7: ="Replacement for "&Instructions!Q2&" Shift" -> Replacement for 10 Pay 11 Shift | E7: =Instructions!R2&" Revenue Adjust Src Code 001" -> FY 2012 Revenue Adjust Src Code 001 | F7: =Instructions!R2&" Net Shift Amount Src Code 020" -> FY 2012 Net Shift Amount Src Code 020 | H7: State Aid Adjustment Src Code 299 | I7: Revenue Adjustment Src Code 299
A9: A | B9: General - Shift & Adjust Aid | C9: =VLOOKUP($A$3,ShiftCY,4,FALSE) -> 11569510 | D9: =VLOOKUP($A$3,ShiftPY,4,FALSE) -> 14582222 | F9: =C9-D9 -> -3012712.2
A10: B | B10: General - Operating Referendum (with aid adjust) | C10: =VLOOKUP($A$3,ShiftCY,5,FALSE) -> 22730186 | D10: =VLOOKUP($A$3,ShiftPY,5,FALSE) -> 21821402 | F10: =C10-D10 -> 908784.28
A11: C | B11: General - Operating Referendum (no aid adjust) | C11: =VLOOKUP($A$3,ShiftCY,6,FALSE) -> 10049626 | D11: =VLOOKUP($A$3,ShiftPY,6,FALSE) -> 10049626 | E11: =C11-D11 -> 0
A12: D | B12: General - Addl Referendum Shift | C12: =VLOOKUP($A$3,ShiftCY,7,FALSE) -> 1205612.7 | D12: =VLOOKUP($A$3,ShiftPY,7,FALSE) -> 1205612.7 | E12: =C12-D12 -> 0
A13: E | B13: General - Career Technical | C13: =VLOOKUP($A$3,ShiftCY,8,FALSE) -> 551214.14 | D13: =VLOOKUP($A$3,ShiftPY,8,FALSE) -> 529738.02 | E13: =C13-D13 -> 21476.12
A14: F | B14: General - 100% Shift, No Adjust | C14: =VLOOKUP($A$3,ShiftCY,9,FALSE) -> 8657778.7 | D14: =VLOOKUP($A$3,ShiftPY,9,FALSE) -> 8867688.3 | E14: =C14-D14 -> -209909.61
A15: G | B15: General - Reemploy Ins (Reserved) | C15: =VLOOKUP($A$3,ShiftCY,10,FALSE) -> 0 | D15: =VLOOKUP($A$3,ShiftPY,10,FALSE) -> 0 | E15: =C15-D15 -> 0
A16: H | B16: General - Reemploy Ins (Unreserved) | C16: =VLOOKUP($A$3,ShiftCY,11,FALSE) -> 1774703.8 | D16: =VLOOKUP($A$3,ShiftPY,11,FALSE) -> 1757181.6 | E16: =C16-D16 -> 17522.16
A17: I | B17: General - Legislative Changes | C17: =VLOOKUP($A$3,ShiftCY,12,FALSE) -> 0 | D17: =VLOOKUP($A$3,ShiftPY,12,FALSE) -> 0 | E17: =C17-D17 -> 0
A18: J | B18: General Fund Total | C18: =SUM(C9:C17) -> 56538632 | D18: =SUM(D9:D17) -> 58813471 | E18: =SUM(E9:E17) -> -170911.33 | F18: =SUM(F9:F17) -> -2103927.9 | H18: =VLOOKUP($A$3,Ideas,4) -> 1703911.3 | I18: =-F18-H18 -> 400016.66
A20: K | B20: Comm Serv - Shift & Adjust Aid | C20: =VLOOKUP($A$3,ShiftCY,13,FALSE) -> 2395202 | D20: =VLOOKUP($A$3,ShiftPY,13,FALSE) -> 1994567.9 | F20: =C20-D20 -> 400634.03
A21: L | B21: Comm Serv - 100% Shift, No Adjust | C21: 0 | D21: 0 | E21: =C21-D21 -> 0
A22: M | B22: Comm Serv - Legislative Change | C22: =VLOOKUP($A$3,ShiftCY,14,FALSE) -> 0 | D22: =VLOOKUP($A$3,ShiftPY,14,FALSE) -> 0 | E22: =C22-D22 -> 0
A23: N | B23: Comm Serv Fund Total | C23: =SUM(C20:C22) -> 2395202 | D23: =SUM(D20:D22) -> 1994567.9 | E23: =SUM(E20:E22) -> 0 | F23: =SUM(F20:F22) -> 400634.03 | H23: =VLOOKUP($A$3,Ideas,5) -> 0 | I23: =-F23-H23 -> -400634.03
A26: O | B26: Total | C26: =C18+C23 -> 58933834 | D26: =D18+D23 -> 60808039 | E26: =E18+E23 -> -170911.33 | F26: =F18+F23 -> -1703293.9 | H26: =H18+H23 -> 1703911.3 | I26: =I18+I23 -> -617.37
A31: Definitions of levy categories within funds
A32: The following categories are mutually exclusive, that is, each levy appears in one category only.
B33: Shift & Adjust Aid | C33: ="For "&Instructions!P1&" this category includes all levies not identified below, shifted at 48.6%." -> For Pay 2012 this category includes all levies not identified below, shifted at 48.6%.
C34: ="For "&Instructions!P2&" this category includes all levies not identified below, shifted at 48.6%." -> For Pay 2011 this category includes all levies not identified below, shifted at 48.6%.
B35: Operating referendum (with aid adjust) | C35: ="For "&Instructions!P1&" this category is the greater of zero, or the "&Instructions!P1&" referendum levy shifted at 48.6% minus" -> For Pay 2012 this category is the greater of zero, or the Pay 2012 referendum levy shifted at 48.6% minus
C36: ="the Pay 2001 referendum shifted at 31%." -> the Pay 2001 referendum shifted at 31%.
B37: Operating referendum (no aid adjust) | C37: This category is the Pay 2001 referendum levy shifted at 31%. This amount will be constant from year to year.
B38: Addl referendum shift | C38: This is an additional revenue shift for districts that had a decrease in Pay 1994 referendum levy
C39: due to the net of changes in the allocation of HACA and the increase in referendum equalization aid.
C40: This amount will be constant from year to year.
B41: Career Technical | C41: Career technical levy and adjustment shifted at 100% with no aid adjustment.
B42: 100% shift, no adjust | C42: Includes levies that are shifted at 100% and for which there is no reduction to state aid. This category
C43: includes integration for first class districts, additional retirement, health benefits, and related adjustments.
B44: Reemploy Ins (reserved) | C44: Includes reemployment insurance levy adjustments for FY 2003 shifted at 100% with no aid adjustment.
B45: Reemploy Ins (unreserved) | C45: Includes reemployment insurance levy and adjustments for FY 2004 and later shifted at 100% with no aid adjustment.
B46: Legislative changes | C46: Includes selected levies that have been adjusted based on legislation that changes a levy authority after the levy has
C47: been certified (See Minnesota Statutes, section 126C.48, subdivision 6). The revenue shift is at 100% and there is
C48: ="no adjustment to state aids. For "&Instructions!P2&" and "&Instructions!P1&" this category is zero." -> no adjustment to state aids. For Pay 2011 and Pay 2012 this category is zero.
A52: =$A$3 -> 1.2 | B52: =VLOOKUP($A$3,ShiftCY,3) -> MINNEAPOLIS | I52: =Instructions!$M$1 -> 41115
A56: ASSUMPTIONS:
A58: 1) | B58: Property Taxes for Subsequent Years (GNL 235) entries have already taken place. Prior to the tax shift entries the balance
B59: ="in account 235 should equal the Certified "&Instructions!P1&" levy from the School Tax Report." -> in account 235 should equal the Certified Pay 2012 levy from the School Tax Report.
A63: 2) | B63: ="If the Advance of Unearned General Education Revenue (GNL 214) was used in "&Instructions!R3&", enough general ed payments should" -> If the Advance of Unearned General Education Revenue (GNL 214) was used in FY 2011, enough general ed payments should
B64: have been coded to 214 to zero out the account. If not, the following entry should be made:
E65: Debit | F65: Credit
A66: REV | B66: 01-005-000-000-211-000 | C66: Gen Ed Revenue | E66: =F68 -> 4894482
A67: REV | B67: 04-005-000-000-211-000 | C67: Gen Ed Revenue | E67: =F69 -> 0
A68: GNL | B68: 01-214 | C68: Adv of Unearned Gen Ed | F68: =-VLOOKUP($A$3,Ideas,7) -> 4894482
A69: GNL | B69: 04-214 | C69: Adv of Unearned Gen Ed | F69: =-VLOOKUP($A$3,Ideas,8) -> 0
A73: 3) | B73: ="The "&Instructions!R2&" tax shift payment adjustments reflected on the IDEAS reports should have been recorded to source 299." -> The FY 2012 tax shift payment adjustments reflected on the IDEAS reports should have been recorded to source 299.
B74: If not, the following entries should be made:
E75: Debit | F75: Credit
A76: REV | B76: 01-005-000-000-299-000 | C76: Prop Tax Shift Adjustment | E76: =IF(H18<=0,-H18," ") | F76: =IF(H18<=0," ",H18) -> 1703911.3
A77: REV | B77: 04-005-000-000-299-000 | C77: Prop Tax Shift Adjustment | E77: =IF(H23<=0,-H23," ") -> 0 | F77: =IF(H23<=0," ",H23)
A78: REV | B78: 01-005-000-XXX-XXX-000 | C78: State Aid Receivable or State Aid Revenue | E78: =F76 -> 1703911.3 | F78: =E76
A79: REV | B79: 04-005-000-XXX-XXX-000 | C79: State Aid Receivable or State Aid Revenue | E79: =F77 | F79: =E77 -> 0
A89: ="ENTER: May/June/July "&RIGHT(Instructions!R2,4)&" Receipts for:" -> ENTER: May/June/July 2012 Receipts for: | E89: General Fund | F89: Comm Service Fund
B91: =Instructions!P1&" Real Estate and Personal Property Taxes" -> Pay 2012 Real Estate and Personal Property Taxes | E91: =VLOOKUP($A3,Receipts!$A$8:$L$344,5,FALSE) -> 51621102 | F91: =VLOOKUP($A3,Receipts!$A$8:$L$344,10,FALSE) -> 2449575.5 | H91: Note: District should override when actual data is available
B92: =Instructions!P2&" and earlier Real Estate and Personal Property Taxes" -> Pay 2011 and earlier Real Estate and Personal Property Taxes | E92: 0 | F92: 0
B93: =Instructions!P1&" Fiscal Disparities" -> Pay 2012 Fiscal Disparities | E93: 0 | F93: 0
B94: =Instructions!P1&" Taconite Homestead Credit" -> Pay 2012 Taconite Homestead Credit | E94: 0 | F94: 0
B95: Mobile Home Taxes | E95: 0 | F95: 0
B97: Total May/June/July Tax Settlement Receipts | E97: =SUM(E91:E95) -> 51621102 | F97: =SUM(F91:F95) -> 2449575.5
A102: =$A$3 -> 1.2 | B102: =VLOOKUP($A$3,ShiftCY,3) -> MINNEAPOLIS | I102: =Instructions!$M$1 -> 41115
A104: ="Entry to record June "&RIGHT(Instructions!R2,4)&" property tax shift" -> Entry to record June 2012 property tax shift | E104: Debit (Credit) | F104: Credit (Debit)
A107: GNL | B107: 01-235 | C107: Prop Tax Sub Years | E107: =IF(C18<E97,C18,E97) -> 51621102 | H107: ="Column "&C6&" - line "&A18 -> Column 1 - line J
B108: 01-214 | C108: Adv of Unearned Gen Ed | E108: =IF(C18-E107<0,0,C18-E107) -> 4917530
A109: GNL | B109: 04-235 | C109: Prop Tax Sub Years | E109: =IF(C23<F97,C23,F97) -> 2395202 | H109: ="Column "&C6&" - line "&A23 -> Column 1 - line N
B110: 04-214 | C110: Adv of Unearned Gen Ed | E110: =C23-E109 -> 0
B111: ="(recognition of gross shift for "&Instructions!R2&")" -> (recognition of gross shift for FY 2012)
A113: REV | B113: 01-005-000-000-001-000 | C113: Local Property Taxes--Reemployment | F113: =C15 -> 0 | H113: ="Column "&C6&" - line "&A15 -> Column 1 - line G
A114: REV | B114: 01-005-000-830-001-000 | C114: Local Property Taxes--Career Technical | F114: =C13-F115 -> 551214.14 | H114: ="Column "&C6&" - line "&A13 -> Column 1 - line E
A115: REV | B115: 01-005-000-830-211-000 (if not enough tax receipts) | C115: Gen Ed Revenue--Career Technical | F115: =MIN(E108-F117,C13) -> 0
A116: REV | B116: 01-005-000-000-001-000 | C116: Local Property Taxes | F116: =C11+C12+C14+C16+C17-F117 -> 16770192 | H116: ="Column "&C6&" - line "&A11&"+"&A12&"+"&A14&"+"&A16&"+"&A17 -> Column 1 - line C+D+F+H+I
A117: REV | B117: 01-005-000-000-211-000 (if not enough tax receipts) | C117: Gen Ed Revenue | F117: =MIN(E108,MAX(0,C11+C12+C14+C16+C17)) -> 4917530
A118: REV | B118: 04-005-000-XXX-001-000 | C118: Local Property Taxes | F118: =C21+C22-F119 -> 0 | H118: ="Column "&C6&" - line "&A21&"+"&A22 -> Column 1 - line L+M
A119: REV | B119: 04-005-000-XXX-211-000 | C119: Gen Ed Revenue | F119: =E110 -> 0
B120: ="(spread of early recognition items for "&Instructions!R2&")" -> (spread of early recognition items for FY 2012)
A122: REV | B122: 01-005-000-000-211-000 | C122: Gen Ed Revenue | F122: =E108-F115-F117 -> 0 | H122: Entry to GNL 214 minus entries to SRC 211
A123: REV | B123: 01-005-000-000-296-000 | C123: Property Tax Shift Offset Adjustment | E123: =F122 -> 0
A124: REV | B124: 04-005-000-000-211-000 | C124: Gen Ed Revenue | F124: =E110-F119 -> 0 | H124: Entry toGNL 214 minus entries to SRC 211
A125: REV | B125: 04-005-000-000-296-000 | C125: Property Tax Shift Offset Adjustment | E125: =F124 -> 0
B126: (adjustment to balance GNL 214 account with SRC 211)
A128: REV | B128: 01-005-000-000-001-000 | C128: Local Property Taxes | F128: =D9+D10 -> 36403624 | H128: ="Column "&D6&" - line "&A9&"+"&A10 -> Column 2 - line A+B
A129: REV | B129: 04-005-000-XXX-001-000 | C129: Local Property Taxes | F129: =D20 -> 1994567.9 | H129: ="Column "&D6&" - line "&A20 -> Column 2 - line K
B130: (reverse prior year shift)
A132: REV | B132: 01-005-000-000-020-000 | C132: Prop Tax Shift Revenue | E132: =IF($F18<0,-$F18," ") -> 2103927.9 | F132: =IF($F18<0," ",$F18) | H132: ="Column "&F6&" - line "&A18 -> Column 4 - line J
A133: REV | B133: 04-005-000-000-020-000 | C133: Prop Tax Shift Revenue | E133: =IF($F23<0,-$F23," ") | F133: =IF($F23<0," ",$F23) -> 400634.03 | H133: ="Column "&F6&" - line "&A23 -> Column 4 - line N
B134: ="(spread of tax shift amount for "&Instructions!R2&")" -> (spread of tax shift amount for FY 2012)
B136: Total | E136: =SUM(E107:E135) -> 61037762 | F136: =SUM(F107:F135) -> 61037762
A141: REV | B141: 01-005-000-000-299-000 | C141: State Aid Adjustment for Shift | E141: =IF(I18<0,-I18," ") | F141: =IF(I18<0," ",I18) -> 400016.66 | H141: ="Column "&I6&" - line "&A18 -> Column 6 - line J
A142: GNL | B142: 01-101 | C142: Cash | E142: =F141 -> 400016.66 | F142: =E141
A143: REV | B143: 04-005-000-000-299-000 | C143: State Aid Adjustment for Shift | E143: =IF(I23<0,-I23," ") -> 400634.03 | F143: =IF(I23<0," ",I23) | H143: ="Column "&I6&" - line "&A23 -> Column 6 - line N
A144: GNL | B144: 04-101 | C144: Cash | E144: =F143 | F144: =E143 -> 400634.03
A145: GNL | B145: 01-213 | C145: Property Tax Shift Adjustment | E145: =F146 | F145: =E146 -> 617.37 | H145: ="Column "&I6&" - line "&A26 -> Column 6 - line O
A146: GNL | B146: 01-101 | C146: Cash | E146: =IF(I26<0,-I26," ") -> 617.37 | F146: =IF(I26<0," ",I26)
B147: (modification by fund to correct (increase or decrease) property tax shift adjustment and redistribution of prior adjustment per Ideas report)
B149: Total | E149: =SUM(E141:E148) -> 801268.06 | F149: =SUM(F141:F148) -> 801268.06

Sheet Funds
A1: Enter certified levies for each year below | K1: =Report!I1 -> 41115
A2: This data is used to report certified levies on Accounts tab
A3: Also used to allocate adjustments and abatements on Accounts tab
D6: Certified Levy
D7: =Instructions!P1 -> Pay 2012 | E7: =Instructions!P2 -> Pay 2011 | F7: =Instructions!P3 -> Pay 2010 | G7: =Instructions!P4 -> Pay 2009 | H7: =Instructions!P5 -> Pay 2008 | I7: =Instructions!P6 -> Pay 2007 | J7: =Instructions!P7 -> Pay 2006 | K7: =Instructions!P8 -> Pay 2005
B9: General | D9: 0 | E9: 0 | F9: 0 | G9: 0 | H9: 0 | I9: 0 | J9: 0 | K9: 0
B10: Community Serv | D10: 0 | E10: 0 | F10: 0 | G10: 0 | H10: 0 | I10: 0 | J10: 0 | K10: 0
B11: Debt Service | D11: 0 | E11: 0 | F11: 0 | G11: 0 | H11: 0 | I11: 0 | J11: 0 | K11: 0
B12: OPEB | D12: 0 | E12: 0 | F12: 0 | G12: 0 | H12: 0 | I12: 0 | J12: 0 | K12: 0
B14: Total Certified Levy | D14: =SUM(D9:D13) -> 0 | E14: =SUM(E9:E13) -> 0 | F14: =SUM(F9:F13) -> 0 | G14: =SUM(G9:G13) -> 0 | H14: =SUM(H9:H13) -> 0 | I14: =SUM(I9:I13) -> 0 | J14: =SUM(J9:J13) -> 0 | K14: =SUM(K9:K13) -> 0
A20: ="Enter each tax settlement received July 1, "&RIGHT(Instructions!P2,4)&" through June 30, "&RIGHT(Instructions!P1,4) -> Enter each tax settlement received July 1, 2011 through June 30, 2012
A21: Enter data in green highlighted cells
A22: If more columns are needed, insert between column M and S
A23: Amounts will be allocated to funds based upon certified levies above
A24: Settlements will be totaled by year and fund for carryover to Accounts tab
A26: If settlement sheet from the county already shows settlements by fund:
A27: Unprotect this tab and enter settlement data directly into cells E56 through S145, orange outlined section below
A28: Caution: You will be overriding the formulas in these cells
E32: County | F32: County | G32: County | H32: County | I32: County | J32: County | K32: County | L32: County | M32: County | N32: County | O32: County | P32: County | Q32: County | R32: County | S32: County
D33: Total | E33: Date | F33: Date | G33: Date | H33: Date | I33: Date | J33: Date | K33: Date | L33: Date | M33: Date | N33: Date | O33: Date | P33: Date | Q33: Date | R33: Date | S33: Date
A35: Taxes receivable | C35: =Instructions!P1 -> Pay 2012 | D35: =SUM(E35:S35) -> 0 | E35: 0 | F35: 0 | G35: 0 | H35: 0 | I35: 0 | J35: 0 | K35: 0 | L35: 0 | M35: 0 | N35: 0 | O35: 0 | P35: 0 | Q35: 0 | R35: 0 | S35: 0
C36: =Instructions!P2 -> Pay 2011 | D36: =SUM(E36:S36) -> 0 | E36: 0 | F36: 0 | G36: 0 | H36: 0 | I36: 0 | J36: 0 | K36: 0 | L36: 0 | M36: 0 | N36: 0 | O36: 0 | P36: 0 | Q36: 0 | R36: 0 | S36: 0
C37: =Instructions!P3 -> Pay 2010 | D37: =SUM(E37:S37) -> 0 | E37: 0 | F37: 0 | G37: 0 | H37: 0 | I37: 0 | J37: 0 | K37: 0 | L37: 0 | M37: 0 | N37: 0 | O37: 0 | P37: 0 | Q37: 0 | R37: 0 | S37: 0
C38: =Instructions!P4 -> Pay 2009 | D38: =SUM(E38:S38) -> 0 | E38: 0 | F38: 0 | G38: 0 | H38: 0 | I38: 0 | J38: 0 | K38: 0 | L38: 0 | M38: 0 | N38: 0 | O38: 0 | P38: 0 | Q38: 0 | R38: 0 | S38: 0
C39: =Instructions!P5 -> Pay 2008 | D39: =SUM(E39:S39) -> 0 | E39: 0 | F39: 0 | G39: 0 | H39: 0 | I39: 0 | J39: 0 | K39: 0 | L39: 0 | M39: 0 | N39: 0 | O39: 0 | P39: 0 | Q39: 0 | R39: 0 | S39: 0
C40: =Instructions!P6 -> Pay 2007 | D40: =SUM(E40:S40) -> 0 | E40: 0 | F40: 0 | G40: 0 | H40: 0 | I40: 0 | J40: 0 | K40: 0 | L40: 0 | M40: 0 | N40: 0 | O40: 0 | P40: 0 | Q40: 0 | R40: 0 | S40: 0
C41: =Instructions!P7 -> Pay 2006 | D41: =SUM(E41:S41) -> 0 | E41: 0 | F41: 0 | G41: 0 | H41: 0 | I41: 0 | J41: 0 | K41: 0 | L41: 0 | M41: 0 | N41: 0 | O41: 0 | P41: 0 | Q41: 0 | R41: 0 | S41: 0
C42: =Instructions!P8 -> Pay 2005 | D42: =SUM(E42:S42) -> 0 | E42: 0 | F42: 0 | G42: 0 | H42: 0 | I42: 0 | J42: 0 | K42: 0 | L42: 0 | M42: 0 | N42: 0 | O42: 0 | P42: 0 | Q42: 0 | R42: 0 | S42: 0
A43: Fiscal disparities | C43: =Instructions!P1 -> Pay 2012 | D43: =SUM(E43:S43) -> 0 | E43: 0 | F43: 0 | G43: 0 | H43: 0 | I43: 0 | J43: 0 | K43: 0 | L43: 0 | M43: 0 | N43: 0 | O43: 0 | P43: 0 | Q43: 0 | R43: 0 | S43: 0
C44: =Instructions!P2 -> Pay 2011 | D44: =SUM(E44:S44) -> 0 | E44: 0 | F44: 0 | G44: 0 | H44: 0 | I44: 0 | J44: 0 | K44: 0 | L44: 0 | M44: 0 | N44: 0 | O44: 0 | P44: 0 | Q44: 0 | R44: 0 | S44: 0
A45: Taconite homestead | C45: =Instructions!P1 -> Pay 2012 | D45: =SUM(E45:S45) -> 0 | E45: 0 | F45: 0 | G45: 0 | H45: 0 | I45: 0 | J45: 0 | K45: 0 | L45: 0 | M45: 0 | N45: 0 | O45: 0 | P45: 0 | Q45: 0 | R45: 0 | S45: 0
C46: =Instructions!P2 -> Pay 2011 | D46: =SUM(E46:S46) -> 0 | E46: 0 | F46: 0 | G46: 0 | H46: 0 | I46: 0 | J46: 0 | K46: 0 | L46: 0 | M46: 0 | N46: 0 | O46: 0 | P46: 0 | Q46: 0 | R46: 0 | S46: 0
A47: Miscellaneous taxes | E47: 0 | F47: 0 | G47: 0 | H47: 0 | I47: 0 | J47: 0 | K47: 0 | L47: 0 | M47: 0 | N47: 0 | O47: 0 | P47: 0 | Q47: 0 | R47: 0 | S47: 0
B49: Total settlement | D49: =SUM(D35:D48) -> 0 | E49: =SUM(E35:E48) -> 0 | F49: =SUM(F35:F48) -> 0 | G49: =SUM(G35:G48) -> 0 | H49: =SUM(H35:H48) -> 0 | I49: =SUM(I35:I48) -> 0 | J49: =SUM(J35:J48) -> 0 | K49: =SUM(K35:K48) -> 0 | ... S49: =SUM(S35:S48) -> 0
A55: Current Taxes receivable
B56: =Instructions!P1 -> Pay 2012 | C56: General | D56: =SUM(E56:S56) -> 0 | E56: =ROUND(IF($D$14=0,0,E$35/$D$14*$D9),2) -> 0 | F56: =ROUND(IF($D$14=0,0,F$35/$D$14*$D9),2) -> 0 | G56: =ROUND(IF($D$14=0,0,G$35/$D$14*$D9),2) -> 0 | H56: =ROUND(IF($D$14=0,0,H$35/$D$14*$D9),2) -> 0 | I56: =ROUND(IF($D$14=0,0,I$35/$D$14*$D9),2) -> 0 | J56: =ROUND(IF($D$14=0,0,J$35/$D$14*$D9),2) -> 0 | K56: =ROUND(IF($D$14=0,0,K$35/$D$14*$D9),2) -> 0 | L56: =ROUND(IF($D$14=0,0,L$35/$D$14*$D9),2) -> 0 | ... S56: =ROUND(IF($D$14=0,0,S$35/$D$14*$D9),2) -> 0
B57: =Instructions!P1 -> Pay 2012 | C57: Comm Serv | D57: =SUM(E57:S57) -> 0 | E57: =ROUND(IF($D$14=0,0,E$35/$D$14*$D10),2) -> 0 | F57: =ROUND(IF($D$14=0,0,F$35/$D$14*$D10),2) -> 0 | G57: =ROUND(IF($D$14=0,0,G$35/$D$14*$D10),2) -> 0 | H57: =ROUND(IF($D$14=0,0,H$35/$D$14*$D10),2) -> 0 | I57: =ROUND(IF($D$14=0,0,I$35/$D$14*$D10),2) -> 0 | J57: =ROUND(IF($D$14=0,0,J$35/$D$14*$D10),2) -> 0 | K57: =ROUND(IF($D$14=0,0,K$35/$D$14*$D10),2) -> 0 | L57: =ROUND(IF($D$14=0,0,L$35/$D$14*$D10),2) -> 0 | ... S57: =ROUND(IF($D$14=0,0,S$35/$D$14*$D10),2) -> 0
B58: =Instructions!P1 -> Pay 2012 | C58: Debt Serv | D58: =SUM(E58:S58) -> 0 | E58: =ROUND(IF($D$14=0,0,E$35/$D$14*$D11),2) -> 0 | F58: =ROUND(IF($D$14=0,0,F$35/$D$14*$D11),2) -> 0 | G58: =ROUND(IF($D$14=0,0,G$35/$D$14*$D11),2) -> 0 | H58: =ROUND(IF($D$14=0,0,H$35/$D$14*$D11),2) -> 0 | I58: =ROUND(IF($D$14=0,0,I$35/$D$14*$D11),2) -> 0 | J58: =ROUND(IF($D$14=0,0,J$35/$D$14*$D11),2) -> 0 | K58: =ROUND(IF($D$14=0,0,K$35/$D$14*$D11),2) -> 0 | L58: =ROUND(IF($D$14=0,0,L$35/$D$14*$D11),2) -> 0 | ... S58: =ROUND(IF($D$14=0,0,S$35/$D$14*$D11),2) -> 0
B59: =Instructions!P1 -> Pay 2012 | C59: OPEB | D59: =SUM(E59:S59) -> 0 | E59: =ROUND(IF($D$14=0,0,E$35/$D$14*$D12),2) -> 0 | F59: =ROUND(IF($D$14=0,0,F$35/$D$14*$D12),2) -> 0 | G59: =ROUND(IF($D$14=0,0,G$35/$D$14*$D12),2) -> 0 | H59: =ROUND(IF($D$14=0,0,H$35/$D$14*$D12),2) -> 0 | I59: =ROUND(IF($D$14=0,0,I$35/$D$14*$D12),2) -> 0 | J59: =ROUND(IF($D$14=0,0,J$35/$D$14*$D12),2) -> 0 | K59: =ROUND(IF($D$14=0,0,K$35/$D$14*$D12),2) -> 0 | L59: =ROUND(IF($D$14=0,0,L$35/$D$14*$D12),2) -> 0 | ... S59: =ROUND(IF($D$14=0,0,S$35/$D$14*$D12),2) -> 0
C61: Subtotal | D61: =SUM(D56:D60) -> 0 | E61: =SUM(E56:E60) -> 0 | F61: =SUM(F56:F60) -> 0 | G61: =SUM(G56:G60) -> 0 | H61: =SUM(H56:H60) -> 0 | I61: =SUM(I56:I60) -> 0 | J61: =SUM(J56:J60) -> 0 | K61: =SUM(K56:K60) -> 0 | ... S61: =SUM(S56:S60) -> 0
A64: Delinquent Taxes receivable
B65: =Instructions!P2 -> Pay 2011 | C65: General | D65: =SUM(E65:S65) -> 0 | E65: =ROUND(IF($E$14=0,0,E$36/$E$14*$E9),2) -> 0 | F65: =ROUND(IF($E$14=0,0,F$36/$E$14*$E9),2) -> 0 | G65: =ROUND(IF($E$14=0,0,G$36/$E$14*$E9),2) -> 0 | H65: =ROUND(IF($E$14=0,0,H$36/$E$14*$E9),2) -> 0 | I65: =ROUND(IF($E$14=0,0,I$36/$E$14*$E9),2) -> 0 | J65: =ROUND(IF($E$14=0,0,J$36/$E$14*$E9),2) -> 0 | K65: =ROUND(IF($E$14=0,0,K$36/$E$14*$E9),2) -> 0 | L65: =ROUND(IF($E$14=0,0,L$36/$E$14*$E9),2) -> 0 | ... S65: =ROUND(IF($E$14=0,0,S$36/$E$14*$E9),2) -> 0
B66: =Instructions!P3 -> Pay 2010 | C66: General | D66: =SUM(E66:S66) -> 0 | E66: =ROUND(IF($F$14=0,0,E$37/$F$14*$F9),2) -> 0 | F66: =ROUND(IF($F$14=0,0,F$37/$F$14*$F9),2) -> 0 | G66: =ROUND(IF($F$14=0,0,G$37/$F$14*$F9),2) -> 0 | H66: =ROUND(IF($F$14=0,0,H$37/$F$14*$F9),2) -> 0 | I66: =ROUND(IF($F$14=0,0,I$37/$F$14*$F9),2) -> 0 | J66: =ROUND(IF($F$14=0,0,J$37/$F$14*$F9),2) -> 0 | K66: =ROUND(IF($F$14=0,0,K$37/$F$14*$F9),2) -> 0 | L66: =ROUND(IF($F$14=0,0,L$37/$F$14*$F9),2) -> 0 | ... S66: =ROUND(IF($F$14=0,0,S$37/$F$14*$F9),2) -> 0
B67: =Instructions!P4 -> Pay 2009 | C67: General | D67: =SUM(E67:S67) -> 0 | E67: =ROUND(IF($G$14=0,0,E$38/$G$14*$G9),2) -> 0 | F67: =ROUND(IF($G$14=0,0,F$38/$G$14*$G9),2) -> 0 | G67: =ROUND(IF($G$14=0,0,G$38/$G$14*$G9),2) -> 0 | H67: =ROUND(IF($G$14=0,0,H$38/$G$14*$G9),2) -> 0 | I67: =ROUND(IF($G$14=0,0,I$38/$G$14*$G9),2) -> 0 | J67: =ROUND(IF($G$14=0,0,J$38/$G$14*$G9),2) -> 0 | K67: =ROUND(IF($G$14=0,0,K$38/$G$14*$G9),2) -> 0 | L67: =ROUND(IF($G$14=0,0,L$38/$G$14*$G9),2) -> 0 | ... S67: =ROUND(IF($G$14=0,0,S$38/$G$14*$G9),2) -> 0
B68: =Instructions!P5 -> Pay 2008 | C68: General | D68: =SUM(E68:S68) -> 0 | E68: =ROUND(IF($H$14=0,0,E$39/$H$14*$H9),2) -> 0 | F68: =ROUND(IF($H$14=0,0,F$39/$H$14*$H9),2) -> 0 | G68: =ROUND(IF($H$14=0,0,G$39/$H$14*$H9),2) -> 0 | H68: =ROUND(IF($H$14=0,0,H$39/$H$14*$H9),2) -> 0 | I68: =ROUND(IF($H$14=0,0,I$39/$H$14*$H9),2) -> 0 | J68: =ROUND(IF($H$14=0,0,J$39/$H$14*$H9),2) -> 0 | K68: =ROUND(IF($H$14=0,0,K$39/$H$14*$H9),2) -> 0 | L68: =ROUND(IF($H$14=0,0,L$39/$H$14*$H9),2) -> 0 | ... S68: =ROUND(IF($H$14=0,0,S$39/$H$14*$H9),2) -> 0
B69: =Instructions!P6 -> Pay 2007 | C69: General | D69: =SUM(E69:S69) -> 0 | E69: =ROUND(IF($I$14=0,0,E$40/$I$14*$I9),2) -> 0 | F69: =ROUND(IF($I$14=0,0,F$40/$I$14*$I9),2) -> 0 | G69: =ROUND(IF($I$14=0,0,G$40/$I$14*$I9),2) -> 0 | H69: =ROUND(IF($I$14=0,0,H$40/$I$14*$I9),2) -> 0 | I69: =ROUND(IF($I$14=0,0,I$40/$I$14*$I9),2) -> 0 | J69: =ROUND(IF($I$14=0,0,J$40/$I$14*$I9),2) -> 0 | K69: =ROUND(IF($I$14=0,0,K$40/$I$14*$I9),2) -> 0 | L69: =ROUND(IF($I$14=0,0,L$40/$I$14*$I9),2) -> 0 | ... S69: =ROUND(IF($I$14=0,0,S$40/$I$14*$I9),2) -> 0
B70: =Instructions!P7 -> Pay 2006 | C70: General | D70: =SUM(E70:S70) -> 0 | E70: =ROUND(IF($J$14=0,0,E$41/$J$14*$J9),2) -> 0 | F70: =ROUND(IF($J$14=0,0,F$41/$J$14*$J9),2) -> 0 | G70: =ROUND(IF($J$14=0,0,G$41/$J$14*$J9),2) -> 0 | H70: =ROUND(IF($J$14=0,0,H$41/$J$14*$J9),2) -> 0 | I70: =ROUND(IF($J$14=0,0,I$41/$J$14*$J9),2) -> 0 | J70: =ROUND(IF($J$14=0,0,J$41/$J$14*$J9),2) -> 0 | K70: =ROUND(IF($J$14=0,0,K$41/$J$14*$J9),2) -> 0 | L70: =ROUND(IF($J$14=0,0,L$41/$J$14*$J9),2) -> 0 | ... S70: =ROUND(IF($J$14=0,0,S$41/$J$14*$J9),2) -> 0
B71: =Instructions!P8 -> Pay 2005 | C71: General | D71: =SUM(E71:S71) -> 0 | E71: =ROUND(IF($K$14=0,0,E$42/$K$14*$K9),2) -> 0 | F71: =ROUND(IF($K$14=0,0,F$42/$K$14*$K9),2) -> 0 | G71: =ROUND(IF($K$14=0,0,G$42/$K$14*$K9),2) -> 0 | H71: =ROUND(IF($K$14=0,0,H$42/$K$14*$K9),2) -> 0 | I71: =ROUND(IF($K$14=0,0,I$42/$K$14*$K9),2) -> 0 | J71: =ROUND(IF($K$14=0,0,J$42/$K$14*$K9),2) -> 0 | K71: =ROUND(IF($K$14=0,0,K$42/$K$14*$K9),2) -> 0 | L71: =ROUND(IF($K$14=0,0,L$42/$K$14*$K9),2) -> 0 | ... S71: =ROUND(IF($K$14=0,0,S$42/$K$14*$K9),2) -> 0
C73: Subtotal | D73: =SUM(D65:D72) -> 0 | E73: =SUM(E65:E72) -> 0 | F73: =SUM(F65:F72) -> 0 | G73: =SUM(G65:G72) -> 0 | H73: =SUM(H65:H72) -> 0 | I73: =SUM(I65:I72) -> 0 | J73: =SUM(J65:J72) -> 0 | K73: =SUM(K65:K72) -> 0 | ... S73: =SUM(S65:S72) -> 0
B76: =Instructions!P2 -> Pay 2011 | C76: Comm Serv | D76: =SUM(E76:S76) -> 0 | E76: =ROUND(IF($E$14=0,0,E$36/$E$14*$E10),2) -> 0 | F76: =ROUND(IF($E$14=0,0,F$36/$E$14*$E10),2) -> 0 | G76: =ROUND(IF($E$14=0,0,G$36/$E$14*$E10),2) -> 0 | H76: =ROUND(IF($E$14=0,0,H$36/$E$14*$E10),2) -> 0 | I76: =ROUND(IF($E$14=0,0,I$36/$E$14*$E10),2) -> 0 | J76: =ROUND(IF($E$14=0,0,J$36/$E$14*$E10),2) -> 0 | K76: =ROUND(IF($E$14=0,0,K$36/$E$14*$E10),2) -> 0 | L76: =ROUND(IF($E$14=0,0,L$36/$E$14*$E10),2) -> 0 | ... S76: =ROUND(IF($E$14=0,0,S$36/$E$14*$E10),2) -> 0
B77: =Instructions!P3 -> Pay 2010 | C77: Comm Serv | D77: =SUM(E77:S77) -> 0 | E77: =ROUND(IF($F$14=0,0,E$37/$F$14*$F10),2) -> 0 | F77: =ROUND(IF($F$14=0,0,F$37/$F$14*$F10),2) -> 0 | G77: =ROUND(IF($F$14=0,0,G$37/$F$14*$F10),2) -> 0 | H77: =ROUND(IF($F$14=0,0,H$37/$F$14*$F10),2) -> 0 | I77: =ROUND(IF($F$14=0,0,I$37/$F$14*$F10),2) -> 0 | J77: =ROUND(IF($F$14=0,0,J$37/$F$14*$F10),2) -> 0 | K77: =ROUND(IF($F$14=0,0,K$37/$F$14*$F10),2) -> 0 | L77: =ROUND(IF($F$14=0,0,L$37/$F$14*$F10),2) -> 0 | ... S77: =ROUND(IF($F$14=0,0,S$37/$F$14*$F10),2) -> 0
B78: =Instructions!P4 -> Pay 2009 | C78: Comm Serv | D78: =SUM(E78:S78) -> 0 | E78: =ROUND(IF($G$14=0,0,E$38/$G$14*$G10),2) -> 0 | F78: =ROUND(IF($G$14=0,0,F$38/$G$14*$G10),2) -> 0 | G78: =ROUND(IF($G$14=0,0,G$38/$G$14*$G10),2) -> 0 | H78: =ROUND(IF($G$14=0,0,H$38/$G$14*$G10),2) -> 0 | I78: =ROUND(IF($G$14=0,0,I$38/$G$14*$G10),2) -> 0 | J78: =ROUND(IF($G$14=0,0,J$38/$G$14*$G10),2) -> 0 | K78: =ROUND(IF($G$14=0,0,K$38/$G$14*$G10),2) -> 0 | L78: =ROUND(IF($G$14=0,0,L$38/$G$14*$G10),2) -> 0 | ... S78: =ROUND(IF($G$14=0,0,S$38/$G$14*$G10),2) -> 0
B79: =Instructions!P5 -> Pay 2008 | C79: Comm Serv | D79: =SUM(E79:S79) -> 0 | E79: =ROUND(IF($H$14=0,0,E$39/$H$14*$H10),2) -> 0 | F79: =ROUND(IF($H$14=0,0,F$39/$H$14*$H10),2) -> 0 | G79: =ROUND(IF($H$14=0,0,G$39/$H$14*$H10),2) -> 0 | H79: =ROUND(IF($H$14=0,0,H$39/$H$14*$H10),2) -> 0 | I79: =ROUND(IF($H$14=0,0,I$39/$H$14*$H10),2) -> 0 | J79: =ROUND(IF($H$14=0,0,J$39/$H$14*$H10),2) -> 0 | K79: =ROUND(IF($H$14=0,0,K$39/$H$14*$H10),2) -> 0 | L79: =ROUND(IF($H$14=0,0,L$39/$H$14*$H10),2) -> 0 | ... S79: =ROUND(IF($H$14=0,0,S$39/$H$14*$H10),2) -> 0
B80: =Instructions!P6 -> Pay 2007 | C80: Comm Serv | D80: =SUM(E80:S80) -> 0 | E80: =ROUND(IF($I$14=0,0,E$40/$I$14*$I10),2) -> 0 | F80: =ROUND(IF($I$14=0,0,F$40/$I$14*$I10),2) -> 0 | G80: =ROUND(IF($I$14=0,0,G$40/$I$14*$I10),2) -> 0 | H80: =ROUND(IF($I$14=0,0,H$40/$I$14*$I10),2) -> 0 | I80: =ROUND(IF($I$14=0,0,I$40/$I$14*$I10),2) -> 0 | J80: =ROUND(IF($I$14=0,0,J$40/$I$14*$I10),2) -> 0 | K80: =ROUND(IF($I$14=0,0,K$40/$I$14*$I10),2) -> 0 | L80: =ROUND(IF($I$14=0,0,L$40/$I$14*$I10),2) -> 0 | ... S80: =ROUND(IF($I$14=0,0,S$40/$I$14*$I10),2) -> 0
B81: =Instructions!P7 -> Pay 2006 | C81: Comm Serv | D81: =SUM(E81:S81) -> 0 | E81: =ROUND(IF($J$14=0,0,E$41/$J$14*$J10),2) -> 0 | F81: =ROUND(IF($J$14=0,0,F$41/$J$14*$J10),2) -> 0 | G81: =ROUND(IF($J$14=0,0,G$41/$J$14*$J10),2) -> 0 | H81: =ROUND(IF($J$14=0,0,H$41/$J$14*$J10),2) -> 0 | I81: =ROUND(IF($J$14=0,0,I$41/$J$14*$J10),2) -> 0 | J81: =ROUND(IF($J$14=0,0,J$41/$J$14*$J10),2) -> 0 | K81: =ROUND(IF($J$14=0,0,K$41/$J$14*$J10),2) -> 0 | L81: =ROUND(IF($J$14=0,0,L$41/$J$14*$J10),2) -> 0 | ... S81: =ROUND(IF($J$14=0,0,S$41/$J$14*$J10),2) -> 0
B82: =Instructions!P8 -> Pay 2005 | C82: Comm Serv | D82: =SUM(E82:S82) -> 0 | E82: =ROUND(IF($K$14=0,0,E$42/$K$14*$K10),2) -> 0 | F82: =ROUND(IF($K$14=0,0,F$42/$K$14*$K10),2) -> 0 | G82: =ROUND(IF($K$14=0,0,G$42/$K$14*$K10),2) -> 0 | H82: =ROUND(IF($K$14=0,0,H$42/$K$14*$K10),2) -> 0 | I82: =ROUND(IF($K$14=0,0,I$42/$K$14*$K10),2) -> 0 | J82: =ROUND(IF($K$14=0,0,J$42/$K$14*$K10),2) -> 0 | K82: =ROUND(IF($K$14=0,0,K$42/$K$14*$K10),2) -> 0 | L82: =ROUND(IF($K$14=0,0,L$42/$K$14*$K10),2) -> 0 | ... S82: =ROUND(IF($K$14=0,0,S$42/$K$14*$K10),2) -> 0
C84: Subtotal | D84: =SUM(D76:D83) -> 0 | E84: =SUM(E76:E83) -> 0 | F84: =SUM(F76:F83) -> 0 | G84: =SUM(G76:G83) -> 0 | H84: =SUM(H76:H83) -> 0 | I84: =SUM(I76:I83) -> 0 | J84: =SUM(J76:J83) -> 0 | K84: =SUM(K76:K83) -> 0 | ... S84: =SUM(S76:S83) -> 0
B87: =Instructions!P2 -> Pay 2011 | C87: Debt Serv | D87: =SUM(E87:S87) -> 0 | E87: =ROUND(IF($E$14=0,0,E$36/$E$14*$E11),2) -> 0 | F87: =ROUND(IF($E$14=0,0,F$36/$E$14*$E11),2) -> 0 | G87: =ROUND(IF($E$14=0,0,G$36/$E$14*$E11),2) -> 0 | H87: =ROUND(IF($E$14=0,0,H$36/$E$14*$E11),2) -> 0 | I87: =ROUND(IF($E$14=0,0,I$36/$E$14*$E11),2) -> 0 | J87: =ROUND(IF($E$14=0,0,J$36/$E$14*$E11),2) -> 0 | K87: =ROUND(IF($E$14=0,0,K$36/$E$14*$E11),2) -> 0 | L87: =ROUND(IF($E$14=0,0,L$36/$E$14*$E11),2) -> 0 | ... S87: =ROUND(IF($E$14=0,0,S$36/$E$14*$E11),2) -> 0
B88: =Instructions!P3 -> Pay 2010 | C88: Debt Serv | D88: =SUM(E88:S88) -> 0 | E88: =ROUND(IF($F$14=0,0,E$37/$F$14*$F11),2) -> 0 | F88: =ROUND(IF($F$14=0,0,F$37/$F$14*$F11),2) -> 0 | G88: =ROUND(IF($F$14=0,0,G$37/$F$14*$F11),2) -> 0 | H88: =ROUND(IF($F$14=0,0,H$37/$F$14*$F11),2) -> 0 | I88: =ROUND(IF($F$14=0,0,I$37/$F$14*$F11),2) -> 0 | J88: =ROUND(IF($F$14=0,0,J$37/$F$14*$F11),2) -> 0 | K88: =ROUND(IF($F$14=0,0,K$37/$F$14*$F11),2) -> 0 | L88: =ROUND(IF($F$14=0,0,L$37/$F$14*$F11),2) -> 0 | ... S88: =ROUND(IF($F$14=0,0,S$37/$F$14*$F11),2) -> 0
B89: =Instructions!P4 -> Pay 2009 | C89: Debt Serv | D89: =SUM(E89:S89) -> 0 | E89: =ROUND(IF($G$14=0,0,E$38/$G$14*$G11),2) -> 0 | F89: =ROUND(IF($G$14=0,0,F$38/$G$14*$G11),2) -> 0 | G89: =ROUND(IF($G$14=0,0,G$38/$G$14*$G11),2) -> 0 | H89: =ROUND(IF($G$14=0,0,H$38/$G$14*$G11),2) -> 0 | I89: =ROUND(IF($G$14=0,0,I$38/$G$14*$G11),2) -> 0 | J89: =ROUND(IF($G$14=0,0,J$38/$G$14*$G11),2) -> 0 | K89: =ROUND(IF($G$14=0,0,K$38/$G$14*$G11),2) -> 0 | L89: =ROUND(IF($G$14=0,0,L$38/$G$14*$G11),2) -> 0 | ... S89: =ROUND(IF($G$14=0,0,S$38/$G$14*$G11),2) -> 0
B90: =Instructions!P5 -> Pay 2008 | C90: Debt Serv | D90: =SUM(E90:S90) -> 0 | E90: =ROUND(IF($H$14=0,0,E$39/$H$14*$H11),2) -> 0 | F90: =ROUND(IF($H$14=0,0,F$39/$H$14*$H11),2) -> 0 | G90: =ROUND(IF($H$14=0,0,G$39/$H$14*$H11),2) -> 0 | H90: =ROUND(IF($H$14=0,0,H$39/$H$14*$H11),2) -> 0 | I90: =ROUND(IF($H$14=0,0,I$39/$H$14*$H11),2) -> 0 | J90: =ROUND(IF($H$14=0,0,J$39/$H$14*$H11),2) -> 0 | K90: =ROUND(IF($H$14=0,0,K$39/$H$14*$H11),2) -> 0 | L90: =ROUND(IF($H$14=0,0,L$39/$H$14*$H11),2) -> 0 | ... S90: =ROUND(IF($H$14=0,0,S$39/$H$14*$H11),2) -> 0
B91: =Instructions!P6 -> Pay 2007 | C91: Debt Serv | D91: =SUM(E91:S91) -> 0 | E91: =ROUND(IF($I$14=0,0,E$40/$I$14*$I11),2) -> 0 | F91: =ROUND(IF($I$14=0,0,F$40/$I$14*$I11),2) -> 0 | G91: =ROUND(IF($I$14=0,0,G$40/$I$14*$I11),2) -> 0 | H91: =ROUND(IF($I$14=0,0,H$40/$I$14*$I11),2) -> 0 | I91: =ROUND(IF($I$14=0,0,I$40/$I$14*$I11),2) -> 0 | J91: =ROUND(IF($I$14=0,0,J$40/$I$14*$I11),2) -> 0 | K91: =ROUND(IF($I$14=0,0,K$40/$I$14*$I11),2) -> 0 | L91: =ROUND(IF($I$14=0,0,L$40/$I$14*$I11),2) -> 0 | ... S91: =ROUND(IF($I$14=0,0,S$40/$I$14*$I11),2) -> 0
B92: =Instructions!P7 -> Pay 2006 | C92: Debt Serv | D92: =SUM(E92:S92) -> 0 | E92: =ROUND(IF($J$14=0,0,E$41/$J$14*$J11),2) -> 0 | F92: =ROUND(IF($J$14=0,0,F$41/$J$14*$J11),2) -> 0 | G92: =ROUND(IF($J$14=0,0,G$41/$J$14*$J11),2) -> 0 | H92: =ROUND(IF($J$14=0,0,H$41/$J$14*$J11),2) -> 0 | I92: =ROUND(IF($J$14=0,0,I$41/$J$14*$J11),2) -> 0 | J92: =ROUND(IF($J$14=0,0,J$41/$J$14*$J11),2) -> 0 | K92: =ROUND(IF($J$14=0,0,K$41/$J$14*$J11),2) -> 0 | L92: =ROUND(IF($J$14=0,0,L$41/$J$14*$J11),2) -> 0 | ... S92: =ROUND(IF($J$14=0,0,S$41/$J$14*$J11),2) -> 0
B93: =Instructions!P8 -> Pay 2005 | C93: Debt Serv | D93: =SUM(E93:S93) -> 0 | E93: =ROUND(IF($K$14=0,0,E$42/$K$14*$K11),2) -> 0 | F93: =ROUND(IF($K$14=0,0,F$42/$K$14*$K11),2) -> 0 | G93: =ROUND(IF($K$14=0,0,G$42/$K$14*$K11),2) -> 0 | H93: =ROUND(IF($K$14=0,0,H$42/$K$14*$K11),2) -> 0 | I93: =ROUND(IF($K$14=0,0,I$42/$K$14*$K11),2) -> 0 | J93: =ROUND(IF($K$14=0,0,J$42/$K$14*$K11),2) -> 0 | K93: =ROUND(IF($K$14=0,0,K$42/$K$14*$K11),2) -> 0 | L93: =ROUND(IF($K$14=0,0,L$42/$K$14*$K11),2) -> 0 | ... S93: =ROUND(IF($K$14=0,0,S$42/$K$14*$K11),2) -> 0
C95: Subtotal | D95: =SUM(D87:D94) -> 0 | E95: =SUM(E87:E94) -> 0 | F95: =SUM(F87:F94) -> 0 | G95: =SUM(G87:G94) -> 0 | H95: =SUM(H87:H94) -> 0 | I95: =SUM(I87:I94) -> 0 | J95: =SUM(J87:J94) -> 0 | K95: =SUM(K87:K94) -> 0 | ... S95: =SUM(S87:S94) -> 0
B98: =Instructions!P2 -> Pay 2011 | C98: OPEB | D98: =SUM(E98:S98) -> 0 | E98: =ROUND(IF($E$14=0,0,E$36/$E$14*$E12),2) -> 0 | F98: =ROUND(IF($E$14=0,0,F$36/$E$14*$E12),2) -> 0 | G98: =ROUND(IF($E$14=0,0,G$36/$E$14*$E12),2) -> 0 | H98: =ROUND(IF($E$14=0,0,H$36/$E$14*$E12),2) -> 0 | I98: =ROUND(IF($E$14=0,0,I$36/$E$14*$E12),2) -> 0 | J98: =ROUND(IF($E$14=0,0,J$36/$E$14*$E12),2) -> 0 | K98: =ROUND(IF($E$14=0,0,K$36/$E$14*$E12),2) -> 0 | L98: =ROUND(IF($E$14=0,0,L$36/$E$14*$E12),2) -> 0 | ... S98: =ROUND(IF($E$14=0,0,S$36/$E$14*$E12),2) -> 0
B99: =Instructions!P3 -> Pay 2010 | C99: OPEB | D99: =SUM(E99:S99) -> 0 | E99: =ROUND(IF($F$14=0,0,E$37/$F$14*$F12),2) -> 0 | F99: =ROUND(IF($F$14=0,0,F$37/$F$14*$F12),2) -> 0 | G99: =ROUND(IF($F$14=0,0,G$37/$F$14*$F12),2) -> 0 | H99: =ROUND(IF($F$14=0,0,H$37/$F$14*$F12),2) -> 0 | I99: =ROUND(IF($F$14=0,0,I$37/$F$14*$F12),2) -> 0 | J99: =ROUND(IF($F$14=0,0,J$37/$F$14*$F12),2) -> 0 | K99: =ROUND(IF($F$14=0,0,K$37/$F$14*$F12),2) -> 0 | L99: =ROUND(IF($F$14=0,0,L$37/$F$14*$F12),2) -> 0 | ... S99: =ROUND(IF($F$14=0,0,S$37/$F$14*$F12),2) -> 0
B100: =Instructions!P4 -> Pay 2009 | C100: OPEB | D100: =SUM(E100:S100) -> 0 | E100: =ROUND(IF($G$14=0,0,E$38/$G$14*$G12),2) -> 0 | F100: =ROUND(IF($G$14=0,0,F$38/$G$14*$G12),2) -> 0 | G100: =ROUND(IF($G$14=0,0,G$38/$G$14*$G12),2) -> 0 | H100: =ROUND(IF($G$14=0,0,H$38/$G$14*$G12),2) -> 0 | I100: =ROUND(IF($G$14=0,0,I$38/$G$14*$G12),2) -> 0 | J100: =ROUND(IF($G$14=0,0,J$38/$G$14*$G12),2) -> 0 | K100: =ROUND(IF($G$14=0,0,K$38/$G$14*$G12),2) -> 0 | L100: =ROUND(IF($G$14=0,0,L$38/$G$14*$G12),2) -> 0 | ... S100: =ROUND(IF($G$14=0,0,S$38/$G$14*$G12),2) -> 0
B101: =Instructions!P5 -> Pay 2008 | C101: OPEB | D101: =SUM(E101:S101) -> 0 | E101: =ROUND(IF($H$14=0,0,E$39/$H$14*$H12),2) -> 0 | F101: =ROUND(IF($H$14=0,0,F$39/$H$14*$H12),2) -> 0 | G101: =ROUND(IF($H$14=0,0,G$39/$H$14*$H12),2) -> 0 | H101: =ROUND(IF($H$14=0,0,H$39/$H$14*$H12),2) -> 0 | I101: =ROUND(IF($H$14=0,0,I$39/$H$14*$H12),2) -> 0 | J101: =ROUND(IF($H$14=0,0,J$39/$H$14*$H12),2) -> 0 | K101: =ROUND(IF($H$14=0,0,K$39/$H$14*$H12),2) -> 0 | L101: =ROUND(IF($H$14=0,0,L$39/$H$14*$H12),2) -> 0 | ... S101: =ROUND(IF($H$14=0,0,S$39/$H$14*$H12),2) -> 0
B102: =Instructions!P6 -> Pay 2007 | C102: OPEB | D102: =SUM(E102:S102) -> 0 | E102: =ROUND(IF($I$14=0,0,E$40/$I$14*$I12),2) -> 0 | F102: =ROUND(IF($I$14=0,0,F$40/$I$14*$I12),2) -> 0 | G102: =ROUND(IF($I$14=0,0,G$40/$I$14*$I12),2) -> 0 | H102: =ROUND(IF($I$14=0,0,H$40/$I$14*$I12),2) -> 0 | I102: =ROUND(IF($I$14=0,0,I$40/$I$14*$I12),2) -> 0 | J102: =ROUND(IF($I$14=0,0,J$40/$I$14*$I12),2) -> 0 | K102: =ROUND(IF($I$14=0,0,K$40/$I$14*$I12),2) -> 0 | L102: =ROUND(IF($I$14=0,0,L$40/$I$14*$I12),2) -> 0 | ... S102: =ROUND(IF($I$14=0,0,S$40/$I$14*$I12),2) -> 0
B103: =Instructions!P7 -> Pay 2006 | C103: OPEB | D103: =SUM(E103:S103) -> 0 | E103: =ROUND(IF($J$14=0,0,E$41/$J$14*$J12),2) -> 0 | F103: =ROUND(IF($J$14=0,0,F$41/$J$14*$J12),2) -> 0 | G103: =ROUND(IF($J$14=0,0,G$41/$J$14*$J12),2) -> 0 | H103: =ROUND(IF($J$14=0,0,H$41/$J$14*$J12),2) -> 0 | I103: =ROUND(IF($J$14=0,0,I$41/$J$14*$J12),2) -> 0 | J103: =ROUND(IF($J$14=0,0,J$41/$J$14*$J12),2) -> 0 | K103: =ROUND(IF($J$14=0,0,K$41/$J$14*$J12),2) -> 0 | L103: =ROUND(IF($J$14=0,0,L$41/$J$14*$J12),2) -> 0 | ... S103: =ROUND(IF($J$14=0,0,S$41/$J$14*$J12),2) -> 0
B104: =Instructions!P8 -> Pay 2005 | C104: OPEB | D104: =SUM(E104:S104) -> 0 | E104: =ROUND(IF($K$14=0,0,E$42/$K$14*$K12),2) -> 0 | F104: =ROUND(IF($K$14=0,0,F$42/$K$14*$K12),2) -> 0 | G104: =ROUND(IF($K$14=0,0,G$42/$K$14*$K12),2) -> 0 | H104: =ROUND(IF($K$14=0,0,H$42/$K$14*$K12),2) -> 0 | I104: =ROUND(IF($K$14=0,0,I$42/$K$14*$K12),2) -> 0 | J104: =ROUND(IF($K$14=0,0,J$42/$K$14*$K12),2) -> 0 | K104: =ROUND(IF($K$14=0,0,K$42/$K$14*$K12),2) -> 0 | L104: =ROUND(IF($K$14=0,0,L$42/$K$14*$K12),2) -> 0 | ... S104: =ROUND(IF($K$14=0,0,S$42/$K$14*$K12),2) -> 0
C106: Subtotal | D106: =SUM(D98:D105) -> 0 | E106: =SUM(E98:E105) -> 0 | F106: =SUM(F98:F105) -> 0 | G106: =SUM(G98:G105) -> 0 | H106: =SUM(H98:H105) -> 0 | I106: =SUM(I98:I105) -> 0 | J106: =SUM(J98:J105) -> 0 | K106: =SUM(K98:K105) -> 0 | ... S106: =SUM(S98:S105) -> 0
A109: Fiscal disparities
B110: =Instructions!P1 -> Pay 2012 | C110: General | D110: =SUM(E110:S110) -> 0 | E110: =ROUND(IF($D$14=0,0,E$43/$D$14*$D9),2) -> 0 | F110: =ROUND(IF($D$14=0,0,F$43/$D$14*$D9),2) -> 0 | G110: =ROUND(IF($D$14=0,0,G$43/$D$14*$D9),2) -> 0 | H110: =ROUND(IF($D$14=0,0,H$43/$D$14*$D9),2) -> 0 | I110: =ROUND(IF($D$14=0,0,I$43/$D$14*$D9),2) -> 0 | J110: =ROUND(IF($D$14=0,0,J$43/$D$14*$D9),2) -> 0 | K110: =ROUND(IF($D$14=0,0,K$43/$D$14*$D9),2) -> 0 | L110: =ROUND(IF($D$14=0,0,L$43/$D$14*$D9),2) -> 0 | ... S110: =ROUND(IF($D$14=0,0,S$43/$D$14*$D9),2) -> 0
B111: =Instructions!P1 -> Pay 2012 | C111: Comm Serv | D111: =SUM(E111:S111) -> 0 | E111: =ROUND(IF($D$14=0,0,E$43/$D$14*$D10),2) -> 0 | F111: =ROUND(IF($D$14=0,0,F$43/$D$14*$D10),2) -> 0 | G111: =ROUND(IF($D$14=0,0,G$43/$D$14*$D10),2) -> 0 | H111: =ROUND(IF($D$14=0,0,H$43/$D$14*$D10),2) -> 0 | I111: =ROUND(IF($D$14=0,0,I$43/$D$14*$D10),2) -> 0 | J111: =ROUND(IF($D$14=0,0,J$43/$D$14*$D10),2) -> 0 | K111: =ROUND(IF($D$14=0,0,K$43/$D$14*$D10),2) -> 0 | L111: =ROUND(IF($D$14=0,0,L$43/$D$14*$D10),2) -> 0 | ... S111: =ROUND(IF($D$14=0,0,S$43/$D$14*$D10),2) -> 0
B112: =Instructions!P1 -> Pay 2012 | C112: Debt Serv | D112: =SUM(E112:S112) -> 0 | E112: =ROUND(IF($D$14=0,0,E$43/$D$14*$D11),2) -> 0 | F112: =ROUND(IF($D$14=0,0,F$43/$D$14*$D11),2) -> 0 | G112: =ROUND(IF($D$14=0,0,G$43/$D$14*$D11),2) -> 0 | H112: =ROUND(IF($D$14=0,0,H$43/$D$14*$D11),2) -> 0 | I112: =ROUND(IF($D$14=0,0,I$43/$D$14*$D11),2) -> 0 | J112: =ROUND(IF($D$14=0,0,J$43/$D$14*$D11),2) -> 0 | K112: =ROUND(IF($D$14=0,0,K$43/$D$14*$D11),2) -> 0 | L112: =ROUND(IF($D$14=0,0,L$43/$D$14*$D11),2) -> 0 | ... S112: =ROUND(IF($D$14=0,0,S$43/$D$14*$D11),2) -> 0
B113: =Instructions!P1 -> Pay 2012 | C113: OPEB | D113: =SUM(E113:S113) -> 0 | E113: =ROUND(IF($D$14=0,0,E$43/$D$14*$D12),2) -> 0 | F113: =ROUND(IF($D$14=0,0,F$43/$D$14*$D12),2) -> 0 | G113: =ROUND(IF($D$14=0,0,G$43/$D$14*$D12),2) -> 0 | H113: =ROUND(IF($D$14=0,0,H$43/$D$14*$D12),2) -> 0 | I113: =ROUND(IF($D$14=0,0,I$43/$D$14*$D12),2) -> 0 | J113: =ROUND(IF($D$14=0,0,J$43/$D$14*$D12),2) -> 0 | K113: =ROUND(IF($D$14=0,0,K$43/$D$14*$D12),2) -> 0 | L113: =ROUND(IF($D$14=0,0,L$43/$D$14*$D12),2) -> 0 | ... S113: =ROUND(IF($D$14=0,0,S$43/$D$14*$D12),2) -> 0
C115: Subtotal | D115: =SUM(D110:D114) -> 0 | E115: =SUM(E110:E114) -> 0 | F115: =SUM(F110:F114) -> 0 | G115: =SUM(G110:G114) -> 0 | H115: =SUM(H110:H114) -> 0 | I115: =SUM(I110:I114) -> 0 | J115: =SUM(J110:J114) -> 0 | K115: =SUM(K110:K114) -> 0 | ... S115: =SUM(S110:S114) -> 0
A118: Fiscal disparities
B119: =Instructions!P2 -> Pay 2011 | C119: General | D119: =SUM(E119:S119) -> 0 | E119: =ROUND(IF($E$14=0,0,E$44/$E$14*$E9),2) -> 0 | F119: =ROUND(IF($E$14=0,0,F$44/$E$14*$E9),2) -> 0 | G119: =ROUND(IF($E$14=0,0,G$44/$E$14*$E9),2) -> 0 | H119: =ROUND(IF($E$14=0,0,H$44/$E$14*$E9),2) -> 0 | I119: =ROUND(IF($E$14=0,0,I$44/$E$14*$E9),2) -> 0 | J119: =ROUND(IF($E$14=0,0,J$44/$E$14*$E9),2) -> 0 | K119: =ROUND(IF($E$14=0,0,K$44/$E$14*$E9),2) -> 0 | L119: =ROUND(IF($E$14=0,0,L$44/$E$14*$E9),2) -> 0 | ... S119: =ROUND(IF($E$14=0,0,S$44/$E$14*$E9),2) -> 0
B120: =Instructions!P2 -> Pay 2011 | C120: Comm Serv | D120: =SUM(E120:S120) -> 0 | E120: =ROUND(IF($E$14=0,0,E$44/$E$14*$E10),2) -> 0 | F120: =ROUND(IF($E$14=0,0,F$44/$E$14*$E10),2) -> 0 | G120: =ROUND(IF($E$14=0,0,G$44/$E$14*$E10),2) -> 0 | H120: =ROUND(IF($E$14=0,0,H$44/$E$14*$E10),2) -> 0 | I120: =ROUND(IF($E$14=0,0,I$44/$E$14*$E10),2) -> 0 | J120: =ROUND(IF($E$14=0,0,J$44/$E$14*$E10),2) -> 0 | K120: =ROUND(IF($E$14=0,0,K$44/$E$14*$E10),2) -> 0 | L120: =ROUND(IF($E$14=0,0,L$44/$E$14*$E10),2) -> 0 | ... S120: =ROUND(IF($E$14=0,0,S$44/$E$14*$E10),2) -> 0
B121: =Instructions!P2 -> Pay 2011 | C121: Debt Serv | D121: =SUM(E121:S121) -> 0 | E121: =ROUND(IF($E$14=0,0,E$44/$E$14*$E11),2) -> 0 | F121: =ROUND(IF($E$14=0,0,F$44/$E$14*$E11),2) -> 0 | G121: =ROUND(IF($E$14=0,0,G$44/$E$14*$E11),2) -> 0 | H121: =ROUND(IF($E$14=0,0,H$44/$E$14*$E11),2) -> 0 | I121: =ROUND(IF($E$14=0,0,I$44/$E$14*$E11),2) -> 0 | J121: =ROUND(IF($E$14=0,0,J$44/$E$14*$E11),2) -> 0 | K121: =ROUND(IF($E$14=0,0,K$44/$E$14*$E11),2) -> 0 | L121: =ROUND(IF($E$14=0,0,L$44/$E$14*$E11),2) -> 0 | ... S121: =ROUND(IF($E$14=0,0,S$44/$E$14*$E11),2) -> 0
B122: =Instructions!P2 -> Pay 2011 | C122: OPEB | D122: =SUM(E122:S122) -> 0 | E122: =ROUND(IF($E$14=0,0,E$44/$E$14*$E12),2) -> 0 | F122: =ROUND(IF($E$14=0,0,F$44/$E$14*$E12),2) -> 0 | G122: =ROUND(IF($E$14=0,0,G$44/$E$14*$E12),2) -> 0 | H122: =ROUND(IF($E$14=0,0,H$44/$E$14*$E12),2) -> 0 | I122: =ROUND(IF($E$14=0,0,I$44/$E$14*$E12),2) -> 0 | J122: =ROUND(IF($E$14=0,0,J$44/$E$14*$E12),2) -> 0 | K122: =ROUND(IF($E$14=0,0,K$44/$E$14*$E12),2) -> 0 | L122: =ROUND(IF($E$14=0,0,L$44/$E$14*$E12),2) -> 0 | ... S122: =ROUND(IF($E$14=0,0,S$44/$E$14*$E12),2) -> 0
C124: Subtotal | D124: =SUM(D119:D123) -> 0 | E124: =SUM(E119:E123) -> 0 | F124: =SUM(F119:F123) -> 0 | G124: =SUM(G119:G123) -> 0 | H124: =SUM(H119:H123) -> 0 | I124: =SUM(I119:I123) -> 0 | J124: =SUM(J119:J123) -> 0 | K124: =SUM(K119:K123) -> 0 | ... S124: =SUM(S119:S123) -> 0
A127: Taconite homestead credit
B128: =Instructions!P1 -> Pay 2012 | C128: General | D128: =SUM(E128:S128) -> 0 | E128: =ROUND(IF($D$14=0,0,E$45/$D$14*$D9),2) -> 0 | F128: =ROUND(IF($D$14=0,0,F$45/$D$14*$D9),2) -> 0 | G128: =ROUND(IF($D$14=0,0,G$45/$D$14*$D9),2) -> 0 | H128: =ROUND(IF($D$14=0,0,H$45/$D$14*$D9),2) -> 0 | I128: =ROUND(IF($D$14=0,0,I$45/$D$14*$D9),2) -> 0 | J128: =ROUND(IF($D$14=0,0,J$45/$D$14*$D9),2) -> 0 | K128: =ROUND(IF($D$14=0,0,K$45/$D$14*$D9),2) -> 0 | L128: =ROUND(IF($D$14=0,0,L$45/$D$14*$D9),2) -> 0 | ... S128: =ROUND(IF($D$14=0,0,S$45/$D$14*$D9),2) -> 0
B129: =Instructions!P1 -> Pay 2012 | C129: Comm Serv | D129: =SUM(E129:S129) -> 0 | E129: =ROUND(IF($D$14=0,0,E$45/$D$14*$D10),2) -> 0 | F129: =ROUND(IF($D$14=0,0,F$45/$D$14*$D10),2) -> 0 | G129: =ROUND(IF($D$14=0,0,G$45/$D$14*$D10),2) -> 0 | H129: =ROUND(IF($D$14=0,0,H$45/$D$14*$D10),2) -> 0 | I129: =ROUND(IF($D$14=0,0,I$45/$D$14*$D10),2) -> 0 | J129: =ROUND(IF($D$14=0,0,J$45/$D$14*$D10),2) -> 0 | K129: =ROUND(IF($D$14=0,0,K$45/$D$14*$D10),2) -> 0 | L129: =ROUND(IF($D$14=0,0,L$45/$D$14*$D10),2) -> 0 | ... S129: =ROUND(IF($D$14=0,0,S$45/$D$14*$D10),2) -> 0
B130: =Instructions!P1 -> Pay 2012 | C130: Debt Serv | D130: =SUM(E130:S130) -> 0 | E130: =ROUND(IF($D$14=0,0,E$45/$D$14*$D11),2) -> 0 | F130: =ROUND(IF($D$14=0,0,F$45/$D$14*$D11),2) -> 0 | G130: =ROUND(IF($D$14=0,0,G$45/$D$14*$D11),2) -> 0 | H130: =ROUND(IF($D$14=0,0,H$45/$D$14*$D11),2) -> 0 | I130: =ROUND(IF($D$14=0,0,I$45/$D$14*$D11),2) -> 0 | J130: =ROUND(IF($D$14=0,0,J$45/$D$14*$D11),2) -> 0 | K130: =ROUND(IF($D$14=0,0,K$45/$D$14*$D11),2) -> 0 | L130: =ROUND(IF($D$14=0,0,L$45/$D$14*$D11),2) -> 0 | ... S130: =ROUND(IF($D$14=0,0,S$45/$D$14*$D11),2) -> 0
B131: =Instructions!P1 -> Pay 2012 | C131: OPEB | D131: =SUM(E131:S131) -> 0 | E131: =ROUND(IF($D$14=0,0,E$45/$D$14*$D12),2) -> 0 | F131: =ROUND(IF($D$14=0,0,F$45/$D$14*$D12),2) -> 0 | G131: =ROUND(IF($D$14=0,0,G$45/$D$14*$D12),2) -> 0 | H131: =ROUND(IF($D$14=0,0,H$45/$D$14*$D12),2) -> 0 | I131: =ROUND(IF($D$14=0,0,I$45/$D$14*$D12),2) -> 0 | J131: =ROUND(IF($D$14=0,0,J$45/$D$14*$D12),2) -> 0 | K131: =ROUND(IF($D$14=0,0,K$45/$D$14*$D12),2) -> 0 | L131: =ROUND(IF($D$14=0,0,L$45/$D$14*$D12),2) -> 0 | ... S131: =ROUND(IF($D$14=0,0,S$45/$D$14*$D12),2) -> 0
C133: Subtotal | D133: =SUM(D128:D132) -> 0 | E133: =SUM(E128:E132) -> 0 | F133: =SUM(F128:F132) -> 0 | G133: =SUM(G128:G132) -> 0 | H133: =SUM(H128:H132) -> 0 | I133: =SUM(I128:I132) -> 0 | J133: =SUM(J128:J132) -> 0 | K133: =SUM(K128:K132) -> 0 | ... S133: =SUM(S128:S132) -> 0
A136: Taconite homestead credit
B137: =Instructions!P2 -> Pay 2011 | C137: General | D137: =SUM(E137:S137) -> 0 | E137: =ROUND(IF($E$14=0,0,E$46/$E$14*$E9),2) -> 0 | F137: =ROUND(IF($E$14=0,0,F$46/$E$14*$E9),2) -> 0 | G137: =ROUND(IF($E$14=0,0,G$46/$E$14*$E9),2) -> 0 | H137: =ROUND(IF($E$14=0,0,H$46/$E$14*$E9),2) -> 0 | I137: =ROUND(IF($E$14=0,0,I$46/$E$14*$E9),2) -> 0 | J137: =ROUND(IF($E$14=0,0,J$46/$E$14*$E9),2) -> 0 | K137: =ROUND(IF($E$14=0,0,K$46/$E$14*$E9),2) -> 0 | L137: =ROUND(IF($E$14=0,0,L$46/$E$14*$E9),2) -> 0 | ... S137: =ROUND(IF($E$14=0,0,S$46/$E$14*$E9),2) -> 0
B138: =Instructions!P2 -> Pay 2011 | C138: Comm Serv | D138: =SUM(E138:S138) -> 0 | E138: =ROUND(IF($E$14=0,0,E$46/$E$14*$E10),2) -> 0 | F138: =ROUND(IF($E$14=0,0,F$46/$E$14*$E10),2) -> 0 | G138: =ROUND(IF($E$14=0,0,G$46/$E$14*$E10),2) -> 0 | H138: =ROUND(IF($E$14=0,0,H$46/$E$14*$E10),2) -> 0 | I138: =ROUND(IF($E$14=0,0,I$46/$E$14*$E10),2) -> 0 | J138: =ROUND(IF($E$14=0,0,J$46/$E$14*$E10),2) -> 0 | K138: =ROUND(IF($E$14=0,0,K$46/$E$14*$E10),2) -> 0 | L138: =ROUND(IF($E$14=0,0,L$46/$E$14*$E10),2) -> 0 | ... S138: =ROUND(IF($E$14=0,0,S$46/$E$14*$E10),2) -> 0
B139: =Instructions!P2 -> Pay 2011 | C139: Debt Serv | D139: =SUM(E139:S139) -> 0 | E139: =ROUND(IF($E$14=0,0,E$46/$E$14*$E11),2) -> 0 | F139: =ROUND(IF($E$14=0,0,F$46/$E$14*$E11),2) -> 0 | G139: =ROUND(IF($E$14=0,0,G$46/$E$14*$E11),2) -> 0 | H139: =ROUND(IF($E$14=0,0,H$46/$E$14*$E11),2) -> 0 | I139: =ROUND(IF($E$14=0,0,I$46/$E$14*$E11),2) -> 0 | J139: =ROUND(IF($E$14=0,0,J$46/$E$14*$E11),2) -> 0 | K139: =ROUND(IF($E$14=0,0,K$46/$E$14*$E11),2) -> 0 | L139: =ROUND(IF($E$14=0,0,L$46/$E$14*$E11),2) -> 0 | ... S139: =ROUND(IF($E$14=0,0,S$46/$E$14*$E11),2) -> 0
B140: =Instructions!P2 -> Pay 2011 | C140: OPEB | D140: =SUM(E140:S140) -> 0 | E140: =ROUND(IF($E$14=0,0,E$46/$E$14*$E12),2) -> 0 | F140: =ROUND(IF($E$14=0,0,F$46/$E$14*$E12),2) -> 0 | G140: =ROUND(IF($E$14=0,0,G$46/$E$14*$E12),2) -> 0 | H140: =ROUND(IF($E$14=0,0,H$46/$E$14*$E12),2) -> 0 | I140: =ROUND(IF($E$14=0,0,I$46/$E$14*$E12),2) -> 0 | J140: =ROUND(IF($E$14=0,0,J$46/$E$14*$E12),2) -> 0 | K140: =ROUND(IF($E$14=0,0,K$46/$E$14*$E12),2) -> 0 | L140: =ROUND(IF($E$14=0,0,L$46/$E$14*$E12),2) -> 0 | ... S140: =ROUND(IF($E$14=0,0,S$46/$E$14*$E12),2) -> 0
C142: Subtotal | D142: =SUM(D137:D141) -> 0 | E142: =SUM(E137:E141) -> 0 | F142: =SUM(F137:F141) -> 0 | G142: =SUM(G137:G141) -> 0 | H142: =SUM(H137:H141) -> 0 | I142: =SUM(I137:I141) -> 0 | J142: =SUM(J137:J141) -> 0 | K142: =SUM(K137:K141) -> 0 | ... S142: =SUM(S137:S141) -> 0
A145: Miscellaneous taxes | D145: =SUM(E145:S145) -> 0 | E145: =E47 -> 0 | F145: =F47 -> 0 | G145: =G47 -> 0 | H145: =H47 -> 0 | I145: =I47 -> 0 | J145: =J47 -> 0 | K145: =K47 -> 0 | L145: =L47 -> 0 | ... S145: =S47 -> 0
B147: Total settlement | D147: =D61+D73+D84+D95+D124+D142+D145 -> 0 | E147: =E61+E73+E84+E95+E106+E115+E124+E133+E142+E145 -> 0 | F147: =F61+F73+F84+F95+F106+F115+F124+F133+F142+F145 -> 0 | G147: =G61+G73+G84+G95+G106+G115+G124+G133+G142+G145 -> 0 | H147: =H61+H73+H84+H95+H106+H115+H124+H133+H142+H145 -> 0 | I147: =I61+I73+I84+I95+I106+I115+I124+I133+I142+I145 -> 0 | J147: =J61+J73+J84+J95+J106+J115+J124+J133+J142+J145 -> 0 | K147: =K61+K73+K84+K95+K106+K115+K124+K133+K142+K145 -> 0 | L147: =L61+L73+L84+L95+L106+L115+L124+L133+L142+L145 -> 0 | ... S147: =S61+S73+S84+S95+S106+S115+S124+S133+S142+S145 -> 0

Sheet Accounts
A1: Reconciation of Property Tax Accounts | I1: =Report!A3 -> 1.2 | J1: =Report!B5 -> MINNEAPOLIS | L1: =Report!I1 -> 41115 | N1: Note:
N2: Account balances are indicated as debit or (credit) balance
A3: On Reports tab enter your district # in cell A3 so correct tax shift amounts carryover | N3: Asset and expenditure accounts would normally have a debit balance
A4: Data entered on Funds tab will carryover and be used to allocate adjustments and abatements | N4: Liability and revenue accounts would normally have a credit balance
A5: On this tab enter data in highlighted fields only--from source indicated | N5: See comments by accounts GNL 214 and SRC 020 and 299
A6: All other fields will compute, including those that come from the Tax Shift spreadsheet
A7: Enter debits as positive and credits as negative, as indicated in column H | I7: General | J7: Comm Serv | K7: Debt | L7: Debt | M7: Total
I8: Debit (Credit) | J8: Debit (Credit) | K8: Debit (Credit) | L8: Debit (Credit) | M8: Debit (Credit)
A10: Balance Sheet Acccounts:
A12: =Instructions!P1&" Certified Levy" -> Pay 2012 Certified Levy | H12: Debit | I12: =Funds!D9 -> 0 | J12: =Funds!D10 -> 0 | K12: =Funds!D11 -> 0 | L12: =Funds!D12 -> 0 | M12: =SUM(I12:L12) -> 0 | N12: Levy Limitation & Certification Report
A13: ="Tax settlements "&Instructions!T4&" for "&Instructions!P1&" levy" -> Tax settlements 05/01/2012 to 06/30/2012 for Pay 2012 levy | H13: (Credit) | I13: =-Funds!D56 -> 0 | J13: =-Funds!D57 -> 0 | K13: =-Funds!D58 -> 0 | L13: =-Funds!D59 -> 0 | M13: =SUM(I13:L13) -> 0 | N13: ="Tax Settlement Reports (Form 52) "&Instructions!T2 -> Tax Settlement Reports (Form 52) 07/01/2011 to 06/30/2012
A14: ="Tax settlements Fiscal disparities "&Instructions!T4&" for "&Instructions!P1&" levy" -> Tax settlements Fiscal disparities 05/01/2012 to 06/30/2012 for Pay 2012 levy | H14: (Credit) | I14: =-Funds!D110 -> 0 | J14: =-Funds!D111 -> 0 | K14: =-Funds!D112 -> 0 | L14: =-Funds!D113 -> 0 | M14: =SUM(I14:L14) -> 0 | N14: ="Tax Settlement Reports (Form 52) "&Instructions!T2 -> Tax Settlement Reports (Form 52) 07/01/2011 to 06/30/2012
A15: ="Tax settlements Taconite homestead credit "&Instructions!T4&" for "&Instructions!P1&" levy" -> Tax settlements Taconite homestead credit 05/01/2012 to 06/30/2012 for Pay 2012 levy | H15: (Credit) | I15: =-Funds!D128 -> 0 | J15: =-Funds!D129 -> 0 | K15: =-Funds!D130 -> 0 | L15: =-Funds!D131 -> 0 | M15: =SUM(I15:L15) -> 0 | N15: ="Tax Settlement Reports (Form 52) "&Instructions!T2 -> Tax Settlement Reports (Form 52) 07/01/2011 to 06/30/2012
A16: (Do not include any July payments)
B18: ="10 Taxes Receivable--Current "&Instructions!S2 -> 10 Taxes Receivable--Current 06/30/12 | I18: =SUM(I12:I16) -> 0 | J18: =SUM(J12:J16) -> 0 | K18: =SUM(K12:K16) -> 0 | L18: =SUM(L12:L16) -> 0
A22: ="Delinquent Taxes Receivable "&Instructions!S3 -> Delinquent Taxes Receivable 06/30/11 | H22: Debit | I22: 0 | J22: 0 | K22: 0 | L22: 0 | M22: =SUM(I22:L22) -> 0 | N22: ="General Ledger "&Instructions!S3 -> General Ledger 06/30/11
A23: ="Current Taxes Receivable "&Instructions!S3 -> Current Taxes Receivable 06/30/11 | H23: Debit | I23: 0 | J23: 0 | K23: 0 | L23: 0 | M23: =SUM(I23:L23) -> 0 | N23: ="General Ledger "&Instructions!S3 -> General Ledger 06/30/11
A24: ="Increase (decrease) to "&Instructions!P2&" levy by county" -> Increase (decrease) to Pay 2011 levy by county | H24: Debit (Credit) | I24: =ROUND(IF(M24=0,0,Funds!E9/Funds!E14*M24),2) -> 0 | J24: =ROUND(IF(M24=0,0,Funds!E10/Funds!E14*M24),2) -> 0 | K24: =ROUND(IF(M24=0,0,Funds!E11/Funds!E14*M24),2) -> 0 | L24: =ROUND(IF(M24=0,0,Funds!E12/Funds!E14*M24),2) -> 0 | M24: 0 | N24: Taxes Receivable Report (Form 51)
A25: ="Increase (decrease) to "&Instructions!P3&" levy by county" -> Increase (decrease) to Pay 2010 levy by county | H25: Debit (Credit) | I25: =ROUND(IF($M$25=0,0,Funds!F9/Funds!$F$14*$M$25),2) -> 0 | J25: =ROUND(IF($M$25=0,0,Funds!F10/Funds!$F$14*$M$25),2) -> 0 | K25: =ROUND(IF($M$25=0,0,Funds!F11/Funds!$F$14*$M$25),2) -> 0 | L25: =ROUND(IF($M$25=0,0,Funds!F12/Funds!$F$14*$M$25),2) -> 0 | M25: 0 | N25: Taxes Receivable Report (Form 51)
A26: ="Education Homestead Market Value Credit for "&Instructions!R2 -> Education Homestead Market Value Credit for FY 2012 | H26: (Credit) | I26: 0 | J26: 0 | K26: 0 | L26: 0 | M26: =SUM(I26:L26) -> 0 | N26: Report of Credits from Dept of Revenue
A27: ="Agricultural Educ Homestead Market Value Credit for "&Instructions!R2 -> Agricultural Educ Homestead Market Value Credit for FY 2012 | H27: (Credit) | I27: 0 | J27: 0 | K27: 0 | L27: 0 | M27: =SUM(I27:L27) -> 0 | N27: Report of Credits from Dept of Revenue
A28: ="Other credits for "&Instructions!R2 -> Other credits for FY 2012 | H28: (Credit) | I28: 0 | J28: 0 | K28: 0 | L28: 0 | M28: =SUM(I28:L28) -> 0 | N28: Report of Credits from Dept of Revenue
A29: ="Disparity Aid adjustments for "&Instructions!R2 -> Disparity Aid adjustments for FY 2012 | H29: (Credit) | I29: 0 | J29: 0 | K29: 0 | L29: 0 | M29: =SUM(I29:L29) -> 0 | N29: Report of Credits from Dept of Revenue
A30: ="Decrease (increase) to credits by county" -> Decrease (increase) to credits by county | H30: Debit (Credit) | I30: =ROUND(IF(Funds!$E$14=0,0,Funds!E9/Funds!$E$14*$M$30),2) -> 0 | J30: =ROUND(IF(Funds!$E$14=0,0,Funds!E10/Funds!$E$14*$M$30),2) -> 0 | K30: =ROUND(IF(Funds!$E$14=0,0,Funds!E11/Funds!$E$14*$M$30),2) -> 0 | L30: =ROUND(IF(Funds!$E$14=0,0,Funds!E12/Funds!$E$14*$M$30),2) -> 0 | M30: 0 | N30: Credits on Taxes receivable minus credits from Revenue
A31: ="Abatements "&Instructions!T2&" for "&Instructions!P2&" levy" -> Abatements 07/01/2011 to 06/30/2012 for Pay 2011 levy | H31: (Credit) | I31: =ROUND(IF(Funds!$E$14=0,0,Funds!E9/Funds!$E$14*$M$31),2) -> 0 | J31: =ROUND(IF(Funds!$E$14=0,0,Funds!E10/Funds!$E$14*$M$31),2) -> 0 | K31: =ROUND(IF(Funds!$E$14=0,0,Funds!E11/Funds!$E$14*$M$31),2) -> 0 | L31: =ROUND(IF(Funds!$E$14=0,0,Funds!E12/Funds!$E$14*$M$31),2) -> 0 | M31: 0 | N31: Taxes Receivable Report (Form 51)
A32: ="Abatements "&Instructions!T2&" for "&Instructions!P3&" levy" -> Abatements 07/01/2011 to 06/30/2012 for Pay 2010 levy | H32: (Credit) | I32: =ROUND(IF(Funds!$F$14=0,0,Funds!F9/Funds!$F$14*$M$32),2) -> 0 | J32: =ROUND(IF(Funds!$F$14=0,0,Funds!F10/Funds!$F$14*$M$32),2) -> 0 | K32: =ROUND(IF(Funds!$F$14=0,0,Funds!F11/Funds!$F$14*$M$32),2) -> 0 | L32: =ROUND(IF(Funds!$F$14=0,0,Funds!F12/Funds!$F$14*$M$32),2) -> 0 | M32: 0 | N32: Taxes Receivable Report (Form 51)
A33: ="Abatements "&Instructions!T2&" for "&Instructions!P4&" levy" -> Abatements 07/01/2011 to 06/30/2012 for Pay 2009 levy | H33: (Credit) | I33: =ROUND(IF(Funds!$G$14=0,0,Funds!G9/Funds!$G$14*$M$33),2) -> 0 | J33: =ROUND(IF(Funds!$G$14=0,0,Funds!G10/Funds!$G$14*$M$33),2) -> 0 | K33: =ROUND(IF(Funds!$G$14=0,0,Funds!G11/Funds!$G$14*$M$33),2) -> 0 | L33: =ROUND(IF(Funds!$G$14=0,0,Funds!G12/Funds!$G$14*$M$33),2) -> 0 | M33: 0 | N33: Taxes Receivable Report (Form 51)
A34: ="Abatements "&Instructions!T2&" for "&Instructions!P5&" levy" -> Abatements 07/01/2011 to 06/30/2012 for Pay 2008 levy | H34: (Credit) | I34: =ROUND(IF(Funds!$H$14=0,0,Funds!H9/Funds!$H$14*$M$34),2) -> 0 | J34: =ROUND(IF(Funds!$H$14=0,0,Funds!H10/Funds!$H$14*$M$34),2) -> 0 | K34: =ROUND(IF(Funds!$H$14=0,0,Funds!H11/Funds!$H$14*$M$34),2) -> 0 | L34: =ROUND(IF(Funds!$H$14=0,0,Funds!H12/Funds!$H$14*$M$34),2) -> 0 | M34: 0 | N34: Taxes Receivable Report (Form 51)
A35: ="Abatements "&Instructions!T2&" for "&Instructions!P6&" levy" -> Abatements 07/01/2011 to 06/30/2012 for Pay 2007 levy | H35: (Credit) | I35: =ROUND(IF(Funds!$I$14=0,0,Funds!I9/Funds!$I$14*$M$35),2) -> 0 | J35: =ROUND(IF(Funds!$I$14=0,0,Funds!I10/Funds!$I$14*$M$35),2) -> 0 | K35: =ROUND(IF(Funds!$I$14=0,0,Funds!I11/Funds!$I$14*$M$35),2) -> 0 | L35: =ROUND(IF(Funds!$I$14=0,0,Funds!I12/Funds!$I$14*$M$35),2) -> 0 | M35: 0 | N35: Taxes Receivable Report (Form 51)
A36: ="Abatements "&Instructions!T2&" for "&Instructions!P7&" levy" -> Abatements 07/01/2011 to 06/30/2012 for Pay 2006 levy | H36: (Credit) | I36: =ROUND(IF(Funds!$J$14=0,0,Funds!J9/Funds!$J$14*$M$36),2) -> 0 | J36: =ROUND(IF(Funds!$J$14=0,0,Funds!J10/Funds!$J$14*$M$36),2) -> 0 | K36: =ROUND(IF(Funds!$J$14=0,0,Funds!J11/Funds!$J$14*$M$36),2) -> 0 | L36: =ROUND(IF(Funds!$J$14=0,0,Funds!J12/Funds!$J$14*$M$36),2) -> 0 | M36: 0 | N36: Taxes Receivable Report (Form 51)
A37: ="Abatements "&Instructions!T2&" for "&Instructions!P8&" levy" -> Abatements 07/01/2011 to 06/30/2012 for Pay 2005 levy | H37: (Credit) | I37: =ROUND(IF(Funds!$K$14=0,0,Funds!K9/Funds!$K$14*$M$37),2) -> 0 | J37: =ROUND(IF(Funds!$K$14=0,0,Funds!K10/Funds!$K$14*$M$37),2) -> 0 | K37: =ROUND(IF(Funds!$K$14=0,0,Funds!K11/Funds!$K$14*$M$37),2) -> 0 | L37: =ROUND(IF(Funds!$K$14=0,0,Funds!K12/Funds!$K$14*$M$37),2) -> 0 | M37: 0 | N37: Taxes Receivable Report (Form 51)
A38: ="Write off "&Instructions!P8&" delinquent taxes negative (positive) balance due" -> Write off Pay 2005 delinquent taxes negative (positive) balance due | H38: Debit (Credit) | I38: =ROUND(IF(Funds!$K$14=0,0,Funds!K9/Funds!$K$14*$M$38),2) -> 0 | J38: =ROUND(IF(Funds!$K$14=0,0,Funds!K10/Funds!$K$14*$M$38),2) -> 0 | K38: =ROUND(IF(Funds!$K$14=0,0,Funds!K11/Funds!$K$14*$M$38),2) -> 0 | L38: =ROUND(IF(Funds!$K$14=0,0,Funds!K12/Funds!$K$14*$M$38),2) -> 0 | M38: 0 | N38: Taxes Receivable Report (Form 51)
A39: ="Tax settlements "&Instructions!T2&" for "&Instructions!P2&" and prior levies" -> Tax settlements 07/01/2011 to 06/30/2012 for Pay 2011 and prior levies | H39: (Credit) | I39: =-Funds!D73 -> 0 | J39: =-Funds!D84 -> 0 | K39: =-Funds!D95 -> 0 | L39: =-Funds!D106 -> 0 | M39: =SUM(I39:L39) -> 0 | N39: ="Tax Settlement Reports (Form 52) "&Instructions!T2 -> Tax Settlement Reports (Form 52) 07/01/2011 to 06/30/2012
A40: ="Tax settlements Fiscal Disparities "&Instructions!T3&" for "&Instructions!P2 -> Tax settlements Fiscal Disparities 07/01/2011 to 04/30/2012 for Pay 2011 | H40: (Credit) | I40: =-Funds!D119 -> 0 | J40: =-Funds!D120 -> 0 | K40: =-Funds!D121 -> 0 | L40: =-Funds!D122 -> 0 | M40: =SUM(I40:L40) -> 0 | N40: ="Tax Settlement Reports (Form 52) "&Instructions!T2 -> Tax Settlement Reports (Form 52) 07/01/2011 to 06/30/2012
A41: ="Tax settlements Taconite homestead credit "&Instructions!T3&" for "&Instructions!P2 -> Tax settlements Taconite homestead credit 07/01/2011 to 04/30/2012 for Pay 2011 | H41: (Credit) | I41: =-Funds!D137 -> 0 | J41: =-Funds!D138 -> 0 | K41: =-Funds!D139 -> 0 | L41: =-Funds!D140 -> 0 | M41: =SUM(I41:L41) -> 0 | N41: ="Tax Settlement Reports (Form 52) "&Instructions!T2 -> Tax Settlement Reports (Form 52) 07/01/2011 to 06/30/2012
B43: ="111 Delinquent Taxes Receivable "&Instructions!S2 -> 111 Delinquent Taxes Receivable 06/30/12 | I43: =SUM(I22:I41) -> 0 | J43: =SUM(J22:J41) -> 0 | K43: =SUM(K22:K41) -> 0 | L43: =SUM(L22:L41) -> 0
A47: Year end receivable (payable) adjustment for property tax shift | H47: (Credit) | I47: =Report!I18 -> 400016.66 | J47: =Report!I23 -> -400634.03 | M47: =SUM(I47:L47) -> -617.37 | N47: Tax Shift Report (column 6)
B49: ="213 Property Tax Shift Adjustment "&Instructions!S2 -> 213 Property Tax Shift Adjustment 06/30/12 | I49: =I47 -> 400016.66 | J49: =J47 -> -400634.03
A53: Amount by which tax shift exceeds property tax receipts | H53: Debit | I53: =Report!E108 -> 4917530 | J53: =Report!E110 -> 0 | M53: =SUM(I53:L53) -> 4917530 | N53: Tax Shift Entry
B55: ="214 Advance of Unearned General Education Aid "&Instructions!S2 -> 214 Advance of Unearned General Education Aid 06/30/12 | I55: =SUM(I53:I54) -> 4917530 | J55: =SUM(J53:J54) -> 0
A59: ="Deferred Revenue for Delinquent Taxes "&Instructions!S3 -> Deferred Revenue for Delinquent Taxes 06/30/11 | H59: (Credit) | I59: 0 | J59: 0 | K59: 0 | L59: 0 | M59: =SUM(I59:L59) -> 0 | N59: ="General Ledger "&Instructions!S3 -> General Ledger 06/30/11
A60: ="Decrease (increase) in Delinquent Taxes from "&Instructions!S3&" to "&Instructions!S2 -> Decrease (increase) in Delinquent Taxes from 06/30/11 to 06/30/12 | H60: Debit (Credit) | I60: =I22-I43 -> 0 | J60: =J22-J43 -> 0 | K60: =K22-K43 -> 0 | L60: =L22-L43 -> 0 | M60: =SUM(I60:L60) -> 0 | N60: General Ledger
A61: ="Increase (decrease) in amount to be collected within 60 days from "&Instructions!S3&" to "&Instructions!S2 -> Increase (decrease) in amount to be collected within 60 days from 06/30/11 to 06/30/12 | H61: Debit (Credit) | I61: 0 | J61: 0 | K61: 0 | L61: 0 | M61: =SUM(I61:L61) -> 0 | N61: Tax Settlement Reports (Form 52) for each July
B63: ="231 Deferred Revenue--Delinquent Taxes "&Instructions!S2 -> 231 Deferred Revenue--Delinquent Taxes 06/30/12 | I63: =SUM(I59:I61) -> 0 | J63: =SUM(J59:J61) -> 0 | K63: =SUM(K59:K61) -> 0 | L63: =SUM(L59:L61) -> 0
A67: =Instructions!P1&" Certified Levy" -> Pay 2012 Certified Levy | H67: (Credit) | I67: =-I12 -> 0 | J67: =-J12 -> 0 | K67: =-K12 -> 0 | L67: =-L12 -> 0 | M67: =SUM(I67:L67) -> 0 | N67: Levy Limitation & Certification Report
A68: ="Property Tax Shift into "&Instructions!R2 -> Property Tax Shift into FY 2012 | H68: Debit | I68: =Report!C18 -> 56538632 | J68: =Report!C23 -> 2395202 | M68: =SUM(I68:L68) -> 58933834 | N68: Tax Shift Report (column 1 - line J or N)
A69: Amount by which tax shift exceeds property tax receipts | H69: (Credit) | I69: =-I55 -> -4917530 | J69: =-J55 -> 0 | M69: =SUM(I69:L69) -> -4917530 | N69: ="Account 214 balance at "&Instructions!S2 -> Account 214 balance at 06/30/12
B71: ="235 Property Taxes for Subsequent Years "&Instructions!S2 -> 235 Property Taxes for Subsequent Years 06/30/12 | I71: =SUM(I67:I69) -> 51621102 | J71: =SUM(J67:J69) -> 2395202 | K71: =SUM(K67:K69) -> 0 | L71: =SUM(L67:L69) -> 0
A75: Revenue Accounts:
A77: =Instructions!P2&" Certified Levy" -> Pay 2011 Certified Levy | H77: (Credit) | I77: =-Funds!E9 -> 0 | J77: =-Funds!E10 -> 0 | K77: =-Funds!E11 -> 0 | L77: =-Funds!E12 -> 0 | M77: =SUM(I77:L77) -> 0 | N77: Levy Limitation & Certification Report
A78: ="Decrease (increase) to "&Instructions!P2&" levy by county" -> Decrease (increase) to Pay 2011 levy by county | H78: Debit (Credit) | I78: =-I24 -> 0 | J78: =-J24 -> 0 | K78: =-K24 -> 0 | L78: =-L24 -> 0 | M78: =SUM(I78:L78) -> 0 | N78: Taxes Receivable Report (Form 51)
A79: ="Decrease (increase) to "&Instructions!P3&" levy by county" -> Decrease (increase) to Pay 2010 levy by county | H79: Debit (Credit) | I79: =-I25 -> 0 | J79: =-J25 -> 0 | K79: =-K25 -> 0 | L79: =-L25 -> 0 | M79: =SUM(I79:L79) -> 0 | N79: Taxes Receivable Report (Form 51)
A80: ="Education Homestead Market Value Credit for "&Instructions!R2 -> Education Homestead Market Value Credit for FY 2012 | H80: Debit | I80: =-I26 -> 0 | J80: =-J26 -> 0 | K80: =-K26 -> 0 | L80: =-L26 -> 0 | M80: =SUM(I80:L80) -> 0 | N80: Taxes Receivable Report (Form 51)
A81: ="Agricultural Educ Homestead Market Value Credit for "&Instructions!R2 -> Agricultural Educ Homestead Market Value Credit for FY 2012 | H81: Debit | I81: =-I27 -> 0 | J81: =-J27 -> 0 | K81: =-K27 -> 0 | L81: =-L27 -> 0 | M81: =SUM(I81:L81) -> 0 | N81: Taxes Receivable Report (Form 51)
A82: ="Other Credits for "&Instructions!R2 -> Other Credits for FY 2012 | H82: Debit | I82: =-I28 -> 0 | J82: =-J28 -> 0 | K82: =-K28 -> 0 | L82: =-L28 -> 0 | M82: =SUM(I82:L82) -> 0 | N82: Taxes Receivable Report (Form 51)
A83: ="Disparity Aid adjustments for "&Instructions!R2 -> Disparity Aid adjustments for FY 2012 | H83: Debit | I83: =-I29 -> 0 | J83: =-J29 -> 0 | K83: =-K29 -> 0 | L83: =-L29 -> 0 | M83: =SUM(I83:L83) -> 0 | N83: Taxes Receivable Report (Form 51)
A84: Increase (decrease) to credits by county | H84: Debit (Credit) | I84: =-I30 -> 0 | J84: =-J30 -> 0 | K84: =-K30 -> 0 | L84: =-L30 -> 0 | M84: =SUM(I84:L84) -> 0 | N84: Credits on Taxes receivable minus credits from Revenue
A85: ="Abatements "&Instructions!T2&" for "&Instructions!P2&" levy" -> Abatements 07/01/2011 to 06/30/2012 for Pay 2011 levy | H85: Debit | I85: =-I31 -> 0 | J85: =-J31 -> 0 | K85: =-K31 -> 0 | L85: =-L31 -> 0 | M85: =SUM(I85:L85) -> 0 | N85: Taxes Receivable Report (Form 51)
A86: ="Abatements "&Instructions!T2&" for "&Instructions!P3&" levy" -> Abatements 07/01/2011 to 06/30/2012 for Pay 2010 levy | H86: Debit | I86: =-I32 -> 0 | J86: =-J32 -> 0 | K86: =-K32 -> 0 | L86: =-L32 -> 0 | M86: =SUM(I86:L86) -> 0 | N86: Taxes Receivable Report (Form 51)
A87: ="Abatements "&Instructions!T2&" for "&Instructions!P4&" levy" -> Abatements 07/01/2011 to 06/30/2012 for Pay 2009 levy | H87: Debit | I87: =-I33 -> 0 | J87: =-J33 -> 0 | K87: =-K33 -> 0 | L87: =-L33 -> 0 | M87: =SUM(I87:L87) -> 0 | N87: Taxes Receivable Report (Form 51)
A88: ="Abatements "&Instructions!T2&" for "&Instructions!P5&" levy" -> Abatements 07/01/2011 to 06/30/2012 for Pay 2008 levy | H88: Debit | I88: =-I34 -> 0 | J88: =-J34 -> 0 | K88: =-K34 -> 0 | L88: =-L34 -> 0 | M88: =SUM(I88:L88) -> 0 | N88: Taxes Receivable Report (Form 51)
A89: ="Abatements "&Instructions!T2&" for "&Instructions!P6&" levy" -> Abatements 07/01/2011 to 06/30/2012 for Pay 2007 levy | H89: Debit | I89: =-I35 -> 0 | J89: =-J35 -> 0 | K89: =-K35 -> 0 | L89: =-L35 -> 0 | M89: =SUM(I89:L89) -> 0 | N89: Taxes Receivable Report (Form 51)
A90: ="Abatements "&Instructions!T2&" for "&Instructions!P7&" levy" -> Abatements 07/01/2011 to 06/30/2012 for Pay 2006 levy | H90: Debit | I90: =-I36 -> 0 | J90: =-J36 -> 0 | K90: =-K36 -> 0 | L90: =-L36 -> 0 | M90: =SUM(I90:L90) -> 0 | N90: Taxes Receivable Report (Form 51)
A91: ="Abatements "&Instructions!T2&" for "&Instructions!P8&" levy" -> Abatements 07/01/2011 to 06/30/2012 for Pay 2005 levy | H91: Debit | I91: =-I37 -> 0 | J91: =-J37 -> 0 | K91: =-K37 -> 0 | L91: =-L37 -> 0 | M91: =SUM(I91:L91) -> 0 | N91: Taxes Receivable Report (Form 51)
A92: ="Write off "&Instructions!P8&" delinquent taxes positive (negative) balance due" -> Write off Pay 2005 delinquent taxes positive (negative) balance due | H92: Debit (Credit) | I92: =-I38 -> 0 | J92: =-J38 -> 0 | K92: =-K38 -> 0 | L92: =-L38 -> 0 | M92: =SUM(I92:L92) -> 0 | N92: Taxes Receivable Report (Form 51)
A93: ="Fiscal Disparities adjustment for "&Instructions!R2 -> Fiscal Disparities adjustment for FY 2012 | H93: Debit | I93: =-I102 -> 0 | J93: =-J102 -> 0 | K93: =-K102 -> 0 | L93: =-L102 -> 0 | M93: =SUM(I93:L93) -> 0 | N93: Tax Settlement Reports (Form 52)
A94: ="Taconite Homestead credit for "&Instructions!R2 -> Taconite Homestead credit for FY 2012 | H94: Debit | I94: =-I108 -> 0 | J94: =-J108 -> 0 | K94: =-K108 -> 0 | L94: =-L108 -> 0 | M94: =SUM(I94:L94) -> 0 | N94: Tax Settlement Reports (Form 52)
A95: ="Property Tax Shift into "&Instructions!R3 -> Property Tax Shift into FY 2011 | H95: Debit | I95: =Report!D11+Report!D12+Report!D13+Report!D14+Report!D15+Report!D16+Report!D17 -> 22409847 | J95: =Report!D21+Report!D22 -> 0 | M95: =SUM(I95:L95) -> 22409847 | N95: Tax Shift Report (column 2 - lines C+D+E+F+G+H+I or L+M)
A96: ="Property Tax Shift into "&Instructions!R2 -> Property Tax Shift into FY 2012 | H96: (Credit) | I96: =-(Report!C11+Report!C12+Report!C13+Report!C14+Report!C15+Report!C16+Report!C17) -> -22238936 | J96: =-(Report!C21+Report!C22) -> 0 | M96: =SUM(I96:L96) -> -22238936 | N96: Tax Shift Report (column 1 - lines C+D+E+F+G+H+I or L+M)
B98: ="001 Tax Revenue for "&Instructions!R2 -> 001 Tax Revenue for FY 2012 | I98: =SUM(I77:I96) -> 170911.33 | J98: =SUM(J77:J96) -> 0 | K98: =SUM(K77:K96) -> 0 | L98: =SUM(L77:L96) -> 0
A102: ="Tax settlements Fiscal Disparities for "&Instructions!P2&" levy" -> Tax settlements Fiscal Disparities for Pay 2011 levy | H102: (Credit) | I102: =I14+I40 -> 0 | J102: =J14+J40 -> 0 | K102: =K14+K40 -> 0 | L102: =L14+L40 -> 0 | M102: =SUM(I102:L102) -> 0 | N102: Tax Settlement Reports (Form 52)
B104: ="009 Fisclal Disparities for "&Instructions!R2 -> 009 Fisclal Disparities for FY 2012 | I104: =SUM(I102) -> 0 | J104: =SUM(J102) -> 0 | K104: =SUM(K102) -> 0 | L104: =SUM(L102) -> 0
A108: ="Tax settlements Taconite homestead credit for "&Instructions!P2&" levy" -> Tax settlements Taconite homestead credit for Pay 2011 levy | H108: (Credit) | I108: =I15+I41 -> 0 | J108: =J15+J41 -> 0 | K108: =K15+K41 -> 0 | L108: =L15+L41 -> 0 | M108: =SUM(I108:L108) -> 0 | N108: Tax Settlement Reports (Form 52)
B110: ="014 Taconite Homestead Credits for "&Instructions!R2 -> 014 Taconite Homestead Credits for FY 2012 | I110: =I108 -> 0 | J110: =J108 -> 0 | K110: =K108 -> 0 | L110: =L108 -> 0
A114: ="Property Tax Shift into "&Instructions!R3 -> Property Tax Shift into FY 2011 | H114: Debit | I114: =Report!D9+Report!D10 -> 36403624 | J114: =Report!D20 -> 1994567.9 | M114: =SUM(I114:L114) -> 38398192 | N114: Tax Shift Report (column 2 - lines A+B or K )
A115: ="Property Tax Shift into "&Instructions!R2 -> Property Tax Shift into FY 2012 | H115: (Credit) | I115: =-(Report!C9+Report!C10) -> -34299696 | J115: =-Report!C20 -> -2395202 | M115: =SUM(I115:L115) -> -36694898 | N115: Tax Shift Report (column 1 - lines A+B or K)
B117: ="020 Property Tax Shift Revenue for "&Instructions!R2 -> 020 Property Tax Shift Revenue for FY 2012 | I117: =SUM(I114:I115) -> 2103927.9 | J117: =SUM(J114:J115) -> -400634.03
A121: Amount of General Ed Aid recognized early for shift with aid reduction | H121: (Credit) | I121: =Report!E123 -> 0 | J121: =Report!E125 -> 0 | M121: =SUM(I121:L121) -> 0 | N121: Tax Shift Entry
B123: ="296 State Aid Adjustment for Shift for "&Instructions!R2 -> 296 State Aid Adjustment for Shift for FY 2012 | I123: =SUM(I121) -> 0 | J123: =SUM(J121) -> 0
A127: ="Reductions to aid payments for "&Instructions!R2&" for property tax shift" -> Reductions to aid payments for FY 2012 for property tax shift | H127: Debit | I127: =-Report!H18 -> -1703911.3 | J127: =-Report!H23 -> 0 | M127: =SUM(I127:L127) -> -1703911.3 | N127: Tax Shift Report (column 5 - line J or N)
A128: Year end payable (receivable) for property tax shift | H128: Debit (Credit) | I128: =-Report!I18 -> -400016.66 | J128: =-Report!I23 -> 400634.03 | M128: =SUM(I128:L128) -> 617.37 | N128: Tax Shift Report (column 6 - line J or N)
B130: ="299 State Aid Adjustment for Shift for "&Instructions!R2 -> 299 State Aid Adjustment for Shift for FY 2012 | I130: =SUM(I127:I128) -> -2103927.9 | J130: =SUM(J127:J128) -> 400634.03

Sheet Entries
A1: Entries to record property taxes | I1: =Report!I1 -> 41115
A4: Jan 1 | B4: Debit | C4: GL 110 | D4: Current Taxes Receivable
B5: Credit | C5: GL 235 | D5: Deferred Revenue
C7: To record current year levy as taxes receivable
A10: Jan 1 | B10: Debit | C10: GL 111 | D10: Delinquent Taxes Receivable
B11: Credit | C11: GL 110 | D11: Current Taxes Receivable
C13: To transfer current taxes receivable to delinquent taxes
A16: Jan - July | B16: Debit | C16: GL 101 | D16: Cash
B17: Credit | C17: GL 110 | D17: Current Taxes Receivable
B18: Credit | C18: GL 111 | D18: Delinquent Taxes Receivable
B19: Credit | C19: SRC 009 | D19: Fiscal Disparities
B20: Credit | C20: SRC 014 | D20: Taconite Homestead Credit
B21: Credit | C21: SRC 019 | D21: Miscellaneous tax revenue
C23: To record first half tax settlements received from counties
A26: June 30 | B26: Debit | C26: GL 235 | D26: Deferred Revenue
B27: Debit | C27: GL 214 | D27: Advance of Unearned Gened
B28: Credit | C28: SRC 001 | D28: Tax Revenue
B29: Credit | C29: SRC 211 | D29: Tax Revenue (Portions with Finance Codes)
C31: To record current year tax shift
B34: Note: Property tax shift entry shown on "Report" tab combines the June 30th entry to record the current year tax shift (entry just above this note) with the prior July 1st entry to reverse the prior year tax shift (entry similar to entry below, but for the previous July 1st).
A39: July 1 | B39: Debit | C39: SRC 001 | D39: Tax Revenue
B40: Debit | C40: SRC 211 | D40: Tax Revenue (Portions with Finance Codes)
B41: Credit | C41: GL 235 | D41: Deferred Revenue
B42: Debit | C42: GL 214 | D42: Advance of Unearned Gened
C44: To reverse prior year tax shift
A47: July 1 | B47: Debit | C47: GL 235 | D47: Deferred Revenue
B48: Credit | C48: SRC 001 | D48: Tax Revenue
B49: Credit | C49: SRC 001 | D49: Tax Revenue (Portions with Finance Codes)
C51: To record levy revenue for current year
A54: July 1 | B54: Debit | C54: SRC 001 | D54: Tax Revenue
B55: Credit | C55: GL 110 | D55: Current Taxes Receivable
C57: To reduce taxes receivable for amount to be paid by state credits
A60: July 1 | B60: Debit | C60: SRC 001 | D60: Tax Revenue
B61: Credit | C61: GL 110 | D61: Current Taxes Receivable
C63: To reduce taxes receivable for amount to be paid by fiscal disparities
A66: July 1 | B66: Debit | C66: SRC 001 | D66: Tax Revenue
B67: Credit | C67: GL 110 | D67: Current Taxes Receivable
C69: To reduce taxes receivable for amount to be paid by taconite homestead credit
A72: July 1 | B72: Debit/Credit | C72: SRC 001 | D72: Tax Revenue
B73: Credit/Debit | C73: GL 110 | D73: Current Taxes Receivable
C75: To adjust taxes receivable for county auditor adjustments
A78: Oct - Jan | B78: Debit | C78: GL 101 | D78: Cash
B79: Credit | C79: GL 110 | D79: Current Taxes Receivable
B80: Credit | C80: GL 111 | D80: Delinquent Taxes Receivable
B81: Credit | C81: GL 009 | D81: Fiscal Disparities
B82: Credit | C82: GL 014 | D82: Taconite Homestead Credit
B83: Credit | C83: SRC 019 | D83: Miscellaneous tax revenue
C85: To record second half tax settlements received from counties
A88: June 30 | B88: Debit | C88: SRC 001 | D88: Tax Revenue
B89: Credit | C89: GL 111 | D89: Delinquent Taxes Receivable
C91: To reduce taxes receivable for abatements
A94: June 30 | B94: Debit | C94: SRC 001 | D94: Tax Revenue
B95: Credit | C95: GL 111 | D95: Delinquent Taxes Receivable
C97: To reduce taxes receivable for seventh-year write offs
A100: June 30 | B100: Debit/Credit | C100: SRC 001 | D100: Tax Revenue
B101: Credit/Debit | C101: GL 231 | D101: Deferred Revenue--Delinquent Taxes
C103: To adjust deferred revenue for delinquent taxes

Sheet Aid Adjust
A1: =Instructions!R2&" Aid Payment (Reduction)" -> FY 2012 Aid Payment (Reduction) | H1: =Report!I1 -> 41115
A2: Positve amount indicates state aid payment
A3: Negative amount indicates reduction to state aid payments
A4: File created from LEVY run under S:\common\TAXSHIFT
D6: General Shift Aid Adjust | E6: Refer Aid Adjust | F6: Total General Aid Adjust | G6: Comm Serv Aid Adjust | H6: Total Aid Adjust
D7: -2.4734801e+08 | E7: -2.455034e+08 | F7: -4.9285142e+08 | G7: -35601749 | H7: -5.2845317e+08
C8: State Total | D8: =SUM(D10:D346) -> 5693766.1 | E8: =SUM(E10:E346) -> -14304632 | F8: =SUM(F10:F346) -> -8610866.3 | G8: =SUM(G10:G346) -> -204065.21 | H8: =SUM(H10:H346) -> -8814931.5
A10: 1 | B10: 1 | C10: AITKIN | D10: =Shift10!D8-Shift11!D8 -> 16354.58 | E10: =Shift10!E8-Shift11!E8 -> 0 | F10: =D10+E10 -> 16354.58 | G10: =Shift10!M8-Shift11!M8 -> 1607.39 | H10: =SUM(F10:G10) -> 17961.97
A11: 1.2 | B11: 3 | C11: MINNEAPOLIS | D11: =Shift10!D9-Shift11!D9 -> 3012712.2 | E11: =Shift10!E9-Shift11!E9 -> -908784.28 | F11: =D11+E11 -> 2103927.9 | G11: =Shift10!M9-Shift11!M9 -> -400634.03 | H11: =SUM(F11:G11) -> 1703293.9
A12: 2 | B12: 1 | C12: HILL CITY | D12: =Shift10!D10-Shift11!D10 -> -13585.7 | E12: =Shift10!E10-Shift11!E10 -> 0 | F12: =D12+E12 -> -13585.7 | G12: =Shift10!M10-Shift11!M10 -> -513.56 | H12: =SUM(F12:G12) -> -14099.26
A13: 4 | B13: 1 | C13: MCGREGOR | D13: =Shift10!D11-Shift11!D11 -> 87838.48 | E13: =Shift10!E11-Shift11!E11 -> 0 | F13: =D13+E13 -> 87838.48 | G13: =Shift10!M11-Shift11!M11 -> -2248.69 | H13: =SUM(F13:G13) -> 85589.79
A14: 6 | B14: 3 | C14: SOUTH ST. PAUL | D14: =Shift10!D12-Shift11!D12 -> -41697.78 | E14: =Shift10!E12-Shift11!E12 -> 103641.93 | F14: =D14+E14 -> 61944.15 | G14: =Shift10!M12-Shift11!M12 -> 999.22 | H14: =SUM(F14:G14) -> 62943.37
A15: 11 | B15: 1 | C15: ANOKA-HENNEPIN | D15: =Shift10!D13-Shift11!D13 -> 2199107.6 | E15: =Shift10!E13-Shift11!E13 -> -308768.4 | F15: =D15+E15 -> 1890339.2 | G15: =Shift10!M13-Shift11!M13 -> 74704.46 | H15: =SUM(F15:G15) -> 1965043.6
A16: 12 | B16: 1 | C16: CENTENNIAL | D16: =Shift10!D14-Shift11!D14 -> -59835.09 | E16: =Shift10!E14-Shift11!E14 -> -681947.78 | F16: =D16+E16 -> -741782.87 | G16: =Shift10!M14-Shift11!M14 -> 13600.76 | H16: =SUM(F16:G16) -> -728182.11
A17: 13 | B17: 1 | C17: COLUMBIA HEIGHTS | D17: =Shift10!D15-Shift11!D15 -> -79953.98 | E17: =Shift10!E15-Shift11!E15 -> -61572.5 | F17: =D17+E17 -> -141526.48 | G17: =Shift10!M15-Shift11!M15 -> -15058.14 | H17: =SUM(F17:G17) -> -156584.62
A18: 14 | B18: 1 | C18: FRIDLEY | D18: =Shift10!D16-Shift11!D16 -> 131811.61 | E18: =Shift10!E16-Shift11!E16 -> 165458.17 | F18: =D18+E18 -> 297269.78 | G18: =Shift10!M16-Shift11!M16 -> -7198.51 | H18: =SUM(F18:G18) -> 290071.27
A19: 15 | B19: 1 | C19: ST. FRANCIS | D19: =Shift10!D17-Shift11!D17 -> 319097.01 | E19: =Shift10!E17-Shift11!E17 -> 121970.06 | F19: =D19+E19 -> 441067.07 | G19: =Shift10!M17-Shift11!M17 -> 24860.94 | H19: =SUM(F19:G19) -> 465928.01
A20: 16 | B20: 1 | C20: SPRING LAKE PARK | D20: =Shift10!D18-Shift11!D18 -> -135051.3 | E20: =Shift10!E18-Shift11!E18 -> -265551.43 | F20: =D20+E20 -> -400602.73 | G20: =Shift10!M18-Shift11!M18 -> -19103.36 | H20: =SUM(F20:G20) -> -419706.09
A21: 22 | B21: 1 | C21: DETROIT LAKES | D21: =Shift10!D19-Shift11!D19 -> 2216.84 | E21: =Shift10!E19-Shift11!E19 -> 7814.34 | F21: =D21+E21 -> 10031.18 | G21: =Shift10!M19-Shift11!M19 -> -5945.62 | H21: =SUM(F21:G21) -> 4085.56
... A346: 2904 | B346: 1 | C346: TRACY AREA | D346: =Shift10!D344-Shift11!D344 -> 23030.14 | E346: =Shift10!E344-Shift11!E344 -> -14354.01 | F346: =D346+E346 -> 8676.13 | G346: =Shift10!M344-Shift11!M344 -> 1736.97 | H346: =SUM(F346:G346) -> 10413.1

Sheet Shift11
A1: =Instructions!P1&" Gross Shift" -> Pay 2012 Gross Shift | Q1: =Report!I1 -> 41115
A3: Shift at | B3: 0.486
D4: Genl with Aid Adjust | E4: Refer with Aid Adjust | F4: Refer No Aid Adjust | G4: Addl Refer Shift | H4: Career Technical | I4: 100% Shift | J4: Reemploy Resv | K4: Reemploy Unrsv | L4: Leg Changes Genl Fund | M4: Comm Serv at Shift % | N4: Leg Changes Comm Serv | O4: Total Gross Shift | P4: Total General Fund Shift | Q4: Total Comm Serv Fund Shift
C6: State Total | D6: =SUM(D8:D344) -> 2.4165425e+08 | E6: =SUM(E8:E344) -> 2.5980804e+08 | F6: =SUM(F8:F344) -> 1.1422854e+08 | G6: =SUM(G8:G344) -> 4282529.2 | H6: =SUM(H8:H344) -> 17147576 | I6: =SUM(I8:I344) -> 28857584 | J6: =SUM(J8:J344) -> -139906.18 | K6: =SUM(K8:K344) -> 19088375 | ... Q6: =SUM(Q8:Q344) -> 35805814
A8: 1 | B8: 1 | C8: AITKIN | D8: =ROUND(Data!AA8*$B$3,2) -> 400273.22 | E8: =MAX(0,Data!AD8-Data!Y8) -> 0 | F8: =Data!Y8 -> 141143.88 | G8: =Data!X8 -> 0 | H8: =Data!K8+Data!R8 -> 29961.63 | I8: =Data!I8+Data!L8+Data!M8+Data!N8+Data!O8+Data!S8 -> 0 | J8: =Data!Q8 -> 0 | K8: =Data!J8+Data!P8 -> 1882.81 | L8: =Data!T8 -> 0 | M8: =ROUND(Data!AB8*$B$3,2) -> 897.18 | N8: =Data!U8 -> 0 | O8: =SUM(D8:N8) -> 574158.72 | P8: =SUM(D8:L8) -> 573261.54 | Q8: =SUM(M8:N8) -> 897.18
A9: 1.2 | B9: 3 | C9: MINNEAPOLIS | D9: =ROUND(Data!AA9*$B$3,2) -> 11569510 | E9: =MAX(0,Data!AD9-Data!Y9) -> 22730186 | F9: =Data!Y9 -> 10049626 | G9: =Data!X9 -> 1205612.7 | H9: =Data!K9+Data!R9 -> 551214.14 | I9: =Data!I9+Data!L9+Data!M9+Data!N9+Data!O9+Data!S9 -> 8657778.7 | J9: =Data!Q9 -> 0 | K9: =Data!J9+Data!P9 -> 1774703.8 | L9: =Data!T9 -> 0 | M9: =ROUND(Data!AB9*$B$3,2) -> 2395202 | N9: =Data!U9 -> 0 | O9: =SUM(D9:N9) -> 58933834 | P9: =SUM(D9:L9) -> 56538632 | Q9: =SUM(M9:N9) -> 2395202
A10: 2 | B10: 1 | C10: HILL CITY | D10: =ROUND(Data!AA10*$B$3,2) -> 60705.45 | E10: =MAX(0,Data!AD10-Data!Y10) -> 0 | F10: =Data!Y10 -> 0 | G10: =Data!X10 -> 0 | H10: =Data!K10+Data!R10 -> 10000 | I10: =Data!I10+Data!L10+Data!M10+Data!N10+Data!O10+Data!S10 -> 0 | J10: =Data!Q10 -> 0 | K10: =Data!J10+Data!P10 -> 16031.66 | L10: =Data!T10 -> 0 | M10: =ROUND(Data!AB10*$B$3,2) -> 9705.42 | N10: =Data!U10 -> 0 | O10: =SUM(D10:N10) -> 96442.53 | P10: =SUM(D10:L10) -> 86737.11 | Q10: =SUM(M10:N10) -> 9705.42
A11: 4 | B11: 1 | C11: MCGREGOR | D11: =ROUND(Data!AA11*$B$3,2) -> 84723.02 | E11: =MAX(0,Data!AD11-Data!Y11) -> 0 | F11: =Data!Y11 -> 51784.65 | G11: =Data!X11 -> 0 | H11: =Data!K11+Data!R11 -> 11665.08 | I11: =Data!I11+Data!L11+Data!M11+Data!N11+Data!O11+Data!S11 -> 0 | J11: =Data!Q11 -> 0 | K11: =Data!J11+Data!P11 -> -12981.29 | L11: =Data!T11 -> 0 | M11: =ROUND(Data!AB11*$B$3,2) -> 27577.1 | N11: =Data!U11 -> 0 | O11: =SUM(D11:N11) -> 162768.56 | P11: =SUM(D11:L11) -> 135191.46 | Q11: =SUM(M11:N11) -> 27577.1
A12: 6 | B12: 3 | C12: SOUTH ST. PAUL | D12: =ROUND(Data!AA12*$B$3,2) -> 1342633.1 | E12: =MAX(0,Data!AD12-Data!Y12) -> 1092426.5 | F12: =Data!Y12 -> 360711.07 | G12: =Data!X12 -> 0 | H12: =Data!K12+Data!R12 -> 70749.16 | I12: =Data!I12+Data!L12+Data!M12+Data!N12+Data!O12+Data!S12 -> 0 | J12: =Data!Q12 -> 0 | K12: =Data!J12+Data!P12 -> 60297.28 | L12: =Data!T12 -> 0 | M12: =ROUND(Data!AB12*$B$3,2) -> 145894.77 | N12: =Data!U12 -> 0 | O12: =SUM(D12:N12) -> 3072711.9 | P12: =SUM(D12:L12) -> 2926817.1 | Q12: =SUM(M12:N12) -> 145894.77
A13: 11 | B13: 1 | C13: ANOKA-HENNEPIN | D13: =ROUND(Data!AA13*$B$3,2) -> 9693090.9 | E13: =MAX(0,Data!AD13-Data!Y13) -> 21313952 | F13: =Data!Y13 -> 3515884.7 | G13: =Data!X13 -> 197692.1 | H13: =Data!K13+Data!R13 -> 939930.34 | I13: =Data!I13+Data!L13+Data!M13+Data!N13+Data!O13+Data!S13 -> 0 | J13: =Data!Q13 -> 0 | K13: =Data!J13+Data!P13 -> 805350.9 | L13: =Data!T13 -> 0 | M13: =ROUND(Data!AB13*$B$3,2) -> 1509866.1 | N13: =Data!U13 -> 0 | O13: =SUM(D13:N13) -> 37975767 | P13: =SUM(D13:L13) -> 36465901 | Q13: =SUM(M13:N13) -> 1509866.1
A14: 12 | B14: 1 | C14: CENTENNIAL | D14: =ROUND(Data!AA14*$B$3,2) -> 1629289.2 | E14: =MAX(0,Data!AD14-Data!Y14) -> 2426127.1 | F14: =Data!Y14 -> 320094.52 | G14: =Data!X14 -> 16533.75 | H14: =Data!K14+Data!R14 -> 115112.6 | I14: =Data!I14+Data!L14+Data!M14+Data!N14+Data!O14+Data!S14 -> 0 | J14: =Data!Q14 -> 0 | K14: =Data!J14+Data!P14 -> 121208.84 | L14: =Data!T14 -> 0 | M14: =ROUND(Data!AB14*$B$3,2) -> 211746.12 | N14: =Data!U14 -> 0 | O14: =SUM(D14:N14) -> 4840112.1 | P14: =SUM(D14:L14) -> 4628366 | Q14: =SUM(M14:N14) -> 211746.12
A15: 13 | B15: 1 | C15: COLUMBIA HEIGHTS | D15: =ROUND(Data!AA15*$B$3,2) -> 1036557.9 | E15: =MAX(0,Data!AD15-Data!Y15) -> 810891.79 | F15: =Data!Y15 -> 848958.71 | G15: =Data!X15 -> 0 | H15: =Data!K15+Data!R15 -> 63473.1 | I15: =Data!I15+Data!L15+Data!M15+Data!N15+Data!O15+Data!S15 -> 0 | J15: =Data!Q15 -> 0 | K15: =Data!J15+Data!P15 -> 32224.07 | L15: =Data!T15 -> 0 | M15: =ROUND(Data!AB15*$B$3,2) -> 154587.27 | N15: =Data!U15 -> 0 | O15: =SUM(D15:N15) -> 2946692.9 | P15: =SUM(D15:L15) -> 2792105.6 | Q15: =SUM(M15:N15) -> 154587.27
A16: 14 | B16: 1 | C16: FRIDLEY | D16: =ROUND(Data!AA16*$B$3,2) -> 1100248.8 | E16: =MAX(0,Data!AD16-Data!Y16) -> 752276.98 | F16: =Data!Y16 -> 468605.33 | G16: =Data!X16 -> 0 | H16: =Data!K16+Data!R16 -> 68582.56 | I16: =Data!I16+Data!L16+Data!M16+Data!N16+Data!O16+Data!S16 -> 0 | J16: =Data!Q16 -> 0 | K16: =Data!J16+Data!P16 -> 106303.92 | L16: =Data!T16 -> 0 | M16: =ROUND(Data!AB16*$B$3,2) -> 226560.16 | N16: =Data!U16 -> 0 | O16: =SUM(D16:N16) -> 2722577.7 | P16: =SUM(D16:L16) -> 2496017.5 | Q16: =SUM(M16:N16) -> 226560.16
A17: 15 | B17: 1 | C17: ST. FRANCIS | D17: =ROUND(Data!AA17*$B$3,2) -> 1089099.9 | E17: =MAX(0,Data!AD17-Data!Y17) -> 596767.85 | F17: =Data!Y17 -> 288492.79 | G17: =Data!X17 -> 0 | H17: =Data!K17+Data!R17 -> 125814.1 | I17: =Data!I17+Data!L17+Data!M17+Data!N17+Data!O17+Data!S17 -> 0 | J17: =Data!Q17 -> 0 | K17: =Data!J17+Data!P17 -> 323183.08 | L17: =Data!T17 -> 0 | M17: =ROUND(Data!AB17*$B$3,2) -> 170083.7 | N17: =Data!U17 -> 0 | O17: =SUM(D17:N17) -> 2593441.4 | P17: =SUM(D17:L17) -> 2423357.7 | Q17: =SUM(M17:N17) -> 170083.7
A18: 16 | B18: 1 | C18: SPRING LAKE PARK | D18: =ROUND(Data!AA18*$B$3,2) -> 2060036.8 | E18: =MAX(0,Data!AD18-Data!Y18) -> 1682306.2 | F18: =Data!Y18 -> 804793.86 | G18: =Data!X18 -> 73286.44 | H18: =Data!K18+Data!R18 -> 81433.57 | I18: =Data!I18+Data!L18+Data!M18+Data!N18+Data!O18+Data!S18 -> 0 | J18: =Data!Q18 -> 0 | K18: =Data!J18+Data!P18 -> 83924.13 | L18: =Data!T18 -> 0 | M18: =ROUND(Data!AB18*$B$3,2) -> 225326.21 | N18: =Data!U18 -> 0 | O18: =SUM(D18:N18) -> 5011107.2 | P18: =SUM(D18:L18) -> 4785781 | Q18: =SUM(M18:N18) -> 225326.21
A19: 22 | B19: 1 | C19: DETROIT LAKES | D19: =ROUND(Data!AA19*$B$3,2) -> 697179.97 | E19: =MAX(0,Data!AD19-Data!Y19) -> 516047.57 | F19: =Data!Y19 -> 133298.49 | G19: =Data!X19 -> 0 | H19: =Data!K19+Data!R19 -> 56261.09 | I19: =Data!I19+Data!L19+Data!M19+Data!N19+Data!O19+Data!S19 -> 0 | J19: =Data!Q19 -> 0 | K19: =Data!J19+Data!P19 -> 40886.23 | L19: =Data!T19 -> 0 | M19: =ROUND(Data!AB19*$B$3,2) -> 102490.6 | N19: =Data!U19 -> 0 | O19: =SUM(D19:N19) -> 1546164 | P19: =SUM(D19:L19) -> 1443673.4 | Q19: =SUM(M19:N19) -> 102490.6
... A344: 2904 | B344: 1 | C344: TRACY AREA | D344: =ROUND(Data!AA344*$B$3,2) -> 180455 | E344: =MAX(0,Data!AD344-Data!Y344) -> 173663.18 | F344: =Data!Y344 -> 99195.2 | G344: =Data!X344 -> 4004.21 | H344: =Data!K344+Data!R344 -> 20309.01 | I344: =Data!I344+Data!L344+Data!M344+Data!N344+Data!O344+Data!S344 -> 0 | J344: =Data!Q344 -> 0 | K344: =Data!J344+Data!P344 -> -6973.8 | L344: =Data!T344 -> 0 | M344: =ROUND(Data!AB344*$B$3,2) -> 34228.49 | N344: =Data!U344 -> 0 | O344: =SUM(D344:N344) -> 504881.29 | P344: =SUM(D344:L344) -> 470652.8 | Q344: =SUM(M344:N344) -> 34228.49

Sheet Data
A1: =Levy!A3 -> Pay 2012 Levy | AD1: =Report!I1 -> 41115
I3: From Certified Levy Summaries
D4: Genl RMV Voter | E4: Genl RMV Other | F4: Genl NTC Voter | G4: Genl NTC Other | H4: Comm Service | I4: Integ--1st Class | J4: Reemploy | K4: Career Technical | L4: Hea Ben | M4: Addl Retire | N4: Int Adj PY--1st Class | O4: Int Adj 2YP--1st Class | P4: Reemploy Adjust Unreserved | Q4: Reemploy Adjust Reserved | R4: Career Tech Adjust | S4: Hea Ben Adjust | T4: Legislative Changes Genl Fund | U4: Legislative Changes Comm Serv | V4: Prinsburg Exclusion RMV Voter | W4: Prinsburg Exclusion NTC Voter | X4: Add'l Referendum | Y4: Pay 2001 Refer Shift | Z4: 100% Shift Total | AA4: Shiftable Oth Gen (E+F+G-U-X-Y-AA) | AB4: Shiftable Comm Serv (H-T-V) | AC4: =Instructions!P1&" Refer at Shift Percent" -> Pay 2012 Refer at Shift Percent | AD4: ="Refer (GTR of "&Instructions!P1&" or Pay 2001)" -> Refer (GTR of Pay 2012 or Pay 2001)
AA5: 5.0894653e+08 | AB5: 73254628
C6: State Total | D6: =SUM(D8:D344) -> 7.6354564e+08 | E6: =SUM(E8:E344) -> 91927344 | F6: =SUM(F8:F344) -> 47134874 | G6: =SUM(G8:G344) -> 4.2705476e+08 | H6: =SUM(H8:H344) -> 73674515 | I6: =SUM(I8:I344) -> 12677369 | J6: =SUM(J8:J344) -> 12942173 | K6: =SUM(K8:K344) -> 17615396 | ... AD6: =SUM(AD8:AD344) -> 3.7403658e+08
A8: 1 | B8: 1 | C8: AITKIN | D8: =Levy!F8 -> 81.54 | E8: =Levy!G8 -> 352047.5 | F8: =Levy!H8 -> 0 | G8: =Levy!I8 -> 503404.39 | H8: =Levy!J8 -> 1846.04 | I8: 0 | J8: 5964 | K8: 30312.4 | L8: 0 | M8: 0 | N8: 0 | O8: 0 | P8: -4081.19 | Q8: 0 | R8: -350.77 | S8: 0 | T8: 0 | U8: 0 | V8: 0 | W8: 0 | X8: 0 | Y8: 141143.88 | Z8: =SUM(I8:T8) -> 31844.44 | AA8: =ROUND(MAX(E8+F8+G8-W8-X8-Z8,0),2) -> 823607.45 | AB8: =ROUND(MAX(H8-U8,0),2) -> 1846.04 | AC8: =ROUND(MAX(0,(D8-V8)*Shift11!$B$3),2) -> 39.63 | AD8: =MAX(AC8,Y8) -> 141143.88
A9: 1.2 | B9: 3 | C9: MINNEAPOLIS | D9: =Levy!F9 -> 67448174 | E9: =Levy!G9 -> 8500163.8 | F9: =Levy!H9 -> 0 | G9: =Levy!I9 -> 27494722 | H9: =Levy!J9 -> 4928399.1 | I9: 6300349.8 | J9: 1428745 | K9: 553068.44 | L9: 0 | M9: 2250000 | N9: 70370.65 | O9: 37058.2 | P9: 345958.81 | Q9: 0 | R9: -1854.3 | S9: 0 | T9: 0 | U9: 0 | V9: 0 | W9: 0 | X9: 1205612.7 | Y9: 10049626 | Z9: =SUM(I9:T9) -> 10983697 | AA9: =ROUND(MAX(E9+F9+G9-W9-X9-Z9,0),2) -> 23805577 | AB9: =ROUND(MAX(H9-U9,0),2) -> 4928399.1 | AC9: =ROUND(MAX(0,(D9-V9)*Shift11!$B$3),2) -> 32779812 | AD9: =MAX(AC9,Y9) -> 32779812
A10: 2 | B10: 1 | C10: HILL CITY | D10: =Levy!F10 -> 0 | E10: =Levy!G10 -> 33615 | F10: =Levy!H10 -> 0 | G10: =Levy!I10 -> 117325 | H10: =Levy!J10 -> 19970 | I10: 0 | J10: 15688.59 | K10: 10000 | L10: 0 | M10: 0 | N10: 0 | O10: 0 | P10: 343.07 | Q10: 0 | R10: 0 | S10: 0 | T10: 0 | U10: 0 | V10: 0 | W10: 0 | X10: 0 | Y10: 0 | Z10: =SUM(I10:T10) -> 26031.66 | AA10: =ROUND(MAX(E10+F10+G10-W10-X10-Z10,0),2) -> 124908.34 | AB10: =ROUND(MAX(H10-U10,0),2) -> 19970 | AC10: =ROUND(MAX(0,(D10-V10)*Shift11!$B$3),2) -> 0 | AD10: =MAX(AC10,Y10) -> 0
A11: 4 | B11: 1 | C11: MCGREGOR | D11: =Levy!F11 -> 0 | E11: =Levy!G11 -> 66483 | F11: =Levy!H11 -> 0 | G11: =Levy!I11 -> 106528 | H11: =Levy!J11 -> 56743 | I11: 0 | J11: 247.02 | K11: 11665.08 | L11: 0 | M11: 0 | N11: 0 | O11: 0 | P11: -13228.31 | Q11: 0 | R11: 0 | S11: 0 | T11: 0 | U11: 0 | V11: 0 | W11: 0 | X11: 0 | Y11: 51784.65 | Z11: =SUM(I11:T11) -> -1316.21 | AA11: =ROUND(MAX(E11+F11+G11-W11-X11-Z11,0),2) -> 174327.21 | AB11: =ROUND(MAX(H11-U11,0),2) -> 56743 | AC11: =ROUND(MAX(0,(D11-V11)*Shift11!$B$3),2) -> 0 | AD11: =MAX(AC11,Y11) -> 51784.65
A12: 6 | B12: 3 | C12: SOUTH ST. PAUL | D12: =Levy!F12 -> 2989995 | E12: =Levy!G12 -> 380899 | F12: =Levy!H12 -> 591403 | G12: =Levy!I12 -> 1921364 | H12: =Levy!J12 -> 300195 | I12: 0 | J12: 40000 | K12: 72643.56 | L12: 0 | M12: 0 | N12: 0 | O12: 0 | P12: 20297.28 | Q12: 0 | R12: -1894.4 | S12: 0 | T12: 0 | U12: 0 | V12: 0 | W12: 0 | X12: 0 | Y12: 360711.07 | Z12: =SUM(I12:T12) -> 131046.44 | AA12: =ROUND(MAX(E12+F12+G12-W12-X12-Z12,0),2) -> 2762619.6 | AB12: =ROUND(MAX(H12-U12,0),2) -> 300195 | AC12: =ROUND(MAX(0,(D12-V12)*Shift11!$B$3),2) -> 1453137.6 | AD12: =MAX(AC12,Y12) -> 1453137.6
A13: 11 | B13: 1 | C13: ANOKA-HENNEPIN | D13: =Levy!F13 -> 51090199 | E13: =Levy!G13 -> 3820592.4 | F13: =Levy!H13 -> 3000000 | G13: =Levy!I13 -> 15067013 | H13: =Levy!J13 -> 3106720.4 | I13: 0 | J13: 500000 | K13: 953759.94 | L13: 0 | M13: 0 | N13: 0 | O13: 0 | P13: 305350.9 | Q13: 0 | R13: -13829.6 | S13: 0 | T13: 0 | U13: 0 | V13: 0 | W13: 0 | X13: 197692.1 | Y13: 3515884.7 | Z13: =SUM(I13:T13) -> 1745281.2 | AA13: =ROUND(MAX(E13+F13+G13-W13-X13-Z13,0),2) -> 19944632 | AB13: =ROUND(MAX(H13-U13,0),2) -> 3106720.4 | AC13: =ROUND(MAX(0,(D13-V13)*Shift11!$B$3),2) -> 24829837 | AD13: =MAX(AC13,Y13) -> 24829837
A14: 12 | B14: 1 | C14: CENTENNIAL | D14: =Levy!F14 -> 5650661.7 | E14: =Levy!G14 -> 764942.25 | F14: =Levy!H14 -> 0 | G14: =Levy!I14 -> 2840359.9 | H14: =Levy!J14 -> 435691.6 | I14: 0 | J14: 75000 | K14: 115112.6 | L14: 0 | M14: 0 | N14: 0 | O14: 0 | P14: 46208.84 | Q14: 0 | R14: 0 | S14: 0 | T14: 0 | U14: 0 | V14: 0 | W14: 0 | X14: 16533.75 | Y14: 320094.52 | Z14: =SUM(I14:T14) -> 236321.44 | AA14: =ROUND(MAX(E14+F14+G14-W14-X14-Z14,0),2) -> 3352447 | AB14: =ROUND(MAX(H14-U14,0),2) -> 435691.6 | AC14: =ROUND(MAX(0,(D14-V14)*Shift11!$B$3),2) -> 2746221.6 | AD14: =MAX(AC14,Y14) -> 2746221.6
A15: 13 | B15: 1 | C15: COLUMBIA HEIGHTS | D15: =Levy!F15 -> 3415330.2 | E15: =Levy!G15 -> 399163.32 | F15: =Levy!H15 -> 0 | G15: =Levy!I15 -> 1829369.1 | H15: =Levy!J15 -> 318080.81 | I15: 0 | J15: 20000 | K15: 62336.3 | L15: 0 | M15: 0 | N15: 0 | O15: 0 | P15: 12224.07 | Q15: 0 | R15: 1136.8 | S15: 0 | T15: 0 | U15: 0 | V15: 0 | W15: 0 | X15: 0 | Y15: 848958.71 | Z15: =SUM(I15:T15) -> 95697.17 | AA15: =ROUND(MAX(E15+F15+G15-W15-X15-Z15,0),2) -> 2132835.3 | AB15: =ROUND(MAX(H15-U15,0),2) -> 318080.81 | AC15: =ROUND(MAX(0,(D15-V15)*Shift11!$B$3),2) -> 1659850.5 | AD15: =MAX(AC15,Y15) -> 1659850.5
A16: 14 | B16: 1 | C16: FRIDLEY | D16: =Levy!F16 -> 2512103.5 | E16: =Levy!G16 -> 336673.52 | F16: =Levy!H16 -> 741000 | G16: =Levy!I16 -> 1361099.3 | H16: =Levy!J16 -> 466173.16 | I16: 0 | J16: 94000 | K16: 68582.56 | L16: 0 | M16: 0 | N16: 0 | O16: 0 | P16: 12303.92 | Q16: 0 | R16: 0 | S16: 0 | T16: 0 | U16: 0 | V16: 0 | W16: 0 | X16: 0 | Y16: 468605.33 | Z16: =SUM(I16:T16) -> 174886.48 | AA16: =ROUND(MAX(E16+F16+G16-W16-X16-Z16,0),2) -> 2263886.3 | AB16: =ROUND(MAX(H16-U16,0),2) -> 466173.16 | AC16: =ROUND(MAX(0,(D16-V16)*Shift11!$B$3),2) -> 1220882.3 | AD16: =MAX(AC16,Y16) -> 1220882.3
A17: 15 | B17: 1 | C17: ST. FRANCIS | D17: =Levy!F17 -> 1821524 | E17: =Levy!G17 -> 578387.61 | F17: =Levy!H17 -> 0 | G17: =Levy!I17 -> 2111555.8 | H17: =Levy!J17 -> 349966.46 | I17: 0 | J17: 150000 | K17: 136178.1 | L17: 0 | M17: 0 | N17: 0 | O17: 0 | P17: 173183.08 | Q17: 0 | R17: -10364 | S17: 0 | T17: 0 | U17: 0 | V17: 0 | W17: 0 | X17: 0 | Y17: 288492.79 | Z17: =SUM(I17:T17) -> 448997.18 | AA17: =ROUND(MAX(E17+F17+G17-W17-X17-Z17,0),2) -> 2240946.2 | AB17: =ROUND(MAX(H17-U17,0),2) -> 349966.46 | AC17: =ROUND(MAX(0,(D17-V17)*Shift11!$B$3),2) -> 885260.64 | AD17: =MAX(AC17,Y17) -> 885260.64
A18: 16 | B18: 1 | C18: SPRING LAKE PARK | D18: =Levy!F18 -> 5117489.9 | E18: =Levy!G18 -> 876015 | F18: =Levy!H18 -> 1065985 | G18: =Levy!I18 -> 2535402.9 | H18: =Levy!J18 -> 463634.17 | I18: 0 | J18: 75000 | K18: 90781.02 | L18: 0 | M18: 0 | N18: 0 | O18: 0 | P18: 8924.13 | Q18: 0 | R18: -9347.45 | S18: 0 | T18: 0 | U18: 0 | V18: 0 | W18: 0 | X18: 73286.44 | Y18: 804793.86 | Z18: =SUM(I18:T18) -> 165357.7 | AA18: =ROUND(MAX(E18+F18+G18-W18-X18-Z18,0),2) -> 4238758.8 | AB18: =ROUND(MAX(H18-U18,0),2) -> 463634.17 | AC18: =ROUND(MAX(0,(D18-V18)*Shift11!$B$3),2) -> 2487100.1 | AD18: =MAX(AC18,Y18) -> 2487100.1
A19: 22 | B19: 1 | C19: DETROIT LAKES | D19: =Levy!F19 -> 1336103 | E19: =Levy!G19 -> 382290 | F19: =Levy!H19 -> 0 | G19: =Levy!I19 -> 1149384 | H19: =Levy!J19 -> 210886 | I19: 0 | J19: 15000 | K19: 56261.09 | L19: 0 | M19: 0 | N19: 0 | O19: 0 | P19: 25886.23 | Q19: 0 | R19: 0 | S19: 0 | T19: 0 | U19: 0 | V19: 0 | W19: 0 | X19: 0 | Y19: 133298.49 | Z19: =SUM(I19:T19) -> 97147.32 | AA19: =ROUND(MAX(E19+F19+G19-W19-X19-Z19,0),2) -> 1434526.7 | AB19: =ROUND(MAX(H19-U19,0),2) -> 210886 | AC19: =ROUND(MAX(0,(D19-V19)*Shift11!$B$3),2) -> 649346.06 | AD19: =MAX(AC19,Y19) -> 649346.06
... A287: 2155 | B287: 1 | C287: WADENA-DEER CREE | D287: =Levy!F287 -> 573218 | E287: =Levy!G287 -> 64669 | F287: =Levy!H287 -> 0 | G287: =Levy!I287 -> 249637 | H287: =Levy!J287 -> 68530 | I287: 0 | J287: 20000 | K287: 34784.42 | L287: 0 | M287: 0 | N287: 0 | O287: 0 | P287: -1405.99 | Q287: 0 | R287: 0 | S287: 0 | T287: 0 | U287: 0 | V287: 0 | W287: 0 | X287: 0 | Y287: 38157.32 | Z287: =SUM(I287:T287) -> 53378.43 | AA287: =ROUND(MAX(E287+F287+G287-W287-X287-Z287,0),2) -> 260927.57 | AB287: =ROUND(MAX(H287-U287,0),2) -> 68530 | AC287: =ROUND(MAX(0,(D287-V287)*Shift11!$B$3),2) -> 278583.95 | AD287: =MAX(AC287,Y287) -> 278583.95
A288: 2159 | B288: 1 | C288: BUFFALO LAKE-HEC | D288: =Levy!F288 -> 501124.39 | E288: =Levy!G288 -> 53588.49 | F288: =Levy!H288 -> 0 | G288: =Levy!I288 -> 290062.04 | H288: =Levy!J288 -> 45624.79 | I288: 0 | J288: 15000 | K288: 13904.77 | L288: 0 | M288: 0 | N288: 0 | O288: 0 | P288: 9915.73 | Q288: 0 | R288: -107.2 | S288: 0 | T288: 0 | U288: 0 | V288: 0 | W288: 0 | X288: =22933.81+919.38 -> 23853.19 | Y288: =98779.38+3741.29 -> 102520.67 | Z288: =SUM(I288:T288) -> 38713.3 | AA288: =ROUND(MAX(E288+F288+G288-W288-X288-Z288,0),2) -> 281084.04 | AB288: =ROUND(MAX(H288-U288,0),2) -> 45624.79 | AC288: =ROUND(MAX(0,(D288-V288)*Shift11!$B$3),2) -> 243546.45 | AD288: =MAX(AC288,Y288) -> 243546.45
A289: 2164 | B289: 1 | C289: DILWORTH-GLYNDON | D289: =Levy!F289 -> 321243.8 | E289: =Levy!G289 -> 114871.4 | F289: =Levy!H289 -> 0 | G289: =Levy!I289 -> 148291.22 | H289: =Levy!J289 -> 75618.63 | I289: 0 | J289: 3700 | K289: 22306.11 | L289: 0 | M289: 0 | N289: 0 | O289: 0 | P289: -1538.69 | Q289: 0 | R289: -5794.94 | S289: 0 | T289: 0 | U289: 0 | V289: 0 | W289: 0 | X289: 0 | Y289: 55510.33 | Z289: =SUM(I289:T289) -> 18672.48 | AA289: =ROUND(MAX(E289+F289+G289-W289-X289-Z289,0),2) -> 244490.14 | AB289: =ROUND(MAX(H289-U289,0),2) -> 75618.63 | AC289: =ROUND(MAX(0,(D289-V289)*Shift11!$B$3),2) -> 156124.49 | AD289: =MAX(AC289,Y289) -> 156124.49
A290: 2165 | B290: 1 | C290: HINCKLEY-FINLAYS | D290: =Levy!F290 -> 273077.14 | E290: =Levy!G290 -> 102425.44 | F290: =Levy!H290 -> 0 | G290: =Levy!I290 -> 304183.13 | H290: =Levy!J290 -> 74225.44 | I290: 0 | J290: 6590.96 | K290: 7886.34 | L290: 0 | M290: 0 | N290: 0 | O290: 0 | P290: 0 | Q290: 0 | R290: 4967.08 | S290: 0 | T290: 0 | U290: 0 | V290: 0 | W290: 0 | X290: 0 | Y290: 51707.97 | Z290: =SUM(I290:T290) -> 19444.38 | AA290: =ROUND(MAX(E290+F290+G290-W290-X290-Z290,0),2) -> 387164.19 | AB290: =ROUND(MAX(H290-U290,0),2) -> 74225.44 | AC290: =ROUND(MAX(0,(D290-V290)*Shift11!$B$3),2) -> 132715.49 | AD290: =MAX(AC290,Y290) -> 132715.49
A291: 2167 | B291: 1 | C291: LAKEVIEW | D291: =Levy!F291 -> 252260 | E291: =Levy!G291 -> 38001 | F291: =Levy!H291 -> 0 | G291: =Levy!I291 -> 287231 | H291: =Levy!J291 -> 38437 | I291: 0 | J291: 0 | K291: 12430.08 | L291: 0 | M291: 0 | N291: 0 | O291: 0 | P291: -6055.53 | Q291: 0 | R291: 0 | S291: 0 | T291: 0 | U291: 0 | V291: 0 | W291: 0 | X291: 5689.16 | Y291: 31840.2 | Z291: =SUM(I291:T291) -> 6374.55 | AA291: =ROUND(MAX(E291+F291+G291-W291-X291-Z291,0),2) -> 313168.29 | AB291: =ROUND(MAX(H291-U291,0),2) -> 38437 | AC291: =ROUND(MAX(0,(D291-V291)*Shift11!$B$3),2) -> 122598.36 | AD291: =MAX(AC291,Y291) -> 122598.36
A292: 2168 | B292: 1 | C292: N.R.H.E.G. | D292: =Levy!F292 -> 292830 | E292: =Levy!G292 -> 84905 | F292: =Levy!H292 -> 0 | G292: =Levy!I292 -> 382972 | H292: =Levy!J292 -> 66922 | I292: 0 | J292: 23052.71 | K292: 24113.11 | L292: 0 | M292: 0 | N292: 0 | O292: 0 | P292: 12332.05 | Q292: 0 | R292: -1839.2 | S292: 0 | T292: 0 | U292: 0 | V292: 0 | W292: 0 | X292: 11668.37 | Y292: 77590.1 | Z292: =SUM(I292:T292) -> 57658.67 | AA292: =ROUND(MAX(E292+F292+G292-W292-X292-Z292,0),2) -> 398549.96 | AB292: =ROUND(MAX(H292-U292,0),2) -> 66922 | AC292: =ROUND(MAX(0,(D292-V292)*Shift11!$B$3),2) -> 142315.38 | AD292: =MAX(AC292,Y292) -> 142315.38
A293: 2169 | B293: 1 | C293: MURRAY COUNTY CE | D293: =Levy!F293 -> 759665.44 | E293: =Levy!G293 -> 39880.02 | F293: =Levy!H293 -> 0 | G293: =Levy!I293 -> 342136.64 | H293: =Levy!J293 -> 72909.22 | I293: 0 | J293: 6000 | K293: 17451.14 | L293: 0 | M293: 0 | N293: 0 | O293: 0 | P293: -3609.65 | Q293: 0 | R293: 0 | S293: 0 | T293: 0 | U293: 0 | V293: 0 | W293: 0 | X293: 5478.96 | Y293: 61280.65 | Z293: =SUM(I293:T293) -> 19841.49 | AA293: =ROUND(MAX(E293+F293+G293-W293-X293-Z293,0),2) -> 356696.21 | AB293: =ROUND(MAX(H293-U293,0),2) -> 72909.22 | AC293: =ROUND(MAX(0,(D293-V293)*Shift11!$B$3),2) -> 369197.4 | AD293: =MAX(AC293,Y293) -> 369197.4
A294: 2170 | B294: 1 | C294: STAPLES-MOTLEY | D294: =Levy!F294 -> 523983 | E294: =Levy!G294 -> 143122 | F294: =Levy!H294 -> 0 | G294: =Levy!I294 -> 335934 | H294: =Levy!J294 -> 126733 | I294: 0 | J294: 20000 | K294: 70965.22 | L294: 0 | M294: 0 | N294: 0 | O294: 0 | P294: -11625.03 | Q294: 0 | R294: 0 | S294: 0 | T294: 0 | U294: 0 | V294: 0 | W294: 0 | X294: 0 | Y294: 78553.36 | Z294: =SUM(I294:T294) -> 79340.19 | AA294: =ROUND(MAX(E294+F294+G294-W294-X294-Z294,0),2) -> 399715.81 | AB294: =ROUND(MAX(H294-U294,0),2) -> 126733 | AC294: =ROUND(MAX(0,(D294-V294)*Shift11!$B$3),2) -> 254655.74 | AD294: =MAX(AC294,Y294) -> 254655.74
A295: 2171 | B295: 1 | C295: KITTSON CENTRAL | D295: =Levy!F295 -> 348763.83 | E295: =Levy!G295 -> 15157.84 | F295: =Levy!H295 -> 0 | G295: =Levy!I295 -> 160183.08 | H295: =Levy!J295 -> 29111 | I295: 0 | J295: 0 | K295: 11665.08 | L295: 0 | M295: 0 | N295: 0 | O295: 0 | P295: -5000 | Q295: 0 | R295: 0 | S295: 0 | T295: 0 | U295: 0 | V295: 0 | W295: 0 | X295: 0 | Y295: 312434.6 | Z295: =SUM(I295:T295) -> 6665.08 | AA295: =ROUND(MAX(E295+F295+G295-W295-X295-Z295,0),2) -> 168675.84 | AB295: =ROUND(MAX(H295-U295,0),2) -> 29111 | AC295: =ROUND(MAX(0,(D295-V295)*Shift11!$B$3),2) -> 169499.22 | AD295: =MAX(AC295,Y295) -> 312434.6
A296: 2172 | B296: 1 | C296: KENYON-WANAMINGO | D296: =Levy!F296 -> 749940 | E296: =Levy!G296 -> 78377 | F296: =Levy!H296 -> 0 | G296: =Levy!I296 -> 370951 | H296: =Levy!J296 -> 105423 | I296: 0 | J296: 8409.23 | K296: 20035.61 | L296: 0 | M296: 0 | N296: 0 | O296: 0 | P296: 7630.89 | Q296: 0 | R296: 0 | S296: 5917.95 | T296: 0 | U296: 0 | V296: 0 | W296: 0 | X296: 0 | Y296: 71959.18 | Z296: =SUM(I296:T296) -> 41993.68 | AA296: =ROUND(MAX(E296+F296+G296-W296-X296-Z296,0),2) -> 407334.32 | AB296: =ROUND(MAX(H296-U296,0),2) -> 105423 | AC296: =ROUND(MAX(0,(D296-V296)*Shift11!$B$3),2) -> 364470.84 | AD296: =MAX(AC296,Y296) -> 364470.84
A297: 2174 | B297: 1 | C297: PINE RIVER-BACKU | D297: =Levy!F297 -> 936.89 | E297: =Levy!G297 -> 211794.68 | F297: =Levy!H297 -> 0 | G297: =Levy!I297 -> 143208.95 | H297: =Levy!J297 -> 122701.25 | I297: 0 | J297: 0 | K297: 23143.51 | L297: 0 | M297: 0 | N297: 0 | O297: 0 | P297: 19509.12 | Q297: 0 | R297: -1578.24 | S297: 0 | T297: 0 | U297: 0 | V297: 0 | W297: 0 | X297: 0 | Y297: 0 | Z297: =SUM(I297:T297) -> 41074.39 | AA297: =ROUND(MAX(E297+F297+G297-W297-X297-Z297,0),2) -> 313929.24 | AB297: =ROUND(MAX(H297-U297,0),2) -> 122701.25 | AC297: =ROUND(MAX(0,(D297-V297)*Shift11!$B$3),2) -> 455.33 | AD297: =MAX(AC297,Y297) -> 455.33
A298: 2176 | B298: 1 | C298: WARREN-ALVARADO- | D298: =Levy!F298 -> 495140 | E298: =Levy!G298 -> 13282 | F298: =Levy!H298 -> 0 | G298: =Levy!I298 -> 329446 | H298: =Levy!J298 -> 54747 | I298: 0 | J298: 4111 | K298: 11665.08 | L298: 0 | M298: 0 | N298: 0 | O298: 0 | P298: 6033.68 | Q298: 0 | R298: 0 | S298: 0 | T298: 0 | U298: 0 | V298: 0 | W298: 0 | X298: 0 | Y298: 228879.6 | Z298: =SUM(I298:T298) -> 21809.76 | AA298: =ROUND(MAX(E298+F298+G298-W298-X298-Z298,0),2) -> 320918.24 | AB298: =ROUND(MAX(H298-U298,0),2) -> 54747 | AC298: =ROUND(MAX(0,(D298-V298)*Shift11!$B$3),2) -> 240638.04 | AD298: =MAX(AC298,Y298) -> 240638.04
A299: 2180 | B299: 1 | C299: M.A.C.C.R.A.Y. | D299: =Levy!F299 -> 1209110.2 | E299: =Levy!G299 -> 12169.67 | F299: =Levy!H299 -> 0 | G299: =Levy!I299 -> 314015.41 | H299: =Levy!J299 -> 39630.93 | I299: 0 | J299: 3000 | K299: 11665.08 | L299: 0 | M299: 0 | N299: 0 | O299: 0 | P299: 21252.68 | Q299: 0 | R299: 0 | S299: 0 | T299: 0 | U299: 0 | V299: 0 | W299: 0 | X299: 0 | Y299: 173617.36 | Z299: =SUM(I299:T299) -> 35917.76 | AA299: =ROUND(MAX(E299+F299+G299-W299-X299-Z299,0),2) -> 290267.32 | AB299: =ROUND(MAX(H299-U299,0),2) -> 39630.93 | AC299: =ROUND(MAX(0,(D299-V299)*Shift11!$B$3),2) -> 587627.57 | AD299: =MAX(AC299,Y299) -> 587627.57
A300: 2184 | B300: 1 | C300: LUVERNE | D300: =Levy!F300 -> 926762.9 | E300: =Levy!G300 -> 55183.28 | F300: =Levy!H300 -> 0 | G300: =Levy!I300 -> 365865.12 | H300: =Levy!J300 -> 80187.34 | I300: 0 | J300: 2000 | K300: 26479.3 | L300: 0 | M300: 0 | N300: 0 | O300: 0 | P300: -2250.05 | Q300: 0 | R300: 0 | S300: 0 | T300: 0 | U300: 0 | V300: 0 | W300: 0 | X300: 2150.03 | Y300: 45058.55 | Z300: =SUM(I300:T300) -> 26229.25 | AA300: =ROUND(MAX(E300+F300+G300-W300-X300-Z300,0),2) -> 392669.12 | AB300: =ROUND(MAX(H300-U300,0),2) -> 80187.34 | AC300: =ROUND(MAX(0,(D300-V300)*Shift11!$B$3),2) -> 450406.77 | AD300: =MAX(AC300,Y300) -> 450406.77
... A308: 2364 | B308: 1 | C308: BELGRADE-BROOTEN | D308: =Levy!F308 -> 420180.98 | E308: =Levy!G308 -> 53520.3 | F308: =Levy!H308 -> 0 | G308: =Levy!I308 -> 74248.46 | H308: =Levy!J308 -> 57069.54 | I308: 0 | J308: 1000 | K308: 25480.96 | L308: 0 | M308: 0 | N308: 0 | O308: 0 | P308: -163.87 | Q308: 0 | R308: 0 | S308: 0 | T308: 0 | U308: 0 | V308: 0 | W308: 0 | X308: 11.77 | Y308: 33392.53 | Z308: =SUM(I308:T308) -> 26317.09 | AA308: =ROUND(MAX(E308+F308+G308-W308-X308-Z308,0),2) -> 101439.9 | AB308: =ROUND(MAX(H308-U308,0),2) -> 57069.54 | AC308: =ROUND(MAX(0,(D308-V308)*Shift11!$B$3),2) -> 204207.96 | AD308: =MAX(AC308,Y308) -> 204207.96
A309: 2365 | B309: 1 | C309: G.F.W. | D309: =Levy!F309 -> 653829.44 | E309: =Levy!G309 -> 65299.1 | F309: =Levy!H309 -> 0 | G309: =Levy!I309 -> 587870.51 | H309: =Levy!J309 -> 95779.53 | I309: 0 | J309: 6000 | K309: 25399.63 | L309: 0 | M309: 0 | N309: 0 | O309: 0 | P309: -4774.32 | Q309: 0 | R309: 0 | S309: 0 | T309: 0 | U309: 0 | V309: 0 | W309: 0 | X309: =0+1584.22 -> 1584.22 | Y309: =144311.37+6446.78 -> 150758.15 | Z309: =SUM(I309:T309) -> 26625.31 | AA309: =ROUND(MAX(E309+F309+G309-W309-X309-Z309,0),2) -> 624960.08 | AB309: =ROUND(MAX(H309-U309,0),2) -> 95779.53 | AC309: =ROUND(MAX(0,(D309-V309)*Shift11!$B$3),2) -> 317761.11 | AD309: =MAX(AC309,Y309) -> 317761.11
A310: 2396 | B310: 1 | C310: A.C.G.C. | D310: =Levy!F310 -> 884467.31 | E310: =Levy!G310 -> 60710.16 | F310: =Levy!H310 -> 0 | G310: =Levy!I310 -> 517269.49 | H310: =Levy!J310 -> 121436.78 | I310: 0 | J310: 1589 | K310: 18241.26 | L310: 0 | M310: 0 | N310: 0 | O310: 0 | P310: -7959.57 | Q310: 0 | R310: 0 | S310: 0 | T310: 0 | U310: 0 | V310: 0 | W310: 0 | X310: 6520.58 | Y310: 102338.72 | Z310: =SUM(I310:T310) -> 11870.69 | AA310: =ROUND(MAX(E310+F310+G310-W310-X310-Z310,0),2) -> 559588.38 | AB310: =ROUND(MAX(H310-U310,0),2) -> 121436.78 | AC310: =ROUND(MAX(0,(D310-V310)*Shift11!$B$3),2) -> 429851.11 | AD310: =MAX(AC310,Y310) -> 429851.11
A311: 2397 | B311: 1 | C311: LESUEUR-HENDERSO | D311: =Levy!F311 -> 871264 | E311: =Levy!G311 -> 112217 | F311: =Levy!H311 -> 0 | G311: =Levy!I311 -> 525073 | H311: =Levy!J311 -> 96943 | I311: 0 | J311: 15000 | K311: 30065.1 | L311: 0 | M311: 0 | N311: 0 | O311: 0 | P311: 2130.18 | Q311: 0 | R311: -10490.32 | S311: 0 | T311: 0 | U311: 0 | V311: 0 | W311: 0 | X311: 0 | Y311: 75648.16 | Z311: =SUM(I311:T311) -> 36704.96 | AA311: =ROUND(MAX(E311+F311+G311-W311-X311-Z311,0),2) -> 600585.04 | AB311: =ROUND(MAX(H311-U311,0),2) -> 96943 | AC311: =ROUND(MAX(0,(D311-V311)*Shift11!$B$3),2) -> 423434.3 | AD311: =MAX(AC311,Y311) -> 423434.3
A312: 2448 | B312: 1 | C312: MARTIN COUNTY WE | D312: =Levy!F312 -> 953632.53 | E312: =Levy!G312 -> 47882.3 | F312: =Levy!H312 -> 0 | G312: =Levy!I312 -> 471894.72 | H312: =Levy!J312 -> 63612.58 | I312: 0 | J312: 10000 | K312: 26950.09 | L312: 0 | M312: 0 | N312: 0 | O312: 0 | P312: -6332.11 | Q312: 0 | R312: 0 | S312: 0 | T312: 0 | U312: 0 | V312: 0 | W312: 0 | X312: 0 | Y312: 221365 | Z312: =SUM(I312:T312) -> 30617.98 | AA312: =ROUND(MAX(E312+F312+G312-W312-X312-Z312,0),2) -> 489159.04 | AB312: =ROUND(MAX(H312-U312,0),2) -> 63612.58 | AC312: =ROUND(MAX(0,(D312-V312)*Shift11!$B$3),2) -> 463465.41 | AD312: =MAX(AC312,Y312) -> 463465.41
A313: 2527 | B313: 1 | C313: NORMAN COUNTY WE | D313: =Levy!F313 -> 245409.89 | E313: =Levy!G313 -> 12966.71 | F313: =Levy!H313 -> 0 | G313: =Levy!I313 -> 176731.36 | H313: =Levy!J313 -> 20995.94 | I313: 0 | J313: 140 | K313: 34000 | L313: 0 | M313: 0 | N313: 0 | O313: 0 | P313: 673.94 | Q313: 0 | R313: -22599.15 | S313: 0 | T313: 0 | U313: 0 | V313: 0 | W313: 0 | X313: 0 | Y313: 61388.37 | Z313: =SUM(I313:T313) -> 12214.79 | AA313: =ROUND(MAX(E313+F313+G313-W313-X313-Z313,0),2) -> 177483.28 | AB313: =ROUND(MAX(H313-U313,0),2) -> 20995.94 | AC313: =ROUND(MAX(0,(D313-V313)*Shift11!$B$3),2) -> 119269.21 | AD313: =MAX(AC313,Y313) -> 119269.21
A314: 2534 | B314: 1 | C314: BIRD ISLAND-OLIV | D314: =Levy!F314 -> 381877.99 | E314: =Levy!G314 -> 51039.87 | F314: =Levy!H314 -> 0 | G314: =Levy!I314 -> 365143.98 | H314: =Levy!J314 -> 74498.18 | I314: 0 | J314: 12757.18 | K314: 24471.01 | L314: 0 | M314: 0 | N314: 0 | O314: 0 | P314: 7156.45 | Q314: 0 | R314: 0 | S314: 0 | T314: 0 | U314: 0 | V314: 0 | W314: 0 | X314: 0 | Y314: 96802.28 | Z314: =SUM(I314:T314) -> 44384.64 | AA314: =ROUND(MAX(E314+F314+G314-W314-X314-Z314,0),2) -> 371799.21 | AB314: =ROUND(MAX(H314-U314,0),2) -> 74498.18 | AC314: =ROUND(MAX(0,(D314-V314)*Shift11!$B$3),2) -> 185592.7 | AD314: =MAX(AC314,Y314) -> 185592.7
A315: 2536 | B315: 1 | C315: GRANADA HUNTLEY- | D315: =Levy!F315 -> 672737.91 | E315: =Levy!G315 -> 9425.71 | F315: =Levy!H315 -> 0 | G315: =Levy!I315 -> 101709.4 | H315: =Levy!J315 -> 36506.22 | I315: 0 | J315: 10000 | K315: 0 | L315: 0 | M315: 0 | N315: 0 | O315: 0 | P315: -1841.83 | Q315: 0 | R315: 0 | S315: 0 | T315: 0 | U315: 0 | V315: 0 | W315: 0 | X315: 0 | Y315: 112538.9 | Z315: =SUM(I315:T315) -> 8158.17 | AA315: =ROUND(MAX(E315+F315+G315-W315-X315-Z315,0),2) -> 102976.94 | AB315: =ROUND(MAX(H315-U315,0),2) -> 36506.22 | AC315: =ROUND(MAX(0,(D315-V315)*Shift11!$B$3),2) -> 326950.62 | AD315: =MAX(AC315,Y315) -> 326950.62
A316: 2580 | B316: 1 | C316: EAST CENTRAL | D316: =Levy!F316 -> 73162.2 | E316: =Levy!G316 -> 117246.51 | F316: =Levy!H316 -> 0 | G316: =Levy!I316 -> 243278.87 | H316: =Levy!J316 -> 76915.75 | I316: 0 | J316: 25000 | K316: 20271.73 | L316: 0 | M316: 0 | N316: 0 | O316: 0 | P316: -11853.85 | Q316: 0 | R316: -5865.7 | S316: 0 | T316: 0 | U316: 0 | V316: 0 | W316: 0 | X316: 0 | Y316: 47527.08 | Z316: =SUM(I316:T316) -> 27552.18 | AA316: =ROUND(MAX(E316+F316+G316-W316-X316-Z316,0),2) -> 332973.2 | AB316: =ROUND(MAX(H316-U316,0),2) -> 76915.75 | AC316: =ROUND(MAX(0,(D316-V316)*Shift11!$B$3),2) -> 35556.83 | AD316: =MAX(AC316,Y316) -> 47527.08
A317: 2609 | B317: 1 | C317: WIN-E-MAC | D317: =Levy!F317 -> 284928.68 | E317: =Levy!G317 -> 22622.67 | F317: =Levy!H317 -> 0 | G317: =Levy!I317 -> 206737.16 | H317: =Levy!J317 -> 7042.65 | I317: 0 | J317: 2000 | K317: 12844.65 | L317: 0 | M317: 0 | N317: 0 | O317: 0 | P317: 0 | Q317: 0 | R317: -305.6 | S317: 0 | T317: 0 | U317: 0 | V317: 0 | W317: 0 | X317: 2194.98 | Y317: 16182.82 | Z317: =SUM(I317:T317) -> 14539.05 | AA317: =ROUND(MAX(E317+F317+G317-W317-X317-Z317,0),2) -> 212625.8 | AB317: =ROUND(MAX(H317-U317,0),2) -> 7042.65 | AC317: =ROUND(MAX(0,(D317-V317)*Shift11!$B$3),2) -> 138475.34 | AD317: =MAX(AC317,Y317) -> 138475.34
A318: 2683 | B318: 1 | C318: GREENBUSH-MIDDLE | D318: =Levy!F318 -> 173395 | E318: =Levy!G318 -> 14218 | F318: =Levy!H318 -> 0 | G318: =Levy!I318 -> 97971 | H318: =Levy!J318 -> 22390 | I318: 0 | J318: 54 | K318: 10545.23 | L318: 0 | M318: 0 | N318: 0 | O318: 0 | P318: 449.71 | Q318: 0 | R318: 960 | S318: 0 | T318: 0 | U318: 0 | V318: 0 | W318: 0 | X318: 0 | Y318: 57512.51 | Z318: =SUM(I318:T318) -> 12008.94 | AA318: =ROUND(MAX(E318+F318+G318-W318-X318-Z318,0),2) -> 100180.06 | AB318: =ROUND(MAX(H318-U318,0),2) -> 22390 | AC318: =ROUND(MAX(0,(D318-V318)*Shift11!$B$3),2) -> 84269.97 | AD318: =MAX(AC318,Y318) -> 84269.97
A319: 2687 | B319: 1 | C319: HOWARD LAKE-WAVE | D319: =Levy!F319 -> 722059 | E319: =Levy!G319 -> 124985 | F319: =Levy!H319 -> 0 | G319: =Levy!I319 -> 511264 | H319: =Levy!J319 -> 106822 | I319: 0 | J319: 7000 | K319: 25760.22 | L319: 0 | M319: 0 | N319: 0 | O319: 0 | P319: -9548.64 | Q319: 0 | R319: -597.6 | S319: 0 | T319: 0 | U319: 0 | V319: 0 | W319: 0 | X319: 0 | Y319: 128380.69 | Z319: =SUM(I319:T319) -> 22613.98 | AA319: =ROUND(MAX(E319+F319+G319-W319-X319-Z319,0),2) -> 613635.02 | AB319: =ROUND(MAX(H319-U319,0),2) -> 106822 | AC319: =ROUND(MAX(0,(D319-V319)*Shift11!$B$3),2) -> 350920.67 | AD319: =MAX(AC319,Y319) -> 350920.67
A320: 2689 | B320: 1 | C320: PIPESTONE AREA S | D320: =Levy!F320 -> 800119 | E320: =Levy!G320 -> 55266 | F320: =Levy!H320 -> 0 | G320: =Levy!I320 -> 386041 | H320: =Levy!J320 -> 108109 | I320: 0 | J320: 6000 | K320: 27707.82 | L320: 0 | M320: 0 | N320: 0 | O320: 0 | P320: -2156.32 | Q320: 0 | R320: -18649.36 | S320: 0 | T320: 0 | U320: 0 | V320: 0 | W320: 0 | X320: 0 | Y320: 41180.28 | Z320: =SUM(I320:T320) -> 12902.14 | AA320: =ROUND(MAX(E320+F320+G320-W320-X320-Z320,0),2) -> 428404.86 | AB320: =ROUND(MAX(H320-U320,0),2) -> 108109 | AC320: =ROUND(MAX(0,(D320-V320)*Shift11!$B$3),2) -> 388857.83 | AD320: =MAX(AC320,Y320) -> 388857.83
A321: 2711 | B321: 1 | C321: MESABI EAST | D321: =Levy!F321 -> 0 | E321: =Levy!G321 -> 112712.94 | F321: =Levy!H321 -> 0 | G321: =Levy!I321 -> 96296.94 | H321: =Levy!J321 -> 0 | I321: 0 | J321: 0 | K321: 22101.82 | L321: 344433.5 | M321: 0 | N321: 0 | O321: 0 | P321: 8294.18 | Q321: 0 | R321: 0 | S321: -9345.13 | T321: 0 | U321: 0 | V321: 0 | W321: 0 | X321: 7178.43 | Y321: 76000.4 | Z321: =SUM(I321:T321) -> 365484.37 | AA321: =ROUND(MAX(E321+F321+G321-W321-X321-Z321,0),2) -> 0 | AB321: =ROUND(MAX(H321-U321,0),2) -> 0 | AC321: =ROUND(MAX(0,(D321-V321)*Shift11!$B$3),2) -> 0 | AD321: =MAX(AC321,Y321) -> 76000.4
... A330: 2856 | B330: 1 | C330: STEPHEN-ARGYLE C | D330: =Levy!F330 -> 242780 | E330: =Levy!G330 -> 22302 | F330: =Levy!H330 -> 0 | G330: =Levy!I330 -> 190452 | H330: =Levy!J330 -> 59609 | I330: 0 | J330: 0 | K330: 11665.08 | L330: 0 | M330: 0 | N330: 0 | O330: 0 | P330: -8259.24 | Q330: 0 | R330: 0 | S330: 0 | T330: 0 | U330: 0 | V330: 0 | W330: 0 | X330: 2021.24 | Y330: 122060.62 | Z330: =SUM(I330:T330) -> 3405.84 | AA330: =ROUND(MAX(E330+F330+G330-W330-X330-Z330,0),2) -> 207326.92 | AB330: =ROUND(MAX(H330-U330,0),2) -> 59609 | AC330: =ROUND(MAX(0,(D330-V330)*Shift11!$B$3),2) -> 117991.08 | AD330: =MAX(AC330,Y330) -> 122060.62
A331: 2859 | B331: 1 | C331: GLENCOE-SILVER L | D331: =Levy!F331 -> 1328627 | E331: =Levy!G331 -> 173434.93 | F331: =Levy!H331 -> 0 | G331: =Levy!I331 -> 536531.52 | H331: =Levy!J331 -> 160732.31 | I331: 0 | J331: 0 | K331: 40643.9 | L331: 0 | M331: 0 | N331: 0 | O331: 0 | P331: 40596.2 | Q331: 0 | R331: -5039.94 | S331: 0 | T331: 0 | U331: 0 | V331: 0 | W331: 0 | X331: =0+3949.77 -> 3949.77 | Y331: =152280.16+16073.06 -> 168353.22 | Z331: =SUM(I331:T331) -> 76200.16 | AA331: =ROUND(MAX(E331+F331+G331-W331-X331-Z331,0),2) -> 629816.52 | AB331: =ROUND(MAX(H331-U331,0),2) -> 160732.31 | AC331: =ROUND(MAX(0,(D331-V331)*Shift11!$B$3),2) -> 645712.7 | AD331: =MAX(AC331,Y331) -> 645712.7
A332: 2860 | B332: 1 | C332: BLUE EARTH AREA | D332: =Levy!F332 -> 475434.03 | E332: =Levy!G332 -> 75725.14 | F332: =Levy!H332 -> 0 | G332: =Levy!I332 -> 465641.57 | H332: =Levy!J332 -> 127553.83 | I332: 0 | J332: 0 | K332: 0 | L332: 0 | M332: 0 | N332: 0 | O332: 0 | P332: 8102.85 | Q332: -8102.85 | R332: 0 | S332: 0 | T332: 0 | U332: 0 | V332: 0 | W332: 0 | X332: 0 | Y332: 161661.34 | Z332: =SUM(I332:T332) -> 0 | AA332: =ROUND(MAX(E332+F332+G332-W332-X332-Z332,0),2) -> 541366.71 | AB332: =ROUND(MAX(H332-U332,0),2) -> 127553.83 | AC332: =ROUND(MAX(0,(D332-V332)*Shift11!$B$3),2) -> 231060.94 | AD332: =MAX(AC332,Y332) -> 231060.94
A333: 2884 | B333: 1 | C333: RED ROCK CENTRAL | D333: =Levy!F333 -> 556955 | E333: =Levy!G333 -> 14878 | F333: =Levy!H333 -> 0 | G333: =Levy!I333 -> 259976 | H333: =Levy!J333 -> 32635 | I333: 0 | J333: 0 | K333: 0 | L333: 0 | M333: 0 | N333: 0 | O333: 0 | P333: 250.64 | Q333: 0 | R333: 0 | S333: 0 | T333: 0 | U333: 0 | V333: 0 | W333: 0 | X333: 16313.15 | Y333: 56094.94 | Z333: =SUM(I333:T333) -> 250.64 | AA333: =ROUND(MAX(E333+F333+G333-W333-X333-Z333,0),2) -> 258290.21 | AB333: =ROUND(MAX(H333-U333,0),2) -> 32635 | AC333: =ROUND(MAX(0,(D333-V333)*Shift11!$B$3),2) -> 270680.13 | AD333: =MAX(AC333,Y333) -> 270680.13
A334: 2886 | B334: 1 | C334: GLENVILLE-EMMONS | D334: =Levy!F334 -> 245077.85 | E334: =Levy!G334 -> 25637 | F334: =Levy!H334 -> 0 | G334: =Levy!I334 -> 156862.11 | H334: =Levy!J334 -> 20102.01 | I334: 0 | J334: 15000 | K334: 8661.09 | L334: 0 | M334: 0 | N334: 0 | O334: 0 | P334: -914.27 | Q334: 0 | R334: 2968.8 | S334: 0 | T334: 0 | U334: 0 | V334: 0 | W334: 0 | X334: 519.49 | Y334: 122081.61 | Z334: =SUM(I334:T334) -> 25715.62 | AA334: =ROUND(MAX(E334+F334+G334-W334-X334-Z334,0),2) -> 156264 | AB334: =ROUND(MAX(H334-U334,0),2) -> 20102.01 | AC334: =ROUND(MAX(0,(D334-V334)*Shift11!$B$3),2) -> 119107.84 | AD334: =MAX(AC334,Y334) -> 122081.61
A335: 2888 | B335: 1 | C335: CLINTON-GRACEVIL | D335: =Levy!F335 -> 199651.8 | E335: =Levy!G335 -> 12511.42 | F335: =Levy!H335 -> 0 | G335: =Levy!I335 -> 177332.82 | H335: =Levy!J335 -> 27843.65 | I335: 0 | J335: 6850 | K335: 11919.95 | L335: 0 | M335: 0 | N335: 0 | O335: 0 | P335: -6622.01 | Q335: 0 | R335: 0 | S335: 0 | T335: 0 | U335: 0 | V335: 0 | W335: 0 | X335: 5805.07 | Y335: 38564.47 | Z335: =SUM(I335:T335) -> 12147.94 | AA335: =ROUND(MAX(E335+F335+G335-W335-X335-Z335,0),2) -> 171891.23 | AB335: =ROUND(MAX(H335-U335,0),2) -> 27843.65 | AC335: =ROUND(MAX(0,(D335-V335)*Shift11!$B$3),2) -> 97030.77 | AD335: =MAX(AC335,Y335) -> 97030.77
A336: 2889 | B336: 1 | C336: LAKE PARK AUDUBO | D336: =Levy!F336 -> 611607 | E336: =Levy!G336 -> 62406 | F336: =Levy!H336 -> 0 | G336: =Levy!I336 -> 258667 | H336: =Levy!J336 -> 77777 | I336: 0 | J336: 5534.23 | K336: 15740.99 | L336: 0 | M336: 0 | N336: 0 | O336: 0 | P336: -5641.66 | Q336: 0 | R336: 0 | S336: 0 | T336: 0 | U336: 0 | V336: 0 | W336: 0 | X336: 11121.56 | Y336: 70465.44 | Z336: =SUM(I336:T336) -> 15633.56 | AA336: =ROUND(MAX(E336+F336+G336-W336-X336-Z336,0),2) -> 294317.88 | AB336: =ROUND(MAX(H336-U336,0),2) -> 77777 | AC336: =ROUND(MAX(0,(D336-V336)*Shift11!$B$3),2) -> 297241 | AD336: =MAX(AC336,Y336) -> 297241
A337: 2890 | B337: 1 | C337: RENVILLE COUNTY | D337: =Levy!F337 -> 993198.01 | E337: =Levy!G337 -> 18588.64 | F337: =Levy!H337 -> 0 | G337: =Levy!I337 -> 410629.9 | H337: =Levy!J337 -> 62602.83 | I337: 0 | J337: 0 | K337: 15208.2 | L337: 0 | M337: 0 | N337: 0 | O337: 0 | P337: -2414.45 | Q337: 0 | R337: 0 | S337: 0 | T337: 0 | U337: 0 | V337: 0 | W337: 0 | X337: 0 | Y337: 202355.05 | Z337: =SUM(I337:T337) -> 12793.75 | AA337: =ROUND(MAX(E337+F337+G337-W337-X337-Z337,0),2) -> 416424.79 | AB337: =ROUND(MAX(H337-U337,0),2) -> 62602.83 | AC337: =ROUND(MAX(0,(D337-V337)*Shift11!$B$3),2) -> 482694.23 | AD337: =MAX(AC337,Y337) -> 482694.23
A338: 2895 | B338: 1 | C338: JACKSON COUNTY C | D338: =Levy!F338 -> 895934 | E338: =Levy!G338 -> 74409 | F338: =Levy!H338 -> 0 | G338: =Levy!I338 -> 780801 | H338: =Levy!J338 -> 113321 | I338: 0 | J338: 30000 | K338: 26809.14 | L338: 0 | M338: 0 | N338: 0 | O338: 0 | P338: 12840.49 | Q338: 0 | R338: -1951.35 | S338: 0 | T338: 0 | U338: 0 | V338: 0 | W338: 0 | X338: 13469.21 | Y338: 40827.55 | Z338: =SUM(I338:T338) -> 67698.28 | AA338: =ROUND(MAX(E338+F338+G338-W338-X338-Z338,0),2) -> 774042.51 | AB338: =ROUND(MAX(H338-U338,0),2) -> 113321 | AC338: =ROUND(MAX(0,(D338-V338)*Shift11!$B$3),2) -> 435423.92 | AD338: =MAX(AC338,Y338) -> 435423.92
A339: 2897 | B339: 1 | C339: REDWOOD AREA SCH | D339: =Levy!F339 -> 797061 | E339: =Levy!G339 -> 77650 | F339: =Levy!H339 -> 0 | G339: =Levy!I339 -> 401625 | H339: =Levy!J339 -> 105550 | I339: 0 | J339: 15000 | K339: 0 | L339: 0 | M339: 0 | N339: 0 | O339: 0 | P339: -1061.11 | Q339: 0 | R339: 0 | S339: 0 | T339: 0 | U339: 0 | V339: 0 | W339: 0 | X339: 0 | Y339: 0 | Z339: =SUM(I339:T339) -> 13938.89 | AA339: =ROUND(MAX(E339+F339+G339-W339-X339-Z339,0),2) -> 465336.11 | AB339: =ROUND(MAX(H339-U339,0),2) -> 105550 | AC339: =ROUND(MAX(0,(D339-V339)*Shift11!$B$3),2) -> 387371.65 | AD339: =MAX(AC339,Y339) -> 387371.65
A340: 2898 | B340: 1 | C340: WESTBROOK-WALNUT | D340: =Levy!F340 -> 142275 | E340: =Levy!G340 -> 42285 | F340: =Levy!H340 -> 0 | G340: =Levy!I340 -> 231071 | H340: =Levy!J340 -> 34049 | I340: 0 | J340: 0 | K340: 0 | L340: 0 | M340: 0 | N340: 0 | O340: 0 | P340: -3146.37 | Q340: 0 | R340: 488 | S340: 0 | T340: 0 | U340: 0 | V340: 0 | W340: 0 | X340: 0 | Y340: 115844.14 | Z340: =SUM(I340:T340) -> -2658.37 | AA340: =ROUND(MAX(E340+F340+G340-W340-X340-Z340,0),2) -> 276014.37 | AB340: =ROUND(MAX(H340-U340,0),2) -> 34049 | AC340: =ROUND(MAX(0,(D340-V340)*Shift11!$B$3),2) -> 69145.65 | AD340: =MAX(AC340,Y340) -> 115844.14
A341: 2899 | B341: 1 | C341: PLAINVIEW-ELGIN-MILLV | D341: =Levy!F341 -> 306724 | E341: =Levy!G341 -> 133785 | F341: =Levy!H341 -> 0 | G341: =Levy!I341 -> 495350 | H341: =Levy!J341 -> 85748 | I341: 0 | J341: 7500 | K341: 38491.02 | L341: 0 | M341: 0 | N341: 0 | O341: 0 | P341: 48994.06 | Q341: 0 | R341: -1107.2 | S341: 0 | T341: 0 | U341: 0 | V341: 0 | W341: 0 | X341: 0 | Y341: 24224.82 | Z341: =SUM(I341:T341) -> 93877.88 | AA341: =ROUND(MAX(E341+F341+G341-W341-X341-Z341,0),2) -> 535257.12 | AB341: =ROUND(MAX(H341-U341,0),2) -> 85748 | AC341: =ROUND(MAX(0,(D341-V341)*Shift11!$B$3),2) -> 149067.86 | AD341: =MAX(AC341,Y341) -> 149067.86
A342: 2902 | B342: 1 | C342: RTR | D342: =Levy!F342 -> 228589 | E342: =Levy!G342 -> 36179 | F342: =Levy!H342 -> 0 | G342: =Levy!I342 -> 431373 | H342: =Levy!J342 -> 35598 | I342: 0 | J342: 13866 | K342: 14617.74 | L342: 0 | M342: 0 | N342: 0 | O342: 0 | P342: 5842.04 | Q342: 0 | R342: -446.4 | S342: 0 | T342: 0 | U342: 0 | V342: 0 | W342: 0 | X342: 479.17 | Y342: 56182.83 | Z342: =SUM(I342:T342) -> 33879.38 | AA342: =ROUND(MAX(E342+F342+G342-W342-X342-Z342,0),2) -> 433193.45 | AB342: =ROUND(MAX(H342-U342,0),2) -> 35598 | AC342: =ROUND(MAX(0,(D342-V342)*Shift11!$B$3),2) -> 111094.25 | AD342: =MAX(AC342,Y342) -> 111094.25
A343: 2903 | B343: 1 | C343: ORTONVILLE-BELLINGHAM | D343: =Levy!F343 -> 374787.24 | E343: =Levy!G343 -> 26195.9 | F343: =Levy!H343 -> 0 | G343: =Levy!I343 -> 223821.65 | H343: =Levy!J343 -> 47292.54 | I343: 0 | J343: 0 | K343: 20351.88 | L343: 0 | M343: 0 | N343: 0 | O343: 0 | P343: 0 | Q343: 0 | R343: -7446.85 | S343: 0 | T343: 0 | U343: 0 | V343: 0 | W343: 0 | X343: 0 | Y343: 78903.95 | Z343: =SUM(I343:T343) -> 12905.03 | AA343: =ROUND(MAX(E343+F343+G343-W343-X343-Z343,0),2) -> 237112.52 | AB343: =ROUND(MAX(H343-U343,0),2) -> 47292.54 | AC343: =ROUND(MAX(0,(D343-V343)*Shift11!$B$3),2) -> 182146.6 | AD343: =MAX(AC343,Y343) -> 182146.6
A344: 2904 | B344: 1 | C344: TRACY AREA | D344: =Levy!F344 -> 561437 | E344: =Levy!G344 -> 72034 | F344: =Levy!H344 -> 0 | G344: =Levy!I344 -> 316612 | H344: =Levy!J344 -> 70429 | I344: 0 | J344: 10000 | K344: 21439 | L344: 0 | M344: 0 | N344: 0 | O344: 0 | P344: -16973.8 | Q344: 0 | R344: -1129.99 | S344: 0 | T344: 0 | U344: 0 | V344: 0 | W344: 0 | X344: 4004.21 | Y344: 99195.2 | Z344: =SUM(I344:T344) -> 13335.21 | AA344: =ROUND(MAX(E344+F344+G344-W344-X344-Z344,0),2) -> 371306.58 | AB344: =ROUND(MAX(H344-U344,0),2) -> 70429 | AC344: =ROUND(MAX(0,(D344-V344)*Shift11!$B$3),2) -> 272858.38 | AD344: =MAX(AC344,Y344) -> 272858.38

Sheet Shift10
A1: ="Actual Pay "&Instructions!P2&" Gross Shift" -> Actual Pay Pay 2011 Gross Shift | O1: =Report!I1 -> 41115
A3: Shift at 48.6%
D4: Genl with Aid Adjust | E4: Refer with Aid Adjust | F4: Refer No Aid Adjust | G4: Addl Refer Shift | H4: Career Technical | I4: 100% Shift | J4: Reemploy Resv | K4: Reemploy Unrsv | L4: Leg Changes Genl Fund | M4: Comm Serv at Shift % | N4: Leg Changes Comm Serv | O4: Total Gross Shift
C6: State Total | D6: =SUM(D8:D344) -> 2.4734801e+08 | E6: =SUM(E8:E344) -> 2.455034e+08 | F6: =SUM(F8:F344) -> 1.1422854e+08 | G6: =SUM(G8:G344) -> 4282529.2 | H6: =SUM(H8:H344) -> 14684640 | I6: =SUM(I8:I344) -> 28020391 | J6: =SUM(J8:J344) -> -172020.46 | K6: =SUM(K8:K344) -> 14230410 | ... O6: =SUM(O8:O344) -> 7.0372766e+08
A8: 1 | B8: 1 | C8: AITKIN | D8: 416627.8 | E8: 0 | F8: 141143.88 | G8: 0 | H8: 25634.83 | I8: 0 | J8: 0 | K8: 3404.09 | L8: 0 | M8: 2504.57 | N8: 0 | O8: =SUM(D8:N8) -> 589315.17
A9: 1.2 | B9: 3 | C9: MINNEAPOLIS | D9: 14582222 | E9: 21821402 | F9: 10049626 | G9: 1205612.7 | H9: 529738.02 | I9: 8867688.3 | J9: 0 | K9: 1757181.6 | L9: 0 | M9: 1994567.9 | N9: 0 | O9: =SUM(D9:N9) -> 60808039
A10: 2 | B10: 1 | C10: HILL CITY | D10: 47119.75 | E10: 0 | F10: 0 | G10: 0 | H10: 10000 | I10: 0 | J10: 0 | K10: 4391.84 | L10: 0 | M10: 9191.86 | N10: 0 | O10: =SUM(D10:N10) -> 70703.45
A11: 4 | B11: 1 | C11: MCGREGOR | D11: 172561.5 | E11: 0 | F11: 51784.65 | G11: 0 | H11: 10000 | I11: 0 | J11: 0 | K11: 20099.8 | L11: 0 | M11: 25328.41 | N11: 0 | O11: =SUM(D11:N11) -> 279774.36
A12: 6 | B12: 3 | C12: SOUTH ST. PAUL | D12: 1300935.3 | E12: 1196068.4 | F12: 360711.07 | G12: 0 | H12: 60380 | I12: 0 | J12: 0 | K12: 31382.34 | L12: 0 | M12: 146893.99 | N12: 0 | O12: =SUM(D12:N12) -> 3096371.2
A13: 11 | B13: 1 | C13: ANOKA-HENNEPIN | D13: 11892199 | E13: 21005184 | F13: 3515884.7 | G13: 197692.1 | H13: 803790.4 | I13: 0 | J13: 0 | K13: 635663.96 | L13: 0 | M13: 1584570.6 | N13: 0 | O13: =SUM(D13:N13) -> 39634984
A14: 12 | B14: 1 | C14: CENTENNIAL | D14: 1569454.1 | E14: 1744179.3 | F14: 320094.52 | G14: 16533.75 | H14: 98681.4 | I14: 0 | J14: 0 | K14: 131350.46 | L14: 0 | M14: 225346.88 | N14: 0 | O14: =SUM(D14:N14) -> 4105640.4
A15: 13 | B15: 1 | C15: COLUMBIA HEIGHTS | D15: 956603.97 | E15: 749319.29 | F15: 848958.71 | G15: 0 | H15: 52152 | I15: 0 | J15: 0 | K15: 39764.67 | L15: 0 | M15: 139529.13 | N15: 0 | O15: =SUM(D15:N15) -> 2786327.8
A16: 14 | B16: 1 | C16: FRIDLEY | D16: 1232060.4 | E16: 917735.15 | F16: 468605.33 | G16: 0 | H16: 58793.07 | I16: 0 | J16: 0 | K16: 81860.44 | L16: 0 | M16: 219361.65 | N16: 0 | O16: =SUM(D16:N16) -> 2978416
A17: 15 | B17: 1 | C17: ST. FRANCIS | D17: 1408196.9 | E17: 718737.91 | F17: 288492.79 | G17: 0 | H17: 106376 | I17: 0 | J17: 0 | K17: 113910.4 | L17: 0 | M17: 194944.64 | N17: 0 | O17: =SUM(D17:N17) -> 2830658.6
A18: 16 | B18: 1 | C18: SPRING LAKE PARK | D18: 1924985.5 | E18: 1416754.8 | F18: 804793.86 | G18: 73286.44 | H18: 68475.46 | I18: 0 | J18: 0 | K18: 50745.49 | L18: 0 | M18: 206222.85 | N18: 0 | O18: =SUM(D18:N18) -> 4545264.4
A19: 22 | B19: 1 | C19: DETROIT LAKES | D19: 699396.81 | E19: 523861.91 | F19: 133298.49 | G19: 0 | H19: 48230.37 | I19: 0 | J19: 0 | K19: 16233.03 | L19: 0 | M19: 96544.98 | N19: 0 | O19: =SUM(D19:N19) -> 1517565.6
... A344: 2904 | B344: 1 | C344: TRACY AREA | D344: 203485.14 | E344: 159309.17 | F344: 99195.2 | G344: 4004.21 | H344: 18378.79 | I344: 0 | J344: 0 | K344: 23538.29 | L344: 0 | M344: 35965.46 | N344: 0 | O344: =SUM(D344:N344) -> 543876.26

Sheet Levy
A1: Computed Credits for Tax Shift | V1: =Report!I1 -> 41115
A2: ="Preliminary "&Instructions!P2&" credits" -> Preliminary Pay 2011 credits
A3: =Instructions!P1&" Levy" -> Pay 2012 Levy | D3: Not Revised | E3: Not Revised | F3: STR 21,22-1 | G3: STR 21,22-2 | H3: STR 21,22-3 | I3: STR 21,22-4 | J3: STR 21,22-5 | K3: STR 21,22-6 | L3: STR 21,22-7 | M3: STR 21,22-8 | N3: STR 21,22-9 | O3: 2.2409359e+09
A4: Estimated Credits Allocation? 1=Yes, 0=No | D4: Prel Pay 2010 Credits | E4: Est Pay 2010 Credits | F4: Genl RMV Voter Levy | G4: Genl RMV Other Levy | H4: Genl NTC Voter Levy | I4: Genl NTC Other Levy | J4: Comm Service Levy | K4: Debt Voter Levy | L4: Debt Other Levy | M4: OPEB Voter Levy | N4: OPEB Other Levy | O4: Total Levy | P4: Total Levy for Credit Allocation | Q4: Genl Levy for Credit Allocation | R4: CSE Levy for Credit Allocation | S4: GDS Levy for Credit Allocation | T4: OPEB Levy for Credit Allocation | U4: Est/Act Fund 1 Credits | V4: Est/Act Fund 4 Credits | W4: Est/Act Fund 7 Credits | X4: Est/Act Fund 47 Credits | Y4: Estimated Total Credits
A5: 0
C6: State Total | D6: =SUM(D8:D344) -> 73730757 | E6: =SUM(E8:E344) -> 76018159 | F6: =SUM(F8:F344) -> 7.6354564e+08 | G6: =SUM(G8:G344) -> 91927344 | H6: =SUM(H8:H344) -> 47134874 | I6: =SUM(I8:I344) -> 4.2705476e+08 | J6: =SUM(J8:J344) -> 73674515 | K6: =SUM(K8:K344) -> 6.0470723e+08 | ... Y6: =SUM(Y8:Y344) -> 17410083
A8: 1 | B8: 1 | C8: AITKIN | D8: 92902.44 | E8: 42148.72 | F8: 81.54 | G8: 352047.5 | H8: 0 | I8: 503404.39 | J8: 1846.04 | K8: 0 | L8: 0 | M8: 0 | N8: 0 | O8: =SUM(F8:N8) -> 857379.47 | P8: =SUM(H8:N8) -> 505250.43 | Q8: =SUM(H8:I8) -> 503404.39 | R8: =J8 -> 1846.04 | S8: =K8+L8 -> 0 | T8: =N8+M8 -> 0 | U8: =IF($A$5=1,IF($P8=0,0,ROUND(Q8/$P8*$E8,2)),Credits!D8)+Credits!J8 -> 65805.1 | V8: =IF($A$5=1,IF($P8=0,0,ROUND(R8/$P8*$E8,2)),Credits!E8)+Credits!K8 -> 184.88 | W8: =IF($A$5=1,IF($P8=0,0,ROUND(S8/$P8*$E8,2)),Credits!F8)+Credits!L8 -> 1335.38 | X8: =IF($A$5=1,IF($P8=0,0,ROUND(T8/$P8*$E8,2)),Credits!G8)+Credits!M8 -> 0 | Y8: =SUM(U8:X8) -> 67325.36
A9: 1.2 | B9: 3 | C9: MINNEAPOLIS | D9: 2663277.4 | E9: 2694951.5 | F9: 67448174 | G9: 8500163.8 | H9: 0 | I9: 27494722 | J9: 4928399.1 | K9: 0 | L9: 54624568 | M9: 0 | N9: 2731434 | O9: =SUM(F9:N9) -> 1.6572746e+08 | P9: =SUM(H9:N9) -> 89779123 | Q9: =SUM(H9:I9) -> 27494722 | R9: =J9 -> 4928399.1 | S9: =K9+L9 -> 54624568 | T9: =N9+M9 -> 2731434 | U9: =IF($A$5=1,IF($P9=0,0,ROUND(Q9/$P9*$E9,2)),Credits!D9)+Credits!J9 -> 200855.6 | V9: =IF($A$5=1,IF($P9=0,0,ROUND(R9/$P9*$E9,2)),Credits!E9)+Credits!K9 -> 29248.09 | W9: =IF($A$5=1,IF($P9=0,0,ROUND(S9/$P9*$E9,2)),Credits!F9)+Credits!L9 -> 324002.28 | X9: =IF($A$5=1,IF($P9=0,0,ROUND(T9/$P9*$E9,2)),Credits!G9)+Credits!M9 -> 16219.78 | Y9: =SUM(U9:X9) -> 570325.75
A10: 2 | B10: 1 | C10: HILL CITY | D10: 61193.02 | E10: 62222.09 | F10: 0 | G10: 33615 | H10: 0 | I10: 117325 | J10: 19970 | K10: 227746 | L10: 0 | M10: 0 | N10: 0 | O10: =SUM(F10:N10) -> 398656 | P10: =SUM(H10:N10) -> 365041 | Q10: =SUM(H10:I10) -> 117325 | R10: =J10 -> 19970 | S10: =K10+L10 -> 227746 | T10: =N10+M10 -> 0 | U10: =IF($A$5=1,IF($P10=0,0,ROUND(Q10/$P10*$E10,2)),Credits!D10)+Credits!J10 -> 3788.95 | V10: =IF($A$5=1,IF($P10=0,0,ROUND(R10/$P10*$E10,2)),Credits!E10)+Credits!K10 -> 645.04 | W10: =IF($A$5=1,IF($P10=0,0,ROUND(S10/$P10*$E10,2)),Credits!F10)+Credits!L10 -> 7354.77 | X10: =IF($A$5=1,IF($P10=0,0,ROUND(T10/$P10*$E10,2)),Credits!G10)+Credits!M10 -> 0 | Y10: =SUM(U10:X10) -> 11788.76
A11: 4 | B11: 1 | C11: MCGREGOR | D11: 80147.9 | E11: 77463.08 | F11: 0 | G11: 66483 | H11: 0 | I11: 106528 | J11: 56743 | K11: 710933 | L11: 50999 | M11: 0 | N11: 160740 | O11: =SUM(F11:N11) -> 1152426 | P11: =SUM(H11:N11) -> 1085943 | Q11: =SUM(H11:I11) -> 106528 | R11: =J11 -> 56743 | S11: =K11+L11 -> 761932 | T11: =N11+M11 -> 160740 | U11: =IF($A$5=1,IF($P11=0,0,ROUND(Q11/$P11*$E11,2)),Credits!D11)+Credits!J11 -> 1648.46 | V11: =IF($A$5=1,IF($P11=0,0,ROUND(R11/$P11*$E11,2)),Credits!E11)+Credits!K11 -> 878.48 | W11: =IF($A$5=1,IF($P11=0,0,ROUND(S11/$P11*$E11,2)),Credits!F11)+Credits!L11 -> 11792.27 | X11: =IF($A$5=1,IF($P11=0,0,ROUND(T11/$P11*$E11,2)),Credits!G11)+Credits!M11 -> 2487.95 | Y11: =SUM(U11:X11) -> 16807.16
A12: 6 | B12: 3 | C12: SOUTH ST. PAUL | D12: 325402.94 | E12: 355904.43 | F12: 2989995 | G12: 380899 | H12: 591403 | I12: 1921364 | J12: 300195 | K12: 1228619 | L12: 0 | M12: 0 | N12: 759712 | O12: =SUM(F12:N12) -> 8172187 | P12: =SUM(H12:N12) -> 4801293 | Q12: =SUM(H12:I12) -> 2512767 | R12: =J12 -> 300195 | S12: =K12+L12 -> 1228619 | T12: =N12+M12 -> 759712 | U12: =IF($A$5=1,IF($P12=0,0,ROUND(Q12/$P12*$E12,2)),Credits!D12)+Credits!J12 -> 186.28 | V12: =IF($A$5=1,IF($P12=0,0,ROUND(R12/$P12*$E12,2)),Credits!E12)+Credits!K12 -> 22.26 | W12: =IF($A$5=1,IF($P12=0,0,ROUND(S12/$P12*$E12,2)),Credits!F12)+Credits!L12 -> 91.09 | X12: =IF($A$5=1,IF($P12=0,0,ROUND(T12/$P12*$E12,2)),Credits!G12)+Credits!M12 -> 56.32 | Y12: =SUM(U12:X12) -> 355.95
A13: 11 | B13: 1 | C13: ANOKA-HENNEPIN | D13: 2321154.1 | E13: 2739867.2 | F13: 51090199 | G13: 3820592.4 | H13: 3000000 | I13: 15067013 | J13: 3106720.4 | K13: 17140272 | L13: 3295170.5 | M13: 0 | N13: 2051394.3 | O13: =SUM(F13:N13) -> 98571362 | P13: =SUM(H13:N13) -> 43660570 | Q13: =SUM(H13:I13) -> 18067013 | R13: =J13 -> 3106720.4 | S13: =K13+L13 -> 20435443 | T13: =N13+M13 -> 2051394.3 | U13: =IF($A$5=1,IF($P13=0,0,ROUND(Q13/$P13*$E13,2)),Credits!D13)+Credits!J13 -> 7401.52 | V13: =IF($A$5=1,IF($P13=0,0,ROUND(R13/$P13*$E13,2)),Credits!E13)+Credits!K13 -> 1335.92 | W13: =IF($A$5=1,IF($P13=0,0,ROUND(S13/$P13*$E13,2)),Credits!F13)+Credits!L13 -> 8839.43 | X13: =IF($A$5=1,IF($P13=0,0,ROUND(T13/$P13*$E13,2)),Credits!G13)+Credits!M13 -> 883.2 | Y13: =SUM(U13:X13) -> 18460.07
A14: 12 | B14: 1 | C14: CENTENNIAL | D14: 435943.19 | E14: 506074.54 | F14: 5650661.7 | G14: 764942.25 | H14: 0 | I14: 2840359.9 | J14: 435691.6 | K14: 6852522 | L14: 385756.12 | M14: 0 | N14: 640053.41 | O14: =SUM(F14:N14) -> 17569987 | P14: =SUM(H14:N14) -> 11154383 | Q14: =SUM(H14:I14) -> 2840359.9 | R14: =J14 -> 435691.6 | S14: =K14+L14 -> 7238278.2 | T14: =N14+M14 -> 640053.41 | U14: =IF($A$5=1,IF($P14=0,0,ROUND(Q14/$P14*$E14,2)),Credits!D14)+Credits!J14 -> 657.62 | V14: =IF($A$5=1,IF($P14=0,0,ROUND(R14/$P14*$E14,2)),Credits!E14)+Credits!K14 -> 97.93 | W14: =IF($A$5=1,IF($P14=0,0,ROUND(S14/$P14*$E14,2)),Credits!F14)+Credits!L14 -> 1554.84 | X14: =IF($A$5=1,IF($P14=0,0,ROUND(T14/$P14*$E14,2)),Credits!G14)+Credits!M14 -> 144.24 | Y14: =SUM(U14:X14) -> 2454.63
A15: 13 | B15: 1 | C15: COLUMBIA HEIGHTS | D15: 313192.28 | E15: 247897.21 | F15: 3415330.2 | G15: 399163.32 | H15: 0 | I15: 1829369.1 | J15: 318080.81 | K15: 2388513 | L15: 0 | M15: 0 | N15: 0 | O15: =SUM(F15:N15) -> 8350456.5 | P15: =SUM(H15:N15) -> 4535963 | Q15: =SUM(H15:I15) -> 1829369.1 | R15: =J15 -> 318080.81 | S15: =K15+L15 -> 2388513 | T15: =N15+M15 -> 0 | U15: =IF($A$5=1,IF($P15=0,0,ROUND(Q15/$P15*$E15,2)),Credits!D15)+Credits!J15 -> 514.9 | V15: =IF($A$5=1,IF($P15=0,0,ROUND(R15/$P15*$E15,2)),Credits!E15)+Credits!K15 -> 84.91 | W15: =IF($A$5=1,IF($P15=0,0,ROUND(S15/$P15*$E15,2)),Credits!F15)+Credits!L15 -> 623.85 | X15: =IF($A$5=1,IF($P15=0,0,ROUND(T15/$P15*$E15,2)),Credits!G15)+Credits!M15 -> 0 | Y15: =SUM(U15:X15) -> 1223.66
A16: 14 | B16: 1 | C16: FRIDLEY | D16: 265890.49 | E16: 273959.9 | F16: 2512103.5 | G16: 336673.52 | H16: 741000 | I16: 1361099.3 | J16: 466173.16 | K16: 1201540.7 | L16: 1440920.9 | M16: 0 | N16: 588660 | O16: =SUM(F16:N16) -> 8648171.1 | P16: =SUM(H16:N16) -> 5799394.1 | Q16: =SUM(H16:I16) -> 2102099.3 | R16: =J16 -> 466173.16 | S16: =K16+L16 -> 2642461.6 | T16: =N16+M16 -> 588660 | U16: =IF($A$5=1,IF($P16=0,0,ROUND(Q16/$P16*$E16,2)),Credits!D16)+Credits!J16 -> 374 | V16: =IF($A$5=1,IF($P16=0,0,ROUND(R16/$P16*$E16,2)),Credits!E16)+Credits!K16 -> 83.69 | W16: =IF($A$5=1,IF($P16=0,0,ROUND(S16/$P16*$E16,2)),Credits!F16)+Credits!L16 -> 481.03 | X16: =IF($A$5=1,IF($P16=0,0,ROUND(T16/$P16*$E16,2)),Credits!G16)+Credits!M16 -> 106.76 | Y16: =SUM(U16:X16) -> 1045.48
A17: 15 | B17: 1 | C17: ST. FRANCIS | D17: 415829.18 | E17: 482378.91 | F17: 1821524 | G17: 578387.61 | H17: 0 | I17: 2111555.8 | J17: 349966.46 | K17: 4904121 | L17: 935691.76 | M17: 0 | N17: 314376 | O17: =SUM(F17:N17) -> 11015623 | P17: =SUM(H17:N17) -> 8615711.1 | Q17: =SUM(H17:I17) -> 2111555.8 | R17: =J17 -> 349966.46 | S17: =K17+L17 -> 5839812.8 | T17: =N17+M17 -> 314376 | U17: =IF($A$5=1,IF($P17=0,0,ROUND(Q17/$P17*$E17,2)),Credits!D17)+Credits!J17 -> 8225.65 | V17: =IF($A$5=1,IF($P17=0,0,ROUND(R17/$P17*$E17,2)),Credits!E17)+Credits!K17 -> 1217.73 | W17: =IF($A$5=1,IF($P17=0,0,ROUND(S17/$P17*$E17,2)),Credits!F17)+Credits!L17 -> 20960.59 | X17: =IF($A$5=1,IF($P17=0,0,ROUND(T17/$P17*$E17,2)),Credits!G17)+Credits!M17 -> 1139.89 | Y17: =SUM(U17:X17) -> 31543.86
A18: 16 | B18: 1 | C18: SPRING LAKE PARK | D18: 425562.85 | E18: 456648.25 | F18: 5117489.9 | G18: 876015 | H18: 1065985 | I18: 2535402.9 | J18: 463634.17 | K18: 8359603.4 | L18: 687667.41 | M18: 0 | N18: 308931 | O18: =SUM(F18:N18) -> 19414729 | P18: =SUM(H18:N18) -> 13421224 | Q18: =SUM(H18:I18) -> 3601387.9 | R18: =J18 -> 463634.17 | S18: =K18+L18 -> 9047270.8 | T18: =N18+M18 -> 308931 | U18: =IF($A$5=1,IF($P18=0,0,ROUND(Q18/$P18*$E18,2)),Credits!D18)+Credits!J18 -> 495.05 | V18: =IF($A$5=1,IF($P18=0,0,ROUND(R18/$P18*$E18,2)),Credits!E18)+Credits!K18 -> 63.24 | W18: =IF($A$5=1,IF($P18=0,0,ROUND(S18/$P18*$E18,2)),Credits!F18)+Credits!L18 -> 1225.84 | X18: =IF($A$5=1,IF($P18=0,0,ROUND(T18/$P18*$E18,2)),Credits!G18)+Credits!M18 -> 41.8 | Y18: =SUM(U18:X18) -> 1825.93
A19: 22 | B19: 1 | C19: DETROIT LAKES | D19: 142876.4 | E19: 142486.25 | F19: 1336103 | G19: 382290 | H19: 0 | I19: 1149384 | J19: 210886 | K19: 800741 | L19: 0 | M19: 0 | N19: 0 | O19: =SUM(F19:N19) -> 3879404 | P19: =SUM(H19:N19) -> 2161011 | Q19: =SUM(H19:I19) -> 1149384 | R19: =J19 -> 210886 | S19: =K19+L19 -> 800741 | T19: =N19+M19 -> 0 | U19: =IF($A$5=1,IF($P19=0,0,ROUND(Q19/$P19*$E19,2)),Credits!D19)+Credits!J19 -> 5223.88 | V19: =IF($A$5=1,IF($P19=0,0,ROUND(R19/$P19*$E19,2)),Credits!E19)+Credits!K19 -> 1265.99 | W19: =IF($A$5=1,IF($P19=0,0,ROUND(S19/$P19*$E19,2)),Credits!F19)+Credits!L19 -> 4805.71 | X19: =IF($A$5=1,IF($P19=0,0,ROUND(T19/$P19*$E19,2)),Credits!G19)+Credits!M19 -> 0 | Y19: =SUM(U19:X19) -> 11295.58
... A344: 2904 | B344: 1 | C344: TRACY AREA | D344: 55444.12 | E344: 53953.45 | F344: 561437 | G344: 72034 | H344: 0 | I344: 316612 | J344: 70429 | K344: 0 | L344: 0 | M344: 0 | N344: 0 | O344: =SUM(F344:N344) -> 1020512 | P344: =SUM(H344:N344) -> 387041 | Q344: =SUM(H344:I344) -> 316612 | R344: =J344 -> 70429 | S344: =K344+L344 -> 0 | T344: =N344+M344 -> 0 | U344: =IF($A$5=1,IF($P344=0,0,ROUND(Q344/$P344*$E344,2)),Credits!D344)+Credits!J344 -> 23345.92 | V344: =IF($A$5=1,IF($P344=0,0,ROUND(R344/$P344*$E344,2)),Credits!E344)+Credits!K344 -> 5198.61 | W344: =IF($A$5=1,IF($P344=0,0,ROUND(S344/$P344*$E344,2)),Credits!F344)+Credits!L344 -> 0 | X344: =IF($A$5=1,IF($P344=0,0,ROUND(T344/$P344*$E344,2)),Credits!G344)+Credits!M344 -> 0 | Y344: =SUM(U344:X344) -> 28544.53

Sheet Credits
A1: Credits by Fund from Revenue | H1: =Report!I1 -> 41115
A2: ="Preliminary "&Instructions!P2&" credits" -> Preliminary Pay 2011 credits
A3: =Instructions!P1&" Levy" -> Pay 2012 Levy | D3: Credits by Fund from Revenue | J3: Taconite Homestead Credit
D4: Fund 1 | E4: Fund 4 | F4: Fund 7 | G4: Fund 47 | H4: Total | J4: Fund 1 | K4: Fund 4 | L4: Fund 7 | M4: Fund 47 | N4: Total
C6: State Total | D6: =SUM(D8:D344) -> 4623914.5 | E6: =SUM(E8:E344) -> 817738.58 | F6: =SUM(F8:F344) -> 9109389.1 | G6: =SUM(G8:G344) -> 486299.93 | H6: =SUM(H8:H344) -> 15037342 | J6: =SUM(J8:J344) -> 590533.53 | K6: =SUM(K8:K344) -> 1557.63 | L6: =SUM(L8:L344) -> 1179514.5 | M6: =SUM(M8:M344) -> 601135.69 | N6: =SUM(N8:N344) -> 2372741.3 | O6: =N6+H6 -> 17410083
A8: 1 | B8: 1 | C8: AITKIN | D8: 6415.57 | E8: 22.44 | F8: 0 | G8: 0 | H8: =SUM(D8:G8) -> 6438.01 | J8: 59389.53 | K8: 162.44 | L8: 1335.38 | M8: 0 | N8: 60887.35
A9: 1.2 | B9: 3 | C9: MINNEAPOLIS | D9: 200855.6 | E9: 29248.09 | F9: 324002.28 | G9: 16219.78 | H9: =SUM(D9:G9) -> 570325.75 | J9: 0 | K9: 0 | L9: 0 | M9: 0 | N9: 0
A10: 2 | B10: 1 | C10: HILL CITY | D10: 3788.95 | E10: 645.04 | F10: 7354.77 | G10: 0 | H10: =SUM(D10:G10) -> 11788.76 | J10: 0 | K10: 0 | L10: 0 | M10: 0 | N10: 0
A11: 4 | B11: 1 | C11: MCGREGOR | D11: 1648.46 | E11: 878.48 | F11: 11792.27 | G11: 2487.95 | H11: =SUM(D11:G11) -> 16807.16 | J11: 0 | K11: 0 | L11: 0 | M11: 0 | N11: 0
A12: 6 | B12: 3 | C12: SOUTH ST. PAUL | D12: 186.28 | E12: 22.26 | F12: 91.09 | G12: 56.32 | H12: =SUM(D12:G12) -> 355.95 | J12: 0 | K12: 0 | L12: 0 | M12: 0 | N12: 0
A13: 11 | B13: 1 | C13: ANOKA-HENNEPIN | D13: 7401.52 | E13: 1335.92 | F13: 8839.43 | G13: 883.2 | H13: =SUM(D13:G13) -> 18460.07 | J13: 0 | K13: 0 | L13: 0 | M13: 0 | N13: 0
A14: 12 | B14: 1 | C14: CENTENNIAL | D14: 657.62 | E14: 97.93 | F14: 1554.84 | G14: 144.24 | H14: =SUM(D14:G14) -> 2454.63 | J14: 0 | K14: 0 | L14: 0 | M14: 0 | N14: 0
A15: 13 | B15: 1 | C15: COLUMBIA HEIGHTS | D15: 514.9 | E15: 84.91 | F15: 623.85 | G15: 0 | H15: =SUM(D15:G15) -> 1223.66 | J15: 0 | K15: 0 | L15: 0 | M15: 0 | N15: 0
A16: 14 | B16: 1 | C16: FRIDLEY | D16: 374 | E16: 83.69 | F16: 481.03 | G16: 106.76 | H16: =SUM(D16:G16) -> 1045.48 | J16: 0 | K16: 0 | L16: 0 | M16: 0 | N16: 0
A17: 15 | B17: 1 | C17: ST. FRANCIS | D17: 8225.65 | E17: 1217.73 | F17: 20960.59 | G17: 1139.89 | H17: =SUM(D17:G17) -> 31543.86 | J17: 0 | K17: 0 | L17: 0 | M17: 0 | N17: 0
A18: 16 | B18: 1 | C18: SPRING LAKE PARK | D18: 495.05 | E18: 63.24 | F18: 1225.84 | G18: 41.8 | H18: =SUM(D18:G18) -> 1825.93 | J18: 0 | K18: 0 | L18: 0 | M18: 0 | N18: 0
A19: 22 | B19: 1 | C19: DETROIT LAKES | D19: 5223.88 | E19: 1265.99 | F19: 4805.71 | G19: 0 | H19: =SUM(D19:G19) -> 11295.58 | J19: 0 | K19: 0 | L19: 0 | M19: 0 | N19: 0
... A344: 2904 | B344: 1 | C344: TRACY AREA | D344: 23345.92 | E344: 5198.61 | F344: 0 | G344: 0 | H344: =SUM(D344:G344) -> 28544.53 | J344: 0 | K344: 0 | L344: 0 | M344: 0 | N344: 0

Sheet Receipts
A1: ="Compare "&Instructions!P1&" Gross Shift to Tax Receipts" -> Compare Pay 2012 Gross Shift to Tax Receipts | L1: =Report!I1 -> 41115
A3: Shift at | B3: =Shift11!B3 -> 0.486 | D3: General Fund | I3: Community Service Fund | N3: Total May-June 2010 Tax Receipts for Ideas | O3: =Instructions!P1&" General + Comm Service Levies" -> Pay 2012 General + Comm Service Levies
D4: Total Gross Shift | E4: ="Est Tax Receipts May-July "&Instructions!O1 -> Est Tax Receipts May-July 2012 | F4: Estimated Gened Recognition | G4: Lesser of Gross Shift or Tax Receipts (but not less than zero) | I4: Total Gross Shift | J4: ="Est Tax Receipts May-July "&Instructions!O1 -> Est Tax Receipts May-July 2012 | K4: Estimated Gened Recognition | L4: Lesser of Gross Shift or Tax Receipts (but not less than zero) | O4: Levy | P4: Credits | Q4: Net Levy
C6: State Total | D6: =SUM(D8:D344) -> 6.8492698e+08 | E6: =SUM(E8:E344) -> 6.6222409e+08 | F6: =SUM(F8:F344) -> 25696992 | G6: =SUM(G8:G344) -> 6.5922999e+08 | I6: =SUM(I8:I344) -> 35805814 | J6: =SUM(J8:J344) -> 36427610 | K6: =SUM(K8:K344) -> 146972.08 | L6: =SUM(L8:L344) -> 35658842 | N6: =SUM(N8:N344) -> 6.9488883e+08 | O6: =SUM(O8:O344) -> 1.4033371e+09 | P6: =SUM(P8:P344) -> 6033744.2 | Q6: =SUM(Q8:Q344) -> 1.3973034e+09
A8: 1 | B8: 1 | C8: AITKIN | D8: =SUM(Shift11!D8:L8) -> 573261.54 | E8: =ROUND(MAX(0,(Levy!Q8+Data!D8+Data!E8-Levy!U8)*0.5),2) -> 394864.17 | F8: =IF(D8>E8,D8-E8,0) -> 178397.37 | G8: =MAX(0,MIN(D8,E8)) -> 394864.17 | I8: =SUM(Shift11!M8:N8) -> 897.18 | J8: =ROUND(MAX(0,(Levy!R8-Levy!V8)*0.5),2) -> 830.58 | K8: =IF(I8>J8,I8-J8,0) -> 66.6 | L8: =MAX(0,MIN(I8,J8)) -> 830.58 | N8: =G8+L8 -> 395694.75 | O8: =SUM(Levy!F8:J8) -> 857379.47 | P8: =SUM(Levy!U8:V8) -> 65989.98 | Q8: =O8-P8 -> 791389.49
A9: 1.2 | B9: 3 | C9: MINNEAPOLIS | D9: =SUM(Shift11!D9:L9) -> 56538632 | E9: =ROUND(MAX(0,(Levy!Q9+Data!D9+Data!E9-Levy!U9)*0.5),2) -> 51621102 | F9: =IF(D9>E9,D9-E9,0) -> 4917530 | G9: =MAX(0,MIN(D9,E9)) -> 51621102 | I9: =SUM(Shift11!M9:N9) -> 2395202 | J9: =ROUND(MAX(0,(Levy!R9-Levy!V9)*0.5),2) -> 2449575.5 | K9: =IF(I9>J9,I9-J9,0) -> 0 | L9: =MAX(0,MIN(I9,J9)) -> 2395202 | N9: =G9+L9 -> 54016304 | O9: =SUM(Levy!F9:J9) -> 1.0837146e+08 | P9: =SUM(Levy!U9:V9) -> 230103.69 | Q9: =O9-P9 -> 1.0814136e+08
A10: 2 | B10: 1 | C10: HILL CITY | D10: =SUM(Shift11!D10:L10) -> 86737.11 | E10: =ROUND(MAX(0,(Levy!Q10+Data!D10+Data!E10-Levy!U10)*0.5),2) -> 73575.53 | F10: =IF(D10>E10,D10-E10,0) -> 13161.58 | G10: =MAX(0,MIN(D10,E10)) -> 73575.53 | I10: =SUM(Shift11!M10:N10) -> 9705.42 | J10: =ROUND(MAX(0,(Levy!R10-Levy!V10)*0.5),2) -> 9662.48 | K10: =IF(I10>J10,I10-J10,0) -> 42.94 | L10: =MAX(0,MIN(I10,J10)) -> 9662.48 | N10: =G10+L10 -> 83238.01 | O10: =SUM(Levy!F10:J10) -> 170910 | P10: =SUM(Levy!U10:V10) -> 4433.99 | Q10: =O10-P10 -> 166476.01
A11: 4 | B11: 1 | C11: MCGREGOR | D11: =SUM(Shift11!D11:L11) -> 135191.46 | E11: =ROUND(MAX(0,(Levy!Q11+Data!D11+Data!E11-Levy!U11)*0.5),2) -> 85681.27 | F11: =IF(D11>E11,D11-E11,0) -> 49510.19 | G11: =MAX(0,MIN(D11,E11)) -> 85681.27 | I11: =SUM(Shift11!M11:N11) -> 27577.1 | J11: =ROUND(MAX(0,(Levy!R11-Levy!V11)*0.5),2) -> 27932.26 | K11: =IF(I11>J11,I11-J11,0) -> 0 | L11: =MAX(0,MIN(I11,J11)) -> 27577.1 | N11: =G11+L11 -> 113258.37 | O11: =SUM(Levy!F11:J11) -> 229754 | P11: =SUM(Levy!U11:V11) -> 2526.94 | Q11: =O11-P11 -> 227227.06
A12: 6 | B12: 3 | C12: SOUTH ST. PAUL | D12: =SUM(Shift11!D12:L12) -> 2926817.1 | E12: =ROUND(MAX(0,(Levy!Q12+Data!D12+Data!E12-Levy!U12)*0.5),2) -> 2941737.4 | F12: =IF(D12>E12,D12-E12,0) -> 0 | G12: =MAX(0,MIN(D12,E12)) -> 2926817.1 | I12: =SUM(Shift11!M12:N12) -> 145894.77 | J12: =ROUND(MAX(0,(Levy!R12-Levy!V12)*0.5),2) -> 150086.37 | K12: =IF(I12>J12,I12-J12,0) -> 0 | L12: =MAX(0,MIN(I12,J12)) -> 145894.77 | N12: =G12+L12 -> 3072711.9 | O12: =SUM(Levy!F12:J12) -> 6183856 | P12: =SUM(Levy!U12:V12) -> 208.54 | Q12: =O12-P12 -> 6183647.5
A13: 11 | B13: 1 | C13: ANOKA-HENNEPIN | D13: =SUM(Shift11!D13:L13) -> 36465901 | E13: =ROUND(MAX(0,(Levy!Q13+Data!D13+Data!E13-Levy!U13)*0.5),2) -> 36485201 | F13: =IF(D13>E13,D13-E13,0) -> 0 | G13: =MAX(0,MIN(D13,E13)) -> 36465901 | I13: =SUM(Shift11!M13:N13) -> 1509866.1 | J13: =ROUND(MAX(0,(Levy!R13-Levy!V13)*0.5),2) -> 1552692.2 | K13: =IF(I13>J13,I13-J13,0) -> 0 | L13: =MAX(0,MIN(I13,J13)) -> 1509866.1 | N13: =G13+L13 -> 37975767 | O13: =SUM(Levy!F13:J13) -> 76084524 | P13: =SUM(Levy!U13:V13) -> 8737.44 | Q13: =O13-P13 -> 76075787
A14: 12 | B14: 1 | C14: CENTENNIAL | D14: =SUM(Shift11!D14:L14) -> 4628366 | E14: =ROUND(MAX(0,(Levy!Q14+Data!D14+Data!E14-Levy!U14)*0.5),2) -> 4627653.1 | F14: =IF(D14>E14,D14-E14,0) -> 712.88 | G14: =MAX(0,MIN(D14,E14)) -> 4627653.1 | I14: =SUM(Shift11!M14:N14) -> 211746.12 | J14: =ROUND(MAX(0,(Levy!R14-Levy!V14)*0.5),2) -> 217796.84 | K14: =IF(I14>J14,I14-J14,0) -> 0 | L14: =MAX(0,MIN(I14,J14)) -> 211746.12 | N14: =G14+L14 -> 4839399.2 | O14: =SUM(Levy!F14:J14) -> 9691655.5 | P14: =SUM(Levy!U14:V14) -> 755.55 | Q14: =O14-P14 -> 9690899.9
A15: 13 | B15: 1 | C15: COLUMBIA HEIGHTS | D15: =SUM(Shift11!D15:L15) -> 2792105.6 | E15: =ROUND(MAX(0,(Levy!Q15+Data!D15+Data!E15-Levy!U15)*0.5),2) -> 2821673.9 | F15: =IF(D15>E15,D15-E15,0) -> 0 | G15: =MAX(0,MIN(D15,E15)) -> 2792105.6 | I15: =SUM(Shift11!M15:N15) -> 154587.27 | J15: =ROUND(MAX(0,(Levy!R15-Levy!V15)*0.5),2) -> 158997.95 | K15: =IF(I15>J15,I15-J15,0) -> 0 | L15: =MAX(0,MIN(I15,J15)) -> 154587.27 | N15: =G15+L15 -> 2946692.9 | O15: =SUM(Levy!F15:J15) -> 5961943.5 | P15: =SUM(Levy!U15:V15) -> 599.81 | Q15: =O15-P15 -> 5961343.7
A16: 14 | B16: 1 | C16: FRIDLEY | D16: =SUM(Shift11!D16:L16) -> 2496017.5 | E16: =ROUND(MAX(0,(Levy!Q16+Data!D16+Data!E16-Levy!U16)*0.5),2) -> 2475251.2 | F16: =IF(D16>E16,D16-E16,0) -> 20766.38 | G16: =MAX(0,MIN(D16,E16)) -> 2475251.2 | I16: =SUM(Shift11!M16:N16) -> 226560.16 | J16: =ROUND(MAX(0,(Levy!R16-Levy!V16)*0.5),2) -> 233044.74 | K16: =IF(I16>J16,I16-J16,0) -> 0 | L16: =MAX(0,MIN(I16,J16)) -> 226560.16 | N16: =G16+L16 -> 2701811.3 | O16: =SUM(Levy!F16:J16) -> 5417049.5 | P16: =SUM(Levy!U16:V16) -> 457.69 | Q16: =O16-P16 -> 5416591.8
A17: 15 | B17: 1 | C17: ST. FRANCIS | D17: =SUM(Shift11!D17:L17) -> 2423357.7 | E17: =ROUND(MAX(0,(Levy!Q17+Data!D17+Data!E17-Levy!U17)*0.5),2) -> 2251620.9 | F17: =IF(D17>E17,D17-E17,0) -> 171736.83 | G17: =MAX(0,MIN(D17,E17)) -> 2251620.9 | I17: =SUM(Shift11!M17:N17) -> 170083.7 | J17: =ROUND(MAX(0,(Levy!R17-Levy!V17)*0.5),2) -> 174374.37 | K17: =IF(I17>J17,I17-J17,0) -> 0 | L17: =MAX(0,MIN(I17,J17)) -> 170083.7 | N17: =G17+L17 -> 2421704.6 | O17: =SUM(Levy!F17:J17) -> 4861433.8 | P17: =SUM(Levy!U17:V17) -> 9443.38 | Q17: =O17-P17 -> 4851990.5
A18: 16 | B18: 1 | C18: SPRING LAKE PARK | D18: =SUM(Shift11!D18:L18) -> 4785781 | E18: =ROUND(MAX(0,(Levy!Q18+Data!D18+Data!E18-Levy!U18)*0.5),2) -> 4797198.9 | F18: =IF(D18>E18,D18-E18,0) -> 0 | G18: =MAX(0,MIN(D18,E18)) -> 4785781 | I18: =SUM(Shift11!M18:N18) -> 225326.21 | J18: =ROUND(MAX(0,(Levy!R18-Levy!V18)*0.5),2) -> 231785.47 | K18: =IF(I18>J18,I18-J18,0) -> 0 | L18: =MAX(0,MIN(I18,J18)) -> 225326.21 | N18: =G18+L18 -> 5011107.2 | O18: =SUM(Levy!F18:J18) -> 10058527 | P18: =SUM(Levy!U18:V18) -> 558.29 | Q18: =O18-P18 -> 10057969
A19: 22 | B19: 1 | C19: DETROIT LAKES | D19: =SUM(Shift11!D19:L19) -> 1443673.4 | E19: =ROUND(MAX(0,(Levy!Q19+Data!D19+Data!E19-Levy!U19)*0.5),2) -> 1431276.6 | F19: =IF(D19>E19,D19-E19,0) -> 12396.79 | G19: =MAX(0,MIN(D19,E19)) -> 1431276.6 | I19: =SUM(Shift11!M19:N19) -> 102490.6 | J19: =ROUND(MAX(0,(Levy!R19-Levy!V19)*0.5),2) -> 104810.01 | K19: =IF(I19>J19,I19-J19,0) -> 0 | L19: =MAX(0,MIN(I19,J19)) -> 102490.6 | N19: =G19+L19 -> 1533767.2 | O19: =SUM(Levy!F19:J19) -> 3078663 | P19: =SUM(Levy!U19:V19) -> 6489.87 | Q19: =O19-P19 -> 3072173.1
... A344: 2904 | B344: 1 | C344: TRACY AREA | D344: =SUM(Shift11!D344:L344) -> 470652.8 | E344: =ROUND(MAX(0,(Levy!Q344+Data!D344+Data!E344-Levy!U344)*0.5),2) -> 463368.54 | F344: =IF(D344>E344,D344-E344,0) -> 7284.26 | G344: =MAX(0,MIN(D344,E344)) -> 463368.54 | I344: =SUM(Shift11!M344:N344) -> 34228.49 | J344: =ROUND(MAX(0,(Levy!R344-Levy!V344)*0.5),2) -> 32615.2 | K344: =IF(I344>J344,I344-J344,0) -> 1613.29 | L344: =MAX(0,MIN(I344,J344)) -> 32615.2 | N344: =G344+L344 -> 495983.74 | O344: =SUM(Levy!F344:J344) -> 1020512 | P344: =SUM(Levy!U344:V344) -> 28544.53 | Q344: =O344-P344 -> 991967.47

Sheet Ideas
A1: IDEAS from State Aid Adjustment (Column 5).xlsx | E1: -1
A2: File created from IDEAS run under S:\common\TAXSFTR
H3: =Report!I1 -> 41115
D4: ="Est Aid Reductions (Payments) in "&Instructions!R2&" for Shift" -> Est Aid Reductions (Payments) in FY 2012 for Shift | G4: ="GNL 214 Account "&Instructions!S3 -> GNL 214 Account 06/30/11
D5: General Fund | E5: Comm Serv Fund | G5: General Fund | H5: Comm Serv Fund
C7: State Total | D7: =SUM(D9:D345) -> -8278445.6 | E7: =SUM(E9:E345) -> -534548.44 | F7: =E7+D7 -> -8812994 | G7: =SUM(G9:G345) -> -13711510 | H7: =SUM(H9:H345) -> -559570.82
A9: 1 | B9: 1 | C9: AITKIN | D9: 17940.47 | E9: 0 | G9: =SUMIF(Query1!$B$4:$B$146,A9,Query1!$F$4:$F$146) -> -125447.35 | H9: =SUMIF(Query4!$B$4:$B$138,A9,Query4!$F$4:$F$138) -> -113.8
A10: 1.2 | B10: 3 | C10: MINNEAPOLIS | D10: 1703911.3 | E10: 0 | G10: =SUMIF(Query1!$B$4:$B$146,A10,Query1!$F$4:$F$146) -> -4894482 | H10: =SUMIF(Query4!$B$4:$B$138,A10,Query4!$F$4:$F$138) -> 0
A11: 2 | B11: 1 | C11: HILL CITY | D11: -14104.02 | E11: 0 | G11: =SUMIF(Query1!$B$4:$B$146,A11,Query1!$F$4:$F$146) -> -5838.56 | H11: =SUMIF(Query4!$B$4:$B$138,A11,Query4!$F$4:$F$138) -> 0
A12: 4 | B12: 1 | C12: MCGREGOR | D12: 85584.94 | E12: 0 | G12: =SUMIF(Query1!$B$4:$B$146,A12,Query1!$F$4:$F$146) -> -61827.11 | H12: =SUMIF(Query4!$B$4:$B$138,A12,Query4!$F$4:$F$138) -> 0
A13: 6 | B13: 3 | C13: SOUTH ST. PAUL | D13: 62940.56 | E13: 0 | G13: =SUMIF(Query1!$B$4:$B$146,A13,Query1!$F$4:$F$146) -> 0 | H13: =SUMIF(Query4!$B$4:$B$138,A13,Query4!$F$4:$F$138) -> 0
A14: 11 | B14: 1 | C14: ANOKA-HENNEPIN | D14: 1965750.1 | E14: 0 | G14: =SUMIF(Query1!$B$4:$B$146,A14,Query1!$F$4:$F$146) -> 0 | H14: =SUMIF(Query4!$B$4:$B$138,A14,Query4!$F$4:$F$138) -> 0
A15: 12 | B15: 1 | C15: CENTENNIAL | D15: -728153.9 | E15: 0 | G15: =SUMIF(Query1!$B$4:$B$146,A15,Query1!$F$4:$F$146) -> 0 | H15: =SUMIF(Query4!$B$4:$B$138,A15,Query4!$F$4:$F$138) -> 0
A16: 13 | B16: 1 | C16: COLUMBIA HEIGHTS | D16: -105184.86 | E16: -51387.52 | G16: =SUMIF(Query1!$B$4:$B$146,A16,Query1!$F$4:$F$146) -> 0 | H16: =SUMIF(Query4!$B$4:$B$138,A16,Query4!$F$4:$F$138) -> 0
A17: 14 | B17: 1 | C17: FRIDLEY | D17: 290079.56 | E17: 0 | G17: =SUMIF(Query1!$B$4:$B$146,A17,Query1!$F$4:$F$146) -> 0 | H17: =SUMIF(Query4!$B$4:$B$138,A17,Query4!$F$4:$F$138) -> 0
A18: 15 | B18: 1 | C18: ST. FRANCIS | D18: 465886.52 | E18: 0 | G18: =SUMIF(Query1!$B$4:$B$146,A18,Query1!$F$4:$F$146) -> 0 | H18: =SUMIF(Query4!$B$4:$B$138,A18,Query4!$F$4:$F$138) -> 0
A19: 16 | B19: 1 | C19: SPRING LAKE PARK | D19: -419679.08 | E19: 0 | G19: =SUMIF(Query1!$B$4:$B$146,A19,Query1!$F$4:$F$146) -> 0 | H19: =SUMIF(Query4!$B$4:$B$138,A19,Query4!$F$4:$F$138) -> 0
A20: 22 | B20: 1 | C20: DETROIT LAKES | D20: 4072.2 | E20: 0 | G20: =SUMIF(Query1!$B$4:$B$146,A20,Query1!$F$4:$F$146) -> 0 | H20: =SUMIF(Query4!$B$4:$B$138,A20,Query4!$F$4:$F$138) -> 0
... A345: 2904 | B345: 1 | C345: TRACY AREA | D345: 10414.43 | E345: 0 | G345: =SUMIF(Query1!$B$4:$B$146,A345,Query1!$F$4:$F$146) -> 0 | H345: =SUMIF(Query4!$B$4:$B$138,A345,Query4!$F$4:$F$138) -> -852.46

Sheet Query1
H1: Query Date 07-06-12
H2: Watch for consolidated districts
A3: dat_yer | B3: dst_num | C3: dst_tye | D3: gen_lgr_num | E3: fun_num | F3: end_bal_amt
A4: 10-11 | B4: 1 | C4: 1 | D4: 2.14 | E4: 1 | F4: -125447.35
A5: 10-11 | B5: 1.2 | C5: 3 | D5: 2.14 | E5: 1 | F5: -4894482
A6: 10-11 | B6: 2 | C6: 1 | D6: 2.14 | E6: 1 | F6: -5838.56
A7: 10-11 | B7: 4 | C7: 1 | D7: 2.14 | E7: 1 | F7: -61827.11
A8: 10-11 | B8: 23 | C8: 1 | D8: 2.14 | E8: 1 | F8: -7125.39
A9: 10-11 | B9: 47 | C9: 1 | D9: 2.14 | E9: 1 | F9: -171125.86
A10: 10-11 | B10: 81 | C10: 1 | D10: 2.14 | E10: 1 | F10: -2913.65
A11: 10-11 | B11: 84 | C11: 1 | D11: 2.14 | E11: 1 | F11: -81174.18
A12: 10-11 | B12: 85 | C12: 1 | D12: 2.14 | E12: 1 | F12: -10735.31
A13: 10-11 | B13: 88 | C13: 1 | D13: 2.14 | E13: 1 | F13: -28539
A14: 10-11 | B14: 91 | C14: 1 | D14: 2.14 | E14: 1 | F14: -345.04
A15: 10-11 | B15: 94 | C15: 1 | D15: 2.14 | E15: 1 | F15: -1231.83
... A146: 10-11 | B146: 2903 | C146: 1 | D146: 2.14 | E146: 1 | F146: -84727
F148: =SUM(F4:F147) -> -13711510

Sheet Query4
H1: Query Date 07-06-12
H2: Watch for consolidated districts
A3: dat_yer | B3: dst_num | C3: dst_tye | D3: gen_lgr_num | E3: fun_num | F3: end_bal_amt
A4: 10-11 | B4: 1 | C4: 1 | D4: 2.14 | E4: 4 | F4: -113.8
A5: 10-11 | B5: 23 | C5: 1 | D5: 2.14 | E5: 4 | F5: -1621.2
A6: 10-11 | B6: 77 | C6: 1 | D6: 2.14 | E6: 4 | F6: -5226
A7: 10-11 | B7: 81 | C7: 1 | D7: 2.14 | E7: 4 | F7: -452.49
A8: 10-11 | B8: 84 | C8: 1 | D8: 2.14 | E8: 4 | F8: -1939.95
A9: 10-11 | B9: 85 | C9: 1 | D9: 2.14 | E9: 4 | F9: -660.03
A10: 10-11 | B10: 88 | C10: 1 | D10: 2.14 | E10: 4 | F10: -2693
A11: 10-11 | B11: 94 | C11: 1 | D11: 2.14 | E11: 4 | F11: 0
A12: 10-11 | B12: 97 | C12: 1 | D12: 2.14 | E12: 4 | F12: -649.96
A13: 10-11 | B13: 99 | C13: 1 | D13: 2.14 | E13: 4 | F13: -795.9
A14: 10-11 | B14: 108 | C14: 1 | D14: 2.14 | E14: 4 | F14: -2926
A15: 10-11 | B15: 111 | C15: 1 | D15: 2.14 | E15: 4 | F15: -1384
... A138: 10-11 | B138: 2904 | C138: 1 | D138: 2.14 | E138: 4 | F138: -852.46
F140: =SUM(F4:F139) -> -559570.82
