Workbook

Sheet Summary
A1: Community and Technical Colleges, Report of Fundable Operating Expenses, Fiscal Year (FY) 2009
A2: Summary of Expense divided Contact Hours
A3: Contact Hours for fall 2008 and spring and summer 2009
A4: Fund | B4: Total Expense by Discipline | D4: Contact Hours | E4: Expense | F4: Expense per Contact Hour
A5: 1 | B5: Agriculture | D5: =D36 -> 1551137 | E5: =E36+E67+IFERROR($E$105/$D$105*D5,0) -> 13876460 | F5: =IFERROR(E5/D5,"") -> 8.9459924
A6: 2 | B6: Architecture and Precision Production Trades | D6: =D37 -> 3763085 | E6: =E37+E68+IFERROR($E$105/$D$105*D6,0) -> 37235884 | F6: =IFERROR(E6/D6,"") -> 9.8950421
A7: 3 | B7: Biology, Physical Sciences, and Science Technology | D7: =D38 -> 31074434 | E7: =E38+E69+IFERROR($E$105/$D$105*D7,0) -> 2.4197537e+08 | F7: =IFERROR(E7/D7,"") -> 7.7869597
A8: 4 | B8: Business Management, Marketing, and Administrative Services | D8: =D39 -> 18277419 | E8: =E39+E70+IFERROR($E$105/$D$105*D8,0) -> 1.4533196e+08 | F8: =IFERROR(E8/D8,"") -> 7.9514488
A9: 5 | B9: Career Pilot | D9: =D40 -> 146309 | E9: =E40+E71+IFERROR($E$105/$D$105*D9,0) -> 5130181.1 | F9: =IFERROR(E9/D9,"") -> 35.064016
A10: 6 | B10: Communications | D10: =D41 -> 4054192 | E10: =E41+E72+IFERROR($E$105/$D$105*D10,0) -> 36137263 | F10: =IFERROR(E10/D10,"") -> 8.913555
A11: 7 | B11: Computer and Information Sciences | D11: =D42 -> 11481191 | E11: =E42+E73+IFERROR($E$105/$D$105*D11,0) -> 1.1340407e+08 | F11: =IFERROR(E11/D11,"") -> 9.8773789
A12: 8 | B12: Construction Trades | D12: =D43 -> 1612212 | E12: =E43+E74+IFERROR($E$105/$D$105*D12,0) -> 17208435 | F12: =IFERROR(E12/D12,"") -> 10.673804
A13: 9 | B13: Consumer and Homemaking Education | D13: =D44 -> 9431343 | E13: =E44+E75+IFERROR($E$105/$D$105*D13,0) -> 73362250 | F13: =IFERROR(E13/D13,"") -> 7.7785582
A14: 10 | B14: Engineering | D14: =D45 -> 294975 | E14: =E45+E76+IFERROR($E$105/$D$105*D14,0) -> 3326493.7 | F14: =IFERROR(E14/D14,"") -> 11.277206
A15: 11 | B15: Engineering Related | D15: =D46 -> 7217480 | E15: =E46+E77+IFERROR($E$105/$D$105*D15,0) -> 60817644 | F15: =IFERROR(E15/D15,"") -> 8.4264374
A16: 12 | B16: English Language, Lit, Philosophy, Humanities, & Interdisciplinary | D16: =D47 -> 41737869 | E16: =E47+E78+IFERROR($E$105/$D$105*D16,0) -> 3.4472903e+08 | F16: =IFERROR(E16/D16,"") -> 8.2593827
... A30: 26 | B30: Visual and Performing Arts | D30: =D61 -> 13836400 | E30: =E61+E92+IFERROR($E$105/$D$105*D30,0) -> 1.3418793e+08 | F30: =IFERROR(E30/D30,"") -> 9.6981825
A31: 28 | B31: Developmental Education - Math | D31: =D62 -> 0 | E31: =E62+E93+IFERROR($E$105/$D$105*D31,0) -> 0 | F31: =IFERROR(E31/D31,0) -> 0
A32: 29 | B32: Developmental Education - Reading/Writing | D32: =D63 -> 0 | E32: =E63+E94+IFERROR($E$105/$D$105*D32,0) -> 0 | F32: =IFERROR(E32/D32,0) -> 0
B33: Total | D33: =SUM(D5:D32) -> 269950015 | E33: =SUM(E5:E32) -> 2272008424 | F33: =IFERROR(E33/D33,"") -> 8.4164041
A35: Fund | B35: Departmental Operating Expense by Discipline | D35: Contact Hours | E35: Expense | F35: Expense per Contact Hour
A36: 1 | B36: Agriculture | D36: =SUM('1:57'!D36) -> 1551137 | E36: =SUM('1:57'!E36) -> 2967127 | F36: =IFERROR(E36/D36,"") -> 1.9128723
A37: 2 | B37: Architecture and Precision Production Trades | D37: =SUM('1:57'!D37) -> 3763085 | E37: =SUM('1:57'!E37) -> 7682498 | F37: =IFERROR(E37/D37,"") -> 2.0415425
A38: 3 | B38: Biology, Physical Sciences, and Science Technology | D38: =SUM('1:57'!D38) -> 31074434 | E38: =SUM('1:57'!E38) -> 32810791 | F38: =IFERROR(E38/D38,"") -> 1.0558773
A39: 4 | B39: Business Management, Marketing, and Administrative Services | D39: =SUM('1:57'!D39) -> 18277419 | E39: =SUM('1:57'!E39) -> 20195638 | F39: =IFERROR(E39/D39,"") -> 1.1049502
A40: 5 | B40: Career Pilot | D40: =SUM('1:57'!D40) -> 146309 | E40: =SUM('1:57'!E40) -> 3242038 | F40: =IFERROR(E40/D40,"") -> 22.158842
A41: 6 | B41: Communications | D41: =SUM('1:57'!D41) -> 4054192 | E41: =SUM('1:57'!E41) -> 10290344 | F41: =IFERROR(E41/D41,"") -> 2.5381985
A42: 7 | B42: Computer and Information Sciences | D42: =SUM('1:57'!D42) -> 11481191 | E42: =SUM('1:57'!E42) -> 23283792 | F42: =IFERROR(E42/D42,"") -> 2.0279945
A43: 8 | B43: Construction Trades | D43: =SUM('1:57'!D43) -> 1612212 | E43: =SUM('1:57'!E43) -> 4576316 | F43: =IFERROR(E43/D43,"") -> 2.8385324
A44: 9 | B44: Consumer and Homemaking Education | D44: =SUM('1:57'!D44) -> 9431343 | E44: =SUM('1:57'!E44) -> 12400648 | F44: =IFERROR(E44/D44,"") -> 1.3148337
A45: 10 | B45: Engineering | D45: =SUM('1:57'!D45) -> 294975 | E45: =SUM('1:57'!E45) -> 679278 | F45: =IFERROR(E45/D45,"") -> 2.3028324
A46: 11 | B46: Engineering Related | D46: =SUM('1:57'!D46) -> 7217480 | E46: =SUM('1:57'!E46) -> 11803661 | F46: =IFERROR(E46/D46,"") -> 1.6354269
A47: 12 | B47: English Language, Lit, Philosophy, Humanities, & Interdisciplinary | D47: =SUM('1:57'!D47) -> 41737869 | E47: =SUM('1:57'!E47) -> 37124038 | F47: =IFERROR(E47/D47,"") -> 0.88945696
... A63: 29 | B63: Developmental Education - Reading/Writing | D63: =SUM('1:57'!D63) -> 0 | E63: =SUM('1:57'!E63) -> 0 | F63: =IFERROR(E63/D63,"")
C64: Total | D64: =SUM(D36:D63) -> 269950015 | E64: =SUM(E36:E63) -> 319938491 | F64: =IFERROR(E64/D64,"") -> 1.1851768
A66: Fund | B66: Faculty Salaries by Discipline | D66: Contact Hours | E66: Expense | F66: Expense per Contact Hour
A67: 1 | B67: Agriculture | D67: =D36 -> 1551137 | E67: =SUM('1:57'!E67) -> 5010423 | F67: =IFERROR(E67/D67,"") -> 3.2301615
A68: 2 | B68: Architecture and Precision Production Trades | D68: =D37 -> 3763085 | E68: =SUM('1:57'!E68) -> 15242530 | F68: =IFERROR(E68/D68,"") -> 4.050541
A69: 3 | B69: Biology, Physical Sciences, and Science Technology | D69: =D38 -> 31074434 | E69: =SUM('1:57'!E69) -> 90989788 | F69: =IFERROR(E69/D69,"") -> 2.9281237
A70: 4 | B70: Business Management, Marketing, and Administrative Services | D70: =D39 -> 18277419 | E70: =SUM('1:57'!E70) -> 55628055 | F70: =IFERROR(E70/D70,"") -> 3.04354
A71: 5 | B71: Career Pilot | D71: =D40 -> 146309 | E71: =SUM('1:57'!E71) -> 1331736 | F71: =IFERROR(E71/D71,"") -> 9.1022152
A72: 6 | B72: Communications | D72: =D41 -> 4054192 | E72: =SUM('1:57'!E72) -> 10428995 | F72: =IFERROR(E72/D72,"") -> 2.5723979
A73: 7 | B73: Computer and Information Sciences | D73: =D42 -> 11481191 | E73: =SUM('1:57'!E73) -> 46457788 | F73: =IFERROR(E73/D73,"") -> 4.0464258
A74: 8 | B74: Construction Trades | D74: =D43 -> 1612212 | E74: =SUM('1:57'!E74) -> 6500944 | F74: =IFERROR(E74/D74,"") -> 4.0323134
A75: 9 | B75: Consumer and Homemaking Education | D75: =D44 -> 9431343 | E75: =SUM('1:57'!E75) -> 25094595 | F75: =IFERROR(E75/D75,"") -> 2.6607658
A76: 10 | B76: Engineering | D76: =D45 -> 294975 | E76: =SUM('1:57'!E76) -> 1525438 | F76: =IFERROR(E76/D76,"") -> 5.1714145
A77: 11 | B77: Engineering Related | D77: =D46 -> 7217480 | E77: =SUM('1:57'!E77) -> 21566205 | F77: =IFERROR(E77/D77,"") -> 2.9880519
A78: 12 | B78: English Language, Lit, Philosophy, Humanities, & Interdisciplinary | D78: =D47 -> 41737869 | E78: =SUM('1:57'!E78) -> 148877608 | F78: =IFERROR(E78/D78,"") -> 3.5669672
... A94: 29 | B94: Developmental Education - Reading/Writing | D94: =D63 -> 0 | E94: =SUM('1:57'!E94) -> 0 | F94: =IFERROR(E94/D94,"")
C95: Total | D95: =SUM(D67:D94) -> 269950015 | E95: =SUM(E67:E94) -> 925461201 | F95: =IFERROR(E95/D95,"") -> 3.4282688
B97: Allocated Administrative Expense | D97: Contact Hours | E97: Expense | F97: Expense per Contact Hour
B98: Institutional Support | E98: =SUM('1:57'!E98) -> 428520273 | F98: =IFERROR(E98/$D$95,"") -> 1.587406
B99: Student Services | E99: =SUM('1:57'!E99) -> 230697408 | F99: =IFERROR(E99/$D$95,"") -> 0.85459305
B100: Academic Support | E100: =SUM('1:57'!E100) -> 238198071 | F100: =IFERROR(E100/$D$95,"") -> 0.88237843
B101: Research | E101: =SUM('1:57'!E101) -> 824232 | F101: =IFERROR(E101/$D$95,"") -> 0.0030532764
B102: Scholarships and Fellowships | E102: =SUM('1:57'!E102) -> 24519546 | F102: =IFERROR(E102/$D$95,"") -> 0.090829949
B103: Equipment Depreciation | E103: =SUM('1:57'!E103) -> 43583803 | F103: =IFERROR(E103/$D$95,"") -> 0.16145138
B104: Local Benefits | E104: =SUM('1:57'!E104) -> 60265399 | F104: =IFERROR(E104/$D$95,"") -> 0.22324651
C105: Total | D105: =D95 -> 269950015 | E105: =SUM(E98:E104) -> 1026608732 | F105: =IFERROR(E105/$D$95,"") -> 3.8029586
B107: Annual Financial Report - Schedule B
B108: Unrestricted - Educational Activities | C108: Salaries and Wages | D108: Local Benefits | E108: Other Expenses | F108: Total
B109: Instruction | C109: =SUM('1:57'!C109) -> 925461201 | D109: =SUM('1:57'!D109) -> 0 | E109: =SUM('1:57'!E109) -> 0 | F109: =SUM('1:57'!F109) -> 925461201
B110: Research | C110: =SUM('1:57'!C110) -> 0 | D110: =SUM('1:57'!D110) -> 0 | E110: =SUM('1:57'!E110) -> 0 | F110: =SUM('1:57'!F110) -> 0
B111: Public Service | C111: =SUM('1:57'!C111) -> 0 | D111: =SUM('1:57'!D111) -> 0 | E111: =SUM('1:57'!E111) -> 0 | F111: =SUM('1:57'!F111) -> 0
B112: Academic Support | C112: =SUM('1:57'!C112) -> 0 | D112: =SUM('1:57'!D112) -> 0 | E112: =SUM('1:57'!E112) -> 0 | F112: =SUM('1:57'!F112) -> 0
B113: Student Services | C113: =SUM('1:57'!C113) -> 0 | D113: =SUM('1:57'!D113) -> 0 | E113: =SUM('1:57'!E113) -> 0 | F113: =SUM('1:57'!F113) -> 0
B114: Instructional Support | C114: =SUM('1:57'!C114) -> 0 | D114: =SUM('1:57'!D114) -> 0 | E114: =SUM('1:57'!E114) -> 0 | F114: =SUM('1:57'!F114) -> 0
B115: Operation and Maintenance of Plant | C115: =SUM('1:57'!C115) -> 0 | D115: =SUM('1:57'!D115) -> 0 | E115: =SUM('1:57'!E115) -> 0 | F115: =SUM('1:57'!F115) -> 0
B116: Scholarships and Fellowships | C116: =SUM('1:57'!C116) -> 0 | D116: =SUM('1:57'!D116) -> 0 | E116: =SUM('1:57'!E116) -> 24519546 | F116: =SUM('1:57'!F116) -> 24519546
B117: Other | C117: =SUM('1:57'!C117) -> 0 | D117: =SUM('1:57'!D117) -> 60265399 | E117: =SUM('1:57'!E117) -> 0 | F117: =SUM('1:57'!F117) -> 60265399
B118: Total | C118: =SUM(C109:C116) -> 925461201 | D118: =SUM(D109:D116) -> 0 | E118: =SUM(E109:E116) -> 24519546 | F118: =SUM(F109:F116) -> 949980747
B120: Depreciation Expense - Equipment | C120: =SUM('1:57'!C120) -> 0 | D120: =SUM('1:57'!D120) -> 0 | E120: =SUM('1:57'!E120) -> 43583803 | F120: =SUM('1:57'!F120) -> 43583803
A122: Each year, the Texas Higher Education Coordinating Board revises the Texas Public Community and Technical Colleges Expense per Contact Hour Rates used in its Instruction and Operations Formula Funding Recommendation to the Legislative Budget Board (LBB). The Report of Fundable Operating Expenses (RFOE), completed by the institutions, collects departmental operating expense, faculty salaries, institutional support, student services, academic support, research, scholarships and fellowships, equipment depreciation, and local benefits for input into this summary using Annual Financial Report (AFR) Schedule B, which ties to the AFR Statement of Revenues, Expenses and Changes in Net Assets (SRECNA). The RFOE subcategorizes the expenditures collected in Schedule B funded with unrestricted funds, totals them for all institutions, and divides them by the statewide contact hours to determine rates by discipline.

Sheet Rate History
A1: =Summary!A1 -> Community and Technical Colleges, Report of Fundable Operating Expenses, Fiscal Year (FY) 2009
A2: Rate History | O2: Year over Year Change
A3: Fund | B3: Expense per Contact Hour by Discipline | C3: 2009 | D3: 2008 | E3: 2007 | F3: 2006 | G3: 2005 | H3: 2004 | I3: 2003 | J3: 2002 | K3: 2001 | L3: 2000 | M3: 1999 | O3: 2009 | P3: 2008 | Q3: 2007 | R3: 2006 | S3: 2005 | T3: 2004 | U3: 2003 | V3: 2002 | W3: 2001 | X3: 2000
A4: 1 | B4: Agriculture | C4: =Summary!F5 -> 8.9459924 | D4: 7.7 | E4: 7.37 | G4: 7.25 | H4: 9.82 | I4: 7.18 | J4: 7.58 | K4: 7 | L4: 6.67 | M4: 6.81 | O4: =IFERROR(C4/D4-1,"") -> 0.16181719 | P4: =IFERROR(D4/E4-1,"") -> 0.044776119 | Q4: =IFERROR(E4/F4-1,"") | R4: =IFERROR(F4/G4-1,"") -> -1 | S4: =IFERROR(G4/H4-1,"") -> -0.26171079 | T4: =IFERROR(H4/I4-1,"") -> 0.36768802 | U4: =IFERROR(I4/J4-1,"") -> -0.052770449 | V4: =IFERROR(J4/K4-1,"") -> 0.082857143 | ... X4: =IFERROR(L4/M4-1,"") -> -0.020558003
A5: 2 | B5: Architecture and Precision Production Trades | C5: =Summary!F6 -> 9.8950421 | D5: 8.88 | E5: 10.29 | G5: 8.82 | H5: 11.31 | I5: 7.31 | J5: 7.27 | K5: 7.56 | L5: 6.83 | M5: 6.64 | O5: =IFERROR(C5/D5-1,"") -> 0.11430654 | P5: =IFERROR(D5/E5-1,"") -> -0.13702624 | Q5: =IFERROR(E5/F5-1,"") | R5: =IFERROR(F5/G5-1,"") -> -1 | S5: =IFERROR(G5/H5-1,"") -> -0.22015915 | T5: =IFERROR(H5/I5-1,"") -> 0.54719562 | U5: =IFERROR(I5/J5-1,"") -> 0.0055020633 | V5: =IFERROR(J5/K5-1,"") -> -0.038359788 | ... X5: =IFERROR(L5/M5-1,"") -> 0.028614458
A6: 3 | B6: Biology, Physical Sciences, and Science Technology | C6: =Summary!F7 -> 7.7869597 | D6: 6.85 | E6: 6.65 | G6: 6.19 | H6: 7.98 | I6: 5.86 | J6: 6.04 | K6: 5.9 | L6: 5.69 | M6: 5.51 | O6: =IFERROR(C6/D6-1,"") -> 0.13678244 | P6: =IFERROR(D6/E6-1,"") -> 0.030075188 | Q6: =IFERROR(E6/F6-1,"") | R6: =IFERROR(F6/G6-1,"") -> -1 | S6: =IFERROR(G6/H6-1,"") -> -0.22431078 | T6: =IFERROR(H6/I6-1,"") -> 0.36177474 | U6: =IFERROR(I6/J6-1,"") -> -0.029801325 | V6: =IFERROR(J6/K6-1,"") -> 0.023728814 | ... X6: =IFERROR(L6/M6-1,"") -> 0.032667877
A7: 4 | B7: Business Management, Marketing, and Administrative Services | C7: =Summary!F8 -> 7.9514488 | D7: 7.11 | E7: 6.97 | G7: 6.58 | H7: 8.86 | I7: 6.69 | J7: 6.46 | K7: 6.07 | L7: 6.13 | M7: 6.22 | O7: =IFERROR(C7/D7-1,"") -> 0.11834723 | P7: =IFERROR(D7/E7-1,"") -> 0.020086083 | Q7: =IFERROR(E7/F7-1,"") | R7: =IFERROR(F7/G7-1,"") -> -1 | S7: =IFERROR(G7/H7-1,"") -> -0.25733634 | T7: =IFERROR(H7/I7-1,"") -> 0.32436472 | U7: =IFERROR(I7/J7-1,"") -> 0.035603715 | V7: =IFERROR(J7/K7-1,"") -> 0.064250412 | ... X7: =IFERROR(L7/M7-1,"") -> -0.014469453
A8: 5 | B8: Career Pilot | C8: =Summary!F9 -> 35.064016 | D8: 33.87 | E8: 30.76 | G8: 23.45 | H8: 25.28 | I8: 13.77 | J8: 11.03 | K8: 16.04 | L8: 19.42 | M8: 18.69 | O8: =IFERROR(C8/D8-1,"") -> 0.035252899 | P8: =IFERROR(D8/E8-1,"") -> 0.10110533 | Q8: =IFERROR(E8/F8-1,"") | R8: =IFERROR(F8/G8-1,"") -> -1 | S8: =IFERROR(G8/H8-1,"") -> -0.072389241 | T8: =IFERROR(H8/I8-1,"") -> 0.83587509 | U8: =IFERROR(I8/J8-1,"") -> 0.24841342 | V8: =IFERROR(J8/K8-1,"") -> -0.31234414 | ... X8: =IFERROR(L8/M8-1,"") -> 0.03905832
A9: 6 | B9: Communications | C9: =Summary!F10 -> 8.913555 | D9: 7.65 | E9: 7.3 | G9: 7.3 | H9: 10.01 | I9: 7.21 | J9: 7.26 | K9: 6.99 | L9: 9.21 | M9: 8.21 | O9: =IFERROR(C9/D9-1,"") -> 0.16517059 | P9: =IFERROR(D9/E9-1,"") -> 0.047945205 | Q9: =IFERROR(E9/F9-1,"") | R9: =IFERROR(F9/G9-1,"") -> -1 | S9: =IFERROR(G9/H9-1,"") -> -0.27072927 | T9: =IFERROR(H9/I9-1,"") -> 0.38834951 | U9: =IFERROR(I9/J9-1,"") -> -0.0068870523 | V9: =IFERROR(J9/K9-1,"") -> 0.038626609 | ... X9: =IFERROR(L9/M9-1,"") -> 0.12180268
A10: 7 | B10: Computer and Information Sciences | C10: =Summary!F11 -> 9.8773789 | D10: 8.52 | E10: 8.44 | G10: 7.57 | H10: 9.93 | I10: 6.94 | J10: 6.92 | K10: 6.69 | L10: 6.32 | M10: 5.44 | O10: =IFERROR(C10/D10-1,"") -> 0.15931678 | P10: =IFERROR(D10/E10-1,"") -> 0.009478673 | Q10: =IFERROR(E10/F10-1,"") | R10: =IFERROR(F10/G10-1,"") -> -1 | S10: =IFERROR(G10/H10-1,"") -> -0.23766365 | T10: =IFERROR(H10/I10-1,"") -> 0.43083573 | U10: =IFERROR(I10/J10-1,"") -> 0.0028901734 | V10: =IFERROR(J10/K10-1,"") -> 0.034379671 | ... X10: =IFERROR(L10/M10-1,"") -> 0.16176471
A11: 8 | B11: Construction Trades | C11: =Summary!F12 -> 10.673804 | D11: 8.03 | E11: 7.77 | G11: 8.2 | H11: 10.92 | I11: 7.36 | J11: 6.75 | K11: 6.12 | L11: 6.42 | M11: 5.99 | O11: =IFERROR(C11/D11-1,"") -> 0.32924089 | P11: =IFERROR(D11/E11-1,"") -> 0.033462033 | Q11: =IFERROR(E11/F11-1,"") | R11: =IFERROR(F11/G11-1,"") -> -1 | S11: =IFERROR(G11/H11-1,"") -> -0.24908425 | T11: =IFERROR(H11/I11-1,"") -> 0.48369565 | U11: =IFERROR(I11/J11-1,"") -> 0.09037037 | V11: =IFERROR(J11/K11-1,"") -> 0.10294118 | ... X11: =IFERROR(L11/M11-1,"") -> 0.071786311
A12: 9 | B12: Consumer and Homemaking Education | C12: =Summary!F13 -> 7.7785582 | D12: 6.75 | E12: 6.49 | G12: 6.14 | H12: 8.08 | I12: 5.49 | J12: 5.51 | K12: 5.52 | L12: 5.14 | M12: 5.35 | O12: =IFERROR(C12/D12-1,"") -> 0.15237899 | P12: =IFERROR(D12/E12-1,"") -> 0.040061633 | Q12: =IFERROR(E12/F12-1,"") | R12: =IFERROR(F12/G12-1,"") -> -1 | S12: =IFERROR(G12/H12-1,"") -> -0.24009901 | T12: =IFERROR(H12/I12-1,"") -> 0.47176685 | U12: =IFERROR(I12/J12-1,"") -> -0.0036297641 | V12: =IFERROR(J12/K12-1,"") -> -0.0018115942 | ... X12: =IFERROR(L12/M12-1,"") -> -0.039252336
A13: 10 | B13: Engineering | C13: =Summary!F14 -> 11.277206 | D13: 7.86 | E13: 7.53 | G13: 10.3 | H13: 11.38 | I13: 8.92 | J13: 8.54 | K13: 11.49 | L13: 9.83 | M13: 7.64 | O13: =IFERROR(C13/D13-1,"") -> 0.43475898 | P13: =IFERROR(D13/E13-1,"") -> 0.043824701 | Q13: =IFERROR(E13/F13-1,"") | R13: =IFERROR(F13/G13-1,"") -> -1 | S13: =IFERROR(G13/H13-1,"") -> -0.094903339 | T13: =IFERROR(H13/I13-1,"") -> 0.27578475 | U13: =IFERROR(I13/J13-1,"") -> 0.044496487 | V13: =IFERROR(J13/K13-1,"") -> -0.256745 | ... X13: =IFERROR(L13/M13-1,"") -> 0.28664921
A14: 11 | B14: Engineering Related | C14: =Summary!F15 -> 8.4264374 | D14: 7.41 | E14: 7.09 | G14: 6.82 | H14: 9.52 | I14: 7.23 | J14: 6.89 | K14: 6.58 | L14: 6.71 | M14: 6.42 | O14: =IFERROR(C14/D14-1,"") -> 0.13717104 | P14: =IFERROR(D14/E14-1,"") -> 0.045133992 | Q14: =IFERROR(E14/F14-1,"") | R14: =IFERROR(F14/G14-1,"") -> -1 | S14: =IFERROR(G14/H14-1,"") -> -0.28361345 | T14: =IFERROR(H14/I14-1,"") -> 0.31673582 | U14: =IFERROR(I14/J14-1,"") -> 0.04934688 | V14: =IFERROR(J14/K14-1,"") -> 0.047112462 | ... X14: =IFERROR(L14/M14-1,"") -> 0.04517134
A15: 12 | B15: English Language, Lit, Philosophy, Humanities, & Interdisciplinary | C15: =Summary!F16 -> 8.2593827 | D15: 7.31 | E15: 7.08 | G15: 6.48 | H15: 8.33 | I15: 5.83 | J15: 5.94 | K15: 5.75 | L15: 5.68 | M15: 5.26 | O15: =IFERROR(C15/D15-1,"") -> 0.12987452 | P15: =IFERROR(D15/E15-1,"") -> 0.032485876 | Q15: =IFERROR(E15/F15-1,"") | R15: =IFERROR(F15/G15-1,"") -> -1 | S15: =IFERROR(G15/H15-1,"") -> -0.22208884 | T15: =IFERROR(H15/I15-1,"") -> 0.42881647 | U15: =IFERROR(I15/J15-1,"") -> -0.018518519 | V15: =IFERROR(J15/K15-1,"") -> 0.033043478 | ... X15: =IFERROR(L15/M15-1,"") -> 0.079847909
... A31: 29 | B31: Developmental Education - Reading/Writing | C31: =Summary!F32 -> 0 | D31: 0 | E31: 0 | G31: 0 | H31: 0 | I31: 0 | J31: 0 | K31: 0 | L31: 0 | M31: 0 | O31: =IFERROR(C31/D31-1,"") | P31: =IFERROR(D31/E31-1,"") | Q31: =IFERROR(E31/F31-1,"") | R31: =IFERROR(F31/G31-1,"") | S31: =IFERROR(G31/H31-1,"") | T31: =IFERROR(H31/I31-1,"") | U31: =IFERROR(I31/J31-1,"") | V31: =IFERROR(J31/K31-1,"") | ... X31: =IFERROR(L31/M31-1,"")
B32: Average | C32: =AVERAGE(C4:C31) -> 9.871227 | D32: =AVERAGE(D4:D31) -> 8.67 | E32: =AVERAGE(E4:E31) -> 8.4635714 | G32: =AVERAGE(G4:G31) -> 7.7992857 | H32: =AVERAGE(H4:H31) -> 9.7525 | I32: =AVERAGE(I4:I31) -> 6.9428571 | J32: =AVERAGE(J4:J31) -> 7.0071429 | K32: =AVERAGE(K4:K31) -> 7.0107143 | L32: =AVERAGE(L4:L31) -> 7.0171429 | M32: =AVERAGE(M4:M31) -> 6.5617857 | O32: =IFERROR(C32/D32-1,"") -> 0.13854982 | P32: =IFERROR(D32/E32-1,"") -> 0.024390244 | Q32: =IFERROR(E32/F32-1,"") | R32: =IFERROR(F32/G32-1,"") -> -1 | S32: =IFERROR(G32/H32-1,"") -> -0.20027832 | T32: =IFERROR(H32/I32-1,"") -> 0.40468107 | U32: =IFERROR(I32/J32-1,"") -> -0.0091743119 | V32: =IFERROR(J32/K32-1,"") -> -0.00050942435 | ... X32: =IFERROR(L32/M32-1,"") -> 0.069395308
B33: Median | C33: =MEDIAN(C4:C31) -> 9.3311851 | D33: =MEDIAN(D4:D31) -> 7.78 | E33: =MEDIAN(E4:E31) -> 7.525 | G33: =MEDIAN(G4:G31) -> 7.345 | H33: =MEDIAN(H4:H31) -> 9.615 | I33: =MEDIAN(I4:I31) -> 6.995 | J33: =MEDIAN(J4:J31) -> 6.905 | K33: =MEDIAN(K4:K31) -> 6.69 | L33: =MEDIAN(L4:L31) -> 6.69 | M33: =MEDIAN(M4:M31) -> 6.32 | O33: =IFERROR(C33/D33-1,"") -> 0.19938111 | P33: =IFERROR(D33/E33-1,"") -> 0.033887043 | Q33: =IFERROR(E33/F33-1,"") | R33: =IFERROR(F33/G33-1,"") -> -1 | S33: =IFERROR(G33/H33-1,"") -> -0.23608944 | T33: =IFERROR(H33/I33-1,"") -> 0.37455325 | U33: =IFERROR(I33/J33-1,"") -> 0.013034033 | V33: =IFERROR(J33/K33-1,"") -> 0.032137519 | ... X33: =IFERROR(L33/M33-1,"") -> 0.058544304
B34: Standard Deviation | C34: =STDEV(C4:C31) -> 5.9203334 | D34: =STDEV(D4:D31) -> 5.7536855 | E34: =STDEV(E4:E31) -> 5.2587227 | G34: =STDEV(G4:G31) -> 4.1137528 | H34: =STDEV(H4:H31) -> 4.4105653 | I34: =STDEV(I4:I31) -> 2.7509808 | J34: =STDEV(J4:J31) -> 2.6772026 | K34: =STDEV(K4:K31) -> 3.0868058 | L34: =STDEV(L4:L31) -> 3.4645516 | M34: =STDEV(M4:M31) -> 3.2525364 | O34: =IFERROR(C34/D34-1,"") -> 0.028963686 | P34: =IFERROR(D34/E34-1,"") -> 0.094122236 | Q34: =IFERROR(E34/F34-1,"") | R34: =IFERROR(F34/G34-1,"") -> -1 | S34: =IFERROR(G34/H34-1,"") -> -0.067295782 | T34: =IFERROR(H34/I34-1,"") -> 0.60327012 | U34: =IFERROR(I34/J34-1,"") -> 0.027557936 | V34: =IFERROR(J34/K34-1,"") -> -0.13269483 | ... X34: =IFERROR(L34/M34-1,"") -> 0.065184562

Sheet FTSE Summary
A1: =Summary!A1 -> Community and Technical Colleges, Report of Fundable Operating Expenses, Fiscal Year (FY) 2009
A2: Average Total Expenditure per Full-Time Student Equivalent (FTSE)
A3: Institution | B3: Annual State Funded Semester Credit Hours | C3: Total FTSE | D3: Total Expenditure | E3: Average Expenditure per FTSE
A4: Alamo | B4: 1058786 | C4: =B4/30 -> 35292.867 | D4: ='1'!$E$33 -> 2.0866447e+08 | E4: =IFERROR(D4/C4,"") -> 5912.3695
A5: Alvin | B5: 95665 | C5: =B5/30 -> 3188.8333 | D5: ='2'!$E$33 -> 21650677 | E5: =IFERROR(D5/C5,"") -> 6789.5292
A6: Amarillo | B6: 182539 | C6: =B6/30 -> 6084.6333 | D6: ='3'!$E$33 -> 37778402 | E6: =IFERROR(D6/C6,"") -> 6208.8215
A7: Angelina | B7: 95200 | C7: =B7/30 -> 3173.3333 | D7: ='4'!$E$33 -> 14259157 | E7: =IFERROR(D7/C7,"") -> 4493.4318
A8: Austin | B8: 697698 | C8: =B8/30 -> 23256.6 | D8: ='5'!$E$33 -> 1.5176977e+08 | E8: =IFERROR(D8/C8,"") -> 6525.8796
A9: Blinn | B9: 355946 | C9: =B9/30 -> 11864.867 | D9: ='6'!$E$33 -> 42057632 | E9: =IFERROR(D9/C9,"") -> 3544.7202
A10: Brazosport | B10: 68879 | C10: =B10/30 -> 2295.9667 | D10: ='7'!$E$33 -> 15048156 | E10: =IFERROR(D10/C10,"") -> 6554.1701
A11: Central Texas | B11: 260038 | C11: =B11/30 -> 8667.9333 | D11: ='8'!$E$33 -> 47596057 | E11: =IFERROR(D11/C11,"") -> 5491.0502
A12: Cisco | B12: 77412 | C12: =B12/30 -> 2580.4 | D12: ='9'!$E$33 -> 9521537 | E12: =IFERROR(D12/C12,"") -> 3689.9461
A13: Clarendon | B13: 29191 | C13: =B13/30 -> 973.03333 | D13: ='10'!$E$33 -> 3900789 | E13: =IFERROR(D13/C13,"") -> 4008.8955
A14: Coastal Bend | B14: 72230 | C14: =B14/30 -> 2407.6667 | D14: ='11'!$E$33 -> 14139348 | E14: =IFERROR(D14/C14,"") -> 5872.6352
A15: College Of The Mainland | B15: 74308 | C15: =B15/30 -> 2476.9333 | D15: ='12'!$E$33 -> 0 | E15: =IFERROR(D15/C15,"") -> 0
A16: Collin | B16: 442157 | C16: =B16/30 -> 14738.567 | D16: ='13'!$E$33 -> 80287869 | E16: =IFERROR(D16/C16,"") -> 5447.4679
A17: Dallas | B17: 1240673 | C17: =B17/30 -> 41355.767 | D17: ='14'!$E$33 -> 233857119 | E17: =IFERROR(D17/C17,"") -> 5654.7644
A18: Del Mar | B18: 211926 | C18: =B18/30 -> 7064.2 | D18: ='15'!$E$33 -> 53827021 | E18: =IFERROR(D18/C18,"") -> 7619.691
A19: El Paso | B19: 492251 | C19: =B19/30 -> 16408.367 | D19: ='16'!$E$33 -> 82584383 | E19: =IFERROR(D19/C19,"") -> 5033.0654
A20: Frank Phillips | B20: 24842 | C20: =B20/30 -> 828.06667 | D20: ='17'!$E$33 -> 6035988 | E20: =IFERROR(D20/C20,"") -> 7289.2537
A21: Galveston | B21: 39172 | C21: =B21/30 -> 1305.7333 | D21: ='18'!$E$33 -> 12047577 | E21: =IFERROR(D21/C21,"") -> 9226.6749
A22: Grayson | B22: 92493 | C22: =B22/30 -> 3083.1 | D22: ='19'!$E$33 -> 14481730 | E22: =IFERROR(D22/C22,"") -> 4697.1328
A23: Hill | B23: 80072 | C23: =B23/30 -> 2669.0667 | D23: ='20'!$E$33 -> 11551061 | E23: =IFERROR(D23/C23,"") -> 4327.7529
A24: Houston | B24: 951017 | C24: =B24/30 -> 31700.567 | D24: ='21'!$E$33 -> 180970906 | E24: =IFERROR(D24/C24,"") -> 5708.7593
A25: Howard | B25: 65104 | C25: =B25/30 -> 2170.1333 | D25: ='22'!$E$33 -> 16020108 | E25: =IFERROR(D25/C25,"") -> 7382.0847
A26: Kilgore | B26: 122178 | C26: =B26/30 -> 4072.6 | D26: ='23'!$E$33 -> 21474142 | E26: =IFERROR(D26/C26,"") -> 5272.8336
A27: Laredo | B27: 165170 | C27: =B27/30 -> 5505.6667 | D27: ='24'!$E$33 -> 35259656 | E27: =IFERROR(D27/C27,"") -> 6404.2482
A28: Lee | B28: 126763 | C28: =B28/30 -> 4225.4333 | D28: ='25'!$E$33 -> 28444801 | E28: =IFERROR(D28/C28,"") -> 6731.8068
A29: Lonestar | B29: 869997 | C29: =B29/30 -> 28999.9 | D29: ='26'!$E$33 -> 166864847 | E29: =IFERROR(D29/C29,"") -> 5753.9801
A30: Mclennan | B30: 176902 | C30: =B30/30 -> 5896.7333 | D30: ='27'!$E$33 -> 36014717 | E30: =IFERROR(D30/C30,"") -> 6107.5709
A31: Midland | B31: 112925 | C31: =B31/30 -> 3764.1667 | D31: ='28'!$E$33 -> 27584805 | E31: =IFERROR(D31/C31,"") -> 7328.2634
A32: Navarro | B32: 186501 | C32: =B32/30 -> 6216.7 | D32: ='29'!$E$33 -> 21320555 | E32: =IFERROR(D32/C32,"") -> 3429.5615
A33: North Central Texas | B33: 159586 | C33: =B33/30 -> 5319.5333 | D33: ='30'!$E$33 -> 18359956 | E33: =IFERROR(D33/C33,"") -> 3451.4223
A34: Northeast Texas | B34: 54306 | C34: =B34/30 -> 1810.2 | D34: ='31'!$E$33 -> 9366376 | E34: =IFERROR(D34/C34,"") -> 5174.2216
A35: Odessa | B35: 87447 | C35: =B35/30 -> 2914.9 | D35: ='32'!$E$33 -> 21099064 | E35: =IFERROR(D35/C35,"") -> 7238.3492
A36: Panola | B36: 42511 | C36: =B36/30 -> 1417.0333 | D36: ='33'!$E$33 -> 9725576 | E36: =IFERROR(D36/C36,"") -> 6863.3361
A37: Paris | B37: 99580 | C37: =B37/30 -> 3319.3333 | D37: ='34'!$E$33 -> 13129915 | E37: =IFERROR(D37/C37,"") -> 3955.588
A38: Ranger | B38: 18370 | C38: =B38/30 -> 612.33333 | D38: ='35'!$E$33 -> 2777146 | E38: =IFERROR(D38/C38,"") -> 4535.35
A39: San Jacinto | B39: 502458 | C39: =B39/30 -> 16748.6 | D39: ='36'!$E$33 -> 91502268 | E39: =IFERROR(D39/C39,"") -> 5463.2786
A40: South Plains | B40: 196135 | C40: =B40/30 -> 6537.8333 | D40: ='37'!$E$33 -> 28369105 | E40: =IFERROR(D40/C40,"") -> 4339.2212
A41: South Texas | B41: 416063 | C41: =B41/30 -> 13868.767 | D41: ='38'!$E$33 -> 74791503 | E41: =IFERROR(D41/C41,"") -> 5392.8013
A42: Southwest Texas | B42: 98820 | C42: =B42/30 -> 3294 | D42: ='39'!$E$33 -> 15709600 | E42: =IFERROR(D42/C42,"") -> 4769.156
A43: Tarrant | B43: 790444 | C43: =B43/30 -> 26348.133 | D43: ='40'!$E$33 -> 127688204 | E43: =IFERROR(D43/C43,"") -> 4846.1955
A44: Temple | B44: 104954 | C44: =B44/30 -> 3498.4667 | D44: ='41'!$E$33 -> 17853380 | E44: =IFERROR(D44/C44,"") -> 5103.2014
A45: Texarkana | B45: 92157 | C45: =B45/30 -> 3071.9 | D45: ='42'!$E$33 -> 0 | E45: =IFERROR(D45/C45,"") -> 0
A46: Texas Southmost | B46: 178331 | C46: =B46/30 -> 5944.3667 | D46: ='43'!$E$33 -> 0 | E46: =IFERROR(D46/C46,"") -> 0
A47: Trinity Valley | B47: 136276 | C47: =B47/30 -> 4542.5333 | D47: ='44'!$E$33 -> 19472846 | E47: =IFERROR(D47/C47,"") -> 4286.7811
A48: Tyler | B48: 223562 | C48: =B48/30 -> 7452.0667 | D48: ='45'!$E$33 -> 37809202 | E48: =IFERROR(D48/C48,"") -> 5073.6532
A49: Vernon | B49: 61116 | C49: =B49/30 -> 2037.2 | D49: ='46'!$E$33 -> 9948125 | E49: =IFERROR(D49/C49,"") -> 4883.2343
A50: Victoria | B50: 74378 | C50: =B50/30 -> 2479.2667 | D50: ='47'!$E$33 -> 17235576 | E50: =IFERROR(D50/C50,"") -> 6951.8847
A51: Weatherford | B51: 98994 | C51: =B51/30 -> 3299.8 | D51: ='48'!$E$33 -> 18428239 | E51: =IFERROR(D51/C51,"") -> 5584.6533
A52: Western Texas | B52: 42061 | C52: =B52/30 -> 1402.0333 | D52: ='49'!$E$33 -> 6840250 | E52: =IFERROR(D52/C52,"") -> 4878.807
A53: Wharton | B53: 125427 | C53: =B53/30 -> 4180.9 | D53: ='50'!$E$33 -> 22124259 | E53: =IFERROR(D53/C53,"") -> 5291.7456
A54: TSTC-Harlingen | B54: 119385 | C54: =B54/30 -> 3979.5 | D54: ='51'!$E$33 -> 21620132 | E54: =IFERROR(D54/C54,"") -> 5432.8765
A55: TSTC-West Texas | B55: 44160 | C55: =B55/30 -> 1472 | D55: ='52'!$E$33 -> 13225931 | E55: =IFERROR(D55/C55,"") -> 8985.0075
A56: TSTC-Marshall | B56: 19832 | C56: =B56/30 -> 661.06667 | D56: ='53'!$E$33 -> 5306505 | E56: =IFERROR(D56/C56,"") -> 8027.1859
A57: TSTC-Waco | B57: 133227 | C57: =B57/30 -> 4440.9 | D57: ='54'!$E$33 -> 32764479 | E57: =IFERROR(D57/C57,"") -> 7377.8916
A58: Lamar-IOT | B58: 64187 | C58: =B58/30 -> 2139.5667 | D58: ='55'!$E$33 -> 21554948 | E58: =IFERROR(D58/C58,"") -> 10074.446
A59: Lamar-Orange | B59: 43271 | C59: =B59/30 -> 1442.3667 | D59: ='56'!$E$33 -> 0 | E59: =IFERROR(D59/C59,"") -> 0
A60: Lamar-Port Arthur | B60: 41210 | C60: =B60/30 -> 1373.6667 | D60: ='57'!$E$33 -> 20292558 | E60: =IFERROR(D60/C60,"") -> 14772.549
A61: Total for Instutions Reporting Expense | B61: =SUMIF(D4:D60,">0",B4:B60) -> 12148216 | C61: =B61/30 -> 404940.53 | D61: =SUM(D4:D60) -> 2272008424 | E61: =IFERROR(D61/C61,"") -> 5610.7212

Sheet Discipline Summary
A1: =Summary!A1 -> Community and Technical Colleges, Report of Fundable Operating Expenses, Fiscal Year (FY) 2009
A2: Discipline Summary of Expense per Contact Hour by Institution
A3: Institution | B3: AG | C3: ARCH | D3: SCI | E3: BA | F3: CP | G3: COMM | H3: CS | I3: CNSTR | J3: HE | K3: ENG | L3: ENGR | M3: LA | N3: FL | O3: HODA | P3: HODH | Q3: HOO | R3: HORT | S3: NUR | T3: MATH | U3: AUTO | V3: MECH | W3: ELECT | X3: PE | Y3: PA | Z3: SS | AA3: FA | AB3: DEM | AC3: DER | AD3: Total
A4: Alamo | B4: ='1'!$F$5 -> 7.603128 | C4: ='1'!$F$6 -> 12.101788 | D4: ='1'!$F$7 -> 9.3650965 | E4: ='1'!$F$8 -> 9.8422926 | F4: ='1'!$F$9 -> 106.94003 | G4: ='1'!$F$10 -> 11.115511 | H4: ='1'!$F$11 -> 10.972126 | I4: ='1'!$F$12 -> 10.720533 | J4: ='1'!$F$13 -> 9.8017384 | K4: ='1'!$F$14 -> 18.137073 | L4: ='1'!$F$15 -> 13.197996 | M4: ='1'!$F$16 -> 9.1869356 | N4: ='1'!$F$17 -> 7.955001 | O4: ='1'!$F$18 -> 18.027764 | P4: ='1'!$F$19 | Q4: ='1'!$F$20 -> 11.011956 | R4: ='1'!$F$21 -> 17.684688 | S4: ='1'!$F$22 -> 12.723883 | T4: ='1'!$F$23 -> 8.807904 | U4: ='1'!$F$24 -> 10.611408 | V4: ='1'!$F$25 -> 12.076936 | W4: ='1'!$F$26 -> 5.3409289 | X4: ='1'!$F$27 -> 10.129854 | Y4: ='1'!$F$28 -> 9.1611829 | Z4: ='1'!$F$29 -> 8.4327659 | AA4: ='1'!$F$30 -> 11.060968 | AB4: ='1'!$F$31 | AC4: ='1'!$F$32 | AD4: ='1'!$F$33 -> 9.7162787
A5: Alvin | B5: ='2'!$F$5 -> 8.6873651 | C5: ='2'!$F$6 -> 8.3352263 | D5: ='2'!$F$7 -> 6.1853423 | E5: ='2'!$F$8 -> 12.184762 | F5: ='2'!$F$9 | G5: ='2'!$F$10 -> 9.9408003 | H5: ='2'!$F$11 -> 11.672517 | I5: ='2'!$F$12 -> 8.7301207 | J5: ='2'!$F$13 -> 8.9508497 | K5: ='2'!$F$14 | L5: ='2'!$F$15 -> 10.821927 | M5: ='2'!$F$16 -> 8.538 | N5: ='2'!$F$17 -> 6.5555529 | O5: ='2'!$F$18 -> 11.376602 | P5: ='2'!$F$19 | Q5: ='2'!$F$20 -> 12.572931 | R5: ='2'!$F$21 -> 13.03966 | S5: ='2'!$F$22 -> 9.328425 | T5: ='2'!$F$23 -> 7.6104371 | U5: ='2'!$F$24 -> 9.7415278 | V5: ='2'!$F$25 -> 4.1168106 | W5: ='2'!$F$26 -> 6.1233897 | X5: ='2'!$F$27 -> 11.653483 | Y5: ='2'!$F$28 -> 8.6467055 | Z5: ='2'!$F$29 -> 7.5431497 | AA5: ='2'!$F$30 -> 15.171573 | AB5: ='2'!$F$31 | AC5: ='2'!$F$32 | AD5: ='2'!$F$33 -> 9.5229469
A6: Amarillo | B6: ='3'!$F$5 -> 8.0869201 | C6: ='3'!$F$6 -> 9.3206261 | D6: ='3'!$F$7 -> 7.6568165 | E6: ='3'!$F$8 -> 8.550775 | F6: ='3'!$F$9 -> 9.372029 | G6: ='3'!$F$10 -> 8.6788066 | H6: ='3'!$F$11 -> 8.4152715 | I6: ='3'!$F$12 -> 9.3683925 | J6: ='3'!$F$13 -> 7.2552275 | K6: ='3'!$F$14 -> 7.6237403 | L6: ='3'!$F$15 -> 8.4617076 | M6: ='3'!$F$16 -> 9.0307993 | N6: ='3'!$F$17 -> 8.0342085 | O6: ='3'!$F$18 -> 9.5572207 | P6: ='3'!$F$19 -> 8.7007774 | Q6: ='3'!$F$20 -> 8.5852933 | R6: ='3'!$F$21 -> 8.7756293 | S6: ='3'!$F$22 -> 9.9102305 | T6: ='3'!$F$23 -> 7.8894405 | U6: ='3'!$F$24 -> 9.3684072 | V6: ='3'!$F$25 -> 9.3647828 | W6: ='3'!$F$26 -> 8.8138505 | X6: ='3'!$F$27 -> 5.9301319 | Y6: ='3'!$F$28 -> 8.3706665 | Z6: ='3'!$F$29 -> 6.1359837 | AA6: ='3'!$F$30 -> 8.0141502 | AB6: ='3'!$F$31 | AC6: ='3'!$F$32 | AD6: ='3'!$F$33 -> 8.1607864
A7: Angelina | B7: ='4'!$F$5 -> 4.6391615 | C7: ='4'!$F$6 -> 9.3478806 | D7: ='4'!$F$7 -> 5.5250562 | E7: ='4'!$F$8 -> 6.2645132 | F7: ='4'!$F$9 | G7: ='4'!$F$10 -> 10.795874 | H7: ='4'!$F$11 -> 11.010949 | I7: ='4'!$F$12 -> 6.9055094 | J7: ='4'!$F$13 -> 6.2990453 | K7: ='4'!$F$14 -> 14.97098 | L7: ='4'!$F$15 -> 6.7748572 | M7: ='4'!$F$16 -> 5.4044949 | N7: ='4'!$F$17 -> 5.2572775 | O7: ='4'!$F$18 -> 10.626404 | P7: ='4'!$F$19 | Q7: ='4'!$F$20 -> 6.3219565 | R7: ='4'!$F$21 -> 9.4369868 | S7: ='4'!$F$22 -> 5.9932117 | T7: ='4'!$F$23 -> 6.6025368 | U7: ='4'!$F$24 -> 9.5240129 | V7: ='4'!$F$25 -> 8.2259822 | W7: ='4'!$F$26 -> 6.7741876 | X7: ='4'!$F$27 -> 7.0417084 | Y7: ='4'!$F$28 -> 5.7587599 | Z7: ='4'!$F$29 -> 5.3035952 | AA7: ='4'!$F$30 -> 7.9509374 | AB7: ='4'!$F$31 | AC7: ='4'!$F$32 | AD7: ='4'!$F$33 -> 6.4829172
A8: Austin | B8: ='5'!$F$5 -> 7.2688884 | C8: ='5'!$F$6 -> 16.158143 | D8: ='5'!$F$7 -> 11.141 | E8: ='5'!$F$8 -> 9.7895707 | F8: ='5'!$F$9 | G8: ='5'!$F$10 -> 8.6445183 | H8: ='5'!$F$11 -> 15.967604 | I8: ='5'!$F$12 -> 6.049005 | J8: ='5'!$F$13 -> 14.841007 | K8: ='5'!$F$14 -> 16.617903 | L8: ='5'!$F$15 -> 12.704747 | M8: ='5'!$F$16 -> 10.011883 | N8: ='5'!$F$17 -> 9.7165447 | O8: ='5'!$F$18 -> 15.532566 | P8: ='5'!$F$19 -> 31.583078 | Q8: ='5'!$F$20 -> 15.016359 | R8: ='5'!$F$21 | S8: ='5'!$F$22 -> 18.609714 | T8: ='5'!$F$23 -> 9.0883159 | U8: ='5'!$F$24 -> 15.092925 | V8: ='5'!$F$25 -> 49.152354 | W8: ='5'!$F$26 -> 31.112665 | X8: ='5'!$F$27 -> 9.8652915 | Y8: ='5'!$F$28 -> 10.288539 | Z8: ='5'!$F$29 -> 8.461757 | AA8: ='5'!$F$30 -> 14.663626 | AB8: ='5'!$F$31 | AC8: ='5'!$F$32 | AD8: ='5'!$F$33 -> 10.858162
A9: Blinn | B9: ='6'!$F$5 -> 7.158193 | C9: ='6'!$F$6 -> 11.25051 | D9: ='6'!$F$7 -> 4.7774171 | E9: ='6'!$F$8 -> 7.3522632 | F9: ='6'!$F$9 | G9: ='6'!$F$10 -> 4.0733694 | H9: ='6'!$F$11 -> 15.342066 | I9: ='6'!$F$12 -> 11.25049 | J9: ='6'!$F$13 -> 3.6226236 | K9: ='6'!$F$14 | L9: ='6'!$F$15 -> 25.121388 | M9: ='6'!$F$16 -> 6.5980677 | N9: ='6'!$F$17 -> 5.9577049 | O9: ='6'!$F$18 -> 14.039926 | P9: ='6'!$F$19 -> 25.203667 | Q9: ='6'!$F$20 -> 7.4140944 | R9: ='6'!$F$21 | S9: ='6'!$F$22 -> 7.74297 | T9: ='6'!$F$23 -> 5.6779825 | U9: ='6'!$F$24 -> 11.250381 | V9: ='6'!$F$25 -> 11.250567 | W9: ='6'!$F$26 -> 11.250705 | X9: ='6'!$F$27 -> 6.999174 | Y9: ='6'!$F$28 -> 5.8783649 | Z9: ='6'!$F$29 -> 4.7355482 | AA9: ='6'!$F$30 -> 6.6259243 | AB9: ='6'!$F$31 | AC9: ='6'!$F$32 | AD9: ='6'!$F$33 -> 6.0424602
A10: Brazosport | B10: ='7'!$F$5 | C10: ='7'!$F$6 -> 11.082239 | D10: ='7'!$F$7 -> 10.834324 | E10: ='7'!$F$8 -> 11.521906 | F10: ='7'!$F$9 | G10: ='7'!$F$10 | H10: ='7'!$F$11 -> 11.140116 | I10: ='7'!$F$12 -> 11.18581 | J10: ='7'!$F$13 -> 7.8099524 | K10: ='7'!$F$14 | L10: ='7'!$F$15 -> 6.2738347 | M10: ='7'!$F$16 -> 9.24087 | N10: ='7'!$F$17 -> 9.5126537 | O10: ='7'!$F$18 -> 22.819283 | P10: ='7'!$F$19 | Q10: ='7'!$F$20 -> 18.302609 | R10: ='7'!$F$21 | S10: ='7'!$F$22 -> 14.667404 | T10: ='7'!$F$23 -> 8.8103484 | U10: ='7'!$F$24 -> 10.574499 | V10: ='7'!$F$25 -> 30.5166 | W10: ='7'!$F$26 -> 12.528932 | X10: ='7'!$F$27 -> 11.329425 | Y10: ='7'!$F$28 -> 9.4245573 | Z10: ='7'!$F$29 -> 8.4508676 | AA10: ='7'!$F$30 -> 13.531377 | AB10: ='7'!$F$31 | AC10: ='7'!$F$32 | AD10: ='7'!$F$33 -> 10.086423
A11: Central Texas | B11: ='8'!$F$5 -> 5.254863 | C11: ='8'!$F$6 -> 13.701736 | D11: ='8'!$F$7 -> 7.5121892 | E11: ='8'!$F$8 -> 7.1024759 | F11: ='8'!$F$9 -> 57.081274 | G11: ='8'!$F$10 -> 7.3751735 | H11: ='8'!$F$11 -> 17.923499 | I11: ='8'!$F$12 -> 9.1514465 | J11: ='8'!$F$13 -> 5.7736249 | K11: ='8'!$F$14 -> 158.1185 | L11: ='8'!$F$15 -> 4.9243556 | M11: ='8'!$F$16 -> 7.1963464 | N11: ='8'!$F$17 -> 7.4144033 | O11: ='8'!$F$18 -> 13.664617 | P11: ='8'!$F$19 | Q11: ='8'!$F$20 -> 10.801458 | R11: ='8'!$F$21 | S11: ='8'!$F$22 -> 9.3515086 | T11: ='8'!$F$23 -> 6.5494019 | U11: ='8'!$F$24 -> 8.8400672 | V11: ='8'!$F$25 -> 7.038938 | W11: ='8'!$F$26 -> 28.22519 | X11: ='8'!$F$27 -> 8.6165652 | Y11: ='8'!$F$28 -> 9.0450087 | Z11: ='8'!$F$29 -> 6.0041752 | AA11: ='8'!$F$30 -> 6.9630226 | AB11: ='8'!$F$31 | AC11: ='8'!$F$32 | AD11: ='8'!$F$33 -> 8.3298475
A12: Cisco | B12: ='9'!$F$5 -> 9.5496279 | C12: ='9'!$F$6 -> 5.831037 | D12: ='9'!$F$7 -> 4.928326 | E12: ='9'!$F$8 -> 4.3696829 | F12: ='9'!$F$9 | G12: ='9'!$F$10 | H12: ='9'!$F$11 -> 19.330405 | I12: ='9'!$F$12 -> 6.1648408 | J12: ='9'!$F$13 -> 5.3224353 | K12: ='9'!$F$14 | L12: ='9'!$F$15 -> 5.7743063 | M12: ='9'!$F$16 -> 5.81278 | N12: ='9'!$F$17 -> 5.6333109 | O12: ='9'!$F$18 -> 7.7161365 | P12: ='9'!$F$19 | Q12: ='9'!$F$20 -> 4.4878608 | R12: ='9'!$F$21 -> 9.06687 | S12: ='9'!$F$22 -> 6.0331279 | T12: ='9'!$F$23 -> 5.7901659 | U12: ='9'!$F$24 -> 10.17417 | V12: ='9'!$F$25 | W12: ='9'!$F$26 -> 6.0870681 | X12: ='9'!$F$27 -> 11.01165 | Y12: ='9'!$F$28 -> 6.4448931 | Z12: ='9'!$F$29 -> 5.2359233 | AA12: ='9'!$F$30 -> 6.3329309 | AB12: ='9'!$F$31 | AC12: ='9'!$F$32 | AD12: ='9'!$F$33 -> 5.9323664
A13: Clarendon | B13: ='10'!$F$5 -> 8.6128713 | C13: ='10'!$F$6 -> 6.4237601 | D13: ='10'!$F$7 -> 5.4478402 | E13: ='10'!$F$8 -> 5.7112874 | F13: ='10'!$F$9 | G13: ='10'!$F$10 -> 4.4995703 | H13: ='10'!$F$11 -> 8.0778073 | I13: ='10'!$F$12 | J13: ='10'!$F$13 -> 4.2064095 | K13: ='10'!$F$14 | L13: ='10'!$F$15 -> 6.8884955 | M13: ='10'!$F$16 -> 5.7055589 | N13: ='10'!$F$17 -> 5.8404329 | O13: ='10'!$F$18 | P13: ='10'!$F$19 | Q13: ='10'!$F$20 -> 3.728902 | R13: ='10'!$F$21 | S13: ='10'!$F$22 -> 6.1526649 | T13: ='10'!$F$23 -> 5.6137572 | U13: ='10'!$F$24 | V13: ='10'!$F$25 | W13: ='10'!$F$26 -> 9.6252648 | X13: ='10'!$F$27 -> 7.1579446 | Y13: ='10'!$F$28 -> 3.2897348 | Z13: ='10'!$F$29 -> 5.2216391 | AA13: ='10'!$F$30 -> 4.6881988 | AB13: ='10'!$F$31 | AC13: ='10'!$F$32 | AD13: ='10'!$F$33 -> 5.8401165
A14: Coastal Bend | B14: ='11'!$F$5 -> 6.1299472 | C14: ='11'!$F$6 -> 7.7305296 | D14: ='11'!$F$7 -> 7.329332 | E14: ='11'!$F$8 -> 9.677696 | F14: ='11'!$F$9 | G14: ='11'!$F$10 -> 8.2196618 | H14: ='11'!$F$11 -> 7.3042059 | I14: ='11'!$F$12 -> 8.1937359 | J14: ='11'!$F$13 -> 7.7345147 | K14: ='11'!$F$14 -> 5.8566515 | L14: ='11'!$F$15 -> 7.2800603 | M14: ='11'!$F$16 -> 7.9696088 | N14: ='11'!$F$17 -> 11.615175 | O14: ='11'!$F$18 -> 20.290563 | P14: ='11'!$F$19 -> 15.271303 | Q14: ='11'!$F$20 -> 7.9136272 | R14: ='11'!$F$21 | S14: ='11'!$F$22 -> 9.3939955 | T14: ='11'!$F$23 -> 8.2826606 | U14: ='11'!$F$24 -> 8.001576 | V14: ='11'!$F$25 -> 12.109986 | W14: ='11'!$F$26 -> 7.7689706 | X14: ='11'!$F$27 -> 7.4397659 | Y14: ='11'!$F$28 -> 9.292929 | Z14: ='11'!$F$29 -> 4.1869452 | AA14: ='11'!$F$30 -> 5.9344476 | AB14: ='11'!$F$31 | AC14: ='11'!$F$32 | AD14: ='11'!$F$33 -> 7.7665212
A15: College Of The Mainland | B15: ='12'!$F$5 | C15: ='12'!$F$6 | D15: ='12'!$F$7 | E15: ='12'!$F$8 | F15: ='12'!$F$9 | G15: ='12'!$F$10 | H15: ='12'!$F$11 | I15: ='12'!$F$12 | J15: ='12'!$F$13 | K15: ='12'!$F$14 | L15: ='12'!$F$15 | M15: ='12'!$F$16 | N15: ='12'!$F$17 | O15: ='12'!$F$18 | P15: ='12'!$F$19 | Q15: ='12'!$F$20 | R15: ='12'!$F$21 | S15: ='12'!$F$22 | T15: ='12'!$F$23 | U15: ='12'!$F$24 | V15: ='12'!$F$25 | W15: ='12'!$F$26 | X15: ='12'!$F$27 | Y15: ='12'!$F$28 | Z15: ='12'!$F$29 | AA15: ='12'!$F$30 | AB15: ='12'!$F$31 | AC15: ='12'!$F$32 | AD15: ='12'!$F$33
A16: Collin | B16: ='13'!$F$5 -> 4.7648644 | C16: ='13'!$F$6 -> 4.7651411 | D16: ='13'!$F$7 -> 9.4830794 | E16: ='13'!$F$8 -> 6.1766291 | F16: ='13'!$F$9 -> 4.7655608 | G16: ='13'!$F$10 -> 5.026632 | H16: ='13'!$F$11 -> 9.626001 | I16: ='13'!$F$12 -> 4.7651824 | J16: ='13'!$F$13 -> 10.133978 | K16: ='13'!$F$14 -> 38.176576 | L16: ='13'!$F$15 -> 10.602595 | M16: ='13'!$F$16 -> 8.2870209 | N16: ='13'!$F$17 -> 6.6600235 | O16: ='13'!$F$18 -> 21.253024 | P16: ='13'!$F$19 -> 25.351457 | Q16: ='13'!$F$20 -> 8.5724336 | R16: ='13'!$F$21 -> 15.697639 | S16: ='13'!$F$22 | T16: ='13'!$F$23 -> 7.7443332 | U16: ='13'!$F$24 | V16: ='13'!$F$25 -> 4.7484744 | W16: ='13'!$F$26 -> 4.7649132 | X16: ='13'!$F$27 -> 9.3597281 | Y16: ='13'!$F$28 -> 10.715827 | Z16: ='13'!$F$29 -> 7.5481908 | AA16: ='13'!$F$30 -> 10.485568 | AB16: ='13'!$F$31 | AC16: ='13'!$F$32 | AD16: ='13'!$F$33 -> 8.5502295
A17: Dallas | B17: ='14'!$F$5 -> 18.048833 | C17: ='14'!$F$6 -> 10.543374 | D17: ='14'!$F$7 -> 7.786414 | E17: ='14'!$F$8 -> 8.0099742 | F17: ='14'!$F$9 -> 14.985355 | G17: ='14'!$F$10 -> 9.2199116 | H17: ='14'!$F$11 -> 8.3429283 | I17: ='14'!$F$12 -> 17.586012 | J17: ='14'!$F$13 -> 7.2534746 | K17: ='14'!$F$14 -> 13.549484 | L17: ='14'!$F$15 -> 5.6978975 | M17: ='14'!$F$16 -> 8.3289394 | N17: ='14'!$F$17 -> 7.4357531 | O17: ='14'!$F$18 -> 11.721522 | P17: ='14'!$F$19 | Q17: ='14'!$F$20 -> 7.9472452 | R17: ='14'!$F$21 -> 18.233515 | S17: ='14'!$F$22 -> 13.271347 | T17: ='14'!$F$23 -> 7.4227707 | U17: ='14'!$F$24 -> 10.26988 | V17: ='14'!$F$25 -> 5.603513 | W17: ='14'!$F$26 -> 7.130562 | X17: ='14'!$F$27 -> 9.131402 | Y17: ='14'!$F$28 -> 7.3195167 | Z17: ='14'!$F$29 -> 6.9661325 | AA17: ='14'!$F$30 -> 8.9691655 | AB17: ='14'!$F$31 | AC17: ='14'!$F$32 | AD17: ='14'!$F$33 -> 8.0469197
A18: Del Mar | B18: ='15'!$F$5 -> 10.756891 | C18: ='15'!$F$6 -> 10.92784 | D18: ='15'!$F$7 -> 8.8862029 | E18: ='15'!$F$8 -> 11.396527 | F18: ='15'!$F$9 | G18: ='15'!$F$10 -> 13.081413 | H18: ='15'!$F$11 -> 10.547526 | I18: ='15'!$F$12 -> 9.6666716 | J18: ='15'!$F$13 -> 10.455213 | K18: ='15'!$F$14 -> 11.504869 | L18: ='15'!$F$15 -> 9.5010016 | M18: ='15'!$F$16 -> 10.539652 | N18: ='15'!$F$17 -> 10.410124 | O18: ='15'!$F$18 -> 12.935012 | P18: ='15'!$F$19 -> 17.961474 | Q18: ='15'!$F$20 -> 10.623309 | R18: ='15'!$F$21 -> 12.432344 | S18: ='15'!$F$22 -> 41.315897 | T18: ='15'!$F$23 -> 11.522115 | U18: ='15'!$F$24 -> 11.302936 | V18: ='15'!$F$25 -> 8.0622707 | W18: ='15'!$F$26 -> 11.951463 | X18: ='15'!$F$27 -> 9.1569601 | Y18: ='15'!$F$28 -> 11.180262 | Z18: ='15'!$F$29 -> 9.0633488 | AA18: ='15'!$F$30 -> 13.553434 | AB18: ='15'!$F$31 | AC18: ='15'!$F$32 | AD18: ='15'!$F$33 -> 10.650911
A19: El Paso | B19: ='16'!$F$5 -> 6.2512499 | C19: ='16'!$F$6 -> 10.244708 | D19: ='16'!$F$7 -> 7.0825259 | E19: ='16'!$F$8 -> 10.151685 | F19: ='16'!$F$9 | G19: ='16'!$F$10 -> 14.204122 | H19: ='16'!$F$11 -> 8.3471899 | I19: ='16'!$F$12 -> 11.96718 | J19: ='16'!$F$13 -> 8.5803816 | K19: ='16'!$F$14 -> 7.556908 | L19: ='16'!$F$15 -> 7.0326793 | M19: ='16'!$F$16 -> 8.1031955 | N19: ='16'!$F$17 -> 8.0218947 | O19: ='16'!$F$18 -> 12.992937 | P19: ='16'!$F$19 -> 19.612233 | Q19: ='16'!$F$20 -> 12.170391 | R19: ='16'!$F$21 -> 18.373765 | S19: ='16'!$F$22 -> 10.396209 | T19: ='16'!$F$23 -> 6.8789527 | U19: ='16'!$F$24 -> 9.1257704 | V19: ='16'!$F$25 -> 13.856148 | W19: ='16'!$F$26 -> 12.795458 | X19: ='16'!$F$27 -> 16.580552 | Y19: ='16'!$F$28 -> 8.9353051 | Z19: ='16'!$F$29 -> 6.7972596 | AA19: ='16'!$F$30 -> 8.6718181 | AB19: ='16'!$F$31 | AC19: ='16'!$F$32 | AD19: ='16'!$F$33 -> 8.225632
A20: Frank Phillips | B20: ='17'!$F$5 -> 15.366507 | C20: ='17'!$F$6 -> 9.8666787 | D20: ='17'!$F$7 -> 8.0573843 | E20: ='17'!$F$8 -> 8.4728841 | F20: ='17'!$F$9 | G20: ='17'!$F$10 | H20: ='17'!$F$11 -> 18.791832 | I20: ='17'!$F$12 -> 8.6581371 | J20: ='17'!$F$13 -> 10.036666 | K20: ='17'!$F$14 | L20: ='17'!$F$15 -> 9.2843395 | M20: ='17'!$F$16 -> 7.4003882 | N20: ='17'!$F$17 -> 4.7219607 | O20: ='17'!$F$18 -> 6.4453714 | P20: ='17'!$F$19 | Q20: ='17'!$F$20 -> 10.305719 | R20: ='17'!$F$21 | S20: ='17'!$F$22 -> 8.205769 | T20: ='17'!$F$23 -> 8.5514496 | U20: ='17'!$F$24 | V20: ='17'!$F$25 -> 7.2632472 | W20: ='17'!$F$26 -> 5.5073506 | X20: ='17'!$F$27 -> 10.055101 | Y20: ='17'!$F$28 -> 5.6336066 | Z20: ='17'!$F$29 -> 8.2165908 | AA20: ='17'!$F$30 -> 6.9306177 | AB20: ='17'!$F$31 | AC20: ='17'!$F$32 | AD20: ='17'!$F$33 -> 9.319715
A21: Galveston | B21: ='18'!$F$5 -> 9.6351592 | C21: ='18'!$F$6 -> 20.76308 | D21: ='18'!$F$7 -> 12.720033 | E21: ='18'!$F$8 -> 13.653291 | F21: ='18'!$F$9 | G21: ='18'!$F$10 -> 20.388707 | H21: ='18'!$F$11 -> 11.258889 | I21: ='18'!$F$12 | J21: ='18'!$F$13 -> 12.027525 | K21: ='18'!$F$14 | L21: ='18'!$F$15 | M21: ='18'!$F$16 -> 11.28605 | N21: ='18'!$F$17 -> 12.664099 | O21: ='18'!$F$18 -> 20.788873 | P21: ='18'!$F$19 | Q21: ='18'!$F$20 -> 10.249885 | R21: ='18'!$F$21 | S21: ='18'!$F$22 -> 15.439726 | T21: ='18'!$F$23 -> 10.70909 | U21: ='18'!$F$24 | V21: ='18'!$F$25 | W21: ='18'!$F$26 -> 17.213707 | X21: ='18'!$F$27 -> 23.458568 | Y21: ='18'!$F$28 -> 15.31952 | Z21: ='18'!$F$29 -> 11.230752 | AA21: ='18'!$F$30 -> 13.524825 | AB21: ='18'!$F$31 | AC21: ='18'!$F$32 | AD21: ='18'!$F$33 -> 12.946699
A22: Grayson | B22: ='19'!$F$5 -> 6.4183174 | C22: ='19'!$F$6 -> 10.378645 | D22: ='19'!$F$7 -> 6.7963108 | E22: ='19'!$F$8 -> 6.8963201 | F22: ='19'!$F$9 | G22: ='19'!$F$10 | H22: ='19'!$F$11 -> 7.248884 | I22: ='19'!$F$12 | J22: ='19'!$F$13 -> 4.9088028 | K22: ='19'!$F$14 -> 5.0417793 | L22: ='19'!$F$15 -> 6.8491772 | M22: ='19'!$F$16 -> 5.9072755 | N22: ='19'!$F$17 -> 6.6074189 | O22: ='19'!$F$18 -> 9.9278488 | P22: ='19'!$F$19 | Q22: ='19'!$F$20 -> 6.33573 | R22: ='19'!$F$21 | S22: ='19'!$F$22 -> 7.2379158 | T22: ='19'!$F$23 -> 5.4382688 | U22: ='19'!$F$24 -> 6.9617466 | V22: ='19'!$F$25 -> 2.830995 | W22: ='19'!$F$26 -> 5.0977583 | X22: ='19'!$F$27 -> 19.163741 | Y22: ='19'!$F$28 -> 8.66081 | Z22: ='19'!$F$29 -> 5.6372614 | AA22: ='19'!$F$30 -> 7.2970461 | AB22: ='19'!$F$31 | AC22: ='19'!$F$32 | AD22: ='19'!$F$33 -> 6.7321438
A23: Hill | B23: ='20'!$F$5 -> 10.636468 | C23: ='20'!$F$6 -> 6.152947 | D23: ='20'!$F$7 -> 5.0571983 | E23: ='20'!$F$8 -> 3.6519747 | F23: ='20'!$F$9 | G23: ='20'!$F$10 -> 3.145252 | H23: ='20'!$F$11 -> 6.1628086 | I23: ='20'!$F$12 -> 44.185693 | J23: ='20'!$F$13 -> 5.2040747 | K23: ='20'!$F$14 | L23: ='20'!$F$15 -> 3.980321 | M23: ='20'!$F$16 -> 4.9163667 | N23: ='20'!$F$17 -> 3.5153807 | O23: ='20'!$F$18 -> 13.113798 | P23: ='20'!$F$19 | Q23: ='20'!$F$20 -> 4.853892 | R23: ='20'!$F$21 | S23: ='20'!$F$22 -> 8.8820794 | T23: ='20'!$F$23 -> 5.418964 | U23: ='20'!$F$24 -> 6.481421 | V23: ='20'!$F$25 -> 3.2209313 | W23: ='20'!$F$26 -> 3.9877765 | X23: ='20'!$F$27 -> 10.102399 | Y23: ='20'!$F$28 -> 4.8454473 | Z23: ='20'!$F$29 -> 4.8376801 | AA23: ='20'!$F$30 -> 5.9413096 | AB23: ='20'!$F$31 | AC23: ='20'!$F$32 | AD23: ='20'!$F$33 -> 5.6533171
A24: Houston | B24: ='21'!$F$5 -> 7.5717862 | C24: ='21'!$F$6 -> 10.49381 | D24: ='21'!$F$7 -> 7.7594327 | E24: ='21'!$F$8 -> 7.927107 | F24: ='21'!$F$9 | G24: ='21'!$F$10 -> 7.100753 | H24: ='21'!$F$11 -> 17.885655 | I24: ='21'!$F$12 -> 8.6766306 | J24: ='21'!$F$13 -> 7.5896704 | K24: ='21'!$F$14 -> 7.0589286 | L24: ='21'!$F$15 -> 7.0593779 | M24: ='21'!$F$16 -> 8.8513603 | N24: ='21'!$F$17 -> 8.0463045 | O24: ='21'!$F$18 -> 11.090433 | P24: ='21'!$F$19 | Q24: ='21'!$F$20 -> 11.210675 | R24: ='21'!$F$21 -> 14.386804 | S24: ='21'!$F$22 -> 17.449869 | T24: ='21'!$F$23 -> 7.5386879 | U24: ='21'!$F$24 -> 10.191141 | V24: ='21'!$F$25 -> 11.277381 | W24: ='21'!$F$26 -> 10.044887 | X24: ='21'!$F$27 -> 10.224512 | Y24: ='21'!$F$28 -> 10.88683 | Z24: ='21'!$F$29 -> 7.3306278 | AA24: ='21'!$F$30 -> 9.2193061 | AB24: ='21'!$F$31 | AC24: ='21'!$F$32 | AD24: ='21'!$F$33 -> 8.4703174
A25: Howard | B25: ='22'!$F$5 -> 6.7855839 | C25: ='22'!$F$6 -> 8.8223869 | D25: ='22'!$F$7 -> 6.4189867 | E25: ='22'!$F$8 -> 5.5783164 | F25: ='22'!$F$9 -> 18.833436 | G25: ='22'!$F$10 -> 5.2008484 | H25: ='22'!$F$11 -> 6.6003836 | I25: ='22'!$F$12 -> 5.7487078 | J25: ='22'!$F$13 -> 4.7556051 | K25: ='22'!$F$14 | L25: ='22'!$F$15 -> 4.8615433 | M25: ='22'!$F$16 -> 9.1752903 | N25: ='22'!$F$17 -> 7.5582872 | O25: ='22'!$F$18 -> 14.286455 | P25: ='22'!$F$19 -> 18.641513 | Q25: ='22'!$F$20 -> 10.551427 | R25: ='22'!$F$21 -> 10.25587 | S25: ='22'!$F$22 -> 8.6249717 | T25: ='22'!$F$23 -> 7.0888624 | U25: ='22'!$F$24 -> 11.585187 | V25: ='22'!$F$25 -> 8.5030693 | W25: ='22'!$F$26 -> 4.9901169 | X25: ='22'!$F$27 -> 21.119922 | Y25: ='22'!$F$28 -> 6.5588598 | Z25: ='22'!$F$29 -> 5.9845289 | AA25: ='22'!$F$30 -> 7.0994931 | AB25: ='22'!$F$31 | AC25: ='22'!$F$32 | AD25: ='22'!$F$33 -> 6.9639624
A26: Kilgore | B26: ='23'!$F$5 -> 10.889133 | C26: ='23'!$F$6 -> 7.5294358 | D26: ='23'!$F$7 -> 6.5107157 | E26: ='23'!$F$8 -> 5.8715035 | F26: ='23'!$F$9 | G26: ='23'!$F$10 -> 9.7377863 | H26: ='23'!$F$11 -> 5.6669197 | I26: ='23'!$F$12 -> 31.500801 | J26: ='23'!$F$13 -> 5.4661961 | K26: ='23'!$F$14 -> 9.6287155 | L26: ='23'!$F$15 -> 6.5452359 | M26: ='23'!$F$16 -> 5.6715125 | N26: ='23'!$F$17 -> 10.738252 | O26: ='23'!$F$18 -> 8.2291732 | P26: ='23'!$F$19 | Q26: ='23'!$F$20 -> 6.4821209 | R26: ='23'!$F$21 | S26: ='23'!$F$22 -> 6.0619576 | T26: ='23'!$F$23 -> 5.5736412 | U26: ='23'!$F$24 -> 8.0798115 | V26: ='23'!$F$25 -> 5.2982565 | W26: ='23'!$F$26 -> 2.6091502 | X26: ='23'!$F$27 -> 7.5815142 | Y26: ='23'!$F$28 -> 7.1914131 | Z26: ='23'!$F$29 -> 4.8182223 | AA26: ='23'!$F$30 -> 7.0699401 | AB26: ='23'!$F$31 | AC26: ='23'!$F$32 | AD26: ='23'!$F$33 -> 6.3100891
A27: Laredo | B27: ='24'!$F$5 | C27: ='24'!$F$6 -> 4.8604269 | D27: ='24'!$F$7 -> 9.0317849 | E27: ='24'!$F$8 -> 11.590372 | F27: ='24'!$F$9 | G27: ='24'!$F$10 -> 46.621408 | H27: ='24'!$F$11 -> 12.264061 | I27: ='24'!$F$12 -> 32.941637 | J27: ='24'!$F$13 -> 4.8604269 | K27: ='24'!$F$14 | L27: ='24'!$F$15 -> 4.8604269 | M27: ='24'!$F$16 -> 9.9950895 | N27: ='24'!$F$17 -> 37.064594 | O27: ='24'!$F$18 -> 15.747452 | P27: ='24'!$F$19 | Q27: ='24'!$F$20 -> 10.976809 | R27: ='24'!$F$21 | S27: ='24'!$F$22 -> 13.978552 | T27: ='24'!$F$23 -> 8.5425702 | U27: ='24'!$F$24 -> 17.820155 | V27: ='24'!$F$25 -> 4.8604269 | W27: ='24'!$F$26 -> 16.945557 | X27: ='24'!$F$27 -> 9.7791978 | Y27: ='24'!$F$28 -> 8.5681104 | Z27: ='24'!$F$29 -> 7.3194094 | AA27: ='24'!$F$30 -> 12.008796 | AB27: ='24'!$F$31 | AC27: ='24'!$F$32 | AD27: ='24'!$F$33 -> 10.006486
A28: Lee | B28: ='25'!$F$5 -> 6.5150615 | C28: ='25'!$F$6 -> 13.296722 | D28: ='25'!$F$7 -> 8.5895474 | E28: ='25'!$F$8 -> 8.3021555 | F28: ='25'!$F$9 -> 13.122999 | G28: ='25'!$F$10 -> 10.827348 | H28: ='25'!$F$11 -> 11.809821 | I28: ='25'!$F$12 -> 13.154391 | J28: ='25'!$F$13 -> 7.6909453 | K28: ='25'!$F$14 | L28: ='25'!$F$15 -> 7.5861246 | M28: ='25'!$F$16 -> 11.660686 | N28: ='25'!$F$17 -> 8.5471707 | O28: ='25'!$F$18 -> 11.974481 | P28: ='25'!$F$19 | Q28: ='25'!$F$20 -> 21.588573 | R28: ='25'!$F$21 | S28: ='25'!$F$22 -> 13.159051 | T28: ='25'!$F$23 -> 9.8617939 | U28: ='25'!$F$24 -> 5.3690544 | V28: ='25'!$F$25 -> 5.0794045 | W28: ='25'!$F$26 -> 8.8564963 | X28: ='25'!$F$27 -> 17.06585 | Y28: ='25'!$F$28 -> 6.9136482 | Z28: ='25'!$F$29 -> 8.4198523 | AA28: ='25'!$F$30 -> 10.893075 | AB28: ='25'!$F$31 | AC28: ='25'!$F$32 | AD28: ='25'!$F$33 -> 9.821547
A29: Lonestar | B29: ='26'!$F$5 -> 7.7134447 | C29: ='26'!$F$6 -> 9.9564979 | D29: ='26'!$F$7 -> 8.5145243 | E29: ='26'!$F$8 -> 8.8563079 | F29: ='26'!$F$9 | G29: ='26'!$F$10 -> 6.2883745 | H29: ='26'!$F$11 -> 8.9180766 | I29: ='26'!$F$12 -> 9.5928889 | J29: ='26'!$F$13 -> 7.7949436 | K29: ='26'!$F$14 -> 11.179744 | L29: ='26'!$F$15 -> 10.280072 | M29: ='26'!$F$16 -> 9.2692435 | N29: ='26'!$F$17 -> 8.2476344 | O29: ='26'!$F$18 -> 13.399958 | P29: ='26'!$F$19 -> 24.630547 | Q29: ='26'!$F$20 -> 11.436342 | R29: ='26'!$F$21 -> 13.665918 | S29: ='26'!$F$22 -> 10.4484 | T29: ='26'!$F$23 -> 8.1846372 | U29: ='26'!$F$24 -> 10.765871 | V29: ='26'!$F$25 -> 20.076787 | W29: ='26'!$F$26 -> 9.6555888 | X29: ='26'!$F$27 -> 9.8459951 | Y29: ='26'!$F$28 -> 8.370463 | Z29: ='26'!$F$29 -> 8.0508206 | AA29: ='26'!$F$30 -> 11.265285 | AB29: ='26'!$F$31 | AC29: ='26'!$F$32 | AD29: ='26'!$F$33 -> 9.0428653
A30: Mclennan | B30: ='27'!$F$5 -> 19.57065 | C30: ='27'!$F$6 | D30: ='27'!$F$7 -> 7.1958456 | E30: ='27'!$F$8 -> 8.6889837 | F30: ='27'!$F$9 | G30: ='27'!$F$10 -> 4.4804666 | H30: ='27'!$F$11 -> 14.144782 | I30: ='27'!$F$12 | J30: ='27'!$F$13 -> 11.933381 | K30: ='27'!$F$14 -> 4.13433 | L30: ='27'!$F$15 -> 5.1270182 | M30: ='27'!$F$16 -> 9.259157 | N30: ='27'!$F$17 -> 7.4724001 | O30: ='27'!$F$18 -> 14.077367 | P30: ='27'!$F$19 | Q30: ='27'!$F$20 -> 9.4475851 | R30: ='27'!$F$21 -> 10.660119 | S30: ='27'!$F$22 -> 9.7085887 | T30: ='27'!$F$23 -> 8.0724652 | U30: ='27'!$F$24 | V30: ='27'!$F$25 -> 4.8658262 | W30: ='27'!$F$26 -> 4.1339904 | X30: ='27'!$F$27 -> 11.360024 | Y30: ='27'!$F$28 -> 8.0652051 | Z30: ='27'!$F$29 -> 7.0317389 | AA30: ='27'!$F$30 -> 11.432698 | AB30: ='27'!$F$31 | AC30: ='27'!$F$32 | AD30: ='27'!$F$33 -> 9.1835904
A31: Midland | B31: ='28'!$F$5 -> 11.751039 | C31: ='28'!$F$6 -> 10.447105 | D31: ='28'!$F$7 -> 8.5459247 | E31: ='28'!$F$8 -> 9.5097997 | F31: ='28'!$F$9 -> 56.354169 | G31: ='28'!$F$10 -> 15.708817 | H31: ='28'!$F$11 -> 18.604414 | I31: ='28'!$F$12 -> 12.224132 | J31: ='28'!$F$13 -> 8.2570613 | K31: ='28'!$F$14 -> 12.224315 | L31: ='28'!$F$15 -> 22.970868 | M31: ='28'!$F$16 -> 10.057296 | N31: ='28'!$F$17 -> 6.1555479 | O31: ='28'!$F$18 -> 11.369432 | P31: ='28'!$F$19 | Q31: ='28'!$F$20 -> 10.998096 | R31: ='28'!$F$21 -> 11.136654 | S31: ='28'!$F$22 -> 10.567138 | T31: ='28'!$F$23 -> 9.4004353 | U31: ='28'!$F$24 -> 12.622044 | V31: ='28'!$F$25 -> 20.467673 | W31: ='28'!$F$26 -> 16.787769 | X31: ='28'!$F$27 -> 11.086924 | Y31: ='28'!$F$28 -> 11.624163 | Z31: ='28'!$F$29 -> 8.4185209 | AA31: ='28'!$F$30 -> 10.499586 | AB31: ='28'!$F$31 | AC31: ='28'!$F$32 | AD31: ='28'!$F$33 -> 10.259887
A32: Navarro | B32: ='29'!$F$5 -> 4.4052562 | C32: ='29'!$F$6 -> 3.6355182 | D32: ='29'!$F$7 -> 4.8736893 | E32: ='29'!$F$8 -> 5.0977139 | F32: ='29'!$F$9 | G32: ='29'!$F$10 -> 9.0342118 | H32: ='29'!$F$11 -> 3.9061387 | I32: ='29'!$F$12 -> 3.0909939 | J32: ='29'!$F$13 -> 3.0239477 | K32: ='29'!$F$14 -> 27.880767 | L32: ='29'!$F$15 -> 4.2812889 | M32: ='29'!$F$16 -> 4.8428438 | N32: ='29'!$F$17 -> 3.9426749 | O32: ='29'!$F$18 -> 9.2492198 | P32: ='29'!$F$19 | Q32: ='29'!$F$20 -> 4.7134093 | R32: ='29'!$F$21 | S32: ='29'!$F$22 -> 7.043702 | T32: ='29'!$F$23 -> 4.8481751 | U32: ='29'!$F$24 | V32: ='29'!$F$25 -> 7.6898541 | W32: ='29'!$F$26 -> 2.5907998 | X32: ='29'!$F$27 -> 5.4138395 | Y32: ='29'!$F$28 -> 4.6277458 | Z32: ='29'!$F$29 -> 4.8070763 | AA32: ='29'!$F$30 -> 5.8691715 | AB32: ='29'!$F$31 | AC32: ='29'!$F$32 | AD32: ='29'!$F$33 -> 4.8550314
A33: North Central Texas | B33: ='30'!$F$5 -> 9.4428956 | C33: ='30'!$F$6 -> 15.918096 | D33: ='30'!$F$7 -> 5.3461661 | E33: ='30'!$F$8 -> 4.0754412 | F33: ='30'!$F$9 | G33: ='30'!$F$10 -> 2.7103647 | H33: ='30'!$F$11 -> 45.815292 | I33: ='30'!$F$12 | J33: ='30'!$F$13 -> 6.0421247 | K33: ='30'!$F$14 | L33: ='30'!$F$15 -> 3.5047304 | M33: ='30'!$F$16 -> 5.8303439 | N33: ='30'!$F$17 -> 4.2004657 | O33: ='30'!$F$18 -> 8.2842734 | P33: ='30'!$F$19 | Q33: ='30'!$F$20 -> 7.2686052 | R33: ='30'!$F$21 | S33: ='30'!$F$22 -> 5.8519113 | T33: ='30'!$F$23 -> 4.8874102 | U33: ='30'!$F$24 | V33: ='30'!$F$25 -> 18.157334 | W33: ='30'!$F$26 -> 18.688033 | X33: ='30'!$F$27 -> 6.5441834 | Y33: ='30'!$F$28 -> 6.578324 | Z33: ='30'!$F$29 -> 4.63345 | AA33: ='30'!$F$30 -> 6.5850482 | AB33: ='30'!$F$31 | AC33: ='30'!$F$32 | AD33: ='30'!$F$33 -> 5.8965891
A34: Northeast Texas | B34: ='31'!$F$5 -> 20.385866 | C34: ='31'!$F$6 -> 6.2137341 | D34: ='31'!$F$7 -> 7.5843059 | E34: ='31'!$F$8 -> 6.8301798 | F34: ='31'!$F$9 | G34: ='31'!$F$10 -> 7.8591085 | H34: ='31'!$F$11 -> 16.737141 | I34: ='31'!$F$12 -> 3.9162287 | J34: ='31'!$F$13 -> 6.1142147 | K34: ='31'!$F$14 | L34: ='31'!$F$15 -> 3.2432249 | M34: ='31'!$F$16 -> 6.0978209 | N34: ='31'!$F$17 -> 12.892973 | O34: ='31'!$F$18 -> 12.441144 | P34: ='31'!$F$19 -> 16.178456 | Q34: ='31'!$F$20 -> 9.1426199 | R34: ='31'!$F$21 | S34: ='31'!$F$22 -> 10.093203 | T34: ='31'!$F$23 -> 7.4010594 | U34: ='31'!$F$24 -> 18.799433 | V34: ='31'!$F$25 -> 28.282114 | W34: ='31'!$F$26 -> 3.2432249 | X34: ='31'!$F$27 -> 6.5276187 | Y34: ='31'!$F$28 -> 8.9216551 | Z34: ='31'!$F$29 -> 6.2182426 | AA34: ='31'!$F$30 -> 10.51268 | AB34: ='31'!$F$31 | AC34: ='31'!$F$32 | AD34: ='31'!$F$33 -> 7.9638673
A35: Odessa | B35: ='32'!$F$5 -> 12.498638 | C35: ='32'!$F$6 -> 7.5442876 | D35: ='32'!$F$7 -> 8.7714862 | E35: ='32'!$F$8 -> 10.283215 | F35: ='32'!$F$9 | G35: ='32'!$F$10 -> 5.7581792 | H35: ='32'!$F$11 -> 11.20881 | I35: ='32'!$F$12 -> 5.4369894 | J35: ='32'!$F$13 -> 9.5969757 | K35: ='32'!$F$14 | L35: ='32'!$F$15 -> 8.8056515 | M35: ='32'!$F$16 -> 9.550645 | N35: ='32'!$F$17 -> 10.228937 | O35: ='32'!$F$18 -> 11.593647 | P35: ='32'!$F$19 | Q35: ='32'!$F$20 -> 12.163211 | R35: ='32'!$F$21 | S35: ='32'!$F$22 -> 10.556769 | T35: ='32'!$F$23 -> 9.3234961 | U35: ='32'!$F$24 -> 10.14441 | V35: ='32'!$F$25 -> 15.067998 | W35: ='32'!$F$26 -> 9.9823519 | X35: ='32'!$F$27 -> 10.759446 | Y35: ='32'!$F$28 -> 11.043071 | Z35: ='32'!$F$29 -> 8.7108221 | AA35: ='32'!$F$30 -> 11.287246 | AB35: ='32'!$F$31 | AC35: ='32'!$F$32 | AD35: ='32'!$F$33 -> 9.876891
A36: Panola | B36: ='33'!$F$5 -> 6.8482311 | C36: ='33'!$F$6 -> 10.667412 | D36: ='33'!$F$7 -> 8.6049741 | E36: ='33'!$F$8 -> 8.5226668 | F36: ='33'!$F$9 | G36: ='33'!$F$10 -> 14.11534 | H36: ='33'!$F$11 -> 16.257305 | I36: ='33'!$F$12 -> 30.563153 | J36: ='33'!$F$13 -> 7.6300123 | K36: ='33'!$F$14 | L36: ='33'!$F$15 -> 11.466413 | M36: ='33'!$F$16 -> 8.4808513 | N36: ='33'!$F$17 -> 11.80611 | O36: ='33'!$F$18 -> 11.106546 | P36: ='33'!$F$19 | Q36: ='33'!$F$20 -> 9.8587208 | R36: ='33'!$F$21 | S36: ='33'!$F$22 -> 8.438679 | T36: ='33'!$F$23 -> 11.055967 | U36: ='33'!$F$24 | V36: ='33'!$F$25 -> 13.123721 | W36: ='33'!$F$26 -> 13.125797 | X36: ='33'!$F$27 -> 10.016527 | Y36: ='33'!$F$28 -> 8.1624002 | Z36: ='33'!$F$29 -> 7.5322617 | AA36: ='33'!$F$30 -> 10.265722 | AB36: ='33'!$F$31 | AC36: ='33'!$F$32 | AD36: ='33'!$F$33 -> 9.5473743
A37: Paris | B37: ='34'!$F$5 -> 11.80778 | C37: ='34'!$F$6 -> 6.4165052 | D37: ='34'!$F$7 -> 4.1966374 | E37: ='34'!$F$8 -> 4.925964 | F37: ='34'!$F$9 | G37: ='34'!$F$10 -> 6.5579111 | H37: ='34'!$F$11 -> 5.2139374 | I37: ='34'!$F$12 -> 4.9842829 | J37: ='34'!$F$13 -> 4.2062521 | K37: ='34'!$F$14 | L37: ='34'!$F$15 -> 4.7571779 | M37: ='34'!$F$16 -> 4.8829156 | N37: ='34'!$F$17 -> 4.9155923 | O37: ='34'!$F$18 -> 10.322751 | P37: ='34'!$F$19 | Q37: ='34'!$F$20 -> 7.1936335 | R37: ='34'!$F$21 | S37: ='34'!$F$22 -> 8.1668483 | T37: ='34'!$F$23 -> 4.0650701 | U37: ='34'!$F$24 | V37: ='34'!$F$25 -> 6.9154212 | W37: ='34'!$F$26 -> 6.7198657 | X37: ='34'!$F$27 -> 5.8543478 | Y37: ='34'!$F$28 -> 4.7662597 | Z37: ='34'!$F$29 -> 4.7796827 | AA37: ='34'!$F$30 -> 6.2983893 | AB37: ='34'!$F$31 | AC37: ='34'!$F$32 | AD37: ='34'!$F$33 -> 5.2325053
A38: Ranger | B38: ='35'!$F$5 -> 9.5295718 | C38: ='35'!$F$6 -> 5.5988156 | D38: ='35'!$F$7 -> 5.4565997 | E38: ='35'!$F$8 -> 8.5030207 | F38: ='35'!$F$9 | G38: ='35'!$F$10 | H38: ='35'!$F$11 -> 5.7573267 | I38: ='35'!$F$12 | J38: ='35'!$F$13 -> 5.6104362 | K38: ='35'!$F$14 | L38: ='35'!$F$15 | M38: ='35'!$F$16 -> 6.3586302 | N38: ='35'!$F$17 | O38: ='35'!$F$18 | P38: ='35'!$F$19 | Q38: ='35'!$F$20 -> 6.2541673 | R38: ='35'!$F$21 | S38: ='35'!$F$22 -> 5.6678692 | T38: ='35'!$F$23 -> 6.6380516 | U38: ='35'!$F$24 | V38: ='35'!$F$25 | W38: ='35'!$F$26 -> 15.279839 | X38: ='35'!$F$27 -> 16.339343 | Y38: ='35'!$F$28 | Z38: ='35'!$F$29 -> 5.1335304 | AA38: ='35'!$F$30 -> 8.622799 | AB38: ='35'!$F$31 | AC38: ='35'!$F$32 | AD38: ='35'!$F$33 -> 6.692547
A39: San Jacinto | B39: ='36'!$F$5 -> 6.2234127 | C39: ='36'!$F$6 -> 7.1857919 | D39: ='36'!$F$7 -> 6.9344729 | E39: ='36'!$F$8 -> 7.1827576 | F39: ='36'!$F$9 -> 27.828345 | G39: ='36'!$F$10 -> 6.6998457 | H39: ='36'!$F$11 -> 10.988779 | I39: ='36'!$F$12 -> 13.586631 | J39: ='36'!$F$13 -> 7.9443031 | K39: ='36'!$F$14 -> 10.113149 | L39: ='36'!$F$15 -> 10.677431 | M39: ='36'!$F$16 -> 7.1640733 | N39: ='36'!$F$17 -> 7.7477582 | O39: ='36'!$F$18 -> 10.773094 | P39: ='36'!$F$19 | Q39: ='36'!$F$20 -> 10.692494 | R39: ='36'!$F$21 -> 10.420676 | S39: ='36'!$F$22 -> 11.306878 | T39: ='36'!$F$23 -> 7.4212012 | U39: ='36'!$F$24 -> 10.181733 | V39: ='36'!$F$25 -> 13.534282 | W39: ='36'!$F$26 -> 8.6333935 | X39: ='36'!$F$27 -> 8.3777158 | Y39: ='36'!$F$28 -> 10.210569 | Z39: ='36'!$F$29 -> 7.1759507 | AA39: ='36'!$F$30 -> 9.5083222 | AB39: ='36'!$F$31 | AC39: ='36'!$F$32 | AD39: ='36'!$F$33 -> 8.2112624
A40: South Plains | B40: ='37'!$F$5 -> 14.089905 | C40: ='37'!$F$6 -> 6.3468567 | D40: ='37'!$F$7 -> 5.7317683 | E40: ='37'!$F$8 -> 6.3595983 | F40: ='37'!$F$9 -> 4.9855256 | G40: ='37'!$F$10 -> 5.4908554 | H40: ='37'!$F$11 -> 6.8326313 | I40: ='37'!$F$12 -> 10.177973 | J40: ='37'!$F$13 -> 5.7200797 | K40: ='37'!$F$14 -> 45.788236 | L40: ='37'!$F$15 -> 7.3147536 | M40: ='37'!$F$16 -> 6.5008245 | N40: ='37'!$F$17 -> 5.6155453 | O40: ='37'!$F$18 -> 6.5513722 | P40: ='37'!$F$19 | Q40: ='37'!$F$20 -> 8.9761028 | R40: ='37'!$F$21 -> 8.495444 | S40: ='37'!$F$22 -> 6.2515868 | T40: ='37'!$F$23 -> 5.3358092 | U40: ='37'!$F$24 -> 6.47327 | V40: ='37'!$F$25 -> 6.0163193 | W40: ='37'!$F$26 -> 19.442521 | X40: ='37'!$F$27 -> 11.043951 | Y40: ='37'!$F$28 -> 3.8530066 | Z40: ='37'!$F$29 -> 5.4109881 | AA40: ='37'!$F$30 -> 10.489288 | AB40: ='37'!$F$31 | AC40: ='37'!$F$32 | AD40: ='37'!$F$33 -> 6.4250799
A41: South Texas | B41: ='38'!$F$5 -> 7.0880896 | C41: ='38'!$F$6 -> 15.71745 | D41: ='38'!$F$7 -> 7.0880919 | E41: ='38'!$F$8 -> 6.2473879 | F41: ='38'!$F$9 | G41: ='38'!$F$10 -> 10.255234 | H41: ='38'!$F$11 -> 7.2816248 | I41: ='38'!$F$12 -> 18.912901 | J41: ='38'!$F$13 -> 9.3563591 | K41: ='38'!$F$14 -> 6.5156227 | L41: ='38'!$F$15 -> 6.7039194 | M41: ='38'!$F$16 -> 9.4295542 | N41: ='38'!$F$17 -> 7.0655019 | O41: ='38'!$F$18 -> 11.050585 | P41: ='38'!$F$19 | Q41: ='38'!$F$20 -> 13.452525 | R41: ='38'!$F$21 -> 12.935407 | S41: ='38'!$F$22 -> 11.562404 | T41: ='38'!$F$23 -> 7.0928549 | U41: ='38'!$F$24 -> 10.215521 | V41: ='38'!$F$25 -> 7.1569102 | W41: ='38'!$F$26 -> 9.5535522 | X41: ='38'!$F$27 -> 9.94766 | Y41: ='38'!$F$28 -> 9.0378882 | Z41: ='38'!$F$29 -> 7.6237884 | AA41: ='38'!$F$30 -> 7.6329139 | AB41: ='38'!$F$31 | AC41: ='38'!$F$32 | AD41: ='38'!$F$33 -> 8.377207
A42: Southwest Texas | B42: ='39'!$F$5 -> 7.5368614 | C42: ='39'!$F$6 -> 9.471967 | D42: ='39'!$F$7 -> 6.8076166 | E42: ='39'!$F$8 -> 8.7949965 | F42: ='39'!$F$9 | G42: ='39'!$F$10 -> 9.633277 | H42: ='39'!$F$11 -> 5.3022917 | I42: ='39'!$F$12 -> 6.3385547 | J42: ='39'!$F$13 -> 6.726714 | K42: ='39'!$F$14 -> 9.2092519 | L42: ='39'!$F$15 -> 11.015075 | M42: ='39'!$F$16 -> 6.8415712 | N42: ='39'!$F$17 -> 4.1328368 | O42: ='39'!$F$18 -> 11.090188 | P42: ='39'!$F$19 | Q42: ='39'!$F$20 -> 7.3976563 | R42: ='39'!$F$21 | S42: ='39'!$F$22 -> 9.5543535 | T42: ='39'!$F$23 -> 7.6088904 | U42: ='39'!$F$24 -> 9.689521 | V42: ='39'!$F$25 -> 17.500323 | W42: ='39'!$F$26 -> 9.3964137 | X42: ='39'!$F$27 -> 8.3075131 | Y42: ='39'!$F$28 -> 6.2340537 | Z42: ='39'!$F$29 -> 6.304809 | AA42: ='39'!$F$30 -> 6.2880694 | AB42: ='39'!$F$31 | AC42: ='39'!$F$32 | AD42: ='39'!$F$33 -> 7.231732
A43: Tarrant | B43: ='40'!$F$5 -> 8.4730089 | C43: ='40'!$F$6 -> 15.334981 | D43: ='40'!$F$7 -> 7.3414033 | E43: ='40'!$F$8 -> 7.1597393 | F43: ='40'!$F$9 | G43: ='40'!$F$10 -> 9.4477071 | H43: ='40'!$F$11 -> 9.1349658 | I43: ='40'!$F$12 -> 9.7110507 | J43: ='40'!$F$13 -> 8.1130231 | K43: ='40'!$F$14 -> 10.635016 | L43: ='40'!$F$15 -> 10.551273 | M43: ='40'!$F$16 -> 7.473798 | N43: ='40'!$F$17 -> 6.9707732 | O43: ='40'!$F$18 -> 13.03877 | P43: ='40'!$F$19 -> 17.97295 | Q43: ='40'!$F$20 -> 12.411795 | R43: ='40'!$F$21 -> 14.96334 | S43: ='40'!$F$22 | T43: ='40'!$F$23 -> 7.531703 | U43: ='40'!$F$24 -> 10.191469 | V43: ='40'!$F$25 -> 11.160881 | W43: ='40'!$F$26 -> 4.3854935 | X43: ='40'!$F$27 -> 7.9565558 | Y43: ='40'!$F$28 -> 13.807047 | Z43: ='40'!$F$29 -> 6.5877421 | AA43: ='40'!$F$30 -> 8.8492737 | AB43: ='40'!$F$31 | AC43: ='40'!$F$32 | AD43: ='40'!$F$33 -> 8.0051647
A44: Temple | B44: ='41'!$F$5 -> 7.6572384 | C44: ='41'!$F$6 -> 7.8684632 | D44: ='41'!$F$7 -> 7.3585778 | E44: ='41'!$F$8 -> 6.0844085 | F44: ='41'!$F$9 | G44: ='41'!$F$10 -> 9.9562398 | H44: ='41'!$F$11 -> 7.757321 | I44: ='41'!$F$12 -> 6.9139566 | J44: ='41'!$F$13 -> 7.3000324 | K44: ='41'!$F$14 | L44: ='41'!$F$15 -> 6.309572 | M44: ='41'!$F$16 -> 6.7707941 | N44: ='41'!$F$17 -> 8.1791123 | O44: ='41'!$F$18 -> 9.6146589 | P44: ='41'!$F$19 -> 23.732601 | Q44: ='41'!$F$20 -> 9.0753562 | R44: ='41'!$F$21 -> 10.261821 | S44: ='41'!$F$22 -> 8.9447005 | T44: ='41'!$F$23 -> 7.1924022 | U44: ='41'!$F$24 | V44: ='41'!$F$25 | W44: ='41'!$F$26 -> 7.8820045 | X44: ='41'!$F$27 -> 6.8701226 | Y44: ='41'!$F$28 -> 8.2279889 | Z44: ='41'!$F$29 -> 6.3743189 | AA44: ='41'!$F$30 -> 9.650991 | AB44: ='41'!$F$31 | AC44: ='41'!$F$32 | AD44: ='41'!$F$33 -> 7.649558
A45: Texarkana | B45: ='42'!$F$5 | C45: ='42'!$F$6 | D45: ='42'!$F$7 | E45: ='42'!$F$8 | F45: ='42'!$F$9 | G45: ='42'!$F$10 | H45: ='42'!$F$11 | I45: ='42'!$F$12 | J45: ='42'!$F$13 | K45: ='42'!$F$14 | L45: ='42'!$F$15 | M45: ='42'!$F$16 | N45: ='42'!$F$17 | O45: ='42'!$F$18 | P45: ='42'!$F$19 | Q45: ='42'!$F$20 | R45: ='42'!$F$21 | S45: ='42'!$F$22 | T45: ='42'!$F$23 | U45: ='42'!$F$24 | V45: ='42'!$F$25 | W45: ='42'!$F$26 | X45: ='42'!$F$27 | Y45: ='42'!$F$28 | Z45: ='42'!$F$29 | AA45: ='42'!$F$30 | AB45: ='42'!$F$31 | AC45: ='42'!$F$32 | AD45: ='42'!$F$33
A46: Texas Southmost | B46: ='43'!$F$5 | C46: ='43'!$F$6 | D46: ='43'!$F$7 | E46: ='43'!$F$8 | F46: ='43'!$F$9 | G46: ='43'!$F$10 | H46: ='43'!$F$11 | I46: ='43'!$F$12 | J46: ='43'!$F$13 | K46: ='43'!$F$14 | L46: ='43'!$F$15 | M46: ='43'!$F$16 | N46: ='43'!$F$17 | O46: ='43'!$F$18 | P46: ='43'!$F$19 | Q46: ='43'!$F$20 | R46: ='43'!$F$21 | S46: ='43'!$F$22 | T46: ='43'!$F$23 | U46: ='43'!$F$24 | V46: ='43'!$F$25 | W46: ='43'!$F$26 | X46: ='43'!$F$27 | Y46: ='43'!$F$28 | Z46: ='43'!$F$29 | AA46: ='43'!$F$30 | AB46: ='43'!$F$31 | AC46: ='43'!$F$32 | AD46: ='43'!$F$33
A47: Trinity Valley | B47: ='44'!$F$5 -> 6.4555868 | C47: ='44'!$F$6 -> 4.8985608 | D47: ='44'!$F$7 -> 5.7942353 | E47: ='44'!$F$8 -> 8.0861636 | F47: ='44'!$F$9 | G47: ='44'!$F$10 -> 4.4480814 | H47: ='44'!$F$11 -> 4.4879839 | I47: ='44'!$F$12 -> 6.124859 | J47: ='44'!$F$13 -> 5.4787709 | K47: ='44'!$F$14 | L47: ='44'!$F$15 -> 5.3435188 | M47: ='44'!$F$16 -> 6.0520136 | N47: ='44'!$F$17 -> 5.2628771 | O47: ='44'!$F$18 -> 7.7599848 | P47: ='44'!$F$19 | Q47: ='44'!$F$20 -> 5.4235215 | R47: ='44'!$F$21 | S47: ='44'!$F$22 -> 6.2683784 | T47: ='44'!$F$23 -> 5.9588893 | U47: ='44'!$F$24 -> 6.323481 | V47: ='44'!$F$25 | W47: ='44'!$F$26 -> 4.9782571 | X47: ='44'!$F$27 -> 8.5859819 | Y47: ='44'!$F$28 -> 5.6845863 | Z47: ='44'!$F$29 -> 5.4912117 | AA47: ='44'!$F$30 -> 7.3374111 | AB47: ='44'!$F$31 | AC47: ='44'!$F$32 | AD47: ='44'!$F$33 -> 5.9830863
A48: Tyler | B48: ='45'!$F$5 -> 5.3221997 | C48: ='45'!$F$6 -> 9.0328871 | D48: ='45'!$F$7 -> 6.6843956 | E48: ='45'!$F$8 -> 5.26012 | F48: ='45'!$F$9 | G48: ='45'!$F$10 -> 17.167449 | H48: ='45'!$F$11 -> 21.347091 | I48: ='45'!$F$12 -> 3.7815018 | J48: ='45'!$F$13 -> 7.2284743 | K48: ='45'!$F$14 -> 3.7814816 | L48: ='45'!$F$15 -> 7.0717304 | M48: ='45'!$F$16 -> 6.8110168 | N48: ='45'!$F$17 -> 5.8483653 | O48: ='45'!$F$18 -> 11.016808 | P48: ='45'!$F$19 -> 16.591659 | Q48: ='45'!$F$20 -> 8.1098863 | R48: ='45'!$F$21 -> 10.585331 | S48: ='45'!$F$22 -> 7.2923086 | T48: ='45'!$F$23 -> 6.7396111 | U48: ='45'!$F$24 -> 11.641297 | V48: ='45'!$F$25 -> 3.7815362 | W48: ='45'!$F$26 -> 3.7815345 | X48: ='45'!$F$27 -> 12.383194 | Y48: ='45'!$F$28 -> 6.7509547 | Z48: ='45'!$F$29 -> 6.3255317 | AA48: ='45'!$F$30 -> 7.5670766 | AB48: ='45'!$F$31 | AC48: ='45'!$F$32 | AD48: ='45'!$F$33 -> 7.379653
A49: Vernon | B49: ='46'!$F$5 -> 12.5819 | C49: ='46'!$F$6 -> 6.2948763 | D49: ='46'!$F$7 -> 6.3024912 | E49: ='46'!$F$8 -> 6.5220013 | F49: ='46'!$F$9 | G49: ='46'!$F$10 | H49: ='46'!$F$11 -> 5.8116676 | I49: ='46'!$F$12 -> 4.8696891 | J49: ='46'!$F$13 -> 6.7780412 | K49: ='46'!$F$14 | L49: ='46'!$F$15 -> 4.8696829 | M49: ='46'!$F$16 -> 6.6243817 | N49: ='46'!$F$17 -> 6.1538322 | O49: ='46'!$F$18 -> 7.2155615 | P49: ='46'!$F$19 | Q49: ='46'!$F$20 -> 5.931895 | R49: ='46'!$F$21 | S49: ='46'!$F$22 -> 6.5868174 | T49: ='46'!$F$23 -> 6.8589878 | U49: ='46'!$F$24 -> 7.945048 | V49: ='46'!$F$25 | W49: ='46'!$F$26 -> 13.565326 | X49: ='46'!$F$27 -> 6.560778 | Y49: ='46'!$F$28 -> 5.4338493 | Z49: ='46'!$F$29 -> 5.7716692 | AA49: ='46'!$F$30 -> 6.9742335 | AB49: ='46'!$F$31 | AC49: ='46'!$F$32 | AD49: ='46'!$F$33 -> 6.3755891
A50: Victoria | B50: ='47'!$F$5 -> 21.203448 | C50: ='47'!$F$6 -> 7.965014 | D50: ='47'!$F$7 -> 8.987404 | E50: ='47'!$F$8 -> 7.685248 | F50: ='47'!$F$9 | G50: ='47'!$F$10 -> 8.5704578 | H50: ='47'!$F$11 -> 10.445328 | I50: ='47'!$F$12 -> 30.915149 | J50: ='47'!$F$13 -> 6.0017028 | K50: ='47'!$F$14 | L50: ='47'!$F$15 -> 11.980259 | M50: ='47'!$F$16 -> 8.3018008 | N50: ='47'!$F$17 -> 10.955131 | O50: ='47'!$F$18 -> 14.431788 | P50: ='47'!$F$19 | Q50: ='47'!$F$20 -> 7.7001688 | R50: ='47'!$F$21 -> 11.646694 | S50: ='47'!$F$22 -> 9.2105501 | T50: ='47'!$F$23 -> 9.543022 | U50: ='47'!$F$24 | V50: ='47'!$F$25 -> 12.346562 | W50: ='47'!$F$26 -> 5.2397167 | X50: ='47'!$F$27 -> 8.2221606 | Y50: ='47'!$F$28 -> 12.426717 | Z50: ='47'!$F$29 -> 7.7480836 | AA50: ='47'!$F$30 -> 11.982096 | AB50: ='47'!$F$31 | AC50: ='47'!$F$32 | AD50: ='47'!$F$33 -> 9.4982836
A51: Weatherford | B51: ='48'!$F$5 -> 10.019135 | C51: ='48'!$F$6 -> 13.117535 | D51: ='48'!$F$7 -> 6.9197624 | E51: ='48'!$F$8 -> 8.0711206 | F51: ='48'!$F$9 | G51: ='48'!$F$10 -> 14.268674 | H51: ='48'!$F$11 -> 7.4628303 | I51: ='48'!$F$12 -> 13.703359 | J51: ='48'!$F$13 -> 7.7473359 | K51: ='48'!$F$14 | L51: ='48'!$F$15 -> 13.493615 | M51: ='48'!$F$16 -> 8.1163482 | N51: ='48'!$F$17 -> 8.0578041 | O51: ='48'!$F$18 -> 10.886618 | P51: ='48'!$F$19 | Q51: ='48'!$F$20 -> 10.379993 | R51: ='48'!$F$21 -> 9.5532372 | S51: ='48'!$F$22 -> 7.9402293 | T51: ='48'!$F$23 -> 8.4196398 | U51: ='48'!$F$24 -> 13.144208 | V51: ='48'!$F$25 -> 16.045205 | W51: ='48'!$F$26 -> 7.4152513 | X51: ='48'!$F$27 -> 7.0717416 | Y51: ='48'!$F$28 -> 8.3402982 | Z51: ='48'!$F$29 -> 6.6146535 | AA51: ='48'!$F$30 -> 10.297558 | AB51: ='48'!$F$31 | AC51: ='48'!$F$32 | AD51: ='48'!$F$33 -> 8.2168121
A52: Western Texas | B52: ='49'!$F$5 -> 6.6856282 | C52: ='49'!$F$6 -> 6.95253 | D52: ='49'!$F$7 -> 5.2986889 | E52: ='49'!$F$8 -> 3.5264677 | F52: ='49'!$F$9 | G52: ='49'!$F$10 -> 39.308572 | H52: ='49'!$F$11 -> 4.209268 | I52: ='49'!$F$12 -> 3.0756697 | J52: ='49'!$F$13 -> 6.3063442 | K52: ='49'!$F$14 | L52: ='49'!$F$15 -> 12.367879 | M52: ='49'!$F$16 -> 5.9159136 | N52: ='49'!$F$17 -> 5.2853528 | O52: ='49'!$F$18 | P52: ='49'!$F$19 | Q52: ='49'!$F$20 -> 4.5895384 | R52: ='49'!$F$21 | S52: ='49'!$F$22 -> 7.1716172 | T52: ='49'!$F$23 -> 4.8287207 | U52: ='49'!$F$24 | V52: ='49'!$F$25 -> 5.7944197 | W52: ='49'!$F$26 -> 8.2997797 | X52: ='49'!$F$27 -> 7.4850952 | Y52: ='49'!$F$28 -> 4.0757517 | Z52: ='49'!$F$29 -> 6.2890966 | AA52: ='49'!$F$30 -> 7.7946571 | AB52: ='49'!$F$31 | AC52: ='49'!$F$32 | AD52: ='49'!$F$33 -> 5.4534663
A53: Wharton | B53: ='50'!$F$5 -> 12.870423 | C53: ='50'!$F$6 -> 10.74286 | D53: ='50'!$F$7 -> 8.4388342 | E53: ='50'!$F$8 -> 7.0416929 | F53: ='50'!$F$9 | G53: ='50'!$F$10 -> 4.3676584 | H53: ='50'!$F$11 -> 11.784396 | I53: ='50'!$F$12 -> 51.836441 | J53: ='50'!$F$13 -> 9.4543595 | K53: ='50'!$F$14 | L53: ='50'!$F$15 -> 7.5874023 | M53: ='50'!$F$16 -> 8.0963189 | N53: ='50'!$F$17 -> 9.5786333 | O53: ='50'!$F$18 -> 15.148963 | P53: ='50'!$F$19 -> 18.586533 | Q53: ='50'!$F$20 -> 9.9133979 | R53: ='50'!$F$21 | S53: ='50'!$F$22 -> 10.332236 | T53: ='50'!$F$23 -> 7.9781862 | U53: ='50'!$F$24 -> 13.841078 | V53: ='50'!$F$25 | W53: ='50'!$F$26 -> 4.3677736 | X53: ='50'!$F$27 -> 9.7093197 | Y53: ='50'!$F$28 -> 13.203833 | Z53: ='50'!$F$29 -> 7.2639791 | AA53: ='50'!$F$30 -> 9.3036541 | AB53: ='50'!$F$31 | AC53: ='50'!$F$32 | AD53: ='50'!$F$33 -> 8.8624585
A54: TSTC-Harlingen | B54: ='51'!$F$5 -> 10.737175 | C54: ='51'!$F$6 -> 11.620771 | D54: ='51'!$F$7 -> 6.2748316 | E54: ='51'!$F$8 -> 5.2265727 | F54: ='51'!$F$9 | G54: ='51'!$F$10 -> 15.563099 | H54: ='51'!$F$11 -> 11.156228 | I54: ='51'!$F$12 -> 21.304819 | J54: ='51'!$F$13 -> 7.3052463 | K54: ='51'!$F$14 -> 3.6344744 | L54: ='51'!$F$15 -> 6.0370752 | M54: ='51'!$F$16 -> 6.7604417 | N54: ='51'!$F$17 -> 6.2067719 | O54: ='51'!$F$18 -> 7.1124383 | P54: ='51'!$F$19 -> 13.167155 | Q54: ='51'!$F$20 -> 10.14244 | R54: ='51'!$F$21 | S54: ='51'!$F$22 -> 13.173775 | T54: ='51'!$F$23 -> 7.1651681 | U54: ='51'!$F$24 -> 7.4264711 | V54: ='51'!$F$25 -> 7.9265788 | W54: ='51'!$F$26 -> 5.3434758 | X54: ='51'!$F$27 -> 3.6375664 | Y54: ='51'!$F$28 -> 4.4211889 | Z54: ='51'!$F$29 -> 5.4903907 | AA54: ='51'!$F$30 -> 4.5062713 | AB54: ='51'!$F$31 | AC54: ='51'!$F$32 | AD54: ='51'!$F$33 -> 7.2571308
A55: TSTC-West Texas | B55: ='52'!$F$5 -> 11.627136 | C55: ='52'!$F$6 -> 11.627447 | D55: ='52'!$F$7 -> 9.9964409 | E55: ='52'!$F$8 -> 9.0524519 | F55: ='52'!$F$9 | G55: ='52'!$F$10 -> 11.627449 | H55: ='52'!$F$11 -> 9.0524483 | I55: ='52'!$F$12 -> 11.627443 | J55: ='52'!$F$13 -> 11.627414 | K55: ='52'!$F$14 | L55: ='52'!$F$15 -> 13.625095 | M55: ='52'!$F$16 -> 9.9968004 | N55: ='52'!$F$17 -> 9.9968028 | O55: ='52'!$F$18 -> 11.832396 | P55: ='52'!$F$19 | Q55: ='52'!$F$20 -> 11.832396 | R55: ='52'!$F$21 | S55: ='52'!$F$22 -> 11.832389 | T55: ='52'!$F$23 -> 9.9967841 | U55: ='52'!$F$24 -> 14.311314 | V55: ='52'!$F$25 -> 14.31128 | W55: ='52'!$F$26 -> 11.629442 | X55: ='52'!$F$27 | Y55: ='52'!$F$28 -> 9.052401 | Z55: ='52'!$F$29 -> 9.9968095 | AA55: ='52'!$F$30 -> 9.0524921 | AB55: ='52'!$F$31 | AC55: ='52'!$F$32 | AD55: ='52'!$F$33 -> 10.729385
A56: TSTC-Marshall | B56: ='53'!$F$5 -> 8.8701101 | C56: ='53'!$F$6 -> 14.041925 | D56: ='53'!$F$7 -> 8.1624322 | E56: ='53'!$F$8 -> 8.4251532 | F56: ='53'!$F$9 | G56: ='53'!$F$10 -> 8.8696663 | H56: ='53'!$F$11 -> 8.4251531 | I56: ='53'!$F$12 -> 8.8698377 | J56: ='53'!$F$13 | K56: ='53'!$F$14 | L56: ='53'!$F$15 -> 10.110439 | M56: ='53'!$F$16 -> 9.5433821 | N56: ='53'!$F$17 | O56: ='53'!$F$18 | P56: ='53'!$F$19 | Q56: ='53'!$F$20 -> 8.8706584 | R56: ='53'!$F$21 | S56: ='53'!$F$22 | T56: ='53'!$F$23 -> 9.3869803 | U56: ='53'!$F$24 -> 9.5332489 | V56: ='53'!$F$25 -> 9.5333116 | W56: ='53'!$F$26 -> 8.869678 | X56: ='53'!$F$27 | Y56: ='53'!$F$28 | Z56: ='53'!$F$29 -> 6.4146586 | AA56: ='53'!$F$30 -> 8.4250565 | AB56: ='53'!$F$31 | AC56: ='53'!$F$32 | AD56: ='53'!$F$33 -> 9.5140429
A57: TSTC-Waco | B57: ='54'!$F$5 -> 9.0116756 | C57: ='54'!$F$6 -> 7.3650278 | D57: ='54'!$F$7 -> 9.0825815 | E57: ='54'!$F$8 -> 6.4036684 | F57: ='54'!$F$9 -> 35.139145 | G57: ='54'!$F$10 -> 6.5553097 | H57: ='54'!$F$11 -> 7.2113493 | I57: ='54'!$F$12 -> 8.067747 | J57: ='54'!$F$13 -> 9.2153263 | K57: ='54'!$F$14 -> 7.5018386 | L57: ='54'!$F$15 -> 8.0012711 | M57: ='54'!$F$16 -> 6.3116566 | N57: ='54'!$F$17 -> 6.3774112 | O57: ='54'!$F$18 -> 6.7317085 | P57: ='54'!$F$19 | Q57: ='54'!$F$20 -> 6.8719983 | R57: ='54'!$F$21 | S57: ='54'!$F$22 | T57: ='54'!$F$23 -> 7.066531 | U57: ='54'!$F$24 -> 7.8966788 | V57: ='54'!$F$25 -> 9.7689252 | W57: ='54'!$F$26 -> 8.762338 | X57: ='54'!$F$27 | Y57: ='54'!$F$28 -> 6.7790258 | Z57: ='54'!$F$29 -> 6.2872384 | AA57: ='54'!$F$30 -> 7.2340083 | AB57: ='54'!$F$31 | AC57: ='54'!$F$32 | AD57: ='54'!$F$33 -> 7.8840062
A58: Lamar-IOT | B58: ='55'!$F$5 | C58: ='55'!$F$6 -> 12.896253 | D58: ='55'!$F$7 -> 12.896259 | E58: ='55'!$F$8 -> 12.896268 | F58: ='55'!$F$9 | G58: ='55'!$F$10 | H58: ='55'!$F$11 -> 12.896247 | I58: ='55'!$F$12 -> 12.896283 | J58: ='55'!$F$13 -> 12.896253 | K58: ='55'!$F$14 | L58: ='55'!$F$15 -> 12.896261 | M58: ='55'!$F$16 -> 12.907142 | N58: ='55'!$F$17 -> 5.8403086 | O58: ='55'!$F$18 | P58: ='55'!$F$19 -> 12.896231 | Q58: ='55'!$F$20 -> 12.896261 | R58: ='55'!$F$21 -> 12.896241 | S58: ='55'!$F$22 | T58: ='55'!$F$23 -> 12.896243 | U58: ='55'!$F$24 -> 12.895864 | V58: ='55'!$F$25 -> 12.896275 | W58: ='55'!$F$26 -> 12.896274 | X58: ='55'!$F$27 | Y58: ='55'!$F$28 -> 12.896256 | Z58: ='55'!$F$29 -> 12.89627 | AA58: ='55'!$F$30 -> 12.896272 | AB58: ='55'!$F$31 | AC58: ='55'!$F$32 | AD58: ='55'!$F$33 -> 12.896258
A59: Lamar-Orange | B59: ='56'!$F$5 | C59: ='56'!$F$6 | D59: ='56'!$F$7 | E59: ='56'!$F$8 | F59: ='56'!$F$9 | G59: ='56'!$F$10 | H59: ='56'!$F$11 | I59: ='56'!$F$12 | J59: ='56'!$F$13 | K59: ='56'!$F$14 | L59: ='56'!$F$15 | M59: ='56'!$F$16 | N59: ='56'!$F$17 | O59: ='56'!$F$18 | P59: ='56'!$F$19 | Q59: ='56'!$F$20 | R59: ='56'!$F$21 | S59: ='56'!$F$22 | T59: ='56'!$F$23 | U59: ='56'!$F$24 | V59: ='56'!$F$25 | W59: ='56'!$F$26 | X59: ='56'!$F$27 | Y59: ='56'!$F$28 | Z59: ='56'!$F$29 | AA59: ='56'!$F$30 | AB59: ='56'!$F$31 | AC59: ='56'!$F$32 | AD59: ='56'!$F$33
A60: Lamar-Port Arthur | B60: ='57'!$F$5 | C60: ='57'!$F$6 | D60: ='57'!$F$7 -> 16.664598 | E60: ='57'!$F$8 -> 16.664588 | F60: ='57'!$F$9 | G60: ='57'!$F$10 -> 16.664598 | H60: ='57'!$F$11 -> 16.664595 | I60: ='57'!$F$12 -> 16.664583 | J60: ='57'!$F$13 -> 16.664603 | K60: ='57'!$F$14 | L60: ='57'!$F$15 -> 16.664596 | M60: ='57'!$F$16 -> 16.664604 | N60: ='57'!$F$17 -> 16.664722 | O60: ='57'!$F$18 -> 16.664578 | P60: ='57'!$F$19 | Q60: ='57'!$F$20 -> 16.664598 | R60: ='57'!$F$21 | S60: ='57'!$F$22 -> 16.664595 | T60: ='57'!$F$23 -> 16.664597 | U60: ='57'!$F$24 -> 16.664571 | V60: ='57'!$F$25 -> 16.664584 | W60: ='57'!$F$26 -> 16.664569 | X60: ='57'!$F$27 -> 16.664571 | Y60: ='57'!$F$28 -> 16.66469 | Z60: ='57'!$F$29 -> 16.664585 | AA60: ='57'!$F$30 -> 16.664566 | AB60: ='57'!$F$31 | AC60: ='57'!$F$32 | AD60: ='57'!$F$33 -> 16.664593
A61: Total | B61: =Summary!$F$5 -> 8.9459924 | C61: =Summary!$F$6 -> 9.8950421 | D61: =Summary!$F$7 -> 7.7869597 | E61: =Summary!$F$8 -> 7.9514488 | F61: =Summary!$F$9 -> 35.064016 | G61: =Summary!$F$10 -> 8.913555 | H61: =Summary!$F$11 -> 9.8773789 | I61: =Summary!$F$12 -> 10.673804 | J61: =Summary!$F$13 -> 7.7785582 | K61: =Summary!$F$14 -> 11.277206 | L61: =Summary!$F$15 -> 8.4264374 | M61: =Summary!$F$16 -> 8.2593827 | N61: =Summary!$F$17 -> 7.5285434 | O61: =Summary!$F$18 -> 12.214498 | P61: =Summary!$F$19 -> 17.743962 | Q61: =Summary!$F$20 -> 9.9532602 | R61: =Summary!$F$21 -> 12.498638 | S61: =Summary!$F$22 -> 9.681962 | T61: =Summary!$F$23 -> 7.5967619 | U61: =Summary!$F$24 -> 10.076582 | V61: =Summary!$F$25 -> 10.221684 | W61: =Summary!$F$26 -> 9.3156647 | X61: =Summary!$F$27 -> 9.3467054 | Y61: =Summary!$F$28 -> 8.5938489 | Z61: =Summary!$F$29 -> 7.0742804 | AA61: =Summary!$F$30 -> 9.6981825 | AD61: =Summary!$F$33 -> 8.4164041
A62: Average (Excluding zero values) | B62: =AVERAGE(B$4:B$60) -> 9.5313699 | C62: =AVERAGE(C$4:C$60) -> 9.7021145 | D62: =AVERAGE(D$4:D$60) -> 7.6742905 | E62: =AVERAGE(E$4:E$60) -> 7.9628238 | F62: =AVERAGE(F$4:F$60) -> 31.764352 | G62: =AVERAGE(G$4:G$60) -> 10.637052 | H62: =AVERAGE(H$4:H$60) -> 11.255187 | I62: =AVERAGE(I$4:I$60) -> 12.888469 | ... AA62: =AVERAGE(AA$4:AA$60) -> 9.2017808 | AD62: =AVERAGE(AD$4:AD$60) -> 8.3321267
A63: High | B63: =MAX(B$4:B$60) -> 21.203448 | C63: =MAX(C$4:C$60) -> 20.76308 | D63: =MAX(D$4:D$60) -> 16.664598 | E63: =MAX(E$4:E$60) -> 16.664588 | F63: =MAX(F$4:F$60) -> 106.94003 | G63: =MAX(G$4:G$60) -> 46.621408 | H63: =MAX(H$4:H$60) -> 45.815292 | I63: =MAX(I$4:I$60) -> 51.836441 | ... AA63: =MAX(AA$4:AA$60) -> 16.664566 | AD63: =MAX(AD$4:AD$60) -> 16.664593
A64: Low (Excluding zero values) | B64: =MIN(B$4:B$60) -> 4.4052562 | C64: =MIN(C$4:C$60) -> 3.6355182 | D64: =MIN(D$4:D$60) -> 4.1966374 | E64: =MIN(E$4:E$60) -> 3.5264677 | F64: =MIN(F$4:F$60) -> 4.7655608 | G64: =MIN(G$4:G$60) -> 2.7103647 | H64: =MIN(H$4:H$60) -> 3.9061387 | I64: =MIN(I$4:I$60) -> 3.0756697 | ... AA64: =MIN(AA$4:AA$60) -> 4.5062713 | AD64: =MIN(AD$4:AD$60) -> 4.8550314
A65: Median (Excluding zero values) | B65: =MEDIAN(B$4:B$60) -> 8.6128713 | C65: =MEDIAN(C$4:C$60) -> 9.471967 | D65: =MEDIAN(D$4:D$60) -> 7.3414033 | E65: =MEDIAN(E$4:E$60) -> 7.927107 | F65: =MEDIAN(F$4:F$60) -> 18.833436 | G65: =MEDIAN(G$4:G$60) -> 8.9519391 | H65: =MEDIAN(H$4:H$60) -> 10.445328 | I65: =MEDIAN(I$4:I$60) -> 9.5928889 | ... AA65: =MEDIAN(AA$4:AA$60) -> 8.8492737 | AD65: =MEDIAN(AD$4:AD$60) -> 8.2112624
B67: Discipline | L67: Discipline | V67: Discipline
B68: AG - Agriculture | L68: ENGR - Engineering Related | V68: MECH - Mechanics and Repairers - Diesel, Aviation Mechanics, and Transportation Workers
B69: ARCH - Architecture and Precision Production Trades | L69: LA - English Language, Lit, Philosophy, Humanities, & Interdisciplinary | V69: ELECT - Mechanics and Repairers - Electronics
B70: SCI - Biology, Physical Sciences, and Science Technology | L70: FL - Foreign Languages | V70: PE - Physical Education and Fitness
B71: BA - Business Management, Marketing, and Administrative Services | L71: HODA - Health Occupations - Dental Assistants, Medical Lab, and Assoc. Degree Nursing | V71: PA - Protective Services and Public Administration
B72: CP - Career Pilot | L72: HODH - Health Occupations - Dental Hygiene | V72: SS - Psychology, Social Sciences, and History
B73: COMM - Communications | L73: HOO - Health Occupations - Other | V73: FA - Visual and Performing Arts
B74: CS - Computer and Information Sciences | L74: HORT - Health Occupations - Respiratory Therapy
B75: CNSTR - Construction Trades | L75: NUR - Health Occupations - Vocational Nursing | V75: DEM - Developmental Education - Math
B76: HE - Consumer and Homemaking Education | L76: MATH - Mathematics | V76: DER - Developmental Education - Reading/Writing
B77: ENG - Engineering | L77: AUTO - Mechanics and Repairers - Automotive | V77: Total - All Disciplines

Sheet Discipline Analysis
A1: =Summary!A1 -> Community and Technical Colleges, Report of Fundable Operating Expenses, Fiscal Year (FY) 2009
A2: Discipline Analysis by Institution | X2: Discipline
A3: 29 | X3: Agriculture
X4: Architecture and Precision Production Trades
A5: Institution | B5: Contact Hours | C5: Total | E5: Faculty Salaries | G5: Academic Support | I5: Institutional Support | K5: Student Services | M5: Departmental Operating Expense | O5: Research | Q5: Scholarships and Fellowships | S5: Equipment Depreciation | U5: Local Benefits | X5: Biology, Physical Sciences, and Science Technology
C6: Expense | D6: per Hour | E6: Expense | F6: per Hour | G6: Expense | H6: per Hour | I6: Expense | J6: per Hour | K6: Expense | L6: per Hour | M6: Expense | N6: per Hour | O6: Expense | P6: per Hour | Q6: Expense | R6: per Hour | S6: Expense | T6: per Hour | U6: Expense | V6: per Hour | X6: Business Management, Marketing, and Administrative Services
A7: Alamo | B7: =OFFSET('1'!$D$4,$A$3,0) -> 21475760 | C7: =OFFSET('1'!$E$4,$A$3,0) -> 2.0866447e+08 | D7: =IFERROR(C7/$B7,"") -> 9.7162787 | E7: =OFFSET('1'!$E$66,$A$3,0) -> 77393596 | F7: =IFERROR(E7/$B7,"") -> 3.6037652 | G7: ='1'!$F$100*B7 -> 20629575 | H7: =IFERROR(G7/$B7,"") -> 0.96059813 | I7: ='1'!$F$98*'Discipline Analysis'!B7 -> 41105949 | J7: =IFERROR(I7/$B7,"") -> 1.9140626 | K7: ='1'!$F$99*'Discipline Analysis'!B7 -> 22112733 | L7: =IFERROR(K7/$B7,"") -> 1.0296601 | M7: =OFFSET('1'!$E$35,$A$3,0) -> 34855466 | N7: =IFERROR(M7/$B7,"") -> 1.6230143 | O7: ='1'!$F$101*'Discipline Analysis'!B7 -> 0 | P7: =IFERROR(O7/$B7,"") -> 0 | Q7: ='1'!$F$102*'Discipline Analysis'!B7 -> 509820 | R7: =IFERROR(Q7/$B7,"") -> 0.023739323 | S7: ='1'!$F$103*'Discipline Analysis'!B7 -> 3850832 | T7: =IFERROR(S7/$B7,"") -> 0.17931063 | U7: ='1'!$F$104*'Discipline Analysis'!B7 -> 8206499 | V7: =IFERROR(U7/$B7,"") -> 0.38212846 | X7: Career Pilot
A8: Alvin | B8: =OFFSET('2'!$D$4,$A$3,0) -> 2273527 | C8: =OFFSET('2'!$E$4,$A$3,0) -> 21650677 | D8: =IFERROR(C8/$B8,"") -> 9.5229469 | E8: =OFFSET('2'!$E$66,$A$3,0) -> 10862327 | F8: =IFERROR(E8/$B8,"") -> 4.7777427 | G8: ='2'!$F$100*B8 -> 2612791 | H8: =IFERROR(G8/$B8,"") -> 1.1492237 | I8: ='2'!$F$98*'Discipline Analysis'!B8 -> 3176221 | J8: =IFERROR(I8/$B8,"") -> 1.3970456 | K8: ='2'!$F$99*'Discipline Analysis'!B8 -> 1824302 | L8: =IFERROR(K8/$B8,"") -> 0.80241053 | M8: =OFFSET('2'!$E$35,$A$3,0) -> 2537931 | N8: =IFERROR(M8/$B8,"") -> 1.1162968 | O8: ='2'!$F$101*'Discipline Analysis'!B8 -> 0 | P8: =IFERROR(O8/$B8,"") -> 0 | Q8: ='2'!$F$102*'Discipline Analysis'!B8 -> 0 | R8: =IFERROR(Q8/$B8,"") -> 0 | S8: ='2'!$F$103*'Discipline Analysis'!B8 -> 350670 | T8: =IFERROR(S8/$B8,"") -> 0.15424053 | U8: ='2'!$F$104*'Discipline Analysis'!B8 -> 286435 | V8: =IFERROR(U8/$B8,"") -> 0.12598707 | X8: Communications
A9: Amarillo | B9: =OFFSET('3'!$D$4,$A$3,0) -> 4629260 | C9: =OFFSET('3'!$E$4,$A$3,0) -> 37778402 | D9: =IFERROR(C9/$B9,"") -> 8.1607864 | E9: =OFFSET('3'!$E$66,$A$3,0) -> 14157756 | F9: =IFERROR(E9/$B9,"") -> 3.0583195 | G9: ='3'!$F$100*B9 -> 2743581 | H9: =IFERROR(G9/$B9,"") -> 0.59266081 | I9: ='3'!$F$98*'Discipline Analysis'!B9 -> 8889447 | J9: =IFERROR(I9/$B9,"") -> 1.9202739 | K9: ='3'!$F$99*'Discipline Analysis'!B9 -> 2938366 | L9: =IFERROR(K9/$B9,"") -> 0.63473773 | M9: =OFFSET('3'!$E$35,$A$3,0) -> 6481338 | N9: =IFERROR(M9/$B9,"") -> 1.4000808 | O9: ='3'!$F$101*'Discipline Analysis'!B9 -> 0 | P9: =IFERROR(O9/$B9,"") -> 0 | Q9: ='3'!$F$102*'Discipline Analysis'!B9 -> 0 | R9: =IFERROR(Q9/$B9,"") -> 0 | S9: ='3'!$F$103*'Discipline Analysis'!B9 -> 875149 | T9: =IFERROR(S9/$B9,"") -> 0.18904728 | U9: ='3'!$F$104*'Discipline Analysis'!B9 -> 1692765 | V9: =IFERROR(U9/$B9,"") -> 0.36566643 | X9: Computer and Information Sciences
A10: Angelina | B10: =OFFSET('4'!$D$4,$A$3,0) -> 2199497 | C10: =OFFSET('4'!$E$4,$A$3,0) -> 14259157 | D10: =IFERROR(C10/$B10,"") -> 6.4829172 | E10: =OFFSET('4'!$E$66,$A$3,0) -> 7703398 | F10: =IFERROR(E10/$B10,"") -> 3.5023453 | G10: ='4'!$F$100*B10 -> 1819097 | H10: =IFERROR(G10/$B10,"") -> 0.82705137 | I10: ='4'!$F$98*'Discipline Analysis'!B10 -> 2051976 | J10: =IFERROR(I10/$B10,"") -> 0.93292967 | K10: ='4'!$F$99*'Discipline Analysis'!B10 -> 981246 | L10: =IFERROR(K10/$B10,"") -> 0.44612291 | M10: =OFFSET('4'!$E$35,$A$3,0) -> 1245818 | N10: =IFERROR(M10/$B10,"") -> 0.56641041 | O10: ='4'!$F$101*'Discipline Analysis'!B10 -> 0 | P10: =IFERROR(O10/$B10,"") -> 0 | Q10: ='4'!$F$102*'Discipline Analysis'!B10 -> 0 | R10: =IFERROR(Q10/$B10,"") -> 0 | S10: ='4'!$F$103*'Discipline Analysis'!B10 -> 301027 | T10: =IFERROR(S10/$B10,"") -> 0.13686175 | U10: ='4'!$F$104*'Discipline Analysis'!B10 -> 156595 | V10: =IFERROR(U10/$B10,"") -> 0.071195823 | X10: Construction Trades
A11: Austin | B11: =OFFSET('5'!$D$4,$A$3,0) -> 13977483 | C11: =OFFSET('5'!$E$4,$A$3,0) -> 1.5176977e+08 | D11: =IFERROR(C11/$B11,"") -> 10.858162 | E11: =OFFSET('5'!$E$66,$A$3,0) -> 66503577 | F11: =IFERROR(E11/$B11,"") -> 4.7579079 | G11: ='5'!$F$100*B11 -> 18485769 | H11: =IFERROR(G11/$B11,"") -> 1.3225392 | I11: ='5'!$F$98*'Discipline Analysis'!B11 -> 26906537 | J11: =IFERROR(I11/$B11,"") -> 1.9249916 | K11: ='5'!$F$99*'Discipline Analysis'!B11 -> 17053869 | L11: =IFERROR(K11/$B11,"") -> 1.2200958 | M11: =OFFSET('5'!$E$35,$A$3,0) -> 16825020 | N11: =IFERROR(M11/$B11,"") -> 1.2037232 | O11: ='5'!$F$101*'Discipline Analysis'!B11 -> 0 | P11: =IFERROR(O11/$B11,"") -> 0 | Q11: ='5'!$F$102*'Discipline Analysis'!B11 -> 0 | R11: =IFERROR(Q11/$B11,"") -> 0 | S11: ='5'!$F$103*'Discipline Analysis'!B11 -> 2282609 | T11: =IFERROR(S11/$B11,"") -> 0.16330615 | U11: ='5'!$F$104*'Discipline Analysis'!B11 -> 3712390 | V11: =IFERROR(U11/$B11,"") -> 0.26559789 | X11: Consumer and Homemaking Education
A12: Blinn | B12: =OFFSET('6'!$D$4,$A$3,0) -> 6960349 | C12: =OFFSET('6'!$E$4,$A$3,0) -> 42057632 | D12: =IFERROR(C12/$B12,"") -> 6.0424602 | E12: =OFFSET('6'!$E$66,$A$3,0) -> 20715696 | F12: =IFERROR(E12/$B12,"") -> 2.9762439 | G12: ='6'!$F$100*B12 -> 3129156 | H12: =IFERROR(G12/$B12,"") -> 0.44956884 | I12: ='6'!$F$98*'Discipline Analysis'!B12 -> 6088267 | J12: =IFERROR(I12/$B12,"") -> 0.87470714 | K12: ='6'!$F$99*'Discipline Analysis'!B12 -> 3887200 | L12: =IFERROR(K12/$B12,"") -> 0.55847774 | M12: =OFFSET('6'!$E$35,$A$3,0) -> 6729802 | N12: =IFERROR(M12/$B12,"") -> 0.96687709 | O12: ='6'!$F$101*'Discipline Analysis'!B12 -> 0 | P12: =IFERROR(O12/$B12,"") -> 0 | Q12: ='6'!$F$102*'Discipline Analysis'!B12 -> 510820 | R12: =IFERROR(Q12/$B12,"") -> 0.073389998 | S12: ='6'!$F$103*'Discipline Analysis'!B12 -> 325793 | T12: =IFERROR(S12/$B12,"") -> 0.046806992 | U12: ='6'!$F$104*'Discipline Analysis'!B12 -> 670898 | V12: =IFERROR(U12/$B12,"") -> 0.096388558 | X12: Engineering
A13: Brazosport | B13: =OFFSET('7'!$D$4,$A$3,0) -> 1491922 | C13: =OFFSET('7'!$E$4,$A$3,0) -> 15048156 | D13: =IFERROR(C13/$B13,"") -> 10.086423 | E13: =OFFSET('7'!$E$66,$A$3,0) -> 6051972 | F13: =IFERROR(E13/$B13,"") -> 4.0564936 | G13: ='7'!$F$100*B13 -> 1517183 | H13: =IFERROR(G13/$B13,"") -> 1.0169319 | I13: ='7'!$F$98*'Discipline Analysis'!B13 -> 3646021 | J13: =IFERROR(I13/$B13,"") -> 2.4438416 | K13: ='7'!$F$99*'Discipline Analysis'!B13 -> 1766793 | L13: =IFERROR(K13/$B13,"") -> 1.1842395 | M13: =OFFSET('7'!$E$35,$A$3,0) -> 1282025 | N13: =IFERROR(M13/$B13,"") -> 0.85931101 | O13: ='7'!$F$101*'Discipline Analysis'!B13 -> 0 | P13: =IFERROR(O13/$B13,"") -> 0 | Q13: ='7'!$F$102*'Discipline Analysis'!B13 -> 268621 | R13: =IFERROR(Q13/$B13,"") -> 0.1800503 | S13: ='7'!$F$103*'Discipline Analysis'!B13 -> 316443 | T13: =IFERROR(S13/$B13,"") -> 0.21210425 | U13: ='7'!$F$104*'Discipline Analysis'!B13 -> 199098 | V13: =IFERROR(U13/$B13,"") -> 0.13345068 | X13: Engineering Related
A14: Central Texas | B14: =OFFSET('8'!$D$4,$A$3,0) -> 5713917 | C14: =OFFSET('8'!$E$4,$A$3,0) -> 47596057 | D14: =IFERROR(C14/$B14,"") -> 8.3298475 | E14: =OFFSET('8'!$E$66,$A$3,0) -> 18193181 | F14: =IFERROR(E14/$B14,"") -> 3.1840121 | G14: ='8'!$F$100*B14 -> 2614480 | H14: =IFERROR(G14/$B14,"") -> 0.45756352 | I14: ='8'!$F$98*'Discipline Analysis'!B14 -> 8804560 | J14: =IFERROR(I14/$B14,"") -> 1.5408974 | K14: ='8'!$F$99*'Discipline Analysis'!B14 -> 4194267 | L14: =IFERROR(K14/$B14,"") -> 0.73404409 | M14: =OFFSET('8'!$E$35,$A$3,0) -> 11226898 | N14: =IFERROR(M14/$B14,"") -> 1.9648339 | O14: ='8'!$F$101*'Discipline Analysis'!B14 -> 0 | P14: =IFERROR(O14/$B14,"") -> 0 | Q14: ='8'!$F$102*'Discipline Analysis'!B14 -> 0 | R14: =IFERROR(Q14/$B14,"") -> 0 | S14: ='8'!$F$103*'Discipline Analysis'!B14 -> 706092 | T14: =IFERROR(S14/$B14,"") -> 0.12357407 | U14: ='8'!$F$104*'Discipline Analysis'!B14 -> 1856579 | V14: =IFERROR(U14/$B14,"") -> 0.32492229 | X14: English Language, Lit, Philosophy, Humanities, & Interdisciplinary
A15: Cisco | B15: =OFFSET('9'!$D$4,$A$3,0) -> 1605015 | C15: =OFFSET('9'!$E$4,$A$3,0) -> 9521537 | D15: =IFERROR(C15/$B15,"") -> 5.9323664 | E15: =OFFSET('9'!$E$66,$A$3,0) -> 4565768 | F15: =IFERROR(E15/$B15,"") -> 2.8446887 | G15: ='9'!$F$100*B15 -> 722845 | H15: =IFERROR(G15/$B15,"") -> 0.45036651 | I15: ='9'!$F$98*'Discipline Analysis'!B15 -> 1954294 | J15: =IFERROR(I15/$B15,"") -> 1.2176173 | K15: ='9'!$F$99*'Discipline Analysis'!B15 -> 991093 | L15: =IFERROR(K15/$B15,"") -> 0.61749766 | M15: =OFFSET('9'!$E$35,$A$3,0) -> 794763 | N15: =IFERROR(M15/$B15,"") -> 0.49517481 | O15: ='9'!$F$101*'Discipline Analysis'!B15 -> 0 | P15: =IFERROR(O15/$B15,"") -> 0 | Q15: ='9'!$F$102*'Discipline Analysis'!B15 -> 0 | R15: =IFERROR(Q15/$B15,"") -> 0 | S15: ='9'!$F$103*'Discipline Analysis'!B15 -> 301503 | T15: =IFERROR(S15/$B15,"") -> 0.18785058 | U15: ='9'!$F$104*'Discipline Analysis'!B15 -> 191271 | V15: =IFERROR(U15/$B15,"") -> 0.11917085 | X15: Foreign Languages
A16: Clarendon | B16: =OFFSET('10'!$D$4,$A$3,0) -> 667930 | C16: =OFFSET('10'!$E$4,$A$3,0) -> 3900789 | D16: =IFERROR(C16/$B16,"") -> 5.8401165 | E16: =OFFSET('10'!$E$66,$A$3,0) -> 1793119 | F16: =IFERROR(E16/$B16,"") -> 2.6845912 | G16: ='10'!$F$100*B16 -> 422070 | H16: =IFERROR(G16/$B16,"") -> 0.63190754 | I16: ='10'!$F$98*'Discipline Analysis'!B16 -> 846408 | J16: =IFERROR(I16/$B16,"") -> 1.2672106 | K16: ='10'!$F$99*'Discipline Analysis'!B16 -> 410958 | L16: =IFERROR(K16/$B16,"") -> 0.61527106 | M16: =OFFSET('10'!$E$35,$A$3,0) -> 104167 | N16: =IFERROR(M16/$B16,"") -> 0.15595497 | O16: ='10'!$F$101*'Discipline Analysis'!B16 -> 0 | P16: =IFERROR(O16/$B16,"") -> 0 | Q16: ='10'!$F$102*'Discipline Analysis'!B16 -> 0 | R16: =IFERROR(Q16/$B16,"") -> 0 | S16: ='10'!$F$103*'Discipline Analysis'!B16 -> 263222 | T16: =IFERROR(S16/$B16,"") -> 0.39408621 | U16: ='10'!$F$104*'Discipline Analysis'!B16 -> 60845 | V16: =IFERROR(U16/$B16,"") -> 0.091094875 | X16: Health Occupations - Dental Assistants, Medical Lab, and Assoc. Degree Nursing
A17: Coastal Bend | B17: =OFFSET('11'!$D$4,$A$3,0) -> 1820551 | C17: =OFFSET('11'!$E$4,$A$3,0) -> 14139348 | D17: =IFERROR(C17/$B17,"") -> 7.7665212 | E17: =OFFSET('11'!$E$66,$A$3,0) -> 5982423 | F17: =IFERROR(E17/$B17,"") -> 3.2860508 | G17: ='11'!$F$100*B17 -> 795200 | H17: =IFERROR(G17/$B17,"") -> 0.43679084 | I17: ='11'!$F$98*'Discipline Analysis'!B17 -> 4158506 | J17: =IFERROR(I17/$B17,"") -> 2.2842019 | K17: ='11'!$F$99*'Discipline Analysis'!B17 -> 1123151 | L17: =IFERROR(K17/$B17,"") -> 0.61692916 | M17: =OFFSET('11'!$E$35,$A$3,0) -> 1456968 | N17: =IFERROR(M17/$B17,"") -> 0.80028958 | O17: ='11'!$F$101*'Discipline Analysis'!B17 -> 0 | P17: =IFERROR(O17/$B17,"") -> 0 | Q17: ='11'!$F$102*'Discipline Analysis'!B17 -> 0 | R17: =IFERROR(Q17/$B17,"") -> 0 | S17: ='11'!$F$103*'Discipline Analysis'!B17 -> 256966 | T17: =IFERROR(S17/$B17,"") -> 0.14114738 | U17: ='11'!$F$104*'Discipline Analysis'!B17 -> 366134 | V17: =IFERROR(U17/$B17,"") -> 0.20111164 | X17: Health Occupations - Dental Hygiene
A18: College Of The Mainland | B18: =OFFSET('12'!$D$4,$A$3,0) -> 0 | C18: =OFFSET('12'!$E$4,$A$3,0) -> 0 | D18: =IFERROR(C18/$B18,"") | E18: =OFFSET('12'!$E$66,$A$3,0) -> 0 | F18: =IFERROR(E18/$B18,"") | G18: ='12'!$F$100*B18 -> 0 | H18: =IFERROR(G18/$B18,"") | I18: ='12'!$F$98*'Discipline Analysis'!B18 -> 0 | J18: =IFERROR(I18/$B18,"") | K18: ='12'!$F$99*'Discipline Analysis'!B18 -> 0 | L18: =IFERROR(K18/$B18,"") | M18: =OFFSET('12'!$E$35,$A$3,0) -> 0 | N18: =IFERROR(M18/$B18,"") | O18: ='12'!$F$101*'Discipline Analysis'!B18 -> 0 | P18: =IFERROR(O18/$B18,"") | Q18: ='12'!$F$102*'Discipline Analysis'!B18 -> 0 | R18: =IFERROR(Q18/$B18,"") | S18: ='12'!$F$103*'Discipline Analysis'!B18 -> 0 | T18: =IFERROR(S18/$B18,"") | U18: ='12'!$F$104*'Discipline Analysis'!B18 -> 0 | V18: =IFERROR(U18/$B18,"") | X18: Health Occupations - Other
A19: Collin | B19: =OFFSET('13'!$D$4,$A$3,0) -> 9390142 | C19: =OFFSET('13'!$E$4,$A$3,0) -> 80287869 | D19: =IFERROR(C19/$B19,"") -> 8.5502295 | E19: =OFFSET('13'!$E$66,$A$3,0) -> 28579323 | F19: =IFERROR(E19/$B19,"") -> 3.0435453 | G19: ='13'!$F$100*B19 -> 9493586 | H19: =IFERROR(G19/$B19,"") -> 1.0110162 | I19: ='13'!$F$98*'Discipline Analysis'!B19 -> 10354147 | J19: =IFERROR(I19/$B19,"") -> 1.1026614 | K19: ='13'!$F$99*'Discipline Analysis'!B19 -> 6650847 | L19: =IFERROR(K19/$B19,"") -> 0.7082797 | M19: =OFFSET('13'!$E$35,$A$3,0) -> 15336071 | N19: =IFERROR(M19/$B19,"") -> 1.6332097 | O19: ='13'!$F$101*'Discipline Analysis'!B19 -> 0 | P19: =IFERROR(O19/$B19,"") -> 0 | Q19: ='13'!$F$102*'Discipline Analysis'!B19 -> 6839746 | R19: =IFERROR(Q19/$B19,"") -> 0.72839644 | S19: ='13'!$F$103*'Discipline Analysis'!B19 -> 2345569 | T19: =IFERROR(S19/$B19,"") -> 0.24979058 | U19: ='13'!$F$104*'Discipline Analysis'!B19 -> 688580 | V19: =IFERROR(U19/$B19,"") -> 0.073330094 | X19: Health Occupations - Respiratory Therapy
A20: Dallas | B20: =OFFSET('14'!$D$4,$A$3,0) -> 29061694 | C20: =OFFSET('14'!$E$4,$A$3,0) -> 233857119 | D20: =IFERROR(C20/$B20,"") -> 8.0469197 | E20: =OFFSET('14'!$E$66,$A$3,0) -> 84092694 | F20: =IFERROR(E20/$B20,"") -> 2.8935923 | G20: ='14'!$F$100*B20 -> 16440735 | H20: =IFERROR(G20/$B20,"") -> 0.5657184 | I20: ='14'!$F$98*'Discipline Analysis'!B20 -> 52220010 | J20: =IFERROR(I20/$B20,"") -> 1.7968674 | K20: ='14'!$F$99*'Discipline Analysis'!B20 -> 26204338 | L20: =IFERROR(K20/$B20,"") -> 0.90167965 | M20: =OFFSET('14'!$E$35,$A$3,0) -> 47143834 | N20: =IFERROR(M20/$B20,"") -> 1.6221984 | O20: ='14'!$F$101*'Discipline Analysis'!B20 -> 0 | P20: =IFERROR(O20/$B20,"") -> 0 | Q20: ='14'!$F$102*'Discipline Analysis'!B20 -> 0 | R20: =IFERROR(Q20/$B20,"") -> 0 | S20: ='14'!$F$103*'Discipline Analysis'!B20 -> 2983540 | T20: =IFERROR(S20/$B20,"") -> 0.10266229 | U20: ='14'!$F$104*'Discipline Analysis'!B20 -> 4771968 | V20: =IFERROR(U20/$B20,"") -> 0.1642013 | X20: Health Occupations - Vocational Nursing
A21: Del Mar | B21: =OFFSET('15'!$D$4,$A$3,0) -> 5053748 | C21: =OFFSET('15'!$E$4,$A$3,0) -> 53827021 | D21: =IFERROR(C21/$B21,"") -> 10.650911 | E21: =OFFSET('15'!$E$66,$A$3,0) -> 25044445 | F21: =IFERROR(E21/$B21,"") -> 4.9556181 | G21: ='15'!$F$100*B21 -> 4836229 | H21: =IFERROR(G21/$B21,"") -> 0.95695887 | I21: ='15'!$F$98*'Discipline Analysis'!B21 -> 12158320 | J21: =IFERROR(I21/$B21,"") -> 2.4058026 | K21: ='15'!$F$99*'Discipline Analysis'!B21 -> 4855666 | L21: =IFERROR(K21/$B21,"") -> 0.96080493 | M21: =OFFSET('15'!$E$35,$A$3,0) -> 5054909 | N21: =IFERROR(M21/$B21,"") -> 1.0002297 | O21: ='15'!$F$101*'Discipline Analysis'!B21 -> 0 | P21: =IFERROR(O21/$B21,"") -> 0 | Q21: ='15'!$F$102*'Discipline Analysis'!B21 -> 0 | R21: =IFERROR(Q21/$B21,"") -> 0 | S21: ='15'!$F$103*'Discipline Analysis'!B21 -> 0 | T21: =IFERROR(S21/$B21,"") -> 0 | U21: ='15'!$F$104*'Discipline Analysis'!B21 -> 1877452 | V21: =IFERROR(U21/$B21,"") -> 0.37149696 | X21: Mathematics
A22: El Paso | B22: =OFFSET('16'!$D$4,$A$3,0) -> 10039883 | C22: =OFFSET('16'!$E$4,$A$3,0) -> 82584383 | D22: =IFERROR(C22/$B22,"") -> 8.225632 | E22: =OFFSET('16'!$E$66,$A$3,0) -> 32823293 | F22: =IFERROR(E22/$B22,"") -> 3.2692904 | G22: ='16'!$F$100*B22 -> 13702548 | H22: =IFERROR(G22/$B22,"") -> 1.3648115 | I22: ='16'!$F$98*'Discipline Analysis'!B22 -> 16890228 | J22: =IFERROR(I22/$B22,"") -> 1.6823132 | K22: ='16'!$F$99*'Discipline Analysis'!B22 -> 7804386 | L22: =IFERROR(K22/$B22,"") -> 0.77733834 | M22: =OFFSET('16'!$E$35,$A$3,0) -> 6815386 | N22: =IFERROR(M22/$B22,"") -> 0.67883122 | O22: ='16'!$F$101*'Discipline Analysis'!B22 -> 45822 | P22: =IFERROR(O22/$B22,"") -> 0.0045639974 | Q22: ='16'!$F$102*'Discipline Analysis'!B22 -> 1526952 | R22: =IFERROR(Q22/$B22,"") -> 0.15208862 | S22: ='16'!$F$103*'Discipline Analysis'!B22 -> 1349105 | T22: =IFERROR(S22/$B22,"") -> 0.13437457 | U22: ='16'!$F$104*'Discipline Analysis'!B22 -> 1626663 | V22: =IFERROR(U22/$B22,"") -> 0.16202012 | X22: Mechanics and Repairers - Automotive
A23: Frank Phillips | B23: =OFFSET('17'!$D$4,$A$3,0) -> 647658 | C23: =OFFSET('17'!$E$4,$A$3,0) -> 6035988 | D23: =IFERROR(C23/$B23,"") -> 9.319715 | E23: =OFFSET('17'!$E$66,$A$3,0) -> 2016183 | F23: =IFERROR(E23/$B23,"") -> 3.1130365 | G23: ='17'!$F$100*B23 -> 175713 | H23: =IFERROR(G23/$B23,"") -> 0.27130523 | I23: ='17'!$F$98*'Discipline Analysis'!B23 -> 1567009 | J23: =IFERROR(I23/$B23,"") -> 2.4195007 | K23: ='17'!$F$99*'Discipline Analysis'!B23 -> 644820 | L23: =IFERROR(K23/$B23,"") -> 0.99561806 | M23: =OFFSET('17'!$E$35,$A$3,0) -> 1022662 | N23: =IFERROR(M23/$B23,"") -> 1.5790155 | O23: ='17'!$F$101*'Discipline Analysis'!B23 -> 0 | P23: =IFERROR(O23/$B23,"") -> 0 | Q23: ='17'!$F$102*'Discipline Analysis'!B23 -> 119114 | R23: =IFERROR(Q23/$B23,"") -> 0.18391497 | S23: ='17'!$F$103*'Discipline Analysis'!B23 -> 369629 | T23: =IFERROR(S23/$B23,"") -> 0.57071633 | U23: ='17'!$F$104*'Discipline Analysis'!B23 -> 120858 | V23: =IFERROR(U23/$B23,"") -> 0.18660775 | X23: Mechanics and Repairers - Diesel, Aviation Mechanics, and Transportation Workers
A24: Galveston | B24: =OFFSET('18'!$D$4,$A$3,0) -> 930552 | C24: =OFFSET('18'!$E$4,$A$3,0) -> 12047577 | D24: =IFERROR(C24/$B24,"") -> 12.946699 | E24: =OFFSET('18'!$E$66,$A$3,0) -> 3975337 | F24: =IFERROR(E24/$B24,"") -> 4.2720203 | G24: ='18'!$F$100*B24 -> 1430723 | H24: =IFERROR(G24/$B24,"") -> 1.5374992 | I24: ='18'!$F$98*'Discipline Analysis'!B24 -> 3856364 | J24: =IFERROR(I24/$B24,"") -> 4.1441682 | K24: ='18'!$F$99*'Discipline Analysis'!B24 -> 1303551 | L24: =IFERROR(K24/$B24,"") -> 1.4008363 | M24: =OFFSET('18'!$E$35,$A$3,0) -> 917498 | N24: =IFERROR(M24/$B24,"") -> 0.98597177 | O24: ='18'!$F$101*'Discipline Analysis'!B24 -> 0 | P24: =IFERROR(O24/$B24,"") -> 0 | Q24: ='18'!$F$102*'Discipline Analysis'!B24 -> 0 | R24: =IFERROR(Q24/$B24,"") -> 0 | S24: ='18'!$F$103*'Discipline Analysis'!B24 -> 146544 | T24: =IFERROR(S24/$B24,"") -> 0.15748072 | U24: ='18'!$F$104*'Discipline Analysis'!B24 -> 417560 | V24: =IFERROR(U24/$B24,"") -> 0.44872291 | X24: Mechanics and Repairers - Electronics
A25: Grayson | B25: =OFFSET('19'!$D$4,$A$3,0) -> 2151132 | C25: =OFFSET('19'!$E$4,$A$3,0) -> 14481730 | D25: =IFERROR(C25/$B25,"") -> 6.7321438 | E25: =OFFSET('19'!$E$66,$A$3,0) -> 6524000 | F25: =IFERROR(E25/$B25,"") -> 3.0328218 | G25: ='19'!$F$100*B25 -> 1310128 | H25: =IFERROR(G25/$B25,"") -> 0.60904119 | I25: ='19'!$F$98*'Discipline Analysis'!B25 -> 2747734 | J25: =IFERROR(I25/$B25,"") -> 1.2773433 | K25: ='19'!$F$99*'Discipline Analysis'!B25 -> 1416808 | L25: =IFERROR(K25/$B25,"") -> 0.65863369 | M25: =OFFSET('19'!$E$35,$A$3,0) -> 1867886 | N25: =IFERROR(M25/$B25,"") -> 0.868327 | O25: ='19'!$F$101*'Discipline Analysis'!B25 -> 0 | P25: =IFERROR(O25/$B25,"") -> 0 | Q25: ='19'!$F$102*'Discipline Analysis'!B25 -> 0 | R25: =IFERROR(Q25/$B25,"") -> 0 | S25: ='19'!$F$103*'Discipline Analysis'!B25 -> 238705 | T25: =IFERROR(S25/$B25,"") -> 0.11096716 | U25: ='19'!$F$104*'Discipline Analysis'!B25 -> 376469 | V25: =IFERROR(U25/$B25,"") -> 0.17500972 | X25: Physical Education and Fitness
A26: Hill | B26: =OFFSET('20'!$D$4,$A$3,0) -> 2043236 | C26: =OFFSET('20'!$E$4,$A$3,0) -> 11551061 | D26: =IFERROR(C26/$B26,"") -> 5.6533171 | E26: =OFFSET('20'!$E$66,$A$3,0) -> 5645745 | F26: =IFERROR(E26/$B26,"") -> 2.763139 | G26: ='20'!$F$100*B26 -> 850202 | H26: =IFERROR(G26/$B26,"") -> 0.41610563 | I26: ='20'!$F$98*'Discipline Analysis'!B26 -> 2597462 | J26: =IFERROR(I26/$B26,"") -> 1.2712491 | K26: ='20'!$F$99*'Discipline Analysis'!B26 -> 1504988 | L26: =IFERROR(K26/$B26,"") -> 0.73657081 | M26: =OFFSET('20'!$E$35,$A$3,0) -> 417811 | N26: =IFERROR(M26/$B26,"") -> 0.20448494 | O26: ='20'!$F$101*'Discipline Analysis'!B26 -> 0 | P26: =IFERROR(O26/$B26,"") -> 0 | Q26: ='20'!$F$102*'Discipline Analysis'!B26 -> 0 | R26: =IFERROR(Q26/$B26,"") -> 0 | S26: ='20'!$F$103*'Discipline Analysis'!B26 -> 194748 | T26: =IFERROR(S26/$B26,"") -> 0.095313512 | U26: ='20'!$F$104*'Discipline Analysis'!B26 -> 340105 | V26: =IFERROR(U26/$B26,"") -> 0.1664541 | X26: Protective Services and Public Administration
A27: Houston | B27: =OFFSET('21'!$D$4,$A$3,0) -> 21365304 | C27: =OFFSET('21'!$E$4,$A$3,0) -> 180970906 | D27: =IFERROR(C27/$B27,"") -> 8.4703174 | E27: =OFFSET('21'!$E$66,$A$3,0) -> 76295558 | F27: =IFERROR(E27/$B27,"") -> 3.5710027 | G27: ='21'!$F$100*B27 -> 17630830 | H27: =IFERROR(G27/$B27,"") -> 0.82520848 | I27: ='21'!$F$98*'Discipline Analysis'!B27 -> 43684052 | J27: =IFERROR(I27/$B27,"") -> 2.0446258 | K27: ='21'!$F$99*'Discipline Analysis'!B27 -> 21894339 | L27: =IFERROR(K27/$B27,"") -> 1.0247614 | M27: =OFFSET('21'!$E$35,$A$3,0) -> 16336723 | N27: =IFERROR(M27/$B27,"") -> 0.76463799 | O27: ='21'!$F$101*'Discipline Analysis'!B27 -> 0 | P27: =IFERROR(O27/$B27,"") -> 0 | Q27: ='21'!$F$102*'Discipline Analysis'!B27 -> 0 | R27: =IFERROR(Q27/$B27,"") -> 0 | S27: ='21'!$F$103*'Discipline Analysis'!B27 -> 2952896 | T27: =IFERROR(S27/$B27,"") -> 0.13820988 | U27: ='21'!$F$104*'Discipline Analysis'!B27 -> 2176508 | V27: =IFERROR(U27/$B27,"") -> 0.10187115 | X27: Psychology, Social Sciences, and History
A28: Howard | B28: =OFFSET('22'!$D$4,$A$3,0) -> 2300430 | C28: =OFFSET('22'!$E$4,$A$3,0) -> 16020108 | D28: =IFERROR(C28/$B28,"") -> 6.9639624 | E28: =OFFSET('22'!$E$66,$A$3,0) -> 6948577 | F28: =IFERROR(E28/$B28,"") -> 3.0205557 | G28: ='22'!$F$100*B28 -> 1227942 | H28: =IFERROR(G28/$B28,"") -> 0.53378803 | I28: ='22'!$F$98*'Discipline Analysis'!B28 -> 3271612 | J28: =IFERROR(I28/$B28,"") -> 1.4221741 | K28: ='22'!$F$99*'Discipline Analysis'!B28 -> 1623120 | L28: =IFERROR(K28/$B28,"") -> 0.70557244 | M28: =OFFSET('22'!$E$35,$A$3,0) -> 2261291 | N28: =IFERROR(M28/$B28,"") -> 0.98298622 | O28: ='22'!$F$101*'Discipline Analysis'!B28 -> 0 | P28: =IFERROR(O28/$B28,"") -> 0 | Q28: ='22'!$F$102*'Discipline Analysis'!B28 -> 0 | R28: =IFERROR(Q28/$B28,"") -> 0 | S28: ='22'!$F$103*'Discipline Analysis'!B28 -> 383078 | T28: =IFERROR(S28/$B28,"") -> 0.16652452 | U28: ='22'!$F$104*'Discipline Analysis'!B28 -> 304488 | V28: =IFERROR(U28/$B28,"") -> 0.13236134 | X28: Visual and Performing Arts
A29: Kilgore | B29: =OFFSET('23'!$D$4,$A$3,0) -> 3403144 | C29: =OFFSET('23'!$E$4,$A$3,0) -> 21474142 | D29: =IFERROR(C29/$B29,"") -> 6.3100891 | E29: =OFFSET('23'!$E$66,$A$3,0) -> 9918393 | F29: =IFERROR(E29/$B29,"") -> 2.9144794 | G29: ='23'!$F$100*B29 -> 2442780 | H29: =IFERROR(G29/$B29,"") -> 0.71780095 | I29: ='23'!$F$98*'Discipline Analysis'!B29 -> 3806281 | J29: =IFERROR(I29/$B29,"") -> 1.1184602 | K29: ='23'!$F$99*'Discipline Analysis'!B29 -> 1375544 | L29: =IFERROR(K29/$B29,"") -> 0.404198 | M29: =OFFSET('23'!$E$35,$A$3,0) -> 2676435 | N29: =IFERROR(M29/$B29,"") -> 0.78645952 | O29: ='23'!$F$101*'Discipline Analysis'!B29 -> 0 | P29: =IFERROR(O29/$B29,"") -> 0 | Q29: ='23'!$F$102*'Discipline Analysis'!B29 -> 90326 | R29: =IFERROR(Q29/$B29,"") -> 0.026541927 | S29: ='23'!$F$103*'Discipline Analysis'!B29 -> 274653 | T29: =IFERROR(S29/$B29,"") -> 0.080705665 | U29: ='23'!$F$104*'Discipline Analysis'!B29 -> 889730 | V29: =IFERROR(U29/$B29,"") -> 0.26144354 | X29: Developmental Education - Math
A30: Laredo | B30: =OFFSET('24'!$D$4,$A$3,0) -> 3523680 | C30: =OFFSET('24'!$E$4,$A$3,0) -> 35259656 | D30: =IFERROR(C30/$B30,"") -> 10.006486 | E30: =OFFSET('24'!$E$66,$A$3,0) -> 13642771 | F30: =IFERROR(E30/$B30,"") -> 3.8717395 | G30: ='24'!$F$100*B30 -> 2845997 | H30: =IFERROR(G30/$B30,"") -> 0.80767748 | I30: ='24'!$F$98*'Discipline Analysis'!B30 -> 7334514 | J30: =IFERROR(I30/$B30,"") -> 2.0814926 | K30: ='24'!$F$99*'Discipline Analysis'!B30 -> 4136221 | L30: =IFERROR(K30/$B30,"") -> 1.1738356 | M30: =OFFSET('24'!$E$35,$A$3,0) -> 4490296 | N30: =IFERROR(M30/$B30,"") -> 1.27432 | O30: ='24'!$F$101*'Discipline Analysis'!B30 -> 0 | P30: =IFERROR(O30/$B30,"") -> 0 | Q30: ='24'!$F$102*'Discipline Analysis'!B30 -> 287299 | R30: =IFERROR(Q30/$B30,"") -> 0.081533794 | S30: ='24'!$F$103*'Discipline Analysis'!B30 -> 942848 | T30: =IFERROR(S30/$B30,"") -> 0.26757481 | U30: ='24'!$F$104*'Discipline Analysis'!B30 -> 1579710 | V30: =IFERROR(U30/$B30,"") -> 0.44831256 | X30: Developmental Education - Reading/Writing
A31: Lee | B31: =OFFSET('25'!$D$4,$A$3,0) -> 2896163 | C31: =OFFSET('25'!$E$4,$A$3,0) -> 28444801 | D31: =IFERROR(C31/$B31,"") -> 9.821547 | E31: =OFFSET('25'!$E$66,$A$3,0) -> 12325828 | F31: =IFERROR(E31/$B31,"") -> 4.2559165 | G31: ='25'!$F$100*B31 -> 2162751 | H31: =IFERROR(G31/$B31,"") -> 0.74676425 | I31: ='25'!$F$98*'Discipline Analysis'!B31 -> 6919340 | J31: =IFERROR(I31/$B31,"") -> 2.3891404 | K31: ='25'!$F$99*'Discipline Analysis'!B31 -> 1906865 | L31: =IFERROR(K31/$B31,"") -> 0.6584108 | M31: =OFFSET('25'!$E$35,$A$3,0) -> 3473933 | N31: =IFERROR(M31/$B31,"") -> 1.199495 | O31: ='25'!$F$101*'Discipline Analysis'!B31 -> 0 | P31: =IFERROR(O31/$B31,"") -> 0 | Q31: ='25'!$F$102*'Discipline Analysis'!B31 -> 0 | R31: =IFERROR(Q31/$B31,"") -> 0 | S31: ='25'!$F$103*'Discipline Analysis'!B31 -> 679023 | T31: =IFERROR(S31/$B31,"") -> 0.23445607 | U31: ='25'!$F$104*'Discipline Analysis'!B31 -> 977061 | V31: =IFERROR(U31/$B31,"") -> 0.33736395 | X31: All Disciplines
A32: Lonestar | B32: =OFFSET('26'!$D$4,$A$3,0) -> 18452652 | C32: =OFFSET('26'!$E$4,$A$3,0) -> 166864847 | D32: =IFERROR(C32/$B32,"") -> 9.0428653 | E32: =OFFSET('26'!$E$66,$A$3,0) -> 65205085 | F32: =IFERROR(E32/$B32,"") -> 3.533643 | G32: ='26'!$F$100*B32 -> 38225105 | H32: =IFERROR(G32/$B32,"") -> 2.0715236 | I32: ='26'!$F$98*'Discipline Analysis'!B32 -> 22152412 | J32: =IFERROR(I32/$B32,"") -> 1.2005002 | K32: ='26'!$F$99*'Discipline Analysis'!B32 -> 19409964 | L32: =IFERROR(K32/$B32,"") -> 1.0518794 | M32: =OFFSET('26'!$E$35,$A$3,0) -> 14670920 | N32: =IFERROR(M32/$B32,"") -> 0.79505753 | O32: ='26'!$F$101*'Discipline Analysis'!B32 -> 0 | P32: =IFERROR(O32/$B32,"") -> 0 | Q32: ='26'!$F$102*'Discipline Analysis'!B32 -> 0 | R32: =IFERROR(Q32/$B32,"") -> 0 | S32: ='26'!$F$103*'Discipline Analysis'!B32 -> 2478963 | T32: =IFERROR(S32/$B32,"") -> 0.13434183 | U32: ='26'!$F$104*'Discipline Analysis'!B32 -> 4722398 | V32: =IFERROR(U32/$B32,"") -> 0.25591975
A33: Mclennan | B33: =OFFSET('27'!$D$4,$A$3,0) -> 3921638 | C33: =OFFSET('27'!$E$4,$A$3,0) -> 36014717 | D33: =IFERROR(C33/$B33,"") -> 9.1835904 | E33: =OFFSET('27'!$E$66,$A$3,0) -> 15880510 | F33: =IFERROR(E33/$B33,"") -> 4.0494584 | G33: ='27'!$F$100*B33 -> 1692239 | H33: =IFERROR(G33/$B33,"") -> 0.43151331 | I33: ='27'!$F$98*'Discipline Analysis'!B33 -> 7420171 | J33: =IFERROR(I33/$B33,"") -> 1.8921101 | K33: ='27'!$F$99*'Discipline Analysis'!B33 -> 2115731 | L33: =IFERROR(K33/$B33,"") -> 0.53950186 | M33: =OFFSET('27'!$E$35,$A$3,0) -> 7762841 | N33: =IFERROR(M33/$B33,"") -> 1.9794894 | O33: ='27'!$F$101*'Discipline Analysis'!B33 -> 0 | P33: =IFERROR(O33/$B33,"") -> 0 | Q33: ='27'!$F$102*'Discipline Analysis'!B33 -> 852915 | R33: =IFERROR(Q33/$B33,"") -> 0.21748948 | S33: ='27'!$F$103*'Discipline Analysis'!B33 -> 0 | T33: =IFERROR(S33/$B33,"") -> 0 | U33: ='27'!$F$104*'Discipline Analysis'!B33 -> 290310 | V33: =IFERROR(U33/$B33,"") -> 0.07402774
A34: Midland | B34: =OFFSET('28'!$D$4,$A$3,0) -> 2688607 | C34: =OFFSET('28'!$E$4,$A$3,0) -> 27584805 | D34: =IFERROR(C34/$B34,"") -> 10.259887 | E34: =OFFSET('28'!$E$66,$A$3,0) -> 10962380 | F34: =IFERROR(E34/$B34,"") -> 4.0773456 | G34: ='28'!$F$100*B34 -> 4284806 | H34: =IFERROR(G34/$B34,"") -> 1.59369 | I34: ='28'!$F$98*'Discipline Analysis'!B34 -> 4190665 | J34: =IFERROR(I34/$B34,"") -> 1.5586752 | K34: ='28'!$F$99*'Discipline Analysis'!B34 -> 2032962 | L34: =IFERROR(K34/$B34,"") -> 0.75613952 | M34: =OFFSET('28'!$E$35,$A$3,0) -> 4458507 | N34: =IFERROR(M34/$B34,"") -> 1.6582963 | O34: ='28'!$F$101*'Discipline Analysis'!B34 -> 0 | P34: =IFERROR(O34/$B34,"") -> 0 | Q34: ='28'!$F$102*'Discipline Analysis'!B34 -> 21696 | R34: =IFERROR(Q34/$B34,"") -> 0.0080696063 | S34: ='28'!$F$103*'Discipline Analysis'!B34 -> 568701 | T34: =IFERROR(S34/$B34,"") -> 0.21152255 | U34: ='28'!$F$104*'Discipline Analysis'!B34 -> 1065088 | V34: =IFERROR(U34/$B34,"") -> 0.39614864
A35: Navarro | B35: =OFFSET('29'!$D$4,$A$3,0) -> 4391435 | C35: =OFFSET('29'!$E$4,$A$3,0) -> 21320555 | D35: =IFERROR(C35/$B35,"") -> 4.8550314 | E35: =OFFSET('29'!$E$66,$A$3,0) -> 10603186 | F35: =IFERROR(E35/$B35,"") -> 2.4145151 | G35: ='29'!$F$100*B35 -> 2516684 | H35: =IFERROR(G35/$B35,"") -> 0.57308921 | I35: ='29'!$F$98*'Discipline Analysis'!B35 -> 3816959 | J35: =IFERROR(I35/$B35,"") -> 0.86918262 | K35: ='29'!$F$99*'Discipline Analysis'!B35 -> 2291059 | L35: =IFERROR(K35/$B35,"") -> 0.52171078 | M35: =OFFSET('29'!$E$35,$A$3,0) -> 985976 | N35: =IFERROR(M35/$B35,"") -> 0.22452251 | O35: ='29'!$F$101*'Discipline Analysis'!B35 -> 0 | P35: =IFERROR(O35/$B35,"") -> 0 | Q35: ='29'!$F$102*'Discipline Analysis'!B35 -> 0 | R35: =IFERROR(Q35/$B35,"") -> 0 | S35: ='29'!$F$103*'Discipline Analysis'!B35 -> 388557 | T35: =IFERROR(S35/$B35,"") -> 0.088480645 | U35: ='29'!$F$104*'Discipline Analysis'!B35 -> 718134 | V35: =IFERROR(U35/$B35,"") -> 0.1635306
A36: North Central Texas | B36: =OFFSET('30'!$D$4,$A$3,0) -> 3113657 | C36: =OFFSET('30'!$E$4,$A$3,0) -> 18359956 | D36: =IFERROR(C36/$B36,"") -> 5.8965891 | E36: =OFFSET('30'!$E$66,$A$3,0) -> 8602149 | F36: =IFERROR(E36/$B36,"") -> 2.7627157 | G36: ='30'!$F$100*B36 -> 2054453 | H36: =IFERROR(G36/$B36,"") -> 0.65981995 | I36: ='30'!$F$98*'Discipline Analysis'!B36 -> 2954319 | J36: =IFERROR(I36/$B36,"") -> 0.94882609 | K36: ='30'!$F$99*'Discipline Analysis'!B36 -> 1330436 | L36: =IFERROR(K36/$B36,"") -> 0.42729048 | M36: =OFFSET('30'!$E$35,$A$3,0) -> 2633215 | N36: =IFERROR(M36/$B36,"") -> 0.84569848 | O36: ='30'!$F$101*'Discipline Analysis'!B36 -> 85056 | P36: =IFERROR(O36/$B36,"") -> 0.027317074 | Q36: ='30'!$F$102*'Discipline Analysis'!B36 -> 0 | R36: =IFERROR(Q36/$B36,"") -> 0 | S36: ='30'!$F$103*'Discipline Analysis'!B36 -> 464026 | T36: =IFERROR(S36/$B36,"") -> 0.14902926 | U36: ='30'!$F$104*'Discipline Analysis'!B36 -> 236302 | V36: =IFERROR(U36/$B36,"") -> 0.07589211
A37: Northeast Texas | B37: =OFFSET('31'!$D$4,$A$3,0) -> 1176109 | C37: =OFFSET('31'!$E$4,$A$3,0) -> 9366376 | D37: =IFERROR(C37/$B37,"") -> 7.9638673 | E37: =OFFSET('31'!$E$66,$A$3,0) -> 4756446 | F37: =IFERROR(E37/$B37,"") -> 4.0442221 | G37: ='31'!$F$100*B37 -> 830127 | H37: =IFERROR(G37/$B37,"") -> 0.70582489 | I37: ='31'!$F$98*'Discipline Analysis'!B37 -> 2115251 | J37: =IFERROR(I37/$B37,"") -> 1.7985161 | K37: ='31'!$F$99*'Discipline Analysis'!B37 -> 722639 | L37: =IFERROR(K37/$B37,"") -> 0.614432 | M37: =OFFSET('31'!$E$35,$A$3,0) -> 795544 | N37: =IFERROR(M37/$B37,"") -> 0.6764203 | O37: ='31'!$F$101*'Discipline Analysis'!B37 -> 0 | P37: =IFERROR(O37/$B37,"") -> 0 | Q37: ='31'!$F$102*'Discipline Analysis'!B37 -> 0 | R37: =IFERROR(Q37/$B37,"") -> 0 | S37: ='31'!$F$103*'Discipline Analysis'!B37 -> 0 | T37: =IFERROR(S37/$B37,"") -> 0 | U37: ='31'!$F$104*'Discipline Analysis'!B37 -> 146369 | V37: =IFERROR(U37/$B37,"") -> 0.1244519
A38: Odessa | B38: =OFFSET('32'!$D$4,$A$3,0) -> 2136205 | C38: =OFFSET('32'!$E$4,$A$3,0) -> 21099064 | D38: =IFERROR(C38/$B38,"") -> 9.876891 | E38: =OFFSET('32'!$E$66,$A$3,0) -> 8007508 | F38: =IFERROR(E38/$B38,"") -> 3.7484736 | G38: ='32'!$F$100*B38 -> 2650347 | H38: =IFERROR(G38/$B38,"") -> 1.2406801 | I38: ='32'!$F$98*'Discipline Analysis'!B38 -> 3878845 | J38: =IFERROR(I38/$B38,"") -> 1.8157644 | K38: ='32'!$F$99*'Discipline Analysis'!B38 -> 2220556 | L38: =IFERROR(K38/$B38,"") -> 1.0394864 | M38: =OFFSET('32'!$E$35,$A$3,0) -> 2127314 | N38: =IFERROR(M38/$B38,"") -> 0.99583795 | O38: ='32'!$F$101*'Discipline Analysis'!B38 -> 0 | P38: =IFERROR(O38/$B38,"") -> 0 | Q38: ='32'!$F$102*'Discipline Analysis'!B38 -> 595276 | R38: =IFERROR(Q38/$B38,"") -> 0.27866052 | S38: ='32'!$F$103*'Discipline Analysis'!B38 -> 534319 | T38: =IFERROR(S38/$B38,"") -> 0.25012534 | U38: ='32'!$F$104*'Discipline Analysis'!B38 -> 1084899 | V38: =IFERROR(U38/$B38,"") -> 0.50786278
A39: Panola | B39: =OFFSET('33'!$D$4,$A$3,0) -> 1018665 | C39: =OFFSET('33'!$E$4,$A$3,0) -> 9725576 | D39: =IFERROR(C39/$B39,"") -> 9.5473743 | E39: =OFFSET('33'!$E$66,$A$3,0) -> 3927404 | F39: =IFERROR(E39/$B39,"") -> 3.8554422 | G39: ='33'!$F$100*B39 -> 1925992 | H39: =IFERROR(G39/$B39,"") -> 1.890702 | I39: ='33'!$F$98*'Discipline Analysis'!B39 -> 1523029 | J39: =IFERROR(I39/$B39,"") -> 1.4951225 | K39: ='33'!$F$99*'Discipline Analysis'!B39 -> 798404 | L39: =IFERROR(K39/$B39,"") -> 0.78377484 | M39: =OFFSET('33'!$E$35,$A$3,0) -> 1055380 | N39: =IFERROR(M39/$B39,"") -> 1.0360423 | O39: ='33'!$F$101*'Discipline Analysis'!B39 -> 0 | P39: =IFERROR(O39/$B39,"") -> 0 | Q39: ='33'!$F$102*'Discipline Analysis'!B39 -> 0 | R39: =IFERROR(Q39/$B39,"") -> 0 | S39: ='33'!$F$103*'Discipline Analysis'!B39 -> 195125 | T39: =IFERROR(S39/$B39,"") -> 0.19154972 | U39: ='33'!$F$104*'Discipline Analysis'!B39 -> 300242 | V39: =IFERROR(U39/$B39,"") -> 0.29474067
A40: Paris | B40: =OFFSET('34'!$D$4,$A$3,0) -> 2509298 | C40: =OFFSET('34'!$E$4,$A$3,0) -> 13129915 | D40: =IFERROR(C40/$B40,"") -> 5.2325053 | E40: =OFFSET('34'!$E$66,$A$3,0) -> 6716456 | F40: =IFERROR(E40/$B40,"") -> 2.6766275 | G40: ='34'!$F$100*B40 -> 972203 | H40: =IFERROR(G40/$B40,"") -> 0.38744023 | I40: ='34'!$F$98*'Discipline Analysis'!B40 -> 2265242 | J40: =IFERROR(I40/$B40,"") -> 0.90273933 | K40: ='34'!$F$99*'Discipline Analysis'!B40 -> 1275833 | L40: =IFERROR(K40/$B40,"") -> 0.5084422 | M40: =OFFSET('34'!$E$35,$A$3,0) -> 1548361 | N40: =IFERROR(M40/$B40,"") -> 0.61704947 | O40: ='34'!$F$101*'Discipline Analysis'!B40 -> 0 | P40: =IFERROR(O40/$B40,"") -> 0 | Q40: ='34'!$F$102*'Discipline Analysis'!B40 -> 0 | R40: =IFERROR(Q40/$B40,"") -> 0 | S40: ='34'!$F$103*'Discipline Analysis'!B40 -> 0 | T40: =IFERROR(S40/$B40,"") -> 0 | U40: ='34'!$F$104*'Discipline Analysis'!B40 -> 351820 | V40: =IFERROR(U40/$B40,"") -> 0.14020654
A41: Ranger | B41: =OFFSET('35'!$D$4,$A$3,0) -> 414961 | C41: =OFFSET('35'!$E$4,$A$3,0) -> 2777146 | D41: =IFERROR(C41/$B41,"") -> 6.692547 | E41: =OFFSET('35'!$E$66,$A$3,0) -> 1212088 | F41: =IFERROR(E41/$B41,"") -> 2.9209685 | G41: ='35'!$F$100*B41 -> 235087 | H41: =IFERROR(G41/$B41,"") -> 0.56652794 | I41: ='35'!$F$98*'Discipline Analysis'!B41 -> 648793 | J41: =IFERROR(I41/$B41,"") -> 1.5635036 | K41: ='35'!$F$99*'Discipline Analysis'!B41 -> 223346 | L41: =IFERROR(K41/$B41,"") -> 0.53823371 | M41: =OFFSET('35'!$E$35,$A$3,0) -> 87345 | N41: =IFERROR(M41/$B41,"") -> 0.21048966 | O41: ='35'!$F$101*'Discipline Analysis'!B41 -> 0 | P41: =IFERROR(O41/$B41,"") -> 0 | Q41: ='35'!$F$102*'Discipline Analysis'!B41 -> 127776 | R41: =IFERROR(Q41/$B41,"") -> 0.30792291 | S41: ='35'!$F$103*'Discipline Analysis'!B41 -> 214890 | T41: =IFERROR(S41/$B41,"") -> 0.51785589 | U41: ='35'!$F$104*'Discipline Analysis'!B41 -> 27821 | V41: =IFERROR(U41/$B41,"") -> 0.067044855
A42: San Jacinto | B42: =OFFSET('36'!$D$4,$A$3,0) -> 11143508 | C42: =OFFSET('36'!$E$4,$A$3,0) -> 91502268 | D42: =IFERROR(C42/$B42,"") -> 8.2112624 | E42: =OFFSET('36'!$E$66,$A$3,0) -> 39431481 | F42: =IFERROR(E42/$B42,"") -> 3.538516 | G42: ='36'!$F$100*B42 -> 8895786 | H42: =IFERROR(G42/$B42,"") -> 0.79829314 | I42: ='36'!$F$98*'Discipline Analysis'!B42 -> 16241788 | J42: =IFERROR(I42/$B42,"") -> 1.4575112 | K42: ='36'!$F$99*'Discipline Analysis'!B42 -> 9698284 | L42: =IFERROR(K42/$B42,"") -> 0.87030799 | M42: =OFFSET('36'!$E$35,$A$3,0) -> 12485404 | N42: =IFERROR(M42/$B42,"") -> 1.1204195 | O42: ='36'!$F$101*'Discipline Analysis'!B42 -> 0 | P42: =IFERROR(O42/$B42,"") -> 0 | Q42: ='36'!$F$102*'Discipline Analysis'!B42 -> 0 | R42: =IFERROR(Q42/$B42,"") -> 0 | S42: ='36'!$F$103*'Discipline Analysis'!B42 -> 2681931 | T42: =IFERROR(S42/$B42,"") -> 0.24067206 | U42: ='36'!$F$104*'Discipline Analysis'!B42 -> 2067594 | V42: =IFERROR(U42/$B42,"") -> 0.18554247
A43: South Plains | B43: =OFFSET('37'!$D$4,$A$3,0) -> 4415370 | C43: =OFFSET('37'!$E$4,$A$3,0) -> 28369105 | D43: =IFERROR(C43/$B43,"") -> 6.4250799 | E43: =OFFSET('37'!$E$66,$A$3,0) -> 15912997 | F43: =IFERROR(E43/$B43,"") -> 3.6040008 | G43: ='37'!$F$100*B43 -> 1818219 | H43: =IFERROR(G43/$B43,"") -> 0.41179312 | I43: ='37'!$F$98*'Discipline Analysis'!B43 -> 3378691 | J43: =IFERROR(I43/$B43,"") -> 0.7652113 | K43: ='37'!$F$99*'Discipline Analysis'!B43 -> 3618245 | L43: =IFERROR(K43/$B43,"") -> 0.81946587 | M43: =OFFSET('37'!$E$35,$A$3,0) -> 1304433 | N43: =IFERROR(M43/$B43,"") -> 0.29543005 | O43: ='37'!$F$101*'Discipline Analysis'!B43 -> 0 | P43: =IFERROR(O43/$B43,"") -> 0 | Q43: ='37'!$F$102*'Discipline Analysis'!B43 -> 87489 | R43: =IFERROR(Q43/$B43,"") -> 0.019814647 | S43: ='37'!$F$103*'Discipline Analysis'!B43 -> 837464 | T43: =IFERROR(S43/$B43,"") -> 0.18967017 | U43: ='37'!$F$104*'Discipline Analysis'!B43 -> 1411567 | V43: =IFERROR(U43/$B43,"") -> 0.31969393
A44: South Texas | B44: =OFFSET('38'!$D$4,$A$3,0) -> 8927976 | C44: =OFFSET('38'!$E$4,$A$3,0) -> 74791503 | D44: =IFERROR(C44/$B44,"") -> 8.377207 | E44: =OFFSET('38'!$E$66,$A$3,0) -> 31617963 | F44: =IFERROR(E44/$B44,"") -> 3.541448 | G44: ='38'!$F$100*B44 -> 5669832 | H44: =IFERROR(G44/$B44,"") -> 0.63506354 | I44: ='38'!$F$98*'Discipline Analysis'!B44 -> 14643946 | J44: =IFERROR(I44/$B44,"") -> 1.6402313 | K44: ='38'!$F$99*'Discipline Analysis'!B44 -> 6858009 | L44: =IFERROR(K44/$B44,"") -> 0.76814823 | M44: =OFFSET('38'!$E$35,$A$3,0) -> 11337943 | N44: =IFERROR(M44/$B44,"") -> 1.2699343 | O44: ='38'!$F$101*'Discipline Analysis'!B44 -> 0 | P44: =IFERROR(O44/$B44,"") -> 0 | Q44: ='38'!$F$102*'Discipline Analysis'!B44 -> 0 | R44: =IFERROR(Q44/$B44,"") -> 0 | S44: ='38'!$F$103*'Discipline Analysis'!B44 -> 2328106 | T44: =IFERROR(S44/$B44,"") -> 0.26076526 | U44: ='38'!$F$104*'Discipline Analysis'!B44 -> 2335704 | V44: =IFERROR(U44/$B44,"") -> 0.26161629
A45: Southwest Texas | B45: =OFFSET('39'!$D$4,$A$3,0) -> 2172315 | C45: =OFFSET('39'!$E$4,$A$3,0) -> 15709600 | D45: =IFERROR(C45/$B45,"") -> 7.231732 | E45: =OFFSET('39'!$E$66,$A$3,0) -> 6875597 | F45: =IFERROR(E45/$B45,"") -> 3.1651013 | G45: ='39'!$F$100*B45 -> 1851305 | H45: =IFERROR(G45/$B45,"") -> 0.85222677 | I45: ='39'!$F$98*'Discipline Analysis'!B45 -> 3161648 | J45: =IFERROR(I45/$B45,"") -> 1.455428 | K45: ='39'!$F$99*'Discipline Analysis'!B45 -> 1408929 | L45: =IFERROR(K45/$B45,"") -> 0.64858411 | M45: =OFFSET('39'!$E$35,$A$3,0) -> 1881011 | N45: =IFERROR(M45/$B45,"") -> 0.86590158 | O45: ='39'!$F$101*'Discipline Analysis'!B45 -> 0 | P45: =IFERROR(O45/$B45,"") -> 0 | Q45: ='39'!$F$102*'Discipline Analysis'!B45 -> 0 | R45: =IFERROR(Q45/$B45,"") -> 0 | S45: ='39'!$F$103*'Discipline Analysis'!B45 -> 246260 | T45: =IFERROR(S45/$B45,"") -> 0.11336293 | U45: ='39'!$F$104*'Discipline Analysis'!B45 -> 284850 | V45: =IFERROR(U45/$B45,"") -> 0.13112739
A46: Tarrant | B46: =OFFSET('40'!$D$4,$A$3,0) -> 15950728 | C46: =OFFSET('40'!$E$4,$A$3,0) -> 127688204 | D46: =IFERROR(C46/$B46,"") -> 8.0051647 | E46: =OFFSET('40'!$E$66,$A$3,0) -> 51589681 | F46: =IFERROR(E46/$B46,"") -> 3.2343151 | G46: ='40'!$F$100*B46 -> 11644335 | H46: =IFERROR(G46/$B46,"") -> 0.73001903 | I46: ='40'!$F$98*'Discipline Analysis'!B46 -> 19358103 | J46: =IFERROR(I46/$B46,"") -> 1.2136188 | K46: ='40'!$F$99*'Discipline Analysis'!B46 -> 13164664 | L46: =IFERROR(K46/$B46,"") -> 0.82533311 | M46: =OFFSET('40'!$E$35,$A$3,0) -> 23535105 | N46: =IFERROR(M46/$B46,"") -> 1.4754878 | O46: ='40'!$F$101*'Discipline Analysis'!B46 -> 0 | P46: =IFERROR(O46/$B46,"") -> 0 | Q46: ='40'!$F$102*'Discipline Analysis'!B46 -> 578017 | R46: =IFERROR(Q46/$B46,"") -> 0.036237656 | S46: ='40'!$F$103*'Discipline Analysis'!B46 -> 2938375 | T46: =IFERROR(S46/$B46,"") -> 0.18421573 | U46: ='40'!$F$104*'Discipline Analysis'!B46 -> 4879924 | V46: =IFERROR(U46/$B46,"") -> 0.30593738
A47: Temple | B47: =OFFSET('41'!$D$4,$A$3,0) -> 2333910 | C47: =OFFSET('41'!$E$4,$A$3,0) -> 17853380 | D47: =IFERROR(C47/$B47,"") -> 7.649558 | E47: =OFFSET('41'!$E$66,$A$3,0) -> 7611330 | F47: =IFERROR(E47/$B47,"") -> 3.2611926 | G47: ='41'!$F$100*B47 -> 1605144 | H47: =IFERROR(G47/$B47,"") -> 0.68774888 | I47: ='41'!$F$98*'Discipline Analysis'!B47 -> 4090396 | J47: =IFERROR(I47/$B47,"") -> 1.7525937 | K47: ='41'!$F$99*'Discipline Analysis'!B47 -> 1248411 | L47: =IFERROR(K47/$B47,"") -> 0.53490109 | M47: =OFFSET('41'!$E$35,$A$3,0) -> 2349470 | N47: =IFERROR(M47/$B47,"") -> 1.0066669 | O47: ='41'!$F$101*'Discipline Analysis'!B47 -> 0 | P47: =IFERROR(O47/$B47,"") -> 0 | Q47: ='41'!$F$102*'Discipline Analysis'!B47 -> 0 | R47: =IFERROR(Q47/$B47,"") -> 0 | S47: ='41'!$F$103*'Discipline Analysis'!B47 -> 261028 | T47: =IFERROR(S47/$B47,"") -> 0.1118415 | U47: ='41'!$F$104*'Discipline Analysis'!B47 -> 687601 | V47: =IFERROR(U47/$B47,"") -> 0.29461333
A48: Texarkana | B48: =OFFSET('42'!$D$4,$A$3,0) -> 0 | C48: =OFFSET('42'!$E$4,$A$3,0) -> 0 | D48: =IFERROR(C48/$B48,"") | E48: =OFFSET('42'!$E$66,$A$3,0) -> 0 | F48: =IFERROR(E48/$B48,"") | G48: ='42'!$F$100*B48 -> 0 | H48: =IFERROR(G48/$B48,"") | I48: ='42'!$F$98*'Discipline Analysis'!B48 -> 0 | J48: =IFERROR(I48/$B48,"") | K48: ='42'!$F$99*'Discipline Analysis'!B48 -> 0 | L48: =IFERROR(K48/$B48,"") | M48: =OFFSET('42'!$E$35,$A$3,0) -> 0 | N48: =IFERROR(M48/$B48,"") | O48: ='42'!$F$101*'Discipline Analysis'!B48 -> 0 | P48: =IFERROR(O48/$B48,"") | Q48: ='42'!$F$102*'Discipline Analysis'!B48 -> 0 | R48: =IFERROR(Q48/$B48,"") | S48: ='42'!$F$103*'Discipline Analysis'!B48 -> 0 | T48: =IFERROR(S48/$B48,"") | U48: ='42'!$F$104*'Discipline Analysis'!B48 -> 0 | V48: =IFERROR(U48/$B48,"")
A49: Texas Southmost | B49: =OFFSET('43'!$D$4,$A$3,0) -> 0 | C49: =OFFSET('43'!$E$4,$A$3,0) -> 0 | D49: =IFERROR(C49/$B49,"") | E49: =OFFSET('43'!$E$66,$A$3,0) -> 0 | F49: =IFERROR(E49/$B49,"") | G49: ='43'!$F$100*B49 -> 0 | H49: =IFERROR(G49/$B49,"") | I49: ='43'!$F$98*'Discipline Analysis'!B49 -> 0 | J49: =IFERROR(I49/$B49,"") | K49: ='43'!$F$99*'Discipline Analysis'!B49 -> 0 | L49: =IFERROR(K49/$B49,"") | M49: =OFFSET('43'!$E$35,$A$3,0) -> 0 | N49: =IFERROR(M49/$B49,"") | O49: ='43'!$F$101*'Discipline Analysis'!B49 -> 0 | P49: =IFERROR(O49/$B49,"") | Q49: ='43'!$F$102*'Discipline Analysis'!B49 -> 0 | R49: =IFERROR(Q49/$B49,"") | S49: ='43'!$F$103*'Discipline Analysis'!B49 -> 0 | T49: =IFERROR(S49/$B49,"") | U49: ='43'!$F$104*'Discipline Analysis'!B49 -> 0 | V49: =IFERROR(U49/$B49,"")
A50: Trinity Valley | B50: =OFFSET('44'!$D$4,$A$3,0) -> 3254649 | C50: =OFFSET('44'!$E$4,$A$3,0) -> 19472846 | D50: =IFERROR(C50/$B50,"") -> 5.9830863 | E50: =OFFSET('44'!$E$66,$A$3,0) -> 9325461 | F50: =IFERROR(E50/$B50,"") -> 2.865274 | G50: ='44'!$F$100*B50 -> 2701938 | H50: =IFERROR(G50/$B50,"") -> 0.830178 | I50: ='44'!$F$98*'Discipline Analysis'!B50 -> 2404908 | J50: =IFERROR(I50/$B50,"") -> 0.7389147 | K50: ='44'!$F$99*'Discipline Analysis'!B50 -> 1741394 | L50: =IFERROR(K50/$B50,"") -> 0.53504817 | M50: =OFFSET('44'!$E$35,$A$3,0) -> 2107952 | N50: =IFERROR(M50/$B50,"") -> 0.64767414 | O50: ='44'!$F$101*'Discipline Analysis'!B50 -> 0 | P50: =IFERROR(O50/$B50,"") -> 0 | Q50: ='44'!$F$102*'Discipline Analysis'!B50 -> 363 | R50: =IFERROR(Q50/$B50,"") -> 0.00011153276 | S50: ='44'!$F$103*'Discipline Analysis'!B50 -> 410239 | T50: =IFERROR(S50/$B50,"") -> 0.12604708 | U50: ='44'!$F$104*'Discipline Analysis'!B50 -> 780591 | V50: =IFERROR(U50/$B50,"") -> 0.23983877
A51: Tyler | B51: =OFFSET('45'!$D$4,$A$3,0) -> 5123439 | C51: =OFFSET('45'!$E$4,$A$3,0) -> 37809202 | D51: =IFERROR(C51/$B51,"") -> 7.379653 | E51: =OFFSET('45'!$E$66,$A$3,0) -> 15791200 | F51: =IFERROR(E51/$B51,"") -> 3.0821485 | G51: ='45'!$F$100*B51 -> 1843441 | H51: =IFERROR(G51/$B51,"") -> 0.3598054 | I51: ='45'!$F$98*'Discipline Analysis'!B51 -> 7115771 | J51: =IFERROR(I51/$B51,"") -> 1.3888662 | K51: ='45'!$F$99*'Discipline Analysis'!B51 -> 5431335 | L51: =IFERROR(K51/$B51,"") -> 1.0600956 | M51: =OFFSET('45'!$E$35,$A$3,0) -> 4972311 | N51: =IFERROR(M51/$B51,"") -> 0.97050263 | O51: ='45'!$F$101*'Discipline Analysis'!B51 -> 0 | P51: =IFERROR(O51/$B51,"") -> 0 | Q51: ='45'!$F$102*'Discipline Analysis'!B51 -> 767792 | R51: =IFERROR(Q51/$B51,"") -> 0.14985872 | S51: ='45'!$F$103*'Discipline Analysis'!B51 -> 711180 | T51: =IFERROR(S51/$B51,"") -> 0.13880911 | U51: ='45'!$F$104*'Discipline Analysis'!B51 -> 1176172 | V51: =IFERROR(U51/$B51,"") -> 0.2295669
A52: Vernon | B52: =OFFSET('46'!$D$4,$A$3,0) -> 1560346 | C52: =OFFSET('46'!$E$4,$A$3,0) -> 9948125 | D52: =IFERROR(C52/$B52,"") -> 6.3755891 | E52: =OFFSET('46'!$E$66,$A$3,0) -> 4292319 | F52: =IFERROR(E52/$B52,"") -> 2.7508764 | G52: ='46'!$F$100*B52 -> 1819355 | H52: =IFERROR(G52/$B52,"") -> 1.1659946 | I52: ='46'!$F$98*'Discipline Analysis'!B52 -> 2052394 | J52: =IFERROR(I52/$B52,"") -> 1.3153454 | K52: ='46'!$F$99*'Discipline Analysis'!B52 -> 1163208 | L52: =IFERROR(K52/$B52,"") -> 0.74548081 | M52: =OFFSET('46'!$E$35,$A$3,0) -> 245592 | N52: =IFERROR(M52/$B52,"") -> 0.15739586 | O52: ='46'!$F$101*'Discipline Analysis'!B52 -> 0 | P52: =IFERROR(O52/$B52,"") -> 0 | Q52: ='46'!$F$102*'Discipline Analysis'!B52 -> 0 | R52: =IFERROR(Q52/$B52,"") -> 0 | S52: ='46'!$F$103*'Discipline Analysis'!B52 -> 159285 | T52: =IFERROR(S52/$B52,"") -> 0.10208313 | U52: ='46'!$F$104*'Discipline Analysis'!B52 -> 215972 | V52: =IFERROR(U52/$B52,"") -> 0.13841289
A53: Victoria | B53: =OFFSET('47'!$D$4,$A$3,0) -> 1814599 | C53: =OFFSET('47'!$E$4,$A$3,0) -> 17235576 | D53: =IFERROR(C53/$B53,"") -> 9.4982836 | E53: =OFFSET('47'!$E$66,$A$3,0) -> 7196893 | F53: =IFERROR(E53/$B53,"") -> 3.9661066 | G53: ='47'!$F$100*B53 -> 1456103 | H53: =IFERROR(G53/$B53,"") -> 0.80243789 | I53: ='47'!$F$98*'Discipline Analysis'!B53 -> 2661091 | J53: =IFERROR(I53/$B53,"") -> 1.4664898 | K53: ='47'!$F$99*'Discipline Analysis'!B53 -> 1546662 | L53: =IFERROR(K53/$B53,"") -> 0.85234369 | M53: =OFFSET('47'!$E$35,$A$3,0) -> 3528567 | N53: =IFERROR(M53/$B53,"") -> 1.9445437 | O53: ='47'!$F$101*'Discipline Analysis'!B53 -> 0 | P53: =IFERROR(O53/$B53,"") -> 0 | Q53: ='47'!$F$102*'Discipline Analysis'!B53 -> 111543 | R53: =IFERROR(Q53/$B53,"") -> 0.061469779 | S53: ='47'!$F$103*'Discipline Analysis'!B53 -> 249527 | T53: =IFERROR(S53/$B53,"") -> 0.13751082 | U53: ='47'!$F$104*'Discipline Analysis'!B53 -> 485190 | V53: =IFERROR(U53/$B53,"") -> 0.26738139
A54: Weatherford | B54: =OFFSET('48'!$D$4,$A$3,0) -> 2242748 | C54: =OFFSET('48'!$E$4,$A$3,0) -> 18428239 | D54: =IFERROR(C54/$B54,"") -> 8.2168121 | E54: =OFFSET('48'!$E$66,$A$3,0) -> 7604690 | F54: =IFERROR(E54/$B54,"") -> 3.3907911 | G54: ='48'!$F$100*B54 -> 1152110 | H54: =IFERROR(G54/$B54,"") -> 0.51370462 | I54: ='48'!$F$98*'Discipline Analysis'!B54 -> 5084425 | J54: =IFERROR(I54/$B54,"") -> 2.2670514 | K54: ='48'!$F$99*'Discipline Analysis'!B54 -> 1510657 | L54: =IFERROR(K54/$B54,"") -> 0.67357412 | M54: =OFFSET('48'!$E$35,$A$3,0) -> 2554100 | N54: =IFERROR(M54/$B54,"") -> 1.1388261 | O54: ='48'!$F$101*'Discipline Analysis'!B54 -> 0 | P54: =IFERROR(O54/$B54,"") -> 0 | Q54: ='48'!$F$102*'Discipline Analysis'!B54 -> 0 | R54: =IFERROR(Q54/$B54,"") -> 0 | S54: ='48'!$F$103*'Discipline Analysis'!B54 -> 330617 | T54: =IFERROR(S54/$B54,"") -> 0.14741603 | U54: ='48'!$F$104*'Discipline Analysis'!B54 -> 191640 | V54: =IFERROR(U54/$B54,"") -> 0.085448744
A55: Western Texas | B55: =OFFSET('49'!$D$4,$A$3,0) -> 1254294 | C55: =OFFSET('49'!$E$4,$A$3,0) -> 6840250 | D55: =IFERROR(C55/$B55,"") -> 5.4534663 | E55: =OFFSET('49'!$E$66,$A$3,0) -> 2644459 | F55: =IFERROR(E55/$B55,"") -> 2.1083247 | G55: ='49'!$F$100*B55 -> 668377 | H55: =IFERROR(G55/$B55,"") -> 0.53287108 | I55: ='49'!$F$98*'Discipline Analysis'!B55 -> 2140554 | J55: =IFERROR(I55/$B55,"") -> 1.7065808 | K55: ='49'!$F$99*'Discipline Analysis'!B55 -> 401906 | L55: =IFERROR(K55/$B55,"") -> 0.32042408 | M55: =OFFSET('49'!$E$35,$A$3,0) -> 337997 | N55: =IFERROR(M55/$B55,"") -> 0.26947191 | O55: ='49'!$F$101*'Discipline Analysis'!B55 -> 0 | P55: =IFERROR(O55/$B55,"") -> 0 | Q55: ='49'!$F$102*'Discipline Analysis'!B55 -> 366978 | R55: =IFERROR(Q55/$B55,"") -> 0.29257734 | S55: ='49'!$F$103*'Discipline Analysis'!B55 -> 205107 | T55: =IFERROR(S55/$B55,"") -> 0.16352386 | U55: ='49'!$F$104*'Discipline Analysis'!B55 -> 74872 | V55: =IFERROR(U55/$B55,"") -> 0.059692544
A56: Wharton | B56: =OFFSET('50'!$D$4,$A$3,0) -> 2496402 | C56: =OFFSET('50'!$E$4,$A$3,0) -> 22124259 | D56: =IFERROR(C56/$B56,"") -> 8.8624585 | E56: =OFFSET('50'!$E$66,$A$3,0) -> 9391065 | F56: =IFERROR(E56/$B56,"") -> 3.76184 | G56: ='50'!$F$100*B56 -> 2381023 | H56: =IFERROR(G56/$B56,"") -> 0.95378188 | I56: ='50'!$F$98*'Discipline Analysis'!B56 -> 4886266 | J56: =IFERROR(I56/$B56,"") -> 1.9573234 | K56: ='50'!$F$99*'Discipline Analysis'!B56 -> 1628557 | L56: =IFERROR(K56/$B56,"") -> 0.65236168 | M56: =OFFSET('50'!$E$35,$A$3,0) -> 1992880 | N56: =IFERROR(M56/$B56,"") -> 0.79830091 | O56: ='50'!$F$101*'Discipline Analysis'!B56 -> 0 | P56: =IFERROR(O56/$B56,"") -> 0 | Q56: ='50'!$F$102*'Discipline Analysis'!B56 -> 601920 | R56: =IFERROR(Q56/$B56,"") -> 0.24111501 | S56: ='50'!$F$103*'Discipline Analysis'!B56 -> 539061 | T56: =IFERROR(S56/$B56,"") -> 0.21593517 | U56: ='50'!$F$104*'Discipline Analysis'!B56 -> 703487 | V56: =IFERROR(U56/$B56,"") -> 0.28180037
A57: TSTC-Harlingen | B57: =OFFSET('51'!$D$4,$A$3,0) -> 2979157 | C57: =OFFSET('51'!$E$4,$A$3,0) -> 21620132 | D57: =IFERROR(C57/$B57,"") -> 7.2571308 | E57: =OFFSET('51'!$E$66,$A$3,0) -> 7795169 | F57: =IFERROR(E57/$B57,"") -> 2.6165687 | G57: ='51'!$F$100*B57 -> 1265817 | H57: =IFERROR(G57/$B57,"") -> 0.424891 | I57: ='51'!$F$98*'Discipline Analysis'!B57 -> 2917595 | J57: =IFERROR(I57/$B57,"") -> 0.97933577 | K57: ='51'!$F$99*'Discipline Analysis'!B57 -> 2325335 | L57: =IFERROR(K57/$B57,"") -> 0.78053456 | M57: =OFFSET('51'!$E$35,$A$3,0) -> 5686810 | N57: =IFERROR(M57/$B57,"") -> 1.9088655 | O57: ='51'!$F$101*'Discipline Analysis'!B57 -> 288457 | P57: =IFERROR(O57/$B57,"") -> 0.096825041 | Q57: ='51'!$F$102*'Discipline Analysis'!B57 -> 579774 | R57: =IFERROR(Q57/$B57,"") -> 0.19461009 | S57: ='51'!$F$103*'Discipline Analysis'!B57 -> 583508 | T57: =IFERROR(S57/$B57,"") -> 0.19586346 | U57: ='51'!$F$104*'Discipline Analysis'!B57 -> 177667 | V57: =IFERROR(U57/$B57,"") -> 0.059636669
A58: TSTC-West Texas | B58: =OFFSET('52'!$D$4,$A$3,0) -> 1232683 | C58: =OFFSET('52'!$E$4,$A$3,0) -> 13225931 | D58: =IFERROR(C58/$B58,"") -> 10.729385 | E58: =OFFSET('52'!$E$66,$A$3,0) -> 4300013 | F58: =IFERROR(E58/$B58,"") -> 3.4883364 | G58: ='52'!$F$100*B58 -> 2334754 | H58: =IFERROR(G58/$B58,"") -> 1.8940425 | I58: ='52'!$F$98*'Discipline Analysis'!B58 -> 1769270 | J58: =IFERROR(I58/$B58,"") -> 1.4353001 | K58: ='52'!$F$99*'Discipline Analysis'!B58 -> 2043214 | L58: =IFERROR(K58/$B58,"") -> 1.657534 | M58: =OFFSET('52'!$E$35,$A$3,0) -> 1961387 | N58: =IFERROR(M58/$B58,"") -> 1.5911528 | O58: ='52'!$F$101*'Discipline Analysis'!B58 -> 489 | P58: =IFERROR(O58/$B58,"") -> 0.00039669566 | Q58: ='52'!$F$102*'Discipline Analysis'!B58 -> 474623 | R58: =IFERROR(Q58/$B58,"") -> 0.38503249 | S58: ='52'!$F$103*'Discipline Analysis'!B58 -> 201778 | T58: =IFERROR(S58/$B58,"") -> 0.1636901 | U58: ='52'!$F$104*'Discipline Analysis'!B58 -> 140403 | V58: =IFERROR(U58/$B58,"") -> 0.11390033
A59: TSTC-Marshall | B59: =OFFSET('53'!$D$4,$A$3,0) -> 557755 | C59: =OFFSET('53'!$E$4,$A$3,0) -> 5306505 | D59: =IFERROR(C59/$B59,"") -> 9.5140429 | E59: =OFFSET('53'!$E$66,$A$3,0) -> 1834938 | F59: =IFERROR(E59/$B59,"") -> 3.2898638 | G59: ='53'!$F$100*B59 -> 580913 | H59: =IFERROR(G59/$B59,"") -> 1.04152 | I59: ='53'!$F$98*'Discipline Analysis'!B59 -> 697618 | J59: =IFERROR(I59/$B59,"") -> 1.2507606 | K59: ='53'!$F$99*'Discipline Analysis'!B59 -> 812831 | L59: =IFERROR(K59/$B59,"") -> 1.4573262 | M59: =OFFSET('53'!$E$35,$A$3,0) -> 749123 | N59: =IFERROR(M59/$B59,"") -> 1.3431041 | O59: ='53'!$F$101*'Discipline Analysis'!B59 -> 165057 | P59: =IFERROR(O59/$B59,"") -> 0.29593101 | Q59: ='53'!$F$102*'Discipline Analysis'!B59 -> 256075 | R59: =IFERROR(Q59/$B59,"") -> 0.45911735 | S59: ='53'!$F$103*'Discipline Analysis'!B59 -> 127431 | T59: =IFERROR(S59/$B59,"") -> 0.22847128 | U59: ='53'!$F$104*'Discipline Analysis'!B59 -> 82519 | V59: =IFERROR(U59/$B59,"") -> 0.14794847
A60: TSTC-Waco | B60: =OFFSET('54'!$D$4,$A$3,0) -> 4155816 | C60: =OFFSET('54'!$E$4,$A$3,0) -> 32764479 | D60: =IFERROR(C60/$B60,"") -> 7.8840062 | E60: =OFFSET('54'!$E$66,$A$3,0) -> 13605816 | F60: =IFERROR(E60/$B60,"") -> 3.2739217 | G60: ='54'!$F$100*B60 -> 3717296 | H60: =IFERROR(G60/$B60,"") -> 0.89448041 | I60: ='54'!$F$98*'Discipline Analysis'!B60 -> 3629141 | J60: =IFERROR(I60/$B60,"") -> 0.87326797 | K60: ='54'!$F$99*'Discipline Analysis'!B60 -> 2444025 | L60: =IFERROR(K60/$B60,"") -> 0.5880975 | M60: =OFFSET('54'!$E$35,$A$3,0) -> 5951279 | N60: =IFERROR(M60/$B60,"") -> 1.4320362 | O60: ='54'!$F$101*'Discipline Analysis'!B60 -> 239351 | P60: =IFERROR(O60/$B60,"") -> 0.057594225 | Q60: ='54'!$F$102*'Discipline Analysis'!B60 -> 1879961 | R60: =IFERROR(Q60/$B60,"") -> 0.45236868 | S60: ='54'!$F$103*'Discipline Analysis'!B60 -> 1005312 | T60: =IFERROR(S60/$B60,"") -> 0.24190484 | U60: ='54'!$F$104*'Discipline Analysis'!B60 -> 292298 | V60: =IFERROR(U60/$B60,"") -> 0.070334683
A61: Lamar-IOT | B61: =OFFSET('55'!$D$4,$A$3,0) -> 1671411 | C61: =OFFSET('55'!$E$4,$A$3,0) -> 21554948 | D61: =IFERROR(C61/$B61,"") -> 12.896258 | E61: =OFFSET('55'!$E$66,$A$3,0) -> 5600986 | F61: =IFERROR(E61/$B61,"") -> 3.3510525 | G61: ='55'!$F$100*B61 -> 421825 | H61: =IFERROR(G61/$B61,"") -> 0.25237658 | I61: ='55'!$F$98*'Discipline Analysis'!B61 -> 3128620 | J61: =IFERROR(I61/$B61,"") -> 1.8718436 | K61: ='55'!$F$99*'Discipline Analysis'!B61 -> 1740832 | L61: =IFERROR(K61/$B61,"") -> 1.0415344 | M61: =OFFSET('55'!$E$35,$A$3,0) -> 6192406 | N61: =IFERROR(M61/$B61,"") -> 3.7048972 | O61: ='55'!$F$101*'Discipline Analysis'!B61 -> 0 | P61: =IFERROR(O61/$B61,"") -> 0 | Q61: ='55'!$F$102*'Discipline Analysis'!B61 -> 3072708 | R61: =IFERROR(Q61/$B61,"") -> 1.8383916 | S61: ='55'!$F$103*'Discipline Analysis'!B61 -> 940422 | T61: =IFERROR(S61/$B61,"") -> 0.56265156 | U61: ='55'!$F$104*'Discipline Analysis'!B61 -> 457149 | V61: =IFERROR(U61/$B61,"") -> 0.27351082
A62: Lamar-Orange | B62: =OFFSET('56'!$D$4,$A$3,0) -> 0 | C62: =OFFSET('56'!$E$4,$A$3,0) -> 0 | D62: =IFERROR(C62/$B62,"") | E62: =OFFSET('56'!$E$66,$A$3,0) -> 0 | F62: =IFERROR(E62/$B62,"") | G62: ='56'!$F$100*B62 -> 0 | H62: =IFERROR(G62/$B62,"") | I62: ='56'!$F$98*'Discipline Analysis'!B62 -> 0 | J62: =IFERROR(I62/$B62,"") | K62: ='56'!$F$99*'Discipline Analysis'!B62 -> 0 | L62: =IFERROR(K62/$B62,"") | M62: =OFFSET('56'!$E$35,$A$3,0) -> 0 | N62: =IFERROR(M62/$B62,"") | O62: ='56'!$F$101*'Discipline Analysis'!B62 -> 0 | P62: =IFERROR(O62/$B62,"") | Q62: ='56'!$F$102*'Discipline Analysis'!B62 -> 0 | R62: =IFERROR(Q62/$B62,"") | S62: ='56'!$F$103*'Discipline Analysis'!B62 -> 0 | T62: =IFERROR(S62/$B62,"") | U62: ='56'!$F$104*'Discipline Analysis'!B62 -> 0 | V62: =IFERROR(U62/$B62,"")
A63: Lamar-Port Arthur | B63: =OFFSET('57'!$D$4,$A$3,0) -> 1217705 | C63: =OFFSET('57'!$E$4,$A$3,0) -> 20292558 | D63: =IFERROR(C63/$B63,"") -> 16.664593 | E63: =OFFSET('57'!$E$66,$A$3,0) -> 5410971 | F63: =IFERROR(E63/$B63,"") -> 4.4435812 | G63: ='57'!$F$100*B63 -> 941544 | H63: =IFERROR(G63/$B63,"") -> 0.7732119 | I63: ='57'!$F$98*'Discipline Analysis'!B63 -> 3157103 | J63: =IFERROR(I63/$B63,"") -> 2.5926665 | K63: ='57'!$F$99*'Discipline Analysis'!B63 -> 884509 | L63: =IFERROR(K63/$B63,"") -> 0.72637379 | M63: =OFFSET('57'!$E$35,$A$3,0) -> 3284387 | N63: =IFERROR(M63/$B63,"") -> 2.6971943 | O63: ='57'!$F$101*'Discipline Analysis'!B63 -> 0 | P63: =IFERROR(O63/$B63,"") -> 0 | Q63: ='57'!$F$102*'Discipline Analysis'!B63 -> 3991942 | R63: =IFERROR(Q63/$B63,"") -> 3.2782505 | S63: ='57'!$F$103*'Discipline Analysis'!B63 -> 1291947 | T63: =IFERROR(S63/$B63,"") -> 1.0609688 | U63: ='57'!$F$104*'Discipline Analysis'!B63 -> 1330155 | V63: =IFERROR(U63/$B63,"") -> 1.0923458
A64: Total | B64: =OFFSET(Summary!$D$4,$A$3,0) -> 269950015 | C64: =OFFSET(Summary!$E$4,$A$3,0) -> 2272008424 | D64: =IFERROR(C64/$B64,"") -> 8.4164041 | E64: =OFFSET(Summary!$E$66,$A$3,0) -> 925461201 | F64: =IFERROR(E64/$B64,"") -> 3.4282688 | G64: =Summary!$F$100*B64 -> 238198071 | H64: =IFERROR(G64/$B64,"") -> 0.88237843 | I64: =Summary!$F$98*'Discipline Analysis'!B64 -> 428520273 | J64: =IFERROR(I64/$B64,"") -> 1.587406 | K64: =Summary!$F$99*'Discipline Analysis'!B64 -> 230697408 | L64: =IFERROR(K64/$B64,"") -> 0.85459305 | M64: =OFFSET(Summary!$E$35,$A$3,0) -> 319938491 | N64: =IFERROR(M64/$B64,"") -> 1.1851768 | O64: =Summary!$F$101*'Discipline Analysis'!B64 -> 824232 | P64: =IFERROR(O64/$B64,"") -> 0.0030532764 | Q64: =Summary!$F$102*'Discipline Analysis'!B64 -> 24519546 | R64: =IFERROR(Q64/$B64,"") -> 0.090829949 | S64: =Summary!$F$103*'Discipline Analysis'!B64 -> 43583803 | T64: =IFERROR(S64/$B64,"") -> 0.16145138 | U64: =Summary!$F$104*'Discipline Analysis'!B64 -> 60265399 | V64: =IFERROR(U64/$B64,"") -> 0.22324651

Sheet Neutral
A1: =Summary!A1 -> Community and Technical Colleges, Report of Fundable Operating Expenses, Fiscal Year (FY) 2009
A2: Percent of Rates to Maintain Funding Total
A3: This calculation is completed to indicate the relative change in financing assuming the legislature were to fund the institutions at the same total as the previous biennium. The percent funded used against the current rates is adjusted so that the total funded for all institutions is equal to the previous biennium's percent funded.
A4: Institution | B4: ="FY 2010 - 2011 Rates @ "&TEXT(B5,"0.00%")&" (Using FY 2009 CH)" -> FY 2010 - 2011 Rates @ 49.46% (Using FY 2009 CH) | C4: ="Annual Budget Neutral Percent Funded "&TEXT(C5,"0.00%")&" (Using FY 2009 CH)" -> Annual Budget Neutral Percent Funded 43.59% (Using FY 2009 CH) | D4: Difference | E4: Percent Change
A5: Percent of Rates Funded | B5: 0.49463092 | C5: 0.43590688 | D5: =C5-B5 -> -0.05872404
A6: Alamo Community College District | B6: =$B$5*('Rate History'!$D$4*SUMIF(Data!$G:$G,Neutral!$A6,Data!$CU:$CU)+'Rate History'!$D$5*SUMIF(Data!$G:$G,Neutral!$A6,Data!$CV:$CV)+'Rate History'!$D$6*SUMIF(Data!$G:$G,Neutral!$A6,Data!$CW:$CW)+'Rate History'!$D$7*SUMIF(Data!$G:$G,Neutral!$A6,Data!$CX:$CX)+'Rate History'!$D$8*SUMIF(Data!$G:$G,Neutral!$A6,Data!$CY:$CY)+'Rate History'!$D$9*SUMIF(Data!$G:$G,Neutral!$A6,Data!$CZ:$CZ)+'Rate History'!$D$10*SUMIF(Data!$G:$G,Neutral!$A6,Data!$DA:$DA)+'Rate History'!$D$11*SUMIF(Data!$G:$G,Neutral!$A6,Data!$DB:$DB)+'Rate History'!$D$12*SUMIF(Data!$G:$G,Neutral!$A6,Data!$DC:$DC)+'Rate History'!$D$13*SUMIF(Data!$G:$G,Neutral!$A6,Data!$DD:$DD)+'Rate History'!$D$14*SUMIF(Data!$G:$G,Neutral!$A6,Data!$DE:$DE)+'Rate History'!$D$15*SUMIF(Data!$G:$G,Neutral!$A6,Data!$DF:$DF)+'Rate History'!$D$16*SUMIF(Data!$G:$G,Neutral!$A6,Data!$DG:$DG)+'Rate History'!$D$17*SUMIF(Data!$G:$G,Neutral!$A6,Data!$DH:$DH)+'Rate History'!$D$18*SUMIF(Data!$G:$G,Neutral!$A6,Data!$DI:$DI)+'Rate History'!$D$19*SUMIF(Data!$G:$G,Neutral!$A6,Data!$DJ:$DJ)+'Rate History'!$D$20*SUMIF(Data!$G:$G,Neutral!$A6,Data!$DK:$DK)+'Rate History'!$D$21*SUMIF(Data!$G:$G,Neutral!$A6,Data!$DL:$DL)+'Rate History'!$D$22*SUMIF(Data!$G:$G,Neutral!$A6,Data!$DM:$DM)+'Rate History'!$D$23*SUMIF(Data!$G:$G,Neutral!$A6,Data!$DN:$DN)+'Rate History'!$D$24*SUMIF(Data!$G:$G,Neutral!$A6,Data!$DO:$DO)+'Rate History'!$D$25*SUMIF(Data!$G:$G,Neutral!$A6,Data!$DP:$DP)+'Rate History'!$D$26*SUMIF(Data!$G:$G,Neutral!$A6,Data!$DQ:$DQ)+'Rate History'!$D$27*SUMIF(Data!$G:$G,Neutral!$A6,Data!$DR:$DR)+'Rate History'!$D$28*SUMIF(Data!$G:$G,Neutral!$A6,Data!$DS:$DS)+'Rate History'!$D$29*SUMIF(Data!$G:$G,Neutral!$A6,Data!$DT:$DT)+'Rate History'!$D$30*SUMIF(Data!$G:$G,Neutral!$A6,Data!$DV:$DV)+'Rate History'!$D$31*SUMIF(Data!$G:$G,Neutral!$A6,Data!$DW:$DW)) -> 77726768 | C6: =$C$5*('Rate History'!$C$4*SUMIF(Data!$G:$G,Neutral!$A6,Data!$CU:$CU)+'Rate History'!$C$5*SUMIF(Data!$G:$G,Neutral!$A6,Data!$CV:$CV)+'Rate History'!$C$6*SUMIF(Data!$G:$G,Neutral!$A6,Data!$CW:$CW)+'Rate History'!$C$7*SUMIF(Data!$G:$G,Neutral!$A6,Data!$CX:$CX)+'Rate History'!$C$8*SUMIF(Data!$G:$G,Neutral!$A6,Data!$CY:$CY)+'Rate History'!$C$9*SUMIF(Data!$G:$G,Neutral!$A6,Data!$CZ:$CZ)+'Rate History'!$C$10*SUMIF(Data!$G:$G,Neutral!$A6,Data!$DA:$DA)+'Rate History'!$C$11*SUMIF(Data!$G:$G,Neutral!$A6,Data!$DB:$DB)+'Rate History'!$C$12*SUMIF(Data!$G:$G,Neutral!$A6,Data!$DC:$DC)+'Rate History'!$C$13*SUMIF(Data!$G:$G,Neutral!$A6,Data!$DD:$DD)+'Rate History'!$C$14*SUMIF(Data!$G:$G,Neutral!$A6,Data!$DE:$DE)+'Rate History'!$C$15*SUMIF(Data!$G:$G,Neutral!$A6,Data!$DF:$DF)+'Rate History'!$C$16*SUMIF(Data!$G:$G,Neutral!$A6,Data!$DG:$DG)+'Rate History'!$C$17*SUMIF(Data!$G:$G,Neutral!$A6,Data!$DH:$DH)+'Rate History'!$C$18*SUMIF(Data!$G:$G,Neutral!$A6,Data!$DI:$DI)+'Rate History'!$C$19*SUMIF(Data!$G:$G,Neutral!$A6,Data!$DJ:$DJ)+'Rate History'!$C$20*SUMIF(Data!$G:$G,Neutral!$A6,Data!$DK:$DK)+'Rate History'!$C$21*SUMIF(Data!$G:$G,Neutral!$A6,Data!$DL:$DL)+'Rate History'!$C$22*SUMIF(Data!$G:$G,Neutral!$A6,Data!$DM:$DM)+'Rate History'!$C$23*SUMIF(Data!$G:$G,Neutral!$A6,Data!$DN:$DN)+'Rate History'!$C$24*SUMIF(Data!$G:$G,Neutral!$A6,Data!$DO:$DO)+'Rate History'!$C$25*SUMIF(Data!$G:$G,Neutral!$A6,Data!$DP:$DP)+'Rate History'!$C$26*SUMIF(Data!$G:$G,Neutral!$A6,Data!$DQ:$DQ)+'Rate History'!$C$27*SUMIF(Data!$G:$G,Neutral!$A6,Data!$DR:$DR)+'Rate History'!$C$28*SUMIF(Data!$G:$G,Neutral!$A6,Data!$DS:$DS)+'Rate History'!$C$29*SUMIF(Data!$G:$G,Neutral!$A6,Data!$DT:$DT)+'Rate History'!$C$30*SUMIF(Data!$G:$G,Neutral!$A6,Data!$DV:$DV)+'Rate History'!$C$31*SUMIF(Data!$G:$G,Neutral!$A6,Data!$DW:$DW)) -> 77520715 | D6: =C6-B6 -> -206052.93 | E6: =IFERROR(D6/B6,"") -> -0.0026509906
A7: Alvin Community College | B7: =$B$5*('Rate History'!$D$4*SUMIF(Data!$G:$G,Neutral!$A7,Data!$CU:$CU)+'Rate History'!$D$5*SUMIF(Data!$G:$G,Neutral!$A7,Data!$CV:$CV)+'Rate History'!$D$6*SUMIF(Data!$G:$G,Neutral!$A7,Data!$CW:$CW)+'Rate History'!$D$7*SUMIF(Data!$G:$G,Neutral!$A7,Data!$CX:$CX)+'Rate History'!$D$8*SUMIF(Data!$G:$G,Neutral!$A7,Data!$CY:$CY)+'Rate History'!$D$9*SUMIF(Data!$G:$G,Neutral!$A7,Data!$CZ:$CZ)+'Rate History'!$D$10*SUMIF(Data!$G:$G,Neutral!$A7,Data!$DA:$DA)+'Rate History'!$D$11*SUMIF(Data!$G:$G,Neutral!$A7,Data!$DB:$DB)+'Rate History'!$D$12*SUMIF(Data!$G:$G,Neutral!$A7,Data!$DC:$DC)+'Rate History'!$D$13*SUMIF(Data!$G:$G,Neutral!$A7,Data!$DD:$DD)+'Rate History'!$D$14*SUMIF(Data!$G:$G,Neutral!$A7,Data!$DE:$DE)+'Rate History'!$D$15*SUMIF(Data!$G:$G,Neutral!$A7,Data!$DF:$DF)+'Rate History'!$D$16*SUMIF(Data!$G:$G,Neutral!$A7,Data!$DG:$DG)+'Rate History'!$D$17*SUMIF(Data!$G:$G,Neutral!$A7,Data!$DH:$DH)+'Rate History'!$D$18*SUMIF(Data!$G:$G,Neutral!$A7,Data!$DI:$DI)+'Rate History'!$D$19*SUMIF(Data!$G:$G,Neutral!$A7,Data!$DJ:$DJ)+'Rate History'!$D$20*SUMIF(Data!$G:$G,Neutral!$A7,Data!$DK:$DK)+'Rate History'!$D$21*SUMIF(Data!$G:$G,Neutral!$A7,Data!$DL:$DL)+'Rate History'!$D$22*SUMIF(Data!$G:$G,Neutral!$A7,Data!$DM:$DM)+'Rate History'!$D$23*SUMIF(Data!$G:$G,Neutral!$A7,Data!$DN:$DN)+'Rate History'!$D$24*SUMIF(Data!$G:$G,Neutral!$A7,Data!$DO:$DO)+'Rate History'!$D$25*SUMIF(Data!$G:$G,Neutral!$A7,Data!$DP:$DP)+'Rate History'!$D$26*SUMIF(Data!$G:$G,Neutral!$A7,Data!$DQ:$DQ)+'Rate History'!$D$27*SUMIF(Data!$G:$G,Neutral!$A7,Data!$DR:$DR)+'Rate History'!$D$28*SUMIF(Data!$G:$G,Neutral!$A7,Data!$DS:$DS)+'Rate History'!$D$29*SUMIF(Data!$G:$G,Neutral!$A7,Data!$DT:$DT)+'Rate History'!$D$30*SUMIF(Data!$G:$G,Neutral!$A7,Data!$DV:$DV)+'Rate History'!$D$31*SUMIF(Data!$G:$G,Neutral!$A7,Data!$DW:$DW)) -> 8524384.4 | C7: =$C$5*('Rate History'!$C$4*SUMIF(Data!$G:$G,Neutral!$A7,Data!$CU:$CU)+'Rate History'!$C$5*SUMIF(Data!$G:$G,Neutral!$A7,Data!$CV:$CV)+'Rate History'!$C$6*SUMIF(Data!$G:$G,Neutral!$A7,Data!$CW:$CW)+'Rate History'!$C$7*SUMIF(Data!$G:$G,Neutral!$A7,Data!$CX:$CX)+'Rate History'!$C$8*SUMIF(Data!$G:$G,Neutral!$A7,Data!$CY:$CY)+'Rate History'!$C$9*SUMIF(Data!$G:$G,Neutral!$A7,Data!$CZ:$CZ)+'Rate History'!$C$10*SUMIF(Data!$G:$G,Neutral!$A7,Data!$DA:$DA)+'Rate History'!$C$11*SUMIF(Data!$G:$G,Neutral!$A7,Data!$DB:$DB)+'Rate History'!$C$12*SUMIF(Data!$G:$G,Neutral!$A7,Data!$DC:$DC)+'Rate History'!$C$13*SUMIF(Data!$G:$G,Neutral!$A7,Data!$DD:$DD)+'Rate History'!$C$14*SUMIF(Data!$G:$G,Neutral!$A7,Data!$DE:$DE)+'Rate History'!$C$15*SUMIF(Data!$G:$G,Neutral!$A7,Data!$DF:$DF)+'Rate History'!$C$16*SUMIF(Data!$G:$G,Neutral!$A7,Data!$DG:$DG)+'Rate History'!$C$17*SUMIF(Data!$G:$G,Neutral!$A7,Data!$DH:$DH)+'Rate History'!$C$18*SUMIF(Data!$G:$G,Neutral!$A7,Data!$DI:$DI)+'Rate History'!$C$19*SUMIF(Data!$G:$G,Neutral!$A7,Data!$DJ:$DJ)+'Rate History'!$C$20*SUMIF(Data!$G:$G,Neutral!$A7,Data!$DK:$DK)+'Rate History'!$C$21*SUMIF(Data!$G:$G,Neutral!$A7,Data!$DL:$DL)+'Rate History'!$C$22*SUMIF(Data!$G:$G,Neutral!$A7,Data!$DM:$DM)+'Rate History'!$C$23*SUMIF(Data!$G:$G,Neutral!$A7,Data!$DN:$DN)+'Rate History'!$C$24*SUMIF(Data!$G:$G,Neutral!$A7,Data!$DO:$DO)+'Rate History'!$C$25*SUMIF(Data!$G:$G,Neutral!$A7,Data!$DP:$DP)+'Rate History'!$C$26*SUMIF(Data!$G:$G,Neutral!$A7,Data!$DQ:$DQ)+'Rate History'!$C$27*SUMIF(Data!$G:$G,Neutral!$A7,Data!$DR:$DR)+'Rate History'!$C$28*SUMIF(Data!$G:$G,Neutral!$A7,Data!$DS:$DS)+'Rate History'!$C$29*SUMIF(Data!$G:$G,Neutral!$A7,Data!$DT:$DT)+'Rate History'!$C$30*SUMIF(Data!$G:$G,Neutral!$A7,Data!$DV:$DV)+'Rate History'!$C$31*SUMIF(Data!$G:$G,Neutral!$A7,Data!$DW:$DW)) -> 8546308.6 | D7: =C7-B7 -> 21924.243 | E7: =IFERROR(D7/B7,"") -> 0.0025719445
A8: Amarillo College | B8: =$B$5*('Rate History'!$D$4*SUMIF(Data!$G:$G,Neutral!$A8,Data!$CU:$CU)+'Rate History'!$D$5*SUMIF(Data!$G:$G,Neutral!$A8,Data!$CV:$CV)+'Rate History'!$D$6*SUMIF(Data!$G:$G,Neutral!$A8,Data!$CW:$CW)+'Rate History'!$D$7*SUMIF(Data!$G:$G,Neutral!$A8,Data!$CX:$CX)+'Rate History'!$D$8*SUMIF(Data!$G:$G,Neutral!$A8,Data!$CY:$CY)+'Rate History'!$D$9*SUMIF(Data!$G:$G,Neutral!$A8,Data!$CZ:$CZ)+'Rate History'!$D$10*SUMIF(Data!$G:$G,Neutral!$A8,Data!$DA:$DA)+'Rate History'!$D$11*SUMIF(Data!$G:$G,Neutral!$A8,Data!$DB:$DB)+'Rate History'!$D$12*SUMIF(Data!$G:$G,Neutral!$A8,Data!$DC:$DC)+'Rate History'!$D$13*SUMIF(Data!$G:$G,Neutral!$A8,Data!$DD:$DD)+'Rate History'!$D$14*SUMIF(Data!$G:$G,Neutral!$A8,Data!$DE:$DE)+'Rate History'!$D$15*SUMIF(Data!$G:$G,Neutral!$A8,Data!$DF:$DF)+'Rate History'!$D$16*SUMIF(Data!$G:$G,Neutral!$A8,Data!$DG:$DG)+'Rate History'!$D$17*SUMIF(Data!$G:$G,Neutral!$A8,Data!$DH:$DH)+'Rate History'!$D$18*SUMIF(Data!$G:$G,Neutral!$A8,Data!$DI:$DI)+'Rate History'!$D$19*SUMIF(Data!$G:$G,Neutral!$A8,Data!$DJ:$DJ)+'Rate History'!$D$20*SUMIF(Data!$G:$G,Neutral!$A8,Data!$DK:$DK)+'Rate History'!$D$21*SUMIF(Data!$G:$G,Neutral!$A8,Data!$DL:$DL)+'Rate History'!$D$22*SUMIF(Data!$G:$G,Neutral!$A8,Data!$DM:$DM)+'Rate History'!$D$23*SUMIF(Data!$G:$G,Neutral!$A8,Data!$DN:$DN)+'Rate History'!$D$24*SUMIF(Data!$G:$G,Neutral!$A8,Data!$DO:$DO)+'Rate History'!$D$25*SUMIF(Data!$G:$G,Neutral!$A8,Data!$DP:$DP)+'Rate History'!$D$26*SUMIF(Data!$G:$G,Neutral!$A8,Data!$DQ:$DQ)+'Rate History'!$D$27*SUMIF(Data!$G:$G,Neutral!$A8,Data!$DR:$DR)+'Rate History'!$D$28*SUMIF(Data!$G:$G,Neutral!$A8,Data!$DS:$DS)+'Rate History'!$D$29*SUMIF(Data!$G:$G,Neutral!$A8,Data!$DT:$DT)+'Rate History'!$D$30*SUMIF(Data!$G:$G,Neutral!$A8,Data!$DV:$DV)+'Rate History'!$D$31*SUMIF(Data!$G:$G,Neutral!$A8,Data!$DW:$DW)) -> 17627944 | C8: =$C$5*('Rate History'!$C$4*SUMIF(Data!$G:$G,Neutral!$A8,Data!$CU:$CU)+'Rate History'!$C$5*SUMIF(Data!$G:$G,Neutral!$A8,Data!$CV:$CV)+'Rate History'!$C$6*SUMIF(Data!$G:$G,Neutral!$A8,Data!$CW:$CW)+'Rate History'!$C$7*SUMIF(Data!$G:$G,Neutral!$A8,Data!$CX:$CX)+'Rate History'!$C$8*SUMIF(Data!$G:$G,Neutral!$A8,Data!$CY:$CY)+'Rate History'!$C$9*SUMIF(Data!$G:$G,Neutral!$A8,Data!$CZ:$CZ)+'Rate History'!$C$10*SUMIF(Data!$G:$G,Neutral!$A8,Data!$DA:$DA)+'Rate History'!$C$11*SUMIF(Data!$G:$G,Neutral!$A8,Data!$DB:$DB)+'Rate History'!$C$12*SUMIF(Data!$G:$G,Neutral!$A8,Data!$DC:$DC)+'Rate History'!$C$13*SUMIF(Data!$G:$G,Neutral!$A8,Data!$DD:$DD)+'Rate History'!$C$14*SUMIF(Data!$G:$G,Neutral!$A8,Data!$DE:$DE)+'Rate History'!$C$15*SUMIF(Data!$G:$G,Neutral!$A8,Data!$DF:$DF)+'Rate History'!$C$16*SUMIF(Data!$G:$G,Neutral!$A8,Data!$DG:$DG)+'Rate History'!$C$17*SUMIF(Data!$G:$G,Neutral!$A8,Data!$DH:$DH)+'Rate History'!$C$18*SUMIF(Data!$G:$G,Neutral!$A8,Data!$DI:$DI)+'Rate History'!$C$19*SUMIF(Data!$G:$G,Neutral!$A8,Data!$DJ:$DJ)+'Rate History'!$C$20*SUMIF(Data!$G:$G,Neutral!$A8,Data!$DK:$DK)+'Rate History'!$C$21*SUMIF(Data!$G:$G,Neutral!$A8,Data!$DL:$DL)+'Rate History'!$C$22*SUMIF(Data!$G:$G,Neutral!$A8,Data!$DM:$DM)+'Rate History'!$C$23*SUMIF(Data!$G:$G,Neutral!$A8,Data!$DN:$DN)+'Rate History'!$C$24*SUMIF(Data!$G:$G,Neutral!$A8,Data!$DO:$DO)+'Rate History'!$C$25*SUMIF(Data!$G:$G,Neutral!$A8,Data!$DP:$DP)+'Rate History'!$C$26*SUMIF(Data!$G:$G,Neutral!$A8,Data!$DQ:$DQ)+'Rate History'!$C$27*SUMIF(Data!$G:$G,Neutral!$A8,Data!$DR:$DR)+'Rate History'!$C$28*SUMIF(Data!$G:$G,Neutral!$A8,Data!$DS:$DS)+'Rate History'!$C$29*SUMIF(Data!$G:$G,Neutral!$A8,Data!$DT:$DT)+'Rate History'!$C$30*SUMIF(Data!$G:$G,Neutral!$A8,Data!$DV:$DV)+'Rate History'!$C$31*SUMIF(Data!$G:$G,Neutral!$A8,Data!$DW:$DW)) -> 17608236 | D8: =C8-B8 -> -19707.954 | E8: =IFERROR(D8/B8,"") -> -0.001117995
A9: Angelina College | B9: =$B$5*('Rate History'!$D$4*SUMIF(Data!$G:$G,Neutral!$A9,Data!$CU:$CU)+'Rate History'!$D$5*SUMIF(Data!$G:$G,Neutral!$A9,Data!$CV:$CV)+'Rate History'!$D$6*SUMIF(Data!$G:$G,Neutral!$A9,Data!$CW:$CW)+'Rate History'!$D$7*SUMIF(Data!$G:$G,Neutral!$A9,Data!$CX:$CX)+'Rate History'!$D$8*SUMIF(Data!$G:$G,Neutral!$A9,Data!$CY:$CY)+'Rate History'!$D$9*SUMIF(Data!$G:$G,Neutral!$A9,Data!$CZ:$CZ)+'Rate History'!$D$10*SUMIF(Data!$G:$G,Neutral!$A9,Data!$DA:$DA)+'Rate History'!$D$11*SUMIF(Data!$G:$G,Neutral!$A9,Data!$DB:$DB)+'Rate History'!$D$12*SUMIF(Data!$G:$G,Neutral!$A9,Data!$DC:$DC)+'Rate History'!$D$13*SUMIF(Data!$G:$G,Neutral!$A9,Data!$DD:$DD)+'Rate History'!$D$14*SUMIF(Data!$G:$G,Neutral!$A9,Data!$DE:$DE)+'Rate History'!$D$15*SUMIF(Data!$G:$G,Neutral!$A9,Data!$DF:$DF)+'Rate History'!$D$16*SUMIF(Data!$G:$G,Neutral!$A9,Data!$DG:$DG)+'Rate History'!$D$17*SUMIF(Data!$G:$G,Neutral!$A9,Data!$DH:$DH)+'Rate History'!$D$18*SUMIF(Data!$G:$G,Neutral!$A9,Data!$DI:$DI)+'Rate History'!$D$19*SUMIF(Data!$G:$G,Neutral!$A9,Data!$DJ:$DJ)+'Rate History'!$D$20*SUMIF(Data!$G:$G,Neutral!$A9,Data!$DK:$DK)+'Rate History'!$D$21*SUMIF(Data!$G:$G,Neutral!$A9,Data!$DL:$DL)+'Rate History'!$D$22*SUMIF(Data!$G:$G,Neutral!$A9,Data!$DM:$DM)+'Rate History'!$D$23*SUMIF(Data!$G:$G,Neutral!$A9,Data!$DN:$DN)+'Rate History'!$D$24*SUMIF(Data!$G:$G,Neutral!$A9,Data!$DO:$DO)+'Rate History'!$D$25*SUMIF(Data!$G:$G,Neutral!$A9,Data!$DP:$DP)+'Rate History'!$D$26*SUMIF(Data!$G:$G,Neutral!$A9,Data!$DQ:$DQ)+'Rate History'!$D$27*SUMIF(Data!$G:$G,Neutral!$A9,Data!$DR:$DR)+'Rate History'!$D$28*SUMIF(Data!$G:$G,Neutral!$A9,Data!$DS:$DS)+'Rate History'!$D$29*SUMIF(Data!$G:$G,Neutral!$A9,Data!$DT:$DT)+'Rate History'!$D$30*SUMIF(Data!$G:$G,Neutral!$A9,Data!$DV:$DV)+'Rate History'!$D$31*SUMIF(Data!$G:$G,Neutral!$A9,Data!$DW:$DW)) -> 8261428 | C9: =$C$5*('Rate History'!$C$4*SUMIF(Data!$G:$G,Neutral!$A9,Data!$CU:$CU)+'Rate History'!$C$5*SUMIF(Data!$G:$G,Neutral!$A9,Data!$CV:$CV)+'Rate History'!$C$6*SUMIF(Data!$G:$G,Neutral!$A9,Data!$CW:$CW)+'Rate History'!$C$7*SUMIF(Data!$G:$G,Neutral!$A9,Data!$CX:$CX)+'Rate History'!$C$8*SUMIF(Data!$G:$G,Neutral!$A9,Data!$CY:$CY)+'Rate History'!$C$9*SUMIF(Data!$G:$G,Neutral!$A9,Data!$CZ:$CZ)+'Rate History'!$C$10*SUMIF(Data!$G:$G,Neutral!$A9,Data!$DA:$DA)+'Rate History'!$C$11*SUMIF(Data!$G:$G,Neutral!$A9,Data!$DB:$DB)+'Rate History'!$C$12*SUMIF(Data!$G:$G,Neutral!$A9,Data!$DC:$DC)+'Rate History'!$C$13*SUMIF(Data!$G:$G,Neutral!$A9,Data!$DD:$DD)+'Rate History'!$C$14*SUMIF(Data!$G:$G,Neutral!$A9,Data!$DE:$DE)+'Rate History'!$C$15*SUMIF(Data!$G:$G,Neutral!$A9,Data!$DF:$DF)+'Rate History'!$C$16*SUMIF(Data!$G:$G,Neutral!$A9,Data!$DG:$DG)+'Rate History'!$C$17*SUMIF(Data!$G:$G,Neutral!$A9,Data!$DH:$DH)+'Rate History'!$C$18*SUMIF(Data!$G:$G,Neutral!$A9,Data!$DI:$DI)+'Rate History'!$C$19*SUMIF(Data!$G:$G,Neutral!$A9,Data!$DJ:$DJ)+'Rate History'!$C$20*SUMIF(Data!$G:$G,Neutral!$A9,Data!$DK:$DK)+'Rate History'!$C$21*SUMIF(Data!$G:$G,Neutral!$A9,Data!$DL:$DL)+'Rate History'!$C$22*SUMIF(Data!$G:$G,Neutral!$A9,Data!$DM:$DM)+'Rate History'!$C$23*SUMIF(Data!$G:$G,Neutral!$A9,Data!$DN:$DN)+'Rate History'!$C$24*SUMIF(Data!$G:$G,Neutral!$A9,Data!$DO:$DO)+'Rate History'!$C$25*SUMIF(Data!$G:$G,Neutral!$A9,Data!$DP:$DP)+'Rate History'!$C$26*SUMIF(Data!$G:$G,Neutral!$A9,Data!$DQ:$DQ)+'Rate History'!$C$27*SUMIF(Data!$G:$G,Neutral!$A9,Data!$DR:$DR)+'Rate History'!$C$28*SUMIF(Data!$G:$G,Neutral!$A9,Data!$DS:$DS)+'Rate History'!$C$29*SUMIF(Data!$G:$G,Neutral!$A9,Data!$DT:$DT)+'Rate History'!$C$30*SUMIF(Data!$G:$G,Neutral!$A9,Data!$DV:$DV)+'Rate History'!$C$31*SUMIF(Data!$G:$G,Neutral!$A9,Data!$DW:$DW)) -> 8284038.3 | D9: =C9-B9 -> 22610.336 | E9: =IFERROR(D9/B9,"") -> 0.0027368557
A10: Austin Community College | B10: =$B$5*('Rate History'!$D$4*SUMIF(Data!$G:$G,Neutral!$A10,Data!$CU:$CU)+'Rate History'!$D$5*SUMIF(Data!$G:$G,Neutral!$A10,Data!$CV:$CV)+'Rate History'!$D$6*SUMIF(Data!$G:$G,Neutral!$A10,Data!$CW:$CW)+'Rate History'!$D$7*SUMIF(Data!$G:$G,Neutral!$A10,Data!$CX:$CX)+'Rate History'!$D$8*SUMIF(Data!$G:$G,Neutral!$A10,Data!$CY:$CY)+'Rate History'!$D$9*SUMIF(Data!$G:$G,Neutral!$A10,Data!$CZ:$CZ)+'Rate History'!$D$10*SUMIF(Data!$G:$G,Neutral!$A10,Data!$DA:$DA)+'Rate History'!$D$11*SUMIF(Data!$G:$G,Neutral!$A10,Data!$DB:$DB)+'Rate History'!$D$12*SUMIF(Data!$G:$G,Neutral!$A10,Data!$DC:$DC)+'Rate History'!$D$13*SUMIF(Data!$G:$G,Neutral!$A10,Data!$DD:$DD)+'Rate History'!$D$14*SUMIF(Data!$G:$G,Neutral!$A10,Data!$DE:$DE)+'Rate History'!$D$15*SUMIF(Data!$G:$G,Neutral!$A10,Data!$DF:$DF)+'Rate History'!$D$16*SUMIF(Data!$G:$G,Neutral!$A10,Data!$DG:$DG)+'Rate History'!$D$17*SUMIF(Data!$G:$G,Neutral!$A10,Data!$DH:$DH)+'Rate History'!$D$18*SUMIF(Data!$G:$G,Neutral!$A10,Data!$DI:$DI)+'Rate History'!$D$19*SUMIF(Data!$G:$G,Neutral!$A10,Data!$DJ:$DJ)+'Rate History'!$D$20*SUMIF(Data!$G:$G,Neutral!$A10,Data!$DK:$DK)+'Rate History'!$D$21*SUMIF(Data!$G:$G,Neutral!$A10,Data!$DL:$DL)+'Rate History'!$D$22*SUMIF(Data!$G:$G,Neutral!$A10,Data!$DM:$DM)+'Rate History'!$D$23*SUMIF(Data!$G:$G,Neutral!$A10,Data!$DN:$DN)+'Rate History'!$D$24*SUMIF(Data!$G:$G,Neutral!$A10,Data!$DO:$DO)+'Rate History'!$D$25*SUMIF(Data!$G:$G,Neutral!$A10,Data!$DP:$DP)+'Rate History'!$D$26*SUMIF(Data!$G:$G,Neutral!$A10,Data!$DQ:$DQ)+'Rate History'!$D$27*SUMIF(Data!$G:$G,Neutral!$A10,Data!$DR:$DR)+'Rate History'!$D$28*SUMIF(Data!$G:$G,Neutral!$A10,Data!$DS:$DS)+'Rate History'!$D$29*SUMIF(Data!$G:$G,Neutral!$A10,Data!$DT:$DT)+'Rate History'!$D$30*SUMIF(Data!$G:$G,Neutral!$A10,Data!$DV:$DV)+'Rate History'!$D$31*SUMIF(Data!$G:$G,Neutral!$A10,Data!$DW:$DW)) -> 50373547 | C10: =$C$5*('Rate History'!$C$4*SUMIF(Data!$G:$G,Neutral!$A10,Data!$CU:$CU)+'Rate History'!$C$5*SUMIF(Data!$G:$G,Neutral!$A10,Data!$CV:$CV)+'Rate History'!$C$6*SUMIF(Data!$G:$G,Neutral!$A10,Data!$CW:$CW)+'Rate History'!$C$7*SUMIF(Data!$G:$G,Neutral!$A10,Data!$CX:$CX)+'Rate History'!$C$8*SUMIF(Data!$G:$G,Neutral!$A10,Data!$CY:$CY)+'Rate History'!$C$9*SUMIF(Data!$G:$G,Neutral!$A10,Data!$CZ:$CZ)+'Rate History'!$C$10*SUMIF(Data!$G:$G,Neutral!$A10,Data!$DA:$DA)+'Rate History'!$C$11*SUMIF(Data!$G:$G,Neutral!$A10,Data!$DB:$DB)+'Rate History'!$C$12*SUMIF(Data!$G:$G,Neutral!$A10,Data!$DC:$DC)+'Rate History'!$C$13*SUMIF(Data!$G:$G,Neutral!$A10,Data!$DD:$DD)+'Rate History'!$C$14*SUMIF(Data!$G:$G,Neutral!$A10,Data!$DE:$DE)+'Rate History'!$C$15*SUMIF(Data!$G:$G,Neutral!$A10,Data!$DF:$DF)+'Rate History'!$C$16*SUMIF(Data!$G:$G,Neutral!$A10,Data!$DG:$DG)+'Rate History'!$C$17*SUMIF(Data!$G:$G,Neutral!$A10,Data!$DH:$DH)+'Rate History'!$C$18*SUMIF(Data!$G:$G,Neutral!$A10,Data!$DI:$DI)+'Rate History'!$C$19*SUMIF(Data!$G:$G,Neutral!$A10,Data!$DJ:$DJ)+'Rate History'!$C$20*SUMIF(Data!$G:$G,Neutral!$A10,Data!$DK:$DK)+'Rate History'!$C$21*SUMIF(Data!$G:$G,Neutral!$A10,Data!$DL:$DL)+'Rate History'!$C$22*SUMIF(Data!$G:$G,Neutral!$A10,Data!$DM:$DM)+'Rate History'!$C$23*SUMIF(Data!$G:$G,Neutral!$A10,Data!$DN:$DN)+'Rate History'!$C$24*SUMIF(Data!$G:$G,Neutral!$A10,Data!$DO:$DO)+'Rate History'!$C$25*SUMIF(Data!$G:$G,Neutral!$A10,Data!$DP:$DP)+'Rate History'!$C$26*SUMIF(Data!$G:$G,Neutral!$A10,Data!$DQ:$DQ)+'Rate History'!$C$27*SUMIF(Data!$G:$G,Neutral!$A10,Data!$DR:$DR)+'Rate History'!$C$28*SUMIF(Data!$G:$G,Neutral!$A10,Data!$DS:$DS)+'Rate History'!$C$29*SUMIF(Data!$G:$G,Neutral!$A10,Data!$DT:$DT)+'Rate History'!$C$30*SUMIF(Data!$G:$G,Neutral!$A10,Data!$DV:$DV)+'Rate History'!$C$31*SUMIF(Data!$G:$G,Neutral!$A10,Data!$DW:$DW)) -> 50183594 | D10: =C10-B10 -> -189953.83 | E10: =IFERROR(D10/B10,"") -> -0.0037709043
A11: Blinn College | B11: =$B$5*('Rate History'!$D$4*SUMIF(Data!$G:$G,Neutral!$A11,Data!$CU:$CU)+'Rate History'!$D$5*SUMIF(Data!$G:$G,Neutral!$A11,Data!$CV:$CV)+'Rate History'!$D$6*SUMIF(Data!$G:$G,Neutral!$A11,Data!$CW:$CW)+'Rate History'!$D$7*SUMIF(Data!$G:$G,Neutral!$A11,Data!$CX:$CX)+'Rate History'!$D$8*SUMIF(Data!$G:$G,Neutral!$A11,Data!$CY:$CY)+'Rate History'!$D$9*SUMIF(Data!$G:$G,Neutral!$A11,Data!$CZ:$CZ)+'Rate History'!$D$10*SUMIF(Data!$G:$G,Neutral!$A11,Data!$DA:$DA)+'Rate History'!$D$11*SUMIF(Data!$G:$G,Neutral!$A11,Data!$DB:$DB)+'Rate History'!$D$12*SUMIF(Data!$G:$G,Neutral!$A11,Data!$DC:$DC)+'Rate History'!$D$13*SUMIF(Data!$G:$G,Neutral!$A11,Data!$DD:$DD)+'Rate History'!$D$14*SUMIF(Data!$G:$G,Neutral!$A11,Data!$DE:$DE)+'Rate History'!$D$15*SUMIF(Data!$G:$G,Neutral!$A11,Data!$DF:$DF)+'Rate History'!$D$16*SUMIF(Data!$G:$G,Neutral!$A11,Data!$DG:$DG)+'Rate History'!$D$17*SUMIF(Data!$G:$G,Neutral!$A11,Data!$DH:$DH)+'Rate History'!$D$18*SUMIF(Data!$G:$G,Neutral!$A11,Data!$DI:$DI)+'Rate History'!$D$19*SUMIF(Data!$G:$G,Neutral!$A11,Data!$DJ:$DJ)+'Rate History'!$D$20*SUMIF(Data!$G:$G,Neutral!$A11,Data!$DK:$DK)+'Rate History'!$D$21*SUMIF(Data!$G:$G,Neutral!$A11,Data!$DL:$DL)+'Rate History'!$D$22*SUMIF(Data!$G:$G,Neutral!$A11,Data!$DM:$DM)+'Rate History'!$D$23*SUMIF(Data!$G:$G,Neutral!$A11,Data!$DN:$DN)+'Rate History'!$D$24*SUMIF(Data!$G:$G,Neutral!$A11,Data!$DO:$DO)+'Rate History'!$D$25*SUMIF(Data!$G:$G,Neutral!$A11,Data!$DP:$DP)+'Rate History'!$D$26*SUMIF(Data!$G:$G,Neutral!$A11,Data!$DQ:$DQ)+'Rate History'!$D$27*SUMIF(Data!$G:$G,Neutral!$A11,Data!$DR:$DR)+'Rate History'!$D$28*SUMIF(Data!$G:$G,Neutral!$A11,Data!$DS:$DS)+'Rate History'!$D$29*SUMIF(Data!$G:$G,Neutral!$A11,Data!$DT:$DT)+'Rate History'!$D$30*SUMIF(Data!$G:$G,Neutral!$A11,Data!$DV:$DV)+'Rate History'!$D$31*SUMIF(Data!$G:$G,Neutral!$A11,Data!$DW:$DW)) -> 24597044 | C11: =$C$5*('Rate History'!$C$4*SUMIF(Data!$G:$G,Neutral!$A11,Data!$CU:$CU)+'Rate History'!$C$5*SUMIF(Data!$G:$G,Neutral!$A11,Data!$CV:$CV)+'Rate History'!$C$6*SUMIF(Data!$G:$G,Neutral!$A11,Data!$CW:$CW)+'Rate History'!$C$7*SUMIF(Data!$G:$G,Neutral!$A11,Data!$CX:$CX)+'Rate History'!$C$8*SUMIF(Data!$G:$G,Neutral!$A11,Data!$CY:$CY)+'Rate History'!$C$9*SUMIF(Data!$G:$G,Neutral!$A11,Data!$CZ:$CZ)+'Rate History'!$C$10*SUMIF(Data!$G:$G,Neutral!$A11,Data!$DA:$DA)+'Rate History'!$C$11*SUMIF(Data!$G:$G,Neutral!$A11,Data!$DB:$DB)+'Rate History'!$C$12*SUMIF(Data!$G:$G,Neutral!$A11,Data!$DC:$DC)+'Rate History'!$C$13*SUMIF(Data!$G:$G,Neutral!$A11,Data!$DD:$DD)+'Rate History'!$C$14*SUMIF(Data!$G:$G,Neutral!$A11,Data!$DE:$DE)+'Rate History'!$C$15*SUMIF(Data!$G:$G,Neutral!$A11,Data!$DF:$DF)+'Rate History'!$C$16*SUMIF(Data!$G:$G,Neutral!$A11,Data!$DG:$DG)+'Rate History'!$C$17*SUMIF(Data!$G:$G,Neutral!$A11,Data!$DH:$DH)+'Rate History'!$C$18*SUMIF(Data!$G:$G,Neutral!$A11,Data!$DI:$DI)+'Rate History'!$C$19*SUMIF(Data!$G:$G,Neutral!$A11,Data!$DJ:$DJ)+'Rate History'!$C$20*SUMIF(Data!$G:$G,Neutral!$A11,Data!$DK:$DK)+'Rate History'!$C$21*SUMIF(Data!$G:$G,Neutral!$A11,Data!$DL:$DL)+'Rate History'!$C$22*SUMIF(Data!$G:$G,Neutral!$A11,Data!$DM:$DM)+'Rate History'!$C$23*SUMIF(Data!$G:$G,Neutral!$A11,Data!$DN:$DN)+'Rate History'!$C$24*SUMIF(Data!$G:$G,Neutral!$A11,Data!$DO:$DO)+'Rate History'!$C$25*SUMIF(Data!$G:$G,Neutral!$A11,Data!$DP:$DP)+'Rate History'!$C$26*SUMIF(Data!$G:$G,Neutral!$A11,Data!$DQ:$DQ)+'Rate History'!$C$27*SUMIF(Data!$G:$G,Neutral!$A11,Data!$DR:$DR)+'Rate History'!$C$28*SUMIF(Data!$G:$G,Neutral!$A11,Data!$DS:$DS)+'Rate History'!$C$29*SUMIF(Data!$G:$G,Neutral!$A11,Data!$DT:$DT)+'Rate History'!$C$30*SUMIF(Data!$G:$G,Neutral!$A11,Data!$DV:$DV)+'Rate History'!$C$31*SUMIF(Data!$G:$G,Neutral!$A11,Data!$DW:$DW)) -> 24472513 | D11: =C11-B11 -> -124531.21 | E11: =IFERROR(D11/B11,"") -> -0.0050628528
A12: Brazosport College | B12: =$B$5*('Rate History'!$D$4*SUMIF(Data!$G:$G,Neutral!$A12,Data!$CU:$CU)+'Rate History'!$D$5*SUMIF(Data!$G:$G,Neutral!$A12,Data!$CV:$CV)+'Rate History'!$D$6*SUMIF(Data!$G:$G,Neutral!$A12,Data!$CW:$CW)+'Rate History'!$D$7*SUMIF(Data!$G:$G,Neutral!$A12,Data!$CX:$CX)+'Rate History'!$D$8*SUMIF(Data!$G:$G,Neutral!$A12,Data!$CY:$CY)+'Rate History'!$D$9*SUMIF(Data!$G:$G,Neutral!$A12,Data!$CZ:$CZ)+'Rate History'!$D$10*SUMIF(Data!$G:$G,Neutral!$A12,Data!$DA:$DA)+'Rate History'!$D$11*SUMIF(Data!$G:$G,Neutral!$A12,Data!$DB:$DB)+'Rate History'!$D$12*SUMIF(Data!$G:$G,Neutral!$A12,Data!$DC:$DC)+'Rate History'!$D$13*SUMIF(Data!$G:$G,Neutral!$A12,Data!$DD:$DD)+'Rate History'!$D$14*SUMIF(Data!$G:$G,Neutral!$A12,Data!$DE:$DE)+'Rate History'!$D$15*SUMIF(Data!$G:$G,Neutral!$A12,Data!$DF:$DF)+'Rate History'!$D$16*SUMIF(Data!$G:$G,Neutral!$A12,Data!$DG:$DG)+'Rate History'!$D$17*SUMIF(Data!$G:$G,Neutral!$A12,Data!$DH:$DH)+'Rate History'!$D$18*SUMIF(Data!$G:$G,Neutral!$A12,Data!$DI:$DI)+'Rate History'!$D$19*SUMIF(Data!$G:$G,Neutral!$A12,Data!$DJ:$DJ)+'Rate History'!$D$20*SUMIF(Data!$G:$G,Neutral!$A12,Data!$DK:$DK)+'Rate History'!$D$21*SUMIF(Data!$G:$G,Neutral!$A12,Data!$DL:$DL)+'Rate History'!$D$22*SUMIF(Data!$G:$G,Neutral!$A12,Data!$DM:$DM)+'Rate History'!$D$23*SUMIF(Data!$G:$G,Neutral!$A12,Data!$DN:$DN)+'Rate History'!$D$24*SUMIF(Data!$G:$G,Neutral!$A12,Data!$DO:$DO)+'Rate History'!$D$25*SUMIF(Data!$G:$G,Neutral!$A12,Data!$DP:$DP)+'Rate History'!$D$26*SUMIF(Data!$G:$G,Neutral!$A12,Data!$DQ:$DQ)+'Rate History'!$D$27*SUMIF(Data!$G:$G,Neutral!$A12,Data!$DR:$DR)+'Rate History'!$D$28*SUMIF(Data!$G:$G,Neutral!$A12,Data!$DS:$DS)+'Rate History'!$D$29*SUMIF(Data!$G:$G,Neutral!$A12,Data!$DT:$DT)+'Rate History'!$D$30*SUMIF(Data!$G:$G,Neutral!$A12,Data!$DV:$DV)+'Rate History'!$D$31*SUMIF(Data!$G:$G,Neutral!$A12,Data!$DW:$DW)) -> 5384342.1 | C12: =$C$5*('Rate History'!$C$4*SUMIF(Data!$G:$G,Neutral!$A12,Data!$CU:$CU)+'Rate History'!$C$5*SUMIF(Data!$G:$G,Neutral!$A12,Data!$CV:$CV)+'Rate History'!$C$6*SUMIF(Data!$G:$G,Neutral!$A12,Data!$CW:$CW)+'Rate History'!$C$7*SUMIF(Data!$G:$G,Neutral!$A12,Data!$CX:$CX)+'Rate History'!$C$8*SUMIF(Data!$G:$G,Neutral!$A12,Data!$CY:$CY)+'Rate History'!$C$9*SUMIF(Data!$G:$G,Neutral!$A12,Data!$CZ:$CZ)+'Rate History'!$C$10*SUMIF(Data!$G:$G,Neutral!$A12,Data!$DA:$DA)+'Rate History'!$C$11*SUMIF(Data!$G:$G,Neutral!$A12,Data!$DB:$DB)+'Rate History'!$C$12*SUMIF(Data!$G:$G,Neutral!$A12,Data!$DC:$DC)+'Rate History'!$C$13*SUMIF(Data!$G:$G,Neutral!$A12,Data!$DD:$DD)+'Rate History'!$C$14*SUMIF(Data!$G:$G,Neutral!$A12,Data!$DE:$DE)+'Rate History'!$C$15*SUMIF(Data!$G:$G,Neutral!$A12,Data!$DF:$DF)+'Rate History'!$C$16*SUMIF(Data!$G:$G,Neutral!$A12,Data!$DG:$DG)+'Rate History'!$C$17*SUMIF(Data!$G:$G,Neutral!$A12,Data!$DH:$DH)+'Rate History'!$C$18*SUMIF(Data!$G:$G,Neutral!$A12,Data!$DI:$DI)+'Rate History'!$C$19*SUMIF(Data!$G:$G,Neutral!$A12,Data!$DJ:$DJ)+'Rate History'!$C$20*SUMIF(Data!$G:$G,Neutral!$A12,Data!$DK:$DK)+'Rate History'!$C$21*SUMIF(Data!$G:$G,Neutral!$A12,Data!$DL:$DL)+'Rate History'!$C$22*SUMIF(Data!$G:$G,Neutral!$A12,Data!$DM:$DM)+'Rate History'!$C$23*SUMIF(Data!$G:$G,Neutral!$A12,Data!$DN:$DN)+'Rate History'!$C$24*SUMIF(Data!$G:$G,Neutral!$A12,Data!$DO:$DO)+'Rate History'!$C$25*SUMIF(Data!$G:$G,Neutral!$A12,Data!$DP:$DP)+'Rate History'!$C$26*SUMIF(Data!$G:$G,Neutral!$A12,Data!$DQ:$DQ)+'Rate History'!$C$27*SUMIF(Data!$G:$G,Neutral!$A12,Data!$DR:$DR)+'Rate History'!$C$28*SUMIF(Data!$G:$G,Neutral!$A12,Data!$DS:$DS)+'Rate History'!$C$29*SUMIF(Data!$G:$G,Neutral!$A12,Data!$DT:$DT)+'Rate History'!$C$30*SUMIF(Data!$G:$G,Neutral!$A12,Data!$DV:$DV)+'Rate History'!$C$31*SUMIF(Data!$G:$G,Neutral!$A12,Data!$DW:$DW)) -> 5402802.2 | D12: =C12-B12 -> 18460.135 | E12: =IFERROR(D12/B12,"") -> 0.0034284849
A13: Central Texas College | B13: =$B$5*('Rate History'!$D$4*SUMIF(Data!$G:$G,Neutral!$A13,Data!$CU:$CU)+'Rate History'!$D$5*SUMIF(Data!$G:$G,Neutral!$A13,Data!$CV:$CV)+'Rate History'!$D$6*SUMIF(Data!$G:$G,Neutral!$A13,Data!$CW:$CW)+'Rate History'!$D$7*SUMIF(Data!$G:$G,Neutral!$A13,Data!$CX:$CX)+'Rate History'!$D$8*SUMIF(Data!$G:$G,Neutral!$A13,Data!$CY:$CY)+'Rate History'!$D$9*SUMIF(Data!$G:$G,Neutral!$A13,Data!$CZ:$CZ)+'Rate History'!$D$10*SUMIF(Data!$G:$G,Neutral!$A13,Data!$DA:$DA)+'Rate History'!$D$11*SUMIF(Data!$G:$G,Neutral!$A13,Data!$DB:$DB)+'Rate History'!$D$12*SUMIF(Data!$G:$G,Neutral!$A13,Data!$DC:$DC)+'Rate History'!$D$13*SUMIF(Data!$G:$G,Neutral!$A13,Data!$DD:$DD)+'Rate History'!$D$14*SUMIF(Data!$G:$G,Neutral!$A13,Data!$DE:$DE)+'Rate History'!$D$15*SUMIF(Data!$G:$G,Neutral!$A13,Data!$DF:$DF)+'Rate History'!$D$16*SUMIF(Data!$G:$G,Neutral!$A13,Data!$DG:$DG)+'Rate History'!$D$17*SUMIF(Data!$G:$G,Neutral!$A13,Data!$DH:$DH)+'Rate History'!$D$18*SUMIF(Data!$G:$G,Neutral!$A13,Data!$DI:$DI)+'Rate History'!$D$19*SUMIF(Data!$G:$G,Neutral!$A13,Data!$DJ:$DJ)+'Rate History'!$D$20*SUMIF(Data!$G:$G,Neutral!$A13,Data!$DK:$DK)+'Rate History'!$D$21*SUMIF(Data!$G:$G,Neutral!$A13,Data!$DL:$DL)+'Rate History'!$D$22*SUMIF(Data!$G:$G,Neutral!$A13,Data!$DM:$DM)+'Rate History'!$D$23*SUMIF(Data!$G:$G,Neutral!$A13,Data!$DN:$DN)+'Rate History'!$D$24*SUMIF(Data!$G:$G,Neutral!$A13,Data!$DO:$DO)+'Rate History'!$D$25*SUMIF(Data!$G:$G,Neutral!$A13,Data!$DP:$DP)+'Rate History'!$D$26*SUMIF(Data!$G:$G,Neutral!$A13,Data!$DQ:$DQ)+'Rate History'!$D$27*SUMIF(Data!$G:$G,Neutral!$A13,Data!$DR:$DR)+'Rate History'!$D$28*SUMIF(Data!$G:$G,Neutral!$A13,Data!$DS:$DS)+'Rate History'!$D$29*SUMIF(Data!$G:$G,Neutral!$A13,Data!$DT:$DT)+'Rate History'!$D$30*SUMIF(Data!$G:$G,Neutral!$A13,Data!$DV:$DV)+'Rate History'!$D$31*SUMIF(Data!$G:$G,Neutral!$A13,Data!$DW:$DW)) -> 21052383 | C13: =$C$5*('Rate History'!$C$4*SUMIF(Data!$G:$G,Neutral!$A13,Data!$CU:$CU)+'Rate History'!$C$5*SUMIF(Data!$G:$G,Neutral!$A13,Data!$CV:$CV)+'Rate History'!$C$6*SUMIF(Data!$G:$G,Neutral!$A13,Data!$CW:$CW)+'Rate History'!$C$7*SUMIF(Data!$G:$G,Neutral!$A13,Data!$CX:$CX)+'Rate History'!$C$8*SUMIF(Data!$G:$G,Neutral!$A13,Data!$CY:$CY)+'Rate History'!$C$9*SUMIF(Data!$G:$G,Neutral!$A13,Data!$CZ:$CZ)+'Rate History'!$C$10*SUMIF(Data!$G:$G,Neutral!$A13,Data!$DA:$DA)+'Rate History'!$C$11*SUMIF(Data!$G:$G,Neutral!$A13,Data!$DB:$DB)+'Rate History'!$C$12*SUMIF(Data!$G:$G,Neutral!$A13,Data!$DC:$DC)+'Rate History'!$C$13*SUMIF(Data!$G:$G,Neutral!$A13,Data!$DD:$DD)+'Rate History'!$C$14*SUMIF(Data!$G:$G,Neutral!$A13,Data!$DE:$DE)+'Rate History'!$C$15*SUMIF(Data!$G:$G,Neutral!$A13,Data!$DF:$DF)+'Rate History'!$C$16*SUMIF(Data!$G:$G,Neutral!$A13,Data!$DG:$DG)+'Rate History'!$C$17*SUMIF(Data!$G:$G,Neutral!$A13,Data!$DH:$DH)+'Rate History'!$C$18*SUMIF(Data!$G:$G,Neutral!$A13,Data!$DI:$DI)+'Rate History'!$C$19*SUMIF(Data!$G:$G,Neutral!$A13,Data!$DJ:$DJ)+'Rate History'!$C$20*SUMIF(Data!$G:$G,Neutral!$A13,Data!$DK:$DK)+'Rate History'!$C$21*SUMIF(Data!$G:$G,Neutral!$A13,Data!$DL:$DL)+'Rate History'!$C$22*SUMIF(Data!$G:$G,Neutral!$A13,Data!$DM:$DM)+'Rate History'!$C$23*SUMIF(Data!$G:$G,Neutral!$A13,Data!$DN:$DN)+'Rate History'!$C$24*SUMIF(Data!$G:$G,Neutral!$A13,Data!$DO:$DO)+'Rate History'!$C$25*SUMIF(Data!$G:$G,Neutral!$A13,Data!$DP:$DP)+'Rate History'!$C$26*SUMIF(Data!$G:$G,Neutral!$A13,Data!$DQ:$DQ)+'Rate History'!$C$27*SUMIF(Data!$G:$G,Neutral!$A13,Data!$DR:$DR)+'Rate History'!$C$28*SUMIF(Data!$G:$G,Neutral!$A13,Data!$DS:$DS)+'Rate History'!$C$29*SUMIF(Data!$G:$G,Neutral!$A13,Data!$DT:$DT)+'Rate History'!$C$30*SUMIF(Data!$G:$G,Neutral!$A13,Data!$DV:$DV)+'Rate History'!$C$31*SUMIF(Data!$G:$G,Neutral!$A13,Data!$DW:$DW)) -> 20992719 | D13: =C13-B13 -> -59664.131 | E13: =IFERROR(D13/B13,"") -> -0.0028340797
A14: Cisco Junior College | B14: =$B$5*('Rate History'!$D$4*SUMIF(Data!$G:$G,Neutral!$A14,Data!$CU:$CU)+'Rate History'!$D$5*SUMIF(Data!$G:$G,Neutral!$A14,Data!$CV:$CV)+'Rate History'!$D$6*SUMIF(Data!$G:$G,Neutral!$A14,Data!$CW:$CW)+'Rate History'!$D$7*SUMIF(Data!$G:$G,Neutral!$A14,Data!$CX:$CX)+'Rate History'!$D$8*SUMIF(Data!$G:$G,Neutral!$A14,Data!$CY:$CY)+'Rate History'!$D$9*SUMIF(Data!$G:$G,Neutral!$A14,Data!$CZ:$CZ)+'Rate History'!$D$10*SUMIF(Data!$G:$G,Neutral!$A14,Data!$DA:$DA)+'Rate History'!$D$11*SUMIF(Data!$G:$G,Neutral!$A14,Data!$DB:$DB)+'Rate History'!$D$12*SUMIF(Data!$G:$G,Neutral!$A14,Data!$DC:$DC)+'Rate History'!$D$13*SUMIF(Data!$G:$G,Neutral!$A14,Data!$DD:$DD)+'Rate History'!$D$14*SUMIF(Data!$G:$G,Neutral!$A14,Data!$DE:$DE)+'Rate History'!$D$15*SUMIF(Data!$G:$G,Neutral!$A14,Data!$DF:$DF)+'Rate History'!$D$16*SUMIF(Data!$G:$G,Neutral!$A14,Data!$DG:$DG)+'Rate History'!$D$17*SUMIF(Data!$G:$G,Neutral!$A14,Data!$DH:$DH)+'Rate History'!$D$18*SUMIF(Data!$G:$G,Neutral!$A14,Data!$DI:$DI)+'Rate History'!$D$19*SUMIF(Data!$G:$G,Neutral!$A14,Data!$DJ:$DJ)+'Rate History'!$D$20*SUMIF(Data!$G:$G,Neutral!$A14,Data!$DK:$DK)+'Rate History'!$D$21*SUMIF(Data!$G:$G,Neutral!$A14,Data!$DL:$DL)+'Rate History'!$D$22*SUMIF(Data!$G:$G,Neutral!$A14,Data!$DM:$DM)+'Rate History'!$D$23*SUMIF(Data!$G:$G,Neutral!$A14,Data!$DN:$DN)+'Rate History'!$D$24*SUMIF(Data!$G:$G,Neutral!$A14,Data!$DO:$DO)+'Rate History'!$D$25*SUMIF(Data!$G:$G,Neutral!$A14,Data!$DP:$DP)+'Rate History'!$D$26*SUMIF(Data!$G:$G,Neutral!$A14,Data!$DQ:$DQ)+'Rate History'!$D$27*SUMIF(Data!$G:$G,Neutral!$A14,Data!$DR:$DR)+'Rate History'!$D$28*SUMIF(Data!$G:$G,Neutral!$A14,Data!$DS:$DS)+'Rate History'!$D$29*SUMIF(Data!$G:$G,Neutral!$A14,Data!$DT:$DT)+'Rate History'!$D$30*SUMIF(Data!$G:$G,Neutral!$A14,Data!$DV:$DV)+'Rate History'!$D$31*SUMIF(Data!$G:$G,Neutral!$A14,Data!$DW:$DW)) -> 5896656.8 | C14: =$C$5*('Rate History'!$C$4*SUMIF(Data!$G:$G,Neutral!$A14,Data!$CU:$CU)+'Rate History'!$C$5*SUMIF(Data!$G:$G,Neutral!$A14,Data!$CV:$CV)+'Rate History'!$C$6*SUMIF(Data!$G:$G,Neutral!$A14,Data!$CW:$CW)+'Rate History'!$C$7*SUMIF(Data!$G:$G,Neutral!$A14,Data!$CX:$CX)+'Rate History'!$C$8*SUMIF(Data!$G:$G,Neutral!$A14,Data!$CY:$CY)+'Rate History'!$C$9*SUMIF(Data!$G:$G,Neutral!$A14,Data!$CZ:$CZ)+'Rate History'!$C$10*SUMIF(Data!$G:$G,Neutral!$A14,Data!$DA:$DA)+'Rate History'!$C$11*SUMIF(Data!$G:$G,Neutral!$A14,Data!$DB:$DB)+'Rate History'!$C$12*SUMIF(Data!$G:$G,Neutral!$A14,Data!$DC:$DC)+'Rate History'!$C$13*SUMIF(Data!$G:$G,Neutral!$A14,Data!$DD:$DD)+'Rate History'!$C$14*SUMIF(Data!$G:$G,Neutral!$A14,Data!$DE:$DE)+'Rate History'!$C$15*SUMIF(Data!$G:$G,Neutral!$A14,Data!$DF:$DF)+'Rate History'!$C$16*SUMIF(Data!$G:$G,Neutral!$A14,Data!$DG:$DG)+'Rate History'!$C$17*SUMIF(Data!$G:$G,Neutral!$A14,Data!$DH:$DH)+'Rate History'!$C$18*SUMIF(Data!$G:$G,Neutral!$A14,Data!$DI:$DI)+'Rate History'!$C$19*SUMIF(Data!$G:$G,Neutral!$A14,Data!$DJ:$DJ)+'Rate History'!$C$20*SUMIF(Data!$G:$G,Neutral!$A14,Data!$DK:$DK)+'Rate History'!$C$21*SUMIF(Data!$G:$G,Neutral!$A14,Data!$DL:$DL)+'Rate History'!$C$22*SUMIF(Data!$G:$G,Neutral!$A14,Data!$DM:$DM)+'Rate History'!$C$23*SUMIF(Data!$G:$G,Neutral!$A14,Data!$DN:$DN)+'Rate History'!$C$24*SUMIF(Data!$G:$G,Neutral!$A14,Data!$DO:$DO)+'Rate History'!$C$25*SUMIF(Data!$G:$G,Neutral!$A14,Data!$DP:$DP)+'Rate History'!$C$26*SUMIF(Data!$G:$G,Neutral!$A14,Data!$DQ:$DQ)+'Rate History'!$C$27*SUMIF(Data!$G:$G,Neutral!$A14,Data!$DR:$DR)+'Rate History'!$C$28*SUMIF(Data!$G:$G,Neutral!$A14,Data!$DS:$DS)+'Rate History'!$C$29*SUMIF(Data!$G:$G,Neutral!$A14,Data!$DT:$DT)+'Rate History'!$C$30*SUMIF(Data!$G:$G,Neutral!$A14,Data!$DV:$DV)+'Rate History'!$C$31*SUMIF(Data!$G:$G,Neutral!$A14,Data!$DW:$DW)) -> 5891791.5 | D14: =C14-B14 -> -4865.2114 | E14: =IFERROR(D14/B14,"") -> -0.00082507963
A15: Clarendon College | B15: =$B$5*('Rate History'!$D$4*SUMIF(Data!$G:$G,Neutral!$A15,Data!$CU:$CU)+'Rate History'!$D$5*SUMIF(Data!$G:$G,Neutral!$A15,Data!$CV:$CV)+'Rate History'!$D$6*SUMIF(Data!$G:$G,Neutral!$A15,Data!$CW:$CW)+'Rate History'!$D$7*SUMIF(Data!$G:$G,Neutral!$A15,Data!$CX:$CX)+'Rate History'!$D$8*SUMIF(Data!$G:$G,Neutral!$A15,Data!$CY:$CY)+'Rate History'!$D$9*SUMIF(Data!$G:$G,Neutral!$A15,Data!$CZ:$CZ)+'Rate History'!$D$10*SUMIF(Data!$G:$G,Neutral!$A15,Data!$DA:$DA)+'Rate History'!$D$11*SUMIF(Data!$G:$G,Neutral!$A15,Data!$DB:$DB)+'Rate History'!$D$12*SUMIF(Data!$G:$G,Neutral!$A15,Data!$DC:$DC)+'Rate History'!$D$13*SUMIF(Data!$G:$G,Neutral!$A15,Data!$DD:$DD)+'Rate History'!$D$14*SUMIF(Data!$G:$G,Neutral!$A15,Data!$DE:$DE)+'Rate History'!$D$15*SUMIF(Data!$G:$G,Neutral!$A15,Data!$DF:$DF)+'Rate History'!$D$16*SUMIF(Data!$G:$G,Neutral!$A15,Data!$DG:$DG)+'Rate History'!$D$17*SUMIF(Data!$G:$G,Neutral!$A15,Data!$DH:$DH)+'Rate History'!$D$18*SUMIF(Data!$G:$G,Neutral!$A15,Data!$DI:$DI)+'Rate History'!$D$19*SUMIF(Data!$G:$G,Neutral!$A15,Data!$DJ:$DJ)+'Rate History'!$D$20*SUMIF(Data!$G:$G,Neutral!$A15,Data!$DK:$DK)+'Rate History'!$D$21*SUMIF(Data!$G:$G,Neutral!$A15,Data!$DL:$DL)+'Rate History'!$D$22*SUMIF(Data!$G:$G,Neutral!$A15,Data!$DM:$DM)+'Rate History'!$D$23*SUMIF(Data!$G:$G,Neutral!$A15,Data!$DN:$DN)+'Rate History'!$D$24*SUMIF(Data!$G:$G,Neutral!$A15,Data!$DO:$DO)+'Rate History'!$D$25*SUMIF(Data!$G:$G,Neutral!$A15,Data!$DP:$DP)+'Rate History'!$D$26*SUMIF(Data!$G:$G,Neutral!$A15,Data!$DQ:$DQ)+'Rate History'!$D$27*SUMIF(Data!$G:$G,Neutral!$A15,Data!$DR:$DR)+'Rate History'!$D$28*SUMIF(Data!$G:$G,Neutral!$A15,Data!$DS:$DS)+'Rate History'!$D$29*SUMIF(Data!$G:$G,Neutral!$A15,Data!$DT:$DT)+'Rate History'!$D$30*SUMIF(Data!$G:$G,Neutral!$A15,Data!$DV:$DV)+'Rate History'!$D$31*SUMIF(Data!$G:$G,Neutral!$A15,Data!$DW:$DW)) -> 2425795.6 | C15: =$C$5*('Rate History'!$C$4*SUMIF(Data!$G:$G,Neutral!$A15,Data!$CU:$CU)+'Rate History'!$C$5*SUMIF(Data!$G:$G,Neutral!$A15,Data!$CV:$CV)+'Rate History'!$C$6*SUMIF(Data!$G:$G,Neutral!$A15,Data!$CW:$CW)+'Rate History'!$C$7*SUMIF(Data!$G:$G,Neutral!$A15,Data!$CX:$CX)+'Rate History'!$C$8*SUMIF(Data!$G:$G,Neutral!$A15,Data!$CY:$CY)+'Rate History'!$C$9*SUMIF(Data!$G:$G,Neutral!$A15,Data!$CZ:$CZ)+'Rate History'!$C$10*SUMIF(Data!$G:$G,Neutral!$A15,Data!$DA:$DA)+'Rate History'!$C$11*SUMIF(Data!$G:$G,Neutral!$A15,Data!$DB:$DB)+'Rate History'!$C$12*SUMIF(Data!$G:$G,Neutral!$A15,Data!$DC:$DC)+'Rate History'!$C$13*SUMIF(Data!$G:$G,Neutral!$A15,Data!$DD:$DD)+'Rate History'!$C$14*SUMIF(Data!$G:$G,Neutral!$A15,Data!$DE:$DE)+'Rate History'!$C$15*SUMIF(Data!$G:$G,Neutral!$A15,Data!$DF:$DF)+'Rate History'!$C$16*SUMIF(Data!$G:$G,Neutral!$A15,Data!$DG:$DG)+'Rate History'!$C$17*SUMIF(Data!$G:$G,Neutral!$A15,Data!$DH:$DH)+'Rate History'!$C$18*SUMIF(Data!$G:$G,Neutral!$A15,Data!$DI:$DI)+'Rate History'!$C$19*SUMIF(Data!$G:$G,Neutral!$A15,Data!$DJ:$DJ)+'Rate History'!$C$20*SUMIF(Data!$G:$G,Neutral!$A15,Data!$DK:$DK)+'Rate History'!$C$21*SUMIF(Data!$G:$G,Neutral!$A15,Data!$DL:$DL)+'Rate History'!$C$22*SUMIF(Data!$G:$G,Neutral!$A15,Data!$DM:$DM)+'Rate History'!$C$23*SUMIF(Data!$G:$G,Neutral!$A15,Data!$DN:$DN)+'Rate History'!$C$24*SUMIF(Data!$G:$G,Neutral!$A15,Data!$DO:$DO)+'Rate History'!$C$25*SUMIF(Data!$G:$G,Neutral!$A15,Data!$DP:$DP)+'Rate History'!$C$26*SUMIF(Data!$G:$G,Neutral!$A15,Data!$DQ:$DQ)+'Rate History'!$C$27*SUMIF(Data!$G:$G,Neutral!$A15,Data!$DR:$DR)+'Rate History'!$C$28*SUMIF(Data!$G:$G,Neutral!$A15,Data!$DS:$DS)+'Rate History'!$C$29*SUMIF(Data!$G:$G,Neutral!$A15,Data!$DT:$DT)+'Rate History'!$C$30*SUMIF(Data!$G:$G,Neutral!$A15,Data!$DV:$DV)+'Rate History'!$C$31*SUMIF(Data!$G:$G,Neutral!$A15,Data!$DW:$DW)) -> 2426096.2 | D15: =C15-B15 -> 300.59339 | E15: =IFERROR(D15/B15,"") -> 0.00012391538
A16: Coastal Bend College | B16: =$B$5*('Rate History'!$D$4*SUMIF(Data!$G:$G,Neutral!$A16,Data!$CU:$CU)+'Rate History'!$D$5*SUMIF(Data!$G:$G,Neutral!$A16,Data!$CV:$CV)+'Rate History'!$D$6*SUMIF(Data!$G:$G,Neutral!$A16,Data!$CW:$CW)+'Rate History'!$D$7*SUMIF(Data!$G:$G,Neutral!$A16,Data!$CX:$CX)+'Rate History'!$D$8*SUMIF(Data!$G:$G,Neutral!$A16,Data!$CY:$CY)+'Rate History'!$D$9*SUMIF(Data!$G:$G,Neutral!$A16,Data!$CZ:$CZ)+'Rate History'!$D$10*SUMIF(Data!$G:$G,Neutral!$A16,Data!$DA:$DA)+'Rate History'!$D$11*SUMIF(Data!$G:$G,Neutral!$A16,Data!$DB:$DB)+'Rate History'!$D$12*SUMIF(Data!$G:$G,Neutral!$A16,Data!$DC:$DC)+'Rate History'!$D$13*SUMIF(Data!$G:$G,Neutral!$A16,Data!$DD:$DD)+'Rate History'!$D$14*SUMIF(Data!$G:$G,Neutral!$A16,Data!$DE:$DE)+'Rate History'!$D$15*SUMIF(Data!$G:$G,Neutral!$A16,Data!$DF:$DF)+'Rate History'!$D$16*SUMIF(Data!$G:$G,Neutral!$A16,Data!$DG:$DG)+'Rate History'!$D$17*SUMIF(Data!$G:$G,Neutral!$A16,Data!$DH:$DH)+'Rate History'!$D$18*SUMIF(Data!$G:$G,Neutral!$A16,Data!$DI:$DI)+'Rate History'!$D$19*SUMIF(Data!$G:$G,Neutral!$A16,Data!$DJ:$DJ)+'Rate History'!$D$20*SUMIF(Data!$G:$G,Neutral!$A16,Data!$DK:$DK)+'Rate History'!$D$21*SUMIF(Data!$G:$G,Neutral!$A16,Data!$DL:$DL)+'Rate History'!$D$22*SUMIF(Data!$G:$G,Neutral!$A16,Data!$DM:$DM)+'Rate History'!$D$23*SUMIF(Data!$G:$G,Neutral!$A16,Data!$DN:$DN)+'Rate History'!$D$24*SUMIF(Data!$G:$G,Neutral!$A16,Data!$DO:$DO)+'Rate History'!$D$25*SUMIF(Data!$G:$G,Neutral!$A16,Data!$DP:$DP)+'Rate History'!$D$26*SUMIF(Data!$G:$G,Neutral!$A16,Data!$DQ:$DQ)+'Rate History'!$D$27*SUMIF(Data!$G:$G,Neutral!$A16,Data!$DR:$DR)+'Rate History'!$D$28*SUMIF(Data!$G:$G,Neutral!$A16,Data!$DS:$DS)+'Rate History'!$D$29*SUMIF(Data!$G:$G,Neutral!$A16,Data!$DT:$DT)+'Rate History'!$D$30*SUMIF(Data!$G:$G,Neutral!$A16,Data!$DV:$DV)+'Rate History'!$D$31*SUMIF(Data!$G:$G,Neutral!$A16,Data!$DW:$DW)) -> 6904178.2 | C16: =$C$5*('Rate History'!$C$4*SUMIF(Data!$G:$G,Neutral!$A16,Data!$CU:$CU)+'Rate History'!$C$5*SUMIF(Data!$G:$G,Neutral!$A16,Data!$CV:$CV)+'Rate History'!$C$6*SUMIF(Data!$G:$G,Neutral!$A16,Data!$CW:$CW)+'Rate History'!$C$7*SUMIF(Data!$G:$G,Neutral!$A16,Data!$CX:$CX)+'Rate History'!$C$8*SUMIF(Data!$G:$G,Neutral!$A16,Data!$CY:$CY)+'Rate History'!$C$9*SUMIF(Data!$G:$G,Neutral!$A16,Data!$CZ:$CZ)+'Rate History'!$C$10*SUMIF(Data!$G:$G,Neutral!$A16,Data!$DA:$DA)+'Rate History'!$C$11*SUMIF(Data!$G:$G,Neutral!$A16,Data!$DB:$DB)+'Rate History'!$C$12*SUMIF(Data!$G:$G,Neutral!$A16,Data!$DC:$DC)+'Rate History'!$C$13*SUMIF(Data!$G:$G,Neutral!$A16,Data!$DD:$DD)+'Rate History'!$C$14*SUMIF(Data!$G:$G,Neutral!$A16,Data!$DE:$DE)+'Rate History'!$C$15*SUMIF(Data!$G:$G,Neutral!$A16,Data!$DF:$DF)+'Rate History'!$C$16*SUMIF(Data!$G:$G,Neutral!$A16,Data!$DG:$DG)+'Rate History'!$C$17*SUMIF(Data!$G:$G,Neutral!$A16,Data!$DH:$DH)+'Rate History'!$C$18*SUMIF(Data!$G:$G,Neutral!$A16,Data!$DI:$DI)+'Rate History'!$C$19*SUMIF(Data!$G:$G,Neutral!$A16,Data!$DJ:$DJ)+'Rate History'!$C$20*SUMIF(Data!$G:$G,Neutral!$A16,Data!$DK:$DK)+'Rate History'!$C$21*SUMIF(Data!$G:$G,Neutral!$A16,Data!$DL:$DL)+'Rate History'!$C$22*SUMIF(Data!$G:$G,Neutral!$A16,Data!$DM:$DM)+'Rate History'!$C$23*SUMIF(Data!$G:$G,Neutral!$A16,Data!$DN:$DN)+'Rate History'!$C$24*SUMIF(Data!$G:$G,Neutral!$A16,Data!$DO:$DO)+'Rate History'!$C$25*SUMIF(Data!$G:$G,Neutral!$A16,Data!$DP:$DP)+'Rate History'!$C$26*SUMIF(Data!$G:$G,Neutral!$A16,Data!$DQ:$DQ)+'Rate History'!$C$27*SUMIF(Data!$G:$G,Neutral!$A16,Data!$DR:$DR)+'Rate History'!$C$28*SUMIF(Data!$G:$G,Neutral!$A16,Data!$DS:$DS)+'Rate History'!$C$29*SUMIF(Data!$G:$G,Neutral!$A16,Data!$DT:$DT)+'Rate History'!$C$30*SUMIF(Data!$G:$G,Neutral!$A16,Data!$DV:$DV)+'Rate History'!$C$31*SUMIF(Data!$G:$G,Neutral!$A16,Data!$DW:$DW)) -> 6906099.2 | D16: =C16-B16 -> 1920.9916 | E16: =IFERROR(D16/B16,"") -> 0.00027823609
A17: College of the Mainland Community College District | B17: =$B$5*('Rate History'!$D$4*SUMIF(Data!$G:$G,Neutral!$A17,Data!$CU:$CU)+'Rate History'!$D$5*SUMIF(Data!$G:$G,Neutral!$A17,Data!$CV:$CV)+'Rate History'!$D$6*SUMIF(Data!$G:$G,Neutral!$A17,Data!$CW:$CW)+'Rate History'!$D$7*SUMIF(Data!$G:$G,Neutral!$A17,Data!$CX:$CX)+'Rate History'!$D$8*SUMIF(Data!$G:$G,Neutral!$A17,Data!$CY:$CY)+'Rate History'!$D$9*SUMIF(Data!$G:$G,Neutral!$A17,Data!$CZ:$CZ)+'Rate History'!$D$10*SUMIF(Data!$G:$G,Neutral!$A17,Data!$DA:$DA)+'Rate History'!$D$11*SUMIF(Data!$G:$G,Neutral!$A17,Data!$DB:$DB)+'Rate History'!$D$12*SUMIF(Data!$G:$G,Neutral!$A17,Data!$DC:$DC)+'Rate History'!$D$13*SUMIF(Data!$G:$G,Neutral!$A17,Data!$DD:$DD)+'Rate History'!$D$14*SUMIF(Data!$G:$G,Neutral!$A17,Data!$DE:$DE)+'Rate History'!$D$15*SUMIF(Data!$G:$G,Neutral!$A17,Data!$DF:$DF)+'Rate History'!$D$16*SUMIF(Data!$G:$G,Neutral!$A17,Data!$DG:$DG)+'Rate History'!$D$17*SUMIF(Data!$G:$G,Neutral!$A17,Data!$DH:$DH)+'Rate History'!$D$18*SUMIF(Data!$G:$G,Neutral!$A17,Data!$DI:$DI)+'Rate History'!$D$19*SUMIF(Data!$G:$G,Neutral!$A17,Data!$DJ:$DJ)+'Rate History'!$D$20*SUMIF(Data!$G:$G,Neutral!$A17,Data!$DK:$DK)+'Rate History'!$D$21*SUMIF(Data!$G:$G,Neutral!$A17,Data!$DL:$DL)+'Rate History'!$D$22*SUMIF(Data!$G:$G,Neutral!$A17,Data!$DM:$DM)+'Rate History'!$D$23*SUMIF(Data!$G:$G,Neutral!$A17,Data!$DN:$DN)+'Rate History'!$D$24*SUMIF(Data!$G:$G,Neutral!$A17,Data!$DO:$DO)+'Rate History'!$D$25*SUMIF(Data!$G:$G,Neutral!$A17,Data!$DP:$DP)+'Rate History'!$D$26*SUMIF(Data!$G:$G,Neutral!$A17,Data!$DQ:$DQ)+'Rate History'!$D$27*SUMIF(Data!$G:$G,Neutral!$A17,Data!$DR:$DR)+'Rate History'!$D$28*SUMIF(Data!$G:$G,Neutral!$A17,Data!$DS:$DS)+'Rate History'!$D$29*SUMIF(Data!$G:$G,Neutral!$A17,Data!$DT:$DT)+'Rate History'!$D$30*SUMIF(Data!$G:$G,Neutral!$A17,Data!$DV:$DV)+'Rate History'!$D$31*SUMIF(Data!$G:$G,Neutral!$A17,Data!$DW:$DW)) -> 0 | C17: =$C$5*('Rate History'!$C$4*SUMIF(Data!$G:$G,Neutral!$A17,Data!$CU:$CU)+'Rate History'!$C$5*SUMIF(Data!$G:$G,Neutral!$A17,Data!$CV:$CV)+'Rate History'!$C$6*SUMIF(Data!$G:$G,Neutral!$A17,Data!$CW:$CW)+'Rate History'!$C$7*SUMIF(Data!$G:$G,Neutral!$A17,Data!$CX:$CX)+'Rate History'!$C$8*SUMIF(Data!$G:$G,Neutral!$A17,Data!$CY:$CY)+'Rate History'!$C$9*SUMIF(Data!$G:$G,Neutral!$A17,Data!$CZ:$CZ)+'Rate History'!$C$10*SUMIF(Data!$G:$G,Neutral!$A17,Data!$DA:$DA)+'Rate History'!$C$11*SUMIF(Data!$G:$G,Neutral!$A17,Data!$DB:$DB)+'Rate History'!$C$12*SUMIF(Data!$G:$G,Neutral!$A17,Data!$DC:$DC)+'Rate History'!$C$13*SUMIF(Data!$G:$G,Neutral!$A17,Data!$DD:$DD)+'Rate History'!$C$14*SUMIF(Data!$G:$G,Neutral!$A17,Data!$DE:$DE)+'Rate History'!$C$15*SUMIF(Data!$G:$G,Neutral!$A17,Data!$DF:$DF)+'Rate History'!$C$16*SUMIF(Data!$G:$G,Neutral!$A17,Data!$DG:$DG)+'Rate History'!$C$17*SUMIF(Data!$G:$G,Neutral!$A17,Data!$DH:$DH)+'Rate History'!$C$18*SUMIF(Data!$G:$G,Neutral!$A17,Data!$DI:$DI)+'Rate History'!$C$19*SUMIF(Data!$G:$G,Neutral!$A17,Data!$DJ:$DJ)+'Rate History'!$C$20*SUMIF(Data!$G:$G,Neutral!$A17,Data!$DK:$DK)+'Rate History'!$C$21*SUMIF(Data!$G:$G,Neutral!$A17,Data!$DL:$DL)+'Rate History'!$C$22*SUMIF(Data!$G:$G,Neutral!$A17,Data!$DM:$DM)+'Rate History'!$C$23*SUMIF(Data!$G:$G,Neutral!$A17,Data!$DN:$DN)+'Rate History'!$C$24*SUMIF(Data!$G:$G,Neutral!$A17,Data!$DO:$DO)+'Rate History'!$C$25*SUMIF(Data!$G:$G,Neutral!$A17,Data!$DP:$DP)+'Rate History'!$C$26*SUMIF(Data!$G:$G,Neutral!$A17,Data!$DQ:$DQ)+'Rate History'!$C$27*SUMIF(Data!$G:$G,Neutral!$A17,Data!$DR:$DR)+'Rate History'!$C$28*SUMIF(Data!$G:$G,Neutral!$A17,Data!$DS:$DS)+'Rate History'!$C$29*SUMIF(Data!$G:$G,Neutral!$A17,Data!$DT:$DT)+'Rate History'!$C$30*SUMIF(Data!$G:$G,Neutral!$A17,Data!$DV:$DV)+'Rate History'!$C$31*SUMIF(Data!$G:$G,Neutral!$A17,Data!$DW:$DW)) -> 0 | D17: =C17-B17 -> 0 | E17: =IFERROR(D17/B17,"")
... A62: Lamar State College-Port Arthur | B62: =$B$5*('Rate History'!$D$4*SUMIF(Data!$G:$G,Neutral!$A62,Data!$CU:$CU)+'Rate History'!$D$5*SUMIF(Data!$G:$G,Neutral!$A62,Data!$CV:$CV)+'Rate History'!$D$6*SUMIF(Data!$G:$G,Neutral!$A62,Data!$CW:$CW)+'Rate History'!$D$7*SUMIF(Data!$G:$G,Neutral!$A62,Data!$CX:$CX)+'Rate History'!$D$8*SUMIF(Data!$G:$G,Neutral!$A62,Data!$CY:$CY)+'Rate History'!$D$9*SUMIF(Data!$G:$G,Neutral!$A62,Data!$CZ:$CZ)+'Rate History'!$D$10*SUMIF(Data!$G:$G,Neutral!$A62,Data!$DA:$DA)+'Rate History'!$D$11*SUMIF(Data!$G:$G,Neutral!$A62,Data!$DB:$DB)+'Rate History'!$D$12*SUMIF(Data!$G:$G,Neutral!$A62,Data!$DC:$DC)+'Rate History'!$D$13*SUMIF(Data!$G:$G,Neutral!$A62,Data!$DD:$DD)+'Rate History'!$D$14*SUMIF(Data!$G:$G,Neutral!$A62,Data!$DE:$DE)+'Rate History'!$D$15*SUMIF(Data!$G:$G,Neutral!$A62,Data!$DF:$DF)+'Rate History'!$D$16*SUMIF(Data!$G:$G,Neutral!$A62,Data!$DG:$DG)+'Rate History'!$D$17*SUMIF(Data!$G:$G,Neutral!$A62,Data!$DH:$DH)+'Rate History'!$D$18*SUMIF(Data!$G:$G,Neutral!$A62,Data!$DI:$DI)+'Rate History'!$D$19*SUMIF(Data!$G:$G,Neutral!$A62,Data!$DJ:$DJ)+'Rate History'!$D$20*SUMIF(Data!$G:$G,Neutral!$A62,Data!$DK:$DK)+'Rate History'!$D$21*SUMIF(Data!$G:$G,Neutral!$A62,Data!$DL:$DL)+'Rate History'!$D$22*SUMIF(Data!$G:$G,Neutral!$A62,Data!$DM:$DM)+'Rate History'!$D$23*SUMIF(Data!$G:$G,Neutral!$A62,Data!$DN:$DN)+'Rate History'!$D$24*SUMIF(Data!$G:$G,Neutral!$A62,Data!$DO:$DO)+'Rate History'!$D$25*SUMIF(Data!$G:$G,Neutral!$A62,Data!$DP:$DP)+'Rate History'!$D$26*SUMIF(Data!$G:$G,Neutral!$A62,Data!$DQ:$DQ)+'Rate History'!$D$27*SUMIF(Data!$G:$G,Neutral!$A62,Data!$DR:$DR)+'Rate History'!$D$28*SUMIF(Data!$G:$G,Neutral!$A62,Data!$DS:$DS)+'Rate History'!$D$29*SUMIF(Data!$G:$G,Neutral!$A62,Data!$DT:$DT)+'Rate History'!$D$30*SUMIF(Data!$G:$G,Neutral!$A62,Data!$DV:$DV)+'Rate History'!$D$31*SUMIF(Data!$G:$G,Neutral!$A62,Data!$DW:$DW)) -> 4618313 | C62: =$C$5*('Rate History'!$C$4*SUMIF(Data!$G:$G,Neutral!$A62,Data!$CU:$CU)+'Rate History'!$C$5*SUMIF(Data!$G:$G,Neutral!$A62,Data!$CV:$CV)+'Rate History'!$C$6*SUMIF(Data!$G:$G,Neutral!$A62,Data!$CW:$CW)+'Rate History'!$C$7*SUMIF(Data!$G:$G,Neutral!$A62,Data!$CX:$CX)+'Rate History'!$C$8*SUMIF(Data!$G:$G,Neutral!$A62,Data!$CY:$CY)+'Rate History'!$C$9*SUMIF(Data!$G:$G,Neutral!$A62,Data!$CZ:$CZ)+'Rate History'!$C$10*SUMIF(Data!$G:$G,Neutral!$A62,Data!$DA:$DA)+'Rate History'!$C$11*SUMIF(Data!$G:$G,Neutral!$A62,Data!$DB:$DB)+'Rate History'!$C$12*SUMIF(Data!$G:$G,Neutral!$A62,Data!$DC:$DC)+'Rate History'!$C$13*SUMIF(Data!$G:$G,Neutral!$A62,Data!$DD:$DD)+'Rate History'!$C$14*SUMIF(Data!$G:$G,Neutral!$A62,Data!$DE:$DE)+'Rate History'!$C$15*SUMIF(Data!$G:$G,Neutral!$A62,Data!$DF:$DF)+'Rate History'!$C$16*SUMIF(Data!$G:$G,Neutral!$A62,Data!$DG:$DG)+'Rate History'!$C$17*SUMIF(Data!$G:$G,Neutral!$A62,Data!$DH:$DH)+'Rate History'!$C$18*SUMIF(Data!$G:$G,Neutral!$A62,Data!$DI:$DI)+'Rate History'!$C$19*SUMIF(Data!$G:$G,Neutral!$A62,Data!$DJ:$DJ)+'Rate History'!$C$20*SUMIF(Data!$G:$G,Neutral!$A62,Data!$DK:$DK)+'Rate History'!$C$21*SUMIF(Data!$G:$G,Neutral!$A62,Data!$DL:$DL)+'Rate History'!$C$22*SUMIF(Data!$G:$G,Neutral!$A62,Data!$DM:$DM)+'Rate History'!$C$23*SUMIF(Data!$G:$G,Neutral!$A62,Data!$DN:$DN)+'Rate History'!$C$24*SUMIF(Data!$G:$G,Neutral!$A62,Data!$DO:$DO)+'Rate History'!$C$25*SUMIF(Data!$G:$G,Neutral!$A62,Data!$DP:$DP)+'Rate History'!$C$26*SUMIF(Data!$G:$G,Neutral!$A62,Data!$DQ:$DQ)+'Rate History'!$C$27*SUMIF(Data!$G:$G,Neutral!$A62,Data!$DR:$DR)+'Rate History'!$C$28*SUMIF(Data!$G:$G,Neutral!$A62,Data!$DS:$DS)+'Rate History'!$C$29*SUMIF(Data!$G:$G,Neutral!$A62,Data!$DT:$DT)+'Rate History'!$C$30*SUMIF(Data!$G:$G,Neutral!$A62,Data!$DV:$DV)+'Rate History'!$C$31*SUMIF(Data!$G:$G,Neutral!$A62,Data!$DW:$DW)) -> 4669230.7 | D62: =C62-B62 -> 50917.746 | E62: =IFERROR(D62/B62,"") -> 0.011025183
A63: Total | B63: =SUM(B5:B62) -> 9.9038411e+08 | C63: =SUM(C6:C62) -> 9.9038411e+08 | D63: =C63-B63 -> 0 | E63: =IFERROR(D63/B63,"") -> 0

Sheet 1
A1: =Summary!A1 -> Community and Technical Colleges, Report of Fundable Operating Expenses, Fiscal Year (FY) 2009
A2: 003607 | B2: =VLOOKUP(A2,Data!A:G,7,0) -> Alamo Community College District
F3: =IFERROR(VLOOKUP(A2,Data!A:C,3,0),"0") -> 1
A4: Fund | B4: Total Expense by Discipline | D4: Contact Hours | E4: Expense | F4: Expense per Contact Hour
A5: 1 | B5: Agriculture | D5: =D36 -> 68847 | E5: =E36+E67+IFERROR($E$105/$D$105*D5,0) -> 523452.55 | F5: =IFERROR(E5/D5,"") -> 7.603128
A6: 2 | B6: Architecture and Precision Production Trades | D6: =D37 -> 179804 | E6: =E37+E68+IFERROR($E$105/$D$105*D6,0) -> 2175949.9 | F6: =IFERROR(E6/D6,"") -> 12.101788
A7: 3 | B7: Biology, Physical Sciences, and Science Technology | D7: =D38 -> 2330704 | E7: =E38+E69+IFERROR($E$105/$D$105*D7,0) -> 21827268 | F7: =IFERROR(E7/D7,"") -> 9.3650965
A8: 4 | B8: Business Management, Marketing, and Administrative Services | D8: =D39 -> 1128485 | E8: =E39+E70+IFERROR($E$105/$D$105*D8,0) -> 11106880 | F8: =IFERROR(E8/D8,"") -> 9.8422926
A9: 5 | B9: Career Pilot | D9: =D40 -> 2992 | E9: =E40+E71+IFERROR($E$105/$D$105*D9,0) -> 319964.58 | F9: =IFERROR(E9/D9,"") -> 106.94003
A10: 6 | B10: Communications | D10: =D41 -> 310847 | E10: =E41+E72+IFERROR($E$105/$D$105*D10,0) -> 3455223.4 | F10: =IFERROR(E10/D10,"") -> 11.115511
A11: 7 | B11: Computer and Information Sciences | D11: =D42 -> 800119 | E11: =E42+E73+IFERROR($E$105/$D$105*D11,0) -> 8779006.6 | F11: =IFERROR(E11/D11,"") -> 10.972126
A12: 8 | B12: Construction Trades | D12: =D43 -> 88658 | E12: =E43+E74+IFERROR($E$105/$D$105*D12,0) -> 950461.02 | F12: =IFERROR(E12/D12,"") -> 10.720533
A13: 9 | B13: Consumer and Homemaking Education | D13: =D44 -> 775268 | E13: =E44+E75+IFERROR($E$105/$D$105*D13,0) -> 7598974.1 | F13: =IFERROR(E13/D13,"") -> 9.8017384
A14: 10 | B14: Engineering | D14: =D45 -> 23168 | E14: =E45+E76+IFERROR($E$105/$D$105*D14,0) -> 420199.72 | F14: =IFERROR(E14/D14,"") -> 18.137073
A15: 11 | B15: Engineering Related | D15: =D46 -> 397436 | E15: =E46+E77+IFERROR($E$105/$D$105*D15,0) -> 5245358.6 | F15: =IFERROR(E15/D15,"") -> 13.197996
A16: 12 | B16: English Language, Lit, Philosophy, Humanities, & Interdisciplinary | D16: =D47 -> 4053134 | E16: =E47+E78+IFERROR($E$105/$D$105*D16,0) -> 37235881 | F16: =IFERROR(E16/D16,"") -> 9.1869356
... A32: 29 | B32: Developmental Education - Reading/Writing | D32: =D63 -> 0 | E32: =E63+E94+IFERROR($E$105/$D$105*D32,0) -> 0 | F32: =IFERROR(E32/D32,"")
C33: Total | D33: =SUM(D5:D32) -> 21475760 | E33: =SUM(E5:E32) -> 2.0866447e+08 | F33: =IFERROR(E33/D33,"") -> 9.7162787
A35: Fund | B35: Departmental Operating Expense by Discipline | D35: Contact Hours | E35: Expense | F35: Expense per Contact Hour
A36: 1 | B36: Agriculture | D36: =IF(F3="1",SUMIF(Data!A:A,$A$2,Data!CU:CU),0) -> 68847 | E36: =IF(F3="1",SUMIF(Data!$A:$A,$A$2,Data!IO:IO),0) -> 108188 | F36: =IFERROR(E36/D36,"") -> 1.5714265
A37: 2 | B37: Architecture and Precision Production Trades | D37: =IF(F3="1",SUMIF(Data!A:A,$A$2,Data!CV:CV),0) -> 179804 | E37: =IF(F3="1",SUMIF(Data!$A:$A,$A$2,Data!IP:IP),0) -> 479594 | F37: =IFERROR(E37/D37,"") -> 2.6673155
A38: 3 | B38: Biology, Physical Sciences, and Science Technology | D38: =IF(F3="1",SUMIF(Data!A:A,$A$2,Data!CW:CW),0) -> 2330704 | E38: =IF(F3="1",SUMIF(Data!$A:$A,$A$2,Data!IQ:IQ),0) -> 3103606 | F38: =IFERROR(E38/D38,"") -> 1.3316174
A39: 4 | B39: Business Management, Marketing, and Administrative Services | D39: =IF(F3="1",SUMIF(Data!A:A,$A$2,Data!CX:CX),0) -> 1128485 | E39: =IF(F3="1",SUMIF(Data!$A:$A,$A$2,Data!IR:IR),0) -> 1963966 | F39: =IFERROR(E39/D39,"") -> 1.7403563
A40: 5 | B40: Career Pilot | D40: =IF(F3="1",SUMIF(Data!A:A,$A$2,Data!CY:CY),0) -> 2992 | E40: =IF(F3="1",SUMIF(Data!$A:$A,$A$2,Data!IS:IS),0) -> 260728 | F40: =IFERROR(E40/D40,"") -> 87.141711
A41: 6 | B41: Communications | D41: =IF(F3="1",SUMIF(Data!A:A,$A$2,Data!CZ:CZ),0) -> 310847 | E41: =IF(F3="1",SUMIF(Data!$A:$A,$A$2,Data!IT:IT),0) -> 1303777 | F41: =IFERROR(E41/D41,"") -> 4.1942724
A42: 7 | B42: Computer and Information Sciences | D42: =IF(F3="1",SUMIF(Data!A:A,$A$2,Data!DA:DA),0) -> 800119 | E42: =IF(F3="1",SUMIF(Data!$A:$A,$A$2,Data!IU:IU),0) -> 1907518 | F42: =IFERROR(E42/D42,"") -> 2.3840429
A43: 8 | B43: Construction Trades | D43: =IF(F3="1",SUMIF(Data!A:A,$A$2,Data!DB:DB),0) -> 88658 | E43: =IF(F3="1",SUMIF(Data!$A:$A,$A$2,Data!IV:IV),0) -> 196901 | F43: =IFERROR(E43/D43,"") -> 2.2209051
A44: 9 | B44: Consumer and Homemaking Education | D44: =IF(F3="1",SUMIF(Data!A:A,$A$2,Data!DC:DC),0) -> 775268 | E44: =IF(F3="1",SUMIF(Data!$A:$A,$A$2,Data!IW:IW),0) -> 2144377 | F44: =IFERROR(E44/D44,"") -> 2.7659816
A45: 10 | B45: Engineering | D45: =IF(F3="1",SUMIF(Data!A:A,$A$2,Data!DD:DD),0) -> 23168 | E45: =IF(F3="1",SUMIF(Data!$A:$A,$A$2,Data!IX:IX),0) -> 111278 | F45: =IFERROR(E45/D45,"") -> 4.8030905
A46: 11 | B46: Engineering Related | D46: =IF(F3="1",SUMIF(Data!A:A,$A$2,Data!DE:DE),0) -> 397436 | E46: =IF(F3="1",SUMIF(Data!$A:$A,$A$2,Data!IY:IY),0) -> 1681784 | F46: =IFERROR(E46/D46,"") -> 4.2315845
A47: 12 | B47: English Language, Lit, Philosophy, Humanities, & Interdisciplinary | D47: =IF(F3="1",SUMIF(Data!A:A,$A$2,Data!DF:DF),0) -> 4053134 | E47: =IF(F3="1",SUMIF(Data!$A:$A,$A$2,Data!IZ:IZ),0) -> 4673136 | F47: =IFERROR(E47/D47,"") -> 1.1529685
A48: 13 | B48: Foreign Languages | D48: =IF(F3="1",SUMIF(Data!A:A,$A$2,Data!DG:DG),0) -> 726212 | E48: =IF(F3="1",SUMIF(Data!$A:$A,$A$2,Data!JA:JA),0) -> 779757 | F48: =IFERROR(E48/D48,"") -> 1.0737319
A49: 14 | B49: Health Occupations - Dental Assistants, Medical Lab, and Assoc. Degree Nursing | D49: =IF(F3="1",SUMIF(Data!A:A,$A$2,Data!DH:DH),0) -> 460608 | E49: =IF(F3="1",SUMIF(Data!$A:$A,$A$2,Data!JB:JB),0) -> 2799995 | F49: =IFERROR(E49/D49,"") -> 6.0789109
A50: 15 | B50: Health Occupations - Dental Hygiene | D50: =IF(F3="1",SUMIF(Data!A:A,$A$2,Data!DI:DI),0) -> 0 | E50: =IF(F3="1",SUMIF(Data!$A:$A,$A$2,Data!JC:JC),0) -> 0 | F50: =IFERROR(E50/D50,"")
A51: 16 | B51: Health Occupations - Other | D51: =IF(F3="1",SUMIF(Data!A:A,$A$2,Data!DJ:DJ),0) -> 686985 | E51: =IF(F3="1",SUMIF(Data!$A:$A,$A$2,Data!JD:JD),0) -> 1925570 | F51: =IFERROR(E51/D51,"") -> 2.8029287
A52: 17 | B52: Health Occupations - Respiratory Therapy | D52: =IF(F3="1",SUMIF(Data!A:A,$A$2,Data!DK:DK),0) -> 41360 | E52: =IF(F3="1",SUMIF(Data!$A:$A,$A$2,Data!JE:JE),0) -> 85935 | F52: =IFERROR(E52/D52,"") -> 2.0777321
A53: 18 | B53: Health Occupations - Vocational Nursing | D53: =IF(F3="1",SUMIF(Data!A:A,$A$2,Data!DL:DL),0) -> 190576 | E53: =IF(F3="1",SUMIF(Data!$A:$A,$A$2,Data!JF:JF),0) -> 388038 | F53: =IFERROR(E53/D53,"") -> 2.0361326
A54: 19 | B54: Mathematics | D54: =IF(F3="1",SUMIF(Data!A:A,$A$2,Data!DM:DM),0) -> 2889492 | E54: =IF(F3="1",SUMIF(Data!$A:$A,$A$2,Data!JG:JG),0) -> 2863669 | F54: =IFERROR(E54/D54,"") -> 0.99106313
A55: 20 | B55: Mechanics and Repairers - Automotive | D55: =IF(F3="1",SUMIF(Data!A:A,$A$2,Data!DN:DN),0) -> 295925 | E55: =IF(F3="1",SUMIF(Data!$A:$A,$A$2,Data!JH:JH),0) -> 706020 | F55: =IFERROR(E55/D55,"") -> 2.3858072
A56: 21 | B56: Mechanics and Repairers - Diesel, Aviation Mechanics, and Transportation Workers | D56: =IF(F3="1",SUMIF(Data!A:A,$A$2,Data!DO:DO),0) -> 187908 | E56: =IF(F3="1",SUMIF(Data!$A:$A,$A$2,Data!JI:JI),0) -> 531577 | F56: =IFERROR(E56/D56,"") -> 2.8289216
A57: 22 | B57: Mechanics and Repairers - Electronics | D57: =IF(F3="1",SUMIF(Data!A:A,$A$2,Data!DP:DP),0) -> 25880 | E57: =IF(F3="1",SUMIF(Data!$A:$A,$A$2,Data!JJ:JJ),0) -> 14318 | F57: =IFERROR(E57/D57,"") -> 0.55324575
A58: 23 | B58: Physical Education and Fitness | D58: =IF(F3="1",SUMIF(Data!A:A,$A$2,Data!DQ:DQ),0) -> 585216 | E58: =IF(F3="1",SUMIF(Data!$A:$A,$A$2,Data!JK:JK),0) -> 844503 | F58: =IFERROR(E58/D58,"") -> 1.443062
A59: 24 | B59: Protective Services and Public Administration | D59: =IF(F3="1",SUMIF(Data!A:A,$A$2,Data!DR:DR),0) -> 540424 | E59: =IF(F3="1",SUMIF(Data!$A:$A,$A$2,Data!JL:JL),0) -> 1173018 | F59: =IFERROR(E59/D59,"") -> 2.1705513
A60: 25 | B60: Psychology, Social Sciences, and History | D60: =IF(F3="1",SUMIF(Data!A:A,$A$2,Data!DS:DS),0) -> 3607776 | E60: =IF(F3="1",SUMIF(Data!$A:$A,$A$2,Data!JM:JM),0) -> 2232871 | F60: =IFERROR(E60/D60,"") -> 0.61890511
A61: 26 | B61: Visual and Performing Arts | D61: =IF(F3="1",SUMIF(Data!A:A,$A$2,Data!DT:DT),0) -> 1077936 | E61: =IF(F3="1",SUMIF(Data!$A:$A,$A$2,Data!JN:JN),0) -> 2575342 | F61: =IFERROR(E61/D61,"") -> 2.3891418
A62: 28 | B62: Developmental Education - Math | D62: =IF(F3="1",SUMIF(Data!A:A,$A$2,Data!DV:DV),0) -> 0 | E62: =IF(F3="1",SUMIF(Data!$A:$A,$A$2,Data!JP:JP),0) -> 0 | F62: =IFERROR(E62/D62,"")
A63: 29 | B63: Developmental Education - Reading/Writing | D63: =IF(F3="1",SUMIF(Data!A:A,$A$2,Data!DW:DW),0) -> 0 | E63: =IF(F3="1",SUMIF(Data!$A:$A,$A$2,Data!JQ:JQ),0) -> 0 | F63: =IFERROR(E63/D63,"")
C64: Total | D64: =SUM(D36:D63) -> 21475760 | E64: =SUM(E36:E63) -> 34855466 | F64: =IFERROR(E64/D64,"") -> 1.6230143
A66: Fund | B66: Faculty Salaries by Discipline | D66: Contact Hours | E66: Expense | F66: Expense per Contact Hour
A67: 1 | B67: Agriculture | D67: =D36 -> 68847 | E67: =IF(F3="1",SUMIF(Data!A:A,$A$2,Data!DY:DY),0) -> 106176 | F67: =IFERROR(E67/D67,"") -> 1.5422023
A68: 2 | B68: Architecture and Precision Production Trades | D68: =D37 -> 179804 | E68: =IF(F3="1",SUMIF(Data!A:A,$A$2,Data!DZ:DZ),0) -> 889126 | F68: =IFERROR(E68/D68,"") -> 4.9449734
A69: 3 | B69: Biology, Physical Sciences, and Science Technology | D69: =D38 -> 2330704 | E69: =IF(F3="1",SUMIF(Data!A:A,$A$2,Data!EA:EA),0) -> 8259968 | F69: =IFERROR(E69/D69,"") -> 3.5439798
A70: 4 | B70: Business Management, Marketing, and Administrative Services | D70: =D39 -> 1128485 | E70: =IF(F3="1",SUMIF(Data!A:A,$A$2,Data!EB:EB),0) -> 4076581 | F70: =IFERROR(E70/D70,"") -> 3.612437
A71: 5 | B71: Career Pilot | D71: =D40 -> 2992 | E71: =IF(F3="1",SUMIF(Data!A:A,$A$2,Data!EC:EC),0) -> 45804 | F71: =IFERROR(E71/D71,"") -> 15.308824
A72: 6 | B72: Communications | D72: =D41 -> 310847 | E72: =IF(F3="1",SUMIF(Data!A:A,$A$2,Data!ED:ED),0) -> 755899 | F72: =IFERROR(E72/D72,"") -> 2.4317397
A73: 7 | B73: Computer and Information Sciences | D73: =D42 -> 800119 | E73: =IF(F3="1",SUMIF(Data!A:A,$A$2,Data!EE:EE),0) -> 3279355 | F73: =IFERROR(E73/D73,"") -> 4.0985841
A74: 8 | B74: Construction Trades | D74: =D43 -> 88658 | E74: =IF(F3="1",SUMIF(Data!A:A,$A$2,Data!EF:EF),0) -> 355530 | F74: =IFERROR(E74/D74,"") -> 4.0101288
A75: 9 | B75: Consumer and Homemaking Education | D75: =D44 -> 775268 | E75: =IF(F3="1",SUMIF(Data!A:A,$A$2,Data!EG:EG),0) -> 1974032 | F75: =IFERROR(E75/D75,"") -> 2.5462576
A76: 10 | B76: Engineering | D76: =D45 -> 23168 | E76: =IF(F3="1",SUMIF(Data!A:A,$A$2,Data!EH:EH),0) -> 204909 | F76: =IFERROR(E76/D76,"") -> 8.8444838
A77: 11 | B77: Engineering Related | D77: =D46 -> 397436 | E77: =IF(F3="1",SUMIF(Data!A:A,$A$2,Data!EI:EI),0) -> 1779286 | F77: =IFERROR(E77/D77,"") -> 4.476912
A78: 12 | B78: English Language, Lit, Philosophy, Humanities, & Interdisciplinary | D78: =D47 -> 4053134 | E78: =IF(F3="1",SUMIF(Data!A:A,$A$2,Data!EJ:EJ),0) -> 14366203 | F78: =IFERROR(E78/D78,"") -> 3.5444678
A79: 13 | B79: Foreign Languages | D79: =D48 -> 726212 | E79: =IF(F3="1",SUMIF(Data!A:A,$A$2,Data!EK:EK),0) -> 1736932 | F79: =IFERROR(E79/D79,"") -> 2.3917699
A80: 14 | B80: Health Occupations - Dental Assistants, Medical Lab, and Assoc. Degree Nursing | D80: =D49 -> 460608 | E80: =IF(F3="1",SUMIF(Data!A:A,$A$2,Data!EL:EL),0) -> 3435838 | F80: =IFERROR(E80/D80,"") -> 7.4593537
A81: 15 | B81: Health Occupations - Dental Hygiene | D81: =D50 -> 0 | E81: =IF(F3="1",SUMIF(Data!A:A,$A$2,Data!EM:EM),0) -> 0 | F81: =IFERROR(E81/D81,"")
A82: 16 | B82: Health Occupations - Other | D82: =D51 -> 686985 | E82: =IF(F3="1",SUMIF(Data!A:A,$A$2,Data!EN:EN),0) -> 2555260 | F82: =IFERROR(E82/D82,"") -> 3.7195281
