Workbook
Name Dnumber: [1]Report!$A$1
Name SPSS: #REF!
Name SPSS: #REF!
Name Start: #REF!
Name Start: 'Tax Bill Summary'!#REF!
Name Start: 'Tax Bill Summary'!#REF!
Name TitelRegion1.a2.t514.2: 'FY16 Tax Bill'!$T$514
Name TitleRegion1.a2.t514.1: 'FY16 Feb Forecast'!$T$514
Name TitleRegion1.a2.t514.3: 'FY16 Change'!$T$514

Sheet Dist Region Table
A1: MPLS & ST PAUL | D1: 1
A2: OTHER METRO, INNER | D2: 2
A3: OTHER METRO, OUTER | D3: 3
A4: NONMET>=2K | D4: 4
A5: NONMET 1K-2K | D5: 5
A6: NONMET < 1K | D6: 6
A7: CHARTER | D7: 7
A8: COOPERATIVES | D8: 8
A9: NONCHARTER FUDGE | D9: 9
A11: 1 | B11: 1 | C11: AITKIN | D11: 5
A12: 1.2 | B12: 3 | C12: MINNEAPOLIS | D12: 1
A13: 2 | B13: 1 | C13: HILL CITY | D13: 6
A14: 4 | B14: 1 | C14: MCGREGOR | D14: 6
A15: 6 | B15: 3 | C15: SOUTH ST. PAUL | D15: 2
A16: 11 | B16: 1 | C16: ANOKA-HENNEPIN | D16: 3
A17: 12 | B17: 1 | C17: CENTENNIAL | D17: 3
A18: 13 | B18: 1 | C18: COLUMBIA HEIGHTS | D18: 2
A19: 14 | B19: 1 | C19: FRIDLEY | D19: 3
A20: 15 | B20: 1 | C20: ST. FRANCIS | D20: 3
A21: 16 | B21: 1 | C21: SPRING LAKE PARK | D21: 3
A22: 22 | B22: 1 | C22: DETROIT LAKES | D22: 4
... A507: 6000 | B507: 62 | C507: COOPERATIVE & INTERMED DISTRICTS | D507: 24

Sheet FY16 Feb Forecast
A1: n/a | C1: n/a | E1: n/a | F1: FY 2016 as of February Forecast - Max Revenue | M1: n/a | N1: n/a | O1: n/a | P1: n/a | Q1: n/a | R1: n/a | S1: n/a | T1: n/a | U1: Column left blank intentionally | V1: Column left blank intentionally | W1: Column left blank intentionally
A2: n/a | B2: n/a | C2: n/a | F2: n/a | G2: n/a | H2: n/a | I2: Location | J2: Location | K2: Location | L2: Refer- | M2: Refer- | N2: Refer- | O2: Total | P2: Total | Q2: Total | R2: Total | S2: Total | T2: Total
A3: n/a | B3: n/a | C3: n/a | E3: FY 2016 | F3: Equity | G3: Equity | H3: Equity | I3: Equity | J3: Equity | K3: Equity | L3: endum | M3: endum | N3: endum | O3: Impacted | P3: Impacted | Q3: Impacted | R3: Revenue / | S3: Levy / | T3: Aid /
A4: n/a | B4: n/a | C4: n/a | E4: ADM | F4: Revenue | G4: Levy | H4: Aid | I4: Revenue | J4: Levy | K4: Aid | L4: Revenue | M4: Levy | N4: Aid | O4: Revenue | P4: Levy | Q4: Aid | R4: APU | S4: APU | T4: APU
A5: line left blank intentionally | B5: n/a
A6: n/a | C6: TOTAL | E6: =SUM(E18:E514) -> 921112 | F6: =SUM(F18:F514) -> 106775552 | G6: =SUM(G18:G514) -> 78879395 | H6: =SUM(H18:H514) -> 27896157 | I6: =SUM(I18:I514) -> 245125421 | J6: =SUM(J18:J514) -> 207462464 | K6: =SUM(K18:K514) -> 37662957 | L6: =SUM(L18:L514) -> 781257518 | ... Q6: =SUM(Q18:Q514) -> 249756664 | R6: =+IF($E6=0, 0, O6/$E6) -> 1230.2071 | S6: =+IF($E6=0, 0, P6/$E6) -> 959.06017 | T6: =+IF($E6=0, 0, Q6/$E6) -> 271.1469
A7: line left blank intentionally
A8: n/a | C8: MPLS & ST PAUL | D8: 1 | E8: =SUMIF($D$18:$D$514,$D8,E$18:E$514) -> 80335 | F8: =SUMIF($D$18:$D$514,$D8,F$18:F$514) -> 4016730 | G8: =SUMIF($D$18:$D$514,$D8,G$18:G$514) -> 3409709 | H8: =SUMIF($D$18:$D$514,$D8,H$18:H$514) -> 607021 | I8: =SUMIF($D$18:$D$514,$D8,I$18:I$514) -> 34061870 | J8: =SUMIF($D$18:$D$514,$D8,J$18:J$514) -> 28914332 | K8: =SUMIF($D$18:$D$514,$D8,K$18:K$514) -> 5147538 | L8: =SUMIF($D$18:$D$514,$D8,L$18:L$514) -> 82021892 | ... N8: =SUMIF($D$18:$D$514,$D8,N$18:N$514) -> 14453242 | O8: =+F8+I8+L8 -> 120100492 | P8: =+G8+J8+M8 -> 99892691 | Q8: =+H8+K8+N8 -> 20207801 | R8: =+IF($E8=0, 0, O8/$E8) -> 1494.9959 | S8: =+IF($E8=0, 0, P8/$E8) -> 1243.4517 | T8: =+IF($E8=0, 0, Q8/$E8) -> 251.54417
A9: n/a | C9: OTHER METRO, INNER | D9: 2 | E9: =SUMIF($D$18:$D$514,$D9,E$18:E$514) -> 95296 | F9: =SUMIF($D$18:$D$514,$D9,F$18:F$514) -> 10087609 | G9: =SUMIF($D$18:$D$514,$D9,G$18:G$514) -> 9084281 | H9: =SUMIF($D$18:$D$514,$D9,H$18:H$514) -> 1003328 | I9: =SUMIF($D$18:$D$514,$D9,I$18:I$514) -> 40405271 | J9: =SUMIF($D$18:$D$514,$D9,J$18:J$514) -> 37193191 | K9: =SUMIF($D$18:$D$514,$D9,K$18:K$514) -> 3212080 | L9: =SUMIF($D$18:$D$514,$D9,L$18:L$514) -> 106269709 | ... N9: =SUMIF($D$18:$D$514,$D9,N$18:N$514) -> 11829212 | O9: =+F9+I9+L9 -> 156762589 | P9: =+G9+J9+M9 -> 140717969 | Q9: =+H9+K9+N9 -> 16044620 | R9: =+IF($E9=0, 0, O9/$E9) -> 1645.007 | S9: =+IF($E9=0, 0, P9/$E9) -> 1476.6409 | T9: =+IF($E9=0, 0, Q9/$E9) -> 168.36614
A10: n/a | C10: OTHER METRO, OUTER | D10: 3 | E10: =SUMIF($D$18:$D$514,$D10,E$18:E$514) -> 286862 | F10: =SUMIF($D$18:$D$514,$D10,F$18:F$514) -> 32447767 | G10: =SUMIF($D$18:$D$514,$D10,G$18:G$514) -> 28447251 | H10: =SUMIF($D$18:$D$514,$D10,H$18:H$514) -> 4000516 | I10: =SUMIF($D$18:$D$514,$D10,I$18:I$514) -> 121629744 | J10: =SUMIF($D$18:$D$514,$D10,J$18:J$514) -> 108437428 | K10: =SUMIF($D$18:$D$514,$D10,K$18:K$514) -> 13192316 | L10: =SUMIF($D$18:$D$514,$D10,L$18:L$514) -> 284810801 | ... N10: =SUMIF($D$18:$D$514,$D10,N$18:N$514) -> 43727936 | O10: =+F10+I10+L10 -> 438888312 | P10: =+G10+J10+M10 -> 377967544 | Q10: =+H10+K10+N10 -> 60920768 | R10: =+IF($E10=0, 0, O10/$E10) -> 1529.9632 | S10: =+IF($E10=0, 0, P10/$E10) -> 1317.5936 | T10: =+IF($E10=0, 0, Q10/$E10) -> 212.3696
A11: n/a | C11: NONMET>=2K | D11: 4 | E11: =SUMIF($D$18:$D$514,$D11,E$18:E$514) -> 199708 | F11: =SUMIF($D$18:$D$514,$D11,F$18:F$514) -> 26041447 | G11: =SUMIF($D$18:$D$514,$D11,G$18:G$514) -> 20430567 | H11: =SUMIF($D$18:$D$514,$D11,H$18:H$514) -> 5610880 | I11: =SUMIF($D$18:$D$514,$D11,I$18:I$514) -> 47481818 | J11: =SUMIF($D$18:$D$514,$D11,J$18:J$514) -> 37095969 | K11: =SUMIF($D$18:$D$514,$D11,K$18:K$514) -> 10385849 | L11: =SUMIF($D$18:$D$514,$D11,L$18:L$514) -> 103221608 | ... N11: =SUMIF($D$18:$D$514,$D11,N$18:N$514) -> 39312714 | O11: =+F11+I11+L11 -> 176744873 | P11: =+G11+J11+M11 -> 121435430 | Q11: =+H11+K11+N11 -> 55309443 | R11: =+IF($E11=0, 0, O11/$E11) -> 885.01649 | S11: =+IF($E11=0, 0, P11/$E11) -> 608.06492 | T11: =+IF($E11=0, 0, Q11/$E11) -> 276.95156
A12: n/a | C12: NONMET 1K-2K | D12: 5 | E12: =SUMIF($D$18:$D$514,$D12,E$18:E$514) -> 101624 | F12: =SUMIF($D$18:$D$514,$D12,F$18:F$514) -> 13061574 | G12: =SUMIF($D$18:$D$514,$D12,G$18:G$514) -> 9109814 | H12: =SUMIF($D$18:$D$514,$D12,H$18:H$514) -> 3951760 | I12: =SUMIF($D$18:$D$514,$D12,I$18:I$514) -> 3608303 | J12: =SUMIF($D$18:$D$514,$D12,J$18:J$514) -> 2797224 | K12: =SUMIF($D$18:$D$514,$D12,K$18:K$514) -> 811079 | L12: =SUMIF($D$18:$D$514,$D12,L$18:L$514) -> 64769230 | ... N12: =SUMIF($D$18:$D$514,$D12,N$18:N$514) -> 28414418 | O12: =+F12+I12+L12 -> 81439107 | P12: =+G12+J12+M12 -> 48261850 | Q12: =+H12+K12+N12 -> 33177257 | R12: =+IF($E12=0, 0, O12/$E12) -> 801.37671 | S12: =+IF($E12=0, 0, P12/$E12) -> 474.90603 | T12: =+IF($E12=0, 0, Q12/$E12) -> 326.47069
A13: n/a | C13: NONMET < 1K | D13: 6 | E13: =SUMIF($D$18:$D$514,$D13,E$18:E$514) -> 92857 | F13: =SUMIF($D$18:$D$514,$D13,F$18:F$514) -> 10778201 | G13: =SUMIF($D$18:$D$514,$D13,G$18:G$514) -> 7006886 | H13: =SUMIF($D$18:$D$514,$D13,H$18:H$514) -> 3771315 | I13: =SUMIF($D$18:$D$514,$D13,I$18:I$514) -> 177444 | J13: =SUMIF($D$18:$D$514,$D13,J$18:J$514) -> 136479 | K13: =SUMIF($D$18:$D$514,$D13,K$18:K$514) -> 40965 | L13: =SUMIF($D$18:$D$514,$D13,L$18:L$514) -> 85404065 | ... N13: =SUMIF($D$18:$D$514,$D13,N$18:N$514) -> 31896813 | O13: =+F13+I13+L13 -> 96359710 | P13: =+G13+J13+M13 -> 60650617 | Q13: =+H13+K13+N13 -> 35709093 | R13: =+IF($E13=0, 0, O13/$E13) -> 1037.7216 | S13: =+IF($E13=0, 0, P13/$E13) -> 653.1615 | T13: =+IF($E13=0, 0, Q13/$E13) -> 384.56005
A14: n/a | C14: CHARTER | D14: 7 | E14: =SUMIF($D$18:$D$514,$D14,E$18:E$514) -> 55972 | F14: =SUMIF($D$18:$D$514,$D14,F$18:F$514) -> 6487360 | G14: =SUMIF($D$18:$D$514,$D14,G$18:G$514) -> 0 | H14: =SUMIF($D$18:$D$514,$D14,H$18:H$514) -> 6487360 | I14: =SUMIF($D$18:$D$514,$D14,I$18:I$514) -> 0 | J14: =SUMIF($D$18:$D$514,$D14,J$18:J$514) -> 0 | K14: =SUMIF($D$18:$D$514,$D14,K$18:K$514) -> 0 | L14: =SUMIF($D$18:$D$514,$D14,L$18:L$514) -> 0 | ... N14: =SUMIF($D$18:$D$514,$D14,N$18:N$514) -> 0 | O14: =+F14+I14+L14 -> 6487360 | P14: =+G14+J14+M14 -> 0 | Q14: =+H14+K14+N14 -> 6487360 | R14: =+IF($E14=0, 0, O14/$E14) -> 115.90367 | S14: =+IF($E14=0, 0, P14/$E14) -> 0 | T14: =+IF($E14=0, 0, Q14/$E14) -> 115.90367
A15: n/a | C15: COOPERATIVES | D15: 8 | E15: =SUMIF($D$18:$D$514,$D15,E$18:E$514) -> 0 | F15: =SUMIF($D$18:$D$514,$D15,F$18:F$514) -> 0 | G15: =SUMIF($D$18:$D$514,$D15,G$18:G$514) -> 0 | H15: =SUMIF($D$18:$D$514,$D15,H$18:H$514) -> 0 | I15: =SUMIF($D$18:$D$514,$D15,I$18:I$514) -> 0 | J15: =SUMIF($D$18:$D$514,$D15,J$18:J$514) -> 0 | K15: =SUMIF($D$18:$D$514,$D15,K$18:K$514) -> 0 | L15: =SUMIF($D$18:$D$514,$D15,L$18:L$514) -> 0 | ... N15: =SUMIF($D$18:$D$514,$D15,N$18:N$514) -> 0 | O15: =+F15+I15+L15 -> 0 | P15: =+G15+J15+M15 -> 0 | Q15: =+H15+K15+N15 -> 0 | R15: =+IF($E15=0, 0, O15/$E15*1000) -> 0 | S15: =+IF($E15=0, 0, P15/$E15*1000) -> 0 | T15: =+IF($E15=0, 0, Q15/$E15*1000) -> 0
A16: n/a | C16: NONCHARTER FUDGE | D16: 9 | E16: =SUMIF($D$18:$D$514,$D16,E$18:E$514) -> 8458 | F16: =SUMIF($D$18:$D$514,$D16,F$18:F$514) -> 3854864 | G16: =SUMIF($D$18:$D$514,$D16,G$18:G$514) -> 1390887 | H16: =SUMIF($D$18:$D$514,$D16,H$18:H$514) -> 2463977 | I16: =SUMIF($D$18:$D$514,$D16,I$18:I$514) -> -2239029 | J16: =SUMIF($D$18:$D$514,$D16,J$18:J$514) -> -7112159 | K16: =SUMIF($D$18:$D$514,$D16,K$18:K$514) -> 4873130 | L16: =SUMIF($D$18:$D$514,$D16,L$18:L$514) -> 54760213 | ... N16: =SUMIF($D$18:$D$514,$D16,N$18:N$514) -> 14563215 | O16: =+F16+I16+L16 -> 56376048 | P16: =+G16+J16+M16 -> 34475726 | Q16: =+H16+K16+N16 -> 21900322 | R16: =+IF($E16=0, 0, O16/$E16) -> 6665.4112 | S16: =+IF($E16=0, 0, P16/$E16) -> 4076.1085 | T16: =+IF($E16=0, 0, Q16/$E16) -> 2589.3027
A17: line left blank intentionally
A18: 1 | B18: 1 | C18: AITKIN | D18: 5 | E18: =+SUMIF('GE16FEB14 Unfudged'!$A$2:$A$498, $A18, 'GE16FEB14 Unfudged'!$D$2:$D$498) -> 1285 | F18: 185040 | G18: 185040 | H18: 0 | I18: 0 | J18: 0 | K18: 0 | L18: 385500 | M18: 260672 | N18: 124828 | O18: =+F18+I18+L18 -> 570540 | P18: =+G18+J18+M18 -> 445712 | Q18: =+H18+K18+N18 -> 124828 | R18: =+IF($E18=0, 0, O18/$E18) -> 444 | S18: =+IF($E18=0, 0, P18/$E18) -> 346.85759 | T18: =+IF($E18=0, 0, Q18/$E18) -> 97.142412
A19: 1.2 | B19: 3 | C19: MINNEAPOLIS | D19: 1 | E19: =+SUMIF('GE16FEB14 Unfudged'!$A$2:$A$498, $A19, 'GE16FEB14 Unfudged'!$D$2:$D$498) -> 39607 | F19: 1980330 | G19: 1980330 | H19: 0 | I19: 16793198 | J19: 16793198 | K19: 0 | L19: 55978780 | M19: 52894542 | N19: 3084238 | O19: =+F19+I19+L19 -> 74752308 | P19: =+G19+J19+M19 -> 71668070 | Q19: =+H19+K19+N19 -> 3084238 | R19: =+IF($E19=0, 0, O19/$E19) -> 1887.3509 | S19: =+IF($E19=0, 0, P19/$E19) -> 1809.4799 | T19: =+IF($E19=0, 0, Q19/$E19) -> 77.871033
A20: 2 | B20: 1 | C20: HILL CITY | D20: 6 | E20: =+SUMIF('GE16FEB14 Unfudged'!$A$2:$A$498, $A20, 'GE16FEB14 Unfudged'!$D$2:$D$498) -> 284 | F20: 40889 | G20: 22793 | H20: 18096 | I20: 0 | J20: 0 | K20: 0 | L20: 85185 | M20: 27520 | N20: 57665 | O20: =+F20+I20+L20 -> 126074 | P20: =+G20+J20+M20 -> 50313 | Q20: =+H20+K20+N20 -> 75761 | R20: =+IF($E20=0, 0, O20/$E20) -> 443.92254 | S20: =+IF($E20=0, 0, P20/$E20) -> 177.15845 | T20: =+IF($E20=0, 0, Q20/$E20) -> 266.76408
A21: 4 | B21: 1 | C21: MCGREGOR | D21: 6 | E21: =+SUMIF('GE16FEB14 Unfudged'!$A$2:$A$498, $A21, 'GE16FEB14 Unfudged'!$D$2:$D$498) -> 434 | F21: 62554 | G21: 62554 | H21: 0 | I21: 0 | J21: 0 | K21: 0 | L21: 130320 | M21: 77314 | N21: 53006 | O21: =+F21+I21+L21 -> 192874 | P21: =+G21+J21+M21 -> 139868 | Q21: =+H21+K21+N21 -> 53006 | R21: =+IF($E21=0, 0, O21/$E21) -> 444.41014 | S21: =+IF($E21=0, 0, P21/$E21) -> 322.2765 | T21: =+IF($E21=0, 0, Q21/$E21) -> 122.13364
A22: 6 | B22: 3 | C22: SOUTH ST. PAUL | D22: 2 | E22: =+SUMIF('GE16FEB14 Unfudged'!$A$2:$A$498, $A22, 'GE16FEB14 Unfudged'!$D$2:$D$498) -> 3736 | F22: 557934 | G22: 396251 | H22: 161683 | I22: 1584234 | J22: 1125142 | K22: 459092 | L22: 2005625 | M22: 1089699 | N22: 915926 | O22: =+F22+I22+L22 -> 4147793 | P22: =+G22+J22+M22 -> 2611092 | Q22: =+H22+K22+N22 -> 1536701 | R22: =+IF($E22=0, 0, O22/$E22) -> 1110.223 | S22: =+IF($E22=0, 0, P22/$E22) -> 698.90043 | T22: =+IF($E22=0, 0, Q22/$E22) -> 411.32254
A23: 11 | B23: 1 | C23: ANOKA-HENNEPIN | D23: 3 | E23: =+SUMIF('GE16FEB14 Unfudged'!$A$2:$A$498, $A23, 'GE16FEB14 Unfudged'!$D$2:$D$498) -> 39798 | F23: 4558334 | G23: 3244342 | H23: 1313992 | I23: 16874267 | J23: 12010067 | K23: 4864200 | L23: 39397832 | M23: 27106091 | N23: 12291741 | O23: =+F23+I23+L23 -> 60830433 | P23: =+G23+J23+M23 -> 42360500 | Q23: =+H23+K23+N23 -> 18469933 | R23: =+IF($E23=0, 0, O23/$E23) -> 1528.4796 | S23: =+IF($E23=0, 0, P23/$E23) -> 1064.3877 | T23: =+IF($E23=0, 0, Q23/$E23) -> 464.09199
A24: 12 | B24: 1 | C24: CENTENNIAL | D24: 3 | E24: =+SUMIF('GE16FEB14 Unfudged'!$A$2:$A$498, $A24, 'GE16FEB14 Unfudged'!$D$2:$D$498) -> 6971 | F24: 1079123 | G24: 838445 | H24: 240678 | I24: 2955789 | J24: 2296557 | K24: 659232 | L24: 3244954 | M24: 1838023 | N24: 1406931 | O24: =+F24+I24+L24 -> 7279866 | P24: =+G24+J24+M24 -> 4973025 | Q24: =+H24+K24+N24 -> 2306841 | R24: =+IF($E24=0, 0, O24/$E24) -> 1044.3073 | S24: =+IF($E24=0, 0, P24/$E24) -> 713.38761 | T24: =+IF($E24=0, 0, Q24/$E24) -> 330.91967
A25: 13 | B25: 1 | C25: COLUMBIA HEIGHTS | D25: 2 | E25: =+SUMIF('GE16FEB14 Unfudged'!$A$2:$A$498, $A25, 'GE16FEB14 Unfudged'!$D$2:$D$498) -> 3362 | F25: 483364 | G25: 360094 | H25: 123270 | I25: 1425361 | J25: 1061860 | K25: 363501 | L25: 2047040 | M25: 1209102 | N25: 837938 | O25: =+F25+I25+L25 -> 3955765 | P25: =+G25+J25+M25 -> 2631056 | Q25: =+H25+K25+N25 -> 1324709 | R25: =+IF($E25=0, 0, O25/$E25) -> 1176.6106 | S25: =+IF($E25=0, 0, P25/$E25) -> 782.58656 | T25: =+IF($E25=0, 0, Q25/$E25) -> 394.02409
A26: 14 | B26: 1 | C26: FRIDLEY | D26: 3 | E26: =+SUMIF('GE16FEB14 Unfudged'!$A$2:$A$498, $A26, 'GE16FEB14 Unfudged'!$D$2:$D$498) -> 3199 | F26: 491056 | G26: 338747 | H26: 152309 | I26: 1356206 | J26: 935555 | K26: 420651 | L26: 1542013 | M26: 785411 | N26: 756602 | O26: =+F26+I26+L26 -> 3389275 | P26: =+G26+J26+M26 -> 2059713 | Q26: =+H26+K26+N26 -> 1329562 | R26: =+IF($E26=0, 0, O26/$E26) -> 1059.4795 | S26: =+IF($E26=0, 0, P26/$E26) -> 643.86152 | T26: =+IF($E26=0, 0, Q26/$E26) -> 415.61801
A27: 15 | B27: 1 | C27: ST. FRANCIS | D27: 3 | E27: =+SUMIF('GE16FEB14 Unfudged'!$A$2:$A$498, $A27, 'GE16FEB14 Unfudged'!$D$2:$D$498) -> 4887 | F27: 818573 | G27: 601361 | H27: 217212 | I27: 2072088 | J27: 1522250 | K27: 549838 | L27: 1466100 | M27: 624207 | N27: 841893 | O27: =+F27+I27+L27 -> 4356761 | P27: =+G27+J27+M27 -> 2747818 | Q27: =+H27+K27+N27 -> 1608943 | R27: =+IF($E27=0, 0, O27/$E27) -> 891.5001 | S27: =+IF($E27=0, 0, P27/$E27) -> 562.27092 | T27: =+IF($E27=0, 0, Q27/$E27) -> 329.22918
A28: 16 | B28: 1 | C28: SPRING LAKE PARK | D28: 3 | E28: =+SUMIF('GE16FEB14 Unfudged'!$A$2:$A$498, $A28, 'GE16FEB14 Unfudged'!$D$2:$D$498) -> 5870 | F28: 922757 | G28: 898386 | H28: 24371 | I28: 2488689 | J28: 2422960 | K28: 65729 | L28: 2547619 | M28: 1759524 | N28: 788095 | O28: =+F28+I28+L28 -> 5959065 | P28: =+G28+J28+M28 -> 5080870 | Q28: =+H28+K28+N28 -> 878195 | R28: =+IF($E28=0, 0, O28/$E28) -> 1015.1729 | S28: =+IF($E28=0, 0, P28/$E28) -> 865.56559 | T28: =+IF($E28=0, 0, Q28/$E28) -> 149.60733
A29: 22 | B29: 1 | C29: DETROIT LAKES | D29: 4 | E29: =+SUMIF('GE16FEB14 Unfudged'!$A$2:$A$498, $A29, 'GE16FEB14 Unfudged'!$D$2:$D$498) -> 3112 | F29: 448128 | G29: 396125 | H29: 52003 | I29: 659744 | J29: 583184 | K29: 76560 | L29: 933600 | M29: 478276 | N29: 455324 | O29: =+F29+I29+L29 -> 2041472 | P29: =+G29+J29+M29 -> 1457585 | Q29: =+H29+K29+N29 -> 583887 | R29: =+IF($E29=0, 0, O29/$E29) -> 656 | S29: =+IF($E29=0, 0, P29/$E29) -> 468.37564 | T29: =+IF($E29=0, 0, Q29/$E29) -> 187.62436
... A514: 6000 | B514: 7 | C514: COOPERATIVE & INTERMED DISTRICTS | D514: 24 | E514: =+SUMIF('GE16FEB14 Unfudged'!$A$2:$A$498, $A514, 'GE16FEB14 Unfudged'!$D$2:$D$498) -> 0 | F514: 0 | G514: 0 | H514: 0 | I514: 0 | J514: 0 | K514: 0 | L514: 0 | M514: 0 | N514: 0 | O514: =+F514+I514+L514 -> 0 | P514: =+G514+J514+M514 -> 0 | Q514: =+H514+K514+N514 -> 0 | R514: =+IF($E514=0, 0, O514/$E514) -> 0 | S514: =+IF($E514=0, 0, P514/$E514) -> 0 | T514: =+IF($E514=0, 0, Q514/$E514) -> 0
A515: End of worksheet

Sheet FY16 Tax Bill
A1: n/a | C1: n/a | E1: n/a | F1: FY 2016 as of 2014 Tax Bill - Max Revenue | L1: n/a | M1: n/a | N1: n/a | O1: n/a | P1: n/a | Q1: n/a | R1: n/a | S1: n/a | T1: n/a | U1: Column left blank intentionally | V1: Column left blank intentionally | W1: Column left blank intentionally
A2: n/a | C2: n/a | E2: n/a | F2: n/a | G2: n/a | H2: n/a | I2: Local | J2: Local | K2: Local | L2: Refer- | M2: Refer- | N2: Refer- | O2: Total | P2: Total | Q2: Total | R2: Total | S2: Total | T2: Total
A3: n/a | C3: n/a | E3: FY 2016 | F3: Equity | G3: Equity | H3: Equity | I3: Optional | J3: Optional | K3: Optional | L3: endum | M3: endum | N3: endum | O3: Impacted | P3: Impacted | Q3: Impacted | R3: Revenue / | S3: Levy / | T3: Aid /
A4: n/a | C4: n/a | E4: APU | F4: Revenue | G4: Levy | H4: Aid | I4: Revenue | J4: Levy | K4: Aid | L4: Revenue | M4: Levy | N4: Aid | O4: Revenue | P4: Levy | Q4: Aid | R4: APU | S4: APU | T4: APU
A5: line left blank intentionally
A6: n/a | C6: TOTAL | E6: =SUM(E18:E514) -> 921112 | F6: =SUM(F18:F514) -> 109031619 | G6: =SUM(G18:G514) -> 80189429 | H6: =SUM(H18:H514) -> 28842190 | I6: =SUM(I18:I514) -> 358810201 | J6: =SUM(J18:J514) -> 285015473 | K6: =SUM(K18:K514) -> 73794728 | L6: =SUM(L18:L514) -> 709804912 | ... Q6: =SUM(Q18:Q514) -> 270921912 | R6: =+IF($E6=0, 0, O6/$E6) -> 1278.5055 | S6: =+IF($E6=0, 0, P6/$E6) -> 984.38064 | T6: =+IF($E6=0, 0, Q6/$E6) -> 294.12483
A7: line left blank intentionally
A8: n/a | C8: MPLS & ST PAUL | D8: 1 | E8: =SUMIF($D$18:$D$514,$D8,E$18:E$514) -> 80335 | F8: =SUMIF($D$18:$D$514,$D8,F$18:F$514) -> 4016730 | G8: =SUMIF($D$18:$D$514,$D8,G$18:G$514) -> 3409709 | H8: =SUMIF($D$18:$D$514,$D8,H$18:H$514) -> 607021 | I8: =SUMIF($D$18:$D$514,$D8,I$18:I$514) -> 34061870 | J8: =SUMIF($D$18:$D$514,$D8,J$18:J$514) -> 28914332 | K8: =SUMIF($D$18:$D$514,$D8,K$18:K$514) -> 5147538 | L8: =SUMIF($D$18:$D$514,$D8,L$18:L$514) -> 82021892 | ... N8: =SUMIF($D$18:$D$514,$D8,N$18:N$514) -> 14453242 | O8: =+F8+I8+L8 -> 120100492 | P8: =+G8+J8+M8 -> 99892691 | Q8: =+H8+K8+N8 -> 20207801 | R8: =+IF($E8=0, 0, O8/$E8) -> 1494.9959 | S8: =+IF($E8=0, 0, P8/$E8) -> 1243.4517 | T8: =+IF($E8=0, 0, Q8/$E8) -> 251.54417
A9: n/a | C9: OTHER METRO, INNER | D9: 2 | E9: =SUMIF($D$18:$D$514,$D9,E$18:E$514) -> 95296 | F9: =SUMIF($D$18:$D$514,$D9,F$18:F$514) -> 10087609 | G9: =SUMIF($D$18:$D$514,$D9,G$18:G$514) -> 9084281 | H9: =SUMIF($D$18:$D$514,$D9,H$18:H$514) -> 1003328 | I9: =SUMIF($D$18:$D$514,$D9,I$18:I$514) -> 40405271 | J9: =SUMIF($D$18:$D$514,$D9,J$18:J$514) -> 37193191 | K9: =SUMIF($D$18:$D$514,$D9,K$18:K$514) -> 3212080 | L9: =SUMIF($D$18:$D$514,$D9,L$18:L$514) -> 106269709 | ... N9: =SUMIF($D$18:$D$514,$D9,N$18:N$514) -> 11829212 | O9: =+F9+I9+L9 -> 156762589 | P9: =+G9+J9+M9 -> 140717969 | Q9: =+H9+K9+N9 -> 16044620 | R9: =+IF($E9=0, 0, O9/$E9) -> 1645.007 | S9: =+IF($E9=0, 0, P9/$E9) -> 1476.6409 | T9: =+IF($E9=0, 0, Q9/$E9) -> 168.36614
A10: n/a | C10: OTHER METRO, OUTER | D10: 3 | E10: =SUMIF($D$18:$D$514,$D10,E$18:E$514) -> 286862 | F10: =SUMIF($D$18:$D$514,$D10,F$18:F$514) -> 32382467 | G10: =SUMIF($D$18:$D$514,$D10,G$18:G$514) -> 28389979 | H10: =SUMIF($D$18:$D$514,$D10,H$18:H$514) -> 3992488 | I10: =SUMIF($D$18:$D$514,$D10,I$18:I$514) -> 121629744 | J10: =SUMIF($D$18:$D$514,$D10,J$18:J$514) -> 108437428 | K10: =SUMIF($D$18:$D$514,$D10,K$18:K$514) -> 13192316 | L10: =SUMIF($D$18:$D$514,$D10,L$18:L$514) -> 284810801 | ... N10: =SUMIF($D$18:$D$514,$D10,N$18:N$514) -> 43727936 | O10: =+F10+I10+L10 -> 438823012 | P10: =+G10+J10+M10 -> 377910272 | Q10: =+H10+K10+N10 -> 60912740 | R10: =+IF($E10=0, 0, O10/$E10) -> 1529.7356 | S10: =+IF($E10=0, 0, P10/$E10) -> 1317.394 | T10: =+IF($E10=0, 0, Q10/$E10) -> 212.34161
A11: n/a | C11: NONMET>=2K | D11: 4 | E11: =SUMIF($D$18:$D$514,$D11,E$18:E$514) -> 199708 | F11: =SUMIF($D$18:$D$514,$D11,F$18:F$514) -> 26617911 | G11: =SUMIF($D$18:$D$514,$D11,G$18:G$514) -> 20860921 | H11: =SUMIF($D$18:$D$514,$D11,H$18:H$514) -> 5756990 | I11: =SUMIF($D$18:$D$514,$D11,I$18:I$514) -> 84675620 | J11: =SUMIF($D$18:$D$514,$D11,J$18:J$514) -> 66996515 | K11: =SUMIF($D$18:$D$514,$D11,K$18:K$514) -> 17679105 | L11: =SUMIF($D$18:$D$514,$D11,L$18:L$514) -> 81888826 | ... N11: =SUMIF($D$18:$D$514,$D11,N$18:N$514) -> 35686373 | O11: =+F11+I11+L11 -> 193182357 | P11: =+G11+J11+M11 -> 134059889 | Q11: =+H11+K11+N11 -> 59122468 | R11: =+IF($E11=0, 0, O11/$E11) -> 967.32408 | S11: =+IF($E11=0, 0, P11/$E11) -> 671.27951 | T11: =+IF($E11=0, 0, Q11/$E11) -> 296.04457
A12: n/a | C12: NONMET 1K-2K | D12: 5 | E12: =SUMIF($D$18:$D$514,$D12,E$18:E$514) -> 101624 | F12: =SUMIF($D$18:$D$514,$D12,F$18:F$514) -> 14050971 | G12: =SUMIF($D$18:$D$514,$D12,G$18:G$514) -> 9767926 | H12: =SUMIF($D$18:$D$514,$D12,H$18:H$514) -> 4283045 | I12: =SUMIF($D$18:$D$514,$D12,I$18:I$514) -> 43086983 | J12: =SUMIF($D$18:$D$514,$D12,J$18:J$514) -> 29722823 | K12: =SUMIF($D$18:$D$514,$D12,K$18:K$514) -> 13364160 | L12: =SUMIF($D$18:$D$514,$D12,L$18:L$514) -> 40101869 | ... N12: =SUMIF($D$18:$D$514,$D12,N$18:N$514) -> 21674980 | O12: =+F12+I12+L12 -> 97239823 | P12: =+G12+J12+M12 -> 57917638 | Q12: =+H12+K12+N12 -> 39322185 | R12: =+IF($E12=0, 0, O12/$E12) -> 956.85884 | S12: =+IF($E12=0, 0, P12/$E12) -> 569.92087 | T12: =+IF($E12=0, 0, Q12/$E12) -> 386.93798
A13: n/a | C13: NONMET < 1K | D13: 6 | E13: =SUMIF($D$18:$D$514,$D13,E$18:E$514) -> 92857 | F13: =SUMIF($D$18:$D$514,$D13,F$18:F$514) -> 11642268 | G13: =SUMIF($D$18:$D$514,$D13,G$18:G$514) -> 7570513 | H13: =SUMIF($D$18:$D$514,$D13,H$18:H$514) -> 4071755 | I13: =SUMIF($D$18:$D$514,$D13,I$18:I$514) -> 39368245 | J13: =SUMIF($D$18:$D$514,$D13,J$18:J$514) -> 25351973 | K13: =SUMIF($D$18:$D$514,$D13,K$18:K$514) -> 14016272 | L13: =SUMIF($D$18:$D$514,$D13,L$18:L$514) -> 57614939 | ... N13: =SUMIF($D$18:$D$514,$D13,N$18:N$514) -> 26749902 | O13: =+F13+I13+L13 -> 108625452 | P13: =+G13+J13+M13 -> 63787523 | Q13: =+H13+K13+N13 -> 44837929 | R13: =+IF($E13=0, 0, O13/$E13) -> 1169.8144 | S13: =+IF($E13=0, 0, P13/$E13) -> 686.94361 | T13: =+IF($E13=0, 0, Q13/$E13) -> 482.87075
A14: n/a | C14: CHARTER | D14: 7 | E14: =SUMIF($D$18:$D$514,$D14,E$18:E$514) -> 55972 | F14: =SUMIF($D$18:$D$514,$D14,F$18:F$514) -> 6624435 | G14: =SUMIF($D$18:$D$514,$D14,G$18:G$514) -> 0 | H14: =SUMIF($D$18:$D$514,$D14,H$18:H$514) -> 6624435 | I14: =SUMIF($D$18:$D$514,$D14,I$18:I$514) -> 0 | J14: =SUMIF($D$18:$D$514,$D14,J$18:J$514) -> 0 | K14: =SUMIF($D$18:$D$514,$D14,K$18:K$514) -> 0 | L14: =SUMIF($D$18:$D$514,$D14,L$18:L$514) -> 0 | ... N14: =SUMIF($D$18:$D$514,$D14,N$18:N$514) -> 0 | O14: =+F14+I14+L14 -> 6624435 | P14: =+G14+J14+M14 -> 0 | Q14: =+H14+K14+N14 -> 6624435 | R14: =+IF($E14=0, 0, O14/$E14) -> 118.35266 | S14: =+IF($E14=0, 0, P14/$E14) -> 0 | T14: =+IF($E14=0, 0, Q14/$E14) -> 118.35266
A15: n/a | C15: COOPERATIVES | D15: 8 | E15: =SUMIF($D$18:$D$514,$D15,E$18:E$514) -> 0 | F15: =SUMIF($D$18:$D$514,$D15,F$18:F$514) -> 0 | G15: =SUMIF($D$18:$D$514,$D15,G$18:G$514) -> 0 | H15: =SUMIF($D$18:$D$514,$D15,H$18:H$514) -> 0 | I15: =SUMIF($D$18:$D$514,$D15,I$18:I$514) -> 0 | J15: =SUMIF($D$18:$D$514,$D15,J$18:J$514) -> 0 | K15: =SUMIF($D$18:$D$514,$D15,K$18:K$514) -> 0 | L15: =SUMIF($D$18:$D$514,$D15,L$18:L$514) -> 0 | ... N15: =SUMIF($D$18:$D$514,$D15,N$18:N$514) -> 0 | O15: =+F15+I15+L15 -> 0 | P15: =+G15+J15+M15 -> 0 | Q15: =+H15+K15+N15 -> 0 | R15: =+IF($E15=0, 0, O15/$E15*1000) -> 0 | S15: =+IF($E15=0, 0, P15/$E15*1000) -> 0 | T15: =+IF($E15=0, 0, Q15/$E15*1000) -> 0
A16: n/a | C16: NONCHARTER FUDGE | D16: 9 | E16: =SUMIF($D$18:$D$514,$D16,E$18:E$514) -> 8458 | F16: =SUMIF($D$18:$D$514,$D16,F$18:F$514) -> 3609228 | G16: =SUMIF($D$18:$D$514,$D16,G$18:G$514) -> 1106100 | H16: =SUMIF($D$18:$D$514,$D16,H$18:H$514) -> 2503128 | I16: =SUMIF($D$18:$D$514,$D16,I$18:I$514) -> -4417532 | J16: =SUMIF($D$18:$D$514,$D16,J$18:J$514) -> -11600789 | K16: =SUMIF($D$18:$D$514,$D16,K$18:K$514) -> 7183257 | L16: =SUMIF($D$18:$D$514,$D16,L$18:L$514) -> 57096876 | ... N16: =SUMIF($D$18:$D$514,$D16,N$18:N$514) -> 14163349 | O16: =+F16+I16+L16 -> 56288572 | P16: =+G16+J16+M16 -> 32438838 | Q16: =+H16+K16+N16 -> 23849734 | R16: =+IF($E16=0, 0, O16/$E16) -> 6655.0688 | S16: =+IF($E16=0, 0, P16/$E16) -> 3835.2847 | T16: =+IF($E16=0, 0, Q16/$E16) -> 2819.7841
A17: line left blank intentionally
A18: 1 | B18: 1 | C18: AITKIN | D18: 5 | E18: =+SUMIF('GE16FEB14 Unfudged'!$A$2:$A$498, $A18, 'GE16FEB14 Unfudged'!$D$2:$D$498) -> 1285 | F18: 185040 | G18: 185040 | H18: 0 | I18: 544840 | J18: 544840 | K18: 0 | L18: 385500 | M18: 260672 | N18: 124828 | O18: =+F18+I18+L18 -> 1115380 | P18: =+G18+J18+M18 -> 990552 | Q18: =+H18+K18+N18 -> 124828 | R18: =+IF($E18=0, 0, O18/$E18) -> 868 | S18: =+IF($E18=0, 0, P18/$E18) -> 770.85759 | T18: =+IF($E18=0, 0, Q18/$E18) -> 97.142412
A19: 1.2 | B19: 3 | C19: MINNEAPOLIS | D19: 1 | E19: =+SUMIF('GE16FEB14 Unfudged'!$A$2:$A$498, $A19, 'GE16FEB14 Unfudged'!$D$2:$D$498) -> 39607 | F19: 1980330 | G19: 1980330 | H19: 0 | I19: 16793198 | J19: 16793198 | K19: 0 | L19: 55978780 | M19: 52894542 | N19: 3084238 | O19: =+F19+I19+L19 -> 74752308 | P19: =+G19+J19+M19 -> 71668070 | Q19: =+H19+K19+N19 -> 3084238 | R19: =+IF($E19=0, 0, O19/$E19) -> 1887.3509 | S19: =+IF($E19=0, 0, P19/$E19) -> 1809.4799 | T19: =+IF($E19=0, 0, Q19/$E19) -> 77.871033
A20: 2 | B20: 1 | C20: HILL CITY | D20: 6 | E20: =+SUMIF('GE16FEB14 Unfudged'!$A$2:$A$498, $A20, 'GE16FEB14 Unfudged'!$D$2:$D$498) -> 284 | F20: 40889 | G20: 22793 | H20: 18096 | I20: 120395 | J20: 67113 | K20: 53282 | L20: 85185 | M20: 27520 | N20: 57665 | O20: =+F20+I20+L20 -> 246469 | P20: =+G20+J20+M20 -> 117426 | Q20: =+H20+K20+N20 -> 129043 | R20: =+IF($E20=0, 0, O20/$E20) -> 867.84859 | S20: =+IF($E20=0, 0, P20/$E20) -> 413.47183 | T20: =+IF($E20=0, 0, Q20/$E20) -> 454.37676
A21: 4 | B21: 1 | C21: MCGREGOR | D21: 6 | E21: =+SUMIF('GE16FEB14 Unfudged'!$A$2:$A$498, $A21, 'GE16FEB14 Unfudged'!$D$2:$D$498) -> 434 | F21: 62554 | G21: 62554 | H21: 0 | I21: 184186 | J21: 184186 | K21: 0 | L21: 130320 | M21: 77314 | N21: 53006 | O21: =+F21+I21+L21 -> 377060 | P21: =+G21+J21+M21 -> 324054 | Q21: =+H21+K21+N21 -> 53006 | R21: =+IF($E21=0, 0, O21/$E21) -> 868.80184 | S21: =+IF($E21=0, 0, P21/$E21) -> 746.6682 | T21: =+IF($E21=0, 0, Q21/$E21) -> 122.13364
A22: 6 | B22: 3 | C22: SOUTH ST. PAUL | D22: 2 | E22: =+SUMIF('GE16FEB14 Unfudged'!$A$2:$A$498, $A22, 'GE16FEB14 Unfudged'!$D$2:$D$498) -> 3736 | F22: 557934 | G22: 396251 | H22: 161683 | I22: 1584234 | J22: 1125142 | K22: 459092 | L22: 2005625 | M22: 1089699 | N22: 915926 | O22: =+F22+I22+L22 -> 4147793 | P22: =+G22+J22+M22 -> 2611092 | Q22: =+H22+K22+N22 -> 1536701 | R22: =+IF($E22=0, 0, O22/$E22) -> 1110.223 | S22: =+IF($E22=0, 0, P22/$E22) -> 698.90043 | T22: =+IF($E22=0, 0, Q22/$E22) -> 411.32254
A23: 11 | B23: 1 | C23: ANOKA-HENNEPIN | D23: 3 | E23: =+SUMIF('GE16FEB14 Unfudged'!$A$2:$A$498, $A23, 'GE16FEB14 Unfudged'!$D$2:$D$498) -> 39798 | F23: 4558334 | G23: 3244342 | H23: 1313992 | I23: 16874267 | J23: 12010067 | K23: 4864200 | L23: 39397832 | M23: 27106091 | N23: 12291741 | O23: =+F23+I23+L23 -> 60830433 | P23: =+G23+J23+M23 -> 42360500 | Q23: =+H23+K23+N23 -> 18469933 | R23: =+IF($E23=0, 0, O23/$E23) -> 1528.4796 | S23: =+IF($E23=0, 0, P23/$E23) -> 1064.3877 | T23: =+IF($E23=0, 0, Q23/$E23) -> 464.09199
A24: 12 | B24: 1 | C24: CENTENNIAL | D24: 3 | E24: =+SUMIF('GE16FEB14 Unfudged'!$A$2:$A$498, $A24, 'GE16FEB14 Unfudged'!$D$2:$D$498) -> 6971 | F24: 1079123 | G24: 838445 | H24: 240678 | I24: 2955789 | J24: 2296557 | K24: 659232 | L24: 3244954 | M24: 1838023 | N24: 1406931 | O24: =+F24+I24+L24 -> 7279866 | P24: =+G24+J24+M24 -> 4973025 | Q24: =+H24+K24+N24 -> 2306841 | R24: =+IF($E24=0, 0, O24/$E24) -> 1044.3073 | S24: =+IF($E24=0, 0, P24/$E24) -> 713.38761 | T24: =+IF($E24=0, 0, Q24/$E24) -> 330.91967
A25: 13 | B25: 1 | C25: COLUMBIA HEIGHTS | D25: 2 | E25: =+SUMIF('GE16FEB14 Unfudged'!$A$2:$A$498, $A25, 'GE16FEB14 Unfudged'!$D$2:$D$498) -> 3362 | F25: 483364 | G25: 360094 | H25: 123270 | I25: 1425361 | J25: 1061860 | K25: 363501 | L25: 2047040 | M25: 1209102 | N25: 837938 | O25: =+F25+I25+L25 -> 3955765 | P25: =+G25+J25+M25 -> 2631056 | Q25: =+H25+K25+N25 -> 1324709 | R25: =+IF($E25=0, 0, O25/$E25) -> 1176.6106 | S25: =+IF($E25=0, 0, P25/$E25) -> 782.58656 | T25: =+IF($E25=0, 0, Q25/$E25) -> 394.02409
A26: 14 | B26: 1 | C26: FRIDLEY | D26: 3 | E26: =+SUMIF('GE16FEB14 Unfudged'!$A$2:$A$498, $A26, 'GE16FEB14 Unfudged'!$D$2:$D$498) -> 3199 | F26: 491056 | G26: 338747 | H26: 152309 | I26: 1356206 | J26: 935555 | K26: 420651 | L26: 1542013 | M26: 785411 | N26: 756602 | O26: =+F26+I26+L26 -> 3389275 | P26: =+G26+J26+M26 -> 2059713 | Q26: =+H26+K26+N26 -> 1329562 | R26: =+IF($E26=0, 0, O26/$E26) -> 1059.4795 | S26: =+IF($E26=0, 0, P26/$E26) -> 643.86152 | T26: =+IF($E26=0, 0, Q26/$E26) -> 415.61801
A27: 15 | B27: 1 | C27: ST. FRANCIS | D27: 3 | E27: =+SUMIF('GE16FEB14 Unfudged'!$A$2:$A$498, $A27, 'GE16FEB14 Unfudged'!$D$2:$D$498) -> 4887 | F27: 818573 | G27: 601361 | H27: 217212 | I27: 2072088 | J27: 1522250 | K27: 549838 | L27: 1466100 | M27: 624207 | N27: 841893 | O27: =+F27+I27+L27 -> 4356761 | P27: =+G27+J27+M27 -> 2747818 | Q27: =+H27+K27+N27 -> 1608943 | R27: =+IF($E27=0, 0, O27/$E27) -> 891.5001 | S27: =+IF($E27=0, 0, P27/$E27) -> 562.27092 | T27: =+IF($E27=0, 0, Q27/$E27) -> 329.22918
A28: 16 | B28: 1 | C28: SPRING LAKE PARK | D28: 3 | E28: =+SUMIF('GE16FEB14 Unfudged'!$A$2:$A$498, $A28, 'GE16FEB14 Unfudged'!$D$2:$D$498) -> 5870 | F28: 922757 | G28: 898386 | H28: 24371 | I28: 2488689 | J28: 2422960 | K28: 65729 | L28: 2547619 | M28: 1759524 | N28: 788095 | O28: =+F28+I28+L28 -> 5959065 | P28: =+G28+J28+M28 -> 5080870 | Q28: =+H28+K28+N28 -> 878195 | R28: =+IF($E28=0, 0, O28/$E28) -> 1015.1729 | S28: =+IF($E28=0, 0, P28/$E28) -> 865.56559 | T28: =+IF($E28=0, 0, Q28/$E28) -> 149.60733
A29: 22 | B29: 1 | C29: DETROIT LAKES | D29: 4 | E29: =+SUMIF('GE16FEB14 Unfudged'!$A$2:$A$498, $A29, 'GE16FEB14 Unfudged'!$D$2:$D$498) -> 3112 | F29: 448128 | G29: 396125 | H29: 52003 | I29: 1319488 | J29: 1166368 | K29: 153120 | L29: 933600 | M29: 478276 | N29: 455324 | O29: =+F29+I29+L29 -> 2701216 | P29: =+G29+J29+M29 -> 2040769 | Q29: =+H29+K29+N29 -> 660447 | R29: =+IF($E29=0, 0, O29/$E29) -> 868 | S29: =+IF($E29=0, 0, P29/$E29) -> 655.7741 | T29: =+IF($E29=0, 0, Q29/$E29) -> 212.2259
... A514: 6000 | B514: 7 | C514: COOPERATIVE & INTERMED DISTRICTS | D514: 24 | E514: =+SUMIF('GE16FEB14 Unfudged'!$A$2:$A$498, $A514, 'GE16FEB14 Unfudged'!$D$2:$D$498) -> 0 | F514: 0 | G514: 0 | H514: 0 | I514: 0 | J514: 0 | K514: 0 | L514: 0 | M514: 0 | N514: 0 | O514: =+F514+I514+L514 -> 0 | P514: =+G514+J514+M514 -> 0 | Q514: =+H514+K514+N514 -> 0 | R514: =+IF($E514=0, 0, O514/$E514) -> 0 | S514: =+IF($E514=0, 0, P514/$E514) -> 0 | T514: =+IF($E514=0, 0, Q514/$E514) -> 0
A515: End of worksheet

Sheet FY16 Change
A1: n/a | C1: n/a | E1: n/a | F1: FY 2016 as of 2014Tax Bill Changes from February Forecast - Max Revenue | R1: n/a | S1: n/a | T1: n/a | U1: Column left blank intentionally | V1: Column left blank intentionally | W1: Column left blank intentionally
A2: n/a | C2: n/a | E2: n/a | F2: n/a | G2: n/a | H2: n/a | I2: Local | J2: Local | K2: Local | L2: Refer- | M2: Refer- | N2: Refer- | O2: Total | P2: Total | Q2: Total | R2: Total | S2: Total | T2: Total
A3: n/a | C3: n/a | E3: FY 2016 | F3: Equity | G3: Equity | H3: Equity | I3: Optional | J3: Optional | K3: Optional | L3: endum | M3: endum | N3: endum | O3: Impacted | P3: Impacted | Q3: Impacted | R3: Revenue / | S3: Levy / | T3: Aid /
A4: n/a | C4: n/a | E4: APU | F4: Revenue | G4: Levy | H4: Aid | I4: Revenue | J4: Levy | K4: Aid | L4: Revenue | M4: Levy | N4: Aid | O4: Revenue | P4: Levy | Q4: Aid | R4: APU | S4: APU | T4: APU
A5: line left blank intentionally
A6: n/a | C6: TOTAL | E6: =SUM(E18:E514) -> 921112 | F6: =+'FY16 Tax Bill'!F6-'FY16 Feb Forecast'!F6 -> 2256067 | G6: =+'FY16 Tax Bill'!G6-'FY16 Feb Forecast'!G6 -> 1310034 | H6: =+'FY16 Tax Bill'!H6-'FY16 Feb Forecast'!H6 -> 946033 | I6: =+'FY16 Tax Bill'!I6-'FY16 Feb Forecast'!I6 -> 113684780 | J6: =+'FY16 Tax Bill'!J6-'FY16 Feb Forecast'!J6 -> 77553009 | K6: =+'FY16 Tax Bill'!K6-'FY16 Feb Forecast'!K6 -> 36131771 | L6: =+'FY16 Tax Bill'!L6-'FY16 Feb Forecast'!L6 -> -71452606 | M6: =+'FY16 Tax Bill'!M6-'FY16 Feb Forecast'!M6 -> -55540050 | ... T6: =+'FY16 Tax Bill'!T6-'FY16 Feb Forecast'!T6 -> 22.977931
A7: line left blank intentionally
A8: n/a | C8: MPLS & ST PAUL | D8: 1 | E8: =SUMIF($D$18:$D$514,$D8,E$18:E$514) -> 80335 | F8: =+'FY16 Tax Bill'!F8-'FY16 Feb Forecast'!F8 -> 0 | G8: =+'FY16 Tax Bill'!G8-'FY16 Feb Forecast'!G8 -> 0 | H8: =+'FY16 Tax Bill'!H8-'FY16 Feb Forecast'!H8 -> 0 | I8: =+'FY16 Tax Bill'!I8-'FY16 Feb Forecast'!I8 -> 0 | J8: =+'FY16 Tax Bill'!J8-'FY16 Feb Forecast'!J8 -> 0 | K8: =+'FY16 Tax Bill'!K8-'FY16 Feb Forecast'!K8 -> 0 | L8: =+'FY16 Tax Bill'!L8-'FY16 Feb Forecast'!L8 -> 0 | M8: =+'FY16 Tax Bill'!M8-'FY16 Feb Forecast'!M8 -> 0 | ... T8: =+'FY16 Tax Bill'!T8-'FY16 Feb Forecast'!T8 -> 0
A9: n/a | C9: OTHER METRO, INNER | D9: 2 | E9: =SUMIF($D$18:$D$514,$D9,E$18:E$514) -> 95296 | F9: =+'FY16 Tax Bill'!F9-'FY16 Feb Forecast'!F9 -> 0 | G9: =+'FY16 Tax Bill'!G9-'FY16 Feb Forecast'!G9 -> 0 | H9: =+'FY16 Tax Bill'!H9-'FY16 Feb Forecast'!H9 -> 0 | I9: =+'FY16 Tax Bill'!I9-'FY16 Feb Forecast'!I9 -> 0 | J9: =+'FY16 Tax Bill'!J9-'FY16 Feb Forecast'!J9 -> 0 | K9: =+'FY16 Tax Bill'!K9-'FY16 Feb Forecast'!K9 -> 0 | L9: =+'FY16 Tax Bill'!L9-'FY16 Feb Forecast'!L9 -> 0 | M9: =+'FY16 Tax Bill'!M9-'FY16 Feb Forecast'!M9 -> 0 | ... T9: =+'FY16 Tax Bill'!T9-'FY16 Feb Forecast'!T9 -> 0
A10: n/a | C10: OTHER METRO, OUTER | D10: 3 | E10: =SUMIF($D$18:$D$514,$D10,E$18:E$514) -> 286862 | F10: =+'FY16 Tax Bill'!F10-'FY16 Feb Forecast'!F10 -> -65300 | G10: =+'FY16 Tax Bill'!G10-'FY16 Feb Forecast'!G10 -> -57272 | H10: =+'FY16 Tax Bill'!H10-'FY16 Feb Forecast'!H10 -> -8028 | I10: =+'FY16 Tax Bill'!I10-'FY16 Feb Forecast'!I10 -> 0 | J10: =+'FY16 Tax Bill'!J10-'FY16 Feb Forecast'!J10 -> 0 | K10: =+'FY16 Tax Bill'!K10-'FY16 Feb Forecast'!K10 -> 0 | L10: =+'FY16 Tax Bill'!L10-'FY16 Feb Forecast'!L10 -> 0 | M10: =+'FY16 Tax Bill'!M10-'FY16 Feb Forecast'!M10 -> 0 | ... T10: =+'FY16 Tax Bill'!T10-'FY16 Feb Forecast'!T10 -> -0.027985582
A11: n/a | C11: NONMET>=2K | D11: 4 | E11: =SUMIF($D$18:$D$514,$D11,E$18:E$514) -> 199708 | F11: =+'FY16 Tax Bill'!F11-'FY16 Feb Forecast'!F11 -> 576464 | G11: =+'FY16 Tax Bill'!G11-'FY16 Feb Forecast'!G11 -> 430354 | H11: =+'FY16 Tax Bill'!H11-'FY16 Feb Forecast'!H11 -> 146110 | I11: =+'FY16 Tax Bill'!I11-'FY16 Feb Forecast'!I11 -> 37193802 | J11: =+'FY16 Tax Bill'!J11-'FY16 Feb Forecast'!J11 -> 29900546 | K11: =+'FY16 Tax Bill'!K11-'FY16 Feb Forecast'!K11 -> 7293256 | L11: =+'FY16 Tax Bill'!L11-'FY16 Feb Forecast'!L11 -> -21332782 | M11: =+'FY16 Tax Bill'!M11-'FY16 Feb Forecast'!M11 -> -17706441 | ... T11: =+'FY16 Tax Bill'!T11-'FY16 Feb Forecast'!T11 -> 19.093001
A12: n/a | C12: NONMET 1K-2K | D12: 5 | E12: =SUMIF($D$18:$D$514,$D12,E$18:E$514) -> 101624 | F12: =+'FY16 Tax Bill'!F12-'FY16 Feb Forecast'!F12 -> 989397 | G12: =+'FY16 Tax Bill'!G12-'FY16 Feb Forecast'!G12 -> 658112 | H12: =+'FY16 Tax Bill'!H12-'FY16 Feb Forecast'!H12 -> 331285 | I12: =+'FY16 Tax Bill'!I12-'FY16 Feb Forecast'!I12 -> 39478680 | J12: =+'FY16 Tax Bill'!J12-'FY16 Feb Forecast'!J12 -> 26925599 | K12: =+'FY16 Tax Bill'!K12-'FY16 Feb Forecast'!K12 -> 12553081 | L12: =+'FY16 Tax Bill'!L12-'FY16 Feb Forecast'!L12 -> -24667361 | M12: =+'FY16 Tax Bill'!M12-'FY16 Feb Forecast'!M12 -> -17927923 | ... T12: =+'FY16 Tax Bill'!T12-'FY16 Feb Forecast'!T12 -> 60.467291
A13: n/a | C13: NONMET < 1K | D13: 6 | E13: =SUMIF($D$18:$D$514,$D13,E$18:E$514) -> 92857 | F13: =+'FY16 Tax Bill'!F13-'FY16 Feb Forecast'!F13 -> 864067 | G13: =+'FY16 Tax Bill'!G13-'FY16 Feb Forecast'!G13 -> 563627 | H13: =+'FY16 Tax Bill'!H13-'FY16 Feb Forecast'!H13 -> 300440 | I13: =+'FY16 Tax Bill'!I13-'FY16 Feb Forecast'!I13 -> 39190801 | J13: =+'FY16 Tax Bill'!J13-'FY16 Feb Forecast'!J13 -> 25215494 | K13: =+'FY16 Tax Bill'!K13-'FY16 Feb Forecast'!K13 -> 13975307 | L13: =+'FY16 Tax Bill'!L13-'FY16 Feb Forecast'!L13 -> -27789126 | M13: =+'FY16 Tax Bill'!M13-'FY16 Feb Forecast'!M13 -> -22642215 | ... T13: =+'FY16 Tax Bill'!T13-'FY16 Feb Forecast'!T13 -> 98.310693
A14: n/a | C14: CHARTER | D14: 7 | E14: =SUMIF($D$18:$D$514,$D14,E$18:E$514) -> 55972 | F14: =+'FY16 Tax Bill'!F14-'FY16 Feb Forecast'!F14 -> 137075 | G14: =+'FY16 Tax Bill'!G14-'FY16 Feb Forecast'!G14 -> 0 | H14: =+'FY16 Tax Bill'!H14-'FY16 Feb Forecast'!H14 -> 137075 | I14: =+'FY16 Tax Bill'!I14-'FY16 Feb Forecast'!I14 -> 0 | J14: =+'FY16 Tax Bill'!J14-'FY16 Feb Forecast'!J14 -> 0 | K14: =+'FY16 Tax Bill'!K14-'FY16 Feb Forecast'!K14 -> 0 | L14: =+'FY16 Tax Bill'!L14-'FY16 Feb Forecast'!L14 -> 0 | M14: =+'FY16 Tax Bill'!M14-'FY16 Feb Forecast'!M14 -> 0 | ... T14: =+'FY16 Tax Bill'!T14-'FY16 Feb Forecast'!T14 -> 2.4489924
A15: n/a | C15: COOPERATIVES | D15: 8 | E15: =SUMIF($D$18:$D$514,$D15,E$18:E$514) -> 0 | F15: =+'FY16 Tax Bill'!F15-'FY16 Feb Forecast'!F15 -> 0 | G15: =+'FY16 Tax Bill'!G15-'FY16 Feb Forecast'!G15 -> 0 | H15: =+'FY16 Tax Bill'!H15-'FY16 Feb Forecast'!H15 -> 0 | I15: =+'FY16 Tax Bill'!I15-'FY16 Feb Forecast'!I15 -> 0 | J15: =+'FY16 Tax Bill'!J15-'FY16 Feb Forecast'!J15 -> 0 | K15: =+'FY16 Tax Bill'!K15-'FY16 Feb Forecast'!K15 -> 0 | L15: =+'FY16 Tax Bill'!L15-'FY16 Feb Forecast'!L15 -> 0 | M15: =+'FY16 Tax Bill'!M15-'FY16 Feb Forecast'!M15 -> 0 | ... T15: =+'FY16 Tax Bill'!T15-'FY16 Feb Forecast'!T15 -> 0
A16: n/a | C16: NONCHARTER FUDGE | D16: 9 | E16: =SUMIF($D$18:$D$514,$D16,E$18:E$514) -> 8458 | F16: =+'FY16 Tax Bill'!F16-'FY16 Feb Forecast'!F16 -> -245636 | G16: =+'FY16 Tax Bill'!G16-'FY16 Feb Forecast'!G16 -> -284787 | H16: =+'FY16 Tax Bill'!H16-'FY16 Feb Forecast'!H16 -> 39151 | I16: =+'FY16 Tax Bill'!I16-'FY16 Feb Forecast'!I16 -> -2178503 | J16: =+'FY16 Tax Bill'!J16-'FY16 Feb Forecast'!J16 -> -4488630 | K16: =+'FY16 Tax Bill'!K16-'FY16 Feb Forecast'!K16 -> 2310127 | L16: =+'FY16 Tax Bill'!L16-'FY16 Feb Forecast'!L16 -> 2336663 | M16: =+'FY16 Tax Bill'!M16-'FY16 Feb Forecast'!M16 -> 2736529 | ... T16: =+'FY16 Tax Bill'!T16-'FY16 Feb Forecast'!T16 -> 230.48144
A17: line left blank intentionally
A18: 1 | B18: 1 | C18: AITKIN | D18: 5 | E18: =+SUMIF('GE16FEB14 Unfudged'!$A$2:$A$498, $A18, 'GE16FEB14 Unfudged'!$D$2:$D$498) -> 1285 | F18: =+'FY16 Tax Bill'!F18-'FY16 Feb Forecast'!F18 -> 0 | G18: =+'FY16 Tax Bill'!G18-'FY16 Feb Forecast'!G18 -> 0 | H18: =+'FY16 Tax Bill'!H18-'FY16 Feb Forecast'!H18 -> 0 | I18: =+'FY16 Tax Bill'!I18-'FY16 Feb Forecast'!I18 -> 544840 | J18: =+'FY16 Tax Bill'!J18-'FY16 Feb Forecast'!J18 -> 544840 | K18: =+'FY16 Tax Bill'!K18-'FY16 Feb Forecast'!K18 -> 0 | L18: =+'FY16 Tax Bill'!L18-'FY16 Feb Forecast'!L18 -> 0 | M18: =+'FY16 Tax Bill'!M18-'FY16 Feb Forecast'!M18 -> 0 | ... T18: =+'FY16 Tax Bill'!T18-'FY16 Feb Forecast'!T18 -> 0
A19: 1.2 | B19: 3 | C19: MINNEAPOLIS | D19: 1 | E19: =+SUMIF('GE16FEB14 Unfudged'!$A$2:$A$498, $A19, 'GE16FEB14 Unfudged'!$D$2:$D$498) -> 39607 | F19: =+'FY16 Tax Bill'!F19-'FY16 Feb Forecast'!F19 -> 0 | G19: =+'FY16 Tax Bill'!G19-'FY16 Feb Forecast'!G19 -> 0 | H19: =+'FY16 Tax Bill'!H19-'FY16 Feb Forecast'!H19 -> 0 | I19: =+'FY16 Tax Bill'!I19-'FY16 Feb Forecast'!I19 -> 0 | J19: =+'FY16 Tax Bill'!J19-'FY16 Feb Forecast'!J19 -> 0 | K19: =+'FY16 Tax Bill'!K19-'FY16 Feb Forecast'!K19 -> 0 | L19: =+'FY16 Tax Bill'!L19-'FY16 Feb Forecast'!L19 -> 0 | M19: =+'FY16 Tax Bill'!M19-'FY16 Feb Forecast'!M19 -> 0 | ... T19: =+'FY16 Tax Bill'!T19-'FY16 Feb Forecast'!T19 -> 0
A20: 2 | B20: 1 | C20: HILL CITY | D20: 6 | E20: =+SUMIF('GE16FEB14 Unfudged'!$A$2:$A$498, $A20, 'GE16FEB14 Unfudged'!$D$2:$D$498) -> 284 | F20: =+'FY16 Tax Bill'!F20-'FY16 Feb Forecast'!F20 -> 0 | G20: =+'FY16 Tax Bill'!G20-'FY16 Feb Forecast'!G20 -> 0 | H20: =+'FY16 Tax Bill'!H20-'FY16 Feb Forecast'!H20 -> 0 | I20: =+'FY16 Tax Bill'!I20-'FY16 Feb Forecast'!I20 -> 120395 | J20: =+'FY16 Tax Bill'!J20-'FY16 Feb Forecast'!J20 -> 67113 | K20: =+'FY16 Tax Bill'!K20-'FY16 Feb Forecast'!K20 -> 53282 | L20: =+'FY16 Tax Bill'!L20-'FY16 Feb Forecast'!L20 -> 0 | M20: =+'FY16 Tax Bill'!M20-'FY16 Feb Forecast'!M20 -> 0 | ... T20: =+'FY16 Tax Bill'!T20-'FY16 Feb Forecast'!T20 -> 187.61268
A21: 4 | B21: 1 | C21: MCGREGOR | D21: 6 | E21: =+SUMIF('GE16FEB14 Unfudged'!$A$2:$A$498, $A21, 'GE16FEB14 Unfudged'!$D$2:$D$498) -> 434 | F21: =+'FY16 Tax Bill'!F21-'FY16 Feb Forecast'!F21 -> 0 | G21: =+'FY16 Tax Bill'!G21-'FY16 Feb Forecast'!G21 -> 0 | H21: =+'FY16 Tax Bill'!H21-'FY16 Feb Forecast'!H21 -> 0 | I21: =+'FY16 Tax Bill'!I21-'FY16 Feb Forecast'!I21 -> 184186 | J21: =+'FY16 Tax Bill'!J21-'FY16 Feb Forecast'!J21 -> 184186 | K21: =+'FY16 Tax Bill'!K21-'FY16 Feb Forecast'!K21 -> 0 | L21: =+'FY16 Tax Bill'!L21-'FY16 Feb Forecast'!L21 -> 0 | M21: =+'FY16 Tax Bill'!M21-'FY16 Feb Forecast'!M21 -> 0 | ... T21: =+'FY16 Tax Bill'!T21-'FY16 Feb Forecast'!T21 -> 0
A22: 6 | B22: 3 | C22: SOUTH ST. PAUL | D22: 2 | E22: =+SUMIF('GE16FEB14 Unfudged'!$A$2:$A$498, $A22, 'GE16FEB14 Unfudged'!$D$2:$D$498) -> 3736 | F22: =+'FY16 Tax Bill'!F22-'FY16 Feb Forecast'!F22 -> 0 | G22: =+'FY16 Tax Bill'!G22-'FY16 Feb Forecast'!G22 -> 0 | H22: =+'FY16 Tax Bill'!H22-'FY16 Feb Forecast'!H22 -> 0 | I22: =+'FY16 Tax Bill'!I22-'FY16 Feb Forecast'!I22 -> 0 | J22: =+'FY16 Tax Bill'!J22-'FY16 Feb Forecast'!J22 -> 0 | K22: =+'FY16 Tax Bill'!K22-'FY16 Feb Forecast'!K22 -> 0 | L22: =+'FY16 Tax Bill'!L22-'FY16 Feb Forecast'!L22 -> 0 | M22: =+'FY16 Tax Bill'!M22-'FY16 Feb Forecast'!M22 -> 0 | ... T22: =+'FY16 Tax Bill'!T22-'FY16 Feb Forecast'!T22 -> 0
A23: 11 | B23: 1 | C23: ANOKA-HENNEPIN | D23: 3 | E23: =+SUMIF('GE16FEB14 Unfudged'!$A$2:$A$498, $A23, 'GE16FEB14 Unfudged'!$D$2:$D$498) -> 39798 | F23: =+'FY16 Tax Bill'!F23-'FY16 Feb Forecast'!F23 -> 0 | G23: =+'FY16 Tax Bill'!G23-'FY16 Feb Forecast'!G23 -> 0 | H23: =+'FY16 Tax Bill'!H23-'FY16 Feb Forecast'!H23 -> 0 | I23: =+'FY16 Tax Bill'!I23-'FY16 Feb Forecast'!I23 -> 0 | J23: =+'FY16 Tax Bill'!J23-'FY16 Feb Forecast'!J23 -> 0 | K23: =+'FY16 Tax Bill'!K23-'FY16 Feb Forecast'!K23 -> 0 | L23: =+'FY16 Tax Bill'!L23-'FY16 Feb Forecast'!L23 -> 0 | M23: =+'FY16 Tax Bill'!M23-'FY16 Feb Forecast'!M23 -> 0 | ... T23: =+'FY16 Tax Bill'!T23-'FY16 Feb Forecast'!T23 -> 0
A24: 12 | B24: 1 | C24: CENTENNIAL | D24: 3 | E24: =+SUMIF('GE16FEB14 Unfudged'!$A$2:$A$498, $A24, 'GE16FEB14 Unfudged'!$D$2:$D$498) -> 6971 | F24: =+'FY16 Tax Bill'!F24-'FY16 Feb Forecast'!F24 -> 0 | G24: =+'FY16 Tax Bill'!G24-'FY16 Feb Forecast'!G24 -> 0 | H24: =+'FY16 Tax Bill'!H24-'FY16 Feb Forecast'!H24 -> 0 | I24: =+'FY16 Tax Bill'!I24-'FY16 Feb Forecast'!I24 -> 0 | J24: =+'FY16 Tax Bill'!J24-'FY16 Feb Forecast'!J24 -> 0 | K24: =+'FY16 Tax Bill'!K24-'FY16 Feb Forecast'!K24 -> 0 | L24: =+'FY16 Tax Bill'!L24-'FY16 Feb Forecast'!L24 -> 0 | M24: =+'FY16 Tax Bill'!M24-'FY16 Feb Forecast'!M24 -> 0 | ... T24: =+'FY16 Tax Bill'!T24-'FY16 Feb Forecast'!T24 -> 0
A25: 13 | B25: 1 | C25: COLUMBIA HEIGHTS | D25: 2 | E25: =+SUMIF('GE16FEB14 Unfudged'!$A$2:$A$498, $A25, 'GE16FEB14 Unfudged'!$D$2:$D$498) -> 3362 | F25: =+'FY16 Tax Bill'!F25-'FY16 Feb Forecast'!F25 -> 0 | G25: =+'FY16 Tax Bill'!G25-'FY16 Feb Forecast'!G25 -> 0 | H25: =+'FY16 Tax Bill'!H25-'FY16 Feb Forecast'!H25 -> 0 | I25: =+'FY16 Tax Bill'!I25-'FY16 Feb Forecast'!I25 -> 0 | J25: =+'FY16 Tax Bill'!J25-'FY16 Feb Forecast'!J25 -> 0 | K25: =+'FY16 Tax Bill'!K25-'FY16 Feb Forecast'!K25 -> 0 | L25: =+'FY16 Tax Bill'!L25-'FY16 Feb Forecast'!L25 -> 0 | M25: =+'FY16 Tax Bill'!M25-'FY16 Feb Forecast'!M25 -> 0 | ... T25: =+'FY16 Tax Bill'!T25-'FY16 Feb Forecast'!T25 -> 0
A26: 14 | B26: 1 | C26: FRIDLEY | D26: 3 | E26: =+SUMIF('GE16FEB14 Unfudged'!$A$2:$A$498, $A26, 'GE16FEB14 Unfudged'!$D$2:$D$498) -> 3199 | F26: =+'FY16 Tax Bill'!F26-'FY16 Feb Forecast'!F26 -> 0 | G26: =+'FY16 Tax Bill'!G26-'FY16 Feb Forecast'!G26 -> 0 | H26: =+'FY16 Tax Bill'!H26-'FY16 Feb Forecast'!H26 -> 0 | I26: =+'FY16 Tax Bill'!I26-'FY16 Feb Forecast'!I26 -> 0 | J26: =+'FY16 Tax Bill'!J26-'FY16 Feb Forecast'!J26 -> 0 | K26: =+'FY16 Tax Bill'!K26-'FY16 Feb Forecast'!K26 -> 0 | L26: =+'FY16 Tax Bill'!L26-'FY16 Feb Forecast'!L26 -> 0 | M26: =+'FY16 Tax Bill'!M26-'FY16 Feb Forecast'!M26 -> 0 | ... T26: =+'FY16 Tax Bill'!T26-'FY16 Feb Forecast'!T26 -> 0
A27: 15 | B27: 1 | C27: ST. FRANCIS | D27: 3 | E27: =+SUMIF('GE16FEB14 Unfudged'!$A$2:$A$498, $A27, 'GE16FEB14 Unfudged'!$D$2:$D$498) -> 4887 | F27: =+'FY16 Tax Bill'!F27-'FY16 Feb Forecast'!F27 -> 0 | G27: =+'FY16 Tax Bill'!G27-'FY16 Feb Forecast'!G27 -> 0 | H27: =+'FY16 Tax Bill'!H27-'FY16 Feb Forecast'!H27 -> 0 | I27: =+'FY16 Tax Bill'!I27-'FY16 Feb Forecast'!I27 -> 0 | J27: =+'FY16 Tax Bill'!J27-'FY16 Feb Forecast'!J27 -> 0 | K27: =+'FY16 Tax Bill'!K27-'FY16 Feb Forecast'!K27 -> 0 | L27: =+'FY16 Tax Bill'!L27-'FY16 Feb Forecast'!L27 -> 0 | M27: =+'FY16 Tax Bill'!M27-'FY16 Feb Forecast'!M27 -> 0 | ... T27: =+'FY16 Tax Bill'!T27-'FY16 Feb Forecast'!T27 -> 0
A28: 16 | B28: 1 | C28: SPRING LAKE PARK | D28: 3 | E28: =+SUMIF('GE16FEB14 Unfudged'!$A$2:$A$498, $A28, 'GE16FEB14 Unfudged'!$D$2:$D$498) -> 5870 | F28: =+'FY16 Tax Bill'!F28-'FY16 Feb Forecast'!F28 -> 0 | G28: =+'FY16 Tax Bill'!G28-'FY16 Feb Forecast'!G28 -> 0 | H28: =+'FY16 Tax Bill'!H28-'FY16 Feb Forecast'!H28 -> 0 | I28: =+'FY16 Tax Bill'!I28-'FY16 Feb Forecast'!I28 -> 0 | J28: =+'FY16 Tax Bill'!J28-'FY16 Feb Forecast'!J28 -> 0 | K28: =+'FY16 Tax Bill'!K28-'FY16 Feb Forecast'!K28 -> 0 | L28: =+'FY16 Tax Bill'!L28-'FY16 Feb Forecast'!L28 -> 0 | M28: =+'FY16 Tax Bill'!M28-'FY16 Feb Forecast'!M28 -> 0 | ... T28: =+'FY16 Tax Bill'!T28-'FY16 Feb Forecast'!T28 -> 0
A29: 22 | B29: 1 | C29: DETROIT LAKES | D29: 4 | E29: =+SUMIF('GE16FEB14 Unfudged'!$A$2:$A$498, $A29, 'GE16FEB14 Unfudged'!$D$2:$D$498) -> 3112 | F29: =+'FY16 Tax Bill'!F29-'FY16 Feb Forecast'!F29 -> 0 | G29: =+'FY16 Tax Bill'!G29-'FY16 Feb Forecast'!G29 -> 0 | H29: =+'FY16 Tax Bill'!H29-'FY16 Feb Forecast'!H29 -> 0 | I29: =+'FY16 Tax Bill'!I29-'FY16 Feb Forecast'!I29 -> 659744 | J29: =+'FY16 Tax Bill'!J29-'FY16 Feb Forecast'!J29 -> 583184 | K29: =+'FY16 Tax Bill'!K29-'FY16 Feb Forecast'!K29 -> 76560 | L29: =+'FY16 Tax Bill'!L29-'FY16 Feb Forecast'!L29 -> 0 | M29: =+'FY16 Tax Bill'!M29-'FY16 Feb Forecast'!M29 -> 0 | ... T29: =+'FY16 Tax Bill'!T29-'FY16 Feb Forecast'!T29 -> 24.601542
... A514: 6000 | B514: 7 | C514: COOPERATIVE & INTERMED DISTRICTS | D514: 24 | E514: =+SUMIF('GE16FEB14 Unfudged'!$A$2:$A$498, $A514, 'GE16FEB14 Unfudged'!$D$2:$D$498) -> 0 | F514: =+'FY16 Tax Bill'!F514-'FY16 Feb Forecast'!F514 -> 0 | G514: =+'FY16 Tax Bill'!G514-'FY16 Feb Forecast'!G514 -> 0 | H514: =+'FY16 Tax Bill'!H514-'FY16 Feb Forecast'!H514 -> 0 | I514: =+'FY16 Tax Bill'!I514-'FY16 Feb Forecast'!I514 -> 0 | J514: =+'FY16 Tax Bill'!J514-'FY16 Feb Forecast'!J514 -> 0 | K514: =+'FY16 Tax Bill'!K514-'FY16 Feb Forecast'!K514 -> 0 | L514: =+'FY16 Tax Bill'!L514-'FY16 Feb Forecast'!L514 -> 0 | M514: =+'FY16 Tax Bill'!M514-'FY16 Feb Forecast'!M514 -> 0 | ... T514: =+'FY16 Tax Bill'!T514-'FY16 Feb Forecast'!T514 -> 0
A515: End of worksheet

Sheet Tax Bill Summary
F2: FY 2016 as of February Forecast | U2: FY 2016 Tax Bill - HF 2547 ($ in 000) | AJ2: Change
I5: Location | J5: Location | K5: Location | L5: Refer- | M5: Refer- | N5: Refer- | O5: Total | P5: Total | Q5: Total | R5: Total | S5: Total | T5: Total | X5: Location | Y5: Location | Z5: Location | AA5: Refer- | AB5: Refer- | AC5: Refer- | AD5: Total | AE5: Total | AF5: Total | AG5: Total | AH5: Total | AI5: Total | AM5: Location | AN5: Location | AO5: Location | AP5: Refer- | AQ5: Refer- | AR5: Refer- | AS5: Total | AT5: Total | AU5: Total | AV5: Total | AW5: Total | AX5: Total
E6: FY 2016 | F6: Equity | G6: Equity | H6: Equity | I6: Equity | J6: Equity | K6: Equity | L6: endum | M6: endum | N6: endum | O6: Impacted | P6: Impacted | Q6: Impacted | R6: Revenue | S6: Levy | T6: Aid | U6: Equity | V6: Equity | W6: Equity | X6: Equity | Y6: Equity | Z6: Equity | AA6: endum | AB6: endum | AC6: endum | AD6: Impacted | AE6: Impacted | AF6: Impacted | AG6: Revenue | AH6: Levy | AI6: Aid | AJ6: Equity | AK6: Equity | AL6: Equity | AM6: Equity | AN6: Equity | AO6: Equity | AP6: endum | AQ6: endum | AR6: endum | AS6: Impacted | AT6: Impacted | AU6: Impacted | AV6: Revenue | AW6: Levy | AX6: Aid
E7: APU | F7: Revenue | G7: Levy | H7: Aid | I7: Revenue | J7: Levy | K7: Aid | L7: Revenue | M7: Levy | N7: Aid | O7: Revenue | P7: Levy | Q7: Aid | R7: Pupil | S7: Pupil | T7: Pupil | U7: Revenue | V7: Levy | W7: Aid | X7: Revenue | Y7: Levy | Z7: Aid | AA7: Revenue | AB7: Levy | AC7: Aid | AD7: Revenue | AE7: Levy | AF7: Aid | AG7: Pupil | AH7: Pupil | AI7: Pupil | AJ7: Revenue | AK7: Levy | AL7: Aid | AM7: Revenue | AN7: Levy | AO7: Aid | AP7: Revenue | AQ7: Levy | AR7: Aid | AS7: Revenue | AT7: Levy | AU7: Aid | AV7: Pupil | AW7: Pupil | AX7: Pupil
C9: TOTAL | E9: =SUM(E21:E517) -> 921112 | F9: =SUM(F21:F517) -> 106775552 | G9: =SUM(G21:G517) -> 78879395 | H9: =SUM(H21:H517) -> 27896157 | I9: =SUM(I21:I517) -> 245125421 | J9: =SUM(J21:J517) -> 207462464 | K9: =SUM(K21:K517) -> 37662957 | L9: =SUM(L21:L517) -> 781257518 | ... Q9: =SUM(Q21:Q517) -> 249756664 | R9: =+IF($E9=0, 0, O9/$E9) -> 1230.2071 | S9: =+IF($E9=0, 0, P9/$E9) -> 959.06017 | T9: =+IF($E9=0, 0, Q9/$E9) -> 271.1469 | U9: =SUM(U21:U517) -> 109031619 | V9: =SUM(V21:V517) -> 80189429 | W9: =SUM(W21:W517) -> 28842190 | X9: =SUM(X21:X517) -> 358810201 | Y9: =SUM(Y21:Y517) -> 285015473 | Z9: =SUM(Z21:Z517) -> 73794728 | AA9: =SUM(AA21:AA517) -> 709804912 | AB9: =SUM(AB21:AB517) -> 541519918 | ... AF9: =SUM(AF21:AF517) -> 270921912 | AG9: =+IF($E9=0, 0, AD9/$E9) -> 1278.5055 | AH9: =+IF($E9=0, 0, AE9/$E9) -> 984.38064 | AI9: =+IF($E9=0, 0, AF9/$E9) -> 294.12483 | AJ9: =+U9-F9 -> 2256067 | AK9: =+V9-G9 -> 1310034 | AL9: =+W9-H9 -> 946033 | AM9: =+X9-I9 -> 113684780 | AN9: =+Y9-J9 -> 77553009 | AO9: =+Z9-K9 -> 36131771 | AP9: =+AA9-L9 -> -71452606 | AQ9: =+AB9-M9 -> -55540050 | ... AX9: =+AI9-T9 -> 22.977931
C11: MPLS & ST PAUL | D11: 1 | E11: =SUMIF($D$21:$D$517,$D11,E$21:E$517) -> 80335 | F11: =SUMIF($D$21:$D$517,$D11,F$21:F$517) -> 4016730 | G11: =SUMIF($D$21:$D$517,$D11,G$21:G$517) -> 3409709 | H11: =SUMIF($D$21:$D$517,$D11,H$21:H$517) -> 607021 | I11: =SUMIF($D$21:$D$517,$D11,I$21:I$517) -> 34061870 | J11: =SUMIF($D$21:$D$517,$D11,J$21:J$517) -> 28914332 | K11: =SUMIF($D$21:$D$517,$D11,K$21:K$517) -> 5147538 | L11: =SUMIF($D$21:$D$517,$D11,L$21:L$517) -> 82021892 | ... N11: =SUMIF($D$21:$D$517,$D11,N$21:N$517) -> 14453242 | O11: =+F11+I11+L11 -> 120100492 | P11: =+G11+J11+M11 -> 99892691 | Q11: =+H11+K11+N11 -> 20207801 | R11: =+IF($E11=0, 0, O11/$E11) -> 1494.9959 | S11: =+IF($E11=0, 0, P11/$E11) -> 1243.4517 | T11: =+IF($E11=0, 0, Q11/$E11) -> 251.54417 | U11: =SUMIF($D$21:$D$517,$D11,U$21:U$517) -> 4016730 | V11: =SUMIF($D$21:$D$517,$D11,V$21:V$517) -> 3409709 | W11: =SUMIF($D$21:$D$517,$D11,W$21:W$517) -> 607021 | X11: =SUMIF($D$21:$D$517,$D11,X$21:X$517) -> 34061870 | Y11: =SUMIF($D$21:$D$517,$D11,Y$21:Y$517) -> 28914332 | Z11: =SUMIF($D$21:$D$517,$D11,Z$21:Z$517) -> 5147538 | AA11: =SUMIF($D$21:$D$517,$D11,AA$21:AA$517) -> 82021892 | AB11: =SUMIF($D$21:$D$517,$D11,AB$21:AB$517) -> 67568650 | AC11: =SUMIF($D$21:$D$517,$D11,AC$21:AC$517) -> 14453242 | AD11: =+U11+X11+AA11 -> 120100492 | AE11: =+V11+Y11+AB11 -> 99892691 | AF11: =+W11+Z11+AC11 -> 20207801 | AG11: =+IF($E11=0, 0, AD11/$E11) -> 1494.9959 | AH11: =+IF($E11=0, 0, AE11/$E11) -> 1243.4517 | AI11: =+IF($E11=0, 0, AF11/$E11) -> 251.54417 | AJ11: =+U11-F11 -> 0 | AK11: =+V11-G11 -> 0 | AL11: =+W11-H11 -> 0 | AM11: =+X11-I11 -> 0 | AN11: =+Y11-J11 -> 0 | AO11: =+Z11-K11 -> 0 | AP11: =+AA11-L11 -> 0 | AQ11: =+AB11-M11 -> 0 | ... AX11: =+AI11-T11 -> 0
C12: OTHER METRO, INNER | D12: 2 | E12: =SUMIF($D$21:$D$517,$D12,E$21:E$517) -> 95296 | F12: =SUMIF($D$21:$D$517,$D12,F$21:F$517) -> 10087609 | G12: =SUMIF($D$21:$D$517,$D12,G$21:G$517) -> 9084281 | H12: =SUMIF($D$21:$D$517,$D12,H$21:H$517) -> 1003328 | I12: =SUMIF($D$21:$D$517,$D12,I$21:I$517) -> 40405271 | J12: =SUMIF($D$21:$D$517,$D12,J$21:J$517) -> 37193191 | K12: =SUMIF($D$21:$D$517,$D12,K$21:K$517) -> 3212080 | L12: =SUMIF($D$21:$D$517,$D12,L$21:L$517) -> 106269709 | ... N12: =SUMIF($D$21:$D$517,$D12,N$21:N$517) -> 11829212 | O12: =+F12+I12+L12 -> 156762589 | P12: =+G12+J12+M12 -> 140717969 | Q12: =+H12+K12+N12 -> 16044620 | R12: =+IF($E12=0, 0, O12/$E12) -> 1645.007 | S12: =+IF($E12=0, 0, P12/$E12) -> 1476.6409 | T12: =+IF($E12=0, 0, Q12/$E12) -> 168.36614 | U12: =SUMIF($D$21:$D$517,$D12,U$21:U$517) -> 10087609 | V12: =SUMIF($D$21:$D$517,$D12,V$21:V$517) -> 9084281 | W12: =SUMIF($D$21:$D$517,$D12,W$21:W$517) -> 1003328 | X12: =SUMIF($D$21:$D$517,$D12,X$21:X$517) -> 40405271 | Y12: =SUMIF($D$21:$D$517,$D12,Y$21:Y$517) -> 37193191 | Z12: =SUMIF($D$21:$D$517,$D12,Z$21:Z$517) -> 3212080 | AA12: =SUMIF($D$21:$D$517,$D12,AA$21:AA$517) -> 106269709 | AB12: =SUMIF($D$21:$D$517,$D12,AB$21:AB$517) -> 94440497 | AC12: =SUMIF($D$21:$D$517,$D12,AC$21:AC$517) -> 11829212 | AD12: =+U12+X12+AA12 -> 156762589 | AE12: =+V12+Y12+AB12 -> 140717969 | AF12: =+W12+Z12+AC12 -> 16044620 | AG12: =+IF($E12=0, 0, AD12/$E12) -> 1645.007 | AH12: =+IF($E12=0, 0, AE12/$E12) -> 1476.6409 | AI12: =+IF($E12=0, 0, AF12/$E12) -> 168.36614 | AJ12: =+U12-F12 -> 0 | AK12: =+V12-G12 -> 0 | AL12: =+W12-H12 -> 0 | AM12: =+X12-I12 -> 0 | AN12: =+Y12-J12 -> 0 | AO12: =+Z12-K12 -> 0 | AP12: =+AA12-L12 -> 0 | AQ12: =+AB12-M12 -> 0 | ... AX12: =+AI12-T12 -> 0
C13: OTHER METRO, OUTER | D13: 3 | E13: =SUMIF($D$21:$D$517,$D13,E$21:E$517) -> 286862 | F13: =SUMIF($D$21:$D$517,$D13,F$21:F$517) -> 32447767 | G13: =SUMIF($D$21:$D$517,$D13,G$21:G$517) -> 28447251 | H13: =SUMIF($D$21:$D$517,$D13,H$21:H$517) -> 4000516 | I13: =SUMIF($D$21:$D$517,$D13,I$21:I$517) -> 121629744 | J13: =SUMIF($D$21:$D$517,$D13,J$21:J$517) -> 108437428 | K13: =SUMIF($D$21:$D$517,$D13,K$21:K$517) -> 13192316 | L13: =SUMIF($D$21:$D$517,$D13,L$21:L$517) -> 284810801 | ... N13: =SUMIF($D$21:$D$517,$D13,N$21:N$517) -> 43727936 | O13: =+F13+I13+L13 -> 438888312 | P13: =+G13+J13+M13 -> 377967544 | Q13: =+H13+K13+N13 -> 60920768 | R13: =+IF($E13=0, 0, O13/$E13) -> 1529.9632 | S13: =+IF($E13=0, 0, P13/$E13) -> 1317.5936 | T13: =+IF($E13=0, 0, Q13/$E13) -> 212.3696 | U13: =SUMIF($D$21:$D$517,$D13,U$21:U$517) -> 32382467 | V13: =SUMIF($D$21:$D$517,$D13,V$21:V$517) -> 28389979 | W13: =SUMIF($D$21:$D$517,$D13,W$21:W$517) -> 3992488 | X13: =SUMIF($D$21:$D$517,$D13,X$21:X$517) -> 121629744 | Y13: =SUMIF($D$21:$D$517,$D13,Y$21:Y$517) -> 108437428 | Z13: =SUMIF($D$21:$D$517,$D13,Z$21:Z$517) -> 13192316 | AA13: =SUMIF($D$21:$D$517,$D13,AA$21:AA$517) -> 284810801 | AB13: =SUMIF($D$21:$D$517,$D13,AB$21:AB$517) -> 241082865 | AC13: =SUMIF($D$21:$D$517,$D13,AC$21:AC$517) -> 43727936 | AD13: =+U13+X13+AA13 -> 438823012 | AE13: =+V13+Y13+AB13 -> 377910272 | AF13: =+W13+Z13+AC13 -> 60912740 | AG13: =+IF($E13=0, 0, AD13/$E13) -> 1529.7356 | AH13: =+IF($E13=0, 0, AE13/$E13) -> 1317.394 | AI13: =+IF($E13=0, 0, AF13/$E13) -> 212.34161 | AJ13: =+U13-F13 -> -65300 | AK13: =+V13-G13 -> -57272 | AL13: =+W13-H13 -> -8028 | AM13: =+X13-I13 -> 0 | AN13: =+Y13-J13 -> 0 | AO13: =+Z13-K13 -> 0 | AP13: =+AA13-L13 -> 0 | AQ13: =+AB13-M13 -> 0 | ... AX13: =+AI13-T13 -> -0.027985582
C14: NONMET>=2K | D14: 4 | E14: =SUMIF($D$21:$D$517,$D14,E$21:E$517) -> 199708 | F14: =SUMIF($D$21:$D$517,$D14,F$21:F$517) -> 26041447 | G14: =SUMIF($D$21:$D$517,$D14,G$21:G$517) -> 20430567 | H14: =SUMIF($D$21:$D$517,$D14,H$21:H$517) -> 5610880 | I14: =SUMIF($D$21:$D$517,$D14,I$21:I$517) -> 47481818 | J14: =SUMIF($D$21:$D$517,$D14,J$21:J$517) -> 37095969 | K14: =SUMIF($D$21:$D$517,$D14,K$21:K$517) -> 10385849 | L14: =SUMIF($D$21:$D$517,$D14,L$21:L$517) -> 103221608 | ... N14: =SUMIF($D$21:$D$517,$D14,N$21:N$517) -> 39312714 | O14: =+F14+I14+L14 -> 176744873 | P14: =+G14+J14+M14 -> 121435430 | Q14: =+H14+K14+N14 -> 55309443 | R14: =+IF($E14=0, 0, O14/$E14) -> 885.01649 | S14: =+IF($E14=0, 0, P14/$E14) -> 608.06492 | T14: =+IF($E14=0, 0, Q14/$E14) -> 276.95156 | U14: =SUMIF($D$21:$D$517,$D14,U$21:U$517) -> 26617911 | V14: =SUMIF($D$21:$D$517,$D14,V$21:V$517) -> 20860921 | W14: =SUMIF($D$21:$D$517,$D14,W$21:W$517) -> 5756990 | X14: =SUMIF($D$21:$D$517,$D14,X$21:X$517) -> 84675620 | Y14: =SUMIF($D$21:$D$517,$D14,Y$21:Y$517) -> 66996515 | Z14: =SUMIF($D$21:$D$517,$D14,Z$21:Z$517) -> 17679105 | AA14: =SUMIF($D$21:$D$517,$D14,AA$21:AA$517) -> 81888826 | AB14: =SUMIF($D$21:$D$517,$D14,AB$21:AB$517) -> 46202453 | AC14: =SUMIF($D$21:$D$517,$D14,AC$21:AC$517) -> 35686373 | AD14: =+U14+X14+AA14 -> 193182357 | AE14: =+V14+Y14+AB14 -> 134059889 | AF14: =+W14+Z14+AC14 -> 59122468 | AG14: =+IF($E14=0, 0, AD14/$E14) -> 967.32408 | AH14: =+IF($E14=0, 0, AE14/$E14) -> 671.27951 | AI14: =+IF($E14=0, 0, AF14/$E14) -> 296.04457 | AJ14: =+U14-F14 -> 576464 | AK14: =+V14-G14 -> 430354 | AL14: =+W14-H14 -> 146110 | AM14: =+X14-I14 -> 37193802 | AN14: =+Y14-J14 -> 29900546 | AO14: =+Z14-K14 -> 7293256 | AP14: =+AA14-L14 -> -21332782 | AQ14: =+AB14-M14 -> -17706441 | ... AX14: =+AI14-T14 -> 19.093001
C15: NONMET 1K-2K | D15: 5 | E15: =SUMIF($D$21:$D$517,$D15,E$21:E$517) -> 101624 | F15: =SUMIF($D$21:$D$517,$D15,F$21:F$517) -> 13061574 | G15: =SUMIF($D$21:$D$517,$D15,G$21:G$517) -> 9109814 | H15: =SUMIF($D$21:$D$517,$D15,H$21:H$517) -> 3951760 | I15: =SUMIF($D$21:$D$517,$D15,I$21:I$517) -> 3608303 | J15: =SUMIF($D$21:$D$517,$D15,J$21:J$517) -> 2797224 | K15: =SUMIF($D$21:$D$517,$D15,K$21:K$517) -> 811079 | L15: =SUMIF($D$21:$D$517,$D15,L$21:L$517) -> 64769230 | ... N15: =SUMIF($D$21:$D$517,$D15,N$21:N$517) -> 28414418 | O15: =+F15+I15+L15 -> 81439107 | P15: =+G15+J15+M15 -> 48261850 | Q15: =+H15+K15+N15 -> 33177257 | R15: =+IF($E15=0, 0, O15/$E15) -> 801.37671 | S15: =+IF($E15=0, 0, P15/$E15) -> 474.90603 | T15: =+IF($E15=0, 0, Q15/$E15) -> 326.47069 | U15: =SUMIF($D$21:$D$517,$D15,U$21:U$517) -> 14050971 | V15: =SUMIF($D$21:$D$517,$D15,V$21:V$517) -> 9767926 | W15: =SUMIF($D$21:$D$517,$D15,W$21:W$517) -> 4283045 | X15: =SUMIF($D$21:$D$517,$D15,X$21:X$517) -> 43086983 | Y15: =SUMIF($D$21:$D$517,$D15,Y$21:Y$517) -> 29722823 | Z15: =SUMIF($D$21:$D$517,$D15,Z$21:Z$517) -> 13364160 | AA15: =SUMIF($D$21:$D$517,$D15,AA$21:AA$517) -> 40101869 | AB15: =SUMIF($D$21:$D$517,$D15,AB$21:AB$517) -> 18426889 | AC15: =SUMIF($D$21:$D$517,$D15,AC$21:AC$517) -> 21674980 | AD15: =+U15+X15+AA15 -> 97239823 | AE15: =+V15+Y15+AB15 -> 57917638 | AF15: =+W15+Z15+AC15 -> 39322185 | AG15: =+IF($E15=0, 0, AD15/$E15) -> 956.85884 | AH15: =+IF($E15=0, 0, AE15/$E15) -> 569.92087 | AI15: =+IF($E15=0, 0, AF15/$E15) -> 386.93798 | AJ15: =+U15-F15 -> 989397 | AK15: =+V15-G15 -> 658112 | AL15: =+W15-H15 -> 331285 | AM15: =+X15-I15 -> 39478680 | AN15: =+Y15-J15 -> 26925599 | AO15: =+Z15-K15 -> 12553081 | AP15: =+AA15-L15 -> -24667361 | AQ15: =+AB15-M15 -> -17927923 | ... AX15: =+AI15-T15 -> 60.467291
C16: NONMET < 1K | D16: 6 | E16: =SUMIF($D$21:$D$517,$D16,E$21:E$517) -> 92857 | F16: =SUMIF($D$21:$D$517,$D16,F$21:F$517) -> 10778201 | G16: =SUMIF($D$21:$D$517,$D16,G$21:G$517) -> 7006886 | H16: =SUMIF($D$21:$D$517,$D16,H$21:H$517) -> 3771315 | I16: =SUMIF($D$21:$D$517,$D16,I$21:I$517) -> 177444 | J16: =SUMIF($D$21:$D$517,$D16,J$21:J$517) -> 136479 | K16: =SUMIF($D$21:$D$517,$D16,K$21:K$517) -> 40965 | L16: =SUMIF($D$21:$D$517,$D16,L$21:L$517) -> 85404065 | ... N16: =SUMIF($D$21:$D$517,$D16,N$21:N$517) -> 31896813 | O16: =+F16+I16+L16 -> 96359710 | P16: =+G16+J16+M16 -> 60650617 | Q16: =+H16+K16+N16 -> 35709093 | R16: =+IF($E16=0, 0, O16/$E16) -> 1037.7216 | S16: =+IF($E16=0, 0, P16/$E16) -> 653.1615 | T16: =+IF($E16=0, 0, Q16/$E16) -> 384.56005 | U16: =SUMIF($D$21:$D$517,$D16,U$21:U$517) -> 11642268 | V16: =SUMIF($D$21:$D$517,$D16,V$21:V$517) -> 7570513 | W16: =SUMIF($D$21:$D$517,$D16,W$21:W$517) -> 4071755 | X16: =SUMIF($D$21:$D$517,$D16,X$21:X$517) -> 39368245 | Y16: =SUMIF($D$21:$D$517,$D16,Y$21:Y$517) -> 25351973 | Z16: =SUMIF($D$21:$D$517,$D16,Z$21:Z$517) -> 14016272 | AA16: =SUMIF($D$21:$D$517,$D16,AA$21:AA$517) -> 57614939 | AB16: =SUMIF($D$21:$D$517,$D16,AB$21:AB$517) -> 30865037 | AC16: =SUMIF($D$21:$D$517,$D16,AC$21:AC$517) -> 26749902 | AD16: =+U16+X16+AA16 -> 108625452 | AE16: =+V16+Y16+AB16 -> 63787523 | AF16: =+W16+Z16+AC16 -> 44837929 | AG16: =+IF($E16=0, 0, AD16/$E16) -> 1169.8144 | AH16: =+IF($E16=0, 0, AE16/$E16) -> 686.94361 | AI16: =+IF($E16=0, 0, AF16/$E16) -> 482.87075 | AJ16: =+U16-F16 -> 864067 | AK16: =+V16-G16 -> 563627 | AL16: =+W16-H16 -> 300440 | AM16: =+X16-I16 -> 39190801 | AN16: =+Y16-J16 -> 25215494 | AO16: =+Z16-K16 -> 13975307 | AP16: =+AA16-L16 -> -27789126 | AQ16: =+AB16-M16 -> -22642215 | ... AX16: =+AI16-T16 -> 98.310693
C17: CHARTER | D17: 7 | E17: =SUMIF($D$21:$D$517,$D17,E$21:E$517) -> 55972 | F17: =SUMIF($D$21:$D$517,$D17,F$21:F$517) -> 6487360 | G17: =SUMIF($D$21:$D$517,$D17,G$21:G$517) -> 0 | H17: =SUMIF($D$21:$D$517,$D17,H$21:H$517) -> 6487360 | I17: =SUMIF($D$21:$D$517,$D17,I$21:I$517) -> 0 | J17: =SUMIF($D$21:$D$517,$D17,J$21:J$517) -> 0 | K17: =SUMIF($D$21:$D$517,$D17,K$21:K$517) -> 0 | L17: =SUMIF($D$21:$D$517,$D17,L$21:L$517) -> 0 | ... N17: =SUMIF($D$21:$D$517,$D17,N$21:N$517) -> 0 | O17: =+F17+I17+L17 -> 6487360 | P17: =+G17+J17+M17 -> 0 | Q17: =+H17+K17+N17 -> 6487360 | R17: =+IF($E17=0, 0, O17/$E17) -> 115.90367 | S17: =+IF($E17=0, 0, P17/$E17) -> 0 | T17: =+IF($E17=0, 0, Q17/$E17) -> 115.90367 | U17: =SUMIF($D$21:$D$517,$D17,U$21:U$517) -> 6624435 | V17: =SUMIF($D$21:$D$517,$D17,V$21:V$517) -> 0 | W17: =SUMIF($D$21:$D$517,$D17,W$21:W$517) -> 6624435 | X17: =SUMIF($D$21:$D$517,$D17,X$21:X$517) -> 0 | Y17: =SUMIF($D$21:$D$517,$D17,Y$21:Y$517) -> 0 | Z17: =SUMIF($D$21:$D$517,$D17,Z$21:Z$517) -> 0 | AA17: =SUMIF($D$21:$D$517,$D17,AA$21:AA$517) -> 0 | AB17: =SUMIF($D$21:$D$517,$D17,AB$21:AB$517) -> 0 | AC17: =SUMIF($D$21:$D$517,$D17,AC$21:AC$517) -> 0 | AD17: =+U17+X17+AA17 -> 6624435 | AE17: =+V17+Y17+AB17 -> 0 | AF17: =+W17+Z17+AC17 -> 6624435 | AG17: =+IF($E17=0, 0, AD17/$E17) -> 118.35266 | AH17: =+IF($E17=0, 0, AE17/$E17) -> 0 | AI17: =+IF($E17=0, 0, AF17/$E17) -> 118.35266 | AJ17: =+U17-F17 -> 137075 | AK17: =+V17-G17 -> 0 | AL17: =+W17-H17 -> 137075 | AM17: =+X17-I17 -> 0 | AN17: =+Y17-J17 -> 0 | AO17: =+Z17-K17 -> 0 | AP17: =+AA17-L17 -> 0 | AQ17: =+AB17-M17 -> 0 | ... AX17: =+AI17-T17 -> 2.4489924
C18: COOPERATIVES | D18: 8 | E18: =SUMIF($D$21:$D$517,$D18,E$21:E$517) -> 0 | F18: =SUMIF($D$21:$D$517,$D18,F$21:F$517) -> 0 | G18: =SUMIF($D$21:$D$517,$D18,G$21:G$517) -> 0 | H18: =SUMIF($D$21:$D$517,$D18,H$21:H$517) -> 0 | I18: =SUMIF($D$21:$D$517,$D18,I$21:I$517) -> 0 | J18: =SUMIF($D$21:$D$517,$D18,J$21:J$517) -> 0 | K18: =SUMIF($D$21:$D$517,$D18,K$21:K$517) -> 0 | L18: =SUMIF($D$21:$D$517,$D18,L$21:L$517) -> 0 | ... N18: =SUMIF($D$21:$D$517,$D18,N$21:N$517) -> 0 | O18: =+F18+I18+L18 -> 0 | P18: =+G18+J18+M18 -> 0 | Q18: =+H18+K18+N18 -> 0 | R18: =+IF($E18=0, 0, O18/$E18*1000) -> 0 | S18: =+IF($E18=0, 0, P18/$E18*1000) -> 0 | T18: =+IF($E18=0, 0, Q18/$E18*1000) -> 0 | U18: =SUMIF($D$21:$D$517,$D18,U$21:U$517) -> 0 | V18: =SUMIF($D$21:$D$517,$D18,V$21:V$517) -> 0 | W18: =SUMIF($D$21:$D$517,$D18,W$21:W$517) -> 0 | X18: =SUMIF($D$21:$D$517,$D18,X$21:X$517) -> 0 | Y18: =SUMIF($D$21:$D$517,$D18,Y$21:Y$517) -> 0 | Z18: =SUMIF($D$21:$D$517,$D18,Z$21:Z$517) -> 0 | AA18: =SUMIF($D$21:$D$517,$D18,AA$21:AA$517) -> 0 | AB18: =SUMIF($D$21:$D$517,$D18,AB$21:AB$517) -> 0 | AC18: =SUMIF($D$21:$D$517,$D18,AC$21:AC$517) -> 0 | AD18: =+U18+X18+AA18 -> 0 | AE18: =+V18+Y18+AB18 -> 0 | AF18: =+W18+Z18+AC18 -> 0 | AG18: =+IF($E18=0, 0, AD18/$E18*1000) -> 0 | AH18: =+IF($E18=0, 0, AE18/$E18*1000) -> 0 | AI18: =+IF($E18=0, 0, AF18/$E18*1000) -> 0 | AJ18: =+U18-F18 -> 0 | AK18: =+V18-G18 -> 0 | AL18: =+W18-H18 -> 0 | AM18: =+X18-I18 -> 0 | AN18: =+Y18-J18 -> 0 | AO18: =+Z18-K18 -> 0 | AP18: =+AA18-L18 -> 0 | AQ18: =+AB18-M18 -> 0 | ... AX18: =+AI18-T18 -> 0
C19: NONCHARTER FUDGE | D19: 9 | E19: =SUMIF($D$21:$D$517,$D19,E$21:E$517) -> 8458 | F19: =SUMIF($D$21:$D$517,$D19,F$21:F$517) -> 3854864 | G19: =SUMIF($D$21:$D$517,$D19,G$21:G$517) -> 1390887 | H19: =SUMIF($D$21:$D$517,$D19,H$21:H$517) -> 2463977 | I19: =SUMIF($D$21:$D$517,$D19,I$21:I$517) -> -2239029 | J19: =SUMIF($D$21:$D$517,$D19,J$21:J$517) -> -7112159 | K19: =SUMIF($D$21:$D$517,$D19,K$21:K$517) -> 4873130 | L19: =SUMIF($D$21:$D$517,$D19,L$21:L$517) -> 54760213 | ... N19: =SUMIF($D$21:$D$517,$D19,N$21:N$517) -> 14563215 | O19: =+F19+I19+L19 -> 56376048 | P19: =+G19+J19+M19 -> 34475726 | Q19: =+H19+K19+N19 -> 21900322 | R19: =+IF($E19=0, 0, O19/$E19) -> 6665.4112 | S19: =+IF($E19=0, 0, P19/$E19) -> 4076.1085 | T19: =+IF($E19=0, 0, Q19/$E19) -> 2589.3027 | U19: =SUMIF($D$21:$D$517,$D19,U$21:U$517) -> 3609228 | V19: =SUMIF($D$21:$D$517,$D19,V$21:V$517) -> 1106100 | W19: =SUMIF($D$21:$D$517,$D19,W$21:W$517) -> 2503128 | X19: =SUMIF($D$21:$D$517,$D19,X$21:X$517) -> -4417532 | Y19: =SUMIF($D$21:$D$517,$D19,Y$21:Y$517) -> -11600789 | Z19: =SUMIF($D$21:$D$517,$D19,Z$21:Z$517) -> 7183257 | AA19: =SUMIF($D$21:$D$517,$D19,AA$21:AA$517) -> 57096876 | AB19: =SUMIF($D$21:$D$517,$D19,AB$21:AB$517) -> 42933527 | AC19: =SUMIF($D$21:$D$517,$D19,AC$21:AC$517) -> 14163349 | AD19: =+U19+X19+AA19 -> 56288572 | AE19: =+V19+Y19+AB19 -> 32438838 | AF19: =+W19+Z19+AC19 -> 23849734 | AG19: =+IF($E19=0, 0, AD19/$E19) -> 6655.0688 | AH19: =+IF($E19=0, 0, AE19/$E19) -> 3835.2847 | AI19: =+IF($E19=0, 0, AF19/$E19) -> 2819.7841 | AJ19: =+U19-F19 -> -245636 | AK19: =+V19-G19 -> -284787 | AL19: =+W19-H19 -> 39151 | AM19: =+X19-I19 -> -2178503 | AN19: =+Y19-J19 -> -4488630 | AO19: =+Z19-K19 -> 2310127 | AP19: =+AA19-L19 -> 2336663 | AQ19: =+AB19-M19 -> 2736529 | ... AX19: =+AI19-T19 -> 230.48144
A21: 1 | B21: 1 | C21: AITKIN | D21: 5 | E21: =+SUMIF('GE16FEB14 Unfudged'!$A$2:$A$498, $A21, 'GE16FEB14 Unfudged'!$D$2:$D$498) -> 1285 | F21: =+SUMIF('GE16FEB14 Unfudged'!$A$2:$A$498, 'Tax Bill Summary'!$A21, 'GE16FEB14 Unfudged'!E$2:E$498) -> 185040 | G21: =+SUMIF('GE16FEB14 Unfudged'!$A$2:$A$498, 'Tax Bill Summary'!$A21, 'GE16FEB14 Unfudged'!F$2:F$498) -> 185040 | H21: =+F21-G21 -> 0 | I21: =+SUMIF('GE16FEB14 Unfudged'!$A$2:$A$498, 'Tax Bill Summary'!$A21, 'GE16FEB14 Unfudged'!G$2:G$498) -> 0 | J21: =+SUMIF('GE16FEB14 Unfudged'!$A$2:$A$498, 'Tax Bill Summary'!$A21, 'GE16FEB14 Unfudged'!H$2:H$498) -> 0 | K21: =+I21-J21 -> 0 | L21: =+SUMIF('GE16FEB14 Unfudged'!$A$2:$A$498, 'Tax Bill Summary'!$A21, 'GE16FEB14 Unfudged'!I$2:IF$498) -> 385500 | M21: =+SUMIF('GE16FEB14 Unfudged'!$A$2:$A$498, 'Tax Bill Summary'!$A21, 'GE16FEB14 Unfudged'!J$2:IG$498) -> 260672 | N21: =+L21-M21 -> 124828 | O21: =+F21+I21+L21 -> 570540 | P21: =+G21+J21+M21 -> 445712 | Q21: =+H21+K21+N21 -> 124828 | R21: =+IF($E21=0, 0, O21/$E21) -> 444 | S21: =+IF($E21=0, 0, P21/$E21) -> 346.85759 | T21: =+IF($E21=0, 0, Q21/$E21) -> 97.142412 | U21: =+SUMIF('GE16FEB14 Tax Bill Unfudged'!$A$2:$A$498, 'Tax Bill Summary'!$A21, 'GE16FEB14 Tax Bill Unfudged'!E$2:E$498) -> 185040 | V21: =+SUMIF('GE16FEB14 Tax Bill Unfudged'!$A$2:$A$498, 'Tax Bill Summary'!$A21, 'GE16FEB14 Tax Bill Unfudged'!F$2:F$498) -> 185040 | W21: =+U21-V21 -> 0 | X21: =+SUMIF('GE16FEB14 Tax Bill Unfudged'!$A$2:$A$498, 'Tax Bill Summary'!$A21, 'GE16FEB14 Tax Bill Unfudged'!G$2:G$498) -> 544840 | Y21: =+SUMIF('GE16FEB14 Tax Bill Unfudged'!$A$2:$A$498, 'Tax Bill Summary'!$A21, 'GE16FEB14 Tax Bill Unfudged'!H$2:H$498) -> 544840 | Z21: =+X21-Y21 -> 0 | AA21: =+SUMIF('GE16FEB14 Tax Bill Unfudged'!$A$2:$A$498, 'Tax Bill Summary'!$A21, 'GE16FEB14 Tax Bill Unfudged'!I$2:I$498) -> 385500 | AB21: =+SUMIF('GE16FEB14 Tax Bill Unfudged'!$A$2:$A$498, 'Tax Bill Summary'!$A21, 'GE16FEB14 Tax Bill Unfudged'!J$2:J$498) -> 260672 | AC21: =+AA21-AB21 -> 124828 | AD21: =+U21+X21+AA21 -> 1115380 | AE21: =+V21+Y21+AB21 -> 990552 | AF21: =+W21+Z21+AC21 -> 124828 | AG21: =+IF($E21=0, 0, AD21/$E21) -> 868 | AH21: =+IF($E21=0, 0, AE21/$E21) -> 770.85759 | AI21: =+IF($E21=0, 0, AF21/$E21) -> 97.142412 | AJ21: =+U21-F21 -> 0 | AK21: =+V21-G21 -> 0 | AL21: =+W21-H21 -> 0 | AM21: =+X21-I21 -> 544840 | AN21: =+Y21-J21 -> 544840 | AO21: =+Z21-K21 -> 0 | AP21: =+AA21-L21 -> 0 | AQ21: =+AB21-M21 -> 0 | ... AX21: =+AI21-T21 -> 0
A22: 1.2 | B22: 3 | C22: MINNEAPOLIS | D22: 1 | E22: =+SUMIF('GE16FEB14 Unfudged'!$A$2:$A$498, $A22, 'GE16FEB14 Unfudged'!$D$2:$D$498) -> 39607 | F22: =+SUMIF('GE16FEB14 Unfudged'!$A$2:$A$498, 'Tax Bill Summary'!$A22, 'GE16FEB14 Unfudged'!E$2:E$498) -> 1980330 | G22: =+SUMIF('GE16FEB14 Unfudged'!$A$2:$A$498, 'Tax Bill Summary'!$A22, 'GE16FEB14 Unfudged'!F$2:F$498) -> 1980330 | H22: =+F22-G22 -> 0 | I22: =+SUMIF('GE16FEB14 Unfudged'!$A$2:$A$498, 'Tax Bill Summary'!$A22, 'GE16FEB14 Unfudged'!G$2:G$498) -> 16793198 | J22: =+SUMIF('GE16FEB14 Unfudged'!$A$2:$A$498, 'Tax Bill Summary'!$A22, 'GE16FEB14 Unfudged'!H$2:H$498) -> 16793198 | K22: =+I22-J22 -> 0 | L22: =+SUMIF('GE16FEB14 Unfudged'!$A$2:$A$498, 'Tax Bill Summary'!$A22, 'GE16FEB14 Unfudged'!I$2:IF$498) -> 55978780 | M22: =+SUMIF('GE16FEB14 Unfudged'!$A$2:$A$498, 'Tax Bill Summary'!$A22, 'GE16FEB14 Unfudged'!J$2:IG$498) -> 52894542 | N22: =+L22-M22 -> 3084238 | O22: =+F22+I22+L22 -> 74752308 | P22: =+G22+J22+M22 -> 71668070 | Q22: =+H22+K22+N22 -> 3084238 | R22: =+IF($E22=0, 0, O22/$E22) -> 1887.3509 | S22: =+IF($E22=0, 0, P22/$E22) -> 1809.4799 | T22: =+IF($E22=0, 0, Q22/$E22) -> 77.871033 | U22: =+SUMIF('GE16FEB14 Tax Bill Unfudged'!$A$2:$A$498, 'Tax Bill Summary'!$A22, 'GE16FEB14 Tax Bill Unfudged'!E$2:E$498) -> 1980330 | V22: =+SUMIF('GE16FEB14 Tax Bill Unfudged'!$A$2:$A$498, 'Tax Bill Summary'!$A22, 'GE16FEB14 Tax Bill Unfudged'!F$2:F$498) -> 1980330 | W22: =+U22-V22 -> 0 | X22: =+SUMIF('GE16FEB14 Tax Bill Unfudged'!$A$2:$A$498, 'Tax Bill Summary'!$A22, 'GE16FEB14 Tax Bill Unfudged'!G$2:G$498) -> 16793198 | Y22: =+SUMIF('GE16FEB14 Tax Bill Unfudged'!$A$2:$A$498, 'Tax Bill Summary'!$A22, 'GE16FEB14 Tax Bill Unfudged'!H$2:H$498) -> 16793198 | Z22: =+X22-Y22 -> 0 | AA22: =+SUMIF('GE16FEB14 Tax Bill Unfudged'!$A$2:$A$498, 'Tax Bill Summary'!$A22, 'GE16FEB14 Tax Bill Unfudged'!I$2:I$498) -> 55978780 | AB22: =+SUMIF('GE16FEB14 Tax Bill Unfudged'!$A$2:$A$498, 'Tax Bill Summary'!$A22, 'GE16FEB14 Tax Bill Unfudged'!J$2:J$498) -> 52894542 | AC22: =+AA22-AB22 -> 3084238 | AD22: =+U22+X22+AA22 -> 74752308 | AE22: =+V22+Y22+AB22 -> 71668070 | AF22: =+W22+Z22+AC22 -> 3084238 | AG22: =+IF($E22=0, 0, AD22/$E22) -> 1887.3509 | AH22: =+IF($E22=0, 0, AE22/$E22) -> 1809.4799 | AI22: =+IF($E22=0, 0, AF22/$E22) -> 77.871033 | AJ22: =+U22-F22 -> 0 | AK22: =+V22-G22 -> 0 | AL22: =+W22-H22 -> 0 | AM22: =+X22-I22 -> 0 | AN22: =+Y22-J22 -> 0 | AO22: =+Z22-K22 -> 0 | AP22: =+AA22-L22 -> 0 | AQ22: =+AB22-M22 -> 0 | ... AX22: =+AI22-T22 -> 0
A23: 2 | B23: 1 | C23: HILL CITY | D23: 6 | E23: =+SUMIF('GE16FEB14 Unfudged'!$A$2:$A$498, $A23, 'GE16FEB14 Unfudged'!$D$2:$D$498) -> 284 | F23: =+SUMIF('GE16FEB14 Unfudged'!$A$2:$A$498, 'Tax Bill Summary'!$A23, 'GE16FEB14 Unfudged'!E$2:E$498) -> 40889 | G23: =+SUMIF('GE16FEB14 Unfudged'!$A$2:$A$498, 'Tax Bill Summary'!$A23, 'GE16FEB14 Unfudged'!F$2:F$498) -> 22793 | H23: =+F23-G23 -> 18096 | I23: =+SUMIF('GE16FEB14 Unfudged'!$A$2:$A$498, 'Tax Bill Summary'!$A23, 'GE16FEB14 Unfudged'!G$2:G$498) -> 0 | J23: =+SUMIF('GE16FEB14 Unfudged'!$A$2:$A$498, 'Tax Bill Summary'!$A23, 'GE16FEB14 Unfudged'!H$2:H$498) -> 0 | K23: =+I23-J23 -> 0 | L23: =+SUMIF('GE16FEB14 Unfudged'!$A$2:$A$498, 'Tax Bill Summary'!$A23, 'GE16FEB14 Unfudged'!I$2:IF$498) -> 85185 | M23: =+SUMIF('GE16FEB14 Unfudged'!$A$2:$A$498, 'Tax Bill Summary'!$A23, 'GE16FEB14 Unfudged'!J$2:IG$498) -> 27520 | N23: =+L23-M23 -> 57665 | O23: =+F23+I23+L23 -> 126074 | P23: =+G23+J23+M23 -> 50313 | Q23: =+H23+K23+N23 -> 75761 | R23: =+IF($E23=0, 0, O23/$E23) -> 443.92254 | S23: =+IF($E23=0, 0, P23/$E23) -> 177.15845 | T23: =+IF($E23=0, 0, Q23/$E23) -> 266.76408 | U23: =+SUMIF('GE16FEB14 Tax Bill Unfudged'!$A$2:$A$498, 'Tax Bill Summary'!$A23, 'GE16FEB14 Tax Bill Unfudged'!E$2:E$498) -> 40889 | V23: =+SUMIF('GE16FEB14 Tax Bill Unfudged'!$A$2:$A$498, 'Tax Bill Summary'!$A23, 'GE16FEB14 Tax Bill Unfudged'!F$2:F$498) -> 22793 | W23: =+U23-V23 -> 18096 | X23: =+SUMIF('GE16FEB14 Tax Bill Unfudged'!$A$2:$A$498, 'Tax Bill Summary'!$A23, 'GE16FEB14 Tax Bill Unfudged'!G$2:G$498) -> 120395 | Y23: =+SUMIF('GE16FEB14 Tax Bill Unfudged'!$A$2:$A$498, 'Tax Bill Summary'!$A23, 'GE16FEB14 Tax Bill Unfudged'!H$2:H$498) -> 67113 | Z23: =+X23-Y23 -> 53282 | AA23: =+SUMIF('GE16FEB14 Tax Bill Unfudged'!$A$2:$A$498, 'Tax Bill Summary'!$A23, 'GE16FEB14 Tax Bill Unfudged'!I$2:I$498) -> 85185 | AB23: =+SUMIF('GE16FEB14 Tax Bill Unfudged'!$A$2:$A$498, 'Tax Bill Summary'!$A23, 'GE16FEB14 Tax Bill Unfudged'!J$2:J$498) -> 27520 | AC23: =+AA23-AB23 -> 57665 | AD23: =+U23+X23+AA23 -> 246469 | AE23: =+V23+Y23+AB23 -> 117426 | AF23: =+W23+Z23+AC23 -> 129043 | AG23: =+IF($E23=0, 0, AD23/$E23) -> 867.84859 | AH23: =+IF($E23=0, 0, AE23/$E23) -> 413.47183 | AI23: =+IF($E23=0, 0, AF23/$E23) -> 454.37676 | AJ23: =+U23-F23 -> 0 | AK23: =+V23-G23 -> 0 | AL23: =+W23-H23 -> 0 | AM23: =+X23-I23 -> 120395 | AN23: =+Y23-J23 -> 67113 | AO23: =+Z23-K23 -> 53282 | AP23: =+AA23-L23 -> 0 | AQ23: =+AB23-M23 -> 0 | ... AX23: =+AI23-T23 -> 187.61268
A24: 4 | B24: 1 | C24: MCGREGOR | D24: 6 | E24: =+SUMIF('GE16FEB14 Unfudged'!$A$2:$A$498, $A24, 'GE16FEB14 Unfudged'!$D$2:$D$498) -> 434 | F24: =+SUMIF('GE16FEB14 Unfudged'!$A$2:$A$498, 'Tax Bill Summary'!$A24, 'GE16FEB14 Unfudged'!E$2:E$498) -> 62554 | G24: =+SUMIF('GE16FEB14 Unfudged'!$A$2:$A$498, 'Tax Bill Summary'!$A24, 'GE16FEB14 Unfudged'!F$2:F$498) -> 62554 | H24: =+F24-G24 -> 0 | I24: =+SUMIF('GE16FEB14 Unfudged'!$A$2:$A$498, 'Tax Bill Summary'!$A24, 'GE16FEB14 Unfudged'!G$2:G$498) -> 0 | J24: =+SUMIF('GE16FEB14 Unfudged'!$A$2:$A$498, 'Tax Bill Summary'!$A24, 'GE16FEB14 Unfudged'!H$2:H$498) -> 0 | K24: =+I24-J24 -> 0 | L24: =+SUMIF('GE16FEB14 Unfudged'!$A$2:$A$498, 'Tax Bill Summary'!$A24, 'GE16FEB14 Unfudged'!I$2:IF$498) -> 130320 | M24: =+SUMIF('GE16FEB14 Unfudged'!$A$2:$A$498, 'Tax Bill Summary'!$A24, 'GE16FEB14 Unfudged'!J$2:IG$498) -> 77314 | N24: =+L24-M24 -> 53006 | O24: =+F24+I24+L24 -> 192874 | P24: =+G24+J24+M24 -> 139868 | Q24: =+H24+K24+N24 -> 53006 | R24: =+IF($E24=0, 0, O24/$E24) -> 444.41014 | S24: =+IF($E24=0, 0, P24/$E24) -> 322.2765 | T24: =+IF($E24=0, 0, Q24/$E24) -> 122.13364 | U24: =+SUMIF('GE16FEB14 Tax Bill Unfudged'!$A$2:$A$498, 'Tax Bill Summary'!$A24, 'GE16FEB14 Tax Bill Unfudged'!E$2:E$498) -> 62554 | V24: =+SUMIF('GE16FEB14 Tax Bill Unfudged'!$A$2:$A$498, 'Tax Bill Summary'!$A24, 'GE16FEB14 Tax Bill Unfudged'!F$2:F$498) -> 62554 | W24: =+U24-V24 -> 0 | X24: =+SUMIF('GE16FEB14 Tax Bill Unfudged'!$A$2:$A$498, 'Tax Bill Summary'!$A24, 'GE16FEB14 Tax Bill Unfudged'!G$2:G$498) -> 184186 | Y24: =+SUMIF('GE16FEB14 Tax Bill Unfudged'!$A$2:$A$498, 'Tax Bill Summary'!$A24, 'GE16FEB14 Tax Bill Unfudged'!H$2:H$498) -> 184186 | Z24: =+X24-Y24 -> 0 | AA24: =+SUMIF('GE16FEB14 Tax Bill Unfudged'!$A$2:$A$498, 'Tax Bill Summary'!$A24, 'GE16FEB14 Tax Bill Unfudged'!I$2:I$498) -> 130320 | AB24: =+SUMIF('GE16FEB14 Tax Bill Unfudged'!$A$2:$A$498, 'Tax Bill Summary'!$A24, 'GE16FEB14 Tax Bill Unfudged'!J$2:J$498) -> 77314 | AC24: =+AA24-AB24 -> 53006 | AD24: =+U24+X24+AA24 -> 377060 | AE24: =+V24+Y24+AB24 -> 324054 | AF24: =+W24+Z24+AC24 -> 53006 | AG24: =+IF($E24=0, 0, AD24/$E24) -> 868.80184 | AH24: =+IF($E24=0, 0, AE24/$E24) -> 746.6682 | AI24: =+IF($E24=0, 0, AF24/$E24) -> 122.13364 | AJ24: =+U24-F24 -> 0 | AK24: =+V24-G24 -> 0 | AL24: =+W24-H24 -> 0 | AM24: =+X24-I24 -> 184186 | AN24: =+Y24-J24 -> 184186 | AO24: =+Z24-K24 -> 0 | AP24: =+AA24-L24 -> 0 | AQ24: =+AB24-M24 -> 0 | ... AX24: =+AI24-T24 -> 0
A25: 6 | B25: 3 | C25: SOUTH ST. PAUL | D25: 2 | E25: =+SUMIF('GE16FEB14 Unfudged'!$A$2:$A$498, $A25, 'GE16FEB14 Unfudged'!$D$2:$D$498) -> 3736 | F25: =+SUMIF('GE16FEB14 Unfudged'!$A$2:$A$498, 'Tax Bill Summary'!$A25, 'GE16FEB14 Unfudged'!E$2:E$498) -> 557934 | G25: =+SUMIF('GE16FEB14 Unfudged'!$A$2:$A$498, 'Tax Bill Summary'!$A25, 'GE16FEB14 Unfudged'!F$2:F$498) -> 396251 | H25: =+F25-G25 -> 161683 | I25: =+SUMIF('GE16FEB14 Unfudged'!$A$2:$A$498, 'Tax Bill Summary'!$A25, 'GE16FEB14 Unfudged'!G$2:G$498) -> 1584234 | J25: =+SUMIF('GE16FEB14 Unfudged'!$A$2:$A$498, 'Tax Bill Summary'!$A25, 'GE16FEB14 Unfudged'!H$2:H$498) -> 1125142 | K25: =+I25-J25 -> 459092 | L25: =+SUMIF('GE16FEB14 Unfudged'!$A$2:$A$498, 'Tax Bill Summary'!$A25, 'GE16FEB14 Unfudged'!I$2:IF$498) -> 2005625 | M25: =+SUMIF('GE16FEB14 Unfudged'!$A$2:$A$498, 'Tax Bill Summary'!$A25, 'GE16FEB14 Unfudged'!J$2:IG$498) -> 1089699 | N25: =+L25-M25 -> 915926 | O25: =+F25+I25+L25 -> 4147793 | P25: =+G25+J25+M25 -> 2611092 | Q25: =+H25+K25+N25 -> 1536701 | R25: =+IF($E25=0, 0, O25/$E25) -> 1110.223 | S25: =+IF($E25=0, 0, P25/$E25) -> 698.90043 | T25: =+IF($E25=0, 0, Q25/$E25) -> 411.32254 | U25: =+SUMIF('GE16FEB14 Tax Bill Unfudged'!$A$2:$A$498, 'Tax Bill Summary'!$A25, 'GE16FEB14 Tax Bill Unfudged'!E$2:E$498) -> 557934 | V25: =+SUMIF('GE16FEB14 Tax Bill Unfudged'!$A$2:$A$498, 'Tax Bill Summary'!$A25, 'GE16FEB14 Tax Bill Unfudged'!F$2:F$498) -> 396251 | W25: =+U25-V25 -> 161683 | X25: =+SUMIF('GE16FEB14 Tax Bill Unfudged'!$A$2:$A$498, 'Tax Bill Summary'!$A25, 'GE16FEB14 Tax Bill Unfudged'!G$2:G$498) -> 1584234 | Y25: =+SUMIF('GE16FEB14 Tax Bill Unfudged'!$A$2:$A$498, 'Tax Bill Summary'!$A25, 'GE16FEB14 Tax Bill Unfudged'!H$2:H$498) -> 1125142 | Z25: =+X25-Y25 -> 459092 | AA25: =+SUMIF('GE16FEB14 Tax Bill Unfudged'!$A$2:$A$498, 'Tax Bill Summary'!$A25, 'GE16FEB14 Tax Bill Unfudged'!I$2:I$498) -> 2005625 | AB25: =+SUMIF('GE16FEB14 Tax Bill Unfudged'!$A$2:$A$498, 'Tax Bill Summary'!$A25, 'GE16FEB14 Tax Bill Unfudged'!J$2:J$498) -> 1089699 | AC25: =+AA25-AB25 -> 915926 | AD25: =+U25+X25+AA25 -> 4147793 | AE25: =+V25+Y25+AB25 -> 2611092 | AF25: =+W25+Z25+AC25 -> 1536701 | AG25: =+IF($E25=0, 0, AD25/$E25) -> 1110.223 | AH25: =+IF($E25=0, 0, AE25/$E25) -> 698.90043 | AI25: =+IF($E25=0, 0, AF25/$E25) -> 411.32254 | AJ25: =+U25-F25 -> 0 | AK25: =+V25-G25 -> 0 | AL25: =+W25-H25 -> 0 | AM25: =+X25-I25 -> 0 | AN25: =+Y25-J25 -> 0 | AO25: =+Z25-K25 -> 0 | AP25: =+AA25-L25 -> 0 | AQ25: =+AB25-M25 -> 0 | ... AX25: =+AI25-T25 -> 0
A26: 11 | B26: 1 | C26: ANOKA-HENNEPIN | D26: 3 | E26: =+SUMIF('GE16FEB14 Unfudged'!$A$2:$A$498, $A26, 'GE16FEB14 Unfudged'!$D$2:$D$498) -> 39798 | F26: =+SUMIF('GE16FEB14 Unfudged'!$A$2:$A$498, 'Tax Bill Summary'!$A26, 'GE16FEB14 Unfudged'!E$2:E$498) -> 4558334 | G26: =+SUMIF('GE16FEB14 Unfudged'!$A$2:$A$498, 'Tax Bill Summary'!$A26, 'GE16FEB14 Unfudged'!F$2:F$498) -> 3244342 | H26: =+F26-G26 -> 1313992 | I26: =+SUMIF('GE16FEB14 Unfudged'!$A$2:$A$498, 'Tax Bill Summary'!$A26, 'GE16FEB14 Unfudged'!G$2:G$498) -> 16874267 | J26: =+SUMIF('GE16FEB14 Unfudged'!$A$2:$A$498, 'Tax Bill Summary'!$A26, 'GE16FEB14 Unfudged'!H$2:H$498) -> 12010067 | K26: =+I26-J26 -> 4864200 | L26: =+SUMIF('GE16FEB14 Unfudged'!$A$2:$A$498, 'Tax Bill Summary'!$A26, 'GE16FEB14 Unfudged'!I$2:IF$498) -> 39397832 | M26: =+SUMIF('GE16FEB14 Unfudged'!$A$2:$A$498, 'Tax Bill Summary'!$A26, 'GE16FEB14 Unfudged'!J$2:IG$498) -> 27106091 | N26: =+L26-M26 -> 12291741 | O26: =+F26+I26+L26 -> 60830433 | P26: =+G26+J26+M26 -> 42360500 | Q26: =+H26+K26+N26 -> 18469933 | R26: =+IF($E26=0, 0, O26/$E26) -> 1528.4796 | S26: =+IF($E26=0, 0, P26/$E26) -> 1064.3877 | T26: =+IF($E26=0, 0, Q26/$E26) -> 464.09199 | U26: =+SUMIF('GE16FEB14 Tax Bill Unfudged'!$A$2:$A$498, 'Tax Bill Summary'!$A26, 'GE16FEB14 Tax Bill Unfudged'!E$2:E$498) -> 4558334 | V26: =+SUMIF('GE16FEB14 Tax Bill Unfudged'!$A$2:$A$498, 'Tax Bill Summary'!$A26, 'GE16FEB14 Tax Bill Unfudged'!F$2:F$498) -> 3244342 | W26: =+U26-V26 -> 1313992 | X26: =+SUMIF('GE16FEB14 Tax Bill Unfudged'!$A$2:$A$498, 'Tax Bill Summary'!$A26, 'GE16FEB14 Tax Bill Unfudged'!G$2:G$498) -> 16874267 | Y26: =+SUMIF('GE16FEB14 Tax Bill Unfudged'!$A$2:$A$498, 'Tax Bill Summary'!$A26, 'GE16FEB14 Tax Bill Unfudged'!H$2:H$498) -> 12010067 | Z26: =+X26-Y26 -> 4864200 | AA26: =+SUMIF('GE16FEB14 Tax Bill Unfudged'!$A$2:$A$498, 'Tax Bill Summary'!$A26, 'GE16FEB14 Tax Bill Unfudged'!I$2:I$498) -> 39397832 | AB26: =+SUMIF('GE16FEB14 Tax Bill Unfudged'!$A$2:$A$498, 'Tax Bill Summary'!$A26, 'GE16FEB14 Tax Bill Unfudged'!J$2:J$498) -> 27106091 | AC26: =+AA26-AB26 -> 12291741 | AD26: =+U26+X26+AA26 -> 60830433 | AE26: =+V26+Y26+AB26 -> 42360500 | AF26: =+W26+Z26+AC26 -> 18469933 | AG26: =+IF($E26=0, 0, AD26/$E26) -> 1528.4796 | AH26: =+IF($E26=0, 0, AE26/$E26) -> 1064.3877 | AI26: =+IF($E26=0, 0, AF26/$E26) -> 464.09199 | AJ26: =+U26-F26 -> 0 | AK26: =+V26-G26 -> 0 | AL26: =+W26-H26 -> 0 | AM26: =+X26-I26 -> 0 | AN26: =+Y26-J26 -> 0 | AO26: =+Z26-K26 -> 0 | AP26: =+AA26-L26 -> 0 | AQ26: =+AB26-M26 -> 0 | ... AX26: =+AI26-T26 -> 0
A27: 12 | B27: 1 | C27: CENTENNIAL | D27: 3 | E27: =+SUMIF('GE16FEB14 Unfudged'!$A$2:$A$498, $A27, 'GE16FEB14 Unfudged'!$D$2:$D$498) -> 6971 | F27: =+SUMIF('GE16FEB14 Unfudged'!$A$2:$A$498, 'Tax Bill Summary'!$A27, 'GE16FEB14 Unfudged'!E$2:E$498) -> 1079123 | G27: =+SUMIF('GE16FEB14 Unfudged'!$A$2:$A$498, 'Tax Bill Summary'!$A27, 'GE16FEB14 Unfudged'!F$2:F$498) -> 838445 | H27: =+F27-G27 -> 240678 | I27: =+SUMIF('GE16FEB14 Unfudged'!$A$2:$A$498, 'Tax Bill Summary'!$A27, 'GE16FEB14 Unfudged'!G$2:G$498) -> 2955789 | J27: =+SUMIF('GE16FEB14 Unfudged'!$A$2:$A$498, 'Tax Bill Summary'!$A27, 'GE16FEB14 Unfudged'!H$2:H$498) -> 2296557 | K27: =+I27-J27 -> 659232 | L27: =+SUMIF('GE16FEB14 Unfudged'!$A$2:$A$498, 'Tax Bill Summary'!$A27, 'GE16FEB14 Unfudged'!I$2:IF$498) -> 3244954 | M27: =+SUMIF('GE16FEB14 Unfudged'!$A$2:$A$498, 'Tax Bill Summary'!$A27, 'GE16FEB14 Unfudged'!J$2:IG$498) -> 1838023 | N27: =+L27-M27 -> 1406931 | O27: =+F27+I27+L27 -> 7279866 | P27: =+G27+J27+M27 -> 4973025 | Q27: =+H27+K27+N27 -> 2306841 | R27: =+IF($E27=0, 0, O27/$E27) -> 1044.3073 | S27: =+IF($E27=0, 0, P27/$E27) -> 713.38761 | T27: =+IF($E27=0, 0, Q27/$E27) -> 330.91967 | U27: =+SUMIF('GE16FEB14 Tax Bill Unfudged'!$A$2:$A$498, 'Tax Bill Summary'!$A27, 'GE16FEB14 Tax Bill Unfudged'!E$2:E$498) -> 1079123 | V27: =+SUMIF('GE16FEB14 Tax Bill Unfudged'!$A$2:$A$498, 'Tax Bill Summary'!$A27, 'GE16FEB14 Tax Bill Unfudged'!F$2:F$498) -> 838445 | W27: =+U27-V27 -> 240678 | X27: =+SUMIF('GE16FEB14 Tax Bill Unfudged'!$A$2:$A$498, 'Tax Bill Summary'!$A27, 'GE16FEB14 Tax Bill Unfudged'!G$2:G$498) -> 2955789 | Y27: =+SUMIF('GE16FEB14 Tax Bill Unfudged'!$A$2:$A$498, 'Tax Bill Summary'!$A27, 'GE16FEB14 Tax Bill Unfudged'!H$2:H$498) -> 2296557 | Z27: =+X27-Y27 -> 659232 | AA27: =+SUMIF('GE16FEB14 Tax Bill Unfudged'!$A$2:$A$498, 'Tax Bill Summary'!$A27, 'GE16FEB14 Tax Bill Unfudged'!I$2:I$498) -> 3244954 | AB27: =+SUMIF('GE16FEB14 Tax Bill Unfudged'!$A$2:$A$498, 'Tax Bill Summary'!$A27, 'GE16FEB14 Tax Bill Unfudged'!J$2:J$498) -> 1838023 | AC27: =+AA27-AB27 -> 1406931 | AD27: =+U27+X27+AA27 -> 7279866 | AE27: =+V27+Y27+AB27 -> 4973025 | AF27: =+W27+Z27+AC27 -> 2306841 | AG27: =+IF($E27=0, 0, AD27/$E27) -> 1044.3073 | AH27: =+IF($E27=0, 0, AE27/$E27) -> 713.38761 | AI27: =+IF($E27=0, 0, AF27/$E27) -> 330.91967 | AJ27: =+U27-F27 -> 0 | AK27: =+V27-G27 -> 0 | AL27: =+W27-H27 -> 0 | AM27: =+X27-I27 -> 0 | AN27: =+Y27-J27 -> 0 | AO27: =+Z27-K27 -> 0 | AP27: =+AA27-L27 -> 0 | AQ27: =+AB27-M27 -> 0 | ... AX27: =+AI27-T27 -> 0
A28: 13 | B28: 1 | C28: COLUMBIA HEIGHTS | D28: 2 | E28: =+SUMIF('GE16FEB14 Unfudged'!$A$2:$A$498, $A28, 'GE16FEB14 Unfudged'!$D$2:$D$498) -> 3362 | F28: =+SUMIF('GE16FEB14 Unfudged'!$A$2:$A$498, 'Tax Bill Summary'!$A28, 'GE16FEB14 Unfudged'!E$2:E$498) -> 483364 | G28: =+SUMIF('GE16FEB14 Unfudged'!$A$2:$A$498, 'Tax Bill Summary'!$A28, 'GE16FEB14 Unfudged'!F$2:F$498) -> 360094 | H28: =+F28-G28 -> 123270 | I28: =+SUMIF('GE16FEB14 Unfudged'!$A$2:$A$498, 'Tax Bill Summary'!$A28, 'GE16FEB14 Unfudged'!G$2:G$498) -> 1425361 | J28: =+SUMIF('GE16FEB14 Unfudged'!$A$2:$A$498, 'Tax Bill Summary'!$A28, 'GE16FEB14 Unfudged'!H$2:H$498) -> 1061860 | K28: =+I28-J28 -> 363501 | L28: =+SUMIF('GE16FEB14 Unfudged'!$A$2:$A$498, 'Tax Bill Summary'!$A28, 'GE16FEB14 Unfudged'!I$2:IF$498) -> 2047040 | M28: =+SUMIF('GE16FEB14 Unfudged'!$A$2:$A$498, 'Tax Bill Summary'!$A28, 'GE16FEB14 Unfudged'!J$2:IG$498) -> 1209102 | N28: =+L28-M28 -> 837938 | O28: =+F28+I28+L28 -> 3955765 | P28: =+G28+J28+M28 -> 2631056 | Q28: =+H28+K28+N28 -> 1324709 | R28: =+IF($E28=0, 0, O28/$E28) -> 1176.6106 | S28: =+IF($E28=0, 0, P28/$E28) -> 782.58656 | T28: =+IF($E28=0, 0, Q28/$E28) -> 394.02409 | U28: =+SUMIF('GE16FEB14 Tax Bill Unfudged'!$A$2:$A$498, 'Tax Bill Summary'!$A28, 'GE16FEB14 Tax Bill Unfudged'!E$2:E$498) -> 483364 | V28: =+SUMIF('GE16FEB14 Tax Bill Unfudged'!$A$2:$A$498, 'Tax Bill Summary'!$A28, 'GE16FEB14 Tax Bill Unfudged'!F$2:F$498) -> 360094 | W28: =+U28-V28 -> 123270 | X28: =+SUMIF('GE16FEB14 Tax Bill Unfudged'!$A$2:$A$498, 'Tax Bill Summary'!$A28, 'GE16FEB14 Tax Bill Unfudged'!G$2:G$498) -> 1425361 | Y28: =+SUMIF('GE16FEB14 Tax Bill Unfudged'!$A$2:$A$498, 'Tax Bill Summary'!$A28, 'GE16FEB14 Tax Bill Unfudged'!H$2:H$498) -> 1061860 | Z28: =+X28-Y28 -> 363501 | AA28: =+SUMIF('GE16FEB14 Tax Bill Unfudged'!$A$2:$A$498, 'Tax Bill Summary'!$A28, 'GE16FEB14 Tax Bill Unfudged'!I$2:I$498) -> 2047040 | AB28: =+SUMIF('GE16FEB14 Tax Bill Unfudged'!$A$2:$A$498, 'Tax Bill Summary'!$A28, 'GE16FEB14 Tax Bill Unfudged'!J$2:J$498) -> 1209102 | AC28: =+AA28-AB28 -> 837938 | AD28: =+U28+X28+AA28 -> 3955765 | AE28: =+V28+Y28+AB28 -> 2631056 | AF28: =+W28+Z28+AC28 -> 1324709 | AG28: =+IF($E28=0, 0, AD28/$E28) -> 1176.6106 | AH28: =+IF($E28=0, 0, AE28/$E28) -> 782.58656 | AI28: =+IF($E28=0, 0, AF28/$E28) -> 394.02409 | AJ28: =+U28-F28 -> 0 | AK28: =+V28-G28 -> 0 | AL28: =+W28-H28 -> 0 | AM28: =+X28-I28 -> 0 | AN28: =+Y28-J28 -> 0 | AO28: =+Z28-K28 -> 0 | AP28: =+AA28-L28 -> 0 | AQ28: =+AB28-M28 -> 0 | ... AX28: =+AI28-T28 -> 0
A29: 14 | B29: 1 | C29: FRIDLEY | D29: 3 | E29: =+SUMIF('GE16FEB14 Unfudged'!$A$2:$A$498, $A29, 'GE16FEB14 Unfudged'!$D$2:$D$498) -> 3199 | F29: =+SUMIF('GE16FEB14 Unfudged'!$A$2:$A$498, 'Tax Bill Summary'!$A29, 'GE16FEB14 Unfudged'!E$2:E$498) -> 491056 | G29: =+SUMIF('GE16FEB14 Unfudged'!$A$2:$A$498, 'Tax Bill Summary'!$A29, 'GE16FEB14 Unfudged'!F$2:F$498) -> 338747 | H29: =+F29-G29 -> 152309 | I29: =+SUMIF('GE16FEB14 Unfudged'!$A$2:$A$498, 'Tax Bill Summary'!$A29, 'GE16FEB14 Unfudged'!G$2:G$498) -> 1356206 | J29: =+SUMIF('GE16FEB14 Unfudged'!$A$2:$A$498, 'Tax Bill Summary'!$A29, 'GE16FEB14 Unfudged'!H$2:H$498) -> 935555 | K29: =+I29-J29 -> 420651 | L29: =+SUMIF('GE16FEB14 Unfudged'!$A$2:$A$498, 'Tax Bill Summary'!$A29, 'GE16FEB14 Unfudged'!I$2:IF$498) -> 1542013 | M29: =+SUMIF('GE16FEB14 Unfudged'!$A$2:$A$498, 'Tax Bill Summary'!$A29, 'GE16FEB14 Unfudged'!J$2:IG$498) -> 785411 | N29: =+L29-M29 -> 756602 | O29: =+F29+I29+L29 -> 3389275 | P29: =+G29+J29+M29 -> 2059713 | Q29: =+H29+K29+N29 -> 1329562 | R29: =+IF($E29=0, 0, O29/$E29) -> 1059.4795 | S29: =+IF($E29=0, 0, P29/$E29) -> 643.86152 | T29: =+IF($E29=0, 0, Q29/$E29) -> 415.61801 | U29: =+SUMIF('GE16FEB14 Tax Bill Unfudged'!$A$2:$A$498, 'Tax Bill Summary'!$A29, 'GE16FEB14 Tax Bill Unfudged'!E$2:E$498) -> 491056 | V29: =+SUMIF('GE16FEB14 Tax Bill Unfudged'!$A$2:$A$498, 'Tax Bill Summary'!$A29, 'GE16FEB14 Tax Bill Unfudged'!F$2:F$498) -> 338747 | W29: =+U29-V29 -> 152309 | X29: =+SUMIF('GE16FEB14 Tax Bill Unfudged'!$A$2:$A$498, 'Tax Bill Summary'!$A29, 'GE16FEB14 Tax Bill Unfudged'!G$2:G$498) -> 1356206 | Y29: =+SUMIF('GE16FEB14 Tax Bill Unfudged'!$A$2:$A$498, 'Tax Bill Summary'!$A29, 'GE16FEB14 Tax Bill Unfudged'!H$2:H$498) -> 935555 | Z29: =+X29-Y29 -> 420651 | AA29: =+SUMIF('GE16FEB14 Tax Bill Unfudged'!$A$2:$A$498, 'Tax Bill Summary'!$A29, 'GE16FEB14 Tax Bill Unfudged'!I$2:I$498) -> 1542013 | AB29: =+SUMIF('GE16FEB14 Tax Bill Unfudged'!$A$2:$A$498, 'Tax Bill Summary'!$A29, 'GE16FEB14 Tax Bill Unfudged'!J$2:J$498) -> 785411 | AC29: =+AA29-AB29 -> 756602 | AD29: =+U29+X29+AA29 -> 3389275 | AE29: =+V29+Y29+AB29 -> 2059713 | AF29: =+W29+Z29+AC29 -> 1329562 | AG29: =+IF($E29=0, 0, AD29/$E29) -> 1059.4795 | AH29: =+IF($E29=0, 0, AE29/$E29) -> 643.86152 | AI29: =+IF($E29=0, 0, AF29/$E29) -> 415.61801 | AJ29: =+U29-F29 -> 0 | AK29: =+V29-G29 -> 0 | AL29: =+W29-H29 -> 0 | AM29: =+X29-I29 -> 0 | AN29: =+Y29-J29 -> 0 | AO29: =+Z29-K29 -> 0 | AP29: =+AA29-L29 -> 0 | AQ29: =+AB29-M29 -> 0 | ... AX29: =+AI29-T29 -> 0
A30: 15 | B30: 1 | C30: ST. FRANCIS | D30: 3 | E30: =+SUMIF('GE16FEB14 Unfudged'!$A$2:$A$498, $A30, 'GE16FEB14 Unfudged'!$D$2:$D$498) -> 4887 | F30: =+SUMIF('GE16FEB14 Unfudged'!$A$2:$A$498, 'Tax Bill Summary'!$A30, 'GE16FEB14 Unfudged'!E$2:E$498) -> 818573 | G30: =+SUMIF('GE16FEB14 Unfudged'!$A$2:$A$498, 'Tax Bill Summary'!$A30, 'GE16FEB14 Unfudged'!F$2:F$498) -> 601361 | H30: =+F30-G30 -> 217212 | I30: =+SUMIF('GE16FEB14 Unfudged'!$A$2:$A$498, 'Tax Bill Summary'!$A30, 'GE16FEB14 Unfudged'!G$2:G$498) -> 2072088 | J30: =+SUMIF('GE16FEB14 Unfudged'!$A$2:$A$498, 'Tax Bill Summary'!$A30, 'GE16FEB14 Unfudged'!H$2:H$498) -> 1522250 | K30: =+I30-J30 -> 549838 | L30: =+SUMIF('GE16FEB14 Unfudged'!$A$2:$A$498, 'Tax Bill Summary'!$A30, 'GE16FEB14 Unfudged'!I$2:IF$498) -> 1466100 | M30: =+SUMIF('GE16FEB14 Unfudged'!$A$2:$A$498, 'Tax Bill Summary'!$A30, 'GE16FEB14 Unfudged'!J$2:IG$498) -> 624207 | N30: =+L30-M30 -> 841893 | O30: =+F30+I30+L30 -> 4356761 | P30: =+G30+J30+M30 -> 2747818 | Q30: =+H30+K30+N30 -> 1608943 | R30: =+IF($E30=0, 0, O30/$E30) -> 891.5001 | S30: =+IF($E30=0, 0, P30/$E30) -> 562.27092 | T30: =+IF($E30=0, 0, Q30/$E30) -> 329.22918 | U30: =+SUMIF('GE16FEB14 Tax Bill Unfudged'!$A$2:$A$498, 'Tax Bill Summary'!$A30, 'GE16FEB14 Tax Bill Unfudged'!E$2:E$498) -> 818573 | V30: =+SUMIF('GE16FEB14 Tax Bill Unfudged'!$A$2:$A$498, 'Tax Bill Summary'!$A30, 'GE16FEB14 Tax Bill Unfudged'!F$2:F$498) -> 601361 | W30: =+U30-V30 -> 217212 | X30: =+SUMIF('GE16FEB14 Tax Bill Unfudged'!$A$2:$A$498, 'Tax Bill Summary'!$A30, 'GE16FEB14 Tax Bill Unfudged'!G$2:G$498) -> 2072088 | Y30: =+SUMIF('GE16FEB14 Tax Bill Unfudged'!$A$2:$A$498, 'Tax Bill Summary'!$A30, 'GE16FEB14 Tax Bill Unfudged'!H$2:H$498) -> 1522250 | Z30: =+X30-Y30 -> 549838 | AA30: =+SUMIF('GE16FEB14 Tax Bill Unfudged'!$A$2:$A$498, 'Tax Bill Summary'!$A30, 'GE16FEB14 Tax Bill Unfudged'!I$2:I$498) -> 1466100 | AB30: =+SUMIF('GE16FEB14 Tax Bill Unfudged'!$A$2:$A$498, 'Tax Bill Summary'!$A30, 'GE16FEB14 Tax Bill Unfudged'!J$2:J$498) -> 624207 | AC30: =+AA30-AB30 -> 841893 | AD30: =+U30+X30+AA30 -> 4356761 | AE30: =+V30+Y30+AB30 -> 2747818 | AF30: =+W30+Z30+AC30 -> 1608943 | AG30: =+IF($E30=0, 0, AD30/$E30) -> 891.5001 | AH30: =+IF($E30=0, 0, AE30/$E30) -> 562.27092 | AI30: =+IF($E30=0, 0, AF30/$E30) -> 329.22918 | AJ30: =+U30-F30 -> 0 | AK30: =+V30-G30 -> 0 | AL30: =+W30-H30 -> 0 | AM30: =+X30-I30 -> 0 | AN30: =+Y30-J30 -> 0 | AO30: =+Z30-K30 -> 0 | AP30: =+AA30-L30 -> 0 | AQ30: =+AB30-M30 -> 0 | ... AX30: =+AI30-T30 -> 0
A31: 16 | B31: 1 | C31: SPRING LAKE PARK | D31: 3 | E31: =+SUMIF('GE16FEB14 Unfudged'!$A$2:$A$498, $A31, 'GE16FEB14 Unfudged'!$D$2:$D$498) -> 5870 | F31: =+SUMIF('GE16FEB14 Unfudged'!$A$2:$A$498, 'Tax Bill Summary'!$A31, 'GE16FEB14 Unfudged'!E$2:E$498) -> 922757 | G31: =+SUMIF('GE16FEB14 Unfudged'!$A$2:$A$498, 'Tax Bill Summary'!$A31, 'GE16FEB14 Unfudged'!F$2:F$498) -> 898386 | H31: =+F31-G31 -> 24371 | I31: =+SUMIF('GE16FEB14 Unfudged'!$A$2:$A$498, 'Tax Bill Summary'!$A31, 'GE16FEB14 Unfudged'!G$2:G$498) -> 2488689 | J31: =+SUMIF('GE16FEB14 Unfudged'!$A$2:$A$498, 'Tax Bill Summary'!$A31, 'GE16FEB14 Unfudged'!H$2:H$498) -> 2422960 | K31: =+I31-J31 -> 65729 | L31: =+SUMIF('GE16FEB14 Unfudged'!$A$2:$A$498, 'Tax Bill Summary'!$A31, 'GE16FEB14 Unfudged'!I$2:IF$498) -> 2547619 | M31: =+SUMIF('GE16FEB14 Unfudged'!$A$2:$A$498, 'Tax Bill Summary'!$A31, 'GE16FEB14 Unfudged'!J$2:IG$498) -> 1759524 | N31: =+L31-M31 -> 788095 | O31: =+F31+I31+L31 -> 5959065 | P31: =+G31+J31+M31 -> 5080870 | Q31: =+H31+K31+N31 -> 878195 | R31: =+IF($E31=0, 0, O31/$E31) -> 1015.1729 | S31: =+IF($E31=0, 0, P31/$E31) -> 865.56559 | T31: =+IF($E31=0, 0, Q31/$E31) -> 149.60733 | U31: =+SUMIF('GE16FEB14 Tax Bill Unfudged'!$A$2:$A$498, 'Tax Bill Summary'!$A31, 'GE16FEB14 Tax Bill Unfudged'!E$2:E$498) -> 922757 | V31: =+SUMIF('GE16FEB14 Tax Bill Unfudged'!$A$2:$A$498, 'Tax Bill Summary'!$A31, 'GE16FEB14 Tax Bill Unfudged'!F$2:F$498) -> 898386 | W31: =+U31-V31 -> 24371 | X31: =+SUMIF('GE16FEB14 Tax Bill Unfudged'!$A$2:$A$498, 'Tax Bill Summary'!$A31, 'GE16FEB14 Tax Bill Unfudged'!G$2:G$498) -> 2488689 | Y31: =+SUMIF('GE16FEB14 Tax Bill Unfudged'!$A$2:$A$498, 'Tax Bill Summary'!$A31, 'GE16FEB14 Tax Bill Unfudged'!H$2:H$498) -> 2422960 | Z31: =+X31-Y31 -> 65729 | AA31: =+SUMIF('GE16FEB14 Tax Bill Unfudged'!$A$2:$A$498, 'Tax Bill Summary'!$A31, 'GE16FEB14 Tax Bill Unfudged'!I$2:I$498) -> 2547619 | AB31: =+SUMIF('GE16FEB14 Tax Bill Unfudged'!$A$2:$A$498, 'Tax Bill Summary'!$A31, 'GE16FEB14 Tax Bill Unfudged'!J$2:J$498) -> 1759524 | AC31: =+AA31-AB31 -> 788095 | AD31: =+U31+X31+AA31 -> 5959065 | AE31: =+V31+Y31+AB31 -> 5080870 | AF31: =+W31+Z31+AC31 -> 878195 | AG31: =+IF($E31=0, 0, AD31/$E31) -> 1015.1729 | AH31: =+IF($E31=0, 0, AE31/$E31) -> 865.56559 | AI31: =+IF($E31=0, 0, AF31/$E31) -> 149.60733 | AJ31: =+U31-F31 -> 0 | AK31: =+V31-G31 -> 0 | AL31: =+W31-H31 -> 0 | AM31: =+X31-I31 -> 0 | AN31: =+Y31-J31 -> 0 | AO31: =+Z31-K31 -> 0 | AP31: =+AA31-L31 -> 0 | AQ31: =+AB31-M31 -> 0 | ... AX31: =+AI31-T31 -> 0
A32: 22 | B32: 1 | C32: DETROIT LAKES | D32: 4 | E32: =+SUMIF('GE16FEB14 Unfudged'!$A$2:$A$498, $A32, 'GE16FEB14 Unfudged'!$D$2:$D$498) -> 3112 | F32: =+SUMIF('GE16FEB14 Unfudged'!$A$2:$A$498, 'Tax Bill Summary'!$A32, 'GE16FEB14 Unfudged'!E$2:E$498) -> 448128 | G32: =+SUMIF('GE16FEB14 Unfudged'!$A$2:$A$498, 'Tax Bill Summary'!$A32, 'GE16FEB14 Unfudged'!F$2:F$498) -> 396125 | H32: =+F32-G32 -> 52003 | I32: =+SUMIF('GE16FEB14 Unfudged'!$A$2:$A$498, 'Tax Bill Summary'!$A32, 'GE16FEB14 Unfudged'!G$2:G$498) -> 659744 | J32: =+SUMIF('GE16FEB14 Unfudged'!$A$2:$A$498, 'Tax Bill Summary'!$A32, 'GE16FEB14 Unfudged'!H$2:H$498) -> 583184 | K32: =+I32-J32 -> 76560 | L32: =+SUMIF('GE16FEB14 Unfudged'!$A$2:$A$498, 'Tax Bill Summary'!$A32, 'GE16FEB14 Unfudged'!I$2:IF$498) -> 933600 | M32: =+SUMIF('GE16FEB14 Unfudged'!$A$2:$A$498, 'Tax Bill Summary'!$A32, 'GE16FEB14 Unfudged'!J$2:IG$498) -> 478276 | N32: =+L32-M32 -> 455324 | O32: =+F32+I32+L32 -> 2041472 | P32: =+G32+J32+M32 -> 1457585 | Q32: =+H32+K32+N32 -> 583887 | R32: =+IF($E32=0, 0, O32/$E32) -> 656 | S32: =+IF($E32=0, 0, P32/$E32) -> 468.37564 | T32: =+IF($E32=0, 0, Q32/$E32) -> 187.62436 | U32: =+SUMIF('GE16FEB14 Tax Bill Unfudged'!$A$2:$A$498, 'Tax Bill Summary'!$A32, 'GE16FEB14 Tax Bill Unfudged'!E$2:E$498) -> 448128 | V32: =+SUMIF('GE16FEB14 Tax Bill Unfudged'!$A$2:$A$498, 'Tax Bill Summary'!$A32, 'GE16FEB14 Tax Bill Unfudged'!F$2:F$498) -> 396125 | W32: =+U32-V32 -> 52003 | X32: =+SUMIF('GE16FEB14 Tax Bill Unfudged'!$A$2:$A$498, 'Tax Bill Summary'!$A32, 'GE16FEB14 Tax Bill Unfudged'!G$2:G$498) -> 1319488 | Y32: =+SUMIF('GE16FEB14 Tax Bill Unfudged'!$A$2:$A$498, 'Tax Bill Summary'!$A32, 'GE16FEB14 Tax Bill Unfudged'!H$2:H$498) -> 1166368 | Z32: =+X32-Y32 -> 153120 | AA32: =+SUMIF('GE16FEB14 Tax Bill Unfudged'!$A$2:$A$498, 'Tax Bill Summary'!$A32, 'GE16FEB14 Tax Bill Unfudged'!I$2:I$498) -> 933600 | AB32: =+SUMIF('GE16FEB14 Tax Bill Unfudged'!$A$2:$A$498, 'Tax Bill Summary'!$A32, 'GE16FEB14 Tax Bill Unfudged'!J$2:J$498) -> 478276 | AC32: =+AA32-AB32 -> 455324 | AD32: =+U32+X32+AA32 -> 2701216 | AE32: =+V32+Y32+AB32 -> 2040769 | AF32: =+W32+Z32+AC32 -> 660447 | AG32: =+IF($E32=0, 0, AD32/$E32) -> 868 | AH32: =+IF($E32=0, 0, AE32/$E32) -> 655.7741 | AI32: =+IF($E32=0, 0, AF32/$E32) -> 212.2259 | AJ32: =+U32-F32 -> 0 | AK32: =+V32-G32 -> 0 | AL32: =+W32-H32 -> 0 | AM32: =+X32-I32 -> 659744 | AN32: =+Y32-J32 -> 583184 | AO32: =+Z32-K32 -> 76560 | AP32: =+AA32-L32 -> 0 | AQ32: =+AB32-M32 -> 0 | ... AX32: =+AI32-T32 -> 24.601542
... A517: 6000 | B517: 7 | C517: COOPERATIVE & INTERMED DISTRICTS | D517: 24 | E517: =+SUMIF('GE16FEB14 Unfudged'!$A$2:$A$498, $A517, 'GE16FEB14 Unfudged'!$D$2:$D$498) -> 0 | F517: =+SUMIF('GE16FEB14 Unfudged'!$A$2:$A$498, 'Tax Bill Summary'!$A517, 'GE16FEB14 Unfudged'!E$2:E$498) -> 0 | G517: =+SUMIF('GE16FEB14 Unfudged'!$A$2:$A$498, 'Tax Bill Summary'!$A517, 'GE16FEB14 Unfudged'!F$2:F$498) -> 0 | H517: =+F517-G517 -> 0 | I517: =+SUMIF('GE16FEB14 Unfudged'!$A$2:$A$498, 'Tax Bill Summary'!$A517, 'GE16FEB14 Unfudged'!G$2:G$498) -> 0 | J517: =+SUMIF('GE16FEB14 Unfudged'!$A$2:$A$498, 'Tax Bill Summary'!$A517, 'GE16FEB14 Unfudged'!H$2:H$498) -> 0 | K517: =+I517-J517 -> 0 | L517: =+SUMIF('GE16FEB14 Unfudged'!$A$2:$A$498, 'Tax Bill Summary'!$A517, 'GE16FEB14 Unfudged'!I$2:IF$498) -> 0 | M517: =+SUMIF('GE16FEB14 Unfudged'!$A$2:$A$498, 'Tax Bill Summary'!$A517, 'GE16FEB14 Unfudged'!J$2:IG$498) -> 0 | N517: =+L517-M517 -> 0 | O517: =+F517+I517+L517 -> 0 | P517: =+G517+J517+M517 -> 0 | Q517: =+H517+K517+N517 -> 0 | R517: =+IF($E517=0, 0, O517/$E517) -> 0 | S517: =+IF($E517=0, 0, P517/$E517) -> 0 | T517: =+IF($E517=0, 0, Q517/$E517) -> 0 | U517: =+SUMIF('GE16FEB14 Tax Bill Unfudged'!$A$2:$A$498, 'Tax Bill Summary'!$A517, 'GE16FEB14 Tax Bill Unfudged'!E$2:E$498) -> 0 | V517: =+SUMIF('GE16FEB14 Tax Bill Unfudged'!$A$2:$A$498, 'Tax Bill Summary'!$A517, 'GE16FEB14 Tax Bill Unfudged'!F$2:F$498) -> 0 | W517: =+U517-V517 -> 0 | X517: =+SUMIF('GE16FEB14 Tax Bill Unfudged'!$A$2:$A$498, 'Tax Bill Summary'!$A517, 'GE16FEB14 Tax Bill Unfudged'!G$2:G$498) -> 0 | Y517: =+SUMIF('GE16FEB14 Tax Bill Unfudged'!$A$2:$A$498, 'Tax Bill Summary'!$A517, 'GE16FEB14 Tax Bill Unfudged'!H$2:H$498) -> 0 | Z517: =+X517-Y517 -> 0 | AA517: =+SUMIF('GE16FEB14 Tax Bill Unfudged'!$A$2:$A$498, 'Tax Bill Summary'!$A517, 'GE16FEB14 Tax Bill Unfudged'!I$2:I$498) -> 0 | AB517: =+SUMIF('GE16FEB14 Tax Bill Unfudged'!$A$2:$A$498, 'Tax Bill Summary'!$A517, 'GE16FEB14 Tax Bill Unfudged'!J$2:J$498) -> 0 | AC517: =+AA517-AB517 -> 0 | AD517: =+U517+X517+AA517 -> 0 | AE517: =+V517+Y517+AB517 -> 0 | AF517: =+W517+Z517+AC517 -> 0 | AG517: =+IF($E517=0, 0, AD517/$E517) -> 0 | AH517: =+IF($E517=0, 0, AE517/$E517) -> 0 | AI517: =+IF($E517=0, 0, AF517/$E517) -> 0 | AJ517: =+U517-F517 -> 0 | AK517: =+V517-G517 -> 0 | AL517: =+W517-H517 -> 0 | AM517: =+X517-I517 -> 0 | AN517: =+Y517-J517 -> 0 | AO517: =+Z517-K517 -> 0 | AP517: =+AA517-L517 -> 0 | AQ517: =+AB517-M517 -> 0 | ... AX517: =+AI517-T517 -> 0

Sheet GE16FEB14 Unfudged
A1: DIST | B1: TYPE | C1: NAME | D1: AADM16N | E1: EQREV16N | F1: EQLVY16N | G1: LOCREV16N | H1: LOCLVY16N | I1: REFREV16N | J1: RFLVYN16N
A2: 1 | B2: 1 | C2: AITKIN | D2: 1285 | E2: 185040 | F2: 185040 | G2: 0 | H2: 0 | I2: 385500 | J2: 260672
A3: 1.2 | B3: 3 | C3: MINNEAPOLIS | D3: 39607 | E3: 1980330 | F3: 1980330 | G3: 16793198 | H3: 16793198 | I3: 55978780 | J3: 52894542
A4: 2 | B4: 1 | C4: HILL CITY | D4: 284 | E4: 40889 | F4: 22793 | G4: 0 | H4: 0 | I4: 85185 | J4: 27520
A5: 4 | B5: 1 | C5: MCGREGOR | D5: 434 | E5: 62554 | F5: 62554 | G5: 0 | H5: 0 | I5: 130320 | J5: 77314
A6: 6 | B6: 3 | C6: SOUTH ST. PAUL | D6: 3736 | E6: 557934 | F6: 396251 | G6: 1584234 | H6: 1125142 | I6: 2005625 | J6: 1089699
A7: 11 | B7: 1 | C7: ANOKA-HENNEPIN | D7: 39798 | E7: 4558334 | F7: 3244342 | G7: 16874267 | H7: 12010067 | I7: 39397832 | J7: 27106091
A8: 12 | B8: 1 | C8: CENTENNIAL | D8: 6971 | E8: 1079123 | F8: 838445 | G8: 2955789 | H8: 2296557 | I8: 3244954 | J8: 1838023
A9: 13 | B9: 1 | C9: COLUMBIA HEIGHTS | D9: 3362 | E9: 483364 | F9: 360094 | G9: 1425361 | H9: 1061860 | I9: 2047040 | J9: 1209102
A10: 14 | B10: 1 | C10: FRIDLEY | D10: 3199 | E10: 491056 | F10: 338747 | G10: 1356206 | H10: 935555 | I10: 1542013 | J10: 785411
A11: 15 | B11: 1 | C11: ST. FRANCIS | D11: 4887 | E11: 818573 | F11: 601361 | G11: 2072088 | H11: 1522250 | I11: 1466100 | J11: 624207
A12: 16 | B12: 1 | C12: SPRING LAKE PARK | D12: 5870 | E12: 922757 | F12: 898386 | G12: 2488689 | H12: 2422960 | I12: 2547619 | J12: 1759524
A13: 22 | B13: 1 | C13: DETROIT LAKES | D13: 3112 | E13: 448128 | F13: 396125 | G13: 659744 | H13: 583184 | I13: 933600 | J13: 478276
... A498: 6000 | B498: 62 | C498: COOPERATIVE & INTERMED DISTRICTS | D498: 0 | E498: 0 | F498: 0 | G498: 0 | H498: 0 | I498: 0 | J498: 0
D500: =SUM(D2:D499) -> 921112 | E500: =SUM(E2:E499) -> 106775552 | F500: =SUM(F2:F499) -> 78879395 | G500: =SUM(G2:G499) -> 245125421 | H500: =SUM(H2:H499) -> 207462464 | I500: =SUM(I2:I499) -> 781257518 | J500: =SUM(J2:J499) -> 597059968
D501: =+'Tax Bill Summary'!E9 -> 921112 | E501: =+'Tax Bill Summary'!F9 -> 106775552 | F501: =+'Tax Bill Summary'!G9 -> 78879395 | G501: =+'Tax Bill Summary'!I9 -> 245125421 | H501: =+'Tax Bill Summary'!J9 -> 207462464 | I501: =+'Tax Bill Summary'!L9 -> 781257518 | J501: =+'Tax Bill Summary'!M9 -> 597059968
D502: =+D500-D501 -> 0 | E502: =+E500-E501 -> 0 | F502: =+F500-F501 -> 0 | G502: =+G500-G501 -> 0 | H502: =+H500-H501 -> 0 | I502: =+I500-I501 -> 0 | J502: =+J500-J501 -> 0

Sheet GE16FEB14 Tax Bill Unfudged
A1: DIST | B1: TYPE | C1: NAME | D1: AADM16N | E1: EQREV16N | F1: EQLVY16N | G1: LOCREV16N | H1: LOCLVY16N | I1: REFREV16N | J1: RFLVYN16N
A2: 1 | B2: 1 | C2: AITKIN | D2: 1285 | E2: 185040 | F2: 185040 | G2: 544840 | H2: 544840 | I2: 385500 | J2: 260672
A3: 1.2 | B3: 3 | C3: MINNEAPOLIS | D3: 39607 | E3: 1980330 | F3: 1980330 | G3: 16793198 | H3: 16793198 | I3: 55978780 | J3: 52894542
A4: 2 | B4: 1 | C4: HILL CITY | D4: 284 | E4: 40889 | F4: 22793 | G4: 120395 | H4: 67113 | I4: 85185 | J4: 27520
A5: 4 | B5: 1 | C5: MCGREGOR | D5: 434 | E5: 62554 | F5: 62554 | G5: 184186 | H5: 184186 | I5: 130320 | J5: 77314
A6: 6 | B6: 3 | C6: SOUTH ST. PAUL | D6: 3736 | E6: 557934 | F6: 396251 | G6: 1584234 | H6: 1125142 | I6: 2005625 | J6: 1089699
A7: 11 | B7: 1 | C7: ANOKA-HENNEPIN | D7: 39798 | E7: 4558334 | F7: 3244342 | G7: 16874267 | H7: 12010067 | I7: 39397832 | J7: 27106091
A8: 12 | B8: 1 | C8: CENTENNIAL | D8: 6971 | E8: 1079123 | F8: 838445 | G8: 2955789 | H8: 2296557 | I8: 3244954 | J8: 1838023
A9: 13 | B9: 1 | C9: COLUMBIA HEIGHTS | D9: 3362 | E9: 483364 | F9: 360094 | G9: 1425361 | H9: 1061860 | I9: 2047040 | J9: 1209102
A10: 14 | B10: 1 | C10: FRIDLEY | D10: 3199 | E10: 491056 | F10: 338747 | G10: 1356206 | H10: 935555 | I10: 1542013 | J10: 785411
A11: 15 | B11: 1 | C11: ST. FRANCIS | D11: 4887 | E11: 818573 | F11: 601361 | G11: 2072088 | H11: 1522250 | I11: 1466100 | J11: 624207
A12: 16 | B12: 1 | C12: SPRING LAKE PARK | D12: 5870 | E12: 922757 | F12: 898386 | G12: 2488689 | H12: 2422960 | I12: 2547619 | J12: 1759524
A13: 22 | B13: 1 | C13: DETROIT LAKES | D13: 3112 | E13: 448128 | F13: 396125 | G13: 1319488 | H13: 1166368 | I13: 933600 | J13: 478276
... A498: 6000 | B498: 62 | C498: COOPERATIVE & INTERMED DISTRICTS | D498: 0 | E498: 0 | F498: 0 | G498: 0 | H498: 0 | I498: 0 | J498: 0
D500: =SUM(D2:D499) -> 921112 | E500: =SUM(E2:E499) -> 109031619 | F500: =SUM(F2:F499) -> 80189429 | G500: =SUM(G2:G499) -> 358810201 | H500: =SUM(H2:H499) -> 285015473 | I500: =SUM(I2:I499) -> 709804912 | J500: =SUM(J2:J499) -> 541519918
D501: =+'Tax Bill Summary'!E9 -> 921112 | E501: =+'Tax Bill Summary'!U9 -> 109031619 | F501: =+'Tax Bill Summary'!V9 -> 80189429 | G501: =+'Tax Bill Summary'!X9 -> 358810201 | H501: =+'Tax Bill Summary'!Y9 -> 285015473 | I501: =+'Tax Bill Summary'!AA9 -> 709804912 | J501: =+'Tax Bill Summary'!AB9 -> 541519918
D502: =+D500-D501 -> 0 | E502: =+E500-E501 -> 0 | F502: =+F500-F501 -> 0 | G502: =+G500-G501 -> 0 | H502: =+H500-H501 -> 0 | I502: =+I500-I501 -> 0 | J502: =+J500-J501 -> 0
