Workbook
Name Bureaus: 'Lookup Values'!$H$3:$I$32
Name Crosswalk: 'Lookup Values'!$A$3:$C$97
Name Funds: 'Lookup Values'!$E$3:$F$91
Name FY2008_09: '$ FY 2008-09'!$A$2:$J$78
Name FY2008_09P: 'Pos FY 2008-09'!$A$2:$F$40
Name FY2009_10: '$ FY 2009-10'!$A$2:$J$80
Name FY2009_10P: 'Pos FY 2009-10'!$A$2:$F$42
Name FY2010_11: '$ FY 2010-11'!$A$2:$J$83
Name FY2010_11P: 'Pos FY 2010-11'!$A$2:$F$42
Name FY2011_12: '$ FY 2011-12'!$A$2:$J$81
Name FY2011_12P: 'Pos FY 2011-12'!$A$2:$F$41
Name FY2012_13: '$ FY 2012-13'!$A$2:$J$80
Name FY2012_13P: 'Pos FY 2012-13'!$A$2:$F$42
Name Model: Model!$A$2:$B$92

Sheet Cost Pool
B1: FY 2012-13 | D1: FY 2014-15
B2: CAL Target | C2: True-Up | D2: CAL Target | E2: Notes
A3: 100-AT | C3: 3896819 | D3: =2407924+2807419 -> 5215343
A4: 100-AU | C4: 7331204 | D4: =3857204+4497147 -> 8354351
A5: 100-BO | C5: 547957 | D5: =906446+1056834 -> 1963280
A6: 100-EM | C6: 1547205 | D6: =934412+1089439 -> 2023851
A7: 100-FR | C7: 118183 | D7: =ROUND((126895*1.025),0) -> 130067 | E7: Emergency mgmt (FREO000004 Fund Center)
A8: 100-GR | C8: 1153236 | D8: =489067+570207 -> 1059274
A9: 100-MF | C9: =6331726+3948799+7738854 -> 18019379 | D9: =3877845+2472450+2282739+4521212+2882650+2661465 -> 18698361 | E9: MFDR, MFIB, MFHR
A10: 100-MY | C10: 1426760 | D10: =880777+1026906 -> 1907683
A11: 100-NI | C11: =276487+99995 -> 376482 | D11: =ROUND(((540500+114494)*1.025),0) -> 671369 | E11: Information & Referral and Public Involvement best practices (CDIR, CDNRNOPI)
A12: 100-OE | C12: =1147492*0.68 -> 780294.56 | D12: =ROUND(((180733+131362+235337+325007)*1.025),0) -> 894250 | E12: Citywide Comm, Training, Tech Support and % admin (CDCEEC, TE, TS & 68% of CDAS)
A13: 100-PA | C13: 1216601 | D13: =427690+498647 -> 926337 | E13: Commissioner's Office (PACO000001)
A14: 100-PN | C14: =982037+889207 -> 1871244 | D14: =ROUND(((0.5*(68428+544977)+758163)*1.025),0) -> 1091487 | E14: Comp Planning & 1/2 of district liaisons (CDAPDI, CDCP00)
A15: 100-PS | C15: 650735 | D15: =427690+498647 -> 926337
A16: 100-PU | C16: 692124 | D16: =427690+498647 -> 926337
A17: 100-PW | C17: 770804 | D17: =427690+498647 -> 926337
A18: 100-SA | C18: 274049 | D18: =134087+156333 -> 290420 | E18: City memberships and dues (MFSA000002)
A19: Total Cost Pool | B19: 44611991 | C19: =SUM(C3:C18) -> 40673077 | D19: =SUM(D3:D18) -> 46005084
A20: Portland Children's Levy Allocation | B20: -25000 | C20: -25000 | D20: -25000
A21: Property Management License | B21: -25000 | C21: -25000 | D21: -25000
A22: Cable Fund | B22: -25000 | C22: -25000 | D22: -25000
A23: Arts Education & Access Fund | B23: -25000 | C23: -25000 | D23: -25000
A24: Convention & Tourism | B24: -25000 | C24: -25000 | D24: -25000
A25: Cost Pool to Allocate | B25: =SUM(B19:B24) -> 44486991 | C25: =SUM(C19:C24) -> 40548077 | D25: =SUM(D19:D24) -> 45880084

Sheet Charges
A1: FY 2014-15 General Fund Overhead
A4: Fund | B4: FY 2013-14 CAL Charge | C4: Difference | D4: FY 2014-15 CAL Charge | E4: FY 2012-13 True-Up | F4: FY 2014-15 Total Charge
A5: 100 - General Fund | B5: 19855263 | C5: 1385103 | D5: 21240366 | E5: 600980 | F5: 21841346
A6: 200 - Transportation Operating Fund | B6: 6564665 | C6: -508470 | D6: 6056195 | E6: -450673 | F6: 5605522
A7: 201 - Assessment Collection Fund | B7: 12 | C7: -12 | D7: 0 | E7: -14 | F7: -14
A8: 202 - Emergency Communication Fund | B8: 877412 | C8: -127411 | D8: 750001 | E8: -93155 | F8: 656846
A9: 203 - Development Services Fund | B9: 1044982 | C9: -65065 | D9: 979917 | E9: 46474 | F9: 1026391
A10: 204 - Property Management License Fund | B10: 0 | C10: 25000 | D10: 25000 | E10: 0 | F10: 25000
A11: 206 - MHCRC Agency Fund | B11: 0 | C11: 25000 | D11: 25000 | E11: 0 | F11: 25000
A12: 209 - Convention and Tourism Fund | B12: 56826 | C12: -31826 | D12: 25000 | E12: 0 | F12: 25000
A13: 213 - Housing Investment Fund | B13: 218979 | C13: -130730 | D13: 88249 | E13: 35960 | F13: 124209
A14: 215 - Parks Local Option Levy Fund | B14: 9633 | C14: 4601 | D14: 14234 | E14: 34000 | F14: 48234
A15: 216 - Children's Investment Fund | B15: 25000 | C15: 0 | D15: 25000 | E15: 0 | F15: 25000
A16: 221 - Tax Increment Financing Reimbursement Fund | B16: 835994 | C16: -92863 | D16: 743131 | E16: -279718 | F16: 463413
... A42: Grand Total | B42: 47391244 | C42: -1386158 | D42: 46005086 | E42: -2483580 | F42: 43521506
C44: Recovery Rate | D44: =1-(GETPIVOTDATA(" FY 2014-15 CAL Charge",$A$3,"Fund","100 - General Fund")/GETPIVOTDATA(" FY 2014-15 CAL Charge",$A$3)) -> 0.53830396

Sheet Model
A1: Allocated Fund | B1: Billed Fund | C1: Fund | D1: Bureau | E1: FY 2008-09 Actuals | F1: FY 2009-10 Actuals | G1: FY 2010-11 Actuals | H1: FY 2011-12 Actuals | I1: FY 2012-13 Actuals | J1: FY 2008-09 Positions | K1: FY 2009-10 Positions | L1: FY 2010-11 Positions | M1: FY 2011-12 Positions | N1: FY 2012-13 Positions | O1: CAL Weighted % | P1: True-Up Weighted % | Q1: FY 2012-13 CAL Charge | R1: FY 2012-13 True-Up | S1: FY 2012-13 True-Up Charge | T1: FY 2013-14 CAL Charge | U1: Difference | V1: FY 2014-15 CAL Charge | W1: FY 2014-15 with True-Up
A2: 100-AT | B2: =VLOOKUP(A2,Crosswalk,2,FALSE) -> 100-AT | C2: =CONCATENATE((LEFT(B2,3))," - ",(VLOOKUP((LEFT(B2,3)),Funds,2,FALSE))) -> 100 - General Fund | D2: =VLOOKUP((RIGHT(B2,2)),Bureaus,2,FALSE) -> Office of the City Attorney | E2: =IF(B2="Excluded",0,(IF(ISNA(VLOOKUP(A2,FY2008_09,10,FALSE)),0,(VLOOKUP(A2,FY2008_09,10,FALSE))))) -> 0 | F2: =IF(B2="Excluded",0,(IF(ISNA(VLOOKUP(A2,FY2009_10,10,FALSE)),0,(VLOOKUP(A2,FY2009_10,10,FALSE))))) -> 0 | G2: =IF(B2="Excluded",0,(IF(ISNA(VLOOKUP(A2,FY2010_11,10,FALSE)),0,(VLOOKUP(A2,FY2010_11,10,FALSE))))) -> 0 | H2: =IF(B2="Excluded",0,(IF(ISNA(VLOOKUP(A2,FY2011_12,10,FALSE)),0,(VLOOKUP(A2,FY2011_12,10,FALSE))))) -> 0 | I2: =IF(B2="Excluded",0,(IF(ISNA(VLOOKUP(A2,FY2012_13,10,FALSE)),0,(VLOOKUP(A2,FY2012_13,10,FALSE))))) -> 0 | J2: =IF(B2="Excluded",0,(IF(ISNA(VLOOKUP(A2,FY2008_09P,6,FALSE)),0,(VLOOKUP(A2,FY2008_09P,6,FALSE))))) -> 0 | K2: =IF(B2="Excluded",0,(IF(ISNA(VLOOKUP(A2,FY2009_10P,6,FALSE)),0,(VLOOKUP(A2,FY2009_10P,6,FALSE))))) -> 0 | L2: =IF(B2="Excluded",0,(IF(ISNA(VLOOKUP(A2,FY2010_11P,6,FALSE)),0,(VLOOKUP(A2,FY2010_11P,6,FALSE))))) -> 0 | M2: =IF(B2="Excluded",0,(IF(ISNA(VLOOKUP(A2,FY2011_12P,6,FALSE)),0,(VLOOKUP(A2,FY2011_12P,6,FALSE))))) -> 0 | N2: =IF(B2="Excluded",0,(IF(ISNA(VLOOKUP(A2,FY2012_13P,6,FALSE)),0,(VLOOKUP(A2,FY2012_13P,6,FALSE))))) -> 0 | O2: =(AVERAGE(G2:I2)*0.75)+(AVERAGE(L2:N2)*0.25) -> 0 | P2: =(AVERAGE(E2:G2)*0.75)+(AVERAGE(J2:L2)*0.25) -> 0 | Q2: 0 | R2: =S2-Q2 -> 0 | S2: =ROUND((P2*'Cost Pool'!$C$25),0) -> 0 | U2: =V2-T2 -> 0 | V2: =ROUND((O2*'Cost Pool'!$D$25),0) -> 0 | W2: =V2+R2 -> 0
A3: 100-AU | B3: =VLOOKUP(A3,Crosswalk,2,FALSE) -> 100-AU | C3: =CONCATENATE((LEFT(B3,3))," - ",(VLOOKUP((LEFT(B3,3)),Funds,2,FALSE))) -> 100 - General Fund | D3: =VLOOKUP((RIGHT(B3,2)),Bureaus,2,FALSE) -> Office of the City Auditor | E3: =IF(B3="Excluded",0,(IF(ISNA(VLOOKUP(A3,FY2008_09,10,FALSE)),0,(VLOOKUP(A3,FY2008_09,10,FALSE))))) -> 0 | F3: =IF(B3="Excluded",0,(IF(ISNA(VLOOKUP(A3,FY2009_10,10,FALSE)),0,(VLOOKUP(A3,FY2009_10,10,FALSE))))) -> 0 | G3: =IF(B3="Excluded",0,(IF(ISNA(VLOOKUP(A3,FY2010_11,10,FALSE)),0,(VLOOKUP(A3,FY2010_11,10,FALSE))))) -> 0 | H3: =IF(B3="Excluded",0,(IF(ISNA(VLOOKUP(A3,FY2011_12,10,FALSE)),0,(VLOOKUP(A3,FY2011_12,10,FALSE))))) -> 0 | I3: =IF(B3="Excluded",0,(IF(ISNA(VLOOKUP(A3,FY2012_13,10,FALSE)),0,(VLOOKUP(A3,FY2012_13,10,FALSE))))) -> 0 | J3: =IF(B3="Excluded",0,(IF(ISNA(VLOOKUP(A3,FY2008_09P,6,FALSE)),0,(VLOOKUP(A3,FY2008_09P,6,FALSE))))) -> 0 | K3: =IF(B3="Excluded",0,(IF(ISNA(VLOOKUP(A3,FY2009_10P,6,FALSE)),0,(VLOOKUP(A3,FY2009_10P,6,FALSE))))) -> 0 | L3: =IF(B3="Excluded",0,(IF(ISNA(VLOOKUP(A3,FY2010_11P,6,FALSE)),0,(VLOOKUP(A3,FY2010_11P,6,FALSE))))) -> 0 | M3: =IF(B3="Excluded",0,(IF(ISNA(VLOOKUP(A3,FY2011_12P,6,FALSE)),0,(VLOOKUP(A3,FY2011_12P,6,FALSE))))) -> 0 | N3: =IF(B3="Excluded",0,(IF(ISNA(VLOOKUP(A3,FY2012_13P,6,FALSE)),0,(VLOOKUP(A3,FY2012_13P,6,FALSE))))) -> 0 | O3: =(AVERAGE(G3:I3)*0.75)+(AVERAGE(L3:N3)*0.25) -> 0 | P3: =(AVERAGE(E3:G3)*0.75)+(AVERAGE(J3:L3)*0.25) -> 0 | R3: =S3-Q3 -> 0 | S3: =ROUND((P3*'Cost Pool'!$C$25),0) -> 0 | U3: =V3-T3 -> 0 | V3: =ROUND((O3*'Cost Pool'!$D$25),0) -> 0 | W3: =V3+R3 -> 0
A4: 100-BO | B4: =VLOOKUP(A4,Crosswalk,2,FALSE) -> 100-BO | C4: =CONCATENATE((LEFT(B4,3))," - ",(VLOOKUP((LEFT(B4,3)),Funds,2,FALSE))) -> 100 - General Fund | D4: =VLOOKUP((RIGHT(B4,2)),Bureaus,2,FALSE) -> City Budget Office | E4: =IF(B4="Excluded",0,(IF(ISNA(VLOOKUP(A4,FY2008_09,10,FALSE)),0,(VLOOKUP(A4,FY2008_09,10,FALSE))))) -> 0 | F4: =IF(B4="Excluded",0,(IF(ISNA(VLOOKUP(A4,FY2009_10,10,FALSE)),0,(VLOOKUP(A4,FY2009_10,10,FALSE))))) -> 0 | G4: =IF(B4="Excluded",0,(IF(ISNA(VLOOKUP(A4,FY2010_11,10,FALSE)),0,(VLOOKUP(A4,FY2010_11,10,FALSE))))) -> 0 | H4: =IF(B4="Excluded",0,(IF(ISNA(VLOOKUP(A4,FY2011_12,10,FALSE)),0,(VLOOKUP(A4,FY2011_12,10,FALSE))))) -> 0 | I4: =IF(B4="Excluded",0,(IF(ISNA(VLOOKUP(A4,FY2012_13,10,FALSE)),0,(VLOOKUP(A4,FY2012_13,10,FALSE))))) -> 0 | J4: =IF(B4="Excluded",0,(IF(ISNA(VLOOKUP(A4,FY2008_09P,6,FALSE)),0,(VLOOKUP(A4,FY2008_09P,6,FALSE))))) -> 0 | K4: =IF(B4="Excluded",0,(IF(ISNA(VLOOKUP(A4,FY2009_10P,6,FALSE)),0,(VLOOKUP(A4,FY2009_10P,6,FALSE))))) -> 0 | L4: =IF(B4="Excluded",0,(IF(ISNA(VLOOKUP(A4,FY2010_11P,6,FALSE)),0,(VLOOKUP(A4,FY2010_11P,6,FALSE))))) -> 0 | M4: =IF(B4="Excluded",0,(IF(ISNA(VLOOKUP(A4,FY2011_12P,6,FALSE)),0,(VLOOKUP(A4,FY2011_12P,6,FALSE))))) -> 0 | N4: =IF(B4="Excluded",0,(IF(ISNA(VLOOKUP(A4,FY2012_13P,6,FALSE)),0,(VLOOKUP(A4,FY2012_13P,6,FALSE))))) -> 0 | O4: =(AVERAGE(G4:I4)*0.75)+(AVERAGE(L4:N4)*0.25) -> 0 | P4: =(AVERAGE(E4:G4)*0.75)+(AVERAGE(J4:L4)*0.25) -> 0 | R4: =S4-Q4 -> 0 | S4: =ROUND((P4*'Cost Pool'!$C$25),0) -> 0 | U4: =V4-T4 -> 0 | V4: =ROUND((O4*'Cost Pool'!$D$25),0) -> 0 | W4: =V4+R4 -> 0
A5: 100-CB | B5: =VLOOKUP(A5,Crosswalk,2,FALSE) -> 100-MF | C5: =CONCATENATE((LEFT(B5,3))," - ",(VLOOKUP((LEFT(B5,3)),Funds,2,FALSE))) -> 100 - General Fund | D5: =VLOOKUP((RIGHT(B5,2)),Bureaus,2,FALSE) -> Office of Management & Finance | E5: =IF(B5="Excluded",0,(IF(ISNA(VLOOKUP(A5,FY2008_09,10,FALSE)),0,(VLOOKUP(A5,FY2008_09,10,FALSE))))) -> 0.0022176202 | F5: =IF(B5="Excluded",0,(IF(ISNA(VLOOKUP(A5,FY2009_10,10,FALSE)),0,(VLOOKUP(A5,FY2009_10,10,FALSE))))) -> 0.0018047776 | G5: =IF(B5="Excluded",0,(IF(ISNA(VLOOKUP(A5,FY2010_11,10,FALSE)),0,(VLOOKUP(A5,FY2010_11,10,FALSE))))) -> 0.0014272866 | H5: =IF(B5="Excluded",0,(IF(ISNA(VLOOKUP(A5,FY2011_12,10,FALSE)),0,(VLOOKUP(A5,FY2011_12,10,FALSE))))) -> 0.001956749 | I5: =IF(B5="Excluded",0,(IF(ISNA(VLOOKUP(A5,FY2012_13,10,FALSE)),0,(VLOOKUP(A5,FY2012_13,10,FALSE))))) -> 0 | J5: =IF(B5="Excluded",0,(IF(ISNA(VLOOKUP(A5,FY2008_09P,6,FALSE)),0,(VLOOKUP(A5,FY2008_09P,6,FALSE))))) -> 0.0011472275 | K5: =IF(B5="Excluded",0,(IF(ISNA(VLOOKUP(A5,FY2009_10P,6,FALSE)),0,(VLOOKUP(A5,FY2009_10P,6,FALSE))))) -> 0.0011013216 | L5: =IF(B5="Excluded",0,(IF(ISNA(VLOOKUP(A5,FY2010_11P,6,FALSE)),0,(VLOOKUP(A5,FY2010_11P,6,FALSE))))) -> 0.0011307243 | M5: =IF(B5="Excluded",0,(IF(ISNA(VLOOKUP(A5,FY2011_12P,6,FALSE)),0,(VLOOKUP(A5,FY2011_12P,6,FALSE))))) -> 0.0010948239 | N5: =IF(B5="Excluded",0,(IF(ISNA(VLOOKUP(A5,FY2012_13P,6,FALSE)),0,(VLOOKUP(A5,FY2012_13P,6,FALSE))))) -> 0 | O5: =(AVERAGE(G5:I5)*0.75)+(AVERAGE(L5:N5)*0.25) -> 0.0010314712 | P5: =(AVERAGE(E5:G5)*0.75)+(AVERAGE(J5:L5)*0.25) -> 0.0016440272 | Q5: 55477 | R5: =S5-Q5 -> 11185 | S5: =ROUND((P5*'Cost Pool'!$C$25),0) -> 66662 | T5: 74159 | U5: =V5-T5 -> -26835 | V5: =ROUND((O5*'Cost Pool'!$D$25),0) -> 47324 | W5: =V5+R5 -> 58509
A6: 100-EM | B6: =VLOOKUP(A6,Crosswalk,2,FALSE) -> 100-EM | C6: =CONCATENATE((LEFT(B6,3))," - ",(VLOOKUP((LEFT(B6,3)),Funds,2,FALSE))) -> 100 - General Fund | D6: =VLOOKUP((RIGHT(B6,2)),Bureaus,2,FALSE) -> Portland Bureau of Emergency Management | E6: =IF(B6="Excluded",0,(IF(ISNA(VLOOKUP(A6,FY2008_09,10,FALSE)),0,(VLOOKUP(A6,FY2008_09,10,FALSE))))) -> 0 | F6: =IF(B6="Excluded",0,(IF(ISNA(VLOOKUP(A6,FY2009_10,10,FALSE)),0,(VLOOKUP(A6,FY2009_10,10,FALSE))))) -> 0 | G6: =IF(B6="Excluded",0,(IF(ISNA(VLOOKUP(A6,FY2010_11,10,FALSE)),0,(VLOOKUP(A6,FY2010_11,10,FALSE))))) -> 0 | H6: =IF(B6="Excluded",0,(IF(ISNA(VLOOKUP(A6,FY2011_12,10,FALSE)),0,(VLOOKUP(A6,FY2011_12,10,FALSE))))) -> 0 | I6: =IF(B6="Excluded",0,(IF(ISNA(VLOOKUP(A6,FY2012_13,10,FALSE)),0,(VLOOKUP(A6,FY2012_13,10,FALSE))))) -> 0 | J6: =IF(B6="Excluded",0,(IF(ISNA(VLOOKUP(A6,FY2008_09P,6,FALSE)),0,(VLOOKUP(A6,FY2008_09P,6,FALSE))))) -> 0 | K6: =IF(B6="Excluded",0,(IF(ISNA(VLOOKUP(A6,FY2009_10P,6,FALSE)),0,(VLOOKUP(A6,FY2009_10P,6,FALSE))))) -> 0 | L6: =IF(B6="Excluded",0,(IF(ISNA(VLOOKUP(A6,FY2010_11P,6,FALSE)),0,(VLOOKUP(A6,FY2010_11P,6,FALSE))))) -> 0 | M6: =IF(B6="Excluded",0,(IF(ISNA(VLOOKUP(A6,FY2011_12P,6,FALSE)),0,(VLOOKUP(A6,FY2011_12P,6,FALSE))))) -> 0 | N6: =IF(B6="Excluded",0,(IF(ISNA(VLOOKUP(A6,FY2012_13P,6,FALSE)),0,(VLOOKUP(A6,FY2012_13P,6,FALSE))))) -> 0 | O6: =(AVERAGE(G6:I6)*0.75)+(AVERAGE(L6:N6)*0.25) -> 0 | P6: =(AVERAGE(E6:G6)*0.75)+(AVERAGE(J6:L6)*0.25) -> 0 | R6: =S6-Q6 -> 0 | S6: =ROUND((P6*'Cost Pool'!$C$25),0) -> 0 | U6: =V6-T6 -> 0 | V6: =ROUND((O6*'Cost Pool'!$D$25),0) -> 0 | W6: =V6+R6 -> 0
A7: 100-FM | B7: =VLOOKUP(A7,Crosswalk,2,FALSE) -> Excluded | C7: =CONCATENATE((LEFT(B7,3))," - ",(VLOOKUP((LEFT(B7,3)),Funds,2,FALSE))) -> #N/A | D7: =VLOOKUP((RIGHT(B7,2)),Bureaus,2,FALSE) -> #N/A | E7: =IF(B7="Excluded",0,(IF(ISNA(VLOOKUP(A7,FY2008_09,10,FALSE)),0,(VLOOKUP(A7,FY2008_09,10,FALSE))))) -> 0 | F7: =IF(B7="Excluded",0,(IF(ISNA(VLOOKUP(A7,FY2009_10,10,FALSE)),0,(VLOOKUP(A7,FY2009_10,10,FALSE))))) -> 0 | G7: =IF(B7="Excluded",0,(IF(ISNA(VLOOKUP(A7,FY2010_11,10,FALSE)),0,(VLOOKUP(A7,FY2010_11,10,FALSE))))) -> 0 | H7: =IF(B7="Excluded",0,(IF(ISNA(VLOOKUP(A7,FY2011_12,10,FALSE)),0,(VLOOKUP(A7,FY2011_12,10,FALSE))))) -> 0 | I7: =IF(B7="Excluded",0,(IF(ISNA(VLOOKUP(A7,FY2012_13,10,FALSE)),0,(VLOOKUP(A7,FY2012_13,10,FALSE))))) -> 0 | J7: =IF(B7="Excluded",0,(IF(ISNA(VLOOKUP(A7,FY2008_09P,6,FALSE)),0,(VLOOKUP(A7,FY2008_09P,6,FALSE))))) -> 0 | K7: =IF(B7="Excluded",0,(IF(ISNA(VLOOKUP(A7,FY2009_10P,6,FALSE)),0,(VLOOKUP(A7,FY2009_10P,6,FALSE))))) -> 0 | L7: =IF(B7="Excluded",0,(IF(ISNA(VLOOKUP(A7,FY2010_11P,6,FALSE)),0,(VLOOKUP(A7,FY2010_11P,6,FALSE))))) -> 0 | M7: =IF(B7="Excluded",0,(IF(ISNA(VLOOKUP(A7,FY2011_12P,6,FALSE)),0,(VLOOKUP(A7,FY2011_12P,6,FALSE))))) -> 0 | N7: =IF(B7="Excluded",0,(IF(ISNA(VLOOKUP(A7,FY2012_13P,6,FALSE)),0,(VLOOKUP(A7,FY2012_13P,6,FALSE))))) -> 0 | O7: =(AVERAGE(G7:I7)*0.75)+(AVERAGE(L7:N7)*0.25) -> 0 | P7: =(AVERAGE(E7:G7)*0.75)+(AVERAGE(J7:L7)*0.25) -> 0 | R7: =S7-Q7 -> 0 | S7: =ROUND((P7*'Cost Pool'!$C$25),0) -> 0 | U7: =V7-T7 -> 0 | V7: =ROUND((O7*'Cost Pool'!$D$25),0) -> 0 | W7: =V7+R7 -> 0
A8: 100-FR | B8: =VLOOKUP(A8,Crosswalk,2,FALSE) -> 100-FR | C8: =CONCATENATE((LEFT(B8,3))," - ",(VLOOKUP((LEFT(B8,3)),Funds,2,FALSE))) -> 100 - General Fund | D8: =VLOOKUP((RIGHT(B8,2)),Bureaus,2,FALSE) -> Portland Fire & Rescue | E8: =IF(B8="Excluded",0,(IF(ISNA(VLOOKUP(A8,FY2008_09,10,FALSE)),0,(VLOOKUP(A8,FY2008_09,10,FALSE))))) -> 0.095037556 | F8: =IF(B8="Excluded",0,(IF(ISNA(VLOOKUP(A8,FY2009_10,10,FALSE)),0,(VLOOKUP(A8,FY2009_10,10,FALSE))))) -> 0.093702445 | G8: =IF(B8="Excluded",0,(IF(ISNA(VLOOKUP(A8,FY2010_11,10,FALSE)),0,(VLOOKUP(A8,FY2010_11,10,FALSE))))) -> 0.092479395 | H8: =IF(B8="Excluded",0,(IF(ISNA(VLOOKUP(A8,FY2011_12,10,FALSE)),0,(VLOOKUP(A8,FY2011_12,10,FALSE))))) -> 0.10048504 | I8: =IF(B8="Excluded",0,(IF(ISNA(VLOOKUP(A8,FY2012_13,10,FALSE)),0,(VLOOKUP(A8,FY2012_13,10,FALSE))))) -> 0.095039456 | J8: =IF(B8="Excluded",0,(IF(ISNA(VLOOKUP(A8,FY2008_09P,6,FALSE)),0,(VLOOKUP(A8,FY2008_09P,6,FALSE))))) -> 0.098279159 | K8: =IF(B8="Excluded",0,(IF(ISNA(VLOOKUP(A8,FY2009_10P,6,FALSE)),0,(VLOOKUP(A8,FY2009_10P,6,FALSE))))) -> 0.092755751 | L8: =IF(B8="Excluded",0,(IF(ISNA(VLOOKUP(A8,FY2010_11P,6,FALSE)),0,(VLOOKUP(A8,FY2010_11P,6,FALSE))))) -> 0.097744833 | M8: =IF(B8="Excluded",0,(IF(ISNA(VLOOKUP(A8,FY2011_12P,6,FALSE)),0,(VLOOKUP(A8,FY2011_12P,6,FALSE))))) -> 0.095249681 | N8: =IF(B8="Excluded",0,(IF(ISNA(VLOOKUP(A8,FY2012_13P,6,FALSE)),0,(VLOOKUP(A8,FY2012_13P,6,FALSE))))) -> 0.083984709 | O8: =(AVERAGE(G8:I8)*0.75)+(AVERAGE(L8:N8)*0.25) -> 0.095082576 | P8: =(AVERAGE(E8:G8)*0.75)+(AVERAGE(J8:L8)*0.25) -> 0.094369828 | Q8: 3790346 | R8: =S8-Q8 -> 36169 | S8: =ROUND((P8*'Cost Pool'!$C$25),0) -> 3826515 | T8: 4615922 | U8: =V8-T8 -> -253525 | V8: =ROUND((O8*'Cost Pool'!$D$25),0) -> 4362397 | W8: =V8+R8 -> 4398566
A9: 100-GR | B9: =VLOOKUP(A9,Crosswalk,2,FALSE) -> 100-GR | C9: =CONCATENATE((LEFT(B9,3))," - ",(VLOOKUP((LEFT(B9,3)),Funds,2,FALSE))) -> 100 - General Fund | D9: =VLOOKUP((RIGHT(B9,2)),Bureaus,2,FALSE) -> Office of Government Relations | E9: =IF(B9="Excluded",0,(IF(ISNA(VLOOKUP(A9,FY2008_09,10,FALSE)),0,(VLOOKUP(A9,FY2008_09,10,FALSE))))) -> 0 | F9: =IF(B9="Excluded",0,(IF(ISNA(VLOOKUP(A9,FY2009_10,10,FALSE)),0,(VLOOKUP(A9,FY2009_10,10,FALSE))))) -> 0 | G9: =IF(B9="Excluded",0,(IF(ISNA(VLOOKUP(A9,FY2010_11,10,FALSE)),0,(VLOOKUP(A9,FY2010_11,10,FALSE))))) -> 0 | H9: =IF(B9="Excluded",0,(IF(ISNA(VLOOKUP(A9,FY2011_12,10,FALSE)),0,(VLOOKUP(A9,FY2011_12,10,FALSE))))) -> 0 | I9: =IF(B9="Excluded",0,(IF(ISNA(VLOOKUP(A9,FY2012_13,10,FALSE)),0,(VLOOKUP(A9,FY2012_13,10,FALSE))))) -> 0 | J9: =IF(B9="Excluded",0,(IF(ISNA(VLOOKUP(A9,FY2008_09P,6,FALSE)),0,(VLOOKUP(A9,FY2008_09P,6,FALSE))))) -> 0 | K9: =IF(B9="Excluded",0,(IF(ISNA(VLOOKUP(A9,FY2009_10P,6,FALSE)),0,(VLOOKUP(A9,FY2009_10P,6,FALSE))))) -> 0 | L9: =IF(B9="Excluded",0,(IF(ISNA(VLOOKUP(A9,FY2010_11P,6,FALSE)),0,(VLOOKUP(A9,FY2010_11P,6,FALSE))))) -> 0 | M9: =IF(B9="Excluded",0,(IF(ISNA(VLOOKUP(A9,FY2011_12P,6,FALSE)),0,(VLOOKUP(A9,FY2011_12P,6,FALSE))))) -> 0 | N9: =IF(B9="Excluded",0,(IF(ISNA(VLOOKUP(A9,FY2012_13P,6,FALSE)),0,(VLOOKUP(A9,FY2012_13P,6,FALSE))))) -> 0 | O9: =(AVERAGE(G9:I9)*0.75)+(AVERAGE(L9:N9)*0.25) -> 0 | P9: =(AVERAGE(E9:G9)*0.75)+(AVERAGE(J9:L9)*0.25) -> 0 | R9: =S9-Q9 -> 0 | S9: =ROUND((P9*'Cost Pool'!$C$25),0) -> 0 | U9: =V9-T9 -> 0 | V9: =ROUND((O9*'Cost Pool'!$D$25),0) -> 0 | W9: =V9+R9 -> 0
A10: 100-HC | B10: =VLOOKUP(A10,Crosswalk,2,FALSE) -> 100-HC | C10: =CONCATENATE((LEFT(B10,3))," - ",(VLOOKUP((LEFT(B10,3)),Funds,2,FALSE))) -> 100 - General Fund | D10: =VLOOKUP((RIGHT(B10,2)),Bureaus,2,FALSE) -> Portland Housing Bureau | E10: =IF(B10="Excluded",0,(IF(ISNA(VLOOKUP(A10,FY2008_09,10,FALSE)),0,(VLOOKUP(A10,FY2008_09,10,FALSE))))) -> 0.016583044 | F10: =IF(B10="Excluded",0,(IF(ISNA(VLOOKUP(A10,FY2009_10,10,FALSE)),0,(VLOOKUP(A10,FY2009_10,10,FALSE))))) -> 0.013071424 | G10: =IF(B10="Excluded",0,(IF(ISNA(VLOOKUP(A10,FY2010_11,10,FALSE)),0,(VLOOKUP(A10,FY2010_11,10,FALSE))))) -> 0.01107242 | H10: =IF(B10="Excluded",0,(IF(ISNA(VLOOKUP(A10,FY2011_12,10,FALSE)),0,(VLOOKUP(A10,FY2011_12,10,FALSE))))) -> 0.013028296 | I10: =IF(B10="Excluded",0,(IF(ISNA(VLOOKUP(A10,FY2012_13,10,FALSE)),0,(VLOOKUP(A10,FY2012_13,10,FALSE))))) -> 0.011762371 | J10: =IF(B10="Excluded",0,(IF(ISNA(VLOOKUP(A10,FY2008_09P,6,FALSE)),0,(VLOOKUP(A10,FY2008_09P,6,FALSE))))) -> 0.0052262588 | K10: =IF(B10="Excluded",0,(IF(ISNA(VLOOKUP(A10,FY2009_10P,6,FALSE)),0,(VLOOKUP(A10,FY2009_10P,6,FALSE))))) -> 0.0045276554 | L10: =IF(B10="Excluded",0,(IF(ISNA(VLOOKUP(A10,FY2010_11P,6,FALSE)),0,(VLOOKUP(A10,FY2010_11P,6,FALSE))))) -> 0.0087945223 | M10: =IF(B10="Excluded",0,(IF(ISNA(VLOOKUP(A10,FY2011_12P,6,FALSE)),0,(VLOOKUP(A10,FY2011_12P,6,FALSE))))) -> 0.0074204732 | N10: =IF(B10="Excluded",0,(IF(ISNA(VLOOKUP(A10,FY2012_13P,6,FALSE)),0,(VLOOKUP(A10,FY2012_13P,6,FALSE))))) -> 0.0066183602 | O10: =(AVERAGE(G10:I10)*0.75)+(AVERAGE(L10:N10)*0.25) -> 0.010868552 | P10: =(AVERAGE(E10:G10)*0.75)+(AVERAGE(J10:L10)*0.25) -> 0.011727425 | Q10: 619527 | R10: =S10-Q10 -> -144002 | S10: =ROUND((P10*'Cost Pool'!$C$25),0) -> 475525 | T10: 756944 | U10: =V10-T10 -> -258294 | V10: =ROUND((O10*'Cost Pool'!$D$25),0) -> 498650 | W10: =V10+R10 -> 354648
A11: 100-HN | B11: =VLOOKUP(A11,Crosswalk,2,FALSE) -> Excluded | C11: =CONCATENATE((LEFT(B11,3))," - ",(VLOOKUP((LEFT(B11,3)),Funds,2,FALSE))) -> #N/A | D11: =VLOOKUP((RIGHT(B11,2)),Bureaus,2,FALSE) -> #N/A | E11: =IF(B11="Excluded",0,(IF(ISNA(VLOOKUP(A11,FY2008_09,10,FALSE)),0,(VLOOKUP(A11,FY2008_09,10,FALSE))))) -> 0 | F11: =IF(B11="Excluded",0,(IF(ISNA(VLOOKUP(A11,FY2009_10,10,FALSE)),0,(VLOOKUP(A11,FY2009_10,10,FALSE))))) -> 0 | G11: =IF(B11="Excluded",0,(IF(ISNA(VLOOKUP(A11,FY2010_11,10,FALSE)),0,(VLOOKUP(A11,FY2010_11,10,FALSE))))) -> 0 | H11: =IF(B11="Excluded",0,(IF(ISNA(VLOOKUP(A11,FY2011_12,10,FALSE)),0,(VLOOKUP(A11,FY2011_12,10,FALSE))))) -> 0 | I11: =IF(B11="Excluded",0,(IF(ISNA(VLOOKUP(A11,FY2012_13,10,FALSE)),0,(VLOOKUP(A11,FY2012_13,10,FALSE))))) -> 0 | J11: =IF(B11="Excluded",0,(IF(ISNA(VLOOKUP(A11,FY2008_09P,6,FALSE)),0,(VLOOKUP(A11,FY2008_09P,6,FALSE))))) -> 0 | K11: =IF(B11="Excluded",0,(IF(ISNA(VLOOKUP(A11,FY2009_10P,6,FALSE)),0,(VLOOKUP(A11,FY2009_10P,6,FALSE))))) -> 0 | L11: =IF(B11="Excluded",0,(IF(ISNA(VLOOKUP(A11,FY2010_11P,6,FALSE)),0,(VLOOKUP(A11,FY2010_11P,6,FALSE))))) -> 0 | M11: =IF(B11="Excluded",0,(IF(ISNA(VLOOKUP(A11,FY2011_12P,6,FALSE)),0,(VLOOKUP(A11,FY2011_12P,6,FALSE))))) -> 0 | N11: =IF(B11="Excluded",0,(IF(ISNA(VLOOKUP(A11,FY2012_13P,6,FALSE)),0,(VLOOKUP(A11,FY2012_13P,6,FALSE))))) -> 0 | O11: =(AVERAGE(G11:I11)*0.75)+(AVERAGE(L11:N11)*0.25) -> 0 | P11: =(AVERAGE(E11:G11)*0.75)+(AVERAGE(J11:L11)*0.25) -> 0 | R11: =S11-Q11 -> 0 | S11: =ROUND((P11*'Cost Pool'!$C$25),0) -> 0 | U11: =V11-T11 -> 0 | V11: =ROUND((O11*'Cost Pool'!$D$25),0) -> 0 | W11: =V11+R11 -> 0
A12: 100-MF | B12: =VLOOKUP(A12,Crosswalk,2,FALSE) -> 100-MF | C12: =CONCATENATE((LEFT(B12,3))," - ",(VLOOKUP((LEFT(B12,3)),Funds,2,FALSE))) -> 100 - General Fund | D12: =VLOOKUP((RIGHT(B12,2)),Bureaus,2,FALSE) -> Office of Management & Finance | E12: =IF(B12="Excluded",0,(IF(ISNA(VLOOKUP(A12,FY2008_09,10,FALSE)),0,(VLOOKUP(A12,FY2008_09,10,FALSE))))) -> 0.01455677 | F12: =IF(B12="Excluded",0,(IF(ISNA(VLOOKUP(A12,FY2009_10,10,FALSE)),0,(VLOOKUP(A12,FY2009_10,10,FALSE))))) -> 0.0089164785 | G12: =IF(B12="Excluded",0,(IF(ISNA(VLOOKUP(A12,FY2010_11,10,FALSE)),0,(VLOOKUP(A12,FY2010_11,10,FALSE))))) -> 0.0086234507 | H12: =IF(B12="Excluded",0,(IF(ISNA(VLOOKUP(A12,FY2011_12,10,FALSE)),0,(VLOOKUP(A12,FY2011_12,10,FALSE))))) -> 0.0092323106 | I12: =IF(B12="Excluded",0,(IF(ISNA(VLOOKUP(A12,FY2012_13,10,FALSE)),0,(VLOOKUP(A12,FY2012_13,10,FALSE))))) -> 0.011412877 | J12: =IF(B12="Excluded",0,(IF(ISNA(VLOOKUP(A12,FY2008_09P,6,FALSE)),0,(VLOOKUP(A12,FY2008_09P,6,FALSE))))) -> 0.0085404716 | K12: =IF(B12="Excluded",0,(IF(ISNA(VLOOKUP(A12,FY2009_10P,6,FALSE)),0,(VLOOKUP(A12,FY2009_10P,6,FALSE))))) -> 0.0085658346 | L12: =IF(B12="Excluded",0,(IF(ISNA(VLOOKUP(A12,FY2010_11P,6,FALSE)),0,(VLOOKUP(A12,FY2010_11P,6,FALSE))))) -> 0.0085432502 | M12: =IF(B12="Excluded",0,(IF(ISNA(VLOOKUP(A12,FY2011_12P,6,FALSE)),0,(VLOOKUP(A12,FY2011_12P,6,FALSE))))) -> 0.0088802384 | N12: =IF(B12="Excluded",0,(IF(ISNA(VLOOKUP(A12,FY2012_13P,6,FALSE)),0,(VLOOKUP(A12,FY2012_13P,6,FALSE))))) -> 0.01004165 | O12: =(AVERAGE(G12:I12)*0.75)+(AVERAGE(L12:N12)*0.25) -> 0.0096059211 | P12: =(AVERAGE(E12:G12)*0.75)+(AVERAGE(J12:L12)*0.25) -> 0.010161638 | Q12: 771800 | R12: =S12-Q12 -> -359765 | S12: =ROUND((P12*'Cost Pool'!$C$25),0) -> 412035 | T12: =40689+408676+24350+21778+869452+164251+86020+133 -> 1615349 | U12: =V12-T12 -> -1174629 | V12: =ROUND((O12*'Cost Pool'!$D$25),0) -> 440720 | W12: =V12+R12 -> 80955
A13: 100-MY | B13: =VLOOKUP(A13,Crosswalk,2,FALSE) -> 100-MY | C13: =CONCATENATE((LEFT(B13,3))," - ",(VLOOKUP((LEFT(B13,3)),Funds,2,FALSE))) -> 100 - General Fund | D13: =VLOOKUP((RIGHT(B13,2)),Bureaus,2,FALSE) -> Office of the Mayor | E13: =IF(B13="Excluded",0,(IF(ISNA(VLOOKUP(A13,FY2008_09,10,FALSE)),0,(VLOOKUP(A13,FY2008_09,10,FALSE))))) -> 6.5888669e-05 | F13: =IF(B13="Excluded",0,(IF(ISNA(VLOOKUP(A13,FY2009_10,10,FALSE)),0,(VLOOKUP(A13,FY2009_10,10,FALSE))))) -> 1.3793117e-05 | G13: =IF(B13="Excluded",0,(IF(ISNA(VLOOKUP(A13,FY2010_11,10,FALSE)),0,(VLOOKUP(A13,FY2010_11,10,FALSE))))) -> 0.00071522188 | H13: =IF(B13="Excluded",0,(IF(ISNA(VLOOKUP(A13,FY2011_12,10,FALSE)),0,(VLOOKUP(A13,FY2011_12,10,FALSE))))) -> 0.001335013 | I13: =IF(B13="Excluded",0,(IF(ISNA(VLOOKUP(A13,FY2012_13,10,FALSE)),0,(VLOOKUP(A13,FY2012_13,10,FALSE))))) -> 0.0016048761 | J13: =IF(B13="Excluded",0,(IF(ISNA(VLOOKUP(A13,FY2008_09P,6,FALSE)),0,(VLOOKUP(A13,FY2008_09P,6,FALSE))))) -> 0.00025493945 | K13: =IF(B13="Excluded",0,(IF(ISNA(VLOOKUP(A13,FY2009_10P,6,FALSE)),0,(VLOOKUP(A13,FY2009_10P,6,FALSE))))) -> 0.00024473813 | L13: =IF(B13="Excluded",0,(IF(ISNA(VLOOKUP(A13,FY2010_11P,6,FALSE)),0,(VLOOKUP(A13,FY2010_11P,6,FALSE))))) -> 0.00025127206 | M13: =IF(B13="Excluded",0,(IF(ISNA(VLOOKUP(A13,FY2011_12P,6,FALSE)),0,(VLOOKUP(A13,FY2011_12P,6,FALSE))))) -> 0.0002432942 | N13: =IF(B13="Excluded",0,(IF(ISNA(VLOOKUP(A13,FY2012_13P,6,FALSE)),0,(VLOOKUP(A13,FY2012_13P,6,FALSE))))) -> 0.00011410966 | O13: =(AVERAGE(G13:I13)*0.75)+(AVERAGE(L13:N13)*0.25) -> 0.00096450075 | P13: =(AVERAGE(E13:G13)*0.75)+(AVERAGE(J13:L13)*0.25) -> 0.00026130505 | R13: =S13-Q13 -> 10595 | S13: =ROUND((P13*'Cost Pool'!$C$25),0) -> 10595 | U13: =V13-T13 -> 44251 | V13: =ROUND((O13*'Cost Pool'!$D$25),0) -> 44251 | W13: =V13+R13 -> 54846
A14: 100-NI | B14: =VLOOKUP(A14,Crosswalk,2,FALSE) -> 100-NI | C14: =CONCATENATE((LEFT(B14,3))," - ",(VLOOKUP((LEFT(B14,3)),Funds,2,FALSE))) -> 100 - General Fund | D14: =VLOOKUP((RIGHT(B14,2)),Bureaus,2,FALSE) -> Office of Neighborhood Involvement | E14: =IF(B14="Excluded",0,(IF(ISNA(VLOOKUP(A14,FY2008_09,10,FALSE)),0,(VLOOKUP(A14,FY2008_09,10,FALSE))))) -> 0.006025896 | F14: =IF(B14="Excluded",0,(IF(ISNA(VLOOKUP(A14,FY2009_10,10,FALSE)),0,(VLOOKUP(A14,FY2009_10,10,FALSE))))) -> 0.0073010783 | G14: =IF(B14="Excluded",0,(IF(ISNA(VLOOKUP(A14,FY2010_11,10,FALSE)),0,(VLOOKUP(A14,FY2010_11,10,FALSE))))) -> 0.0066956638 | H14: =IF(B14="Excluded",0,(IF(ISNA(VLOOKUP(A14,FY2011_12,10,FALSE)),0,(VLOOKUP(A14,FY2011_12,10,FALSE))))) -> 0.006416703 | I14: =IF(B14="Excluded",0,(IF(ISNA(VLOOKUP(A14,FY2012_13,10,FALSE)),0,(VLOOKUP(A14,FY2012_13,10,FALSE))))) -> 0.0062092428 | J14: =IF(B14="Excluded",0,(IF(ISNA(VLOOKUP(A14,FY2008_09P,6,FALSE)),0,(VLOOKUP(A14,FY2008_09P,6,FALSE))))) -> 0.0059910771 | K14: =IF(B14="Excluded",0,(IF(ISNA(VLOOKUP(A14,FY2009_10P,6,FALSE)),0,(VLOOKUP(A14,FY2009_10P,6,FALSE))))) -> 0.0052618698 | L14: =IF(B14="Excluded",0,(IF(ISNA(VLOOKUP(A14,FY2010_11P,6,FALSE)),0,(VLOOKUP(A14,FY2010_11P,6,FALSE))))) -> 0.0056536215 | M14: =IF(B14="Excluded",0,(IF(ISNA(VLOOKUP(A14,FY2011_12P,6,FALSE)),0,(VLOOKUP(A14,FY2011_12P,6,FALSE))))) -> 0.0051091783 | N14: =IF(B14="Excluded",0,(IF(ISNA(VLOOKUP(A14,FY2012_13P,6,FALSE)),0,(VLOOKUP(A14,FY2012_13P,6,FALSE))))) -> 0.0051349347 | O14: =(AVERAGE(G14:I14)*0.75)+(AVERAGE(L14:N14)*0.25) -> 0.0061552136 | P14: =(AVERAGE(E14:G14)*0.75)+(AVERAGE(J14:L14)*0.25) -> 0.0064145402 | Q14: 255373 | R14: =S14-Q14 -> 4724 | S14: =ROUND((P14*'Cost Pool'!$C$25),0) -> 260097 | T14: 307900 | U14: =V14-T14 -> -25498 | V14: =ROUND((O14*'Cost Pool'!$D$25),0) -> 282402 | W14: =V14+R14 -> 287126
A15: 100-OE | B15: =VLOOKUP(A15,Crosswalk,2,FALSE) -> 100-OE | C15: =CONCATENATE((LEFT(B15,3))," - ",(VLOOKUP((LEFT(B15,3)),Funds,2,FALSE))) -> 100 - General Fund | D15: =VLOOKUP((RIGHT(B15,2)),Bureaus,2,FALSE) -> Office of Equity & Human Rights | E15: =IF(B15="Excluded",0,(IF(ISNA(VLOOKUP(A15,FY2008_09,10,FALSE)),0,(VLOOKUP(A15,FY2008_09,10,FALSE))))) -> 0 | F15: =IF(B15="Excluded",0,(IF(ISNA(VLOOKUP(A15,FY2009_10,10,FALSE)),0,(VLOOKUP(A15,FY2009_10,10,FALSE))))) -> 0.00012879132 | G15: =IF(B15="Excluded",0,(IF(ISNA(VLOOKUP(A15,FY2010_11,10,FALSE)),0,(VLOOKUP(A15,FY2010_11,10,FALSE))))) -> 0.00012795821 | H15: =IF(B15="Excluded",0,(IF(ISNA(VLOOKUP(A15,FY2011_12,10,FALSE)),0,(VLOOKUP(A15,FY2011_12,10,FALSE))))) -> 0.00013486394 | I15: =IF(B15="Excluded",0,(IF(ISNA(VLOOKUP(A15,FY2012_13,10,FALSE)),0,(VLOOKUP(A15,FY2012_13,10,FALSE))))) -> 0.00034857036 | J15: =IF(B15="Excluded",0,(IF(ISNA(VLOOKUP(A15,FY2008_09P,6,FALSE)),0,(VLOOKUP(A15,FY2008_09P,6,FALSE))))) -> 0 | K15: =IF(B15="Excluded",0,(IF(ISNA(VLOOKUP(A15,FY2009_10P,6,FALSE)),0,(VLOOKUP(A15,FY2009_10P,6,FALSE))))) -> 0.00073421439 | L15: =IF(B15="Excluded",0,(IF(ISNA(VLOOKUP(A15,FY2010_11P,6,FALSE)),0,(VLOOKUP(A15,FY2010_11P,6,FALSE))))) -> 0.00075381619 | M15: =IF(B15="Excluded",0,(IF(ISNA(VLOOKUP(A15,FY2011_12P,6,FALSE)),0,(VLOOKUP(A15,FY2011_12P,6,FALSE))))) -> 0.00072988261 | N15: =IF(B15="Excluded",0,(IF(ISNA(VLOOKUP(A15,FY2012_13P,6,FALSE)),0,(VLOOKUP(A15,FY2012_13P,6,FALSE))))) -> 0.0010269869 | O15: =(AVERAGE(G15:I15)*0.75)+(AVERAGE(L15:N15)*0.25) -> 0.00036207194 | P15: =(AVERAGE(E15:G15)*0.75)+(AVERAGE(J15:L15)*0.25) -> 0.00018818993 | R15: =S15-Q15 -> 7631 | S15: =ROUND((P15*'Cost Pool'!$C$25),0) -> 7631 | T15: 5027 | U15: =V15-T15 -> 11585 | V15: =ROUND((O15*'Cost Pool'!$D$25),0) -> 16612 | W15: =V15+R15 -> 24243
A16: 100-PA | B16: =VLOOKUP(A16,Crosswalk,2,FALSE) -> 100-PA | C16: =CONCATENATE((LEFT(B16,3))," - ",(VLOOKUP((LEFT(B16,3)),Funds,2,FALSE))) -> 100 - General Fund | D16: =VLOOKUP((RIGHT(B16,2)),Bureaus,2,FALSE) -> Commissioner of Public Affairs | E16: =IF(B16="Excluded",0,(IF(ISNA(VLOOKUP(A16,FY2008_09,10,FALSE)),0,(VLOOKUP(A16,FY2008_09,10,FALSE))))) -> 0.00014060118 | F16: =IF(B16="Excluded",0,(IF(ISNA(VLOOKUP(A16,FY2009_10,10,FALSE)),0,(VLOOKUP(A16,FY2009_10,10,FALSE))))) -> 0.00054905953 | G16: =IF(B16="Excluded",0,(IF(ISNA(VLOOKUP(A16,FY2010_11,10,FALSE)),0,(VLOOKUP(A16,FY2010_11,10,FALSE))))) -> 0.00054550792 | H16: =IF(B16="Excluded",0,(IF(ISNA(VLOOKUP(A16,FY2011_12,10,FALSE)),0,(VLOOKUP(A16,FY2011_12,10,FALSE))))) -> 0.0005678438 | I16: =IF(B16="Excluded",0,(IF(ISNA(VLOOKUP(A16,FY2012_13,10,FALSE)),0,(VLOOKUP(A16,FY2012_13,10,FALSE))))) -> 0.00051316152 | J16: =IF(B16="Excluded",0,(IF(ISNA(VLOOKUP(A16,FY2008_09P,6,FALSE)),0,(VLOOKUP(A16,FY2008_09P,6,FALSE))))) -> 0.00025493945 | K16: =IF(B16="Excluded",0,(IF(ISNA(VLOOKUP(A16,FY2009_10P,6,FALSE)),0,(VLOOKUP(A16,FY2009_10P,6,FALSE))))) -> 0.00012236907 | L16: =IF(B16="Excluded",0,(IF(ISNA(VLOOKUP(A16,FY2010_11P,6,FALSE)),0,(VLOOKUP(A16,FY2010_11P,6,FALSE))))) -> 0.00025127206 | M16: =IF(B16="Excluded",0,(IF(ISNA(VLOOKUP(A16,FY2011_12P,6,FALSE)),0,(VLOOKUP(A16,FY2011_12P,6,FALSE))))) -> 0.0002432942 | N16: =IF(B16="Excluded",0,(IF(ISNA(VLOOKUP(A16,FY2012_13P,6,FALSE)),0,(VLOOKUP(A16,FY2012_13P,6,FALSE))))) -> 0.00022821932 | O16: =(AVERAGE(G16:I16)*0.75)+(AVERAGE(L16:N16)*0.25) -> 0.00046686044 | P16: =(AVERAGE(E16:G16)*0.75)+(AVERAGE(J16:L16)*0.25) -> 0.00036117387 | R16: =S16-Q16 -> 14645 | S16: =ROUND((P16*'Cost Pool'!$C$25),0) -> 14645 | U16: =V16-T16 -> 21420 | V16: =ROUND((O16*'Cost Pool'!$D$25),0) -> 21420 | W16: =V16+R16 -> 36065
A17: 100-PK | B17: =VLOOKUP(A17,Crosswalk,2,FALSE) -> 100-PK | C17: =CONCATENATE((LEFT(B17,3))," - ",(VLOOKUP((LEFT(B17,3)),Funds,2,FALSE))) -> 100 - General Fund | D17: =VLOOKUP((RIGHT(B17,2)),Bureaus,2,FALSE) -> Portland Parks & Recreation | E17: =IF(B17="Excluded",0,(IF(ISNA(VLOOKUP(A17,FY2008_09,10,FALSE)),0,(VLOOKUP(A17,FY2008_09,10,FALSE))))) -> 0.056437483 | F17: =IF(B17="Excluded",0,(IF(ISNA(VLOOKUP(A17,FY2009_10,10,FALSE)),0,(VLOOKUP(A17,FY2009_10,10,FALSE))))) -> 0.055888742 | G17: =IF(B17="Excluded",0,(IF(ISNA(VLOOKUP(A17,FY2010_11,10,FALSE)),0,(VLOOKUP(A17,FY2010_11,10,FALSE))))) -> 0.055903952 | H17: =IF(B17="Excluded",0,(IF(ISNA(VLOOKUP(A17,FY2011_12,10,FALSE)),0,(VLOOKUP(A17,FY2011_12,10,FALSE))))) -> 0.061110813 | I17: =IF(B17="Excluded",0,(IF(ISNA(VLOOKUP(A17,FY2012_13,10,FALSE)),0,(VLOOKUP(A17,FY2012_13,10,FALSE))))) -> 0.057201607 | J17: =IF(B17="Excluded",0,(IF(ISNA(VLOOKUP(A17,FY2008_09P,6,FALSE)),0,(VLOOKUP(A17,FY2008_09P,6,FALSE))))) -> 0.29713193 | K17: =IF(B17="Excluded",0,(IF(ISNA(VLOOKUP(A17,FY2009_10P,6,FALSE)),0,(VLOOKUP(A17,FY2009_10P,6,FALSE))))) -> 0.33810573 | L17: =IF(B17="Excluded",0,(IF(ISNA(VLOOKUP(A17,FY2010_11P,6,FALSE)),0,(VLOOKUP(A17,FY2010_11P,6,FALSE))))) -> 0.34059928 | M17: =IF(B17="Excluded",0,(IF(ISNA(VLOOKUP(A17,FY2011_12P,6,FALSE)),0,(VLOOKUP(A17,FY2011_12P,6,FALSE))))) -> 0.36141354 | N17: =IF(B17="Excluded",0,(IF(ISNA(VLOOKUP(A17,FY2012_13P,6,FALSE)),0,(VLOOKUP(A17,FY2012_13P,6,FALSE))))) -> 0.41444628 | O17: =(AVERAGE(G17:I17)*0.75)+(AVERAGE(L17:N17)*0.25) -> 0.13659235 | P17: =(AVERAGE(E17:G17)*0.75)+(AVERAGE(J17:L17)*0.25) -> 0.12337729 | Q17: 3463800 | R17: =S17-Q17 -> 1538912 | S17: =ROUND((P17*'Cost Pool'!$C$25),0) -> 5002712 | T17: 4009808 | U17: =V17-T17 -> 2257061 | V17: =ROUND((O17*'Cost Pool'!$D$25),0) -> 6266869 | W17: =V17+R17 -> 7805781
A18: 100-PL | B18: =VLOOKUP(A18,Crosswalk,2,FALSE) -> 100-PL | C18: =CONCATENATE((LEFT(B18,3))," - ",(VLOOKUP((LEFT(B18,3)),Funds,2,FALSE))) -> 100 - General Fund | D18: =VLOOKUP((RIGHT(B18,2)),Bureaus,2,FALSE) -> Portland Police Bureau | E18: =IF(B18="Excluded",0,(IF(ISNA(VLOOKUP(A18,FY2008_09,10,FALSE)),0,(VLOOKUP(A18,FY2008_09,10,FALSE))))) -> 0.14605162 | F18: =IF(B18="Excluded",0,(IF(ISNA(VLOOKUP(A18,FY2009_10,10,FALSE)),0,(VLOOKUP(A18,FY2009_10,10,FALSE))))) -> 0.14926776 | G18: =IF(B18="Excluded",0,(IF(ISNA(VLOOKUP(A18,FY2010_11,10,FALSE)),0,(VLOOKUP(A18,FY2010_11,10,FALSE))))) -> 0.13726817 | H18: =IF(B18="Excluded",0,(IF(ISNA(VLOOKUP(A18,FY2011_12,10,FALSE)),0,(VLOOKUP(A18,FY2011_12,10,FALSE))))) -> 0.1574626 | I18: =IF(B18="Excluded",0,(IF(ISNA(VLOOKUP(A18,FY2012_13,10,FALSE)),0,(VLOOKUP(A18,FY2012_13,10,FALSE))))) -> 0.14672147 | J18: =IF(B18="Excluded",0,(IF(ISNA(VLOOKUP(A18,FY2008_09P,6,FALSE)),0,(VLOOKUP(A18,FY2008_09P,6,FALSE))))) -> 0.17195666 | K18: =IF(B18="Excluded",0,(IF(ISNA(VLOOKUP(A18,FY2009_10P,6,FALSE)),0,(VLOOKUP(A18,FY2009_10P,6,FALSE))))) -> 0.15993637 | L18: =IF(B18="Excluded",0,(IF(ISNA(VLOOKUP(A18,FY2010_11P,6,FALSE)),0,(VLOOKUP(A18,FY2010_11P,6,FALSE))))) -> 0.15754758 | M18: =IF(B18="Excluded",0,(IF(ISNA(VLOOKUP(A18,FY2011_12P,6,FALSE)),0,(VLOOKUP(A18,FY2011_12P,6,FALSE))))) -> 0.15157229 | N18: =IF(B18="Excluded",0,(IF(ISNA(VLOOKUP(A18,FY2012_13P,6,FALSE)),0,(VLOOKUP(A18,FY2012_13P,6,FALSE))))) -> 0.13978433 | O18: =(AVERAGE(G18:I18)*0.75)+(AVERAGE(L18:N18)*0.25) -> 0.14777174 | P18: =(AVERAGE(E18:G18)*0.75)+(AVERAGE(J18:L18)*0.25) -> 0.14893361 | Q18: 7796139 | R18: =S18-Q18 -> -1757168 | S18: =ROUND((P18*'Cost Pool'!$C$25),0) -> 6038971 | T18: 7405955 | U18: =V18-T18 -> -626175 | V18: =ROUND((O18*'Cost Pool'!$D$25),0) -> 6779780 | W18: =V18+R18 -> 5022612
A19: 100-PN | B19: =VLOOKUP(A19,Crosswalk,2,FALSE) -> 100-PN | C19: =CONCATENATE((LEFT(B19,3))," - ",(VLOOKUP((LEFT(B19,3)),Funds,2,FALSE))) -> 100 - General Fund | D19: =VLOOKUP((RIGHT(B19,2)),Bureaus,2,FALSE) -> Bureau of Planning & Sustainability | E19: =IF(B19="Excluded",0,(IF(ISNA(VLOOKUP(A19,FY2008_09,10,FALSE)),0,(VLOOKUP(A19,FY2008_09,10,FALSE))))) -> 0.0089831277 | F19: =IF(B19="Excluded",0,(IF(ISNA(VLOOKUP(A19,FY2009_10,10,FALSE)),0,(VLOOKUP(A19,FY2009_10,10,FALSE))))) -> 0.010856299 | G19: =IF(B19="Excluded",0,(IF(ISNA(VLOOKUP(A19,FY2010_11,10,FALSE)),0,(VLOOKUP(A19,FY2010_11,10,FALSE))))) -> 0.0075519462 | H19: =IF(B19="Excluded",0,(IF(ISNA(VLOOKUP(A19,FY2011_12,10,FALSE)),0,(VLOOKUP(A19,FY2011_12,10,FALSE))))) -> 0.00809581 | I19: =IF(B19="Excluded",0,(IF(ISNA(VLOOKUP(A19,FY2012_13,10,FALSE)),0,(VLOOKUP(A19,FY2012_13,10,FALSE))))) -> 0.0072462535 | J19: =IF(B19="Excluded",0,(IF(ISNA(VLOOKUP(A19,FY2008_09P,6,FALSE)),0,(VLOOKUP(A19,FY2008_09P,6,FALSE))))) -> 0.010452518 | K19: =IF(B19="Excluded",0,(IF(ISNA(VLOOKUP(A19,FY2009_10P,6,FALSE)),0,(VLOOKUP(A19,FY2009_10P,6,FALSE))))) -> 0.012236907 | L19: =IF(B19="Excluded",0,(IF(ISNA(VLOOKUP(A19,FY2010_11P,6,FALSE)),0,(VLOOKUP(A19,FY2010_11P,6,FALSE))))) -> 0.010993153 | M19: =IF(B19="Excluded",0,(IF(ISNA(VLOOKUP(A19,FY2011_12P,6,FALSE)),0,(VLOOKUP(A19,FY2011_12P,6,FALSE))))) -> 0.011252357 | N19: =IF(B19="Excluded",0,(IF(ISNA(VLOOKUP(A19,FY2012_13P,6,FALSE)),0,(VLOOKUP(A19,FY2012_13P,6,FALSE))))) -> 0.0087293889 | O19: =(AVERAGE(G19:I19)*0.75)+(AVERAGE(L19:N19)*0.25) -> 0.008304744 | P19: =(AVERAGE(E19:G19)*0.75)+(AVERAGE(J19:L19)*0.25) -> 0.0096547247 | Q19: 722401 | R19: =S19-Q19 -> -330920 | S19: =ROUND((P19*'Cost Pool'!$C$25),0) -> 391481 | T19: 794342 | U19: =V19-T19 -> -413320 | V19: =ROUND((O19*'Cost Pool'!$D$25),0) -> 381022 | W19: =V19+R19 -> 50102
A20: 100-PS | B20: =VLOOKUP(A20,Crosswalk,2,FALSE) -> 100-PS | C20: =CONCATENATE((LEFT(B20,3))," - ",(VLOOKUP((LEFT(B20,3)),Funds,2,FALSE))) -> 100 - General Fund | D20: =VLOOKUP((RIGHT(B20,2)),Bureaus,2,FALSE) -> Commissioner of Public Safety | E20: =IF(B20="Excluded",0,(IF(ISNA(VLOOKUP(A20,FY2008_09,10,FALSE)),0,(VLOOKUP(A20,FY2008_09,10,FALSE))))) -> 0 | F20: =IF(B20="Excluded",0,(IF(ISNA(VLOOKUP(A20,FY2009_10,10,FALSE)),0,(VLOOKUP(A20,FY2009_10,10,FALSE))))) -> 0 | G20: =IF(B20="Excluded",0,(IF(ISNA(VLOOKUP(A20,FY2010_11,10,FALSE)),0,(VLOOKUP(A20,FY2010_11,10,FALSE))))) -> 0 | H20: =IF(B20="Excluded",0,(IF(ISNA(VLOOKUP(A20,FY2011_12,10,FALSE)),0,(VLOOKUP(A20,FY2011_12,10,FALSE))))) -> 0 | I20: =IF(B20="Excluded",0,(IF(ISNA(VLOOKUP(A20,FY2012_13,10,FALSE)),0,(VLOOKUP(A20,FY2012_13,10,FALSE))))) -> 0 | J20: =IF(B20="Excluded",0,(IF(ISNA(VLOOKUP(A20,FY2008_09P,6,FALSE)),0,(VLOOKUP(A20,FY2008_09P,6,FALSE))))) -> 0 | K20: =IF(B20="Excluded",0,(IF(ISNA(VLOOKUP(A20,FY2009_10P,6,FALSE)),0,(VLOOKUP(A20,FY2009_10P,6,FALSE))))) -> 0 | L20: =IF(B20="Excluded",0,(IF(ISNA(VLOOKUP(A20,FY2010_11P,6,FALSE)),0,(VLOOKUP(A20,FY2010_11P,6,FALSE))))) -> 0 | M20: =IF(B20="Excluded",0,(IF(ISNA(VLOOKUP(A20,FY2011_12P,6,FALSE)),0,(VLOOKUP(A20,FY2011_12P,6,FALSE))))) -> 0 | N20: =IF(B20="Excluded",0,(IF(ISNA(VLOOKUP(A20,FY2012_13P,6,FALSE)),0,(VLOOKUP(A20,FY2012_13P,6,FALSE))))) -> 0 | O20: =(AVERAGE(G20:I20)*0.75)+(AVERAGE(L20:N20)*0.25) -> 0 | P20: =(AVERAGE(E20:G20)*0.75)+(AVERAGE(J20:L20)*0.25) -> 0 | R20: =S20-Q20 -> 0 | S20: =ROUND((P20*'Cost Pool'!$C$25),0) -> 0 | U20: =V20-T20 -> 0 | V20: =ROUND((O20*'Cost Pool'!$D$25),0) -> 0 | W20: =V20+R20 -> 0
A21: 100-PU | B21: =VLOOKUP(A21,Crosswalk,2,FALSE) -> 100-PU | C21: =CONCATENATE((LEFT(B21,3))," - ",(VLOOKUP((LEFT(B21,3)),Funds,2,FALSE))) -> 100 - General Fund | D21: =VLOOKUP((RIGHT(B21,2)),Bureaus,2,FALSE) -> Commissioner of Public Utilities | E21: =IF(B21="Excluded",0,(IF(ISNA(VLOOKUP(A21,FY2008_09,10,FALSE)),0,(VLOOKUP(A21,FY2008_09,10,FALSE))))) -> 0 | F21: =IF(B21="Excluded",0,(IF(ISNA(VLOOKUP(A21,FY2009_10,10,FALSE)),0,(VLOOKUP(A21,FY2009_10,10,FALSE))))) -> 0 | G21: =IF(B21="Excluded",0,(IF(ISNA(VLOOKUP(A21,FY2010_11,10,FALSE)),0,(VLOOKUP(A21,FY2010_11,10,FALSE))))) -> 0 | H21: =IF(B21="Excluded",0,(IF(ISNA(VLOOKUP(A21,FY2011_12,10,FALSE)),0,(VLOOKUP(A21,FY2011_12,10,FALSE))))) -> 0 | I21: =IF(B21="Excluded",0,(IF(ISNA(VLOOKUP(A21,FY2012_13,10,FALSE)),0,(VLOOKUP(A21,FY2012_13,10,FALSE))))) -> 0 | J21: =IF(B21="Excluded",0,(IF(ISNA(VLOOKUP(A21,FY2008_09P,6,FALSE)),0,(VLOOKUP(A21,FY2008_09P,6,FALSE))))) -> 0 | K21: =IF(B21="Excluded",0,(IF(ISNA(VLOOKUP(A21,FY2009_10P,6,FALSE)),0,(VLOOKUP(A21,FY2009_10P,6,FALSE))))) -> 0 | L21: =IF(B21="Excluded",0,(IF(ISNA(VLOOKUP(A21,FY2010_11P,6,FALSE)),0,(VLOOKUP(A21,FY2010_11P,6,FALSE))))) -> 0 | M21: =IF(B21="Excluded",0,(IF(ISNA(VLOOKUP(A21,FY2011_12P,6,FALSE)),0,(VLOOKUP(A21,FY2011_12P,6,FALSE))))) -> 0 | N21: =IF(B21="Excluded",0,(IF(ISNA(VLOOKUP(A21,FY2012_13P,6,FALSE)),0,(VLOOKUP(A21,FY2012_13P,6,FALSE))))) -> 0 | O21: =(AVERAGE(G21:I21)*0.75)+(AVERAGE(L21:N21)*0.25) -> 0 | P21: =(AVERAGE(E21:G21)*0.75)+(AVERAGE(J21:L21)*0.25) -> 0 | R21: =S21-Q21 -> 0 | S21: =ROUND((P21*'Cost Pool'!$C$25),0) -> 0 | U21: =V21-T21 -> 0 | V21: =ROUND((O21*'Cost Pool'!$D$25),0) -> 0 | W21: =V21+R21 -> 0
A22: 100-PW | B22: =VLOOKUP(A22,Crosswalk,2,FALSE) -> 100-PW | C22: =CONCATENATE((LEFT(B22,3))," - ",(VLOOKUP((LEFT(B22,3)),Funds,2,FALSE))) -> 100 - General Fund | D22: =VLOOKUP((RIGHT(B22,2)),Bureaus,2,FALSE) -> Commissioner of Public Works | E22: =IF(B22="Excluded",0,(IF(ISNA(VLOOKUP(A22,FY2008_09,10,FALSE)),0,(VLOOKUP(A22,FY2008_09,10,FALSE))))) -> 0 | F22: =IF(B22="Excluded",0,(IF(ISNA(VLOOKUP(A22,FY2009_10,10,FALSE)),0,(VLOOKUP(A22,FY2009_10,10,FALSE))))) -> 0 | G22: =IF(B22="Excluded",0,(IF(ISNA(VLOOKUP(A22,FY2010_11,10,FALSE)),0,(VLOOKUP(A22,FY2010_11,10,FALSE))))) -> 0 | H22: =IF(B22="Excluded",0,(IF(ISNA(VLOOKUP(A22,FY2011_12,10,FALSE)),0,(VLOOKUP(A22,FY2011_12,10,FALSE))))) -> 0 | I22: =IF(B22="Excluded",0,(IF(ISNA(VLOOKUP(A22,FY2012_13,10,FALSE)),0,(VLOOKUP(A22,FY2012_13,10,FALSE))))) -> 0 | J22: =IF(B22="Excluded",0,(IF(ISNA(VLOOKUP(A22,FY2008_09P,6,FALSE)),0,(VLOOKUP(A22,FY2008_09P,6,FALSE))))) -> 0 | K22: =IF(B22="Excluded",0,(IF(ISNA(VLOOKUP(A22,FY2009_10P,6,FALSE)),0,(VLOOKUP(A22,FY2009_10P,6,FALSE))))) -> 0 | L22: =IF(B22="Excluded",0,(IF(ISNA(VLOOKUP(A22,FY2010_11P,6,FALSE)),0,(VLOOKUP(A22,FY2010_11P,6,FALSE))))) -> 0 | M22: =IF(B22="Excluded",0,(IF(ISNA(VLOOKUP(A22,FY2011_12P,6,FALSE)),0,(VLOOKUP(A22,FY2011_12P,6,FALSE))))) -> 0 | N22: =IF(B22="Excluded",0,(IF(ISNA(VLOOKUP(A22,FY2012_13P,6,FALSE)),0,(VLOOKUP(A22,FY2012_13P,6,FALSE))))) -> 0 | O22: =(AVERAGE(G22:I22)*0.75)+(AVERAGE(L22:N22)*0.25) -> 0 | P22: =(AVERAGE(E22:G22)*0.75)+(AVERAGE(J22:L22)*0.25) -> 0 | R22: =S22-Q22 -> 0 | S22: =ROUND((P22*'Cost Pool'!$C$25),0) -> 0 | U22: =V22-T22 -> 0 | V22: =ROUND((O22*'Cost Pool'!$D$25),0) -> 0 | W22: =V22+R22 -> 0
A23: 100-SA | B23: =VLOOKUP(A23,Crosswalk,2,FALSE) -> 100-SA | C23: =CONCATENATE((LEFT(B23,3))," - ",(VLOOKUP((LEFT(B23,3)),Funds,2,FALSE))) -> 100 - General Fund | D23: =VLOOKUP((RIGHT(B23,2)),Bureaus,2,FALSE) -> Special Appropriations | E23: =IF(B23="Excluded",0,(IF(ISNA(VLOOKUP(A23,FY2008_09,10,FALSE)),0,(VLOOKUP(A23,FY2008_09,10,FALSE))))) -> 0.013632242 | F23: =IF(B23="Excluded",0,(IF(ISNA(VLOOKUP(A23,FY2009_10,10,FALSE)),0,(VLOOKUP(A23,FY2009_10,10,FALSE))))) -> 0.0079987576 | G23: =IF(B23="Excluded",0,(IF(ISNA(VLOOKUP(A23,FY2010_11,10,FALSE)),0,(VLOOKUP(A23,FY2010_11,10,FALSE))))) -> 0.0068913073 | H23: =IF(B23="Excluded",0,(IF(ISNA(VLOOKUP(A23,FY2011_12,10,FALSE)),0,(VLOOKUP(A23,FY2011_12,10,FALSE))))) -> 0.009156456 | I23: =IF(B23="Excluded",0,(IF(ISNA(VLOOKUP(A23,FY2012_13,10,FALSE)),0,(VLOOKUP(A23,FY2012_13,10,FALSE))))) -> 0.014089506 | J23: =IF(B23="Excluded",0,(IF(ISNA(VLOOKUP(A23,FY2008_09P,6,FALSE)),0,(VLOOKUP(A23,FY2008_09P,6,FALSE))))) -> 0 | K23: =IF(B23="Excluded",0,(IF(ISNA(VLOOKUP(A23,FY2009_10P,6,FALSE)),0,(VLOOKUP(A23,FY2009_10P,6,FALSE))))) -> 0 | L23: =IF(B23="Excluded",0,(IF(ISNA(VLOOKUP(A23,FY2010_11P,6,FALSE)),0,(VLOOKUP(A23,FY2010_11P,6,FALSE))))) -> 0 | M23: =IF(B23="Excluded",0,(IF(ISNA(VLOOKUP(A23,FY2011_12P,6,FALSE)),0,(VLOOKUP(A23,FY2011_12P,6,FALSE))))) -> 0 | N23: =IF(B23="Excluded",0,(IF(ISNA(VLOOKUP(A23,FY2012_13P,6,FALSE)),0,(VLOOKUP(A23,FY2012_13P,6,FALSE))))) -> 0 | O23: =(AVERAGE(G23:I23)*0.75)+(AVERAGE(L23:N23)*0.25) -> 0.0075343173 | P23: =(AVERAGE(E23:G23)*0.75)+(AVERAGE(J23:L23)*0.25) -> 0.0071305767 | R23: =S23-Q23 -> 289131 | S23: =ROUND((P23*'Cost Pool'!$C$25),0) -> 289131 | T23: 269857 | U23: =V23-T23 -> 75818 | V23: =ROUND((O23*'Cost Pool'!$D$25),0) -> 345675 | W23: =V23+R23 -> 634806
A24: 100-SD | B24: =VLOOKUP(A24,Crosswalk,2,FALSE) -> 100-PN | C24: =CONCATENATE((LEFT(B24,3))," - ",(VLOOKUP((LEFT(B24,3)),Funds,2,FALSE))) -> 100 - General Fund | D24: =VLOOKUP((RIGHT(B24,2)),Bureaus,2,FALSE) -> Bureau of Planning & Sustainability | E24: =IF(B24="Excluded",0,(IF(ISNA(VLOOKUP(A24,FY2008_09,10,FALSE)),0,(VLOOKUP(A24,FY2008_09,10,FALSE))))) -> 0.0030128132 | F24: =IF(B24="Excluded",0,(IF(ISNA(VLOOKUP(A24,FY2009_10,10,FALSE)),0,(VLOOKUP(A24,FY2009_10,10,FALSE))))) -> 0 | G24: =IF(B24="Excluded",0,(IF(ISNA(VLOOKUP(A24,FY2010_11,10,FALSE)),0,(VLOOKUP(A24,FY2010_11,10,FALSE))))) -> 0 | H24: =IF(B24="Excluded",0,(IF(ISNA(VLOOKUP(A24,FY2011_12,10,FALSE)),0,(VLOOKUP(A24,FY2011_12,10,FALSE))))) -> 0 | I24: =IF(B24="Excluded",0,(IF(ISNA(VLOOKUP(A24,FY2012_13,10,FALSE)),0,(VLOOKUP(A24,FY2012_13,10,FALSE))))) -> 0 | J24: =IF(B24="Excluded",0,(IF(ISNA(VLOOKUP(A24,FY2008_09P,6,FALSE)),0,(VLOOKUP(A24,FY2008_09P,6,FALSE))))) -> 0.0035691523 | K24: =IF(B24="Excluded",0,(IF(ISNA(VLOOKUP(A24,FY2009_10P,6,FALSE)),0,(VLOOKUP(A24,FY2009_10P,6,FALSE))))) -> 0 | L24: =IF(B24="Excluded",0,(IF(ISNA(VLOOKUP(A24,FY2010_11P,6,FALSE)),0,(VLOOKUP(A24,FY2010_11P,6,FALSE))))) -> 0 | M24: =IF(B24="Excluded",0,(IF(ISNA(VLOOKUP(A24,FY2011_12P,6,FALSE)),0,(VLOOKUP(A24,FY2011_12P,6,FALSE))))) -> 0 | N24: =IF(B24="Excluded",0,(IF(ISNA(VLOOKUP(A24,FY2012_13P,6,FALSE)),0,(VLOOKUP(A24,FY2012_13P,6,FALSE))))) -> 0 | O24: =(AVERAGE(G24:I24)*0.75)+(AVERAGE(L24:N24)*0.25) -> 0 | P24: =(AVERAGE(E24:G24)*0.75)+(AVERAGE(J24:L24)*0.25) -> 0.0010506327 | R24: =S24-Q24 -> 42601 | S24: =ROUND((P24*'Cost Pool'!$C$25),0) -> 42601 | U24: =V24-T24 -> 0 | V24: =ROUND((O24*'Cost Pool'!$D$25),0) -> 0 | W24: =V24+R24 -> 42601
A25: 100-ZD | B25: =VLOOKUP(A25,Crosswalk,2,FALSE) -> PDC | C25: =CONCATENATE((LEFT(B25,3))," - ",(VLOOKUP((LEFT(B25,3)),Funds,2,FALSE))) -> PDC - Portland Development Commission | D25: =VLOOKUP((RIGHT(B25,2)),Bureaus,2,FALSE) -> #N/A | E25: =IF(B25="Excluded",0,(IF(ISNA(VLOOKUP(A25,FY2008_09,10,FALSE)),0,(VLOOKUP(A25,FY2008_09,10,FALSE))))) -> 0 | F25: =IF(B25="Excluded",0,(IF(ISNA(VLOOKUP(A25,FY2009_10,10,FALSE)),0,(VLOOKUP(A25,FY2009_10,10,FALSE))))) -> 0.0069937688 | G25: =IF(B25="Excluded",0,(IF(ISNA(VLOOKUP(A25,FY2010_11,10,FALSE)),0,(VLOOKUP(A25,FY2010_11,10,FALSE))))) -> 0.0041964137 | H25: =IF(B25="Excluded",0,(IF(ISNA(VLOOKUP(A25,FY2011_12,10,FALSE)),0,(VLOOKUP(A25,FY2011_12,10,FALSE))))) -> 0.0053166192 | I25: =IF(B25="Excluded",0,(IF(ISNA(VLOOKUP(A25,FY2012_13,10,FALSE)),0,(VLOOKUP(A25,FY2012_13,10,FALSE))))) -> 0.0064587168 | J25: =IF(B25="Excluded",0,(IF(ISNA(VLOOKUP(A25,FY2008_09P,6,FALSE)),0,(VLOOKUP(A25,FY2008_09P,6,FALSE))))) -> 0 | K25: =IF(B25="Excluded",0,(IF(ISNA(VLOOKUP(A25,FY2009_10P,6,FALSE)),0,(VLOOKUP(A25,FY2009_10P,6,FALSE))))) -> 0 | L25: =IF(B25="Excluded",0,(IF(ISNA(VLOOKUP(A25,FY2010_11P,6,FALSE)),0,(VLOOKUP(A25,FY2010_11P,6,FALSE))))) -> 0 | M25: =IF(B25="Excluded",0,(IF(ISNA(VLOOKUP(A25,FY2011_12P,6,FALSE)),0,(VLOOKUP(A25,FY2011_12P,6,FALSE))))) -> 0 | N25: =IF(B25="Excluded",0,(IF(ISNA(VLOOKUP(A25,FY2012_13P,6,FALSE)),0,(VLOOKUP(A25,FY2012_13P,6,FALSE))))) -> 0 | O25: =(AVERAGE(G25:I25)*0.75)+(AVERAGE(L25:N25)*0.25) -> 0.0039929374 | P25: =(AVERAGE(E25:G25)*0.75)+(AVERAGE(J25:L25)*0.25) -> 0.0027975456 | Q25: 126913 | R25: =S25-Q25 -> -13478 | S25: =ROUND((P25*'Cost Pool'!$C$25),0) -> 113435 | T25: 146823 | U25: =V25-T25 -> 36373 | V25: =ROUND((O25*'Cost Pool'!$D$25),0) -> 183196 | W25: =V25+R25 -> 169718
A26: 200-TR | B26: =VLOOKUP(A26,Crosswalk,2,FALSE) -> 200 | C26: =CONCATENATE((LEFT(B26,3))," - ",(VLOOKUP((LEFT(B26,3)),Funds,2,FALSE))) -> 200 - Transportation Operating Fund | D26: =VLOOKUP((RIGHT(B26,2)),Bureaus,2,FALSE) -> #N/A | E26: =IF(B26="Excluded",0,(IF(ISNA(VLOOKUP(A26,FY2008_09,10,FALSE)),0,(VLOOKUP(A26,FY2008_09,10,FALSE))))) -> 0.10596635 | F26: =IF(B26="Excluded",0,(IF(ISNA(VLOOKUP(A26,FY2009_10,10,FALSE)),0,(VLOOKUP(A26,FY2009_10,10,FALSE))))) -> 0.11291081 | G26: =IF(B26="Excluded",0,(IF(ISNA(VLOOKUP(A26,FY2010_11,10,FALSE)),0,(VLOOKUP(A26,FY2010_11,10,FALSE))))) -> 0.11137921 | H26: =IF(B26="Excluded",0,(IF(ISNA(VLOOKUP(A26,FY2011_12,10,FALSE)),0,(VLOOKUP(A26,FY2011_12,10,FALSE))))) -> 0.10835876 | I26: =IF(B26="Excluded",0,(IF(ISNA(VLOOKUP(A26,FY2012_13,10,FALSE)),0,(VLOOKUP(A26,FY2012_13,10,FALSE))))) -> 0.12633395 | J26: =IF(B26="Excluded",0,(IF(ISNA(VLOOKUP(A26,FY2008_09P,6,FALSE)),0,(VLOOKUP(A26,FY2008_09P,6,FALSE))))) -> 0.10184831 | K26: =IF(B26="Excluded",0,(IF(ISNA(VLOOKUP(A26,FY2009_10P,6,FALSE)),0,(VLOOKUP(A26,FY2009_10P,6,FALSE))))) -> 0.093734704 | L26: =IF(B26="Excluded",0,(IF(ISNA(VLOOKUP(A26,FY2010_11P,6,FALSE)),0,(VLOOKUP(A26,FY2010_11P,6,FALSE))))) -> 0.097116653 | M26: =IF(B26="Excluded",0,(IF(ISNA(VLOOKUP(A26,FY2011_12P,6,FALSE)),0,(VLOOKUP(A26,FY2011_12P,6,FALSE))))) -> 0.094884739 | N26: =IF(B26="Excluded",0,(IF(ISNA(VLOOKUP(A26,FY2012_13P,6,FALSE)),0,(VLOOKUP(A26,FY2012_13P,6,FALSE))))) -> 0.086038683 | O26: =(AVERAGE(G26:I26)*0.75)+(AVERAGE(L26:N26)*0.25) -> 0.10968799 | P26: =(AVERAGE(E26:G26)*0.75)+(AVERAGE(J26:L26)*0.25) -> 0.10695573 | Q26: 5760647 | R26: =S26-Q26 -> -1423798 | S26: =ROUND((P26*'Cost Pool'!$C$25),0) -> 4336849 | T26: 6564665 | U26: =V26-T26 -> -1532171 | V26: =ROUND((O26*'Cost Pool'!$D$25),0) -> 5032494 | W26: =V26+R26 -> 3608696
A27: 201-AU | B27: =VLOOKUP(A27,Crosswalk,2,FALSE) -> 201 | C27: =CONCATENATE((LEFT(B27,3))," - ",(VLOOKUP((LEFT(B27,3)),Funds,2,FALSE))) -> 201 - Assessment Collection Fund | D27: =VLOOKUP((RIGHT(B27,2)),Bureaus,2,FALSE) -> #N/A | E27: =IF(B27="Excluded",0,(IF(ISNA(VLOOKUP(A27,FY2008_09,10,FALSE)),0,(VLOOKUP(A27,FY2008_09,10,FALSE))))) -> 0 | F27: =IF(B27="Excluded",0,(IF(ISNA(VLOOKUP(A27,FY2009_10,10,FALSE)),0,(VLOOKUP(A27,FY2009_10,10,FALSE))))) -> 0 | G27: =IF(B27="Excluded",0,(IF(ISNA(VLOOKUP(A27,FY2010_11,10,FALSE)),0,(VLOOKUP(A27,FY2010_11,10,FALSE))))) -> 0 | H27: =IF(B27="Excluded",0,(IF(ISNA(VLOOKUP(A27,FY2011_12,10,FALSE)),0,(VLOOKUP(A27,FY2011_12,10,FALSE))))) -> 0 | I27: =IF(B27="Excluded",0,(IF(ISNA(VLOOKUP(A27,FY2012_13,10,FALSE)),0,(VLOOKUP(A27,FY2012_13,10,FALSE))))) -> 0 | J27: =IF(B27="Excluded",0,(IF(ISNA(VLOOKUP(A27,FY2008_09P,6,FALSE)),0,(VLOOKUP(A27,FY2008_09P,6,FALSE))))) -> 0 | K27: =IF(B27="Excluded",0,(IF(ISNA(VLOOKUP(A27,FY2009_10P,6,FALSE)),0,(VLOOKUP(A27,FY2009_10P,6,FALSE))))) -> 0 | L27: =IF(B27="Excluded",0,(IF(ISNA(VLOOKUP(A27,FY2010_11P,6,FALSE)),0,(VLOOKUP(A27,FY2010_11P,6,FALSE))))) -> 0 | M27: =IF(B27="Excluded",0,(IF(ISNA(VLOOKUP(A27,FY2011_12P,6,FALSE)),0,(VLOOKUP(A27,FY2011_12P,6,FALSE))))) -> 0 | N27: =IF(B27="Excluded",0,(IF(ISNA(VLOOKUP(A27,FY2012_13P,6,FALSE)),0,(VLOOKUP(A27,FY2012_13P,6,FALSE))))) -> 0 | O27: =(AVERAGE(G27:I27)*0.75)+(AVERAGE(L27:N27)*0.25) -> 0 | P27: =(AVERAGE(E27:G27)*0.75)+(AVERAGE(J27:L27)*0.25) -> 0 | Q27: 14 | R27: =S27-Q27 -> -14 | S27: =ROUND((P27*'Cost Pool'!$C$25),0) -> 0 | T27: 12 | U27: =V27-T27 -> -12 | V27: =ROUND((O27*'Cost Pool'!$D$25),0) -> 0 | W27: =V27+R27 -> -14
A28: 202-EC | B28: =VLOOKUP(A28,Crosswalk,2,FALSE) -> 202 | C28: =CONCATENATE((LEFT(B28,3))," - ",(VLOOKUP((LEFT(B28,3)),Funds,2,FALSE))) -> 202 - Emergency Communication Fund | D28: =VLOOKUP((RIGHT(B28,2)),Bureaus,2,FALSE) -> #N/A | E28: =IF(B28="Excluded",0,(IF(ISNA(VLOOKUP(A28,FY2008_09,10,FALSE)),0,(VLOOKUP(A28,FY2008_09,10,FALSE))))) -> 0.015096047 | F28: =IF(B28="Excluded",0,(IF(ISNA(VLOOKUP(A28,FY2009_10,10,FALSE)),0,(VLOOKUP(A28,FY2009_10,10,FALSE))))) -> 0.015061403 | G28: =IF(B28="Excluded",0,(IF(ISNA(VLOOKUP(A28,FY2010_11,10,FALSE)),0,(VLOOKUP(A28,FY2010_11,10,FALSE))))) -> 0.014385446 | H28: =IF(B28="Excluded",0,(IF(ISNA(VLOOKUP(A28,FY2011_12,10,FALSE)),0,(VLOOKUP(A28,FY2011_12,10,FALSE))))) -> 0.015384301 | I28: =IF(B28="Excluded",0,(IF(ISNA(VLOOKUP(A28,FY2012_13,10,FALSE)),0,(VLOOKUP(A28,FY2012_13,10,FALSE))))) -> 0.014987205 | J28: =IF(B28="Excluded",0,(IF(ISNA(VLOOKUP(A28,FY2008_09P,6,FALSE)),0,(VLOOKUP(A28,FY2008_09P,6,FALSE))))) -> 0.019120459 | K28: =IF(B28="Excluded",0,(IF(ISNA(VLOOKUP(A28,FY2009_10P,6,FALSE)),0,(VLOOKUP(A28,FY2009_10P,6,FALSE))))) -> 0.018844836 | L28: =IF(B28="Excluded",0,(IF(ISNA(VLOOKUP(A28,FY2010_11P,6,FALSE)),0,(VLOOKUP(A28,FY2010_11P,6,FALSE))))) -> 0.018971041 | M28: =IF(B28="Excluded",0,(IF(ISNA(VLOOKUP(A28,FY2011_12P,6,FALSE)),0,(VLOOKUP(A28,FY2011_12P,6,FALSE))))) -> 0.017760477 | N28: =IF(B28="Excluded",0,(IF(ISNA(VLOOKUP(A28,FY2012_13P,6,FALSE)),0,(VLOOKUP(A28,FY2012_13P,6,FALSE))))) -> 0.016317681 | O28: =(AVERAGE(G28:I28)*0.75)+(AVERAGE(L28:N28)*0.25) -> 0.015610005 | P28: =(AVERAGE(E28:G28)*0.75)+(AVERAGE(J28:L28)*0.25) -> 0.015880419 | Q28: 785607 | R28: =S28-Q28 -> -141687 | S28: =ROUND((P28*'Cost Pool'!$C$25),0) -> 643920 | T28: 877412 | U28: =V28-T28 -> -161224 | V28: =ROUND((O28*'Cost Pool'!$D$25),0) -> 716188 | W28: =V28+R28 -> 574501
A29: 202-MF | B29: =VLOOKUP(A29,Crosswalk,2,FALSE) -> 202 | C29: =CONCATENATE((LEFT(B29,3))," - ",(VLOOKUP((LEFT(B29,3)),Funds,2,FALSE))) -> 202 - Emergency Communication Fund | D29: =VLOOKUP((RIGHT(B29,2)),Bureaus,2,FALSE) -> #N/A | E29: =IF(B29="Excluded",0,(IF(ISNA(VLOOKUP(A29,FY2008_09,10,FALSE)),0,(VLOOKUP(A29,FY2008_09,10,FALSE))))) -> 0.00013500757 | F29: =IF(B29="Excluded",0,(IF(ISNA(VLOOKUP(A29,FY2009_10,10,FALSE)),0,(VLOOKUP(A29,FY2009_10,10,FALSE))))) -> 0.0020342999 | G29: =IF(B29="Excluded",0,(IF(ISNA(VLOOKUP(A29,FY2010_11,10,FALSE)),0,(VLOOKUP(A29,FY2010_11,10,FALSE))))) -> 0.0025591922 | H29: =IF(B29="Excluded",0,(IF(ISNA(VLOOKUP(A29,FY2011_12,10,FALSE)),0,(VLOOKUP(A29,FY2011_12,10,FALSE))))) -> 0.00017401543 | I29: =IF(B29="Excluded",0,(IF(ISNA(VLOOKUP(A29,FY2012_13,10,FALSE)),0,(VLOOKUP(A29,FY2012_13,10,FALSE))))) -> 1.0510384e-05 | J29: =IF(B29="Excluded",0,(IF(ISNA(VLOOKUP(A29,FY2008_09P,6,FALSE)),0,(VLOOKUP(A29,FY2008_09P,6,FALSE))))) -> 0 | K29: =IF(B29="Excluded",0,(IF(ISNA(VLOOKUP(A29,FY2009_10P,6,FALSE)),0,(VLOOKUP(A29,FY2009_10P,6,FALSE))))) -> 0 | L29: =IF(B29="Excluded",0,(IF(ISNA(VLOOKUP(A29,FY2010_11P,6,FALSE)),0,(VLOOKUP(A29,FY2010_11P,6,FALSE))))) -> 0 | M29: =IF(B29="Excluded",0,(IF(ISNA(VLOOKUP(A29,FY2011_12P,6,FALSE)),0,(VLOOKUP(A29,FY2011_12P,6,FALSE))))) -> 0 | N29: =IF(B29="Excluded",0,(IF(ISNA(VLOOKUP(A29,FY2012_13P,6,FALSE)),0,(VLOOKUP(A29,FY2012_13P,6,FALSE))))) -> 0 | O29: =(AVERAGE(G29:I29)*0.75)+(AVERAGE(L29:N29)*0.25) -> 0.0006859295 | P29: =(AVERAGE(E29:G29)*0.75)+(AVERAGE(J29:L29)*0.25) -> 0.0011821249 | R29: =S29-Q29 -> 47933 | S29: =ROUND((P29*'Cost Pool'!$C$25),0) -> 47933 | U29: =V29-T29 -> 31471 | V29: =ROUND((O29*'Cost Pool'!$D$25),0) -> 31471 | W29: =V29+R29 -> 79404
A30: 203-DS | B30: =VLOOKUP(A30,Crosswalk,2,FALSE) -> 203 | C30: =CONCATENATE((LEFT(B30,3))," - ",(VLOOKUP((LEFT(B30,3)),Funds,2,FALSE))) -> 203 - Development Services Fund | D30: =VLOOKUP((RIGHT(B30,2)),Bureaus,2,FALSE) -> #N/A | E30: =IF(B30="Excluded",0,(IF(ISNA(VLOOKUP(A30,FY2008_09,10,FALSE)),0,(VLOOKUP(A30,FY2008_09,10,FALSE))))) -> 0.036798226 | F30: =IF(B30="Excluded",0,(IF(ISNA(VLOOKUP(A30,FY2009_10,10,FALSE)),0,(VLOOKUP(A30,FY2009_10,10,FALSE))))) -> 0.022244936 | G30: =IF(B30="Excluded",0,(IF(ISNA(VLOOKUP(A30,FY2010_11,10,FALSE)),0,(VLOOKUP(A30,FY2010_11,10,FALSE))))) -> 0.017730271 | H30: =IF(B30="Excluded",0,(IF(ISNA(VLOOKUP(A30,FY2011_12,10,FALSE)),0,(VLOOKUP(A30,FY2011_12,10,FALSE))))) -> 0.021407969 | I30: =IF(B30="Excluded",0,(IF(ISNA(VLOOKUP(A30,FY2012_13,10,FALSE)),0,(VLOOKUP(A30,FY2012_13,10,FALSE))))) -> 0.023347979 | J30: =IF(B30="Excluded",0,(IF(ISNA(VLOOKUP(A30,FY2008_09P,6,FALSE)),0,(VLOOKUP(A30,FY2008_09P,6,FALSE))))) -> 0.047418738 | K30: =IF(B30="Excluded",0,(IF(ISNA(VLOOKUP(A30,FY2009_10P,6,FALSE)),0,(VLOOKUP(A30,FY2009_10P,6,FALSE))))) -> 0.038056779 | L30: =IF(B30="Excluded",0,(IF(ISNA(VLOOKUP(A30,FY2010_11P,6,FALSE)),0,(VLOOKUP(A30,FY2010_11P,6,FALSE))))) -> 0.021358126 | M30: =IF(B30="Excluded",0,(IF(ISNA(VLOOKUP(A30,FY2011_12P,6,FALSE)),0,(VLOOKUP(A30,FY2011_12P,6,FALSE))))) -> 0.022748008 | N30: =IF(B30="Excluded",0,(IF(ISNA(VLOOKUP(A30,FY2012_13P,6,FALSE)),0,(VLOOKUP(A30,FY2012_13P,6,FALSE))))) -> 0.024419467 | O30: =(AVERAGE(G30:I30)*0.75)+(AVERAGE(L30:N30)*0.25) -> 0.021332021 | P30: =(AVERAGE(E30:G30)*0.75)+(AVERAGE(J30:L30)*0.25) -> 0.028096162 | Q30: 1092926 | R30: =S30-Q30 -> 46319 | S30: =ROUND((P30*'Cost Pool'!$C$25),0) -> 1139245 | T30: 1044982 | U30: =V30-T30 -> -66267 | V30: =ROUND((O30*'Cost Pool'!$D$25),0) -> 978715 | W30: =V30+R30 -> 1025034
A31: 204-MF | B31: =VLOOKUP(A31,Crosswalk,2,FALSE) -> 204 | C31: =CONCATENATE((LEFT(B31,3))," - ",(VLOOKUP((LEFT(B31,3)),Funds,2,FALSE))) -> 204 - Property Management License Fund | D31: =VLOOKUP((RIGHT(B31,2)),Bureaus,2,FALSE) -> #N/A | E31: =IF(B31="Excluded",0,(IF(ISNA(VLOOKUP(A31,FY2008_09,10,FALSE)),0,(VLOOKUP(A31,FY2008_09,10,FALSE))))) -> 0 | F31: =IF(B31="Excluded",0,(IF(ISNA(VLOOKUP(A31,FY2009_10,10,FALSE)),0,(VLOOKUP(A31,FY2009_10,10,FALSE))))) -> 0 | G31: =IF(B31="Excluded",0,(IF(ISNA(VLOOKUP(A31,FY2010_11,10,FALSE)),0,(VLOOKUP(A31,FY2010_11,10,FALSE))))) -> 0 | H31: =IF(B31="Excluded",0,(IF(ISNA(VLOOKUP(A31,FY2011_12,10,FALSE)),0,(VLOOKUP(A31,FY2011_12,10,FALSE))))) -> 0 | I31: =IF(B31="Excluded",0,(IF(ISNA(VLOOKUP(A31,FY2012_13,10,FALSE)),0,(VLOOKUP(A31,FY2012_13,10,FALSE))))) -> 0 | J31: =IF(B31="Excluded",0,(IF(ISNA(VLOOKUP(A31,FY2008_09P,6,FALSE)),0,(VLOOKUP(A31,FY2008_09P,6,FALSE))))) -> 0 | K31: =IF(B31="Excluded",0,(IF(ISNA(VLOOKUP(A31,FY2009_10P,6,FALSE)),0,(VLOOKUP(A31,FY2009_10P,6,FALSE))))) -> 0 | L31: =IF(B31="Excluded",0,(IF(ISNA(VLOOKUP(A31,FY2010_11P,6,FALSE)),0,(VLOOKUP(A31,FY2010_11P,6,FALSE))))) -> 0 | M31: =IF(B31="Excluded",0,(IF(ISNA(VLOOKUP(A31,FY2011_12P,6,FALSE)),0,(VLOOKUP(A31,FY2011_12P,6,FALSE))))) -> 0 | N31: =IF(B31="Excluded",0,(IF(ISNA(VLOOKUP(A31,FY2012_13P,6,FALSE)),0,(VLOOKUP(A31,FY2012_13P,6,FALSE))))) -> 0 | O31: =(AVERAGE(G31:I31)*0.75)+(AVERAGE(L31:N31)*0.25) -> 0 | P31: =(AVERAGE(E31:G31)*0.75)+(AVERAGE(J31:L31)*0.25) -> 0 | R31: =S31-Q31 -> 0 | S31: =ROUND((P31*'Cost Pool'!$C$25),0) -> 0 | T31: 0 | U31: =V31-T31 -> 25000 | V31: 25000 | W31: 25000
A32: 206-CB | B32: =VLOOKUP(A32,Crosswalk,2,FALSE) -> 206-MF | C32: =CONCATENATE((LEFT(B32,3))," - ",(VLOOKUP((LEFT(B32,3)),Funds,2,FALSE))) -> 206 - MHCRC Agency Fund | D32: =VLOOKUP((RIGHT(B32,2)),Bureaus,2,FALSE) -> Office of Management & Finance | E32: =IF(B32="Excluded",0,(IF(ISNA(VLOOKUP(A32,FY2008_09,10,FALSE)),0,(VLOOKUP(A32,FY2008_09,10,FALSE))))) -> 0 | F32: =IF(B32="Excluded",0,(IF(ISNA(VLOOKUP(A32,FY2009_10,10,FALSE)),0,(VLOOKUP(A32,FY2009_10,10,FALSE))))) -> 0 | G32: =IF(B32="Excluded",0,(IF(ISNA(VLOOKUP(A32,FY2010_11,10,FALSE)),0,(VLOOKUP(A32,FY2010_11,10,FALSE))))) -> 0 | H32: =IF(B32="Excluded",0,(IF(ISNA(VLOOKUP(A32,FY2011_12,10,FALSE)),0,(VLOOKUP(A32,FY2011_12,10,FALSE))))) -> 0 | I32: =IF(B32="Excluded",0,(IF(ISNA(VLOOKUP(A32,FY2012_13,10,FALSE)),0,(VLOOKUP(A32,FY2012_13,10,FALSE))))) -> 0 | J32: =IF(B32="Excluded",0,(IF(ISNA(VLOOKUP(A32,FY2008_09P,6,FALSE)),0,(VLOOKUP(A32,FY2008_09P,6,FALSE))))) -> 0 | K32: =IF(B32="Excluded",0,(IF(ISNA(VLOOKUP(A32,FY2009_10P,6,FALSE)),0,(VLOOKUP(A32,FY2009_10P,6,FALSE))))) -> 0 | L32: =IF(B32="Excluded",0,(IF(ISNA(VLOOKUP(A32,FY2010_11P,6,FALSE)),0,(VLOOKUP(A32,FY2010_11P,6,FALSE))))) -> 0 | M32: =IF(B32="Excluded",0,(IF(ISNA(VLOOKUP(A32,FY2011_12P,6,FALSE)),0,(VLOOKUP(A32,FY2011_12P,6,FALSE))))) -> 0 | N32: =IF(B32="Excluded",0,(IF(ISNA(VLOOKUP(A32,FY2012_13P,6,FALSE)),0,(VLOOKUP(A32,FY2012_13P,6,FALSE))))) -> 0 | O32: =(AVERAGE(G32:I32)*0.75)+(AVERAGE(L32:N32)*0.25) -> 0 | P32: =(AVERAGE(E32:G32)*0.75)+(AVERAGE(J32:L32)*0.25) -> 0 | Q32: 0 | R32: =S32-Q32 -> 0 | S32: =ROUND((P32*'Cost Pool'!$C$25),0) -> 0 | T32: 0 | U32: =V32-T32 -> 25000 | V32: 25000 | W32: 25000
A33: 209-MF | B33: =VLOOKUP(A33,Crosswalk,2,FALSE) -> 209 | C33: =CONCATENATE((LEFT(B33,3))," - ",(VLOOKUP((LEFT(B33,3)),Funds,2,FALSE))) -> 209 - Convention and Tourism Fund | D33: =VLOOKUP((RIGHT(B33,2)),Bureaus,2,FALSE) -> #N/A | E33: =IF(B33="Excluded",0,(IF(ISNA(VLOOKUP(A33,FY2008_09,10,FALSE)),0,(VLOOKUP(A33,FY2008_09,10,FALSE))))) -> 0 | F33: =IF(B33="Excluded",0,(IF(ISNA(VLOOKUP(A33,FY2009_10,10,FALSE)),0,(VLOOKUP(A33,FY2009_10,10,FALSE))))) -> 0 | G33: =IF(B33="Excluded",0,(IF(ISNA(VLOOKUP(A33,FY2010_11,10,FALSE)),0,(VLOOKUP(A33,FY2010_11,10,FALSE))))) -> 0 | H33: =IF(B33="Excluded",0,(IF(ISNA(VLOOKUP(A33,FY2011_12,10,FALSE)),0,(VLOOKUP(A33,FY2011_12,10,FALSE))))) -> 0 | I33: =IF(B33="Excluded",0,(IF(ISNA(VLOOKUP(A33,FY2012_13,10,FALSE)),0,(VLOOKUP(A33,FY2012_13,10,FALSE))))) -> 0 | J33: =IF(B33="Excluded",0,(IF(ISNA(VLOOKUP(A33,FY2008_09P,6,FALSE)),0,(VLOOKUP(A33,FY2008_09P,6,FALSE))))) -> 0 | K33: =IF(B33="Excluded",0,(IF(ISNA(VLOOKUP(A33,FY2009_10P,6,FALSE)),0,(VLOOKUP(A33,FY2009_10P,6,FALSE))))) -> 0 | L33: =IF(B33="Excluded",0,(IF(ISNA(VLOOKUP(A33,FY2010_11P,6,FALSE)),0,(VLOOKUP(A33,FY2010_11P,6,FALSE))))) -> 0 | M33: =IF(B33="Excluded",0,(IF(ISNA(VLOOKUP(A33,FY2011_12P,6,FALSE)),0,(VLOOKUP(A33,FY2011_12P,6,FALSE))))) -> 0 | N33: =IF(B33="Excluded",0,(IF(ISNA(VLOOKUP(A33,FY2012_13P,6,FALSE)),0,(VLOOKUP(A33,FY2012_13P,6,FALSE))))) -> 0 | O33: =(AVERAGE(G33:I33)*0.75)+(AVERAGE(L33:N33)*0.25) -> 0 | P33: =(AVERAGE(E33:G33)*0.75)+(AVERAGE(J33:L33)*0.25) -> 0 | Q33: 0 | R33: =S33-Q33 -> 0 | S33: =ROUND((P33*'Cost Pool'!$C$25),0) -> 0 | T33: 56826 | U33: =V33-T33 -> -31826 | V33: 25000 | W33: 25000
A34: 211-FM | B34: =VLOOKUP(A34,Crosswalk,2,FALSE) -> Excluded | C34: =CONCATENATE((LEFT(B34,3))," - ",(VLOOKUP((LEFT(B34,3)),Funds,2,FALSE))) -> #N/A | D34: =VLOOKUP((RIGHT(B34,2)),Bureaus,2,FALSE) -> #N/A | E34: =IF(B34="Excluded",0,(IF(ISNA(VLOOKUP(A34,FY2008_09,10,FALSE)),0,(VLOOKUP(A34,FY2008_09,10,FALSE))))) -> 0 | F34: =IF(B34="Excluded",0,(IF(ISNA(VLOOKUP(A34,FY2009_10,10,FALSE)),0,(VLOOKUP(A34,FY2009_10,10,FALSE))))) -> 0 | G34: =IF(B34="Excluded",0,(IF(ISNA(VLOOKUP(A34,FY2010_11,10,FALSE)),0,(VLOOKUP(A34,FY2010_11,10,FALSE))))) -> 0 | H34: =IF(B34="Excluded",0,(IF(ISNA(VLOOKUP(A34,FY2011_12,10,FALSE)),0,(VLOOKUP(A34,FY2011_12,10,FALSE))))) -> 0 | I34: =IF(B34="Excluded",0,(IF(ISNA(VLOOKUP(A34,FY2012_13,10,FALSE)),0,(VLOOKUP(A34,FY2012_13,10,FALSE))))) -> 0 | J34: =IF(B34="Excluded",0,(IF(ISNA(VLOOKUP(A34,FY2008_09P,6,FALSE)),0,(VLOOKUP(A34,FY2008_09P,6,FALSE))))) -> 0 | K34: =IF(B34="Excluded",0,(IF(ISNA(VLOOKUP(A34,FY2009_10P,6,FALSE)),0,(VLOOKUP(A34,FY2009_10P,6,FALSE))))) -> 0 | L34: =IF(B34="Excluded",0,(IF(ISNA(VLOOKUP(A34,FY2010_11P,6,FALSE)),0,(VLOOKUP(A34,FY2010_11P,6,FALSE))))) -> 0 | M34: =IF(B34="Excluded",0,(IF(ISNA(VLOOKUP(A34,FY2011_12P,6,FALSE)),0,(VLOOKUP(A34,FY2011_12P,6,FALSE))))) -> 0 | N34: =IF(B34="Excluded",0,(IF(ISNA(VLOOKUP(A34,FY2012_13P,6,FALSE)),0,(VLOOKUP(A34,FY2012_13P,6,FALSE))))) -> 0 | O34: =(AVERAGE(G34:I34)*0.75)+(AVERAGE(L34:N34)*0.25) -> 0 | P34: =(AVERAGE(E34:G34)*0.75)+(AVERAGE(J34:L34)*0.25) -> 0 | R34: =S34-Q34 -> 0 | S34: =ROUND((P34*'Cost Pool'!$C$25),0) -> 0 | U34: =V34-T34 -> 0 | V34: =ROUND((O34*'Cost Pool'!$D$25),0) -> 0 | W34: =V34+R34 -> 0
A35: 213-HC | B35: =VLOOKUP(A35,Crosswalk,2,FALSE) -> 213 | C35: =CONCATENATE((LEFT(B35,3))," - ",(VLOOKUP((LEFT(B35,3)),Funds,2,FALSE))) -> 213 - Housing Investment Fund | D35: =VLOOKUP((RIGHT(B35,2)),Bureaus,2,FALSE) -> #N/A | E35: =IF(B35="Excluded",0,(IF(ISNA(VLOOKUP(A35,FY2008_09,10,FALSE)),0,(VLOOKUP(A35,FY2008_09,10,FALSE))))) -> 0.013587146 | F35: =IF(B35="Excluded",0,(IF(ISNA(VLOOKUP(A35,FY2009_10,10,FALSE)),0,(VLOOKUP(A35,FY2009_10,10,FALSE))))) -> 0.0087797137 | G35: =IF(B35="Excluded",0,(IF(ISNA(VLOOKUP(A35,FY2010_11,10,FALSE)),0,(VLOOKUP(A35,FY2010_11,10,FALSE))))) -> 0.0042028308 | H35: =IF(B35="Excluded",0,(IF(ISNA(VLOOKUP(A35,FY2011_12,10,FALSE)),0,(VLOOKUP(A35,FY2011_12,10,FALSE))))) -> 0.0019175398 | I35: =IF(B35="Excluded",0,(IF(ISNA(VLOOKUP(A35,FY2012_13,10,FALSE)),0,(VLOOKUP(A35,FY2012_13,10,FALSE))))) -> 0.0015735122 | J35: =IF(B35="Excluded",0,(IF(ISNA(VLOOKUP(A35,FY2008_09P,6,FALSE)),0,(VLOOKUP(A35,FY2008_09P,6,FALSE))))) -> 0 | K35: =IF(B35="Excluded",0,(IF(ISNA(VLOOKUP(A35,FY2009_10P,6,FALSE)),0,(VLOOKUP(A35,FY2009_10P,6,FALSE))))) -> 0 | L35: =IF(B35="Excluded",0,(IF(ISNA(VLOOKUP(A35,FY2010_11P,6,FALSE)),0,(VLOOKUP(A35,FY2010_11P,6,FALSE))))) -> 0 | M35: =IF(B35="Excluded",0,(IF(ISNA(VLOOKUP(A35,FY2011_12P,6,FALSE)),0,(VLOOKUP(A35,FY2011_12P,6,FALSE))))) -> 0 | N35: =IF(B35="Excluded",0,(IF(ISNA(VLOOKUP(A35,FY2012_13P,6,FALSE)),0,(VLOOKUP(A35,FY2012_13P,6,FALSE))))) -> 0 | O35: =(AVERAGE(G35:I35)*0.75)+(AVERAGE(L35:N35)*0.25) -> 0.0019234707 | P35: =(AVERAGE(E35:G35)*0.75)+(AVERAGE(J35:L35)*0.25) -> 0.0066424226 | Q35: 233377 | R35: =S35-Q35 -> 35960 | S35: =ROUND((P35*'Cost Pool'!$C$25),0) -> 269337 | T35: 218979 | U35: =V35-T35 -> -130730 | V35: =ROUND((O35*'Cost Pool'!$D$25),0) -> 88249 | W35: =V35+R35 -> 124209
A36: 214-AU | B36: =VLOOKUP(A36,Crosswalk,2,FALSE) -> Excluded | C36: =CONCATENATE((LEFT(B36,3))," - ",(VLOOKUP((LEFT(B36,3)),Funds,2,FALSE))) -> #N/A | D36: =VLOOKUP((RIGHT(B36,2)),Bureaus,2,FALSE) -> #N/A | E36: =IF(B36="Excluded",0,(IF(ISNA(VLOOKUP(A36,FY2008_09,10,FALSE)),0,(VLOOKUP(A36,FY2008_09,10,FALSE))))) -> 0 | F36: =IF(B36="Excluded",0,(IF(ISNA(VLOOKUP(A36,FY2009_10,10,FALSE)),0,(VLOOKUP(A36,FY2009_10,10,FALSE))))) -> 0 | G36: =IF(B36="Excluded",0,(IF(ISNA(VLOOKUP(A36,FY2010_11,10,FALSE)),0,(VLOOKUP(A36,FY2010_11,10,FALSE))))) -> 0 | H36: =IF(B36="Excluded",0,(IF(ISNA(VLOOKUP(A36,FY2011_12,10,FALSE)),0,(VLOOKUP(A36,FY2011_12,10,FALSE))))) -> 0 | I36: =IF(B36="Excluded",0,(IF(ISNA(VLOOKUP(A36,FY2012_13,10,FALSE)),0,(VLOOKUP(A36,FY2012_13,10,FALSE))))) -> 0 | J36: =IF(B36="Excluded",0,(IF(ISNA(VLOOKUP(A36,FY2008_09P,6,FALSE)),0,(VLOOKUP(A36,FY2008_09P,6,FALSE))))) -> 0 | K36: =IF(B36="Excluded",0,(IF(ISNA(VLOOKUP(A36,FY2009_10P,6,FALSE)),0,(VLOOKUP(A36,FY2009_10P,6,FALSE))))) -> 0 | L36: =IF(B36="Excluded",0,(IF(ISNA(VLOOKUP(A36,FY2010_11P,6,FALSE)),0,(VLOOKUP(A36,FY2010_11P,6,FALSE))))) -> 0 | M36: =IF(B36="Excluded",0,(IF(ISNA(VLOOKUP(A36,FY2011_12P,6,FALSE)),0,(VLOOKUP(A36,FY2011_12P,6,FALSE))))) -> 0 | N36: =IF(B36="Excluded",0,(IF(ISNA(VLOOKUP(A36,FY2012_13P,6,FALSE)),0,(VLOOKUP(A36,FY2012_13P,6,FALSE))))) -> 0 | O36: =(AVERAGE(G36:I36)*0.75)+(AVERAGE(L36:N36)*0.25) -> 0 | P36: =(AVERAGE(E36:G36)*0.75)+(AVERAGE(J36:L36)*0.25) -> 0 | R36: =S36-Q36 -> 0 | S36: =ROUND((P36*'Cost Pool'!$C$25),0) -> 0 | U36: =V36-T36 -> 0 | V36: =ROUND((O36*'Cost Pool'!$D$25),0) -> 0 | W36: =V36+R36 -> 0
A37: 215-PK | B37: =VLOOKUP(A37,Crosswalk,2,FALSE) -> 215 | C37: =CONCATENATE((LEFT(B37,3))," - ",(VLOOKUP((LEFT(B37,3)),Funds,2,FALSE))) -> 215 - Parks Local Option Levy Fund | D37: =VLOOKUP((RIGHT(B37,2)),Bureaus,2,FALSE) -> #N/A | E37: =IF(B37="Excluded",0,(IF(ISNA(VLOOKUP(A37,FY2008_09,10,FALSE)),0,(VLOOKUP(A37,FY2008_09,10,FALSE))))) -> 0.0033601126 | F37: =IF(B37="Excluded",0,(IF(ISNA(VLOOKUP(A37,FY2009_10,10,FALSE)),0,(VLOOKUP(A37,FY2009_10,10,FALSE))))) -> 0.00094509348 | G37: =IF(B37="Excluded",0,(IF(ISNA(VLOOKUP(A37,FY2010_11,10,FALSE)),0,(VLOOKUP(A37,FY2010_11,10,FALSE))))) -> 0.00045981274 | H37: =IF(B37="Excluded",0,(IF(ISNA(VLOOKUP(A37,FY2011_12,10,FALSE)),0,(VLOOKUP(A37,FY2011_12,10,FALSE))))) -> 0.00044308465 | I37: =IF(B37="Excluded",0,(IF(ISNA(VLOOKUP(A37,FY2012_13,10,FALSE)),0,(VLOOKUP(A37,FY2012_13,10,FALSE))))) -> 0.0003380511 | J37: =IF(B37="Excluded",0,(IF(ISNA(VLOOKUP(A37,FY2008_09P,6,FALSE)),0,(VLOOKUP(A37,FY2008_09P,6,FALSE))))) -> 0 | K37: =IF(B37="Excluded",0,(IF(ISNA(VLOOKUP(A37,FY2009_10P,6,FALSE)),0,(VLOOKUP(A37,FY2009_10P,6,FALSE))))) -> 0 | L37: =IF(B37="Excluded",0,(IF(ISNA(VLOOKUP(A37,FY2010_11P,6,FALSE)),0,(VLOOKUP(A37,FY2010_11P,6,FALSE))))) -> 0 | M37: =IF(B37="Excluded",0,(IF(ISNA(VLOOKUP(A37,FY2011_12P,6,FALSE)),0,(VLOOKUP(A37,FY2011_12P,6,FALSE))))) -> 0 | N37: =IF(B37="Excluded",0,(IF(ISNA(VLOOKUP(A37,FY2012_13P,6,FALSE)),0,(VLOOKUP(A37,FY2012_13P,6,FALSE))))) -> 0 | O37: =(AVERAGE(G37:I37)*0.75)+(AVERAGE(L37:N37)*0.25) -> 0.00031023712 | P37: =(AVERAGE(E37:G37)*0.75)+(AVERAGE(J37:L37)*0.25) -> 0.0011912547 | Q37: 14303 | R37: =S37-Q37 -> 34000 | S37: =ROUND((P37*'Cost Pool'!$C$25),0) -> 48303 | T37: 9633 | U37: =V37-T37 -> 4601 | V37: =ROUND((O37*'Cost Pool'!$D$25),0) -> 14234 | W37: =V37+R37 -> 48234
A38: 216-PA | B38: =VLOOKUP(A38,Crosswalk,2,FALSE) -> 216 | C38: =CONCATENATE((LEFT(B38,3))," - ",(VLOOKUP((LEFT(B38,3)),Funds,2,FALSE))) -> 216 - Children's Investment Fund | D38: =VLOOKUP((RIGHT(B38,2)),Bureaus,2,FALSE) -> #N/A | E38: =IF(B38="Excluded",0,(IF(ISNA(VLOOKUP(A38,FY2008_09,10,FALSE)),0,(VLOOKUP(A38,FY2008_09,10,FALSE))))) -> 0 | F38: =IF(B38="Excluded",0,(IF(ISNA(VLOOKUP(A38,FY2009_10,10,FALSE)),0,(VLOOKUP(A38,FY2009_10,10,FALSE))))) -> 0 | G38: =IF(B38="Excluded",0,(IF(ISNA(VLOOKUP(A38,FY2010_11,10,FALSE)),0,(VLOOKUP(A38,FY2010_11,10,FALSE))))) -> 0 | H38: =IF(B38="Excluded",0,(IF(ISNA(VLOOKUP(A38,FY2011_12,10,FALSE)),0,(VLOOKUP(A38,FY2011_12,10,FALSE))))) -> 0 | I38: =IF(B38="Excluded",0,(IF(ISNA(VLOOKUP(A38,FY2012_13,10,FALSE)),0,(VLOOKUP(A38,FY2012_13,10,FALSE))))) -> 0 | J38: =IF(B38="Excluded",0,(IF(ISNA(VLOOKUP(A38,FY2008_09P,6,FALSE)),0,(VLOOKUP(A38,FY2008_09P,6,FALSE))))) -> 0 | K38: =IF(B38="Excluded",0,(IF(ISNA(VLOOKUP(A38,FY2009_10P,6,FALSE)),0,(VLOOKUP(A38,FY2009_10P,6,FALSE))))) -> 0 | L38: =IF(B38="Excluded",0,(IF(ISNA(VLOOKUP(A38,FY2010_11P,6,FALSE)),0,(VLOOKUP(A38,FY2010_11P,6,FALSE))))) -> 0 | M38: =IF(B38="Excluded",0,(IF(ISNA(VLOOKUP(A38,FY2011_12P,6,FALSE)),0,(VLOOKUP(A38,FY2011_12P,6,FALSE))))) -> 0 | N38: =IF(B38="Excluded",0,(IF(ISNA(VLOOKUP(A38,FY2012_13P,6,FALSE)),0,(VLOOKUP(A38,FY2012_13P,6,FALSE))))) -> 0 | O38: =(AVERAGE(G38:I38)*0.75)+(AVERAGE(L38:N38)*0.25) -> 0 | P38: =(AVERAGE(E38:G38)*0.75)+(AVERAGE(J38:L38)*0.25) -> 0 | Q38: 25000 | R38: =S38-Q38 -> 0 | S38: 25000 | T38: 25000 | U38: =V38-T38 -> 0 | V38: 25000 | W38: =V38+R38 -> 25000
A39: 217-DS | B39: =VLOOKUP(A39,Crosswalk,2,FALSE) -> 203 | C39: =CONCATENATE((LEFT(B39,3))," - ",(VLOOKUP((LEFT(B39,3)),Funds,2,FALSE))) -> 203 - Development Services Fund | D39: =VLOOKUP((RIGHT(B39,2)),Bureaus,2,FALSE) -> #N/A | E39: =IF(B39="Excluded",0,(IF(ISNA(VLOOKUP(A39,FY2008_09,10,FALSE)),0,(VLOOKUP(A39,FY2008_09,10,FALSE))))) -> 0 | F39: =IF(B39="Excluded",0,(IF(ISNA(VLOOKUP(A39,FY2009_10,10,FALSE)),0,(VLOOKUP(A39,FY2009_10,10,FALSE))))) -> 0 | G39: =IF(B39="Excluded",0,(IF(ISNA(VLOOKUP(A39,FY2010_11,10,FALSE)),0,(VLOOKUP(A39,FY2010_11,10,FALSE))))) -> 1.5299588e-05 | H39: =IF(B39="Excluded",0,(IF(ISNA(VLOOKUP(A39,FY2011_12,10,FALSE)),0,(VLOOKUP(A39,FY2011_12,10,FALSE))))) -> 8.0768018e-05 | I39: =IF(B39="Excluded",0,(IF(ISNA(VLOOKUP(A39,FY2012_13,10,FALSE)),0,(VLOOKUP(A39,FY2012_13,10,FALSE))))) -> 8.7214952e-06 | J39: =IF(B39="Excluded",0,(IF(ISNA(VLOOKUP(A39,FY2008_09P,6,FALSE)),0,(VLOOKUP(A39,FY2008_09P,6,FALSE))))) -> 0 | K39: =IF(B39="Excluded",0,(IF(ISNA(VLOOKUP(A39,FY2009_10P,6,FALSE)),0,(VLOOKUP(A39,FY2009_10P,6,FALSE))))) -> 0 | L39: =IF(B39="Excluded",0,(IF(ISNA(VLOOKUP(A39,FY2010_11P,6,FALSE)),0,(VLOOKUP(A39,FY2010_11P,6,FALSE))))) -> 0 | M39: =IF(B39="Excluded",0,(IF(ISNA(VLOOKUP(A39,FY2011_12P,6,FALSE)),0,(VLOOKUP(A39,FY2011_12P,6,FALSE))))) -> 0 | N39: =IF(B39="Excluded",0,(IF(ISNA(VLOOKUP(A39,FY2012_13P,6,FALSE)),0,(VLOOKUP(A39,FY2012_13P,6,FALSE))))) -> 0 | O39: =(AVERAGE(G39:I39)*0.75)+(AVERAGE(L39:N39)*0.25) -> 2.6197275e-05 | P39: =(AVERAGE(E39:G39)*0.75)+(AVERAGE(J39:L39)*0.25) -> 3.8248971e-06 | R39: =S39-Q39 -> 155 | S39: =ROUND((P39*'Cost Pool'!$C$25),0) -> 155 | U39: =V39-T39 -> 1202 | V39: =ROUND((O39*'Cost Pool'!$D$25),0) -> 1202 | W39: =V39+R39 -> 1357
A40: 217-EC | B40: =VLOOKUP(A40,Crosswalk,2,FALSE) -> 202 | C40: =CONCATENATE((LEFT(B40,3))," - ",(VLOOKUP((LEFT(B40,3)),Funds,2,FALSE))) -> 202 - Emergency Communication Fund | D40: =VLOOKUP((RIGHT(B40,2)),Bureaus,2,FALSE) -> #N/A | E40: =IF(B40="Excluded",0,(IF(ISNA(VLOOKUP(A40,FY2008_09,10,FALSE)),0,(VLOOKUP(A40,FY2008_09,10,FALSE))))) -> 1.6842622e-06 | F40: =IF(B40="Excluded",0,(IF(ISNA(VLOOKUP(A40,FY2009_10,10,FALSE)),0,(VLOOKUP(A40,FY2009_10,10,FALSE))))) -> 3.6964291e-05 | G40: =IF(B40="Excluded",0,(IF(ISNA(VLOOKUP(A40,FY2010_11,10,FALSE)),0,(VLOOKUP(A40,FY2010_11,10,FALSE))))) -> 2.039763e-05 | H40: =IF(B40="Excluded",0,(IF(ISNA(VLOOKUP(A40,FY2011_12,10,FALSE)),0,(VLOOKUP(A40,FY2011_12,10,FALSE))))) -> 0.00018319786 | I40: =IF(B40="Excluded",0,(IF(ISNA(VLOOKUP(A40,FY2012_13,10,FALSE)),0,(VLOOKUP(A40,FY2012_13,10,FALSE))))) -> 5.9983503e-07 | J40: =IF(B40="Excluded",0,(IF(ISNA(VLOOKUP(A40,FY2008_09P,6,FALSE)),0,(VLOOKUP(A40,FY2008_09P,6,FALSE))))) -> 0 | K40: =IF(B40="Excluded",0,(IF(ISNA(VLOOKUP(A40,FY2009_10P,6,FALSE)),0,(VLOOKUP(A40,FY2009_10P,6,FALSE))))) -> 0 | L40: =IF(B40="Excluded",0,(IF(ISNA(VLOOKUP(A40,FY2010_11P,6,FALSE)),0,(VLOOKUP(A40,FY2010_11P,6,FALSE))))) -> 0 | M40: =IF(B40="Excluded",0,(IF(ISNA(VLOOKUP(A40,FY2011_12P,6,FALSE)),0,(VLOOKUP(A40,FY2011_12P,6,FALSE))))) -> 0 | N40: =IF(B40="Excluded",0,(IF(ISNA(VLOOKUP(A40,FY2012_13P,6,FALSE)),0,(VLOOKUP(A40,FY2012_13P,6,FALSE))))) -> 0 | O40: =(AVERAGE(G40:I40)*0.75)+(AVERAGE(L40:N40)*0.25) -> 5.1048831e-05 | P40: =(AVERAGE(E40:G40)*0.75)+(AVERAGE(J40:L40)*0.25) -> 1.4761546e-05 | R40: =S40-Q40 -> 599 | S40: =ROUND((P40*'Cost Pool'!$C$25),0) -> 599 | U40: =V40-T40 -> 2342 | V40: =ROUND((O40*'Cost Pool'!$D$25),0) -> 2342 | W40: =V40+R40 -> 2941
A41: 217-EM | B41: =VLOOKUP(A41,Crosswalk,2,FALSE) -> 100-EM | C41: =CONCATENATE((LEFT(B41,3))," - ",(VLOOKUP((LEFT(B41,3)),Funds,2,FALSE))) -> 100 - General Fund | D41: =VLOOKUP((RIGHT(B41,2)),Bureaus,2,FALSE) -> Portland Bureau of Emergency Management | E41: =IF(B41="Excluded",0,(IF(ISNA(VLOOKUP(A41,FY2008_09,10,FALSE)),0,(VLOOKUP(A41,FY2008_09,10,FALSE))))) -> 0.0072282592 | F41: =IF(B41="Excluded",0,(IF(ISNA(VLOOKUP(A41,FY2009_10,10,FALSE)),0,(VLOOKUP(A41,FY2009_10,10,FALSE))))) -> 0.0047365231 | G41: =IF(B41="Excluded",0,(IF(ISNA(VLOOKUP(A41,FY2010_11,10,FALSE)),0,(VLOOKUP(A41,FY2010_11,10,FALSE))))) -> 0.0053859447 | H41: =IF(B41="Excluded",0,(IF(ISNA(VLOOKUP(A41,FY2011_12,10,FALSE)),0,(VLOOKUP(A41,FY2011_12,10,FALSE))))) -> 0.0076579545 | I41: =IF(B41="Excluded",0,(IF(ISNA(VLOOKUP(A41,FY2012_13,10,FALSE)),0,(VLOOKUP(A41,FY2012_13,10,FALSE))))) -> 0.0064891608 | J41: =IF(B41="Excluded",0,(IF(ISNA(VLOOKUP(A41,FY2008_09P,6,FALSE)),0,(VLOOKUP(A41,FY2008_09P,6,FALSE))))) -> 0 | K41: =IF(B41="Excluded",0,(IF(ISNA(VLOOKUP(A41,FY2009_10P,6,FALSE)),0,(VLOOKUP(A41,FY2009_10P,6,FALSE))))) -> 0 | L41: =IF(B41="Excluded",0,(IF(ISNA(VLOOKUP(A41,FY2010_11P,6,FALSE)),0,(VLOOKUP(A41,FY2010_11P,6,FALSE))))) -> 0 | M41: =IF(B41="Excluded",0,(IF(ISNA(VLOOKUP(A41,FY2011_12P,6,FALSE)),0,(VLOOKUP(A41,FY2011_12P,6,FALSE))))) -> 0 | N41: =IF(B41="Excluded",0,(IF(ISNA(VLOOKUP(A41,FY2012_13P,6,FALSE)),0,(VLOOKUP(A41,FY2012_13P,6,FALSE))))) -> 0 | O41: =(AVERAGE(G41:I41)*0.75)+(AVERAGE(L41:N41)*0.25) -> 0.004883265 | P41: =(AVERAGE(E41:G41)*0.75)+(AVERAGE(J41:L41)*0.25) -> 0.0043376817 | R41: =S41-Q41 -> 175885 | S41: =ROUND((P41*'Cost Pool'!$C$25),0) -> 175885 | U41: =V41-T41 -> 224045 | V41: =ROUND((O41*'Cost Pool'!$D$25),0) -> 224045 | W41: =V41+R41 -> 399930
A42: 217-ES | B42: =VLOOKUP(A42,Crosswalk,2,FALSE) -> 600 | C42: =CONCATENATE((LEFT(B42,3))," - ",(VLOOKUP((LEFT(B42,3)),Funds,2,FALSE))) -> 600 - Sewer System Operating Fund | D42: =VLOOKUP((RIGHT(B42,2)),Bureaus,2,FALSE) -> #N/A | E42: =IF(B42="Excluded",0,(IF(ISNA(VLOOKUP(A42,FY2008_09,10,FALSE)),0,(VLOOKUP(A42,FY2008_09,10,FALSE))))) -> 0.0010873884 | F42: =IF(B42="Excluded",0,(IF(ISNA(VLOOKUP(A42,FY2009_10,10,FALSE)),0,(VLOOKUP(A42,FY2009_10,10,FALSE))))) -> -1.3487017e-05 | G42: =IF(B42="Excluded",0,(IF(ISNA(VLOOKUP(A42,FY2010_11,10,FALSE)),0,(VLOOKUP(A42,FY2010_11,10,FALSE))))) -> 0.0015153177 | H42: =IF(B42="Excluded",0,(IF(ISNA(VLOOKUP(A42,FY2011_12,10,FALSE)),0,(VLOOKUP(A42,FY2011_12,10,FALSE))))) -> 0.001185399 | I42: =IF(B42="Excluded",0,(IF(ISNA(VLOOKUP(A42,FY2012_13,10,FALSE)),0,(VLOOKUP(A42,FY2012_13,10,FALSE))))) -> 0.0011261844 | J42: =IF(B42="Excluded",0,(IF(ISNA(VLOOKUP(A42,FY2008_09P,6,FALSE)),0,(VLOOKUP(A42,FY2008_09P,6,FALSE))))) -> 0 | K42: =IF(B42="Excluded",0,(IF(ISNA(VLOOKUP(A42,FY2009_10P,6,FALSE)),0,(VLOOKUP(A42,FY2009_10P,6,FALSE))))) -> 0 | L42: =IF(B42="Excluded",0,(IF(ISNA(VLOOKUP(A42,FY2010_11P,6,FALSE)),0,(VLOOKUP(A42,FY2010_11P,6,FALSE))))) -> 0 | M42: =IF(B42="Excluded",0,(IF(ISNA(VLOOKUP(A42,FY2011_12P,6,FALSE)),0,(VLOOKUP(A42,FY2011_12P,6,FALSE))))) -> 0 | N42: =IF(B42="Excluded",0,(IF(ISNA(VLOOKUP(A42,FY2012_13P,6,FALSE)),0,(VLOOKUP(A42,FY2012_13P,6,FALSE))))) -> 0 | O42: =(AVERAGE(G42:I42)*0.75)+(AVERAGE(L42:N42)*0.25) -> 0.00095672528 | P42: =(AVERAGE(E42:G42)*0.75)+(AVERAGE(J42:L42)*0.25) -> 0.00064730477 | R42: =S42-Q42 -> 26247 | S42: =ROUND((P42*'Cost Pool'!$C$25),0) -> 26247 | U42: =V42-T42 -> 43895 | V42: =ROUND((O42*'Cost Pool'!$D$25),0) -> 43895 | W42: =V42+R42 -> 70142
A43: 217-FR | B43: =VLOOKUP(A43,Crosswalk,2,FALSE) -> 100-FR | C43: =CONCATENATE((LEFT(B43,3))," - ",(VLOOKUP((LEFT(B43,3)),Funds,2,FALSE))) -> 100 - General Fund | D43: =VLOOKUP((RIGHT(B43,2)),Bureaus,2,FALSE) -> Portland Fire & Rescue | E43: =IF(B43="Excluded",0,(IF(ISNA(VLOOKUP(A43,FY2008_09,10,FALSE)),0,(VLOOKUP(A43,FY2008_09,10,FALSE))))) -> 0.00041576678 | F43: =IF(B43="Excluded",0,(IF(ISNA(VLOOKUP(A43,FY2009_10,10,FALSE)),0,(VLOOKUP(A43,FY2009_10,10,FALSE))))) -> 0.0014352678 | G43: =IF(B43="Excluded",0,(IF(ISNA(VLOOKUP(A43,FY2010_11,10,FALSE)),0,(VLOOKUP(A43,FY2010_11,10,FALSE))))) -> 0.00080119136 | H43: =IF(B43="Excluded",0,(IF(ISNA(VLOOKUP(A43,FY2011_12,10,FALSE)),0,(VLOOKUP(A43,FY2011_12,10,FALSE))))) -> 0.0019415996 | I43: =IF(B43="Excluded",0,(IF(ISNA(VLOOKUP(A43,FY2012_13,10,FALSE)),0,(VLOOKUP(A43,FY2012_13,10,FALSE))))) -> 0.0016022974 | J43: =IF(B43="Excluded",0,(IF(ISNA(VLOOKUP(A43,FY2008_09P,6,FALSE)),0,(VLOOKUP(A43,FY2008_09P,6,FALSE))))) -> 0 | K43: =IF(B43="Excluded",0,(IF(ISNA(VLOOKUP(A43,FY2009_10P,6,FALSE)),0,(VLOOKUP(A43,FY2009_10P,6,FALSE))))) -> 0 | L43: =IF(B43="Excluded",0,(IF(ISNA(VLOOKUP(A43,FY2010_11P,6,FALSE)),0,(VLOOKUP(A43,FY2010_11P,6,FALSE))))) -> 0 | M43: =IF(B43="Excluded",0,(IF(ISNA(VLOOKUP(A43,FY2011_12P,6,FALSE)),0,(VLOOKUP(A43,FY2011_12P,6,FALSE))))) -> 0 | N43: =IF(B43="Excluded",0,(IF(ISNA(VLOOKUP(A43,FY2012_13P,6,FALSE)),0,(VLOOKUP(A43,FY2012_13P,6,FALSE))))) -> 0 | O43: =(AVERAGE(G43:I43)*0.75)+(AVERAGE(L43:N43)*0.25) -> 0.0010862721 | P43: =(AVERAGE(E43:G43)*0.75)+(AVERAGE(J43:L43)*0.25) -> 0.00066305648 | R43: =S43-Q43 -> 26886 | S43: =ROUND((P43*'Cost Pool'!$C$25),0) -> 26886 | U43: =V43-T43 -> 49838 | V43: =ROUND((O43*'Cost Pool'!$D$25),0) -> 49838 | W43: =V43+R43 -> 76724
A44: 217-HC | B44: =VLOOKUP(A44,Crosswalk,2,FALSE) -> 100-HC | C44: =CONCATENATE((LEFT(B44,3))," - ",(VLOOKUP((LEFT(B44,3)),Funds,2,FALSE))) -> 100 - General Fund | D44: =VLOOKUP((RIGHT(B44,2)),Bureaus,2,FALSE) -> Portland Housing Bureau | E44: =IF(B44="Excluded",0,(IF(ISNA(VLOOKUP(A44,FY2008_09,10,FALSE)),0,(VLOOKUP(A44,FY2008_09,10,FALSE))))) -> 0.0039283116 | F44: =IF(B44="Excluded",0,(IF(ISNA(VLOOKUP(A44,FY2009_10,10,FALSE)),0,(VLOOKUP(A44,FY2009_10,10,FALSE))))) -> 0.0072740327 | G44: =IF(B44="Excluded",0,(IF(ISNA(VLOOKUP(A44,FY2010_11,10,FALSE)),0,(VLOOKUP(A44,FY2010_11,10,FALSE))))) -> 0.0098056275 | H44: =IF(B44="Excluded",0,(IF(ISNA(VLOOKUP(A44,FY2011_12,10,FALSE)),0,(VLOOKUP(A44,FY2011_12,10,FALSE))))) -> 0.0043501976 | I44: =IF(B44="Excluded",0,(IF(ISNA(VLOOKUP(A44,FY2012_13,10,FALSE)),0,(VLOOKUP(A44,FY2012_13,10,FALSE))))) -> 0.0061267214 | J44: =IF(B44="Excluded",0,(IF(ISNA(VLOOKUP(A44,FY2008_09P,6,FALSE)),0,(VLOOKUP(A44,FY2008_09P,6,FALSE))))) -> 0 | K44: =IF(B44="Excluded",0,(IF(ISNA(VLOOKUP(A44,FY2009_10P,6,FALSE)),0,(VLOOKUP(A44,FY2009_10P,6,FALSE))))) -> 0 | L44: =IF(B44="Excluded",0,(IF(ISNA(VLOOKUP(A44,FY2010_11P,6,FALSE)),0,(VLOOKUP(A44,FY2010_11P,6,FALSE))))) -> 0 | M44: =IF(B44="Excluded",0,(IF(ISNA(VLOOKUP(A44,FY2011_12P,6,FALSE)),0,(VLOOKUP(A44,FY2011_12P,6,FALSE))))) -> 0 | N44: =IF(B44="Excluded",0,(IF(ISNA(VLOOKUP(A44,FY2012_13P,6,FALSE)),0,(VLOOKUP(A44,FY2012_13P,6,FALSE))))) -> 0 | O44: =(AVERAGE(G44:I44)*0.75)+(AVERAGE(L44:N44)*0.25) -> 0.0050706366 | P44: =(AVERAGE(E44:G44)*0.75)+(AVERAGE(J44:L44)*0.25) -> 0.0052519929 | R44: =S44-Q44 -> 212958 | S44: =ROUND((P44*'Cost Pool'!$C$25),0) -> 212958 | U44: =V44-T44 -> 232641 | V44: =ROUND((O44*'Cost Pool'!$D$25),0) -> 232641 | W44: =V44+R44 -> 445599
A45: 217-MF | B45: =VLOOKUP(A45,Crosswalk,2,FALSE) -> 100-MF | C45: =CONCATENATE((LEFT(B45,3))," - ",(VLOOKUP((LEFT(B45,3)),Funds,2,FALSE))) -> 100 - General Fund | D45: =VLOOKUP((RIGHT(B45,2)),Bureaus,2,FALSE) -> Office of Management & Finance | E45: =IF(B45="Excluded",0,(IF(ISNA(VLOOKUP(A45,FY2008_09,10,FALSE)),0,(VLOOKUP(A45,FY2008_09,10,FALSE))))) -> 0.00015295361 | F45: =IF(B45="Excluded",0,(IF(ISNA(VLOOKUP(A45,FY2009_10,10,FALSE)),0,(VLOOKUP(A45,FY2009_10,10,FALSE))))) -> 0.00064871677 | G45: =IF(B45="Excluded",0,(IF(ISNA(VLOOKUP(A45,FY2010_11,10,FALSE)),0,(VLOOKUP(A45,FY2010_11,10,FALSE))))) -> 0.0042575181 | H45: =IF(B45="Excluded",0,(IF(ISNA(VLOOKUP(A45,FY2011_12,10,FALSE)),0,(VLOOKUP(A45,FY2011_12,10,FALSE))))) -> 0.0042634666 | I45: =IF(B45="Excluded",0,(IF(ISNA(VLOOKUP(A45,FY2012_13,10,FALSE)),0,(VLOOKUP(A45,FY2012_13,10,FALSE))))) -> 0.0021732888 | J45: =IF(B45="Excluded",0,(IF(ISNA(VLOOKUP(A45,FY2008_09P,6,FALSE)),0,(VLOOKUP(A45,FY2008_09P,6,FALSE))))) -> 0 | K45: =IF(B45="Excluded",0,(IF(ISNA(VLOOKUP(A45,FY2009_10P,6,FALSE)),0,(VLOOKUP(A45,FY2009_10P,6,FALSE))))) -> 0 | L45: =IF(B45="Excluded",0,(IF(ISNA(VLOOKUP(A45,FY2010_11P,6,FALSE)),0,(VLOOKUP(A45,FY2010_11P,6,FALSE))))) -> 0 | M45: =IF(B45="Excluded",0,(IF(ISNA(VLOOKUP(A45,FY2011_12P,6,FALSE)),0,(VLOOKUP(A45,FY2011_12P,6,FALSE))))) -> 0 | N45: =IF(B45="Excluded",0,(IF(ISNA(VLOOKUP(A45,FY2012_13P,6,FALSE)),0,(VLOOKUP(A45,FY2012_13P,6,FALSE))))) -> 0 | O45: =(AVERAGE(G45:I45)*0.75)+(AVERAGE(L45:N45)*0.25) -> 0.0026735684 | P45: =(AVERAGE(E45:G45)*0.75)+(AVERAGE(J45:L45)*0.25) -> 0.0012647971 | R45: =S45-Q45 -> 51285 | S45: =ROUND((P45*'Cost Pool'!$C$25),0) -> 51285 | U45: =V45-T45 -> 122664 | V45: =ROUND((O45*'Cost Pool'!$D$25),0) -> 122664 | W45: =V45+R45 -> 173949
A46: 217-MY | B46: =VLOOKUP(A46,Crosswalk,2,FALSE) -> 100-MY | C46: =CONCATENATE((LEFT(B46,3))," - ",(VLOOKUP((LEFT(B46,3)),Funds,2,FALSE))) -> 100 - General Fund | D46: =VLOOKUP((RIGHT(B46,2)),Bureaus,2,FALSE) -> Office of the Mayor | E46: =IF(B46="Excluded",0,(IF(ISNA(VLOOKUP(A46,FY2008_09,10,FALSE)),0,(VLOOKUP(A46,FY2008_09,10,FALSE))))) -> 0 | F46: =IF(B46="Excluded",0,(IF(ISNA(VLOOKUP(A46,FY2009_10,10,FALSE)),0,(VLOOKUP(A46,FY2009_10,10,FALSE))))) -> 0 | G46: =IF(B46="Excluded",0,(IF(ISNA(VLOOKUP(A46,FY2010_11,10,FALSE)),0,(VLOOKUP(A46,FY2010_11,10,FALSE))))) -> 0 | H46: =IF(B46="Excluded",0,(IF(ISNA(VLOOKUP(A46,FY2011_12,10,FALSE)),0,(VLOOKUP(A46,FY2011_12,10,FALSE))))) -> 2.7115202e-06 | I46: =IF(B46="Excluded",0,(IF(ISNA(VLOOKUP(A46,FY2012_13,10,FALSE)),0,(VLOOKUP(A46,FY2012_13,10,FALSE))))) -> 0 | J46: =IF(B46="Excluded",0,(IF(ISNA(VLOOKUP(A46,FY2008_09P,6,FALSE)),0,(VLOOKUP(A46,FY2008_09P,6,FALSE))))) -> 0 | K46: =IF(B46="Excluded",0,(IF(ISNA(VLOOKUP(A46,FY2009_10P,6,FALSE)),0,(VLOOKUP(A46,FY2009_10P,6,FALSE))))) -> 0 | L46: =IF(B46="Excluded",0,(IF(ISNA(VLOOKUP(A46,FY2010_11P,6,FALSE)),0,(VLOOKUP(A46,FY2010_11P,6,FALSE))))) -> 0 | M46: =IF(B46="Excluded",0,(IF(ISNA(VLOOKUP(A46,FY2011_12P,6,FALSE)),0,(VLOOKUP(A46,FY2011_12P,6,FALSE))))) -> 0 | N46: =IF(B46="Excluded",0,(IF(ISNA(VLOOKUP(A46,FY2012_13P,6,FALSE)),0,(VLOOKUP(A46,FY2012_13P,6,FALSE))))) -> 0 | O46: =(AVERAGE(G46:I46)*0.75)+(AVERAGE(L46:N46)*0.25) -> 6.7788006e-07 | P46: =(AVERAGE(E46:G46)*0.75)+(AVERAGE(J46:L46)*0.25) -> 0 | R46: =S46-Q46 -> 0 | S46: =ROUND((P46*'Cost Pool'!$C$25),0) -> 0 | U46: =V46-T46 -> 31 | V46: =ROUND((O46*'Cost Pool'!$D$25),0) -> 31 | W46: =V46+R46 -> 31
A47: 217-NI | B47: =VLOOKUP(A47,Crosswalk,2,FALSE) -> 100-NI | C47: =CONCATENATE((LEFT(B47,3))," - ",(VLOOKUP((LEFT(B47,3)),Funds,2,FALSE))) -> 100 - General Fund | D47: =VLOOKUP((RIGHT(B47,2)),Bureaus,2,FALSE) -> Office of Neighborhood Involvement | E47: =IF(B47="Excluded",0,(IF(ISNA(VLOOKUP(A47,FY2008_09,10,FALSE)),0,(VLOOKUP(A47,FY2008_09,10,FALSE))))) -> 0 | F47: =IF(B47="Excluded",0,(IF(ISNA(VLOOKUP(A47,FY2009_10,10,FALSE)),0,(VLOOKUP(A47,FY2009_10,10,FALSE))))) -> 0 | G47: =IF(B47="Excluded",0,(IF(ISNA(VLOOKUP(A47,FY2010_11,10,FALSE)),0,(VLOOKUP(A47,FY2010_11,10,FALSE))))) -> 4.9177248e-05 | H47: =IF(B47="Excluded",0,(IF(ISNA(VLOOKUP(A47,FY2011_12,10,FALSE)),0,(VLOOKUP(A47,FY2011_12,10,FALSE))))) -> 5.6185666e-06 | I47: =IF(B47="Excluded",0,(IF(ISNA(VLOOKUP(A47,FY2012_13,10,FALSE)),0,(VLOOKUP(A47,FY2012_13,10,FALSE))))) -> 0 | J47: =IF(B47="Excluded",0,(IF(ISNA(VLOOKUP(A47,FY2008_09P,6,FALSE)),0,(VLOOKUP(A47,FY2008_09P,6,FALSE))))) -> 0 | K47: =IF(B47="Excluded",0,(IF(ISNA(VLOOKUP(A47,FY2009_10P,6,FALSE)),0,(VLOOKUP(A47,FY2009_10P,6,FALSE))))) -> 0 | L47: =IF(B47="Excluded",0,(IF(ISNA(VLOOKUP(A47,FY2010_11P,6,FALSE)),0,(VLOOKUP(A47,FY2010_11P,6,FALSE))))) -> 0 | M47: =IF(B47="Excluded",0,(IF(ISNA(VLOOKUP(A47,FY2011_12P,6,FALSE)),0,(VLOOKUP(A47,FY2011_12P,6,FALSE))))) -> 0 | N47: =IF(B47="Excluded",0,(IF(ISNA(VLOOKUP(A47,FY2012_13P,6,FALSE)),0,(VLOOKUP(A47,FY2012_13P,6,FALSE))))) -> 0 | O47: =(AVERAGE(G47:I47)*0.75)+(AVERAGE(L47:N47)*0.25) -> 1.3698954e-05 | P47: =(AVERAGE(E47:G47)*0.75)+(AVERAGE(J47:L47)*0.25) -> 1.2294312e-05 | R47: =S47-Q47 -> 499 | S47: =ROUND((P47*'Cost Pool'!$C$25),0) -> 499 | U47: =V47-T47 -> 629 | V47: =ROUND((O47*'Cost Pool'!$D$25),0) -> 629 | W47: =V47+R47 -> 1128
A48: 217-PA | B48: =VLOOKUP(A48,Crosswalk,2,FALSE) -> 100-PA | C48: =CONCATENATE((LEFT(B48,3))," - ",(VLOOKUP((LEFT(B48,3)),Funds,2,FALSE))) -> 100 - General Fund | D48: =VLOOKUP((RIGHT(B48,2)),Bureaus,2,FALSE) -> Commissioner of Public Affairs | E48: =IF(B48="Excluded",0,(IF(ISNA(VLOOKUP(A48,FY2008_09,10,FALSE)),0,(VLOOKUP(A48,FY2008_09,10,FALSE))))) -> 0 | F48: =IF(B48="Excluded",0,(IF(ISNA(VLOOKUP(A48,FY2009_10,10,FALSE)),0,(VLOOKUP(A48,FY2009_10,10,FALSE))))) -> 0 | G48: =IF(B48="Excluded",0,(IF(ISNA(VLOOKUP(A48,FY2010_11,10,FALSE)),0,(VLOOKUP(A48,FY2010_11,10,FALSE))))) -> 5.3221804e-05 | H48: =IF(B48="Excluded",0,(IF(ISNA(VLOOKUP(A48,FY2011_12,10,FALSE)),0,(VLOOKUP(A48,FY2011_12,10,FALSE))))) -> 6.0454652e-05 | I48: =IF(B48="Excluded",0,(IF(ISNA(VLOOKUP(A48,FY2012_13,10,FALSE)),0,(VLOOKUP(A48,FY2012_13,10,FALSE))))) -> 0.0001815706 | J48: =IF(B48="Excluded",0,(IF(ISNA(VLOOKUP(A48,FY2008_09P,6,FALSE)),0,(VLOOKUP(A48,FY2008_09P,6,FALSE))))) -> 0 | K48: =IF(B48="Excluded",0,(IF(ISNA(VLOOKUP(A48,FY2009_10P,6,FALSE)),0,(VLOOKUP(A48,FY2009_10P,6,FALSE))))) -> 0 | L48: =IF(B48="Excluded",0,(IF(ISNA(VLOOKUP(A48,FY2010_11P,6,FALSE)),0,(VLOOKUP(A48,FY2010_11P,6,FALSE))))) -> 0 | M48: =IF(B48="Excluded",0,(IF(ISNA(VLOOKUP(A48,FY2011_12P,6,FALSE)),0,(VLOOKUP(A48,FY2011_12P,6,FALSE))))) -> 0 | N48: =IF(B48="Excluded",0,(IF(ISNA(VLOOKUP(A48,FY2012_13P,6,FALSE)),0,(VLOOKUP(A48,FY2012_13P,6,FALSE))))) -> 0 | O48: =(AVERAGE(G48:I48)*0.75)+(AVERAGE(L48:N48)*0.25) -> 7.3811763e-05 | P48: =(AVERAGE(E48:G48)*0.75)+(AVERAGE(J48:L48)*0.25) -> 1.3305451e-05 | R48: =S48-Q48 -> 540 | S48: =ROUND((P48*'Cost Pool'!$C$25),0) -> 540 | U48: =V48-T48 -> 3386 | V48: =ROUND((O48*'Cost Pool'!$D$25),0) -> 3386 | W48: =V48+R48 -> 3926
A49: 217-PK | B49: =VLOOKUP(A49,Crosswalk,2,FALSE) -> 100-PK | C49: =CONCATENATE((LEFT(B49,3))," - ",(VLOOKUP((LEFT(B49,3)),Funds,2,FALSE))) -> 100 - General Fund | D49: =VLOOKUP((RIGHT(B49,2)),Bureaus,2,FALSE) -> Portland Parks & Recreation | E49: =IF(B49="Excluded",0,(IF(ISNA(VLOOKUP(A49,FY2008_09,10,FALSE)),0,(VLOOKUP(A49,FY2008_09,10,FALSE))))) -> 0.00041348873 | F49: =IF(B49="Excluded",0,(IF(ISNA(VLOOKUP(A49,FY2009_10,10,FALSE)),0,(VLOOKUP(A49,FY2009_10,10,FALSE))))) -> 0.00086730848 | G49: =IF(B49="Excluded",0,(IF(ISNA(VLOOKUP(A49,FY2010_11,10,FALSE)),0,(VLOOKUP(A49,FY2010_11,10,FALSE))))) -> 0.00094827286 | H49: =IF(B49="Excluded",0,(IF(ISNA(VLOOKUP(A49,FY2011_12,10,FALSE)),0,(VLOOKUP(A49,FY2011_12,10,FALSE))))) -> 0.0010336145 | I49: =IF(B49="Excluded",0,(IF(ISNA(VLOOKUP(A49,FY2012_13,10,FALSE)),0,(VLOOKUP(A49,FY2012_13,10,FALSE))))) -> 0.0010944967 | J49: =IF(B49="Excluded",0,(IF(ISNA(VLOOKUP(A49,FY2008_09P,6,FALSE)),0,(VLOOKUP(A49,FY2008_09P,6,FALSE))))) -> 0 | K49: =IF(B49="Excluded",0,(IF(ISNA(VLOOKUP(A49,FY2009_10P,6,FALSE)),0,(VLOOKUP(A49,FY2009_10P,6,FALSE))))) -> 0 | L49: =IF(B49="Excluded",0,(IF(ISNA(VLOOKUP(A49,FY2010_11P,6,FALSE)),0,(VLOOKUP(A49,FY2010_11P,6,FALSE))))) -> 0 | M49: =IF(B49="Excluded",0,(IF(ISNA(VLOOKUP(A49,FY2011_12P,6,FALSE)),0,(VLOOKUP(A49,FY2011_12P,6,FALSE))))) -> 0 | N49: =IF(B49="Excluded",0,(IF(ISNA(VLOOKUP(A49,FY2012_13P,6,FALSE)),0,(VLOOKUP(A49,FY2012_13P,6,FALSE))))) -> 0 | O49: =(AVERAGE(G49:I49)*0.75)+(AVERAGE(L49:N49)*0.25) -> 0.00076909602 | P49: =(AVERAGE(E49:G49)*0.75)+(AVERAGE(J49:L49)*0.25) -> 0.00055726752 | R49: =S49-Q49 -> 22596 | S49: =ROUND((P49*'Cost Pool'!$C$25),0) -> 22596 | U49: =V49-T49 -> 35286 | V49: =ROUND((O49*'Cost Pool'!$D$25),0) -> 35286 | W49: =V49+R49 -> 57882
A50: 217-PL | B50: =VLOOKUP(A50,Crosswalk,2,FALSE) -> 100-PL | C50: =CONCATENATE((LEFT(B50,3))," - ",(VLOOKUP((LEFT(B50,3)),Funds,2,FALSE))) -> 100 - General Fund | D50: =VLOOKUP((RIGHT(B50,2)),Bureaus,2,FALSE) -> Portland Police Bureau | E50: =IF(B50="Excluded",0,(IF(ISNA(VLOOKUP(A50,FY2008_09,10,FALSE)),0,(VLOOKUP(A50,FY2008_09,10,FALSE))))) -> 0.0019010719 | F50: =IF(B50="Excluded",0,(IF(ISNA(VLOOKUP(A50,FY2009_10,10,FALSE)),0,(VLOOKUP(A50,FY2009_10,10,FALSE))))) -> 0.0034875977 | G50: =IF(B50="Excluded",0,(IF(ISNA(VLOOKUP(A50,FY2010_11,10,FALSE)),0,(VLOOKUP(A50,FY2010_11,10,FALSE))))) -> 0.0044458112 | H50: =IF(B50="Excluded",0,(IF(ISNA(VLOOKUP(A50,FY2011_12,10,FALSE)),0,(VLOOKUP(A50,FY2011_12,10,FALSE))))) -> 0.0045249463 | I50: =IF(B50="Excluded",0,(IF(ISNA(VLOOKUP(A50,FY2012_13,10,FALSE)),0,(VLOOKUP(A50,FY2012_13,10,FALSE))))) -> 0.0029546143 | J50: =IF(B50="Excluded",0,(IF(ISNA(VLOOKUP(A50,FY2008_09P,6,FALSE)),0,(VLOOKUP(A50,FY2008_09P,6,FALSE))))) -> 0 | K50: =IF(B50="Excluded",0,(IF(ISNA(VLOOKUP(A50,FY2009_10P,6,FALSE)),0,(VLOOKUP(A50,FY2009_10P,6,FALSE))))) -> 0 | L50: =IF(B50="Excluded",0,(IF(ISNA(VLOOKUP(A50,FY2010_11P,6,FALSE)),0,(VLOOKUP(A50,FY2010_11P,6,FALSE))))) -> 0 | M50: =IF(B50="Excluded",0,(IF(ISNA(VLOOKUP(A50,FY2011_12P,6,FALSE)),0,(VLOOKUP(A50,FY2011_12P,6,FALSE))))) -> 0 | N50: =IF(B50="Excluded",0,(IF(ISNA(VLOOKUP(A50,FY2012_13P,6,FALSE)),0,(VLOOKUP(A50,FY2012_13P,6,FALSE))))) -> 0 | O50: =(AVERAGE(G50:I50)*0.75)+(AVERAGE(L50:N50)*0.25) -> 0.002981343 | P50: =(AVERAGE(E50:G50)*0.75)+(AVERAGE(J50:L50)*0.25) -> 0.0024586202 | R50: =S50-Q50 -> 99692 | S50: =ROUND((P50*'Cost Pool'!$C$25),0) -> 99692 | U50: =V50-T50 -> 136784 | V50: =ROUND((O50*'Cost Pool'!$D$25),0) -> 136784 | W50: =V50+R50 -> 236476
... A59: 220-PK | B59: =VLOOKUP(A59,Crosswalk,2,FALSE) -> Excluded | C59: =CONCATENATE((LEFT(B59,3))," - ",(VLOOKUP((LEFT(B59,3)),Funds,2,FALSE))) -> #N/A | D59: =VLOOKUP((RIGHT(B59,2)),Bureaus,2,FALSE) -> #N/A | E59: =IF(B59="Excluded",0,(IF(ISNA(VLOOKUP(A59,FY2008_09,10,FALSE)),0,(VLOOKUP(A59,FY2008_09,10,FALSE))))) -> 0 | F59: =IF(B59="Excluded",0,(IF(ISNA(VLOOKUP(A59,FY2009_10,10,FALSE)),0,(VLOOKUP(A59,FY2009_10,10,FALSE))))) -> 0 | G59: =IF(B59="Excluded",0,(IF(ISNA(VLOOKUP(A59,FY2010_11,10,FALSE)),0,(VLOOKUP(A59,FY2010_11,10,FALSE))))) -> 0 | H59: =IF(B59="Excluded",0,(IF(ISNA(VLOOKUP(A59,FY2011_12,10,FALSE)),0,(VLOOKUP(A59,FY2011_12,10,FALSE))))) -> 0 | I59: =IF(B59="Excluded",0,(IF(ISNA(VLOOKUP(A59,FY2012_13,10,FALSE)),0,(VLOOKUP(A59,FY2012_13,10,FALSE))))) -> 0 | J59: =IF(B59="Excluded",0,(IF(ISNA(VLOOKUP(A59,FY2008_09P,6,FALSE)),0,(VLOOKUP(A59,FY2008_09P,6,FALSE))))) -> 0 | K59: =IF(B59="Excluded",0,(IF(ISNA(VLOOKUP(A59,FY2009_10P,6,FALSE)),0,(VLOOKUP(A59,FY2009_10P,6,FALSE))))) -> 0 | L59: =IF(B59="Excluded",0,(IF(ISNA(VLOOKUP(A59,FY2010_11P,6,FALSE)),0,(VLOOKUP(A59,FY2010_11P,6,FALSE))))) -> 0 | M59: =IF(B59="Excluded",0,(IF(ISNA(VLOOKUP(A59,FY2011_12P,6,FALSE)),0,(VLOOKUP(A59,FY2011_12P,6,FALSE))))) -> 0 | N59: =IF(B59="Excluded",0,(IF(ISNA(VLOOKUP(A59,FY2012_13P,6,FALSE)),0,(VLOOKUP(A59,FY2012_13P,6,FALSE))))) -> 0 | O59: =(AVERAGE(G59:I59)*0.75)+(AVERAGE(L59:N59)*0.25) -> 0 | P59: =(AVERAGE(E59:G59)*0.75)+(AVERAGE(J59:L59)*0.25) -> 0 | R59: =S59-Q59 -> 0 | S59: =ROUND((P59*'Cost Pool'!$C$25),0) -> 0 | U59: =V59-T59 -> 0 | V59: =ROUND((O59*'Cost Pool'!$D$25),0) -> 0 | W59: =V59+R59 -> 0
A60: 221-HC | B60: =VLOOKUP(A60,Crosswalk,2,FALSE) -> 221 | C60: =CONCATENATE((LEFT(B60,3))," - ",(VLOOKUP((LEFT(B60,3)),Funds,2,FALSE))) -> 221 - Tax Increment Financing Reimbursement Fund | D60: =VLOOKUP((RIGHT(B60,2)),Bureaus,2,FALSE) -> #N/A | E60: =IF(B60="Excluded",0,(IF(ISNA(VLOOKUP(A60,FY2008_09,10,FALSE)),0,(VLOOKUP(A60,FY2008_09,10,FALSE))))) -> 0 | F60: =IF(B60="Excluded",0,(IF(ISNA(VLOOKUP(A60,FY2009_10,10,FALSE)),0,(VLOOKUP(A60,FY2009_10,10,FALSE))))) -> 0.00043641675 | G60: =IF(B60="Excluded",0,(IF(ISNA(VLOOKUP(A60,FY2010_11,10,FALSE)),0,(VLOOKUP(A60,FY2010_11,10,FALSE))))) -> 0.020617164 | H60: =IF(B60="Excluded",0,(IF(ISNA(VLOOKUP(A60,FY2011_12,10,FALSE)),0,(VLOOKUP(A60,FY2011_12,10,FALSE))))) -> 0.026985688 | I60: =IF(B60="Excluded",0,(IF(ISNA(VLOOKUP(A60,FY2012_13,10,FALSE)),0,(VLOOKUP(A60,FY2012_13,10,FALSE))))) -> 0.017186126 | J60: =IF(B60="Excluded",0,(IF(ISNA(VLOOKUP(A60,FY2008_09P,6,FALSE)),0,(VLOOKUP(A60,FY2008_09P,6,FALSE))))) -> 0 | K60: =IF(B60="Excluded",0,(IF(ISNA(VLOOKUP(A60,FY2009_10P,6,FALSE)),0,(VLOOKUP(A60,FY2009_10P,6,FALSE))))) -> 0 | L60: =IF(B60="Excluded",0,(IF(ISNA(VLOOKUP(A60,FY2010_11P,6,FALSE)),0,(VLOOKUP(A60,FY2010_11P,6,FALSE))))) -> 0 | M60: =IF(B60="Excluded",0,(IF(ISNA(VLOOKUP(A60,FY2011_12P,6,FALSE)),0,(VLOOKUP(A60,FY2011_12P,6,FALSE))))) -> 0 | N60: =IF(B60="Excluded",0,(IF(ISNA(VLOOKUP(A60,FY2012_13P,6,FALSE)),0,(VLOOKUP(A60,FY2012_13P,6,FALSE))))) -> 0 | O60: =(AVERAGE(G60:I60)*0.75)+(AVERAGE(L60:N60)*0.25) -> 0.016197244 | P60: =(AVERAGE(E60:G60)*0.75)+(AVERAGE(J60:L60)*0.25) -> 0.0052633951 | Q60: 493139 | R60: =S60-Q60 -> -279718 | S60: =ROUND((P60*'Cost Pool'!$C$25),0) -> 213421 | T60: 835994 | U60: =V60-T60 -> -92863 | V60: =ROUND((O60*'Cost Pool'!$D$25),0) -> 743131 | W60: =V60+R60 -> 463413
A61: 222-PL | B61: =VLOOKUP(A61,Crosswalk,2,FALSE) -> 222 | C61: =CONCATENATE((LEFT(B61,3))," - ",(VLOOKUP((LEFT(B61,3)),Funds,2,FALSE))) -> 222 - Police Special Revenue Fund | D61: =VLOOKUP((RIGHT(B61,2)),Bureaus,2,FALSE) -> #N/A | E61: =IF(B61="Excluded",0,(IF(ISNA(VLOOKUP(A61,FY2008_09,10,FALSE)),0,(VLOOKUP(A61,FY2008_09,10,FALSE))))) -> 1.771359e-06 | F61: =IF(B61="Excluded",0,(IF(ISNA(VLOOKUP(A61,FY2009_10,10,FALSE)),0,(VLOOKUP(A61,FY2009_10,10,FALSE))))) -> 0.00050244423 | G61: =IF(B61="Excluded",0,(IF(ISNA(VLOOKUP(A61,FY2010_11,10,FALSE)),0,(VLOOKUP(A61,FY2010_11,10,FALSE))))) -> 0.00057752231 | H61: =IF(B61="Excluded",0,(IF(ISNA(VLOOKUP(A61,FY2011_12,10,FALSE)),0,(VLOOKUP(A61,FY2011_12,10,FALSE))))) -> 0.00061007632 | I61: =IF(B61="Excluded",0,(IF(ISNA(VLOOKUP(A61,FY2012_13,10,FALSE)),0,(VLOOKUP(A61,FY2012_13,10,FALSE))))) -> 0.00088661882 | J61: =IF(B61="Excluded",0,(IF(ISNA(VLOOKUP(A61,FY2008_09P,6,FALSE)),0,(VLOOKUP(A61,FY2008_09P,6,FALSE))))) -> 0 | K61: =IF(B61="Excluded",0,(IF(ISNA(VLOOKUP(A61,FY2009_10P,6,FALSE)),0,(VLOOKUP(A61,FY2009_10P,6,FALSE))))) -> 0 | L61: =IF(B61="Excluded",0,(IF(ISNA(VLOOKUP(A61,FY2010_11P,6,FALSE)),0,(VLOOKUP(A61,FY2010_11P,6,FALSE))))) -> 0 | M61: =IF(B61="Excluded",0,(IF(ISNA(VLOOKUP(A61,FY2011_12P,6,FALSE)),0,(VLOOKUP(A61,FY2011_12P,6,FALSE))))) -> 0 | N61: =IF(B61="Excluded",0,(IF(ISNA(VLOOKUP(A61,FY2012_13P,6,FALSE)),0,(VLOOKUP(A61,FY2012_13P,6,FALSE))))) -> 0 | O61: =(AVERAGE(G61:I61)*0.75)+(AVERAGE(L61:N61)*0.25) -> 0.00051855436 | P61: =(AVERAGE(E61:G61)*0.75)+(AVERAGE(J61:L61)*0.25) -> 0.00027043447 | Q61: 10601 | R61: =S61-Q61 -> 365 | S61: =ROUND((P61*'Cost Pool'!$C$25),0) -> 10966 | T61: 11137 | U61: =V61-T61 -> 12654 | V61: =ROUND((O61*'Cost Pool'!$D$25),0) -> 23791 | W61: =V61+R61 -> 24156
A62: 223-MF | B62: =VLOOKUP(A62,Crosswalk,2,FALSE) -> 223 | C62: =CONCATENATE((LEFT(B62,3))," - ",(VLOOKUP((LEFT(B62,3)),Funds,2,FALSE))) -> 223 - Arts Education & Access Fund | D62: =VLOOKUP((RIGHT(B62,2)),Bureaus,2,FALSE) -> #N/A | E62: =IF(B62="Excluded",0,(IF(ISNA(VLOOKUP(A62,FY2008_09,10,FALSE)),0,(VLOOKUP(A62,FY2008_09,10,FALSE))))) -> 0 | F62: =IF(B62="Excluded",0,(IF(ISNA(VLOOKUP(A62,FY2009_10,10,FALSE)),0,(VLOOKUP(A62,FY2009_10,10,FALSE))))) -> 0 | G62: =IF(B62="Excluded",0,(IF(ISNA(VLOOKUP(A62,FY2010_11,10,FALSE)),0,(VLOOKUP(A62,FY2010_11,10,FALSE))))) -> 0 | H62: =IF(B62="Excluded",0,(IF(ISNA(VLOOKUP(A62,FY2011_12,10,FALSE)),0,(VLOOKUP(A62,FY2011_12,10,FALSE))))) -> 0 | I62: =IF(B62="Excluded",0,(IF(ISNA(VLOOKUP(A62,FY2012_13,10,FALSE)),0,(VLOOKUP(A62,FY2012_13,10,FALSE))))) -> 0 | J62: =IF(B62="Excluded",0,(IF(ISNA(VLOOKUP(A62,FY2008_09P,6,FALSE)),0,(VLOOKUP(A62,FY2008_09P,6,FALSE))))) -> 0 | K62: =IF(B62="Excluded",0,(IF(ISNA(VLOOKUP(A62,FY2009_10P,6,FALSE)),0,(VLOOKUP(A62,FY2009_10P,6,FALSE))))) -> 0 | L62: =IF(B62="Excluded",0,(IF(ISNA(VLOOKUP(A62,FY2010_11P,6,FALSE)),0,(VLOOKUP(A62,FY2010_11P,6,FALSE))))) -> 0 | M62: =IF(B62="Excluded",0,(IF(ISNA(VLOOKUP(A62,FY2011_12P,6,FALSE)),0,(VLOOKUP(A62,FY2011_12P,6,FALSE))))) -> 0 | N62: =IF(B62="Excluded",0,(IF(ISNA(VLOOKUP(A62,FY2012_13P,6,FALSE)),0,(VLOOKUP(A62,FY2012_13P,6,FALSE))))) -> 0 | O62: =(AVERAGE(G62:I62)*0.75)+(AVERAGE(L62:N62)*0.25) -> 0 | P62: =(AVERAGE(E62:G62)*0.75)+(AVERAGE(J62:L62)*0.25) -> 0 | R62: =S62-Q62 -> 0 | S62: =ROUND((P62*'Cost Pool'!$C$25),0) -> 0 | T62: 0 | U62: =V62-T62 -> 25000 | V62: 25000 | W62: =V62+R62 -> 25000
A63: 303-FM | B63: =VLOOKUP(A63,Crosswalk,2,FALSE) -> Excluded | C63: =CONCATENATE((LEFT(B63,3))," - ",(VLOOKUP((LEFT(B63,3)),Funds,2,FALSE))) -> #N/A | D63: =VLOOKUP((RIGHT(B63,2)),Bureaus,2,FALSE) -> #N/A | E63: =IF(B63="Excluded",0,(IF(ISNA(VLOOKUP(A63,FY2008_09,10,FALSE)),0,(VLOOKUP(A63,FY2008_09,10,FALSE))))) -> 0 | F63: =IF(B63="Excluded",0,(IF(ISNA(VLOOKUP(A63,FY2009_10,10,FALSE)),0,(VLOOKUP(A63,FY2009_10,10,FALSE))))) -> 0 | G63: =IF(B63="Excluded",0,(IF(ISNA(VLOOKUP(A63,FY2010_11,10,FALSE)),0,(VLOOKUP(A63,FY2010_11,10,FALSE))))) -> 0 | H63: =IF(B63="Excluded",0,(IF(ISNA(VLOOKUP(A63,FY2011_12,10,FALSE)),0,(VLOOKUP(A63,FY2011_12,10,FALSE))))) -> 0 | I63: =IF(B63="Excluded",0,(IF(ISNA(VLOOKUP(A63,FY2012_13,10,FALSE)),0,(VLOOKUP(A63,FY2012_13,10,FALSE))))) -> 0 | J63: =IF(B63="Excluded",0,(IF(ISNA(VLOOKUP(A63,FY2008_09P,6,FALSE)),0,(VLOOKUP(A63,FY2008_09P,6,FALSE))))) -> 0 | K63: =IF(B63="Excluded",0,(IF(ISNA(VLOOKUP(A63,FY2009_10P,6,FALSE)),0,(VLOOKUP(A63,FY2009_10P,6,FALSE))))) -> 0 | L63: =IF(B63="Excluded",0,(IF(ISNA(VLOOKUP(A63,FY2010_11P,6,FALSE)),0,(VLOOKUP(A63,FY2010_11P,6,FALSE))))) -> 0 | M63: =IF(B63="Excluded",0,(IF(ISNA(VLOOKUP(A63,FY2011_12P,6,FALSE)),0,(VLOOKUP(A63,FY2011_12P,6,FALSE))))) -> 0 | N63: =IF(B63="Excluded",0,(IF(ISNA(VLOOKUP(A63,FY2012_13P,6,FALSE)),0,(VLOOKUP(A63,FY2012_13P,6,FALSE))))) -> 0 | O63: =(AVERAGE(G63:I63)*0.75)+(AVERAGE(L63:N63)*0.25) -> 0 | P63: =(AVERAGE(E63:G63)*0.75)+(AVERAGE(J63:L63)*0.25) -> 0 | R63: =S63-Q63 -> 0 | S63: =ROUND((P63*'Cost Pool'!$C$25),0) -> 0 | U63: =V63-T63 -> 0 | V63: =ROUND((O63*'Cost Pool'!$D$25),0) -> 0 | W63: =V63+R63 -> 0
A64: 306-FM | B64: =VLOOKUP(A64,Crosswalk,2,FALSE) -> Excluded | C64: =CONCATENATE((LEFT(B64,3))," - ",(VLOOKUP((LEFT(B64,3)),Funds,2,FALSE))) -> #N/A | D64: =VLOOKUP((RIGHT(B64,2)),Bureaus,2,FALSE) -> #N/A | E64: =IF(B64="Excluded",0,(IF(ISNA(VLOOKUP(A64,FY2008_09,10,FALSE)),0,(VLOOKUP(A64,FY2008_09,10,FALSE))))) -> 0 | F64: =IF(B64="Excluded",0,(IF(ISNA(VLOOKUP(A64,FY2009_10,10,FALSE)),0,(VLOOKUP(A64,FY2009_10,10,FALSE))))) -> 0 | G64: =IF(B64="Excluded",0,(IF(ISNA(VLOOKUP(A64,FY2010_11,10,FALSE)),0,(VLOOKUP(A64,FY2010_11,10,FALSE))))) -> 0 | H64: =IF(B64="Excluded",0,(IF(ISNA(VLOOKUP(A64,FY2011_12,10,FALSE)),0,(VLOOKUP(A64,FY2011_12,10,FALSE))))) -> 0 | I64: =IF(B64="Excluded",0,(IF(ISNA(VLOOKUP(A64,FY2012_13,10,FALSE)),0,(VLOOKUP(A64,FY2012_13,10,FALSE))))) -> 0 | J64: =IF(B64="Excluded",0,(IF(ISNA(VLOOKUP(A64,FY2008_09P,6,FALSE)),0,(VLOOKUP(A64,FY2008_09P,6,FALSE))))) -> 0 | K64: =IF(B64="Excluded",0,(IF(ISNA(VLOOKUP(A64,FY2009_10P,6,FALSE)),0,(VLOOKUP(A64,FY2009_10P,6,FALSE))))) -> 0 | L64: =IF(B64="Excluded",0,(IF(ISNA(VLOOKUP(A64,FY2010_11P,6,FALSE)),0,(VLOOKUP(A64,FY2010_11P,6,FALSE))))) -> 0 | M64: =IF(B64="Excluded",0,(IF(ISNA(VLOOKUP(A64,FY2011_12P,6,FALSE)),0,(VLOOKUP(A64,FY2011_12P,6,FALSE))))) -> 0 | N64: =IF(B64="Excluded",0,(IF(ISNA(VLOOKUP(A64,FY2012_13P,6,FALSE)),0,(VLOOKUP(A64,FY2012_13P,6,FALSE))))) -> 0 | O64: =(AVERAGE(G64:I64)*0.75)+(AVERAGE(L64:N64)*0.25) -> 0 | P64: =(AVERAGE(E64:G64)*0.75)+(AVERAGE(J64:L64)*0.25) -> 0 | R64: =S64-Q64 -> 0 | S64: =ROUND((P64*'Cost Pool'!$C$25),0) -> 0 | U64: =V64-T64 -> 0 | V64: =ROUND((O64*'Cost Pool'!$D$25),0) -> 0 | W64: =V64+R64 -> 0
A65: 317-FM | B65: =VLOOKUP(A65,Crosswalk,2,FALSE) -> Excluded | C65: =CONCATENATE((LEFT(B65,3))," - ",(VLOOKUP((LEFT(B65,3)),Funds,2,FALSE))) -> #N/A | D65: =VLOOKUP((RIGHT(B65,2)),Bureaus,2,FALSE) -> #N/A | E65: =IF(B65="Excluded",0,(IF(ISNA(VLOOKUP(A65,FY2008_09,10,FALSE)),0,(VLOOKUP(A65,FY2008_09,10,FALSE))))) -> 0 | F65: =IF(B65="Excluded",0,(IF(ISNA(VLOOKUP(A65,FY2009_10,10,FALSE)),0,(VLOOKUP(A65,FY2009_10,10,FALSE))))) -> 0 | G65: =IF(B65="Excluded",0,(IF(ISNA(VLOOKUP(A65,FY2010_11,10,FALSE)),0,(VLOOKUP(A65,FY2010_11,10,FALSE))))) -> 0 | H65: =IF(B65="Excluded",0,(IF(ISNA(VLOOKUP(A65,FY2011_12,10,FALSE)),0,(VLOOKUP(A65,FY2011_12,10,FALSE))))) -> 0 | I65: =IF(B65="Excluded",0,(IF(ISNA(VLOOKUP(A65,FY2012_13,10,FALSE)),0,(VLOOKUP(A65,FY2012_13,10,FALSE))))) -> 0 | J65: =IF(B65="Excluded",0,(IF(ISNA(VLOOKUP(A65,FY2008_09P,6,FALSE)),0,(VLOOKUP(A65,FY2008_09P,6,FALSE))))) -> 0 | K65: =IF(B65="Excluded",0,(IF(ISNA(VLOOKUP(A65,FY2009_10P,6,FALSE)),0,(VLOOKUP(A65,FY2009_10P,6,FALSE))))) -> 0 | L65: =IF(B65="Excluded",0,(IF(ISNA(VLOOKUP(A65,FY2010_11P,6,FALSE)),0,(VLOOKUP(A65,FY2010_11P,6,FALSE))))) -> 0 | M65: =IF(B65="Excluded",0,(IF(ISNA(VLOOKUP(A65,FY2011_12P,6,FALSE)),0,(VLOOKUP(A65,FY2011_12P,6,FALSE))))) -> 0 | N65: =IF(B65="Excluded",0,(IF(ISNA(VLOOKUP(A65,FY2012_13P,6,FALSE)),0,(VLOOKUP(A65,FY2012_13P,6,FALSE))))) -> 0 | O65: =(AVERAGE(G65:I65)*0.75)+(AVERAGE(L65:N65)*0.25) -> 0 | P65: =(AVERAGE(E65:G65)*0.75)+(AVERAGE(J65:L65)*0.25) -> 0 | R65: =S65-Q65 -> 0 | S65: =ROUND((P65*'Cost Pool'!$C$25),0) -> 0 | U65: =V65-T65 -> 0 | V65: =ROUND((O65*'Cost Pool'!$D$25),0) -> 0 | W65: =V65+R65 -> 0
A66: 400-MF | B66: =VLOOKUP(A66,Crosswalk,2,FALSE) -> 400 | C66: =CONCATENATE((LEFT(B66,3))," - ",(VLOOKUP((LEFT(B66,3)),Funds,2,FALSE))) -> 400 - BFRES Facilities GO Bond Construction Fund | D66: =VLOOKUP((RIGHT(B66,2)),Bureaus,2,FALSE) -> #N/A | E66: =IF(B66="Excluded",0,(IF(ISNA(VLOOKUP(A66,FY2008_09,10,FALSE)),0,(VLOOKUP(A66,FY2008_09,10,FALSE))))) -> 0.0044390179 | F66: =IF(B66="Excluded",0,(IF(ISNA(VLOOKUP(A66,FY2009_10,10,FALSE)),0,(VLOOKUP(A66,FY2009_10,10,FALSE))))) -> 0.0024850616 | G66: =IF(B66="Excluded",0,(IF(ISNA(VLOOKUP(A66,FY2010_11,10,FALSE)),0,(VLOOKUP(A66,FY2010_11,10,FALSE))))) -> 0.0014376258 | H66: =IF(B66="Excluded",0,(IF(ISNA(VLOOKUP(A66,FY2011_12,10,FALSE)),0,(VLOOKUP(A66,FY2011_12,10,FALSE))))) -> 0.00092333107 | I66: =IF(B66="Excluded",0,(IF(ISNA(VLOOKUP(A66,FY2012_13,10,FALSE)),0,(VLOOKUP(A66,FY2012_13,10,FALSE))))) -> 1.8897458e-06 | J66: =IF(B66="Excluded",0,(IF(ISNA(VLOOKUP(A66,FY2008_09P,6,FALSE)),0,(VLOOKUP(A66,FY2008_09P,6,FALSE))))) -> 0 | K66: =IF(B66="Excluded",0,(IF(ISNA(VLOOKUP(A66,FY2009_10P,6,FALSE)),0,(VLOOKUP(A66,FY2009_10P,6,FALSE))))) -> 0 | L66: =IF(B66="Excluded",0,(IF(ISNA(VLOOKUP(A66,FY2010_11P,6,FALSE)),0,(VLOOKUP(A66,FY2010_11P,6,FALSE))))) -> 0 | M66: =IF(B66="Excluded",0,(IF(ISNA(VLOOKUP(A66,FY2011_12P,6,FALSE)),0,(VLOOKUP(A66,FY2011_12P,6,FALSE))))) -> 0 | N66: =IF(B66="Excluded",0,(IF(ISNA(VLOOKUP(A66,FY2012_13P,6,FALSE)),0,(VLOOKUP(A66,FY2012_13P,6,FALSE))))) -> 0 | O66: =(AVERAGE(G66:I66)*0.75)+(AVERAGE(L66:N66)*0.25) -> 0.00059071166 | P66: =(AVERAGE(E66:G66)*0.75)+(AVERAGE(J66:L66)*0.25) -> 0.0020904263 | Q66: 44921 | R66: =S66-Q66 -> 39842 | S66: =ROUND((P66*'Cost Pool'!$C$25),0) -> 84763 | T66: 46490 | U66: =V66-T66 -> -19388 | V66: =ROUND((O66*'Cost Pool'!$D$25),0) -> 27102 | W66: =V66+R66 -> 66944
A67: 401-AU | B67: =VLOOKUP(A67,Crosswalk,2,FALSE) -> 401 | C67: =CONCATENATE((LEFT(B67,3))," - ",(VLOOKUP((LEFT(B67,3)),Funds,2,FALSE))) -> 401 - Local Improvement District Fund | D67: =VLOOKUP((RIGHT(B67,2)),Bureaus,2,FALSE) -> #N/A | E67: =IF(B67="Excluded",0,(IF(ISNA(VLOOKUP(A67,FY2008_09,10,FALSE)),0,(VLOOKUP(A67,FY2008_09,10,FALSE))))) -> 5.3482094e-06 | F67: =IF(B67="Excluded",0,(IF(ISNA(VLOOKUP(A67,FY2009_10,10,FALSE)),0,(VLOOKUP(A67,FY2009_10,10,FALSE))))) -> 5.2155436e-06 | G67: =IF(B67="Excluded",0,(IF(ISNA(VLOOKUP(A67,FY2010_11,10,FALSE)),0,(VLOOKUP(A67,FY2010_11,10,FALSE))))) -> 0.00047604341 | H67: =IF(B67="Excluded",0,(IF(ISNA(VLOOKUP(A67,FY2011_12,10,FALSE)),0,(VLOOKUP(A67,FY2011_12,10,FALSE))))) -> 3.3149543e-06 | I67: =IF(B67="Excluded",0,(IF(ISNA(VLOOKUP(A67,FY2012_13,10,FALSE)),0,(VLOOKUP(A67,FY2012_13,10,FALSE))))) -> 1.4863169e-06 | J67: =IF(B67="Excluded",0,(IF(ISNA(VLOOKUP(A67,FY2008_09P,6,FALSE)),0,(VLOOKUP(A67,FY2008_09P,6,FALSE))))) -> 0 | K67: =IF(B67="Excluded",0,(IF(ISNA(VLOOKUP(A67,FY2009_10P,6,FALSE)),0,(VLOOKUP(A67,FY2009_10P,6,FALSE))))) -> 0 | L67: =IF(B67="Excluded",0,(IF(ISNA(VLOOKUP(A67,FY2010_11P,6,FALSE)),0,(VLOOKUP(A67,FY2010_11P,6,FALSE))))) -> 0 | M67: =IF(B67="Excluded",0,(IF(ISNA(VLOOKUP(A67,FY2011_12P,6,FALSE)),0,(VLOOKUP(A67,FY2011_12P,6,FALSE))))) -> 0 | N67: =IF(B67="Excluded",0,(IF(ISNA(VLOOKUP(A67,FY2012_13P,6,FALSE)),0,(VLOOKUP(A67,FY2012_13P,6,FALSE))))) -> 0 | O67: =(AVERAGE(G67:I67)*0.75)+(AVERAGE(L67:N67)*0.25) -> 0.00012021117 | P67: =(AVERAGE(E67:G67)*0.75)+(AVERAGE(J67:L67)*0.25) -> 0.00012165179 | Q67: 74671 | R67: =S67-Q67 -> -69738 | S67: =ROUND((P67*'Cost Pool'!$C$25),0) -> 4933 | T67: 48200 | U67: =V67-T67 -> -42685 | V67: =ROUND((O67*'Cost Pool'!$D$25),0) -> 5515 | W67: =V67+R67 -> -64223
A68: 402-PK | B68: =VLOOKUP(A68,Crosswalk,2,FALSE) -> 402 | C68: =CONCATENATE((LEFT(B68,3))," - ",(VLOOKUP((LEFT(B68,3)),Funds,2,FALSE))) -> 402 - Parks Capital Improvement Program Fund | D68: =VLOOKUP((RIGHT(B68,2)),Bureaus,2,FALSE) -> #N/A | E68: =IF(B68="Excluded",0,(IF(ISNA(VLOOKUP(A68,FY2008_09,10,FALSE)),0,(VLOOKUP(A68,FY2008_09,10,FALSE))))) -> 0.013219754 | F68: =IF(B68="Excluded",0,(IF(ISNA(VLOOKUP(A68,FY2009_10,10,FALSE)),0,(VLOOKUP(A68,FY2009_10,10,FALSE))))) -> 0.0095530082 | G68: =IF(B68="Excluded",0,(IF(ISNA(VLOOKUP(A68,FY2010_11,10,FALSE)),0,(VLOOKUP(A68,FY2010_11,10,FALSE))))) -> 0.0028015104 | H68: =IF(B68="Excluded",0,(IF(ISNA(VLOOKUP(A68,FY2011_12,10,FALSE)),0,(VLOOKUP(A68,FY2011_12,10,FALSE))))) -> 0.0045358963 | I68: =IF(B68="Excluded",0,(IF(ISNA(VLOOKUP(A68,FY2012_13,10,FALSE)),0,(VLOOKUP(A68,FY2012_13,10,FALSE))))) -> 0.0080130269 | J68: =IF(B68="Excluded",0,(IF(ISNA(VLOOKUP(A68,FY2008_09P,6,FALSE)),0,(VLOOKUP(A68,FY2008_09P,6,FALSE))))) -> 0.0019120459 | K68: =IF(B68="Excluded",0,(IF(ISNA(VLOOKUP(A68,FY2009_10P,6,FALSE)),0,(VLOOKUP(A68,FY2009_10P,6,FALSE))))) -> 0.001835536 | L68: =IF(B68="Excluded",0,(IF(ISNA(VLOOKUP(A68,FY2010_11P,6,FALSE)),0,(VLOOKUP(A68,FY2010_11P,6,FALSE))))) -> 0.0016332684 | M68: =IF(B68="Excluded",0,(IF(ISNA(VLOOKUP(A68,FY2011_12P,6,FALSE)),0,(VLOOKUP(A68,FY2011_12P,6,FALSE))))) -> 0.0018247065 | N68: =IF(B68="Excluded",0,(IF(ISNA(VLOOKUP(A68,FY2012_13P,6,FALSE)),0,(VLOOKUP(A68,FY2012_13P,6,FALSE))))) -> 0.0011410966 | O68: =(AVERAGE(G68:I68)*0.75)+(AVERAGE(L68:N68)*0.25) -> 0.0042208643 | P68: =(AVERAGE(E68:G68)*0.75)+(AVERAGE(J68:L68)*0.25) -> 0.0068419723 | Q68: 245651 | R68: =S68-Q68 -> 31778 | S68: =ROUND((P68*'Cost Pool'!$C$25),0) -> 277429 | T68: 190847 | U68: =V68-T68 -> 2807 | V68: =ROUND((O68*'Cost Pool'!$D$25),0) -> 193654 | W68: =V68+R68 -> 225432
A69: 403-FR | B69: =VLOOKUP(A69,Crosswalk,2,FALSE) -> 403 | C69: =CONCATENATE((LEFT(B69,3))," - ",(VLOOKUP((LEFT(B69,3)),Funds,2,FALSE))) -> 403 - Public Safety GO Bond Fund | D69: =VLOOKUP((RIGHT(B69,2)),Bureaus,2,FALSE) -> #N/A | E69: =IF(B69="Excluded",0,(IF(ISNA(VLOOKUP(A69,FY2008_09,10,FALSE)),0,(VLOOKUP(A69,FY2008_09,10,FALSE))))) -> 0 | F69: =IF(B69="Excluded",0,(IF(ISNA(VLOOKUP(A69,FY2009_10,10,FALSE)),0,(VLOOKUP(A69,FY2009_10,10,FALSE))))) -> 0 | G69: =IF(B69="Excluded",0,(IF(ISNA(VLOOKUP(A69,FY2010_11,10,FALSE)),0,(VLOOKUP(A69,FY2010_11,10,FALSE))))) -> 0 | H69: =IF(B69="Excluded",0,(IF(ISNA(VLOOKUP(A69,FY2011_12,10,FALSE)),0,(VLOOKUP(A69,FY2011_12,10,FALSE))))) -> 0.00024254116 | I69: =IF(B69="Excluded",0,(IF(ISNA(VLOOKUP(A69,FY2012_13,10,FALSE)),0,(VLOOKUP(A69,FY2012_13,10,FALSE))))) -> 0.0021118227 | J69: =IF(B69="Excluded",0,(IF(ISNA(VLOOKUP(A69,FY2008_09P,6,FALSE)),0,(VLOOKUP(A69,FY2008_09P,6,FALSE))))) -> 0 | K69: =IF(B69="Excluded",0,(IF(ISNA(VLOOKUP(A69,FY2009_10P,6,FALSE)),0,(VLOOKUP(A69,FY2009_10P,6,FALSE))))) -> 0 | L69: =IF(B69="Excluded",0,(IF(ISNA(VLOOKUP(A69,FY2010_11P,6,FALSE)),0,(VLOOKUP(A69,FY2010_11P,6,FALSE))))) -> 0 | M69: =IF(B69="Excluded",0,(IF(ISNA(VLOOKUP(A69,FY2011_12P,6,FALSE)),0,(VLOOKUP(A69,FY2011_12P,6,FALSE))))) -> 0 | N69: =IF(B69="Excluded",0,(IF(ISNA(VLOOKUP(A69,FY2012_13P,6,FALSE)),0,(VLOOKUP(A69,FY2012_13P,6,FALSE))))) -> 0 | O69: =(AVERAGE(G69:I69)*0.75)+(AVERAGE(L69:N69)*0.25) -> 0.00058859098 | P69: =(AVERAGE(E69:G69)*0.75)+(AVERAGE(J69:L69)*0.25) -> 0 | R69: =S69-Q69 -> 0 | S69: =ROUND((P69*'Cost Pool'!$C$25),0) -> 0 | T69: 40107 | U69: =V69-T69 -> -13102 | V69: =ROUND((O69*'Cost Pool'!$D$25),0) -> 27005 | W69: =V69+R69 -> 27005
A70: 403-MF | B70: =VLOOKUP(A70,Crosswalk,2,FALSE) -> 403 | C70: =CONCATENATE((LEFT(B70,3))," - ",(VLOOKUP((LEFT(B70,3)),Funds,2,FALSE))) -> 403 - Public Safety GO Bond Fund | D70: =VLOOKUP((RIGHT(B70,2)),Bureaus,2,FALSE) -> #N/A | E70: =IF(B70="Excluded",0,(IF(ISNA(VLOOKUP(A70,FY2008_09,10,FALSE)),0,(VLOOKUP(A70,FY2008_09,10,FALSE))))) -> 0 | F70: =IF(B70="Excluded",0,(IF(ISNA(VLOOKUP(A70,FY2009_10,10,FALSE)),0,(VLOOKUP(A70,FY2009_10,10,FALSE))))) -> 0.0023599061 | G70: =IF(B70="Excluded",0,(IF(ISNA(VLOOKUP(A70,FY2010_11,10,FALSE)),0,(VLOOKUP(A70,FY2010_11,10,FALSE))))) -> 0.0023446412 | H70: =IF(B70="Excluded",0,(IF(ISNA(VLOOKUP(A70,FY2011_12,10,FALSE)),0,(VLOOKUP(A70,FY2011_12,10,FALSE))))) -> 0.001033464 | I70: =IF(B70="Excluded",0,(IF(ISNA(VLOOKUP(A70,FY2012_13,10,FALSE)),0,(VLOOKUP(A70,FY2012_13,10,FALSE))))) -> 0.0027263437 | J70: =IF(B70="Excluded",0,(IF(ISNA(VLOOKUP(A70,FY2008_09P,6,FALSE)),0,(VLOOKUP(A70,FY2008_09P,6,FALSE))))) -> 0 | K70: =IF(B70="Excluded",0,(IF(ISNA(VLOOKUP(A70,FY2009_10P,6,FALSE)),0,(VLOOKUP(A70,FY2009_10P,6,FALSE))))) -> 0 | L70: =IF(B70="Excluded",0,(IF(ISNA(VLOOKUP(A70,FY2010_11P,6,FALSE)),0,(VLOOKUP(A70,FY2010_11P,6,FALSE))))) -> 0 | M70: =IF(B70="Excluded",0,(IF(ISNA(VLOOKUP(A70,FY2011_12P,6,FALSE)),0,(VLOOKUP(A70,FY2011_12P,6,FALSE))))) -> 0 | N70: =IF(B70="Excluded",0,(IF(ISNA(VLOOKUP(A70,FY2012_13P,6,FALSE)),0,(VLOOKUP(A70,FY2012_13P,6,FALSE))))) -> 0 | O70: =(AVERAGE(G70:I70)*0.75)+(AVERAGE(L70:N70)*0.25) -> 0.0015261122 | P70: =(AVERAGE(E70:G70)*0.75)+(AVERAGE(J70:L70)*0.25) -> 0.0011761368 | Q70: 26306 | R70: =S70-Q70 -> 21384 | S70: =ROUND((P70*'Cost Pool'!$C$25),0) -> 47690 | U70: =V70-T70 -> 70018 | V70: =ROUND((O70*'Cost Pool'!$D$25),0) -> 70018 | W70: =V70+R70 -> 91402
A71: 500-PK | B71: =VLOOKUP(A71,Crosswalk,2,FALSE) -> Excluded | C71: =CONCATENATE((LEFT(B71,3))," - ",(VLOOKUP((LEFT(B71,3)),Funds,2,FALSE))) -> #N/A | D71: =VLOOKUP((RIGHT(B71,2)),Bureaus,2,FALSE) -> #N/A | E71: =IF(B71="Excluded",0,(IF(ISNA(VLOOKUP(A71,FY2008_09,10,FALSE)),0,(VLOOKUP(A71,FY2008_09,10,FALSE))))) -> 0 | F71: =IF(B71="Excluded",0,(IF(ISNA(VLOOKUP(A71,FY2009_10,10,FALSE)),0,(VLOOKUP(A71,FY2009_10,10,FALSE))))) -> 0 | G71: =IF(B71="Excluded",0,(IF(ISNA(VLOOKUP(A71,FY2010_11,10,FALSE)),0,(VLOOKUP(A71,FY2010_11,10,FALSE))))) -> 0 | H71: =IF(B71="Excluded",0,(IF(ISNA(VLOOKUP(A71,FY2011_12,10,FALSE)),0,(VLOOKUP(A71,FY2011_12,10,FALSE))))) -> 0 | I71: =IF(B71="Excluded",0,(IF(ISNA(VLOOKUP(A71,FY2012_13,10,FALSE)),0,(VLOOKUP(A71,FY2012_13,10,FALSE))))) -> 0 | J71: =IF(B71="Excluded",0,(IF(ISNA(VLOOKUP(A71,FY2008_09P,6,FALSE)),0,(VLOOKUP(A71,FY2008_09P,6,FALSE))))) -> 0 | K71: =IF(B71="Excluded",0,(IF(ISNA(VLOOKUP(A71,FY2009_10P,6,FALSE)),0,(VLOOKUP(A71,FY2009_10P,6,FALSE))))) -> 0 | L71: =IF(B71="Excluded",0,(IF(ISNA(VLOOKUP(A71,FY2010_11P,6,FALSE)),0,(VLOOKUP(A71,FY2010_11P,6,FALSE))))) -> 0 | M71: =IF(B71="Excluded",0,(IF(ISNA(VLOOKUP(A71,FY2011_12P,6,FALSE)),0,(VLOOKUP(A71,FY2011_12P,6,FALSE))))) -> 0 | N71: =IF(B71="Excluded",0,(IF(ISNA(VLOOKUP(A71,FY2012_13P,6,FALSE)),0,(VLOOKUP(A71,FY2012_13P,6,FALSE))))) -> 0 | O71: =(AVERAGE(G71:I71)*0.75)+(AVERAGE(L71:N71)*0.25) -> 0 | P71: =(AVERAGE(E71:G71)*0.75)+(AVERAGE(J71:L71)*0.25) -> 0 | R71: =S71-Q71 -> 0 | S71: =ROUND((P71*'Cost Pool'!$C$25),0) -> 0 | U71: =V71-T71 -> 0 | V71: =ROUND((O71*'Cost Pool'!$D$25),0) -> 0 | W71: =V71+R71 -> 0
A72: 600-ES | B72: =VLOOKUP(A72,Crosswalk,2,FALSE) -> 600 | C72: =CONCATENATE((LEFT(B72,3))," - ",(VLOOKUP((LEFT(B72,3)),Funds,2,FALSE))) -> 600 - Sewer System Operating Fund | D72: =VLOOKUP((RIGHT(B72,2)),Bureaus,2,FALSE) -> #N/A | E72: =IF(B72="Excluded",0,(IF(ISNA(VLOOKUP(A72,FY2008_09,10,FALSE)),0,(VLOOKUP(A72,FY2008_09,10,FALSE))))) -> 0.15699686 | F72: =IF(B72="Excluded",0,(IF(ISNA(VLOOKUP(A72,FY2009_10,10,FALSE)),0,(VLOOKUP(A72,FY2009_10,10,FALSE))))) -> 0.16002829 | G72: =IF(B72="Excluded",0,(IF(ISNA(VLOOKUP(A72,FY2010_11,10,FALSE)),0,(VLOOKUP(A72,FY2010_11,10,FALSE))))) -> 0.16154128 | H72: =IF(B72="Excluded",0,(IF(ISNA(VLOOKUP(A72,FY2011_12,10,FALSE)),0,(VLOOKUP(A72,FY2011_12,10,FALSE))))) -> 0.11581596 | I72: =IF(B72="Excluded",0,(IF(ISNA(VLOOKUP(A72,FY2012_13,10,FALSE)),0,(VLOOKUP(A72,FY2012_13,10,FALSE))))) -> 0.12779373 | J72: =IF(B72="Excluded",0,(IF(ISNA(VLOOKUP(A72,FY2008_09P,6,FALSE)),0,(VLOOKUP(A72,FY2008_09P,6,FALSE))))) -> 0.067686424 | K72: =IF(B72="Excluded",0,(IF(ISNA(VLOOKUP(A72,FY2009_10P,6,FALSE)),0,(VLOOKUP(A72,FY2009_10P,6,FALSE))))) -> 0.070117474 | L72: =IF(B72="Excluded",0,(IF(ISNA(VLOOKUP(A72,FY2010_11P,6,FALSE)),0,(VLOOKUP(A72,FY2010_11P,6,FALSE))))) -> 0.072240719 | M72: =IF(B72="Excluded",0,(IF(ISNA(VLOOKUP(A72,FY2011_12P,6,FALSE)),0,(VLOOKUP(A72,FY2011_12P,6,FALSE))))) -> 0.069460495 | N72: =IF(B72="Excluded",0,(IF(ISNA(VLOOKUP(A72,FY2012_13P,6,FALSE)),0,(VLOOKUP(A72,FY2012_13P,6,FALSE))))) -> 0.063901409 | O72: =(AVERAGE(G72:I72)*0.75)+(AVERAGE(L72:N72)*0.25) -> 0.11842129 | P72: =(AVERAGE(E72:G72)*0.75)+(AVERAGE(J72:L72)*0.25) -> 0.13714532 | Q72: 7371659 | R72: =S72-Q72 -> -1810680 | S72: =ROUND((P72*'Cost Pool'!$C$25),0) -> 5560979 | T72: 7072025 | U72: =V72-T72 -> -1638846 | V72: =ROUND((O72*'Cost Pool'!$D$25),0) -> 5433179 | W72: =V72+R72 -> 3622499
A73: 601-WA | B73: =VLOOKUP(A73,Crosswalk,2,FALSE) -> 601 | C73: =CONCATENATE((LEFT(B73,3))," - ",(VLOOKUP((LEFT(B73,3)),Funds,2,FALSE))) -> 601 - Hydroelectric Power Operating Fund | D73: =VLOOKUP((RIGHT(B73,2)),Bureaus,2,FALSE) -> #N/A | E73: =IF(B73="Excluded",0,(IF(ISNA(VLOOKUP(A73,FY2008_09,10,FALSE)),0,(VLOOKUP(A73,FY2008_09,10,FALSE))))) -> 0.00069501535 | F73: =IF(B73="Excluded",0,(IF(ISNA(VLOOKUP(A73,FY2009_10,10,FALSE)),0,(VLOOKUP(A73,FY2009_10,10,FALSE))))) -> 0.00037674072 | G73: =IF(B73="Excluded",0,(IF(ISNA(VLOOKUP(A73,FY2010_11,10,FALSE)),0,(VLOOKUP(A73,FY2010_11,10,FALSE))))) -> 0.0004172777 | H73: =IF(B73="Excluded",0,(IF(ISNA(VLOOKUP(A73,FY2011_12,10,FALSE)),0,(VLOOKUP(A73,FY2011_12,10,FALSE))))) -> 0.00038467516 | I73: =IF(B73="Excluded",0,(IF(ISNA(VLOOKUP(A73,FY2012_13,10,FALSE)),0,(VLOOKUP(A73,FY2012_13,10,FALSE))))) -> 0.00042401808 | J73: =IF(B73="Excluded",0,(IF(ISNA(VLOOKUP(A73,FY2008_09P,6,FALSE)),0,(VLOOKUP(A73,FY2008_09P,6,FALSE))))) -> 0.00038240918 | K73: =IF(B73="Excluded",0,(IF(ISNA(VLOOKUP(A73,FY2009_10P,6,FALSE)),0,(VLOOKUP(A73,FY2009_10P,6,FALSE))))) -> 0.0003671072 | L73: =IF(B73="Excluded",0,(IF(ISNA(VLOOKUP(A73,FY2010_11P,6,FALSE)),0,(VLOOKUP(A73,FY2010_11P,6,FALSE))))) -> 0.0003769081 | M73: =IF(B73="Excluded",0,(IF(ISNA(VLOOKUP(A73,FY2011_12P,6,FALSE)),0,(VLOOKUP(A73,FY2011_12P,6,FALSE))))) -> 0.00036494131 | N73: =IF(B73="Excluded",0,(IF(ISNA(VLOOKUP(A73,FY2012_13P,6,FALSE)),0,(VLOOKUP(A73,FY2012_13P,6,FALSE))))) -> 0.00034232898 | O73: =(AVERAGE(G73:I73)*0.75)+(AVERAGE(L73:N73)*0.25) -> 0.00039684093 | P73: =(AVERAGE(E73:G73)*0.75)+(AVERAGE(J73:L73)*0.25) -> 0.00046612715 | Q73: 42063 | R73: =S73-Q73 -> -23162 | S73: =ROUND((P73*'Cost Pool'!$C$25),0) -> 18901 | T73: 29624 | U73: =V73-T73 -> -11417 | V73: =ROUND((O73*'Cost Pool'!$D$25),0) -> 18207 | W73: =V73+R73 -> -4955
A74: 602-WA | B74: =VLOOKUP(A74,Crosswalk,2,FALSE) -> 602 | C74: =CONCATENATE((LEFT(B74,3))," - ",(VLOOKUP((LEFT(B74,3)),Funds,2,FALSE))) -> 602 - Water Fund | D74: =VLOOKUP((RIGHT(B74,2)),Bureaus,2,FALSE) -> #N/A | E74: =IF(B74="Excluded",0,(IF(ISNA(VLOOKUP(A74,FY2008_09,10,FALSE)),0,(VLOOKUP(A74,FY2008_09,10,FALSE))))) -> 0.091970499 | F74: =IF(B74="Excluded",0,(IF(ISNA(VLOOKUP(A74,FY2009_10,10,FALSE)),0,(VLOOKUP(A74,FY2009_10,10,FALSE))))) -> 0.088735428 | G74: =IF(B74="Excluded",0,(IF(ISNA(VLOOKUP(A74,FY2010_11,10,FALSE)),0,(VLOOKUP(A74,FY2010_11,10,FALSE))))) -> 0.086632971 | H74: =IF(B74="Excluded",0,(IF(ISNA(VLOOKUP(A74,FY2011_12,10,FALSE)),0,(VLOOKUP(A74,FY2011_12,10,FALSE))))) -> 0.096805221 | I74: =IF(B74="Excluded",0,(IF(ISNA(VLOOKUP(A74,FY2012_13,10,FALSE)),0,(VLOOKUP(A74,FY2012_13,10,FALSE))))) -> 0.12364508 | J74: =IF(B74="Excluded",0,(IF(ISNA(VLOOKUP(A74,FY2008_09P,6,FALSE)),0,(VLOOKUP(A74,FY2008_09P,6,FALSE))))) -> 0.087699171 | K74: =IF(B74="Excluded",0,(IF(ISNA(VLOOKUP(A74,FY2009_10P,6,FALSE)),0,(VLOOKUP(A74,FY2009_10P,6,FALSE))))) -> 0.080641214 | L74: =IF(B74="Excluded",0,(IF(ISNA(VLOOKUP(A74,FY2010_11P,6,FALSE)),0,(VLOOKUP(A74,FY2010_11P,6,FALSE))))) -> 0.082668509 | M74: =IF(B74="Excluded",0,(IF(ISNA(VLOOKUP(A74,FY2011_12P,6,FALSE)),0,(VLOOKUP(A74,FY2011_12P,6,FALSE))))) -> 0.078584028 | N74: =IF(B74="Excluded",0,(IF(ISNA(VLOOKUP(A74,FY2012_13P,6,FALSE)),0,(VLOOKUP(A74,FY2012_13P,6,FALSE))))) -> 0.071660866 | O74: =(AVERAGE(G74:I74)*0.75)+(AVERAGE(L74:N74)*0.25) -> 0.096180269 | P74: =(AVERAGE(E74:G74)*0.75)+(AVERAGE(J74:L74)*0.25) -> 0.087752132 | Q74: 4029348 | R74: =S74-Q74 -> -471168 | S74: =ROUND((P74*'Cost Pool'!$C$25),0) -> 3558180 | T74: 4533246 | U74: =V74-T74 -> -120487 | V74: =ROUND((O74*'Cost Pool'!$D$25),0) -> 4412759 | W74: =V74+R74 -> 3941591
A75: 603-PK | B75: =VLOOKUP(A75,Crosswalk,2,FALSE) -> 603 | C75: =CONCATENATE((LEFT(B75,3))," - ",(VLOOKUP((LEFT(B75,3)),Funds,2,FALSE))) -> 603 - Golf Fund | D75: =VLOOKUP((RIGHT(B75,2)),Bureaus,2,FALSE) -> #N/A | E75: =IF(B75="Excluded",0,(IF(ISNA(VLOOKUP(A75,FY2008_09,10,FALSE)),0,(VLOOKUP(A75,FY2008_09,10,FALSE))))) -> 0.0073643896 | F75: =IF(B75="Excluded",0,(IF(ISNA(VLOOKUP(A75,FY2009_10,10,FALSE)),0,(VLOOKUP(A75,FY2009_10,10,FALSE))))) -> 0.0072196066 | G75: =IF(B75="Excluded",0,(IF(ISNA(VLOOKUP(A75,FY2010_11,10,FALSE)),0,(VLOOKUP(A75,FY2010_11,10,FALSE))))) -> 0.0066473078 | H75: =IF(B75="Excluded",0,(IF(ISNA(VLOOKUP(A75,FY2011_12,10,FALSE)),0,(VLOOKUP(A75,FY2011_12,10,FALSE))))) -> 0.0069989809 | I75: =IF(B75="Excluded",0,(IF(ISNA(VLOOKUP(A75,FY2012_13,10,FALSE)),0,(VLOOKUP(A75,FY2012_13,10,FALSE))))) -> 0.0071553121 | J75: =IF(B75="Excluded",0,(IF(ISNA(VLOOKUP(A75,FY2008_09P,6,FALSE)),0,(VLOOKUP(A75,FY2008_09P,6,FALSE))))) -> 0.0052262588 | K75: =IF(B75="Excluded",0,(IF(ISNA(VLOOKUP(A75,FY2009_10P,6,FALSE)),0,(VLOOKUP(A75,FY2009_10P,6,FALSE))))) -> 0.0063631914 | L75: =IF(B75="Excluded",0,(IF(ISNA(VLOOKUP(A75,FY2010_11P,6,FALSE)),0,(VLOOKUP(A75,FY2010_11P,6,FALSE))))) -> 0.0070356178 | M75: =IF(B75="Excluded",0,(IF(ISNA(VLOOKUP(A75,FY2011_12P,6,FALSE)),0,(VLOOKUP(A75,FY2011_12P,6,FALSE))))) -> 0.0053524725 | N75: =IF(B75="Excluded",0,(IF(ISNA(VLOOKUP(A75,FY2012_13P,6,FALSE)),0,(VLOOKUP(A75,FY2012_13P,6,FALSE))))) -> 0.0054772637 | O75: =(AVERAGE(G75:I75)*0.75)+(AVERAGE(L75:N75)*0.25) -> 0.0066891797 | P75: =(AVERAGE(E75:G75)*0.75)+(AVERAGE(J75:L75)*0.25) -> 0.006859915 | Q75: 258742 | R75: =S75-Q75 -> 19414 | S75: =ROUND((P75*'Cost Pool'!$C$25),0) -> 278156 | T75: 302239 | U75: =V75-T75 -> 4661 | V75: =ROUND((O75*'Cost Pool'!$D$25),0) -> 306900 | W75: =V75+R75 -> 326314
A76: 604-PK | B76: =VLOOKUP(A76,Crosswalk,2,FALSE) -> 604 | C76: =CONCATENATE((LEFT(B76,3))," - ",(VLOOKUP((LEFT(B76,3)),Funds,2,FALSE))) -> 604 - Portland International Raceway Fund | D76: =VLOOKUP((RIGHT(B76,2)),Bureaus,2,FALSE) -> #N/A | E76: =IF(B76="Excluded",0,(IF(ISNA(VLOOKUP(A76,FY2008_09,10,FALSE)),0,(VLOOKUP(A76,FY2008_09,10,FALSE))))) -> 0.0015100923 | F76: =IF(B76="Excluded",0,(IF(ISNA(VLOOKUP(A76,FY2009_10,10,FALSE)),0,(VLOOKUP(A76,FY2009_10,10,FALSE))))) -> 0.00155141 | G76: =IF(B76="Excluded",0,(IF(ISNA(VLOOKUP(A76,FY2010_11,10,FALSE)),0,(VLOOKUP(A76,FY2010_11,10,FALSE))))) -> 0.0014160075 | H76: =IF(B76="Excluded",0,(IF(ISNA(VLOOKUP(A76,FY2011_12,10,FALSE)),0,(VLOOKUP(A76,FY2011_12,10,FALSE))))) -> 0.0014106114 | I76: =IF(B76="Excluded",0,(IF(ISNA(VLOOKUP(A76,FY2012_13,10,FALSE)),0,(VLOOKUP(A76,FY2012_13,10,FALSE))))) -> 0.0013745464 | J76: =IF(B76="Excluded",0,(IF(ISNA(VLOOKUP(A76,FY2008_09P,6,FALSE)),0,(VLOOKUP(A76,FY2008_09P,6,FALSE))))) -> 0.0062460166 | K76: =IF(B76="Excluded",0,(IF(ISNA(VLOOKUP(A76,FY2009_10P,6,FALSE)),0,(VLOOKUP(A76,FY2009_10P,6,FALSE))))) -> 0.0061184533 | L76: =IF(B76="Excluded",0,(IF(ISNA(VLOOKUP(A76,FY2010_11P,6,FALSE)),0,(VLOOKUP(A76,FY2010_11P,6,FALSE))))) -> 0.0054023494 | M76: =IF(B76="Excluded",0,(IF(ISNA(VLOOKUP(A76,FY2011_12P,6,FALSE)),0,(VLOOKUP(A76,FY2011_12P,6,FALSE))))) -> 0.0079070616 | N76: =IF(B76="Excluded",0,(IF(ISNA(VLOOKUP(A76,FY2012_13P,6,FALSE)),0,(VLOOKUP(A76,FY2012_13P,6,FALSE))))) -> 0.0084441148 | O76: =(AVERAGE(G76:I76)*0.75)+(AVERAGE(L76:N76)*0.25) -> 0.0028630851 | P76: =(AVERAGE(E76:G76)*0.75)+(AVERAGE(J76:L76)*0.25) -> 0.0025999457 | Q76: 55684 | R76: =S76-Q76 -> 49739 | S76: =ROUND((P76*'Cost Pool'!$C$25),0) -> 105423 | T76: 63031 | U76: =V76-T76 -> 68328 | V76: =ROUND((O76*'Cost Pool'!$D$25),0) -> 131359 | W76: =V76+R76 -> 181098
A77: 605-PN | B77: =VLOOKUP(A77,Crosswalk,2,FALSE) -> 605 | C77: =CONCATENATE((LEFT(B77,3))," - ",(VLOOKUP((LEFT(B77,3)),Funds,2,FALSE))) -> 605 - Solid Waste Management Fund | D77: =VLOOKUP((RIGHT(B77,2)),Bureaus,2,FALSE) -> #N/A | E77: =IF(B77="Excluded",0,(IF(ISNA(VLOOKUP(A77,FY2008_09,10,FALSE)),0,(VLOOKUP(A77,FY2008_09,10,FALSE))))) -> 0.0026965568 | F77: =IF(B77="Excluded",0,(IF(ISNA(VLOOKUP(A77,FY2009_10,10,FALSE)),0,(VLOOKUP(A77,FY2009_10,10,FALSE))))) -> 0.0029226876 | G77: =IF(B77="Excluded",0,(IF(ISNA(VLOOKUP(A77,FY2010_11,10,FALSE)),0,(VLOOKUP(A77,FY2010_11,10,FALSE))))) -> 0.0033945689 | H77: =IF(B77="Excluded",0,(IF(ISNA(VLOOKUP(A77,FY2011_12,10,FALSE)),0,(VLOOKUP(A77,FY2011_12,10,FALSE))))) -> 0.0039272095 | I77: =IF(B77="Excluded",0,(IF(ISNA(VLOOKUP(A77,FY2012_13,10,FALSE)),0,(VLOOKUP(A77,FY2012_13,10,FALSE))))) -> 0.0036343729 | J77: =IF(B77="Excluded",0,(IF(ISNA(VLOOKUP(A77,FY2008_09P,6,FALSE)),0,(VLOOKUP(A77,FY2008_09P,6,FALSE))))) -> 0.0038240918 | K77: =IF(B77="Excluded",0,(IF(ISNA(VLOOKUP(A77,FY2009_10P,6,FALSE)),0,(VLOOKUP(A77,FY2009_10P,6,FALSE))))) -> 0.0040381791 | L77: =IF(B77="Excluded",0,(IF(ISNA(VLOOKUP(A77,FY2010_11P,6,FALSE)),0,(VLOOKUP(A77,FY2010_11P,6,FALSE))))) -> 0.003769081 | M77: =IF(B77="Excluded",0,(IF(ISNA(VLOOKUP(A77,FY2011_12P,6,FALSE)),0,(VLOOKUP(A77,FY2011_12P,6,FALSE))))) -> 0.0038927073 | N77: =IF(B77="Excluded",0,(IF(ISNA(VLOOKUP(A77,FY2012_13P,6,FALSE)),0,(VLOOKUP(A77,FY2012_13P,6,FALSE))))) -> 0.0033091801 | O77: =(AVERAGE(G77:I77)*0.75)+(AVERAGE(L77:N77)*0.25) -> 0.0036532852 | P77: =(AVERAGE(E77:G77)*0.75)+(AVERAGE(J77:L77)*0.25) -> 0.0032227326 | Q77: 151418 | R77: =S77-Q77 -> -20742 | S77: =ROUND((P77*'Cost Pool'!$C$25),0) -> 130676 | T77: 188043 | U77: =V77-T77 -> -20430 | V77: =ROUND((O77*'Cost Pool'!$D$25),0) -> 167613 | W77: =V77+R77 -> 146871
A78: 606-TR | B78: =VLOOKUP(A78,Crosswalk,2,FALSE) -> 606 | C78: =CONCATENATE((LEFT(B78,3))," - ",(VLOOKUP((LEFT(B78,3)),Funds,2,FALSE))) -> 606 - Parking Facilities Fund | D78: =VLOOKUP((RIGHT(B78,2)),Bureaus,2,FALSE) -> #N/A | E78: =IF(B78="Excluded",0,(IF(ISNA(VLOOKUP(A78,FY2008_09,10,FALSE)),0,(VLOOKUP(A78,FY2008_09,10,FALSE))))) -> 0.0045315929 | F78: =IF(B78="Excluded",0,(IF(ISNA(VLOOKUP(A78,FY2009_10,10,FALSE)),0,(VLOOKUP(A78,FY2009_10,10,FALSE))))) -> 0.0036505998 | G78: =IF(B78="Excluded",0,(IF(ISNA(VLOOKUP(A78,FY2010_11,10,FALSE)),0,(VLOOKUP(A78,FY2010_11,10,FALSE))))) -> 0.0036924879 | H78: =IF(B78="Excluded",0,(IF(ISNA(VLOOKUP(A78,FY2011_12,10,FALSE)),0,(VLOOKUP(A78,FY2011_12,10,FALSE))))) -> 0.0049173076 | I78: =IF(B78="Excluded",0,(IF(ISNA(VLOOKUP(A78,FY2012_13,10,FALSE)),0,(VLOOKUP(A78,FY2012_13,10,FALSE))))) -> 0.0033352994 | J78: =IF(B78="Excluded",0,(IF(ISNA(VLOOKUP(A78,FY2008_09P,6,FALSE)),0,(VLOOKUP(A78,FY2008_09P,6,FALSE))))) -> 0 | K78: =IF(B78="Excluded",0,(IF(ISNA(VLOOKUP(A78,FY2009_10P,6,FALSE)),0,(VLOOKUP(A78,FY2009_10P,6,FALSE))))) -> 0 | L78: =IF(B78="Excluded",0,(IF(ISNA(VLOOKUP(A78,FY2010_11P,6,FALSE)),0,(VLOOKUP(A78,FY2010_11P,6,FALSE))))) -> 0 | M78: =IF(B78="Excluded",0,(IF(ISNA(VLOOKUP(A78,FY2011_12P,6,FALSE)),0,(VLOOKUP(A78,FY2011_12P,6,FALSE))))) -> 0 | N78: =IF(B78="Excluded",0,(IF(ISNA(VLOOKUP(A78,FY2012_13P,6,FALSE)),0,(VLOOKUP(A78,FY2012_13P,6,FALSE))))) -> 0.00011410966 | O78: =(AVERAGE(G78:I78)*0.75)+(AVERAGE(L78:N78)*0.25) -> 0.0029957829 | P78: =(AVERAGE(E78:G78)*0.75)+(AVERAGE(J78:L78)*0.25) -> 0.0029686701 | Q78: 195603 | R78: =S78-Q78 -> -75229 | S78: =ROUND((P78*'Cost Pool'!$C$25),0) -> 120374 | T78: 169525 | U78: =V78-T78 -> -32078 | V78: =ROUND((O78*'Cost Pool'!$D$25),0) -> 137447 | W78: =V78+R78 -> 62218
A79: 607-MF | B79: =VLOOKUP(A79,Crosswalk,2,FALSE) -> 607 | C79: =CONCATENATE((LEFT(B79,3))," - ",(VLOOKUP((LEFT(B79,3)),Funds,2,FALSE))) -> 607 - Spectator Facilities Operating Fund | D79: =VLOOKUP((RIGHT(B79,2)),Bureaus,2,FALSE) -> #N/A | E79: =IF(B79="Excluded",0,(IF(ISNA(VLOOKUP(A79,FY2008_09,10,FALSE)),0,(VLOOKUP(A79,FY2008_09,10,FALSE))))) -> 0.00259981 | F79: =IF(B79="Excluded",0,(IF(ISNA(VLOOKUP(A79,FY2009_10,10,FALSE)),0,(VLOOKUP(A79,FY2009_10,10,FALSE))))) -> 0.0030888634 | G79: =IF(B79="Excluded",0,(IF(ISNA(VLOOKUP(A79,FY2010_11,10,FALSE)),0,(VLOOKUP(A79,FY2010_11,10,FALSE))))) -> 0.0080034125 | H79: =IF(B79="Excluded",0,(IF(ISNA(VLOOKUP(A79,FY2011_12,10,FALSE)),0,(VLOOKUP(A79,FY2011_12,10,FALSE))))) -> 0.0016023388 | I79: =IF(B79="Excluded",0,(IF(ISNA(VLOOKUP(A79,FY2012_13,10,FALSE)),0,(VLOOKUP(A79,FY2012_13,10,FALSE))))) -> 0.0031211843 | J79: =IF(B79="Excluded",0,(IF(ISNA(VLOOKUP(A79,FY2008_09P,6,FALSE)),0,(VLOOKUP(A79,FY2008_09P,6,FALSE))))) -> 0 | K79: =IF(B79="Excluded",0,(IF(ISNA(VLOOKUP(A79,FY2009_10P,6,FALSE)),0,(VLOOKUP(A79,FY2009_10P,6,FALSE))))) -> 0 | L79: =IF(B79="Excluded",0,(IF(ISNA(VLOOKUP(A79,FY2010_11P,6,FALSE)),0,(VLOOKUP(A79,FY2010_11P,6,FALSE))))) -> 0 | M79: =IF(B79="Excluded",0,(IF(ISNA(VLOOKUP(A79,FY2011_12P,6,FALSE)),0,(VLOOKUP(A79,FY2011_12P,6,FALSE))))) -> 0 | N79: =IF(B79="Excluded",0,(IF(ISNA(VLOOKUP(A79,FY2012_13P,6,FALSE)),0,(VLOOKUP(A79,FY2012_13P,6,FALSE))))) -> 0.00011410966 | O79: =(AVERAGE(G79:I79)*0.75)+(AVERAGE(L79:N79)*0.25) -> 0.003191243 | P79: =(AVERAGE(E79:G79)*0.75)+(AVERAGE(J79:L79)*0.25) -> 0.0034230215 | Q79: 180109 | R79: =S79-Q79 -> -41312 | S79: =ROUND((P79*'Cost Pool'!$C$25),0) -> 138797 | T79: 197855 | U79: =V79-T79 -> -51441 | V79: =ROUND((O79*'Cost Pool'!$D$25),0) -> 146414 | W79: =V79+R79 -> 105102
A80: 608-ES | B80: =VLOOKUP(A80,Crosswalk,2,FALSE) -> 608 | C80: =CONCATENATE((LEFT(B80,3))," - ",(VLOOKUP((LEFT(B80,3)),Funds,2,FALSE))) -> 608 - Environmental Remediation Fund | D80: =VLOOKUP((RIGHT(B80,2)),Bureaus,2,FALSE) -> #N/A | E80: =IF(B80="Excluded",0,(IF(ISNA(VLOOKUP(A80,FY2008_09,10,FALSE)),0,(VLOOKUP(A80,FY2008_09,10,FALSE))))) -> 0.0049115206 | F80: =IF(B80="Excluded",0,(IF(ISNA(VLOOKUP(A80,FY2009_10,10,FALSE)),0,(VLOOKUP(A80,FY2009_10,10,FALSE))))) -> 0.0057749698 | G80: =IF(B80="Excluded",0,(IF(ISNA(VLOOKUP(A80,FY2010_11,10,FALSE)),0,(VLOOKUP(A80,FY2010_11,10,FALSE))))) -> 0.0052480583 | H80: =IF(B80="Excluded",0,(IF(ISNA(VLOOKUP(A80,FY2011_12,10,FALSE)),0,(VLOOKUP(A80,FY2011_12,10,FALSE))))) -> 0.0037814071 | I80: =IF(B80="Excluded",0,(IF(ISNA(VLOOKUP(A80,FY2012_13,10,FALSE)),0,(VLOOKUP(A80,FY2012_13,10,FALSE))))) -> 0.0024017644 | J80: =IF(B80="Excluded",0,(IF(ISNA(VLOOKUP(A80,FY2008_09P,6,FALSE)),0,(VLOOKUP(A80,FY2008_09P,6,FALSE))))) -> 0.00063734863 | K80: =IF(B80="Excluded",0,(IF(ISNA(VLOOKUP(A80,FY2009_10P,6,FALSE)),0,(VLOOKUP(A80,FY2009_10P,6,FALSE))))) -> 0.00061184533 | L80: =IF(B80="Excluded",0,(IF(ISNA(VLOOKUP(A80,FY2010_11P,6,FALSE)),0,(VLOOKUP(A80,FY2010_11P,6,FALSE))))) -> 0.00075381619 | M80: =IF(B80="Excluded",0,(IF(ISNA(VLOOKUP(A80,FY2011_12P,6,FALSE)),0,(VLOOKUP(A80,FY2011_12P,6,FALSE))))) -> 0.00060823551 | N80: =IF(B80="Excluded",0,(IF(ISNA(VLOOKUP(A80,FY2012_13P,6,FALSE)),0,(VLOOKUP(A80,FY2012_13P,6,FALSE))))) -> 0.00045643864 | O80: =(AVERAGE(G80:I80)*0.75)+(AVERAGE(L80:N80)*0.25) -> 0.0030093483 | P80: =(AVERAGE(E80:G80)*0.75)+(AVERAGE(J80:L80)*0.25) -> 0.0041505547 | Q80: 160973 | R80: =S80-Q80 -> 7324 | S80: =ROUND((P80*'Cost Pool'!$C$25),0) -> 168297 | T80: 170185 | U80: =V80-T80 -> -32116 | V80: =ROUND((O80*'Cost Pool'!$D$25),0) -> 138069 | W80: =V80+R80 -> 145393
A81: 614-ES | B81: =VLOOKUP(A81,Crosswalk,2,FALSE) -> 600 | C81: =CONCATENATE((LEFT(B81,3))," - ",(VLOOKUP((LEFT(B81,3)),Funds,2,FALSE))) -> 600 - Sewer System Operating Fund | D81: =VLOOKUP((RIGHT(B81,2)),Bureaus,2,FALSE) -> #N/A | E81: =IF(B81="Excluded",0,(IF(ISNA(VLOOKUP(A81,FY2008_09,10,FALSE)),0,(VLOOKUP(A81,FY2008_09,10,FALSE))))) -> 8.6802474e-06 | F81: =IF(B81="Excluded",0,(IF(ISNA(VLOOKUP(A81,FY2009_10,10,FALSE)),0,(VLOOKUP(A81,FY2009_10,10,FALSE))))) -> 0 | G81: =IF(B81="Excluded",0,(IF(ISNA(VLOOKUP(A81,FY2010_11,10,FALSE)),0,(VLOOKUP(A81,FY2010_11,10,FALSE))))) -> 0 | H81: =IF(B81="Excluded",0,(IF(ISNA(VLOOKUP(A81,FY2011_12,10,FALSE)),0,(VLOOKUP(A81,FY2011_12,10,FALSE))))) -> 0 | I81: =IF(B81="Excluded",0,(IF(ISNA(VLOOKUP(A81,FY2012_13,10,FALSE)),0,(VLOOKUP(A81,FY2012_13,10,FALSE))))) -> 0 | J81: =IF(B81="Excluded",0,(IF(ISNA(VLOOKUP(A81,FY2008_09P,6,FALSE)),0,(VLOOKUP(A81,FY2008_09P,6,FALSE))))) -> 0 | K81: =IF(B81="Excluded",0,(IF(ISNA(VLOOKUP(A81,FY2009_10P,6,FALSE)),0,(VLOOKUP(A81,FY2009_10P,6,FALSE))))) -> 0 | L81: =IF(B81="Excluded",0,(IF(ISNA(VLOOKUP(A81,FY2010_11P,6,FALSE)),0,(VLOOKUP(A81,FY2010_11P,6,FALSE))))) -> 0 | M81: =IF(B81="Excluded",0,(IF(ISNA(VLOOKUP(A81,FY2011_12P,6,FALSE)),0,(VLOOKUP(A81,FY2011_12P,6,FALSE))))) -> 0 | N81: =IF(B81="Excluded",0,(IF(ISNA(VLOOKUP(A81,FY2012_13P,6,FALSE)),0,(VLOOKUP(A81,FY2012_13P,6,FALSE))))) -> 0 | O81: =(AVERAGE(G81:I81)*0.75)+(AVERAGE(L81:N81)*0.25) -> 0 | P81: =(AVERAGE(E81:G81)*0.75)+(AVERAGE(J81:L81)*0.25) -> 2.1700619e-06 | R81: =S81-Q81 -> 88 | S81: =ROUND((P81*'Cost Pool'!$C$25),0) -> 88 | U81: =V81-T81 -> 0 | V81: =ROUND((O81*'Cost Pool'!$D$25),0) -> 0 | W81: =V81+R81 -> 88
A82: 621-HC | B82: =VLOOKUP(A82,Crosswalk,2,FALSE) -> Excluded | C82: =CONCATENATE((LEFT(B82,3))," - ",(VLOOKUP((LEFT(B82,3)),Funds,2,FALSE))) -> #N/A | D82: =VLOOKUP((RIGHT(B82,2)),Bureaus,2,FALSE) -> #N/A | E82: =IF(B82="Excluded",0,(IF(ISNA(VLOOKUP(A82,FY2008_09,10,FALSE)),0,(VLOOKUP(A82,FY2008_09,10,FALSE))))) -> 0 | F82: =IF(B82="Excluded",0,(IF(ISNA(VLOOKUP(A82,FY2009_10,10,FALSE)),0,(VLOOKUP(A82,FY2009_10,10,FALSE))))) -> 0 | G82: =IF(B82="Excluded",0,(IF(ISNA(VLOOKUP(A82,FY2010_11,10,FALSE)),0,(VLOOKUP(A82,FY2010_11,10,FALSE))))) -> 0 | H82: =IF(B82="Excluded",0,(IF(ISNA(VLOOKUP(A82,FY2011_12,10,FALSE)),0,(VLOOKUP(A82,FY2011_12,10,FALSE))))) -> 0 | I82: =IF(B82="Excluded",0,(IF(ISNA(VLOOKUP(A82,FY2012_13,10,FALSE)),0,(VLOOKUP(A82,FY2012_13,10,FALSE))))) -> 0 | J82: =IF(B82="Excluded",0,(IF(ISNA(VLOOKUP(A82,FY2008_09P,6,FALSE)),0,(VLOOKUP(A82,FY2008_09P,6,FALSE))))) -> 0 | K82: =IF(B82="Excluded",0,(IF(ISNA(VLOOKUP(A82,FY2009_10P,6,FALSE)),0,(VLOOKUP(A82,FY2009_10P,6,FALSE))))) -> 0 | L82: =IF(B82="Excluded",0,(IF(ISNA(VLOOKUP(A82,FY2010_11P,6,FALSE)),0,(VLOOKUP(A82,FY2010_11P,6,FALSE))))) -> 0 | M82: =IF(B82="Excluded",0,(IF(ISNA(VLOOKUP(A82,FY2011_12P,6,FALSE)),0,(VLOOKUP(A82,FY2011_12P,6,FALSE))))) -> 0 | N82: =IF(B82="Excluded",0,(IF(ISNA(VLOOKUP(A82,FY2012_13P,6,FALSE)),0,(VLOOKUP(A82,FY2012_13P,6,FALSE))))) -> 0 | O82: =(AVERAGE(G82:I82)*0.75)+(AVERAGE(L82:N82)*0.25) -> 0 | P82: =(AVERAGE(E82:G82)*0.75)+(AVERAGE(J82:L82)*0.25) -> 0 | Q82: 0 | R82: =S82-Q82 -> 0 | S82: =ROUND((P82*'Cost Pool'!$C$25),0) -> 0 | U82: =V82-T82 -> 0 | V82: =ROUND((O82*'Cost Pool'!$D$25),0) -> 0 | W82: =V82+R82 -> 0
A83: 700-MF | B83: =VLOOKUP(A83,Crosswalk,2,FALSE) -> 700 | C83: =CONCATENATE((LEFT(B83,3))," - ",(VLOOKUP((LEFT(B83,3)),Funds,2,FALSE))) -> 700 - Health Insurance Operating Fund | D83: =VLOOKUP((RIGHT(B83,2)),Bureaus,2,FALSE) -> #N/A | E83: =IF(B83="Excluded",0,(IF(ISNA(VLOOKUP(A83,FY2008_09,10,FALSE)),0,(VLOOKUP(A83,FY2008_09,10,FALSE))))) -> 0.0046306289 | F83: =IF(B83="Excluded",0,(IF(ISNA(VLOOKUP(A83,FY2009_10,10,FALSE)),0,(VLOOKUP(A83,FY2009_10,10,FALSE))))) -> 0.0042904689 | G83: =IF(B83="Excluded",0,(IF(ISNA(VLOOKUP(A83,FY2010_11,10,FALSE)),0,(VLOOKUP(A83,FY2010_11,10,FALSE))))) -> 0.0052232292 | H83: =IF(B83="Excluded",0,(IF(ISNA(VLOOKUP(A83,FY2011_12,10,FALSE)),0,(VLOOKUP(A83,FY2011_12,10,FALSE))))) -> 0.004954924 | I83: =IF(B83="Excluded",0,(IF(ISNA(VLOOKUP(A83,FY2012_13,10,FALSE)),0,(VLOOKUP(A83,FY2012_13,10,FALSE))))) -> 0.0049312629 | J83: =IF(B83="Excluded",0,(IF(ISNA(VLOOKUP(A83,FY2008_09P,6,FALSE)),0,(VLOOKUP(A83,FY2008_09P,6,FALSE))))) -> 0.0012746973 | K83: =IF(B83="Excluded",0,(IF(ISNA(VLOOKUP(A83,FY2009_10P,6,FALSE)),0,(VLOOKUP(A83,FY2009_10P,6,FALSE))))) -> 0.0013460597 | L83: =IF(B83="Excluded",0,(IF(ISNA(VLOOKUP(A83,FY2010_11P,6,FALSE)),0,(VLOOKUP(A83,FY2010_11P,6,FALSE))))) -> 0.0015076324 | M83: =IF(B83="Excluded",0,(IF(ISNA(VLOOKUP(A83,FY2011_12P,6,FALSE)),0,(VLOOKUP(A83,FY2011_12P,6,FALSE))))) -> 0.0013381181 | N83: =IF(B83="Excluded",0,(IF(ISNA(VLOOKUP(A83,FY2012_13P,6,FALSE)),0,(VLOOKUP(A83,FY2012_13P,6,FALSE))))) -> 0.0012552063 | O83: =(AVERAGE(G83:I83)*0.75)+(AVERAGE(L83:N83)*0.25) -> 0.0041191004 | P83: =(AVERAGE(E83:G83)*0.75)+(AVERAGE(J83:L83)*0.25) -> 0.0038801142 | Q83: 77033 | R83: =S83-Q83 -> 80298 | S83: =ROUND((P83*'Cost Pool'!$C$25),0) -> 157331 | T83: 88889 | U83: =V83-T83 -> 100096 | V83: =ROUND((O83*'Cost Pool'!$D$25),0) -> 188985 | W83: =V83+R83 -> 269283
A84: 701-MF | B84: =VLOOKUP(A84,Crosswalk,2,FALSE) -> 701 | C84: =CONCATENATE((LEFT(B84,3))," - ",(VLOOKUP((LEFT(B84,3)),Funds,2,FALSE))) -> 701 - Facilities Services Operating Fund | D84: =VLOOKUP((RIGHT(B84,2)),Bureaus,2,FALSE) -> #N/A | E84: =IF(B84="Excluded",0,(IF(ISNA(VLOOKUP(A84,FY2008_09,10,FALSE)),0,(VLOOKUP(A84,FY2008_09,10,FALSE))))) -> 0.021681392 | F84: =IF(B84="Excluded",0,(IF(ISNA(VLOOKUP(A84,FY2009_10,10,FALSE)),0,(VLOOKUP(A84,FY2009_10,10,FALSE))))) -> 0.021793354 | G84: =IF(B84="Excluded",0,(IF(ISNA(VLOOKUP(A84,FY2010_11,10,FALSE)),0,(VLOOKUP(A84,FY2010_11,10,FALSE))))) -> 0.018602503 | H84: =IF(B84="Excluded",0,(IF(ISNA(VLOOKUP(A84,FY2011_12,10,FALSE)),0,(VLOOKUP(A84,FY2011_12,10,FALSE))))) -> 0.024454637 | I84: =IF(B84="Excluded",0,(IF(ISNA(VLOOKUP(A84,FY2012_13,10,FALSE)),0,(VLOOKUP(A84,FY2012_13,10,FALSE))))) -> 0.021751616 | J84: =IF(B84="Excluded",0,(IF(ISNA(VLOOKUP(A84,FY2008_09P,6,FALSE)),0,(VLOOKUP(A84,FY2008_09P,6,FALSE))))) -> 0.0045889101 | K84: =IF(B84="Excluded",0,(IF(ISNA(VLOOKUP(A84,FY2009_10P,6,FALSE)),0,(VLOOKUP(A84,FY2009_10P,6,FALSE))))) -> 0.0045276554 | L84: =IF(B84="Excluded",0,(IF(ISNA(VLOOKUP(A84,FY2010_11P,6,FALSE)),0,(VLOOKUP(A84,FY2010_11P,6,FALSE))))) -> 0.0045228972 | M84: =IF(B84="Excluded",0,(IF(ISNA(VLOOKUP(A84,FY2011_12P,6,FALSE)),0,(VLOOKUP(A84,FY2011_12P,6,FALSE))))) -> 0.0045009428 | N84: =IF(B84="Excluded",0,(IF(ISNA(VLOOKUP(A84,FY2012_13P,6,FALSE)),0,(VLOOKUP(A84,FY2012_13P,6,FALSE))))) -> 0.0039938381 | O84: =(AVERAGE(G84:I84)*0.75)+(AVERAGE(L84:N84)*0.25) -> 0.017286995 | P84: =(AVERAGE(E84:G84)*0.75)+(AVERAGE(J84:L84)*0.25) -> 0.016655934 | Q84: 813820 | R84: =S84-Q84 -> -138454 | S84: =ROUND((P84*'Cost Pool'!$C$25),0) -> 675366 | T84: 870715 | U84: =V84-T84 -> -77586 | V84: =ROUND((O84*'Cost Pool'!$D$25),0) -> 793129 | W84: =V84+R84 -> 654675
A85: 702-MF | B85: =VLOOKUP(A85,Crosswalk,2,FALSE) -> 702 | C85: =CONCATENATE((LEFT(B85,3))," - ",(VLOOKUP((LEFT(B85,3)),Funds,2,FALSE))) -> 702 - CityFleet Operating Fund | D85: =VLOOKUP((RIGHT(B85,2)),Bureaus,2,FALSE) -> #N/A | E85: =IF(B85="Excluded",0,(IF(ISNA(VLOOKUP(A85,FY2008_09,10,FALSE)),0,(VLOOKUP(A85,FY2008_09,10,FALSE))))) -> 0.027904139 | F85: =IF(B85="Excluded",0,(IF(ISNA(VLOOKUP(A85,FY2009_10,10,FALSE)),0,(VLOOKUP(A85,FY2009_10,10,FALSE))))) -> 0.021785242 | G85: =IF(B85="Excluded",0,(IF(ISNA(VLOOKUP(A85,FY2010_11,10,FALSE)),0,(VLOOKUP(A85,FY2010_11,10,FALSE))))) -> 0.023580401 | H85: =IF(B85="Excluded",0,(IF(ISNA(VLOOKUP(A85,FY2011_12,10,FALSE)),0,(VLOOKUP(A85,FY2011_12,10,FALSE))))) -> 0.023384181 | I85: =IF(B85="Excluded",0,(IF(ISNA(VLOOKUP(A85,FY2012_13,10,FALSE)),0,(VLOOKUP(A85,FY2012_13,10,FALSE))))) -> 0.022542773 | J85: =IF(B85="Excluded",0,(IF(ISNA(VLOOKUP(A85,FY2008_09P,6,FALSE)),0,(VLOOKUP(A85,FY2008_09P,6,FALSE))))) -> 0.0098151689 | K85: =IF(B85="Excluded",0,(IF(ISNA(VLOOKUP(A85,FY2009_10P,6,FALSE)),0,(VLOOKUP(A85,FY2009_10P,6,FALSE))))) -> 0.0097895252 | L85: =IF(B85="Excluded",0,(IF(ISNA(VLOOKUP(A85,FY2010_11P,6,FALSE)),0,(VLOOKUP(A85,FY2010_11P,6,FALSE))))) -> 0.0097996105 | M85: =IF(B85="Excluded",0,(IF(ISNA(VLOOKUP(A85,FY2011_12P,6,FALSE)),0,(VLOOKUP(A85,FY2011_12P,6,FALSE))))) -> 0.0093668268 | N85: =IF(B85="Excluded",0,(IF(ISNA(VLOOKUP(A85,FY2012_13P,6,FALSE)),0,(VLOOKUP(A85,FY2012_13P,6,FALSE))))) -> 0.0087864438 | O85: =(AVERAGE(G85:I85)*0.75)+(AVERAGE(L85:N85)*0.25) -> 0.019706245 | P85: =(AVERAGE(E85:G85)*0.75)+(AVERAGE(J85:L85)*0.25) -> 0.020767804 | Q85: 781119 | R85: =S85-Q85 -> 60976 | S85: =ROUND((P85*'Cost Pool'!$C$25),0) -> 842095 | T85: 966077 | U85: =V85-T85 -> -61953 | V85: =ROUND((O85*'Cost Pool'!$D$25),0) -> 904124 | W85: =V85+R85 -> 965100
A86: 703-MF | B86: =VLOOKUP(A86,Crosswalk,2,FALSE) -> 703 | C86: =CONCATENATE((LEFT(B86,3))," - ",(VLOOKUP((LEFT(B86,3)),Funds,2,FALSE))) -> 703 - Printing & Distribution Services Operating Fund | D86: =VLOOKUP((RIGHT(B86,2)),Bureaus,2,FALSE) -> #N/A | E86: =IF(B86="Excluded",0,(IF(ISNA(VLOOKUP(A86,FY2008_09,10,FALSE)),0,(VLOOKUP(A86,FY2008_09,10,FALSE))))) -> 0.0069855536 | F86: =IF(B86="Excluded",0,(IF(ISNA(VLOOKUP(A86,FY2009_10,10,FALSE)),0,(VLOOKUP(A86,FY2009_10,10,FALSE))))) -> 0.0066605851 | G86: =IF(B86="Excluded",0,(IF(ISNA(VLOOKUP(A86,FY2010_11,10,FALSE)),0,(VLOOKUP(A86,FY2010_11,10,FALSE))))) -> 0.0061196638 | H86: =IF(B86="Excluded",0,(IF(ISNA(VLOOKUP(A86,FY2011_12,10,FALSE)),0,(VLOOKUP(A86,FY2011_12,10,FALSE))))) -> 0.006196453 | I86: =IF(B86="Excluded",0,(IF(ISNA(VLOOKUP(A86,FY2012_13,10,FALSE)),0,(VLOOKUP(A86,FY2012_13,10,FALSE))))) -> 0.0054654187 | J86: =IF(B86="Excluded",0,(IF(ISNA(VLOOKUP(A86,FY2008_09P,6,FALSE)),0,(VLOOKUP(A86,FY2008_09P,6,FALSE))))) -> 0.0036966221 | K86: =IF(B86="Excluded",0,(IF(ISNA(VLOOKUP(A86,FY2009_10P,6,FALSE)),0,(VLOOKUP(A86,FY2009_10P,6,FALSE))))) -> 0.003671072 | L86: =IF(B86="Excluded",0,(IF(ISNA(VLOOKUP(A86,FY2010_11P,6,FALSE)),0,(VLOOKUP(A86,FY2010_11P,6,FALSE))))) -> 0.0036434449 | M86: =IF(B86="Excluded",0,(IF(ISNA(VLOOKUP(A86,FY2011_12P,6,FALSE)),0,(VLOOKUP(A86,FY2011_12P,6,FALSE))))) -> 0.0031628246 | N86: =IF(B86="Excluded",0,(IF(ISNA(VLOOKUP(A86,FY2012_13P,6,FALSE)),0,(VLOOKUP(A86,FY2012_13P,6,FALSE))))) -> 0.0027386318 | O86: =(AVERAGE(G86:I86)*0.75)+(AVERAGE(L86:N86)*0.25) -> 0.0052407923 | P86: =(AVERAGE(E86:G86)*0.75)+(AVERAGE(J86:L86)*0.25) -> 0.0058590455 | Q86: 226844 | R86: =S86-Q86 -> 10729 | S86: =ROUND((P86*'Cost Pool'!$C$25),0) -> 237573 | T86: 255395 | U86: =V86-T86 -> -14947 | V86: =ROUND((O86*'Cost Pool'!$D$25),0) -> 240448 | W86: =V86+R86 -> 251177
A87: 704-MF | B87: =VLOOKUP(A87,Crosswalk,2,FALSE) -> 704 | C87: =CONCATENATE((LEFT(B87,3))," - ",(VLOOKUP((LEFT(B87,3)),Funds,2,FALSE))) -> 704 - Insurance and Claims Operating Fund | D87: =VLOOKUP((RIGHT(B87,2)),Bureaus,2,FALSE) -> #N/A | E87: =IF(B87="Excluded",0,(IF(ISNA(VLOOKUP(A87,FY2008_09,10,FALSE)),0,(VLOOKUP(A87,FY2008_09,10,FALSE))))) -> 0.0052626451 | F87: =IF(B87="Excluded",0,(IF(ISNA(VLOOKUP(A87,FY2009_10,10,FALSE)),0,(VLOOKUP(A87,FY2009_10,10,FALSE))))) -> 0.007281944 | G87: =IF(B87="Excluded",0,(IF(ISNA(VLOOKUP(A87,FY2010_11,10,FALSE)),0,(VLOOKUP(A87,FY2010_11,10,FALSE))))) -> 0.0058995125 | H87: =IF(B87="Excluded",0,(IF(ISNA(VLOOKUP(A87,FY2011_12,10,FALSE)),0,(VLOOKUP(A87,FY2011_12,10,FALSE))))) -> 0.0072372981 | I87: =IF(B87="Excluded",0,(IF(ISNA(VLOOKUP(A87,FY2012_13,10,FALSE)),0,(VLOOKUP(A87,FY2012_13,10,FALSE))))) -> 0.0050496475 | J87: =IF(B87="Excluded",0,(IF(ISNA(VLOOKUP(A87,FY2008_09P,6,FALSE)),0,(VLOOKUP(A87,FY2008_09P,6,FALSE))))) -> 0.0019120459 | K87: =IF(B87="Excluded",0,(IF(ISNA(VLOOKUP(A87,FY2009_10P,6,FALSE)),0,(VLOOKUP(A87,FY2009_10P,6,FALSE))))) -> 0.001835536 | L87: =IF(B87="Excluded",0,(IF(ISNA(VLOOKUP(A87,FY2010_11P,6,FALSE)),0,(VLOOKUP(A87,FY2010_11P,6,FALSE))))) -> 0.0017589045 | M87: =IF(B87="Excluded",0,(IF(ISNA(VLOOKUP(A87,FY2011_12P,6,FALSE)),0,(VLOOKUP(A87,FY2011_12P,6,FALSE))))) -> 0.0018247065 | N87: =IF(B87="Excluded",0,(IF(ISNA(VLOOKUP(A87,FY2012_13P,6,FALSE)),0,(VLOOKUP(A87,FY2012_13P,6,FALSE))))) -> 0.0015975352 | O87: =(AVERAGE(G87:I87)*0.75)+(AVERAGE(L87:N87)*0.25) -> 0.0049783767 | P87: =(AVERAGE(E87:G87)*0.75)+(AVERAGE(J87:L87)*0.25) -> 0.0050698993 | Q87: 251835 | R87: =S87-Q87 -> -46260 | S87: =ROUND((P87*'Cost Pool'!$C$25),0) -> 205575 | T87: 269709 | U87: =V87-T87 -> -41301 | V87: =ROUND((O87*'Cost Pool'!$D$25),0) -> 228408 | W87: =V87+R87 -> 182148
A88: 705-MF | B88: =VLOOKUP(A88,Crosswalk,2,FALSE) -> 705 | C88: =CONCATENATE((LEFT(B88,3))," - ",(VLOOKUP((LEFT(B88,3)),Funds,2,FALSE))) -> 705 - Workers' Comp. Self Insurance Operating Fund | D88: =VLOOKUP((RIGHT(B88,2)),Bureaus,2,FALSE) -> #N/A | E88: =IF(B88="Excluded",0,(IF(ISNA(VLOOKUP(A88,FY2008_09,10,FALSE)),0,(VLOOKUP(A88,FY2008_09,10,FALSE))))) -> 0.0037818949 | F88: =IF(B88="Excluded",0,(IF(ISNA(VLOOKUP(A88,FY2009_10,10,FALSE)),0,(VLOOKUP(A88,FY2009_10,10,FALSE))))) -> 0.0041454191 | G88: =IF(B88="Excluded",0,(IF(ISNA(VLOOKUP(A88,FY2010_11,10,FALSE)),0,(VLOOKUP(A88,FY2010_11,10,FALSE))))) -> 0.003995646 | H88: =IF(B88="Excluded",0,(IF(ISNA(VLOOKUP(A88,FY2011_12,10,FALSE)),0,(VLOOKUP(A88,FY2011_12,10,FALSE))))) -> 0.0039275736 | I88: =IF(B88="Excluded",0,(IF(ISNA(VLOOKUP(A88,FY2012_13,10,FALSE)),0,(VLOOKUP(A88,FY2012_13,10,FALSE))))) -> 0.0037107159 | J88: =IF(B88="Excluded",0,(IF(ISNA(VLOOKUP(A88,FY2008_09P,6,FALSE)),0,(VLOOKUP(A88,FY2008_09P,6,FALSE))))) -> 0.0010197578 | K88: =IF(B88="Excluded",0,(IF(ISNA(VLOOKUP(A88,FY2009_10P,6,FALSE)),0,(VLOOKUP(A88,FY2009_10P,6,FALSE))))) -> 0.00073421439 | L88: =IF(B88="Excluded",0,(IF(ISNA(VLOOKUP(A88,FY2010_11P,6,FALSE)),0,(VLOOKUP(A88,FY2010_11P,6,FALSE))))) -> 0.00087945223 | M88: =IF(B88="Excluded",0,(IF(ISNA(VLOOKUP(A88,FY2011_12P,6,FALSE)),0,(VLOOKUP(A88,FY2011_12P,6,FALSE))))) -> 0.00085152971 | N88: =IF(B88="Excluded",0,(IF(ISNA(VLOOKUP(A88,FY2012_13P,6,FALSE)),0,(VLOOKUP(A88,FY2012_13P,6,FALSE))))) -> 0.00079876762 | O88: =(AVERAGE(G88:I88)*0.75)+(AVERAGE(L88:N88)*0.25) -> 0.0031192963 | P88: =(AVERAGE(E88:G88)*0.75)+(AVERAGE(J88:L88)*0.25) -> 0.003200192 | Q88: 128504 | R88: =S88-Q88 -> 1258 | S88: =ROUND((P88*'Cost Pool'!$C$25),0) -> 129762 | T88: 146759 | U88: =V88-T88 -> -3645 | V88: =ROUND((O88*'Cost Pool'!$D$25),0) -> 143114 | W88: =V88+R88 -> 144372
A89: 706-MF | B89: =VLOOKUP(A89,Crosswalk,2,FALSE) -> 706 | C89: =CONCATENATE((LEFT(B89,3))," - ",(VLOOKUP((LEFT(B89,3)),Funds,2,FALSE))) -> 706 - Technology Services Fund | D89: =VLOOKUP((RIGHT(B89,2)),Bureaus,2,FALSE) -> #N/A | E89: =IF(B89="Excluded",0,(IF(ISNA(VLOOKUP(A89,FY2008_09,10,FALSE)),0,(VLOOKUP(A89,FY2008_09,10,FALSE))))) -> 0.056439074 | F89: =IF(B89="Excluded",0,(IF(ISNA(VLOOKUP(A89,FY2009_10,10,FALSE)),0,(VLOOKUP(A89,FY2009_10,10,FALSE))))) -> 0.041097707 | G89: =IF(B89="Excluded",0,(IF(ISNA(VLOOKUP(A89,FY2010_11,10,FALSE)),0,(VLOOKUP(A89,FY2010_11,10,FALSE))))) -> 0.037828661 | H89: =IF(B89="Excluded",0,(IF(ISNA(VLOOKUP(A89,FY2011_12,10,FALSE)),0,(VLOOKUP(A89,FY2011_12,10,FALSE))))) -> 0.043791206 | I89: =IF(B89="Excluded",0,(IF(ISNA(VLOOKUP(A89,FY2012_13,10,FALSE)),0,(VLOOKUP(A89,FY2012_13,10,FALSE))))) -> 0.042350597 | J89: =IF(B89="Excluded",0,(IF(ISNA(VLOOKUP(A89,FY2008_09P,6,FALSE)),0,(VLOOKUP(A89,FY2008_09P,6,FALSE))))) -> 0.030720204 | K89: =IF(B89="Excluded",0,(IF(ISNA(VLOOKUP(A89,FY2009_10P,6,FALSE)),0,(VLOOKUP(A89,FY2009_10P,6,FALSE))))) -> 0.029246207 | L89: =IF(B89="Excluded",0,(IF(ISNA(VLOOKUP(A89,FY2010_11P,6,FALSE)),0,(VLOOKUP(A89,FY2010_11P,6,FALSE))))) -> 0.02914756 | M89: =IF(B89="Excluded",0,(IF(ISNA(VLOOKUP(A89,FY2011_12P,6,FALSE)),0,(VLOOKUP(A89,FY2011_12P,6,FALSE))))) -> 0.027735539 | N89: =IF(B89="Excluded",0,(IF(ISNA(VLOOKUP(A89,FY2012_13P,6,FALSE)),0,(VLOOKUP(A89,FY2012_13P,6,FALSE))))) -> 0.024419467 | O89: =(AVERAGE(G89:I89)*0.75)+(AVERAGE(L89:N89)*0.25) -> 0.03776783 | P89: =(AVERAGE(E89:G89)*0.75)+(AVERAGE(J89:L89)*0.25) -> 0.041267525 | Q89: 1590788 | R89: =S89-Q89 -> 82531 | S89: =ROUND((P89*'Cost Pool'!$C$25),0) -> 1673319 | T89: 1788183 | U89: =V89-T89 -> -55392 | V89: =ROUND((O89*'Cost Pool'!$D$25),0) -> 1732791 | W89: =V89+R89 -> 1815322
A90: 708-MF | B90: =VLOOKUP(A90,Crosswalk,2,FALSE) -> 708 | C90: =CONCATENATE((LEFT(B90,3))," - ",(VLOOKUP((LEFT(B90,3)),Funds,2,FALSE))) -> 708 - EBS Services Fund | D90: =VLOOKUP((RIGHT(B90,2)),Bureaus,2,FALSE) -> #N/A | E90: =IF(B90="Excluded",0,(IF(ISNA(VLOOKUP(A90,FY2008_09,10,FALSE)),0,(VLOOKUP(A90,FY2008_09,10,FALSE))))) -> 0.00059264963 | F90: =IF(B90="Excluded",0,(IF(ISNA(VLOOKUP(A90,FY2009_10,10,FALSE)),0,(VLOOKUP(A90,FY2009_10,10,FALSE))))) -> 0.0060978047 | G90: =IF(B90="Excluded",0,(IF(ISNA(VLOOKUP(A90,FY2010_11,10,FALSE)),0,(VLOOKUP(A90,FY2010_11,10,FALSE))))) -> 0.0030234396 | H90: =IF(B90="Excluded",0,(IF(ISNA(VLOOKUP(A90,FY2011_12,10,FALSE)),0,(VLOOKUP(A90,FY2011_12,10,FALSE))))) -> 0.004183524 | I90: =IF(B90="Excluded",0,(IF(ISNA(VLOOKUP(A90,FY2012_13,10,FALSE)),0,(VLOOKUP(A90,FY2012_13,10,FALSE))))) -> 0.0042864572 | J90: =IF(B90="Excluded",0,(IF(ISNA(VLOOKUP(A90,FY2008_09P,6,FALSE)),0,(VLOOKUP(A90,FY2008_09P,6,FALSE))))) -> 0 | K90: =IF(B90="Excluded",0,(IF(ISNA(VLOOKUP(A90,FY2009_10P,6,FALSE)),0,(VLOOKUP(A90,FY2009_10P,6,FALSE))))) -> 0.0024473813 | L90: =IF(B90="Excluded",0,(IF(ISNA(VLOOKUP(A90,FY2010_11P,6,FALSE)),0,(VLOOKUP(A90,FY2010_11P,6,FALSE))))) -> 0.0028896287 | M90: =IF(B90="Excluded",0,(IF(ISNA(VLOOKUP(A90,FY2011_12P,6,FALSE)),0,(VLOOKUP(A90,FY2011_12P,6,FALSE))))) -> 0.002432942 | N90: =IF(B90="Excluded",0,(IF(ISNA(VLOOKUP(A90,FY2012_13P,6,FALSE)),0,(VLOOKUP(A90,FY2012_13P,6,FALSE))))) -> 0.0023963028 | O90: =(AVERAGE(G90:I90)*0.75)+(AVERAGE(L90:N90)*0.25) -> 0.0035165947 | P90: =(AVERAGE(E90:G90)*0.75)+(AVERAGE(J90:L90)*0.25) -> 0.0028732243 | Q90: 246475 | R90: =S90-Q90 -> -129971 | S90: =ROUND((P90*'Cost Pool'!$C$25),0) -> 116504 | T90: 210491 | U90: =V90-T90 -> -49149 | V90: =ROUND((O90*'Cost Pool'!$D$25),0) -> 161342 | W90: =V90+R90 -> 31371
A91: 800-DR | B91: =VLOOKUP(A91,Crosswalk,2,FALSE) -> 800 | C91: =CONCATENATE((LEFT(B91,3))," - ",(VLOOKUP((LEFT(B91,3)),Funds,2,FALSE))) -> 800 - Fire & Police Disability & Retirement Fund | D91: =VLOOKUP((RIGHT(B91,2)),Bureaus,2,FALSE) -> #N/A | E91: =IF(B91="Excluded",0,(IF(ISNA(VLOOKUP(A91,FY2008_09,10,FALSE)),0,(VLOOKUP(A91,FY2008_09,10,FALSE))))) -> 0.0027243442 | F91: =IF(B91="Excluded",0,(IF(ISNA(VLOOKUP(A91,FY2009_10,10,FALSE)),0,(VLOOKUP(A91,FY2009_10,10,FALSE))))) -> 0.0024421315 | G91: =IF(B91="Excluded",0,(IF(ISNA(VLOOKUP(A91,FY2010_11,10,FALSE)),0,(VLOOKUP(A91,FY2010_11,10,FALSE))))) -> 0.0026193048 | H91: =IF(B91="Excluded",0,(IF(ISNA(VLOOKUP(A91,FY2011_12,10,FALSE)),0,(VLOOKUP(A91,FY2011_12,10,FALSE))))) -> 0.0028210755 | I91: =IF(B91="Excluded",0,(IF(ISNA(VLOOKUP(A91,FY2012_13,10,FALSE)),0,(VLOOKUP(A91,FY2012_13,10,FALSE))))) -> 0.002598083 | J91: =IF(B91="Excluded",0,(IF(ISNA(VLOOKUP(A91,FY2008_09P,6,FALSE)),0,(VLOOKUP(A91,FY2008_09P,6,FALSE))))) -> 0.0021669853 | K91: =IF(B91="Excluded",0,(IF(ISNA(VLOOKUP(A91,FY2009_10P,6,FALSE)),0,(VLOOKUP(A91,FY2009_10P,6,FALSE))))) -> 0.0020802741 | L91: =IF(B91="Excluded",0,(IF(ISNA(VLOOKUP(A91,FY2010_11P,6,FALSE)),0,(VLOOKUP(A91,FY2010_11P,6,FALSE))))) -> 0.0022614486 | M91: =IF(B91="Excluded",0,(IF(ISNA(VLOOKUP(A91,FY2011_12P,6,FALSE)),0,(VLOOKUP(A91,FY2011_12P,6,FALSE))))) -> 0.0021896478 | N91: =IF(B91="Excluded",0,(IF(ISNA(VLOOKUP(A91,FY2012_13P,6,FALSE)),0,(VLOOKUP(A91,FY2012_13P,6,FALSE))))) -> 0.0021680835 | O91: =(AVERAGE(G91:I91)*0.75)+(AVERAGE(L91:N91)*0.25) -> 0.0025612142 | P91: =(AVERAGE(E91:G91)*0.75)+(AVERAGE(J91:L91)*0.25) -> 0.0024888375 | Q91: 85706 | R91: =S91-Q91 -> 15212 | S91: =ROUND((P91*'Cost Pool'!$C$25),0) -> 100918 | T91: 96883 | U91: =V91-T91 -> 20626 | V91: =ROUND((O91*'Cost Pool'!$D$25),0) -> 117509 | W91: =V91+R91 -> 132721
A92: 802-FM | B92: =VLOOKUP(A92,Crosswalk,2,FALSE) -> Excluded | C92: =CONCATENATE((LEFT(B92,3))," - ",(VLOOKUP((LEFT(B92,3)),Funds,2,FALSE))) -> #N/A | D92: =VLOOKUP((RIGHT(B92,2)),Bureaus,2,FALSE) -> #N/A | E92: =IF(B92="Excluded",0,(IF(ISNA(VLOOKUP(A92,FY2008_09,10,FALSE)),0,(VLOOKUP(A92,FY2008_09,10,FALSE))))) -> 0 | F92: =IF(B92="Excluded",0,(IF(ISNA(VLOOKUP(A92,FY2009_10,10,FALSE)),0,(VLOOKUP(A92,FY2009_10,10,FALSE))))) -> 0 | G92: =IF(B92="Excluded",0,(IF(ISNA(VLOOKUP(A92,FY2010_11,10,FALSE)),0,(VLOOKUP(A92,FY2010_11,10,FALSE))))) -> 0 | H92: =IF(B92="Excluded",0,(IF(ISNA(VLOOKUP(A92,FY2011_12,10,FALSE)),0,(VLOOKUP(A92,FY2011_12,10,FALSE))))) -> 0 | I92: =IF(B92="Excluded",0,(IF(ISNA(VLOOKUP(A92,FY2012_13,10,FALSE)),0,(VLOOKUP(A92,FY2012_13,10,FALSE))))) -> 0 | J92: =IF(B92="Excluded",0,(IF(ISNA(VLOOKUP(A92,FY2008_09P,6,FALSE)),0,(VLOOKUP(A92,FY2008_09P,6,FALSE))))) -> 0 | K92: =IF(B92="Excluded",0,(IF(ISNA(VLOOKUP(A92,FY2009_10P,6,FALSE)),0,(VLOOKUP(A92,FY2009_10P,6,FALSE))))) -> 0 | L92: =IF(B92="Excluded",0,(IF(ISNA(VLOOKUP(A92,FY2010_11P,6,FALSE)),0,(VLOOKUP(A92,FY2010_11P,6,FALSE))))) -> 0 | M92: =IF(B92="Excluded",0,(IF(ISNA(VLOOKUP(A92,FY2011_12P,6,FALSE)),0,(VLOOKUP(A92,FY2011_12P,6,FALSE))))) -> 0 | N92: =IF(B92="Excluded",0,(IF(ISNA(VLOOKUP(A92,FY2012_13P,6,FALSE)),0,(VLOOKUP(A92,FY2012_13P,6,FALSE))))) -> 0 | O92: =(AVERAGE(G92:I92)*0.75)+(AVERAGE(L92:N92)*0.25) -> 0 | P92: =(AVERAGE(E92:G92)*0.75)+(AVERAGE(J92:L92)*0.25) -> 0 | R92: =S92-Q92 -> 0 | S92: =ROUND((P92*'Cost Pool'!$C$25),0) -> 0 | T92: 0 | U92: =V92-T92 -> 0 | V92: =ROUND((O92*'Cost Pool'!$D$25),0) -> 0 | W92: =V92+R92 -> 0
E93: =SUM(E2:E92) -> 1 | F93: =SUM(F2:F92) -> 1 | G93: =SUM(G2:G92) -> 1 | H93: =SUM(H2:H92) -> 1 | I93: =SUM(I2:I92) -> 1 | J93: =SUM(J2:J92) -> 1 | K93: =SUM(K2:K92) -> 1 | L93: =SUM(L2:L92) -> 1 | ... P93: =SUM(P2:P92) -> 1

Sheet Lookup Values
A1: Array - Paying_Fund | E1: Array - Funds | H1: Array - Bureaus
A2: Cost Incurred By | B2: Cost Billed To | C2: Notes | E2: Fund | F2: Fund Name | H2: Bureau | I2: Bureau Name
A3: 100-AT | B3: 100-AT | C3: 100% Overhead | E3: 100 | F3: General Fund | H3: AT | I3: Office of the City Attorney
A4: 100-AU | B4: 100-AU | C4: 100% Overhead | E4: 200 | F4: Transportation Operating Fund | H4: AU | I4: Office of the City Auditor
A5: 100-BO | B5: 100-BO | C5: 100% Overhead | E5: 201 | F5: Assessment Collection Fund | H5: BO | I5: City Budget Office
A6: 100-CB | B6: 100-MF | E6: 202 | F6: Emergency Communication Fund | H6: CB | I6: Office for Community Technology
A7: 100-EM | B7: 100-EM | C7: 100% Overhead | E7: 203 | F7: Development Services Fund | H7: DR | I7: Bureau of Fire & Police Disability & Retirement
A8: 100-FM | B8: Excluded | E8: 204 | F8: Property Management License Fund | H8: DS | I8: Bureau of Development Services
A9: 100-FR | B9: 100-FR | C9: Exclude expenditures for emergency mgmt (FREO000004 Fund Center) | E9: 205 | F9: Closed - Public Safety Fund | H9: EC | I9: Bureau of Emergency Communications
A10: 100-GR | B10: 100-GR | C10: 100% Overhead | E10: 206 | F10: MHCRC Agency Fund | H10: EM | I10: Portland Bureau of Emergency Management
A11: 100-HC | B11: 100-HC | E11: 207 | F11: Closed - Private for Hire Trans. Safety Fund | H11: ES | I11: Bureau of Environmental Services
A12: 100-HN | B12: Excluded | E12: 208 | F12: Closed - Business License Surcharge Fund | H12: FM | I12: Fund & Debt Management
A13: 100-MF | B13: 100-MF | C13: Exclude MFHR, MFDR, MFIB | E13: 209 | F13: Convention and Tourism Fund | H13: FR | I13: Portland Fire & Rescue
A14: 100-MY | B14: 100-MY | C14: Exclude expenditures for Admin & Support (LAMYAS Functional Area) | E14: 210 | F14: General Reserve Fund | H14: GR | I14: Office of Government Relations
A15: 100-NI | B15: 100-NI | C15: Exclude expenditures for Information & Referral and Public Involvement best practices (CDIR, CDNRNOPI) | E15: 211 | F15: Special Finance and Resource Fund | H15: HC | I15: Portland Housing Bureau
A16: 100-OE | B16: 100-OE | C16: Rollback in 09-10 & 10-11. Exclude expenditures for Citywide Comm, Training, Tech Support and % admin (CDCEEC, TE, TS & portion CDAS (68%)) | E16: 212 | F16: Transportation Reserve Fund | H16: HN | I16: Office of Human Relations
A17: 100-PA | B17: 100-PA | C17: Exclude Commissioner's Office (PACO000001) | E17: 213 | F17: Housing Investment Fund | H17: MF | I17: Office of Management & Finance
A18: 100-PK | B18: 100-PK | E18: 214 | F18: Closed - Campaign Finance Fund | H18: MY | I18: Office of the Mayor
A19: 100-PL | B19: 100-PL | E19: 215 | F19: Parks Local Option Levy Fund | H19: NI | I19: Office of Neighborhood Involvement
A20: 100-PN | B20: 100-PN | C20: Exclude expenditures for Comp Planning & 1/2 of district liaisons (CDAPDI, CDCP00) | E20: 216 | F20: Children's Investment Fund | H20: OE | I20: Office of Equity & Human Rights
A21: 100-PS | B21: 100-PS | C21: 100% Overhead | E21: 217 | F21: Grants Fund | H21: PA | I21: Commissioner of Public Affairs
A22: 100-PU | B22: 100-PU | C22: 100% Overhead | E22: 218 | F22: Community Development Block Grant Fund | H22: PK | I22: Portland Parks & Recreation
A23: 100-PW | B23: 100-PW | C23: 100% Overhead | E23: 219 | F23: HOME Grant Fund | H23: PL | I23: Portland Police Bureau
A24: 100-SA | B24: 100-SA | C24: Exclude expenditures for City memberships and dues (MFSA000002) | E24: 220 | F24: Portland Parks Memorial Fund | H24: PN | I24: Bureau of Planning & Sustainability
A25: 100-SD | B25: 100-PN | E25: 221 | F25: Tax Increment Financing Reimbursement Fund | H25: PS | I25: Commissioner of Public Safety
A26: 100-ZD | B26: PDC | E26: 222 | F26: Police Special Revenue Fund | H26: PU | I26: Commissioner of Public Utilities
A27: 200-TR | B27: 200 | E27: 223 | F27: Arts Education & Access Fund | H27: PW | I27: Commissioner of Public Works
A28: 201-AU | B28: 201 | E28: 301 | F28: River District URA Debt Redemption Fund | H28: SA | I28: Special Appropriations
A29: 202-EC | B29: 202 | E29: 302 | F29: Bonded Debt Interest and Sinking Fund | H29: SD | I29: Office of Sustainable Development
A30: 202-MF | B30: 202 | E30: 303 | F30: Waterfront Renewal Bond Sinking Fund | H30: TR | I30: Portland Bureau of Transportation
A31: 203-DS | B31: 203 | E31: 304 | F31: Interstate Corridor Debt Service Fund | H31: WA | I31: Portland Water Bureau
A32: 204-MF | B32: 204 | C32: Fixed at $25,000 (hardcoded in Model) | E32: 305 | F32: Pension Debt Redemption Fund | H32: ZD | I32: Portland Development Commission
A33: 206-CB | B33: 206-MF | C33: Fixed at $25,000 (hardcoded in Model) | E33: 306 | F33: South Park Blocks Redemption Fund
A34: 206-MF | B34: 206-MF | E34: 307 | F34: Airport Way Debt Service Fund
A35: 207-MF | B35: Excluded | E35: 308 | F35: Gas Tax Bond Redemption Fund
A36: 209-MF | B36: 209 | C36: Fixed at $25,000 (hardcoded in Model) | E36: 309 | F36: Lents Town Center URA Debt Redemption Fund
A37: 211-FM | B37: Excluded | E37: 310 | F37: Central Eastside Ind. District Debt Service Fund
A38: 213-HC | B38: 213 | C38: 50% discount for operating projects | E38: 311 | F38: Bancroft Bond Interest and Sinking Fund
A39: 214-AU | B39: Excluded | E39: 312 | F39: Convention Center Area Debt Service Fund
A40: 215-PK | B40: 215 | E40: 313 | F40: North Macadam URA Debt Redemption Fund
A41: 216-PA | B41: 216 | C41: Fixed at $25,000 (hardcoded in Model) | E41: 314 | F41: Special Projects Debt Service Fund
A42: 217-DS | B42: 203 | E42: 315 | F42: Gateway URA Debt Redemption Fund
A43: 217-EC | B43: 202 | E43: 316 | F43: Willamette Industrial URA Debt Service Fund
A44: 217-EM | B44: 100-EM | E44: 317 | F44: Governmental Bond Redemption Fund
A45: 217-ES | B45: 600 | E45: 318 | F45: Education URA Debt Service Fund
A46: 217-FR | B46: 100-FR | E46: 319 | F46: 42nd Avenue NPI Debt Service Fund
A47: 217-HC | B47: 100-HC | E47: 320 | F47: Cully Blvd. NPI Debt Service Fund
A48: 217-MF | B48: 100-MF | E48: 321 | F48: Parkrose NPI Debt Service Fund
A49: 217-MY | B49: 100-MY | E49: 322 | F49: Rosewood NPI Debt Service Fund
A50: 217-NI | B50: 100-NI | E50: 323 | F50: Division-Midway NPI Debt Service Fund
A51: 217-PA | B51: 100-PA | E51: 324 | F51: 82nd Ave/Division NPI Debt Service Fund
A52: 217-PK | B52: 100-PK | E52: 400 | F52: BFRES Facilities GO Bond Construction Fund
A53: 217-PL | B53: 100-PL | E53: 401 | F53: Local Improvement District Fund
A54: 217-PN | B54: 100-PN | E54: 402 | F54: Parks Capital Improvement Program Fund
A55: 217-PU | B55: 100-PU | E55: 403 | F55: Public Safety GO Bond Fund
A56: 217-SD | B56: 100-PN | E56: 500 | F56: Parks Endowment Fund
A57: 217-TR | B57: 200 | E57: 600 | F57: Sewer System Operating Fund
A58: 217-WA | B58: 602 | E58: 601 | F58: Hydroelectric Power Operating Fund
A59: 217-ZD | B59: PDC | E59: 602 | F59: Water Fund
A60: 218-HC | B60: 100-HC | E60: 603 | F60: Golf Fund
A61: 219-HC | B61: 100-HC | E61: 604 | F61: Portland International Raceway Fund
A62: 220-PK | B62: Excluded | E62: 605 | F62: Solid Waste Management Fund
A63: 221-HC | B63: 221 | C63: 50% discount for operating projects | E63: 606 | F63: Parking Facilities Fund
A64: 222-PL | B64: 222 | E64: 607 | F64: Spectator Facilities Operating Fund
A65: 223-MF | B65: 223 | C65: Fixed at $25,000 (hardcoded in Model) | E65: 608 | F65: Environmental Remediation Fund
A66: 301-FM | B66: Excluded | E66: 609 | F66: Sewer System Debt Redemption Fund
A67: 303-FM | B67: Excluded | E67: 610 | F67: Golf Revenue Bond Redemption Fund
A68: 306-FM | B68: Excluded | E68: 611 | F68: Hydroelectric Power Bond Redemption Fund
A69: 317-FM | B69: Excluded | E69: 612 | F69: Water Bond Sinking Fund
A70: 400-MF | B70: 400 | E70: 613 | F70: Closed - Parking Facilities Debt Redemption Fund
A71: 401-AU | B71: 401 | E71: 614 | F71: Sewer System Construction Fund
A72: 402-PK | B72: 402 | E72: 615 | F72: Water Construction Fund
A73: 403-FR | B73: 403 | E73: 616 | F73: Closed - Water Growth Impact Charge Trust Fund
A74: 403-MF | B74: 403 | E74: 617 | F74: Sewer System Rate Stabilization Fund
A75: 500-PK | B75: Excluded | E75: 618 | F75: Hydroelectric Power Renewal Replacement Fund
A76: 600-ES | B76: 600 | E76: 619 | F76: Sewer System Safety Net Fund
A77: 601-WA | B77: 601 | E77: 620 | F77: Sewer Revolving Loan Fund
A78: 602-WA | B78: 602 | E78: 621 | F78: Headwaters Apartment Complex Fund
A79: 603-PK | B79: 603 | E79: 700 | F79: Health Insurance Operating Fund
A80: 604-PK | B80: 604 | E80: 701 | F80: Facilities Services Operating Fund
A81: 605-PN | B81: 605 | E81: 702 | F81: CityFleet Operating Fund
A82: 606-TR | B82: 606 | E82: 703 | F82: Printing & Distribution Services Operating Fund
A83: 607-MF | B83: 607 | E83: 704 | F83: Insurance and Claims Operating Fund
A84: 608-ES | B84: 608 | E84: 705 | F84: Workers' Comp. Self Insurance Operating Fund
A85: 614-ES | B85: 600 | E85: 706 | F85: Technology Services Fund
A86: 621-HC | B86: Excluded | E86: 707 | F86: Closed - Portland Police Assoc Health Insurnc Fd
A87: 700-MF | B87: 700 | C87: Excludes insurance claim payouts (529721) | E87: 708 | F87: EBS Services Fund
A88: 701-MF | B88: 701 | E88: 800 | F88: Fire & Police Disability & Retirement Fund
A89: 702-MF | B89: 702 | E89: 801 | F89: Fire & Police Disability & Retirement Res Fund
A90: 703-MF | B90: 703 | E90: 802 | F90: Fire & Police Supplemental Retirement Res Fund
A91: 704-MF | B91: 704 | E91: PDC | F91: Portland Development Commission
A92: 705-MF | B92: 705
A93: 706-MF | B93: 706
A94: 707-MF | B94: Excluded
A95: 708-MF | B95: 708
A96: 800-DR | B96: 800 | C96: Excludes retirement payouts, PERS contributions, and disability/death benefits (547000, 547100)
A97: 802-FM | B97: Excluded

Sheet $ FY 2008-09
A1: Fund/Bureau | B1: Operating | C1: Capital | D1: Total | E1: 50% Capital Discount | F1: Passthrough Discount | G1: Other Discounts | H1: Overhead Bureau Discount | I1: Revised Total | J1: Allocation Percent | K1: In Model?
A2: 100-AT | B2: 7278731 | C2: 0 | D2: =SUM(B2:C2) -> 7278731 | E2: =C2*-0.5 -> 0 | H2: =-D2-E2-F2-G2 -> -7278731 | I2: =IF((VLOOKUP(A2,Crosswalk,2,FALSE)="Excluded"),0,(D2+E2+F2+G2+H2)) -> 0 | J2: =I2/(SUM($I$2:$I$78)) -> 0 | K2: =IF(VLOOKUP(A2,Model,2,FALSE)<>"","Yes","No") -> Yes | L2: =IF((VLOOKUP(A2,Crosswalk,3,FALSE))=0," ",(VLOOKUP(A2,Crosswalk,3,FALSE))) -> 100% Overhead
A3: 100-AU | B3: 5743961 | C3: 0 | D3: =SUM(B3:C3) -> 5743961 | E3: =C3*-0.5 -> 0 | H3: =-D3-E3-F3-G3 -> -5743961 | I3: =IF((VLOOKUP(A3,Crosswalk,2,FALSE)="Excluded"),0,(D3+E3+F3+G3+H3)) -> 0 | J3: =I3/(SUM($I$2:$I$78)) -> 0 | K3: =IF(VLOOKUP(A3,Model,2,FALSE)<>"","Yes","No") -> Yes | L3: =IF((VLOOKUP(A3,Crosswalk,3,FALSE))=0," ",(VLOOKUP(A3,Crosswalk,3,FALSE))) -> 100% Overhead
A4: 100-CB | B4: 1884157 | C4: 0 | D4: =SUM(B4:C4) -> 1884157 | E4: =C4*-0.5 -> 0 | I4: =IF((VLOOKUP(A4,Crosswalk,2,FALSE)="Excluded"),0,(D4+E4+F4+G4+H4)) -> 1884157 | J4: =I4/(SUM($I$2:$I$78)) -> 0.0022176202 | K4: =IF(VLOOKUP(A4,Model,2,FALSE)<>"","Yes","No") -> Yes | L4: =IF((VLOOKUP(A4,Crosswalk,3,FALSE))=0," ",(VLOOKUP(A4,Crosswalk,3,FALSE)))
A5: 100-EM | B5: 1200075 | C5: 0 | D5: =SUM(B5:C5) -> 1200075 | E5: =C5*-0.5 -> 0 | H5: =-D5-E5-F5-G5 -> -1200075 | I5: =IF((VLOOKUP(A5,Crosswalk,2,FALSE)="Excluded"),0,(D5+E5+F5+G5+H5)) -> 0 | J5: =I5/(SUM($I$2:$I$78)) -> 0 | K5: =IF(VLOOKUP(A5,Model,2,FALSE)<>"","Yes","No") -> Yes | L5: =IF((VLOOKUP(A5,Crosswalk,3,FALSE))=0," ",(VLOOKUP(A5,Crosswalk,3,FALSE))) -> 100% Overhead
A6: 100-FR | B6: 81034766 | C6: 15000 | D6: =SUM(B6:C6) -> 81049766 | E6: =C6*-0.5 -> -7500 | H6: -295492 | I6: =IF((VLOOKUP(A6,Crosswalk,2,FALSE)="Excluded"),0,(D6+E6+F6+G6+H6)) -> 80746774 | J6: =I6/(SUM($I$2:$I$78)) -> 0.095037556 | K6: =IF(VLOOKUP(A6,Model,2,FALSE)<>"","Yes","No") -> Yes | L6: =IF((VLOOKUP(A6,Crosswalk,3,FALSE))=0," ",(VLOOKUP(A6,Crosswalk,3,FALSE))) -> Exclude expenditures for emergency mgmt (FREO000004 Fund Center)
A7: 100-GR | B7: 1055827 | C7: 0 | D7: =SUM(B7:C7) -> 1055827 | E7: =C7*-0.5 -> 0 | H7: =-D7-E7-F7-G7 -> -1055827 | I7: =IF((VLOOKUP(A7,Crosswalk,2,FALSE)="Excluded"),0,(D7+E7+F7+G7+H7)) -> 0 | J7: =I7/(SUM($I$2:$I$78)) -> 0 | K7: =IF(VLOOKUP(A7,Model,2,FALSE)<>"","Yes","No") -> Yes | L7: =IF((VLOOKUP(A7,Crosswalk,3,FALSE))=0," ",(VLOOKUP(A7,Crosswalk,3,FALSE))) -> 100% Overhead
A8: 100-HC | B8: 14089454 | C8: 0 | D8: =SUM(B8:C8) -> 14089454 | E8: =C8*-0.5 -> 0 | I8: =IF((VLOOKUP(A8,Crosswalk,2,FALSE)="Excluded"),0,(D8+E8+F8+G8+H8)) -> 14089454 | J8: =I8/(SUM($I$2:$I$78)) -> 0.016583044 | K8: =IF(VLOOKUP(A8,Model,2,FALSE)<>"","Yes","No") -> Yes | L8: =IF((VLOOKUP(A8,Crosswalk,3,FALSE))=0," ",(VLOOKUP(A8,Crosswalk,3,FALSE)))
A9: 100-HN | B9: 373696 | C9: 0 | D9: =SUM(B9:C9) -> 373696 | E9: =C9*-0.5 -> 0 | I9: =IF((VLOOKUP(A9,Crosswalk,2,FALSE)="Excluded"),0,(D9+E9+F9+G9+H9)) -> 0 | J9: =I9/(SUM($I$2:$I$78)) -> 0 | K9: =IF(VLOOKUP(A9,Model,2,FALSE)<>"","Yes","No") -> Yes | L9: =IF((VLOOKUP(A9,Crosswalk,3,FALSE))=0," ",(VLOOKUP(A9,Crosswalk,3,FALSE)))
A10: 100-MF | B10: 33122805 | C10: 233920 | D10: =SUM(B10:C10) -> 33356725 | E10: =C10*-0.5 -> -116960 | H10: =-(9476177+4013463+7382254) -> -20871894 | I10: =IF((VLOOKUP(A10,Crosswalk,2,FALSE)="Excluded"),0,(D10+E10+F10+G10+H10)) -> 12367871 | J10: =I10/(SUM($I$2:$I$78)) -> 0.01455677 | K10: =IF(VLOOKUP(A10,Model,2,FALSE)<>"","Yes","No") -> Yes | L10: =IF((VLOOKUP(A10,Crosswalk,3,FALSE))=0," ",(VLOOKUP(A10,Crosswalk,3,FALSE))) -> Exclude MFHR, MFDR, MFIB
A11: 100-MY | B11: 1954746 | C11: 0 | D11: =SUM(B11:C11) -> 1954746 | E11: =C11*-0.5 -> 0 | H11: -1898765 | I11: =IF((VLOOKUP(A11,Crosswalk,2,FALSE)="Excluded"),0,(D11+E11+F11+G11+H11)) -> 55981 | J11: =I11/(SUM($I$2:$I$78)) -> 6.5888669e-05 | K11: =IF(VLOOKUP(A11,Model,2,FALSE)<>"","Yes","No") -> Yes | L11: =IF((VLOOKUP(A11,Crosswalk,3,FALSE))=0," ",(VLOOKUP(A11,Crosswalk,3,FALSE))) -> Exclude expenditures for Admin & Support (LAMYAS Functional Area)
A12: 100-NI | B12: 5482681 | C12: 0 | D12: =SUM(B12:C12) -> 5482681 | E12: =C12*-0.5 -> 0 | H12: -362898 | I12: =IF((VLOOKUP(A12,Crosswalk,2,FALSE)="Excluded"),0,(D12+E12+F12+G12+H12)) -> 5119783 | J12: =I12/(SUM($I$2:$I$78)) -> 0.006025896 | K12: =IF(VLOOKUP(A12,Model,2,FALSE)<>"","Yes","No") -> Yes | L12: =IF((VLOOKUP(A12,Crosswalk,3,FALSE))=0," ",(VLOOKUP(A12,Crosswalk,3,FALSE))) -> Exclude expenditures for Information & Referral and Public Involvement best practices (CDIR, CDNRNOPI)
A13: 100-PA | B13: 808689 | C13: 0 | D13: =SUM(B13:C13) -> 808689 | E13: =C13*-0.5 -> 0 | H13: -689230 | I13: =IF((VLOOKUP(A13,Crosswalk,2,FALSE)="Excluded"),0,(D13+E13+F13+G13+H13)) -> 119459 | J13: =I13/(SUM($I$2:$I$78)) -> 0.00014060118 | K13: =IF(VLOOKUP(A13,Model,2,FALSE)<>"","Yes","No") -> Yes | L13: =IF((VLOOKUP(A13,Crosswalk,3,FALSE))=0," ",(VLOOKUP(A13,Crosswalk,3,FALSE))) -> Exclude Commissioner's Office (PACO000001)
A14: 100-PK | B14: 47835512 | C14: 230952 | D14: =SUM(B14:C14) -> 48066464 | E14: =C14*-0.5 -> -115476 | I14: =IF((VLOOKUP(A14,Crosswalk,2,FALSE)="Excluded"),0,(D14+E14+F14+G14+H14)) -> 47950988 | J14: =I14/(SUM($I$2:$I$78)) -> 0.056437483 | K14: =IF(VLOOKUP(A14,Model,2,FALSE)<>"","Yes","No") -> Yes | L14: =IF((VLOOKUP(A14,Crosswalk,3,FALSE))=0," ",(VLOOKUP(A14,Crosswalk,3,FALSE)))
A15: 100-PL | B15: 124089859 | C15: 0 | D15: =SUM(B15:C15) -> 124089859 | E15: =C15*-0.5 -> 0 | I15: =IF((VLOOKUP(A15,Crosswalk,2,FALSE)="Excluded"),0,(D15+E15+F15+G15+H15)) -> 124089859 | J15: =I15/(SUM($I$2:$I$78)) -> 0.14605162 | K15: =IF(VLOOKUP(A15,Model,2,FALSE)<>"","Yes","No") -> Yes | L15: =IF((VLOOKUP(A15,Crosswalk,3,FALSE))=0," ",(VLOOKUP(A15,Crosswalk,3,FALSE)))
A16: 100-PN | B16: 8853802 | C16: 0 | D16: =SUM(B16:C16) -> 8853802 | E16: =C16*-0.5 -> 0 | H16: =1628621*-0.75 -> -1221465.8 | I16: =IF((VLOOKUP(A16,Crosswalk,2,FALSE)="Excluded"),0,(D16+E16+F16+G16+H16)) -> 7632336.2 | J16: =I16/(SUM($I$2:$I$78)) -> 0.0089831277 | K16: =IF(VLOOKUP(A16,Model,2,FALSE)<>"","Yes","No") -> Yes | L16: =IF((VLOOKUP(A16,Crosswalk,3,FALSE))=0," ",(VLOOKUP(A16,Crosswalk,3,FALSE))) -> Exclude expenditures for Comp Planning & 1/2 of district liaisons (CDAPDI, CDCP00)
A17: 100-PS | B17: 566746 | C17: 0 | D17: =SUM(B17:C17) -> 566746 | E17: =C17*-0.5 -> 0 | H17: =-D17-E17-F17-G17 -> -566746 | I17: =IF((VLOOKUP(A17,Crosswalk,2,FALSE)="Excluded"),0,(D17+E17+F17+G17+H17)) -> 0 | J17: =I17/(SUM($I$2:$I$78)) -> 0 | K17: =IF(VLOOKUP(A17,Model,2,FALSE)<>"","Yes","No") -> Yes | L17: =IF((VLOOKUP(A17,Crosswalk,3,FALSE))=0," ",(VLOOKUP(A17,Crosswalk,3,FALSE))) -> 100% Overhead
A18: 100-PU | B18: 648573 | C18: 14750 | D18: =SUM(B18:C18) -> 663323 | E18: =C18*-0.5 -> -7375 | H18: =-D18-E18-F18-G18 -> -655948 | I18: =IF((VLOOKUP(A18,Crosswalk,2,FALSE)="Excluded"),0,(D18+E18+F18+G18+H18)) -> 0 | J18: =I18/(SUM($I$2:$I$78)) -> 0 | K18: =IF(VLOOKUP(A18,Model,2,FALSE)<>"","Yes","No") -> Yes | L18: =IF((VLOOKUP(A18,Crosswalk,3,FALSE))=0," ",(VLOOKUP(A18,Crosswalk,3,FALSE))) -> 100% Overhead
A19: 100-PW | B19: 631654 | C19: 0 | D19: =SUM(B19:C19) -> 631654 | E19: =C19*-0.5 -> 0 | H19: =-D19-E19-F19-G19 -> -631654 | I19: =IF((VLOOKUP(A19,Crosswalk,2,FALSE)="Excluded"),0,(D19+E19+F19+G19+H19)) -> 0 | J19: =I19/(SUM($I$2:$I$78)) -> 0 | K19: =IF(VLOOKUP(A19,Model,2,FALSE)<>"","Yes","No") -> Yes | L19: =IF((VLOOKUP(A19,Crosswalk,3,FALSE))=0," ",(VLOOKUP(A19,Crosswalk,3,FALSE))) -> 100% Overhead
A20: 100-SA | B20: 11877579 | C20: 0 | D20: =SUM(B20:C20) -> 11877579 | E20: =C20*-0.5 -> 0 | H20: -295215 | I20: =IF((VLOOKUP(A20,Crosswalk,2,FALSE)="Excluded"),0,(D20+E20+F20+G20+H20)) -> 11582364 | J20: =I20/(SUM($I$2:$I$78)) -> 0.013632242 | K20: =IF(VLOOKUP(A20,Model,2,FALSE)<>"","Yes","No") -> Yes | L20: =IF((VLOOKUP(A20,Crosswalk,3,FALSE))=0," ",(VLOOKUP(A20,Crosswalk,3,FALSE))) -> Exclude expenditures for City memberships and dues (MFSA000002)
A21: 100-SD | B21: 2559777 | C21: 0 | D21: =SUM(B21:C21) -> 2559777 | E21: =C21*-0.5 -> 0 | I21: =IF((VLOOKUP(A21,Crosswalk,2,FALSE)="Excluded"),0,(D21+E21+F21+G21+H21)) -> 2559777 | J21: =I21/(SUM($I$2:$I$78)) -> 0.0030128132 | K21: =IF(VLOOKUP(A21,Model,2,FALSE)<>"","Yes","No") -> Yes | L21: =IF((VLOOKUP(A21,Crosswalk,3,FALSE))=0," ",(VLOOKUP(A21,Crosswalk,3,FALSE)))
A22: 200-TR | B22: 81652734 | C22: 16758952 | D22: =SUM(B22:C22) -> 98411686 | E22: =C22*-0.5 -> -8379476 | I22: =IF((VLOOKUP(A22,Crosswalk,2,FALSE)="Excluded"),0,(D22+E22+F22+G22+H22)) -> 90032210 | J22: =I22/(SUM($I$2:$I$78)) -> 0.10596635 | K22: =IF(VLOOKUP(A22,Model,2,FALSE)<>"","Yes","No") -> Yes | L22: =IF((VLOOKUP(A22,Crosswalk,3,FALSE))=0," ",(VLOOKUP(A22,Crosswalk,3,FALSE)))
A23: 202-EC | B23: 12826057 | C23: 0 | D23: =SUM(B23:C23) -> 12826057 | E23: =C23*-0.5 -> 0 | I23: =IF((VLOOKUP(A23,Crosswalk,2,FALSE)="Excluded"),0,(D23+E23+F23+G23+H23)) -> 12826057 | J23: =I23/(SUM($I$2:$I$78)) -> 0.015096047 | K23: =IF(VLOOKUP(A23,Model,2,FALSE)<>"","Yes","No") -> Yes | L23: =IF((VLOOKUP(A23,Crosswalk,3,FALSE))=0," ",(VLOOKUP(A23,Crosswalk,3,FALSE)))
A24: 202-MF | B24: 0 | C24: 229413 | D24: =SUM(B24:C24) -> 229413 | E24: =C24*-0.5 -> -114706.5 | I24: =IF((VLOOKUP(A24,Crosswalk,2,FALSE)="Excluded"),0,(D24+E24+F24+G24+H24)) -> 114706.5 | J24: =I24/(SUM($I$2:$I$78)) -> 0.00013500757 | K24: =IF(VLOOKUP(A24,Model,2,FALSE)<>"","Yes","No") -> Yes | L24: =IF((VLOOKUP(A24,Crosswalk,3,FALSE))=0," ",(VLOOKUP(A24,Crosswalk,3,FALSE)))
A25: 203-DS | B25: 31264883 | C25: 0 | D25: =SUM(B25:C25) -> 31264883 | E25: =C25*-0.5 -> 0 | I25: =IF((VLOOKUP(A25,Crosswalk,2,FALSE)="Excluded"),0,(D25+E25+F25+G25+H25)) -> 31264883 | J25: =I25/(SUM($I$2:$I$78)) -> 0.036798226 | K25: =IF(VLOOKUP(A25,Model,2,FALSE)<>"","Yes","No") -> Yes | L25: =IF((VLOOKUP(A25,Crosswalk,3,FALSE))=0," ",(VLOOKUP(A25,Crosswalk,3,FALSE)))
A26: 204-MF | B26: 4405507 | C26: 0 | D26: =SUM(B26:C26) -> 4405507 | E26: =C26*-0.5 -> 0 | G26: -4405507 | I26: =IF((VLOOKUP(A26,Crosswalk,2,FALSE)="Excluded"),0,(D26+E26+F26+G26+H26)) -> 0 | J26: =I26/(SUM($I$2:$I$78)) -> 0 | K26: =IF(VLOOKUP(A26,Model,2,FALSE)<>"","Yes","No") -> Yes | L26: =IF((VLOOKUP(A26,Crosswalk,3,FALSE))=0," ",(VLOOKUP(A26,Crosswalk,3,FALSE))) -> Fixed at $25,000 (hardcoded in Model)
A27: 206-CB | B27: 3931842 | C27: 0 | D27: =SUM(B27:C27) -> 3931842 | E27: =C27*-0.5 -> 0 | G27: -3931842 | I27: =IF((VLOOKUP(A27,Crosswalk,2,FALSE)="Excluded"),0,(D27+E27+F27+G27+H27)) -> 0 | J27: =I27/(SUM($I$2:$I$78)) -> 0 | K27: =IF(VLOOKUP(A27,Model,2,FALSE)<>"","Yes","No") -> Yes | L27: =IF((VLOOKUP(A27,Crosswalk,3,FALSE))=0," ",(VLOOKUP(A27,Crosswalk,3,FALSE))) -> Fixed at $25,000 (hardcoded in Model)
A28: 207-MF | B28: 27110 | C28: 0 | D28: =SUM(B28:C28) -> 27110 | E28: =C28*-0.5 -> 0 | I28: =IF((VLOOKUP(A28,Crosswalk,2,FALSE)="Excluded"),0,(D28+E28+F28+G28+H28)) -> 0 | J28: =I28/(SUM($I$2:$I$78)) -> 0 | K28: =IF(VLOOKUP(A28,Model,2,FALSE)<>"","Yes","No") -> #N/A | L28: =IF((VLOOKUP(A28,Crosswalk,3,FALSE))=0," ",(VLOOKUP(A28,Crosswalk,3,FALSE)))
A29: 209-MF | B29: 3111156 | C29: 0 | D29: =SUM(B29:C29) -> 3111156 | E29: =C29*-0.5 -> 0 | G29: -3111156 | I29: =IF((VLOOKUP(A29,Crosswalk,2,FALSE)="Excluded"),0,(D29+E29+F29+G29+H29)) -> 0 | J29: =I29/(SUM($I$2:$I$78)) -> 0 | K29: =IF(VLOOKUP(A29,Model,2,FALSE)<>"","Yes","No") -> Yes | L29: =IF((VLOOKUP(A29,Crosswalk,3,FALSE))=0," ",(VLOOKUP(A29,Crosswalk,3,FALSE))) -> Fixed at $25,000 (hardcoded in Model)
A30: 211-FM | B30: 104679571 | C30: 0 | D30: =SUM(B30:C30) -> 104679571 | E30: =C30*-0.5 -> 0 | I30: =IF((VLOOKUP(A30,Crosswalk,2,FALSE)="Excluded"),0,(D30+E30+F30+G30+H30)) -> 0 | J30: =I30/(SUM($I$2:$I$78)) -> 0 | K30: =IF(VLOOKUP(A30,Model,2,FALSE)<>"","Yes","No") -> Yes | L30: =IF((VLOOKUP(A30,Crosswalk,3,FALSE))=0," ",(VLOOKUP(A30,Crosswalk,3,FALSE)))
A31: 213-HC | B31: 11544049 | C31: 0 | D31: =SUM(B31:C31) -> 11544049 | E31: =C31*-0.5 -> 0 | I31: =IF((VLOOKUP(A31,Crosswalk,2,FALSE)="Excluded"),0,(D31+E31+F31+G31+H31)) -> 11544049 | J31: =I31/(SUM($I$2:$I$78)) -> 0.013587146 | K31: =IF(VLOOKUP(A31,Model,2,FALSE)<>"","Yes","No") -> Yes | L31: =IF((VLOOKUP(A31,Crosswalk,3,FALSE))=0," ",(VLOOKUP(A31,Crosswalk,3,FALSE))) -> 50% discount for operating projects
A32: 214-AU | B32: 306661 | C32: 0 | D32: =SUM(B32:C32) -> 306661 | E32: =C32*-0.5 -> 0 | I32: =IF((VLOOKUP(A32,Crosswalk,2,FALSE)="Excluded"),0,(D32+E32+F32+G32+H32)) -> 0 | J32: =I32/(SUM($I$2:$I$78)) -> 0 | K32: =IF(VLOOKUP(A32,Model,2,FALSE)<>"","Yes","No") -> Yes | L32: =IF((VLOOKUP(A32,Crosswalk,3,FALSE))=0," ",(VLOOKUP(A32,Crosswalk,3,FALSE)))
A33: 215-PK | B33: 2854853 | C33: 0 | D33: =SUM(B33:C33) -> 2854853 | E33: =C33*-0.5 -> 0 | I33: =IF((VLOOKUP(A33,Crosswalk,2,FALSE)="Excluded"),0,(D33+E33+F33+G33+H33)) -> 2854853 | J33: =I33/(SUM($I$2:$I$78)) -> 0.0033601126 | K33: =IF(VLOOKUP(A33,Model,2,FALSE)<>"","Yes","No") -> Yes | L33: =IF((VLOOKUP(A33,Crosswalk,3,FALSE))=0," ",(VLOOKUP(A33,Crosswalk,3,FALSE)))
A34: 216-PA | B34: 9963872 | C34: 0 | D34: =SUM(B34:C34) -> 9963872 | E34: =C34*-0.5 -> 0 | G34: -9963872 | I34: =IF((VLOOKUP(A34,Crosswalk,2,FALSE)="Excluded"),0,(D34+E34+F34+G34+H34)) -> 0 | J34: =I34/(SUM($I$2:$I$78)) -> 0 | K34: =IF(VLOOKUP(A34,Model,2,FALSE)<>"","Yes","No") -> Yes | L34: =IF((VLOOKUP(A34,Crosswalk,3,FALSE))=0," ",(VLOOKUP(A34,Crosswalk,3,FALSE))) -> Fixed at $25,000 (hardcoded in Model)
A35: 217-EC | B35: 1431 | C35: 0 | D35: =SUM(B35:C35) -> 1431 | E35: =C35*-0.5 -> 0 | I35: =IF((VLOOKUP(A35,Crosswalk,2,FALSE)="Excluded"),0,(D35+E35+F35+G35+H35)) -> 1431 | J35: =I35/(SUM($I$2:$I$78)) -> 1.6842622e-06 | K35: =IF(VLOOKUP(A35,Model,2,FALSE)<>"","Yes","No") -> Yes | L35: =IF((VLOOKUP(A35,Crosswalk,3,FALSE))=0," ",(VLOOKUP(A35,Crosswalk,3,FALSE)))
A36: 217-EM | B36: 6141347 | C36: 0 | D36: =SUM(B36:C36) -> 6141347 | E36: =C36*-0.5 -> 0 | I36: =IF((VLOOKUP(A36,Crosswalk,2,FALSE)="Excluded"),0,(D36+E36+F36+G36+H36)) -> 6141347 | J36: =I36/(SUM($I$2:$I$78)) -> 0.0072282592 | K36: =IF(VLOOKUP(A36,Model,2,FALSE)<>"","Yes","No") -> Yes | L36: =IF((VLOOKUP(A36,Crosswalk,3,FALSE))=0," ",(VLOOKUP(A36,Crosswalk,3,FALSE)))
A37: 217-ES | B37: 526973 | C37: 793810 | D37: =SUM(B37:C37) -> 1320783 | E37: =C37*-0.5 -> -396905 | I37: =IF((VLOOKUP(A37,Crosswalk,2,FALSE)="Excluded"),0,(D37+E37+F37+G37+H37)) -> 923878 | J37: =I37/(SUM($I$2:$I$78)) -> 0.0010873884 | K37: =IF(VLOOKUP(A37,Model,2,FALSE)<>"","Yes","No") -> Yes | L37: =IF((VLOOKUP(A37,Crosswalk,3,FALSE))=0," ",(VLOOKUP(A37,Crosswalk,3,FALSE)))
A38: 217-FR | B38: 353248 | C38: 0 | D38: =SUM(B38:C38) -> 353248 | E38: =C38*-0.5 -> 0 | I38: =IF((VLOOKUP(A38,Crosswalk,2,FALSE)="Excluded"),0,(D38+E38+F38+G38+H38)) -> 353248 | J38: =I38/(SUM($I$2:$I$78)) -> 0.00041576678 | K38: =IF(VLOOKUP(A38,Model,2,FALSE)<>"","Yes","No") -> Yes | L38: =IF((VLOOKUP(A38,Crosswalk,3,FALSE))=0," ",(VLOOKUP(A38,Crosswalk,3,FALSE)))
A39: 217-HC | B39: 3337612 | C39: 0 | D39: =SUM(B39:C39) -> 3337612 | E39: =C39*-0.5 -> 0 | I39: =IF((VLOOKUP(A39,Crosswalk,2,FALSE)="Excluded"),0,(D39+E39+F39+G39+H39)) -> 3337612 | J39: =I39/(SUM($I$2:$I$78)) -> 0.0039283116 | K39: =IF(VLOOKUP(A39,Model,2,FALSE)<>"","Yes","No") -> Yes | L39: =IF((VLOOKUP(A39,Crosswalk,3,FALSE))=0," ",(VLOOKUP(A39,Crosswalk,3,FALSE)))
A40: 217-MF | B40: 117668 | C40: 24572 | D40: =SUM(B40:C40) -> 142240 | E40: =C40*-0.5 -> -12286 | I40: =IF((VLOOKUP(A40,Crosswalk,2,FALSE)="Excluded"),0,(D40+E40+F40+G40+H40)) -> 129954 | J40: =I40/(SUM($I$2:$I$78)) -> 0.00015295361 | K40: =IF(VLOOKUP(A40,Model,2,FALSE)<>"","Yes","No") -> Yes | L40: =IF((VLOOKUP(A40,Crosswalk,3,FALSE))=0," ",(VLOOKUP(A40,Crosswalk,3,FALSE)))
A41: 217-PK | B41: 302517 | C41: 97591 | D41: =SUM(B41:C41) -> 400108 | E41: =C41*-0.5 -> -48795.5 | I41: =IF((VLOOKUP(A41,Crosswalk,2,FALSE)="Excluded"),0,(D41+E41+F41+G41+H41)) -> 351312.5 | J41: =I41/(SUM($I$2:$I$78)) -> 0.00041348873 | K41: =IF(VLOOKUP(A41,Model,2,FALSE)<>"","Yes","No") -> Yes | L41: =IF((VLOOKUP(A41,Crosswalk,3,FALSE))=0," ",(VLOOKUP(A41,Crosswalk,3,FALSE)))
A42: 217-PL | B42: 1615208 | C42: 0 | D42: =SUM(B42:C42) -> 1615208 | E42: =C42*-0.5 -> 0 | I42: =IF((VLOOKUP(A42,Crosswalk,2,FALSE)="Excluded"),0,(D42+E42+F42+G42+H42)) -> 1615208 | J42: =I42/(SUM($I$2:$I$78)) -> 0.0019010719 | K42: =IF(VLOOKUP(A42,Model,2,FALSE)<>"","Yes","No") -> Yes | L42: =IF((VLOOKUP(A42,Crosswalk,3,FALSE))=0," ",(VLOOKUP(A42,Crosswalk,3,FALSE)))
A43: 217-PN | B43: 89786 | C43: 0 | D43: =SUM(B43:C43) -> 89786 | E43: =C43*-0.5 -> 0 | I43: =IF((VLOOKUP(A43,Crosswalk,2,FALSE)="Excluded"),0,(D43+E43+F43+G43+H43)) -> 89786 | J43: =I43/(SUM($I$2:$I$78)) -> 0.00010567657 | K43: =IF(VLOOKUP(A43,Model,2,FALSE)<>"","Yes","No") -> Yes | L43: =IF((VLOOKUP(A43,Crosswalk,3,FALSE))=0," ",(VLOOKUP(A43,Crosswalk,3,FALSE)))
A44: 217-SD | B44: 1389776 | C44: 0 | D44: =SUM(B44:C44) -> 1389776 | E44: =C44*-0.5 -> 0 | I44: =IF((VLOOKUP(A44,Crosswalk,2,FALSE)="Excluded"),0,(D44+E44+F44+G44+H44)) -> 1389776 | J44: =I44/(SUM($I$2:$I$78)) -> 0.0016357423 | K44: =IF(VLOOKUP(A44,Model,2,FALSE)<>"","Yes","No") -> Yes | L44: =IF((VLOOKUP(A44,Crosswalk,3,FALSE))=0," ",(VLOOKUP(A44,Crosswalk,3,FALSE)))
A45: 217-TR | B45: 470314 | C45: 12424399 | D45: =SUM(B45:C45) -> 12894713 | E45: =C45*-0.5 -> -6212199.5 | I45: =IF((VLOOKUP(A45,Crosswalk,2,FALSE)="Excluded"),0,(D45+E45+F45+G45+H45)) -> 6682513.5 | J45: =I45/(SUM($I$2:$I$78)) -> 0.0078652028 | K45: =IF(VLOOKUP(A45,Model,2,FALSE)<>"","Yes","No") -> Yes | L45: =IF((VLOOKUP(A45,Crosswalk,3,FALSE))=0," ",(VLOOKUP(A45,Crosswalk,3,FALSE)))
A46: 217-WA | B46: 241016 | C46: 246412 | D46: =SUM(B46:C46) -> 487428 | E46: =C46*-0.5 -> -123206 | I46: =IF((VLOOKUP(A46,Crosswalk,2,FALSE)="Excluded"),0,(D46+E46+F46+G46+H46)) -> 364222 | J46: =I46/(SUM($I$2:$I$78)) -> 0.00042868299 | K46: =IF(VLOOKUP(A46,Model,2,FALSE)<>"","Yes","No") -> Yes | L46: =IF((VLOOKUP(A46,Crosswalk,3,FALSE))=0," ",(VLOOKUP(A46,Crosswalk,3,FALSE)))
... A67: 621-HC | B67: 0 | C67: 0 | D67: =SUM(B67:C67) -> 0 | E67: =C67*-0.5 -> 0 | I67: =IF((VLOOKUP(A67,Crosswalk,2,FALSE)="Excluded"),0,(D67+E67+F67+G67+H67)) -> 0 | J67: =I67/(SUM($I$2:$I$78)) -> 0 | K67: =IF(VLOOKUP(A67,Model,2,FALSE)<>"","Yes","No") -> Yes | L67: =IF((VLOOKUP(A67,Crosswalk,3,FALSE))=0," ",(VLOOKUP(A67,Crosswalk,3,FALSE)))
A68: 700-MF | B68: 35716847 | C68: 0 | D68: =SUM(B68:C68) -> 35716847 | E68: =C68*-0.5 -> 0 | F68: -31782525 | I68: =IF((VLOOKUP(A68,Crosswalk,2,FALSE)="Excluded"),0,(D68+E68+F68+G68+H68)) -> 3934322 | J68: =I68/(SUM($I$2:$I$78)) -> 0.0046306289 | K68: =IF(VLOOKUP(A68,Model,2,FALSE)<>"","Yes","No") -> Yes | L68: =IF((VLOOKUP(A68,Crosswalk,3,FALSE))=0," ",(VLOOKUP(A68,Crosswalk,3,FALSE))) -> Excludes insurance claim payouts (529721)
A69: 701-MF | B69: 16403604 | C69: 4035121 | D69: =SUM(B69:C69) -> 20438725 | E69: =C69*-0.5 -> -2017560.5 | I69: =IF((VLOOKUP(A69,Crosswalk,2,FALSE)="Excluded"),0,(D69+E69+F69+G69+H69)) -> 18421164 | J69: =I69/(SUM($I$2:$I$78)) -> 0.021681392 | K69: =IF(VLOOKUP(A69,Model,2,FALSE)<>"","Yes","No") -> Yes | L69: =IF((VLOOKUP(A69,Crosswalk,3,FALSE))=0," ",(VLOOKUP(A69,Crosswalk,3,FALSE)))
A70: 702-MF | B70: 21995234 | C70: 3425928 | D70: =SUM(B70:C70) -> 25421162 | E70: =C70*-0.5 -> -1712964 | I70: =IF((VLOOKUP(A70,Crosswalk,2,FALSE)="Excluded"),0,(D70+E70+F70+G70+H70)) -> 23708198 | J70: =I70/(SUM($I$2:$I$78)) -> 0.027904139 | K70: =IF(VLOOKUP(A70,Model,2,FALSE)<>"","Yes","No") -> Yes | L70: =IF((VLOOKUP(A70,Crosswalk,3,FALSE))=0," ",(VLOOKUP(A70,Crosswalk,3,FALSE)))
A71: 703-MF | B71: 5935137 | C71: 0 | D71: =SUM(B71:C71) -> 5935137 | E71: =C71*-0.5 -> 0 | I71: =IF((VLOOKUP(A71,Crosswalk,2,FALSE)="Excluded"),0,(D71+E71+F71+G71+H71)) -> 5935137 | J71: =I71/(SUM($I$2:$I$78)) -> 0.0069855536 | K71: =IF(VLOOKUP(A71,Model,2,FALSE)<>"","Yes","No") -> Yes | L71: =IF((VLOOKUP(A71,Crosswalk,3,FALSE))=0," ",(VLOOKUP(A71,Crosswalk,3,FALSE)))
A72: 704-MF | B72: 4471302 | C72: 0 | D72: =SUM(B72:C72) -> 4471302 | E72: =C72*-0.5 -> 0 | I72: =IF((VLOOKUP(A72,Crosswalk,2,FALSE)="Excluded"),0,(D72+E72+F72+G72+H72)) -> 4471302 | J72: =I72/(SUM($I$2:$I$78)) -> 0.0052626451 | K72: =IF(VLOOKUP(A72,Model,2,FALSE)<>"","Yes","No") -> Yes | L72: =IF((VLOOKUP(A72,Crosswalk,3,FALSE))=0," ",(VLOOKUP(A72,Crosswalk,3,FALSE)))
A73: 705-MF | B73: 3213212 | C73: 0 | D73: =SUM(B73:C73) -> 3213212 | E73: =C73*-0.5 -> 0 | I73: =IF((VLOOKUP(A73,Crosswalk,2,FALSE)="Excluded"),0,(D73+E73+F73+G73+H73)) -> 3213212 | J73: =I73/(SUM($I$2:$I$78)) -> 0.0037818949 | K73: =IF(VLOOKUP(A73,Model,2,FALSE)<>"","Yes","No") -> Yes | L73: =IF((VLOOKUP(A73,Crosswalk,3,FALSE))=0," ",(VLOOKUP(A73,Crosswalk,3,FALSE)))
A74: 706-MF | B74: 39643710 | C74: 16617259 | D74: =SUM(B74:C74) -> 56260969 | E74: =C74*-0.5 -> -8308629.5 | I74: =IF((VLOOKUP(A74,Crosswalk,2,FALSE)="Excluded"),0,(D74+E74+F74+G74+H74)) -> 47952340 | J74: =I74/(SUM($I$2:$I$78)) -> 0.056439074 | K74: =IF(VLOOKUP(A74,Model,2,FALSE)<>"","Yes","No") -> Yes | L74: =IF((VLOOKUP(A74,Crosswalk,3,FALSE))=0," ",(VLOOKUP(A74,Crosswalk,3,FALSE)))
A75: 707-MF | B75: 87361 | C75: 0 | D75: =SUM(B75:C75) -> 87361 | E75: =C75*-0.5 -> 0 | I75: =IF((VLOOKUP(A75,Crosswalk,2,FALSE)="Excluded"),0,(D75+E75+F75+G75+H75)) -> 0 | J75: =I75/(SUM($I$2:$I$78)) -> 0 | K75: =IF(VLOOKUP(A75,Model,2,FALSE)<>"","Yes","No") -> #N/A | L75: =IF((VLOOKUP(A75,Crosswalk,3,FALSE))=0," ",(VLOOKUP(A75,Crosswalk,3,FALSE)))
A76: 708-MF | B76: 503533 | C76: 0 | D76: =SUM(B76:C76) -> 503533 | E76: =C76*-0.5 -> 0 | I76: =IF((VLOOKUP(A76,Crosswalk,2,FALSE)="Excluded"),0,(D76+E76+F76+G76+H76)) -> 503533 | J76: =I76/(SUM($I$2:$I$78)) -> 0.00059264963 | K76: =IF(VLOOKUP(A76,Model,2,FALSE)<>"","Yes","No") -> Yes | L76: =IF((VLOOKUP(A76,Crosswalk,3,FALSE))=0," ",(VLOOKUP(A76,Crosswalk,3,FALSE)))
A77: 800-DR | B77: 95952497 | C77: 0 | D77: =SUM(B77:C77) -> 95952497 | E77: =C77*-0.5 -> 0 | F77: =-(85079520+8558292) -> -93637812 | I77: =IF((VLOOKUP(A77,Crosswalk,2,FALSE)="Excluded"),0,(D77+E77+F77+G77+H77)) -> 2314685 | J77: =I77/(SUM($I$2:$I$78)) -> 0.0027243442 | K77: =IF(VLOOKUP(A77,Model,2,FALSE)<>"","Yes","No") -> Yes | L77: =IF((VLOOKUP(A77,Crosswalk,3,FALSE))=0," ",(VLOOKUP(A77,Crosswalk,3,FALSE))) -> Excludes retirement payouts, PERS contributions, and disability/death benefits (547000, 547100)
A78: 802-FM | B78: 7940 | C78: 0 | D78: =SUM(B78:C78) -> 7940 | E78: =C78*-0.5 -> 0 | I78: =IF((VLOOKUP(A78,Crosswalk,2,FALSE)="Excluded"),0,(D78+E78+F78+G78+H78)) -> 0 | J78: =I78/(SUM($I$2:$I$78)) -> 0 | K78: =IF(VLOOKUP(A78,Model,2,FALSE)<>"","Yes","No") -> Yes | L78: =IF((VLOOKUP(A78,Crosswalk,3,FALSE))=0," ",(VLOOKUP(A78,Crosswalk,3,FALSE)))
J79: =SUM(J2:J78) -> 1

Sheet Pos FY 2008-09
A1: Fund/Bureau | B1: Position Count from SAP | C1: Vacant Casuals | D1: Other Adjustments | E1: Revised Position Count | F1: Allocation Percent | G1: In Model? | H1: Notes
A2: 100-AT | B2: 63 | C2: -1 | D2: -62 | E2: =IF((VLOOKUP(A2,Crosswalk,2,FALSE)="Excluded"),0,(SUM(B2+C2+D2))) -> 0 | F2: =E2/SUM($E$2:$E$40) -> 0 | G2: =IF(VLOOKUP(A2,Model,2,FALSE)<>"","Yes","No") -> Yes | H2: =IF((VLOOKUP(A2,Crosswalk,3,FALSE))=0," ",(VLOOKUP(A2,Crosswalk,3,FALSE))) -> 100% Overhead
A3: 100-AU | B3: 63 | C3: -4 | D3: -59 | E3: =IF((VLOOKUP(A3,Crosswalk,2,FALSE)="Excluded"),0,(SUM(B3+C3+D3))) -> 0 | F3: =E3/SUM($E$2:$E$40) -> 0 | G3: =IF(VLOOKUP(A3,Model,2,FALSE)<>"","Yes","No") -> Yes | H3: =IF((VLOOKUP(A3,Crosswalk,3,FALSE))=0," ",(VLOOKUP(A3,Crosswalk,3,FALSE))) -> 100% Overhead
A4: 100-CB | B4: 9 | E4: =IF((VLOOKUP(A4,Crosswalk,2,FALSE)="Excluded"),0,(SUM(B4+C4+D4))) -> 9 | F4: =E4/SUM($E$2:$E$40) -> 0.0011472275 | G4: =IF(VLOOKUP(A4,Model,2,FALSE)<>"","Yes","No") -> Yes | H4: =IF((VLOOKUP(A4,Crosswalk,3,FALSE))=0," ",(VLOOKUP(A4,Crosswalk,3,FALSE)))
A5: 100-EM | B5: 17 | D5: -17 | E5: =IF((VLOOKUP(A5,Crosswalk,2,FALSE)="Excluded"),0,(SUM(B5+C5+D5))) -> 0 | F5: =E5/SUM($E$2:$E$40) -> 0 | G5: =IF(VLOOKUP(A5,Model,2,FALSE)<>"","Yes","No") -> Yes | H5: =IF((VLOOKUP(A5,Crosswalk,3,FALSE))=0," ",(VLOOKUP(A5,Crosswalk,3,FALSE))) -> 100% Overhead
A6: 100-FR | B6: 782 | C6: -10 | D6: -1 | E6: =IF((VLOOKUP(A6,Crosswalk,2,FALSE)="Excluded"),0,(SUM(B6+C6+D6))) -> 771 | F6: =E6/SUM($E$2:$E$40) -> 0.098279159 | G6: =IF(VLOOKUP(A6,Model,2,FALSE)<>"","Yes","No") -> Yes | H6: =IF((VLOOKUP(A6,Crosswalk,3,FALSE))=0," ",(VLOOKUP(A6,Crosswalk,3,FALSE))) -> Exclude expenditures for emergency mgmt (FREO000004 Fund Center)
A7: 100-GR | B7: 9 | D7: -9 | E7: =IF((VLOOKUP(A7,Crosswalk,2,FALSE)="Excluded"),0,(SUM(B7+C7+D7))) -> 0 | F7: =E7/SUM($E$2:$E$40) -> 0 | G7: =IF(VLOOKUP(A7,Model,2,FALSE)<>"","Yes","No") -> Yes | H7: =IF((VLOOKUP(A7,Crosswalk,3,FALSE))=0," ",(VLOOKUP(A7,Crosswalk,3,FALSE))) -> 100% Overhead
A8: 100-HC | B8: 42 | C8: -1 | E8: =IF((VLOOKUP(A8,Crosswalk,2,FALSE)="Excluded"),0,(SUM(B8+C8+D8))) -> 41 | F8: =E8/SUM($E$2:$E$40) -> 0.0052262588 | G8: =IF(VLOOKUP(A8,Model,2,FALSE)<>"","Yes","No") -> Yes | H8: =IF((VLOOKUP(A8,Crosswalk,3,FALSE))=0," ",(VLOOKUP(A8,Crosswalk,3,FALSE)))
A9: 100-HN | B9: 4 | E9: =IF((VLOOKUP(A9,Crosswalk,2,FALSE)="Excluded"),0,(SUM(B9+C9+D9))) -> 0 | F9: =E9/SUM($E$2:$E$40) -> 0 | G9: =IF(VLOOKUP(A9,Model,2,FALSE)<>"","Yes","No") -> Yes | H9: =IF((VLOOKUP(A9,Crosswalk,3,FALSE))=0," ",(VLOOKUP(A9,Crosswalk,3,FALSE)))
A10: 100-MF | B10: 605 | C10: -9 | D10: =-535+6 -> -529 | E10: =IF((VLOOKUP(A10,Crosswalk,2,FALSE)="Excluded"),0,(SUM(B10+C10+D10))) -> 67 | F10: =E10/SUM($E$2:$E$40) -> 0.0085404716 | G10: =IF(VLOOKUP(A10,Model,2,FALSE)<>"","Yes","No") -> Yes | H10: =IF((VLOOKUP(A10,Crosswalk,3,FALSE))=0," ",(VLOOKUP(A10,Crosswalk,3,FALSE))) -> Exclude MFHR, MFDR, MFIB
A11: 100-MY | B11: 31 | C11: -1 | D11: =-29+1 -> -28 | E11: =IF((VLOOKUP(A11,Crosswalk,2,FALSE)="Excluded"),0,(SUM(B11+C11+D11))) -> 2 | F11: =E11/SUM($E$2:$E$40) -> 0.00025493945 | G11: =IF(VLOOKUP(A11,Model,2,FALSE)<>"","Yes","No") -> Yes | H11: =IF((VLOOKUP(A11,Crosswalk,3,FALSE))=0," ",(VLOOKUP(A11,Crosswalk,3,FALSE))) -> Exclude expenditures for Admin & Support (LAMYAS Functional Area)
A12: 100-NI | B12: 58 | C12: -5 | D12: -6 | E12: =IF((VLOOKUP(A12,Crosswalk,2,FALSE)="Excluded"),0,(SUM(B12+C12+D12))) -> 47 | F12: =E12/SUM($E$2:$E$40) -> 0.0059910771 | G12: =IF(VLOOKUP(A12,Model,2,FALSE)<>"","Yes","No") -> Yes | H12: =IF((VLOOKUP(A12,Crosswalk,3,FALSE))=0," ",(VLOOKUP(A12,Crosswalk,3,FALSE))) -> Exclude expenditures for Information & Referral and Public Involvement best practices (CDIR, CDNRNOPI)
A13: 100-PA | B13: 14 | C13: -1 | D13: -11 | E13: =IF((VLOOKUP(A13,Crosswalk,2,FALSE)="Excluded"),0,(SUM(B13+C13+D13))) -> 2 | F13: =E13/SUM($E$2:$E$40) -> 0.00025493945 | G13: =IF(VLOOKUP(A13,Model,2,FALSE)<>"","Yes","No") -> Yes | H13: =IF((VLOOKUP(A13,Crosswalk,3,FALSE))=0," ",(VLOOKUP(A13,Crosswalk,3,FALSE))) -> Exclude Commissioner's Office (PACO000001)
A14: 100-PK | B14: 3364 | C14: -1033 | E14: =IF((VLOOKUP(A14,Crosswalk,2,FALSE)="Excluded"),0,(SUM(B14+C14+D14))) -> 2331 | F14: =E14/SUM($E$2:$E$40) -> 0.29713193 | G14: =IF(VLOOKUP(A14,Model,2,FALSE)<>"","Yes","No") -> Yes | H14: =IF((VLOOKUP(A14,Crosswalk,3,FALSE))=0," ",(VLOOKUP(A14,Crosswalk,3,FALSE)))
A15: 100-PL | B15: 1351 | C15: -2 | E15: =IF((VLOOKUP(A15,Crosswalk,2,FALSE)="Excluded"),0,(SUM(B15+C15+D15))) -> 1349 | F15: =E15/SUM($E$2:$E$40) -> 0.17195666 | G15: =IF(VLOOKUP(A15,Model,2,FALSE)<>"","Yes","No") -> Yes | H15: =IF((VLOOKUP(A15,Crosswalk,3,FALSE))=0," ",(VLOOKUP(A15,Crosswalk,3,FALSE)))
A16: 100-PN | B16: 101 | C16: -5 | D16: =(10*-0.5)-9 -> -14 | E16: =IF((VLOOKUP(A16,Crosswalk,2,FALSE)="Excluded"),0,(SUM(B16+C16+D16))) -> 82 | F16: =E16/SUM($E$2:$E$40) -> 0.010452518 | G16: =IF(VLOOKUP(A16,Model,2,FALSE)<>"","Yes","No") -> Yes | H16: =IF((VLOOKUP(A16,Crosswalk,3,FALSE))=0," ",(VLOOKUP(A16,Crosswalk,3,FALSE))) -> Exclude expenditures for Comp Planning & 1/2 of district liaisons (CDAPDI, CDCP00)
A17: 100-PS | B17: 8 | C17: -1 | D17: -7 | E17: =IF((VLOOKUP(A17,Crosswalk,2,FALSE)="Excluded"),0,(SUM(B17+C17+D17))) -> 0 | F17: =E17/SUM($E$2:$E$40) -> 0 | G17: =IF(VLOOKUP(A17,Model,2,FALSE)<>"","Yes","No") -> Yes | H17: =IF((VLOOKUP(A17,Crosswalk,3,FALSE))=0," ",(VLOOKUP(A17,Crosswalk,3,FALSE))) -> 100% Overhead
A18: 100-PU | B18: 10 | D18: -10 | E18: =IF((VLOOKUP(A18,Crosswalk,2,FALSE)="Excluded"),0,(SUM(B18+C18+D18))) -> 0 | F18: =E18/SUM($E$2:$E$40) -> 0 | G18: =IF(VLOOKUP(A18,Model,2,FALSE)<>"","Yes","No") -> Yes | H18: =IF((VLOOKUP(A18,Crosswalk,3,FALSE))=0," ",(VLOOKUP(A18,Crosswalk,3,FALSE))) -> 100% Overhead
A19: 100-PW | B19: 7 | D19: -7 | E19: =IF((VLOOKUP(A19,Crosswalk,2,FALSE)="Excluded"),0,(SUM(B19+C19+D19))) -> 0 | F19: =E19/SUM($E$2:$E$40) -> 0 | G19: =IF(VLOOKUP(A19,Model,2,FALSE)<>"","Yes","No") -> Yes | H19: =IF((VLOOKUP(A19,Crosswalk,3,FALSE))=0," ",(VLOOKUP(A19,Crosswalk,3,FALSE))) -> 100% Overhead
A20: 100-SD | B20: 28 | E20: =IF((VLOOKUP(A20,Crosswalk,2,FALSE)="Excluded"),0,(SUM(B20+C20+D20))) -> 28 | F20: =E20/SUM($E$2:$E$40) -> 0.0035691523 | G20: =IF(VLOOKUP(A20,Model,2,FALSE)<>"","Yes","No") -> Yes | H20: =IF((VLOOKUP(A20,Crosswalk,3,FALSE))=0," ",(VLOOKUP(A20,Crosswalk,3,FALSE)))
A21: 200-TR | B21: 826 | C21: -27 | E21: =IF((VLOOKUP(A21,Crosswalk,2,FALSE)="Excluded"),0,(SUM(B21+C21+D21))) -> 799 | F21: =E21/SUM($E$2:$E$40) -> 0.10184831 | G21: =IF(VLOOKUP(A21,Model,2,FALSE)<>"","Yes","No") -> Yes | H21: =IF((VLOOKUP(A21,Crosswalk,3,FALSE))=0," ",(VLOOKUP(A21,Crosswalk,3,FALSE)))
A22: 202-EC | B22: 150 | E22: =IF((VLOOKUP(A22,Crosswalk,2,FALSE)="Excluded"),0,(SUM(B22+C22+D22))) -> 150 | F22: =E22/SUM($E$2:$E$40) -> 0.019120459 | G22: =IF(VLOOKUP(A22,Model,2,FALSE)<>"","Yes","No") -> Yes | H22: =IF((VLOOKUP(A22,Crosswalk,3,FALSE))=0," ",(VLOOKUP(A22,Crosswalk,3,FALSE)))
A23: 203-DS | B23: 373 | C23: -1 | E23: =IF((VLOOKUP(A23,Crosswalk,2,FALSE)="Excluded"),0,(SUM(B23+C23+D23))) -> 372 | F23: =E23/SUM($E$2:$E$40) -> 0.047418738 | G23: =IF(VLOOKUP(A23,Model,2,FALSE)<>"","Yes","No") -> Yes | H23: =IF((VLOOKUP(A23,Crosswalk,3,FALSE))=0," ",(VLOOKUP(A23,Crosswalk,3,FALSE)))
A24: 216-PA | B24: 5 | D24: -5 | E24: =IF((VLOOKUP(A24,Crosswalk,2,FALSE)="Excluded"),0,(SUM(B24+C24+D24))) -> 0 | F24: =E24/SUM($E$2:$E$40) -> 0 | G24: =IF(VLOOKUP(A24,Model,2,FALSE)<>"","Yes","No") -> Yes | H24: =IF((VLOOKUP(A24,Crosswalk,3,FALSE))=0," ",(VLOOKUP(A24,Crosswalk,3,FALSE))) -> Fixed at $25,000 (hardcoded in Model)
A25: 402-PK | B25: 17 | C25: -2 | E25: =IF((VLOOKUP(A25,Crosswalk,2,FALSE)="Excluded"),0,(SUM(B25+C25+D25))) -> 15 | F25: =E25/SUM($E$2:$E$40) -> 0.0019120459 | G25: =IF(VLOOKUP(A25,Model,2,FALSE)<>"","Yes","No") -> Yes | H25: =IF((VLOOKUP(A25,Crosswalk,3,FALSE))=0," ",(VLOOKUP(A25,Crosswalk,3,FALSE)))
A26: 600-ES | B26: 562 | C26: -31 | E26: =IF((VLOOKUP(A26,Crosswalk,2,FALSE)="Excluded"),0,(SUM(B26+C26+D26))) -> 531 | F26: =E26/SUM($E$2:$E$40) -> 0.067686424 | G26: =IF(VLOOKUP(A26,Model,2,FALSE)<>"","Yes","No") -> Yes | H26: =IF((VLOOKUP(A26,Crosswalk,3,FALSE))=0," ",(VLOOKUP(A26,Crosswalk,3,FALSE)))
A27: 601-WA | B27: 3 | E27: =IF((VLOOKUP(A27,Crosswalk,2,FALSE)="Excluded"),0,(SUM(B27+C27+D27))) -> 3 | F27: =E27/SUM($E$2:$E$40) -> 0.00038240918 | G27: =IF(VLOOKUP(A27,Model,2,FALSE)<>"","Yes","No") -> Yes | H27: =IF((VLOOKUP(A27,Crosswalk,3,FALSE))=0," ",(VLOOKUP(A27,Crosswalk,3,FALSE)))
A28: 602-WA | B28: 706 | C28: -18 | E28: =IF((VLOOKUP(A28,Crosswalk,2,FALSE)="Excluded"),0,(SUM(B28+C28+D28))) -> 688 | F28: =E28/SUM($E$2:$E$40) -> 0.087699171 | G28: =IF(VLOOKUP(A28,Model,2,FALSE)<>"","Yes","No") -> Yes | H28: =IF((VLOOKUP(A28,Crosswalk,3,FALSE))=0," ",(VLOOKUP(A28,Crosswalk,3,FALSE)))
A29: 603-PK | B29: 66 | C29: -25 | E29: =IF((VLOOKUP(A29,Crosswalk,2,FALSE)="Excluded"),0,(SUM(B29+C29+D29))) -> 41 | F29: =E29/SUM($E$2:$E$40) -> 0.0052262588 | G29: =IF(VLOOKUP(A29,Model,2,FALSE)<>"","Yes","No") -> Yes | H29: =IF((VLOOKUP(A29,Crosswalk,3,FALSE))=0," ",(VLOOKUP(A29,Crosswalk,3,FALSE)))
A30: 604-PK | B30: 71 | C30: -22 | E30: =IF((VLOOKUP(A30,Crosswalk,2,FALSE)="Excluded"),0,(SUM(B30+C30+D30))) -> 49 | F30: =E30/SUM($E$2:$E$40) -> 0.0062460166 | G30: =IF(VLOOKUP(A30,Model,2,FALSE)<>"","Yes","No") -> Yes | H30: =IF((VLOOKUP(A30,Crosswalk,3,FALSE))=0," ",(VLOOKUP(A30,Crosswalk,3,FALSE)))
A31: 605-PN | B31: 30 | E31: =IF((VLOOKUP(A31,Crosswalk,2,FALSE)="Excluded"),0,(SUM(B31+C31+D31))) -> 30 | F31: =E31/SUM($E$2:$E$40) -> 0.0038240918 | G31: =IF(VLOOKUP(A31,Model,2,FALSE)<>"","Yes","No") -> Yes | H31: =IF((VLOOKUP(A31,Crosswalk,3,FALSE))=0," ",(VLOOKUP(A31,Crosswalk,3,FALSE)))
A32: 608-ES | B32: 5 | E32: =IF((VLOOKUP(A32,Crosswalk,2,FALSE)="Excluded"),0,(SUM(B32+C32+D32))) -> 5 | F32: =E32/SUM($E$2:$E$40) -> 0.00063734863 | G32: =IF(VLOOKUP(A32,Model,2,FALSE)<>"","Yes","No") -> Yes | H32: =IF((VLOOKUP(A32,Crosswalk,3,FALSE))=0," ",(VLOOKUP(A32,Crosswalk,3,FALSE)))
A33: 700-MF | B33: 10 | E33: =IF((VLOOKUP(A33,Crosswalk,2,FALSE)="Excluded"),0,(SUM(B33+C33+D33))) -> 10 | F33: =E33/SUM($E$2:$E$40) -> 0.0012746973 | G33: =IF(VLOOKUP(A33,Model,2,FALSE)<>"","Yes","No") -> Yes | H33: =IF((VLOOKUP(A33,Crosswalk,3,FALSE))=0," ",(VLOOKUP(A33,Crosswalk,3,FALSE))) -> Excludes insurance claim payouts (529721)
A34: 701-MF | B34: 36 | E34: =IF((VLOOKUP(A34,Crosswalk,2,FALSE)="Excluded"),0,(SUM(B34+C34+D34))) -> 36 | F34: =E34/SUM($E$2:$E$40) -> 0.0045889101 | G34: =IF(VLOOKUP(A34,Model,2,FALSE)<>"","Yes","No") -> Yes | H34: =IF((VLOOKUP(A34,Crosswalk,3,FALSE))=0," ",(VLOOKUP(A34,Crosswalk,3,FALSE)))
A35: 702-MF | B35: 78 | C35: -1 | E35: =IF((VLOOKUP(A35,Crosswalk,2,FALSE)="Excluded"),0,(SUM(B35+C35+D35))) -> 77 | F35: =E35/SUM($E$2:$E$40) -> 0.0098151689 | G35: =IF(VLOOKUP(A35,Model,2,FALSE)<>"","Yes","No") -> Yes | H35: =IF((VLOOKUP(A35,Crosswalk,3,FALSE))=0," ",(VLOOKUP(A35,Crosswalk,3,FALSE)))
A36: 703-MF | B36: 32 | C36: -3 | E36: =IF((VLOOKUP(A36,Crosswalk,2,FALSE)="Excluded"),0,(SUM(B36+C36+D36))) -> 29 | F36: =E36/SUM($E$2:$E$40) -> 0.0036966221 | G36: =IF(VLOOKUP(A36,Model,2,FALSE)<>"","Yes","No") -> Yes | H36: =IF((VLOOKUP(A36,Crosswalk,3,FALSE))=0," ",(VLOOKUP(A36,Crosswalk,3,FALSE)))
A37: 704-MF | B37: 15 | E37: =IF((VLOOKUP(A37,Crosswalk,2,FALSE)="Excluded"),0,(SUM(B37+C37+D37))) -> 15 | F37: =E37/SUM($E$2:$E$40) -> 0.0019120459 | G37: =IF(VLOOKUP(A37,Model,2,FALSE)<>"","Yes","No") -> Yes | H37: =IF((VLOOKUP(A37,Crosswalk,3,FALSE))=0," ",(VLOOKUP(A37,Crosswalk,3,FALSE)))
A38: 705-MF | B38: 8 | E38: =IF((VLOOKUP(A38,Crosswalk,2,FALSE)="Excluded"),0,(SUM(B38+C38+D38))) -> 8 | F38: =E38/SUM($E$2:$E$40) -> 0.0010197578 | G38: =IF(VLOOKUP(A38,Model,2,FALSE)<>"","Yes","No") -> Yes | H38: =IF((VLOOKUP(A38,Crosswalk,3,FALSE))=0," ",(VLOOKUP(A38,Crosswalk,3,FALSE)))
A39: 706-MF | B39: 242 | C39: -1 | E39: =IF((VLOOKUP(A39,Crosswalk,2,FALSE)="Excluded"),0,(SUM(B39+C39+D39))) -> 241 | F39: =E39/SUM($E$2:$E$40) -> 0.030720204 | G39: =IF(VLOOKUP(A39,Model,2,FALSE)<>"","Yes","No") -> Yes | H39: =IF((VLOOKUP(A39,Crosswalk,3,FALSE))=0," ",(VLOOKUP(A39,Crosswalk,3,FALSE)))
A40: 800-DR | B40: 17 | E40: =IF((VLOOKUP(A40,Crosswalk,2,FALSE)="Excluded"),0,(SUM(B40+C40+D40))) -> 17 | F40: =E40/SUM($E$2:$E$40) -> 0.0021669853 | G40: =IF(VLOOKUP(A40,Model,2,FALSE)<>"","Yes","No") -> Yes | H40: =IF((VLOOKUP(A40,Crosswalk,3,FALSE))=0," ",(VLOOKUP(A40,Crosswalk,3,FALSE))) -> Excludes retirement payouts, PERS contributions, and disability/death benefits (547000, 547100)
F41: =SUM(F2:F40) -> 1

Sheet $ FY 2009-10
A1: Fund/Bureau | B1: Operating | C1: Capital | D1: Total | E1: 50% Capital Discount | F1: Passthrough Discount | G1: Other Discounts | H1: Overhead Bureau Discount | I1: Revised Total | J1: Allocation Percent | K1: In Model?
A2: 100-AT | B2: 7636300 | C2: 0 | D2: =SUM(B2:C2) -> 7636300 | E2: =C2*-0.5 -> 0 | H2: =-D2-E2-F2-G2 -> -7636300 | I2: =IF((VLOOKUP(A2,Crosswalk,2,FALSE)="Excluded"),0,(D2+E2+F2+G2+H2)) -> 0 | J2: =I2/(SUM($I$2:$I$80)) -> 0 | K2: =IF(VLOOKUP(A2,Model,2,FALSE)<>"","Yes","No") -> Yes | L2: =IF((VLOOKUP(A2,Crosswalk,3,FALSE))=0," ",(VLOOKUP(A2,Crosswalk,3,FALSE))) -> 100% Overhead
A3: 100-AU | B3: 5746863 | C3: 1548 | D3: =SUM(B3:C3) -> 5748411 | E3: =C3*-0.5 -> -774 | H3: =-D3-E3-F3-G3 -> -5747637 | I3: =IF((VLOOKUP(A3,Crosswalk,2,FALSE)="Excluded"),0,(D3+E3+F3+G3+H3)) -> 0 | J3: =I3/(SUM($I$2:$I$80)) -> 0 | K3: =IF(VLOOKUP(A3,Model,2,FALSE)<>"","Yes","No") -> Yes | L3: =IF((VLOOKUP(A3,Crosswalk,3,FALSE))=0," ",(VLOOKUP(A3,Crosswalk,3,FALSE))) -> 100% Overhead
A4: 100-CB | B4: 1600773 | C4: 0 | D4: =SUM(B4:C4) -> 1600773 | E4: =C4*-0.5 -> 0 | I4: =IF((VLOOKUP(A4,Crosswalk,2,FALSE)="Excluded"),0,(D4+E4+F4+G4+H4)) -> 1600773 | J4: =I4/(SUM($I$2:$I$80)) -> 0.0018047776 | K4: =IF(VLOOKUP(A4,Model,2,FALSE)<>"","Yes","No") -> Yes | L4: =IF((VLOOKUP(A4,Crosswalk,3,FALSE))=0," ",(VLOOKUP(A4,Crosswalk,3,FALSE)))
A5: 100-EM | B5: 1211697 | C5: 0 | D5: =SUM(B5:C5) -> 1211697 | E5: =C5*-0.5 -> 0 | H5: =-D5-E5-F5-G5 -> -1211697 | I5: =IF((VLOOKUP(A5,Crosswalk,2,FALSE)="Excluded"),0,(D5+E5+F5+G5+H5)) -> 0 | J5: =I5/(SUM($I$2:$I$80)) -> 0 | K5: =IF(VLOOKUP(A5,Model,2,FALSE)<>"","Yes","No") -> Yes | L5: =IF((VLOOKUP(A5,Crosswalk,3,FALSE))=0," ",(VLOOKUP(A5,Crosswalk,3,FALSE))) -> 100% Overhead
A6: 100-FR | B6: 81712119 | C6: 3025597 | D6: =SUM(B6:C6) -> 84737716 | E6: =C6*-0.5 -> -1512798.5 | H6: =-113805-406 -> -114211 | I6: =IF((VLOOKUP(A6,Crosswalk,2,FALSE)="Excluded"),0,(D6+E6+F6+G6+H6)) -> 83110706 | J6: =I6/(SUM($I$2:$I$80)) -> 0.093702445 | K6: =IF(VLOOKUP(A6,Model,2,FALSE)<>"","Yes","No") -> Yes | L6: =IF((VLOOKUP(A6,Crosswalk,3,FALSE))=0," ",(VLOOKUP(A6,Crosswalk,3,FALSE))) -> Exclude expenditures for emergency mgmt (FREO000004 Fund Center)
A7: 100-GR | B7: 1008299 | C7: 0 | D7: =SUM(B7:C7) -> 1008299 | E7: =C7*-0.5 -> 0 | H7: =-D7-E7-F7-G7 -> -1008299 | I7: =IF((VLOOKUP(A7,Crosswalk,2,FALSE)="Excluded"),0,(D7+E7+F7+G7+H7)) -> 0 | J7: =I7/(SUM($I$2:$I$80)) -> 0 | K7: =IF(VLOOKUP(A7,Model,2,FALSE)<>"","Yes","No") -> Yes | L7: =IF((VLOOKUP(A7,Crosswalk,3,FALSE))=0," ",(VLOOKUP(A7,Crosswalk,3,FALSE))) -> 100% Overhead
A8: 100-HC | B8: 11593884 | C8: 0 | D8: =SUM(B8:C8) -> 11593884 | E8: =C8*-0.5 -> 0 | I8: =IF((VLOOKUP(A8,Crosswalk,2,FALSE)="Excluded"),0,(D8+E8+F8+G8+H8)) -> 11593884 | J8: =I8/(SUM($I$2:$I$80)) -> 0.013071424 | K8: =IF(VLOOKUP(A8,Model,2,FALSE)<>"","Yes","No") -> Yes | L8: =IF((VLOOKUP(A8,Crosswalk,3,FALSE))=0," ",(VLOOKUP(A8,Crosswalk,3,FALSE)))
A9: 100-HN | B9: 641362 | C9: 0 | D9: =SUM(B9:C9) -> 641362 | E9: =C9*-0.5 -> 0 | I9: =IF((VLOOKUP(A9,Crosswalk,2,FALSE)="Excluded"),0,(D9+E9+F9+G9+H9)) -> 0 | J9: =I9/(SUM($I$2:$I$80)) -> 0 | K9: =IF(VLOOKUP(A9,Model,2,FALSE)<>"","Yes","No") -> Yes | L9: =IF((VLOOKUP(A9,Crosswalk,3,FALSE))=0," ",(VLOOKUP(A9,Crosswalk,3,FALSE)))
A10: 100-MF | B10: 29386088 | C10: 304629 | D10: =SUM(B10:C10) -> 29690717 | E10: =C10*-0.5 -> -152314.5 | H10: =-(9317634+4623862+7688310) -> -21629806 | I10: =IF((VLOOKUP(A10,Crosswalk,2,FALSE)="Excluded"),0,(D10+E10+F10+G10+H10)) -> 7908596.5 | J10: =I10/(SUM($I$2:$I$80)) -> 0.0089164785 | K10: =IF(VLOOKUP(A10,Model,2,FALSE)<>"","Yes","No") -> Yes | L10: =IF((VLOOKUP(A10,Crosswalk,3,FALSE))=0," ",(VLOOKUP(A10,Crosswalk,3,FALSE))) -> Exclude MFHR, MFDR, MFIB
A11: 100-MY | B11: 2593945 | C11: 0 | D11: =SUM(B11:C11) -> 2593945 | E11: =C11*-0.5 -> 0 | H11: =-2055958-525753 -> -2581711 | I11: =IF((VLOOKUP(A11,Crosswalk,2,FALSE)="Excluded"),0,(D11+E11+F11+G11+H11)) -> 12234 | J11: =I11/(SUM($I$2:$I$80)) -> 1.3793117e-05 | K11: =IF(VLOOKUP(A11,Model,2,FALSE)<>"","Yes","No") -> Yes | L11: =IF((VLOOKUP(A11,Crosswalk,3,FALSE))=0," ",(VLOOKUP(A11,Crosswalk,3,FALSE))) -> Exclude expenditures for Admin & Support (LAMYAS Functional Area)
A12: 100-NI | B12: 6845374 | C12: 6729 | D12: =SUM(B12:C12) -> 6852103 | E12: =C12*-0.5 -> -3364.5 | H12: -372944 | I12: =IF((VLOOKUP(A12,Crosswalk,2,FALSE)="Excluded"),0,(D12+E12+F12+G12+H12)) -> 6475794.5 | J12: =I12/(SUM($I$2:$I$80)) -> 0.0073010783 | K12: =IF(VLOOKUP(A12,Model,2,FALSE)<>"","Yes","No") -> Yes | L12: =IF((VLOOKUP(A12,Crosswalk,3,FALSE))=0," ",(VLOOKUP(A12,Crosswalk,3,FALSE))) -> Exclude expenditures for Information & Referral and Public Involvement best practices (CDIR, CDNRNOPI)
A13: 100-OE | B13: 356979 | C13: 0 | D13: =SUM(B13:C13) -> 356979 | E13: =C13*-0.5 -> 0 | H13: =-0.68*D13 -> -242745.72 | I13: =IF((VLOOKUP(A13,Crosswalk,2,FALSE)="Excluded"),0,(D13+E13+F13+G13+H13)) -> 114233.28 | J13: =I13/(SUM($I$2:$I$80)) -> 0.00012879132 | K13: =IF(VLOOKUP(A13,Model,2,FALSE)<>"","Yes","No") -> Yes | L13: =IF((VLOOKUP(A13,Crosswalk,3,FALSE))=0," ",(VLOOKUP(A13,Crosswalk,3,FALSE))) -> Rollback in 09-10 & 10-11. Exclude expenditures for Citywide Comm, Training, Tech Support and % admin (CDCEEC, TE, TS & portion CDAS (68%))
