Workbook

Sheet Cover Page
A1: UTAH STATE OFFICE OF EDUCATION
A2: STANDARD APPLICATION FOR FINANCIAL ASSISTANCE
A5: 1. LEA NAME and COMPLETE MAILING ADDRESS
B6: Area Code and Telephone Number
B8: Website
A10: 2. DATE APPLICATION SUBMITTED
A11: 3. EXPENDITURE PERIOD Beginning Date of Project: | B11: Date of approved budget - completed by USOE
A12: Ending Date of Project:
A13: 4. PROJECT DIRECTOR
A14: Name of Employee Responsible for Supervising This Project:
A15: E-Mail Address:
A16: Phone Number: (include area code)
A17: 5. IMMEDIATE SUPERVISOR
A18: Name of Employee To Whom The Project Director Reports:
A19: E-Mail Address:
A20: Phone Number: (include area code)
A21: 6. DESCRIPTIVE NAME OF PROGRAM State Start-up & Implementation Grant
A23: 7. AMOUNT REQUESTED FOR FUNDING (include the total for all available years)
A24: The agency certifies to the best of its knowledge and belief, the data in this application is true and correct. The agency will agree to meet all of the requirements, including the project objectives outlined within the grant application. The agency also agrees to comply with all other applicable State Finance Regulations.
... A26: Signature of Charter School Board Chair (not designee)
A28: Return Application To: | B28: FOR USOE USE ONLY
A29: Marlies Burns, Charter Schools | B29: Date Application Received:
A30: Utah State Office of Education
A31: 250 East 500 South | B31: Program Content Reviewed By/Date:
A32: PO Box 144200
A33: Salt Lake City, UT 84114-4200 | B33: Budget Reviewed By/Date:
A34: marlies.burns@schools.utah.gov
A35: "Standard Application for Discretionary Funds"

Sheet Part I Summary
A1: Part I Budget Information
A2: Applicants requesting funding for only one year should complete the column under "Project Year 1." Applicants requesting funding for multi-year grants
A3: should complete all applicable columns. Please read all instructions and guidance in Chapter 5 before completing form. Remember that subgrant funds cannot
A4: be spent or encumbered until final written approval is received (i.e., after the budget is approved). Budget your time wisely.
A5: Budget Summary
A6: Budget Categories | B6: Project Year 1 | C6: Project Year 2 | D6: Project Year 3 | E6: Total
A7: A. Salaries (100) and Benefits (200) | B7: =SUM('Salaries & Benefits (100-200)'!B8:B12) -> 0 | C7: =SUM('Salaries & Benefits (100-200)'!C8:C12) -> 0 | D7: =SUM('Salaries & Benefits (100-200)'!D8:D12) -> 0 | E7: =SUM('Salaries & Benefits (100-200)'!E8:E12) -> 0
A8: B. Purchased Professional and Technical Services (300) | B8: =SUM('Professional Services (300)'!B9:B23) -> 0 | C8: =SUM('Professional Services (300)'!C9:C23) -> 0 | D8: =SUM('Professional Services (300)'!D9:D23) -> 0 | E8: =SUM('Professional Services (300)'!E9:E23) -> 0
A9: C. Purchased Property Services (400) | B9: =SUM('Property Services (400)'!B6:B29) -> 0 | C9: =SUM('Property Services (400)'!C6:C29) -> 0 | D9: =SUM('Property Services (400)'!D6:D29) -> 0 | E9: =SUM('Property Services (400)'!E6:E29) -> 0
A10: D. Other Purchased Services (500) | B10: =SUM('Other (500)'!B7:B30) -> 0 | C10: =SUM('Other (500)'!C7:C30) -> 0 | D10: =SUM('Other (500)'!D7:D30) -> 0 | E10: =SUM('Other (500)'!E7:E30) -> 0
A11: E. Travel (580) | B11: =SUM('Travel (580)'!B7:B30) -> 0 | C11: =SUM('Travel (580)'!C7:C30) -> 0 | D11: =SUM('Travel (580)'!D7:D30) -> 0 | E11: =SUM('Travel (580)'!E7:E30) -> 0
A12: F. Supplies and Materials (600) | B12: =SUM('Supplies and Materials (600)'!B7:B30) -> 0 | C12: =SUM('Supplies and Materials (600)'!C7:C30) -> 0 | D12: =SUM('Supplies and Materials (600)'!D7:D30) -> 0 | E12: =SUM('Supplies and Materials (600)'!E7:E30) -> 0
A13: G. Property (includes equipment and computer hardware) (700) | B13: =SUM('Property (700)'!B7:B30) -> 0 | C13: =SUM('Property (700)'!C7:C30) -> 0 | D13: =SUM('Property (700)'!D7:D30) -> 0 | E13: =SUM('Property (700)'!E7:E30) -> 0
A14: TOTALS (lines A through G) | B14: =SUM(B7:B13) -> 0 | C14: =SUM(C7:C13) -> 0 | D14: =SUM(D7:D13) -> 0 | E14: =SUM(E7:E13) -> 0
A16: NOTE: The values for Project Years 1 - 3 and Total will populate automatically as you complete worksheets in Part II Budget Detail.

Sheet Salaries & Benefits (100-200)
A1: Part II Budget Detail
A2: Amount paid to employees of the LEA/Agency in positions of a permanent nature or hired temporarily, including substitutes for those that are in permanent
A3: positions. Benefits include amounts paid by LEA on behalf of employees which are over and above salary. Funds must supplement rather than supplant local
A4: effort. Funds may be used for salary and benefits , not to exceed $5,000 per month.
A5: Salaries (100) and Benefits (200)
B6: Project Year 1 | C6: Project Year 2 | D6: Project Year 3 | E6: Total
A7: Employee name, Title
E8: =SUM(B8:D8) -> 0
E9: =SUM(B9:D9) -> 0
E10: =SUM(B10:D10) -> 0
E11: =SUM(B11:D11) -> 0
E12: =SUM(B12:D12) -> 0

Sheet Professional Services (300)
A1: Part II Budget Detail
A2: Purchased services which, by their nature, can be performed only by persons with specialized skills, knowledge and services. Included are the services of
A3: accountants, architects, auditors, consultants, dentists, lawyers, medical, etc. (list substitutes hired for permanent positions under “salaries”). This area will
A4: also include any associated expenses paid to the service provider such as travel, per-diem, and miscellaneous items. In the Description, provide details such
A5: as: (1) Name of consultant, presenter, (2) Amount per hour /day to be paid per person and name of services, (3) purpose of services and products or
A6: evaluations expected.
A7: Purchased Professional and Technical Services (300)
A8: Description | B8: Project Year 1 | C8: Project Year 2 | D8: Project Year 3 | E8: Total
E9: =SUM(B9:D9) -> 0
E10: =SUM(B10:D10) -> 0
E11: =SUM(B11:D11) -> 0
E12: =SUM(B12:D12) -> 0
E13: =SUM(B13:D13) -> 0
E14: =SUM(B14:D14) -> 0
E15: =SUM(B15:D15) -> 0
E16: =SUM(B16:D16) -> 0
E17: =SUM(B17:D17) -> 0
E18: =SUM(B18:D18) -> 0
E19: =SUM(B19:D19) -> 0
E20: =SUM(B20:D20) -> 0
... E23: =SUM(B23:D23) -> 0

Sheet Property Services (400)
A1: Part II Budget Detail
A2: Amounts paid for services, rendered by organizations or personnel not on payroll of the school, to operate, repair, maintain, insure and rent property
A3: owned and/or used by the school.
A4: Purchased Property Services (400)
A5: Description | B5: Project Year 1 | C5: Project Year 2 | D5: Project Year 3 | E5: Total
E6: =SUM(B6:D6) -> 0
E7: =SUM(B7:D7) -> 0
E8: =SUM(B8:D8) -> 0
E9: =SUM(B9:D9) -> 0
E10: =SUM(B10:D10) -> 0
E11: =SUM(B11:D11) -> 0
E12: =SUM(B12:D12) -> 0
E13: =SUM(B13:D13) -> 0
E14: =SUM(B14:D14) -> 0
E15: =SUM(B15:D15) -> 0
E16: =SUM(B16:D16) -> 0
E17: =SUM(B17:D17) -> 0
... E29: =SUM(B29:D29) -> 0

Sheet Other (500)
A1: Part II Budget Detail
A2: Amounts paid for services rendered by organizations or personnel not on payroll of the school, and other than Professional and Technical Services (300),
A3: or Purchased Property Services (400). This would also include expenses for meeting facilities, conference hotels (which may include direct-billed items for
A4: group meals and lodging provided to participants, equipment, space charges, and miscellaneous). Also, any travel and per-diem expenses for participants.
A5: Other Purchased Services (500)
A6: Description | B6: Project Year 1 | C6: Project Year 2 | D6: Project Year 3 | E6: Total
E7: =SUM(B7:D7) -> 0
E8: =SUM(B8:D8) -> 0
E9: =SUM(B9:D9) -> 0
E10: =SUM(B10:D10) -> 0
E11: =SUM(B11:D11) -> 0
E12: =SUM(B12:D12) -> 0
E13: =SUM(B13:D13) -> 0
E14: =SUM(B14:D14) -> 0
E15: =SUM(B15:D15) -> 0
E16: =SUM(B16:D16) -> 0
E17: =SUM(B17:D17) -> 0
E18: =SUM(B18:D18) -> 0
... E30: =SUM(B30:D30) -> 0

Sheet Travel (580)
A1: Part II Budget Detail
A2: Expenditures for transportation, meals, hotel, and other expenses associated with staff (on payroll) travel for the school. Payments for per-diem in lieu of
A3: reimbursements for subsistence (room and board) also are charged here. Provide details such as names of staff (on payroll) who will be conducting
A4: activities of this project and will be drawing from this fund source.
A5: Travel (580)
A6: Description | B6: Project Year 1 | C6: Project Year 2 | D6: Project Year 3 | E6: Total
E7: =SUM(B7:D7) -> 0
E8: =SUM(B8:D8) -> 0
E9: =SUM(B9:D9) -> 0
E10: =SUM(B10:D10) -> 0
E11: =SUM(B11:D11) -> 0
E12: =SUM(B12:D12) -> 0
E13: =SUM(B13:D13) -> 0
E14: =SUM(B14:D14) -> 0
E15: =SUM(B15:D15) -> 0
E16: =SUM(B16:D16) -> 0
E17: =SUM(B17:D17) -> 0
E18: =SUM(B18:D18) -> 0
... E30: =SUM(B30:D30) -> 0

Sheet Supplies and Materials (600)
A1: Part II Budget Detail
A2: Amounts paid for items of an expendable nature that are consumed, worn out, or deteriorated in use; or items that lose their identity through fabrication or
A3: incorporation into different or more complex units or substances are considered supply expenditures. Amounts paid for non-equipment items and with
A4: reasonable care and use may be expected to last for more than one year, are considered material expenditures. Includes computer programs (software).
A5: Supplies and Materials (600)
A6: Description | B6: Project Year 1 | C6: Project Year 2 | D6: Project Year 3 | E6: Total
E7: =SUM(B7:D7) -> 0
E8: =SUM(B8:D8) -> 0
E9: =SUM(B9:D9) -> 0
E10: =SUM(B10:D10) -> 0
E11: =SUM(B11:D11) -> 0
E12: =SUM(B12:D12) -> 0
E13: =SUM(B13:D13) -> 0
E14: =SUM(B14:D14) -> 0
E15: =SUM(B15:D15) -> 0
E16: =SUM(B16:D16) -> 0
E17: =SUM(B17:D17) -> 0
E18: =SUM(B18:D18) -> 0
... E30: =SUM(B30:D30) -> 0

Sheet Property (700)
A1: Part II Budget Detail
A2: Expenditures for the acquisition of fixed assets, including expenditures for land or existing buildings and improvements of grounds; initial equipment;
A3: additional equipment; and replacement of equipment. (i.e., machinery, school buses, furniture & fixtures, audiovisual equipment, non-bus vehicles,
A4: computer equipment (hardware)).
A5: Property (700)
A6: Description | B6: Project Year 1 | C6: Project Year 2 | D6: Project Year 3 | E6: Total
E7: =SUM(B7:D7) -> 0
E8: =SUM(B8:D8) -> 0
E9: =SUM(B9:D9) -> 0
E10: =SUM(B10:D10) -> 0
E11: =SUM(B11:D11) -> 0
E12: =SUM(B12:D12) -> 0
E13: =SUM(B13:D13) -> 0
E14: =SUM(B14:D14) -> 0
E15: =SUM(B15:D15) -> 0
E16: =SUM(B16:D16) -> 0
E17: =SUM(B17:D17) -> 0
E18: =SUM(B18:D18) -> 0
... E30: =SUM(B30:D30) -> 0
