Workbook

Sheet COVER
A1: KETCHIKAN GATEWAY BOROUGH
A2: Department of Assessment, 1900 First Avenue, Suite 219, Ketchikan, AK 99901
A3: Phone: 907.228.6640 Fax: 907.228.6655 Email: bp@kgbak.us
A4: The Business Personal Return is also available for electronic filing (Excel) at www.kgbak.us
A5: 2015 - BUSINESS/PERSONAL PROPERTY RETURN
A6: THIS FORM IS TO BE FILED ON OR BEFORE JANUARY 15th 2015.
A11: Person to Contact Concerning This Report
A15: Instructions for filing Business/Personal Property Return: This return should be used for any retail, wholesale, industrial, hotel, service, professional, or other enterprises and aircraft are to be declared on this return. Property that is temporarily out of the City of Ketchikan on January 1st is taxable. Licensed vehicles, boats, and inventory are not to be declared on this form. Include a leased equipment listing, so that the lessor may be contacted.
A16: Fair market value should be given for each category of assets listed. IRS depreciation is not acceptable. Note separately any assets sold or discarded during the preceding year. All returns are subject to the Department of Assessment review and/or revision. Incomplete forms may be returned.
A17: ITEMIZATION IS REQUIRED; A PRINTOUT OF ASSETS MAY BE ATTACHED TO THIS FORM.
A18: The Department of Assessment will declare a value for returns not received by the due date and the property assessment will be based upon the Department’s declared value.
A19: Who must file? Every person, firm, association, or corporation - regardless of residency - who owns or controls personal property which is not specifically exempt in the City of Ketchikan. | D19: What must be listed? All personal property located in the City of Ketchikan that was in the control of, or use by, the taxpayer on January 1. This includes assets owned, leased by, loaned to, or borrowed by the taxpayer.
A20: How Do I File? Complete this report by reviewing steps 1 through 10 on the BPP Summary page. The electronic form will self calculate depreciation and value for assets. | D20: When and where do I file? Upon formal request by the taxpayer, the Assessor may grant an extension of up to 30 days to submit the return by January 15 of the assessment year.
A22: KGB 4.45.190. Failure to file return; penalty. (a) If a taxpayer fails to file a return as provided in 4.45.170 (a) by January 15th of the tax year and, as allowed under 4.45.180, the Assessor prepares a valuation based upon information available or obtained by the Assessor of the taxable property (also referred to as a “forced filing”) the taxpayer shall be subject to a fee of two hundred dollars ($200) for the costs of the Assessor’s preparation of the forced filing return. Upon formal request by the taxpayer, the Assessor may grant an extension of up to 30 days to submit the return. The Assessor shall notify the taxpayer of the fee as of the date of mailing of Personal Property assessment notices.

Sheet SUMMARY
A1: KETCHIKAN GATEWAY BOROUGH
A2: Department of Assessment, 1900 First Avenue, Suite 219, Ketchikan, AK 99901
A3: Phone: 907.228.6640 Fax: 907.228.6655 Email: bp@kgbak.us
A4: The Business Personal Return is also available for electronic filing (Excel) at www.kgbak.us
A5: 2015 BUSINESS/PERSONAL PROPERTY RETURN
A6: I HEREBY DECLARE OWNERSHIP OR CONTROL OF THE FOLLOWING TAXABLE BUSINESS PROPERTY
A7: NO CHANGE FROM PREVIOUS YEAR? | D7: (Enter "No Change" at right, sign & date return)
A8: NO LONGER IN BUSINESS? | D8: (Complete lines 1,2,&3 below, sign & date return)
A9: 1
A10: 2
A11: 3
A12: ASSETS
C13: ACQUISITION COST | D13: ACCRUED DEPRECIATION | E13: MARKET VALUE | F13: FOR OFFICE USE ONLY
A14: Pages 3 & 4 | B14: OFFICE EQUIPMENT AND COMPUTERS | C14: =IF(SUM('COMPUTERS (Pg. 3)'!B3:B50)+SUM('OFFICE EQUIPMENT (Pg. 4)'!B3:B50)=0,"", SUM('COMPUTERS (Pg. 3)'!B3:B50)+SUM('OFFICE EQUIPMENT (Pg. 4)'!B3:B50)) | D14: =IF(E14="","",C14-E14) | E14: =IF(C14="","",SUM('COMPUTERS (Pg. 3)'!F3:F50)+SUM('OFFICE EQUIPMENT (Pg. 4)'!F3:F50))
A16: Page 5 | B16: FURNITURE, FIXTURES AND LEASEHOLD | C16: =IF(SUM('FURNITURE & FIXTURES (Pg. 5)'!B3:B50)=0,"",SUM('FURNITURE & FIXTURES (Pg. 5)'!B3:B50)) | D16: =IF(E16="","",C16-E16) | E16: =IF(C16="","",SUM('FURNITURE & FIXTURES (Pg. 5)'!G3:G50))
A18: Page 6 | B18: MACHINERY AND EQUIPMENT | C18: =IF(SUM('MACHINERY & EQUIPMENT (Pg. 6)'!B3:B50)=0,"",SUM('MACHINERY & EQUIPMENT (Pg. 6)'!B3:B50)) | D18: =IF(E18="","",C18-E18) | E18: =IF(C18="","",SUM('MACHINERY & EQUIPMENT (Pg. 6)'!F3:F50))
B19: TOTAL (RND $100) | C19: =IF(AND(C14="",C16="",C18="")=TRUE,"",ROUND(SUM(C14:C18),-2)) | D19: =IF(AND(D14="",D16="",D18="")=TRUE,"",ROUND(SUM(D14:D18),-2)) | E19: =IF(AND(E14="",E16="",E18="")=TRUE,"",ROUND(SUM(E14:E18),-2))
A21: Page 7 | B21: LEASED ASSETS | C21: SEE PAGE 6
A23: Page 7 | B23: SOLD OR DISPOSED ASSETS | C23: SEE PAGE 6
A25: AIRCRAFT & HELICOPTERS
F26: MARKET VALUE
A27: Page 8 | B27: AIRCRAFT | F27: =IF(ROUND(SUM('AIRCRAFT (Pg. 8)'!E3:E47),-2)=0,"",ROUND(SUM('AIRCRAFT (Pg. 8)'!E3:E47),-2))
B29: SOLD AIRCRAFT
B30: TRANSFER PRICE (AIRCRAFT) | D30: BUYERS NAME
B31: TRANSFER DATE | D31: MAILING ADDRESS
A35: SIGNATURE/TITLE OF PERSON PREPARING RETURN | E35: DATE

Sheet COMPUTERS (Pg. 3)
B1: COMPUTERS & SOFTWARE
A2: ITEM DESCRIPTION | B2: ACQUISTION COST | C2: YEAR ACQUIRED | D2: ECONOMIC LIFE | E2: DEPRECIATION | F2: MARKET VALUE | H2: OFFICE USE ONLY
E3: =IF(D3="","",IF(('OFFICE USE'!$H$1-C3)/D3>1,0.8,LOOKUP(('OFFICE USE'!$H$1-C3)/D3,'OFFICE USE'!$C$2:$D$102))) | F3: =IF(E3="","",B3*(1-E3))
E4: =IF(D4="","",IF(('OFFICE USE'!$H$1-C4)/D4>1,0.8,LOOKUP(('OFFICE USE'!$H$1-C4)/D4,'OFFICE USE'!$C$2:$D$102))) | F4: =IF(E4="","",B4*(1-E4))
E5: =IF(D5="","",IF(('OFFICE USE'!$H$1-C5)/D5>1,0.8,LOOKUP(('OFFICE USE'!$H$1-C5)/D5,'OFFICE USE'!$C$2:$D$102))) | F5: =IF(E5="","",B5*(1-E5))
E6: =IF(D6="","",IF(('OFFICE USE'!$H$1-C6)/D6>1,0.8,LOOKUP(('OFFICE USE'!$H$1-C6)/D6,'OFFICE USE'!$C$2:$D$102))) | F6: =IF(E6="","",B6*(1-E6))
E7: =IF(D7="","",IF(('OFFICE USE'!$H$1-C7)/D7>1,0.8,LOOKUP(('OFFICE USE'!$H$1-C7)/D7,'OFFICE USE'!$C$2:$D$102))) | F7: =IF(E7="","",B7*(1-E7))
E8: =IF(D8="","",IF(('OFFICE USE'!$H$1-C8)/D8>1,0.8,LOOKUP(('OFFICE USE'!$H$1-C8)/D8,'OFFICE USE'!$C$2:$D$102))) | F8: =IF(E8="","",B8*(1-E8))
E9: =IF(D9="","",IF(('OFFICE USE'!$H$1-C9)/D9>1,0.8,LOOKUP(('OFFICE USE'!$H$1-C9)/D9,'OFFICE USE'!$C$2:$D$102))) | F9: =IF(E9="","",B9*(1-E9))
E10: =IF(D10="","",IF(('OFFICE USE'!$H$1-C10)/D10>1,0.8,LOOKUP(('OFFICE USE'!$H$1-C10)/D10,'OFFICE USE'!$C$2:$D$102))) | F10: =IF(E10="","",B10*(1-E10))
E11: =IF(D11="","",IF(('OFFICE USE'!$H$1-C11)/D11>1,0.8,LOOKUP(('OFFICE USE'!$H$1-C11)/D11,'OFFICE USE'!$C$2:$D$102))) | F11: =IF(E11="","",B11*(1-E11))
E12: =IF(D12="","",IF(('OFFICE USE'!$H$1-C12)/D12>1,0.8,LOOKUP(('OFFICE USE'!$H$1-C12)/D12,'OFFICE USE'!$C$2:$D$102))) | F12: =IF(E12="","",B12*(1-E12))
E13: =IF(D13="","",IF(('OFFICE USE'!$H$1-C13)/D13>1,0.8,LOOKUP(('OFFICE USE'!$H$1-C13)/D13,'OFFICE USE'!$C$2:$D$102))) | F13: =IF(E13="","",B13*(1-E13))
E14: =IF(D14="","",IF(('OFFICE USE'!$H$1-C14)/D14>1,0.8,LOOKUP(('OFFICE USE'!$H$1-C14)/D14,'OFFICE USE'!$C$2:$D$102))) | F14: =IF(E14="","",B14*(1-E14))
... E50: =IF(D50="","",IF(('OFFICE USE'!$H$1-C50)/D50>1,0.8,LOOKUP(('OFFICE USE'!$H$1-C50)/D50,'OFFICE USE'!$C$2:$D$102))) | F50: =IF(E50="","",B50*(1-E50))

Sheet OFFICE EQUIPMENT (Pg. 4)
B1: OFFICE EQUIPMENT
A2: ITEM DESCRIPTION | B2: ACQUISTION COST | C2: YEAR ACQUIRED | D2: ECONOMIC LIFE | E2: DEPRECIATION | F2: MARKET VALUE | H2: OFFICE USE ONLY
E3: =IF(D3="","",IF(('OFFICE USE'!$H$1-C3)/D3>1,0.8,LOOKUP(('OFFICE USE'!$H$1-C3)/D3,'OFFICE USE'!$C$2:$D$102))) | F3: =IF(E3="","",B3*(1-E3))
E4: =IF(D4="","",IF(('OFFICE USE'!$H$1-C4)/D4>1,0.8,LOOKUP(('OFFICE USE'!$H$1-C4)/D4,'OFFICE USE'!$C$2:$D$102))) | F4: =IF(E4="","",B4*(1-E4))
E5: =IF(D5="","",IF(('OFFICE USE'!$H$1-C5)/D5>1,0.8,LOOKUP(('OFFICE USE'!$H$1-C5)/D5,'OFFICE USE'!$C$2:$D$102))) | F5: =IF(E5="","",B5*(1-E5))
E6: =IF(D6="","",IF(('OFFICE USE'!$H$1-C6)/D6>1,0.8,LOOKUP(('OFFICE USE'!$H$1-C6)/D6,'OFFICE USE'!$C$2:$D$102))) | F6: =IF(E6="","",B6*(1-E6))
E7: =IF(D7="","",IF(('OFFICE USE'!$H$1-C7)/D7>1,0.8,LOOKUP(('OFFICE USE'!$H$1-C7)/D7,'OFFICE USE'!$C$2:$D$102))) | F7: =IF(E7="","",B7*(1-E7))
E8: =IF(D8="","",IF(('OFFICE USE'!$H$1-C8)/D8>1,0.8,LOOKUP(('OFFICE USE'!$H$1-C8)/D8,'OFFICE USE'!$C$2:$D$102))) | F8: =IF(E8="","",B8*(1-E8))
E9: =IF(D9="","",IF(('OFFICE USE'!$H$1-C9)/D9>1,0.8,LOOKUP(('OFFICE USE'!$H$1-C9)/D9,'OFFICE USE'!$C$2:$D$102))) | F9: =IF(E9="","",B9*(1-E9))
E10: =IF(D10="","",IF(('OFFICE USE'!$H$1-C10)/D10>1,0.8,LOOKUP(('OFFICE USE'!$H$1-C10)/D10,'OFFICE USE'!$C$2:$D$102))) | F10: =IF(E10="","",B10*(1-E10))
E11: =IF(D11="","",IF(('OFFICE USE'!$H$1-C11)/D11>1,0.8,LOOKUP(('OFFICE USE'!$H$1-C11)/D11,'OFFICE USE'!$C$2:$D$102))) | F11: =IF(E11="","",B11*(1-E11))
E12: =IF(D12="","",IF(('OFFICE USE'!$H$1-C12)/D12>1,0.8,LOOKUP(('OFFICE USE'!$H$1-C12)/D12,'OFFICE USE'!$C$2:$D$102))) | F12: =IF(E12="","",B12*(1-E12))
E13: =IF(D13="","",IF(('OFFICE USE'!$H$1-C13)/D13>1,0.8,LOOKUP(('OFFICE USE'!$H$1-C13)/D13,'OFFICE USE'!$C$2:$D$102))) | F13: =IF(E13="","",B13*(1-E13))
E14: =IF(D14="","",IF(('OFFICE USE'!$H$1-C14)/D14>1,0.8,LOOKUP(('OFFICE USE'!$H$1-C14)/D14,'OFFICE USE'!$C$2:$D$102))) | F14: =IF(E14="","",B14*(1-E14))
... E50: =IF(D50="","",IF(('OFFICE USE'!$H$1-C50)/D50>1,0.8,LOOKUP(('OFFICE USE'!$H$1-C50)/D50,'OFFICE USE'!$C$2:$D$102))) | F50: =IF(E50="","",B50*(1-E50))

Sheet FURNITURE & FIXTURES (Pg. 5)
A1: FURNITURE, FIXTURES & LEASEHOLD | L1: YES
A2: ITEM DESCRIPTION | B2: ACQUISTION COST | C2: YEAR ACQUIRED | D2: ECONOMIC LIFE | E2: DEPRECIATE YES / NO | F2: DEPRECIATION | G2: MARKET VALUE | I2: OFFICE USE ONLY | L2: NO
F3: =IF(E3="","",IF(E3="NO",0%,IF(('OFFICE USE'!$H$1-C3)/D3>1,0.8,(LOOKUP(('OFFICE USE'!$H$1-C3)/D3,'OFFICE USE'!$C$2:$D$102))))) | G3: =IF(F3="","",B3*(1-F3))
F4: =IF(E4="","",IF(E4="NO",0%,IF(('OFFICE USE'!$H$1-C4)/D4>1,0.8,(LOOKUP(('OFFICE USE'!$H$1-C4)/D4,'OFFICE USE'!$C$2:$D$102))))) | G4: =IF(F4="","",B4*(1-F4))
F5: =IF(E5="","",IF(E5="NO",0%,IF(('OFFICE USE'!$H$1-C5)/D5>1,0.8,(LOOKUP(('OFFICE USE'!$H$1-C5)/D5,'OFFICE USE'!$C$2:$D$102))))) | G5: =IF(F5="","",B5*(1-F5))
F6: =IF(E6="","",IF(E6="NO",0%,IF(('OFFICE USE'!$H$1-C6)/D6>1,0.8,(LOOKUP(('OFFICE USE'!$H$1-C6)/D6,'OFFICE USE'!$C$2:$D$102))))) | G6: =IF(F6="","",B6*(1-F6))
F7: =IF(E7="","",IF(E7="NO",0%,IF(('OFFICE USE'!$H$1-C7)/D7>1,0.8,(LOOKUP(('OFFICE USE'!$H$1-C7)/D7,'OFFICE USE'!$C$2:$D$102))))) | G7: =IF(F7="","",B7*(1-F7))
F8: =IF(E8="","",IF(E8="NO",0%,IF(('OFFICE USE'!$H$1-C8)/D8>1,0.8,(LOOKUP(('OFFICE USE'!$H$1-C8)/D8,'OFFICE USE'!$C$2:$D$102))))) | G8: =IF(F8="","",B8*(1-F8))
F9: =IF(E9="","",IF(E9="NO",0%,IF(('OFFICE USE'!$H$1-C9)/D9>1,0.8,(LOOKUP(('OFFICE USE'!$H$1-C9)/D9,'OFFICE USE'!$C$2:$D$102))))) | G9: =IF(F9="","",B9*(1-F9))
F10: =IF(E10="","",IF(E10="NO",0%,IF(('OFFICE USE'!$H$1-C10)/D10>1,0.8,(LOOKUP(('OFFICE USE'!$H$1-C10)/D10,'OFFICE USE'!$C$2:$D$102))))) | G10: =IF(F10="","",B10*(1-F10))
F11: =IF(E11="","",IF(E11="NO",0%,IF(('OFFICE USE'!$H$1-C11)/D11>1,0.8,(LOOKUP(('OFFICE USE'!$H$1-C11)/D11,'OFFICE USE'!$C$2:$D$102))))) | G11: =IF(F11="","",B11*(1-F11))
F12: =IF(E12="","",IF(E12="NO",0%,IF(('OFFICE USE'!$H$1-C12)/D12>1,0.8,(LOOKUP(('OFFICE USE'!$H$1-C12)/D12,'OFFICE USE'!$C$2:$D$102))))) | G12: =IF(F12="","",B12*(1-F12))
F13: =IF(E13="","",IF(E13="NO",0%,IF(('OFFICE USE'!$H$1-C13)/D13>1,0.8,(LOOKUP(('OFFICE USE'!$H$1-C13)/D13,'OFFICE USE'!$C$2:$D$102))))) | G13: =IF(F13="","",B13*(1-F13))
F14: =IF(E14="","",IF(E14="NO",0%,IF(('OFFICE USE'!$H$1-C14)/D14>1,0.8,(LOOKUP(('OFFICE USE'!$H$1-C14)/D14,'OFFICE USE'!$C$2:$D$102))))) | G14: =IF(F14="","",B14*(1-F14))
... F50: =IF(E50="","",IF(E50="NO",0%,IF(('OFFICE USE'!$H$1-C50)/D50>1,0.8,(LOOKUP(('OFFICE USE'!$H$1-C50)/D50,'OFFICE USE'!$C$2:$D$102))))) | G50: =IF(F50="","",B50*(1-F50))

Sheet MACHINERY & EQUIPMENT (Pg. 6)
B1: MACHINERY & EQUIPMENT
A2: ITEM DESCRIPTION | B2: ACQUISTION COST | C2: YEAR ACQUIRED | D2: ECONOMIC LIFE | E2: DEPRECIATION | F2: MARKET VALUE | H2: OFFICE USE ONLY
E3: =IF(D3="","",IF(('OFFICE USE'!$H$1-C3)/D3>1,0.8,LOOKUP(('OFFICE USE'!$H$1-C3)/D3,'OFFICE USE'!$C$2:$D$102))) | F3: =IF(C3>0,B3*(1-E3),"")
E4: =IF(D4="","",IF(('OFFICE USE'!$H$1-C4)/D4>1,0.8,LOOKUP(('OFFICE USE'!$H$1-C4)/D4,'OFFICE USE'!$C$2:$D$102))) | F4: =IF(C4>0,B4*(1-E4),"")
E5: =IF(D5="","",IF(('OFFICE USE'!$H$1-C5)/D5>1,0.8,LOOKUP(('OFFICE USE'!$H$1-C5)/D5,'OFFICE USE'!$C$2:$D$102))) | F5: =IF(C5>0,B5*(1-E5),"")
E6: =IF(D6="","",IF(('OFFICE USE'!$H$1-C6)/D6>1,0.8,LOOKUP(('OFFICE USE'!$H$1-C6)/D6,'OFFICE USE'!$C$2:$D$102))) | F6: =IF(C6>0,B6*(1-E6),"")
E7: =IF(D7="","",IF(('OFFICE USE'!$H$1-C7)/D7>1,0.8,LOOKUP(('OFFICE USE'!$H$1-C7)/D7,'OFFICE USE'!$C$2:$D$102))) | F7: =IF(C7>0,B7*(1-E7),"")
E8: =IF(D8="","",IF(('OFFICE USE'!$H$1-C8)/D8>1,0.8,LOOKUP(('OFFICE USE'!$H$1-C8)/D8,'OFFICE USE'!$C$2:$D$102))) | F8: =IF(C8>0,B8*(1-E8),"")
E9: =IF(D9="","",IF(('OFFICE USE'!$H$1-C9)/D9>1,0.8,LOOKUP(('OFFICE USE'!$H$1-C9)/D9,'OFFICE USE'!$C$2:$D$102))) | F9: =IF(C9>0,B9*(1-E9),"")
E10: =IF(D10="","",IF(('OFFICE USE'!$H$1-C10)/D10>1,0.8,LOOKUP(('OFFICE USE'!$H$1-C10)/D10,'OFFICE USE'!$C$2:$D$102))) | F10: =IF(C10>0,B10*(1-E10),"")
E11: =IF(D11="","",IF(('OFFICE USE'!$H$1-C11)/D11>1,0.8,LOOKUP(('OFFICE USE'!$H$1-C11)/D11,'OFFICE USE'!$C$2:$D$102))) | F11: =IF(C11>0,B11*(1-E11),"")
E12: =IF(D12="","",IF(('OFFICE USE'!$H$1-C12)/D12>1,0.8,LOOKUP(('OFFICE USE'!$H$1-C12)/D12,'OFFICE USE'!$C$2:$D$102))) | F12: =IF(C12>0,B12*(1-E12),"")
E13: =IF(D13="","",IF(('OFFICE USE'!$H$1-C13)/D13>1,0.8,LOOKUP(('OFFICE USE'!$H$1-C13)/D13,'OFFICE USE'!$C$2:$D$102))) | F13: =IF(C13>0,B13*(1-E13),"")
E14: =IF(D14="","",IF(('OFFICE USE'!$H$1-C14)/D14>1,0.8,LOOKUP(('OFFICE USE'!$H$1-C14)/D14,'OFFICE USE'!$C$2:$D$102))) | F14: =IF(C14>0,B14*(1-E14),"")
... E50: =IF(D50="","",IF(('OFFICE USE'!$H$1-C50)/D50>1,0.8,LOOKUP(('OFFICE USE'!$H$1-C50)/D50,'OFFICE USE'!$C$2:$D$102))) | F50: =IF(C50>0,B50*(1-E50),"")
E51: =IF(C51>0,LOOKUP(#REF!-C51,#REF!),"") | F51: =IF(C51>0,B51*(1-E51),"")
E52: =IF(C52>0,LOOKUP(#REF!-C52,#REF!),"") | F52: =IF(C52>0,B52*(1-E52),"")
E53: =IF(C53>0,LOOKUP(#REF!-C53,#REF!),"") | F53: =IF(C53>0,B53*(1-E53),"")
E54: =IF(C54>0,LOOKUP(#REF!-C54,#REF!),"") | F54: =IF(C54>0,B54*(1-E54),"")
E55: =IF(C55>0,LOOKUP(#REF!-C55,#REF!),"") | F55: =IF(C55>0,B55*(1-E55),"")
E56: =IF(C56>0,LOOKUP(#REF!-C56,#REF!),"") | F56: =IF(C56>0,B56*(1-E56),"")
E57: =IF(C57>0,LOOKUP(#REF!-C57,#REF!),"") | F57: =IF(C57>0,B57*(1-E57),"")
E58: =IF(C58>0,LOOKUP(#REF!-C58,#REF!),"") | F58: =IF(C58>0,B58*(1-E58),"")
E59: =IF(C59>0,LOOKUP(#REF!-C59,#REF!),"") | F59: =IF(C59>0,B59*(1-E59),"")
E60: =IF(C60>0,LOOKUP(#REF!-C60,#REF!),"") | F60: =IF(C60>0,B60*(1-E60),"")
E61: =IF(C61>0,LOOKUP(#REF!-C61,#REF!),"") | F61: =IF(C61>0,B61*(1-E61),"")
E62: =IF(C62>0,LOOKUP(#REF!-C62,#REF!),"") | F62: =IF(C62>0,B62*(1-E62),"")
... E101: =IF(C101>0,LOOKUP(#REF!-C101,#REF!),"") | F101: =IF(C101>0,B101*(1-E101),"")

Sheet LEASED OR SOLD ASSETS (Pg. 7)
B1: LEASED AND SOLD ASSETS
A2: LEASED / SOLD ITEM DESCRIPTION | B2: LEASE (L) SOLD (S) | C2: LESSOR / BUYER | D2: ADDRESS | F2: OFFICE USE ONLY

Sheet AIRCRAFT (Pg. 8)
A1: AIRCRAFT AND HELICOPTERS
A2: MANUFACTURER | B2: MODEL | C2: TAIL NUMBER | D2: YEAR BUILT | E2: MARKET VALUE | G2: OFFICE USE ONLY

Sheet OFFICE USE
A1: AGE | B1: ECON LIFE | C1: % USED | D1: DEPR | G1: TAX YEAR | H1: 2015
A2: 0 | B2: 100 | C2: =A2/B2 -> 0 | D2: =($H$2*(C2^3)+($H$3*(C2^2)+($H$4*(C2)))) -> 0 | G2: CUBE | H2: 1.0204
A3: 1 | B3: 100 | C3: =A3/B3 -> 0.01 | D3: =($H$2*(C3^3)+($H$3*(C3^2)+($H$4*(C3)))) -> 0.02186478 | G3: SQUARE | H3: -2.4324
A4: 2 | B4: 100 | C4: =A4/B4 -> 0.02 | D4: =($H$2*(C4^3)+($H$3*(C4^2)+($H$4*(C4)))) -> 0.043249203 | G4: SINGLE | H4: 2.2107
A5: 3 | B5: 100 | C5: =A5/B5 -> 0.03 | D5: =($H$2*(C5^3)+($H$3*(C5^2)+($H$4*(C5)))) -> 0.064159391
A6: 4 | B6: 100 | C6: =A6/B6 -> 0.04 | D6: =($H$2*(C6^3)+($H$3*(C6^2)+($H$4*(C6)))) -> 0.084601466
A7: 5 | B7: 100 | C7: =A7/B7 -> 0.05 | D7: =($H$2*(C7^3)+($H$3*(C7^2)+($H$4*(C7)))) -> 0.10458155
A8: 6 | B8: 100 | C8: =A8/B8 -> 0.06 | D8: =($H$2*(C8^3)+($H$3*(C8^2)+($H$4*(C8)))) -> 0.12410577
A9: 7 | B9: 100 | C9: =A9/B9 -> 0.07 | D9: =($H$2*(C9^3)+($H$3*(C9^2)+($H$4*(C9)))) -> 0.14318024
A10: 8 | B10: 100 | C10: =A10/B10 -> 0.08 | D10: =($H$2*(C10^3)+($H$3*(C10^2)+($H$4*(C10)))) -> 0.16181108
A11: 9 | B11: 100 | C11: =A11/B11 -> 0.09 | D11: =($H$2*(C11^3)+($H$3*(C11^2)+($H$4*(C11)))) -> 0.18000443
A12: 10 | B12: 100 | C12: =A12/B12 -> 0.1 | D12: =($H$2*(C12^3)+($H$3*(C12^2)+($H$4*(C12)))) -> 0.1977664
A13: 11 | B13: 100 | C13: =A13/B13 -> 0.11 | D13: =($H$2*(C13^3)+($H$3*(C13^2)+($H$4*(C13)))) -> 0.21510311
A14: 12 | B14: 100 | C14: =A14/B14 -> 0.12 | D14: =($H$2*(C14^3)+($H$3*(C14^2)+($H$4*(C14)))) -> 0.23202069
A15: 13 | B15: 100 | C15: =A15/B15 -> 0.13 | D15: =($H$2*(C15^3)+($H$3*(C15^2)+($H$4*(C15)))) -> 0.24852526
A16: 14 | B16: 100 | C16: =A16/B16 -> 0.14 | D16: =($H$2*(C16^3)+($H$3*(C16^2)+($H$4*(C16)))) -> 0.26462294
... A102: 100 | B102: 100 | C102: =A102/B102 -> 1 | D102: =($H$2*(C102^3)+($H$3*(C102^2)+($H$4*(C102)))) -> 0.7987
