Workbook
Name Budget: '[1]List Data'!$A$1:$A$2
Name budget: [2]Other!$A$1:$A$4
Name budget: Other!$A$1:$A$2
Name Budget_Object: '3-Budget Detail'!$A$6:$A$500
Name capitalized: Other!$D$17:$D$18
Name coverpage: '[3]2-Cover Page'!$C$4
Name detailcode: '[4]Calculation Detail'!$E$6:$E$500
Name detailcode: #REF!
Name detailcost: '[4]Calculation Detail'!$C$6:$C$500
Name detailcost: #REF!
Name equipmentcost: #REF!
Name fundingyear: #REF!
Name Look1: #REF!
Name Look1: '[5]7-Rate Table'!$A$2:$D$67
Name Objects: '[1]List Data'!$C$1:$C$8
Name objects: [2]Other!$D$1:$D$12
Name objects: Other!$D$1:$D$14
Name Program: '[1]List Data'!$C$11:$C$12
Name Programs: #REF!
Name Projects: [2]Other!$A$5:$A$14
Name Projects: Other!$A$5:$A$9
Name years: [3]Other!$A$5
Name years: [5]Other!$A$5:$A$7

Sheet 1-Instructions

Sheet 2-Cover Page
A1: COLORADO GRADUATION PATHWAYS
A2: JULY 1, 2014 THROUGH JUNE 30, 2015
B3: CFDA: 84.360A | D3: GRANT CODE: 5360
B5: Name of School/s:
B6: Disctrict Code
B7: District Name: | C7: =VLOOKUP(C6,'Indirect Rates'!B3:E202,3) -> #N/A
B9: Budget Report:
B10: Revision number:
B11: Date:
B13: Name of person completing the budget
B15: Name:
B16: Phone No.:
B17: E-mail:
B19: Submit Excel File To: | C19: rodriguez_m@cde.state.co.us AND perea_d@cde.state.co.us
B20: CDE Contact:
B21: Grants Fiscal Contact | C21: Marti Rodriguez 303-866-6739
B22: Program Contact | C22: Dawn Perea 303-866-6142

Sheet 3-Budget Detail
A1: ='2-Cover Page'!A1:G1 -> COLORADO GRADUATION PATHWAYS
A2: BUDGET DETAIL
A3: ='2-Cover Page'!C5 | E3: ='2-Cover Page'!C11 -> 0
A4: 1 | C4: 2 | D4: 3 | E4: 4
A5: Program/Object | B5: Schools | C5: Cost | D5: Description/Budget Narrative | E5: Expected Date of Completion

Sheet 4-Equipment
A1: ='3-Budget Detail'!A1:E1 -> COLORADO GRADUATION PATHWAYS
A2: EQUIPMENT REQUEST AND INVENTORY
A3: ='2-Cover Page'!C5 | G3: ='2-Cover Page'!C11 -> 0
A4: 1 | B4: 2 | C4: 2 | D4: 3 | E4: 4 | F4: 5 | G4: 6
A5: Description of item | B5: Serial Number | C5: Date Acquired | D5: Actual Cost | E5: Capitalized | F5: Describe Use of Equipment | G5: Expected Date of Completion

Sheet 5-Budget Summary
A1: ='4-Equipment'!A1:G1 -> COLORADO GRADUATION PATHWAYS
A2: BUDGET SUMMARY
A3: FY2014-15
A4: ='2-Cover Page'!C5 | C4: ='2-Cover Page'!C11 -> 0
A5: FY2014-2015 Allocation:
A6: Anticipated Carryover as of June 30, 2014
A7: Carryover is limited to 15%. Districts are allowed to identify CGP expenditures from July 1, 2014 through September 30, 2014 to be in compliance with the 15% restriction. Provide information on the 10 Revision-Comment Sheet if your carryover exceeds 15% on this line.
A8: Total Funds Available | C8: =SUM(C5:C6) -> 0
A9: INSTRUCTIONAL PROGRAM
B10: Salaries (0100) | C10: {=SUM(IF(LEFT(Budget_Object,3)&RIGHT(Budget_Object,5)="Ins0100)",'3-Budget Detail'!$C$6:$C$500))} -> 0
B11: Employee Benefits (0200) | C11: {=SUM(IF(LEFT(Budget_Object,3)&RIGHT(Budget_Object,5)="Ins0200)",'3-Budget Detail'!$C$6:$C$500))} -> 0
B12: Purchased Professional & Technical Services (0300) | C12: {=SUM(IF(LEFT(Budget_Object,3)&RIGHT(Budget_Object,5)="Ins0300)",'3-Budget Detail'!$C$6:$C$500))} -> 0
B13: Other Purchased Services (0500) | C13: {=SUM(IF(LEFT(Budget_Object,3)&RIGHT(Budget_Object,5)="Ins0500)",'3-Budget Detail'!$C$6:$C$500))} -> 0
B14: Travel, Registration, and Entrance (0580) | C14: {=SUM(IF(LEFT(Budget_Object,3)&RIGHT(Budget_Object,5)="Ins0580)",'3-Budget Detail'!$C$6:$C$500))} -> 0
B15: Supplies (0600) | C15: {=SUM(IF(LEFT(Budget_Object,3)&RIGHT(Budget_Object,5)="Ins0600)",'3-Budget Detail'!$C$6:$C$500))} -> 0
B16: Other (0800) | C16: {=SUM(IF(LEFT(Budget_Object,3)&RIGHT(Budget_Object,5)="Ins0800)",'3-Budget Detail'!$C$6:$C$500))} -> 0
B17: Subtotal-Instructional Program | C17: =SUM(C10:C16) -> 0
A19: SUPPORT PROGRAM
B20: Salaries (0100) | C20: {=SUM(IF(LEFT(Budget_Object,3)&RIGHT(Budget_Object,5)="Sup0100)",'3-Budget Detail'!$C$6:$C$500))} -> 0
B21: Employee Benefits (0200) | C21: {=SUM(IF(LEFT(Budget_Object,3)&RIGHT(Budget_Object,5)="Sup0200)",'3-Budget Detail'!$C$6:$C$500))} -> 0
B22: Purchased Professional & Technical Services (0300) | C22: {=SUM(IF(LEFT(Budget_Object,3)&RIGHT(Budget_Object,5)="Sup0300)",'3-Budget Detail'!$C$6:$C$500))} -> 0
B23: Other Purchased Services (0500) | C23: {=SUM(IF(LEFT(Budget_Object,3)&RIGHT(Budget_Object,5)="Sup0500)",'3-Budget Detail'!$C$6:$C$500))} -> 0
B24: Travel, Registration, and Entrance (0580) | C24: {=SUM(IF(LEFT(Budget_Object,3)&RIGHT(Budget_Object,5)="Sup0580)",'3-Budget Detail'!$C$6:$C$500))} -> 0
B25: Supplies (0600) | C25: {=SUM(IF(LEFT(Budget_Object,3)&RIGHT(Budget_Object,5)="Sup0600)",'3-Budget Detail'!$C$6:$C$500))} -> 0
B26: Other (0800) | C26: {=SUM(IF(LEFT(Budget_Object,3)&RIGHT(Budget_Object,5)="Sup0800)",'3-Budget Detail'!$C$6:$C$500))} -> 0
B27: Subtotal- Support Program | C27: =SUM(C20:C26) -> 0
B28: Total - Instructional and Support Programs | C28: =+C27+C17 -> 0
B29: Indirect Cost Rate
B30: Indirect Costs | C30: =(C28+C32)*C29 -> 0
B31: Indirect Cost Override
B32: Non-Capitalized Equipment (0735) | C32: =SUMIF('4-Equipment'!$E$6:$E$150,"non-capitalized",'4-Equipment'!$D$6:$D$150) -> 0
B33: Capitalized Equipment (0730) | C33: =SUMIF('4-Equipment'!$E$6:$E$150,"capitalized",'4-Equipment'!$D$6:$D$150) -> 0
B34: Grand Total - Lines 15, 17 or 18, 19 | C34: =IF(ISBLANK(C31)=TRUE,C28+C30+C32,C28+C31+C32+C33) -> 0

Sheet 6- AFR Detail
A1: ='5-Budget Summary'!A1:C1 -> COLORADO GRADUATION PATHWAYS
A2: ANNUAL FINANCIAL REPORT DETAIL
A3: ='2-Cover Page'!C5 | D3: ='2-Cover Page'!C11 -> 0
A4: 1 | B4: 2 | C4: 3 | D4: 4
A5: Program/Budget | B5: Cost | C5: Description/Budget Narrative | D5: Expected Date of Completion

Sheet 7-AFR Equipment Detail
A1: ='6- AFR Detail'!A1:D1 -> COLORADO GRADUATION PATHWAYS
A2: ANNUAL FINANCIAL REPORT EQUIPMENT DETAIL
A3: ='2-Cover Page'!C5 | F3: ='2-Cover Page'!C11 -> 0
A4: 1 | B4: 2 | C4: 2 | D4: 3 | E4: 4 | F4: 5
A5: Description of item | B5: Serial Number | C5: Date Purchased | D5: Actual Cost | E5: Capitalized | F5: Describe Use of Equipment

Sheet 8-Annual Financial Report
A1: ='7-AFR Equipment Detail'!A1:F1 -> COLORADO GRADUATION PATHWAYS
A2: Annual Financial Report
A3: FY 14-15
A5: District: | C5: =+'2-Cover Page'!C7:D7 -> #N/A
A6: School: | C6: ='2-Cover Page'!C5:D5
C7: Due September 1, 2015
D10: FY 14-15
C11: PROGRAM CATEGORIES | D11: Budget | E11: Actual Expenditures
B12: Instructional Program
B13: 1 | C13: Salaries (0100) | D13: =+'5-Budget Summary'!C10 -> 0 | E13: =SUMIF('6- AFR Detail'!$A$6:$A$500,"Inst. - Salaries (0100)",'6- AFR Detail'!$B$6:$B$500) -> 0
B14: 2 | C14: Employee Benefits (0200) | D14: =+'5-Budget Summary'!C11 -> 0 | E14: =SUMIF('6- AFR Detail'!$A$6:$A$500,"Inst. - Employee Benefits (0200)",'6- AFR Detail'!$B$6:$B$500) -> 0
B15: 3 | C15: Purchased Professional & Technical Services (0300) | D15: =+'5-Budget Summary'!C12 -> 0 | E15: =SUMIF('6- AFR Detail'!$A$6:$A$500,"Inst. - Purchased Professional & Technical Services (0300)",'6- AFR Detail'!$B$6:$B$500) -> 0
B16: 4 | C16: Other Purchased Services (0500) | D16: =+'5-Budget Summary'!C13 -> 0 | E16: =SUMIF('6- AFR Detail'!$A$6:$A$500,"Inst. - Other Purchased Services (0500)",'6- AFR Detail'!$B$6:$B$500) -> 0
B17: 5 | C17: Travel, Registration, and Entrance (0580) | D17: =+'5-Budget Summary'!C14 -> 0 | E17: =SUMIF('6- AFR Detail'!$A$6:$A$500,"Inst. - Travel, Registration and Entrance (0580)",'6- AFR Detail'!$B$6:$B$500) -> 0
B18: 6 | C18: Supplies (0600) | D18: =+'5-Budget Summary'!C15 -> 0 | E18: =SUMIF('6- AFR Detail'!$A$6:$A$500,"Inst. - Supplies (0600)",'6- AFR Detail'!$B$6:$B$500) -> 0
B19: 7 | C19: Other (0800) | D19: =+'5-Budget Summary'!C16 -> 0 | E19: =SUMIF('6- AFR Detail'!$A$6:$A$500,"Inst. - Other (0800)",'6- AFR Detail'!$B$6:$B$500) -> 0
B20: 8 | C20: Subtotal Instructional Program (lines 1 through 6) | D20: =SUM(D13:D19) -> 0 | E20: =SUM(E13:E19) -> 0
B21: Support Program
B22: 9 | C22: Salaries (0100) | D22: =+'5-Budget Summary'!C20 -> 0 | E22: =SUMIF('6- AFR Detail'!$A$6:$A$500,"Support - Salaries (0100)",'6- AFR Detail'!$B$6:$B$500) -> 0
B23: 10 | C23: Employee Benefits (0200) | D23: =+'5-Budget Summary'!C21 -> 0 | E23: =SUMIF('6- AFR Detail'!$A$6:$A$500,"Support - Employee Benefits (0200)",'6- AFR Detail'!$B$6:$B$500) -> 0
B24: 11 | C24: Purchased Professional & Technical Services (0300) | D24: =+'5-Budget Summary'!C22 -> 0 | E24: =SUMIF('6- AFR Detail'!$A$6:$A$500,"Support - Purchased Professional & Technical Services (0300)",'6- AFR Detail'!$B$6:$B$500) -> 0
B25: 12 | C25: Other Purchased Services (0500) | D25: =+'5-Budget Summary'!C23 -> 0 | E25: =SUMIF('6- AFR Detail'!$A$6:$A$500,"Support - Other Purchased Services (0500)",'6- AFR Detail'!$B$6:$B$500) -> 0
B26: 13 | C26: Travel, Registration, and Entrance (0580) | D26: =+'5-Budget Summary'!C24 -> 0 | E26: =SUMIF('6- AFR Detail'!$A$6:$A$500,"Support - Travel, Registration and Entrance (0580)",'6- AFR Detail'!$B$6:$B$500) -> 0
B27: 14 | C27: Supplies (0600) | D27: =+'5-Budget Summary'!C25 -> 0 | E27: =SUMIF('6- AFR Detail'!$A$6:$A$500,"Support - Supplies (0600)",'6- AFR Detail'!$B$6:$B$500) -> 0
B28: 15 | C28: Other (0800) | D28: =+'5-Budget Summary'!C26 -> 0 | E28: =SUMIF('6- AFR Detail'!$A$6:$A$500,"Support - Other (0800)",'6- AFR Detail'!$B$6:$B$500) -> 0
B29: 16 | C29: Subtotal Support Program (lines 8 through 15) | D29: =SUM(D22:D28) -> 0 | E29: =SUM(E22:E28) -> 0
B30: 17 | C30: Indirect Costs | D30: =IF(ISBLANK('5-Budget Summary'!C31)=TRUE,'5-Budget Summary'!C30,'5-Budget Summary'!C31) -> 0
B31: 18 | C31: Non-Capitalized Equipment (0735) | D31: =+'5-Budget Summary'!C32 -> 0 | E31: =+SUMIF('7-AFR Equipment Detail'!$E$6:$E$150,"non-capitalized",'7-AFR Equipment Detail'!$D$6:$D$150) -> 0
B32: 19 | C32: Capitalized Equipment (0730) | D32: =+'5-Budget Summary'!C33 -> 0 | E32: =+SUMIF('7-AFR Equipment Detail'!$E$6:$E$150,"capitalized",'7-AFR Equipment Detail'!$D$6:$D$150) -> 0
B33: 20 | C33: Total Budget (lines 7 and 16) | D33: =D29+D20+D30+D31 -> 0 | E33: =E29+E20+E30+E31 -> 0
C40: Typed Name of Person Preparing Report Date | F40: Signature of School District Authorized Representative*
C42: *Check with your school district budget office for the signature of the school district authorized representative.

Sheet 9-Error Checking
B2: ='2-Cover Page'!C5
C4: Error Checking
F5: ='2-Cover Page'!C11 -> 0
C9: Detail Sheets | D9: 5-Budget Summary
B10: 3-Budget Detail | C10: =+SUM('3-Budget Detail'!C6:C500) -> 0 | D10: =+'5-Budget Summary'!C17+'5-Budget Summary'!C27 -> 0 | E10: =IF(C10=D10,"equal","not equal!") -> equal
B11: 4-Equipment | C11: =SUM('4-Equipment'!D6:D150) -> 0 | D11: =+'5-Budget Summary'!C32+'5-Budget Summary'!C33 -> 0 | E11: =IF(C11=D11,"equal","not equal!") -> equal
B12: Total | C12: =SUM(C10:C11) -> 0 | D12: =SUM(D10:D11) -> 0 | E12: =IF(C12=D12,"equal","not equal!") -> equal
B15: If the subtotals do not equal each other, the most likely problem is on the
B16: detail sheet. All required entries may not have been entered.

Sheet 10-Revisions-Comments
A1: ='2-Cover Page'!C5 | C1: ='2-Cover Page'!C11 -> 0
A3: Use this sheet to report any revisions to the original Budget submitted
A5: This page must be completed when submitting a revised budget. Start with the original electronic budget submitted and make corrections on the “3-Budget Detail” and the “4-Equipment” pages as appropriate. On this page, describe in detail the changes/revisions, the reason for the revisions, etc. Don’t forget to make the appropriate changes on the “2-Cover Page”. It is important that you mark revision in the budget report box; mark the revision number, and also enter the revision date.
A6: Date | B6: Comment | C6: Initials

Sheet Indirect Rates
A1: Indirect Cost Rates for Use in FY2010-2011
B2: District Code | C2: County | D2: District Name | E2: Restricted Rate | F2: Unrestricted Rate
A3: 20102011 | B3: 10 | C3: Adams | D3: Mapleton Public Schools | E3: 0.0612 | F3: 0.2002
A4: 20102011 | B4: 20 | C4: Adams | D4: Adams 12 Five Star Schools | E4: 0.0556 | F4: 0.167
A5: 20102011 | B5: 30 | C5: Adams | D5: Adams County 14 | E5: 0.0446 | F5: 0.1694
A6: 20102011 | B6: 40 | C6: Adams | D6: Brighton 27J | E6: 0.0373 | F6: 0.2149
A7: 20102011 | B7: 50 | C7: Adams | D7: Bennett 29J | E7: 0.0808 | F7: 0.2683
A8: 20102011 | B8: 60 | C8: Adams | D8: Strasburg 31J | E8: 0.0304 | F8: 0.3193
A9: 20102011 | B9: 70 | C9: Adams | D9: Westminster 50 | E9: 0.0842 | F9: 0.2387
A10: 20102011 | B10: 100 | C10: Alamosa | D10: Alamosa RE 11J | E10: 0.0577 | F10: 0.2226
A11: 20102011 | B11: 110 | C11: Alamosa | D11: Sangre De Cristo RE-22J | E11: 0.0242 | F11: 0.2631
A12: 20102011 | B12: 120 | C12: Arapahoe | D12: Englewood 1 | E12: 0.0552 | F12: 0.1909
A13: 20102011 | B13: 123 | C13: Arapahoe | D13: Sheridan 2 | E13: 0.093 | F13: 0.2305
A14: 20102011 | B14: 130 | C14: Arapahoe | D14: Cherry Creek 5 | E14: 0.0469 | F14: 0.1469
... A202: 20102011 | B202: 9165 | C202: BOCES | D202: Ute Pass BOCES | E202: 0 | F202: 0

Sheet Other
A1: Original Budget | D1: Inst. - Salaries (0100)
A2: Revised Budget | D2: Inst. - Employee Benefits (0200)
D3: Inst. - Purchased Professional & Technical Services (0300)
D4: Inst. - Other Purchased Services (0500)
A5: Project 1 | D5: Inst. - Travel, Registration and Entrance (0580)
A6: Project 2 | D6: Inst. - Supplies (0600)
A7: Project 3 | D7: Inst. - Other (0800)
A8: Project 4 | D8: Support - Salaries (0100)
A9: Project 5 | D9: Support - Employee Benefits (0200)
A10: Project 1-Year 2 | D10: Support - Purchased Professional & Technical Services (0300)
A11: Project 2-Year 2 | D11: Support - Other Purchased Services (0500)
A12: Project 3-Year 2 | D12: Support - Travel, Registration and Entrance (0580)
A13: Project 4-Year 2 | D13: Support - Supplies (0600)
A14: Project 5-Year 2 | D14: Support - Other (0800)
A15: Project 1-Year 3
A16: Project 2-Year 3
A17: Project 3-Year 3 | D17: Capitalized
A18: Project 4-Year 3 | D18: Non-Capitalized
A19: Project 5-Year 3
A20: Project 1-Year 4
A21: Project 2-Year 4
A22: Project 3-Year 4
A23: Project 4-Year 4
A24: Project 5-Year 4
A25: Project 1-Year 5
A26: Project 2-Year 5
A27: Project 3-Year 5
A28: Project 4-Year 5
A29: Project 5-Year 5
