Workbook

Sheet Contents
A1: Present Worth Workbook Contents
A3: Input | C3: 2Replace Costs Results 11-15 | E3: 4Capital Costs | G3: 5Replace Costs Results 16-20
A4: Capital Costs | C4: 2Replace Costs Results 16-20 | E4: 4Replacement Costs - Entry | G4: 5Yearly O&M 1-10
A5: Replacement Costs - Entry | C5: 2Yearly O&M Costs 1-10 | E5: 4Replace Costs Results 1-5 | G5: 5Yearly O&M 11-20
A6: Replace Costs Results 1-5 | C6: 2Yearly O&M Costs 11-20 | E6: 4Replace Costs Results 6-10 | G6: 5Inter O&M Entry
A7: Replace Costs Results 6-10 | C7: 2Inter O&M Entry | E7: 4Replace Costs Results 11-15 | G7: 5Inter O&M 1-10
A8: Replace Costs Results 11-15 | C8: 2Inter O&M 1-10 | E8: 4Replace Costs Results 16-20 | G8: 5Inter O&M 11-20
A9: Replace Costs Results16-20 | C9: 2Inter O&M 11-20 | E9: 4Yearly O&M Costs 1-10 | G9: 6Capital Costs
A10: Yearly O&M Costs 1-10 | C10: 3Capital Costs | E10: 4Yearly O&M Costs 11-20 | G10: 6Replacement Costs - Entry
A11: Yearly O&M Costs 11-20 | C11: 3Replacement Costs - Entry | E11: 4Inter O&M Entry | G11: 6Replace Costs Results 1-5
A12: Inter O&M Entry | C12: 3Replace Costs Results 1-5 | E12: 4Inter O&M 1-10 | G12: 6Replace Costs Results 6-10
A13: Inter O&M 1-10 | C13: 3Replace Costs Results 6-10 | E13: 4Inter O&M 11-20 | G13: 6Replace Costs Results 11-15
A14: Inter O&M 11-20 | C14: 3Replace Costs Results 11-15 | E14: 5Capital Costs | G14: 6Replace Costs Results 16-20
... A18: 2Replace Costs Results 6-10 | C18: 3Inter O&M Entry | E18: 5Replace Costs Results 11-15 | G18: 6Inter O&M 1-10
C19: 3Inter O&M 1-10 | G19: 6Inter O&M 11-20
C20: 3Inter O&M 11-20 | G20: Total Present Worth

Sheet Input
A2: Enter information into the gray areas. For the Preferred Alternative, place the word Preferred in parentheses after the alternative name.
A4: Project Name:
A5: LGU Name:
A6: Alternative 1 Name:
A7: Alternative 2 Name:
A8: Alternative 3 Name:
A9: Alternative 4 Name:
A10: Alternative 5 Name:
A11: Alternative 6 Name:

Sheet Capital Costs
A2: Table 5.2.1. Capital Costs
A3: =Input!B4 -> 0
A4: =Input!B5 -> 0
A5: Complete the areas shown in gray below. Where shown, use pulldown menu to select options. The spreadsheet will calculate the capital costs.
A7: Project Administration ($):
A8: Component | B8: Unit Costa | C8: Unit | D8: Quantity | E8: Total Cost
E9: =B9*D9 -> 0
E10: =B10*D10 -> 0
E11: =B11*D11 -> 0
E12: =B12*D12 -> 0
E13: =B13*D13 -> 0
E14: =B14*D14 -> 0
E15: =B15*D15 -> 0
E16: =B16*D16 -> 0
E17: =B17*D17 -> 0
E18: =B18*D18 -> 0
E19: =B19*D19 -> 0
E20: =B20*D20 -> 0
... E37: =B37*D37 -> 0
A38: aUnit costs are in today's dollars, not future dollars. | D38: Total Construction Cost: | E38: =SUM(E9:E37) -> 0
D39: Construction Contingency Cost: | E39: =E38*$B$42 -> 0
D40: Project Administration Cost: | E40: =$B$7 -> 0
D41: Total Capital Cost: | E41: =SUM(E38:E40) -> 0
A42: Construction Contingency | B42: 0.1

Sheet Replacement Costs - Entry
A1: Replacement Costs Input
A3: Alternative: | B3: ='Capital Costs'!B6 -> 0
A5: For each component, enter "Y" in the gray area in the year in which replacement, if any, will occur.
J7: Year Replacement Needed? (Insert Y in year where replacement is needed.)
A8: Component | B8: Unit Cost | C8: Unit | D8: Quantity | E8: Replacement Needed? (Years 1-5) | F8: Replacement Needed? (Years 6-10) | G8: Replacement Needed (Years 11-15) | H8: Replacement Needed? (Years 16-20) | I8: Replacement Needed? (Years 1-20) | J8: 1 | K8: 2 | L8: 3 | M8: 4 | N8: 5 | O8: 6 | P8: 7 | Q8: 8 | R8: 9 | S8: 10 | T8: 11 | U8: 12 | V8: 13 | W8: 14 | X8: 15 | Y8: 16 | Z8: 17 | AA8: 18 | AB8: 19 | AC8: 20
A9: =IF('Capital Costs'!A9<>"", 'Capital Costs'!A9, "") | B9: =IF('Capital Costs'!B9<>"", 'Capital Costs'!B9, "") | C9: =IF('Capital Costs'!C9<>"", 'Capital Costs'!C9, "") | D9: =IF('Capital Costs'!D9<>"", 'Capital Costs'!D9, "") | E9: =IF(N9="Y", "Y", (IF(M9="Y", "Y", (IF(L9="Y", "Y", (IF(K9="Y", "Y", (IF(J9="Y", "Y", " "))))))))) | F9: =IF(S9="Y", "Y", (IF(R9="Y", "Y", (IF(Q9="Y", "Y", (IF(P9="Y", "Y", (IF(O9="Y", "Y", " "))))))))) | G9: =IF(X9="Y", "Y", (IF(W9="Y", "Y", (IF(V9="Y", "Y", (IF(U9="Y", "Y", (IF(T9="Y", "Y", " "))))))))) | H9: =IF(AC9="Y", "Y", (IF(AB9="Y", "Y", (IF(AA9="Y", "Y", (IF(Z9="Y", "Y", (IF(Y9="Y", "Y", " "))))))))) | I9: =IF(H9="Y", "Y", (IF(G9="Y", "Y", (IF(F9="Y", "Y", (IF(E9="Y", "Y", " ")))))))
A10: =IF('Capital Costs'!A10<>"", 'Capital Costs'!A10, "") | B10: =IF('Capital Costs'!B10<>"", 'Capital Costs'!B10, "") | C10: =IF('Capital Costs'!C10<>"", 'Capital Costs'!C10, "") | D10: =IF('Capital Costs'!D10<>"", 'Capital Costs'!D10, "") | E10: =IF(N10="Y", "Y", (IF(M10="Y", "Y", (IF(L10="Y", "Y", (IF(K10="Y", "Y", (IF(J10="Y", "Y", " "))))))))) | F10: =IF(S10="Y", "Y", (IF(R10="Y", "Y", (IF(Q10="Y", "Y", (IF(P10="Y", "Y", (IF(O10="Y", "Y", " "))))))))) | G10: =IF(X10="Y", "Y", (IF(W10="Y", "Y", (IF(V10="Y", "Y", (IF(U10="Y", "Y", (IF(T10="Y", "Y", " "))))))))) | H10: =IF(AC10="Y", "Y", (IF(AB10="Y", "Y", (IF(AA10="Y", "Y", (IF(Z10="Y", "Y", (IF(Y10="Y", "Y", " "))))))))) | I10: =IF(H10="Y", "Y", (IF(G10="Y", "Y", (IF(F10="Y", "Y", (IF(E10="Y", "Y", " ")))))))
A11: =IF('Capital Costs'!A11<>"", 'Capital Costs'!A11, "") | B11: =IF('Capital Costs'!B11<>"", 'Capital Costs'!B11, "") | C11: =IF('Capital Costs'!C11<>"", 'Capital Costs'!C11, "") | D11: =IF('Capital Costs'!D11<>"", 'Capital Costs'!D11, "") | E11: =IF(N11="Y", "Y", (IF(M11="Y", "Y", (IF(L11="Y", "Y", (IF(K11="Y", "Y", (IF(J11="Y", "Y", " "))))))))) | F11: =IF(S11="Y", "Y", (IF(R11="Y", "Y", (IF(Q11="Y", "Y", (IF(P11="Y", "Y", (IF(O11="Y", "Y", " "))))))))) | G11: =IF(X11="Y", "Y", (IF(W11="Y", "Y", (IF(V11="Y", "Y", (IF(U11="Y", "Y", (IF(T11="Y", "Y", " "))))))))) | H11: =IF(AC11="Y", "Y", (IF(AB11="Y", "Y", (IF(AA11="Y", "Y", (IF(Z11="Y", "Y", (IF(Y11="Y", "Y", " "))))))))) | I11: =IF(H11="Y", "Y", (IF(G11="Y", "Y", (IF(F11="Y", "Y", (IF(E11="Y", "Y", " ")))))))
A12: =IF('Capital Costs'!A12<>"", 'Capital Costs'!A12, "") | B12: =IF('Capital Costs'!B12<>"", 'Capital Costs'!B12, "") | C12: =IF('Capital Costs'!C12<>"", 'Capital Costs'!C12, "") | D12: =IF('Capital Costs'!D12<>"", 'Capital Costs'!D12, "") | E12: =IF(N12="Y", "Y", (IF(M12="Y", "Y", (IF(L12="Y", "Y", (IF(K12="Y", "Y", (IF(J12="Y", "Y", " "))))))))) | F12: =IF(S12="Y", "Y", (IF(R12="Y", "Y", (IF(Q12="Y", "Y", (IF(P12="Y", "Y", (IF(O12="Y", "Y", " "))))))))) | G12: =IF(X12="Y", "Y", (IF(W12="Y", "Y", (IF(V12="Y", "Y", (IF(U12="Y", "Y", (IF(T12="Y", "Y", " "))))))))) | H12: =IF(AC12="Y", "Y", (IF(AB12="Y", "Y", (IF(AA12="Y", "Y", (IF(Z12="Y", "Y", (IF(Y12="Y", "Y", " "))))))))) | I12: =IF(H12="Y", "Y", (IF(G12="Y", "Y", (IF(F12="Y", "Y", (IF(E12="Y", "Y", " ")))))))
A13: =IF('Capital Costs'!A13<>"", 'Capital Costs'!A13, "") | B13: =IF('Capital Costs'!B13<>"", 'Capital Costs'!B13, "") | C13: =IF('Capital Costs'!C13<>"", 'Capital Costs'!C13, "") | D13: =IF('Capital Costs'!D13<>"", 'Capital Costs'!D13, "") | E13: =IF(N13="Y", "Y", (IF(M13="Y", "Y", (IF(L13="Y", "Y", (IF(K13="Y", "Y", (IF(J13="Y", "Y", " "))))))))) | F13: =IF(S13="Y", "Y", (IF(R13="Y", "Y", (IF(Q13="Y", "Y", (IF(P13="Y", "Y", (IF(O13="Y", "Y", " "))))))))) | G13: =IF(X13="Y", "Y", (IF(W13="Y", "Y", (IF(V13="Y", "Y", (IF(U13="Y", "Y", (IF(T13="Y", "Y", " "))))))))) | H13: =IF(AC13="Y", "Y", (IF(AB13="Y", "Y", (IF(AA13="Y", "Y", (IF(Z13="Y", "Y", (IF(Y13="Y", "Y", " "))))))))) | I13: =IF(H13="Y", "Y", (IF(G13="Y", "Y", (IF(F13="Y", "Y", (IF(E13="Y", "Y", " ")))))))
A14: =IF('Capital Costs'!A14<>"", 'Capital Costs'!A14, "") | B14: =IF('Capital Costs'!B14<>"", 'Capital Costs'!B14, "") | C14: =IF('Capital Costs'!C14<>"", 'Capital Costs'!C14, "") | D14: =IF('Capital Costs'!D14<>"", 'Capital Costs'!D14, "") | E14: =IF(N14="Y", "Y", (IF(M14="Y", "Y", (IF(L14="Y", "Y", (IF(K14="Y", "Y", (IF(J14="Y", "Y", " "))))))))) | F14: =IF(S14="Y", "Y", (IF(R14="Y", "Y", (IF(Q14="Y", "Y", (IF(P14="Y", "Y", (IF(O14="Y", "Y", " "))))))))) | G14: =IF(X14="Y", "Y", (IF(W14="Y", "Y", (IF(V14="Y", "Y", (IF(U14="Y", "Y", (IF(T14="Y", "Y", " "))))))))) | H14: =IF(AC14="Y", "Y", (IF(AB14="Y", "Y", (IF(AA14="Y", "Y", (IF(Z14="Y", "Y", (IF(Y14="Y", "Y", " "))))))))) | I14: =IF(H14="Y", "Y", (IF(G14="Y", "Y", (IF(F14="Y", "Y", (IF(E14="Y", "Y", " ")))))))
A15: =IF('Capital Costs'!A15<>"", 'Capital Costs'!A15, "") | B15: =IF('Capital Costs'!B15<>"", 'Capital Costs'!B15, "") | C15: =IF('Capital Costs'!C15<>"", 'Capital Costs'!C15, "") | D15: =IF('Capital Costs'!D15<>"", 'Capital Costs'!D15, "") | E15: =IF(N15="Y", "Y", (IF(M15="Y", "Y", (IF(L15="Y", "Y", (IF(K15="Y", "Y", (IF(J15="Y", "Y", " "))))))))) | F15: =IF(S15="Y", "Y", (IF(R15="Y", "Y", (IF(Q15="Y", "Y", (IF(P15="Y", "Y", (IF(O15="Y", "Y", " "))))))))) | G15: =IF(X15="Y", "Y", (IF(W15="Y", "Y", (IF(V15="Y", "Y", (IF(U15="Y", "Y", (IF(T15="Y", "Y", " "))))))))) | H15: =IF(AC15="Y", "Y", (IF(AB15="Y", "Y", (IF(AA15="Y", "Y", (IF(Z15="Y", "Y", (IF(Y15="Y", "Y", " "))))))))) | I15: =IF(H15="Y", "Y", (IF(G15="Y", "Y", (IF(F15="Y", "Y", (IF(E15="Y", "Y", " ")))))))
A16: =IF('Capital Costs'!A16<>"", 'Capital Costs'!A16, "") | B16: =IF('Capital Costs'!B16<>"", 'Capital Costs'!B16, "") | C16: =IF('Capital Costs'!C16<>"", 'Capital Costs'!C16, "") | D16: =IF('Capital Costs'!D16<>"", 'Capital Costs'!D16, "") | E16: =IF(N16="Y", "Y", (IF(M16="Y", "Y", (IF(L16="Y", "Y", (IF(K16="Y", "Y", (IF(J16="Y", "Y", " "))))))))) | F16: =IF(S16="Y", "Y", (IF(R16="Y", "Y", (IF(Q16="Y", "Y", (IF(P16="Y", "Y", (IF(O16="Y", "Y", " "))))))))) | G16: =IF(X16="Y", "Y", (IF(W16="Y", "Y", (IF(V16="Y", "Y", (IF(U16="Y", "Y", (IF(T16="Y", "Y", " "))))))))) | H16: =IF(AC16="Y", "Y", (IF(AB16="Y", "Y", (IF(AA16="Y", "Y", (IF(Z16="Y", "Y", (IF(Y16="Y", "Y", " "))))))))) | I16: =IF(H16="Y", "Y", (IF(G16="Y", "Y", (IF(F16="Y", "Y", (IF(E16="Y", "Y", " ")))))))
A17: =IF('Capital Costs'!A17<>"", 'Capital Costs'!A17, "") | B17: =IF('Capital Costs'!B17<>"", 'Capital Costs'!B17, "") | C17: =IF('Capital Costs'!C17<>"", 'Capital Costs'!C17, "") | D17: =IF('Capital Costs'!D17<>"", 'Capital Costs'!D17, "") | E17: =IF(N17="Y", "Y", (IF(M17="Y", "Y", (IF(L17="Y", "Y", (IF(K17="Y", "Y", (IF(J17="Y", "Y", " "))))))))) | F17: =IF(S17="Y", "Y", (IF(R17="Y", "Y", (IF(Q17="Y", "Y", (IF(P17="Y", "Y", (IF(O17="Y", "Y", " "))))))))) | G17: =IF(X17="Y", "Y", (IF(W17="Y", "Y", (IF(V17="Y", "Y", (IF(U17="Y", "Y", (IF(T17="Y", "Y", " "))))))))) | H17: =IF(AC17="Y", "Y", (IF(AB17="Y", "Y", (IF(AA17="Y", "Y", (IF(Z17="Y", "Y", (IF(Y17="Y", "Y", " "))))))))) | I17: =IF(H17="Y", "Y", (IF(G17="Y", "Y", (IF(F17="Y", "Y", (IF(E17="Y", "Y", " ")))))))
A18: =IF('Capital Costs'!A18<>"", 'Capital Costs'!A18, "") | B18: =IF('Capital Costs'!B18<>"", 'Capital Costs'!B18, "") | C18: =IF('Capital Costs'!C18<>"", 'Capital Costs'!C18, "") | D18: =IF('Capital Costs'!D18<>"", 'Capital Costs'!D18, "") | E18: =IF(N18="Y", "Y", (IF(M18="Y", "Y", (IF(L18="Y", "Y", (IF(K18="Y", "Y", (IF(J18="Y", "Y", " "))))))))) | F18: =IF(S18="Y", "Y", (IF(R18="Y", "Y", (IF(Q18="Y", "Y", (IF(P18="Y", "Y", (IF(O18="Y", "Y", " "))))))))) | G18: =IF(X18="Y", "Y", (IF(W18="Y", "Y", (IF(V18="Y", "Y", (IF(U18="Y", "Y", (IF(T18="Y", "Y", " "))))))))) | H18: =IF(AC18="Y", "Y", (IF(AB18="Y", "Y", (IF(AA18="Y", "Y", (IF(Z18="Y", "Y", (IF(Y18="Y", "Y", " "))))))))) | I18: =IF(H18="Y", "Y", (IF(G18="Y", "Y", (IF(F18="Y", "Y", (IF(E18="Y", "Y", " ")))))))
A19: =IF('Capital Costs'!A19<>"", 'Capital Costs'!A19, "") | B19: =IF('Capital Costs'!B19<>"", 'Capital Costs'!B19, "") | C19: =IF('Capital Costs'!C19<>"", 'Capital Costs'!C19, "") | D19: =IF('Capital Costs'!D19<>"", 'Capital Costs'!D19, "") | E19: =IF(N19="Y", "Y", (IF(M19="Y", "Y", (IF(L19="Y", "Y", (IF(K19="Y", "Y", (IF(J19="Y", "Y", " "))))))))) | F19: =IF(S19="Y", "Y", (IF(R19="Y", "Y", (IF(Q19="Y", "Y", (IF(P19="Y", "Y", (IF(O19="Y", "Y", " "))))))))) | G19: =IF(X19="Y", "Y", (IF(W19="Y", "Y", (IF(V19="Y", "Y", (IF(U19="Y", "Y", (IF(T19="Y", "Y", " "))))))))) | H19: =IF(AC19="Y", "Y", (IF(AB19="Y", "Y", (IF(AA19="Y", "Y", (IF(Z19="Y", "Y", (IF(Y19="Y", "Y", " "))))))))) | I19: =IF(H19="Y", "Y", (IF(G19="Y", "Y", (IF(F19="Y", "Y", (IF(E19="Y", "Y", " ")))))))
A20: =IF('Capital Costs'!A20<>"", 'Capital Costs'!A20, "") | B20: =IF('Capital Costs'!B20<>"", 'Capital Costs'!B20, "") | C20: =IF('Capital Costs'!C20<>"", 'Capital Costs'!C20, "") | D20: =IF('Capital Costs'!D20<>"", 'Capital Costs'!D20, "") | E20: =IF(N20="Y", "Y", (IF(M20="Y", "Y", (IF(L20="Y", "Y", (IF(K20="Y", "Y", (IF(J20="Y", "Y", " "))))))))) | F20: =IF(S20="Y", "Y", (IF(R20="Y", "Y", (IF(Q20="Y", "Y", (IF(P20="Y", "Y", (IF(O20="Y", "Y", " "))))))))) | G20: =IF(X20="Y", "Y", (IF(W20="Y", "Y", (IF(V20="Y", "Y", (IF(U20="Y", "Y", (IF(T20="Y", "Y", " "))))))))) | H20: =IF(AC20="Y", "Y", (IF(AB20="Y", "Y", (IF(AA20="Y", "Y", (IF(Z20="Y", "Y", (IF(Y20="Y", "Y", " "))))))))) | I20: =IF(H20="Y", "Y", (IF(G20="Y", "Y", (IF(F20="Y", "Y", (IF(E20="Y", "Y", " ")))))))
... A37: =IF('Capital Costs'!A37<>"", 'Capital Costs'!A37, "") | B37: =IF('Capital Costs'!B37<>"", 'Capital Costs'!B37, "") | C37: =IF('Capital Costs'!C37<>"", 'Capital Costs'!C37, "") | D37: =IF('Capital Costs'!D37<>"", 'Capital Costs'!D37, "") | E37: =IF(N37="Y", "Y", (IF(M37="Y", "Y", (IF(L37="Y", "Y", (IF(K37="Y", "Y", (IF(J37="Y", "Y", " "))))))))) | F37: =IF(S37="Y", "Y", (IF(R37="Y", "Y", (IF(Q37="Y", "Y", (IF(P37="Y", "Y", (IF(O37="Y", "Y", " "))))))))) | G37: =IF(X37="Y", "Y", (IF(W37="Y", "Y", (IF(V37="Y", "Y", (IF(U37="Y", "Y", (IF(T37="Y", "Y", " "))))))))) | H37: =IF(AC37="Y", "Y", (IF(AB37="Y", "Y", (IF(AA37="Y", "Y", (IF(Z37="Y", "Y", (IF(Y37="Y", "Y", " "))))))))) | I37: =IF(H37="Y", "Y", (IF(G37="Y", "Y", (IF(F37="Y", "Y", (IF(E37="Y", "Y", " ")))))))

Sheet Replace Costs - Results 1-5
A1: Table 5.2.3. Replacement Costs (Years 1 to 5)
A2: =Input!B4 -> 0
A3: =Input!B5 -> 0
A4: ='Capital Costs'!B6 -> 0
A5: Current Inflation Rate based on Construction Cost Index: | B5: =('CCI-MCI'!B3-'CCI-MCI'!B2)/'CCI-MCI'!B2 -> 0.020671835 | E5: EPA Discount Rate: | F5: 0.04875
E6: Present Value of Replacement Costs in Year:
A7: Component | B7: Unit Cost | C7: Unit | D7: Quantity | E7: 1 | F7: 2 | G7: 3 | H7: 4 | I7: 5
A8: =IF('Capital Costs'!A9<>"", 'Capital Costs'!A9, "") | B8: =IF('Capital Costs'!B9<>"", 'Capital Costs'!B9, "") | C8: =IF('Capital Costs'!C9<>"", 'Capital Costs'!C9, "") | D8: =IF('Capital Costs'!D9<>"", 'Capital Costs'!D9, "") | E8: =IF($A8<>"", (IF('Replacement Costs - Entry'!J9="Y",((($B8*$D8)*((1+$B$5)^E$7))*(1/((1+$F$5)^E$7))),0)), "") | F8: =IF($A8<>"", (IF('Replacement Costs - Entry'!K9="Y",((($B8*$D8)*((1+$B$5)^F$7))*(1/((1+$F$5)^F$7))),0)), "") | G8: =IF($A8<>"", (IF('Replacement Costs - Entry'!L9="Y",((($B8*$D8)*((1+$B$5)^G$7))*(1/((1+$F$5)^G$7))),0)), "") | H8: =IF($A8<>"", (IF('Replacement Costs - Entry'!M9="Y",((($B8*$D8)*((1+$B$5)^H$7))*(1/((1+$F$5)^H$7))),0)), "") | I8: =IF($A8<>"", (IF('Replacement Costs - Entry'!N9="Y",((($B8*$D8)*((1+$B$5)^I$7))*(1/((1+$F$5)^I$7))),0)), "")
A9: =IF('Capital Costs'!A10<>"", 'Capital Costs'!A10, "") | B9: =IF('Capital Costs'!B10<>"", 'Capital Costs'!B10, "") | C9: =IF('Capital Costs'!C10<>"", 'Capital Costs'!C10, "") | D9: =IF('Capital Costs'!D10<>"", 'Capital Costs'!D10, "") | E9: =IF($A9<>"", (IF('Replacement Costs - Entry'!J10="Y",((($B9*$D9)*((1+$B$5)^E$7))*(1/((1+$F$5)^E$7))),0)), "") | F9: =IF($A9<>"", (IF('Replacement Costs - Entry'!K10="Y",((($B9*$D9)*((1+$B$5)^F$7))*(1/((1+$F$5)^F$7))),0)), "") | G9: =IF($A9<>"", (IF('Replacement Costs - Entry'!L10="Y",((($B9*$D9)*((1+$B$5)^G$7))*(1/((1+$F$5)^G$7))),0)), "") | H9: =IF($A9<>"", (IF('Replacement Costs - Entry'!M10="Y",((($B9*$D9)*((1+$B$5)^H$7))*(1/((1+$F$5)^H$7))),0)), "") | I9: =IF($A9<>"", (IF('Replacement Costs - Entry'!N10="Y",((($B9*$D9)*((1+$B$5)^I$7))*(1/((1+$F$5)^I$7))),0)), "")
A10: =IF('Capital Costs'!A11<>"", 'Capital Costs'!A11, "") | B10: =IF('Capital Costs'!B11<>"", 'Capital Costs'!B11, "") | C10: =IF('Capital Costs'!C11<>"", 'Capital Costs'!C11, "") | D10: =IF('Capital Costs'!D11<>"", 'Capital Costs'!D11, "") | E10: =IF($A10<>"", (IF('Replacement Costs - Entry'!J11="Y",((($B10*$D10)*((1+$B$5)^E$7))*(1/((1+$F$5)^E$7))),0)), "") | F10: =IF($A10<>"", (IF('Replacement Costs - Entry'!K11="Y",((($B10*$D10)*((1+$B$5)^F$7))*(1/((1+$F$5)^F$7))),0)), "") | G10: =IF($A10<>"", (IF('Replacement Costs - Entry'!L11="Y",((($B10*$D10)*((1+$B$5)^G$7))*(1/((1+$F$5)^G$7))),0)), "") | H10: =IF($A10<>"", (IF('Replacement Costs - Entry'!M11="Y",((($B10*$D10)*((1+$B$5)^H$7))*(1/((1+$F$5)^H$7))),0)), "") | I10: =IF($A10<>"", (IF('Replacement Costs - Entry'!N11="Y",((($B10*$D10)*((1+$B$5)^I$7))*(1/((1+$F$5)^I$7))),0)), "")
A11: =IF('Capital Costs'!A12<>"", 'Capital Costs'!A12, "") | B11: =IF('Capital Costs'!B12<>"", 'Capital Costs'!B12, "") | C11: =IF('Capital Costs'!C12<>"", 'Capital Costs'!C12, "") | D11: =IF('Capital Costs'!D12<>"", 'Capital Costs'!D12, "") | E11: =IF($A11<>"", (IF('Replacement Costs - Entry'!J12="Y",((($B11*$D11)*((1+$B$5)^E$7))*(1/((1+$F$5)^E$7))),0)), "") | F11: =IF($A11<>"", (IF('Replacement Costs - Entry'!K12="Y",((($B11*$D11)*((1+$B$5)^F$7))*(1/((1+$F$5)^F$7))),0)), "") | G11: =IF($A11<>"", (IF('Replacement Costs - Entry'!L12="Y",((($B11*$D11)*((1+$B$5)^G$7))*(1/((1+$F$5)^G$7))),0)), "") | H11: =IF($A11<>"", (IF('Replacement Costs - Entry'!M12="Y",((($B11*$D11)*((1+$B$5)^H$7))*(1/((1+$F$5)^H$7))),0)), "") | I11: =IF($A11<>"", (IF('Replacement Costs - Entry'!N12="Y",((($B11*$D11)*((1+$B$5)^I$7))*(1/((1+$F$5)^I$7))),0)), "")
A12: =IF('Capital Costs'!A13<>"", 'Capital Costs'!A13, "") | B12: =IF('Capital Costs'!B13<>"", 'Capital Costs'!B13, "") | C12: =IF('Capital Costs'!C13<>"", 'Capital Costs'!C13, "") | D12: =IF('Capital Costs'!D13<>"", 'Capital Costs'!D13, "") | E12: =IF($A12<>"", (IF('Replacement Costs - Entry'!J13="Y",((($B12*$D12)*((1+$B$5)^E$7))*(1/((1+$F$5)^E$7))),0)), "") | F12: =IF($A12<>"", (IF('Replacement Costs - Entry'!K13="Y",((($B12*$D12)*((1+$B$5)^F$7))*(1/((1+$F$5)^F$7))),0)), "") | G12: =IF($A12<>"", (IF('Replacement Costs - Entry'!L13="Y",((($B12*$D12)*((1+$B$5)^G$7))*(1/((1+$F$5)^G$7))),0)), "") | H12: =IF($A12<>"", (IF('Replacement Costs - Entry'!M13="Y",((($B12*$D12)*((1+$B$5)^H$7))*(1/((1+$F$5)^H$7))),0)), "") | I12: =IF($A12<>"", (IF('Replacement Costs - Entry'!N13="Y",((($B12*$D12)*((1+$B$5)^I$7))*(1/((1+$F$5)^I$7))),0)), "")
A13: =IF('Capital Costs'!A14<>"", 'Capital Costs'!A14, "") | B13: =IF('Capital Costs'!B14<>"", 'Capital Costs'!B14, "") | C13: =IF('Capital Costs'!C14<>"", 'Capital Costs'!C14, "") | D13: =IF('Capital Costs'!D14<>"", 'Capital Costs'!D14, "") | E13: =IF($A13<>"", (IF('Replacement Costs - Entry'!J14="Y",((($B13*$D13)*((1+$B$5)^E$7))*(1/((1+$F$5)^E$7))),0)), "") | F13: =IF($A13<>"", (IF('Replacement Costs - Entry'!K14="Y",((($B13*$D13)*((1+$B$5)^F$7))*(1/((1+$F$5)^F$7))),0)), "") | G13: =IF($A13<>"", (IF('Replacement Costs - Entry'!L14="Y",((($B13*$D13)*((1+$B$5)^G$7))*(1/((1+$F$5)^G$7))),0)), "") | H13: =IF($A13<>"", (IF('Replacement Costs - Entry'!M14="Y",((($B13*$D13)*((1+$B$5)^H$7))*(1/((1+$F$5)^H$7))),0)), "") | I13: =IF($A13<>"", (IF('Replacement Costs - Entry'!N14="Y",((($B13*$D13)*((1+$B$5)^I$7))*(1/((1+$F$5)^I$7))),0)), "")
A14: =IF('Capital Costs'!A15<>"", 'Capital Costs'!A15, "") | B14: =IF('Capital Costs'!B15<>"", 'Capital Costs'!B15, "") | C14: =IF('Capital Costs'!C15<>"", 'Capital Costs'!C15, "") | D14: =IF('Capital Costs'!D15<>"", 'Capital Costs'!D15, "") | E14: =IF($A14<>"", (IF('Replacement Costs - Entry'!J15="Y",((($B14*$D14)*((1+$B$5)^E$7))*(1/((1+$F$5)^E$7))),0)), "") | F14: =IF($A14<>"", (IF('Replacement Costs - Entry'!K15="Y",((($B14*$D14)*((1+$B$5)^F$7))*(1/((1+$F$5)^F$7))),0)), "") | G14: =IF($A14<>"", (IF('Replacement Costs - Entry'!L15="Y",((($B14*$D14)*((1+$B$5)^G$7))*(1/((1+$F$5)^G$7))),0)), "") | H14: =IF($A14<>"", (IF('Replacement Costs - Entry'!M15="Y",((($B14*$D14)*((1+$B$5)^H$7))*(1/((1+$F$5)^H$7))),0)), "") | I14: =IF($A14<>"", (IF('Replacement Costs - Entry'!N15="Y",((($B14*$D14)*((1+$B$5)^I$7))*(1/((1+$F$5)^I$7))),0)), "")
A15: =IF('Capital Costs'!A16<>"", 'Capital Costs'!A16, "") | B15: =IF('Capital Costs'!B16<>"", 'Capital Costs'!B16, "") | C15: =IF('Capital Costs'!C16<>"", 'Capital Costs'!C16, "") | D15: =IF('Capital Costs'!D16<>"", 'Capital Costs'!D16, "") | E15: =IF($A15<>"", (IF('Replacement Costs - Entry'!J16="Y",((($B15*$D15)*((1+$B$5)^E$7))*(1/((1+$F$5)^E$7))),0)), "") | F15: =IF($A15<>"", (IF('Replacement Costs - Entry'!K16="Y",((($B15*$D15)*((1+$B$5)^F$7))*(1/((1+$F$5)^F$7))),0)), "") | G15: =IF($A15<>"", (IF('Replacement Costs - Entry'!L16="Y",((($B15*$D15)*((1+$B$5)^G$7))*(1/((1+$F$5)^G$7))),0)), "") | H15: =IF($A15<>"", (IF('Replacement Costs - Entry'!M16="Y",((($B15*$D15)*((1+$B$5)^H$7))*(1/((1+$F$5)^H$7))),0)), "") | I15: =IF($A15<>"", (IF('Replacement Costs - Entry'!N16="Y",((($B15*$D15)*((1+$B$5)^I$7))*(1/((1+$F$5)^I$7))),0)), "")
A16: =IF('Capital Costs'!A17<>"", 'Capital Costs'!A17, "") | B16: =IF('Capital Costs'!B17<>"", 'Capital Costs'!B17, "") | C16: =IF('Capital Costs'!C17<>"", 'Capital Costs'!C17, "") | D16: =IF('Capital Costs'!D17<>"", 'Capital Costs'!D17, "") | E16: =IF($A16<>"", (IF('Replacement Costs - Entry'!J17="Y",((($B16*$D16)*((1+$B$5)^E$7))*(1/((1+$F$5)^E$7))),0)), "") | F16: =IF($A16<>"", (IF('Replacement Costs - Entry'!K17="Y",((($B16*$D16)*((1+$B$5)^F$7))*(1/((1+$F$5)^F$7))),0)), "") | G16: =IF($A16<>"", (IF('Replacement Costs - Entry'!L17="Y",((($B16*$D16)*((1+$B$5)^G$7))*(1/((1+$F$5)^G$7))),0)), "") | H16: =IF($A16<>"", (IF('Replacement Costs - Entry'!M17="Y",((($B16*$D16)*((1+$B$5)^H$7))*(1/((1+$F$5)^H$7))),0)), "") | I16: =IF($A16<>"", (IF('Replacement Costs - Entry'!N17="Y",((($B16*$D16)*((1+$B$5)^I$7))*(1/((1+$F$5)^I$7))),0)), "")
A17: =IF('Capital Costs'!A18<>"", 'Capital Costs'!A18, "") | B17: =IF('Capital Costs'!B18<>"", 'Capital Costs'!B18, "") | C17: =IF('Capital Costs'!C18<>"", 'Capital Costs'!C18, "") | D17: =IF('Capital Costs'!D18<>"", 'Capital Costs'!D18, "") | E17: =IF($A17<>"", (IF('Replacement Costs - Entry'!J18="Y",((($B17*$D17)*((1+$B$5)^E$7))*(1/((1+$F$5)^E$7))),0)), "") | F17: =IF($A17<>"", (IF('Replacement Costs - Entry'!K18="Y",((($B17*$D17)*((1+$B$5)^F$7))*(1/((1+$F$5)^F$7))),0)), "") | G17: =IF($A17<>"", (IF('Replacement Costs - Entry'!L18="Y",((($B17*$D17)*((1+$B$5)^G$7))*(1/((1+$F$5)^G$7))),0)), "") | H17: =IF($A17<>"", (IF('Replacement Costs - Entry'!M18="Y",((($B17*$D17)*((1+$B$5)^H$7))*(1/((1+$F$5)^H$7))),0)), "") | I17: =IF($A17<>"", (IF('Replacement Costs - Entry'!N18="Y",((($B17*$D17)*((1+$B$5)^I$7))*(1/((1+$F$5)^I$7))),0)), "")
A18: =IF('Capital Costs'!A19<>"", 'Capital Costs'!A19, "") | B18: =IF('Capital Costs'!B19<>"", 'Capital Costs'!B19, "") | C18: =IF('Capital Costs'!C19<>"", 'Capital Costs'!C19, "") | D18: =IF('Capital Costs'!D19<>"", 'Capital Costs'!D19, "") | E18: =IF($A18<>"", (IF('Replacement Costs - Entry'!J19="Y",((($B18*$D18)*((1+$B$5)^E$7))*(1/((1+$F$5)^E$7))),0)), "") | F18: =IF($A18<>"", (IF('Replacement Costs - Entry'!K19="Y",((($B18*$D18)*((1+$B$5)^F$7))*(1/((1+$F$5)^F$7))),0)), "") | G18: =IF($A18<>"", (IF('Replacement Costs - Entry'!L19="Y",((($B18*$D18)*((1+$B$5)^G$7))*(1/((1+$F$5)^G$7))),0)), "") | H18: =IF($A18<>"", (IF('Replacement Costs - Entry'!M19="Y",((($B18*$D18)*((1+$B$5)^H$7))*(1/((1+$F$5)^H$7))),0)), "") | I18: =IF($A18<>"", (IF('Replacement Costs - Entry'!N19="Y",((($B18*$D18)*((1+$B$5)^I$7))*(1/((1+$F$5)^I$7))),0)), "")
A19: =IF('Capital Costs'!A20<>"", 'Capital Costs'!A20, "") | B19: =IF('Capital Costs'!B20<>"", 'Capital Costs'!B20, "") | C19: =IF('Capital Costs'!C20<>"", 'Capital Costs'!C20, "") | D19: =IF('Capital Costs'!D20<>"", 'Capital Costs'!D20, "") | E19: =IF($A19<>"", (IF('Replacement Costs - Entry'!J20="Y",((($B19*$D19)*((1+$B$5)^E$7))*(1/((1+$F$5)^E$7))),0)), "") | F19: =IF($A19<>"", (IF('Replacement Costs - Entry'!K20="Y",((($B19*$D19)*((1+$B$5)^F$7))*(1/((1+$F$5)^F$7))),0)), "") | G19: =IF($A19<>"", (IF('Replacement Costs - Entry'!L20="Y",((($B19*$D19)*((1+$B$5)^G$7))*(1/((1+$F$5)^G$7))),0)), "") | H19: =IF($A19<>"", (IF('Replacement Costs - Entry'!M20="Y",((($B19*$D19)*((1+$B$5)^H$7))*(1/((1+$F$5)^H$7))),0)), "") | I19: =IF($A19<>"", (IF('Replacement Costs - Entry'!N20="Y",((($B19*$D19)*((1+$B$5)^I$7))*(1/((1+$F$5)^I$7))),0)), "")
... A36: =IF('Capital Costs'!A37<>"", 'Capital Costs'!A37, "") | B36: =IF('Capital Costs'!B37<>"", 'Capital Costs'!B37, "") | C36: =IF('Capital Costs'!C37<>"", 'Capital Costs'!C37, "") | D36: =IF('Capital Costs'!D37<>"", 'Capital Costs'!D37, "") | E36: =IF($A36<>"", (IF('Replacement Costs - Entry'!J37="Y",((($B36*$D36)*((1+$B$5)^E$7))*(1/((1+$F$5)^E$7))),0)), "") | F36: =IF($A36<>"", (IF('Replacement Costs - Entry'!K37="Y",((($B36*$D36)*((1+$B$5)^F$7))*(1/((1+$F$5)^F$7))),0)), "") | G36: =IF($A36<>"", (IF('Replacement Costs - Entry'!L37="Y",((($B36*$D36)*((1+$B$5)^G$7))*(1/((1+$F$5)^G$7))),0)), "") | H36: =IF($A36<>"", (IF('Replacement Costs - Entry'!M37="Y",((($B36*$D36)*((1+$B$5)^H$7))*(1/((1+$F$5)^H$7))),0)), "") | I36: =IF($A36<>"", (IF('Replacement Costs - Entry'!N37="Y",((($B36*$D36)*((1+$B$5)^I$7))*(1/((1+$F$5)^I$7))),0)), "")
D37: Total Present Value of Replacement Costs (Years 1 to 5): | E37: =SUM(E8:E36) -> 0 | F37: =SUM(F8:F36) -> 0 | G37: =SUM(G8:G36) -> 0 | H37: =SUM(H8:H36) -> 0 | I37: =SUM(I8:I36) -> 0

Sheet Replace Costs-Results 6-10
A1: Table 5.2.4. Replacement Costs (Years 6 to 10)
A2: =Input!B4 -> 0
A3: =Input!B5 -> 0
A4: ='Capital Costs'!B6 -> 0
A5: ='Replace Costs - Results 1-5'!A5 -> Current Inflation Rate based on Construction Cost Index: | B5: ='Replace Costs - Results 1-5'!B5 -> 0.020671835 | E5: EPA Discount Rate: | F5: ='Replace Costs - Results 1-5'!F5 -> 0.04875
E6: Present Value of Replacement Costs in Year:
A7: Component | B7: Unit Cost | C7: Unit | D7: Quantity | E7: 6 | F7: 7 | G7: 8 | H7: 9 | I7: 10
A8: =IF('Capital Costs'!A9<>"", 'Capital Costs'!A9, "") | B8: =IF('Capital Costs'!B9<>"", 'Capital Costs'!B9, "") | C8: =IF('Capital Costs'!C9<>"", 'Capital Costs'!C9, "") | D8: =IF('Capital Costs'!D9<>"", 'Capital Costs'!D9, "") | E8: =IF($A8<>"", (IF('Replacement Costs - Entry'!O9="Y",((($B8*$D8)*((1+$B$5)^E$7))*(1/((1+$F$5)^E$7))),0)), "") | F8: =IF($A8<>"", (IF('Replacement Costs - Entry'!P9="Y",((($B8*$D8)*((1+$B$5)^F$7))*(1/((1+$F$5)^F$7))),0)), "") | G8: =IF($A8<>"", (IF('Replacement Costs - Entry'!Q9="Y",((($B8*$D8)*((1+$B$5)^G$7))*(1/((1+$F$5)^G$7))),0)), "") | H8: =IF($A8<>"", (IF('Replacement Costs - Entry'!R9="Y",((($B8*$D8)*((1+$B$5)^H$7))*(1/((1+$F$5)^H$7))),0)), "") | I8: =IF($A8<>"", (IF('Replacement Costs - Entry'!S9="Y",((($B8*$D8)*((1+$B$5)^I$7))*(1/((1+$F$5)^I$7))),0)), "")
A9: =IF('Capital Costs'!A10<>"", 'Capital Costs'!A10, "") | B9: =IF('Capital Costs'!B10<>"", 'Capital Costs'!B10, "") | C9: =IF('Capital Costs'!C10<>"", 'Capital Costs'!C10, "") | D9: =IF('Capital Costs'!D10<>"", 'Capital Costs'!D10, "") | E9: =IF($A9<>"", (IF('Replacement Costs - Entry'!O10="Y",((($B9*$D9)*((1+$B$5)^E$7))*(1/((1+$F$5)^E$7))),0)), "") | F9: =IF($A9<>"", (IF('Replacement Costs - Entry'!P10="Y",((($B9*$D9)*((1+$B$5)^F$7))*(1/((1+$F$5)^F$7))),0)), "") | G9: =IF($A9<>"", (IF('Replacement Costs - Entry'!Q10="Y",((($B9*$D9)*((1+$B$5)^G$7))*(1/((1+$F$5)^G$7))),0)), "") | H9: =IF($A9<>"", (IF('Replacement Costs - Entry'!R10="Y",((($B9*$D9)*((1+$B$5)^H$7))*(1/((1+$F$5)^H$7))),0)), "") | I9: =IF($A9<>"", (IF('Replacement Costs - Entry'!S10="Y",((($B9*$D9)*((1+$B$5)^I$7))*(1/((1+$F$5)^I$7))),0)), "")
A10: =IF('Capital Costs'!A11<>"", 'Capital Costs'!A11, "") | B10: =IF('Capital Costs'!B11<>"", 'Capital Costs'!B11, "") | C10: =IF('Capital Costs'!C11<>"", 'Capital Costs'!C11, "") | D10: =IF('Capital Costs'!D11<>"", 'Capital Costs'!D11, "") | E10: =IF($A10<>"", (IF('Replacement Costs - Entry'!O11="Y",((($B10*$D10)*((1+$B$5)^E$7))*(1/((1+$F$5)^E$7))),0)), "") | F10: =IF($A10<>"", (IF('Replacement Costs - Entry'!P11="Y",((($B10*$D10)*((1+$B$5)^F$7))*(1/((1+$F$5)^F$7))),0)), "") | G10: =IF($A10<>"", (IF('Replacement Costs - Entry'!Q11="Y",((($B10*$D10)*((1+$B$5)^G$7))*(1/((1+$F$5)^G$7))),0)), "") | H10: =IF($A10<>"", (IF('Replacement Costs - Entry'!R11="Y",((($B10*$D10)*((1+$B$5)^H$7))*(1/((1+$F$5)^H$7))),0)), "") | I10: =IF($A10<>"", (IF('Replacement Costs - Entry'!S11="Y",((($B10*$D10)*((1+$B$5)^I$7))*(1/((1+$F$5)^I$7))),0)), "")
A11: =IF('Capital Costs'!A12<>"", 'Capital Costs'!A12, "") | B11: =IF('Capital Costs'!B12<>"", 'Capital Costs'!B12, "") | C11: =IF('Capital Costs'!C12<>"", 'Capital Costs'!C12, "") | D11: =IF('Capital Costs'!D12<>"", 'Capital Costs'!D12, "") | E11: =IF($A11<>"", (IF('Replacement Costs - Entry'!O12="Y",((($B11*$D11)*((1+$B$5)^E$7))*(1/((1+$F$5)^E$7))),0)), "") | F11: =IF($A11<>"", (IF('Replacement Costs - Entry'!P12="Y",((($B11*$D11)*((1+$B$5)^F$7))*(1/((1+$F$5)^F$7))),0)), "") | G11: =IF($A11<>"", (IF('Replacement Costs - Entry'!Q12="Y",((($B11*$D11)*((1+$B$5)^G$7))*(1/((1+$F$5)^G$7))),0)), "") | H11: =IF($A11<>"", (IF('Replacement Costs - Entry'!R12="Y",((($B11*$D11)*((1+$B$5)^H$7))*(1/((1+$F$5)^H$7))),0)), "") | I11: =IF($A11<>"", (IF('Replacement Costs - Entry'!S12="Y",((($B11*$D11)*((1+$B$5)^I$7))*(1/((1+$F$5)^I$7))),0)), "")
A12: =IF('Capital Costs'!A13<>"", 'Capital Costs'!A13, "") | B12: =IF('Capital Costs'!B13<>"", 'Capital Costs'!B13, "") | C12: =IF('Capital Costs'!C13<>"", 'Capital Costs'!C13, "") | D12: =IF('Capital Costs'!D13<>"", 'Capital Costs'!D13, "") | E12: =IF($A12<>"", (IF('Replacement Costs - Entry'!O13="Y",((($B12*$D12)*((1+$B$5)^E$7))*(1/((1+$F$5)^E$7))),0)), "") | F12: =IF($A12<>"", (IF('Replacement Costs - Entry'!P13="Y",((($B12*$D12)*((1+$B$5)^F$7))*(1/((1+$F$5)^F$7))),0)), "") | G12: =IF($A12<>"", (IF('Replacement Costs - Entry'!Q13="Y",((($B12*$D12)*((1+$B$5)^G$7))*(1/((1+$F$5)^G$7))),0)), "") | H12: =IF($A12<>"", (IF('Replacement Costs - Entry'!R13="Y",((($B12*$D12)*((1+$B$5)^H$7))*(1/((1+$F$5)^H$7))),0)), "") | I12: =IF($A12<>"", (IF('Replacement Costs - Entry'!S13="Y",((($B12*$D12)*((1+$B$5)^I$7))*(1/((1+$F$5)^I$7))),0)), "")
A13: =IF('Capital Costs'!A14<>"", 'Capital Costs'!A14, "") | B13: =IF('Capital Costs'!B14<>"", 'Capital Costs'!B14, "") | C13: =IF('Capital Costs'!C14<>"", 'Capital Costs'!C14, "") | D13: =IF('Capital Costs'!D14<>"", 'Capital Costs'!D14, "") | E13: =IF($A13<>"", (IF('Replacement Costs - Entry'!O14="Y",((($B13*$D13)*((1+$B$5)^E$7))*(1/((1+$F$5)^E$7))),0)), "") | F13: =IF($A13<>"", (IF('Replacement Costs - Entry'!P14="Y",((($B13*$D13)*((1+$B$5)^F$7))*(1/((1+$F$5)^F$7))),0)), "") | G13: =IF($A13<>"", (IF('Replacement Costs - Entry'!Q14="Y",((($B13*$D13)*((1+$B$5)^G$7))*(1/((1+$F$5)^G$7))),0)), "") | H13: =IF($A13<>"", (IF('Replacement Costs - Entry'!R14="Y",((($B13*$D13)*((1+$B$5)^H$7))*(1/((1+$F$5)^H$7))),0)), "") | I13: =IF($A13<>"", (IF('Replacement Costs - Entry'!S14="Y",((($B13*$D13)*((1+$B$5)^I$7))*(1/((1+$F$5)^I$7))),0)), "")
A14: =IF('Capital Costs'!A15<>"", 'Capital Costs'!A15, "") | B14: =IF('Capital Costs'!B15<>"", 'Capital Costs'!B15, "") | C14: =IF('Capital Costs'!C15<>"", 'Capital Costs'!C15, "") | D14: =IF('Capital Costs'!D15<>"", 'Capital Costs'!D15, "") | E14: =IF($A14<>"", (IF('Replacement Costs - Entry'!O15="Y",((($B14*$D14)*((1+$B$5)^E$7))*(1/((1+$F$5)^E$7))),0)), "") | F14: =IF($A14<>"", (IF('Replacement Costs - Entry'!P15="Y",((($B14*$D14)*((1+$B$5)^F$7))*(1/((1+$F$5)^F$7))),0)), "") | G14: =IF($A14<>"", (IF('Replacement Costs - Entry'!Q15="Y",((($B14*$D14)*((1+$B$5)^G$7))*(1/((1+$F$5)^G$7))),0)), "") | H14: =IF($A14<>"", (IF('Replacement Costs - Entry'!R15="Y",((($B14*$D14)*((1+$B$5)^H$7))*(1/((1+$F$5)^H$7))),0)), "") | I14: =IF($A14<>"", (IF('Replacement Costs - Entry'!S15="Y",((($B14*$D14)*((1+$B$5)^I$7))*(1/((1+$F$5)^I$7))),0)), "")
A15: =IF('Capital Costs'!A16<>"", 'Capital Costs'!A16, "") | B15: =IF('Capital Costs'!B16<>"", 'Capital Costs'!B16, "") | C15: =IF('Capital Costs'!C16<>"", 'Capital Costs'!C16, "") | D15: =IF('Capital Costs'!D16<>"", 'Capital Costs'!D16, "") | E15: =IF($A15<>"", (IF('Replacement Costs - Entry'!O16="Y",((($B15*$D15)*((1+$B$5)^E$7))*(1/((1+$F$5)^E$7))),0)), "") | F15: =IF($A15<>"", (IF('Replacement Costs - Entry'!P16="Y",((($B15*$D15)*((1+$B$5)^F$7))*(1/((1+$F$5)^F$7))),0)), "") | G15: =IF($A15<>"", (IF('Replacement Costs - Entry'!Q16="Y",((($B15*$D15)*((1+$B$5)^G$7))*(1/((1+$F$5)^G$7))),0)), "") | H15: =IF($A15<>"", (IF('Replacement Costs - Entry'!R16="Y",((($B15*$D15)*((1+$B$5)^H$7))*(1/((1+$F$5)^H$7))),0)), "") | I15: =IF($A15<>"", (IF('Replacement Costs - Entry'!S16="Y",((($B15*$D15)*((1+$B$5)^I$7))*(1/((1+$F$5)^I$7))),0)), "")
A16: =IF('Capital Costs'!A17<>"", 'Capital Costs'!A17, "") | B16: =IF('Capital Costs'!B17<>"", 'Capital Costs'!B17, "") | C16: =IF('Capital Costs'!C17<>"", 'Capital Costs'!C17, "") | D16: =IF('Capital Costs'!D17<>"", 'Capital Costs'!D17, "") | E16: =IF($A16<>"", (IF('Replacement Costs - Entry'!O17="Y",((($B16*$D16)*((1+$B$5)^E$7))*(1/((1+$F$5)^E$7))),0)), "") | F16: =IF($A16<>"", (IF('Replacement Costs - Entry'!P17="Y",((($B16*$D16)*((1+$B$5)^F$7))*(1/((1+$F$5)^F$7))),0)), "") | G16: =IF($A16<>"", (IF('Replacement Costs - Entry'!Q17="Y",((($B16*$D16)*((1+$B$5)^G$7))*(1/((1+$F$5)^G$7))),0)), "") | H16: =IF($A16<>"", (IF('Replacement Costs - Entry'!R17="Y",((($B16*$D16)*((1+$B$5)^H$7))*(1/((1+$F$5)^H$7))),0)), "") | I16: =IF($A16<>"", (IF('Replacement Costs - Entry'!S17="Y",((($B16*$D16)*((1+$B$5)^I$7))*(1/((1+$F$5)^I$7))),0)), "")
A17: =IF('Capital Costs'!A18<>"", 'Capital Costs'!A18, "") | B17: =IF('Capital Costs'!B18<>"", 'Capital Costs'!B18, "") | C17: =IF('Capital Costs'!C18<>"", 'Capital Costs'!C18, "") | D17: =IF('Capital Costs'!D18<>"", 'Capital Costs'!D18, "") | E17: =IF($A17<>"", (IF('Replacement Costs - Entry'!O18="Y",((($B17*$D17)*((1+$B$5)^E$7))*(1/((1+$F$5)^E$7))),0)), "") | F17: =IF($A17<>"", (IF('Replacement Costs - Entry'!P18="Y",((($B17*$D17)*((1+$B$5)^F$7))*(1/((1+$F$5)^F$7))),0)), "") | G17: =IF($A17<>"", (IF('Replacement Costs - Entry'!Q18="Y",((($B17*$D17)*((1+$B$5)^G$7))*(1/((1+$F$5)^G$7))),0)), "") | H17: =IF($A17<>"", (IF('Replacement Costs - Entry'!R18="Y",((($B17*$D17)*((1+$B$5)^H$7))*(1/((1+$F$5)^H$7))),0)), "") | I17: =IF($A17<>"", (IF('Replacement Costs - Entry'!S18="Y",((($B17*$D17)*((1+$B$5)^I$7))*(1/((1+$F$5)^I$7))),0)), "")
A18: =IF('Capital Costs'!A19<>"", 'Capital Costs'!A19, "") | B18: =IF('Capital Costs'!B19<>"", 'Capital Costs'!B19, "") | C18: =IF('Capital Costs'!C19<>"", 'Capital Costs'!C19, "") | D18: =IF('Capital Costs'!D19<>"", 'Capital Costs'!D19, "") | E18: =IF($A18<>"", (IF('Replacement Costs - Entry'!O19="Y",((($B18*$D18)*((1+$B$5)^E$7))*(1/((1+$F$5)^E$7))),0)), "") | F18: =IF($A18<>"", (IF('Replacement Costs - Entry'!P19="Y",((($B18*$D18)*((1+$B$5)^F$7))*(1/((1+$F$5)^F$7))),0)), "") | G18: =IF($A18<>"", (IF('Replacement Costs - Entry'!Q19="Y",((($B18*$D18)*((1+$B$5)^G$7))*(1/((1+$F$5)^G$7))),0)), "") | H18: =IF($A18<>"", (IF('Replacement Costs - Entry'!R19="Y",((($B18*$D18)*((1+$B$5)^H$7))*(1/((1+$F$5)^H$7))),0)), "") | I18: =IF($A18<>"", (IF('Replacement Costs - Entry'!S19="Y",((($B18*$D18)*((1+$B$5)^I$7))*(1/((1+$F$5)^I$7))),0)), "")
A19: =IF('Capital Costs'!A20<>"", 'Capital Costs'!A20, "") | B19: =IF('Capital Costs'!B20<>"", 'Capital Costs'!B20, "") | C19: =IF('Capital Costs'!C20<>"", 'Capital Costs'!C20, "") | D19: =IF('Capital Costs'!D20<>"", 'Capital Costs'!D20, "") | E19: =IF($A19<>"", (IF('Replacement Costs - Entry'!O20="Y",((($B19*$D19)*((1+$B$5)^E$7))*(1/((1+$F$5)^E$7))),0)), "") | F19: =IF($A19<>"", (IF('Replacement Costs - Entry'!P20="Y",((($B19*$D19)*((1+$B$5)^F$7))*(1/((1+$F$5)^F$7))),0)), "") | G19: =IF($A19<>"", (IF('Replacement Costs - Entry'!Q20="Y",((($B19*$D19)*((1+$B$5)^G$7))*(1/((1+$F$5)^G$7))),0)), "") | H19: =IF($A19<>"", (IF('Replacement Costs - Entry'!R20="Y",((($B19*$D19)*((1+$B$5)^H$7))*(1/((1+$F$5)^H$7))),0)), "") | I19: =IF($A19<>"", (IF('Replacement Costs - Entry'!S20="Y",((($B19*$D19)*((1+$B$5)^I$7))*(1/((1+$F$5)^I$7))),0)), "")
... A36: =IF('Capital Costs'!A37<>"", 'Capital Costs'!A37, "") | B36: =IF('Capital Costs'!B37<>"", 'Capital Costs'!B37, "") | C36: =IF('Capital Costs'!C37<>"", 'Capital Costs'!C37, "") | D36: =IF('Capital Costs'!D37<>"", 'Capital Costs'!D37, "") | E36: =IF($A36<>"", (IF('Replacement Costs - Entry'!O37="Y",((($B36*$D36)*((1+$B$5)^E$7))*(1/((1+$F$5)^E$7))),0)), "") | F36: =IF($A36<>"", (IF('Replacement Costs - Entry'!P37="Y",((($B36*$D36)*((1+$B$5)^F$7))*(1/((1+$F$5)^F$7))),0)), "") | G36: =IF($A36<>"", (IF('Replacement Costs - Entry'!Q37="Y",((($B36*$D36)*((1+$B$5)^G$7))*(1/((1+$F$5)^G$7))),0)), "") | H36: =IF($A36<>"", (IF('Replacement Costs - Entry'!R37="Y",((($B36*$D36)*((1+$B$5)^H$7))*(1/((1+$F$5)^H$7))),0)), "") | I36: =IF($A36<>"", (IF('Replacement Costs - Entry'!S37="Y",((($B36*$D36)*((1+$B$5)^I$7))*(1/((1+$F$5)^I$7))),0)), "")
D37: Total Present Value of Replacement Costs (Years 6 to 10): | E37: =SUM(E8:E36) -> 0 | F37: =SUM(F8:F36) -> 0 | G37: =SUM(G8:G36) -> 0 | H37: =SUM(H8:H36) -> 0 | I37: =SUM(I8:I36) -> 0

Sheet Replace Costs-Results 11-15
A1: Table 5.2.5. Replacement Costs (Years 11 to 15)
A2: =Input!B4 -> 0
A3: =Input!B5 -> 0
A4: ='Capital Costs'!B6 -> 0
A5: ='Replace Costs-Results 6-10'!A5 -> Current Inflation Rate based on Construction Cost Index: | B5: ='Replace Costs-Results 6-10'!B5 -> 0.020671835 | E5: EPA Discount Rate: | F5: ='Replace Costs-Results 6-10'!F5 -> 0.04875
E6: Present Value of Replacement Costs in Year:
A7: Component | B7: Unit Cost | C7: Unit | D7: Quantity | E7: 11 | F7: 12 | G7: 13 | H7: 14 | I7: 15
A8: =IF('Capital Costs'!A9<>"", 'Capital Costs'!A9, "") | B8: =IF('Capital Costs'!B9<>"", 'Capital Costs'!B9, "") | C8: =IF('Capital Costs'!C9<>"", 'Capital Costs'!C9, "") | D8: =IF('Capital Costs'!D9<>"", 'Capital Costs'!D9, "") | E8: =IF($A8<>"", (IF('Replacement Costs - Entry'!T9="Y",((($B8*$D8)*((1+$B$5)^E$7))*(1/((1+$F$5)^E$7))),0)), "") | F8: =IF($A8<>"", (IF('Replacement Costs - Entry'!U9="Y",((($B8*$D8)*((1+$B$5)^F$7))*(1/((1+$F$5)^F$7))),0)), "") | G8: =IF($A8<>"", (IF('Replacement Costs - Entry'!V9="Y",((($B8*$D8)*((1+$B$5)^G$7))*(1/((1+$F$5)^G$7))),0)), "") | H8: =IF($A8<>"", (IF('Replacement Costs - Entry'!W9="Y",((($B8*$D8)*((1+$B$5)^H$7))*(1/((1+$F$5)^H$7))),0)), "") | I8: =IF($A8<>"", (IF('Replacement Costs - Entry'!X9="Y",((($B8*$D8)*((1+$B$5)^I$7))*(1/((1+$F$5)^I$7))),0)), "")
A9: =IF('Capital Costs'!A10<>"", 'Capital Costs'!A10, "") | B9: =IF('Capital Costs'!B10<>"", 'Capital Costs'!B10, "") | C9: =IF('Capital Costs'!C10<>"", 'Capital Costs'!C10, "") | D9: =IF('Capital Costs'!D10<>"", 'Capital Costs'!D10, "") | E9: =IF($A9<>"", (IF('Replacement Costs - Entry'!T10="Y",((($B9*$D9)*((1+$B$5)^E$7))*(1/((1+$F$5)^E$7))),0)), "") | F9: =IF($A9<>"", (IF('Replacement Costs - Entry'!U10="Y",((($B9*$D9)*((1+$B$5)^F$7))*(1/((1+$F$5)^F$7))),0)), "") | G9: =IF($A9<>"", (IF('Replacement Costs - Entry'!V10="Y",((($B9*$D9)*((1+$B$5)^G$7))*(1/((1+$F$5)^G$7))),0)), "") | H9: =IF($A9<>"", (IF('Replacement Costs - Entry'!W10="Y",((($B9*$D9)*((1+$B$5)^H$7))*(1/((1+$F$5)^H$7))),0)), "") | I9: =IF($A9<>"", (IF('Replacement Costs - Entry'!X10="Y",((($B9*$D9)*((1+$B$5)^I$7))*(1/((1+$F$5)^I$7))),0)), "")
A10: =IF('Capital Costs'!A11<>"", 'Capital Costs'!A11, "") | B10: =IF('Capital Costs'!B11<>"", 'Capital Costs'!B11, "") | C10: =IF('Capital Costs'!C11<>"", 'Capital Costs'!C11, "") | D10: =IF('Capital Costs'!D11<>"", 'Capital Costs'!D11, "") | E10: =IF($A10<>"", (IF('Replacement Costs - Entry'!T11="Y",((($B10*$D10)*((1+$B$5)^E$7))*(1/((1+$F$5)^E$7))),0)), "") | F10: =IF($A10<>"", (IF('Replacement Costs - Entry'!U11="Y",((($B10*$D10)*((1+$B$5)^F$7))*(1/((1+$F$5)^F$7))),0)), "") | G10: =IF($A10<>"", (IF('Replacement Costs - Entry'!V11="Y",((($B10*$D10)*((1+$B$5)^G$7))*(1/((1+$F$5)^G$7))),0)), "") | H10: =IF($A10<>"", (IF('Replacement Costs - Entry'!W11="Y",((($B10*$D10)*((1+$B$5)^H$7))*(1/((1+$F$5)^H$7))),0)), "") | I10: =IF($A10<>"", (IF('Replacement Costs - Entry'!X11="Y",((($B10*$D10)*((1+$B$5)^I$7))*(1/((1+$F$5)^I$7))),0)), "")
A11: =IF('Capital Costs'!A12<>"", 'Capital Costs'!A12, "") | B11: =IF('Capital Costs'!B12<>"", 'Capital Costs'!B12, "") | C11: =IF('Capital Costs'!C12<>"", 'Capital Costs'!C12, "") | D11: =IF('Capital Costs'!D12<>"", 'Capital Costs'!D12, "") | E11: =IF($A11<>"", (IF('Replacement Costs - Entry'!T12="Y",((($B11*$D11)*((1+$B$5)^E$7))*(1/((1+$F$5)^E$7))),0)), "") | F11: =IF($A11<>"", (IF('Replacement Costs - Entry'!U12="Y",((($B11*$D11)*((1+$B$5)^F$7))*(1/((1+$F$5)^F$7))),0)), "") | G11: =IF($A11<>"", (IF('Replacement Costs - Entry'!V12="Y",((($B11*$D11)*((1+$B$5)^G$7))*(1/((1+$F$5)^G$7))),0)), "") | H11: =IF($A11<>"", (IF('Replacement Costs - Entry'!W12="Y",((($B11*$D11)*((1+$B$5)^H$7))*(1/((1+$F$5)^H$7))),0)), "") | I11: =IF($A11<>"", (IF('Replacement Costs - Entry'!X12="Y",((($B11*$D11)*((1+$B$5)^I$7))*(1/((1+$F$5)^I$7))),0)), "")
A12: =IF('Capital Costs'!A13<>"", 'Capital Costs'!A13, "") | B12: =IF('Capital Costs'!B13<>"", 'Capital Costs'!B13, "") | C12: =IF('Capital Costs'!C13<>"", 'Capital Costs'!C13, "") | D12: =IF('Capital Costs'!D13<>"", 'Capital Costs'!D13, "") | E12: =IF($A12<>"", (IF('Replacement Costs - Entry'!T13="Y",((($B12*$D12)*((1+$B$5)^E$7))*(1/((1+$F$5)^E$7))),0)), "") | F12: =IF($A12<>"", (IF('Replacement Costs - Entry'!U13="Y",((($B12*$D12)*((1+$B$5)^F$7))*(1/((1+$F$5)^F$7))),0)), "") | G12: =IF($A12<>"", (IF('Replacement Costs - Entry'!V13="Y",((($B12*$D12)*((1+$B$5)^G$7))*(1/((1+$F$5)^G$7))),0)), "") | H12: =IF($A12<>"", (IF('Replacement Costs - Entry'!W13="Y",((($B12*$D12)*((1+$B$5)^H$7))*(1/((1+$F$5)^H$7))),0)), "") | I12: =IF($A12<>"", (IF('Replacement Costs - Entry'!X13="Y",((($B12*$D12)*((1+$B$5)^I$7))*(1/((1+$F$5)^I$7))),0)), "")
A13: =IF('Capital Costs'!A14<>"", 'Capital Costs'!A14, "") | B13: =IF('Capital Costs'!B14<>"", 'Capital Costs'!B14, "") | C13: =IF('Capital Costs'!C14<>"", 'Capital Costs'!C14, "") | D13: =IF('Capital Costs'!D14<>"", 'Capital Costs'!D14, "") | E13: =IF($A13<>"", (IF('Replacement Costs - Entry'!T14="Y",((($B13*$D13)*((1+$B$5)^E$7))*(1/((1+$F$5)^E$7))),0)), "") | F13: =IF($A13<>"", (IF('Replacement Costs - Entry'!U14="Y",((($B13*$D13)*((1+$B$5)^F$7))*(1/((1+$F$5)^F$7))),0)), "") | G13: =IF($A13<>"", (IF('Replacement Costs - Entry'!V14="Y",((($B13*$D13)*((1+$B$5)^G$7))*(1/((1+$F$5)^G$7))),0)), "") | H13: =IF($A13<>"", (IF('Replacement Costs - Entry'!W14="Y",((($B13*$D13)*((1+$B$5)^H$7))*(1/((1+$F$5)^H$7))),0)), "") | I13: =IF($A13<>"", (IF('Replacement Costs - Entry'!X14="Y",((($B13*$D13)*((1+$B$5)^I$7))*(1/((1+$F$5)^I$7))),0)), "")
A14: =IF('Capital Costs'!A15<>"", 'Capital Costs'!A15, "") | B14: =IF('Capital Costs'!B15<>"", 'Capital Costs'!B15, "") | C14: =IF('Capital Costs'!C15<>"", 'Capital Costs'!C15, "") | D14: =IF('Capital Costs'!D15<>"", 'Capital Costs'!D15, "") | E14: =IF($A14<>"", (IF('Replacement Costs - Entry'!T15="Y",((($B14*$D14)*((1+$B$5)^E$7))*(1/((1+$F$5)^E$7))),0)), "") | F14: =IF($A14<>"", (IF('Replacement Costs - Entry'!U15="Y",((($B14*$D14)*((1+$B$5)^F$7))*(1/((1+$F$5)^F$7))),0)), "") | G14: =IF($A14<>"", (IF('Replacement Costs - Entry'!V15="Y",((($B14*$D14)*((1+$B$5)^G$7))*(1/((1+$F$5)^G$7))),0)), "") | H14: =IF($A14<>"", (IF('Replacement Costs - Entry'!W15="Y",((($B14*$D14)*((1+$B$5)^H$7))*(1/((1+$F$5)^H$7))),0)), "") | I14: =IF($A14<>"", (IF('Replacement Costs - Entry'!X15="Y",((($B14*$D14)*((1+$B$5)^I$7))*(1/((1+$F$5)^I$7))),0)), "")
A15: =IF('Capital Costs'!A16<>"", 'Capital Costs'!A16, "") | B15: =IF('Capital Costs'!B16<>"", 'Capital Costs'!B16, "") | C15: =IF('Capital Costs'!C16<>"", 'Capital Costs'!C16, "") | D15: =IF('Capital Costs'!D16<>"", 'Capital Costs'!D16, "") | E15: =IF($A15<>"", (IF('Replacement Costs - Entry'!T16="Y",((($B15*$D15)*((1+$B$5)^E$7))*(1/((1+$F$5)^E$7))),0)), "") | F15: =IF($A15<>"", (IF('Replacement Costs - Entry'!U16="Y",((($B15*$D15)*((1+$B$5)^F$7))*(1/((1+$F$5)^F$7))),0)), "") | G15: =IF($A15<>"", (IF('Replacement Costs - Entry'!V16="Y",((($B15*$D15)*((1+$B$5)^G$7))*(1/((1+$F$5)^G$7))),0)), "") | H15: =IF($A15<>"", (IF('Replacement Costs - Entry'!W16="Y",((($B15*$D15)*((1+$B$5)^H$7))*(1/((1+$F$5)^H$7))),0)), "") | I15: =IF($A15<>"", (IF('Replacement Costs - Entry'!X16="Y",((($B15*$D15)*((1+$B$5)^I$7))*(1/((1+$F$5)^I$7))),0)), "")
A16: =IF('Capital Costs'!A17<>"", 'Capital Costs'!A17, "") | B16: =IF('Capital Costs'!B17<>"", 'Capital Costs'!B17, "") | C16: =IF('Capital Costs'!C17<>"", 'Capital Costs'!C17, "") | D16: =IF('Capital Costs'!D17<>"", 'Capital Costs'!D17, "") | E16: =IF($A16<>"", (IF('Replacement Costs - Entry'!T17="Y",((($B16*$D16)*((1+$B$5)^E$7))*(1/((1+$F$5)^E$7))),0)), "") | F16: =IF($A16<>"", (IF('Replacement Costs - Entry'!U17="Y",((($B16*$D16)*((1+$B$5)^F$7))*(1/((1+$F$5)^F$7))),0)), "") | G16: =IF($A16<>"", (IF('Replacement Costs - Entry'!V17="Y",((($B16*$D16)*((1+$B$5)^G$7))*(1/((1+$F$5)^G$7))),0)), "") | H16: =IF($A16<>"", (IF('Replacement Costs - Entry'!W17="Y",((($B16*$D16)*((1+$B$5)^H$7))*(1/((1+$F$5)^H$7))),0)), "") | I16: =IF($A16<>"", (IF('Replacement Costs - Entry'!X17="Y",((($B16*$D16)*((1+$B$5)^I$7))*(1/((1+$F$5)^I$7))),0)), "")
A17: =IF('Capital Costs'!A18<>"", 'Capital Costs'!A18, "") | B17: =IF('Capital Costs'!B18<>"", 'Capital Costs'!B18, "") | C17: =IF('Capital Costs'!C18<>"", 'Capital Costs'!C18, "") | D17: =IF('Capital Costs'!D18<>"", 'Capital Costs'!D18, "") | E17: =IF($A17<>"", (IF('Replacement Costs - Entry'!T18="Y",((($B17*$D17)*((1+$B$5)^E$7))*(1/((1+$F$5)^E$7))),0)), "") | F17: =IF($A17<>"", (IF('Replacement Costs - Entry'!U18="Y",((($B17*$D17)*((1+$B$5)^F$7))*(1/((1+$F$5)^F$7))),0)), "") | G17: =IF($A17<>"", (IF('Replacement Costs - Entry'!V18="Y",((($B17*$D17)*((1+$B$5)^G$7))*(1/((1+$F$5)^G$7))),0)), "") | H17: =IF($A17<>"", (IF('Replacement Costs - Entry'!W18="Y",((($B17*$D17)*((1+$B$5)^H$7))*(1/((1+$F$5)^H$7))),0)), "") | I17: =IF($A17<>"", (IF('Replacement Costs - Entry'!X18="Y",((($B17*$D17)*((1+$B$5)^I$7))*(1/((1+$F$5)^I$7))),0)), "")
A18: =IF('Capital Costs'!A19<>"", 'Capital Costs'!A19, "") | B18: =IF('Capital Costs'!B19<>"", 'Capital Costs'!B19, "") | C18: =IF('Capital Costs'!C19<>"", 'Capital Costs'!C19, "") | D18: =IF('Capital Costs'!D19<>"", 'Capital Costs'!D19, "") | E18: =IF($A18<>"", (IF('Replacement Costs - Entry'!T19="Y",((($B18*$D18)*((1+$B$5)^E$7))*(1/((1+$F$5)^E$7))),0)), "") | F18: =IF($A18<>"", (IF('Replacement Costs - Entry'!U19="Y",((($B18*$D18)*((1+$B$5)^F$7))*(1/((1+$F$5)^F$7))),0)), "") | G18: =IF($A18<>"", (IF('Replacement Costs - Entry'!V19="Y",((($B18*$D18)*((1+$B$5)^G$7))*(1/((1+$F$5)^G$7))),0)), "") | H18: =IF($A18<>"", (IF('Replacement Costs - Entry'!W19="Y",((($B18*$D18)*((1+$B$5)^H$7))*(1/((1+$F$5)^H$7))),0)), "") | I18: =IF($A18<>"", (IF('Replacement Costs - Entry'!X19="Y",((($B18*$D18)*((1+$B$5)^I$7))*(1/((1+$F$5)^I$7))),0)), "")
A19: =IF('Capital Costs'!A20<>"", 'Capital Costs'!A20, "") | B19: =IF('Capital Costs'!B20<>"", 'Capital Costs'!B20, "") | C19: =IF('Capital Costs'!C20<>"", 'Capital Costs'!C20, "") | D19: =IF('Capital Costs'!D20<>"", 'Capital Costs'!D20, "") | E19: =IF($A19<>"", (IF('Replacement Costs - Entry'!T20="Y",((($B19*$D19)*((1+$B$5)^E$7))*(1/((1+$F$5)^E$7))),0)), "") | F19: =IF($A19<>"", (IF('Replacement Costs - Entry'!U20="Y",((($B19*$D19)*((1+$B$5)^F$7))*(1/((1+$F$5)^F$7))),0)), "") | G19: =IF($A19<>"", (IF('Replacement Costs - Entry'!V20="Y",((($B19*$D19)*((1+$B$5)^G$7))*(1/((1+$F$5)^G$7))),0)), "") | H19: =IF($A19<>"", (IF('Replacement Costs - Entry'!W20="Y",((($B19*$D19)*((1+$B$5)^H$7))*(1/((1+$F$5)^H$7))),0)), "") | I19: =IF($A19<>"", (IF('Replacement Costs - Entry'!X20="Y",((($B19*$D19)*((1+$B$5)^I$7))*(1/((1+$F$5)^I$7))),0)), "")
... A36: =IF('Capital Costs'!A37<>"", 'Capital Costs'!A37, "") | B36: =IF('Capital Costs'!B37<>"", 'Capital Costs'!B37, "") | C36: =IF('Capital Costs'!C37<>"", 'Capital Costs'!C37, "") | D36: =IF('Capital Costs'!D37<>"", 'Capital Costs'!D37, "") | E36: =IF($A36<>"", (IF('Replacement Costs - Entry'!T37="Y",((($B36*$D36)*((1+$B$5)^E$7))*(1/((1+$F$5)^E$7))),0)), "") | F36: =IF($A36<>"", (IF('Replacement Costs - Entry'!U37="Y",((($B36*$D36)*((1+$B$5)^F$7))*(1/((1+$F$5)^F$7))),0)), "") | G36: =IF($A36<>"", (IF('Replacement Costs - Entry'!V37="Y",((($B36*$D36)*((1+$B$5)^G$7))*(1/((1+$F$5)^G$7))),0)), "") | H36: =IF($A36<>"", (IF('Replacement Costs - Entry'!W37="Y",((($B36*$D36)*((1+$B$5)^H$7))*(1/((1+$F$5)^H$7))),0)), "") | I36: =IF($A36<>"", (IF('Replacement Costs - Entry'!X37="Y",((($B36*$D36)*((1+$B$5)^I$7))*(1/((1+$F$5)^I$7))),0)), "")
D37: Total Present Value of Replacement Costs (Years 11 to 15): | E37: =SUM(E8:E36) -> 0 | F37: =SUM(F8:F36) -> 0 | G37: =SUM(G8:G36) -> 0 | H37: =SUM(H8:H36) -> 0 | I37: =SUM(I8:I36) -> 0

Sheet Replace Costs-Results 16-20
A1: Table 5.2.6. Replacement Costs (Years 16 to 20)
A2: =Input!B4 -> 0
A3: =Input!B5 -> 0
A4: ='Capital Costs'!B6 -> 0
A5: ='Replace Costs-Results 11-15'!A5 -> Current Inflation Rate based on Construction Cost Index: | B5: ='Replace Costs-Results 11-15'!B5 -> 0.020671835 | E5: EPA Discount Rate: | F5: ='Replace Costs-Results 11-15'!F5 -> 0.04875
E6: Present Value of Replacement Costs in Year:
A7: Component | B7: Unit Cost | C7: Unit | D7: Quantity | E7: 16 | F7: 17 | G7: 18 | H7: 19 | I7: 20
A8: =IF('Capital Costs'!A9<>"", 'Capital Costs'!A9, "") | B8: =IF('Capital Costs'!B9<>"", 'Capital Costs'!B9, "") | C8: =IF('Capital Costs'!C9<>"", 'Capital Costs'!C9, "") | D8: =IF('Capital Costs'!D9<>"", 'Capital Costs'!D9, "") | E8: =IF($A8<>"", (IF('Replacement Costs - Entry'!Y9="Y",((($B8*$D8)*((1+$B$5)^E$7))*(1/((1+$F$5)^E$7))),0)), "") | F8: =IF($A8<>"", (IF('Replacement Costs - Entry'!Z9="Y",((($B8*$D8)*((1+$B$5)^F$7))*(1/((1+$F$5)^F$7))),0)), "") | G8: =IF($A8<>"", (IF('Replacement Costs - Entry'!AA9="Y",((($B8*$D8)*((1+$B$5)^G$7))*(1/((1+$F$5)^G$7))),0)), "") | H8: =IF($A8<>"", (IF('Replacement Costs - Entry'!AB9="Y",((($B8*$D8)*((1+$B$5)^H$7))*(1/((1+$F$5)^H$7))),0)), "") | I8: =IF($A8<>"", (IF('Replacement Costs - Entry'!AC9="Y",((($B8*$D8)*((1+$B$5)^I$7))*(1/((1+$F$5)^I$7))),0)), "")
A9: =IF('Capital Costs'!A10<>"", 'Capital Costs'!A10, "") | B9: =IF('Capital Costs'!B10<>"", 'Capital Costs'!B10, "") | C9: =IF('Capital Costs'!C10<>"", 'Capital Costs'!C10, "") | D9: =IF('Capital Costs'!D10<>"", 'Capital Costs'!D10, "") | E9: =IF($A9<>"", (IF('Replacement Costs - Entry'!Y10="Y",((($B9*$D9)*((1+$B$5)^E$7))*(1/((1+$F$5)^E$7))),0)), "") | F9: =IF($A9<>"", (IF('Replacement Costs - Entry'!Z10="Y",((($B9*$D9)*((1+$B$5)^F$7))*(1/((1+$F$5)^F$7))),0)), "") | G9: =IF($A9<>"", (IF('Replacement Costs - Entry'!AA10="Y",((($B9*$D9)*((1+$B$5)^G$7))*(1/((1+$F$5)^G$7))),0)), "") | H9: =IF($A9<>"", (IF('Replacement Costs - Entry'!AB10="Y",((($B9*$D9)*((1+$B$5)^H$7))*(1/((1+$F$5)^H$7))),0)), "") | I9: =IF($A9<>"", (IF('Replacement Costs - Entry'!AC10="Y",((($B9*$D9)*((1+$B$5)^I$7))*(1/((1+$F$5)^I$7))),0)), "")
A10: =IF('Capital Costs'!A11<>"", 'Capital Costs'!A11, "") | B10: =IF('Capital Costs'!B11<>"", 'Capital Costs'!B11, "") | C10: =IF('Capital Costs'!C11<>"", 'Capital Costs'!C11, "") | D10: =IF('Capital Costs'!D11<>"", 'Capital Costs'!D11, "") | E10: =IF($A10<>"", (IF('Replacement Costs - Entry'!Y11="Y",((($B10*$D10)*((1+$B$5)^E$7))*(1/((1+$F$5)^E$7))),0)), "") | F10: =IF($A10<>"", (IF('Replacement Costs - Entry'!Z11="Y",((($B10*$D10)*((1+$B$5)^F$7))*(1/((1+$F$5)^F$7))),0)), "") | G10: =IF($A10<>"", (IF('Replacement Costs - Entry'!AA11="Y",((($B10*$D10)*((1+$B$5)^G$7))*(1/((1+$F$5)^G$7))),0)), "") | H10: =IF($A10<>"", (IF('Replacement Costs - Entry'!AB11="Y",((($B10*$D10)*((1+$B$5)^H$7))*(1/((1+$F$5)^H$7))),0)), "") | I10: =IF($A10<>"", (IF('Replacement Costs - Entry'!AC11="Y",((($B10*$D10)*((1+$B$5)^I$7))*(1/((1+$F$5)^I$7))),0)), "")
A11: =IF('Capital Costs'!A12<>"", 'Capital Costs'!A12, "") | B11: =IF('Capital Costs'!B12<>"", 'Capital Costs'!B12, "") | C11: =IF('Capital Costs'!C12<>"", 'Capital Costs'!C12, "") | D11: =IF('Capital Costs'!D12<>"", 'Capital Costs'!D12, "") | E11: =IF($A11<>"", (IF('Replacement Costs - Entry'!Y12="Y",((($B11*$D11)*((1+$B$5)^E$7))*(1/((1+$F$5)^E$7))),0)), "") | F11: =IF($A11<>"", (IF('Replacement Costs - Entry'!Z12="Y",((($B11*$D11)*((1+$B$5)^F$7))*(1/((1+$F$5)^F$7))),0)), "") | G11: =IF($A11<>"", (IF('Replacement Costs - Entry'!AA12="Y",((($B11*$D11)*((1+$B$5)^G$7))*(1/((1+$F$5)^G$7))),0)), "") | H11: =IF($A11<>"", (IF('Replacement Costs - Entry'!AB12="Y",((($B11*$D11)*((1+$B$5)^H$7))*(1/((1+$F$5)^H$7))),0)), "") | I11: =IF($A11<>"", (IF('Replacement Costs - Entry'!AC12="Y",((($B11*$D11)*((1+$B$5)^I$7))*(1/((1+$F$5)^I$7))),0)), "")
A12: =IF('Capital Costs'!A13<>"", 'Capital Costs'!A13, "") | B12: =IF('Capital Costs'!B13<>"", 'Capital Costs'!B13, "") | C12: =IF('Capital Costs'!C13<>"", 'Capital Costs'!C13, "") | D12: =IF('Capital Costs'!D13<>"", 'Capital Costs'!D13, "") | E12: =IF($A12<>"", (IF('Replacement Costs - Entry'!Y13="Y",((($B12*$D12)*((1+$B$5)^E$7))*(1/((1+$F$5)^E$7))),0)), "") | F12: =IF($A12<>"", (IF('Replacement Costs - Entry'!Z13="Y",((($B12*$D12)*((1+$B$5)^F$7))*(1/((1+$F$5)^F$7))),0)), "") | G12: =IF($A12<>"", (IF('Replacement Costs - Entry'!AA13="Y",((($B12*$D12)*((1+$B$5)^G$7))*(1/((1+$F$5)^G$7))),0)), "") | H12: =IF($A12<>"", (IF('Replacement Costs - Entry'!AB13="Y",((($B12*$D12)*((1+$B$5)^H$7))*(1/((1+$F$5)^H$7))),0)), "") | I12: =IF($A12<>"", (IF('Replacement Costs - Entry'!AC13="Y",((($B12*$D12)*((1+$B$5)^I$7))*(1/((1+$F$5)^I$7))),0)), "")
A13: =IF('Capital Costs'!A14<>"", 'Capital Costs'!A14, "") | B13: =IF('Capital Costs'!B14<>"", 'Capital Costs'!B14, "") | C13: =IF('Capital Costs'!C14<>"", 'Capital Costs'!C14, "") | D13: =IF('Capital Costs'!D14<>"", 'Capital Costs'!D14, "") | E13: =IF($A13<>"", (IF('Replacement Costs - Entry'!Y14="Y",((($B13*$D13)*((1+$B$5)^E$7))*(1/((1+$F$5)^E$7))),0)), "") | F13: =IF($A13<>"", (IF('Replacement Costs - Entry'!Z14="Y",((($B13*$D13)*((1+$B$5)^F$7))*(1/((1+$F$5)^F$7))),0)), "") | G13: =IF($A13<>"", (IF('Replacement Costs - Entry'!AA14="Y",((($B13*$D13)*((1+$B$5)^G$7))*(1/((1+$F$5)^G$7))),0)), "") | H13: =IF($A13<>"", (IF('Replacement Costs - Entry'!AB14="Y",((($B13*$D13)*((1+$B$5)^H$7))*(1/((1+$F$5)^H$7))),0)), "") | I13: =IF($A13<>"", (IF('Replacement Costs - Entry'!AC14="Y",((($B13*$D13)*((1+$B$5)^I$7))*(1/((1+$F$5)^I$7))),0)), "")
A14: =IF('Capital Costs'!A15<>"", 'Capital Costs'!A15, "") | B14: =IF('Capital Costs'!B15<>"", 'Capital Costs'!B15, "") | C14: =IF('Capital Costs'!C15<>"", 'Capital Costs'!C15, "") | D14: =IF('Capital Costs'!D15<>"", 'Capital Costs'!D15, "") | E14: =IF($A14<>"", (IF('Replacement Costs - Entry'!Y15="Y",((($B14*$D14)*((1+$B$5)^E$7))*(1/((1+$F$5)^E$7))),0)), "") | F14: =IF($A14<>"", (IF('Replacement Costs - Entry'!Z15="Y",((($B14*$D14)*((1+$B$5)^F$7))*(1/((1+$F$5)^F$7))),0)), "") | G14: =IF($A14<>"", (IF('Replacement Costs - Entry'!AA15="Y",((($B14*$D14)*((1+$B$5)^G$7))*(1/((1+$F$5)^G$7))),0)), "") | H14: =IF($A14<>"", (IF('Replacement Costs - Entry'!AB15="Y",((($B14*$D14)*((1+$B$5)^H$7))*(1/((1+$F$5)^H$7))),0)), "") | I14: =IF($A14<>"", (IF('Replacement Costs - Entry'!AC15="Y",((($B14*$D14)*((1+$B$5)^I$7))*(1/((1+$F$5)^I$7))),0)), "")
A15: =IF('Capital Costs'!A16<>"", 'Capital Costs'!A16, "") | B15: =IF('Capital Costs'!B16<>"", 'Capital Costs'!B16, "") | C15: =IF('Capital Costs'!C16<>"", 'Capital Costs'!C16, "") | D15: =IF('Capital Costs'!D16<>"", 'Capital Costs'!D16, "") | E15: =IF($A15<>"", (IF('Replacement Costs - Entry'!Y16="Y",((($B15*$D15)*((1+$B$5)^E$7))*(1/((1+$F$5)^E$7))),0)), "") | F15: =IF($A15<>"", (IF('Replacement Costs - Entry'!Z16="Y",((($B15*$D15)*((1+$B$5)^F$7))*(1/((1+$F$5)^F$7))),0)), "") | G15: =IF($A15<>"", (IF('Replacement Costs - Entry'!AA16="Y",((($B15*$D15)*((1+$B$5)^G$7))*(1/((1+$F$5)^G$7))),0)), "") | H15: =IF($A15<>"", (IF('Replacement Costs - Entry'!AB16="Y",((($B15*$D15)*((1+$B$5)^H$7))*(1/((1+$F$5)^H$7))),0)), "") | I15: =IF($A15<>"", (IF('Replacement Costs - Entry'!AC16="Y",((($B15*$D15)*((1+$B$5)^I$7))*(1/((1+$F$5)^I$7))),0)), "")
A16: =IF('Capital Costs'!A17<>"", 'Capital Costs'!A17, "") | B16: =IF('Capital Costs'!B17<>"", 'Capital Costs'!B17, "") | C16: =IF('Capital Costs'!C17<>"", 'Capital Costs'!C17, "") | D16: =IF('Capital Costs'!D17<>"", 'Capital Costs'!D17, "") | E16: =IF($A16<>"", (IF('Replacement Costs - Entry'!Y17="Y",((($B16*$D16)*((1+$B$5)^E$7))*(1/((1+$F$5)^E$7))),0)), "") | F16: =IF($A16<>"", (IF('Replacement Costs - Entry'!Z17="Y",((($B16*$D16)*((1+$B$5)^F$7))*(1/((1+$F$5)^F$7))),0)), "") | G16: =IF($A16<>"", (IF('Replacement Costs - Entry'!AA17="Y",((($B16*$D16)*((1+$B$5)^G$7))*(1/((1+$F$5)^G$7))),0)), "") | H16: =IF($A16<>"", (IF('Replacement Costs - Entry'!AB17="Y",((($B16*$D16)*((1+$B$5)^H$7))*(1/((1+$F$5)^H$7))),0)), "") | I16: =IF($A16<>"", (IF('Replacement Costs - Entry'!AC17="Y",((($B16*$D16)*((1+$B$5)^I$7))*(1/((1+$F$5)^I$7))),0)), "")
A17: =IF('Capital Costs'!A18<>"", 'Capital Costs'!A18, "") | B17: =IF('Capital Costs'!B18<>"", 'Capital Costs'!B18, "") | C17: =IF('Capital Costs'!C18<>"", 'Capital Costs'!C18, "") | D17: =IF('Capital Costs'!D18<>"", 'Capital Costs'!D18, "") | E17: =IF($A17<>"", (IF('Replacement Costs - Entry'!Y18="Y",((($B17*$D17)*((1+$B$5)^E$7))*(1/((1+$F$5)^E$7))),0)), "") | F17: =IF($A17<>"", (IF('Replacement Costs - Entry'!Z18="Y",((($B17*$D17)*((1+$B$5)^F$7))*(1/((1+$F$5)^F$7))),0)), "") | G17: =IF($A17<>"", (IF('Replacement Costs - Entry'!AA18="Y",((($B17*$D17)*((1+$B$5)^G$7))*(1/((1+$F$5)^G$7))),0)), "") | H17: =IF($A17<>"", (IF('Replacement Costs - Entry'!AB18="Y",((($B17*$D17)*((1+$B$5)^H$7))*(1/((1+$F$5)^H$7))),0)), "") | I17: =IF($A17<>"", (IF('Replacement Costs - Entry'!AC18="Y",((($B17*$D17)*((1+$B$5)^I$7))*(1/((1+$F$5)^I$7))),0)), "")
A18: =IF('Capital Costs'!A19<>"", 'Capital Costs'!A19, "") | B18: =IF('Capital Costs'!B19<>"", 'Capital Costs'!B19, "") | C18: =IF('Capital Costs'!C19<>"", 'Capital Costs'!C19, "") | D18: =IF('Capital Costs'!D19<>"", 'Capital Costs'!D19, "") | E18: =IF($A18<>"", (IF('Replacement Costs - Entry'!Y19="Y",((($B18*$D18)*((1+$B$5)^E$7))*(1/((1+$F$5)^E$7))),0)), "") | F18: =IF($A18<>"", (IF('Replacement Costs - Entry'!Z19="Y",((($B18*$D18)*((1+$B$5)^F$7))*(1/((1+$F$5)^F$7))),0)), "") | G18: =IF($A18<>"", (IF('Replacement Costs - Entry'!AA19="Y",((($B18*$D18)*((1+$B$5)^G$7))*(1/((1+$F$5)^G$7))),0)), "") | H18: =IF($A18<>"", (IF('Replacement Costs - Entry'!AB19="Y",((($B18*$D18)*((1+$B$5)^H$7))*(1/((1+$F$5)^H$7))),0)), "") | I18: =IF($A18<>"", (IF('Replacement Costs - Entry'!AC19="Y",((($B18*$D18)*((1+$B$5)^I$7))*(1/((1+$F$5)^I$7))),0)), "")
A19: =IF('Capital Costs'!A20<>"", 'Capital Costs'!A20, "") | B19: =IF('Capital Costs'!B20<>"", 'Capital Costs'!B20, "") | C19: =IF('Capital Costs'!C20<>"", 'Capital Costs'!C20, "") | D19: =IF('Capital Costs'!D20<>"", 'Capital Costs'!D20, "") | E19: =IF($A19<>"", (IF('Replacement Costs - Entry'!Y20="Y",((($B19*$D19)*((1+$B$5)^E$7))*(1/((1+$F$5)^E$7))),0)), "") | F19: =IF($A19<>"", (IF('Replacement Costs - Entry'!Z20="Y",((($B19*$D19)*((1+$B$5)^F$7))*(1/((1+$F$5)^F$7))),0)), "") | G19: =IF($A19<>"", (IF('Replacement Costs - Entry'!AA20="Y",((($B19*$D19)*((1+$B$5)^G$7))*(1/((1+$F$5)^G$7))),0)), "") | H19: =IF($A19<>"", (IF('Replacement Costs - Entry'!AB20="Y",((($B19*$D19)*((1+$B$5)^H$7))*(1/((1+$F$5)^H$7))),0)), "") | I19: =IF($A19<>"", (IF('Replacement Costs - Entry'!AC20="Y",((($B19*$D19)*((1+$B$5)^I$7))*(1/((1+$F$5)^I$7))),0)), "")
... A36: =IF('Capital Costs'!A37<>"", 'Capital Costs'!A37, "") | B36: =IF('Capital Costs'!B37<>"", 'Capital Costs'!B37, "") | C36: =IF('Capital Costs'!C37<>"", 'Capital Costs'!C37, "") | D36: =IF('Capital Costs'!D37<>"", 'Capital Costs'!D37, "") | E36: =IF($A36<>"", (IF('Replacement Costs - Entry'!Y37="Y",((($B36*$D36)*((1+$B$5)^E$7))*(1/((1+$F$5)^E$7))),0)), "") | F36: =IF($A36<>"", (IF('Replacement Costs - Entry'!Z37="Y",((($B36*$D36)*((1+$B$5)^F$7))*(1/((1+$F$5)^F$7))),0)), "") | G36: =IF($A36<>"", (IF('Replacement Costs - Entry'!AA37="Y",((($B36*$D36)*((1+$B$5)^G$7))*(1/((1+$F$5)^G$7))),0)), "") | H36: =IF($A36<>"", (IF('Replacement Costs - Entry'!AB37="Y",((($B36*$D36)*((1+$B$5)^H$7))*(1/((1+$F$5)^H$7))),0)), "") | I36: =IF($A36<>"", (IF('Replacement Costs - Entry'!AC37="Y",((($B36*$D36)*((1+$B$5)^I$7))*(1/((1+$F$5)^I$7))),0)), "")
D37: Total Present Value of Replacement Costs (Years 16 to 20): | E37: =SUM(E8:E36) -> 0 | F37: =SUM(F8:F36) -> 0 | G37: =SUM(G8:G36) -> 0 | H37: =SUM(H8:H36) -> 0 | I37: =SUM(I8:I36) -> 0
H38: Total Present Value of Replacement Costs (Life of Project): | I38: ='Replace Costs - Results 1-5'!E37+'Replace Costs - Results 1-5'!F37+'Replace Costs - Results 1-5'!G37+'Replace Costs - Results 1-5'!H37+'Replace Costs - Results 1-5'!I37+'Replace Costs-Results 6-10'!E37+'Replace Costs-Results 6-10'!F37+'Replace Costs-Results 6-10'!G37+'Replace Costs-Results 6-10'!H37+'Replace Costs-Results 6-10'!I37+'Replace Costs-Results 11-15'!E37+'Replace Costs-Results 11-15'!F37+'Replace Costs-Results 11-15'!G37+'Replace Costs-Results 11-15'!H37+'Replace Costs-Results 11-15'!I37+'Replace Costs-Results 16-20'!E37+'Replace Costs-Results 16-20'!F37+'Replace Costs-Results 16-20'!G37+'Replace Costs-Results 16-20'!H37+'Replace Costs-Results 16-20'!I37 -> 0

Sheet Yearly O&M Costs 1-10
A1: Table 5.2.7. Present Value of Operations and Maintenance Costs (Years 1-10)
A2: ='Capital Costs'!A3:E3 -> 0
A3: ='Capital Costs'!A4:E4 -> 0
A4: ='Capital Costs'!B6 -> 0
A5: Complete the cells shown in gray below.
A6: Current Inflation Rate Based on Municipal Cost Index: | B6: =('CCI-MCI'!B7-'CCI-MCI'!B6)/'CCI-MCI'!B6 -> 0.027598896 | M6: EPA Discount Rate: | N6: ='Replace Costs-Results 16-20'!F5 -> 0.04875
E7: Present Value of O&M Costs for Year:
A8: Component | B8: Unit Cost | C8: Unit | D8: Quantity | E8: 1 | F8: 2 | G8: 3 | H8: 4 | I8: 5 | J8: 6 | K8: 7 | L8: 8 | M8: 9 | N8: 10
E9: =IF($A9<>"", (($B9*$D9)*((1+$B$6)^E$8)*(1/((1+$N$6)^E$8))), "") | F9: =IF($A9<>"", (($B9*$D9)*((1+$B$6)^F$8)*(1/((1+$N$6)^F$8))), "") | G9: =IF($A9<>"", (($B9*$D9)*((1+$B$6)^G$8)*(1/((1+$N$6)^G$8))), "") | H9: =IF($A9<>"", (($B9*$D9)*((1+$B$6)^H$8)*(1/((1+$N$6)^H$8))), "") | I9: =IF($A9<>"", (($B9*$D9)*((1+$B$6)^I$8)*(1/((1+$N$6)^I$8))), "") | J9: =IF($A9<>"", (($B9*$D9)*((1+$B$6)^J$8)*(1/((1+$N$6)^J$8))), "") | K9: =IF($A9<>"", (($B9*$D9)*((1+$B$6)^K$8)*(1/((1+$N$6)^K$8))), "") | L9: =IF($A9<>"", (($B9*$D9)*((1+$B$6)^L$8)*(1/((1+$N$6)^L$8))), "") | ... N9: =IF($A9<>"", (($B9*$D9)*((1+$B$6)^N$8)*(1/((1+$N$6)^N$8))), "")
E10: =IF($A10<>"", (($B10*$D10)*((1+$B$6)^E$8)*(1/((1+$N$6)^E$8))), "") | F10: =IF($A10<>"", (($B10*$D10)*((1+$B$6)^F$8)*(1/((1+$N$6)^F$8))), "") | G10: =IF($A10<>"", (($B10*$D10)*((1+$B$6)^G$8)*(1/((1+$N$6)^G$8))), "") | H10: =IF($A10<>"", (($B10*$D10)*((1+$B$6)^H$8)*(1/((1+$N$6)^H$8))), "") | I10: =IF($A10<>"", (($B10*$D10)*((1+$B$6)^I$8)*(1/((1+$N$6)^I$8))), "") | J10: =IF($A10<>"", (($B10*$D10)*((1+$B$6)^J$8)*(1/((1+$N$6)^J$8))), "") | K10: =IF($A10<>"", (($B10*$D10)*((1+$B$6)^K$8)*(1/((1+$N$6)^K$8))), "") | L10: =IF($A10<>"", (($B10*$D10)*((1+$B$6)^L$8)*(1/((1+$N$6)^L$8))), "") | ... N10: =IF($A10<>"", (($B10*$D10)*((1+$B$6)^N$8)*(1/((1+$N$6)^N$8))), "")
E11: =IF($A11<>"", (($B11*$D11)*((1+$B$6)^E$8)*(1/((1+$N$6)^E$8))), "") | F11: =IF($A11<>"", (($B11*$D11)*((1+$B$6)^F$8)*(1/((1+$N$6)^F$8))), "") | G11: =IF($A11<>"", (($B11*$D11)*((1+$B$6)^G$8)*(1/((1+$N$6)^G$8))), "") | H11: =IF($A11<>"", (($B11*$D11)*((1+$B$6)^H$8)*(1/((1+$N$6)^H$8))), "") | I11: =IF($A11<>"", (($B11*$D11)*((1+$B$6)^I$8)*(1/((1+$N$6)^I$8))), "") | J11: =IF($A11<>"", (($B11*$D11)*((1+$B$6)^J$8)*(1/((1+$N$6)^J$8))), "") | K11: =IF($A11<>"", (($B11*$D11)*((1+$B$6)^K$8)*(1/((1+$N$6)^K$8))), "") | L11: =IF($A11<>"", (($B11*$D11)*((1+$B$6)^L$8)*(1/((1+$N$6)^L$8))), "") | ... N11: =IF($A11<>"", (($B11*$D11)*((1+$B$6)^N$8)*(1/((1+$N$6)^N$8))), "")
E12: =IF($A12<>"", (($B12*$D12)*((1+$B$6)^E$8)*(1/((1+$N$6)^E$8))), "") | F12: =IF($A12<>"", (($B12*$D12)*((1+$B$6)^F$8)*(1/((1+$N$6)^F$8))), "") | G12: =IF($A12<>"", (($B12*$D12)*((1+$B$6)^G$8)*(1/((1+$N$6)^G$8))), "") | H12: =IF($A12<>"", (($B12*$D12)*((1+$B$6)^H$8)*(1/((1+$N$6)^H$8))), "") | I12: =IF($A12<>"", (($B12*$D12)*((1+$B$6)^I$8)*(1/((1+$N$6)^I$8))), "") | J12: =IF($A12<>"", (($B12*$D12)*((1+$B$6)^J$8)*(1/((1+$N$6)^J$8))), "") | K12: =IF($A12<>"", (($B12*$D12)*((1+$B$6)^K$8)*(1/((1+$N$6)^K$8))), "") | L12: =IF($A12<>"", (($B12*$D12)*((1+$B$6)^L$8)*(1/((1+$N$6)^L$8))), "") | ... N12: =IF($A12<>"", (($B12*$D12)*((1+$B$6)^N$8)*(1/((1+$N$6)^N$8))), "")
E13: =IF($A13<>"", (($B13*$D13)*((1+$B$6)^E$8)*(1/((1+$N$6)^E$8))), "") | F13: =IF($A13<>"", (($B13*$D13)*((1+$B$6)^F$8)*(1/((1+$N$6)^F$8))), "") | G13: =IF($A13<>"", (($B13*$D13)*((1+$B$6)^G$8)*(1/((1+$N$6)^G$8))), "") | H13: =IF($A13<>"", (($B13*$D13)*((1+$B$6)^H$8)*(1/((1+$N$6)^H$8))), "") | I13: =IF($A13<>"", (($B13*$D13)*((1+$B$6)^I$8)*(1/((1+$N$6)^I$8))), "") | J13: =IF($A13<>"", (($B13*$D13)*((1+$B$6)^J$8)*(1/((1+$N$6)^J$8))), "") | K13: =IF($A13<>"", (($B13*$D13)*((1+$B$6)^K$8)*(1/((1+$N$6)^K$8))), "") | L13: =IF($A13<>"", (($B13*$D13)*((1+$B$6)^L$8)*(1/((1+$N$6)^L$8))), "") | ... N13: =IF($A13<>"", (($B13*$D13)*((1+$B$6)^N$8)*(1/((1+$N$6)^N$8))), "")
E14: =IF($A14<>"", (($B14*$D14)*((1+$B$6)^E$8)*(1/((1+$N$6)^E$8))), "") | F14: =IF($A14<>"", (($B14*$D14)*((1+$B$6)^F$8)*(1/((1+$N$6)^F$8))), "") | G14: =IF($A14<>"", (($B14*$D14)*((1+$B$6)^G$8)*(1/((1+$N$6)^G$8))), "") | H14: =IF($A14<>"", (($B14*$D14)*((1+$B$6)^H$8)*(1/((1+$N$6)^H$8))), "") | I14: =IF($A14<>"", (($B14*$D14)*((1+$B$6)^I$8)*(1/((1+$N$6)^I$8))), "") | J14: =IF($A14<>"", (($B14*$D14)*((1+$B$6)^J$8)*(1/((1+$N$6)^J$8))), "") | K14: =IF($A14<>"", (($B14*$D14)*((1+$B$6)^K$8)*(1/((1+$N$6)^K$8))), "") | L14: =IF($A14<>"", (($B14*$D14)*((1+$B$6)^L$8)*(1/((1+$N$6)^L$8))), "") | ... N14: =IF($A14<>"", (($B14*$D14)*((1+$B$6)^N$8)*(1/((1+$N$6)^N$8))), "")
E15: =IF($A15<>"", (($B15*$D15)*((1+$B$6)^E$8)*(1/((1+$N$6)^E$8))), "") | F15: =IF($A15<>"", (($B15*$D15)*((1+$B$6)^F$8)*(1/((1+$N$6)^F$8))), "") | G15: =IF($A15<>"", (($B15*$D15)*((1+$B$6)^G$8)*(1/((1+$N$6)^G$8))), "") | H15: =IF($A15<>"", (($B15*$D15)*((1+$B$6)^H$8)*(1/((1+$N$6)^H$8))), "") | I15: =IF($A15<>"", (($B15*$D15)*((1+$B$6)^I$8)*(1/((1+$N$6)^I$8))), "") | J15: =IF($A15<>"", (($B15*$D15)*((1+$B$6)^J$8)*(1/((1+$N$6)^J$8))), "") | K15: =IF($A15<>"", (($B15*$D15)*((1+$B$6)^K$8)*(1/((1+$N$6)^K$8))), "") | L15: =IF($A15<>"", (($B15*$D15)*((1+$B$6)^L$8)*(1/((1+$N$6)^L$8))), "") | ... N15: =IF($A15<>"", (($B15*$D15)*((1+$B$6)^N$8)*(1/((1+$N$6)^N$8))), "")
E16: =IF($A16<>"", (($B16*$D16)*((1+$B$6)^E$8)*(1/((1+$N$6)^E$8))), "") | F16: =IF($A16<>"", (($B16*$D16)*((1+$B$6)^F$8)*(1/((1+$N$6)^F$8))), "") | G16: =IF($A16<>"", (($B16*$D16)*((1+$B$6)^G$8)*(1/((1+$N$6)^G$8))), "") | H16: =IF($A16<>"", (($B16*$D16)*((1+$B$6)^H$8)*(1/((1+$N$6)^H$8))), "") | I16: =IF($A16<>"", (($B16*$D16)*((1+$B$6)^I$8)*(1/((1+$N$6)^I$8))), "") | J16: =IF($A16<>"", (($B16*$D16)*((1+$B$6)^J$8)*(1/((1+$N$6)^J$8))), "") | K16: =IF($A16<>"", (($B16*$D16)*((1+$B$6)^K$8)*(1/((1+$N$6)^K$8))), "") | L16: =IF($A16<>"", (($B16*$D16)*((1+$B$6)^L$8)*(1/((1+$N$6)^L$8))), "") | ... N16: =IF($A16<>"", (($B16*$D16)*((1+$B$6)^N$8)*(1/((1+$N$6)^N$8))), "")
E17: =IF($A17<>"", (($B17*$D17)*((1+$B$6)^E$8)*(1/((1+$N$6)^E$8))), "") | F17: =IF($A17<>"", (($B17*$D17)*((1+$B$6)^F$8)*(1/((1+$N$6)^F$8))), "") | G17: =IF($A17<>"", (($B17*$D17)*((1+$B$6)^G$8)*(1/((1+$N$6)^G$8))), "") | H17: =IF($A17<>"", (($B17*$D17)*((1+$B$6)^H$8)*(1/((1+$N$6)^H$8))), "") | I17: =IF($A17<>"", (($B17*$D17)*((1+$B$6)^I$8)*(1/((1+$N$6)^I$8))), "") | J17: =IF($A17<>"", (($B17*$D17)*((1+$B$6)^J$8)*(1/((1+$N$6)^J$8))), "") | K17: =IF($A17<>"", (($B17*$D17)*((1+$B$6)^K$8)*(1/((1+$N$6)^K$8))), "") | L17: =IF($A17<>"", (($B17*$D17)*((1+$B$6)^L$8)*(1/((1+$N$6)^L$8))), "") | ... N17: =IF($A17<>"", (($B17*$D17)*((1+$B$6)^N$8)*(1/((1+$N$6)^N$8))), "")
E18: =IF($A18<>"", (($B18*$D18)*((1+$B$6)^E$8)*(1/((1+$N$6)^E$8))), "") | F18: =IF($A18<>"", (($B18*$D18)*((1+$B$6)^F$8)*(1/((1+$N$6)^F$8))), "") | G18: =IF($A18<>"", (($B18*$D18)*((1+$B$6)^G$8)*(1/((1+$N$6)^G$8))), "") | H18: =IF($A18<>"", (($B18*$D18)*((1+$B$6)^H$8)*(1/((1+$N$6)^H$8))), "") | I18: =IF($A18<>"", (($B18*$D18)*((1+$B$6)^I$8)*(1/((1+$N$6)^I$8))), "") | J18: =IF($A18<>"", (($B18*$D18)*((1+$B$6)^J$8)*(1/((1+$N$6)^J$8))), "") | K18: =IF($A18<>"", (($B18*$D18)*((1+$B$6)^K$8)*(1/((1+$N$6)^K$8))), "") | L18: =IF($A18<>"", (($B18*$D18)*((1+$B$6)^L$8)*(1/((1+$N$6)^L$8))), "") | ... N18: =IF($A18<>"", (($B18*$D18)*((1+$B$6)^N$8)*(1/((1+$N$6)^N$8))), "")
E19: =IF($A19<>"", (($B19*$D19)*((1+$B$6)^E$8)*(1/((1+$N$6)^E$8))), "") | F19: =IF($A19<>"", (($B19*$D19)*((1+$B$6)^F$8)*(1/((1+$N$6)^F$8))), "") | G19: =IF($A19<>"", (($B19*$D19)*((1+$B$6)^G$8)*(1/((1+$N$6)^G$8))), "") | H19: =IF($A19<>"", (($B19*$D19)*((1+$B$6)^H$8)*(1/((1+$N$6)^H$8))), "") | I19: =IF($A19<>"", (($B19*$D19)*((1+$B$6)^I$8)*(1/((1+$N$6)^I$8))), "") | J19: =IF($A19<>"", (($B19*$D19)*((1+$B$6)^J$8)*(1/((1+$N$6)^J$8))), "") | K19: =IF($A19<>"", (($B19*$D19)*((1+$B$6)^K$8)*(1/((1+$N$6)^K$8))), "") | L19: =IF($A19<>"", (($B19*$D19)*((1+$B$6)^L$8)*(1/((1+$N$6)^L$8))), "") | ... N19: =IF($A19<>"", (($B19*$D19)*((1+$B$6)^N$8)*(1/((1+$N$6)^N$8))), "")
E20: =IF($A20<>"", (($B20*$D20)*((1+$B$6)^E$8)*(1/((1+$N$6)^E$8))), "") | F20: =IF($A20<>"", (($B20*$D20)*((1+$B$6)^F$8)*(1/((1+$N$6)^F$8))), "") | G20: =IF($A20<>"", (($B20*$D20)*((1+$B$6)^G$8)*(1/((1+$N$6)^G$8))), "") | H20: =IF($A20<>"", (($B20*$D20)*((1+$B$6)^H$8)*(1/((1+$N$6)^H$8))), "") | I20: =IF($A20<>"", (($B20*$D20)*((1+$B$6)^I$8)*(1/((1+$N$6)^I$8))), "") | J20: =IF($A20<>"", (($B20*$D20)*((1+$B$6)^J$8)*(1/((1+$N$6)^J$8))), "") | K20: =IF($A20<>"", (($B20*$D20)*((1+$B$6)^K$8)*(1/((1+$N$6)^K$8))), "") | L20: =IF($A20<>"", (($B20*$D20)*((1+$B$6)^L$8)*(1/((1+$N$6)^L$8))), "") | ... N20: =IF($A20<>"", (($B20*$D20)*((1+$B$6)^N$8)*(1/((1+$N$6)^N$8))), "")
... E31: =IF($A31<>"", (($B31*$D31)*((1+$B$6)^E$8)*(1/((1+$N$6)^E$8))), "") | F31: =IF($A31<>"", (($B31*$D31)*((1+$B$6)^F$8)*(1/((1+$N$6)^F$8))), "") | G31: =IF($A31<>"", (($B31*$D31)*((1+$B$6)^G$8)*(1/((1+$N$6)^G$8))), "") | H31: =IF($A31<>"", (($B31*$D31)*((1+$B$6)^H$8)*(1/((1+$N$6)^H$8))), "") | I31: =IF($A31<>"", (($B31*$D31)*((1+$B$6)^I$8)*(1/((1+$N$6)^I$8))), "") | J31: =IF($A31<>"", (($B31*$D31)*((1+$B$6)^J$8)*(1/((1+$N$6)^J$8))), "") | K31: =IF($A31<>"", (($B31*$D31)*((1+$B$6)^K$8)*(1/((1+$N$6)^K$8))), "") | L31: =IF($A31<>"", (($B31*$D31)*((1+$B$6)^L$8)*(1/((1+$N$6)^L$8))), "") | ... N31: =IF($A31<>"", (($B31*$D31)*((1+$B$6)^N$8)*(1/((1+$N$6)^N$8))), "")
D32: Total Present Value of Yearly O&M Expenses (Years 1-10): | E32: =SUM(E9:E31) -> 0 | F32: =SUM(F9:F31) -> 0 | G32: =SUM(G9:G31) -> 0 | H32: =SUM(H9:H31) -> 0 | I32: =SUM(I9:I31) -> 0 | J32: =SUM(J9:J31) -> 0 | K32: =SUM(K9:K31) -> 0 | L32: =SUM(L9:L31) -> 0 | ... N32: =SUM(N9:N31) -> 0
A35: i= | B35: 0.04875

Sheet Yearly O&M Costs 11-20
A1: Table 5.2.8. Present Value of Operations and Maintenance Costs (Years 11-20)
A2: ='Capital Costs'!A3:E3 -> 0
A3: ='Capital Costs'!A4:E4 -> 0
A4: ='Capital Costs'!B6 -> 0
A5: ='Yearly O&M Costs 1-10'!A6 -> Current Inflation Rate Based on Municipal Cost Index: | B5: ='Yearly O&M Costs 1-10'!B6 -> 0.027598896 | M5: EPA Discount Rate: | N5: ='Replace Costs-Results 16-20'!F5 -> 0.04875
E6: Present Value of O&M Costs for Year:
A7: Component | B7: Unit Cost | C7: Unit | D7: Quantity | E7: 11 | F7: 12 | G7: 13 | H7: 14 | I7: 15 | J7: 16 | K7: 17 | L7: 18 | M7: 19 | N7: 20
A8: =IF('Yearly O&M Costs 1-10'!A9<>"", 'Yearly O&M Costs 1-10'!A9, "") | B8: =IF('Yearly O&M Costs 1-10'!B9<>"", 'Yearly O&M Costs 1-10'!B9, "") | C8: =IF('Yearly O&M Costs 1-10'!C9<>"", 'Yearly O&M Costs 1-10'!C9, "") | D8: =IF('Yearly O&M Costs 1-10'!D9<>"", 'Yearly O&M Costs 1-10'!D9, "") | E8: =IF($A8<>"", (($B8*$D8)*((1+$B$5)^E$7)*(1/((1+$N$5)^E$7))), "") | F8: =IF($A8<>"", (($B8*$D8)*((1+$B$5)^F$7)*(1/((1+$N$5)^F$7))), "") | G8: =IF($A8<>"", (($B8*$D8)*((1+$B$5)^G$7)*(1/((1+$N$5)^G$7))), "") | H8: =IF($A8<>"", (($B8*$D8)*((1+$B$5)^H$7)*(1/((1+$N$5)^H$7))), "") | I8: =IF($A8<>"", (($B8*$D8)*((1+$B$5)^I$7)*(1/((1+$N$5)^I$7))), "") | J8: =IF($A8<>"", (($B8*$D8)*((1+$B$5)^J$7)*(1/((1+$N$5)^J$7))), "") | K8: =IF($A8<>"", (($B8*$D8)*((1+$B$5)^K$7)*(1/((1+$N$5)^K$7))), "") | L8: =IF($A8<>"", (($B8*$D8)*((1+$B$5)^L$7)*(1/((1+$N$5)^L$7))), "") | ... N8: =IF($A8<>"", (($B8*$D8)*((1+$B$5)^N$7)*(1/((1+$N$5)^N$7))), "")
A9: =IF('Yearly O&M Costs 1-10'!A10<>"", 'Yearly O&M Costs 1-10'!A10, "") | B9: =IF('Yearly O&M Costs 1-10'!B10<>"", 'Yearly O&M Costs 1-10'!B10, "") | C9: =IF('Yearly O&M Costs 1-10'!C10<>"", 'Yearly O&M Costs 1-10'!C10, "") | D9: =IF('Yearly O&M Costs 1-10'!D10<>"", 'Yearly O&M Costs 1-10'!D10, "") | E9: =IF($A9<>"", (($B9*$D9)*((1+$B$5)^E$7)*(1/((1+$N$5)^E$7))), "") | F9: =IF($A9<>"", (($B9*$D9)*((1+$B$5)^F$7)*(1/((1+$N$5)^F$7))), "") | G9: =IF($A9<>"", (($B9*$D9)*((1+$B$5)^G$7)*(1/((1+$N$5)^G$7))), "") | H9: =IF($A9<>"", (($B9*$D9)*((1+$B$5)^H$7)*(1/((1+$N$5)^H$7))), "") | I9: =IF($A9<>"", (($B9*$D9)*((1+$B$5)^I$7)*(1/((1+$N$5)^I$7))), "") | J9: =IF($A9<>"", (($B9*$D9)*((1+$B$5)^J$7)*(1/((1+$N$5)^J$7))), "") | K9: =IF($A9<>"", (($B9*$D9)*((1+$B$5)^K$7)*(1/((1+$N$5)^K$7))), "") | L9: =IF($A9<>"", (($B9*$D9)*((1+$B$5)^L$7)*(1/((1+$N$5)^L$7))), "") | ... N9: =IF($A9<>"", (($B9*$D9)*((1+$B$5)^N$7)*(1/((1+$N$5)^N$7))), "")
A10: =IF('Yearly O&M Costs 1-10'!A11<>"", 'Yearly O&M Costs 1-10'!A11, "") | B10: =IF('Yearly O&M Costs 1-10'!B11<>"", 'Yearly O&M Costs 1-10'!B11, "") | C10: =IF('Yearly O&M Costs 1-10'!C11<>"", 'Yearly O&M Costs 1-10'!C11, "") | D10: =IF('Yearly O&M Costs 1-10'!D11<>"", 'Yearly O&M Costs 1-10'!D11, "") | E10: =IF($A10<>"", (($B10*$D10)*((1+$B$5)^E$7)*(1/((1+$N$5)^E$7))), "") | F10: =IF($A10<>"", (($B10*$D10)*((1+$B$5)^F$7)*(1/((1+$N$5)^F$7))), "") | G10: =IF($A10<>"", (($B10*$D10)*((1+$B$5)^G$7)*(1/((1+$N$5)^G$7))), "") | H10: =IF($A10<>"", (($B10*$D10)*((1+$B$5)^H$7)*(1/((1+$N$5)^H$7))), "") | I10: =IF($A10<>"", (($B10*$D10)*((1+$B$5)^I$7)*(1/((1+$N$5)^I$7))), "") | J10: =IF($A10<>"", (($B10*$D10)*((1+$B$5)^J$7)*(1/((1+$N$5)^J$7))), "") | K10: =IF($A10<>"", (($B10*$D10)*((1+$B$5)^K$7)*(1/((1+$N$5)^K$7))), "") | L10: =IF($A10<>"", (($B10*$D10)*((1+$B$5)^L$7)*(1/((1+$N$5)^L$7))), "") | ... N10: =IF($A10<>"", (($B10*$D10)*((1+$B$5)^N$7)*(1/((1+$N$5)^N$7))), "")
A11: =IF('Yearly O&M Costs 1-10'!A12<>"", 'Yearly O&M Costs 1-10'!A12, "") | B11: =IF('Yearly O&M Costs 1-10'!B12<>"", 'Yearly O&M Costs 1-10'!B12, "") | C11: =IF('Yearly O&M Costs 1-10'!C12<>"", 'Yearly O&M Costs 1-10'!C12, "") | D11: =IF('Yearly O&M Costs 1-10'!D12<>"", 'Yearly O&M Costs 1-10'!D12, "") | E11: =IF($A11<>"", (($B11*$D11)*((1+$B$5)^E$7)*(1/((1+$N$5)^E$7))), "") | F11: =IF($A11<>"", (($B11*$D11)*((1+$B$5)^F$7)*(1/((1+$N$5)^F$7))), "") | G11: =IF($A11<>"", (($B11*$D11)*((1+$B$5)^G$7)*(1/((1+$N$5)^G$7))), "") | H11: =IF($A11<>"", (($B11*$D11)*((1+$B$5)^H$7)*(1/((1+$N$5)^H$7))), "") | I11: =IF($A11<>"", (($B11*$D11)*((1+$B$5)^I$7)*(1/((1+$N$5)^I$7))), "") | J11: =IF($A11<>"", (($B11*$D11)*((1+$B$5)^J$7)*(1/((1+$N$5)^J$7))), "") | K11: =IF($A11<>"", (($B11*$D11)*((1+$B$5)^K$7)*(1/((1+$N$5)^K$7))), "") | L11: =IF($A11<>"", (($B11*$D11)*((1+$B$5)^L$7)*(1/((1+$N$5)^L$7))), "") | ... N11: =IF($A11<>"", (($B11*$D11)*((1+$B$5)^N$7)*(1/((1+$N$5)^N$7))), "")
A12: =IF('Yearly O&M Costs 1-10'!A13<>"", 'Yearly O&M Costs 1-10'!A13, "") | B12: =IF('Yearly O&M Costs 1-10'!B13<>"", 'Yearly O&M Costs 1-10'!B13, "") | C12: =IF('Yearly O&M Costs 1-10'!C13<>"", 'Yearly O&M Costs 1-10'!C13, "") | D12: =IF('Yearly O&M Costs 1-10'!D13<>"", 'Yearly O&M Costs 1-10'!D13, "") | E12: =IF($A12<>"", (($B12*$D12)*((1+$B$5)^E$7)*(1/((1+$N$5)^E$7))), "") | F12: =IF($A12<>"", (($B12*$D12)*((1+$B$5)^F$7)*(1/((1+$N$5)^F$7))), "") | G12: =IF($A12<>"", (($B12*$D12)*((1+$B$5)^G$7)*(1/((1+$N$5)^G$7))), "") | H12: =IF($A12<>"", (($B12*$D12)*((1+$B$5)^H$7)*(1/((1+$N$5)^H$7))), "") | I12: =IF($A12<>"", (($B12*$D12)*((1+$B$5)^I$7)*(1/((1+$N$5)^I$7))), "") | J12: =IF($A12<>"", (($B12*$D12)*((1+$B$5)^J$7)*(1/((1+$N$5)^J$7))), "") | K12: =IF($A12<>"", (($B12*$D12)*((1+$B$5)^K$7)*(1/((1+$N$5)^K$7))), "") | L12: =IF($A12<>"", (($B12*$D12)*((1+$B$5)^L$7)*(1/((1+$N$5)^L$7))), "") | ... N12: =IF($A12<>"", (($B12*$D12)*((1+$B$5)^N$7)*(1/((1+$N$5)^N$7))), "")
A13: =IF('Yearly O&M Costs 1-10'!A14<>"", 'Yearly O&M Costs 1-10'!A14, "") | B13: =IF('Yearly O&M Costs 1-10'!B14<>"", 'Yearly O&M Costs 1-10'!B14, "") | C13: =IF('Yearly O&M Costs 1-10'!C14<>"", 'Yearly O&M Costs 1-10'!C14, "") | D13: =IF('Yearly O&M Costs 1-10'!D14<>"", 'Yearly O&M Costs 1-10'!D14, "") | E13: =IF($A13<>"", (($B13*$D13)*((1+$B$5)^E$7)*(1/((1+$N$5)^E$7))), "") | F13: =IF($A13<>"", (($B13*$D13)*((1+$B$5)^F$7)*(1/((1+$N$5)^F$7))), "") | G13: =IF($A13<>"", (($B13*$D13)*((1+$B$5)^G$7)*(1/((1+$N$5)^G$7))), "") | H13: =IF($A13<>"", (($B13*$D13)*((1+$B$5)^H$7)*(1/((1+$N$5)^H$7))), "") | I13: =IF($A13<>"", (($B13*$D13)*((1+$B$5)^I$7)*(1/((1+$N$5)^I$7))), "") | J13: =IF($A13<>"", (($B13*$D13)*((1+$B$5)^J$7)*(1/((1+$N$5)^J$7))), "") | K13: =IF($A13<>"", (($B13*$D13)*((1+$B$5)^K$7)*(1/((1+$N$5)^K$7))), "") | L13: =IF($A13<>"", (($B13*$D13)*((1+$B$5)^L$7)*(1/((1+$N$5)^L$7))), "") | ... N13: =IF($A13<>"", (($B13*$D13)*((1+$B$5)^N$7)*(1/((1+$N$5)^N$7))), "")
A14: =IF('Yearly O&M Costs 1-10'!A15<>"", 'Yearly O&M Costs 1-10'!A15, "") | B14: =IF('Yearly O&M Costs 1-10'!B15<>"", 'Yearly O&M Costs 1-10'!B15, "") | C14: =IF('Yearly O&M Costs 1-10'!C15<>"", 'Yearly O&M Costs 1-10'!C15, "") | D14: =IF('Yearly O&M Costs 1-10'!D15<>"", 'Yearly O&M Costs 1-10'!D15, "") | E14: =IF($A14<>"", (($B14*$D14)*((1+$B$5)^E$7)*(1/((1+$N$5)^E$7))), "") | F14: =IF($A14<>"", (($B14*$D14)*((1+$B$5)^F$7)*(1/((1+$N$5)^F$7))), "") | G14: =IF($A14<>"", (($B14*$D14)*((1+$B$5)^G$7)*(1/((1+$N$5)^G$7))), "") | H14: =IF($A14<>"", (($B14*$D14)*((1+$B$5)^H$7)*(1/((1+$N$5)^H$7))), "") | I14: =IF($A14<>"", (($B14*$D14)*((1+$B$5)^I$7)*(1/((1+$N$5)^I$7))), "") | J14: =IF($A14<>"", (($B14*$D14)*((1+$B$5)^J$7)*(1/((1+$N$5)^J$7))), "") | K14: =IF($A14<>"", (($B14*$D14)*((1+$B$5)^K$7)*(1/((1+$N$5)^K$7))), "") | L14: =IF($A14<>"", (($B14*$D14)*((1+$B$5)^L$7)*(1/((1+$N$5)^L$7))), "") | ... N14: =IF($A14<>"", (($B14*$D14)*((1+$B$5)^N$7)*(1/((1+$N$5)^N$7))), "")
A15: =IF('Yearly O&M Costs 1-10'!A16<>"", 'Yearly O&M Costs 1-10'!A16, "") | B15: =IF('Yearly O&M Costs 1-10'!B16<>"", 'Yearly O&M Costs 1-10'!B16, "") | C15: =IF('Yearly O&M Costs 1-10'!C16<>"", 'Yearly O&M Costs 1-10'!C16, "") | D15: =IF('Yearly O&M Costs 1-10'!D16<>"", 'Yearly O&M Costs 1-10'!D16, "") | E15: =IF($A15<>"", (($B15*$D15)*((1+$B$5)^E$7)*(1/((1+$N$5)^E$7))), "") | F15: =IF($A15<>"", (($B15*$D15)*((1+$B$5)^F$7)*(1/((1+$N$5)^F$7))), "") | G15: =IF($A15<>"", (($B15*$D15)*((1+$B$5)^G$7)*(1/((1+$N$5)^G$7))), "") | H15: =IF($A15<>"", (($B15*$D15)*((1+$B$5)^H$7)*(1/((1+$N$5)^H$7))), "") | I15: =IF($A15<>"", (($B15*$D15)*((1+$B$5)^I$7)*(1/((1+$N$5)^I$7))), "") | J15: =IF($A15<>"", (($B15*$D15)*((1+$B$5)^J$7)*(1/((1+$N$5)^J$7))), "") | K15: =IF($A15<>"", (($B15*$D15)*((1+$B$5)^K$7)*(1/((1+$N$5)^K$7))), "") | L15: =IF($A15<>"", (($B15*$D15)*((1+$B$5)^L$7)*(1/((1+$N$5)^L$7))), "") | ... N15: =IF($A15<>"", (($B15*$D15)*((1+$B$5)^N$7)*(1/((1+$N$5)^N$7))), "")
A16: =IF('Yearly O&M Costs 1-10'!A17<>"", 'Yearly O&M Costs 1-10'!A17, "") | B16: =IF('Yearly O&M Costs 1-10'!B17<>"", 'Yearly O&M Costs 1-10'!B17, "") | C16: =IF('Yearly O&M Costs 1-10'!C17<>"", 'Yearly O&M Costs 1-10'!C17, "") | D16: =IF('Yearly O&M Costs 1-10'!D17<>"", 'Yearly O&M Costs 1-10'!D17, "") | E16: =IF($A16<>"", (($B16*$D16)*((1+$B$5)^E$7)*(1/((1+$N$5)^E$7))), "") | F16: =IF($A16<>"", (($B16*$D16)*((1+$B$5)^F$7)*(1/((1+$N$5)^F$7))), "") | G16: =IF($A16<>"", (($B16*$D16)*((1+$B$5)^G$7)*(1/((1+$N$5)^G$7))), "") | H16: =IF($A16<>"", (($B16*$D16)*((1+$B$5)^H$7)*(1/((1+$N$5)^H$7))), "") | I16: =IF($A16<>"", (($B16*$D16)*((1+$B$5)^I$7)*(1/((1+$N$5)^I$7))), "") | J16: =IF($A16<>"", (($B16*$D16)*((1+$B$5)^J$7)*(1/((1+$N$5)^J$7))), "") | K16: =IF($A16<>"", (($B16*$D16)*((1+$B$5)^K$7)*(1/((1+$N$5)^K$7))), "") | L16: =IF($A16<>"", (($B16*$D16)*((1+$B$5)^L$7)*(1/((1+$N$5)^L$7))), "") | ... N16: =IF($A16<>"", (($B16*$D16)*((1+$B$5)^N$7)*(1/((1+$N$5)^N$7))), "")
A17: =IF('Yearly O&M Costs 1-10'!A18<>"", 'Yearly O&M Costs 1-10'!A18, "") | B17: =IF('Yearly O&M Costs 1-10'!B18<>"", 'Yearly O&M Costs 1-10'!B18, "") | C17: =IF('Yearly O&M Costs 1-10'!C18<>"", 'Yearly O&M Costs 1-10'!C18, "") | D17: =IF('Yearly O&M Costs 1-10'!D18<>"", 'Yearly O&M Costs 1-10'!D18, "") | E17: =IF($A17<>"", (($B17*$D17)*((1+$B$5)^E$7)*(1/((1+$N$5)^E$7))), "") | F17: =IF($A17<>"", (($B17*$D17)*((1+$B$5)^F$7)*(1/((1+$N$5)^F$7))), "") | G17: =IF($A17<>"", (($B17*$D17)*((1+$B$5)^G$7)*(1/((1+$N$5)^G$7))), "") | H17: =IF($A17<>"", (($B17*$D17)*((1+$B$5)^H$7)*(1/((1+$N$5)^H$7))), "") | I17: =IF($A17<>"", (($B17*$D17)*((1+$B$5)^I$7)*(1/((1+$N$5)^I$7))), "") | J17: =IF($A17<>"", (($B17*$D17)*((1+$B$5)^J$7)*(1/((1+$N$5)^J$7))), "") | K17: =IF($A17<>"", (($B17*$D17)*((1+$B$5)^K$7)*(1/((1+$N$5)^K$7))), "") | L17: =IF($A17<>"", (($B17*$D17)*((1+$B$5)^L$7)*(1/((1+$N$5)^L$7))), "") | ... N17: =IF($A17<>"", (($B17*$D17)*((1+$B$5)^N$7)*(1/((1+$N$5)^N$7))), "")
A18: =IF('Yearly O&M Costs 1-10'!A19<>"", 'Yearly O&M Costs 1-10'!A19, "") | B18: =IF('Yearly O&M Costs 1-10'!B19<>"", 'Yearly O&M Costs 1-10'!B19, "") | C18: =IF('Yearly O&M Costs 1-10'!C19<>"", 'Yearly O&M Costs 1-10'!C19, "") | D18: =IF('Yearly O&M Costs 1-10'!D19<>"", 'Yearly O&M Costs 1-10'!D19, "") | E18: =IF($A18<>"", (($B18*$D18)*((1+$B$5)^E$7)*(1/((1+$N$5)^E$7))), "") | F18: =IF($A18<>"", (($B18*$D18)*((1+$B$5)^F$7)*(1/((1+$N$5)^F$7))), "") | G18: =IF($A18<>"", (($B18*$D18)*((1+$B$5)^G$7)*(1/((1+$N$5)^G$7))), "") | H18: =IF($A18<>"", (($B18*$D18)*((1+$B$5)^H$7)*(1/((1+$N$5)^H$7))), "") | I18: =IF($A18<>"", (($B18*$D18)*((1+$B$5)^I$7)*(1/((1+$N$5)^I$7))), "") | J18: =IF($A18<>"", (($B18*$D18)*((1+$B$5)^J$7)*(1/((1+$N$5)^J$7))), "") | K18: =IF($A18<>"", (($B18*$D18)*((1+$B$5)^K$7)*(1/((1+$N$5)^K$7))), "") | L18: =IF($A18<>"", (($B18*$D18)*((1+$B$5)^L$7)*(1/((1+$N$5)^L$7))), "") | ... N18: =IF($A18<>"", (($B18*$D18)*((1+$B$5)^N$7)*(1/((1+$N$5)^N$7))), "")
A19: =IF('Yearly O&M Costs 1-10'!A20<>"", 'Yearly O&M Costs 1-10'!A20, "") | B19: =IF('Yearly O&M Costs 1-10'!B20<>"", 'Yearly O&M Costs 1-10'!B20, "") | C19: =IF('Yearly O&M Costs 1-10'!C20<>"", 'Yearly O&M Costs 1-10'!C20, "") | D19: =IF('Yearly O&M Costs 1-10'!D20<>"", 'Yearly O&M Costs 1-10'!D20, "") | E19: =IF($A19<>"", (($B19*$D19)*((1+$B$5)^E$7)*(1/((1+$N$5)^E$7))), "") | F19: =IF($A19<>"", (($B19*$D19)*((1+$B$5)^F$7)*(1/((1+$N$5)^F$7))), "") | G19: =IF($A19<>"", (($B19*$D19)*((1+$B$5)^G$7)*(1/((1+$N$5)^G$7))), "") | H19: =IF($A19<>"", (($B19*$D19)*((1+$B$5)^H$7)*(1/((1+$N$5)^H$7))), "") | I19: =IF($A19<>"", (($B19*$D19)*((1+$B$5)^I$7)*(1/((1+$N$5)^I$7))), "") | J19: =IF($A19<>"", (($B19*$D19)*((1+$B$5)^J$7)*(1/((1+$N$5)^J$7))), "") | K19: =IF($A19<>"", (($B19*$D19)*((1+$B$5)^K$7)*(1/((1+$N$5)^K$7))), "") | L19: =IF($A19<>"", (($B19*$D19)*((1+$B$5)^L$7)*(1/((1+$N$5)^L$7))), "") | ... N19: =IF($A19<>"", (($B19*$D19)*((1+$B$5)^N$7)*(1/((1+$N$5)^N$7))), "")
... A30: =IF('Yearly O&M Costs 1-10'!A31<>"", 'Yearly O&M Costs 1-10'!A31, "") | B30: =IF('Yearly O&M Costs 1-10'!B31<>"", 'Yearly O&M Costs 1-10'!B31, "") | C30: =IF('Yearly O&M Costs 1-10'!C31<>"", 'Yearly O&M Costs 1-10'!C31, "") | D30: =IF('Yearly O&M Costs 1-10'!D31<>"", 'Yearly O&M Costs 1-10'!D31, "") | E30: =IF($A30<>"", (($B30*$D30)*((1+$B$5)^E$7)*(1/((1+$N$5)^E$7))), "") | F30: =IF($A30<>"", (($B30*$D30)*((1+$B$5)^F$7)*(1/((1+$N$5)^F$7))), "") | G30: =IF($A30<>"", (($B30*$D30)*((1+$B$5)^G$7)*(1/((1+$N$5)^G$7))), "") | H30: =IF($A30<>"", (($B30*$D30)*((1+$B$5)^H$7)*(1/((1+$N$5)^H$7))), "") | I30: =IF($A30<>"", (($B30*$D30)*((1+$B$5)^I$7)*(1/((1+$N$5)^I$7))), "") | J30: =IF($A30<>"", (($B30*$D30)*((1+$B$5)^J$7)*(1/((1+$N$5)^J$7))), "") | K30: =IF($A30<>"", (($B30*$D30)*((1+$B$5)^K$7)*(1/((1+$N$5)^K$7))), "") | L30: =IF($A30<>"", (($B30*$D30)*((1+$B$5)^L$7)*(1/((1+$N$5)^L$7))), "") | ... N30: =IF($A30<>"", (($B30*$D30)*((1+$B$5)^N$7)*(1/((1+$N$5)^N$7))), "")
D31: Total Present Value of Yearly O&M Expenses (Years 11-20): | E31: =SUM(E8:E30) -> 0 | F31: =SUM(F8:F30) -> 0 | G31: =SUM(G8:G30) -> 0 | H31: =SUM(H8:H30) -> 0 | I31: =SUM(I8:I30) -> 0 | J31: =SUM(J8:J30) -> 0 | K31: =SUM(K8:K30) -> 0 | L31: =SUM(L8:L30) -> 0 | ... N31: =SUM(N8:N30) -> 0
M32: Total Present Value of Annual O&M Costs (Life of Project): | N32: ='Yearly O&M Costs 1-10'!E32+'Yearly O&M Costs 1-10'!F32+'Yearly O&M Costs 1-10'!G32+'Yearly O&M Costs 1-10'!H32+'Yearly O&M Costs 1-10'!I32+'Yearly O&M Costs 1-10'!J32+'Yearly O&M Costs 1-10'!K32+'Yearly O&M Costs 1-10'!L32+'Yearly O&M Costs 1-10'!M32+'Yearly O&M Costs 1-10'!N32+'Yearly O&M Costs 11-20'!E31+'Yearly O&M Costs 11-20'!F31+'Yearly O&M Costs 11-20'!G31+'Yearly O&M Costs 11-20'!H31+'Yearly O&M Costs 11-20'!I31+'Yearly O&M Costs 11-20'!J31+'Yearly O&M Costs 11-20'!K31+'Yearly O&M Costs 11-20'!L31+'Yearly O&M Costs 11-20'!M31+'Yearly O&M Costs 11-20'!N31 -> 0
A34: i= | B34: 0.04875

Sheet Inter O&M Entry
A1: O&M Intermittent Costs Input
A3: Alternative: | B3: ='Capital Costs'!B6 -> 0
A5: For each component, enter "Y" in the gray area in the year in which replacement, if any, will occur.
I7: Year O&M Needed? (Insert Y in year where O&M is needed.)
A8: Component | B8: Unit Cost | C8: Unit | D8: Quantity | E8: Replacement Needed? (Years 1-5) | F8: Replacement Needed? (Years 6-10) | G8: Replacement Needed (Years 11-15) | H8: Replacement Needed? (Years 16-20) | I8: 1 | J8: 2 | K8: 3 | L8: 4 | M8: 5 | N8: 6 | O8: 7 | P8: 8 | Q8: 9 | R8: 10 | S8: 11 | T8: 12 | U8: 13 | V8: 14 | W8: 15 | X8: 16 | Y8: 17 | Z8: 18 | AA8: 19 | AB8: 20

Sheet Inter O&M 1-10
A1: Table 5.2.9. Present Value of Intermittent Operations and Maintenance Costs (Years 1-10)
A2: =Input!B4 -> 0
A3: =Input!B5 -> 0
A4: =Input!B6 -> 0
A5: ='Yearly O&M Costs 1-10'!A6 -> Current Inflation Rate Based on Municipal Cost Index: | B5: ='Yearly O&M Costs 1-10'!B6 -> 0.027598896 | M5: EPA Discount Rate: | N5: ='Yearly O&M Costs 11-20'!N5 -> 0.04875
E6: Present Value of O&M Costs for Year:
A7: Component | B7: Unit Cost | C7: Unit | D7: Quantity | E7: 1 | F7: 2 | G7: 3 | H7: 4 | I7: 5 | J7: 6 | K7: 7 | L7: 8 | M7: 9 | N7: 10
A8: =IF('Inter O&M Entry'!A9<>"", 'Inter O&M Entry'!A9, "") | B8: =IF('Inter O&M Entry'!B9<>"", 'Inter O&M Entry'!B9, "") | C8: =IF('Inter O&M Entry'!C9<>"", 'Inter O&M Entry'!C9, "") | D8: =IF('Inter O&M Entry'!D9<>"", 'Inter O&M Entry'!D9, "") | E8: =IF($A8<>"", (IF('Inter O&M Entry'!I9="Y", ((($B8*$D8)*((1+$B$5)^E$7))*(1/((1+$N$5)^E$7))), 0)), "") | F8: =IF($A8<>"", (IF('Inter O&M Entry'!J9="Y", ((($B8*$D8)*((1+$B$5)^F$7))*(1/((1+$N$5)^F$7))), 0)), "") | G8: =IF($A8<>"", (IF('Inter O&M Entry'!K9="Y", ((($B8*$D8)*((1+$B$5)^G$7))*(1/((1+$N$5)^G$7))), 0)), "") | H8: =IF($A8<>"", (IF('Inter O&M Entry'!L9="Y", ((($B8*$D8)*((1+$B$5)^H$7))*(1/((1+$N$5)^H$7))), 0)), "") | I8: =IF($A8<>"", (IF('Inter O&M Entry'!M9="Y", ((($B8*$D8)*((1+$B$5)^I$7))*(1/((1+$N$5)^I$7))), 0)), "") | J8: =IF($A8<>"", (IF('Inter O&M Entry'!N9="Y", ((($B8*$D8)*((1+$B$5)^J$7))*(1/((1+$N$5)^J$7))), 0)), "") | K8: =IF($A8<>"", (IF('Inter O&M Entry'!O9="Y", ((($B8*$D8)*((1+$B$5)^K$7))*(1/((1+$N$5)^K$7))), 0)), "") | L8: =IF($A8<>"", (IF('Inter O&M Entry'!P9="Y", ((($B8*$D8)*((1+$B$5)^L$7))*(1/((1+$N$5)^L$7))), 0)), "") | ... N8: =IF($A8<>"", (IF('Inter O&M Entry'!R9="Y", ((($B8*$D8)*((1+$B$5)^N$7))*(1/((1+$N$5)^N$7))), 0)), "")
A9: =IF('Inter O&M Entry'!A10<>"", 'Inter O&M Entry'!A10, "") | B9: =IF('Inter O&M Entry'!B10<>"", 'Inter O&M Entry'!B10, "") | C9: =IF('Inter O&M Entry'!C10<>"", 'Inter O&M Entry'!C10, "") | D9: =IF('Inter O&M Entry'!D10<>"", 'Inter O&M Entry'!D10, "") | E9: =IF($A9<>"", (IF('Inter O&M Entry'!I10="Y", ((($B9*$D9)*((1+$B$5)^E$7))*(1/((1+$N$5)^E$7))), 0)), "") | F9: =IF($A9<>"", (IF('Inter O&M Entry'!J10="Y", ((($B9*$D9)*((1+$B$5)^F$7))*(1/((1+$N$5)^F$7))), 0)), "") | G9: =IF($A9<>"", (IF('Inter O&M Entry'!K10="Y", ((($B9*$D9)*((1+$B$5)^G$7))*(1/((1+$N$5)^G$7))), 0)), "") | H9: =IF($A9<>"", (IF('Inter O&M Entry'!L10="Y", ((($B9*$D9)*((1+$B$5)^H$7))*(1/((1+$N$5)^H$7))), 0)), "") | I9: =IF($A9<>"", (IF('Inter O&M Entry'!M10="Y", ((($B9*$D9)*((1+$B$5)^I$7))*(1/((1+$N$5)^I$7))), 0)), "") | J9: =IF($A9<>"", (IF('Inter O&M Entry'!N10="Y", ((($B9*$D9)*((1+$B$5)^J$7))*(1/((1+$N$5)^J$7))), 0)), "") | K9: =IF($A9<>"", (IF('Inter O&M Entry'!O10="Y", ((($B9*$D9)*((1+$B$5)^K$7))*(1/((1+$N$5)^K$7))), 0)), "") | L9: =IF($A9<>"", (IF('Inter O&M Entry'!P10="Y", ((($B9*$D9)*((1+$B$5)^L$7))*(1/((1+$N$5)^L$7))), 0)), "") | ... N9: =IF($A9<>"", (IF('Inter O&M Entry'!R10="Y", ((($B9*$D9)*((1+$B$5)^N$7))*(1/((1+$N$5)^N$7))), 0)), "")
A10: =IF('Inter O&M Entry'!A11<>"", 'Inter O&M Entry'!A11, "") | B10: =IF('Inter O&M Entry'!B11<>"", 'Inter O&M Entry'!B11, "") | C10: =IF('Inter O&M Entry'!C11<>"", 'Inter O&M Entry'!C11, "") | D10: =IF('Inter O&M Entry'!D11<>"", 'Inter O&M Entry'!D11, "") | E10: =IF($A10<>"", (IF('Inter O&M Entry'!I11="Y", ((($B10*$D10)*((1+$B$5)^E$7))*(1/((1+$N$5)^E$7))), 0)), "") | F10: =IF($A10<>"", (IF('Inter O&M Entry'!J11="Y", ((($B10*$D10)*((1+$B$5)^F$7))*(1/((1+$N$5)^F$7))), 0)), "") | G10: =IF($A10<>"", (IF('Inter O&M Entry'!K11="Y", ((($B10*$D10)*((1+$B$5)^G$7))*(1/((1+$N$5)^G$7))), 0)), "") | H10: =IF($A10<>"", (IF('Inter O&M Entry'!L11="Y", ((($B10*$D10)*((1+$B$5)^H$7))*(1/((1+$N$5)^H$7))), 0)), "") | I10: =IF($A10<>"", (IF('Inter O&M Entry'!M11="Y", ((($B10*$D10)*((1+$B$5)^I$7))*(1/((1+$N$5)^I$7))), 0)), "") | J10: =IF($A10<>"", (IF('Inter O&M Entry'!N11="Y", ((($B10*$D10)*((1+$B$5)^J$7))*(1/((1+$N$5)^J$7))), 0)), "") | K10: =IF($A10<>"", (IF('Inter O&M Entry'!O11="Y", ((($B10*$D10)*((1+$B$5)^K$7))*(1/((1+$N$5)^K$7))), 0)), "") | L10: =IF($A10<>"", (IF('Inter O&M Entry'!P11="Y", ((($B10*$D10)*((1+$B$5)^L$7))*(1/((1+$N$5)^L$7))), 0)), "") | ... N10: =IF($A10<>"", (IF('Inter O&M Entry'!R11="Y", ((($B10*$D10)*((1+$B$5)^N$7))*(1/((1+$N$5)^N$7))), 0)), "")
A11: =IF('Inter O&M Entry'!A12<>"", 'Inter O&M Entry'!A12, "") | B11: =IF('Inter O&M Entry'!B12<>"", 'Inter O&M Entry'!B12, "") | C11: =IF('Inter O&M Entry'!C12<>"", 'Inter O&M Entry'!C12, "") | D11: =IF('Inter O&M Entry'!D12<>"", 'Inter O&M Entry'!D12, "") | E11: =IF($A11<>"", (IF('Inter O&M Entry'!I12="Y", ((($B11*$D11)*((1+$B$5)^E$7))*(1/((1+$N$5)^E$7))), 0)), "") | F11: =IF($A11<>"", (IF('Inter O&M Entry'!J12="Y", ((($B11*$D11)*((1+$B$5)^F$7))*(1/((1+$N$5)^F$7))), 0)), "") | G11: =IF($A11<>"", (IF('Inter O&M Entry'!K12="Y", ((($B11*$D11)*((1+$B$5)^G$7))*(1/((1+$N$5)^G$7))), 0)), "") | H11: =IF($A11<>"", (IF('Inter O&M Entry'!L12="Y", ((($B11*$D11)*((1+$B$5)^H$7))*(1/((1+$N$5)^H$7))), 0)), "") | I11: =IF($A11<>"", (IF('Inter O&M Entry'!M12="Y", ((($B11*$D11)*((1+$B$5)^I$7))*(1/((1+$N$5)^I$7))), 0)), "") | J11: =IF($A11<>"", (IF('Inter O&M Entry'!N12="Y", ((($B11*$D11)*((1+$B$5)^J$7))*(1/((1+$N$5)^J$7))), 0)), "") | K11: =IF($A11<>"", (IF('Inter O&M Entry'!O12="Y", ((($B11*$D11)*((1+$B$5)^K$7))*(1/((1+$N$5)^K$7))), 0)), "") | L11: =IF($A11<>"", (IF('Inter O&M Entry'!P12="Y", ((($B11*$D11)*((1+$B$5)^L$7))*(1/((1+$N$5)^L$7))), 0)), "") | ... N11: =IF($A11<>"", (IF('Inter O&M Entry'!R12="Y", ((($B11*$D11)*((1+$B$5)^N$7))*(1/((1+$N$5)^N$7))), 0)), "")
A12: =IF('Inter O&M Entry'!A13<>"", 'Inter O&M Entry'!A13, "") | B12: =IF('Inter O&M Entry'!B13<>"", 'Inter O&M Entry'!B13, "") | C12: =IF('Inter O&M Entry'!C13<>"", 'Inter O&M Entry'!C13, "") | D12: =IF('Inter O&M Entry'!D13<>"", 'Inter O&M Entry'!D13, "") | E12: =IF($A12<>"", (IF('Inter O&M Entry'!I13="Y", ((($B12*$D12)*((1+$B$5)^E$7))*(1/((1+$N$5)^E$7))), 0)), "") | F12: =IF($A12<>"", (IF('Inter O&M Entry'!J13="Y", ((($B12*$D12)*((1+$B$5)^F$7))*(1/((1+$N$5)^F$7))), 0)), "") | G12: =IF($A12<>"", (IF('Inter O&M Entry'!K13="Y", ((($B12*$D12)*((1+$B$5)^G$7))*(1/((1+$N$5)^G$7))), 0)), "") | H12: =IF($A12<>"", (IF('Inter O&M Entry'!L13="Y", ((($B12*$D12)*((1+$B$5)^H$7))*(1/((1+$N$5)^H$7))), 0)), "") | I12: =IF($A12<>"", (IF('Inter O&M Entry'!M13="Y", ((($B12*$D12)*((1+$B$5)^I$7))*(1/((1+$N$5)^I$7))), 0)), "") | J12: =IF($A12<>"", (IF('Inter O&M Entry'!N13="Y", ((($B12*$D12)*((1+$B$5)^J$7))*(1/((1+$N$5)^J$7))), 0)), "") | K12: =IF($A12<>"", (IF('Inter O&M Entry'!O13="Y", ((($B12*$D12)*((1+$B$5)^K$7))*(1/((1+$N$5)^K$7))), 0)), "") | L12: =IF($A12<>"", (IF('Inter O&M Entry'!P13="Y", ((($B12*$D12)*((1+$B$5)^L$7))*(1/((1+$N$5)^L$7))), 0)), "") | ... N12: =IF($A12<>"", (IF('Inter O&M Entry'!R13="Y", ((($B12*$D12)*((1+$B$5)^N$7))*(1/((1+$N$5)^N$7))), 0)), "")
A13: =IF('Inter O&M Entry'!A14<>"", 'Inter O&M Entry'!A14, "") | B13: =IF('Inter O&M Entry'!B14<>"", 'Inter O&M Entry'!B14, "") | C13: =IF('Inter O&M Entry'!C14<>"", 'Inter O&M Entry'!C14, "") | D13: =IF('Inter O&M Entry'!D14<>"", 'Inter O&M Entry'!D14, "") | E13: =IF($A13<>"", (IF('Inter O&M Entry'!I14="Y", ((($B13*$D13)*((1+$B$5)^E$7))*(1/((1+$N$5)^E$7))), 0)), "") | F13: =IF($A13<>"", (IF('Inter O&M Entry'!J14="Y", ((($B13*$D13)*((1+$B$5)^F$7))*(1/((1+$N$5)^F$7))), 0)), "") | G13: =IF($A13<>"", (IF('Inter O&M Entry'!K14="Y", ((($B13*$D13)*((1+$B$5)^G$7))*(1/((1+$N$5)^G$7))), 0)), "") | H13: =IF($A13<>"", (IF('Inter O&M Entry'!L14="Y", ((($B13*$D13)*((1+$B$5)^H$7))*(1/((1+$N$5)^H$7))), 0)), "") | I13: =IF($A13<>"", (IF('Inter O&M Entry'!M14="Y", ((($B13*$D13)*((1+$B$5)^I$7))*(1/((1+$N$5)^I$7))), 0)), "") | J13: =IF($A13<>"", (IF('Inter O&M Entry'!N14="Y", ((($B13*$D13)*((1+$B$5)^J$7))*(1/((1+$N$5)^J$7))), 0)), "") | K13: =IF($A13<>"", (IF('Inter O&M Entry'!O14="Y", ((($B13*$D13)*((1+$B$5)^K$7))*(1/((1+$N$5)^K$7))), 0)), "") | L13: =IF($A13<>"", (IF('Inter O&M Entry'!P14="Y", ((($B13*$D13)*((1+$B$5)^L$7))*(1/((1+$N$5)^L$7))), 0)), "") | ... N13: =IF($A13<>"", (IF('Inter O&M Entry'!R14="Y", ((($B13*$D13)*((1+$B$5)^N$7))*(1/((1+$N$5)^N$7))), 0)), "")
A14: =IF('Inter O&M Entry'!A15<>"", 'Inter O&M Entry'!A15, "") | B14: =IF('Inter O&M Entry'!B15<>"", 'Inter O&M Entry'!B15, "") | C14: =IF('Inter O&M Entry'!C15<>"", 'Inter O&M Entry'!C15, "") | D14: =IF('Inter O&M Entry'!D15<>"", 'Inter O&M Entry'!D15, "") | E14: =IF($A14<>"", (IF('Inter O&M Entry'!I15="Y", ((($B14*$D14)*((1+$B$5)^E$7))*(1/((1+$N$5)^E$7))), 0)), "") | F14: =IF($A14<>"", (IF('Inter O&M Entry'!J15="Y", ((($B14*$D14)*((1+$B$5)^F$7))*(1/((1+$N$5)^F$7))), 0)), "") | G14: =IF($A14<>"", (IF('Inter O&M Entry'!K15="Y", ((($B14*$D14)*((1+$B$5)^G$7))*(1/((1+$N$5)^G$7))), 0)), "") | H14: =IF($A14<>"", (IF('Inter O&M Entry'!L15="Y", ((($B14*$D14)*((1+$B$5)^H$7))*(1/((1+$N$5)^H$7))), 0)), "") | I14: =IF($A14<>"", (IF('Inter O&M Entry'!M15="Y", ((($B14*$D14)*((1+$B$5)^I$7))*(1/((1+$N$5)^I$7))), 0)), "") | J14: =IF($A14<>"", (IF('Inter O&M Entry'!N15="Y", ((($B14*$D14)*((1+$B$5)^J$7))*(1/((1+$N$5)^J$7))), 0)), "") | K14: =IF($A14<>"", (IF('Inter O&M Entry'!O15="Y", ((($B14*$D14)*((1+$B$5)^K$7))*(1/((1+$N$5)^K$7))), 0)), "") | L14: =IF($A14<>"", (IF('Inter O&M Entry'!P15="Y", ((($B14*$D14)*((1+$B$5)^L$7))*(1/((1+$N$5)^L$7))), 0)), "") | ... N14: =IF($A14<>"", (IF('Inter O&M Entry'!R15="Y", ((($B14*$D14)*((1+$B$5)^N$7))*(1/((1+$N$5)^N$7))), 0)), "")
A15: =IF('Inter O&M Entry'!A16<>"", 'Inter O&M Entry'!A16, "") | B15: =IF('Inter O&M Entry'!B16<>"", 'Inter O&M Entry'!B16, "") | C15: =IF('Inter O&M Entry'!C16<>"", 'Inter O&M Entry'!C16, "") | D15: =IF('Inter O&M Entry'!D16<>"", 'Inter O&M Entry'!D16, "") | E15: =IF($A15<>"", (IF('Inter O&M Entry'!I16="Y", ((($B15*$D15)*((1+$B$5)^E$7))*(1/((1+$N$5)^E$7))), 0)), "") | F15: =IF($A15<>"", (IF('Inter O&M Entry'!J16="Y", ((($B15*$D15)*((1+$B$5)^F$7))*(1/((1+$N$5)^F$7))), 0)), "") | G15: =IF($A15<>"", (IF('Inter O&M Entry'!K16="Y", ((($B15*$D15)*((1+$B$5)^G$7))*(1/((1+$N$5)^G$7))), 0)), "") | H15: =IF($A15<>"", (IF('Inter O&M Entry'!L16="Y", ((($B15*$D15)*((1+$B$5)^H$7))*(1/((1+$N$5)^H$7))), 0)), "") | I15: =IF($A15<>"", (IF('Inter O&M Entry'!M16="Y", ((($B15*$D15)*((1+$B$5)^I$7))*(1/((1+$N$5)^I$7))), 0)), "") | J15: =IF($A15<>"", (IF('Inter O&M Entry'!N16="Y", ((($B15*$D15)*((1+$B$5)^J$7))*(1/((1+$N$5)^J$7))), 0)), "") | K15: =IF($A15<>"", (IF('Inter O&M Entry'!O16="Y", ((($B15*$D15)*((1+$B$5)^K$7))*(1/((1+$N$5)^K$7))), 0)), "") | L15: =IF($A15<>"", (IF('Inter O&M Entry'!P16="Y", ((($B15*$D15)*((1+$B$5)^L$7))*(1/((1+$N$5)^L$7))), 0)), "") | ... N15: =IF($A15<>"", (IF('Inter O&M Entry'!R16="Y", ((($B15*$D15)*((1+$B$5)^N$7))*(1/((1+$N$5)^N$7))), 0)), "")
A16: =IF('Inter O&M Entry'!A17<>"", 'Inter O&M Entry'!A17, "") | B16: =IF('Inter O&M Entry'!B17<>"", 'Inter O&M Entry'!B17, "") | C16: =IF('Inter O&M Entry'!C17<>"", 'Inter O&M Entry'!C17, "") | D16: =IF('Inter O&M Entry'!D17<>"", 'Inter O&M Entry'!D17, "") | E16: =IF($A16<>"", (IF('Inter O&M Entry'!I17="Y", ((($B16*$D16)*((1+$B$5)^E$7))*(1/((1+$N$5)^E$7))), 0)), "") | F16: =IF($A16<>"", (IF('Inter O&M Entry'!J17="Y", ((($B16*$D16)*((1+$B$5)^F$7))*(1/((1+$N$5)^F$7))), 0)), "") | G16: =IF($A16<>"", (IF('Inter O&M Entry'!K17="Y", ((($B16*$D16)*((1+$B$5)^G$7))*(1/((1+$N$5)^G$7))), 0)), "") | H16: =IF($A16<>"", (IF('Inter O&M Entry'!L17="Y", ((($B16*$D16)*((1+$B$5)^H$7))*(1/((1+$N$5)^H$7))), 0)), "") | I16: =IF($A16<>"", (IF('Inter O&M Entry'!M17="Y", ((($B16*$D16)*((1+$B$5)^I$7))*(1/((1+$N$5)^I$7))), 0)), "") | J16: =IF($A16<>"", (IF('Inter O&M Entry'!N17="Y", ((($B16*$D16)*((1+$B$5)^J$7))*(1/((1+$N$5)^J$7))), 0)), "") | K16: =IF($A16<>"", (IF('Inter O&M Entry'!O17="Y", ((($B16*$D16)*((1+$B$5)^K$7))*(1/((1+$N$5)^K$7))), 0)), "") | L16: =IF($A16<>"", (IF('Inter O&M Entry'!P17="Y", ((($B16*$D16)*((1+$B$5)^L$7))*(1/((1+$N$5)^L$7))), 0)), "") | ... N16: =IF($A16<>"", (IF('Inter O&M Entry'!R17="Y", ((($B16*$D16)*((1+$B$5)^N$7))*(1/((1+$N$5)^N$7))), 0)), "")
A17: =IF('Inter O&M Entry'!A18<>"", 'Inter O&M Entry'!A18, "") | B17: =IF('Inter O&M Entry'!B18<>"", 'Inter O&M Entry'!B18, "") | C17: =IF('Inter O&M Entry'!C18<>"", 'Inter O&M Entry'!C18, "") | D17: =IF('Inter O&M Entry'!D18<>"", 'Inter O&M Entry'!D18, "") | E17: =IF($A17<>"", (IF('Inter O&M Entry'!I18="Y", ((($B17*$D17)*((1+$B$5)^E$7))*(1/((1+$N$5)^E$7))), 0)), "") | F17: =IF($A17<>"", (IF('Inter O&M Entry'!J18="Y", ((($B17*$D17)*((1+$B$5)^F$7))*(1/((1+$N$5)^F$7))), 0)), "") | G17: =IF($A17<>"", (IF('Inter O&M Entry'!K18="Y", ((($B17*$D17)*((1+$B$5)^G$7))*(1/((1+$N$5)^G$7))), 0)), "") | H17: =IF($A17<>"", (IF('Inter O&M Entry'!L18="Y", ((($B17*$D17)*((1+$B$5)^H$7))*(1/((1+$N$5)^H$7))), 0)), "") | I17: =IF($A17<>"", (IF('Inter O&M Entry'!M18="Y", ((($B17*$D17)*((1+$B$5)^I$7))*(1/((1+$N$5)^I$7))), 0)), "") | J17: =IF($A17<>"", (IF('Inter O&M Entry'!N18="Y", ((($B17*$D17)*((1+$B$5)^J$7))*(1/((1+$N$5)^J$7))), 0)), "") | K17: =IF($A17<>"", (IF('Inter O&M Entry'!O18="Y", ((($B17*$D17)*((1+$B$5)^K$7))*(1/((1+$N$5)^K$7))), 0)), "") | L17: =IF($A17<>"", (IF('Inter O&M Entry'!P18="Y", ((($B17*$D17)*((1+$B$5)^L$7))*(1/((1+$N$5)^L$7))), 0)), "") | ... N17: =IF($A17<>"", (IF('Inter O&M Entry'!R18="Y", ((($B17*$D17)*((1+$B$5)^N$7))*(1/((1+$N$5)^N$7))), 0)), "")
A18: =IF('Inter O&M Entry'!A19<>"", 'Inter O&M Entry'!A19, "") | B18: =IF('Inter O&M Entry'!B19<>"", 'Inter O&M Entry'!B19, "") | C18: =IF('Inter O&M Entry'!C19<>"", 'Inter O&M Entry'!C19, "") | D18: =IF('Inter O&M Entry'!D19<>"", 'Inter O&M Entry'!D19, "") | E18: =IF($A18<>"", (IF('Inter O&M Entry'!I19="Y", ((($B18*$D18)*((1+$B$5)^E$7))*(1/((1+$N$5)^E$7))), 0)), "") | F18: =IF($A18<>"", (IF('Inter O&M Entry'!J19="Y", ((($B18*$D18)*((1+$B$5)^F$7))*(1/((1+$N$5)^F$7))), 0)), "") | G18: =IF($A18<>"", (IF('Inter O&M Entry'!K19="Y", ((($B18*$D18)*((1+$B$5)^G$7))*(1/((1+$N$5)^G$7))), 0)), "") | H18: =IF($A18<>"", (IF('Inter O&M Entry'!L19="Y", ((($B18*$D18)*((1+$B$5)^H$7))*(1/((1+$N$5)^H$7))), 0)), "") | I18: =IF($A18<>"", (IF('Inter O&M Entry'!M19="Y", ((($B18*$D18)*((1+$B$5)^I$7))*(1/((1+$N$5)^I$7))), 0)), "") | J18: =IF($A18<>"", (IF('Inter O&M Entry'!N19="Y", ((($B18*$D18)*((1+$B$5)^J$7))*(1/((1+$N$5)^J$7))), 0)), "") | K18: =IF($A18<>"", (IF('Inter O&M Entry'!O19="Y", ((($B18*$D18)*((1+$B$5)^K$7))*(1/((1+$N$5)^K$7))), 0)), "") | L18: =IF($A18<>"", (IF('Inter O&M Entry'!P19="Y", ((($B18*$D18)*((1+$B$5)^L$7))*(1/((1+$N$5)^L$7))), 0)), "") | ... N18: =IF($A18<>"", (IF('Inter O&M Entry'!R19="Y", ((($B18*$D18)*((1+$B$5)^N$7))*(1/((1+$N$5)^N$7))), 0)), "")
A19: =IF('Inter O&M Entry'!A20<>"", 'Inter O&M Entry'!A20, "") | B19: =IF('Inter O&M Entry'!B20<>"", 'Inter O&M Entry'!B20, "") | C19: =IF('Inter O&M Entry'!C20<>"", 'Inter O&M Entry'!C20, "") | D19: =IF('Inter O&M Entry'!D20<>"", 'Inter O&M Entry'!D20, "") | E19: =IF($A19<>"", (IF('Inter O&M Entry'!I20="Y", ((($B19*$D19)*((1+$B$5)^E$7))*(1/((1+$N$5)^E$7))), 0)), "") | F19: =IF($A19<>"", (IF('Inter O&M Entry'!J20="Y", ((($B19*$D19)*((1+$B$5)^F$7))*(1/((1+$N$5)^F$7))), 0)), "") | G19: =IF($A19<>"", (IF('Inter O&M Entry'!K20="Y", ((($B19*$D19)*((1+$B$5)^G$7))*(1/((1+$N$5)^G$7))), 0)), "") | H19: =IF($A19<>"", (IF('Inter O&M Entry'!L20="Y", ((($B19*$D19)*((1+$B$5)^H$7))*(1/((1+$N$5)^H$7))), 0)), "") | I19: =IF($A19<>"", (IF('Inter O&M Entry'!M20="Y", ((($B19*$D19)*((1+$B$5)^I$7))*(1/((1+$N$5)^I$7))), 0)), "") | J19: =IF($A19<>"", (IF('Inter O&M Entry'!N20="Y", ((($B19*$D19)*((1+$B$5)^J$7))*(1/((1+$N$5)^J$7))), 0)), "") | K19: =IF($A19<>"", (IF('Inter O&M Entry'!O20="Y", ((($B19*$D19)*((1+$B$5)^K$7))*(1/((1+$N$5)^K$7))), 0)), "") | L19: =IF($A19<>"", (IF('Inter O&M Entry'!P20="Y", ((($B19*$D19)*((1+$B$5)^L$7))*(1/((1+$N$5)^L$7))), 0)), "") | ... N19: =IF($A19<>"", (IF('Inter O&M Entry'!R20="Y", ((($B19*$D19)*((1+$B$5)^N$7))*(1/((1+$N$5)^N$7))), 0)), "")
D20: Total Present Value of Intermittent Operations & Maintenace Costs (Years 1-10): | E20: =SUM(E8:E19) -> 0 | F20: =SUM(F8:F19) -> 0 | G20: =SUM(G8:G19) -> 0 | H20: =SUM(H8:H19) -> 0 | I20: =SUM(I8:I19) -> 0 | J20: =SUM(J8:J19) -> 0 | K20: =SUM(K8:K19) -> 0 | L20: =SUM(L8:L19) -> 0 | ... N20: =SUM(N8:N19) -> 0

Sheet Inter O&M 11-20
A1: Table 5.2.10. Present Value of Intermittent Operations and Maintenance Costs (Years 11-20)
A2: =Input!B4 -> 0
A3: =Input!B5 -> 0
A4: =Input!B6 -> 0
A5: ='Yearly O&M Costs 1-10'!A6 -> Current Inflation Rate Based on Municipal Cost Index: | B5: ='Yearly O&M Costs 11-20'!B5 -> 0.027598896 | M5: EPA Discount Rate: | N5: ='Yearly O&M Costs 11-20'!N5 -> 0.04875
E6: Present Value of O&M Costs for Year:
A7: Component | B7: Unit Cost | C7: Unit | D7: Quantity | E7: 11 | F7: 12 | G7: 13 | H7: 14 | I7: 15 | J7: 16 | K7: 17 | L7: 18 | M7: 19 | N7: 20
A8: =IF('Inter O&M Entry'!A9<>"", 'Inter O&M Entry'!A9, "") | B8: =IF('Inter O&M Entry'!B9<>"", 'Inter O&M Entry'!B9, "") | C8: =IF('Inter O&M Entry'!C9<>"", 'Inter O&M Entry'!C9, "") | D8: =IF('Inter O&M Entry'!D9<>"", 'Inter O&M Entry'!D9, "") | E8: =IF($A8<>"", (IF('Inter O&M Entry'!I9="Y", ((($B8*$D8)*((1+$B$5)^E$7))*(1/((1+$N$5)^E$7))), 0)), "") | F8: =IF($A8<>"", (IF('Inter O&M Entry'!J9="Y", ((($B8*$D8)*((1+$B$5)^F$7))*(1/((1+$N$5)^F$7))), 0)), "") | G8: =IF($A8<>"", (IF('Inter O&M Entry'!K9="Y", ((($B8*$D8)*((1+$B$5)^G$7))*(1/((1+$N$5)^G$7))), 0)), "") | H8: =IF($A8<>"", (IF('Inter O&M Entry'!L9="Y", ((($B8*$D8)*((1+$B$5)^H$7))*(1/((1+$N$5)^H$7))), 0)), "") | I8: =IF($A8<>"", (IF('Inter O&M Entry'!M9="Y", ((($B8*$D8)*((1+$B$5)^I$7))*(1/((1+$N$5)^I$7))), 0)), "") | J8: =IF($A8<>"", (IF('Inter O&M Entry'!N9="Y", ((($B8*$D8)*((1+$B$5)^J$7))*(1/((1+$N$5)^J$7))), 0)), "") | K8: =IF($A8<>"", (IF('Inter O&M Entry'!O9="Y", ((($B8*$D8)*((1+$B$5)^K$7))*(1/((1+$N$5)^K$7))), 0)), "") | L8: =IF($A8<>"", (IF('Inter O&M Entry'!P9="Y", ((($B8*$D8)*((1+$B$5)^L$7))*(1/((1+$N$5)^L$7))), 0)), "") | ... N8: =IF($A8<>"", (IF('Inter O&M Entry'!R9="Y", ((($B8*$D8)*((1+$B$5)^N$7))*(1/((1+$N$5)^N$7))), 0)), "")
A9: =IF('Inter O&M Entry'!A10<>"", 'Inter O&M Entry'!A10, "") | B9: =IF('Inter O&M Entry'!B10<>"", 'Inter O&M Entry'!B10, "") | C9: =IF('Inter O&M Entry'!C10<>"", 'Inter O&M Entry'!C10, "") | D9: =IF('Inter O&M Entry'!D10<>"", 'Inter O&M Entry'!D10, "") | E9: =IF($A9<>"", (IF('Inter O&M Entry'!I10="Y", ((($B9*$D9)*((1+$B$5)^E$7))*(1/((1+$N$5)^E$7))), 0)), "") | F9: =IF($A9<>"", (IF('Inter O&M Entry'!J10="Y", ((($B9*$D9)*((1+$B$5)^F$7))*(1/((1+$N$5)^F$7))), 0)), "") | G9: =IF($A9<>"", (IF('Inter O&M Entry'!K10="Y", ((($B9*$D9)*((1+$B$5)^G$7))*(1/((1+$N$5)^G$7))), 0)), "") | H9: =IF($A9<>"", (IF('Inter O&M Entry'!L10="Y", ((($B9*$D9)*((1+$B$5)^H$7))*(1/((1+$N$5)^H$7))), 0)), "") | I9: =IF($A9<>"", (IF('Inter O&M Entry'!M10="Y", ((($B9*$D9)*((1+$B$5)^I$7))*(1/((1+$N$5)^I$7))), 0)), "") | J9: =IF($A9<>"", (IF('Inter O&M Entry'!N10="Y", ((($B9*$D9)*((1+$B$5)^J$7))*(1/((1+$N$5)^J$7))), 0)), "") | K9: =IF($A9<>"", (IF('Inter O&M Entry'!O10="Y", ((($B9*$D9)*((1+$B$5)^K$7))*(1/((1+$N$5)^K$7))), 0)), "") | L9: =IF($A9<>"", (IF('Inter O&M Entry'!P10="Y", ((($B9*$D9)*((1+$B$5)^L$7))*(1/((1+$N$5)^L$7))), 0)), "") | ... N9: =IF($A9<>"", (IF('Inter O&M Entry'!R10="Y", ((($B9*$D9)*((1+$B$5)^N$7))*(1/((1+$N$5)^N$7))), 0)), "")
A10: =IF('Inter O&M Entry'!A11<>"", 'Inter O&M Entry'!A11, "") | B10: =IF('Inter O&M Entry'!B11<>"", 'Inter O&M Entry'!B11, "") | C10: =IF('Inter O&M Entry'!C11<>"", 'Inter O&M Entry'!C11, "") | D10: =IF('Inter O&M Entry'!D11<>"", 'Inter O&M Entry'!D11, "") | E10: =IF($A10<>"", (IF('Inter O&M Entry'!I11="Y", ((($B10*$D10)*((1+$B$5)^E$7))*(1/((1+$N$5)^E$7))), 0)), "") | F10: =IF($A10<>"", (IF('Inter O&M Entry'!J11="Y", ((($B10*$D10)*((1+$B$5)^F$7))*(1/((1+$N$5)^F$7))), 0)), "") | G10: =IF($A10<>"", (IF('Inter O&M Entry'!K11="Y", ((($B10*$D10)*((1+$B$5)^G$7))*(1/((1+$N$5)^G$7))), 0)), "") | H10: =IF($A10<>"", (IF('Inter O&M Entry'!L11="Y", ((($B10*$D10)*((1+$B$5)^H$7))*(1/((1+$N$5)^H$7))), 0)), "") | I10: =IF($A10<>"", (IF('Inter O&M Entry'!M11="Y", ((($B10*$D10)*((1+$B$5)^I$7))*(1/((1+$N$5)^I$7))), 0)), "") | J10: =IF($A10<>"", (IF('Inter O&M Entry'!N11="Y", ((($B10*$D10)*((1+$B$5)^J$7))*(1/((1+$N$5)^J$7))), 0)), "") | K10: =IF($A10<>"", (IF('Inter O&M Entry'!O11="Y", ((($B10*$D10)*((1+$B$5)^K$7))*(1/((1+$N$5)^K$7))), 0)), "") | L10: =IF($A10<>"", (IF('Inter O&M Entry'!P11="Y", ((($B10*$D10)*((1+$B$5)^L$7))*(1/((1+$N$5)^L$7))), 0)), "") | ... N10: =IF($A10<>"", (IF('Inter O&M Entry'!R11="Y", ((($B10*$D10)*((1+$B$5)^N$7))*(1/((1+$N$5)^N$7))), 0)), "")
A11: =IF('Inter O&M Entry'!A12<>"", 'Inter O&M Entry'!A12, "") | B11: =IF('Inter O&M Entry'!B12<>"", 'Inter O&M Entry'!B12, "") | C11: =IF('Inter O&M Entry'!C12<>"", 'Inter O&M Entry'!C12, "") | D11: =IF('Inter O&M Entry'!D12<>"", 'Inter O&M Entry'!D12, "") | E11: =IF($A11<>"", (IF('Inter O&M Entry'!I12="Y", ((($B11*$D11)*((1+$B$5)^E$7))*(1/((1+$N$5)^E$7))), 0)), "") | F11: =IF($A11<>"", (IF('Inter O&M Entry'!J12="Y", ((($B11*$D11)*((1+$B$5)^F$7))*(1/((1+$N$5)^F$7))), 0)), "") | G11: =IF($A11<>"", (IF('Inter O&M Entry'!K12="Y", ((($B11*$D11)*((1+$B$5)^G$7))*(1/((1+$N$5)^G$7))), 0)), "") | H11: =IF($A11<>"", (IF('Inter O&M Entry'!L12="Y", ((($B11*$D11)*((1+$B$5)^H$7))*(1/((1+$N$5)^H$7))), 0)), "") | I11: =IF($A11<>"", (IF('Inter O&M Entry'!M12="Y", ((($B11*$D11)*((1+$B$5)^I$7))*(1/((1+$N$5)^I$7))), 0)), "") | J11: =IF($A11<>"", (IF('Inter O&M Entry'!N12="Y", ((($B11*$D11)*((1+$B$5)^J$7))*(1/((1+$N$5)^J$7))), 0)), "") | K11: =IF($A11<>"", (IF('Inter O&M Entry'!O12="Y", ((($B11*$D11)*((1+$B$5)^K$7))*(1/((1+$N$5)^K$7))), 0)), "") | L11: =IF($A11<>"", (IF('Inter O&M Entry'!P12="Y", ((($B11*$D11)*((1+$B$5)^L$7))*(1/((1+$N$5)^L$7))), 0)), "") | ... N11: =IF($A11<>"", (IF('Inter O&M Entry'!R12="Y", ((($B11*$D11)*((1+$B$5)^N$7))*(1/((1+$N$5)^N$7))), 0)), "")
A12: =IF('Inter O&M Entry'!A13<>"", 'Inter O&M Entry'!A13, "") | B12: =IF('Inter O&M Entry'!B13<>"", 'Inter O&M Entry'!B13, "") | C12: =IF('Inter O&M Entry'!C13<>"", 'Inter O&M Entry'!C13, "") | D12: =IF('Inter O&M Entry'!D13<>"", 'Inter O&M Entry'!D13, "") | E12: =IF($A12<>"", (IF('Inter O&M Entry'!I13="Y", ((($B12*$D12)*((1+$B$5)^E$7))*(1/((1+$N$5)^E$7))), 0)), "") | F12: =IF($A12<>"", (IF('Inter O&M Entry'!J13="Y", ((($B12*$D12)*((1+$B$5)^F$7))*(1/((1+$N$5)^F$7))), 0)), "") | G12: =IF($A12<>"", (IF('Inter O&M Entry'!K13="Y", ((($B12*$D12)*((1+$B$5)^G$7))*(1/((1+$N$5)^G$7))), 0)), "") | H12: =IF($A12<>"", (IF('Inter O&M Entry'!L13="Y", ((($B12*$D12)*((1+$B$5)^H$7))*(1/((1+$N$5)^H$7))), 0)), "") | I12: =IF($A12<>"", (IF('Inter O&M Entry'!M13="Y", ((($B12*$D12)*((1+$B$5)^I$7))*(1/((1+$N$5)^I$7))), 0)), "") | J12: =IF($A12<>"", (IF('Inter O&M Entry'!N13="Y", ((($B12*$D12)*((1+$B$5)^J$7))*(1/((1+$N$5)^J$7))), 0)), "") | K12: =IF($A12<>"", (IF('Inter O&M Entry'!O13="Y", ((($B12*$D12)*((1+$B$5)^K$7))*(1/((1+$N$5)^K$7))), 0)), "") | L12: =IF($A12<>"", (IF('Inter O&M Entry'!P13="Y", ((($B12*$D12)*((1+$B$5)^L$7))*(1/((1+$N$5)^L$7))), 0)), "") | ... N12: =IF($A12<>"", (IF('Inter O&M Entry'!R13="Y", ((($B12*$D12)*((1+$B$5)^N$7))*(1/((1+$N$5)^N$7))), 0)), "")
A13: =IF('Inter O&M Entry'!A14<>"", 'Inter O&M Entry'!A14, "") | B13: =IF('Inter O&M Entry'!B14<>"", 'Inter O&M Entry'!B14, "") | C13: =IF('Inter O&M Entry'!C14<>"", 'Inter O&M Entry'!C14, "") | D13: =IF('Inter O&M Entry'!D14<>"", 'Inter O&M Entry'!D14, "") | E13: =IF($A13<>"", (IF('Inter O&M Entry'!I14="Y", ((($B13*$D13)*((1+$B$5)^E$7))*(1/((1+$N$5)^E$7))), 0)), "") | F13: =IF($A13<>"", (IF('Inter O&M Entry'!J14="Y", ((($B13*$D13)*((1+$B$5)^F$7))*(1/((1+$N$5)^F$7))), 0)), "") | G13: =IF($A13<>"", (IF('Inter O&M Entry'!K14="Y", ((($B13*$D13)*((1+$B$5)^G$7))*(1/((1+$N$5)^G$7))), 0)), "") | H13: =IF($A13<>"", (IF('Inter O&M Entry'!L14="Y", ((($B13*$D13)*((1+$B$5)^H$7))*(1/((1+$N$5)^H$7))), 0)), "") | I13: =IF($A13<>"", (IF('Inter O&M Entry'!M14="Y", ((($B13*$D13)*((1+$B$5)^I$7))*(1/((1+$N$5)^I$7))), 0)), "") | J13: =IF($A13<>"", (IF('Inter O&M Entry'!N14="Y", ((($B13*$D13)*((1+$B$5)^J$7))*(1/((1+$N$5)^J$7))), 0)), "") | K13: =IF($A13<>"", (IF('Inter O&M Entry'!O14="Y", ((($B13*$D13)*((1+$B$5)^K$7))*(1/((1+$N$5)^K$7))), 0)), "") | L13: =IF($A13<>"", (IF('Inter O&M Entry'!P14="Y", ((($B13*$D13)*((1+$B$5)^L$7))*(1/((1+$N$5)^L$7))), 0)), "") | ... N13: =IF($A13<>"", (IF('Inter O&M Entry'!R14="Y", ((($B13*$D13)*((1+$B$5)^N$7))*(1/((1+$N$5)^N$7))), 0)), "")
A14: =IF('Inter O&M Entry'!A15<>"", 'Inter O&M Entry'!A15, "") | B14: =IF('Inter O&M Entry'!B15<>"", 'Inter O&M Entry'!B15, "") | C14: =IF('Inter O&M Entry'!C15<>"", 'Inter O&M Entry'!C15, "") | D14: =IF('Inter O&M Entry'!D15<>"", 'Inter O&M Entry'!D15, "") | E14: =IF($A14<>"", (IF('Inter O&M Entry'!I15="Y", ((($B14*$D14)*((1+$B$5)^E$7))*(1/((1+$N$5)^E$7))), 0)), "") | F14: =IF($A14<>"", (IF('Inter O&M Entry'!J15="Y", ((($B14*$D14)*((1+$B$5)^F$7))*(1/((1+$N$5)^F$7))), 0)), "") | G14: =IF($A14<>"", (IF('Inter O&M Entry'!K15="Y", ((($B14*$D14)*((1+$B$5)^G$7))*(1/((1+$N$5)^G$7))), 0)), "") | H14: =IF($A14<>"", (IF('Inter O&M Entry'!L15="Y", ((($B14*$D14)*((1+$B$5)^H$7))*(1/((1+$N$5)^H$7))), 0)), "") | I14: =IF($A14<>"", (IF('Inter O&M Entry'!M15="Y", ((($B14*$D14)*((1+$B$5)^I$7))*(1/((1+$N$5)^I$7))), 0)), "") | J14: =IF($A14<>"", (IF('Inter O&M Entry'!N15="Y", ((($B14*$D14)*((1+$B$5)^J$7))*(1/((1+$N$5)^J$7))), 0)), "") | K14: =IF($A14<>"", (IF('Inter O&M Entry'!O15="Y", ((($B14*$D14)*((1+$B$5)^K$7))*(1/((1+$N$5)^K$7))), 0)), "") | L14: =IF($A14<>"", (IF('Inter O&M Entry'!P15="Y", ((($B14*$D14)*((1+$B$5)^L$7))*(1/((1+$N$5)^L$7))), 0)), "") | ... N14: =IF($A14<>"", (IF('Inter O&M Entry'!R15="Y", ((($B14*$D14)*((1+$B$5)^N$7))*(1/((1+$N$5)^N$7))), 0)), "")
A15: =IF('Inter O&M Entry'!A16<>"", 'Inter O&M Entry'!A16, "") | B15: =IF('Inter O&M Entry'!B16<>"", 'Inter O&M Entry'!B16, "") | C15: =IF('Inter O&M Entry'!C16<>"", 'Inter O&M Entry'!C16, "") | D15: =IF('Inter O&M Entry'!D16<>"", 'Inter O&M Entry'!D16, "") | E15: =IF($A15<>"", (IF('Inter O&M Entry'!I16="Y", ((($B15*$D15)*((1+$B$5)^E$7))*(1/((1+$N$5)^E$7))), 0)), "") | F15: =IF($A15<>"", (IF('Inter O&M Entry'!J16="Y", ((($B15*$D15)*((1+$B$5)^F$7))*(1/((1+$N$5)^F$7))), 0)), "") | G15: =IF($A15<>"", (IF('Inter O&M Entry'!K16="Y", ((($B15*$D15)*((1+$B$5)^G$7))*(1/((1+$N$5)^G$7))), 0)), "") | H15: =IF($A15<>"", (IF('Inter O&M Entry'!L16="Y", ((($B15*$D15)*((1+$B$5)^H$7))*(1/((1+$N$5)^H$7))), 0)), "") | I15: =IF($A15<>"", (IF('Inter O&M Entry'!M16="Y", ((($B15*$D15)*((1+$B$5)^I$7))*(1/((1+$N$5)^I$7))), 0)), "") | J15: =IF($A15<>"", (IF('Inter O&M Entry'!N16="Y", ((($B15*$D15)*((1+$B$5)^J$7))*(1/((1+$N$5)^J$7))), 0)), "") | K15: =IF($A15<>"", (IF('Inter O&M Entry'!O16="Y", ((($B15*$D15)*((1+$B$5)^K$7))*(1/((1+$N$5)^K$7))), 0)), "") | L15: =IF($A15<>"", (IF('Inter O&M Entry'!P16="Y", ((($B15*$D15)*((1+$B$5)^L$7))*(1/((1+$N$5)^L$7))), 0)), "") | ... N15: =IF($A15<>"", (IF('Inter O&M Entry'!R16="Y", ((($B15*$D15)*((1+$B$5)^N$7))*(1/((1+$N$5)^N$7))), 0)), "")
A16: =IF('Inter O&M Entry'!A17<>"", 'Inter O&M Entry'!A17, "") | B16: =IF('Inter O&M Entry'!B17<>"", 'Inter O&M Entry'!B17, "") | C16: =IF('Inter O&M Entry'!C17<>"", 'Inter O&M Entry'!C17, "") | D16: =IF('Inter O&M Entry'!D17<>"", 'Inter O&M Entry'!D17, "") | E16: =IF($A16<>"", (IF('Inter O&M Entry'!I17="Y", ((($B16*$D16)*((1+$B$5)^E$7))*(1/((1+$N$5)^E$7))), 0)), "") | F16: =IF($A16<>"", (IF('Inter O&M Entry'!J17="Y", ((($B16*$D16)*((1+$B$5)^F$7))*(1/((1+$N$5)^F$7))), 0)), "") | G16: =IF($A16<>"", (IF('Inter O&M Entry'!K17="Y", ((($B16*$D16)*((1+$B$5)^G$7))*(1/((1+$N$5)^G$7))), 0)), "") | H16: =IF($A16<>"", (IF('Inter O&M Entry'!L17="Y", ((($B16*$D16)*((1+$B$5)^H$7))*(1/((1+$N$5)^H$7))), 0)), "") | I16: =IF($A16<>"", (IF('Inter O&M Entry'!M17="Y", ((($B16*$D16)*((1+$B$5)^I$7))*(1/((1+$N$5)^I$7))), 0)), "") | J16: =IF($A16<>"", (IF('Inter O&M Entry'!N17="Y", ((($B16*$D16)*((1+$B$5)^J$7))*(1/((1+$N$5)^J$7))), 0)), "") | K16: =IF($A16<>"", (IF('Inter O&M Entry'!O17="Y", ((($B16*$D16)*((1+$B$5)^K$7))*(1/((1+$N$5)^K$7))), 0)), "") | L16: =IF($A16<>"", (IF('Inter O&M Entry'!P17="Y", ((($B16*$D16)*((1+$B$5)^L$7))*(1/((1+$N$5)^L$7))), 0)), "") | ... N16: =IF($A16<>"", (IF('Inter O&M Entry'!R17="Y", ((($B16*$D16)*((1+$B$5)^N$7))*(1/((1+$N$5)^N$7))), 0)), "")
A17: =IF('Inter O&M Entry'!A18<>"", 'Inter O&M Entry'!A18, "") | B17: =IF('Inter O&M Entry'!B18<>"", 'Inter O&M Entry'!B18, "") | C17: =IF('Inter O&M Entry'!C18<>"", 'Inter O&M Entry'!C18, "") | D17: =IF('Inter O&M Entry'!D18<>"", 'Inter O&M Entry'!D18, "") | E17: =IF($A17<>"", (IF('Inter O&M Entry'!I18="Y", ((($B17*$D17)*((1+$B$5)^E$7))*(1/((1+$N$5)^E$7))), 0)), "") | F17: =IF($A17<>"", (IF('Inter O&M Entry'!J18="Y", ((($B17*$D17)*((1+$B$5)^F$7))*(1/((1+$N$5)^F$7))), 0)), "") | G17: =IF($A17<>"", (IF('Inter O&M Entry'!K18="Y", ((($B17*$D17)*((1+$B$5)^G$7))*(1/((1+$N$5)^G$7))), 0)), "") | H17: =IF($A17<>"", (IF('Inter O&M Entry'!L18="Y", ((($B17*$D17)*((1+$B$5)^H$7))*(1/((1+$N$5)^H$7))), 0)), "") | I17: =IF($A17<>"", (IF('Inter O&M Entry'!M18="Y", ((($B17*$D17)*((1+$B$5)^I$7))*(1/((1+$N$5)^I$7))), 0)), "") | J17: =IF($A17<>"", (IF('Inter O&M Entry'!N18="Y", ((($B17*$D17)*((1+$B$5)^J$7))*(1/((1+$N$5)^J$7))), 0)), "") | K17: =IF($A17<>"", (IF('Inter O&M Entry'!O18="Y", ((($B17*$D17)*((1+$B$5)^K$7))*(1/((1+$N$5)^K$7))), 0)), "") | L17: =IF($A17<>"", (IF('Inter O&M Entry'!P18="Y", ((($B17*$D17)*((1+$B$5)^L$7))*(1/((1+$N$5)^L$7))), 0)), "") | ... N17: =IF($A17<>"", (IF('Inter O&M Entry'!R18="Y", ((($B17*$D17)*((1+$B$5)^N$7))*(1/((1+$N$5)^N$7))), 0)), "")
A18: =IF('Inter O&M Entry'!A19<>"", 'Inter O&M Entry'!A19, "") | B18: =IF('Inter O&M Entry'!B19<>"", 'Inter O&M Entry'!B19, "") | C18: =IF('Inter O&M Entry'!C19<>"", 'Inter O&M Entry'!C19, "") | D18: =IF('Inter O&M Entry'!D19<>"", 'Inter O&M Entry'!D19, "") | E18: =IF($A18<>"", (IF('Inter O&M Entry'!I19="Y", ((($B18*$D18)*((1+$B$5)^E$7))*(1/((1+$N$5)^E$7))), 0)), "") | F18: =IF($A18<>"", (IF('Inter O&M Entry'!J19="Y", ((($B18*$D18)*((1+$B$5)^F$7))*(1/((1+$N$5)^F$7))), 0)), "") | G18: =IF($A18<>"", (IF('Inter O&M Entry'!K19="Y", ((($B18*$D18)*((1+$B$5)^G$7))*(1/((1+$N$5)^G$7))), 0)), "") | H18: =IF($A18<>"", (IF('Inter O&M Entry'!L19="Y", ((($B18*$D18)*((1+$B$5)^H$7))*(1/((1+$N$5)^H$7))), 0)), "") | I18: =IF($A18<>"", (IF('Inter O&M Entry'!M19="Y", ((($B18*$D18)*((1+$B$5)^I$7))*(1/((1+$N$5)^I$7))), 0)), "") | J18: =IF($A18<>"", (IF('Inter O&M Entry'!N19="Y", ((($B18*$D18)*((1+$B$5)^J$7))*(1/((1+$N$5)^J$7))), 0)), "") | K18: =IF($A18<>"", (IF('Inter O&M Entry'!O19="Y", ((($B18*$D18)*((1+$B$5)^K$7))*(1/((1+$N$5)^K$7))), 0)), "") | L18: =IF($A18<>"", (IF('Inter O&M Entry'!P19="Y", ((($B18*$D18)*((1+$B$5)^L$7))*(1/((1+$N$5)^L$7))), 0)), "") | ... N18: =IF($A18<>"", (IF('Inter O&M Entry'!R19="Y", ((($B18*$D18)*((1+$B$5)^N$7))*(1/((1+$N$5)^N$7))), 0)), "")
A19: =IF('Inter O&M Entry'!A20<>"", 'Inter O&M Entry'!A20, "") | B19: =IF('Inter O&M Entry'!B20<>"", 'Inter O&M Entry'!B20, "") | C19: =IF('Inter O&M Entry'!C20<>"", 'Inter O&M Entry'!C20, "") | D19: =IF('Inter O&M Entry'!D20<>"", 'Inter O&M Entry'!D20, "") | E19: =IF($A19<>"", (IF('Inter O&M Entry'!I20="Y", ((($B19*$D19)*((1+$B$5)^E$7))*(1/((1+$N$5)^E$7))), 0)), "") | F19: =IF($A19<>"", (IF('Inter O&M Entry'!J20="Y", ((($B19*$D19)*((1+$B$5)^F$7))*(1/((1+$N$5)^F$7))), 0)), "") | G19: =IF($A19<>"", (IF('Inter O&M Entry'!K20="Y", ((($B19*$D19)*((1+$B$5)^G$7))*(1/((1+$N$5)^G$7))), 0)), "") | H19: =IF($A19<>"", (IF('Inter O&M Entry'!L20="Y", ((($B19*$D19)*((1+$B$5)^H$7))*(1/((1+$N$5)^H$7))), 0)), "") | I19: =IF($A19<>"", (IF('Inter O&M Entry'!M20="Y", ((($B19*$D19)*((1+$B$5)^I$7))*(1/((1+$N$5)^I$7))), 0)), "") | J19: =IF($A19<>"", (IF('Inter O&M Entry'!N20="Y", ((($B19*$D19)*((1+$B$5)^J$7))*(1/((1+$N$5)^J$7))), 0)), "") | K19: =IF($A19<>"", (IF('Inter O&M Entry'!O20="Y", ((($B19*$D19)*((1+$B$5)^K$7))*(1/((1+$N$5)^K$7))), 0)), "") | L19: =IF($A19<>"", (IF('Inter O&M Entry'!P20="Y", ((($B19*$D19)*((1+$B$5)^L$7))*(1/((1+$N$5)^L$7))), 0)), "") | ... N19: =IF($A19<>"", (IF('Inter O&M Entry'!R20="Y", ((($B19*$D19)*((1+$B$5)^N$7))*(1/((1+$N$5)^N$7))), 0)), "")
D20: Total Present Value of Intermittent Operations & Maintenace Costs (Years 11-20): | E20: =SUM(E8:E19) -> 0 | F20: =SUM(F8:F19) -> 0 | G20: =SUM(G8:G19) -> 0 | H20: =SUM(H8:H19) -> 0 | I20: =SUM(I8:I19) -> 0 | J20: =SUM(J8:J19) -> 0 | K20: =SUM(K8:K19) -> 0 | L20: =SUM(L8:L19) -> 0 | ... N20: =SUM(N8:N19) -> 0
M21: Total Present Value of Intermittent Operations & Maintenance Costs (Life of Project): | N21: ='Inter O&M 1-10'!E20+'Inter O&M 1-10'!F20+'Inter O&M 1-10'!G20+'Inter O&M 1-10'!H20+'Inter O&M 1-10'!I20+'Inter O&M 1-10'!J20+'Inter O&M 1-10'!K20+'Inter O&M 1-10'!L20+'Inter O&M 1-10'!M20+'Inter O&M 1-10'!N20+'Inter O&M 11-20'!E20+'Inter O&M 11-20'!F20+'Inter O&M 11-20'!G20+'Inter O&M 11-20'!H20+'Inter O&M 11-20'!I20+'Inter O&M 11-20'!J20+'Inter O&M 11-20'!K20+'Inter O&M 11-20'!L20+'Inter O&M 11-20'!M20+'Inter O&M 11-20'!N20 -> 0

Sheet 2Capital Costs
A2: Table 5.2.11. Capital Costs
A3: =Input!B4 -> 0
A4: =Input!B5 -> 0
A5: Complete the areas shown in gray below. Where shown, use pulldown menus to select options. The spreadsheet will calculate the capital costs.
A6: Alternative:
A7: Project Administration ($):
A8: Component | B8: Unit Costa | C8: Unit | D8: Quantity | E8: Total Cost
E9: =B9*D9 -> 0
E10: =B10*D10 -> 0
E11: =B11*D11 -> 0
E12: =B12*D12 -> 0
E13: =B13*D13 -> 0
E14: =B14*D14 -> 0
E15: =B15*D15 -> 0
E16: =B16*D16 -> 0
E17: =B17*D17 -> 0
E18: =B18*D18 -> 0
E19: =B19*D19 -> 0
E20: =B20*D20 -> 0
... E37: =B37*D37 -> 0
A38: aUnit costs are in today's dollars, not future dollars. | D38: Total Construction Cost: | E38: =SUM(E9:E37) -> 0
D39: Construction Contingency Cost: | E39: =E38*$B$42 -> 0
D40: Project Administration Cost: | E40: =B7 -> 0
D41: Total Capital Cost: | E41: =SUM(E38:E40) -> 0
A42: Construction Contingency: | B42: 0.1

Sheet 2Replacement Costs - Entry
A1: Replacement Costs Input
A3: Alternative: | B3: ='2Capital Costs'!B6 -> 0
A5: For each component, enter "Y" in the gray area in the year in which replacement, if any, will occur.
J7: Year Replacement Needed? (Insert Y in year where replacement is needed.)
A8: Component | B8: Unit Cost | C8: Unit | D8: Quantity | E8: Replacement Needed? (Years 1-5) | F8: Replacement Needed? (Years 6-10) | G8: Replacement Needed (Years 11-15) | H8: Replacement Needed? (Years 16-20) | I8: Replacement Needed? (Years 1-20) | J8: 1 | K8: 2 | L8: 3 | M8: 4 | N8: 5 | O8: 6 | P8: 7 | Q8: 8 | R8: 9 | S8: 10 | T8: 11 | U8: 12 | V8: 13 | W8: 14 | X8: 15 | Y8: 16 | Z8: 17 | AA8: 18 | AB8: 19 | AC8: 20
A9: ='2Capital Costs'!A9 -> 0 | B9: ='2Capital Costs'!B9 -> 0 | C9: ='2Capital Costs'!C9 -> 0 | D9: ='2Capital Costs'!D9 -> 0 | E9: =IF(N9="Y", "Y", (IF(M9="Y", "Y", (IF(L9="Y", "Y", (IF(K9="Y", "Y", (IF(J9="Y", "Y", " "))))))))) | F9: =IF(S9="Y", "Y", (IF(R9="Y", "Y", (IF(Q9="Y", "Y", (IF(P9="Y", "Y", (IF(O9="Y", "Y", " "))))))))) | G9: =IF(X9="Y", "Y", (IF(W9="Y", "Y", (IF(V9="Y", "Y", (IF(U9="Y", "Y", (IF(T9="Y", "Y", " "))))))))) | H9: =IF(AC9="Y", "Y", (IF(AB9="Y", "Y", (IF(AA9="Y", "Y", (IF(Z9="Y", "Y", (IF(Y9="Y", "Y", " "))))))))) | I9: =IF(H9="Y", "Y", (IF(G9="Y", "Y", (IF(F9="Y", "Y", (IF(E9="Y", "Y", " ")))))))
A10: ='2Capital Costs'!A10 -> 0 | B10: ='2Capital Costs'!B10 -> 0 | C10: ='2Capital Costs'!C10 -> 0 | D10: ='2Capital Costs'!D10 -> 0 | E10: =IF(N10="Y", "Y", (IF(M10="Y", "Y", (IF(L10="Y", "Y", (IF(K10="Y", "Y", (IF(J10="Y", "Y", " "))))))))) | F10: =IF(S10="Y", "Y", (IF(R10="Y", "Y", (IF(Q10="Y", "Y", (IF(P10="Y", "Y", (IF(O10="Y", "Y", " "))))))))) | G10: =IF(X10="Y", "Y", (IF(W10="Y", "Y", (IF(V10="Y", "Y", (IF(U10="Y", "Y", (IF(T10="Y", "Y", " "))))))))) | H10: =IF(AC10="Y", "Y", (IF(AB10="Y", "Y", (IF(AA10="Y", "Y", (IF(Z10="Y", "Y", (IF(Y10="Y", "Y", " "))))))))) | I10: =IF(H10="Y", "Y", (IF(G10="Y", "Y", (IF(F10="Y", "Y", (IF(E10="Y", "Y", " ")))))))
A11: ='2Capital Costs'!A11 -> 0 | B11: ='2Capital Costs'!B11 -> 0 | C11: ='2Capital Costs'!C11 -> 0 | D11: ='2Capital Costs'!D11 -> 0 | E11: =IF(N11="Y", "Y", (IF(M11="Y", "Y", (IF(L11="Y", "Y", (IF(K11="Y", "Y", (IF(J11="Y", "Y", " "))))))))) | F11: =IF(S11="Y", "Y", (IF(R11="Y", "Y", (IF(Q11="Y", "Y", (IF(P11="Y", "Y", (IF(O11="Y", "Y", " "))))))))) | G11: =IF(X11="Y", "Y", (IF(W11="Y", "Y", (IF(V11="Y", "Y", (IF(U11="Y", "Y", (IF(T11="Y", "Y", " "))))))))) | H11: =IF(AC11="Y", "Y", (IF(AB11="Y", "Y", (IF(AA11="Y", "Y", (IF(Z11="Y", "Y", (IF(Y11="Y", "Y", " "))))))))) | I11: =IF(H11="Y", "Y", (IF(G11="Y", "Y", (IF(F11="Y", "Y", (IF(E11="Y", "Y", " ")))))))
A12: ='2Capital Costs'!A12 -> 0 | B12: ='2Capital Costs'!B12 -> 0 | C12: ='2Capital Costs'!C12 -> 0 | D12: ='2Capital Costs'!D12 -> 0 | E12: =IF(N12="Y", "Y", (IF(M12="Y", "Y", (IF(L12="Y", "Y", (IF(K12="Y", "Y", (IF(J12="Y", "Y", " "))))))))) | F12: =IF(S12="Y", "Y", (IF(R12="Y", "Y", (IF(Q12="Y", "Y", (IF(P12="Y", "Y", (IF(O12="Y", "Y", " "))))))))) | G12: =IF(X12="Y", "Y", (IF(W12="Y", "Y", (IF(V12="Y", "Y", (IF(U12="Y", "Y", (IF(T12="Y", "Y", " "))))))))) | H12: =IF(AC12="Y", "Y", (IF(AB12="Y", "Y", (IF(AA12="Y", "Y", (IF(Z12="Y", "Y", (IF(Y12="Y", "Y", " "))))))))) | I12: =IF(H12="Y", "Y", (IF(G12="Y", "Y", (IF(F12="Y", "Y", (IF(E12="Y", "Y", " ")))))))
A13: ='2Capital Costs'!A13 -> 0 | B13: ='2Capital Costs'!B13 -> 0 | C13: ='2Capital Costs'!C13 -> 0 | D13: ='2Capital Costs'!D13 -> 0 | E13: =IF(N13="Y", "Y", (IF(M13="Y", "Y", (IF(L13="Y", "Y", (IF(K13="Y", "Y", (IF(J13="Y", "Y", " "))))))))) | F13: =IF(S13="Y", "Y", (IF(R13="Y", "Y", (IF(Q13="Y", "Y", (IF(P13="Y", "Y", (IF(O13="Y", "Y", " "))))))))) | G13: =IF(X13="Y", "Y", (IF(W13="Y", "Y", (IF(V13="Y", "Y", (IF(U13="Y", "Y", (IF(T13="Y", "Y", " "))))))))) | H13: =IF(AC13="Y", "Y", (IF(AB13="Y", "Y", (IF(AA13="Y", "Y", (IF(Z13="Y", "Y", (IF(Y13="Y", "Y", " "))))))))) | I13: =IF(H13="Y", "Y", (IF(G13="Y", "Y", (IF(F13="Y", "Y", (IF(E13="Y", "Y", " ")))))))
A14: ='2Capital Costs'!A14 -> 0 | B14: ='2Capital Costs'!B14 -> 0 | C14: ='2Capital Costs'!C14 -> 0 | D14: ='2Capital Costs'!D14 -> 0 | E14: =IF(N14="Y", "Y", (IF(M14="Y", "Y", (IF(L14="Y", "Y", (IF(K14="Y", "Y", (IF(J14="Y", "Y", " "))))))))) | F14: =IF(S14="Y", "Y", (IF(R14="Y", "Y", (IF(Q14="Y", "Y", (IF(P14="Y", "Y", (IF(O14="Y", "Y", " "))))))))) | G14: =IF(X14="Y", "Y", (IF(W14="Y", "Y", (IF(V14="Y", "Y", (IF(U14="Y", "Y", (IF(T14="Y", "Y", " "))))))))) | H14: =IF(AC14="Y", "Y", (IF(AB14="Y", "Y", (IF(AA14="Y", "Y", (IF(Z14="Y", "Y", (IF(Y14="Y", "Y", " "))))))))) | I14: =IF(H14="Y", "Y", (IF(G14="Y", "Y", (IF(F14="Y", "Y", (IF(E14="Y", "Y", " ")))))))
A15: ='2Capital Costs'!A15 -> 0 | B15: ='2Capital Costs'!B15 -> 0 | C15: ='2Capital Costs'!C15 -> 0 | D15: ='2Capital Costs'!D15 -> 0 | E15: =IF(N15="Y", "Y", (IF(M15="Y", "Y", (IF(L15="Y", "Y", (IF(K15="Y", "Y", (IF(J15="Y", "Y", " "))))))))) | F15: =IF(S15="Y", "Y", (IF(R15="Y", "Y", (IF(Q15="Y", "Y", (IF(P15="Y", "Y", (IF(O15="Y", "Y", " "))))))))) | G15: =IF(X15="Y", "Y", (IF(W15="Y", "Y", (IF(V15="Y", "Y", (IF(U15="Y", "Y", (IF(T15="Y", "Y", " "))))))))) | H15: =IF(AC15="Y", "Y", (IF(AB15="Y", "Y", (IF(AA15="Y", "Y", (IF(Z15="Y", "Y", (IF(Y15="Y", "Y", " "))))))))) | I15: =IF(H15="Y", "Y", (IF(G15="Y", "Y", (IF(F15="Y", "Y", (IF(E15="Y", "Y", " ")))))))
A16: ='2Capital Costs'!A16 -> 0 | B16: ='2Capital Costs'!B16 -> 0 | C16: ='2Capital Costs'!C16 -> 0 | D16: ='2Capital Costs'!D16 -> 0 | E16: =IF(N16="Y", "Y", (IF(M16="Y", "Y", (IF(L16="Y", "Y", (IF(K16="Y", "Y", (IF(J16="Y", "Y", " "))))))))) | F16: =IF(S16="Y", "Y", (IF(R16="Y", "Y", (IF(Q16="Y", "Y", (IF(P16="Y", "Y", (IF(O16="Y", "Y", " "))))))))) | G16: =IF(X16="Y", "Y", (IF(W16="Y", "Y", (IF(V16="Y", "Y", (IF(U16="Y", "Y", (IF(T16="Y", "Y", " "))))))))) | H16: =IF(AC16="Y", "Y", (IF(AB16="Y", "Y", (IF(AA16="Y", "Y", (IF(Z16="Y", "Y", (IF(Y16="Y", "Y", " "))))))))) | I16: =IF(H16="Y", "Y", (IF(G16="Y", "Y", (IF(F16="Y", "Y", (IF(E16="Y", "Y", " ")))))))
A17: ='2Capital Costs'!A17 -> 0 | B17: ='2Capital Costs'!B17 -> 0 | C17: ='2Capital Costs'!C17 -> 0 | D17: ='2Capital Costs'!D17 -> 0 | E17: =IF(N17="Y", "Y", (IF(M17="Y", "Y", (IF(L17="Y", "Y", (IF(K17="Y", "Y", (IF(J17="Y", "Y", " "))))))))) | F17: =IF(S17="Y", "Y", (IF(R17="Y", "Y", (IF(Q17="Y", "Y", (IF(P17="Y", "Y", (IF(O17="Y", "Y", " "))))))))) | G17: =IF(X17="Y", "Y", (IF(W17="Y", "Y", (IF(V17="Y", "Y", (IF(U17="Y", "Y", (IF(T17="Y", "Y", " "))))))))) | H17: =IF(AC17="Y", "Y", (IF(AB17="Y", "Y", (IF(AA17="Y", "Y", (IF(Z17="Y", "Y", (IF(Y17="Y", "Y", " "))))))))) | I17: =IF(H17="Y", "Y", (IF(G17="Y", "Y", (IF(F17="Y", "Y", (IF(E17="Y", "Y", " ")))))))
A18: ='2Capital Costs'!A18 -> 0 | B18: ='2Capital Costs'!B18 -> 0 | C18: ='2Capital Costs'!C18 -> 0 | D18: ='2Capital Costs'!D18 -> 0 | E18: =IF(N18="Y", "Y", (IF(M18="Y", "Y", (IF(L18="Y", "Y", (IF(K18="Y", "Y", (IF(J18="Y", "Y", " "))))))))) | F18: =IF(S18="Y", "Y", (IF(R18="Y", "Y", (IF(Q18="Y", "Y", (IF(P18="Y", "Y", (IF(O18="Y", "Y", " "))))))))) | G18: =IF(X18="Y", "Y", (IF(W18="Y", "Y", (IF(V18="Y", "Y", (IF(U18="Y", "Y", (IF(T18="Y", "Y", " "))))))))) | H18: =IF(AC18="Y", "Y", (IF(AB18="Y", "Y", (IF(AA18="Y", "Y", (IF(Z18="Y", "Y", (IF(Y18="Y", "Y", " "))))))))) | I18: =IF(H18="Y", "Y", (IF(G18="Y", "Y", (IF(F18="Y", "Y", (IF(E18="Y", "Y", " ")))))))
A19: ='2Capital Costs'!A19 -> 0 | B19: ='2Capital Costs'!B19 -> 0 | C19: ='2Capital Costs'!C19 -> 0 | D19: ='2Capital Costs'!D19 -> 0 | E19: =IF(N19="Y", "Y", (IF(M19="Y", "Y", (IF(L19="Y", "Y", (IF(K19="Y", "Y", (IF(J19="Y", "Y", " "))))))))) | F19: =IF(S19="Y", "Y", (IF(R19="Y", "Y", (IF(Q19="Y", "Y", (IF(P19="Y", "Y", (IF(O19="Y", "Y", " "))))))))) | G19: =IF(X19="Y", "Y", (IF(W19="Y", "Y", (IF(V19="Y", "Y", (IF(U19="Y", "Y", (IF(T19="Y", "Y", " "))))))))) | H19: =IF(AC19="Y", "Y", (IF(AB19="Y", "Y", (IF(AA19="Y", "Y", (IF(Z19="Y", "Y", (IF(Y19="Y", "Y", " "))))))))) | I19: =IF(H19="Y", "Y", (IF(G19="Y", "Y", (IF(F19="Y", "Y", (IF(E19="Y", "Y", " ")))))))
A20: ='2Capital Costs'!A20 -> 0 | B20: ='2Capital Costs'!B20 -> 0 | C20: ='2Capital Costs'!C20 -> 0 | D20: ='2Capital Costs'!D20 -> 0 | E20: =IF(N20="Y", "Y", (IF(M20="Y", "Y", (IF(L20="Y", "Y", (IF(K20="Y", "Y", (IF(J20="Y", "Y", " "))))))))) | F20: =IF(S20="Y", "Y", (IF(R20="Y", "Y", (IF(Q20="Y", "Y", (IF(P20="Y", "Y", (IF(O20="Y", "Y", " "))))))))) | G20: =IF(X20="Y", "Y", (IF(W20="Y", "Y", (IF(V20="Y", "Y", (IF(U20="Y", "Y", (IF(T20="Y", "Y", " "))))))))) | H20: =IF(AC20="Y", "Y", (IF(AB20="Y", "Y", (IF(AA20="Y", "Y", (IF(Z20="Y", "Y", (IF(Y20="Y", "Y", " "))))))))) | I20: =IF(H20="Y", "Y", (IF(G20="Y", "Y", (IF(F20="Y", "Y", (IF(E20="Y", "Y", " ")))))))
... A37: ='2Capital Costs'!A37 -> 0 | B37: ='2Capital Costs'!B37 -> 0 | C37: ='2Capital Costs'!C37 -> 0 | D37: ='2Capital Costs'!D37 -> 0 | E37: =IF(N37="Y", "Y", (IF(M37="Y", "Y", (IF(L37="Y", "Y", (IF(K37="Y", "Y", (IF(J37="Y", "Y", " "))))))))) | F37: =IF(S37="Y", "Y", (IF(R37="Y", "Y", (IF(Q37="Y", "Y", (IF(P37="Y", "Y", (IF(O37="Y", "Y", " "))))))))) | G37: =IF(X37="Y", "Y", (IF(W37="Y", "Y", (IF(V37="Y", "Y", (IF(U37="Y", "Y", (IF(T37="Y", "Y", " "))))))))) | H37: =IF(AC37="Y", "Y", (IF(AB37="Y", "Y", (IF(AA37="Y", "Y", (IF(Z37="Y", "Y", (IF(Y37="Y", "Y", " "))))))))) | I37: =IF(H37="Y", "Y", (IF(G37="Y", "Y", (IF(F37="Y", "Y", (IF(E37="Y", "Y", " ")))))))

Sheet 2Replace Costs - Results 1-5
A1: Table 5.2.13. Replacement Costs (Years 1 to 5)
A2: =Input!B4 -> 0
A3: =Input!B5 -> 0
A4: ='2Capital Costs'!B6 -> 0
A5: ='Replace Costs - Results 1-5'!A5 -> Current Inflation Rate based on Construction Cost Index: | B5: ='Replace Costs - Results 1-5'!B5 -> 0.020671835 | E5: EPA Discount Rate: | F5: ='Replace Costs - Results 1-5'!F5 -> 0.04875
E6: Present Value of Replacement Costs in Year:
A7: Component | B7: Unit Cost | C7: Unit | D7: Quantity | E7: 1 | F7: 2 | G7: 3 | H7: 4 | I7: 5
A8: =IF('2Capital Costs'!A9<>"", '2Capital Costs'!A9, "") | B8: =IF('2Capital Costs'!B9<>"", '2Capital Costs'!B9, "") | C8: =IF('2Capital Costs'!C9<>"", '2Capital Costs'!C9, "") | D8: =IF('2Capital Costs'!D9<>"", '2Capital Costs'!D9, "") | E8: =IF($A8<>"", (IF('2Replacement Costs - Entry'!J9="Y",((($B8*$D8)*((1+$B$5)^E$7))*(1/((1+$F$5)^E$7))),0)), "") | F8: =IF($A8<>"", (IF('2Replacement Costs - Entry'!K9="Y",((($B8*$D8)*((1+$B$5)^F$7))*(1/((1+$F$5)^F$7))),0)), "") | G8: =IF($A8<>"", (IF('2Replacement Costs - Entry'!L9="Y",((($B8*$D8)*((1+$B$5)^G$7))*(1/((1+$F$5)^G$7))),0)), "") | H8: =IF($A8<>"", (IF('2Replacement Costs - Entry'!M9="Y",((($B8*$D8)*((1+$B$5)^H$7))*(1/((1+$F$5)^H$7))),0)), "") | I8: =IF($A8<>"", (IF('2Replacement Costs - Entry'!N9="Y",((($B8*$D8)*((1+$B$5)^I$7))*(1/((1+$F$5)^I$7))),0)), "")
A9: =IF('2Capital Costs'!A10<>"", '2Capital Costs'!A10, "") | B9: =IF('2Capital Costs'!B10<>"", '2Capital Costs'!B10, "") | C9: =IF('2Capital Costs'!C10<>"", '2Capital Costs'!C10, "") | D9: =IF('2Capital Costs'!D10<>"", '2Capital Costs'!D10, "") | E9: =IF($A9<>"", (IF('2Replacement Costs - Entry'!J10="Y",((($B9*$D9)*((1+$B$5)^E$7))*(1/((1+$F$5)^E$7))),0)), "") | F9: =IF($A9<>"", (IF('2Replacement Costs - Entry'!K10="Y",((($B9*$D9)*((1+$B$5)^F$7))*(1/((1+$F$5)^F$7))),0)), "") | G9: =IF($A9<>"", (IF('2Replacement Costs - Entry'!L10="Y",((($B9*$D9)*((1+$B$5)^G$7))*(1/((1+$F$5)^G$7))),0)), "") | H9: =IF($A9<>"", (IF('2Replacement Costs - Entry'!M10="Y",((($B9*$D9)*((1+$B$5)^H$7))*(1/((1+$F$5)^H$7))),0)), "") | I9: =IF($A9<>"", (IF('2Replacement Costs - Entry'!N10="Y",((($B9*$D9)*((1+$B$5)^I$7))*(1/((1+$F$5)^I$7))),0)), "")
A10: =IF('2Capital Costs'!A11<>"", '2Capital Costs'!A11, "") | B10: =IF('2Capital Costs'!B11<>"", '2Capital Costs'!B11, "") | C10: =IF('2Capital Costs'!C11<>"", '2Capital Costs'!C11, "") | D10: =IF('2Capital Costs'!D11<>"", '2Capital Costs'!D11, "") | E10: =IF($A10<>"", (IF('2Replacement Costs - Entry'!J11="Y",((($B10*$D10)*((1+$B$5)^E$7))*(1/((1+$F$5)^E$7))),0)), "") | F10: =IF($A10<>"", (IF('2Replacement Costs - Entry'!K11="Y",((($B10*$D10)*((1+$B$5)^F$7))*(1/((1+$F$5)^F$7))),0)), "") | G10: =IF($A10<>"", (IF('2Replacement Costs - Entry'!L11="Y",((($B10*$D10)*((1+$B$5)^G$7))*(1/((1+$F$5)^G$7))),0)), "") | H10: =IF($A10<>"", (IF('2Replacement Costs - Entry'!M11="Y",((($B10*$D10)*((1+$B$5)^H$7))*(1/((1+$F$5)^H$7))),0)), "") | I10: =IF($A10<>"", (IF('2Replacement Costs - Entry'!N11="Y",((($B10*$D10)*((1+$B$5)^I$7))*(1/((1+$F$5)^I$7))),0)), "")
A11: =IF('2Capital Costs'!A12<>"", '2Capital Costs'!A12, "") | B11: =IF('2Capital Costs'!B12<>"", '2Capital Costs'!B12, "") | C11: =IF('2Capital Costs'!C12<>"", '2Capital Costs'!C12, "") | D11: =IF('2Capital Costs'!D12<>"", '2Capital Costs'!D12, "") | E11: =IF($A11<>"", (IF('2Replacement Costs - Entry'!J12="Y",((($B11*$D11)*((1+$B$5)^E$7))*(1/((1+$F$5)^E$7))),0)), "") | F11: =IF($A11<>"", (IF('2Replacement Costs - Entry'!K12="Y",((($B11*$D11)*((1+$B$5)^F$7))*(1/((1+$F$5)^F$7))),0)), "") | G11: =IF($A11<>"", (IF('2Replacement Costs - Entry'!L12="Y",((($B11*$D11)*((1+$B$5)^G$7))*(1/((1+$F$5)^G$7))),0)), "") | H11: =IF($A11<>"", (IF('2Replacement Costs - Entry'!M12="Y",((($B11*$D11)*((1+$B$5)^H$7))*(1/((1+$F$5)^H$7))),0)), "") | I11: =IF($A11<>"", (IF('2Replacement Costs - Entry'!N12="Y",((($B11*$D11)*((1+$B$5)^I$7))*(1/((1+$F$5)^I$7))),0)), "")
A12: =IF('2Capital Costs'!A13<>"", '2Capital Costs'!A13, "") | B12: =IF('2Capital Costs'!B13<>"", '2Capital Costs'!B13, "") | C12: =IF('2Capital Costs'!C13<>"", '2Capital Costs'!C13, "") | D12: =IF('2Capital Costs'!D13<>"", '2Capital Costs'!D13, "") | E12: =IF($A12<>"", (IF('2Replacement Costs - Entry'!J13="Y",((($B12*$D12)*((1+$B$5)^E$7))*(1/((1+$F$5)^E$7))),0)), "") | F12: =IF($A12<>"", (IF('2Replacement Costs - Entry'!K13="Y",((($B12*$D12)*((1+$B$5)^F$7))*(1/((1+$F$5)^F$7))),0)), "") | G12: =IF($A12<>"", (IF('2Replacement Costs - Entry'!L13="Y",((($B12*$D12)*((1+$B$5)^G$7))*(1/((1+$F$5)^G$7))),0)), "") | H12: =IF($A12<>"", (IF('2Replacement Costs - Entry'!M13="Y",((($B12*$D12)*((1+$B$5)^H$7))*(1/((1+$F$5)^H$7))),0)), "") | I12: =IF($A12<>"", (IF('2Replacement Costs - Entry'!N13="Y",((($B12*$D12)*((1+$B$5)^I$7))*(1/((1+$F$5)^I$7))),0)), "")
A13: =IF('2Capital Costs'!A14<>"", '2Capital Costs'!A14, "") | B13: =IF('2Capital Costs'!B14<>"", '2Capital Costs'!B14, "") | C13: =IF('2Capital Costs'!C14<>"", '2Capital Costs'!C14, "") | D13: =IF('2Capital Costs'!D14<>"", '2Capital Costs'!D14, "") | E13: =IF($A13<>"", (IF('2Replacement Costs - Entry'!J14="Y",((($B13*$D13)*((1+$B$5)^E$7))*(1/((1+$F$5)^E$7))),0)), "") | F13: =IF($A13<>"", (IF('2Replacement Costs - Entry'!K14="Y",((($B13*$D13)*((1+$B$5)^F$7))*(1/((1+$F$5)^F$7))),0)), "") | G13: =IF($A13<>"", (IF('2Replacement Costs - Entry'!L14="Y",((($B13*$D13)*((1+$B$5)^G$7))*(1/((1+$F$5)^G$7))),0)), "") | H13: =IF($A13<>"", (IF('2Replacement Costs - Entry'!M14="Y",((($B13*$D13)*((1+$B$5)^H$7))*(1/((1+$F$5)^H$7))),0)), "") | I13: =IF($A13<>"", (IF('2Replacement Costs - Entry'!N14="Y",((($B13*$D13)*((1+$B$5)^I$7))*(1/((1+$F$5)^I$7))),0)), "")
A14: =IF('2Capital Costs'!A15<>"", '2Capital Costs'!A15, "") | B14: =IF('2Capital Costs'!B15<>"", '2Capital Costs'!B15, "") | C14: =IF('2Capital Costs'!C15<>"", '2Capital Costs'!C15, "") | D14: =IF('2Capital Costs'!D15<>"", '2Capital Costs'!D15, "") | E14: =IF($A14<>"", (IF('2Replacement Costs - Entry'!J15="Y",((($B14*$D14)*((1+$B$5)^E$7))*(1/((1+$F$5)^E$7))),0)), "") | F14: =IF($A14<>"", (IF('2Replacement Costs - Entry'!K15="Y",((($B14*$D14)*((1+$B$5)^F$7))*(1/((1+$F$5)^F$7))),0)), "") | G14: =IF($A14<>"", (IF('2Replacement Costs - Entry'!L15="Y",((($B14*$D14)*((1+$B$5)^G$7))*(1/((1+$F$5)^G$7))),0)), "") | H14: =IF($A14<>"", (IF('2Replacement Costs - Entry'!M15="Y",((($B14*$D14)*((1+$B$5)^H$7))*(1/((1+$F$5)^H$7))),0)), "") | I14: =IF($A14<>"", (IF('2Replacement Costs - Entry'!N15="Y",((($B14*$D14)*((1+$B$5)^I$7))*(1/((1+$F$5)^I$7))),0)), "")
A15: =IF('2Capital Costs'!A16<>"", '2Capital Costs'!A16, "") | B15: =IF('2Capital Costs'!B16<>"", '2Capital Costs'!B16, "") | C15: =IF('2Capital Costs'!C16<>"", '2Capital Costs'!C16, "") | D15: =IF('2Capital Costs'!D16<>"", '2Capital Costs'!D16, "") | E15: =IF($A15<>"", (IF('2Replacement Costs - Entry'!J16="Y",((($B15*$D15)*((1+$B$5)^E$7))*(1/((1+$F$5)^E$7))),0)), "") | F15: =IF($A15<>"", (IF('2Replacement Costs - Entry'!K16="Y",((($B15*$D15)*((1+$B$5)^F$7))*(1/((1+$F$5)^F$7))),0)), "") | G15: =IF($A15<>"", (IF('2Replacement Costs - Entry'!L16="Y",((($B15*$D15)*((1+$B$5)^G$7))*(1/((1+$F$5)^G$7))),0)), "") | H15: =IF($A15<>"", (IF('2Replacement Costs - Entry'!M16="Y",((($B15*$D15)*((1+$B$5)^H$7))*(1/((1+$F$5)^H$7))),0)), "") | I15: =IF($A15<>"", (IF('2Replacement Costs - Entry'!N16="Y",((($B15*$D15)*((1+$B$5)^I$7))*(1/((1+$F$5)^I$7))),0)), "")
A16: =IF('2Capital Costs'!A17<>"", '2Capital Costs'!A17, "") | B16: =IF('2Capital Costs'!B17<>"", '2Capital Costs'!B17, "") | C16: =IF('2Capital Costs'!C17<>"", '2Capital Costs'!C17, "") | D16: =IF('2Capital Costs'!D17<>"", '2Capital Costs'!D17, "") | E16: =IF($A16<>"", (IF('2Replacement Costs - Entry'!J17="Y",((($B16*$D16)*((1+$B$5)^E$7))*(1/((1+$F$5)^E$7))),0)), "") | F16: =IF($A16<>"", (IF('2Replacement Costs - Entry'!K17="Y",((($B16*$D16)*((1+$B$5)^F$7))*(1/((1+$F$5)^F$7))),0)), "") | G16: =IF($A16<>"", (IF('2Replacement Costs - Entry'!L17="Y",((($B16*$D16)*((1+$B$5)^G$7))*(1/((1+$F$5)^G$7))),0)), "") | H16: =IF($A16<>"", (IF('2Replacement Costs - Entry'!M17="Y",((($B16*$D16)*((1+$B$5)^H$7))*(1/((1+$F$5)^H$7))),0)), "") | I16: =IF($A16<>"", (IF('2Replacement Costs - Entry'!N17="Y",((($B16*$D16)*((1+$B$5)^I$7))*(1/((1+$F$5)^I$7))),0)), "")
A17: =IF('2Capital Costs'!A18<>"", '2Capital Costs'!A18, "") | B17: =IF('2Capital Costs'!B18<>"", '2Capital Costs'!B18, "") | C17: =IF('2Capital Costs'!C18<>"", '2Capital Costs'!C18, "") | D17: =IF('2Capital Costs'!D18<>"", '2Capital Costs'!D18, "") | E17: =IF($A17<>"", (IF('2Replacement Costs - Entry'!J18="Y",((($B17*$D17)*((1+$B$5)^E$7))*(1/((1+$F$5)^E$7))),0)), "") | F17: =IF($A17<>"", (IF('2Replacement Costs - Entry'!K18="Y",((($B17*$D17)*((1+$B$5)^F$7))*(1/((1+$F$5)^F$7))),0)), "") | G17: =IF($A17<>"", (IF('2Replacement Costs - Entry'!L18="Y",((($B17*$D17)*((1+$B$5)^G$7))*(1/((1+$F$5)^G$7))),0)), "") | H17: =IF($A17<>"", (IF('2Replacement Costs - Entry'!M18="Y",((($B17*$D17)*((1+$B$5)^H$7))*(1/((1+$F$5)^H$7))),0)), "") | I17: =IF($A17<>"", (IF('2Replacement Costs - Entry'!N18="Y",((($B17*$D17)*((1+$B$5)^I$7))*(1/((1+$F$5)^I$7))),0)), "")
A18: =IF('2Capital Costs'!A19<>"", '2Capital Costs'!A19, "") | B18: =IF('2Capital Costs'!B19<>"", '2Capital Costs'!B19, "") | C18: =IF('2Capital Costs'!C19<>"", '2Capital Costs'!C19, "") | D18: =IF('2Capital Costs'!D19<>"", '2Capital Costs'!D19, "") | E18: =IF($A18<>"", (IF('2Replacement Costs - Entry'!J19="Y",((($B18*$D18)*((1+$B$5)^E$7))*(1/((1+$F$5)^E$7))),0)), "") | F18: =IF($A18<>"", (IF('2Replacement Costs - Entry'!K19="Y",((($B18*$D18)*((1+$B$5)^F$7))*(1/((1+$F$5)^F$7))),0)), "") | G18: =IF($A18<>"", (IF('2Replacement Costs - Entry'!L19="Y",((($B18*$D18)*((1+$B$5)^G$7))*(1/((1+$F$5)^G$7))),0)), "") | H18: =IF($A18<>"", (IF('2Replacement Costs - Entry'!M19="Y",((($B18*$D18)*((1+$B$5)^H$7))*(1/((1+$F$5)^H$7))),0)), "") | I18: =IF($A18<>"", (IF('2Replacement Costs - Entry'!N19="Y",((($B18*$D18)*((1+$B$5)^I$7))*(1/((1+$F$5)^I$7))),0)), "")
A19: =IF('2Capital Costs'!A20<>"", '2Capital Costs'!A20, "") | B19: =IF('2Capital Costs'!B20<>"", '2Capital Costs'!B20, "") | C19: =IF('2Capital Costs'!C20<>"", '2Capital Costs'!C20, "") | D19: =IF('2Capital Costs'!D20<>"", '2Capital Costs'!D20, "") | E19: =IF($A19<>"", (IF('2Replacement Costs - Entry'!J20="Y",((($B19*$D19)*((1+$B$5)^E$7))*(1/((1+$F$5)^E$7))),0)), "") | F19: =IF($A19<>"", (IF('2Replacement Costs - Entry'!K20="Y",((($B19*$D19)*((1+$B$5)^F$7))*(1/((1+$F$5)^F$7))),0)), "") | G19: =IF($A19<>"", (IF('2Replacement Costs - Entry'!L20="Y",((($B19*$D19)*((1+$B$5)^G$7))*(1/((1+$F$5)^G$7))),0)), "") | H19: =IF($A19<>"", (IF('2Replacement Costs - Entry'!M20="Y",((($B19*$D19)*((1+$B$5)^H$7))*(1/((1+$F$5)^H$7))),0)), "") | I19: =IF($A19<>"", (IF('2Replacement Costs - Entry'!N20="Y",((($B19*$D19)*((1+$B$5)^I$7))*(1/((1+$F$5)^I$7))),0)), "")
... A36: =IF('2Capital Costs'!A37<>"", '2Capital Costs'!A37, "") | B36: =IF('2Capital Costs'!B37<>"", '2Capital Costs'!B37, "") | C36: =IF('2Capital Costs'!C37<>"", '2Capital Costs'!C37, "") | D36: =IF('2Capital Costs'!D37<>"", '2Capital Costs'!D37, "") | E36: =IF($A36<>"", (IF('2Replacement Costs - Entry'!J37="Y",((($B36*$D36)*((1+$B$5)^E$7))*(1/((1+$F$5)^E$7))),0)), "") | F36: =IF($A36<>"", (IF('2Replacement Costs - Entry'!K37="Y",((($B36*$D36)*((1+$B$5)^F$7))*(1/((1+$F$5)^F$7))),0)), "") | G36: =IF($A36<>"", (IF('2Replacement Costs - Entry'!L37="Y",((($B36*$D36)*((1+$B$5)^G$7))*(1/((1+$F$5)^G$7))),0)), "") | H36: =IF($A36<>"", (IF('2Replacement Costs - Entry'!M37="Y",((($B36*$D36)*((1+$B$5)^H$7))*(1/((1+$F$5)^H$7))),0)), "") | I36: =IF($A36<>"", (IF('2Replacement Costs - Entry'!N37="Y",((($B36*$D36)*((1+$B$5)^I$7))*(1/((1+$F$5)^I$7))),0)), "")
D37: Total Present Value of Replacement Costs (Years 1 to 5): | E37: =SUM(E8:E36) -> 0 | F37: =SUM(F8:F36) -> 0 | G37: =SUM(G8:G36) -> 0 | H37: =SUM(H8:H36) -> 0 | I37: =SUM(I8:I36) -> 0

Sheet 2Replace Costs-Results 6-10
A1: Table 5.2.14. Replacement Costs (Years 6 to 10)
A2: =Input!B4 -> 0
A3: =Input!B5 -> 0
A4: ='2Capital Costs'!B6 -> 0
A5: ='2Replace Costs - Results 1-5'!A5 -> Current Inflation Rate based on Construction Cost Index: | B5: ='2Replace Costs - Results 1-5'!B5 -> 0.020671835 | E5: EPA Discount Rate: | F5: ='2Replace Costs - Results 1-5'!F5 -> 0.04875
E6: Present Value of Replacement Costs in Year:
A7: Component | B7: Unit Cost | C7: Unit | D7: Quantity | E7: 6 | F7: 7 | G7: 8 | H7: 9 | I7: 10
A8: =IF('2Capital Costs'!A9<>"", '2Capital Costs'!A9, "") | B8: =IF('2Capital Costs'!B9<>"", '2Capital Costs'!B9, "") | C8: =IF('2Capital Costs'!C9<>"", '2Capital Costs'!C9, "") | D8: =IF('2Capital Costs'!D9<>"", '2Capital Costs'!D9, "") | E8: =IF($A8<>"", (IF('2Replacement Costs - Entry'!O9="Y",((($B8*$D8)*((1+$B$5)^E$7))*(1/((1+$F$5)^E$7))), 0)), "") | F8: =IF($A8<>"", (IF('2Replacement Costs - Entry'!P9="Y",((($B8*$D8)*((1+$B$5)^F$7))*(1/((1+$F$5)^F$7))), 0)), "") | G8: =IF($A8<>"", (IF('2Replacement Costs - Entry'!Q9="Y",((($B8*$D8)*((1+$B$5)^G$7))*(1/((1+$F$5)^G$7))), 0)), "") | H8: =IF($A8<>"", (IF('2Replacement Costs - Entry'!R9="Y",((($B8*$D8)*((1+$B$5)^H$7))*(1/((1+$F$5)^H$7))), 0)), "") | I8: =IF($A8<>"", (IF('2Replacement Costs - Entry'!S9="Y",((($B8*$D8)*((1+$B$5)^I$7))*(1/((1+$F$5)^I$7))), 0)), "")
A9: =IF('2Capital Costs'!A10<>"", '2Capital Costs'!A10, "") | B9: =IF('2Capital Costs'!B10<>"", '2Capital Costs'!B10, "") | C9: =IF('2Capital Costs'!C10<>"", '2Capital Costs'!C10, "") | D9: =IF('2Capital Costs'!D10<>"", '2Capital Costs'!D10, "") | E9: =IF($A9<>"", (IF('2Replacement Costs - Entry'!O10="Y",((($B9*$D9)*((1+$B$5)^E$7))*(1/((1+$F$5)^E$7))), 0)), "") | F9: =IF($A9<>"", (IF('2Replacement Costs - Entry'!P10="Y",((($B9*$D9)*((1+$B$5)^F$7))*(1/((1+$F$5)^F$7))), 0)), "") | G9: =IF($A9<>"", (IF('2Replacement Costs - Entry'!Q10="Y",((($B9*$D9)*((1+$B$5)^G$7))*(1/((1+$F$5)^G$7))), 0)), "") | H9: =IF($A9<>"", (IF('2Replacement Costs - Entry'!R10="Y",((($B9*$D9)*((1+$B$5)^H$7))*(1/((1+$F$5)^H$7))), 0)), "") | I9: =IF($A9<>"", (IF('2Replacement Costs - Entry'!S10="Y",((($B9*$D9)*((1+$B$5)^I$7))*(1/((1+$F$5)^I$7))), 0)), "")
A10: =IF('2Capital Costs'!A11<>"", '2Capital Costs'!A11, "") | B10: =IF('2Capital Costs'!B11<>"", '2Capital Costs'!B11, "") | C10: =IF('2Capital Costs'!C11<>"", '2Capital Costs'!C11, "") | D10: =IF('2Capital Costs'!D11<>"", '2Capital Costs'!D11, "") | E10: =IF($A10<>"", (IF('2Replacement Costs - Entry'!O11="Y",((($B10*$D10)*((1+$B$5)^E$7))*(1/((1+$F$5)^E$7))), 0)), "") | F10: =IF($A10<>"", (IF('2Replacement Costs - Entry'!P11="Y",((($B10*$D10)*((1+$B$5)^F$7))*(1/((1+$F$5)^F$7))), 0)), "") | G10: =IF($A10<>"", (IF('2Replacement Costs - Entry'!Q11="Y",((($B10*$D10)*((1+$B$5)^G$7))*(1/((1+$F$5)^G$7))), 0)), "") | H10: =IF($A10<>"", (IF('2Replacement Costs - Entry'!R11="Y",((($B10*$D10)*((1+$B$5)^H$7))*(1/((1+$F$5)^H$7))), 0)), "") | I10: =IF($A10<>"", (IF('2Replacement Costs - Entry'!S11="Y",((($B10*$D10)*((1+$B$5)^I$7))*(1/((1+$F$5)^I$7))), 0)), "")
A11: =IF('2Capital Costs'!A12<>"", '2Capital Costs'!A12, "") | B11: =IF('2Capital Costs'!B12<>"", '2Capital Costs'!B12, "") | C11: =IF('2Capital Costs'!C12<>"", '2Capital Costs'!C12, "") | D11: =IF('2Capital Costs'!D12<>"", '2Capital Costs'!D12, "") | E11: =IF($A11<>"", (IF('2Replacement Costs - Entry'!O12="Y",((($B11*$D11)*((1+$B$5)^E$7))*(1/((1+$F$5)^E$7))), 0)), "") | F11: =IF($A11<>"", (IF('2Replacement Costs - Entry'!P12="Y",((($B11*$D11)*((1+$B$5)^F$7))*(1/((1+$F$5)^F$7))), 0)), "") | G11: =IF($A11<>"", (IF('2Replacement Costs - Entry'!Q12="Y",((($B11*$D11)*((1+$B$5)^G$7))*(1/((1+$F$5)^G$7))), 0)), "") | H11: =IF($A11<>"", (IF('2Replacement Costs - Entry'!R12="Y",((($B11*$D11)*((1+$B$5)^H$7))*(1/((1+$F$5)^H$7))), 0)), "") | I11: =IF($A11<>"", (IF('2Replacement Costs - Entry'!S12="Y",((($B11*$D11)*((1+$B$5)^I$7))*(1/((1+$F$5)^I$7))), 0)), "")
A12: =IF('2Capital Costs'!A13<>"", '2Capital Costs'!A13, "") | B12: =IF('2Capital Costs'!B13<>"", '2Capital Costs'!B13, "") | C12: =IF('2Capital Costs'!C13<>"", '2Capital Costs'!C13, "") | D12: =IF('2Capital Costs'!D13<>"", '2Capital Costs'!D13, "") | E12: =IF($A12<>"", (IF('2Replacement Costs - Entry'!O13="Y",((($B12*$D12)*((1+$B$5)^E$7))*(1/((1+$F$5)^E$7))), 0)), "") | F12: =IF($A12<>"", (IF('2Replacement Costs - Entry'!P13="Y",((($B12*$D12)*((1+$B$5)^F$7))*(1/((1+$F$5)^F$7))), 0)), "") | G12: =IF($A12<>"", (IF('2Replacement Costs - Entry'!Q13="Y",((($B12*$D12)*((1+$B$5)^G$7))*(1/((1+$F$5)^G$7))), 0)), "") | H12: =IF($A12<>"", (IF('2Replacement Costs - Entry'!R13="Y",((($B12*$D12)*((1+$B$5)^H$7))*(1/((1+$F$5)^H$7))), 0)), "") | I12: =IF($A12<>"", (IF('2Replacement Costs - Entry'!S13="Y",((($B12*$D12)*((1+$B$5)^I$7))*(1/((1+$F$5)^I$7))), 0)), "")
A13: =IF('2Capital Costs'!A14<>"", '2Capital Costs'!A14, "") | B13: =IF('2Capital Costs'!B14<>"", '2Capital Costs'!B14, "") | C13: =IF('2Capital Costs'!C14<>"", '2Capital Costs'!C14, "") | D13: =IF('2Capital Costs'!D14<>"", '2Capital Costs'!D14, "") | E13: =IF($A13<>"", (IF('2Replacement Costs - Entry'!O14="Y",((($B13*$D13)*((1+$B$5)^E$7))*(1/((1+$F$5)^E$7))), 0)), "") | F13: =IF($A13<>"", (IF('2Replacement Costs - Entry'!P14="Y",((($B13*$D13)*((1+$B$5)^F$7))*(1/((1+$F$5)^F$7))), 0)), "") | G13: =IF($A13<>"", (IF('2Replacement Costs - Entry'!Q14="Y",((($B13*$D13)*((1+$B$5)^G$7))*(1/((1+$F$5)^G$7))), 0)), "") | H13: =IF($A13<>"", (IF('2Replacement Costs - Entry'!R14="Y",((($B13*$D13)*((1+$B$5)^H$7))*(1/((1+$F$5)^H$7))), 0)), "") | I13: =IF($A13<>"", (IF('2Replacement Costs - Entry'!S14="Y",((($B13*$D13)*((1+$B$5)^I$7))*(1/((1+$F$5)^I$7))), 0)), "")
A14: =IF('2Capital Costs'!A15<>"", '2Capital Costs'!A15, "") | B14: =IF('2Capital Costs'!B15<>"", '2Capital Costs'!B15, "") | C14: =IF('2Capital Costs'!C15<>"", '2Capital Costs'!C15, "") | D14: =IF('2Capital Costs'!D15<>"", '2Capital Costs'!D15, "") | E14: =IF($A14<>"", (IF('2Replacement Costs - Entry'!O15="Y",((($B14*$D14)*((1+$B$5)^E$7))*(1/((1+$F$5)^E$7))), 0)), "") | F14: =IF($A14<>"", (IF('2Replacement Costs - Entry'!P15="Y",((($B14*$D14)*((1+$B$5)^F$7))*(1/((1+$F$5)^F$7))), 0)), "") | G14: =IF($A14<>"", (IF('2Replacement Costs - Entry'!Q15="Y",((($B14*$D14)*((1+$B$5)^G$7))*(1/((1+$F$5)^G$7))), 0)), "") | H14: =IF($A14<>"", (IF('2Replacement Costs - Entry'!R15="Y",((($B14*$D14)*((1+$B$5)^H$7))*(1/((1+$F$5)^H$7))), 0)), "") | I14: =IF($A14<>"", (IF('2Replacement Costs - Entry'!S15="Y",((($B14*$D14)*((1+$B$5)^I$7))*(1/((1+$F$5)^I$7))), 0)), "")
A15: =IF('2Capital Costs'!A16<>"", '2Capital Costs'!A16, "") | B15: =IF('2Capital Costs'!B16<>"", '2Capital Costs'!B16, "") | C15: =IF('2Capital Costs'!C16<>"", '2Capital Costs'!C16, "") | D15: =IF('2Capital Costs'!D16<>"", '2Capital Costs'!D16, "") | E15: =IF($A15<>"", (IF('2Replacement Costs - Entry'!O16="Y",((($B15*$D15)*((1+$B$5)^E$7))*(1/((1+$F$5)^E$7))), 0)), "") | F15: =IF($A15<>"", (IF('2Replacement Costs - Entry'!P16="Y",((($B15*$D15)*((1+$B$5)^F$7))*(1/((1+$F$5)^F$7))), 0)), "") | G15: =IF($A15<>"", (IF('2Replacement Costs - Entry'!Q16="Y",((($B15*$D15)*((1+$B$5)^G$7))*(1/((1+$F$5)^G$7))), 0)), "") | H15: =IF($A15<>"", (IF('2Replacement Costs - Entry'!R16="Y",((($B15*$D15)*((1+$B$5)^H$7))*(1/((1+$F$5)^H$7))), 0)), "") | I15: =IF($A15<>"", (IF('2Replacement Costs - Entry'!S16="Y",((($B15*$D15)*((1+$B$5)^I$7))*(1/((1+$F$5)^I$7))), 0)), "")
A16: =IF('2Capital Costs'!A17<>"", '2Capital Costs'!A17, "") | B16: =IF('2Capital Costs'!B17<>"", '2Capital Costs'!B17, "") | C16: =IF('2Capital Costs'!C17<>"", '2Capital Costs'!C17, "") | D16: =IF('2Capital Costs'!D17<>"", '2Capital Costs'!D17, "") | E16: =IF($A16<>"", (IF('2Replacement Costs - Entry'!O17="Y",((($B16*$D16)*((1+$B$5)^E$7))*(1/((1+$F$5)^E$7))), 0)), "") | F16: =IF($A16<>"", (IF('2Replacement Costs - Entry'!P17="Y",((($B16*$D16)*((1+$B$5)^F$7))*(1/((1+$F$5)^F$7))), 0)), "") | G16: =IF($A16<>"", (IF('2Replacement Costs - Entry'!Q17="Y",((($B16*$D16)*((1+$B$5)^G$7))*(1/((1+$F$5)^G$7))), 0)), "") | H16: =IF($A16<>"", (IF('2Replacement Costs - Entry'!R17="Y",((($B16*$D16)*((1+$B$5)^H$7))*(1/((1+$F$5)^H$7))), 0)), "") | I16: =IF($A16<>"", (IF('2Replacement Costs - Entry'!S17="Y",((($B16*$D16)*((1+$B$5)^I$7))*(1/((1+$F$5)^I$7))), 0)), "")
A17: =IF('2Capital Costs'!A18<>"", '2Capital Costs'!A18, "") | B17: =IF('2Capital Costs'!B18<>"", '2Capital Costs'!B18, "") | C17: =IF('2Capital Costs'!C18<>"", '2Capital Costs'!C18, "") | D17: =IF('2Capital Costs'!D18<>"", '2Capital Costs'!D18, "") | E17: =IF($A17<>"", (IF('2Replacement Costs - Entry'!O18="Y",((($B17*$D17)*((1+$B$5)^E$7))*(1/((1+$F$5)^E$7))), 0)), "") | F17: =IF($A17<>"", (IF('2Replacement Costs - Entry'!P18="Y",((($B17*$D17)*((1+$B$5)^F$7))*(1/((1+$F$5)^F$7))), 0)), "") | G17: =IF($A17<>"", (IF('2Replacement Costs - Entry'!Q18="Y",((($B17*$D17)*((1+$B$5)^G$7))*(1/((1+$F$5)^G$7))), 0)), "") | H17: =IF($A17<>"", (IF('2Replacement Costs - Entry'!R18="Y",((($B17*$D17)*((1+$B$5)^H$7))*(1/((1+$F$5)^H$7))), 0)), "") | I17: =IF($A17<>"", (IF('2Replacement Costs - Entry'!S18="Y",((($B17*$D17)*((1+$B$5)^I$7))*(1/((1+$F$5)^I$7))), 0)), "")
A18: =IF('2Capital Costs'!A19<>"", '2Capital Costs'!A19, "") | B18: =IF('2Capital Costs'!B19<>"", '2Capital Costs'!B19, "") | C18: =IF('2Capital Costs'!C19<>"", '2Capital Costs'!C19, "") | D18: =IF('2Capital Costs'!D19<>"", '2Capital Costs'!D19, "") | E18: =IF($A18<>"", (IF('2Replacement Costs - Entry'!O19="Y",((($B18*$D18)*((1+$B$5)^E$7))*(1/((1+$F$5)^E$7))), 0)), "") | F18: =IF($A18<>"", (IF('2Replacement Costs - Entry'!P19="Y",((($B18*$D18)*((1+$B$5)^F$7))*(1/((1+$F$5)^F$7))), 0)), "") | G18: =IF($A18<>"", (IF('2Replacement Costs - Entry'!Q19="Y",((($B18*$D18)*((1+$B$5)^G$7))*(1/((1+$F$5)^G$7))), 0)), "") | H18: =IF($A18<>"", (IF('2Replacement Costs - Entry'!R19="Y",((($B18*$D18)*((1+$B$5)^H$7))*(1/((1+$F$5)^H$7))), 0)), "") | I18: =IF($A18<>"", (IF('2Replacement Costs - Entry'!S19="Y",((($B18*$D18)*((1+$B$5)^I$7))*(1/((1+$F$5)^I$7))), 0)), "")
A19: =IF('2Capital Costs'!A20<>"", '2Capital Costs'!A20, "") | B19: =IF('2Capital Costs'!B20<>"", '2Capital Costs'!B20, "") | C19: =IF('2Capital Costs'!C20<>"", '2Capital Costs'!C20, "") | D19: =IF('2Capital Costs'!D20<>"", '2Capital Costs'!D20, "") | E19: =IF($A19<>"", (IF('2Replacement Costs - Entry'!O20="Y",((($B19*$D19)*((1+$B$5)^E$7))*(1/((1+$F$5)^E$7))), 0)), "") | F19: =IF($A19<>"", (IF('2Replacement Costs - Entry'!P20="Y",((($B19*$D19)*((1+$B$5)^F$7))*(1/((1+$F$5)^F$7))), 0)), "") | G19: =IF($A19<>"", (IF('2Replacement Costs - Entry'!Q20="Y",((($B19*$D19)*((1+$B$5)^G$7))*(1/((1+$F$5)^G$7))), 0)), "") | H19: =IF($A19<>"", (IF('2Replacement Costs - Entry'!R20="Y",((($B19*$D19)*((1+$B$5)^H$7))*(1/((1+$F$5)^H$7))), 0)), "") | I19: =IF($A19<>"", (IF('2Replacement Costs - Entry'!S20="Y",((($B19*$D19)*((1+$B$5)^I$7))*(1/((1+$F$5)^I$7))), 0)), "")
... A36: =IF('2Capital Costs'!A37<>"", '2Capital Costs'!A37, "") | B36: =IF('2Capital Costs'!B37<>"", '2Capital Costs'!B37, "") | C36: =IF('2Capital Costs'!C37<>"", '2Capital Costs'!C37, "") | D36: =IF('2Capital Costs'!D37<>"", '2Capital Costs'!D37, "") | E36: =IF($A36<>"", (IF('2Replacement Costs - Entry'!O37="Y",((($B36*$D36)*((1+$B$5)^E$7))*(1/((1+$F$5)^E$7))), 0)), "") | F36: =IF($A36<>"", (IF('2Replacement Costs - Entry'!P37="Y",((($B36*$D36)*((1+$B$5)^F$7))*(1/((1+$F$5)^F$7))), 0)), "") | G36: =IF($A36<>"", (IF('2Replacement Costs - Entry'!Q37="Y",((($B36*$D36)*((1+$B$5)^G$7))*(1/((1+$F$5)^G$7))), 0)), "") | H36: =IF($A36<>"", (IF('2Replacement Costs - Entry'!R37="Y",((($B36*$D36)*((1+$B$5)^H$7))*(1/((1+$F$5)^H$7))), 0)), "") | I36: =IF($A36<>"", (IF('2Replacement Costs - Entry'!S37="Y",((($B36*$D36)*((1+$B$5)^I$7))*(1/((1+$F$5)^I$7))), 0)), "")
D37: Total Present Value of Replacement Costs (Years 6 to 10): | E37: =SUM(E8:E36) -> 0 | F37: =SUM(F8:F36) -> 0 | G37: =SUM(G8:G36) -> 0 | H37: =SUM(H8:H36) -> 0 | I37: =SUM(I8:I36) -> 0

Sheet 2Replace Costs-Results 11-15
A1: Table 5.2.15. Replacement Costs (Years 11 to 15)
A2: =Input!B4 -> 0
A3: =Input!B5 -> 0
A4: ='2Capital Costs'!B6 -> 0
A5: ='2Replace Costs-Results 6-10'!A5 -> Current Inflation Rate based on Construction Cost Index: | B5: ='2Replace Costs-Results 6-10'!B5 -> 0.020671835 | E5: EPA Discount Rate: | F5: ='2Replace Costs-Results 6-10'!F5 -> 0.04875
E6: Present Value of Replacement Costs in Year:
A7: Component | B7: Unit Cost | C7: Unit | D7: Quantity | E7: 11 | F7: 12 | G7: 13 | H7: 14 | I7: 15
A8: =IF('2Capital Costs'!A9<>"", '2Capital Costs'!A9, "") | B8: =IF('2Capital Costs'!B9<>"", '2Capital Costs'!B9, "") | C8: =IF('2Capital Costs'!C9<>"", '2Capital Costs'!C9, "") | D8: =IF('2Capital Costs'!D9<>"", '2Capital Costs'!D9, "") | E8: =IF($A8<>"", (IF('2Replacement Costs - Entry'!T9="Y",((($B8*$D8)*((1+$B$5)^E$7))*(1/((1+$F$5)^E$7))),0)), "") | F8: =IF($A8<>"", (IF('2Replacement Costs - Entry'!U9="Y",((($B8*$D8)*((1+$B$5)^F$7))*(1/((1+$F$5)^F$7))),0)), "") | G8: =IF($A8<>"", (IF('2Replacement Costs - Entry'!V9="Y",((($B8*$D8)*((1+$B$5)^G$7))*(1/((1+$F$5)^G$7))),0)), "") | H8: =IF($A8<>"", (IF('2Replacement Costs - Entry'!W9="Y",((($B8*$D8)*((1+$B$5)^H$7))*(1/((1+$F$5)^H$7))),0)), "") | I8: =IF($A8<>"", (IF('2Replacement Costs - Entry'!X9="Y",((($B8*$D8)*((1+$B$5)^I$7))*(1/((1+$F$5)^I$7))),0)), "")
A9: =IF('2Capital Costs'!A10<>"", '2Capital Costs'!A10, "") | B9: =IF('2Capital Costs'!B10<>"", '2Capital Costs'!B10, "") | C9: =IF('2Capital Costs'!C10<>"", '2Capital Costs'!C10, "") | D9: =IF('2Capital Costs'!D10<>"", '2Capital Costs'!D10, "") | E9: =IF($A9<>"", (IF('2Replacement Costs - Entry'!T10="Y",((($B9*$D9)*((1+$B$5)^E$7))*(1/((1+$F$5)^E$7))),0)), "") | F9: =IF($A9<>"", (IF('2Replacement Costs - Entry'!U10="Y",((($B9*$D9)*((1+$B$5)^F$7))*(1/((1+$F$5)^F$7))),0)), "") | G9: =IF($A9<>"", (IF('2Replacement Costs - Entry'!V10="Y",((($B9*$D9)*((1+$B$5)^G$7))*(1/((1+$F$5)^G$7))),0)), "") | H9: =IF($A9<>"", (IF('2Replacement Costs - Entry'!W10="Y",((($B9*$D9)*((1+$B$5)^H$7))*(1/((1+$F$5)^H$7))),0)), "") | I9: =IF($A9<>"", (IF('2Replacement Costs - Entry'!X10="Y",((($B9*$D9)*((1+$B$5)^I$7))*(1/((1+$F$5)^I$7))),0)), "")
A10: =IF('2Capital Costs'!A11<>"", '2Capital Costs'!A11, "") | B10: =IF('2Capital Costs'!B11<>"", '2Capital Costs'!B11, "") | C10: =IF('2Capital Costs'!C11<>"", '2Capital Costs'!C11, "") | D10: =IF('2Capital Costs'!D11<>"", '2Capital Costs'!D11, "") | E10: =IF($A10<>"", (IF('2Replacement Costs - Entry'!T11="Y",((($B10*$D10)*((1+$B$5)^E$7))*(1/((1+$F$5)^E$7))),0)), "") | F10: =IF($A10<>"", (IF('2Replacement Costs - Entry'!U11="Y",((($B10*$D10)*((1+$B$5)^F$7))*(1/((1+$F$5)^F$7))),0)), "") | G10: =IF($A10<>"", (IF('2Replacement Costs - Entry'!V11="Y",((($B10*$D10)*((1+$B$5)^G$7))*(1/((1+$F$5)^G$7))),0)), "") | H10: =IF($A10<>"", (IF('2Replacement Costs - Entry'!W11="Y",((($B10*$D10)*((1+$B$5)^H$7))*(1/((1+$F$5)^H$7))),0)), "") | I10: =IF($A10<>"", (IF('2Replacement Costs - Entry'!X11="Y",((($B10*$D10)*((1+$B$5)^I$7))*(1/((1+$F$5)^I$7))),0)), "")
A11: =IF('2Capital Costs'!A12<>"", '2Capital Costs'!A12, "") | B11: =IF('2Capital Costs'!B12<>"", '2Capital Costs'!B12, "") | C11: =IF('2Capital Costs'!C12<>"", '2Capital Costs'!C12, "") | D11: =IF('2Capital Costs'!D12<>"", '2Capital Costs'!D12, "") | E11: =IF($A11<>"", (IF('2Replacement Costs - Entry'!T12="Y",((($B11*$D11)*((1+$B$5)^E$7))*(1/((1+$F$5)^E$7))),0)), "") | F11: =IF($A11<>"", (IF('2Replacement Costs - Entry'!U12="Y",((($B11*$D11)*((1+$B$5)^F$7))*(1/((1+$F$5)^F$7))),0)), "") | G11: =IF($A11<>"", (IF('2Replacement Costs - Entry'!V12="Y",((($B11*$D11)*((1+$B$5)^G$7))*(1/((1+$F$5)^G$7))),0)), "") | H11: =IF($A11<>"", (IF('2Replacement Costs - Entry'!W12="Y",((($B11*$D11)*((1+$B$5)^H$7))*(1/((1+$F$5)^H$7))),0)), "") | I11: =IF($A11<>"", (IF('2Replacement Costs - Entry'!X12="Y",((($B11*$D11)*((1+$B$5)^I$7))*(1/((1+$F$5)^I$7))),0)), "")
A12: =IF('2Capital Costs'!A13<>"", '2Capital Costs'!A13, "") | B12: =IF('2Capital Costs'!B13<>"", '2Capital Costs'!B13, "") | C12: =IF('2Capital Costs'!C13<>"", '2Capital Costs'!C13, "") | D12: =IF('2Capital Costs'!D13<>"", '2Capital Costs'!D13, "") | E12: =IF($A12<>"", (IF('2Replacement Costs - Entry'!T13="Y",((($B12*$D12)*((1+$B$5)^E$7))*(1/((1+$F$5)^E$7))),0)), "") | F12: =IF($A12<>"", (IF('2Replacement Costs - Entry'!U13="Y",((($B12*$D12)*((1+$B$5)^F$7))*(1/((1+$F$5)^F$7))),0)), "") | G12: =IF($A12<>"", (IF('2Replacement Costs - Entry'!V13="Y",((($B12*$D12)*((1+$B$5)^G$7))*(1/((1+$F$5)^G$7))),0)), "") | H12: =IF($A12<>"", (IF('2Replacement Costs - Entry'!W13="Y",((($B12*$D12)*((1+$B$5)^H$7))*(1/((1+$F$5)^H$7))),0)), "") | I12: =IF($A12<>"", (IF('2Replacement Costs - Entry'!X13="Y",((($B12*$D12)*((1+$B$5)^I$7))*(1/((1+$F$5)^I$7))),0)), "")
A13: =IF('2Capital Costs'!A14<>"", '2Capital Costs'!A14, "") | B13: =IF('2Capital Costs'!B14<>"", '2Capital Costs'!B14, "") | C13: =IF('2Capital Costs'!C14<>"", '2Capital Costs'!C14, "") | D13: =IF('2Capital Costs'!D14<>"", '2Capital Costs'!D14, "") | E13: =IF($A13<>"", (IF('2Replacement Costs - Entry'!T14="Y",((($B13*$D13)*((1+$B$5)^E$7))*(1/((1+$F$5)^E$7))),0)), "") | F13: =IF($A13<>"", (IF('2Replacement Costs - Entry'!U14="Y",((($B13*$D13)*((1+$B$5)^F$7))*(1/((1+$F$5)^F$7))),0)), "") | G13: =IF($A13<>"", (IF('2Replacement Costs - Entry'!V14="Y",((($B13*$D13)*((1+$B$5)^G$7))*(1/((1+$F$5)^G$7))),0)), "") | H13: =IF($A13<>"", (IF('2Replacement Costs - Entry'!W14="Y",((($B13*$D13)*((1+$B$5)^H$7))*(1/((1+$F$5)^H$7))),0)), "") | I13: =IF($A13<>"", (IF('2Replacement Costs - Entry'!X14="Y",((($B13*$D13)*((1+$B$5)^I$7))*(1/((1+$F$5)^I$7))),0)), "")
A14: =IF('2Capital Costs'!A15<>"", '2Capital Costs'!A15, "") | B14: =IF('2Capital Costs'!B15<>"", '2Capital Costs'!B15, "") | C14: =IF('2Capital Costs'!C15<>"", '2Capital Costs'!C15, "") | D14: =IF('2Capital Costs'!D15<>"", '2Capital Costs'!D15, "") | E14: =IF($A14<>"", (IF('2Replacement Costs - Entry'!T15="Y",((($B14*$D14)*((1+$B$5)^E$7))*(1/((1+$F$5)^E$7))),0)), "") | F14: =IF($A14<>"", (IF('2Replacement Costs - Entry'!U15="Y",((($B14*$D14)*((1+$B$5)^F$7))*(1/((1+$F$5)^F$7))),0)), "") | G14: =IF($A14<>"", (IF('2Replacement Costs - Entry'!V15="Y",((($B14*$D14)*((1+$B$5)^G$7))*(1/((1+$F$5)^G$7))),0)), "") | H14: =IF($A14<>"", (IF('2Replacement Costs - Entry'!W15="Y",((($B14*$D14)*((1+$B$5)^H$7))*(1/((1+$F$5)^H$7))),0)), "") | I14: =IF($A14<>"", (IF('2Replacement Costs - Entry'!X15="Y",((($B14*$D14)*((1+$B$5)^I$7))*(1/((1+$F$5)^I$7))),0)), "")
A15: =IF('2Capital Costs'!A16<>"", '2Capital Costs'!A16, "") | B15: =IF('2Capital Costs'!B16<>"", '2Capital Costs'!B16, "") | C15: =IF('2Capital Costs'!C16<>"", '2Capital Costs'!C16, "") | D15: =IF('2Capital Costs'!D16<>"", '2Capital Costs'!D16, "") | E15: =IF($A15<>"", (IF('2Replacement Costs - Entry'!T16="Y",((($B15*$D15)*((1+$B$5)^E$7))*(1/((1+$F$5)^E$7))),0)), "") | F15: =IF($A15<>"", (IF('2Replacement Costs - Entry'!U16="Y",((($B15*$D15)*((1+$B$5)^F$7))*(1/((1+$F$5)^F$7))),0)), "") | G15: =IF($A15<>"", (IF('2Replacement Costs - Entry'!V16="Y",((($B15*$D15)*((1+$B$5)^G$7))*(1/((1+$F$5)^G$7))),0)), "") | H15: =IF($A15<>"", (IF('2Replacement Costs - Entry'!W16="Y",((($B15*$D15)*((1+$B$5)^H$7))*(1/((1+$F$5)^H$7))),0)), "") | I15: =IF($A15<>"", (IF('2Replacement Costs - Entry'!X16="Y",((($B15*$D15)*((1+$B$5)^I$7))*(1/((1+$F$5)^I$7))),0)), "")
A16: =IF('2Capital Costs'!A17<>"", '2Capital Costs'!A17, "") | B16: =IF('2Capital Costs'!B17<>"", '2Capital Costs'!B17, "") | C16: =IF('2Capital Costs'!C17<>"", '2Capital Costs'!C17, "") | D16: =IF('2Capital Costs'!D17<>"", '2Capital Costs'!D17, "") | E16: =IF($A16<>"", (IF('2Replacement Costs - Entry'!T17="Y",((($B16*$D16)*((1+$B$5)^E$7))*(1/((1+$F$5)^E$7))),0)), "") | F16: =IF($A16<>"", (IF('2Replacement Costs - Entry'!U17="Y",((($B16*$D16)*((1+$B$5)^F$7))*(1/((1+$F$5)^F$7))),0)), "") | G16: =IF($A16<>"", (IF('2Replacement Costs - Entry'!V17="Y",((($B16*$D16)*((1+$B$5)^G$7))*(1/((1+$F$5)^G$7))),0)), "") | H16: =IF($A16<>"", (IF('2Replacement Costs - Entry'!W17="Y",((($B16*$D16)*((1+$B$5)^H$7))*(1/((1+$F$5)^H$7))),0)), "") | I16: =IF($A16<>"", (IF('2Replacement Costs - Entry'!X17="Y",((($B16*$D16)*((1+$B$5)^I$7))*(1/((1+$F$5)^I$7))),0)), "")
A17: =IF('2Capital Costs'!A18<>"", '2Capital Costs'!A18, "") | B17: =IF('2Capital Costs'!B18<>"", '2Capital Costs'!B18, "") | C17: =IF('2Capital Costs'!C18<>"", '2Capital Costs'!C18, "") | D17: =IF('2Capital Costs'!D18<>"", '2Capital Costs'!D18, "") | E17: =IF($A17<>"", (IF('2Replacement Costs - Entry'!T18="Y",((($B17*$D17)*((1+$B$5)^E$7))*(1/((1+$F$5)^E$7))),0)), "") | F17: =IF($A17<>"", (IF('2Replacement Costs - Entry'!U18="Y",((($B17*$D17)*((1+$B$5)^F$7))*(1/((1+$F$5)^F$7))),0)), "") | G17: =IF($A17<>"", (IF('2Replacement Costs - Entry'!V18="Y",((($B17*$D17)*((1+$B$5)^G$7))*(1/((1+$F$5)^G$7))),0)), "") | H17: =IF($A17<>"", (IF('2Replacement Costs - Entry'!W18="Y",((($B17*$D17)*((1+$B$5)^H$7))*(1/((1+$F$5)^H$7))),0)), "") | I17: =IF($A17<>"", (IF('2Replacement Costs - Entry'!X18="Y",((($B17*$D17)*((1+$B$5)^I$7))*(1/((1+$F$5)^I$7))),0)), "")
A18: =IF('2Capital Costs'!A19<>"", '2Capital Costs'!A19, "") | B18: =IF('2Capital Costs'!B19<>"", '2Capital Costs'!B19, "") | C18: =IF('2Capital Costs'!C19<>"", '2Capital Costs'!C19, "") | D18: =IF('2Capital Costs'!D19<>"", '2Capital Costs'!D19, "") | E18: =IF($A18<>"", (IF('2Replacement Costs - Entry'!T19="Y",((($B18*$D18)*((1+$B$5)^E$7))*(1/((1+$F$5)^E$7))),0)), "") | F18: =IF($A18<>"", (IF('2Replacement Costs - Entry'!U19="Y",((($B18*$D18)*((1+$B$5)^F$7))*(1/((1+$F$5)^F$7))),0)), "") | G18: =IF($A18<>"", (IF('2Replacement Costs - Entry'!V19="Y",((($B18*$D18)*((1+$B$5)^G$7))*(1/((1+$F$5)^G$7))),0)), "") | H18: =IF($A18<>"", (IF('2Replacement Costs - Entry'!W19="Y",((($B18*$D18)*((1+$B$5)^H$7))*(1/((1+$F$5)^H$7))),0)), "") | I18: =IF($A18<>"", (IF('2Replacement Costs - Entry'!X19="Y",((($B18*$D18)*((1+$B$5)^I$7))*(1/((1+$F$5)^I$7))),0)), "")
A19: =IF('2Capital Costs'!A20<>"", '2Capital Costs'!A20, "") | B19: =IF('2Capital Costs'!B20<>"", '2Capital Costs'!B20, "") | C19: =IF('2Capital Costs'!C20<>"", '2Capital Costs'!C20, "") | D19: =IF('2Capital Costs'!D20<>"", '2Capital Costs'!D20, "") | E19: =IF($A19<>"", (IF('2Replacement Costs - Entry'!T20="Y",((($B19*$D19)*((1+$B$5)^E$7))*(1/((1+$F$5)^E$7))),0)), "") | F19: =IF($A19<>"", (IF('2Replacement Costs - Entry'!U20="Y",((($B19*$D19)*((1+$B$5)^F$7))*(1/((1+$F$5)^F$7))),0)), "") | G19: =IF($A19<>"", (IF('2Replacement Costs - Entry'!V20="Y",((($B19*$D19)*((1+$B$5)^G$7))*(1/((1+$F$5)^G$7))),0)), "") | H19: =IF($A19<>"", (IF('2Replacement Costs - Entry'!W20="Y",((($B19*$D19)*((1+$B$5)^H$7))*(1/((1+$F$5)^H$7))),0)), "") | I19: =IF($A19<>"", (IF('2Replacement Costs - Entry'!X20="Y",((($B19*$D19)*((1+$B$5)^I$7))*(1/((1+$F$5)^I$7))),0)), "")
... A36: =IF('2Capital Costs'!A37<>"", '2Capital Costs'!A37, "") | B36: =IF('2Capital Costs'!B37<>"", '2Capital Costs'!B37, "") | C36: =IF('2Capital Costs'!C37<>"", '2Capital Costs'!C37, "") | D36: =IF('2Capital Costs'!D37<>"", '2Capital Costs'!D37, "") | E36: =IF($A36<>"", (IF('2Replacement Costs - Entry'!T37="Y",((($B36*$D36)*((1+$B$5)^E$7))*(1/((1+$F$5)^E$7))),0)), "") | F36: =IF($A36<>"", (IF('2Replacement Costs - Entry'!U37="Y",((($B36*$D36)*((1+$B$5)^F$7))*(1/((1+$F$5)^F$7))),0)), "") | G36: =IF($A36<>"", (IF('2Replacement Costs - Entry'!V37="Y",((($B36*$D36)*((1+$B$5)^G$7))*(1/((1+$F$5)^G$7))),0)), "") | H36: =IF($A36<>"", (IF('2Replacement Costs - Entry'!W37="Y",((($B36*$D36)*((1+$B$5)^H$7))*(1/((1+$F$5)^H$7))),0)), "") | I36: =IF($A36<>"", (IF('2Replacement Costs - Entry'!X37="Y",((($B36*$D36)*((1+$B$5)^I$7))*(1/((1+$F$5)^I$7))),0)), "")
D37: Total Present Value of Replacement Costs (Years 11 to 15): | E37: =SUM(E8:E36) -> 0 | F37: =SUM(F8:F36) -> 0 | G37: =SUM(G8:G36) -> 0 | H37: =SUM(H8:H36) -> 0 | I37: =SUM(I8:I36) -> 0

Sheet 2Replace Costs-Results 16-20
A1: Table 5.2.16. Replacement Costs (Years 16 to 20)
A2: =Input!B4 -> 0
A3: =Input!B5 -> 0
A4: ='2Capital Costs'!B6 -> 0
A5: ='2Replace Costs-Results 11-15'!A5 -> Current Inflation Rate based on Construction Cost Index: | B5: ='2Replace Costs-Results 11-15'!B5 -> 0.020671835 | E5: EPA Discount Rate: | F5: ='2Replace Costs-Results 11-15'!F5 -> 0.04875
E6: Present Value of Replacement Costs in Year:
A7: Component | B7: Unit Cost | C7: Unit | D7: Quantity | E7: 16 | F7: 17 | G7: 18 | H7: 19 | I7: 20
A8: =IF('2Capital Costs'!A9<>"", '2Capital Costs'!A9, "") | B8: =IF('2Capital Costs'!B9<>"", '2Capital Costs'!B9, "") | C8: =IF('2Capital Costs'!C9<>"", '2Capital Costs'!C9, "") | D8: =IF('2Capital Costs'!D9<>"", '2Capital Costs'!D9, "") | E8: =IF($A8<>"", (IF('2Replacement Costs - Entry'!Y9="Y",((($B8*$D8)*((1+$B$5)^E$7))*(1/((1+$F$5)^E$7))),0)), "") | F8: =IF($A8<>"", (IF('2Replacement Costs - Entry'!Z9="Y",((($B8*$D8)*((1+$B$5)^F$7))*(1/((1+$F$5)^F$7))),0)), "") | G8: =IF($A8<>"", (IF('2Replacement Costs - Entry'!AA9="Y",((($B8*$D8)*((1+$B$5)^G$7))*(1/((1+$F$5)^G$7))),0)), "") | H8: =IF($A8<>"", (IF('2Replacement Costs - Entry'!AB9="Y",((($B8*$D8)*((1+$B$5)^H$7))*(1/((1+$F$5)^H$7))),0)), "") | I8: =IF($A8<>"", (IF('2Replacement Costs - Entry'!AC9="Y",((($B8*$D8)*((1+$B$5)^I$7))*(1/((1+$F$5)^I$7))),0)), "")
A9: =IF('2Capital Costs'!A10<>"", '2Capital Costs'!A10, "") | B9: =IF('2Capital Costs'!B10<>"", '2Capital Costs'!B10, "") | C9: =IF('2Capital Costs'!C10<>"", '2Capital Costs'!C10, "") | D9: =IF('2Capital Costs'!D10<>"", '2Capital Costs'!D10, "") | E9: =IF($A9<>"", (IF('2Replacement Costs - Entry'!Y10="Y",((($B9*$D9)*((1+$B$5)^E$7))*(1/((1+$F$5)^E$7))),0)), "") | F9: =IF($A9<>"", (IF('2Replacement Costs - Entry'!Z10="Y",((($B9*$D9)*((1+$B$5)^F$7))*(1/((1+$F$5)^F$7))),0)), "") | G9: =IF($A9<>"", (IF('2Replacement Costs - Entry'!AA10="Y",((($B9*$D9)*((1+$B$5)^G$7))*(1/((1+$F$5)^G$7))),0)), "") | H9: =IF($A9<>"", (IF('2Replacement Costs - Entry'!AB10="Y",((($B9*$D9)*((1+$B$5)^H$7))*(1/((1+$F$5)^H$7))),0)), "") | I9: =IF($A9<>"", (IF('2Replacement Costs - Entry'!AC10="Y",((($B9*$D9)*((1+$B$5)^I$7))*(1/((1+$F$5)^I$7))),0)), "")
A10: =IF('2Capital Costs'!A11<>"", '2Capital Costs'!A11, "") | B10: =IF('2Capital Costs'!B11<>"", '2Capital Costs'!B11, "") | C10: =IF('2Capital Costs'!C11<>"", '2Capital Costs'!C11, "") | D10: =IF('2Capital Costs'!D11<>"", '2Capital Costs'!D11, "") | E10: =IF($A10<>"", (IF('2Replacement Costs - Entry'!Y11="Y",((($B10*$D10)*((1+$B$5)^E$7))*(1/((1+$F$5)^E$7))),0)), "") | F10: =IF($A10<>"", (IF('2Replacement Costs - Entry'!Z11="Y",((($B10*$D10)*((1+$B$5)^F$7))*(1/((1+$F$5)^F$7))),0)), "") | G10: =IF($A10<>"", (IF('2Replacement Costs - Entry'!AA11="Y",((($B10*$D10)*((1+$B$5)^G$7))*(1/((1+$F$5)^G$7))),0)), "") | H10: =IF($A10<>"", (IF('2Replacement Costs - Entry'!AB11="Y",((($B10*$D10)*((1+$B$5)^H$7))*(1/((1+$F$5)^H$7))),0)), "") | I10: =IF($A10<>"", (IF('2Replacement Costs - Entry'!AC11="Y",((($B10*$D10)*((1+$B$5)^I$7))*(1/((1+$F$5)^I$7))),0)), "")
A11: =IF('2Capital Costs'!A12<>"", '2Capital Costs'!A12, "") | B11: =IF('2Capital Costs'!B12<>"", '2Capital Costs'!B12, "") | C11: =IF('2Capital Costs'!C12<>"", '2Capital Costs'!C12, "") | D11: =IF('2Capital Costs'!D12<>"", '2Capital Costs'!D12, "") | E11: =IF($A11<>"", (IF('2Replacement Costs - Entry'!Y12="Y",((($B11*$D11)*((1+$B$5)^E$7))*(1/((1+$F$5)^E$7))),0)), "") | F11: =IF($A11<>"", (IF('2Replacement Costs - Entry'!Z12="Y",((($B11*$D11)*((1+$B$5)^F$7))*(1/((1+$F$5)^F$7))),0)), "") | G11: =IF($A11<>"", (IF('2Replacement Costs - Entry'!AA12="Y",((($B11*$D11)*((1+$B$5)^G$7))*(1/((1+$F$5)^G$7))),0)), "") | H11: =IF($A11<>"", (IF('2Replacement Costs - Entry'!AB12="Y",((($B11*$D11)*((1+$B$5)^H$7))*(1/((1+$F$5)^H$7))),0)), "") | I11: =IF($A11<>"", (IF('2Replacement Costs - Entry'!AC12="Y",((($B11*$D11)*((1+$B$5)^I$7))*(1/((1+$F$5)^I$7))),0)), "")
A12: =IF('2Capital Costs'!A13<>"", '2Capital Costs'!A13, "") | B12: =IF('2Capital Costs'!B13<>"", '2Capital Costs'!B13, "") | C12: =IF('2Capital Costs'!C13<>"", '2Capital Costs'!C13, "") | D12: =IF('2Capital Costs'!D13<>"", '2Capital Costs'!D13, "") | E12: =IF($A12<>"", (IF('2Replacement Costs - Entry'!Y13="Y",((($B12*$D12)*((1+$B$5)^E$7))*(1/((1+$F$5)^E$7))),0)), "") | F12: =IF($A12<>"", (IF('2Replacement Costs - Entry'!Z13="Y",((($B12*$D12)*((1+$B$5)^F$7))*(1/((1+$F$5)^F$7))),0)), "") | G12: =IF($A12<>"", (IF('2Replacement Costs - Entry'!AA13="Y",((($B12*$D12)*((1+$B$5)^G$7))*(1/((1+$F$5)^G$7))),0)), "") | H12: =IF($A12<>"", (IF('2Replacement Costs - Entry'!AB13="Y",((($B12*$D12)*((1+$B$5)^H$7))*(1/((1+$F$5)^H$7))),0)), "") | I12: =IF($A12<>"", (IF('2Replacement Costs - Entry'!AC13="Y",((($B12*$D12)*((1+$B$5)^I$7))*(1/((1+$F$5)^I$7))),0)), "")
A13: =IF('2Capital Costs'!A14<>"", '2Capital Costs'!A14, "") | B13: =IF('2Capital Costs'!B14<>"", '2Capital Costs'!B14, "") | C13: =IF('2Capital Costs'!C14<>"", '2Capital Costs'!C14, "") | D13: =IF('2Capital Costs'!D14<>"", '2Capital Costs'!D14, "") | E13: =IF($A13<>"", (IF('2Replacement Costs - Entry'!Y14="Y",((($B13*$D13)*((1+$B$5)^E$7))*(1/((1+$F$5)^E$7))),0)), "") | F13: =IF($A13<>"", (IF('2Replacement Costs - Entry'!Z14="Y",((($B13*$D13)*((1+$B$5)^F$7))*(1/((1+$F$5)^F$7))),0)), "") | G13: =IF($A13<>"", (IF('2Replacement Costs - Entry'!AA14="Y",((($B13*$D13)*((1+$B$5)^G$7))*(1/((1+$F$5)^G$7))),0)), "") | H13: =IF($A13<>"", (IF('2Replacement Costs - Entry'!AB14="Y",((($B13*$D13)*((1+$B$5)^H$7))*(1/((1+$F$5)^H$7))),0)), "") | I13: =IF($A13<>"", (IF('2Replacement Costs - Entry'!AC14="Y",((($B13*$D13)*((1+$B$5)^I$7))*(1/((1+$F$5)^I$7))),0)), "")
A14: =IF('2Capital Costs'!A15<>"", '2Capital Costs'!A15, "") | B14: =IF('2Capital Costs'!B15<>"", '2Capital Costs'!B15, "") | C14: =IF('2Capital Costs'!C15<>"", '2Capital Costs'!C15, "") | D14: =IF('2Capital Costs'!D15<>"", '2Capital Costs'!D15, "") | E14: =IF($A14<>"", (IF('2Replacement Costs - Entry'!Y15="Y",((($B14*$D14)*((1+$B$5)^E$7))*(1/((1+$F$5)^E$7))),0)), "") | F14: =IF($A14<>"", (IF('2Replacement Costs - Entry'!Z15="Y",((($B14*$D14)*((1+$B$5)^F$7))*(1/((1+$F$5)^F$7))),0)), "") | G14: =IF($A14<>"", (IF('2Replacement Costs - Entry'!AA15="Y",((($B14*$D14)*((1+$B$5)^G$7))*(1/((1+$F$5)^G$7))),0)), "") | H14: =IF($A14<>"", (IF('2Replacement Costs - Entry'!AB15="Y",((($B14*$D14)*((1+$B$5)^H$7))*(1/((1+$F$5)^H$7))),0)), "") | I14: =IF($A14<>"", (IF('2Replacement Costs - Entry'!AC15="Y",((($B14*$D14)*((1+$B$5)^I$7))*(1/((1+$F$5)^I$7))),0)), "")
A15: =IF('2Capital Costs'!A16<>"", '2Capital Costs'!A16, "") | B15: =IF('2Capital Costs'!B16<>"", '2Capital Costs'!B16, "") | C15: =IF('2Capital Costs'!C16<>"", '2Capital Costs'!C16, "") | D15: =IF('2Capital Costs'!D16<>"", '2Capital Costs'!D16, "") | E15: =IF($A15<>"", (IF('2Replacement Costs - Entry'!Y16="Y",((($B15*$D15)*((1+$B$5)^E$7))*(1/((1+$F$5)^E$7))),0)), "") | F15: =IF($A15<>"", (IF('2Replacement Costs - Entry'!Z16="Y",((($B15*$D15)*((1+$B$5)^F$7))*(1/((1+$F$5)^F$7))),0)), "") | G15: =IF($A15<>"", (IF('2Replacement Costs - Entry'!AA16="Y",((($B15*$D15)*((1+$B$5)^G$7))*(1/((1+$F$5)^G$7))),0)), "") | H15: =IF($A15<>"", (IF('2Replacement Costs - Entry'!AB16="Y",((($B15*$D15)*((1+$B$5)^H$7))*(1/((1+$F$5)^H$7))),0)), "") | I15: =IF($A15<>"", (IF('2Replacement Costs - Entry'!AC16="Y",((($B15*$D15)*((1+$B$5)^I$7))*(1/((1+$F$5)^I$7))),0)), "")
A16: =IF('2Capital Costs'!A17<>"", '2Capital Costs'!A17, "") | B16: =IF('2Capital Costs'!B17<>"", '2Capital Costs'!B17, "") | C16: =IF('2Capital Costs'!C17<>"", '2Capital Costs'!C17, "") | D16: =IF('2Capital Costs'!D17<>"", '2Capital Costs'!D17, "") | E16: =IF($A16<>"", (IF('2Replacement Costs - Entry'!Y17="Y",((($B16*$D16)*((1+$B$5)^E$7))*(1/((1+$F$5)^E$7))),0)), "") | F16: =IF($A16<>"", (IF('2Replacement Costs - Entry'!Z17="Y",((($B16*$D16)*((1+$B$5)^F$7))*(1/((1+$F$5)^F$7))),0)), "") | G16: =IF($A16<>"", (IF('2Replacement Costs - Entry'!AA17="Y",((($B16*$D16)*((1+$B$5)^G$7))*(1/((1+$F$5)^G$7))),0)), "") | H16: =IF($A16<>"", (IF('2Replacement Costs - Entry'!AB17="Y",((($B16*$D16)*((1+$B$5)^H$7))*(1/((1+$F$5)^H$7))),0)), "") | I16: =IF($A16<>"", (IF('2Replacement Costs - Entry'!AC17="Y",((($B16*$D16)*((1+$B$5)^I$7))*(1/((1+$F$5)^I$7))),0)), "")
A17: =IF('2Capital Costs'!A18<>"", '2Capital Costs'!A18, "") | B17: =IF('2Capital Costs'!B18<>"", '2Capital Costs'!B18, "") | C17: =IF('2Capital Costs'!C18<>"", '2Capital Costs'!C18, "") | D17: =IF('2Capital Costs'!D18<>"", '2Capital Costs'!D18, "") | E17: =IF($A17<>"", (IF('2Replacement Costs - Entry'!Y18="Y",((($B17*$D17)*((1+$B$5)^E$7))*(1/((1+$F$5)^E$7))),0)), "") | F17: =IF($A17<>"", (IF('2Replacement Costs - Entry'!Z18="Y",((($B17*$D17)*((1+$B$5)^F$7))*(1/((1+$F$5)^F$7))),0)), "") | G17: =IF($A17<>"", (IF('2Replacement Costs - Entry'!AA18="Y",((($B17*$D17)*((1+$B$5)^G$7))*(1/((1+$F$5)^G$7))),0)), "") | H17: =IF($A17<>"", (IF('2Replacement Costs - Entry'!AB18="Y",((($B17*$D17)*((1+$B$5)^H$7))*(1/((1+$F$5)^H$7))),0)), "") | I17: =IF($A17<>"", (IF('2Replacement Costs - Entry'!AC18="Y",((($B17*$D17)*((1+$B$5)^I$7))*(1/((1+$F$5)^I$7))),0)), "")
A18: =IF('2Capital Costs'!A19<>"", '2Capital Costs'!A19, "") | B18: =IF('2Capital Costs'!B19<>"", '2Capital Costs'!B19, "") | C18: =IF('2Capital Costs'!C19<>"", '2Capital Costs'!C19, "") | D18: =IF('2Capital Costs'!D19<>"", '2Capital Costs'!D19, "") | E18: =IF($A18<>"", (IF('2Replacement Costs - Entry'!Y19="Y",((($B18*$D18)*((1+$B$5)^E$7))*(1/((1+$F$5)^E$7))),0)), "") | F18: =IF($A18<>"", (IF('2Replacement Costs - Entry'!Z19="Y",((($B18*$D18)*((1+$B$5)^F$7))*(1/((1+$F$5)^F$7))),0)), "") | G18: =IF($A18<>"", (IF('2Replacement Costs - Entry'!AA19="Y",((($B18*$D18)*((1+$B$5)^G$7))*(1/((1+$F$5)^G$7))),0)), "") | H18: =IF($A18<>"", (IF('2Replacement Costs - Entry'!AB19="Y",((($B18*$D18)*((1+$B$5)^H$7))*(1/((1+$F$5)^H$7))),0)), "") | I18: =IF($A18<>"", (IF('2Replacement Costs - Entry'!AC19="Y",((($B18*$D18)*((1+$B$5)^I$7))*(1/((1+$F$5)^I$7))),0)), "")
A19: =IF('2Capital Costs'!A20<>"", '2Capital Costs'!A20, "") | B19: =IF('2Capital Costs'!B20<>"", '2Capital Costs'!B20, "") | C19: =IF('2Capital Costs'!C20<>"", '2Capital Costs'!C20, "") | D19: =IF('2Capital Costs'!D20<>"", '2Capital Costs'!D20, "") | E19: =IF($A19<>"", (IF('2Replacement Costs - Entry'!Y20="Y",((($B19*$D19)*((1+$B$5)^E$7))*(1/((1+$F$5)^E$7))),0)), "") | F19: =IF($A19<>"", (IF('2Replacement Costs - Entry'!Z20="Y",((($B19*$D19)*((1+$B$5)^F$7))*(1/((1+$F$5)^F$7))),0)), "") | G19: =IF($A19<>"", (IF('2Replacement Costs - Entry'!AA20="Y",((($B19*$D19)*((1+$B$5)^G$7))*(1/((1+$F$5)^G$7))),0)), "") | H19: =IF($A19<>"", (IF('2Replacement Costs - Entry'!AB20="Y",((($B19*$D19)*((1+$B$5)^H$7))*(1/((1+$F$5)^H$7))),0)), "") | I19: =IF($A19<>"", (IF('2Replacement Costs - Entry'!AC20="Y",((($B19*$D19)*((1+$B$5)^I$7))*(1/((1+$F$5)^I$7))),0)), "")
... A36: =IF('2Capital Costs'!A37<>"", '2Capital Costs'!A37, "") | B36: =IF('2Capital Costs'!B37<>"", '2Capital Costs'!B37, "") | C36: =IF('2Capital Costs'!C37<>"", '2Capital Costs'!C37, "") | D36: =IF('2Capital Costs'!D37<>"", '2Capital Costs'!D37, "") | E36: =IF($A36<>"", (IF('2Replacement Costs - Entry'!Y37="Y",((($B36*$D36)*((1+$B$5)^E$7))*(1/((1+$F$5)^E$7))),0)), "") | F36: =IF($A36<>"", (IF('2Replacement Costs - Entry'!Z37="Y",((($B36*$D36)*((1+$B$5)^F$7))*(1/((1+$F$5)^F$7))),0)), "") | G36: =IF($A36<>"", (IF('2Replacement Costs - Entry'!AA37="Y",((($B36*$D36)*((1+$B$5)^G$7))*(1/((1+$F$5)^G$7))),0)), "") | H36: =IF($A36<>"", (IF('2Replacement Costs - Entry'!AB37="Y",((($B36*$D36)*((1+$B$5)^H$7))*(1/((1+$F$5)^H$7))),0)), "") | I36: =IF($A36<>"", (IF('2Replacement Costs - Entry'!AC37="Y",((($B36*$D36)*((1+$B$5)^I$7))*(1/((1+$F$5)^I$7))),0)), "")
D37: Total Present Value of Replacment Costs (Years 16 to 20): | E37: =SUM(E8:E36) -> 0 | F37: =SUM(F8:F36) -> 0 | G37: =SUM(G8:G36) -> 0 | H37: =SUM(H8:H36) -> 0 | I37: =SUM(I8:I36) -> 0
H38: Total Present Value of Replacement Costs (Life of Project): | I38: ='2Replace Costs - Results 1-5'!E37+'2Replace Costs - Results 1-5'!F37+'2Replace Costs - Results 1-5'!G37+'2Replace Costs - Results 1-5'!H37+'2Replace Costs - Results 1-5'!I37+'2Replace Costs-Results 6-10'!E37+'2Replace Costs-Results 6-10'!F37+'2Replace Costs-Results 6-10'!G37+'2Replace Costs-Results 6-10'!H37+'2Replace Costs-Results 6-10'!I37+'2Replace Costs-Results 11-15'!E37+'2Replace Costs-Results 11-15'!F37+'2Replace Costs-Results 11-15'!G37+'2Replace Costs-Results 11-15'!H37+'2Replace Costs-Results 11-15'!I37+'2Replace Costs-Results 16-20'!E37+'2Replace Costs-Results 16-20'!F37+'2Replace Costs-Results 16-20'!G37+'2Replace Costs-Results 16-20'!H37+'2Replace Costs-Results 16-20'!I37 -> 0

Sheet 2Yearly O&M Costs 1-10
A1: Table 5.2.17. Present Value of Operations and Maintenance Costs (Years 1-10)
A2: ='Capital Costs'!A3:E3 -> 0
A3: ='Capital Costs'!A4:E4 -> 0
A4: ='2Capital Costs'!B6 -> 0
A5: Complete the cells shown in gray below.
A6: ='Yearly O&M Costs 11-20'!A5 -> Current Inflation Rate Based on Municipal Cost Index: | B6: ='Yearly O&M Costs 1-10'!B6 -> 0.027598896 | M6: EPA Discount Rate: | N6: ='Replace Costs-Results 16-20'!F5 -> 0.04875
E7: Present Value of O&M Costs for Year:
A8: Component | B8: Unit Cost | C8: Unit | D8: Quantity | E8: 1 | F8: 2 | G8: 3 | H8: 4 | I8: 5 | J8: 6 | K8: 7 | L8: 8 | M8: 9 | N8: 10
E9: =IF($A9<>"", (($B9*$D9)*((1+$B$6)^E$8)*(1/((1+$N$6)^E$8))), "") | F9: =IF($A9<>"", (($B9*$D9)*((1+$B$6)^F$8)*(1/((1+$N$6)^F$8))), "") | G9: =IF($A9<>"", (($B9*$D9)*((1+$B$6)^G$8)*(1/((1+$N$6)^G$8))), "") | H9: =IF($A9<>"", (($B9*$D9)*((1+$B$6)^H$8)*(1/((1+$N$6)^H$8))), "") | I9: =IF($A9<>"", (($B9*$D9)*((1+$B$6)^I$8)*(1/((1+$N$6)^I$8))), "") | J9: =IF($A9<>"", (($B9*$D9)*((1+$B$6)^J$8)*(1/((1+$N$6)^J$8))), "") | K9: =IF($A9<>"", (($B9*$D9)*((1+$B$6)^K$8)*(1/((1+$N$6)^K$8))), "") | L9: =IF($A9<>"", (($B9*$D9)*((1+$B$6)^L$8)*(1/((1+$N$6)^L$8))), "") | ... N9: =IF($A9<>"", (($B9*$D9)*((1+$B$6)^N$8)*(1/((1+$N$6)^N$8))), "")
E10: =IF($A10<>"", (($B10*$D10)*((1+$B$6)^E$8)*(1/((1+$N$6)^E$8))), "") | F10: =IF($A10<>"", (($B10*$D10)*((1+$B$6)^F$8)*(1/((1+$N$6)^F$8))), "") | G10: =IF($A10<>"", (($B10*$D10)*((1+$B$6)^G$8)*(1/((1+$N$6)^G$8))), "") | H10: =IF($A10<>"", (($B10*$D10)*((1+$B$6)^H$8)*(1/((1+$N$6)^H$8))), "") | I10: =IF($A10<>"", (($B10*$D10)*((1+$B$6)^I$8)*(1/((1+$N$6)^I$8))), "") | J10: =IF($A10<>"", (($B10*$D10)*((1+$B$6)^J$8)*(1/((1+$N$6)^J$8))), "") | K10: =IF($A10<>"", (($B10*$D10)*((1+$B$6)^K$8)*(1/((1+$N$6)^K$8))), "") | L10: =IF($A10<>"", (($B10*$D10)*((1+$B$6)^L$8)*(1/((1+$N$6)^L$8))), "") | ... N10: =IF($A10<>"", (($B10*$D10)*((1+$B$6)^N$8)*(1/((1+$N$6)^N$8))), "")
E11: =IF($A11<>"", (($B11*$D11)*((1+$B$6)^E$8)*(1/((1+$N$6)^E$8))), "") | F11: =IF($A11<>"", (($B11*$D11)*((1+$B$6)^F$8)*(1/((1+$N$6)^F$8))), "") | G11: =IF($A11<>"", (($B11*$D11)*((1+$B$6)^G$8)*(1/((1+$N$6)^G$8))), "") | H11: =IF($A11<>"", (($B11*$D11)*((1+$B$6)^H$8)*(1/((1+$N$6)^H$8))), "") | I11: =IF($A11<>"", (($B11*$D11)*((1+$B$6)^I$8)*(1/((1+$N$6)^I$8))), "") | J11: =IF($A11<>"", (($B11*$D11)*((1+$B$6)^J$8)*(1/((1+$N$6)^J$8))), "") | K11: =IF($A11<>"", (($B11*$D11)*((1+$B$6)^K$8)*(1/((1+$N$6)^K$8))), "") | L11: =IF($A11<>"", (($B11*$D11)*((1+$B$6)^L$8)*(1/((1+$N$6)^L$8))), "") | ... N11: =IF($A11<>"", (($B11*$D11)*((1+$B$6)^N$8)*(1/((1+$N$6)^N$8))), "")
E12: =IF($A12<>"", (($B12*$D12)*((1+$B$6)^E$8)*(1/((1+$N$6)^E$8))), "") | F12: =IF($A12<>"", (($B12*$D12)*((1+$B$6)^F$8)*(1/((1+$N$6)^F$8))), "") | G12: =IF($A12<>"", (($B12*$D12)*((1+$B$6)^G$8)*(1/((1+$N$6)^G$8))), "") | H12: =IF($A12<>"", (($B12*$D12)*((1+$B$6)^H$8)*(1/((1+$N$6)^H$8))), "") | I12: =IF($A12<>"", (($B12*$D12)*((1+$B$6)^I$8)*(1/((1+$N$6)^I$8))), "") | J12: =IF($A12<>"", (($B12*$D12)*((1+$B$6)^J$8)*(1/((1+$N$6)^J$8))), "") | K12: =IF($A12<>"", (($B12*$D12)*((1+$B$6)^K$8)*(1/((1+$N$6)^K$8))), "") | L12: =IF($A12<>"", (($B12*$D12)*((1+$B$6)^L$8)*(1/((1+$N$6)^L$8))), "") | ... N12: =IF($A12<>"", (($B12*$D12)*((1+$B$6)^N$8)*(1/((1+$N$6)^N$8))), "")
E13: =IF($A13<>"", (($B13*$D13)*((1+$B$6)^E$8)*(1/((1+$N$6)^E$8))), "") | F13: =IF($A13<>"", (($B13*$D13)*((1+$B$6)^F$8)*(1/((1+$N$6)^F$8))), "") | G13: =IF($A13<>"", (($B13*$D13)*((1+$B$6)^G$8)*(1/((1+$N$6)^G$8))), "") | H13: =IF($A13<>"", (($B13*$D13)*((1+$B$6)^H$8)*(1/((1+$N$6)^H$8))), "") | I13: =IF($A13<>"", (($B13*$D13)*((1+$B$6)^I$8)*(1/((1+$N$6)^I$8))), "") | J13: =IF($A13<>"", (($B13*$D13)*((1+$B$6)^J$8)*(1/((1+$N$6)^J$8))), "") | K13: =IF($A13<>"", (($B13*$D13)*((1+$B$6)^K$8)*(1/((1+$N$6)^K$8))), "") | L13: =IF($A13<>"", (($B13*$D13)*((1+$B$6)^L$8)*(1/((1+$N$6)^L$8))), "") | ... N13: =IF($A13<>"", (($B13*$D13)*((1+$B$6)^N$8)*(1/((1+$N$6)^N$8))), "")
E14: =IF($A14<>"", (($B14*$D14)*((1+$B$6)^E$8)*(1/((1+$N$6)^E$8))), "") | F14: =IF($A14<>"", (($B14*$D14)*((1+$B$6)^F$8)*(1/((1+$N$6)^F$8))), "") | G14: =IF($A14<>"", (($B14*$D14)*((1+$B$6)^G$8)*(1/((1+$N$6)^G$8))), "") | H14: =IF($A14<>"", (($B14*$D14)*((1+$B$6)^H$8)*(1/((1+$N$6)^H$8))), "") | I14: =IF($A14<>"", (($B14*$D14)*((1+$B$6)^I$8)*(1/((1+$N$6)^I$8))), "") | J14: =IF($A14<>"", (($B14*$D14)*((1+$B$6)^J$8)*(1/((1+$N$6)^J$8))), "") | K14: =IF($A14<>"", (($B14*$D14)*((1+$B$6)^K$8)*(1/((1+$N$6)^K$8))), "") | L14: =IF($A14<>"", (($B14*$D14)*((1+$B$6)^L$8)*(1/((1+$N$6)^L$8))), "") | ... N14: =IF($A14<>"", (($B14*$D14)*((1+$B$6)^N$8)*(1/((1+$N$6)^N$8))), "")
E15: =IF($A15<>"", (($B15*$D15)*((1+$B$6)^E$8)*(1/((1+$N$6)^E$8))), "") | F15: =IF($A15<>"", (($B15*$D15)*((1+$B$6)^F$8)*(1/((1+$N$6)^F$8))), "") | G15: =IF($A15<>"", (($B15*$D15)*((1+$B$6)^G$8)*(1/((1+$N$6)^G$8))), "") | H15: =IF($A15<>"", (($B15*$D15)*((1+$B$6)^H$8)*(1/((1+$N$6)^H$8))), "") | I15: =IF($A15<>"", (($B15*$D15)*((1+$B$6)^I$8)*(1/((1+$N$6)^I$8))), "") | J15: =IF($A15<>"", (($B15*$D15)*((1+$B$6)^J$8)*(1/((1+$N$6)^J$8))), "") | K15: =IF($A15<>"", (($B15*$D15)*((1+$B$6)^K$8)*(1/((1+$N$6)^K$8))), "") | L15: =IF($A15<>"", (($B15*$D15)*((1+$B$6)^L$8)*(1/((1+$N$6)^L$8))), "") | ... N15: =IF($A15<>"", (($B15*$D15)*((1+$B$6)^N$8)*(1/((1+$N$6)^N$8))), "")
E16: =IF($A16<>"", (($B16*$D16)*((1+$B$6)^E$8)*(1/((1+$N$6)^E$8))), "") | F16: =IF($A16<>"", (($B16*$D16)*((1+$B$6)^F$8)*(1/((1+$N$6)^F$8))), "") | G16: =IF($A16<>"", (($B16*$D16)*((1+$B$6)^G$8)*(1/((1+$N$6)^G$8))), "") | H16: =IF($A16<>"", (($B16*$D16)*((1+$B$6)^H$8)*(1/((1+$N$6)^H$8))), "") | I16: =IF($A16<>"", (($B16*$D16)*((1+$B$6)^I$8)*(1/((1+$N$6)^I$8))), "") | J16: =IF($A16<>"", (($B16*$D16)*((1+$B$6)^J$8)*(1/((1+$N$6)^J$8))), "") | K16: =IF($A16<>"", (($B16*$D16)*((1+$B$6)^K$8)*(1/((1+$N$6)^K$8))), "") | L16: =IF($A16<>"", (($B16*$D16)*((1+$B$6)^L$8)*(1/((1+$N$6)^L$8))), "") | ... N16: =IF($A16<>"", (($B16*$D16)*((1+$B$6)^N$8)*(1/((1+$N$6)^N$8))), "")
E17: =IF($A17<>"", (($B17*$D17)*((1+$B$6)^E$8)*(1/((1+$N$6)^E$8))), "") | F17: =IF($A17<>"", (($B17*$D17)*((1+$B$6)^F$8)*(1/((1+$N$6)^F$8))), "") | G17: =IF($A17<>"", (($B17*$D17)*((1+$B$6)^G$8)*(1/((1+$N$6)^G$8))), "") | H17: =IF($A17<>"", (($B17*$D17)*((1+$B$6)^H$8)*(1/((1+$N$6)^H$8))), "") | I17: =IF($A17<>"", (($B17*$D17)*((1+$B$6)^I$8)*(1/((1+$N$6)^I$8))), "") | J17: =IF($A17<>"", (($B17*$D17)*((1+$B$6)^J$8)*(1/((1+$N$6)^J$8))), "") | K17: =IF($A17<>"", (($B17*$D17)*((1+$B$6)^K$8)*(1/((1+$N$6)^K$8))), "") | L17: =IF($A17<>"", (($B17*$D17)*((1+$B$6)^L$8)*(1/((1+$N$6)^L$8))), "") | ... N17: =IF($A17<>"", (($B17*$D17)*((1+$B$6)^N$8)*(1/((1+$N$6)^N$8))), "")
E18: =IF($A18<>"", (($B18*$D18)*((1+$B$6)^E$8)*(1/((1+$N$6)^E$8))), "") | F18: =IF($A18<>"", (($B18*$D18)*((1+$B$6)^F$8)*(1/((1+$N$6)^F$8))), "") | G18: =IF($A18<>"", (($B18*$D18)*((1+$B$6)^G$8)*(1/((1+$N$6)^G$8))), "") | H18: =IF($A18<>"", (($B18*$D18)*((1+$B$6)^H$8)*(1/((1+$N$6)^H$8))), "") | I18: =IF($A18<>"", (($B18*$D18)*((1+$B$6)^I$8)*(1/((1+$N$6)^I$8))), "") | J18: =IF($A18<>"", (($B18*$D18)*((1+$B$6)^J$8)*(1/((1+$N$6)^J$8))), "") | K18: =IF($A18<>"", (($B18*$D18)*((1+$B$6)^K$8)*(1/((1+$N$6)^K$8))), "") | L18: =IF($A18<>"", (($B18*$D18)*((1+$B$6)^L$8)*(1/((1+$N$6)^L$8))), "") | ... N18: =IF($A18<>"", (($B18*$D18)*((1+$B$6)^N$8)*(1/((1+$N$6)^N$8))), "")
E19: =IF($A19<>"", (($B19*$D19)*((1+$B$6)^E$8)*(1/((1+$N$6)^E$8))), "") | F19: =IF($A19<>"", (($B19*$D19)*((1+$B$6)^F$8)*(1/((1+$N$6)^F$8))), "") | G19: =IF($A19<>"", (($B19*$D19)*((1+$B$6)^G$8)*(1/((1+$N$6)^G$8))), "") | H19: =IF($A19<>"", (($B19*$D19)*((1+$B$6)^H$8)*(1/((1+$N$6)^H$8))), "") | I19: =IF($A19<>"", (($B19*$D19)*((1+$B$6)^I$8)*(1/((1+$N$6)^I$8))), "") | J19: =IF($A19<>"", (($B19*$D19)*((1+$B$6)^J$8)*(1/((1+$N$6)^J$8))), "") | K19: =IF($A19<>"", (($B19*$D19)*((1+$B$6)^K$8)*(1/((1+$N$6)^K$8))), "") | L19: =IF($A19<>"", (($B19*$D19)*((1+$B$6)^L$8)*(1/((1+$N$6)^L$8))), "") | ... N19: =IF($A19<>"", (($B19*$D19)*((1+$B$6)^N$8)*(1/((1+$N$6)^N$8))), "")
E20: =IF($A20<>"", (($B20*$D20)*((1+$B$6)^E$8)*(1/((1+$N$6)^E$8))), "") | F20: =IF($A20<>"", (($B20*$D20)*((1+$B$6)^F$8)*(1/((1+$N$6)^F$8))), "") | G20: =IF($A20<>"", (($B20*$D20)*((1+$B$6)^G$8)*(1/((1+$N$6)^G$8))), "") | H20: =IF($A20<>"", (($B20*$D20)*((1+$B$6)^H$8)*(1/((1+$N$6)^H$8))), "") | I20: =IF($A20<>"", (($B20*$D20)*((1+$B$6)^I$8)*(1/((1+$N$6)^I$8))), "") | J20: =IF($A20<>"", (($B20*$D20)*((1+$B$6)^J$8)*(1/((1+$N$6)^J$8))), "") | K20: =IF($A20<>"", (($B20*$D20)*((1+$B$6)^K$8)*(1/((1+$N$6)^K$8))), "") | L20: =IF($A20<>"", (($B20*$D20)*((1+$B$6)^L$8)*(1/((1+$N$6)^L$8))), "") | ... N20: =IF($A20<>"", (($B20*$D20)*((1+$B$6)^N$8)*(1/((1+$N$6)^N$8))), "")
... E31: =IF($A31<>"", (($B31*$D31)*((1+$B$6)^E$8)*(1/((1+$N$6)^E$8))), "") | F31: =IF($A31<>"", (($B31*$D31)*((1+$B$6)^F$8)*(1/((1+$N$6)^F$8))), "") | G31: =IF($A31<>"", (($B31*$D31)*((1+$B$6)^G$8)*(1/((1+$N$6)^G$8))), "") | H31: =IF($A31<>"", (($B31*$D31)*((1+$B$6)^H$8)*(1/((1+$N$6)^H$8))), "") | I31: =IF($A31<>"", (($B31*$D31)*((1+$B$6)^I$8)*(1/((1+$N$6)^I$8))), "") | J31: =IF($A31<>"", (($B31*$D31)*((1+$B$6)^J$8)*(1/((1+$N$6)^J$8))), "") | K31: =IF($A31<>"", (($B31*$D31)*((1+$B$6)^K$8)*(1/((1+$N$6)^K$8))), "") | L31: =IF($A31<>"", (($B31*$D31)*((1+$B$6)^L$8)*(1/((1+$N$6)^L$8))), "") | ... N31: =IF($A31<>"", (($B31*$D31)*((1+$B$6)^N$8)*(1/((1+$N$6)^N$8))), "")
D32: Total Present Value of Yearly O&M Expenses (Years 1-10): | E32: =SUM(E9:E31) -> 0 | F32: =SUM(F9:F31) -> 0 | G32: =SUM(G9:G31) -> 0 | H32: =SUM(H9:H31) -> 0 | I32: =SUM(I9:I31) -> 0 | J32: =SUM(J9:J31) -> 0 | K32: =SUM(K9:K31) -> 0 | L32: =SUM(L9:L31) -> 0 | ... N32: =SUM(N9:N31) -> 0
A35: i= | B35: 0.04875

Sheet 2Yearly O&M Costs 11-20
A1: Table 5.2.18. Present Value of Operations and Maintenance Costs (Years 11-20)
A2: ='Capital Costs'!A3:E3 -> 0
A3: ='Capital Costs'!A4:E4 -> 0
A4: ='2Capital Costs'!B6 -> 0
A5: ='Yearly O&M Costs 1-10'!A6 -> Current Inflation Rate Based on Municipal Cost Index: | B5: ='Yearly O&M Costs 1-10'!B6 -> 0.027598896 | M5: EPA Discount Rate: | N5: ='Replace Costs-Results 16-20'!F5 -> 0.04875
E6: Present Value of O&M Costs for Year:
A7: Component | B7: Unit Cost | C7: Unit | D7: Quantity | E7: 11 | F7: 12 | G7: 13 | H7: 14 | I7: 15 | J7: 16 | K7: 17 | L7: 18 | M7: 19 | N7: 20
A8: =IF('2Yearly O&M Costs 1-10'!A9<>"", '2Yearly O&M Costs 1-10'!A9, "") | B8: =IF('2Yearly O&M Costs 1-10'!B9<>"", '2Yearly O&M Costs 1-10'!B9, "") | C8: =IF('2Yearly O&M Costs 1-10'!C9<>"", '2Yearly O&M Costs 1-10'!C9, "") | D8: =IF('2Yearly O&M Costs 1-10'!D9<>"", '2Yearly O&M Costs 1-10'!D9, "") | E8: =IF($A8<>"", (($B8*$D8)*((1+$B$5)^E$7)*(1/((1+$N$5)^E$7))), "") | F8: =IF($A8<>"", (($B8*$D8)*((1+$B$5)^F$7)*(1/((1+$N$5)^F$7))), "") | G8: =IF($A8<>"", (($B8*$D8)*((1+$B$5)^G$7)*(1/((1+$N$5)^G$7))), "") | H8: =IF($A8<>"", (($B8*$D8)*((1+$B$5)^H$7)*(1/((1+$N$5)^H$7))), "") | I8: =IF($A8<>"", (($B8*$D8)*((1+$B$5)^I$7)*(1/((1+$N$5)^I$7))), "") | J8: =IF($A8<>"", (($B8*$D8)*((1+$B$5)^J$7)*(1/((1+$N$5)^J$7))), "") | K8: =IF($A8<>"", (($B8*$D8)*((1+$B$5)^K$7)*(1/((1+$N$5)^K$7))), "") | L8: =IF($A8<>"", (($B8*$D8)*((1+$B$5)^L$7)*(1/((1+$N$5)^L$7))), "") | ... N8: =IF($A8<>"", (($B8*$D8)*((1+$B$5)^N$7)*(1/((1+$N$5)^N$7))), "")
A9: =IF('2Yearly O&M Costs 1-10'!A10<>"", '2Yearly O&M Costs 1-10'!A10, "") | B9: =IF('2Yearly O&M Costs 1-10'!B10<>"", '2Yearly O&M Costs 1-10'!B10, "") | C9: =IF('2Yearly O&M Costs 1-10'!C10<>"", '2Yearly O&M Costs 1-10'!C10, "") | D9: =IF('2Yearly O&M Costs 1-10'!D10<>"", '2Yearly O&M Costs 1-10'!D10, "") | E9: =IF($A9<>"", (($B9*$D9)*((1+$B$5)^E$7)*(1/((1+$N$5)^E$7))), "") | F9: =IF($A9<>"", (($B9*$D9)*((1+$B$5)^F$7)*(1/((1+$N$5)^F$7))), "") | G9: =IF($A9<>"", (($B9*$D9)*((1+$B$5)^G$7)*(1/((1+$N$5)^G$7))), "") | H9: =IF($A9<>"", (($B9*$D9)*((1+$B$5)^H$7)*(1/((1+$N$5)^H$7))), "") | I9: =IF($A9<>"", (($B9*$D9)*((1+$B$5)^I$7)*(1/((1+$N$5)^I$7))), "") | J9: =IF($A9<>"", (($B9*$D9)*((1+$B$5)^J$7)*(1/((1+$N$5)^J$7))), "") | K9: =IF($A9<>"", (($B9*$D9)*((1+$B$5)^K$7)*(1/((1+$N$5)^K$7))), "") | L9: =IF($A9<>"", (($B9*$D9)*((1+$B$5)^L$7)*(1/((1+$N$5)^L$7))), "") | ... N9: =IF($A9<>"", (($B9*$D9)*((1+$B$5)^N$7)*(1/((1+$N$5)^N$7))), "")
A10: =IF('2Yearly O&M Costs 1-10'!A11<>"", '2Yearly O&M Costs 1-10'!A11, "") | B10: =IF('2Yearly O&M Costs 1-10'!B11<>"", '2Yearly O&M Costs 1-10'!B11, "") | C10: =IF('2Yearly O&M Costs 1-10'!C11<>"", '2Yearly O&M Costs 1-10'!C11, "") | D10: =IF('2Yearly O&M Costs 1-10'!D11<>"", '2Yearly O&M Costs 1-10'!D11, "") | E10: =IF($A10<>"", (($B10*$D10)*((1+$B$5)^E$7)*(1/((1+$N$5)^E$7))), "") | F10: =IF($A10<>"", (($B10*$D10)*((1+$B$5)^F$7)*(1/((1+$N$5)^F$7))), "") | G10: =IF($A10<>"", (($B10*$D10)*((1+$B$5)^G$7)*(1/((1+$N$5)^G$7))), "") | H10: =IF($A10<>"", (($B10*$D10)*((1+$B$5)^H$7)*(1/((1+$N$5)^H$7))), "") | I10: =IF($A10<>"", (($B10*$D10)*((1+$B$5)^I$7)*(1/((1+$N$5)^I$7))), "") | J10: =IF($A10<>"", (($B10*$D10)*((1+$B$5)^J$7)*(1/((1+$N$5)^J$7))), "") | K10: =IF($A10<>"", (($B10*$D10)*((1+$B$5)^K$7)*(1/((1+$N$5)^K$7))), "") | L10: =IF($A10<>"", (($B10*$D10)*((1+$B$5)^L$7)*(1/((1+$N$5)^L$7))), "") | ... N10: =IF($A10<>"", (($B10*$D10)*((1+$B$5)^N$7)*(1/((1+$N$5)^N$7))), "")
A11: =IF('2Yearly O&M Costs 1-10'!A12<>"", '2Yearly O&M Costs 1-10'!A12, "") | B11: =IF('2Yearly O&M Costs 1-10'!B12<>"", '2Yearly O&M Costs 1-10'!B12, "") | C11: =IF('2Yearly O&M Costs 1-10'!C12<>"", '2Yearly O&M Costs 1-10'!C12, "") | D11: =IF('2Yearly O&M Costs 1-10'!D12<>"", '2Yearly O&M Costs 1-10'!D12, "") | E11: =IF($A11<>"", (($B11*$D11)*((1+$B$5)^E$7)*(1/((1+$N$5)^E$7))), "") | F11: =IF($A11<>"", (($B11*$D11)*((1+$B$5)^F$7)*(1/((1+$N$5)^F$7))), "") | G11: =IF($A11<>"", (($B11*$D11)*((1+$B$5)^G$7)*(1/((1+$N$5)^G$7))), "") | H11: =IF($A11<>"", (($B11*$D11)*((1+$B$5)^H$7)*(1/((1+$N$5)^H$7))), "") | I11: =IF($A11<>"", (($B11*$D11)*((1+$B$5)^I$7)*(1/((1+$N$5)^I$7))), "") | J11: =IF($A11<>"", (($B11*$D11)*((1+$B$5)^J$7)*(1/((1+$N$5)^J$7))), "") | K11: =IF($A11<>"", (($B11*$D11)*((1+$B$5)^K$7)*(1/((1+$N$5)^K$7))), "") | L11: =IF($A11<>"", (($B11*$D11)*((1+$B$5)^L$7)*(1/((1+$N$5)^L$7))), "") | ... N11: =IF($A11<>"", (($B11*$D11)*((1+$B$5)^N$7)*(1/((1+$N$5)^N$7))), "")
A12: =IF('2Yearly O&M Costs 1-10'!A13<>"", '2Yearly O&M Costs 1-10'!A13, "") | B12: =IF('2Yearly O&M Costs 1-10'!B13<>"", '2Yearly O&M Costs 1-10'!B13, "") | C12: =IF('2Yearly O&M Costs 1-10'!C13<>"", '2Yearly O&M Costs 1-10'!C13, "") | D12: =IF('2Yearly O&M Costs 1-10'!D13<>"", '2Yearly O&M Costs 1-10'!D13, "") | E12: =IF($A12<>"", (($B12*$D12)*((1+$B$5)^E$7)*(1/((1+$N$5)^E$7))), "") | F12: =IF($A12<>"", (($B12*$D12)*((1+$B$5)^F$7)*(1/((1+$N$5)^F$7))), "") | G12: =IF($A12<>"", (($B12*$D12)*((1+$B$5)^G$7)*(1/((1+$N$5)^G$7))), "") | H12: =IF($A12<>"", (($B12*$D12)*((1+$B$5)^H$7)*(1/((1+$N$5)^H$7))), "") | I12: =IF($A12<>"", (($B12*$D12)*((1+$B$5)^I$7)*(1/((1+$N$5)^I$7))), "") | J12: =IF($A12<>"", (($B12*$D12)*((1+$B$5)^J$7)*(1/((1+$N$5)^J$7))), "") | K12: =IF($A12<>"", (($B12*$D12)*((1+$B$5)^K$7)*(1/((1+$N$5)^K$7))), "") | L12: =IF($A12<>"", (($B12*$D12)*((1+$B$5)^L$7)*(1/((1+$N$5)^L$7))), "") | ... N12: =IF($A12<>"", (($B12*$D12)*((1+$B$5)^N$7)*(1/((1+$N$5)^N$7))), "")
A13: =IF('2Yearly O&M Costs 1-10'!A14<>"", '2Yearly O&M Costs 1-10'!A14, "") | B13: =IF('2Yearly O&M Costs 1-10'!B14<>"", '2Yearly O&M Costs 1-10'!B14, "") | C13: =IF('2Yearly O&M Costs 1-10'!C14<>"", '2Yearly O&M Costs 1-10'!C14, "") | D13: =IF('2Yearly O&M Costs 1-10'!D14<>"", '2Yearly O&M Costs 1-10'!D14, "") | E13: =IF($A13<>"", (($B13*$D13)*((1+$B$5)^E$7)*(1/((1+$N$5)^E$7))), "") | F13: =IF($A13<>"", (($B13*$D13)*((1+$B$5)^F$7)*(1/((1+$N$5)^F$7))), "") | G13: =IF($A13<>"", (($B13*$D13)*((1+$B$5)^G$7)*(1/((1+$N$5)^G$7))), "") | H13: =IF($A13<>"", (($B13*$D13)*((1+$B$5)^H$7)*(1/((1+$N$5)^H$7))), "") | I13: =IF($A13<>"", (($B13*$D13)*((1+$B$5)^I$7)*(1/((1+$N$5)^I$7))), "") | J13: =IF($A13<>"", (($B13*$D13)*((1+$B$5)^J$7)*(1/((1+$N$5)^J$7))), "") | K13: =IF($A13<>"", (($B13*$D13)*((1+$B$5)^K$7)*(1/((1+$N$5)^K$7))), "") | L13: =IF($A13<>"", (($B13*$D13)*((1+$B$5)^L$7)*(1/((1+$N$5)^L$7))), "") | ... N13: =IF($A13<>"", (($B13*$D13)*((1+$B$5)^N$7)*(1/((1+$N$5)^N$7))), "")
A14: =IF('2Yearly O&M Costs 1-10'!A15<>"", '2Yearly O&M Costs 1-10'!A15, "") | B14: =IF('2Yearly O&M Costs 1-10'!B15<>"", '2Yearly O&M Costs 1-10'!B15, "") | C14: =IF('2Yearly O&M Costs 1-10'!C15<>"", '2Yearly O&M Costs 1-10'!C15, "") | D14: =IF('2Yearly O&M Costs 1-10'!D15<>"", '2Yearly O&M Costs 1-10'!D15, "") | E14: =IF($A14<>"", (($B14*$D14)*((1+$B$5)^E$7)*(1/((1+$N$5)^E$7))), "") | F14: =IF($A14<>"", (($B14*$D14)*((1+$B$5)^F$7)*(1/((1+$N$5)^F$7))), "") | G14: =IF($A14<>"", (($B14*$D14)*((1+$B$5)^G$7)*(1/((1+$N$5)^G$7))), "") | H14: =IF($A14<>"", (($B14*$D14)*((1+$B$5)^H$7)*(1/((1+$N$5)^H$7))), "") | I14: =IF($A14<>"", (($B14*$D14)*((1+$B$5)^I$7)*(1/((1+$N$5)^I$7))), "") | J14: =IF($A14<>"", (($B14*$D14)*((1+$B$5)^J$7)*(1/((1+$N$5)^J$7))), "") | K14: =IF($A14<>"", (($B14*$D14)*((1+$B$5)^K$7)*(1/((1+$N$5)^K$7))), "") | L14: =IF($A14<>"", (($B14*$D14)*((1+$B$5)^L$7)*(1/((1+$N$5)^L$7))), "") | ... N14: =IF($A14<>"", (($B14*$D14)*((1+$B$5)^N$7)*(1/((1+$N$5)^N$7))), "")
A15: =IF('2Yearly O&M Costs 1-10'!A16<>"", '2Yearly O&M Costs 1-10'!A16, "") | B15: =IF('2Yearly O&M Costs 1-10'!B16<>"", '2Yearly O&M Costs 1-10'!B16, "") | C15: =IF('2Yearly O&M Costs 1-10'!C16<>"", '2Yearly O&M Costs 1-10'!C16, "") | D15: =IF('2Yearly O&M Costs 1-10'!D16<>"", '2Yearly O&M Costs 1-10'!D16, "") | E15: =IF($A15<>"", (($B15*$D15)*((1+$B$5)^E$7)*(1/((1+$N$5)^E$7))), "") | F15: =IF($A15<>"", (($B15*$D15)*((1+$B$5)^F$7)*(1/((1+$N$5)^F$7))), "") | G15: =IF($A15<>"", (($B15*$D15)*((1+$B$5)^G$7)*(1/((1+$N$5)^G$7))), "") | H15: =IF($A15<>"", (($B15*$D15)*((1+$B$5)^H$7)*(1/((1+$N$5)^H$7))), "") | I15: =IF($A15<>"", (($B15*$D15)*((1+$B$5)^I$7)*(1/((1+$N$5)^I$7))), "") | J15: =IF($A15<>"", (($B15*$D15)*((1+$B$5)^J$7)*(1/((1+$N$5)^J$7))), "") | K15: =IF($A15<>"", (($B15*$D15)*((1+$B$5)^K$7)*(1/((1+$N$5)^K$7))), "") | L15: =IF($A15<>"", (($B15*$D15)*((1+$B$5)^L$7)*(1/((1+$N$5)^L$7))), "") | ... N15: =IF($A15<>"", (($B15*$D15)*((1+$B$5)^N$7)*(1/((1+$N$5)^N$7))), "")
A16: =IF('2Yearly O&M Costs 1-10'!A17<>"", '2Yearly O&M Costs 1-10'!A17, "") | B16: =IF('2Yearly O&M Costs 1-10'!B17<>"", '2Yearly O&M Costs 1-10'!B17, "") | C16: =IF('2Yearly O&M Costs 1-10'!C17<>"", '2Yearly O&M Costs 1-10'!C17, "") | D16: =IF('2Yearly O&M Costs 1-10'!D17<>"", '2Yearly O&M Costs 1-10'!D17, "") | E16: =IF($A16<>"", (($B16*$D16)*((1+$B$5)^E$7)*(1/((1+$N$5)^E$7))), "") | F16: =IF($A16<>"", (($B16*$D16)*((1+$B$5)^F$7)*(1/((1+$N$5)^F$7))), "") | G16: =IF($A16<>"", (($B16*$D16)*((1+$B$5)^G$7)*(1/((1+$N$5)^G$7))), "") | H16: =IF($A16<>"", (($B16*$D16)*((1+$B$5)^H$7)*(1/((1+$N$5)^H$7))), "") | I16: =IF($A16<>"", (($B16*$D16)*((1+$B$5)^I$7)*(1/((1+$N$5)^I$7))), "") | J16: =IF($A16<>"", (($B16*$D16)*((1+$B$5)^J$7)*(1/((1+$N$5)^J$7))), "") | K16: =IF($A16<>"", (($B16*$D16)*((1+$B$5)^K$7)*(1/((1+$N$5)^K$7))), "") | L16: =IF($A16<>"", (($B16*$D16)*((1+$B$5)^L$7)*(1/((1+$N$5)^L$7))), "") | ... N16: =IF($A16<>"", (($B16*$D16)*((1+$B$5)^N$7)*(1/((1+$N$5)^N$7))), "")
A17: =IF('2Yearly O&M Costs 1-10'!A18<>"", '2Yearly O&M Costs 1-10'!A18, "") | B17: =IF('2Yearly O&M Costs 1-10'!B18<>"", '2Yearly O&M Costs 1-10'!B18, "") | C17: =IF('2Yearly O&M Costs 1-10'!C18<>"", '2Yearly O&M Costs 1-10'!C18, "") | D17: =IF('2Yearly O&M Costs 1-10'!D18<>"", '2Yearly O&M Costs 1-10'!D18, "") | E17: =IF($A17<>"", (($B17*$D17)*((1+$B$5)^E$7)*(1/((1+$N$5)^E$7))), "") | F17: =IF($A17<>"", (($B17*$D17)*((1+$B$5)^F$7)*(1/((1+$N$5)^F$7))), "") | G17: =IF($A17<>"", (($B17*$D17)*((1+$B$5)^G$7)*(1/((1+$N$5)^G$7))), "") | H17: =IF($A17<>"", (($B17*$D17)*((1+$B$5)^H$7)*(1/((1+$N$5)^H$7))), "") | I17: =IF($A17<>"", (($B17*$D17)*((1+$B$5)^I$7)*(1/((1+$N$5)^I$7))), "") | J17: =IF($A17<>"", (($B17*$D17)*((1+$B$5)^J$7)*(1/((1+$N$5)^J$7))), "") | K17: =IF($A17<>"", (($B17*$D17)*((1+$B$5)^K$7)*(1/((1+$N$5)^K$7))), "") | L17: =IF($A17<>"", (($B17*$D17)*((1+$B$5)^L$7)*(1/((1+$N$5)^L$7))), "") | ... N17: =IF($A17<>"", (($B17*$D17)*((1+$B$5)^N$7)*(1/((1+$N$5)^N$7))), "")
A18: =IF('2Yearly O&M Costs 1-10'!A19<>"", '2Yearly O&M Costs 1-10'!A19, "") | B18: =IF('2Yearly O&M Costs 1-10'!B19<>"", '2Yearly O&M Costs 1-10'!B19, "") | C18: =IF('2Yearly O&M Costs 1-10'!C19<>"", '2Yearly O&M Costs 1-10'!C19, "") | D18: =IF('2Yearly O&M Costs 1-10'!D19<>"", '2Yearly O&M Costs 1-10'!D19, "") | E18: =IF($A18<>"", (($B18*$D18)*((1+$B$5)^E$7)*(1/((1+$N$5)^E$7))), "") | F18: =IF($A18<>"", (($B18*$D18)*((1+$B$5)^F$7)*(1/((1+$N$5)^F$7))), "") | G18: =IF($A18<>"", (($B18*$D18)*((1+$B$5)^G$7)*(1/((1+$N$5)^G$7))), "") | H18: =IF($A18<>"", (($B18*$D18)*((1+$B$5)^H$7)*(1/((1+$N$5)^H$7))), "") | I18: =IF($A18<>"", (($B18*$D18)*((1+$B$5)^I$7)*(1/((1+$N$5)^I$7))), "") | J18: =IF($A18<>"", (($B18*$D18)*((1+$B$5)^J$7)*(1/((1+$N$5)^J$7))), "") | K18: =IF($A18<>"", (($B18*$D18)*((1+$B$5)^K$7)*(1/((1+$N$5)^K$7))), "") | L18: =IF($A18<>"", (($B18*$D18)*((1+$B$5)^L$7)*(1/((1+$N$5)^L$7))), "") | ... N18: =IF($A18<>"", (($B18*$D18)*((1+$B$5)^N$7)*(1/((1+$N$5)^N$7))), "")
A19: =IF('2Yearly O&M Costs 1-10'!A20<>"", '2Yearly O&M Costs 1-10'!A20, "") | B19: =IF('2Yearly O&M Costs 1-10'!B20<>"", '2Yearly O&M Costs 1-10'!B20, "") | C19: =IF('2Yearly O&M Costs 1-10'!C20<>"", '2Yearly O&M Costs 1-10'!C20, "") | D19: =IF('2Yearly O&M Costs 1-10'!D20<>"", '2Yearly O&M Costs 1-10'!D20, "") | E19: =IF($A19<>"", (($B19*$D19)*((1+$B$5)^E$7)*(1/((1+$N$5)^E$7))), "") | F19: =IF($A19<>"", (($B19*$D19)*((1+$B$5)^F$7)*(1/((1+$N$5)^F$7))), "") | G19: =IF($A19<>"", (($B19*$D19)*((1+$B$5)^G$7)*(1/((1+$N$5)^G$7))), "") | H19: =IF($A19<>"", (($B19*$D19)*((1+$B$5)^H$7)*(1/((1+$N$5)^H$7))), "") | I19: =IF($A19<>"", (($B19*$D19)*((1+$B$5)^I$7)*(1/((1+$N$5)^I$7))), "") | J19: =IF($A19<>"", (($B19*$D19)*((1+$B$5)^J$7)*(1/((1+$N$5)^J$7))), "") | K19: =IF($A19<>"", (($B19*$D19)*((1+$B$5)^K$7)*(1/((1+$N$5)^K$7))), "") | L19: =IF($A19<>"", (($B19*$D19)*((1+$B$5)^L$7)*(1/((1+$N$5)^L$7))), "") | ... N19: =IF($A19<>"", (($B19*$D19)*((1+$B$5)^N$7)*(1/((1+$N$5)^N$7))), "")
... A30: =IF('2Yearly O&M Costs 1-10'!A31<>"", '2Yearly O&M Costs 1-10'!A31, "") | B30: =IF('2Yearly O&M Costs 1-10'!B31<>"", '2Yearly O&M Costs 1-10'!B31, "") | C30: =IF('2Yearly O&M Costs 1-10'!C31<>"", '2Yearly O&M Costs 1-10'!C31, "") | D30: =IF('2Yearly O&M Costs 1-10'!D31<>"", '2Yearly O&M Costs 1-10'!D31, "") | E30: =IF($A30<>"", (($B30*$D30)*((1+$B$5)^E$7)*(1/((1+$N$5)^E$7))), "") | F30: =IF($A30<>"", (($B30*$D30)*((1+$B$5)^F$7)*(1/((1+$N$5)^F$7))), "") | G30: =IF($A30<>"", (($B30*$D30)*((1+$B$5)^G$7)*(1/((1+$N$5)^G$7))), "") | H30: =IF($A30<>"", (($B30*$D30)*((1+$B$5)^H$7)*(1/((1+$N$5)^H$7))), "") | I30: =IF($A30<>"", (($B30*$D30)*((1+$B$5)^I$7)*(1/((1+$N$5)^I$7))), "") | J30: =IF($A30<>"", (($B30*$D30)*((1+$B$5)^J$7)*(1/((1+$N$5)^J$7))), "") | K30: =IF($A30<>"", (($B30*$D30)*((1+$B$5)^K$7)*(1/((1+$N$5)^K$7))), "") | L30: =IF($A30<>"", (($B30*$D30)*((1+$B$5)^L$7)*(1/((1+$N$5)^L$7))), "") | ... N30: =IF($A30<>"", (($B30*$D30)*((1+$B$5)^N$7)*(1/((1+$N$5)^N$7))), "")
D31: Total Present Value of Yearly O&M Expenses (Years 11-20): | E31: =SUM(E8:E30) -> 0 | F31: =SUM(F8:F30) -> 0 | G31: =SUM(G8:G30) -> 0 | H31: =SUM(H8:H30) -> 0 | I31: =SUM(I8:I30) -> 0 | J31: =SUM(J8:J30) -> 0 | K31: =SUM(K8:K30) -> 0 | L31: =SUM(L8:L30) -> 0 | ... N31: =SUM(N8:N30) -> 0
M32: Total Present Value of Annual O&M Costs (Life of Project): | N32: ='2Yearly O&M Costs 1-10'!E32+'2Yearly O&M Costs 1-10'!F32+'2Yearly O&M Costs 1-10'!G32+'2Yearly O&M Costs 1-10'!H32+'2Yearly O&M Costs 1-10'!I32+'2Yearly O&M Costs 1-10'!J32+'2Yearly O&M Costs 1-10'!K32+'2Yearly O&M Costs 1-10'!L32+'2Yearly O&M Costs 1-10'!M32+'2Yearly O&M Costs 1-10'!N32+'2Yearly O&M Costs 11-20'!E31+'2Yearly O&M Costs 11-20'!F31+'2Yearly O&M Costs 11-20'!G31+'2Yearly O&M Costs 11-20'!H31+'2Yearly O&M Costs 11-20'!I31+'2Yearly O&M Costs 11-20'!J31+'2Yearly O&M Costs 11-20'!K31+'2Yearly O&M Costs 11-20'!L31+'2Yearly O&M Costs 11-20'!M31+'2Yearly O&M Costs 11-20'!N31 -> 0
A34: i= | B34: 0.04875

Sheet 2Inter O&M Entry
A1: Intermittent O&M Costs Input
