Workbook

Sheet Cover

Sheet Introduction
A4: American Indian Higher Education Consortium
A5: American Indian Measures for Success (AIMS)
A7: AIMS-Key Indicator System 2011 (AKIS-2011)

Sheet INSTRUCTIONS
A1: American Indian Higher Education Consortium
A2: American Indian Measures for Success (AIMS)
A4: AIMS-Key Indicator System 2011 (AKIS-2011)
A6: INSTRUCTIONS

Sheet 1.1 Overall Institution Profile
A1: Institution | B1: =B5 -> Oglala Lakota College | K1: degree
A2: Indicator 1: Overall Institution Profile | K2: 4-year & master's
A3: Table 1.1: Institution Profile, Contact Information, and Data Sources / AY 2010-11 | K3: 4-year& doctoral
A4: Institution Profile | K4: 4-year undergraduate
A5: Institution Name | B5: Oglala Lakota College | G5: Web Address | H5: www.olc.edu | K5: 2-year
A6: Address 1 | B6: Piya Wiconi - Three Mile Creek Road | G6: Highest Degree Offered | H6: 4-year & master's | I6: Academic Term | J6: semester
A7: Address 2 | B7: P.O. Box 490 | G7: Year Founded | H7: 1971 | I7: Land Granted Status | J7: yes | K7: academic term
A8: City | B8: Kyle | C8: State | D8: SD | E8: Zip | F8: 57752 | G8: Chartering Tribe | H8: Oglala Sioux Tribal Council | K8: quarter
A9: Telephone | B9: (605) 455-6000 | G9: Location | H9: on-reservation | I9: Operational Funding Source | J9: Pl-471 | K9: semester
A10: Person(s) Responsible for this Report | K10: trimester
A11: Name | B11: Title | D11: Telephone | G11: Email Address | K11: other
A12: Ursula R. Gaertmer. Ph.D. | B12: Institutional Research | D12: 605-455-6044 | G12: ugaertner@olc.edu
K13: land granted status
K14: yes
A15: Data Sources | K15: no
D16: Person(s) Responsible | G16: Notes
A17: Indicator 1: Overall Institution Profile | D17: Ursula R. Gaertner | K17: location
A18: Indicator 2: Financial Resources and Student Costs | D18: W. Eric Christiansen | K18: on reservation
A19: Indicator 3: Physical Resources | D19: W. Eric Christiansen | K19: off reservation
A20: Indicator 4: Student Enrollment and Graduation by Major Group | D20: Leslie Mesteth
A21: Indicator 5: Course Enrollment and Completion | D21: Leslie Mesteth
A22: Indicator 6: Student Activities | D22: Ruth Cedar Face
A23: Indicator 7: Personnel Demographics, Professional Development, Research, and Outcomes | D23: Faith Richards
A24: Indicator 8: Students with Disabilities Enrollment and Graduation | D24: Ruth Cedar Face
A25: Notes:
A27: Please certify that your institution's President has seen and approved this submission.
A28: Thomas Shortbull, President | D28: Ursula R. Gaertner, Institutional Research | H28: 40876
A29: President's Name | D29: Certified By | H29: Date

Sheet 1.2 Institution Profile
A1: Institution | D1: ='1.1 Overall Institution Profile'!$B$1 -> Oglala Lakota College
A2: Indicator 1: Overall Institution Profile
A3: Table 1.2: Institution Indian Student Count or Full Time Equivalent and Tribal Affiliations / AY 2010-11
A4: Please enter the institution's Indian Student Count or Full time Equivalent (FTE)1 and five largest tribal affiliations of enrolled students.
A5: Indian Student Count
B6: AY 2003-04 | E6: AY 2004-05 | H6: AY 2005-06 | K6: AY 2006-07 | N6: AY 2007-08
B7: Total | E7: Total | H7: Total | K7: Total | N7: Total
B8: 1126.4 | E8: 1202.51 | H8: 1131.51 | K8: 1069.8 | N8: 1069.63
B9: AY 2008-09
B10: Total
B11: 1046.35
A12: Full Time Equivalent (FTE)
C13: AY 2003-04 | H13: AY 2004-05 | M13: AY 2005-06
A14: American Indian | C14: Non-Indian | E14: FTE | F14: American Indian | H14: Non-Indian | J14: FTE | K14: American Indian | M14: Non-Indian | O14: FTE
A15: M | B15: F | C15: M | D15: F | E15: Total | F15: M | G15: F | H15: M | I15: F | J15: Total | K15: M | L15: F | M15: M | N15: F | O15: Total
A16: 0 | B16: 0 | C16: 0 | D16: 0 | E16: =SUM(A16:D16) -> 0 | F16: 0 | G16: 0 | H16: 0 | I16: 0 | J16: =SUM(F16:I16) -> 0 | K16: 0 | L16: 0 | M16: 0 | N16: 0 | O16: =SUM(K16:N16) -> 0
C17: AY 2006-07 | H17: AY 2007-08 | M17: AY 2008-09
A18: American Indian | C18: Non-Indian | E18: FTE | F18: American Indian | H18: Non-Indian | J18: FTE | K18: American Indian | M18: Non-Indian | O18: FTE
A19: M | B19: F | C19: M | D19: F | E19: Total | F19: M | G19: F | H19: M | I19: F | J19: Total | K19: M | L19: F | M19: M | N19: F | O19: Total
A20: 0 | B20: 0 | C20: 0 | D20: 0 | E20: =SUM(A20:D20) -> 0 | F20: 0 | G20: 0 | H20: 0 | I20: 0 | J20: =SUM(F20:I20) -> 0 | K20: 0 | L20: 0 | M20: 0 | N20: 0 | O20: =SUM(K20:N20) -> 0
A21: AY 2010-11 | C21: Part-Time AI Students | D21: Part-Time Non-AI Students | E21: Full-Time AI Students | F21: Full-Time Non-AI Students | G21: Part-Time AI Credits | H21: Part-Time Non-AI Credits | I21: Full-Time AI Credits | J21: Full-Time Non-AI Credits | K21: CEU AI Credits TOTAL | L21: CEU Non-AI Credits TOTAL | M21: ISC (see note) | N21: FTE (see note)
A22: Summer 2010 | C22: 282 | D22: 46 | E22: 40 | F22: 4 | G22: 1441 | H22: 181 | I22: 497 | J22: 49 | K22: 0 | L22: 0
A23: Fall 2010 | C23: 756 | D23: 98 | E23: 919 | F23: 57 | G23: 4427 | H23: 497 | I23: 11359 | J23: 717 | K23: 0 | L23: 0
A24: Winter 2011 | C24: NA | D24: NA | E24: NA | F24: NA | G24: NA | H24: NA | I24: NA | J24: NA | K24: NA | L24: NA
A25: Spring 2011 | C25: 719 | D25: 109 | E25: 967 | F25: 52 | G25: 4125 | H25: 462 | I25: 12131 | J25: 659 | K25: 0 | L25: 0
A26: TOTAL | C26: =SUM(C22:C25) -> 1757 | D26: =SUM(D22:D25) -> 253 | E26: =SUM(E22:E25) -> 1926 | F26: =SUM(F22:F25) -> 113 | G26: =SUM(G22:G25) -> 9993 | H26: =SUM(H22:H25) -> 1140 | I26: =SUM(I22:I25) -> 23987 | J26: =SUM(J22:J25) -> 1425 | ... L26: =SUM(L22:L25) -> 0 | M26: =SUM(G26,I26,K26)/24 -> 1415.8333 | N26: =SUM(G26:J26)/24 -> 1522.7083
A27: ISC-- See glossary for full definition. ISC=(FTAICR+PTAICR+CEU)/24, where CEUs used in calculation are limited to 10 percent of the institution’s ISC.
A28: FTE--The sum of credits enrolled in by all students divided by 24 equals the full-time equivalency. FTE=(FTCR+PTCR)/24
A29: Five Largest Tribal Affiliations of Students Enrolled at Tribal College
A30: Please list the five largest federally recognized tribes served by your institution. Total should not exceed total number of American Indian students enrolled (please see Table 4.2).
A31: Fall 2010 (October 15, 2010)
A32: Tribe | F32: # Enrolled | G32: % of Enrollment
A33: Oglala Sioux Tribe | F33: 1101 | G33: =SUM(F33/SUM('4.2 Major Group Totals'!D$10:'4.2 Major Group Totals'!E$10)) -> 0.65731343
A34: Cheyenne River | F34: 297 | G34: =SUM(F34/SUM('4.2 Major Group Totals'!D$10:'4.2 Major Group Totals'!E$10)) -> 0.17731343
A35: Rosebud Sioux | F35: 94 | G35: =SUM(F35/SUM('4.2 Major Group Totals'!D$10:'4.2 Major Group Totals'!E$10)) -> 0.056119403
A36: Standing Rock | F36: 42 | G36: =SUM(F36/SUM('4.2 Major Group Totals'!D$10:'4.2 Major Group Totals'!E$10)) -> 0.025074627
A37: Sisseton-Wahpeton | F37: 13 | G37: =SUM(F37/SUM('4.2 Major Group Totals'!D$10:'4.2 Major Group Totals'!E$10)) -> 0.007761194 | I37: =SUM(G33:H37) -> 0.92358209
A39: Other Tribes Represented Within Student Body | I39: NEW FOR 2011
A40: Please list all federally recognized tribes served by your institution. If more space is needed, please insert more lines.
A41: Fall 2010 (October 15, 2010)
A42: Alaska Native Claim Settlement
A43: Apache Tribe of Oklahoma
A44: Bay Mills Chippewa
A45: Crow Agency
A46: Central California Agency -Concow/Maidu
A47: Crow Creek Sioux Tribe
A48: Creek Tribe of Oklahoma
A49: Conf. Tribes of Colville Reservation
A50: Devils Lake Sioux Tribe
A51: Delaware Tribe of Western Oklahoma
... A82: Yankton Sioux

Sheet 1.3(11) First Time Students
A1: Institution | D1: ='1.1 Overall Institution Profile'!$B$1 -> Oglala Lakota College
A2: Indicator 1: Overall Institution Profile
A3: Table 1.3(10): First Time Entering Students Demographics / AY 2010-11
A4: Please enter the institution's first time entering student enrollment, background, and characteristics, including first-time freshman and transfer-in students. All data on this page is for the first time entering students only- not the entire institution
A5: First Time Entering Student Enrollment | L5: First Time Entering Student Background and Characteristics
D6: American Indian | F6: Non-Indian | H6: Total | L6: Number of students who graduated from
D7: M | E7: F | F7: M | G7: F | H7: M | I7: F | J7: Total | L7: Public High School not located on a reservation | R7: 38
A8: Full Time | D8: 129 | E8: 169 | F8: 4 | G8: 4 | H8: =SUM(D8,F8) -> 133 | I8: =SUM(E8,G8) -> 173 | J8: =SUM(H8:I8) -> 306 | L8: Reservation-based public High School | R8: 5
A9: Part Time | D9: 39 | E9: 50 | F9: 5 | G9: 9 | H9: =SUM(D9,F9) -> 44 | I9: =SUM(E9,G9) -> 59 | J9: =SUM(H9:I9) -> 103 | L9: BIA school | R9: 87
A10: Total | D10: =SUM(D8:D9) -> 168 | E10: =SUM(E8:E9) -> 219 | F10: =SUM(F8:F9) -> 9 | G10: =SUM(G8:G9) -> 13 | H10: =SUM(D10,F10) -> 177 | I10: =SUM(E10,G10) -> 232 | J10: =SUM(H10:I10) -> 409 | L10: Tribal or Contract High School | R10: 54
L11: Other High School | R11: 114
A12: First Time Entering Students Pre-College Preparation | L12: Not Reported | R12: 0
A13: Number of students who
A14: Graduated High School with Diploma | J14: 298 | L14: Number of students who are
A15: Earned GED | J15: 111 | L15: Single - No Children | R15: 205
A16: Enrolled under Ability to Benefit provision | J16: 0 | L16: Single with dependent children | R16: 168
A17: Dual enrolled High School and College | J17: 0 | L17: Married - No Children | R17: 8
A18: Have No High School Diploma or GED | J18: 0 | L18: Married with dependent children | R18: 28
A19: Not Reported | J19: 0 | L19: Not Reported | R19: 0 | S19: =SUM(R15:R19) -> 409
J20: =SUM(J14:J19) -> 409 | L20: Responsible for elderly family members in home | R20: 0
A21: Age range of students
A22: Number of students who are: | D22: 16-24 | E22: 25-34 | F22: 35-49 | G22: 50-64 | H22: 65 & over | I22: Not Reported | L22: Number of students who are
D23: 243 | E23: 115 | F23: 39 | G23: 9 | H23: 3 | I23: 0 | L23: First Generation Students | R23: 345
I24: =SUM(D23:J23) -> 409 | L24: Not First Generation Students | R24: 64 | S24: =SUM(R23:R24) -> 409
A25: Native language speakers | D25: None | E25: Basic | F25: Inter. | G25: Adv. | H25: Fluent | I25: Not Reported | L25: Not Reported | R25: 0
A26: (Self-reporting) | D26: 0 | E26: 38 | F26: 0 | G26: 0 | H26: 0 | I26: 371
I27: =SUM(D26:J26) -> 409 | L27: Primary residence is
A28: Skill Assessment / Placement Test Results | L28: On / near reservation (within 60 miles) | R28: 409
C29: Reading | E29: Writing / Composition | G29: Mathematics | I29: Science | L29: In-State | R29: 404
B30: Test Name | C30: Accuplacer | E30: NA | G30: Accuplacer | I30: NA | L30: Out-of-State | R30: 5
A31: Number of students | B31: Taking Test | C31: 344 | E31: NA | G31: 336 | I31: NA | L31: Not Reported | R31: 0
B32: Placed in Remedial / | C32: 204 | E32: NA | G32: 236 | I32: NA
B33: Development Course | L33: Financial Background
B34: Based on Test Results | L34: Average family income ($) in student's household | R34: 12987
L35: Number of students employed less than 20 hrs/week (excluding work / study) | R35: 65
A36: Please note if any data collected is from a sample of students (e.g. financial background data is only from students | L36: Number of students employed 20 or more hrs/week (excluding work / study) | R36: 80
A37: who applied for financial aid). | L37: Number of students eligible for financial aid | R37: 348
A38: Notes: | L38: Number of students in need, but not eligible for financial aid | R38: 24 | S38: =SUM(R37:R38) -> 372
A39: Re. Skills assessment: students take the Reading/sentence structure test and the Math test. Reading and Comp are in one test. We do not test Science.

Sheet 1.4 Institution Retention
A1: Institution | B1: ='1.1 Overall Institution Profile'!$B$1 -> Oglala Lakota College
A2: Indicator 1: Overall Institution Profile
A3: Table 1.4: Institution Total Student Retention and Completion -- NEW FOR 2011
A4: Accurate retention numbers for all Tribal Colleges and Universities have been a challenge to obtain. The method that has been used has yielded grossly undercalculated numbers. In an effort to find a way to capture a true representation of retention numbers for degree seekers and to include those students who are non-degree-seeking but whose completion is a success, please complete the following tables. If you have suggestions on how to improve this indicator, please include them in the Notes section below. If your institution uses a different method of calculating retention and/or completion, please demonstrate it on this page (e.g., create tables, provide formulas).
A5: Please enter the total number of students entering the institution for the first-time in Fall 2009, including transfers.
B6: Certificate | D6: Associate's | F6: Bachelor's | H6: Total
B7: Part-Time | C7: Full-Time | D7: Part-Time | E7: Full-Time | F7: Part-Time | G7: Full-Time | H7: Part-Time | I7: Full-Time
A8: First-time entering students in fall 2009 | B8: 0 | C8: 3 | D8: 26 | E8: 116 | F8: 9 | G8: 51 | H8: =SUM(B8,D8,F8) -> 35 | I8: =SUM(C8,E8,G8) -> 170
A9: Graduated in AY 2009-10 | B9: 0 | C9: 0 | D9: 0 | E9: 1 | F9: 0 | G9: 0 | H9: =SUM(B9,D9,F9) -> 0 | I9: =SUM(C9,E9,G9) -> 1
A10: Transferred to another college or university in AY 2009-10 | B10: 0 | C10: 0 | D10: 0 | E10: 0 | F10: 0 | G10: 0 | H10: =SUM(B10,D10,F10) -> 0 | I10: =SUM(C10,E10,G10) -> 0
A11: Withdrew or stopped out in AY 2009-10 | B11: 0 | C11: 2 | D11: 15 | E11: 42 | F11: 7 | G11: 24 | H11: =SUM(B11,D11,F11) -> 22 | I11: =SUM(C11,E11,G11) -> 68
A12: Other Exclusions in 2009-10* | B12: 0 | C12: 0 | D12: 0 | E12: 0 | F12: 0 | G12: 0 | H12: =SUM(B12,D12,F12) -> 0 | I12: =SUM(C12,E12,G12) -> 0
A13: Returned in fall 2010 | B13: 0 | C13: 1 | D13: 11 | E13: 74 | F13: 2 | G13: 27 | H13: =SUM(B13,D13,F13) -> 13 | I13: =SUM(C13,E13,G13) -> 102
A14: Graduated in AY 2010-11 | B14: 0 | C14: 0 | D14: 0 | E14: 1 | F14: 0 | G14: 0 | H14: =SUM(B14,D14,F14) -> 0 | I14: =SUM(C14,E14,G14) -> 1
A15: Transferred to another college or university in AY 2010-11 | B15: 0 | C15: 0 | D15: 0 | E15: 0 | F15: 0 | G15: 0 | H15: =SUM(B15,D15,F15) -> 0 | I15: =SUM(C15,E15,G15) -> 0
A16: Withdrew or stopped out in AY 2010-11 | B16: 0 | C16: 0 | D16: 2 | E16: 27 | F16: 1 | G16: 5 | H16: =SUM(B16,D16,F16) -> 3 | I16: =SUM(C16,E16,G16) -> 32
A17: Other Exclusions in 2010-11* | B17: 0 | C17: 0 | D17: 0 | E17: 0 | F17: 0 | G17: 0 | H17: =SUM(B17,D17,F17) -> 0 | I17: =SUM(C17,E17,G17) -> 0
A18: Returned in fall 2011 | B18: 0 | C18: 1 | D18: 10 | E18: 41 | F18: 4 | G18: 18 | H18: =SUM(B18,D18,F18) -> 14 | I18: =SUM(C18,E18,G18) -> 60
A19: Retention Rate 2009 to 2010 | B19: =(B13+B9)/(B8-B10-B12) -> #DIV/0! | C19: =(C13+C9)/(C8-C10-C12) -> 0.33333333 | D19: =(D13+D9)/(D8-D10-D12) -> 0.42307692 | E19: =(E13+E9)/(E8-E10-E12) -> 0.64655172 | F19: =(F13+F9)/(F8-F10-F12) -> 0.22222222 | G19: =(G13+G9)/(G8-G10-G12) -> 0.52941176 | H19: =(H13+H9)/(H8-H10-H12) -> 0.37142857 | I19: =(I13+I9)/(I8-I10-I12) -> 0.60588235
A20: Retention Rate 2010 to 2011 | B20: =(B18+B14)/(B8-B15-B17) -> #DIV/0! | C20: =(C18+C14)/(C8-C15-C17) -> 0.33333333 | D20: =(D18+D14)/(D8-D15-D17) -> 0.38461538 | E20: =(E18+E14)/(E8-E15-E17) -> 0.36206897 | F20: =(F18+F14)/(F8-F15-F17) -> 0.44444444 | G20: =(G18+G14)/(G8-G15-G17) -> 0.35294118 | H20: =(H18+H14)/(H8-H15-H17) -> 0.4 | I20: =(I18+I14)/(I8-I15-I17) -> 0.35882353
A22: Please enter the total number of students entering the institution for the first-time in Fall 2010, including transfers.
B23: Certificate | D23: Associate's | F23: Bachelor's | H23: Total
B24: Part-Time | C24: Full-Time | D24: Part-Time | E24: Full-Time | F24: Part-Time | G24: Full-Time | H24: Part-Time | I24: Full-Time
A25: First-time entering students in fall 2010 | B25: 0 | C25: 1 | D25: 34 | E25: 115 | F25: 21 | G25: 57 | H25: =SUM(B25,D25,F25) -> 55 | I25: =SUM(C25,E25,G25) -> 173
A26: Graduated in AY 2010-11 | B26: 0 | C26: 0 | D26: 0 | E26: 0 | F26: 0 | G26: 0 | H26: =SUM(B26,D26,F26) -> 0 | I26: =SUM(C26,E26,G26) -> 0
A27: Transferred to another college or university in AY 2010-11 | B27: 0 | C27: 0 | D27: 0 | E27: 0 | F27: 0 | G27: 0 | H27: =SUM(B27,D27,F27) -> 0 | I27: =SUM(C27,E27,G27) -> 0
A28: Withdrew or stopped out in AY 2010-11 | B28: 0 | C28: 1 | D28: 21 | E28: 76 | F28: 14 | G28: 37 | H28: =SUM(B28,D28,F28) -> 35 | I28: =SUM(C28,E28,G28) -> 114
A29: Other Exclusions in 2010-11* | B29: 0 | C29: 0 | D29: 0 | E29: 0 | F29: 0 | G29: 0 | H29: =SUM(B29,D29,F29) -> 0 | I29: =SUM(C29,E29,G29) -> 0
A30: Returned in fall 2011 | B30: 0 | C30: 0 | D30: 16 | E30: 47 | F30: 8 | G30: 25 | H30: =SUM(B30,D30,F30) -> 24 | I30: =SUM(C30,E30,G30) -> 72
A31: Retention Rate 2010 to 2011 | B31: =(B30+B26)/(B25-B27-B29) -> #DIV/0! | C31: =(C30+C26)/(C25-C27-C29) -> 0 | D31: =(D30+D26)/(D25-D27-D29) -> 0.47058824 | E31: =(E30+E26)/(E25-E27-E29) -> 0.40869565 | F31: =(F30+F26)/(F25-F27-F29) -> 0.38095238 | G31: =(G30+G26)/(G25-G27-G29) -> 0.43859649 | H31: =SUM(B31,D31,F31) -> #DIV/0! | I31: =SUM(C31,E31,G31) -> 0.84729214
A32: * Exclusions include students who are deceased, permanently disabled, have joined armed forces, and are on official church missions.
A34: Successful Course Completion
A35: Please enter the total number of students.
B36: Non-Degree Seeking or Undeclared | E36: Certificate or Degree-Seeking | H36: Total
B37: Fall 2010 | C37: Spring 2011 | D37: Summer 2011 | E37: Fall 2010 | F37: Spring 2011 | G37: Summer 2011 | H37: Fall 2010 | I37: Spring 2011 | J37: Summer 2011 | K37: AY 10-11 Total
A38: Total Number of Course Enrollments* | B38: 383 | C38: 427 | D38: 39 | E38: 6283 | F38: 6386 | G38: 443 | H38: =SUM(B38,E38) -> 6666 | I38: =SUM(C38,F38) -> 6813 | J38: =SUM(D38,G38) -> 482 | K38: =SUM(H38:J38) -> 13961
A39: Total Number of Successful Course Completions** | B39: 275 | C39: 349 | D39: 3 | E39: 3419 | F39: 3419 | G39: 331 | H39: =SUM(B39,E39) -> 3694 | I39: =SUM(C39,F39) -> 3768 | J39: =SUM(D39,G39) -> 334 | K39: =SUM(H39:J39) -> 7796
A40: Successful Course Completion Rate | B40: =B39/B38 -> 0.71801567 | C40: =C39/C38 -> 0.81733021 | D40: =D39/D38 -> 0.076923077 | E40: =E39/E38 -> 0.5441668 | F40: =F39/F38 -> 0.53538992 | G40: =G39/G38 -> 0.74717833 | H40: =H39/H38 -> 0.55415542 | I40: =I39/I38 -> 0.55306033 | ... K40: =K39/K38 -> 0.55841272
A41: * This will count students multiple times.
A42: ** Successful completion means passing with a grade of A, B, C, D, CR (credit), or P (pass)
A44: Institutional Persistence | B44: #s will auto-fill | C44: If there is a discrepancy between the numbers in this table and your institutional records, please explain in the Notes section below.
A45: Total FTE AY 2009-10 | B45: 1488.79 | C45: from Tab 1.2, AKIS A 2010
A46: Total Graduates AY 2009-10 | B46: 175 | C46: from Tab 4.2, AKIS A 2010
A47: Total FTE AY 2010-11 | B47: ='1.2 Institution Profile'!$N$26 -> 1522.7083 | C47: from Tab 1.2, AKIS A 2011
A48: First-time entering students in AY 2010-11 | B48: ='1.3(11) First Time Students'!$J$10 -> 409 | C48: from Tab 1.3, AKIS A 2011
A49: Persistence Rate 2009-10 to 2010-11 | B49: =(B47-B48)/(B45-B46) -> 0.84770651
A51: NOTES

Sheet 1.5(11) Community Education
B1: Institution | C1: ='1.1 Overall Institution Profile'!$B$1 -> Oglala Lakota College
A2: Indicator 1: Overall Institution Profile
A3: Table 1.5(10): Community Education Participation and Program Completion / AY 2010-11
A4: Please enter the institution's participation in community education programs
A5: Community Education Participation: (June 2009 - May 2010)
A6: Target Audience | B6: Program Name | C6: Funding Source of Program | D6: Number of Participants | H6: Number of students who completed the program* | I6: After completion of the program, Number matriculated into
D7: American Indian | E7: Non-Indian | F7: Unknown Race | G7: Total | I7: Your Institution | J7: Another Institution of Higher Education
A8: K-Grade 5 Students | B8: 4-Highschool Enrichment Ag in the classroom | C8: USDA NIFA | D8: 46 | E8: 0 | F8: 0 | G8: =SUM(D8:F8) -> 46 | H8: m
B9: Eagle Nest District Literacy Project | C9: BIA | D9: 10 | E9: 0 | F9: 0 | G9: =SUM(D9:F9) -> 10 | H9: 10
B10: NASA/SEMA/STEEP | C10: NASA | D10: 1800 | E10: 0 | F10: 0 | G10: =SUM(D10:F10) -> 1800 | H10: 1800
B11: Build your own Library Program | C11: Build your own Library Program | D11: 1000 | E11: 0 | F11: 0 | G11: =SUM(D11:F11) -> 1000 | H11: 1000
B12: Woksape Tipi Taniyohila Kici (Library) | C12: IMLS Grant | D12: 1054 | E12: 0 | F12: 0 | G12: =SUM(D12:F12) -> 1054 | H12: 1054
A13: Grade 6-8 Students | B13: 4-Highschool Enrichment Ag in the classroom | C13: USDA NIFA | D13: 60 | E13: 0 | F13: 0 | G13: =SUM(D13:F13) -> 60 | H13: m
B14: Juging OLC Science Fair | C14: USDA NIFA | D14: 30 | E14: 0 | F14: 0 | G14: =SUM(D14:F14) -> 30 | H14: m
B15: Eagle Nest District Literacy Project | C15: BIA | D15: 10 | E15: 0 | F15: 0 | G15: =SUM(D15:F15) -> 10 | H15: 10
B16: NASA/SEMA//LNSFC | C16: NASA | D16: 1200 | E16: 0 | F16: 0 | G16: =SUM(D16:F16) -> 1200 | H16: 1200
B17: STEEP | C17: NSF/HOPA/BUSH | D17: 30 | E17: 0 | F17: 0 | G17: =SUM(D17:F17) -> 30 | H17: 30
A18: Grade 9-12 Students | B18: JDC Organic Gardening | C18: USDA NIFA | D18: 75 | E18: 0 | F18: 0 | G18: =SUM(D18:F18) -> 75 | H18: m | I18: m | J18: m
B19: Career Day Pine Ridge Highschool | C19: NACTEP | D19: 150 | E19: 0 | F19: 0 | G19: =SUM(D19:F19) -> 150 | H19: 150 | I19: m | J19: m
B20: Career Day PR College Center | C20: NACTEP | D20: 30 | E20: 0 | F20: 0 | G20: =SUM(D20:F20) -> 30 | H20: 30 | I20: m | J20: m
B21: NASA/SEMA | C21: NASA | D21: 600 | E21: 0 | F21: 0 | G21: =SUM(D21:F21) -> 600 | H21: 600 | I21: m | J21: m
B22: LNSFC/STEEP | C22: NASA | D22: 30 | E22: 0 | F22: 0 | G22: =SUM(D22:F22) -> 30 | H22: 30 | I22: m | J22: m
G23: =SUM(D23:F23) -> 0
G24: =SUM(D24:F24) -> 0
B25: Build your own Library Program | C25: Build your own Library Program | D25: 500 | E25: 0 | F25: 0 | G25: =SUM(D25:F25) -> 500 | H25: 500 | I25: m | J25: m
A26: Adults | B26: Community Workshop/Community Gardening | C26: USDA NIFA | D26: 25 | E26: 0 | F26: 0 | G26: =SUM(D26:F26) -> 25 | H26: m | I26: m | J26: m
B27: Home Food Preservation | C27: USDA NIFA | D27: 30 | E27: 0 | F27: 0 | G27: =SUM(D27:F27) -> 30 | H27: m | I27: m | J27: m
B28: phone & e-mail requests for Ag information | C28: USDA NIFA | D28: 120 | E28: 0 | F28: 0 | G28: =SUM(D28:F28) -> 120 | H28: m | I28: m | J28: m
B29: Tree Planting | C29: USDA NIFA | D29: 10 | E29: 0 | F29: 0 | G29: =SUM(D29:F29) -> 10 | H29: m | I29: m | J29: m
B30: Erosion Control | C30: USDA NIFA | D30: 35 | E30: 0 | F30: 0 | G30: =SUM(D30:F30) -> 35 | H30: m | I30: m | J30: m
B31: NASA/SEMA | C31: NASA | D31: 30 | E31: 0 | F31: 0 | G31: =SUM(D31:F31) -> 30 | H31: m | I31: m | J31: m
B32: LNSFC | C32: NASA | D32: 10 | E32: 0 | F32: 0 | G32: =SUM(D32:F32) -> 10 | H32: m | I32: m | J32: m
B33: STEEP | C33: STEEP | D33: 20 | E33: 0 | F33: 0 | G33: =SUM(D33:F33) -> 20 | H33: m | I33: m | J33: m
B34: Lakota Premiere of "The Chiefs…." | C34: Library | D34: 20 | E34: 0 | F34: 0 | G34: =SUM(D34:F34) -> 20 | H34: m | I34: m | J34: m
B35: 3rd Annual Gathering of Lakota Elders | C35: Library | D35: 30 | E35: 0 | F35: 0 | G35: =SUM(D35:F35) -> 30 | H35: m | I35: m | J35: m
B36: Defenders of the Black Hills | C36: Library | D36: 25 | E36: 0 | F36: 0 | G36: =SUM(D36:F36) -> 25 | H36: m | I36: m | J36: m
B37: Sweetgrass Project "Bullying" | C37: Library | D37: 25 | E37: 0 | F37: 0 | G37: =SUM(D37:F37) -> 25 | H37: m | I37: m | J37: m
B38: 2010 Census | C38: Library | D38: 20 | E38: 0 | F38: 0 | G38: =SUM(D38:F38) -> 20 | H38: m | I38: m | J38: m
B39: James Welch by Kim Bettelyoun | C39: Library | D39: 25 | E39: 0 | F39: 0 | G39: =SUM(D39:F39) -> 25 | H39: m | I39: m | J39: m
B40: GED | C40: BIA/471 | D40: 597 | E40: 12 | F40: 0 | G40: =SUM(D40:F40) -> 609 | H40: 10 | I40: m | J40: m
B41: Adults continued: Itancan Waste Kici | C41: Department of Ed | D41: 23 | E41: 0 | F41: 0 | G41: =SUM(D41:F41) -> 23 | H41: m | I41: m | J41: m
B42: Eagle Nest District Literacy Project | C42: BIA | D42: 5 | E42: 0 | F42: 0 | G42: =SUM(D42:F42) -> 5 | H42: 5 | I42: m | J42: m
G43: =SUM(D43:F43) -> 0
G44: =SUM(D44:F44) -> 0
E46: Total | G46: =SUM(G8:G45) -> 7687 | H46: =SUM(H8:H45) -> 6429 | I46: =SUM(I8:I45) -> 0 | J46: =SUM(J8:J45) -> 0
A47: * Completed a program: did not receive a college credential (diploma, certificate, degree) but successfully completed requirements of a specific program (e.g. GED, Medical Billing Coder, Firefighter).
A48: Notes:
A49: Note: We do not track participants in community education projects.

Sheet 2.1 Student Tuition & Costs
A1: Institution | C1: ='1.1 Overall Institution Profile'!B1 -> Oglala Lakota College
A2: Indicator 2: Financial Resources and Student Costs
A3: Table 2.1: Student Tuition, Financial Aid, and Costs / AY 2010-11
A4: Please enter the tuition cost per credit hour, the total amount of financial aid received and the number of students receiving aid, and undergraduate student costs.
A5: Tuition Cost per Credit Hour | D5: AY 10-11
A6: Undergraduate | B6: American Indian Student | D6: 80
B7: Non-Indian Student | D7: 98
A8: Graduate | B8: American Indian Student | D8: 115
B9: Non-Indian Student | D9: 115
A11: Sources and Amount of Financial Aid | D11: AY 10-11
A12: American Indian College Fund Scholarship | C12: Total Dollar Amount | D12: 270830
C13: Total Number of Recipients | D13: 208
A14: Federal Pell Grants | C14: Total Dollar Amount | D14: 5189010
C15: Total Number of Recipients | D15: 1445
A16: Federal Supplemental Educational Opportunity Grant | C16: Total Dollar Amount | D16: 86872
C17: Total Number of Recipients | D17: 195
A18: State Scholarships/Grants | C18: Total Dollar Amount | D18: 74947
C19: Total Number of Recipients | D19: 249
A20: Academic Competitiveness Grant | C20: Total Dollar Amount | D20: 15893
C21: Total Number of Recipients | D21: 28
A22: School-to-Work | C22: Total Dollar Amount | D22: 0
C23: Total Number of Recipients | D23: 0
A24: Tribal Scholarships | C24: Total Dollar Amount | D24: 922811
C25: Total Number of Recipients | D25: 423
A26: Tuition Waiver/Discount | C26: Total Dollar Amount | D26: 30149
C27: Total Number of Recipients | D27: 67
A28: Other Scholarships | C28: Total Dollar Amount | D28: 253854
C29: Total Number of Recipients | D29: 189
A30: Federal College Work Study | C30: Total Dollar Amount | D30: 72855
C31: Total Number of Recipients | D31: 51
A32: State Work Study | C32: Total Dollar Amount | D32: 0
C33: Total Number of Recipients | D33: 0
A34: Institutional Work Study | C34: Total Dollar Amount | D34: 0
C35: Total Number of Recipients | D35: 0
A37: Average Full Time Undergraduate Student Costs for Academic Year | D37: AY 10-11
A38: Tuition | D38: 1920
A39: Room and Board | D39: 5400
A40: Transportation | D40: 3000
A41: Text Books | D41: 1200
A42: Supplies | D42: m
A43: Personal Expenses | D43: m
A44: Miscellaneous Expenses | D44: 1850
A45: Fees | D45: 476
A46: Total Student Costs | D46: =SUM(D38:D45) -> 13846
A48: Notes:

Sheet 3.1 Academic Building
A1: Institution | B1: ='1.1 Overall Institution Profile'!B1 -> Oglala Lakota College
A2: Indicator 3: Physical Resources
A3: Table 3.1: Building Facilities
A4: Please briefly summarize the institution's buildings. Identify building usage by main function. Reproduce this work sheet as needed. If building is used for multiple purposes (e.g. classroom and laboratory) please list building name as many times as necessary and identify total square feet for each main function.
A5: Does your institution have daycare or other early childhood learning facilities? | G5: NEW FOR 2011
A6: Existing Buildings
A7: Building Name | B7: Campus Site | C7: Year Built / Acquired | D7: No. of Stories | E7: Total sq. ft. | F7: Main Function | G7: Own / Lease | H7: Note | J7: Campus Site
A8: Piya Wiconi | B8: Main Campus | C8: 1980 | D8: 2 | E8: 24800 | F8: Administration/Office | G8: Own | J8: Main Campus
A9: Pine Ridge House 1 | B9: Satellite Site | C9: 1939 | D9: 1 | E9: 1700 | F9: Auxiliary | G9: Own | J9: Branch Campus
A10: Pine Ridge House 2 | B10: Satellite Site | C10: 1939 | D10: 1 | E10: 1700 | F10: Auxiliary | G10: Own | J10: Satellite Site
A11: Classrooms | B11: Satellite Site | C11: 1970 | D11: 1 | E11: 3080 | F11: Classroom | G11: Own
A12: Martin Building | B12: Satellite Site | C12: 1947 | D12: 1 | E12: 2500 | F12: Auxiliary | G12: Own | J12: Main Function
A13: Voc-Ed Building Metal Building | B13: Main Campus | C13: 1981 | D13: 1 | E13: 8400 | F13: Administration/Office | G13: Own | J13: Administration/Office
A14: Wooden Building | B14: Main Campus | C14: 1988 | D14: 1 | E14: 2100 | F14: Administration/Office | G14: Own | J14: Auxiliary
A15: Kyle Center | B15: Satellite Site | C15: 1994 | D15: 1 | E15: m | F15: Administration/Office | G15: Own | J15: Classroom
A16: Batesland Center | B16: Satellite Site | C16: 1994 | D16: 1 | E16: 5000 | F16: Administration/Office | G16: Own | J16: Cultural Center/Museum
A17: Porcupine Center | B17: Satellite Site | C17: 1997 | D17: 1 | E17: 6582 | F17: Classroom | G17: Own | J17: Distance Learning
A18: Pine Ridge Center | B18: Satellite Site | C18: 1997 | D18: 1 | E18: 12150 | F18: Classroom | G18: Own | J18: Laboratory
A19: Manderson Center | B19: Satellite Site | C19: 1998 | D19: 1 | E19: m | F19: Classroom | G19: Own | J19: Library
A20: Wanblee Center | B20: Satellite Site | C20: 1998 | D20: 1 | E20: m | F20: Classroom | G20: Own | J20: Research
A21: Oglala Center | B21: Satellite Site | C21: 1998 | D21: 1 | E21: m | F21: Classroom | G21: Own | J21: Residence
A22: Allen Center | B22: Satellite Site | C22: 1999 | D22: 1 | E22: m | F22: Classroom | G22: Own | J22: Student Services/Recreation
A23: Martin Center | B23: Satellite Site | C23: 1999 | D23: 1 | E23: m | F23: Classroom | G23: Own
A24: Rapid City Center | B24: Satellite Site | C24: 1999 | D24: 1 | E24: m | F24: Classroom | G24: Own | J24: Own/Lease
A25: Kyle Center Addition | B25: Satellite Site | C25: 2001 | D25: 1 | E25: m | F25: Classroom | G25: Own | J25: Assigned by Tribe
A26: Pine Ridge Log Cabin | B26: Satellite Site | C26: m | D26: 1 | E26: 4526 | F26: Auxiliary | G26: Own | J26: Donated
A27: Nursing Dorm | B27: Satellite Site | C27: 2003 | D27: 1 | E27: m | F27: Residence | G27: Own | J27: Lease/Rent
A28: Lakota Center for Science & Technology | B28: Main Campus | C28: 2003 | D28: 1 | E28: 6000 | F28: Laboratory | G28: Own | J28: Own
A29: Nursing Building | B29: Satellite Site | C29: 2004 | D29: 1 | E29: 8000 | F29: Classroom | G29: Own
A30: Pine Ridge College Center Expansion | B30: Satellite Site | C30: 2004 | D30: 1 | E30: 4500 | F30: Classroom | G30: Own
A31: He Sapa College Center Expansion | B31: Satellite Site | C31: 2006 | D31: 1 | E31: 6500 | F31: Classroom | G31: Own
A32: Cheyenne River College Center | B32: Satellite Site | C32: 2000 | D32: 1 | E32: 25000 | F32: Classroom | G32: Assigned by Tribe
A33: Pine Ridge Dorms | B33: Satellite Site | C33: 2006 | D33: 1 | E33: 4200 | F33: Residence | G33: Own
A34: Pole Barn Building | B34: Main Campus | C34: 2008 | D34: 1 | E34: 2040 | F34: Administration/Office | G34: Own
A35: Bookstore | B35: Main Campus | C35: 2008 | D35: 1 | E35: 3625 | F35: Administration/Office | G35: Own
A36: Batesland Head Start | B36: Satellite Site | C36: 2008 | D36: 1 | E36: 1680 | F36: Classroom | G36: Own
A37: Wanblee Head Start | B37: Satellite Site | C37: 2008 | D37: 1 | E37: 2576 | F37: Classroom | G37: Own
A38: Pejuta Haka Dorms | B38: Satellite Site | C38: 2009 | D38: 1 | E38: 9000 | F38: Residence | G38: Own
A39: Martin Head Start | B39: Satellite Site | C39: 2009 | D39: 1 | E39: 2591 | F39: Classroom | G39: Own
A40: Manderson Head Start | B40: Satellite Site | C40: 2009 | D40: 1 | E40: 3200 | F40: Classroom | G40: Own
A41: Multipurpose Building | B41: Main Campus | C41: 2010 | D41: 1 | E41: 14733 | F41: Student Services/Recreation | G41: Own | H41: Gymnasium
A42: Auto Technology Building | B42: Satellite Site | C42: 2011 | D42: 1 | E42: 8400 | F42: Classroom | G42: Own
A43: Rapid City Center #2 | B43: Satellite Site | C43: 2011 | D43: 2 | E43: 4850 | F43: Classroom | G43: Own
A58: Notes:

Sheet 3.2 Library Fac & Res Equipment
A1: Institution | D1: ='1.1 Overall Institution Profile'!B1 -> Oglala Lakota College
A2: Indicator 3: Physical Resources | N2: Inter-Library System
A3: Table 3.2: Library Facilities / AY 2010-11 | N3: Computer Lab w/ Internet
A4: Please briefly summarize the current status of library facilities. | N4: <select one>
A5: Library Facility | N5: Yes
A6: Library Name | C6: Total sq. ft. | D6: Year Built / Remodeled | E6: Volumes | F6: Periodicals | H6: Catalogue On-line Access | I6: Inter-Library System | J6: Computer Lab w/ Internet | K6: Community Library Status | L6: Community Learning Center | N6: No
F7: Print | G7: Electronic
A8: Woksape Tipi | C8: 18000 | D8: 1997 | E8: 49000 | F8: 60 | G8: 80* | H8: Yes | I8: Yes | J8: Yes | K8: Community Library | L8: Yes
N10: Community Library
A11: Special Cultural Collections: Please briefly describe any cultural or tribal museum/archival collections housed in library or other building.
A12: Museum, Archival Collections; - Lakota Artifacts (e.g. head dresses, pipes, moccasins), - manuscripts, microfilm, video, audio, photographs, maps, posters, rare books, publications covering broad spectrum of Lakota history, society, culture, and institutions; - institutional records of Oglala Lakota College and Oglala Sioux Tribe; - Artwork by Oglala Lakota artists (contemporary).
A13: Library Improvements / Acquisitions during academic year
A14: AY 10-11 | B14: None. Remodeling project is underway for AY2011-2012.
A15: Notes:
A16: * w/3000+ titles

Sheet 3.3 Research Equipment
A1: Institution | B1: ='1.1 Overall Institution Profile'!B1 -> Oglala Lakota College
A2: Indicator 3: Physical Resources
A3: Table 3.3: Instructional/ Research Equipment and Facilities Acquired /AY 2010-11
A4: Please enter major instructional/ research equipment and facilities acquired during the academic year
A5: Major Instructional/ Research Equipment and Facilities Acquisition
B6: AY 10-11
A7: Equipment or Facility Name | B7: Math & Science Lab Renovation - New equipment
A8: Purchase Cost | B8: 73818
A9: Number of Units | B9: 1 lot
A10: Purpose | B10: update science labs
A11: Equipment or Facility Name
A12: Purchase Cost
A13: Number of Units
A14: Purpose
A15: Equipment or Facility Name
A16: Purchase Cost
A17: Number of Units
A18: Purpose
A19: Equipment or Facility Name
A20: Purchase Cost
A21: Number of Units
A22: Purpose
... A63: Notes:
A64: 0

Sheet 4.1 Majors
B1: Institution | C1: ='1.1 Overall Institution Profile'!$B$1 -> Oglala Lakota College | E1: Major Group ID/Major Groups
A2: Indicator 4: Student Enrollment and Graduation by Major Group | E2: AC - Accounting
A3: Table 4.1: Major Groups | E3: AG - Agriculture and Farming
A4: Please identify your institution's specific majors and degrees offered by major group. If you have additional majors, please add them as needed. | E4: AL - American Indian Languages
A5: Major Groups | E5: AS - American Indian Studies
A6: I.D. | B6: Major Groups | C6: Specific Majors (and Degrees Offered) | E6: AR - Art
A7: AC | B7: Accounting | C7: (AA) | E7: AU - Automotive Technology
A8: AL | B8: American Indian Languages | C8: Lakota Language (CT) | E8: BI - Biology
A9: AS | B9: American Indian Studies | C9: Lakota Studies (AA, BA); K-12 Lakota Studies Education (BS); Tribal Law (AA); | E9: BT - Building Trades
A10: AR | B10: Art | C10: Fine Art (AA) | E10: BU - Business
A11: BT | B11: Building Trades | C11: Electrical Technology (AAS); General Construction (CT, AAS); | E11: CH - Chemistry
A12: BU | B12: Business | C12: Business Administration (BS); | E12: CS - Computer Science
A13: CS | B13: Computer Science | C13: Information Technology (AA, BS); | E13: CT - Computer Technology
E14: CL - Corrections/Law Enforcement
A15: EA | B15: Education-Paraprofessional | C15: Child Development Associate (CT); Early Childhood (AA); Elementary Education (AA) | E15: EA - Education-Paraprofessional
A16: EO | B16: Education-Professional | C16: Early Childhood (BA); K-8 Elementary Education (BS); | E16: EO - Education-Professional
A17: ES | B17: Environmental Science/Natural Resources | C17: Natural Science (BS) | E17: EN - English
A18: HC | E18: ES - Environmental Science/Natural Resources
A19: HI | B19: Hospitality Industry | C19: Customer Service (CT, AAS) | E19: GE - Geography
A20: HS | B20: Human Services | C20: Social Work (BSW); Chemical Dependency Counseling (AA) | E20: HS - Health Careers
A21: LA | B21: Liberal Arts/General Studies | C21: Liberal Atrs (AA); English and Communications (BA) | E21: HI - Hospitality Industry
A22: LS | B22: Life Science | C22: Life Science (AA) | E22: HS - Human Services
A23: NU | B23: Nursing | C23: Nursing (AA) | E23: IP - Individualized Program
A24: OA | B24: Office Administration/Technology | C24: Office Technology (CT, AAS); Office Software Applications (CT, AAS) | E24: LA - Liberal Arts/General Studies
A25: SC | B25: Science | C25: Science, Engineering & Mathematics (AA); Secondary Education Physical Science (BS) | E25: LS - Life Sciences
A26: SS | B26: Social Science | C26: Social Science (AA, BA) | E26: MA - Mathematics
A27: VC | B27: Vocational | C27: program discontinued
A28: MS | B28: Master's | C28: Lakota Leadership/Management (MA); Secondary/Middle/Elementary Educational Administration (MA) | E28: NU - Nursing
A29: UN | B29: Undeclared/Nondeclared | C29: Undeclared | E29: OA - Office Administration/Technology
E30: PA - Paralegal
E31: PE - Pre-Engineering/Engineering
E32: PV - Pre-Veterinary Science
E33: SC - Science
E34: SS - Social Science
A35: Notes: | E35: VC - Vocational/Career Programs
E36: UD - Undeclared/Nondeclared
E37: MS - Master's Degree Programs

Sheet 4.2(AC) Major Group Enroll-Grad
A1: Institution | D1: ='1.1 Overall Institution Profile'!B1 -> Oglala Lakota College
A2: Indicator 4: Student Enrollment and Graduation by Major Group
A3: Table 4.2(AC): Major Group Fall Enrollment, Graduation & Post-Graduate / AY 2010-11
B4: Major Group | C4: AC - Accounting
B5: Please enter the number of students enrolled in this major group for the fall semester.
F6: Fall 2010 (October 15, 2010)
B7: Fall Enrollment (Snapshot) | D7: American Indian | F7: Non-Indian
D8: M | E8: F | F8: M | G8: F | H8: Total
C9: Full Time | D9: 0 | E9: 19 | F9: 0 | G9: 2 | H9: =SUM(D9:G9) -> 21
C10: Part Time | D10: 0 | E10: 14 | F10: 0 | G10: 0 | H10: =SUM(D10:G10) -> 14
C11: Total | D11: =SUM(D9:D10) -> 0 | E11: =SUM(E9:E10) -> 33 | F11: =SUM(F9:F10) -> 0 | G11: =SUM(G9:G10) -> 2 | H11: =SUM(D11:G11) -> 35
B12: Please enter the number of diploma, certificates, and degrees earned in this major group. Also enter the number of students graduating with degrees who earned a GPA of 3.0 or above, and the number who were admitted to a 4 year (Associate degree graduates), or graduate school (Bachelor's degree graduates). Lastly, enter the number of all graduating students(certificate or degree) who secured employment after graduation.
F13: July 1, 2010- June 30, 2011
B14: Graduation | D14: American Indian | F14: Non-Indian
D15: M | E15: F | F15: M | G15: F | H15: Total
A16: Apprenticeship/Occupational Program | D16: na | E16: na | F16: na | G16: na | H16: =SUM(D16:G16) -> 0
A17: Diploma | D17: na | E17: na | F17: na | G17: na | H17: =SUM(D17:G17) -> 0
A18: Certificate | D18: na | E18: na | F18: na | G18: na | H18: =SUM(D18:G18) -> 0
A19: Associate Degree | D19: 2 | E19: 10 | F19: 0 | G19: 1 | H19: =SUM(D19:G19) -> 13
B20: Assoc. graduates admitted to four-year program | D20: 0 | E20: 0 | F20: 0 | G20: 0 | H20: =SUM(D20:G20) -> 0
B21: Assoc. graduated with a GPA of 3.0 or above | D21: 1 | E21: 4 | F21: 0 | G21: 1 | H21: =SUM(D21:G21) -> 6
A22: Bachelor's Degree | D22: na | E22: na | F22: na | G22: na | H22: =SUM(D22:G22) -> 0
B23: Bach. graduates admitted to graduate school | D23: na | E23: na | F23: na | G23: na | H23: =SUM(D23:G23) -> 0
B24: Bach. graduated with a GPA of 3.0 or above | D24: na | E24: na | F24: na | G24: na | H24: =SUM(D24:G24) -> 0
A25: Master's Degree | D25: na | E25: na | F25: na | G25: na | H25: =SUM(D25:G25) -> 0
A26: Employed after graduation | D26: m | E26: m | F26: m | G26: m | H26: =SUM(D26:G26) -> 0
A28: Notes:
A29: na = not offered; m = not tracked

Sheet 4.2(AG) Major Group Enroll-Grad
A1: Institution | D1: ='1.1 Overall Institution Profile'!B1 -> Oglala Lakota College
A2: Indicator 4: Student Enrollment and Graduation by Major Group
A3: Table 4.2(AG): Major Group Fall Enrollment, Graduation & Post-Graduate / AY 2010-11
B4: Major Group | C4: AG - Agriculture and Farming
B5: Please enter the number of students enrolled in this major group for the fall semester.
F6: Fall 2010 (October 15, 2010)
B7: Fall Enrollment (Snapshot) | D7: American Indian | F7: Non-Indian
D8: M | E8: F | F8: M | G8: F | H8: Total
C9: Full Time | D9: na | E9: na | F9: na | G9: na | H9: =SUM(D9:G9) -> 0
C10: Part Time | D10: na | E10: na | F10: na | G10: na | H10: =SUM(D10:G10) -> 0
C11: Total | D11: =SUM(D9:D10) -> 0 | E11: =SUM(E9:E10) -> 0 | F11: =SUM(F9:F10) -> 0 | G11: =SUM(G9:G10) -> 0 | H11: =SUM(D11:G11) -> 0
B12: Please enter the number of diploma, certificates, and degrees earned in this major group. Also enter the number of students graduating with degrees who earned a GPA of 3.0 or above, and the number who were admitted to a 4 year (Associate degree graduates), or graduate school (Bachelor's degree graduates). Lastly, enter the number of all graduating students(certificate or degree) who secured employment after graduation.
F13: July 1, 2010- June 30, 2011
B14: Graduation | D14: American Indian | F14: Non-Indian
D15: M | E15: F | F15: M | G15: F | H15: Total
A16: Apprenticeship/Occupational Program | D16: na | E16: na | F16: na | G16: na | H16: =SUM(D16:G16) -> 0
A17: Diploma | D17: na | E17: na | F17: na | G17: na | H17: =SUM(D17:G17) -> 0
A18: Certificate | D18: na | E18: na | F18: na | G18: na | H18: =SUM(D18:G18) -> 0
A19: Associate Degree | D19: na | E19: na | F19: na | G19: na | H19: =SUM(D19:G19) -> 0
B20: Assoc. graduates admitted to four-year program | D20: na | E20: na | F20: na | G20: na | H20: =SUM(D20:G20) -> 0
B21: Assoc. graduated with a GPA of 3.0 or above | D21: na | E21: na | F21: na | G21: na | H21: =SUM(D21:G21) -> 0
A22: Bachelor's Degree | D22: na | E22: na | F22: na | G22: na | H22: =SUM(D22:G22) -> 0
B23: Bach. graduates admitted to graduate school | D23: na | E23: na | F23: na | G23: na | H23: =SUM(D23:G23) -> 0
B24: Bach. graduated with a GPA of 3.0 or above | D24: na | E24: na | F24: na | G24: na | H24: =SUM(D24:G24) -> 0
A25: Master's Degree | D25: na | E25: na | F25: na | G25: na | H25: =SUM(D25:G25) -> 0
A26: Employed after graduation | D26: na | E26: na | F26: na | G26: na | H26: =SUM(D26:G26) -> 0
A28: Notes:

Sheet 4.2(AL) Major Group Enroll-Grad
A1: Institution | D1: ='1.1 Overall Institution Profile'!B1 -> Oglala Lakota College
A2: Indicator 4: Student Enrollment and Graduation by Major Group
A3: Table 4.2(AL): Major Group Fall Enrollment, Graduation & Post-Graduate / AY 2010-11
B4: Major Group | C4: AL - American Indian Languages
B5: Please enter the number of students enrolled in this major group for the fall semester.
F6: Fall 2010 (October 15, 2010)
B7: Fall Enrollment (Snapshot) | D7: American Indian | F7: Non-Indian
D8: M | E8: F | F8: M | G8: F | H8: Total
C9: Full Time | D9: 0 | E9: 0 | F9: 0 | G9: 0 | H9: =SUM(D9:G9) -> 0
C10: Part Time | D10: 0 | E10: 0 | F10: 0 | G10: 0 | H10: =SUM(D10:G10) -> 0
C11: Total | D11: =SUM(D9:D10) -> 0 | E11: =SUM(E9:E10) -> 0 | F11: =SUM(F9:F10) -> 0 | G11: =SUM(G9:G10) -> 0 | H11: =SUM(D11:G11) -> 0
B12: Please enter the number of diploma, certificates, and degrees earned in this major group. Also enter the number of students graduating with degrees who earned a GPA of 3.0 or above, and the number who were admitted to a 4 year (Associate degree graduates), or graduate school (Bachelor's degree graduates). Lastly, enter the number of all graduating students(certificate or degree) who secured employment after graduation.
F13: July 1, 2010- June 30, 2011
B14: Graduation | D14: American Indian | F14: Non-Indian
D15: M | E15: F | F15: M | G15: F | H15: Total
A16: Apprenticeship/Occupational Program | D16: na | E16: na | F16: na | G16: na | H16: =SUM(D16:G16) -> 0
A17: Diploma | D17: na | E17: na | F17: na | G17: na | H17: =SUM(D17:G17) -> 0
A18: Certificate | D18: 0 | E18: 5 | F18: 0 | G18: 0 | H18: =SUM(D18:G18) -> 5
A19: Associate Degree | D19: na | E19: na | F19: na | G19: na | H19: =SUM(D19:G19) -> 0
B20: Assoc. graduates admitted to four-year program | D20: na | E20: na | F20: na | G20: na | H20: =SUM(D20:G20) -> 0
B21: Assoc. graduated with a GPA of 3.0 or above | D21: na | E21: na | F21: na | G21: na | H21: =SUM(D21:G21) -> 0
A22: Bachelor's Degree | D22: na | E22: na | F22: na | G22: na | H22: =SUM(D22:G22) -> 0
B23: Bach. graduates admitted to graduate school | D23: na | E23: na | F23: na | G23: na | H23: =SUM(D23:G23) -> 0
B24: Bach. graduated with a GPA of 3.0 or above | D24: na | E24: na | F24: na | G24: na | H24: =SUM(D24:G24) -> 0
A25: Master's Degree | D25: na | E25: na | F25: na | G25: na | H25: =SUM(D25:G25) -> 0
A26: Employed after graduation | D26: m | E26: m | F26: m | G26: m | H26: =SUM(D26:G26) -> 0
A28: Notes:
A29: na = not offered; m = not tracked;

Sheet 4.2(AS) Major Group Enroll-Grad
A1: Institution | D1: ='1.1 Overall Institution Profile'!B1 -> Oglala Lakota College
A2: Indicator 4: Student Enrollment and Graduation by Major Group
A3: Table 4.2(AS): Major Group Fall Enrollment, Graduation & Post-Graduate / AY 2010-11
B4: Major Group | C4: AS - American Indian Studies
B5: Please enter the number of students enrolled in this major group for the fall semester.
F6: Fall 2010 (October 15, 2010)
B7: Fall Enrollment (Snapshot) | D7: American Indian | F7: Non-Indian
D8: M | E8: F | F8: M | G8: F | H8: Total
C9: Full Time | D9: 31 | E9: 39 | F9: 0 | G9: 0 | H9: =SUM(D9:G9) -> 70
C10: Part Time | D10: 23 | E10: 46 | F10: 3 | G10: 2 | H10: =SUM(D10:G10) -> 74
C11: Total | D11: =SUM(D9:D10) -> 54 | E11: =SUM(E9:E10) -> 85 | F11: =SUM(F9:F10) -> 3 | G11: =SUM(G9:G10) -> 2 | H11: =SUM(D11:G11) -> 144
B12: Please enter the number of diploma, certificates, and degrees earned in this major group. Also enter the number of students graduating with degrees who earned a GPA of 3.0 or above, and the number who were admitted to a 4 year (Associate degree graduates), or graduate school (Bachelor's degree graduates). Lastly, enter the number of all graduating students(certificate or degree) who secured employment after graduation.
F13: July 1, 2010- June 30, 2011
B14: Graduation | D14: American Indian | F14: Non-Indian
D15: M | E15: F | F15: M | G15: F | H15: Total
A16: Apprenticeship/Occupational Program | D16: na | E16: na | F16: na | G16: na | H16: =SUM(D16:G16) -> 0
A17: Diploma | D17: na | E17: na | F17: na | G17: na | H17: =SUM(D17:G17) -> 0
A18: Certificate | D18: na | E18: na | F18: na | G18: na | H18: =SUM(D18:G18) -> 0
A19: Associate Degree | D19: 7 | E19: 20 | F19: 0 | G19: 1 | H19: =SUM(D19:G19) -> 28
B20: Assoc. graduates admitted to four-year program | D20: 0 | E20: 0 | F20: 0 | G20: 0 | H20: =SUM(D20:G20) -> 0
B21: Assoc. graduated with a GPA of 3.0 or above | D21: 2 | E21: 12 | F21: 0 | G21: 1 | H21: =SUM(D21:G21) -> 15
A22: Bachelor's Degree | D22: 4 | E22: 6 | F22: 1 | G22: 0 | H22: =SUM(D22:G22) -> 11
B23: Bach. graduates admitted to graduate school | D23: 0 | E23: 0 | F23: 0 | G23: 0 | H23: =SUM(D23:G23) -> 0
B24: Bach. graduated with a GPA of 3.0 or above | D24: 2 | E24: 3 | F24: 1 | G24: 0 | H24: =SUM(D24:G24) -> 6
A25: Master's Degree | D25: na | E25: na | F25: na | G25: na | H25: =SUM(D25:G25) -> 0
A26: Employed after graduation | D26: m | E26: m | F26: m | G26: m | H26: =SUM(D26:G26) -> 0
A28: Notes:
A29: na = not offered; m = not tracked;

Sheet 4.2(AR) Major Group Enroll-Grad
A1: Institution | D1: ='1.1 Overall Institution Profile'!B1 -> Oglala Lakota College
A2: Indicator 4: Student Enrollment and Graduation by Major Group
A3: Table 4.2(AR): Major Group Fall Enrollment, Graduation & Post-Graduate / AY 2010-11
B4: Major Group | C4: AR - Art
B5: Please enter the number of students enrolled in this major group for the fall semester.
F6: Fall 2010 (October 15, 2010)
B7: Fall Enrollment (Snapshot) | D7: American Indian | F7: Non-Indian
D8: M | E8: F | F8: M | G8: F | H8: Total
C9: Full Time | D9: 6 | E9: 2 | F9: 0 | G9: 0 | H9: =SUM(D9:G9) -> 8
C10: Part Time | D10: 1 | E10: 1 | F10: 0 | G10: 0 | H10: =SUM(D10:G10) -> 2
C11: Total | D11: =SUM(D9:D10) -> 7 | E11: =SUM(E9:E10) -> 3 | F11: =SUM(F9:F10) -> 0 | G11: =SUM(G9:G10) -> 0 | H11: =SUM(D11:G11) -> 10
B12: Please enter the number of diploma, certificates, and degrees earned in this major group. Also enter the number of students graduating with degrees who earned a GPA of 3.0 or above, and the number who were admitted to a 4 year (Associate degree graduates), or graduate school (Bachelor's degree graduates). Lastly, enter the number of all graduating students(certificate or degree) who secured employment after graduation.
F13: July 1, 2010- June 30, 2011
B14: Graduation | D14: American Indian | F14: Non-Indian
D15: M | E15: F | F15: M | G15: F | H15: Total
A16: Apprenticeship/Occupational Program | D16: na | E16: na | F16: na | G16: na | H16: =SUM(D16:G16) -> 0
A17: Diploma | D17: na | E17: na | F17: na | G17: na | H17: =SUM(D17:G17) -> 0
A18: Certificate | D18: na | E18: na | F18: na | G18: na | H18: =SUM(D18:G18) -> 0
A19: Associate Degree | D19: 0 | E19: 0 | F19: 0 | G19: 0 | H19: =SUM(D19:G19) -> 0
B20: Assoc. graduates admitted to four-year program | D20: 0 | E20: 0 | F20: 0 | G20: 0 | H20: =SUM(D20:G20) -> 0
B21: Assoc. graduated with a GPA of 3.0 or above | D21: 0 | E21: 0 | F21: 0 | G21: 0 | H21: =SUM(D21:G21) -> 0
A22: Bachelor's Degree | D22: na | E22: na | F22: na | G22: na | H22: =SUM(D22:G22) -> 0
B23: Bach. graduates admitted to graduate school | D23: na | E23: na | F23: na | G23: na | H23: =SUM(D23:G23) -> 0
B24: Bach. graduated with a GPA of 3.0 or above | D24: na | E24: na | F24: na | G24: na | H24: =SUM(D24:G24) -> 0
A25: Master's Degree | D25: na | E25: na | F25: na | G25: na | H25: =SUM(D25:G25) -> 0
A26: Employed after graduation | D26: m | E26: m | F26: m | G26: m | H26: =SUM(D26:G26) -> 0
A28: Notes:
A29: na = not offered; m = not tracked;

Sheet 4.2(AU) Major Group Enroll-Grad
A1: Institution | D1: ='1.1 Overall Institution Profile'!B1 -> Oglala Lakota College
A2: Indicator 4: Student Enrollment and Graduation by Major Group
A3: Table 4.2(AU): Major Group Fall Enrollment, Graduation & Post-Graduate / AY 2010-11
B4: Major Group | C4: AU - Automotive
B5: Please enter the number of students enrolled in this major group for the fall semester.
F6: Fall 2010 (October 15, 2010)
B7: Fall Enrollment (Snapshot) | D7: American Indian | F7: Non-Indian
D8: M | E8: F | F8: M | G8: F | H8: Total
C9: Full Time | D9: na | E9: na | F9: na | G9: na | H9: =SUM(D9:G9) -> 0
C10: Part Time | D10: na | E10: na | F10: na | G10: na | H10: =SUM(D10:G10) -> 0
C11: Total | D11: =SUM(D9:D10) -> 0 | E11: =SUM(E9:E10) -> 0 | F11: =SUM(F9:F10) -> 0 | G11: =SUM(G9:G10) -> 0 | H11: =SUM(D11:G11) -> 0
B12: Please enter the number of diploma, certificates, and degrees earned in this major group. Also enter the number of students graduating with degrees who earned a GPA of 3.0 or above, and the number who were admitted to a 4 year (Associate degree graduates), or graduate school (Bachelor's degree graduates). Lastly, enter the number of all graduating students(certificate or degree) who secured employment after graduation.
F13: July 1, 2010- June 30, 2011
B14: Graduation | D14: American Indian | F14: Non-Indian
D15: M | E15: F | F15: M | G15: F | H15: Total
A16: Apprenticeship/Occupational Program | D16: na | E16: na | F16: na | G16: na | H16: =SUM(D16:G16) -> 0
A17: Diploma | D17: na | E17: na | F17: na | G17: na | H17: =SUM(D17:G17) -> 0
A18: Certificate | D18: na | E18: na | F18: na | G18: na | H18: =SUM(D18:G18) -> 0
A19: Associate Degree | D19: na | E19: na | F19: na | G19: na | H19: =SUM(D19:G19) -> 0
B20: Assoc. graduates admitted to four-year program | D20: na | E20: na | F20: na | G20: na | H20: =SUM(D20:G20) -> 0
B21: Assoc. graduated with a GPA of 3.0 or above | D21: na | E21: na | F21: na | G21: na | H21: =SUM(D21:G21) -> 0
A22: Bachelor's Degree | D22: na | E22: na | F22: na | G22: na | H22: =SUM(D22:G22) -> 0
B23: Bach. graduates admitted to graduate school | D23: na | E23: na | F23: na | G23: na | H23: =SUM(D23:G23) -> 0
B24: Bach. graduated with a GPA of 3.0 or above | D24: na | E24: na | F24: na | G24: na | H24: =SUM(D24:G24) -> 0
A25: Master's Degree | D25: na | E25: na | F25: na | G25: na | H25: =SUM(D25:G25) -> 0
A26: Employed after graduation | D26: na | E26: na | F26: na | G26: na | H26: =SUM(D26:G26) -> 0
A28: Notes:

Sheet 4.2(BI) Major Group Enroll-Grad
A1: Institution | D1: ='1.1 Overall Institution Profile'!B1 -> Oglala Lakota College
A2: Indicator 4: Student Enrollment and Graduation by Major Group
A3: Table 4.2(BI): Major Group Fall Enrollment, Graduation & Post-Graduate / AY 2010-11
B4: Major Group | C4: BI - Biology
B5: Please enter the number of students enrolled in this major group for the fall semester.
F6: Fall 2010 (October 15, 2010)
B7: Fall Enrollment (Snapshot) | D7: American Indian | F7: Non-Indian
D8: M | E8: F | F8: M | G8: F | H8: Total
C9: Full Time | D9: na | E9: na | F9: na | G9: na | H9: =SUM(D9:G9) -> 0
C10: Part Time | D10: na | E10: na | F10: na | G10: na | H10: =SUM(D10:G10) -> 0
C11: Total | D11: =SUM(D9:D10) -> 0 | E11: =SUM(E9:E10) -> 0 | F11: =SUM(F9:F10) -> 0 | G11: =SUM(G9:G10) -> 0 | H11: =SUM(D11:G11) -> 0
B12: Please enter the number of diploma, certificates, and degrees earned in this major group. Also enter the number of students graduating with degrees who earned a GPA of 3.0 or above, and the number who were admitted to a 4 year (Associate degree graduates), or graduate school (Bachelor's degree graduates). Lastly, enter the number of all graduating students(certificate or degree) who secured employment after graduation.
F13: July 1, 2010- June 30, 2011
B14: Graduation | D14: American Indian | F14: Non-Indian
D15: M | E15: F | F15: M | G15: F | H15: Total
A16: Apprenticeship/Occupational Program | D16: na | E16: na | F16: na | G16: na | H16: =SUM(D16:G16) -> 0
A17: Diploma | D17: na | E17: na | F17: na | G17: na | H17: =SUM(D17:G17) -> 0
A18: Certificate | D18: na | E18: na | F18: na | G18: na | H18: =SUM(D18:G18) -> 0
A19: Associate Degree | D19: na | E19: na | F19: na | G19: na | H19: =SUM(D19:G19) -> 0
B20: Assoc. graduates admitted to four-year program | D20: na | E20: na | F20: na | G20: na | H20: =SUM(D20:G20) -> 0
B21: Assoc. graduated with a GPA of 3.0 or above | D21: na | E21: na | F21: na | G21: na | H21: =SUM(D21:G21) -> 0
A22: Bachelor's Degree | D22: na | E22: na | F22: na | G22: na | H22: =SUM(D22:G22) -> 0
B23: Bach. graduates admitted to graduate school | D23: na | E23: na | F23: na | G23: na | H23: =SUM(D23:G23) -> 0
B24: Bach. graduated with a GPA of 3.0 or above | D24: na | E24: na | F24: na | G24: na | H24: =SUM(D24:G24) -> 0
A25: Master's Degree | D25: na | E25: na | F25: na | G25: na | H25: =SUM(D25:G25) -> 0
A26: Employed after graduation | D26: na | E26: na | F26: na | G26: na | H26: =SUM(D26:G26) -> 0
A28: Notes:

Sheet 4.2(BT) Major Group Enroll-Grad
A1: Institution | D1: ='1.1 Overall Institution Profile'!B1 -> Oglala Lakota College
A2: Indicator 4: Student Enrollment and Graduation by Major Group
A3: Table 4.2(BT): Major Group Fall Enrollment, Graduation & Post-Graduate / AY 2010-11
B4: Major Group | C4: BT - Building Trades
B5: Please enter the number of students enrolled in this major group for the fall semester.
F6: Fall 2010 (October 15, 2010)
B7: Fall Enrollment (Snapshot) | D7: American Indian | F7: Non-Indian
D8: M | E8: F | F8: M | G8: F | H8: Total
C9: Full Time | D9: 0 | E9: 0 | F9: 0 | G9: 0 | H9: =SUM(D9:G9) -> 0
C10: Part Time | D10: 0 | E10: 0 | F10: 0 | G10: 0 | H10: =SUM(D10:G10) -> 0
C11: Total | D11: =SUM(D9:D10) -> 0 | E11: =SUM(E9:E10) -> 0 | F11: =SUM(F9:F10) -> 0 | G11: =SUM(G9:G10) -> 0 | H11: =SUM(D11:G11) -> 0
B12: Please enter the number of diploma, certificates, and degrees earned in this major group. Also enter the number of students graduating with degrees who earned a GPA of 3.0 or above, and the number who were admitted to a 4 year (Associate degree graduates), or graduate school (Bachelor's degree graduates). Lastly, enter the number of all graduating students(certificate or degree) who secured employment after graduation.
F13: July 1, 2010- June 30, 2011
B14: Graduation | D14: American Indian | F14: Non-Indian
D15: M | E15: F | F15: M | G15: F | H15: Total
A16: Apprenticeship/Occupational Program | D16: na | E16: na | F16: na | G16: na | H16: =SUM(D16:G16) -> 0
A17: Diploma | D17: na | E17: na | F17: na | G17: na | H17: =SUM(D17:G17) -> 0
A18: Certificate | D18: 2 | E18: 1 | F18: 0 | G18: 0 | H18: =SUM(D18:G18) -> 3
A19: Associate Degree | D19: 4 | E19: 0 | F19: 0 | G19: 0 | H19: =SUM(D19:G19) -> 4
B20: Assoc. graduates admitted to four-year program | D20: 0 | E20: 0 | F20: 0 | G20: 0 | H20: =SUM(D20:G20) -> 0
B21: Assoc. graduated with a GPA of 3.0 or above | D21: 2 | E21: 0 | F21: 0 | G21: 0 | H21: =SUM(D21:G21) -> 2
A22: Bachelor's Degree | D22: na | E22: na | F22: na | G22: na | H22: =SUM(D22:G22) -> 0
B23: Bach. graduates admitted to graduate school | D23: na | E23: na | F23: na | G23: na | H23: =SUM(D23:G23) -> 0
B24: Bach. graduated with a GPA of 3.0 or above | D24: na | E24: na | F24: na | G24: na | H24: =SUM(D24:G24) -> 0
A25: Master's Degree | D25: na | E25: na | F25: na | G25: na | H25: =SUM(D25:G25) -> 0
A26: Employed after graduation | D26: m | E26: m | F26: m | G26: m | H26: =SUM(D26:G26) -> 0
A28: Notes:
A29: na = not offered; m = not tracked;

Sheet 4.2(BU) Major Group Enroll-Grad
A1: Institution | D1: ='1.1 Overall Institution Profile'!B1 -> Oglala Lakota College
A2: Indicator 4: Student Enrollment and Graduation by Major Group
A3: Table 4.2(BU): Major Group Fall Enrollment, Graduation & Post-Graduate / AY 2010-11
B4: Major Group | C4: BU - Business
B5: Please enter the number of students enrolled in this major group for the fall semester.
F6: Fall 2010 (October 15, 2010)
B7: Fall Enrollment (Snapshot) | D7: American Indian | F7: Non-Indian
D8: M | E8: F | F8: M | G8: F | H8: Total
C9: Full Time | D9: 77 | E9: 115 | F9: 3 | G9: 0 | H9: =SUM(D9:G9) -> 195
C10: Part Time | D10: 40 | E10: 69 | F10: 2 | G10: 4 | H10: =SUM(D10:G10) -> 115
C11: Total | D11: =SUM(D9:D10) -> 117 | E11: =SUM(E9:E10) -> 184 | F11: =SUM(F9:F10) -> 5 | G11: =SUM(G9:G10) -> 4 | H11: =SUM(D11:G11) -> 310
B12: Please enter the number of diploma, certificates, and degrees earned in this major group. Also enter the number of students graduating with degrees who earned a GPA of 3.0 or above, and the number who were admitted to a 4 year (Associate degree graduates), or graduate school (Bachelor's degree graduates). Lastly, enter the number of all graduating students(certificate or degree) who secured employment after graduation.
F13: July 1, 2010- June 30, 2011
B14: Graduation | D14: American Indian | F14: Non-Indian
D15: M | E15: F | F15: M | G15: F | H15: Total
A16: Apprenticeship/Occupational Program | D16: na | E16: na | F16: na | G16: na | H16: =SUM(D16:G16) -> 0
A17: Diploma | D17: na | E17: na | F17: na | G17: na | H17: =SUM(D17:G17) -> 0
A18: Certificate | D18: 0 | E18: 0 | F18: 0 | G18: 0 | H18: =SUM(D18:G18) -> 0
A19: Associate Degree | D19: 3 | E19: 20 | F19: 0 | G19: 1 | H19: =SUM(D19:G19) -> 24
B20: Assoc. graduates admitted to four-year program | D20: 0 | E20: 0 | F20: 0 | G20: 0 | H20: =SUM(D20:G20) -> 0
B21: Assoc. graduated with a GPA of 3.0 or above | D21: 2 | E21: 12 | F21: 0 | G21: 1 | H21: =SUM(D21:G21) -> 15
A22: Bachelor's Degree | D22: 1 | E22: 8 | F22: 0 | G22: 1 | H22: =SUM(D22:G22) -> 10
B23: Bach. graduates admitted to graduate school | D23: 0 | E23: 0 | F23: 0 | G23: 0 | H23: =SUM(D23:G23) -> 0
B24: Bach. graduated with a GPA of 3.0 or above | D24: 1 | E24: 8 | F24: 0 | G24: 1 | H24: =SUM(D24:G24) -> 10
A25: Master's Degree | D25: na | E25: na | F25: na | G25: na | H25: =SUM(D25:G25) -> 0
A26: Employed after graduation | D26: m | E26: m | F26: m | G26: m | H26: =SUM(D26:G26) -> 0
A28: Notes:
A29: na = not offered; m = not tracked;

Sheet 4.2(CH) Major Group Enroll-Grad
A1: Institution | D1: ='1.1 Overall Institution Profile'!B1 -> Oglala Lakota College
A2: Indicator 4: Student Enrollment and Graduation by Major Group
A3: Table 4.2(CH): Major Group Fall Enrollment, Graduation & Post-Graduate / AY 2010-11
B4: Major Group | C4: CH - Chemistry
B5: Please enter the number of students enrolled in this major group for the fall semester.
F6: Fall 2010 (October 15, 2010)
B7: Fall Enrollment (Snapshot) | D7: American Indian | F7: Non-Indian
D8: M | E8: F | F8: M | G8: F | H8: Total
C9: Full Time | D9: na | E9: na | F9: na | G9: na | H9: =SUM(D9:G9) -> 0
C10: Part Time | D10: na | E10: na | F10: na | G10: na | H10: =SUM(D10:G10) -> 0
C11: Total | D11: =SUM(D9:D10) -> 0 | E11: =SUM(E9:E10) -> 0 | F11: =SUM(F9:F10) -> 0 | G11: =SUM(G9:G10) -> 0 | H11: =SUM(D11:G11) -> 0
B12: Please enter the number of diploma, certificates, and degrees earned in this major group. Also enter the number of students graduating with degrees who earned a GPA of 3.0 or above, and the number who were admitted to a 4 year (Associate degree graduates), or graduate school (Bachelor's degree graduates). Lastly, enter the number of all graduating students(certificate or degree) who secured employment after graduation.
F13: July 1, 2010- June 30, 2011
B14: Graduation | D14: American Indian | F14: Non-Indian
D15: M | E15: F | F15: M | G15: F | H15: Total
A16: Apprenticeship/Occupational Program | D16: na | E16: na | F16: na | G16: na | H16: =SUM(D16:G16) -> 0
A17: Diploma | D17: na | E17: na | F17: na | G17: na | H17: =SUM(D17:G17) -> 0
A18: Certificate | D18: na | E18: na | F18: na | G18: na | H18: =SUM(D18:G18) -> 0
A19: Associate Degree | D19: na | E19: na | F19: na | G19: na | H19: =SUM(D19:G19) -> 0
B20: Assoc. graduates admitted to four-year program | D20: na | E20: na | F20: na | G20: na | H20: =SUM(D20:G20) -> 0
B21: Assoc. graduated with a GPA of 3.0 or above | D21: na | E21: na | F21: na | G21: na | H21: =SUM(D21:G21) -> 0
A22: Bachelor's Degree | D22: na | E22: na | F22: na | G22: na | H22: =SUM(D22:G22) -> 0
B23: Bach. graduates admitted to graduate school | D23: na | E23: na | F23: na | G23: na | H23: =SUM(D23:G23) -> 0
B24: Bach. graduated with a GPA of 3.0 or above | D24: na | E24: na | F24: na | G24: na | H24: =SUM(D24:G24) -> 0
A25: Master's Degree | D25: na | E25: na | F25: na | G25: na | H25: =SUM(D25:G25) -> 0
A26: Employed after graduation | D26: na | E26: na | F26: na | G26: na | H26: =SUM(D26:G26) -> 0
A28: Notes:

Sheet 4.2(CS) Major Group Enroll-Grad
A1: Institution | D1: ='1.1 Overall Institution Profile'!B1 -> Oglala Lakota College
A2: Indicator 4: Student Enrollment and Graduation by Major Group
A3: Table 4.2(CS): Major Group Fall Enrollment, Graduation & Post-Graduate / AY 2010-11
B4: Major Group | C4: CS - Computer Science
B5: Please enter the number of students enrolled in this major group for the fall semester.
F6: Fall 2010 (October 15, 2010)
B7: Fall Enrollment (Snapshot) | D7: American Indian | F7: Non-Indian
D8: M | E8: F | F8: M | G8: F | H8: Total
C9: Full Time | D9: 19 | E9: 21 | F9: 2 | G9: 2 | H9: =SUM(D9:G9) -> 44
C10: Part Time | D10: 12 | E10: 8 | F10: 0 | G10: 0 | H10: =SUM(D10:G10) -> 20
C11: Total | D11: =SUM(D9:D10) -> 31 | E11: =SUM(E9:E10) -> 29 | F11: =SUM(F9:F10) -> 2 | G11: =SUM(G9:G10) -> 2 | H11: =SUM(D11:G11) -> 64
B12: Please enter the number of diploma, certificates, and degrees earned in this major group. Also enter the number of students graduating with degrees who earned a GPA of 3.0 or above, and the number who were admitted to a 4 year (Associate degree graduates), or graduate school (Bachelor's degree graduates). Lastly, enter the number of all graduating students(certificate or degree) who secured employment after graduation.
F13: July 1, 2010- June 30, 2011
B14: Graduation | D14: American Indian | F14: Non-Indian
D15: M | E15: F | F15: M | G15: F | H15: Total
A16: Apprenticeship/Occupational Program | D16: na | E16: na | F16: na | G16: na | H16: =SUM(D16:G16) -> 0
A17: Diploma | D17: na | E17: na | F17: na | G17: na | H17: =SUM(D17:G17) -> 0
A18: Certificate | D18: na | E18: na | F18: na | G18: na | H18: =SUM(D18:G18) -> 0
A19: Associate Degree | D19: 0 | E19: 0 | F19: 0 | G19: 0 | H19: =SUM(D19:G19) -> 0
B20: Assoc. graduates admitted to four-year program | D20: 0 | E20: 0 | F20: 0 | G20: 0 | H20: =SUM(D20:G20) -> 0
B21: Assoc. graduated with a GPA of 3.0 or above | D21: 0 | E21: 0 | F21: 0 | G21: 0 | H21: =SUM(D21:G21) -> 0
A22: Bachelor's Degree | D22: 0 | E22: 0 | F22: 0 | G22: 0 | H22: =SUM(D22:G22) -> 0
B23: Bach. graduates admitted to graduate school | D23: 0 | E23: 0 | F23: 0 | G23: 0 | H23: =SUM(D23:G23) -> 0
B24: Bach. graduated with a GPA of 3.0 or above | D24: 0 | E24: 0 | F24: 0 | G24: 0 | H24: =SUM(D24:G24) -> 0
A25: Master's Degree | D25: na | E25: na | F25: na | G25: na | H25: =SUM(D25:G25) -> 0
A26: Employed after graduation | D26: m | E26: m | F26: m | G26: m | H26: =SUM(D26:G26) -> 0
A28: Notes:
A29: na = not offered; m = not tracked;

Sheet 4.2(CT) Major Group Enroll-Grad
A1: Institution | D1: ='1.1 Overall Institution Profile'!B1 -> Oglala Lakota College
A2: Indicator 4: Student Enrollment and Graduation by Major Group
A3: Table 4.2(CT): Major Group Fall Enrollment, Graduation & Post-Graduate / AY 2010-11
B4: Major Group | C4: CT - Computer Technology
B5: Please enter the number of students enrolled in this major group for the fall semester.
F6: Fall 2010 (October 15, 2010)
B7: Fall Enrollment (Snapshot) | D7: American Indian | F7: Non-Indian
D8: M | E8: F | F8: M | G8: F | H8: Total
C9: Full Time | D9: 0 | E9: 0 | F9: 0 | G9: 0 | H9: =SUM(D9:G9) -> 0
C10: Part Time | D10: 0 | E10: 0 | F10: 0 | G10: 0 | H10: =SUM(D10:G10) -> 0
C11: Total | D11: =SUM(D9:D10) -> 0 | E11: =SUM(E9:E10) -> 0 | F11: =SUM(F9:F10) -> 0 | G11: =SUM(G9:G10) -> 0 | H11: =SUM(D11:G11) -> 0
B12: Please enter the number of diploma, certificates, and degrees earned in this major group. Also enter the number of students graduating with degrees who earned a GPA of 3.0 or above, and the number who were admitted to a 4 year (Associate degree graduates), or graduate school (Bachelor's degree graduates). Lastly, enter the number of all graduating students(certificate or degree) who secured employment after graduation.
F13: July 1, 2010- June 30, 2011
B14: Graduation | D14: American Indian | F14: Non-Indian
D15: M | E15: F | F15: M | G15: F | H15: Total
A16: Apprenticeship/Occupational Program | D16: na | E16: na | F16: na | G16: na | H16: =SUM(D16:G16) -> 0
A17: Diploma | D17: na | E17: na | F17: na | G17: na | H17: =SUM(D17:G17) -> 0
A18: Certificate | D18: na | E18: na | F18: na | G18: na | H18: =SUM(D18:G18) -> 0
A19: Associate Degree | D19: 0 | E19: 0 | F19: 0 | G19: 0 | H19: =SUM(D19:G19) -> 0
B20: Assoc. graduates admitted to four-year program | D20: 0 | E20: 0 | F20: 0 | G20: 0 | H20: =SUM(D20:G20) -> 0
B21: Assoc. graduated with a GPA of 3.0 or above | D21: 0 | E21: 0 | F21: 0 | G21: 0 | H21: =SUM(D21:G21) -> 0
A22: Bachelor's Degree | D22: na | E22: na | F22: na | G22: na | H22: =SUM(D22:G22) -> 0
B23: Bach. graduates admitted to graduate school | D23: na | E23: na | F23: na | G23: na | H23: =SUM(D23:G23) -> 0
B24: Bach. graduated with a GPA of 3.0 or above | D24: na | E24: na | F24: na | G24: na | H24: =SUM(D24:G24) -> 0
A25: Master's Degree | D25: na | E25: na | F25: na | G25: na | H25: =SUM(D25:G25) -> 0
A26: Employed after graduation | D26: na | E26: na | F26: na | G26: na | H26: =SUM(D26:G26) -> 0
A28: program discontinued
A29: na = not offered; m = not tracked;

Sheet 4.2(CL) Major Group Enroll-Grad
A1: Institution | D1: ='1.1 Overall Institution Profile'!B1 -> Oglala Lakota College
A2: Indicator 4: Student Enrollment and Graduation by Major Group
A3: Table 4.2(CL): Major Group Fall Enrollment, Graduation & Post-Graduate / AY 2010-11
B4: Major Group | C4: CL - Corrections/Law Enforcement
B5: Please enter the number of students enrolled in this major group for the fall semester.
F6: Fall 2010 (October 15, 2010)
B7: Fall Enrollment (Snapshot) | D7: American Indian | F7: Non-Indian
D8: M | E8: F | F8: M | G8: F | H8: Total
C9: Full Time | D9: na | E9: na | F9: na | G9: na | H9: =SUM(D9:G9) -> 0
C10: Part Time | D10: na | E10: na | F10: na | G10: na | H10: =SUM(D10:G10) -> 0
C11: Total | D11: =SUM(D9:D10) -> 0 | E11: =SUM(E9:E10) -> 0 | F11: =SUM(F9:F10) -> 0 | G11: =SUM(G9:G10) -> 0 | H11: =SUM(D11:G11) -> 0
B12: Please enter the number of diploma, certificates, and degrees earned in this major group. Also enter the number of students graduating with degrees who earned a GPA of 3.0 or above, and the number who were admitted to a 4 year (Associate degree graduates), or graduate school (Bachelor's degree graduates). Lastly, enter the number of all graduating students(certificate or degree) who secured employment after graduation.
F13: July 1, 2010- June 30, 2011
B14: Graduation | D14: American Indian | F14: Non-Indian
D15: M | E15: F | F15: M | G15: F | H15: Total
A16: Apprenticeship/Occupational Program | D16: na | E16: na | F16: na | G16: na | H16: =SUM(D16:G16) -> 0
A17: Diploma | D17: na | E17: na | F17: na | G17: na | H17: =SUM(D17:G17) -> 0
A18: Certificate | D18: na | E18: na | F18: na | G18: na | H18: =SUM(D18:G18) -> 0
A19: Associate Degree | D19: na | E19: na | F19: na | G19: na | H19: =SUM(D19:G19) -> 0
B20: Assoc. graduates admitted to four-year program | D20: na | E20: na | F20: na | G20: na | H20: =SUM(D20:G20) -> 0
B21: Assoc. graduated with a GPA of 3.0 or above | D21: na | E21: na | F21: na | G21: na | H21: =SUM(D21:G21) -> 0
A22: Bachelor's Degree | D22: na | E22: na | F22: na | G22: na | H22: =SUM(D22:G22) -> 0
B23: Bach. graduates admitted to graduate school | D23: na | E23: na | F23: na | G23: na | H23: =SUM(D23:G23) -> 0
B24: Bach. graduated with a GPA of 3.0 or above | D24: na | E24: na | F24: na | G24: na | H24: =SUM(D24:G24) -> 0
A25: Master's Degree | D25: na | E25: na | F25: na | G25: na | H25: =SUM(D25:G25) -> 0
A26: Employed after graduation | D26: na | E26: na | F26: na | G26: na | H26: =SUM(D26:G26) -> 0
A28: Notes:

Sheet 4.2(EA) Major Group Enroll-Grad
A1: Institution | D1: ='1.1 Overall Institution Profile'!B1 -> Oglala Lakota College
A2: Indicator 4: Student Enrollment and Graduation by Major Group
A3: Table 4.2(EA): Major Group Fall Enrollment, Graduation & Post-Graduate / AY 2010-11
B4: Major Group | C4: EA - Education - Paraprofessional
B5: Please enter the number of students enrolled in this major group for the fall semester.
F6: Fall 2010 (October 15, 2010)
B7: Fall Enrollment (Snapshot) | D7: American Indian | F7: Non-Indian
D8: M | E8: F | F8: M | G8: F | H8: Total
C9: Full Time | D9: 8 | E9: 43 | F9: 0 | G9: 0 | H9: =SUM(D9:G9) -> 51
C10: Part Time | D10: 10 | E10: 54 | F10: 0 | G10: 14 | H10: =SUM(D10:G10) -> 78
C11: Total | D11: =SUM(D9:D10) -> 18 | E11: =SUM(E9:E10) -> 97 | F11: =SUM(F9:F10) -> 0 | G11: =SUM(G9:G10) -> 14 | H11: =SUM(D11:G11) -> 129
B12: Please enter the number of diploma, certificates, and degrees earned in this major group. Also enter the number of students graduating with degrees who earned a GPA of 3.0 or above, and the number who were admitted to a 4 year (Associate degree graduates), or graduate school (Bachelor's degree graduates). Lastly, enter the number of all graduating students(certificate or degree) who secured employment after graduation.
F13: July 1, 2010- June 30, 2011
B14: Graduation | D14: American Indian | F14: Non-Indian
D15: M | E15: F | F15: M | G15: F | H15: Total
A16: Apprenticeship/Occupational Program | D16: na | E16: na | F16: na | G16: na | H16: =SUM(D16:G16) -> 0
A17: Diploma | D17: na | E17: na | F17: na | G17: na | H17: =SUM(D17:G17) -> 0
A18: Certificate | D18: 0 | E18: 0 | F18: 0 | G18: 0 | H18: =SUM(D18:G18) -> 0
A19: Associate Degree | D19: 3 | E19: 29 | F19: 0 | G19: 1 | H19: =SUM(D19:G19) -> 33
B20: Assoc. graduates admitted to four-year program | D20: 0 | E20: 0 | F20: 0 | G20: 0 | H20: =SUM(D20:G20) -> 0
B21: Assoc. graduated with a GPA of 3.0 or above | D21: 2 | E21: 18 | F21: 0 | G21: 1 | H21: =SUM(D21:G21) -> 21
A22: Bachelor's Degree | D22: na | E22: na | F22: na | G22: na | H22: =SUM(D22:G22) -> 0
B23: Bach. graduates admitted to graduate school | D23: na | E23: na | F23: na | G23: na | H23: =SUM(D23:G23) -> 0
B24: Bach. graduated with a GPA of 3.0 or above | D24: na | E24: na | F24: na | G24: na | H24: =SUM(D24:G24) -> 0
A25: Master's Degree | D25: na | E25: na | F25: na | G25: na | H25: =SUM(D25:G25) -> 0
A26: Employed after graduation | D26: m | E26: m | F26: m | G26: m | H26: =SUM(D26:G26) -> 0
A28: Notes:
A29: na = not offered; m = not tracked;

Sheet 4.2(EO) Major Group Enroll-Grad
A1: Institution | D1: ='1.1 Overall Institution Profile'!B1 -> Oglala Lakota College
A2: Indicator 4: Student Enrollment and Graduation by Major Group
A3: Table 4.2(EO): Major Group Fall Enrollment, Graduation & Post-Graduate / AY 2010-11
B4: Major Group | C4: EO - Education - Professional
B5: Please enter the number of students enrolled in this major group for the fall semester.
F6: Fall 2010 (October 15, 2010)
B7: Fall Enrollment (Snapshot) | D7: American Indian | F7: Non-Indian
D8: M | E8: F | F8: M | G8: F | H8: Total
C9: Full Time | D9: 20 | E9: 52 | F9: 1 | G9: 5 | H9: =SUM(D9:G9) -> 78
C10: Part Time | D10: 14 | E10: 38 | F10: 1 | G10: 3 | H10: =SUM(D10:G10) -> 56
C11: Total | D11: =SUM(D9:D10) -> 34 | E11: =SUM(E9:E10) -> 90 | F11: =SUM(F9:F10) -> 2 | G11: =SUM(G9:G10) -> 8 | H11: =SUM(D11:G11) -> 134
B12: Please enter the number of diploma, certificates, and degrees earned in this major group. Also enter the number of students graduating with degrees who earned a GPA of 3.0 or above, and the number who were admitted to a 4 year (Associate degree graduates), or graduate school (Bachelor's degree graduates). Lastly, enter the number of all graduating students(certificate or degree) who secured employment after graduation.
F13: July 1, 2010- June 30, 2011
B14: Graduation | D14: American Indian | F14: Non-Indian
D15: M | E15: F | F15: M | G15: F | H15: Total
A16: Apprenticeship/Occupational Program | D16: na | E16: na | F16: na | G16: na | H16: =SUM(D16:G16) -> 0
A17: Diploma | D17: na | E17: na | F17: na | G17: na | H17: =SUM(D17:G17) -> 0
A18: Certificate | D18: 0 | E18: 0 | F18: 0 | G18: 0 | H18: =SUM(D18:G18) -> 0
A19: Associate Degree | D19: na | E19: na | F19: na | G19: na | H19: =SUM(D19:G19) -> 0
B20: Assoc. graduates admitted to four-year program | D20: na | E20: na | F20: na | G20: na | H20: =SUM(D20:G20) -> 0
B21: Assoc. graduated with a GPA of 3.0 or above | D21: na | E21: na | F21: na | G21: na | H21: =SUM(D21:G21) -> 0
A22: Bachelor's Degree | D22: 0 | E22: 9 | F22: 1 | G22: 2 | H22: =SUM(D22:G22) -> 12
B23: Bach. graduates admitted to graduate school | D23: 0 | E23: 0 | F23: 0 | G23: 0 | H23: =SUM(D23:G23) -> 0
B24: Bach. graduated with a GPA of 3.0 or above | D24: 0 | E24: 8 | F24: 1 | G24: 2 | H24: =SUM(D24:G24) -> 11
A25: Master's Degree | D25: na | E25: na | F25: na | G25: na | H25: =SUM(D25:G25) -> 0
A26: Employed after graduation | D26: m | E26: m | F26: m | G26: m | H26: =SUM(D26:G26) -> 0
A28: Notes:
A29: na = not offered; m = not tracked;

Sheet 4.2(EN) Major Group Enroll-Grad
A1: Institution | D1: ='1.1 Overall Institution Profile'!B1 -> Oglala Lakota College
A2: Indicator 4: Student Enrollment and Graduation by Major Group
A3: Table 4.2(EN): Major Group Fall Enrollment, Graduation & Post-Graduate / AY 2010-11
B4: Major Group | C4: EN - English
B5: Please enter the number of students enrolled in this major group for the fall semester.
F6: Fall 2010 (October 15, 2010)
B7: Fall Enrollment (Snapshot) | D7: American Indian | F7: Non-Indian
D8: M | E8: F | F8: M | G8: F | H8: Total
C9: Full Time | D9: na | E9: na | F9: na | G9: na | H9: =SUM(D9:G9) -> 0
C10: Part Time | D10: na | E10: na | F10: na | G10: na | H10: =SUM(D10:G10) -> 0
C11: Total | D11: =SUM(D9:D10) -> 0 | E11: =SUM(E9:E10) -> 0 | F11: =SUM(F9:F10) -> 0 | G11: =SUM(G9:G10) -> 0 | H11: =SUM(D11:G11) -> 0
B12: Please enter the number of diploma, certificates, and degrees earned in this major group. Also enter the number of students graduating with degrees who earned a GPA of 3.0 or above, and the number who were admitted to a 4 year (Associate degree graduates), or graduate school (Bachelor's degree graduates). Lastly, enter the number of all graduating students(certificate or degree) who secured employment after graduation.
F13: July 1, 2010- June 30, 2011
B14: Graduation | D14: American Indian | F14: Non-Indian
D15: M | E15: F | F15: M | G15: F | H15: Total
A16: Apprenticeship/Occupational Program | D16: na | E16: na | F16: na | G16: na | H16: =SUM(D16:G16) -> 0
A17: Diploma | D17: na | E17: na | F17: na | G17: na | H17: =SUM(D17:G17) -> 0
A18: Certificate | D18: na | E18: na | F18: na | G18: na | H18: =SUM(D18:G18) -> 0
A19: Associate Degree | D19: na | E19: na | F19: na | G19: na | H19: =SUM(D19:G19) -> 0
B20: Assoc. graduates admitted to four-year program | D20: na | E20: na | F20: na | G20: na | H20: =SUM(D20:G20) -> 0
B21: Assoc. graduated with a GPA of 3.0 or above | D21: na | E21: na | F21: na | G21: na | H21: =SUM(D21:G21) -> 0
A22: Bachelor's Degree | D22: na | E22: na | F22: na | G22: na | H22: =SUM(D22:G22) -> 0
B23: Bach. graduates admitted to graduate school | D23: na | E23: na | F23: na | G23: na | H23: =SUM(D23:G23) -> 0
B24: Bach. graduated with a GPA of 3.0 or above | D24: na | E24: na | F24: na | G24: na | H24: =SUM(D24:G24) -> 0
A25: Master's Degree | D25: na | E25: na | F25: na | G25: na | H25: =SUM(D25:G25) -> 0
A26: Employed after graduation | D26: na | E26: na | F26: na | G26: na | H26: =SUM(D26:G26) -> 0
A28: Notes:

Sheet 4.2(ES) Major Group Enroll-Grad
A1: Institution | D1: ='1.1 Overall Institution Profile'!B1 -> Oglala Lakota College
A2: Indicator 4: Student Enrollment and Graduation by Major Group
A3: Table 4.2(ES): Major Group Fall Enrollment, Graduation & Post-Graduate / AY 2010-11
B4: Major Group | C4: ES - Environmental Science/Natural Resources
B5: Please enter the number of students enrolled in this major group for the fall semester.
F6: Fall 2010 (October 15, 2010)
B7: Fall Enrollment (Snapshot) | D7: American Indian | F7: Non-Indian
D8: M | E8: F | F8: M | G8: F | H8: Total
C9: Full Time | D9: 20 | E9: 10 | F9: 1 | G9: 3 | H9: =SUM(D9:G9) -> 34
C10: Part Time | D10: 9 | E10: 10 | F10: 4 | G10: 1 | H10: =SUM(D10:G10) -> 24
C11: Total | D11: =SUM(D9:D10) -> 29 | E11: =SUM(E9:E10) -> 20 | F11: =SUM(F9:F10) -> 5 | G11: =SUM(G9:G10) -> 4 | H11: =SUM(D11:G11) -> 58
B12: Please enter the number of diploma, certificates, and degrees earned in this major group. Also enter the number of students graduating with degrees who earned a GPA of 3.0 or above, and the number who were admitted to a 4 year (Associate degree graduates), or graduate school (Bachelor's degree graduates). Lastly, enter the number of all graduating students(certificate or degree) who secured employment after graduation.
F13: July 1, 2010- June 30, 2011
B14: Graduation | D14: American Indian | F14: Non-Indian
D15: M | E15: F | F15: M | G15: F | H15: Total
A16: Apprenticeship/Occupational Program | D16: na | E16: na | F16: na | G16: na | H16: =SUM(D16:G16) -> 0
A17: Diploma | D17: na | E17: na | F17: na | G17: na | H17: =SUM(D17:G17) -> 0
A18: Certificate | D18: na | E18: na | F18: na | G18: na | H18: =SUM(D18:G18) -> 0
A19: Associate Degree | D19: 0 | E19: 0 | F19: 0 | G19: 1 | H19: =SUM(D19:G19) -> 1
B20: Assoc. graduates admitted to four-year program | D20: 0 | E20: 0 | F20: 0 | G20: 0 | H20: =SUM(D20:G20) -> 0
B21: Assoc. graduated with a GPA of 3.0 or above | D21: 0 | E21: 0 | F21: 0 | G21: 1 | H21: =SUM(D21:G21) -> 1
A22: Bachelor's Degree | D22: 2 | E22: 0 | F22: 0 | G22: 0 | H22: =SUM(D22:G22) -> 2
B23: Bach. graduates admitted to graduate school | D23: 0 | E23: 0 | F23: 0 | G23: 0 | H23: =SUM(D23:G23) -> 0
B24: Bach. graduated with a GPA of 3.0 or above | D24: 1 | E24: 0 | F24: 0 | G24: 0 | H24: =SUM(D24:G24) -> 1
A25: Master's Degree | D25: na | E25: na | F25: na | G25: na | H25: =SUM(D25:G25) -> 0
A26: Employed after graduation | D26: m | E26: m | F26: m | G26: m | H26: =SUM(D26:G26) -> 0
A28: Notes:
A29: na = not offered; m = not tracked;

Sheet 4.2(GE) Major Group Enroll-Grad
A1: Institution | D1: ='1.1 Overall Institution Profile'!B1 -> Oglala Lakota College
A2: Indicator 4: Student Enrollment and Graduation by Major Group
A3: Table 4.2(GE): Major Group Fall Enrollment, Graduation & Post-Graduate / AY 2010-11
B4: Major Group | C4: GE - Geography
B5: Please enter the number of students enrolled in this major group for the fall semester.
F6: Fall 2010 (October 15, 2010)
B7: Fall Enrollment (Snapshot) | D7: American Indian | F7: Non-Indian
D8: M | E8: F | F8: M | G8: F | H8: Total
C9: Full Time | D9: na | E9: na | F9: na | G9: na | H9: =SUM(D9:G9) -> 0
C10: Part Time | D10: na | E10: na | F10: na | G10: na | H10: =SUM(D10:G10) -> 0
C11: Total | D11: =SUM(D9:D10) -> 0 | E11: =SUM(E9:E10) -> 0 | F11: =SUM(F9:F10) -> 0 | G11: =SUM(G9:G10) -> 0 | H11: =SUM(D11:G11) -> 0
B12: Please enter the number of diploma, certificates, and degrees earned in this major group. Also enter the number of students graduating with degrees who earned a GPA of 3.0 or above, and the number who were admitted to a 4 year (Associate degree graduates), or graduate school (Bachelor's degree graduates). Lastly, enter the number of all graduating students(certificate or degree) who secured employment after graduation.
F13: July 1, 2010- June 30, 2011
B14: Graduation | D14: American Indian | F14: Non-Indian
D15: M | E15: F | F15: M | G15: F | H15: Total
A16: Apprenticeship/Occupational Program | D16: na | E16: na | F16: na | G16: na | H16: =SUM(D16:G16) -> 0
A17: Diploma | D17: na | E17: na | F17: na | G17: na | H17: =SUM(D17:G17) -> 0
A18: Certificate | D18: na | E18: na | F18: na | G18: na | H18: =SUM(D18:G18) -> 0
A19: Associate Degree | D19: na | E19: na | F19: na | G19: na | H19: =SUM(D19:G19) -> 0
B20: Assoc. graduates admitted to four-year program | D20: na | E20: na | F20: na | G20: na | H20: =SUM(D20:G20) -> 0
B21: Assoc. graduated with a GPA of 3.0 or above | D21: na | E21: na | F21: na | G21: na | H21: =SUM(D21:G21) -> 0
A22: Bachelor's Degree | D22: na | E22: na | F22: na | G22: na | H22: =SUM(D22:G22) -> 0
B23: Bach. graduates admitted to graduate school | D23: na | E23: na | F23: na | G23: na | H23: =SUM(D23:G23) -> 0
B24: Bach. graduated with a GPA of 3.0 or above | D24: na | E24: na | F24: na | G24: na | H24: =SUM(D24:G24) -> 0
A25: Master's Degree | D25: na | E25: na | F25: na | G25: na | H25: =SUM(D25:G25) -> 0
A26: Employed after graduation | D26: na | E26: na | F26: na | G26: na | H26: =SUM(D26:G26) -> 0
A28: Notes:

Sheet 4.2(HC) Major Group Enroll-Grad
A1: Institution | D1: ='1.1 Overall Institution Profile'!B1 -> Oglala Lakota College
A2: Indicator 4: Student Enrollment and Graduation by Major Group
A3: Table 4.2(HC): Major Group Fall Enrollment, Graduation & Post-Graduate / AY 2010-11
B4: Major Group | C4: HC - Health Careers
B5: Please enter the number of students enrolled in this major group for the fall semester.
F6: Fall 2010 (October 15, 2010)
B7: Fall Enrollment (Snapshot) | D7: American Indian | F7: Non-Indian
D8: M | E8: F | F8: M | G8: F | H8: Total
C9: Full Time | D9: 2 | E9: 2 | F9: 0 | G9: 0 | H9: =SUM(D9:G9) -> 4
C10: Part Time | D10: 0 | E10: 1 | F10: 0 | G10: 0 | H10: =SUM(D10:G10) -> 1
C11: Total | D11: =SUM(D9:D10) -> 2 | E11: =SUM(E9:E10) -> 3 | F11: =SUM(F9:F10) -> 0 | G11: =SUM(G9:G10) -> 0 | H11: =SUM(D11:G11) -> 5
B12: Please enter the number of diploma, certificates, and degrees earned in this major group. Also enter the number of students graduating with degrees who earned a GPA of 3.0 or above, and the number who were admitted to a 4 year (Associate degree graduates), or graduate school (Bachelor's degree graduates). Lastly, enter the number of all graduating students(certificate or degree) who secured employment after graduation.
F13: July 1, 2010- June 30, 2011
B14: Graduation | D14: American Indian | F14: Non-Indian
D15: M | E15: F | F15: M | G15: F | H15: Total
A16: Apprenticeship/Occupational Program | D16: na | E16: na | F16: na | G16: na | H16: =SUM(D16:G16) -> 0
A17: Diploma | D17: na | E17: na | F17: na | G17: na | H17: =SUM(D17:G17) -> 0
A18: Certificate | D18: na | E18: na | F18: na | G18: na | H18: =SUM(D18:G18) -> 0
A19: Associate Degree | D19: 0 | E19: 0 | F19: 0 | G19: 0 | H19: =SUM(D19:G19) -> 0
B20: Assoc. graduates admitted to four-year program | D20: 0 | E20: 0 | F20: 0 | G20: 0 | H20: =SUM(D20:G20) -> 0
B21: Assoc. graduated with a GPA of 3.0 or above | D21: 0 | E21: 0 | F21: 0 | G21: 0 | H21: =SUM(D21:G21) -> 0
A22: Bachelor's Degree | D22: na | E22: na | F22: na | G22: na | H22: =SUM(D22:G22) -> 0
B23: Bach. graduates admitted to graduate school | D23: na | E23: na | F23: na | G23: na | H23: =SUM(D23:G23) -> 0
B24: Bach. graduated with a GPA of 3.0 or above | D24: na | E24: na | F24: na | G24: na | H24: =SUM(D24:G24) -> 0
A25: Master's Degree | D25: na | E25: na | F25: na | G25: na | H25: =SUM(D25:G25) -> 0
A26: Employed after graduation | D26: na | E26: na | F26: na | G26: na | H26: =SUM(D26:G26) -> 0
A28: Notes:
A29: Program discontinued

Sheet 4.2(HI) Major Group Enroll-Grad
A1: Institution | D1: ='1.1 Overall Institution Profile'!B1 -> Oglala Lakota College
A2: Indicator 4: Student Enrollment and Graduation by Major Group
A3: Table 4.2(HI): Major Group Fall Enrollment, Graduation & Post-Graduate / AY 2010-11
B4: Major Group | C4: HI - Hospitality Industry
B5: Please enter the number of students enrolled in this major group for the fall semester.
F6: Fall 2010 (October 15, 2010)
B7: Fall Enrollment (Snapshot) | D7: American Indian | F7: Non-Indian
D8: M | E8: F | F8: M | G8: F | H8: Total
C9: Full Time | D9: 0 | E9: 4 | F9: 0 | G9: 0 | H9: =SUM(D9:G9) -> 4
C10: Part Time | D10: 0 | E10: 1 | F10: 0 | G10: 0 | H10: =SUM(D10:G10) -> 1
C11: Total | D11: =SUM(D9:D10) -> 0 | E11: =SUM(E9:E10) -> 5 | F11: =SUM(F9:F10) -> 0 | G11: =SUM(G9:G10) -> 0 | H11: =SUM(D11:G11) -> 5
B12: Please enter the number of diploma, certificates, and degrees earned in this major group. Also enter the number of students graduating with degrees who earned a GPA of 3.0 or above, and the number who were admitted to a 4 year (Associate degree graduates), or graduate school (Bachelor's degree graduates). Lastly, enter the number of all graduating students(certificate or degree) who secured employment after graduation.
F13: July 1, 2010- June 30, 2011
B14: Graduation | D14: American Indian | F14: Non-Indian
D15: M | E15: F | F15: M | G15: F | H15: Total
A16: Apprenticeship/Occupational Program | D16: na | E16: na | F16: na | G16: na | H16: =SUM(D16:G16) -> 0
A17: Diploma | D17: na | E17: na | F17: na | G17: na | H17: =SUM(D17:G17) -> 0
A18: Certificate | D18: 0 | E18: 1 | F18: 0 | G18: 0 | H18: =SUM(D18:G18) -> 1
A19: Associate Degree | D19: 0 | E19: 2 | F19: 0 | G19: 0 | H19: =SUM(D19:G19) -> 2
B20: Assoc. graduates admitted to four-year program | D20: 0 | E20: 0 | F20: 0 | G20: 0 | H20: =SUM(D20:G20) -> 0
B21: Assoc. graduated with a GPA of 3.0 or above | D21: 0 | E21: 2 | F21: 0 | G21: 0 | H21: =SUM(D21:G21) -> 2
A22: Bachelor's Degree | D22: na | E22: na | F22: na | G22: na | H22: =SUM(D22:G22) -> 0
B23: Bach. graduates admitted to graduate school | D23: na | E23: na | F23: na | G23: na | H23: =SUM(D23:G23) -> 0
B24: Bach. graduated with a GPA of 3.0 or above | D24: na | E24: na | F24: na | G24: na | H24: =SUM(D24:G24) -> 0
A25: Master's Degree | D25: na | E25: na | F25: na | G25: na | H25: =SUM(D25:G25) -> 0
A26: Employed after graduation | D26: m | E26: m | F26: m | G26: m | H26: =SUM(D26:G26) -> 0
A28: Notes:
A29: na = not offered; m = not tracked;

Sheet 4.2(HS) Major Group Enroll-Grad
A1: Institution | D1: ='1.1 Overall Institution Profile'!B1 -> Oglala Lakota College
A2: Indicator 4: Student Enrollment and Graduation by Major Group
A3: Table 4.2(HS): Major Group Fall Enrollment, Graduation & Post-Graduate / AY 2010-11
B4: Major Group | C4: HS - Human Services
B5: Please enter the number of students enrolled in this major group for the fall semester.
F6: Fall 2010 (October 15, 2010)
B7: Fall Enrollment (Snapshot) | D7: American Indian | F7: Non-Indian
D8: M | E8: F | F8: M | G8: F | H8: Total
C9: Full Time | D9: 22 | E9: 46 | F9: 6 | G9: 4 | H9: =SUM(D9:G9) -> 78
C10: Part Time | D10: 8 | E10: 37 | F10: 2 | G10: 6 | H10: =SUM(D10:G10) -> 53
C11: Total | D11: =SUM(D9:D10) -> 30 | E11: =SUM(E9:E10) -> 83 | F11: =SUM(F9:F10) -> 8 | G11: =SUM(G9:G10) -> 10 | H11: =SUM(D11:G11) -> 131
B12: Please enter the number of diploma, certificates, and degrees earned in this major group. Also enter the number of students graduating with degrees who earned a GPA of 3.0 or above, and the number who were admitted to a 4 year (Associate degree graduates), or graduate school (Bachelor's degree graduates). Lastly, enter the number of all graduating students(certificate or degree) who secured employment after graduation.
F13: July 1, 2010- June 30, 2011
B14: Graduation | D14: American Indian | F14: Non-Indian
D15: M | E15: F | F15: M | G15: F | H15: Total
A16: Apprenticeship/Occupational Program | D16: na | E16: na | F16: na | G16: na | H16: =SUM(D16:G16) -> 0
A17: Diploma | D17: na | E17: na | F17: na | G17: na | H17: =SUM(D17:G17) -> 0
A18: Certificate | D18: na | E18: na | F18: na | G18: na | H18: =SUM(D18:G18) -> 0
A19: Associate Degree | D19: 1 | E19: 1 | F19: 0 | G19: 0 | H19: =SUM(D19:G19) -> 2
B20: Assoc. graduates admitted to four-year program | D20: 0 | E20: 0 | F20: 0 | G20: 0 | H20: =SUM(D20:G20) -> 0
B21: Assoc. graduated with a GPA of 3.0 or above | D21: 1 | E21: 0 | F21: 0 | G21: 0 | H21: =SUM(D21:G21) -> 1
A22: Bachelor's Degree | D22: 1 | E22: 5 | F22: 2 | G22: 0 | H22: =SUM(D22:G22) -> 8
B23: Bach. graduates admitted to graduate school | D23: 0 | E23: 0 | F23: 0 | G23: 0 | H23: =SUM(D23:G23) -> 0
B24: Bach. graduated with a GPA of 3.0 or above | D24: 1 | E24: 3 | F24: 1 | G24: 0 | H24: =SUM(D24:G24) -> 5
A25: Master's Degree | D25: na | E25: na | F25: na | G25: na | H25: =SUM(D25:G25) -> 0
A26: Employed after graduation | D26: m | E26: m | F26: m | G26: m | H26: =SUM(D26:G26) -> 0
A28: Notes:
A29: na = not offered; m = not tracked;

Sheet 4.2(IP) Major Group Enroll-Grad
A1: Institution | D1: ='1.1 Overall Institution Profile'!B1 -> Oglala Lakota College
A2: Indicator 4: Student Enrollment and Graduation by Major Group
A3: Table 4.2(IP): Major Group Fall Enrollment, Graduation & Post-Graduate / AY 2010-11
B4: Major Group | C4: IP - Individualized Program
B5: Please enter the number of students enrolled in this major group for the fall semester.
F6: Fall 2010 (October 15, 2010)
B7: Fall Enrollment (Snapshot) | D7: American Indian | F7: Non-Indian
D8: M | E8: F | F8: M | G8: F | H8: Total
C9: Full Time | D9: na | E9: na | F9: na | G9: na | H9: =SUM(D9:G9) -> 0
C10: Part Time | D10: na | E10: na | F10: na | G10: na | H10: =SUM(D10:G10) -> 0
C11: Total | D11: =SUM(D9:D10) -> 0 | E11: =SUM(E9:E10) -> 0 | F11: =SUM(F9:F10) -> 0 | G11: =SUM(G9:G10) -> 0 | H11: =SUM(D11:G11) -> 0
B12: Please enter the number of diploma, certificates, and degrees earned in this major group. Also enter the number of students graduating with degrees who earned a GPA of 3.0 or above, and the number who were admitted to a 4 year (Associate degree graduates), or graduate school (Bachelor's degree graduates). Lastly, enter the number of all graduating students(certificate or degree) who secured employment after graduation.
F13: July 1, 2010- June 30, 2011
B14: Graduation | D14: American Indian | F14: Non-Indian
D15: M | E15: F | F15: M | G15: F | H15: Total
A16: Apprenticeship/Occupational Program | D16: na | E16: na | F16: na | G16: na | H16: =SUM(D16:G16) -> 0
A17: Diploma | D17: na | E17: na | F17: na | G17: na | H17: =SUM(D17:G17) -> 0
A18: Certificate | D18: na | E18: na | F18: na | G18: na | H18: =SUM(D18:G18) -> 0
A19: Associate Degree | D19: na | E19: na | F19: na | G19: na | H19: =SUM(D19:G19) -> 0
B20: Assoc. graduates admitted to four-year program | D20: na | E20: na | F20: na | G20: na | H20: =SUM(D20:G20) -> 0
B21: Assoc. graduated with a GPA of 3.0 or above | D21: na | E21: na | F21: na | G21: na | H21: =SUM(D21:G21) -> 0
A22: Bachelor's Degree | D22: na | E22: na | F22: na | G22: na | H22: =SUM(D22:G22) -> 0
B23: Bach. graduates admitted to graduate school | D23: na | E23: na | F23: na | G23: na | H23: =SUM(D23:G23) -> 0
B24: Bach. graduated with a GPA of 3.0 or above | D24: na | E24: na | F24: na | G24: na | H24: =SUM(D24:G24) -> 0
A25: Master's Degree | D25: na | E25: na | F25: na | G25: na | H25: =SUM(D25:G25) -> 0
A26: Employed after graduation | D26: na | E26: na | F26: na | G26: na | H26: =SUM(D26:G26) -> 0
A28: Notes:

Sheet 4.2(LA) Major Group Enroll-Grad
A1: Institution | D1: ='1.1 Overall Institution Profile'!B1 -> Oglala Lakota College
A2: Indicator 4: Student Enrollment and Graduation by Major Group
A3: Table 4.2(LA): Major Group Fall Enrollment, Graduation & Post-Graduate / AY 2010-11
B4: Major Group | C4: LA - Liberal Arts
B5: Please enter the number of students enrolled in this major group for the fall semester.
F6: Fall 2010 (October 15, 2010)
B7: Fall Enrollment (Snapshot) | D7: American Indian | F7: Non-Indian
D8: M | E8: F | F8: M | G8: F | H8: Total
C9: Full Time | D9: 0 | E9: 2 | F9: 0 | G9: 0 | H9: =SUM(D9:G9) -> 2
C10: Part Time | D10: 0 | E10: 1 | F10: 0 | G10: 0 | H10: =SUM(D10:G10) -> 1
C11: Total | D11: =SUM(D9:D10) -> 0 | E11: =SUM(E9:E10) -> 3 | F11: =SUM(F9:F10) -> 0 | G11: =SUM(G9:G10) -> 0 | H11: =SUM(D11:G11) -> 3
B12: Please enter the number of diploma, certificates, and degrees earned in this major group. Also enter the number of students graduating with degrees who earned a GPA of 3.0 or above, and the number who were admitted to a 4 year (Associate degree graduates), or graduate school (Bachelor's degree graduates). Lastly, enter the number of all graduating students(certificate or degree) who secured employment after graduation.
F13: July 1, 2010- June 30, 2011
B14: Graduation | D14: American Indian | F14: Non-Indian
D15: M | E15: F | F15: M | G15: F | H15: Total
A16: Apprenticeship/Occupational Program | D16: na | E16: na | F16: na | G16: na | H16: =SUM(D16:G16) -> 0
A17: Diploma | D17: na | E17: na | F17: na | G17: na | H17: =SUM(D17:G17) -> 0
A18: Certificate | D18: na | E18: na | F18: na | G18: na | H18: =SUM(D18:G18) -> 0
A19: Associate Degree | D19: 3 | E19: 19 | F19: 0 | G19: 1 | H19: =SUM(D19:G19) -> 23
B20: Assoc. graduates admitted to four-year program | D20: 0 | E20: 0 | F20: 0 | G20: 0 | H20: =SUM(D20:G20) -> 0
B21: Assoc. graduated with a GPA of 3.0 or above | D21: 2 | E21: 8 | F21: 0 | G21: 1 | H21: =SUM(D21:G21) -> 11
A22: Bachelor's Degree | D22: 0 | E22: 1 | F22: 0 | G22: 0 | H22: =SUM(D22:G22) -> 1
B23: Bach. graduates admitted to graduate school | D23: 0 | E23: 0 | F23: 0 | G23: 0 | H23: =SUM(D23:G23) -> 0
B24: Bach. graduated with a GPA of 3.0 or above | D24: 0 | E24: 1 | F24: 0 | G24: 0 | H24: =SUM(D24:G24) -> 1
A25: Master's Degree | D25: na | E25: na | F25: na | G25: na | H25: =SUM(D25:G25) -> 0
A26: Employed after graduation | D26: m | E26: m | F26: m | G26: m | H26: =SUM(D26:G26) -> 0
A28: Notes:
A29: na = not offered; m = not tracked;

Sheet 4.2(LS) Major Group Enroll-Grad
A1: Institution | D1: ='1.1 Overall Institution Profile'!B1 -> Oglala Lakota College
A2: Indicator 4: Student Enrollment and Graduation by Major Group
A3: Table 4.2(LS): Major Group Fall Enrollment, Graduation & Post-Graduate / AY 2010-11
B4: Major Group | C4: LS - Life Sciences
B5: Please enter the number of students enrolled in this major group for the fall semester.
F6: Fall 2010 (October 15, 2010)
B7: Fall Enrollment (Snapshot) | D7: American Indian | F7: Non-Indian
D8: M | E8: F | F8: M | G8: F | H8: Total
C9: Full Time | D9: 3 | E9: 1 | F9: 0 | G9: 0 | H9: =SUM(D9:G9) -> 4
C10: Part Time | D10: 1 | E10: 1 | F10: 0 | G10: 0 | H10: =SUM(D10:G10) -> 2
C11: Total | D11: =SUM(D9:D10) -> 4 | E11: =SUM(E9:E10) -> 2 | F11: =SUM(F9:F10) -> 0 | G11: =SUM(G9:G10) -> 0 | H11: =SUM(D11:G11) -> 6
B12: Please enter the number of diploma, certificates, and degrees earned in this major group. Also enter the number of students graduating with degrees who earned a GPA of 3.0 or above, and the number who were admitted to a 4 year (Associate degree graduates), or graduate school (Bachelor's degree graduates). Lastly, enter the number of all graduating students(certificate or degree) who secured employment after graduation.
F13: July 1, 2010- June 30, 2011
B14: Graduation | D14: American Indian | F14: Non-Indian
D15: M | E15: F | F15: M | G15: F | H15: Total
A16: Apprenticeship/Occupational Program | D16: na | E16: na | F16: na | G16: na | H16: =SUM(D16:G16) -> 0
A17: Diploma | D17: na | E17: na | F17: na | G17: na | H17: =SUM(D17:G17) -> 0
A18: Certificate | D18: na | E18: na | F18: na | G18: na | H18: =SUM(D18:G18) -> 0
A19: Associate Degree | D19: 0 | E19: 0 | F19: 0 | G19: 0 | H19: =SUM(D19:G19) -> 0
B20: Assoc. graduates admitted to four-year program | D20: 0 | E20: 0 | F20: 0 | G20: 0 | H20: =SUM(D20:G20) -> 0
B21: Assoc. graduated with a GPA of 3.0 or above | D21: 0 | E21: 0 | F21: 0 | G21: 0 | H21: =SUM(D21:G21) -> 0
A22: Bachelor's Degree | D22: na | E22: na | F22: na | G22: na | H22: =SUM(D22:G22) -> 0
B23: Bach. graduates admitted to graduate school | D23: na | E23: na | F23: na | G23: na | H23: =SUM(D23:G23) -> 0
B24: Bach. graduated with a GPA of 3.0 or above | D24: na | E24: na | F24: na | G24: na | H24: =SUM(D24:G24) -> 0
A25: Master's Degree | D25: na | E25: na | F25: na | G25: na | H25: =SUM(D25:G25) -> 0
A26: Employed after graduation | D26: m | E26: m | F26: m | G26: m | H26: =SUM(D26:G26) -> 0
A28: Notes:
A29: na = not offered; m = not tracked;

Sheet 4.2(MA) Major Group Enroll-Grad
A1: Institution | D1: ='1.1 Overall Institution Profile'!B1 -> Oglala Lakota College
A2: Indicator 4: Student Enrollment and Graduation by Major Group
A3: Table 4.2(MA): Major Group Fall Enrollment, Graduation & Post-Graduate / AY 2010-11
B4: Major Group | C4: MA - Mathematics
B5: Please enter the number of students enrolled in this major group for the fall semester.
F6: Fall 2010 (October 15, 2010)
B7: Fall Enrollment (Snapshot) | D7: American Indian | F7: Non-Indian
D8: M | E8: F | F8: M | G8: F | H8: Total
C9: Full Time | D9: na | E9: na | F9: na | G9: na | H9: =SUM(D9:G9) -> 0
C10: Part Time | D10: na | E10: na | F10: na | G10: na | H10: =SUM(D10:G10) -> 0
C11: Total | D11: =SUM(D9:D10) -> 0 | E11: =SUM(E9:E10) -> 0 | F11: =SUM(F9:F10) -> 0 | G11: =SUM(G9:G10) -> 0 | H11: =SUM(D11:G11) -> 0
B12: Please enter the number of diploma, certificates, and degrees earned in this major group. Also enter the number of students graduating with degrees who earned a GPA of 3.0 or above, and the number who were admitted to a 4 year (Associate degree graduates), or graduate school (Bachelor's degree graduates). Lastly, enter the number of all graduating students(certificate or degree) who secured employment after graduation.
F13: July 1, 2010- June 30, 2011
B14: Graduation | D14: American Indian | F14: Non-Indian
D15: M | E15: F | F15: M | G15: F | H15: Total
A16: Apprenticeship/Occupational Program | D16: na | E16: na | F16: na | G16: na | H16: =SUM(D16:G16) -> 0
A17: Diploma | D17: na | E17: na | F17: na | G17: na | H17: =SUM(D17:G17) -> 0
A18: Certificate | D18: na | E18: na | F18: na | G18: na | H18: =SUM(D18:G18) -> 0
A19: Associate Degree | D19: na | E19: na | F19: na | G19: na | H19: =SUM(D19:G19) -> 0
B20: Assoc. graduates admitted to four-year program | D20: na | E20: na | F20: na | G20: na | H20: =SUM(D20:G20) -> 0
B21: Assoc. graduated with a GPA of 3.0 or above | D21: na | E21: na | F21: na | G21: na | H21: =SUM(D21:G21) -> 0
A22: Bachelor's Degree | D22: na | E22: na | F22: na | G22: na | H22: =SUM(D22:G22) -> 0
B23: Bach. graduates admitted to graduate school | D23: na | E23: na | F23: na | G23: na | H23: =SUM(D23:G23) -> 0
B24: Bach. graduated with a GPA of 3.0 or above | D24: na | E24: na | F24: na | G24: na | H24: =SUM(D24:G24) -> 0
A25: Master's Degree | D25: na | E25: na | F25: na | G25: na | H25: =SUM(D25:G25) -> 0
A26: Employed after graduation | D26: na | E26: na | F26: na | G26: na | H26: =SUM(D26:G26) -> 0
A28: Notes:

Sheet 4.2(NS) Major Group Enroll-Grad
A1: Institution | D1: ='1.1 Overall Institution Profile'!B1 -> Oglala Lakota College
A2: Indicator 4: Student Enrollment and Graduation by Major Group
A3: Table 4.2(NS): Major Group Fall Enrollment, Graduation & Post-Graduate / AY 2010-11
B4: Major Group | C4: NS - Natural Science
B5: Please enter the number of students enrolled in this major group for the fall semester.
F6: Fall 2010 (October 15, 2010)
B7: Fall Enrollment (Snapshot) | D7: American Indian | F7: Non-Indian
D8: M | E8: F | F8: M | G8: F | H8: Total
C9: Full Time | D9: na | E9: na | F9: na | G9: na | H9: =SUM(D9:G9) -> 0
C10: Part Time | D10: na | E10: na | F10: na | G10: na | H10: =SUM(D10:G10) -> 0
C11: Total | D11: =SUM(D9:D10) -> 0 | E11: =SUM(E9:E10) -> 0 | F11: =SUM(F9:F10) -> 0 | G11: =SUM(G9:G10) -> 0 | H11: =SUM(D11:G11) -> 0
B12: Please enter the number of diploma, certificates, and degrees earned in this major group. Also enter the number of students graduating with degrees who earned a GPA of 3.0 or above, and the number who were admitted to a 4 year (Associate degree graduates), or graduate school (Bachelor's degree graduates). Lastly, enter the number of all graduating students(certificate or degree) who secured employment after graduation.
F13: July 1, 2010- June 30, 2011
B14: Graduation | D14: American Indian | F14: Non-Indian
D15: M | E15: F | F15: M | G15: F | H15: Total
A16: Apprenticeship/Occupational Program | D16: na | E16: na | F16: na | G16: na | H16: =SUM(D16:G16) -> 0
A17: Diploma | D17: na | E17: na | F17: na | G17: na | H17: =SUM(D17:G17) -> 0
A18: Certificate | D18: na | E18: na | F18: na | G18: na | H18: =SUM(D18:G18) -> 0
A19: Associate Degree | D19: na | E19: na | F19: na | G19: na | H19: =SUM(D19:G19) -> 0
B20: Assoc. graduates admitted to four-year program | D20: na | E20: na | F20: na | G20: na | H20: =SUM(D20:G20) -> 0
B21: Assoc. graduated with a GPA of 3.0 or above | D21: na | E21: na | F21: na | G21: na | H21: =SUM(D21:G21) -> 0
A22: Bachelor's Degree | D22: na | E22: na | F22: na | G22: na | H22: =SUM(D22:G22) -> 0
B23: Bach. graduates admitted to graduate school | D23: na | E23: na | F23: na | G23: na | H23: =SUM(D23:G23) -> 0
B24: Bach. graduated with a GPA of 3.0 or above | D24: na | E24: na | F24: na | G24: na | H24: =SUM(D24:G24) -> 0
A25: Master's Degree | D25: na | E25: na | F25: na | G25: na | H25: =SUM(D25:G25) -> 0
A26: Employed after graduation | D26: na | E26: na | F26: na | G26: na | H26: =SUM(D26:G26) -> 0
A28: Notes:

Sheet 4.2(NU) Major Group Enroll-Grad
A1: Institution | D1: ='1.1 Overall Institution Profile'!B1 -> Oglala Lakota College
A2: Indicator 4: Student Enrollment and Graduation by Major Group
A3: Table 4.2(NU): Major Group Fall Enrollment, Graduation & Post-Graduate / AY 2010-11
B4: Major Group | C4: NU - Nursing
B5: Please enter the number of students enrolled in this major group for the fall semester.
F6: Fall 2010 (October 15, 2010)
B7: Fall Enrollment (Snapshot) | D7: American Indian | F7: Non-Indian
D8: M | E8: F | F8: M | G8: F | H8: Total
C9: Full Time | D9: 11 | E9: 154 | F9: 1 | G9: 8 | H9: =SUM(D9:G9) -> 174
C10: Part Time | D10: 6 | E10: 74 | F10: 1 | G10: 8 | H10: =SUM(D10:G10) -> 89
C11: Total | D11: =SUM(D9:D10) -> 17 | E11: =SUM(E9:E10) -> 228 | F11: =SUM(F9:F10) -> 2 | G11: =SUM(G9:G10) -> 16 | H11: =SUM(D11:G11) -> 263
B12: Please enter the number of diploma, certificates, and degrees earned in this major group. Also enter the number of students graduating with degrees who earned a GPA of 3.0 or above, and the number who were admitted to a 4 year (Associate degree graduates), or graduate school (Bachelor's degree graduates). Lastly, enter the number of all graduating students(certificate or degree) who secured employment after graduation.
F13: July 1, 2010- June 30, 2011
B14: Graduation | D14: American Indian | F14: Non-Indian
D15: M | E15: F | F15: M | G15: F | H15: Total
A16: Apprenticeship/Occupational Program | D16: na | E16: na | F16: na | G16: na | H16: =SUM(D16:G16) -> 0
A17: Diploma | D17: na | E17: na | F17: na | G17: na | H17: =SUM(D17:G17) -> 0
A18: Certificate | D18: na | E18: na | F18: na | G18: na | H18: =SUM(D18:G18) -> 0
A19: Associate Degree | D19: 0 | E19: 10 | F19: 0 | G19: 2 | H19: =SUM(D19:G19) -> 12
B20: Assoc. graduates admitted to four-year program | D20: 0 | E20: 0 | F20: 0 | G20: 0 | H20: =SUM(D20:G20) -> 0
B21: Assoc. graduated with a GPA of 3.0 or above | D21: 0 | E21: 4 | F21: 0 | G21: 1 | H21: =SUM(D21:G21) -> 5
A22: Bachelor's Degree | D22: na | E22: na | F22: na | G22: na | H22: =SUM(D22:G22) -> 0
B23: Bach. graduates admitted to graduate school | D23: na | E23: na | F23: na | G23: na | H23: =SUM(D23:G23) -> 0
B24: Bach. graduated with a GPA of 3.0 or above | D24: na | E24: na | F24: na | G24: na | H24: =SUM(D24:G24) -> 0
A25: Master's Degree | D25: na | E25: na | F25: na | G25: na | H25: =SUM(D25:G25) -> 0
A26: Employed after graduation | D26: m | E26: m | F26: m | G26: m | H26: =SUM(D26:G26) -> 0
A28: Notes:
A29: na = not offered; m = not tacked;

Sheet 4.2(OA) Major Group Enroll-Grad
A1: Institution | D1: ='1.1 Overall Institution Profile'!B1 -> Oglala Lakota College
A2: Indicator 4: Student Enrollment and Graduation by Major Group
A3: Table 4.2(OA): Major Group Fall Enrollment, Graduation & Post-Graduate / AY 2010-11
B4: Major Group | C4: OA - Office Administration
B5: Please enter the number of students enrolled in this major group for the fall semester.
F6: Fall 2010 (October 15, 2010)
B7: Fall Enrollment (Snapshot) | D7: American Indian | F7: Non-Indian
D8: M | E8: F | F8: M | G8: F | H8: Total
C9: Full Time | D9: 0 | E9: 0 | F9: 0 | G9: 0 | H9: =SUM(D9:G9) -> 0
C10: Part Time | D10: 0 | E10: 0 | F10: 0 | G10: 0 | H10: =SUM(D10:G10) -> 0
C11: Total | D11: =SUM(D9:D10) -> 0 | E11: =SUM(E9:E10) -> 0 | F11: =SUM(F9:F10) -> 0 | G11: =SUM(G9:G10) -> 0 | H11: =SUM(D11:G11) -> 0
B12: Please enter the number of diploma, certificates, and degrees earned in this major group. Also enter the number of students graduating with degrees who earned a GPA of 3.0 or above, and the number who were admitted to a 4 year (Associate degree graduates), or graduate school (Bachelor's degree graduates). Lastly, enter the number of all graduating students(certificate or degree) who secured employment after graduation.
F13: July 1, 2010- June 30, 2011
B14: Graduation | D14: American Indian | F14: Non-Indian
D15: M | E15: F | F15: M | G15: F | H15: Total
A16: Apprenticeship/Occupational Program | D16: na | E16: na | F16: na | G16: na | H16: =SUM(D16:G16) -> 0
A17: Diploma | D17: na | E17: na | F17: na | G17: na | H17: =SUM(D17:G17) -> 0
A18: Certificate | D18: 1 | E18: 29 | F18: 0 | G18: 0 | H18: =SUM(D18:G18) -> 30
A19: Associate Degree | D19: 1 | E19: 9 | F19: 0 | G19: 0 | H19: =SUM(D19:G19) -> 10
B20: Assoc. graduates admitted to four-year program | D20: 0 | E20: 0 | F20: 0 | G20: 0 | H20: =SUM(D20:G20) -> 0
B21: Assoc. graduated with a GPA of 3.0 or above | D21: 1 | E21: 6 | F21: 0 | G21: 0 | H21: =SUM(D21:G21) -> 7
A22: Bachelor's Degree | D22: na | E22: na | F22: na | G22: na | H22: =SUM(D22:G22) -> 0
B23: Bach. graduates admitted to graduate school | D23: na | E23: na | F23: na | G23: na | H23: =SUM(D23:G23) -> 0
B24: Bach. graduated with a GPA of 3.0 or above | D24: na | E24: na | F24: na | G24: na | H24: =SUM(D24:G24) -> 0
A25: Master's Degree | D25: na | E25: na | F25: na | G25: na | H25: =SUM(D25:G25) -> 0
A26: Employed after graduation | D26: m | E26: m | F26: m | G26: m | H26: =SUM(D26:G26) -> 0
A28: Notes:
A29: na = not offered; m = not tracked;

Sheet 4.2(PA) Major Group Enroll-Grad
A1: Institution | D1: ='1.1 Overall Institution Profile'!B1 -> Oglala Lakota College
A2: Indicator 4: Student Enrollment and Graduation by Major Group
A3: Table 4.2(PA): Major Group Fall Enrollment, Graduation & Post-Graduate / AY 2010-11
B4: Major Group | C4: PA - Paralegal
B5: Please enter the number of students enrolled in this major group for the fall semester.
F6: Fall 2010 (October 15, 2010)
B7: Fall Enrollment (Snapshot) | D7: American Indian | F7: Non-Indian
D8: M | E8: F | F8: M | G8: F | H8: Total
C9: Full Time | D9: na | E9: na | F9: na | G9: na | H9: =SUM(D9:G9) -> 0
C10: Part Time | D10: na | E10: na | F10: na | G10: na | H10: =SUM(D10:G10) -> 0
C11: Total | D11: =SUM(D9:D10) -> 0 | E11: =SUM(E9:E10) -> 0 | F11: =SUM(F9:F10) -> 0 | G11: =SUM(G9:G10) -> 0 | H11: =SUM(D11:G11) -> 0
B12: Please enter the number of diploma, certificates, and degrees earned in this major group. Also enter the number of students graduating with degrees who earned a GPA of 3.0 or above, and the number who were admitted to a 4 year (Associate degree graduates), or graduate school (Bachelor's degree graduates). Lastly, enter the number of all graduating students(certificate or degree) who secured employment after graduation.
F13: July 1, 2010- June 30, 2011
B14: Graduation | D14: American Indian | F14: Non-Indian
D15: M | E15: F | F15: M | G15: F | H15: Total
A16: Apprenticeship/Occupational Program | D16: na | E16: na | F16: na | G16: na | H16: =SUM(D16:G16) -> 0
A17: Diploma | D17: na | E17: na | F17: na | G17: na | H17: =SUM(D17:G17) -> 0
A18: Certificate | D18: na | E18: na | F18: na | G18: na | H18: =SUM(D18:G18) -> 0
A19: Associate Degree | D19: na | E19: na | F19: na | G19: na | H19: =SUM(D19:G19) -> 0
B20: Assoc. graduates admitted to four-year program | D20: na | E20: na | F20: na | G20: na | H20: =SUM(D20:G20) -> 0
B21: Assoc. graduated with a GPA of 3.0 or above | D21: na | E21: na | F21: na | G21: na | H21: =SUM(D21:G21) -> 0
A22: Bachelor's Degree | D22: na | E22: na | F22: na | G22: na | H22: =SUM(D22:G22) -> 0
B23: Bach. graduates admitted to graduate school | D23: na | E23: na | F23: na | G23: na | H23: =SUM(D23:G23) -> 0
B24: Bach. graduated with a GPA of 3.0 or above | D24: na | E24: na | F24: na | G24: na | H24: =SUM(D24:G24) -> 0
A25: Master's Degree | D25: na | E25: na | F25: na | G25: na | H25: =SUM(D25:G25) -> 0
A26: Employed after graduation | D26: na | E26: na | F26: na | G26: na | H26: =SUM(D26:G26) -> 0
A28: Notes:

Sheet 4.2(PE) Major Group Enroll-Grad
A1: Institution | D1: ='1.1 Overall Institution Profile'!B1 -> Oglala Lakota College
A2: Indicator 4: Student Enrollment and Graduation by Major Group
A3: Table 4.2(PE): Major Group Fall Enrollment, Graduation & Post-Graduate / AY 2010-11
B4: Major Group | C4: PE - Pre-Engineering/Engineering
B5: Please enter the number of students enrolled in this major group for the fall semester.
F6: Fall 2010 (October 15, 2010)
B7: Fall Enrollment (Snapshot) | D7: American Indian | F7: Non-Indian
D8: M | E8: F | F8: M | G8: F | H8: Total
C9: Full Time | D9: na | E9: na | F9: na | G9: na | H9: =SUM(D9:G9) -> 0
C10: Part Time | D10: na | E10: na | F10: na | G10: na | H10: =SUM(D10:G10) -> 0
C11: Total | D11: =SUM(D9:D10) -> 0 | E11: =SUM(E9:E10) -> 0 | F11: =SUM(F9:F10) -> 0 | G11: =SUM(G9:G10) -> 0 | H11: =SUM(D11:G11) -> 0
B12: Please enter the number of diploma, certificates, and degrees earned in this major group. Also enter the number of students graduating with degrees who earned a GPA of 3.0 or above, and the number who were admitted to a 4 year (Associate degree graduates), or graduate school (Bachelor's degree graduates). Lastly, enter the number of all graduating students(certificate or degree) who secured employment after graduation.
F13: July 1, 2010- June 30, 2011
B14: Graduation | D14: American Indian | F14: Non-Indian
D15: M | E15: F | F15: M | G15: F | H15: Total
A16: Apprenticeship/Occupational Program | D16: na | E16: na | F16: na | G16: na | H16: =SUM(D16:G16) -> 0
A17: Diploma | D17: na | E17: na | F17: na | G17: na | H17: =SUM(D17:G17) -> 0
A18: Certificate | D18: na | E18: na | F18: na | G18: na | H18: =SUM(D18:G18) -> 0
A19: Associate Degree | D19: na | E19: na | F19: na | G19: na | H19: =SUM(D19:G19) -> 0
B20: Assoc. graduates admitted to four-year program | D20: na | E20: na | F20: na | G20: na | H20: =SUM(D20:G20) -> 0
B21: Assoc. graduated with a GPA of 3.0 or above | D21: na | E21: na | F21: na | G21: na | H21: =SUM(D21:G21) -> 0
A22: Bachelor's Degree | D22: na | E22: na | F22: na | G22: na | H22: =SUM(D22:G22) -> 0
B23: Bach. graduates admitted to graduate school | D23: na | E23: na | F23: na | G23: na | H23: =SUM(D23:G23) -> 0
B24: Bach. graduated with a GPA of 3.0 or above | D24: na | E24: na | F24: na | G24: na | H24: =SUM(D24:G24) -> 0
A25: Master's Degree | D25: na | E25: na | F25: na | G25: na | H25: =SUM(D25:G25) -> 0
A26: Employed after graduation | D26: na | E26: na | F26: na | G26: na | H26: =SUM(D26:G26) -> 0
A28: Notes:

Sheet 4.2(PV) Major Group Enroll-Grad
A1: Institution | D1: ='1.1 Overall Institution Profile'!B1 -> Oglala Lakota College
A2: Indicator 4: Student Enrollment and Graduation by Major Group
A3: Table 4.2(PV): Major Group Fall Enrollment, Graduation & Post-Graduate / AY 2010-11
B4: Major Group | C4: PV - Pre-Veterinary
B5: Please enter the number of students enrolled in this major group for the fall semester.
F6: Fall 2010 (October 15, 2010)
B7: Fall Enrollment (Snapshot) | D7: American Indian | F7: Non-Indian
D8: M | E8: F | F8: M | G8: F | H8: Total
C9: Full Time | D9: na | E9: na | F9: na | G9: na | H9: =SUM(D9:G9) -> 0
C10: Part Time | D10: na | E10: na | F10: na | G10: na | H10: =SUM(D10:G10) -> 0
C11: Total | D11: =SUM(D9:D10) -> 0 | E11: =SUM(E9:E10) -> 0 | F11: =SUM(F9:F10) -> 0 | G11: =SUM(G9:G10) -> 0 | H11: =SUM(D11:G11) -> 0
B12: Please enter the number of diploma, certificates, and degrees earned in this major group. Also enter the number of students graduating with degrees who earned a GPA of 3.0 or above, and the number who were admitted to a 4 year (Associate degree graduates), or graduate school (Bachelor's degree graduates). Lastly, enter the number of all graduating students(certificate or degree) who secured employment after graduation.
F13: July 1, 2010- June 30, 2011
B14: Graduation | D14: American Indian | F14: Non-Indian
D15: M | E15: F | F15: M | G15: F | H15: Total
A16: Apprenticeship/Occupational Program | D16: na | E16: na | F16: na | G16: na | H16: =SUM(D16:G16) -> 0
A17: Diploma | D17: na | E17: na | F17: na | G17: na | H17: =SUM(D17:G17) -> 0
A18: Certificate | D18: na | E18: na | F18: na | G18: na | H18: =SUM(D18:G18) -> 0
A19: Associate Degree | D19: na | E19: na | F19: na | G19: na | H19: =SUM(D19:G19) -> 0
B20: Assoc. graduates admitted to four-year program | D20: na | E20: na | F20: na | G20: na | H20: =SUM(D20:G20) -> 0
B21: Assoc. graduated with a GPA of 3.0 or above | D21: na | E21: na | F21: na | G21: na | H21: =SUM(D21:G21) -> 0
A22: Bachelor's Degree | D22: na | E22: na | F22: na | G22: na | H22: =SUM(D22:G22) -> 0
B23: Bach. graduates admitted to graduate school | D23: na | E23: na | F23: na | G23: na | H23: =SUM(D23:G23) -> 0
B24: Bach. graduated with a GPA of 3.0 or above | D24: na | E24: na | F24: na | G24: na | H24: =SUM(D24:G24) -> 0
A25: Master's Degree | D25: na | E25: na | F25: na | G25: na | H25: =SUM(D25:G25) -> 0
A26: Employed after graduation | D26: na | E26: na | F26: na | G26: na | H26: =SUM(D26:G26) -> 0
A28: Notes:

Sheet 4.2(SC) Major Group Enroll-Grad
A1: Institution | D1: ='1.1 Overall Institution Profile'!B1 -> Oglala Lakota College
A2: Indicator 4: Student Enrollment and Graduation by Major Group
A3: Table 4.2(SC): Major Group Fall Enrollment, Graduation & Post-Graduate / AY 2010-11
B4: Major Group | C4: SC - Science
B5: Please enter the number of students enrolled in this major group for the fall semester.
F6: Fall 2010 (October 15, 2010)
B7: Fall Enrollment (Snapshot) | D7: American Indian | F7: Non-Indian
D8: M | E8: F | F8: M | G8: F | H8: Total
C9: Full Time | D9: 2 | E9: 1 | F9: 0 | G9: 1 | H9: =SUM(D9:G9) -> 4
C10: Part Time | D10: 1 | E10: 0 | F10: 0 | G10: 0 | H10: =SUM(D10:G10) -> 1
C11: Total | D11: =SUM(D9:D10) -> 3 | E11: =SUM(E9:E10) -> 1 | F11: =SUM(F9:F10) -> 0 | G11: =SUM(G9:G10) -> 1 | H11: =SUM(D11:G11) -> 5
B12: Please enter the number of diploma, certificates, and degrees earned in this major group. Also enter the number of students graduating with degrees who earned a GPA of 3.0 or above, and the number who were admitted to a 4 year (Associate degree graduates), or graduate school (Bachelor's degree graduates). Lastly, enter the number of all graduating students(certificate or degree) who secured employment after graduation.
F13: July 1, 2010- June 30, 2011
B14: Graduation | D14: American Indian | F14: Non-Indian
D15: M | E15: F | F15: M | G15: F | H15: Total
A16: Apprenticeship/Occupational Program | D16: na | E16: na | F16: na | G16: na | H16: =SUM(D16:G16) -> 0
A17: Diploma | D17: na | E17: na | F17: na | G17: na | H17: =SUM(D17:G17) -> 0
A18: Certificate | D18: na | E18: na | F18: na | G18: na | H18: =SUM(D18:G18) -> 0
A19: Associate Degree | D19: 0 | E19: 0 | F19: 0 | G19: 0 | H19: =SUM(D19:G19) -> 0
B20: Assoc. graduates admitted to four-year program | D20: 0 | E20: 0 | F20: 0 | G20: 0 | H20: =SUM(D20:G20) -> 0
B21: Assoc. graduated with a GPA of 3.0 or above | D21: 0 | E21: 0 | F21: 0 | G21: 0 | H21: =SUM(D21:G21) -> 0
A22: Bachelor's Degree | D22: 0 | E22: 0 | F22: 0 | G22: 0 | H22: =SUM(D22:G22) -> 0
B23: Bach. graduates admitted to graduate school | D23: 0 | E23: 0 | F23: 0 | G23: 0 | H23: =SUM(D23:G23) -> 0
B24: Bach. graduated with a GPA of 3.0 or above | D24: 0 | E24: 0 | F24: 0 | G24: 0 | H24: =SUM(D24:G24) -> 0
A25: Master's Degree | D25: na | E25: na | F25: na | G25: na | H25: =SUM(D25:G25) -> 0
A26: Employed after graduation | D26: m | E26: m | F26: m | G26: m | H26: =SUM(D26:G26) -> 0
A28: Notes:
A29: na = not offered; m = not tracked;

Sheet 4.2(SS) Major Group Enroll-Grad
A1: Institution | D1: ='1.1 Overall Institution Profile'!B1 -> Oglala Lakota College
A2: Indicator 4: Student Enrollment and Graduation by Major Group
A3: Table 4.2(SS): Major Group Fall Enrollment, Graduation & Post-Graduate / AY 2010-11
B4: Major Group | C4: SS - Social Science
B5: Please enter the number of students enrolled in this major group for the fall semester.
F6: Fall 2010 (October 15, 2010)
B7: Fall Enrollment (Snapshot) | D7: American Indian | F7: Non-Indian
D8: M | E8: F | F8: M | G8: F | H8: Total
C9: Full Time | D9: 19 | E9: 42 | F9: 1 | G9: 8 | H9: =SUM(D9:G9) -> 70
C10: Part Time | D10: 9 | E10: 26 | F10: 1 | G10: 2 | H10: =SUM(D10:G10) -> 38
C11: Total | D11: =SUM(D9:D10) -> 28 | E11: =SUM(E9:E10) -> 68 | F11: =SUM(F9:F10) -> 2 | G11: =SUM(G9:G10) -> 10 | H11: =SUM(D11:G11) -> 108
B12: Please enter the number of diploma, certificates, and degrees earned in this major group. Also enter the number of students graduating with degrees who earned a GPA of 3.0 or above, and the number who were admitted to a 4 year (Associate degree graduates), or graduate school (Bachelor's degree graduates). Lastly, enter the number of all graduating students(certificate or degree) who secured employment after graduation.
F13: July 1, 2010- June 30, 2011
B14: Graduation | D14: American Indian | F14: Non-Indian
D15: M | E15: F | F15: M | G15: F | H15: Total
A16: Apprenticeship/Occupational Program | D16: na | E16: na | F16: na | G16: na | H16: =SUM(D16:G16) -> 0
A17: Diploma | D17: na | E17: na | F17: na | G17: na | H17: =SUM(D17:G17) -> 0
A18: Certificate | D18: na | E18: na | F18: na | G18: na | H18: =SUM(D18:G18) -> 0
A19: Associate Degree | D19: 1 | E19: 3 | F19: 0 | G19: 0 | H19: =SUM(D19:G19) -> 4
B20: Assoc. graduates admitted to four-year program | D20: 0 | E20: 0 | F20: 0 | G20: 0 | H20: =SUM(D20:G20) -> 0
B21: Assoc. graduated with a GPA of 3.0 or above | D21: 0 | E21: 1 | F21: 0 | G21: 0 | H21: =SUM(D21:G21) -> 1
A22: Bachelor's Degree | D22: 0 | E22: 3 | F22: 1 | G22: 0 | H22: =SUM(D22:G22) -> 4
B23: Bach. graduates admitted to graduate school | D23: 0 | E23: 0 | F23: 0 | G23: 0 | H23: =SUM(D23:G23) -> 0
B24: Bach. graduated with a GPA of 3.0 or above | D24: 0 | E24: 2 | F24: 1 | G24: 0 | H24: =SUM(D24:G24) -> 3
A25: Master's Degree | D25: na | E25: na | F25: na | G25: na | H25: =SUM(D25:G25) -> 0
A26: Employed after graduation | D26: m | E26: m | F26: m | G26: m | H26: =SUM(D26:G26) -> 0
A28: Notes:
A29: na = not offered; m = not tracked;

Sheet 4.2(VC) Major Group Enroll-Grad
A1: Institution | D1: ='1.1 Overall Institution Profile'!B1 -> Oglala Lakota College
A2: Indicator 4: Student Enrollment and Graduation by Major Group
A3: Table 4.2(VC): Major Group Fall Enrollment, Graduation & Post-Graduate / AY 2010-11
B4: Major Group | C4: VC - Vocational
B5: Please enter the number of students enrolled in this major group for the fall semester.
F6: Fall 2010 (October 15, 2010)
B7: Fall Enrollment (Snapshot) | D7: American Indian | F7: Non-Indian
D8: M | E8: F | F8: M | G8: F | H8: Total
C9: Full Time | D9: 50 | E9: 36 | F9: 3 | G9: 1 | H9: =SUM(D9:G9) -> 90
C10: Part Time | D10: 34 | E10: 46 | F10: 0 | G10: 1 | H10: =SUM(D10:G10) -> 81
C11: Total | D11: =SUM(D9:D10) -> 84 | E11: =SUM(E9:E10) -> 82 | F11: =SUM(F9:F10) -> 3 | G11: =SUM(G9:G10) -> 2 | H11: =SUM(D11:G11) -> 171
B12: Please enter the number of diploma, certificates, and degrees earned in this major group. Also enter the number of students graduating with degrees who earned a GPA of 3.0 or above, and the number who were admitted to a 4 year (Associate degree graduates), or graduate school (Bachelor's degree graduates). Lastly, enter the number of all graduating students(certificate or degree) who secured employment after graduation.
F13: July 1, 2010- June 30, 2011
B14: Graduation | D14: American Indian | F14: Non-Indian
D15: M | E15: F | F15: M | G15: F | H15: Total
A16: Apprenticeship/Occupational Program | D16: na | E16: na | F16: na | G16: na | H16: =SUM(D16:G16) -> 0
A17: Diploma | D17: na | E17: na | F17: na | G17: na | H17: =SUM(D17:G17) -> 0
A18: Certificate | D18: 0 | E18: 0 | F18: 0 | G18: 0 | H18: =SUM(D18:G18) -> 0
A19: Associate Degree | D19: 0 | E19: 0 | F19: 0 | G19: 0 | H19: =SUM(D19:G19) -> 0
B20: Assoc. graduates admitted to four-year program | D20: 0 | E20: 0 | F20: 0 | G20: 0 | H20: =SUM(D20:G20) -> 0
B21: Assoc. graduated with a GPA of 3.0 or above | D21: 0 | E21: 0 | F21: 0 | G21: 0 | H21: =SUM(D21:G21) -> 0
A22: Bachelor's Degree | D22: na | E22: na | F22: na | G22: na | H22: =SUM(D22:G22) -> 0
B23: Bach. graduates admitted to graduate school | D23: na | E23: na | F23: na | G23: na | H23: =SUM(D23:G23) -> 0
B24: Bach. graduated with a GPA of 3.0 or above | D24: na | E24: na | F24: na | G24: na | H24: =SUM(D24:G24) -> 0
A25: Master's Degree | D25: na | E25: na | F25: na | G25: na | H25: =SUM(D25:G25) -> 0
A26: Employed after graduation | D26: na | E26: na | F26: na | G26: na | H26: =SUM(D26:G26) -> 0
A28: Notes:
A29: Program discontinued

Sheet 4.2(UN) Major Group Enroll-Grad
A1: Institution | D1: ='1.1 Overall Institution Profile'!B1 -> Oglala Lakota College
A2: Indicator 4: Student Enrollment and Graduation by Major Group
A3: Table 4.2(UN): Major Group Fall Enrollment, Graduation & Post-Graduate / AY 2010-11
B4: Major Group | C4: UN - Undeclared/Nondeclared
B5: Please enter the number of students enrolled in this major group for the fall semester.
F6: Fall 2010 (October 15, 2010)
B7: Fall Enrollment (Snapshot) | D7: American Indian | F7: Non-Indian
D8: M | E8: F | F8: M | G8: F | H8: Total
C9: Full Time | D9: 14 | E9: 25 | F9: 3 | G9: 2 | H9: =SUM(D9:G9) -> 44
C10: Part Time | D10: 40 | E10: 81 | F10: 6 | G10: 33 | H10: =SUM(D10:G10) -> 160
C11: Total | D11: =SUM(D9:D10) -> 54 | E11: =SUM(E9:E10) -> 106 | F11: =SUM(F9:F10) -> 9 | G11: =SUM(G9:G10) -> 35 | H11: =SUM(D11:G11) -> 204
B12: Please enter the number of diploma, certificates, and degrees earned in this major group. Also enter the number of students graduating with degrees who earned a GPA of 3.0 or above, and the number who were admitted to a 4 year (Associate degree graduates), or graduate school (Bachelor's degree graduates). Lastly, enter the number of all graduating students(certificate or degree) who secured employment after graduation.
F13: July 1, 2010- June 30, 2011
B14: Graduation | D14: American Indian | F14: Non-Indian
D15: M | E15: F | F15: M | G15: F | H15: Total
A16: Apprenticeship/Occupational Program | D16: na | E16: na | F16: na | G16: na | H16: =SUM(D16:G16) -> 0
A17: Diploma | D17: na | E17: na | F17: na | G17: na | H17: =SUM(D17:G17) -> 0
A18: Certificate | D18: na | E18: na | F18: na | G18: na | H18: =SUM(D18:G18) -> 0
A19: Associate Degree | D19: na | E19: na | F19: na | G19: na | H19: =SUM(D19:G19) -> 0
B20: Assoc. graduates admitted to four-year program | D20: na | E20: na | F20: na | G20: na | H20: =SUM(D20:G20) -> 0
B21: Assoc. graduated with a GPA of 3.0 or above | D21: na | E21: na | F21: na | G21: na | H21: =SUM(D21:G21) -> 0
A22: Bachelor's Degree | D22: na | E22: na | F22: na | G22: na | H22: =SUM(D22:G22) -> 0
B23: Bach. graduates admitted to graduate school | D23: na | E23: na | F23: na | G23: na | H23: =SUM(D23:G23) -> 0
B24: Bach. graduated with a GPA of 3.0 or above | D24: na | E24: na | F24: na | G24: na | H24: =SUM(D24:G24) -> 0
A25: Master's Degree | D25: na | E25: na | F25: na | G25: na | H25: =SUM(D25:G25) -> 0
A26: Employed after graduation | D26: na | E26: na | F26: na | G26: na | H26: =SUM(D26:G26) -> 0
A28: Notes:

Sheet 4.2(UK) Major Group Enroll-Grad
A1: Institution | D1: ='1.1 Overall Institution Profile'!B1 -> Oglala Lakota College
A2: Indicator 4: Student Enrollment and Graduation by Major Group
A3: Table 4.2(UK): Major Group Fall Enrollment, Graduation & Post-Graduate / AY 2010-11
B4: Major Group | C4: UK - Unknown
B5: Please enter the number of students enrolled in this major group for the fall semester.
F6: Fall 2010 (October 15, 2010)
B7: Fall Enrollment (Snapshot) | D7: American Indian | F7: Non-Indian
D8: M | E8: F | F8: M | G8: F | H8: Total
C9: Full Time | D9: na | E9: na | F9: na | G9: na | H9: =SUM(D9:G9) -> 0
C10: Part Time | D10: na | E10: na | F10: na | G10: na | H10: =SUM(D10:G10) -> 0
C11: Total | D11: =SUM(D9:D10) -> 0 | E11: =SUM(E9:E10) -> 0 | F11: =SUM(F9:F10) -> 0 | G11: =SUM(G9:G10) -> 0 | H11: =SUM(D11:G11) -> 0
B12: Please enter the number of diploma, certificates, and degrees earned in this major group. Also enter the number of students graduating with degrees who earned a GPA of 3.0 or above, and the number who were admitted to a 4 year (Associate degree graduates), or graduate school (Bachelor's degree graduates). Lastly, enter the number of all graduating students(certificate or degree) who secured employment after graduation.
F13: July 1, 2010- June 30, 2011
B14: Graduation | D14: American Indian | F14: Non-Indian
D15: M | E15: F | F15: M | G15: F | H15: Total
A16: Apprenticeship/Occupational Program | D16: na | E16: na | F16: na | G16: na | H16: =SUM(D16:G16) -> 0
A17: Diploma | D17: na | E17: na | F17: na | G17: na | H17: =SUM(D17:G17) -> 0
A18: Certificate | D18: na | E18: na | F18: na | G18: na | H18: =SUM(D18:G18) -> 0
A19: Associate Degree | D19: na | E19: na | F19: na | G19: na | H19: =SUM(D19:G19) -> 0
B20: Assoc. graduates admitted to four-year program | D20: na | E20: na | F20: na | G20: na | H20: =SUM(D20:G20) -> 0
B21: Assoc. graduated with a GPA of 3.0 or above | D21: na | E21: na | F21: na | G21: na | H21: =SUM(D21:G21) -> 0
A22: Bachelor's Degree | D22: na | E22: na | F22: na | G22: na | H22: =SUM(D22:G22) -> 0
B23: Bach. graduates admitted to graduate school | D23: na | E23: na | F23: na | G23: na | H23: =SUM(D23:G23) -> 0
B24: Bach. graduated with a GPA of 3.0 or above | D24: na | E24: na | F24: na | G24: na | H24: =SUM(D24:G24) -> 0
A25: Master's Degree | D25: na | E25: na | F25: na | G25: na | H25: =SUM(D25:G25) -> 0
A26: Employed after graduation | D26: na | E26: na | F26: na | G26: na | H26: =SUM(D26:G26) -> 0
A28: Notes:

Sheet 4.2(MS) Major Group Enroll-Grad
A1: Institution | D1: ='1.1 Overall Institution Profile'!B1 -> Oglala Lakota College
A2: Indicator 4: Student Enrollment and Graduation by Major Group
A3: Table 4.2(MS): Major Group Fall Enrollment, Graduation & Post-Graduate / AY 2010-11
B4: Major Group | C4: MS - Master's
B5: Please enter the number of students enrolled in this major group for the fall semester.
F6: Fall 2010 (October 15, 2010)
B7: Fall Enrollment (Snapshot) | D7: American Indian | F7: Non-Indian
D8: M | E8: F | F8: M | G8: F | H8: Total
C9: Full Time | D9: 9 | E9: 21 | F9: 0 | G9: 2 | H9: =SUM(D9:G9) -> 32
C10: Part Time | D10: 4 | E10: 7 | F10: 1 | G10: 0 | H10: =SUM(D10:G10) -> 12
C11: Total | D11: =SUM(D9:D10) -> 13 | E11: =SUM(E9:E10) -> 28 | F11: =SUM(F9:F10) -> 1 | G11: =SUM(G9:G10) -> 2 | H11: =SUM(D11:G11) -> 44
B12: Please enter the number of diploma, certificates, and degrees earned in this major group. Also enter the number of students graduating with degrees who earned a GPA of 3.0 or above, and the number who were admitted to a 4 year (Associate degree graduates), or graduate school (Bachelor's degree graduates). Lastly, enter the number of all graduating students(certificate or degree) who secured employment after graduation.
F13: July 1, 2010- June 30, 2011
B14: Graduation | D14: American Indian | F14: Non-Indian
D15: M | E15: F | F15: M | G15: F | H15: Total
A16: Apprenticeship/Occupational Program | D16: na | E16: na | F16: na | G16: na | H16: =SUM(D16:G16) -> 0
A17: Diploma | D17: na | E17: na | F17: na | G17: na | H17: =SUM(D17:G17) -> 0
A18: Certificate | D18: na | E18: na | F18: na | G18: na | H18: =SUM(D18:G18) -> 0
A19: Associate Degree | D19: na | E19: na | F19: na | G19: na | H19: =SUM(D19:G19) -> 0
B20: Assoc. graduates admitted to four-year program | D20: na | E20: na | F20: na | G20: na | H20: =SUM(D20:G20) -> 0
B21: Assoc. graduated with a GPA of 3.0 or above | D21: na | E21: na | F21: na | G21: na | H21: =SUM(D21:G21) -> 0
A22: Bachelor's Degree | D22: na | E22: na | F22: na | G22: na | H22: =SUM(D22:G22) -> 0
B23: Bach. graduates admitted to graduate school | D23: na | E23: na | F23: na | G23: na | H23: =SUM(D23:G23) -> 0
B24: Bach. graduated with a GPA of 3.0 or above | D24: na | E24: na | F24: na | G24: na | H24: =SUM(D24:G24) -> 0
A25: Master's Degree | D25: 0 | E25: 3 | F25: 0 | G25: 0 | H25: =SUM(D25:G25) -> 3
A26: Employed after graduation | D26: m | E26: m | F26: m | G26: m | H26: =SUM(D26:G26) -> 0
A28: Notes:
A29: m = not tracked;

Sheet 4.2 Major Group Totals
A1: Institution | D1: ='1.1 Overall Institution Profile'!B1 -> Oglala Lakota College
A2: Indicator 4: Student Enrollment and Graduation by Major Group
A3: Table 4.2: Major Group Fall Enrollment, Graduation & Post-Graduate Totals / AY 2010-11
A4: Please enter the number of students enrolled in this major group for the fall semester. DO NOT CHANGE THE FORMULAS ON THIS PAGE.
F5: Fall 2003 (October 15, 2003)
B6: Fall Enrollment (Snapshot) | D6: American Indian | F6: Non-Indian
D7: M | E7: F | F7: M | G7: F | H7: Total
C8: Full Time | D8: =SUM('4.2(AC) Major Group Enroll-Grad:4.2(MS) Major Group Enroll-Grad'!D9) -> 313 | E8: =SUM('4.2(AC) Major Group Enroll-Grad:4.2(MS) Major Group Enroll-Grad'!E9) -> 635 | F8: =SUM('4.2(AC) Major Group Enroll-Grad:4.2(MS) Major Group Enroll-Grad'!F9) -> 21 | G8: =SUM('4.2(AC) Major Group Enroll-Grad:4.2(MS) Major Group Enroll-Grad'!G9) -> 38 | H8: =SUM(D8:G8) -> 1007
C9: Part Time | D9: =SUM('4.2(AC) Major Group Enroll-Grad:4.2(MS) Major Group Enroll-Grad'!D10) -> 212 | E9: =SUM('4.2(AC) Major Group Enroll-Grad:4.2(MS) Major Group Enroll-Grad'!E10) -> 515 | F9: =SUM('4.2(AC) Major Group Enroll-Grad:4.2(MS) Major Group Enroll-Grad'!F10) -> 21 | G9: =SUM('4.2(AC) Major Group Enroll-Grad:4.2(MS) Major Group Enroll-Grad'!G10) -> 74 | H9: =SUM(D9:G9) -> 822
C10: Total | D10: =SUM(D8:D9) -> 525 | E10: =SUM(E8:E9) -> 1150 | F10: =SUM(F8:F9) -> 42 | G10: =SUM(G8:G9) -> 112 | H10: =SUM(D10:G10) -> 1829
A11: Please enter the number of diploma, certificates, and degrees earned in this major group. Also enter the number of students graduating with degrees who earned a GPA of 3.0 or above, and the number who were admitted to a 4 year (Associate degree graduates), or graduate school (Bachelor's degree graduates). Lastly, enter the number of all graduating students(certificate or degree) who secured employment after graduation.
F12: July 1, 2003 - June 30, 2004
B13: Graduation | D13: American Indian | F13: Non-Indian
D14: M | E14: F | F14: M | G14: F | H14: Total
A15: Apprenticeship/Occupational Program | D15: =SUM('4.2(AC) Major Group Enroll-Grad:4.2(MS) Major Group Enroll-Grad'!D16) -> 0 | E15: =SUM('4.2(AC) Major Group Enroll-Grad:4.2(MS) Major Group Enroll-Grad'!E16) -> 0 | F15: =SUM('4.2(AC) Major Group Enroll-Grad:4.2(MS) Major Group Enroll-Grad'!F16) -> 0 | G15: =SUM('4.2(AC) Major Group Enroll-Grad:4.2(MS) Major Group Enroll-Grad'!G16) -> 0 | H15: =SUM(D15:G15) -> 0
A16: Diploma | D16: =SUM('4.2(AC) Major Group Enroll-Grad:4.2(MS) Major Group Enroll-Grad'!D17) -> 0 | E16: =SUM('4.2(AC) Major Group Enroll-Grad:4.2(MS) Major Group Enroll-Grad'!E17) -> 0 | F16: =SUM('4.2(AC) Major Group Enroll-Grad:4.2(MS) Major Group Enroll-Grad'!F17) -> 0 | G16: =SUM('4.2(AC) Major Group Enroll-Grad:4.2(MS) Major Group Enroll-Grad'!G17) -> 0 | H16: =SUM(D16:G16) -> 0
A17: Certificate | D17: =SUM('4.2(AC) Major Group Enroll-Grad:4.2(MS) Major Group Enroll-Grad'!D18) -> 3 | E17: =SUM('4.2(AC) Major Group Enroll-Grad:4.2(MS) Major Group Enroll-Grad'!E18) -> 36 | F17: =SUM('4.2(AC) Major Group Enroll-Grad:4.2(MS) Major Group Enroll-Grad'!F18) -> 0 | G17: =SUM('4.2(AC) Major Group Enroll-Grad:4.2(MS) Major Group Enroll-Grad'!G18) -> 0 | H17: =SUM(D17:G17) -> 39
A18: Associate Degree | D18: =SUM('4.2(AC) Major Group Enroll-Grad:4.2(MS) Major Group Enroll-Grad'!D19) -> 25 | E18: =SUM('4.2(AC) Major Group Enroll-Grad:4.2(MS) Major Group Enroll-Grad'!E19) -> 123 | F18: =SUM('4.2(AC) Major Group Enroll-Grad:4.2(MS) Major Group Enroll-Grad'!F19) -> 0 | G18: =SUM('4.2(AC) Major Group Enroll-Grad:4.2(MS) Major Group Enroll-Grad'!G19) -> 8 | H18: =SUM(D18:G18) -> 156
B19: Admitted to four-year program | D19: =SUM('4.2(AC) Major Group Enroll-Grad:4.2(MS) Major Group Enroll-Grad'!D20) -> 0 | E19: =SUM('4.2(AC) Major Group Enroll-Grad:4.2(MS) Major Group Enroll-Grad'!E20) -> 0 | F19: =SUM('4.2(AC) Major Group Enroll-Grad:4.2(MS) Major Group Enroll-Grad'!F20) -> 0 | G19: =SUM('4.2(AC) Major Group Enroll-Grad:4.2(MS) Major Group Enroll-Grad'!G20) -> 0 | H19: =SUM(D19:G19) -> 0
B20: Graduated (Assoc. Degree) with a GPA of 3.0 or above | D20: =SUM('4.2(AC) Major Group Enroll-Grad:4.2(MS) Major Group Enroll-Grad'!D21) -> 13 | E20: =SUM('4.2(AC) Major Group Enroll-Grad:4.2(MS) Major Group Enroll-Grad'!E21) -> 67 | F20: =SUM('4.2(AC) Major Group Enroll-Grad:4.2(MS) Major Group Enroll-Grad'!F21) -> 0 | G20: =SUM('4.2(AC) Major Group Enroll-Grad:4.2(MS) Major Group Enroll-Grad'!G21) -> 7 | H20: =SUM(D20:G20) -> 87
A21: Bachelor's Degree | D21: =SUM('4.2(AC) Major Group Enroll-Grad:4.2(MS) Major Group Enroll-Grad'!D22) -> 8 | E21: =SUM('4.2(AC) Major Group Enroll-Grad:4.2(MS) Major Group Enroll-Grad'!E22) -> 32 | F21: =SUM('4.2(AC) Major Group Enroll-Grad:4.2(MS) Major Group Enroll-Grad'!F22) -> 5 | G21: =SUM('4.2(AC) Major Group Enroll-Grad:4.2(MS) Major Group Enroll-Grad'!G22) -> 3 | H21: =SUM(D21:G21) -> 48
B22: Admitted to graduate school | D22: =SUM('4.2(AC) Major Group Enroll-Grad:4.2(MS) Major Group Enroll-Grad'!D23) -> 0 | E22: =SUM('4.2(AC) Major Group Enroll-Grad:4.2(MS) Major Group Enroll-Grad'!E23) -> 0 | F22: =SUM('4.2(AC) Major Group Enroll-Grad:4.2(MS) Major Group Enroll-Grad'!F23) -> 0 | G22: =SUM('4.2(AC) Major Group Enroll-Grad:4.2(MS) Major Group Enroll-Grad'!G23) -> 0 | H22: =SUM(D22:G22) -> 0
B23: Graduated (Bach. Degree) with a GPA of 3.0 or above | D23: =SUM('4.2(AC) Major Group Enroll-Grad:4.2(MS) Major Group Enroll-Grad'!D24) -> 5 | E23: =SUM('4.2(AC) Major Group Enroll-Grad:4.2(MS) Major Group Enroll-Grad'!E24) -> 25 | F23: =SUM('4.2(AC) Major Group Enroll-Grad:4.2(MS) Major Group Enroll-Grad'!F24) -> 4 | G23: =SUM('4.2(AC) Major Group Enroll-Grad:4.2(MS) Major Group Enroll-Grad'!G24) -> 3 | H23: =SUM(D23:G23) -> 37
A24: Master's Degree | D24: =SUM('4.2(AC) Major Group Enroll-Grad:4.2(MS) Major Group Enroll-Grad'!D25) -> 0 | E24: =SUM('4.2(AC) Major Group Enroll-Grad:4.2(MS) Major Group Enroll-Grad'!E25) -> 3 | F24: =SUM('4.2(AC) Major Group Enroll-Grad:4.2(MS) Major Group Enroll-Grad'!F25) -> 0 | G24: =SUM('4.2(AC) Major Group Enroll-Grad:4.2(MS) Major Group Enroll-Grad'!G25) -> 0 | H24: =SUM(D24:G24) -> 3
A25: Employed after graduation (all students) | D25: m | E25: m | F25: m | G25: m | H25: m
A27: Notes:
A28: m = not tracked;

Sheet 5.1 Academic Core Curriculum
A1: Institution | B1: ='1.1 Overall Institution Profile'!B1 -> Oglala Lakota College
A2: Indicator 5: Course Enrollment and Completion
A3: Table 5.1: Academic Core Curriculum Courses
A4: Please identify your institution's specific Academic Program's Core Curriculum courses required for all students in 2 or 4 year program. Enter 'nr' if the course is not required. Please add additional academic core curriculum courses in the spaces provided.
A5: Course | B5: Course ID(s) | C5: Course Title(s) | D5: Credits Given
A6: English Composition I | B6: ENGL 103 | C6: Freshman English I | D6: 3
A7: English Composition II | B7: ENGL 113 | C7: Freshman English II | D7: 3
A8: Communications | B8: SPCM 103 | C8: Speech Communications | D8: 3
A9: College Algebra | B9: MATH 103 | C9: Elementary Algebra | D9: 4
A10: Introduction to Computers | B10: MIS 113 | C10: Applied Information Processing | D10: 3
A11: Native American Studies | B11: LAK 103 | C11: Lakota Language I | D11: 3
A12: Lakota Language II | B12: LAK 233 | C12: Lakota Language II | D12: 3
A13: Lakota Culture | B13: LSOC 103 | C13: Lakota Culture | D13: 3
A14: College Success | B14: COSU 103 | C14: College Success - not required | D14: 3
A17: Notes:

Sheet 5.2 Acad Course Enroll & Comp
A1: Institution | B1: ='1.1 Overall Institution Profile'!B1 -> Oglala Lakota College
A2: Indicator 5: Course Enrollment and Completion
A3: Table 5.2: Academic Core Curriculum Course Enrollment and Successful Completion / AY 2010-11
A4: Please enter Course Enrollment and Successful Completion data (passed with grade 'C' or better) for the courses listed in Table 5.1. Enter 'no' if the course is not offered that semester/quarter, or 'nr' if course is not required.
A5: Academic Core Curriculum Course Enrollment and Successful Completion
A6: Course | B6: Number of Students | D6: AY 2010-11
C7: Summer 10 | D7: Fall 10 | E7: Spring 11
B8: Enrolled | C8: 18 | D8: 232 | E8: 220
A9: ='5.1 Academic Core Curriculum'!A6 -> English Composition I | B9: Success Comp. | C9: 18 | D9: 129 | E9: 97
A10: Engl 103 | B10: Withdrew | C10: 0 | D10: 103 | E10: 123
B11: Enrolled | C11: 32 | D11: 168 | E11: 207
A12: ='5.1 Academic Core Curriculum'!A7 -> English Composition II | B12: Success Comp. | C12: 31 | D12: 95 | E12: 97
A13: Engl113 | B13: Withdrew | C13: 1 | D13: 73 | E13: 110
B14: Enrolled | C14: 7 | D14: 239 | E14: 171
A15: ='5.1 Academic Core Curriculum'!A8 -> Communications | B15: Success Comp. | C15: 7 | D15: 141 | E15: 92
A16: SpCm 103 | B16: Withdrew | C16: 0 | D16: 98 | E16: 79
B17: Enrolled | C17: 39 | D17: 192 | E17: 164
A18: Elem. Algebra Math 103 | B18: Success Comp. | C18: 29 | D18: 75 | E18: 60
B19: Withdrew | C19: 10 | D19: 117 | E19: 104
B20: Enrolled | C20: 32 | D20: 219 | E20: 215
A21: ='5.1 Academic Core Curriculum'!A10 -> Introduction to Computers | B21: Success Comp. | C21: 27 | D21: 91 | E21: 101
A22: MIS 113 | B22: Withdrew | C22: 5 | D22: 128 | E22: 114
B23: Enrolled | C23: 36 | D23: 214 | E23: 231
A24: ='5.1 Academic Core Curriculum'!A11 -> Native American Studies | B24: Success Comp. | C24: 36 | D24: 113 | E24: 131
A25: Lak 103 | B25: Withdrew | C25: 0 | D25: 101 | E25: 100
B26: Enrolled | C26: 44 | D26: 119 | E26: 130
A27: =IF('5.1 Academic Core Curriculum'!A12=0,"",'5.1 Academic Core Curriculum'!A12) -> Lakota Language II | B27: Success Comp. | C27: 41 | D27: 86 | E27: 90
A28: Lak 233 | B28: Withdrew | C28: 3 | D28: 33 | E28: 40
B29: Enrolled | C29: 0 | D29: 259 | E29: 208
A30: =IF('5.1 Academic Core Curriculum'!A13=0,"",'5.1 Academic Core Curriculum'!A13) -> Lakota Culture | B30: Success Comp. | C30: 0 | D30: 160 | E30: 128
A31: Lsoc 103 | B31: Withdrew | C31: 0 | D31: 99 | E31: 80
B32: Enrolled | C32: 0 | D32: 0 | E32: 0
A33: =IF('5.1 Academic Core Curriculum'!A14=0,"",'5.1 Academic Core Curriculum'!A14) -> College Success | B33: Success Comp. | C33: 0 | D33: 0 | E33: 0
A34: NR | B34: Withdrew | C34: 0 | D34: 0 | E34: 0
B35: Enrolled
A36: =IF('5.1 Academic Core Curriculum'!A15=0,"",'5.1 Academic Core Curriculum'!A15) | B36: Success Comp.
B37: Withdrew
A38: =IF('5.1 Academic Core Curriculum'!A16=0,"",'5.1 Academic Core Curriculum'!A16) | B38: Enrolled
B39: Success Comp.
B40: Withdrew
A42: Notes:

Sheet 5.3 Vocational Core Curriculum
A1: Institution | B1: ='1.1 Overall Institution Profile'!B1 -> Oglala Lakota College
A2: Indicator 5: Course Enrollment and Completion
A3: Table 5.3: Vocational Core Curriculum Courses
A4: Please identify your institution's specific Vocational Program's Core Curriculum courses required for diploma / certificate program. Enter 'nr' if the course is not required. Please add additional vocational core curriculum courses in the spaces provided.
A5: Course | B5: Course ID(s) | C5: Course Title(s) | D5: Credits Given
A6: English Composition I | B6: ENGL 103 | C6: Freshman English I | D6: 3
A7: Freshman English II | B7: ENGL 113 | C7: only required for Oofice Technology | D7: 3
A8: Communications | B8: SPCM 103 | C8: Speech Communications | D8: 3
A9: General Mathematics | B9: MATH103, OMATH113,CMATH153 | C9: Elementary Algebra, Occupational Math, Consumer Math (Any one of these courses meet the requirement). | D9: 3
A10: Introduction to Computers | B10: na | C10: not required | D10: na
A11: Native American Studies | B11: LAK 103 | C11: Lakota Language I | D11: 3
A12: College Success | B12: COSU 103 | C12: College Success -not required | D12: 3
A17: Notes:
A18: We will only report on Academic Core curriculum - or we would have to separate the student body by degree in order to determine those students in Vocational programs.

Sheet 5.4 Voc Course Enroll & Comp
A1: Institution | B1: ='1.1 Overall Institution Profile'!B1 -> Oglala Lakota College
A2: Indicator 5: Course Enrollment and Completion
A3: Table 5.4: Vocational Core Curriculum Course Enrollment and Successful Completion / AY 2010-11
A4: Please enter Course Enrollment and Successful Completion data (passed with grade 'C' or better) for the courses listed in Table 5.3. Enter 'no' if the course is not offered that semester / quarter, or 'nr' if course is not required.
A5: Vocational Core Curriculum Course Enrollment and Successful Completion
A6: Course | B6: Number of Students | D6: AY 2010-11
C7: Summer 10 | D7: Fall 10 | E7: Spring 11
B8: Enrolled | C8: m | D8: m | E8: m
A9: ='5.3 Vocational Core Curriculum'!A6 -> English Composition I | B9: Success Comp. | C9: m | D9: m | E9: m
B10: Withdrew | C10: m | D10: m | E10: m
B11: Enrolled | C11: m | D11: m | E11: m
A12: ='5.3 Vocational Core Curriculum'!A7 -> Freshman English II | B12: Success Comp. | C12: m | D12: m | E12: m
B13: Withdrew | C13: m | D13: m | E13: m
B14: Enrolled | C14: m | D14: m | E14: m
A15: ='5.3 Vocational Core Curriculum'!A8 -> Communications | B15: Success Comp. | C15: m | D15: m | E15: m
B16: Withdrew | C16: m | D16: m | E16: m
B17: Enrolled | C17: m | D17: m | E17: m
A18: ='5.3 Vocational Core Curriculum'!A9 -> General Mathematics | B18: Success Comp. | C18: m | D18: m | E18: m
B19: Withdrew | C19: m | D19: m | E19: m
B20: Enrolled | C20: m | D20: m | E20: m
A21: ='5.3 Vocational Core Curriculum'!A10 -> Introduction to Computers | B21: Success Comp. | C21: m | D21: m | E21: m
B22: Withdrew | C22: m | D22: m | E22: m
B23: Enrolled | C23: m | D23: m | E23: m
A24: ='5.3 Vocational Core Curriculum'!A11 -> Native American Studies | B24: Success Comp. | C24: m | D24: m | E24: m
B25: Withdrew | C25: m | D25: m | E25: m
B26: Enrolled | C26: m | D26: m | E26: m
A27: =IF('5.3 Vocational Core Curriculum'!A12=0,"",'5.3 Vocational Core Curriculum'!A12) -> College Success | B27: Success Comp. | C27: m | D27: m | E27: m
B28: Withdrew | C28: m | D28: m | E28: m
B29: Enrolled | C29: m | D29: m | E29: m
A30: =IF('5.3 Vocational Core Curriculum'!A13=0,"",'5.3 Vocational Core Curriculum'!A13) | B30: Success Comp. | C30: m | D30: m | E30: m
B31: Withdrew | C31: m | D31: m | E31: m
B32: Enrolled | C32: m | D32: m | E32: m
A33: =IF('5.3 Vocational Core Curriculum'!A14=0,"",'5.3 Vocational Core Curriculum'!A14) | B33: Success Comp. | C33: m | D33: m | E33: m
B34: Withdrew | C34: m | D34: m | E34: m
B35: Enrolled | C35: m | D35: m | E35: m
A36: =IF('5.3 Vocational Core Curriculum'!A15=0,"",'5.3 Vocational Core Curriculum'!A15) | B36: Success Comp. | C36: m | D36: m | E36: m
B37: Withdrew | C37: m | D37: m | E37: m
B38: Enrolled | C38: m | D38: m | E38: m
A39: =IF('5.3 Vocational Core Curriculum'!A16=0,"",'5.3 Vocational Core Curriculum'!A16) | B39: Success Comp. | C39: m | D39: m | E39: m
B40: Withdrew | C40: m | D40: m | E40: m
A41: Notes:
A42: Please see note under table 5.3.; we do not count vocational enrollment separately from general student enrollment.

Sheet 5.5 & 5.6 Remedial-Dev Courses
A1: Institution | B1: ='1.1 Overall Institution Profile'!B1 -> Oglala Lakota College
A2: Indicator 5: Course Enrollment and Completion
A3: Table 5.5: Remedial/Developmental Courses
A4: Please identify your institution's specific Remedial/Developmental courses. Enter 'no' if the course is not offered.
A5: Course | B5: Course ID(s) | C5: Course Title(s) | E5: Credits Given
A6: Reading | B6: RW 083 | C6: Introduction to College Reading and Writing | E6: 3
A7: Writing/Composition | B7: RW 093 | C7: Transition to Reading and Writing | E7: 3
A8: Mathematics | B8: Math 083/093 | C8: Basic Math 1 and 2 | E8: 6
A9: Science | B9: na | C9: na | E9: na
A10: Table 5.6: Remedial/Developmental Course Enrollment and Successful Completion / AY 2010-11
A11: Please enter Course Enrollment and Successful Completion data (passed with grade 'C' or better). Enter 'no' if the course is not offered that semester / quarter, or 'nr' if course is not required.
A12: Remedial/Developmental Course Enrollment and Successful Completion
A13: Course | B13: Number of Students | D13: AY 2010-11
C14: Summer 10 | D14: Fall 10 | E14: Spring 11
B15: Enrolled | C15: 22 | D15: 309 | E15: 235
A16: Reading RW 083/093 | B16: Success Comp. | C16: 21 | D16: 156 | E16: 91
B17: Withdrew | C17: 1 | D17: 153 | E17: 144
B18: Enrolled | C18: na | D18: na | E18: na
A19: =A7 -> Writing/Composition | B19: Success Comp. | C19: na | D19: na | E19: na
B20: Withdrew | C20: na | D20: na | E20: na
B21: Enrolled | C21: 44 | D21: 419 | E21: 391
A22: =A8 -> Mathematics | B22: Success Comp. | C22: 22 | D22: 182 | E22: 190
A23: Math 083/093 | B23: Withdrew | C23: 22 | D23: 237 | E23: 201
B24: Enrolled | C24: na | D24: na | E24: na
A25: =A9 -> Science | B25: Success Comp. | C25: na | D25: na | E25: na
B26: Withdrew | C26: na | D26: na | E26: na
A27: Notes:
A28: Writing/Composition is included in Reading/Writing (RW); we have no remedial courses in science.

Sheet 5.7 Distance Learning
A1: Institution | B1: ='1.1 Overall Institution Profile'!B1 -> Oglala Lakota College
A2: Indicator 5: Course Enrollment and Completion
A3: Table 5.7: Online and Distance Course Enrollment and Successful Completion / AY 2010-11
A4: Please enter Online and Distance Course Information.
A5: I. Online Courses - Please enter the number of students enrolled in courses offered by your institution via the internet asynchronously, and the number of those students who passed.
A6: Online courses were NOT offered in 2010-11: | E6: Please place an X in the box if the highlighted statement is correct.
A7: Number of | C7: AY 2010-11
B8: Summer 10 | C8: Fall 10 | D8: Spring 11 | E8: Virtual Campus courses
A9: Courses Offered | B9: 0 | C9: 10 | D9: 15
A10: Students Enrolled1 | B10: 0 | C10: 174 | D10: 251
A11: Students Passed2 | B11: 0 | C11: 132 | D11: 194
A12: Students Withdrew | B12: 0 | C12: 42 | D12: 57
A13: Faculty Teaching Online Courses3 | B13: 0 | C13: 6 | D13: 10
A14: II. Distance Courses Provided by Your Campus - Please enter the number of students enrolled in courses offered by your campus via satellite, interactive television, internet etc. to other campuses or institutions synchronously, and the number of those students who passed.
A15: Distance courses were NOT provided BY your campus in 2010-11: | E15: Please place an X in the box if the highlighted statement is correct.
A16: Number of | C16: AY 2010-11
B17: Summer 10 | C17: Fall 10 | D17: Spring 11 | E17: Pictel courses
A18: Courses Offered | B18: 0 | C18: 30 | D18: 35
A19: Students Enrolled1 | B19: 0 | C19: 187 | D19: 210
A20: Students Passed2 | B20: 0 | C20: 126 | D20: 136
A21: Students Withdrew | B21: 0 | C21: 61 | D21: 74
A22: Faculty Teaching Distance Courses3 | B22: 0 | C22: 12 | D22: 17
A23: Sites Courses sent to | B23: 0 | C23: 30 | D23: 38
A24: III. Distance Courses Provided to Your Campus - Please enter the number of students enrolled in courses offered on your campus synchronously taken via satellite, interactive television, internet etc. by external providers, and the number of those students who passed.
A25: Distance courses were NOT provided TO your campus in 2010-11: | D25: X | E25: Please place an X in the box if the highlighted statement is correct.
A26: Number of | C26: AY 2010-11
B27: Summer 10 | C27: Fall 10 | D27: Spring 11
A28: Courses Offered | B28: na | C28: na | D28: na
A29: Students Enrolled1 | B29: na | C29: na | D29: na
A30: Students Passed2 | B30: na | C30: na | D30: na
A31: Students Withdrew | B31: na | C31: na | D31: na
A32: 1 Headcount of all students taking Distance Learning Courses through your institution.
A33: 2 Passed with grade 'C' or better.
A34: 3 Each faculty member (both FT and PT) is counted once (no duplicates).
A35: Notes:
A36: na = not applicable;

Sheet 6.1(11) Student Research
A1: Institution | B1: ='1.1 Overall Institution Profile'!B1 -> Oglala Lakota College
A2: Indicator 6: Student Activities
A3: Table 6.1(11): Student Academic Research and Extracurricular Activities / AY 2010-11
A4: Please indicate if any students were involved in the activity. If yes, enter number of students (or m, if number is missing) participating in institution or grant supported activities during the academic year June 2010 - May 2011. If no, enter zero. DO NOT LEAVE SPACES BLANK.
A5: Academic Development Activities | E5: Financial Support
A6: Students who | C6: Number | E6: Students who | F6: Number
A7: Received Academic Advising | C7: 662 | E7: Received financial support (need-based) | F7: 337
A8: Attended Orientation | C8: 35 | E8: Received merit scholarships | F8: 0
A9: Attended High School to College Bridge Program | C9: 0 | E9: Received athletic scholarships | F9: 0
A10: Attended Academic Workshop | C10: 12 | E10: Participated in work-study program | F10: 17
A11: Attended Summer Program other than those listed above | C11: 23 | E11: Extracurricular Activities
A12: Participated in special faculty/alumni mentoring program | C12: 25 | E12: Students who | F12: Number
A13: Participated in service learning/internships | C13: 73 | E13: Attended a National Conference | F13: 31
A14: Participated in First Year Experience program | C14: 0 | E14: Presented at a National Conference (oral/poster) | F14: 10
A15: Received Tutoring | C15: 33 | E15: Were involved in Student Government | F15: 0
A16: Academic Awards | E16: Participated in Student Activity Clubs | F16: 11
A17: Students who | C17: Number | E17: Volunteered for on-campus activities (e.g. campus tour, homecoming) | F17: 0
A18: Received Academic Awards from your college | C18: 2 | E18: Were Involved in Student Chapters of National Organizations | F18: 0
A19: Received Academic Awards from outside college | C19: 3 | E19: Participated in Athletic Programs | F19: 0
A20: Research, Teaching and Active Learning Activities | E20: Career Development
A21: Students who | C21: Number | E21: Students who | F21: Number
A22: Have been a Research Assistant/Involved in Independent Research | C22: 37 | E22: Received career advising | F22: 92
A23: Have been a Teaching Assistant | C23: 2 | E23: Attended career seminar/workshop | F23: 0
A24: Participated in on-campus research internship | C24: 23 | E24: Participated in work experience internship/co-op on campus | F24: 25
A25: Participated in off-campus research internship | C25: 2 | E25: Participated in work experience internship/co-op off campus | F25: 6
A26: Participated in an International Learning Experience | C26: 4 | E26: Received assistance from Placement Office | F26: 3
A27: Served as a Peer Tutor | C27: 2 | E27: Notes:

Sheet 6.2(11) Student Comm Act
A1: Institution | C1: ='1.1 Overall Institution Profile'!B1 -> Oglala Lakota College
A2: Indicator 6: Student Activities
A3: Table 6.2(11): Student Community and Cultural Activities, and Student Services as a Result or Based on College Experience / AY 2010-11
A4: Please indicate if any students were involved in the activity. If yes, enter number of students (or m, if missing) participating in institution or grant supported activities during the academic year June 2010 - May 2011. If no, enter zero. DO NOT LEAVE SPACES BLANK.
A5: Service to the Community | F5: Culturally Relevant Activities
A6: Students who | D6: Number | F6: Students who | H6: Number
A7: Volunteered in youth-related programs | D7: 0 | F7: Participated in culturally relevant learning activities on campus | H7: 232
A8: Volunteered in elder programs | D8: 17 | F8: Learned traditional tribal knowledge from elders in a long term and sustained relationship | H8: 56
A9: Participated in Tribal Boards or Community Organizations | D9: 12 | F9: Participated in cultural activities outside of college | H9: 352
A10: Volunteered to help with community/cultural events | D10: 23 | F10: Other activities | H10: 0
A11: Involved in family-oral histories | D11: 50 | F11: Please List
A12: Volunteered to organize powwows | D12: 2
A13: Other Activities | D13: 0
A14: Please List | F14: Student Services Offered
F15: Students who received | H15: Number
F16: Counseling | H16: 6
F17: Day care services | H17: 12
F18: Health/wellness services | H18: 26
F19: Housing | H19: 3
F20: Parenting skills | H20: 0
F21: Transportation services | H21: 35
F22: Financial management education | H22: 27
A23: Notes:

Sheet 7.1 Personnel Demographics
A1: Institution | B1: ='1.1 Overall Institution Profile'!B1 -> Oglala Lakota College
A2: Indicator 7: Personnel Demographics, Professional Development, Research, and Outcomes
A3: Table 7.1: Personnel Demographics / AY 2010-11
A4: Please note that an individual should only be counted once in the following four tables.
A5: Number of Individuals Who Are Faculty Only | D5: AY 2010-11
B6: American Indian | D6: Non-Indian | F6: Total
B7: M | C7: F | D7: M | E7: F
A8: Full Time Faculty | B8: 13 | C8: 10 | D8: 15 | E8: 23 | F8: =SUM(B8:E8) -> 61
A9: Part Time/Adjunct Faculty | B9: 25 | C9: 43 | D9: 26 | E9: 30 | F9: =SUM(B9:E9) -> 124
A10: Visiting Faculty | B10: 0 | C10: 0 | D10: 0 | E10: 0 | F10: =SUM(B10:E10) -> 0
A11: Total Headcount | B11: =SUM(B8:B10) -> 38 | C11: =SUM(C8:C10) -> 53 | D11: =SUM(D8:D10) -> 41 | E11: =SUM(E8:E10) -> 53 | F11: =SUM(F8:F10) -> 185
A13: Number of Individuals Who Are Administrators Only | D13: AY 2010-11
B14: American Indian | D14: Non-Indian | F14: Total
B15: M | C15: F | D15: M | E15: F
A16: Full Time | B16: 1 | C16: 0 | D16: 1 | E16: 1 | F16: =SUM(B16:E16) -> 3
A17: Part Time | B17: 0 | C17: 0 | D17: 0 | E17: 0 | F17: =SUM(B17:E17) -> 0
A18: Total Headcount | B18: =SUM(B15:B17) -> 1 | C18: =SUM(C15:C17) -> 0 | D18: =SUM(D15:D17) -> 1 | E18: =SUM(E15:E17) -> 1 | F18: =SUM(F15:F17) -> 3
A20: Number of Individuals Who Are Staff Only | D20: AY 2010-11
B21: American Indian | D21: Non-Indian | F21: Total
B22: M | C22: F | D22: M | E22: F
A23: Full Time | B23: 13 | C23: 80 | D23: 11 | E23: 11 | F23: =SUM(B23:E23) -> 115
A24: Part Time | B24: 0 | C24: 0 | D24: 0 | E24: 0 | F24: =SUM(B24:E24) -> 0
A25: Total Headcount | B25: =SUM(B22:B24) -> 13 | C25: =SUM(C22:C24) -> 80 | D25: =SUM(D22:D24) -> 11 | E25: =SUM(E22:E24) -> 11 | F25: =SUM(F22:F24) -> 115
A27: Number of Individuals Who Are Both Faculty and Administrators/Staff | D27: AY 2010-11
B28: American Indian | D28: Non-Indian | F28: Total
B29: M | C29: F | D29: M | E29: F
A30: Full Time | B30: 27 | C30: 90 | D30: 27 | E30: 35 | F30: =SUM(B30:E30) -> 179
A31: Part Time / Adjunct | B31: 25 | C31: 43 | D31: 26 | E31: 30 | F31: =SUM(B31:E31) -> 124
A32: Visiting | B32: 0 | C32: 0 | D32: 0 | E32: 0 | F32: =SUM(B32:E32) -> 0
A33: Total Headcount | B33: =SUM(B30:B32) -> 52 | C33: =SUM(C30:C32) -> 133 | D33: =SUM(D30:D32) -> 53 | E33: =SUM(E30:E32) -> 65 | F33: =SUM(F30:F32) -> 303
A35: Note:

Sheet 7.2 Fac Prof Demographics
A1: Institution | D1: ='1.1 Overall Institution Profile'!B1 -> Oglala Lakota College
A2: Indicator 7: Personnel Demographics, Professional Development, Research, and Outcomes
A3: Table 7.2: Faculty, Teaching Staff, and Administrator Professional Demographics / AY 2010-11
A4: Please enter Faculty, Teaching Staff, and Administrator degrees held, salary, and teaching load.
A5: Full Time Faculty, Teaching Staff, and Administrators - Highest Degree Held | E5: AY 2010-11
C6: American Indian | E6: Non-Indian | G6: Total
C7: M | D7: F | E7: M | F7: F
A8: No Degree - Expert in Field | C8: 3 | D8: 0 | E8: 1 | F8: 0 | G8: =SUM(C8:F8) -> 4
A9: Associate | C9: 0 | D9: 0 | E9: 0 | F9: 0 | G9: =SUM(C9:F9) -> 0
A10: Bachelors | C10: 5 | D10: 5 | E10: 1 | F10: 0 | G10: =SUM(C10:F10) -> 11
A11: Masters | C11: 5 | D11: 5 | E11: 13 | F11: 22 | G11: =SUM(C11:F11) -> 45
A12: Doctorate | C12: 1 | D12: 0 | E12: 1 | F12: 2 | G12: =SUM(C12:F12) -> 4
A13: Other | C13: 0 | D13: 0 | E13: 0 | F13: 0 | G13: =SUM(C13:F13) -> 0
A14: Total | C14: =SUM(C8:C13) -> 14 | D14: =SUM(D8:D13) -> 10 | E14: =SUM(E8:E13) -> 16 | F14: =SUM(F8:F13) -> 24 | G14: =SUM(G8:G13) -> 64
A16: Part Time Faculty, Teaching Staff, and Administrators - Highest Degree Held | E16: AY 2010-11
C17: American Indian | E17: Non-Indian | G17: Total
C18: M | D18: F | E18: M | F18: F
A19: No Degree - Expert in Field | C19: 4 | D19: 4 | E19: 0 | F19: 0 | G19: =SUM(C19:F19) -> 8
A20: Associate | C20: 1 | D20: 1 | E20: 0 | F20: 0 | G20: =SUM(C20:F20) -> 2
A21: Bachelors | C21: 11 | D21: 21 | E21: 9 | F21: 5 | G21: =SUM(C21:F21) -> 46
A22: Masters | C22: 8 | D22: 14 | E22: 12 | F22: 22 | G22: =SUM(C22:F22) -> 56
A23: Doctorate | C23: 1 | D23: 3 | E23: 5 | F23: 3 | G23: =SUM(C23:F23) -> 12
A24: Other | C24: 0 | D24: 0 | E24: 0 | F24: 0 | G24: =SUM(C24:F24) -> 0
A25: Total | C25: =SUM(C19:C24) -> 25 | D25: =SUM(D19:D24) -> 43 | E25: =SUM(E19:E24) -> 26 | F25: =SUM(F19:F24) -> 30 | G25: =SUM(G19:G24) -> 124
A27: Teaching Staff Salaries and Teaching Load | E27: AY 2010-11
C28: American Indian | E28: Non-Indian | G28: Non Weighted Average
C29: M | D29: F | E29: M | F29: F
A30: Full Time | B30: Average Salary per academic year* | C30: 42136 | D30: 44168 | E30: 44448 | F30: 42641 | G30: =IF(SUM(C30:F30)=0,0,AVERAGE(C30:F30)) -> 43348.25
B31: Average # of courses taught each year | C31: 4 | D31: 4 | E31: 4 | F31: 4 | G31: =IF(SUM(C31:F31)=0,0,AVERAGE(C31:F31)) -> 4
B32: Average # of students per course | C32: 11 | D32: 11 | E32: 11 | F32: 11 | G32: =IF(SUM(C32:F32)=0,0,AVERAGE(C32:F32)) -> 11
A33: Part Time | B33: Average Salary per credit hour | C33: 482 | D33: 482 | E33: 482 | F33: 482 | G33: =IF(SUM(C33:F33)=0,0,AVERAGE(C33:F33)) -> 482
B34: Average # of courses taught each year | C34: 2 | D34: 2 | E34: 2 | F34: 2 | G34: =IF(SUM(C34:F34)=0,0,AVERAGE(C34:F34)) -> 2
B35: Average # of students per course | C35: 11 | D35: 11 | E35: 11 | F35: 11 | G35: =IF(SUM(C35:F35)=0,0,AVERAGE(C35:F35)) -> 11
A37: * Please specify contract duration: | C37: 9 | D37: months
A39: Notes:

Sheet 7.3 Fac Prof Dev Service
A1: Institution | B1: ='1.1 Overall Institution Profile'!B1 -> Oglala Lakota College
A2: Indicator 7: Personnel Demographics, Professional Development, Research, and Outcomes
A3: Table 7.3: Faculty, Administrator, and Staff Professional Development and Service / AY 2010-11
A4: Please enter the number of faculty participating in, and the Person Activities (PA) or Total FTE for professional development activities, research, and service. PA is equal to the number of people attending an activity times the number of activities (e.g., if 2 people attend 2 conferences, and 1 person attends 3 conferences, PA equals (2 x 2) + (1 x 3) = 7. Total FTE is the sum of the FTE of each faculty member involved in research or service.
A5: Professional Development Activities
C6: AY 2010-11
C7: Number of Faculty / Administrator / Staff | D7: Person Activities (PA)
A8: Attended National Conferences | C8: 3 | D8: m
A9: Attended Workshops/Seminars | C9: 28 | D9: faculty development
A10: Enrolled in study for advanced degree or certification | C10: 8 | D10: Ph.D. or Ed.D.
A11: Participated in Summer Programs | C11: 3 | D11: m
A12: Faculty / Administrator / Staff Service Contribution
C13: AY 2010-11
C14: Number of Faculty / Administrator / Staff | D14: Total Hours
A15: Student Support Services | C15: 0 | D15: 0
A16: Campus Activities/Committee Services | C16: 11 | D16: 264
A17: Curriculum/Course Development | C17: 1 | D17: 90
A18: Laboratory Development/Enhancement | C18: 1 | D18: 480
A19: Community Service as a representative of the institution (e.g. Tribal Committee) | C19: 5 | D19: 3170
A20: Notes:
A21: The figures provided are activities funded by OLC. We do not keep data on professional development activities that are funded by individual departments or by individuals.

Sheet 7.4 Faculty Research
A1: Institution | B1: ='1.1 Overall Institution Profile'!B1 -> Oglala Lakota College
A2: Indicator 7: Personnel Demographics, Professional Development, Research, and Outcomes
A3: Table 7.4: Faculty/Administrator/Staff Research, Creative Activities, and Outcomes / AY 2010-11
A4: Please enter faculty/administrator/staff research and creative activities and outcomes.
A5: Publications and Presentations
C6: AY 2010-11
C7: Number of Faculty / Administrator / Staff | D7: Number of Pub. & Pres.
A8: Refereed Journal Papers Submitted | C8: 1 | D8: 1
A9: Refereed Journal Papers Published | C9: 1 | D9: 1
A10: Other Publications(books, chapters, etc.) | C10: 1 | D10: 1
A11: Conference Proceedings Published | C11: 0 | D11: 0
A12: Scholarly creative cultural activities (ex. exhibit, play) | C12: 7 | D12: 4
A13: Professional Presentations at National Conferences | C13: 3 | D13: 3
A14: Professional Presentations at on-campus workshops/ seminars | C14: 3 | D14: 1
A15: Professional Presentations at off-campus workshops/ seminars | C15: 162 | D15: 8
A16: Proposals Submitted and Funded
C17: AY 2010-11
C18: Number of Faculty / Administrator / Staff | D18: Number of Proposals
A19: Proposals Submitted for External Funding | C19: 3 | D19: 7
A20: External Proposals Funded | C20: 2 | D20: 4
A21: Total Amount of Funded Awards ($) | C21: 300000
A22: Faculty/Administrator/Staff Support for Research
C23: AY 2010-11
C24: Number of Faculty / Administrator / Staff | D24: Total Hours
A25: Release Time/Reduction of Course Load | C25: 1 | D25: 184
A26: Provision of Professional Research Staff | C26: 0 | D26: 0
A27: Provision of Student Research Assistant | C27: 0 | D27: 0
A28: Notes:

Sheet 8.1 Students with Disabilities 
A1: Institution | C1: ='1.1 Overall Institution Profile'!B1 -> Oglala Lakota College
A2: Indicator 8: Students with Disabilities Enrollment and Graduation
A3: Table 8.1: Enrollment and Graduation of Students with Disabilities / AY 2010-11
A4: Please enter the student with disabilities enrollment and graduation data.
A5: Disabled Students Enrollment
F6: Fall 2010 (October 15, 2010)
C7: American Indian | E7: Non-Indian | H7: Total
C8: M | D8: F | E8: M | F8: F | G8: M | H8: F | I8: Total
A9: Undergraduate | B9: Full Time Total | C9: m | D9: m | E9: m | F9: m | G9: =SUM(C9,E9) -> 0 | H9: =SUM(D9,F9) -> 0 | I9: =SUM(G9:H9) -> 0
B10: Part Time Total | C10: m | D10: m | E10: m | F10: m | G10: =SUM(C10,E10) -> 0 | H10: =SUM(D10,F10) -> 0 | I10: =SUM(G10:H10) -> 0
B11: Total Undergraduate Students | C11: =SUM(C9:C10) -> 0 | D11: =SUM(D9:D10) -> 0 | E11: =SUM(E9:E10) -> 0 | F11: =SUM(F9:F10) -> 0 | G11: =SUM(G9:G10) -> 0 | H11: =SUM(H9:H10) -> 0 | I11: =SUM(I9:I10) -> 0
A12: Graduate | B12: Full Time Total | G12: =SUM(C12,E12) -> 0 | H12: =SUM(D12,F12) -> 0 | I12: =SUM(G12:H12) -> 0
B13: Part Time Total | G13: =SUM(C13,E13) -> 0 | H13: =SUM(D13,F13) -> 0 | I13: =SUM(G13:H13) -> 0
B14: Total Graduate Students | C14: =SUM(C12:C13) -> 0 | D14: =SUM(D12:D13) -> 0 | E14: =SUM(E12:E13) -> 0 | F14: =SUM(F12:F13) -> 0 | G14: =SUM(G12:G13) -> 0 | H14: =SUM(H12:H13) -> 0 | I14: =SUM(I12:I13) -> 0
A15: Total Headcount | C15: =C11+C14 -> 0 | D15: =D11+D14 -> 0 | E15: =E11+E14 -> 0 | F15: =F11+F14 -> 0 | G15: =SUM(G11,G14) -> 0 | H15: =SUM(H11,H14) -> 0 | I15: =SUM(I11,I14) -> 0
A16: Number of students receiving services | C16: m | D16: m | E16: m | F16: m | G16: =SUM(C16,E16) -> 0 | H16: =SUM(D16,F16) -> 0 | I16: =SUM(G16:H16) -> 0
A17: Degrees / Certificates Conferred to Disabled Students
A18: Degrees / Certificates Conferred | F18: July 1, 2010 - June 30, 2011
A19: Number of Students who Earned | C19: American Indian | E19: Non-Indian | H19: Total
C20: M | D20: F | E20: M | F20: F | G20: M | H20: F | I20: Total
A21: Apprenticeship/Occupational Program | G21: =SUM(C21,E21) -> 0 | H21: =SUM(D21,F21) -> 0 | I21: =SUM(G21:H21) -> 0
A22: Diploma | G22: =SUM(C22,E22) -> 0 | H22: =SUM(D22,F22) -> 0 | I22: =SUM(G22:H22) -> 0
A23: Certificate | C23: m | D23: m | E23: m | F23: m | G23: =SUM(C23,E23) -> 0 | H23: =SUM(D23,F23) -> 0 | I23: =SUM(G23:H23) -> 0
A24: Associate Degree | C24: m | D24: m | E24: m | F24: m | G24: =SUM(C24,E24) -> 0 | H24: =SUM(D24,F24) -> 0 | I24: =SUM(G24:H24) -> 0
A25: Bachelor's Degree | C25: m | D25: m | E25: m | F25: m | G25: =SUM(C25,E25) -> 0 | H25: =SUM(D25,F25) -> 0 | I25: =SUM(G25:H25) -> 0
A26: Master's Degree | C26: m | D26: m | E26: m | F26: m | G26: =SUM(C26,E26) -> 0 | H26: =SUM(D26,F26) -> 0 | I26: =SUM(G26:H26) -> 0
A27: Total number degrees conferred | C27: =SUM(C21:C26) -> 0 | D27: =SUM(D21:D26) -> 0 | E27: =SUM(E21:E26) -> 0 | F27: =SUM(F21:F26) -> 0 | G27: =SUM(G21:G26) -> 0 | H27: =SUM(H21:H26) -> 0 | I27: =SUM(I21:I26) -> 0
A28: Number of Associate's Degree graduates admitted to four-year program | C28: m | D28: m | E28: m | F28: m | G28: =SUM(C28,E28) -> 0 | H28: =SUM(D28,F28) -> 0 | I28: =SUM(G28:H28) -> 0
A29: Number of Bachelor's Degree graduates admitted to graduate school | G29: =SUM(C29,E29) -> 0 | H29: =SUM(D29,F29) -> 0 | I29: =SUM(G29:H29) -> 0
A30: Number of graduates employed after graduation | C30: m | D30: m | E30: m | F30: m | G30: =SUM(C30,E30) -> 0 | H30: =SUM(D30,F30) -> 0 | I30: =SUM(G30:H30) -> 0
A31: Notes:
A32: We have seven (7) male and four (4) female students with disabilities. They are all Native American. They are not separated by full-time or part-time, nor do we separate them out with regard to degrees/Certificates conferred. Tracking is being refined.

Sheet MENU INFO
A1: Drop-Down Menu Item List
B3: Table 1.1 | G3: Table 3.1 | L3: Table 4.1
B4: Highest Degree Offered | G4: Campus Site | L4: Major Group ID/Major Groups
B5: 4 year & master's | G5: Main Campus | L5: AC - Accounting
B6: 4 year & doctoral | G6: Branch Campus | L6: AG - Agriculture and Farming
B7: 4 year undergraduate | G7: Satellite Site | L7: AL - American Indian Languages
B8: 2 year | L8: AS - American Indian Studies
G9: Table 3.1 | L9: AR - Art
B10: Table 1.1 | G10: Main Function | L10: AU - Automotive Technology
B11: Academic Term | G11: Administration/Office | L11: BI - Biology
B12: Quarter | G12: Auxiliary | L12: BT - Building Trades
B13: Semester | G13: Classroom | L13: BU - Business
B14: Trimester | G14: Cultural Center/Museum | L14: CH - Chemistry
B15: Other | G15: Distance Learning | L15: CS - Computer Science
G16: Laboratory | L16: CT - Computer Technology
B17: Table 1.1 | G17: Library | L17: CL - Corrections/Law Enforcement
B18: Land-Granted | G18: Research | L18: EA - Education-Paraprofessional
B19: Yes | G19: Residence | L19: EO - Education-Professional
B20: No | G20: Student Services/Recreation | L20: EN - English
L21: ES - Environmental Science/Natural Resources
B22: Table 1.1 | G22: Table 3.1 | L22: GE - Geography
B23: Location | G23: Own/Lease | L23: HS - Health Careers
B24: On Reservation | G24: Assigned by Tribe | L24: HI - Hospitality Industry
B25: Off Reservation | G25: Donated | L25: HS - Human Services
G26: Lease/Rent | L26: IP - Individualized Program
G27: Own | L27: LA - Liberal Arts/General Studies
L28: LS - Life Sciences
G29: Table 3.2 | L29: MA - Mathematics
G30: Catalogue On-line Access | L30: NS - Natural Science
G31: Inter-Library System | L31: NU - Nursing
G32: Computer Lab w/ Internet | L32: OA - Office Administration/Technology
G33: Yes | L33: PA - Paralegal
G34: No | L34: PE - Pre-Engineering
L35: PV - Pre-Veterinary Science
G36: Table 3.2 | L36: SC - Science
G37: Community Library Status | L37: SS - Social Science
G38: Community Library | L38: VC - Vocational/Career Programs
G39: Institution Use Only | L39: UD - Undeclared/Nondeclared
L40: MS - Master Degree Programs
G41: Table 3.2
G42: Community Learning Center
G43: Yes
G44: No
