Workbook

Sheet Dates
B3: Key Dates for Odd year Election Calendar | D3: DATES
B6: Enter Date of Previous November General Election | D6: 41583
B7: Enter Date that Legislative Session Begins | D7: 41695
B8: Enter Date of First Monday in January | D8: 41645
B9: Enter Date of Township Election (2nd Tues in March) | D9: 41709
B10: Enter Date of Primary Election (2nd Tues.) | D10: 41863
B11: Enter Date of General Election (1st Tuesday after 1st Monday in Nov.) | D11: 41947
B12: Enter Date of Next Years March Township Election | D12: 42073
B13: Enter New Years Day | D13: 41640
B14: Enter Martin Luther King Jr. Day | D14: 41659
B15: Enter Presidents Day | D15: 41687
B16: Enter Memorial Day | D16: 41785
B17: Enter Independence Day Holiday | D17: 41824
... B31: Enter date of 2014 Precinct Caucuses | D31: 41674
B34: Formulas on next pages will automatically update Calendar (Even Year)

Sheet Combined Elections Calendar
A1: 2014 Minnesota Combined Elections Calendar - Revised
A2: Updated 6-17-2014
A3: This calendar lists important election dates related to the 2014 Election Cycle. Date entries include citations to Minnesota Statutes or Minnesota Rules. Minnesota Statutes and Rules are available at http://www.revisor.leg.state.mn.us. In all matters, Minnesota Election Law is the final authority, not this calendar. Changes to Minnesota Election Law enacted by the Minnesota State Legislature in 2014 may alter dates or other information on this calendar. For the most current version of this document please check the Secretary of State's website at www.sos.state.mn.us.
A5: This calendar is not intended to provide legal advice and should not be used as a substitute for legal guidance. Readers should consult with an attorney for advice concerning specific situations.
A7: *Metro Towns (200.02, subd. 24): Towns located in Anoka, Carver, Chisago, Dakota, Hennepin, Isanti, Ramsey, Scott, Sherburne, Washington, and Wright Counties.
A9: **Metropolitan area (473.121, subd. 2): The area over which the Metropolitan Council has jurisdiction, including only the counties of Anoka; Carver; Dakota excluding the city of Northfield; Hennepin excluding the cities of Hanover and Rockford; Ramsey; Scott excluding the city of New Prague; and Washington.
A11: Calculation of Dates: Dates on the 2014 Minnesota Combined Election Calendar are calculated in the following manner, pursuant to Minnesota Statutes, Chapter 645: When counting the number of days before an election or other event, the day before the event is the first day counted. When counting the number of days after an election or other event, the day after the event is the first day counted. When the last day falls on a weekend or legal holiday, that day is usually omitted from the computation.
A13: Note: When Minnesota Election Law requires that action be taken on or before a date that falls on a weekend, this calendar usually uses the previous Friday date to ensure timely action.
A15: For relevant law on the calculation of dates, see Minn. Stat. §§ 645.13; 645.15; 645.151; 331A.08, subd. 1; 331A.08, subd. 2.
A17: 645.13 Time; publication for successive weeks. When the term "successive weeks" is used in any law providing for the publishing of notices, the word "weeks" shall be construed as calendar weeks. The publication upon any day of such weeks shall be sufficient publication for that week, but at least five days shall elapse between each publication. At least the number of weeks specified in "successive weeks" shall elapse between the first publication and the day for the happening of the event for which the publication is made.
A19: 645.15 Computation of time. Where the performance or doing of any act, duty, matter, payment, or thing is ordered or directed, and the period of time or duration for the performance or doing thereof is prescribed and fixed by law, the time, except as otherwise provided in sections 645.13 and 645.14, shall be computed so as to exclude the first and include the last day of the prescribed or fixed period or duration of time. When the last day of the period falls on Saturday, Sunday or a legal holiday, that day shall be omitted from the computation.
A21: 645.151 Timely delivery or filing. When an application, payment, return, claim, statement or other document is to be delivered to or filed with a department, agency or instrumentality of this state or of a political subdivision on or before a prescribed date and the prescribed date falls on a Saturday, Sunday or legal holiday, it is timely delivered or filed if it is delivered or filed on the next succeeding day which is not a Saturday, Sunday or legal holiday.
A23: 331A.08 Subd.1. Time for publication. The time for publication of public notices shall be computed to exclude the first day of publication and include the day on which the act or event, of which notice is given, is to happen or which completes the full period required for publication. Subd. 2. Time for act or proceeding. The time within which an act is to be done or proceeding had or taken, as prescribed by the rules of procedure, shall be computed by excluding the first day and including the last. If the last day is Sunday or a legal holiday the party shall have the next secular day in which to do the act or take the proceeding.
A25: Begin Date | B25: End Date | C25: Bolded type indicates subdivision affected: | D25: Statute § | E25: Affected | F25: Reference
A26: 41603 | B26: 41603 | C26: Secretary of State: Deadline for 2013 HAVA Grant Progress Reports on HAVA grant funds used for both the 2005 HAVA grants and 2010 HAVA equipment grants. Unless all funds have been disbursed and reported on in a previous year. These reports cover the period of 10/1/2012 to 9/30/2013. 42 U.S.C. 15421 | D26: 42 USC 15421 | E26: Secretary of State | F26: HAVA
A27: 41603 | B27: 41603 | C27: Counties: Deadline for 2013 HAVA Grant Progress Reports on HAVA grant funds used for both the 2005 HAVA grants and 2010 HAVA equipment grants. Unless all funds have been disbursed and reported on in a previous year. These reports cover the period of 10/1/2012 to 9/30/2013. 42 U.S.C. 15421 | D27: 42 USC 15421 | E27: Counties | F27: HAVA
A28: =+Dates!$D$9-98 -> 41611 | B28: =+Dates!$D$9-98 -> 41611 | C28: Counties: Last day to designate location for March township elections absentee voting - 14 weeks before election. Minn. Stat. §203B.081 | D28: 203B.081 | E28: Counties | F28: AB
A29: =+Dates!$D$9-98 -> 41611 | B29: =+Dates!$D$9-98 -> 41611 | C29: Towns with March Elections: Last day to designate location for March township elections absentee voting - 14 weeks before election. Minn. Stat. §203B.081 | D29: 203B.081 | E29: Towns with March Elections | F29: AB
A30: 41612 | B30: 41612 | C30: Secretary of State: Application deadline for cities, townships, and counties applying for 2013-2014 EAID Grant. 42 U.S.C. 15421 | D30: 42 USC 15421 | E30: Secretary of State | F30: HAVA
A31: 41612 | B31: 41612 | C31: Counties: Application deadline for cities, townships, and counties applying for 2013-2014 EAID Grant. 42 U.S.C. 15421 | D31: 42 USC 15421 | E31: Counties | F31: HAVA
A32: 41612 | B32: 41612 | C32: Cities with a Primary: Application deadline for cities, townships, and counties applying for 2013-2014 EAID Grant. 42 U.S.C. 15421 | D32: 42 USC 15421 | E32: Cities with a Primary | F32: HAVA
A33: 41612 | B33: 41612 | C33: Cities without a Primary: Application deadline for cities, townships, and counties applying for 2013-2014 EAID Grant. 42 U.S.C. 15421 | D33: 42 USC 15421 | E33: Cities without a Primary | F33: HAVA
A34: 41612 | B34: 41612 | C34: Towns with March Elections: Application deadline for cities, townships, and counties applying for 2013-2014 EAID Grant. 42 U.S.C. 15421 | D34: 42 USC 15421 | E34: Towns with March Elections | F34: HAVA
A35: 41612 | B35: 41612 | C35: Towns with November Elections: Application deadline for cities, townships, and counties applying for 2013-2014 EAID Grant. 42 U.S.C. 15421 | D35: 42 USC 15421 | E35: Towns with November Elections | F35: HAVA
A36: =+Dates!$D$9-90 -> 41619 | B36: =+Dates!$D$9-90 -> 41619 | C36: Counties: Last day to change polling place prior to March township elections - not less than 90 days prior to election. Minn. Stat. §204B.16, subd. 3 | D36: 204B.16, subd. 3 | E36: Counties | F36: Polling Place
A37: =+Dates!$D$9-90 -> 41619 | B37: =+Dates!$D$9-90 -> 41619 | C37: Towns with March Elections: Last day to change polling place prior to March township elections - not less than 90 days prior to election. Minn. Stat. §204B.16, subd. 3 | D37: 204B.16, subd. 3 | E37: Towns with March Elections | F37: Polling Place
A38: =+Dates!$D$9-90 -> 41619 | B38: =+Dates!$D$9-90 -> 41619 | C38: Secretary of State: The municipal governing body, school board, or county board may authorize mail balloting by resolution - no later than 90 days prior to the first election at which mail balloting will be used. Minn. Rule 8210.3000, subp. 2 | D38: 8210.3000, subp. 2 | E38: Secretary of State | F38: Mail Elections
A39: =+Dates!$D$9-90 -> 41619 | B39: =+Dates!$D$9-90 -> 41619 | C39: Counties: The municipal governing body, school board, or county board may authorize mail balloting by resolution - no later than 90 days prior to the first election at which mail balloting will be used. Minn. Rule 8210.3000, subp. 2 | D39: 8210.3000, subp. 2 | E39: Counties | F39: Mail Elections
A40: =+Dates!$D$9-90 -> 41619 | B40: =+Dates!$D$9-90 -> 41619 | C40: Towns with March Elections: The municipal governing body, school board, or county board may authorize mail balloting by resolution - no later than 90 days prior to the first election at which mail balloting will be used. Minn. Rule 8210.3000, subp. 2 | D40: 8210.3000, subp. 2 | E40: Towns with March Elections | F40: Mail Elections
A41: =+Dates!$D$9-90 -> 41619 | B41: =+Dates!$D$9-90 -> 41619 | C41: Secretary of State: Last day for townships with March election to revoke mail election precinct prior to election - no later than 90 days before the next affected election. Minn. Rule 8210.3000, subp. 2 | D41: 8210.3000, subp. 2 | E41: Secretary of State | F41: Mail Elections
A42: =+Dates!$D$9-90 -> 41619 | B42: =+Dates!$D$9-90 -> 41619 | C42: Counties: Last day for townships with March election to revoke mail election precinct prior to election - no later than 90 days before the next affected election. Minn. Rule 8210.3000, subp. 2 | D42: 8210.3000, subp. 2 | E42: Counties | F42: Mail Elections
A43: =+Dates!$D$9-90 -> 41619 | B43: =+Dates!$D$9-90 -> 41619 | C43: Towns with March Elections: Last day for townships with March election to revoke mail election precinct prior to election - no later than 90 days before the next affected election. Minn. Rule 8210.3000, subp. 2 | D43: 8210.3000, subp. 2 | E43: Towns with March Elections | F43: Mail Elections
A44: =+Dates!$D$6+40 -> 41623 | B44: =+Dates!$D$6+47 -> 41630 | C44: School Districts with a Primary: Last day for winning candidates to file an acceptance and oath of office with the clerk - within 30 days of issuance of certificate of election. Minn. Stat. §205A.10, subd. 3 | D44: 205A.10, subd. 3 | E44: School Districts with a Primary | F44: After the Election
A45: =+Dates!$D$6+40 -> 41623 | B45: =+Dates!$D$6+47 -> 41630 | C45: School Districts without a Primary: Last day for winning candidates to file an acceptance and oath of office with the clerk - within 30 days of issuance of certificate of election. Minn. Stat. §205A.10, subd. 3 | D45: 205A.10, subd. 3 | E45: School Districts without a Primary | F45: After the Election
A46: =+Dates!$D$9-84 -> 41625 | B46: =+Dates!$D$9-84 -> 41625 | C46: Secretary of State: Last day for County Auditor to meet or otherwise communicate with March township officials to review election procedures for 2014 March Township Elections - at least 12 weeks before the March town general election. Minn. Stat. §204B.28, subd. 1 | D46: 204B.28, subd. 1 | E46: Secretary of State | F46: Election Day
A47: =+Dates!$D$9-84 -> 41625 | B47: =+Dates!$D$9-84 -> 41625 | C47: Counties: Last day for County Auditor to meet or otherwise communicate with March township officials to review election procedures for 2014 March Township Elections - at least 12 weeks before the March town general election. Minn. Stat. §204B.28, subd. 1 | D47: 204B.28, subd. 1 | E47: Counties | F47: Election Day
A48: =+Dates!$D$9-84 -> 41625 | B48: =+Dates!$D$9-84 -> 41625 | C48: Towns with March Elections: Last day for County Auditor to meet or otherwise communicate with March township officials to review election procedures for 2014 March Township Elections - at least 12 weeks before the March town general election. Minn. Stat. §204B.28, subd. 1 | D48: 204B.28, subd. 1 | E48: Towns with March Elections | F48: Election Day
A49: =+Dates!$D$9-84 -> 41625 | B49: =+Dates!$D$9-84 -> 41625 | C49: Towns with March Elections: Last day to publish first of two notices of town offices to be elected at March election. Notice to include first and last dates to file for town office, and the closing time for filing (new 2013 language requires the municipal clerk's office to be open for filing from 1-5 p.m. on the last day of the filing period) – at least two weeks before the first day to file an Affidavit of Candidacy. Minn. Stat. §205.13, subd. 2 | D49: 205.13, subd. 2 | E49: Towns with March Elections | F49: Notice
A50: =+Dates!$D$9-81 -> 41628 | B50: =+Dates!$D$9-81 -> 41628 | C50: Towns with March Elections: Last day to post notice of town offices to be elected at March election. Notice to include first and last dates to file for town office, and the closing time for filing on the last day to file - 10 days before the first day to file affidavits of candidacy. Minn. Stat. §205.13, subd. 2 | D50: 205.13, subd. 2 | E50: Towns with March Elections | F50: Notice
A51: =+Dates!$D$9-77 -> 41632 | B51: =+Dates!$D$9-77 -> 41632 | C51: Towns with March Elections: Last day to publish second of two notices of town offices to be elected at March election. Notice to include first and last dates to file for town office, and the closing time for filing (new 2013 language requires the municipal clerk's office to be open for filing from 1-5 p.m. on the last day of the filing period) – at least two weeks before the first day to file an Affidavit of Candidacy. Minn. Stat. §205.13, subd. 2 | D51: 205.13, subd. 2 | E51: Towns with March Elections | F51: Notice
A52: 41633 | B52: 41633 | C52: Christmas Day Holiday. No public business shall be transacted, except in cases of necessity. Minn. Stat. §645.44, subd.5 | D52: 645.44, subd. 5 | E52: Holiday | F52: Holiday
A53: =+Dates!$D$9-74 -> 41635 | B53: =+Dates!$D$9-74 -> 41635 | C53: Secretary of State: Last day for township to provide written notice of election to auditor – at least 74 days before election. Minn. Stat. §205.16, subd. 4 | D53: 205.16, subd. 4 | E53: Secretary of State | F53: Notice
A54: =+Dates!$D$9-74 -> 41635 | B54: =+Dates!$D$9-74 -> 41635 | C54: Counties: Last day for township to provide written notice of election to auditor – at least 74 days before election. Minn. Stat. §205.16, subd. 4 | D54: 205.16, subd. 4 | E54: Counties | F54: Notice
A55: =+Dates!$D$9-74 -> 41635 | B55: =+Dates!$D$9-74 -> 41635 | C55: Towns with March Elections: Last day to provide written notice of election to auditor – at least 74 days before election. Minn. Stat. §205.16, subd. 4 | D55: 205.16, subd. 4 | E55: Towns with March Elections | F55: Notice
A56: =+Dates!$D$9-74 -> 41635 | B56: =+Dates!$D$9-74 -> 41635 | C56: Secretary of State: Last day for Auditor to notify the Secretary of State of March Township Elections – at least 74 days before election. Minn. Stat. §205.16, subd. 5 | D56: 205.16, subd.5 | E56: Secretary of State | F56: Notice
A57: =+Dates!$D$9-74 -> 41635 | B57: =+Dates!$D$9-74 -> 41635 | C57: Counties: Last day for Auditor to notify the Secretary of State of March Township Elections – at least 74 days before election. Minn. Stat. §205.16, subd. 5 | D57: 205.16, subd.5 | E57: Counties | F57: Notice
A58: =+Dates!$D$9-74 -> 41635 | B58: =+Dates!$D$9-74 -> 41635 | C58: Towns with March Elections: Last day for Auditor to notify the Secretary of State of March Township Elections – at least 74 days before election. Minn. Stat. §205.16, subd. 5 | D58: 205.16, subd.5 | E58: Towns with March Elections | F58: Notice
A59: 41639 | B59: 41639 | C59: Counties: Suggested Administrative Procedure: Please record the following amounts relating to HAVA funds: 1) The amount spent to purchase election equipment; 2) The amount spent for operating costs; 3) The balance left from assistive voting machine grants; 4) The balance left from optical scan central count and precinct count machine grants; 5) Interest earned from: a) Assistive voting machine grants; and b) optical scan central count and precinct count machines grant; and 6) Balances left from interest earned. 42 U.S.C. 15421 | D59: 42 USC 15421 | E59: Counties | F59: HAVA
A60: 41639 | B60: 41639 | C60: Secretary of State: Deadline for Secretary of State to file HAVA grant and EAID grant reports with the EAC for federal fiscal year ending September 30, 2013. 42.U.S.C. 15421 | D60: 42 USC 15421 | E60: Secretary of State | F60: HAVA
A61: =+Dates!$D$9-70 -> 41639 | B61: =+Dates!$D$9-70 -> 41639 | C61: Secretary of State: Last day to change precinct boundary prior to March Township Election - at least 10 weeks before the date of the next election. Minn. Stat. §204B.14, subd. 4 | D61: 204B.14, subd.4 | E61: Secretary of State | F61: Boundaries
A62: =+Dates!$D$9-70 -> 41639 | B62: =+Dates!$D$9-70 -> 41639 | C62: Counties: Last day to change precinct boundary prior to March Township Election - at least 10 weeks before the date of the next election. Minn. Stat. §204B.14, subd. 4 | D62: 204B.14, subd.4 | E62: Counties | F62: Boundaries
A63: =+Dates!$D$9-70 -> 41639 | B63: =+Dates!$D$9-70 -> 41639 | C63: Towns with March Elections: Last day to change precinct boundary prior to March Township Election - at least 10 weeks before the date of the next election. Minn. Stat. §204B.14, subd. 4 | D63: 204B.14, subd.4 | E63: Towns with March Elections | F63: Boundaries
A64: 41639 | B64: 41639 | C64: Secretary of State: Last day for Secretary of State to make the absentee ballot application forms available to County Auditors through electronic means - by January 1 of each even-numbered. Minn. Stat. §203B.04, subd. 1 | D64: 203B.04, subd. 1 | E64: Secretary of State | F64: AB
A65: 41639 | B65: 41639 | C65: Counties: Last day for Secretary of State to make the absentee ballot application forms available to County Auditors through electronic means - by January 1 of each even-numbered. Minn. Stat. §203B.04, subd. 1 | D65: 203B.04, subd. 1 | E65: Counties | F65: AB
A66: =+Dates!$D$9-70 -> 41639 | B66: =+Dates!$D$9-70 -> 41639 | C66: Secretary of State: Last day to provide notice of election and the special mail procedure - at least 10 weeks prior to the election. Minn. Stat. §204B.45, subd. 2 | D66: 204B.45, subd. 2 | E66: Secretary of State | F66: Mail Elections
A67: =+Dates!$D$9-70 -> 41639 | B67: =+Dates!$D$9-70 -> 41639 | C67: Counties: Last day to provide notice of election and the special mail procedure - at least 10 weeks prior to the election. Minn. Stat. §204B.45, subd. 2 | D67: 204B.45, subd. 2 | E67: Counties | F67: Mail Elections
A68: =+Dates!$D$9-70 -> 41639 | B68: =+Dates!$D$9-70 -> 41639 | C68: Towns with March Elections: Last day to provide notice of election and the special mail procedure - at least 10 weeks prior to the election. Minn. Stat. §204B.45,subd. 2 | D68: 204B.45, subd. 2 | E68: Towns with March Elections | F68: Mail Elections
A69: =+Dates!$D$9-70 -> 41639 | B69: =+Dates!$D$9-56 -> 41653 | C69: Secretary of State: Candidate filing period for March township elections— Between 70 and 56 days before the election. Minn. Stat. §205.13, subd.1a | D69: 205.13, subd. 1a | E69: Secretary of State | F69: Filing
A70: =+Dates!$D$9-70 -> 41639 | B70: =+Dates!$D$9-56 -> 41653 | C70: Campaign Finance: Candidate filing period for March township elections— Between 70 and 56 days before the election. Minn. Stat. § 205.13, subd.1a | D70: 205.13, subd. 1a | E70: Campaign Finance | F70: Filing
A71: =+Dates!$D$9-70 -> 41639 | B71: =+Dates!$D$9-56 -> 41653 | C71: Counties: Candidate filing period for March township elections— Between 70 and 56 days before the election. Minn. Stat. §205.13, subd.1a | D71: 205.13, subd. 1a | E71: Counties | F71: Filing
A72: =+Dates!$D$9-70 -> 41639 | B72: =+Dates!$D$9-56 -> 41653 | C72: Towns with March Elections: Candidate filing period for March township elections— Between 70 and 56 days before the election. Minn. Stat. § 205.13, subd.1a | D72: 205.13, subd. 1a | E72: Towns with March Elections | F72: Filing
A73: =+Dates!$D$13 -> 41640 | B73: =+Dates!$D$13 -> 41640 | C73: New Year's Day Holiday. No public business shall be transacted, except in cases of necessity. Minn. Stat. §645.44, subd.5 | D73: 645.44, subd. 5 | E73: Holiday | F73: Holiday
A74: 41640 | B74: 41640 | C74: Secretary of State: Annual List Maintenance (ALM). After the close of the calendar year, the OSS shall determine if any registrants have not voted during the preceding four years. Those records will be changed to the status of "inactive." The OSS prepares a report to the county auditor containing the names of all registrants whose status was changed to "inactive." Minn. Stat. §201.171 | D74: 201.171 | E74: Secretary of State | F74: Reg.
A75: 41640 | B75: 41640 | C75: Campaign Finance: Annual List Maintenance (ALM). After the close of the calendar year, the OSS shall determine if any registrants have not voted during the preceding four years. Those records will be changed to the status of "inactive." The OSS prepares a report to the county auditor containing the names of all registrants whose status was changed to "inactive." Minn. Stat. §201.171 | D75: 201.171 | E75: Campaign Finance | F75: Reg.
A76: 41640 | B76: 41640 | C76: Political Parties: Annual List Maintenance (ALM). After the close of the calendar year, the OSS shall determine if any registrants have not voted during the preceding four years. Those records will be changed to the status of "inactive." The OSS prepares a report to the county auditor containing the names of all registrants whose status was changed to "inactive." Minn. Stat. §201.171 | D76: 201.171 | E76: Political Parties | F76: Reg.
A77: 41640 | B77: 41640 | C77: Counties: Annual List Maintenance (ALM). After the close of the calendar year, the OSS shall determine if any registrants have not voted during the preceding four years. Those records will be changed to the status of "inactive." The OSS prepares a report to the county auditor containing the names of all registrants whose status was changed to "inactive." Minn. Stat. §201.171 | D77: 201.171 | E77: Counties | F77: Reg.
A78: 41640 | B78: 41640 | C78: Soil and Water Conservation Districts: Annual List Maintenance (ALM). After the close of the calendar year, the OSS shall determine if any registrants have not voted during the preceding four years. Those records will be changed to the status of "inactive." The OSS prepares a report to the county auditor containing the names of all registrants whose status was changed to "inactive." Minn. Stat. §201.171 | D78: 201.171 | E78: Soil & Water Conservation Dist. | F78: Reg.
A79: 41640 | B79: 41640 | C79: Cities with a Primary: Annual List Maintenance (ALM). After the close of the calendar year, the OSS shall determine if any registrants have not voted during the preceding four years. Those records will be changed to the status of "inactive." The OSS prepares a report to the county auditor containing the names of all registrants whose status was changed to "inactive." Minn. Stat. §201.171 | D79: 201.171 | E79: Cities with a Primary | F79: Reg.
A80: 41640 | B80: 41640 | C80: Cities without a Primary: Annual List Maintenance (ALM). After the close of the calendar year, the OSS shall determine if any registrants have not voted during the preceding four years. Those records will be changed to the status of "inactive." The OSS prepares a report to the county auditor containing the names of all registrants whose status was changed to "inactive." Minn. Stat. §201.171 | D80: 201.171 | E80: Cities without a Primary | F80: Reg.
A81: 41640 | B81: 41640 | C81: Towns with March Elections: Annual List Maintenance (ALM). After the close of the calendar year, the OSS shall determine if any registrants have not voted during the preceding four years. Those records will be changed to the status of "inactive." The OSS prepares a report to the county auditor containing the names of all registrants whose status was changed to "inactive." Minn. Stat. §201.171 | D81: 201.171 | E81: Towns with March Elections | F81: Reg.
A82: 41640 | B82: 41640 | C82: Towns with November Elections: Annual List Maintenance (ALM). After the close of the calendar year, the OSS shall determine if any registrants have not voted during the preceding four years. Those records will be changed to the status of "inactive." The OSS prepares a report to the county auditor containing the names of all registrants whose status was changed to "inactive." Minn. Stat. §201.171 | D82: 201.171 | E82: Towns with November Elections | F82: Reg.
A83: 41640 | B83: 41640 | C83: School Districts with a Primary: Annual List Maintenance (ALM). After the close of the calendar year, the OSS shall determine if any registrants have not voted during the preceding four years. Those records will be changed to the status of "inactive." The OSS prepares a report to the county auditor containing the names of all registrants whose status was changed to "inactive." Minn. Stat. §201.171 | D83: 201.171 | E83: School Districts with a Primary | F83: Reg.
A84: 41640 | B84: 41640 | C84: School Districts without a Primary: Annual List Maintenance (ALM). After the close of the calendar year, the OSS shall determine if any registrants have not voted during the preceding four years. Those records will be changed to the status of "inactive." The OSS prepares a report to the county auditor containing the names of all registrants whose status was changed to "inactive." Minn. Stat. §201.171 | D84: 201.171 | E84: School Districts without a Primary | F84: Reg.
A85: 41640 | B85: 41640 | C85: Hospital Districts: Annual List Maintenance (ALM). After the close of the calendar year, the OSS shall determine if any registrants have not voted during the preceding four years. Those records will be changed to the status of "inactive." The OSS prepares a report to the county auditor containing the names of all registrants whose status was changed to "inactive." Minn. Stat. §201.171 | D85: 201.171 | E85: Hospital Districts | F85: Reg.
... A87: 41640 | B87: 41640 | C87: Counties: The OSS must provide county auditors with Dept of Corrections data - as part of ALM. Minn. Stat. §201.157 | D87: 201.157 | E87: Counties | F87: Reg.
A88: 41640 | B88: =+Dates!$D$11 -> 41947 | C88: Secretary of State: Initial Campaign Financial Report due within 14 days of raising or spending more than $750. Minn. Stat. §211A.02, subd. 1 | D88: 211A.02, subd. 1 | E88: Secretary of State | F88: Filing
A89: 41640 | B89: =+Dates!$D$11 -> 41947 | C89: Campaign Finance: Initial Campaign Financial Report due within 14 days of raising or spending more than $750. Minn. Stat. §211A.02, subd. 1 | D89: 211A.02, subd. 1 | E89: Campaign Finance | F89: Filing
A90: 41640 | B90: =+Dates!$D$11 -> 41947 | C90: Political Parties: Initial Campaign Financial Report due within 14 days of raising or spending more than $750. Minn. Stat. §211A.02, subd. 1 | D90: 211A.02, subd. 1 | E90: Political Parties | F90: Filing
A91: =+Dates!$D$8 -> 41645 | B91: =+Dates!$D$8 -> 41645 | C91: Secretary of State: Terms begin for city, town, and school district officers elected at the November 2013 General Election - first Monday in January. Minn. Stat. §412.02, subd. 2; §367.03, subd. 4; 123B.09 | D91: 412.02, subd. 2; 367.03, subd. 4; 123B.09 | E91: Secretary of State | F91: After the Election
A92: =+Dates!$D$8 -> 41645 | B92: =+Dates!$D$8 -> 41645 | C92: Counties: Terms begin for city, town, and school district officers elected at the November 2013 General Election - first Monday in January. Minn. Stat. §412.02, subd. 2; 367.03, subd. 4; 123B.09 , subd. 1 | D92: 412.02, subd. 2; 367.03, subd. 4; 123B.09, subd. 1 | E92: Counties | F92: After the Election
A93: =+Dates!$D$8 -> 41645 | B93: =+Dates!$D$8 -> 41645 | C93: Cities without a Primary: Terms begin for officers elected at the November 2013 General Election - first Monday in January. Minn. Stat. §412.02, subd. 2 | D93: 412.02, subd. 2 | E93: Cities without a Primary | F93: After the Election
A94: =+Dates!$D$8 -> 41645 | B94: =+Dates!$D$8 -> 41645 | C94: Cities with a Primary: Terms begin for officers elected at the November 2013 General Election - first Monday in January. Minn. Stat. §412.02, subd. 2 | D94: 412.02, subd. 2 | E94: Cities with a Primary | F94: After the Election
A95: =+Dates!$D$8 -> 41645 | B95: =+Dates!$D$8 -> 41645 | C95: Towns with November Elections: Terms begin for township officers elected at the November 2013 General Election - first Monday in January. Minn. Stat. §367.03, subd. 4 | D95: 367.03, subd.4 | E95: Towns with November Elections | F95: After the Election
A96: =+Dates!$D$8 -> 41645 | B96: =+Dates!$D$8 -> 41645 | C96: School Districts with a Primary: Terms begin for school district officers elected at the November 2013 General Election - first Monday in January. Minn. Stat. §123B.09, subd. 1 | D96: 123B.09, subd. 1 | E96: School Districts with a Primary | F96: After the Election
A97: =+Dates!$D$8 -> 41645 | B97: =+Dates!$D$8 -> 41645 | C97: School Districts without a Primary: Terms begin for school district officers elected at the November 2013 General Election - first Monday in January. Minn. Stat. §123B.09, subd. 1 | D97: 123B.09, subd. 1 | E97: School Districts without a Primary | F97: After the Election
A98: =+Dates!$D$9-62 -> 41647 | B98: =+Dates!$D$9-62 -> 41647 | C98: Secretary of State: Secretary of State must send Example Ballot to township clerk - 30 days before absentee ballots must be made available. Minn. Stat. §205.17, subd. 7 | D98: 205.17, subd. 7 | E98: Secretary of State | F98: Ballots
A99: =+Dates!$D$9-62 -> 41647 | B99: =+Dates!$D$9-62 -> 41647 | C99: Counties: Secretary of State must send Example Ballot to township clerk - 30 days before absentee ballots must be made available. Minn. Stat. §205.17, subd. 7 | D99: 205.17, subd. 7 | E99: Counties | F99: Ballots
A100: =+Dates!$D$9-62 -> 41647 | B100: =+Dates!$D$9-62 -> 41647 | C100: Towns with March Elections: Secretary of State must send Example Ballots to township clerk - 30 days before absentee ballots must be made available. Minn. Stat. §205.17, subd. 7 | D100: 205.17, subd. 7 | E100: Towns with March Elections | F100: Ballots
A101: =+Dates!$D$9-60 -> 41649 | B101: =+Dates!$D$9-60 -> 41649 | C101: Towns with March Elections: Last day to disseminate information to the public about the use of a new voting system – at least 60 days prior to the election. Minn. Stat. §206.58, subd. 1 | D101: 206.58, subd. 1 | E101: Towns with March Elections | F101: Equipment
A102: 41652 | B102: 41656 | C102: Counties: MACO winter conference. | E102: Counties
A103: 41652 | B103: 41656 | C103: Secretary of State: MACO winter conference. | E103: Secretary of State
A104: =+Dates!$D$9-56 -> 41653 | B104: =+Dates!$D$9-56 -> 41653 | C104: Secretary of State: Candidate filing closes for March township elections - 56 days before the election. The municipal clerk's office must be open for filing from 1:00 p.m. to 5:00 p.m. on the last day of the filing period. Minn. Stat.§205.13, subd. 1a | D104: 205.13, subd. 1a | E104: Secretary of State | F104: Filing
A105: =+Dates!$D$9-56 -> 41653 | B105: =+Dates!$D$9-56 -> 41653 | C105: Counties: Candidate filing closes for March township elections - 56 days before the election. The municipal clerk's office must be open for filing from 1:00 p.m. to 5:00 p.m. on the last day of the filing period. Minn. Stat.§205.13, subd. 1a | D105: 205.13, subd. 1a | E105: Counties | F105: Filing
A106: =+Dates!$D$9-56 -> 41653 | B106: =+Dates!$D$9-56 -> 41653 | C106: Towns with March Elections: Candidate filing closes for March township elections - 56 days before the election. The municipal clerk's office must be open for filing from 1:00 p.m. to 5:00 p.m. on the last day of the filing period. Minn. Stat.§205.13, subd. 1a | D106: 205.13, subd. 1a | E106: Towns with March Elections | F106: Filing
A107: =+Dates!$D$9-56 -> 41653 | B107: =+Dates!$D$9-56 -> 41653 | C107: Campaign Finance: Candidate filing closes for March township elections - 56 days before the election. The municipal clerk's office must be open for filing from 1:00 p.m. to 5:00 p.m. on the last day of the filing period. Minn. Stat.§205.13, subd. 1a | D107: 205.13, subd. 1a | E107: Campaign Finance | F107: Filing
A108: =+Dates!$D$9-56 -> 41653 | B108: =+Dates!$D$9+56 -> 41765 | C108: Secretary of State: A special election may not be held during the 56 days before and the 56 days after a regularly scheduled primary or general election [March township elections] conducted wholly or partially within the school district/hospital district. Minn. Stat. §§205A.05, subd. 1; 447.32, subd 2 | D108: 205A.05, subd. 1; 447.32, subd. 2 | E108: Secretary of State | F108: Special Elections
A109: =+Dates!$D$9-56 -> 41653 | B109: =+Dates!$D$9+56 -> 41765 | C109: Counties: A special election may not be held during the 56 days before and the 56 days after a regularly scheduled primary or general election [March township elections] conducted wholly or partially within the school district/hospital district. Minn. Stat. §205A.05, subd. 1;447.32, subd 2 | D109: 205A.05, subd. 1; 447.32, subd. 2 | E109: Counties | F109: Special Elections
A110: =+Dates!$D$9-56 -> 41653 | B110: =+Dates!$D$9+56 -> 41765 | C110: School Districts with a Primary: A special election may not be held during the 56 days before and the 56 days after a regularly scheduled primary or general election [March township elections] conducted wholly or partially within the school district. Minn. Stat. §205A.05, subd. 1 | D110: 205A.05, subd. 1 | E110: School Districts with a Primary | F110: Special Elections
A111: =+Dates!$D$9-56 -> 41653 | B111: =+Dates!$D$9+56 -> 41765 | C111: School Districts without a Primary: A special election may not be held during the 56 days before and the 56 days after a regularly scheduled primary or general election [March township elections] conducted wholly or partially within the school district. Minn. Stat. §205A.05, subd. 1 | D111: 205A.05, subd. 1 | E111: School Districts without a Primary | F111: Special Elections
A112: =+Dates!$D$9-56 -> 41653 | B112: =+Dates!$D$9+56 -> 41765 | C112: Hospital Districts: A special election may not be conducted either during the 56 days before or the 56 days after a regularly scheduled primary or general election [March township elections] conducted wholly or partially within the hospital district. Minn. Stat. §447.32, subd. 2 | D112: 447.32, subd. 2 | E112: Hospital Districts | F112: Special Elections
...

Sheet 1
A3: l;l | B3: kk | C3: kk
A28: Begin Date | B28: End Date | C28: Bolded type indicates subdivision affected: | D28: Statute § | E28: Affected | F28: Reference

Sheet 2

Sheet 3

Sheet 4

Sheet 5

Sheet 6

Sheet 7

Sheet 8

Sheet 9

Sheet 10

Sheet 11

Sheet 12

Sheet 13

Sheet 14

Sheet 15

Sheet 16
