Workbook

Sheet 1 - BCA 20-year (Recent)
B1: ATTACHMENT 1: BENEFIT-COST ANALYSIS
B3: Vasco Road Safety Improvements Project - Phase 2
B4: TIGER V Grant Application
C7: Beneift/Cost Ratio = | D7: Total Benefits | E7: = | F7: =I62 -> 62225735 | G7: = | H7: =F7/F8 -> 3.9699183 | I7: (3% Discount)
D8: Total Costs | F8: =G89 -> 15674311
F10: =+J62 -> 44283283 | G10: = | H10: =F10/F11 -> 3.053039 | I10: (7% Discount)
F11: =H89 -> 14504657
B13: Benefits
B14: Calendar Year | C14: Project Year | D14: Affected drivers4 | E14: Average Travel Time saved (veh-hrs)5 | F14: Value of Travel Time Benefits (Surface modes)2,3 | G14: Value of Travel Time Benefits (Truck Drivers)2,3 | H14: Total Value of Travel Time Benefits | I14: Total Present Value of Travel Time Benefits - 3% Discount (2013 dollars)1 | J14: Total Present Value of Travel Time Benefits - 7% Discount (2013 dollars)1
B15: 2014 | C15: 0 | D15: 23740 | E15: - | F15: 0 | G15: 0 | H15: 0 | I15: 0 | J15: 0
B16: 2015 | C16: 1 | D16: =+D15*1.015 -> 24096.1 | E16: 0.3 | F16: =D16*E16*$H$99*(1-$E$96) -> 115704.93 | G16: =D16*E16*$H$100*$E$96 -> 6878.9598 | H16: =SUM(F16:G16) -> 122583.89 | I16: =H16/((1+$E$92)^C16) -> 119013.48 | J16: =H16/((1+$E$93)^C16) -> 114564.38
B17: 2016 | C17: 2 | D17: =+D16*1.015 -> 24457.541 | E17: 0.3 | F17: =D17*E17*$H$99*(1-$E$96) -> 117440.5 | G17: =D17*E17*$H$100*$E$96 -> 6982.1442 | H17: =SUM(F17:G17) -> 124422.65 | I17: =H17/((1+$E$92)^C17) -> 117280.28 | J17: =H17/((1+$E$93)^C17) -> 108675.56
B18: 2017 | C18: 3 | D18: =+D17*1.015 -> 24824.405 | E18: 0.3 | F18: =D18*E18*$H$99*(1-$E$96) -> 119202.11 | G18: =D18*E18*$H$100*$E$96 -> 7086.8764 | H18: =SUM(F18:G18) -> 126288.98 | I18: =H18/((1+$E$92)^C18) -> 115572.31 | J18: =H18/((1+$E$93)^C18) -> 103089.43
B19: 2018 | C19: 4 | D19: =+D18*1.015 -> 25196.771 | E19: 0.3 | F19: =D19*E19*$H$99*(1-$E$96) -> 120990.14 | G19: =D19*E19*$H$100*$E$96 -> 7193.1795 | H19: =SUM(F19:G19) -> 128183.32 | I19: =H19/((1+$E$92)^C19) -> 113889.22 | J19: =H19/((1+$E$93)^C19) -> 97790.441
B20: 2019 | C20: 5 | D20: =+D19*1.015 -> 25574.722 | E20: 0.3 | F20: =D20*E20*$H$99*(1-$E$96) -> 122804.99 | G20: =D20*E20*$H$100*$E$96 -> 7301.0772 | H20: =SUM(F20:G20) -> 130106.07 | I20: =H20/((1+$E$92)^C20) -> 112230.64 | J20: =H20/((1+$E$93)^C20) -> 92763.829
B21: 2020 | C21: 6 | D21: =+D20*1.015 -> 25958.343 | E21: 0.3 | F21: =D21*E21*$H$99*(1-$E$96) -> 124647.07 | G21: =D21*E21*$H$100*$E$96 -> 7410.5934 | H21: =SUM(F21:G21) -> 132057.66 | I21: =H21/((1+$E$92)^C21) -> 110596.21 | J21: =H21/((1+$E$93)^C21) -> 87995.595
B22: 2021 | C22: 7 | D22: =+D21*1.015 -> 26347.718 | E22: 0.3 | F22: =D22*E22*$H$99*(1-$E$96) -> 126516.77 | G22: =D22*E22*$H$100*$E$96 -> 7521.7523 | H22: =SUM(F22:G22) -> 134038.53 | I22: =H22/((1+$E$92)^C22) -> 108985.59 | J22: =H22/((1+$E$93)^C22) -> 83472.457
B23: 2022 | C23: 8 | D23: =+D22*1.015 -> 26742.934 | E23: 0.3 | F23: =D23*E23*$H$99*(1-$E$96) -> 128414.52 | G23: =D23*E23*$H$100*$E$96 -> 7634.5786 | H23: =SUM(F23:G23) -> 136049.1 | I23: =H23/((1+$E$92)^C23) -> 107398.42 | J23: =H23/((1+$E$93)^C23) -> 79181.817
B24: 2023 | C24: 9 | D24: =+D23*1.015 -> 27144.078 | E24: 0.3 | F24: =D24*E24*$H$99*(1-$E$96) -> 130340.74 | G24: =D24*E24*$H$100*$E$96 -> 7749.0972 | H24: =SUM(F24:G24) -> 138089.84 | I24: =H24/((1+$E$92)^C24) -> 105834.36 | J24: =H24/((1+$E$93)^C24) -> 75111.723
B25: 2024 | C25: 10 | D25: =+D24*1.015 -> 27551.239 | E25: 0.3 | F25: =D25*E25*$H$99*(1-$E$96) -> 132295.85 | G25: =D25*E25*$H$100*$E$96 -> 7865.3337 | H25: =SUM(F25:G25) -> 140161.19 | I25: =H25/((1+$E$92)^C25) -> 104293.09 | J25: =H25/((1+$E$93)^C25) -> 71250.84
B26: 2025 | C26: 11 | D26: =+D25*1.015 -> 27964.508 | E26: 0.3 | F26: =D26*E26*$H$99*(1-$E$96) -> 134280.29 | G26: =D26*E26*$H$100*$E$96 -> 7983.3137 | H26: =SUM(F26:G26) -> 142263.61 | I26: =H26/((1+$E$92)^C26) -> 102774.26 | J26: =H26/((1+$E$93)^C26) -> 67588.414
B27: 2026 | C27: 12 | D27: =+D26*1.015 -> 28383.975 | E27: 0.3 | F27: =D27*E27*$H$99*(1-$E$96) -> 136294.5 | G27: =D27*E27*$H$100*$E$96 -> 8103.0634 | H27: =SUM(F27:G27) -> 144397.56 | I27: =H27/((1+$E$92)^C27) -> 101277.54 | J27: =H27/((1+$E$93)^C27) -> 64114.243
... B35: 2034 | C35: 20 | D35: =+D34*1.015 -> 31974.338 | E35: 0.3 | F35: =D35*E35*$H$99*(1-$E$96) -> 153534.74 | G35: =D35*E35*$H$100*$E$96 -> 9128.0408 | H35: =SUM(F35:G35) -> 162662.78 | I35: =H35/((1+$E$92)^C35) -> 90062.437 | J35: =H35/((1+$E$93)^C35) -> 42035.153
I36: =SUM(I15:I35) -> 2078034.2 | J36: =SUM(J15:J35) -> 1453058.3
B38: Calendar Year | C38: Project Year | D38: Average Annual Injuries Prevented6 | E38: Average Annual Fatalities Prevented6 | F38: Value of Injury Benefits7 | G38: Value of Fatality Benefits7 | H38: Total Value of Collision Benefits | I38: Total Present Value of Collision Benefits - 3% Discount (2013 dollars)1 | J38: Total Present Value of Collision Benefits - 7% Discount (2013 dollars)1
B39: 2014 | C39: 0 | D39: - | E39: - | F39: 0 | G39: 0 | H39: 0 | I39: 0 | J39: 0
B40: 2015 | C40: 1 | D40: ='6 - 5yr Collision (Recent)'!$E$37 -> 4.8 | E40: ='6 - 5yr Collision (Recent)'!$E$38 -> 0.4 | F40: ='7 - Collision Benefits'!$H$17 -> 402870.26 | G40: ='7 - Collision Benefits'!$E$17 -> 3640000 | H40: =F40+G40 -> 4042870.3 | I40: =H40/((1+$E$92)^C40) -> 3925116.8 | J40: =H40/((1+$E$93)^C40) -> 3778383.4
B41: 2016 | C41: 2 | D41: ='6 - 5yr Collision (Recent)'!$E$37 -> 4.8 | E41: ='6 - 5yr Collision (Recent)'!$E$38 -> 0.4 | F41: ='7 - Collision Benefits'!$H$17 -> 402870.26 | G41: ='7 - Collision Benefits'!$E$17 -> 3640000 | H41: =F41+G41 -> 4042870.3 | I41: =H41/((1+$E$92)^C41) -> 3810793 | J41: =H41/((1+$E$93)^C41) -> 3531199.5
B42: 2017 | C42: 3 | D42: ='6 - 5yr Collision (Recent)'!$E$37 -> 4.8 | E42: ='6 - 5yr Collision (Recent)'!$E$38 -> 0.4 | F42: ='7 - Collision Benefits'!$H$17 -> 402870.26 | G42: ='7 - Collision Benefits'!$E$17 -> 3640000 | H42: =F42+G42 -> 4042870.3 | I42: =H42/((1+$E$92)^C42) -> 3699799 | J42: =H42/((1+$E$93)^C42) -> 3300186.4
B43: 2018 | C43: 4 | D43: ='6 - 5yr Collision (Recent)'!$E$37 -> 4.8 | E43: ='6 - 5yr Collision (Recent)'!$E$38 -> 0.4 | F43: ='7 - Collision Benefits'!$H$17 -> 402870.26 | G43: ='7 - Collision Benefits'!$E$17 -> 3640000 | H43: =F43+G43 -> 4042870.3 | I43: =H43/((1+$E$92)^C43) -> 3592037.9 | J43: =H43/((1+$E$93)^C43) -> 3084286.4
B44: 2019 | C44: 5 | D44: ='6 - 5yr Collision (Recent)'!$E$37 -> 4.8 | E44: ='6 - 5yr Collision (Recent)'!$E$38 -> 0.4 | F44: ='7 - Collision Benefits'!$H$17 -> 402870.26 | G44: ='7 - Collision Benefits'!$E$17 -> 3640000 | H44: =F44+G44 -> 4042870.3 | I44: =H44/((1+$E$92)^C44) -> 3487415.4 | J44: =H44/((1+$E$93)^C44) -> 2882510.6
B45: 2020 | C45: 6 | D45: ='6 - 5yr Collision (Recent)'!$E$37 -> 4.8 | E45: ='6 - 5yr Collision (Recent)'!$E$38 -> 0.4 | F45: ='7 - Collision Benefits'!$H$17 -> 402870.26 | G45: ='7 - Collision Benefits'!$E$17 -> 3640000 | H45: =F45+G45 -> 4042870.3 | I45: =H45/((1+$E$92)^C45) -> 3385840.2 | J45: =H45/((1+$E$93)^C45) -> 2693935.2
B46: 2021 | C46: 7 | D46: ='6 - 5yr Collision (Recent)'!$E$37 -> 4.8 | E46: ='6 - 5yr Collision (Recent)'!$E$38 -> 0.4 | F46: ='7 - Collision Benefits'!$H$17 -> 402870.26 | G46: ='7 - Collision Benefits'!$E$17 -> 3640000 | H46: =F46+G46 -> 4042870.3 | I46: =H46/((1+$E$92)^C46) -> 3287223.5 | J46: =H46/((1+$E$93)^C46) -> 2517696.4
B47: 2022 | C47: 8 | D47: ='6 - 5yr Collision (Recent)'!$E$37 -> 4.8 | E47: ='6 - 5yr Collision (Recent)'!$E$38 -> 0.4 | F47: ='7 - Collision Benefits'!$H$17 -> 402870.26 | G47: ='7 - Collision Benefits'!$E$17 -> 3640000 | H47: =F47+G47 -> 4042870.3 | I47: =H47/((1+$E$92)^C47) -> 3191479.1 | J47: =H47/((1+$E$93)^C47) -> 2352987.3
B48: 2023 | C48: 9 | D48: ='6 - 5yr Collision (Recent)'!$E$37 -> 4.8 | E48: ='6 - 5yr Collision (Recent)'!$E$38 -> 0.4 | F48: ='7 - Collision Benefits'!$H$17 -> 402870.26 | G48: ='7 - Collision Benefits'!$E$17 -> 3640000 | H48: =F48+G48 -> 4042870.3 | I48: =H48/((1+$E$92)^C48) -> 3098523.4 | J48: =H48/((1+$E$93)^C48) -> 2199053.6
B49: 2024 | C49: 10 | D49: ='6 - 5yr Collision (Recent)'!$E$37 -> 4.8 | E49: ='6 - 5yr Collision (Recent)'!$E$38 -> 0.4 | F49: ='7 - Collision Benefits'!$H$17 -> 402870.26 | G49: ='7 - Collision Benefits'!$E$17 -> 3640000 | H49: =F49+G49 -> 4042870.3 | I49: =H49/((1+$E$92)^C49) -> 3008275.2 | J49: =H49/((1+$E$93)^C49) -> 2055190.2
B50: 2025 | C50: 11 | D50: ='6 - 5yr Collision (Recent)'!$E$37 -> 4.8 | E50: ='6 - 5yr Collision (Recent)'!$E$38 -> 0.4 | F50: ='7 - Collision Benefits'!$H$17 -> 402870.26 | G50: ='7 - Collision Benefits'!$E$17 -> 3640000 | H50: =F50+G50 -> 4042870.3 | I50: =H50/((1+$E$92)^C50) -> 2920655.5 | J50: =H50/((1+$E$93)^C50) -> 1920738.5
B51: 2026 | C51: 12 | D51: ='6 - 5yr Collision (Recent)'!$E$37 -> 4.8 | E51: ='6 - 5yr Collision (Recent)'!$E$38 -> 0.4 | F51: ='7 - Collision Benefits'!$H$17 -> 402870.26 | G51: ='7 - Collision Benefits'!$E$17 -> 3640000 | H51: =F51+G51 -> 4042870.3 | I51: =H51/((1+$E$92)^C51) -> 2835587.9 | J51: =H51/((1+$E$93)^C51) -> 1795082.7
... B59: 2034 | C59: 20 | D59: ='6 - 5yr Collision (Recent)'!$E$37 -> 4.8 | E59: ='6 - 5yr Collision (Recent)'!$E$38 -> 0.4 | F59: ='7 - Collision Benefits'!$H$17 -> 402870.26 | G59: ='7 - Collision Benefits'!$E$17 -> 3640000 | H59: =F59+G59 -> 4042870.3 | I59: =H59/((1+$E$92)^C59) -> 2238439.2 | J59: =H59/((1+$E$93)^C59) -> 1044754.5
I60: =SUM(I39:I59) -> 60147701 | J60: =SUM(J39:J59) -> 42830225
H62: Total Benefits | I62: =I36+I60 -> 62225735 | J62: =J36+J60 -> 44283283
B64: Costs
B65: Calendar Year | C65: Project Year | D65: Project Costs | E65: Operations and Maintenance Costs8 | F65: Total Project Costs | G65: Total Present Value of Collision Costs - 3% Discount (2013 dollars)1 | H65: Total Present Value of Collision Costs - 7% Discount (2013 dollars)1
B66: 2014 | C66: 0 | D66: 2711750 | E66: 0 | F66: =D66+E66 -> 2711750 | G66: =F66/((1+$E$92)^C66) -> 2711750 | H66: =F66/((1+$E$93)^C66) -> 2711750
B67: 2015 | C67: 1 | D67: 5000000 | E67: 0 | F67: =D67+E67 -> 5000000 | G67: =F67/((1+$E$92)^C67) -> 4854368.9 | H67: =F67/((1+$E$93)^C67) -> 4672897.2
B68: 2016 | C68: 2 | D68: 7288250 | E68: 0 | F68: =D68+E68 -> 7288250 | G68: =F68/((1+$E$92)^C68) -> 6869874.6 | H68: =F68/((1+$E$93)^C68) -> 6365839.8
B69: 2017 | C69: 3 | D69: 0 | E69: ='8 - O&M Costs'!$B$6 -> 20000 | F69: =D69+E69 -> 20000 | G69: =F69/((1+$E$92)^C69) -> 18302.833 | H69: =F69/((1+$E$93)^C69) -> 16325.958
B70: 2018 | C70: 4 | D70: 0 | E70: ='8 - O&M Costs'!$B$6 -> 20000 | F70: =D70+E70 -> 20000 | G70: =F70/((1+$E$92)^C70) -> 17769.741 | H70: =F70/((1+$E$93)^C70) -> 15257.904
B71: 2019 | C71: 5 | D71: 0 | E71: ='8 - O&M Costs'!$B$6 -> 20000 | F71: =D71+E71 -> 20000 | G71: =F71/((1+$E$92)^C71) -> 17252.176 | H71: =F71/((1+$E$93)^C71) -> 14259.724
B72: 2020 | C72: 6 | D72: 0 | E72: ='8 - O&M Costs'!$B$6 -> 20000 | F72: =D72+E72 -> 20000 | G72: =F72/((1+$E$92)^C72) -> 16749.685 | H72: =F72/((1+$E$93)^C72) -> 13326.844
B73: 2021 | C73: 7 | D73: 0 | E73: ='8 - O&M Costs'!$B$6 -> 20000 | F73: =D73+E73 -> 20000 | G73: =F73/((1+$E$92)^C73) -> 16261.83 | H73: =F73/((1+$E$93)^C73) -> 12454.995
B74: 2022 | C74: 8 | D74: 0 | E74: ='8 - O&M Costs'!$B$6 -> 20000 | F74: =D74+E74 -> 20000 | G74: =F74/((1+$E$92)^C74) -> 15788.185 | H74: =F74/((1+$E$93)^C74) -> 11640.182
B75: 2023 | C75: 9 | D75: 0 | E75: ='8 - O&M Costs'!$B$6 -> 20000 | F75: =D75+E75 -> 20000 | G75: =F75/((1+$E$92)^C75) -> 15328.335 | H75: =F75/((1+$E$93)^C75) -> 10878.675
B76: 2024 | C76: 10 | D76: 0 | E76: ='8 - O&M Costs'!E15 -> 774400 | F76: =D76+E76 -> 774400 | G76: =F76/((1+$E$92)^C76) -> 576226.33 | H76: =F76/((1+$E$93)^C76) -> 393665.69
B77: 2025 | C77: 11 | D77: 0 | E77: ='8 - O&M Costs'!$B$6 -> 20000 | F77: =D77+E77 -> 20000 | G77: =F77/((1+$E$92)^C77) -> 14448.426 | H77: =F77/((1+$E$93)^C77) -> 9501.8559
B78: 2026 | C78: 12 | D78: 0 | E78: ='8 - O&M Costs'!$B$6 -> 20000 | F78: =D78+E78 -> 20000 | G78: =F78/((1+$E$92)^C78) -> 14027.598 | H78: =F78/((1+$E$93)^C78) -> 8880.2392
B79: 2027 | C79: 13 | D79: 0 | E79: ='8 - O&M Costs'!$B$6 -> 20000 | F79: =D79+E79 -> 20000 | G79: =F79/((1+$E$92)^C79) -> 13619.027 | H79: =F79/((1+$E$93)^C79) -> 8299.289
B80: 2028 | C80: 14 | D80: 0 | E80: ='8 - O&M Costs'!$B$6 -> 20000 | F80: =D80+E80 -> 20000 | G80: =F80/((1+$E$92)^C80) -> 13222.356 | H80: =F80/((1+$E$93)^C80) -> 7756.3448
B81: 2029 | C81: 15 | D81: 0 | E81: ='8 - O&M Costs'!$B$6 -> 20000 | F81: =D81+E81 -> 20000 | G81: =F81/((1+$E$92)^C81) -> 12837.239 | H81: =F81/((1+$E$93)^C81) -> 7248.9204
B82: 2030 | C82: 16 | D82: 0 | E82: ='8 - O&M Costs'!$B$6 -> 20000 | F82: =D82+E82 -> 20000 | G82: =F82/((1+$E$92)^C82) -> 12463.339 | H82: =F82/((1+$E$93)^C82) -> 6774.692
B83: 2031 | C83: 17 | D83: 0 | E83: ='8 - O&M Costs'!$B$6 -> 20000 | F83: =D83+E83 -> 20000 | G83: =F83/((1+$E$92)^C83) -> 12100.329 | H83: =F83/((1+$E$93)^C83) -> 6331.4878
B84: 2032 | C84: 18 | D84: 0 | E84: ='8 - O&M Costs'!$B$6 -> 20000 | F84: =D84+E84 -> 20000 | G84: =F84/((1+$E$92)^C84) -> 11747.892 | H84: =F84/((1+$E$93)^C84) -> 5917.2783
B85: 2033 | C85: 19 | D85: 0 | E85: ='8 - O&M Costs'!$B$6 -> 20000 | F85: =D85+E85 -> 20000 | G85: =F85/((1+$E$92)^C85) -> 11405.721 | H85: =F85/((1+$E$93)^C85) -> 5530.1667
B86: 2034 | C86: 20 | D86: 0 | E86: ='8 - O&M Costs'!E15 -> 774400 | F86: =D86+E86 -> 774400 | G86: =F86/((1+$E$92)^C86) -> 428766.5 | H86: =F86/((1+$E$93)^C86) -> 200119.68
D87: =SUM(D66:D73) -> 15000000 | E87: =SUM(E66:E86) -> 1868800 | F87: =SUM(F66:F86) -> 16868800 | G87: =SUM(G66:G86) -> 15674311 | H87: =SUM(H66:H86) -> 14504657
F89: Total Costs | G89: =G63+G87 -> 15674311 | H89: =H63+H87 -> 14504657
B90: Assumptions:
A91: 1 | B91: Discount rate assumed for public expenditures per Federal Office of Management and Budget (OMB) Ciculars A-4 and A-94.
C92: Discount rate | E92: 0.03
C93: Discount rate | E93: 0.07
A94: 2 | B94: See Attachment 3: Truck Traffic. Percent truck traffic includes buses and is based on Truck Traffic Turning Movement Counts taken by the Contra Costa County
B95: Public Works Department from May 12-15, 2008.
C96: Percent Truck Traffic | E96: =649/15618 -> 0.041554616
A97: 3 | B97: Recommended hourly values of travel time savings taken from the US DOT memorandum "Revised Departmental Guidance on Valuation of
B98: Travel Time in Economic Analysis (Revision 2 - corrected)".
C99: Recommended Hourly Value of Travel Time Savings (Table 4, Intercity Personal) | H99: 16.7 | I99: per person-hour
C100: Recommended Hourly Value of Travel Time Savings (Table 4, Intercity Business) | H100: 22.9 | I100: per person-hour
A101: 4 | B101: See Attachment 2: Traffic Volumes. Affected drivers assuming straight-line approximation (1.5% annual increase) of future traffic volumes from the Contra Costa
B102: Transportation Authority Travel Demand Model, 2012.
A103: 5 | B103: See Attachment 4: Travel Time Savings. Average travel time saved calculated for peak 15-minute period per Chapter 20 - Two lane Highways, HCM 2000.
B104: Assuming a base free flow speed of 65 miles per hour and using vehicular traffic counts taken by the Contra Costa County Public Works Department on Vasco
B105: Road - 1 mile South of Camino Diablo on August 5, 2009.
A106: 6 | B106: See Attachment 5: Collision History and Attachment 6: 5-year Collision Data. Average annual collisions prevented based on analysis of 2008-2012 collisions data.
A107: 7 | B107: See Attachment 7: Collisions Benefits. Collisions Benefits calculated using AIS calculation.
A108: 8 | B108: See Attachment 8: Operations & Maintenance Costs for calculations of marginal costs.

Sheet 2 - Traffic Volumes
A1: ATTACHMENT 2: Average Daily Traffic (ADT)
A3: Existing Traffic Volumes: Vasco Road South of Camino Diablo
A4: Source: Vehicular Traffic Counts, Contra Costa County Public Works Department
H5: Northbound | M5: Southbound
H6: AM PEAK | J6: PM PEAK | M6: AM PEAK | O6: PM PEAK
A7: Year | B7: Date | D7: Northbound Volume | E7: Southbound Volume | F7: Total Daily Volume | H7: Volume | I7: Time | J7: Volume | K7: Time | M7: Volume | N7: Time | O7: Volume | P7: Time
A8: 2009 | B8: 40030 | D8: 9889 | E8: 9917 | F8: =SUM(D8:E8) -> 19806 | H8: 283 | I8: 1200 | J8: 1517 | K8: 1800 | M8: 1483 | N8: 645 | O8: 373 | P8: 1430
A9: 2008 | B9: 39666 | D9: 9887 | E9: 10001 | F9: =SUM(D9:E9) -> 19888 | H9: 296 | I9: 1200 | J9: 1575 | K9: 1800 | M9: 1539 | N9: 700 | O9: 361 | P9: 1630
A10: 2007 | B10: 39323 | D10: 10826 | E10: 10902 | F10: =SUM(D10:E10) -> 21728 | H10: 339 | I10: 1145 | J10: 1474 | K10: 1715 | M10: 1629 | N10: 645 | O10: 417 | P10: 1615
A11: 2006 | B11: 38931 | D11: 11122 | E11: 11313 | F11: =SUM(D11:E11) -> 22435 | H11: 379 | I11: 730 | J11: 1432 | K11: 1745 | M11: 1674 | N11: 630 | O11: 517 | P11: 1615
A12: 2005 | B12: 38548 | D12: 11375 | E12: 11064 | F12: =SUM(D12:E12) -> 22439 | H12: 390 | I12: 730 | J12: 1318 | K12: 1800 | M12: 1471 | N12: 945 | O12: 546 | P12: 1630
A13: 2004 | B13: 38077 | D13: 10864 | E13: 11254 | F13: =SUM(D13:E13) -> 22118 | H13: 391 | I13: 730 | J13: 1378 | K13: 1645 | M13: 1635 | N13: 630 | O13: 451 | P13: 1630
A14: 2003 | B14: 37817 | D14: 10911 | E14: 10833 | F14: =SUM(D14:E14) -> 21744 | H14: 378 | I14: 700 | J14: 1252 | K14: 1815 | M14: 1491 | N14: 730 | O14: 479 | P14: 1630
A15: 1997 | B15: 35537 | D15: 10326 | E15: 7757 | F15: =SUM(D15:E15) -> 18083 | H15: 424 | I15: 830 | J15: 1593 | K15: 1730 | M15: 1515 | N15: 700 | O15: 235 | P15: 1415
A16: 1996 | B16: 35193 | D16: 8152 | E16: 8170 | F16: =SUM(D16:E16) -> 16322 | H16: 224 | I16: 800 | J16: 1450 | K16: 1815 | M16: 1497 | N16: 715 | O16: 307 | P16: 1430
A19: Future Traffic Volumes
A20: Source: CCTA Decennial Model , Contra Costa Transportation Authority
A22: Vasco Road North of Camino Diablo
B23: SB | C23: NB | D23: Total | E23: % Increase
A24: 2000 | B24: 9577 | C24: 8819 | D24: =SUM(B24:C24) -> 18396 | E24: -
A25: 2030 | B25: 19215 | C25: 14003 | D25: =SUM(B25:C25) -> 33218 | E25: =(D25-D24)/D24 -> 0.80571863
A26: Annual Increase (%) | E26: =E25/30 -> 0.026857288
A28: Vasco Road South of Camino Diablo
B29: SB | C29: NB | D29: Total
A30: 2000 | B30: 10783 | C30: 8814 | D30: =SUM(B30:C30) -> 19597
A31: 2030 | B31: 14556 | C31: 13982 | D31: =SUM(B31:C31) -> 28538 | E31: =(D31-D30)/D30 -> 0.4562433
A32: Annual Increase (%) | E32: =E31/30 -> 0.01520811
A34: Vasco Road North of Alameda/Contra Costa County Line
B35: NB | C35: SB | D35: Total
A36: 2000 | B36: 8798 | C36: 10764 | D36: =SUM(B36:C36) -> 19562
A37: 2030 | B37: 13964 | C37: 14521 | D37: =SUM(B37:C37) -> 28485 | E37: =(D37-D36)/D36 -> 0.45613945
A38: Annual Increase (%) | E38: =E37/30 -> 0.015204648
H44: N/B or E/B DIRECTION | M44: S/B or W/B DIRECTION
D45: N/B | E45: S/B | F45: TOTAL | H45: AM PEAK | J45: PM PEAK | M45: AM PEAK | O45: PM PEAK
A46: Year | B46: DATE | D46: VOL | E46: VOL | F46: 24 HR | H46: VOL | I46: TIME | J46: VOL | K46: TIME | M46: VOL | N46: TIME | O46: VOL | P46: TIME
A47: 1996 | B47: 35193 | D47: 8152 | E47: 8170 | F47: =D47+E47 -> 16322 | H47: 224 | I47: 800 | J47: 1450 | K47: 1815 | M47: 1497 | N47: 715 | O47: 307 | P47: 1430
B48: 40030 | D48: 9936 | E48: 9756 | F48: =(D48+E48) -> 19692 | H48: 277 | I48: 1200 | J48: 1554 | K48: 1800 | M48: 1437 | N48: 645 | O48: 372 | P48: 1630
A49: 1997 | B49: 35537 | D49: 10326 | E49: 7757 | F49: =D49+E49 -> 18083 | H49: 424 | I49: 830 | J49: 1593 | K49: 1730 | M49: 1515 | N49: 700 | O49: 235 | P49: 1415
B50: 39666 | D50: 9886 | E50: 9844 | F50: =(D50+E50) -> 19730 | H50: 296 | I50: 1200 | J50: 1571 | K50: 1800 | M50: 1484 | N50: 700 | O50: 365 | P50: 1630
A51: 2003 | B51: 37817 | D51: 10911 | E51: 10833 | F51: =D51+E51 -> 21744 | H51: 378 | I51: 700 | J51: 1252 | K51: 1815 | M51: 1491 | N51: 730 | O51: 479 | P51: 1630
B52: 39323 | D52: 10784 | E52: 10909 | F52: =(D52+E52) -> 21693 | H52: 318 | I52: 1145 | J52: 1468 | K52: 1815 | M52: 1616 | N52: 645 | O52: 418 | P52: 1615
A53: 2004 | B53: 38077 | D53: 10864 | E53: 11254 | F53: =D53+E53 -> 22118 | H53: 391 | I53: 730 | J53: 1378 | K53: 1645 | M53: 1635 | N53: 630 | O53: 451 | P53: 1630
B54: 38931 | D54: 11116 | E54: 11278 | F54: =(D54+E54) -> 22394 | H54: 384 | I54: 730 | J54: 1489 | K54: 1730 | M54: 1672 | N54: 645 | O54: 509 | P54: 1615
B55: 38650 | D55: 10795 | E55: 11117 | F55: =(D55+E55) -> 21912 | H55: 396 | I55: 730 | J55: 1506 | K55: 1745 | M55: 1698 | N55: 630 | O55: 490 | P55: 1645
A56: 2005 | B56: 38548 | D56: 11375 | E56: 11064 | F56: =D56+E56 -> 22439 | H56: 390 | I56: 730 | J56: 1318 | K56: 1800 | M56: 1471 | N56: 945 | O56: 546 | P56: 1630
B57: 38329 | D57: 9519 | E57: 9562 | F57: =D57+E57 -> 19081 | H57: 280 | I57: 645 | J57: 1320 | K57: 1545 | M57: 1367 | N57: 530 | O57: 304 | P57: 1200
B58: 38076 | D58: 10689 | E58: 16696 | F58: =D58+E58 -> 27385 | H58: 373 | I58: 800 | J58: 1433 | K58: 1715 | M58: 1597 | N58: 630 | O58: ----- | P58: -----
B59: 38077 | D59: 10632 | E59: 11309 | F59: =D59+E59 -> 21941 | H59: 372 | I59: 730 | J59: 1340 | K59: 1630 | M59: 1590 | N59: 645 | O59: 490 | P59: 1630
A60: 2006 | B60: 38931 | D60: 11122 | E60: 11313 | F60: =(D60+E60) -> 22435 | H60: 379 | I60: 730 | J60: 1432 | K60: 1745 | M60: 1674 | N60: 630 | O60: 517 | P60: 1615
B61: 37944 | D61: 9762 | E61: 10825 | F61: =D61+E61 -> 20587 | H61: 412 | I61: 730 | J61: 1170 | K61: 1945 | M61: 1495 | N61: 645 | O61: 504 | P61: 1615
A62: 2007 | B62: 39323 | D62: 10826 | E62: 10902 | F62: =(D62+E62) -> 21728 | H62: 339 | I62: 1145 | J62: 1474 | K62: 1715 | M62: 1629 | N62: 645 | O62: 417 | P62: 1615
A63: 2008 | B63: 39666 | D63: 9887 | E63: 10001 | F63: =(D63+E63) -> 19888 | H63: 296 | I63: 1200 | J63: 1575 | K63: 1800 | M63: 1539 | N63: 700 | O63: 361 | P63: 1630
A64: 2009 | B64: 40030 | D64: 9889 | E64: 9917 | F64: =(D64+E64) -> 19806 | H64: 283 | I64: 1200 | J64: 1517 | K64: 1800 | M64: 1483 | N64: 645 | O64: 373 | P64: 1430
B94: See Appendix B: Truck Traffic. Percent truck traffic includes buses and is based on Truck Traffic Turning Movement Counts taken by the Contra Costa County
B95: Public Works Department from May 12-15, 2008.
B101: See Appendix A: Traffic Volumes. Affected drivers assuming straight-line approximation (1.5% annual increase) of future traffic volumes from the Contra Costa
B102: Transportation Authority Travel Demand Model, 2012.
B103: See Appendix C: Travel Time Savings. Average travel time saved calculated for peak 15-minute period per Chapter 20 - Two lane Highways, HCM 2000.

Sheet 3 - Truck Traffic
A1: ATTACHMENT 3: Truck Traffic
A3: Existing Truck Traffic
A4: Source: Truck Traffic Turning Movement Counts,
A5: Contra Costa County Public Works Department, May 12-15, 2008
A7: Vasco Road North of Camino Diablo (5:00-18:00)
B8: Number of Vehicles
A9: Truck Count | B9: 467
A10: Bus Count | B10: 10
A11: Traffic Count | B11: 13291
A12: Percentage of Truck Traffic | B12: =(B9+B10)/B11 -> 0.035888947
A14: Vasco Road South of Camino Diablo (5:00-18:00)
B15: Number of Vehicles
A16: Truck Count | B16: 642
A17: Bus Count | B17: 7
A18: Traffic Count | B18: 15618
A19: Percentage of Truck Traffic | B19: =(B16+B17)/B18 -> 0.041554616

Sheet 4 - Travel Time Savings
A1: ATTACHMENT 4: Travel Time Savings
A3: Level of Service Analysis
A4: Source: Highway Capacity Manual 2000, Transportation Research Board
B6: Percent Time-Spent-Following (%) | C6: Level of Service | D6: Average Travel Speed (mph) | E6: Level of Service | F6: Travel Time during the peak 15-minute period (veh-hr)
A7: Without Project | B7: 84.18 | C7: E | D7: 49.1 | E7: C | F7: 24.2
A8: With Project | B8: 81.28 | C8: E | D8: 49.8 | E8: C | F8: 23.9
A9: Decrease/Increase | B9: =B7-B8 -> 2.9 | C9: - | D9: =D7-D8 -> -0.7 | E9: - | F9: =F7-F8 -> 0.3
D11: Travel Time Savings (veh-hr) | F11: =F9 -> 0.3
A13: Note: LOS Criteria for Two-Lane Highways in Class I per Exhibit 20-2, Highway Capacity Manual 2000
A14: Average travel time saved calculated for peak 15-minute period per Chapter 20 - Two lane Highways, Highway Capacity Manual 2000. Assuming a base free flow speed of 65 miles per hour and using vehicular traffic counts taken by the Contra Costa County Public Works Department on Vasco Road - 1 mile South of Camino Diablo on August 5, 2009.

Sheet 5 - Collision History
A1: ATTACHMENT 5: Collision History
A3: Collision Reports
A4: Vasco Road Safety Improvements - Phase 2
A5: Source: Statewide Integrated Traffic Records System (SWITRS), California Highway Patrol (CHP)
C7: Injury | D7: Fatal | J7: Injury | K7: Fatal | Q7: Injury | R7: Fatal
A8: 1996 | B8: Collisions | C8: Collisions | D8: Collisions | E8: Injuries | F8: Fatalities | H8: 1997 | I8: Collisions | J8: Collisions | K8: Collisions | L8: Injuries | M8: Fatalities | O8: 1998 | P8: Collisions | Q8: Collisions | R8: Collisions | S8: Injuries | T8: Fatalities
A9: 35065 | B9: 2 | C9: 0 | D9: 0 | E9: 0 | F9: 0 | H9: 35431 | I9: 1 | J9: 1 | K9: 0 | L9: 2 | M9: 0 | O9: 35796 | P9: 2 | Q9: 0 | R9: 0 | S9: 0 | T9: 0
A10: 35096 | B10: 7 | C10: 4 | D10: 0 | E10: 4 | F10: 0 | H10: 35462 | I10: 1 | J10: 0 | K10: 0 | L10: 0 | M10: 0 | O10: 35827 | P10: 4 | Q10: 0 | R10: 0 | S10: 1 | T10: 0
A11: 35125 | B11: 1 | C11: 1 | D11: 0 | E11: 1 | F11: 0 | H11: 35490 | I11: 0 | J11: 0 | K11: 0 | L11: 0 | M11: 0 | O11: 35855 | P11: 1 | Q11: 1 | R11: 0 | S11: 1 | T11: 0
A12: 35156 | B12: 1 | C12: 1 | D12: 0 | E12: 3 | F12: 0 | H12: 35521 | I12: 1 | J12: 1 | K12: 0 | L12: 2 | M12: 0 | O12: 35886 | P12: 0 | Q12: 0 | R12: 0 | S12: 0 | T12: 0
A13: 35186 | B13: 1 | C13: 1 | D13: 0 | E13: 2 | F13: 0 | H13: 35551 | I13: 3 | J13: 1 | K13: 0 | L13: 2 | M13: 0 | O13: 35916 | P13: 2 | Q13: 1 | R13: 0 | S13: 1 | T13: 0
A14: 35217 | B14: 2 | C14: 0 | D14: 0 | E14: 0 | F14: 0 | H14: 35582 | I14: 5 | J14: 3 | K14: 0 | L14: 3 | M14: 0 | O14: 35947 | P14: 1 | Q14: 1 | R14: 0 | S14: 3 | T14: 0
A15: 35247 | B15: 5 | C15: 3 | D15: 0 | E15: 5 | F15: 0 | H15: 35612 | I15: 1 | J15: 1 | K15: 0 | L15: 5 | M15: 0 | O15: 35977 | P15: 3 | Q15: 0 | R15: 0 | S15: 0 | T15: 0
A16: 35278 | B16: 1 | C16: 1 | D16: 0 | E16: 2 | F16: 0 | H16: 35643 | I16: 0 | J16: 0 | K16: 0 | L16: 0 | M16: 0 | O16: 36008 | P16: 2 | Q16: 1 | R16: 0 | S16: 2 | T16: 0
A17: 35309 | B17: 1 | C17: 0 | D17: 0 | E17: 0 | F17: 0 | H17: 35674 | I17: 2 | J17: 2 | K17: 0 | L17: 5 | M17: 0 | O17: 36039 | P17: 7 | Q17: 3 | R17: 0 | S17: 3 | T17: 0
A18: 35339 | B18: 1 | C18: 0 | D18: 0 | E18: 0 | F18: 0 | H18: 35704 | I18: 0 | J18: 0 | K18: 0 | L18: 0 | M18: 0 | O18: 36069 | P18: 1 | Q18: 0 | R18: 0 | S18: 0 | T18: 0
A19: 35370 | B19: 4 | C19: 3 | D19: 0 | E19: 6 | F19: 0 | H19: 35735 | I19: 2 | J19: 2 | K19: 0 | L19: 3 | M19: 0 | O19: 36100 | P19: 2 | Q19: 2 | R19: 0 | S19: 4 | T19: 0
A20: 35400 | B20: 0 | C20: 0 | D20: 0 | E20: 0 | F20: 0 | H20: 35765 | I20: 2 | J20: 1 | K20: 0 | L20: 4 | M20: 0 | O20: 36130 | P20: 2 | Q20: 2 | R20: 0 | S20: 2 | T20: 0
A21: Total | B21: =SUM(B9:B20) -> 26 | C21: =SUM(C9:C20) -> 14 | D21: =SUM(D9:D20) -> 0 | E21: =SUM(E9:E20) -> 23 | F21: =SUM(F9:F20) -> 0 | H21: Total | I21: =SUM(I9:I20) -> 18 | J21: =SUM(J9:J20) -> 12 | K21: =SUM(K9:K20) -> 0 | L21: =SUM(L9:L20) -> 26 | M21: =SUM(M9:M20) -> 0 | O21: Total | P21: =SUM(P9:P20) -> 27 | Q21: =SUM(Q9:Q20) -> 11 | R21: =SUM(R9:R20) -> 0 | S21: =SUM(S9:S20) -> 17 | T21: =SUM(T9:T20) -> 0
C23: Injury | D23: Fatal | J23: Injury | K23: Fatal | Q23: Injury | R23: Fatal
A24: 1999 | B24: Collisions | C24: Collisions | D24: Collisions | E24: Injuries | F24: Fatalities | H24: 2000 | I24: Collisions | J24: Collisions | K24: Collisions | L24: Injuries | M24: Fatalities | O24: 2001 | P24: Collisions | Q24: Collisions | R24: Collisions | S24: Injuries | T24: Fatalities
A25: 36161 | B25: 4 | C25: 2 | D25: 0 | E25: 5 | F25: 0 | H25: 36526 | I25: 3 | J25: 1 | K25: 0 | L25: 1 | M25: 0 | O25: 36892 | P25: 2 | Q25: 1 | R25: 0 | S25: 3 | T25: 0
A26: 36192 | B26: 4 | C26: 1 | D26: 0 | E26: 2 | F26: 0 | H26: 36557 | I26: 9 | J26: 1 | K26: 0 | L26: 3 | M26: 0 | O26: 36923 | P26: 0 | Q26: 0 | R26: 0 | S26: 0 | T26: 0
A27: 36220 | B27: 2 | C27: 0 | D27: 0 | E27: 0 | F27: 0 | H27: 36586 | I27: 2 | J27: 1 | K27: 0 | L27: 1 | M27: 0 | O27: 36951 | P27: 3 | Q27: 3 | R27: 0 | S27: 3 | T27: 0
A28: 36251 | B28: 3 | C28: 1 | D28: 0 | E28: 1 | F28: 0 | H28: 36617 | I28: 3 | J28: 0 | K28: 0 | L28: 0 | M28: 0 | O28: 36982 | P28: 2 | Q28: 1 | R28: 0 | S28: 1 | T28: 0
A29: 36281 | B29: 0 | C29: 0 | D29: 0 | E29: 0 | F29: 0 | H29: 36647 | I29: 1 | J29: 1 | K29: 0 | L29: 2 | M29: 0 | O29: 37012 | P29: 3 | Q29: 2 | R29: 0 | S29: 10 | T29: 0
A30: 36312 | B30: 2 | C30: 1 | D30: 0 | E30: 1 | F30: 0 | H30: 36678 | I30: 2 | J30: 1 | K30: 0 | L30: 1 | M30: 0 | O30: 37043 | P30: 1 | Q30: 0 | R30: 0 | S30: 0 | T30: 0
A31: 36342 | B31: 3 | C31: 0 | D31: 0 | E31: 0 | F31: 0 | H31: 36708 | I31: 1 | J31: 0 | K31: 0 | L31: 0 | M31: 0 | O31: 37073 | P31: 2 | Q31: 0 | R31: 0 | S31: 0 | T31: 0
A32: 36373 | B32: 3 | C32: 2 | D32: 0 | E32: 2 | F32: 0 | H32: 36739 | I32: 0 | J32: 0 | K32: 0 | L32: 0 | M32: 0 | O32: 37104 | P32: 1 | Q32: 1 | R32: 0 | S32: 1 | T32: 0
A33: 36404 | B33: 1 | C33: 0 | D33: 0 | E33: 0 | F33: 0 | H33: 36770 | I33: 5 | J33: 3 | K33: 0 | L33: 8 | M33: 0 | O33: 37135 | P33: 2 | Q33: 0 | R33: 0 | S33: 0 | T33: 0
A34: 36434 | B34: 3 | C34: 2 | D34: 0 | E34: 2 | F34: 0 | H34: 36800 | I34: 3 | J34: 1 | K34: 0 | L34: 2 | M34: 0 | O34: 37165 | P34: 1 | Q34: 1 | R34: 0 | S34: 2 | T34: 0
A35: 36465 | B35: 3 | C35: 0 | D35: 0 | E35: 0 | F35: 0 | H35: 36831 | I35: 5 | J35: 1 | K35: 0 | L35: 3 | M35: 0 | O35: 37196 | P35: 2 | Q35: 1 | R35: 0 | S35: 1 | T35: 0
A36: 36495 | B36: 1 | C36: 0 | D36: 0 | E36: 0 | F36: 0 | H36: 36861 | I36: 1 | J36: 0 | K36: 0 | L36: 0 | M36: 0 | O36: 37226 | P36: 4 | Q36: 2 | R36: 0 | S36: 3 | T36: 0
A37: Total | B37: =SUM(B25:B36) -> 29 | C37: =SUM(C25:C36) -> 9 | D37: =SUM(D25:D36) -> 0 | E37: =SUM(E25:E36) -> 13 | F37: =SUM(F25:F36) -> 0 | H37: Total | I37: =SUM(I25:I36) -> 35 | J37: =SUM(J25:J36) -> 10 | K37: =SUM(K25:K36) -> 0 | L37: =SUM(L25:L36) -> 21 | M37: =SUM(M25:M36) -> 0 | O37: Total | P37: =SUM(P25:P36) -> 23 | Q37: =SUM(Q25:Q36) -> 12 | R37: =SUM(R25:R36) -> 0 | S37: =SUM(S25:S36) -> 24 | T37: =SUM(T25:T36) -> 0
C39: Injury | D39: Fatal | J39: Injury | K39: Fatal | Q39: Injury | R39: Fatal
A40: 2002 | B40: Collisions | C40: Collisions | D40: Collisions | E40: Injuries | F40: Fatalities | H40: 2003 | I40: Collisions | J40: Collisions | K40: Collisions | L40: Injuries | M40: Fatalities | O40: 2004 | P40: Collisions | Q40: Collisions | R40: Collisions | S40: Injuries | T40: Fatalities
A41: 37257 | B41: 3 | C41: 0 | D41: 0 | E41: 0 | F41: 0 | H41: 37622 | I41: 2 | J41: 0 | K41: 0 | L41: 0 | M41: 0 | O41: 37987 | P41: 1 | Q41: 1 | R41: 0 | S41: 1 | T41: 0
A42: 37288 | B42: 4 | C42: 2 | D42: 0 | E42: 2 | F42: 0 | H42: 37653 | I42: 1 | J42: 0 | K42: 0 | L42: 0 | M42: 0 | O42: 38018 | P42: 2 | Q42: 1 | R42: 0 | S42: 2 | T42: 0
A43: 37316 | B43: 1 | C43: 0 | D43: 0 | E43: 0 | F43: 0 | H43: 37681 | I43: 2 | J43: 1 | K43: 0 | L43: 2 | M43: 0 | O43: 38047 | P43: 5 | Q43: 2 | R43: 0 | S43: 3 | T43: 0
A44: 37347 | B44: 4 | C44: 0 | D44: 0 | E44: 0 | F44: 0 | H44: 37712 | I44: 3 | J44: 1 | K44: 0 | L44: 1 | M44: 0 | O44: 38078 | P44: 4 | Q44: 1 | R44: 0 | S44: 1 | T44: 0
A45: 37377 | B45: 3 | C45: 1 | D45: 0 | E45: 1 | F45: 0 | H45: 37742 | I45: 1 | J45: 1 | K45: 0 | L45: 1 | M45: 0 | O45: 38108 | P45: 2 | Q45: 1 | R45: 0 | S45: 1 | T45: 0
A46: 37408 | B46: 3 | C46: 1 | D46: 0 | E46: 1 | F46: 0 | H46: 37773 | I46: 7 | J46: 4 | K46: 1 | L46: 9 | M46: 3 | O46: 38139 | P46: 2 | Q46: 0 | R46: 0 | S46: 0 | T46: 0
A47: 37438 | B47: 5 | C47: 3 | D47: 0 | E47: 6 | F47: 0 | H47: 37803 | I47: 5 | J47: 0 | K47: 0 | L47: 0 | M47: 0 | O47: 38169 | P47: 3 | Q47: 1 | R47: 0 | S47: 1 | T47: 0
A48: 37469 | B48: 4 | C48: 1 | D48: 0 | E48: 2 | F48: 0 | H48: 37834 | I48: 7 | J48: 3 | K48: 1 | L48: 6 | M48: 1 | O48: 38200 | P48: 4 | Q48: 3 | R48: 0 | S48: 9 | T48: 0
A49: 37500 | B49: 1 | C49: 1 | D49: 0 | E49: 1 | F49: 0 | H49: 37865 | I49: 4 | J49: 1 | K49: 0 | L49: 1 | M49: 0 | O49: 38231 | P49: 3 | Q49: 2 | R49: 1 | S49: 3 | T49: 4
A50: 37530 | B50: 3 | C50: 1 | D50: 1 | E50: 1 | F50: 1 | H50: 37895 | I50: 2 | J50: 0 | K50: 0 | L50: 0 | M50: 0 | O50: 38261 | P50: 2 | Q50: 0 | R50: 0 | S50: 0 | T50: 0
A51: 37561 | B51: 4 | C51: 1 | D51: 0 | E51: 1 | F51: 0 | H51: 37926 | I51: 3 | J51: 0 | K51: 0 | L51: 0 | M51: 0 | O51: 38292 | P51: 1 | Q51: 0 | R51: 0 | S51: 0 | T51: 0
A52: 37591 | B52: 0 | C52: 0 | D52: 0 | E52: 0 | F52: 0 | H52: 37956 | I52: 4 | J52: 2 | K52: 0 | L52: 3 | M52: 0 | O52: 38322 | P52: 5 | Q52: 1 | R52: 0 | S52: 1 | T52: 0
A53: Total | B53: =SUM(B41:B52) -> 35 | C53: =SUM(C41:C52) -> 11 | D53: =SUM(D41:D52) -> 1 | E53: =SUM(E41:E52) -> 15 | F53: =SUM(F41:F52) -> 1 | H53: Total | I53: =SUM(I41:I52) -> 41 | J53: =SUM(J41:J52) -> 13 | K53: =SUM(K41:K52) -> 2 | L53: =SUM(L41:L52) -> 23 | M53: =SUM(M41:M52) -> 4 | O53: Total | P53: =SUM(P41:P52) -> 34 | Q53: =SUM(Q41:Q52) -> 13 | R53: =SUM(R41:R52) -> 1 | S53: =SUM(S41:S52) -> 22 | T53: =SUM(T41:T52) -> 4
C55: Injury | D55: Fatal | J55: Injury | K55: Fatal | Q55: Injury | R55: Fatal
A56: 2005 | B56: Collisions | C56: Collisions | D56: Collisions | E56: Injuries | F56: Fatalities | H56: 2006 | I56: Collisions | J56: Collisions | K56: Collisions | L56: Injuries | M56: Fatalities | O56: 2007 | P56: Collisions | Q56: Collisions | R56: Collisions | S56: Injuries | T56: Fatalities
A57: 38353 | B57: 7 | C57: 3 | D57: 0 | E57: 4 | F57: 0 | H57: 38718 | I57: 3 | J57: 1 | K57: 0 | L57: 1 | M57: 0 | O57: 39083 | P57: 1 | Q57: 0 | R57: 0 | S57: 0 | T57: 0
A58: 38384 | B58: 1 | C58: 1 | D58: 0 | E58: 1 | F58: 0 | H58: 38749 | I58: 0 | J58: 0 | K58: 0 | L58: 0 | M58: 0 | O58: 39114 | P58: 0 | Q58: 0 | R58: 0 | S58: 0 | T58: 0
A59: 38412 | B59: 4 | C59: 2 | D59: 0 | E59: 2 | F59: 0 | H59: 38777 | I59: 1 | J59: 1 | K59: 0 | L59: 1 | M59: 0 | O59: 39142 | P59: 1 | Q59: 0 | R59: 0 | S59: 0 | T59: 0
A60: 38443 | B60: 3 | C60: 0 | D60: 0 | E60: 0 | F60: 0 | H60: 38808 | I60: 3 | J60: 0 | K60: 0 | L60: 0 | M60: 0 | O60: 39173 | P60: 1 | Q60: 0 | R60: 0 | S60: 0 | T60: 0
A61: 38473 | B61: 2 | C61: 1 | D61: 0 | E61: 2 | F61: 0 | H61: 38838 | I61: 2 | J61: 1 | K61: 0 | L61: 1 | M61: 0 | O61: 39203 | P61: 2 | Q61: 0 | R61: 0 | S61: 0 | T61: 0
A62: 38504 | B62: 4 | C62: 2 | D62: 1 | E62: 6 | F62: 1 | H62: 38869 | I62: 4 | J62: 2 | K62: 0 | L62: 3 | M62: 0 | O62: 39234 | P62: 3 | Q62: 1 | R62: 0 | S62: 1 | T62: 0
A63: 38534 | B63: 1 | C63: 1 | D63: 0 | E63: 1 | F63: 0 | H63: 38899 | I63: 2 | J63: 2 | K63: 0 | L63: 4 | M63: 0 | O63: 39264 | P63: 0 | Q63: 0 | R63: 0 | S63: 0 | T63: 0
A64: 38565 | B64: 3 | C64: 1 | D64: 0 | E64: 1 | F64: 0 | H64: 38930 | I64: 6 | J64: 2 | K64: 2 | L64: 2 | M64: 5 | O64: 39295 | P64: 3 | Q64: 2 | R64: 0 | S64: 2 | T64: 0
A65: 38596 | B65: 0 | C65: 0 | D65: 0 | E65: 0 | F65: 0 | H65: 38961 | I65: 3 | J65: 1 | K65: 0 | L65: 1 | M65: 0 | O65: 39326 | P65: 0 | Q65: 0 | R65: 0 | S65: 0 | T65: 0
A66: 38626 | B66: 6 | C66: 1 | D66: 0 | E66: 1 | F66: 0 | H66: 38991 | I66: 3 | J66: 0 | K66: 0 | L66: 0 | M66: 0 | O66: 39356 | P66: 6 | Q66: 3 | R66: 0 | S66: 3 | T66: 0
A67: 38657 | B67: 0 | C67: 0 | D67: 0 | E67: 0 | F67: 0 | H67: 39022 | I67: 1 | J67: 0 | K67: 1 | L67: 0 | M67: 1 | O67: 39387 | P67: 1 | Q67: 0 | R67: 0 | S67: 0 | T67: 0
A68: 38687 | B68: 2 | C68: 0 | D68: 0 | E68: 0 | F68: 0 | H68: 39052 | I68: 3 | J68: 1 | K68: 0 | L68: 2 | M68: 0 | O68: 39417 | P68: 2 | Q68: 2 | R68: 0 | S68: 2 | T68: 0
A69: Total | B69: =SUM(B57:B68) -> 33 | C69: =SUM(C57:C68) -> 12 | D69: =SUM(D57:D68) -> 1 | E69: =SUM(E57:E68) -> 18 | F69: =SUM(F57:F68) -> 1 | H69: Total | I69: =SUM(I57:I68) -> 31 | J69: =SUM(J57:J68) -> 11 | K69: =SUM(K57:K68) -> 3 | L69: =SUM(L57:L68) -> 15 | M69: =SUM(M57:M68) -> 6 | O69: Total | P69: =SUM(P57:P68) -> 20 | Q69: =SUM(Q57:Q68) -> 8 | R69: =SUM(R57:R68) -> 0 | S69: =SUM(S57:S68) -> 8 | T69: =SUM(T57:T68) -> 0
C72: Injury | D72: Fatal
A73: 2008 | B73: Collisions | C73: Collisions | D73: Collisions | E73: Injuries | F73: Fatalities
A74: 39448 | B74: 1 | C74: 1 | D74: 0 | E74: 1 | F74: 0
A75: 39479 | B75: 2 | C75: 0 | D75: 0 | E75: 0 | F75: 0
A76: 39508 | B76: 1 | C76: 1 | D76: 0 | E76: 1 | F76: 0
A77: 39539 | B77: 2 | C77: 0 | D77: 0 | E77: 0 | F77: 0
A78: 39569 | B78: 4 | C78: 0 | D78: 0 | E78: 0 | F78: 0
A79: 39600 | B79: 2 | C79: 2 | D79: 0 | E79: 3 | F79: 0
A80: 39630 | B80: 3 | C80: 1 | D80: 0 | E80: 1 | F80: 0
A81: 39661 | B81: 2 | C81: 1 | D81: 0 | E81: 2 | F81: 0
A82: 39692 | B82: 0 | C82: 0 | D82: 0 | E82: 0 | F82: 0
A83: 39722 | B83: 7 | C83: 6 | D83: 0 | E83: 8 | F83: 0
A84: 39753 | B84: 2 | C84: 0 | D84: 0 | E84: 0 | F84: 0
A85: 39783 | B85: 2 | C85: 0 | D85: 0 | E85: 0 | F85: 0
A86: Total | B86: =SUM(B74:B85) -> 28 | C86: =SUM(C74:C85) -> 12 | D86: =SUM(D74:D85) -> 0 | E86: =SUM(E74:E85) -> 16 | F86: =SUM(F74:F85) -> 0
C88: Injury | D88: Fatal
B89: Collisions | C89: Collisions | D89: Collisions | E89: Injuries | F89: Fatalities
A90: Total 1996-2008 | B90: =SUM(B21,I21,P21,B37,I37,P37,B53,I53,P53,B69,I69,P69,B86,I86,P86,V86) -> 380 | C90: =SUM(C21,J21,Q21,C37,J37,Q37,C53,J53,Q53,C69,J69,Q69,C86,J86,Q86,W86) -> 148 | D90: =SUM(D21,K21,R21,D37,K37,R37,D53,K53,R53,D69,K69,R69,D86,K86,R86,X86) -> 8 | E90: =SUM(E21,L21,S21,E37,L37,S37,E53,L53,S53,E69,L69,S69,E86,L86,S86,Y86) -> 241 | F90: =SUM(F21,M21,T21,F37,M37,T37,F53,M53,T53,F69,M69,T69,F86,M86,T86,Z86) -> 16
C92: Actual Accident Rate | H92: Statewide Average Rate*
A93: Period | B93: Number of Accidents | C93: Fatal (F) | D93: Injury (I) | E93: F + I | F93: All | H93: Fatal (F) | I93: Injury (I) | J93: F + I | K93: All | L93: ADT
A94: 1996 | B94: See Appendix B: Truck Traffic. Percent truck traffic includes buses and is based on Truck Traffic Turning Movement Counts taken by the Contra Costa County | C94: =(D21*1000000)/(365*1*L94*9.8) -> 0 | D94: =(C21*1000000)/(365*1*L94*9.8) -> 0.23979257 | E94: 0.12 | F94: =(B94*1000000)/(365*1*L94*9.8) -> #VALUE! | H94: 0.04 | I94: 0.41 | J94: 0.45 | K94: 0.92 | L94: 16322
A95: 1997 | B95: Public Works Department from May 12-15, 2008. | C95: =(K21*1000000)/(365*1*L95*9.8) -> 0 | D95: =(J21*1000000)/(365*1*L95*9.8) -> 0.19684132 | E95: 0.12 | F95: =(B95*1000000)/(365*1*L95*9.8) -> #VALUE! | H95: 0.04 | I95: 0.41 | J95: 0.45 | K95: 0.92 | L95: =L96-725 -> 17043
A96: 1998 | B96: =P21 -> 27 | C96: =(R21*1000000)/(365*1*L96*9.8) -> 0 | D96: =(Q21*1000000)/(365*1*L96*9.8) -> 0.17307534 | E96: 0.12 | F96: =(B96*1000000)/(365*1*L96*9.8) -> 0.42482129 | H96: 0.04 | I96: 0.41 | J96: 0.45 | K96: 0.92 | L96: =L97-725 -> 17768
A97: 1999 | B97: =B37 -> 29 | C97: =(D37*1000000)/(365*1*L97*9.8) -> 0 | D97: =(C37*1000000)/(365*1*L97*9.8) -> 0.13605553 | E97: 0.12 | F97: =(B97*1000000)/(365*1*L97*9.8) -> 0.43840115 | H97: 0.04 | I97: 0.41 | J97: 0.45 | K97: 0.92 | L97: =L98-725 -> 18493
A98: 2000 | B98: =I37 -> 35 | C98: =(K37*1000000)/(365*1*L98*9.8) -> 0 | D98: =(J37*1000000)/(365*1*L98*9.8) -> 0.14546981 | E98: 0.25 | F98: =(B98*1000000)/(365*1*L98*9.8) -> 0.50914433 | H98: 0.04 | I98: 0.41 | J98: 0.45 | K98: 0.92 | L98: =L99-725 -> 19218
A99: 2001 | B99: =P37 -> 23 | C99: =(R37*1000000)/(365*1*L99*9.8) -> 0 | D99: =(Q37*1000000)/(365*1*L99*9.8) -> 0.16821775 | E99: 0.25 | F99: =(B99*1000000)/(365*1*L99*9.8) -> 0.32241735 | H99: 0.04 | I99: 0.41 | J99: 0.45 | K99: 0.92 | L99: =L100-725 -> 19943
A100: 2002 | B100: =B53 -> 35 | C100: =(D53*1000000)/(365*1*L100*9.8) -> 0.013526412 | D100: =(C53*1000000)/(365*1*L100*9.8) -> 0.14879053 | E100: 0.15 | F100: =(B100*1000000)/(365*1*L100*9.8) -> 0.47342442 | H100: 0.04 | I100: 0.41 | J100: 0.45 | K100: 0.92 | L100: =L101-725 -> 20668
A101: 2003 | B101: See Appendix A: Traffic Volumes. Affected drivers assuming straight-line approximation (1.5% annual increase) of future traffic volumes from the Contra Costa | C101: =(K53*1000000)/(365*1*L101*9.8) -> 0.026136015 | D101: =(J53*1000000)/(365*1*L101*9.8) -> 0.1698841 | E101: 0.16 | F101: =(B101*1000000)/(365*1*L101*9.8) -> #VALUE! | H101: 0.04 | I101: 0.41 | J101: 0.45 | K101: 0.92 | L101: =L102-725 -> 21393
A102: 2004 | B102: Transportation Authority Travel Demand Model, 2012. | C102: =(R53*1000000)/(365*1*L102*9.8) -> 0.012639655 | D102: =(Q53*1000000)/(365*1*L102*9.8) -> 0.16431551 | E102: =SUM(C102:D102) -> 0.17695516 | F102: =(B102*1000000)/(365*1*L102*9.8) -> #VALUE! | H102: 0.04 | I102: 0.41 | J102: 0.45 | K102: 0.92 | L102: 22118
A103: 2005 | B103: See Appendix C: Travel Time Savings. Average travel time saved calculated for peak 15-minute period per Chapter 20 - Two lane Highways, HCM 2000. | C103: =(D69*1000000)/(365*1*L103*9.8) -> 0.012639655 | D103: =(C69*1000000)/(365*1*L103*9.8) -> 0.15167586 | E103: =SUM(C103:D103) -> 0.16431551 | F103: =(B103*1000000)/(365*1*L103*9.8) -> #VALUE! | H103: 0.04 | I103: 0.41 | J103: 0.45 | K103: 0.92 | L103: 22118
A104: 2006 | B104: =I69 -> 31 | C104: =(K69*1000000)/(365*1*L104*9.8) -> 0.03738318 | D104: =(J69*1000000)/(365*1*L104*9.8) -> 0.13707166 | E104: =SUM(C104:D104) -> 0.17445484 | F104: =(B104*1000000)/(365*1*L104*9.8) -> 0.38629286 | H104: 0.04 | I104: 0.41 | J104: 0.45 | K104: 0.92 | L104: 22435
A105: 2007 | B105: =P69 -> 20 | C105: =(R69*1000000)/(365*1*L105*9.8) -> 0 | D105: =(Q69*1000000)/(365*1*L105*9.8) -> 0.10293221 | E105: =SUM(C105:D105) -> 0.10293221 | F105: =(B105*1000000)/(365*1*L105*9.8) -> 0.25733052 | H105: 0.04 | I105: 0.41 | J105: 0.45 | K105: 0.92 | L105: 21728
A106: 2008 | B106: =+B86 -> 28 | C106: =(D86*1000000)/(365*1*L106*9.8) -> 0 | D106: =(C86*1000000)/(365*1*L106*9.8) -> 0.16868295 | E106: =SUM(C106:D106) -> 0.16868295 | F106: =(B106*1000000)/(365*1*L106*9.8) -> 0.39359356 | H106: 0.04 | I106: 0.41 | J106: 0.45 | K106: 0.92 | L106: 19888
A107: 1996-2008 | B107: =B90 -> 380 | C107: =(D90*1000000)/(365*8*L107*9.8) -> 0.014024854 | D107: =(C90*1000000)/(365*8*L107*9.8) -> 0.25945979 | E107: =SUM(C107:D107) -> 0.27348465 | F107: =(B107*1000000)/(365*8*L107*9.8) -> 0.66618055 | H107: 0.04 | I107: 0.41 | J107: 0.45 | K107: 0.92 | L107: =AVERAGE(L94:L106) -> 19933.462
A109: Period | B109: Number of Accidents | C109: Fatals | D109: Injuries | E109: Property Damage Only
A111: 1996 | B111: =B94 -> See Appendix B: Truck Traffic. Percent truck traffic includes buses and is based on Truck Traffic Turning Movement Counts taken by the Contra Costa County | C111: =D21 -> 0 | D111: =C21 -> 14 | E111: =B111-C111-D111 -> #VALUE!
...

Sheet 6 - 5yr Collision (Recent)
A1: ATTACHMENT 6: 5-Year Collision Data (2008-2012)
A3: Collision Reports 2008-2012
A4: Vasco Road Safety Improvements - Phase 2
A5: Source: Collision Reports, California Highway Patrol (CHP)
A7: Primary Cause | B7: 2008 | C7: 2009 | D7: 2010 | E7: 2011 | F7: 2012 | G7: Total | H7: %
A8: Improper Turning | B8: 2 | C8: 0 | D8: 0 | E8: 0 | F8: 0 | G8: =SUM(B8:F8) -> 2 | H8: =G8/$G$18 -> 0.023255814
A9: Wrong Side of Road | B9: 3 | C9: 1 | D9: 0 | E9: 0 | F9: 0 | G9: =SUM(B9:F9) -> 4 | H9: =G9/$G$18 -> 0.046511628
A10: Unsafe Lane Change | B10: 1 | C10: 0 | D10: 0 | E10: 0 | F10: 0 | G10: =SUM(B10:F10) -> 1 | H10: =G10/$G$18 -> 0.011627907
A11: Unsafe Turning Movement | B11: 0 | C11: 6 | D11: 2 | E11: 6 | F11: 3 | G11: =SUM(B11:F11) -> 17 | H11: =G11/$G$18 -> 0.19767442
A12: Unsafe Speed | B12: 2 | C12: 12 | D12: 4 | E12: 12 | F12: 6 | G12: =SUM(B12:F12) -> 36 | H12: =G12/$G$18 -> 0.41860465
A13: Improper Passing | B13: 1 | C13: 0 | D13: 1 | E13: 0 | F13: 0 | G13: =SUM(B13:F13) -> 2 | H13: =G13/$G$18 -> 0.023255814
A14: Driving Under Influence | B14: 0 | C14: 1 | D14: 3 | E14: 1 | F14: 2 | G14: =SUM(B14:F14) -> 7 | H14: =G14/$G$18 -> 0.081395349
A15: Traffic Signals and Signs | B15: 0 | C15: 0 | D15: 3 | E15: 0 | F15: 0 | G15: =SUM(B15:F15) -> 3 | H15: =G15/$G$18 -> 0.034883721
A16: Unknown | B16: 0 | C16: 1 | D16: 0 | E16: 0 | F16: 0 | G16: =SUM(B16:F16) -> 1 | H16: =G16/$G$18 -> 0.011627907
A17: Other | B17: 1 | C17: 3 | D17: 1 | E17: 5 | F17: 3 | G17: =SUM(B17:F17) -> 13 | H17: =G17/$G$18 -> 0.15116279
A18: Total | B18: =SUM(B8:B17) -> 10 | C18: =SUM(C8:C17) -> 24 | D18: =SUM(D8:D17) -> 14 | E18: =SUM(E8:E17) -> 24 | F18: =SUM(F8:F17) -> 14 | G18: =SUM(B18:F18) -> 86 | H18: =SUM(H8:H17) -> 1
B20: 2008 | C20: 2009 | D20: 2010 | E20: 2011 | F20: 2012 | G20: Total
A21: Total Collisions | B21: 10 | C21: 24 | D21: 14 | E21: 24 | F21: 14 | G21: =SUM(B21:F21) -> 86
A22: Injury Collisions | B22: 4 | C22: 6 | D22: 8 | E22: 5 | F22: 3 | G22: =SUM(B22:F22) -> 26
A23: Fatal Collisions | B23: 0 | C23: 1 | D23: 0 | E23: 1 | F23: 0 | G23: =SUM(B23:F23) -> 2
A25: Severity | B25: 2008 | C25: 2009 | D25: 2010 | E25: 2011 | F25: 2012 | G25: Total
A26: Injuries | B26: 4 | C26: 6 | D26: 18 | E26: 9 | F26: 4 | G26: =SUM(B26:F26) -> 41
A27: Fatalities | B27: 0 | C27: 1 | D27: 0 | E27: 1 | F27: 0 | G27: =SUM(B27:F27) -> 2
A28: Total | B28: =SUM(B26:B27) -> 4 | C28: =SUM(C26:C27) -> 7 | D28: =SUM(D26:D27) -> 18 | E28: =SUM(E26:E27) -> 10 | F28: =SUM(F26:F27) -> 4 | G28: =SUM(B28:F28) -> 43
A30: Collisions that could have been prevented by median barrier:
A31: Severity | B31: 2008 | C31: 2009 | D31: 2010 | E31: 2011 | F31: 2012 | G31: Total
A32: Injuries | B32: 2 | C32: 2 | D32: 12 | E32: 7 | F32: 1 | G32: =SUM(B32:F32) -> 24
A33: Fatalities | B33: 0 | C33: 1 | D33: 0 | E33: 1 | F33: 0 | G33: =SUM(B33:F33) -> 2
A34: Total | B34: =SUM(B32:B33) -> 2 | C34: =SUM(C32:C33) -> 3 | D34: =SUM(D32:D33) -> 12 | E34: =SUM(E32:E33) -> 8 | F34: =SUM(F32:F33) -> 1 | G34: =SUM(G32:G33) -> 26
B36: 5-Year Total | C36: Prevented | D36: % | E36: 5-Year Average
A37: Injuries | B37: =G26 -> 41 | C37: =G32 -> 24 | D37: =C37/B37 -> 0.58536585 | E37: =C37/5 -> 4.8
A38: Fatalities | B38: =G27 -> 2 | C38: =G33 -> 2 | D38: =C38/B38 -> 1 | E38: =C38/5 -> 0.4

Sheet 7 - Collision Benefits
A1: ATTACHMENT 7: Collision Benefits
A3: Average Annual Collision Benefits
A4: Source: Abbreviated Injury Scale (AIS) Calculation for Monetizing Accident Reduction, TIGER BCA Resource Guide
B6: 2008-2012 | D6: Fatal Accidents | G6: # Non-fatal Accidents
D7: # Fatalities at Crash Site | G7: Unknown if injured
D8: 0.4 | E8: $ Value | F8: Pr(AISx) | G8: 4.8 | H8: $ Value
B9: Accident Counts | E9: Fatalities * VSL | H9: [Pr(AISx)*Value(AISx)]
B10: AIS | C10: 0 | D10: 0 | E10: 0 | F10: 0.43676 | G10: =F10*$G$8 -> 2.096448 | H10: 0
C11: 1 | D11: 0 | E11: 0 | F11: 0.41739 | G11: =F11*$G$8 -> 2.003472 | H11: =27300*G11 -> 54694.786
C12: 2 | D12: 0 | E12: 0 | F12: 0.08872 | G12: =F12*$G$8 -> 0.425856 | H12: =427700*G12 -> 182138.61
C13: 3 | D13: 0 | E13: 0 | F13: 0.04817 | G13: =F13*$G$8 -> 0.231216 | H13: =95500*G13 -> 22081.128
C14: 4 | D14: 0 | E14: 0 | F14: 0.00617 | G14: =F14*$G$8 -> 0.029616 | H14: =2420600*G14 -> 71688.49
C15: 5 | D15: 0 | E15: 0 | F15: 0.00279 | G15: =F15*$G$8 -> 0.013392 | H15: =5396300*G15 -> 72267.25
C16: Fatality | D16: =D8 -> 0.4 | E16: 9100000 | F16: 0 | G16: =F16*$G$8 -> 0 | H16: 0
B17: SUBTOTALS | D17: =SUM(D10:D16) -> 0.4 | E17: =D16*E16 -> 3640000 | F17: =SUM(F10:F16) -> 1 | G17: =SUM(G10:G16) -> 4.8 | H17: =SUM(H10:H16) -> 402870.26
B19: TOTAL VALUE OF FATALITIES & INJURIES | H19: =SUM(E17,H17) -> 4042870.3

Sheet 8 - O&M Costs
A1: ATTACHMENT 8: Operations and Maintenance Costs
A3: Source: Contra Costa County Public Works Department
A5: Annual operations and maintenance costs incurred along Vasco Road by construction of the project:
B6: 20000
A8: Additional cost to provide pavement maintenance on project widening:
E9: Value | F9: Unit
D10: Useful life of pavement maintenance | E10: 10 | F10: years
D11: Estimated unit cost to overlay the roadway | E11: 40 | F11: per sy
D12: Project length | E12: =1.5*5280 -> 7920 | F12: feet
D13: Approximate project pavement widening | E13: 22 | F13: feet
D14: Additional pavement area added by project | E14: =E13*E12/9 -> 19360 | F14: sy
D15: Marginal pavement maintenance cost | E15: =E14*E11 -> 774400 | F15: every 10-years

Sheet 9 - BCA 20-year (Previous)
B1: ATTACHMENT 9: BENEFIT-COST ANALYSIS (Prior 5-year safety benefits)
B3: Vasco Road Safety Improvements Project - Phase 2
B4: TIGER V Grant Application
C6: Beneift/Cost Ratio = | D6: Total Benefits | E6: = | F6: =I60 -> 2.5101555e+08 | G6: = | H6: =F6/F7 -> 16.014455 | I6: (3% Discount)
D7: Total Costs | F7: =G87 -> 15674311
F9: =+J60 -> 1.7871752e+08 | G9: = | H9: =F9/F10 -> 12.321389 | I9: (7% Discount)
F10: =H87 -> 14504657
B11: Benefits
B12: Calendar Year | C12: Project Year | D12: Affected drivers4 | E12: Average Travel Time saved (veh-hrs)5 | F12: Value of Travel Time Benefits (Surface modes)2,3 | G12: Value of Travel Time Benefits (Truck Drivers)2,3 | H12: Total Value of Travel Time Benefits | I12: Total Present Value of Travel Time Benefits - 3% Discount (2013 dollars)1 | J12: Total Present Value of Travel Time Benefits - 7% Discount (2013 dollars)1
B13: 2014 | C13: 0 | D13: 23740 | E13: - | F13: 0 | G13: 0 | H13: 0 | I13: 0 | J13: 0
B14: 2015 | C14: 1 | D14: =+D13*1.015 -> 24096.1 | E14: 0.3 | F14: =D14*E14*$H$98*(1-$E$95) -> 115704.93 | G14: =D14*E14*$H$99*$E$95 -> 6878.9598 | H14: =SUM(F14:G14) -> 122583.89 | I14: =H14/((1+$E$91)^C14) -> 119013.48 | J14: =H14/((1+$E$92)^C14) -> 114564.38
B15: 2016 | C15: 2 | D15: =+D14*1.015 -> 24457.541 | E15: 0.3 | F15: =D15*E15*$H$98*(1-$E$95) -> 117440.5 | G15: =D15*E15*$H$99*$E$95 -> 6982.1442 | H15: =SUM(F15:G15) -> 124422.65 | I15: =H15/((1+$E$91)^C15) -> 117280.28 | J15: =H15/((1+$E$92)^C15) -> 108675.56
B16: 2017 | C16: 3 | D16: =+D15*1.015 -> 24824.405 | E16: 0.3 | F16: =D16*E16*$H$98*(1-$E$95) -> 119202.11 | G16: =D16*E16*$H$99*$E$95 -> 7086.8764 | H16: =SUM(F16:G16) -> 126288.98 | I16: =H16/((1+$E$91)^C16) -> 115572.31 | J16: =H16/((1+$E$92)^C16) -> 103089.43
B17: 2018 | C17: 4 | D17: =+D16*1.015 -> 25196.771 | E17: 0.3 | F17: =D17*E17*$H$98*(1-$E$95) -> 120990.14 | G17: =D17*E17*$H$99*$E$95 -> 7193.1795 | H17: =SUM(F17:G17) -> 128183.32 | I17: =H17/((1+$E$91)^C17) -> 113889.22 | J17: =H17/((1+$E$92)^C17) -> 97790.441
B18: 2019 | C18: 5 | D18: =+D17*1.015 -> 25574.722 | E18: 0.3 | F18: =D18*E18*$H$98*(1-$E$95) -> 122804.99 | G18: =D18*E18*$H$99*$E$95 -> 7301.0772 | H18: =SUM(F18:G18) -> 130106.07 | I18: =H18/((1+$E$91)^C18) -> 112230.64 | J18: =H18/((1+$E$92)^C18) -> 92763.829
B19: 2020 | C19: 6 | D19: =+D18*1.015 -> 25958.343 | E19: 0.3 | F19: =D19*E19*$H$98*(1-$E$95) -> 124647.07 | G19: =D19*E19*$H$99*$E$95 -> 7410.5934 | H19: =SUM(F19:G19) -> 132057.66 | I19: =H19/((1+$E$91)^C19) -> 110596.21 | J19: =H19/((1+$E$92)^C19) -> 87995.595
B20: 2021 | C20: 7 | D20: =+D19*1.015 -> 26347.718 | E20: 0.3 | F20: =D20*E20*$H$98*(1-$E$95) -> 126516.77 | G20: =D20*E20*$H$99*$E$95 -> 7521.7523 | H20: =SUM(F20:G20) -> 134038.53 | I20: =H20/((1+$E$91)^C20) -> 108985.59 | J20: =H20/((1+$E$92)^C20) -> 83472.457
B21: 2022 | C21: 8 | D21: =+D20*1.015 -> 26742.934 | E21: 0.3 | F21: =D21*E21*$H$98*(1-$E$95) -> 128414.52 | G21: =D21*E21*$H$99*$E$95 -> 7634.5786 | H21: =SUM(F21:G21) -> 136049.1 | I21: =H21/((1+$E$91)^C21) -> 107398.42 | J21: =H21/((1+$E$92)^C21) -> 79181.817
B22: 2023 | C22: 9 | D22: =+D21*1.015 -> 27144.078 | E22: 0.3 | F22: =D22*E22*$H$98*(1-$E$95) -> 130340.74 | G22: =D22*E22*$H$99*$E$95 -> 7749.0972 | H22: =SUM(F22:G22) -> 138089.84 | I22: =H22/((1+$E$91)^C22) -> 105834.36 | J22: =H22/((1+$E$92)^C22) -> 75111.723
B23: 2024 | C23: 10 | D23: =+D22*1.015 -> 27551.239 | E23: 0.3 | F23: =D23*E23*$H$98*(1-$E$95) -> 132295.85 | G23: =D23*E23*$H$99*$E$95 -> 7865.3337 | H23: =SUM(F23:G23) -> 140161.19 | I23: =H23/((1+$E$91)^C23) -> 104293.09 | J23: =H23/((1+$E$92)^C23) -> 71250.84
B24: 2025 | C24: 11 | D24: =+D23*1.015 -> 27964.508 | E24: 0.3 | F24: =D24*E24*$H$98*(1-$E$95) -> 134280.29 | G24: =D24*E24*$H$99*$E$95 -> 7983.3137 | H24: =SUM(F24:G24) -> 142263.61 | I24: =H24/((1+$E$91)^C24) -> 102774.26 | J24: =H24/((1+$E$92)^C24) -> 67588.414
B25: 2026 | C25: 12 | D25: =+D24*1.015 -> 28383.975 | E25: 0.3 | F25: =D25*E25*$H$98*(1-$E$95) -> 136294.5 | G25: =D25*E25*$H$99*$E$95 -> 8103.0634 | H25: =SUM(F25:G25) -> 144397.56 | I25: =H25/((1+$E$91)^C25) -> 101277.54 | J25: =H25/((1+$E$92)^C25) -> 64114.243
... B33: 2034 | C33: 20 | D33: =+D32*1.015 -> 31974.338 | E33: 0.3 | F33: =D33*E33*$H$98*(1-$E$95) -> 153534.74 | G33: =D33*E33*$H$99*$E$95 -> 9128.0408 | H33: =SUM(F33:G33) -> 162662.78 | I33: =H33/((1+$E$91)^C33) -> 90062.437 | J33: =H33/((1+$E$92)^C33) -> 42035.153
I34: =SUM(I13:I33) -> 2078034.2 | J34: =SUM(J13:J33) -> 1453058.3
B36: Calendar Year | C36: Project Year | D36: Average Annual Injuries Prevented6 | E36: Average Annual Fatalities Prevented6 | F36: Value of Injury Benefits7 | G36: Value of Fatality Benefits7 | H36: Total Value of Collision Benefits | I36: Total Present Value of Collision Benefits - 3% Discount (2013 dollars)1 | J36: Total Present Value of Collision Benefits - 7% Discount (2013 dollars)1
B37: 2014 | C37: 0 | D37: - | E37: - | F37: 0 | G37: 0 | H37: 0 | I37: 0 | J37: 0
B38: 2015 | C38: 1 | D38: ='9 - 5yr Collision (Previous)'!$E$40 -> 4.2 | E38: ='9 - 5yr Collision (Previous)'!$E$41 -> 1.8 | F38: ='9 - Collision Benefits'!$H$17 -> 352511.48 | G38: ='9 - Collision Benefits'!$E$17 -> 16380000 | H38: =F38+G38 -> 16732511 | I38: =H38/((1+$E$91)^C38) -> 16245157 | J38: =H38/((1+$E$92)^C38) -> 15637861
B39: 2016 | C39: 2 | D39: ='9 - 5yr Collision (Previous)'!$E$40 -> 4.2 | E39: ='9 - 5yr Collision (Previous)'!$E$41 -> 1.8 | F39: ='9 - Collision Benefits'!$H$17 -> 352511.48 | G39: ='9 - Collision Benefits'!$E$17 -> 16380000 | H39: =F39+G39 -> 16732511 | I39: =H39/((1+$E$91)^C39) -> 15771997 | J39: =H39/((1+$E$92)^C39) -> 14614824
B40: 2017 | C40: 3 | D40: ='9 - 5yr Collision (Previous)'!$E$40 -> 4.2 | E40: ='9 - 5yr Collision (Previous)'!$E$41 -> 1.8 | F40: ='9 - Collision Benefits'!$H$17 -> 352511.48 | G40: ='9 - Collision Benefits'!$E$17 -> 16380000 | H40: =F40+G40 -> 16732511 | I40: =H40/((1+$E$91)^C40) -> 15312618 | J40: =H40/((1+$E$92)^C40) -> 13658714
B41: 2018 | C41: 4 | D41: ='9 - 5yr Collision (Previous)'!$E$40 -> 4.2 | E41: ='9 - 5yr Collision (Previous)'!$E$41 -> 1.8 | F41: ='9 - Collision Benefits'!$H$17 -> 352511.48 | G41: ='9 - Collision Benefits'!$E$17 -> 16380000 | H41: =F41+G41 -> 16732511 | I41: =H41/((1+$E$91)^C41) -> 14866620 | J41: =H41/((1+$E$92)^C41) -> 12765153
B42: 2019 | C42: 5 | D42: ='9 - 5yr Collision (Previous)'!$E$40 -> 4.2 | E42: ='9 - 5yr Collision (Previous)'!$E$41 -> 1.8 | F42: ='9 - Collision Benefits'!$H$17 -> 352511.48 | G42: ='9 - Collision Benefits'!$E$17 -> 16380000 | H42: =F42+G42 -> 16732511 | I42: =H42/((1+$E$91)^C42) -> 14433611 | J42: =H42/((1+$E$92)^C42) -> 11930049
B43: 2020 | C43: 6 | D43: ='9 - 5yr Collision (Previous)'!$E$40 -> 4.2 | E43: ='9 - 5yr Collision (Previous)'!$E$41 -> 1.8 | F43: ='9 - Collision Benefits'!$H$17 -> 352511.48 | G43: ='9 - Collision Benefits'!$E$17 -> 16380000 | H43: =F43+G43 -> 16732511 | I43: =H43/((1+$E$91)^C43) -> 14013215 | J43: =H43/((1+$E$92)^C43) -> 11149579
B44: 2021 | C44: 7 | D44: ='9 - 5yr Collision (Previous)'!$E$40 -> 4.2 | E44: ='9 - 5yr Collision (Previous)'!$E$41 -> 1.8 | F44: ='9 - Collision Benefits'!$H$17 -> 352511.48 | G44: ='9 - Collision Benefits'!$E$17 -> 16380000 | H44: =F44+G44 -> 16732511 | I44: =H44/((1+$E$91)^C44) -> 13605063 | J44: =H44/((1+$E$92)^C44) -> 10420167
B45: 2022 | C45: 8 | D45: ='9 - 5yr Collision (Previous)'!$E$40 -> 4.2 | E45: ='9 - 5yr Collision (Previous)'!$E$41 -> 1.8 | F45: ='9 - Collision Benefits'!$H$17 -> 352511.48 | G45: ='9 - Collision Benefits'!$E$17 -> 16380000 | H45: =F45+G45 -> 16732511 | I45: =H45/((1+$E$91)^C45) -> 13208799 | J45: =H45/((1+$E$92)^C45) -> 9738474
B46: 2023 | C46: 9 | D46: ='9 - 5yr Collision (Previous)'!$E$40 -> 4.2 | E46: ='9 - 5yr Collision (Previous)'!$E$41 -> 1.8 | F46: ='9 - Collision Benefits'!$H$17 -> 352511.48 | G46: ='9 - Collision Benefits'!$E$17 -> 16380000 | H46: =F46+G46 -> 16732511 | I46: =H46/((1+$E$91)^C46) -> 12824077 | J46: =H46/((1+$E$92)^C46) -> 9101377.6
B47: 2024 | C47: 10 | D47: ='9 - 5yr Collision (Previous)'!$E$40 -> 4.2 | E47: ='9 - 5yr Collision (Previous)'!$E$41 -> 1.8 | F47: ='9 - Collision Benefits'!$H$17 -> 352511.48 | G47: ='9 - Collision Benefits'!$E$17 -> 16380000 | H47: =F47+G47 -> 16732511 | I47: =H47/((1+$E$91)^C47) -> 12450560 | J47: =H47/((1+$E$92)^C47) -> 8505960.4
B48: 2025 | C48: 11 | D48: ='9 - 5yr Collision (Previous)'!$E$40 -> 4.2 | E48: ='9 - 5yr Collision (Previous)'!$E$41 -> 1.8 | F48: ='9 - Collision Benefits'!$H$17 -> 352511.48 | G48: ='9 - Collision Benefits'!$E$17 -> 16380000 | H48: =F48+G48 -> 16732511 | I48: =H48/((1+$E$91)^C48) -> 12087922 | J48: =H48/((1+$E$92)^C48) -> 7949495.7
B49: 2026 | C49: 12 | D49: ='9 - 5yr Collision (Previous)'!$E$40 -> 4.2 | E49: ='9 - 5yr Collision (Previous)'!$E$41 -> 1.8 | F49: ='9 - Collision Benefits'!$H$17 -> 352511.48 | G49: ='9 - Collision Benefits'!$E$17 -> 16380000 | H49: =F49+G49 -> 16732511 | I49: =H49/((1+$E$91)^C49) -> 11735847 | J49: =H49/((1+$E$92)^C49) -> 7429435.2
... B57: 2034 | C57: 20 | D57: ='9 - 5yr Collision (Previous)'!$E$40 -> 4.2 | E57: ='9 - 5yr Collision (Previous)'!$E$41 -> 1.8 | F57: ='9 - Collision Benefits'!$H$17 -> 352511.48 | G57: ='9 - Collision Benefits'!$E$17 -> 16380000 | H57: =F57+G57 -> 16732511 | I57: =H57/((1+$E$91)^C57) -> 9264385.9 | J57: =H57/((1+$E$92)^C57) -> 4323998.9
I58: =SUM(I37:I57) -> 2.4893752e+08 | J58: =SUM(J37:J57) -> 1.7726446e+08
H60: Total Benefits | I60: =I34+I58 -> 2.5101555e+08 | J60: =J34+J58 -> 1.7871752e+08
B62: Costs
B63: Calendar Year | C63: Project Year | D63: Project Costs | E63: Operations and Maintenance Costs8 | F63: Total Project Costs | G63: Total Present Value of Collision Costs - 3% Discount (2013 dollars)1 | H63: Total Present Value of Collision Costs - 7% Discount (2013 dollars)1
B64: 2014 | C64: 0 | D64: 2711750 | E64: 0 | F64: =D64+E64 -> 2711750 | G64: =F64/((1+$E$91)^C64) -> 2711750 | H64: =F64/((1+$E$92)^C64) -> 2711750
B65: 2015 | C65: 1 | D65: 5000000 | E65: 0 | F65: =D65+E65 -> 5000000 | G65: =F65/((1+$E$91)^C65) -> 4854368.9 | H65: =F65/((1+$E$92)^C65) -> 4672897.2
B66: 2016 | C66: 2 | D66: 7288250 | E66: 0 | F66: =D66+E66 -> 7288250 | G66: =F66/((1+$E$91)^C66) -> 6869874.6 | H66: =F66/((1+$E$92)^C66) -> 6365839.8
B67: 2017 | C67: 3 | D67: 0 | E67: ='8 - O&M Costs'!$B$6 -> 20000 | F67: =D67+E67 -> 20000 | G67: =F67/((1+$E$91)^C67) -> 18302.833 | H67: =F67/((1+$E$92)^C67) -> 16325.958
B68: 2018 | C68: 4 | D68: 0 | E68: ='8 - O&M Costs'!$B$6 -> 20000 | F68: =D68+E68 -> 20000 | G68: =F68/((1+$E$91)^C68) -> 17769.741 | H68: =F68/((1+$E$92)^C68) -> 15257.904
B69: 2019 | C69: 5 | D69: 0 | E69: ='8 - O&M Costs'!$B$6 -> 20000 | F69: =D69+E69 -> 20000 | G69: =F69/((1+$E$91)^C69) -> 17252.176 | H69: =F69/((1+$E$92)^C69) -> 14259.724
B70: 2020 | C70: 6 | D70: 0 | E70: ='8 - O&M Costs'!$B$6 -> 20000 | F70: =D70+E70 -> 20000 | G70: =F70/((1+$E$91)^C70) -> 16749.685 | H70: =F70/((1+$E$92)^C70) -> 13326.844
B71: 2021 | C71: 7 | D71: 0 | E71: ='8 - O&M Costs'!$B$6 -> 20000 | F71: =D71+E71 -> 20000 | G71: =F71/((1+$E$91)^C71) -> 16261.83 | H71: =F71/((1+$E$92)^C71) -> 12454.995
B72: 2022 | C72: 8 | D72: 0 | E72: ='8 - O&M Costs'!$B$6 -> 20000 | F72: =D72+E72 -> 20000 | G72: =F72/((1+$E$91)^C72) -> 15788.185 | H72: =F72/((1+$E$92)^C72) -> 11640.182
B73: 2023 | C73: 9 | D73: 0 | E73: ='8 - O&M Costs'!$B$6 -> 20000 | F73: =D73+E73 -> 20000 | G73: =F73/((1+$E$91)^C73) -> 15328.335 | H73: =F73/((1+$E$92)^C73) -> 10878.675
B74: 2024 | C74: 10 | D74: 0 | E74: ='8 - O&M Costs'!E15 -> 774400 | F74: =D74+E74 -> 774400 | G74: =F74/((1+$E$91)^C74) -> 576226.33 | H74: =F74/((1+$E$92)^C74) -> 393665.69
B75: 2025 | C75: 11 | D75: 0 | E75: ='8 - O&M Costs'!$B$6 -> 20000 | F75: =D75+E75 -> 20000 | G75: =F75/((1+$E$91)^C75) -> 14448.426 | H75: =F75/((1+$E$92)^C75) -> 9501.8559
B76: 2026 | C76: 12 | D76: 0 | E76: ='8 - O&M Costs'!$B$6 -> 20000 | F76: =D76+E76 -> 20000 | G76: =F76/((1+$E$91)^C76) -> 14027.598 | H76: =F76/((1+$E$92)^C76) -> 8880.2392
B77: 2027 | C77: 13 | D77: 0 | E77: ='8 - O&M Costs'!$B$6 -> 20000 | F77: =D77+E77 -> 20000 | G77: =F77/((1+$E$91)^C77) -> 13619.027 | H77: =F77/((1+$E$92)^C77) -> 8299.289
B78: 2028 | C78: 14 | D78: 0 | E78: ='8 - O&M Costs'!$B$6 -> 20000 | F78: =D78+E78 -> 20000 | G78: =F78/((1+$E$91)^C78) -> 13222.356 | H78: =F78/((1+$E$92)^C78) -> 7756.3448
B79: 2029 | C79: 15 | D79: 0 | E79: ='8 - O&M Costs'!$B$6 -> 20000 | F79: =D79+E79 -> 20000 | G79: =F79/((1+$E$91)^C79) -> 12837.239 | H79: =F79/((1+$E$92)^C79) -> 7248.9204
B80: 2030 | C80: 16 | D80: 0 | E80: ='8 - O&M Costs'!$B$6 -> 20000 | F80: =D80+E80 -> 20000 | G80: =F80/((1+$E$91)^C80) -> 12463.339 | H80: =F80/((1+$E$92)^C80) -> 6774.692
B81: 2031 | C81: 17 | D81: 0 | E81: ='8 - O&M Costs'!$B$6 -> 20000 | F81: =D81+E81 -> 20000 | G81: =F81/((1+$E$91)^C81) -> 12100.329 | H81: =F81/((1+$E$92)^C81) -> 6331.4878
B82: 2032 | C82: 18 | D82: 0 | E82: ='8 - O&M Costs'!$B$6 -> 20000 | F82: =D82+E82 -> 20000 | G82: =F82/((1+$E$91)^C82) -> 11747.892 | H82: =F82/((1+$E$92)^C82) -> 5917.2783
B83: 2033 | C83: 19 | D83: 0 | E83: ='8 - O&M Costs'!$B$6 -> 20000 | F83: =D83+E83 -> 20000 | G83: =F83/((1+$E$91)^C83) -> 11405.721 | H83: =F83/((1+$E$92)^C83) -> 5530.1667
B84: 2034 | C84: 20 | D84: 0 | E84: ='8 - O&M Costs'!E15 -> 774400 | F84: =D84+E84 -> 774400 | G84: =F84/((1+$E$91)^C84) -> 428766.5 | H84: =F84/((1+$E$92)^C84) -> 200119.68
D85: =SUM(D64:D71) -> 15000000 | E85: =SUM(E64:E84) -> 1868800 | F85: =SUM(F64:F84) -> 16868800 | G85: =SUM(G64:G84) -> 15674311 | H85: =SUM(H64:H84) -> 14504657
F87: Total Costs | G87: =G61+G85 -> 15674311 | H87: =H61+H85 -> 14504657
B89: Assumptions:
A90: 1 | B90: Discount rate assumed for public expenditures per Federal Office of Management and Budget (OMB) Ciculars A-4 and A-94.
C91: Discount rate | E91: 0.03
C92: Discount rate | E92: 0.07
A93: 2 | B93: See Appendix B: Truck Traffic. Percent truck traffic includes buses and is based on Truck Traffic Turning Movement Counts taken by the Contra Costa County
B94: Public Works Department from May 12-15, 2008.
C95: Percent Truck Traffic | E95: =649/15618 -> 0.041554616
A96: 3 | B96: Recommended hourly values of travel time savings taken from the US DOT memorandum "Revised Departmental Guidance on Valuation of
B97: Travel Time in Economic Analysis (Revision 2 - corrected)".
C98: Recommended Hourly Value of Travel Time Savings (Table 4, Intercity Personal) | H98: 16.7 | I98: per person-hour
C99: Recommended Hourly Value of Travel Time Savings (Table 4, Intercity Business) | H99: 22.9 | I99: per person-hour
A100: 4 | B100: See Appendix A: Traffic Volumes. Affected drivers assuming straight-line approximation (1.5% annual increase) of future traffic volumes from the Contra Costa
B101: Transportation Authority Travel Demand Model, 2012.
A102: 5 | B102: See Appendix C: Travel Time Savings. Average travel time saved calculated for peak 15-minute period per Chapter 20 - Two lane Highways, HCM 2000.
B103: Assuming a base free flow speed of 65 miles per hour and using vehicular traffic counts taken by the Contra Costa County Public Works Department on Vasco
B104: Road - 1 mile South of Camino Diablo on August 5, 2009.
A105: 6 | B105: See Appendix D: Collision History and Appendix E: 5-year Collision Data. Average annual collisions prevented based on analysis of 2004-2008 collisions data.
A106: 7 | B106: See Appendix F: Collisions Benefits. Collisions Benefits calculated using AIS calculation.
A107: 8 | B107: See Appendix G: Operations & Maintenance Costs for calculations of marginal costs.

Sheet 9 - 5yr Collision (Previous)
A1: ATTACHMENT 9: Prior 5-Year Collision Data (2004-2008)
A3: Collision Reports 2004-2008
A4: Vasco Road Safety Improvements - Phase 2
A5: Source: Collision Reports, California Highway Patrol (CHP)
A7: Primary Cause | B7: 2004 | C7: 2005 | D7: 2006 | E7: 2007 | F7: 2008 | G7: Total | H7: %
A8: Improper Turning | B8: 7 | C8: 3 | D8: 3 | E8: 2 | F8: 2 | G8: =SUM(B8:F8) -> 17 | H8: =G8/$G$21 -> 0.17
A9: Wrong Side of Road | B9: 1 | C9: 0 | D9: 0 | E9: 0 | F9: 3 | G9: =SUM(B9:F9) -> 4 | H9: =G9/$G$21 -> 0.04
A10: Unsafe Lane Change | B10: 1 | C10: 0 | D10: 0 | E10: 1 | F10: 1 | G10: =SUM(B10:F10) -> 3 | H10: =G10/$G$21 -> 0.03
A11: Unsafe Speed | B11: 12 | C11: 13 | D11: 16 | E11: 6 | F11: 2 | G11: =SUM(B11:F11) -> 49 | H11: =G11/$G$21 -> 0.49
A12: Other Equipment | B12: 0 | C12: 0 | D12: 0 | E12: 0 | F12: 1 | G12: =SUM(B12:F12) -> 1 | H12: =G12/$G$21 -> 0.01
A13: Improper Passing | B13: 1 | C13: 2 | D13: 0 | E13: 1 | F13: 1 | G13: =SUM(B13:F13) -> 5 | H13: =G13/$G$21 -> 0.05
A14: Auto R/W Violation | B14: 0 | C14: 1 | D14: 2 | E14: 2 | F14: 0 | G14: =SUM(B14:F14) -> 5 | H14: =G14/$G$21 -> 0.05
A15: Following Too Closely | B15: 0 | C15: 0 | D15: 2 | E15: 1 | F15: 0 | G15: =SUM(B15:F15) -> 3 | H15: =G15/$G$21 -> 0.03
A16: Driving Under Influence | B16: 2 | C16: 0 | D16: 2 | E16: 0 | F16: 0 | G16: =SUM(B16:F16) -> 4 | H16: =G16/$G$21 -> 0.04
A17: Other Than Driver or Ped | B17: 3 | C17: 2 | D17: 1 | E17: 0 | F17: 0 | G17: =SUM(B17:F17) -> 6 | H17: =G17/$G$21 -> 0.06
A18: Unknown | B18: 1 | C18: 0 | D18: 0 | E18: 0 | F18: 0 | G18: =SUM(B18:F18) -> 1 | H18: =G18/$G$21 -> 0.01
A19: Traffic Signals and Signs | B19: 1 | C19: 0 | D19: 0 | E19: 0 | F19: 0 | G19: =SUM(B19:F19) -> 1 | H19: =G19/$G$21 -> 0.01
A20: Other Hazardous Movement | B20: 1 | C20: 0 | D20: 0 | E20: 0 | F20: 0 | G20: =SUM(B20:F20) -> 1 | H20: =G20/$G$21 -> 0.01
A21: Total | B21: =SUM(B8:B20) -> 30 | C21: =SUM(C8:C20) -> 21 | D21: =SUM(D8:D20) -> 26 | E21: =SUM(E8:E20) -> 13 | F21: =SUM(F8:F20) -> 10 | G21: =SUM(B21:F21) -> 100 | H21: =SUM(H8:H20) -> 1
B23: 2004 | C23: 2005 | D23: 2006 | E23: 2007 | F23: 2008 | G23: Total
A24: Total Collisions | B24: 30 | C24: 21 | D24: 26 | E24: 13 | F24: 10 | G24: =SUM(B24:F24) -> 100
A25: Injury Collisions | B25: 11 | C25: 8 | D25: 12 | E25: 5 | F25: 4 | G25: =SUM(B25:F25) -> 40
A26: Fatal Collisions | B26: 1 | C26: 1 | D26: 2 | E26: 0 | F26: 0 | G26: =SUM(B26:F26) -> 4
A28: Severity | B28: 2004 | C28: 2005 | D28: 2006 | E28: 2007 | F28: 2008 | G28: Total
A29: Injuries | B29: 20 | C29: 13 | D29: 17 | E29: 5 | F29: 4 | G29: =SUM(B29:F29) -> 59
A30: Fatalities | B30: 4 | C30: 1 | D30: 5 | E30: 0 | F30: 0 | G30: =SUM(B30:F30) -> 10
A31: Total | B31: =SUM(B29:B30) -> 24 | C31: =SUM(C29:C30) -> 14 | D31: =SUM(D29:D30) -> 22 | E31: =SUM(E29:E30) -> 5 | F31: =SUM(F29:F30) -> 4 | G31: =SUM(B31:F31) -> 69
A33: Collisions that could have been prevented by median barrier:
A34: Severity | B34: 2004 | C34: 2005 | D34: 2006 | E34: 2007 | F34: 2008 | G34: Total
A35: Injuries | B35: 6 | C35: 4 | D35: 7 | E35: 2 | F35: 2 | G35: =SUM(B35:F35) -> 21
A36: Fatalities | B36: 4 | C36: 1 | D36: 4 | E36: 0 | F36: 0 | G36: =SUM(B36:F36) -> 9
A37: Total | B37: =SUM(B35:B36) -> 10 | C37: =SUM(C35:C36) -> 5 | D37: =SUM(D35:D36) -> 11 | E37: =SUM(E35:E36) -> 2 | F37: =SUM(F35:F36) -> 2 | G37: =SUM(G35:G36) -> 30
B39: 5-Year Total | C39: Prevented | D39: % | E39: 5-Year Average
A40: Injuries | B40: =G29 -> 59 | C40: =G35 -> 21 | D40: =C40/B40 -> 0.3559322 | E40: =C40/5 -> 4.2
A41: Fatalities | B41: =G30 -> 10 | C41: =G36 -> 9 | D41: =C41/B41 -> 0.9 | E41: =C41/5 -> 1.8

Sheet 9 - Collision Benefits
A1: ATTACHMENT 9: Collision Benefits
A3: Average Annual Collision Benefits
A4: Source: Abbreviated Injury Scale (AIS) Calculation for Monetizing Accident Reduction, TIGER BCA Resource Guide
B6: 2004-2008 | D6: Fatal Accidents | G6: # Non-fatal Accidents
D7: # Fatalities at Crash Site | G7: Unknown if injured
D8: 1.8 | E8: $ Value | F8: Pr(AISx) | G8: 4.2 | H8: $ Value
B9: Accident Counts | E9: Fatalities * VSL | H9: [Pr(AISx)*Value(AISx)]
B10: AIS | C10: 0 | D10: 0 | E10: 0 | F10: 0.43676 | G10: =F10*$G$8 -> 1.834392 | H10: 0
C11: 1 | D11: 0 | E11: 0 | F11: 0.41739 | G11: =F11*$G$8 -> 1.753038 | H11: =27300*G11 -> 47857.937
C12: 2 | D12: 0 | E12: 0 | F12: 0.08872 | G12: =F12*$G$8 -> 0.372624 | H12: =427700*G12 -> 159371.28
C13: 3 | D13: 0 | E13: 0 | F13: 0.04817 | G13: =F13*$G$8 -> 0.202314 | H13: =95500*G13 -> 19320.987
C14: 4 | D14: 0 | E14: 0 | F14: 0.00617 | G14: =F14*$G$8 -> 0.025914 | H14: =2420600*G14 -> 62727.428
C15: 5 | D15: 0 | E15: 0 | F15: 0.00279 | G15: =F15*$G$8 -> 0.011718 | H15: =5396300*G15 -> 63233.843
C16: Fatality | D16: =D8 -> 1.8 | E16: 9100000 | F16: 0 | G16: =F16*$G$8 -> 0 | H16: 0
B17: SUBTOTALS | D17: =SUM(D10:D16) -> 1.8 | E17: =D16*E16 -> 16380000 | F17: =SUM(F10:F16) -> 1 | G17: =SUM(G10:G16) -> 4.2 | H17: =SUM(H10:H16) -> 352511.48
B19: TOTAL VALUE OF FATALITIES & INJURIES | H19: =SUM(E17,H17) -> 16732511
B21: 2008-2012 | D21: Fatal Accidents | G21: # Non-fatal Accidents
D22: # Fatalities at Crash Site | G22: Unknown if injured
D23: 0.4 | E23: $ Value | F23: Pr(AISx) | G23: 4.8 | H23: $ Value
B24: Accident Counts | E24: Fatalities * VSL | H24: [Pr(AISx)*Value(AISx)]
B25: AIS | C25: 0 | D25: 0 | E25: 0 | F25: 0.43676 | G25: =F25*$G$23 -> 2.096448 | H25: 0
C26: 1 | D26: 0 | E26: 0 | F26: 0.41739 | G26: =F26*$G$23 -> 2.003472 | H26: =27300*G26 -> 54694.786
C27: 2 | D27: 0 | E27: 0 | F27: 0.08872 | G27: =F27*$G$23 -> 0.425856 | H27: =427700*G27 -> 182138.61
C28: 3 | D28: 0 | E28: 0 | F28: 0.04817 | G28: =F28*$G$23 -> 0.231216 | H28: =95500*G28 -> 22081.128
C29: 4 | D29: 0 | E29: 0 | F29: 0.00617 | G29: =F29*$G$23 -> 0.029616 | H29: =2420600*G29 -> 71688.49
C30: 5 | D30: 0 | E30: 0 | F30: 0.00279 | G30: =F30*$G$23 -> 0.013392 | H30: =5396300*G30 -> 72267.25
C31: Fatality | D31: =D23 -> 0.4 | E31: 9100000 | F31: 0 | G31: =F31*$G$23 -> 0 | H31: 0
B32: SUBTOTALS | D32: =SUM(D25:D31) -> 0.4 | E32: =D31*E31 -> 3640000 | F32: =SUM(F25:F31) -> 1 | G32: =SUM(G25:G31) -> 4.8 | H32: =SUM(H25:H31) -> 402870.26
B34: TOTAL VALUE OF FATALITIES & INJURIES | H34: =SUM(E32,H32) -> 4042870.3
