Workbook

Sheet Descriptions
A1: 12-13 LAR Strategy Descriptions for Board Summary
A2: updated: | B2: 40358
A4: Strat # | B4: Strat Name | C4: Description
A5: A.1.1. | B5: Close Gaps in Participation and Success | C5: This strategy supports efforts to meet Closing the Gaps by 2015’s participation and success goals. Activities include implementing the P-16 College Readiness and Success Strategic Action Plan; collaborating with public schools and community-based organizations to provide information to historically underrepresented populations to prepare them academically and financially for college; ensuring the success of student recruitment and retention by Texas colleges and universities; supporting high schools with low college-going rates; implementing an outreach plan for students in foster care; promoting information on the tuition and fee exemption program; collaborating with state leadership in public education and workforce, and other stakeholders to ensure a seamless, and high-quality educational system; and supporting non-loan financial aid programs (including grants, scholarships, work-study, and instuition exemptions administered by the Coordinating Board to help financially needed students), loan forgiveness programs and loan repayment programs.
A6: A.1.2. | B6: Close Gaps by Administering Loan Programs | C6: This strategy includes funding for administration of the Hinson-Hazlewood Loan Program. No General Revenue is used to support the loan program. All of these funds are generated by the program. In FY09, 8,812 students received $87,389,984 in loans for an average loan amount of $9,917. It is estimated that 9,500 students will receive $95,000,000 in loans in FY10 for an average amount of $10,000.
A7: A.1.3. | B7: Close Gaps by Administering College Readiness Initiatives | C7: This strategy includes funding for the administration of all college readiness programs and initiatives that support the goals and objectives of the P-16 College Readiness and Success Strategic Action Plan. The Plan is designed to increase student success and decrease the number of students enrolling in developmental course work in institutions of higher education. The strategy includes staff resources for college readiness activities, including Adult Basic Education and Developmental Education activities, in the Divisions of P-16 Initiatives, Academic Affairs and Research, and Planning and Accountability.
A8: A.2.1. | B8: Close Gaps in Excellence | C8: This strategy includes funding for the academic program responsibilities of the Academic Affairs and Research Division, including funding for excellence initiatives. The strategy includes funding for the personnel whose primary responsibility is institutional program review, administration of the health-related trusteed funds (including the residency programs and the grant programs supported by the tobacco settlement funding included in Goal G), and the Coordinating Board efforts to close the gaps in excellence.
A9: A.2.2. | B9: Close Gaps in Research | C9: This strategy provides all of the funding for the administration and staff supervision of the research programs by the Academic Affairs and Research Division. The strategy includes funding for personnel whose primary responsibility is administration of the Norman Hackerman Advanced Research Program, Summer Engineering Program, Engineering Recruitment Program, Research Assessment Program, Research Development Fund, and the agency’s related efforts to close the gaps in research.
A10: A.3.1. | B10: Close Gaps by Providing Planning and Information | C10: This strategy provides all of the funding for the Planning and Accountability Division, including the Education Data Center and Information Access Initiative, and funding for planning initiatives. The strategy includes funding for the personnel whose responsibilities include planning for higher education, collection of the state’s higher education data, analysis of higher education issues, the state’s higher education accountability system, planning for the state’s higher education facilities, and higher education finance analysis. This strategy includes funding for the Higher Education Policy Institute (HEPI). The Coordinating Board received a grant from the Houston Endowment, Inc. to conduct research and analysis of the critical higher education issues that challenge Texas. HEPI has established research agendas in the four areas as approved by the Houston Endowment: student outcomes, developmental education, Hispanic student success, and cost efficiency. The project has provided the Coordinating Board critical input that has shaped internal policy as well as its recommendations to the legislature, thereby fulfilling the intent of the original grant proposal. In preparation for the 2011 legislative session, HEPI is developing recommendations to further influence policy.
A11: B.1.1. | B11: License Plate Scholarships Program | C11: The Coordinating Board manages accounts for a number of specialty license plate programs designed to generate funding for scholarships and other education-related programs. These include (citation provided for authorizing statute in the Texas Transportation Code): • Texas Collegiate License Plate Scholarship (§ 504.615); • Houston Livestock Show and Rodeo License Plate Scholarship (§ 504.613); • Girl Scout License Plate Programs (§ 504.622); • “College for All Texans” Campaign License Plate Program (§ 504.657); • Boy Scout License Plate Scholarship (§ 504.6545); and • Cotton Boll License Plate Scholarship (§ 504.636). In a typical year, approximately 40 students will receive awards totaling $50,000 through the Collegiate License Plate program. The other specialty plates represent approximately 10 awards per year for $13,500.
A12: B.1.2. | B12: Fifth-Year Accounting Students Program | C12: The Fifth-Year Accounting Student Scholarship Program provides need-based scholarships to students who have completed 120 hours of college work and sign a statement of intent to take the Texas CPA examination. Eligible students must be enrolled on at least a half-time basis. This program was created in 1991 when the requirements to sit for the Texas CPA exam were changed from 120 to 150 hours of required course work. Because of the added financial burden of an additional year of college work, this program was created to provide scholarships to students with financial need who have completed at least 120 hours of college work, including 15 hours of Accounting. Funding in this program is provided through set-asides from state fees paid by Certified Public Accountants. HB 2440, 81st Texas legislature, shifted all scholarship activities to the Texas State Board of Public Accountancy (TSBPA) by the end of the fall 2009 term. As new fees are collected, they will be retained and accumulated by TSBPA. In accordance with these provisions, new funds for the next biennium will not be transferred to THECB.
A13: B.1.3. | B13: Early High School Graduation Scholarship Program | C13: For students graduating prior to September 1, 2005, this program provides funds for reimbursing institutions for tuition exemptions up to $1,000 to students who completed grades 9-12 in no more than 36 continuous months. For students graduating after September 1, 2005, the program provides tuition and fee exemptions up to $2,000 to students who completed grades 9-12 with the Recommended or higher High School Program in no more than 36 months. Students who graduate within 41 or 46 months may qualify (with a lesser award) if the student also graduates with a specified number of college credits. Students at independent colleges may receive awards if their colleges provide matching awards. The funding is provided from the Foundation School Fund through an inter-agency contract with the Texas Education Agency. In FY 2009, a total of 6,783 students received a total of $6,562,746 (average award of $968). Thus far in FY 2010, a total of 6,268 students have received a $5,968,540 (average award of $952).
A14: B.1.4. | B14: TANF Scholarship Program | C14: This program provides a one-year exemption from the payment of tuition and fees to students who were dependent children for whom their families received federal Temporary Assistance to Need Families (TANF) for at least six months during their senior year in high school. The funding is provided from the Foundation School Fund through an inter-agency contract with the Texas Education Agency. In FY 2009, 24 students received a total of $80,513 (average award of $3,355). Thus far in FY 2010,12 students have received $27,936 (average award of $2,328).
A15: B.1.5. | B15: Educational Aide Program | C15: The intent of this program is to encourage certain educational aides and substitute teachers to obtain full teaching certification. The Educational Aide program provides need-based exemptions from the payment of tuition and fees (other than class or laboratory fees) to students enrolled in courses leading up to teacher certification at Texas public institutions of higher education. To receive an initial award, a student must be a Texas resident, have worked at least one of the past five years as an educational aide or 180 days of the past five years as a substitute teacher, be currently employed in some capacity by a school district in Texas, show financial need, be enrolled in courses leading to teacher certification, and meet the academic progress standards of the institution. The funding is provided from the Foundation School Fund through an inter-agency contract with the Texas Education Agency. In FY 2009, a total of 4,958 students received $12,541,202 (average award of $2,529). Thus far in FY 2010, 4,022 students have received $9,326,465 (average award of $2,319).
... A69: H.1.3. | B69: Other Support Services | C69: This strategy includes Building Services, Purchasing and Supply, Mail Services, and Copy Services. Operating and support costs are allocated based on the percentage of operating budget associated with each direct strategy, with the exception of building rent, which is allocated based on the FTEs associated with each direct strategy.

Sheet EI
B1: 12-13 LAR Exceptional Items Summary -- DRAFT 06/24
A2: Ranking | B2: Agency Priority | C2: Exceptional Item Name/Strategy (in strategy order) | D2: EI Name | E2: Short EI Name | F2: Division | G2: Divisional Priority | H2: BOARD Description | I2: Short Description | J2: FY12 | K2: FY13 | L2: Biennium Total | M2: MOF
A3: 9 | B3: Exceptional Item Request #9 | C3: Texas High School Completion and Success Initiatives (HB2237) A.1.3. College Readiness Admin ($300,000/yr) | D3: Texas High School Completion and Success Initiatives (HB2237) | E3: Transfer HB2237 Funds (Admin) | F3: A1.3. | G3: 1st | H3: The 81st Texas Legislature moved the statutory responsibility for Mathematics, Science, Technology Teacher Preparatory Academies and the Intensive Programs from the public education section to the higher education section of the Texas Education Code but did not appropriate funding to the Coordinating Board. Currently, funding is provided to TEA under General Appropriations Act, Senate Bill 1, 81st Texas Legislature, Section 51 (pages III-19 and 20), Texas High School Completion and Success Initiative. In turn, TEA provides the Coordinating Board with funding through a Memorandum of Understanding. TEA has indicated they will not request funding in the 2012-2013 LAR since they have no statutory authority for these two programs. Therefore, the Coordinating Board would need to seek this appropriation in order to fund these programs for the 2012-2013. The amounts indicated above represent administrative funds. The requested grant funds are shown in Strategy E.1.10. | I3: Provides a direct appropriation to THECB of GR funds for Texas High School Completion and Success Initiative (HB 2237). These funds are currently appropriated to TEA and then transferred to CB via MOU. TEA has indicated that they will not request these funds in 12-13. | J3: 300000 | K3: 300000 | L3: =J3+K3 -> 600000 | M3: GR
A4: 10 | B4: Exceptional Item Request #10 | C4: National Student Clearinghouse Data A.3.1. Planning and Information | D4: National Student Clearing House Data | E4: National Student Clearing House Data | F4: A.3.1. | G4: 3rd | H4: To enhance the capability of research in the area of college access and success, this purchase of matching records from the National Student Clearing house would provide increased coverage of student higher education attendance patterns. Currently the longitudinal tracking is limited to only students attending higher education institutions in the state. | I4: Provides funds to purchase matching records from NSCH to provide increased coverage of student higher education attendance patterns. | J4: 250000 | K4: 250000 | L4: 500000 | M4: GR
A5: 6 | B5: Exceptional Item Request #6 | C5: Teach for Texas Loan Repayment Program -- B.1.6. | D5: Teach for Texas Loan Repayment Program | E5: Teach for Texas Loan Repay Program | F5: B.1.6. | G5: 5th | H5: The number of applications for participation in this program has increased by 76% during the past four years, and yet the funding has increased by 16% during that period. Funding for the FY2010-2011 biennium ($11.2 million) was sufficient for only 1,124 of approximately 5,000 applicant teachers in FY2010 (22%). Staff recommends raising the funding level by $19,378,557 per year over the base funding, to provide loan repayment for 5,000 teachers. (Note: For FY10 receipts from borrower payments applied to TFT conditional grants will provide loan repayment funds for approximately 200 additional teachers. This source of funds will diminish over the next few years as the loans in these portfolios are paid-in-full or go into default.) | I5: Provides loan repayment for 5,000 additional teachers. | J5: 19378557 | K5: 19378557 | L5: 38757114 | M5: GR
A6: 1 | B6: Exceptional Item Request #1 | C6: TEXAS Grants B.1.9. Student Financial Aid | D6: TEXAS Grants | E6: TEXAS Grants | F6: B.1.9. | G6: 1st | H6: CB staff recommends increased funding for this program by $148.33 million. This will enable us to keep the number of new students added to the program level with the numbers added for the 2010/2011 biennium and increase the overall number of students by over 17,000 students for the biennium. | I6: Keeps the number of new students added to the program level with the numbers added for the 2010/2011 biennium and increases the overall number of students by over 17,000 students for the biennium. | J6: 53365819 | K6: 94963455 | L6: =J6+K6 -> 148329274
A7: 2 | B7: Exceptional Item Request #2 | C7: Texas Education Opportunity Grants (TEOG) B.1.9. Student Financial Aid | D7: Texas Education Opportunity Grants (TEOG) | E7: Texas Education Opportunity Grants | F7: B.1.9. | G7: 2nd | H7: CB staff recommends that the Legislature substantially increase funding for the TEOG by $10 million. This will enable an additional 2,630 new students to enter the program during the 2012/2013 biennium and overall fund an additional 4,090 students for the biennium. | I7: Provides funding for an additional 2,630 new students to enter the program during the 2012/2013 biennium and overall funding for an additional 4,090 students for the biennium. | J7: 4706947 | K7: 5293053 | L7: =J7+K7 -> 10000000
A8: 3 | B8: Exceptional Item Request #3 | C8: Texas College Work Study B.1.9. Student Financial Aid | D8: Texas College Work Study | E8: Texas College Work Study | F8: B.1.9. | G8: 3rd | H8: CB staff recommends doubling the funding over the 2010-2011 biennium, which was $15 million. This increase will enable an additional 6,024 students to participate in the program each year of the biennium. | I8: Provides funding for an additional 6,024 students to participate in the program each year of the biennium (double the funding over the 2010-2011 biennium). | J8: 7500000 | K8: 7500000 | L8: =J8+K8 -> 15000000
A9: 4 | B9: Exceptional Item Request #4 | C9: Tuition Equalization Grants (TEG) B.1.9. | D9: Tuition Equalization Grants (TEG) | E9: Tuition Equalization Grants | F9: B.1.9. | G9: 4th | H9: CB staff recommends that the Legislature increase funding for the TEG by $10,587,465. This will enable the number of students served by the program to remain relatively steady for the 2012/2013 biennium. | I9: Provides funding to enable the number of students served by the program to remain relatively steady for the 2012/2013 biennium. | J9: 5293732 | K9: 5293733 | L9: =J9+K9 -> 10587465
A10: 5 | B10: Exceptional Item Request #5 | C10: Higher Education Performance Incentive Initiative | D10: Higher Education Performance Incentive Initiative | E10: Higher Ed Perf Incentive Initiative | F10: B.1.12. | G10: 1st | H10: The incentive funding was originally appropriated by rider in FY 2009 as General Revenue funds and then funded during the FY 2010-11 biennium through federal American Recovery and Reinvestment (ARRA) funds, which will not be available for FY 2012-13. This request would restore the General Revenue funding for this program. | I10: Restores GR that was replaced by ARRA funds in 10-11. | J10: 40000000 | K10: 40000000 | L10: 80000000 | M10: GR
A11: 11 | B11: Exceptional Item Request #11 | C11: Baylor College of Medicine Undergraduate Education -- D.1.1. | D11: Baylor College of Medicine Undergraduate Education | E11: Baylor College of Medicine | F11: D.1.1. | G11: 2nd | H11: This Exceptional Item funding of $6,868,594 would provide to Baylor College of Medicine (BCM) the amount it is authorized by statute to receive for each Texas medical student enrolled at the College. This per-student amount is based on the average General Revenue (GR) expended in the previous fiscal year for each medical student at The University of Texas Medical Branch at Galveston and The University of Texas Southwestern Medical Center in Dallas. The per-student amount includes GR expended by the two UT institutions for instruction and operations, infrastructure and benefits, but does not include formula funding appropriated to the UT institutions for research. This funding is the equivalent formula funding that is provided to all public Health-Related Institutions for medical education. | I11: Provides to Baylor College of Medicine the amount it is authorized by statute to receive for each Texas medical student enrolled at the College. | J11: 4637202.1 | K11: 2231392.1 | L11: 6868594.2 | M11: GR
A12: 7 | B12: Exceptional Item Request #7 | C12: Physician Education Loan Repayment Program -- D.1.8. | D12: Physician Education Loan Repayment Program | E12: Physician Ed Loan Repayment | F12: D.1.8. | G12: 6th | H12: The 81st Legislature authorized changes to the tax code relating to smokeless tobacco and directed specified percentages of the increased revenue to a new account for the PELRP. The increased funding allows for loan repayments in the amount of $25,000, $35,000, $45,000, and $55,000 for 1st, 2nd, 3rd, and 4th- year participants, for a maximum aggregate of $160,000. The State Comptroller's revenue projections for this fund exceed the amount of this exceptional item, which is requested to fund administrative costs and loan repayments totaling $13,500,000 to 450 physicians in FY2012 and $23,625,000 to 675 physicians in FY2013. The administrative costs of $346,711 in FY12 and $348,711 in FY13 include personnel costs for the 4 FTEs authorized in Contingency Rider 17.49 for the FY2010-2011 biennium. | I12: Authorizes spending authority for additional revenue available from smokeless tobacco funds (GR-D 5144) under HB 2154 (81st). | J12: 6846711 | K12: 8973711 | L12: 15820422 | M12: GR-D
A13: 8 | B13: Exceptional Item Request #8 | C13: Restoration of Reduction to College Readiness Grants Strategy -- E.1.10. | D13: Restoration of Reduction to College Readiness Grants Strategy | E13: Restoration of Reduction to CRI Grants | F13: E.1.10. | G13: 2nd | H13: This exceptional item would restore funding to the original 2010-2011 level to address the goal of the P-16 College Readiness and Success Strategic Action Plan to "reduce the need for developmental education and to increase student success." Restoring these funds would ensure the Coordinating Board has resources necessary to support vertical alignment statewide through higher education engagement activities and vertical alignment initiatives that involve both higher education and K-12 faculty. | I13: Restores 10-11 funding included in the 5% reductions. | J13: 1351445.4 | K13: 900963.6 | L13: 2252409 | M13: GR
A14: 9 | B14: Exceptional Item Request #9 | C14: Texas High School Completion and Success Initiatives (HB2237) E.1.10. College Readiness Grants ($6,009,000/yr) | D14: Texas High School Completion and Success Initiatives (HB2237) | E14: Transfer HB2237 Funds (Grants) | F14: E.1.10. | G14: 1st | H14: The 81st Texas Legislature moved the statutory responsibility for Mathematics, Science, Technology Teacher Preparatory Academies and the Intensive Programs from the public education section to the higher education section of the Texas Education Code but did not appropriate funding to the Coordinating Board. Currently, funding is provided to TEA under General Appropriations Act, Senate Bill 1, 81st Texas Legislature, Section 51 (pages III-19 and 20), Texas High School Completion and Success Initiative. In turn, TEA provides the Coordinating Board with funding through a Memorandum of Understanding. TEA has indicated they will not request funding in the 2012-2013 LAR since they have no statutory authority for these two programs. Therefore, the Coordinating Board would need to seek this appropriation in order to fund these programs for the 2012-2013. The amounts indicated above represent grants funds. The requested administrative funds are shown in Strategy A.1.3. | I14: Provides a direct appropriation to THECB of GR funds for Texas High School Completion and Success Initiative (HB 2237). These funds are currently appropriated to TEA and then transferred to CB via MOU. TEA has indicated that they will not request these funds in 12-13. | J14: =4704500-300000 -> 4404500 | K14: =4704500-300000 -> 4404500 | L14: =J14+K14 -> 8809000 | M14: GR
B15: Total, All Exceptional Items | J15: 78772916 | K15: 78043624 | L15: 1.5681654e+08

Sheet A - Baseline Request
A1: 2014-15 Baseline Request Summary
B2: Biennial Total | D2: FY14 | G2: FY 15 | L2: Biennium
B3: Gen Rev | C3: GR- Dedicated | D3: GR-Related | E3: Other | F3: TOTAL | G3: Gen Rev | H3: GR- Dedicated | I3: GR-Related | J3: Other | K3: TOTAL | L3: Gen Rev | M3: GR- Dedicated | N3: GR-Related | O3: Other | P3: TOTAL
A4: Goal A: Coordinate Higher Education
A5: A.1.1. College Readiness and Success | B5: 4437458 | C5: 0 | D5: ='[1]In and Out Base '!$L$3 -> 1863521 | E5: =SUM('[2]Agency Summary'!$H$8:$L$9) -> 0 | F5: =D5+E5 -> 1863521 | G5: 3070224 | H5: 404431 | I5: ='[1]In and Out Base '!$N$3 -> 1863521 | J5: =SUM('[2]Agency Summary'!$M$8:$Q$9) -> 0 | K5: =I5+J5 -> 1863521 | L5: =G5+B5 -> 7507682 | M5: =H5+C5 -> 404431 | N5: =SUM(F5,K5) -> 3727042 | O5: =J5+E5 -> 0 | P5: =N5+O5 -> 3727042 | S5: =N5='[3]In and Out Base '!$S$3 -> TRUE
A6: A.1.2. State Loan Programs | B6: 0 | C6: 0 | D6: =B6/2 -> 0 | E6: =SUM('[2]Agency Summary'!$H$10:$L$10) -> 5650000 | F6: =D6+E6 -> 5650000 | G6: 0 | H6: 0 | I6: =B6/2 -> 0 | J6: =SUM('[2]Agency Summary'!$M$10:$Q$10) -> 5650000 | K6: =I6+J6 -> 5650000 | L6: =G6+B6 -> 0 | M6: =H6+C6 -> 0 | N6: =D6+I6 -> 0 | O6: =J6+E6 -> 11300000 | P6: =N6+O6 -> 11300000
A7: A.1.3. Student Grants and Special Programs | B7: 2256682 | C7: 0 | D7: ='[1]In and Out Base '!$L$4 -> 925301 | E7: 0 | F7: =D7+E7 -> 925301 | G7: 1618572 | H7: 0 | I7: ='[1]In and Out Base '!$N$4 -> 925301 | J7: 0 | K7: =I7+J7 -> 925301 | L7: =G7+B7 -> 3875254 | M7: =H7+C7 -> 0 | N7: =D7+I7 -> 1850602 | O7: =J7+E7 -> 0 | P7: =N7+O7 -> 1850602 | S7: =N7='[3]In and Out Base '!$S$4 -> TRUE
A8: A.2.1. Workforce, Academic Affairs, and Research | B8: 3078290 | C8: 0 | D8: ='[1]In and Out Base '!$L$5 -> 1692255 | E8: =SUM('[2]Agency Summary'!$H$15:$L$15) -> 3000 | F8: =D8+E8 -> 1695255 | G8: 1558356 | H8: 0 | I8: =SUM('[1]In and Out Base '!$M$5:$N$5) -> 1692255 | J8: =SUM('[2]Agency Summary'!$M$15:$Q$15) -> 3000 | K8: =I8+J8 -> 1695255 | L8: =G8+B8 -> 4636646 | M8: =H8+C8 -> 0 | N8: =D8+I8 -> 3384510 | O8: =J8+E8 -> 6000 | P8: =N8+O8 -> 3390510 | S8: =N8='[3]In and Out Base '!$S$5 -> TRUE
A9: A.2.2. Close Gaps in Research | B9: 0 | C9: 0 | D9: =B9/2 -> 0 | E9: 0 | F9: =D9+E9 -> 0 | G9: 326285 | H9: 0 | I9: =B9/2 -> 0 | J9: 0 | K9: =I9+J9 -> 0 | L9: =G9+B9 -> 326285 | M9: =H9+C9 -> 0 | N9: =D9+I9 -> 0 | O9: =J9+E9 -> 0 | P9: =N9+O9 -> 0
A10: A.3.1. Planning, Information, & Evaluation | B10: 3244680 | C10: 0 | D10: ='[1]In and Out Base '!$L$6 -> 1989978 | E10: =SUM('[2]Agency Summary'!$H$16:$L$16) -> 400000 | F10: =D10+E10 -> 2389978 | G10: 2064813 | H10: 0 | I10: =SUM('[1]In and Out Base '!$M$6:$N$6) -> 1989978 | J10: =SUM('[2]Agency Summary'!$M$16:$Q$16) -> 0 | K10: =I10+J10 -> 1989978 | L10: =G10+B10 -> 5309493 | M10: =H10+C10 -> 0 | N10: =D10+I10 -> 3979956 | O10: =J10+E10 -> 400000 | P10: =N10+O10 -> 4379956 | S10: =N10='[3]In and Out Base '!$S$6 -> TRUE
A11: A.3.2. Higher Education Policy Institute | D11: =B11+C11 -> 0 | E11: =SUM('[2]Agency Summary'!$H$17:$L$17) -> 423060 | F11: =D11+E11 -> 423060 | I11: =G11+H11 -> 0 | J11: =SUM('[2]Agency Summary'!$M$17:$Q$17) -> 423060 | K11: =I11+J11 -> 423060 | N11: =D11+I11 -> 0 | O11: =J11+E11 -> 846120 | P11: =N11+O11 -> 846120
A12: Goal B: Close the Gaps by Improving Affordability
A13: B.1.1 Texas Grant Program | B13: ='B - Reductions '!I11 -> 1549925 | D13: ='[3]In and Out Base '!$L$7 -> 290391465 | E13: =SUM('[2]Agency Summary'!$H$26:$L$26) -> 5000 | F13: =D13+E13 -> 290396465 | I13: ='[3]In and Out Base '!$N$7 -> 290391465 | J13: =SUM('[2]Agency Summary'!$M$26:$Q$26) -> 5000 | K13: =I13+J13 -> 290396465 | N13: =D13+I13 -> 580782930 | O13: =J13+E13 -> 10000 | P13: =N13+O13 -> 580792930 | S13: =N13='[3]In and Out Base '!$S$7 -> TRUE
A14: B.1.2 Texas B-On-Time Program | B14: ='B - Reductions '!I12 -> 7067451 | C14: ='B - Reductions '!J12 -> 0 | D14: ='[3]In and Out Base '!$M$8 -> 40278896 | E14: 0 | F14: =D14+E14 -> 40278896 | I14: ='[3]In and Out Base '!$O$8 -> 40278895 | K14: =I14+J14 -> 40278895 | N14: =D14+I14 -> 80557791 | O14: =J14+E14 -> 0 | P14: =N14+O14 -> 80557791 | S14: =N14='[3]In and Out Base '!$S$8 -> TRUE
A15: B.1.3 Tuition Equalization Grants | B15: ='B - Reductions '!I14 -> 4006794 | D15: ='[1]In and Out Base '!$L$9 -> 84422827 | F15: =D15+E15 -> 84422827 | I15: =SUM('[1]In and Out Base '!$M$9:$N$9) -> 84422827 | K15: =I15+J15 -> 84422827 | N15: =D15+I15 -> 168845654 | O15: =J15+E15 -> 0 | P15: =N15+O15 -> 168845654 | S15: =N15='[3]In and Out Base '!$S$9 -> TRUE
A16: B.1.4 Texas Educational Opportunity Grant Prg | B16: ='B - Reductions '!I13 -> 35625000 | D16: ='[1]In and Out Base '!$L$10 -> 32674694 | F16: =D16+E16 -> 32674694 | I16: =SUM('[1]In and Out Base '!$M$10:$N$10) -> 32674694 | K16: =I16+J16 -> 32674694 | N16: =D16+I16 -> 65349388 | O16: =J16+E16 -> 0 | P16: =N16+O16 -> 65349388 | S16: =N16='[3]In and Out Base '!$S$10 -> TRUE
A17: B.1.5. College Work Study Program | B17: ='B - Reductions '!I15 -> 2637650 | D17: ='[1]In and Out Base '!$L$11 -> 7529639 | F17: =D17+E17 -> 7529639 | I17: =SUM('[1]In and Out Base '!$M$11:$N$11) -> 7529639 | K17: =I17+J17 -> 7529639 | N17: =D17+I17 -> 15059278 | O17: =J17+E17 -> 0 | P17: =N17+O17 -> 15059278 | S17: =N17='[3]In and Out Base '!$S$11 -> TRUE
A18: B.1.6. License Plate Scholarships Program | B18: 0 | C18: 1099000 | D18: ='[1]In and Out Base '!$M$12 -> 549500 | E18: =SUM('[2]Agency Summary'!$H$18:$L$18) -> 0 | F18: =D18+E18 -> 549500 | G18: 0 | H18: 93000 | I18: =SUM('[1]In and Out Base '!$M$12:$N$12) -> 549500 | J18: =SUM('[2]Agency Summary'!$M$18:$Q$18) -> 0 | K18: =I18+J18 -> 549500 | L18: =G18+B18 -> 0 | M18: =C18 -> 1099000 | N18: =D18+I18 -> 1099000 | O18: =J18+E18 -> 0 | P18: =N18+O18 -> 1099000 | S18: =N18='[3]In and Out Base '!$S$12 -> TRUE
A19: B.1.2. Fifth-Year Accounting Students Prg | B19: 0 | C19: 0 | D19: =B19+C19 -> 0 | E19: 0 | F19: =D19+E19 -> 0 | G19: 0 | H19: 0 | I19: =G19+H19 -> 0 | J19: 0 | K19: =I19+J19 -> 0 | L19: =G19+B19 -> 0 | M19: =H19+C19 -> 0 | N19: =D19+I19 -> 0 | O19: =J19+E19 -> 0 | P19: =N19+O19 -> 0
A20: B.1.7. Early High School Grad Scholarships | B20: 0 | C20: 0 | D20: =B20+C20 -> 0 | E20: =SUM('[2]Agency Summary'!$H$19:$L$19) -> 0 | F20: =D20+E20 -> 0 | G20: 0 | H20: 0 | I20: =G20+H20 -> 0 | J20: =SUM('[2]Agency Summary'!$M$19:$Q$19) -> 0 | K20: =I20+J20 -> 0 | L20: =G20+B20 -> 0 | M20: =H20+C20 -> 0 | N20: =D20+I20 -> 0 | O20: =J20+E20 -> 0 | P20: =N20+O20 -> 0
A21: B.1.8. TANF Scholarship Program | B21: 0 | C21: 0 | D21: =B21+C21 -> 0 | E21: =SUM('[2]Agency Summary'!$H$20:$L$20) -> 0 | F21: =D21+E21 -> 0 | G21: 0 | H21: 0 | I21: =G21+H21 -> 0 | J21: =SUM('[2]Agency Summary'!$M$20:$Q$20) -> 0 | K21: =I21+J21 -> 0 | L21: =G21+B21 -> 0 | M21: =H21+C21 -> 0 | N21: =D21+I21 -> 0 | O21: =J21+E21 -> 0 | P21: =N21+O21 -> 0
A22: B.1.9. Educational Aide Program | B22: 0 | C22: 0 | D22: =B22+C22 -> 0 | E22: =SUM('[2]Agency Summary'!$H$21:$L$21) -> 0 | F22: =D22+E22 -> 0 | G22: 0 | H22: 0 | I22: =G22+H22 -> 0 | J22: =SUM('[2]Agency Summary'!$M$21:$Q$21) -> 0 | K22: =I22+J22 -> 0 | L22: =G22+B22 -> 0 | M22: =H22+C22 -> 0 | N22: =D22+I22 -> 0 | O22: =J22+E22 -> 0 | P22: =N22+O22 -> 0
A23: B.1.10. Teach for Texas Loan Repayment | B23: 10000000 | C23: 0 | D23: ='[1]In and Out Base '!$L$16 -> 500000 | E23: =SUM('[2]Agency Summary'!$H$22:$L$22) -> 0 | F23: =D23+E23 -> 500000 | G23: 5771443 | H23: 0 | I23: =SUM('[1]In and Out Base '!$M$16:$N$16) -> 500000 | J23: =SUM('[2]Agency Summary'!$M$22:$Q$22) -> 0 | K23: =I23+J23 -> 500000 | L23: =B23 -> 10000000 | M23: =H23+C23 -> 0 | N23: =D23+I23 -> 1000000 | O23: =J23+E23 -> 0 | P23: =N23+O23 -> 1000000 | S23: =N23='[3]In and Out Base '!$S$16 -> TRUE
A24: B.1.11. Border Faculty Loan Repayment Prg | B24: 375626 | C24: 0 | D24: =SUM('[1]In and Out Base '!$K$17:$L$17) -> 187813 | E24: =SUM('[2]Agency Summary'!$H$23:$L$23) -> 0 | F24: =D24+E24 -> 187813 | G24: 187813 | H24: 0 | I24: =SUM('[1]In and Out Base '!$M$17:$N$17) -> 187813 | J24: =SUM('[2]Agency Summary'!$M$23:$Q$23) -> 0 | K24: =I24+J24 -> 187813 | L24: =B24 -> 375626 | M24: =H24+C24 -> 0 | N24: =D24+I24 -> 375626 | O24: =J24+E24 -> 0 | P24: =N24+O24 -> 375626 | S24: =N24='[3]In and Out Base '!$S$17 -> TRUE
A25: B.1.12. OAG Lawyers Loan Repayment Prg | B25: 496072 | C25: 0 | D25: =SUM('[1]In and Out Base '!$K$18:$L$18) -> 248036 | E25: =SUM('[2]Agency Summary'!$H$24:$L$24) -> 0 | F25: =D25+E25 -> 248036 | G25: 330715 | H25: 0 | I25: =SUM('[1]In and Out Base '!$M$18:$N$18) -> 248036 | J25: =SUM('[2]Agency Summary'!$M$24:$Q$24) -> 0 | K25: =I25+J25 -> 248036 | L25: =B25 -> 496072 | M25: =H25+C25 -> 0 | N25: =D25+I25 -> 496072 | O25: =J25+E25 -> 0 | P25: =N25+O25 -> 496072 | S25: =N25='[3]In and Out Base '!$S$18 -> TRUE
A26: B.1.13. Doctoral Incentive Program | B26: 0 | C26: 0 | D26: =B26+C26 -> 0 | E26: =SUM('[2]Agency Summary'!$H$31:$L$31) -> 0 | F26: =D26+E26 -> 0 | G26: 650000 | H26: 0 | I26: 0 | J26: =SUM('[2]Agency Summary'!$M$31:$Q$31) -> 0 | K26: =I26+J26 -> 0 | L26: =G26+B26 -> 650000 | M26: =H26+C26 -> 0 | N26: =D26+I26 -> 0 | O26: =J26+E26 -> 0 | P26: =N26+O26 -> 0
A27: B.1.14. Engineering Recruitment Program | B27: 0 | C27: 0 | D27: =B27+C27 -> 0 | E27: =SUM('[2]Agency Summary'!$H$32:$L$32) -> 0 | F27: =D27+E27 -> 0 | G27: 950000 | H27: 0 | I27: 0 | J27: =SUM('[2]Agency Summary'!$M$32:$Q$32) -> 0 | K27: =I27+J27 -> 0 | L27: =G27+B27 -> 950000 | M27: =H27+C27 -> 0 | N27: =D27+I27 -> 0 | O27: =J27+E27 -> 0 | P27: =N27+O27 -> 0
A28: B.1.15. Top Ten Percent Scholarships | B28: 8500000 | C28: 0 | D28: ='[1]In and Out Base '!$L$21 -> 4250000 | E28: =SUM('[2]Agency Summary'!$H$34:$L$34) -> 0 | F28: =D28+E28 -> 4250000 | G28: 25612000 | H28: 0 | I28: =SUM('[1]In and Out Base '!$M$21:$N$21) -> 4250000 | J28: =SUM('[2]Agency Summary'!$M$34:$Q$34) -> 0 | K28: =I28+J28 -> 4250000 | L28: =G28+B28 -> 34112000 | M28: =H28+C28 -> 0 | N28: =D28+I28 -> 8500000 | O28: =J28+E28 -> 0 | P28: =N28+O28 -> 8500000 | S28: =N28='[3]In and Out Base '!$S$21 -> TRUE
A29: B.1.16. Texas Armed Services Scholarships | B29: 4220000 | C29: 0 | D29: ='[3]In and Out Base '!$L$22 -> 3560000 | E29: =SUM('[2]Agency Summary'!$H$35:$L$35) -> 0 | F29: =D29+E29 -> 3560000 | G29: 875000 | H29: 0 | I29: ='[3]In and Out Base '!$N$22 -> 3560000 | J29: =SUM('[2]Agency Summary'!$M$35:$Q$35) -> 0 | K29: =I29+J29 -> 3560000 | L29: =G29+B29 -> 5095000 | M29: =H29+C29 -> 0 | N29: =D29+I29 -> 7120000 | O29: =J29+E29 -> 0 | P29: =N29+O29 -> 7120000 | S29: =N29='[3]In and Out Base '!$S$22 -> TRUE
A30: B.1.17. Combat Tuition Reimbursement Prg | B30: 0 | C30: 0 | D30: =B30+C30 -> 0 | E30: =SUM('[2]Agency Summary'!$H$36:$L$36) -> 0 | F30: =D30+E30 -> 0 | G30: 349500 | H30: 0 | I30: 0 | J30: =SUM('[2]Agency Summary'!$M$36:$Q$36) -> 0 | K30: =I30+J30 -> 0 | L30: =G30+B30 -> 349500 | M30: =H30+C30 -> 0 | N30: =D30+I30 -> 0 | O30: =J30+E30 -> 0 | P30: =N30+O30 -> 0
A31: B.1.18. Texas Career Opportunity Grants | B31: 0 | C31: 0 | D31: =B31+C31 -> 0 | E31: =SUM('[2]Agency Summary'!$H$37:$L$37) -> 0 | F31: =D31+E31 -> 0 | G31: 642500 | H31: 0 | I31: 0 | J31: =SUM('[2]Agency Summary'!$M$37:$Q$37) -> 0 | K31: =I31+J31 -> 0 | L31: =G31+B31 -> 642500 | M31: =H31+C31 -> 0 | N31: =D31+I31 -> 0 | O31: =J31+E31 -> 0 | P31: =N31+O31 -> 0
A32: B.1.19. T-STEM Challenge Scholarship Prg | B32: 0 | C32: 0 | D32: =B32/2 -> 0 | E32: =SUM('[2]Agency Summary'!$H$39:$L$39) -> 3000000 | F32: =D32+E32 -> 3000000 | I32: =B32/2 -> 0 | J32: =SUM('[2]Agency Summary'!$M$39:$Q$39) -> 3000000 | K32: =I32+J32 -> 3000000 | N32: =D32+I32 -> 0 | O32: =SUM(E32,J32) -> 6000000 | P32: =N32+O32 -> 6000000
A33: Goal C: Close the Gaps by Providing Trusteed Funds for Research
A34: C.1.1. N. Hackerman Advanced Research Prg | B34: 3000000 | C34: 0 | D34: =SUM('[1]In and Out Base '!$K$26:$L$26) -> 1000000 | E34: =SUM('[2]Agency Summary'!$H$40:$L$40) -> 0 | F34: =D34+E34 -> 1000000 | G34: 0 | H34: 0 | I34: UB | J34: =SUM('[2]Agency Summary'!$M$40:$Q$40) -> 0 | K34: =J34 -> 0 | L34: =G34+B34 -> 3000000 | M34: =H34+C34 -> 0 | N34: =D34 -> 1000000 | O34: =J34+E34 -> 0 | P34: =N34+O34 -> 1000000 | S34: =N34='[3]In and Out Base '!$S$26 -> TRUE
A35: C.1.2. Texas Research Incentive Prg | B35: 35625000 | D35: =SUM('[1]In and Out Base '!$K$27:$L$27) -> 17812500 | E35: =SUM('[2]Agency Summary'!$H$38:$L$38) -> 0 | F35: =D35+E35 -> 17812500 | I35: =SUM('[1]In and Out Base '!$M$27:$N$27) -> 17812500 | J35: =SUM('[2]Agency Summary'!$M$38:$Q$38) -> 0 | K35: =I35+J35 -> 17812500 | N35: =D35+I35 -> 35625000 | O35: =E35+J35 -> 0 | P35: =N35+O35 -> 35625000 | S35: =N35='[3]In and Out Base '!$S$27 -> TRUE
A36: Goal D: Close the Gaps by Providing Trusteed Funds for Health Care Education
A37: D.1.1. Family Practice Residency Program | B37: 7600000 | C37: 0 | D37: ='[1]In and Out Base '!$L$28 -> 4800000 | E37: =SUM('[2]Agency Summary'!$H$43:$L$43) -> 0 | F37: =D37+E37 -> 4800000 | G37: 0 | H37: 0 | I37: =SUM('[1]In and Out Base '!$M$28:$N$28) -> 4800000 | J37: =SUM('[2]Agency Summary'!$M$43:$Q$43) -> 0 | K37: =I37+J37 -> 4800000 | L37: =G37+B37 -> 7600000 | M37: =H37+C37 -> 0 | N37: =D37+I37 -> 9600000 | O37: =J37+E37 -> 0 | P37: =N37+O37 -> 9600000 | S37: =N37='[3]In and Out Base '!$S$28 -> TRUE
A38: D.1.2. Preceptorship Program | B38: 0 | C38: 0 | D38: =B38+C38 -> 0 | E38: =SUM('[2]Agency Summary'!$H$44:$L$44) -> 0 | F38: =D38+E38 -> 0 | G38: 0 | H38: 0 | I38: 0 | J38: =SUM('[2]Agency Summary'!$M$44:$Q$44) -> 0 | K38: =I38+J38 -> 0 | L38: =G38+B38 -> 0 | M38: =H38+C38 -> 0 | N38: =D38+I38 -> 0 | O38: =J38+E38 -> 0 | P38: =N38+O38 -> 0
A39: D.1.3. Primary Care Residency Program | B39: 0 | C39: 0 | D39: =B39+C39 -> 0 | E39: =SUM('[2]Agency Summary'!$H$45:$L$45) -> 0 | F39: =D39+E39 -> 0 | G39: 0 | H39: 0 | I39: 0 | J39: =SUM('[2]Agency Summary'!$M$45:$Q$45) -> 0 | K39: =I39+J39 -> 0 | L39: =G39+B39 -> 0 | M39: =H39+C39 -> 0 | N39: =D39+I39 -> 0 | O39: =J39+E39 -> 0 | P39: =N39+O39 -> 0
A40: D.1.4. Graduate Medical Education (GME) | B40: 0 | C40: 0 | D40: =B40+C40 -> 0 | E40: =SUM('[2]Agency Summary'!$H$46:$L$46) -> 0 | F40: =D40+E40 -> 0 | G40: 0 | H40: 0 | I40: 0 | J40: =SUM('[2]Agency Summary'!$M$46:$Q$46) -> 0 | K40: =I40+J40 -> 0 | L40: =G40+B40 -> 0 | M40: =H40+C40 -> 0 | N40: =D40+I40 -> 0 | O40: =J40+E40 -> 0 | P40: =N40+O40 -> 0
A41: D.1.5. Joint Admission Medical Prg (JAMP) | B41: 4006794 | C41: 0 | D41: ='[1]In and Out Base '!$L$32 -> 4006794 | E41: =SUM('[2]Agency Summary'!$H$47:$L$47) -> 0 | F41: =D41+E41 -> 4006794 | G41: 0 | H41: 0 | I41: ='[1]In and Out Base '!$N$32 -> UB | J41: =SUM('[2]Agency Summary'!$M$47:$Q$47) -> 0 | K41: =J41 -> 0 | L41: =G41+B41 -> 4006794 | M41: =H41+C41 -> 0 | N41: =D41 -> 4006794 | O41: =J41+E41 -> 0 | P41: =N41+O41 -> 4006794 | S41: =N41='[3]In and Out Base '!$S$32 -> TRUE
A42: D.1.6. Physician Education Loan Repayment | B42: 0 | C42: 5600000 | D42: ='[1]In and Out Base '!$M$33 -> 2800000 | E42: =SUM('[2]Agency Summary'!$H$48:$L$48) -> 0 | F42: =D42+E42 -> 2800000 | G42: 0 | H42: 0 | I42: =SUM('[1]In and Out Base '!$M$33:$N$33) -> 2800000 | J42: =SUM('[2]Agency Summary'!$M$48:$Q$48) -> 0 | K42: =I42+J42 -> 2800000 | L42: =G42+B42 -> 0 | M42: =H42+C42 -> 5600000 | N42: =D42+I42 -> 5600000 | O42: =J42+E42 -> 0 | P42: =N42+O42 -> 5600000 | S42: =N42='[3]In and Out Base '!$S$33 -> TRUE
A43: D.1.7. Financial Aid: Prof Nursing Students | B43: 0 | C43: 0 | D43: =B43+C43 -> 0 | E43: =SUM('[2]Agency Summary'!$H$49:$L$49) -> 0 | F43: =D43+E43 -> 0 | G43: 0 | H43: 0 | I43: =G43+H43 -> 0 | J43: =SUM('[2]Agency Summary'!$M$49:$Q$49) -> 0 | K43: =I43+J43 -> 0 | L43: =G43+B43 -> 0 | M43: =H43+C43 -> 0 | N43: =D43+I43 -> 0 | O43: =J43+E43 -> 0 | P43: =N43+O43 -> 0
A44: D.1.8. Fin Aid: Vocational Nurs Students | B44: 0 | C44: 0 | D44: =B44+C44 -> 0 | E44: =SUM('[2]Agency Summary'!$H$50:$L$50) -> 0 | F44: =D44+E44 -> 0 | G44: 0 | H44: 0 | I44: =G44+H44 -> 0 | J44: =SUM('[2]Agency Summary'!$M$50:$Q$50) -> 0 | K44: =I44+J44 -> 0 | L44: =G44+B44 -> 0 | M44: =H44+C44 -> 0 | N44: =D44+I44 -> 0 | O44: =J44+E44 -> 0 | P44: =N44+O44 -> 0
A45: D.1.9. Dental Education Loan Repayment | B45: 0 | C45: 0 | D45: =B45+C45 -> 0 | E45: =SUM('[2]Agency Summary'!$H$51:$L$51) -> 0 | F45: =D45+E45 -> 0 | G45: 0 | H45: 0 | I45: =G45+H45 -> 0 | J45: =SUM('[2]Agency Summary'!$M$51:$Q$51) -> 0 | K45: =I45+J45 -> 0 | L45: =G45+B45 -> 0 | M45: =H45+C45 -> 0 | N45: =D45+I45 -> 0 | O45: =J45+E45 -> 0 | P45: =N45+O45 -> 0
A46: D.1.10. Prof Nursing Shortage Reduction | B46: 30000000 | C46: 0 | D46: =SUM('[1]In and Out Base '!$K$37:$L$37) -> 15000000 | E46: =SUM('[2]Agency Summary'!$H$52:$L$52) -> 0 | F46: =D46+E46 -> 15000000 | G46: 21046739 | H46: 0 | I46: =SUM('[1]In and Out Base '!$M$37:$N$37) -> 15000000 | J46: =SUM('[2]Agency Summary'!$M$52:$Q$52) -> 0 | K46: =I46+J46 -> 15000000 | L46: =G46+B46 -> 51046739 | M46: =H46+C46 -> 0 | N46: =D46+I46 -> 30000000 | O46: =J46+E46 -> 0 | P46: =N46+O46 -> 30000000 | S46: =N46='[3]In and Out Base '!$S$37 -> TRUE
A47: D.1.11. Alzheimer's Disease Centers | B47: 4230625 | C47: 0 | D47: ='[1]In and Out Base '!$L$38 -> 4230625 | E47: =SUM('[2]Agency Summary'!$H$53:$L$53) -> 0 | F47: =D47+E47 -> 4230625 | H47: 0 | I47: ='[1]In and Out Base '!$N$38 -> UB | J47: =SUM('[2]Agency Summary'!$M$53:$Q$53) -> 0 | K47: =J47 -> 0 | L47: =G47+B47 -> 4230625 | M47: =H47+C47 -> 0 | N47: =D47 -> 4230625 | O47: =J47+E47 -> 0 | P47: =N47+O47 -> 4230625 | S47: =N47='[3]In and Out Base '!$S$38 -> TRUE
A48: D.1.12. Hosp-Based Nurs Educ Partnership Grnts | B48: 0 | C48: 0 | D48: =B48+C48 -> 0 | E48: =SUM('[2]Agency Summary'!$H$54:$L$54) -> 0 | F48: =D48+E48 -> 0 | G48: 2375000 | H48: 0 | I48: 0 | J48: =SUM('[2]Agency Summary'!$M$54:$Q$54) -> 0 | K48: =I48+J48 -> 0 | L48: =G48+B48 -> 2375000 | M48: =H48+C48 -> 0 | N48: =D48+I48 -> 0 | O48: =J48+E48 -> 0 | P48: =N48+O48 -> 0
A49: D.1.13. Children’s Medicaid Loan Repayment | B49: 0 | C49: 0 | D49: =B49+C49 -> 0 | E49: =SUM('[2]Agency Summary'!$H$55:$L$55) -> 0 | F49: =D49+E49 -> 0 | G49: 0 | H49: 0 | I49: =G49+H49 -> 0 | J49: =SUM('[2]Agency Summary'!$M$55:$Q$55) -> 0 | K49: =I49+J49 -> 0 | L49: =G49+B49 -> 0 | M49: =H49+C49 -> 0 | N49: =D49+I49 -> 0 | O49: =J49+E49 -> 0 | P49: =N49+O49 -> 0
A50: D.1.14. Physician and Nurse Trauma Care | D50: =B50+C50 -> 0 | E50: 0 | F50: =D50+E50 -> 0 | I50: =G50+H50 -> 0 | J50: 0 | K50: =I50+J50 -> 0 | N50: =D50+I50 -> 0 | O50: =J50+E50 -> 0 | P50: =N50+O50 -> 0
A51: Goal E: Baylor College of Medicine
A52: E.1.1. Baylor College of Medicine UGME | B52: 75864812 | C52: 0 | D52: ='[3]In and Out Base '!$S$42 -> 0 | E52: =SUM('[2]Agency Summary'!$H$41:$L$41) -> 0 | F52: =D52+E52 -> 0 | G52: 39569961 | H52: 0 | I52: =SUM('[1]In and Out Base '!$M$42:$N$42) -> 0 | J52: =SUM('[2]Agency Summary'!$M$41:$Q$41) -> 0 | K52: =I52+J52 -> 0 | L52: =G52+B52 -> 115434773 | M52: =H52+C52 -> 0 | N52: =D52+I52 -> 0 | O52: =J52+E52 -> 0 | P52: =N52+O52 -> 0
A53: E.1.2. Baylor College of Medicine GME | B53: 10353014 | C53: 0 | D53: =[3]Reductions!$S$28 -> 0 | E53: =SUM('[2]Agency Summary'!$H$42:$L$42) -> 0 | F53: =D53+E53 -> 0 | G53: 7256038 | H53: 0 | I53: =SUM('[1]In and Out Base '!$M$43:$N$43) -> 0 | J53: =SUM('[2]Agency Summary'!$M$42:$Q$42) -> 0 | K53: =I53+J53 -> 0 | L53: =G53+B53 -> 17609052 | M53: =H53+C53 -> 0 | N53: =D53+I53 -> 0 | O53: =J53+E53 -> 0 | P53: =N53+O53 -> 0
A54: E.1.3. Tobacco Earnings - Baylor College of Med | B54: 0 | C54: 0 | D54: =B54+C54 -> 0 | E54: =SUM('[2]Agency Summary'!$H$73:$L$73) -> 1125000 | F54: =D54+E54 -> 1125000 | G54: 0 | H54: 0 | I54: =G54+H54 -> 0 | J54: =SUM('[2]Agency Summary'!$M$73:$Q$73) -> 1125000 | K54: =I54+J54 -> 1125000 | L54: =G54+B54 -> 0 | M54: =H54+C54 -> 0 | N54: =D54+I54 -> 0 | O54: =J54+E54 -> 2250000 | P54: =N54+O54 -> 2250000
A55: E.1.4. Tobacco Earnings - Perm Hlth Fund BCM | B55: 0 | C55: 0 | D55: =B55+C55 -> 0 | E55: =SUM('[2]Agency Summary'!$H$74:$L$74) -> 1915830 | F55: =D55+E55 -> 1915830 | G55: 0 | H55: 0 | I55: =G55+H55 -> 0 | J55: =SUM('[2]Agency Summary'!$M$74:$Q$74) -> 1915830 | K55: =I55+J55 -> 1915830 | L55: =G55+B55 -> 0 | M55: =H55+C55 -> 0 | N55: =D55+I55 -> 0 | O55: =J55+E55 -> 3831660 | P55: =N55+O55 -> 3831660
A56: Goal F: Close the Gaps by Providing Trusteed Funds to Improve Quality/Delivery
A57: F.1.1. Developmental Education Program | B57: 4000000 | C57: 0 | D57: =SUM('[1]In and Out Base '!$K$46:$L$46) -> 2000000 | E57: =SUM('[2]Agency Summary'!$H$57:$L$57) -> 0 | F57: =D57+E57 -> 2000000 | G57: 2375000 | H57: 0 | I57: =B57/2 -> 2000000 | J57: =SUM('[2]Agency Summary'!$M$57:$Q$57) -> 0 | K57: =I57+J57 -> 2000000 | L57: =G57+B57 -> 6375000 | M57: =H57+C57 -> 0 | N57: =D57+I57 -> 4000000 | O57: =J57+E57 -> 0 | P57: =N57+O57 -> 4000000 | S57: =N57='[3]In and Out Base '!$S$46 -> TRUE
A58: F.1.2. Centers for Teacher Education | B58: 3040706 | C58: 0 | D58: ='[1]In and Out Base '!$L$47 -> 760177 | E58: =SUM('[2]Agency Summary'!$H$58:$L$58) -> 0 | F58: =D58+E58 -> 760177 | G58: 3040705 | H58: 0 | I58: ='[1]In and Out Base '!$N$47 -> 760176 | J58: =SUM('[2]Agency Summary'!$M$58:$Q$58) -> 0 | K58: =I58+J58 -> 760176 | L58: =G58+B58 -> 6081411 | M58: =H58+C58 -> 0 | N58: =D58+I58 -> 1520353 | O58: =J58+E58 -> 0 | P58: =N58+O58 -> 1520353 | S58: =N58='[3]In and Out Base '!$S$47 -> TRUE
A59: F.1.3. Two-year Institution Enrollment Growth | B59: 0 | C59: 0 | D59: =B59+C59 -> 0 | E59: =SUM('[2]Agency Summary'!$H$59:$L$59) -> 0 | F59: =D59+E59 -> 0 | G59: 2645085 | H59: 0 | I59: 0 | J59: =SUM('[2]Agency Summary'!$M$59:$Q$59) -> 0 | K59: =I59+J59 -> 0 | L59: =G59+B59 -> 2645085 | M59: =H59+C59 -> 0 | N59: =D59+I59 -> 0 | O59: =J59+E59 -> 0 | P59: =N59+O59 -> 0
A60: F.1.4. New Community College Campuses | B60: 0 | C60: 0 | D60: =B60+C60 -> 0 | E60: =SUM('[2]Agency Summary'!$H$60:$L$60) -> 0 | F60: =D60+E60 -> 0 | G60: 0 | H60: 0 | I60: =G60+H60 -> 0 | J60: =SUM('[2]Agency Summary'!$M$60:$Q$60) -> 0 | K60: =I60+J60 -> 0 | L60: =G60+B60 -> 0 | M60: =H60+C60 -> 0 | N60: =D60+I60 -> 0 | O60: =J60+E60 -> 0 | P60: =N60+O60 -> 0
A61: F.1.5. Gen Acad Institution Enrollment Growth | B61: 0 | C61: 0 | D61: =B61+C61 -> 0 | E61: =SUM('[2]Agency Summary'!$H$61:$L$61) -> 0 | F61: =D61+E61 -> 0 | G61: 1750000 | H61: 0 | I61: 0 | J61: =SUM('[2]Agency Summary'!$M$61:$Q$61) -> 0 | K61: =I61+J61 -> 0 | L61: =G61+B61 -> 1750000 | M61: =H61+C61 -> 0 | N61: =D61+I61 -> 0 | O61: =J61+E61 -> 0 | P61: =N61+O61 -> 0
A62: F.1.6. African American Museum Internship | B62: 133432 | C62: 0 | D62: 0 | E62: =SUM('[2]Agency Summary'!$H$62:$L$62) -> 0 | F62: =D62+E62 -> 0 | G62: 88954 | H62: 0 | I62: 0 | J62: =SUM('[2]Agency Summary'!$M$62:$Q$62) -> 0 | K62: =I62+J62 -> 0 | L62: =G62+B62 -> 222386 | M62: =H62+C62 -> 0 | N62: =D62+I62 -> 0 | O62: =J62+E62 -> 0 | P62: =N62+O62 -> 0
A63: F.1.7. Adult Basic Educ Comm College Grants | B63: 4000000 | C63: 0 | D63: =SUM('[1]In and Out Base '!$K$52:$L$52) -> 2000000 | E63: =SUM('[2]Agency Summary'!$H$63:$L$63) -> 0 | F63: =D63+E63 -> 2000000 | G63: 4750000 | H63: 0 | I63: =SUM('[1]In and Out Base '!$M$52:$N$52) -> 2000000 | J63: =SUM('[2]Agency Summary'!$M$63:$Q$63) -> 0 | K63: =I63+J63 -> 2000000 | L63: =G63+B63 -> 8750000 | M63: =H63+C63 -> 0 | N63: =D63+I63 -> 4000000 | O63: =J63+E63 -> 0 | P63: =N63+O63 -> 4000000 | S63: =N63='[3]In and Out Base '!$S$52 -> TRUE
A64: F.1.8. Alt Teaching Cert Prgs at Comm Colleges | B64: 0 | C64: 0 | D64: =B64+C64 -> 0 | E64: =SUM('[2]Agency Summary'!$H$64:$L$64) -> 0 | F64: =D64+E64 -> 0 | G64: 1068750 | H64: 0 | I64: 0 | J64: =SUM('[2]Agency Summary'!$M$64:$Q$64) -> 0 | K64: =I64+J64 -> 0 | L64: =G64+B64 -> 1068750 | M64: =H64+C64 -> 0 | N64: =D64+I64 -> 0 | O64: =J64+E64 -> 0 | P64: =N64+O64 -> 0
A65: F.1.9. College Readiness Grants | B65: 0 | C65: 0 | D65: ='[1]In and Out Base '!$L$54 -> 760177 | E65: =SUM('[2]Agency Summary'!$H$65:$L$65) -> 0 | F65: =D65+E65 -> 760177 | G65: 7071300 | H65: 0 | I65: ='[1]In and Out Base '!$N$54 -> 760176 | J65: =SUM('[2]Agency Summary'!$M$65:$Q$65) -> 0 | K65: =I65+J65 -> 760176 | L65: =G65+B65 -> 7071300 | M65: =H65+C65 -> 0 | N65: =D65+I65 -> 1520353 | O65: =J65+E65 -> 0 | P65: =N65+O65 -> 1520353 | S65: =N65='[3]In and Out Base '!$S$54 -> TRUE
A66: F.1.10. Higher Educ Performance Incentive | B66: 0 | C66: 0 | D66: =B66+C66 -> 0 | E66: =SUM('[2]Agency Summary'!$H$33:$L$33) -> 0 | F66: =D66+E66 -> 0 | G66: 23750000 | H66: 0 | I66: 0 | J66: =SUM('[2]Agency Summary'!$M$33:$Q$33) -> 0 | K66: =I66+J66 -> 0 | L66: =G66+B66 -> 23750000 | M66: =H66+C66 -> 0 | N66: =D66+I66 -> 0 | O66: =J66+E66 -> 0 | P66: =N66+O66 -> 0
A67: Goal G: Close the Gaps by Providing Federal Funding to Institutions and Students
A68: G.1.1. Student Financial Assistance Programs | B68: 0 | C68: 0 | D68: =B68+C68 -> 0 | E68: 0 | F68: =D68+E68 -> 0 | G68: 0 | H68: 0 | I68: =G68+H68 -> 0 | J68: 0 | K68: =I68+J68 -> 0 | L68: =G68+B68 -> 0 | M68: =H68+C68 -> 0 | N68: =D68+I68 -> 0 | O68: =J68+E68 -> 0 | P68: =N68+O68 -> 0
A69: G.1.2. Career and Technical Ed Programs | B69: 0 | C69: 0 | D69: =B69+C69 -> 0 | E69: =SUM('[2]Agency Summary'!$H$67:$L$67) -> 24000000 | F69: =D69+E69 -> 24000000 | G69: 0 | H69: 0 | I69: =G69+H69 -> 0 | J69: =SUM('[2]Agency Summary'!$M$67:$Q$67) -> 24000000 | K69: =I69+J69 -> 24000000 | L69: =G69+B69 -> 0 | M69: =H69+C69 -> 0 | N69: =D69+I69 -> 0 | O69: =E69+J69 -> 48000000 | P69: =N69+O69 -> 48000000
A70: G.1.3. Teacher Quality Grants Programs | B70: 0 | C70: 0 | D70: =B70+C70 -> 0 | E70: =SUM('[2]Agency Summary'!$H$68:$L$68) -> 5484000 | F70: =D70+E70 -> 5484000 | G70: 0 | H70: 0 | I70: =G70+H70 -> 0 | J70: =SUM('[2]Agency Summary'!$M$68:$Q$68) -> 284000 | K70: =I70+J70 -> 284000 | L70: =G70+B70 -> 0 | M70: =H70+C70 -> 0 | N70: =D70+I70 -> 0 | O70: =J70+E70 -> 5768000 | P70: =N70+O70 -> 5768000
A71: G.1.4. College Access Challenge Grants Program | B71: 0 | C71: 0 | D71: =B71+C71 -> 0 | E71: =SUM('[2]Agency Summary'!$H$69:$L$69) -> 112000 | F71: =D71+E71 -> 112000 | G71: 0 | H71: 0 | I71: =G71+H71 -> 0 | J71: =SUM('[2]Agency Summary'!$M$69:$Q$69) -> 112000 | K71: =I71+J71 -> 112000 | L71: =G71+B71 -> 0 | M71: =H71+C71 -> 0 | N71: =D71+I71 -> 0 | O71: =J71+E71 -> 224000 | P71: =N71+O71 -> 224000
A72: G.1.5. Other Federal Grants Programs | B72: 0 | C72: 0 | D72: =B72+C72 -> 0 | E72: =SUM('[2]Agency Summary'!$H$70:$L$70) -> 291000 | F72: =D72+E72 -> 291000 | G72: 0 | H72: 0 | I72: =G72+H72 -> 0 | J72: =SUM('[2]Agency Summary'!$M$70:$Q$70) -> 263000 | K72: =I72+J72 -> 263000 | L72: =G72+B72 -> 0 | M72: =H72+C72 -> 0 | N72: =D72+I72 -> 0 | O72: =J72+E72 -> 554000 | P72: =N72+O72 -> 554000
D73: =B73+C73 -> 0 | F73: =D73+E73 -> 0 | I73: =G73+H73 -> 0 | K73: =I73+J73 -> 0 | N73: =D73+I73 -> 0 | P73: =N73+O73 -> 0
A74: Goal H: Close the Gaps by Providing Tobacco Settlement Funds to Institutions
A75: H.1.1. Tobacco Earnings - Minority Hlth Research & Ed | B75: 0 | C75: 0 | D75: =B75+C75 -> 0 | E75: =SUM('[2]Agency Summary'!$H$71:$L$71) -> 1225000 | F75: =D75+E75 -> 1225000 | G75: 0 | H75: 0 | I75: =G75+H75 -> 0 | J75: =SUM('[2]Agency Summary'!$M$71:$Q$71) -> 1225000 | K75: =I75+J75 -> 1225000 | L75: =G75+B75 -> 0 | M75: =H75+C75 -> 0 | N75: =D75+I75 -> 0 | O75: =J75+E75 -> 2450000 | P75: =N75+O75 -> 2450000
A76: H.1.2. Tobacco Earnings - Nursing, Allied Hlth, Other | B76: 0 | C76: 0 | D76: =B76+C76 -> 0 | E76: =SUM('[2]Agency Summary'!$H$72:$L$72) -> 2200000 | F76: =D76+E76 -> 2200000 | G76: 0 | H76: 0 | I76: =G76+H76 -> 0 | J76: =SUM('[2]Agency Summary'!$M$72:$Q$72) -> 2200000 | K76: =I76+J76 -> 2200000 | L76: =G76+B76 -> 0 | M76: =H76+C76 -> 0 | N76: =D76+I76 -> 0 | O76: =J76+E76 -> 4400000 | P76: =N76+O76 -> 4400000
A77: Goal I: Indirect Administration
A78: I.1.1. Central Administration | B78: 6934019 | C78: 0 | D78: ='[1]In and Out Base '!$L$63 -> 3571226 | E78: =SUM('[2]Agency Summary'!$H$75:$L$75) -> 1315186 | F78: =D78+E78 -> 4886412 | G78: 3370308 | H78: 356962 | I78: =SUM('[1]In and Out Base '!$M$63:$N$63) -> 3571225 | J78: =SUM('[2]Agency Summary'!$M$75:$Q$75) -> 1315187 | K78: =I78+J78 -> 4886412 | L78: =G78+B78 -> 10304327 | M78: =H78+C78 -> 356962 | N78: =SUM(D78,I78) -> 7142451 | O78: =J78+E78 -> 2630373 | P78: =N78+O78 -> 9772824 | S78: =N78='[3]In and Out Base '!$S$63 -> TRUE
A79: I.1.2. Information Resources | B79: 2637650 | C79: 0 | D79: =SUM('[1]In and Out Base '!$K$64:$L$64) -> 1320017 | E79: =SUM('[2]Agency Summary'!$H$76:$L$76) -> 1234032 | F79: =D79+E79 -> 2554049 | G79: 1507164 | H79: 900174 | I79: =SUM('[1]In and Out Base '!$M$64:$N$64) -> 1320016 | J79: =SUM('[2]Agency Summary'!$M$76:$Q$76) -> 1234031 | K79: =I79+J79 -> 2554047 | L79: =G79+B79 -> 4144814 | M79: =H79+C79 -> 900174 | N79: =D79+I79 -> 2640033 | O79: =J79+E79 -> 2468063 | P79: =N79+O79 -> 5108096 | S79: =N79='[3]In and Out Base '!$S$64 -> TRUE
A80: I.1.3. Other Support Services | B80: 1549925 | C80: 0 | D80: =SUM('[1]In and Out Base '!$K$65:$L$65) -> 774963 | E80: =SUM('[2]Agency Summary'!$H$77:$L$77) -> 659942 | F80: =D80+E80 -> 1434905 | G80: 911720 | H80: 516222 | I80: =SUM('[1]In and Out Base '!$M$65:$N$65) -> 774962 | J80: =SUM('[2]Agency Summary'!$M$77:$Q$77) -> 659941 | K80: =I80+J80 -> 1434903 | L80: =G80+B80 -> 2461645 | M80: =H80+C80 -> 516222 | N80: =D80+I80 -> 1549925 | O80: =J80+E80 -> 1319883 | P80: =N80+O80 -> 2869808 | S80: =N80='[3]In and Out Base '!$S$65 -> TRUE
A81: TOTAL | B81: =SUM(B5:B80) -> 280471605 | C81: =SUM(C5:C80) -> 6699000 | D81: =SUM(D5:D80) -> 531900404 | E81: =SUM(E5:E80) -> 49043050 | F81: =SUM(F5:F80) -> 580943454 | G81: =SUM(G5:G80) -> 166583945 | H81: =SUM(H5:H80) -> 2270789 | I81: =SUM(I5:I80) -> 522662979 | ... P81: =SUM(P5:P80) -> 1147021482
E83: =E81='[2]Agency Summary'!$J$80 -> TRUE | J83: =J81='[2]Agency Summary'!$O$80 -> TRUE | O83: =O81='[2]Agency Summary'!$L$81 -> TRUE
A87: Student Loan Funds Included Above: | D87: =SUM(E78:E80,E6) -> 8859160 | E87: =SUM(J6,J78:J80) -> 8859159 | F87: =SUM(D87:E87) -> 17718319
A88: Total Loan Funds Appted for 12-13: | D88: =8847085+8871234 -> 17718319 | F88: =SUM(E78:E80,J78:J80,E6,J6)=F87 -> TRUE | I88: :sl | K88: gr check: | N88: =N81='B - Reductions '!K38 -> TRUE
A89: Average Amount per FY: | D89: =D88/2 -> 8859159.5 | E89: =D81-'[3]In and Out Base '!$L$66-'[3]In and Out Base '!$M$66 -> 0 | K89: gr check: | N89: =N81='[1]In and Out Base '!$S$66 -> TRUE
E90: check 14 base | I90: =I81-'[3]In and Out Base '!$N$66-'[3]In and Out Base '!$O$66 -> 0
I91: check 15 base
N92: =N81-'B - Reductions '!K38 -> 0
A93: 1054563383 | D93: LBB approved GR/GR-D Limit
A94: =N81-A93 -> 0 | E94: =A94/2 -> 0
D112: 5103
D113: 759141
D114: 759141
D115: 449225
D116: 449227
A117: 80557791 | D117: =SUM(D113:D116) -> 2416734
A118: =A117*0.03 -> 2416733.7
A119: =48822904*0.03 -> 1464687.1
A120: =31734887*0.03 -> 952046.61

Sheet B - Reductions 
A1: 10 Percent Biennial Base Reduction Options Schedule
A3: First 5% Reduction | Z3: Second 5% Reduction
A4: (priority order) | B4: Strategy Name | C4: FY12 Budgeted | E4: FY13 Budgeted | G4: FY12-13 Budgeted Base | I4: Proposed FY14-15 Base | K4: Proposed FY14-15 Base | L4: First Proposed Reduction | O4: Second Proposed Reduction | R4: FTE Reductions (FY12-FY13 Base) | T4: First Reduction % of Proposed Base | U4: Second Reduction % of Proposed Base | V4: TOTAL Reduction % of Proposed Base | W4: Running Total | X4: Cumulative % | Z4: (priority order) | AA4: Strategy Name | AB4: Proposed FY14-15 Base | AC4: Second Proposed Reduction | AD4: Second Reduction % of Proposed Base
A5: Rank of First Reduction | C5: GR | D5: GR-D | E5: GR | F5: GR-D | G5: GR | H5: GR-D | I5: GR | J5: GR-D | K5: GR/GR-D | L5: GR | M5: GR-Dedicated | N5: GR/GR-D | O5: GR | P5: GR-Dedicated | Q5: Total GR/ GR-D | R5: FY 12 | S5: FY 13 | Z5: Rank of Second Reduction | AB5: GR/GR-D | AC5: GR/GR-D
A6: Column1 | B6: Column3 | C6: Column4 | D6: Column5 | E6: Column6 | F6: Column7 | G6: Column8 | H6: Column9 | I6: Column10 | J6: Column11 | K6: Column112 | L6: Column12 | M6: Column13 | N6: Column14 | O6: Column15 | P6: Column16 | Q6: Column17 | R6: Column18 | S6: Column19 | T6: Column20 | U6: Column21 | V6: Column22 | W6: =W4+N7+Q7 -> #VALUE! | X6: =W6/(G$38+H$38) -> #VALUE! | Z6: Column2 | AA6: Column3 | AB6: Column112 | AC6: Column17 | AD6: Column21
A7: 1 | B7: D.1.11. Alzheimer's Disease Cen | C7: 5230625 | G7: =SUM(C7,E7) -> 5230625 | H7: =SUM(D7,F7) -> 0 | I7: =[4]WAAR!F13 -> 4230625 | K7: =SUM(Table1[[#This Row],[Column10]:[Column11]]) -> 4230625 | L7: =[4]WAAR!H13 -> 0 | M7: =[4]WAAR!I13 -> 0 | N7: 627035 | O7: =[4]WAAR!H27 -> 475000 | P7: =[4]WAAR!I27 -> 0 | Q7: =SUM(O7:P7) -> 475000 | R7: 0 | S7: 0 | T7: =N7/(SUM(I7:J7)) -> 0.14821333 | U7: =Q7/SUM(I7:J7) -> 0.11227655 | V7: =(N7+Q7)/(I7+J7) -> 0.26048988 | W7: =W5+#REF!+#REF! -> #REF! | X7: =W7/(G$38+H$38) -> #REF! | Z7: 1 | AA7: D.1.11. Alzheimer's Disease Cen | AB7: 4230625 | AC7: =[1]Reductions!$Q$26 -> 152035 | AD7: =Table2[[#This Row],[Column17]]/Table2[[#This Row],[Column112]] -> 0.035936771 | AH7: E.1.2. Baylor COM-GME | AK7: =T8+Table2[[#This Row],[Column21]] -> 0.1954032
A8: 2 | B8: A.1.1. College Readiness and Success | C8: =1415140-101036 -> 1314104 | E8: =1415140-142388 -> 1272752 | G8: =SUM(C8,E8) -> 2586856 | H8: =SUM(D8,F8) -> 0 | I8: =SUM('[5]In and Out Base '!$K$3,'[5]In and Out Base '!$M$3) -> 4027042 | K8: ='A - Baseline Request'!N5 -> 3727042 | L8: =[5]Reductions!$P$4 -> 642178 | M8: 0 | N8: =L8+M8 -> 642178 | O8: =[5]Reductions!$Q$4 -> 569695 | P8: 0 | Q8: =SUM(O8:P8) -> 569695 | R8: 0 | S8: 0 | T8: =N8/(SUM(I8:J8)) -> 0.15946643 | U8: =Q8/SUM(I8:J8) -> 0.14146736 | V8: =(N8+Q8)/(I8+J8) -> 0.30093379 | W8: =#REF!+N9+Q9 -> #REF! | X8: =W8/(G$38+H$38) -> #REF! | Z8: 2 | AA8: A.1.1. College Readiness and Success | AB8: ='A - Baseline Request'!N5 -> 3727042 | AC8: 569695 | AD8: =Table2[[#This Row],[Column17]]/Table2[[#This Row],[Column112]] -> 0.15285446 | AH8: E.1.1. Baylor Col of Med UGME | AK8: =T9+Table2[[#This Row],[Column21]] -> 0.19936135
A9: 3 | B9: A.2.1. Workforce, Academic Affairs, & Research | C9: =1244915-95000+120000 -> 1269915 | E9: =1244916-97001+120000 -> 1267915 | G9: =SUM(C9,E9) -> 2537830 | H9: =SUM(D9,F9) -> 0 | I9: 3309510 | K9: ='A - Baseline Request'!N8 -> 3384510 | L9: =[5]Reductions!$P$6 -> 153915 | M9: =[4]WAAR!I8 -> 0 | N9: =L9+M9 -> 153915 | O9: =[5]Reductions!$Q$6 -> 174442 | P9: =[4]WAAR!I22 -> 0 | Q9: =SUM(O9:P9) -> 174442 | R9: 0 | S9: 0 | T9: =N9/(SUM(I9:J9)) -> 0.046506885 | U9: =Q9/SUM(I9:J9) -> 0.052709313 | V9: =(N9+Q9)/(I9+J9) -> 0.099216198 | W9: =W8+#REF!+#REF! -> #REF! | X9: =W9/(G$38+H$38) -> #REF! | Z9: 3 | AA9: A.2.1. Workforce, Academic Affairs, & Research | AB9: ='A - Baseline Request'!N8 -> 3384510 | AC9: 174442 | AD9: =Table2[[#This Row],[Column17]]/Table2[[#This Row],[Column112]] -> 0.051541287 | AH9: A.1.1. College Readiness and Success | AK9: =T10+Table2[[#This Row],[Column21]] -> 0.10010581
A10: 4 | B10: A.3.1. Planning, Information and Evaluation | C10: =1755091-107751 -> 1647340 | E10: =1755091-157751 -> 1597340 | G10: =SUM(C10,E10) -> 3244680 | H10: =SUM(D10,F10) -> 0 | I10: 3829956 | K10: ='A - Baseline Request'!N10 -> 3979956 | L10: =[5]Reductions!$P$7 -> 186000 | M10: =[4]PIE!I8 -> 0 | N10: =L10+M10 -> 186000 | O10: =[5]Reductions!$Q$7 -> 149956 | P10: =[4]PIE!I18 -> 0 | Q10: =SUM(O10:P10) -> 149956 | R10: 0 | S10: 0 | T10: =N10/(SUM(I10:J10)) -> 0.048564527 | U10: =Q10/SUM(I10:J10) -> 0.039153452 | V10: =(N10+Q10)/(I10+J10) -> 0.087717979 | W10: =#REF!+#REF!+#REF! -> #REF! | X10: =W10/(G$38+H$38) -> #REF! | Z10: 4 | AA10: A.3.1. Planning, Information and Evaluation | AB10: ='A - Baseline Request'!N10 -> 3979956 | AC10: 149956 | AD10: =Table2[[#This Row],[Column17]]/Table2[[#This Row],[Column112]] -> 0.037677803 | AH10: A.2.1. Workforce, Academic Affairs, and Research | AK10: =T11+Table2[[#This Row],[Column21]] -> 0.087677642
A11: 5 | B11: I.1.3. Other Support Services | C11: 774963 | E11: 774962 | G11: =SUM(C11,E11) -> 1549925 | H11: =SUM(D11,F11) -> 0 | I11: =[4]BSS!F21 -> 1549925 | K11: =SUM(Table1[[#This Row],[Column10]:[Column11]]) -> 1549925 | L11: =[4]BSS!H21 -> 77496 | M11: =[4]BSS!I21 -> 0 | N11: =L11+M11 -> 77496 | O11: =[4]BSS!H40 -> 77496 | P11: =[4]BSS!I40 -> 0 | Q11: =SUM(O11:P11) -> 77496 | R11: 0 | S11: 0 | T11: =N11/(SUM(I11:J11)) -> 0.049999839 | U11: =Q11/SUM(I11:J11) -> 0.049999839 | V11: =(N11+Q11)/(I11+J11) -> 0.099999677 | W11: =#REF!+N13+Q13 -> #REF! | Z11: 5 | AA11: I.1.3. Other Support Services | AB11: 1549925 | AC11: 77496 | AD11: =Table2[[#This Row],[Column17]]/Table2[[#This Row],[Column112]] -> 0.049999839 | AH11: A.3.1. Planning, Information and Evaluation | AK11: =T12+Table2[[#This Row],[Column21]] -> 0.071543815
A12: 6 | B12: I.1.1. Central Administration | C12: =2911961+615252 -> 3527213 | E12: =2911961+494845 -> 3406806 | G12: =SUM(C12,E12) -> 6934019 | H12: =SUM(D12,F12) -> 0 | I12: =[4]BSS!F20+133432 -> 7067451 | K12: ='A - Baseline Request'!N78 -> 7142451 | L12: =[4]BSS!H20 -> 346701 | M12: =[4]BSS!I20 -> 0 | N12: =[1]Reductions!$P$34 -> 152261 | O12: =[4]BSS!H39 -> 346701 | P12: =[4]BSS!I39 -> 0 | Q12: =SUM(O12:P12) -> 346701 | R12: 0 | S12: 0 | T12: =N12/(SUM(I12:J12)) -> 0.021543977 | U12: =Q12/SUM(I12:J12) -> 0.049056018 | V12: =(N12+Q12)/(I12+J12) -> 0.070599994 | W12: =W14+N15+Q15 -> #REF! | Z12: 6 | AA12: B.1.11. Border Faculty LRP | AB12: 375626 | AC12: 375626 | AD12: =Table2[[#This Row],[Column17]]/Table2[[#This Row],[Column112]] -> 1 | AH12: I.1.3. Other Sup Ser | AK12: =T14+Table2[[#This Row],[Column21]] -> 1.2370973
A13: 7 | B13: C.1.2. TX Research Incentive Pro | C13: 17812500 | E13: 17812500 | G13: =SUM(C13,E13) -> 35625000 | H13: =SUM(D13,F13) -> 0 | I13: =[4]PIE!F9 -> 35625000 | K13: =SUM(Table1[[#This Row],[Column10]:[Column11]]) -> 35625000 | L13: =ROUND([4]PIE!H9,0) -> 1781250 | M13: =[4]PIE!I9 -> 0 | N13: =ROUND(L13+M13,0) -> 1781250 | O13: =[4]PIE!H19 -> 1781250 | P13: =[4]PIE!I19 -> 0 | Q13: =ROUND(SUM(O13:P13),0) -> 1781250 | R13: 0 | S13: 0 | T13: =N13/(SUM(I13:J13)) -> 0.05 | U13: =Q13/SUM(I13:J13) -> 0.05 | V13: =(N13+Q13)/(I13+J13) -> 0.1 | W13: =W11+N14+Q14 -> #REF! | Z13: 7 | AA13: A.1.3. Student Grants and Special Prgs | AB13: 1850602 | AC13: 92530 | AD13: =Table2[[#This Row],[Column17]]/Table2[[#This Row],[Column112]] -> 0.049999946 | AH13: B.1.11. Border Faculty LRP | AK13: =T23+Table2[[#This Row],[Column21]] -> 0.049999946
A14: 8 | B14: D.1.5. Joint Admiss Md Pro | C14: 7006794 | G14: =SUM(C14,E14) -> 7006794 | H14: =SUM(D14,F14) -> 0 | I14: =[4]WAAR!F12 -> 4006794 | K14: =SUM(Table1[[#This Row],[Column10]:[Column11]]) -> 4006794 | L14: =[4]WAAR!H12 -> 950000 | M14: =[4]WAAR!I12 -> 0 | N14: =L14+M14 -> 950000 | O14: =[4]WAAR!H26 -> 475000 | P14: =[4]WAAR!I26 -> 0 | Q14: =SUM(O14:P14) -> 475000 | R14: 0 | S14: 0 | T14: =N14/(SUM(I14:J14)) -> 0.23709729 | U14: =Q14/SUM(I14:J14) -> 0.11854865 | V14: =(N14+Q14)/(I14+J14) -> 0.35564594 | W14: =W13+N12+Q12 -> #REF! | Z14: 8 | AA14: I.1.1. Central Administration | AB14: ='A - Baseline Request'!N78 -> 7142451 | AC14: 474425 | AD14: =Table2[[#This Row],[Column17]]/Table2[[#This Row],[Column112]] -> 0.066423277 | AH14: A.1.3. Student Grants and Special Prgs | AK14: =T18+Table2[[#This Row],[Column21]] -> 0.64363225
A15: 9 | B15: I.1.2. Information Resources | C15: =1281089-72067 -> 1209022 | E15: =1281089-86655+234194 -> 1428628 | G15: =SUM(C15,E15)-1299000 -> 1338650 | H15: =SUM(D15,F15) -> 0 | I15: =[4]ISS!F8 -> 2637650 | K15: ='A - Baseline Request'!N79 -> 2640033 | L15: =[4]ISS!H8 -> 0 | M15: =[4]ISS!I8 -> 0 | N15: 66933 | O15: =[4]ISS!H13 -> 66933 | P15: =[4]ISS!I13 -> 0 | Q15: =SUM(O15:P15) -> 66933 | R15: 0 | S15: 0 | T15: =N15/(SUM(I15:J15)) -> 0.025375998 | U15: =Q15/SUM(I15:J15) -> 0.025375998 | V15: =(N15+Q15)/(I15+J15) -> 0.050751995 | W15: =W12+#REF!+#REF! -> #REF! | X15: =W15/(G$38+H$38) -> #REF! | Z15: 9 | AA15: I.1.2. Information Resources | AB15: ='A - Baseline Request'!N79 -> 2640033 | AC15: 66933 | AD15: =Table2[[#This Row],[Column17]]/Table2[[#This Row],[Column112]] -> 0.025353092 | AH15: I.1.1. Central Adm | AK15: =Table1[[#This Row],[Column20]]+Table2[[#This Row],[Column21]] -> 0.05072909
A16: 10 | B16: A.1.3. Student Grants and Special Prgs | C16: =1300774-172433 -> 1128341 | E16: =1300774-172433 -> 1128341 | G16: =SUM(C16,E16) -> 2256682 | H16: =SUM(D16,F16) -> 0 | I16: 1850602 | K16: =SUM(Table1[[#This Row],[Column10]:[Column11]]) -> 1850602 | L16: =[5]Reductions!$P$5 -> 92530 | M16: =[4]P16!I9 -> 0 | N16: =L16+M16 -> 92530 | O16: =[5]Reductions!$Q$5 -> 92530 | P16: =[4]P16!I20 -> 0 | Q16: =SUM(O16:P16) -> 92530 | R16: 0 | S16: 0 | T16: =N16/(SUM(I16:J16)) -> 0.049999946 | U16: =Q16/SUM(I16:J16) -> 0.049999946 | V16: =(N16+Q16)/(I16+J16) -> 0.099999892 | W16: =#REF!+#REF!+#REF! -> #REF! | X16: =W16/(G$38+H$38) -> #REF! | Z16: 10 | AA16: D.1.10. Prof Nurse Shortage | AB16: 30000000 | AC16: 1500000 | AD16: =Table2[[#This Row],[Column17]]/Table2[[#This Row],[Column112]] -> 0.05 | AH16: I.1.2. Info Resources | AK16: =T37+Table2[[#This Row],[Column21]] -> 0.05
A17: 11 | B17: D.1.10. Prof Nurse Shortage | C17: 15000000 | E17: 15000000 | G17: =SUM(C17,E17) -> 30000000 | H17: =SUM(D17,F17) -> 0 | I17: =[4]PIE!F12 -> 30000000 | K17: =SUM(Table1[[#This Row],[Column10]:[Column11]]) -> 30000000 | L17: =[4]PIE!H12 -> 1500000 | M17: =[4]PIE!I12 -> 0 | N17: =L17+M17 -> 1500000 | O17: =[4]PIE!H22 -> 1500000 | P17: =[4]PIE!I22 -> 0 | Q17: =SUM(O17:P17) -> 1500000 | R17: 0 | S17: 0 | T17: =N17/(SUM(I17:J17)) -> 0.05 | U17: =Q17/SUM(I17:J17) -> 0.05 | V17: =(N17+Q17)/(I17+J17) -> 0.1 | W17: =#REF!+N18+Q18 -> #REF! | X17: =W17/(G$38+H$38) -> #REF! | Z17: 11 | AA17: D.1.5. Joint Admiss Md Pro | AB17: 4006794 | AC17: 475000 | AD17: =Table2[[#This Row],[Column17]]/Table2[[#This Row],[Column112]] -> 0.11854865 | AH17: F.1.2. Centers for Teacher Ed | AK17: =T13+Table2[[#This Row],[Column21]] -> 0.16854865
A18: 12 | B18: B.1.2 Texas B-On-Time | C18: 17304000 | D18: 80557791 | E18: 14104000 | G18: =SUM(C18,E18) -> 31408000 | H18: =SUM(D18,F18) -> 80557791 | I18: =[4]BSS!F15 -> 14000000 | J18: =[4]BSS!G15 -> 33000000 | K18: ='A - Baseline Request'!N14 -> 80557791 | L18: =[4]BSS!H15 -> 0 | M18: =[4]BSS!I15 -> 0 | N18: =[3]Reductions!$P$10 -> 46498680 | O18: =[4]BSS!H34 -> 0 | P18: =[4]BSS!I34 -> 0 | Q18: =SUM(O18:P18) -> 0 | T18: =N18/(SUM(Table1[[#This Row],[Column112]])) -> 0.57720898 | U18: =Q18/SUM(I18:J18) -> 0 | V18: =(N18+Q18)/(I18+J18) -> 0.98933362 | W18: =W17+#REF!+#REF! -> #REF! | X18: =W18/(G$38+H$38) -> #REF! | Z18: 12 | AA18: C.1.2. TX Research Incentive Pro | AB18: 35625000 | AC18: 1781250 | AD18: =Table2[[#This Row],[Column17]]/Table2[[#This Row],[Column112]] -> 0.05 | AH18: D.1.10. Prof Nurse Shortage | AK18: =#REF!+Table2[[#This Row],[Column21]] -> #REF!
B19: B.1.1 TEXAS Grants | C19: 325164261 | E19: 234373565 | G19: =SUM(C19,E19) -> 559537826 | H19: =SUM(D19,F19) -> 0 | I19: =[4]BSS!F12 -> 600000000 | K19: ='A - Baseline Request'!N13 -> 580782930 | L19: =[4]BSS!H12 -> 0 | M19: =[4]BSS!I12 -> 0 | N19: 0 | O19: =[4]BSS!H31 -> 40302661 | P19: =[4]BSS!I31 -> 0 | Q19: =SUM(O19:P19) -> 40302661 | T19: =N19/(SUM(I19:J19)) -> 0 | U19: =Q19/SUM(I19:J19) -> 0.067171102 | V19: =(N19+Q19)/(I19+J19) -> 0.067171102 | W19: =W18+#REF!+#REF! -> #REF! | X19: =W19/(G$38+H$38) -> #REF! | Z19: 13 | AA19: B.1.3 Tuition Equalization Grants | AB19: ='A - Baseline Request'!N15 -> 168845654 | AC19: =[3]Reductions!$Q$11 -> 9703951 | AD19: =Table2[[#This Row],[Column17]]/Table2[[#This Row],[Column112]] -> 0.057472317 | AH19: D.1.5. Joint Admiss Md Pro | AK19: =T17+Table2[[#This Row],[Column21]] -> 0.10747232
B20: B.1.3 Tuition Equalization Grants | C20: 12030800 | E20: 12030800 | G20: =SUM(C20,E20) -> 24061600 | H20: =SUM(D20,F20) -> 0 | I20: 168845954 | K20: ='A - Baseline Request'!N15 -> 168845654 | L20: 15273669 | M20: =[4]BSS!I13 -> 0 | N20: 0 | O20: =[6]BSS!$H$33 -> 15273669 | P20: =[4]BSS!I32 -> 0 | Q20: =SUM(O20:P20) -> 15273669 | T20: =N20/(SUM(I20:J20)) -> 0 | U20: =Q20/SUM(I20:J20) -> 0.090459195 | V20: =(N20+Q20)/(I20+J20) -> 0.090459195 | W20: =#REF!+#REF!+#REF! -> #REF! | X20: =W20/(G$38+H$38) -> #REF! | Z20: 14 | AA20: B.1.4. Texas Educational Opp. Grnt Prg | AB20: ='A - Baseline Request'!N16 -> 65349388 | AC20: =[3]Reductions!$Q$12 -> 3755781 | AD20: =Table2[[#This Row],[Column17]]/Table2[[#This Row],[Column112]] -> 0.057472321 | AH20: C.1.2. TX Research Incentive Pro | AK20: =T16+Table2[[#This Row],[Column21]] -> 0.10747227
B21: B.1.4. Texas Educational Opp. Grnt Prg | C21: 84422827 | E21: 84422827 | G21: =SUM(C21,E21) -> 168845654 | H21: =SUM(D21,F21) -> 0 | I21: 58649087 | K21: ='A - Baseline Request'!N16 -> 65349388 | N21: =L21+M21 -> 0 | Q21: =SUM(O21:P21) -> 0 | T21: 0 | W21: =W20+#REF!+#REF! -> #REF! | X21: =W21/(G$38+H$38) -> #REF! | Z21: 15 | AA21: B.1.1 TEXAS Grants | AB21: ='A - Baseline Request'!N13 -> 580782930 | AC21: =[3]Reductions!$Q$9 -> 33378940 | AD21: =Table2[[#This Row],[Column17]]/Table2[[#This Row],[Column112]] -> 0.057472316 | AH21: B.1.3 Tuition Equalization Grants | AK21: =#REF!+Table2[[#This Row],[Column21]] -> #REF!
B22: B.1.5 College Work Study | C22: 7529639 | E22: 7529639 | G22: =SUM(C22,E22) -> 15059278 | H22: =SUM(D22,F22) -> 0 | I22: 30000000 | K22: ='A - Baseline Request'!N17 -> 15059278 | L22: =[4]BSS!H16 -> 0 | M22: =[4]BSS!I16 -> 0 | N22: =L22+M22 -> 0 | O22: =[4]BSS!H35 -> 0 | P22: =[4]BSS!I35 -> 0 | Q22: =SUM(O22:P22) -> 0 | T22: =N22/(SUM(I22:J22)) -> 0 | U22: =Q22/SUM(I22:J22) -> 0 | V22: =(N22+Q22)/(I22+J22) -> 0 | W22: =#REF!+N19+Q19 -> #REF! | X22: =W22/(G$38+H$38) -> #REF! | AA22: B.1.2 Texas B-On-Time | AB22: ='A - Baseline Request'!N14 -> 80557791 | AC22: 0 | AD22: =Table2[[#This Row],[Column17]]/Table2[[#This Row],[Column112]] -> 0 | AH22: B.1.4. Texas Educational Opp. Grnt Prg | AK22: =#REF!+Table2[[#This Row],[Column21]] -> #REF!
B23: B.1.6. License Plate Scholarships | C23: 0 | D23: 542000 | F23: 557000 | G23: =SUM(C23,E23) -> 0 | H23: =SUM(D23,F23) -> 1099000 | J23: =[4]BSS!G8 -> 1099000 | K23: =SUM(Table1[[#This Row],[Column10]:[Column11]]) -> 1099000 | L23: =[4]BSS!H8 -> 0 | M23: =[4]BSS!I8 -> 0 | N23: =L23+M23 -> 0 | O23: =[4]BSS!H27 -> 0 | P23: =[4]BSS!I27 -> 0 | Q23: =SUM(O23:P23) -> 0 | R23: 0 | S23: 0 | T23: =N23/(SUM(I23:J23)) -> 0 | U23: =Q23/SUM(I23:J23) -> 0 | V23: =(N23+Q23)/(I23+J23) -> 0 | W23: =#REF!+N26+Q26 -> #REF! | X23: =W23/(G$38+H$38) -> #REF! | AA23: B.1.5 College Work Study | AB23: ='A - Baseline Request'!N17 -> 15059278 | AC23: 0 | AD23: =Table2[[#This Row],[Column17]]/Table2[[#This Row],[Column112]] -> 0 | AH23: B.1.1 TEXAS Grants | AK23: =+#REF!+Table2[[#This Row],[Column21]] -> #REF!
B24: B.1.10. Teach for TX LRP | C24: 500000 | E24: 500000 | G24: =SUM(C24,E24) -> 1000000 | H24: =SUM(D24,F24) -> 0 | I24: =[4]BSS!F9 -> 10000000 | K24: ='A - Baseline Request'!N23 -> 1000000 | N24: =L24+M24 -> 0 | Q24: =SUM(O24:P24) -> 0 | T24: 0 | W24: =W30+#REF!+#REF! -> #REF! | X24: =W24/(G$38+H$38) -> #REF! | AA24: B.1.6. License Plate Scholarships | AB24: ='A - Baseline Request'!N18 -> 1099000 | AC24: 0 | AD24: =Table2[[#This Row],[Column17]]/Table2[[#This Row],[Column112]] -> 0 | AH24: B.1.2 Texas B-On-Time | AK24: 0
B25: B.1.11. Border Faculty LRP | C25: 187813 | E25: 187813 | G25: =SUM(C25,E25) -> 375626 | H25: =SUM(D25,F25) -> 0 | I25: =[4]BSS!F10 -> 375626 | K25: =SUM(Table1[[#This Row],[Column10]:[Column11]]) -> 375626 | L25: =[4]BSS!H10 -> 0 | M25: =[4]BSS!I10 -> 0 | N25: =L25+M25 -> 0 | O25: =[4]BSS!H29 -> 375626 | P25: =[4]BSS!I29 -> 0 | Q25: =SUM(O25:P25) -> 375626 | R25: 0 | S25: 0 | T25: =N25/(SUM(I25:J25)) -> 0 | U25: =Q25/SUM(I25:J25) -> 1 | V25: =(N25+Q25)/(I25+J25) -> 1 | W25: =#REF!+N22+Q22 -> #REF! | X25: =W25/(G$38+H$38) -> #REF! | AA25: B.1.10. Teach for TX LRP | AB25: ='A - Baseline Request'!N23 -> 1000000 | AC25: 0 | AD25: =Table2[[#This Row],[Column17]]/Table2[[#This Row],[Column112]] -> 0 | AH25: B.1.5 College Work Study | AK25: 0
B26: B.1.12. OAG Lawyers LRP | C26: 248036 | E26: 248036 | G26: =SUM(C26,E26) -> 496072 | H26: =SUM(D26,F26) -> 0 | I26: =[4]BSS!F11 -> 496072 | K26: =SUM(Table1[[#This Row],[Column10]:[Column11]]) -> 496072 | L26: =[4]BSS!H11 -> 0 | M26: =[4]BSS!I11 -> 0 | N26: =L26+M26 -> 0 | O26: =[4]BSS!H30 -> 0 | P26: =[4]BSS!I30 -> 0 | Q26: =SUM(O26:P26) -> 0 | R26: 0 | S26: 0 | T26: =N26/(SUM(I26:J26)) -> 0 | U26: =Q26/SUM(I26:J26) -> 0 | V26: =(N26+Q26)/(I26+J26) -> 0 | W26: =W25+#REF!+#REF! -> #REF! | X26: =W26/(G$38+H$38) -> #REF! | AA26: B.1.12. OAG Lawyers LRP | AB26: =SUM(Table1[[#This Row],[Column10]:[Column11]]) -> 496072 | AC26: 0 | AD26: =Table2[[#This Row],[Column17]]/Table2[[#This Row],[Column112]] -> 0 | AH26: B.1.6. License Plate Scholarships | AK26: 0
B27: B.1.15. Top 10% Scholarships | C27: 21862446 | E27: 17762446 | G27: =SUM(C27,E27) -> 39624892 | H27: =SUM(D27,F27) -> 0 | I27: =[4]BSS!F17 -> 8500000 | K27: =SUM(Table1[[#This Row],[Column10]:[Column11]]) -> 8500000 | L27: =[4]BSS!H17 -> 0 | M27: =[4]BSS!I17 -> 0 | N27: =L27+M27 -> 0 | O27: =[4]BSS!H36 -> 0 | P27: =[4]BSS!I36 -> 0 | Q27: =SUM(O27:P27) -> 0 | R27: 0 | S27: 0 | T27: =N27/(SUM(I27:J27)) -> 0 | U27: =Q27/SUM(I27:J27) -> 0 | V27: =(N27+Q27)/(I27+J27) -> 0 | W27: =#REF!+N25+Q25 -> #REF! | X27: =W27/(G$38+H$38) -> #REF! | AA27: B.1.15. Top 10% Scholarships | AB27: =SUM(Table1[[#This Row],[Column10]:[Column11]]) -> 8500000 | AC27: 0 | AD27: =Table2[[#This Row],[Column17]]/Table2[[#This Row],[Column112]] -> 0 | AH27: B.1.10. Teach for TX LRP | AK27: =#REF!+Table2[[#This Row],[Column21]] -> #REF!
B28: B.1.16. Armed Services Scholarships | C28: 3560000 | E28: 3560000 | G28: =SUM(C28,E28) -> 7120000 | H28: =SUM(D28,F28) -> 0 | I28: =[4]BSS!F18 -> 4220000 | K28: ='[3]In and Out Base '!$S$22 -> 7120000 | L28: =[4]BSS!H18 -> 0 | M28: =[4]BSS!I18 -> 0 | N28: =L28+M28 -> 0 | O28: =[4]BSS!H37 -> 0 | P28: =[4]BSS!I37 -> 0 | Q28: =SUM(O28:P28) -> 0 | R28: 1.9 | S28: 1.9 | T28: =N28/(SUM(I28:J28)) -> 0 | U28: =Q28/SUM(I28:J28) -> 0 | V28: =(N28+Q28)/(I28+J28) -> 0 | W28: =W27+#REF!+#REF! -> #REF! | X28: =W28/(G$38+H$38) -> #REF! | AA28: B.1.16. Armed Services Scholarships | AB28: ='A - Baseline Request'!N29 -> 7120000 | AC28: 0 | AD28: =Table2[[#This Row],[Column17]]/Table2[[#This Row],[Column112]] -> 0 | AH28: B.1.12. OAG Lawyers LRP | AK28: 0
B29: C.1.1. Advanced Research Pro | C29: 1000000 | E29: 0 | G29: =SUM(C29,E29) -> 1000000 | H29: =SUM(D29,F29) -> 0 | I29: =[4]WAAR!F10 -> 3000000 | K29: ='A - Baseline Request'!N34 -> 1000000 | L29: =[4]WAAR!H10 -> 0 | M29: =[4]WAAR!I10 -> 0 | N29: =L29+M29 -> 0 | O29: =[4]WAAR!H24 -> 0 | P29: =[4]WAAR!I24 -> 0 | Q29: =SUM(O29:P29) -> 0 | R29: 0 | S29: 0 | T29: =N29/(SUM(I29:J29)) -> 0 | U29: =Q29/SUM(I29:J29) -> 0 | V29: =(N29+Q29)/(I29+J29) -> 0 | W29: =W23+N27+Q27 -> #REF! | X29: =W29/(G$38+H$38) -> #REF! | AA29: C.1.1. Advanced Research Pro | AB29: ='A - Baseline Request'!N34 -> 1000000 | AC29: 0 | AD29: =Table2[[#This Row],[Column17]]/Table2[[#This Row],[Column112]] -> 0 | AH29: B.1.15. Top 10% Scholarships | AK29: =0 -> 0
B30: D.1.1. Family Practice Res Pro | C30: 2800000 | E30: 2800000 | G30: =SUM(C30,E30) -> 5600000 | H30: =SUM(D30,F30) -> 0 | I30: =[4]WAAR!F11 -> 7600000 | K30: ='A - Baseline Request'!N37 -> 9600000 | L30: =[4]WAAR!H11 -> 0 | M30: =[4]WAAR!I11 -> 0 | N30: =L30+M30 -> 0 | O30: =[4]WAAR!H25 -> 0 | P30: =[4]WAAR!I25 -> 0 | Q30: =SUM(O30:P30) -> 0 | R30: 0 | S30: 0 | T30: =N30/(SUM(I30:J30)) -> 0 | U30: =Q30/SUM(I30:J30) -> 0 | V30: =(N30+Q30)/(I30+J30) -> 0 | W30: =W29+#REF!+#REF! -> #REF! | X30: =W30/(G$38+H$38) -> #REF! | AA30: D.1.1. Family Practice Res Pro | AB30: ='A - Baseline Request'!N37 -> 9600000 | AC30: 0 | AD30: =Table2[[#This Row],[Column17]]/Table2[[#This Row],[Column112]] -> 0 | AH30: B.1.16. Armed Services Scholarships | AK30: 0
B31: D.1.6. Physician Ed Loan Repay | C31: 0 | D31: 5600000 | G31: =SUM(C31,E31) -> 0 | H31: =SUM(D31,F31) -> 5600000 | J31: =[4]BSS!G19 -> 5600000 | K31: =SUM(Table1[[#This Row],[Column10]:[Column11]]) -> 5600000 | L31: =[4]BSS!H19 -> 0 | M31: =[4]BSS!I19 -> 0 | N31: =L31+M31 -> 0 | O31: =[4]BSS!H38 -> 0 | P31: =[4]BSS!I38 -> 0 | Q31: =SUM(O31:P31) -> 0 | R31: 0 | S31: 0 | T31: =N31/(SUM(I31:J31)) -> 0 | U31: =Q31/SUM(I31:J31) -> 0 | V31: =(N31+Q31)/(I31+J31) -> 0 | W31: =#REF!+N29+Q29 -> #REF! | X31: =W31/(G$38+H$38) -> #REF! | AA31: D.1.6. Physician Ed Loan Repay | AB31: =SUM(Table1[[#This Row],[Column10]:[Column11]]) -> 5600000 | AC31: 0 | AD31: =Table2[[#This Row],[Column17]]/Table2[[#This Row],[Column112]] -> 0 | AH31: C.1.1. Adv Research Pro | AK31: 0
B32: E.1.1. Baylor Col of Med - UGME | C32: 40123625 | E32: 35741187 | G32: =SUM(C32,E32) -> 75864812 | H32: =SUM(D32,F32) -> 0 | I32: =[4]PIE!F10 -> 75864812 | K32: 0 | N32: =L32+M32 -> 0 | Q32: =SUM(O32:P32) -> 0 | T32: 0 | W32: =W31+#REF!+#REF! -> #REF! | X32: =W32/(G$38+H$38) -> #REF! | AA32: E.1.1. Baylor Col of Med - UGME | AB32: 0 | AD32: 0 | AH32: D.1.1. Fam Pract Res Pro | AK32: 0
B33: E.1.2. Baylor Col of Med - GME | C33: 5176507 | E33: 5176507 | G33: =SUM(C33,E33) -> 10353014 | H33: =SUM(D33,F33) -> 0 | I33: =[4]PIE!F11 -> 10353014 | K33: 0 | N33: =L33+M33 -> 0 | Q33: =SUM(O33:P33) -> 0 | T33: 0 | W33: =#REF!+#REF!+#REF! -> #REF! | X33: =W33/(G$38+H$38) -> #REF! | AA33: E.1.2. Baylor Col of Med - GME | AB33: 0 | AD33: 0 | AH33: D.1.6. Physician Ed Loan Repay | AK33: 0
B34: F.1.1. Developmental Ed Program | C34: 2000000 | E34: 2000000 | G34: =SUM(C34,E34) -> 4000000 | H34: =SUM(D34,F34) -> 0 | I34: =[4]P16!F10 -> 4000000 | K34: =SUM(Table1[[#This Row],[Column10]:[Column11]]) -> 4000000 | L34: =[4]P16!H10 -> 0 | M34: =[4]P16!I10 -> 0 | N34: =L34+M34 -> 0 | O34: =[4]P16!H21 -> 0 | P34: =[4]P16!I21 -> 0 | Q34: =SUM(O34:P34) -> 0 | R34: 0 | S34: 0 | T34: =N34/(SUM(I34:J34)) -> 0 | U34: =Q34/SUM(I34:J34) -> 0 | V34: =(N34+Q34)/(I34+J34) -> 0 | W34: =#REF!+N34+Q34 -> #REF! | X34: =W34/(G$38+H$38) -> #REF! | AA34: F.1.1. Developmental Ed Program | AB34: =SUM(Table1[[#This Row],[Column10]:[Column11]]) -> 4000000 | AC34: 0 | AD34: =Table2[[#This Row],[Column17]]/Table2[[#This Row],[Column112]] -> 0 | AH34: D.1.11. Alzheimer's Dis Cen | AK34: =T7 -> 0.14821333
B35: F.1.2. Centers for Teacher Ed | C35: 1520353 | E35: 1520353 | G35: =SUM(C35,E35) -> 3040706 | H35: =SUM(D35,F35) -> 0 | I35: =[4]P16!F11 -> 3040706 | K35: ='A - Baseline Request'!N58 -> 1520353 | N35: =L35+M35 -> 0 | Q35: =SUM(O35:P35) -> 0 | T35: 0 | W35: =W34+N37+Q37 -> #REF! | X35: =W35/(G$38+H$38) -> #REF! | AA35: F.1.2. Centers for Teacher Ed | AB35: ='A - Baseline Request'!N58 -> 1520353 | AD35: =Table2[[#This Row],[Column17]]/Table2[[#This Row],[Column112]] -> 0 | AH35: F.1.1. Developmental Ed Program | AK35: 0
B36: F.1.7. ABE Community College Grants | C36: 2000000 | E36: 2000000 | G36: =SUM(C36,E36) -> 4000000 | H36: =SUM(D36,F36) -> 0 | I36: =[4]P16!F12 -> 4000000 | K36: =SUM(Table1[[#This Row],[Column10]:[Column11]]) -> 4000000 | L36: =[4]P16!H12 -> 0 | M36: =[4]P16!I12 -> 0 | N36: =L36+M36 -> 0 | O36: =[4]P16!H23 -> 0 | P36: =[4]P16!I23 -> 0 | Q36: =SUM(O36:P36) -> 0 | R36: 0 | S36: 0 | T36: =N36/(SUM(I36:J36)) -> 0 | U36: =Q36/SUM(I36:J36) -> 0 | V36: =(N36+Q36)/(I36+J36) -> 0 | AA36: F.1.7. ABE Community College Grants | AB36: 4000000 | AC36: 0 | AD36: =Table2[[#This Row],[Column17]]/Table2[[#This Row],[Column112]] -> 0 | AH36: F.1.7. ABE Community College Grants | AK36: 0
B37: F.1.9. College Readiness Grants | G37: =SUM(C37,E37) -> 0 | H37: =SUM(D37,F37) -> 0 | K37: ='A - Baseline Request'!N65 -> 1520353 | N37: =L37+M37 -> 0 | Q37: =SUM(O37:P37) -> 0 | T37: 0 | AA37: F.1.9. College Readiness Grants | AB37: =Table1[[#This Row],[Column112]] -> 1520353 | AC37: 0 | AD37: =Table2[[#This Row],[Column17]]/Table2[[#This Row],[Column112]] -> 0 | AK37: =SUM(AK7:AK34) -> #REF!
B38: TOTAL FY 14-15 Base | C38: =SUM(C19:C37,C8:C33) -> 1082726453 | D38: =SUM(D19:D37,D8:D33) -> 92841791 | E38: =SUM(E19:E37,E8:E33) -> 871979237 | F38: =SUM(F19:F37,F8:F33) -> 1114000 | G38: =SUM(G19:G37,G8:G33) -> 1953406690 | H38: =SUM(H19:H37,H8:H33) -> 93955791 | I38: =SUM(I19:I37,I8:I33,I7) -> 2078984391 | J38: =SUM(J19:J37,J8:J33,J7) -> 46398000 | K38: =SUM(Table1[Column112]) -> 1054563383 | AA38: TOTAL FY 14-15 Base | AB38: =SUM(Table2[Column112]) -> 1054563383 | AK38: =AK37=SUM(T7:T37,AD7:AD37) -> #REF!
B39: SUBTOTAL, First Proposed Reduction | N39: =SUM(Table1[Column14]) -> 52728278 | R39: =SUM(R8:R37) -> 1.9 | S39: =SUM(S8:S37) -> 1.9 | T39: =N39/K38 -> 0.050000103 | AA39: SUBTOTAL, Second Proposed Reduction | AC39: =SUM(AC7:AC37) -> 52728060 | AD39: =AC39/AB38 -> 0.049999896
B40: Target: | N40: 57038941
B41: Target: | Q41: 57038941
E42: =SUM(C38:F38) -> 2048661481 | F42: =SUM(G38:H38) -> 2047362481 | G42: =E42-F42 -> 1299000
A43: Total 10% Biennial Base Reduction | T43: =SUM(N39+AC39) -> 105456338 | AA43: =(N39+AC39)/K38 -> 0.1
L46: GR | M46: GR-Dedicated | O46: TOTAL | Q46: TARGETS
K47: Base | L47: =L39 -> 0 | M47: =M39 -> 0 | N47: =K38='[1]In and Out Base '!$S$66 -> TRUE | O47: =#REF!/(SUM(I38:J38)) -> #REF! | Q47: 57038941
K48: First 5% | L48: =#REF! -> #REF! | M48: =#REF! -> #REF! | N48: =N39='[1]First 5% Reduction'!$R$36 -> TRUE | O48: =#REF!/SUM(I38:J38) -> #REF! | Q48: 57038941 | Y48: =T39+AD39 -> 0.1 | AB48: =K38-AB38 -> 0
B49: AGENCY Biennial Total | L49: =SUM(L47:L48) -> #REF! | M49: =SUM(M47:M48) -> #REF! | N49: =SUM(N47:N48) -> 0 | O49: =(#REF!+#REF!)/(I38+J38) -> #REF! | P49: =SUM(Q47:Q48) -> 114077882 | T49: =N49-P49 -> -114077882
G50: Second 5% | N50: =AC39='[1]Second 5% Reduction'!$K$36 -> TRUE | O50: =N50-N49 -> 1 | AA50: =T43 -> 105456338
G51: Variance | L51: =L49-L50 -> #REF! | M51: =M49-M50 -> #REF! | R51: 0 | S51: 0 | U51: =T51=T49 -> FALSE
O53: 273669 | AA53: =T43=105456338 -> TRUE
O54: 0.09987 | AA54: =K38=1054563383 -> TRUE
H55: =SUM(G38:H38)-SUM(I38:J38) -> -78019910

Sheet C - EI Format
B1: Exceptional Items - Sorted by Agency Ranking
A2: Agency Rank | B2: Division Rank | C2: Name | D2: Strategy | E2: Description | F2: FY14 | G2: FY15 | H2: Total | I2: FTE | J2: PG #
A3: 1 | B3: 1 | C3: TEXAS Grants | D3: BSS/ B.1.1 | E3: This request will allow 158,719 students with an Expected family Contribution (EFC) up to $8,000 to receive a TEXAS Grant in the biennium. This will fund nearly 100% of all eligible new university students and an estimated 41,225 new transfer students that have not previously been eligible for the Program. | F3: 38537345 | G3: 67970755 | H3: =SUM(F3:G3) -> 106508100 | I3: 0 | J3: D4
A4: 2 | B4: 1 | C4: DCS | D4: ISS/ I.1.2 | E4: The agency is one of 27 state agencies mandated to use the Data Center Services contract for our computer center operations. This contract provides essential day-to-day services related to print services and server/network operations for the agency. Based on the FY13 baseline and projected FY14 and FY15 DCS costs provided by DIR, we are requesting the additional capital funding to offset the projected shortfall + 12% growth in storage needs which is needed to keep the growing amount of data that the agency is required to keep. | F4: 199146 | G4: 344776 | H4: =SUM(F4:G4) -> 543922 | I4: 0 | J4: D27
A5: 3 | B5: 2 | C5: Teach for Texas LRP | D5: BSS/ B.1.10 | E5: Current biennium funding at $1million represents a 91% reduction, compared with the 2010-2011 biennium. This required that we reduce annual loan repayment awards from $5,000 to $2,500 and that we accept applications only from prior year recipients. Awards for the current year will be disbursed for only 44% of those who were invited to apply. With an additional $9 million in funding, we will be able to contribute to the retention of 900 additional teachers per year, if the annual award amount is restored to $5,000, or 1,800 additional teachers, if the award amount remains at $2,500. | F5: 4500000 | G5: 4500000 | H5: =SUM(F5:G5) -> 9000000 | I5: 0 | J5: D9
A6: 4 | B6: 1 | C6: Graduate Medical Education Expansion Effort | D6: WAAR/ D.1.4 | E6: Texas must quickly increase the number of first year entering medical residents or Texas medical school graduates will no longer have enough available first year residency positions to retain its medical school graduates. The proposed Graduate Medical Education Expansion Effort would provide funding support to Texas residency programs offering first year residency positions. The goal of the program would be to achieve a 1.1 to 1 ratio of Texas first-year entering positions to medical school graduates. The new funding of $11.7 million ($15,000 per resident x 779 positions) would support 10 percent of the cost for new first-year entering residency training positions beginning in the 2014-2015 biennium. The program would support the addition of 220 first-year entering residency positions beginning in 2014, and allow the residents to continue training, and add 339 first-year entering residents in 2015. The administration and management of the new program would be absorbed by the agency with existing staff, with less than 2 percent of the proposed funding used to support salaries and wages. | F6: 5750000 | G6: 5750000 | H6: =SUM(F6:G6) -> 11500000 | I6: 0 | J6: D15
A7: 5 | B7: 2 | C7: Texas Science Technology Engineering and Math | D7: WAAR/ B.1.19 | E7: The Texas Science, Technology, Engineering, and Math (T-STEM) Challenge Scholarship Program was established by House Bill 2910, passed by the 82nd Legislature, Regular Session in 2011. The T-STEM program is funded through a grant provided to the Texas Higher Education Coordinating Board from the Texas Guaranteed Student Loan Corporation. The T-STEM program provides grant awards to qualified Texas public community and technical colleges. | F7: 1750000 | G7: 1750000 | H7: =SUM(F7:G7) -> 3500000 | I7: 0 | J7: D12
A8: 6 | B8: 3 | C8: Family Practice Residency Program | D8: WAAR/ D.1.1 | E8: The Family Practice Residency Program (FPRP) improves the distribution of family physicians throughout the state and provides increased medical care to patients in underserved areas. Funds are allocated based on the certified number of residents training in each approved family practice residency program, which must receive significant local support to qualify for state funds. This strategy also supports rural and public health rotations, which offer family practice residents the opportunity for supervised training in a rural community or public health facility. Since its inception in 1979, the program has provided funding support for more than 8,000 family practice residents. Family physicians who complete residency training have a 70 percent retention rate in Texas. The exceptional item request for an additional $10 million to the current level of funding of $5.6 million would allow the per resident funding level to increase from the current level of $3,985 to $10,764 to support approximately 706 family practice residents, and provide for an increase in the number of rural and public health rotations that could be completed from the current level of 25 funded at $2,000 to 80 funded at $2,500. | F8: 5000000 | G8: 5000000 | H8: =SUM(F8:G8) -> 10000000 | I8: 0 | J8: D13
A9: 7 | B9: 4 | C9: Norman Hackerman Advance Research Program | D9: WAAR/ C.1.1 | E9: The Norman Hackerman Advanced Research Program (NHARP) was established by the 70th Texas Legislature (1987, TEC Chapter 142) helps close the gap in research by providing competitive, peer-reviewed grants for basic research at Texas higher education institutions. The established peer-review process ensures that selected research projects are at the forefront of science: research that attracts and retains the best faculty and students and develops the knowledge base needed for continuing innovation. NHARP funds enable investigators to do initial studies necessary to secure additional funding from the federal government, private industry, not-for-profit organizations, and private donors. | F9: 8000000 | G9: 0 | H9: =SUM(F9:G9) -> 8000000 | I9: 0 | J9: D12
A10: 8 | B10: 5 | C10: Engineering Recruitment Program | D10: WAAR/ B.1.14 | E10: Texas is not meeting the Closing the Gaps target of graduates in science, technology, engineering, and math (STEM) fields. The Engineering Recruitment Program (ERP) helps close the gaps in participation and success, specific to engineering, through the Engineering Summer Program (ESP). The ESP supports one-week summer program experiences for middle and high school students at Texas public and private general academic institutions that offer engineering degree programs. ESP students participate in courses similar in content to engineering courses, with a focus on math and science preparation. The ESP is an early intervention initiative to engage and encourage middle and high school students to consider engineering as a profession. The program was not funded in FYs 2012 and 2013. In FY 2011, the ESP received an appropriation of $500,000 and supported 25 summer programs with 790 middle and high school students participating. Approximately half the number of programs and students would be supported, if funding were provided in FYs 2014 and 2015. | F10: 250000 | G10: 250000 | H10: =SUM(F10:G10) -> 500000 | I10: 0 | J10: D10
A11: 9 | B11: 6 | C11: Emergency and Trauma Care Education Partnership Program | D11: WAAR/ D.1.14 | E11: The Emergency and Trauma Care Education Partnership Program (ETEP), was established by passage of Senate Bill 7 during the First Called Session of the 82nd Legislature in 2011. Authority to administer the program was given to the Coordinating Board in Texas Education Code, Section 61.9802 and in Title 19, Texas Administrative Code, Chapter 6, Subchapter E. However, funding to administer the program was not appropriated to the Coordinating Board. Currently, funding is provided to the Department of State Health Services (DSHS) under General Appropriations Act, Senate Bill 1, 82nd Texas Legislature, B.3.1. Strategy: EMS AND TRAUMA CARE SYSTEMS (page II-49). In turn, DSHS provides the Coordinating Board with funding through a Memorandum of Understanding. To reduce unnecessary administrative effort between agencies, a request would be made that this appropriation go directly to the Coordinating Board. DSHS has indicated it will not request funding in the 2014-2015 LAR since it has no statutory authority for the program. | F11: 2250000 | G11: 2250000 | H11: =SUM(F11:G11) -> 4500000 | I11: 0 | J11: D19
A12: 10 | B12: 3 | C12: Physician Ed. LRP | D12: BSS/ D.1.6 | E12: The Physician Education Loan Repayment Program (PELRP) provides student loan repayment awards for physicians who have agreed to provide four years of service for underserved Texans in Health Professional Shortage Areas (HPSAs). The 81st Legislature authorized changes to the tax code relating to smokeless tobacco and directed specified percentages of the increased revenue to be used for loan repayments in the amount of up to $25,000, $35,000, $45,000, and $55,000 for 1st, 2nd, 3rd, and 4th years of service, for a maximum of $160,000. The State Comptroller's revenue projections for the PELRP fund far exceed the amount of this exceptional item, which is requested to fund loan repayments as follows: FY2014 - $1.5 million for 60 additional first-year participants (bringing the total of new participants to 100 for this year); FY2015 - $3.2 million for 60 second-year participants and 44 additional new participants. The recruitment of 60 new physicians practicing in HPSAs will provide access to primary care services for at least 210,000 underserved Texans in FY2014. The recruitment and retention of 144 physicians practicing in HPSAs will provide access to primary care services for at least 504,000 underserved Texans. | F12: 1500000 | G12: 3200000 | H12: =SUM(F12:G12) -> 4700000 | I12: 0 | J12: D16
A13: 11 | B13: 1 | C13: Compliance Monitoring to Address Sunset Issue 5 | D13: Internal Audit/ I.1.1 | E13: The Sunset Advisory Commission’s Staff Report on the Texas Higher Education Coordinating Board included Issue 5 – The Coordinating Board’s Limited Monitoring of Funding and Data Fails to Ensure Their Appropriate Use and Accuracy. This Special Item Request is needed to address Sunset Issue 5, through the creation of four FTEs dedicated to performing compliance monitoring of data and funds for which the THECB has oversight responsibility. | F13: 285368 | G13: 285368 | H13: =SUM(F13:G13) -> 570736 | I13: 4 | J13: D26
A14: 12 | B14: 2 | C14: Acquisition of Information Technology Resources | D14: ISS/ I.1.2 | E14: With no capital funding having been approved for technology acquisitions in FY12-13, funding of capital acquisitions in the FY 14-15 biennium is essential to the maintenance of agency operations and staff productivity. Replacement of obsolete technologies in place at the agency is required to enhance agency staff productivity and to improve service to the agency's stakeholders (institutions of higher education, students, legislature, Board and the public). | F14: 805000 | G14: 345000 | H14: =SUM(F14:G14) -> 1150000 | I14: 0 | J14: D27
C15: TOTAL | F15: =SUM(F3:F14) -> 68826859 | G15: =SUM(G3:G14) -> 91645899 | H15: =SUM(H3:H14) -> 160472758 | I15: =SUM(I3:I14) -> 4
B17: *

Sheet D - SUMMARY FOR BOARD
A1: Summary of 2014-15 Legislative Appropriations Request (LAR)
A2: Description of Strategies, Reduction Options, and Exceptional Item Requests | J2: =SUM(A20,C20,A48,C48,A68,C68,A106,C106,A140,C140,A183,C183,A203,C203,A279,C279,A301,C301,A425,C425,A494,C494,A555,C555,A574,C574,A628,C628,A648,C648,A693,C693,A859,C859,C883,A883,A907,C907,A163,C163) -> 105456338 | K2: =J2='B - Reductions '!AA50 -> TRUE | L2: =J2/J3 -> 0.1 | N2: =J2-105456338 -> 0
J3: =SUM(G9:H9,G37:H37,G57:H57,G95:H95,G116:H116,G128:H128,G152:H152,G172:H172,G192:H192,G212:H212,G221:H221,G240:H240,G249:H249,G258:H258,G267:H267,G290:H290,G309:H309,G320:H320,G330:H330,G344:H344,G354:H354,G364:H364,G373:H373,G383:H383,G399:H399,G414:H414,G436:H436,G450:H450,G460:H460,G469:H469,G483,G502:H502,G526:H526,G535:H535,G544:H544,G563,G582:H582,G592:H592,G601:H601,G617:H617,G637:H637,G673:H673,G682:H682,G701:H701,G720:H720,G729:H729,G739:H739,G749:H749,G767:H767,G777:H777,G847:H847,G870:H870,G896:H896) -> 1054563383 | K3: =J3='A - Baseline Request'!N81 -> TRUE
A4: This document describes each of the Texas Higher Education Coordinating Board’s (THECB) strategies included in the General Appropriations Act. These funding strategies represent all of the budget goals and strategies in the same order as they appear in the THECB’s appropriations bill pattern. Additionally, this document summarizes the contents of the THECB’s LAR for the 2014-15 biennium, and includes the baseline request for each strategy, proposed reductions to applicable strategies, and exceptional items associated with the applicable strategy. In developing the LAR, the THECB staff closely adhered to the following guiding principles as directed by the Commissioner of Higher Education: 1. no across-the board cuts; 2. preserve as much as possible the programs that contribute the most to achieving the goals of the state’s higher education plan, Closing the Gaps by 2015 (i.e., participation, success, excellence, and research); 3. preserve as much as possible the programs that contribute the most to achieving the goals of the Accelerated Plan for Closing the Gaps by 2015 (i.e., increasing the higher education participation of Hispanics and African American males, increasing higher education success of Hispanics and African Americans, increasing the number of STEM field graduates, and increasing the number of well-prepared certified teachers); and 4. preserve as much as possible student financial aid programs that serve the most needy students.
J5: EIs: | K5: =SUM(G130:H130,G332:H332,G385:H385,G401:H401,G438:H438,G471:H471,G504:H504,G603:H603,G849:H849,G872:H873,G269:H269) -> 160472758 | L5: =K5='C - EI Format'!H15 -> TRUE
A6: Budget Goal A: Coordinate Higher Education
A8: A.1.1. | B8: College Readiness and Success | G8: FY 2014 | H8: FY 2015
A9: FY 2014-15 GR-Related Baseline Request | G9: ='A - Baseline Request'!D5 -> 1863521 | H9: ='A - Baseline Request'!I5 -> 1863521
A10: FY 2014-15 Non-GR-Related Request | G10: ='A - Baseline Request'!E5 -> 0 | H10: ='A - Baseline Request'!J5 -> 0
A11: Total Request | G11: =SUM(G9:G10) -> 1863521 | H11: =SUM(H9:H10) -> 1863521
C12: Total Biennial Request (FY 2014 + FY 2015) | G12: =G11+H11 -> 3727042
A14: Strategy Description:
A15: This strategy includes funding for the administration of all college readiness and success programs and initiatives that support the goals of Closing the Gaps by 2015. Funding under this Strategy is designed (1) to support professional development activities for pre-service and in-service teachers who teach in public high schools with low college-going rates in Houston and Dallas, and (2) to increase college readiness and student success. The strategy includes staff resources to implement the professional development activities in Houston and Dallas and for college readiness and success activities funded at institutions of higher education and other entities across the state.
A17: PROPOSED Reduction:
A18: 1st Reduction | C18: 2nd Reduction
A19: Rank #2 | C19: Rank #2
A20: ='B - Reductions '!N8 -> 642178 | C20: ='B - Reductions '!AC8 -> 569695
A21: =A20/(G9+H9) -> 0.17230232 | C21: =C20/(G9+H9) -> 0.15285446
A22: =SUM(A20,C20) -> 1211873 | D22: =(A20+C20)/SUM(G9:H9) -> 0.32515679 | E22: Total Reduction
A23: =#REF! -> #REF!
A24: Impact Statement
A25: Reduction will have little impact on the Board staff's ability to promote access initiatives (i.e., Advise TX, Generation TX, and special activities that support underrepresented populations) and to oversee the remaining college readiness and student success projects and the ongoing collaborative work with Texas Education Agency to implement the Texas College and Career Readiness Standards, including the ongoing review and revision of the Texas College and Career Readiness Standards, and the three-year studies required for review of the performance measures for End of Course assessments. However, these reductions may impact the staff's ability to carry out the professional develoment activities for pre-service and in-service teachers as described in the strategy.
A27: A.1.2. | B27: State Loan Programs | G27: FY 2014 | H27: FY 2015
A28: FY 2014-15 GR-Related Baseline Request | G28: 0 | H28: 0
A29: FY 2014-15 Non-GR-Related Request | G29: ='A - Baseline Request'!E6 -> 5650000 | H29: ='A - Baseline Request'!J6 -> 5650000
A30: Total Request | G30: =G29 -> 5650000 | H30: =H29 -> 5650000
C31: Total Biennial Request (FY 2014 + FY 2015) | G31: =G30+H30 -> 11300000
A33: Strategy Description:
A34: This strategy includes funding for administration of the Hinson-Hazlewood Loan Program. No General Revenue is used to support the loan program. All funds for this program are generated by self-supporting bond proceeds and loan repayments. In FY11, 8,684 students received $101,547,713 in loans for an average loan amount of $9,613. It is estimated that 10,500 students will receive $110,000,000 in loans in FY12 for an average amount of $10,476.
A36: A.1.3. | B36: Student Grants and Special Programs | G36: FY 2014 | H36: FY 2015
A37: FY 2014-15 GR-Related Baseline Request | G37: ='A - Baseline Request'!D7 -> 925301 | H37: ='A - Baseline Request'!I7 -> 925301
A38: FY 2014-15 Non-GR-Related Request | G38: ='A - Baseline Request'!E7 -> 0 | H38: ='A - Baseline Request'!J7 -> 0
A39: Total Request (including exceptional items) | G39: =G37+G38 -> 925301 | H39: =H37+H38 -> 925301
C40: Total Biennial Request (FY 2014 + FY 2015) | G40: =G39+H39 -> 1850602
A42: Strategy Description:
A43: This strategy includes funding for the administration of all grant and success programs and initiatives that support the goals of Closing the Gaps by 2015. Funding under this Strategy is designed to increase student success and decrease the number of students enrolling in developmental education at institutions of higher education.
A45: PROPOSED Reduction:
A46: 1st Reduction | C46: 2nd Reduction
A47: Rank #10 | C47: Rank #7
A48: ='B - Reductions '!N16 -> 92530 | C48: ='B - Reductions '!AC13 -> 92530
A49: =A48/(G37+H37) -> 0.049999946 | C49: =C48/(G37+H37) -> 0.049999946
A50: =A48+C48 -> 185060 | D50: =A50/SUM(G37:H37) -> 0.099999892 | E50: Total Reduction
C51: =B49+D49 -> 0
A52: Impact Statement
A53: The first five percent reduction will result in reduced training and elimination of one FTE from the department. The second five percent reduction will cause a second FTE reduction.
A56: A.2.1. | B56: Workforce, Academic Affairs, and Research | G56: FY 2014 | H56: FY 2015
A57: FY 2014-15 GR-Related Baseline Request | G57: ='A - Baseline Request'!D8 -> 1692255 | H57: ='A - Baseline Request'!I8 -> 1692255
A58: FY 2014-15 Non-GR-Related Request | G58: ='A - Baseline Request'!E8 -> 3000 | H58: ='A - Baseline Request'!J8 -> 3000
A59: Total Request | G59: =G57+G58 -> 1695255 | H59: =H57+H58 -> 1695255
C60: Total Biennial Request (FY 2014 + FY 2015) | G60: =G59+H59 -> 3390510
A62: Strategy Description:
A63: This strategy includes funding for academic and research program responsibilities. The strategy includes funding for the personnel whose primary responsibility is institutional program review, administration of trusteed funds (including the residency programs and the grant programs supported by the tobacco settlement funding included in Goal H), Norman Hackerman Advanced Research Program (NHARP), Research Assessment Program, Research Development Fund (RDF), and the THECB efforts to close the gaps in excellence and research.
A65: PROPOSED Reduction:
A66: 1st Reduction | C66: 2nd Reduction
A67: Rank #3 | C67: Rank #3
A68: ='B - Reductions '!N9 -> 153915 | C68: ='B - Reductions '!AC9 -> 174442
B69: =A68/(G57+H57) -> 0.045476302 | D69: =C68/(G57+H57) -> 0.051541287
A70: =A68+C68 -> 328357 | D70: =A70/SUM(G57:H57) -> 0.097017589 | E70: Total Reduction
C71: =B69+D69 -> 0.097017589
A72: Impact Statement
A73: This amount comes from reductions in planned travel, professional expenses, and staff development and training.
A75: A.2.2. | B75: Close Gaps in Research | G75: FY 2014 | H75: FY 2015
A76: FY 2014-15 GR-Related Baseline Request | G76: ='A - Baseline Request'!D9 -> 0 | H76: ='A - Baseline Request'!I9 -> 0
A77: FY 2014-15 Non-GR-Related Request | G77: 0 | H77: 0
A78: Total Request | G78: =G76+G77 -> 0 | H78: =H76+H77 -> 0
C79: Total Biennial Request (FY 2014 + FY 2015) | G79: =G78+H78 -> 0
A81: Strategy Description:
A82: This strategy provides funding for the administration and staff supervision of the research programs by the Academic Affairs and Research Division. The strategy includes funding for personnel whose primary responsibility is administration of the Norman Hackerman Advanced Research Program, Summer Engineering Program, Engineering Recruitment Program, Research Assessment Program, Research Development Fund, and the agency’s related efforts to close the gaps in research.
A84: PROPOSED Reduction:
A85: 1st Reduction | C85: 2nd Reduction
A86: Rank # 15 | C86: Rank # 9
A87: 32628 | C87: 16314
B88: =A87/(G76+H76) -> #DIV/0! | D88: =C87/(G76+H76) -> #DIV/0!
A89: $ 48,942 7.50% | E89: Total Reduction
C90: =B88+D88 -> #DIV/0!
A91: Impact Statement
A92: The first proposed reduction will reduce travel and professional expenses associated with the Research Assessment Program and site reviews of existing research programs. The second proposed reduction will result in the elimination of staff site reviews of existing research programs.
A94: A.3.1. | B94: Planning, Information, & Evaluation | G94: FY 2014 | H94: FY 2015
A95: FY 2014-15 GR-Related Baseline Request | G95: ='A - Baseline Request'!D10 -> 1989978 | H95: ='A - Baseline Request'!I10 -> 1989978
A96: FY 2014-15 Non-GR-Related Request | G96: ='A - Baseline Request'!E10 -> 400000 | H96: ='A - Baseline Request'!J10 -> 0
A97: Total Request (including exceptional items) | G97: =G95+G96 -> 2389978 | H97: =H95+H96 -> 1989978
C98: Total Biennial Request (FY 2014 + FY 2015) | G98: =G97+H97 -> 4379956
A100: Strategy Description:
A101: This strategy provides funding for the Planning and Accountability Division, including the Education Data Center and Information Access Initiative, and funding for planning initiatives. The strategy includes funding for the personnel whose responsibilities include planning for higher education, collection of the state’s higher education data, analysis of higher education issues, maintaining the state’s higher education accountability system, planning for the state’s higher education facilities, including efficient use of higher education resources for construction, renovation and purchase of real estate, and higher education finance analysis, including recommendations for fair and equitable allocation of state formula funding among institutions.
A103: PROPOSED Reduction:
A104: 1st Reduction | C104: 2nd Reduction
A105: Rank #4 | C105: Rank #4
A106: ='B - Reductions '!N10 -> 186000 | C106: ='B - Reductions '!AC10 -> 149956
B107: =A106/(G95+H95) -> 0.046734185 | D107: =C106/(G95+H95) -> 0.037677803
A108: =A106+C106 -> 335956 | D108: =A108/SUM(G95:H95) -> 0.084411988 | E108: Total Reduction
C109: =B107+D107 -> 0.084411988
A110: Impact Statement
A111: The impact of the reduction will stop the progress planned for developing web pages for education data and accountability system presentations. The cut would reduce the amounts available for adjustments in staff compensation to reward and retain the high performers in the division. The cut would prohibit the division from addressing the monitoring function that was recommended by the Sunset Commission staff. The cut would eliminate the attendance of division staff at conferences held in state and out of state. Much of the coordination activities of the division involve presenting at statewide conferences (TACRO, TAIR, TASSCUBO, TACCBO, TAPPA, TCUF).
A115: A.3.2. | B115: Higher Education Policy Institute | G115: FY 2014 | H115: FY 2015
A116: FY 2014-15 GR-Related Baseline Request | G116: ='A - Baseline Request'!D11 -> 0 | H116: ='A - Baseline Request'!I11 -> 0
A117: FY 2014-15 Non-GR-Related Request | G117: ='A - Baseline Request'!E11 -> 423060 | H117: ='A - Baseline Request'!J11 -> 423060
A118: Total Request | G118: =SUM(G116:G117) -> 423060 | H118: =SUM(H116:H117) -> 423060
C119: Total Biennial Request (FY 2014 + FY 2015) | G119: =G118+H118 -> 846120
A121: Strategy Description:
A122: The Board received a grant from the Houston Endowment, Inc., to conduct research and analysis of the critical higher education issues that challenge Texas.
...

Sheet Goal Names
A1: Budget Goal A: Close the Gaps in Higher Education
A2: Budget Goal F: Close the Gaps by Providing Federal Funding to Institutions and Students (Administration of Federal Funding)
A3: Budget Goal H: Indirect Administration
A5: Budget Goal B: Close the Gaps – Affordability
A6: Budget Goal C: Close the Gaps – Research
A7: Budget Goal D: Close the Gaps – Health Programs
A8: Budget Goal E: Close the Gaps in Quality and Participation
A9: Budget Goal F: Federal Grant Programs
A10: Budget Goal G: Tobacco Settlement Endowment Funds

Sheet TOC
A3: Reduction Options
A4: 10 Percent Biennial Reduction Option Schedule | B4: A1
A5: Exceptional Items
A6: Exceptional Items | B6: B1
A7: FY12-FY13 Legislative Appropriations Request (LAR)
A8: Description of Strategies, Exceptional Item Requests and Reduction Options
A9: A.1.1. Close Gaps in Participation and Success | B9: C1
A10: A.1.2. Close Gaps by Administering Loan Programs
A11: A.1.3. Close Gaps by Administering College Readiness Initiatives
A12: A.2.1. Close Gaps in Excellence
A13: A.2.2. Close Gaps in Research
A14: A.3.1. Close Gaps by Providing Planning and Information
A15: B.1.1. License Plate Scholarships Program
A16: B.1.2. Fifth-Year Accounting Students Program
A17: B.1.3. Early High School Graduation Scholarship Program
A18: B.1.4. TANF Scholarship Program
A19: B.1.5. Educational Aide Program
A20: B.1.6. Teach for Texas Loan Repayment Assistance Program
A21: B.1.7. Border Faculty Loan Repayment Program
... A73: H.1.3. Other Support Services

Sheet EI Format (2)
A1: Exceptional Items - Sorted by Agency Ranking
A2: RANKING | B2: NAME | C2: Strategy | D2: Description | E2: FY12 | F2: FY13 | G2: FTE | H2: Total | I2: * PG #
A3: =EI!A6 -> 1 | B3: =EI!D6 -> TEXAS Grants | C3: =EI!F6 -> B.1.9. | D3: =EI!H6 -> CB staff recommends increased funding for this program by $148.33 million. This will enable us to keep the number of new students added to the program level with the numbers added for the 2010/2011 biennium and increase the overall number of students by over 17,000 students for the biennium. | E3: =EI!J6 -> 53365819 | F3: =EI!K6 -> 94963455 | G3: 0 | H3: =E3+F3 -> 148329274 | I3: A11
A4: =EI!A7 -> 2 | B4: =EI!D7 -> Texas Education Opportunity Grants (TEOG) | C4: =EI!F7 -> B.1.9. | D4: =EI!H7 -> CB staff recommends that the Legislature substantially increase funding for the TEOG by $10 million. This will enable an additional 2,630 new students to enter the program during the 2012/2013 biennium and overall fund an additional 4,090 students for the biennium. | E4: =EI!J7 -> 4706947 | F4: =EI!K7 -> 5293053 | G4: 0 | H4: =E4+F4 -> 10000000 | I4: A11
A5: =EI!A8 -> 3 | B5: =EI!D8 -> Texas College Work Study | C5: =EI!F8 -> B.1.9. | D5: =EI!H8 -> CB staff recommends doubling the funding over the 2010-2011 biennium, which was $15 million. This increase will enable an additional 6,024 students to participate in the program each year of the biennium. | E5: =EI!J8 -> 7500000 | F5: =EI!K8 -> 7500000 | G5: 0 | H5: =E5+F5 -> 15000000 | I5: A11
A6: 4 | B6: =EI!D9 -> Tuition Equalization Grants (TEG) | C6: =EI!F9 -> B.1.9. | D6: =EI!H9 -> CB staff recommends that the Legislature increase funding for the TEG by $10,587,465. This will enable the number of students served by the program to remain relatively steady for the 2012/2013 biennium. | E6: =EI!J9 -> 5293732 | F6: =EI!K9 -> 5293733 | G6: 0 | H6: =E6+F6 -> 10587465 | I6: A11
A7: 5 | B7: =EI!D10 -> Higher Education Performance Incentive Initiative | C7: =EI!F10 -> B.1.12. | D7: =EI!H10 -> The incentive funding was originally appropriated by rider in FY 2009 as General Revenue funds and then funded during the FY 2010-11 biennium through federal American Recovery and Reinvestment (ARRA) funds, which will not be available for FY 2012-13. This request would restore the General Revenue funding for this program. | E7: =EI!J10 -> 40000000 | F7: =EI!K10 -> 40000000 | G7: 0 | H7: =E7+F7 -> 80000000 | I7: A14
A8: 6 | B8: =EI!D5 -> Teach for Texas Loan Repayment Program | C8: =EI!F5 -> B.1.6. | D8: =EI!H5 -> The number of applications for participation in this program has increased by 76% during the past four years, and yet the funding has increased by 16% during that period. Funding for the FY2010-2011 biennium ($11.2 million) was sufficient for only 1,124 of approximately 5,000 applicant teachers in FY2010 (22%). Staff recommends raising the funding level by $19,378,557 per year over the base funding, to provide loan repayment for 5,000 teachers. (Note: For FY10 receipts from borrower payments applied to TFT conditional grants will provide loan repayment funds for approximately 200 additional teachers. This source of funds will diminish over the next few years as the loans in these portfolios are paid-in-full or go into default.) | E8: =EI!J5 -> 19378557 | F8: =EI!K5 -> 19378557 | G8: 0 | H8: =E8+F8 -> 38757114 | I8: A8
A9: 7 | B9: =EI!D12 -> Physician Education Loan Repayment Program | C9: =EI!F12 -> D.1.8. | D9: =EI!H12 -> The 81st Legislature authorized changes to the tax code relating to smokeless tobacco and directed specified percentages of the increased revenue to a new account for the PELRP. The increased funding allows for loan repayments in the amount of $25,000, $35,000, $45,000, and $55,000 for 1st, 2nd, 3rd, and 4th- year participants, for a maximum aggregate of $160,000. The State Comptroller's revenue projections for this fund exceed the amount of this exceptional item, which is requested to fund administrative costs and loan repayments totaling $13,500,000 to 450 physicians in FY2012 and $23,625,000 to 675 physicians in FY2013. The administrative costs of $346,711 in FY12 and $348,711 in FY13 include personnel costs for the 4 FTEs authorized in Contingency Rider 17.49 for the FY2010-2011 biennium. | E9: =EI!J12 -> 6846711 | F9: =EI!K12 -> 8973711 | G9: 0 | H9: =E9+F9 -> 15820422 | I9: A23
A10: 8 | B10: =EI!D13 -> Restoration of Reduction to College Readiness Grants Strategy | C10: =EI!F13 -> E.1.10. | D10: =EI!H13 -> This exceptional item would restore funding to the original 2010-2011 level to address the goal of the P-16 College Readiness and Success Strategic Action Plan to "reduce the need for developmental education and to increase student success." Restoring these funds would ensure the Coordinating Board has resources necessary to support vertical alignment statewide through higher education engagement activities and vertical alignment initiatives that involve both higher education and K-12 faculty. | E10: =EI!J13 -> 1351445.4 | F10: =EI!K13 -> 900963.6 | G10: 0 | H10: =E10+F10 -> 2252409 | I10: A32
A11: 9 | B11: Texas High School Completion and Success Initiatives (HB2237) | C11: - | D11: =EI!H2 -> BOARD Description | E11: =E12+E13 -> 4704500 | F11: =F12+F13 -> 4704500 | G11: 0 | H11: =E11+F11 -> 9409000
B12: - Admin | C12: =EI!F3 -> A1.3. | D12: =EI!H3 -> The 81st Texas Legislature moved the statutory responsibility for Mathematics, Science, Technology Teacher Preparatory Academies and the Intensive Programs from the public education section to the higher education section of the Texas Education Code but did not appropriate funding to the Coordinating Board. Currently, funding is provided to TEA under General Appropriations Act, Senate Bill 1, 81st Texas Legislature, Section 51 (pages III-19 and 20), Texas High School Completion and Success Initiative. In turn, TEA provides the Coordinating Board with funding through a Memorandum of Understanding. TEA has indicated they will not request funding in the 2012-2013 LAR since they have no statutory authority for these two programs. Therefore, the Coordinating Board would need to seek this appropriation in order to fund these programs for the 2012-2013. The amounts indicated above represent administrative funds. The requested grant funds are shown in Strategy E.1.10. | E12: =EI!J3 -> 300000 | F12: =EI!K3 -> 300000 | G12: 0 | H12: =E12+F12 -> 600000 | I12: A2
B13: - Grants | C13: =EI!F14 -> E.1.10. | D13: =EI!H14 -> The 81st Texas Legislature moved the statutory responsibility for Mathematics, Science, Technology Teacher Preparatory Academies and the Intensive Programs from the public education section to the higher education section of the Texas Education Code but did not appropriate funding to the Coordinating Board. Currently, funding is provided to TEA under General Appropriations Act, Senate Bill 1, 81st Texas Legislature, Section 51 (pages III-19 and 20), Texas High School Completion and Success Initiative. In turn, TEA provides the Coordinating Board with funding through a Memorandum of Understanding. TEA has indicated they will not request funding in the 2012-2013 LAR since they have no statutory authority for these two programs. Therefore, the Coordinating Board would need to seek this appropriation in order to fund these programs for the 2012-2013. The amounts indicated above represent grants funds. The requested administrative funds are shown in Strategy A.1.3. | E13: =EI!J14 -> 4404500 | F13: =EI!K14 -> 4404500 | G13: 0 | H13: =E13+F13 -> 8809000 | I13: A32
A14: 10 | B14: =EI!D4 -> National Student Clearing House Data | C14: =EI!F4 -> A.3.1. | D14: =EI!H4 -> To enhance the capability of research in the area of college access and success, this purchase of matching records from the National Student Clearing house would provide increased coverage of student higher education attendance patterns. Currently the longitudinal tracking is limited to only students attending higher education institutions in the state. | E14: =EI!J4 -> 250000 | F14: =EI!K4 -> 250000 | G14: 0 | H14: =E14+F14 -> 500000 | I14: A5
A15: =EI!A11 -> 11 | B15: =EI!D11 -> Baylor College of Medicine Undergraduate Education | C15: =EI!F11 -> D.1.1. | D15: =EI!H11 -> This Exceptional Item funding of $6,868,594 would provide to Baylor College of Medicine (BCM) the amount it is authorized by statute to receive for each Texas medical student enrolled at the College. This per-student amount is based on the average General Revenue (GR) expended in the previous fiscal year for each medical student at The University of Texas Medical Branch at Galveston and The University of Texas Southwestern Medical Center in Dallas. The per-student amount includes GR expended by the two UT institutions for instruction and operations, infrastructure and benefits, but does not include formula funding appropriated to the UT institutions for research. This funding is the equivalent formula funding that is provided to all public Health-Related Institutions for medical education. | E15: =EI!J11 -> 4637202.1 | F15: =EI!K11 -> 2231392.1 | G15: 0 | H15: =E15+F15 -> 6868594.2 | I15: A18
B16: TOTAL . | D16: TOTAL | E16: =SUM(E3:E15) -> 1.5273941e+08 | F16: =SUM(F3:F15) -> 1.9419386e+08 | G16: =SUM(G3:G15) -> 0 | H16: =E16+F16 -> 3.4693328e+08
A19: * | B19: Page number refers to the document titled FY12-FY13 Legislative Appropriation Request (LAR) Description of Strategies, Exeptional Item Requests and Reduction Options.
