Workbook

Sheet Conto Economico
C1: 2009 | D1: 2010
C3: (mln €) | D3: (mln €)
B4: Ricavo dei Prodotti Venduti | C4: 67 | D4: 115
B6: Costo del venduto | C6: -38 | D6: -65
B8: Risultato lordo della gestione industriale | C8: =+C4+C6 -> 29 | D8: =+D4+D6 -> 50
B10: Costi della funzione commerciale | C10: -10 | D10: -11
B12: Costi della funzione amministrativa | C12: -6 | D12: -9
B14: Risultato operativo lordo della gestione caratteristica | C14: =+C8+C10+C12 -> 13 | D14: =+D8+D10+D12 -> 30
B16: Risultato della gestione finanziaria | C16: 6 | D16: 14
B18: Risultato della gestione atipica | C18: -8 | D18: -4
B20: Risultato della gestione straordinaria | C20: 4 | D20: -3
B22: Risultato economico lordo prima delle Imposte | C22: =+C14+C16+C18+C20 -> 15 | D22: =+D14+D16+D18+D20 -> 37
B24: Imposte sul reddito | C24: -9 | D24: -18
B26: Risultato economico dell'esercizio | C26: =+C22+C24 -> 6 | D26: =+D22+D24 -> 19

Sheet Grafico a ponte
D1: Conto Economico esercizio 2009 | E1: Conto Economico esercizio 2010 | F1: (Lato inferiore) | G1: Risultato Economico 2010 | H1: Minus | I1: Plus | J1: Risultato Economico 2009
B2: Risultato 2009 | C2: =B2 -> Risultato 2009 | J2: =SUM(D3:D10) -> 6
A3: =IF(H3=0,"+","-") -> + | B3: Ricavi | C3: =CONCATENATE("(",A3,")"," ",B3) -> (+) Ricavi | D3: =+'Conto Economico'!C4 -> 67 | E3: =+'Conto Economico'!D4 -> 115 | F3: =+F2+I2+J2-H3 -> 6 | H3: =IF(D3>E3,D3-E3,0) -> 0 | I3: =IF(D3<=E3,E3-D3,0) -> 48
A4: =IF(H4=0,"+","-") -> - | B4: Costo del venduto | C4: =CONCATENATE("(",A4,")"," ",B4) -> (-) Costo del venduto | D4: =+'Conto Economico'!C6 -> -38 | E4: =+'Conto Economico'!D6 -> -65 | F4: =+F3+I3+J3-H4 -> 27 | H4: =IF(D4>E4,D4-E4,0) -> 27 | I4: =IF(D4<=E4,E4-D4,0) -> 0
A5: =IF(H5=0,"+","-") -> - | B5: Costi commerciali | C5: =CONCATENATE("(",A5,")"," ",B5) -> (-) Costi commerciali | D5: =+'Conto Economico'!C10 -> -10 | E5: =+'Conto Economico'!D10 -> -11 | F5: =+F4+I4+J4-H5 -> 26 | H5: =IF(D5>E5,D5-E5,0) -> 1 | I5: =IF(D5<=E5,E5-D5,0) -> 0
A6: =IF(H6=0,"+","-") -> - | B6: Costi amministrativi | C6: =CONCATENATE("(",A6,")"," ",B6) -> (-) Costi amministrativi | D6: =+'Conto Economico'!C12 -> -6 | E6: =+'Conto Economico'!D12 -> -9 | F6: =+F5+I5+J5-H6 -> 23 | H6: =IF(D6>E6,D6-E6,0) -> 3 | I6: =IF(D6<=E6,E6-D6,0) -> 0
A7: =IF(H7=0,"+","-") -> + | B7: Gestione finanziaria | C7: =CONCATENATE("(",A7,")"," ",B7) -> (+) Gestione finanziaria | D7: =+'Conto Economico'!C16 -> 6 | E7: =+'Conto Economico'!D16 -> 14 | F7: =+F6+I6+J6-H7 -> 23 | H7: =IF(D7>E7,D7-E7,0) -> 0 | I7: =IF(D7<=E7,E7-D7,0) -> 8
A8: =IF(H8=0,"+","-") -> + | B8: Gestione atipica | C8: =CONCATENATE("(",A8,")"," ",B8) -> (+) Gestione atipica | D8: =+'Conto Economico'!C18 -> -8 | E8: =+'Conto Economico'!D18 -> -4 | F8: =+F7+I7+J7-H8 -> 31 | H8: =IF(D8>E8,D8-E8,0) -> 0 | I8: =IF(D8<=E8,E8-D8,0) -> 4
A9: =IF(H9=0,"+","-") -> - | B9: Gestione straordinaria | C9: =CONCATENATE("(",A9,")"," ",B9) -> (-) Gestione straordinaria | D9: =+'Conto Economico'!C20 -> 4 | E9: =+'Conto Economico'!D20 -> -3 | F9: =+F8+I8+J8-H9 -> 28 | H9: =IF(D9>E9,D9-E9,0) -> 7 | I9: =IF(D9<=E9,E9-D9,0) -> 0
A10: =IF(H10=0,"+","-") -> - | B10: Imposte sul reddito | C10: =CONCATENATE("(",A10,")"," ",B10) -> (-) Imposte sul reddito | D10: =+'Conto Economico'!C24 -> -9 | E10: =+'Conto Economico'!D24 -> -18 | F10: =+F9+I9+J9-H10 -> 19 | H10: =IF(D10>E10,D10-E10,0) -> 9 | I10: =IF(D10<=E10,E10-D10,0) -> 0
B11: Risultato 2010 | C11: =+B11 -> Risultato 2010 | G11: =SUM(E3:E10) -> 19
