Workbook

Sheet Worksheet Instructions
B2: Charter School Funding -- Inequity Persists
B3: May 2010
B5: Supporting Excel Spreadsheet
B6: Worksheet Legend and Instructions
B7: Arizona
B9: Data Source:
B10: The source for revenue and enrollment data was the Arizona Department of Education’s (ADE) web site. District and charter data were obtained from the FY 2006-07 Annual Report of the Arizona Superintendent of Public Instruction, Volume I and Volume II. At web site:
B11: http://www/ade.state.az.us/schoolfinance/Reports/Default.asp
B13: Disclaimer:
B14: This is a "read only" file containing data collections from the Arizona Department of Education. The conclusions reached in this document are those of the author(s) and do not necessarily represent those of Ball State University.
B16: File Management:
B17: This is a "Final (Read-Only)" Excel file. This means you will not be able to edit this file, but you can copy whole worksheets, paste them into a new file (workbook), and then save that file under a different name. No "Protection" has been set for this file.
... B20: This spreadsheet was designed for use by the author/researcher, not for third-party use. Some of the data in this spreadsheet may be useful to third-parties, but any interpretations or additional analysis by third-parties is done so at their own risk.

Sheet TEMPLATE-Figure 1 Amounts
A1: Figure 1 | G1: Figure 2
A2: Arizona 2006-07 | B2: Statewide | D2: Maricopa County
A3: Per-Pupil Revenue
A4: District | B4: ='#s for Report-State'!I32 -> 9576.9467 | D4: ='#s for Report-Maricopa County'!I12 -> 9559.6363
A5: Charter | B5: ='#s for Report-State'!I39 -> 7596.7418 | D5: ='#s for Report-Maricopa County'!I18 -> 7376.2156
A6: Difference | B6: =B4-B5 -> 1980.2049 | D6: =D4-D5 -> 2183.4207
B7: =B6/B4 -> 0.20676787 | D7: =D6/D4 -> 0.22839998
A8: Per-Pupil Revenue by Source | B8: District | C8: Charter | D8: District | E8: Charter
A9: Federal | B9: ='#s for Report-State'!M32 -> 1022.1014 | C9: ='#s for Report-State'!M39 -> 657.67405 | D9: ='#s for Report-Maricopa County'!M12 -> 770.7282 | E9: ='#s for Report-Maricopa County'!M18 -> 393.02965
A10: State | B10: ='#s for Report-State'!L32 -> 4668.6343 | C10: ='#s for Report-State'!L39 -> 6402.4844 | D10: ='#s for Report-Maricopa County'!L12 -> 4452.2663 | E10: ='#s for Report-Maricopa County'!L18 -> 6409.1268
A11: Local | B11: ='#s for Report-State'!J32 -> 3881.851 | C11: ='#s for Report-State'!J39 -> 522.96061 | D11: ='#s for Report-Maricopa County'!J12 -> 4334.1476 | E11: ='#s for Report-Maricopa County'!J18 -> 565.41195
A12: Other | B12: ='#s for Report-State'!K32 -> 4.3600155 | C12: ='#s for Report-State'!K39 -> 13.622706 | D12: ='#s for Report-Maricopa County'!K12 -> 2.4942239 | E12: ='#s for Report-Maricopa County'!K18 -> 8.6472116
A13: Indeterminate | B13: 0 | C13: 0 | D13: 0 | E13: 0
A14: Total | B14: =SUM(B9:B13) -> 9576.9467 | C14: =SUM(C9:C13) -> 7596.7418 | D14: =SUM(D9:D13) -> 9559.6363 | E14: =SUM(E9:E13) -> 7376.2156
A15: Enrollment
A16: District | B16: ='#s for Report-State'!H31 -> 934595.52 | D16: ='#s for Report-Maricopa County'!H11 -> 587562.72
B17: =B16/(B16+B18) -> 0.91285604 | D17: =D16/(D16+D18) -> 0.90934342 | H17: District | I17: Charter | J17: Difference
A18: Charter | B18: ='#s for Report-State'!H38 -> 89219.276 | D18: ='#s for Report-Maricopa County'!H17 -> 58576.802 | G18: Arizona | H18: =B4 -> 9576.9467 | I18: =B5 -> 7596.7418 | J18: =B6 -> 1980.2049
B19: =B18/(B16+B18) -> 0.08714396 | D19: =D18/(D16+D18) -> 0.090656584 | G19: Maricopa County | H19: =D4 -> 9559.6363 | I19: =D5 -> 7376.2156 | J19: =D6 -> 2183.4207
A20: Number of Charters | B20: ='#s for Report-State'!G38 -> 448 | D20: ='#s for Report-Maricopa County'!G17 -> 194 | G20: City B Name Here | H20: 0 | I20: 0 | J20: 0
A21: Total Revenue | G21: City C Name Here | H21: 0 | I21: 0 | J21: 0
A22: District | B22: ='#s for Report-State'!I31 -> 8.9505715e+09 | D22: ='#s for Report-Maricopa County'!I11 -> 5616885964
B23: =B22/B26 -> 0.92960622 | D23: =D22/D26 -> 0.92857036
A24: Charter | B24: ='#s for Report-State'!I38 -> 6.777758e+08 | D24: ='#s for Report-Maricopa County'!I17 -> 432075120
B25: =B24/B26 -> 0.070393784 | D25: =D24/D26 -> 0.071429641
A26: Total | B26: =B24+B22 -> 9628347269 | D26: =D24+D22 -> 6048961084
A27: Percentage of Revenue by Source | B27: District | C27: Charter | D27: District | E27: Charter | G27: Figure 4
A28: Federal | B28: ='#s for Report-State'!M33 -> 0.10672518 | C28: ='#s for Report-State'!M40 -> 0.086573175 | D28: ='#s for Report-Maricopa County'!M13 -> 0.080623171 | E28: ='#s for Report-Maricopa County'!M19 -> 0.053283374
A29: State | B29: ='#s for Report-State'!L33 -> 0.48748671 | C29: ='#s for Report-State'!L40 -> 0.84279348 | D29: ='#s for Report-Maricopa County'!L13 -> 0.46573595 | E29: ='#s for Report-Maricopa County'!L19 -> 0.86889092
A30: Local | B30: ='#s for Report-State'!J33 -> 0.40533284 | C30: ='#s for Report-State'!J40 -> 0.068840119 | D30: ='#s for Report-Maricopa County'!J13 -> 0.45337996 | E30: ='#s for Report-Maricopa County'!J19 -> 0.076653393
A31: Other | B31: ='#s for Report-State'!K33 -> 0.00045526155 | C31: ='#s for Report-State'!K40 -> 0.0017932301 | D31: ='#s for Report-Maricopa County'!K13 -> 0.00026091201 | E31: ='#s for Report-Maricopa County'!K19 -> 0.00117231
A32: Change in district school funding if subjected to charter funding structure
B33: ='#s for Report-State'!I52 -> -1.8506906e+09 | D33: ='#s for Report-Maricopa County'!I31 -> -1.2828966e+09
B35: =SUM(B28:B31) -> 1 | C35: =SUM(C28:C31) -> 1 | D35: =SUM(D28:D31) -> 1 | E35: =SUM(E28:E31) -> 1
H48: Federal | I48: State | J48: Local | K48: Other | L48: Indeterminate
G49: Statewide District | H49: =B9 -> 1022.1014 | I49: =B10 -> 4668.6343 | J49: =B11 -> 3881.851 | K49: =B12 -> 4.3600155 | L49: 0
G50: Statewide Charter | H50: =C9 -> 657.67405 | I50: =C10 -> 6402.4844 | J50: =C11 -> 522.96061 | K50: =C12 -> 13.622706 | L50: 0
G51: Maricopa-District | H51: =D9 -> 770.7282 | I51: =D10 -> 4452.2663 | J51: =D11 -> 4334.1476 | K51: =D12 -> 2.4942239 | L51: 0
G52: Maricopa-Charter | H52: =E9 -> 393.02965 | I52: =E10 -> 6409.1268 | J52: =E11 -> 565.41195 | K52: =E12 -> 8.6472116 | L52: 0
G53: City B District | H53: 0 | I53: 0 | J53: 0 | K53: 0 | L53: 0
G54: City B Charter | H54: 0 | I54: 0 | J54: 0 | K54: 0 | L54: 0
G55: City C District | H55: 0 | I55: 0 | J55: 0 | K55: 0 | L55: 0
G56: City C Charter | H56: 0 | I56: 0 | J56: 0 | K56: 0 | L56: 0

Sheet Figures 1,2,4-Weighted
A1: Figure 1 | I1: Figure 2
A2: Arizona 2006-07 | B2: Statewide | D2: Statewide Weighted for Charter Enrollment | F2: Maricopa County
A3: Per-Pupil Revenue
A4: District | B4: ='[1]#s for Report-State'!I32 -> 9576.9467 | D4: 9576 | F4: ='[1]#s for Report-Maricopa County'!I12 -> 9559.6363
A5: Charter | B5: ='[1]#s for Report-State'!I39 -> 7596.7418 | D5: 7597 | F5: ='[1]#s for Report-Maricopa County'!I18 -> 7376.2156
A6: Difference | B6: =B4-B5 -> 1980.2049 | D6: 1979 | F6: =F4-F5 -> 2183.4207
B7: =B6/B4 -> 0.20676787 | D7: 0.207 | F7: =F6/F4 -> 0.22839998
A8: Per-Pupil Revenue by Source | B8: District | C8: Charter | D8: District | E8: Charter | F8: District | G8: Charter
A9: Federal | B9: ='[1]#s for Report-State'!M32 -> 1022.1014 | C9: ='[1]#s for Report-State'!M39 -> 657.67405 | D9: =1003 -> 1003 | E9: =C9 -> 657.67405 | F9: ='[1]#s for Report-Maricopa County'!M12 -> 770.7282 | G9: ='[1]#s for Report-Maricopa County'!M18 -> 393.02965
A10: State | B10: ='[1]#s for Report-State'!L32 -> 4668.6343 | C10: ='[1]#s for Report-State'!L39 -> 6402.4844 | D10: 4653 | E10: =C10 -> 6402.4844 | F10: ='[1]#s for Report-Maricopa County'!L12 -> 4452.2663 | G10: ='[1]#s for Report-Maricopa County'!L18 -> 6409.1268
A11: Local | B11: ='[1]#s for Report-State'!J32 -> 3881.851 | C11: ='[1]#s for Report-State'!J39 -> 522.96061 | D11: 3916 | E11: =C11 -> 522.96061 | F11: ='[1]#s for Report-Maricopa County'!J12 -> 4334.1476 | G11: ='[1]#s for Report-Maricopa County'!J18 -> 565.41195
A12: Other | B12: ='[1]#s for Report-State'!K32 -> 4.3600155 | C12: ='[1]#s for Report-State'!K39 -> 13.622706 | D12: 4 | E12: =C12 -> 13.622706 | F12: ='[1]#s for Report-Maricopa County'!K12 -> 2.4942239 | G12: ='[1]#s for Report-Maricopa County'!K18 -> 8.6472116
A13: Indeterminate | B13: 0 | C13: 0 | D13: 0 | E13: =C13 -> 0 | F13: 0 | G13: 0
A14: Total | B14: =SUM(B9:B13) -> 9576.9467 | C14: =SUM(C9:C13) -> 7596.7418 | D14: =D4 -> 9576 | E14: =C14 -> 7596.7418 | F14: =SUM(F9:F13) -> 9559.6363 | G14: =SUM(G9:G13) -> 7376.2156
A15: Enrollment
A16: District | B16: ='[1]#s for Report-State'!H31 -> 934595.52 | D16: n/a | F16: ='[1]#s for Report-Maricopa County'!H11 -> 587562.72
B17: =B16/(B16+B18) -> 0.91285604 | D17: n/a | F17: =F16/(F16+F18) -> 0.90934342 | J17: District | K17: Charter | L17: Difference
A18: Charter | B18: ='[1]#s for Report-State'!H38 -> 89219.276 | D18: n/a | F18: ='[1]#s for Report-Maricopa County'!H17 -> 58576.802 | I18: Arizona | J18: =B4 -> 9576.9467 | K18: =B5 -> 7596.7418 | L18: =B6 -> 1980.2049
B19: =B18/(B16+B18) -> 0.08714396 | D19: n/a | F19: =F18/(F16+F18) -> 0.090656584 | I19: Arizona Weighted | J19: =D4 -> 9576 | K19: =D5 -> 7597 | L19: =D6 -> 1979
A20: Number of Charters | B20: ='[1]#s for Report-State'!G38 -> 448 | D20: n/a | F20: ='[1]#s for Report-Maricopa County'!G17 -> 194 | I20: Maricopa County | J20: =F4 -> 9559.6363 | K20: =F5 -> 7376.2156 | L20: =F6 -> 2183.4207
A21: Total Revenue | I21: City C Name Here | J21: 0 | K21: 0 | L21: 0
A22: District | B22: ='[1]#s for Report-State'!I31 -> 8.9505715e+09 | D22: n/a | F22: ='[1]#s for Report-Maricopa County'!I11 -> 5616885964
B23: =B22/B26 -> 0.92960622 | D23: n/a | F23: =F22/F26 -> 0.92857036
A24: Charter | B24: ='[1]#s for Report-State'!I38 -> 6.777758e+08 | D24: n/a | F24: ='[1]#s for Report-Maricopa County'!I17 -> 432075120
B25: =B24/B26 -> 0.070393784 | D25: n/a | F25: =F24/F26 -> 0.071429641
A26: Total | B26: =B24+B22 -> 9628347269 | D26: n/a | F26: =F24+F22 -> 6048961084
A27: Percentage of Revenue by Source | B27: District | C27: Charter | D27: District | E27: Charter | F27: District | G27: Charter | I27: Figure 4
A28: Federal | B28: ='[1]#s for Report-State'!M33 -> 0.10672518 | C28: ='[1]#s for Report-State'!M40 -> 0.086573175 | D28: =D9/$D$14 -> 0.10474102 | E28: =C28 -> 0.086573175 | F28: ='[1]#s for Report-Maricopa County'!M13 -> 0.080623171 | G28: ='[1]#s for Report-Maricopa County'!M19 -> 0.053283374
A29: State | B29: ='[1]#s for Report-State'!L33 -> 0.48748671 | C29: ='[1]#s for Report-State'!L40 -> 0.84279348 | D29: =D10/$D$14 -> 0.48590226 | E29: =C29 -> 0.84279348 | F29: ='[1]#s for Report-Maricopa County'!L13 -> 0.46573595 | G29: ='[1]#s for Report-Maricopa County'!L19 -> 0.86889092
A30: Local | B30: ='[1]#s for Report-State'!J33 -> 0.40533284 | C30: ='[1]#s for Report-State'!J40 -> 0.068840119 | D30: =D11/$D$14 -> 0.40893901 | E30: =C30 -> 0.068840119 | F30: ='[1]#s for Report-Maricopa County'!J13 -> 0.45337996 | G30: ='[1]#s for Report-Maricopa County'!J19 -> 0.076653393
A31: Other | B31: ='[1]#s for Report-State'!K33 -> 0.00045526155 | C31: ='[1]#s for Report-State'!K40 -> 0.0017932301 | D31: =D12/$D$14 -> 0.00041771094 | E31: =C31 -> 0.0017932301 | F31: ='[1]#s for Report-Maricopa County'!K13 -> 0.00026091201 | G31: ='[1]#s for Report-Maricopa County'!K19 -> 0.00117231
A32: Change in district school funding if subjected to charter funding structure
B33: ($1.9 billion) | F33: ($1.3 billion)
B35: =(B$16*B$5)-B$22 -> -1.8506906e+09 | F35: =(F$16*F$5)-F$22 -> -1.2828966e+09
B36: =SUM(B28:B31) -> 1 | C36: =SUM(C28:C31) -> 1 | F36: =SUM(F28:F31) -> 1 | G36: =SUM(G28:G31) -> 1
J48: Federal | K48: State | L48: Local | M48: Other | N48: Indeterminate
I49: Statewide District | J49: =B9 -> 1022.1014 | K49: =B10 -> 4668.6343 | L49: =B11 -> 3881.851 | M49: =B12 -> 4.3600155 | N49: 0
I50: Statewide Weighted | J50: =D9 -> 1003 | K50: =D10 -> 4653 | L50: =D11 -> 3916 | M50: =D12 -> 4 | N50: =D13 -> 0
I51: Statewide Charter | J51: =C9 -> 657.67405 | K51: =C10 -> 6402.4844 | L51: =C11 -> 522.96061 | M51: =C12 -> 13.622706 | N51: 0
I52: Maricopa District | J52: =F9 -> 770.7282 | K52: =F10 -> 4452.2663 | L52: =F11 -> 4334.1476 | M52: =F12 -> 2.4942239 | N52: 0
I53: Maricopa Charter | J53: =G9 -> 393.02965 | K53: =G10 -> 6409.1268 | L53: =G11 -> 565.41195 | M53: =G12 -> 8.6472116 | N53: 0
I54: City B Charter | J54: 0 | K54: 0 | L54: 0 | M54: 0 | N54: 0
I55: City C District | J55: 0 | K55: 0 | L55: 0 | M55: 0 | N55: 0
I56: City C Charter | J56: 0 | K56: 0 | L56: 0 | M56: 0 | N56: 0

Sheet Report Figures 1,3,5,6
B3: Figure 1
B4: Arizona (2006-07) | C4: Statewide | E4: Statewide Weighted for Charter Enrollment | G4: Maricopa County | J4: Scroll down & to right
B5: Per-Pupil Revenue
B6: District | C6: 9576.9467 | E6: 9576 | G6: 9559.6363
B7: Charter | C7: 7596.7418 | E7: 7597 | G7: 7376.2156
B8: Difference | C8: ($1,980) | E8: ($1,979) | G8: ($2,183)
C9: (20.7%) | E9: (20.7%) | G9: (22.8%)
B10: Per-Pupil Revenue by Source | C10: District | D10: Charter | E10: District | F10: Charter | G10: District | H10: Charter
B11: Federal | C11: 1022.1014 | D11: 657.67405 | E11: 1003 | F11: 657.67405 | G11: 770.7282 | H11: 393.02965
B12: State | C12: 4668.6343 | D12: 6402.4844 | E12: 4653 | F12: 6402.4844 | G12: 4452.2663 | H12: 6409.1268
B13: Local | C13: 3881.851 | D13: 522.96061 | E13: 3916 | F13: 522.96061 | G13: 4334.1476 | H13: 565.41195
B14: Other | C14: 4.3600155 | D14: 13.622706 | E14: 4 | F14: 13.622706 | G14: 2.4942239 | H14: 8.6472116
B15: Indeterminate | C15: 0 | D15: 0 | E15: 0 | F15: 0 | G15: 0 | H15: 0
B16: Total | C16: 9576.9467 | D16: 7596.7418 | E16: 9576 | F16: 7596.7418 | G16: 9559.6363 | H16: 7376.2156
B17: Enrollment
B18: District | C18: 934595.52 | E18: N/A | G18: 587562.72
C19: 0.91285604 | E19: N/A | G19: 0.90934342
B20: Charter | C20: 89219.276 | E20: N/A | G20: 58576.802
C21: 0.08714396 | E21: N/A | G21: 0.090656584
B22: Number of Charters | C22: 448 | E22: N/A | G22: 194
B23: Total Revenue
B24: District | C24: 8.9505715e+09 | E24: N/A | G24: 5616885964
C25: 0.92960622 | E25: N/A | G25: 0.92857036
B26: Charter | C26: 6.777758e+08 | E26: N/A | G26: 432075120
C27: 0.070393784 | E27: N/A | G27: 0.071429641
B28: Total | C28: 9628347269 | E28: N/A | G28: 6048961084
B29: Percentage of Revenue by Source | C29: District | D29: Charter | E29: District | F29: Charter | G29: District | H29: Charter
B30: Federal | C30: 0.10672518 | D30: 0.086573175 | E30: 0.10474102 | F30: 0.086573175 | G30: 0.080623171 | H30: 0.053283374
B31: State | C31: 0.48748671 | D31: 0.84279348 | E31: 0.48590226 | F31: 0.84279348 | G31: 0.46573595 | H31: 0.86889092
B32: Local | C32: 0.40533284 | D32: 0.068840119 | E32: 0.40893901 | F32: 0.068840119 | G32: 0.45337996 | H32: 0.076653393
B33: Other | C33: 0.00045526155 | D33: 0.0017932301 | E33: 0.00041771094 | F33: 0.0017932301 | G33: 0.00026091201 | H33: 0.00117231
B34: Indeterminate | C34: =C15 -> 0 | D34: =D15 -> 0 | E34: 0 | F34: 0 | G34: 0 | H34: 0
B35: Change in district school funding if subjected to charter funding structure
C36: ($1.9 billion) | G36: ($1.3 billion)
J38: Figure 3
J39: State Policies | K39: Yes | L39: No | M39: Partial
J40: Charter schools receive their funding directly from the state | M40: X3
J41: Charter schools are eligible for local funding | L41: X
J42: Cap on funding a charter school can receive | L42: X
J43: District public schools receive differential funding (e.g. more funding for 9-12 vs. K-8 schools) | K43: X
J44: Charter schools receive differential funding | K44: X
J45: State allows district to withhold funding from charter schools for providing administrative services | K45: X4
J46: State "holds harmless" district funding for charter enrollment | L46: X
J47: School is considered LEA if authorized by non-district organization | K47: X
J48: School is considered LEA if authorized by district | L48: X
J49: Cap on number of charter schools | L49: X
J50: Cap on number of charter schools authorized per year | L50: X
J51: Cap on number of students attending charter schools | L51: X
J52: Charter schools have an open enrollment policy | K52: X5
A54: Figure 3 Notes:
A55: 3 | B55: All state-approved charters function as local education agencies (LEAs), act as their own independent fiscal agents, and receive their funding directly from the state; whereas district-sponsored charter schools receive their funding through their district and do not act as their own independent fiscal agent, but provide an adequately detailed Annual Financial Report (AFR) of revenues and expenditures for purposes of identifying the sources of revenues.
A56: 4 | B56: As part of the contract between the local school board and the charter school, the board may withhold a negotiated portion of the funding for oversight of and providing of services to the charter.
A57: 5 | B57: Arizona charter schools are open to all students in the state. While admission requirements are not permitted, charters schools can provide preferences for enrollment to the siblings of current students and, if sponsored by a local school board, to district residents.
O58: Figure 5
O59: Arizona (2006-07) | P59: Statewide District | Q59: Statewide Charters
O60: Percentage of students eligible for free or reduced price lunch6 | P60: 0.4168097 | Q60: 0.31556971
O61: Percentage of schools eligible for Title I | P61: 0.56261682 | Q61: 0.56144068
O62: Percentage of students by school type:
O63: Primary (K-5) | P63: 0.55122987 | Q63: 0.42631629
O64: Middle (6-8) | P64: 0.16096153 | Q64: 0.029611956
O65: High (9-12) | P65: 0.26477114 | Q65: 0.3161236
O66: Other (K-12, K-8, etc.) | P66: 0.023037456 | Q66: 0.22794815
S68: Figure 6
T69: Findings | U69: AZ
S70: Federal Funding | T70: Charters have access to federal funds according to state statutes (Yes = black, No = white) | U70: Y
T71: Percentage of federal revenue is greater than (>; black), equal to (=; black), or is less than (<; white) that of total enrollment for charter schools | U71: <
S72: State Funding | T72: Charters have access to state funds according to state statutes (Yes = black, No = white) | U72: Y
T73: Percentage of state revenue is greater than (>; black), equal to (=; black), or is less than (<; white) that of total enrollment for charter schools | U73: >
S74: Local Funding | T74: Charters have access to local funds according to state statutes (Yes = black, No = white) | U74: N
T75: Percentage of local revenue is greater than (>; black), equal to (=; black), or is less than (<; white) that of total enrollment for charter schools | U75: <
S76: Facilities Funding | T76: Charters have access to facilities funds according to state statutes (Yes = black, No = white) | U76: Y
T77: Percentage of facilities revenue is greater than (>; black), equal to (=; black), or is less than (<; white) that of total enrollment for charter schools | U77: <
S78: Data Availability | T78: State provides detailed, public data on federal, state, local, and other revenues for district schools (Yes = black, Partial = grey, No = white) | U78: Y
T79: State provides detailed, public data on federal, state, local and other revenues for charter schools (Yes = black, Partial = grey, No = white) | U79: Y
S80: Funding Formula | T80: Charters are treated as LEAs for funding purposes (Yes = black, Partial = grey, No = white) | U80: P8
T81: State funds student (black) or the LEA (grey) | U81: S
T82: State funding formula is fair and equitable (Yes = black, No = white) | U82: N
P85: Figure 6 Notes:
O86: 8 | P86: All charter schools are considered LEAs for purposes of receiving and administering federal funds; however, district-sponsored charter schools receive their funding through their district.

Sheet #s for Report-State
B3: Calculation of District and Charter School Amounts -- State Totals | N3: 1/21/2009
G4: # of | H4: 2006-2007 Revenues
G5: Districts /
G6: Charter | K6: County /
G7: Schools | H7: ADM | I7: Total | J7: Local | K7: Intermediate | L7: State | M7: Federal | N7: NOTES
B8: State Districts: Per Annual Report of the Arizona Superintendent of Public Instruction, Fiscal Year 2006-2007, Volume II, Section I | G8: 238 | H8: 935227.91 | I8: =SUM(J8:M8) -> 8953120539 | J8: 3627960547 | K8: 4074851 | L8: 4365833746 | M8: 955251395
C9: Adjustments:
D10: District-Sponsored Charter Schools -- AFR Not Submitted: Per Annual Report of the Arizona Superintendent of Public Instruction, Fiscal Year 2006-2007, Volume II, pg. II-5
D11: San Pedro Valley High Schools | G11: N/A | H11: -39.3 | L11: =-225563.11-16767.478-1737.9 -> -244068.49 | N11: 1
E12: #020209700
E13: Benson Unified School District
D14: Sterling Acad of Math & Science | G14: N/A | H14: -36.903 | L14: =-69629.33-3034.616-344.4 -> -73008.346 | N14: 1
E15: #080208760
E16: Peach Springs Unified SD
D17: Vail Charter High School | G17: N/A | H17: -142.845 | L17: =-813348.45-64316.604-6666.23 -> -884331.28 | N17: 1
E18: #100220700
E19: Vail Unified School District
D20: Civano Charter School | G20: N/A | H20: -86.385 | L20: =-446489.57-35298.998-4006.18 -> -485794.75 | N20: 1
E21: #100220705
E22: Vail Unified School District
D23: Coolidge High School | G23: N/A | H23: -63.12 | L23: =-103103.17-28928.852-2998.39 -> -135030.41 | N23: 1
E24: #110221710
E25: Coolidge Unified SD
D26: Casa Verde High School | G26: N/A | H26: -263.84 | L26: =-595729.2-118795.147-12312.79 -> -726837.14 | N26: 1
E27: #110502700
E28: Casa Grande Union High SD
E29: Adjustment Subtotal | G29: N/A | H29: =SUM(H11:H26) -> -632.393 | L29: =SUM(L11:L26) -> -2549070.4 | N29: 5
B31: Total -- State Districts | G31: 238 | H31: =H8+H29 -> 934595.52 | I31: =SUM(J31:M31) -> 8.9505715e+09 | J31: =J8+J29 -> 3627960547 | K31: =K8+K29 -> 4074851 | L31: =L8+L29 -> 4.3632847e+09 | M31: =M8+M29 -> 955251395 | N31: 3
B32: Total -- District Per Pupil | I32: =I31/$H31 -> 9576.9467 | J32: =J31/$H31 -> 3881.851 | K32: =K31/$H31 -> 4.3600155 | L32: =L31/$H31 -> 4668.6343 | M32: =M31/$H31 -> 1022.1014
B33: % of Revenues by Source: Districts | I33: =SUM(J33:M33) -> 1 | J33: =J31/$I31 -> 0.40533284 | K33: =K31/$I31 -> 0.00045526155 | L33: =L31/$I31 -> 0.48748671 | M33: =M31/$I31 -> 0.10672518
B34: State Charter Schools: Per Annual Report of the Arizona Superintendent of Public Instruction, Fiscal Year 2006-2007, Volume II, Section II | G34: 442 | H34: 88586.883 | I34: =SUM(J34:M34) -> 675226730 | J34: 46658167 | K34: 1215408 | L34: 568675952 | M34: 58677203
C35: Adjustments:
D36: District-Sponsored Charter Schools -- AFR Not Submitted: Per Annual Report of the Arizona Superintendent of Public Instruction, Fiscal Year 2006-2007, Volume II, pg. II-5 -- subtotal from above | G36: 6 | H36: 632.393 | L36: 2549070.4 | N36: 2 & 5
B38: Total -- State Charter Schools4 | G38: =G34+G36 -> 448 | H38: =H34+H36 -> 89219.276 | I38: =SUM(J38:M38) -> 6.777758e+08 | J38: =J34+J36 -> 46658167 | K38: =K34+K36 -> 1215408 | L38: =L34+L36 -> 5.7122502e+08 | M38: =M34+M36 -> 58677203 | N38: 3
B39: Total -- Charter Schools Per Pupil4 | I39: =I38/$H38 -> 7596.7418 | J39: =J38/$H38 -> 522.96061 | K39: =K38/$H38 -> 13.622706 | L39: =L38/$H38 -> 6402.4844 | M39: =M38/$H38 -> 657.67405
B40: % of Revenues by Source: Charters | I40: =SUM(J40:M40) -> 1 | J40: =J38/$I38 -> 0.068840119 | K40: =K38/$I38 -> 0.0017932301 | L40: =L38/$I38 -> 0.84279348 | M40: =M38/$I38 -> 0.086573175
B41: Statistics: | H41: ADM | I41: Total | J41: Local | K41: County/ Interm. | L41: State | M41: Federal
C42: Total State Public K-12 Education-ADM | H42: =H31+H38 -> 1023814.8
C43: Total State Public K-12 Education-Revenue | I43: =SUM(J43:M43) -> 9628347269 | J43: =J38+J31 -> 3674618714 | K43: =K38+K31 -> 5290259 | L43: =L38+L31 -> 4934509698 | M43: =M38+M31 -> 1013928598
C44: State K-12 Total-% of Revenue by Source | I44: =SUM(J44:M44) -> 1 | J44: =J43/I43 -> 0.38164584 | K44: =K43/I43 -> 0.00054944622 | L44: =L43/I43 -> 0.5124981 | M44: =M43/I43 -> 0.10530661
C45: % District Students | H45: =H31/H42 -> 0.91285604
C46: % Charter Students | H46: =H38/H42 -> 0.08714396
C47: Revenue by Source-% District Share | I47: =I31/I43 -> 0.92960622 | J47: =J31/J43 -> 0.98730258 | K47: =K31/K43 -> 0.77025548 | L47: =L31/L43 -> 0.88423875 | M47: =M31/M43 -> 0.94212886
C48: Revenue by Source-% Charter Share | I48: =I38/I43 -> 0.070393784 | J48: =J38/J43 -> 0.012697417 | K48: =K38/K43 -> 0.22974452 | L48: =L38/L43 -> 0.11576125 | M48: =M38/M43 -> 0.057871139
I49: =SUM(I47:I48) -> 1 | J49: =SUM(J47:J48) -> 1 | K49: =SUM(K47:K48) -> 1 | L49: =SUM(L47:L48) -> 1 | M49: =SUM(M47:M48) -> 1
C50: Per Pupil Difference: Districts-Charters | I50: =I32-I39 -> 1980.2049 | J50: =J32-J39 -> 3358.8904 | K50: =K32-K39 -> -9.2626908 | L50: =L32-L39 -> -1733.8501 | M50: =M32-M39 -> 364.42735
C51: Change in charter school funding if district per pupil is applied to charter schools: More / (Less) | I51: =SUM(J51:M51) -> 1.7667245e+08 | J51: =(J32*$H$38)-J38 -> 2.9967777e+08 | K51: =(K32*$H$38)-K38 -> -826410.57 | L51: =(L32*$H$38)-L38 -> -1.5469285e+08 | M51: =(M32*$H$38)-M38 -> 32513944
C52: Change in district school funding if charter schools per pupil is applied to all districts: More / (Less) | I52: =SUM(J52:M52) -> -1.8506906e+09 | J52: =(J39*$H$31)-J31 -> -3.1392039e+09 | K52: =(K39*$H$31)-K31 -> 8656869.4 | L52: =(L39*$H$31)-L31 -> 1.6204486e+09 | M52: =(M39*$H$31)-M31 -> -3.4059217e+08
B55: NOTES:
B56: 1 | C56: Data for district-sponsored charter schools is included in sponsoring district data (Section I), and not included in charter school totals (Section II); thus subtracted from districts.
B57: 2 | C57: Data for district-sponsored charter schools is included in sponsoring district data (Section I), and not included in charter school totals (Section II); thus added to charter schools.
B58: 3 | C58: Total used for the 2006-2007 Charter School Funding study.
B59: 4 | C59: In 2006-2007 there were 342 state- and district-sponsored charter organizations operating 448 charter school campuses statewide.
B60: 5 | C60: Per the Arizona Department of Education's School Finance Unit's Legislative, Business & Policy Advisor charter-specific local and federal revenue data is not collected for
C61: district-sponsored charter schools not submitting an AFR because the sponsoring district is treated as a single entity. Therefore, those charters may have received local and
C62: federal revenue, but the amounts cannot be determined.

Sheet #s for Report-Maricopa County
B3: Calculation of District and Charter School Amounts -- Maricopa County Totals | N3: 1/21/2009
G4: # of | H4: 2006-2007 Revenues
G5: Districts /
G6: Charter | K6: County /
G7: Schools | H7: ADM | I7: Total | J7: Local | K7: Intermediate | L7: State | M7: Federal | N7: NOTES
B8: Maricopa County Districts: Per Annual Report of the Arizona Superintendent of Public Instruction, Fiscal Year 2006-2007, Volume II, Section I | G8: 58 | H8: 587562.72 | I8: =SUM(J8:M8) -> 5616885964 | J8: 2546583549 | K8: 1465513 | L8: 2615985743 | M8: 452851159
C9: No Adjustments:
B11: Total -- Maricopa County Districts | G11: =G8+G9 -> 58 | H11: =SUM(H8:H9) -> 587562.72 | I11: =SUM(J11:M11) -> 5616885964 | J11: =J8 -> 2546583549 | K11: =K8 -> 1465513 | L11: =L8 -> 2615985743 | M11: =M8 -> 452851159 | N11: 1
B12: Total -- District Per Pupil | I12: =I11/$H11 -> 9559.6363 | J12: =J11/$H11 -> 4334.1476 | K12: =K11/$H11 -> 2.4942239 | L12: =L11/$H11 -> 4452.2663 | M12: =M11/$H11 -> 770.7282
B13: % of Revenues by Source: Districts | I13: =SUM(J13:M13) -> 1 | J13: =J11/$I11 -> 0.45337996 | K13: =K11/$I11 -> 0.00026091201 | L13: =L11/$I11 -> 0.46573595 | M13: =M11/$I11 -> 0.080623171
B14: Maricopa County Charter Schools: Per Annual Report of the Arizona Superintendent of Public Instruction, Fiscal Year 2006-2007, Volume II, Section II | G14: 194 | H14: 58576.802 | I14: =SUM(J14:M14) -> 432075120 | J14: 33120024 | K14: 506526 | L14: 375426150 | M14: 23022420
C15: No Adjustments:
B17: Total -- Maricopa Charter Schools2 | G17: =G14+G15 -> 194 | H17: =H14+H15 -> 58576.802 | I17: =SUM(J17:M17) -> 432075120 | J17: =J14+J15 -> 33120024 | K17: =K14+K15 -> 506526 | L17: =L14+L15 -> 375426150 | M17: =M14+M15 -> 23022420 | N17: 1
B18: Total -- Charter Schools Per Pupil | I18: =I17/$H17 -> 7376.2156 | J18: =J17/$H17 -> 565.41195 | K18: =K17/$H17 -> 8.6472116 | L18: =L17/$H17 -> 6409.1268 | M18: =M17/$H17 -> 393.02965
B19: % of Revenues by Source: Charters | I19: =SUM(J19:M19) -> 1 | J19: =J17/$I17 -> 0.076653393 | K19: =K17/$I17 -> 0.00117231 | L19: =L17/$I17 -> 0.86889092 | M19: =M17/$I17 -> 0.053283374
B20: Statistics: | H20: ADM | I20: Total | J20: Local | K20: County/ Interm. | L20: State | M20: Federal
C21: Total Maricopa County Public K-12 Education | H21: =H11+H17 -> 646139.53
C22: Total Maricopa County Public K-12-Revenue | I22: =SUM(J22:M22) -> 6048961084 | J22: =J17+J11 -> 2579703573 | K22: =K17+K11 -> 1972039 | L22: =L17+L11 -> 2991411893 | M22: =M17+M11 -> 475873579
C23: Maricopa Total-% of Revenue by Source | I23: =SUM(J23:M23) -> 1 | J23: =J22/I22 -> 0.42647052 | K23: =K22/I22 -> 0.00032601284 | L23: =L22/I22 -> 0.49453317 | M23: =M22/I22 -> 0.078670299
C24: % District Students | H24: =H11/H21 -> 0.90934342
C25: % Charter Students | H25: =H17/H21 -> 0.090656584
C26: Revenue by Source-% District Share | I26: =I11/I22 -> 0.92857036 | J26: =J11/J22 -> 0.98716131 | K26: =K11/K22 -> 0.74314605 | L26: =L11/L22 -> 0.87449868 | M26: =M11/M22 -> 0.95162072
C27: Revenue by Source-% Charter Share | I27: =I17/I22 -> 0.071429641 | J27: =J17/J22 -> 0.012838694 | K27: =K17/K22 -> 0.25685395 | L27: =L17/L22 -> 0.12550132 | M27: =M17/M22 -> 0.048379278
I28: =SUM(I26:I27) -> 1 | J28: =SUM(J26:J27) -> 1 | K28: =SUM(K26:K27) -> 1 | L28: =SUM(L26:L27) -> 1 | M28: =SUM(M26:M27) -> 1
C29: Per Pupil Difference: Districts-Charters | I29: =I12-I18 -> 2183.4207 | J29: =J12-J18 -> 3768.7356 | K29: =K12-K18 -> -6.1529877 | L29: =L12-L18 -> -1956.8604 | M29: =M12-M18 -> 377.69855
C30: Change in charter school funding if district per pupil is applied to charter schools: More / (Less) | I30: =(I12*$H$17)-I17 -> 1.278978e+08 | J30: =(J12*$H$17)-J17 -> 2.2076048e+08 | K30: =(K12*$H$17)-K17 -> -360422.34 | L30: =(L12*$H$17)-L17 -> -1.1462663e+08 | M30: =(M12*$H$17)-M17 -> 22124373
C31: Change in district school funding if charter schools per pupil is applied to all districts: More / (Less) | I31: =(I18*$H$11)-I11 -> -1.2828966e+09 | J31: =(J18*$H$11)-J11 -> -2.2143686e+09 | K31: =(K18*$H$11)-K11 -> 3615266.2 | L31: =(L18*$H$11)-L11 -> 1.1497782e+09 | M31: =(M18*$H$11)-M11 -> -2.2192159e+08
B34: NOTES:
B35: 1 | C35: Total used for the 2006-2007 Charter School Funding study.
B36: 2 | C36: In 2006-2007 in Maricopa County there were 194 state-sponsored charter organizations (none district-sponsored) operating 252 charter school campuses.

Sheet Charter & District Data
A1: Per Pupil Revenue
A2: For Public School Districts and 337 State-Sponsored Public Charter Schools | T2: Revenue by Source and Total Per Pupil Revenue
A3: 2006-2007 | L3: SAVE A COPY OF THIS FILE | T3: Maricopa County Charter Schools
A4: County | D4: District or Charter | G4: Total | H4: Enroll- | L4: BEFORE YOU BEGIN TO SORT | T4: 2006-2007
A5: # | B5: Name | C5: D/C | D5: # | E5: Name | F5: Type | G5: Revenue | H5: ment | I5: $PP | T5: County | W5: Charter Organization | Z5: Revenue Source | AF5: Per Pupil
A6: A | B6: B | C6: C | D6: D | E6: E | F6: F | G6: G | H6: H | I6: I | T6: # | U6: Name | V6: C/D | W6: # | X6: Name | Y6: Type | Z6: Local | AA6: Intermed | AB6: State | AC6: Federal | AD6: Total | AE6: ADM | AF6: Revenue
A7: 0 | B7: ~State | C7: ~C | D7: ~C-999999999 | E7: ~Total-Charters | F7: ~99 | G7: 675226730 | H7: 88586.893 | I7: 7622.1968 | K7: About MS Excel 2007 Tables (see at LEFT) | T7: 07 | U7: Maricopa | V7: C | W7: C-078799000 | X7: Academy of Arizona | Y7: 87 | Z7: 1483 | AA7: 0 | AB7: 2146211 | AC7: 123011 | AD7: =SUM(Z7:AC7) -> 2270705 | AE7: 338.68 | AF7: 6704.5736
A8: 0 | B8: ~State | C8: ~D | D8: ~D-999999999 | E8: ~Total-Districts | F8: ~99 | G8: 8953120539 | H8: 935228 | I8: 9573 | L8: Click the the arrow buttons in row 6 (purple) to sort. | T8: 07 | U8: Maricopa | V8: C | W8: C-078604000 | X8: Academy of Excellence | Y8: 86 | Z8: 23754 | AA8: 0 | AB8: 991909 | AC8: 177218 | AD8: =SUM(Z8:AC8) -> 1192881 | AE8: 115.59 | AF8: 10319.933
A9: 01 | B9: Apache | C9: C | D9: C-999999000 | E9: ~Subtotal-Charter Schools | F9: 99 | G9: 1095428 | H9: 96.525 | I9: 11348.645 | L9: Select a sort order to sort the list. | T9: 07 | U9: Maricopa | V9: C | W9: C-078794000 | X9: Academy with Community Partners | Y9: 87 | Z9: 19740 | AA9: 0 | AB9: 1246414 | AC9: 99506 | AD9: =SUM(Z9:AC9) -> 1365660 | AE9: 175.41 | AF9: 7785.531
A10: 01 | B10: Apache | C10: D | D10: D-999999000 | E10: ~Subtotal-Districts | F10: 9 | G10: 180814970 | H10: 12885.848 | I10: 14032.058 | L10: The last button used displays an up or down arrow. | T10: 07 | U10: Maricopa | V10: C | W10: C-078979000 | X10: Accelerated Learning Center | Y10: 89 | Z10: 64628 | AA10: 0 | AB10: 1931842 | AC10: 0 | AD10: =SUM(Z10:AC10) -> 1996470 | AE10: 282.34 | AF10: 7071.1553
A11: 01 | B11: Apache | C11: C | D11: C-018752000 | E11: 4-Winds Academy | F11: 87 | G11: 382743 | H11: 31.875 | I11: 12007.624 | L11: Always use buttons to sort (not Data | Sort). | T11: 07 | U11: Maricopa | V11: C | W11: C-078701000 | X11: Acclaim | Y11: 87 | Z11: 61351 | AA11: 0 | AB11: 2179720 | AC11: 381239 | AD11: =SUM(Z11:AC11) -> 2622310 | AE11: 336.59 | AF11: 7790.8137
A12: 01 | B12: Apache | C12: D | D12: D-010307000 | E12: Alpine | F12: E | G12: 1218442 | H12: 54.09 | I12: 22526.197 | L12: For lowest to highest per pupil in a county: | T12: 07 | U12: Maricopa | V12: C | W12: C-078938000 | X12: Advance Ed Services | Y12: 89 | Z12: 43397 | AA12: 3347 | AB12: 249416 | AC12: 6522 | AD12: =SUM(Z12:AC12) -> 302682 | AE12: 41.86 | AF12: 7230.817
A13: 01 | B13: Apache | C13: D | D13: D-010224000 | E13: Chinle | F13: U | G13: 54534230 | H13: 3658.725 | I13: 14905.255 | L13: First, sort $PP from lowest to highest (col. I). | T13: 07 | U13: Maricopa | V13: C | W13: C-078782000 | X13: Advance Ed Services, Inc. | Y13: 87 | Z13: 176722 | AA13: 1065 | AB13: 1140201 | AC13: 10052 | AD13: =SUM(Z13:AC13) -> 1328040 | AE13: 163.925 | AF13: 8101.5098
A14: 01 | B14: Apache | C14: D | D14: D-010306000 | E14: Choncho | F14: E | G14: 3138263 | H14: 187.71 | I14: 16718.678 | L14: Then, sort by County (col. A or B) | T14: 07 | U14: Maricopa | V14: C | W14: C-078501000 | X14: Ahwatukee Foothills Prep | Y14: 85 | Z14: 197337 | AA14: 0 | AB14: 1592269 | AC14: 98778 | AD14: =SUM(Z14:AC14) -> 1888384 | AE14: 225.95 | AF14: 8357.5304
A15: 01 | B15: Apache | C15: D | D15: D-010220000 | E15: Ganado | F15: U | G15: 24947680 | H15: 1759.295 | I15: 14180.498 | L15: To see all subtotals by county and the state total: | T15: 07 | U15: Maricopa | V15: C | W15: C-078793000 | X15: AIBT Non-Profit-Phoenix | Y15: 87 | Z15: 7578 | AA15: 0 | AB15: 1052557 | AC15: 25552 | AD15: =SUM(Z15:AC15) -> 1085687 | AE15: 151.76 | AF15: 7153.9734
A16: 01 | B16: Apache | C16: C | D16: C-018759000 | E16: Kin Dah Lichii Olta | F16: 87 | G16: 433103 | H16: 40.49 | I16: 10696.542 | L16: Click the arrow button in E6 and sort A to Z. | T16: 07 | U16: Maricopa | V16: C | W16: C-078970000 | X16: Air Academy High | Y16: 89 | Z16: 171861 | AA16: 0 | AB16: 1179817 | AC16: 1344 | AD16: =SUM(Z16:AC16) -> 1353022 | AE16: 188.848 | AF16: 7164.6086
A17: 01 | B17: Apache | C17: D | D17: D-010323000 | E17: Mcnary | F17: E | G17: 2548648 | H17: 155.78 | I17: 16360.56 | L17: To return tor original sort order: | T17: 07 | U17: Maricopa | V17: C | W17: C-078967000 | X17: All Aboard | Y17: 89 | Z17: 3357 | AA17: 0 | AB17: 437264 | AC17: 17689 | AD17: =SUM(Z17:AC17) -> 458310 | AE17: 61.155 | AF17: 7494.236
A18: 01 | B18: Apache | C18: C | D18: C-018760000 | E18: Nazlini Community | F18: 87 | G18: 279582 | H18: 24.16 | I18: 11572.103 | M18: 1) Use button at E6 to sort A to Z. | T18: 07 | U18: Maricopa | V18: C | W18: C-078724000 | X18: Allen-Cochran | Y18: 87 | Z18: 66356 | AA18: 0 | AB18: 1890662 | AC18: 0 | AD18: =SUM(Z18:AC18) -> 1957018 | AE18: 290.66 | AF18: 6733.0145
A19: 01 | B19: Apache | C19: D | D19: D-010227000 | E19: Red Mesa | F19: U | G19: 17339902 | H19: 975.785 | I19: 17770.208 | M19: 2) Use button at B6 to sort A to Z. | T19: 07 | U19: Maricopa | V19: C | W19: C-078989000 | X19: American Basic | Y19: 89 | Z19: 113998 | AA19: 0 | AB19: 3542782 | AC19: 169125 | AD19: =SUM(Z19:AC19) -> 3825905 | AE19: 582.51 | AF19: 6567.9645
A20: 01 | B20: Apache | C20: D | D20: D-010210000 | E20: Round Valley | F20: U | G20: 12377297 | H20: 1411.95 | I20: 8766.1015 | T20: 07 | U20: Maricopa | V20: C | W20: C-078785000 | X20: APEX Ed Systems, Inc. | Y20: 87 | Z20: 106359 | AA20: 0 | AB20: 1011226 | AC20: 0 | AD20: =SUM(Z20:AC20) -> 1117585 | AE20: 153.575 | AF20: 7277.1284
A21: 01 | B21: Apache | C21: D | D21: D-010218000 | E21: Sanders | F21: U | G21: 15088528 | H21: 1037.9 | I21: 14537.555 | T21: 07 | U21: Maricopa | V21: C | W21: C-078946000 | X21: Apex Public Academy | Y21: 89 | Z21: 1595 | AA21: 0 | AB21: 268774 | AC21: 34343 | AD21: =SUM(Z21:AC21) -> 304712 | AE21: 44.1 | AF21: 6909.5692
A22: 01 | B22: Apache | C22: D | D22: D-010201000 | E22: St. Johns | F22: U | G22: 9633254 | H22: 999.813 | I22: 9635.0558 | T22: 07 | U22: Maricopa | V22: C | W22: C-078665000 | X22: Arizona Academy of Sci. & Tech. | Y22: 86 | Z22: 5236 | AA22: 0 | AB22: 883625 | AC22: 30832 | AD22: =SUM(Z22:AC22) -> 919693 | AE22: 132.605 | AF22: 6935.5831
A23: 01 | B23: Apache | C23: D | D23: D-010309000 | E23: Vernon | F23: E | G23: 1469331 | H23: 71.515 | I23: 20545.774 | K23: Highlighting Legend: | T23: 07 | U23: Maricopa | V23: C | W23: C-078707000 | X23: Arizona Agribus. & Equine, Inc. | Y23: 87 | Z23: 36706 | AA23: 0 | AB23: 1596867 | AC23: 19509 | AD23: =SUM(Z23:AC23) -> 1653082 | AE23: 229.043 | AF23: 7217.3435
A24: 01 | B24: Apache | C24: D | D24: D-010208000 | E24: Window Rock | F24: U | G24: 38519395 | H24: 2573.285 | I24: 14968.958 | L24: Purple = Drop-down arrow buttons. | T24: 07 | U24: Maricopa | V24: C | W24: C-078993000 | X24: Arizona Agribusiness & Equine | Y24: 89 | Z24: 38521 | AA24: 0 | AB24: 1978054 | AC24: 208687 | AD24: 2225262 | AE24: 288.66 | AF24: 7708.9379
A25: 02 | B25: Cochise | C25: C | D25: C-999999000 | E25: ~Subtotal-Charter Schools | F25: 99 | G25: 10348167 | H25: 1338.95 | I25: 7728.5687 | L25: Yellow = Subtotals by county and state total | T25: 07 | U25: Maricopa | V25: C | W25: C-078723000 | X25: Arizona Call-a-Teen Youth | Y25: 87 | Z25: 202706 | AA25: 0 | AB25: 572577 | AC25: 0 | AD25: =SUM(Z25:AC25) -> 775283 | AE25: 84.818 | AF25: 9140.548
A26: 02 | B26: Cochise | C26: D | D26: D-999999000 | E26: ~Subtotal-Districts | F26: 9 | G26: 168974628 | H26: 18844.609 | I26: 8966.7357 | M26: for public charter schools. | T26: 07 | U26: Maricopa | V26: C | W26: C-078511000 | X26: Arizona Connections | Y26: 85 | Z26: 20910 | AA26: 0 | AB26: 3065283 | AC26: 0 | AD26: =SUM(Z26:AC26) -> 3086193 | AE26: 475.86 | AF26: 6485.5062
A27: 02 | B27: Cochise | C27: D | D27: D-020342000 | E27: Apache | F27: E | G27: 174587 | H27: 6.54 | I27: 26695.26 | L27: Green = Subtotals by county and state total | T27: 07 | U27: Maricopa | V27: C | W27: C-078922000 | X27: Arizona Integrated Academics & Tech | Y27: 89 | Z27: 0 | AA27: 0 | AB27: 2541796 | AC27: 0 | AD27: =SUM(Z27:AC27) -> 2541796 | AE27: 413.71 | AF27: 6143.9076
A28: 02 | B28: Cochise | C28: D | D28: D-020453000 | E28: Ash Creek | F28: E | G28: 854056 | H28: 31.085 | I28: 27474.859 | M28: for public school districts. | T28: 07 | U28: Maricopa | V28: C | W28: C-078991000 | X28: Arizona Montessori-Anthem | Y28: 89 | Z28: 24518 | AA28: 0 | AB28: 599486 | AC28: 217523 | AD28: =SUM(Z28:AC28) -> 841527 | AE28: 88.38 | AF28: 9521.6904
A29: 02 | B29: Cochise | C29: D | D29: D-020209000 | E29: Benson | F29: U | G29: 9145748 | H29: 972.485 | I29: 9404.5132 | T29: 07 | U29: Maricopa | V29: C | W29: C-078722000 | X29: Arizona School for the Arts | Y29: 87 | Z29: 364418 | AA29: 51000 | AB29: 2407732 | AC29: 30388 | AD29: =SUM(Z29:AC29) -> 2853538 | AE29: 361.71 | AF29: 7889.0216
A30: 02 | B30: Cochise | C30: D | D30: D-020202000 | E30: Bisbee | F30: U | G30: 10861881 | H30: 944.19 | I30: 11503.914 | T30: 07 | U30: Maricopa | V30: C | W30: C-078961000 | X30: Ascending Roots | Y30: 89 | Z30: 19830 | AA30: 0 | AB30: 618973 | AC30: 128296 | AD30: =SUM(Z30:AC30) -> 767099 | AE30: 93.81 | AF30: 8177.156
A31: 02 | B31: Cochise | C31: D | D31: D-020214000 | E31: Bowie | F31: U | G31: 1632181 | H31: 91.12 | I31: 17912.434 | T31: 07 | U31: Maricopa | V31: C | W31: C-078510000 | X31: Arizona Agribus. & Equine, Inc. | Y31: 85 | Z31: 16677 | AA31: 0 | AB31: 872503 | AC31: 3141 | AD31: =SUM(Z31:AC31) -> 892321 | AE31: 124.11 | AF31: 7189.7591
A32: 02 | B32: Cochise | C32: C | D32: C-028750000 | E32: Center for Academic Success | F32: 87 | G32: 4572594 | H32: 583.825 | I32: 7832.1312 | T32: 07 | U32: Maricopa | V32: C | W32: C-078614000 | X32: Avondale Learning | Y32: 86 | Z32: 8297 | AA32: 0 | AB32: 565100 | AC32: 20644 | AD32: =SUM(Z32:AC32) -> 594041 | AE32: 78.19 | AF32: 7597.4038
A33: 02 | B33: Cochise | C33: D | D33: D-020326000 | E33: Cochise | F33: E | G33: 1230120 | H33: 59.615 | I33: 20634.404 | K33: D/C Legend: | T33: 07 | U33: Maricopa | V33: C | W33: C-078731000 | X33: Back-to-Basics | Y33: 87 | Z33: 15210 | AA33: 0 | AB33: 1115515 | AC33: 170015 | AD33: =SUM(Z33:AC33) -> 1300740 | AE33: 168.39 | AF33: 7724.568
A34: 02 | B34: Cochise | C34: C | D34: C-028701000 | E34: Cochise Community Dev. Corp | F34: 87 | G34: 1567979 | H34: 211.105 | I34: 7427.484 | L34: C = Public Charter School | T34: 07 | U34: Maricopa | V34: C | W34: C-078988000 | X34: Ball Charter-Dobson | Y34: 89 | Z34: 503809 | AA34: 0 | AB34: 3492648 | AC34: 14138 | AD34: =SUM(Z34:AC34) -> 4010595 | AE34: 561.715 | AF34: 7139.9108
A35: 02 | B35: Cochise | C35: D | D35: D-020801000 | E35: Cochise Tech | F35: T | G35: 2083967 | H35: 474.273 | I35: 4394.0241 | L35: D = Traditional Public School District | T35: 07 | U35: Maricopa | V35: C | W35: C-078987000 | X35: Ball Charter-Hearn | Y35: 89 | Z35: 297748 | AA35: 0 | AB35: 3115399 | AC35: 85283 | AD35: 3498430 | AE35: 518.555 | AF35: 6746.4975
A36: 02 | B36: Cochise | C36: D | D36: D-020345000 | E36: Double Adobe | F36: E | G36: 601016 | H36: 55.54 | I36: 10821.318 | T36: 07 | U36: Maricopa | V36: C | W36: C-078736000 | X36: BASIS | Y36: 87 | Z36: 289180 | AA36: 0 | AB36: 1586098 | AC36: 55463 | AD36: =SUM(Z36:AC36) -> 1930741 | AE36: 248.63 | AF36: 7765.519
A37: 02 | B37: Cochise | C37: D | D37: D-020227000 | E37: Douglas | F37: U | G37: 31399430 | H37: 3985.565 | I37: 7878.2883 | T37: 07 | U37: Maricopa | V37: C | W37: C-078972000 | X37: Bell Canyon | Y37: 89 | Z37: 136073 | AA37: 0 | AB37: 2172997 | AC37: 130483 | AD37: =SUM(Z37:AC37) -> 2439553 | AE37: 346.1 | AF37: 7048.694
A38: 02 | B38: Cochise | C38: D | D38: D-020412000 | E38: Elfrida | F38: E | G38: 1475013 | H38: 167.45 | I38: 8808.6772 | T38: 07 | U38: Maricopa | V38: C | W38: C-078766000 | X38: Benchmark | Y38: 87 | Z38: 154416 | AA38: 0 | AB38: 2387546 | AC38: 32157 | AD38: =SUM(Z38:AC38) -> 2574119 | AE38: 374.98 | AF38: 6864.6834
A39: 02 | B39: Cochise | C39: D | D39: D-020381000 | E39: Forrest | F39: E | G39: 0 | H39: 0 | I39: 0 | K39: Type Code Legend: | T39: 07 | U39: Maricopa | V39: C | W39: C-078754000 | X39: Benjamin Franklin | Y39: 87 | Z39: 203513 | AA39: 0 | AB39: 9985260 | AC39: 0 | AD39: =SUM(Z39:AC39) -> 10188773 | AE39: 1716.453 | AF39: 5935.9464
A40: 02 | B40: Cochise | C40: D | D40: D-020100000 | E40: Fort Huachuca | F40: A | G40: 14746472 | H40: 971.32 | I40: 15181.889 | T40: 07 | U40: Maricopa | V40: C | W40: C-078745000 | X40: Blueprint Ed | Y40: 87 | Z40: 9984 | AA40: 0 | AB40: 1222666 | AC40: 130196 | AD40: =SUM(Z40:AC40) -> 1362846 | AE40: 175.4 | AF40: 7769.9316
A41: 02 | B41: Cochise | C41: D | D41: D-020355000 | E41: McNeal | F41: E | G41: 710706 | H41: 43.54 | I41: 16323.059 | L41: Public School Districts: | T41: 07 | U41: Maricopa | V41: C | W41: C-078746000 | X41: Bradley Academy | Y41: 87 | Z41: 101693 | AA41: 0 | AB41: 853844 | AC41: 88788 | AD41: =SUM(Z41:AC41) -> 1044325 | AE41: 122.535 | AF41: 8522.667
A42: 02 | B42: Cochise | C42: D | D42: D-020323000 | E42: Naco | F42: E | G42: 3038606 | H42: 251.845 | I42: 12065.381 | M42: E = Elementary District | T42: 07 | U42: Maricopa | V42: C | W42: C-078762000 | X42: Bright Beginnings | Y42: 87 | Z42: 359788 | AA42: 0 | AB42: 2654908 | AC42: 0 | AD42: =SUM(Z42:AC42) -> 3014696 | AE42: 411.485 | AF42: 7326.3813
A43: 02 | B43: Cochise | C43: C | D43: C-028751000 | E43: Omega Alpha | F43: 87 | G43: 3768203 | H43: 484.58 | I43: 7776.2248 | M43: H= Union High School District | T43: 07 | U43: Maricopa | V43: C | W43: C-098749000 | X43: CAFA | Y43: 87 | Z43: 68188 | AA43: 0 | AB43: 2711680 | AC43: 280689 | AD43: =SUM(Z43:AC43) -> 3060557 | AE43: 408.565 | AF43: 7490.9916
A44: 02 | B44: Cochise | C44: D | D44: D-020349000 | E44: Palominas | F44: E | G44: 11755829 | H44: 1019.685 | I44: 11528.883 | M44: U = Unified District | T44: 07 | U44: Maricopa | V44: C | W44: C-078768000 | X44: Cambridge Academy East | Y44: 87 | Z44: 64794 | AA44: 0 | AB44: 1370871 | AC44: 17939 | AD44: =SUM(Z44:AC44) -> 1453604 | AE44: 211.51 | AF44: 6872.5072
A45: 02 | B45: Cochise | C45: D | D45: D-020422000 | E45: Pearce | F45: E | G45: 1297023 | H45: 114.475 | I45: 11330.186 | M45: C = Consolidated District | T45: 07 | U45: Maricopa | V45: C | W45: C-078909000 | X45: Carden Elementary | Y45: 89 | Z45: 52857 | AA45: 0 | AB45: 2584508 | AC45: 160505 | AD45: =SUM(Z45:AC45) -> 2797870 | AE45: 404.72 | AF45: 6913.1004
A46: 02 | B46: Cochise | C46: D | D46: D-020364000 | E46: Pomerene | F46: E | G46: 1273551 | H46: 122.73 | I46: 10376.852 | M46: CE = Consolidated Elementary District | T46: 07 | U46: Maricopa | V46: C | W46: C-078524000 | X46: Career Success | Y46: 85 | Z46: 74179 | AA46: 0 | AB46: 4437778 | AC46: 477645 | AD46: =SUM(Z46:AC46) -> 4989602 | AE46: 799.198 | AF46: 6243.2614
A47: 02 | B47: Cochise | C47: D | D47: D-020366000 | E47: Rucker | F47: E | G47: 2752 | H47: 0 | I47: 0 | M47: A = Accommodation District | T47: 07 | U47: Maricopa | V47: C | W47: C-078908000 | X47: CASY Country Day | Y47: 89 | Z47: 273969 | AA47: 0 | AB47: 1812354 | AC47: 29811 | AD47: =SUM(Z47:AC47) -> 2116134 | AE47: 276.795 | AF47: 7645.1309
A48: 02 | B48: Cochise | C48: D | D48: D-020218000 | E48: San Simon | F48: U | G48: 1594516 | H48: 122.415 | I48: 13025.495 | M48: T = Technology District | T48: 07 | U48: Maricopa | V48: C | W48: C-078772000 | X48: Challenge School | Y48: 87 | Z48: 275273 | AA48: 0 | AB48: 3387260 | AC48: 179442 | AD48: =SUM(Z48:AC48) -> 3841975 | AE48: 566.43 | AF48: 6782.7887
A49: 02 | B49: Cochise | C49: C | D49: C-028752000 | E49: Sierra Summit | F49: 87 | G49: 439391 | H49: 59.44 | I49: 7392.177 | M49: R = Regional District | T49: 07 | U49: Maricopa | V49: C | W49: C-078957000 | X49: Challenger Basic | Y49: 89 | Z49: 41227 | AA49: 0 | AB49: 1007201 | AC49: 14715 | AD49: =SUM(Z49:AC49) -> 1063143 | AE49: 147.77 | AF49: 7194.5794
A50: 02 | B50: Cochise | C50: D | D50: D-020268000 | E50: Sierra Vista | F50: U | G50: 48638288 | H50: 6610.383 | I50: 7357.8623 | M50: V = Vocational District | T50: 07 | U50: Maricopa | V50: C | W50: C-078515000 | X50: Chandler Prep | Y50: 85 | Z50: 249817 | AA50: 0 | AB50: 1489026 | AC50: 41636 | AD50: =SUM(Z50:AC50) -> 1780479 | AE50: 229.86 | AF50: 7745.928
A51: 02 | B51: Cochise | C51: D | D51: D-020221000 | E51: St David | F51: U | G51: 4720642 | H51: 460.513 | I51: 10250.833 | M51: EC = Education Center | T51: 07 | U51: Maricopa | V51: C | W51: C-078971000 | X51: Choice Ed & Dev-Arizona | Y51: 89 | Z51: 48845 | AA51: 0 | AB51: 1796159 | AC51: 160250 | AD51: =SUM(Z51:AC51) -> 2005254 | AE51: 269.365 | AF51: 7444.3747
A52: 02 | B52: Cochise | C52: D | D52: D-020201000 | E52: Tombstone | F52: U | G52: 7911813 | H52: 868.78 | I52: 9106.8084 | M52: RA = Regional Accommodation District | T52: 07 | U52: Maricopa | V52: C | W52: C-078744000 | X52: Choice Ed & Dev-Corp | Y52: 87 | Z52: 45221 | AA52: 0 | AB52: 1388809 | AC52: 0 | AD52: =SUM(Z52:AC52) -> 1434030 | AE52: 64.34 | AF52: 22288.312
A53: 02 | B53: Cochise | C53: D | D53: D-020522000 | E53: Valley | F53: H | G53: 2157147 | H53: 162.59 | I53: 13267.403 | T53: 07 | U53: Maricopa | V53: C | W53: C-078916000 | X53: Choice Ed & Dev-Learning | Y53: 89 | Z53: 16861 | AA53: 0 | AB53: 998532 | AC53: 0 | AD53: =SUM(Z53:AC53) -> 1015393 | AE53: 143.853 | AF53: 7058.5459
A54: 02 | B54: Cochise | C54: D | D54: D-020213000 | E54: Wilcox | F54: U | G54: 11669284 | H54: 1308.47 | I54: 8918.2664 | L54: 337 State-Sponsored Public Charter Schools: | T54: 07 | U54: Maricopa | V54: C | W54: C-078915000 | X54: Choice Ed & Dev-Sequoia | Y54: 89 | Z54: 93834 | AA54: 0 | AB54: 4680081 | AC54: 0 | AD54: =SUM(Z54:AC54) -> 4773915 | AE54: 653.92 | AF54: 7300.4572
A55: 03 | B55: Coconino | C55: C | D55: C-999999000 | E55: ~Subtotal-Charter Schools | F55: 99 | G55: 12989688 | H55: 1574.003 | I55: 8252.645 | M55: 86 = State Board of Education | T55: 07 | U55: Maricopa | V55: C | W55: C-078917000 | X55: Choice Ed & Dev-Sequoia | Y55: 89 | Z55: 23737 | AA55: 0 | AB55: 1088414 | AC55: 0 | AD55: =SUM(Z55:AC55) -> 1112151 | AE55: 146.42 | AF55: 7595.6222
A56: 03 | B56: Coconino | C56: D | D56: D-999999000 | E56: ~Subtotal-Districts | F56: 9 | G56: 187279342 | H56: 17937.885 | I56: 10440.436 | M56: 87 & 89 = State Board for Charter Schools | T56: 07 | U56: Maricopa | V56: C | W56: C-078995000 | X56: Cholla Academy | Y56: 89 | Z56: 15495 | AA56: 2629 | AB56: 1716254 | AC56: 26413 | AD56: =SUM(Z56:AC56) -> 1760791 | AE56: 255.965 | AF56: 6879.0303
A57: 03 | B57: Coconino | C57: D | D57: D-030801000 | E57: CAVIAT | F57: V | G57: 2255166 | H57: 678.31 | I57: 3324.6834 | T57: 07 | U57: Maricopa | V57: C | W57: C-078994000 | X57: Cornerstone | Y57: 89 | Z57: 4014 | AA57: 0 | AB57: 1379631 | AC57: 0 | AD57: =SUM(Z57:AC57) -> 1383645 | AE57: 198.27 | AF57: 6978.5898
A58: 03 | B58: Coconino | C58: D | D58: D-030305000 | E58: Chevelon Butte | G58: 480179 | H58: 0 | I58: 0 | T58: 07 | U58: Maricopa | V58: C | W58: C-078975000 | X58: Cortez Middle | Y58: 89 | Z58: 19937 | AA58: 0 | AB58: 1049866 | AC58: 212203 | AD58: =SUM(Z58:AC58) -> 1282006 | AE58: 164.54 | AF58: 7791.455
A59: 03 | B59: Coconino | C59: D | D59: D-030199000 | E59: Coconino County | F59: RA | G59: 1427181 | H59: 136.245 | I59: 10475.107 | K59: Source: | T59: 07 | U59: Maricopa | V59: C | W59: C-078513000 | X59: County Gradens Ed Services | Y59: 85 | Z59: 43213 | AA59: 0 | AB59: 2517369 | AC59: 0 | AD59: =SUM(Z59:AC59) -> 2560582 | AE59: 374.29 | AF59: 6841.1713
A60: 03 | B60: Coconino | C60: D | D60: D-030201000 | E60: Flagstaff | F60: U | G60: 104885235 | H60: 10666.983 | I60: 9832.6992 | T60: 07 | U60: Maricopa | V60: C | W60: C-078921000 | X60: Crown | Y60: 89 | Z60: 123536 | AA60: 0 | AB60: 2053081 | AC60: 114507 | AD60: =SUM(Z60:AC60) -> 2291124 | AE60: 293.75 | AF60: 7799.5711
A61: 03 | B61: Coconino | C61: C | D61: C-038750000 | E61: Flagstaff Arts | F61: 87 | G61: 1168815 | H61: 161.335 | I61: 7244.6462 | L61: District Data: | T61: 07 | U61: Maricopa | V61: C | W61: C-078702000 | X61: D. W. Higgins Institute | Y61: 87 | Z61: 63459 | AA61: 0 | AB61: 879561 | AC61: 14546 | AD61: =SUM(Z61:AC61) -> 957566 | AE61: 114.515 | AF61: 8361.9264
A62: 03 | B62: Coconino | C62: C | D62: C-038752000 | E62: Flagstaff Junior Academy | F62: 87 | G62: 1544319 | H62: 197.19 | I62: 7831.6294 | L62: Per Annual Report of the Arizona Superintendent of Public | T62: 07 | U62: Maricopa | V62: C | W62: C-078704000 | X62: DCS Partner | Y62: 87 | Z62: 105980 | AA62: 0 | AB62: 1157165 | AC62: 63505 | AD62: =SUM(Z62:AC62) -> 1326650 | AE62: 164.82 | AF62: 8049.0838
A63: 03 | B63: Coconino | C63: C | D63: C-038703000 | E63: Flagstaff Unified | F63: 87 | G63: 350876 | H63: 35.84 | I63: 9790.067 | L63: Instruction, Fiscal Year 2006-2007, Volume II, Section I. | T63: 07 | U63: Maricopa | V63: C | W63: C-078934000 | X63: Deer Valley | Y63: 89 | Z63: 5565 | AA63: 0 | AB63: 436294 | AC63: 10281 | AD63: =SUM(Z63:AC63) -> 452140 | AE63: 67.743 | AF63: 6674.3427
A64: 03 | B64: Coconino | C64: D | D64: D-030206000 | E64: Fredonia-Moccasin | F64: U | G64: 3380358 | H64: 357.48 | I64: 9456.0759 | T64: 07 | U64: Maricopa | V64: C | W64: C-078947000 | X64: Desert hills Public | Y64: 89 | Z64: 93867 | AA64: 0 | AB64: 3316027 | AC64: 156036 | AD64: =SUM(Z64:AC64) -> 3565930 | AE64: 506.64 | AF64: 7038.3902
A65: 03 | B65: Coconino | C65: D | D65: D-030204000 | E65: Grand Canyon | F65: U | G65: 4037319 | H65: 280.03 | I65: 14417.452 | L65: Charter Data: | T65: 07 | U65: Maricopa | V65: C | W65: C-078725000 | X65: Eagles Aerie | Y65: 87 | Z65: 118005 | AA65: 0 | AB65: 1532425 | AC65: 0 | AD65: =SUM(Z65:AC65) -> 1650430 | AE65: 233.22 | AF65: 7076.7087
A66: 03 | B66: Coconino | C66: D | D66: D-030310000 | E66: Maine | F66: C | G66: 1924461 | H66: 102.828 | I66: 18715.34 | L66: Per Annual Report of the Arizona Superintendent of Public | T66: 07 | U66: Maricopa | V66: C | W66: C-078509000 | X66: East Mesa | Y66: 85 | Z66: 226944 | AA66: 0 | AB66: 2711740 | AC66: 348814 | AD66: =SUM(Z66:AC66) -> 3287498 | AE66: 408.695 | AF66: 8043.8909
A67: 03 | B67: Coconino | C67: C | D67: C-038705000 | E67: Montessori-Flagstaff | F67: 87 | G67: 1656628 | H67: 242.3 | I67: 6837.0945 | L67: Instruction, Fiscal Year 2006-2007, Volume II, Section II. | T67: 07 | U67: Maricopa | V67: C | W67: C-078683000 | X67: East Valley Academy | Y67: 86 | Z67: 0 | AA67: 0 | AB67: 143574 | AC67: 0 | AD67: =SUM(Z67:AC67) -> 143574 | AE67: 20.71 | AF67: 6932.593
A68: 03 | B68: Coconino | C68: C | D68: C-038751000 | E68: Mountain School | F68: 87 | G68: 1114660 | H68: 134.625 | I68: 8279.74 | T68: 07 | U68: Maricopa | V68: C | W68: C-078990000 | X68: E-cademie | Y68: 89 | Z68: 34903 | AA68: 0 | AB68: 969019 | AC68: 204217 | AD68: =SUM(Z68:AC68) -> 1208139 | AE68: 136.89 | AF68: 8825.6191
A69: 03 | B69: Coconino | C69: C | D69: C-038701000 | E69: Northland Prep | F69: 87 | G69: 2521493 | H69: 344.483 | I69: 7319.6442 | T69: 07 | U69: Maricopa | V69: C | W69: C-078742000 | X69: Edkey-Pathfinder Academy | Y69: 87 | Z69: 3370 | AA69: 0 | AB69: 356071 | AC69: 0 | AD69: =SUM(Z69:AC69) -> 359441 | AE69: 52.845 | AF69: 6801.7977
A70: 03 | B70: Coconino | C70: D | D70: D-030208000 | E70: Page | F70: U | G70: 32002000 | H70: 2877.718 | I70: 11120.617 | T70: 07 | U70: Maricopa | V70: C | W70: C-078740000 | X70: Edkey-Redwood Academy | Y70: 87 | Z70: 43119 | AA70: 0 | AB70: 569493 | AC70: 0 | AD70: =SUM(Z70:AC70) -> 612612 | AE70: 85.868 | AF70: 7134.3457
A71: 03 | B71: Coconino | C71: C | D71: C-038753000 | E71: Painted Desert Demonstration | F71: 87 | G71: 1281147 | H71: 68.81 | I71: 18618.616 | T71: 07 | U71: Maricopa | V71: C | W71: C-078739000 | X71: Educational Admin Services | Y71: 87 | Z71: 0 | AA71: 0 | AB71: 435445 | AC71: 13591 | AD71: =SUM(Z71:AC71) -> 449036 | AE71: 65.38 | AF71: 6868.0942
A72: 03 | B72: Coconino | C72: C | D72: C-038702000 | E72: PEAK Schools | F72: 87 | G72: 1128816 | H72: 116.595 | I72: 9681.5129 | T72: 07 | U72: Maricopa | V72: C | W72: C-078717000 | X72: EduPreneurship | Y72: 87 | Z72: 5191 | AA72: 3000 | AB72: 940195 | AC72: 53550 | AD72: =SUM(Z72:AC72) -> 1001936 | AE72: 143.23 | AF72: 6995.2943
A73: 03 | B73: Coconino | C73: C | D73: C-038706000 | E73: Pine Forest Ed Assoc | F73: 87 | G73: 1580038 | H73: 199.345 | I73: 7926.1481 | T73: 07 | U73: Maricopa | V73: C | W73: C-078634000 | X73: Edu-Prize | Y73: 86 | Z73: 193560 | AA73: 0 | AB73: 6085873 | AC73: 117855 | AD73: =SUM(Z73:AC73) -> 6397288 | AE73: 1048.785 | AF73: 6099.7135
A74: 03 | B74: Coconino | C74: D | D74: D-030215000 | E74: Tuba City | F74: U | G74: 29200795 | H74: 2103.378 | I74: 13882.809 | T74: 07 | U74: Maricopa | V74: C | W74: C-078911000 | X74: E-Institute | Y74: 89 | Z74: 0 | AA74: 0 | AB74: 1467396 | AC74: 46737 | AD74: =SUM(Z74:AC74) -> 1514133 | AE74: 254.34 | AF74: 5953.1847
A75: 03 | B75: Coconino | C75: C | D75: C-038708000 | E75: Visions Unlimited | F75: 87 | G75: 642896 | H75: 73.48 | I75: 8749.2651 | T75: 07 | U75: Maricopa | V75: C | W75: C-078718000 | X75: El Dorado High | Y75: 87 | Z75: 17478 | AA75: 0 | AB75: 1512378 | AC75: 119411 | AD75: =SUM(Z75:AC75) -> 1649267 | AE75: 216.805 | AF75: 7607.1447
A76: 03 | B76: Coconino | C76: D | D76: D-030202000 | E76: Williams | F76: U | G76: 7686648 | H76: 734.913 | I76: 10459.263 | T76: 07 | U76: Maricopa | V76: C | W76: C-078664000 | X76: Employ-Ability Unlimited | Y76: 86 | Z76: 61077 | AA76: 0 | AB76: 1651633 | AC76: 277594 | AD76: =SUM(Z76:AC76) -> 1990304 | AE76: 244.575 | AF76: 8137.8064
A77: 04 | B77: Gila | C77: C | D77: C-999999000 | E77: ~Subtotal-Charter Schools | F77: 99 | G77: 3695854 | H77: 429.015 | I77: 8614.7431 | T77: 07 | U77: Maricopa | V77: C | W77: C-078610000 | X77: Enterprise Academy | Y77: 86 | Z77: 8734 | AA77: 0 | AB77: 524823 | AC77: 71963 | AD77: =SUM(Z77:AC77) -> 605520 | AE77: 77.16 | AF77: 7847.5894
A78: 04 | B78: Gila | C78: D | D78: D-999999000 | E78: ~Subtotal-Districts | F78: 9 | G78: 78430782 | H78: 7585.492 | I78: 10339.577 | T78: 07 | U78: Maricopa | V78: C | W78: C-078505000 | X78: Esperanza Community | Y78: 85 | Z78: 57652 | AA78: 0 | AB78: 564556 | AC78: 149837 | AD78: =SUM(Z78:AC78) -> 772045 | AE78: 66.93 | AF78: 11535.111
A79: 04 | B79: Gila | C79: C | D79: C-048701000 | E79: Destiny | F79: 87 | G79: 2167951 | H79: 224.87 | I79: 9640.9081 | T79: 07 | U79: Maricopa | V79: C | W79: C-078110000 | X79: Expiritu Community | Y79: 81 | Z79: 39610 | AA79: 227910 | AB79: 4706523 | AC79: 1003300 | AD79: =SUM(Z79:AC79) -> 5977343 | AE79: 752.86 | AF79: 7939.5147
A80: 04 | B80: Gila | C80: D | D80: D-040149000 | E80: Gila County | F80: R | G80: 661865 | H80: 91.72 | I80: 7216.147 | T80: 07 | U80: Maricopa | V80: C | W80: C-078948000 | X80: Extrella High | Y80: 89 | Z80: 23798 | AA80: 0 | AB80: 3107712 | AC80: 258916 | AD80: =SUM(Z80:AC80) -> 3390426 | AE80: 475.64 | AF80: 7128.1347
A81: 04 | B81: Gila | C81: D | D81: D-040201000 | E81: Globe | F81: U | G81: 15778010 | H81: 1887.68 | I81: 8358.4135 | T81: 07 | U81: Maricopa | V81: C | W81: C-078901000 | X81: Excalibur | Y81: 89 | Z81: 61055 | AA81: 0 | AB81: 2629172 | AC81: 524887 | AD81: =SUM(Z81:AC81) -> 3215114 | AE81: 393.46 | AF81: 8171.3872
A82: 04 | B82: Gila | C82: D | D82: D-040241000 | E82: Hayden-Winkelman | F82: U | G82: 5980679 | H82: 412.955 | I82: 14482.641 | T82: 07 | U82: Maricopa | V82: C | W82: C-078608000 | X82: Florence Critteton Services | Y82: 86 | Z82: 153085 | AA82: 3500 | AB82: 1269945 | AC82: 144171 | AD82: =SUM(Z82:AC82) -> 1570701 | AE82: 191.93 | AF82: 8183.718
A83: 04 | B83: Gila | C83: C | D83: C-048750000 | E83: Liberty High | F83: 87 | G83: 477794 | H83: 65.66 | I83: 7276.7895 | T83: 07 | U83: Maricopa | V83: C | W83: C-078628000 | X83: Foothills Academy | Y83: 86 | Z83: 196085 | AA83: 0 | AB83: 1624008 | AC83: 64060 | AD83: =SUM(Z83:AC83) -> 1884153 | AE83: 238.71 | AF83: 7893.0627
A84: 04 | B84: Gila | C84: D | D84: D-040240000 | E84: Miami | F84: U | G84: 9226111 | H84: 1098.378 | I84: 8399.7595 | T84: 07 | U84: Maricopa | V84: C | W84: C-078755000 | X84: Fountain Hills | Y84: 87 | Z84: 185701 | AA84: 0 | AB84: 1089568 | AC84: 0 | AD84: =SUM(Z84:AC84) -> 1275269 | AE84: 164.97 | AF84: 7730.3085
A85: 04 | B85: Gila | C85: D | D85: D-040210000 | E85: Payson | F85: U | G85: 23065434 | H85: 2699.125 | I85: 8545.5227 | T85: 07 | U85: Maricopa | V85: C | W85: C-078910000 | X85: Franklin Arts Academies | Y85: 89 | Z85: 749578 | AA85: 0 | AB85: 3964427 | AC85: 318770 | AD85: =SUM(Z85:AC85) -> 5032775 | AE85: 650.68 | AF85: 7734.6391
A86: 04 | B86: Gila | C86: C | D86: C-040210700 | E86: Payson Center for Success | F86: 02 | G86: 376272 | H86: 51.955 | I86: 7242.2673 | T86: 07 | U86: Maricopa | V86: C | W86: C-078611000 | X86: Friendly House | Y86: 86 | Z86: 40325 | AA86: 9689 | AB86: 1394359 | AC86: 338463 | AD86: =SUM(Z86:AC86) -> 1782836 | AE86: 219.89 | AF86: 8107.8539
A87: 04 | B87: Gila | C87: D | D87: D-040312000 | E87: Pine Strawberry | F87: E | G87: 2685156 | H87: 106.25 | I87: 25272.056 | T87: 07 | U87: Maricopa | V87: C | W87: C-078679000 | X87: GAR-Student Choice | Y87: 86 | Z87: 6179 | AA87: 0 | AB87: 871836 | AC87: 0 | AD87: =SUM(Z87:AC87) -> 878015 | AE87: 124.105 | AF87: 7074.7754
A88: 04 | B88: Gila | C88: D | D88: D-040220000 | E88: San Carlos | F88: U | G88: 18642669 | H88: 1155.635 | I88: 16131.97 | T88: 07 | U88: Maricopa | V88: C | W88: C-078774000 | X88: Gem Charter | Y88: 87 | Z88: 14417 | AA88: 0 | AB88: 440808 | AC88: 9596 | AD88: =SUM(Z88:AC88) -> 464821 | AE88: 62.705 | AF88: 7412.8219
A89: 04 | B89: Gila | C89: C | D89: C-048703000 | E89: Shelby | F89: 87 | G89: 673837 | H89: 86.53 | I89: 7787.3223 | T89: 07 | U89: Maricopa | V89: C | W89: C-078708000 | X89: Genesis Academy | Y89: 87 | Z89: 91471 | AA89: 0 | AB89: 853392 | AC89: 128570 | AD89: =SUM(Z89:AC89) -> 1073433 | AE89: 119.705 | AF89: 8967.3197
... A91: 04 | B91: Gila | C91: D | D91: D-040305000 | E91: Young | F91: E | G91: 1287288 | H91: 61.259 | I91: 21013.859 | T91: 07 | U91: Maricopa | V91: C | W91: C-078998000 | X91: Happy Valley | Y91: 89 | Z91: 366432 | AA91: 0 | AB91: 3859590 | AC91: 89847 | AD91: =SUM(Z91:AC91) -> 4315869 | AE91: 653.02 | AF91: 6609.0916
A92: 05 | B92: Graham | C92: C | D92: C-999999000 | E92: ~Subtotal-Charter Schools | F92: 99 | G92: 2072064 | H92: 278.305 | I92: 7445.2992 | T92: 07 | U92: Maricopa | V92: C | W92: C-078712000 | X92: Heritage Academy | Y92: 87 | Z92: 199169 | AA92: 0 | AB92: 2662558 | AC92: 0 | AD92: =SUM(Z92:AC92) -> 2861727 | AE92: 403.465 | AF92: 7092.8755
A93: 05 | B93: Graham | C93: D | D93: D-999999000 | E93: ~Subtotal-Districts | F93: 9 | G93: 50375843 | H93: 5744.063 | I93: 8770.0715 | T93: 07 | U93: Maricopa | V93: C | W93: C-078985000 | X93: Heritage Elementary | Y93: 89 | Z93: 176533 | AA93: 0 | AB93: 3759343 | AC93: 86874 | AD93: =SUM(Z93:AC93) -> 4022750 | AE93: 638.495 | AF93: 6300.3626
A94: 05 | B94: Graham | C94: D | D94: D-050316000 | E94: Bonita | F94: E | G94: 1504061 | H94: 96.925 | I94: 15517.782 | T94: 07 | U94: Maricopa | V94: C | W94: C-078752000 | X94: Horizon Community | Y94: 87 | Z94: 1853395 | AA94: 0 | AB94: 8538116 | AC94: 142695 | AD94: =SUM(Z94:AC94) -> 10534206 | AE94: 1409.18 | AF94: 7475.4155
A95: 05 | B95: Graham | C95: C | D95: C-058703000 | E95: Discovery Plus Academy | F95: 87 | G95: 777112 | H95: 85.765 | I95: 9060.9456 | T95: 07 | U95: Maricopa | V95: C | W95: C-078713000 | X95: Humanities & Sciences | Y95: 87 | Z95: 227 | AA95: 0 | AB95: 4763455 | AC95: 0 | AD95: =SUM(Z95:AC95) -> 4763682 | AE95: 797.29 | AF95: 5974.8423
A96: 05 | B96: Graham | C96: D | D96: D-050207000 | E96: Ft. Thomas | F96: U | G96: 9159165 | H96: 477.845 | I96: 19167.649 | T96: 07 | U96: Maricopa | V96: C | W96: C-078519000 | X96: Imagine Elementary-Camelback | Y96: 85 | Z96: 236501 | AA96: 0 | AB96: 875304 | AC96: 174711 | AD96: =SUM(Z96:AC96) -> 1286516 | AE96: 128.385 | AF96: 10020.766
A97: 05 | B97: Graham | C97: C | D97: C-058701000 | E97: Gila Ed Group | F97: 87 | G97: 689729 | H97: 104.655 | I97: 6590.5021 | T97: 07 | U97: Maricopa | V97: C | W97: C-078520000 | X97: Imagine Elementary-Desert West | Y97: 85 | Z97: 341235 | AA97: 0 | AB97: 2211908 | AC97: 341284 | AD97: =SUM(Z97:AC97) -> 2894427 | AE97: 307.095 | AF97: 9425.1844
A98: 05 | B98: Graham | C98: D | D98: D-050802000 | E98: Gila Institute for Tech | F98: T | G98: 1860226 | H98: 391.718 | I98: 4748.8908 | T98: 07 | U98: Maricopa | V98: C | W98: C-078523000 | X98: Imagine Elementary-Tempe | Y98: 85 | Z98: 124509 | AA98: 0 | AB98: 843631 | AC98: 169692 | AD98: =SUM(Z98:AC98) -> 1137832 | AE98: 120.79 | AF98: 9419.9189
A99: 05 | B99: Graham | C99: D | D99: D-050309000 | E99: Klondyke | F99: E | G99: 75110 | H99: 0 | I99: 0 | T99: 07 | U99: Maricopa | V99: C | W99: C-078521000 | X99: Imagine Middle-East Mesa | Y99: 85 | Z99: 2714 | AA99: 0 | AB99: 180153 | AC99: 11048 | AD99: =SUM(Z99:AC99) -> 193915 | AE99: 26.32 | AF99: 7367.5912
A100: 05 | B100: Graham | C100: D | D100: D-050206000 | E100: Pima | F100: U | G100: 5048741 | H100: 637.58 | I100: 7918.6 | T100: 07 | U100: Maricopa | V100: C | W100: C-078522000 | X100: Imagine Middle-Surprise | Y100: 85 | Z100: 11889 | AA100: 0 | AB100: 719990 | AC100: 115083 | AD100: =SUM(Z100:AC100) -> 846962 | AE100: 115.84 | AF100: 7311.4814
A101: 05 | B101: Graham | C101: D | D101: D-050201000 | E101: Safford | F101: U | G101: 21824408 | H101: 2769.4 | I101: 7880.5546 | T101: 07 | U101: Maricopa | V101: C | W101: C-078751000 | X101: Integrity Ed Corp | Y101: 87 | Z101: 71768 | AA101: 0 | AB101: 492706 | AC101: 112122 | AD101: =SUM(Z101:AC101) -> 676596 | AE101: 70.115 | AF101: 9649.8039
...

Sheet County Revenue Sources
A1: Traditional Public School District Revenue and Public Charter School Revenue By Source**
A2: Aggregated by County & State for Public School Districts & by Total State for Public Charter Schools
A3: 2006-2007 | T3: SAVE A COPY OF THIS FILE
A4: County | C4: Total | D4: Enroll- | F4: Federal | I4: State | L4: County/Intermediate* | O4: Local | T4: BEFORE YOU BEGIN TO SORT
A5: # | B5: Name | C5: Revenue | D5: ment | E5: $PP | F5: Amount | G5: % | H5: $PP | I5: Amount | J5: % | K5: $PP | L5: Amount | M5: % | N5: $PP | O5: Amount | P5: % | Q5: $PP
A6: A | B6: B | C6: C | D6: D | E6: E | F6: F | G6: G | H6: H | I6: I | J6: J | K6: K | L6: L | M6: M | N6: N | O6: O | P6: P | Q6: Q
A7: 0 | B7: ~Total-C | C7: 675226730 | D7: 88587 | E7: 7622.1876 | F7: 58677203 | G7: 0.0869 | H7: 662.3681 | I7: 5.6867595e+08 | J7: 0.8422 | K7: 6419.4064 | L7: 1215408.1 | M7: 0.0018 | N7: 13.719938 | O7: 46658167 | P7: 0.0691 | Q7: 526.69316 | S7: About Excel 2007 Tables
A8: 0 | B8: ~Total-D | C8: 8953120539 | D8: 935219 | E8: 9573.2877 | F8: 955251395 | G8: 0.1066948 | H8: 1021.42 | I8: 4365833746 | J8: 0.48763263 | K8: 4668.2475 | L8: 4074850 | M8: 0.00045513181 | N8: 4.3571078 | O8: 3627960548 | P8: 0.40521744 | Q8: 3879.2631 | T8: 1) Click the the arrow buttons in row 6 (purple) to sort.
A9: 01 | B9: Apache | C9: =F9+I9+L9+O9 -> 180814970 | D9: 12885 | E9: =$C9/D9 -> 14032.982 | F9: 77676166 | G9: =F9/$C9 -> 0.42958924 | H9: =F9/$D9 -> 6028.418 | I9: 78896695 | J9: =I9/$C9 -> 0.4363394 | K9: =I9/$D9 -> 6123.1428 | L9: 61698 | M9: =L9/$C9 -> 0.00034122175 | N9: =L9/$D9 -> 4.7883586 | O9: 24180411 | P9: =O9/$C9 -> 0.13373014 | Q9: =O9/$D9 -> 1876.6326 | T9: 2) Select a sort order to sort the list.
A10: 02 | B10: Cochise | C10: =F10+I10+L10+O10 -> 168974628 | D10: 18844 | E10: =$C10/D10 -> 8967.0255 | F10: 26240638 | G10: =F10/$C10 -> 0.15529336 | H10: =F10/$D10 -> 1392.5195 | I10: 95406241 | J10: =I10/$C10 -> 0.56461874 | K10: =I10/$D10 -> 5062.9506 | L10: 120996 | M10: =L10/$C10 -> 0.00071606016 | N10: =L10/$D10 -> 6.4209297 | O10: 47206753 | P10: =O10/$C10 -> 0.27937184 | Q10: =O10/$D10 -> 2505.1344 | T10: The last button used displays an up or down arrow.
A11: 03 | B11: Coconino | C11: =F11+I11+L11+O11 -> 187279341 | D11: 17937 | E11: =$C11/D11 -> 10440.951 | F11: 39779807 | G11: =F11/$C11 -> 0.21240894 | H11: =F11/$D11 -> 2217.7514 | I11: 71999887 | J11: =I11/$C11 -> 0.38445184 | K11: =I11/$D11 -> 4014.0429 | L11: 1121484 | M11: =L11/$C11 -> 0.0059882953 | N11: =L11/$D11 -> 62.523499 | O11: 74378163 | P11: =O11/$C11 -> 0.39715092 | Q11: =O11/$D11 -> 4146.6334 | T11: Always use buttons to sort (not Data | Sort).
A12: 04 | B12: Gila | C12: =F12+I12+L12+O12 -> 78430781 | D12: 7585 | E12: =$C12/D12 -> 10340.248 | F12: 16969152 | G12: =F12/$C12 -> 0.21635832 | H12: =F12/$D12 -> 2237.1987 | I12: 35924121 | J12: =I12/$C12 -> 0.458036 | K12: =I12/$D12 -> 4736.2058 | L12: 0 | M12: =L12/$C12 -> 0 | N12: =L12/$D12 -> 0 | O12: 25537508 | P12: =O12/$C12 -> 0.32560568 | Q12: =O12/$D12 -> 3366.8435 | T12: For lowest to highest revenue per pupil ($PP) by county:
A13: 05 | B13: Graham | C13: =F13+I13+L13+O13 -> 50375843 | D13: 5744 | E13: =$C13/D13 -> 8770.1677 | F13: 7804918 | G13: =F13/$C13 -> 0.15493374 | H13: =F13/$D13 -> 1358.7949 | I13: 33115297 | J13: =I13/$C13 -> 0.65736462 | K13: =I13/$D13 -> 5765.1979 | L13: 22392 | M13: =L13/$C13 -> 0.00044449877 | N13: =L13/$D13 -> 3.8983287 | O13: 9433236 | P13: =O13/$C13 -> 0.18725713 | Q13: =O13/$D13 -> 1642.2765 | T13: 1) Click the arrow button in cell E6.
A14: 06 | B14: Greenlee | C14: =F14+I14+L14+O14 -> 13872990 | D14: 1620 | E14: =$C14/D14 -> 8563.5741 | F14: 990720 | G14: =F14/$C14 -> 0.071413589 | H14: =F14/$D14 -> 611.55556 | I14: 4079074 | J14: =I14/$C14 -> 0.29402991 | K14: =I14/$D14 -> 2517.9469 | L14: 0 | M14: =L14/$C14 -> 0 | N14: =L14/$D14 -> 0 | O14: 8803196 | P14: =O14/$C14 -> 0.6345565 | Q14: =O14/$D14 -> 5434.0716 | T14: 2) Select "Sort Smallest to Largest"
A15: 15 | B15: La Paz | C15: =F15+I15+L15+O15 -> 27062698 | D15: 2514 | E15: =$C15/D15 -> 10764.796 | F15: 9104245 | G15: =F15/$C15 -> 0.33641306 | H15: =F15/$D15 -> 3621.4181 | I15: 11527455 | J15: =I15/$C15 -> 0.42595365 | K15: =I15/$D15 -> 4585.3043 | L15: 10287 | M15: =L15/$C15 -> 0.00038011731 | N15: =L15/$D15 -> 4.0918854 | O15: 6420711 | P15: =O15/$C15 -> 0.23725317 | Q15: =O15/$D15 -> 2553.9821 | T15: To return tor original sort order:
A16: 07 | B16: Maricopa | C16: =F16+I16+L16+O16 -> 5616885964 | D16: 587562 | E16: =$C16/D16 -> 9559.6481 | F16: 452851159 | G16: =F16/$C16 -> 0.080623171 | H16: =F16/$D16 -> 770.72915 | I16: 2615985743 | J16: =I16/$C16 -> 0.46573595 | K16: =I16/$D16 -> 4452.2718 | L16: 1465513 | M16: =L16/$C16 -> 0.00026091201 | N16: =L16/$D16 -> 2.494227 | O16: 2546583549 | P16: =O16/$C16 -> 0.45337996 | Q16: =O16/$D16 -> 4334.1529 | U16: Use button at B6 to sort A to Z.
A17: 08 | B17: Mohave | C17: =F17+I17+L17+O17 -> 179327654 | D17: 23158 | E17: =$C17/D17 -> 7743.659 | F17: 21858795 | G17: =F17/$C17 -> 0.12189305 | H17: =F17/$D17 -> 943.89822 | I17: 85494623 | J17: =I17/$C17 -> 0.47675091 | K17: =I17/$D17 -> 3691.7965 | L17: 488878 | M17: =L17/$C17 -> 0.0027261718 | N17: =L17/$D17 -> 21.110545 | O17: 71485358 | P17: =O17/$C17 -> 0.39862986 | Q17: =O17/$D17 -> 3086.8537
A18: 09 | B18: Navajo | C18: =F18+I18+L18+O18 -> 214837537 | D18: 20947 | E18: =$C18/D18 -> 10256.244 | F18: 62747791 | G18: =F18/$C18 -> 0.29207089 | H18: =F18/$D18 -> 2995.5502 | I18: 106962377 | J18: =I18/$C18 -> 0.49787564 | K18: =I18/$D18 -> 5106.3339 | L18: 162264 | M18: =L18/$C18 -> 0.00075528701 | N18: =L18/$D18 -> 7.7464076 | O18: 44965105 | P18: =O18/$C18 -> 0.20929818 | Q18: =O18/$D18 -> 2146.6131
A19: 10 | B19: Pima | C19: =F19+I19+L19+O19 -> 1205478547 | D19: 127936 | E19: =$C19/D19 -> 9422.5124 | F19: 124072911 | G19: =F19/$C19 -> 0.1029242 | H19: =F19/$D19 -> 969.80452 | I19: 619064850 | J19: =I19/$C19 -> 0.51354282 | K19: =I19/$D19 -> 4838.8636 | L19: 310694 | M19: =L19/$C19 -> 0.00025773499 | N19: =L19/$D19 -> 2.4285111 | O19: 462030092 | P19: =O19/$C19 -> 0.38327525 | Q19: =O19/$D19 -> 3611.4158
A20: 11 | B20: Pinal | C20: =F20+I20+L20+O20 -> 437783091 | D20: 40439 | E20: =$C20/D20 -> 10825.765 | F20: 36208180 | G20: =F20/$C20 -> 0.082708037 | H20: =F20/$D20 -> 895.37773 | I20: 270879276 | J20: =I20/$C20 -> 0.61875226 | K20: =I20/$D20 -> 6698.4662 | L20: 154352 | M20: =L20/$C20 -> 0.00035257643 | N20: =L20/$D20 -> 3.8169094 | O20: 130541283 | P20: =O20/$C20 -> 0.29818713 | Q20: =O20/$D20 -> 3228.1036
A21: 12 | B21: Santa Cruz | C21: =F21+I21+L21+O21 -> 89180580 | D21: 9976 | E21: =$C21/D21 -> 8939.5128 | F21: 12160176 | G21: =F21/$C21 -> 0.13635453 | H21: =F21/$D21 -> 1218.9431 | I21: 50186210 | J21: =I21/$C21 -> 0.56274819 | K21: =I21/$D21 -> 5030.6947 | L21: 40682 | M21: =L21/$C21 -> 0.00045617555 | N21: =L21/$D21 -> 4.0779872 | O21: 26793512 | P21: =O21/$C21 -> 0.30044111 | Q21: =O21/$D21 -> 2685.7971
A22: 13 | B22: Yavapai | C22: =F22+I22+L22+O22 -> 192793187 | D22: 23707 | E22: =$C22/D22 -> 8132.3317 | F22: 16917820 | G22: =F22/$C22 -> 0.08775113 | H22: =F22/$D22 -> 713.62129 | I22: 86553264 | J22: =I22/$C22 -> 0.44894358 | K22: =I22/$D22 -> 3650.9581 | L22: 19126 | M22: =L22/$C22 -> 9.920475e-05 | N22: =L22/$D22 -> 0.80676593 | O22: 89302977 | P22: =O22/$C22 -> 0.46320608 | Q22: =O22/$D22 -> 3766.9455
A23: 14 | B23: Yuma | C23: =F23+I23+L23+O23 -> 310022728 | D23: 34365 | E23: =$C23/D23 -> 9021.4674 | F23: 49868917 | G23: =F23/$C23 -> 0.16085568 | H23: =F23/$D23 -> 1451.1543 | I23: 199758633 | J23: =I23/$C23 -> 0.64433545 | K23: =I23/$D23 -> 5812.8512 | L23: 96484 | M23: =L23/$C23 -> 0.00031121589 | N23: =L23/$D23 -> 2.807624 | O23: 60298694 | P23: =O23/$C23 -> 0.19449766 | Q23: =O23/$D23 -> 1754.6543
A24: * For traditional school districts these amounts represent "County" revenues (with zero Intermediate revenue dollars); for public charter schools these amounts represent "Intermediate" revenues (with zero County revenue dollars).
A25: $PP = Dollars Per Pupil | S25: Highlighting Legend:
A26: DATA SOURCE: Annual Report of the Arizona Superintendent of Public Instruction; Volume II, Fiscal Year 2006-2007. | T26: Purple = Drop-down arrow buttons.
A27: DATA PRESENTATION: By EduAnalytics, LLC; November, 2008. | T27: Yellow = Total for 337 state-sponsored public
A28: ~Total-C = The total of 337 state-sponsored public charter schools (Yellow Highlight). | U28: charter schools.
A29: ~Total-D = The total of all public school districts (Green Highlight). | T29: Green = Total for all public school districts.
A30: ** Includes 337 state-sponsored public charter schools.

Sheet County Valuations & Other
A1: Revenues, Special Program Expenditures, & Tax Metrics by Public School Districts & Public Charter Schools**
A2: Aggregated by County & State for Public School Districts & by Total State for Public Charter Schools
A3: 2006-2007 | S3: SAVE A COPY OF THIS FILE
A4: County | C4: Total | D4: Enroll- | F4: Special Prog. Expenditures | I4: F&RL | J4: Primary Tax | M4: Secondary Tax | S4: BEFORE YOU BEGIN TO SORT
A5: # | B5: Name | C5: Revenue | D5: ment | E5: $PP | F5: Amount | G5: % Rev | H5: $PP | I5: %* | J5: Rates | K5: Valuation | L5: v$PP | M5: Rates | N5: Valuation | O5: v$PP | P5: SRP
A6: A | B6: B | C6: C | D6: D | E6: E | F6: F | G6: G | H6: H | I6: I | J6: J | K6: K | L6: L | M6: M | N6: N | O6: O | P6: P
A7: 0 | B7: ~Total-C | C7: 675226730 | D7: 88587 | E7: 7622.1876 | F7: 21322550 | G7: =F7/$C7 -> 0.031578356 | H7: =F7/$D7 -> 240.69615 | I7: 0.71 | J7: N/A | K7: N/A | L7: N/A | M7: N/A | N7: N/A | O7: N/A | P7: N/A | R7: About Excel 2007 Tables
A8: 0 | B8: ~Total-D | C8: 8953120539 | D8: 935219 | E8: 9573.2877 | F8: 830546708 | G8: 0.092766171 | H8: 888.07724 | I8: 0.51 | J8: 3.3472 | K8: 97703636366 | L8: =K8/D8 -> 104471.4 | M8: 1.0029 | N8: 68138541654 | O8: =N8/D8 -> 72858.38 | P8: 1577237503 | S8: 1) Click the the arrow buttons in row 6 (purple) to sort.
A9: 01 | B9: Apache | C9: 180814970 | D9: 12885 | E9: =$C9/D9 -> 14032.982 | F9: 12222014 | G9: =F9/$C9 -> 0.067594038 | H9: =F9/$D9 -> 948.54591 | I9: 0.76 | J9: 1.7785 | K9: 316510258 | L9: =K9/D9 -> 24564.242 | M9: 0.324 | N9: 323062906 | O9: =N9/D9 -> 25072.791 | P9: 96920585 | S9: 2) Select a sort order to sort the list.
A10: 02 | B10: Cochise | C10: 168974628 | D10: 18844 | E10: =$C10/D10 -> 8967.0255 | F10: 15983209 | G10: =F10/$C10 -> 0.094589402 | H10: =F10/$D10 -> 848.18558 | I10: 0.53 | J10: 4.3933 | K10: 1058250292 | L10: =K10/D10 -> 56158.474 | M10: 0.5179 | N10: 481706105 | O10: =N10/D10 -> 25562.837 | P10: 0 | S10: The last button used displays an up or down arrow.
A11: 03 | B11: Coconino | C11: 187279341 | D11: 17937 | E11: =$C11/D11 -> 10440.951 | F11: 16121806 | G11: =F11/$C11 -> 0.086084273 | H11: =F11/$D11 -> 898.80169 | I11: 0.52 | J11: 2.1987 | K11: 2487006890 | L11: =K11/D11 -> 138652.33 | M11: 1.3394 | N11: 1313169139 | O11: =N11/D11 -> 73210.076 | P11: 64250389 | S11: Always use buttons to sort (not Data | Sort).
A12: 04 | B12: Gila | C12: 78430781 | D12: 7585 | E12: =$C12/D12 -> 10340.248 | F12: 5668384 | G12: =F12/$C12 -> 0.072272441 | H12: =F12/$D12 -> 747.31496 | I12: 0.59 | J12: 4.0733 | K12: 412254721 | L12: =K12/D12 -> 54351.315 | M12: 0.5917 | N12: 422267703 | O12: =N12/D12 -> 55671.418 | P12: 4552243 | S12: For lowest to highest revenue per pupil ($PP) by county:
A13: 05 | B13: Graham | C13: 50375843 | D13: 5744 | E13: =$C13/D13 -> 8770.1677 | F13: 3835905 | G13: =F13/$C13 -> 0.076145723 | H13: =F13/$D13 -> 667.81076 | I13: 0.54 | J13: 2.8143 | K13: 231877607 | L13: =K13/D13 -> 40368.664 | M13: 0.5419 | N13: 119712036 | O13: =N13/D13 -> 20841.232 | P13: 0 | S13: 1) Click the arrow button in cell E6.
A14: 06 | B14: Greenlee | C14: 13872990 | D14: 1620 | E14: =$C14/D14 -> 8563.5741 | F14: 663995 | G14: =F14/$C14 -> 0.047862429 | H14: =F14/$D14 -> 409.87346 | I14: 0.32 | J14: 2.9344 | K14: 226709610 | L14: =K14/D14 -> 139944.2 | M14: 1.0906 | N14: 226907616 | O14: =N14/D14 -> 140066.43 | P14: 0 | S14: 2) Select "Sort Smallest to Largest"
A15: 15 | B15: La Paz | C15: 27062698 | D15: 2514 | E15: =$C15/D15 -> 10764.796 | F15: 2032601 | G15: =F15/$C15 -> 0.075107109 | H15: =F15/$D15 -> 808.51273 | I15: 0.73 | J15: 3.4066 | K15: 242972908 | L15: =K15/D15 -> 96647.935 | M15: 0.3623 | N15: 262162688 | O15: =N15/D15 -> 104281.1 | P15: 22844 | S15: To return tor original sort order:
A16: 07 | B16: Maricopa | C16: 5616885964 | D16: 587562 | E16: =$C16/D16 -> 9559.6481 | F16: 551193121 | G16: =F16/$C16 -> 0.098131442 | H16: =F16/$D16 -> 938.10206 | I16: 0.47 | J16: 3.4581 | K16: 73908685462 | L16: =K16/D16 -> 125788.74 | M16: 1.5597 | N16: 48596875163 | O16: =N16/D16 -> 82709.357 | P16: 1179789391 | T16: Use button at B6 to sort A to Z.
A17: 08 | B17: Mohave | C17: 179327654 | D17: 23158 | E17: =$C17/D17 -> 7743.659 | F17: 13405112 | G17: =F17/$C17 -> 0.074752063 | H17: =F17/$D17 -> 578.85448 | I17: 0.54 | J17: 3.3332 | K17: 2070249481 | L17: =K17/D17 -> 89396.73 | M17: 0.737 | N17: 2427944665 | O17: =N17/D17 -> 104842.59 | P17: 934488
A18: 09 | B18: Navajo | C18: 214837537 | D18: 20947 | E18: =$C18/D18 -> 10256.244 | F18: 20970400 | G18: =F18/$C18 -> 0.097610503 | H18: =F18/$D18 -> 1001.1171 | I18: 0.64 | J18: 1.7753 | K18: 2017524373 | L18: =K18/D18 -> 96315.672 | M18: 1.3906 | N18: 753947031 | O18: =N18/D18 -> 35993.079 | P18: 99333204
A19: 10 | B19: Pima | C19: 1205478547 | D19: 127936 | E19: =$C19/D19 -> 9422.5124 | F19: 110854999 | G19: =F19/$C19 -> 0.09195933 | H19: =F19/$D19 -> 866.48792 | I19: 0.54 | J19: 4.096 | K19: 6457831337 | L19: =K19/D19 -> 50477.046 | M19: 1.2892 | N19: 6858304185 | O19: =N19/D19 -> 53607.305 | P19: 0
A20: 11 | B20: Pinal | C20: 437783091 | D20: 40439 | E20: =$C20/D20 -> 10825.765 | F20: 32725880 | G20: =F20/$C20 -> 0.074753641 | H20: =F20/$D20 -> 809.26531 | I20: 0.51 | J20: 3.2501 | K20: 2879274131 | L20: =K20/D20 -> 71200.429 | M20: 1.3179 | N20: 2016929870 | O20: =N20/D20 -> 49875.859 | P20: 130324799
A21: 12 | B21: Santa Cruz | C21: 89180580 | D21: 9976 | E21: =$C21/D21 -> 8939.5128 | F21: 6734141 | G21: =F21/$C21 -> 0.075511294 | H21: =F21/$D21 -> 675.03418 | I21: 0.73 | J21: 4.4039 | K21: 313107669 | L21: =K21/D21 -> 31386.094 | M21: 0.6747 | N21: 330896085 | O21: =N21/D21 -> 33169.215 | P21: 0 | R21: Highlighting Legend:
A22: 13 | B22: Yavapai | C22: 192793187 | D22: 23707 | E22: =$C22/D22 -> 8132.3317 | F22: 17427946 | G22: =F22/$C22 -> 0.090397105 | H22: =F22/$D22 -> 735.13924 | I22: 0.47 | J22: 3.5565 | K22: 3438516696 | L22: =K22/D22 -> 145042.25 | M22: 0.3018 | N22: 2169966384 | O22: =N22/D22 -> 91532.728 | P22: 1109560 | S22: Purple = Drop-down arrow buttons.
A23: 14 | B23: Yuma | C23: 310022728 | D23: 34365 | E23: =$C23/D23 -> 9021.4674 | F23: 20707195 | G23: =F23/$C23 -> 0.066792506 | H23: =F23/$D23 -> 602.56642 | I23: 0.72 | J23: 2.8466 | K23: 1642864931 | L23: =K23/D23 -> 47806.342 | M23: 1.0706 | N23: 1834663078 | O23: =N23/D23 -> 53387.548 | P23: 0 | S23: Yellow = Total for 337 state-sponsored public
A24: * Percentage of Free & Reduced Price Lunch Eligibility at March 2007 for public school districts; as of 2008 for public charter schools. | T24: charter schools.
A25: $PP = dollars per pupil. | S25: Green = Total for all public school districts.
A26: v$PP = Valuation on a per pupil basis.
A27: DATA SOURCE: Annual Report of the Arizona Superintendent of Public Instruction; Volume II, Fiscal Year 2006-2007.
A28: DATA PRESENTATION: By EduAnalytics, LLC; November, 2008.
A29: ~Total-C = The total of 337 state-sponsored public charter schools (Yellow Highlight).
A30: ~Total-D = The total of all public school districts (Green Highlight).
A31: ** Includes 337 state-sponsored public charter schools.
