Workbook

Sheet GF Recon
B2: DSA | C2: FY 2010 | D2: FY 2011
B3: Adult Ed | C3: 2400000 | D3: 3600000
B4: IDEA MOE | C4: =7607573+1968 -> 7609541 | D4: =6526678+1968 -> 6528646
B5: Early Childhood Education | C5: -26109 | D5: -58191
B6: RPDP | C6: 7897804 | D6: =+C6 -> 7897804
C8: =SUM(C3:C7) -> 17881236 | D8: =SUM(D3:D7) -> 17968259
C18: GOV | D18: LEG | F18: GOV | G18: LEG | I18: BIENNIAL
C19: FY 2010 | D19: FY2010 | E19: DIFF | F19: FY 2011 | G19: FY 2011 | H19: DIFF | I19: TOTAL
B20: SLOT TAX | C20: 36173569 | D20: 35888197 | E20: =D20-C20 -> -285372.33 | F20: 36571479 | G20: 36554830 | H20: =G20-F20 -> -16648.589 | I20: =E20+H20 -> -302020.92
B21: PERM SCHOOL FUND | C21: 14631920 | D21: 13100000 | E21: =D21-C21 -> -1531920 | F21: 14924558 | G21: 13100000 | H21: =G21-F21 -> -1824558 | I21: =E21+H21 -> -3356478
B22: FEDERAL LEASE REVENUE | C22: 9198446 | D22: 10706000 | E22: =D22-C22 -> 1507554 | F22: 9474399 | G22: 10706000 | H22: =G22-F22 -> 1231601 | I22: =E22+H22 -> 2739155
B23: REAL PROPERTY TRANS TAX AB 458 | D23: 1000000 | E23: =D23-C23 -> 1000000 | F23: 0 | G23: 1000000 | H23: =G23-F23 -> 1000000 | I23: =E23+H23 -> 2000000
C25: =SUM(C20:C24) -> 60003935 | D25: =SUM(D20:D24) -> 60694197 | E25: =SUM(E20:E24) -> 690261.67 | F25: =SUM(F20:F24) -> 60970436 | G25: =SUM(G20:G24) -> 61360830 | H25: =SUM(H20:H24) -> 390394.41 | I25: =SUM(I20:I24) -> 1080656.1

Sheet DSA
A1: State of Nevada
A2: Distributive School Account
A3: Fiscal Years 2010 Through 2013
H4: Legislature Approved Plus
B5: Legislature Approved | F5: Actual | H5: 26th Special Session Adjustments | L5: Governor Recommends | P5: Biennium | R5: Biennium
B6: FY 2008 | D6: FY 2009 | F6: FY 2009 | H6: FY 2010 | J6: FY 2011 | L6: FY 2012 | N6: FY 2013 | P6: Total | R6: Change
A7: Revenues and Appropriations
A8: General Fund Appropriations | B8: 1041362589 | D8: 1090795262 | F8: 1137402312 | H8: =1173542690+69080821-18917900-42371-33893 -> 1223629347 | J8: =1154625174-69080821+33893+139533874 -> 1225112120 | L8: =DSASUMM!AI130 -> 1.0882807e+09 | N8: =DSASUMM!AK130 -> 1.1113311e+09 | P8: =SUM(L8:N8) -> 2.1996118e+09 | R8: =P8-SUM(H8:J8) -> -2.4912964e+08
A10: Federal Education Stabilization Fund | B10: 0 | D10: 0 | F10: 139626106 | H10: 0 | J10: 0 | L10: 0 | N10: 0 | P10: =SUM(L10:N10) -> 0 | R10: =P10-SUM(H10:J10) -> 0
A12: State Guaranteed Revenues
A13: Local School Support Tax | B13: 1021135885 | D13: 1108717188 | H13: 872948748 | J13: 888433910 | L13: =-DSASUMM!AI121 -> 9.4173479e+08 | N13: =-DSASUMM!AK121 -> 9.6998665e+08 | P13: =SUM(L13:N13) -> 1.9117214e+09 | R13: =P13-SUM(H13:J13) -> 1.5033878e+08
A14: Local School Support Tax Rate Sunset | H14: 0 | J14: 0 | P14: =SUM(L14:N14) -> 0 | R14: =P14-SUM(H14:J14) -> 0
A15: Public School Operating Property Tax (1/3) | B15: 258661179 | D15: 290268708 | H15: 262851182 | J15: 212922114 | L15: =-DSASUMM!AI122 -> 202433266 | N15: =-DSASUMM!AK122 -> 202931773 | P15: =SUM(L15:N15) -> 405365039 | R15: =P15-SUM(H15:J15) -> -70408257
A16: School District Debt Service Excess Reserves | H16: 0 | J16: 0 | L16: =-DSASUMM!AI123 -> 0 | N16: =-DSASUMM!AK123 -> 0 | P16: =SUM(L16:N16) -> 0 | R16: =P16-SUM(H16:J16) -> 0
A17: Clark County School District Capital Construction Funds | B17: 0 | D17: 0 | H17: 10000000 | J17: 10000000 | L17: =-DSASUMM!AI124 -> 20000000 | N17: =-DSASUMM!AK124 -> 20000000 | P17: =SUM(L17:N17) -> 40000000 | R17: =P17-SUM(H17:J17) -> 20000000
A18: Transfer from closure of CC RDA | B18: 0 | D18: 0 | H18: 6000000 | J18: 5400000 | L18: 0 | N18: 0 | P18: =SUM(L18:N18) -> 0 | R18: =P18-SUM(H18:J18) -> -11400000
A19: 26th Special Session - CCSD Capital Construction Funds | H19: 0 | J19: 25000000 | L19: 0 | N19: 0 | P19: =SUM(L19:N19) -> 0 | R19: =P19-SUM(H19:J19) -> -25000000
A21: Total State Guaranteed Revenues | B21: =SUM(B13:B20) -> 1279797064 | D21: =SUM(D13:D20) -> 1398985896 | F21: =SUM(F13:F20) -> 0 | H21: =SUM(H13:H20) -> 1151799930 | J21: =SUM(J13:J20) -> 1141756024 | L21: =SUM(L13:L20) -> 1.1641681e+09 | N21: =SUM(N13:N20) -> 1.1929184e+09 | P21: =SUM(P13:P20) -> 2.3570865e+09 | R21: =SUM(R13:R20) -> 63530526
A23: Dedicated State Revenues
A24: DSA Share of Slot Tax | B24: 37682635 | D24: 40294194 | F24: 34617391 | H24: 33712074 | J24: 33359606 | L24: =DSASUMM!AI133 -> 33542238 | N24: =DSASUMM!AK133 -> 34144068 | P24: =SUM(L24:N24) -> 67686306 | R24: =P24-SUM(H24:J24) -> 614626
A25: Permanent School Fund | B25: 11800136 | D25: 12315982 | F25: 13118714 | H25: 9173420 | J25: 8000000 | L25: =DSASUMM!AI134 -> 6600000 | N25: =DSASUMM!AK134 -> 6800000 | P25: =SUM(L25:N25) -> 13400000 | R25: =P25-SUM(H25:J25) -> -3773420
A26: Federal Mineral Lease Revenue | B26: 6354164 | D26: 6354164 | F26: 21609333 | H26: 8116846 | J26: 8000000 | L26: =DSASUMM!G135 -> 8000000 | N26: =DSASUMM!H135 -> 8000000 | P26: =SUM(L26:N26) -> 16000000 | R26: =P26-SUM(H26:J26) -> -116846
A27: Out of State Local School Support Tax | B27: 116384350 | D27: 123716564 | F27: 93575531 | H27: 86190829 | J27: 87867090 | L27: =DSASUMM!AI136 -> 93138606 | N27: =DSASUMM!AK136 -> 95932745 | P27: =SUM(L27:N27) -> 1.8907135e+08 | R27: =P27-SUM(H27:J27) -> 15013432
A28: Out of State Local School Support Tax Sunset | H28: 0 | J28: 0 | P28: =SUM(L28:N28) -> 0 | R28: =P28-SUM(H28:J28) -> 0
A29: Estate Tax | B29: 100 | D29: 100 | F29: 16.32 | H29: 0 | J29: 0 | P29: =SUM(L29:N29) -> 0 | R29: =P29-SUM(H29:J29) -> 0
A30: Prior Year Refunds | B30: 0 | D30: 0 | F30: 35787.86 | H30: 816539 | J30: 0 | L30: 0 | N30: 0 | P30: =SUM(L30:N30) -> 0 | R30: =P30-SUM(H30:J30) -> -816539
A31: Real Property Tax - Sec. 36 of AB 458 | B31: 0 | D31: 0 | F31: 0 | H31: 0 | J31: 0 | L31: 0 | N31: 0 | P31: =SUM(L31:N31) -> 0 | R31: =P31-SUM(H31:J31) -> 0
A32: Other | H32: 0 | P32: =SUM(L32:N32) -> 0 | R32: =P32-SUM(H32:J32) -> 0
A34: Total Dedicated State Revenues | B34: =SUM(B24:B33) -> 172221385 | D34: =SUM(D24:D33) -> 182681004 | F34: =SUM(F24:F33) -> 1.6295677e+08 | H34: =SUM(H24:H33) -> 138009708 | J34: =SUM(J24:J33) -> 137226696 | L34: =SUM(L24:L33) -> 1.4128084e+08 | N34: =SUM(N24:N33) -> 1.4487681e+08 | P34: =SUM(P24:P33) -> 2.8615766e+08 | R34: =SUM(R24:R33) -> 10921253
A36: Local Revenues
A37: Federal Revenue | B37: 5837244 | D37: 5837244 | H37: 8499450 | J37: 7863361 | L37: =-DSASUMM!AI73 -> 8499450 | N37: =-DSASUMM!AK73 -> 8499450 | P37: =SUM(L37:N37) -> 16998900 | R37: =P37-SUM(H37:J37) -> 636089
A38: Other Local Revenue | B38: 52643811 | D38: 52643811 | H38: 80820145 | J38: 94520861 | L38: =-DSASUMM!AI74 -> 80820145 | N38: =-DSASUMM!AK74 -> 80820145 | P38: =SUM(L38:N38) -> 161640290 | R38: =P38-SUM(H38:J38) -> -13700716
A39: Public School Operating Property Tax (2/3) | B39: 517322359 | D39: 580537415 | H39: 525702505 | J39: 425844229 | L39: =-DSASUMM!AI75 -> 404866532 | N39: =-DSASUMM!AK75 -> 405863545 | P39: =SUM(L39:N39) -> 810730077 | R39: =P39-SUM(H39:J39) -> -140816657
A40: Government Services Tax | B40: 98664516 | D40: 102591364 | H40: 75725120 | J40: 81402633 | L40: =-DSASUMM!AI76 -> 72381781 | N40: =-DSASUMM!AK76 -> 72381781 | P40: =SUM(L40:N40) -> 144763562 | R40: =P40-SUM(H40:J40) -> -12364191
A41: Franchise Tax | B41: 2940945 | D41: 3029173 | H41: 3451000 | J41: 4236760 | L41: =-DSASUMM!AI77 -> 3661166 | N41: =-DSASUMM!AK77 -> 3771001 | P41: =SUM(L41:N41) -> 7432167 | R41: =P41-SUM(H41:J41) -> -255593
A42: Obligations | B42: 2748725 | D42: 2748725 | H42: 710310 | J42: 49497203 | L42: 0 | N42: 0 | P42: =SUM(L42:N42) -> 0 | R42: =P42-SUM(H42:J42) -> -50207513
A43: Other State Support | B43: 210381 | D43: 210381 | H43: =76582+931314 -> 1007896 | J43: 879943 | L43: =-DSASUMM!AI85 -> 931314 | N43: =-DSASUMM!AK85 -> 931314 | P43: =SUM(L43:N43) -> 1862628 | R43: =P43-SUM(H43:J43) -> -25211
A44: School District Fund Balance | B44: 0 | D44: 0 | H44: 26897029 | J44: 92308915 | L44: 0 | N44: 0 | P44: =SUM(L44:N44) -> 0 | R44: =P44-SUM(H44:J44) -> -119205944
A46: Total Local Revenues | B46: =SUM(B37:B45) -> 680367981 | D46: =SUM(D37:D45) -> 747598113 | F46: =SUM(F37:F45) -> 0 | H46: =SUM(H37:H45) -> 722813455 | J46: =SUM(J37:J45) -> 756553905 | L46: =SUM(L37:L45) -> 571160388 | N46: =SUM(N37:N45) -> 572267236 | P46: =SUM(P37:P45) -> 1143427624 | R46: =SUM(R37:R45) -> -335939736
A48: Total Revenues and Appropriations | B48: =B8+B10+B21+B34+B46 -> 3173749019 | D48: =D8+D10+D21+D34+D46 -> 3420060275 | F48: =F8+F10+F21+F34+F46 -> 1.4399852e+09 | H48: =H8+H10+H21+H34+H46 -> 3236252440 | J48: =J8+J10+J21+J34+J46 -> 3260648745 | L48: =L8+L10+L21+L34+L46 -> 2.96489e+09 | N48: =N8+N10+N21+N34+N46 -> 3.0213936e+09 | P48: =P8+P10+P21+P34+P46 -> 5.9862836e+09 | R48: =R8+R10+R21+R34+R46 -> -5.106176e+08
A49: % Change | D49: =(D48-B48)/B48 -> 0.077608927 | F49: =(F48-D48)/D48 -> -0.57895912 | H49: =(H48-D48)/D48 -> -0.053744034 | J49: =(J48-H48)/H48 -> 0.0075384431 | L49: =(L48-J48)/J48 -> -0.090705485 | N49: =(N48-L48)/L48 -> 0.019057554
A50: Expenditures
A51: Operating Expenditures
A52: Salaries and Fringe Benefits | B52: 2406712387 | D52: 2616698949 | H52: 2620269079 | J52: 2635962977 | L52: =DSASUMM!AI21 -> 2.5483815e+09 | N52: =DSASUMM!AK21 -> 2.6000854e+09 | P52: =SUM(L52:N52) -> 5.1484669e+09 | R52: =P52-SUM(H52:J52) -> -1.077652e+08
A53: Operating | B53: 353574041 | D53: 365329939 | H53: =368286245+27626901 -> 395913146 | J53: =379567265+87426570 -> 466993835 | L53: =DSASUMM!AI47 -> 316648166 | N53: =DSASUMM!AK47 -> 321365950 | P53: =SUM(L53:N53) -> 638014116 | R53: =P53-SUM(H53:J53) -> -224892865
A54: Equipment | B54: 58080903 | D54: 59602878 | H54: 20675812 | J54: 17884361 | L54: =DSASUMM!AI57 -> 20524848 | N54: =DSASUMM!AK57 -> 20589344 | P54: =SUM(L54:N54) -> 41114192 | R54: =P54-SUM(H54:J54) -> 2554019
A55: Transfer to State Special Education | B55: 18775970 | D55: 18775970 | H55: 19328159 | J55: 15518220 | L55: =DSASUMM!AI60 -> 19328159 | N55: =DSASUMM!AK60 -> 19328159 | P55: =SUM(L55:N55) -> 38656318 | R55: =P55-SUM(H55:J55) -> 3809939
A56: Other Obligations | B56: 133642087 | D56: 133642087 | L56: 0 | N56: 0 | P56: =SUM(L56:N56) -> 0 | R56: =P56-SUM(H56:J56) -> 0
A57: Other Adjustments | B57: 0 | D57: 0 | H57: 29896678 | J57: 30662744 | L57: =DSASUMM!AI62+DSASUMM!AI63+DSASUMM!AI90 -> 9068729 | N57: =DSASUMM!AK62+DSASUMM!AK63+DSASUMM!AK90 -> 8666856 | P57: =SUM(L57:N57) -> 17735585 | R57: =P57-SUM(H57:J57) -> -42823837
A58: Agency Request 10% Reduction | H58: 0 | J58: 0 | P58: =SUM(L58:N58) -> 0 | R58: =P58-SUM(H58:J58) -> 0
A59: 26th Special Session Reductions | H59: -27626901 | J59: -87426570 | P59: =SUM(L59:N59) -> 0 | R59: =P59-SUM(H59:J59) -> 115053471
A61: Total Operating Expenditures (Note 1 & 2) | B61: =SUM(B52:B60) -> 2970785388 | D61: =SUM(D52:D60) -> 3194049823 | F61: =SUM(F52:F60) -> 0 | H61: =SUM(H52:H60) -> 3058455973 | J61: =SUM(J52:J60) -> 3079595567 | L61: =SUM(L52:L60) -> 2.9139514e+09 | N61: =SUM(N52:N60) -> 2.9700357e+09 | P61: =SUM(P52:P60) -> 5.8839871e+09 | R61: =SUM(R52:R60) -> -2.5406447e+08
A62: % Change | D62: =(D61-B61)/B61 -> 0.075153337 | F62: =(F61-D61)/D61 -> -1 | H62: =(H61-D61)/D61 -> -0.042452015 | J62: =(J61-H61)/H61 -> 0.0069118517 | L62: =(L61-J61)/J61 -> -0.053787642 | N62: =(N61-L61)/L61 -> 0.01924682
A64: Categorical Expenditures
A65: Class Size Reduction | B65: 141209596 | D65: 153710996 | F65: 152111146 | H65: 142682930 | J65: 144348993 | L65: 0 | N65: 0 | P65: =SUM(L65:N65) -> 0 | R65: =P65-SUM(H65:J65) -> -287031923
A66: Adult Education | B66: =21457122-9167 -> 21447955 | D66: =23372144-9148 -> 23362996 | F66: 22385170 | H66: 21170456 | J66: 22673833 | L66: =DSASUMM!AI104 -> 17011957 | N66: =DSASUMM!AK104 -> 17758916 | P66: =SUM(L66:N66) -> 34770873 | R66: =P66-SUM(H66:J66) -> -9073416.4
A67: Special Units / Gifted and Talented | B67: 171898 | D67: 163656 | F67: 163645.21 | H67: 162566 | J67: 167459 | L67: 0 | N67: 0 | P67: =SUM(L67:N67) -> 0 | R67: =P67-SUM(H67:J67) -> -330025
A68: Regional Professional Development | B68: 13089934 | D68: 13513162 | F68: 11854119 | H68: 7897804 | J68: 7897804 | L68: 0 | N68: 0 | P68: =SUM(L68:N68) -> 0 | R68: =P68-SUM(H68:J68) -> -15795608
A69: Early Childhood Education | B69: 3251671 | D69: 3338875 | F69: 3313939 | H69: 3304982 | J69: 3338875 | L69: 0 | N69: 0 | P69: =SUM(L69:N69) -> 0 | R69: =P69-SUM(H69:J69) -> -6643857
A70: Special Transportation | B70: 12670517 | D70: 20312278 | F70: 0 | H70: 128541 | J70: 170908 | L70: 0 | N70: 0 | P70: =SUM(L70:N70) -> 0 | R70: =P70-SUM(H70:J70) -> -299449
A71: High Impact Position Stipends | B71: 10272060 | D71: 10758489 | F71: 0 | H71: 0 | J71: 0 | L71: 0 | N71: 0 | P71: =SUM(L71:N71) -> 0 | R71: =P71-SUM(H71:J71) -> 0
A72: Special Elementary Counseling | B72: 850000 | D72: 850000 | F72: 838187 | H72: 850000 | J72: 850000 | L72: 0 | N72: 0 | P72: =SUM(L72:N72) -> 0 | R72: =P72-SUM(H72:J72) -> -1700000
A73: Class Size Reduction - At Risk Kindergarten Teachers | B73: 0 | D73: 0 | F73: 1599850 | H73: 1580390 | J73: 1586508 | L73: 0 | N73: 0 | P73: =SUM(L73:N73) -> 0 | R73: =P73-SUM(H73:J73) -> -3166898
A74: Library Media Specialist | B74: 0 | D74: 0 | F74: 18798 | H74: 18798 | J74: 18798 | L74: 0 | N74: 0 | P74: =SUM(L74:N74) -> 0 | R74: =P74-SUM(H74:J74) -> -37596
A76: Total Categorical Expenditures | B76: =SUM(B65:B75) -> 202963631 | D76: =SUM(D65:D75) -> 226010452 | F76: =SUM(F65:F75) -> 1.9228485e+08 | H76: =SUM(H65:H75) -> 177796467 | J76: =SUM(J65:J75) -> 181053178 | L76: =SUM(L65:L75) -> 17011957 | N76: =SUM(N65:N75) -> 17758916 | P76: =SUM(P65:P75) -> 34770873 | R76: =SUM(R65:R75) -> -3.2407877e+08
A77: % Change | D77: =(D76-B76)/B76 -> 0.11355148 | F77: =(F76-D76)/D76 -> -0.14922141 | H77: =(H76-D76)/D76 -> -0.21332635 | J77: =(J76-H76)/H76 -> 0.018317074 | L77: =(L76-J76)/J76 -> -0.90603889 | N77: =(N76-L76)/L76 -> 0.043907855
A79: Total Expenditures | B79: =B61+B76 -> 3173749019 | D79: =D61+D76 -> 3420060275 | F79: =F61+F76 -> 1.9228485e+08 | H79: =H61+H76 -> 3236252440 | J79: =J61+J76 -> 3260648745 | L79: =L61+L76 -> 2.9309633e+09 | N79: =N61+N76 -> 2.9877946e+09 | P79: =P61+P76 -> 5.9187579e+09 | R79: =R61+R76 -> -5.7814325e+08
A80: % Change | D80: =(D79-B79)/B79 -> 0.077608927 | F80: =(F79-D79)/D79 -> -0.94377735 | H80: =(H79-D79)/D79 -> -0.053744034 | J80: =(J79-H79)/H79 -> 0.0075384431 | L80: =(L79-J79)/J79 -> -0.10111037 | N80: =(N79-L79)/L79 -> 0.019389958
A82: Total Revenue and Appropriations Less Total Expenditures | B82: =B48-B79 -> 0 | D82: =D48-D79 -> 0 | F82: =F48-F79 -> 1.2477003e+09 | H82: =H48-H79 -> 0 | J82: =J48-J79 -> 0 | L82: =L48-L79 -> 33926676 | N82: =N48-N79 -> 33598973 | P82: =P48-P79 -> 67525649 | R82: =R48-R79 -> 67525649
A84: Note 1 - Total Operating Expenditures Include the following:
A85: Special Education | B85: 111303886 | D85: 121250664 | H85: 121252632 | J85: 121252632 | L85: 121252632 | N85: 121252632
A86: Special Transportation | B86: 112012 | D86: 112012 | F86: 121294.31 | H86: 128541 | J86: 170908 | L86: 0 | N86: 0
A87: School Lunch Program Match | B87: 588732 | D87: 588732 | F87: 588732 | H87: 588732 | J87: 588732 | L87: 588732 | N87: 588732
A89: Note 2 - Calculation of Basic Support:
A90: Total Operating Expenditures | B90: =B61 -> 2970785388 | D90: =D61 -> 3194049823 | F90: =F61 -> 0 | H90: =H61 -> 3058455973 | J90: =J61 -> 3079595567 | L90: =L61 -> 2.9139514e+09 | N90: =N61 -> 2.9700357e+09
A91: Less:
A92: Local Revenues | B92: =-B46 -> -680367981 | D92: =-D46 -> -747598113 | F92: =-F46 -> 0 | H92: =-H46 -> -722813455 | J92: =-J46 -> -756553905 | L92: =-L46 -> -571160388 | N92: =-N46 -> -572267236
A93: Special Education | B93: =-B85 -> -111303886 | D93: =-D85 -> -121250664 | F93: =-F85 -> 0 | H93: =-H85 -> -121252632 | J93: =-J85 -> -121252632 | L93: =-L85 -> -121252632 | N93: =-N85 -> -121252632
A94: Special Transportation | B94: =-B86 -> -112012 | D94: =-D86 -> -112012 | F94: =-F86 -> -121294.31 | H94: =-H86 -> -128541 | J94: =-J86 -> -170908 | L94: =-L86 -> 0 | N94: =-N86 -> 0
A95: School Lunch Program Match | B95: =-B87 -> -588732 | D95: =-D87 -> -588732 | F95: =-F87 -> -588732 | H95: =-H87 -> -588732 | J95: =-J87 -> -588732 | L95: =-L87 -> -588732 | N95: =-N87 -> -588732
A96: Total Basic Support | B96: =SUM(B90:B95) -> 2178412777 | D96: =SUM(D90:D95) -> 2324500302 | F96: =SUM(F90:F95) -> -710026.31 | H96: =SUM(H90:H95) -> 2213672613 | J96: =SUM(J90:J95) -> 2201029390 | L96: =SUM(L90:L95) -> 2.2209496e+09 | N96: =SUM(N90:N95) -> 2.2759271e+09
A98: Weighted Enrollment | B98: 425270.2 | D98: 436675.2 | H98: 425679.2 | J98: =DSABUDGET!F7 -> 423936.8 | L98: =DSABUDGET!H7 -> 421987.1 | N98: =DSABUDGET!J7 -> 423499.6
A100: Basic Support Per Pupil | B100: =B96/B98 -> 5122.4205 | D100: =D96/D98 -> 5323.1791 | F100: =F96/F98 -> #DIV/0! | H100: =H96/H98 -> 5200.3307 | J100: =J96/J98 -> 5191.8809 | L100: =L96/L98 -> 5263.0747 | N100: =N96/N98 -> 5374.095
A102: % Change | D102: =(D100-B100)/B100 -> 0.039192144 | F102: =(F100-D100)/D100 -> #DIV/0! | H102: =(H100-D100)/D100 -> -0.023078015 | J102: =(J100-H100)/H100 -> -0.0016248517 | L102: =(L100-J100)/J100 -> 0.01371252 | N102: =(N100-L100)/L100 -> 0.021094189
A104: Note 3 - Categorical Programs transferred out of DSA
A105: The following amounts have been transferred from the DSA to the Remediation Trust and rolled into a Student Achievement Block Grant
A106: Class Size Reduction | L106: =-DSASUMM!AG101 -> 0 | N106: =-DSASUMM!AH101 -> 0
A107: Special Units / Gifted and Talented | L107: =-DSASUMM!AG103 -> 0 | N107: =-DSASUMM!AH103 -> 0
A108: Early Childhood Education | L108: =-DSASUMM!AG111 -> 0 | N108: =-DSASUMM!AH111 -> 0
A109: Special Transportation | L109: =-DSASUMM!AG117 -> 0 | N109: =-DSASUMM!AH117 -> 0
A110: Special Elementary Counseling | L110: =-DSASUMM!AG115 -> 0 | N110: =-DSASUMM!AH115 -> 0
A111: Class Size Reduction - At Risk Kindergarten Teachers | L111: =-DSASUMM!AG116 -> 0 | N111: =-DSASUMM!AH116 -> 0
A112: Library Media Specialist | L112: =-DSASUMM!AG112 -> 0 | N112: =-DSASUMM!AH112 -> 0
A114: Note 4 - Regional Professional Development Programs transferred to
A115: Remediation Trust | L115: =-DSASUMM!AC109 -> 7560948 | N115: =-DSASUMM!AD109 -> 7560948
A117: Total Transfers from DSA to Remediation Trust | L117: =SUM(L106:L116) -> 7560948 | N117: =SUM(N106:N116) -> 7560948

Sheet DSABUDGET
B1: DISTRIBUTIVE SCHOOL ACCOUNT - SUMMARY FOR 2011-13 BIENNIUM
C2: 2010 | E2: 2011 | H2: 2012 | J2: 2013
C3: 26th Special | D3: 2010 | E3: 26th Special | F3: 2011 | H3: Legislature | J3: Legislature
C4: Session | D4: Actual | E4: Session | F4: Estimated | H4: Approved | J4: Approved
A5: WEIGHTED ENROLLMENT | C5: 425648.4 | D5: 421386.6 | E5: 429706.6 | F5: =DSADATABASE!B4 -> 422569.6 | H5: =+DSASUMM!AI97 -> 421987.1 | J5: =+DSASUMM!AK97 -> 423499.6
B6: ADDITIONAL ENROLLMENT FOR HOLD HARMLESS | C6: 0 | D6: 4140.6 | E6: 0 | F6: 1367.2 | H6: 0 | J6: 0
A7: TOTAL ENROLLMENT * | C7: =SUM(C5:C6) -> 425648.4 | D7: =SUM(D5:D6) -> 425527.2 | E7: =SUM(E5:E6) -> 429706.6 | F7: =SUM(F5:F6) -> 423936.8 | H7: =SUM(H5:H6) -> 421987.1 | J7: =SUM(J5:J6) -> 423499.6
A8: BASIC SUPPORT | C8: =C9/C7 -> 5186.3621 | D8: =D9/D7 -> 5185.6039 | E8: 5192 | F8: =F9/F7 -> 5192.2041 | H8: =ROUND(H9/H7,0) -> 5263 | J8: =ROUND(J9/J7,0) -> 5374
A9: TOTAL REGULAR BASIC SUPPORT ** | C9: =DSASUMM!B95 -> 2207566730 | D9: =DSASUMM!C95 -> 2206615525 | E9: 2230973023 | F9: 2201166405 | H9: =DSASUMM!AI95 -> 2.2209496e+09 | J9: =DSASUMM!AK95 -> 2.2759271e+09
A11: CATEGORICAL FUNDING:
B12: SPECIAL EDUCATION *** | C12: =DSASUMM!B102 -> 121252632 | D12: =DSASUMM!C102 -> 121252632 | E12: =DSASUMM!E102 -> 121252632 | F12: =DSASUMM!E102 -> 121252632 | H12: =DSASUMM!AI102 -> 121252632 | J12: =DSASUMM!AK102 -> 121252632
B13: CLASS-SIZE REDUCTION | C13: =DSASUMM!B101 -> 142682929 | D13: =DSASUMM!C101 -> 142682930 | E13: =DSASUMM!E101 -> 144348993 | F13: =DSASUMM!E101 -> 144348993 | H13: =DSASUMM!AI101-1 -> 1.3921345e+08 | J13: =DSASUMM!AK101 -> 1.4263961e+08
B14: CLASS-SIZE REDUCTION - AT-RISK KINDERGARTEN | C14: =DSASUMM!B116 -> 1580391 | D14: =DSASUMM!C116 -> 1580390 | E14: =DSASUMM!E116 -> 1586508 | F14: =DSASUMM!E116 -> 1586508 | H14: =DSASUMM!AI116+1 -> 1554599 | J14: =DSASUMM!AK116 -> 1582409.4
B15: SPECIAL UNITS/GIFTED & TALENTED | C15: =DSASUMM!B103 -> 162571 | D15: =DSASUMM!C103 -> 162566 | E15: =DSASUMM!E103 -> 167459 | F15: =DSASUMM!E103 -> 167459 | H15: =DSASUMM!AI103 -> 158414 | J15: =DSASUMM!AK103 -> 162163
B16: ADULT HIGH SCHOOL DIPLOMA | C16: =DSASUMM!B104 -> 21170456 | D16: =DSASUMM!C104 -> 21170456 | E16: =DSASUMM!E104 -> 22673833 | F16: =DSASUMM!E104 -> 22673833 | H16: =DSASUMM!AI104 -> 17011957 | J16: =DSASUMM!AK104 -> 17758916
B17: SCHOOL LUNCH PROGRAM STATE MATCH | C17: =DSASUMM!B105 -> 588732 | D17: =DSASUMM!C105 -> 588732 | E17: =DSASUMM!E105 -> 588732 | F17: =DSASUMM!E105 -> 588732 | H17: =DSASUMM!AI105 -> 588732 | J17: =DSASUMM!AK105 -> 588732
B18: RPDP - TRANSFER TO REMEDIATION TRUST FUND | C18: =DSASUMM!B109 -> 7897804 | D18: =DSASUMM!C109 -> 7897804 | E18: =DSASUMM!E109 -> 7897804 | F18: =DSASUMM!E109 -> 7897804 | H18: =DSASUMM!AI109 -> 0 | J18: =DSASUMM!AK109 -> 0
B19: EARLY CHILDHOOD EDUCATION | C19: =DSASUMM!B111 -> 3338875 | D19: =DSASUMM!C111 -> 3304982 | E19: 3338875 | F19: =DSASUMM!E111 -> 3372768 | H19: =DSASUMM!AI111 -> 3338875 | J19: =DSASUMM!AK111 -> 3338875
B20: LIBRARY MEDIA SPECIALIST | C20: =DSASUMM!B112 -> 18798 | D20: =DSASUMM!C112 -> 18798 | E20: =DSASUMM!E112 -> 18798 | F20: =DSASUMM!E112 -> 18798 | H20: =DSASUMM!AI112 -> 18798 | J20: =DSASUMM!AK112 -> 18798
B21: SPECIAL ELEMENTARY COUNSELING | C21: =DSASUMM!B115 -> 850000 | D21: =DSASUMM!C115 -> 850000 | E21: =DSASUMM!E115 -> 850000 | F21: =DSASUMM!E115 -> 850000 | H21: =DSASUMM!AI115 -> 850000 | J21: =DSASUMM!AK115 -> 850000
B22: SPECIAL TRANSPORTATION | C22: =DSASUMM!B117 -> 170908 | D22: =DSASUMM!C117 -> 128541 | E22: =DSASUMM!E117 -> 170908 | F22: =DSASUMM!E117 -> 170908 | H22: =DSASUMM!AI117 -> 128541 | J22: =DSASUMM!AK117 -> 128541
A24: NRS ADJUSTMENT | C24: =+DSASUMM!B106 -> 0 | D24: 7225368 | E24: 0 | F24: =DSASUMM!E106 -> 0 | G24: 0 | H24: 0 | J24: 0
A25: OTHER ADJUSTMENTS | C25: =DSASUMM!B118 -> 0 | D25: =DSASUMM!C118 -> -39739 | E25: 0 | F25: 0 | H25: =DSASUMM!AI118 -> 0 | J25: =DSASUMM!AK118 -> 0
A26: TOTAL REQUIRED STATE SUPPORT | C26: =SUM(C12:C25)+C9 -> 2507280826 | D26: =SUM(D12:D25)+D9 -> 2513438985 | E26: =SUM(E12:E25)+E9+1 -> 2533867566 | F26: =SUM(F12:F25)+F9 -> 2504094840 | H26: =SUM(H12:H25)+H9 -> 2.5050656e+09 | J26: =SUM(J12:J25)+J9 -> 2.5642478e+09
A28: LESS
B29: =DSASUMM!A121 -> LOCAL SCHOOL SUPPORT TAX - 2.60% | C29: =DSASUMM!B121 -> -905809371 | D29: =DSASUMM!C121 -> -872948748 | E29: -944174996 | F29: =DSASUMM!E121 -> -9.2146231e+08 | H29: =DSASUMM!AI121 -> -9.4173479e+08 | J29: =DSASUMM!AK121 -> -9.6998665e+08
B30: =DSASUMM!A122 -> 1/3 PUBLIC SCHOOLS OPERATING PROPERTY TAX | C30: =DSASUMM!B122 -> -253196604 | D30: =DSASUMM!C122 -> -262851182 | E30: -231116201 | F30: =DSASUMM!E122 -> -220536619 | H30: =DSASUMM!AI122 -> -202433266 | J30: =DSASUMM!AK122 -> -202931773
B31: =+DSASUMM!A124 -> CAPITAL CONSTRUCTION FUNDS | C31: =DSASUMM!B124 -> -10000000 | D31: =C31 -> -10000000 | E31: =DSASUMM!E124 -> -35000000 | F31: =DSASUMM!E124 -> -35000000 | H31: =+DSASUMM!AI124 -> -20000000 | J31: =+DSASUMM!AK124 -> -20000000
B32: TRANSFER FROM CLOSURE OF CC RDA | C32: =DSASUMM!B125 -> -6000000 | D32: =DSASUMM!C125 -> -6000000 | E32: =DSASUMM!E125 -> -5400000 | F32: =DSASUMM!E125 -> -5400000 | H32: =+DSADATABASE!C88 -> 0 | J32: =+DSADATABASE!D88 -> 0
A33: TOTAL STATE SHARE | C33: =SUM(C26:C32) -> 1332274851 | D33: =SUM(D26:D32) -> 1361639055 | E33: =SUM(E26:E32) -> 1318176369 | F33: =SUM(F26:F32) -> 1.3216959e+09 | H33: =SUM(H26:H32) -> 1.3408976e+09 | J33: =SUM(J26:J32) -> 1.3713293e+09
A35: STATE SHARE ELEMENTS
B36: =+DSASUMM!A130 -> GENERAL FUND | C36: =DSASUMM!B130 -> 1173542690 | D36: =DSASUMM!C130 -> 1173542690 | E36: =1267051744-112426570 -> 1154625174 | F36: =DSASUMM!E130 -> 1154625174 | H36: =((1083061369-33139431)+273232418+47028999+1559)-19078532-57561639-42519999-197260069-1+57950189-3147958-286178-20000000 -> 1088280727 | J36: =((920092905-21438031)+406170563+95121601+25)-19078532+1196-58769982-42732000-195882063+52392914-3147958-1113360-286178-20000000 -> 1111331100
B37: =+DSASUMM!A131 -> GENERAL FUND TRANSFER FY 2010 TO FY 2009 | C37: =DSASUMM!B131 -> 0 | D37: =DSASUMM!C131 -> -18917900 | E37: =DSASUMM!E131 -> 0 | F37: 0 | H37: =DSASUMM!AI131 -> 0 | J37: =DSASUMM!AK131 -> 0
B38: =+DSASUMM!A132 -> GENERAL FUND TRANSFER FY 2011 TO FY 2010 | C38: 0 | D38: =DSASUMM!C132 -> 69080821 | E38: 0 | F38: =DSASUMM!E132 -> -69080821 | H38: 0 | J38: 0
B39: =+DSASUMM!A133 -> DSA SHARE OF SLOT TAX | C39: =DSASUMM!B133 -> 35888197 | D39: =DSASUMM!C133 -> 33712074 | E39: 36554830 | F39: =DSASUMM!E133 -> 33300806 | H39: =DSASUMM!AI133 -> 33542238 | J39: =DSASUMM!AK133 -> 34144068
B40: =+DSASUMM!A134 -> PERMANENT SCHOOL FUND | C40: =DSASUMM!B134 -> 13100000 | D40: =DSASUMM!C134 -> 9173420 | E40: 13100000 | F40: =DSASUMM!E134 -> 6700000 | H40: =DSASUMM!AI134 -> 6600000 | J40: =DSASUMM!AK134 -> 6800000
B41: =+DSASUMM!A135 -> FEDERAL MINERAL LEASE REVENUE | C41: =DSASUMM!B135 -> 10706000 | D41: =DSASUMM!C135 -> 8116846 | E41: 10706000 | F41: =DSASUMM!E135 -> 8000000 | H41: =DSASUMM!AI135 -> 8000000 | J41: =DSASUMM!AK135 -> 8000000
B42: =+DSASUMM!A136 -> OUT OF STATE LSST - 2.60% | C42: =DSASUMM!B136 -> 98037864 | D42: =DSASUMM!C136 -> 86190829 | E42: 102190265 | F42: =DSASUMM!E136 -> 91133635 | H42: =DSASUMM!AI136 -> 93138606 | J42: =DSASUMM!AK136 -> 95932745
B43: =+DSASUMM!A137 -> IP1 (2009) ROOM TAX REVENUE TRANSFER | C43: 0 | D43: 0 | E43: 0 | F43: 0 | H43: =+DSASUMM!AI137 -> 111336000 | J43: =+DSASUMM!AK137 -> 115121424
B44: =+DSASUMM!A138 -> REAL PROPERTY TAX | C44: =DSASUMM!B138 -> 1000000 | D44: =DSASUMM!C138 -> 0 | E44: 1000000 | F44: 0 | H44: =DSASUMM!AI138 -> 0 | J44: =DSASUMM!AK138 -> 0
B45: =+DSASUMM!A139 -> ESTATE TAX | C45: =DSASUMM!B139 -> 100 | D45: =DSASUMM!C139 -> 0 | E45: 100 | F45: 0 | H45: =DSASUMM!AI139 -> 0 | J45: =DSASUMM!AK139 -> 0
B46: =+DSASUMM!A140 -> PRIOR YEAR REFUNDS | C46: =DSASUMM!B140 -> 0 | D46: =DSASUMM!C140 -> 816539 | E46: =DSASUMM!E140 -> 0 | F46: 0 | H46: =DSASUMM!AI141 -> 0 | J46: =DSASUMM!AK140 -> 0
B47: =+DSASUMM!A141 -> GENERAL FUND SUPPLEMENTAL APPROPRIATION | C47: =DSASUMM!B141 -> 0 | D47: =DSASUMM!C141 -> 0 | E47: 0 | F47: =DSASUMM!E141-43850647 -> 96983227 | H47: =DSASUMM!AI143 -> 0 | J47: =DSASUMM!AK141 -> 0
B48: =+DSASUMM!A142 -> REVERSION TO STATE GENERAL FUND | C48: =DSASUMM!B143 -> 0 | D48: =DSASUMM!C142 -> -42371 | E48: =DSASUMM!E143 -> 0 | F48: 0 | H48: =DSASUMM!AI144 -> 0 | J48: =DSASUMM!AK143 -> 0
B49: BALANCE FORWARD TO NEXT FISCAL YEAR | C49: =DSASUMM!B144 -> 0 | D49: =DSASUMM!C144 -> -33893 | E49: 0 | F49: =E49 -> 0 | H49: =DSASUMM!AI144 -> 0 | J49: =DSASUMM!AK144 -> 0
A50: TOTAL SHARE STATE ELEMENTS | C50: =SUM(C36:C49) -> 1332274851 | D50: =SUM(D36:D49) -> 1361639055 | E50: =SUM(E36:E49) -> 1318176369 | F50: =SUM(F36:F49) -> 1.321662e+09 | H50: =SUM(H36:H49) -> 1.3408976e+09 | J50: =SUM(J36:J49) -> 1.3713293e+09
D53: No. of Units | E53: $ per Unit | H53: No. of Units | J53: $ per Unit
A54: *** | B54: Special Education Units | C54: 2009-2010 | D54: 3049 | E54: 39768 | F54: 2011-2012 | H54: 3049 | J54: =E54 -> 39768
C55: 2010-2011 | D55: 3049 | E55: 39768 | F55: 2012-2013 | H55: 3049 | J55: =E55 -> 39768
A57: * | B57: FY 10 Actual Weighted Apportioned Enrollment; FY 11, 12 & 13 reflect Estimated and Projected
A58: ** | B58: Totals May Not Balance Due to Rounding
A59: *** | B59: Special Education Unit funded separately from Basic Support

Sheet DSADATABASE
A1: DISTRIBUTIVE SCHOOL ACCOUNT DATA BASE ELEMENTS
A2: TOTAL WEIGHTED ENROLLMENT | F2: AVERAGE SALARIES - FY 10 ACTUAL
A3: FY 10 Actual | B3: FY 11 Actual | C3: FY 12 Projected | D3: FY 13 Projected | I3: Total | J3: Total | K3: Average
A4: 425527.2 | B4: 422569.6 | C4: =423191.8-1204.7 -> 421987.1 | D4: =424460.6-961 -> 423499.6 | F4: Classification | I4: Expenditures | J4: FTE | K4: Salary
A5: % Increase | B5: =B4/A4-1 -> -0.006950437 | C5: =C4/B4-1 -> -0.0013784711 | D5: =D4/C4-1 -> 0.0035842328 | F5: Instruction - Licensed | I5: =904927421+189927658 -> 1094855079 | J5: =C25 -> 20489.15 | K5: =ROUND(I5/J5,0) -> 53436
F6: Instruction - Non-Licensed | I6: =63583541 -> 63583541 | J6: =C26 -> 2051.3 | K6: =ROUND(I6/J6,0) -> 30997
A7: 1ST GRADE ENROLLMENT | F7: Instruction Support - Licensed | I7: 151777440 | J7: =C27 -> 2328.71 | K7: =ROUND(I7/J7,0) -> 65177
A8: =A$3 -> FY 10 Actual | B8: =B$3 -> FY 11 Actual | C8: =C$3 -> FY 12 Projected | D8: =D$3 -> FY 13 Projected | F8: Instruction Support - Non-Licensed | I8: 37561815 | J8: =C28 -> 959.07 | K8: =ROUND(I8/J8,0) -> 39165
A9: 33849 | B9: 33865 | C9: 33933 | D9: 34379 | F9: Administration - Licensed | I9: 123265166 | J9: =C29 -> 1405.47 | K9: =ROUND(I9/J9,0) -> 87704
A10: % Increase | B10: =B9/A9-1 -> 0.00047268752 | C10: =C9/B9-1 -> 0.0020079728 | D10: =D9/C9-1 -> 0.013143548 | F10: Administration - Non-Licensed | I10: 133143886 | J10: =C30 -> 2881.37 | K10: =ROUND(I10/J10,0) -> 46209
F11: All Other Personnel | I11: =245320910+7112424 -> 252433334 | J11: =C31 -> 5844.97 | K11: =ROUND(I11/J11,0) -> 43188
A12: 2ND GRADE ENROLLMENT | F12: Class Size Reduction Personnel | I12: 107048220 | J12: 2173 | K12: =ROUND(I12/J12,0) -> 49263
A13: =A$3 -> FY 10 Actual | B13: =B$3 -> FY 11 Actual | C13: =C$3 -> FY 12 Projected | D13: =D$3 -> FY 13 Projected | F13: AVERAGE STARTING SALARY - FY 11
A14: 33824 | B14: 33447 | C14: 33688 | D14: 33848 | F14: Instruction - Licensed | K14: 39166
A15: % Increase | B15: =B14/A14-1 -> -0.011145932 | C15: =C14/B14-1 -> 0.0072054295 | D15: =D14/C14-1 -> 0.0047494657 | F15: Instruction - Non-Licensed | K15: =ROUND(K6*1*0.75,0) -> 23248
F16: Instruction Support - Licensed | K16: =ROUND(K7*1*0.75,0) -> 48883
A17: 3RD GRADE ENROLLMENT | F17: Instruction Support - Non-Licensed | K17: =ROUND(K8*1*0.75,0) -> 29374
A18: =A$3 -> FY 10 Actual | B18: =B$3 -> FY 11 Actual | C18: =C$3 -> FY 12 Projected | D18: =D$3 -> FY 13 Projected | F18: Administration - Licensed | K18: =ROUND(K9*1*0.75,0) -> 65778
A19: 34068 | B19: 33631 | C19: 33533 | D19: 33773 | F19: Administration - Non-Licensed | K19: =ROUND(K10*1*0.75,0) -> 34657
A20: % Increase | B20: =B19/A19-1 -> -0.012827287 | C20: =C19/B19-1 -> -0.0029139782 | D20: =D19/C19-1 -> 0.0071571288 | F20: All Other Personnel | K20: =ROUND(K11*1*0.75,0) -> 32391
F22: DSA Licensed Instruction Avg Salary | J22: =K5 -> 53436
A23: STUDENT STAFFING RATIO - FY 10 ACTUAL | F23: CSR Licensed Instruction Avg Salary | J23: =K12 -> 49263
A24: Classification | C24: FY 10 FTE | D24: Ratio | F24: CSR as % of DSA Avg Salary | J24: =J23/J22 -> 0.92190658
A25: Instruction - Licensed | C25: =16984.12+3505.03 -> 20489.15 | D25: =A$4/C25 -> 20.768416
A26: Instruction - Non-Licensed | C26: =722.62+1328.68 -> 2051.3 | D26: =A$4/C26 -> 207.44269
A27: Instruction Support - Licensed | C27: =1907.5+421.21 -> 2328.71 | D27: =A$4/C27 -> 182.73087 | F27: COST OF LIVING ADJUSTMENT | J27: FY 12 | K27: FY 13
A28: Instruction Support - Non-Licensed | C28: =879.2+79.87 -> 959.07 | D28: =A$4/C28 -> 443.68732 | F28: Decision Unit E-670 | J28: =1-0.025 -> 0.975 | K28: 1
A29: Administration - Licensed | C29: =1395.67+9.8 -> 1405.47 | D29: =A$4/C29 -> 302.76505
A30: Administration - Non-Licensed | C30: =2862.93+18.44 -> 2881.37 | D30: =A$4/C30 -> 147.68225
A31: All Other Personnel | C31: =4938.68+906.29 -> 5844.97 | D31: =A$4/C31 -> 72.80229 | F31: BUILDING SQUARE FOOTAGE | I31: FY 10 | J31: FY 11 | K31: FY 12 | L31: FY 13
A32: Total Personnel | C32: =SUM(C25:C31) -> 35960.04 | D32: =A$4/C32 -> 11.833335 | F32: Elementary Schools | I32: 18694453 | J32: 18993030 | K32: =J32 -> 18993030 | L32: 19073275
F33: Middle/Junior High Schools | I33: 10814292 | J33: 10910924 | K33: 10921298 | L33: 10905431
F34: High Schools | I34: 16789936 | J34: 17193059 | K34: 17232900 | L34: =K34 -> 17232900
A35: LOCAL SCHOOL SUPPORT TAX | F35: Special Schools | I35: 616424 | J35: 619924 | K35: =J35 -> 619924 | L35: =K35 -> 619924
A36: =A$3 -> FY 10 Actual | B36: =B$3 -> FY 11 Actual | C36: =C$3 -> FY 12 Projected | D36: =D$3 -> FY 13 Projected | F36: Other Facilities | I36: 3159801 | J36: =I36 -> 3159801 | K36: 3175121 | L36: 3207827
A37: =-DSASUMM!C121 -> 872948748 | B37: =((976301000+36294942)*0.91) -> 9.2146231e+08 | C37: =((856899000+38664518)*0.91) -> 8.149628e+08 | D37: =(884060000+38370244)*0.91 -> 8.3941152e+08 | F37: Total Building Square Footage | I37: =SUM(I32:I36) -> 50074906 | J37: =SUM(J32:J36) -> 50876738 | K37: =SUM(K32:K36) -> 50942273 | L37: =SUM(L32:L36) -> 51039357 | N37: =872948748/N38 -> 0.91013734
A38: % Increase | B38: =(B37-A37)/A37 -> 0.05557435 | C38: =(C37-B37)/B37 -> -0.11557663 | D38: =(D37-C37)/C37 -> 0.0299998 | F38: Yearly % Increase | J38: =J37/I37-1 -> 0.016012651 | K38: =K37/J37-1 -> 0.0012881132 | L38: =L37/K37-1 -> 0.001905765 | N38: =872948748+86190829 -> 959139577
A40: OUT OF STATE LOCAL SCHOOL SUPPORT TAX | H40: ENHANCEMENT | I40: =DSASUMM!Q3 -> DSAE671 | K40: =J$27 -> FY 12 | L40: =K$27 -> FY 13
A41: =A$3 -> FY 10 Actual | B41: =B$3 -> FY 11 Actual | C41: =C$3 -> FY 12 Projected | D41: =D$3 -> FY 13 Projected | H41: Suspend Merits | K41: =DSASUMM!Q146 -> 0.4529 | L41: =DSASUMM!R146 -> -0.0912
A42: =DSASUMM!C136 -> 86190829 | B42: =(976301000+36294942)-B37 -> 91133635 | C42: =((856899000+38664518)-C37) -> 80600717 | D42: =(884060000+38370244)-D37 -> 83018722
A43: % Increase | B43: =(B42-A42)/A42 -> 0.057347236 | C43: =(C42-B42)/B42 -> -0.11557663 | D43: =(D42-C42)/C42 -> 0.0299998 | H43: ENHANCEMENT | I43: DSAE670 | K43: =J$27 -> FY 12 | L43: =K$27 -> FY 13
H44: 2.5% Pay Reduction | K44: =DSASUMM!O146 -> -63267152 | L44: =DSASUMM!P150 -> -64540600
A45: PUBLIC SCHOOL OPERATING PROPERTY TAX - 1/3
A46: =A$3 -> FY 10 Actual | B46: =B41 -> FY 11 Actual | C46: =C$3 -> FY 12 Projected | D46: =D$3 -> FY 13 Projected | H46: ENHANCEMENT | I46: DSAE601 | K46: =J$27 -> FY 12 | L46: =K$27 -> FY 13
A47: =-DSASUMM!C122 -> 262851182 | B47: =ROUND(B$57/3,0)+8473040 -> 220536619 | C47: =ROUND(C$59/3,0) -> 202433266 | D47: =ROUND(D$59/3,0) -> 202931773 | H47: PERS Equalization | K47: =DSASUMM!S127 -> -1.045881e+08 | L47: =DSASUMM!T127 -> -1.0702013e+08
A48: % Increase | B48: =B60 -> -0.19321823 | C48: =C60 -> -0.095793399 | D48: =D60 -> 0.0025997837
H49: ENHANCEMENT | I49: DSAE600 | K49: =J$27 -> FY 12 | L49: =K$27 -> FY 13
A50: PUBLIC SCHOOL OPERATING PROPERTY TAX - 2/3 | H50: Budget Reduction | K50: =DSASUMM!W150 -> -52052912 | L50: =DSASUMM!X150 -> -48382960
A51: =A$3 -> FY 10 Actual | B51: FY 11 Actual* | C51: =C$3 -> FY 12 Projected | D51: =D$3 -> FY 13 Projected
A52: =-DSASUMM!C75 -> 525702505 | B52: =ROUND(B$57/3*2,0) -> 424127158 | C52: =ROUND(C$59/3*2,0) -> 404866532 | D52: =ROUND(D$59/3*2,0) -> 405863545 | H52: ENHANCEMENT | I52: =DSASUMM!Y3 -> DSAE710 | K52: =J$27 -> FY 12 | L52: =K$27 -> FY 13
A53: % Increase | B53: =B60 -> -0.19321823 | C53: =C60 -> -0.095793399 | D53: =D60 -> 0.0025997837 | H53: Replacement Equipment. | K53: =DSASUMM!Y146 -> 20675812 | L53: =DSASUMM!Z146 -> 20675812
A55: PSOPT and NET PROCEEDS OF MINERALS - TOTAL REVENUE | H55: ENHANCEMENT | I55: DSAE602 | K55: =J$27 -> FY 12 | L55: =K$27 -> FY 13
A56: =A$3 -> FY 10 Actual | B56: =B51 -> FY 11 Actual* | C56: =C$3 -> FY 12 Projected | D56: =D$3 -> FY 13 Projected | H56: School District Debt Service Excess Reserves | K56: 0 | L56: =K56 -> 0
A57: =+A47+A52 -> 788553687 | B57: =638766343-2575606 -> 636190737 | C57: =(587507098-12259234) -> 575247864 | D57: =(593554990-16811606) -> 576743384
C58: =(28617798)+(28617798*0.12) -> 32051934 | D58: =(28617798)+(28617798*0.12) -> 32051934 | H58: ENHANCEMENT | I58: DSAE300 | K58: =J$27 -> FY 12 | L58: =K$27 -> FY 13
A59: =SUM(A57:A58) -> 788553687 | B59: =SUM(B57:B58) -> 636190737 | C59: =SUM(C57:C58) -> 6.072998e+08 | D59: =SUM(D57:D58) -> 6.0879532e+08 | H59: IDEA MOE | K59: =DSASUMM!U150 -> 8798548 | L59: =DSASUMM!V150 -> 8396675
A60: % Increase | B60: =(B57-A57)/A57 -> -0.19321823 | C60: =(C57-B57)/B57 -> -0.095793399 | D60: =(D57-C57)/C57 -> 0.0025997837
H61: ENHANCEMENT | I61: DSAE900 | K61: =J$27 -> FY 12 | L61: =K$27 -> FY 13
H62: Transfer categoricals to block grant | K62: 0 | L62: 0
A63: DSA FRINGE BENEFIT RATES
C64: BASE/M200 | D64: M300 FY12 | E64: M300 FY13 | H64: ENHANCEMENT | I64: DSAE130 | K64: FY 12 Projected | L64: FY 13 Projected
A65: RETIREMENT | C65: 0.215 | D65: 0.2375 | E65: =ROUND((D65/1)*1,6) -> 0.2375 | H65: Transfer IP1 Room Tax Funding from BA 2617 | K65: 111336000 | L65: =114008064+1113360 -> 115121424
A66: WORKERS' COMPENSATION | C66: =ROUND(DSASUMM!C10/(DSASUMM!C5+DSASUMM!C6+DSASUMM!C7),6) -> 0.004076 | D66: =C66 -> 0.004076 | E66: =D66 -> 0.004076
A67: UNEMPLOYMENT INSURANCE | C67: =ROUND(DSASUMM!C11/(DSASUMM!C5+DSASUMM!C6+DSASUMM!C7),6) -> 0.003592 | D67: =C67 -> 0.003592 | E67: =ROUND((D67/1)*1,6) -> 0.003592 | H67: ENHANCEMENT | I67: DSAE140 | K67: =J$27 -> FY 12 | L67: =K$27 -> FY 13
A68: MEDICARE | C68: =ROUND(DSASUMM!C12/(DSASUMM!C5+DSASUMM!C6+DSASUMM!C7),6) -> 0.013034 | D68: =C68 -> 0.013034 | E68: =D68 -> 0.013034 | H68: Extend LSST from 2.25% to 2.60% (91%) | K68: =139309881*0.91 -> 1.2677199e+08 | L68: =143489149*0.91 -> 1.3057513e+08
A69: OTHER (INCLUDES FICA) | C69: =ROUND(DSASUMM!C14/(DSASUMM!C5+DSASUMM!C6+DSASUMM!C7),6) -> 0.004306 | D69: =C69 -> 0.004306 | E69: =D69 -> 0.004306 | H69: Extend LSST from 2.25% to 2.60% OOS LSST (9%) | K69: =139309881*0.09 -> 12537889 | L69: =143489149*0.09 -> 12914023
A70: MEDICAL INSURANCE (PER FTE) | C70: =ROUND(DSASUMM!C13/DSADATABASE!C32,2) -> 6980.69 | D70: =ROUND(C70*1,2) -> 6980.69 | E70: =ROUND(D70*1,2) -> 6980.69 | H70: Total Additional LSST from extending rate sunset | K70: =SUM(K68:K69) -> 139309881 | L70: =SUM(L68:L69) -> 143489149
A72: CSR FRINGE BENEFIT RATES
C73: BASE/M200 | D73: =D64 -> M300 FY12 | E73: =E64 -> M300 FY13
A74: =A65 -> RETIREMENT | C74: =C65 -> 0.215 | D74: =D65 -> 0.2375 | E74: =ROUND(($D74/1)*1,6) -> 0.2375
A75: =A66 -> WORKERS' COMPENSATION | C75: =ROUND(330421/107048220,6) -> 0.003087 | D75: =C75 -> 0.003087 | E75: =D75 -> 0.003087
A76: =A67 -> UNEMPLOYMENT INSURANCE | C76: =ROUND(322081/107048220,6) -> 0.003009 | D76: =C76 -> 0.003009 | E76: =ROUND((D76/1)*1,6) -> 0.003009
A77: =A68 -> MEDICARE | C77: =ROUND(1488206/107048220,6) -> 0.013902 | D77: =C77 -> 0.013902 | E77: =D77 -> 0.013902
A78: =A69 -> OTHER (INCLUDES FICA) | C78: =ROUND(573507/107048220,6) -> 0.005357 | D78: =C78 -> 0.005357 | E78: =D78 -> 0.005357
A79: =A70 -> MEDICAL INSURANCE (PER FTE) | C79: =C70 -> 6980.69 | D79: =ROUND(C79*1,2) -> 6980.69 | E79: =ROUND(D79*1,2) -> 6980.69
A81: CAPITAL CONSTRUCTION FUNDS
A82: =A$3 -> FY 10 Actual | B82: FY 11 Actual | C82: FY 2012 | D82: FY 2013
A83: 10000000 | B83: =10000000+25000000 -> 35000000 | C83: 20000000 | D83: 20000000
A84: % Increase | C84: 0 | D84: 0
A86: TRANSFER FROM CLOSURE OF CC RDA
A87: =A$3 -> FY 10 Actual | B87: =B82 -> FY 11 Actual | C87: =C$3 -> FY 12 Projected | D87: =D$3 -> FY 13 Projected
A88: =6000000 -> 6000000 | B88: 5400000 | C88: =+DSASUMM!AI125 -> 0 | D88: =+DSASUMM!AK125 -> 0
A89: % Increase | C89: 0 | D89: 0

Sheet DSASUMM
I1: Enrollment Change | M1: Benefit Change | O1: 2.5% Salary Reduction | Q1: Merit/Longevity | S1: PERS Equalization | W1: Per Pupil Budget Reduction | Y1: New Equipment | AC1: Transfer RPDP$ to BA 2615 | AE1: IP1 Rm Tx to DSA | AG1: Revenue Adjustments
A2: DISTRIBUTIVE SCHOOL ACCOUNT MAIN WORK SHEET - 2011-13 BIENNIUM
B3: 2009-10 | E3: 2010-11 | F3: % | G3: DSABASE | H3: DSABASE | I3: DSAM200 | J3: DSAM200 | K3: DSAM101 | L3: =K3 -> DSAM101 | M3: DSAM300 | N3: DSAM300 | O3: DSAE670 | P3: =O3 -> DSAE670 | Q3: DSAE671 | R3: =Q3 -> DSAE671 | S3: DSAE601 | T3: =S3 -> DSAE601 | U3: DSAE300 | V3: =U3 -> DSAE300 | W3: DSAE600 | X3: =W3 -> DSAE600 | Y3: DSAE710 | Z3: =Y3 -> DSAE710 | AA3: DSAE602 | AB3: =AA3 -> DSAE602 | AC3: DSAE904 | AD3: =AC3 -> DSAE904 | AE3: DSAE130 | AF3: =AE3 -> DSAE130 | AG3: DSAE140 | AH3: =AG3 -> DSAE140 | AI3: DSABME | AJ3: % CHG | AK3: DSABME | AL3: % CHG
B4: WK PROGRAM | C4: ACTUAL | D4: % CHG | E4: WK PROGRAM | F4: CHG | G4: 2011-12 | H4: 2012-13 | I4: =$G4 -> 2011-12 | J4: =$H4 -> 2012-13 | K4: =$G4 -> 2011-12 | L4: =$H4 -> 2012-13 | M4: =$G4 -> 2011-12 | N4: =$H4 -> 2012-13 | O4: =$G4 -> 2011-12 | P4: =$H4 -> 2012-13 | Q4: =$G$4 -> 2011-12 | R4: =$H$4 -> 2012-13 | S4: =$G$4 -> 2011-12 | T4: =$H$4 -> 2012-13 | U4: =$G$4 -> 2011-12 | V4: =$H$4 -> 2012-13 | W4: =$G$4 -> 2011-12 | X4: =$H$4 -> 2012-13 | Y4: =$G$4 -> 2011-12 | Z4: =$H$4 -> 2012-13 | AA4: =$G$4 -> 2011-12 | AB4: =$H$4 -> 2012-13 | AC4: =Y4 -> 2011-12 | AD4: =Z4 -> 2012-13 | AE4: =Y4 -> 2011-12 | AF4: =Z4 -> 2012-13 | AG4: =AA4 -> 2011-12 | AH4: =AB4 -> 2012-13 | AI4: =$G$4 -> 2011-12 | AJ4: =$G$4 -> 2011-12 | AK4: =$H$4 -> 2012-13 | AL4: =$H$4 -> 2012-13
A5: SALARIES | B5: 1813834741 | C5: =1912223758-C6-C7 -> 1856620261 | D5: =ROUND(C5/B5-1,4) -> 0.0236 | E5: =1911029454-E6-E7 -> 1849660599 | F5: =ROUND(E5/C5-1,4) -> -0.0037 | G5: =BASESAL!F53 -> 1901538049 | H5: =BASESAL!H53 -> 1939568810 | I5: =M200SAL!D69 -> -1881325 | J5: =M200SAL!G69 -> 2963658 | M5: =M300SAL!D72 -> -21371138 | N5: =M300SAL!G72 -> -21853490 | O5: =+E670SAL!D71 -> -46957144 | P5: =+E670SAL!G71 -> -47896287 | Q5: =E671SAL!D72+E671SAL!D81 -> 0 | R5: =E671SAL!G72+E671SAL!G81 -> 0 | S5: ='E601 SAL'!D72+'E601 SAL'!D81 -> -77466814 | T5: ='E601 SAL'!G72+'E601 SAL'!F81 -> -79220365 | AC5: 0 | AD5: 0 | AE5: 0 | AF5: 0 | AG5: 0 | AH5: 0 | AI5: =G5+I5+K5+M5+O5+Q5+S5+U5+W5+Y5+AA5+AG5+AC5+AE5 -> 1.7538616e+09 | AJ5: =ROUND(AI5/C5-1,4) -> -0.0553 | AK5: =H5+J5+L5+N5+P5+R5+T5+V5+X5+Z5+AB5+AH5+AD5+AF5 -> 1.7935623e+09 | AL5: =ROUND(AK5/AI5-1,4) -> 0.0226
A6: SUBSTITUTE PAY | B6: 39306246 | C6: =35121511+1216611 -> 36338122 | D6: =ROUND(C6/B6-1,4) -> -0.0755 | E6: =36975586+1044466 -> 38020052 | F6: =ROUND(E6/C6-1,4) -> 0.0463 | G6: =BASESAL!F54 -> 36338122 | H6: =BASESAL!H54 -> 36338122 | I6: =M200SAL!D70 -> -302309 | J6: =M200SAL!G70 -> -173148 | M6: =M300SAL!D73 -> 0 | N6: =M300SAL!G73 -> 0 | O6: =+E670SAL!D72 -> 0 | P6: =+E670SAL!G72 -> 0 | Q6: =E671SAL!D73 -> 0 | R6: =E671SAL!G73 -> 0 | AC6: 0 | AD6: 0 | AE6: 0 | AF6: 0 | AG6: 0 | AH6: 0 | AI6: =G6+I6+K6+M6+O6+Q6+S6+U6+W6+Y6+AA6+AG6+AC6+AE6 -> 36035813 | AJ6: =ROUND(AI6/C6,4)-1 -> -0.0083 | AK6: =H6+J6+L6+N6+P6+R6+T6+V6+X6+Z6+AB6+AH6+AD6+AF6 -> 36164974 | AL6: =ROUND(AK6/AI6-1,4) -> 0.0036
A7: EXTRA DUTY MISCELLANEOUS | B7: 25416599 | C7: 19265375 | D7: =ROUND(C7/B7-1,4) -> -0.242 | E7: 23348803 | F7: =ROUND(E7/C7-1,4) -> 0.212 | G7: =BASESAL!F55 -> 20845444 | H7: =BASESAL!H55 -> 21262353 | I7: =M200SAL!D71 -> -173420 | J7: =M200SAL!G71 -> -101313 | M7: =M300SAL!D74 -> 0 | N7: =M300SAL!G74 -> 0 | O7: =+E670SAL!D73 -> 0 | P7: =+E670SAL!G73 -> 0 | Q7: =E671SAL!D74 -> 0 | R7: =E671SAL!G74 -> 0 | AC7: 0 | AD7: 0 | AE7: 0 | AF7: 0 | AG7: 0 | AH7: 0 | AI7: =G7+I7+K7+M7+O7+Q7+S7+U7+W7+Y7+AA7+AG7+AC7+AE7 -> 20672024 | AJ7: =ROUND(AI7/C7,4)-1 -> 0.073 | AK7: =H7+J7+L7+N7+P7+R7+T7+V7+X7+Z7+AB7+AH7+AD7+AF7 -> 21161040 | AL7: =ROUND(AK7/AI7-1,4) -> 0.0237
A8: FRINGES | AC8: 0 | AD8: 0 | AE8: 0 | AF8: 0 | AG8: 0 | AH8: 0 | AI8: =G8+I8+K8+M8+O8+Q8+S8+U8+W8+Y8+AA8+AG8+AC8+AE8 -> 0 | AK8: =H8+J8+L8+N8+P8+R8+T8+V8+X8+Z8+AB8+AH8+AD8+AF8 -> 0
A9: RETIREMENT | B9: 387981279 | C9: 381217472 | D9: =ROUND(C9/B9-1,4) -> -0.0174 | E9: 384499471 | F9: =ROUND(E9/C9-1,4) -> 0.0086 | G9: =BASESAL!F57 -> 408830681 | H9: =BASESAL!H57 -> 417007294 | I9: =M200SAL!D72 -> -404485.34 | J9: =M200SAL!G72 -> 637186.62 | M9: =M300SAL!D75 -> 37666631 | N9: =M300SAL!G75 -> 38516776 | O9: =E670SAL!D74 -> -11152322 | P9: =E670SAL!G74 -> -11375368 | Q9: =E671SAL!D75 -> 0 | R9: =E671SAL!G75 -> 0 | S9: ='E601 SAL'!D75 -> -18398368 | T9: ='E601 SAL'!G75 -> -18814837 | AC9: 0 | AD9: 0 | AE9: 0 | AF9: 0 | AG9: 0 | AH9: 0 | AI9: =G9+I9+K9+M9+O9+Q9+S9+U9+W9+Y9+AA9+AG9+AC9+AE9 -> 416542137 | AJ9: =ROUND(AI9/C9,4)-1 -> 0.0927 | AK9: =H9+J9+L9+N9+P9+R9+T9+V9+X9+Z9+AB9+AH9+AD9+AF9 -> 425971052 | AL9: =ROUND(AK9/AI9-1,4) -> 0.0226
A10: WORKER'S COMP | B10: 14085077 | C10: 7794417 | D10: =ROUND(C10/B10-1,4) -> -0.4466 | E10: 9375209 | F10: =ROUND(E10/C10-1,4) -> 0.2028 | G10: =BASESAL!F58 -> 7983749 | H10: =BASESAL!H58 -> 8140462 | I10: =M200SAL!D73 -> -9607 | J10: =M200SAL!G73 -> 10961 | M10: =M300SAL!D76 -> -87109 | N10: =M300SAL!G76 -> -89075 | O10: =+E670SAL!D75 -> -191397 | P10: =+E670SAL!G75 -> -195225 | Q10: =E671SAL!D76 -> 0 | R10: =E671SAL!G76 -> 0 | S10: ='E601 SAL'!D76 -> -315755 | T10: ='E601 SAL'!G76 -> -322902 | AC10: 0 | AD10: 0 | AE10: 0 | AF10: 0 | AG10: 0 | AH10: 0 | AI10: =G10+I10+K10+M10+O10+Q10+S10+U10+W10+Y10+AA10+AG10+AC10+AE10 -> 7379881 | AJ10: =ROUND(AI10/C10,4)-1 -> -0.0532 | AK10: =H10+J10+L10+N10+P10+R10+T10+V10+X10+Z10+AB10+AH10+AD10+AF10 -> 7544221 | AL10: =ROUND(AK10/AI10-1,4) -> 0.0223
A11: UNEMPLOYMENT COMP | B11: 1499168 | C11: 6869299 | D11: =ROUND(C11/B11-1,4) -> 3.5821 | E11: 6488035 | F11: =ROUND(E11/C11-1,4) -> -0.0555 | G11: =BASESAL!F59 -> 7035728 | H11: =BASESAL!H59 -> 7173832 | I11: =M200SAL!D74 -> -8466 | J11: =M200SAL!G74 -> 9660 | M11: =M300SAL!D77 -> -76766 | N11: =M300SAL!G77 -> -78498 | O11: =+E670SAL!D76 -> -168670 | P11: =+E670SAL!G76 -> -172044 | Q11: =E671SAL!D77 -> 0 | R11: =E671SAL!G77 -> 0 | S11: ='E601 SAL'!D77 -> -278260 | T11: ='E601 SAL'!G77 -> -284559 | AC11: 0 | AD11: 0 | AE11: 0 | AF11: 0 | AG11: 0 | AH11: 0 | AI11: =G11+I11+K11+M11+O11+Q11+S11+U11+W11+Y11+AA11+AG11+AC11+AE11 -> 6503566 | AJ11: =ROUND(AI11/C11,4)-1 -> -0.0532 | AK11: =H11+J11+L11+N11+P11+R11+T11+V11+X11+Z11+AB11+AH11+AD11+AF11 -> 6648391 | AL11: =ROUND(AK11/AI11-1,4) -> 0.0223
A12: MEDICARE | B12: 24848431 | C12: 24924833 | D12: =ROUND(C12/B12-1,4) -> 0.0031 | E12: 26283600 | F12: =ROUND(E12/C12-1,4) -> 0.0545 | G12: =BASESAL!F60 -> 25529978 | H12: =BASESAL!H60 -> 26031104 | I12: =M200SAL!D75 -> -30722 | J12: =M200SAL!G75 -> 35051 | M12: =M300SAL!D78 -> -278552 | N12: =M300SAL!G78 -> -284838 | O12: =+E670SAL!D77 -> -612039 | P12: =+E670SAL!G77 -> -624280 | Q12: =E671SAL!D78 -> 0 | R12: =E671SAL!G78 -> 0 | S12: ='E601 SAL'!D78 -> -1009703 | T12: ='E601 SAL'!G78 -> -1032558 | AC12: 0 | AD12: 0 | AE12: 0 | AF12: 0 | AG12: 0 | AH12: 0 | AI12: =G12+I12+K12+M12+O12+Q12+S12+U12+W12+Y12+AA12+AG12+AC12+AE12 -> 23598962 | AJ12: =ROUND(AI12/C12,4)-1 -> -0.0532 | AK12: =H12+J12+L12+N12+P12+R12+T12+V12+X12+Z12+AB12+AH12+AD12+AF12 -> 24124479 | AL12: =ROUND(AK12/AI12-1,4) -> 0.0223
A13: MEDICAL INSURANCE | B13: 255724363 | C13: 251025893 | D13: =ROUND(C13/B13-1,4) -> -0.0184 | E13: 260273017 | F13: =ROUND(E13/C13-1,4) -> 0.0368 | G13: =BASESAL!F61 -> 249272063 | H13: =BASESAL!H61 -> 249272063 | I13: =M200SAL!D76 -> -343729 | J13: =M200SAL!G76 -> 548403 | M13: =M300SAL!D79 -> 0 | N13: =M300SAL!G79 -> 0 | O13: =+E670SAL!D78 -> 0 | P13: =+E670SAL!G78 -> 0 | Q13: =E671SAL!D79 -> 0 | R13: =E671SAL!G79 -> 0 | AA13: 0 | AB13: 0 | AC13: 0 | AD13: 0 | AE13: 0 | AF13: 0 | AG13: 0 | AH13: 0 | AI13: =G13+I13+K13+M13+O13+Q13+S13+U13+W13+Y13+AA13+AG13+AC13+AE13 -> 248928334 | AJ13: =ROUND(AI13/C13,4)-1 -> -0.0084 | AK13: =H13+J13+L13+N13+P13+R13+T13+V13+X13+Z13+AB13+AH13+AD13+AF13 -> 249820466 | AL13: =ROUND(AK13/AI13-1,4) -> 0.0036
A14: OTHER | B14: 9998816 | C14: 8233092 | D14: =ROUND(C14/B14-1,4) -> -0.1766 | E14: 8594046 | F14: =ROUND(E14/C14-1,4) -> 0.0438 | G14: =BASESAL!F62 -> 8434255 | H14: =BASESAL!H62 -> 8599811 | I14: =M200SAL!D77 -> -10149 | J14: =M200SAL!G77 -> 11580 | M14: =M300SAL!D80 -> -92024 | N14: =M300SAL!G80 -> -94102 | O14: =+E670SAL!D79 -> -202198 | P14: =+E670SAL!G79 -> -206241 | Q14: =E671SAL!D80 -> 0 | R14: =E671SAL!G80 -> 0 | S14: ='E601 SAL'!D80 -> -333572 | T14: ='E601 SAL'!G80 -> -341123 | AC14: 0 | AD14: 0 | AE14: 0 | AF14: 0 | AG14: 0 | AH14: 0 | AI14: =G14+I14+K14+M14+O14+Q14+S14+U14+W14+Y14+AA14+AG14+AC14+AE14 -> 7796312 | AJ14: =ROUND(AI14/C14,4)-1 -> -0.0531 | AK14: =H14+J14+L14+N14+P14+R14+T14+V14+X14+Z14+AB14+AH14+AD14+AF14 -> 7969925 | AL14: =ROUND(AK14/AI14-1,4) -> 0.0223
A15: TOTAL FRINGES | B15: =SUM(B9:B14) -> 694137134 | C15: =SUM(C9:C14) -> 680065006 | D15: =ROUND(C15/B15-1,4) -> -0.0203 | E15: =SUM(E9:E14) -> 695513378 | F15: =ROUND(E15/C15-1,4) -> 0.0227 | G15: =SUM(G9:G14) -> 707086454 | H15: =SUM(H9:H14) -> 716224566 | I15: =SUM(I9:I14) -> -807158.34 | J15: =SUM(J9:J14) -> 1252841.6 | K15: =SUM(K9:K14) -> 0 | L15: =SUM(L9:L14) -> 0 | M15: =SUM(M9:M14) -> 37132180 | N15: =SUM(N9:N14) -> 37970263 | ... AH15: =SUM(AH9:AH14) -> 0 | AI15: =G15+I15+K15+M15+O15+Q15+S15+U15+W15+Y15+AA15+AG15+AC15+AE15 -> 710749192 | AJ15: =ROUND(AI15/C15-1,4) -> 0.0451 | AK15: =(H15+L15+J15+N15+P15+R15+T15+V15+X15+Z15+AB15+AH15+AF15) -> 722078534 | AL15: =ROUND(AK15/AI15-1,4) -> 0.0159
A16: Sub-Total - Salaries and Fringe | B16: =+B5+B6+B7+B15 -> 2572694720 | C16: =+C5+C6+C7+C15 -> 2592288764 | E16: =+E5+E6+E7+E15 -> 2606542832 | G16: =+G5+G6+G7+G15 -> 2665808069 | H16: =+H5+H6+H7+H15 -> 2713393851 | I16: =+I5+I6+I7+I15 -> -3164212.3 | J16: =+J5+J6+J7+J15 -> 3942038.6 | K16: =+K5+K6+K7+K15 -> 0 | L16: =+L5+L6+L7+L15 -> 0 | M16: =+M5+M6+M7+M15 -> 15761042 | N16: =+N5+N6+N7+N15 -> 16116773 | ... AI16: =+AI5+AI6+AI7+AI15 -> 2.5213187e+09 | AK16: =+AK5+AK6+AK7+AK15 -> 2.5729669e+09
A18: FULL DAY KINDERGARTEN - 22 | B18: 0 | C18: 0 | D18: =ROUND(C18/B18-1,4) -> #DIV/0! | E18: 0 | F18: =ROUND(E18/C18-1,4) -> #DIV/0! | G18: =C18 -> 0 | H18: =G18 -> 0 | AI18: =(G18+K18+I18+M18+O18+Q18+S18+U18+W18+Y18+AA18) -> 0 | AJ18: =ROUND(AI18/C18,4)-1 -> #DIV/0! | AK18: =(H18+L18+J18+N18+P18+R18+T18+V18+X18+Z18+AB18) -> 0 | AL18: =ROUND(AK18/AI18-1,4) -> #DIV/0!
A19: RETIRED EMPOYEES GROUP INS | B19: 36645582 | C19: 27980315 | D19: =ROUND(C19/B19-1,4) -> -0.2365 | E19: =25660901+3759244 -> 29420145 | F19: =ROUND(E19/C19-1,4) -> 0.0515 | G19: 27062825 | H19: 27118499 | AA19: 0 | AB19: 0 | AI19: =G19+I19+K19+M19+O19+Q19+S19+U19+W19+Y19+AA19+AG19+AC19+AE19 -> 27062825 | AJ19: =ROUND(AI19/C19,4)-1 -> -0.0328 | AK19: =H19+J19+L19+N19+P19+R19+T19+V19+X19+Z19+AB19+AH19+AD19+AF19 -> 27118499 | AL19: =ROUND(AK19/AI19-1,4) -> 0.0021
A21: TOTAL SALARY AND FRINGE | B21: =SUM(B16:B20) -> 2609340302 | C21: =SUM(C16:C20) -> 2620269079 | D21: =ROUND(C21/B21-1,4) -> 0.0042 | E21: =SUM(E16:E20) -> 2635962977 | F21: =ROUND(E21/C21-1,4) -> 0.006 | G21: =SUM(G16:G20) -> 2692870894 | H21: =SUM(H16:H20) -> 2740512350 | I21: =SUM(I16:I20) -> -3164212.3 | J21: =SUM(J16:J20) -> 3942038.6 | K21: =SUM(K16:K20) -> 0 | L21: =SUM(L16:L20) -> 0 | M21: =SUM(M16:M20) -> 15761042 | N21: =SUM(N16:N20) -> 16116773 | ... AI21: =SUM(AI16:AI20) -> 2.5483815e+09 | AJ21: =ROUND(AI21/C21-1,4) -> -0.0274 | AK21: =SUM(AK16:AK20) -> 2.6000854e+09 | AL21: =ROUND(AK21/AI21-1,4) -> 0.0203
A22: BENEFIT/SALARY | B22: =B15/B5 -> 0.3826904 | C22: =C15/C5 -> 0.36629192 | D22: =ROUND(C22/B22-1,4) -> -0.0429 | E22: =E15/E5 -> 0.37602216 | F22: =ROUND(E22/C22-1,4) -> 0.0266 | G22: =G15/G5 -> 0.37184975 | H22: =H15/H5 -> 0.36927 | I22: =I15/I5 -> 0.42903716 | J22: =J15/J5 -> 0.42273488 | O22: =O15/O5 -> 0.262508 | P22: =P15/P5 -> 0.26250799 | AI22: =AI15/AI5 -> 0.40524816 | AK22: =AK15/AK5 -> 0.40259462
A23: OPERATING:
A24: Heat | B24: 15147689 | C24: 12057552 | D24: =ROUND(C24/B24-1,4) -> -0.204 | E24: 12626587 | F24: =ROUND(E24/C24-1,4) -> 0.0472 | G24: =C24 -> 12057552 | H24: =G24 -> 12057552 | I24: =M200OPR!R55 -> 209347 | J24: =M200OPR!T55 -> 232725 | K24: =M101INF!S55 -> 0 | L24: =M101INF!V55 -> 0 | AC24: 0 | AD24: 0 | AE24: 0 | AF24: 0 | AG24: 0 | AH24: 0 | AI24: =G24+I24+K24+M24+O24+Q24+S24+U24+W24+Y24+AA24+AG24+AC24+AE24 -> 12266899 | AJ24: =ROUND(AI24/C24,4)-1 -> 0.0174 | AK24: =H24+J24+L24+N24+P24+R24+T24+V24+X24+Z24+AB24+AH24+AD24+AF24 -> 12290277 | AL24: =ROUND(AK24/AI24-1,4) -> 0.0019
A25: Electricity | B25: 72409307 | C25: 65089232 | D25: =ROUND(C25/B25-1,4) -> -0.1011 | E25: 70760567 | F25: =ROUND(E25/C25-1,4) -> 0.0871 | G25: =C25 -> 65089232 | H25: =G25 -> 65089232 | I25: =M200OPR!R56 -> 1125534 | J25: =M200OPR!T56 -> 1251724 | K25: =M101INF!S56 -> 0 | L25: =M101INF!V56 -> 0 | AC25: 0 | AD25: 0 | AE25: 0 | AF25: 0 | AG25: 0 | AH25: 0 | AI25: =G25+I25+K25+M25+O25+Q25+S25+U25+W25+Y25+AA25+AG25+AC25+AE25 -> 66214766 | AJ25: =ROUND(AI25/C25,4)-1 -> 0.0173 | AK25: =H25+J25+L25+N25+P25+R25+T25+V25+X25+Z25+AB25+AH25+AD25+AF25 -> 66340956 | AL25: =ROUND(AK25/AI25-1,4) -> 0.0019
A26: Pupil Transportation | B26: 25014207 | C26: 16707325 | D26: =ROUND(C26/B26-1,4) -> -0.3321 | E26: 16907458 | F26: =ROUND(E26/C26-1,4) -> 0.012 | G26: =C26 -> 16707325 | H26: =G26 -> 16707325 | I26: =M200OPR!R60 -> -139014 | J26: =M200OPR!T60 -> -79630 | K26: =M101INF!S60 -> 0 | L26: =M101INF!V60 -> 0 | AC26: 0 | AD26: 0 | AE26: 0 | AF26: 0 | AG26: 0 | AH26: 0 | AI26: =G26+I26+K26+M26+O26+Q26+S26+U26+W26+Y26+AA26+AG26+AC26+AE26 -> 16568311 | AJ26: =ROUND(AI26/C26,4)-1 -> -0.0083 | AK26: =H26+J26+L26+N26+P26+R26+T26+V26+X26+Z26+AB26+AH26+AD26+AF26 -> 16627695 | AL26: =ROUND(AK26/AI26-1,4) -> 0.0036 | AM26: Total Txtbook, Software, Hardware, Instructional Supplies
A27: Textbooks | B27: 28420804 | C27: 23810368 | D27: =ROUND(C27/B27-1,4) -> -0.1622 | E27: 36559619 | F27: =ROUND(E27/C27-1,4) -> 0.5354 | G27: =C27 -> 23810368 | H27: =G27 -> 23810368 | I27: =M200OPR!R61 -> -198080 | J27: =M200OPR!T61 -> -113448 | K27: =M101INF!S61 -> 0 | L27: =M101INF!V61 -> 0 | AC27: 0 | AD27: 0 | AE27: 0 | AF27: 0 | AG27: 0 | AH27: 0 | AI27: =G27+I27+K27+M27+O27+Q27+S27+U27+W27+Y27+AA27+AG27+AC27+AE27 -> 23612288 | AJ27: =ROUND(AI27/C27,4)-1 -> -0.0083 | AK27: =H27+J27+L27+N27+P27+R27+T27+V27+X27+Z27+AB27+AH27+AD27+AF27 -> 23696920 | AL27: =ROUND(AK27/AI27-1,4) -> 0.0036 | AM27: =AI27+AI36+AI37+AI52 -> 101336415 | AN27: =AK27+AK36+AK37+AK52 -> 101699617
A28: Library | B28: 2389288 | C28: 2397912 | D28: =ROUND(C28/B28-1,4) -> 0.0036 | E28: 2674356 | F28: =ROUND(E28/C28-1,4) -> 0.1153 | G28: =C28 -> 2397912 | H28: =G28 -> 2397912 | I28: =M200OPR!R62 -> -19930 | J28: =M200OPR!T62 -> -11407 | K28: =M101INF!S62 -> 0 | L28: =M101INF!V62 -> 0 | AC28: 0 | AD28: 0 | AE28: 0 | AF28: 0 | AG28: 0 | AH28: 0 | AI28: =G28+I28+K28+M28+O28+Q28+S28+U28+W28+Y28+AA28+AG28+AC28+AE28 -> 2377982 | AJ28: =ROUND(AI28/C28,4)-1 -> -0.0083 | AK28: =H28+J28+L28+N28+P28+R28+T28+V28+X28+Z28+AB28+AH28+AD28+AF28 -> 2386505 | AL28: =ROUND(AK28/AI28-1,4) -> 0.0036
A29: Maintenance/Repair | B29: 37797695 | C29: 25553696 | D29: =ROUND(C29/B29-1,4) -> -0.3239 | E29: 29366243 | F29: =ROUND(E29/C29-1,4) -> 0.1492 | G29: =C29 -> 25553696 | H29: =G29 -> 25553696 | I29: =M200OPR!R59 -> 442146 | J29: =M200OPR!T59 -> 491688 | K29: =M101INF!S59 -> 0 | L29: =M101INF!V59 -> 0 | AC29: 0 | AD29: 0 | AE29: 0 | AF29: 0 | AG29: 0 | AH29: 0 | AI29: =G29+I29+K29+M29+O29+Q29+S29+U29+W29+Y29+AA29+AG29+AC29+AE29 -> 25995842 | AJ29: =ROUND(AI29/C29,4)-1 -> 0.0173 | AK29: =H29+J29+L29+N29+P29+R29+T29+V29+X29+Z29+AB29+AH29+AD29+AF29 -> 26045384 | AL29: =ROUND(AK29/AI29-1,4) -> 0.0019
A30: Professional Services | B30: 60276021 | C30: 47269193 | D30: =ROUND(C30/B30-1,4) -> -0.2158 | E30: 44995473 | F30: =ROUND(E30/C30-1,4) -> -0.0481 | G30: =C30 -> 47269193 | H30: =G30 -> 47269193 | I30: =M200OPR!R66 -> -394980 | J30: =M200OPR!T66 -> -226987 | K30: =M101INF!S66 -> 0 | L30: =M101INF!V66 -> 0 | AC30: 0 | AD30: 0 | AE30: 0 | AF30: 0 | AG30: 0 | AH30: 0 | AI30: =G30+I30+K30+M30+O30+Q30+S30+U30+W30+Y30+AA30+AG30+AC30+AE30 -> 46874213 | AJ30: =ROUND(AI30/C30,4)-1 -> -0.0084 | AK30: =H30+J30+L30+N30+P30+R30+T30+V30+X30+Z30+AB30+AH30+AD30+AF30 -> 47042206 | AL30: =ROUND(AK30/AI30-1,4) -> 0.0036
A31: Water/Sewer/Garbage | B31: 26434884 | C31: 26757018 | D31: =ROUND(C31/B31-1,4) -> 0.0122 | E31: 28806985 | F31: =ROUND(E31/C31-1,4) -> 0.0766 | G31: =C31 -> 26757018 | H31: =G31 -> 26757018 | I31: =M200OPR!R57 -> 461438 | J31: =M200OPR!T57 -> 513310 | K31: =M101INF!S57 -> 0 | L31: =M101INF!V57 -> 0 | AC31: 0 | AD31: 0 | AE31: 0 | AF31: 0 | AG31: 0 | AH31: 0 | AI31: =G31+I31+K31+M31+O31+Q31+S31+U31+W31+Y31+AA31+AG31+AC31+AE31 -> 27218456 | AJ31: =ROUND(AI31/C31,4)-1 -> 0.0172 | AK31: =H31+J31+L31+N31+P31+R31+T31+V31+X31+Z31+AB31+AH31+AD31+AF31 -> 27270328 | AL31: =ROUND(AK31/AI31-1,4) -> 0.0019
A32: Liability Insurance | B32: 14869666 | C32: 5925229 | D32: =ROUND(C32/B32-1,4) -> -0.6015 | E32: 11103735 | F32: =ROUND(E32/C32-1,4) -> 0.874 | G32: =C32 -> 5925229 | H32: =G32 -> 5925229 | I32: =M200OPR!R67 -> -49511 | J32: =M200OPR!T67 -> -28453 | K32: =M101INF!S67 -> 0 | L32: =M101INF!V67 -> 0 | AC32: 0 | AD32: 0 | AE32: 0 | AF32: 0 | AG32: 0 | AH32: 0 | AI32: =G32+I32+K32+M32+O32+Q32+S32+U32+W32+Y32+AA32+AG32+AC32+AE32 -> 5875718 | AJ32: =ROUND(AI32/C32,4)-1 -> -0.0084 | AK32: =H32+J32+L32+N32+P32+R32+T32+V32+X32+Z32+AB32+AH32+AD32+AF32 -> 5896776 | AL32: =ROUND(AK32/AI32-1,4) -> 0.0036
A33: Property Insurance | B33: 2110090 | C33: 1981658 | D33: =ROUND(C33/B33-1,4) -> -0.0609 | E33: 2096411 | F33: =ROUND(E33/C33-1,4) -> 0.0579 | G33: =C33 -> 1981658 | H33: =G33 -> 1981658 | I33: =M200OPR!R58 -> 35656 | J33: =M200OPR!T58 -> 39501 | K33: =M101INF!S58 -> 0 | L33: =M101INF!V58 -> 0 | AC33: 0 | AD33: 0 | AE33: 0 | AF33: 0 | AG33: 0 | AH33: 0 | AI33: =G33+I33+K33+M33+O33+Q33+S33+U33+W33+Y33+AA33+AG33+AC33+AE33 -> 2017314 | AJ33: =ROUND(AI33/C33,4)-1 -> 0.018 | AK33: =H33+J33+L33+N33+P33+R33+T33+V33+X33+Z33+AB33+AH33+AD33+AF33 -> 2021159 | AL33: =ROUND(AK33/AI33-1,4) -> 0.0019
A34: Postage/Communications | B34: 9132685 | C34: 13152322 | D34: =ROUND(C34/B34-1,4) -> 0.4401 | E34: 15645874 | F34: =ROUND(E34/C34-1,4) -> 0.1896 | G34: =C34 -> 13152322 | H34: =G34 -> 13152322 | I34: =M200OPR!R68 -> -109899 | J34: =M200OPR!T68 -> -63156 | K34: =M101INF!S68 -> 0 | L34: =M101INF!V68 -> 0 | AC34: 0 | AD34: 0 | AE34: 0 | AF34: 0 | AG34: 0 | AH34: 0 | AI34: =G34+I34+K34+M34+O34+Q34+S34+U34+W34+Y34+AA34+AG34+AC34+AE34 -> 13042423 | AJ34: =ROUND(AI34/C34,4)-1 -> -0.0084 | AK34: =H34+J34+L34+N34+P34+R34+T34+V34+X34+Z34+AB34+AH34+AD34+AF34 -> 13089166 | AL34: =ROUND(AK34/AI34-1,4) -> 0.0036
A35: Printing/Binding | B35: 4744863 | C35: 3217410 | D35: =ROUND(C35/B35-1,4) -> -0.3219 | E35: 3570599 | F35: =ROUND(E35/C35-1,4) -> 0.1098 | G35: =C35 -> 3217410 | H35: =G35 -> 3217410 | I35: =M200OPR!R69 -> -26885 | J35: =M200OPR!T69 -> -15450 | K35: =M101INF!S69 -> 0 | L35: =M101INF!V69 -> 0 | AC35: 0 | AD35: 0 | AE35: 0 | AF35: 0 | AG35: 0 | AH35: 0 | AI35: =G35+I35+K35+M35+O35+Q35+S35+U35+W35+Y35+AA35+AG35+AC35+AE35 -> 3190525 | AJ35: =ROUND(AI35/C35,4)-1 -> -0.0084 | AK35: =H35+J35+L35+N35+P35+R35+T35+V35+X35+Z35+AB35+AH35+AD35+AF35 -> 3201960 | AL35: =ROUND(AK35/AI35-1,4) -> 0.0036
A36: Instructional Supplies | B36: 50790482 | C36: 70944435 | D36: =ROUND(C36/B36-1,4) -> 0.3968 | E36: 43758545 | F36: =ROUND(E36/C36-1,4) -> -0.3832 | G36: =C36 -> 70944435 | H36: =G36 -> 70944435 | I36: =M200OPR!R63 -> -590197 | J36: =M200OPR!T63 -> -338031 | K36: =M101INF!S63 -> 0 | L36: =M101INF!V63 -> 0 | AC36: 0 | AD36: 0 | AE36: 0 | AF36: 0 | AG36: 0 | AH36: 0 | AI36: =G36+I36+K36+M36+O36+Q36+S36+U36+W36+Y36+AA36+AG36+AC36+AE36 -> 70354238 | AJ36: =ROUND(AI36/C36,4)-1 -> -0.0083 | AK36: =H36+J36+L36+N36+P36+R36+T36+V36+X36+Z36+AB36+AH36+AD36+AF36 -> 70606404 | AL36: =ROUND(AK36/AI36-1,4) -> 0.0036
A37: Instructional Computer Software | B37: 4542022 | C37: 7384984 | D37: =ROUND(C37/B37-1,4) -> 0.6259 | E37: 12090009 | F37: =ROUND(E37/C37-1,4) -> 0.6371 | G37: =C37 -> 7384984 | H37: =G37 -> 7384984 | I37: =M200OPR!R64 -> -61440 | J37: =M200OPR!T64 -> -35191 | K37: =M101INF!S64 -> 0 | L37: =M101INF!V64 -> 0 | AC37: 0 | AD37: 0 | AE37: 0 | AF37: 0 | AG37: 0 | AH37: 0 | AI37: =G37+I37+K37+M37+O37+Q37+S37+U37+W37+Y37+AA37+AG37+AC37+AE37 -> 7323544 | AJ37: =ROUND(AI37/C37,4)-1 -> -0.0083 | AK37: =H37+J37+L37+N37+P37+R37+T37+V37+X37+Z37+AB37+AH37+AD37+AF37 -> 7349793 | AL37: =ROUND(AK37/AI37-1,4) -> 0.0036
A38: Other Supplies | B38: 17719581 | C38: 16515016 | D38: =ROUND(C38/B38-1,4) -> -0.068 | E38: 12943249 | F38: =ROUND(E38/C38-1,4) -> -0.2163 | G38: =C38 -> 16515016 | H38: =G38 -> 16515016 | I38: =M200OPR!R65 -> -137401 | J38: =M200OPR!T65 -> -78700 | K38: =M101INF!S65 -> 0 | L38: =M101INF!V65 -> 0 | AC38: 0 | AD38: 0 | AE38: 0 | AF38: 0 | AG38: 0 | AH38: 0 | AI38: =G38+I38+K38+M38+O38+Q38+S38+U38+W38+Y38+AA38+AG38+AC38+AE38 -> 16377615 | AJ38: =ROUND(AI38/C38,4)-1 -> -0.0083 | AK38: =H38+J38+L38+N38+P38+R38+T38+V38+X38+Z38+AB38+AH38+AD38+AF38 -> 16436316 | AL38: =ROUND(AK38/AI38-1,4) -> 0.0036
A39: Other Fuel | B39: 3147423 | C39: 2531857 | D39: =ROUND(C39/B39-1,4) -> -0.1956 | E39: 2598274 | F39: =ROUND(E39/C39-1,4) -> 0.0262 | G39: =C39 -> 2531857 | H39: =G39 -> 2531857 | I39: =M200OPR!R70 -> -21157 | J39: =M200OPR!T70 -> -12158 | K39: =M101INF!S70 -> 0 | L39: =M101INF!V70 -> 0 | AC39: 0 | AD39: 0 | AE39: 0 | AF39: 0 | AG39: 0 | AH39: 0 | AI39: =G39+I39+K39+M39+O39+Q39+S39+U39+W39+Y39+AA39+AG39+AC39+AE39 -> 2510700 | AJ39: =ROUND(AI39/C39,4)-1 -> -0.0084 | AK39: =H39+J39+L39+N39+P39+R39+T39+V39+X39+Z39+AB39+AH39+AD39+AF39 -> 2519699 | AL39: =ROUND(AK39/AI39-1,4) -> 0.0036
A40: Staff Travel/Training | B40: 5086485 | C40: 3539980 | D40: =ROUND(C40/B40-1,4) -> -0.304 | E40: 3252815 | F40: =ROUND(E40/C40-1,4) -> -0.0811 | G40: =C40 -> 3539980 | H40: =G40 -> 3539980 | I40: =M200OPR!R71 -> -29582 | J40: =M200OPR!T71 -> -17001 | K40: =M101INF!S71 -> 0 | L40: =M101INF!V71 -> 0 | AC40: 0 | AD40: 0 | AE40: 0 | AF40: 0 | AG40: 0 | AH40: 0 | AI40: =G40+I40+K40+M40+O40+Q40+S40+U40+W40+Y40+AA40+AG40+AC40+AE40 -> 3510398 | AJ40: =ROUND(AI40/C40,4)-1 -> -0.0084 | AK40: =H40+J40+L40+N40+P40+R40+T40+V40+X40+Z40+AB40+AH40+AD40+AF40 -> 3522979 | AL40: =ROUND(AK40/AI40-1,4) -> 0.0036
A41: All Other | B41: 12417407 | C41: =9226066+492955 -> 9719021 | D41: =ROUND(C41/B41-1,4) -> -0.2173 | E41: =14087021+505890 -> 14592911 | F41: =ROUND(E41/C41-1,4) -> 0.5015 | G41: =C41 -> 9719021 | H41: =G41 -> 9719021 | I41: =M200OPR!R72 -> -81212 | J41: =M200OPR!T72 -> -46671 | K41: =M101INF!S72 -> 0 | L41: =M101INF!V72 -> 0 | AC41: 0 | AD41: 0 | AE41: 0 | AF41: 0 | AG41: 0 | AH41: 0 | AI41: =G41+I41+K41+M41+O41+Q41+S41+U41+W41+Y41+AA41+AG41+AC41+AE41 -> 9637809 | AJ41: =ROUND(AI41/C41,4)-1 -> -0.0084 | AK41: =H41+J41+L41+N41+P41+R41+T41+V41+X41+Z41+AB41+AH41+AD41+AF41 -> 9672350 | AL41: =ROUND(AK41/AI41-1,4) -> 0.0036
A42: Facility Leasing/Rental | B42: 7564852 | C42: 8531546 | D42: =ROUND(C42/B42-1,4) -> 0.1278 | E42: 8889492 | F42: =ROUND(E42/C42-1,4) -> 0.042 | G42: =C42 -> 8531546 | H42: =G42 -> 8531546 | AC42: 0 | AD42: 0 | AE42: 0 | AF42: 0 | AG42: 0 | AH42: 0 | AI42: =G42+I42+K42+M42+O42+Q42+S42+U42+W42+Y42+AA42+AG42+AC42+AE42 -> 8531546 | AJ42: =ROUND(AI42/C42,4)-1 -> 0 | AK42: =H42+J42+L42+N42+P42+R42+T42+V42+X42+Z42+AB42+AH42+AD42+AF42 -> 8531546 | AL42: =ROUND(AK42/AI42-1,4) -> 0
A43: 26th Special Session Reduction/ 2011-13 Bud Reduction | B43: -27626901 | C43: 0 | D43: =ROUND(C43/B43-1,4) -> -1 | F43: =ROUND(E43/C43-1,4) -> #DIV/0! | G43: 0 | H43: =G43 -> 0 | W43: =(-121032912+111500000)-42520000 -> -52052912 | X43: =(-117150960+111500000)-42732000 -> -48382960 | AC43: 0 | AD43: 0 | AE43: 0 | AF43: 0 | AG43: 0 | AH43: 0 | AI43: =G43+I43+K43+M43+O43+Q43+S43+U43+W43+Y43+AA43+AG43+AC43+AE43 -> -52052912 | AJ43: =ROUND(AI43/C43,4)-1 -> #DIV/0! | AK43: =H43+J43+L43+N43+P43+R43+T43+V43+X43+Z43+AB43+AH43+AD43+AF43 -> -48382960 | AL43: =ROUND(AK43/AI43-1,4) -> -0.0705
A44: To balance to district expend | B44: 0 | C44: 0 | D44: =ROUND(C44/B44-1,4) -> #DIV/0! | E44: 11513368 | F44: =ROUND(E44/C44-1,4) -> #DIV/0! | G44: 0 | H44: =G44 -> 0 | AC44: 0 | AD44: 0 | AE44: 0 | AF44: 0 | AG44: 0 | AH44: 0 | AI44: =G44+I44+K44+M44+O44+Q44+S44+U44+W44+Y44+AA44+AG44+AC44+AE44 -> 0 | AJ44: =ROUND(AI44/C44,4)-1 -> #DIV/0! | AK44: =H44+J44+L44+N44+P44+R44+T44+V44+X44+Z44+AB44+AH44+AD44+AF44 -> 0 | AL44: =ROUND(AK44/AI44-1,4) -> #DIV/0!
A45: Charter School Fees/Management Fees | B45: 0 | C45: =3984106+627653 -> 4611759 | D45: =ROUND(C45/B45-1,4) -> #DIV/0! | E45: =5646485+681578 -> 6328063 | F45: =ROUND(E45/C45-1,4) -> 0.3722 | G45: =C45 -> 4611759 | H45: =G45 -> 4611759 | AC45: 0 | AD45: 0 | AE45: 0 | AF45: 0 | AG45: 0 | AH45: 0 | AI45: =G45+I45+K45+M45+O45+Q45+S45+U45+W45+Y45+AA45+AG45+AC45+AE45 -> 4611759 | AJ45: =ROUND(AI45/C45,4)-1 -> 0 | AK45: =H45+J45+L45+N45+P45+R45+T45+V45+X45+Z45+AB45+AH45+AD45+AF45 -> 4611759 | AL45: =ROUND(AK45/AI45-1,4) -> 0
A46: Nat'l School Lunch Prog State Match | B46: 588732 | C46: 588732 | D46: =ROUND(C46/B46-1,4) -> 0 | E46: 588732 | F46: =ROUND(E46/C46-1,4) -> 0 | G46: =E46 -> 588732 | H46: =G46 -> 588732 | AC46: 0 | AD46: 0 | AE46: 0 | AF46: 0 | AG46: 0 | AH46: 0 | AI46: =G46+I46+K46+M46+O46+Q46+S46+U46+W46+Y46+AA46+AG46+AC46+AE46 -> 588732 | AJ46: =ROUND(AI46/C46,4)-1 -> 0 | AK46: =H46+J46+L46+N46+P46+R46+T46+V46+X46+Z46+AB46+AH46+AD46+AF46 -> 588732 | AL46: =ROUND(AK46/AI46-1,4) -> 0
A47: TOTAL OPERATING | B47: =SUM(B24:B46) -> 372977282 | C47: =SUM(C24:C46) -> 368286245 | D47: =ROUND(C47/B47-1,4) -> -0.0126 | E47: =SUM(E24:E46) -> 391669365 | F47: =ROUND(E47/C47-1,4) -> 0.0635 | G47: =SUM(G24:G46) -> 368286245 | H47: =SUM(H24:H46) -> 368286245 | I47: =SUM(I24:I46) -> 414833 | J47: =SUM(J24:J46) -> 1462665 | K47: =SUM(K24:K46) -> 0 | L47: =SUM(L24:L46) -> 0 | M47: =SUM(M24:M46) -> 0 | N47: =SUM(N24:N46) -> 0 | ... AI47: =SUM(AI24:AI46) -> 316648166 | AJ47: =ROUND(AI47/C47-1,4) -> -0.1402 | AK47: =SUM(AK24:AK46) -> 321365950 | AL47: =ROUND(AK47/AI47-1,4) -> 0.0149
A48: EQUIPMENT
A49: Pupil Transportation | B49: 5255992 | C49: 12421609 | D49: =ROUND(C49/B49-1,4) -> 1.3633 | E49: 2773528 | F49: =ROUND(E49/C49-1,4) -> -0.7767 | G49: 0 | H49: 0 | I49: =M200EQP!S16 -> -103341 | J49: =M200EQP!U16 -> -59190 | Y49: =$C49 -> 12421609 | Z49: =$C49 -> 12421609 | AC49: 0 | AD49: 0 | AE49: 0 | AF49: 0 | AG49: 0 | AH49: 0 | AI49: =G49+I49+K49+M49+O49+Q49+S49+U49+W49+Y49+AA49+AG49+AC49+AE49 -> 12318268 | AJ49: =ROUND(AI49/C49,4)-1 -> -0.0083 | AK49: =H49+J49+L49+N49+P49+R49+T49+V49+X49+Z49+AB49+AH49+AD49+AF49 -> 12362419 | AL49: =ROUND(AK49/AI49-1,4) -> 0.0036
A50: Pupil Transportation-Capital Lease | B50: 1995000 | C50: 870000 | D50: =ROUND(C50/B50-1,4) -> -0.5639 | E50: 0 | F50: =ROUND(E50/C50-1,4) -> -1 | G50: 0 | H50: =G50 -> 0 | Y50: =C50 -> 870000 | Z50: =Y50 -> 870000 | AC50: 0 | AD50: 0 | AE50: 0 | AF50: 0 | AG50: 0 | AH50: 0 | AI50: =G50+I50+K50+M50+O50+Q50+S50+U50+W50+Y50+AA50+AG50+AC50+AE50 -> 870000 | AJ50: =ROUND(AI50/C50,4)-1 -> 0 | AK50: =H50+J50+L50+N50+P50+R50+T50+V50+X50+Z50+AB50+AH50+AD50+AF50 -> 870000 | AL50: =ROUND(AK50/AI50-1,4) -> 0
A51: Instructional Equipment | B51: 3053548 | C51: 2095024 | D51: =ROUND(C51/B51-1,4) -> -0.3139 | E51: 5176561 | F51: =ROUND(E51/C51-1,4) -> 1.4709 | G51: 0 | H51: 0 | I51: =M200EQP!S17 -> -17429 | J51: =M200EQP!U17 -> -9966 | Y51: =$C51 -> 2095024 | Z51: =$C51 -> 2095024 | AC51: 0 | AD51: 0 | AE51: 0 | AF51: 0 | AG51: 0 | AH51: 0 | AI51: =G51+I51+K51+M51+O51+Q51+S51+U51+W51+Y51+AA51+AG51+AC51+AE51 -> 2077595 | AJ51: =ROUND(AI51/C51,4)-1 -> -0.0083 | AK51: =H51+J51+L51+N51+P51+R51+T51+V51+X51+Z51+AB51+AH51+AD51+AF51 -> 2085058 | AL51: =ROUND(AK51/AI51-1,4) -> 0.0036
A52: Instructional Hardware | B52: 1020155 | C52: 46734 | D52: =ROUND(C52/B52-1,4) -> -0.9542 | E52: 212200 | F52: =ROUND(E52/C52-1,4) -> 3.5406 | G52: 0 | H52: 0 | I52: =M200EQP!S18 -> -389 | J52: =M200EQP!U18 -> -234 | Y52: =$C52 -> 46734 | Z52: =$C52 -> 46734 | AC52: 0 | AD52: 0 | AE52: 0 | AF52: 0 | AG52: 0 | AH52: 0 | AI52: =G52+I52+K52+M52+O52+Q52+S52+U52+W52+Y52+AA52+AG52+AC52+AE52 -> 46345 | AJ52: =ROUND(AI52/C52,4)-1 -> -0.0083 | AK52: =H52+J52+L52+N52+P52+R52+T52+V52+X52+Z52+AB52+AH52+AD52 -> 46500 | AL52: =ROUND(AK52/AI52-1,4) -> 0.0033
A53: Computer Hardware | C53: 1411876 | D53: =ROUND(C53/B53-1,4) -> #DIV/0! | E53: 6247090 | F53: =ROUND(E53/C53-1,4) -> 3.4247 | G53: 0 | H53: 0 | Y53: =$C53 -> 1411876 | Z53: =$C53 -> 1411876 | AC53: 0 | AD53: 0 | AE53: 0 | AF53: 0 | AG53: 0 | AH53: 0 | AI53: =G53+I53+K53+M53+O53+Q53+S53+U53+W53+Y53+AA53+AG53+AC53 -> 1411876 | AJ53: =ROUND(AI53/C53,4)-1 -> 0 | AK53: =H53+J53+L53+N53+P53+R53+T53+V53+X53+Z53+AB53+AH53+AD53+AF53 -> 1411876 | AL53: =ROUND(AK53/AI53-1,4) -> 0
A54: Computer hardware - Capital Lease | C54: 117889 | D54: =ROUND(C54/B54-1,4) -> #DIV/0! | E54: 121612 | F54: =ROUND(E54/C54-1,4) -> 0.0316 | G54: 0 | H54: 0 | Y54: =$C54 -> 117889 | Z54: =$C54 -> 117889 | AC54: 0 | AD54: 0 | AE54: 0 | AF54: 0 | AG54: 0 | AH54: 0 | AI54: =G54+I54+K54+M54+O54+Q54+S54+U54+W54+Y54+AA54+AG54+AC54 -> 117889 | AJ54: =ROUND(AI54/C54,4)-1 -> 0 | AK54: =H54+J54+L54+N54+P54+R54+T54+V54+X54+Z54+AB54+AH54+AD54+AF54 -> 117889 | AL54: =ROUND(AK54/AI54-1,4) -> 0
A55: All Other Equipment | B55: 5809066 | C55: 3582606 | D55: =ROUND(C55/B55-1,4) -> -0.3833 | E55: 3311490 | F55: =ROUND(E55/C55-1,4) -> -0.0757 | G55: 0 | H55: 0 | I55: =M200EQP!S19 -> -29805 | J55: =M200EQP!U19 -> -17078 | Y55: =$C55 -> 3582606 | Z55: =$C55 -> 3582606 | AC55: 0 | AD55: 0 | AE55: 0 | AF55: 0 | AG55: 0 | AH55: 0 | AI55: =G55+I55+K55+M55+O55+Q55+S55+U55+W55+Y55+AA55+AG55+AC55 -> 3552801 | AJ55: =ROUND(AI55/C55,4)-1 -> -0.0083 | AK55: =H55+J55+L55+N55+P55+R55+T55+V55+X55+Z55+AB55+AH55+AD55+AF55 -> 3565528 | AL55: =ROUND(AK55/AI55-1,4) -> 0.0036
A56: All Other Equipment-Capital Lease | B56: 298516 | C56: 130074 | D56: =ROUND(C56/B56-1,4) -> -0.5643 | E56: 41880 | F56: =ROUND(E56/C56-1,4) -> -0.678 | G56: 0 | H56: =G56 -> 0 | Y56: =$C56 -> 130074 | Z56: =$C56 -> 130074 | AC56: 0 | AD56: 0 | AE56: 0 | AF56: 0 | AG56: 0 | AH56: 0 | AI56: =G56+I56+K56+M56+O56+Q56+S56+U56+W56+Y56+AA56+AG56+AC56 -> 130074 | AJ56: =ROUND(AI56/C56,4)-1 -> 0 | AK56: =H56+J56+L56+N56+P56+R56+T56+V56+X56+Z56+AB56+AH56+AD56+AF56 -> 130074 | AL56: =ROUND(AK56/AI56-1,4) -> 0
A57: TOTAL EQUIPMENT | B57: =SUM(B49:B56) -> 17432277 | C57: =SUM(C49:C56) -> 20675812 | D57: =ROUND(C57/B57-1,4) -> 0.1861 | E57: =SUM(E49:E56) -> 17884361 | F57: =ROUND(E57/C57-1,4) -> -0.135 | G57: =SUM(G49:G56) -> 0 | H57: =SUM(H49:H56) -> 0 | I57: =SUM(I49:I56) -> -150964 | J57: =SUM(J49:J56) -> -86468 | K57: =SUM(K49:K56) -> 0 | L57: =SUM(L49:L56) -> 0 | M57: =SUM(M49:M56) -> 0 | N57: =SUM(N49:N56) -> 0 | ... AI57: =SUM(AI49:AI56) -> 20524848 | AJ57: =ROUND(AI57/C57-1,4) -> -0.0073 | AK57: =SUM(AK49:AK56) -> 20589344 | AL57: =ROUND(AK57/AI57-1,4) -> 0.0031
A58: SUBTOTAL EXP | B58: =B21+B47+B57 -> 2999749861 | C58: =C21+C47+C57 -> 3009231136 | D58: =ROUND(C58/B58-1,4) -> 0.0032 | E58: =E21+E47+E57 -> 3045516703 | F58: =ROUND(E58/C58-1,4) -> 0.0121 | G58: =G21+G47+G57 -> 3061157139 | H58: =H21+H47+H57 -> 3108798595 | I58: =I21+I47+I57 -> -2900343.3 | J58: =J21+J47+J57 -> 5318235.6 | K58: =K21+K47+K57 -> 0 | L58: =L21+L47+L57 -> 0 | M58: =M21+M47+M57 -> 15761042 | N58: =N21+N47+N57 -> 16116773 | ... AI58: =AI21+AI47+AI57 -> 2.8855545e+09 | AJ58: =ROUND(AI58/C58-1,4) -> -0.0411 | AK58: =AK21+AK47+AK57 -> 2.9420407e+09 | AL58: =ROUND(AK58/AI58-1,4) -> 0.0196
A59: ADJUSTMENTS
A60: Transfer of Funds to State Spec Ed | B60: 23415652 | C60: =19397308-69149 -> 19328159 | D60: =ROUND(C60/B60-1,4) -> -0.1746 | E60: =15518220 -> 15518220 | F60: =ROUND(E60/C60-1,4) -> -0.1971 | G60: =C60 -> 19328159 | H60: =G60 -> 19328159 | AI60: =G60+I60+K60+M60+O60+Q60+S60+U60+W60+Y60+AA60+AG60+AC60+AE60 -> 19328159 | AJ60: =ROUND(AI60/C60,4)-1 -> 0 | AK60: =H60+J60+L60+N60+P60+R60+T60+V60+X60+Z60+AB60+AH60+AD60+AF60 -> 19328159 | AL60: =ROUND(AK60/AI60-1,4) -> 0
A61: Adult Education Expense | B61: 21170456 | C61: 21170456 | D61: =ROUND(C61/B61-1,4) -> 0 | E61: 22673833 | F61: =ROUND(E61/C61-1,4) -> 0.071 | G61: ='Adult Ed'!G5 -> 22918550 | H61: ='Adult Ed'!H5 -> 23376921 | I61: ='Adult Ed'!I5 -> -4600850 | J61: ='Adult Ed'!J5 -> -4255153.5 | M61: ='Adult Ed'!K5 -> 108428 | N61: ='Adult Ed'!L5 -> 113413 | O61: ='Adult Ed'!M5 -> -460653 | P61: ='Adult Ed'!N5 -> -480880 | Q61: ='Adult Ed'!O5 -> 0 | R61: ='Adult Ed'!P5 -> 0 | S61: ='Adult Ed'!Q5 -> -953518 | T61: ='Adult Ed'!R5 -> -995385 | AI61: =G61+I61+K61+M61+O61+Q61+S61+U61+W61+Y61+AA61+AG61+AC61+AE61 -> 17011957 | AJ61: =ROUND(AI61/C61,4)-1 -> -0.1964 | AK61: =H61+J61+L61+N61+P61+R61+T61+V61+X61+Z61+AB61+AH61+AD61+AF61 -> 17758916 | AL61: =ROUND(AK61/AI61-1,4) -> 0.0439
A62: Special Education Adjustment | B62: 0 | D62: =ROUND(C62/B62-1,4) -> #DIV/0! | F62: =ROUND(E62/C62-1,4) -> #DIV/0! | G62: =C62 -> 0 | H62: =G62 -> 0 | U62: =-U89 -> 8798548 | V62: =-V89 -> 8396675 | AI62: =G62+I62+K62+M62+O62+Q62+S62+U62+W62+Y62+AA62+AG62+AC62+AE62 -> 8798548 | AJ62: =ROUND(AI62/C62,4)-1 -> #DIV/0! | AK62: =H62+J62+L62+N62+P62+R62+T62+V62+X62+Z62+AB62+AH62+AD62+AF62 -> 8396675 | AL62: =ROUND(AK62/AI62-1,4) -> -0.0457
A63: charter school fees | B63: 0 | C63: 398722 | D63: =ROUND(C63/B63-1,4) -> #DIV/0! | F63: =ROUND(E63/C63-1,4) -> -1 | G63: =C63 -> 398722 | H63: =G63 -> 398722 | U63: =-U90 -> 0 | V63: =-V90 -> 0 | AI63: =G63+I63+K63+M63+O63+Q63+S63+U63+W63+Y63+AA63+AG63+AC63+AE63 -> 398722 | AJ63: =ROUND(AI63/C63,4)-1 -> 0 | AK63: =H63+J63+L63+N63+P63+R63+T63+V63+X63+Z63+AB63+AH63+AD63+AF63 -> 398722 | AL63: =ROUND(AK63/AI63-1,4) -> 0
A64: prior year adjustments | B64: 0 | C64: =1915583 -> 1915583 | D64: =ROUND(C64/B64-1,4) -> #DIV/0! | F64: =ROUND(E64/C64-1,4) -> -1 | G64: 0 | H64: =G64 -> 0 | U64: =-U91 -> 0 | V64: =-V91 -> 0 | AI64: =G64+I64+K64+M64+O64+Q64+S64+U64+W64+Y64+AA64+AG64+AC64+AE64 -> 0 | AJ64: =ROUND(AI64/C64,4)-1 -> -1 | AK64: =H64+J64+L64+N64+P64+R64+T64+V64+X64+Z64+AB64+AH64+AD64+AF64 -> 0 | AL64: =ROUND(AK64/AI64-1,4) -> #DIV/0!
A65: NRS Conversion | B65: 3615476 | C65: =6411917 -> 6411917 | D65: =ROUND(C65/B65-1,4) -> 0.7735 | E65: 7988911 | F65: =ROUND(E65/C65-1,4) -> 0.2459 | G65: 0 | H65: =G65 -> 0 | AI65: =G65+I65+K65+M65+O65+Q65+S65+U65+W65+Y65+AA65+AG65+AC65+AE65 -> 0 | AJ65: =ROUND(AI65/C65,4)-1 -> -1 | AK65: =H65+J65+L65+N65+P65+R65+T65+V65+X65+Z65+AB65+AH65+AD65+AF65 -> 0 | AL65: =ROUND(AK65/AI65-1,4) -> #DIV/0!
A66: Other Obligations | B66: 0 | C66: =5421341+3527237+2341589+122930141 -> 134220308 | D66: =ROUND(C66/B66-1,4) -> #DIV/0! | E66: =45610113+3143328-5120204 -> 43633237 | F66: =ROUND(E66/C66-1,4) -> -0.6749 | G66: 0 | H66: =G66 -> 0 | AI66: =G66+I66+K66+M66+O66+Q66+S66+U66+W66+Y66+AA66+AG66+AC66+AE66 -> 0 | AJ66: =ROUND(AI66/C66,4)-1 -> -1 | AK66: =H66+J66+L66+N66+P66+R66+T66+V66+X66+Z66+AB66+AH66+AD66+AF66 -> 0 | AL66: =ROUND(AK66/AI66-1,4) -> #DIV/0!
A67: TOTAL ADJUSTMENTS | B67: =SUM(B60:B66) -> 48201584 | C67: =SUM(C60:C66) -> 183445145 | D67: =ROUND(C67/B67-1,4) -> 2.8058 | E67: =SUM(E60:E66) -> 89814201 | F67: =ROUND(E67/C67-1,4) -> -0.5104 | G67: =SUM(G60:G66) -> 42645431 | H67: =SUM(H60:H66) -> 43103802 | I67: =SUM(I60:I66) -> -4600850 | J67: =SUM(J60:J66) -> -4255153.5 | K67: =SUM(K60:K66) -> 0 | L67: =SUM(L60:L66) -> 0 | M67: =SUM(M60:M66) -> 108428 | N67: =SUM(N60:N66) -> 113413 | ... AI67: =SUM(AI60:AI66) -> 45537386 | AJ67: =ROUND(AI67/C67-1,4) -> -0.7518 | AK67: =SUM(AK60:AK66) -> 45882472 | AL67: =ROUND(AK67/AI67-1,4) -> 0.0076
A68: SUBTOTAL EXP | B68: =B58+B67 -> 3047951445 | C68: =C58+C67 -> 3192676281 | D68: =ROUND(C68/B68-1,4) -> 0.0475 | E68: =E58+E67 -> 3135330904 | F68: =ROUND(E68/C68-1,4) -> -0.018 | G68: =G58+G67 -> 3103802570 | H68: =H58+H67 -> 3151902397 | I68: =I58+I67 -> -7501193.3 | J68: =J58+J67 -> 1063082.2 | K68: =K58+K67 -> 0 | L68: =L58+L67 -> 0 | M68: =M58+M67 -> 15869470 | N68: =N58+N67 -> 16230186 | ... AI68: =AI58+AI67 -> 2.9310919e+09 | AJ68: =ROUND(AI68/C68-1,4) -> -0.0819 | AK68: =AK58+AK67 -> 2.9879231e+09 | AL68: =ROUND(AK68/AI68-1,4) -> 0.0194
A69: ENDING FUND BAL | B69: 249763067 | C69: 162650614 | D69: =ROUND(C69/B69-1,4) -> -0.3488 | E69: 81986721 | F69: =ROUND(E69/C69-1,4) -> -0.4959 | G69: =E69 -> 81986721 | H69: =G69 -> 81986721 | AI69: =G69+I69+K69+M69+O69+Q69+S69+U69+W69+Y69+AA69+AG69+AE69+AC69 -> 81986721 | AJ69: =ROUND(AI69/C69,4)-1 -> -0.4959 | AK69: =(H69+L69+J69+N69+P69+R69+T69+V69+X69+Z69+AB69+AF69+AD69+AH69) -> 81986721 | AL69: =ROUND(AK69/AI69-1,4) -> 0
A70: TOTAL EXPENDITURES | B70: =SUM(B68:B69) -> 3297714512 | C70: =SUM(C68:C69) -> 3355326895 | D70: =ROUND(C70/B70-1,4) -> 0.0175 | E70: =SUM(E68:E69) -> 3217317625 | F70: =ROUND(E70/C70-1,4) -> -0.0411 | G70: =SUM(G68:G69) -> 3185789291 | H70: =SUM(H68:H69) -> 3233889118 | I70: =SUM(I68:I69) -> -7501193.3 | J70: =SUM(J68:J69) -> 1063082.2 | K70: =SUM(K68:K69) -> 0 | L70: =SUM(L68:L69) -> 0 | M70: =SUM(M68:M69) -> 15869470 | N70: =SUM(N68:N69) -> 16230186 | ... AI70: =SUM(AI68:AI69) -> 3.0130786e+09 | AJ70: =ROUND(AI70/C70-1,4) -> -0.102 | AK70: =SUM(AK68:AK69) -> 3.0699099e+09 | AL70: =ROUND(AK70/AI70-1,4) -> 0.0189
A71: LESS
A72: OPENING BALANCE | B72: -251791688 | C72: =-174620824 -> -174620824 | D72: =ROUND(C72/B72-1,4) -> -0.3065 | E72: =-C69 -> -162650614 | F72: =ROUND(E72/C72-1,4) -> -0.0685 | G72: =-E69 -> -81986721 | H72: =-G69 -> -81986721 | AI72: =G72+I72+K72+M72+O72+Q72+S72+U72+W72+Y72+AA72+AG72+AC72+AE72 -> -81986721 | AJ72: =ROUND(AI72/C72,4)-1 -> -0.5305 | AK72: =H72+J72+L72+N72+P72+R72+T72+V72+X72+Z72+AB72+AH72+AD72+AF72 -> -81986721 | AL72: =ROUND(AK72/AI72-1,4) -> 0
A73: FEDERAL REVENUE | B73: -7863361 | C73: -8499450 | D73: =ROUND(C73/B73-1,4) -> 0.0809 | E73: -7863361 | F73: =ROUND(E73/C73-1,4) -> -0.0748 | G73: =C73 -> -8499450 | H73: =G73 -> -8499450 | AI73: =G73+I73+K73+M73+O73+Q73+S73+U73+W73+Y73+AA73+AG73+AC73+AE73 -> -8499450 | AJ73: =ROUND(AI73/C73,4)-1 -> 0 | AK73: =H73+J73+L73+N73+P73+R73+T73+V73+X73+Z73+AB73+AH73+AD73+AF73 -> -8499450 | AL73: =ROUND(AK73/AI73-1,4) -> 0
A74: OTHER LOCAL REVENUE | B74: -94520861 | C74: =-13971748-46793755-19011812-172830-870000 -> -80820145 | D74: =ROUND(C74/B74-1,4) -> -0.1449 | E74: -94520861 | F74: =ROUND(E74/C74-1,4) -> 0.1695 | G74: =C74 -> -80820145 | H74: =G74 -> -80820145 | AI74: =G74+I74+K74+M74+O74+Q74+S74+U74+W74+Y74+AA74+AG74+AC74+AE74 -> -80820145 | AJ74: =ROUND(AI74/C74,4)-1 -> 0 | AK74: =H74+J74+L74+N74+P74+R74+T74+V74+X74+Z74+AB74+AH74+AD74+AF74 -> -80820145 | AL74: =ROUND(AK74/AI74-1,4) -> 0
A75: PSOPT 2/3 (PREVIOUSLY $.50) | B75: -506393209 | C75: =-528819032+3116527 -> -525702505 | D75: =ROUND(C75/B75-1,4) -> 0.0381 | E75: =-DSADATABASE!B52 -> -424127158 | F75: =ROUND(E75/C75-1,4) -> -0.1932 | G75: =-DSADATABASE!C52 -> -404866532 | H75: =-DSADATABASE!D52 -> -405863545 | AI75: =G75+I75+K75+M75+O75+Q75+S75+U75+W75+Y75+AA75+AG75+AC75+AE75 -> -404866532 | AJ75: =ROUND(AI75/C75,4)-1 -> -0.2299 | AK75: =H75+J75+L75+N75+P75+R75+T75+V75+X75+Z75+AB75+AH75+AD75+AF75 -> -405863545 | AL75: =ROUND(AK75/AI75-1,4) -> 0.0025
A76: GOVT SERVICES TAX | B76: -81402633 | C76: =-75725120 -> -75725120 | D76: =ROUND(C76/B76-1,4) -> -0.0697 | E76: -81402633 | F76: =ROUND(E76/C76-1,4) -> 0.075 | G76: =-68947722-3434059 -> -72381781 | H76: =G76 -> -72381781 | AI76: =G76+I76+K76+M76+O76+Q76+S76+U76+W76+Y76+AA76+AG76+AC76+AE76 -> -72381781 | AJ76: =ROUND(AI76/C76,4)-1 -> -0.0442 | AK76: =H76+J76+L76+N76+P76+R76+T76+V76+X76+Z76+AB76+AH76+AD76+AF76 -> -72381781 | AL76: =ROUND(AK76/AI76-1,4) -> 0
A77: FRANCHISE TAX | B77: -4113359 | C77: -3451000 | D77: =ROUND(C77/B77-1,4) -> -0.161 | E77: -4236760 | F77: =ROUND(E77/C77-1,4) -> 0.2277 | G77: =ROUND((C77*1.03)*1.03,0) -> -3661166 | H77: =ROUND(G77*1.03,0) -> -3771001 | AI77: =G77+I77+K77+M77+O77+Q77+S77+U77+W77+Y77+AA77+AG77+AC77+AE77 -> -3661166 | AJ77: =ROUND(AI77/C77,4)-1 -> 0.0609 | AK77: =H77+J77+L77+N77+P77+R77+T77+V77+X77+Z77+AB77+AH77+AD77+AF77 -> -3771001 | AL77: =ROUND(AK77/AI77-1,4) -> 0.03
A78: OBLIGATIONS | C78: =-111378250-14824313-5002705-3725350 -> -134930618 | D78: =ROUND(C78/B78-1,4) -> #DIV/0! | E78: =-95107316-4932204-3339497 -> -103379017 | F78: =ROUND(E78/C78-1,4) -> -0.2338 | G78: 0 | H78: =G78 -> 0 | AI78: =G78+I78+K78+M78+O78+Q78+S78+U78+W78+Y78+AA78+AG78+AC78+AE78 -> 0 | AJ78: =ROUND(AI78/C78,4)-1 -> -1 | AK78: =H78+J78+L78+N78+P78+R78+T78+V78+X78+Z78+AB78+AH78+AD78+AF78 -> 0 | AL78: =ROUND(AK78/AI78-1,4) -> #DIV/0!
A79: CHARTER SCHOOL ADJ | D79: =ROUND(C79/B79-1,4) -> #DIV/0! | F79: =ROUND(E79/C79-1,4) -> #DIV/0! | G79: =C79 -> 0 | H79: =G79 -> 0 | AI79: =G79+I79+K79+M79+O79+Q79+S79+U79+W79+Y79+AA79+AG79+AC79+AE79 -> 0 | AJ79: =ROUND(AI79/C79,4)-1 -> #DIV/0! | AK79: =H79+J79+L79+N79+P79+R79+T79+V79+X79+Z79+AB79+AH79+AD79+AF79 -> 0 | AL79: =ROUND(AK79/AI79-1,4) -> #DIV/0!
A80: ELEMENTARY COUNSELORS | D80: =ROUND(C80/B80-1,4) -> #DIV/0! | F80: =ROUND(E80/C80-1,4) -> #DIV/0! | G80: 0 | H80: =G80 -> 0 | AI80: =G80+I80+K80+M80+O80+Q80+S80+U80+W80+Y80+AA80+AG80+AC80+AE80 -> 0 | AJ80: =ROUND(AI80/C80,4)-1 -> #DIV/0! | AK80: =H80+J80+L80+N80+P80+R80+T80+V80+X80+Z80+AB80+AH80+AD80+AF80 -> 0 | AL80: =ROUND(AK80/AI80-1,4) -> #DIV/0!
A81: CERTIFIED COUNSELOR STIPEND | D81: =ROUND(C81/B81-1,4) -> #DIV/0! | F81: =ROUND(E81/C81-1,4) -> #DIV/0! | G81: 0 | H81: =G81 -> 0 | AI81: =G81+I81+K81+M81+O81+Q81+S81+U81+W81+Y81+AA81+AG81+AC81+AE81 -> 0 | AJ81: =ROUND(AI81/C81,4)-1 -> #DIV/0! | AK81: =H81+J81+L81+N81+P81+R81+T81+V81+X81+Z81+AB81+AH81+AD81+AF81 -> 0 | AL81: =ROUND(AK81/AI81-1,4) -> #DIV/0!
A82: GROUP INS SPEC APPROP | D82: =ROUND(C82/B82-1,4) -> #DIV/0! | F82: =ROUND(E82/C82-1,4) -> #DIV/0! | G82: =C82 -> 0 | H82: =G82 -> 0 | AI82: =G82+I82+K82+M82+O82+Q82+S82+U82+W82+Y82+AA82+AG82+AC82+AE82 -> 0 | AJ82: =ROUND(AI82/C82,4)-1 -> #DIV/0! | AK82: =H82+J82+L82+N82+P82+R82+T82+V82+X82+Z82+AB82+AH82+AD82+AF82 -> 0 | AL82: =ROUND(AK82/AI82-1,4) -> #DIV/0!
A83: RETIRED EMPL GROUP INS | D83: =ROUND(C83/B83-1,4) -> #DIV/0! | F83: =ROUND(E83/C83-1,4) -> #DIV/0! | G83: 0 | H83: 0 | I83: =-I19 -> 0 | J83: =-J19 -> 0 | AI83: =G83+I83+K83+M83+O83+Q83+S83+U83+W83+Y83+AA83+AG83+AC83+AE83 -> 0 | AJ83: =ROUND(AI83/C83,4)-1 -> #DIV/0! | AK83: =H83+J83+L83+N83+P83+R83+T83+V83+X83+Z83+AB83+AH83+AD83+AF83 -> 0 | AL83: =ROUND(AK83/AI83-1,4) -> #DIV/0!
A84: PRIOR FY SHORTFALL IN CURRENT FY | C84: -76582 | D84: =ROUND(C84/B84-1,4) -> #DIV/0! | F84: =ROUND(E84/C84-1,4) -> -1 | G84: =-G20 -> 0 | H84: =G84 -> 0 | AI84: =G84+I84+K84+M84+O84+Q84+S84+U84+W84+Y84+AA84+AG84+AC84+AE84 -> 0 | AJ84: =ROUND(AI84/C84,4)-1 -> -1 | AK84: =H84+J84+L84+N84+P84+R84+T84+V84+X84+Z84+AB84+AH84+AD84+AF84 -> 0 | AL84: =ROUND(AK84/AI84-1,4) -> #DIV/0!
A85: OTHER STATE SUPPORT | B85: -879943 | C85: =375034-1177807-128541 -> -931314 | D85: =ROUND(C85/B85-1,4) -> 0.0584 | E85: -879943 | F85: =ROUND(E85/C85-1,4) -> -0.0552 | G85: =C85 -> -931314 | H85: =G85 -> -931314 | AI85: =G85+I85+K85+M85+O85+Q85+S85+U85+W85+Y85+AA85+AG85+AC85+AE85 -> -931314 | AJ85: =ROUND(AI85/C85,4)-1 -> 0 | AK85: =H85+J85+L85+N85+P85+R85+T85+V85+X85+Z85+AB85+AH85+AD85+AF85 -> -931314 | AL85: =ROUND(AK85/AI85-1,4) -> 0
A86: STATE RESPONSIBILITY | B86: =SUM(B70:B85) -> 2350749458 | C86: =SUM(C70:C85) -> 2350569337 | D86: =ROUND(C86/B86-1,4) -> -0.0001 | E86: =SUM(E70:E85) -> 2338257278 | F86: =ROUND(E86/C86-1,4) -> -0.0052 | G86: =SUM(G70:G85) -> 2532642182 | H86: =SUM(H70:H85) -> 2579635161 | I86: =SUM(I70:I85) -> -7501193.3 | J86: =SUM(J70:J85) -> 1063082.2 | K86: =SUM(K70:K85) -> 0 | L86: =SUM(L70:L85) -> 0 | M86: =SUM(M70:M85) -> 15869470 | N86: =SUM(N70:N85) -> 16230186 | ... AI86: =SUM(AI70:AI85) -> 2.3599315e+09 | AJ86: =ROUND(AI86/C86-1,4) -> 0.004 | AK86: =SUM(AK70:AK85) -> 2.4156559e+09 | AL86: =ROUND(AK86/AI86-1,4) -> 0.0236
A87: LESS:
A88: ADULT EDUCATION | B88: -21170456 | C88: -21170456 | D88: =ROUND(C88/B88-1,4) -> 0 | E88: -22673833 | F88: =ROUND(E88/C88-1,4) -> 0.071 | G88: =-G61 -> -22918550 | H88: =-H61 -> -23376921 | I88: =-I61 -> 4600850 | J88: =-J61 -> 4255153.5 | K88: =-K61 -> 0 | L88: =-L61 -> 0 | M88: =-M61 -> -108428 | N88: =-N61 -> -113413 | ... AD88: =-AD61 -> 0 | AE88: 0 | AF88: 0 | AG88: =-AG61 -> 0 | AH88: =-AH61 -> 0 | AI88: =G88+I88+K88+M88+O88+Q88+S88+U88+W88+Y88+AA88+AG88+AC88+AE88 -> -17011957 | AJ88: =ROUND(AI88/C88,4)-1 -> -0.1964 | AK88: =H88+J88+L88+N88+P88+R88+T88+V88+X88+Z88+AB88+AH88+AD88+AF88 -> -17758916 | AL88: =ROUND(AK88/AI88-1,4) -> 0.0439
A89: SPECIAL EDUCATION | B89: -121252632 | C89: -121252632 | D89: =ROUND(C89/B89-1,4) -> 0 | E89: -121252632 | F89: =ROUND(E89/C89-1,4) -> 0 | G89: =ROUND((E89/E97*G97)*1.02,0) -> -123677685 | H89: =ROUND(G89*1.02,0) -> -126151239 | I89: =ROUND(G89/$G$97*$I$97+62,0) -> 170548 | J89: =ROUND(H89/$H$97*$J$97+2874,0) -> -274762 | M89: =(G89+I89)*M300SAL!D83 -> -731078.32 | N89: =(H89+J89)*M300SAL!G83 -> -749844.43 | O89: =ROUND((G89+I89+M89)*DSADATABASE!$J$28,0)-G89-I89-M89 -> 3105955.3 | P89: =ROUND((H89+J89+N89)*DSADATABASE!$J$28,0)-H89-J89-N89 -> 3179396.4 | Q89: =-ROUND((-G89-I89-O89-M89)/1.02,0)-G89-I89-O89-M89 -> 2375142 | R89: =-ROUND((-H89-J89-P89-N89)/1.02/1.02,0)-H89-J89-P89-N89 -> 4814933 | S89: =ROUND((G89+I89+M89+O89+Q89)*0.946925-(G89+I89+M89+O89+Q89),0) -> 6303034 | T89: =ROUND((H89+J89+N89+P89+R89)*0.946925-(H89+J89+N89+P89+R89),0) -> 6325559 | U89: =E89-G89-I89-O89-Q89-S89-M89 -> -8798548 | V89: =E89-H89-J89-P89-R89-T89-N89 -> -8396675 | W89: 0 | X89: 0 | Y89: 0 | Z89: 0 | AA89: 0 | AB89: 0 | AC89: 0 | AD89: 0 | AE89: 0 | AF89: 0 | AG89: 0 | AH89: 0 | AI89: =G89+I89+K89+M89+O89+Q89+S89+U89+W89+Y89+AA89+AG89+AC89+AE89 -> -121252632 | AJ89: =ROUND(AI89/C89,4)-1 -> 0 | AK89: =H89+J89+L89+N89+P89+R89+T89+V89+X89+Z89+AB89+AH89+AD89+AF89 -> -121252632 | AL89: =ROUND(AK89/AI89-1,4) -> 0
A90: SPECIAL TRANSPORTATION | B90: -170908 | C90: -128541 | D90: =ROUND(C90/B90-1,4) -> -0.2479 | E90: -170908 | F90: =ROUND(E90/C90-1,4) -> 0.3296 | G90: =C90 -> -128541 | H90: =G90 -> -128541 | AI90: =G90+I90+K90+M90+O90+Q90+S90+U90+W90+Y90+AA90+AG90+AC90+AE90 -> -128541 | AJ90: =ROUND(AI90/C90,4)-1 -> 0 | AK90: =H90+J90+L90+N90+P90+R90+T90+V90+X90+Z90+AB90+AH90+AD90+AF90 -> -128541 | AL90: =ROUND(AK90/AI90-1,4) -> 0
A91: SCHOOL LUNCH PROG MATCH | B91: -588732 | C91: -588732 | D91: =ROUND(C91/B91-1,4) -> 0 | E91: -588732 | F91: =ROUND(E91/C91-1,4) -> 0 | G91: =E91 -> -588732 | H91: =G91 -> -588732 | AI91: =G91+I91+K91+M91+O91+Q91+S91+U91+W91+Y91+AA91+AG91+AC91+AE91 -> -588732 | AJ91: =ROUND(AI91/C91,4)-1 -> 0 | AK91: =H91+J91+L91+N91+P91+R91+T91+V91+X91+Z91+AB91+AH91+AD91+AF91 -> -588732 | AL91: =ROUND(AK91/AI91-1,4) -> 0
A92: GROWTH INCREMENT | B92: 0 | C92: -631134 | D92: =ROUND(C92/B92-1,4) -> #DIV/0! | F92: =ROUND(E92/C92-1,4) -> -1 | G92: =E92 -> 0 | H92: =G92 -> 0 | AI92: =G92+I92+K92+M92+O92+Q92+S92+U92+W92+Y92+AA92+AG92+AC92+AE92 -> 0 | AJ92: =ROUND(AI92/C92,4)-1 -> -1 | AK92: =H92+J92+L92+N92+P92+R92+T92+V92+X92+Z92+AB92+AH92+AD92+AF92 -> 0 | AL92: =ROUND(AK92/AI92-1,4) -> #DIV/0!
A93: NON-TRADITIONAL STUDENT | B93: 0 | C93: -182317 | D93: =ROUND(C93/B93-1,4) -> #DIV/0! | F93: =ROUND(E93/C93-1,4) -> -1 | G93: =E93 -> 0 | H93: =G93 -> 0 | AI93: =G93+I93+K93+M93+O93+Q93+S93+U93+W93+Y93+AA93+AG93+AC93+AE93 -> 0 | AJ93: =ROUND(AI93/C93,4)-1 -> -1 | AK93: =H93+J93+L93+N93+P93+R93+T93+V93+X93+Z93+AB93+AH93+AD93+AF93 -> 0 | AL93: =ROUND(AK93/AI93-1,4) -> #DIV/0!
A94: NET PROCEEDS FROM MINES | B94: 0 | D94: =ROUND(C94/B94-1,4) -> #DIV/0! | F94: =ROUND(E94/C94-1,4) -> #DIV/0! | G94: =E94 -> 0 | H94: =G94 -> 0 | AI94: =G94+I94+K94+M94+O94+Q94+S94+U94+W94+Y94+AA94+AG94+AC94+AE94 -> 0 | AJ94: =ROUND(AI94/C94,4)-1 -> #DIV/0! | AK94: =H94+J94+L94+N94+P94+R94+T94+V94+X94+Z94+AB94+AH94+AD94+AF94 -> 0 | AL94: =ROUND(AK94/AI94-1,4) -> #DIV/0!
A95: TOTAL BASIC SUPP | B95: =SUM(B88:B94)+B86 -> 2207566730 | C95: =SUM(C88:C94)+C86 -> 2206615525 | D95: =ROUND(C95/B95-1,4) -> -0.0004 | E95: =SUM(E86:E94) -> 2193571173 | F95: =ROUND(E95/C95-1,4) -> -0.0059 | G95: =SUM(G88:G94)+G86 -> 2385328674 | H95: =SUM(H88:H94)+H86 -> 2429389728 | I95: =SUM(I88:I94)+I86 -> -2729795.3 | J95: =SUM(J88:J94)+J86 -> 5043473.6 | K95: =SUM(K88:K94)+K86 -> 0 | L95: =SUM(L88:L94)+L86 -> 0 | M95: =SUM(M88:M94)+M86 -> 15029964 | N95: =SUM(N88:N94)+N86 -> 15366929 | ... AI95: =SUM(AI88:AI94)+AI86 -> 2.2209496e+09 | AJ95: =ROUND(AI95/C95-1,4) -> 0.0065 | AK95: =SUM(AK88:AK94)+AK86 -> 2.2759271e+09 | AL95: =ROUND(AK95/AI95-1,4) -> 0.0248
A97: WEIGHTED ENROLLMENT | B97: 425270.2 | C97: =DSADATABASE!A4 -> 425527.2 | D97: =C97/B97-1 -> 0.00060432168 | E97: =DSADATABASE!B4 -> 422569.6 | F97: =ROUND(E97/C97-1,4) -> -0.007 | G97: =DSADATABASE!B4 -> 422569.6 | H97: =DSADATABASE!B4 -> 422569.6 | I97: =DSADATABASE!$C$4-DSADATABASE!$B$4 -> -582.5 | J97: =DSADATABASE!$D$4-DSADATABASE!$B$4 -> 930 | K97: =DSADATABASE!$C$4 -> 421987.1 | L97: =DSADATABASE!$D$4 -> 423499.6 | M97: =DSADATABASE!$C$4 -> 421987.1 | N97: =DSADATABASE!$D$4 -> 423499.6 | O97: =DSADATABASE!$C$4 -> 421987.1 | P97: =DSADATABASE!$D$4 -> 423499.6 | Q97: =DSADATABASE!$C$4 -> 421987.1 | R97: =DSADATABASE!$D$4 -> 423499.6 | S97: 0 | T97: 0 | U97: =DSADATABASE!$C$4 -> 421987.1 | V97: =DSADATABASE!$D$4 -> 423499.6 | W97: =DSADATABASE!$C$4 -> 421987.1 | X97: =DSADATABASE!$D$4 -> 423499.6 | Y97: =DSADATABASE!$C$4 -> 421987.1 | Z97: =DSADATABASE!$D$4 -> 423499.6 | AA97: 0 | AB97: 0 | AC97: 0 | AD97: 0 | AE97: 0 | AF97: 0 | AG97: 0 | AH97: 0 | AI97: =+G97+I97+S97+AA97+AG97+AC97+AE97 -> 421987.1 | AJ97: =ROUND(AI97/C97-1,4) -> -0.0083 | AK97: =+H97+J97+T97+AB97+AH97+AD97+AF97 -> 423499.6 | AL97: =ROUND(AK97/AI97-1,4) -> 0.0036
A99: BASIC SUPPORT PER PUPIL | B99: =ROUND(B95/B97,2) -> 5190.97 | C99: =ROUND(C95/C97,2) -> 5185.6 | D99: =ROUND(C99/B99-1,4) -> -0.001 | E99: =E95/E97 -> 5191.0293 | F99: =ROUND(E99/C99-1,4) -> 0.001 | G99: =ROUND(G95/G97,2) -> 5644.82 | H99: =ROUND(H95/H97,2) -> 5749.09 | I99: =ROUND(I95/I97,2) -> 4686.34 | J99: =ROUND(J95/J97,2) -> 5423.09 | K99: =ROUND(K95/K97,2) -> 0 | L99: =ROUND(L95/L97,2) -> 0 | M99: =ROUND(M95/M97,2) -> 35.62 | N99: =ROUND(N95/N97,2) -> 36.29 | ... AD99: =ROUND(AD95/AD97,2) -> #DIV/0! | AG99: =ROUND(AG95/AG97,2) -> #DIV/0! | AH99: =ROUND(AH95/AH97,2) -> #DIV/0! | AI99: =ROUND(AI95/AI97,0) -> 5263 | AJ99: =ROUND(AI99/C99-1,4) -> 0.0149 | AK99: =ROUND(AK95/AK97,0) -> 5374 | AL99: =ROUND(AK99/AI99-1,4) -> 0.0211
A101: CLASS SIZE REDUCTION-16* | B101: 142682929 | C101: =142682930 -> 142682930 | D101: =ROUND(C101/B101-1,4) -> 0 | E101: 144348993 | F101: =ROUND(E101/C101-1,4) -> 0.0117 | G101: =CSRBASESAL!F53-G116 -> 1.4687247e+08 | H101: =CSRBASESAL!H53-H116 -> 1.495171e+08 | I101: =CSRM200SAL!D64 -> 318915 | J101: =CSRM200SAL!G64 -> 1318467 | K101: 0 | L101: 0 | M101: =CSRM300SAL!D66-M116 -> 869006.1 | N101: =CSRM300SAL!G66-N116 -> 892199.06 | O101: =CSRE670SAL!D71-O116 -> -3334486 | P101: =CSRE670SAL!G71-P116 -> -3401178.2 | Q101: =CSRE671SAL!D69-Q116 -> 0.4529 | R101: =CSRE671SAL!G69-R116 -> -0.0912 | S101: ='CSRE601 SAL'!D69-DSASUMM!S116 -> -5512458.4 | T101: ='CSRE601 SAL'!G69-DSASUMM!T116 -> -5686982.3 | U101: 0 | V101: 0 | W101: 0 | X101: 0 | Y101: 0 | Z101: 0 | AA101: 0 | AB101: 0 | AC101: 0 | AD101: 0 | AE101: 0 | AF101: 0 | AG101: 0 | AH101: 0 | AI101: =G101+I101+K101+M101+O101+Q101+S101+U101+W101+Y101+AA101+AG101+AC101+AE101 -> 1.3921345e+08 | AJ101: =ROUND(AI101/C101,4)-1 -> -0.0243 | AK101: =H101+J101+L101+N101+P101+R101+T101+V101+X101+Z101+AB101+AH101+AD101+AF101 -> 1.4263961e+08 | AL101: =ROUND(AK101/AI101-1,4) -> 0.0246
A102: SPECIAL EDUCATION-15 | B102: 121252632 | C102: 121252632 | D102: =ROUND(C102/B102-1,4) -> 0 | E102: 121252632 | F102: =ROUND(E102/C102-1,4) -> 0 | G102: =G89*-1 -> 123677685 | H102: =H89*-1 -> 126151239 | I102: =-I89 -> -170548 | J102: =-J89 -> 274762 | K102: =-K89 -> 0 | L102: =-L89 -> 0 | M102: =-M89 -> 731078.32 | N102: =-N89 -> 749844.43 | O102: =-O89 -> -3105955.3 | P102: =-P89 -> -3179396.4 | ... AC102: =-AC89 -> 0 | AD102: 0 | AE102: 0 | AF102: 0 | AG102: =-AG89 -> 0 | AH102: =-AH89 -> 0 | AI102: =G102+I102+K102+M102+O102+Q102+S102+U102+W102+Y102+AA102+AG102+AC102+AE102 -> 121252632 | AJ102: =ROUND(AI102/C102,4)-1 -> 0 | AK102: =H102+J102+L102+N102+P102+R102+T102+V102+X102+Z102+AB102+AH102+AD102+AF102 -> 121252632 | AL102: =ROUND(AK102/AI102-1,4) -> 0
A103: SPEC UNITS/GIFTED & TALENT-33 | B103: 162571 | C103: 162566 | D103: =ROUND(C103/B103-1,4) -> 0 | E103: 167459 | F103: =ROUND(E103/C103-1,4) -> 0.0301 | G103: =ROUND(E103*1.02,0) -> 170808 | H103: =ROUND(G103*1.02,) -> 174224 | I103: =ROUND(G103/$G$97*($I$97+G97-E97),0) -> -235 | J103: =ROUND(H103/$H$97*($J$97+H97-E97),0) -> 383 | K103: 0 | L103: 0 | M103: =(G103+I103)*M300SAL!D83 -> 1009.6762 | N103: =(H103+J103)*M300SAL!G83 -> 1035.6104 | O103: =ROUND((G103+I103+M103)*DSADATABASE!$J$28,0)-G103-I103-M103 -> -4289.6762 | P103: =ROUND((H103+J103+N103)*DSADATABASE!$J$28,0)-H103-J103-N103 -> -4390.6104 | Q103: =-ROUND((-G103-I103-O103-M103)/1,0)-G103-I103-O103-M103 -> 0 | R103: =-ROUND((-H103-J103-P103-N103)/1/1,0)-H103-J103-P103-N103 -> 0 | S103: =ROUND((G103+I103+M103+O103+Q103)*0.946925-(G103+I103+M103+O103+Q103),0) -> -8879 | T103: =ROUND((H103+J103+N103+P103+R103)*0.946925-(H103+J103+N103+P103+R103),0) -> -9089 | AI103: =G103+I103+K103+M103+O103+Q103+S103+U103+W103+Y103+AA103+AG103+AC103+AE103 -> 158414 | AJ103: =ROUND(AI103/C103,4)-1 -> -0.0255 | AK103: =H103+J103+L103+N103+P103+R103+T103+V103+X103+Z103+AB103+AH103+AD103+AF103 -> 162163 | AL103: =ROUND(AK103/AI103-1,4) -> 0.0237
A104: ADULT HIGH SCHOOL DIPLOMA-78 | B104: 21170456 | C104: 21170456 | D104: =ROUND(C104/B104-1,4) -> 0 | E104: 22673833 | F104: =ROUND(E104/C104-1,4) -> 0.071 | G104: =-G88 -> 22918550 | H104: =-H88 -> 23376921 | I104: =-I88 -> -4600850 | J104: =-J88 -> -4255153.5 | K104: 0 | L104: 0 | M104: =-M88 -> 108428 | N104: =-N88 -> 113413 | O104: =-O88 -> -460653 | P104: =-P88 -> -480880 | Q104: =-Q88 -> 0 | R104: =-R88 -> 0 | S104: =-S88 -> -953518 | T104: =-T88 -> -995385 | ... AC104: =-AC88 -> 0 | AD104: 0 | AE104: 0 | AF104: 0 | AG104: =-AG88 -> 0 | AH104: =-AH88 -> 0 | AI104: =G104+I104+K104+M104+O104+Q104+S104+U104+W104+Y104+AA104+AG104+AC104+AE104 -> 17011957 | AJ104: =ROUND(AI104/C104,4)-1 -> -0.1964 | AK104: =H104+J104+L104+N104+P104+R104+T104+V104+X104+Z104+AB104+AH104+AD104+AF104 -> 17758916 | AL104: =ROUND(AK104/AI104-1,4) -> 0.0439
A105: SCHOOL LUNCH PROG MATCH-17 | B105: 588732 | C105: 588732 | D105: =ROUND(C105/B105-1,4) -> 0 | E105: 588732 | F105: =ROUND(E105/C105-1,4) -> 0 | G105: =E105 -> 588732 | H105: =E105 -> 588732 | I105: 0 | J105: 0 | K105: 0 | L105: 0 | M105: 0 | N105: 0 | O105: 0 | P105: 0 | Q105: 0 | R105: 0 | S105: 0 | T105: 0 | U105: 0 | V105: 0 | W105: 0 | X105: 0 | Y105: 0 | Z105: 0 | AA105: 0 | AB105: 0 | AC105: 0 | AD105: 0 | AE105: 0 | AF105: 0 | AG105: 0 | AH105: 0 | AI105: =G105+I105+K105+M105+O105+Q105+S105+U105+W105+Y105+AA105+AG105+AC105+AE105 -> 588732 | AJ105: =ROUND(AI105/C105,4)-1 -> 0 | AK105: =H105+J105+L105+N105+P105+R105+T105+V105+X105+Z105+AB105+AH105+AD105+AF105 -> 588732 | AL105: =ROUND(AK105/AI105-1,4) -> 0
...

Sheet AVG SAL
A1: DSA CALCULATIONS - AVERAGE TEACHER SALARY AND FRINGE BENEFITS (SEE NOTE)
E2: 10 FY | F2: 11 FY | G2: 12 FY | H2: 13 FY
E3: SALARY | F3: SALARY | G3: SALARY | H3: SALARY
A4: INSTRUCTIONAL PERSONNEL
A5: FY 10 AVG SALARY | E5: =DSADATABASE!K5 -> 53436
A6: FY 11 @ 1% Roll-Up PLUS 0% Cola | F6: =ROUND((E5*1.01)*1,0) -> 53970
A7: FY 12 @ 2% Roll-Up | G7: =ROUND(F6*1.02,0) -> 55049
A8: FY 13 @ 2% Roll-Up | H8: =ROUND(G7*1.02,0) -> 56150
C9: 11 FY
A10: FRINGE BENEFITS | C10: AVG RATE
A11: RETIREMENT | C11: =BASESAL!C57 -> 0.215 | E11: =ROUND(E$5*C11,0) -> 11489 | F11: =ROUND(F$6*C11,0) -> 11604 | G11: =ROUND(G$7*C11,0) -> 11836 | H11: =ROUND(H$8*C11,0) -> 12072
A12: WORKER'S COMP | C12: =BASESAL!C58 -> 0.004076 | E12: =ROUND(E$5*C12,0) -> 218 | F12: =ROUND(F$6*C12,0) -> 220 | G12: =ROUND(G$7*C12,0) -> 224 | H12: =ROUND(H$8*C12,0) -> 229
A13: UNEMP INS | C13: =BASESAL!C59 -> 0.003592 | E13: =ROUND(E$5*C13,0) -> 192 | F13: =ROUND(F$6*C13,0) -> 194 | G13: =ROUND(G$7*C13,0) -> 198 | H13: =ROUND(H$8*C13,0) -> 202
A14: MEDICARE | C14: =BASESAL!C60 -> 0.013034 | E14: =ROUND(E$5*C14,0) -> 696 | F14: =ROUND(F$6*C14,0) -> 703 | G14: =ROUND(G$7*C14,0) -> 718 | H14: =ROUND(H$8*C14,0) -> 732
A15: MEDICAL INS | C15: =DSADATABASE!C70 -> 6980.69 | E15: =DSADATABASE!C70 -> 6980.69 | F15: =DSADATABASE!C70 -> 6980.69 | G15: =DSADATABASE!D70 -> 6980.69 | H15: =DSADATABASE!E70 -> 6980.69
A16: OTHER | C16: =BASESAL!C62 -> 0.004306 | E16: =ROUND(E$5*C16,0) -> 230 | F16: =ROUND(F$6*C16,0) -> 232 | G16: =ROUND(G$7*C16,0) -> 237 | H16: =H$8*C16 -> 241.7819
E17: =SUM(E11:E16) -> 19805.69 | F17: =SUM(F11:F16) -> 19933.69 | G17: =SUM(G11:G16) -> 20193.69 | H17: =SUM(H11:H16) -> 20457.472
A19: TOTAL SALARY AND FRINGE BENEFITS | E19: =E5+E17 -> 73241.69 | F19: =F6+F17 -> 73903.69 | G19: =G7+G17 -> 75242.69 | H19: =H8+H17 -> 76607.472
A21: NOTE: VARIABLES TO IMPACT AVERAGE
A22: 1. AVERAGE STARTING SALARIES OF NEW TEACHERS HIRED AFTER FY ACTUAL AVERAGE
A23: 2. NUMBER OF FY 10 TEACHERS WHO LEAVE SERVICE (RETIREMENT, CHANGE OF PROFESSION, ETC)
A24: 3. NUMBER OF FY 10 TEACHERS NO LONGER ELIGIBLE FOR MERIT ADJUSTMENT
A25: 4. FINAL FRINGE RATES AFTER FY 11 BUDGETED AVERAGE
A26: 5. LOCAL COLLECTIVE BARGAINING AGREEMENTS

Sheet BASESAL
A1: DISTRIBUTIVE SCHOOL ACCOUNT - BASE SALARY
B2: FY10 | C2: FY11 | D2: =C2 -> FY11 | E2: FY12 | F2: =E2 -> FY12 | G2: FY13 | H2: =G2 -> FY13
B3: POS | C3: POS | D3: $ | E3: POS | F3: $ | G3: POS | H3: $
A4: WEIGHTED ENROLLMENT | B4: =DSADATABASE!A4 -> 425527.2 | C4: =DSADATABASE!B4 -> 422569.6 | E4: =DSADATABASE!C4 -> 421987.1 | G4: =DSADATABASE!D4 -> 423499.6
A5: AVG STARTING TEACHER SALARY | D5: =DSADATABASE!K14 -> 39166 | F5: =D5 -> 39166 | H5: =F5 -> 39166
A7: INSTRUCTIONAL PERSONNEL
A8: LICENSED | B8: =DSADATABASE!C25 -> 20489.15 | C8: =ROUND(C$4/B9,2)-B8 -> -143.96 | E8: =(B8) -> 20489.15 | G8: =(E12) -> 20345.19
A9: STUDENT RATIO | B9: =ROUND(B$4/B8,2) -> 20.77 | D9: =ROUND(C8*D5,0) -> -5638337 | E9: =(C8) -> -143.96 | F9: =ROUND(D9*1.02,0) -> -5751104 | H9: =ROUND(F9*1.02,0) -> -5866126
A10: 2%ROLL-UP | D10: =ROUND(B8*B12,0) -> 1105799426 | F10: =ROUND(D10*1.02,0) -> 1127915415 | H10: =ROUND((F10+F11)*1.02,0) -> 1150473723
A11: FY 10 AVG SALARY | B11: =DSADATABASE!K5 -> 53436 | F11: =E11*F5 -> 0 | H11: =G11*H5 -> 0
A12: FY11 = FY10 @ 1% Roll-Up Plus 0% Cola | B12: =ROUND((B11*1.01)*1,0) -> 53970 | E12: =SUM(E8:E11) -> 20345.19 | F12: =SUM(F8:F11) -> 1122164311 | G12: =SUM(G8:G11) -> 20345.19 | H12: =SUM(H8:H11) -> 1144607597
A14: INSTRUCTIONAL PERSONNEL
A15: NON-LICENSED | B15: =DSADATABASE!C26 -> 2051.3 | C15: =ROUND(C$4/B16,2)-B15 -> -14.23 | E15: =(B15) -> 2051.3 | G15: =(E19) -> 2037.07
A16: STUDENT RATIO | B16: =ROUND(B$4/B15,2) -> 207.44 | D16: =ROUND(C15*DSADATABASE!K15,0) -> -330819 | E16: =(C15) -> -14.23 | F16: =ROUND(D16*1.02,0) -> -337435 | H16: =ROUND(F16*1.02,0) -> -344184
A17: 2%ROLL-UP | D17: =ROUND(B15*B19,0) -> 64220049 | F17: =ROUND(D17*1.02,0) -> 65504450 | H17: =ROUND((F17+F18)*1.02,0) -> 66814539
A18: =$A$11 -> FY 10 AVG SALARY | B18: =DSADATABASE!K6 -> 30997 | H18: =(G18*B19)*0.75 -> 0
A19: =$A$12 -> FY11 = FY10 @ 1% Roll-Up Plus 0% Cola | B19: =ROUND((B18*1.01)*1,0) -> 31307 | E19: =SUM(E15:E18) -> 2037.07 | F19: =SUM(F15:F18) -> 65167015 | G19: =SUM(G15:G18) -> 2037.07 | H19: =SUM(H15:H18) -> 66470355
A21: INSTRUCTION SUPPORT PERSONNEL
A22: LICENSED | B22: =DSADATABASE!C27 -> 2328.71 | C22: =ROUND(C$4/B23,2)-B22 -> -16.17 | E22: =(B22) -> 2328.71 | G22: =(E26) -> 2312.54
A23: STUDENT RATIO | B23: =ROUND(B$4/B22,2) -> 182.73 | D23: =ROUND(C22*DSADATABASE!K16,0) -> -790438 | E23: =(C22) -> -16.17 | F23: =ROUND(D23*1.02,0) -> -806247 | H23: =ROUND(F23*1.02,0) -> -822372
A24: 2%ROLL-UP | D24: =ROUND(B22*B26,0) -> 153296651 | F24: =ROUND(D24*1.02,0) -> 156362584 | H24: =ROUND((F24+F25)*1.02,0) -> 159489836
A25: =$A$11 -> FY 10 AVG SALARY | B25: =DSADATABASE!K7 -> 65177 | H25: =(G25*B26)*0.75 -> 0
A26: =$A$12 -> FY11 = FY10 @ 1% Roll-Up Plus 0% Cola | B26: =ROUND((B25*1.01)*1,0) -> 65829 | E26: =SUM(E22:E25) -> 2312.54 | F26: =SUM(F22:F25) -> 155556337 | G26: =SUM(G22:G25) -> 2312.54 | H26: =SUM(H22:H25) -> 158667464
A28: NON LICENSED | B28: =DSADATABASE!C28 -> 959.07 | C28: =ROUND(C$4/B29,2)-B28 -> -6.67 | E28: =(B28) -> 959.07 | G28: =(E32) -> 952.4
A29: STUDENT RATIO | B29: =ROUND(B$4/B28,2) -> 443.69 | D29: =ROUND(C28*DSADATABASE!K17,0) -> -195925 | E29: =(C28) -> -6.67 | F29: =ROUND(D29*1.02,0) -> -199844 | H29: =ROUND(F29*1.02,0) -> -203841
A30: 2%ROLL-UP | D30: =ROUND(B28*B32,0) -> 37937932 | F30: =ROUND(D30*1.02,0) -> 38696691 | H30: =ROUND((F30+F31)*1.02,0) -> 39470625
A31: =$A$11 -> FY 10 AVG SALARY | B31: =DSADATABASE!K8 -> 39165 | H31: =(G31*B32)*0.75 -> 0
A32: =$A$12 -> FY11 = FY10 @ 1% Roll-Up Plus 0% Cola | B32: =ROUND((B31*1.01)*1,0) -> 39557 | E32: =SUM(E28:E31) -> 952.4 | F32: =SUM(F28:F31) -> 38496847 | G32: =SUM(G28:G31) -> 952.4 | H32: =SUM(H28:H31) -> 39266784
A34: ADMINISTRATIVE SUPPORT PERSONNEL
A35: LICENSED | B35: =DSADATABASE!C29 -> 1405.47 | C35: =ROUND(C$4/B36,2)-B35 -> -9.79 | E35: =(B35) -> 1405.47 | G35: =(E39) -> 1395.68
A36: STUDENT RATIO | B36: =ROUND(B$4/B35,2) -> 302.77 | D36: =ROUND(C35*DSADATABASE!K18,0) -> -643967 | E36: =(C35) -> -9.79 | F36: =ROUND(D36*1.02,0) -> -656846 | H36: =ROUND(F36*1.02,0) -> -669983
A37: 2%ROLL-UP | D37: =ROUND(B35*B39,0) -> 124497938 | F37: =ROUND(D37*1.02,0) -> 126987897 | H37: =ROUND((F37+F38)*1.02,0) -> 129527655
A38: =$A$11 -> FY 10 AVG SALARY | B38: =DSADATABASE!K9 -> 87704 | H38: =(G38*B39)*0.75 -> 0
A39: =$A$12 -> FY11 = FY10 @ 1% Roll-Up Plus 0% Cola | B39: =ROUND((B38*1.01)*1,0) -> 88581 | E39: =SUM(E35:E38) -> 1395.68 | F39: =SUM(F35:F38) -> 126331051 | G39: =SUM(G35:G38) -> 1395.68 | H39: =SUM(H35:H38) -> 128857672
A41: NON-LICENSED | B41: =DSADATABASE!C30 -> 2881.37 | C41: =ROUND(C$4/B42,2)-B41 -> -19.98 | E41: =(B41) -> 2881.37 | G41: =(E45) -> 2861.39
A42: STUDENT RATIO | B42: =ROUND(B$4/B41,2) -> 147.68 | D42: =ROUND(C41*DSADATABASE!K19,0) -> -692447 | E42: =(C41) -> -19.98 | F42: =ROUND(D42*1.02,0) -> -706296 | H42: =ROUND(F42*1.02,0) -> -720422
A43: 2%ROLL-UP | D43: =ROUND(B41*B45,0) -> 133145226 | F43: =ROUND(D43*1.02,0) -> 135808131 | H43: =ROUND((F43+F44)*1.02,0) -> 138524294
A44: =$A$11 -> FY 10 AVG SALARY | B44: =DSADATABASE!K10 -> 46209 | H44: =(G44*B45)*0.75 -> 0
A45: =$A$12 -> FY11 = FY10 @ 1% Roll-Up Plus 0% Cola | B45: =ROUND((B44*1)*1,0) -> 46209 | E45: =SUM(E41:E44) -> 2861.39 | F45: =SUM(F41:F44) -> 135101835 | G45: =SUM(G41:G44) -> 2861.39 | H45: =SUM(H41:H44) -> 137803872
A47: OTHER LICENSED & NON-LICENSED | B47: =DSADATABASE!C31 -> 5844.97 | C47: =ROUND(C$4/B48,2)-B47 -> -40.44 | E47: =(B47) -> 5844.97 | G47: =(E51) -> 5804.53
A48: STUDENT RATIO | B48: =ROUND(B$4/B47,2) -> 72.8 | D48: =ROUND(C47*DSADATABASE!K20,0) -> -1309892 | E48: =(C47) -> -40.44 | F48: =ROUND(D48*1.02,0) -> -1336090 | H48: =ROUND(F48*1.02,0) -> -1362812
A49: 2%ROLL-UP | D49: =ROUND(B47*B51,0) -> 254957591 | F49: =ROUND(D49*1.02,0) -> 260056743 | H49: =ROUND((F49+F50)*1.02,0) -> 265257878
A50: =$A$11 -> FY 10 AVG SALARY | B50: =DSADATABASE!K11 -> 43188 | H50: =(G50*B51)*0.75 -> 0
A51: =$A$12 -> FY11 = FY10 @ 1% Roll-Up Plus 0% Cola | B51: =ROUND((B50*1.01)*1,0) -> 43620 | D51: =SUM(D9:D49) -> 1864252988 | E51: =SUM(E47:E50) -> 5804.53 | F51: =SUM(F47:F50) -> 258720653 | G51: =SUM(G47:G50) -> 5804.53 | H51: =SUM(H47:H50) -> 263895066
A53: TOTAL SALARIES | B53: =+B8+B15+B22+B28+B35+B41+B47 -> 35960.04 | C53: =+C8+C15+C22+C28+C35+C41+C47 -> -251.24 | E53: =SUM(E12+E19+E26+E32+E39+E45+E51) -> 35708.8 | F53: =SUM(F12+F19+F26+F32+F39+F45+F51) -> 1901538049 | G53: =SUM(G12+G19+G26+G32+G39+G45+G51) -> 35708.8 | H53: =SUM(H12+H19+H26+H32+H39+H45+H51) -> 1939568810
A54: SUBSTITUTE SALARIES | B54: =+DSASUMM!C6 -> 36338122 | D54: =+DSASUMM!C6 -> 36338122 | F54: =DSASUMM!C6 -> 36338122 | H54: =F54 -> 36338122
A55: EXTRA PAY, MISC SALARIES | B55: =+DSASUMM!C7 -> 19265375 | D55: =ROUND(B55*1.02*1.04,0) -> 20436710 | F55: =ROUND(D55*1.02,0) -> 20845444 | H55: =ROUND(F55*1.02,0) -> 21262353
A56: FRINGE BENEFITS
A57: RETIREMENT | B57: =DSADATABASE!C65 -> 0.215 | C57: =B57 -> 0.215 | F57: =ROUND(F$53*$B57,0) -> 408830681 | H57: =ROUND(H$53*$C57,0) -> 417007294
A58: WORKER'S COMP | B58: =DSADATABASE!C66 -> 0.004076 | C58: =B58 -> 0.004076 | F58: =ROUND(SUM(F$53:F$55)*$B58,0) -> 7983749 | H58: =ROUND(SUM(H$53:H$55)*$C58,0) -> 8140462
A59: UNEMP INS | B59: =DSADATABASE!C67 -> 0.003592 | C59: =B59 -> 0.003592 | F59: =ROUND(SUM(F$53:F$55)*$B59,0) -> 7035728 | H59: =ROUND(SUM(H$53:H$55)*$C59,0) -> 7173832
A60: MEDICARE | B60: =DSADATABASE!C68 -> 0.013034 | C60: =B60 -> 0.013034 | F60: =ROUND(SUM(F$53:F$55)*$B60,0) -> 25529978 | H60: =ROUND(SUM(H$53:H$55)*$C60,0) -> 26031104
A61: MEDICAL INS | B61: =DSADATABASE!C70 -> 6980.69 | C61: =B61 -> 6980.69 | F61: =ROUND(E$53*$B61,0) -> 249272063 | H61: =ROUND(G$53*$C61,0) -> 249272063
A62: OTHER | B62: =DSADATABASE!C69 -> 0.004306 | C62: =B62 -> 0.004306 | F62: =ROUND(SUM(F$53:$F55)*$B62,0) -> 8434255 | H62: =ROUND(SUM(H$53:H55)*$C62,0) -> 8599811
F63: =SUM(F57:F62) -> 707086454 | H63: =SUM(H57:H62) -> 716224566
A64: TOTAL POSITIONS/SALARIES
A65: AND FRINGE BENEFITS | E65: =E53+E63 -> 35708.8 | F65: =F53+F54+F55+F63 -> 2665808069 | G65: =G53+G63 -> 35708.8 | H65: =H53+H54+H55+H63 -> 2713393851
A66: BENEFIT/SALARY RATIO | F66: =F63/F53 -> 0.37184975 | H66: =H63/H53 -> 0.36927

Sheet M200SAL
A1: DISTRIBUTIVE SCHOOL ACCOUNT - DECISION M-200 SALARY
B2: =BASESAL!B2 -> FY10 | C2: =BASESAL!C2 -> FY11 | D2: =BASESAL!D2 -> FY11 | E2: =BASESAL!E2 -> FY12 | F2: =BASESAL!F2 -> FY12 | G2: =BASESAL!G2 -> FY13 | H2: =BASESAL!H2 -> FY13
B3: POS | C3: POS | D3: $ | E3: POS | F3: $ | G3: POS | H3: $
A4: WEIGHTED ENROLLMENT | B4: =BASESAL!B4 -> 425527.2 | C4: =BASESAL!C4 -> 422569.6 | E4: =BASESAL!E4 -> 421987.1 | G4: =BASESAL!G4 -> 423499.6
A5: AVG STARTING TEACHER SALARY | D5: =BASESAL!D5 -> 39166 | F5: =D5 -> 39166 | H5: =F5 -> 39166
A7: INSTRUCTIONAL PERSONNEL
A8: LICENSED | B8: =BASESAL!B8 -> 20489.15 | C8: =BASESAL!C8 -> -143.96 | E8: =(B8) -> 20489.15 | G8: =(E12) -> 20317.14
A9: STUDENT RATIO | B9: =BASESAL!B9 -> 20.77 | D9: =ROUND(C8*D5,0) -> -5638337 | E9: =(C8) -> -143.96 | F9: =ROUND(D9*1.02,0) -> -5751104 | H9: =ROUND(F9*1.02,0) -> -5866126
A10: 2%ROLL-UP | D10: =ROUND(B8*B12,0) -> 1105799426 | F10: =ROUND(D10*1.02,0) -> 1127915415 | H10: =ROUND((F10+F11)*1.02,0) -> 1149353145
A11: =BASESAL!A11 -> FY 10 AVG SALARY | B11: =BASESAL!B11 -> 53436 | E11: =ROUND((E$4/B9)-E8-E9,2) -> -28.05 | F11: =ROUND(E11*F5,0) -> -1098606 | G11: =ROUND((G$4/B9)-G8-G9,2) -> 72.83 | H11: =ROUND(G11*H5,0) -> 2852460
A12: =BASESAL!A12 -> FY11 = FY10 @ 1% Roll-Up Plus 0% Cola | B12: =BASESAL!B12 -> 53970 | E12: =SUM(E8:E11) -> 20317.14 | F12: =SUM(F8:F11) -> 1121065705 | G12: =SUM(G8:G11) -> 20389.97 | H12: =SUM(H8:H11) -> 1146339479
A14: INSTRUCTIONAL PERSONNEL
A15: NON-LICENSED | B15: =BASESAL!B15 -> 2051.3 | C15: =BASESAL!C15 -> -14.23 | E15: =(B15) -> 2051.3 | G15: =(E19) -> 2034.26
A16: STUDENT RATIO | B16: =BASESAL!B16 -> 207.44 | D16: =ROUND(C15*DSADATABASE!K15,0) -> -330819 | E16: =(C15) -> -14.23 | F16: =ROUND(D16*1.02,0) -> -337435 | H16: =ROUND(F16*1.02,0) -> -344184
A17: 2%ROLL-UP | D17: =ROUND(B15*B19,0) -> 64220049 | F17: =ROUND(D17*1.02,0) -> 65504450 | H17: =ROUND((F17+F18)*1.02,0) -> 66747905
A18: =$A$11 -> FY 10 AVG SALARY | B18: =BASESAL!B18 -> 30997 | E18: =ROUND((E$4/B16)-E15-E16,2) -> -2.81 | F18: =ROUND(E18*DSADATABASE!$K$15,0) -> -65327 | G18: =ROUND((G$4/B16)-G15-G16,2) -> 7.29 | H18: =ROUND(G18*DSADATABASE!$K$15,0) -> 169478
A19: =$A$12 -> FY11 = FY10 @ 1% Roll-Up Plus 0% Cola | B19: =BASESAL!B19 -> 31307 | E19: =SUM(E15:E18) -> 2034.26 | F19: =SUM(F15:F18) -> 65101688 | G19: =SUM(G15:G18) -> 2041.55 | H19: =SUM(H15:H18) -> 66573199
A21: INSTRUCTION SUPPORT PERSONNEL
A22: LICENSED | B22: =BASESAL!B22 -> 2328.71 | C22: =BASESAL!C22 -> -16.17 | E22: =(B22) -> 2328.71 | G22: =(E26) -> 2309.35
A23: STUDENT RATIO | B23: =BASESAL!B23 -> 182.73 | D23: =ROUND(C22*DSADATABASE!K16,0) -> -790438 | E23: =(C22) -> -16.17 | F23: =ROUND(D23*1.02,0) -> -806247 | H23: =ROUND(F23*1.02,0) -> -822372
A24: 2%ROLL-UP | D24: =ROUND(B22*B26,0) -> 153296651 | F24: =ROUND(D24*1.02,0) -> 156362584 | H24: =ROUND((F24+F25)*1.02,0) -> 159330780
A25: =$A$11 -> FY 10 AVG SALARY | B25: =BASESAL!B25 -> 65177 | E25: =ROUND((E$4/B23)-E22-E23,2) -> -3.19 | F25: =ROUND(E25*DSADATABASE!$K$16,0) -> -155937 | G25: =ROUND((G$4/B23)-G22-G23,2) -> 8.27 | H25: =ROUND(G25*DSADATABASE!$K$16,0) -> 404262
A26: =$A$12 -> FY11 = FY10 @ 1% Roll-Up Plus 0% Cola | B26: =BASESAL!B26 -> 65829 | E26: =SUM(E22:E25) -> 2309.35 | F26: =SUM(F22:F25) -> 155400400 | G26: =SUM(G22:G25) -> 2317.62 | H26: =SUM(H22:H25) -> 158912670
A28: NON-LICENSED | B28: =BASESAL!B28 -> 959.07 | C28: =BASESAL!C28 -> -6.67 | E28: =(B28) -> 959.07 | G28: =(E32) -> 951.09
A29: STUDENT RATIO | B29: =BASESAL!B29 -> 443.69 | D29: =ROUND(C28*DSADATABASE!K17,0) -> -195925 | E29: =(C28) -> -6.67 | F29: =ROUND(D29*1.02,0) -> -199844 | H29: =ROUND(F29*1.02,0) -> -203841
A30: 2%ROLL-UP | D30: =ROUND(B28*B32,0) -> 37937932 | F30: =ROUND(D30*1.02,0) -> 38696691 | H30: =ROUND((F30+F31)*1.02,0) -> 39431375
A31: =$A$11 -> FY 10 AVG SALARY | B31: =BASESAL!B31 -> 39165 | E31: =ROUND((E$4/B29)-E28-E29,2) -> -1.31 | F31: =ROUND(E31*DSADATABASE!$K$17,0) -> -38480 | G31: =ROUND((G$4/B29)-G28-G29,2) -> 3.4 | H31: =ROUND(G31*DSADATABASE!$K$17,0) -> 99872
A32: =$A$12 -> FY11 = FY10 @ 1% Roll-Up Plus 0% Cola | B32: =BASESAL!B32 -> 39557 | E32: =SUM(E28:E31) -> 951.09 | F32: =SUM(F28:F31) -> 38458367 | G32: =SUM(G28:G31) -> 954.49 | H32: =SUM(H28:H31) -> 39327406
A34: ADMINISTRATIVE SUPPORT PERSONNEL
A35: LICENSED | B35: =BASESAL!B35 -> 1405.47 | C35: =BASESAL!C35 -> -9.79 | E35: =(B35) -> 1405.47 | G35: =(E39) -> 1393.75
A36: STUDENT RATIO | B36: =BASESAL!B36 -> 302.77 | D36: =ROUND(C35*DSADATABASE!K18,0) -> -643967 | E36: =(C35) -> -9.79 | F36: =ROUND(D36*1.02,0) -> -656846 | H36: =ROUND(F36*1.02,0) -> -669983
A37: 2%ROLL-UP | D37: =ROUND(B35*B39,0) -> 124497938 | F37: =ROUND(D37*1.02,0) -> 126987897 | H37: =ROUND((F37+F38)*1.02,0) -> 129398164
A38: =$A$11 -> FY 10 AVG SALARY | B38: =BASESAL!B38 -> 87704 | E38: =ROUND((E$4/B36)-E35-E36,2) -> -1.93 | F38: =ROUND(E38*DSADATABASE!$K$18,0) -> -126952 | G38: =ROUND((G$4/B36)-G35-G36,2) -> 5 | H38: =ROUND(G38*DSADATABASE!$K$18,0) -> 328890
A39: =$A$12 -> FY11 = FY10 @ 1% Roll-Up Plus 0% Cola | B39: =BASESAL!B39 -> 88581 | E39: =SUM(E35:E38) -> 1393.75 | F39: =SUM(F35:F38) -> 126204099 | G39: =SUM(G35:G38) -> 1398.75 | H39: =SUM(H35:H38) -> 129057071
A41: NON-LICENSED | B41: =BASESAL!B41 -> 2881.37 | C41: =BASESAL!C41 -> -19.98 | E41: =(B41) -> 2881.37 | G41: =(E45) -> 2857.44
A42: STUDENT RATIO | B42: =BASESAL!B42 -> 147.68 | D42: =ROUND(C41*DSADATABASE!K19,0) -> -692447 | E42: =(C41) -> -19.98 | F42: =ROUND(D42*1.02,0) -> -706296 | H42: =ROUND(F42*1.02,0) -> -720422
A43: 2%ROLL-UP | D43: =ROUND(B41*B45,0) -> 133145226 | F43: =ROUND(D43*1.02,0) -> 135808131 | H43: =ROUND((F43+F44)*1.02,0) -> 138384661
A44: =$A$11 -> FY 10 AVG SALARY | B44: =BASESAL!B44 -> 46209 | E44: =ROUND((E$4/B42)-E41-E42,2) -> -3.95 | F44: =ROUND(E44*DSADATABASE!$K$19,0) -> -136895 | G44: =ROUND((G$4/B42)-G41-G42,2) -> 10.24 | H44: =ROUND(G44*DSADATABASE!$K$19,0) -> 354888
A45: =$A$12 -> FY11 = FY10 @ 1% Roll-Up Plus 0% Cola | B45: =BASESAL!B45 -> 46209 | E45: =SUM(E41:E44) -> 2857.44 | F45: =SUM(F41:F44) -> 134964940 | G45: =SUM(G41:G44) -> 2867.68 | H45: =SUM(H41:H44) -> 138019127
A47: OTHER LICENSED & NON-LICENSED | B47: =BASESAL!B47 -> 5844.97 | C47: =BASESAL!C47 -> -40.44 | E47: =(B47) -> 5844.97 | G47: =(E51) -> 5796.53
A48: STUDENT RATIO | B48: =BASESAL!B48 -> 72.8 | D48: =ROUND(C47*DSADATABASE!K20,0) -> -1309892 | E48: =(C47) -> -40.44 | F48: =ROUND(D48*1.02,0) -> -1336090 | H48: =ROUND(F48*1.02,0) -> -1362812
A49: 2%ROLL-UP | D49: =ROUND(B47*B51,0) -> 254957591 | F49: =ROUND(D49*1.02,0) -> 260056743 | H49: =ROUND((F49+F50)*1.02,0) -> 264993567
A50: =$A$11 -> FY 10 AVG SALARY | B50: =BASESAL!B50 -> 43188 | E50: =ROUND((E$4/B48)-E47-E48,2) -> -8 | F50: =ROUND(E50*DSADATABASE!$K$20,0) -> -259128 | G50: =ROUND((G$4/B48)-G47-G48,2) -> 20.77 | H50: =ROUND(G50*DSADATABASE!$K$20,0) -> 672761
A51: =$A$12 -> FY11 = FY10 @ 1% Roll-Up Plus 0% Cola | B51: =BASESAL!B51 -> 43620 | E51: =SUM(E47:E50) -> 5796.53 | F51: =SUM(F47:F50) -> 258461525 | G51: =SUM(G47:G50) -> 5817.3 | H51: =SUM(H47:H50) -> 264303516
A53: TOTAL SALARIES | B53: =B8+B15+B22+B28+B35+B41+B47 -> 35960.04 | C53: =C8+C15+C22+C28+C35+C41+C47 -> -251.24 | D53: =SUM(D9:D49) -> 1864252988 | E53: =SUM(E12+E19+E26+E32+E39+E45+E51) -> 35659.56 | F53: =SUM(F12+F19+F26+F32+F39+F45+F51) -> 1899656724 | G53: =SUM(G12+G19+G26+G32+G39+G45+G51) -> 35787.36 | H53: =SUM(H12+H19+H26+H32+H39+H45+H51) -> 1942532468
A54: SUBSTITUTE SALARIES | B54: =+BASESAL!B54 -> 36338122 | C54: =ROUND(B54/B4*C4,0) -> 36085556 | F54: =ROUND(C54/C4*E4,0) -> 36035813 | H54: =ROUND(F54/E4*G4,0) -> 36164974
A55: =BASESAL!A55 -> EXTRA PAY, MISC SALARIES | B55: =+BASESAL!B55 -> 19265375 | C55: =ROUND(BASESAL!D55/M200SAL!B4*M200SAL!C4,0) -> 20294666 | F55: =ROUND((C55/C4*E4)*1.02,0) -> 20672024 | H55: =ROUND((F55/E4*G4)*1.02,0) -> 21161040
A56: FRINGE BENEFITS
A57: RETIREMENT | B57: =BASESAL!B57 -> 0.215 | C57: =BASESAL!C57 -> 0.215 | F57: =SUM(F$53*B57,0) -> 4.084262e+08 | H57: =H$53*C57 -> 4.1764448e+08
A58: WORKER'S COMP | B58: =BASESAL!B58 -> 0.004076 | C58: =BASESAL!C58 -> 0.004076 | F58: =ROUND(SUM(F$53:F$55)*B58,0) -> 7974142 | H58: =ROUND(SUM(H$53:H$55)*C58,0) -> 8151423
A59: UNEMP INS | B59: =BASESAL!B59 -> 0.003592 | C59: =BASESAL!C59 -> 0.003592 | F59: =ROUND(SUM(F$53:F$55)*B59,0) -> 7027262 | H59: =ROUND(SUM(H$53:H$55)*C59,0) -> 7183492
A60: MEDICARE | B60: =BASESAL!B60 -> 0.013034 | C60: =BASESAL!C60 -> 0.013034 | F60: =ROUND(SUM(F$53:F$55)*B60,0) -> 25499256 | H60: =ROUND(SUM(H$53:H$55)*C60,0) -> 26066155
A61: MEDICAL INS | B61: =BASESAL!B61 -> 6980.69 | C61: =BASESAL!C61 -> 6980.69 | F61: =ROUND(E$53*B61,0) -> 248928334 | H61: =ROUND(G$53*C61,0) -> 249820466
A62: OTHER | B62: =BASESAL!B62 -> 0.004306 | C62: =BASESAL!C62 -> 0.004306 | F62: =ROUND(SUM(F$53:$F55)*$B62,0) -> 8424106 | H62: =ROUND(SUM(H$53:H55)*$C62,0) -> 8611391
F63: =SUM(F57:F62) -> 7.062793e+08 | H63: =SUM(H57:H62) -> 7.1747741e+08
A64: TOTAL POSITIONS/SALARIES
A65: AND FRINGE BENEFITS | E65: =E53+E63 -> 35659.56 | F65: =F53+F54+F55+F63 -> 2.6626439e+09 | G65: =G53+G63 -> 35787.36 | H65: =H53+H54+H55+H63 -> 2.7173359e+09
A66: BENEFIT/SALARY RATIO | F66: =F63/F53 -> 0.37179312 | H66: =H63/H53 -> 0.36935157
B67: FY12 | C67: =B67 -> FY12 | D67: Net | E67: FY13 | F67: =E67 -> FY13 | G67: Net
A68: Summary | B68: Base | C68: M200 | D68: Diff | E68: Base | F68: M200 | G68: Diff
A69: Salaries | B69: =BASESAL!F53 -> 1901538049 | C69: =F53 -> 1899656724 | D69: =C69-B69 -> -1881325 | E69: =BASESAL!H53 -> 1939568810 | F69: =H53 -> 1942532468 | G69: =F69-E69 -> 2963658
A70: Substitute Salaries | B70: =BASESAL!F54 -> 36338122 | C70: =+F54 -> 36035813 | D70: =C70-B70 -> -302309 | E70: =BASESAL!H54 -> 36338122 | F70: =+H54 -> 36164974 | G70: =F70-E70 -> -173148
A71: Extra Pay, Misc Salaries | B71: =BASESAL!F55 -> 20845444 | C71: =+F55 -> 20672024 | D71: =C71-B71 -> -173420 | E71: =BASESAL!H55 -> 21262353 | F71: =+H55 -> 21161040 | G71: =F71-E71 -> -101313
A72: Retirement | B72: =BASESAL!F57 -> 408830681 | C72: =F57 -> 4.084262e+08 | D72: =C72-B72 -> -404485.34 | E72: =BASESAL!H57 -> 417007294 | F72: =H57 -> 4.1764448e+08 | G72: =F72-E72 -> 637186.62
A73: Worker's Comp | B73: =BASESAL!F58 -> 7983749 | C73: =F58 -> 7974142 | D73: =C73-B73 -> -9607 | E73: =BASESAL!H58 -> 8140462 | F73: =H58 -> 8151423 | G73: =F73-E73 -> 10961
A74: Unemp Comp | B74: =BASESAL!F59 -> 7035728 | C74: =F59 -> 7027262 | D74: =C74-B74 -> -8466 | E74: =BASESAL!H59 -> 7173832 | F74: =H59 -> 7183492 | G74: =F74-E74 -> 9660
A75: Medicare | B75: =BASESAL!F60 -> 25529978 | C75: =F60 -> 25499256 | D75: =C75-B75 -> -30722 | E75: =BASESAL!H60 -> 26031104 | F75: =H60 -> 26066155 | G75: =F75-E75 -> 35051
A76: Medical | B76: =BASESAL!F61 -> 249272063 | C76: =F61 -> 248928334 | D76: =C76-B76 -> -343729 | E76: =BASESAL!H61 -> 249272063 | F76: =H61 -> 249820466 | G76: =F76-E76 -> 548403
A77: Other | B77: =BASESAL!F62 -> 8434255 | C77: =F62 -> 8424106 | D77: =C77-B77 -> -10149 | E77: =BASESAL!H62 -> 8599811 | F77: =H62 -> 8611391 | G77: =F77-E77 -> 11580
A79: Total Salaries and Fringe Benefits | B79: =SUM(B69:B77) -> 2665808069 | C79: =SUM(C69:C77) -> 2.6626439e+09 | D79: =C79-B79 -> -3164212.3 | E79: =SUM(E69:E77) -> 2713393851 | F79: =SUM(F69:F77) -> 2.7173359e+09 | G79: =F79-E79 -> 3942038.6

Sheet M300SAL
A1: DISTRIBUTIVE SCHOOL ACCOUNT - DECISION M-300 SALARY
B2: =BASESAL!B2 -> FY10 | C2: =BASESAL!C2 -> FY11 | D2: =BASESAL!D2 -> FY11 | E2: =BASESAL!E2 -> FY12 | F2: =BASESAL!F2 -> FY12 | G2: =BASESAL!G2 -> FY13 | H2: =BASESAL!H2 -> FY13
B3: POS | C3: POS | D3: $ | E3: POS | F3: $ | G3: POS | H3: $
A4: WEIGHTED ENROLLMENT | B4: =M200SAL!B4 -> 425527.2 | C4: =M200SAL!C4 -> 422569.6 | E4: =M200SAL!E4 -> 421987.1 | G4: =M200SAL!G4 -> 423499.6
A5: AVG STARTING TEACHER SALARY | D5: =M200SAL!H5 -> 39166 | F5: =D5 -> 39166 | H5: =F5 -> 39166
A8: INSTRUCTIONAL PERSONNEL
A9: LICENSED | B9: =M200SAL!B8 -> 20489.15 | C9: =M200SAL!C8 -> -143.96 | E9: =(B9) -> 20489.15 | G9: =(E13) -> 20317.14
A10: STUDENT RATIO | B10: =M200SAL!B9 -> 20.77 | D10: =ROUND(C9*D5,0) -> -5638337 | E10: =(C9) -> -143.96 | F10: =ROUND(D10*1.02,0) -> -5751104 | H10: =ROUND(F10*1.02,0) -> -5866126
A11: 2%ROLL-UP | D11: =ROUND(B9*B13,0) -> 1105799426 | F11: =ROUND(D11*1.02,0) -> 1127915415 | H11: =ROUND((F11+F12)*1.02,0) -> 1149353145
A12: =BASESAL!A11 -> FY 10 AVG SALARY | B12: =M200SAL!B11 -> 53436 | E12: =ROUND((E$4/B10)-E9-E10,2) -> -28.05 | F12: =ROUND(E12*F5,0) -> -1098606 | G12: =ROUND((G$4/B10)-G9-G10,2) -> 72.83 | H12: =ROUND(G12*H5,0) -> 2852460
A13: =M200SAL!A12 -> FY11 = FY10 @ 1% Roll-Up Plus 0% Cola | B13: =M200SAL!B12 -> 53970 | E13: =SUM(E9:E12) -> 20317.14 | F13: =SUM(F9:F12) -> 1121065705 | G13: =SUM(G9:G12) -> 20389.97 | H13: =SUM(H9:H12) -> 1146339479
A15: INSTRUCTIONAL PERSONNEL
A16: NON-LICENSED | B16: =M200SAL!B15 -> 2051.3 | C16: =M200SAL!C15 -> -14.23 | E16: =(B16) -> 2051.3 | G16: =(E20) -> 2034.26
A17: STUDENT RATIO | B17: =M200SAL!B16 -> 207.44 | D17: =ROUND(C16*DSADATABASE!K15,0) -> -330819 | E17: =(C16) -> -14.23 | F17: =ROUND(D17*1.02,0) -> -337435 | H17: =ROUND(F17*1.02,0) -> -344184
A18: 2%ROLL-UP | D18: =ROUND(B16*B20,0) -> 64220049 | F18: =ROUND(D18*1.02,0) -> 65504450 | H18: =ROUND((F18+F19)*1.02,0) -> 66747905
A19: =$A$12 -> FY 10 AVG SALARY | B19: =M200SAL!B18 -> 30997 | E19: =ROUND((E$4/B17)-E16-E17,2) -> -2.81 | F19: =ROUND(E19*DSADATABASE!$K$15,0) -> -65327 | G19: =ROUND((G$4/B17)-G16-G17,2) -> 7.29 | H19: =ROUND(G19*DSADATABASE!$K$15,0) -> 169478
A20: =$A$13 -> FY11 = FY10 @ 1% Roll-Up Plus 0% Cola | B20: =M200SAL!B19 -> 31307 | E20: =SUM(E16:E19) -> 2034.26 | F20: =SUM(F16:F19) -> 65101688 | G20: =SUM(G16:G19) -> 2041.55 | H20: =SUM(H16:H19) -> 66573199
A22: INSTRUCTION SUPPORT PERSONNEL
A23: LICENSED | B23: =M200SAL!B22 -> 2328.71 | C23: =M200SAL!C22 -> -16.17 | E23: =(B23) -> 2328.71 | G23: =(E27) -> 2309.35
A24: STUDENT RATIO | B24: =M200SAL!B23 -> 182.73 | D24: =ROUND(C23*DSADATABASE!K16,0) -> -790438 | E24: =(C23) -> -16.17 | F24: =ROUND(D24*1.02,0) -> -806247 | H24: =ROUND(F24*1.02,0) -> -822372
A25: 2%ROLL-UP | D25: =ROUND(B23*B27,0) -> 153296651 | F25: =ROUND(D25*1.02,0) -> 156362584 | H25: =ROUND((F25+F26)*1.02,0) -> 159330780
A26: =$A$12 -> FY 10 AVG SALARY | B26: =M200SAL!B25 -> 65177 | E26: =ROUND((E$4/B24)-E23-E24,2) -> -3.19 | F26: =ROUND(E26*DSADATABASE!$K$16,0) -> -155937 | G26: =ROUND((G$4/B24)-G23-G24,2) -> 8.27 | H26: =ROUND(G26*DSADATABASE!$K$16,0) -> 404262
A27: =$A$13 -> FY11 = FY10 @ 1% Roll-Up Plus 0% Cola | B27: =M200SAL!B26 -> 65829 | E27: =SUM(E23:E26) -> 2309.35 | F27: =SUM(F23:F26) -> 155400400 | G27: =SUM(G23:G26) -> 2317.62 | H27: =SUM(H23:H26) -> 158912670
A29: NON-LICENSED | B29: =M200SAL!B28 -> 959.07 | C29: =M200SAL!C28 -> -6.67 | E29: =(B29) -> 959.07 | G29: =(E33) -> 951.09
A30: STUDENT RATIO | B30: =M200SAL!B29 -> 443.69 | D30: =ROUND(C29*DSADATABASE!K17,0) -> -195925 | E30: =(C29) -> -6.67 | F30: =ROUND(D30*1.02,0) -> -199844 | H30: =ROUND(F30*1.02,0) -> -203841
A31: 2%ROLL-UP | D31: =ROUND(B29*B33,0) -> 37937932 | F31: =ROUND(D31*1.02,0) -> 38696691 | H31: =ROUND((F31+F32)*1.02,0) -> 39431375
A32: =$A$12 -> FY 10 AVG SALARY | B32: =M200SAL!B31 -> 39165 | E32: =ROUND((E$4/B30)-E29-E30,2) -> -1.31 | F32: =ROUND(E32*DSADATABASE!$K$17,0) -> -38480 | G32: =ROUND((G$4/B30)-G29-G30,2) -> 3.4 | H32: =ROUND(G32*DSADATABASE!$K$17,0) -> 99872
A33: =$A$13 -> FY11 = FY10 @ 1% Roll-Up Plus 0% Cola | B33: =M200SAL!B32 -> 39557 | E33: =SUM(E29:E32) -> 951.09 | F33: =SUM(F29:F32) -> 38458367 | G33: =SUM(G29:G32) -> 954.49 | H33: =SUM(H29:H32) -> 39327406
A35: ADMINISTRATIVE SUPPORT PERSONNEL
A36: LICENSED | B36: =M200SAL!B35 -> 1405.47 | C36: =M200SAL!C35 -> -9.79 | E36: =(B36) -> 1405.47 | G36: =(E40) -> 1393.75
A37: STUDENT RATIO | B37: =M200SAL!B36 -> 302.77 | D37: =ROUND(C36*DSADATABASE!K18,0) -> -643967 | E37: =(C36) -> -9.79 | F37: =ROUND(D37*1.02,0) -> -656846 | H37: =ROUND(F37*1.02,0) -> -669983
A38: 2%ROLL-UP | D38: =ROUND(B36*B40,0) -> 124497938 | F38: =ROUND(D38*1.02,0) -> 126987897 | H38: =ROUND((F38+F39)*1.02,0) -> 129398164
A39: =$A$12 -> FY 10 AVG SALARY | B39: =M200SAL!B38 -> 87704 | E39: =ROUND((E$4/B37)-E36-E37,2) -> -1.93 | F39: =ROUND(E39*DSADATABASE!$K$18,0) -> -126952 | G39: =ROUND((G$4/B37)-G36-G37,2) -> 5 | H39: =ROUND(G39*DSADATABASE!$K$18,0) -> 328890
A40: =$A$13 -> FY11 = FY10 @ 1% Roll-Up Plus 0% Cola | B40: =M200SAL!B39 -> 88581 | E40: =SUM(E36:E39) -> 1393.75 | F40: =SUM(F36:F39) -> 126204099 | G40: =SUM(G36:G39) -> 1398.75 | H40: =SUM(H36:H39) -> 129057071
A42: NON-LICENSED | B42: =M200SAL!B41 -> 2881.37 | C42: =M200SAL!C41 -> -19.98 | E42: =(B42) -> 2881.37 | G42: =(E46) -> 2857.44
A43: STUDENT RATIO | B43: =M200SAL!B42 -> 147.68 | D43: =ROUND(C42*DSADATABASE!K19,0) -> -692447 | E43: =(C42) -> -19.98 | F43: =ROUND(D43*1.02,0) -> -706296 | H43: =ROUND(F43*1.02,0) -> -720422
A44: 2%ROLL-UP | D44: =ROUND(B42*B46,0) -> 133145226 | F44: =ROUND(D44*1.02,0) -> 135808131 | H44: =ROUND((F44+F45)*1.02,0) -> 138384661
A45: =$A$12 -> FY 10 AVG SALARY | B45: =M200SAL!B44 -> 46209 | E45: =ROUND((E$4/B43)-E42-E43,2) -> -3.95 | F45: =ROUND(E45*DSADATABASE!$K$19,0) -> -136895 | G45: =ROUND((G$4/B43)-G42-G43,2) -> 10.24 | H45: =ROUND(G45*DSADATABASE!$K$19,0) -> 354888
A46: =$A$13 -> FY11 = FY10 @ 1% Roll-Up Plus 0% Cola | B46: =M200SAL!B45 -> 46209 | E46: =SUM(E42:E45) -> 2857.44 | F46: =SUM(F42:F45) -> 134964940 | G46: =SUM(G42:G45) -> 2867.68 | H46: =SUM(H42:H45) -> 138019127
A48: OTHER LICENSED & NON-LICENSED | B48: =M200SAL!B47 -> 5844.97 | C48: =M200SAL!C47 -> -40.44 | E48: =(B48) -> 5844.97 | G48: =(E52) -> 5796.53
A49: STUDENT RATIO | B49: =M200SAL!B48 -> 72.8 | D49: =ROUND(C48*DSADATABASE!K20,0) -> -1309892 | E49: =(C48) -> -40.44 | F49: =ROUND(D49*1.02,0) -> -1336090 | H49: =ROUND(F49*1.02,0) -> -1362812
A50: 2%ROLL-UP | D50: =ROUND(B48*B52,0) -> 254957591 | F50: =ROUND(D50*1.02,0) -> 260056743 | H50: =ROUND((F50+F51)*1.02,0) -> 264993567
A51: =$A$12 -> FY 10 AVG SALARY | B51: =M200SAL!B50 -> 43188 | E51: =ROUND((E$4/B49)-E48-E49,2) -> -8 | F51: =ROUND(E51*DSADATABASE!$K$20,0) -> -259128 | G51: =ROUND((G$4/B49)-G48-G49,2) -> 20.77 | H51: =ROUND(G51*DSADATABASE!$K$20,0) -> 672761
A52: =$A$13 -> FY11 = FY10 @ 1% Roll-Up Plus 0% Cola | B52: =M200SAL!B51 -> 43620 | E52: =SUM(E48:E51) -> 5796.53 | F52: =SUM(F48:F51) -> 258461525 | G52: =SUM(G48:G51) -> 5817.3 | H52: =SUM(H48:H51) -> 264303516
A54: TOTAL SALARIES | B54: =+B9+B16+B23+B29+B36+B42+B48 -> 35960.04 | C54: =+C9+C16+C23+C29+C36+C42+C48 -> -251.24 | E54: =SUM(E13+E20+E27+E33+E40+E46+E52) -> 35659.56 | F54: =SUM(F13+F20+F27+F33+F40+F46+F52) -> 1899656724 | G54: =SUM(G13+G20+G27+G33+G40+G46+G52) -> 35787.36 | H54: =SUM(H13+H20+H27+H33+H40+H46+H52) -> 1942532468
A55: PERS Rate Change (23.75%-21.5%*.50) | F55: =-F54*(0.2375-0.215)*0.5 -> -21371138 | H55: =-H54*(0.2375-0.215)*0.5 -> -21853490
A56: TOTAL SALARIES LESS PERS RATE CHANGE | F56: =+F54+F55 -> 1.8782856e+09 | H56: =+H54+H55 -> 1.920679e+09
A57: SUBSTITUTE SALARIES | F57: =M200SAL!F54 -> 36035813 | H57: =M200SAL!H54 -> 36164974
A58: =M200SAL!A55 -> EXTRA PAY, MISC SALARIES | F58: =M200SAL!F55 -> 20672024 | H58: =M200SAL!H55 -> 21161040
A59: FRINGE BENEFITS
A60: RETIREMENT | B60: =DSADATABASE!D65 -> 0.2375 | C60: =DSADATABASE!E65 -> 0.2375 | F60: =ROUND(F$56*B60,0) -> 446092827 | H60: =ROUND(H$56*C60,0) -> 456161257
A61: WORKER'S COMP | B61: =DSADATABASE!D66 -> 0.004076 | C61: =DSADATABASE!E66 -> 0.004076 | F61: =ROUND(SUM(F$56:F$58)*B61,0) -> 7887033 | H61: =ROUND(SUM(H$56:H$58)*C61,0) -> 8062348
A62: UNEMP INS | B62: =DSADATABASE!D67 -> 0.003592 | C62: =DSADATABASE!E67 -> 0.003592 | F62: =ROUND(SUM(F$56:F$58)*B62,0) -> 6950496 | H62: =ROUND(SUM(H$56:H$58)*C62,0) -> 7104994
A63: MEDICARE | B63: =DSADATABASE!D68 -> 0.013034 | C63: =DSADATABASE!E68 -> 0.013034 | F63: =ROUND(SUM(F$56:F$58)*B63,0) -> 25220704 | H63: =ROUND(SUM(H$56:H$58)*C63,0) -> 25781317
A64: MEDICAL INS | B64: =DSADATABASE!D70 -> 6980.69 | C64: =DSADATABASE!E70 -> 6980.69 | F64: =ROUND(E$54*B64,0) -> 248928334 | H64: =ROUND(G$54*C64,0) -> 249820466
A65: OTHER | B65: =DSADATABASE!D69 -> 0.004306 | C65: =DSADATABASE!E69 -> 0.004306 | F65: =ROUND(SUM(F$56:$F58)*$B65,0) -> 8332082 | H65: =ROUND(SUM(H$56:H58)*$C65,0) -> 8517289
F66: =SUM(F60:F65) -> 743411476 | H66: =SUM(H60:H65) -> 755447671
A67: TOTAL POSITIONS/SALARIES
A68: AND FRINGE BENEFITS | E68: =E54+E66 -> 35659.56 | F68: =F56+F57+F58+F66 -> 2.6784049e+09 | G68: =G54+G66 -> 35787.36 | H68: =H56+H57+H58+H66 -> 2.7334527e+09
A69: BENEFIT/SALARY RATIO | F69: =F66/F54 -> 0.3913399 | H69: =H66/H54 -> 0.38889835
B70: =+M200SAL!B67 -> FY12 | C70: =+B70 -> FY12 | D70: Net | E70: =+M200SAL!E67 -> FY13 | F70: =+E70 -> FY13 | G70: Net
A71: Summary | B71: M200 | C71: M300 | D71: Diff | E71: M200 | F71: M300 | G71: Diff
A72: Salaries | B72: =M200SAL!C69 -> 1899656724 | C72: =F56 -> 1.8782856e+09 | D72: =C72-B72 -> -21371138 | E72: =M200SAL!F69 -> 1942532468 | F72: =H56 -> 1.920679e+09 | G72: =F72-E72 -> -21853490
A73: Substitute Salaries | B73: =M200SAL!C70 -> 36035813 | C73: =F57 -> 36035813 | D73: =C73-B73 -> 0 | E73: =M200SAL!F70 -> 36164974 | F73: =H57 -> 36164974 | G73: =F73-E73 -> 0
A74: Extra Duty, Misc Salaries | B74: =M200SAL!C71 -> 20672024 | C74: =F58 -> 20672024 | D74: =C74-B74 -> 0 | E74: =M200SAL!F71 -> 21161040 | F74: =H58 -> 21161040 | G74: =F74-E74 -> 0
A75: Retirement | B75: =M200SAL!C72 -> 4.084262e+08 | C75: =F60 -> 446092827 | D75: =C75-B75 -> 37666631 | E75: =M200SAL!F72 -> 4.1764448e+08 | F75: =H60 -> 456161257 | G75: =F75-E75 -> 38516776
A76: Worker's Comp | B76: =M200SAL!C73 -> 7974142 | C76: =F61 -> 7887033 | D76: =C76-B76 -> -87109 | E76: =M200SAL!F73 -> 8151423 | F76: =H61 -> 8062348 | G76: =F76-E76 -> -89075
A77: Unemp Comp | B77: =M200SAL!C74 -> 7027262 | C77: =F62 -> 6950496 | D77: =C77-B77 -> -76766 | E77: =M200SAL!F74 -> 7183492 | F77: =H62 -> 7104994 | G77: =F77-E77 -> -78498
A78: Medicare | B78: =M200SAL!C75 -> 25499256 | C78: =F63 -> 25220704 | D78: =C78-B78 -> -278552 | E78: =M200SAL!F75 -> 26066155 | F78: =H63 -> 25781317 | G78: =F78-E78 -> -284838
A79: Medical | B79: =M200SAL!C76 -> 248928334 | C79: =F64 -> 248928334 | D79: =C79-B79 -> 0 | E79: =M200SAL!F76 -> 249820466 | F79: =H64 -> 249820466 | G79: =F79-E79 -> 0
A80: Other | B80: =M200SAL!C77 -> 8424106 | C80: =F65 -> 8332082 | D80: =C80-B80 -> -92024 | E80: =M200SAL!F77 -> 8611391 | F80: =H65 -> 8517289 | G80: =F80-E80 -> -94102
A82: Total Salaries and Fringe Benefits | B82: =SUM(B72:B80) -> 2.6626439e+09 | C82: =SUM(C72:C80) -> 2.6784049e+09 | D82: =C82-B82 -> 15761042 | E82: =SUM(E72:E80) -> 2.7173359e+09 | F82: =SUM(F72:F80) -> 2.7334527e+09 | G82: =F82-E82 -> 16116773
D83: =D82/B82 -> 0.0059193204 | G83: =G82/E82 -> 0.0059310935
D84: PERS+UI | G84: PERS+UI

Sheet E670SAL
A1: DISTRIBUTIVE SCHOOL ACCOUNT - DECISION E-670 SALARY
B2: =BASESAL!B2 -> FY10 | C2: =BASESAL!C2 -> FY11 | D2: =BASESAL!D2 -> FY11 | E2: =BASESAL!E2 -> FY12 | F2: =BASESAL!F2 -> FY12 | G2: =BASESAL!G2 -> FY13 | H2: =BASESAL!H2 -> FY13
B3: POS | C3: POS | D3: $ | E3: POS | F3: $ | G3: POS | H3: $
A4: WEIGHTED ENROLLMENT | B4: =M300SAL!B4 -> 425527.2 | C4: =M300SAL!C4 -> 422569.6 | E4: =M300SAL!E4 -> 421987.1 | G4: =M300SAL!G4 -> 423499.6
A5: AVG STARTING TEACHER SALARY | D5: =M300SAL!H5 -> 39166 | F5: =D5 -> 39166 | H5: =F5 -> 39166
A6: SALARY ADJUSTMENT (COLA) | F6: =DSADATABASE!J28 -> 0.975 | H6: =DSADATABASE!K28 -> 1
A7: INSTRUCTIONAL PERSONNEL
A8: LICENSED | B8: =M300SAL!B9 -> 20489.15 | C8: =M300SAL!C9 -> -143.96
A9: STUDENT RATIO | B9: =M300SAL!B10 -> 20.77 | E9: =(B8) -> 20489.15 | G9: =(E13) -> 20317.14
A10: 2%ROLL-UP | D10: =ROUND(C8*D5,0) -> -5638337 | E10: =(C8) -> -143.96 | F10: =ROUND(D10*1.02*F$6,0) -> -5607326 | H10: =ROUND((F10*1.02)*H$6,0) -> -5719473
A11: =M300SAL!A12 -> FY 10 AVG SALARY | B11: =M300SAL!B12 -> 53436 | D11: =ROUND(B8*B12,0) -> 1105799426 | F11: =ROUND(D11*1.02*F$6,0) -> 1099717529 | H11: =ROUND(((F11+F12)*1.02)*H$6,0) -> 1120619316
A12: =M300SAL!A13 -> FY11 = FY10 @ 1% Roll-Up Plus 0% Cola | B12: =M300SAL!B13 -> 53970 | E12: =ROUND((E$4/B9)-E9-E10,2) -> -28.05 | F12: =ROUND((E12*F5)*F$6,0) -> -1071141 | G12: =ROUND((G$4/B9)-G9-G10,2) -> 72.83 | H12: =ROUND((G12*H5)*H$6,0) -> 2852460
E13: =SUM(E9:E12) -> 20317.14 | F13: =SUM(F9:F12) -> 1093039062 | G13: =SUM(G9:G12) -> 20389.97 | H13: =SUM(H9:H12) -> 1117752303
A14: INSTRUCTIONAL PERSONNEL
A15: NON-LICENSED | B15: =M300SAL!B16 -> 2051.3 | C15: =M300SAL!C16 -> -14.23 | E15: =(B15) -> 2051.3 | G15: =(E19) -> 2034.26
A16: STUDENT RATIO | B16: =M300SAL!B17 -> 207.44 | D16: =ROUND(C15*DSADATABASE!K15,0) -> -330819 | E16: =(C15) -> -14.23 | F16: =ROUND(D16*1.02*F$6,0) -> -328999 | H16: =ROUND((F16*1.02)*H$6,0) -> -335579
A17: 2%ROLL-UP | D17: =ROUND(B15*B19,0) -> 64220049 | F17: =ROUND(D17*1.02*F$6,0) -> 63866839 | H17: =ROUND(((F17+F18)*1.02)*H$6,0) -> 65079208
A18: =$A$11 -> FY 10 AVG SALARY | B18: =M300SAL!B19 -> 30997 | E18: =ROUND((E$4/B16)-E15-E16,2) -> -2.81 | F18: =ROUND(M300SAL!F19*F6,0) -> -63694 | G18: =ROUND((G$4/B16)-G15-G16,2) -> 7.29 | H18: =ROUND(M300SAL!H19*H6,0) -> 169478
A19: =$A$12 -> FY11 = FY10 @ 1% Roll-Up Plus 0% Cola | B19: =M300SAL!B20 -> 31307 | E19: =SUM(E15:E18) -> 2034.26 | F19: =SUM(F15:F18) -> 63474146 | G19: =SUM(G15:G18) -> 2041.55 | H19: =SUM(H15:H18) -> 64913107
A21: INSTRUCTION SUPPORT PERSONNEL
A22: LICENSED | B22: =M300SAL!B23 -> 2328.71 | C22: =M300SAL!C23 -> -16.17 | E22: =(B22) -> 2328.71 | G22: =(E26) -> 2309.35
A23: STUDENT RATIO | B23: =M300SAL!B24 -> 182.73 | D23: =ROUND(C22*DSADATABASE!K16,0) -> -790438 | E23: =(C22) -> -16.17 | F23: =ROUND(D23*1.02*F$6,0) -> -786091 | H23: =ROUND((F23*1.02)*H$6,0) -> -801813
A24: 2%ROLL-UP | D24: =ROUND(B22*B26,0) -> 153296651 | F24: =ROUND(D24*1.02*F$6,0) -> 152453519 | H24: =ROUND(((F24+F25)*1.02)*H$6,0) -> 155347510
A25: =$A$11 -> FY 10 AVG SALARY | B25: =M300SAL!B26 -> 65177 | E25: =ROUND((E$4/B23)-E22-E23,2) -> -3.19 | F25: =ROUND(M300SAL!F26*F6,0) -> -152039 | G25: =ROUND((G$4/B23)-G22-G23,2) -> 8.27 | H25: =ROUND(M300SAL!H26*H6,0) -> 404262
A26: =$A$12 -> FY11 = FY10 @ 1% Roll-Up Plus 0% Cola | B26: =M300SAL!B27 -> 65829 | E26: =SUM(E22:E25) -> 2309.35 | F26: =SUM(F22:F25) -> 151515389 | G26: =SUM(G22:G25) -> 2317.62 | H26: =SUM(H22:H25) -> 154949959
A28: NON-LICENSED | B28: =M300SAL!B29 -> 959.07 | C28: =M300SAL!C29 -> -6.67 | E28: =(B28) -> 959.07 | G28: =(E32) -> 951.09
A29: STUDENT RATIO | B29: =M300SAL!B30 -> 443.69 | D29: =ROUND(C28*DSADATABASE!K17,0) -> -195925 | E29: =(C28) -> -6.67 | F29: =ROUND(D29*1.02*F$6,0) -> -194847 | H29: =ROUND((F29*1.02)*H$6,0) -> -198744
A30: 2%ROLL-UP | D30: =ROUND(B28*B32,0) -> 37937932 | F30: =ROUND(D30*1.02*F$6,0) -> 37729273 | H30: =ROUND(((F30+F31)*1.02)*H$6,0) -> 38445590
A31: =$A$11 -> FY 10 AVG SALARY | B31: =M300SAL!B32 -> 39165 | E31: =ROUND((E$4/B29)-E28-E29,2) -> -1.31 | F31: =ROUND(M300SAL!F32*F6,0) -> -37518 | G31: =ROUND((G$4/B29)-G28-G29,2) -> 3.4 | H31: =ROUND(M300SAL!H32*H6,0) -> 99872
A32: =$A$12 -> FY11 = FY10 @ 1% Roll-Up Plus 0% Cola | B32: =M300SAL!B33 -> 39557 | E32: =SUM(E28:E31) -> 951.09 | F32: =SUM(F28:F31) -> 37496908 | G32: =SUM(G28:G31) -> 954.49 | H32: =SUM(H28:H31) -> 38346718
A34: ADMINISTRATIVE SUPPORT PERSONNEL
A35: LICENSED | B35: =M300SAL!B36 -> 1405.47 | C35: =M300SAL!C36 -> -9.79 | E35: =(B35) -> 1405.47 | G35: =(E39) -> 1393.75
A36: STUDENT RATIO | B36: =M300SAL!B37 -> 302.77 | D36: =ROUND(C35*DSADATABASE!K18,0) -> -643967 | E36: =(C35) -> -9.79 | F36: =ROUND(D36*1.02*F$6,0) -> -640425 | H36: =ROUND((F36*1.02)*H$6,0) -> -653234
A37: 2%ROLL-UP | D37: =ROUND(B35*B39,0) -> 124497938 | F37: =ROUND(D37*1.02*F$6,0) -> 123813199 | H37: =ROUND(((F37+F38)*1.02)*H$6,0) -> 126163209
A38: =$A$11 -> FY 10 AVG SALARY | B38: =M300SAL!B39 -> 87704 | E38: =ROUND((E$4/B36)-E35-E36,2) -> -1.93 | F38: =ROUND(M300SAL!F39*F6,0) -> -123778 | G38: =ROUND((G$4/B36)-G35-G36,2) -> 5 | H38: =ROUND(M300SAL!H39*H6,0) -> 328890
A39: =$A$12 -> FY11 = FY10 @ 1% Roll-Up Plus 0% Cola | B39: =M300SAL!B40 -> 88581 | E39: =SUM(E35:E38) -> 1393.75 | F39: =SUM(F35:F38) -> 123048996 | G39: =SUM(G35:G38) -> 1398.75 | H39: =SUM(H35:H38) -> 125838865
A41: NON-LICENSED | B41: =M300SAL!B42 -> 2881.37 | C41: =M300SAL!C42 -> -19.98 | E41: =(B41) -> 2881.37 | G41: =(E45) -> 2857.44
A42: STUDENT RATIO | B42: =M300SAL!B43 -> 147.68 | D42: =ROUND(C41*DSADATABASE!K19,0) -> -692447 | E42: =(C41) -> -19.98 | F42: =ROUND(D42*1.02*F$6,0) -> -688639 | H42: =ROUND((F42*1.02)*H$6,0) -> -702412
A43: 2%ROLL-UP | D43: =ROUND(B41*B45,0) -> 133145226 | F43: =ROUND(D43*1.02*F$6,0) -> 132412927 | H43: =ROUND(((F43+F44)*1.02)*H$6,0) -> 134925043
A44: =$A$11 -> FY 10 AVG SALARY | B44: =M300SAL!B45 -> 46209 | E44: =ROUND((E$4/B42)-E41-E42,2) -> -3.95 | F44: =ROUND(M300SAL!F45*F6,0) -> -133473 | G44: =ROUND((G$4/B42)-G41-G42,2) -> 10.24 | H44: =ROUND(M300SAL!H45*H6,0) -> 354888
A45: =$A$12 -> FY11 = FY10 @ 1% Roll-Up Plus 0% Cola | B45: =M300SAL!B46 -> 46209 | E45: =SUM(E41:E44) -> 2857.44 | F45: =SUM(F41:F44) -> 131590815 | G45: =SUM(G41:G44) -> 2867.68 | H45: =SUM(H41:H44) -> 134577519
A47: OTHER LICENSED & NON-LICENSED | B47: =M300SAL!B48 -> 5844.97 | C47: =M300SAL!C48 -> -40.44 | E47: =(B47) -> 5844.97 | G47: =(E51) -> 5796.53
A48: STUDENT RATIO | B48: =M300SAL!B49 -> 72.8 | D48: =ROUND(C47*DSADATABASE!K20,0) -> -1309892 | E48: =(C47) -> -40.44 | F48: =ROUND(D48*1.02*F$6,0) -> -1302688 | H48: =ROUND((F48*1.02)*H$6,0) -> -1328742
A49: 2%ROLL-UP | D49: =ROUND(B47*B51,0) -> 254957591 | F49: =ROUND(D49*1.02*F$6,0) -> 253555324 | H49: =ROUND(((F49+F50)*1.02)*H$6,0) -> 258368727
A50: =$A$11 -> FY 10 AVG SALARY | B50: =M300SAL!B51 -> 43188 | E50: =ROUND((E$4/B48)-E47-E48,2) -> -8 | F50: =ROUND(M300SAL!F51*F6,0) -> -252650 | G50: =ROUND((G$4/B48)-G47-G48,2) -> 20.77 | H50: =ROUND(M300SAL!H51*H6,0) -> 672761
A51: =$A$12 -> FY11 = FY10 @ 1% Roll-Up Plus 0% Cola | B51: =M300SAL!B52 -> 43620 | E51: =SUM(E47:E50) -> 5796.53 | F51: =SUM(F47:F50) -> 251999986 | G51: =SUM(G47:G50) -> 5817.3 | H51: =SUM(H47:H50) -> 257712746
A53: TOTAL SALARIES | B53: =+B8+B15+B22+B28+B35+B41+B47 -> 35960.04 | C53: =+C8+C15+C22+C28+C35+C41+C47 -> -251.24 | E53: =SUM(E13+E19+E26+E32+E39+E45+E51) -> 35659.56 | F53: =SUM(F13+F19+F26+F32+F39+F45+F51) -> 1852165302 | G53: =SUM(G13+G19+G26+G32+G39+G45+G51) -> 35787.36 | H53: =SUM(H13+H19+H26+H32+H39+H45+H51) -> 1894091217
A54: PERS Rate Change (23.75%-21.5%*.50) | F54: =-F53*(0.2375-0.215)*0.5 -> -20836860 | H54: =-H53*(0.2375-0.215)*0.5 -> -21308526
A55: TOTAL SALARIES LESS PERS RATE CHANGE | F55: =+F53+F54 -> 1.8313284e+09 | H55: =+H53+H54 -> 1.8727827e+09
A56: SUBSTITUTE SALARIES | F56: =M300SAL!F57 -> 36035813 | H56: =M300SAL!H57 -> 36164974
A57: =M300SAL!A58 -> EXTRA PAY, MISC SALARIES | F57: =M300SAL!F58 -> 20672024 | H57: =M300SAL!H58 -> 21161040
A58: FRINGE BENEFITS
A59: RETIREMENT | B59: =M300SAL!B60 -> 0.2375 | C59: =M300SAL!C60 -> 0.2375 | F59: =ROUND(F$55*B59,0) -> 434940505 | H59: =ROUND(H$55*C59,0) -> 444785889
A60: SIIS | B60: =M300SAL!B61 -> 0.004076 | C60: =M300SAL!C61 -> 0.004076 | F60: =ROUND(SUM(F$55:F$57)*B60,0) -> 7695636 | H60: =ROUND(SUM(H$55:H$57)*C60,0) -> 7867123
A61: UNEMP INS | B61: =M300SAL!B62 -> 0.003592 | C61: =M300SAL!C62 -> 0.003592 | F61: =ROUND(SUM(F$55:F$57)*B61,0) -> 6781826 | H61: =ROUND(SUM(H$55:H$57)*C61,0) -> 6932950
A62: MEDICARE | B62: =M300SAL!B63 -> 0.013034 | C62: =M300SAL!C63 -> 0.013034 | F62: =ROUND(SUM(F$55:F$57)*B62,0) -> 24608665 | H62: =ROUND(SUM(H$55:H$57)*C62,0) -> 25157037
A63: MEDICAL INS | B63: =M300SAL!B64 -> 6980.69 | C63: =M300SAL!C64 -> 6980.69 | F63: =ROUND(E$53*B63,0) -> 248928334 | H63: =ROUND(G$53*C63,0) -> 249820466
A64: OTHER | B64: =M300SAL!B65 -> 0.004306 | C64: =M300SAL!C65 -> 0.004306 | F64: =ROUND(SUM(F$55:$F57)*$B64,0) -> 8129884 | H64: =ROUND(SUM(H$55:H57)*$C64,0) -> 8311048
F65: =SUM(F59:F64) -> 731084850 | H65: =SUM(H59:H64) -> 742874513
A66: TOTAL POSITIONS/SALARIES
A67: AND FRINGE BENEFITS | E67: =E53+E65 -> 35659.56 | F67: =F55+F56+F57+F65 -> 2.6191211e+09 | G67: =G53+G65 -> 35787.36 | H67: =H55+H56+H57+H65 -> 2.6729832e+09
A68: BENEFIT/SALARY RATIO | F68: =F65/F53 -> 0.39471901 | H68: =H65/H53 -> 0.3922063
B69: =+M200SAL!B67 -> FY12 | C69: =+B69 -> FY12 | D69: Net | E69: =+M200SAL!E67 -> FY13 | F69: =+E69 -> FY13 | G69: Net
A70: Summary | B70: M300 | C70: E670 | D70: Diff | E70: M300 | F70: E670 | G70: Diff
A71: Salaries | B71: =M300SAL!C72 -> 1.8782856e+09 | C71: =F55 -> 1.8313284e+09 | D71: =C71-B71 -> -46957144 | E71: =M300SAL!F72 -> 1.920679e+09 | F71: =H55 -> 1.8727827e+09 | G71: =F71-E71 -> -47896287
A72: Substitute Salaries | B72: =M300SAL!C73 -> 36035813 | C72: =F56 -> 36035813 | D72: =C72-B72 -> 0 | E72: =M300SAL!F73 -> 36164974 | F72: =H56 -> 36164974 | G72: =F72-E72 -> 0
A73: Extra Duty, Misc Salaries | B73: =M300SAL!C74 -> 20672024 | C73: =F57 -> 20672024 | D73: =C73-B73 -> 0 | E73: =M300SAL!F74 -> 21161040 | F73: =H57 -> 21161040 | G73: =F73-E73 -> 0
A74: Retirement | B74: =M300SAL!C75 -> 446092827 | C74: =F59 -> 434940505 | D74: =C74-B74 -> -11152322 | E74: =M300SAL!F75 -> 456161257 | F74: =H59 -> 444785889 | G74: =F74-E74 -> -11375368
A75: SIIS | B75: =M300SAL!C76 -> 7887033 | C75: =F60 -> 7695636 | D75: =C75-B75 -> -191397 | E75: =M300SAL!F76 -> 8062348 | F75: =H60 -> 7867123 | G75: =F75-E75 -> -195225
A76: Unemp Comp | B76: =M300SAL!C77 -> 6950496 | C76: =F61 -> 6781826 | D76: =C76-B76 -> -168670 | E76: =M300SAL!F77 -> 7104994 | F76: =H61 -> 6932950 | G76: =F76-E76 -> -172044
A77: Medicare | B77: =M300SAL!C78 -> 25220704 | C77: =F62 -> 24608665 | D77: =C77-B77 -> -612039 | E77: =M300SAL!F78 -> 25781317 | F77: =H62 -> 25157037 | G77: =F77-E77 -> -624280
A78: Medical | B78: =M300SAL!C79 -> 248928334 | C78: =F63 -> 248928334 | D78: =C78-B78 -> 0 | E78: =M300SAL!F79 -> 249820466 | F78: =H63 -> 249820466 | G78: =F78-E78 -> 0
A79: Other | B79: =M300SAL!C80 -> 8332082 | C79: =F64 -> 8129884 | D79: =C79-B79 -> -202198 | E79: =M300SAL!F80 -> 8517289 | F79: =H64 -> 8311048 | G79: =F79-E79 -> -206241
A81: Total Salaries and Fringe Benefits | B81: =SUM(B71:B79) -> 2.6784049e+09 | C81: =SUM(C71:C79) -> 2.6191211e+09 | D81: =C81-B81 -> -59283770 | E81: =SUM(E71:E79) -> 2.7334527e+09 | F81: =SUM(F71:F79) -> 2.6729832e+09 | G81: =F81-E81 -> -60469445
D83: =D81+D82 -> -59283770 | G83: =G81+G82 -> -60469445

Sheet E671SAL
A1: DISTRIBUTIVE SCHOOL ACCOUNT - DECISION E-671 SALARY
B2: =BASESAL!B2 -> FY10 | C2: =BASESAL!C2 -> FY11 | D2: =BASESAL!D2 -> FY11 | E2: =BASESAL!E2 -> FY12 | F2: =BASESAL!F2 -> FY12 | G2: =BASESAL!G2 -> FY13 | H2: =BASESAL!H2 -> FY13
B3: POS | C3: POS | D3: $ | E3: POS | F3: $ | G3: POS | H3: $
A4: WEIGHTED ENROLLMENT | B4: =E670SAL!B4 -> 425527.2 | C4: =E670SAL!C4 -> 422569.6 | E4: =E670SAL!E4 -> 421987.1 | G4: =E670SAL!G4 -> 423499.6
A5: AVG STARTING TEACHER SALARY | D5: =E670SAL!H5 -> 39166 | F5: =D5 -> 39166 | H5: =F5 -> 39166
A6: SALARY ADJUSTMENT (COLA) | F6: =DSADATABASE!J28 -> 0.975 | H6: =DSADATABASE!K28 -> 1
A8: INSTRUCTIONAL PERSONNEL
A9: LICENSED | B9: =E670SAL!B8 -> 20489.15 | C9: =E670SAL!C8 -> -143.96 | E9: =(B9) -> 20489.15 | G9: =(E13) -> 20317.14
A10: STUDENT RATIO | B10: =E670SAL!B9 -> 20.77 | D10: =ROUND(C9*D5,0) -> -5638337 | E10: =(C9) -> -143.96 | F10: =ROUND(D10*1.02*F$6,0) -> -5607326 | H10: =ROUND((F10*1.02)*H$6,0) -> -5719473
A11: 2%ROLL-UP | D11: =ROUND(B9*B13,0) -> 1105799426 | F11: =ROUND(D11*1.02*F$6,0) -> 1099717529 | H11: =ROUND(((F11+F12)*1.02)*H$6,0) -> 1120619316
A12: =BASESAL!A11 -> FY 10 AVG SALARY | B12: =E670SAL!B11 -> 53436 | E12: =ROUND((E$4/B10)-E9-E10,2) -> -28.05 | F12: =ROUND((E12*F$5*1)*F$6,0) -> -1071141 | G12: =ROUND((G$4/B10)-G9-G10,2) -> 72.83 | H12: =ROUND((G12*H5*1)*H$6,0) -> 2852460
A13: =M200SAL!A12 -> FY11 = FY10 @ 1% Roll-Up Plus 0% Cola | B13: =E670SAL!B12 -> 53970 | E13: =SUM(E9:E12) -> 20317.14 | F13: =SUM(F9:F12) -> 1093039062 | G13: =SUM(G9:G12) -> 20389.97 | H13: =SUM(H9:H12) -> 1117752303
A15: INSTRUCTIONAL PERSONNEL
A16: NON-LICENSED | B16: =E670SAL!B15 -> 2051.3 | C16: =E670SAL!C15 -> -14.23 | E16: =(B16) -> 2051.3 | G16: =(E20) -> 2034.26
A17: STUDENT RATIO | B17: =E670SAL!B16 -> 207.44 | D17: =ROUND(C16*DSADATABASE!K15,0) -> -330819 | E17: =(C16) -> -14.23 | F17: =ROUND(D17*1.02*F$6,0) -> -328999 | H17: =ROUND((F17*1.02)*H$6,0) -> -335579
A18: 2%ROLL-UP | D18: =ROUND(B16*B20,0) -> 64220049 | F18: =ROUND(D18*1.02*F$6,0) -> 63866839 | H18: =ROUND(((F18+F19)*1.02)*H$6,0) -> 65079208
A19: =$A$12 -> FY 10 AVG SALARY | B19: =E670SAL!B18 -> 30997 | E19: =ROUND((E$4/B17)-E16-E17,2) -> -2.81 | F19: =E670SAL!F18*1 -> -63694 | G19: =ROUND((G$4/B17)-G16-G17,2) -> 7.29 | H19: =E670SAL!H18*1 -> 169478
A20: =$A$13 -> FY11 = FY10 @ 1% Roll-Up Plus 0% Cola | B20: =E670SAL!B19 -> 31307 | E20: =SUM(E16:E19) -> 2034.26 | F20: =SUM(F16:F19) -> 63474146 | G20: =SUM(G16:G19) -> 2041.55 | H20: =SUM(H16:H19) -> 64913107
A22: INSTRUCTION SUPPORT PERSONNEL
A23: LICENSED | B23: =E670SAL!B22 -> 2328.71 | C23: =E670SAL!C22 -> -16.17 | E23: =(B23) -> 2328.71 | G23: =(E27) -> 2309.35
A24: STUDENT RATIO | B24: =E670SAL!B23 -> 182.73 | D24: =ROUND(C23*DSADATABASE!K16,0) -> -790438 | E24: =(C23) -> -16.17 | F24: =ROUND(D24*1.02*F$6,0) -> -786091 | H24: =ROUND((F24*1.02)*H$6,0) -> -801813
A25: 2%ROLL-UP | D25: =ROUND(B23*B27,0) -> 153296651 | F25: =ROUND(D25*1.02*F$6,0) -> 152453519 | H25: =ROUND(((F25+F26)*1.02)*H$6,0) -> 155347510
A26: =$A$12 -> FY 10 AVG SALARY | B26: =E670SAL!B25 -> 65177 | E26: =ROUND((E$4/B24)-E23-E24,2) -> -3.19 | F26: =E670SAL!F25*1 -> -152039 | G26: =ROUND((G$4/B24)-G23-G24,2) -> 8.27 | H26: =E670SAL!H25*1 -> 404262
A27: =$A$13 -> FY11 = FY10 @ 1% Roll-Up Plus 0% Cola | B27: =E670SAL!B26 -> 65829 | E27: =SUM(E23:E26) -> 2309.35 | F27: =SUM(F23:F26) -> 151515389 | G27: =SUM(G23:G26) -> 2317.62 | H27: =SUM(H23:H26) -> 154949959
A29: NON-LICENSED | B29: =E670SAL!B28 -> 959.07 | C29: =E670SAL!C28 -> -6.67 | E29: =(B29) -> 959.07 | G29: =(E33) -> 951.09
A30: STUDENT RATIO | B30: =E670SAL!B29 -> 443.69 | D30: =ROUND(C29*DSADATABASE!K17,0) -> -195925 | E30: =(C29) -> -6.67 | F30: =ROUND(D30*1.02*F$6,0) -> -194847 | H30: =ROUND((F30*1.02)*H$6,0) -> -198744
A31: 2%ROLL-UP | D31: =ROUND(B29*B33,0) -> 37937932 | F31: =ROUND(D31*1.02*F$6,0) -> 37729273 | H31: =ROUND(((F31+F32)*1.02)*H$6,0) -> 38445590
A32: =$A$12 -> FY 10 AVG SALARY | B32: =E670SAL!B31 -> 39165 | E32: =ROUND((E$4/B30)-E29-E30,2) -> -1.31 | F32: =E670SAL!F31*1 -> -37518 | G32: =ROUND((G$4/B30)-G29-G30,2) -> 3.4 | H32: =E670SAL!H31*1 -> 99872
A33: =$A$13 -> FY11 = FY10 @ 1% Roll-Up Plus 0% Cola | B33: =E670SAL!B32 -> 39557 | E33: =SUM(E29:E32) -> 951.09 | F33: =SUM(F29:F32) -> 37496908 | G33: =SUM(G29:G32) -> 954.49 | H33: =SUM(H29:H32) -> 38346718
A35: ADMINISTRATIVE SUPPORT PERSONNEL
A36: LICENSED | B36: =E670SAL!B35 -> 1405.47 | C36: =E670SAL!C35 -> -9.79 | E36: =(B36) -> 1405.47 | G36: =(E40) -> 1393.75
A37: STUDENT RATIO | B37: =E670SAL!B36 -> 302.77 | D37: =ROUND(C36*DSADATABASE!K18,0) -> -643967 | E37: =(C36) -> -9.79 | F37: =ROUND(D37*1.02*F$6,0) -> -640425 | H37: =ROUND((F37*1.02)*H$6,0) -> -653234
A38: 2%ROLL-UP | D38: =ROUND(B36*B40,0) -> 124497938 | F38: =ROUND(D38*1.02*F$6,0) -> 123813199 | H38: =ROUND(((F38+F39)*1.02)*H$6,0) -> 126163209
A39: =$A$12 -> FY 10 AVG SALARY | B39: =E670SAL!B38 -> 87704 | E39: =ROUND((E$4/B37)-E36-E37,2) -> -1.93 | F39: =E670SAL!F38*1 -> -123778 | G39: =ROUND((G$4/B37)-G36-G37,2) -> 5 | H39: =E670SAL!H38*1 -> 328890
A40: =$A$13 -> FY11 = FY10 @ 1% Roll-Up Plus 0% Cola | B40: =E670SAL!B39 -> 88581 | E40: =SUM(E36:E39) -> 1393.75 | F40: =SUM(F36:F39) -> 123048996 | G40: =SUM(G36:G39) -> 1398.75 | H40: =SUM(H36:H39) -> 125838865
A42: NON-LICENSED | B42: =E670SAL!B41 -> 2881.37 | C42: =E670SAL!C41 -> -19.98 | E42: =(B42) -> 2881.37 | G42: =(E46) -> 2857.44
A43: STUDENT RATIO | B43: =E670SAL!B42 -> 147.68 | D43: =ROUND(C42*DSADATABASE!K19,0) -> -692447 | E43: =(C42) -> -19.98 | F43: =ROUND(D43*1.02*F$6,0) -> -688639 | H43: =ROUND((F43*1.02)*H$6,0) -> -702412
A44: 2%ROLL-UP | D44: =ROUND(B42*B46,0) -> 133145226 | F44: =ROUND(D44*1.02*F$6,0) -> 132412927 | H44: =ROUND(((F44+F45)*1.02)*H$6,0) -> 134925043
A45: =$A$12 -> FY 10 AVG SALARY | B45: =E670SAL!B44 -> 46209 | E45: =ROUND((E$4/B43)-E42-E43,2) -> -3.95 | F45: =E670SAL!F44*1 -> -133473 | G45: =ROUND((G$4/B43)-G42-G43,2) -> 10.24 | H45: =E670SAL!H44*1 -> 354888
A46: =$A$13 -> FY11 = FY10 @ 1% Roll-Up Plus 0% Cola | B46: =E670SAL!B45 -> 46209 | E46: =SUM(E42:E45) -> 2857.44 | F46: =SUM(F42:F45) -> 131590815 | G46: =SUM(G42:G45) -> 2867.68 | H46: =SUM(H42:H45) -> 134577519
A48: OTHER LICENSED & NON-LICENSED | B48: =E670SAL!B47 -> 5844.97 | C48: =E670SAL!C47 -> -40.44 | E48: =(B48) -> 5844.97 | G48: =(E52) -> 5796.53
A49: STUDENT RATIO | B49: =E670SAL!B48 -> 72.8 | D49: =ROUND(C48*DSADATABASE!K20,0) -> -1309892 | E49: =(C48) -> -40.44 | F49: =ROUND(D49*1.02*F$6,0) -> -1302688 | H49: =ROUND((F49*1.02)*H$6,0) -> -1328742
A50: 2%ROLL-UP | D50: =ROUND(B48*B52,0) -> 254957591 | F50: =ROUND(D50*1.02*F$6,0) -> 253555324 | H50: =ROUND(((F50+F51)*1.02)*H$6,0) -> 258368727
A51: =$A$12 -> FY 10 AVG SALARY | B51: =E670SAL!B50 -> 43188 | E51: =ROUND((E$4/B49)-E48-E49,2) -> -8 | F51: =E670SAL!F50*1 -> -252650 | G51: =ROUND((G$4/B49)-G48-G49,2) -> 20.77 | H51: =E670SAL!H50*1 -> 672761
A52: =$A$13 -> FY11 = FY10 @ 1% Roll-Up Plus 0% Cola | B52: =E670SAL!B51 -> 43620 | E52: =SUM(E48:E51) -> 5796.53 | F52: =SUM(F48:F51) -> 251999986 | G52: =SUM(G48:G51) -> 5817.3 | H52: =SUM(H48:H51) -> 257712746
A54: TOTAL SALARIES | B54: =+B9+B16+B23+B29+B36+B42+B48 -> 35960.04 | C54: =+C9+C16+C23+C29+C36+C42+C48 -> -251.24 | E54: =SUM(E13+E20+E27+E33+E40+E46+E52) -> 35659.56 | F54: =SUM(F13+F20+F27+F33+F40+F46+F52) -> 1852165302 | G54: =SUM(G13+G20+G27+G33+G40+G46+G52) -> 35787.36 | H54: =SUM(H13+H20+H27+H33+H40+H46+H52) -> 1894091217
A55: PERS Rate Change (23.75%-21.5%*.50) | F55: =-F54*(0.2375-0.215)*0.5 -> -20836860 | H55: =-H54*(0.2375-0.215)*0.5 -> -21308526
A56: TOTAL SALARIES LESS PERS RATE CHANGE | F56: =+F54+F55 -> 1.8313284e+09 | H56: =+H54+H55 -> 1.8727827e+09
A57: SUBSTITUTE SALARIES | F57: =E670SAL!F56 -> 36035813 | H57: =E670SAL!H56 -> 36164974
A58: =M200SAL!A55 -> EXTRA PAY, MISC SALARIES | F58: =E670SAL!F57 -> 20672024 | H58: =E670SAL!H57 -> 21161040
A59: FRINGE BENEFITS
A60: RETIREMENT | B60: =E670SAL!B59 -> 0.2375 | C60: =E670SAL!C59 -> 0.2375 | F60: =ROUND(F$56*B60,0) -> 434940505 | H60: =ROUND(H$56*C60,0) -> 444785889
A61: WORKER'S COMP | B61: =E670SAL!B60 -> 0.004076 | C61: =E670SAL!C60 -> 0.004076 | F61: =ROUND(SUM(F$56:F$58)*B61,0) -> 7695636 | H61: =ROUND(SUM(H$56:H$58)*C61,0) -> 7867123
A62: UNEMP INS | B62: =E670SAL!B61 -> 0.003592 | C62: =E670SAL!C61 -> 0.003592 | F62: =ROUND(SUM(F$56:F$58)*B62,0) -> 6781826 | H62: =ROUND(SUM(H$56:H$58)*C62,0) -> 6932950
A63: MEDICARE | B63: =E670SAL!B62 -> 0.013034 | C63: =E670SAL!C62 -> 0.013034 | F63: =ROUND(SUM(F$56:F$58)*B63,0) -> 24608665 | H63: =ROUND(SUM(H$56:H$58)*C63,0) -> 25157037
A64: MEDICAL INS | B64: =E670SAL!B63 -> 6980.69 | C64: =E670SAL!C63 -> 6980.69 | F64: =ROUND(E$54*B64,0) -> 248928334 | H64: =ROUND(G$54*C64,0) -> 249820466
A65: OTHER | B65: =E670SAL!B64 -> 0.004306 | C65: =E670SAL!C64 -> 0.004306 | F65: =ROUND(SUM(F$56:$F58)*$B65,0) -> 8129884 | H65: =ROUND(SUM(H$56:H58)*$C65,0) -> 8311048
F66: =SUM(F60:F65) -> 731084850 | H66: =SUM(H60:H65) -> 742874513
A67: TOTAL POSITIONS/SALARIES
A68: AND FRINGE BENEFITS | E68: =E54+E66 -> 35659.56 | F68: =F56+F57+F58+F66 -> 2.6191211e+09 | G68: =G54+G66 -> 35787.36 | H68: =H56+H57+H58+H66 -> 2.6729832e+09
A69: BENEFIT/SALARY RATIO | F69: =F66/F54 -> 0.39471901 | H69: =H66/H54 -> 0.3922063
B70: =+M200SAL!B67 -> FY12 | C70: =+B70 -> FY12 | D70: Net | E70: =+M200SAL!E67 -> FY13 | F70: =+E70 -> FY13 | G70: Net
A71: Summary | B71: E670 | C71: E671 | D71: Diff | E71: E670 | F71: E671 | G71: Diff
A72: Salaries | B72: =E670SAL!C71 -> 1.8313284e+09 | C72: =F56 -> 1.8313284e+09 | D72: =C72-B72 -> 0 | E72: =E670SAL!F71 -> 1.8727827e+09 | F72: =H56 -> 1.8727827e+09 | G72: =F72-E72 -> 0
A73: Substitute Salaries | B73: =E670SAL!C72 -> 36035813 | C73: =F57 -> 36035813 | D73: =C73-B73 -> 0 | E73: =E670SAL!F72 -> 36164974 | F73: =H57 -> 36164974 | G73: =F73-E73 -> 0
A74: Extra Duty, Misc Salaries | B74: =E670SAL!C73 -> 20672024 | C74: =F58 -> 20672024 | D74: =C74-B74 -> 0 | E74: =E670SAL!F73 -> 21161040 | F74: =H58 -> 21161040 | G74: =F74-E74 -> 0
A75: Retirement | B75: =E670SAL!C74 -> 434940505 | C75: =F60 -> 434940505 | D75: =C75-B75 -> 0 | E75: =E670SAL!F74 -> 444785889 | F75: =H60 -> 444785889 | G75: =F75-E75 -> 0
A76: Worker's Comp | B76: =E670SAL!C75 -> 7695636 | C76: =F61 -> 7695636 | D76: =C76-B76 -> 0 | E76: =E670SAL!F75 -> 7867123 | F76: =H61 -> 7867123 | G76: =F76-E76 -> 0
A77: Unemp Comp | B77: =E670SAL!C76 -> 6781826 | C77: =F62 -> 6781826 | D77: =C77-B77 -> 0 | E77: =E670SAL!F76 -> 6932950 | F77: =H62 -> 6932950 | G77: =F77-E77 -> 0
A78: Medicare | B78: =E670SAL!C77 -> 24608665 | C78: =F63 -> 24608665 | D78: =C78-B78 -> 0 | E78: =E670SAL!F77 -> 25157037 | F78: =H63 -> 25157037 | G78: =F78-E78 -> 0
A79: Medical | B79: =E670SAL!C78 -> 248928334 | C79: =F64 -> 248928334 | D79: =C79-B79 -> 0 | E79: =E670SAL!F78 -> 249820466 | F79: =H64 -> 249820466 | G79: =F79-E79 -> 0
A80: Other | B80: =E670SAL!C79 -> 8129884 | C80: =F65 -> 8129884 | D80: =C80-B80 -> 0 | E80: =E670SAL!F79 -> 8311048 | F80: =H65 -> 8311048 | G80: =F80-E80 -> 0
A81: Add back estimated column adjustments* | B81: 0 | C81: 0 | D81: =C81-B81 -> 0 | E81: 0 | F81: 0 | G81: =F81-E81 -> 0
A83: Total Salaries and Fringe Benefits | B83: =SUM(B72:B80) -> 2.6191211e+09 | C83: =SUM(C72:C81) -> 2.6191211e+09 | D83: =SUM(D72:D81) -> 0 | E83: =SUM(E72:E81) -> 2.6729832e+09 | F83: =SUM(F72:F82) -> 2.6729832e+09 | G83: =SUM(G72:G81) -> 0

Sheet E601 SAL
A1: DISTRIBUTIVE SCHOOL ACCOUNT - DECISION E-601 SALARY
B2: =BASESAL!B2 -> FY10 | C2: =BASESAL!C2 -> FY11 | D2: =BASESAL!D2 -> FY11 | E2: =BASESAL!E2 -> FY12 | F2: =BASESAL!F2 -> FY12 | G2: =BASESAL!G2 -> FY13 | H2: =BASESAL!H2 -> FY13
B3: POS | C3: POS | D3: $ | E3: POS | F3: $ | G3: POS | H3: $
A4: WEIGHTED ENROLLMENT | B4: =E670SAL!B4 -> 425527.2 | C4: =E670SAL!C4 -> 422569.6 | E4: =E670SAL!E4 -> 421987.1 | G4: =E670SAL!G4 -> 423499.6
A5: AVG STARTING TEACHER SALARY | D5: =E670SAL!H5 -> 39166 | F5: =D5 -> 39166 | H5: =F5 -> 39166
A6: SALARY ADJUSTMENT (COLA) | F6: =DSADATABASE!J28 -> 0.975 | H6: =DSADATABASE!K28 -> 1
A8: INSTRUCTIONAL PERSONNEL
A9: LICENSED | B9: =E670SAL!B8 -> 20489.15 | C9: =E670SAL!C8 -> -143.96 | E9: =(B9) -> 20489.15 | G9: =(E13) -> 20317.14
A10: STUDENT RATIO | B10: =E670SAL!B9 -> 20.77 | D10: =ROUND(C9*D5,0) -> -5638337 | E10: =(C9) -> -143.96 | F10: =ROUND(D10*1.02*F$6,0) -> -5607326 | H10: =ROUND((F10*1.02)*H$6,0) -> -5719473
A11: 2%ROLL-UP | D11: =ROUND(B9*B13,0) -> 1105799426 | F11: =ROUND(D11*1.02*F$6,0) -> 1099717529 | H11: =ROUND(((F11+F12)*1.02)*H$6,0) -> 1120619316
A12: =BASESAL!A11 -> FY 10 AVG SALARY | B12: =E670SAL!B11 -> 53436 | E12: =ROUND((E$4/B10)-E9-E10,2) -> -28.05 | F12: =ROUND((E12*F$5*1)*F$6,0) -> -1071141 | G12: =ROUND((G$4/B10)-G9-G10,2) -> 72.83 | H12: =ROUND((G12*H5*1)*H$6,0) -> 2852460
A13: =M200SAL!A12 -> FY11 = FY10 @ 1% Roll-Up Plus 0% Cola | B13: =E670SAL!B12 -> 53970 | E13: =SUM(E9:E12) -> 20317.14 | F13: =SUM(F9:F12) -> 1093039062 | G13: =SUM(G9:G12) -> 20389.97 | H13: =SUM(H9:H12) -> 1117752303
A15: INSTRUCTIONAL PERSONNEL
A16: NON-LICENSED | B16: =E670SAL!B15 -> 2051.3 | C16: =E670SAL!C15 -> -14.23 | E16: =(B16) -> 2051.3 | G16: =(E20) -> 2034.26
A17: STUDENT RATIO | B17: =E670SAL!B16 -> 207.44 | D17: =ROUND(C16*DSADATABASE!K15,0) -> -330819 | E17: =(C16) -> -14.23 | F17: =ROUND(D17*1.02*F$6,0) -> -328999 | H17: =ROUND((F17*1.02)*H$6,0) -> -335579
A18: 2%ROLL-UP | D18: =ROUND(B16*B20,0) -> 64220049 | F18: =ROUND(D18*1.02*F$6,0) -> 63866839 | H18: =ROUND(((F18+F19)*1.02)*H$6,0) -> 65079208
A19: =$A$12 -> FY 10 AVG SALARY | B19: =E670SAL!B18 -> 30997 | E19: =ROUND((E$4/B17)-E16-E17,2) -> -2.81 | F19: =E670SAL!F18*1 -> -63694 | G19: =ROUND((G$4/B17)-G16-G17,2) -> 7.29 | H19: =E670SAL!H18*1 -> 169478
A20: =$A$13 -> FY11 = FY10 @ 1% Roll-Up Plus 0% Cola | B20: =E670SAL!B19 -> 31307 | E20: =SUM(E16:E19) -> 2034.26 | F20: =SUM(F16:F19) -> 63474146 | G20: =SUM(G16:G19) -> 2041.55 | H20: =SUM(H16:H19) -> 64913107
A22: INSTRUCTION SUPPORT PERSONNEL
A23: LICENSED | B23: =E670SAL!B22 -> 2328.71 | C23: =E670SAL!C22 -> -16.17 | E23: =(B23) -> 2328.71 | G23: =(E27) -> 2309.35
A24: STUDENT RATIO | B24: =E670SAL!B23 -> 182.73 | D24: =ROUND(C23*DSADATABASE!K16,0) -> -790438 | E24: =(C23) -> -16.17 | F24: =ROUND(D24*1.02*F$6,0) -> -786091 | H24: =ROUND((F24*1.02)*H$6,0) -> -801813
A25: 2%ROLL-UP | D25: =ROUND(B23*B27,0) -> 153296651 | F25: =ROUND(D25*1.02*F$6,0) -> 152453519 | H25: =ROUND(((F25+F26)*1.02)*H$6,0) -> 155347510
A26: =$A$12 -> FY 10 AVG SALARY | B26: =E670SAL!B25 -> 65177 | E26: =ROUND((E$4/B24)-E23-E24,2) -> -3.19 | F26: =E670SAL!F25*1 -> -152039 | G26: =ROUND((G$4/B24)-G23-G24,2) -> 8.27 | H26: =E670SAL!H25*1 -> 404262
A27: =$A$13 -> FY11 = FY10 @ 1% Roll-Up Plus 0% Cola | B27: =E670SAL!B26 -> 65829 | E27: =SUM(E23:E26) -> 2309.35 | F27: =SUM(F23:F26) -> 151515389 | G27: =SUM(G23:G26) -> 2317.62 | H27: =SUM(H23:H26) -> 154949959
A29: NON-LICENSED | B29: =E670SAL!B28 -> 959.07 | C29: =E670SAL!C28 -> -6.67 | E29: =(B29) -> 959.07 | G29: =(E33) -> 951.09
A30: STUDENT RATIO | B30: =E670SAL!B29 -> 443.69 | D30: =ROUND(C29*DSADATABASE!K17,0) -> -195925 | E30: =(C29) -> -6.67 | F30: =ROUND(D30*1.02*F$6,0) -> -194847 | H30: =ROUND((F30*1.02)*H$6,0) -> -198744
A31: 2%ROLL-UP | D31: =ROUND(B29*B33,0) -> 37937932 | F31: =ROUND(D31*1.02*F$6,0) -> 37729273 | H31: =ROUND(((F31+F32)*1.02)*H$6,0) -> 38445590
A32: =$A$12 -> FY 10 AVG SALARY | B32: =E670SAL!B31 -> 39165 | E32: =ROUND((E$4/B30)-E29-E30,2) -> -1.31 | F32: =E670SAL!F31*1 -> -37518 | G32: =ROUND((G$4/B30)-G29-G30,2) -> 3.4 | H32: =E670SAL!H31*1 -> 99872
A33: =$A$13 -> FY11 = FY10 @ 1% Roll-Up Plus 0% Cola | B33: =E670SAL!B32 -> 39557 | E33: =SUM(E29:E32) -> 951.09 | F33: =SUM(F29:F32) -> 37496908 | G33: =SUM(G29:G32) -> 954.49 | H33: =SUM(H29:H32) -> 38346718
A35: ADMINISTRATIVE SUPPORT PERSONNEL
A36: LICENSED | B36: =E670SAL!B35 -> 1405.47 | C36: =E670SAL!C35 -> -9.79 | E36: =(B36) -> 1405.47 | G36: =(E40) -> 1393.75
A37: STUDENT RATIO | B37: =E670SAL!B36 -> 302.77 | D37: =ROUND(C36*DSADATABASE!K18,0) -> -643967 | E37: =(C36) -> -9.79 | F37: =ROUND(D37*1.02*F$6,0) -> -640425 | H37: =ROUND((F37*1.02)*H$6,0) -> -653234
A38: 2%ROLL-UP | D38: =ROUND(B36*B40,0) -> 124497938 | F38: =ROUND(D38*1.02*F$6,0) -> 123813199 | H38: =ROUND(((F38+F39)*1.02)*H$6,0) -> 126163209
A39: =$A$12 -> FY 10 AVG SALARY | B39: =E670SAL!B38 -> 87704 | E39: =ROUND((E$4/B37)-E36-E37,2) -> -1.93 | F39: =E670SAL!F38*1 -> -123778 | G39: =ROUND((G$4/B37)-G36-G37,2) -> 5 | H39: =E670SAL!H38*1 -> 328890
A40: =$A$13 -> FY11 = FY10 @ 1% Roll-Up Plus 0% Cola | B40: =E670SAL!B39 -> 88581 | E40: =SUM(E36:E39) -> 1393.75 | F40: =SUM(F36:F39) -> 123048996 | G40: =SUM(G36:G39) -> 1398.75 | H40: =SUM(H36:H39) -> 125838865
A42: NON-LICENSED | B42: =E670SAL!B41 -> 2881.37 | C42: =E670SAL!C41 -> -19.98 | E42: =(B42) -> 2881.37 | G42: =(E46) -> 2857.44
A43: STUDENT RATIO | B43: =E670SAL!B42 -> 147.68 | D43: =ROUND(C42*DSADATABASE!K19,0) -> -692447 | E43: =(C42) -> -19.98 | F43: =ROUND(D43*1.02*F$6,0) -> -688639 | H43: =ROUND((F43*1.02)*H$6,0) -> -702412
A44: 2%ROLL-UP | D44: =ROUND(B42*B46,0) -> 133145226 | F44: =ROUND(D44*1.02*F$6,0) -> 132412927 | H44: =ROUND(((F44+F45)*1.02)*H$6,0) -> 134925043
A45: =$A$12 -> FY 10 AVG SALARY | B45: =E670SAL!B44 -> 46209 | E45: =ROUND((E$4/B43)-E42-E43,2) -> -3.95 | F45: =E670SAL!F44*1 -> -133473 | G45: =ROUND((G$4/B43)-G42-G43,2) -> 10.24 | H45: =E670SAL!H44*1 -> 354888
A46: =$A$13 -> FY11 = FY10 @ 1% Roll-Up Plus 0% Cola | B46: =E670SAL!B45 -> 46209 | E46: =SUM(E42:E45) -> 2857.44 | F46: =SUM(F42:F45) -> 131590815 | G46: =SUM(G42:G45) -> 2867.68 | H46: =SUM(H42:H45) -> 134577519
A48: OTHER LICENSED & NON-LICENSED | B48: =E670SAL!B47 -> 5844.97 | C48: =E670SAL!C47 -> -40.44 | E48: =(B48) -> 5844.97 | G48: =(E52) -> 5796.53
A49: STUDENT RATIO | B49: =E670SAL!B48 -> 72.8 | D49: =ROUND(C48*DSADATABASE!K20,0) -> -1309892 | E49: =(C48) -> -40.44 | F49: =ROUND(D49*1.02*F$6,0) -> -1302688 | H49: =ROUND((F49*1.02)*H$6,0) -> -1328742
A50: 2%ROLL-UP | D50: =ROUND(B48*B52,0) -> 254957591 | F50: =ROUND(D50*1.02*F$6,0) -> 253555324 | H50: =ROUND(((F50+F51)*1.02)*H$6,0) -> 258368727
A51: =$A$12 -> FY 10 AVG SALARY | B51: =E670SAL!B50 -> 43188 | E51: =ROUND((E$4/B49)-E48-E49,2) -> -8 | F51: =E670SAL!F50*1 -> -252650 | G51: =ROUND((G$4/B49)-G48-G49,2) -> 20.77 | H51: =E670SAL!H50*1 -> 672761
A52: =$A$13 -> FY11 = FY10 @ 1% Roll-Up Plus 0% Cola | B52: =E670SAL!B51 -> 43620 | E52: =SUM(E48:E51) -> 5796.53 | F52: =SUM(F48:F51) -> 251999986 | G52: =SUM(G48:G51) -> 5817.3 | H52: =SUM(H48:H51) -> 257712746
A54: TOTAL SALARIES | B54: =+B9+B16+B23+B29+B36+B42+B48 -> 35960.04 | C54: =+C9+C16+C23+C29+C36+C42+C48 -> -251.24 | E54: =SUM(E13+E20+E27+E33+E40+E46+E52) -> 35659.56 | F54: =SUM(F13+F20+F27+F33+F40+F46+F52) -> 1852165302 | G54: =SUM(G13+G20+G27+G33+G40+G46+G52) -> 35787.36 | H54: =SUM(H13+H20+H27+H33+H40+H46+H52) -> 1894091217
A55: 50% of the PERS pay factor (state employee pay factor = 89.385%, DSA factor = 94.6925%) | F55: =(F54*0.946925)-F54 -> -98303673 | H55: =(H54*0.946925)-H54 -> -1.0052889e+08
A56: TOTAL SALARIES LESS 25% PERS EQUAL | F56: =+F54+F55 -> 1.7538616e+09 | H56: =+H54+H55 -> 1.7935623e+09 | I56: state pay factor = .89385
A57: SUBSTITUTE SALARIES | F57: =E670SAL!F56 -> 36035813 | H57: =E670SAL!H56 -> 36164974 | I57: use 50% of employee pay reduction for DSA
A58: =M200SAL!A55 -> EXTRA PAY, MISC SALARIES | F58: =E670SAL!F57 -> 20672024 | H58: =E670SAL!H57 -> 21161040
A59: FRINGE BENEFITS
A60: RETIREMENT | B60: =E670SAL!B59 -> 0.2375 | C60: =E670SAL!C59 -> 0.2375 | F60: =ROUND(F$56*B60,0) -> 416542137 | H60: =ROUND(H$56*C60,0) -> 425971052
A61: WORKER'S COMP | B61: =E670SAL!B60 -> 0.004076 | C61: =E670SAL!C60 -> 0.004076 | F61: =ROUND(SUM(F$56:F$58)*B61,0) -> 7379881 | H61: =ROUND(SUM(H$56:H$58)*C61,0) -> 7544221
A62: UNEMP INS | B62: =E670SAL!B61 -> 0.003592 | C62: =E670SAL!C61 -> 0.003592 | F62: =ROUND(SUM(F$56:F$58)*B62,0) -> 6503566 | H62: =ROUND(SUM(H$56:H$58)*C62,0) -> 6648391
A63: MEDICARE | B63: =E670SAL!B62 -> 0.013034 | C63: =E670SAL!C62 -> 0.013034 | F63: =ROUND(SUM(F$56:F$58)*B63,0) -> 23598962 | H63: =ROUND(SUM(H$56:H$58)*C63,0) -> 24124479
A64: MEDICAL INS | B64: =E670SAL!B63 -> 6980.69 | C64: =E670SAL!C63 -> 6980.69 | F64: =ROUND(E$54*B64,0) -> 248928334 | H64: =ROUND(G$54*C64,0) -> 249820466
A65: OTHER | B65: =E670SAL!B64 -> 0.004306 | C65: =E670SAL!C64 -> 0.004306 | F65: =ROUND(SUM(F$56:$F58)*$B65,0) -> 7796312 | H65: =ROUND(SUM(H$56:H58)*$C65,0) -> 7969925
F66: =SUM(F60:F65) -> 710749192 | H66: =SUM(H60:H65) -> 722078534
A67: TOTAL POSITIONS/SALARIES
A68: AND FRINGE BENEFITS | E68: =E54+E66 -> 35659.56 | F68: =F56+F57+F58+F66 -> 2.5213187e+09 | G68: =G54+G66 -> 35787.36 | H68: =H56+H57+H58+H66 -> 2.5729669e+09
A69: BENEFIT/SALARY RATIO | F69: =F66/F54 -> 0.38373961 | H69: =H66/H54 -> 0.38122691
B70: =+M200SAL!B67 -> FY12 | C70: =+B70 -> FY12 | D70: Net | E70: =+M200SAL!E67 -> FY13 | F70: =+E70 -> FY13 | G70: Net
A71: Summary | B71: E671 | C71: E601 | D71: Diff | E71: E671 | F71: E601 | G71: Diff
A72: Salaries | B72: =E671SAL!C72 -> 1.8313284e+09 | C72: =F56 -> 1.7538616e+09 | D72: =C72-B72 -> -77466814 | E72: =E671SAL!F72 -> 1.8727827e+09 | F72: =H56 -> 1.7935623e+09 | G72: =F72-E72 -> -79220365
A73: Substitute Salaries | B73: =E671SAL!C73 -> 36035813 | C73: =F57 -> 36035813 | D73: =C73-B73 -> 0 | E73: =E671SAL!F73 -> 36164974 | F73: =H57 -> 36164974 | G73: =F73-E73 -> 0
A74: Extra Duty, Misc Salaries | B74: =E671SAL!C74 -> 20672024 | C74: =F58 -> 20672024 | D74: =C74-B74 -> 0 | E74: =E671SAL!F74 -> 21161040 | F74: =H58 -> 21161040 | G74: =F74-E74 -> 0
A75: Retirement | B75: =E671SAL!C75 -> 434940505 | C75: =F60 -> 416542137 | D75: =C75-B75 -> -18398368 | E75: =E671SAL!F75 -> 444785889 | F75: =H60 -> 425971052 | G75: =F75-E75 -> -18814837
A76: Worker's Comp | B76: =E671SAL!C76 -> 7695636 | C76: =F61 -> 7379881 | D76: =C76-B76 -> -315755 | E76: =E671SAL!F76 -> 7867123 | F76: =H61 -> 7544221 | G76: =F76-E76 -> -322902
A77: Unemp Comp | B77: =E671SAL!C77 -> 6781826 | C77: =F62 -> 6503566 | D77: =C77-B77 -> -278260 | E77: =E671SAL!F77 -> 6932950 | F77: =H62 -> 6648391 | G77: =F77-E77 -> -284559
A78: Medicare | B78: =E671SAL!C78 -> 24608665 | C78: =F63 -> 23598962 | D78: =C78-B78 -> -1009703 | E78: =E671SAL!F78 -> 25157037 | F78: =H63 -> 24124479 | G78: =F78-E78 -> -1032558
A79: Medical | B79: =E671SAL!C79 -> 248928334 | C79: =F64 -> 248928334 | D79: =C79-B79 -> 0 | E79: =E671SAL!F79 -> 249820466 | F79: =H64 -> 249820466 | G79: =F79-E79 -> 0
A80: Other | B80: =E671SAL!C80 -> 8129884 | C80: =F65 -> 7796312 | D80: =C80-B80 -> -333572 | E80: =E671SAL!F80 -> 8311048 | F80: =H65 -> 7969925 | G80: =F80-E80 -> -341123
A81: Add back estimated column adjustments* | B81: 0 | D81: =C81-B81 -> 0 | E81: 0 | G81: =F81-E81 -> 0
A83: Total Salaries and Fringe Benefits | B83: =SUM(B72:B80) -> 2.6191211e+09 | C83: =SUM(C72:C81) -> 2.5213187e+09 | D83: =SUM(D72:D81) -> -97802472 | E83: =SUM(E72:E81) -> 2.6729832e+09 | F83: =SUM(F72:F81) -> 2.5729669e+09 | G83: =SUM(G72:G81) -> -1.0001634e+08

Sheet Adult Ed
B2: 2009-10 | E2: 2010-11 | F2: % | G2: DSABASE | H2: DSABASE | I2: DSAM200 | J2: DSAM200 | K2: DSAM300 | L2: =K2 -> DSAM300 | M2: DSAE670 | N2: =M2 -> DSAE670 | O2: DSAE671 | P2: =O2 -> DSAE671 | Q2: DSAE601 | R2: =Q2 -> DSAE601 | S2: DSABME | T2: % CHG | U2: DSABME | V2: % CHG
B3: WK PROGRAM | C3: ACTUAL | D3: % CHG | E3: WK PROGRAM | F3: CHG | G3: 2011-12 | H3: 2012-13 | I3: =G3 -> 2011-12 | J3: =H3 -> 2012-13 | K3: =I3 -> 2011-12 | L3: =J3 -> 2012-13 | M3: 2011-12 | N3: 2012-13 | O3: 2011-12 | P3: 2012-13 | Q3: 2011-12 | R3: 2012-13 | S3: =G3 -> 2011-12 | U3: =R3 -> 2012-13
A4: If using Adult HS Enrollment & Enrollment Growth:
A5: ADULT EDUCATION | B5: 21170456 | C5: 21170456 | D5: =ROUND(C5/B5-1,4) -> 0 | E5: 22673833 | F5: =ROUND(E5/C5-1,4) -> 0.071 | G5: =ROUND(((C5*1.02)*1)/C10*G10,0) -> 22918550 | H5: =ROUND(G5*1.02,0) -> 23376921 | I5: =G5/G10*I11-G5 -> -4600850 | J5: =H5/H10*J11-H5 -> -4255153.5 | K5: =ROUND((G5+I5)*M300SAL!D83,0) -> 108428 | L5: =ROUND((H5+J5)*M300SAL!G83,0) -> 113413 | M5: =ROUND((G5+I5+K5)*DSADATABASE!J28-(G5+I5+K5),0) -> -460653 | N5: =ROUND((H5+J5+L5)*DSADATABASE!J28*DSADATABASE!K28-('Adult Ed'!H5+'Adult Ed'!J5+L5),0) -> -480880 | O5: =ROUND((G5+I5+M5+K5)/1-(G5+I5+M5+K5),0) -> 0 | P5: =ROUND((H5+J5+N5+L5)/1/1-(H5+J5+N5+L5),0) -> 0 | Q5: =ROUND((G5+I5+M5+O5+K5)*0.946925-('Adult Ed'!G5+'Adult Ed'!I5+'Adult Ed'!M5+'Adult Ed'!O5+K5),0) -> -953518 | R5: =ROUND((H5+J5+N5+P5+L5)*0.946925-('Adult Ed'!H5+'Adult Ed'!J5+'Adult Ed'!N5+'Adult Ed'!P5+L5),0) -> -995385 | S5: =G5+I5+K5+M5+O5+Q5 -> 17011957 | T5: =ROUND(S5/C5,4)-1 -> -0.1964 | U5: =H5+J5+L5+N5+P5+R5 -> 17758916 | V5: =ROUND(U5/S5-1,4) -> 0.0439
C7: FY2010 L01 | E7: FY 2011 L01 | I7: FY 2012 | J7: FY 2013
A8: Adult HS Enrollment - Regular | C8: =25365+B33 -> 25316.437 | E8: =27093+C33 -> 27016.055 | I8: =I17 -> 21513 | J8: =K17 -> 22092
A9: Adult HS Enrollment - Corrections | C9: 5731 | E9: 5936 | I9: =I16 -> 4824 | J9: =K16 -> 4862
A10: Adult HS Enrollment - Total | C10: =SUM(C8:C9) -> 31047.437 | E10: =SUM(E8:E9) -> 32952.055 | G10: =+E10 -> 32952.055 | H10: =+E10 -> 32952.055 | I10: =+I11-G10 -> -6615.0546 | J10: =+J11-H10 -> -5998.0546
A11: AHS Projected Enrollment | I11: =+I8+I9 -> 26337 | J11: =+J8+J9 -> 26954
A13: Enrollment projections above for 2011, 2012, 2013 made using average enrollment growth for Fiscal Years 2006 through 2010
G14: Projected | I14: Projected | K14: Projected
E15: FY 2010 Actual | G15: FY 2011 | I15: FY 2012 | K15: FY 2013
B16: Corrections | C16: 0.0078 | E16: 4750 | G16: =ROUND(E16+(E16*$C16),0) -> 4787 | I16: =ROUND(G16+(G16*$C16),0) -> 4824 | K16: =ROUND(I16+(I16*$C16),0) -> 4862
B17: Regular | C17: 0.0269 | E17: 20400 | G17: =ROUND(E17+(E17*$C17),0) -> 20949 | I17: =ROUND(G17+(G17*$C17),0) -> 21513 | K17: =ROUND(I17+(I17*$C17),0) -> 22092
B18: Total | C18: 0.0224 | E18: =SUM(E16:E17) -> 25150 | G18: =SUM(G16:G17) -> 25736 | I18: =SUM(I16:I17) -> 26337 | K18: =SUM(K16:K17) -> 26954
A22: L01
A23: workbook | B23: FY 2010 | C23: FY 2011
A24: funding | B24: 21170456 | C24: 22673833
A25: enrollment | B25: 31096 | C25: 33029
A27: should have been | B27: 21203570 | C27: 22726778
A29: Per pupil | B29: =B27/B25 -> 681.87452 | C29: =C27/C25 -> 688.08556
A31: funded enrollment | B31: =B24/B29 -> 31047.437 | C31: =C24/C29 -> 32952.055
A33: difference | B33: =B31-B25 -> -48.563187 | C33: =C31-C25 -> -76.945373

Sheet M200OPR
A1: OPERATING CALCULATIONS - M-200 GROWTH ADJUSTMENTS
A2: BLDG SQUARE | C2: 1992 Actual | D2: 1993 Add'l | E2: 1993 Actual | F2: 1994 Add'l | G2: 1994 Actual | H2: 1995 Actual | I2: 1996 Add'l | J2: 1996 Actual | K2: 1997 Actual | L2: 1998 Actual | M2: 1999 Actual | N2: 2000 Actual | O2: =M101INF!O2 -> 2010 Actual | P2: =M101INF!P2 -> 2010 Add'l | Q2: =M101INF!Q2 -> 2011 Proj | R2: =M101INF!R2 -> 2011 Add'l | S2: =M101INF!S2 -> 2012 Proj | T2: =M101INF!T2 -> 2012 Add'l | U2: =M101INF!U2 -> 2013 Proj
A3: FOOTAGE PER | C3: Sq Ft | D3: Sq Ft | E3: Sq Ft | F3: Sq Ft | G3: Sq Ft | H3: Sq Ft | I3: Sq Ft | J3: Sq Ft | K3: Sq Ft | L3: Sq Ft | M3: Sq Ft | N3: Sq Ft | O3: Sq Ft | P3: Sq Ft | Q3: Sq Ft | R3: Sq Ft | S3: Sq Ft | T3: Sq Ft | U3: Sq Ft
A4: =DSADATABASE!F32 -> Elementary Schools | C4: 7247657 | D4: 121544 | E4: 7369201 | F4: 925768 | G4: 8294969 | H4: 8676500 | I4: 227639 | J4: 8904139 | K4: 9173936 | L4: 9891512 | M4: 10518428 | N4: 11015402 | O4: =DSADATABASE!I32 -> 18694453 | P4: =Q4-O4 -> 298577 | Q4: =DSADATABASE!J32 -> 18993030 | R4: =S4-Q4 -> 0 | S4: =DSADATABASE!K32 -> 18993030 | T4: =U4-S4 -> 80245 | U4: =DSADATABASE!L32 -> 19073275
A5: =DSADATABASE!F33 -> Middle/Junior High Schools | C5: 4550811 | D5: 249981 | E5: 4800792 | F5: 232460 | G5: 5033252 | H5: 5205648 | I5: 238770 | J5: 5444418 | K5: 5542278 | L5: 6056303 | M5: 6580378 | N5: 6770495 | O5: =DSADATABASE!I33 -> 10814292 | P5: =Q5-O5 -> 96632 | Q5: =DSADATABASE!J33 -> 10910924 | R5: =S5-Q5 -> 10374 | S5: =DSADATABASE!K33 -> 10921298 | T5: =U5-S5 -> -15867 | U5: =DSADATABASE!L33 -> 10905431
A6: =DSADATABASE!F34 -> High Schools | C6: 9489184 | D6: 560106 | E6: 10049290 | F6: 450821 | G6: 10500111 | H6: 10795697 | I6: -219343 | J6: 10576354 | K6: 11477744 | L6: 12237749 | M6: 13007029 | N6: 13543573 | O6: =DSADATABASE!I34 -> 16789936 | P6: =Q6-O6 -> 403123 | Q6: =DSADATABASE!J34 -> 17193059 | R6: =S6-Q6 -> 39841 | S6: =DSADATABASE!K34 -> 17232900 | T6: =U6-S6 -> 0 | U6: =DSADATABASE!L34 -> 17232900
A7: =DSADATABASE!F35 -> Special Schools | C7: 367658 | D7: 18907 | E7: 386565 | F7: 0 | G7: 386565 | H7: 386565 | I7: 84743 | J7: 471308 | K7: 472748 | L7: 481892 | M7: 477265 | N7: 435564 | O7: =DSADATABASE!I35 -> 616424 | P7: =Q7-O7 -> 3500 | Q7: =DSADATABASE!J35 -> 619924 | R7: =S7-Q7 -> 0 | S7: =DSADATABASE!K35 -> 619924 | T7: =U7-S7 -> 0 | U7: =DSADATABASE!L35 -> 619924
A8: =DSADATABASE!F36 -> Other Facilities | C8: 836012 | D8: 29981 | E8: 865993 | F8: 6500 | G8: 872493 | H8: 872493 | I8: -22856 | J8: 849637 | K8: 906342 | L8: 874666 | M8: 810790 | N8: 939893 | O8: =DSADATABASE!I36 -> 3159801 | P8: =Q8-O8 -> 0 | Q8: =DSADATABASE!J36 -> 3159801 | R8: =S8-Q8 -> 15320 | S8: =DSADATABASE!K36 -> 3175121 | T8: =U8-S8 -> 32706 | U8: =DSADATABASE!L36 -> 3207827
C9: 22491322 | D9: 980519 | E9: 23471841 | F9: 1615549 | G9: 25087390 | H9: 25936903 | I9: 308953 | J9: 26245856 | K9: 27573048 | L9: 29542122 | M9: 31393890 | N9: 32704927 | O9: =SUM(O4:O8) -> 50074906 | P9: =SUM(P4:P8) -> 801832 | Q9: =SUM(Q4:Q8) -> 50876738 | R9: =SUM(R4:R8) -> 65535 | S9: =SUM(S4:S8) -> 50942273 | T9: =SUM(T4:T8) -> 97084 | U9: =SUM(U4:U8) -> 51039357
Q10: =ROUND(Q9/O9,4)-1 -> 0.016 | S10: =ROUND(S9/Q9,4)-1 -> 0.0013 | U10: =ROUND(U9/S9,42)-1 -> 0.001905765
A11: BUILDING | B11: 1992 Actual | C11: 1992 Cost | D11: 1993 Actual | E11: 1993 Cost | F11: 1994 Actual | G11: 1994 Cost | H11: 1995 Actual | I11: 1995 Cost | J11: 1996 Cost | K11: 1997 Actual | L11: 1998 Cost | M11: 1999 Cost | N11: 2000 Cost | O11: 2010 Actual | P11: 2010 Cost | Q11: 2011 Annual | R11: 2012 Add'l | S11: 2012 Cost | T11: 2012 Annual | U11: 2013 Add'l | V11: 2013 Cost
A12: DRIVEN COST | B12: Cost | C12: Per Sq Ft | D12: Cost | E12: Per Sq Ft | F12: Cost | G12: Per Sq Ft | H12: Cost | I12: Per Sq Ft | J12: Per Sq Ft | K12: Cost | L12: Per Sq Ft | M12: Per Sq Ft | N12: Per Sq Ft | O12: Cost * | P12: Per Sq Ft | Q12: Cost | R12: Cost | S12: Per Sq Ft | T12: Cost | U12: Cost | V12: Per Sq Ft
A13: Heat | B13: 3166807 | C13: 0.14080128 | D13: 3546205 | E13: 0.15108338 | F13: 3765474 | G13: 0.15009429 | H13: 4043666 | I13: 0.15590396 | J13: 0.117 | K13: 4030593 | L13: 0.164 | M13: 0.155 | N13: 0.141 | O13: =DSASUMM!G24 -> 12057552 | P13: =M101INF!P13 -> 0.2408 | Q13: =ROUND(S$9*S13,0) -> 12266899 | R13: =(Q13-O13) -> 209347 | S13: =P13 -> 0.2408 | T13: =ROUND(U$9*V13,0) -> 12290277 | U13: =T13-Q13 -> 23378 | V13: =P13 -> 0.2408
A14: Electricity | B14: 14598682 | C14: 0.64908065 | D14: 15535256 | E14: 0.66186781 | F14: 17341109 | G14: 0.6912281 | H14: 18686182 | I14: 0.7204477 | J14: 0.712 | K14: 20195540 | L14: 0.703 | M14: 0.661 | N14: 0.83 | O14: =DSASUMM!G25 -> 65089232 | P14: =M101INF!P14 -> 1.2998 | Q14: =ROUND(S$9*S14,0) -> 66214766 | R14: =(Q14-O14) -> 1125534 | S14: =P14 -> 1.2998 | T14: =ROUND(U$9*V14,0) -> 66340956 | U14: =T14-Q14 -> 126190 | V14: =P14 -> 1.2998
A15: Water,sewer,garbage | B15: 6312546 | C15: 0.28066585 | D15: 6576015 | E15: 0.28016614 | F15: 8056235 | G15: 0.32112687 | H15: 8908413 | I15: 0.34346479 | J15: 0.375 | K15: 11063663 | L15: 0.374 | M15: 0.352 | N15: 0.44 | O15: =DSASUMM!C31 -> 26757018 | P15: =M101INF!P15 -> 0.5343 | Q15: =ROUND(S$9*S15,0) -> 27218456 | R15: =(Q15-O15) -> 461438 | S15: =P15 -> 0.5343 | T15: =ROUND(U$9*V15,0) -> 27270328 | U15: =T15-Q15 -> 51872 | V15: =P15 -> 0.5343
A16: Property Insurance | B16: 1501429 | C16: 0.066755925 | D16: 1110434 | E16: 0.047309199 | F16: 885169 | G16: 0.035283423 | H16: 837499 | I16: 0.032289861 | J16: 0.034 | K16: 546170 | L16: 0.011 | M16: 0.011 | N16: 0.01 | O16: =DSASUMM!C33 -> 1981658 | P16: =M101INF!P16 -> 0.0396 | Q16: =ROUND(S$9*S16,0) -> 2017314 | R16: =(Q16-O16) -> 35656 | S16: =P16 -> 0.0396 | T16: =ROUND(U$9*V16,0) -> 2021159 | U16: =T16-Q16 -> 3845 | V16: =P16 -> 0.0396
A17: Maint/Repair | B17: 2180215 | C17: 0.096935832 | D17: 2670046 | E17: 0.11375529 | F17: 2934985 | G17: 0.11699045 | H17: 2949015 | I17: 0.11369958 | J17: 0.163 | K17: 5143470 | L17: 0.175 | M17: 0.164 | N17: 0.445 | O17: =DSASUMM!C29 -> 25553696 | P17: =M101INF!P17 -> 0.5103 | Q17: =ROUND(S$9*S17,0) -> 25995842 | R17: =(Q17-O17) -> 442146 | S17: =P17 -> 0.5103 | T17: =ROUND(U$9*V17,0) -> 26045384 | U17: =T17-Q17 -> 49542 | V17: =P17 -> 0.5103
B18: 27759679 | D18: 29437956 | F18: 32982972 | H18: 35424775 | K18: 40979436 | L18: 1.427 | M18: 1.343 | N18: 1.866 | O18: =SUM(O13:O17) -> 131439156 | P18: =SUM(P13:P17) -> 2.6248 | Q18: =SUM(Q13:Q17) -> 133713277 | R18: =SUM(R13:R17) -> 2274121 | S18: =SUM(S13:S17) -> 2.6248 | T18: =SUM(T13:T17) -> 133968104 | U18: =SUM(U13:U17) -> 254827 | V18: =SUM(V13:V17) -> 2.6248
Q19: =Q18-O18 -> 2274121 | T19: =T18-O18 -> 2528948
A21: SCHOOL WEIGHTED | C21: 1992 | E21: 1993 | G21: 1994 | I21: 1995 | J21: 1996 | L21: 1998 | N21: 1999 | O21: =O2 -> 2010 Actual | Q21: 2012 | T21: 2013
A22: ENROLLMENTS | C22: Actual | E22: Actual | G22: Actual | I22: Actual | J22: Actual | L22: Actual | N22: Actual | O22: Actual | Q22: Projected | T22: Projected
C23: 204207 | E23: 214997 | G23: 227302 | I23: 227302 | J23: 255215.4 | L23: 285990 | N23: 300115.4 | O23: =DSADATABASE!A4 -> 425527.2 | Q23: =DSADATABASE!C4 -> 421987.1 | T23: =DSADATABASE!D4 -> 423499.6
A25: STUDENT | B25: 1992 Actual | C25: 1992 Cost | D25: 1993 Actual | E25: 1993 Cost | F25: 1994 Actual | G25: 1994 Cost | H25: 1995 Actual | I25: 1995 Cost | J25: 1996 Cost | K25: 1997 Actual | L25: 1998 Cost | M25: 1999 Cost | N25: 2000 Cost | O25: =O$11 -> 2010 Actual | P25: =P$11 -> 2010 Cost | Q25: =Q$11 -> 2011 Annual | R25: =R$11 -> 2012 Add'l | S25: =S$11 -> 2012 Cost | T25: =T$11 -> 2012 Annual | U25: =U$11 -> 2013 Add'l | V25: =V$11 -> 2013 Cost
A26: DRIVEN COST | B26: Cost | C26: Per Student | D26: Cost | E26: Per Student | F26: Cost | G26: Per Student | H26: Cost | I26: Per Student | J26: Per Student | K26: Cost | L26: Per Student | M26: Per Student | N26: Per Student | O26: Cost | P26: Per Student | Q26: Cost | R26: Cost | S26: Per Student | T26: Cost | U26: Cost | V26: Per Student
A27: Pupil Transportation | B27: 6410321 | C27: 31.391289 | D27: 6149230 | E27: 28.601469 | F27: 7888311 | G27: 34.704099 | H27: 7317118 | I27: 32.191173 | J27: 50.96 | K27: 9462961 | L27: 35.1 | M27: 31.2 | N27: 40.07 | O27: =DSASUMM!C26 -> 16707325 | P27: =M101INF!P27 -> 39.2626 | Q27: =ROUND(Q$23*P27,0) -> 16568311 | R27: =Q27-O27 -> -139014 | S27: =P27 -> 39.2626 | T27: =ROUND(T$23*S27,0) -> 16627695 | U27: =T27-Q27 -> 59384 | V27: =P27 -> 39.2626
A28: Textbooks | B28: 8226072 | C28: 40.283007 | D28: 8534733 | E28: 39.696986 | F28: 9274867 | G28: 40.804159 | H28: 9993340 | I28: 43.965033 | J28: 36.64 | K28: 11750179 | L28: 49.54 | M28: 52.71 | N28: 43.43 | O28: =DSASUMM!C27 -> 23810368 | P28: =M101INF!P28 -> 55.955 | Q28: =ROUND(Q$23*P28,0) -> 23612288 | R28: =Q28-O28 -> -198080 | S28: =P28 -> 55.955 | T28: =ROUND(T$23*S28,0) -> 23696920 | U28: =T28-Q28 -> 84632 | V28: =P28 -> 55.955
A29: Library | B29: 1363322 | C29: 6.6761766 | D29: 1044344 | E29: 4.8574817 | F29: 1567481 | G29: 6.8960282 | H29: 1351462 | I29: 5.945667 | J29: 6.43 | K29: 1853767 | L29: 7.59 | M29: 8.01 | N29: 6.46 | O29: =DSASUMM!C28 -> 2397912 | P29: =M101INF!P29 -> 5.6352 | Q29: =ROUND(Q$23*P29,0) -> 2377982 | R29: =Q29-O29 -> -19930 | S29: =P29 -> 5.6352 | T29: =ROUND(T$23*S29,0) -> 2386505 | U29: =T29-Q29 -> 8523 | V29: =P29 -> 5.6352
A30: Instruction Supplies | B30: 10650126 | C30: 52.153579 | D30: 10031838 | E30: 46.660363 | F30: 13887603 | G30: 61.097584 | H30: 14228829 | I30: 62.598785 | J30: 54.27 | K30: 15120627 | L30: 59.36 | M30: 60 | N30: 61.61 | O30: =DSASUMM!C36 -> 70944435 | P30: =M101INF!P30 -> 166.7213 | Q30: =ROUND(Q$23*P30,0) -> 70354238 | R30: =Q30-O30 -> -590197 | S30: =P30 -> 166.7213 | T30: =ROUND(T$23*S30,0) -> 70606404 | U30: =T30-Q30 -> 252166 | V30: =P30 -> 166.7213
A31: Instruction Software | G31: n/a | H31: 1010617 | I31: 4.4461421 | J31: 3.19 | K31: 2745463 | L31: 7.17 | M31: 7.96 | N31: 3.94 | O31: =DSASUMM!C37 -> 7384984 | P31: =M101INF!P31 -> 17.3549 | Q31: =ROUND(Q$23*P31,0) -> 7323544 | R31: =Q31-O31 -> -61440 | S31: =P31 -> 17.3549 | T31: =ROUND(T$23*S31,0) -> 7349793 | U31: =T31-Q31 -> 26249 | V31: =P31 -> 17.3549
A32: Other Supplies | B32: 10444298 | C32: 51.145641 | D32: 8033202 | E32: 37.364252 | F32: 10518106 | G32: 46.273706 | H32: 10503038 | I32: 46.207416 | J32: 35.59 | K32: 11692320 | L32: 43.88 | M32: 16.46 | N32: 18.35 | O32: =DSASUMM!C38 -> 16515016 | P32: =M101INF!P32 -> 38.8107 | Q32: =ROUND(Q$23*P32,0) -> 16377615 | R32: =Q32-O32 -> -137401 | S32: =P32 -> 38.8107 | T32: =ROUND(T$23*S32,0) -> 16436316 | U32: =T32-Q32 -> 58701 | V32: =P32 -> 38.8107
B33: 37094139 | D33: 33793347 | F33: 43136368 | H33: 44404404 | K33: 52625317 | L33: 202.64 | M33: 176.34 | N33: 173.86 | O33: =SUM(O27:O32) -> 137760040 | P33: =SUM(P27:P32) -> 323.7397 | Q33: =SUM(Q27:Q32) -> 136613978 | R33: =SUM(R27:R32) -> -1146062 | S33: =SUM(S27:S32) -> 323.7397 | T33: =SUM(T27:T32) -> 137103633 | U33: =SUM(U28:U32) -> 430271 | V33: =SUM(V27:V32) -> 323.7397
Q34: =Q33-O33 -> -1146062 | T34: =T33-O33 -> -656407
A36: SCHOOL GENERAL | C36: 1992 | E36: 1993 | G36: 1994 | I36: 1995 | J36: 1996 | L36: 1998 | N36: 1999 | O36: =O21 -> 2010 Actual | Q36: =Q21 -> 2012 | T36: =T21 -> 2013
A37: TOTAL STAFF | C37: Actual | E37: Actual | G37: Actual | I37: Actual | J37: Actual | L37: Actual | N37: Actual | O37: Actual | Q37: Projected | T37: Projected
C38: 18758.9 | E38: 19566.2 | G38: 20374 | I38: 20374 | J38: 21933.7 | L38: 25421 | N38: 26851.6 | O38: =M200SAL!B53 -> 35960.04 | Q38: =M200SAL!E53 -> 35659.56 | T38: =M200SAL!G53 -> 35787.36
A40: STAFF | B40: 1992 Actual | C40: 1992 Cost | D40: 1993 Actual | E40: 1993 Cost | F40: 1994 Actual | G40: 1994 Cost | H40: 1995 Actual | I40: 1995 Cost | J40: 1996 Cost | K40: 1997 Actual | L40: 1998 Cost | M40: 1999 Cost | N40: 2000 Cost | O40: =O$11 -> 2010 Actual | P40: =P$11 -> 2010 Cost | Q40: =Q$11 -> 2011 Annual | R40: =R$11 -> 2012 Add'l | S40: =S$11 -> 2012 Cost | T40: =T$11 -> 2012 Annual | U40: =U$11 -> 2013 Add'l | V40: =V$11 -> 2013 Cost
A41: DRIVEN COST | B41: Cost | C41: Per Staff | D41: Cost | E41: Per Staff | F41: Cost | G41: Per Staff | H41: Cost | I41: Per Staff | J41: Per Staff | K41: Cost | L41: Per Staff | M41: Per Staff | N41: Per Staff | O41: Cost | P41: Per Staff | Q41: Cost | R41: Cost | S41: Per Sq Ft | T41: Cost | U41: Cost | V41: Per Sq Ft
A42: Prof Service | B42: 4588671 | C42: 244.61301 | D42: 4057187 | E42: 207.35692 | F42: 4224654 | G42: 207.35516 | H42: 5569499 | I42: 273.36306 | J42: 268.23 | K42: 10221123 | L42: 424.4 | M42: 452.34 | N42: 397.09 | O42: =DSASUMM!C30 -> 47269193 | P42: =M101INF!P42 -> 1314.4922 | Q42: =ROUND(Q$38*S42,0) -> 46874213 | R42: =Q42-O42 -> -394980 | S42: =P42 -> 1314.4922 | T42: =ROUND(T$38*V42,0) -> 47042206 | U42: =T42-Q42 -> 167993 | V42: =P42 -> 1314.4922
A43: Liability Insurance | B43: 2262928 | C43: 120.63223 | D43: 2353400 | E43: 120.27885 | F43: 2951811 | G43: 144.88127 | H43: 2889601 | I43: 141.82787 | J43: 249.46 | K43: 2733417 | L43: 61.56 | M43: 59.28 | N43: 194.25 | O43: =DSASUMM!C32 -> 5925229 | P43: =M101INF!P43 -> 164.7726 | Q43: =ROUND(Q$38*S43,0) -> 5875718 | R43: =Q43-O43 -> -49511 | S43: =P43 -> 164.7726 | T43: =ROUND(T$38*V43,0) -> 5896776 | U43: =T43-Q43 -> 21058 | V43: =P43 -> 164.7726
A44: Postage/Comm | B44: 3244336 | C44: 172.94916 | D44: 3265363 | E44: 166.88795 | F44: 3841730 | G44: 188.56042 | H44: 4407402 | I44: 216.32483 | J44: 195.33 | K44: 5184830 | L44: 229.89 | M44: 242.49 | N44: 270.02 | O44: =DSASUMM!C34 -> 13152322 | P44: =M101INF!P44 -> 365.7483 | Q44: =ROUND(Q$38*S44,0) -> 13042423 | R44: =Q44-O44 -> -109899 | S44: =P44 -> 365.7483 | T44: =ROUND(T$38*V44,0) -> 13089166 | U44: =T44-Q44 -> 46743 | V44: =P44 -> 365.7483
A45: Printing/Binding | B45: 1074234 | C45: 57.265298 | D45: 1346604 | E45: 68.82297 | F45: 1718898 | G45: 84.367233 | H45: 1990302 | I45: 97.688328 | J45: 91.54 | K45: 2073473 | L45: 108.14 | M45: 122.74 | N45: 132.63 | O45: =DSASUMM!C35 -> 3217410 | P45: =M101INF!P45 -> 89.4718 | Q45: =ROUND(Q$38*S45,0) -> 3190525 | R45: =Q45-O45 -> -26885 | S45: =P45 -> 89.4718 | T45: =ROUND(T$38*V45,0) -> 3201960 | U45: =T45-Q45 -> 11435 | V45: =P45 -> 89.4718
A46: Other Fuel | B46: 333980 | C46: 17.803816 | D46: 378061 | E46: 19.322147 | F46: 292111 | G46: 14.33744 | H46: 266047 | I46: 13.058162 | J46: 14.94 | K46: 381414 | L46: 19.36 | M46: 19.4 | N46: 25.92 | O46: =DSASUMM!C39 -> 2531857 | P46: =M101INF!P46 -> 70.4075 | Q46: =ROUND(Q$38*S46,0) -> 2510700 | R46: =Q46-O46 -> -21157 | S46: =P46 -> 70.4075 | T46: =ROUND(T$38*V46,0) -> 2519699 | U46: =T46-Q46 -> 8999 | V46: =P46 -> 70.4075
A47: Staff Travel | B47: 1380013 | C47: 73.565774 | D47: 1422066 | E47: 72.679723 | F47: 1708117 | G47: 83.838078 | H47: 1655142 | I47: 81.23795 | J47: 77.36 | K47: 2232645 | L47: 89.12 | M47: 89.8 | N47: 88.24 | O47: =DSASUMM!C40 -> 3539980 | P47: =M101INF!P47 -> 98.442 | Q47: =ROUND(Q$38*S47,0) -> 3510398 | R47: =Q47-O47 -> -29582 | S47: =P47 -> 98.442 | T47: =ROUND(T$38*V47,0) -> 3522979 | U47: =T47-Q47 -> 12581 | V47: =P47 -> 98.442
A48: All Other | B48: 7646527 | C48: 407.62129 | D48: 17288242 | E48: 883.57688 | F48: 6686660 | G48: 328.19574 | H48: 8200377 | I48: 402.49225 | J48: 384.13 | K48: 9704400 | L48: 253.57 | M48: 330.62 | N48: 331.84 | O48: =DSASUMM!C41 -> 9719021 | P48: =M101INF!P48 -> 270.2728 | Q48: =ROUND(Q$38*S48,0) -> 9637809 | R48: =Q48-O48 -> -81212 | S48: =P48 -> 270.2728 | T48: =ROUND(T$38*V48,0) -> 9672350 | U48: =T48-Q48 -> 34541 | V48: =P48 -> 270.2728
B49: 13679090 | D49: 23700336 | F49: 21423981 | H49: 24978370 | K49: 32531302 | L49: 1186.04 | M49: 1316.67 | N49: 1439.99 | O49: =SUM(O42:O48) -> 85355012 | P49: =SUM(P42:P48) -> 2373.6072 | Q49: =SUM(Q42:Q48) -> 84641786 | R49: =SUM(R42:R48) -> -713226 | S49: =SUM(S42:S48) -> 2373.6072 | T49: =SUM(T42:T48) -> 84945136 | U49: =SUM(U42:U48) -> 303350 | V49: =SUM(V42:V48) -> 2373.6072
Q50: =Q49-O49 -> -713226 | T50: =T49-O49 -> -409876
Q51: =SUM(Q19+Q34+Q50) -> 414833 | T51: =SUM(T19+T34+T50) -> 1462665
O52: TOTAL GROWTH ADJUSTMENTS
O53: Operating | P53: 2010 Actual | Q53: 2012 | R53: Net | S53: 2013 | T53: Net
O54: Unit | P54: Cost | Q54: Adj | R54: Diff | S54: Adj | T54: Diff
O55: Heat | P55: =O13 -> 12057552 | Q55: =Q13 -> 12266899 | R55: =Q55-P55 -> 209347 | S55: =T13 -> 12290277 | T55: =S55-P55 -> 232725
O56: Electricity | P56: =O14 -> 65089232 | Q56: =Q14 -> 66214766 | R56: =Q56-P56 -> 1125534 | S56: =T14 -> 66340956 | T56: =S56-P56 -> 1251724
O57: Water/Sewer/Garbage | P57: =O15 -> 26757018 | Q57: =Q15 -> 27218456 | R57: =Q57-P57 -> 461438 | S57: =T15 -> 27270328 | T57: =S57-P57 -> 513310
O58: Property Insurance | P58: =O16 -> 1981658 | Q58: =Q16 -> 2017314 | R58: =Q58-P58 -> 35656 | S58: =T16 -> 2021159 | T58: =S58-P58 -> 39501
O59: Maint/Repair | P59: =O17 -> 25553696 | Q59: =Q17 -> 25995842 | R59: =Q59-P59 -> 442146 | S59: =T17 -> 26045384 | T59: =S59-P59 -> 491688
O60: Pupil Transportation | P60: =O27 -> 16707325 | Q60: =Q27 -> 16568311 | R60: =Q60-P60 -> -139014 | S60: =T27 -> 16627695 | T60: =S60-P60 -> -79630
O61: Textbooks | P61: =O28 -> 23810368 | Q61: =Q28 -> 23612288 | R61: =Q61-P61 -> -198080 | S61: =T28 -> 23696920 | T61: =S61-P61 -> -113448
O62: Library | P62: =O29 -> 2397912 | Q62: =Q29 -> 2377982 | R62: =Q62-P62 -> -19930 | S62: =T29 -> 2386505 | T62: =S62-P62 -> -11407
O63: Instruction Supplies | P63: =O30 -> 70944435 | Q63: =Q30 -> 70354238 | R63: =Q63-P63 -> -590197 | S63: =T30 -> 70606404 | T63: =S63-P63 -> -338031
O64: Instruct Software | P64: =O31 -> 7384984 | Q64: =Q31 -> 7323544 | R64: =Q64-P64 -> -61440 | S64: =T31 -> 7349793 | T64: =S64-P64 -> -35191
O65: Other Supplies | P65: =O32 -> 16515016 | Q65: =Q32 -> 16377615 | R65: =Q65-P65 -> -137401 | S65: =T32 -> 16436316 | T65: =S65-P65 -> -78700
O66: Prof Service | P66: =O42 -> 47269193 | Q66: =Q42 -> 46874213 | R66: =Q66-P66 -> -394980 | S66: =T42 -> 47042206 | T66: =S66-P66 -> -226987
O67: Liability Insurance | P67: =O43 -> 5925229 | Q67: =Q43 -> 5875718 | R67: =Q67-P67 -> -49511 | S67: =T43 -> 5896776 | T67: =S67-P67 -> -28453
O68: Postage/Comm | P68: =O44 -> 13152322 | Q68: =Q44 -> 13042423 | R68: =Q68-P68 -> -109899 | S68: =T44 -> 13089166 | T68: =S68-P68 -> -63156
O69: Printing/Binding | P69: =O45 -> 3217410 | Q69: =Q45 -> 3190525 | R69: =Q69-P69 -> -26885 | S69: =T45 -> 3201960 | T69: =S69-P69 -> -15450
O70: Other Fuel | P70: =O46 -> 2531857 | Q70: =Q46 -> 2510700 | R70: =Q70-P70 -> -21157 | S70: =T46 -> 2519699 | T70: =S70-P70 -> -12158
O71: Staff Travel | P71: =O47 -> 3539980 | Q71: =Q47 -> 3510398 | R71: =Q71-P71 -> -29582 | S71: =T47 -> 3522979 | T71: =S71-P71 -> -17001
O72: All Other | P72: =O48 -> 9719021 | Q72: =Q48 -> 9637809 | R72: =Q72-P72 -> -81212 | S72: =T48 -> 9672350 | T72: =S72-P72 -> -46671
P73: =SUM(P55:P72) -> 354554208 | Q73: =SUM(Q55:Q72) -> 354969041 | R73: =(Q73-P73) -> 414833 | S73: =SUM(S55:S72) -> 356016873 | T73: =SUM(T55:T72) -> 1462665

Sheet M101INF
A1: OPERATING CALCULATIONS - M-101 AGENCY SPECIFIC INFLATION ADJUSTMENTS
A2: BLDG SQUARE | C2: 1992 Actual | D2: 1993 Add'l | E2: 1993 Actual | F2: 1994 Add'l | G2: 1994 Actual | H2: 1995 Actual | I2: 1996 Add'l | J2: 1996 Actual | K2: 1997 Actual | L2: 1998 Actual | M2: 1999 Actual | N2: 2000 Actual | O2: 2010 Actual | P2: 2010 Add'l | Q2: 2011 Proj | R2: 2011 Add'l | S2: 2012 Proj | T2: 2012 Add'l | U2: 2013 Proj
A3: FOOTAGE PER | C3: Sq Ft | D3: Sq Ft | E3: Sq Ft | F3: Sq Ft | G3: Sq Ft | H3: Sq Ft | I3: Sq Ft | J3: Sq Ft | K3: Sq Ft | L3: Sq Ft | M3: Sq Ft | N3: Sq Ft | O3: Sq Ft | P3: Sq Ft | Q3: Sq Ft | R3: Sq Ft | S3: Sq Ft | T3: Sq Ft | U3: Sq Ft
A4: =DSADATABASE!F32 -> Elementary Schools | C4: 7247657 | D4: 121544 | E4: 7369201 | F4: 925768 | G4: 8294969 | H4: 8676500 | I4: 227639 | J4: 8904139 | K4: 9173936 | L4: 9891512 | M4: 10518428 | N4: 11015402 | O4: =DSADATABASE!I32 -> 18694453 | P4: =Q4-O4 -> 298577 | Q4: =DSADATABASE!J32 -> 18993030 | R4: =S4-Q4 -> 0 | S4: =DSADATABASE!K32 -> 18993030 | T4: =U4-S4 -> 80245 | U4: =DSADATABASE!L32 -> 19073275
A5: =DSADATABASE!F33 -> Middle/Junior High Schools | C5: 4550811 | D5: 249981 | E5: 4800792 | F5: 232460 | G5: 5033252 | H5: 5205648 | I5: 238770 | J5: 5444418 | K5: 5542278 | L5: 6056303 | M5: 6580378 | N5: 6770495 | O5: =DSADATABASE!I33 -> 10814292 | P5: =Q5-O5 -> 96632 | Q5: =DSADATABASE!J33 -> 10910924 | R5: =S5-Q5 -> 10374 | S5: =DSADATABASE!K33 -> 10921298 | T5: =U5-S5 -> -15867 | U5: =DSADATABASE!L33 -> 10905431
A6: =DSADATABASE!F34 -> High Schools | C6: 9489184 | D6: 560106 | E6: 10049290 | F6: 450821 | G6: 10500111 | H6: 10795697 | I6: -219343 | J6: 10576354 | K6: 11477744 | L6: 12237749 | M6: 13007029 | N6: 13543573 | O6: =DSADATABASE!I34 -> 16789936 | P6: =Q6-O6 -> 403123 | Q6: =DSADATABASE!J34 -> 17193059 | R6: =S6-Q6 -> 39841 | S6: =DSADATABASE!K34 -> 17232900 | T6: =U6-S6 -> 0 | U6: =DSADATABASE!L34 -> 17232900
A7: =DSADATABASE!F35 -> Special Schools | C7: 367658 | D7: 18907 | E7: 386565 | F7: 0 | G7: 386565 | H7: 386565 | I7: 84743 | J7: 471308 | K7: 472748 | L7: 481892 | M7: 477265 | N7: 435564 | O7: =DSADATABASE!I35 -> 616424 | P7: =Q7-O7 -> 3500 | Q7: =DSADATABASE!J35 -> 619924 | R7: =S7-Q7 -> 0 | S7: =DSADATABASE!K35 -> 619924 | T7: =U7-S7 -> 0 | U7: =DSADATABASE!L35 -> 619924
A8: =DSADATABASE!F36 -> Other Facilities | C8: 836012 | D8: 29981 | E8: 865993 | F8: 6500 | G8: 872493 | H8: 872493 | I8: -22856 | J8: 849637 | K8: 906342 | L8: 874666 | M8: 810790 | N8: 939893 | O8: =DSADATABASE!I36 -> 3159801 | P8: =Q8-O8 -> 0 | Q8: =DSADATABASE!J36 -> 3159801 | R8: =S8-Q8 -> 15320 | S8: =DSADATABASE!K36 -> 3175121 | T8: =U8-S8 -> 32706 | U8: =DSADATABASE!L36 -> 3207827
C9: 22491322 | D9: 980519 | E9: 23471841 | F9: 1615549 | G9: 25087390 | H9: 25936903 | I9: 308953 | J9: 26245856 | K9: 27573048 | L9: 29542122 | M9: 31393890 | N9: 32704927 | O9: =SUM(O4:O8) -> 50074906 | P9: =SUM(P4:P8) -> 801832 | Q9: =SUM(Q4:Q8) -> 50876738 | R9: =SUM(R4:R8) -> 65535 | S9: =SUM(S4:S8) -> 50942273 | T9: =SUM(T4:T8) -> 97084 | U9: =SUM(U4:U8) -> 51039357
A11: BUILDING | B11: 1992 Actual | C11: 1992 Cost | D11: 1993 Actual | E11: 1993 Cost | F11: 1994 Actual | G11: 1994 Cost | H11: 1995 Actual | I11: 1995 Cost | J11: 1996 Cost | K11: 1997 Actual | L11: 1998 Cost | M11: 1999 Cost | N11: 2000 Cost | O11: 2010 Actual | P11: 2010 Cost | Q11: 2012 Cost | R11: 2012 Add'l | S11: 2012 Cost | T11: 2012 Cost | U11: 2013 Add'l | V11: 2013 Cost
A12: DRIVEN COST | B12: Cost | C12: Per Sq Ft | D12: Cost | E12: Per Sq Ft | F12: Cost | G12: Per Sq Ft | H12: Cost | I12: Per Sq Ft | J12: Per Sq Ft | K12: Cost | L12: Per Sq Ft | M12: Per Sq Ft | N12: Per Sq Ft | O12: Cost * | P12: Per Sq Ft | Q12: With Cola | R12: Cost | S12: Per Sq Ft | T12: With Cola | U12: Cost | V12: Per Sq Ft
A13: Heat | B13: 3166807 | C13: 0.14080128 | D13: 3546205 | E13: 0.15108338 | F13: 3765474 | G13: 0.15009429 | H13: 4043666 | I13: 0.15590396 | J13: 0.117 | K13: 4030593 | L13: 0.164 | M13: 0.155 | N13: 0.141 | O13: =M200OPR!O13 -> 12057552 | P13: =ROUND(O13/O$9,4) -> 0.2408 | Q13: =ROUND($S$9*S13,0) -> 12266899 | R13: =Q13-M200OPR!Q13 -> 0 | S13: =ROUND(P13*1,5) -> 0.2408 | T13: =ROUND($U$9*V13,0) -> 12290277 | U13: =T13-M200OPR!T13 -> 0 | V13: =ROUND(S13*1,5) -> 0.2408
A14: Electricity | B14: 14598682 | C14: 0.64908065 | D14: 15535256 | E14: 0.66186781 | F14: 17341109 | G14: 0.6912281 | H14: 18686182 | I14: 0.7204477 | J14: 0.712 | K14: 20195540 | L14: 0.703 | M14: 0.661 | N14: 0.83 | O14: =M200OPR!O14 -> 65089232 | P14: =ROUND(O14/O$9,4) -> 1.2998 | Q14: =ROUND($S$9*S14,0) -> 66214766 | R14: =Q14-M200OPR!Q14 -> 0 | S14: =ROUND(P14*1,5) -> 1.2998 | T14: =ROUND($U$9*V14,0) -> 66340956 | U14: =T14-M200OPR!T14 -> 0 | V14: =ROUND(S14*1,5) -> 1.2998
A15: Water,sewer,garbage | B15: 6312546 | C15: 0.28066585 | D15: 6576015 | E15: 0.28016614 | F15: 8056235 | G15: 0.32112687 | H15: 8908413 | I15: 0.34346479 | J15: 0.375 | K15: 11063663 | L15: 0.374 | M15: 0.352 | N15: 0.44 | O15: =M200OPR!O15 -> 26757018 | P15: =ROUND(O15/O$9,4) -> 0.5343 | Q15: =ROUND($S$9*S15,0) -> 27218456 | R15: =Q15-M200OPR!Q15 -> 0 | S15: =ROUND(P15*1,5) -> 0.5343 | T15: =ROUND($U$9*V15,0) -> 27270328 | U15: =T15-M200OPR!T15 -> 0 | V15: =ROUND(S15*1,5) -> 0.5343
A16: Property Insurance | B16: 1501429 | C16: 0.066755925 | D16: 1110434 | E16: 0.047309199 | F16: 885169 | G16: 0.035283423 | H16: 837499 | I16: 0.032289861 | J16: 0.034 | K16: 546170 | L16: 0.011 | M16: 0.011 | N16: 0.01 | O16: =M200OPR!O16 -> 1981658 | P16: =ROUND(O16/O$9,4) -> 0.0396 | Q16: =ROUND($S$9*S16,0) -> 2017314 | R16: =Q16-M200OPR!Q16 -> 0 | S16: =ROUND(P16*1,5) -> 0.0396 | T16: =ROUND($U$9*V16,0) -> 2021159 | U16: =T16-M200OPR!T16 -> 0 | V16: =ROUND(S16*1,5) -> 0.0396
A17: Maint/Repair | B17: 2180215 | C17: 0.096935832 | D17: 2670046 | E17: 0.11375529 | F17: 2934985 | G17: 0.11699045 | H17: 2949015 | I17: 0.11369958 | J17: 0.163 | K17: 5143470 | L17: 0.175 | M17: 0.164 | N17: 0.445 | O17: =M200OPR!O17 -> 25553696 | P17: =ROUND(O17/O$9,4) -> 0.5103 | Q17: =ROUND($S$9*S17,0) -> 25995842 | R17: =Q17-M200OPR!Q17 -> 0 | S17: =ROUND(P17*1,5) -> 0.5103 | T17: =ROUND($U$9*V17,0) -> 26045384 | U17: =T17-M200OPR!T17 -> 0 | V17: =ROUND(S17*1,5) -> 0.5103
B18: 27759679 | D18: 29437956 | F18: 32982972 | H18: 35424775 | K18: 40979436 | L18: 1.427 | M18: 1.343 | N18: 1.866 | O18: =SUM(O13:O17) -> 131439156 | P18: =SUM(P13:P17) -> 2.6248 | Q18: =SUM(Q13:Q17) -> 133713277 | R18: =SUM(R13:R17) -> 0 | S18: =ROUND(P18*1,5) -> 2.6248 | T18: =SUM(T13:T17) -> 133968104 | U18: =SUM(U13:U17) -> 0 | V18: =ROUND(S18*1,5) -> 2.6248
Q19: =Q18-M200OPR!Q18 -> 0 | T19: =T18-M200OPR!T18 -> 0
A21: SCHOOL WEIGHTED | C21: 1992 | E21: 1993 | G21: 1994 | I21: 1995 | J21: 1996 | L21: 1998 | N21: 1999 | O21: 2010 | Q21: 2012 | T21: 2013
A22: ENROLLMENTS | C22: Actual | E22: Actual | G22: Actual | I22: Actual | J22: Actual | L22: Actual | N22: Actual | O22: Actual | Q22: Projected | T22: Projected
C23: 204207 | E23: 214997 | G23: 227302 | I23: 227302 | J23: 255215.4 | L23: 285990 | N23: 300115.4 | O23: =DSADATABASE!A4 -> 425527.2 | Q23: =DSADATABASE!C4 -> 421987.1 | T23: =DSADATABASE!D4 -> 423499.6
A25: STUDENT | B25: 1992 Actual | C25: 1992 Cost | D25: 1993 Actual | E25: 1993 Cost | F25: 1994 Actual | G25: 1994 Cost | H25: 1995 Actual | I25: 1995 Cost | J25: 1996 Cost | K25: 1997 Actual | L25: 1998 Cost | M25: 1999 Cost | N25: 2000 Cost | O25: =O$11 -> 2010 Actual | P25: =P$11 -> 2010 Cost | Q25: =Q$11 -> 2012 Cost | R25: =R$11 -> 2012 Add'l | S25: =S$11 -> 2012 Cost | T25: =T$11 -> 2012 Cost | U25: =U$11 -> 2013 Add'l | V25: =V$11 -> 2013 Cost
A26: DRIVEN COST | B26: Cost | C26: Per Student | D26: Cost | E26: Per Student | F26: Cost | G26: Per Student | H26: Cost | I26: Per Student | J26: Per Student | K26: Cost | L26: Per Student | M26: Per Student | N26: Per Student | O26: Cost | P26: Per Student | Q26: W Cola | R26: Cost | S26: Per Student | T26: W Cola | U26: Cost | V26: Per Student
A27: Pupil Transportation | B27: 6410321 | C27: 31.391289 | D27: 6149230 | E27: 28.601469 | F27: 7888311 | G27: 34.704099 | H27: 7317118 | I27: 32.191173 | J27: 50.96 | K27: 9462961 | L27: 35.1 | M27: 31.2 | N27: 40.07 | O27: =M200OPR!O27 -> 16707325 | P27: =ROUND(O27/O$23,4) -> 39.2626 | Q27: =ROUND($Q$23*S27,0) -> 16568311 | R27: =Q27-M200OPR!Q27 -> 0 | S27: =ROUND(P27*1,5) -> 39.2626 | T27: =ROUND($T$23*V27,0) -> 16627695 | U27: =T27-M200OPR!T27 -> 0 | V27: =ROUND(S27*1,5) -> 39.2626
A28: Textbooks | B28: 8226072 | C28: 40.283007 | D28: 8534733 | E28: 39.696986 | F28: 9274867 | G28: 40.804159 | H28: 9993340 | I28: 43.965033 | J28: 36.64 | K28: 11750179 | L28: 49.54 | M28: 52.71 | N28: 43.43 | O28: =M200OPR!O28 -> 23810368 | P28: =ROUND(O28/O$23,4) -> 55.955 | Q28: =ROUND($Q$23*S28,0) -> 23612288 | R28: =Q28-M200OPR!Q28 -> 0 | S28: =ROUND(P28*1,5) -> 55.955 | T28: =ROUND($T$23*V28,0) -> 23696920 | U28: =T28-M200OPR!T28 -> 0 | V28: =ROUND(S28*1,5) -> 55.955
A29: Library | B29: 1363322 | C29: 6.6761766 | D29: 1044344 | E29: 4.8574817 | F29: 1567481 | G29: 6.8960282 | H29: 1351462 | I29: 5.945667 | J29: 6.43 | K29: 1853767 | L29: 7.59 | M29: 8.01 | N29: 6.46 | O29: =M200OPR!O29 -> 2397912 | P29: =ROUND(O29/O$23,4) -> 5.6352 | Q29: =ROUND($Q$23*S29,0) -> 2377982 | R29: =Q29-M200OPR!Q29 -> 0 | S29: =ROUND(P29*1,5) -> 5.6352 | T29: =ROUND($T$23*V29,0) -> 2386505 | U29: =T29-M200OPR!T29 -> 0 | V29: =ROUND(S29*1,5) -> 5.6352
A30: Instruction Supplies | B30: 10650126 | C30: 52.153579 | D30: 10031838 | E30: 46.660363 | F30: 13887603 | G30: 61.097584 | H30: 14228829 | I30: 62.598785 | J30: 54.27 | K30: 15120627 | L30: 59.36 | M30: 60 | N30: 61.61 | O30: =M200OPR!O30 -> 70944435 | P30: =ROUND(O30/O$23,4) -> 166.7213 | Q30: =ROUND($Q$23*S30,0) -> 70354238 | R30: =Q30-M200OPR!Q30 -> 0 | S30: =ROUND(P30*1,5) -> 166.7213 | T30: =ROUND($T$23*V30,0) -> 70606404 | U30: =T30-M200OPR!T30 -> 0 | V30: =ROUND(S30*1,5) -> 166.7213
A31: Instruction Software | G31: n/a | H31: 1010617 | I31: 4.4461421 | J31: 3.19 | K31: 2745463 | L31: 7.17 | M31: 7.96 | N31: 3.94 | O31: =M200OPR!O31 -> 7384984 | P31: =ROUND(O31/O$23,4) -> 17.3549 | Q31: =ROUND($Q$23*S31,0) -> 7323544 | R31: =Q31-M200OPR!Q31 -> 0 | S31: =ROUND(P31*1,5) -> 17.3549 | T31: =ROUND($T$23*V31,0) -> 7349793 | U31: =T31-M200OPR!T31 -> 0 | V31: =ROUND(S31*1,5) -> 17.3549
A32: Other Supplies | B32: 10444298 | C32: 51.145641 | D32: 8033202 | E32: 37.364252 | F32: 10518106 | G32: 46.273706 | H32: 10503038 | I32: 46.207416 | J32: 35.59 | K32: 11692320 | L32: 43.88 | M32: 16.46 | N32: 18.35 | O32: =M200OPR!O32 -> 16515016 | P32: =ROUND(O32/O$23,4) -> 38.8107 | Q32: =ROUND($Q$23*S32,0) -> 16377615 | R32: =Q32-M200OPR!Q32 -> 0 | S32: =ROUND(P32*1,5) -> 38.8107 | T32: =ROUND($T$23*V32,0) -> 16436316 | U32: =T32-M200OPR!T32 -> 0 | V32: =ROUND(S32*1,5) -> 38.8107
B33: 37094139 | D33: 33793347 | F33: 43136368 | H33: 44404404 | K33: 52625317 | L33: 202.64 | M33: 176.34 | N33: 173.86 | O33: =SUM(O27:O32) -> 137760040 | P33: =SUM(P27:P32) -> 323.7397 | Q33: =SUM(Q27:Q32) -> 136613978 | R33: =SUM(R28:R32) -> 0 | S33: =SUM(S27:S32) -> 323.7397 | T33: =SUM(T27:T32) -> 137103633 | U33: =SUM(U28:U32) -> 0 | V33: =SUM(V27:V32) -> 323.7397
Q34: =Q33-M200OPR!Q33 -> 0 | T34: =T33-M200OPR!T33 -> 0
A36: SCHOOL GENERAL | C36: 1992 | E36: 1993 | G36: 1994 | I36: 1995 | J36: 1996 | L36: 1998 | N36: 1999 | O36: =O21 -> 2010 | Q36: =Q21 -> 2012 | T36: =T21 -> 2013
A37: TOTAL STAFF | C37: Actual | E37: Actual | G37: Actual | I37: Actual | J37: Actual | L37: Actual | N37: Actual | O37: Actual | Q37: Projected | T37: Projected
C38: 18758.9 | E38: 19566.2 | G38: 20374 | I38: 20374 | J38: 21933.7 | L38: 25421 | N38: 26851.6 | O38: =M200SAL!B53 -> 35960.04 | Q38: =M200SAL!E53 -> 35659.56 | T38: =M200SAL!G53 -> 35787.36
A40: STAFF | B40: 1992 Actual | C40: 1992 Cost | D40: 1993 Actual | E40: 1993 Cost | F40: 1994 Actual | G40: 1994 Cost | H40: 1995 Actual | I40: 1995 Cost | J40: 1996 Cost | K40: 1997 Actual | L40: 1998 Cost | M40: 1999 Cost | N40: 2000 Cost | O40: =O$11 -> 2010 Actual | P40: =P$11 -> 2010 Cost | Q40: =Q$11 -> 2012 Cost | R40: =R$11 -> 2012 Add'l | S40: =S$11 -> 2012 Cost | T40: =T$11 -> 2012 Cost | U40: =U$11 -> 2013 Add'l | V40: =V$11 -> 2013 Cost
A41: DRIVEN COST | B41: Cost | C41: Per Staff | D41: Cost | E41: Per Staff | F41: Cost | G41: Per Staff | H41: Cost | I41: Per Staff | J41: Per Staff | K41: Cost | L41: Per Staff | M41: Per Staff | N41: Per Staff | O41: Cost | P41: Per Staff | Q41: W Cola | R41: Cost | S41: Per Staff | T41: W Cola | U41: Cost | V41: Per Staff
A42: Prof Service | B42: 4588671 | C42: 244.61301 | D42: 4057187 | E42: 207.35692 | F42: 4224654 | G42: 207.35516 | H42: 5569499 | I42: 273.36306 | J42: 268.23 | K42: 10221123 | L42: 424.4 | M42: 452.34 | N42: 397.09 | O42: =M200OPR!O42 -> 47269193 | P42: =ROUND(O42/O$38,4) -> 1314.4922 | Q42: =ROUND($Q$38*S42,0) -> 46874213 | R42: =Q42-M200OPR!Q42 -> 0 | S42: =ROUND(P42*1,5) -> 1314.4922 | T42: =ROUND($T$38*V42,0) -> 47042206 | U42: =T42-M200OPR!T42 -> 0 | V42: =ROUND(S42*1,5) -> 1314.4922
A43: Liability Insurance | B43: 2262928 | C43: 120.63223 | D43: 2353400 | E43: 120.27885 | F43: 2951811 | G43: 144.88127 | H43: 2889601 | I43: 141.82787 | J43: 249.46 | K43: 2733417 | L43: 61.56 | M43: 59.28 | N43: 194.25 | O43: =M200OPR!O43 -> 5925229 | P43: =ROUND(O43/O$38,4) -> 164.7726 | Q43: =ROUND($Q$38*S43,0) -> 5875718 | R43: =Q43-M200OPR!Q43 -> 0 | S43: =ROUND(P43*1,5) -> 164.7726 | T43: =ROUND($T$38*V43,0) -> 5896776 | U43: =T43-M200OPR!T43 -> 0 | V43: =ROUND(S43*1,5) -> 164.7726
A44: Postage/Comm | B44: 3244336 | C44: 172.94916 | D44: 3265363 | E44: 166.88795 | F44: 3841730 | G44: 188.56042 | H44: 4407402 | I44: 216.32483 | J44: 195.33 | K44: 5184830 | L44: 229.89 | M44: 242.49 | N44: 270.02 | O44: =M200OPR!O44 -> 13152322 | P44: =ROUND(O44/O$38,4) -> 365.7483 | Q44: =ROUND($Q$38*S44,0) -> 13042423 | R44: =Q44-M200OPR!Q44 -> 0 | S44: =ROUND(P44*1,5) -> 365.7483 | T44: =ROUND($T$38*V44,0) -> 13089166 | U44: =T44-M200OPR!T44 -> 0 | V44: =ROUND(S44*1,5) -> 365.7483
A45: Printing/Binding | B45: 1074234 | C45: 57.265298 | D45: 1346604 | E45: 68.82297 | F45: 1718898 | G45: 84.367233 | H45: 1990302 | I45: 97.688328 | J45: 91.54 | K45: 2073473 | L45: 108.14 | M45: 122.74 | N45: 132.63 | O45: =M200OPR!O45 -> 3217410 | P45: =ROUND(O45/O$38,4) -> 89.4718 | Q45: =ROUND($Q$38*S45,0) -> 3190525 | R45: =Q45-M200OPR!Q45 -> 0 | S45: =ROUND(P45*1,5) -> 89.4718 | T45: =ROUND($T$38*V45,0) -> 3201960 | U45: =T45-M200OPR!T45 -> 0 | V45: =ROUND(S45*1,5) -> 89.4718
A46: Other Fuel | B46: 333980 | C46: 17.803816 | D46: 378061 | E46: 19.322147 | F46: 292111 | G46: 14.33744 | H46: 266047 | I46: 13.058162 | J46: 14.94 | K46: 381414 | L46: 19.36 | M46: 19.4 | N46: 25.92 | O46: =M200OPR!O46 -> 2531857 | P46: =ROUND(O46/O$38,4) -> 70.4075 | Q46: =ROUND($Q$38*S46,0) -> 2510700 | R46: =Q46-M200OPR!Q46 -> 0 | S46: =ROUND(P46*1,5) -> 70.4075 | T46: =ROUND($T$38*V46,0) -> 2519699 | U46: =T46-M200OPR!T46 -> 0 | V46: =ROUND(S46*1,5) -> 70.4075
A47: Staff Travel | B47: 1380013 | C47: 73.565774 | D47: 1422066 | E47: 72.679723 | F47: 1708117 | G47: 83.838078 | H47: 1655142 | I47: 81.23795 | J47: 77.36 | K47: 2232645 | L47: 89.12 | M47: 89.8 | N47: 88.24 | O47: =M200OPR!O47 -> 3539980 | P47: =ROUND(O47/O$38,4) -> 98.442 | Q47: =ROUND($Q$38*S47,0) -> 3510398 | R47: =Q47-M200OPR!Q47 -> 0 | S47: =ROUND(P47*1,5) -> 98.442 | T47: =ROUND($T$38*V47,0) -> 3522979 | U47: =T47-M200OPR!T47 -> 0 | V47: =ROUND(S47*1,5) -> 98.442
A48: All Other | B48: 7646527 | C48: 407.62129 | D48: 17288242 | E48: 883.57688 | F48: 6686660 | G48: 328.19574 | H48: 8200377 | I48: 402.49225 | J48: 384.13 | K48: 9704400 | L48: 253.57 | M48: 330.62 | N48: 331.84 | O48: =M200OPR!O48 -> 9719021 | P48: =ROUND(O48/O$38,4) -> 270.2728 | Q48: =ROUND($Q$38*S48,0) -> 9637809 | R48: =Q48-M200OPR!Q48 -> 0 | S48: =ROUND(P48*1,5) -> 270.2728 | T48: =ROUND($T$38*V48,0) -> 9672350 | U48: =T48-M200OPR!T48 -> 0 | V48: =ROUND(S48*1,5) -> 270.2728
