Workbook
Name __0506New: #REF!
Name __0506New: #REF!
Name __2006_07_New_Total: #REF!
Name __2006_07_New_Total: #REF!
Name __2006_07SF: #REF!
Name __2006_07SF: #REF!
Name __2007_08: #REF!
Name _01_02: #REF!
Name _02_03: #REF!
Name _0405: #REF!
Name _0506New: #REF!
Name _0506tot: '[1]FY 2005-06'!$A$1:$F$77
Name _2005_06_SF: #REF!
Name _2005_06_SF: #REF!
Name _2005_06_Total: #REF!
Name _2005_06_Total: #REF!
Name _2006_07_New_Total: #REF!
Name _2006_07_New_Total: #REF!
Name _2006_07SF: #REF!
Name _2007_08: #REF!
Name _3_2006_07_New_Total: #REF!
Name _4_2006_07SF: #REF!
Name _8_2006_07_New_SF: #REF!
Name AMTLU: [2]Names!$B$11:$I$69
Name AMTLU: [2]Names!$B$11:$I$69
Name AMTLU: [3]Names!$B$75:$I$83
Name AMTLU: [4]Names!$B$11:$I$69
Name AMTLU: [5]Names!$B$11:$I$69
Name AMTLU: Names!$B$75:$I$83
Name FTSELU: FTSE!$B$6:$P$53
Name FY2007Total: #REF!
Name FY2007Total: #REF!
Name New_Fall_2008: [6]New_Fall_2008!$A$1:$G$79
Name New_SF_05: #REF!
Name New_SF_05: #REF!
Name New_Total_2005: #REF!
Name New_Total_2005: #REF!
Name New05_06: #REF!
Name New05_06: #REF!
Name New0506SF: #REF!
Name NewSF06: #REF!
Name NewTotal: #REF!
Name SCHRPT2: #REF!
Name SCHRPT2: #REF!

Sheet Index
B1: Research Expenditures | C1: Links to Institution Tabs
B2: FY 2010 - Year Ended August 31, 2010 | D2: Accountability
D3: Research
D4: Data
H5: For Insitution Specific Questions, Please Contact the Institution Point of Contact
B6: HRI Institutions - Summary | D6: Click Here | H6: Institution Point of Contact for Sources & Uses Package
H7: Name | I7: Phone Number | J7: Email
B10: The University of Texas Southwestern Medical Center at Dallas | D10: Click Here
B11: The University of Texas Medical Branch at Galveston | D11: Click Here
B12: The University of Texas Health Science Center at Houston | D12: Click Here
B13: The University of Texas Health Science Center at San Antonio | D13: Click Here
B14: The University of Texas M.D. Anderson Cancer Center | D14: Click Here
B15: The University of Texas Health Center at Tyler | D15: Click Here
B16: Texas A&M University System Health Science Center | D16: Click Here
B17: University of North Texas Health Science Center at Fort Worth | D17: Click Here
B18: Texas Tech University Health Sciences Center | D18: Click Here
B20: Input Schedules
B21: FTSE & FTFE
B22: Names Schedule
B23: Template Input Schedule
B25: Output Schedules
B26: Almanac
B27: Accountability - HRI_IE_Research

Sheet Almanac
F1: Health-Related Institutions | K1: Return to Index
F2: FY 2010 Summary of Research Expenditures Data to Almanac Publication
A4: Note: Copy and past Column E values to S&U Almanac Tab. Do not send separately.
A5: Almanac Order | B5: FICE Code | C5: Year | D5: Institution | E5: Total Research Expenditures As Deetermined by Research Survey
A6: 1 | B6: 000089 | C6: FY 10 | D6: Texas A&M HSC | E6: =TAMHSC!$L$17 -> 78170881
A7: 2 | B7: 000412 | C7: =C6 -> FY 10 | D7: Texas Tech HSC | E7: =TTUHSC!$L$17 -> 50888460
A8: 3 | B8: 000130 | C8: =C7 -> FY 10 | D8: U. North Texas HSC | E8: =UNTHSC!$L$17 -> 39854879
A9: 4 | B9: 104952 | C9: =C8 -> FY 10 | D9: UT Galveston Medical Branch | E9: =MBG!$L$17 -> 156825004
A10: 5 | B10: 000404 | C10: =C9 -> FY 10 | D10: UT Health Center Tyler | E10: =THC!$L$17 -> 14378132
A11: 6 | B11: 011618 | C11: =C10 -> FY 10 | D11: UT Houston Health Science Center | E11: =HSH!$L$17 -> 240772552
A12: 7 | B12: 025554 | C12: =C11 -> FY 10 | D12: UT M. D. Anderson | E12: =MDA!$L$17 -> 547034744
A13: 8 | B13: 000040 | C13: =C12 -> FY 10 | D13: UT San Antonio HSC | E13: =HSSA!$L$17 -> 185229018
A14: 9 | B14: 000030 | C14: =C13 -> FY 10 | D14: UT Southwestern Med. | E14: =SWM!$L$17 -> 395314936
D15: Total | E15: =SUM(E6:E14) -> 1708468606
D16: =COUNTA(D6:D14) -> 9
D18: 9 Ok
E19: =IF(E15<>Summary!L98,"Error","Balanced") -> Balanced

Sheet HRI_IE_Research
G1: Academic Institutions | N1: Return to Index
G2: FY 2010 Accountability Data From Sources & Uses Reports To HRI_Research
A3: Purpose: This tab is used for input to the Accountability System | G3: November 15, 2012
A5: Data to HRI_Research | F5: FICE
E6: 2010 | F6: Code
F7: Order Used | R7: Institution Point of Contact for Sources & Uses
A8: S & U Order | D8: Institution Name | E8: Load Year | F8: FICE Code | G8: Total of Federal & Private | H8: Expenditures Per Tenure/Tenure Track FTE | I8: Federal & Private As a % of St. Approp. | J8: Federal | K8: State | L8: Private | M8: Institutional | N8: Total Research Expenditures | R8: Name | S8: Phone Number | T8: Email
A9: HRI_Research Columns | E9: A | F9: B | G9: C | H9: D | I9: E | J9: F | K9: G | L9: H | M9: I | N9: J | O9: K | P9: L | Q9: M
A10: HRI_Research Data Labels | E10: Load_Year | F10: FICE | G10: Expenditures | H10: ExpendPerFTE | I10: Eres_StApprop | J10: TResearch_Fed | K10: TResearch_State | L10: TResearch_Pri | M10: TResearch_Inst | N10: TResearch_Total | O10: Patents | P10: PatentApply | Q10: PatentIssue
A11: 390 | D11: UT Southwestern Med. | E11: =$E$6 -> 2010 | F11: 30 | G11: =J11+L11 -> 326768776 | H11: =SWM!$O$44 -> 905578 | I11: =SWM!$O$42 -> 186.3 | J11: =SWM!$F$41 -> 232026985 | K11: =SWM!$G$41+SWM!$H$41 -> 49817136 | L11: =SWM!$J$41+SWM!$K$41 -> 94741791 | M11: =SWM!$I$41 -> 18729024 | N11: =SWM!$L$17 -> 395314936
A12: 420 | D12: UT San Antonio HSC | E12: =$E$6 -> 2010 | F12: 40 | G12: =J12+L12 -> 157403572 | H12: =HSSA!$O$44 -> 476980521 | I12: =HSSA!$O$42 -> 235.5 | J12: =HSSA!$F$41 -> 121723410 | K12: =HSSA!$G$41+HSSA!$H$41 -> 6949370 | L12: =HSSA!$J$41+HSSA!$K$41 -> 35680162 | M12: =HSSA!$I$41 -> 20876076 | N12: =HSSA!$L$17 -> 185229018
A13: 450 | D13: Texas A&M HSC | E13: =$E$6 -> 2010 | F13: 89 | G13: =J13+L13 -> 39619168 | H13: =TAMHSC!$O$44 -> 1760852 | I13: =TAMHSC!$O$42 -> 21.39 | J13: =TAMHSC!$F$41 -> 33511244 | K13: =TAMHSC!$G$41+TAMHSC!$H$41 -> 11348288 | L13: =TAMHSC!$J$41+TAMHSC!$K$41 -> 6107924 | M13: =TAMHSC!$I$41 -> 27203425 | N13: =TAMHSC!$L$17 -> 78170881
A14: 460 | D14: U. North Texas HSC | E14: =$E$6 -> 2010 | F14: 130 | G14: =J14+L14 -> 29666539 | H14: =UNTHSC!$O$44 -> 725343 | I14: =UNTHSC!$O$42 -> 16.47 | J14: =UNTHSC!$F$41 -> 25935870 | K14: =UNTHSC!$G$41+UNTHSC!$H$41 -> 1316900 | L14: =UNTHSC!$J$41+UNTHSC!$K$41 -> 3730669 | M14: =UNTHSC!$I$41 -> 8871440 | N14: =UNTHSC!$L$17 -> 39854879
A15: 440 | D15: UT Health Center Tyler | E15: =$E$6 -> 2010 | F15: 404 | G15: =J15+L15 -> 8798651 | H15: =THC!$O$44 -> N/A | I15: =THC!$O$42 -> 4.54 | J15: =THC!$F$41 -> 7250324 | K15: =THC!$G$41+THC!$H$41 -> 2339810 | L15: =THC!$J$41+THC!$K$41 -> 1548327 | M15: =THC!$I$41 -> 3239671 | N15: =THC!$L$17 -> 14378132
A16: 470 | D16: Texas Tech HSC | E16: =$E$6 -> 2010 | F16: 412 | G16: =J16+L16 -> 16905019 | H16: =TTUHSC!$O$44 -> 211313 | I16: =TTUHSC!$O$42 -> 3.96 | J16: =TTUHSC!$F$41 -> 12950246 | K16: =TTUHSC!$G$41+TTUHSC!$H$41 -> 29208029 | L16: =TTUHSC!$J$41+TTUHSC!$K$41 -> 3954773 | M16: =TTUHSC!$I$41 -> 4775412 | N16: =TTUHSC!$L$17 -> 50888460
A17: 410 | D17: UT Houston Health Science Center | E17: =$E$6 -> 2010 | F17: 11618 | G17: =J17+L17 -> 185676139 | H17: =HSH!$O$44 -> 676687 | I17: =HSH!$O$42 -> 158.08 | J17: =HSH!$F$41 -> 150323653 | K17: =HSH!$G$41+HSH!$H$41 -> 43517011 | L17: =HSH!$J$41+HSH!$K$41 -> 35352486 | M17: =HSH!$I$41 -> 11579402 | N17: =HSH!$L$17 -> 240772552
A18: 430 | D18: UT M. D. Anderson | E18: =$E$6 -> 2010 | F18: 25554 | G18: =J18+L18 -> 339032775 | H18: =MDA!$O$44 -> 832595 | I18: =MDA!$O$42 -> 769.99 | J18: =MDA!$F$41 -> 206664447 | K18: =MDA!$G$41+MDA!$H$41 -> 176805729 | L18: =MDA!$J$41+MDA!$K$41 -> 132368328 | M18: =MDA!$I$41 -> 31196240 | N18: =MDA!$L$17 -> 547034744
A19: 400 | D19: UT Galveston Medical Branch | E19: =$E$6 -> 2010 | F19: 104952 | G19: =J19+L19 -> 147318206 | H19: =MBG!$O$44 -> 449772 | I19: =MBG!$O$42 -> 81.1 | J19: =MBG!$F$41 -> 128839602 | K19: =MBG!$G$41+MBG!$H$41 -> 1674687 | L19: =MBG!$J$41+MBG!$K$41 -> 18478604 | M19: =MBG!$I$41 -> 7832111 | N19: =MBG!$L$17 -> 156825004
D20: Statewide Total | E20: =$E$6 -> 2010 | F20: 445566 | G20: =J20+L20 -> 1251188845 | H20: =Summary!$O$341 -> 826576 | I20: =Summary!$O$330 -> 79.6 | J20: =SUM(J11:J19) -> 919225781 | K20: =SUM(K11:K19) -> 322976960 | L20: =SUM(L11:L19) -> 331963064 | M20: =SUM(M11:M19) -> 134302801 | N20: =SUM(N11:N19) -> 1708468606
E21: =COUNTA(E11:E19) -> 9
B22: Note: Accountability Data excludes all Auxiliary Revenue & Expenditures.
B23: Accountability Data excludes all Public Service Expenditures.
J32: =IF(J20<>Summary!$F$320,"Error","Balanced") -> Balanced | K32: =IF(K20<>(Summary!$G$320+Summary!$H$320),"Error","Balanced") -> Balanced | L32: =IF(L20<>(Summary!$J$320+Summary!$K$320),"Error","Balanced") -> Balanced | M32: =IF(M20<>Summary!$I$320,"Error","Balanced") -> Balanced | N32: =IF(N20<>Summary!$L$320,"Error","Balanced") -> Balanced
G38: 1251188845 | J38: 919225781 | K38: 322976960 | L38: 331963064 | M38: 134302801 | N38: 1708468606
G40: =G38-G20 -> 0 | N40: =N38-N20 -> 0
D42: 2010 Hash Totals | F42: =SUM(F11:F20) -> 588795 | G42: =SUM(G11:G20) -> 2502377690 | H42: =SUM(H11:H20) -> 483369237 | I42: =SUM(I11:I20) -> 1556.93 | J42: =SUM(J11:J20) -> 1838451562 | K42: =SUM(K11:K20) -> 645953920 | L42: =SUM(L11:L20) -> 663926128 | M42: =SUM(M11:M20) -> 268605602 | N42: =SUM(N11:N20) -> 3416937212 | P42: =SUM(F42:O42) -> 9.8202117e+09

Sheet Accountability
E1: Health-Related Institutions | I1: Return to Index
E2: FY 2010 Summary of Research Expenditures By Source to Accountability System
E3: August 17, 2011
A5: Note: Copy and past Columns D,E,F,&G values to S&U Accountability Tab. Do not send separately.
A6: FICE Code | B6: Year | C6: Institution | D6: Total Research Expenditures | E6: Federal | F6: State | G6: Private | H6: Institutional | I6: Check
A7: 000030 | B7: FY 10 | C7: UT Southwestern Med. | D7: =SWM!$L$17 -> 395314936 | E7: =SWM!$F$41 -> 232026985 | F7: =SWM!$G$41+SWM!$H$41 -> 49817136 | G7: =SWM!$J$41+SWM!$K$41 -> 94741791 | H7: =SWM!$I$41 -> 18729024 | I7: =IF(SUM(E7:H7)<>D7,"Error", "Balanced") -> Balanced
A8: 000040 | B8: =B7 -> FY 10 | C8: UT San Antonio HSC | D8: =HSSA!$L$17 -> 185229018 | E8: =HSSA!$F$41 -> 121723410 | F8: =HSSA!$G$41+HSSA!$H$41 -> 6949370 | G8: =HSSA!$J$41+HSSA!$K$41 -> 35680162 | H8: =HSSA!$I$41 -> 20876076 | I8: =IF(SUM(E8:H8)<>D8,"Error", "Balanced") -> Balanced
A9: 000089 | B9: =B8 -> FY 10 | C9: Texas A&M HSC | D9: =TAMHSC!$L$17 -> 78170881 | E9: =TAMHSC!$F$41 -> 33511244 | F9: =TAMHSC!$G$41+TAMHSC!$H$41 -> 11348288 | G9: =TAMHSC!$J$41+TAMHSC!$K$41 -> 6107924 | H9: =TAMHSC!$I$41 -> 27203425 | I9: =IF(SUM(E9:H9)<>D9,"Error", "Balanced") -> Balanced
A10: 000130 | B10: =B9 -> FY 10 | C10: U. North Texas HSC | D10: =UNTHSC!$L$17 -> 39854879 | E10: =UNTHSC!$F$41 -> 25935870 | F10: =UNTHSC!$G$41+UNTHSC!$H$41 -> 1316900 | G10: =UNTHSC!$J$41+UNTHSC!$K$41 -> 3730669 | H10: =UNTHSC!$I$41 -> 8871440 | I10: =IF(SUM(E10:H10)<>D10,"Error", "Balanced") -> Balanced
A11: 000404 | B11: =B10 -> FY 10 | C11: UT Health Center Tyler | D11: =THC!$L$17 -> 14378132 | E11: =THC!$F$41 -> 7250324 | F11: =THC!$G$41+THC!$H$41 -> 2339810 | G11: =THC!$J$41+THC!$K$41 -> 1548327 | H11: =THC!$I$41 -> 3239671 | I11: =IF(SUM(E11:H11)<>D11,"Error", "Balanced") -> Balanced
A12: 000412 | B12: =B11 -> FY 10 | C12: Texas Tech HSC | D12: =TTUHSC!$L$17 -> 50888460 | E12: =TTUHSC!$F$41 -> 12950246 | F12: =TTUHSC!$G$41+TTUHSC!$H$41 -> 29208029 | G12: =TTUHSC!$J$41+TTUHSC!$K$41 -> 3954773 | H12: =TTUHSC!$I$41 -> 4775412 | I12: =IF(SUM(E12:H12)<>D12,"Error", "Balanced") -> Balanced
A13: 011618 | B13: =B12 -> FY 10 | C13: UT Houston Health Science Center | D13: =HSH!$L$17 -> 240772552 | E13: =HSH!$F$41 -> 150323653 | F13: =HSH!$G$41+HSH!$H$41 -> 43517011 | G13: =HSH!$J$41+HSH!$K$41 -> 35352486 | H13: =HSH!$I$41 -> 11579402 | I13: =IF(SUM(E13:H13)<>D13,"Error", "Balanced") -> Balanced
A14: 025554 | B14: =B13 -> FY 10 | C14: UT M. D. Anderson | D14: =MDA!$L$17 -> 547034744 | E14: =MDA!$F$41 -> 206664447 | F14: =MDA!$G$41+MDA!$H$41 -> 176805729 | G14: =MDA!$J$41+MDA!$K$41 -> 132368328 | H14: =MDA!$I$41 -> 31196240 | I14: =IF(SUM(E14:H14)<>D14,"Error", "Balanced") -> Balanced
A15: 104952 | B15: =B14 -> FY 10 | C15: UT Galveston Medical Branch | D15: =MBG!$L$17 -> 156825004 | E15: =MBG!$F$41 -> 128839602 | F15: =MBG!$G$41+MBG!$H$41 -> 1674687 | G15: =MBG!$J$41+MBG!$K$41 -> 18478604 | H15: =MBG!$I$41 -> 7832111 | I15: =IF(SUM(E15:H15)<>D15,"Error", "Balanced") -> Balanced
C16: Total | D16: =SUM(D7:D15) -> 1708468606 | E16: =SUM(E7:E15) -> 919225781 | F16: =SUM(F7:F15) -> 322976960 | G16: =SUM(G7:G15) -> 331963064 | H16: =SUM(H7:H15) -> 134302801 | I16: =IF(SUM(E16:H16)<>D16,"Error", "Balanced") -> Balanced
C17: =COUNTA(C7:C15) -> 9
C19: 9 Ok
D21: =IF(D16<>Summary!L98,"Error","Balanced") -> Balanced | E21: =IF(E16<>Summary!F320,"Error","Balanced") -> Balanced | F21: =IF(F16<>Summary!G320+Summary!H320,"Error","Balanced") -> Balanced | G21: =IF(G16<>Summary!J320+Summary!K320,"Error","Balanced") -> Balanced | H21: =IF(H16<>Summary!I320,"Error","Balanced") -> Balanced

Sheet List
D1: Health-Related Institutions | H1: Return to Index
D2: FY 2010 Summary of Research Expenditures
D3: December 21, 2011
A5: Institution | B5: Research Expenditures Per SRECNA | C5: R & D Not Meeting the Definition of the Research Exp. Survey | D5: Indirect Costs Associated w/ R & D | E5: Capital Outlay for Research | F5: Institution's Research Foundation Expenditures for R & D | G5: Pass Throughts From TX Eng. Exp. Station | H5: Total Research Expenditures As Deetermined by Research Survey
A6: =SWM!$B$1 -> The University of Texas Southwestern Medical Center at Dallas | B6: =SWM!$K$10 -> 308606969 | C6: =SWM!$K$9*-1 -> 0 | D6: =SWM!$L$13 -> 75968647 | E6: =SWM!$L$14 -> 10739320 | F6: =SWM!$L$15 -> 0 | G6: =SWM!$L$16 -> 0 | H6: =SUM(B6:G6) -> 395314936
A7: =MBG!$B$1 -> The University of Texas Medical Branch at Galveston | B7: =MBG!$K$10 -> 116760151 | C7: =MBG!$K$9*-1 -> 0 | D7: =MBG!$L$13 -> 35455128 | E7: =MBG!$L$14 -> 4609725 | F7: =MBG!$L$15 -> 0 | G7: =MBG!$L$16 -> 0 | H7: =SUM(B7:G7) -> 156825004
A8: =HSH!$B$1 -> The University of Texas Health Science Center at Houston | B8: =HSH!$K$10 -> 194367928 | C8: =HSH!$K$9*-1 -> 0 | D8: =HSH!$L$13 -> 42189454 | E8: =HSH!$L$14 -> 4215170 | F8: =HSH!$L$15 -> 0 | G8: =HSH!$L$16 -> 0 | H8: =SUM(B8:G8) -> 240772552
A9: =HSSA!$B$1 -> The University of Texas Health Science Center at San Antonio | B9: =HSSA!$K$10 -> 145165310 | C9: =HSSA!$K$9*-1 -> 0 | D9: =HSSA!$L$13 -> 33528292 | E9: =HSSA!$L$14 -> 6535416 | F9: =HSSA!$L$15 -> 0 | G9: =HSSA!$L$16 -> 0 | H9: =SUM(B9:G9) -> 185229018
A10: =MDA!$B$1 -> The University of Texas M.D. Anderson Cancer Center | B10: =MDA!$K$10 -> 463104671 | C10: =MDA!$K$9*-1 -> 0 | D10: =MDA!$L$13 -> 75631023 | E10: =MDA!$L$14 -> 8299050 | F10: =MDA!$L$15 -> 0 | G10: =MDA!$L$16 -> 0 | H10: =SUM(B10:G10) -> 547034744
A11: =THC!$B$1 -> The University of Texas Health Center at Tyler | B11: =THC!$K$10 -> 12168890 | C11: =THC!$K$9*-1 -> 0 | D11: =THC!$L$13 -> 1844206 | E11: =THC!$L$14 -> 365036 | F11: =THC!$L$15 -> 0 | G11: =THC!$L$16 -> 0 | H11: =SUM(B11:G11) -> 14378132
A12: =TAMHSC!$B$1 -> Texas A&M University System Health Science Center | B12: =TAMHSC!$K$10 -> 39877051 | C12: =TAMHSC!$K$9*-1 -> -1645160 | D12: =TAMHSC!$L$13 -> 678676 | E12: =TAMHSC!$L$14 -> 1386271 | F12: =TAMHSC!$L$15 -> 37511984 | G12: =TAMHSC!$L$16 -> 362059 | H12: =SUM(B12:G12) -> 78170881
A13: =UNTHSC!$B$1 -> University of North Texas Health Science Center at Fort Worth | B13: =UNTHSC!$K$10 -> 33368122 | C13: =UNTHSC!$K$9*-1 -> 0 | D13: =UNTHSC!$L$13 -> 5567035 | E13: =UNTHSC!$L$14 -> 919722 | F13: =UNTHSC!$L$15 -> 0 | G13: =UNTHSC!$L$16 -> 0 | H13: =SUM(B13:G13) -> 39854879
A14: =TTUHSC!$B$1 -> Texas Tech University Health Sciences Center | B14: =TTUHSC!$K$10 -> 41854717 | C14: =TTUHSC!$K$9*-1 -> 0 | D14: =TTUHSC!$L$13 -> 3872809 | E14: =TTUHSC!$L$14 -> 5160934 | F14: =TTUHSC!$L$15 -> 0 | G14: =TTUHSC!$L$16 -> 0 | H14: =SUM(B14:G14) -> 50888460
A15: Total | B15: =SUM(B6:B14) -> 1355273809 | C15: =SUM(C6:C14) -> -1645160 | D15: =SUM(D6:D14) -> 274735270 | E15: =SUM(E6:E14) -> 42230644 | F15: =SUM(F6:F14) -> 37511984 | G15: =SUM(G6:G14) -> 362059 | H15: =SUM(H6:H14) -> 1708468606
A16: =COUNTA(A6:A14) -> 9
H18: =IF(H15<>Summary!L98,"Error","")
H20: Amounts for Formula Funding

Sheet Summary
B1: Summary of All University Institutions | N1: Return to Index | AA1: 12 | AB1: 13
B2: =Input!$B$5 -> For the Year Ended August 31, 2010
B3: =Input!$B$6 -> Source: FY 2010 Research Expenditure Survey
N4: Zoom % should be at 75%.
B6: =Input!$B$7 -> FY 2010
B7: Summary of R & D Expenditures | K7: Overall Total | L7: Defined For Survey
K8: =HSH!$K$8 -> 194367928 | L8: =HSH!$L$8 -> 194367928
K9: =HSSA!$K$8 -> 145165310 | L9: =HSSA!$L$8 -> 145165310
K10: =MBG!$K$8 -> 116760151 | L10: =MBG!$L$8 -> 116760151
K11: =MDA!$K$8 -> 463104671 | L11: =MDA!$L$8 -> 463104671
K12: =SWM!$K$8 -> 308606969 | L12: =SWM!$L$8 -> 308606969
K13: =TAMHSC!$K$8 -> 38231891 | L13: =TAMHSC!$L$8 -> 38231891
K14: =THC!$K$8 -> 12168890 | L14: =THC!$L$8 -> 12168890
K15: =TTUHSC!$K$8 -> 41854717 | L15: =TTUHSC!$L$8 -> 41854717
K16: =UNTHSC!$K$8 -> 33368122 | L16: =UNTHSC!$L$8 -> 33368122
B17: R & D Expenses as defined for the Research Expenditure Survey | K17: =SUM(K8:K16) -> 1353628649 | L17: =SUM(L8:L16) -> 1353628649 | AB17: =SUM(C17:L17) -> 2707257298
K18: =HSH!$K$9 -> 0
K19: =HSSA!$K$9 -> 0
K20: =MBG!$K$9 -> 0
K21: =MDA!$K$9 -> 0
K22: =SWM!$K$9 -> 0
K23: =TAMHSC!$K$9 -> 1645160
K24: =THC!$K$9 -> 0
K25: =TTUHSC!$K$9 -> 0
K26: =UNTHSC!$K$9 -> 0
B27: R & D Expenses not meeting the narrow definition of R & D used in the Research Expenditures Survey | K27: =SUM(K18:K26) -> 1645160 | AB27: =SUM(C27:L27) -> 1645160
K28: =HSH!$K$10 -> 194367928
K29: =HSSA!$K$10 -> 145165310
K30: =MBG!$K$10 -> 116760151
K31: =MDA!$K$10 -> 463104671
K32: =SWM!$K$10 -> 308606969
K33: =TAMHSC!$K$10 -> 39877051
K34: =THC!$K$10 -> 12168890
K35: =TTUHSC!$K$10 -> 41854717
K36: =UNTHSC!$K$10 -> 33368122
B37: Total Expenses for R & D as reported on the Statement of Revenues, Expenses and Changes in Net Assets | K37: =SUM(K28:K36) -> 1355273809
AB38: =SUM(C37:L37) -> 1355273809
K39: =HSH!$K$12 -> 0
K40: =HSSA!$K$12 -> 0
K41: =MBG!$K$12 -> 0
K42: =MDA!$K$12 -> 0
K43: =SWM!$K$12 -> 806596
K44: =TAMHSC!$K$12 -> 0
K45: =THC!$K$12 -> 0
K46: =TTUHSC!$K$12 -> 99282
K47: =UNTHSC!$K$12 -> 0
B48: Other Research-related Equipment Expenditures (noncurrent fund expenditures, etc. - do not include R & D plant expenses or construction) | K48: =SUM(K39:K47) -> 905878 | AB48: =SUM(C38:L38) -> 0
K49: =HSH!$K$13 -> 42189454 | L49: =HSH!$L$13 -> 42189454
K50: =HSSA!$K$13 -> 33528292 | L50: =HSSA!$L$13 -> 33528292
K51: =MBG!$K$13 -> 35455128 | L51: =MBG!$L$13 -> 35455128
K52: =MDA!$K$13 -> 75631023 | L52: =MDA!$L$13 -> 75631023
K53: =SWM!$K$13 -> 75968647 | L53: =SWM!$L$13 -> 75968647
K54: =TAMHSC!$K$13 -> 678676 | L54: =TAMHSC!$L$13 -> 678676
K55: =THC!$K$13 -> 1844206 | L55: =THC!$L$13 -> 1844206
K56: =TTUHSC!$K$13 -> 3872809 | L56: =TTUHSC!$L$13 -> 3872809
K57: =UNTHSC!$K$13 -> 5567035 | L57: =UNTHSC!$L$13 -> 5567035
B58: Indirect Costs associated with Expenses for R & D as defined for this survey | K58: =SUM(K49:K57) -> 274735270 | L58: =SUM(L49:L57) -> 274735270 | AB58: =SUM(C58:L58) -> 549470540
K59: =HSH!$K$14 -> 4215170 | L59: =HSH!$L$14 -> 4215170
K60: =HSSA!$K$14 -> 6535416 | L60: =HSSA!$L$14 -> 6535416
K61: =MBG!$K$14 -> 4609725 | L61: =MBG!$L$14 -> 4609725
K62: =MDA!$K$14 -> 8299050 | L62: =MDA!$L$14 -> 8299050
K63: =SWM!$K$14 -> 10739320 | L63: =SWM!$L$14 -> 10739320
K64: =TAMHSC!$K$14 -> 1386271 | L64: =TAMHSC!$L$14 -> 1386271
K65: =THC!$K$14 -> 365036 | L65: =THC!$L$14 -> 365036
K66: =TTUHSC!$K$14 -> 5160934 | L66: =TTUHSC!$L$14 -> 5160934
K67: =UNTHSC!$K$14 -> 919722 | L67: =UNTHSC!$L$14 -> 919722
B68: Capital Outlay for research equipment (do not include R & D plant expenses or construction) | K68: =SUM(K59:K67) -> 42230644 | L68: =SUM(L59:L67) -> 42230644 | AB68: =SUM(C68:L68) -> 84461288
K69: =HSH!$K$15 -> 0 | L69: =HSH!$L$15 -> 0
K70: =HSSA!$K$15 -> 0 | L70: =HSSA!$L$15 -> 0
K71: =MBG!$K$15 -> 0 | L71: =MBG!$L$15 -> 0
K72: =MDA!$K$15 -> 0 | L72: =MDA!$L$15 -> 0
K73: =SWM!$K$15 -> 0 | L73: =SWM!$L$15 -> 0
K74: =TAMHSC!$K$15 -> 37511984 | L74: =TAMHSC!$L$15 -> 37511984
K75: =THC!$K$15 -> 0 | L75: =THC!$L$15 -> 0
K76: =TTUHSC!$K$15 -> 0 | L76: =TTUHSC!$L$15 -> 0
K77: =UNTHSC!$K$15 -> 0 | L77: =UNTHSC!$L$15 -> 0
B78: Expenditures for conduct of R & D made by institution's research foundation or 501© corporation on behalf of the institution and not report in institution AFR, including indirect costs not reported above | K78: =SUM(K69:K77) -> 37511984 | L78: =SUM(L69:L77) -> 37511984 | AB78: =SUM(C78:L78) -> 75023968
K79: =HSH!$K$16 -> 0 | L79: =HSH!$L$16 -> 0
K80: =HSSA!$K$16 -> 0 | L80: =HSSA!$L$16 -> 0
K81: =MBG!$K$16 -> 0 | L81: =MBG!$L$16 -> 0
K82: =MDA!$K$16 -> 0 | L82: =MDA!$L$16 -> 0
K83: =SWM!$K$16 -> 0 | L83: =SWM!$L$16 -> 0
K84: =TAMHSC!$K$16 -> 362059 | L84: =TAMHSC!$L$16 -> 362059
K85: =THC!$K$16 -> 0 | L85: =THC!$L$16 -> 0
K86: =TTUHSC!$K$16 -> 0 | L86: =TTUHSC!$L$16 -> 0
K87: =UNTHSC!$K$16 -> 0 | L87: =UNTHSC!$L$16 -> 0
B88: Pass-throughs from Texas Engineering Experiment Station not reported in R & D Expenditures as defined for the Research Expenditure Survey | K88: =SUM(K79:K87) -> 362059 | L88: =SUM(L79:L87) -> 362059 | AB88: =SUM(C88:L88) -> 724118
K89: =HSH!$K$17 -> 240772552 | L89: =HSH!$L$17 -> 240772552 | S89: =HSH!$S$17 -> 0
K90: =HSSA!$K$17 -> 185229018 | L90: =HSSA!$L$17 -> 185229018 | S90: =HSSA!$S$17 -> 0
K91: =MBG!$K$17 -> 156825004 | L91: =MBG!$L$17 -> 156825004 | S91: =MBG!$S$17 -> 0
K92: =MDA!$K$17 -> 547034744 | L92: =MDA!$L$17 -> 547034744 | S92: =MDA!$S$17 -> 0
K93: =SWM!$K$17 -> 396121532 | L93: =SWM!$L$17 -> 395314936 | S93: =SWM!$S$17 -> 0
K94: =TAMHSC!$K$17 -> 79816041 | L94: =TAMHSC!$L$17 -> 78170881 | S94: =TAMHSC!$S$17 -> 0
K95: =THC!$K$17 -> 14378132 | L95: =THC!$L$17 -> 14378132 | S95: =THC!$S$17 -> 0
K96: =TTUHSC!$K$17 -> 50987742 | L96: =TTUHSC!$L$17 -> 50888460 | S96: =TTUHSC!$S$17 -> 0
K97: =UNTHSC!$K$17 -> 39854879 | L97: =UNTHSC!$L$17 -> 39854879 | S97: =UNTHSC!$S$17 -> 0
B98: Total R & D Expenditures | K98: =SUM(K89:K97) -> 1711019644 | L98: =SUM(L89:L97) -> 1708468606 | S98: =SUM(S89:S97) -> 0 | T98: 0 | U98: 0 | V98: 0 | AB98: =#REF!+#REF!+#REF!+#REF! -> #REF!
B100: R & D Expenditures By Funding Source
F101: =HSH!$F$20 -> 0 | G101: =HSH!$G$20 -> 0 | H101: =HSH!$H$20 -> 0 | I101: =HSH!$I$20 -> 0 | J101: =HSH!$J$20 -> 0 | K101: =HSH!$K$20 -> 0 | L101: =HSH!$L$20 -> 0
F102: =HSSA!$F$20 -> 0 | G102: =HSSA!$G$20 -> 0 | H102: =HSSA!$H$20 -> 0 | I102: =HSSA!$I$20 -> 0 | J102: =HSSA!$J$20 -> 0 | K102: =HSSA!$K$20 -> 0 | L102: =HSSA!$L$20 -> 0
...

Sheet SWM
B1: The University of Texas Southwestern Medical Center at Dallas | N1: Return to Index | AA1: 12 | AB1: 13
B2: =Input!$B$5 -> For the Year Ended August 31, 2010
B3: =Input!$B$6 -> Source: FY 2010 Research Expenditure Survey
N4: Zoom % should be at 75%.
B6: =Input!$B$7 -> FY 2010
B7: Summary of R & D Expenditures | K7: Overall Total | L7: Defined For Survey
B8: R & D Expenses as defined for the Research Expenditure Survey | K8: =L8 -> 308606969 | L8: =Input!$H$10 -> 308606969 | AB8: =SUM(C8:L8) -> 617213938
B9: R & D Expenses not meeting the narrow definition of R & D used in the Research Expenditures Survey | K9: =Input!$F$10 -> 0 | AB9: =SUM(C9:L9) -> 0
B10: Total Expenses for R & D as reported on the Statement of Revenues, Expenses and Changes in Net Assets | H10: =IF(O10<>0,"Out of Balance with SRECNA","") | K10: =SUM(K8:K9) -> 308606969
AB11: =SUM(C10:L10) -> 308606969
B12: Other Research-related Equipment Expenditures (noncurrent fund expenditures, etc. - do not include R & D plant expenses or construction) | K12: =Input!$G$10 -> 806596 | AB12: =SUM(C11:L11) -> 0
B13: Indirect Costs associated with Expenses for R & D as defined for this survey | K13: =L13 -> 75968647 | L13: =Input!$I$10 -> 75968647 | AB13: =SUM(C13:L13) -> 151937294
B14: Capital Outlay for research equipment (do not include R & D plant expenses or construction) | K14: =L14 -> 10739320 | L14: =Input!$J$10 -> 10739320 | AB14: =SUM(C14:L14) -> 21478640
B15: Expenditures for conduct of R & D made by institution's research foundation or 501© corporation on behalf of the institution and not report in institution AFR, including indirect costs not reported above | K15: =L15 -> 0 | L15: =Input!$K$10 -> 0 | AB15: =SUM(C15:L15) -> 0
B16: Pass-throughs from Texas Engineering Experiment Station not reported in R & D Expenditures as defined for the Research Expenditure Survey | K16: =L16 -> 0 | L16: =Input!$L$10 -> 0 | AB16: =SUM(C16:L16) -> 0
B17: Total R & D Expenditures | K17: =SUM(K10:K16) -> 396121532 | L17: =SUM(L8:L16) -> 395314936 | S17: =L17-INT(L17) -> 0 | T17: 0 | U17: 0 | V17: 0 | AB17: =#REF!+#REF!+#REF!+#REF! -> #REF!
F18: =IF(OR(S17<>0,S41<>0,S54<>0),"Do not Enter Cents - Whole Dollars Only","")
B19: R & D Expenditures By Funding Source | F19: Federal | G19: State Appropriations | H19: State Contracts/Grants | I19: Institution Resources | J19: Private For-Profit | K19: Private Non-Profit | L19: Total
B20: Agricultural Sciences | F20: =Input!$M$10 -> 0 | G20: =Input!$N$10 -> 0 | H20: =Input!$O$10 -> 0 | I20: =Input!$P$10 -> 0 | J20: =Input!$Q$10 -> 0 | K20: =Input!$R$10 -> 0 | L20: =SUM(F20:K20) -> 0 | AB20: =SUM(C20:L20) -> 0
B21: Biological and Other Life Sciences | F21: =Input!$S$10 -> 106280934 | G21: =Input!$T$10 -> 18291963 | H21: =Input!$U$10 -> 1441732 | I21: =Input!$V$10 -> 4367700 | J21: =Input!$W$10 -> 2442520 | K21: =Input!$X$10 -> 32004547 | L21: =SUM(F21:K21) -> 164829396 | AB21: =SUM(C21:L21) -> 329658792
B22: Computer Science | F22: =Input!$Y$10 -> 0 | G22: =Input!$Z$10 -> 0 | H22: =Input!$AA$10 -> 0 | I22: =Input!$AB$10 -> 0 | J22: =Input!$AC$10 -> 0 | K22: =Input!$AD$10 -> 0 | L22: =SUM(F22:K22) -> 0 | AB22: =SUM(C22:L22) -> 0
B23: Engineering | F23: =Input!$AE$10 -> 0 | G23: =Input!$AF$10 -> 0 | H23: =Input!$AG$10 -> 0 | I23: =Input!$AH$10 -> 0 | J23: =Input!$AI$10 -> 0 | K23: =Input!$AJ$10 -> 0 | L23: =SUM(F23:K23) -> 0 | AB23: =SUM(C23:L23) -> 0
B24: Environmental Sciences | F24: =Input!$AK$10 -> 0 | G24: =Input!$AL$10 -> 0 | H24: =Input!$AM$10 -> 0 | I24: =Input!$AN$10 -> 0 | J24: =Input!$AO$10 -> 0 | K24: =Input!$AP$10 -> 0 | L24: =SUM(F24:K24) -> 0 | AB24: =SUM(C24:L24) -> 0
B25: Mathematical Sciences | F25: =Input!$AQ$10 -> 0 | G25: =Input!$AR$10 -> 0 | H25: =Input!$AS$10 -> 0 | I25: =Input!$AT$10 -> 0 | J25: =Input!$AU$10 -> 0 | K25: =Input!$AV$10 -> 0 | L25: =SUM(F25:K25) -> 0 | O25: Difference | AB25: =SUM(C25:L25) -> 0
B26: Medical Sciences | F26: =Input!$AW$10 -> 125591611 | G26: =Input!$AX$10 -> 24005050 | H26: =Input!$AY$10 -> 2302310 | I26: =Input!$AZ$10 -> 12131179 | J26: =Input!$BA$10 -> 17165769 | K26: =Input!$BB$10 -> 39115472 | L26: =SUM(F26:K26) -> 220311391 | N26: =IF(O26<>0,"Out of Balance","Balanced") -> Balanced | O26: =L17-L41 -> 0
B27: Physical Sciences | F27: =Input!$BC$10 -> 0 | G27: =Input!$BD$10 -> 0 | H27: =Input!$BE$10 -> 0 | I27: =Input!$BF$10 -> 0 | J27: =Input!$BG$10 -> 0 | K27: =Input!$BH$10 -> 0 | L27: =SUM(F27:K27) -> 0
B28: Psychology | F28: =Input!$BI$10 -> 0 | G28: =Input!$BJ$10 -> 0 | H28: =Input!$BK$10 -> 0 | I28: =Input!$BL$10 -> 0 | J28: =Input!$BM$10 -> 0 | K28: =Input!$BN$10 -> 0 | L28: =SUM(F28:K28) -> 0
B29: Social Sciences | F29: =Input!$BO$10 -> 0 | G29: =Input!$BP$10 -> 0 | H29: =Input!$BQ$10 -> 0 | I29: =Input!$BR$10 -> 0 | J29: =Input!$BS$10 -> 0 | K29: =Input!$BT$10 -> 0 | L29: =SUM(F29:K29) -> 0
B30: Other Sciences not classified above | F30: =Input!$BU$10 -> 154440 | G30: =Input!$BV$10 -> 3548064 | H30: =Input!$BW$10 -> 228017 | I30: =Input!$BX$10 -> 2230145 | J30: =Input!$BY$10 -> 7569 | K30: =Input!$BZ$10 -> 4005914 | L30: =SUM(F30:K30) -> 10174149
B31: Arts and Humanities | F31: =Input!$CA$10 -> 0 | G31: =Input!$CB$10 -> 0 | H31: =Input!$CC$10 -> 0 | I31: =Input!$CD$10 -> 0 | J31: =Input!$CE$10 -> 0 | K31: =Input!$CF$10 -> 0 | L31: =SUM(F31:K31) -> 0
B32: Business Administration | F32: =Input!$CG$10 -> 0 | G32: =Input!$CH$10 -> 0 | H32: =Input!$CI$10 -> 0 | I32: =Input!$CJ$10 -> 0 | J32: =Input!$CK$10 -> 0 | K32: =Input!$CL$10 -> 0 | L32: =SUM(F32:K32) -> 0
B33: Education | F33: =Input!$CM$10 -> 0 | G33: =Input!$CN$10 -> 0 | H33: =Input!$CO$10 -> 0 | I33: =Input!$CP$10 -> 0 | J33: =Input!$CQ$10 -> 0 | K33: =Input!$CR$10 -> 0 | L33: =SUM(F33:K33) -> 0
B34: Law | F34: =Input!$CS$10 -> 0 | G34: =Input!$CT$10 -> 0 | H34: =Input!$CU$10 -> 0 | I34: =Input!$CV$10 -> 0 | J34: =Input!$CW$10 -> 0 | K34: =Input!$CX$10 -> 0 | L34: =SUM(F34:K34) -> 0
B35: Field of Study - Future Use 1 | F35: =Input!$CY$10 -> 0 | G35: =Input!$CZ$10 -> 0 | H35: =Input!$DA$10 -> 0 | I35: =Input!$DB$10 -> 0 | J35: =Input!$DC$10 -> 0 | K35: =Input!$DD$10 -> 0 | L35: =SUM(F35:K35) -> 0
B36: Field of Study - Future Use 2 | F36: =Input!$DE$10 -> 0 | G36: =Input!$DF$10 -> 0 | H36: =Input!$DG$10 -> 0 | I36: =Input!$DH$10 -> 0 | J36: =Input!$DI$10 -> 0 | K36: =Input!$DJ$10 -> 0 | L36: =SUM(F36:K36) -> 0
B37: Field of Study - Future Use 3 | F37: =Input!$DK$10 -> 0 | G37: =Input!$DL$10 -> 0 | H37: =Input!$DM$10 -> 0 | I37: =Input!$DN$10 -> 0 | J37: =Input!$DO$10 -> 0 | K37: =Input!$DP$10 -> 0 | L37: =SUM(F37:K37) -> 0
B38: Field of Study - Future Use 4 | F38: =Input!$DQ$10 -> 0 | G38: =Input!$DR$10 -> 0 | H38: =Input!$DS$10 -> 0 | I38: =Input!$DT$10 -> 0 | J38: =Input!$DU$10 -> 0 | K38: =Input!$DV$10 -> 0 | L38: =SUM(F38:K38) -> 0
B39: Field of Study - Future Use 5 | F39: =Input!$DW$10 -> 0 | G39: =Input!$DX$10 -> 0 | H39: =Input!$DY$10 -> 0 | I39: =Input!$DZ$10 -> 0 | J39: =Input!$EA$10 -> 0 | K39: =Input!$EB$10 -> 0 | L39: =SUM(F39:K39) -> 0
B40: Other Non-Science Activities | F40: =Input!$EC$10 -> 0 | G40: =Input!$ED$10 -> 0 | H40: =Input!$EE$10 -> 0 | I40: =Input!$EF$10 -> 0 | J40: =Input!$EG$10 -> 0 | K40: =Input!$EH$10 -> 0 | L40: =SUM(F40:K40) -> 0 | O40: To Accountability | P40: Sources & Uses | AB40: =SUM(C40:L40) -> 0
B41: Total R & D Expenditures By Funding Source | F41: =SUM(F20:F40) -> 232026985 | G41: =SUM(G20:G40) -> 45845077 | H41: =SUM(H20:H40) -> 3972059 | I41: =SUM(I20:I40) -> 18729024 | J41: =SUM(J20:J40) -> 19615858 | K41: =SUM(K20:K40) -> 75125933 | L41: =SUM(L20:L40) -> 395314936 | O41: ResPercGenRev | P41: State Appropriations | S41: =L41-INT(L41) -> 0 | AB41: =SUM(AB20:AB40) -> 329658792
G42: State Total | H42: =H41+G41 -> 49817136 | J42: Pvt. Total | K42: =K41+J41 -> 94741791 | L42: Federal & Private | N42: =K42+F41 -> 326768776 | O42: =ROUND((N42/P42)*100,1) -> 186.3 | P42: =Input!$GR$10 -> 175412063 | Z42: =IF(Z41<>0,"Out of Balance","")
B43: R & D Expenditures - Select Areas of Special Interest | O43: ExpendPerFTE
B44: Aging | F44: =Input!$EI$10 -> 6384572 | G44: =Input!$EJ$10 -> 68577 | H44: =Input!$EK$10 -> 1252750 | I44: =Input!$EL$10 -> 186711 | J44: =Input!$EM$10 -> 300461 | K44: =Input!$EN$10 -> 1990416 | L44: =SUM(F44:K44) -> 10183487 | O44: =ROUND(N42/O46,0) -> 905578 | AB44: =SUM(C44:L44) -> 20366974
B45: Cancer Research | F45: =Input!$EO$10 -> 39702425 | G45: =Input!$EP$10 -> 1273457 | H45: =Input!$EQ$10 -> 1469560 | I45: =Input!$ER$10 -> 2082484 | J45: =Input!$ES$10 -> 6297255 | K45: =Input!$ET$10 -> 10060710 | L45: =SUM(F45:K45) -> 60885891 | O45: T/TT Fall Fac FTE
B46: Cardiovascular Research | F46: =Input!$EU$10 -> 21268029 | G46: =Input!$EV$10 -> 915079 | H46: =Input!$EW$10 -> 74519 | I46: =Input!$EX$10 -> 912012 | J46: =Input!$EY$10 -> 538872 | K46: =Input!$EZ$10 -> 7957458 | L46: =SUM(F46:K46) -> 31665969 | O46: =FTSE!$O$6 -> 360.84
B47: Child Health and Human Development | F47: =Input!$FA$10 -> 10822319 | G47: =Input!$FB$10 -> 846276 | H47: =Input!$FC$10 -> 17821 | I47: =Input!$FD$10 -> 677136 | J47: =Input!$FE$10 -> 471342 | K47: =Input!$FF$10 -> 3122225 | L47: =SUM(F47:K47) -> 15957119 | O47: As of Fall xxxxx
B48: Mental Health | F48: =Input!$FG$10 -> 20270635 | G48: =Input!$FH$10 -> 320640 | H48: =Input!$FI$10 -> 0 | I48: =Input!$FJ$10 -> 80797 | J48: =Input!$FK$10 -> 824241 | K48: =Input!$FL$10 -> 3227401 | L48: =SUM(F48:K48) -> 24723714
B49: HRI Special Interest - Future Use 1 | F49: =Input!$FM$10 -> 0 | G49: =Input!$FN$10 -> 0 | H49: =Input!$FO$10 -> 0 | I49: =Input!$FP$10 -> 0 | J49: =Input!$FQ$10 -> 0 | K49: =Input!$FR$10 -> 0 | L49: =SUM(F49:K49) -> 0
B50: HRI Special Interest - Future Use 2 | F50: =Input!$FS$10 -> 0 | G50: =Input!$FT$10 -> 0 | H50: =Input!$FU$10 -> 0 | I50: =Input!$FV$10 -> 0 | J50: =Input!$FW$10 -> 0 | K50: =Input!$FX$10 -> 0 | L50: =SUM(F50:K50) -> 0
B51: HRI Special Interest - Future Use 3 | F51: =Input!$FY$10 -> 0 | G51: =Input!$FZ$10 -> 0 | H51: =Input!$GA$10 -> 0 | I51: =Input!$GB$10 -> 0 | J51: =Input!$GC$10 -> 0 | K51: =Input!$GD$10 -> 0 | L51: =SUM(F51:K51) -> 0
B52: HRI Special Interest - Future Use 4 | F52: =Input!$GE$10 -> 0 | G52: =Input!$GF$10 -> 0 | H52: =Input!$GG$10 -> 0 | I52: =Input!$GH$10 -> 0 | J52: =Input!$GI$10 -> 0 | K52: =Input!$GJ$10 -> 0 | L52: =SUM(F52:K52) -> 0
B53: HRI Special Interest - Future Use 5 | F53: =Input!$GK$10 -> 0 | G53: =Input!$GL$10 -> 0 | H53: =Input!$GM$10 -> 0 | I53: =Input!$GN$10 -> 0 | J53: =Input!$GO$10 -> 0 | K53: =Input!$GP$10 -> 0 | L53: =SUM(F53:K53) -> 0
B54: Total R & D Expenditures - Select Areas of Special Interest | F54: =SUM(F44:F53) -> 98447980 | G54: =SUM(G44:G53) -> 3424029 | H54: =SUM(H44:H53) -> 2814650 | I54: =SUM(I44:I53) -> 3939140 | J54: =SUM(J44:J53) -> 8432171 | K54: =SUM(K44:K53) -> 26358210 | L54: =SUM(L44:L53) -> 143416180 | S54: =L54-INT(L54) -> 0 | AB54: =SUM(AB44:AB48) -> 20366974
F61: =F54+F41 -> 330474965 | G61: =G54+G41 -> 49269106 | H61: =H54+H41 -> 6786709 | I61: =I54+I41 -> 22668164 | J61: =J54+J41 -> 28048029 | K61: =K54+K41 -> 101484143 | L61: =L54+L41 -> 538731116
L62: =SUM(K8:K9)+SUM(K12:K16) -> 396121532
L63: =SUM(L61:L62) -> 934852648
L65: =IF($L$63+L64<>Input!$D$10,"Error","Balanced") -> Balanced

Sheet MBG
B1: The University of Texas Medical Branch at Galveston | N1: Return to Index | AA1: 12 | AB1: 13
B2: =Input!$B$5 -> For the Year Ended August 31, 2010
B3: =Input!$B$6 -> Source: FY 2010 Research Expenditure Survey
N4: Zoom % should be at 75%.
B6: =Input!$B$7 -> FY 2010
B7: Summary of R & D Expenditures | K7: Overall Total | L7: Defined For Survey
B8: R & D Expenses as defined for the Research Expenditure Survey | K8: =L8 -> 116760151 | L8: =Input!$H$11 -> 116760151 | AB8: =SUM(C8:L8) -> 233520302
B9: R & D Expenses not meeting the narrow definition of R & D used in the Research Expenditures Survey | K9: =Input!$F$11 -> 0 | AB9: =SUM(C9:L9) -> 0
B10: Total Expenses for R & D as reported on the Statement of Revenues, Expenses and Changes in Net Assets | H10: =IF(O10<>0,"Out of Balance with SRECNA","") | K10: =SUM(K8:K9) -> 116760151
AB11: =SUM(C10:L10) -> 116760151
B12: Other Research-related Equipment Expenditures (noncurrent fund expenditures, etc. - do not include R & D plant expenses or construction) | K12: =Input!$G$11 -> 0 | AB12: =SUM(C11:L11) -> 0
B13: Indirect Costs associated with Expenses for R & D as defined for this survey | K13: =L13 -> 35455128 | L13: =Input!$I$11 -> 35455128 | AB13: =SUM(C13:L13) -> 70910256
B14: Capital Outlay for research equipment (do not include R & D plant expenses or construction) | K14: =L14 -> 4609725 | L14: =Input!$J$11 -> 4609725 | AB14: =SUM(C14:L14) -> 9219450
B15: Expenditures for conduct of R & D made by institution's research foundation or 501© corporation on behalf of the institution and not report in institution AFR, including indirect costs not reported above | K15: =L15 -> 0 | L15: =Input!$K$11 -> 0 | AB15: =SUM(C15:L15) -> 0
B16: Pass-throughs from Texas Engineering Experiment Station not reported in R & D Expenditures as defined for the Research Expenditure Survey | K16: =L16 -> 0 | L16: =Input!$L$11 -> 0 | AB16: =SUM(C16:L16) -> 0
B17: Total R & D Expenditures | K17: =SUM(K10:K16) -> 156825004 | L17: =SUM(L8:L16) -> 156825004 | S17: =L17-INT(L17) -> 0 | T17: 0 | U17: 0 | V17: 0 | AB17: =#REF!+#REF!+#REF!+#REF! -> #REF!
F18: =IF(OR(S17<>0,S41<>0,S54<>0),"Do not Enter Cents - Whole Dollars Only","")
B19: R & D Expenditures By Funding Source | F19: Federal | G19: State Appropriations | H19: State Contracts/Grants | I19: Institution Resources | J19: Private For-Profit | K19: Private Non-Profit | L19: Total
B20: Agricultural Sciences | F20: =Input!$M$11 -> 0 | G20: =Input!$N$11 -> 0 | H20: =Input!$O$11 -> 0 | I20: =Input!$P$11 -> 0 | J20: =Input!$Q$11 -> 0 | K20: =Input!$R$11 -> 0 | L20: =SUM(F20:K20) -> 0 | AB20: =SUM(C20:L20) -> 0
B21: Biological and Other Life Sciences | F21: =Input!$S$11 -> 51523589 | G21: =Input!$T$11 -> 318588 | H21: =Input!$U$11 -> 90752 | I21: =Input!$V$11 -> 4497868 | J21: =Input!$W$11 -> 1321290 | K21: =Input!$X$11 -> 5361267 | L21: =SUM(F21:K21) -> 63113354 | AB21: =SUM(C21:L21) -> 126226708
B22: Computer Science | F22: =Input!$Y$11 -> 0 | G22: =Input!$Z$11 -> 0 | H22: =Input!$AA$11 -> 0 | I22: =Input!$AB$11 -> 0 | J22: =Input!$AC$11 -> 0 | K22: =Input!$AD$11 -> 0 | L22: =SUM(F22:K22) -> 0 | AB22: =SUM(C22:L22) -> 0
B23: Engineering | F23: =Input!$AE$11 -> 886702 | G23: =Input!$AF$11 -> 398247 | H23: =Input!$AG$11 -> 0 | I23: =Input!$AH$11 -> 99878 | J23: =Input!$AI$11 -> 54945 | K23: =Input!$AJ$11 -> 1482 | L23: =SUM(F23:K23) -> 1441254 | AB23: =SUM(C23:L23) -> 2882508
B24: Environmental Sciences | F24: =Input!$AK$11 -> 0 | G24: =Input!$AL$11 -> 0 | H24: =Input!$AM$11 -> 0 | I24: =Input!$AN$11 -> 0 | J24: =Input!$AO$11 -> 0 | K24: =Input!$AP$11 -> 0 | L24: =SUM(F24:K24) -> 0 | AB24: =SUM(C24:L24) -> 0
B25: Mathematical Sciences | F25: =Input!$AQ$11 -> 0 | G25: =Input!$AR$11 -> 0 | H25: =Input!$AS$11 -> 0 | I25: =Input!$AT$11 -> 0 | J25: =Input!$AU$11 -> 0 | K25: =Input!$AV$11 -> 0 | L25: =SUM(F25:K25) -> 0 | O25: Difference | AB25: =SUM(C25:L25) -> 0
B26: Medical Sciences | F26: =Input!$AW$11 -> 76429311 | G26: =Input!$AX$11 -> 187413 | H26: =Input!$AY$11 -> 679687 | I26: =Input!$AZ$11 -> 3234365 | J26: =Input!$BA$11 -> 2288952 | K26: =Input!$BB$11 -> 9450668 | L26: =SUM(F26:K26) -> 92270396 | N26: =IF(O26<>0,"Out of Balance","Balanced") -> Balanced | O26: =L17-L41 -> 0
B27: Physical Sciences | F27: =Input!$BC$11 -> 0 | G27: =Input!$BD$11 -> 0 | H27: =Input!$BE$11 -> 0 | I27: =Input!$BF$11 -> 0 | J27: =Input!$BG$11 -> 0 | K27: =Input!$BH$11 -> 0 | L27: =SUM(F27:K27) -> 0
B28: Psychology | F28: =Input!$BI$11 -> 0 | G28: =Input!$BJ$11 -> 0 | H28: =Input!$BK$11 -> 0 | I28: =Input!$BL$11 -> 0 | J28: =Input!$BM$11 -> 0 | K28: =Input!$BN$11 -> 0 | L28: =SUM(F28:K28) -> 0
B29: Social Sciences | F29: =Input!$BO$11 -> 0 | G29: =Input!$BP$11 -> 0 | H29: =Input!$BQ$11 -> 0 | I29: =Input!$BR$11 -> 0 | J29: =Input!$BS$11 -> 0 | K29: =Input!$BT$11 -> 0 | L29: =SUM(F29:K29) -> 0
B30: Other Sciences not classified above | F30: =Input!$BU$11 -> 0 | G30: =Input!$BV$11 -> 0 | H30: =Input!$BW$11 -> 0 | I30: =Input!$BX$11 -> 0 | J30: =Input!$BY$11 -> 0 | K30: =Input!$BZ$11 -> 0 | L30: =SUM(F30:K30) -> 0
B31: Arts and Humanities | F31: =Input!$CA$11 -> 0 | G31: =Input!$CB$11 -> 0 | H31: =Input!$CC$11 -> 0 | I31: =Input!$CD$11 -> 0 | J31: =Input!$CE$11 -> 0 | K31: =Input!$CF$11 -> 0 | L31: =SUM(F31:K31) -> 0
B32: Business Administration | F32: =Input!$CG$11 -> 0 | G32: =Input!$CH$11 -> 0 | H32: =Input!$CI$11 -> 0 | I32: =Input!$CJ$11 -> 0 | J32: =Input!$CK$11 -> 0 | K32: =Input!$CL$11 -> 0 | L32: =SUM(F32:K32) -> 0
B33: Education | F33: =Input!$CM$11 -> 0 | G33: =Input!$CN$11 -> 0 | H33: =Input!$CO$11 -> 0 | I33: =Input!$CP$11 -> 0 | J33: =Input!$CQ$11 -> 0 | K33: =Input!$CR$11 -> 0 | L33: =SUM(F33:K33) -> 0
B34: Law | F34: =Input!$CS$11 -> 0 | G34: =Input!$CT$11 -> 0 | H34: =Input!$CU$11 -> 0 | I34: =Input!$CV$11 -> 0 | J34: =Input!$CW$11 -> 0 | K34: =Input!$CX$11 -> 0 | L34: =SUM(F34:K34) -> 0
B35: Field of Study - Future Use 1 | F35: =Input!$CY$11 -> 0 | G35: =Input!$CZ$11 -> 0 | H35: =Input!$DA$11 -> 0 | I35: =Input!$DB$11 -> 0 | J35: =Input!$DC$11 -> 0 | K35: =Input!$DD$11 -> 0 | L35: =SUM(F35:K35) -> 0
B36: Field of Study - Future Use 2 | F36: =Input!$DE$11 -> 0 | G36: =Input!$DF$11 -> 0 | H36: =Input!$DG$11 -> 0 | I36: =Input!$DH$11 -> 0 | J36: =Input!$DI$11 -> 0 | K36: =Input!$DJ$11 -> 0 | L36: =SUM(F36:K36) -> 0
B37: Field of Study - Future Use 3 | F37: =Input!$DK$11 -> 0 | G37: =Input!$DL$11 -> 0 | H37: =Input!$DM$11 -> 0 | I37: =Input!$DN$11 -> 0 | J37: =Input!$DO$11 -> 0 | K37: =Input!$DP$11 -> 0 | L37: =SUM(F37:K37) -> 0
B38: Field of Study - Future Use 4 | F38: =Input!$DQ$11 -> 0 | G38: =Input!$DR$11 -> 0 | H38: =Input!$DS$11 -> 0 | I38: =Input!$DT$11 -> 0 | J38: =Input!$DU$11 -> 0 | K38: =Input!$DV$11 -> 0 | L38: =SUM(F38:K38) -> 0
B39: Field of Study - Future Use 5 | F39: =Input!$DW$11 -> 0 | G39: =Input!$DX$11 -> 0 | H39: =Input!$DY$11 -> 0 | I39: =Input!$DZ$11 -> 0 | J39: =Input!$EA$11 -> 0 | K39: =Input!$EB$11 -> 0 | L39: =SUM(F39:K39) -> 0
B40: Other Non-Science Activities | F40: =Input!$EC$11 -> 0 | G40: =Input!$ED$11 -> 0 | H40: =Input!$EE$11 -> 0 | I40: =Input!$EF$11 -> 0 | J40: =Input!$EG$11 -> 0 | K40: =Input!$EH$11 -> 0 | L40: =SUM(F40:K40) -> 0 | O40: To Accountability | P40: Sources & Uses | AB40: =SUM(C40:L40) -> 0
B41: Total R & D Expenditures By Funding Source | F41: =SUM(F20:F40) -> 128839602 | G41: =SUM(G20:G40) -> 904248 | H41: =SUM(H20:H40) -> 770439 | I41: =SUM(I20:I40) -> 7832111 | J41: =SUM(J20:J40) -> 3665187 | K41: =SUM(K20:K40) -> 14813417 | L41: =SUM(L20:L40) -> 156825004 | O41: ResPercGenRev | P41: State Appropriations | S41: =L41-INT(L41) -> 0 | AB41: =SUM(AB20:AB40) -> 129109216
G42: State Total | H42: =H41+G41 -> 1674687 | J42: Pvt. Total | K42: =K41+J41 -> 18478604 | L42: Federal & Private | N42: =K42+F41 -> 147318206 | O42: =ROUND((N42/P42)*100,2) -> 81.1 | P42: =Input!$GR$11 -> 181651995 | Z42: =IF(Z41<>0,"Out of Balance","")
B43: R & D Expenditures - Select Areas of Special Interest | O43: ExpendPerFTE
B44: Aging | F44: =Input!$EI$11 -> 8597797 | G44: =Input!$EJ$11 -> 0 | H44: =Input!$EK$11 -> 6194 | I44: =Input!$EL$11 -> 0 | J44: =Input!$EM$11 -> 326773 | K44: =Input!$EN$11 -> 583641 | L44: =SUM(F44:K44) -> 9514405 | O44: =ROUND(N42/O46,0) -> 449772 | AB44: =SUM(C44:L44) -> 19028810
B45: Cancer Research | F45: =Input!$EO$11 -> 10417568 | G45: =Input!$EP$11 -> 0 | H45: =Input!$EQ$11 -> 14033 | I45: =Input!$ER$11 -> 0 | J45: =Input!$ES$11 -> 77508 | K45: =Input!$ET$11 -> 415488 | L45: =SUM(F45:K45) -> 10924597 | O45: T/TT Fall Fac FTE
B46: Cardiovascular Research | F46: =Input!$EU$11 -> 2398159 | G46: =Input!$EV$11 -> 0 | H46: =Input!$EW$11 -> 0 | I46: =Input!$EX$11 -> 0 | J46: =Input!$EY$11 -> 518794 | K46: =Input!$EZ$11 -> 1030055 | L46: =SUM(F46:K46) -> 3947008 | O46: =FTSE!$O$10 -> 327.54
B47: Child Health and Human Development | F47: =Input!$FA$11 -> 5352931 | G47: =Input!$FB$11 -> 0 | H47: =Input!$FC$11 -> 0 | I47: =Input!$FD$11 -> 0 | J47: =Input!$FE$11 -> 254205 | K47: =Input!$FF$11 -> 258248 | L47: =SUM(F47:K47) -> 5865384 | O47: As of Fall xxxxx
B48: Mental Health | F48: =Input!$FG$11 -> 325035 | G48: =Input!$FH$11 -> 0 | H48: =Input!$FI$11 -> 0 | I48: =Input!$FJ$11 -> 0 | J48: =Input!$FK$11 -> 286186 | K48: =Input!$FL$11 -> 415022 | L48: =SUM(F48:K48) -> 1026243
B49: HRI Special Interest - Future Use 1 | F49: =Input!$FM$11 -> 0 | G49: =Input!$FN$11 -> 0 | H49: =Input!$FO$11 -> 0 | I49: =Input!$FP$11 -> 0 | J49: =Input!$FQ$11 -> 0 | K49: =Input!$FR$11 -> 0 | L49: =SUM(F49:K49) -> 0
B50: HRI Special Interest - Future Use 2 | F50: =Input!$FS$11 -> 0 | G50: =Input!$FT$11 -> 0 | H50: =Input!$FU$11 -> 0 | I50: =Input!$FV$11 -> 0 | J50: =Input!$FW$11 -> 0 | K50: =Input!$FX$11 -> 0 | L50: =SUM(F50:K50) -> 0
B51: HRI Special Interest - Future Use 3 | F51: =Input!$FY$11 -> 0 | G51: =Input!$FZ$11 -> 0 | H51: =Input!$GA$11 -> 0 | I51: =Input!$GB$11 -> 0 | J51: =Input!$GC$11 -> 0 | K51: =Input!$GD$11 -> 0 | L51: =SUM(F51:K51) -> 0
B52: HRI Special Interest - Future Use 4 | F52: =Input!$GE$11 -> 0 | G52: =Input!$GF$11 -> 0 | H52: =Input!$GG$11 -> 0 | I52: =Input!$GH$11 -> 0 | J52: =Input!$GI$11 -> 0 | K52: =Input!$GJ$11 -> 0 | L52: =SUM(F52:K52) -> 0
B53: HRI Special Interest - Future Use 5 | F53: =Input!$GK$11 -> 0 | G53: =Input!$GL$11 -> 0 | H53: =Input!$GM$11 -> 0 | I53: =Input!$GN$11 -> 0 | J53: =Input!$GO$11 -> 0 | K53: =Input!$GP$11 -> 0 | L53: =SUM(F53:K53) -> 0
B54: Total R & D Expenditures - Select Areas of Special Interest | F54: =SUM(F44:F53) -> 27091490 | G54: =SUM(G44:G53) -> 0 | H54: =SUM(H44:H53) -> 20227 | I54: =SUM(I44:I53) -> 0 | J54: =SUM(J44:J53) -> 1463466 | K54: =SUM(K44:K53) -> 2702454 | L54: =SUM(L44:L53) -> 31277637 | S54: =L54-INT(L54) -> 0 | AB54: =SUM(AB44:AB48) -> 19028810
F61: =F54+F41 -> 155931092 | G61: =G54+G41 -> 904248 | H61: =H54+H41 -> 790666 | I61: =I54+I41 -> 7832111 | J61: =J54+J41 -> 5128653 | K61: =K54+K41 -> 17515871 | L61: =L54+L41 -> 188102641
L62: =SUM(K8:K9)+SUM(K12:K16) -> 156825004
L63: =SUM(L61:L62) -> 344927645
L65: =IF($L$63+L64<>Input!$D$11,"Error","Balanced") -> Balanced

Sheet HSH
B1: The University of Texas Health Science Center at Houston | N1: Return to Index | AA1: 12 | AB1: 13
B2: =Input!$B$5 -> For the Year Ended August 31, 2010
B3: =Input!$B$6 -> Source: FY 2010 Research Expenditure Survey
N4: Zoom % should be at 75%.
B6: =Input!$B$7 -> FY 2010
B7: Summary of R & D Expenditures | K7: Overall Total | L7: Defined For Survey
B8: R & D Expenses as defined for the Research Expenditure Survey | K8: =L8 -> 194367928 | L8: =Input!$H$12 -> 194367928 | AB8: =SUM(C8:L8) -> 388735856
B9: R & D Expenses not meeting the narrow definition of R & D used in the Research Expenditures Survey | K9: =Input!$F$12 -> 0 | AB9: =SUM(C9:L9) -> 0
B10: Total Expenses for R & D as reported on the Statement of Revenues, Expenses and Changes in Net Assets | H10: =IF(O10<>0,"Out of Balance with SRECNA","") | K10: =SUM(K8:K9) -> 194367928
AB11: =SUM(C10:L10) -> 194367928
B12: Other Research-related Equipment Expenditures (noncurrent fund expenditures, etc. - do not include R & D plant expenses or construction) | K12: =Input!$G$12 -> 0 | AB12: =SUM(C11:L11) -> 0
B13: Indirect Costs associated with Expenses for R & D as defined for this survey | K13: =L13 -> 42189454 | L13: =Input!$I$12 -> 42189454 | AB13: =SUM(C13:L13) -> 84378908
B14: Capital Outlay for research equipment (do not include R & D plant expenses or construction) | K14: =L14 -> 4215170 | L14: =Input!$J$12 -> 4215170 | AB14: =SUM(C14:L14) -> 8430340
B15: Expenditures for conduct of R & D made by institution's research foundation or 501© corporation on behalf of the institution and not report in institution AFR, including indirect costs not reported above | K15: =L15 -> 0 | L15: =Input!$K$12 -> 0 | AB15: =SUM(C15:L15) -> 0
B16: Pass-throughs from Texas Engineering Experiment Station not reported in R & D Expenditures as defined for the Research Expenditure Survey | K16: =L16 -> 0 | L16: =Input!$L$12 -> 0 | AB16: =SUM(C16:L16) -> 0
B17: Total R & D Expenditures | K17: =SUM(K10:K16) -> 240772552 | L17: =SUM(L8:L16) -> 240772552 | S17: =L17-INT(L17) -> 0 | T17: 0 | U17: 0 | V17: 0 | AB17: =#REF!+#REF!+#REF!+#REF! -> #REF!
F18: =IF(OR(S17<>0,S41<>0,S54<>0),"Do not Enter Cents - Whole Dollars Only","")
B19: R & D Expenditures By Funding Source | F19: Federal | G19: State Appropriations | H19: State Contracts/Grants | I19: Institution Resources | J19: Private For-Profit | K19: Private Non-Profit | L19: Total
B20: Agricultural Sciences | F20: =Input!$M$12 -> 0 | G20: =Input!$N$12 -> 0 | H20: =Input!$O$12 -> 0 | I20: =Input!$P$12 -> 0 | J20: =Input!$Q$12 -> 0 | K20: =Input!$R$12 -> 0 | L20: =SUM(F20:K20) -> 0 | AB20: =SUM(C20:L20) -> 0
B21: Biological and Other Life Sciences | F21: =Input!$S$12 -> 35368893 | G21: =Input!$T$12 -> 1162935 | H21: =Input!$U$12 -> 388260 | I21: =Input!$V$12 -> 1126511 | J21: =Input!$W$12 -> 399375 | K21: =Input!$X$12 -> 2807980 | L21: =SUM(F21:K21) -> 41253954 | AB21: =SUM(C21:L21) -> 82507908
B22: Computer Science | F22: =Input!$Y$12 -> 0 | G22: =Input!$Z$12 -> 0 | H22: =Input!$AA$12 -> 0 | I22: =Input!$AB$12 -> 0 | J22: =Input!$AC$12 -> 0 | K22: =Input!$AD$12 -> 0 | L22: =SUM(F22:K22) -> 0 | AB22: =SUM(C22:L22) -> 0
B23: Engineering | F23: =Input!$AE$12 -> 0 | G23: =Input!$AF$12 -> 0 | H23: =Input!$AG$12 -> 0 | I23: =Input!$AH$12 -> 0 | J23: =Input!$AI$12 -> 0 | K23: =Input!$AJ$12 -> 0 | L23: =SUM(F23:K23) -> 0 | AB23: =SUM(C23:L23) -> 0
B24: Environmental Sciences | F24: =Input!$AK$12 -> 0 | G24: =Input!$AL$12 -> 0 | H24: =Input!$AM$12 -> 0 | I24: =Input!$AN$12 -> 0 | J24: =Input!$AO$12 -> 0 | K24: =Input!$AP$12 -> 0 | L24: =SUM(F24:K24) -> 0 | AB24: =SUM(C24:L24) -> 0
B25: Mathematical Sciences | F25: =Input!$AQ$12 -> 0 | G25: =Input!$AR$12 -> 0 | H25: =Input!$AS$12 -> 0 | I25: =Input!$AT$12 -> 0 | J25: =Input!$AU$12 -> 0 | K25: =Input!$AV$12 -> 0 | L25: =SUM(F25:K25) -> 0 | O25: Difference | AB25: =SUM(C25:L25) -> 0
B26: Medical Sciences | F26: =Input!$AW$12 -> 114954760 | G26: =Input!$AX$12 -> 16759332 | H26: =Input!$AY$12 -> 25206484 | I26: =Input!$AZ$12 -> 10452891 | J26: =Input!$BA$12 -> 8712860 | K26: =Input!$BB$12 -> 23432271 | L26: =SUM(F26:K26) -> 199518598 | N26: =IF(O26<>0,"Out of Balance","Balanced") -> Balanced | O26: =L17-L41 -> 0
B27: Physical Sciences | F27: =Input!$BC$12 -> 0 | G27: =Input!$BD$12 -> 0 | H27: =Input!$BE$12 -> 0 | I27: =Input!$BF$12 -> 0 | J27: =Input!$BG$12 -> 0 | K27: =Input!$BH$12 -> 0 | L27: =SUM(F27:K27) -> 0
B28: Psychology | F28: =Input!$BI$12 -> 0 | G28: =Input!$BJ$12 -> 0 | H28: =Input!$BK$12 -> 0 | I28: =Input!$BL$12 -> 0 | J28: =Input!$BM$12 -> 0 | K28: =Input!$BN$12 -> 0 | L28: =SUM(F28:K28) -> 0
B29: Social Sciences | F29: =Input!$BO$12 -> 0 | G29: =Input!$BP$12 -> 0 | H29: =Input!$BQ$12 -> 0 | I29: =Input!$BR$12 -> 0 | J29: =Input!$BS$12 -> 0 | K29: =Input!$BT$12 -> 0 | L29: =SUM(F29:K29) -> 0
B30: Other Sciences not classified above | F30: =Input!$BU$12 -> 0 | G30: =Input!$BV$12 -> 0 | H30: =Input!$BW$12 -> 0 | I30: =Input!$BX$12 -> 0 | J30: =Input!$BY$12 -> 0 | K30: =Input!$BZ$12 -> 0 | L30: =SUM(F30:K30) -> 0
B31: Arts and Humanities | F31: =Input!$CA$12 -> 0 | G31: =Input!$CB$12 -> 0 | H31: =Input!$CC$12 -> 0 | I31: =Input!$CD$12 -> 0 | J31: =Input!$CE$12 -> 0 | K31: =Input!$CF$12 -> 0 | L31: =SUM(F31:K31) -> 0
B32: Business Administration | F32: =Input!$CG$12 -> 0 | G32: =Input!$CH$12 -> 0 | H32: =Input!$CI$12 -> 0 | I32: =Input!$CJ$12 -> 0 | J32: =Input!$CK$12 -> 0 | K32: =Input!$CL$12 -> 0 | L32: =SUM(F32:K32) -> 0
B33: Education | F33: =Input!$CM$12 -> 0 | G33: =Input!$CN$12 -> 0 | H33: =Input!$CO$12 -> 0 | I33: =Input!$CP$12 -> 0 | J33: =Input!$CQ$12 -> 0 | K33: =Input!$CR$12 -> 0 | L33: =SUM(F33:K33) -> 0
B34: Law | F34: =Input!$CS$12 -> 0 | G34: =Input!$CT$12 -> 0 | H34: =Input!$CU$12 -> 0 | I34: =Input!$CV$12 -> 0 | J34: =Input!$CW$12 -> 0 | K34: =Input!$CX$12 -> 0 | L34: =SUM(F34:K34) -> 0
B35: Field of Study - Future Use 1 | F35: =Input!$CY$12 -> 0 | G35: =Input!$CZ$12 -> 0 | H35: =Input!$DA$12 -> 0 | I35: =Input!$DB$12 -> 0 | J35: =Input!$DC$12 -> 0 | K35: =Input!$DD$12 -> 0 | L35: =SUM(F35:K35) -> 0
B36: Field of Study - Future Use 2 | F36: =Input!$DE$12 -> 0 | G36: =Input!$DF$12 -> 0 | H36: =Input!$DG$12 -> 0 | I36: =Input!$DH$12 -> 0 | J36: =Input!$DI$12 -> 0 | K36: =Input!$DJ$12 -> 0 | L36: =SUM(F36:K36) -> 0
B37: Field of Study - Future Use 3 | F37: =Input!$DK$12 -> 0 | G37: =Input!$DL$12 -> 0 | H37: =Input!$DM$12 -> 0 | I37: =Input!$DN$12 -> 0 | J37: =Input!$DO$12 -> 0 | K37: =Input!$DP$12 -> 0 | L37: =SUM(F37:K37) -> 0
B38: Field of Study - Future Use 4 | F38: =Input!$DQ$12 -> 0 | G38: =Input!$DR$12 -> 0 | H38: =Input!$DS$12 -> 0 | I38: =Input!$DT$12 -> 0 | J38: =Input!$DU$12 -> 0 | K38: =Input!$DV$12 -> 0 | L38: =SUM(F38:K38) -> 0
B39: Field of Study - Future Use 5 | F39: =Input!$DW$12 -> 0 | G39: =Input!$DX$12 -> 0 | H39: =Input!$DY$12 -> 0 | I39: =Input!$DZ$12 -> 0 | J39: =Input!$EA$12 -> 0 | K39: =Input!$EB$12 -> 0 | L39: =SUM(F39:K39) -> 0
B40: Other Non-Science Activities | F40: =Input!$EC$12 -> 0 | G40: =Input!$ED$12 -> 0 | H40: =Input!$EE$12 -> 0 | I40: =Input!$EF$12 -> 0 | J40: =Input!$EG$12 -> 0 | K40: =Input!$EH$12 -> 0 | L40: =SUM(F40:K40) -> 0 | O40: To Accountability | P40: Sources & Uses | AB40: =SUM(C40:L40) -> 0
B41: Total R & D Expenditures By Funding Source | F41: =SUM(F20:F40) -> 150323653 | G41: =SUM(G20:G40) -> 17922267 | H41: =SUM(H20:H40) -> 25594744 | I41: =SUM(I20:I40) -> 11579402 | J41: =SUM(J20:J40) -> 9112235 | K41: =SUM(K20:K40) -> 26240251 | L41: =SUM(L20:L40) -> 240772552 | O41: ResPercGenRev | P41: State Appropriations | S41: =L41-INT(L41) -> 0 | AB41: =SUM(AB20:AB40) -> 82507908
G42: State Total | H42: =H41+G41 -> 43517011 | J42: Pvt. Total | K42: =K41+J41 -> 35352486 | L42: Federal & Private | N42: =K42+F41 -> 185676139 | O42: =ROUND((N42/P42)*100,2) -> 158.08 | P42: =Input!$GR$12 -> 117456319 | Z42: =IF(Z41<>0,"Out of Balance","")
B43: R & D Expenditures - Select Areas of Special Interest | O43: ExpendPerFTE
B44: Aging | F44: =Input!$EI$12 -> 608411 | G44: =Input!$EJ$12 -> 0 | H44: =Input!$EK$12 -> 0 | I44: =Input!$EL$12 -> 0 | J44: =Input!$EM$12 -> 0 | K44: =Input!$EN$12 -> 24062 | L44: =SUM(F44:K44) -> 632473 | O44: =ROUND(N42/O46,0) -> 676687 | AB44: =SUM(C44:L44) -> 1264946
B45: Cancer Research | F45: =Input!$EO$12 -> 6646285 | G45: =Input!$EP$12 -> 0 | H45: =Input!$EQ$12 -> 369604 | I45: =Input!$ER$12 -> 0 | J45: =Input!$ES$12 -> 3338 | K45: =Input!$ET$12 -> 559101 | L45: =SUM(F45:K45) -> 7578328 | O45: T/TT Fall Fac FTE
B46: Cardiovascular Research | F46: =Input!$EU$12 -> 13576432 | G46: =Input!$EV$12 -> 1259657 | H46: =Input!$EW$12 -> 0 | I46: =Input!$EX$12 -> 74990 | J46: =Input!$EY$12 -> 153349 | K46: =Input!$EZ$12 -> 2782673 | L46: =SUM(F46:K46) -> 17847101 | O46: =FTSE!$O$15 -> 274.39
B47: Child Health and Human Development | F47: =Input!$FA$12 -> 8274088 | G47: =Input!$FB$12 -> 1849578 | H47: =Input!$FC$12 -> 4850362 | I47: =Input!$FD$12 -> 15262 | J47: =Input!$FE$12 -> 186302 | K47: =Input!$FF$12 -> 1617912 | L47: =SUM(F47:K47) -> 16793504 | O47: As of Fall xxxxx
B48: Mental Health | F48: =Input!$FG$12 -> 2759354 | G48: =Input!$FH$12 -> 6408 | H48: =Input!$FI$12 -> 29881 | I48: =Input!$FJ$12 -> 0 | J48: =Input!$FK$12 -> 273037 | K48: =Input!$FL$12 -> 55167 | L48: =SUM(F48:K48) -> 3123847
B49: HRI Special Interest - Future Use 1 | F49: =Input!$FM$12 -> 0 | G49: =Input!$FN$12 -> 0 | H49: =Input!$FO$12 -> 0 | I49: =Input!$FP$12 -> 0 | J49: =Input!$FQ$12 -> 0 | K49: =Input!$FR$12 -> 0 | L49: =SUM(F49:K49) -> 0
B50: HRI Special Interest - Future Use 2 | F50: =Input!$FS$12 -> 0 | G50: =Input!$FT$12 -> 0 | H50: =Input!$FU$12 -> 0 | I50: =Input!$FV$12 -> 0 | J50: =Input!$FW$12 -> 0 | K50: =Input!$FX$12 -> 0 | L50: =SUM(F50:K50) -> 0
B51: HRI Special Interest - Future Use 3 | F51: =Input!$FY$12 -> 0 | G51: =Input!$FZ$12 -> 0 | H51: =Input!$GA$12 -> 0 | I51: =Input!$GB$12 -> 0 | J51: =Input!$GC$12 -> 0 | K51: =Input!$GD$12 -> 0 | L51: =SUM(F51:K51) -> 0
B52: HRI Special Interest - Future Use 4 | F52: =Input!$GE$12 -> 0 | G52: =Input!$GF$12 -> 0 | H52: =Input!$GG$12 -> 0 | I52: =Input!$GH$12 -> 0 | J52: =Input!$GI$12 -> 0 | K52: =Input!$GJ$12 -> 0 | L52: =SUM(F52:K52) -> 0
B53: HRI Special Interest - Future Use 5 | F53: =Input!$GK$12 -> 0 | G53: =Input!$GL$12 -> 0 | H53: =Input!$GM$12 -> 0 | I53: =Input!$GN$12 -> 0 | J53: =Input!$GO$12 -> 0 | K53: =Input!$GP$12 -> 0 | L53: =SUM(F53:K53) -> 0
B54: Total R & D Expenditures - Select Areas of Special Interest | F54: =SUM(F44:F53) -> 31864570 | G54: =SUM(G44:G53) -> 3115643 | H54: =SUM(H44:H53) -> 5249847 | I54: =SUM(I44:I53) -> 90252 | J54: =SUM(J44:J53) -> 616026 | K54: =SUM(K44:K53) -> 5038915 | L54: =SUM(L44:L53) -> 45975253 | S54: =L54-INT(L54) -> 0 | AB54: =SUM(AB44:AB48) -> 1264946
F61: =F54+F41 -> 182188223 | G61: =G54+G41 -> 21037910 | H61: =H54+H41 -> 30844591 | I61: =I54+I41 -> 11669654 | J61: =J54+J41 -> 9728261 | K61: =K54+K41 -> 31279166 | L61: =L54+L41 -> 286747805
L62: =SUM(K8:K9)+SUM(K12:K16) -> 240772552
L63: =SUM(L61:L62) -> 527520357
L65: =IF($L$63+L64<>Input!$D$12,"Error","Balanced") -> Balanced

Sheet HSSA
B1: The University of Texas Health Science Center at San Antonio | N1: Return to Index | AA1: 12 | AB1: 13
B2: =Input!$B$5 -> For the Year Ended August 31, 2010
B3: =Input!$B$6 -> Source: FY 2010 Research Expenditure Survey
N4: Zoom % should be at 75%.
B6: =Input!$B$7 -> FY 2010
B7: Summary of R & D Expenditures | K7: Overall Total | L7: Defined For Survey
B8: R & D Expenses as defined for the Research Expenditure Survey | K8: =L8 -> 145165310 | L8: =Input!$H$13 -> 145165310 | AB8: =SUM(C8:L8) -> 290330620
B9: R & D Expenses not meeting the narrow definition of R & D used in the Research Expenditures Survey | K9: =Input!$F$13 -> 0 | AB9: =SUM(C9:L9) -> 0
B10: Total Expenses for R & D as reported on the Statement of Revenues, Expenses and Changes in Net Assets | H10: =IF(O10<>0,"Out of Balance with SRECNA","") | K10: =SUM(K8:K9) -> 145165310
AB11: =SUM(C10:L10) -> 145165310
B12: Other Research-related Equipment Expenditures (noncurrent fund expenditures, etc. - do not include R & D plant expenses or construction) | K12: =Input!$G$13 -> 0 | AB12: =SUM(C11:L11) -> 0
B13: Indirect Costs associated with Expenses for R & D as defined for this survey | K13: =L13 -> 33528292 | L13: =Input!$I$13 -> 33528292 | AB13: =SUM(C13:L13) -> 67056584
B14: Capital Outlay for research equipment (do not include R & D plant expenses or construction) | K14: =L14 -> 6535416 | L14: =Input!$J$13 -> 6535416 | AB14: =SUM(C14:L14) -> 13070832
B15: Expenditures for conduct of R & D made by institution's research foundation or 501© corporation on behalf of the institution and not report in institution AFR, including indirect costs not reported above | K15: =L15 -> 0 | L15: =Input!$K$13 -> 0 | AB15: =SUM(C15:L15) -> 0
B16: Pass-throughs from Texas Engineering Experiment Station not reported in R & D Expenditures as defined for the Research Expenditure Survey | K16: =L16 -> 0 | L16: =Input!$L$13 -> 0 | AB16: =SUM(C16:L16) -> 0
B17: Total R & D Expenditures | K17: =SUM(K10:K16) -> 185229018 | L17: =SUM(L8:L16) -> 185229018 | S17: =L17-INT(L17) -> 0 | T17: 0 | U17: 0 | V17: 0 | AB17: =#REF!+#REF!+#REF!+#REF! -> #REF!
F18: =IF(OR(S17<>0,S41<>0,S54<>0),"Do not Enter Cents - Whole Dollars Only","")
B19: R & D Expenditures By Funding Source | F19: Federal | G19: State Appropriations | H19: State Contracts/Grants | I19: Institution Resources | J19: Private For-Profit | K19: Private Non-Profit | L19: Total
B20: Agricultural Sciences | F20: =Input!$M$13 -> 0 | G20: =Input!$N$13 -> 0 | H20: =Input!$O$13 -> 0 | I20: =Input!$P$13 -> 0 | J20: =Input!$Q$13 -> 0 | K20: =Input!$R$13 -> 0 | L20: =SUM(F20:K20) -> 0 | AB20: =SUM(C20:L20) -> 0
B21: Biological and Other Life Sciences | F21: =Input!$S$13 -> 0 | G21: =Input!$T$13 -> 0 | H21: =Input!$U$13 -> 0 | I21: =Input!$V$13 -> 0 | J21: =Input!$W$13 -> 0 | K21: =Input!$X$13 -> 0 | L21: =SUM(F21:K21) -> 0 | AB21: =SUM(C21:L21) -> 0
B22: Computer Science | F22: =Input!$Y$13 -> 0 | G22: =Input!$Z$13 -> 0 | H22: =Input!$AA$13 -> 0 | I22: =Input!$AB$13 -> 0 | J22: =Input!$AC$13 -> 0 | K22: =Input!$AD$13 -> 0 | L22: =SUM(F22:K22) -> 0 | AB22: =SUM(C22:L22) -> 0
B23: Engineering | F23: =Input!$AE$13 -> 0 | G23: =Input!$AF$13 -> 0 | H23: =Input!$AG$13 -> 0 | I23: =Input!$AH$13 -> 0 | J23: =Input!$AI$13 -> 0 | K23: =Input!$AJ$13 -> 0 | L23: =SUM(F23:K23) -> 0 | AB23: =SUM(C23:L23) -> 0
B24: Environmental Sciences | F24: =Input!$AK$13 -> 0 | G24: =Input!$AL$13 -> 0 | H24: =Input!$AM$13 -> 0 | I24: =Input!$AN$13 -> 0 | J24: =Input!$AO$13 -> 0 | K24: =Input!$AP$13 -> 0 | L24: =SUM(F24:K24) -> 0 | AB24: =SUM(C24:L24) -> 0
B25: Mathematical Sciences | F25: =Input!$AQ$13 -> 0 | G25: =Input!$AR$13 -> 0 | H25: =Input!$AS$13 -> 0 | I25: =Input!$AT$13 -> 0 | J25: =Input!$AU$13 -> 0 | K25: =Input!$AV$13 -> 0 | L25: =SUM(F25:K25) -> 0 | O25: Difference | AB25: =SUM(C25:L25) -> 0
B26: Medical Sciences | F26: =Input!$AW$13 -> 121723410 | G26: =Input!$AX$13 -> 6240743 | H26: =Input!$AY$13 -> 708627 | I26: =Input!$AZ$13 -> 20876076 | J26: =Input!$BA$13 -> 22353048 | K26: =Input!$BB$13 -> 13327114 | L26: =SUM(F26:K26) -> 185229018 | N26: =IF(O26<>0,"Out of Balance","Balanced") -> Balanced | O26: =L17-L41 -> 0
B27: Physical Sciences | F27: =Input!$BC$13 -> 0 | G27: =Input!$BD$13 -> 0 | H27: =Input!$BE$13 -> 0 | I27: =Input!$BF$13 -> 0 | J27: =Input!$BG$13 -> 0 | K27: =Input!$BH$13 -> 0 | L27: =SUM(F27:K27) -> 0
B28: Psychology | F28: =Input!$BI$13 -> 0 | G28: =Input!$BJ$13 -> 0 | H28: =Input!$BK$13 -> 0 | I28: =Input!$BL$13 -> 0 | J28: =Input!$BM$13 -> 0 | K28: =Input!$BN$13 -> 0 | L28: =SUM(F28:K28) -> 0
B29: Social Sciences | F29: =Input!$BO$13 -> 0 | G29: =Input!$BP$13 -> 0 | H29: =Input!$BQ$13 -> 0 | I29: =Input!$BR$13 -> 0 | J29: =Input!$BS$13 -> 0 | K29: =Input!$BT$13 -> 0 | L29: =SUM(F29:K29) -> 0
B30: Other Sciences not classified above | F30: =Input!$BU$13 -> 0 | G30: =Input!$BV$13 -> 0 | H30: =Input!$BW$13 -> 0 | I30: =Input!$BX$13 -> 0 | J30: =Input!$BY$13 -> 0 | K30: =Input!$BZ$13 -> 0 | L30: =SUM(F30:K30) -> 0
B31: Arts and Humanities | F31: =Input!$CA$13 -> 0 | G31: =Input!$CB$13 -> 0 | H31: =Input!$CC$13 -> 0 | I31: =Input!$CD$13 -> 0 | J31: =Input!$CE$13 -> 0 | K31: =Input!$CF$13 -> 0 | L31: =SUM(F31:K31) -> 0
B32: Business Administration | F32: =Input!$CG$13 -> 0 | G32: =Input!$CH$13 -> 0 | H32: =Input!$CI$13 -> 0 | I32: =Input!$CJ$13 -> 0 | J32: =Input!$CK$13 -> 0 | K32: =Input!$CL$13 -> 0 | L32: =SUM(F32:K32) -> 0
B33: Education | F33: =Input!$CM$13 -> 0 | G33: =Input!$CN$13 -> 0 | H33: =Input!$CO$13 -> 0 | I33: =Input!$CP$13 -> 0 | J33: =Input!$CQ$13 -> 0 | K33: =Input!$CR$13 -> 0 | L33: =SUM(F33:K33) -> 0
B34: Law | F34: =Input!$CS$13 -> 0 | G34: =Input!$CT$13 -> 0 | H34: =Input!$CU$13 -> 0 | I34: =Input!$CV$13 -> 0 | J34: =Input!$CW$13 -> 0 | K34: =Input!$CX$13 -> 0 | L34: =SUM(F34:K34) -> 0
B35: Field of Study - Future Use 1 | F35: =Input!$CY$13 -> 0 | G35: =Input!$CZ$13 -> 0 | H35: =Input!$DA$13 -> 0 | I35: =Input!$DB$13 -> 0 | J35: =Input!$DC$13 -> 0 | K35: =Input!$DD$13 -> 0 | L35: =SUM(F35:K35) -> 0
B36: Field of Study - Future Use 2 | F36: =Input!$DE$13 -> 0 | G36: =Input!$DF$13 -> 0 | H36: =Input!$DG$13 -> 0 | I36: =Input!$DH$13 -> 0 | J36: =Input!$DI$13 -> 0 | K36: =Input!$DJ$13 -> 0 | L36: =SUM(F36:K36) -> 0
B37: Field of Study - Future Use 3 | F37: =Input!$DK$13 -> 0 | G37: =Input!$DL$13 -> 0 | H37: =Input!$DM$13 -> 0 | I37: =Input!$DN$13 -> 0 | J37: =Input!$DO$13 -> 0 | K37: =Input!$DP$13 -> 0 | L37: =SUM(F37:K37) -> 0
B38: Field of Study - Future Use 4 | F38: =Input!$DQ$13 -> 0 | G38: =Input!$DR$13 -> 0 | H38: =Input!$DS$13 -> 0 | I38: =Input!$DT$13 -> 0 | J38: =Input!$DU$13 -> 0 | K38: =Input!$DV$13 -> 0 | L38: =SUM(F38:K38) -> 0
B39: Field of Study - Future Use 5 | F39: =Input!$DW$13 -> 0 | G39: =Input!$DX$13 -> 0 | H39: =Input!$DY$13 -> 0 | I39: =Input!$DZ$13 -> 0 | J39: =Input!$EA$13 -> 0 | K39: =Input!$EB$13 -> 0 | L39: =SUM(F39:K39) -> 0
B40: Other Non-Science Activities | F40: =Input!$EC$13 -> 0 | G40: =Input!$ED$13 -> 0 | H40: =Input!$EE$13 -> 0 | I40: =Input!$EF$13 -> 0 | J40: =Input!$EG$13 -> 0 | K40: =Input!$EH$13 -> 0 | L40: =SUM(F40:K40) -> 0 | O40: To Accountability | P40: Sources & Uses | AB40: =SUM(C40:L40) -> 0
B41: Total R & D Expenditures By Funding Source | F41: =SUM(F20:F40) -> 121723410 | G41: =SUM(G20:G40) -> 6240743 | H41: =SUM(H20:H40) -> 708627 | I41: =SUM(I20:I40) -> 20876076 | J41: =SUM(J20:J40) -> 22353048 | K41: =SUM(K20:K40) -> 13327114 | L41: =SUM(L20:L40) -> 185229018 | O41: ResPercGenRev | P41: State Appropriations | S41: =L41-INT(L41) -> 0 | AB41: =SUM(AB20:AB40) -> 0
G42: State Total | H42: =H41+G41 -> 6949370 | J42: Pvt. Total | K42: =K41+J41 -> 35680162 | L42: Federal & Private | N42: =K42+F41 -> 157403572 | O42: =ROUND((N42/P42)*100,2) -> 235.5 | P42: =Input!$GR$13 -> 66838749 | Z42: =IF(Z41<>0,"Out of Balance","")
B43: R & D Expenditures - Select Areas of Special Interest | O43: ExpendPerFTE
B44: Aging | F44: =Input!$EI$13 -> 20440616 | G44: =Input!$EJ$13 -> 74736 | H44: =Input!$EK$13 -> 388019 | I44: =Input!$EL$13 -> 57450 | J44: =Input!$EM$13 -> 2063641 | K44: =Input!$EN$13 -> 2454936 | L44: =SUM(F44:K44) -> 25479398 | O44: =ROUND(N42/O46,0) -> 476980521 | AB44: =SUM(C44:L44) -> 50958796
B45: Cancer Research | F45: =Input!$EO$13 -> 22013135 | G45: =Input!$EP$13 -> 85619 | H45: =Input!$EQ$13 -> 14784 | I45: =Input!$ER$13 -> 9086254 | J45: =Input!$ES$13 -> 8881781 | K45: =Input!$ET$13 -> 1932546 | L45: =SUM(F45:K45) -> 42014119 | O45: T/TT Fall Fac FTE
B46: Cardiovascular Research | F46: =Input!$EU$13 -> 12310269 | G46: =Input!$EV$13 -> 22949 | H46: =Input!$EW$13 -> 0 | I46: =Input!$EX$13 -> 55092 | J46: =Input!$EY$13 -> 728720 | K46: =Input!$EZ$13 -> 1694519 | L46: =SUM(F46:K46) -> 14811549 | O46: =FTSE!$O$24 -> 0.33
B47: Child Health and Human Development | F47: =Input!$FA$13 -> 13948080 | G47: =Input!$FB$13 -> 10443 | H47: =Input!$FC$13 -> 132833 | I47: =Input!$FD$13 -> 8402333 | J47: =Input!$FE$13 -> 995968 | K47: =Input!$FF$13 -> 1909613 | L47: =SUM(F47:K47) -> 25399270 | O47: As of Fall xxxxx
B48: Mental Health | F48: =Input!$FG$13 -> 20708771 | G48: =Input!$FH$13 -> 0 | H48: =Input!$FI$13 -> 388019 | I48: =Input!$FJ$13 -> 0 | J48: =Input!$FK$13 -> 1286588 | K48: =Input!$FL$13 -> 174526 | L48: =SUM(F48:K48) -> 22557904
B49: HRI Special Interest - Future Use 1 | F49: =Input!$FM$13 -> 0 | G49: =Input!$FN$13 -> 0 | H49: =Input!$FO$13 -> 0 | I49: =Input!$FP$13 -> 0 | J49: =Input!$FQ$13 -> 0 | K49: =Input!$FR$13 -> 0 | L49: =SUM(F49:K49) -> 0
B50: HRI Special Interest - Future Use 2 | F50: =Input!$FS$13 -> 0 | G50: =Input!$FT$13 -> 0 | H50: =Input!$FU$13 -> 0 | I50: =Input!$FV$13 -> 0 | J50: =Input!$FW$13 -> 0 | K50: =Input!$FX$13 -> 0 | L50: =SUM(F50:K50) -> 0
B51: HRI Special Interest - Future Use 3 | F51: =Input!$FY$13 -> 0 | G51: =Input!$FZ$13 -> 0 | H51: =Input!$GA$13 -> 0 | I51: =Input!$GB$13 -> 0 | J51: =Input!$GC$13 -> 0 | K51: =Input!$GD$13 -> 0 | L51: =SUM(F51:K51) -> 0
B52: HRI Special Interest - Future Use 4 | F52: =Input!$GE$13 -> 0 | G52: =Input!$GF$13 -> 0 | H52: =Input!$GG$13 -> 0 | I52: =Input!$GH$13 -> 0 | J52: =Input!$GI$13 -> 0 | K52: =Input!$GJ$13 -> 0 | L52: =SUM(F52:K52) -> 0
B53: HRI Special Interest - Future Use 5 | F53: =Input!$GK$13 -> 0 | G53: =Input!$GL$13 -> 0 | H53: =Input!$GM$13 -> 0 | I53: =Input!$GN$13 -> 0 | J53: =Input!$GO$13 -> 0 | K53: =Input!$GP$13 -> 0 | L53: =SUM(F53:K53) -> 0
B54: Total R & D Expenditures - Select Areas of Special Interest | F54: =SUM(F44:F53) -> 89420871 | G54: =SUM(G44:G53) -> 193747 | H54: =SUM(H44:H53) -> 923655 | I54: =SUM(I44:I53) -> 17601129 | J54: =SUM(J44:J53) -> 13956698 | K54: =SUM(K44:K53) -> 8166140 | L54: =SUM(L44:L53) -> 130262240 | S54: =L54-INT(L54) -> 0 | AB54: =SUM(AB44:AB48) -> 50958796
F61: =F54+F41 -> 211144281 | G61: =G54+G41 -> 6434490 | H61: =H54+H41 -> 1632282 | I61: =I54+I41 -> 38477205 | J61: =J54+J41 -> 36309746 | K61: =K54+K41 -> 21493254 | L61: =L54+L41 -> 315491258
L62: =SUM(K8:K9)+SUM(K12:K16) -> 185229018
L63: =SUM(L61:L62) -> 500720276
L65: =IF($L$63+L64<>Input!$D$13,"Error","Balanced") -> Balanced

Sheet MDA
B1: The University of Texas M.D. Anderson Cancer Center | N1: Return to Index | AA1: 12 | AB1: 13
B2: =Input!$B$5 -> For the Year Ended August 31, 2010
B3: =Input!$B$6 -> Source: FY 2010 Research Expenditure Survey
N4: Zoom % should be at 75%.
B6: =Input!$B$7 -> FY 2010
B7: Summary of R & D Expenditures | K7: Overall Total | L7: Defined For Survey
B8: R & D Expenses as defined for the Research Expenditure Survey | K8: =L8 -> 463104671 | L8: =Input!$H$14 -> 463104671 | AB8: =SUM(C8:L8) -> 926209342
B9: R & D Expenses not meeting the narrow definition of R & D used in the Research Expenditures Survey | K9: =Input!$F$14 -> 0 | AB9: =SUM(C9:L9) -> 0
B10: Total Expenses for R & D as reported on the Statement of Revenues, Expenses and Changes in Net Assets | H10: =IF(O10<>0,"Out of Balance with SRECNA","") | K10: =SUM(K8:K9) -> 463104671
AB11: =SUM(C10:L10) -> 463104671
B12: Other Research-related Equipment Expenditures (noncurrent fund expenditures, etc. - do not include R & D plant expenses or construction) | K12: =Input!$G$14 -> 0 | AB12: =SUM(C11:L11) -> 0
B13: Indirect Costs associated with Expenses for R & D as defined for this survey | K13: =L13 -> 75631023 | L13: =Input!$I$14 -> 75631023 | AB13: =SUM(C13:L13) -> 151262046
B14: Capital Outlay for research equipment (do not include R & D plant expenses or construction) | K14: =L14 -> 8299050 | L14: =Input!$J$14 -> 8299050 | AB14: =SUM(C14:L14) -> 16598100
B15: Expenditures for conduct of R & D made by institution's research foundation or 501© corporation on behalf of the institution and not report in institution AFR, including indirect costs not reported above | K15: =L15 -> 0 | L15: =Input!$K$14 -> 0 | AB15: =SUM(C15:L15) -> 0
B16: Pass-throughs from Texas Engineering Experiment Station not reported in R & D Expenditures as defined for the Research Expenditure Survey | K16: =L16 -> 0 | L16: =Input!$L$14 -> 0 | AB16: =SUM(C16:L16) -> 0
B17: Total R & D Expenditures | K17: =SUM(K10:K16) -> 547034744 | L17: =SUM(L8:L16) -> 547034744 | S17: =L17-INT(L17) -> 0 | T17: 0 | U17: 0 | V17: 0 | AB17: =#REF!+#REF!+#REF!+#REF! -> #REF!
F18: =IF(OR(S17<>0,S41<>0,S54<>0),"Do not Enter Cents - Whole Dollars Only","")
B19: R & D Expenditures By Funding Source | F19: Federal | G19: State Appropriations | H19: State Contracts/Grants | I19: Institution Resources | J19: Private For-Profit | K19: Private Non-Profit | L19: Total
B20: Agricultural Sciences | F20: =Input!$M$14 -> 0 | G20: =Input!$N$14 -> 0 | H20: =Input!$O$14 -> 0 | I20: =Input!$P$14 -> 0 | J20: =Input!$Q$14 -> 0 | K20: =Input!$R$14 -> 0 | L20: =SUM(F20:K20) -> 0 | AB20: =SUM(C20:L20) -> 0
B21: Biological and Other Life Sciences | F21: =Input!$S$14 -> 65655783 | G21: =Input!$T$14 -> 65613402 | H21: =Input!$U$14 -> 217616 | I21: =Input!$V$14 -> 7409082 | J21: =Input!$W$14 -> 4646129 | K21: =Input!$X$14 -> 20725473 | L21: =SUM(F21:K21) -> 164267485 | AB21: =SUM(C21:L21) -> 328534970
B22: Computer Science | F22: =Input!$Y$14 -> 0 | G22: =Input!$Z$14 -> 0 | H22: =Input!$AA$14 -> 0 | I22: =Input!$AB$14 -> 0 | J22: =Input!$AC$14 -> 0 | K22: =Input!$AD$14 -> 0 | L22: =SUM(F22:K22) -> 0 | AB22: =SUM(C22:L22) -> 0
B23: Engineering | F23: =Input!$AE$14 -> 0 | G23: =Input!$AF$14 -> 0 | H23: =Input!$AG$14 -> 0 | I23: =Input!$AH$14 -> 0 | J23: =Input!$AI$14 -> 0 | K23: =Input!$AJ$14 -> 0 | L23: =SUM(F23:K23) -> 0 | AB23: =SUM(C23:L23) -> 0
B24: Environmental Sciences | F24: =Input!$AK$14 -> 0 | G24: =Input!$AL$14 -> 0 | H24: =Input!$AM$14 -> 0 | I24: =Input!$AN$14 -> 0 | J24: =Input!$AO$14 -> 0 | K24: =Input!$AP$14 -> 0 | L24: =SUM(F24:K24) -> 0 | AB24: =SUM(C24:L24) -> 0
B25: Mathematical Sciences | F25: =Input!$AQ$14 -> 5614173 | G25: =Input!$AR$14 -> 13409038 | H25: =Input!$AS$14 -> 0 | I25: =Input!$AT$14 -> 355017 | J25: =Input!$AU$14 -> 59418 | K25: =Input!$AV$14 -> 396902 | L25: =SUM(F25:K25) -> 19834548 | O25: Difference | AB25: =SUM(C25:L25) -> 39669096
B26: Medical Sciences | F26: =Input!$AW$14 -> 114729585 | G26: =Input!$AX$14 -> 86116417 | H26: =Input!$AY$14 -> 62296 | I26: =Input!$AZ$14 -> 18723770 | J26: =Input!$BA$14 -> 44912739 | K26: =Input!$BB$14 -> 58303336 | L26: =SUM(F26:K26) -> 322848143 | N26: =IF(O26<>0,"Out of Balance","Balanced") -> Balanced | O26: =L17-L41 -> 0
B27: Physical Sciences | F27: =Input!$BC$14 -> 7389134 | G27: =Input!$BD$14 -> 3855001 | H27: =Input!$BE$14 -> 64055 | I27: =Input!$BF$14 -> 871307 | J27: =Input!$BG$14 -> 752820 | K27: =Input!$BH$14 -> 97414 | L27: =SUM(F27:K27) -> 13029731
B28: Psychology | F28: =Input!$BI$14 -> 6777540 | G28: =Input!$BJ$14 -> 5125903 | H28: =Input!$BK$14 -> 0 | I28: =Input!$BL$14 -> 2875185 | J28: =Input!$BM$14 -> 341015 | K28: =Input!$BN$14 -> 1299904 | L28: =SUM(F28:K28) -> 16419547
B29: Social Sciences | F29: =Input!$BO$14 -> 6498232 | G29: =Input!$BP$14 -> 2342001 | H29: =Input!$BQ$14 -> 0 | I29: =Input!$BR$14 -> 961879 | J29: =Input!$BS$14 -> 0 | K29: =Input!$BT$14 -> 833178 | L29: =SUM(F29:K29) -> 10635290
B30: Other Sciences not classified above | F30: =Input!$BU$14 -> 0 | G30: =Input!$BV$14 -> 0 | H30: =Input!$BW$14 -> 0 | I30: =Input!$BX$14 -> 0 | J30: =Input!$BY$14 -> 0 | K30: =Input!$BZ$14 -> 0 | L30: =SUM(F30:K30) -> 0
B31: Arts and Humanities | F31: =Input!$CA$14 -> 0 | G31: =Input!$CB$14 -> 0 | H31: =Input!$CC$14 -> 0 | I31: =Input!$CD$14 -> 0 | J31: =Input!$CE$14 -> 0 | K31: =Input!$CF$14 -> 0 | L31: =SUM(F31:K31) -> 0
B32: Business Administration | F32: =Input!$CG$14 -> 0 | G32: =Input!$CH$14 -> 0 | H32: =Input!$CI$14 -> 0 | I32: =Input!$CJ$14 -> 0 | J32: =Input!$CK$14 -> 0 | K32: =Input!$CL$14 -> 0 | L32: =SUM(F32:K32) -> 0
B33: Education | F33: =Input!$CM$14 -> 0 | G33: =Input!$CN$14 -> 0 | H33: =Input!$CO$14 -> 0 | I33: =Input!$CP$14 -> 0 | J33: =Input!$CQ$14 -> 0 | K33: =Input!$CR$14 -> 0 | L33: =SUM(F33:K33) -> 0
B34: Law | F34: =Input!$CS$14 -> 0 | G34: =Input!$CT$14 -> 0 | H34: =Input!$CU$14 -> 0 | I34: =Input!$CV$14 -> 0 | J34: =Input!$CW$14 -> 0 | K34: =Input!$CX$14 -> 0 | L34: =SUM(F34:K34) -> 0
B35: Field of Study - Future Use 1 | F35: =Input!$CY$14 -> 0 | G35: =Input!$CZ$14 -> 0 | H35: =Input!$DA$14 -> 0 | I35: =Input!$DB$14 -> 0 | J35: =Input!$DC$14 -> 0 | K35: =Input!$DD$14 -> 0 | L35: =SUM(F35:K35) -> 0
B36: Field of Study - Future Use 2 | F36: =Input!$DE$14 -> 0 | G36: =Input!$DF$14 -> 0 | H36: =Input!$DG$14 -> 0 | I36: =Input!$DH$14 -> 0 | J36: =Input!$DI$14 -> 0 | K36: =Input!$DJ$14 -> 0 | L36: =SUM(F36:K36) -> 0
B37: Field of Study - Future Use 3 | F37: =Input!$DK$14 -> 0 | G37: =Input!$DL$14 -> 0 | H37: =Input!$DM$14 -> 0 | I37: =Input!$DN$14 -> 0 | J37: =Input!$DO$14 -> 0 | K37: =Input!$DP$14 -> 0 | L37: =SUM(F37:K37) -> 0
B38: Field of Study - Future Use 4 | F38: =Input!$DQ$14 -> 0 | G38: =Input!$DR$14 -> 0 | H38: =Input!$DS$14 -> 0 | I38: =Input!$DT$14 -> 0 | J38: =Input!$DU$14 -> 0 | K38: =Input!$DV$14 -> 0 | L38: =SUM(F38:K38) -> 0
B39: Field of Study - Future Use 5 | F39: =Input!$DW$14 -> 0 | G39: =Input!$DX$14 -> 0 | H39: =Input!$DY$14 -> 0 | I39: =Input!$DZ$14 -> 0 | J39: =Input!$EA$14 -> 0 | K39: =Input!$EB$14 -> 0 | L39: =SUM(F39:K39) -> 0
B40: Other Non-Science Activities | F40: =Input!$EC$14 -> 0 | G40: =Input!$ED$14 -> 0 | H40: =Input!$EE$14 -> 0 | I40: =Input!$EF$14 -> 0 | J40: =Input!$EG$14 -> 0 | K40: =Input!$EH$14 -> 0 | L40: =SUM(F40:K40) -> 0 | O40: To Accountability | P40: Sources & Uses | AB40: =SUM(C40:L40) -> 0
B41: Total R & D Expenditures By Funding Source | F41: =SUM(F20:F40) -> 206664447 | G41: =SUM(G20:G40) -> 176461762 | H41: =SUM(H20:H40) -> 343967 | I41: =SUM(I20:I40) -> 31196240 | J41: =SUM(J20:J40) -> 50712121 | K41: =SUM(K20:K40) -> 81656207 | L41: =SUM(L20:L40) -> 547034744 | O41: ResPercGenRev | P41: State Appropriations | S41: =L41-INT(L41) -> 0 | AB41: =SUM(AB20:AB40) -> 368204066
G42: State Total | H42: =H41+G41 -> 176805729 | J42: Pvt. Total | K42: =K41+J41 -> 132368328 | L42: Federal & Private | N42: =K42+F41 -> 339032775 | O42: =ROUND((N42/P42)*100,2) -> 769.99 | P42: =Input!$GR$14 -> 44031032 | Z42: =IF(Z41<>0,"Out of Balance","")
B43: R & D Expenditures - Select Areas of Special Interest | O43: ExpendPerFTE
B44: Aging | F44: =Input!$EI$14 -> 0 | G44: =Input!$EJ$14 -> 0 | H44: =Input!$EK$14 -> 0 | I44: =Input!$EL$14 -> 0 | J44: =Input!$EM$14 -> 0 | K44: =Input!$EN$14 -> 0 | L44: =SUM(F44:K44) -> 0 | O44: =ROUND(N42/O46,0) -> 832595 | AB44: =SUM(C44:L44) -> 0
B45: Cancer Research | F45: =Input!$EO$14 -> 206664447 | G45: =Input!$EP$14 -> 176461762 | H45: =Input!$EQ$14 -> 343967 | I45: =Input!$ER$14 -> 31196240 | J45: =Input!$ES$14 -> 50712121 | K45: =Input!$ET$14 -> 81656207 | L45: =SUM(F45:K45) -> 547034744 | O45: T/TT Fall Fac FTE
B46: Cardiovascular Research | F46: =Input!$EU$14 -> 0 | G46: =Input!$EV$14 -> 0 | H46: =Input!$EW$14 -> 0 | I46: =Input!$EX$14 -> 0 | J46: =Input!$EY$14 -> 0 | K46: =Input!$EZ$14 -> 0 | L46: =SUM(F46:K46) -> 0 | O46: =FTSE!$O$31 -> 407.2
B47: Child Health and Human Development | F47: =Input!$FA$14 -> 0 | G47: =Input!$FB$14 -> 0 | H47: =Input!$FC$14 -> 0 | I47: =Input!$FD$14 -> 0 | J47: =Input!$FE$14 -> 0 | K47: =Input!$FF$14 -> 0 | L47: =SUM(F47:K47) -> 0 | O47: As of Fall xxxxx
B48: Mental Health | F48: =Input!$FG$14 -> 0 | G48: =Input!$FH$14 -> 0 | H48: =Input!$FI$14 -> 0 | I48: =Input!$FJ$14 -> 0 | J48: =Input!$FK$14 -> 0 | K48: =Input!$FL$14 -> 0 | L48: =SUM(F48:K48) -> 0
B49: HRI Special Interest - Future Use 1 | F49: =Input!$FM$14 -> 0 | G49: =Input!$FN$14 -> 0 | H49: =Input!$FO$14 -> 0 | I49: =Input!$FP$14 -> 0 | J49: =Input!$FQ$14 -> 0 | K49: =Input!$FR$14 -> 0 | L49: =SUM(F49:K49) -> 0
B50: HRI Special Interest - Future Use 2 | F50: =Input!$FS$14 -> 0 | G50: =Input!$FT$14 -> 0 | H50: =Input!$FU$14 -> 0 | I50: =Input!$FV$14 -> 0 | J50: =Input!$FW$14 -> 0 | K50: =Input!$FX$14 -> 0 | L50: =SUM(F50:K50) -> 0
B51: HRI Special Interest - Future Use 3 | F51: =Input!$FY$14 -> 0 | G51: =Input!$FZ$14 -> 0 | H51: =Input!$GA$14 -> 0 | I51: =Input!$GB$14 -> 0 | J51: =Input!$GC$14 -> 0 | K51: =Input!$GD$14 -> 0 | L51: =SUM(F51:K51) -> 0
B52: HRI Special Interest - Future Use 4 | F52: =Input!$GE$14 -> 0 | G52: =Input!$GF$14 -> 0 | H52: =Input!$GG$14 -> 0 | I52: =Input!$GH$14 -> 0 | J52: =Input!$GI$14 -> 0 | K52: =Input!$GJ$14 -> 0 | L52: =SUM(F52:K52) -> 0
B53: HRI Special Interest - Future Use 5 | F53: =Input!$GK$14 -> 0 | G53: =Input!$GL$14 -> 0 | H53: =Input!$GM$14 -> 0 | I53: =Input!$GN$14 -> 0 | J53: =Input!$GO$14 -> 0 | K53: =Input!$GP$14 -> 0 | L53: =SUM(F53:K53) -> 0
B54: Total R & D Expenditures - Select Areas of Special Interest | F54: =SUM(F44:F53) -> 206664447 | G54: =SUM(G44:G53) -> 176461762 | H54: =SUM(H44:H53) -> 343967 | I54: =SUM(I44:I53) -> 31196240 | J54: =SUM(J44:J53) -> 50712121 | K54: =SUM(K44:K53) -> 81656207 | L54: =SUM(L44:L53) -> 547034744 | S54: =L54-INT(L54) -> 0 | AB54: =SUM(AB44:AB48) -> 0
F61: =F54+F41 -> 413328894 | G61: =G54+G41 -> 352923524 | H61: =H54+H41 -> 687934 | I61: =I54+I41 -> 62392480 | J61: =J54+J41 -> 101424242 | K61: =K54+K41 -> 163312414 | L61: =L54+L41 -> 1094069488
L62: =SUM(K8:K9)+SUM(K12:K16) -> 547034744
L63: =SUM(L61:L62) -> 1641104232
L65: =IF($L$63+L64<>Input!$D$14,"Error","Balanced") -> Balanced

Sheet THC
B1: The University of Texas Health Center at Tyler | N1: Return to Index | AA1: 12 | AB1: 13
B2: =Input!$B$5 -> For the Year Ended August 31, 2010
B3: =Input!$B$6 -> Source: FY 2010 Research Expenditure Survey
N4: Zoom % should be at 75%.
B6: =Input!$B$7 -> FY 2010
B7: Summary of R & D Expenditures | K7: Overall Total | L7: Defined For Survey
B8: R & D Expenses as defined for the Research Expenditure Survey | K8: =L8 -> 12168890 | L8: =Input!$H$15 -> 12168890 | AB8: =SUM(C8:L8) -> 24337780
B9: R & D Expenses not meeting the narrow definition of R & D used in the Research Expenditures Survey | K9: =Input!$F$15 -> 0 | AB9: =SUM(C9:L9) -> 0
B10: Total Expenses for R & D as reported on the Statement of Revenues, Expenses and Changes in Net Assets | H10: =IF(O10<>0,"Out of Balance with SRECNA","") | K10: =SUM(K8:K9) -> 12168890
AB11: =SUM(C10:L10) -> 12168890
B12: Other Research-related Equipment Expenditures (noncurrent fund expenditures, etc. - do not include R & D plant expenses or construction) | K12: =Input!$G$15 -> 0 | AB12: =SUM(C11:L11) -> 0
B13: Indirect Costs associated with Expenses for R & D as defined for this survey | K13: =L13 -> 1844206 | L13: =Input!$I$15 -> 1844206 | AB13: =SUM(C13:L13) -> 3688412
B14: Capital Outlay for research equipment (do not include R & D plant expenses or construction) | K14: =L14 -> 365036 | L14: =Input!$J$15 -> 365036 | AB14: =SUM(C14:L14) -> 730072
B15: Expenditures for conduct of R & D made by institution's research foundation or 501© corporation on behalf of the institution and not report in institution AFR, including indirect costs not reported above | K15: =L15 -> 0 | L15: =Input!$K$15 -> 0 | AB15: =SUM(C15:L15) -> 0
B16: Pass-throughs from Texas Engineering Experiment Station not reported in R & D Expenditures as defined for the Research Expenditure Survey | K16: =L16 -> 0 | L16: =Input!$L$15 -> 0 | AB16: =SUM(C16:L16) -> 0
B17: Total R & D Expenditures | K17: =SUM(K10:K16) -> 14378132 | L17: =SUM(L8:L16) -> 14378132 | S17: =L17-INT(L17) -> 0 | T17: 0 | U17: 0 | V17: 0 | AB17: =#REF!+#REF!+#REF!+#REF! -> #REF!
F18: =IF(OR(S17<>0,S41<>0,S54<>0),"Do not Enter Cents - Whole Dollars Only","")
B19: R & D Expenditures By Funding Source | F19: Federal | G19: State Appropriations | H19: State Contracts/Grants | I19: Institution Resources | J19: Private For-Profit | K19: Private Non-Profit | L19: Total
B20: Agricultural Sciences | F20: =Input!$M$15 -> 1299948 | G20: =Input!$N$15 -> 0 | H20: =Input!$O$15 -> 0 | I20: =Input!$P$15 -> 0 | J20: =Input!$Q$15 -> 0 | K20: =Input!$R$15 -> 0 | L20: =SUM(F20:K20) -> 1299948 | AB20: =SUM(C20:L20) -> 2599896
B21: Biological and Other Life Sciences | F21: =Input!$S$15 -> 0 | G21: =Input!$T$15 -> 0 | H21: =Input!$U$15 -> 0 | I21: =Input!$V$15 -> 0 | J21: =Input!$W$15 -> 0 | K21: =Input!$X$15 -> 0 | L21: =SUM(F21:K21) -> 0 | AB21: =SUM(C21:L21) -> 0
B22: Computer Science | F22: =Input!$Y$15 -> 0 | G22: =Input!$Z$15 -> 0 | H22: =Input!$AA$15 -> 0 | I22: =Input!$AB$15 -> 0 | J22: =Input!$AC$15 -> 0 | K22: =Input!$AD$15 -> 0 | L22: =SUM(F22:K22) -> 0 | AB22: =SUM(C22:L22) -> 0
B23: Engineering | F23: =Input!$AE$15 -> 0 | G23: =Input!$AF$15 -> 0 | H23: =Input!$AG$15 -> 0 | I23: =Input!$AH$15 -> 0 | J23: =Input!$AI$15 -> 0 | K23: =Input!$AJ$15 -> 0 | L23: =SUM(F23:K23) -> 0 | AB23: =SUM(C23:L23) -> 0
B24: Environmental Sciences | F24: =Input!$AK$15 -> 0 | G24: =Input!$AL$15 -> 0 | H24: =Input!$AM$15 -> 0 | I24: =Input!$AN$15 -> 0 | J24: =Input!$AO$15 -> 0 | K24: =Input!$AP$15 -> 0 | L24: =SUM(F24:K24) -> 0 | AB24: =SUM(C24:L24) -> 0
B25: Mathematical Sciences | F25: =Input!$AQ$15 -> 0 | G25: =Input!$AR$15 -> 0 | H25: =Input!$AS$15 -> 0 | I25: =Input!$AT$15 -> 0 | J25: =Input!$AU$15 -> 0 | K25: =Input!$AV$15 -> 0 | L25: =SUM(F25:K25) -> 0 | O25: Difference | AB25: =SUM(C25:L25) -> 0
B26: Medical Sciences | F26: =Input!$AW$15 -> 5950376 | G26: =Input!$AX$15 -> 2339810 | H26: =Input!$AY$15 -> 0 | I26: =Input!$AZ$15 -> 3239671 | J26: =Input!$BA$15 -> 505126 | K26: =Input!$BB$15 -> 1043201 | L26: =SUM(F26:K26) -> 13078184 | N26: =IF(O26<>0,"Out of Balance","Balanced") -> Balanced | O26: =L17-L41 -> 0
B27: Physical Sciences | F27: =Input!$BC$15 -> 0 | G27: =Input!$BD$15 -> 0 | H27: =Input!$BE$15 -> 0 | I27: =Input!$BF$15 -> 0 | J27: =Input!$BG$15 -> 0 | K27: =Input!$BH$15 -> 0 | L27: =SUM(F27:K27) -> 0
B28: Psychology | F28: =Input!$BI$15 -> 0 | G28: =Input!$BJ$15 -> 0 | H28: =Input!$BK$15 -> 0 | I28: =Input!$BL$15 -> 0 | J28: =Input!$BM$15 -> 0 | K28: =Input!$BN$15 -> 0 | L28: =SUM(F28:K28) -> 0
B29: Social Sciences | F29: =Input!$BO$15 -> 0 | G29: =Input!$BP$15 -> 0 | H29: =Input!$BQ$15 -> 0 | I29: =Input!$BR$15 -> 0 | J29: =Input!$BS$15 -> 0 | K29: =Input!$BT$15 -> 0 | L29: =SUM(F29:K29) -> 0
B30: Other Sciences not classified above | F30: =Input!$BU$15 -> 0 | G30: =Input!$BV$15 -> 0 | H30: =Input!$BW$15 -> 0 | I30: =Input!$BX$15 -> 0 | J30: =Input!$BY$15 -> 0 | K30: =Input!$BZ$15 -> 0 | L30: =SUM(F30:K30) -> 0
B31: Arts and Humanities | F31: =Input!$CA$15 -> 0 | G31: =Input!$CB$15 -> 0 | H31: =Input!$CC$15 -> 0 | I31: =Input!$CD$15 -> 0 | J31: =Input!$CE$15 -> 0 | K31: =Input!$CF$15 -> 0 | L31: =SUM(F31:K31) -> 0
B32: Business Administration | F32: =Input!$CG$15 -> 0 | G32: =Input!$CH$15 -> 0 | H32: =Input!$CI$15 -> 0 | I32: =Input!$CJ$15 -> 0 | J32: =Input!$CK$15 -> 0 | K32: =Input!$CL$15 -> 0 | L32: =SUM(F32:K32) -> 0
B33: Education | F33: =Input!$CM$15 -> 0 | G33: =Input!$CN$15 -> 0 | H33: =Input!$CO$15 -> 0 | I33: =Input!$CP$15 -> 0 | J33: =Input!$CQ$15 -> 0 | K33: =Input!$CR$15 -> 0 | L33: =SUM(F33:K33) -> 0
B34: Law | F34: =Input!$CS$15 -> 0 | G34: =Input!$CT$15 -> 0 | H34: =Input!$CU$15 -> 0 | I34: =Input!$CV$15 -> 0 | J34: =Input!$CW$15 -> 0 | K34: =Input!$CX$15 -> 0 | L34: =SUM(F34:K34) -> 0
B35: Field of Study - Future Use 1 | F35: =Input!$CY$15 -> 0 | G35: =Input!$CZ$15 -> 0 | H35: =Input!$DA$15 -> 0 | I35: =Input!$DB$15 -> 0 | J35: =Input!$DC$15 -> 0 | K35: =Input!$DD$15 -> 0 | L35: =SUM(F35:K35) -> 0
B36: Field of Study - Future Use 2 | F36: =Input!$DE$15 -> 0 | G36: =Input!$DF$15 -> 0 | H36: =Input!$DG$15 -> 0 | I36: =Input!$DH$15 -> 0 | J36: =Input!$DI$15 -> 0 | K36: =Input!$DJ$15 -> 0 | L36: =SUM(F36:K36) -> 0
B37: Field of Study - Future Use 3 | F37: =Input!$DK$15 -> 0 | G37: =Input!$DL$15 -> 0 | H37: =Input!$DM$15 -> 0 | I37: =Input!$DN$15 -> 0 | J37: =Input!$DO$15 -> 0 | K37: =Input!$DP$15 -> 0 | L37: =SUM(F37:K37) -> 0
B38: Field of Study - Future Use 4 | F38: =Input!$DQ$15 -> 0 | G38: =Input!$DR$15 -> 0 | H38: =Input!$DS$15 -> 0 | I38: =Input!$DT$15 -> 0 | J38: =Input!$DU$15 -> 0 | K38: =Input!$DV$15 -> 0 | L38: =SUM(F38:K38) -> 0
B39: Field of Study - Future Use 5 | F39: =Input!$DW$15 -> 0 | G39: =Input!$DX$15 -> 0 | H39: =Input!$DY$15 -> 0 | I39: =Input!$DZ$15 -> 0 | J39: =Input!$EA$15 -> 0 | K39: =Input!$EB$15 -> 0 | L39: =SUM(F39:K39) -> 0
B40: Other Non-Science Activities | F40: =Input!$EC$15 -> 0 | G40: =Input!$ED$15 -> 0 | H40: =Input!$EE$15 -> 0 | I40: =Input!$EF$15 -> 0 | J40: =Input!$EG$15 -> 0 | K40: =Input!$EH$15 -> 0 | L40: =SUM(F40:K40) -> 0 | O40: To Accountability | P40: Sources & Uses | AB40: =SUM(C40:L40) -> 0
B41: Total R & D Expenditures By Funding Source | F41: =SUM(F20:F40) -> 7250324 | G41: =SUM(G20:G40) -> 2339810 | H41: =SUM(H20:H40) -> 0 | I41: =SUM(I20:I40) -> 3239671 | J41: =SUM(J20:J40) -> 505126 | K41: =SUM(K20:K40) -> 1043201 | L41: =SUM(L20:L40) -> 14378132 | O41: ResPercGenRev | P41: State Appropriations | S41: =L41-INT(L41) -> 0 | AB41: =SUM(AB20:AB40) -> 2599896
G42: State Total | H42: =H41+G41 -> 2339810 | J42: Pvt. Total | K42: =K41+J41 -> 1548327 | L42: Federal & Private | N42: =K42+F41 -> 8798651 | O42: =ROUND((N42/P42)*100,2) -> 4.54 | P42: =Input!$GR$15 -> 193696298 | Z42: =IF(Z41<>0,"Out of Balance","")
B43: R & D Expenditures - Select Areas of Special Interest | O43: ExpendPerFTE
B44: Aging | F44: =Input!$EI$15 -> 0 | G44: =Input!$EJ$15 -> 0 | H44: =Input!$EK$15 -> 0 | I44: =Input!$EL$15 -> 0 | J44: =Input!$EM$15 -> 0 | K44: =Input!$EN$15 -> 2406 | L44: =SUM(F44:K44) -> 2406 | O44: N/A | AB44: =SUM(C44:L44) -> 4812
B45: Cancer Research | F45: =Input!$EO$15 -> 22813 | G45: =Input!$EP$15 -> 0 | H45: =Input!$EQ$15 -> 0 | I45: =Input!$ER$15 -> 0 | J45: =Input!$ES$15 -> 0 | K45: =Input!$ET$15 -> 9737 | L45: =SUM(F45:K45) -> 32550 | O45: T/TT Fall Fac FTE
B46: Cardiovascular Research | F46: =Input!$EU$15 -> 554099 | G46: =Input!$EV$15 -> 0 | H46: =Input!$EW$15 -> 0 | I46: =Input!$EX$15 -> 0 | J46: =Input!$EY$15 -> 0 | K46: =Input!$EZ$15 -> 0 | L46: =SUM(F46:K46) -> 554099 | O46: =FTSE!$O$32 -> N/A
B47: Child Health and Human Development | F47: =Input!$FA$15 -> 0 | G47: =Input!$FB$15 -> 0 | H47: =Input!$FC$15 -> 0 | I47: =Input!$FD$15 -> 0 | J47: =Input!$FE$15 -> 0 | K47: =Input!$FF$15 -> 0 | L47: =SUM(F47:K47) -> 0 | O47: As of Fall xxxxx
B48: Mental Health | F48: =Input!$FG$15 -> 0 | G48: =Input!$FH$15 -> 0 | H48: =Input!$FI$15 -> 0 | I48: =Input!$FJ$15 -> 0 | J48: =Input!$FK$15 -> 0 | K48: =Input!$FL$15 -> 0 | L48: =SUM(F48:K48) -> 0
B49: HRI Special Interest - Future Use 1 | F49: =Input!$FM$15 -> 0 | G49: =Input!$FN$15 -> 0 | H49: =Input!$FO$15 -> 0 | I49: =Input!$FP$15 -> 0 | J49: =Input!$FQ$15 -> 0 | K49: =Input!$FR$15 -> 0 | L49: =SUM(F49:K49) -> 0
B50: HRI Special Interest - Future Use 2 | F50: =Input!$FS$15 -> 0 | G50: =Input!$FT$15 -> 0 | H50: =Input!$FU$15 -> 0 | I50: =Input!$FV$15 -> 0 | J50: =Input!$FW$15 -> 0 | K50: =Input!$FX$15 -> 0 | L50: =SUM(F50:K50) -> 0
B51: HRI Special Interest - Future Use 3 | F51: =Input!$FY$15 -> 0 | G51: =Input!$FZ$15 -> 0 | H51: =Input!$GA$15 -> 0 | I51: =Input!$GB$15 -> 0 | J51: =Input!$GC$15 -> 0 | K51: =Input!$GD$15 -> 0 | L51: =SUM(F51:K51) -> 0
B52: HRI Special Interest - Future Use 4 | F52: =Input!$GE$15 -> 0 | G52: =Input!$GF$15 -> 0 | H52: =Input!$GG$15 -> 0 | I52: =Input!$GH$15 -> 0 | J52: =Input!$GI$15 -> 0 | K52: =Input!$GJ$15 -> 0 | L52: =SUM(F52:K52) -> 0
B53: HRI Special Interest - Future Use 5 | F53: =Input!$GK$15 -> 0 | G53: =Input!$GL$15 -> 0 | H53: =Input!$GM$15 -> 0 | I53: =Input!$GN$15 -> 0 | J53: =Input!$GO$15 -> 0 | K53: =Input!$GP$15 -> 0 | L53: =SUM(F53:K53) -> 0
B54: Total R & D Expenditures - Select Areas of Special Interest | F54: =SUM(F44:F53) -> 576912 | G54: =SUM(G44:G53) -> 0 | H54: =SUM(H44:H53) -> 0 | I54: =SUM(I44:I53) -> 0 | J54: =SUM(J44:J53) -> 0 | K54: =SUM(K44:K53) -> 12143 | L54: =SUM(L44:L53) -> 589055 | S54: =L54-INT(L54) -> 0 | AB54: =SUM(AB44:AB48) -> 4812
F61: =F54+F41 -> 7827236 | G61: =G54+G41 -> 2339810 | H61: =H54+H41 -> 0 | I61: =I54+I41 -> 3239671 | J61: =J54+J41 -> 505126 | K61: =K54+K41 -> 1055344 | L61: =L54+L41 -> 14967187
L62: =SUM(K8:K9)+SUM(K12:K16) -> 14378132
L63: =SUM(L61:L62) -> 29345319
L65: =IF($L$63+L64<>Input!$D$15,"Error","Balanced") -> Balanced

Sheet TAMHSC
B1: Texas A&M University System Health Science Center | N1: Return to Index | AA1: 12 | AB1: 13
B2: =Input!$B$5 -> For the Year Ended August 31, 2010
B3: =Input!$B$6 -> Source: FY 2010 Research Expenditure Survey
N4: Zoom % should be at 75%.
B6: =Input!$B$7 -> FY 2010
B7: Summary of R & D Expenditures | K7: Overall Total | L7: Defined For Survey
B8: R & D Expenses as defined for the Research Expenditure Survey | K8: =L8 -> 38231891 | L8: =Input!$H$16 -> 38231891 | AB8: =SUM(C8:L8) -> 76463782
B9: R & D Expenses not meeting the narrow definition of R & D used in the Research Expenditures Survey | K9: =Input!$F$16 -> 1645160 | AB9: =SUM(C9:L9) -> 1645160
B10: Total Expenses for R & D as reported on the Statement of Revenues, Expenses and Changes in Net Assets | H10: =IF(O10<>0,"Out of Balance with SRECNA","") | K10: =SUM(K8:K9) -> 39877051
AB11: =SUM(C10:L10) -> 39877051
B12: Other Research-related Equipment Expenditures (noncurrent fund expenditures, etc. - do not include R & D plant expenses or construction) | K12: =Input!$G$16 -> 0 | AB12: =SUM(C11:L11) -> 0
B13: Indirect Costs associated with Expenses for R & D as defined for this survey | K13: =L13 -> 678676 | L13: =Input!$I$16 -> 678676 | AB13: =SUM(C13:L13) -> 1357352
B14: Capital Outlay for research equipment (do not include R & D plant expenses or construction) | K14: =L14 -> 1386271 | L14: =Input!$J$16 -> 1386271 | AB14: =SUM(C14:L14) -> 2772542
B15: Expenditures for conduct of R & D made by institution's research foundation or 501© corporation on behalf of the institution and not report in institution AFR, including indirect costs not reported above | K15: =L15 -> 37511984 | L15: =Input!$K$16 -> 37511984 | AB15: =SUM(C15:L15) -> 75023968
B16: Pass-throughs from Texas Engineering Experiment Station not reported in R & D Expenditures as defined for the Research Expenditure Survey | K16: =L16 -> 362059 | L16: =Input!$L$16 -> 362059 | AB16: =SUM(C16:L16) -> 724118
B17: Total R & D Expenditures | K17: =SUM(K10:K16) -> 79816041 | L17: =SUM(L8:L16) -> 78170881 | S17: =L17-INT(L17) -> 0 | T17: 0 | U17: 0 | V17: 0 | AB17: =#REF!+#REF!+#REF!+#REF! -> #REF!
F18: =IF(OR(S17<>0,S41<>0,S54<>0),"Do not Enter Cents - Whole Dollars Only","")
B19: R & D Expenditures By Funding Source | F19: Federal | G19: State Appropriations | H19: State Contracts/Grants | I19: Institution Resources | J19: Private For-Profit | K19: Private Non-Profit | L19: Total
B20: Agricultural Sciences | F20: =Input!$M$16 -> 179076 | G20: =Input!$N$16 -> 0 | H20: =Input!$O$16 -> 0 | I20: =Input!$P$16 -> 97183 | J20: =Input!$Q$16 -> 0 | K20: =Input!$R$16 -> 0 | L20: =SUM(F20:K20) -> 276259 | AB20: =SUM(C20:L20) -> 552518
B21: Biological and Other Life Sciences | F21: =Input!$S$16 -> 225501 | G21: =Input!$T$16 -> 0 | H21: =Input!$U$16 -> 0 | I21: =Input!$V$16 -> 12760 | J21: =Input!$W$16 -> 0 | K21: =Input!$X$16 -> 0 | L21: =SUM(F21:K21) -> 238261 | AB21: =SUM(C21:L21) -> 476522
B22: Computer Science | F22: =Input!$Y$16 -> 0 | G22: =Input!$Z$16 -> 0 | H22: =Input!$AA$16 -> 0 | I22: =Input!$AB$16 -> 1530 | J22: =Input!$AC$16 -> 0 | K22: =Input!$AD$16 -> 0 | L22: =SUM(F22:K22) -> 1530 | AB22: =SUM(C22:L22) -> 3060
B23: Engineering | F23: =Input!$AE$16 -> 214490 | G23: =Input!$AF$16 -> 0 | H23: =Input!$AG$16 -> 0 | I23: =Input!$AH$16 -> 2616 | J23: =Input!$AI$16 -> 0 | K23: =Input!$AJ$16 -> 0 | L23: =SUM(F23:K23) -> 217106 | AB23: =SUM(C23:L23) -> 434212
B24: Environmental Sciences | F24: =Input!$AK$16 -> 0 | G24: =Input!$AL$16 -> 0 | H24: =Input!$AM$16 -> 0 | I24: =Input!$AN$16 -> 0 | J24: =Input!$AO$16 -> 0 | K24: =Input!$AP$16 -> 0 | L24: =SUM(F24:K24) -> 0 | AB24: =SUM(C24:L24) -> 0
B25: Mathematical Sciences | F25: =Input!$AQ$16 -> 0 | G25: =Input!$AR$16 -> 0 | H25: =Input!$AS$16 -> 0 | I25: =Input!$AT$16 -> 0 | J25: =Input!$AU$16 -> 0 | K25: =Input!$AV$16 -> 0 | L25: =SUM(F25:K25) -> 0 | O25: Difference | AB25: =SUM(C25:L25) -> 0
B26: Medical Sciences | F26: =Input!$AW$16 -> 31734365 | G26: =Input!$AX$16 -> 9283802 | H26: =Input!$AY$16 -> 2064486 | I26: =Input!$AZ$16 -> 27089336 | J26: =Input!$BA$16 -> 1231008 | K26: =Input!$BB$16 -> 4876916 | L26: =SUM(F26:K26) -> 76279913 | N26: =IF(O26<>0,"Out of Balance","Balanced") -> Balanced | O26: =L17-L41 -> 0
B27: Physical Sciences | F27: =Input!$BC$16 -> 12184 | G27: =Input!$BD$16 -> 0 | H27: =Input!$BE$16 -> 0 | I27: =Input!$BF$16 -> 0 | J27: =Input!$BG$16 -> 0 | K27: =Input!$BH$16 -> 0 | L27: =SUM(F27:K27) -> 12184
B28: Psychology | F28: =Input!$BI$16 -> 216476 | G28: =Input!$BJ$16 -> 0 | H28: =Input!$BK$16 -> 0 | I28: =Input!$BL$16 -> 0 | J28: =Input!$BM$16 -> 0 | K28: =Input!$BN$16 -> 0 | L28: =SUM(F28:K28) -> 216476
B29: Social Sciences | F29: =Input!$BO$16 -> 929152 | G29: =Input!$BP$16 -> 0 | H29: =Input!$BQ$16 -> 0 | I29: =Input!$BR$16 -> 0 | J29: =Input!$BS$16 -> 0 | K29: =Input!$BT$16 -> 0 | L29: =SUM(F29:K29) -> 929152
B30: Other Sciences not classified above | F30: =Input!$BU$16 -> 0 | G30: =Input!$BV$16 -> 0 | H30: =Input!$BW$16 -> 0 | I30: =Input!$BX$16 -> 0 | J30: =Input!$BY$16 -> 0 | K30: =Input!$BZ$16 -> 0 | L30: =SUM(F30:K30) -> 0
B31: Arts and Humanities | F31: =Input!$CA$16 -> 0 | G31: =Input!$CB$16 -> 0 | H31: =Input!$CC$16 -> 0 | I31: =Input!$CD$16 -> 0 | J31: =Input!$CE$16 -> 0 | K31: =Input!$CF$16 -> 0 | L31: =SUM(F31:K31) -> 0
B32: Business Administration | F32: =Input!$CG$16 -> 0 | G32: =Input!$CH$16 -> 0 | H32: =Input!$CI$16 -> 0 | I32: =Input!$CJ$16 -> 0 | J32: =Input!$CK$16 -> 0 | K32: =Input!$CL$16 -> 0 | L32: =SUM(F32:K32) -> 0
B33: Education | F33: =Input!$CM$16 -> 0 | G33: =Input!$CN$16 -> 0 | H33: =Input!$CO$16 -> 0 | I33: =Input!$CP$16 -> 0 | J33: =Input!$CQ$16 -> 0 | K33: =Input!$CR$16 -> 0 | L33: =SUM(F33:K33) -> 0
B34: Law | F34: =Input!$CS$16 -> 0 | G34: =Input!$CT$16 -> 0 | H34: =Input!$CU$16 -> 0 | I34: =Input!$CV$16 -> 0 | J34: =Input!$CW$16 -> 0 | K34: =Input!$CX$16 -> 0 | L34: =SUM(F34:K34) -> 0
B35: Field of Study - Future Use 1 | F35: =Input!$CY$16 -> 0 | G35: =Input!$CZ$16 -> 0 | H35: =Input!$DA$16 -> 0 | I35: =Input!$DB$16 -> 0 | J35: =Input!$DC$16 -> 0 | K35: =Input!$DD$16 -> 0 | L35: =SUM(F35:K35) -> 0
B36: Field of Study - Future Use 2 | F36: =Input!$DE$16 -> 0 | G36: =Input!$DF$16 -> 0 | H36: =Input!$DG$16 -> 0 | I36: =Input!$DH$16 -> 0 | J36: =Input!$DI$16 -> 0 | K36: =Input!$DJ$16 -> 0 | L36: =SUM(F36:K36) -> 0
B37: Field of Study - Future Use 3 | F37: =Input!$DK$16 -> 0 | G37: =Input!$DL$16 -> 0 | H37: =Input!$DM$16 -> 0 | I37: =Input!$DN$16 -> 0 | J37: =Input!$DO$16 -> 0 | K37: =Input!$DP$16 -> 0 | L37: =SUM(F37:K37) -> 0
B38: Field of Study - Future Use 4 | F38: =Input!$DQ$16 -> 0 | G38: =Input!$DR$16 -> 0 | H38: =Input!$DS$16 -> 0 | I38: =Input!$DT$16 -> 0 | J38: =Input!$DU$16 -> 0 | K38: =Input!$DV$16 -> 0 | L38: =SUM(F38:K38) -> 0
B39: Field of Study - Future Use 5 | F39: =Input!$DW$16 -> 0 | G39: =Input!$DX$16 -> 0 | H39: =Input!$DY$16 -> 0 | I39: =Input!$DZ$16 -> 0 | J39: =Input!$EA$16 -> 0 | K39: =Input!$EB$16 -> 0 | L39: =SUM(F39:K39) -> 0
B40: Other Non-Science Activities | F40: =Input!$EC$16 -> 0 | G40: =Input!$ED$16 -> 0 | H40: =Input!$EE$16 -> 0 | I40: =Input!$EF$16 -> 0 | J40: =Input!$EG$16 -> 0 | K40: =Input!$EH$16 -> 0 | L40: =SUM(F40:K40) -> 0 | O40: To Accountability | P40: Sources & Uses | AB40: =SUM(C40:L40) -> 0
B41: Total R & D Expenditures By Funding Source | F41: =SUM(F20:F40) -> 33511244 | G41: =SUM(G20:G40) -> 9283802 | H41: =SUM(H20:H40) -> 2064486 | I41: =SUM(I20:I40) -> 27203425 | J41: =SUM(J20:J40) -> 1231008 | K41: =SUM(K20:K40) -> 4876916 | L41: =SUM(L20:L40) -> 78170881 | O41: ResPercGenRev | P41: State Appropriations | S41: =L41-INT(L41) -> 0 | AB41: =SUM(AB20:AB40) -> 1466312
G42: State Total | H42: =H41+G41 -> 11348288 | J42: Pvt. Total | K42: =K41+J41 -> 6107924 | L42: Federal & Private | N42: =K42+F41 -> 39619168 | O42: =ROUND((N42/P42)*100,2) -> 21.39 | P42: =Input!$GR$16 -> 185190976 | Z42: =IF(Z41<>0,"Out of Balance","")
B43: R & D Expenditures - Select Areas of Special Interest | O43: ExpendPerFTE
B44: Aging | F44: =Input!$EI$16 -> 944421 | G44: =Input!$EJ$16 -> 0 | H44: =Input!$EK$16 -> 25994 | I44: =Input!$EL$16 -> 5799 | J44: =Input!$EM$16 -> 150562 | K44: =Input!$EN$16 -> 86453 | L44: =SUM(F44:K44) -> 1213229 | O44: =ROUND(N42/O46,0) -> 1760852 | AB44: =SUM(C44:L44) -> 2426458
B45: Cancer Research | F45: =Input!$EO$16 -> 2921403 | G45: =Input!$EP$16 -> 0 | H45: =Input!$EQ$16 -> 396344 | I45: =Input!$ER$16 -> 20627 | J45: =Input!$ES$16 -> 805636 | K45: =Input!$ET$16 -> 654872 | L45: =SUM(F45:K45) -> 4798882 | O45: T/TT Fall Fac FTE
B46: Cardiovascular Research | F46: =Input!$EU$16 -> 2250872 | G46: =Input!$EV$16 -> 0 | H46: =Input!$EW$16 -> 0 | I46: =Input!$EX$16 -> 66907 | J46: =Input!$EY$16 -> 244146 | K46: =Input!$EZ$16 -> 830311 | L46: =SUM(F46:K46) -> 3392236 | O46: =FTSE!$O$33 -> 22.5
B47: Child Health and Human Development | F47: =Input!$FA$16 -> 1195464 | G47: =Input!$FB$16 -> 0 | H47: =Input!$FC$16 -> 268125 | I47: =Input!$FD$16 -> 22000 | J47: =Input!$FE$16 -> 3894 | K47: =Input!$FF$16 -> 609324 | L47: =SUM(F47:K47) -> 2098807 | O47: As of Fall xxxxx
B48: Mental Health | F48: =Input!$FG$16 -> 3443521 | G48: =Input!$FH$16 -> 0 | H48: =Input!$FI$16 -> 0 | I48: =Input!$FJ$16 -> 0 | J48: =Input!$FK$16 -> 0 | K48: =Input!$FL$16 -> 138198 | L48: =SUM(F48:K48) -> 3581719
B49: HRI Special Interest - Future Use 1 | F49: =Input!$FM$16 -> 0 | G49: =Input!$FN$16 -> 0 | H49: =Input!$FO$16 -> 0 | I49: =Input!$FP$16 -> 0 | J49: =Input!$FQ$16 -> 0 | K49: =Input!$FR$16 -> 0 | L49: =SUM(F49:K49) -> 0
B50: HRI Special Interest - Future Use 2 | F50: =Input!$FS$16 -> 0 | G50: =Input!$FT$16 -> 0 | H50: =Input!$FU$16 -> 0 | I50: =Input!$FV$16 -> 0 | J50: =Input!$FW$16 -> 0 | K50: =Input!$FX$16 -> 0 | L50: =SUM(F50:K50) -> 0
B51: HRI Special Interest - Future Use 3 | F51: =Input!$FY$16 -> 0 | G51: =Input!$FZ$16 -> 0 | H51: =Input!$GA$16 -> 0 | I51: =Input!$GB$16 -> 0 | J51: =Input!$GC$16 -> 0 | K51: =Input!$GD$16 -> 0 | L51: =SUM(F51:K51) -> 0
B52: HRI Special Interest - Future Use 4 | F52: =Input!$GE$16 -> 0 | G52: =Input!$GF$16 -> 0 | H52: =Input!$GG$16 -> 0 | I52: =Input!$GH$16 -> 0 | J52: =Input!$GI$16 -> 0 | K52: =Input!$GJ$16 -> 0 | L52: =SUM(F52:K52) -> 0
B53: HRI Special Interest - Future Use 5 | F53: =Input!$GK$16 -> 0 | G53: =Input!$GL$16 -> 0 | H53: =Input!$GM$16 -> 0 | I53: =Input!$GN$16 -> 0 | J53: =Input!$GO$16 -> 0 | K53: =Input!$GP$16 -> 0 | L53: =SUM(F53:K53) -> 0
B54: Total R & D Expenditures - Select Areas of Special Interest | F54: =SUM(F44:F53) -> 10755681 | G54: =SUM(G44:G53) -> 0 | H54: =SUM(H44:H53) -> 690463 | I54: =SUM(I44:I53) -> 115333 | J54: =SUM(J44:J53) -> 1204238 | K54: =SUM(K44:K53) -> 2319158 | L54: =SUM(L44:L53) -> 15084873 | S54: =L54-INT(L54) -> 0 | AB54: =SUM(AB44:AB48) -> 2426458
F61: =F54+F41 -> 44266925 | G61: =G54+G41 -> 9283802 | H61: =H54+H41 -> 2754949 | I61: =I54+I41 -> 27318758 | J61: =J54+J41 -> 2435246 | K61: =K54+K41 -> 7196074 | L61: =L54+L41 -> 93255754
L62: =SUM(K8:K9)+SUM(K12:K16) -> 79816041
L63: =SUM(L61:L62) -> 173071795
L65: =IF($L$63+L64<>Input!$D$16,"Error","Balanced") -> Balanced

Sheet UNTHSC
B1: University of North Texas Health Science Center at Fort Worth | N1: Return to Index | AA1: 12 | AB1: 13
B2: =Input!$B$5 -> For the Year Ended August 31, 2010
B3: =Input!$B$6 -> Source: FY 2010 Research Expenditure Survey
N4: Zoom % should be at 75%.
B6: =Input!$B$7 -> FY 2010
B7: Summary of R & D Expenditures | K7: Overall Total | L7: Defined For Survey
B8: R & D Expenses as defined for the Research Expenditure Survey | K8: =L8 -> 33368122 | L8: =Input!$H$17 -> 33368122 | AB8: =SUM(C8:L8) -> 66736244
B9: R & D Expenses not meeting the narrow definition of R & D used in the Research Expenditures Survey | K9: =Input!$F$17 -> 0 | AB9: =SUM(C9:L9) -> 0
B10: Total Expenses for R & D as reported on the Statement of Revenues, Expenses and Changes in Net Assets | H10: =IF(O10<>0,"Out of Balance with SRECNA","") | K10: =SUM(K8:K9) -> 33368122
AB11: =SUM(C10:L10) -> 33368122
B12: Other Research-related Equipment Expenditures (noncurrent fund expenditures, etc. - do not include R & D plant expenses or construction) | K12: =Input!$G$17 -> 0 | AB12: =SUM(C11:L11) -> 0
B13: Indirect Costs associated with Expenses for R & D as defined for this survey | K13: =L13 -> 5567035 | L13: =Input!$I$17 -> 5567035 | AB13: =SUM(C13:L13) -> 11134070
B14: Capital Outlay for research equipment (do not include R & D plant expenses or construction) | K14: =L14 -> 919722 | L14: =Input!$J$17 -> 919722 | AB14: =SUM(C14:L14) -> 1839444
B15: Expenditures for conduct of R & D made by institution's research foundation or 501© corporation on behalf of the institution and not report in institution AFR, including indirect costs not reported above | K15: =L15 -> 0 | L15: =Input!$K$17 -> 0 | AB15: =SUM(C15:L15) -> 0
B16: Pass-throughs from Texas Engineering Experiment Station not reported in R & D Expenditures as defined for the Research Expenditure Survey | K16: =L16 -> 0 | L16: =Input!$L$17 -> 0 | AB16: =SUM(C16:L16) -> 0
B17: Total R & D Expenditures | K17: =SUM(K10:K16) -> 39854879 | L17: =SUM(L8:L16) -> 39854879 | S17: =L17-INT(L17) -> 0 | T17: 0 | U17: 0 | V17: 0 | AB17: =#REF!+#REF!+#REF!+#REF! -> #REF!
F18: =IF(OR(S17<>0,S41<>0,S54<>0),"Do not Enter Cents - Whole Dollars Only","")
B19: R & D Expenditures By Funding Source | F19: Federal | G19: State Appropriations | H19: State Contracts/Grants | I19: Institution Resources | J19: Private For-Profit | K19: Private Non-Profit | L19: Total
B20: Agricultural Sciences | F20: =Input!$M$17 -> 0 | G20: =Input!$N$17 -> 0 | H20: =Input!$O$17 -> 0 | I20: =Input!$P$17 -> 0 | J20: =Input!$Q$17 -> 0 | K20: =Input!$R$17 -> 0 | L20: =SUM(F20:K20) -> 0 | AB20: =SUM(C20:L20) -> 0
B21: Biological and Other Life Sciences | F21: =Input!$S$17 -> 22251110 | G21: =Input!$T$17 -> 0 | H21: =Input!$U$17 -> 947302 | I21: =Input!$V$17 -> 6448897 | J21: =Input!$W$17 -> 1778661 | K21: =Input!$X$17 -> 886844 | L21: =SUM(F21:K21) -> 32312814 | AB21: =SUM(C21:L21) -> 64625628
B22: Computer Science | F22: =Input!$Y$17 -> 0 | G22: =Input!$Z$17 -> 0 | H22: =Input!$AA$17 -> 0 | I22: =Input!$AB$17 -> 0 | J22: =Input!$AC$17 -> 0 | K22: =Input!$AD$17 -> 0 | L22: =SUM(F22:K22) -> 0 | AB22: =SUM(C22:L22) -> 0
B23: Engineering | F23: =Input!$AE$17 -> 0 | G23: =Input!$AF$17 -> 0 | H23: =Input!$AG$17 -> 0 | I23: =Input!$AH$17 -> 0 | J23: =Input!$AI$17 -> 0 | K23: =Input!$AJ$17 -> 0 | L23: =SUM(F23:K23) -> 0 | AB23: =SUM(C23:L23) -> 0
B24: Environmental Sciences | F24: =Input!$AK$17 -> 0 | G24: =Input!$AL$17 -> 0 | H24: =Input!$AM$17 -> 0 | I24: =Input!$AN$17 -> 0 | J24: =Input!$AO$17 -> 0 | K24: =Input!$AP$17 -> 0 | L24: =SUM(F24:K24) -> 0 | AB24: =SUM(C24:L24) -> 0
B25: Mathematical Sciences | F25: =Input!$AQ$17 -> 0 | G25: =Input!$AR$17 -> 0 | H25: =Input!$AS$17 -> 0 | I25: =Input!$AT$17 -> 0 | J25: =Input!$AU$17 -> 0 | K25: =Input!$AV$17 -> 0 | L25: =SUM(F25:K25) -> 0 | O25: Difference | AB25: =SUM(C25:L25) -> 0
B26: Medical Sciences | F26: =Input!$AW$17 -> 3684760 | G26: =Input!$AX$17 -> 0 | H26: =Input!$AY$17 -> 369598 | I26: =Input!$AZ$17 -> 2422543 | J26: =Input!$BA$17 -> 154249 | K26: =Input!$BB$17 -> 910915 | L26: =SUM(F26:K26) -> 7542065 | N26: =IF(O26<>0,"Out of Balance","Balanced") -> Balanced | O26: =L17-L41 -> 0
B27: Physical Sciences | F27: =Input!$BC$17 -> 0 | G27: =Input!$BD$17 -> 0 | H27: =Input!$BE$17 -> 0 | I27: =Input!$BF$17 -> 0 | J27: =Input!$BG$17 -> 0 | K27: =Input!$BH$17 -> 0 | L27: =SUM(F27:K27) -> 0
B28: Psychology | F28: =Input!$BI$17 -> 0 | G28: =Input!$BJ$17 -> 0 | H28: =Input!$BK$17 -> 0 | I28: =Input!$BL$17 -> 0 | J28: =Input!$BM$17 -> 0 | K28: =Input!$BN$17 -> 0 | L28: =SUM(F28:K28) -> 0
B29: Social Sciences | F29: =Input!$BO$17 -> 0 | G29: =Input!$BP$17 -> 0 | H29: =Input!$BQ$17 -> 0 | I29: =Input!$BR$17 -> 0 | J29: =Input!$BS$17 -> 0 | K29: =Input!$BT$17 -> 0 | L29: =SUM(F29:K29) -> 0
B30: Other Sciences not classified above | F30: =Input!$BU$17 -> 0 | G30: =Input!$BV$17 -> 0 | H30: =Input!$BW$17 -> 0 | I30: =Input!$BX$17 -> 0 | J30: =Input!$BY$17 -> 0 | K30: =Input!$BZ$17 -> 0 | L30: =SUM(F30:K30) -> 0
B31: Arts and Humanities | F31: =Input!$CA$17 -> 0 | G31: =Input!$CB$17 -> 0 | H31: =Input!$CC$17 -> 0 | I31: =Input!$CD$17 -> 0 | J31: =Input!$CE$17 -> 0 | K31: =Input!$CF$17 -> 0 | L31: =SUM(F31:K31) -> 0
B32: Business Administration | F32: =Input!$CG$17 -> 0 | G32: =Input!$CH$17 -> 0 | H32: =Input!$CI$17 -> 0 | I32: =Input!$CJ$17 -> 0 | J32: =Input!$CK$17 -> 0 | K32: =Input!$CL$17 -> 0 | L32: =SUM(F32:K32) -> 0
B33: Education | F33: =Input!$CM$17 -> 0 | G33: =Input!$CN$17 -> 0 | H33: =Input!$CO$17 -> 0 | I33: =Input!$CP$17 -> 0 | J33: =Input!$CQ$17 -> 0 | K33: =Input!$CR$17 -> 0 | L33: =SUM(F33:K33) -> 0
B34: Law | F34: =Input!$CS$17 -> 0 | G34: =Input!$CT$17 -> 0 | H34: =Input!$CU$17 -> 0 | I34: =Input!$CV$17 -> 0 | J34: =Input!$CW$17 -> 0 | K34: =Input!$CX$17 -> 0 | L34: =SUM(F34:K34) -> 0
B35: Field of Study - Future Use 1 | F35: =Input!$CY$17 -> 0 | G35: =Input!$CZ$17 -> 0 | H35: =Input!$DA$17 -> 0 | I35: =Input!$DB$17 -> 0 | J35: =Input!$DC$17 -> 0 | K35: =Input!$DD$17 -> 0 | L35: =SUM(F35:K35) -> 0
B36: Field of Study - Future Use 2 | F36: =Input!$DE$17 -> 0 | G36: =Input!$DF$17 -> 0 | H36: =Input!$DG$17 -> 0 | I36: =Input!$DH$17 -> 0 | J36: =Input!$DI$17 -> 0 | K36: =Input!$DJ$17 -> 0 | L36: =SUM(F36:K36) -> 0
B37: Field of Study - Future Use 3 | F37: =Input!$DK$17 -> 0 | G37: =Input!$DL$17 -> 0 | H37: =Input!$DM$17 -> 0 | I37: =Input!$DN$17 -> 0 | J37: =Input!$DO$17 -> 0 | K37: =Input!$DP$17 -> 0 | L37: =SUM(F37:K37) -> 0
B38: Field of Study - Future Use 4 | F38: =Input!$DQ$17 -> 0 | G38: =Input!$DR$17 -> 0 | H38: =Input!$DS$17 -> 0 | I38: =Input!$DT$17 -> 0 | J38: =Input!$DU$17 -> 0 | K38: =Input!$DV$17 -> 0 | L38: =SUM(F38:K38) -> 0
B39: Field of Study - Future Use 5 | F39: =Input!$DW$17 -> 0 | G39: =Input!$DX$17 -> 0 | H39: =Input!$DY$17 -> 0 | I39: =Input!$DZ$17 -> 0 | J39: =Input!$EA$17 -> 0 | K39: =Input!$EB$17 -> 0 | L39: =SUM(F39:K39) -> 0
B40: Other Non-Science Activities | F40: =Input!$EC$17 -> 0 | G40: =Input!$ED$17 -> 0 | H40: =Input!$EE$17 -> 0 | I40: =Input!$EF$17 -> 0 | J40: =Input!$EG$17 -> 0 | K40: =Input!$EH$17 -> 0 | L40: =SUM(F40:K40) -> 0 | O40: To Accountability | P40: Sources & Uses | AB40: =SUM(C40:L40) -> 0
B41: Total R & D Expenditures By Funding Source | F41: =SUM(F20:F40) -> 25935870 | G41: =SUM(G20:G40) -> 0 | H41: =SUM(H20:H40) -> 1316900 | I41: =SUM(I20:I40) -> 8871440 | J41: =SUM(J20:J40) -> 1932910 | K41: =SUM(K20:K40) -> 1797759 | L41: =SUM(L20:L40) -> 39854879 | O41: ResPercGenRev | P41: State Appropriations | S41: =L41-INT(L41) -> 0 | AB41: =SUM(AB20:AB40) -> 64625628
G42: State Total | H42: =H41+G41 -> 1316900 | J42: Pvt. Total | K42: =K41+J41 -> 3730669 | L42: Federal & Private | N42: =K42+F41 -> 29666539 | O42: =ROUND((N42/P42)*100,2) -> 16.47 | P42: =Input!$GR$17 -> 180110173 | Z42: =IF(Z41<>0,"Out of Balance","")
B43: R & D Expenditures - Select Areas of Special Interest | O43: ExpendPerFTE
B44: Aging | F44: =Input!$EI$17 -> 6872512 | G44: =Input!$EJ$17 -> 0 | H44: =Input!$EK$17 -> 371839 | I44: =Input!$EL$17 -> 173495 | J44: =Input!$EM$17 -> 65065 | K44: =Input!$EN$17 -> 235472 | L44: =SUM(F44:K44) -> 7718383 | O44: =ROUND(N42/O46,0) -> 725343 | AB44: =SUM(C44:L44) -> 15436766
B45: Cancer Research | F45: =Input!$EO$17 -> 2968045 | G45: =Input!$EP$17 -> 0 | H45: =Input!$EQ$17 -> 121598 | I45: =Input!$ER$17 -> 136838 | J45: =Input!$ES$17 -> 8066 | K45: =Input!$ET$17 -> 171566 | L45: =SUM(F45:K45) -> 3406113 | O45: T/TT Fall Fac FTE
B46: Cardiovascular Research | F46: =Input!$EU$17 -> 3940808 | G46: =Input!$EV$17 -> 0 | H46: =Input!$EW$17 -> 0 | I46: =Input!$EX$17 -> 98518 | J46: =Input!$EY$17 -> 3725 | K46: =Input!$EZ$17 -> 201704 | L46: =SUM(F46:K46) -> 4244755 | O46: =FTSE!$O$42 -> 40.9
B47: Child Health and Human Development | F47: =Input!$FA$17 -> 114194 | G47: =Input!$FB$17 -> 0 | H47: =Input!$FC$17 -> 0 | I47: =Input!$FD$17 -> 14976 | J47: =Input!$FE$17 -> 80 | K47: =Input!$FF$17 -> 0 | L47: =SUM(F47:K47) -> 129250 | O47: As of Fall xxxxx
B48: Mental Health | F48: =Input!$FG$17 -> 1260051 | G48: =Input!$FH$17 -> 0 | H48: =Input!$FI$17 -> 0 | I48: =Input!$FJ$17 -> 19766 | J48: =Input!$FK$17 -> 5612 | K48: =Input!$FL$17 -> 415483 | L48: =SUM(F48:K48) -> 1700912
B49: HRI Special Interest - Future Use 1 | F49: =Input!$FM$17 -> 0 | G49: =Input!$FN$17 -> 0 | H49: =Input!$FO$17 -> 0 | I49: =Input!$FP$17 -> 0 | J49: =Input!$FQ$17 -> 0 | K49: =Input!$FR$17 -> 0 | L49: =SUM(F49:K49) -> 0
B50: HRI Special Interest - Future Use 2 | F50: =Input!$FS$17 -> 0 | G50: =Input!$FT$17 -> 0 | H50: =Input!$FU$17 -> 0 | I50: =Input!$FV$17 -> 0 | J50: =Input!$FW$17 -> 0 | K50: =Input!$FX$17 -> 0 | L50: =SUM(F50:K50) -> 0
B51: HRI Special Interest - Future Use 3 | F51: =Input!$FY$17 -> 0 | G51: =Input!$FZ$17 -> 0 | H51: =Input!$GA$17 -> 0 | I51: =Input!$GB$17 -> 0 | J51: =Input!$GC$17 -> 0 | K51: =Input!$GD$17 -> 0 | L51: =SUM(F51:K51) -> 0
B52: HRI Special Interest - Future Use 4 | F52: =Input!$GE$17 -> 0 | G52: =Input!$GF$17 -> 0 | H52: =Input!$GG$17 -> 0 | I52: =Input!$GH$17 -> 0 | J52: =Input!$GI$17 -> 0 | K52: =Input!$GJ$17 -> 0 | L52: =SUM(F52:K52) -> 0
B53: HRI Special Interest - Future Use 5 | F53: =Input!$GK$17 -> 0 | G53: =Input!$GL$17 -> 0 | H53: =Input!$GM$17 -> 0 | I53: =Input!$GN$17 -> 0 | J53: =Input!$GO$17 -> 0 | K53: =Input!$GP$17 -> 0 | L53: =SUM(F53:K53) -> 0
B54: Total R & D Expenditures - Select Areas of Special Interest | F54: =SUM(F44:F53) -> 15155610 | G54: =SUM(G44:G53) -> 0 | H54: =SUM(H44:H53) -> 493437 | I54: =SUM(I44:I53) -> 443593 | J54: =SUM(J44:J53) -> 82548 | K54: =SUM(K44:K53) -> 1024225 | L54: =SUM(L44:L53) -> 17199413 | S54: =L54-INT(L54) -> 0 | AB54: =SUM(AB44:AB48) -> 15436766
F61: =F54+F41 -> 41091480 | G61: =G54+G41 -> 0 | H61: =H54+H41 -> 1810337 | I61: =I54+I41 -> 9315033 | J61: =J54+J41 -> 2015458 | K61: =K54+K41 -> 2821984 | L61: =L54+L41 -> 57054292
L62: =SUM(K8:K9)+SUM(K12:K16) -> 39854879
L63: =SUM(L61:L62) -> 96909171
L65: =IF($L$63+L64<>Input!$D$17,"Error","Balanced") -> Balanced

Sheet TTUHSC
B1: Texas Tech University Health Sciences Center | N1: Return to Index | AA1: 12 | AB1: 13
B2: =Input!$B$5 -> For the Year Ended August 31, 2010
B3: =Input!$B$6 -> Source: FY 2010 Research Expenditure Survey
N4: Zoom % should be at 75%.
B6: =Input!$B$7 -> FY 2010
B7: Summary of R & D Expenditures | K7: Overall Total | L7: Defined For Survey
B8: R & D Expenses as defined for the Research Expenditure Survey | K8: =L8 -> 41854717 | L8: =Input!$H$18 -> 41854717 | AB8: =SUM(C8:L8) -> 83709434
B9: R & D Expenses not meeting the narrow definition of R & D used in the Research Expenditures Survey | K9: =Input!$F$18 -> 0 | AB9: =SUM(C9:L9) -> 0
B10: Total Expenses for R & D as reported on the Statement of Revenues, Expenses and Changes in Net Assets | H10: =IF(O10<>0,"Out of Balance with SRECNA","") | K10: =SUM(K8:K9) -> 41854717
AB11: =SUM(C10:L10) -> 41854717
B12: Other Research-related Equipment Expenditures (noncurrent fund expenditures, etc. - do not include R & D plant expenses or construction) | K12: =Input!$G$18 -> 99282 | AB12: =SUM(C11:L11) -> 0
B13: Indirect Costs associated with Expenses for R & D as defined for this survey | K13: =L13 -> 3872809 | L13: =Input!$I$18 -> 3872809 | AB13: =SUM(C13:L13) -> 7745618
B14: Capital Outlay for research equipment (do not include R & D plant expenses or construction) | K14: =L14 -> 5160934 | L14: =Input!$J$18 -> 5160934 | AB14: =SUM(C14:L14) -> 10321868
B15: Expenditures for conduct of R & D made by institution's research foundation or 501© corporation on behalf of the institution and not report in institution AFR, including indirect costs not reported above | K15: =L15 -> 0 | L15: =Input!$K$18 -> 0 | AB15: =SUM(C15:L15) -> 0
B16: Pass-throughs from Texas Engineering Experiment Station not reported in R & D Expenditures as defined for the Research Expenditure Survey | K16: =L16 -> 0 | L16: =Input!$L$18 -> 0 | AB16: =SUM(C16:L16) -> 0
B17: Total R & D Expenditures | K17: =SUM(K10:K16) -> 50987742 | L17: =SUM(L8:L16) -> 50888460 | S17: =L17-INT(L17) -> 0 | T17: 0 | U17: 0 | V17: 0 | AB17: =#REF!+#REF!+#REF!+#REF! -> #REF!
F18: =IF(OR(S17<>0,S41<>0,S54<>0),"Do not Enter Cents - Whole Dollars Only","")
B19: R & D Expenditures By Funding Source | F19: Federal | G19: State Appropriations | H19: State Contracts/Grants | I19: Institution Resources | J19: Private For-Profit | K19: Private Non-Profit | L19: Total
B20: Agricultural Sciences | F20: =Input!$M$18 -> 0 | G20: =Input!$N$18 -> 0 | H20: =Input!$O$18 -> 0 | I20: =Input!$P$18 -> 0 | J20: =Input!$Q$18 -> 0 | K20: =Input!$R$18 -> 0 | L20: =SUM(F20:K20) -> 0 | AB20: =SUM(C20:L20) -> 0
B21: Biological and Other Life Sciences | F21: =Input!$S$18 -> 8162590 | G21: =Input!$T$18 -> 7878037 | H21: =Input!$U$18 -> 135985 | I21: =Input!$V$18 -> 1848257 | J21: =Input!$W$18 -> 387508 | K21: =Input!$X$18 -> 961705 | L21: =SUM(F21:K21) -> 19374082 | AB21: =SUM(C21:L21) -> 38748164
B22: Computer Science | F22: =Input!$Y$18 -> 0 | G22: =Input!$Z$18 -> 0 | H22: =Input!$AA$18 -> 0 | I22: =Input!$AB$18 -> 0 | J22: =Input!$AC$18 -> 0 | K22: =Input!$AD$18 -> 0 | L22: =SUM(F22:K22) -> 0 | AB22: =SUM(C22:L22) -> 0
B23: Engineering | F23: =Input!$AE$18 -> 0 | G23: =Input!$AF$18 -> 0 | H23: =Input!$AG$18 -> 0 | I23: =Input!$AH$18 -> 0 | J23: =Input!$AI$18 -> 0 | K23: =Input!$AJ$18 -> 0 | L23: =SUM(F23:K23) -> 0 | AB23: =SUM(C23:L23) -> 0
B24: Environmental Sciences | F24: =Input!$AK$18 -> 0 | G24: =Input!$AL$18 -> 0 | H24: =Input!$AM$18 -> 0 | I24: =Input!$AN$18 -> 0 | J24: =Input!$AO$18 -> 0 | K24: =Input!$AP$18 -> 0 | L24: =SUM(F24:K24) -> 0 | AB24: =SUM(C24:L24) -> 0
B25: Mathematical Sciences | F25: =Input!$AQ$18 -> 0 | G25: =Input!$AR$18 -> 0 | H25: =Input!$AS$18 -> 0 | I25: =Input!$AT$18 -> 0 | J25: =Input!$AU$18 -> 0 | K25: =Input!$AV$18 -> 0 | L25: =SUM(F25:K25) -> 0 | O25: Difference | AB25: =SUM(C25:L25) -> 0
B26: Medical Sciences | F26: =Input!$AW$18 -> 4787656 | G26: =Input!$AX$18 -> 17890230 | H26: =Input!$AY$18 -> 3303777 | I26: =Input!$AZ$18 -> 2927155 | J26: =Input!$BA$18 -> 647358 | K26: =Input!$BB$18 -> 1958202 | L26: =SUM(F26:K26) -> 31514378 | N26: =IF(O26<>0,"Out of Balance","Balanced") -> Balanced | O26: =L17-L41 -> 0
B27: Physical Sciences | F27: =Input!$BC$18 -> 0 | G27: =Input!$BD$18 -> 0 | H27: =Input!$BE$18 -> 0 | I27: =Input!$BF$18 -> 0 | J27: =Input!$BG$18 -> 0 | K27: =Input!$BH$18 -> 0 | L27: =SUM(F27:K27) -> 0
B28: Psychology | F28: =Input!$BI$18 -> 0 | G28: =Input!$BJ$18 -> 0 | H28: =Input!$BK$18 -> 0 | I28: =Input!$BL$18 -> 0 | J28: =Input!$BM$18 -> 0 | K28: =Input!$BN$18 -> 0 | L28: =SUM(F28:K28) -> 0
B29: Social Sciences | F29: =Input!$BO$18 -> 0 | G29: =Input!$BP$18 -> 0 | H29: =Input!$BQ$18 -> 0 | I29: =Input!$BR$18 -> 0 | J29: =Input!$BS$18 -> 0 | K29: =Input!$BT$18 -> 0 | L29: =SUM(F29:K29) -> 0
B30: Other Sciences not classified above | F30: =Input!$BU$18 -> 0 | G30: =Input!$BV$18 -> 0 | H30: =Input!$BW$18 -> 0 | I30: =Input!$BX$18 -> 0 | J30: =Input!$BY$18 -> 0 | K30: =Input!$BZ$18 -> 0 | L30: =SUM(F30:K30) -> 0
B31: Arts and Humanities | F31: =Input!$CA$18 -> 0 | G31: =Input!$CB$18 -> 0 | H31: =Input!$CC$18 -> 0 | I31: =Input!$CD$18 -> 0 | J31: =Input!$CE$18 -> 0 | K31: =Input!$CF$18 -> 0 | L31: =SUM(F31:K31) -> 0
B32: Business Administration | F32: =Input!$CG$18 -> 0 | G32: =Input!$CH$18 -> 0 | H32: =Input!$CI$18 -> 0 | I32: =Input!$CJ$18 -> 0 | J32: =Input!$CK$18 -> 0 | K32: =Input!$CL$18 -> 0 | L32: =SUM(F32:K32) -> 0
B33: Education | F33: =Input!$CM$18 -> 0 | G33: =Input!$CN$18 -> 0 | H33: =Input!$CO$18 -> 0 | I33: =Input!$CP$18 -> 0 | J33: =Input!$CQ$18 -> 0 | K33: =Input!$CR$18 -> 0 | L33: =SUM(F33:K33) -> 0
B34: Law | F34: =Input!$CS$18 -> 0 | G34: =Input!$CT$18 -> 0 | H34: =Input!$CU$18 -> 0 | I34: =Input!$CV$18 -> 0 | J34: =Input!$CW$18 -> 0 | K34: =Input!$CX$18 -> 0 | L34: =SUM(F34:K34) -> 0
B35: Field of Study - Future Use 1 | F35: =Input!$CY$18 -> 0 | G35: =Input!$CZ$18 -> 0 | H35: =Input!$DA$18 -> 0 | I35: =Input!$DB$18 -> 0 | J35: =Input!$DC$18 -> 0 | K35: =Input!$DD$18 -> 0 | L35: =SUM(F35:K35) -> 0
B36: Field of Study - Future Use 2 | F36: =Input!$DE$18 -> 0 | G36: =Input!$DF$18 -> 0 | H36: =Input!$DG$18 -> 0 | I36: =Input!$DH$18 -> 0 | J36: =Input!$DI$18 -> 0 | K36: =Input!$DJ$18 -> 0 | L36: =SUM(F36:K36) -> 0
B37: Field of Study - Future Use 3 | F37: =Input!$DK$18 -> 0 | G37: =Input!$DL$18 -> 0 | H37: =Input!$DM$18 -> 0 | I37: =Input!$DN$18 -> 0 | J37: =Input!$DO$18 -> 0 | K37: =Input!$DP$18 -> 0 | L37: =SUM(F37:K37) -> 0
B38: Field of Study - Future Use 4 | F38: =Input!$DQ$18 -> 0 | G38: =Input!$DR$18 -> 0 | H38: =Input!$DS$18 -> 0 | I38: =Input!$DT$18 -> 0 | J38: =Input!$DU$18 -> 0 | K38: =Input!$DV$18 -> 0 | L38: =SUM(F38:K38) -> 0
B39: Field of Study - Future Use 5 | F39: =Input!$DW$18 -> 0 | G39: =Input!$DX$18 -> 0 | H39: =Input!$DY$18 -> 0 | I39: =Input!$DZ$18 -> 0 | J39: =Input!$EA$18 -> 0 | K39: =Input!$EB$18 -> 0 | L39: =SUM(F39:K39) -> 0
B40: Other Non-Science Activities | F40: =Input!$EC$18 -> 0 | G40: =Input!$ED$18 -> 0 | H40: =Input!$EE$18 -> 0 | I40: =Input!$EF$18 -> 0 | J40: =Input!$EG$18 -> 0 | K40: =Input!$EH$18 -> 0 | L40: =SUM(F40:K40) -> 0 | O40: To Accountability | P40: Sources & Uses | AB40: =SUM(C40:L40) -> 0
B41: Total R & D Expenditures By Funding Source | F41: =SUM(F20:F40) -> 12950246 | G41: =SUM(G20:G40) -> 25768267 | H41: =SUM(H20:H40) -> 3439762 | I41: =SUM(I20:I40) -> 4775412 | J41: =SUM(J20:J40) -> 1034866 | K41: =SUM(K20:K40) -> 2919907 | L41: =SUM(L20:L40) -> 50888460 | O41: ResPercGenRev | P41: State Appropriations | S41: =L41-INT(L41) -> 0 | AB41: =SUM(AB20:AB40) -> 38748164
G42: State Total | H42: =H41+G41 -> 29208029 | J42: Pvt. Total | K42: =K41+J41 -> 3954773 | L42: Federal & Private | N42: =K42+F41 -> 16905019 | O42: =ROUND((N42/P42)*100,2) -> 3.96 | P42: =Input!$GR$18 -> 427245097 | Z42: =IF(Z41<>0,"Out of Balance","")
B43: R & D Expenditures - Select Areas of Special Interest | O43: ExpendPerFTE
B44: Aging | F44: =Input!$EI$18 -> 991806 | G44: =Input!$EJ$18 -> 1712024 | H44: =Input!$EK$18 -> 397120 | I44: =Input!$EL$18 -> 988967 | J44: =Input!$EM$18 -> 205164 | K44: =Input!$EN$18 -> 493076 | L44: =SUM(F44:K44) -> 4788157 | O44: =ROUND(N42/O46,0) -> 211313 | AB44: =SUM(C44:L44) -> 9576314
B45: Cancer Research | F45: =Input!$EO$18 -> 4634425 | G45: =Input!$EP$18 -> 9548039 | H45: =Input!$EQ$18 -> 693015 | I45: =Input!$ER$18 -> 1552901 | J45: =Input!$ES$18 -> 461864 | K45: =Input!$ET$18 -> 573290 | L45: =SUM(F45:K45) -> 17463534 | O45: T/TT Fall Fac FTE
B46: Cardiovascular Research | F46: =Input!$EU$18 -> 2395297 | G46: =Input!$EV$18 -> 5474769 | H46: =Input!$EW$18 -> 335809 | I46: =Input!$EX$18 -> 1837397 | J46: =Input!$EY$18 -> 428055 | K46: =Input!$EZ$18 -> 270066 | L46: =SUM(F46:K46) -> 10741393 | O46: =FTSE!$O$47 -> 80
B47: Child Health and Human Development | F47: =Input!$FA$18 -> 509291 | G47: =Input!$FB$18 -> 963902 | H47: =Input!$FC$18 -> 619634 | I47: =Input!$FD$18 -> 590036 | J47: =Input!$FE$18 -> 192568 | K47: =Input!$FF$18 -> 174701 | L47: =SUM(F47:K47) -> 3050132 | O47: As of Fall xxxxx
B48: Mental Health | F48: =Input!$FG$18 -> 1141029 | G48: =Input!$FH$18 -> 2252485 | H48: =Input!$FI$18 -> 387998 | I48: =Input!$FJ$18 -> 830984 | J48: =Input!$FK$18 -> 200533 | K48: =Input!$FL$18 -> 168435 | L48: =SUM(F48:K48) -> 4981464
B49: HRI Special Interest - Future Use 1 | F49: =Input!$FM$18 -> 0 | G49: =Input!$FN$18 -> 0 | H49: =Input!$FO$18 -> 0 | I49: =Input!$FP$18 -> 0 | J49: =Input!$FQ$18 -> 0 | K49: =Input!$FR$18 -> 0 | L49: =SUM(F49:K49) -> 0
B50: HRI Special Interest - Future Use 2 | F50: =Input!$FS$18 -> 0 | G50: =Input!$FT$18 -> 0 | H50: =Input!$FU$18 -> 0 | I50: =Input!$FV$18 -> 0 | J50: =Input!$FW$18 -> 0 | K50: =Input!$FX$18 -> 0 | L50: =SUM(F50:K50) -> 0
B51: HRI Special Interest - Future Use 3 | F51: =Input!$FY$18 -> 0 | G51: =Input!$FZ$18 -> 0 | H51: =Input!$GA$18 -> 0 | I51: =Input!$GB$18 -> 0 | J51: =Input!$GC$18 -> 0 | K51: =Input!$GD$18 -> 0 | L51: =SUM(F51:K51) -> 0
B52: HRI Special Interest - Future Use 4 | F52: =Input!$GE$18 -> 0 | G52: =Input!$GF$18 -> 0 | H52: =Input!$GG$18 -> 0 | I52: =Input!$GH$18 -> 0 | J52: =Input!$GI$18 -> 0 | K52: =Input!$GJ$18 -> 0 | L52: =SUM(F52:K52) -> 0
B53: HRI Special Interest - Future Use 5 | F53: =Input!$GK$18 -> 0 | G53: =Input!$GL$18 -> 0 | H53: =Input!$GM$18 -> 0 | I53: =Input!$GN$18 -> 0 | J53: =Input!$GO$18 -> 0 | K53: =Input!$GP$18 -> 0 | L53: =SUM(F53:K53) -> 0
B54: Total R & D Expenditures - Select Areas of Special Interest | F54: =SUM(F44:F53) -> 9671848 | G54: =SUM(G44:G53) -> 19951219 | H54: =SUM(H44:H53) -> 2433576 | I54: =SUM(I44:I53) -> 5800285 | J54: =SUM(J44:J53) -> 1488184 | K54: =SUM(K44:K53) -> 1679568 | L54: =SUM(L44:L53) -> 41024680 | S54: =L54-INT(L54) -> 0 | AB54: =SUM(AB44:AB48) -> 9576314
F61: =F54+F41 -> 22622094 | G61: =G54+G41 -> 45719486 | H61: =H54+H41 -> 5873338 | I61: =I54+I41 -> 10575697 | J61: =J54+J41 -> 2523050 | K61: =K54+K41 -> 4599475 | L61: =L54+L41 -> 91913140
L62: =SUM(K8:K9)+SUM(K12:K16) -> 50987742
L63: =SUM(L61:L62) -> 142900882
L65: =IF($L$63+L64<>Input!$D$18,"Error","Balanced") -> Balanced

Sheet Input
A1: 380 | B1: Health-Related Institutions: | H1: GP Final Column | J1: Return to Index | GP1: Return to Index
B3: Date Input Area for Complete Report
B5: For the Year Ended August 31, 2010
B6: Source: FY 2010 Research Expenditure Survey
B7: FY 2010
D8: Checksum may exclude FICE | M8: Agricultural Sciences | S8: Biological and Other Life Sciences | Y8: Computer Science | AE8: Engineering | AK8: Environmental Sciences | AQ8: Mathematical Sciences | AW8: Medical Sciences | BC8: Physical Sciences | BI8: Psychology | BO8: Social Sciences | BU8: Other Sciences not classified above | CA8: Arts and Humanities | CG8: Business Administration | CM8: Education | CS8: Law | CY8: Field of Study - Future Use 1 | DE8: Field of Study - Future Use 2 | DK8: Field of Study - Future Use 3 | DQ8: Field of Study - Future Use 4 | DW8: Field of Study - Future Use 5 | EC8: Other Non-Science Activities | EI8: Aging | EO8: Cancer Research | EU8: Cardiovascular Research | FA8: Child Health and Human Development | FG8: Mental Health | FM8: HRI Special Interest - Future Use 1 | FS8: HRI Special Interest - Future Use 2 | FY8: HRI Special Interest - Future Use 3 | GE8: HRI Special Interest - Future Use 4 | GK8: HRI Special Interest - Future Use 5 | GR8: State Approp.
D9: Checksum | E9: FICE | F9: K9 | G9: K12 | H9: L8 | I9: L13 | J9: L14 | K9: L15 | L9: L16 | M9: F20 | N9: G20 | O9: H20 | P9: I20 | Q9: J20 | R9: K20 | S9: F21 | T9: G21 | U9: H21 | V9: I21 | W9: J21 | X9: K21 | Y9: F22 | Z9: G22 | AA9: H22 | AB9: I22 | AC9: J22 | AD9: K22 | AE9: F23 | AF9: G23 | AG9: H23 | AH9: I23 | AI9: J23 | AJ9: K23 | AK9: F24 | AL9: G24 | AM9: H24 | AN9: I24 | AO9: J24 | AP9: K24 | AQ9: F25 | AR9: G25 | AS9: H25 | AT9: I25 | AU9: J25 | AV9: K25 | AW9: F26 | AX9: G26 | AY9: H26 | AZ9: I26 | BA9: J26 | BB9: K26 | BC9: F27 | BD9: G27 | BE9: H27 | BF9: I27 | BG9: J27 | BH9: K27 | BI9: F28 | BJ9: G28 | BK9: H28 | BL9: I28 | BM9: J28 | BN9: K28 | BO9: F29 | BP9: G29 | BQ9: H29 | BR9: I29 | BS9: J29 | BT9: K29 | BU9: F30 | BV9: G30 | BW9: H30 | BX9: I30 | BY9: J30 | BZ9: K30 | CA9: F31 | CB9: G31 | CC9: H31 | CD9: I31 | CE9: J31 | CF9: K31 | CG9: F32 | CH9: G32 | CI9: H32 | CJ9: I32 | CK9: J32 | CL9: K32 | CM9: F33 | CN9: G33 | CO9: H33 | CP9: I33 | CQ9: J33 | CR9: K33 | CS9: F34 | CT9: G34 | CU9: H34 | CV9: I34 | CW9: J34 | CX9: K34 | CY9: F35 | CZ9: G35 | DA9: H35 | DB9: I35 | DC9: J35 | DD9: K35 | DE9: F36 | DF9: G36 | DG9: H36 | DH9: I36 | DI9: J36 | DJ9: K36 | DK9: F37 | DL9: G37 | DM9: H37 | DN9: I37 | DO9: J37 | DP9: K37 | DQ9: F38 | DR9: G38 | DS9: H38 | DT9: I38 | DU9: J38 | DV9: K38 | DW9: F39 | DX9: G39 | DY9: H39 | DZ9: I39 | EA9: J39 | EB9: K39 | EC9: F40 | ED9: G40 | EE9: H40 | EF9: I40 | EG9: J40 | EH9: K40 | EI9: F44 | EJ9: G44 | EK9: H44 | EL9: I44 | EM9: J44 | EN9: K44 | EO9: F45 | EP9: G45 | EQ9: H45 | ER9: I45 | ES9: J45 | ET9: K45 | EU9: F46 | EV9: G46 | EW9: H46 | EX9: I46 | EY9: J46 | EZ9: K46 | FA9: F47 | FB9: G47 | FC9: H47 | FD9: I47 | FE9: J47 | FF9: K47 | FG9: F48 | FH9: G48 | FI9: H48 | FJ9: I48 | FK9: J48 | FL9: K48 | FM9: F49 | FN9: G49 | FO9: H49 | FP9: I49 | FQ9: J49 | FR9: K49 | FS9: F50 | FT9: G50 | FU9: H50 | FV9: I50 | FW9: J50 | FX9: K50 | FY9: F51 | FZ9: G51 | GA9: H51 | GB9: I51 | GC9: J51 | GD9: K51 | GE9: F52 | GF9: G52 | GG9: H52 | GH9: I52 | GI9: J52 | GJ9: K52 | GK9: F53 | GL9: G53 | GM9: H53 | GN9: I53 | GO9: J53 | GP9: K53 | GR9: P42
A10: 390 | B10: The University of Texas Southwestern Medical Center at Dallas | C10: SWM | D10: =934852678-E10 -> 934852648 | E10: 30 | F10: 0 | G10: 806596 | H10: 308606969 | I10: 75968647 | J10: 10739320 | K10: 0 | L10: 0 | M10: 0 | N10: 0 | O10: 0 | P10: 0 | Q10: 0 | R10: 0 | S10: 106280934 | T10: 18291963 | U10: 1441732 | V10: 4367700 | W10: 2442520 | X10: 32004547 | Y10: 0 | Z10: 0 | AA10: 0 | AB10: 0 | AC10: 0 | AD10: 0 | AE10: 0 | AF10: 0 | AG10: 0 | AH10: 0 | AI10: 0 | AJ10: 0 | AK10: 0 | AL10: 0 | AM10: 0 | AN10: 0 | AO10: 0 | AP10: 0 | AQ10: 0 | AR10: 0 | AS10: 0 | AT10: 0 | AU10: 0 | AV10: 0 | AW10: 125591611 | AX10: 24005050 | AY10: 2302310 | AZ10: 12131179 | BA10: 17165769 | BB10: 39115472 | BC10: 0 | BD10: 0 | BE10: 0 | BF10: 0 | BG10: 0 | BH10: 0 | BI10: 0 | BJ10: 0 | BK10: 0 | BL10: 0 | BM10: 0 | BN10: 0 | BO10: 0 | BP10: 0 | BQ10: 0 | BR10: 0 | BS10: 0 | BT10: 0 | BU10: 154440 | BV10: 3548064 | BW10: 228017 | BX10: 2230145 | BY10: 7569 | BZ10: 4005914 | CA10: 0 | CB10: 0 | CC10: 0 | CD10: 0 | CE10: 0 | CF10: 0 | CG10: 0 | CH10: 0 | CI10: 0 | CJ10: 0 | CK10: 0 | CL10: 0 | CM10: 0 | CN10: 0 | CO10: 0 | CP10: 0 | CQ10: 0 | CR10: 0 | CS10: 0 | CT10: 0 | CU10: 0 | CV10: 0 | CW10: 0 | CX10: 0 | CY10: 0 | CZ10: 0 | DA10: 0 | DB10: 0 | DC10: 0 | DD10: 0 | DE10: 0 | DF10: 0 | DG10: 0 | DH10: 0 | DI10: 0 | DJ10: 0 | DK10: 0 | DL10: 0 | DM10: 0 | DN10: 0 | DO10: 0 | DP10: 0 | DQ10: 0 | DR10: 0 | DS10: 0 | DT10: 0 | DU10: 0 | DV10: 0 | DW10: 0 | DX10: 0 | DY10: 0 | DZ10: 0 | EA10: 0 | EB10: 0 | EC10: 0 | ED10: 0 | EE10: 0 | EF10: 0 | EG10: 0 | EH10: 0 | EI10: 6384572 | EJ10: 68577 | EK10: 1252750 | EL10: 186711 | EM10: 300461 | EN10: 1990416 | EO10: 39702425 | EP10: 1273457 | EQ10: 1469560 | ER10: 2082484 | ES10: 6297255 | ET10: 10060710 | EU10: 21268029 | EV10: 915079 | EW10: 74519 | EX10: 912012 | EY10: 538872 | EZ10: 7957458 | FA10: 10822319 | FB10: 846276 | FC10: 17821 | FD10: 677136 | FE10: 471342 | FF10: 3122225 | FG10: 20270635 | FH10: 320640 | FI10: 0 | FJ10: 80797 | FK10: 824241 | FL10: 3227401 | FM10: 0 | FN10: 0 | FO10: 0 | FP10: 0 | FQ10: 0 | FR10: 0 | FS10: 0 | FT10: 0 | FU10: 0 | FV10: 0 | FW10: 0 | FX10: 0 | FY10: 0 | FZ10: 0 | GA10: 0 | GB10: 0 | GC10: 0 | GD10: 0 | GE10: 0 | GF10: 0 | GG10: 0 | GH10: 0 | GI10: 0 | GJ10: 0 | GK10: 0 | GL10: 0 | GM10: 0 | GN10: 0 | GO10: 0 | GP10: 0 | GR10: 175412063
A11: 400 | B11: The University of Texas Medical Branch at Galveston | C11: MBG | D11: 344927645 | E11: 104952 | F11: 0 | G11: 0 | H11: 116760151 | I11: 35455128 | J11: 4609725 | K11: 0 | L11: 0 | M11: 0 | N11: 0 | O11: 0 | P11: 0 | Q11: 0 | R11: 0 | S11: 51523589 | T11: 318588 | U11: 90752 | V11: 4497868 | W11: 1321290 | X11: 5361267 | Y11: 0 | Z11: 0 | AA11: 0 | AB11: 0 | AC11: 0 | AD11: 0 | AE11: 886702 | AF11: 398247 | AG11: 0 | AH11: 99878 | AI11: 54945 | AJ11: 1482 | AK11: 0 | AL11: 0 | AM11: 0 | AN11: 0 | AO11: 0 | AP11: 0 | AQ11: 0 | AR11: 0 | AS11: 0 | AT11: 0 | AU11: 0 | AV11: 0 | AW11: 76429311 | AX11: 187413 | AY11: 679687 | AZ11: 3234365 | BA11: 2288952 | BB11: 9450668 | BC11: 0 | BD11: 0 | BE11: 0 | BF11: 0 | BG11: 0 | BH11: 0 | BI11: 0 | BJ11: 0 | BK11: 0 | BL11: 0 | BM11: 0 | BN11: 0 | BO11: 0 | BP11: 0 | BQ11: 0 | BR11: 0 | BS11: 0 | BT11: 0 | BU11: 0 | BV11: 0 | BW11: 0 | BX11: 0 | BY11: 0 | BZ11: 0 | CA11: 0 | CB11: 0 | CC11: 0 | CD11: 0 | CE11: 0 | CF11: 0 | CG11: 0 | CH11: 0 | CI11: 0 | CJ11: 0 | CK11: 0 | CL11: 0 | CM11: 0 | CN11: 0 | CO11: 0 | CP11: 0 | CQ11: 0 | CR11: 0 | CS11: 0 | CT11: 0 | CU11: 0 | CV11: 0 | CW11: 0 | CX11: 0 | CY11: 0 | CZ11: 0 | DA11: 0 | DB11: 0 | DC11: 0 | DD11: 0 | DE11: 0 | DF11: 0 | DG11: 0 | DH11: 0 | DI11: 0 | DJ11: 0 | DK11: 0 | DL11: 0 | DM11: 0 | DN11: 0 | DO11: 0 | DP11: 0 | DQ11: 0 | DR11: 0 | DS11: 0 | DT11: 0 | DU11: 0 | DV11: 0 | DW11: 0 | DX11: 0 | DY11: 0 | DZ11: 0 | EA11: 0 | EB11: 0 | EC11: 0 | ED11: 0 | EE11: 0 | EF11: 0 | EG11: 0 | EH11: 0 | EI11: 8597797 | EJ11: 0 | EK11: 6194 | EL11: 0 | EM11: 326773 | EN11: 583641 | EO11: 10417568 | EP11: 0 | EQ11: 14033 | ER11: 0 | ES11: 77508 | ET11: 415488 | EU11: 2398159 | EV11: 0 | EW11: 0 | EX11: 0 | EY11: 518794 | EZ11: 1030055 | FA11: 5352931 | FB11: 0 | FC11: 0 | FD11: 0 | FE11: 254205 | FF11: 258248 | FG11: 325035 | FH11: 0 | FI11: 0 | FJ11: 0 | FK11: 286186 | FL11: 415022 | FM11: 0 | FN11: 0 | FO11: 0 | FP11: 0 | FQ11: 0 | FR11: 0 | FS11: 0 | FT11: 0 | FU11: 0 | FV11: 0 | FW11: 0 | FX11: 0 | FY11: 0 | FZ11: 0 | GA11: 0 | GB11: 0 | GC11: 0 | GD11: 0 | GE11: 0 | GF11: 0 | GG11: 0 | GH11: 0 | GI11: 0 | GJ11: 0 | GK11: 0 | GL11: 0 | GM11: 0 | GN11: 0 | GO11: 0 | GP11: 0 | GR11: 181651995
A12: 410 | B12: The University of Texas Health Science Center at Houston | C12: HSH | D12: 527520357 | E12: 011618 | F12: 0 | G12: 0 | H12: 194367928 | I12: 42189454 | J12: 4215170 | K12: 0 | L12: 0 | M12: 0 | N12: 0 | O12: 0 | P12: 0 | Q12: 0 | R12: 0 | S12: 35368893 | T12: 1162935 | U12: 388260 | V12: 1126511 | W12: 399375 | X12: 2807980 | Y12: 0 | Z12: 0 | AA12: 0 | AB12: 0 | AC12: 0 | AD12: 0 | AE12: 0 | AF12: 0 | AG12: 0 | AH12: 0 | AI12: 0 | AJ12: 0 | AK12: 0 | AL12: 0 | AM12: 0 | AN12: 0 | AO12: 0 | AP12: 0 | AQ12: 0 | AR12: 0 | AS12: 0 | AT12: 0 | AU12: 0 | AV12: 0 | AW12: 114954760 | AX12: 16759332 | AY12: 25206484 | AZ12: 10452891 | BA12: 8712860 | BB12: 23432271 | BC12: 0 | BD12: 0 | BE12: 0 | BF12: 0 | BG12: 0 | BH12: 0 | BI12: 0 | BJ12: 0 | BK12: 0 | BL12: 0 | BM12: 0 | BN12: 0 | BO12: 0 | BP12: 0 | BQ12: 0 | BR12: 0 | BS12: 0 | BT12: 0 | BU12: 0 | BV12: 0 | BW12: 0 | BX12: 0 | BY12: 0 | BZ12: 0 | CA12: 0 | CB12: 0 | CC12: 0 | CD12: 0 | CE12: 0 | CF12: 0 | CG12: 0 | CH12: 0 | CI12: 0 | CJ12: 0 | CK12: 0 | CL12: 0 | CM12: 0 | CN12: 0 | CO12: 0 | CP12: 0 | CQ12: 0 | CR12: 0 | CS12: 0 | CT12: 0 | CU12: 0 | CV12: 0 | CW12: 0 | CX12: 0 | CY12: 0 | CZ12: 0 | DA12: 0 | DB12: 0 | DC12: 0 | DD12: 0 | DE12: 0 | DF12: 0 | DG12: 0 | DH12: 0 | DI12: 0 | DJ12: 0 | DK12: 0 | DL12: 0 | DM12: 0 | DN12: 0 | DO12: 0 | DP12: 0 | DQ12: 0 | DR12: 0 | DS12: 0 | DT12: 0 | DU12: 0 | DV12: 0 | DW12: 0 | DX12: 0 | DY12: 0 | DZ12: 0 | EA12: 0 | EB12: 0 | EC12: 0 | ED12: 0 | EE12: 0 | EF12: 0 | EG12: 0 | EH12: 0 | EI12: 608411 | EJ12: 0 | EK12: 0 | EL12: 0 | EM12: 0 | EN12: 24062 | EO12: 6646285 | EP12: 0 | EQ12: 369604 | ER12: 0 | ES12: 3338 | ET12: 559101 | EU12: 13576432 | EV12: 1259657 | EW12: 0 | EX12: 74990 | EY12: 153349 | EZ12: 2782673 | FA12: 8274088 | FB12: 1849578 | FC12: 4850362 | FD12: 15262 | FE12: 186302 | FF12: 1617912 | FG12: 2759354 | FH12: 6408 | FI12: 29881 | FJ12: 0 | FK12: 273037 | FL12: 55167 | FM12: 0 | FN12: 0 | FO12: 0 | FP12: 0 | FQ12: 0 | FR12: 0 | FS12: 0 | FT12: 0 | FU12: 0 | FV12: 0 | FW12: 0 | FX12: 0 | FY12: 0 | FZ12: 0 | GA12: 0 | GB12: 0 | GC12: 0 | GD12: 0 | GE12: 0 | GF12: 0 | GG12: 0 | GH12: 0 | GI12: 0 | GJ12: 0 | GK12: 0 | GL12: 0 | GM12: 0 | GN12: 0 | GO12: 0 | GP12: 0 | GR12: 117456319
A13: 420 | B13: The University of Texas Health Science Center at San Antonio | C13: HSSA | D13: 500720276 | E13: 000040 | F13: 0 | G13: 0 | H13: 145165310 | I13: 33528292 | J13: 6535416 | K13: 0 | L13: 0 | M13: 0 | N13: 0 | O13: 0 | P13: 0 | Q13: 0 | R13: 0 | S13: 0 | T13: 0 | U13: 0 | V13: 0 | W13: 0 | X13: 0 | Y13: 0 | Z13: 0 | AA13: 0 | AB13: 0 | AC13: 0 | AD13: 0 | AE13: 0 | AF13: 0 | AG13: 0 | AH13: 0 | AI13: 0 | AJ13: 0 | AK13: 0 | AL13: 0 | AM13: 0 | AN13: 0 | AO13: 0 | AP13: 0 | AQ13: 0 | AR13: 0 | AS13: 0 | AT13: 0 | AU13: 0 | AV13: 0 | AW13: 121723410 | AX13: 6240743 | AY13: 708627 | AZ13: 20876076 | BA13: 22353048 | BB13: 13327114 | BC13: 0 | BD13: 0 | BE13: 0 | BF13: 0 | BG13: 0 | BH13: 0 | BI13: 0 | BJ13: 0 | BK13: 0 | BL13: 0 | BM13: 0 | BN13: 0 | BO13: 0 | BP13: 0 | BQ13: 0 | BR13: 0 | BS13: 0 | BT13: 0 | BU13: 0 | BV13: 0 | BW13: 0 | BX13: 0 | BY13: 0 | BZ13: 0 | CA13: 0 | CB13: 0 | CC13: 0 | CD13: 0 | CE13: 0 | CF13: 0 | CG13: 0 | CH13: 0 | CI13: 0 | CJ13: 0 | CK13: 0 | CL13: 0 | CM13: 0 | CN13: 0 | CO13: 0 | CP13: 0 | CQ13: 0 | CR13: 0 | CS13: 0 | CT13: 0 | CU13: 0 | CV13: 0 | CW13: 0 | CX13: 0 | CY13: 0 | CZ13: 0 | DA13: 0 | DB13: 0 | DC13: 0 | DD13: 0 | DE13: 0 | DF13: 0 | DG13: 0 | DH13: 0 | DI13: 0 | DJ13: 0 | DK13: 0 | DL13: 0 | DM13: 0 | DN13: 0 | DO13: 0 | DP13: 0 | DQ13: 0 | DR13: 0 | DS13: 0 | DT13: 0 | DU13: 0 | DV13: 0 | DW13: 0 | DX13: 0 | DY13: 0 | DZ13: 0 | EA13: 0 | EB13: 0 | EC13: 0 | ED13: 0 | EE13: 0 | EF13: 0 | EG13: 0 | EH13: 0 | EI13: 20440616 | EJ13: 74736 | EK13: 388019 | EL13: 57450 | EM13: 2063641 | EN13: 2454936 | EO13: 22013135 | EP13: 85619 | EQ13: 14784 | ER13: 9086254 | ES13: 8881781 | ET13: 1932546 | EU13: 12310269 | EV13: 22949 | EW13: 0 | EX13: 55092 | EY13: 728720 | EZ13: 1694519 | FA13: 13948080 | FB13: 10443 | FC13: 132833 | FD13: 8402333 | FE13: 995968 | FF13: 1909613 | FG13: 20708771 | FH13: 0 | FI13: 388019 | FJ13: 0 | FK13: 1286588 | FL13: 174526 | FM13: 0 | FN13: 0 | FO13: 0 | FP13: 0 | FQ13: 0 | FR13: 0 | FS13: 0 | FT13: 0 | FU13: 0 | FV13: 0 | FW13: 0 | FX13: 0 | FY13: 0 | FZ13: 0 | GA13: 0 | GB13: 0 | GC13: 0 | GD13: 0 | GE13: 0 | GF13: 0 | GG13: 0 | GH13: 0 | GI13: 0 | GJ13: 0 | GK13: 0 | GL13: 0 | GM13: 0 | GN13: 0 | GO13: 0 | GP13: 0 | GR13: 66838749
A14: 430 | B14: The University of Texas M.D. Anderson Cancer Center | C14: MDA | D14: 1641104232 | E14: 025554 | F14: 0 | G14: 0 | H14: 463104671 | I14: 75631023 | J14: 8299050 | K14: 0 | L14: 0 | M14: 0 | N14: 0 | O14: 0 | P14: 0 | Q14: 0 | R14: 0 | S14: 65655783 | T14: 65613402 | U14: 217616 | V14: 7409082 | W14: 4646129 | X14: 20725473 | Y14: 0 | Z14: 0 | AA14: 0 | AB14: 0 | AC14: 0 | AD14: 0 | AE14: 0 | AF14: 0 | AG14: 0 | AH14: 0 | AI14: 0 | AJ14: 0 | AK14: 0 | AL14: 0 | AM14: 0 | AN14: 0 | AO14: 0 | AP14: 0 | AQ14: 5614173 | AR14: 13409038 | AS14: 0 | AT14: 355017 | AU14: 59418 | AV14: 396902 | AW14: 114729585 | AX14: 86116417 | AY14: 62296 | AZ14: 18723770 | BA14: 44912739 | BB14: 58303336 | BC14: 7389134 | BD14: 3855001 | BE14: 64055 | BF14: 871307 | BG14: 752820 | BH14: 97414 | BI14: 6777540 | BJ14: 5125903 | BK14: 0 | BL14: 2875185 | BM14: 341015 | BN14: 1299904 | BO14: 6498232 | BP14: 2342001 | BQ14: 0 | BR14: 961879 | BS14: 0 | BT14: 833178 | BU14: 0 | BV14: 0 | BW14: 0 | BX14: 0 | BY14: 0 | BZ14: 0 | CA14: 0 | CB14: 0 | CC14: 0 | CD14: 0 | CE14: 0 | CF14: 0 | CG14: 0 | CH14: 0 | CI14: 0 | CJ14: 0 | CK14: 0 | CL14: 0 | CM14: 0 | CN14: 0 | CO14: 0 | CP14: 0 | CQ14: 0 | CR14: 0 | CS14: 0 | CT14: 0 | CU14: 0 | CV14: 0 | CW14: 0 | CX14: 0 | CY14: 0 | CZ14: 0 | DA14: 0 | DB14: 0 | DC14: 0 | DD14: 0 | DE14: 0 | DF14: 0 | DG14: 0 | DH14: 0 | DI14: 0 | DJ14: 0 | DK14: 0 | DL14: 0 | DM14: 0 | DN14: 0 | DO14: 0 | DP14: 0 | DQ14: 0 | DR14: 0 | DS14: 0 | DT14: 0 | DU14: 0 | DV14: 0 | DW14: 0 | DX14: 0 | DY14: 0 | DZ14: 0 | EA14: 0 | EB14: 0 | EC14: 0 | ED14: 0 | EE14: 0 | EF14: 0 | EG14: 0 | EH14: 0 | EI14: 0 | EJ14: 0 | EK14: 0 | EL14: 0 | EM14: 0 | EN14: 0 | EO14: 206664447 | EP14: 176461762 | EQ14: 343967 | ER14: 31196240 | ES14: 50712121 | ET14: 81656207 | EU14: 0 | EV14: 0 | EW14: 0 | EX14: 0 | EY14: 0 | EZ14: 0 | FA14: 0 | FB14: 0 | FC14: 0 | FD14: 0 | FE14: 0 | FF14: 0 | FG14: 0 | FH14: 0 | FI14: 0 | FJ14: 0 | FK14: 0 | FL14: 0 | FM14: 0 | FN14: 0 | FO14: 0 | FP14: 0 | FQ14: 0 | FR14: 0 | FS14: 0 | FT14: 0 | FU14: 0 | FV14: 0 | FW14: 0 | FX14: 0 | FY14: 0 | FZ14: 0 | GA14: 0 | GB14: 0 | GC14: 0 | GD14: 0 | GE14: 0 | GF14: 0 | GG14: 0 | GH14: 0 | GI14: 0 | GJ14: 0 | GK14: 0 | GL14: 0 | GM14: 0 | GN14: 0 | GO14: 0 | GP14: 0 | GR14: 44031032
A15: 440 | B15: The University of Texas Health Center at Tyler | C15: THC | D15: 29345319 | E15: 000404 | F15: 0 | G15: 0 | H15: 12168890 | I15: 1844206 | J15: 365036 | K15: 0 | L15: 0 | M15: 1299948 | N15: 0 | O15: 0 | P15: 0 | Q15: 0 | R15: 0 | S15: 0 | T15: 0 | U15: 0 | V15: 0 | W15: 0 | X15: 0 | Y15: 0 | Z15: 0 | AA15: 0 | AB15: 0 | AC15: 0 | AD15: 0 | AE15: 0 | AF15: 0 | AG15: 0 | AH15: 0 | AI15: 0 | AJ15: 0 | AK15: 0 | AL15: 0 | AM15: 0 | AN15: 0 | AO15: 0 | AP15: 0 | AQ15: 0 | AR15: 0 | AS15: 0 | AT15: 0 | AU15: 0 | AV15: 0 | AW15: 5950376 | AX15: 2339810 | AY15: 0 | AZ15: 3239671 | BA15: 505126 | BB15: 1043201 | BC15: 0 | BD15: 0 | BE15: 0 | BF15: 0 | BG15: 0 | BH15: 0 | BI15: 0 | BJ15: 0 | BK15: 0 | BL15: 0 | BM15: 0 | BN15: 0 | BO15: 0 | BP15: 0 | BQ15: 0 | BR15: 0 | BS15: 0 | BT15: 0 | BU15: 0 | BV15: 0 | BW15: 0 | BX15: 0 | BY15: 0 | BZ15: 0 | CA15: 0 | CB15: 0 | CC15: 0 | CD15: 0 | CE15: 0 | CF15: 0 | CG15: 0 | CH15: 0 | CI15: 0 | CJ15: 0 | CK15: 0 | CL15: 0 | CM15: 0 | CN15: 0 | CO15: 0 | CP15: 0 | CQ15: 0 | CR15: 0 | CS15: 0 | CT15: 0 | CU15: 0 | CV15: 0 | CW15: 0 | CX15: 0 | CY15: 0 | CZ15: 0 | DA15: 0 | DB15: 0 | DC15: 0 | DD15: 0 | DE15: 0 | DF15: 0 | DG15: 0 | DH15: 0 | DI15: 0 | DJ15: 0 | DK15: 0 | DL15: 0 | DM15: 0 | DN15: 0 | DO15: 0 | DP15: 0 | DQ15: 0 | DR15: 0 | DS15: 0 | DT15: 0 | DU15: 0 | DV15: 0 | DW15: 0 | DX15: 0 | DY15: 0 | DZ15: 0 | EA15: 0 | EB15: 0 | EC15: 0 | ED15: 0 | EE15: 0 | EF15: 0 | EG15: 0 | EH15: 0 | EI15: 0 | EJ15: 0 | EK15: 0 | EL15: 0 | EM15: 0 | EN15: 2406 | EO15: 22813 | EP15: 0 | EQ15: 0 | ER15: 0 | ES15: 0 | ET15: 9737 | EU15: 554099 | EV15: 0 | EW15: 0 | EX15: 0 | EY15: 0 | EZ15: 0 | FA15: 0 | FB15: 0 | FC15: 0 | FD15: 0 | FE15: 0 | FF15: 0 | FG15: 0 | FH15: 0 | FI15: 0 | FJ15: 0 | FK15: 0 | FL15: 0 | FM15: 0 | FN15: 0 | FO15: 0 | FP15: 0 | FQ15: 0 | FR15: 0 | FS15: 0 | FT15: 0 | FU15: 0 | FV15: 0 | FW15: 0 | FX15: 0 | FY15: 0 | FZ15: 0 | GA15: 0 | GB15: 0 | GC15: 0 | GD15: 0 | GE15: 0 | GF15: 0 | GG15: 0 | GH15: 0 | GI15: 0 | GJ15: 0 | GK15: 0 | GL15: 0 | GM15: 0 | GN15: 0 | GO15: 0 | GP15: 0 | GR15: 193696298
A16: 450 | B16: Texas A&M University System Health Science Center | C16: TAMHSC | D16: 173071795 | E16: 000089 | F16: 1645160 | G16: 0 | H16: 38231891 | I16: 678676 | J16: 1386271 | K16: 37511984 | L16: 362059 | M16: 179076 | N16: 0 | O16: 0 | P16: 97183 | Q16: 0 | R16: 0 | S16: 225501 | T16: 0 | U16: 0 | V16: 12760 | W16: 0 | X16: 0 | Y16: 0 | Z16: 0 | AA16: 0 | AB16: 1530 | AC16: 0 | AD16: 0 | AE16: 214490 | AF16: 0 | AG16: 0 | AH16: 2616 | AI16: 0 | AJ16: 0 | AK16: 0 | AL16: 0 | AM16: 0 | AN16: 0 | AO16: 0 | AP16: 0 | AQ16: 0 | AR16: 0 | AS16: 0 | AT16: 0 | AU16: 0 | AV16: 0 | AW16: 31734365 | AX16: 9283802 | AY16: 2064486 | AZ16: 27089336 | BA16: 1231008 | BB16: 4876916 | BC16: 12184 | BD16: 0 | BE16: 0 | BF16: 0 | BG16: 0 | BH16: 0 | BI16: 216476 | BJ16: 0 | BK16: 0 | BL16: 0 | BM16: 0 | BN16: 0 | BO16: 929152 | BP16: 0 | BQ16: 0 | BR16: 0 | BS16: 0 | BT16: 0 | BU16: 0 | BV16: 0 | BW16: 0 | BX16: 0 | BY16: 0 | BZ16: 0 | CA16: 0 | CB16: 0 | CC16: 0 | CD16: 0 | CE16: 0 | CF16: 0 | CG16: 0 | CH16: 0 | CI16: 0 | CJ16: 0 | CK16: 0 | CL16: 0 | CM16: 0 | CN16: 0 | CO16: 0 | CP16: 0 | CQ16: 0 | CR16: 0 | CS16: 0 | CT16: 0 | CU16: 0 | CV16: 0 | CW16: 0 | CX16: 0 | CY16: 0 | CZ16: 0 | DA16: 0 | DB16: 0 | DC16: 0 | DD16: 0 | DE16: 0 | DF16: 0 | DG16: 0 | DH16: 0 | DI16: 0 | DJ16: 0 | DK16: 0 | DL16: 0 | DM16: 0 | DN16: 0 | DO16: 0 | DP16: 0 | DQ16: 0 | DR16: 0 | DS16: 0 | DT16: 0 | DU16: 0 | DV16: 0 | DW16: 0 | DX16: 0 | DY16: 0 | DZ16: 0 | EA16: 0 | EB16: 0 | EC16: 0 | ED16: 0 | EE16: 0 | EF16: 0 | EG16: 0 | EH16: 0 | EI16: 944421 | EJ16: 0 | EK16: 25994 | EL16: 5799 | EM16: 150562 | EN16: 86453 | EO16: 2921403 | EP16: 0 | EQ16: 396344 | ER16: 20627 | ES16: 805636 | ET16: 654872 | EU16: 2250872 | EV16: 0 | EW16: 0 | EX16: 66907 | EY16: 244146 | EZ16: 830311 | FA16: 1195464 | FB16: 0 | FC16: 268125 | FD16: 22000 | FE16: 3894 | FF16: 609324 | FG16: 3443521 | FH16: 0 | FI16: 0 | FJ16: 0 | FK16: 0 | FL16: 138198 | FM16: 0 | FN16: 0 | FO16: 0 | FP16: 0 | FQ16: 0 | FR16: 0 | FS16: 0 | FT16: 0 | FU16: 0 | FV16: 0 | FW16: 0 | FX16: 0 | FY16: 0 | FZ16: 0 | GA16: 0 | GB16: 0 | GC16: 0 | GD16: 0 | GE16: 0 | GF16: 0 | GG16: 0 | GH16: 0 | GI16: 0 | GJ16: 0 | GK16: 0 | GL16: 0 | GM16: 0 | GN16: 0 | GO16: 0 | GP16: 0 | GR16: 185190976
A17: 460 | B17: University of North Texas Health Science Center at Fort Worth | C17: UNTHSC | D17: 96909171 | E17: 000130 | F17: 0 | G17: 0 | H17: 33368122 | I17: 5567035 | J17: 919722 | K17: 0 | L17: 0 | M17: 0 | N17: 0 | O17: 0 | P17: 0 | Q17: 0 | R17: 0 | S17: 22251110 | T17: 0 | U17: 947302 | V17: 6448897 | W17: 1778661 | X17: 886844 | Y17: 0 | Z17: 0 | AA17: 0 | AB17: 0 | AC17: 0 | AD17: 0 | AE17: 0 | AF17: 0 | AG17: 0 | AH17: 0 | AI17: 0 | AJ17: 0 | AK17: 0 | AL17: 0 | AM17: 0 | AN17: 0 | AO17: 0 | AP17: 0 | AQ17: 0 | AR17: 0 | AS17: 0 | AT17: 0 | AU17: 0 | AV17: 0 | AW17: 3684760 | AX17: 0 | AY17: 369598 | AZ17: 2422543 | BA17: 154249 | BB17: 910915 | BC17: 0 | BD17: 0 | BE17: 0 | BF17: 0 | BG17: 0 | BH17: 0 | BI17: 0 | BJ17: 0 | BK17: 0 | BL17: 0 | BM17: 0 | BN17: 0 | BO17: 0 | BP17: 0 | BQ17: 0 | BR17: 0 | BS17: 0 | BT17: 0 | BU17: 0 | BV17: 0 | BW17: 0 | BX17: 0 | BY17: 0 | BZ17: 0 | CA17: 0 | CB17: 0 | CC17: 0 | CD17: 0 | CE17: 0 | CF17: 0 | CG17: 0 | CH17: 0 | CI17: 0 | CJ17: 0 | CK17: 0 | CL17: 0 | CM17: 0 | CN17: 0 | CO17: 0 | CP17: 0 | CQ17: 0 | CR17: 0 | CS17: 0 | CT17: 0 | CU17: 0 | CV17: 0 | CW17: 0 | CX17: 0 | CY17: 0 | CZ17: 0 | DA17: 0 | DB17: 0 | DC17: 0 | DD17: 0 | DE17: 0 | DF17: 0 | DG17: 0 | DH17: 0 | DI17: 0 | DJ17: 0 | DK17: 0 | DL17: 0 | DM17: 0 | DN17: 0 | DO17: 0 | DP17: 0 | DQ17: 0 | DR17: 0 | DS17: 0 | DT17: 0 | DU17: 0 | DV17: 0 | DW17: 0 | DX17: 0 | DY17: 0 | DZ17: 0 | EA17: 0 | EB17: 0 | EC17: 0 | ED17: 0 | EE17: 0 | EF17: 0 | EG17: 0 | EH17: 0 | EI17: 6872512 | EJ17: 0 | EK17: 371839 | EL17: 173495 | EM17: 65065 | EN17: 235472 | EO17: 2968045 | EP17: 0 | EQ17: 121598 | ER17: 136838 | ES17: 8066 | ET17: 171566 | EU17: 3940808 | EV17: 0 | EW17: 0 | EX17: 98518 | EY17: 3725 | EZ17: 201704 | FA17: 114194 | FB17: 0 | FC17: 0 | FD17: 14976 | FE17: 80 | FF17: 0 | FG17: 1260051 | FH17: 0 | FI17: 0 | FJ17: 19766 | FK17: 5612 | FL17: 415483 | FM17: 0 | FN17: 0 | FO17: 0 | FP17: 0 | FQ17: 0 | FR17: 0 | FS17: 0 | FT17: 0 | FU17: 0 | FV17: 0 | FW17: 0 | FX17: 0 | FY17: 0 | FZ17: 0 | GA17: 0 | GB17: 0 | GC17: 0 | GD17: 0 | GE17: 0 | GF17: 0 | GG17: 0 | GH17: 0 | GI17: 0 | GJ17: 0 | GK17: 0 | GL17: 0 | GM17: 0 | GN17: 0 | GO17: 0 | GP17: 0 | GR17: 180110173
A18: 470 | B18: Texas Tech University Health Sciences Center | C18: TTUHSC | D18: 142900882 | E18: 000412 | F18: 0 | G18: 99282 | H18: 41854717 | I18: 3872809 | J18: 5160934 | K18: 0 | L18: 0 | M18: 0 | N18: 0 | O18: 0 | P18: 0 | Q18: 0 | R18: 0 | S18: 8162590 | T18: 7878037 | U18: 135985 | V18: 1848257 | W18: 387508 | X18: 961705 | Y18: 0 | Z18: 0 | AA18: 0 | AB18: 0 | AC18: 0 | AD18: 0 | AE18: 0 | AF18: 0 | AG18: 0 | AH18: 0 | AI18: 0 | AJ18: 0 | AK18: 0 | AL18: 0 | AM18: 0 | AN18: 0 | AO18: 0 | AP18: 0 | AQ18: 0 | AR18: 0 | AS18: 0 | AT18: 0 | AU18: 0 | AV18: 0 | AW18: 4787656 | AX18: 17890230 | AY18: 3303777 | AZ18: 2927155 | BA18: 647358 | BB18: 1958202 | BC18: 0 | BD18: 0 | BE18: 0 | BF18: 0 | BG18: 0 | BH18: 0 | BI18: 0 | BJ18: 0 | BK18: 0 | BL18: 0 | BM18: 0 | BN18: 0 | BO18: 0 | BP18: 0 | BQ18: 0 | BR18: 0 | BS18: 0 | BT18: 0 | BU18: 0 | BV18: 0 | BW18: 0 | BX18: 0 | BY18: 0 | BZ18: 0 | CA18: 0 | CB18: 0 | CC18: 0 | CD18: 0 | CE18: 0 | CF18: 0 | CG18: 0 | CH18: 0 | CI18: 0 | CJ18: 0 | CK18: 0 | CL18: 0 | CM18: 0 | CN18: 0 | CO18: 0 | CP18: 0 | CQ18: 0 | CR18: 0 | CS18: 0 | CT18: 0 | CU18: 0 | CV18: 0 | CW18: 0 | CX18: 0 | CY18: 0 | CZ18: 0 | DA18: 0 | DB18: 0 | DC18: 0 | DD18: 0 | DE18: 0 | DF18: 0 | DG18: 0 | DH18: 0 | DI18: 0 | DJ18: 0 | DK18: 0 | DL18: 0 | DM18: 0 | DN18: 0 | DO18: 0 | DP18: 0 | DQ18: 0 | DR18: 0 | DS18: 0 | DT18: 0 | DU18: 0 | DV18: 0 | DW18: 0 | DX18: 0 | DY18: 0 | DZ18: 0 | EA18: 0 | EB18: 0 | EC18: 0 | ED18: 0 | EE18: 0 | EF18: 0 | EG18: 0 | EH18: 0 | EI18: 991806 | EJ18: 1712024 | EK18: 397120 | EL18: 988967 | EM18: 205164 | EN18: 493076 | EO18: 4634425 | EP18: 9548039 | EQ18: 693015 | ER18: 1552901 | ES18: 461864 | ET18: 573290 | EU18: 2395297 | EV18: 5474769 | EW18: 335809 | EX18: 1837397 | EY18: 428055 | EZ18: 270066 | FA18: 509291 | FB18: 963902 | FC18: 619634 | FD18: 590036 | FE18: 192568 | FF18: 174701 | FG18: 1141029 | FH18: 2252485 | FI18: 387998 | FJ18: 830984 | FK18: 200533 | FL18: 168435 | FM18: 0 | FN18: 0 | FO18: 0 | FP18: 0 | FQ18: 0 | FR18: 0 | FS18: 0 | FT18: 0 | FU18: 0 | FV18: 0 | FW18: 0 | FX18: 0 | FY18: 0 | FZ18: 0 | GA18: 0 | GB18: 0 | GC18: 0 | GD18: 0 | GE18: 0 | GF18: 0 | GG18: 0 | GH18: 0 | GI18: 0 | GJ18: 0 | GK18: 0 | GL18: 0 | GM18: 0 | GN18: 0 | GO18: 0 | GP18: 0 | GR18: 427245097
A19: =COUNT(A10:A18) -> 9 | D19: =SUM(D10:D18) -> 4391352325 | GR19: =SUM(GR10:GR18) -> 1571632702

Sheet Names
F1: Statements of Sources and Uses | I1: Return to Index
F2: Universities, Health-Related Institutions, Lamar State Colleges, and TSTC
F3: FY 2010
F4: File and Tab Naming Conventions/ Authorized Amounts
B5: New Additions
B6: Institution Name | F6: Assigned Excel File | G6: Texas Competitive Knowledge Fund Sec 55 III-251 | H6: Research Development Funds Sec 55 III-250 | I6: H.E.A.F.
C7: FICE Code | D7: Tab Name | E7: Number | F7: Name on Returned File | I7: Higher Education Assistance Funds - As Adjusted
G8: FY 2010 | H8: FY 2010 | I8: FY 2010
B9: University Institutions: | E9: 30 | F9: 30 - Reserved for Summary
B11: The University of Texas System | D11: UTS | E11: S40 | F11: S40 - S & U - FY 2010 - UTS.xlsx
B12: The University of Texas at Arlington | C12: 003656 | D12: ARL | E12: 40 | F12: 40 - S & U - FY 2010 - ARL.xlsx | H12: 3452814
B13: The University of Texas at Austin | C13: 003658 | D13: AUS | E13: 50 | F13: 50 - S & U - FY 2010 - AUS.xlsx | G13: 27534452
B14: The University of Texas at Dallas | C14: 009741 | D14: DAL | E14: 60 | F14: 60 - S & U - FY 2010 - DAL.xlsx | H14: 5627594
B15: The University of Texas at El Paso | C15: 003661 | D15: E-P | E15: 70 | F15: 70 - S & U - FY 2010 - E-P.xlsx | H15: 4263330
B16: The University of Texas - Pan American | C16: 003599 | D16: P-A | E16: 80 | F16: 80 - S & U - FY 2010 - P-A.xlsx | H16: 740210 | I16: 13176800
B17: The University of Texas at Brownsville | C17: 030646 | D17: BRW | E17: 90 | F17: 90 - S & U - FY 2010 - BRW.xlsx | H17: 668711 | I17: 4284677
B18: The University of Texas of the Permian Basin | C18: 009930 | D18: P-B | E18: 100 | F18: 100 - S & U - FY 2010 - P-B.xlsx | H18: 250623
B19: The University of Texas at San Antonio | C19: 010115 | D19: S-A | E19: 110 | F19: 110 - S & U - FY 2010 - S-A.xlsx | H19: 3402524
B20: The University of Texas at Tyler | C20: 011163 | D20: TYL | E20: 120 | F20: 120 - S & U - FY 2010 - TYL.xlsx | H20: 228118
B21: Texas A&M University System | D21: TAMUS | E21: S130 | F21: S130 - S & U - FY 2010 - TAMUS.xlsx
B22: Texas A&M University | C22: 003632 | D22: TAMU | E22: 130 | F22: 130 - S & U - FY 2010 - TAMU.xlsx | G22: 28068280
B23: Texas A&M University at Galveston | C23: 010298 | D23: TAMUG | E23: 140 | F23: 140 - S & U - FY 2010 - TAMUG.xlsx | H23: 407402
B24: Prairie View A & M University | C24: 003630 | D24: PVAMU | E24: 150 | F24: 150 - S & U - FY 2010 - PVAMU.xlsx
B25: Tarleton State University | C25: 003631 | D25: TARLST | E25: 160 | F25: 160 - S & U - FY 2010 - TARL ST.xlsx | H25: 1115775
B26: Texas A&M University - Corpus Christi | C26: 011161 | D26: TAMUCC | E26: 170 | F26: 170 - S & U - FY 2010 - TAMUCC.xlsx | H26: 1495540 | I26: 8471116
B27: Texas A&M University - Kingsville | C27: 003639 | D27: TAMUK | E27: 180 | F27: 180 - S & U - FY 2010 - TAMUK.xlsx | H27: 1267265 | I27: 5167540
B28: Texas A&M International University | C28: 009651 | D28: TAMIU | E28: 190 | F28: 190 - S & U - FY 2010 - TAMIU.xlsx | H28: 34904 | I28: 3202241
B29: West Texas A&M University | C29: 003665 | D29: WTAMU | E29: 200 | F29: 200 - S & U - FY 2010 - WTAMU.xlsx | H29: 527219 | I29: 4886159
B30: Texas A&M University - Commerce | C30: 003565 | D30: TAMUC | E30: 210 | F30: 210 - S & U - FY 2010 - TAMUC.xlsx | H30: 218046 | I30: 5684047
B31: Texas A&M University -Texarkana | C31: 029269 | D31: TAMUT | E31: 220 | F31: 220 - S & U - FY 2010 - TAMUT.xlsx | I31: 1684587
B32: Texas A&M University - Central Texas | C32: 103631 | D32: TAMUCT | E32: 223 | F32: 223 - S & U - FY 2010 - TAMUCT.xlsx
B33: Texas A&M University - San Antonio | C33: 103639 | D33: TAMUSA | E33: 226 | F33: 226 - S & U - FY 2010 - TAMUSA.xlsx
B34: Texas AgriLife Research | C34: 000556 | D34: TAR | E34: 600 | F34: 600 - S & U - FY 2010 - TAR.xlsx
B35: Texas AgriLife Extension Service | C35: 000555 | D35: TAES | E35: 605 | F35: 605 - S & U - FY 2010 - TAES.xlsx
B36: Texas Engineering Experiment Station | C36: 000712 | D36: TEES1 | E36: 610 | F36: 610 - S & U - FY 2010 - TEES1.xlsx
B37: Texas Engineering Extension Service | C37: 000716 | D37: TEES2 | E37: 615 | F37: 615 - S & U - FY 2010 - TEES2.xlsx
B38: Texas Forest Service | C38: 000576 | D38: TFS | E38: 620 | F38: 620 - S & U - FY 2010 - TFS.xlsx
B39: Texas Transportation Institute | C39: 000727 | D39: TTI | E39: 625 | F39: 625 - S & U - FY 2010 - TTI.xlsx
B40: Texas Vet. Medical Diagnostic Laboratory | C40: 000557 | D40: TVMDL | E40: 630 | F40: 630 - S & U - FY 2010 - TVMDL.xlsx
B41: Texas A&M Research Foundation | C41: 000518 | D41: TAMRF | E41: 635 | F41: 635 - S & U - FY 2010 - TAMRF.xlsx
B42: University of Houston System | D42: UTS | E42: S230 | F42: S230 - S & U - FY 2010 - UTS.xlsx
B43: University of Houston | C43: 003652 | D43: UH | E43: 230 | F43: 230 - S & U - FY 2010 - UH.xlsx | G43: 4535210 | H43: 6380651 | I43: 36091538
B44: University of Houston - Clear Lake | C44: 011711 | D44: UHCL | E44: 240 | F44: 240 - S & U - FY 2010 - UHCL.xlsx | H44: 74975 | I44: 5355874
B45: University of Houston – Downtown | C45: 012826 | D45: UHD | E45: 250 | F45: 250 - S & U - FY 2010 - UHD.xlsx | H45: 56984 | I45: 9548995
B46: University of Houston – Victoria | C46: 013231 | D46: UHV | E46: 260 | F46: 260 - S & U - FY 2010 - UHV.xlsx | I46: 2335692
B47: Texas State System | D47: TXSTS | E47: S270 | F47: S270 - S & U - FY 2010 - TXSTS.xlsx
B48: Lamar University | C48: 003581 | D48: LU | E48: 270 | F48: 270 - S & U - FY 2010 - LU.xlsx | H48: 437890 | I48: 8028333
B49: Sam Houston State University | C49: 003606 | D49: SHSU | E49: 280 | F49: 280 - S & U - FY 2010 - SHSU.xlsx | H49: 381074 | I49: 10184001
B50: Texas State University - San Marcos | C50: 003615 | D50: TXST | E50: 290 | F50: 290 - S & U - FY 2010 - TXST.xlsx | H50: 1352702 | I50: 20258248
B51: Sul Ross State University | C51: 003625 | D51: SRSU | E51: 300 | F51: 300 - S & U - FY 2010 - SRSU.xlsx | H51: 290581 | I51: =2090896+388203 -> 2479099
B52: Texas Tech University System | D52: TTUS | E52: S310 | F52: S310 - S & U - FY 2010 - TTUS.xlsx
B53: Texas Tech University | C53: 003644 | D53: TTU | E53: 310 | F53: 310 - S & U - FY 2010 - TTU.xlsx | G53: 2965865 | H53: 4868296 | I53: 27446656
B54: Angelo State University | C54: 003541 | D54: ASU | E54: 320 | F54: 320 - S & U - FY 2010 - ASU.xlsx | H54: 41632 | I54: 3667497
B55: University of North Texas System | D55: UNTS | E55: S330 | F55: S330 - S & U - FY 2010 - UNTS.xlsx
B56: University of North Texas | C56: 003594 | D56: UNT | E56: 330 | F56: 330 - S & U - FY 2010 - UNT.xlsx | H56: 1602313 | I56: 27122687
B57: University of North Texas at Dallas | C57: 113594 | D57: UNTD | E57: 333 | F57: 333 - S & U - FY 2010 - UNTD.xlsx
B58: Midwestern State University | C58: 003592 | D58: MidWST | E58: 340 | F58: 340 - S & U - FY 2010 - MidWST.xlsx | H58: 8286 | I58: 3810377
B59: Stephen F. Austin State University | C59: 003624 | D59: SFA | E59: 350 | F59: 350 - S & U - FY 2010 - SFA.xlsx | H59: 634501 | I59: 6907643
B60: Texas Southern University | C60: 003642 | D60: TSU | E60: 360 | F60: 360 - S & U - FY 2010 - TSU.xlsx | H60: 430341 | I60: 11283387
B61: Texas Woman's University | C61: 003646 | D61: TWU | E61: 370 | F61: 370 - S & U - FY 2010 - TWU.xlsx | H61: 171113 | I61: 8615167
B62: Lamar Institute of Technology | C62: 036273 | D62: LIT | E62: 490 | F62: 490 - S & U - FY 2010 - LIT.xlsx | I62: 1825332
B63: Lamar State College - Orange | C63: 023582 | D63: LSCO | E63: 500 | F63: 500 - S & U - FY 2010 - LSCO.xlsx | I63: 1140745
B64: Lamar State College - Port Arthur | C64: 023485 | D64: LSCPA | E64: 510 | F64: 510 - S & U - FY 2010 - LSCPA.xlsx | I64: 1217124
B65: Texas State Technical College - Harlingen | C65: 009225 | D65: TSTCH | E65: 520 | F65: 520 - S & U - FY 2010 - TSTCH.xlsx | I65: 5775000
B66: Texas State Technical College – West Texas | C66: 009932 | D66: TSTCWTX | E66: 530 | F66: 530 - S & U - FY 2010 - TSTCWT.xlsx
B67: Texas State Technical College - Marshall | C67: 033965 | D67: TSTCM | E67: 540 | F67: 540 - S & U - FY 2010 - TSTCM.xlsx
B68: Texas State Technical College - Waco | C68: 003634 | D68: TSTCW | E68: 550 | F68: 550 - S & U - FY 2010 - TSTCW.xlsx
I70: =SUM(I62:I69) -> 9958201
I72: =SUM(I10:I71) -> 249608763
B73: Health-Related Institutions: | E73: 380 | F73: 380 - Reserved for Summary
B75: The University of Texas Southwestern Medical Center at Dallas | C75: 000030 | D75: SWM | E75: 390 | F75: 390 - S & U - FY 2010 - SWM.xlsx
B76: The University of Texas Medical Branch at Galveston | C76: 104952 | D76: MBG | E76: 400 | F76: 400 - S & U - FY 2010 - MBG.xlsx
B77: The University of Texas Health Science Center at Houston | C77: 011618 | D77: HSH | E77: 410 | F77: 410 - S & U - FY 2010 - HSH.xlsx
B78: The University of Texas Health Science Center at San Antonio | C78: 000040 | D78: HSSA | E78: 420 | F78: 420 - S & U - FY 2010 - HSSA.xlsx
B79: The University of Texas M.D. Anderson Cancer Center | C79: 025554 | D79: MDA | E79: 430 | F79: 430 - S & U - FY 2010 - MDA.xlsx
B80: The University of Texas Health Center at Tyler | C80: 000404 | D80: THC | E80: 440 | F80: 440 - S & U - FY 2010 - THC.xlsx
B81: Texas A&M University System Health Science Center | C81: 000089 | D81: TAMHSC | E81: 450 | F81: 450 - S & U - FY 2010 - TAMHSC.xlsx
B82: University of North Texas Health Science Center at Fort Worth | C82: 000130 | D82: UNTHSC | E82: 460 | F82: 460 - S & U - FY 2010 - UNTHSC.xlsx | I82: 7994676
B83: Texas Tech University Health Sciences Center | C83: 000412 | D83: TTUHSC | E83: 470 | F83: 470 - S & U - FY 2010 - TTUHSC.xlsx | I83: 14854762
I85: =SUM(I74:I83) -> 22849438
F88: Total | G88: =SUM(G10:G87) -> 63103807 | H88: =SUM(H10:H87) -> 40431414 | I88: =I70+I85+I72 -> 282416402
G91: 63103807 | H91: 40431414 | I91: 262500000
G92: =G88-G91 -> 0 | H92: =H88-H91 -> 0 | I92: =I88-I91 -> 19916402

Sheet FTSE
B1: STATE-FUNDED SEMESTER CREDIT HOURS BY LEVEL | J1: Return to Index | O1: For Research
B2: Texas Public Health-Related Institutions, FY 2009-10 | K2: FTSE Used | M2: For Accountability Use; Source Kathy Cox
A3: Source: Janice McIver 11-15-10 | D3: Fall 299, Spring 2010, Summer 2010 | K3: For S&U | M3: HRI IE Keys
C4: Under- graduate | D4: Master's1 | E4: Doctoral | F4: Total SCH | G4: Professional & Professional Specialty Headcount | H4: Full-Time Student Equivalents2 | J4: Rounded | K4: Rounded | L4: FICE Code | M4: FTFE-Annual | O4: T/TT Fall Fac FTE teach
A6: 100 | B6: The University of Texas Southwestern Medical Center at Dallas | L6: 000030 | M6: 1805.82 | O6: 360.84
A7: 110 | B7: Grad School of Biomedical Sciences | C7: 0 | D7: 6195 | E7: 13359 | F7: 19554 | G7: 0 | H7: =SUM((C7/30)+(D7/24)+(E7/18)+G7) -> 1000.2917 | J7: =ROUND(H7,2) -> 1000.29
A8: 120 | B8: School of Health Professions | C8: 2676 | D8: 8328 | E8: 0 | F8: 11004 | G8: 0 | H8: =SUM((C8/30)+(D8/24)+(E8/18)+G8) -> 436.2 | J8: =ROUND(H8,2) -> 436.2
A9: 130 | B9: Southwestern Medical School | C9: 0 | D9: 0 | E9: 0 | F9: 0 | G9: 896 | H9: =SUM((C9/30)+(D9/24)+(E9/18)+G9) -> 896 | J9: =ROUND(H9,2) -> 896 | K9: =SUM(J7:J9) -> 2332.49
A10: 200 | B10: The University of Texas Medical Branch at Galveston | L10: 104952 | M10: 1157.02 | O10: 327.54
A11: 210 | B11: Grad School of Biomedical Sciences | C11: 0 | D11: 1319 | E11: 5435 | F11: 6754 | G11: 0 | H11: =SUM((C11/30)+(D11/24)+(E11/18)+G11) -> 356.90278 | J11: =ROUND(H11,2) -> 356.9
A12: 220 | B12: Medical School | C12: 0 | D12: 0 | E12: 0 | F12: 0 | G12: 920 | H12: =SUM((C12/30)+(D12/24)+(E12/18)+G12) -> 920 | J12: =ROUND(H12,2) -> 920
A13: 230 | B13: School of Health Professions | C13: 4333 | D13: 8993 | E13: 4019 | F13: 17345 | G13: 0 | H13: =SUM((C13/30)+(D13/24)+(E13/18)+G13) -> 742.41944 | J13: =ROUND(H13,2) -> 742.42
A14: 240 | B14: School of Nursing | C14: 14524 | D14: 4045 | E14: 706 | F14: 19275 | G14: 0 | H14: =SUM((C14/30)+(D14/24)+(E14/18)+G14) -> 691.89722 | J14: =ROUND(H14,2) -> 691.9 | K14: =SUM(J11:J14) -> 2711.22
A15: 300 | B15: The University of Texas Health Science Center at Houston | L15: 011618 | M15: 1371.01 | O15: 274.39
A16: 310 | B16: Dental Branch/Academics | C16: 2533 | D16: 0 | E16: 0 | F16: 2533 | G16: 72 | H16: =SUM((C16/30)+(D16/24)+(E16/18)+G16) -> 156.43333 | J16: =ROUND(H16,2) -> 156.43
A17: 320 | B17: Dental School | C17: 0 | D17: 0 | E17: 0 | F17: 0 | G17: 329 | H17: =SUM((C17/30)+(D17/24)+(E17/18)+G17) -> 329 | J17: =ROUND(H17,2) -> 329 | Q17: 000030 | R17: 1805.82
A18: 330 | B18: Grad School of Biomedical Sciences | C18: 0 | D18: 1917 | E18: 11634 | F18: 13551 | G18: 0 | H18: =SUM((C18/30)+(D18/24)+(E18/18)+G18) -> 726.20833 | J18: =ROUND(H18,2) -> 726.21 | Q18: 000040 | R18: 1509
A19: 340 | B19: Medical School | C19: 0 | D19: 0 | E19: 0 | F19: 0 | G19: 942 | H19: =SUM((C19/30)+(D19/24)+(E19/18)+G19) -> 942 | J19: =ROUND(H19,2) -> 942 | Q19: 000089 | R19: 373.41
A20: 350 | B20: Medical School/Academics | C20: 0 | D20: 507 | E20: 0 | F20: 507 | G20: 0 | H20: =SUM((C20/30)+(D20/24)+(E20/18)+G20) -> 21.125 | J20: =ROUND(H20,2) -> 21.13 | Q20: 000130 | R20: 436.13
A21: 360 | B21: School of Biomedical Informatics | C21: 0 | D21: 1035 | E21: 429 | F21: 1464 | G21: 0 | H21: =SUM((C21/30)+(D21/24)+(E21/18)+G21) -> 66.958333 | J21: =ROUND(H21,2) -> 66.96 | Q21: 000404 | R21: 80.25
A22: 370 | B22: School of Nursing | C22: 15265 | D22: 5571 | E22: 1228 | F22: 22064 | G22: 0 | H22: =SUM((C22/30)+(D22/24)+(E22/18)+G22) -> 809.18056 | J22: =ROUND(H22,2) -> 809.18 | Q22: 000412 | R22: 887.24
A23: 380 | B23: School of Public Health | C23: 16 | D23: 14165 | E23: 4520 | F23: 18701 | G23: 0 | H23: =SUM((C23/30)+(D23/24)+(E23/18)+G23) -> 841.85278 | J23: =ROUND(H23,2) -> 841.85 | K23: =SUM(J16:J23) -> 3892.76 | Q23: 011618 | R23: 1371.01
A24: 400 | B24: The University of Texas Health Science Center at San Antonio | L24: 000040 | M24: 1509 | O24: 0.33 | Q24: 025554 | R24: 1554.59
A25: 410 | B25: Dental School | C25: 0 | D25: 0 | E25: 0 | F25: 0 | G25: 399 | H25: =SUM((C25/30)+(D25/24)+(E25/18)+G25) -> 399 | J25: =ROUND(H25,2) -> 399 | Q25: 104952 | R25: 1157.02
A26: 420 | B26: Dental School/Academics | C26: 0 | D26: 0 | E26: 0 | F26: 0 | G26: 92 | H26: =SUM((C26/30)+(D26/24)+(E26/18)+G26) -> 92 | J26: =ROUND(H26,2) -> 92 | R26: 9174.47
A27: 430 | B27: Grad School of Biomedical Sciences | C27: 0 | D27: 2181 | E27: 6077 | F27: 8258 | G27: 0 | H27: =SUM((C27/30)+(D27/24)+(E27/18)+G27) -> 428.48611 | J27: =ROUND(H27,2) -> 428.49
A28: 440 | B28: Medical School | C28: 0 | D28: 0 | E28: 0 | F28: 0 | G28: 900 | H28: =SUM((C28/30)+(D28/24)+(E28/18)+G28) -> 900 | J28: =ROUND(H28,2) -> 900
A29: 450 | B29: School of Health Professions | C29: 9532 | D29: 8286 | E29: 4088 | F29: 21906 | G29: 0 | H29: =SUM((C29/30)+(D29/24)+(E29/18)+G29) -> 890.09444 | J29: =ROUND(H29,2) -> 890.09
A30: 460 | B30: School of Nursing | C30: 14593 | D30: 3772 | E30: 333 | F30: 18698 | G30: 0 | H30: =SUM((C30/30)+(D30/24)+(E30/18)+G30) -> 662.1 | J30: =ROUND(H30,2) -> 662.1 | K30: =SUM(J25:J30) -> 3371.68
A31: 500 | B31: The University of Texas M.D. Anderson Cancer Center | C31: 8285 | D31: 0 | E31: 0 | F31: 8285 | G31: 0 | H31: =SUM((C31/30)+(D31/24)+(E31/18)+G31) -> 276.16667 | J31: =ROUND(H31,2) -> 276.17 | K31: =J31 -> 276.17 | L31: 025554 | M31: 1554.59 | O31: 407.2
B32: The University of Texas Health Center at Tyler | L32: 000404 | M32: 80.25 | O32: N/A
A33: 700 | B33: Texas A&M University System Health Science Center | L33: 000089 | M33: 373.41 | O33: 22.5
A34: 710 | B34: Baylor Col Dentistry-Advanced Educ | C34: 0 | D34: 152 | E34: 219 | F34: 371 | G34: 87 | H34: =SUM((C34/30)+(D34/24)+(E34/18)+G34) -> 105.5 | J34: =ROUND(H34,2) -> 105.5
A35: 720 | B35: Baylor Col Dentistry-Dental Hygiene | C35: 1973 | D35: 0 | E35: 0 | F35: 1973 | G35: 0 | H35: =SUM((C35/30)+(D35/24)+(E35/18)+G35) -> 65.766667 | J35: =ROUND(H35,2) -> 65.77
A36: 730 | B36: Baylor Col Dentistry-Dental School | C36: 0 | D36: 0 | E36: 0 | F36: 0 | G36: 390 | H36: =SUM((C36/30)+(D36/24)+(E36/18)+G36) -> 390 | J36: =ROUND(H36,2) -> 390
A37: 740 | B37: College of Medicine | C37: 0 | D37: 0 | E37: 0 | F37: 0 | G37: 481 | H37: =SUM((C37/30)+(D37/24)+(E37/18)+G37) -> 481 | J37: =ROUND(H37,2) -> 481
A38: 750 | B38: College of Nursing | C38: 3769 | D38: 0 | E38: 0 | F38: 3769 | G38: 0 | H38: =SUM((C38/30)+(D38/24)+(E38/18)+G38) -> 125.63333 | J38: =ROUND(H38,2) -> 125.63
A39: 760 | B39: College of Pharmacy | C39: 0 | D39: 11592 | E39: 0 | F39: 11592 | G39: 0 | H39: =SUM((C39/30)+(D39/24)+(E39/18)+G39) -> 483 | J39: =ROUND(H39,2) -> 483
A40: 770 | B40: Grad School of Biomedical Sciences | C40: 0 | D40: 91 | E40: 2172 | F40: 2263 | G40: 0 | H40: =SUM((C40/30)+(D40/24)+(E40/18)+G40) -> 124.45833 | J40: =ROUND(H40,2) -> 124.46
A41: 780 | B41: School of Rural Public Health | C41: 0 | D41: 4703 | E41: 373 | F41: 5076 | G41: 0 | H41: =SUM((C41/30)+(D41/24)+(E41/18)+G41) -> 216.68056 | J41: =ROUND(H41,2) -> 216.68 | K41: =SUM(J34:J41) -> 1992.04
A42: 800 | B42: University of North Texas Health Science Center at Fort Worth | L42: 000130 | M42: 436.13 | O42: 40.9
A43: 810 | B43: Grad School of Biomedical Sciences | C43: 0 | D43: 6445 | E43: 2686 | F43: 9131 | G43: 0 | H43: =SUM((C43/30)+(D43/24)+(E43/18)+G43) -> 417.76389 | J43: =ROUND(H43,2) -> 417.76
A44: 820 | B44: School of Public Health | C44: 0 | D44: 4468 | E44: 950 | F44: 5418 | G44: 0 | H44: =SUM((C44/30)+(D44/24)+(E44/18)+G44) -> 238.94444 | J44: =ROUND(H44,2) -> 238.94
A45: 830 | B45: Texas Col of Osteopathic Medicine | C45: 0 | D45: 0 | E45: 0 | F45: 0 | G45: 685 | H45: =SUM((C45/30)+(D45/24)+(E45/18)+G45) -> 685 | J45: =ROUND(H45,2) -> 685
A46: 840 | B46: Texas Col of Osteopathic Medicine/Acad | C46: 0 | D46: 6138 | E46: 0 | F46: 6138 | G46: 0 | H46: =SUM((C46/30)+(D46/24)+(E46/18)+G46) -> 255.75 | J46: =ROUND(H46,2) -> 255.75 | K46: =SUM(J43:J46) -> 1597.45
A47: 900 | B47: Texas Tech University Health Sciences Center | L47: 000412 | M47: 887.24 | O47: 80
A48: 910 | B48: Grad School of Biomedical Sciences | C48: 0 | D48: 598 | E48: 1872 | F48: 2470 | G48: 0 | H48: =SUM((C48/30)+(D48/24)+(E48/18)+G48) -> 128.91667 | J48: =ROUND(H48,2) -> 128.92
A49: 920 | B49: School of Allied Health | C49: 5369 | D49: 18223 | E49: 7158 | F49: 30750 | G49: 0 | H49: =SUM((C49/30)+(D49/24)+(E49/18)+G49) -> 1335.925 | J49: =ROUND(H49,2) -> 1335.93
A50: 930 | B50: School of Medicine | C50: 0 | D50: 0 | E50: 0 | F50: 0 | G50: 581 | H50: =SUM((C50/30)+(D50/24)+(E50/18)+G50) -> 581 | J50: =ROUND(H50,2) -> 581
A51: 935 | B51: Paul L. Foster School of Medicine | C51: 0 | D51: 0 | E51: 0 | F51: 0 | G51: 40 | H51: =SUM((C51/30)+(D51/24)+(E51/18)+G51) -> 40 | J51: =ROUND(H51,2) -> 40
A52: 940 | B52: School of Nursing | C52: 22012 | D52: 8949 | E52: 1069 | F52: 32030 | G52: 0 | H52: =SUM((C52/30)+(D52/24)+(E52/18)+G52) -> 1165.9972 | J52: =ROUND(H52,2) -> 1166
A53: 950 | B53: School of Pharmacy | C53: 0 | D53: 20072 | E53: 0 | F53: 20072 | G53: 0 | H53: =SUM((C53/30)+(D53/24)+(E53/18)+G53) -> 836.33333 | J53: =ROUND(H53,2) -> 836.33 | K53: =SUM(J48:J53) -> 4088.18
B55: TOTAL | C55: =SUM(C7:C54) -> 104880 | D55: =SUM(D7:D54) -> 147745 | E55: =SUM(E7:E54) -> 68327 | F55: =SUM(F7:F54) -> 320952 | G55: =SUM(G7:G54) -> 6814 | H55: =SUM(H7:H54) -> 20261.986 | J55: =SUM(J7:J54) -> 20261.99 | K55: =SUM(K7:K54) -> 20261.99 | L55: 445566 | M55: =SUM(M6:M54) -> 9174.47 | O55: =SUM(O6:O54) -> 1513.7
B57: 1Includes post-baccalaureate, master's, AUD, and PharmD.
B58: 2The sum of undergraduate semester credit hours divided by 30, master's semester credit hours divided by 24, doctoral semester credit hours divided by 18, and professional and professional specialty headcount enrollments (the larger of the fall or summer semester in the fiscal year). | J58: 20261.99 | O58: 1513.7
B59: Notes: Dual degree (FE=2) and inter-institutional students (FE=4), are included; all other inter-institutional, flexible entry, and non-state-funded hours are excluded. Source of data is CBM001. | O59: Fall 2010
O60: Checked OK

Sheet Summary (2)
B1: Summary of All University Institutions | N1: Return to Index | AA1: 12 | AB1: 13
B2: =Input!$B$5 -> For the Year Ended August 31, 2010
B3: =Input!$B$6 -> Source: FY 2010 Research Expenditure Survey
N4: Zoom % should be at 75%.
B6: =Input!$B$7 -> FY 2010
B7: Summary of R & D Expenditures | K7: Overall Total | L7: Defined For Survey
B8: R & D Expenses as defined for the Research Expenditure Survey | AB8: =SUM(C8:L8) -> 0
B9: R & D Expenses not meeting the narrow definition of R & D used in the Research Expenditures Survey | AB9: =SUM(C9:L9) -> 0
B10: Total Expenses for R & D as reported on the Statement of Revenues, Expenses and Changes in Net Assets | H10: =IF(O10<>0,"Out of Balance with SRECNA","")
AB11: =SUM(C10:L10) -> 0
B12: Other Research-related Equipment Expenditures (noncurrent fund expenditures, etc. - do not include R & D plant expenses or construction) | AB12: =SUM(C11:L11) -> 0
B13: Indirect Costs associated with Expenses for R & D as defined for this survey | AB13: =SUM(C13:L13) -> 0
B14: Capital Outlay for research equipment (do not include R & D plant expenses or construction) | AB14: =SUM(C14:L14) -> 0
B15: Expenditures for conduct of R & D made by institution's research foundation or 501© corporation on behalf of the institution and not report in institution AFR, including indirect costs not reported above | AB15: =SUM(C15:L15) -> 0
B16: Pass-throughs from Texas Engineering Experiment Station not reported in R & D Expenditures as defined for the Research Expenditure Survey | AB16: =SUM(C16:L16) -> 0
B17: Total R & D Expenditures | S17: =L17-INT(L17) -> 0 | T17: 0 | U17: 0 | V17: 0 | AB17: =#REF!+#REF!+#REF!+#REF! -> #REF!
F18: =IF(OR(S17<>0,S41<>0,S54<>0),"Do not Enter Cents - Whole Dollars Only","")
B19: R & D Expenditures By Funding Source | F19: Federal | G19: State Appropriations | H19: State Contracts/Grants | I19: Institution Resources | J19: Private For-Profit | K19: Private Non-Profit | L19: Total
B20: Agricultural Sciences | AB20: =SUM(C20:L20) -> 0
B21: Biological and Other Life Sciences | AB21: =SUM(C21:L21) -> 0
B22: Computer Science | AB22: =SUM(C22:L22) -> 0
B23: Engineering | AB23: =SUM(C23:L23) -> 0
B24: Environmental Sciences | AB24: =SUM(C24:L24) -> 0
B25: Mathematical Sciences | O25: Difference | AB25: =SUM(C25:L25) -> 0
B26: Medical Sciences | N26: =IF(O26<>0,"Out of Balance","Balanced") -> Balanced | O26: =L17-L41 -> 0
B27: Physical Sciences
B28: Psychology
B29: Social Sciences
B30: Other Sciences not classified above
B31: Arts and Humanities
B32: Business Administration
B33: Education
B34: Law
B35: Field of Study - Future Use 1
B36: Field of Study - Future Use 2
B37: Field of Study - Future Use 3
B38: Field of Study - Future Use 4
B39: Field of Study - Future Use 5
B40: Other Non-Science Activities | O40: To Accountability | P40: Sources & Uses | AB40: =SUM(C40:L40) -> 0
B41: Total R & D Expenditures By Funding Source | O41: ResPercGenRev | P41: State Appropriations | S41: =L41-INT(L41) -> 0 | AB41: =SUM(AB20:AB40) -> 0
G42: State Total | J42: Pvt. Total | L42: Federal & Private | Z42: =IF(Z41<>0,"Out of Balance","")
B43: R & D Expenditures - Select Areas of Special Interest | O43: ExpendPerFTE
B44: Aging | AB44: =SUM(C44:L44) -> 0
B45: Cancer Research | O45: T/TT Fall Fac FTE
B46: Cardiovascular Research
B47: Child Health and Human Development | O47: As of Fall xxxxx
B48: Mental Health
B49: HRI Special Interest - Future Use 1
B50: HRI Special Interest - Future Use 2
B51: HRI Special Interest - Future Use 3
B52: HRI Special Interest - Future Use 4
B53: HRI Special Interest - Future Use 5
B54: Total R & D Expenditures - Select Areas of Special Interest | S54: =L54-INT(L54) -> 0 | AB54: =SUM(AB44:AB51) -> 0
