Workbook

Sheet Fed-Public Sponsor
A1: PI/PD; Co-PI/PD(s) | D1: Base Salary | E1: AY FTE (Release) | F1: # Summer Months | G1: Summer FTE | H1: # Years
A2: PI/PD | D2: 0 | E2: 0 | F2: 0 | G2: 0 | H2: 2
A3: Co-PI/PD | D3: 0 | E3: 0 | F3: 0 | G3: 0
A4: Co-PI/PD | D4: 0 | E4: 0.1 | F4: 2 | G4: 0.1
C5: COLA | D5: 1.03
D7: Year 1 | E7: =IF($H2>1, "Year 2", "") -> Year 2 | F7: =IF($H2>2, "Year 3", "") | G7: =IF($H2>3, "Year 4", "") | H7: =IF($H2>4, "Year 5", "")
A8: Key Personnel (Salary)
A9: =A2 -> PI/PD | B9: AY | C9: =C2 -> 0 | D9: =$D2*$E2 -> 0 | E9: =IF($H$2>1,D9*$D$5, "") -> 0 | F9: =IF($H2>2,E9*$D$5, "") | G9: =IF($H2>3,F9*$D$5, "") | H9: =IF($H2>4,G9*$D$5, "")
B10: Summer | D10: =(D2*2+D2*D5*11)/13/9*F2*G2 -> 0 | E10: =IF($H$2>1,D10*$D$5, "") -> 0 | F10: =IF($H$2>2,E10*$D$5, "") | G10: =IF($H$2>3,F10*$D$5, "") | H10: =IF($H$2>4,G10*$D$5, "")
A11: =A3 -> Co-PI/PD | B11: AY | C11: =C3 -> 0 | D11: =$D3*$E3 -> 0 | E11: =IF($H$2>1,D11*$D$5, "") -> 0 | F11: =IF($H$2>2,E11*$D$5, "") | G11: =IF($H$2>3,F11*$D$5, "") | H11: =IF($H$2>4,G11*$D$5, "")
B12: Summer | D12: =(D3*2+D3*D5*11)/13/9*F3*G3 -> 0 | E12: =IF($H$2>1,D12*$D$5, "") -> 0 | F12: =IF($H$2>2,E12*$D$5, "") | G12: =IF($H$2>3,F12*$D$5, "") | H12: =IF($H$2>4,G12*$D$5, "")
A13: =A4 -> Co-PI/PD | B13: AY | C13: =C4 -> 0 | D13: =$D4/9*$E4 -> 0 | E13: =IF($H$2>1,D13*$D$5, "") -> 0 | F13: =IF($H$2>2,E13*$D$5, "") | G13: =IF($H$2>3,F13*$D$5, "") | H13: =IF($H$2>4,G13*$D$5, "")
B14: Summer | D14: =(D4*2+D4*D5*11)/13/9*F4*G4 -> 0 | E14: =IF($H$2>1,D14*$D$5, "") -> 0 | F14: =IF($H$2>2,E14*$D$5, "") | G14: =IF($H$2>3,F14*$D$5, "") | H14: =IF($H$2>4,G14*$D$5, "")
A15: Key Pers | B15: AY | D15: 0 | E15: =IF($H$2>1,D15*$D$5, "") -> 0 | F15: =IF($H$2>2,E15*$D$5, "") | G15: =IF($H$2>3,F15*$D$5, "") | H15: =IF($H$2>4,G15*$D$5, "")
B16: Summer | D16: 0 | E16: =IF($H$2>1,D16*$D$5, "") -> 0 | F16: =IF($H$2>2,E16*$D$5, "") | G16: =IF($H$2>3,F16*$D$5, "") | H16: =IF($H$2>4,G16*$D$5, "")
A17: Key Pers | B17: AY | D17: 0 | E17: =IF($H$2>1,D17*$D$5, "") -> 0 | F17: =IF($H$2>2,E17*$D$5, "") | G17: =IF($H$2>3,F17*$D$5, "") | H17: =IF($H$2>4,G17*$D$5, "")
B18: Summer | D18: 0 | E18: =IF($H$2>1,D18*$D$5, "") -> 0 | F18: =IF($H$2>2,E18*$D$5, "") | G18: =IF($H$2>3,F18*$D$5, "") | H18: =IF($H$2>4,G18*$D$5, "")
C19: Total Key Personnel (Salary) | D19: =SUM(D9:D18) -> 0 | E19: =IF($H$2>1,SUM(E9:E18),"") -> 0 | F19: =IF($H$2>2,SUM(F9:F18),"") | G19: =IF($H$2>3,SUM(G9:G18),"") | H19: =IF($H$2>4,SUM(H9:H18),"")
A21: Fringe Benefits
C22: Key Personnel (31.7%) | D22: =(D19)*0.317 -> 0 | E22: =IF($H$2>1, (E19)*0.317, "") -> 0 | F22: =IF($H$2>2, F19*0.317, "") | G22: =IF($H$2>3, G19*0.317, "") | H22: =IF($H$2>4, H19*0.317, "")
C23: Total Key Personnel (Fringe) | D23: =SUM(D22:D22) -> 0 | E23: =IF(H2>1,E22,"") -> 0 | F23: =IF(H2>2,F22,"") | G23: =IF(H2>3,G22,"") | H23: =IF(H2>4,H22,"")
A25: Student Wages | I25: Rate | J25: Hours | K25: Weeks | L25: # Students at this rate
C26: Student 1 | D26: =IF($L$26=0,IF($L$27>=1,$I$27*$J$27*$K$27,IF($L$27=0,IF($L$28>=1,$I$28*$J$28*$K$28,IF($L$28=0,IF($L$29>=1,$I$29*$J$29*$K$29,0),0)),0)),IF($L$26>=1,$I$26*$J$26*$K$26,0)) -> 0 | E26: =IF($H$2>1,D26*$D$5,"") -> 0 | F26: =IF($H$2>2,E26*$D$5,"") | G26: =IF($H$2>3,F26*$D$5,"") | H26: =IF($H$2>4,G26*$D$5,"") | I26: 8.95 | J26: 10 | K26: 8 | L26: 0
C27: Student 2 | D27: =IF($L$26=0,IF($L$27>1,$I$27*$J$27*$K$27,IF($L$27=1,IF($L$28>=1,$I$28*$J$28*$K$28,IF($L$28=0,IF($L$29>=1,$I$29*$J$29*$K$29,0),0)),IF($L$27=0,IF($L$28>=2,$I$28*$J$28*$K$28,IF($L$28=1,IF($L$29>=1,$I$29*$J$29*$K$29,0),IF($L$28=0,IF($L$29>1,$I$29*$J$29*$K$29,0),0)))))),IF($L$26>=2,$I$26*$J$26*$K$26,IF($L$26=1,IF($L$27>=1,$I$27*$J$27*$K$27,IF($L$28>=1,$I$28*$J$28*$K$28,IF($L$29>=1,$I$29*$J$29*K$29,0))),0))) -> 0 | E27: =IF($H$2>1,D27*$D$5,"") -> 0 | F27: =IF($H$2>2,E27*$D$5,"") | G27: =IF($H$2>3,F27*$D$5,"") | H27: =IF($H$2>4,G27*$D$5,"") | I27: 10.25 | J27: 10 | K27: 8 | L27: 0
C28: Student 3 | D28: =IF($L$26=0,IF($L$27>2,$I$27*$J$27*$K$27,IF($L$27=2,IF($L$28>=1,$I$28*$J$28*$K$28,IF($L$28=0,IF($L$29>=1,$I$29*$J$29*$K$29,0),0)),IF($L$27=1, IF($L$28>=2,$I$28*$J$28*$K$28,IF($L$28=1, IF($L$29>=1, $I$29*$J$29*$K$29,0),IF($L$28=0,IF($L$29>=2,$I$29*$J$29*$K$29,0)))),IF($L$27=0,IF($L$28>=3,$I$28*$J$28*$K$28,IF($L$29>=3,$I$29*$J$29*$K$29,IF($L$28=2,IF($L$29>=1,$I$29*$J$29*$K$29,IF($L$28=1,IF($L$29>=2,$I$29*$J$29*$K$29,0))),0))),0)))),IF($L$26>=3,$I$26*$J$26*$K$26,IF($L$26=2,IF($L$27>=1,$I$27*$J$27*$K$27, IF($L$28>=1,$I$28*$J$28*$K$28,IF($L$29>=1,$I$29*$J$29*$K$29,0))),IF($L$26=1, IF($L$27>=2,$I$27*$J$27*$K$27, IF($L$27=1, IF($L$28>=1, $I$28*$J$28*$K$28,IF($L$29>=1, $I$29*$J$29*$K$29,0)),IF($L$27=0,IF($L$28>=2,$I$28*$J$28*$K$28,IF($L$28=1,IF($L$29>=1, $I$29*$J$29*$K$29,0),IF($L$28=0, IF($L$29>=2, $I$29*$J$29*$K$29,0),0))),0))),0)))) -> 0 | E28: =IF($H$2>1,D28*$D$5,"") -> 0 | F28: =IF($H$2>2,E28*$D$5,"") | G28: =IF($H$2>3,F28*$D$5,"") | H28: =IF($H$2>4,G28*$D$5,"") | I28: 11.3 | J28: 10 | K28: 8 | L28: 0
C29: Student 4 | D29: =IF($L$26=0,IF($L$27>3,$I$27*$J$27*$K$27,IF($L$27=3,IF($L$28>=1,$I$28*$J$28*$K$28,IF($L$28=0,IF($L$29>=1,$I$29*$J$29*$K$29,0),0)),IF($L$27=2, IF($L$28>=2,$I$28*$J$28*$K$28,IF($L$28=1, IF($L$29>=1, $I$29*$J$29*$K$29,0),IF($L$28=0,IF($L$29>=2,$I$29*$J$29*$K$29,0),0))),IF($L$27=1,IF($L$28>=3,$I$28*$J$28*$K$28,IF($L$28=2,IF($L$29>=1,$I$29*$J$29*$K$29,0),IF($L$28=1,IF($L$29>=2,$I$29*$J$29*$K$29,0),IF($L$28=0, IF($L$29>=3,$I$29*$J$29*$K$29,0),0)))),IF($L$27=0,IF($L$28>3,$I$28*$J$28*$K$28,IF($L$28=3, IF($L$29>=1,$I$29*$J$29*$K$29,0),IF($L$28=2, IF($L$29>=2,$I$29*$J$29*$K$29,0),IF($L$28=1, IF($L$29>=3, $I$29*$J$29*$K$29,0),IF($L$28=0, IF($L$29>=4, $I$29*$J$29*$K$29,0),0))))),0))))),IF($L$26>=4,$I$26*$J$26*$K$26,IF($L$26=3,IF($L$27=1,$I$27*$J$27*$K$27, IF($L$28=1,$I$28*$J$28*$K$28,IF($L$29=1,$I$29*$J$29*$K$29,0))),IF($L$26=2, IF($L$27>=2,$I$27*$J$27*$K$27, IF($L$27=1, IF($L$28>=1, $I$28*$J$28*$K$28,IF($L$29>=1, $I$29*$J$29*$K$29,0)),IF($L$27=0,IF($L$28>=2,$I$28*$J$28*$K$28,IF($L$28=1,IF($L$29>=1, $I$29*$J$29*$K$29,0),IF($L$28=0, IF($L$29>=2, $I$29*$J$29*$K$29,0),0))),0))),IF($L$26=1, IF($L$27>=3,$I$28*$J$28*$K$28, IF($L$27=2, IF($L$28>=1,$I$28*$J$28*$K$28, IF($L$29>=1, $I$29*$J$29*$K$29,0)),IF($L$27=1, IF($L$28>=2,$I$28*$J$28*$K$28, IF($L$28=1, IF($L$29>=1, $I$29*$J$29*$K$29,0), IF($L$28=0, IF($L$29>=2,$I$29*$J$29*$K$29,0),0))),IF($L$27=0, IF($L$28>=3,$I$28*$J$28*$K$28, IF($L$28=2, IF($L$29>=1,$I$29*$J$29*$K$29,0),IF($L$28=1, IF($L$29>=2,$I$29*$J$29*$K$29,0),IF($L$28=0, IF($L$29>=3,$I$29*$J$29*$K$29,0),0)))),0)))),0))))) -> 0 | E29: =IF($H$2>1,D29*$D$5,"") -> 0 | F29: =IF($H$2>2,E29*$D$5,"") | G29: =IF($H$2>3,F29*$D$5,"") | H29: =IF($H$2>4,G29*$D$5,"") | I29: 19.79 | J29: 10 | K29: 8 | L29: 0
C30: Total Undergraduate Stipends | D30: =SUM(D26:D29) -> 0 | E30: =IF($H$2>1,SUM(E26:E29),"") -> 0 | F30: =IF($H$2>2,SUM(F26:F29),"") | G30: =IF($H$2>3,SUM(G26:G29),"") | H30: =IF($H$2>4,SUM(H26:H29),"")
J31: Total students = 4
A32: Travel
C33: Domestic Travel | D33: ='Travel Worksheet'!E19 -> 0 | E33: ='Travel Worksheet'!E35 -> 0 | F33: =IF(H2>2,'Travel Worksheet'!E51,"") | G33: =IF(H2>3,'Travel Worksheet'!E67,"") | H33: =IF(H2>4,'Travel Worksheet'!E83,"")
C34: Foreign Travel | D34: ='Travel Worksheet'!E100 -> 0 | E34: ='Travel Worksheet'!E116 -> 0 | F34: =IF(H2>2,'Travel Worksheet'!E132,"") | G34: =IF(H2>3,'Travel Worksheet'!E132,"") | H34: =IF(H2>4,'Travel Worksheet'!E164,"")
C35: Total Travel | D35: =SUM(D33:D34) -> 0 | E35: =IF($H$2>1,SUM(E33:E34),"") -> 0 | F35: =IF($H$2>2,SUM(F33:F34),"") | G35: =IF($H$2>3,SUM(G33:G34),"") | H35: =IF($H$2>4,SUM(H33:H34),"")
A37: Equipment (>$5,000)
C38: Equipment 1 | D38: 0 | E38: =IF($H$2>1,0,"") -> 0 | F38: =IF($H$2>2,0,"") | G38: =IF($H$2>3,0,"") | H38: =IF($H$2>4,0,"")
C39: Equipment 2 | D39: 0 | E39: =IF($H$2>1,0,"") -> 0 | F39: =IF($H$2>2,0,"") | G39: =IF($H$2>3,0,"") | H39: =IF($H$2>4,0,"")
C40: Equipment 3 | D40: 0 | E40: =IF($H$2>1,0,"") -> 0 | F40: =IF($H$2>2,0,"") | G40: =IF($H$2>3,0,"") | H40: =IF($H$2>4,0,"")
C41: Total Equipment | D41: =SUM(D38:D40) -> 0 | E41: =IF($H$2>1,SUM(E38:E40),"") -> 0 | F41: =IF($H$2>2,SUM(F38:F40),"") | G41: =IF($H$2>3,SUM(G38:G40),"") | H41: =IF($H$2>4,SUM(H38:H40),"")
A43: Supplies
C44: Supplies 1 | D44: 0 | E44: =IF($H$2>1,0,"") -> 0 | F44: =IF($H$2>2,0,"") | G44: =IF($H$2>3,0,"") | H44: =IF($H$2>4,0,"")
C45: Supplies 2 | D45: 0 | E45: =IF($H$2>1,0,"") -> 0 | F45: =IF($H$2>2,0,"") | G45: =IF($H$2>3,0,"") | H45: =IF($H$2>4,0,"")
C46: Supplies 3 | D46: 0 | E46: =IF($H$2>1,0,"") -> 0 | F46: =IF($H$2>2,0,"") | G46: =IF($H$2>3,0,"") | H46: =IF($H$2>4,0,"")
C47: Total Supplies | D47: =SUM(D44:D46) -> 0 | E47: =IF($H$2>1,SUM(E44:E46),"") -> 0 | F47: =IF($H$2>2,SUM(F44:F46),"") | G47: =IF($H$2>3,SUM(G44:G46),"") | H47: =IF($H$2>4,SUM(H44:H46),"")
A49: Other
C50: Other 1 | D50: 0 | E50: =IF($H$2>1,0,"") -> 0 | F50: =IF($H$2>2,0,"") | G50: =IF($H$2>3,0,"") | H50: =IF($H$2>4,0,"")
C51: Other 2 | D51: 0 | E51: =IF($H$2>1,0,"") -> 0 | F51: =IF($H$2>2,0,"") | G51: =IF($H$2>3,0,"") | H51: =IF($H$2>4,0,"")
C52: Other 3 | D52: 0 | E52: =IF($H$2>1,0,"") -> 0 | F52: =IF($H$2>2,0,"") | G52: =IF($H$2>3,0,"") | H52: =IF($H$2>4,0,"")
C53: Total Other | D53: =SUM(D50:D52) -> 0 | E53: =IF($H$2>1,SUM(E50:E52),"") -> 0 | F53: =IF($H$2>2,SUM(F50:F52),"") | G53: =IF($H$2>3,SUM(G50:G52),"") | H53: =IF($H$2>4,SUM(H50:H52),"")
A55: Consultants
C56: Consultant 1 | D56: 0 | E56: =IF($H$2>1,0,"") -> 0 | F56: =IF($H$2>2,0,"") | G56: =IF($H$2>3,0,"") | H56: =IF($H$2>4,0,"")
C57: Consultant 2 | D57: 0 | E57: =IF($H$2>1,0,"") -> 0 | F57: =IF($H$2>2,0,"") | G57: =IF($H$2>3,0,"") | H57: =IF($H$2>4,0,"")
C58: Consultant 3 | D58: 0 | E58: =IF($H$2>1,0,"") -> 0 | F58: =IF($H$2>2,0,"") | G58: =IF($H$2>3,0,"") | H58: =IF($H$2>4,0,"")
C59: Total Consultants | D59: =SUM(D56:D58) -> 0 | E59: =IF($H$2>1,SUM(E56:E58),"") -> 0 | F59: =IF($H$2>2,SUM(F56:F58),"") | G59: =IF($H$2>3,SUM(G56:G58),"") | H59: =IF($H$2>4,SUM(H56:H58),"")
A61: Total Direct Costs | D61: =D19+D23+D30+D35+D41+D47+D53+D59 -> 0 | E61: =IF($H$2>1,E19+E23+E30+E35+E41+E47+E53+E59,"") -> 0 | F61: =IF($H$2>2,F19+F23+F30+F35+F41+F47+F53+F59,"") | G61: =IF($H$2>3,G19+G23+G30+G35+G41+G47+G53+G59,"") | H61: =IF($H$2>4,H19+H23+H30+H35+H41+H47+H53+H59,"")
A62: Total Indirect Costs (48.5% of S&W only) | D62: =(D19+D30)*0.485 -> 0 | E62: =IF($H$2>1,(E19+E30)*0.485,"") -> 0 | F62: =IF($H$2>2,(F19+F30)*0.485,"") | G62: =IF($H$2>3,(G19+G30)*0.485,"") | H62: =IF($H$2>4,(H19+H30)*0.485,"")
A63: Total Costs | D63: =IF(D62<F62, D61+D62, D61+F62) -> 0 | E63: =IF(E62<G62, E61+E62, E61+G62) -> 0 | F63: =IF($H$2>2,SUM(F61:F62),"") | G63: =IF($H$2>3,SUM(G61:G62),"") | H63: =IF($H$2>4,SUM(H61:H62),"")

Sheet Private Sponsor
A1: PI/PD; Co-PI/PD(s) | D1: Base Salary | E1: AY FTE (Release) | F1: # Summer Months | G1: Summer FTE | H1: # Years
A2: PI/PD | D2: 0 | E2: 0.15 | F2: 3 | G2: 0.6 | H2: 5
A3: Co-PI/PD | D3: 0 | E3: 0.1 | F3: 2 | G3: 0.1
A4: Co-PI/PD | D4: 0 | E4: 0.1 | F4: 2 | G4: 0.1
C5: COLA | D5: 1.03
D7: Year 1 | E7: =IF($H2>1, "Year 2", "") -> Year 2 | F7: =IF($H2>2, "Year 3", "") -> Year 3 | G7: =IF($H2>3, "Year 4", "") -> Year 4 | H7: =IF($H2>4, "Year 5", "") -> Year 5
A8: Key Personnel (Salary)
A9: =A2 -> PI/PD | B9: AY | C9: =C2 -> 0 | D9: =$D2/9*$E2 -> 0 | E9: =IF($H$2>1,D9*$D$5, "") -> 0 | F9: =IF($H2>2,E9*$D$5, "") -> 0 | G9: =IF($H2>3,F9*$D$5, "") -> 0 | H9: =IF($H2>4,G9*$D$5, "") -> 0
B10: Summer | D10: =(D2*2+D2*D5*11)/13/9*F2*G2 -> 0 | E10: =IF($H$2>1,D10*$D$5, "") -> 0 | F10: =IF($H$2>2,E10*$D$5, "") -> 0 | G10: =IF($H$2>3,F10*$D$5, "") -> 0 | H10: =IF($H$2>4,G10*$D$5, "") -> 0
A11: =A3 -> Co-PI/PD | B11: AY | C11: =C3 -> 0 | D11: =$D3/9*$E3 -> 0 | E11: =IF($H$2>1,D11*$D$5, "") -> 0 | F11: =IF($H$2>2,E11*$D$5, "") -> 0 | G11: =IF($H$2>3,F11*$D$5, "") -> 0 | H11: =IF($H$2>4,G11*$D$5, "") -> 0
B12: Summer | D12: =(D3*2+D3*D5*11)/13/9*F3*G3 -> 0 | E12: =IF($H$2>1,D12*$D$5, "") -> 0 | F12: =IF($H$2>2,E12*$D$5, "") -> 0 | G12: =IF($H$2>3,F12*$D$5, "") -> 0 | H12: =IF($H$2>4,G12*$D$5, "") -> 0
A13: =A4 -> Co-PI/PD | B13: AY | C13: =C4 -> 0 | D13: =$D4/9*$E4 -> 0 | E13: =IF($H$2>1,D13*$D$5, "") -> 0 | F13: =IF($H$2>2,E13*$D$5, "") -> 0 | G13: =IF($H$2>3,F13*$D$5, "") -> 0 | H13: =IF($H$2>4,G13*$D$5, "") -> 0
B14: Summer | D14: =(D4*2+D4*D5*11)/13/9*F4*G4 -> 0 | E14: =IF($H$2>1,D14*$D$5, "") -> 0 | F14: =IF($H$2>2,E14*$D$5, "") -> 0 | G14: =IF($H$2>3,F14*$D$5, "") -> 0 | H14: =IF($H$2>4,G14*$D$5, "") -> 0
A15: Key Pers | B15: AY | D15: 0 | E15: =IF($H$2>1,D15*$D$5, "") -> 0 | F15: =IF($H$2>2,E15*$D$5, "") -> 0 | G15: =IF($H$2>3,F15*$D$5, "") -> 0 | H15: =IF($H$2>4,G15*$D$5, "") -> 0
B16: Summer | D16: 0 | E16: =IF($H$2>1,D16*$D$5, "") -> 0 | F16: =IF($H$2>2,E16*$D$5, "") -> 0 | G16: =IF($H$2>3,F16*$D$5, "") -> 0 | H16: =IF($H$2>4,G16*$D$5, "") -> 0
A17: Key Pers | B17: AY | D17: 0 | E17: =IF($H$2>1,D17*$D$5, "") -> 0 | F17: =IF($H$2>2,E17*$D$5, "") -> 0 | G17: =IF($H$2>3,F17*$D$5, "") -> 0 | H17: =IF($H$2>4,G17*$D$5, "") -> 0
B18: Summer | D18: 0 | E18: =IF($H$2>1,D18*$D$5, "") -> 0 | F18: =IF($H$2>2,E18*$D$5, "") -> 0 | G18: =IF($H$2>3,F18*$D$5, "") -> 0 | H18: =IF($H$2>4,G18*$D$5, "") -> 0
C19: Total Key Personnel (Salary) | D19: =SUM(D9:D18) -> 0 | E19: =IF($H$2>1,SUM(E9:E18),"") -> 0 | F19: =IF($H$2>2,SUM(F9:F18),"") -> 0 | G19: =IF($H$2>3,SUM(G9:G18),"") -> 0 | H19: =IF($H$2>4,SUM(H9:H18),"") -> 0
A21: Fringe Benefits
C22: Key Personnel (32.75%) | D22: =D19*0.3275 -> 0 | E22: =IF($H$2>1, E19*0.3275, "") -> 0 | F22: =IF($H$2>2, F19*0.3275, "") -> 0 | G22: =IF($H$2>3, G19*0.3275, "") -> 0 | H22: =IF($H$2>4, H19*0.3275, "") -> 0
C23: Total Key Personnel (Fringe) | D23: =SUM(D22:D22) -> 0 | E23: =IF(H2>1,E22,"") -> 0 | F23: =IF(H2>2,F22,"") -> 0 | G23: =IF(H2>3,G22,"") -> 0 | H23: =IF(H2>4,H22,"") -> 0
A25: Student Wages | I25: Rate | J25: Hours | K25: Weeks | L25: # Students at this rate
C26: Student 1 | D26: =IF($L$26=0,IF($L$27>=1,$I$27*$J$27*$K$27,IF($L$27=0,IF($L$28>=1,$I$28*$J$28*$K$28,IF($L$28=0,IF($L$29>=1,$I$29*$J$29*$K$29,0),0)),0)),IF($L$26>=1,$I$26*$J$26*$K$26,0)) -> 0 | E26: =IF($H$2>1,D26*$D$5,"") -> 0 | F26: =IF($H$2>2,E26*$D$5,"") -> 0 | G26: =IF($H$2>3,F26*$D$5,"") -> 0 | H26: =IF($H$2>4,G26*$D$5,"") -> 0 | I26: 8.95 | J26: 10 | K26: 8 | L26: 0
C27: Student 2 | D27: =IF($L$26=0,IF($L$27>1,$I$27*$J$27*$K$27,IF($L$27=1,IF($L$28>=1,$I$28*$J$28*$K$28,IF($L$28=0,IF($L$29>=1,$I$29*$J$29*$K$29,0),0)),IF($L$27=0,IF($L$28>=2,$I$28*$J$28*$K$28,IF($L$28=1,IF($L$29>=1,$I$29*$J$29*$K$29,0),IF($L$28=0,IF($L$29>1,$I$29*$J$29*$K$29,0),0)))))),IF($L$26>=2,$I$26*$J$26*$K$26,IF($L$26=1,IF($L$27>=1,$I$27*$J$27*$K$27,IF($L$28>=1,$I$28*$J$28*$K$28,IF($L$29>=1,$I$29*$J$29*K$29,0))),0))) -> 0 | E27: =IF($H$2>1,D27*$D$5,"") -> 0 | F27: =IF($H$2>2,E27*$D$5,"") -> 0 | G27: =IF($H$2>3,F27*$D$5,"") -> 0 | H27: =IF($H$2>4,G27*$D$5,"") -> 0 | I27: 10.25 | J27: 10 | K27: 8 | L27: 0
C28: Student 3 | D28: =IF($L$26=0,IF($L$27>2,$I$27*$J$27*$K$27,IF($L$27=2,IF($L$28>=1,$I$28*$J$28*$K$28,IF($L$28=0,IF($L$29>=1,$I$29*$J$29*$K$29,0),0)),IF($L$27=1, IF($L$28>=2,$I$28*$J$28*$K$28,IF($L$28=1, IF($L$29>=1, $I$29*$J$29*$K$29,0),IF($L$28=0,IF($L$29>=2,$I$29*$J$29*$K$29,0)))),IF($L$27=0,IF($L$28>=3,$I$28*$J$28*$K$28,IF($L$29>=3,$I$29*$J$29*$K$29,IF($L$28=2,IF($L$29>=1,$I$29*$J$29*$K$29,IF($L$28=1,IF($L$29>=2,$I$29*$J$29*$K$29,0))),0))),0)))),IF($L$26>=3,$I$26*$J$26*$K$26,IF($L$26=2,IF($L$27>=1,$I$27*$J$27*$K$27, IF($L$28>=1,$I$28*$J$28*$K$28,IF($L$29>=1,$I$29*$J$29*$K$29,0))),IF($L$26=1, IF($L$27>=2,$I$27*$J$27*$K$27, IF($L$27=1, IF($L$28>=1, $I$28*$J$28*$K$28,IF($L$29>=1, $I$29*$J$29*$K$29,0)),IF($L$27=0,IF($L$28>=2,$I$28*$J$28*$K$28,IF($L$28=1,IF($L$29>=1, $I$29*$J$29*$K$29,0),IF($L$28=0, IF($L$29>=2, $I$29*$J$29*$K$29,0),0))),0))),0)))) -> 0 | E28: =IF($H$2>1,D28*$D$5,"") -> 0 | F28: =IF($H$2>2,E28*$D$5,"") -> 0 | G28: =IF($H$2>3,F28*$D$5,"") -> 0 | H28: =IF($H$2>4,G28*$D$5,"") -> 0 | I28: 11.3 | J28: 10 | K28: 8 | L28: 0
C29: Student 4 | D29: =IF($L$26=0,IF($L$27>3,$I$27*$J$27*$K$27,IF($L$27=3,IF($L$28>=1,$I$28*$J$28*$K$28,IF($L$28=0,IF($L$29>=1,$I$29*$J$29*$K$29,0),0)),IF($L$27=2, IF($L$28>=2,$I$28*$J$28*$K$28,IF($L$28=1, IF($L$29>=1, $I$29*$J$29*$K$29,0),IF($L$28=0,IF($L$29>=2,$I$29*$J$29*$K$29,0),0))),IF($L$27=1,IF($L$28>=3,$I$28*$J$28*$K$28,IF($L$28=2,IF($L$29>=1,$I$29*$J$29*$K$29,0),IF($L$28=1,IF($L$29>=2,$I$29*$J$29*$K$29,0),IF($L$28=0, IF($L$29>=3,$I$29*$J$29*$K$29,0),0)))),IF($L$27=0,IF($L$28>3,$I$28*$J$28*$K$28,IF($L$28=3, IF($L$29>=1,$I$29*$J$29*$K$29,0),IF($L$28=2, IF($L$29>=2,$I$29*$J$29*$K$29,0),IF($L$28=1, IF($L$29>=3, $I$29*$J$29*$K$29,0),IF($L$28=0, IF($L$29>=4, $I$29*$J$29*$K$29,0),0))))),0))))),IF($L$26>=4,$I$26*$J$26*$K$26,IF($L$26=3,IF($L$27=1,$I$27*$J$27*$K$27, IF($L$28=1,$I$28*$J$28*$K$28,IF($L$29=1,$I$29*$J$29*$K$29,0))),IF($L$26=2, IF($L$27>=2,$I$27*$J$27*$K$27, IF($L$27=1, IF($L$28>=1, $I$28*$J$28*$K$28,IF($L$29>=1, $I$29*$J$29*$K$29,0)),IF($L$27=0,IF($L$28>=2,$I$28*$J$28*$K$28,IF($L$28=1,IF($L$29>=1, $I$29*$J$29*$K$29,0),IF($L$28=0, IF($L$29>=2, $I$29*$J$29*$K$29,0),0))),0))),IF($L$26=1, IF($L$27>=3,$I$28*$J$28*$K$28, IF($L$27=2, IF($L$28>=1,$I$28*$J$28*$K$28, IF($L$29>=1, $I$29*$J$29*$K$29,0)),IF($L$27=1, IF($L$28>=2,$I$28*$J$28*$K$28, IF($L$28=1, IF($L$29>=1, $I$29*$J$29*$K$29,0), IF($L$28=0, IF($L$29>=2,$I$29*$J$29*$K$29,0),0))),IF($L$27=0, IF($L$28>=3,$I$28*$J$28*$K$28, IF($L$28=2, IF($L$29>=1,$I$29*$J$29*$K$29,0),IF($L$28=1, IF($L$29>=2,$I$29*$J$29*$K$29,0),IF($L$28=0, IF($L$29>=3,$I$29*$J$29*$K$29,0),0)))),0)))),0))))) -> 0 | E29: =IF($H$2>1,D29*$D$5,"") -> 0 | F29: =IF($H$2>2,E29*$D$5,"") -> 0 | G29: =IF($H$2>3,F29*$D$5,"") -> 0 | H29: =IF($H$2>4,G29*$D$5,"") -> 0 | I29: 19.79 | J29: 10 | K29: 8 | L29: 0
C30: Total Undergraduate Stipends | D30: =SUM(D26:D29) -> 0 | E30: =IF($H$2>1,SUM(E26:E29),"") -> 0 | F30: =IF($H$2>2,SUM(F26:F29),"") -> 0 | G30: =IF($H$2>3,SUM(G26:G29),"") -> 0 | H30: =IF($H$2>4,SUM(H26:H29),"") -> 0
J31: Total students = 4
A32: Travel
C33: Domestic Travel | D33: ='Travel Worksheet'!E19 -> 0 | E33: =IF(H2>1,'Travel Worksheet'!E35,"") -> 0 | F33: =IF(H2>2,'Travel Worksheet'!E51,"") -> 0 | G33: =IF(H2>3,'Travel Worksheet'!E67,"") -> 0 | H33: =IF(H2>4,'Travel Worksheet'!E83,"") -> 0
C34: Foreign Travel | D34: ='Travel Worksheet'!E100 -> 0 | E34: =IF(H2>1,'Travel Worksheet'!E116,"") -> 0 | F34: =IF(H2>2,'Travel Worksheet'!E132,"") -> 0 | G34: =IF(H2>3,'Travel Worksheet'!E132,"") -> 0 | H34: =IF(H2>4,'Travel Worksheet'!E164,"") -> 0
C35: Total Travel | D35: =SUM(D33:D34) -> 0 | E35: =IF($H$2>1,SUM(E33:E34),"") -> 0 | F35: =IF($H$2>2,SUM(F33:F34),"") -> 0 | G35: =IF($H$2>3,SUM(G33:G34),"") -> 0 | H35: =IF($H$2>4,SUM(H33:H34),"") -> 0
A37: Equipment (>$5,000)
C38: Equipment 1 | D38: 0 | E38: =IF($H$2>1,0,"") -> 0 | F38: =IF($H$2>2,0,"") -> 0 | G38: =IF($H$2>3,0,"") -> 0 | H38: =IF($H$2>4,0,"") -> 0
C39: Equipment 2 | D39: 0 | E39: =IF($H$2>1,0,"") -> 0 | F39: =IF($H$2>2,0,"") -> 0 | G39: =IF($H$2>3,0,"") -> 0 | H39: =IF($H$2>4,0,"") -> 0
C40: Equipment 3 | D40: 0 | E40: =IF($H$2>1,0,"") -> 0 | F40: =IF($H$2>2,0,"") -> 0 | G40: =IF($H$2>3,0,"") -> 0 | H40: =IF($H$2>4,0,"") -> 0
C41: Total Equipment | D41: =SUM(D38:D40) -> 0 | E41: =IF($H$2>1,SUM(E38:E40),"") -> 0 | F41: =IF($H$2>2,SUM(F38:F40),"") -> 0 | G41: =IF($H$2>3,SUM(G38:G40),"") -> 0 | H41: =IF($H$2>4,SUM(H38:H40),"") -> 0
A43: Supplies
C44: Supplies 1 | D44: 0 | E44: =IF($H$2>1,0,"") -> 0 | F44: =IF($H$2>2,0,"") -> 0 | G44: =IF($H$2>3,0,"") -> 0 | H44: =IF($H$2>4,0,"") -> 0
C45: Supplies 2 | D45: 0 | E45: =IF($H$2>1,0,"") -> 0 | F45: =IF($H$2>2,0,"") -> 0 | G45: =IF($H$2>3,0,"") -> 0 | H45: =IF($H$2>4,0,"") -> 0
C46: Supplies 3 | D46: 0 | E46: =IF($H$2>1,0,"") -> 0 | F46: =IF($H$2>2,0,"") -> 0 | G46: =IF($H$2>3,0,"") -> 0 | H46: =IF($H$2>4,0,"") -> 0
C47: Total Supplies | D47: =SUM(D44:D46) -> 0 | E47: =IF($H$2>1,SUM(E44:E46),"") -> 0 | F47: =IF($H$2>2,SUM(F44:F46),"") -> 0 | G47: =IF($H$2>3,SUM(G44:G46),"") -> 0 | H47: =IF($H$2>4,SUM(H44:H46),"") -> 0
A49: Other
C50: Other 1 | D50: 0 | E50: =IF($H$2>1,0,"") -> 0 | F50: =IF($H$2>2,0,"") -> 0 | G50: =IF($H$2>3,0,"") -> 0 | H50: =IF($H$2>4,0,"") -> 0
C51: Other 2 | D51: 0 | E51: =IF($H$2>1,0,"") -> 0 | F51: =IF($H$2>2,0,"") -> 0 | G51: =IF($H$2>3,0,"") -> 0 | H51: =IF($H$2>4,0,"") -> 0
C52: Other 3 | D52: 0 | E52: =IF($H$2>1,0,"") -> 0 | F52: =IF($H$2>2,0,"") -> 0 | G52: =IF($H$2>3,0,"") -> 0 | H52: =IF($H$2>4,0,"") -> 0
C53: Total Other | D53: =SUM(D50:D52) -> 0 | E53: =IF($H$2>1,SUM(E50:E52),"") -> 0 | F53: =IF($H$2>2,SUM(F50:F52),"") -> 0 | G53: =IF($H$2>3,SUM(G50:G52),"") -> 0 | H53: =IF($H$2>4,SUM(H50:H52),"") -> 0
A55: Consultants
C56: Consultant 1 | D56: 0 | E56: =IF($H$2>1,0,"") -> 0 | F56: =IF($H$2>2,0,"") -> 0 | G56: =IF($H$2>3,0,"") -> 0 | H56: =IF($H$2>4,0,"") -> 0
C57: Consultant 2 | D57: 0 | E57: =IF($H$2>1,0,"") -> 0 | F57: =IF($H$2>2,0,"") -> 0 | G57: =IF($H$2>3,0,"") -> 0 | H57: =IF($H$2>4,0,"") -> 0
C58: Consultant 3 | D58: 0 | E58: =IF($H$2>1,0,"") -> 0 | F58: =IF($H$2>2,0,"") -> 0 | G58: =IF($H$2>3,0,"") -> 0 | H58: =IF($H$2>4,0,"") -> 0
C59: Total Consultants | D59: =SUM(D56:D58) -> 0 | E59: =IF($H$2>1,SUM(E56:E58),"") -> 0 | F59: =IF($H$2>2,SUM(F56:F58),"") -> 0 | G59: =IF($H$2>3,SUM(G56:G58),"") -> 0 | H59: =IF($H$2>4,SUM(H56:H58),"") -> 0
A61: Total Direct Costs | D61: =D19+D23+D30+D35+D41+D47+D53+D59 -> 0 | E61: =IF($H$2>1,E19+E23+E30+E35+E41+E47+E53+E59,"") -> 0 | F61: =IF($H$2>2,F19+F23+F30+F35+F41+F47+F53+F59,"") -> 0 | G61: =IF($H$2>3,G19+G23+G30+G35+G41+G47+G53+G59,"") -> 0 | H61: =IF($H$2>4,H19+H23+H30+H35+H41+H47+H53+H59,"") -> 0
A62: Total Indirect Costs (48.5% of S&W only) | D62: =(D19+D30)*0.485 -> 0 | E62: =IF($H$2>1,(E19+E30)*0.485,"") -> 0 | F62: =IF($H$2>2,(F19+F30)*0.485,"") -> 0 | G62: =IF($H$2>3,(G19+G30)*0.485,"") -> 0 | H62: =IF($H$2>4,(H19+H30)*0.485,"") -> 0
A63: Total Costs | D63: =D61+D62 -> 0 | E63: =IF($H$2>1,SUM(E61:E62),"") -> 0 | F63: =IF($H$2>2,SUM(F61:F62),"") -> 0 | G63: =IF($H$2>3,SUM(G61:G62),"") -> 0 | H63: =IF($H$2>4,SUM(H61:H62),"") -> 0

Sheet Equipment Grant
A1: Names
A2: PI 1:
A3: PI 2:
C5: Year 1
A6: Equipment (>$5,000)
B7: Equipment 1 | C7: 0
B8: Equipment 2 | C8: 0
B9: Equipment 3 | C9: 0
B10: Equipment 4 | C10: 0
B11: Equipment 5 | C11: 0
B12: Total Equipment | C12: =SUM(C7:C11) -> 0
A14: Supplies
B15: Supplies 1 | C15: 0
B16: Supplies 2 | C16: 0
B17: Supplies 3 | C17: 0
B18: Supplies 4 | C18: 0
B19: Supplies 5 | C19: 0
B20: Total Supplies | C20: =SUM(C15:C19) -> 0
A22: Service Contract | C22: 0
A24: Other
B25: Other 1 | C25: 0
B26: Other 2 | C26: 0
B27: Other 3 | C27: 0
B28: Other 4 | C28: 0
B29: Other 5 | C29: 0
B30: Total Other | C30: =SUM(C25:C29) -> 0
A33: Total Direct Costs | C33: =C12+C20+C22+C30 -> 0
A34: Total Indirect Costs (Normally, N/A) | C34: 0
A35: Total Costs | C35: =C33+C34 -> 0

Sheet Travel Worksheet
A1: TRAVEL BUDGET
A4: Please complete fields hightlighted in yellow to calculate expenses.
A6: DOMESTIC TRAVEL YEAR 1
B8: DESTINATION:
B9: PURPOSE:
B11: # Travelers | D11: Days
A12: 35 | B12: Per Day Per Diem | E12: =A12*A11*C11 -> 0
A13: 0 | B13: Per Night Hotel | E13: =A11*(C11)*A13*1.2 -> 0
A14: 0 | B14: Registration | E14: =A11*A14 -> 0
A15: 0 | B15: Mileage @$.5/mile | E15: =A15*A11 -> 0
A16: 0 | B16: Ground Transportation | E16: =A16*A11 -> 0
A17: 0 | B17: Rental Car, per day | E17: =A17*A11*C11 -> 0
A18: 0 | B18: Airfare | E18: =A18*A11 -> 0
B19: Total Estimated Trip Cost | E19: =SUM(E12:E18) -> 0
A22: DOMESTIC TRAVEL YEAR 2
B24: DESTINATION:
B25: PURPOSE:
B27: # Travelers | D27: Days
A28: 35 | B28: Per Day Per Diem | E28: =A28*A27*C27 -> 0
A29: 0 | B29: Per Night Hotel | E29: =A27*(C27)*A29*1.2 -> 0
A30: 0 | B30: Registration | E30: =A27*A30 -> 0
A31: 0 | B31: Mileage @$.5/mile | E31: =A31*A27 -> 0
A32: 0 | B32: Ground Transportation | E32: =A32*A27 -> 0
A33: 0 | B33: Rental Car, per day | E33: =A33*A27*C27 -> 0
A34: 0 | B34: Airfare | E34: =A34*A27 -> 0
B35: Total Estimated Trip Cost | E35: =SUM(E28:E34) -> 0
A38: DOMESTIC TRAVEL YEAR 3
B40: DESTINATION:
B41: PURPOSE:
B43: # Travelers | D43: Days
A44: 35 | B44: Per Day Per Diem | E44: =A44*A43*C43 -> 0
A45: 0 | B45: Per Night Hotel | E45: =A43*(C43)*A45*1.2 -> 0
A46: 0 | B46: Registration | E46: =A43*A46 -> 0
A47: 0 | B47: Mileage @$.5/mile | E47: =A47*A43 -> 0
A48: 0 | B48: Ground Transportation | E48: =A48*A43 -> 0
A49: 0 | B49: Rental Car, per day | E49: =A49*A43*C43 -> 0
A50: 0 | B50: Airfare | E50: =A50*A43 -> 0
B51: Total Estimated Trip Cost | E51: =SUM(E44:E50) -> 0
A54: DOMESTIC TRAVEL YEAR 4
B56: DESTINATION:
B57: PURPOSE:
B59: # Travelers | D59: Days
A60: 35 | B60: Per Day Per Diem | E60: =A60*A59*C59 -> 0
A61: 0 | B61: Per Night Hotel | E61: =A59*(C59)*A61*1.2 -> 0
A62: 0 | B62: Registration | E62: =A59*A62 -> 0
A63: 0 | B63: Mileage @$.5/mile | E63: =A63*A59 -> 0
A64: 0 | B64: Ground Transportation | E64: =A64*A59 -> 0
A65: 0 | B65: Rental Car, per day | E65: =A65*A59*C59 -> 0
A66: 0 | B66: Airfare | E66: =A66*A59 -> 0
B67: Total Estimated Trip Cost | E67: =SUM(E60:E66) -> 0
A70: DOMESTIC TRAVEL YEAR 5
B72: DESTINATION:
B73: PURPOSE:
B75: # Travelers | D75: Days
A76: 35 | B76: Per Day Per Diem | E76: =A76*A75*C75 -> 0
A77: 0 | B77: Per Night Hotel | E77: =A75*(C75)*A77*1.2 -> 0
A78: 0 | B78: Registration | E78: =A75*A78 -> 0
A79: 0 | B79: Mileage @$.5/mile | E79: =A79*A75 -> 0
A80: 0 | B80: Ground Transportation | E80: =A80*A75 -> 0
A81: 0 | B81: Rental Car, per day | E81: =A81*A75*C75 -> 0
A82: 0 | B82: Airfare | E82: =A82*A75 -> 0
B83: Total Estimated Trip Cost | E83: =SUM(E76:E82) -> 0
A87: FOREIGN TRAVEL YEAR 1
B89: DESTINATION:
B90: PURPOSE:
B92: # Travelers | D92: Days
A93: 35 | B93: Per Day Per Diem | E93: =A93*A92*C92 -> 0
A94: 0 | B94: Per Night Hotel | E94: =A92*(C92)*A94*1.2 -> 0
A95: 0 | B95: Registration | E95: =A92*A95 -> 0
A96: 0 | B96: Mileage @$.5/mile | E96: =A96*A92 -> 0
A97: 0 | B97: Ground Transportation | E97: =A97*A92 -> 0
A98: 0 | B98: Rental Car, per day | E98: =A98*A92*C92 -> 0
A99: 0 | B99: Airfare | E99: =A99*A92 -> 0
B100: Total Estimated Trip Cost | E100: =SUM(E93:E99) -> 0
A103: FOREIGN TRAVEL YEAR 2
B105: DESTINATION:
B106: PURPOSE:
B108: # Travelers | D108: Days
A109: 35 | B109: Per Day Per Diem | E109: =A109*A108*C108 -> 0
A110: 0 | B110: Per Night Hotel | E110: =A108*(C108)*A110*1.2 -> 0
A111: 0 | B111: Registration | E111: =A108*A111 -> 0
A112: 0 | B112: Mileage @$.5/mile | E112: =A112*A108 -> 0
A113: 0 | B113: Ground Transportation | E113: =A113*A108 -> 0
A114: 0 | B114: Rental Car, per day | E114: =A114*A108*C108 -> 0
A115: 0 | B115: Airfare | E115: =A115*A108 -> 0
B116: Total Estimated Trip Cost | E116: =SUM(E109:E115) -> 0
A119: FOREIGN TRAVEL YEAR 3
B121: DESTINATION:
B122: PURPOSE:
B124: # Travelers | D124: Days
A125: 35 | B125: Per Day Per Diem | E125: =A125*A124*C124 -> 0
A126: 0 | B126: Per Night Hotel | E126: =A124*(C124)*A126*1.2 -> 0
A127: 0 | B127: Registration | E127: =A124*A127 -> 0
A128: 0 | B128: Mileage @$.5/mile | E128: =A128*A124 -> 0
A129: 0 | B129: Ground Transportation | E129: =A129*A124 -> 0
A130: 0 | B130: Rental Car, per day | E130: =A130*A124*C124 -> 0
A131: 0 | B131: Airfare | E131: =A131*A124 -> 0
B132: Total Estimated Trip Cost | E132: =SUM(E125:E131) -> 0
A135: FOREIGN TRAVEL YEAR 4
B137: DESTINATION:
...
