Workbook
Name Query_from_DanaDWStaging: 'FY07 TTL Revenue Master'!#REF!
Name Query_from_Profiles: 'FY07 TTL Revenue Master'!$A$6:$AB$494
Name Query_from_Profiles_1: 'Charter Minnea St. Paul Wrk'!$A$6:$R$67
Name Query_from_Profiles_1: 'Charter State Work'!$A$6:$R$136
Name Query_from_Profiles_1: 'District St Wrk'!$A$6:$R$346
Name Query_from_Profiles_1: 'Minnea St Paul Dist wrk'!$A$6:$R$10
Name Query_from_ProfilesRevenue: 'FY07 TTL Revenue Master'!$A$6:$AB$493

Sheet Legend
A2: Legend
D3: Local
D5: State
D7: Federal
D9: Other
D11: Indeterminate
D13: Minneapolis
D15: St. Paul
A18: Source | B18: Minnesota Department of Education
A20: All files are "read only" and based on data collections from the Minnesota Department of Education.
A21: The conclusions reached in this document are those of the author(s) and do not necessarily represent those
A22: of Ball State University.

Sheet Figures 1,2,4
A1: Figure 1 | K1: Figure 2
A2: Minnesota (2006-07) | B2: Statewide | D2: Statewide Weighted for Charter Enrollment | F2: Minneapolis | H2: St. Paul | L2: District | M2: Charter | N2: Difference
A3: Per-Pupil Revenue | K3: State | L3: 11250.462 | M3: 11081.364 | N3: 169.09764
A4: District | B4: =B14 -> 11250.462 | D4: 12720 | F4: =F14 -> 15117.723 | H4: =H14 -> 13509.847 | K4: Statewide Weighted | L4: 12720 | M4: 11081 | N4: 1639
A5: Charter | B5: =C14 -> 11081.364 | D5: 11081 | F5: =G14 -> 11929.984 | H5: =I14 -> 11700.126 | K5: Minneapolis | L5: 15117.723 | M5: 11929.984 | N5: 3187.7392
A6: Difference | B6: =B4-B5 -> 169.09764 | D6: 1639 | F6: =F4-F5 -> 3187.7392 | H6: =H4-H5 -> 1809.7214 | K6: St. Paul | L6: 13509.847 | M6: 11700.126 | N6: 1809.7214
B7: =B6/B4 -> 0.015030284 | D7: 0.129 | F7: =F6/F4 -> 0.21086107 | H7: =H6/H4 -> 0.13395573
A8: Per-Pupil Revenue by Source | B8: District | C8: Charter | D8: District | E8: Charter | F8: District | G8: Charter | H8: District | I8: Charter
A9: Federal | B9: ='District St Wrk'!S348 -> 617.29505 | C9: ='Charter State Work'!S138 -> 1039.2773 | D9: 1080 | E9: 1039.2773 | F9: ='Minnea St Paul Dist wrk'!S8 -> 1729.2229 | G9: ='Charter Minnea St. Paul Wrk'!S37 -> 1211.4557 | H9: ='Minnea St Paul Dist wrk'!S12 -> 1453.0301 | I9: ='Charter Minnea St. Paul Wrk'!S69 -> 975.52296
A10: State | B10: ='District St Wrk'!Q348 -> 7656.899 | C10: ='Charter State Work'!Q138 -> 9429.9787 | D10: 8646 | E10: 9429.9787 | F10: ='Minnea St Paul Dist wrk'!Q8 -> 9750.1383 | G10: ='Charter Minnea St. Paul Wrk'!Q37 -> 9910.712 | H10: ='Minnea St Paul Dist wrk'!Q12 -> 9772.058 | I10: ='Charter Minnea St. Paul Wrk'!Q69 -> 10216.018
A11: Local | B11: ='District St Wrk'!M348 -> 2467.3583 | C11: ='Charter State Work'!M138 -> 488.59691 | D11: 2689 | E11: 488.59691 | F11: ='Minnea St Paul Dist wrk'!M8 -> 3461.8077 | G11: ='Charter Minnea St. Paul Wrk'!M37 -> 780.94731 | H11: ='Minnea St Paul Dist wrk'!M12 -> 2328.0031 | I11: ='Charter Minnea St. Paul Wrk'!M69 -> 453.05269
A12: Other | B12: ='District St Wrk'!T348 -> 658.30959 | C12: ='Charter State Work'!T138 -> 128.73442 | D12: 535 | E12: 128.73442 | F12: ='Minnea St Paul Dist wrk'!T8 -> 475.10942 | G12: ='Charter Minnea St. Paul Wrk'!T37 -> 34.247547 | H12: ='Minnea St Paul Dist wrk'!T12 -> 305.80474 | I12: ='Charter Minnea St. Paul Wrk'!T69 -> 55.531566
A13: Indeterminate | B13: ='District St Wrk'!V348 -> -149.4001 | C13: ='Charter State Work'!V138 -> -5.2231697 | D13: -230 | E13: -5.2231697 | F13: ='Minnea St Paul Dist wrk'!V8 -> -298.55559 | G13: ='Charter Minnea St. Paul Wrk'!V37 -> -7.3789752 | H13: ='Minnea St Paul Dist wrk'!V12 -> -349.0491 | I13: ='Charter Minnea St. Paul Wrk'!V69 -> 0
A14: Total | B14: =SUM(B9:B13) -> 11250.462 | C14: =SUM(C9:C13) -> 11081.364 | D14: 12720 | E14: 11081.364 | F14: =SUM(F9:F13) -> 15117.723 | G14: =SUM(G9:G13) -> 11929.984 | H14: =SUM(H9:H13) -> 13509.847 | I14: =SUM(I9:I13) -> 11700.126
A15: Enrollment
A16: District | B16: ='District St Wrk'!J346 -> 814733.22 | D16: n/a | F16: ='Minnea St Paul Dist wrk'!J6 -> 39479.31 | H16: ='Minnea St Paul Dist wrk'!J10 -> 42379.85
B17: =B16/(B16+B18) -> 0.97159836 | D17: n/a | F17: =F16/(F16+F18) -> 0.85604008 | H17: =H16/(H16+H18) -> 0.87904738
A18: Charter | B18: ='Charter State Work'!J136 -> 23816.18 | D18: n/a | F18: ='Charter Minnea St. Paul Wrk'!J35 -> 6639.22 | H18: ='Charter Minnea St. Paul Wrk'!J67 -> 5831.26
B19: =B18/(B16+B18) -> 0.028401642 | D19: n/a | F19: =F18/(F16+F18) -> 0.14395992 | H19: =H18/(H16+H18) -> 0.12095262
A20: Number of Charters | B20: 129 | D20: n/a | F20: 29 | H20: 27
A21: Total Revenue
A22: District | B22: ='District St Wrk'!W347 -> 9.166125e+09 | D22: n/a | F22: ='Minnea St Paul Dist wrk'!W7 -> 5.9683726e+08 | H22: ='Minnea St Paul Dist wrk'!W11 -> 5.7254528e+08
B23: =B22/B26 -> 0.9720133 | D23: n/a | F23: =F22/F26 -> 0.88283914 | H23: =H22/H26 -> 0.89352453
A24: Charter | B24: ='Charter State Work'!W137 -> 2.6391576e+08 | D24: n/a | F24: ='Charter Minnea St. Paul Wrk'!W36 -> 79205785 | H24: ='Charter Minnea St. Paul Wrk'!W68 -> 68226474
B25: =B24/B26 -> 0.027986705 | D25: n/a | F25: =F24/F26 -> 0.11716086 | H25: =H24/H26 -> 0.10647547
A26: Total | B26: =B22+B24 -> 9.4300407e+09 | D26: n/a | F26: =F22+F24 -> 6.7604305e+08 | H26: =H22+H24 -> 6.4077176e+08
A27: Percentage of Revenue by Source | B27: District | C27: Charter | D27: District | E27: Charter | F27: District | G27: Charter | H27: District | I27: Charter | K27: Figure 4
A28: Federal | B28: =B9/B14 -> 0.054868419 | C28: =C9/C14 -> 0.093786046 | D28: 0.08490566 | E28: 0.093786046 | F28: =F9/F14 -> 0.11438382 | G28: =G9/G14 -> 0.10154714 | H28: =H9/H14 -> 0.10755341 | I28: =I9/I14 -> 0.083377136 | L28: Federal | M28: State | N28: Local | O28: Other | P28: Indeterminate
A29: State | B29: =B10/B14 -> 0.6805853 | C29: =C10/C14 -> 0.85097634 | D29: 0.67971698 | E29: 0.85097634 | F29: =F10/F14 -> 0.64494755 | G29: =G10/G14 -> 0.83073978 | H29: =H10/H14 -> 0.72332855 | I29: =I10/I14 -> 0.87315459 | K29: Statewide District | L29: 617.29505 | M29: 7656.899 | N29: 2467.3583 | O29: 658.30959 | P29: -149.4001
A30: Local | B30: =B11/B14 -> 0.21931174 | C30: =C11/C14 -> 0.044091766 | D30: 0.21139937 | E30: 0.044091766 | F30: =F11/F14 -> 0.22899003 | G30: =G11/G14 -> 0.065460887 | H30: =H11/H14 -> 0.17231899 | I30: =I11/I14 -> 0.038722036 | K30: Statewide Charter | L30: 1039.2773 | M30: 9429.9787 | N30: 488.59691 | O30: 128.73442 | P30: -5.2231697
A31: Other | B31: =B12/B14 -> 0.058514006 | C31: =C12/C14 -> 0.011617199 | D31: 0.042059748 | E31: 0.011617199 | F31: =F12/F14 -> 0.031427314 | G31: =G12/G14 -> 0.002870712 | H31: =H12/H14 -> 0.022635692 | I31: =I12/I14 -> 0.0047462368 | K31: Statewide Weighted | L31: 1080 | M31: 8646 | N31: 2689 | O31: 535 | P31: -230
A32: Indeterminate | B32: =B13/B14 -> -0.013279464 | C32: =C13/C14 -> -0.00047134718 | D32: -0.018081761 | E32: -0.00047134718 | F32: =F13/F14 -> -0.019748715 | G32: =G13/G14 -> -0.00061852351 | H32: =H13/H14 -> -0.025836643 | I32: =I13/I14 -> 0 | K32: Minneapolis District | L32: 1729.2229 | M32: 9750.1383 | N32: 3461.8077 | O32: 475.10942 | P32: -298.55559
A33: Change in district school funding if subjected to charter funding structure | K33: Minneapolis Charter | L33: 1211.4557 | M33: 9910.712 | N33: 780.94731 | O33: 34.247547 | P33: -7.3789752
B34: (137.7 million) | F34: ($125.8 million) | H34: (76.6 million) | K34: St. Paul District | L34: 1453.0301 | M34: 9772.058 | N34: 2328.0031 | O34: 305.80474 | P34: -349.0491
B35: =B6*B16 -> 1.3776946e+08 | F35: =F6*F16 -> 1.2584974e+08 | H35: =H6*H16 -> 76695720 | K35: St. Paul Charter | L35: 975.52296 | M35: 10216.018 | N35: 453.05269 | O35: 55.531566 | P35: 0
A36: Number of schools based only on those schools open during the FY07 school year and received funds
A37: for operations.

Sheet Figure 3
A1: State Charter School Policies
A2: Figure 3
A3: State Policies | B3: Yes | C3: No | D3: Partial
A4: Charter schools received their funding directly from the state | B4: X
A5: Charter schools are eligible for local funding | D5: X1
A6: Cap on funding a charter school can receive | C6: X
A7: District public school receive differential funding (e.g. more funding for 9-12 vs. K-8 schools) | B7: X
A8: Charter schools receive differential funding | B8: X
A9: State allows districts to withhold funding from charter schools for providing adminstrative services | C9: X
A10: State "holds harmless" ditrict funding for charter enrollment | C10: X
A11: School is considered LEA if authorized by non-district organization | B11: X
A12: School is considered LEA if authorized by district | B12: X
A13: Cap on number of charter schools | C13: X2
A14: Cap on number of charters schools authorized per year | C14: X
A15: Cap on number of studens attending charter schools | C15: X
A16: Charter schools have an open enrollment policy | B16: X
A18: 1. Charter schools receive funding equal to the statewide average property tax amount and a minimal amount of additional equalization funding to offset the fiscal impact of district excess levy referenda. However, these additional revenues do not address the disparity in local funding between charter schools and district schools in areas like the Twin Cities.
A19: 2. Minnesota allows the State Department of Education, public and private universities and community colleges, non-profit organizations with assets of at least $2 million, and local public school districts to sponsor an unleimited number of schools with an initial charter term of up to three years.
A20: 3. Minnesota charter schools are available to all students in the state. While admissions prerequisiets are not permitted, charter schools can provide preference for enrollmetn to the siblings of current students and residents.

Sheet Figure 5
C2: Statewide District | D2: Statewide Charter
A3: Percentage of stuents eligible for free or reduced price lunch | C3: 0.302 | D3: 0.533
A4: Percentage of schools eligible for Title 1 | C4: 0.332 | D4: 0.497
A5: Percent of students by school type
B6: Primary (K-5) | C6: 0.452 | D6: 0.504
B7: Middle (6-8) | C7: 0.184 | D7: 0.071
B8: High (9-12) | C8: 0.334 | D8: 0.27
B9: Other (K-12,K-8, etc.) | C9: 0.029 | D9: 0.156

Sheet Figure 6
A1: Figure 6: State Scorecard
B2: Findings | C2: Minnesota | E2: Use the following options only
A3: Federal Funding | B3: Charters have access to federal funds according to state statutes (Yes = black, No = white)* | C3: Y | E3: Y
B4: Percentage of federal revenue equals percentage of total enrollment for charter schools (<, >, or =) | C4: > | E4: P
A5: State Funding | B5: Charters have access to state funds according to state statutes (Yes = black, No = white) | C5: Y | E5: N
B6: Percentage of state revenue equals percentage of total enrollment for charter schools (<, >, or =) | C6: >
A7: Local Funding | B7: Charters have access to local funds according to state statutes (Yes = black, No = white) | C7: Y
B8: Percentage of local revenue equals percentage of total enrollment for charter schools (<, >, or =) | C8: <
A9: Facilities Funding | B9: Charters have access to facilities funds according to state statutes (Yes = black, No = white) | C9: Y
B10: Percentage of facilities revenue equals percentage of total enrollment for charter schools (<, >, or =) | C10: NA
A11: Data Availability | B11: State provides detailed, public data on federal, state, local and other revenues for district schools (Yes = black, Partial = grey, No = white) | C11: Y
B12: State provides detailed, public data on federal, state, local and other revenues for charter schools (Yes = black, Partial = grey, No = white) | C12: Y
A13: Funding Formula | B13: Charters are treated as LEAs for funding purposes (Yes = black, Partial = grey, No = white) | C13: Y
B14: State funds student (black) or the LEA (grey) | C14: S | E14: S | F14: L | H14: Use these options for the query to the left only (B18)
B15: State funding formula is fair and equitable (Yes = black, No = white | C15: N
A17: * For this finding, No could indicate that the statue is silent or that it denies access.

Sheet FY07 TTL Revenue Master
F1: Click here for Definitions
A2: Economic Development Region Number | B2: Economic Development Region | C2: District Type | D2: County Number | E2: County Name | F2: Total Revenues FY07 | G2: District Number | J2: District ADM Served Plus Tuitioned Out | K2: General Fund Revenues | T2: Other Funds Revenues | X2: Grand Total Revenue for All Funds | Y2: Funds 01-07 Total Revenues
K3: Local Sources | N3: State Sources | R3: Federal Sources | S3: Fund 01 Total Revenue | T3: Local, State and Federal Sources | Y3: Local Sources | AA3: State Sources | AB3: Federal Sources
H4: Charter | I4: Charter Location | K4: Property Taxes | L4: Other | M4: Total Local Sources | N4: General Education Aid | O4: Special Education Aid | P4: All Other State Aid | Q4: Total State Sources | R4: Federal | T4: Food Service | U4: Community Service | V4: Building Construction | W4: Debt Service | Y4: Property Taxes | Z4: Other | AG4: deduct from community service fund | AJ4: deduct from community service fund | AO4: Other funds revenues distributed by Local Other State and Federal
F5: Counties and Districts | K5: 1. | L5: 2. You may need to treat this as local to align with Dave's FY03 data | M5: 3. | N5: 4. | O5: 5. | P5: 6. | Q5: 7. | R5: 8. | S5: 9. | T5: 10. | U5: 11. | V5: 12. | W5: 13. | X5: 14. | Y5: 15. | Z5: 16. | AA5: 17. | AB5: 18. | AC5: dat_yer | AD5: NUMBER | AE5: TYPE | AF5: NAME | AG5: Community Service Fund Revenue, Early Childhood Programs | AH5: TYPE | AI5: NAME | AJ5: ABE_AdltDisbld | AK5: Early Childhood Reduction | AL5: ABE Reduction | AO5: Local | AP5: Other | AQ5: State | AR5: Federal
A6: 3 | B6: Northeast Minnesota | C6: 01 | D6: 1 | E6: Aitkin | F6: AITKIN PUBLIC SCHOOL DISTRICT | G6: 0001 | J6: 1322.2 | K6: 613626 | L6: 1325974 | M6: 1939600 | N6: 8539952 | O6: 679449 | P6: 52813 | Q6: 9272214 | R6: 255760 | S6: 11467574 | T6: 589084 | U6: 266585 | V6: 0 | W6: 235402 | X6: 12558645 | Y6: 796996 | Z6: 1895424 | AA6: 9350914 | AB6: 515311 | AC6: 06-07 | AD6: 1 | AE6: 1 | AF6: AITKIN PUBLIC SCHOOL DISTRICT | AG6: 98691.4 | AH6: 1 | AI6: AITKIN PUBLIC SCHOOL DISTRICT | AJ6: 109867.98 | AK6: =AG6*AM6 -> -98691.4 | AL6: =AJ6*AM6 -> -109867.98 | AM6: -1 | AO6: =Y6-K6 -> 183370 | AP6: =Z6-L6 -> 569450 | AQ6: =AA6-Q6 -> 78700 | AR6: =AB6-R6 -> 259551
A7: 11 | B7: Twin Cities Metropolitan Area | C7: 03 | D7: 27 | E7: Hennepin | F7: MINNEAPOLIS PUBLIC SCHOOL DIST. | G7: 0001 | H7: District | I7: Minneapolis | J7: 39479.31 | K7: 58005565 | L7: 20520348 | M7: 78525913 | N7: 293589390 | O7: 49228337 | P7: 18490543 | Q7: 361308270 | R7: 52989194 | S7: 492823377 | T7: 14321379 | U7: 24987946 | V7: 5969817 | W7: 70521510 | X7: 608624030 | Y7: 116149433 | Z7: 39277340 | AA7: 384928731 | AB7: 68268526 | AC7: 06-07 | AD7: 1 | AE7: 3 | AF7: MINNEAPOLIS PUBLIC SCHOOL DIST. | AG7: 4444620.9 | AH7: 3 | AI7: MINNEAPOLIS PUBLIC SCHOOL DIST. | AJ7: 7342147.7 | AK7: =AG7*AM7 -> -4444620.9 | AL7: =AJ7*AM7 -> -7342147.7 | AM7: -1 | AO7: =Y7-K7 -> 58143868 | AP7: =Z7-L7 -> 18756992 | AQ7: =AA7-Q7 -> 23620461 | AR7: =AB7-R7 -> 15279332
A8: 3 | B8: Northeast Minnesota | C8: 01 | D8: 1 | E8: Aitkin | F8: HILL CITY PUBLIC SCHOOL DISTRICT | G8: 0002 | J8: 314.26 | K8: 59861 | L8: 422365 | M8: 482226 | N8: 2659597 | O8: 182721 | P8: 6745 | Q8: 2849063 | R8: 145220 | S8: 3476509 | T8: 146067 | U8: 60528 | V8: 540 | W8: 362730 | X8: 4046376 | Y8: 341788 | Z8: 507664 | AA8: 2965150 | AB8: 231774 | AC8: 06-07 | AD8: 2 | AE8: 1 | AF8: HILL CITY PUBLIC SCHOOL DISTRICT | AG8: 24582.72 | AH8: 1 | AI8: HILL CITY PUBLIC SCHOOL DISTRICT | AJ8: 0 | AK8: =AG8*AM8 -> -24582.72 | AL8: =AJ8*AM8 -> 0 | AM8: -1 | AO8: =Y8-K8 -> 281927 | AP8: =Z8-L8 -> 85299 | AQ8: =AA8-Q8 -> 116087 | AR8: =AB8-R8 -> 86554
A9: 3 | B9: Northeast Minnesota | C9: 01 | D9: 1 | E9: Aitkin | F9: MCGREGOR PUBLIC SCHOOL DISTRICT | G9: 0004 | J9: 421.83 | K9: 362632 | L9: 571834 | M9: 934466 | N9: 3626076 | O9: 220535 | P9: 90345 | Q9: 3936956 | R9: 400799 | S9: 5272221 | T9: 237907 | U9: 146635 | V9: 0 | W9: 750977 | X9: 6407741 | Y9: 1093875 | Z9: 741527 | AA9: 4047284 | AB9: 525055 | AC9: 06-07 | AD9: 4 | AE9: 1 | AF9: MCGREGOR PUBLIC SCHOOL DISTRICT | AG9: 33513.61 | AH9: 1 | AI9: MCGREGOR PUBLIC SCHOOL DISTRICT | AJ9: 0 | AK9: =AG9*AM9 -> -33513.61 | AL9: =AJ9*AM9 -> 0 | AM9: -1 | AO9: =Y9-K9 -> 731243 | AP9: =Z9-L9 -> 169693 | AQ9: =AA9-Q9 -> 110328 | AR9: =AB9-R9 -> 124256
A10: 11 | B10: Twin Cities Metropolitan Area | C10: 03 | D10: 19 | E10: Dakota | F10: SOUTH ST. PAUL PUBLIC SCHOOL DIST. | G10: 0006 | J10: 3331.77 | K10: 4375528 | L10: 1428160 | M10: 5803688 | N10: 21969776 | O10: 2395108 | P10: 590260 | Q10: 24955144 | R10: 1212734 | S10: 31971566 | T10: 1513869 | U10: 2039417 | V10: 0 | W10: 2582813 | X10: 38107665 | Y10: 6668375 | Z10: 3819649 | AA10: 25722047 | AB10: 1897594 | AC10: 06-07 | AD10: 6 | AE10: 3 | AF10: SOUTH ST. PAUL PUBLIC SCHOOL DIST. | AG10: 529225.97 | AH10: 3 | AI10: SOUTH ST. PAUL PUBLIC SCHOOL DIST. | AJ10: 429155.35 | AK10: =AG10*AM10 -> -529225.97 | AL10: =AJ10*AM10 -> -429155.35 | AM10: -1 | AO10: =Y10-K10 -> 2292847 | AP10: =Z10-L10 -> 2391489 | AQ10: =AA10-Q10 -> 766903 | AR10: =AB10-R10 -> 684860
A11: 11 | B11: Twin Cities Metropolitan Area | C11: 01 | D11: 2 | E11: Anoka | F11: ANOKA-HENNEPIN PUBLIC SCHOOL DIST. | G11: 0011 | J11: 41062.22 | K11: 43956546 | L11: 16656073 | M11: 60612619 | N11: 261189813 | O11: 32332020 | P11: 8770426 | Q11: 302292259 | R11: 12194021 | S11: 375098899 | T11: 17386532 | U11: 18176536 | V11: 378597 | W11: 23642958 | X11: 434683523 | Y11: 67622629 | Z11: 40522729 | AA11: 308838462 | AB11: 17699703 | AC11: 06-07 | AD11: 11 | AE11: 1 | AF11: ANOKA-HENNEPIN PUBLIC SCHOOL DIST. | AG11: 3155425.1 | AH11: 1 | AI11: ANOKA-HENNEPIN PUBLIC SCHOOL DIST. | AJ11: 2883706.4 | AK11: =AG11*AM11 -> -3155425.1 | AL11: =AJ11*AM11 -> -2883706.4 | AM11: -1 | AO11: =Y11-K11 -> 23666083 | AP11: =Z11-L11 -> 23866656 | AQ11: =AA11-Q11 -> 6546203 | AR11: =AB11-R11 -> 5505682
A12: 11 | B12: Twin Cities Metropolitan Area | C12: 01 | D12: 2 | E12: Anoka | F12: CENTENNIAL PUBLIC SCHOOL DISTRICT | G12: 0012 | J12: 6985.42 | K12: 5921669 | L12: 2129295 | M12: 8050964 | N12: 45247529 | O12: 6124782 | P12: 162398 | Q12: 51534709 | R12: 1658177 | S12: 61243850 | T12: 2739209 | U12: 2762687 | V12: 0 | W12: 11144656 | X12: 77890403 | Y12: 14114841 | Z12: 7670914 | AA12: 53873080 | AB12: 2231568 | AC12: 06-07 | AD12: 12 | AE12: 1 | AF12: CENTENNIAL PUBLIC SCHOOL DISTRICT | AG12: 399860.9 | AH12: 1 | AI12: CENTENNIAL PUBLIC SCHOOL DISTRICT | AJ12: 46184.74 | AK12: =AG12*AM12 -> -399860.9 | AL12: =AJ12*AM12 -> -46184.74 | AM12: -1 | AO12: =Y12-K12 -> 8193172 | AP12: =Z12-L12 -> 5541619 | AQ12: =AA12-Q12 -> 2338371 | AR12: =AB12-R12 -> 573391
A13: 11 | B13: Twin Cities Metropolitan Area | C13: 01 | D13: 2 | E13: Anoka | F13: COLUMBIA HEIGHTS PUBLIC SCHOOL DIST | G13: 0013 | J13: 3007.27 | K13: 4364222 | L13: 1241359 | M13: 5605581 | N13: 21076189 | O13: 2419271 | P13: 1225006 | Q13: 24720466 | R13: 1588601 | S13: 31914648 | T13: 1401247 | U13: 845664 | V13: 278137 | W13: 3383227 | X13: 37822921 | Y13: 6946875 | Z13: 3271324 | AA13: 25136697 | AB13: 2468025 | AC13: 06-07 | AD13: 13 | AE13: 1 | AF13: COLUMBIA HEIGHTS PUBLIC SCHOOL DIST | AG13: 295832.13 | AH13: 1 | AI13: COLUMBIA HEIGHTS PUBLIC SCHOOL DIST | AJ13: 6533.52 | AK13: =AG13*AM13 -> -295832.13 | AL13: =AJ13*AM13 -> -6533.52 | AM13: -1 | AO13: =Y13-K13 -> 2582653 | AP13: =Z13-L13 -> 2029965 | AQ13: =AA13-Q13 -> 416231 | AR13: =AB13-R13 -> 879424
A14: 11 | B14: Twin Cities Metropolitan Area | C14: 01 | D14: 2 | E14: Anoka | F14: FRIDLEY PUBLIC SCHOOL DISTRICT | G14: 0014 | J14: 2617.16 | K14: 4032545 | L14: 901577 | M14: 4934122 | N14: 17240811 | O14: 2748286 | P14: 512181 | Q14: 20501278 | R14: 1622095 | S14: 27057495 | T14: 1262958 | U14: 1629777 | V14: 49172 | W14: 1006512 | X14: 31005914 | Y14: 5259264 | Z14: 2460173 | AA14: 21077801 | AB14: 2208676 | AC14: 06-07 | AD14: 14 | AE14: 1 | AF14: FRIDLEY PUBLIC SCHOOL DISTRICT | AG14: 197003.37 | AH14: 1 | AI14: FRIDLEY PUBLIC SCHOOL DISTRICT | AJ14: 45764 | AK14: =AG14*AM14 -> -197003.37 | AL14: =AJ14*AM14 -> -45764 | AM14: -1 | AO14: =Y14-K14 -> 1226719 | AP14: =Z14-L14 -> 1558596 | AQ14: =AA14-Q14 -> 576523 | AR14: =AB14-R14 -> 586581
A15: 11 | B15: Twin Cities Metropolitan Area | C15: 01 | D15: 2 | E15: Anoka | F15: ST. FRANCIS PUBLIC SCHOOL DISTRICT | G15: 0015 | J15: 5879.67 | K15: 4143303 | L15: 3622109 | M15: 7765412 | N15: 37742931 | O15: 2948520 | P15: 212446 | Q15: 40903897 | R15: 1663583 | S15: 50332892 | T15: 2522340 | U15: 2144025 | V15: 216362 | W15: 4514165 | X15: 59729783 | Y15: 8341332 | Z15: 7367531 | AA15: 41619575 | AB15: 2401345 | AC15: 06-07 | AD15: 15 | AE15: 1 | AF15: ST. FRANCIS PUBLIC SCHOOL DISTRICT | AG15: 357035.83 | AH15: 1 | AI15: ST. FRANCIS PUBLIC SCHOOL DISTRICT | AJ15: 77119.78 | AK15: =AG15*AM15 -> -357035.83 | AL15: =AJ15*AM15 -> -77119.78 | AM15: -1 | AO15: =Y15-K15 -> 4198029 | AP15: =Z15-L15 -> 3745422 | AQ15: =AA15-Q15 -> 715678 | AR15: =AB15-R15 -> 737762
A16: 11 | B16: Twin Cities Metropolitan Area | C16: 01 | D16: 2 | E16: Anoka | F16: SPRING LAKE PARK PUBLIC SCHOOLS | G16: 0016 | J16: 4712.17 | K16: 5727758 | L16: 1753294 | M16: 7481052 | N16: 28313376 | O16: 2695964 | P16: 215791 | Q16: 31225131 | R16: 1646160 | S16: 40352343 | T16: 1656756 | U16: 2087106 | V16: 4322772 | W16: 2966882 | X16: 51385859 | Y16: 10377295 | Z16: 6919759 | AA16: 31601453 | AB16: 2487352 | AC16: 06-07 | AD16: 16 | AE16: 1 | AF16: SPRING LAKE PARK PUBLIC SCHOOLS | AG16: 251104.86 | AH16: 1 | AI16: SPRING LAKE PARK PUBLIC SCHOOLS | AJ16: 0 | AK16: =AG16*AM16 -> -251104.86 | AL16: =AJ16*AM16 -> 0 | AM16: -1 | AO16: =Y16-K16 -> 4649537 | AP16: =Z16-L16 -> 5166465 | AQ16: =AA16-Q16 -> 376322 | AR16: =AB16-R16 -> 841192
A17: 4 | B17: West Central Minnesota | C17: 01 | D17: 3 | E17: Becker | F17: DETROIT LAKES PUBLIC SCHOOL DIST. | G17: 0022 | J17: 2740.58 | K17: 1347341 | L17: 1331261 | M17: 2678602 | N17: 17848049 | O17: 1881048 | P17: 282182 | Q17: 20011279 | R17: 1499213 | S17: 24189094 | T17: 985590 | U17: 649159 | V17: 0 | W17: 1392084 | X17: 27215927 | Y17: 2662112 | Z17: 2222348 | AA17: 20417666 | AB17: 1913801 | AC17: 06-07 | AD17: 22 | AE17: 1 | AF17: DETROIT LAKES PUBLIC SCHOOL DIST. | AG17: 184375.54 | AH17: 1 | AI17: DETROIT LAKES PUBLIC SCHOOL DIST. | AJ17: 124309.58 | AK17: =AG17*AM17 -> -184375.54 | AL17: =AJ17*AM17 -> -124309.58 | AM17: -1 | AO17: =Y17-K17 -> 1314771 | AP17: =Z17-L17 -> 891087 | AQ17: =AA17-Q17 -> 406387 | AR17: =AB17-R17 -> 414588
A18: 4 | B18: West Central Minnesota | C18: 01 | D18: 3 | E18: Becker | F18: FRAZEE-VERGAS PUBLIC SCHOOL DIST. | G18: 0023 | J18: 1019.77 | K18: 324335 | L18: 529269 | M18: 853604 | N18: 6959062 | O18: 573577 | P18: 28893 | Q18: 7561532 | R18: 579931 | S18: 8995067 | T18: 428245 | U18: 200231 | V18: 0 | W18: 1010079 | X18: 10633621 | Y18: 1244281 | Z18: 793982 | AA18: 7783584 | AB18: 811774 | AC18: 06-07 | AD18: 23 | AE18: 1 | AF18: FRAZEE-VERGAS PUBLIC SCHOOL DIST. | AG18: 92910.66 | AH18: 1 | AI18: FRAZEE-VERGAS PUBLIC SCHOOL DIST. | AJ18: 0 | AK18: =AG18*AM18 -> -92910.66 | AL18: =AJ18*AM18 -> 0 | AM18: -1 | AO18: =Y18-K18 -> 919946 | AP18: =Z18-L18 -> 264713 | AQ18: =AA18-Q18 -> 222052 | AR18: =AB18-R18 -> 231843
A19: 4 | B19: West Central Minnesota | C19: 01 | D19: 3 | E19: Becker | F19: PINE POINT PUBLIC SCHOOL DISTRICT | G19: 0025 | J19: 63.82 | K19: 0 | L19: 201650 | M19: 201650 | N19: 534471 | O19: 77184 | P19: 112998 | Q19: 724653 | R19: 447403 | S19: 1373706 | T19: 61029 | U19: 687185 | V19: 0 | W19: 0 | X19: 2121921 | Y19: 0 | Z19: 257949 | AA19: 756175 | AB19: 1107797 | AC19: 06-07 | AD19: 25 | AE19: 1 | AF19: PINE POINT PUBLIC SCHOOL DISTRICT | AG19: 41869.19 | AH19: 1 | AI19: PINE POINT PUBLIC SCHOOL DISTRICT | AJ19: 0 | AK19: =AG19*AM19 -> -41869.19 | AL19: =AJ19*AM19 -> 0 | AM19: -1 | AO19: =Y19-K19 -> 0 | AP19: =Z19-L19 -> 56299 | AQ19: =AA19-Q19 -> 31522 | AR19: =AB19-R19 -> 660394
... A196: 11 | B196: Twin Cities Metropolitan Area | C196: 01 | D196: 62 | E196: Ramsey | F196: WHITE BEAR LAKE SCHOOL DISTRICT | G196: 0624 | J196: 8636.64 | K196: 13069286 | L196: 2330619 | M196: 15399905 | N196: 51388885 | O196: 7330916 | P196: 1518204 | Q196: 60238005 | R196: 2360414 | S196: 77998324 | T196: 3762902 | U196: 4050704 | V196: 1793277 | W196: 7003993 | X196: 94609201 | Y196: 20693864 | Z196: 9425383 | AA196: 61009375 | AB196: 3480579 | AC196: 06-07 | AD196: 624 | AE196: 1 | AF196: WHITE BEAR LAKE SCHOOL DISTRICT | AG196: 449533.57 | AH196: 1 | AI196: WHITE BEAR LAKE SCHOOL DISTRICT | AJ196: 8641.03 | AK196: =AG196*AM196 -> -449533.57 | AL196: =AJ196*AM196 -> -8641.03 | AM196: -1 | AO196: =Y196-K196 -> 7624578 | AP196: =Z196-L196 -> 7094764 | AQ196: =AA196-Q196 -> 771370 | AR196: =AB196-R196 -> 1120165
A197: 11 | B197: Twin Cities Metropolitan Area | C197: 01 | D197: 62 | E197: Ramsey | F197: ST. PAUL PUBLIC SCHOOL DISTRICT | G197: 0625 | H197: District | I197: St. Paul | J197: 42379.85 | K197: 48650687 | L197: 18437068 | M197: 67087755 | N197: 329659792 | O197: 43546172 | P197: 23370195 | Q197: 396576159 | R197: 41434769 | S197: 505098683 | T197: 20203751 | U197: 25727064 | V197: 2428882 | W197: 33879553 | X197: 587337933 | Y197: 80223356 | Z197: 31397027 | AA197: 414138351 | AB197: 61579199 | AC197: 06-07 | AD197: 625 | AE197: 1 | AF197: ST. PAUL PUBLIC SCHOOL DISTRICT | AG197: 5597682.3 | AH197: 1 | AI197: ST. PAUL PUBLIC SCHOOL DISTRICT | AJ197: 9194966.1 | AK197: =AG197*AM197 -> -5597682.3 | AL197: =AJ197*AM197 -> -9194966.1 | AM197: -1 | AO197: =Y197-K197 -> 31572669 | AP197: =Z197-L197 -> 12959959 | AQ197: =AA197-Q197 -> 17562192 | AR197: =AB197-R197 -> 20144430
A198: 1 | B198: Northwest Minnesota | C198: 01 | D198: 63 | E198: Red Lake | F198: OKLEE PUBLIC SCHOOL DISTRICT | G198: 0627 | J198: 245.46 | K198: 148368 | L198: 293101 | M198: 441469 | N198: 1914632 | O198: 91835 | P198: 17653 | Q198: 2024120 | R198: 47102 | S198: 2512691 | T198: 77741 | U198: 36534 | V198: 0 | W198: 0 | X198: 2626965 | Y198: 156707 | Z198: 321262 | AA198: 2052367 | AB198: 96629 | AC198: 06-07 | AD198: 627 | AE198: 1 | AF198: OKLEE PUBLIC SCHOOL DISTRICT | AG198: 22632.26 | AH198: 1 | AI198: OKLEE PUBLIC SCHOOL DISTRICT | AJ198: 0 | AK198: =AG198*AM198 -> -22632.26 | AL198: =AJ198*AM198 -> 0 | AM198: -1 | AO198: =Y198-K198 -> 8339 | AP198: =Z198-L198 -> 28161 | AQ198: =AA198-Q198 -> 28247 | AR198: =AB198-R198 -> 49527
A199: 1 | B199: Northwest Minnesota | C199: 01 | D199: 63 | E199: Red Lake | F199: PLUMMER PUBLIC SCHOOL DISTRICT | G199: 0628 | J199: 229.96 | K199: 162657 | L199: 445957 | M199: 608614 | N199: 1075937 | O199: 169125 | P199: 10391 | Q199: 1255453 | R199: 134894 | S199: 1998961 | T199: 103912 | U199: 60142 | V199: 0 | W199: 0 | X199: 2163015 | Y199: 183117 | Z199: 490106 | AA199: 1291088 | AB199: 198704 | AC199: 06-07 | AD199: 628 | AE199: 1 | AF199: PLUMMER PUBLIC SCHOOL DISTRICT | AG199: 22685.57 | AH199: 1 | AI199: PLUMMER PUBLIC SCHOOL DISTRICT | AJ199: 0 | AK199: =AG199*AM199 -> -22685.57 | AL199: =AJ199*AM199 -> 0 | AM199: -1 | AO199: =Y199-K199 -> 20460 | AP199: =Z199-L199 -> 44149 | AQ199: =AA199-Q199 -> 35635 | AR199: =AB199-R199 -> 63810
A200: 1 | B200: Northwest Minnesota | C200: 01 | D200: 63 | E200: Red Lake | F200: RED LAKE FALLS PUBLIC SCHOOL DIST. | G200: 0630 | J200: 379.51 | K200: 186066 | L200: 168707 | M200: 354773 | N200: 3041414 | O200: 343943 | P200: 41478 | Q200: 3426835 | R200: 152990 | S200: 3934598 | T200: 181351 | U200: 78621 | V200: 0 | W200: 486947 | X200: 4681517 | Y200: 397248 | Z200: 284487 | AA200: 3767172 | AB200: 232609 | AC200: 06-07 | AD200: 630 | AE200: 1 | AF200: RED LAKE FALLS PUBLIC SCHOOL DIST. | AG200: 29341.52 | AH200: 1 | AI200: RED LAKE FALLS PUBLIC SCHOOL DIST. | AJ200: 0 | AK200: =AG200*AM200 -> -29341.52 | AL200: =AJ200*AM200 -> 0 | AM200: -1 | AO200: =Y200-K200 -> 211182 | AP200: =Z200-L200 -> 115780 | AQ200: =AA200-Q200 -> 340337 | AR200: =AB200-R200 -> 79619
A201: 8 | B201: Southwest Minnesota | C201: 01 | D201: 64 | E201: Redwood | F201: MILROY PUBLIC SCHOOL DISTRICT | G201: 0635 | J201: 69.9 | K201: 144924 | L201: 159717 | M201: 304641 | N201: 572890 | O201: -22840 | P201: 17252 | Q201: 567302 | R201: 56313 | S201: 928256 | T201: 45035 | U201: 34837 | V201: 0 | W201: 0 | X201: 1008127 | Y201: 156666 | Z201: 188930 | AA201: 583271 | AB201: 79260 | AC201: 06-07 | AD201: 635 | AE201: 1 | AF201: MILROY PUBLIC SCHOOL DISTRICT | AG201: 14733.53 | AH201: 1 | AI201: MILROY PUBLIC SCHOOL DISTRICT | AJ201: 0 | AK201: =AG201*AM201 -> -14733.53 | AL201: =AJ201*AM201 -> 0 | AM201: -1 | AO201: =Y201-K201 -> 11742 | AP201: =Z201-L201 -> 29213 | AQ201: =AA201-Q201 -> 15969 | AR201: =AB201-R201 -> 22947
A202: 8 | B202: Southwest Minnesota | C202: 01 | D202: 64 | E202: Redwood | F202: WABASSO PUBLIC SCHOOL DISTRICT | G202: 0640 | J202: 402.19 | K202: 238819 | L202: 195221 | M202: 434040 | N202: 2802615 | O202: 167586 | P202: 74977 | Q202: 3045178 | R202: 150358 | S202: 3629576 | T202: 176686 | U202: 95696 | V202: 0 | W202: 484542 | X202: 4386500 | Y202: 580478 | Z202: 465270 | AA202: 3119492 | AB202: 221260 | AC202: 06-07 | AD202: 640 | AE202: 1 | AF202: WABASSO PUBLIC SCHOOL DISTRICT | AG202: 39033.96 | AH202: 1 | AI202: WABASSO PUBLIC SCHOOL DISTRICT | AJ202: 0 | AK202: =AG202*AM202 -> -39033.96 | AL202: =AJ202*AM202 -> 0 | AM202: -1 | AO202: =Y202-K202 -> 341659 | AP202: =Z202-L202 -> 270049 | AQ202: =AA202-Q202 -> 74314 | AR202: =AB202-R202 -> 70902
A203: 10 | B203: Southeast Minnesota | C203: 01 | D203: 66 | E203: Rice | F203: FARIBAULT PUBLIC SCHOOL DISTRICT | G203: 0656 | J203: 4058.93 | K203: 2724651 | L203: 1545729 | M203: 4270380 | N203: 26710861 | O203: 2872560 | P203: 259970 | Q203: 29843391 | R203: 2072172 | S203: 36185943 | T203: 1955907 | U203: 2522704 | V203: 7198 | W203: 4666791 | X203: 45338543 | Y203: 7030250 | Z203: 3520143 | AA203: 31061382 | AB203: 3726768 | AC203: 06-07 | AD203: 656 | AE203: 1 | AF203: FARIBAULT PUBLIC SCHOOL DISTRICT | AG203: 348147.75 | AH203: 1 | AI203: FARIBAULT PUBLIC SCHOOL DISTRICT | AJ203: 412448.22 | AK203: =AG203*AM203 -> -348147.75 | AL203: =AJ203*AM203 -> -412448.22 | AM203: -1 | AO203: =Y203-K203 -> 4305599 | AP203: =Z203-L203 -> 1974414 | AQ203: =AA203-Q203 -> 1217991 | AR203: =AB203-R203 -> 1654596
A204: 10 | B204: Southeast Minnesota | C204: 01 | D204: 66 | E204: Rice | F204: NORTHFIELD PUBLIC SCHOOL DISTRICT | G204: 0659 | J204: 3944.86 | K204: 4376967 | L204: 1458002 | M204: 5834969 | N204: 24572268 | O204: 1884185 | P204: 259912 | Q204: 26716365 | R204: 1308168 | S204: 33859502 | T204: 1690285 | U204: 2008557 | V204: 64469 | W204: 5562520 | X204: 43185333 | Y204: 9857276 | Z204: 4228288 | AA204: 27319200 | AB204: 1780569 | AC204: 06-07 | AD204: 659 | AE204: 1 | AF204: NORTHFIELD PUBLIC SCHOOL DISTRICT | AG204: 368495.78 | AH204: 1 | AI204: NORTHFIELD PUBLIC SCHOOL DISTRICT | AJ204: 15029 | AK204: =AG204*AM204 -> -368495.78 | AL204: =AJ204*AM204 -> -15029 | AM204: -1 | AO204: =Y204-K204 -> 5480309 | AP204: =Z204-L204 -> 2770286 | AQ204: =AA204-Q204 -> 602835 | AR204: =AB204-R204 -> 472401
A205: 8 | B205: Southwest Minnesota | C205: 01 | D205: 67 | E205: Rock | F205: HILLS-BEAVER CREEK SCHOOL DISTRICT | G205: 0671 | J205: 339.54 | K205: 201896 | L205: 159749 | M205: 361645 | N205: 2382775 | O205: 145498 | P205: 16848 | Q205: 2545121 | R205: 91279 | S205: 2998045 | T205: 132644 | U205: 78344 | V205: 0 | W205: 178002 | X205: 3387035 | Y205: 375605 | Z205: 275839 | AA205: 2586627 | AB205: 148963 | AC205: 06-07 | AD205: 671 | AE205: 1 | AF205: HILLS-BEAVER CREEK SCHOOL DISTRICT | AG205: 20391.98 | AH205: 1 | AI205: HILLS-BEAVER CREEK SCHOOL DISTRICT | AJ205: 0 | AK205: =AG205*AM205 -> -20391.98 | AL205: =AJ205*AM205 -> 0 | AM205: -1 | AO205: =Y205-K205 -> 173709 | AP205: =Z205-L205 -> 116090 | AQ205: =AA205-Q205 -> 41506 | AR205: =AB205-R205 -> 57684
A206: 1 | B206: Northwest Minnesota | C206: 01 | D206: 68 | E206: Roseau | F206: BADGER PUBLIC SCHOOL DISTRICT | G206: 0676 | J206: 226.99 | K206: 183259 | L206: 181091 | M206: 364350 | N206: 1875831 | O206: 91198 | P206: 27430 | Q206: 1994459 | R206: 68634 | S206: 2427443 | T206: 110203 | U206: 37512 | V206: 0 | W206: 53686 | X206: 2628845 | Y206: 233270 | Z206: 226010 | AA206: 2036959 | AB206: 132605 | AC206: 06-07 | AD206: 676 | AE206: 1 | AF206: BADGER PUBLIC SCHOOL DISTRICT | AG206: 20448.88 | AH206: 1 | AI206: BADGER PUBLIC SCHOOL DISTRICT | AJ206: 0 | AK206: =AG206*AM206 -> -20448.88 | AL206: =AJ206*AM206 -> 0 | AM206: -1 | AO206: =Y206-K206 -> 50011 | AP206: =Z206-L206 -> 44919 | AQ206: =AA206-Q206 -> 42500 | AR206: =AB206-R206 -> 63971
A207: 1 | B207: Northwest Minnesota | C207: 01 | D207: 68 | E207: Roseau | F207: ROSEAU PUBLIC SCHOOL DISTRICT | G207: 0682 | J207: 1333.17 | K207: 559893 | L207: 507903 | M207: 1067796 | N207: 9141472 | O207: 738031 | P207: 70128 | Q207: 9949631 | R207: 415248 | S207: 11432675 | T207: 484686 | U207: 309307 | V207: 0 | W207: 1400851 | X207: 13627519 | Y207: 1571428 | Z207: 1082877 | AA207: 10391671 | AB207: 581543 | AC207: 06-07 | AD207: 682 | AE207: 1 | AF207: ROSEAU PUBLIC SCHOOL DISTRICT | AG207: 89591.06 | AH207: 1 | AI207: ROSEAU PUBLIC SCHOOL DISTRICT | AJ207: 0 | AK207: =AG207*AM207 -> -89591.06 | AL207: =AJ207*AM207 -> 0 | AM207: -1 | AO207: =Y207-K207 -> 1011535 | AP207: =Z207-L207 -> 574974 | AQ207: =AA207-Q207 -> 442040 | AR207: =AB207-R207 -> 166295
A208: 1 | B208: Northwest Minnesota | C208: 01 | D208: 68 | E208: Roseau | F208: WARROAD PUBLIC SCHOOL DISTRICT | G208: 0690 | J208: 1261.52 | K208: 456583 | L208: 854426 | M208: 1311009 | N208: 8717220 | O208: 444674 | P208: 224178 | Q208: 9386072 | R208: 649488 | S208: 11346569 | T208: 499742 | U208: 556417 | V208: 38777 | W208: 1293227 | X208: 13734731 | Y208: 1391098 | Z208: 1442918 | AA208: 10025091 | AB208: 875624 | AC208: 06-07 | AD208: 690 | AE208: 1 | AF208: WARROAD PUBLIC SCHOOL DISTRICT | AG208: 109254.74 | AH208: 1 | AI208: WARROAD PUBLIC SCHOOL DISTRICT | AJ208: 0 | AK208: =AG208*AM208 -> -109254.74 | AL208: =AJ208*AM208 -> 0 | AM208: -1 | AO208: =Y208-K208 -> 934515 | AP208: =Z208-L208 -> 588492 | AQ208: =AA208-Q208 -> 639019 | AR208: =AB208-R208 -> 226136
A209: 3 | B209: Northeast Minnesota | C209: 01 | D209: 69 | E209: Saint Louis | F209: CHISHOLM PUBLIC SCHOOL DISTRICT | G209: 0695 | J209: 757.37 | K209: 483555 | L209: 1212906 | M209: 1696461 | N209: 5280620 | O209: 165386 | P209: 94746 | Q209: 5540752 | R209: 307940 | S209: 7545153 | T209: 262046 | U209: 168485 | V209: 0 | W209: 820611 | X209: 8796296 | Y209: 638347 | Z209: 1939270 | AA209: 5749211 | AB209: 469468 | AC209: 06-07 | AD209: 695 | AE209: 1 | AF209: CHISHOLM PUBLIC SCHOOL DISTRICT | AG209: 58610.12 | AH209: 1 | AI209: CHISHOLM PUBLIC SCHOOL DISTRICT | AJ209: 0 | AK209: =AG209*AM209 -> -58610.12 | AL209: =AJ209*AM209 -> 0 | AM209: -1 | AO209: =Y209-K209 -> 154792 | AP209: =Z209-L209 -> 726364 | AQ209: =AA209-Q209 -> 208459 | AR209: =AB209-R209 -> 161528
... A345: 8 | B345: Southwest Minnesota | C345: 01 | D345: 41 | E345: Lincoln | F345: RTR PUBLIC SCHOOLS | G345: 2902 | J345: 564.36 | K345: 406449 | L345: 300075 | M345: 706524 | N345: 3790735 | O345: 148612 | P345: 338771 | Q345: 4278118 | R345: 388758 | S345: 5373400 | T345: 281159 | U345: 97801 | V345: 0 | W345: 62577 | X345: 5814939 | Y345: 503607 | Z345: 480585 | AA345: 4329076 | AB345: 501671 | AC345: 06-07 | AD345: 2902 | AE345: 1 | AF345: RTR PUBLIC SCHOOLS | AG345: 46641.83 | AH345: 1 | AI345: RTR PUBLIC SCHOOLS | AJ345: 0 | AK345: =AG345*AM345 -> -46641.83 | AL345: =AJ345*AM345 -> 0 | AM345: -1 | AO345: =Y345-K345 -> 97158 | AP345: =Z345-L345 -> 180510 | AQ345: =AA345-Q345 -> 50958 | AR345: =AB345-R345 -> 112913
A346: 11 | B346: Twin Cities Metropolitan Area | C346: 07 | D346: 62 | E346: Ramsey | F346: ACADEMIA CESAR CHAVEZ CHARTER SCH. | G346: 4073 | H346: Charter | I346: St. Paul | J346: 262.75 | K346: 0 | L346: 47885 | M346: 47885 | N346: 2086879 | O346: 198549 | P346: 270454 | Q346: 2555882 | R346: 184592 | S346: 2788359 | T346: 146884 | U346: 0 | V346: 0 | W346: 0 | X346: 2935244 | Y346: 0 | Z346: 51947 | AA346: 2564036 | AB346: 319261 | AC346: 06-07 | AD346: 4073 | AE346: 7 | AF346: ACADEMIA CESAR CHAVEZ CHARTER SCH. | AG346: 0 | AH346: 7 | AI346: ACADEMIA CESAR CHAVEZ CHARTER SCH. | AJ346: 0 | AK346: =AG346*AM346 -> 0 | AL346: =AJ346*AM346 -> 0 | AM346: -1 | AO346: =Y346-K346 -> 0 | AP346: =Z346-L346 -> 4062 | AQ346: =AA346-Q346 -> 8154 | AR346: =AB346-R346 -> 134669
A347: 10 | B347: Southeast Minnesota | C347: 07 | D347: 85 | E347: Winona | F347: ACADEMY OF BIOSCIENCES | G347: 4148 | H347: Charter | I347: Statewide | J347: 157.75 | K347: 0 | L347: 17595 | M347: 17595 | N347: 1119571 | O347: 81301 | P347: 330392 | Q347: 1531264 | R347: 233166 | S347: 1782025 | T347: 62354 | U347: 0 | V347: 0 | W347: 0 | X347: 1844380 | Y347: 0 | Z347: 42665 | AA347: 1534220 | AB347: 267495 | AC347: 06-07 | AD347: 4148 | AE347: 7 | AF347: ACADEMY OF BIOSCIENCES | AG347: 0 | AH347: 7 | AI347: ACADEMY OF BIOSCIENCES | AJ347: 0 | AK347: =AG347*AM347 -> 0 | AL347: =AJ347*AM347 -> 0 | AM347: -1 | AO347: =Y347-K347 -> 0 | AP347: =Z347-L347 -> 25070 | AQ347: =AA347-Q347 -> 2956 | AR347: =AB347-R347 -> 34329
A348: 11 | B348: Twin Cities Metropolitan Area | C348: 07 | D348: 82 | E348: Washington | F348: ACHIEVE LANGUAGE ACADEMY | G348: 4018 | H348: Charter | I348: St. Paul | J348: 409.08 | K348: 0 | L348: 89030 | M348: 89030 | N348: 3228896 | O348: 182561 | P348: 598530 | Q348: 4009987 | R348: 227280 | S348: 4326297 | T348: 0 | U348: 24975 | V348: 0 | W348: 0 | X348: 4351272 | Y348: 0 | Z348: 114005 | AA348: 4009987 | AB348: 227280 | AC348: 06-07 | AD348: 4018 | AE348: 7 | AF348: ACHIEVE LANGUAGE ACADEMY | AG348: 0 | AH348: 7 | AI348: ACHIEVE LANGUAGE ACADEMY | AJ348: 0 | AK348: =AG348*AM348 -> 0 | AL348: =AJ348*AM348 -> 0 | AM348: -1 | AO348: =Y348-K348 -> 0 | AP348: =Z348-L348 -> 24975 | AQ348: =AA348-Q348 -> 0 | AR348: =AB348-R348 -> 0
A349: 11 | B349: Twin Cities Metropolitan Area | C349: 07 | D349: 27 | E349: Hennepin | F349: ADAM ABDULLE ACADEMY | G349: 4135 | H349: Charter | I349: Statewide | J349: 112.29 | K349: 0 | L349: 1278 | M349: 1278 | N349: 1080750 | O349: 19392 | P349: 266690 | Q349: 1366832 | R349: 176006 | S349: 1544116 | T349: 67570 | U349: 0 | V349: 0 | W349: 0 | X349: 1611686 | Y349: 0 | Z349: 1278 | AA349: 1368860 | AB349: 241548 | AC349: 06-07 | AD349: 4135 | AE349: 7 | AF349: ADAM ABDULLE ACADEMY | AG349: 0 | AH349: 7 | AI349: ADAM ABDULLE ACADEMY | AJ349: 0 | AK349: =AG349*AM349 -> 0 | AL349: =AJ349*AM349 -> 0 | AM349: -1 | AO349: =Y349-K349 -> 0 | AP349: =Z349-L349 -> 0 | AQ349: =AA349-Q349 -> 2028 | AR349: =AB349-R349 -> 65542
A350: 11 | B350: Twin Cities Metropolitan Area | C350: 07 | D350: 62 | E350: Ramsey | F350: AGRICULTURAL FOOD SCIENCE ACADEMY | G350: 4074 | H350: Charter | I350: Statewide | J350: 203.87 | K350: 0 | L350: 271848 | M350: 271848 | N350: 1439440 | O350: 376937 | P350: 366283 | Q350: 2182660 | R350: 69454 | S350: 2523962 | T350: 38080 | U350: 0 | V350: 0 | W350: 0 | X350: 2562042 | Y350: 0 | Z350: 288268 | AA350: 2184563 | AB350: 89211 | AC350: 06-07 | AD350: 4074 | AE350: 7 | AF350: AGRICULTURAL FOOD SCIENCE ACADEMY | AG350: 0 | AH350: 7 | AI350: AGRICULTURAL FOOD SCIENCE ACADEMY | AJ350: 0 | AK350: =AG350*AM350 -> 0 | AL350: =AJ350*AM350 -> 0 | AM350: -1 | AO350: =Y350-K350 -> 0 | AP350: =Z350-L350 -> 16420 | AQ350: =AA350-Q350 -> 1903 | AR350: =AB350-R350 -> 19757
A351: 11 | B351: Twin Cities Metropolitan Area | C351: 07 | D351: 62 | E351: Ramsey | F351: ARTECH | G351: 4091 | H351: Charter | I351: Statewide | J351: 122.6 | K351: 0 | L351: 16752 | M351: 16752 | N351: 854895 | O351: 203462 | P351: 178658 | Q351: 1237015 | R351: 32280 | S351: 1286047 | T351: 15134 | U351: 0 | V351: 0 | W351: 0 | X351: 1301181 | Y351: 0 | Z351: 27878 | AA351: 1237462 | AB351: 35841 | AC351: 06-07 | AD351: 4091 | AE351: 7 | AF351: ARTECH | AG351: 0 | AH351: 7 | AI351: ARTECH | AJ351: 0 | AK351: =AG351*AM351 -> 0 | AL351: =AJ351*AM351 -> 0 | AM351: -1 | AO351: =Y351-K351 -> 0 | AP351: =Z351-L351 -> 11126 | AQ351: =AA351-Q351 -> 447 | AR351: =AB351-R351 -> 3561
A352: 9 | B352: South Central Minnesota | C352: 07 | D352: 72 | E352: Sibley | F352: ASCENSION ACADEMY CHARTER SCHOOL | G352: 4114 | H352: Charter | I352: Minneapolis | J352: 87.16 | K352: 0 | L352: 62267 | M352: 62267 | N352: 718200 | O352: 15027 | P352: 134815 | Q352: 868042 | R352: 157517 | S352: 1087826 | T352: 27405 | U352: 0 | V352: 0 | W352: 0 | X352: 1115230 | Y352: 0 | Z352: 63766 | AA352: 869385 | AB352: 182079 | AC352: 06-07 | AD352: 4114 | AE352: 7 | AF352: ASCENSION ACADEMY CHARTER SCHOOL | AG352: 0 | AH352: 7 | AI352: ASCENSION ACADEMY CHARTER SCHOOL | AJ352: 0 | AK352: =AG352*AM352 -> 0 | AL352: =AJ352*AM352 -> 0 | AM352: -1 | AO352: =Y352-K352 -> 0 | AP352: =Z352-L352 -> 1499 | AQ352: =AA352-Q352 -> 1343 | AR352: =AB352-R352 -> 24562
A353: 11 | B353: Twin Cities Metropolitan Area | C353: 07 | D353: 2 | E353: Anoka | F353: AUGSBURG ACADEMY FOR HEALTH CAREERS | G353: 4111 | H353: Charter | I353: Minneapolis | J353: 70.7 | K353: 0 | L353: 13027 | M353: 13027 | N353: 599649 | O353: 53838 | P353: 144839 | Q353: 798326 | R353: 183653 | S353: 995006 | T353: 16419 | U353: 0 | V353: 0 | W353: 0 | X353: 1011426 | Y353: 0 | Z353: 14100 | AA353: 798965 | AB353: 198361 | AC353: 06-07 | AD353: 4111 | AE353: 7 | AF353: AUGSBURG ACADEMY FOR HEALTH CAREERS | AG353: 0 | AH353: 7 | AI353: AUGSBURG ACADEMY FOR HEALTH CAREERS | AJ353: 0 | AK353: =AG353*AM353 -> 0 | AL353: =AJ353*AM353 -> 0 | AM353: -1 | AO353: =Y353-K353 -> 0 | AP353: =Z353-L353 -> 1073 | AQ353: =AA353-Q353 -> 639 | AR353: =AB353-R353 -> 14708
A354: 11 | B354: Twin Cities Metropolitan Area | C354: 07 | D354: 27 | E354: Hennepin | F354: AURORA CHARTER SCHOOL | G354: 4067 | H354: Charter | I354: Minneapolis | J354: 231.57 | K354: 0 | L354: 2320 | M354: 2320 | N354: 1781024 | O354: 28680 | P354: 128902 | Q354: 1938606 | R354: 120732 | S354: 2061658 | T354: 117369 | U354: 5702 | V354: 0 | W354: 0 | X354: 2184730 | Y354: 0 | Z354: 24414 | AA354: 1943071 | AB354: 217245 | AC354: 06-07 | AD354: 4067 | AE354: 7 | AF354: AURORA CHARTER SCHOOL | AG354: 2653.05 | AH354: 7 | AI354: AURORA CHARTER SCHOOL | AJ354: 0 | AK354: =AG354*AM354 -> -2653.05 | AL354: =AJ354*AM354 -> 0 | AM354: -1 | AO354: =Y354-K354 -> 0 | AP354: =Z354-L354 -> 22094 | AQ354: =AA354-Q354 -> 4465 | AR354: =AB354-R354 -> 96513
A355: 5 | B355: North Central Minnesota | C355: 07 | D355: 18 | E355: Crow Wing | F355: AVALON SCHOOL | G355: 4075 | H355: Charter | I355: St. Paul | J355: 154.51 | K355: 0 | L355: 88885 | M355: 88885 | N355: 1115713 | O355: 191219 | P355: 242377 | Q355: 1549309 | R355: 9127 | S355: 1647321 | T355: 9987 | U355: 0 | V355: 0 | W355: 0 | X355: 1657307 | Y355: 0 | Z355: 91540 | AA355: 1549680 | AB355: 16087 | AC355: 06-07 | AD355: 4075 | AE355: 7 | AF355: AVALON SCHOOL | AG355: 0 | AH355: 7 | AI355: AVALON SCHOOL | AJ355: 0 | AK355: =AG355*AM355 -> 0 | AL355: =AJ355*AM355 -> 0 | AM355: -1 | AO355: =Y355-K355 -> 0 | AP355: =Z355-L355 -> 2655 | AQ355: =AA355-Q355 -> 371 | AR355: =AB355-R355 -> 6960
A356: 11 | B356: Twin Cities Metropolitan Area | C356: 07 | D356: 62 | E356: Ramsey | F356: BEACON ACADEMY | G356: 4124 | H356: Charter | I356: Statewide | J356: 253.08 | K356: 0 | L356: 203659 | M356: 203659 | N356: 1447572 | O356: 138333 | P356: 305412 | Q356: 1891317 | R356: 191318 | S356: 2286294 | T356: 58912 | U356: 0 | V356: 0 | W356: 0 | X356: 2345206 | Y356: 0 | Z356: 244792 | AA356: 1893381 | AB356: 207033 | AC356: 06-07 | AD356: 4124 | AE356: 7 | AF356: BEACON ACADEMY | AG356: 0 | AH356: 7 | AI356: BEACON ACADEMY | AJ356: 0 | AK356: =AG356*AM356 -> 0 | AL356: =AJ356*AM356 -> 0 | AM356: -1 | AO356: =Y356-K356 -> 0 | AP356: =Z356-L356 -> 41133 | AQ356: =AA356-Q356 -> 2064 | AR356: =AB356-R356 -> 15715
A357: 11 | B357: Twin Cities Metropolitan Area | C357: 07 | D357: 10 | E357: Carver | F357: BEACON PREPARATORY SCHOOL | G357: 4133 | H357: Charter | I357: Statewide | J357: 29.97 | K357: 0 | L357: 56117 | M357: 56117 | N357: 174451 | O357: 20096 | P357: 88124 | Q357: 282671 | R357: 171909 | S357: 510697 | T357: 3631 | U357: 0 | V357: 0 | W357: 0 | X357: 514327 | Y357: 0 | Z357: 59748 | AA357: 282670 | AB357: 171909 | AC357: 06-07 | AD357: 4133 | AE357: 7 | AF357: BEACON PREPARATORY SCHOOL | AG357: 0 | AH357: 7 | AI357: BEACON PREPARATORY SCHOOL | AJ357: 0 | AK357: =AG357*AM357 -> 0 | AL357: =AJ357*AM357 -> 0 | AM357: -1 | AO357: =Y357-K357 -> 0 | AP357: =Z357-L357 -> 3631 | AQ357: =AA357-Q357 -> -1 | AR357: =AB357-R357 -> 0
... A362: 6W | B362: Upper Southwest Minnesota | C362: 07 | D362: 87 | E362: Yellow Medicine | F362: CITY ACADEMY | G362: 4000 | H362: Charter | I362: St. Paul | J362: 117.19 | K362: 0 | L362: 62266 | M362: 62266 | N362: 1083305 | O362: 0 | P362: 143110 | Q362: 1226415 | R362: 0 | S362: 1288681 | T362: 0 | U362: 0 | V362: 0 | W362: 0 | X362: 1288681 | Y362: 0 | Z362: 62266 | AA362: 1226415 | AB362: 0 | AC362: 06-07 | AD362: 4000 | AE362: 7 | AF362: CITY ACADEMY | AG362: 0 | AH362: 7 | AI362: CITY ACADEMY | AJ362: 0 | AK362: =AG362*AM362 -> 0 | AL362: =AJ362*AM362 -> 0 | AM362: -1 | AO362: =Y362-K362 -> 0 | AP362: =Z362-L362 -> 0 | AQ362: =AA362-Q362 -> 0 | AR362: =AB362-R362 -> 0
A363: 11 | B363: Twin Cities Metropolitan Area | C363: 07 | D363: 62 | E363: Ramsey | F363: CLARKFIELD CHARTER SCHOOL | G363: 4172 | H363: Charter | J363: 0 | K363: 0 | L363: 8819 | M363: 8819 | N363: 0 | O363: 0 | P363: 0 | Q363: 0 | R363: 45600 | S363: 54419 | T363: 0 | U363: 0 | V363: 0 | W363: 0 | X363: 54419 | Y363: 0 | Z363: 8819 | AA363: 0 | AB363: 45600 | AC363: 06-07 | AD363: 4172 | AE363: 7 | AF363: CLARKFIELD CHARTER SCHOOL | AG363: 0 | AH363: 7 | AI363: CLARKFIELD CHARTER SCHOOL | AJ363: 0 | AK363: =AG363*AM363 -> 0 | AL363: =AJ363*AM363 -> 0 | AM363: -1 | AO363: =Y363-K363 -> 0 | AP363: =Z363-L363 -> 0 | AQ363: =AA363-Q363 -> 0 | AR363: =AB363-R363 -> 0
A364: 8 | B364: Southwest Minnesota | C364: 07 | D364: 64 | E364: Redwood | F364: COMMUNITY OF PEACE ACADEMY | G364: 4015 | H364: Charter | I364: St. Paul | J364: 590.4 | K364: 0 | L364: 87237 | M364: 87237 | N364: 4920091 | O364: 627865 | P364: 1024715 | Q364: 6572671 | R364: 438125 | S364: 7098033 | T364: 0 | U364: 0 | V364: 0 | W364: 0 | X364: 7098033 | Y364: 0 | Z364: 87237 | AA364: 6572671 | AB364: 438125 | AC364: 06-07 | AD364: 4015 | AE364: 7 | AF364: COMMUNITY OF PEACE ACADEMY | AG364: 0 | AH364: 7 | AI364: COMMUNITY OF PEACE ACADEMY | AJ364: 0 | AK364: =AG364*AM364 -> 0 | AL364: =AJ364*AM364 -> 0 | AM364: -1 | AO364: =Y364-K364 -> 0 | AP364: =Z364-L364 -> 0 | AQ364: =AA364-Q364 -> 0 | AR364: =AB364-R364 -> 0
A365: 11 | B365: Twin Cities Metropolitan Area | C365: 07 | D365: 62 | E365: Ramsey | F365: COMMUNITY SCHOOL OF EXCELLENCE | G365: 4181 | H365: Charter | I365: St. Paul | J365: 0 | K365: 0 | L365: 1000 | M365: 1000 | N365: 0 | O365: 0 | P365: 0 | Q365: 0 | R365: 69269 | S365: 70269 | T365: 0 | U365: 0 | V365: 0 | W365: 0 | X365: 70269 | Y365: 0 | Z365: 1000 | AA365: 0 | AB365: 69269 | AC365: 06-07 | AD365: 4181 | AE365: 7 | AF365: COMMUNITY SCHOOL OF EXCELLENCE | AG365: 0 | AH365: 7 | AI365: COMMUNITY SCHOOL OF EXCELLENCE | AJ365: 0 | AK365: =AG365*AM365 -> 0 | AL365: =AJ365*AM365 -> 0 | AM365: -1 | AO365: =Y365-K365 -> 0 | AP365: =Z365-L365 -> 0 | AQ365: =AA365-Q365 -> 0 | AR365: =AB365-R365 -> 0
A366: 11 | B366: Twin Cities Metropolitan Area | C366: 07 | D366: 27 | E366: Hennepin | F366: CONCORDIA CREATIVE LEARNING ACADEMY | G366: 4035 | H366: Charter | I366: St. Paul | J366: 161.97 | K366: 0 | L366: 37122 | M366: 37122 | N366: 1129769 | O366: 214488 | P366: 210634 | Q366: 1554891 | R366: 106947 | S366: 1698960 | T366: 80539 | U366: 9433 | V366: 0 | W366: 0 | X366: 1788932 | Y366: 0 | Z366: 48679 | AA366: 1558149 | AB366: 182104 | AC366: 06-07 | AD366: 4035 | AE366: 7 | AF366: CONCORDIA CREATIVE LEARNING ACADEMY | AG366: 0 | AH366: 7 | AI366: CONCORDIA CREATIVE LEARNING ACADEMY | AJ366: 0 | AK366: =AG366*AM366 -> 0 | AL366: =AJ366*AM366 -> 0 | AM366: -1 | AO366: =Y366-K366 -> 0 | AP366: =Z366-L366 -> 11557 | AQ366: =AA366-Q366 -> 3258 | AR366: =AB366-R366 -> 75157
A367: 11 | B367: Twin Cities Metropolitan Area | C367: 07 | D367: 62 | E367: Ramsey | F367: CROSSLAKE COMMUNITY CHARTER SCHOOL | G367: 4059 | H367: Charter | I367: Statewide | J367: 110.76 | K367: 0 | L367: 27089 | M367: 27089 | N367: 713918 | O367: 183951 | P367: 137379 | Q367: 1035248 | R367: 33111 | S367: 1095448 | T367: 40276 | U367: 0 | V367: 0 | W367: 0 | X367: 1135723 | Y367: 0 | Z367: 48368 | AA367: 1036839 | AB367: 50516 | AC367: 06-07 | AD367: 4059 | AE367: 7 | AF367: CROSSLAKE COMMUNITY CHARTER SCHOOL | AG367: 0 | AH367: 7 | AI367: CROSSLAKE COMMUNITY CHARTER SCHOOL | AJ367: 0 | AK367: =AG367*AM367 -> 0 | AL367: =AJ367*AM367 -> 0 | AM367: -1 | AO367: =Y367-K367 -> 0 | AP367: =Z367-L367 -> 21279 | AQ367: =AA367-Q367 -> 1591 | AR367: =AB367-R367 -> 17405
A368: 11 | B368: Twin Cities Metropolitan Area | C368: 07 | D368: 27 | E368: Hennepin | F368: CYBER VILLAGE ACADEMY | G368: 4025 | H368: Charter | I368: St. Paul | J368: 119.5 | K368: 0 | L368: 99413 | M368: 99413 | N368: 751760 | O368: 45959 | P368: 213038 | Q368: 1010757 | R368: 53944 | S368: 1164114 | T368: 0 | U368: 0 | V368: 0 | W368: 0 | X368: 1164114 | Y368: 0 | Z368: 99413 | AA368: 1010757 | AB368: 53944 | AC368: 06-07 | AD368: 4025 | AE368: 7 | AF368: CYBER VILLAGE ACADEMY | AG368: 0 | AH368: 7 | AI368: CYBER VILLAGE ACADEMY | AJ368: 0 | AK368: =AG368*AM368 -> 0 | AL368: =AJ368*AM368 -> 0 | AM368: -1 | AO368: =Y368-K368 -> 0 | AP368: =Z368-L368 -> 0 | AQ368: =AA368-Q368 -> 0 | AR368: =AB368-R368 -> 0
A369: 11 | B369: Twin Cities Metropolitan Area | C369: 07 | D369: 62 | E369: Ramsey | F369: CYGNUS ACADEMY | G369: 4149 | H369: Charter | I369: Statewide | J369: 87.38 | K369: 0 | L369: 24590 | M369: 24590 | N369: 537417 | O369: 72690 | P369: 148575 | Q369: 758682 | R369: 189256 | S369: 972528 | T369: 22717 | U369: 0 | V369: 0 | W369: 0 | X369: 995245 | Y369: 0 | Z369: 41389 | AA369: 760234 | AB369: 193622 | AC369: 06-07 | AD369: 4149 | AE369: 7 | AF369: CYGNUS ACADEMY | AG369: 0 | AH369: 7 | AI369: CYGNUS ACADEMY | AJ369: 0 | AK369: =AG369*AM369 -> 0 | AL369: =AJ369*AM369 -> 0 | AM369: -1 | AO369: =Y369-K369 -> 0 | AP369: =Z369-L369 -> 16799 | AQ369: =AA369-Q369 -> 1552 | AR369: =AB369-R369 -> 4366
A370: 11 | B370: Twin Cities Metropolitan Area | C370: 07 | D370: 62 | E370: Ramsey | F370: DAKOTA ACADEMY | G370: 4158 | H370: Charter | I370: Statewide | J370: 95.93 | K370: 0 | L370: 37905 | M370: 37905 | N370: 608235 | O370: 162561 | P370: 165099 | Q370: 935895 | R370: 127465 | S370: 1101265 | T370: 21323 | U370: 0 | V370: 0 | W370: 0 | X370: 1122588 | Y370: 0 | Z370: 55405 | AA370: 936141 | AB370: 131042 | AC370: 06-07 | AD370: 4158 | AE370: 7 | AF370: DAKOTA ACADEMY | AG370: 0 | AH370: 7 | AI370: DAKOTA ACADEMY | AJ370: 0 | AK370: =AG370*AM370 -> 0 | AL370: =AJ370*AM370 -> 0 | AM370: -1 | AO370: =Y370-K370 -> 0 | AP370: =Z370-L370 -> 17500 | AQ370: =AA370-Q370 -> 246 | AR370: =AB370-R370 -> 3577
A371: 11 | B371: Twin Cities Metropolitan Area | C371: 07 | D371: 27 | E371: Hennepin | F371: DAKOTA AREA COMMUNITY CHARTER SCH | G371: 4123 | H371: Charter | I371: Statewide | J371: 52 | K371: 0 | L371: 3406 | M371: 3406 | N371: 293378 | O371: 52639 | P371: 66408 | Q371: 412425 | R371: 185044 | S371: 600875 | T371: 20459 | U371: 21279 | V371: 0 | W371: 0 | X371: 642612 | Y371: 0 | Z371: 41906 | AA371: 412924 | AB371: 187782 | AC371: 06-07 | AD371: 4123 | AE371: 7 | AF371: DAKOTA AREA COMMUNITY CHARTER SCH | AG371: 8992.63 | AH371: 7 | AI371: DAKOTA AREA COMMUNITY CHARTER SCH | AJ371: 0 | AK371: =AG371*AM371 -> -8992.63 | AL371: =AJ371*AM371 -> 0 | AM371: -1 | AO371: =Y371-K371 -> 0 | AP371: =Z371-L371 -> 38500 | AQ371: =AA371-Q371 -> 499 | AR371: =AB371-R371 -> 2738
A372: 11 | B372: Twin Cities Metropolitan Area | C372: 07 | D372: 62 | E372: Ramsey | F372: DISCOVERY PUBLIC SCHOOL FARIBAULT | G372: 4081 | H372: Charter | I372: Statewide | J372: 53.41 | K372: 0 | L372: 18702 | M372: 18702 | N372: 393131 | O372: 51975 | P372: 75615 | Q372: 520721 | R372: 41534 | S372: 580957 | T372: 16528 | U372: 0 | V372: 0 | W372: 0 | X372: 597485 | Y372: 0 | Z372: 21721 | AA372: 521708 | AB372: 54056 | AC372: 06-07 | AD372: 4081 | AE372: 7 | AF372: DISCOVERY PUBLIC SCHOOL FARIBAULT | AG372: 0 | AH372: 7 | AI372: DISCOVERY PUBLIC SCHOOL FARIBAULT | AJ372: 0 | AK372: =AG372*AM372 -> 0 | AL372: =AJ372*AM372 -> 0 | AM372: -1 | AO372: =Y372-K372 -> 0 | AP372: =Z372-L372 -> 3019 | AQ372: =AA372-Q372 -> 987 | AR372: =AB372-R372 -> 12522
A373: 11 | B373: Twin Cities Metropolitan Area | C373: 07 | D373: 62 | E373: Ramsey | F373: DUGSI ACADEMY | G373: 4153 | H373: Charter | I373: St. Paul | J373: 184.66 | K373: 0 | L373: 4041 | M373: 4041 | N373: 1509922 | O373: 12079 | P373: 352879 | Q373: 1874880 | R373: 291058 | S373: 2169979 | T373: 109837 | U373: 0 | V373: 0 | W373: 0 | X373: 2279817 | Y373: 0 | Z373: 4173 | AA373: 1878865 | AB373: 396779 | AC373: 06-07 | AD373: 4153 | AE373: 7 | AF373: DUGSI ACADEMY | AG373: 0 | AH373: 7 | AI373: DUGSI ACADEMY | AJ373: 0 | AK373: =AG373*AM373 -> 0 | AL373: =AJ373*AM373 -> 0 | AM373: -1 | AO373: =Y373-K373 -> 0 | AP373: =Z373-L373 -> 132 | AQ373: =AA373-Q373 -> 3985 | AR373: =AB373-R373 -> 105721
A374: 11 | B374: Twin Cities Metropolitan Area | C374: 07 | D374: 82 | E374: Washington | F374: DULUTH PUBLIC SCHOOLS ACADEMY | G374: 4020 | H374: Charter | I374: Statewide | J374: 789.96 | K374: 0 | L374: 66804 | M374: 66804 | N374: 6064093 | O374: 610437 | P374: 531820 | Q374: 7206350 | R374: 515930 | S374: 7789084 | T374: 298689 | U374: 72349 | V374: 0 | W374: 0 | X374: 8160121 | Y374: 0 | Z374: 224352 | AA374: 7227568 | AB374: 708201 | AC374: 06-07 | AD374: 4020 | AE374: 7 | AF374: DULUTH PUBLIC SCHOOLS ACADEMY | AG374: 0 | AH374: 7 | AI374: DULUTH PUBLIC SCHOOLS ACADEMY | AJ374: 0 | AK374: =AG374*AM374 -> 0 | AL374: =AJ374*AM374 -> 0 | AM374: -1 | AO374: =Y374-K374 -> 0 | AP374: =Z374-L374 -> 157548 | AQ374: =AA374-Q374 -> 21218 | AR374: =AB374-R374 -> 192271
A375: 11 | B375: Twin Cities Metropolitan Area | C375: 07 | D375: 27 | E375: Hennepin | F375: DUNWOODY ACADEMY | G375: 4173 | H375: Charter | J375: 0 | K375: 0 | L375: 492201 | M375: 492201 | N375: 0 | O375: 0 | P375: 0 | Q375: 0 | R375: 104495 | S375: 596696 | T375: 0 | U375: 0 | V375: 0 | W375: 0 | X375: 596696 | Y375: 0 | Z375: 492201 | AA375: 0 | AB375: 104495 | AC375: 06-07 | AD375: 4173 | AE375: 7 | AF375: DUNWOODY ACADEMY | AG375: 0 | AH375: 7 | AI375: DUNWOODY ACADEMY | AJ375: 0 | AK375: =AG375*AM375 -> 0 | AL375: =AJ375*AM375 -> 0 | AM375: -1 | AO375: =Y375-K375 -> 0 | AP375: =Z375-L375 -> 0 | AQ375: =AA375-Q375 -> 0 | AR375: =AB375-R375 -> 0
A376: 4 | B376: West Central Minnesota | C376: 07 | D376: 21 | E376: Douglas | F376: E.C.H.O. CHARTER SCHOOL | G376: 4026 | H376: Charter | I376: Statewide | J376: 170.21 | K376: 0 | L376: 115377 | M376: 115377 | N376: 1247994 | O376: 159083 | P376: 216144 | Q376: 1623221 | R376: 65373 | S376: 1803971 | T376: 74573 | U376: 0 | V376: 0 | W376: 0 | X376: 1878545 | Y376: 0 | Z376: 147640 | AA376: 1628713 | AB376: 102192 | AC376: 06-07 | AD376: 4026 | AE376: 7 | AF376: E.C.H.O. CHARTER SCHOOL | AG376: 0 | AH376: 7 | AI376: E.C.H.O. CHARTER SCHOOL | AJ376: 0 | AK376: =AG376*AM376 -> 0 | AL376: =AJ376*AM376 -> 0 | AM376: -1 | AO376: =Y376-K376 -> 0 | AP376: =Z376-L376 -> 32263 | AQ376: =AA376-Q376 -> 5492 | AR376: =AB376-R376 -> 36819
A377: 3 | B377: Northeast Minnesota | C377: 07 | D377: 69 | E377: Saint Louis | F377: EAGLE RIDGE ACADEMY CHARTER SCHOOL | G377: 4122 | H377: Charter | I377: Statewide | J377: 196.02 | K377: 0 | L377: 50882 | M377: 50882 | N377: 1305478 | O377: 66183 | P377: 296893 | Q377: 1668554 | R377: 112022 | S377: 1831458 | T377: 0 | U377: 0 | V377: 0 | W377: 0 | X377: 1831458 | Y377: 0 | Z377: 50882 | AA377: 1668554 | AB377: 112022 | AC377: 06-07 | AD377: 4122 | AE377: 7 | AF377: EAGLE RIDGE ACADEMY CHARTER SCHOOL | AG377: 0 | AH377: 7 | AI377: EAGLE RIDGE ACADEMY CHARTER SCHOOL | AJ377: 0 | AK377: =AG377*AM377 -> 0 | AL377: =AJ377*AM377 -> 0 | AM377: -1 | AO377: =Y377-K377 -> 0 | AP377: =Z377-L377 -> 0 | AQ377: =AA377-Q377 -> 0 | AR377: =AB377-R377 -> 0
A378: 7W | B378: Central Minnesota | C378: 07 | D378: 73 | E378: Stearns | F378: EAST RANGE ACADEMY OF TECH &SCIENCE | G378: 4166 | H378: Charter | J378: 0 | K378: 0 | L378: 1484 | M378: 1484 | N378: 0 | O378: 0 | P378: 0 | Q378: 0 | R378: 41719 | S378: 43203 | T378: 0 | U378: 0 | V378: 0 | W378: 0 | X378: 43203 | Y378: 0 | Z378: 1484 | AA378: 0 | AB378: 41719 | AC378: 06-07 | AD378: 4166 | AE378: 7 | AF378: EAST RANGE ACADEMY OF TECH &SCIENCE | AG378: 0 | AH378: 7 | AI378: EAST RANGE ACADEMY OF TECH &SCIENCE | AJ378: 0 | AK378: =AG378*AM378 -> 0 | AL378: =AJ378*AM378 -> 0 | AM378: -1 | AO378: =Y378-K378 -> 0 | AP378: =Z378-L378 -> 0 | AQ378: =AA378-Q378 -> 0 | AR378: =AB378-R378 -> 0
A379: 11 | B379: Twin Cities Metropolitan Area | C379: 07 | D379: 2 | E379: Anoka | F379: ECI' NOMPA WOONSPE | G379: 4028 | H379: Charter | I379: Statewide | J379: 27.21 | K379: 0 | L379: 10661 | M379: 10661 | N379: 212788 | O379: 108700 | P379: 75006 | Q379: 396494 | R379: 149628 | S379: 556783 | T379: 6649 | U379: 0 | V379: 0 | W379: 0 | X379: 563433 | Y379: 0 | Z379: 17310 | AA379: 396495 | AB379: 149628 | AC379: 06-07 | AD379: 4028 | AE379: 7 | AF379: ECI' NOMPA WOONSPE | AG379: 0 | AH379: 7 | AI379: ECI' NOMPA WOONSPE | AJ379: 0 | AK379: =AG379*AM379 -> 0 | AL379: =AJ379*AM379 -> 0 | AM379: -1 | AO379: =Y379-K379 -> 0 | AP379: =Z379-L379 -> 6649 | AQ379: =AA379-Q379 -> 1 | AR379: =AB379-R379 -> 0
A380: 9 | B380: South Central Minnesota | C380: 07 | D380: 52 | E380: Nicollet | F380: EDVISIONS OFF CAMPUS SCHOOL | G380: 4151 | H380: Charter | I380: Minneapolis | J380: 65.33 | K380: 0 | L380: 12235 | M380: 12235 | N380: 488689 | O380: 22708 | P380: 50241 | Q380: 561638 | R380: 195901 | S380: 769774 | T380: 0 | U380: 0 | V380: 0 | W380: 0 | X380: 769774 | Y380: 0 | Z380: 12235 | AA380: 561638 | AB380: 195901 | AC380: 06-07 | AD380: 4151 | AE380: 7 | AF380: EDVISIONS OFF CAMPUS SCHOOL | AG380: 0 | AH380: 7 | AI380: EDVISIONS OFF CAMPUS SCHOOL | AJ380: 0 | AK380: =AG380*AM380 -> 0 | AL380: =AJ380*AM380 -> 0 | AM380: -1 | AO380: =Y380-K380 -> 0 | AP380: =Z380-L380 -> 0 | AQ380: =AA380-Q380 -> 0 | AR380: =AB380-R380 -> 0
A381: 11 | B381: Twin Cities Metropolitan Area | C381: 07 | D381: 27 | E381: Hennepin | F381: EL COLEGIO CHARTER SCHOOL | G381: 4057 | H381: Charter | I381: Minneapolis | J381: 91.39 | K381: 0 | L381: 99168 | M381: 99168 | N381: 762669 | O381: 88581 | P381: 175256 | Q381: 1026506 | R381: 61727 | S381: 1187401 | T381: 36802 | U381: 0 | V381: 0 | W381: 0 | X381: 1224204 | Y381: 0 | Z381: 99460 | AA381: 1028080 | AB381: 96664 | AC381: 06-07 | AD381: 4057 | AE381: 7 | AF381: EL COLEGIO CHARTER SCHOOL | AG381: 0 | AH381: 7 | AI381: EL COLEGIO CHARTER SCHOOL | AJ381: 0 | AK381: =AG381*AM381 -> 0 | AL381: =AJ381*AM381 -> 0 | AM381: -1 | AO381: =Y381-K381 -> 0 | AP381: =Z381-L381 -> 292 | AQ381: =AA381-Q381 -> 1574 | AR381: =AB381-R381 -> 34937
A382: 11 | B382: Twin Cities Metropolitan Area | C382: 07 | D382: 82 | E382: Washington | F382: ELOM INTERNATIONAL SCHOOL | G382: 4165 | H382: Charter | J382: 0 | K382: 0 | L382: 208116 | M382: 208116 | N382: 0 | O382: 0 | P382: 0 | Q382: 0 | R382: 115204 | S382: 323320 | T382: 0 | U382: 0 | V382: 0 | W382: 0 | X382: 323320 | Y382: 0 | Z382: 208116 | AA382: 0 | AB382: 115204 | AC382: 06-07 | AD382: 4165 | AE382: 7 | AF382: ELOM INTERNATIONAL SCHOOL | AG382: 0 | AH382: 7 | AI382: ELOM INTERNATIONAL SCHOOL | AJ382: 0 | AK382: =AG382*AM382 -> 0 | AL382: =AJ382*AM382 -> 0 | AM382: -1 | AO382: =Y382-K382 -> 0 | AP382: =Z382-L382 -> 0 | AQ382: =AA382-Q382 -> 0 | AR382: =AB382-R382 -> 0
A383: 10 | B383: Southeast Minnesota | C383: 07 | D383: 28 | E383: Houston | F383: EMILY CHARTER SCHOOL | G383: 4012 | H383: Charter | I383: Statewide | J383: 59.72 | K383: 0 | L383: 28645 | M383: 28645 | N383: 400216 | O383: 54359 | P383: 71254 | Q383: 525829 | R383: 34368 | S383: 588842 | T383: 28923 | U383: 6503 | V383: 0 | W383: 0 | X383: 624268 | Y383: 0 | Z383: 42505 | AA383: 533917 | AB383: 47846 | AC383: 06-07 | AD383: 4012 | AE383: 7 | AF383: EMILY CHARTER SCHOOL | AG383: 270 | AH383: 7 | AI383: EMILY CHARTER SCHOOL | AJ383: 0 | AK383: =AG383*AM383 -> -270 | AL383: =AJ383*AM383 -> 0 | AM383: -1 | AO383: =Y383-K383 -> 0 | AP383: =Z383-L383 -> 13860 | AQ383: =AA383-Q383 -> 8088 | AR383: =AB383-R383 -> 13478
A384: 10 | B384: Southeast Minnesota | C384: 07 | D384: 66 | E384: Rice | F384: EMILY O. GOODRIDGE-GREY ACCELERATED | G384: 4180 | H384: Charter | I384: Minneapolis | J384: 0 | K384: 0 | L384: 168 | M384: 168 | N384: 0 | O384: 0 | P384: 0 | Q384: 0 | R384: 51752 | S384: 51920 | T384: 0 | U384: 0 | V384: 0 | W384: 0 | X384: 51920 | Y384: 0 | Z384: 168 | AA384: 0 | AB384: 51752 | AC384: 06-07 | AD384: 4180 | AE384: 7 | AF384: EMILY O. GOODRIDGE-GREY ACCELERATED | AG384: 0 | AH384: 7 | AI384: EMILY O. GOODRIDGE-GREY ACCELERATED | AJ384: 0 | AK384: =AG384*AM384 -> 0 | AL384: =AJ384*AM384 -> 0 | AM384: -1 | AO384: =Y384-K384 -> 0 | AP384: =Z384-L384 -> 0 | AQ384: =AA384-Q384 -> 0 | AR384: =AB384-R384 -> 0
A385: 10 | B385: Southeast Minnesota | C385: 07 | D385: 55 | E385: Olmsted | F385: EXCELL ACADEMY CHARTER | G385: 4068 | H385: Charter | I385: Statewide | J385: 290.65 | K385: 0 | L385: 56030 | M385: 56030 | N385: 1920598 | O385: 213513 | P385: 430880 | Q385: 2564991 | R385: 127638 | S385: 2748659 | T385: 174887 | U385: 219659 | V385: 0 | W385: 0 | X385: 3143206 | Y385: 0 | Z385: 287309 | AA385: 2579538 | AB385: 276359 | AC385: 06-07 | AD385: 4068 | AE385: 7 | AF385: EXCELL ACADEMY CHARTER | AG385: 5121.6 | AH385: 7 | AI385: EXCELL ACADEMY CHARTER | AJ385: 0 | AK385: =AG385*AM385 -> -5121.6 | AL385: =AJ385*AM385 -> 0 | AM385: -1 | AO385: =Y385-K385 -> 0 | AP385: =Z385-L385 -> 231279 | AQ385: =AA385-Q385 -> 14547 | AR385: =AB385-R385 -> 148721
A386: 11 | B386: Twin Cities Metropolitan Area | C386: 07 | D386: 27 | E386: Hennepin | F386: FACE TO FACE ACADEMY | G386: 4036 | H386: Charter | I386: St. Paul | J386: 61.6 | K386: 0 | L386: 53067 | M386: 53067 | N386: 473940 | O386: 53888 | P386: 96001 | Q386: 623829 | R386: 42681 | S386: 719577 | T386: 13048 | U386: 0 | V386: 0 | W386: 0 | X386: 732624 | Y386: 0 | Z386: 53067 | AA386: 624698 | AB386: 54859 | AC386: 06-07 | AD386: 4036 | AE386: 7 | AF386: FACE TO FACE ACADEMY | AG386: 0 | AH386: 7 | AI386: FACE TO FACE ACADEMY | AJ386: 0 | AK386: =AG386*AM386 -> 0 | AL386: =AJ386*AM386 -> 0 | AM386: -1 | AO386: =Y386-K386 -> 0 | AP386: =Z386-L386 -> 0 | AQ386: =AA386-Q386 -> 869 | AR386: =AB386-R386 -> 12178
A387: 2 | B387: Headwaters | C387: 07 | D387: 4 | E387: Beltrami | F387: FOUR DIRECTIONS CHARTER SCHOOLS | G387: 4052 | H387: Charter | I387: Minneapolis | J387: 98.74 | K387: 0 | L387: 10035 | M387: 10035 | N387: 907045 | O387: 179048 | P387: 107383 | Q387: 1193476 | R387: 94532 | S387: 1298043 | T387: 3614 | U387: 0 | V387: 0 | W387: 0 | X387: 1301656 | Y387: 0 | Z387: 13649 | AA387: 1193475 | AB387: 94532 | AC387: 06-07 | AD387: 4052 | AE387: 7 | AF387: FOUR DIRECTIONS CHARTER SCHOOLS | AG387: 0 | AH387: 7 | AI387: FOUR DIRECTIONS CHARTER SCHOOLS | AJ387: 0 | AK387: =AG387*AM387 -> 0 | AL387: =AJ387*AM387 -> 0 | AM387: -1 | AO387: =Y387-K387 -> 0 | AP387: =Z387-L387 -> 3614 | AQ387: =AA387-Q387 -> -1 | AR387: =AB387-R387 -> 0
A388: 5 | B388: North Central Minnesota | C388: 07 | D388: 18 | E388: Crow Wing | F388: FRASER ACADEMY | G388: 4113 | H388: Charter | I388: Minneapolis | J388: 69.95 | K388: 0 | L388: 86982 | M388: 86982 | N388: 405697 | O388: 1498269 | P388: 91524 | Q388: 1995490 | R388: 116718 | S388: 2199190 | T388: 756 | U388: 0 | V388: 0 | W388: 0 | X388: 2199946 | Y388: 0 | Z388: 86982 | AA388: 1995505 | AB388: 117459 | AC388: 06-07 | AD388: 4113 | AE388: 7 | AF388: FRASER ACADEMY | AG388: 0 | AH388: 7 | AI388: FRASER ACADEMY | AJ388: 0 | AK388: =AG388*AM388 -> 0 | AL388: =AJ388*AM388 -> 0 | AM388: -1 | AO388: =Y388-K388 -> 0 | AP388: =Z388-L388 -> 0 | AQ388: =AA388-Q388 -> 15 | AR388: =AB388-R388 -> 741
A389: 10 | B389: Southeast Minnesota | C389: 07 | D389: 55 | E389: Olmsted | F389: FRIENDSHIP ACDMY OF FINE ARTS CHTR. | G389: 4079 | H389: Charter | I389: Minneapolis | J389: 94.53 | K389: 0 | L389: 44942 | M389: 44942 | N389: 664325 | O389: 18177 | P389: 81381 | Q389: 763883 | R389: 73086 | S389: 881911 | T389: 59200 | U389: 0 | V389: 0 | W389: 0 | X389: 941110 | Y389: 0 | Z389: 45614 | AA389: 764940 | AB389: 130556 | AC389: 06-07 | AD389: 4079 | AE389: 7 | AF389: FRIENDSHIP ACDMY OF FINE ARTS CHTR. | AG389: 0 | AH389: 7 | AI389: FRIENDSHIP ACDMY OF FINE ARTS CHTR. | AJ389: 0 | AK389: =AG389*AM389 -> 0 | AL389: =AJ389*AM389 -> 0 | AM389: -1 | AO389: =Y389-K389 -> 0 | AP389: =Z389-L389 -> 672 | AQ389: =AA389-Q389 -> 1057 | AR389: =AB389-R389 -> 57470
A390: 10 | B390: Southeast Minnesota | C390: 07 | D390: 85 | E390: Winona | F390: GENERAL JOHN VESSEY JR LEADERSHIP | G390: 4108 | H390: Charter | I390: Statewide | J390: 107.81 | K390: 0 | L390: 53395 | M390: 53395 | N390: 886372 | O390: 60135 | P390: 152899 | Q390: 1099406 | R390: 164401 | S390: 1317202 | T390: 32534 | U390: 0 | V390: 0 | W390: 0 | X390: 1349737 | Y390: 0 | Z390: 64897 | AA390: 1100941 | AB390: 183899 | AC390: 06-07 | AD390: 4108 | AE390: 7 | AF390: GENERAL JOHN VESSEY JR LEADERSHIP | AG390: 0 | AH390: 7 | AI390: GENERAL JOHN VESSEY JR LEADERSHIP | AJ390: 0 | AK390: =AG390*AM390 -> 0 | AL390: =AJ390*AM390 -> 0 | AM390: -1 | AO390: =Y390-K390 -> 0 | AP390: =Z390-L390 -> 11502 | AQ390: =AA390-Q390 -> 1535 | AR390: =AB390-R390 -> 19498
A391: 9 | B391: South Central Minnesota | C391: 07 | D391: 7 | E391: Blue Earth | F391: GLACIAL HILLS ELEMENTARY | G391: 4168 | H391: Charter | I391: Statewide | J391: 0 | K391: 0 | L391: 34273 | M391: 34273 | N391: 0 | O391: 0 | P391: 0 | Q391: 0 | R391: 72000 | S391: 106273 | T391: 0 | U391: 0 | V391: 0 | W391: 0 | X391: 106273 | Y391: 0 | Z391: 34273 | AA391: 0 | AB391: 72000 | AC391: 06-07 | AD391: 4168 | AE391: 7 | AF391: GLACIAL HILLS ELEMENTARY | AG391: 0 | AH391: 7 | AI391: GLACIAL HILLS ELEMENTARY | AJ391: 0 | AK391: =AG391*AM391 -> 0 | AL391: =AJ391*AM391 -> 0 | AM391: -1 | AO391: =Y391-K391 -> 0 | AP391: =Z391-L391 -> 0 | AQ391: =AA391-Q391 -> 0 | AR391: =AB391-R391 -> 0
A392: 11 | B392: Twin Cities Metropolitan Area | C392: 07 | D392: 27 | E392: Hennepin | F392: GREAT EXPECTATIONS | G392: 4100 | H392: Charter | I392: Statewide | J392: 40.46 | K392: 0 | L392: 12167 | M392: 12167 | N392: 229095 | O392: 91935 | P392: 51325 | Q392: 372355 | R392: 191836 | S392: 576358 | T392: 771 | U392: 0 | V392: 0 | W392: 0 | X392: 577128 | Y392: 0 | Z392: 12167 | AA392: 372388 | AB392: 192573 | AC392: 06-07 | AD392: 4100 | AE392: 7 | AF392: GREAT EXPECTATIONS | AG392: 0 | AH392: 7 | AI392: GREAT EXPECTATIONS | AJ392: 0 | AK392: =AG392*AM392 -> 0 | AL392: =AJ392*AM392 -> 0 | AM392: -1 | AO392: =Y392-K392 -> 0 | AP392: =Z392-L392 -> 0 | AQ392: =AA392-Q392 -> 33 | AR392: =AB392-R392 -> 737
A393: 11 | B393: Twin Cities Metropolitan Area | C393: 07 | D393: 27 | E393: Hennepin | F393: GREAT RIVER EDUCATION CENTER | G393: 4048 | H393: Charter | I393: Statewide | J393: 29.15 | K393: 0 | L393: 4911 | M393: 4911 | N393: 229433 | O393: 50497 | P393: 43860 | Q393: 323790 | R393: 15365 | S393: 344066 | T393: 0 | U393: 0 | V393: 0 | W393: 0 | X393: 344066 | Y393: 0 | Z393: 4911 | AA393: 323790 | AB393: 15365 | AC393: 06-07 | AD393: 4048 | AE393: 7 | AF393: GREAT RIVER EDUCATION CENTER | AG393: 0 | AH393: 7 | AI393: GREAT RIVER EDUCATION CENTER | AJ393: 0 | AK393: =AG393*AM393 -> 0 | AL393: =AJ393*AM393 -> 0 | AM393: -1 | AO393: =Y393-K393 -> 0 | AP393: =Z393-L393 -> 0 | AQ393: =AA393-Q393 -> 0 | AR393: =AB393-R393 -> 0
A394: 11 | B394: Twin Cities Metropolitan Area | C394: 07 | D394: 62 | E394: Ramsey | F394: GREAT RIVER SCHOOL | G394: 4105 | H394: Charter | I394: St. Paul | J394: 174.46 | K394: 0 | L394: 145654 | M394: 145654 | N394: 1215108 | O394: 169535 | P394: 258913 | Q394: 1643556 | R394: 92763 | S394: 1881973 | T394: 0 | U394: 0 | V394: 0 | W394: 0 | X394: 1881973 | Y394: 0 | Z394: 145654 | AA394: 1643556 | AB394: 92763 | AC394: 06-07 | AD394: 4105 | AE394: 7 | AF394: GREAT RIVER SCHOOL | AG394: 0 | AH394: 7 | AI394: GREAT RIVER SCHOOL | AJ394: 0 | AK394: =AG394*AM394 -> 0 | AL394: =AJ394*AM394 -> 0 | AM394: -1 | AO394: =Y394-K394 -> 0 | AP394: =Z394-L394 -> 0 | AQ394: =AA394-Q394 -> 0 | AR394: =AB394-R394 -> 0
... A415: 6E | B415: Southwest Central Minnesota | C415: 07 | D415: 43 | E415: McLeod | F415: LIGHTHOUSE ACADEMY OF NATIONS | G415: 4131 | H415: Charter | I415: Minneapolis | J415: 130.93 | K415: 0 | L415: 47902 | M415: 47902 | N415: 1242956 | O415: 6043 | P415: 286662 | Q415: 1535661 | R415: 202808 | S415: 1786371 | T415: 52055 | U415: 0 | V415: 0 | W415: 0 | X415: 1838427 | Y415: 0 | Z415: 47902 | AA415: 1537190 | AB415: 253335 | AC415: 06-07 | AD415: 4131 | AE415: 7 | AF415: LIGHTHOUSE ACADEMY OF NATIONS | AG415: 0 | AH415: 7 | AI415: LIGHTHOUSE ACADEMY OF NATIONS | AJ415: 0 | AK415: =AG415*AM415 -> 0 | AL415: =AJ415*AM415 -> 0 | AM415: -1 | AO415: =Y415-K415 -> 0 | AP415: =Z415-L415 -> 0 | AQ415: =AA415-Q415 -> 1529 | AR415: =AB415-R415 -> 50527
A416: 7E | B416: East Central Minnesota | C416: 07 | D416: 13 | E416: Chisago | F416: LINCOLN INTERNATIONAL SCHOOL | G416: 4178 | H416: Charter | J416: 0 | K416: 0 | L416: 0 | M416: 0 | N416: 0 | O416: 0 | P416: 0 | Q416: 0 | R416: 41518 | S416: 41518 | T416: 0 | U416: 0 | V416: 0 | W416: 0 | X416: 41518 | Y416: 0 | Z416: 0 | AA416: 0 | AB416: 41518 | AC416: 06-07 | AD416: 4178 | AE416: 7 | AF416: LINCOLN INTERNATIONAL SCHOOL | AG416: 0 | AH416: 7 | AI416: LINCOLN INTERNATIONAL SCHOOL | AJ416: 0 | AK416: =AG416*AM416 -> 0 | AL416: =AJ416*AM416 -> 0 | AM416: -1 | AO416: =Y416-K416 -> 0 | AP416: =Z416-L416 -> 0 | AQ416: =AA416-Q416 -> 0 | AR416: =AB416-R416 -> 0
A417: 11 | B417: Twin Cities Metropolitan Area | C417: 07 | D417: 27 | E417: Hennepin | F417: LONG TIENG ACADEMY | G417: 4175 | H417: Charter | J417: 0 | K417: 0 | L417: 56232 | M417: 56232 | N417: 0 | O417: 0 | P417: 0 | Q417: 0 | R417: 1451 | S417: 57683 | T417: 0 | U417: 0 | V417: 0 | W417: 0 | X417: 57683 | Y417: 0 | Z417: 56232 | AA417: 0 | AB417: 1451 | AC417: 06-07 | AD417: 4175 | AE417: 7 | AF417: LONG TIENG ACADEMY | AG417: 0 | AH417: 7 | AI417: LONG TIENG ACADEMY | AJ417: 0 | AK417: =AG417*AM417 -> 0 | AL417: =AJ417*AM417 -> 0 | AM417: -1 | AO417: =Y417-K417 -> 0 | AP417: =Z417-L417 -> 0 | AQ417: =AA417-Q417 -> 0 | AR417: =AB417-R417 -> 0
A418: 11 | B418: Twin Cities Metropolitan Area | C418: 07 | D418: 62 | E418: Ramsey | F418: LOVEWORKS ACADEMY FOR ARTS | G418: 4139 | H418: Charter | I418: Statewide | J418: 257.62 | K418: 0 | L418: 4000 | M418: 4000 | N418: 1520424 | O418: 64463 | P418: 413685 | Q418: 1998572 | R418: 250456 | S418: 2253028 | T418: 68216 | U418: 0 | V418: 0 | W418: 0 | X418: 2321242 | Y418: 0 | Z418: 15955 | AA418: 2003307 | AB418: 301980 | AC418: 06-07 | AD418: 4139 | AE418: 7 | AF418: LOVEWORKS ACADEMY FOR ARTS | AG418: 0 | AH418: 7 | AI418: LOVEWORKS ACADEMY FOR ARTS | AJ418: 0 | AK418: =AG418*AM418 -> 0 | AL418: =AJ418*AM418 -> 0 | AM418: -1 | AO418: =Y418-K418 -> 0 | AP418: =Z418-L418 -> 11955 | AQ418: =AA418-Q418 -> 4735 | AR418: =AB418-R418 -> 51524
A419: 11 | B419: Twin Cities Metropolitan Area | C419: 07 | D419: 19 | E419: Dakota | F419: MAIN STREET SCHOOL PERFORMING ARTS | G419: 4110 | H419: Charter | I419: Statewide | J419: 191.5 | K419: 0 | L419: 310577 | M419: 310577 | N419: 1316715 | O419: 126805 | P419: 302182 | Q419: 1745702 | R419: 141754 | S419: 2198033 | T419: 0 | U419: 0 | V419: 0 | W419: 0 | X419: 2198033 | Y419: 0 | Z419: 310577 | AA419: 1745702 | AB419: 141754 | AC419: 06-07 | AD419: 4110 | AE419: 7 | AF419: MAIN STREET SCHOOL PERFORMING ARTS | AG419: 0 | AH419: 7 | AI419: MAIN STREET SCHOOL PERFORMING ARTS | AJ419: 0 | AK419: =AG419*AM419 -> 0 | AL419: =AJ419*AM419 -> 0 | AM419: -1 | AO419: =Y419-K419 -> 0 | AP419: =Z419-L419 -> 0 | AQ419: =AA419-Q419 -> 0 | AR419: =AB419-R419 -> 0
A420: 3 | B420: Northeast Minnesota | C420: 07 | D420: 16 | E420: Cook | F420: MATH & SCIENCE ACADEMY | G420: 4043 | H420: Charter | I420: Statewide | J420: 280.28 | K420: 0 | L420: 47313 | M420: 47313 | N420: 1797418 | O420: 148719 | P420: 422715 | Q420: 2368852 | R420: 65104 | S420: 2481269 | T420: 0 | U420: 0 | V420: 0 | W420: 0 | X420: 2481269 | Y420: 0 | Z420: 47313 | AA420: 2368852 | AB420: 65104 | AC420: 06-07 | AD420: 4043 | AE420: 7 | AF420: MATH & SCIENCE ACADEMY | AG420: 0 | AH420: 7 | AI420: MATH & SCIENCE ACADEMY | AJ420: 0 | AK420: =AG420*AM420 -> 0 | AL420: =AJ420*AM420 -> 0 | AM420: -1 | AO420: =Y420-K420 -> 0 | AP420: =Z420-L420 -> 0 | AQ420: =AA420-Q420 -> 0 | AR420: =AB420-R420 -> 0
A421: 11 | B421: Twin Cities Metropolitan Area | C421: 07 | D421: 62 | E421: Ramsey | F421: METRO DEAF SCHOOL | G421: 4005 | H421: Charter | I421: St. Paul | J421: 65.15 | K421: 0 | L421: 157746 | M421: 157746 | N421: 69773 | O421: 2173881 | P421: 105930 | Q421: 2349584 | R421: 106240 | S421: 2613570 | T421: 14954 | U421: 0 | V421: 0 | W421: 0 | X421: 2628525 | Y421: 0 | Z421: 165333 | AA421: 2350056 | AB421: 113136 | AC421: 06-07 | AD421: 4005 | AE421: 7 | AF421: METRO DEAF SCHOOL | AG421: 0 | AH421: 7 | AI421: METRO DEAF SCHOOL | AJ421: 0 | AK421: =AG421*AM421 -> 0 | AL421: =AJ421*AM421 -> 0 | AM421: -1 | AO421: =Y421-K421 -> 0 | AP421: =Z421-L421 -> 7587 | AQ421: =AA421-Q421 -> 472 | AR421: =AB421-R421 -> 6896
A422: 11 | B422: Twin Cities Metropolitan Area | C422: 07 | D422: 27 | E422: Hennepin | F422: MILROY AREA CHARTER SCHOOL | G422: 4138 | H422: Charter | I422: Statewide | J422: 43.2 | K422: 0 | L422: 20604 | M422: 20604 | N422: 276673 | O422: 11446 | P422: 90331 | Q422: 378450 | R422: 184578 | S422: 583632 | T422: 0 | U422: 0 | V422: 0 | W422: 0 | X422: 583632 | Y422: 0 | Z422: 20604 | AA422: 378450 | AB422: 184578 | AC422: 06-07 | AD422: 4138 | AE422: 7 | AF422: MILROY AREA CHARTER SCHOOL | AG422: 0 | AH422: 7 | AI422: MILROY AREA CHARTER SCHOOL | AJ422: 0 | AK422: =AG422*AM422 -> 0 | AL422: =AJ422*AM422 -> 0 | AM422: -1 | AO422: =Y422-K422 -> 0 | AP422: =Z422-L422 -> 0 | AQ422: =AA422-Q422 -> 0 | AR422: =AB422-R422 -> 0
A423: 11 | B423: Twin Cities Metropolitan Area | C423: 07 | D423: 27 | E423: Hennepin | F423: MINISINAAKWAANG LEADERSHIP ACADEMY | G423: 4177 | H423: Charter | J423: 0 | K423: 0 | L423: 26800 | M423: 26800 | N423: 0 | O423: 0 | P423: 0 | Q423: 0 | R423: 57774 | S423: 84574 | T423: 0 | U423: 0 | V423: 0 | W423: 0 | X423: 84574 | Y423: 0 | Z423: 26800 | AA423: 0 | AB423: 57774 | AC423: 06-07 | AD423: 4177 | AE423: 7 | AF423: MINISINAAKWAANG LEADERSHIP ACADEMY | AG423: 0 | AH423: 7 | AI423: MINISINAAKWAANG LEADERSHIP ACADEMY | AJ423: 0 | AK423: =AG423*AM423 -> 0 | AL423: =AJ423*AM423 -> 0 | AM423: -1 | AO423: =Y423-K423 -> 0 | AP423: =Z423-L423 -> 0 | AQ423: =AA423-Q423 -> 0 | AR423: =AB423-R423 -> 0
A424: 11 | B424: Twin Cities Metropolitan Area | C424: 07 | D424: 2 | E424: Anoka | F424: MINNEAPOLIS ACADEMY CHARTER SCHOOL | G424: 4115 | H424: Charter | I424: Minneapolis | J424: 112.07 | K424: 0 | L424: 69020 | M424: 69020 | N424: 941101 | O424: 73419 | P424: 150550 | Q424: 1165070 | R424: 150033 | S424: 1384123 | T424: 60211 | U424: 0 | V424: 0 | W424: 0 | X424: 1444334 | Y424: 0 | Z424: 72445 | AA424: 1168972 | AB424: 202917 | AC424: 06-07 | AD424: 4115 | AE424: 7 | AF424: MINNEAPOLIS ACADEMY CHARTER SCHOOL | AG424: 0 | AH424: 7 | AI424: MINNEAPOLIS ACADEMY CHARTER SCHOOL | AJ424: 0 | AK424: =AG424*AM424 -> 0 | AL424: =AJ424*AM424 -> 0 | AM424: -1 | AO424: =Y424-K424 -> 0 | AP424: =Z424-L424 -> 3425 | AQ424: =AA424-Q424 -> 3902 | AR424: =AB424-R424 -> 52884
A425: 11 | B425: Twin Cities Metropolitan Area | C425: 07 | D425: 27 | E425: Hennepin | F425: MINNESOTA INTERNSHIP CENTER | G425: 4102 | H425: Charter | I425: Minneapolis | J425: 423.75 | K425: 0 | L425: 49959 | M425: 49959 | N425: 4176083 | O425: 192597 | P425: 275197 | Q425: 4643877 | R425: 279764 | S425: 4973600 | T425: 156935 | U425: 46338 | V425: 0 | W425: 0 | X425: 5176872 | Y425: 0 | Z425: 80651 | AA425: 4667264 | AB425: 428957 | AC425: 06-07 | AD425: 4102 | AE425: 7 | AF425: MINNESOTA INTERNSHIP CENTER | AG425: 0 | AH425: 7 | AI425: MINNESOTA INTERNSHIP CENTER | AJ425: 46337.59 | AK425: =AG425*AM425 -> 0 | AL425: =AJ425*AM425 -> -46337.59 | AM425: -1 | AO425: =Y425-K425 -> 0 | AP425: =Z425-L425 -> 30692 | AQ425: =AA425-Q425 -> 23387 | AR425: =AB425-R425 -> 149193
A426: 2 | B426: Headwaters | C426: 07 | D426: 4 | E426: Beltrami | F426: MINNESOTA NEW COUNTRY SCHOOL | G426: 4007 | H426: Charter | I426: Statewide | J426: 103.42 | K426: 0 | L426: 39731 | M426: 39731 | N426: 757240 | O426: 117703 | P426: 144916 | Q426: 1019859 | R426: 32705 | S426: 1092295 | T426: 0 | U426: 0 | V426: 0 | W426: 0 | X426: 1092295 | Y426: 0 | Z426: 39731 | AA426: 1019859 | AB426: 32705 | AC426: 06-07 | AD426: 4007 | AE426: 7 | AF426: MINNESOTA NEW COUNTRY SCHOOL | AG426: 0 | AH426: 7 | AI426: MINNESOTA NEW COUNTRY SCHOOL | AJ426: 0 | AK426: =AG426*AM426 -> 0 | AL426: =AJ426*AM426 -> 0 | AM426: -1 | AO426: =Y426-K426 -> 0 | AP426: =Z426-L426 -> 0 | AQ426: =AA426-Q426 -> 0 | AR426: =AB426-R426 -> 0
A427: 2 | B427: Headwaters | C427: 07 | D427: 4 | E427: Beltrami | F427: MINNESOTA NORTH STAR ACADEMY | G427: 4101 | H427: Charter | I427: St. Paul | J427: 23.5 | K427: 0 | L427: 112939 | M427: 112939 | N427: 34223 | O427: 523489 | P427: 29902 | Q427: 587614 | R427: 11253 | S427: 711806 | T427: 8120 | U427: 0 | V427: 0 | W427: 0 | X427: 719926 | Y427: 0 | Z427: 117390 | AA427: 587853 | AB427: 14683 | AC427: 06-07 | AD427: 4101 | AE427: 7 | AF427: MINNESOTA NORTH STAR ACADEMY | AG427: 0 | AH427: 7 | AI427: MINNESOTA NORTH STAR ACADEMY | AJ427: 0 | AK427: =AG427*AM427 -> 0 | AL427: =AJ427*AM427 -> 0 | AM427: -1 | AO427: =Y427-K427 -> 0 | AP427: =Z427-L427 -> 4451 | AQ427: =AA427-Q427 -> 239 | AR427: =AB427-R427 -> 3430
A428: 11 | B428: Twin Cities Metropolitan Area | C428: 07 | D428: 62 | E428: Ramsey | F428: MINNESOTA ONLINE HIGH SCHOOL | G428: 4150 | H428: Charter | I428: Minneapolis | J428: 93.84 | K428: 0 | L428: 10785 | M428: 10785 | N428: 675472 | O428: 9760 | P428: 72134 | Q428: 757366 | R428: 122772 | S428: 890923 | T428: 0 | U428: 0 | V428: 0 | W428: 0 | X428: 890922 | Y428: 0 | Z428: 10785 | AA428: 757365 | AB428: 122772 | AC428: 06-07 | AD428: 4150 | AE428: 7 | AF428: MINNESOTA ONLINE HIGH SCHOOL | AG428: 0 | AH428: 7 | AI428: MINNESOTA ONLINE HIGH SCHOOL | AJ428: 0 | AK428: =AG428*AM428 -> 0 | AL428: =AJ428*AM428 -> 0 | AM428: -1 | AO428: =Y428-K428 -> 0 | AP428: =Z428-L428 -> 0 | AQ428: =AA428-Q428 -> -1 | AR428: =AB428-R428 -> 0
A429: 11 | B429: Twin Cities Metropolitan Area | C429: 07 | D429: 62 | E429: Ramsey | F429: MINNESOTA TRANSITIONS CHARTER SCH | G429: 4017 | H429: Charter | I429: Minneapolis | J429: 1346.13 | K429: 0 | L429: 361509 | M429: 361509 | N429: 10472542 | O429: 456761 | P429: 1240160 | Q429: 12169463 | R429: 721653 | S429: 13252625 | T429: 276082 | U429: 0 | V429: 0 | W429: 0 | X429: 13528707 | Y429: 0 | Z429: 361509 | AA429: 12182842 | AB429: 984356 | AC429: 06-07 | AD429: 4017 | AE429: 7 | AF429: MINNESOTA TRANSITIONS CHARTER SCH | AG429: 0 | AH429: 7 | AI429: MINNESOTA TRANSITIONS CHARTER SCH | AJ429: 0 | AK429: =AG429*AM429 -> 0 | AL429: =AJ429*AM429 -> 0 | AM429: -1 | AO429: =Y429-K429 -> 0 | AP429: =Z429-L429 -> 0 | AQ429: =AA429-Q429 -> 13379 | AR429: =AB429-R429 -> 262703
A430: 11 | B430: Twin Cities Metropolitan Area | C430: 07 | D430: 27 | E430: Hennepin | F430: MN INTERNATIONAL MIDDLE CHARTER | G430: 4078 | H430: Charter | I430: Minneapolis | J430: 291.36 | K430: 0 | L430: 140828 | M430: 140828 | N430: 2742385 | O430: 124375 | P430: 268218 | Q430: 3134978 | R430: 156952 | S430: 3432758 | T430: 162205 | U430: 0 | V430: 0 | W430: 0 | X430: 3594963 | Y430: 0 | Z430: 140828 | AA430: 3140218 | AB430: 313917 | AC430: 06-07 | AD430: 4078 | AE430: 7 | AF430: MN INTERNATIONAL MIDDLE CHARTER | AG430: 0 | AH430: 7 | AI430: MN INTERNATIONAL MIDDLE CHARTER | AJ430: 0 | AK430: =AG430*AM430 -> 0 | AL430: =AJ430*AM430 -> 0 | AM430: -1 | AO430: =Y430-K430 -> 0 | AP430: =Z430-L430 -> 0 | AQ430: =AA430-Q430 -> 5240 | AR430: =AB430-R430 -> 156965
A431: 11 | B431: Twin Cities Metropolitan Area | C431: 07 | D431: 27 | E431: Hennepin | F431: NAYTAHWAUSH COMMUNITY SCHOOL | G431: 4155 | H431: Charter | I431: Statewide | J431: 92.32 | K431: 0 | L431: 26635 | M431: 26635 | N431: 643308 | O431: 50474 | P431: 149781 | Q431: 843563 | R431: 796358 | S431: 1666556 | T431: 49470 | U431: 0 | V431: 0 | W431: 0 | X431: 1716026 | Y431: 0 | Z431: 33811 | AA431: 845088 | AB431: 837127 | AC431: 06-07 | AD431: 4155 | AE431: 7 | AF431: NAYTAHWAUSH COMMUNITY SCHOOL | AG431: 0 | AH431: 7 | AI431: NAYTAHWAUSH COMMUNITY SCHOOL | AJ431: 0 | AK431: =AG431*AM431 -> 0 | AL431: =AJ431*AM431 -> 0 | AM431: -1 | AO431: =Y431-K431 -> 0 | AP431: =Z431-L431 -> 7176 | AQ431: =AA431-Q431 -> 1525 | AR431: =AB431-R431 -> 40769
A432: 11 | B432: Twin Cities Metropolitan Area | C432: 07 | D432: 62 | E432: Ramsey | F432: NERSTRAND CHARTER SCHOOL | G432: 4055 | H432: Charter | I432: Statewide | J432: 153.98 | K432: 0 | L432: 36999 | M432: 36999 | N432: 809548 | O432: 103865 | P432: 198983 | Q432: 1112396 | R432: 55550 | S432: 1204945 | T432: 0 | U432: 7011 | V432: 0 | W432: 0 | X432: 1211956 | Y432: 0 | Z432: 44010 | AA432: 1112396 | AB432: 55550 | AC432: 06-07 | AD432: 4055 | AE432: 7 | AF432: NERSTRAND CHARTER SCHOOL | AG432: 0 | AH432: 7 | AI432: NERSTRAND CHARTER SCHOOL | AJ432: 0 | AK432: =AG432*AM432 -> 0 | AL432: =AJ432*AM432 -> 0 | AM432: -1 | AO432: =Y432-K432 -> 0 | AP432: =Z432-L432 -> 7011 | AQ432: =AA432-Q432 -> 0 | AR432: =AB432-R432 -> 0
A433: 11 | B433: Twin Cities Metropolitan Area | C433: 07 | D433: 27 | E433: Hennepin | F433: NEW CENTURY CHARTER SCHOOL | G433: 4093 | H433: Charter | I433: Statewide | J433: 145.19 | K433: 0 | L433: 90261 | M433: 90261 | N433: 1058385 | O433: 87845 | P433: 140289 | Q433: 1286519 | R433: 50937 | S433: 1427717 | T433: 29243 | U433: 0 | V433: 0 | W433: 0 | X433: 1456958 | Y433: 0 | Z433: 107708 | AA433: 1287529 | AB433: 61721 | AC433: 06-07 | AD433: 4093 | AE433: 7 | AF433: NEW CENTURY CHARTER SCHOOL | AG433: 0 | AH433: 7 | AI433: NEW CENTURY CHARTER SCHOOL | AJ433: 0 | AK433: =AG433*AM433 -> 0 | AL433: =AJ433*AM433 -> 0 | AM433: -1 | AO433: =Y433-K433 -> 0 | AP433: =Z433-L433 -> 17447 | AQ433: =AA433-Q433 -> 1010 | AR433: =AB433-R433 -> 10784
A434: 11 | B434: Twin Cities Metropolitan Area | C434: 07 | D434: 27 | E434: Hennepin | F434: NEW CITY SCHOOL | G434: 4089 | H434: Charter | I434: Minneapolis | J434: 125.09 | K434: 0 | L434: 7304 | M434: 7304 | N434: 790237 | O434: 108026 | P434: 75756 | Q434: 974019 | R434: 48777 | S434: 1030100 | T434: 44983 | U434: 0 | V434: 0 | W434: 0 | X434: 1075082 | Y434: 0 | Z434: 18692 | AA434: 976122 | AB434: 80268 | AC434: 06-07 | AD434: 4089 | AE434: 7 | AF434: NEW CITY SCHOOL | AG434: 0 | AH434: 7 | AI434: NEW CITY SCHOOL | AJ434: 0 | AK434: =AG434*AM434 -> 0 | AL434: =AJ434*AM434 -> 0 | AM434: -1 | AO434: =Y434-K434 -> 0 | AP434: =Z434-L434 -> 11388 | AQ434: =AA434-Q434 -> 2103 | AR434: =AB434-R434 -> 31491
A435: 11 | B435: Twin Cities Metropolitan Area | C435: 07 | D435: 27 | E435: Hennepin | F435: NEW DISCOVERIES MONTESSORI ACADEMY | G435: 4161 | H435: Charter | I435: Statewide | J435: 79.74 | K435: 0 | L435: 12824 | M435: 12824 | N435: 414207 | O435: 50632 | P435: 139159 | Q435: 603998 | R435: 198058 | S435: 814880 | T435: 22922 | U435: 0 | V435: 0 | W435: 0 | X435: 837803 | Y435: 0 | Z435: 30451 | AA435: 604748 | AB435: 202604 | AC435: 06-07 | AD435: 4161 | AE435: 7 | AF435: NEW DISCOVERIES MONTESSORI ACADEMY | AG435: 0 | AH435: 7 | AI435: NEW DISCOVERIES MONTESSORI ACADEMY | AJ435: 0 | AK435: =AG435*AM435 -> 0 | AL435: =AJ435*AM435 -> 0 | AM435: -1 | AO435: =Y435-K435 -> 0 | AP435: =Z435-L435 -> 17627 | AQ435: =AA435-Q435 -> 750 | AR435: =AB435-R435 -> 4546
...

Sheet District St Wrk
F1: Click here for Definitions
A2: Economic Development Region Number | B2: Economic Development Region | C2: District Type | D2: County Number | E2: County Name | F2: Total Revenues FY07 | G2: District Number | J2: District ADM Served Plus Tuitioned Out | K2: General Fund Revenues
K3: Local Sources | O3: State Sources | R3: Federal Sources
H4: Charter | I4: Charter Location | K4: Property Taxes | L4: Other funds revenues distributed by Local Other State and Federal | M4: Other | O4: General Education Aid | P4: Special Education Aid | Q4: All Other State Aid | R4: Federal | S4: Federal | T4: Other
F5: Counties and Districts | K5: 1. | L5: Local | M5: 2. | N5: State | O5: 4. | P5: 5. | Q5: 6. | R5: 8. | U5: Early Childhood Reduction | V5: ABE Reduction
A6: 3 | B6: Northeast Minnesota | C6: 01 | D6: 1 | E6: Aitkin | F6: AITKIN PUBLIC SCHOOL DISTRICT | G6: 0001 | J6: 1322.2 | K6: 613626 | L6: 183370 | M6: 1325974 | N6: 78700 | O6: 8539952 | P6: 679449 | Q6: 52813 | R6: 255760 | S6: 259551 | T6: 569450 | U6: -98691.4 | V6: -109867.98
A7: 11 | B7: Twin Cities Metropolitan Area | C7: 03 | D7: 27 | E7: Hennepin | F7: MINNEAPOLIS PUBLIC SCHOOL DIST. | G7: 0001 | H7: District | I7: Minneapolis | J7: 39479.31 | K7: 58005565 | L7: 58143868 | M7: 20520348 | N7: 23620461 | O7: 293589390 | P7: 49228337 | Q7: 18490543 | R7: 52989194 | S7: 15279332 | T7: 18756992 | U7: -4444620.9 | V7: -7342147.7
A8: 3 | B8: Northeast Minnesota | C8: 01 | D8: 1 | E8: Aitkin | F8: HILL CITY PUBLIC SCHOOL DISTRICT | G8: 0002 | J8: 314.26 | K8: 59861 | L8: 281927 | M8: 422365 | N8: 116087 | O8: 2659597 | P8: 182721 | Q8: 6745 | R8: 145220 | S8: 86554 | T8: 85299 | U8: -24582.72 | V8: 0
A9: 3 | B9: Northeast Minnesota | C9: 01 | D9: 1 | E9: Aitkin | F9: MCGREGOR PUBLIC SCHOOL DISTRICT | G9: 0004 | J9: 421.83 | K9: 362632 | L9: 731243 | M9: 571834 | N9: 110328 | O9: 3626076 | P9: 220535 | Q9: 90345 | R9: 400799 | S9: 124256 | T9: 169693 | U9: -33513.61 | V9: 0
A10: 11 | B10: Twin Cities Metropolitan Area | C10: 03 | D10: 19 | E10: Dakota | F10: SOUTH ST. PAUL PUBLIC SCHOOL DIST. | G10: 0006 | J10: 3331.77 | K10: 4375528 | L10: 2292847 | M10: 1428160 | N10: 766903 | O10: 21969776 | P10: 2395108 | Q10: 590260 | R10: 1212734 | S10: 684860 | T10: 2391489 | U10: -529225.97 | V10: -429155.35
A11: 11 | B11: Twin Cities Metropolitan Area | C11: 01 | D11: 2 | E11: Anoka | F11: ANOKA-HENNEPIN PUBLIC SCHOOL DIST. | G11: 0011 | J11: 41062.22 | K11: 43956546 | L11: 23666083 | M11: 16656073 | N11: 6546203 | O11: 261189813 | P11: 32332020 | Q11: 8770426 | R11: 12194021 | S11: 5505682 | T11: 23866656 | U11: -3155425.1 | V11: -2883706.4
A12: 11 | B12: Twin Cities Metropolitan Area | C12: 01 | D12: 2 | E12: Anoka | F12: CENTENNIAL PUBLIC SCHOOL DISTRICT | G12: 0012 | J12: 6985.42 | K12: 5921669 | L12: 8193172 | M12: 2129295 | N12: 2338371 | O12: 45247529 | P12: 6124782 | Q12: 162398 | R12: 1658177 | S12: 573391 | T12: 5541619 | U12: -399860.9 | V12: -46184.74
A13: 11 | B13: Twin Cities Metropolitan Area | C13: 01 | D13: 2 | E13: Anoka | F13: COLUMBIA HEIGHTS PUBLIC SCHOOL DIST | G13: 0013 | J13: 3007.27 | K13: 4364222 | L13: 2582653 | M13: 1241359 | N13: 416231 | O13: 21076189 | P13: 2419271 | Q13: 1225006 | R13: 1588601 | S13: 879424 | T13: 2029965 | U13: -295832.13 | V13: -6533.52
A14: 11 | B14: Twin Cities Metropolitan Area | C14: 01 | D14: 2 | E14: Anoka | F14: FRIDLEY PUBLIC SCHOOL DISTRICT | G14: 0014 | J14: 2617.16 | K14: 4032545 | L14: 1226719 | M14: 901577 | N14: 576523 | O14: 17240811 | P14: 2748286 | Q14: 512181 | R14: 1622095 | S14: 586581 | T14: 1558596 | U14: -197003.37 | V14: -45764
A15: 11 | B15: Twin Cities Metropolitan Area | C15: 01 | D15: 2 | E15: Anoka | F15: ST. FRANCIS PUBLIC SCHOOL DISTRICT | G15: 0015 | J15: 5879.67 | K15: 4143303 | L15: 4198029 | M15: 3622109 | N15: 715678 | O15: 37742931 | P15: 2948520 | Q15: 212446 | R15: 1663583 | S15: 737762 | T15: 3745422 | U15: -357035.83 | V15: -77119.78
A16: 11 | B16: Twin Cities Metropolitan Area | C16: 01 | D16: 2 | E16: Anoka | F16: SPRING LAKE PARK PUBLIC SCHOOLS | G16: 0016 | J16: 4712.17 | K16: 5727758 | L16: 4649537 | M16: 1753294 | N16: 376322 | O16: 28313376 | P16: 2695964 | Q16: 215791 | R16: 1646160 | S16: 841192 | T16: 5166465 | U16: -251104.86 | V16: 0
A17: 4 | B17: West Central Minnesota | C17: 01 | D17: 3 | E17: Becker | F17: DETROIT LAKES PUBLIC SCHOOL DIST. | G17: 0022 | J17: 2740.58 | K17: 1347341 | L17: 1314771 | M17: 1331261 | N17: 406387 | O17: 17848049 | P17: 1881048 | Q17: 282182 | R17: 1499213 | S17: 414588 | T17: 891087 | U17: -184375.54 | V17: -124309.58
A18: 4 | B18: West Central Minnesota | C18: 01 | D18: 3 | E18: Becker | F18: FRAZEE-VERGAS PUBLIC SCHOOL DIST. | G18: 0023 | J18: 1019.77 | K18: 324335 | L18: 919946 | M18: 529269 | N18: 222052 | O18: 6959062 | P18: 573577 | Q18: 28893 | R18: 579931 | S18: 231843 | T18: 264713 | U18: -92910.66 | V18: 0
A19: 4 | B19: West Central Minnesota | C19: 01 | D19: 3 | E19: Becker | F19: PINE POINT PUBLIC SCHOOL DISTRICT | G19: 0025 | J19: 63.82 | K19: 0 | L19: 0 | M19: 201650 | N19: 31522 | O19: 534471 | P19: 77184 | Q19: 112998 | R19: 447403 | S19: 660394 | T19: 56299 | U19: -41869.19 | V19: 0
... A196: 11 | B196: Twin Cities Metropolitan Area | C196: 01 | D196: 62 | E196: Ramsey | F196: WHITE BEAR LAKE SCHOOL DISTRICT | G196: 0624 | J196: 8636.64 | K196: 13069286 | L196: 7624578 | M196: 2330619 | N196: 771370 | O196: 51388885 | P196: 7330916 | Q196: 1518204 | R196: 2360414 | S196: 1120165 | T196: 7094764 | U196: -449533.57 | V196: -8641.03
A197: 11 | B197: Twin Cities Metropolitan Area | C197: 01 | D197: 62 | E197: Ramsey | F197: ST. PAUL PUBLIC SCHOOL DISTRICT | G197: 0625 | H197: District | I197: St. Paul | J197: 42379.85 | K197: 48650687 | L197: 31572669 | M197: 18437068 | N197: 17562192 | O197: 329659792 | P197: 43546172 | Q197: 23370195 | R197: 41434769 | S197: 20144430 | T197: 12959959 | U197: -5597682.3 | V197: -9194966.1
A198: 1 | B198: Northwest Minnesota | C198: 01 | D198: 63 | E198: Red Lake | F198: OKLEE PUBLIC SCHOOL DISTRICT | G198: 0627 | J198: 245.46 | K198: 148368 | L198: 8339 | M198: 293101 | N198: 28247 | O198: 1914632 | P198: 91835 | Q198: 17653 | R198: 47102 | S198: 49527 | T198: 28161 | U198: -22632.26 | V198: 0
A199: 1 | B199: Northwest Minnesota | C199: 01 | D199: 63 | E199: Red Lake | F199: PLUMMER PUBLIC SCHOOL DISTRICT | G199: 0628 | J199: 229.96 | K199: 162657 | L199: 20460 | M199: 445957 | N199: 35635 | O199: 1075937 | P199: 169125 | Q199: 10391 | R199: 134894 | S199: 63810 | T199: 44149 | U199: -22685.57 | V199: 0
A200: 1 | B200: Northwest Minnesota | C200: 01 | D200: 63 | E200: Red Lake | F200: RED LAKE FALLS PUBLIC SCHOOL DIST. | G200: 0630 | J200: 379.51 | K200: 186066 | L200: 211182 | M200: 168707 | N200: 340337 | O200: 3041414 | P200: 343943 | Q200: 41478 | R200: 152990 | S200: 79619 | T200: 115780 | U200: -29341.52 | V200: 0
A201: 8 | B201: Southwest Minnesota | C201: 01 | D201: 64 | E201: Redwood | F201: MILROY PUBLIC SCHOOL DISTRICT | G201: 0635 | J201: 69.9 | K201: 144924 | L201: 11742 | M201: 159717 | N201: 15969 | O201: 572890 | P201: -22840 | Q201: 17252 | R201: 56313 | S201: 22947 | T201: 29213 | U201: -14733.53 | V201: 0
A202: 8 | B202: Southwest Minnesota | C202: 01 | D202: 64 | E202: Redwood | F202: WABASSO PUBLIC SCHOOL DISTRICT | G202: 0640 | J202: 402.19 | K202: 238819 | L202: 341659 | M202: 195221 | N202: 74314 | O202: 2802615 | P202: 167586 | Q202: 74977 | R202: 150358 | S202: 70902 | T202: 270049 | U202: -39033.96 | V202: 0
A203: 10 | B203: Southeast Minnesota | C203: 01 | D203: 66 | E203: Rice | F203: FARIBAULT PUBLIC SCHOOL DISTRICT | G203: 0656 | J203: 4058.93 | K203: 2724651 | L203: 4305599 | M203: 1545729 | N203: 1217991 | O203: 26710861 | P203: 2872560 | Q203: 259970 | R203: 2072172 | S203: 1654596 | T203: 1974414 | U203: -348147.75 | V203: -412448.22
A204: 10 | B204: Southeast Minnesota | C204: 01 | D204: 66 | E204: Rice | F204: NORTHFIELD PUBLIC SCHOOL DISTRICT | G204: 0659 | J204: 3944.86 | K204: 4376967 | L204: 5480309 | M204: 1458002 | N204: 602835 | O204: 24572268 | P204: 1884185 | Q204: 259912 | R204: 1308168 | S204: 472401 | T204: 2770286 | U204: -368495.78 | V204: -15029
A205: 8 | B205: Southwest Minnesota | C205: 01 | D205: 67 | E205: Rock | F205: HILLS-BEAVER CREEK SCHOOL DISTRICT | G205: 0671 | J205: 339.54 | K205: 201896 | L205: 173709 | M205: 159749 | N205: 41506 | O205: 2382775 | P205: 145498 | Q205: 16848 | R205: 91279 | S205: 57684 | T205: 116090 | U205: -20391.98 | V205: 0
A206: 1 | B206: Northwest Minnesota | C206: 01 | D206: 68 | E206: Roseau | F206: BADGER PUBLIC SCHOOL DISTRICT | G206: 0676 | J206: 226.99 | K206: 183259 | L206: 50011 | M206: 181091 | N206: 42500 | O206: 1875831 | P206: 91198 | Q206: 27430 | R206: 68634 | S206: 63971 | T206: 44919 | U206: -20448.88 | V206: 0
A207: 1 | B207: Northwest Minnesota | C207: 01 | D207: 68 | E207: Roseau | F207: ROSEAU PUBLIC SCHOOL DISTRICT | G207: 0682 | J207: 1333.17 | K207: 559893 | L207: 1011535 | M207: 507903 | N207: 442040 | O207: 9141472 | P207: 738031 | Q207: 70128 | R207: 415248 | S207: 166295 | T207: 574974 | U207: -89591.06 | V207: 0
A208: 1 | B208: Northwest Minnesota | C208: 01 | D208: 68 | E208: Roseau | F208: WARROAD PUBLIC SCHOOL DISTRICT | G208: 0690 | J208: 1261.52 | K208: 456583 | L208: 934515 | M208: 854426 | N208: 639019 | O208: 8717220 | P208: 444674 | Q208: 224178 | R208: 649488 | S208: 226136 | T208: 588492 | U208: -109254.74 | V208: 0
A209: 3 | B209: Northeast Minnesota | C209: 01 | D209: 69 | E209: Saint Louis | F209: CHISHOLM PUBLIC SCHOOL DISTRICT | G209: 0695 | J209: 757.37 | K209: 483555 | L209: 154792 | M209: 1212906 | N209: 208459 | O209: 5280620 | P209: 165386 | Q209: 94746 | R209: 307940 | S209: 161528 | T209: 726364 | U209: -58610.12 | V209: 0
... A345: 8 | B345: Southwest Minnesota | C345: 01 | D345: 41 | E345: Lincoln | F345: RTR PUBLIC SCHOOLS | G345: 2902 | J345: 564.36 | K345: 406449 | L345: 97158 | M345: 300075 | N345: 50958 | O345: 3790735 | P345: 148612 | Q345: 338771 | R345: 388758 | S345: 112913 | T345: 180510 | U345: -46641.83 | V345: 0
F346: State | G346: 9999 | J346: =SUM(J6:J345) -> 814733.22 | K346: =SUM(K6:K345) -> 855760925 | L346: =SUM(L6:L345) -> 744354569 | M346: =SUM(M6:M345) -> 410123276 | N346: =SUM(N6:N345) -> 181696457 | O346: =SUM(O6:O345) -> 5305522900 | P346: =SUM(P6:P345) -> 599074487 | Q346: =SUM(Q6:Q345) -> 152036093 | ... V346: =SUM(V6:V345) -> -46502968
M347: =SUM(K346:M346) -> 2010238770 | Q347: =SUM(N346:Q346) -> 6238329937 | S347: =SUM(R346:S346) -> 502930782 | T347: =T346 -> 536346689 | V347: =SUM(U346:V346) -> -1.2172122e+08 | W347: =SUM(M347:V347) -> 9.166125e+09
M348: =M347/J346 -> 2467.3583 | Q348: =Q347/J346 -> 7656.899 | S348: =S347/J346 -> 617.29505 | T348: =T347/J346 -> 658.30959 | V348: =V347/J346 -> -149.4001 | W348: =SUM(K348:V348) -> 11250.462

Sheet Minnea St Paul Dist wrk
F1: Click here for Definitions
A2: Economic Development Region Number | B2: Economic Development Region | C2: District Type | D2: County Number | E2: County Name | F2: Total Revenues FY07 | G2: District Number | J2: District ADM Served Plus Tuitioned Out | K2: General Fund Revenues
K3: Local Sources | O3: State Sources | R3: Federal Sources
H4: Charter | I4: Charter Location | K4: Property Taxes | L4: Other funds revenues distributed by Local Other State and Federal | M4: Other | O4: General Education Aid | P4: Special Education Aid | Q4: All Other State Aid | R4: Federal | S4: Federal | T4: Other
F5: Counties and Districts | K5: 1. | L5: Local | M5: 2. | N5: State | O5: 4. | P5: 5. | Q5: 6. | R5: 8. | U5: Early Childhood Reduction | V5: ABE Reduction
A6: 11 | B6: Twin Cities Metropolitan Area | C6: 03 | D6: 27 | E6: Hennepin | F6: MINNEAPOLIS PUBLIC SCHOOL DIST. | G6: 0001 | H6: District | I6: Minneapolis | J6: 39479.31 | K6: 58005565 | L6: 58143868 | M6: 20520348 | N6: 23620461 | O6: 293589390 | P6: 49228337 | Q6: 18490543 | R6: 52989194 | S6: 15279332 | T6: 18756992 | U6: -4444620.9 | V6: -7342147.7
M7: =SUM(K6:M6) -> 136669781 | Q7: =SUM(N6:Q6) -> 384928731 | S7: =SUM(R6:S6) -> 68268526 | T7: =T6 -> 18756992 | V7: =SUM(U6:V6) -> -11786769 | W7: =SUM(K7:V7) -> 5.9683726e+08
M8: =M7/J6 -> 3461.8077 | Q8: =Q7/J6 -> 9750.1383 | S8: =S7/J6 -> 1729.2229 | T8: =T7/J6 -> 475.10942 | V8: =V7/J6 -> -298.55559 | W8: =SUM(K8:V8) -> 15117.723
A10: 11 | B10: Twin Cities Metropolitan Area | C10: 01 | D10: 62 | E10: Ramsey | F10: ST. PAUL PUBLIC SCHOOL DISTRICT | G10: 0625 | H10: District | I10: St. Paul | J10: 42379.85 | K10: 48650687 | L10: 31572669 | M10: 18437068 | N10: 17562192 | O10: 329659792 | P10: 43546172 | Q10: 23370195 | R10: 41434769 | S10: 20144430 | T10: 12959959 | U10: -5597682.3 | V10: -9194966.1
M11: =SUM(K10:M10) -> 98660424 | Q11: =SUM(N10:Q10) -> 414138351 | S11: =SUM(R10:S10) -> 61579199 | T11: =T10 -> 12959959 | V11: =SUM(U10:V10) -> -14792648 | W11: =SUM(K11:V11) -> 5.7254528e+08
M12: =M11/J10 -> 2328.0031 | Q12: =Q11/J10 -> 9772.058 | S12: =S11/J10 -> 1453.0301 | T12: =T11/J10 -> 305.80474 | V12: =V11/J10 -> -349.0491 | W12: =SUM(K12:V12) -> 13509.847

Sheet Charter State Work
F1: Click here for Definitions
A2: Economic Development Region Number | B2: Economic Development Region | C2: District Type | D2: County Number | E2: County Name | F2: Total Revenues FY07 | G2: District Number | J2: District ADM Served Plus Tuitioned Out | K2: General Fund Revenues
K3: Local Sources | O3: State Sources | R3: Federal Sources
H4: Charter | I4: Charter Location | K4: Property Taxes | L4: Other funds revenues distributed by Local Other State and Federal | M4: Other | O4: General Education Aid | P4: Special Education Aid | Q4: All Other State Aid | R4: Federal | S4: Federal | T4: Other
F5: Counties and Districts | K5: 1. | L5: Local | M5: 2. | N5: State | O5: 4. | P5: 5. | Q5: 6. | R5: 8. | U5: Early Childhood Reduction | V5: ABE Reduction
A6: 11 | B6: Twin Cities Metropolitan Area | C6: 07 | D6: 62 | E6: Ramsey | F6: ACADEMIA CESAR CHAVEZ CHARTER SCH. | G6: 4073 | H6: Charter | I6: St. Paul | J6: 262.75 | K6: 0 | L6: 0 | M6: 47885 | N6: 8154 | O6: 2086879 | P6: 198549 | Q6: 270454 | R6: 184592 | S6: 134669 | T6: 4062 | U6: 0 | V6: 0
A7: 10 | B7: Southeast Minnesota | C7: 07 | D7: 85 | E7: Winona | F7: ACADEMY OF BIOSCIENCES | G7: 4148 | H7: Charter | I7: Statewide | J7: 157.75 | K7: 0 | L7: 0 | M7: 17595 | N7: 2956 | O7: 1119571 | P7: 81301 | Q7: 330392 | R7: 233166 | S7: 34329 | T7: 25070 | U7: 0 | V7: 0
A8: 11 | B8: Twin Cities Metropolitan Area | C8: 07 | D8: 82 | E8: Washington | F8: ACHIEVE LANGUAGE ACADEMY | G8: 4018 | H8: Charter | I8: St. Paul | J8: 409.08 | K8: 0 | L8: 0 | M8: 89030 | N8: 0 | O8: 3228896 | P8: 182561 | Q8: 598530 | R8: 227280 | S8: 0 | T8: 24975 | U8: 0 | V8: 0
A9: 11 | B9: Twin Cities Metropolitan Area | C9: 07 | D9: 27 | E9: Hennepin | F9: ADAM ABDULLE ACADEMY | G9: 4135 | H9: Charter | I9: Statewide | J9: 112.29 | K9: 0 | L9: 0 | M9: 1278 | N9: 2028 | O9: 1080750 | P9: 19392 | Q9: 266690 | R9: 176006 | S9: 65542 | T9: 0 | U9: 0 | V9: 0
A10: 11 | B10: Twin Cities Metropolitan Area | C10: 07 | D10: 62 | E10: Ramsey | F10: AGRICULTURAL FOOD SCIENCE ACADEMY | G10: 4074 | H10: Charter | I10: Statewide | J10: 203.87 | K10: 0 | L10: 0 | M10: 271848 | N10: 1903 | O10: 1439440 | P10: 376937 | Q10: 366283 | R10: 69454 | S10: 19757 | T10: 16420 | U10: 0 | V10: 0
A11: 11 | B11: Twin Cities Metropolitan Area | C11: 07 | D11: 62 | E11: Ramsey | F11: ARTECH | G11: 4091 | H11: Charter | I11: Statewide | J11: 122.6 | K11: 0 | L11: 0 | M11: 16752 | N11: 447 | O11: 854895 | P11: 203462 | Q11: 178658 | R11: 32280 | S11: 3561 | T11: 11126 | U11: 0 | V11: 0
A12: 9 | B12: South Central Minnesota | C12: 07 | D12: 72 | E12: Sibley | F12: ASCENSION ACADEMY CHARTER SCHOOL | G12: 4114 | H12: Charter | I12: Minneapolis | J12: 87.16 | K12: 0 | L12: 0 | M12: 62267 | N12: 1343 | O12: 718200 | P12: 15027 | Q12: 134815 | R12: 157517 | S12: 24562 | T12: 1499 | U12: 0 | V12: 0
A13: 11 | B13: Twin Cities Metropolitan Area | C13: 07 | D13: 2 | E13: Anoka | F13: AUGSBURG ACADEMY FOR HEALTH CAREERS | G13: 4111 | H13: Charter | I13: Minneapolis | J13: 70.7 | K13: 0 | L13: 0 | M13: 13027 | N13: 639 | O13: 599649 | P13: 53838 | Q13: 144839 | R13: 183653 | S13: 14708 | T13: 1073 | U13: 0 | V13: 0
A14: 11 | B14: Twin Cities Metropolitan Area | C14: 07 | D14: 27 | E14: Hennepin | F14: AURORA CHARTER SCHOOL | G14: 4067 | H14: Charter | I14: Minneapolis | J14: 231.57 | K14: 0 | L14: 0 | M14: 2320 | N14: 4465 | O14: 1781024 | P14: 28680 | Q14: 128902 | R14: 120732 | S14: 96513 | T14: 22094 | U14: -2653.05 | V14: 0
A15: 5 | B15: North Central Minnesota | C15: 07 | D15: 18 | E15: Crow Wing | F15: AVALON SCHOOL | G15: 4075 | H15: Charter | I15: St. Paul | J15: 154.51 | K15: 0 | L15: 0 | M15: 88885 | N15: 371 | O15: 1115713 | P15: 191219 | Q15: 242377 | R15: 9127 | S15: 6960 | T15: 2655 | U15: 0 | V15: 0
A16: 11 | B16: Twin Cities Metropolitan Area | C16: 07 | D16: 62 | E16: Ramsey | F16: BEACON ACADEMY | G16: 4124 | H16: Charter | I16: Statewide | J16: 253.08 | K16: 0 | L16: 0 | M16: 203659 | N16: 2064 | O16: 1447572 | P16: 138333 | Q16: 305412 | R16: 191318 | S16: 15715 | T16: 41133 | U16: 0 | V16: 0
A17: 11 | B17: Twin Cities Metropolitan Area | C17: 07 | D17: 10 | E17: Carver | F17: BEACON PREPARATORY SCHOOL | G17: 4133 | H17: Charter | I17: Statewide | J17: 29.97 | K17: 0 | L17: 0 | M17: 56117 | N17: -1 | O17: 174451 | P17: 20096 | Q17: 88124 | R17: 171909 | S17: 0 | T17: 3631 | U17: 0 | V17: 0
... A135: 11 | B135: Twin Cities Metropolitan Area | C135: 07 | D135: 82 | E135: Washington | F135: YINGHUA ACADEMY | G135: 4140 | H135: Charter | I135: St. Paul | J135: 81.73 | K135: 0 | L135: 0 | M135: 123084 | N135: 365 | O135: 399191 | P135: 6818 | Q135: 138457 | R135: 185491 | S135: 812 | T135: 81600 | U135: 0 | V135: 0
F136: State | G136: 9999 | J136: =SUM(J6:J135) -> 23816.18 | K136: =SUM(K6:K135) -> 0 | L136: =SUM(L6:L135) -> 0 | M136: =SUM(M6:M135) -> 11636512 | N136: =SUM(N6:N135) -> 347133 | O136: =SUM(O6:O135) -> 172745986 | P136: =SUM(P6:P135) -> 19975462 | Q136: =SUM(Q6:Q135) -> 31517488 | ... V136: =SUM(V6:V135) -> -46337.59
M137: =SUM(K136:M136) -> 11636512 | Q137: =SUM(N136:Q136) -> 224586069 | S137: =SUM(R136:S136) -> 24751616 | T137: =T136 -> 3065962 | V137: =SUM(U136:V136) -> -124395.95 | W137: =SUM(M137:V137) -> 2.6391576e+08
M138: =M137/J136 -> 488.59691 | Q138: =Q137/J136 -> 9429.9787 | S138: =S137/J136 -> 1039.2773 | T138: =T137/J136 -> 128.73442 | V138: =V137/J136 -> -5.2231697 | W138: =SUM(M138:V138) -> 11081.364

Sheet Charter Minnea St. Paul Wrk
F1: Click here for Definitions
A2: Economic Development Region Number | B2: Economic Development Region | C2: District Type | D2: County Number | E2: County Name | F2: Total Revenues FY07 | G2: District Number | J2: District ADM Served Plus Tuitioned Out | K2: General Fund Revenues
K3: Local Sources | O3: State Sources | R3: Federal Sources
H4: Charter | I4: Charter Location | K4: Property Taxes | L4: Other funds revenues distributed by Local Other State and Federal | M4: Other | O4: General Education Aid | P4: Special Education Aid | Q4: All Other State Aid | R4: Federal | S4: Federal | T4: Other
F5: Counties and Districts | K5: 1. | L5: Local | M5: 2. | N5: State | O5: 4. | P5: 5. | Q5: 6. | R5: 8. | U5: Early Childhood Reduction | V5: ABE Reduction
A6: 9 | B6: South Central Minnesota | C6: 07 | D6: 72 | E6: Sibley | F6: ASCENSION ACADEMY CHARTER SCHOOL | G6: 4114 | H6: Charter | I6: Minneapolis | J6: 87.16 | K6: 0 | L6: 0 | M6: 62267 | N6: 1343 | O6: 718200 | P6: 15027 | Q6: 134815 | R6: 157517 | S6: 24562 | T6: 1499 | U6: 0 | V6: 0
A7: 11 | B7: Twin Cities Metropolitan Area | C7: 07 | D7: 2 | E7: Anoka | F7: AUGSBURG ACADEMY FOR HEALTH CAREERS | G7: 4111 | H7: Charter | I7: Minneapolis | J7: 70.7 | K7: 0 | L7: 0 | M7: 13027 | N7: 639 | O7: 599649 | P7: 53838 | Q7: 144839 | R7: 183653 | S7: 14708 | T7: 1073 | U7: 0 | V7: 0
A8: 11 | B8: Twin Cities Metropolitan Area | C8: 07 | D8: 27 | E8: Hennepin | F8: AURORA CHARTER SCHOOL | G8: 4067 | H8: Charter | I8: Minneapolis | J8: 231.57 | K8: 0 | L8: 0 | M8: 2320 | N8: 4465 | O8: 1781024 | P8: 28680 | Q8: 128902 | R8: 120732 | S8: 96513 | T8: 22094 | U8: -2653.05 | V8: 0
A9: 11 | B9: Twin Cities Metropolitan Area | C9: 07 | D9: 62 | E9: Ramsey | F9: CEDAR RIVERSIDE COMMUNITY SCHOOL | G9: 4004 | H9: Charter | I9: Minneapolis | J9: 110.46 | K9: 0 | L9: 0 | M9: 31615 | N9: 2455 | O9: 977382 | P9: 40608 | Q9: 39720 | R9: 203272 | S9: 66767 | T9: 1001 | U9: 0 | V9: 0
A10: 9 | B10: South Central Minnesota | C10: 07 | D10: 52 | E10: Nicollet | F10: EDVISIONS OFF CAMPUS SCHOOL | G10: 4151 | H10: Charter | I10: Minneapolis | J10: 65.33 | K10: 0 | L10: 0 | M10: 12235 | N10: 0 | O10: 488689 | P10: 22708 | Q10: 50241 | R10: 195901 | S10: 0 | T10: 0 | U10: 0 | V10: 0
A11: 11 | B11: Twin Cities Metropolitan Area | C11: 07 | D11: 27 | E11: Hennepin | F11: EL COLEGIO CHARTER SCHOOL | G11: 4057 | H11: Charter | I11: Minneapolis | J11: 91.39 | K11: 0 | L11: 0 | M11: 99168 | N11: 1574 | O11: 762669 | P11: 88581 | Q11: 175256 | R11: 61727 | S11: 34937 | T11: 292 | U11: 0 | V11: 0
A12: 2 | B12: Headwaters | C12: 07 | D12: 4 | E12: Beltrami | F12: FOUR DIRECTIONS CHARTER SCHOOLS | G12: 4052 | H12: Charter | I12: Minneapolis | J12: 98.74 | K12: 0 | L12: 0 | M12: 10035 | N12: -1 | O12: 907045 | P12: 179048 | Q12: 107383 | R12: 94532 | S12: 0 | T12: 3614 | U12: 0 | V12: 0
A13: 5 | B13: North Central Minnesota | C13: 07 | D13: 18 | E13: Crow Wing | F13: FRASER ACADEMY | G13: 4113 | H13: Charter | I13: Minneapolis | J13: 69.95 | K13: 0 | L13: 0 | M13: 86982 | N13: 15 | O13: 405697 | P13: 1498269 | Q13: 91524 | R13: 116718 | S13: 741 | T13: 0 | U13: 0 | V13: 0
A14: 10 | B14: Southeast Minnesota | C14: 07 | D14: 55 | E14: Olmsted | F14: FRIENDSHIP ACDMY OF FINE ARTS CHTR. | G14: 4079 | H14: Charter | I14: Minneapolis | J14: 94.53 | K14: 0 | L14: 0 | M14: 44942 | N14: 1057 | O14: 664325 | P14: 18177 | Q14: 81381 | R14: 73086 | S14: 57470 | T14: 672 | U14: 0 | V14: 0
A15: 11 | B15: Twin Cities Metropolitan Area | C15: 07 | D15: 62 | E15: Ramsey | F15: HARVEST PREP SCHOOL/SEED ACADEMY | G15: 4032 | H15: Charter | I15: Minneapolis | J15: 486.14 | K15: 0 | L15: 0 | M15: 864437 | N15: 12528 | O15: 2928319 | P15: 171005 | Q15: 807159 | R15: 207337 | S15: 142522 | T15: 72901 | U15: 0 | V15: 0
A16: 11 | B16: Twin Cities Metropolitan Area | C16: 07 | D16: 62 | E16: Ramsey | F16: HEART OF THE EARTH CHARTER | G16: 4044 | H16: Charter | I16: Minneapolis | J16: 223.32 | K16: 0 | L16: 0 | M16: 119210 | N16: 4489 | O16: 1886683 | P16: 117237 | Q16: 300745 | R16: 240509 | S16: 82731 | T16: 0 | U16: 0 | V16: 0
A17: 10 | B17: Southeast Minnesota | C17: 07 | D17: 66 | E17: Rice | F17: LEARNING FOR LEADERSHIP CHARTER | G17: 4163 | H17: Charter | I17: Minneapolis | J17: 147.7 | K17: 0 | L17: 0 | M17: 4725 | N17: 3190 | O17: 1232154 | P17: 151537 | Q17: 282863 | R17: 189544 | S17: 64693 | T17: 576 | U17: 0 | V17: 0
... A34: 11 | B34: Twin Cities Metropolitan Area | C34: 07 | D34: 82 | E34: Washington | F34: WOODSON INSTITUTE FOR EXCELLENCE CH | G34: 4086 | H34: Charter | I34: Minneapolis | J34: 244.16 | K34: 0 | L34: 0 | M34: 644556 | N34: 3846 | O34: 1837119 | P34: 74495 | Q34: 369273 | R34: 145764 | S34: 148037 | T34: 11935 | U34: 0 | V34: 0
J35: =SUM(J6:J34) -> 6639.22 | K35: =SUM(K6:K34) -> 0 | L35: =SUM(L6:L34) -> 0 | M35: =SUM(M6:M34) -> 5184881 | N35: =SUM(N6:N34) -> 135235 | O35: =SUM(O6:O34) -> 52777257 | P35: =SUM(P6:P34) -> 4886323 | Q35: =SUM(Q6:Q34) -> 8000582 | ... V35: =SUM(V6:V34) -> -46337.59
M36: =SUM(K35:M35) -> 5184881 | Q36: =SUM(N35:Q35) -> 65799397 | S36: =SUM(R35:S35) -> 8043121 | T36: =T35 -> 227377 | V36: =SUM(U35:V35) -> -48990.64 | W36: =SUM(K36:V36) -> 79205785
M37: =M36/J35 -> 780.94731 | Q37: =Q36/J35 -> 9910.712 | S37: =S36/J35 -> 1211.4557 | T37: =T36/J35 -> 34.247547 | V37: =V36/J35 -> -7.3789752 | W37: =SUM(K37:V37) -> 11929.984
A40: 11 | B40: Twin Cities Metropolitan Area | C40: 07 | D40: 62 | E40: Ramsey | F40: ACADEMIA CESAR CHAVEZ CHARTER SCH. | G40: 4073 | H40: Charter | I40: St. Paul | J40: 262.75 | K40: 0 | L40: 0 | M40: 47885 | N40: 8154 | O40: 2086879 | P40: 198549 | Q40: 270454 | R40: 184592 | S40: 134669 | T40: 4062 | U40: 0 | V40: 0
A41: 11 | B41: Twin Cities Metropolitan Area | C41: 07 | D41: 82 | E41: Washington | F41: ACHIEVE LANGUAGE ACADEMY | G41: 4018 | H41: Charter | I41: St. Paul | J41: 409.08 | K41: 0 | L41: 0 | M41: 89030 | N41: 0 | O41: 3228896 | P41: 182561 | Q41: 598530 | R41: 227280 | S41: 0 | T41: 24975 | U41: 0 | V41: 0
A42: 5 | B42: North Central Minnesota | C42: 07 | D42: 18 | E42: Crow Wing | F42: AVALON SCHOOL | G42: 4075 | H42: Charter | I42: St. Paul | J42: 154.51 | K42: 0 | L42: 0 | M42: 88885 | N42: 371 | O42: 1115713 | P42: 191219 | Q42: 242377 | R42: 9127 | S42: 6960 | T42: 2655 | U42: 0 | V42: 0
A43: 6W | B43: Upper Southwest Minnesota | C43: 07 | D43: 87 | E43: Yellow Medicine | F43: CITY ACADEMY | G43: 4000 | H43: Charter | I43: St. Paul | J43: 117.19 | K43: 0 | L43: 0 | M43: 62266 | N43: 0 | O43: 1083305 | P43: 0 | Q43: 143110 | R43: 0 | S43: 0 | T43: 0 | U43: 0 | V43: 0
A44: 8 | B44: Southwest Minnesota | C44: 07 | D44: 64 | E44: Redwood | F44: COMMUNITY OF PEACE ACADEMY | G44: 4015 | H44: Charter | I44: St. Paul | J44: 590.4 | K44: 0 | L44: 0 | M44: 87237 | N44: 0 | O44: 4920091 | P44: 627865 | Q44: 1024715 | R44: 438125 | S44: 0 | T44: 0 | U44: 0 | V44: 0
A45: 11 | B45: Twin Cities Metropolitan Area | C45: 07 | D45: 27 | E45: Hennepin | F45: CONCORDIA CREATIVE LEARNING ACADEMY | G45: 4035 | H45: Charter | I45: St. Paul | J45: 161.97 | K45: 0 | L45: 0 | M45: 37122 | N45: 3258 | O45: 1129769 | P45: 214488 | Q45: 210634 | R45: 106947 | S45: 75157 | T45: 11557 | U45: 0 | V45: 0
A46: 11 | B46: Twin Cities Metropolitan Area | C46: 07 | D46: 27 | E46: Hennepin | F46: CYBER VILLAGE ACADEMY | G46: 4025 | H46: Charter | I46: St. Paul | J46: 119.5 | K46: 0 | L46: 0 | M46: 99413 | N46: 0 | O46: 751760 | P46: 45959 | Q46: 213038 | R46: 53944 | S46: 0 | T46: 0 | U46: 0 | V46: 0
A47: 11 | B47: Twin Cities Metropolitan Area | C47: 07 | D47: 62 | E47: Ramsey | F47: DUGSI ACADEMY | G47: 4153 | H47: Charter | I47: St. Paul | J47: 184.66 | K47: 0 | L47: 0 | M47: 4041 | N47: 3985 | O47: 1509922 | P47: 12079 | Q47: 352879 | R47: 291058 | S47: 105721 | T47: 132 | U47: 0 | V47: 0
A48: 11 | B48: Twin Cities Metropolitan Area | C48: 07 | D48: 27 | E48: Hennepin | F48: FACE TO FACE ACADEMY | G48: 4036 | H48: Charter | I48: St. Paul | J48: 61.6 | K48: 0 | L48: 0 | M48: 53067 | N48: 869 | O48: 473940 | P48: 53888 | Q48: 96001 | R48: 42681 | S48: 12178 | T48: 0 | U48: 0 | V48: 0
A49: 11 | B49: Twin Cities Metropolitan Area | C49: 07 | D49: 62 | E49: Ramsey | F49: GREAT RIVER SCHOOL | G49: 4105 | H49: Charter | I49: St. Paul | J49: 174.46 | K49: 0 | L49: 0 | M49: 145654 | N49: 0 | O49: 1215108 | P49: 169535 | Q49: 258913 | R49: 92763 | S49: 0 | T49: 0 | U49: 0 | V49: 0
A50: 11 | B50: Twin Cities Metropolitan Area | C50: 07 | D50: 27 | E50: Hennepin | F50: HIGH SCHOOL FOR RECORDING ARTS | G50: 4039 | H50: Charter | I50: St. Paul | J50: 201.25 | K50: 0 | L50: 0 | M50: 91331 | N50: 3263 | O50: 1887375 | P50: 219439 | Q50: 227151 | R50: 120847 | S50: 75719 | T50: 0 | U50: 0 | V50: 0
A51: 11 | B51: Twin Cities Metropolitan Area | C51: 07 | D51: 27 | E51: Hennepin | F51: HIGHER GROUND ACADEMY | G51: 4027 | H51: Charter | I51: St. Paul | J51: 512.75 | K51: 0 | L51: 0 | M51: 122843 | N51: 9528 | O51: 4291060 | P51: 159015 | Q51: 662619 | R51: 232478 | S51: 303958 | T51: 1357 | U51: 0 | V51: 0
... A66: 11 | B66: Twin Cities Metropolitan Area | C66: 07 | D66: 82 | E66: Washington | F66: YINGHUA ACADEMY | G66: 4140 | H66: Charter | I66: St. Paul | J66: 81.73 | K66: 0 | L66: 0 | M66: 123084 | N66: 365 | O66: 399191 | P66: 6818 | Q66: 138457 | R66: 185491 | S66: 812 | T66: 81600 | U66: 0 | V66: 0
F67: State | G67: 9999 | J67: =SUM(J40:J66) -> 5831.26 | K67: =SUM(K40:K66) -> 0 | L67: =SUM(L40:L66) -> 0 | M67: =SUM(M40:M66) -> 2641868 | N67: =SUM(N40:N66) -> 69609 | O67: =SUM(O40:O66) -> 44731970 | P67: =SUM(P40:P66) -> 6246588 | Q67: =SUM(Q40:Q66) -> 8524092 | ... V67: =SUM(V40:V66) -> 0
M68: =SUM(K67:M67) -> 2641868 | Q68: =SUM(N67:Q67) -> 59572259 | S68: =SUM(R67:S67) -> 5688528 | T68: =T67 -> 323819 | V68: =SUM(U67:V67) -> 0 | W68: =SUM(K68:V68) -> 68226474
M69: =M68/J67 -> 453.05269 | Q69: =Q68/J67 -> 10216.018 | S69: =S68/J67 -> 975.52296 | T69: =T68/J67 -> 55.531566 | V69: =V68/J67 -> 0 | W69: =SUM(K69:V69) -> 11700.126
