Workbook
Name \C: #REF!
Name TABLE1: 'BUDGET DETAIL'!$B$4:$L$140
Name table3: 'BUDGET DETAIL'!$A$4:$L$150
Name table4: 'BUDGET DETAIL'!$A$154:$L$158
Name table5: 'BUDGET DETAIL'!$A$162:$L$169

Sheet BUDGETSIZE
O3: RETIREMENT | P3: TRUST FUND | Q3: REVENUE FUND | R3: DEBT FUND | S3: CONSTRUCTION | T3: OPERATING | U3: TOTAL
A4: SAP | N4: ADJUSTED | O4: @ 0% | P4: @ 0% | Q4: @ 50% | R4: @ 50% | S4: @ 50% | T4: @ 100% | U4: ACTUAL
A5: FUND NO. | B5: OPERATING BUREAUS/FUNDS | C5: LOOK UP VALUES | K5: TABLE | L5: FY 2012 EXP | M5: ADJUSTMENTS | N5: FY 2012 EXP | O5: OF BUDGET | P5: OF BUDGET | Q5: OF BUDGET | R5: OF BUDGET | S5: OF BUDGET | T5: OF BUDGET | U5: ALLOCATED
A7: 100000 | B7: Portland Police Bureau | C7: 18 | E7: 61 | F7: 62 | K7: TABLE 3 | L7: =VLOOKUP(C7,table3,12)+VLOOKUP(D7,table3,12)+VLOOKUP(E7,table3,12)+VLOOKUP(F7,table3,12)+VLOOKUP(G7,table3,12) -> 1.4420687e+08 | N7: =SUM(M7,L7) -> 1.4420687e+08 | T7: =SUM(N7)-SUM(O7:P7)-SUM(Q7:S7)*2 -> 1.4420687e+08 | U7: =SUM(O7:T7) -> 1.4420687e+08
A8: 214000 | B8: Campaign Finance (closed) | K8: TABLE 3 | L8: =VLOOKUP(C8,table3,12)+VLOOKUP(D8,table3,12)+VLOOKUP(E8,table3,12)+VLOOKUP(F8,table3,12)+VLOOKUP(G8,table3,12) -> 0 | N8: =SUM(M8,L8) -> 0 | T8: =SUM(N8)-SUM(O8:P8)-SUM(Q8:S8)*2 -> 0 | U8: =SUM(O8:T8) -> 0
A9: 100000 | B9: Portland Fire & Rescue | C9: 5 | D9: 6 | E9: 50 | F9: 51 | G9: 79 | H9: 81 | K9: TABLE 3 | L9: =VLOOKUP(C9,table3,12)+VLOOKUP(D9,table3,12)+VLOOKUP(E9,table3,12)+VLOOKUP(F9,table3,12)+VLOOKUP(G9,table3,12)+VLOOKUP(H9,table3,12) -> 92119356 | N9: =SUM(M9,L9) -> 92119356 | S9: =VLOOKUP(C9,table3,12)/2+VLOOKUP(G9,table3,12)/2+VLOOKUP(H9,table3,12)/2 -> 640574.41 | T9: =SUM(N9)-SUM(O9:P9)-SUM(Q9:S9)*2 -> 90838207 | U9: =SUM(O9:T9) -> 91478782
A10: 100000 | B10: Portland Parks & Recreation | C10: 16 | D10: ='BUDGET DETAIL'!A21 -> 17 | E10: ='BUDGET DETAIL'!A63 -> 59 | F10: ='BUDGET DETAIL'!A64 -> 60 | K10: TABLE 3 | L10: =VLOOKUP(C10,table3,12)+VLOOKUP(D10,table3,12)+VLOOKUP(E10,table3,12)+VLOOKUP(F10,table3,12)+VLOOKUP(G10,table3,12) -> 56151485 | N10: =SUM(M10,L10) -> 56151485 | S10: =VLOOKUP(C10,table3,12)/2+VLOOKUP(E10,table3,12)/2 -> 919449.24 | T10: =SUM(N10)-SUM(O10:P10)-SUM(Q10:S10)*2 -> 54312587 | U10: =SUM(O10:T10) -> 55232036
A11: 600000 | B11: Sewer System Op | C11: 102 | D11: 103 | E11: ='BUDGET DETAIL'!A51 -> 47 | F11: ='BUDGET DETAIL'!A52 -> 48 | G11: ='BUDGET DETAIL'!A53 -> 49 | K11: TABLE 3 | L11: =VLOOKUP(C11,table3,12)+VLOOKUP(D11,table3,12)+VLOOKUP(E11,table3,12)+VLOOKUP(F11,table3,12)+VLOOKUP(G11,table3,12) -> 1.6866374e+08 | N11: =SUM(M11,L11) -> 1.6866374e+08 | S11: =(VLOOKUP(C11,table3,12)+VLOOKUP(D11,table3,10))/2+VLOOKUP(F11,table3,12)/2 -> 64557865 | T11: =SUM(N11)-SUM(O11:P11)-SUM(Q11:S11)*2 -> 39548010 | U11: =SUM(O11:T11) -> 1.0410587e+08
A12: 608000 | B12: Envtl Remediation | C12: ='BUDGET DETAIL'!A119 -> 115 | D12: 83 | K12: TABLE 3 | L12: =VLOOKUP(C12,table3,12)+VLOOKUP(D12,table3,12)+VLOOKUP(E12,table3,12)+VLOOKUP(F12,table3,12)+VLOOKUP(G12,table3,12) -> 3395384.2 | N12: =SUM(M12,L12) -> 3395384.2 | R12: 0 | S12: =(VLOOKUP(D12,table3,12)) -> 60567 | T12: =SUM(N12)-SUM(O12:P12)-SUM(Q12:S12)*2 -> 3274250.2 | U12: =SUM(O12:T12) -> 3334817.2
A13: 605000 | B13: Solid Waste Mgt | C13: ='BUDGET DETAIL'!A114 -> 110 | K13: TABLE 3 | L13: =VLOOKUP(C13,table3,12)+VLOOKUP(D13,table3,12)+VLOOKUP(E13,table3,12)+VLOOKUP(F13,table3,12)+VLOOKUP(G13,table3,12) -> 3494849.2 | N13: =SUM(M13,L13) -> 3494849.2 | R13: 0 | T13: =SUM(N13)-SUM(O13:P13)-SUM(Q13:S13)*2 -> 3494849.2 | U13: =SUM(O13:T13) -> 3494849.2
A14: 200000 | B14: Transportation Op | C14: 26 | D14: ='BUDGET DETAIL'!A31 -> 27 | E14: 66 | F14: ='BUDGET DETAIL'!A71 -> 67 | G14: ='BUDGET DETAIL'!A72 -> 68 | K14: TABLE 3 | L14: =VLOOKUP(C14,table3,12)+VLOOKUP(D14,table3,12)+VLOOKUP(E14,table3,12)+VLOOKUP(F14,table3,12)+VLOOKUP(G14,table3,12) -> 1.6582504e+08 | N14: =SUM(M14,L14) -> 1.6582504e+08 | R14: 0 | S14: =(VLOOKUP(F14,table3,12)+VLOOKUP(D14,table3,12))/2 -> 43351483 | T14: =SUM(N14)-SUM(O14:P14)-SUM(Q14:S14)*2 -> 79122077 | U14: =SUM(O14:T14) -> 1.2247356e+08
A15: 212000 | B15: Transportation Resv | K15: TABLE 3 | L15: =VLOOKUP(C15,table3,12)+VLOOKUP(D15,table3,12)+VLOOKUP(E15,table3,12)+VLOOKUP(F15,table3,12)+VLOOKUP(G15,table3,12) -> 0 | N15: =SUM(M15,L15) -> 0 | Q15: =N15*0.5 -> 0 | T15: =SUM(N15)-SUM(O15:P15)-SUM(Q15:S15)*2 -> 0 | U15: =SUM(O15:T15) -> 0
A16: 614000 | B16: Sewer System Constr | C16: ='BUDGET DETAIL'!A124 -> 120 | K16: TABLE 3 | L16: =VLOOKUP(C16,table3,12)+VLOOKUP(D16,table3,12)+VLOOKUP(E16,table3,12)+VLOOKUP(F16,table3,12)+VLOOKUP(G16,table3,12) -> 0 | N16: =SUM(M16,L16) -> 0 | T16: =SUM(N16)-SUM(O16:P16)-SUM(Q16:S16)*2 -> 0 | U16: =SUM(O16:T16) -> 0
A17: 609000 | B17: Sewer Sys Debt Rdmpt | C17: 116 | K17: TABLE 3 | L17: =VLOOKUP(C17,table3,12)+VLOOKUP(D17,table3,12)+VLOOKUP(E17,table3,12)+VLOOKUP(F17,table3,12)+VLOOKUP(G17,table3,12) -> 0 | N17: =SUM(M17,L17) -> 0 | R17: 0 | T17: =SUM(N17)-SUM(O17:P17)-SUM(Q17:S17)*2 -> 0 | U17: =SUM(O17:T17) -> 0
A18: 602000 | B18: Water | C18: 105 | D18: 106 | E18: ='BUDGET DETAIL'!$A$73 -> 69 | F18: ='BUDGET DETAIL'!$A$74 -> 70 | K18: TABLE 3 | L18: =VLOOKUP(C18,table3,12)+VLOOKUP(D18,table3,12)+VLOOKUP(E18,table3,12)+VLOOKUP(F18,table3,12)+VLOOKUP(G18,table3,12) -> 1.2132837e+08 | N18: =SUM(M18,L18) -> 1.2132837e+08 | R18: 0 | S18: =(VLOOKUP(F18,table3,12)+VLOOKUP(D18,table3,12))/2 -> 34494078 | T18: =SUM(N18)-SUM(O18:P18)-SUM(Q18:S18)*2 -> 52340211 | U18: =SUM(O18:T18) -> 86834290
A19: 615000 | B19: Water Construction | K19: TABLE 3 | L19: =VLOOKUP(C19,table3,12)+VLOOKUP(D19,table3,12)+VLOOKUP(E19,table3,12)+VLOOKUP(F19,table3,12)+VLOOKUP(G19,table3,12) -> 0 | N19: =SUM(M19,L19) -> 0 | S19: =+N19*0.5 -> 0 | T19: =SUM(N19)-SUM(O19:P19)-SUM(Q19:S19)*2 -> 0 | U19: =SUM(O19:T19) -> 0
A20: 612000 | B20: Water Bond Sinking | C20: ='BUDGET DETAIL'!A123 -> 119 | K20: TABLE 3 | L20: =VLOOKUP(C20,table3,12)+VLOOKUP(D20,table3,12)+VLOOKUP(E20,table3,12)+VLOOKUP(F20,table3,12)+VLOOKUP(G20,table3,12) -> 0 | N20: =SUM(M20,L20) -> 0 | R20: 0 | T20: =SUM(N20)-SUM(O20:P20)-SUM(Q20:S20)*2 -> 0 | U20: =SUM(O20:T20) -> 0
A21: 607000 | B21: Spectator Fac Op | C21: ='BUDGET DETAIL'!$A$117 -> 113 | D21: ='BUDGET DETAIL'!$A$118 -> 114 | K21: TABLE 3 | L21: =VLOOKUP(C21,table3,12)+VLOOKUP(D21,table3,12)+VLOOKUP(E21,table3,12)+VLOOKUP(F21,table3,12)+VLOOKUP(G21,table3,12) -> 1619760.2 | N21: =SUM(M21,L21) -> 1619760.2 | R21: 0 | S21: =(VLOOKUP(C21,table3,12))/2 -> 193827.18 | T21: =SUM(N21)-SUM(O21:P21)-SUM(Q21:S21)*2 -> 1232105.8 | U21: =SUM(O21:T21) -> 1425933
A22: 617000 | B22: Sewer Sys Rate Stblt | K22: TABLE 3 | L22: =VLOOKUP(C22,table3,12)+VLOOKUP(D22,table3,12)+VLOOKUP(E22,table3,12)+VLOOKUP(F22,table3,12)+VLOOKUP(G22,table3,12) -> 0 | N22: =SUM(M22,L22) -> 0 | P22: =+N22*0 -> 0 | T22: =SUM(N22)-SUM(O22:P22)-SUM(Q22:S22)*2 -> 0 | U22: =SUM(O22:T22) -> 0
A23: 619000 | B23: Sewer Sys Safety Net | K23: TABLE 3 | L23: =VLOOKUP(C23,table3,12)+VLOOKUP(D23,table3,12)+VLOOKUP(E23,table3,12)+VLOOKUP(F23,table3,12)+VLOOKUP(G23,table3,12) -> 0 | N23: =SUM(M23,L23) -> 0 | T23: =SUM(N23)-SUM(O23:P23)-SUM(Q23:S23)*2 -> 0 | U23: =SUM(O23:T23) -> 0
A24: 620000 | B24: Sewer Revolving Loan | K24: TABLE 3 | L24: =VLOOKUP(C24,table3,12)+VLOOKUP(D24,table3,12)+VLOOKUP(E24,table3,12)+VLOOKUP(F24,table3,12)+VLOOKUP(G24,table3,12) -> 0 | N24: =SUM(M24,L24) -> 0 | T24: =SUM(N24)-SUM(O24:P24)-SUM(Q24:S24)*2 -> 0 | U24: =SUM(O24:T24) -> 0
A25: 802000 | B25: F&P Suppl Retir Rsrv | C25: 136 | K25: TABLE 3 | L25: =VLOOKUP(C25,table3,12)+VLOOKUP(D25,table3,12)+VLOOKUP(E25,table3,12)+VLOOKUP(F25,table3,12)+VLOOKUP(G25,table3,12) -> 8108.94 | N25: =SUM(M25,L25) -> 8108.94 | O25: =+N25*0 -> 0 | U25: =SUM(O25:T25) -> 0
A26: 800000 | B26: FPDR | C26: ='BUDGET DETAIL'!A138 -> 134 | D26: ='BUDGET DETAIL'!A139 -> 135 | K26: TABLE 3 | L26: =VLOOKUP(C26,table3,12)+VLOOKUP(D26,table3,12)+VLOOKUP(E26,table3,12)+VLOOKUP(F26,table3,12)+VLOOKUP(G26,table3,12) -> 1.0412361e+08 | M26: =-102662983.36 -> -1.0266298e+08 | N26: =SUM(M26,L26) -> 1460629.2 | T26: =SUM(N26)-SUM(O26:P26)-SUM(Q26:S26)*2 -> 1460629.2 | U26: =SUM(O26:T26) -> 1460629.2
A27: 801000 | B27: FPDR Reserve | K27: TABLE 3 | L27: =VLOOKUP(C27,table3,12)+VLOOKUP(D27,table3,12)+VLOOKUP(E27,table3,12)+VLOOKUP(F27,table3,12)+VLOOKUP(G27,table3,12) -> 0 | N27: =SUM(M27,L27) -> 0 | O27: =+N27*0 -> 0 | T27: =SUM(N27)-SUM(O27:P27)-SUM(Q27:S27)*2 -> 0 | U27: =SUM(O27:T27) -> 0
A28: 211000 | B28: Spec Fin & Resource | C28: ='BUDGET DETAIL'!A42 -> 38 | K28: TABLE 3 | L28: =VLOOKUP(C28,table3,12)+VLOOKUP(D28,table3,12)+VLOOKUP(E28,table3,12)+VLOOKUP(F28,table3,12)+VLOOKUP(G28,table3,12) -> 1.3378731e+08 | M28: =-L28 -> -1.3378731e+08 | N28: =SUM(M28,L28) -> 0 | R28: 0 | T28: =SUM(N28)-SUM(O28:P28)-SUM(Q28:S28)*2 -> 0 | U28: =SUM(O28:T28) -> 0
A29: 217000 | B29: Grants | K29: TABLE 3 | L29: =VLOOKUP(C29,table3,12)+VLOOKUP(D29,table3,12)+VLOOKUP(E29,table3,12)+VLOOKUP(F29,table3,12)+VLOOKUP(G29,table3,12) -> 0 | N29: =SUM(M29,L29) -> 0 | Q29: =N29*0.5 -> 0 | T29: =SUM(N29)-SUM(O29:P29)-SUM(Q29:S29)*2 -> 0 | U29: =SUM(O29:T29) -> 0
A30: 853000 | B30: PDC Accounts | C30: ='BUDGET DETAIL'!A29 -> 25 | D30: 71 | K30: TABLE 3 | L30: =VLOOKUP(C30,table3,12)+VLOOKUP(D30,table3,12)+VLOOKUP(E30,table3,12)+VLOOKUP(F30,table3,12)+VLOOKUP(G30,table3,12) -> 4748443.4 | N30: =SUM(M30,L30) -> 4748443.4 | T30: =SUM(N30)-SUM(O30:P30)-SUM(Q30:S30)*2 -> 4748443.4 | U30: =SUM(O30:T30) -> 4748443.4
A31: 204000 | B31: Property Mgt License | C31: ='BUDGET DETAIL'!A39 -> 35 | K31: TABLE 3 | L31: =VLOOKUP(C31,table3,12)+VLOOKUP(D31,table3,12)+VLOOKUP(E31,table3,12)+VLOOKUP(F31,table3,12)+VLOOKUP(G31,table3,12) -> 4683825 | N31: =SUM(M31,L31) -> 4683825 | T31: =SUM(N31)-SUM(O31:P31)-SUM(Q31:S31)*2 -> 4683825 | U31: =SUM(O31:T31) -> 4683825
A32: 201000 | B32: Assessmnt Collection | C32: ='BUDGET DETAIL'!A32 -> 28 | K32: TABLE 3 | L32: =VLOOKUP(C32,table3,12)+VLOOKUP(D32,table3,12)+VLOOKUP(E32,table3,12)+VLOOKUP(F32,table3,12)+VLOOKUP(G32,table3,12) -> 0 | N32: =SUM(M32,L32) -> 0 | T32: =SUM(N32)-SUM(O32:P32)-SUM(Q32:S32)*2 -> 0 | U32: =SUM(O32:T32) -> 0
A33: 209000 | B33: Convention & Tourism | C33: ='BUDGET DETAIL'!A41 -> 37 | K33: TABLE 3 | L33: =VLOOKUP(C33,table3,12)+VLOOKUP(D33,table3,12)+VLOOKUP(E33,table3,12)+VLOOKUP(F33,table3,12)+VLOOKUP(G33,table3,12) -> 3394785.2 | N33: =SUM(M33,L33) -> 3394785.2 | Q33: =+N33*0.5 -> 1697392.6 | T33: =SUM(N33)-SUM(O33:P33)-SUM(Q33:S33)*2 -> 0 | U33: =SUM(O33:T33) -> 1697392.6
A34: 215000 | B34: Parks Local Opt Levy | C34: ='BUDGET DETAIL'!A45 -> 41 | K34: TABLE 3 | L34: =VLOOKUP(C34,table3,12)+VLOOKUP(D34,table3,12)+VLOOKUP(E34,table3,12)+VLOOKUP(F34,table3,12)+VLOOKUP(G34,table3,12) -> 394304 | N34: =SUM(M34,L34) -> 394304 | Q34: =+N34*0.5 -> 197152 | T34: =SUM(N34)-SUM(O34:P34)-SUM(Q34:S34)*2 -> 0 | U34: =SUM(O34:T34) -> 197152
A35: 216000 | B35: Children Investment | C35: ='BUDGET DETAIL'!A46 -> 42 | K35: TABLE 3 | L35: =VLOOKUP(C35,table3,12)+VLOOKUP(D35,table3,12)+VLOOKUP(E35,table3,12)+VLOOKUP(F35,table3,12)+VLOOKUP(G35,table3,12) -> 13946517 | M35: 48701 | N35: =SUM(M35,L35) -> 13995218 | Q35: =+N35*0.5 -> 6997608.8 | T35: =SUM(N35)-SUM(O35:P35)-SUM(Q35:S35)*2 -> 0 | U35: =SUM(O35:T35) -> 6997608.8
A36: 403000 | B36: Public Safety | C36: ='BUDGET DETAIL'!A103 -> 99 | K36: TABLE 3 | L36: =VLOOKUP(C36,table3,12)+VLOOKUP(D36,table3,12)+VLOOKUP(E36,table3,12)+VLOOKUP(F36,table3,12)+VLOOKUP(G36,table3,12) -> 1838261.4 | N36: =SUM(M36,L36) -> 1838261.4 | R36: 0 | S36: =(VLOOKUP(C36,table3,12))/2 -> 919130.68 | T36: =SUM(N36)-SUM(O36:P36)-SUM(Q36:S36)*2 -> 0 | U36: =SUM(O36:T36) -> 919130.68
A37: 316000 | B37: Willamtte Ind URA DS | C37: ='BUDGET DETAIL'!A96 -> 92 | K37: TABLE 3 | L37: =VLOOKUP(C37,table3,12)+VLOOKUP(D37,table3,12)+VLOOKUP(E37,table3,12)+VLOOKUP(F37,table3,12)+VLOOKUP(G37,table3,12) -> 0 | N37: =SUM(M37,L37) -> 0 | R37: 0 | T37: =SUM(N37)-SUM(O37:P37)-SUM(Q37:S37)*2 -> 0 | U37: =SUM(O37:T37) -> 0
A38: 301000 | B38: River Dist URA DR | K38: TABLE 3 | L38: =VLOOKUP(C38,table3,12)+VLOOKUP(D38,table3,12)+VLOOKUP(E38,table3,12)+VLOOKUP(F38,table3,12)+VLOOKUP(G38,table3,12) -> 0 | N38: =SUM(M38,L38) -> 0 | R38: 0 | T38: =SUM(N38)-SUM(O38:P38)-SUM(Q38:S38)*2 -> 0 | U38: =SUM(O38:T38) -> 0
A39: 302000 | B39: Bonded Dbt Int&Sinkg | K39: TABLE 3 | L39: =VLOOKUP(C39,table3,12)+VLOOKUP(D39,table3,12)+VLOOKUP(E39,table3,12)+VLOOKUP(F39,table3,12)+VLOOKUP(G39,table3,12) -> 0 | N39: =SUM(M39,L39) -> 0 | R39: 0 | T39: =SUM(N39)-SUM(O39:P39)-SUM(Q39:S39)*2 -> 0 | U39: =SUM(O39:T39) -> 0
A40: 303000 | B40: DTWF Renwl Bd Sink | K40: TABLE 3 | L40: =VLOOKUP(C40,table3,12)+VLOOKUP(D40,table3,12)+VLOOKUP(E40,table3,12)+VLOOKUP(F40,table3,12)+VLOOKUP(G40,table3,12) -> 0 | N40: =SUM(M40,L40) -> 0 | R40: 0 | T40: =SUM(N40)-SUM(O40:P40)-SUM(Q40:S40)*2 -> 0 | U40: =SUM(O40:T40) -> 0
A41: 305000 | B41: Pension Debt Rdmpt | K41: TABLE 3 | L41: =VLOOKUP(C41,table3,12)+VLOOKUP(D41,table3,12)+VLOOKUP(E41,table3,12)+VLOOKUP(F41,table3,12)+VLOOKUP(G41,table3,12) -> 0 | N41: =SUM(M41,L41) -> 0 | R41: 0 | T41: =SUM(N41)-SUM(O41:P41)-SUM(Q41:S41)*2 -> 0 | U41: =SUM(O41:T41) -> 0
A42: 306000 | B42: SO Park Block Rdmpt | K42: TABLE 3 | L42: =VLOOKUP(C42,table3,12)+VLOOKUP(D42,table3,12)+VLOOKUP(E42,table3,12)+VLOOKUP(F42,table3,12)+VLOOKUP(G42,table3,12) -> 0 | N42: =SUM(M42,L42) -> 0 | R42: 0 | T42: =SUM(N42)-SUM(O42:P42)-SUM(Q42:S42)*2 -> 0 | U42: =SUM(O42:T42) -> 0
A43: 310000 | B43: Cntrl E Ind Distr DS | K43: TABLE 3 | L43: =VLOOKUP(C43,table3,12)+VLOOKUP(D43,table3,12)+VLOOKUP(E43,table3,12)+VLOOKUP(F43,table3,12)+VLOOKUP(G43,table3,12) -> 0 | N43: =SUM(M43,L43) -> 0 | R43: 0 | T43: =SUM(N43)-SUM(O43:P43)-SUM(Q43:S43)*2 -> 0 | U43: =SUM(O43:T43) -> 0
A44: 307000 | B44: Airport Way Dbt Srvc | K44: TABLE 3 | L44: =VLOOKUP(C44,table3,12)+VLOOKUP(D44,table3,12)+VLOOKUP(E44,table3,12)+VLOOKUP(F44,table3,12)+VLOOKUP(G44,table3,12) -> 0 | N44: =SUM(M44,L44) -> 0 | R44: 0 | T44: =SUM(N44)-SUM(O44:P44)-SUM(Q44:S44)*2 -> 0 | U44: =SUM(O44:T44) -> 0
A45: 312000 | B45: Convention Cntr ADS | C45: ='BUDGET DETAIL'!A92 -> 88 | K45: TABLE 3 | L45: =VLOOKUP(C45,table3,12)+VLOOKUP(D45,table3,12)+VLOOKUP(E45,table3,12)+VLOOKUP(F45,table3,12)+VLOOKUP(G45,table3,12) -> 0 | N45: =SUM(M45,L45) -> 0 | R45: 0 | T45: =SUM(N45)-SUM(O45:P45)-SUM(Q45:S45)*2 -> 0 | U45: =SUM(O45:T45) -> 0
A46: 309000 | B46: Lents Twn Ctr URA DR | K46: TABLE 3 | L46: =VLOOKUP(C46,table3,12)+VLOOKUP(D46,table3,12)+VLOOKUP(E46,table3,12)+VLOOKUP(F46,table3,12)+VLOOKUP(G46,table3,12) -> 0 | N46: =SUM(M46,L46) -> 0 | R46: 0 | T46: =SUM(N46)-SUM(O46:P46)-SUM(Q46:S46)*2 -> 0 | U46: =SUM(O46:T46) -> 0
A47: 313000 | B47: N Macadam URA DR | C47: ='BUDGET DETAIL'!A93 -> 89 | K47: TABLE 3 | L47: =VLOOKUP(C47,table3,12)+VLOOKUP(D47,table3,12)+VLOOKUP(E47,table3,12)+VLOOKUP(F47,table3,12)+VLOOKUP(G47,table3,12) -> 0 | N47: =SUM(M47,L47) -> 0 | R47: 0 | T47: =SUM(N47)-SUM(O47:P47)-SUM(Q47:S47)*2 -> 0 | U47: =SUM(O47:T47) -> 0
A48: 314000 | B48: Special Prjt Dbt Svc | C48: ='BUDGET DETAIL'!A94 -> 90 | K48: TABLE 3 | L48: =VLOOKUP(C48,table3,12)+VLOOKUP(D48,table3,12)+VLOOKUP(E48,table3,12)+VLOOKUP(F48,table3,12)+VLOOKUP(G48,table3,12) -> 0 | N48: =SUM(M48,L48) -> 0 | R48: 0 | T48: =SUM(N48)-SUM(O48:P48)-SUM(Q48:S48)*2 -> 0 | U48: =SUM(O48:T48) -> 0
A49: 315000 | B49: Gateway URA DR | C49: ='BUDGET DETAIL'!A95 -> 91 | K49: TABLE 3 | L49: =VLOOKUP(C49,table3,12)+VLOOKUP(D49,table3,12)+VLOOKUP(E49,table3,12)+VLOOKUP(F49,table3,12)+VLOOKUP(G49,table3,12) -> 0 | N49: =SUM(M49,L49) -> 0 | R49: 0 | T49: =SUM(N49)-SUM(O49:P49)-SUM(Q49:S49)*2 -> 0 | U49: =SUM(O49:T49) -> 0
A50: 213000 | B50: Housing Investment | C50: ='BUDGET DETAIL'!A43 -> 39 | D50: ='BUDGET DETAIL'!A56 -> 52 | E50: ='BUDGET DETAIL'!A57 -> 53 | K50: TABLE 3 | L50: =VLOOKUP(C50,table3,12)+VLOOKUP(D50,table3,12)+VLOOKUP(E50,table3,12)+VLOOKUP(F50,table3,12)+VLOOKUP(G50,table3,12) -> 6142941.8 | N50: =SUM(M50,L50) -> 6142941.8 | Q50: =+N50*0.5 -> 3071470.9 | T50: =SUM(N50)-SUM(O50:P50)-SUM(Q50:S50)*2 -> 0 | U50: =SUM(O50:T50) -> 3071470.9
A51: 210000 | B51: General Reserve | K51: TABLE 3 | L51: =VLOOKUP(C51,table3,12)+VLOOKUP(D51,table3,12)+VLOOKUP(E51,table3,12)+VLOOKUP(F51,table3,12)+VLOOKUP(G51,table3,12) -> 0 | N51: =SUM(M51,L51) -> 0 | Q51: =+N51*0.5 -> 0 | T51: =SUM(N51)-SUM(O51:P51)-SUM(Q51:S51)*2 -> 0 | U51: =SUM(O51:T51) -> 0
A52: 304000 | B52: Interstate C Dbt Svc | K52: TABLE 3 | L52: =VLOOKUP(C52,table3,12)+VLOOKUP(D52,table3,12)+VLOOKUP(E52,table3,12)+VLOOKUP(F52,table3,12)+VLOOKUP(G52,table3,12) -> 0 | N52: =SUM(M52,L52) -> 0 | R52: 0 | T52: =SUM(N52)-SUM(O52:P52)-SUM(Q52:S52)*2 -> 0 | U52: =SUM(O52:T52) -> 0
A53: 100000 | B53: General Fund Contingency | K53: TABLE 3 | L53: =VLOOKUP(C53,table3,12)+VLOOKUP(D53,table3,12)+VLOOKUP(E53,table3,12)+VLOOKUP(F53,table3,12)+VLOOKUP(G53,table3,12) -> 0 | N53: =SUM(M53,L53) -> 0 | T53: =SUM(N53)-SUM(O53:P53)-SUM(Q53:S53)*2 -> 0 | U53: =SUM(O53:T53) -> 0
A54: 100000 | B54: Gen Fund Reimb Expenditures | K54: TABLE 3 | L54: =VLOOKUP(C54,table3,12)+VLOOKUP(D54,table3,12)+VLOOKUP(E54,table3,12)+VLOOKUP(F54,table3,12)+VLOOKUP(G54,table3,12) -> 0 | N54: =SUM(M54,L54) -> 0 | Q54: =+N54*0.5 -> 0 | T54: =SUM(N54)-SUM(O54:P54)-SUM(Q54:S54)*2 -> 0 | U54: =SUM(O54:T54) -> 0
A55: 100000 | B55: General Fund Transfers | K55: TABLE 3 | L55: =VLOOKUP(C55,table3,12)+VLOOKUP(D55,table3,12)+VLOOKUP(E55,table3,12)+VLOOKUP(F55,table3,12)+VLOOKUP(G55,table3,12) -> 0 | N55: =SUM(M55,L55) -> 0 | T55: =SUM(N55)-SUM(O55:P55)-SUM(Q55:S55)*2 -> 0 | U55: =SUM(O55:T55) -> 0
A56: 100000 | B56: Cable Communications & Franchise Management | C56: ='BUDGET DETAIL'!A7 -> 3 | K56: TABLE 3 | L56: =VLOOKUP(C56,table3,12)+VLOOKUP(D56,table3,12)+VLOOKUP(E56,table3,12)+VLOOKUP(F56,table3,12)+VLOOKUP(G56,table3,12) -> 2173400.8 | N56: =SUM(M56,L56) -> 2173400.8 | T56: =SUM(N56)-SUM(O56:P56)-SUM(Q56:S56)*2 -> 2173400.8 | U56: =SUM(O56:T56) -> 2173400.8
A57: 100000 | B57: Office of Sustainable Development (OSD) | K57: TABLE 3 | L57: =VLOOKUP(C57,table3,12)+VLOOKUP(D57,table3,12)+VLOOKUP(E57,table3,12)+VLOOKUP(F57,table3,12)+VLOOKUP(G57,table3,12) -> 0 | N57: =SUM(M57,L57) -> 0 | T57: =SUM(N57)-SUM(O57:P57)-SUM(Q57:S57)*2 -> 0 | U57: =SUM(O57:T57) -> 0
A58: 206000 | B58: Cable | C58: ='BUDGET DETAIL'!A40 -> 36 | K58: TABLE 3 | L58: =VLOOKUP(C58,table3,12)+VLOOKUP(D58,table3,12)+VLOOKUP(E58,table3,12)+VLOOKUP(F58,table3,12)+VLOOKUP(G58,table3,12) -> 5315702.4 | N58: =SUM(M58,L58) -> 5315702.4 | Q58: =+N58*0.5 -> 2657851.2 | T58: =SUM(N58)-SUM(O58:P58)-SUM(Q58:S58)*2 -> 0 | U58: =SUM(O58:T58) -> 2657851.2
A59: 100000 | B59: Office of Human Relations | C59: ='BUDGET DETAIL'!A13 -> 9 | K59: TABLE 3 | L59: =VLOOKUP(C59,table3,12)+VLOOKUP(D59,table3,12)+VLOOKUP(E59,table3,12)+VLOOKUP(F59,table3,12)+VLOOKUP(G59,table3,12) -> 230029.91 | N59: =SUM(M59,L59) -> 230029.91 | T59: =SUM(N59)-SUM(O59:P59)-SUM(Q59:S59)*2 -> 230029.91 | U59: =SUM(O59:T59) -> 230029.91
A60: 100000 | B60: General Fund Revenues/Balance | K60: TABLE 3 | L60: =VLOOKUP(C60,table3,12)+VLOOKUP(D60,table3,12)+VLOOKUP(E60,table3,12)+VLOOKUP(F60,table3,12)+VLOOKUP(G60,table3,12) -> 0 | N60: =SUM(M60,L60) -> 0 | T60: =SUM(N60)-SUM(O60:P60)-SUM(Q60:S60)*2 -> 0 | U60: =SUM(O60:T60) -> 0
A61: 100000 | B61: Business Licenses | K61: TABLE 3 | L61: =VLOOKUP(C61,table3,12)+VLOOKUP(D61,table3,12)+VLOOKUP(E61,table3,12)+VLOOKUP(F61,table3,12)+VLOOKUP(G61,table3,12) -> 0 | N61: =SUM(M61,L61) -> 0 | T61: =SUM(N61)-SUM(O61:P61)-SUM(Q61:S61)*2 -> 0 | U61: =SUM(O61:T61) -> 0
A62: 208000 | B62: Business Lic Surchg | K62: TABLE 3 | L62: =VLOOKUP(C62,table3,12)+VLOOKUP(D62,table3,12)+VLOOKUP(E62,table3,12)+VLOOKUP(F62,table3,12)+VLOOKUP(G62,table3,12) -> 0 | N62: =SUM(M62,L62) -> 0 | Q62: =+N62*0.5 -> 0 | T62: =SUM(N62)-SUM(O62:P62)-SUM(Q62:S62)*2 -> 0 | U62: =SUM(O62:T62) -> 0
A63: 207000 | B63: Prvt Hire TR Safety | K63: TABLE 3 | L63: =VLOOKUP(C63,table3,12)+VLOOKUP(D63,table3,12)+VLOOKUP(E63,table3,12)+VLOOKUP(F63,table3,12)+VLOOKUP(G63,table3,12) -> 0 | N63: =SUM(M63,L63) -> 0 | Q63: =+N63*0.5 -> 0 | T63: =SUM(N63)-SUM(O63:P63)-SUM(Q63:S63)*2 -> 0 | U63: =SUM(O63:T63) -> 0
A64: 100000 | B64: Office of Neighborhood Involvement | C64: ='BUDGET DETAIL'!A17 -> 13 | D64: ='BUDGET DETAIL'!A18 -> 14 | E64: 57 | K64: TABLE 3 | L64: =VLOOKUP(C64,table3,12)+VLOOKUP(D64,table3,12)+VLOOKUP(E64,table3,12)+VLOOKUP(F64,table3,12)+VLOOKUP(G64,table3,12) -> 6207640.8 | M64: =45000*0 -> 0 | N64: =SUM(M64,L64) -> 6207640.8 | S64: =(VLOOKUP(D64,table3,12))/2 -> 4359.95 | T64: =SUM(N64)-SUM(O64:P64)-SUM(Q64:S64)*2 -> 6198920.9 | U64: =SUM(O64:T64) -> 6203280.8
A65: mfop000071 | B65: Internal Business Sv | C65: 7 | D65: 8 | K65: TABLE 5 | L65: =VLOOKUP(C65,table5,12)-VLOOKUP(D65,table5,12) -> 247782.87 | N65: =SUM(M65,L65) -> 247782.87 | T65: =SUM(N65)-SUM(O65:P65)-SUM(Q65:S65)*2 -> 247782.87 | U65: =SUM(O65:T65) -> 247782.87
A66: mfcp | B66: Citywide Projects | C66: 6 | K66: TABLE 5 | L66: =VLOOKUP(C66,table5,12) -> 1051576.9 | N66: =SUM(M66,L66) -> 1051576.9 | T66: =SUM(N66)-SUM(O66:P66)-SUM(Q66:S66)*2 -> 1051576.9 | U66: =SUM(O66:T66) -> 1051576.9
A67: 703000 | B67: P&D Srvcs Operating | C67: 127 | K67: TABLE 3 | L67: =VLOOKUP(C67,table3,12)+VLOOKUP(D67,table3,12)+VLOOKUP(E67,table3,12)+VLOOKUP(F67,table3,12)+VLOOKUP(G67,table3,12) -> 5514266.5 | N67: =SUM(M67,L67) -> 5514266.5 | R67: 0 | S67: 0 | T67: =SUM(N67)-SUM(O67:P67)-SUM(Q67:S67)*2 -> 5514266.5 | U67: =SUM(O67:T67) -> 5514266.5
A68: 0 | B68: ='BUDGET DETAIL'!E82 -> Office of Equity & Human Rights | C68: 78 | K68: TABLE 3 | L68: =VLOOKUP(C68,table3,12)+VLOOKUP(D68,table3,12)+VLOOKUP(E68,table3,12)+VLOOKUP(F68,table3,12)+VLOOKUP(G68,table3,12) -> 375051.66 | N68: =SUM(M68,L68) -> 375051.66 | R68: 0 | S68: 0 | T68: =SUM(N68)-SUM(O68:P68)-SUM(Q68:S68)*2 -> 375051.66 | U68: =SUM(O68:T68) -> 375051.66
A69: 100000 | B69: Revenue Bureau | C69: 5 | K69: TABLE 5 | L69: =VLOOKUP(C69,table5,12)+VLOOKUP(D69,table3,12)+VLOOKUP(E69,table3,12)+VLOOKUP(F69,table3,12)+VLOOKUP(G169,table3,12)+VLOOKUP(H69,table3,12) -> 7398354.2 | N69: =SUM(M69,L69) -> 7398354.2 | T69: =SUM(N69)-SUM(O69:P69)-SUM(Q69:S69)*2 -> 7398354.2 | U69: =SUM(O69:T69) -> 7398354.2
A70: mfsa | B70: Special Appropriations | K70: TABLE 3 | L70: =VLOOKUP(C70,table3,12)+VLOOKUP(D70,table3,12)+VLOOKUP(E70,table3,12)+VLOOKUP(F70,table3,12)+VLOOKUP(G70,table3,12) -> 0 | N70: 6476768.1 | T70: =SUM(N70)-SUM(O70:P70)-SUM(Q70:S70)*2 -> 6476768.1 | U70: =SUM(O70:T70) -> 6476768.1
A71: 220000 | B71: Portland Park Mem Tr | C71: ='BUDGET DETAIL'!A78 -> 74 | K71: TABLE 3 | L71: =VLOOKUP(C71,table3,12)+VLOOKUP(D71,table3,12)+VLOOKUP(E71,table3,12)+VLOOKUP(F71,table3,12)+VLOOKUP(G71,table3,12) -> 476962.72 | N71: 0 | P71: 818233 | S71: =(VLOOKUP(C71,table3,10))/2 -> 0 | T71: =SUM(N71)-SUM(O71:P71)-SUM(Q71:S71)*2 -> -818233 | U71: =SUM(O71:T71) -> 0
A72: 500000 | B72: Parks Endowment | C72: ='BUDGET DETAIL'!A105 -> 101 | K72: TABLE 3 | L72: =VLOOKUP(C72,table3,12)+VLOOKUP(D72,table3,12)+VLOOKUP(E72,table3,12)+VLOOKUP(F72,table3,12)+VLOOKUP(G72,table3,12) -> 0 | N72: =SUM(M72,L72) -> 0 | P72: 225 | T72: =SUM(N72)-SUM(O72:P72)-SUM(Q72:S72)*2 -> -225 | U72: =SUM(O72:T72) -> 0
A73: 616000 | B73: Wtr Grwth Imp Chg Tr | K73: TABLE 3 | L73: =VLOOKUP(C73,table3,12)+VLOOKUP(D73,table3,12)+VLOOKUP(E73,table3,12)+VLOOKUP(F73,table3,12)+VLOOKUP(G73,table3,12) -> 0 | N73: =SUM(M73,L73) -> 0 | P73: =+N73*0 -> 0 | T73: =SUM(N73)-SUM(O73:P73)-SUM(Q73:S73)*2 -> 0 | U73: =SUM(O73:T73) -> 0
A74: mfhr000010 | B74: Health Insurance Op | K74: TABLE 3 | L74: =1115804.32+94718.06 -> 1210522.4 | N74: =SUM(M74,L74) -> 1210522.4 | R74: 0 | T74: =SUM(N74)-SUM(O74:P74)-SUM(Q74:S74)*2 -> 1210522.4 | U74: =SUM(O74:T74) -> 1210522.4
A75: 100000 | B75: Bureau of Planning & Sustainability | C75: ='BUDGET DETAIL'!A23 -> 19 | D75: ='BUDGET DETAIL'!A24 -> 20 | E75: ='BUDGET DETAIL'!A67 -> 63 | F75: ='BUDGET DETAIL'!A68 -> 64 | K75: TABLE 3 | L75: =VLOOKUP(C75,table3,12)+VLOOKUP(D75,table3,12)+VLOOKUP(E75,table3,12)+VLOOKUP(F75,table3,12)+VLOOKUP(G75,table3,12) -> 22876794 | N75: =SUM(M75,L75) -> 22876794 | S75: =(VLOOKUP(D75,table3,12))/2 -> 1152.115 | T75: =SUM(N75)-SUM(O75:P75)-SUM(Q75:S75)*2 -> 22874490 | U75: =SUM(O75:T75) -> 22875642
A76: 203000 | B76: Development Services | C76: ='BUDGET DETAIL'!A37 -> 33 | D76: ='BUDGET DETAIL'!A38 -> 34 | E76: ='BUDGET DETAIL'!A47 -> 43 | K76: TABLE 3 | L76: =VLOOKUP(C76,table3,12)+VLOOKUP(D76,table3,12)+VLOOKUP(E76,table3,12)+VLOOKUP(F76,table3,12)+VLOOKUP(G76,table3,12) -> 19345623 | N76: =SUM(M76,L76) -> 19345623 | R76: 0 | S76: =(VLOOKUP(D76,table3,12)+VLOOKUP(E76,table3,10))/2 -> 222651.35 | T76: =SUM(N76)-SUM(O76:P76)-SUM(Q76:S76)*2 -> 18900321 | U76: =SUM(O76:T76) -> 19122972
A77: 218000 | B77: CDBG Incoming (Ext) | C77: ='BUDGET DETAIL'!A76 -> 72 | K77: TABLE 3 | L77: =VLOOKUP(C77,table3,12)+VLOOKUP(D77,table3,12)+VLOOKUP(E77,table3,12)+VLOOKUP(F77,table3,12)+VLOOKUP(G77,table3,12) -> 8788094.9 | N77: =SUM(M77,L77) -> 8788094.9 | Q77: =+N77*0.5 -> 4394047.4 | T77: =SUM(N77)-SUM(O77:P77)-SUM(Q77:S77)*2 -> 0 | U77: =SUM(O77:T77) -> 4394047.4
A78: 219000 | B78: HOME Incoming (Ext) | C78: ='BUDGET DETAIL'!A77 -> 73 | K78: TABLE 3 | L78: =VLOOKUP(C78,table3,12)+VLOOKUP(D78,table3,12)+VLOOKUP(E78,table3,12)+VLOOKUP(F78,table3,12)+VLOOKUP(G78,table3,12) -> 3945472.2 | N78: =SUM(M78,L78) -> 3945472.2 | Q78: =+N78*0.5 -> 1972736.1 | T78: =SUM(N78)-SUM(O78:P78)-SUM(Q78:S78)*2 -> 0 | U78: =SUM(O78:T78) -> 1972736.1
A79: 100000 | B79: Portland Housing Bureau | C79: ='BUDGET DETAIL'!A12 -> 8 | K79: TABLE 3 | L79: =VLOOKUP(C79,table3,12)+VLOOKUP(D79,table3,12)+VLOOKUP(E79,table3,12)+VLOOKUP(F79,table3,12)+VLOOKUP(G79,table3,12) -> 11593972 | N79: =SUM(M79,L79) -> 11593972 | R79: =0*0.5 -> 0 | T79: =SUM(N79)-SUM(O79:P79)-SUM(Q79:S79)*2 -> 11593972 | U79: =SUM(O79:T79) -> 11593972
A80: 621000 | B80: Headwaters Apartment Complex Fund | C80: ='BUDGET DETAIL'!A125 -> 121 | K80: TABLE 3 | L80: =VLOOKUP(C80,table3,12)+VLOOKUP(D80,table3,12)+VLOOKUP(E80,table3,12)+VLOOKUP(F80,table3,12)+VLOOKUP(G80,table3,12) -> 175 | N80: =SUM(M80,L80) -> 175 | R80: 0 | T80: =SUM(N80)-SUM(O80:P80)-SUM(Q80:S80)*2 -> 175 | U80: =SUM(O80:T80) -> 175
A81: 706000 | B81: Technology Services | C81: ='BUDGET DETAIL'!A134 -> 130 | D81: ='BUDGET DETAIL'!A135 -> 131 | K81: TABLE 3, TABLE 4 | L81: =VLOOKUP(C81,table3,12)+VLOOKUP(D81,table3,12)+VLOOKUP(E81,table3,12)+VLOOKUP(F81,table3,12)+VLOOKUP(G81,table3,12) -> 40853188 | M81: =VLOOKUP(5,table4,12) -> 110679.3 | N81: =SUM(M81,L81) -> 40963868 | R81: 0 | S81: =(VLOOKUP(D81,table3,12)+VLOOKUP(E81,table3,10))/2 -> 1883096.4 | T81: =SUM(N81)-SUM(O81:P81)-SUM(Q81:S81)*2 -> 37197675 | U81: =SUM(O81:T81) -> 39080771
A82: 702000 | B82: CityFleet Operating | C82: 125 | D82: 126 | K82: TABLE 3, TABLE 4 | L82: =VLOOKUP(C82,table3,12)+VLOOKUP(D82,table3,12)+VLOOKUP(E82,table3,12)+VLOOKUP(F82,table3,12)+VLOOKUP(G82,table3,12) -> 24170631 | M82: =VLOOKUP(1,table4,12) -> 0 | N82: =SUM(M82,L82) -> 24170631 | R82: 0 | S82: =(VLOOKUP(D82,table3,10))/2 -> 0 | T82: =SUM(N82)-SUM(O82:P82)-SUM(Q82:S82)*2 -> 24170631 | U82: =SUM(O82:T82) -> 24170631
A83: 704000 | B83: Insurance & Claim Op | C83: ='BUDGET DETAIL'!A132 -> 128 | K83: TABLE 3 | L83: =VLOOKUP(C83,table3,12)+VLOOKUP(D83,table3,12)+VLOOKUP(E83,table3,12)+VLOOKUP(F83,table3,12)+VLOOKUP(G83,table3,12) -> 6440525.6 | N83: =SUM(M83,L83) -> 6440525.6 | R83: 0 | S83: =(VLOOKUP(D83,table3,10))/2 -> 0 | T83: =SUM(N83)-SUM(O83:P83)-SUM(Q83:S83)*2 -> 6440525.6 | U83: =SUM(O83:T83) -> 6440525.6
A84: 705000 | B84: Wkr Comp Self Ins Op | C84: ='BUDGET DETAIL'!A133 -> 129 | K84: TABLE 3 | L84: =VLOOKUP(C84,table3,12)+VLOOKUP(D84,table3,12)+VLOOKUP(E84,table3,12)+VLOOKUP(F84,table3,12)+VLOOKUP(G84,table3,12) -> 3495172.9 | N84: =SUM(M84,L84) -> 3495172.9 | R84: 0 | S84: =(VLOOKUP(D84,table3,10))/2 -> 0 | T84: =SUM(N84)-SUM(O84:P84)-SUM(Q84:S84)*2 -> 3495172.9 | U84: =SUM(O84:T84) -> 3495172.9
A85: 707000 | B85: PPA Health Insurance | K85: TABLE 3 | L85: 0 | N85: =SUM(M85,L85) -> 0 | T85: =SUM(N85)-SUM(O85:P85)-SUM(Q85:S85)*2 -> 0 | U85: =SUM(O85:T85) -> 0
A86: 612000 | B86: Water Bond Sinking | K86: TABLE 3 | L86: 0 | N86: =SUM(M86,L86) -> 0 | T86: =SUM(N86)-SUM(O86:P86)-SUM(Q86:S86)*2 -> 0 | U86: =SUM(O86:T86) -> 0
A87: 604000 | B87: Portland Int Raceway | C87: ='BUDGET DETAIL'!A113 -> 109 | D87: 82 | K87: TABLE 3 | L87: =VLOOKUP(C87,table3,12)+VLOOKUP(D87,table3,12)+VLOOKUP(E87,table3,12)+VLOOKUP(F87,table3,12)+VLOOKUP(G87,table3,12) -> 1263254.7 | N87: =SUM(M87,L87) -> 1263254.7 | R87: 0 | S87: =(VLOOKUP(D87,table3,12))/2 -> 7942.525 | T87: =SUM(N87)-SUM(O87:P87)-SUM(Q87:S87)*2 -> 1247369.6 | U87: =SUM(O87:T87) -> 1255312.1
A88: 603000 | B88: Golf | C88: ='BUDGET DETAIL'!A111 -> 107 | D88: ='BUDGET DETAIL'!A112 -> 108 | K88: TABLE 3 | L88: =VLOOKUP(C88,table3,12)+VLOOKUP(D88,table3,12)+VLOOKUP(E88,table3,12)+VLOOKUP(F88,table3,12)+VLOOKUP(G88,table3,12) -> 6364493.5 | N88: =SUM(M88,L88) -> 6364493.5 | R88: 0 | S88: =(VLOOKUP(C88,table3,12))/2 -> 136051.35 | T88: =SUM(N88)-SUM(O88:P88)-SUM(Q88:S88)*2 -> 6092390.8 | U88: =SUM(O88:T88) -> 6228442.1
A89: 610000 | B89: Golf Rev Bond Rdmpt | C89: ='BUDGET DETAIL'!A121 -> 117 | K89: TABLE 3 | L89: =VLOOKUP(C89,table3,12)+VLOOKUP(D89,table3,12)+VLOOKUP(E89,table3,12)+VLOOKUP(F89,table3,12)+VLOOKUP(G89,table3,12) -> 0 | N89: =SUM(M89,L89) -> 0 | R89: 0 | T89: =SUM(N89)-SUM(O89:P89)-SUM(Q89:S89)*2 -> 0 | U89: =SUM(O89:T89) -> 0
A90: 202000 | B90: Emergency Comm | C90: ='BUDGET DETAIL'!A33 -> 29 | D90: ='BUDGET DETAIL'!A34 -> 30 | E90: ='BUDGET DETAIL'!A35 -> 31 | F90: ='BUDGET DETAIL'!A36 -> 32 | G90: 44 | H90: 56 | K90: TABLE 3 | L90: =VLOOKUP(C90,table3,12)+VLOOKUP(D90,table3,12)+VLOOKUP(E90,table3,12)+VLOOKUP(F90,table3,12)+VLOOKUP(G90,table3,12)+VLOOKUP(H90,table3,12) -> 14302492 | N90: =SUM(M90,L90) -> 14302492 | R90: 0 | S90: =(VLOOKUP(D90,table3,12))/2+(VLOOKUP(H90,table3,12)/2) -> 69586.845 | T90: =SUM(N90)-SUM(O90:P90)-SUM(Q90:S90)*2 -> 14163318 | U90: =SUM(O90:T90) -> 14232905
A91: 601000 | B91: Hydroelectric Pwr Op | C91: ='BUDGET DETAIL'!A108 -> 104 | K91: TABLE 3 | L91: =VLOOKUP(C91,table3,12)+VLOOKUP(D91,table3,12)+VLOOKUP(E91,table3,12)+VLOOKUP(F91,table3,12)+VLOOKUP(G91,table3,12) -> 342322.09 | N91: =SUM(M91,L91) -> 342322.09 | R91: 0 | T91: =SUM(N91)-SUM(O91:P91)-SUM(Q91:S91)*2 -> 342322.09 | U91: =SUM(O91:T91) -> 342322.09
A92: 611000 | B92: Hydro Pwr Bond Rdmpt | C92: ='BUDGET DETAIL'!A122 -> 118 | K92: TABLE 3 | L92: =VLOOKUP(C92,table3,12)+VLOOKUP(D92,table3,12)+VLOOKUP(E92,table3,12)+VLOOKUP(F92,table3,12)+VLOOKUP(G92,table3,12) -> 0 | N92: =SUM(M92,L92) -> 0 | R92: 0 | T92: =SUM(N92)-SUM(O92:P92)-SUM(Q92:S92)*2 -> 0 | U92: =SUM(O92:T92) -> 0
A93: 618000 | B93: Hydro Pwr Rnwl Rplmt | K93: TABLE 3 | L93: 0 | N93: =SUM(M93,L93) -> 0 | P93: =+N93*0 -> 0 | T93: =SUM(N93)-SUM(O93:P93)-SUM(Q93:S93)*2 -> 0 | U93: =SUM(O93:T93) -> 0
A94: 606000 | B94: Parking Facilities | C94: ='BUDGET DETAIL'!A116 -> 112 | D94: 111 | K94: TABLE 3 | L94: =VLOOKUP(C94,table3,12)+VLOOKUP(D94,table3,12)+VLOOKUP(E94,table3,12)+VLOOKUP(F94,table3,12)+VLOOKUP(G94,table3,12) -> 4996465.6 | N94: =SUM(M94,L94) -> 4996465.6 | R94: 0 | S94: =(VLOOKUP(D94,table3,12))/2 -> 620518.81 | T94: =SUM(N94)-SUM(O94:P94)-SUM(Q94:S94)*2 -> 3755428 | U94: =SUM(O94:T94) -> 4375946.8
A95: 613000 | B95: Parking Fac Db Rdmpt | K95: TABLE 3 | L95: 0 | N95: =SUM(M95,L95) -> 0 | R95: 0 | T95: =SUM(N95)-SUM(O95:P95)-SUM(Q95:S95)*2 -> 0 | U95: =SUM(O95:T95) -> 0
A96: 701000 | B96: Facilities Svcs Op | C96: ='BUDGET DETAIL'!A127 -> 123 | D96: ='BUDGET DETAIL'!A128 -> 124 | K96: TABLE 3, TABLE 4 | L96: =VLOOKUP(C96,table3,12)+VLOOKUP(D96,table3,12)+VLOOKUP(E96,table3,12)+VLOOKUP(F96,table3,12)+VLOOKUP(G96,table3,12) -> 26946921 | M96: =VLOOKUP(2,table4,12)+VLOOKUP(3,table4,12)+VLOOKUP(4,table4,12) -> 4470031.2 | N96: =SUM(M96,L96) -> 31416952 | R96: 0 | S96: =VLOOKUP(D96,table3,12)+VLOOKUP(3,table4,10) -> 10369149 | T96: =SUM(N96)-SUM(O96:P96)-SUM(Q96:S96)*2 -> 10678655 | U96: =SUM(O96:T96) -> 21047803
A97: 400000 | B97: BFRES Fac GO Bd Cstr | C97: ='BUDGET DETAIL'!A98 -> 94 | D97: ='BUDGET DETAIL'!A99 -> 95 | K97: TABLE 3 | L97: =VLOOKUP(C97,table3,12)+VLOOKUP(D97,table3,12)+VLOOKUP(E97,table3,12)+VLOOKUP(F97,table3,12)+VLOOKUP(G97,table3,12) -> 1643006.2 | N97: =SUM(M97,L97) -> 1643006.2 | R97: 0 | S97: =(VLOOKUP(D97,table3,12)/2) -> 821328.09 | T97: =SUM(N97)-SUM(O97:P97)-SUM(Q97:S97)*2 -> 350 | U97: =SUM(O97:T97) -> 821678.09
A98: 401000 | B98: LID Construction | C98: ='BUDGET DETAIL'!A100 -> 96 | K98: TABLE 3 | L98: =VLOOKUP(C98,table3,12)+VLOOKUP(D98,table3,12)+VLOOKUP(E98,table3,12)+VLOOKUP(F98,table3,12)+VLOOKUP(G98,table3,12) -> 2950 | N98: =SUM(M98,L98) -> 2950 | R98: 0 | S98: =(VLOOKUP(C98,table3,12)/2) -> 1475 | T98: =SUM(N98)-SUM(O98:P98)-SUM(Q98:S98)*2 -> 0 | U98: =SUM(O98:T98) -> 1475
A99: 308000 | B99: Gas Tax Bond Rdmpt | C99: ='BUDGET DETAIL'!A88 -> 84 | K99: TABLE 3 | L99: =VLOOKUP(C99,table3,12)+VLOOKUP(D99,table3,12)+VLOOKUP(E99,table3,12)+VLOOKUP(F99,table3,12)+VLOOKUP(G99,table3,12) -> 0 | N99: =SUM(M99,L99) -> 0 | R99: 0 | T99: =SUM(N99)-SUM(O99:P99)-SUM(Q99:S99)*2 -> 0 | U99: =SUM(O99:T99) -> 0
A100: 311000 | B100: Bancroft Int & Sinkg | C100: ='BUDGET DETAIL'!A91 -> 87 | K100: TABLE 3 | L100: =VLOOKUP(C100,table3,12)+VLOOKUP(D100,table3,12)+VLOOKUP(E100,table3,12)+VLOOKUP(F100,table3,12)+VLOOKUP(G100,table3,12) -> 0 | N100: =SUM(M100,L100) -> 0 | R100: 0 | T100: =SUM(N100)-SUM(O100:P100)-SUM(Q100:S100)*2 -> 0 | U100: =SUM(O100:T100) -> 0
A101: 401000 | B101: LID Construction | C101: 0 | K101: TABLE 3 | L101: 0 | N101: =SUM(M101,L101) -> 0 | T101: =SUM(N101)-SUM(O101:P101)-SUM(Q101:S101)*2 -> 0 | U101: =SUM(O101:T101) -> 0
A102: 402000 | B102: Parks Cap Cstr Maint | C102: ='BUDGET DETAIL'!A101 -> 97 | D102: ='BUDGET DETAIL'!A102 -> 98 | K102: TABLE 3 | L102: =VLOOKUP(C102,table3,12)+VLOOKUP(D102,table3,12)+VLOOKUP(E102,table3,12)+VLOOKUP(F102,table3,12)+VLOOKUP(G102,table3,12) -> 6655464.3 | N102: =SUM(M102,L102) -> 6655464.3 | R102: 0 | S102: =(VLOOKUP(D102,table3,12)/2)+(VLOOKUP(C102,table3,12)/2) -> 3327732.2 | T102: =SUM(N102)-SUM(O102:P102)-SUM(Q102:S102)*2 -> 0 | U102: =SUM(O102:T102) -> 3327732.2
A103: 317000 | B103: Governmentl Bd Rdmpt | C103: ='BUDGET DETAIL'!A97 -> 93 | K103: TABLE 3 | L103: =VLOOKUP(C103,table3,12)+VLOOKUP(D103,table3,12)+VLOOKUP(E103,table3,12)+VLOOKUP(F103,table3,12)+VLOOKUP(G103,table3,12) -> 0 | N103: =SUM(M103,L103) -> 0 | R103: 0 | T103: =SUM(N103)-SUM(O103:P103)-SUM(Q103:S103)*2 -> 0 | U103: =SUM(O103:T103) -> 0
...

Sheet BUDGET DETAIL
B2: Fund | C2: Fund_Name | D2: Bureau | E2: Bureau_Name | F2: Type | G2: Personal | H2: EMS | I2: IMS | J2: CAPITAL_OUTLAY | K2: Debt_Service
A3: TABLE3
A4: 0
A5: 1 | B5: 100 | C5: General Fund | D5: AT | E5: Office of City Attorney | F5: Operating | G5: 0 | H5: 0 | I5: 0 | J5: 0 | K5: 0 | L5: 8387785.4
A6: =A5+1 -> 2 | B6: 100 | C6: General Fund | D6: AU | E6: Office of the City Auditor | F6: Operating | G6: 0 | H6: 0 | I6: 0 | J6: 0 | K6: 0 | L6: 6285473.2
A7: =A6+1 -> 3 | B7: 100 | C7: General Fund | D7: CB | E7: Cable Communications and Franchise Management | F7: Operating | G7: 0 | H7: 0 | I7: 0 | J7: 0 | K7: 0 | L7: 2173400.8
A8: =A7+1 -> 4 | B8: 100 | C8: General Fund | D8: EM | E8: Portland Office of Emergency Management | F8: Operating | G8: 0 | H8: 0 | I8: 0 | J8: 0 | K8: 0 | L8: 1273146.9
A9: =A8+1 -> 5 | B9: 100 | C9: General Fund | D9: FR | E9: Portland Fire and Rescue | F9: Capital | G9: 0 | H9: 0 | I9: 0 | J9: 0 | K9: 0 | L9: 513003.51
A10: =A9+1 -> 6 | B10: 100 | C10: General Fund | D10: FR | E10: Portland Fire and Rescue | F10: Operating | G10: 0 | H10: 0 | I10: 0 | J10: 0 | K10: 0 | L10: 89278598
A11: =A10+1 -> 7 | B11: 100 | C11: General Fund | D11: GR | E11: Office of Government Relations | F11: Operating | G11: 0 | H11: 0 | I11: 0 | J11: 0 | K11: 0 | L11: 1096031.6
A12: =A11+1 -> 8 | B12: 100 | C12: General Fund | D12: HC | E12: Portland Housing Bureau | F12: Operating | G12: 0 | H12: 0 | I12: 0 | J12: 0 | K12: 0 | L12: 11593972
A13: =A12+1 -> 9 | B13: 100 | C13: General Fund | D13: HN | E13: Office of Human Relations | F13: Operating | G13: 0 | H13: 0 | I13: 0 | J13: 0 | K13: 0 | L13: 230029.91
A14: =A13+1 -> 10 | B14: 100 | C14: General Fund | D14: MF | E14: Office of Management and Finance | F14: Operating | G14: 0 | H14: 0 | I14: 0 | J14: 0 | K14: 0 | L14: 37750743
A15: =A14+1 -> 11 | B15: 100 | C15: General Fund | D15: MF | E15: Office of Management and Finance | F15: Capital | G15: 0 | H15: 0 | I15: 0 | J15: 0 | K15: 0 | L15: 532438.52
A16: =A15+1 -> 12 | B16: 100 | C16: General Fund | D16: MY | E16: Office of the Mayor | F16: Operating | G16: 0 | H16: 0 | I16: 0 | J16: 0 | K16: 0 | L16: 3538476.9
A17: =A16+1 -> 13 | B17: 100 | C17: General Fund | D17: NI | E17: Office of Neighborhood Involvement | F17: Operating | G17: 0 | H17: 0 | I17: 0 | J17: 0 | K17: 0 | L17: 6193920.9
... A83: =A82+1 -> 79 | B83: 217 | C83: Grants Fund | D83: FR | E83: Portland Fire and Rescue | F83: Capital | G83: 0 | H83: 0 | I83: 0 | J83: 0 | K83: 0 | L83: 336467.38
A84: =A83+1 -> 80 | B84: 217 | C84: Grants Fund | D84: MY | E84: =#REF! -> #REF! | F84: Operating | G84: 0 | H84: 0 | I84: 0 | J84: 0 | K84: 0 | L84: 2412.5
A85: =A84+1 -> 81 | B85: 403 | C85: Public Safety GO Bond Fund | D85: FR | E85: Portland Fire & Rescue | F85: Capital | G85: 0 | H85: 0 | I85: 0 | J85: 0 | K85: 0 | L85: 431677.92
A86: =A85+1 -> 82 | B86: 604 | C86: Portland International Raceway Fund | D86: PK | E86: Portland Parks & Recreation | F86: Capital | G86: 0 | H86: 0 | I86: 0 | J86: 0 | K86: 0 | L86: 15885.05
A87: =A86+1 -> 83 | B87: 608 | C87: Environmental Remediation Fund | D87: ES | E87: Bureau of Environmental Services | F87: Capital | G87: 0 | H87: 0 | I87: 0 | J87: 0 | K87: 0 | L87: 60567
A88: =A87+1 -> 84 | B88: 308 | C88: Gas Tax Bond Redemption Fund | D88: TR | E88: Portland Bureau of Transportation | F88: Operating | G88: 0 | H88: 0 | I88: 0 | J88: 0 | K88: 0 | L88: 0
A89: =A88+1 -> 85 | B89: 309 | C89: Lents Town Ctr URA Debt Redemption Fund | D89: MF | E89: Office of Management and Finance | F89: Operating | G89: 0 | H89: 0 | I89: 0 | J89: 0 | K89: 0 | L89: 0
A90: =A89+1 -> 86 | B90: 310 | C90: Central Eastside Ind District Debt Service Fund | D90: MF | E90: Office of Management and Finance | F90: Operating | G90: 0 | H90: 0 | I90: 0 | J90: 0 | K90: 0 | L90: 0
A91: =A90+1 -> 87 | B91: 311 | C91: Bancroft Bond Interest and Sinking Fund | D91: AU | E91: Office of the City Auditor | F91: Operating | G91: 0 | H91: 0 | I91: 0 | J91: 0 | K91: 0 | L91: 0
A92: =A91+1 -> 88 | B92: 312 | C92: Convention Center Area Debt Service Fund | D92: MF | E92: Office of Management and Finance | F92: Operating | G92: 0 | H92: 0 | I92: 0 | J92: 0 | K92: 0 | L92: 0
A93: =A92+1 -> 89 | B93: 313 | C93: North Macadam URA Debt Redemption Fund | D93: MF | E93: Office of Management and Finance | F93: Operating | G93: 0 | H93: 0 | I93: 0 | J93: 0 | K93: 0 | L93: 0
A94: =A93+1 -> 90 | B94: 314 | C94: Special Projects Debt Service Fund | D94: MF | E94: Office of Management and Finance | F94: Operating | G94: 0 | H94: 0 | I94: 0 | J94: 0 | K94: 0 | L94: 0
A95: =A94+1 -> 91 | B95: 315 | C95: Gateway URA Debt Redemption Fund | D95: MF | E95: Office of Management and Finance | F95: Operating | G95: 0 | H95: 0 | I95: 0 | J95: 0 | K95: 0 | L95: 0
A96: =A95+1 -> 92 | B96: 316 | C96: Willamette Industrial URA Debt Service Fund | D96: MF | E96: Office of Management and Finance | F96: Operating | G96: 0 | H96: 0 | I96: 0 | J96: 0 | K96: 0 | L96: 0
... A140: =A139+1 -> 136 | B140: 802 | C140: Fire & Police Supplemental Retirement Res Fund | D140: MF | E140: Office of Management and Finance | F140: Operating | G140: 0 | H140: 0 | I140: 0 | J140: 0 | K140: 0 | L140: 8108.94
A141: =A140+1 -> 137
L142: =SUM(L5:L140) -> 1.4281886e+09
A153: TABLE4
A154: 1 | E154: MFOP000010 (Maintenance and Repair) | I154: 0 | L154: =SUM(G154:K154) -> 0
A155: =A154+1 -> 2 | E155: MFOP000042 (facilities) | G155: 178000.5 | H155: 2585852.4 | I155: 0 | L155: =SUM(G155:K155) -> 2763852.9
A156: =A155+1 -> 3 | E156: MFOP000045 (Portland Building) | I156: 0 | L156: =SUM(G156:K156) -> 0
A157: =A156+1 -> 4 | E157: MFOP000061 (Union Station) | G157: 50429.5 | H157: 1655748.8 | I157: 0 | L157: =SUM(G157:K157) -> 1706178.3
A158: =A157+1 -> 5 | E158: MFTS000028 (BTS) | H158: 110679.3 | I158: 0 | L158: =SUM(G158:K158) -> 110679.3
A161: TABLE5
A162: 1 | D162: MFDR000001 | G162: 386521.09 | H162: 20950.17 | L162: =SUM(G162:K162) -> 407471.26
A163: =A162+1 -> 2 | D163: MFFS | G163: 6033127.3 | H163: 493623.2 | L163: =SUM(G163:K163) -> 6526750.5
A164: =A163+1 -> 3 | D164: MFHR | G164: 6529706.7 | H164: 573448.96 | L164: =SUM(G164:K164) -> 7103155.6
A165: =A164+1 -> 4 | D165: MFOP000001 | G165: 2881193 | H165: 130458.9 | L165: =SUM(G165:K165) -> 3011651.9
A166: 5 | D166: MFRB | G166: 6207502.1 | H166: 1190852.1 | L166: =SUM(G166:K166) -> 7398354.2
A167: 6 | D167: MFCP | G167: 830179.23 | H167: 221397.67 | L167: =SUM(G167:K167) -> 1051576.9
A168: 7 | D168: MFIB | G168: 3981714.4 | H168: 476334.27 | L168: =SUM(G168:K168) -> 4458048.7
A169: =A168+1 -> 8 | D169: MFOP000001..3 | G169: 3738927.8 | H169: 471337.97 | L169: =SUM(G169:K169) -> 4210265.8
A278: 0
A279: 1 | B279: 100 | C279: General Fund | D279: AT | E279: Office of City Attorney | F279: Operating | G279: 7318606.2 | H279: 386043.04 | I279: 0 | J279: 0 | K279: 0 | L279: =SUM(G279:K279) -> 7704649.2
A280: =A279+1 -> 2 | B280: 100 | C280: General Fund | D280: AU | E280: Office of the City Auditor | F280: Operating | G280: 4733285.3 | H280: 1120468.7 | I280: 0 | J280: 0 | K280: 0 | L280: =SUM(G280:K280) -> 5853754
A281: =A280+1 -> 3 | B281: 100 | C281: General Fund | D281: CB | E281: Cable Communications and Franchise Management | F281: Operating | G281: 567935.65 | H281: 301037.35 | I281: 0 | J281: 0 | K281: 0 | L281: =SUM(G281:K281) -> 868973
A282: =A281+1 -> 4 | B282: 100 | C282: General Fund | D282: EM | E282: Portland Office of Emergency Management | F282: Operating | G282: 1111465.8 | H282: 80517.85 | I282: 0 | J282: 0 | K282: 0 | L282: =SUM(G282:K282) -> 1191983.6
A283: =A282+1 -> 5 | B283: 100 | C283: General Fund | D283: FR | E283: Portland Fire and Rescue | F283: Capital | G283: 41992.93 | H283: 15000 | I283: 0 | J283: 1169052.6 | K283: 0 | L283: =SUM(G283:K283) -> 1226045.5
A284: =A283+1 -> 6 | B284: 100 | C284: General Fund | D284: FR | E284: Portland Fire and Rescue | F284: Operating | G284: 78676734 | H284: 4993578 | I284: 0 | J284: 330435.85 | K284: 0 | L284: =SUM(G284:K284) -> 84000748
A285: =A284+1 -> 7 | B285: 100 | C285: General Fund | D285: GR | E285: Office of Government Relations | F285: Operating | G285: 733225.74 | H285: 275449.9 | I285: 0 | J285: 0 | K285: 0 | L285: =SUM(G285:K285) -> 1008675.6
A286: =A285+1 -> 8 | B286: 100 | C286: General Fund | D286: HC | E286: Portland Housing Bureau | F286: Operating | G286: 412223.02 | H286: 9691609.5 | I286: 0 | J286: 0 | K286: 0 | L286: =SUM(G286:K286) -> 10103832
A287: =A286+1 -> 9 | B287: 100 | C287: General Fund | D287: HN | E287: Office of Human Relations | F287: Operating | G287: 420431.86 | H287: 64870.95 | I287: 0 | J287: 0 | K287: 0 | L287: =SUM(G287:K287) -> 485302.81
A288: =A287+1 -> 10 | B288: 100 | C288: General Fund | D288: MF | E288: Office of Management and Finance | F288: Operating | G288: 24830554 | H288: 10083617 | I288: 0 | J288: 0 | K288: 0 | L288: =SUM(G288:K288) -> 34914171
A289: =A288+1 -> 11 | B289: 100 | C289: General Fund | D289: MF | E289: Office of Management and Finance | F289: Capital | G289: 189143.31 | H289: 19602.8 | I289: 0 | J289: 0 | K289: 0 | L289: =SUM(G289:K289) -> 208746.11
A290: =A289+1 -> 12 | B290: 100 | C290: General Fund | D290: MY | E290: Office of the Mayor | F290: Operating | G290: 2190710.9 | H290: 445622.06 | I290: 0 | J290: 0 | K290: 0 | L290: =SUM(G290:K290) -> 2636332.9
A291: =A290+1 -> 13 | B291: 100 | C291: General Fund | D291: NI | E291: Office of Neighborhood Involvement | F291: Operating | G291: 3185301.5 | H291: 2693800.5 | I291: 0 | J291: 0 | K291: 0 | L291: =SUM(G291:K291) -> 5879101.9
... A414: =A413+1 -> 136 | B414: 802 | C414: Fire & Police Supplemental Retirement Res Fund | D414: MF | E414: Office of Management and Finance | F414: Operating | G414: 0 | H414: 8160.1 | I414: 0 | J414: 0 | K414: 0 | L414: =SUM(G414:K414) -> 8160.1
A415: =A414+1 -> 137
G416: =SUM(G279:G414) -> 5.5199514e+08 | H416: =SUM(H279:H414) -> 5.7938179e+08 | I416: =SUM(I279:I414) -> 0 | J416: =SUM(J279:J414) -> 3.0833783e+08 | K416: =SUM(K279:K414) -> 0
G418: =SUM(G416:K416) -> 1.4397148e+09
A423: TABLE4
A424: 1 | E424: MFOP000010 (Maintenance and Repair) | G424: 39209.1 | H424: 14496.64 | I424: 0 | L424: =SUM(G424:K424) -> 53705.74
A425: =A424+1 -> 2 | E425: MFOP000042 (facilities) | G425: 151177.71 | H425: 2734288.8 | I425: 0 | L425: =SUM(G425:K425) -> 2885466.5
A426: =A425+1 -> 3 | E426: MFOP000045 (Portland Building) | H426: 175000 | I426: 0 | J426: 294250 | L426: =SUM(G426:K426) -> 469250
A427: =A426+1 -> 4 | E427: MFOP000061 (Union Station) | G427: -3907.63 | I427: 0 | L427: =SUM(G427:K427) -> -3907.63
A428: =A427+1 -> 5 | E428: MFTS000028 (BTS) | H428: 8800 | I428: 0 | L428: =SUM(G428:K428) -> 8800
A431: TABLE5
A432: 1 | D432: MFDR | G432: 313194.68 | H432: 4861.45 | L432: =SUM(G432:K432) -> 318056.13
A433: =A432+1 -> 2 | D433: MFFS | G433: 5573123.9 | H433: 610453.69 | L433: =SUM(G433:K433) -> 6183577.6
A434: =A433+1 -> 3 | D434: MFHR | G434: 6027343.5 | H434: 444684.54 | L434: =SUM(G434:K434) -> 6472028
A435: =A434+1 -> 4 | D435: MFOP | G435: 2773048 | H435: 4714.47 | L435: =SUM(G435:K435) -> 2777762.4
A436: 5 | D436: MFRB | G436: 5732252.6 | H436: 1308842.1 | L436: =SUM(G436:K436) -> 7041094.7

Sheet ALLOCATION
A1: 12/13 | B1: =$A$1&+" CENTRAL SERVICES ALLOCATIONS" -> 12/13 CENTRAL SERVICES ALLOCATIONS
A4: SAP
A5: FUND NO. | C5: OPERATING BUREAUS/FUNDS
F8: NUMBER OF EMPLOYEES | L8: ADJUSTED BUDGET SIZE
D9: FY 09/10 | E9: FY 10/11 | F9: FY 2012 No. | G9: FY 11/12 | H9: THREE YEAR | J9: FY 09/10 | K9: FY 10/11 | L9: FY 2012 Adj | N9: THREE YEAR | P9: BLENDED
D10: % | E10: % | F10: of Employees | G10: % | H10: AVERAGE | I10: 0.25 | J10: % | K10: % | L10: Actual Expend. | N10: AVERAGE | O10: 0.75 | P10: FACTOR
A12: 100000 | B12: PL | C12: Portland Police Bureau | D12: 0.1950994 | E12: 0.18715826 | F12: 1207 | G12: =F12/$F$127 -> 0.19287312 | H12: =AVERAGE(G12,E12,D12) -> 0.19171026 | I12: =H12*$I$10 -> 0.047927565 | J12: 157297509 | K12: 1.2957383e+08 | L12: =BUDGETSIZE!U7 -> 1.4420687e+08 | M12: =((J12/$J$127)+(K12/$K$127)+(L12/$L$127))/3 -> 0.13342631 | N12: =M12/$M$127 -> 0.13342631 | O12: =$O$10*N12 -> 0.10006973 | P12: =(O12+I12) -> 0.1479973
A13: 214000 | C13: Campaign Finance | D13: 0 | E13: 0 | F13: 0 | G13: =F13/$F$127 -> 0 | H13: =AVERAGE(G13,E13,D13) -> 0 | I13: =H13*$I$10 -> 0 | J13: 0 | K13: 0 | L13: =BUDGETSIZE!U8 -> 0 | M13: =((J13/$J$127)+(K13/$K$127)+(L13/$L$127))/3 -> 0 | N13: =M13/$M$127 -> 0 | O13: =$O$10*N13 -> 0 | P13: =(O13+I13) -> 0
A14: 100000 | B14: FR | C14: Portland Fire & Rescue | D14: 0.11126522 | E14: 0.11951258 | F14: 750 | G14: =F14/$F$127 -> 0.1198466 | H14: =AVERAGE(G14,E14,D14) -> 0.1168748 | I14: =H14*$I$10 -> 0.029218699 | J14: 92615296 | K14: 85346907 | L14: =BUDGETSIZE!U9 -> 91478782 | M14: =((J14/$J$127)+(K14/$K$127)+(L14/$L$127))/3 -> 0.084031754 | N14: =M14/$M$127 -> 0.084031754 | O14: =$O$10*N14 -> 0.063023816 | P14: =(O14+I14) -> 0.092242515
A15: 100000 | B15: PK | C15: Portland Parks & Recreation | D15: 0.17013407 | E15: 0.16872364 | F15: 974 | G15: =F15/$F$127 -> 0.15564078 | H15: =AVERAGE(G15,E15,D15) -> 0.16483283 | I15: =H15*$I$10 -> 0.041208207 | J15: 60130076 | K15: 51967979 | L15: =BUDGETSIZE!U10 -> 55232036 | M15: =((J15/$J$127)+(K15/$K$127)+(L15/$L$127))/3 -> 0.051883339 | N15: =M15/$M$127 -> 0.051883339 | O15: =$O$10*N15 -> 0.038912505 | P15: =(O15+I15) -> 0.080120712
A16: 600000 | C16: Sewer System Op | D16: 0.073971336 | E16: 0.08467427 | F16: 534 | G16: =F16/$F$127 -> 0.085330777 | H16: =AVERAGE(G16,E16,D16) -> 0.081325461 | I16: =H16*$I$10 -> 0.020331365 | J16: 99640069 | K16: 1.6330032e+08 | L16: =BUDGETSIZE!U11 -> 1.0410587e+08 | M16: =((J16/$J$127)+(K16/$K$127)+(L16/$L$127))/3 -> 0.11710471 | N16: =M16/$M$127 -> 0.11710471 | O16: =$O$10*N16 -> 0.08782853 | P16: =(O16+I16) -> 0.1081599
A17: 608000 | C17: Envtl Remediation | D17: 0.0083217753 | E17: 0.00093735354 | F17: 3 | G17: =F17/$F$127 -> 0.00047938639 | H17: =AVERAGE(G17,E17,D17) -> 0.0032461717 | I17: =H17*$I$10 -> 0.00081154294 | J17: 5556186 | K17: 2744587.6 | L17: =BUDGETSIZE!U12 -> 3334817.2 | M17: =((J17/$J$127)+(K17/$K$127)+(L17/$L$127))/3 -> 0.0034524874 | N17: =M17/$M$127 -> 0.0034524874 | O17: =$O$10*N17 -> 0.0025893655 | P17: =(O17+I17) -> 0.0034009085
A18: 605000 | C18: Solid Waste Mgt | D18: 0.0033903529 | E18: 0.0042180909 | F18: 32 | G18: =F18/$F$127 -> 0.0051134548 | H18: =AVERAGE(G18,E18,D18) -> 0.0042406329 | I18: =H18*$I$10 -> 0.0010601582 | J18: 5397170 | K18: 3106227.1 | L18: =BUDGETSIZE!U13 -> 3494849.2 | M18: =((J18/$J$127)+(K18/$K$127)+(L18/$L$127))/3 -> 0.0035968227 | N18: =M18/$M$127 -> 0.0035968227 | O18: =$O$10*N18 -> 0.002697617 | P18: =(O18+I18) -> 0.0037577752
A19: 200000 | C19: Transportation Op | D19: 0.11126522 | E19: 0.11248242 | F19: 718 | G19: =F19/$F$127 -> 0.11473314 | H19: =AVERAGE(G19,E19,D19) -> 0.11282693 | I19: =H19*$I$10 -> 0.028206732 | J19: 180216986 | K19: 1.4721976e+08 | L19: =BUDGETSIZE!U14 -> 1.2247356e+08 | M19: =((J19/$J$127)+(K19/$K$127)+(L19/$L$127))/3 -> 0.1371764 | N19: =M19/$M$127 -> 0.1371764 | O19: =$O$10*N19 -> 0.1028823 | P19: =(O19+I19) -> 0.13108903
A20: 212000 | C20: Transportation Resv | D20: 0 | E20: 0 | F20: 0 | G20: =F20/$F$127 -> 0 | H20: =AVERAGE(G20,E20,D20) -> 0 | I20: =H20*$I$10 -> 0 | J20: 0 | K20: 0 | L20: =BUDGETSIZE!U15 -> 0 | M20: =((J20/$J$127)+(K20/$K$127)+(L20/$L$127))/3 -> 0 | N20: =M20/$M$127 -> 0 | O20: =$O$10*N20 -> 0 | P20: =(O20+I20) -> 0
A21: 614000 | C21: Sewer System Constr | D21: 0 | E21: 0 | F21: 0 | G21: =F21/$F$127 -> 0 | H21: =AVERAGE(G21,E21,D21) -> 0 | I21: =H21*$I$10 -> 0 | J21: 111275102 | K21: 0 | L21: =BUDGETSIZE!U16 -> 0 | M21: =((J21/$J$127)+(K21/$K$127)+(L21/$L$127))/3 -> 0.026323674 | N21: =M21/$M$127 -> 0.026323674 | O21: =$O$10*N21 -> 0.019742755 | P21: =(O21+I21) -> 0.019742755
A22: 609000 | C22: Sewer Sys Debt Rdmpt | D22: 0 | E22: 0 | F22: 0 | G22: =F22/$F$127 -> 0 | H22: =AVERAGE(G22,E22,D22) -> 0 | I22: =H22*$I$10 -> 0 | J22: 75647150 | K22: 0 | L22: =BUDGETSIZE!U17 -> 0 | M22: =((J22/$J$127)+(K22/$K$127)+(L22/$L$127))/3 -> 0.017895386 | N22: =M22/$M$127 -> 0.017895386 | O22: =$O$10*N22 -> 0.01342154 | P22: =(O22+I22) -> 0.01342154
A23: 602000 | C23: Water | D23: 0.097549699 | E23: 0.09670364 | F23: 595 | G23: =F23/$F$127 -> 0.0950783 | H23: =AVERAGE(G23,E23,D23) -> 0.09644388 | I23: =H23*$I$10 -> 0.02411097 | J23: 76779020 | K23: 79748481 | L23: =BUDGETSIZE!U18 -> 86834290 | M23: =((J23/$J$127)+(K23/$K$127)+(L23/$L$127))/3 -> 0.076694795 | N23: =M23/$M$127 -> 0.076694795 | O23: =$O$10*N23 -> 0.057521096 | P23: =(O23+I23) -> 0.081632066
A24: 615000 | C24: Water Construction | D24: 0 | E24: 0 | F24: 0 | G24: =F24/$F$127 -> 0 | H24: =AVERAGE(G24,E24,D24) -> 0 | I24: =H24*$I$10 -> 0 | J24: 36338000 | K24: 0 | L24: =BUDGETSIZE!U19 -> 0 | M24: =((J24/$J$127)+(K24/$K$127)+(L24/$L$127))/3 -> 0.0085962596 | N24: =M24/$M$127 -> 0.0085962596 | O24: =$O$10*N24 -> 0.0064471947 | P24: =(O24+I24) -> 0.0064471947
A25: 612000 | C25: Water Bond Sinking | D25: 0 | E25: 0 | F25: 0 | G25: =F25/$F$127 -> 0 | H25: =AVERAGE(G25,E25,D25) -> 0 | I25: =H25*$I$10 -> 0 | J25: 14153186 | K25: 0 | L25: =BUDGETSIZE!U20 -> 0 | M25: =((J25/$J$127)+(K25/$K$127)+(L25/$L$127))/3 -> 0.0033481331 | N25: =M25/$M$127 -> 0.0033481331 | O25: =$O$10*N25 -> 0.0025110998 | P25: =(O25+I25) -> 0.0025110998
A26: 607000 | C26: Spectator Fac Op | D26: 0 | E26: 0 | F26: 0 | G26: =F26/$F$127 -> 0 | H26: =AVERAGE(G26,E26,D26) -> 0 | I26: =H26*$I$10 -> 0 | J26: 10184872 | K26: 6818850.4 | L26: =BUDGETSIZE!U21 -> 1425933 | M26: =((J26/$J$127)+(K26/$K$127)+(L26/$L$127))/3 -> 0.0052717913 | N26: =M26/$M$127 -> 0.0052717913 | O26: =$O$10*N26 -> 0.0039538435 | P26: =(O26+I26) -> 0.0039538435
A27: 617000 | C27: Sewer Sys Rate Stblt | D27: 0 | E27: 0 | F27: 0 | G27: =F27/$F$127 -> 0 | H27: =AVERAGE(G27,E27,D27) -> 0 | I27: =H27*$I$10 -> 0 | J27: 0 | K27: 0 | L27: =BUDGETSIZE!U22 -> 0 | M27: =((J27/$J$127)+(K27/$K$127)+(L27/$L$127))/3 -> 0 | N27: =M27/$M$127 -> 0 | O27: =$O$10*N27 -> 0 | P27: =(O27+I27) -> 0
... A60: 100000 | C60: General Fund Transfers | D60: 0 | E60: 0 | F60: 0 | G60: =F60/$F$127 -> 0 | H60: =AVERAGE(G60,E60,D60) -> 0 | I60: =H60*$I$10 -> 0 | J60: 0 | K60: 0 | L60: =BUDGETSIZE!U55 -> 0 | M60: =((J60/$J$127)+(K60/$K$127)+(L60/$L$127))/3 -> 0 | N60: =M60/$M$127 -> 0 | O60: =$O$10*N60 -> 0 | P60: =(O60+I60) -> 0
A61: 100000 | B61: CB | C61: Community Technology | D61: 0.0013869626 | E61: 0.0014060303 | F61: 9 | G61: =F61/$F$127 -> 0.0014381592 | H61: =AVERAGE(G61,E61,D61) -> 0.001410384 | I61: =H61*$I$10 -> 0.000352596 | J61: 1816671 | K61: 868973 | L61: =BUDGETSIZE!U56 -> 2173400.8 | M61: =((J61/$J$127)+(K61/$K$127)+(L61/$L$127))/3 -> 0.0015058108 | N61: =M61/$M$127 -> 0.0015058108 | O61: =$O$10*N61 -> 0.0011293581 | P61: =(O61+I61) -> 0.0014819541
A62: 100000 | C62: Office of Sustainable Development (OSD) | D62: 0.0075512406 | E62: 0 | F62: 0 | G62: =F62/$F$127 -> 0 | H62: =AVERAGE(G62,E62,D62) -> 0.0025170802 | I62: =H62*$I$10 -> 0.00062927005 | J62: 0 | K62: 0 | L62: =BUDGETSIZE!U57 -> 0 | M62: =((J62/$J$127)+(K62/$K$127)+(L62/$L$127))/3 -> 0 | N62: =M62/$M$127 -> 0 | O62: =$O$10*N62 -> 0 | P62: =(O62+I62) -> 0.00062927005
A63: 206000 | C63: Cable | D63: 0 | E63: 0 | F63: 0 | G63: =F63/$F$127 -> 0 | H63: =AVERAGE(G63,E63,D63) -> 0 | I63: =H63*$I$10 -> 0 | J63: 2563138 | K63: 2134040.6 | L63: =BUDGETSIZE!U58 -> 2657851.2 | M63: =((J63/$J$127)+(K63/$K$127)+(L63/$L$127))/3 -> 0.0022919809 | N63: =M63/$M$127 -> 0.0022919809 | O63: =$O$10*N63 -> 0.0017189857 | P63: =(O63+I63) -> 0.0017189857
A64: 100000 | B64: HN | C64: Office of Human Relations | D64: 0.0006164278 | E64: 0.00062490236 | F64: 3 | G64: =F64/$F$127 -> 0.00047938639 | H64: =AVERAGE(G64,E64,D64) -> 0.00057357218 | I64: =H64*$I$10 -> 0.00014339305 | J64: 589509 | K64: 485302.81 | L64: =BUDGETSIZE!U59 -> 230029.91 | M64: =((J64/$J$127)+(K64/$K$127)+(L64/$L$127))/3 -> 0.00038908336 | N64: =M64/$M$127 -> 0.00038908336 | O64: =$O$10*N64 -> 0.00029181252 | P64: =(O64+I64) -> 0.00043520557
A65: 100000 | C65: General Fund Revenues/Balance | D65: 0 | E65: 0 | F65: 0 | G65: =F65/$F$127 -> 0 | H65: =AVERAGE(G65,E65,D65) -> 0 | I65: =H65*$I$10 -> 0 | J65: 0 | K65: 0 | L65: =BUDGETSIZE!U60 -> 0 | M65: =((J65/$J$127)+(K65/$K$127)+(L65/$L$127))/3 -> 0 | N65: =M65/$M$127 -> 0 | O65: =$O$10*N65 -> 0 | P65: =(O65+I65) -> 0
A66: 100000 | C66: Business Licenses | D66: 0 | E66: 0 | F66: 0 | G66: =F66/$F$127 -> 0 | H66: =AVERAGE(G66,E66,D66) -> 0 | I66: =H66*$I$10 -> 0 | J66: 0 | K66: 0 | L66: =BUDGETSIZE!U61 -> 0 | M66: =((J66/$J$127)+(K66/$K$127)+(L66/$L$127))/3 -> 0 | N66: =M66/$M$127 -> 0 | O66: =$O$10*N66 -> 0 | P66: =(O66+I66) -> 0
A67: 208000 | C67: Business Lic Surchg | D67: 0 | E67: 0 | F67: 0 | G67: =F67/$F$127 -> 0 | H67: =AVERAGE(G67,E67,D67) -> 0 | I67: =H67*$I$10 -> 0 | J67: 0 | K67: 0 | L67: =BUDGETSIZE!U62 -> 0 | M67: =((J67/$J$127)+(K67/$K$127)+(L67/$L$127))/3 -> 0 | N67: =M67/$M$127 -> 0 | O67: =$O$10*N67 -> 0 | P67: =(O67+I67) -> 0
A68: 207000 | C68: Prvt Hire TR Safety | D68: 0 | E68: 0 | F68: 0 | G68: =F68/$F$127 -> 0 | H68: =AVERAGE(G68,E68,D68) -> 0 | I68: =H68*$I$10 -> 0 | J68: 15000 | K68: 0 | L68: =BUDGETSIZE!U63 -> 0 | M68: =((J68/$J$127)+(K68/$K$127)+(L68/$L$127))/3 -> 3.5484588e-06 | N68: =M68/$M$127 -> 3.5484588e-06 | O68: =$O$10*N68 -> 2.6613441e-06 | P68: =(O68+I68) -> 2.6613441e-06
A69: 100000 | B69: NI | C69: Office of Neighborhood Involvement | D69: 0.0070889197 | E69: 0.0073426027 | F69: 46 | G69: =F69/$F$127 -> 0.0073505912 | H69: =AVERAGE(G69,E69,D69) -> 0.0072607046 | I69: =H69*$I$10 -> 0.0018151761 | J69: 6439822 | K69: 5925598.8 | L69: =BUDGETSIZE!U64 -> 6203280.8 | M69: =((J69/$J$127)+(K69/$K$127)+(L69/$L$127))/3 -> 0.0057836827 | N69: =M69/$M$127 -> 0.0057836827 | O69: =$O$10*N69 -> 0.004337762 | P69: =(O69+I69) -> 0.0061529381
A70: 100000 | C70: General Services | D70: 0 | E70: 0 | F70: 0 | G70: =F70/$F$127 -> 0 | H70: =AVERAGE(G70,E70,D70) -> 0 | I70: =H70*$I$10 -> 0 | J70: 200320 | K70: 193750 | L70: =BUDGETSIZE!U65 -> 247782.87 | M70: =((J70/$J$127)+(K70/$K$127)+(L70/$L$127))/3 -> 0.00020274036 | N70: =M70/$M$127 -> 0.00020274036 | O70: =$O$10*N70 -> 0.00015205527 | P70: =(O70+I70) -> 0.00015205527
A71: 100000 | C71: Utility Billing Sys Implent | D71: 0 | E71: 0 | F71: 0 | G71: =F71/$F$127 -> 0 | H71: =AVERAGE(G71,E71,D71) -> 0 | I71: =H71*$I$10 -> 0 | J71: 1576023 | K71: 973016 | L71: =BUDGETSIZE!U66 -> 1051576.9 | M71: =((J71/$J$127)+(K71/$K$127)+(L71/$L$127))/3 -> 0.0010841594 | N71: =M71/$M$127 -> 0.0010841594 | O71: =$O$10*N71 -> 0.00081311955 | P71: =(O71+I71) -> 0.00081311955
A72: 703000 | C72: P&D Srvcs Operating | D72: 0.0041608877 | E72: 0.0037494142 | F72: 24 | G72: =F72/$F$127 -> 0.0038350911 | H72: =AVERAGE(G72,E72,D72) -> 0.003915131 | I72: =H72*$I$10 -> 0.00097878274 | J72: 6668958 | K72: 5599834.3 | L72: =BUDGETSIZE!U67 -> 5514266.5 | M72: =((J72/$J$127)+(K72/$K$127)+(L72/$L$127))/3 -> 0.0054794044 | N72: =M72/$M$127 -> 0.0054794044 | O72: =$O$10*N72 -> 0.0041095533 | P72: =(O72+I72) -> 0.0050883361
A73: 100000 | B73: OE | C73: ='BUDGET DETAIL'!E82 -> Office of Equity & Human Rights | D73: 0 | E73: 0 | F73: 0 | G73: =F73/$F$127 -> 0 | H73: =AVERAGE(G73,E73,D73) -> 0 | I73: =H73*$I$10 -> 0 | J73: 0 | K73: 0 | L73: =BUDGETSIZE!U68 -> 375051.66 | M73: =((J73/$J$127)+(K73/$K$127)+(L73/$L$127))/3 -> 0.00013393922 | N73: =M73/$M$127 -> 0.00013393922 | O73: =$O$10*N73 -> 0.00010045441 | P73: =(O73+I73) -> 0.00010045441
A74: 100000 | C74: Revenue Bureau | D74: 0.010325166 | E74: 0.010154663 | F74: 67 | G74: =F74/$F$127 -> 0.010706296 | H74: =AVERAGE(G74,E74,D74) -> 0.010395375 | I74: =H74*$I$10 -> 0.0025988437 | J74: 9942050 | K74: 7041094.7 | L74: =BUDGETSIZE!U69 -> 7398354.2 | M74: =((J74/$J$127)+(K74/$K$127)+(L74/$L$127))/3 -> 0.0074239283 | N74: =M74/$M$127 -> 0.0074239283 | O74: =$O$10*N74 -> 0.0055679462 | P74: =(O74+I74) -> 0.0081667899
A75: 100000 | C75: Special Appropriations | D75: 0 | E75: 0 | F75: 0 | G75: =F75/$F$127 -> 0 | H75: =AVERAGE(G75,E75,D75) -> 0 | I75: =H75*$I$10 -> 0 | J75: 11168785 | K75: 6476768.1 | L75: =BUDGETSIZE!U70 -> 6476768.1 | M75: =((J75/$J$127)+(K75/$K$127)+(L75/$L$127))/3 -> 0.0071902616 | N75: =M75/$M$127 -> 0.0071902616 | O75: =$O$10*N75 -> 0.0053926962 | P75: =(O75+I75) -> 0.0053926962
A76: 220000 | C76: Portland Park Mem Tr | D76: 0 | E76: 0 | F76: 0 | G76: =F76/$F$127 -> 0 | H76: =AVERAGE(G76,E76,D76) -> 0 | I76: =H76*$I$10 -> 0 | J76: 53252 | K76: 0 | L76: =BUDGETSIZE!U71 -> 0 | M76: =((J76/$J$127)+(K76/$K$127)+(L76/$L$127))/3 -> 1.2597502e-05 | N76: =M76/$M$127 -> 1.2597502e-05 | O76: =$O$10*N76 -> 9.4481263e-06 | P76: =(O76+I76) -> 9.4481263e-06
A77: 500000 | C77: Parks Endowment | D77: 0 | E77: 0 | F77: 0 | G77: =F77/$F$127 -> 0 | H77: =AVERAGE(G77,E77,D77) -> 0 | I77: =H77*$I$10 -> 0 | J77: 0 | K77: 225 | L77: =BUDGETSIZE!U72 -> 0 | M77: =((J77/$J$127)+(K77/$K$127)+(L77/$L$127))/3 -> 7.7647524e-08 | N77: =M77/$M$127 -> 7.7647524e-08 | O77: =$O$10*N77 -> 5.8235643e-08 | P77: =(O77+I77) -> 5.8235643e-08
A78: 616000 | C78: Wtr Grwth Imp Chg Tr | D78: 0 | E78: 0 | F78: 0 | G78: =F78/$F$127 -> 0 | H78: =AVERAGE(G78,E78,D78) -> 0 | I78: =H78*$I$10 -> 0 | J78: 0 | K78: 0 | L78: =BUDGETSIZE!U73 -> 0 | M78: =((J78/$J$127)+(K78/$K$127)+(L78/$L$127))/3 -> 0 | N78: =M78/$M$127 -> 0 | O78: =$O$10*N78 -> 0 | P78: =(O78+I78) -> 0
A79: 700000 | C79: Health Insurance Op | D79: 0.0016951765 | E79: 0.0017184815 | F79: 11 | G79: =F79/$F$127 -> 0.0017577501 | H79: =AVERAGE(G79,E79,D79) -> 0.0017238027 | I79: =H79*$I$10 -> 0.00043095067 | J79: 2304009 | K79: 2365925.5 | L79: =BUDGETSIZE!U74 -> 1210522.4 | M79: =((J79/$J$127)+(K79/$K$127)+(L79/$L$127))/3 -> 0.0017938308 | N79: =M79/$M$127 -> 0.0017938308 | O79: =$O$10*N79 -> 0.0013453731 | P79: =(O79+I79) -> 0.0017763237
A80: 100000 | B80: PN | C80: Bureau of Planning & Sustainability | D80: 0.012944984 | E80: 0.014372754 | F80: 98 | G80: =F80/$F$127 -> 0.015659955 | H80: =AVERAGE(G80,E80,D80) -> 0.014325898 | I80: =H80*$I$10 -> 0.0035814744 | J80: 11099756 | K80: 13780055 | L80: =BUDGETSIZE!U75 -> 22875642 | M80: =((J80/$J$127)+(K80/$K$127)+(L80/$L$127))/3 -> 0.015550696 | N80: =M80/$M$127 -> 0.015550696 | O80: =$O$10*N80 -> 0.011663022 | P80: =(O80+I80) -> 0.015244497
A81: 203000 | C81: Development Services | D81: 0.025427647 | E81: 0.024214966 | F81: 174 | G81: =F81/$F$127 -> 0.02780441 | H81: =AVERAGE(G81,E81,D81) -> 0.025815675 | I81: =H81*$I$10 -> 0.0064539186 | J81: 28801272 | K81: 16214012 | L81: =BUDGETSIZE!U76 -> 19122972 | M81: =((J81/$J$127)+(K81/$K$127)+(L81/$L$127))/3 -> 0.019238034 | N81: =M81/$M$127 -> 0.019238034 | O81: =$O$10*N81 -> 0.014428525 | P81: =(O81+I81) -> 0.020882444
A82: 218000 | C82: CDBG Incoming (Ext) | D82: 0 | E82: 0 | F82: 0 | G82: =F82/$F$127 -> 0 | H82: =AVERAGE(G82,E82,D82) -> 0 | I82: =H82*$I$10 -> 0 | J82: 8242403 | K82: 5342360.8 | L82: =BUDGETSIZE!U77 -> 4394047.4 | M82: =((J82/$J$127)+(K82/$K$127)+(L82/$L$127))/3 -> 0.0053627156 | N82: =M82/$M$127 -> 0.0053627156 | O82: =$O$10*N82 -> 0.0040220367 | P82: =(O82+I82) -> 0.0040220367
A83: 219000 | C83: HOME Incoming (Ext) | D83: 0 | E83: 0 | F83: 0 | G83: =F83/$F$127 -> 0 | H83: =AVERAGE(G83,E83,D83) -> 0 | I83: =H83*$I$10 -> 0 | J83: 2498261 | K83: 2565098.6 | L83: =BUDGETSIZE!U78 -> 1972736.1 | M83: =((J83/$J$127)+(K83/$K$127)+(L83/$L$127))/3 -> 0.0021807218 | N83: =M83/$M$127 -> 0.0021807218 | O83: =$O$10*N83 -> 0.0016355413 | P83: =(O83+I83) -> 0.0016355413
A84: 100000 | B84: HC | C84: Portland Housing Bureau | D84: 0.0050855294 | E84: 0.0099984377 | F84: 54 | G84: =F84/$F$127 -> 0.0086289549 | H84: =AVERAGE(G84,E84,D84) -> 0.0079043073 | I84: =H84*$I$10 -> 0.0019760768 | J84: 9989120 | K84: 10103832 | L84: =BUDGETSIZE!U79 -> 11593972 | M84: =((J84/$J$127)+(K84/$K$127)+(L84/$L$127))/3 -> 0.0099903621 | N84: =M84/$M$127 -> 0.0099903621 | O84: =$O$10*N84 -> 0.0074927716 | P84: =(O84+I84) -> 0.0094688484
F85: 0 | J85: 875305 | K85: 729.12 | L85: =BUDGETSIZE!U80 -> 175 | M85: =((J85/$J$127)+(K85/$K$127)+(L85/$L$127))/3 -> 0.0002073797 | N85: =M85/$M$127 -> 0.0002073797 | O85: =$O$10*N85 -> 0.00015553477 | P85: =(O85+I85) -> 0.00015553477
A86: 706000 | C86: Technology Services | D86: 0.033749422 | E86: 0.032494923 | F86: 202 | G86: =F86/$F$127 -> 0.032278683 | H86: =AVERAGE(G86,E86,D86) -> 0.032841009 | I86: =H86*$I$10 -> 0.0082102523 | J86: 45641587 | K86: 34612873 | L86: =BUDGETSIZE!U81 -> 39080771 | M86: =((J86/$J$127)+(K86/$K$127)+(L86/$L$127))/3 -> 0.036698664 | N86: =M86/$M$127 -> 0.036698664 | O86: =$O$10*N86 -> 0.027523998 | P86: =(O86+I86) -> 0.03573425
A87: 702000 | C87: CityFleet Operating | D87: 0.011866235 | E87: 0.011560694 | F87: 74 | G87: =F87/$F$127 -> 0.011824864 | H87: =AVERAGE(G87,E87,D87) -> 0.011750598 | I87: =H87*$I$10 -> 0.0029376494 | J87: 23925207 | K87: 21641351 | L87: =BUDGETSIZE!U82 -> 24170631 | M87: =((J87/$J$127)+(K87/$K$127)+(L87/$L$127))/3 -> 0.021760139 | N87: =M87/$M$127 -> 0.021760139 | O87: =$O$10*N87 -> 0.016320104 | P87: =(O87+I87) -> 0.019257753
A88: 704000 | C88: Insurance & Claim Op | D88: 0.0023116043 | E88: 0.0021871583 | F88: 14 | G88: =F88/$F$127 -> 0.0022371365 | H88: =AVERAGE(G88,E88,D88) -> 0.0022452997 | I88: =H88*$I$10 -> 0.00056132491 | J88: 9534393 | K88: 5398647.2 | L88: =BUDGETSIZE!U83 -> 6440525.6 | M88: =((J88/$J$127)+(K88/$K$127)+(L88/$L$127))/3 -> 0.0064186208 | N88: =M88/$M$127 -> 0.0064186208 | O88: =$O$10*N88 -> 0.0048139656 | P88: =(O88+I88) -> 0.0053752905
A89: 705000 | C89: Wkr Comp Self Ins Op | D89: 0.00077053475 | E89: 0.0010935791 | F89: 7 | G89: =F89/$F$127 -> 0.0011185682 | H89: =AVERAGE(G89,E89,D89) -> 0.00099422737 | I89: =H89*$I$10 -> 0.00024855684 | J89: 4418094 | K89: 3686446.9 | L89: =BUDGETSIZE!U84 -> 3495172.9 | M89: =((J89/$J$127)+(K89/$K$127)+(L89/$L$127))/3 -> 0.0035655582 | N89: =M89/$M$127 -> 0.0035655582 | O89: =$O$10*N89 -> 0.0026741686 | P89: =(O89+I89) -> 0.0029227255
A90: 707000 | C90: PPA Health Insurance | D90: 0 | E90: 0 | F90: 0 | G90: =F90/$F$127 -> 0 | H90: =AVERAGE(G90,E90,D90) -> 0 | I90: =H90*$I$10 -> 0 | J90: 0 | K90: 0 | L90: =BUDGETSIZE!U85 -> 0 | M90: =((J90/$J$127)+(K90/$K$127)+(L90/$L$127))/3 -> 0 | N90: =M90/$M$127 -> 0 | O90: =$O$10*N90 -> 0 | P90: =(O90+I90) -> 0
A91: 612000 | C91: Water Bond Sinking | D91: 0 | E91: 0 | F91: 0 | G91: =F91/$F$127 -> 0 | H91: =AVERAGE(G91,E91,D91) -> 0 | I91: =H91*$I$10 -> 0 | J91: 0 | K91: 0 | L91: =BUDGETSIZE!U86 -> 0 | M91: =((J91/$J$127)+(K91/$K$127)+(L91/$L$127))/3 -> 0 | N91: =M91/$M$127 -> 0 | O91: =$O$10*N91 -> 0 | P91: =(O91+I91) -> 0
A92: 604000 | C92: Portland Int Raceway | D92: 0.0015410695 | E92: 0.00093735354 | F92: 6 | G92: =F92/$F$127 -> 0.00095877277 | H92: =AVERAGE(G92,E92,D92) -> 0.0011457319 | I92: =H92*$I$10 -> 0.00028643298 | J92: 1699679 | K92: 1295730.3 | L92: =BUDGETSIZE!U87 -> 1255312.1 | M92: =((J92/$J$127)+(K92/$K$127)+(L92/$L$127))/3 -> 0.001297539 | N92: =M92/$M$127 -> 0.001297539 | O92: =$O$10*N92 -> 0.00097315427 | P92: =(O92+I92) -> 0.0012595873
A93: 603000 | C93: Golf | D93: 0.0057019572 | E93: 0.0064052492 | F93: 37 | G93: =F93/$F$127 -> 0.0059124321 | H93: =AVERAGE(G93,E93,D93) -> 0.0060065461 | I93: =H93*$I$10 -> 0.0015016365 | J93: 6898605 | K93: 6082666.5 | L93: =BUDGETSIZE!U88 -> 6228442.1 | M93: =((J93/$J$127)+(K93/$K$127)+(L93/$L$127))/3 -> 0.0059554039 | N93: =M93/$M$127 -> 0.0059554039 | O93: =$O$10*N93 -> 0.0044665529 | P93: =(O93+I93) -> 0.0059681895
A94: 610000 | C94: Golf Rev Bond Rdmpt | D94: 0 | E94: 0 | F94: 0 | G94: =F94/$F$127 -> 0 | H94: =AVERAGE(G94,E94,D94) -> 0 | I94: =H94*$I$10 -> 0 | J94: 403640 | K94: 0 | L94: =BUDGETSIZE!U89 -> 0 | M94: =((J94/$J$127)+(K94/$K$127)+(L94/$L$127))/3 -> 9.5486659e-05 | N94: =M94/$M$127 -> 9.5486659e-05 | O94: =$O$10*N94 -> 7.1614995e-05 | P94: =(O94+I94) -> 7.1614995e-05
A95: 202000 | C95: Emergency Comm | D95: 0.022345508 | E95: 0.021559131 | F95: 132 | G95: =F95/$F$127 -> 0.021093001 | H95: =AVERAGE(G95,E95,D95) -> 0.02166588 | I95: =H95*$I$10 -> 0.00541647 | J95: 20040533 | K95: 18350353 | L95: =BUDGETSIZE!U90 -> 14232905 | M95: =((J95/$J$127)+(K95/$K$127)+(L95/$L$127))/3 -> 0.01615646 | N95: =M95/$M$127 -> 0.01615646 | O95: =$O$10*N95 -> 0.012117345 | P95: =(O95+I95) -> 0.017533815
A96: 601000 | C96: Hydroelectric Pwr Op | D96: 0.00046232085 | E96: 0 | F96: 0 | G96: =F96/$F$127 -> 0 | H96: =AVERAGE(G96,E96,D96) -> 0.00015410695 | I96: =H96*$I$10 -> 3.8526738e-05 | J96: 687311 | K96: 381836.61 | L96: =BUDGETSIZE!U91 -> 342322.09 | M96: =((J96/$J$127)+(K96/$K$127)+(L96/$L$127))/3 -> 0.0004166156 | N96: =M96/$M$127 -> 0.0004166156 | O96: =$O$10*N96 -> 0.0003124617 | P96: =(O96+I96) -> 0.00035098844
A97: 611000 | C97: Hydro Pwr Bond Rdmpt | D97: 0 | E97: 0 | F97: 0 | G97: =F97/$F$127 -> 0 | H97: =AVERAGE(G97,E97,D97) -> 0 | I97: =H97*$I$10 -> 0 | J97: 1358405 | K97: 0 | L97: =BUDGETSIZE!U92 -> 0 | M97: =((J97/$J$127)+(K97/$K$127)+(L97/$L$127))/3 -> 0.00032134961 | N97: =M97/$M$127 -> 0.00032134961 | O97: =$O$10*N97 -> 0.00024101221 | P97: =(O97+I97) -> 0.00024101221
... A111: 221000 | C111: Tax Increment Financing Reimbursment | D111: 0 | E111: 0 | F111: 0 | G111: =F111/$F$127 -> 0 | H111: =AVERAGE(G111,E111,D111) -> 0 | I111: =H111*$I$10 -> 0 | J111: 33993769 | K111: 17921491 | L111: =BUDGETSIZE!U106 -> 22536937 | M111: =((J111/$J$127)+(K111/$K$127)+(L111/$L$127))/3 -> 0.022274845 | N111: =M111/$M$127 -> 0.022274845 | O111: =$O$10*N111 -> 0.016706133 | P111: =(O111+I111) -> 0.016706133
A112: 100000 | B112: MFFM | C112: Fund Management | D112: 0 | E112: 0 | F112: 0 | G112: =F112/$F$127 -> 0 | H112: =AVERAGE(G112,E112,D112) -> 0 | I112: =H112*$I$10 -> 0 | J112: 2742562 | K112: 0 | L112: =BUDGETSIZE!U107 -> 0 | M112: =((J112/$J$127)+(K112/$K$127)+(L112/$L$127))/3 -> 0.00064879121 | N112: =M112/$M$127 -> 0.00064879121 | O112: =$O$10*N112 -> 0.00048659341 | P112: =(O112+I112) -> 0.00048659341
A119: 100000 | B119: GR, MY, PA, PS, PU, PW | C119: Council | D119: 0.010941593 | E119: 0.011404468 | F119: 75 | G119: =F119/$F$127 -> 0.01198466 | H119: =AVERAGE(G119,E119,D119) -> 0.011443574 | I119: =H119*$I$10 -> 0.0028608934 | J119: 9198637 | K119: 7161645 | L119: =BUDGETSIZE!U114 -> 8150723.8 | M119: =((J119/$J$127)+(K119/$K$127)+(L119/$L$127))/3 -> 0.0075583533 | N119: =M119/$M$127 -> 0.0075583533 | O119: =$O$10*N119 -> 0.0056687649 | P119: =(O119+I119) -> 0.0085296584
A120: 100000 | B120: EM | C120: Portland Office of Emergency Management | D120: 0.0024657112 | E120: 0.002655835 | F120: 18 | G120: =F120/$F$127 -> 0.0028763183 | H120: =AVERAGE(G120,E120,D120) -> 0.0026659548 | I120: =H120*$I$10 -> 0.00066648871 | J120: 10305359 | K120: 6120432.6 | L120: =BUDGETSIZE!U115 -> 8088010.4 | M120: =((J120/$J$127)+(K120/$K$127)+(L120/$L$127))/3 -> 0.0074384449 | N120: =M120/$M$127 -> 0.0074384449 | O120: =$O$10*N120 -> 0.0055788337 | P120: =(O120+I120) -> 0.0062453224
A121: 100000 | B121: MF | C121: Office of Management & Finance | D121: 0.030204962 | E121: 0.031088892 | F121: 193 | G121: =F121/$F$127 -> 0.030840524 | H121: =AVERAGE(G121,E121,D121) -> 0.03071146 | I121: =H121*$I$10 -> 0.0076778649 | J121: 20245606 | K121: 15751424 | L121: =BUDGETSIZE!U116 -> 17049029 | M121: =((J121/$J$127)+(K121/$K$127)+(L121/$L$127))/3 -> 0.016313782 | N121: =M121/$M$127 -> 0.016313782 | O121: =$O$10*N121 -> 0.012235337 | P121: =(O121+I121) -> 0.019913202
A122: 100000 | B122: AT | C122: Office of City Attorney | D122: 0.009400524 | E122: 0.0093735354 | F122: 63 | G122: =F122/$F$127 -> 0.010067114 | H122: =AVERAGE(G122,E122,D122) -> 0.0096137245 | I122: =H122*$I$10 -> 0.0024034311 | J122: 8586319 | K122: 7704649.2 | L122: =BUDGETSIZE!U117 -> 8387785.4 | M122: =((J122/$J$127)+(K122/$K$127)+(L122/$L$127))/3 -> 0.0076855516 | N122: =M122/$M$127 -> 0.0076855516 | O122: =$O$10*N122 -> 0.0057641637 | P122: =(O122+I122) -> 0.0081675948
A123: 100000 | C123: Purchasing | D123: 0 | E123: 0 | F123: 0 | G123: =F123/$F$127 -> 0 | H123: =AVERAGE(G123,E123,D123) -> 0 | I123: =H123*$I$10 -> 0 | J123: 4825133 | K123: 4620935 | L123: =BUDGETSIZE!U118 -> 4210265.8 | M123: =((J123/$J$127)+(K123/$K$127)+(L123/$L$127))/3 -> 0.0042397163 | N123: =M123/$M$127 -> 0.0042397163 | O123: =$O$10*N123 -> 0.0031797872 | P123: =(O123+I123) -> 0.0031797872
A124: 100000 | B124: AU | C124: Office of the City Auditor | D124: 0.0081676684 | E124: 0.0084361818 | F124: 55 | G124: =F124/$F$127 -> 0.0087887504 | H124: =AVERAGE(G124,E124,D124) -> 0.0084642002 | I124: =H124*$I$10 -> 0.0021160501 | J124: 9037735 | K124: 5853754 | L124: =BUDGETSIZE!U119 -> 6288735.9 | M124: =((J124/$J$127)+(K124/$K$127)+(L124/$L$127))/3 -> 0.0064039794 | N124: =M124/$M$127 -> 0.0064039794 | O124: =$O$10*N124 -> 0.0048029845 | P124: =(O124+I124) -> 0.0069190346
C127: TOTAL | D127: =SUM(D119:D124,D12:D112) -> 1 | E127: =SUM(E119:E124,E12:E112) -> 1 | F127: =SUM(F119:F124,F12:F112) -> 6258 | G127: =SUM(G119:G124,G12:G112) -> 1 | H127: =SUM(H119:H124,H12:H112) -> 1 | I127: =SUM(I119:I124,I12:I112) -> 0.25 | J127: =SUM(J119:J124,J12:J112) -> 1409062454 | K127: =SUM(K119:K124,K12:K112) -> 9.6590331e+08 | ... P127: =SUM(P119:P124,P12:P112) -> 1

Sheet ACTUAL EXP
A1: CITY OF PORTLAND
A2: FY 11/12 GENERAL FUND OVERHEAD "TRUE-UP"
A3: BASED ON ACTUAL EXPENDITURES
A4: USING FY 11/12 DATA
A5: 0.99
D6: BUREAU COST CATEGORIES
G8: ALLOCABLE
D9: TOTAL | E9: INTERNAL | F9: OUTSIDE | G9: OVERHEAD
B10: COST CENTERS | D10: EXPENSE | E10: REVENUE | F10: REVENUE | G10: COSTS
A12: ATTORNEY
B13: AT Office of City Attorney | D13: =5339928*A5 -> 5286528.7 | E13: 0 | F13: 0 | G13: =+D13-E13-F13 -> 5286528.7
A14: AUDITOR
B15: AUDA000001 Management | D15: =8612471*A5 -> 8526346.3 | E15: 0 | F15: 0 | G15: =+D15-E15-F15 -> 8526346.3
B16: AUCA000002 Ind Police Review | D16: 0 | E16: 0 | F16: 0 | G16: =+D16-E16-F16 -> 0
B17: AUDA000002 Council/Contracts | D17: 0 | E17: 0 | F17: 0 | G17: =+D17-E17-F17 -> 0
B18: AUDA000004 Assmts/Fin/Foreclose | D18: 0 | E18: 0 | F18: 0 | G18: =+D18-E18-F18 -> 0
B19: AUCA000003 Progress Board | D19: 0 | E19: 0 | F19: 0 | G19: =+D19-E19-F19 -> 0
B20: AUCA000005 Hearings Officer | D20: 0 | E20: 0 | F20: 0 | G20: =+D20-E20-F20 -> 0
B21: Public involvement best practices | D21: =95752.74*1.027 -> 98338.064 | E21: 0 | F21: 0 | G21: =+D21-E21-F21 -> 98338.064
B22: AUCA000004 Ombudsman Office | D22: 0 | E22: 0 | F22: 0 | G22: =+D22-E22-F22 -> 0
B23: AUCA000006 City Auditor | D23: 0 | E23: 0 | F23: 0 | G23: =+D23-E23-F23 -> 0
A24: AUDIT SERVICES
B25: LAAUAU00000000GL | D25: 0 | E25: 0 | F25: 0 | G25: =+D25-E25-F25 -> 0
B26: LAAUAUPD000000GL | D26: 0 | E26: 0 | F26: 0 | G26: =+D26-E26-F26 -> 0
B27: RECORDS MANAGERMENT | D27: 0 | E27: 0 | F27: 0 | G27: =+D27-E27-F27 -> 0
B28: AUDA000003 Archives & Records | D28: 0 | E28: 0 | F28: 0 | G28: =+D28-E28-F28 -> 0
A29: CITY COUNCIL
B30: PW Commissioner of Public Works | D30: =865896*A5 -> 857237.04 | E30: 0 | F30: 0 | G30: =+D30-E30-F30 -> 857237.04
B31: PS Commissioner of Public Safety | D31: =819242*A5 -> 811049.58 | E31: 0 | F31: 0 | G31: =+D31-E31-F31 -> 811049.58
B32: PA Commissioner of Public Affairs | D32: =1641395*0.666*A5 -> 1082237.4 | E32: 0 | F32: =420.93-420.93 -> 0 | G32: =+D32-E32-F32 -> 1082237.4
B33: PU Commissioner of Public Utilities | D33: =837912*A5 -> 829532.88 | E33: 0 | F33: 0 | G33: =+D33-E33-F33 -> 829532.88
B34: MY Office of the Mayor | D34: =2874982*A5 -> 2846232.2 | E34: 0 | F34: 0 | G34: =+D34-E34-F34 -> 2846232.2
B35: GR Office of Governmental Relations | D35: =1238725*A5 -> 1226337.8 | E35: 0 | F35: 0 | G35: =+D35-E35-F35 -> 1226337.8
A36: PLANNING
B37: Comprehensive Planning | D37: =150820.53*1.027 -> 154892.68 | E37: 0 | F37: 0 | G37: =+D37-E37-F37 -> 154892.68
B38: Governmental Coordination | D38: =115820.48*1.027 -> 118947.63 | E38: 0 | F38: 0 | G38: =+D38-E38-F38 -> 118947.63
B39: District Planning CAPD10000 | D39: =(1276723*1.027)/2 -> 655597.26 | E39: 0 | F39: 0 | G39: =+D39-E39-F39 -> 655597.26
A40: ONI
B41: NIIR Information & Referral | D41: =519862.03*1.027 -> 533898.3 | E41: 0 | F41: =249095*1.027 -> 255820.56 | G41: =+D41-E41-F41 -> 278077.74
A42: PURCHASING
B43: MFPU000001 Procurement | D43: =3611652.54*1.15493*A5 -> 4129493.8 | E43: =467908*1.15493*A5 -> 534996.98 | F43: =280193.93*1.15493*A5 -> 320368.33 | G43: =+D43-E43-F43 -> 3274128.5
B44: MFPU000002 Director | D44: 0 | E44: 0.25 | F44: 0 | G44: =+D44-E44-F44 -> -0.25
B45: MFPU000003 Outside Services | D45: =1103199.97*1.15493*A5 -> 1261377.6 | E45: 0 | F45: =27647.25*1.15493*A5 -> 31611.332 | G45: =+D45-E45-F45 -> 1229766.2
B46: Minority Evaluator position | D46: =118526 -> 118526 | E46: 0 | F46: 0 | G46: =+D46-E46-F46 -> 118526
B47: MFIB - MFOP000071 | D47: 0 | E47: 0 | F47: 0 | G47: =+D47-E47-F47 -> 0
A48: OMF
B49: MFDR000001 CAO | D49: =441845.07*(1.290751519)*A5 -> 564609.07 | E49: =40633*(1.290751519)*A5 -> 51922.635 | F49: =7138*(1.290751519)*A5 -> 9121.2505 | G49: =+D49-E49-F49 -> 503565.19
B50: MFOP000001 Fin & Mgmt Srvs | D50: =3622806.49*(1.290751519)*A5 -> 4629381.6 | E50: =2121341*(1.290751519)*A5 -> 2710742.9 | F50: =160227.25*(1.290751519)*A5 -> 204745.43 | G50: =+D50-E50-F50 -> 1713893.2
A51: FINANCIAL PLANNING
B52: MFFS000008 Financial Planning | D52: =2406719.93*0.88*1.15493*A5 -> 2421581.5 | E52: =80863.34*0.88*1.15493*A5 -> 81362.672 | F52: 0 | G52: =+D52-E52-F52 -> 2340218.8
B53: MFEB EBS Ongoing | D53: 0 | E53: 0 | F53: 0 | G53: =+D53-E53-F53 -> 0
B54: GRANTS | D54: =2406719.93*0.12*1.15493*A5 -> 330215.65 | E54: =80863.34*0.12*1.15493*A5 -> 11094.91 | F54: 0 | G54: =+D54-E54-F54 -> 319120.74
B55: Unused | D55: 0 | E55: 0 | F55: 0 | G55: =+D55-E55-F55 -> 0
B56: 9AUSA0000001 Single Audit | D56: 0 | E56: 0 | F56: 0 | G56: =+D56-E56-F56 -> 0
A57: ACCOUNTING
B58: MFFS000001 Acct Admin | D58: =718070*1.15493*A5 -> 821027.38 | E58: =803.25*1.15493*A5 -> 918.42055 | F58: =48.15*1.15493*A5 -> 55.053781 | G58: =+D58-E58-F58 -> 820053.9
B59: MFFS000002 Acct Process | D59: =903564.4*1.15493*A5 -> 1033118.1 | E59: 0 | F59: =42384.48*1.15493*A5 -> 48461.596 | G59: =+D59-E59-F59 -> 984656.5
B60: MFFS000003 Acct Technical | D60: =1177367.39*1.15493*A5 -> 1346179.2 | E60: =8785.05*1.15493*A5 -> 10044.657 | F60: =(10255.44-8765.052)*1.15493*A5 -> 1704.0809 | G60: =+D60-E60-F60 -> 1334430.4
B61: MFFS000004 Acct Customer | D61: =768014.67*1.15493*A5 -> 878133.15 | E61: =1247.29*1.15493*A5 -> 1426.1273 | F61: =45*1.15493*A5 -> 51.452132 | G61: =+D61-E61-F61 -> 876655.57
B62: LAAUAUCA000000GL CAFR audit | D62: 0 | E62: 0 | F62: 0 | G62: =+D62-E62-F62 -> 0
A63: SPECIAL APPROPRIATION
B64: MFSA000002 City Membership/Dues | D64: =280513*A5 -> 277707.87 | E64: 0 | F64: 0 | G64: =+D64-E64-F64 -> 277707.87
B65: MFSA000003 Leaders Roundtable | D65: 0 | E65: 0 | F65: 0 | G65: =+D65-E65-F65 -> 0
B66: MFSA000005 Council E-Funds | D66: 0 | E66: 0 | F66: 0 | G66: =+D66-E66-F66 -> 0
A67: HR ORG 1..6
B68: MFHR000001 Operations | D68: =5455763.04*1.15493*A5 -> 6238014.2 | E68: =55397.42*1.15493*A5 -> 63340.341 | F68: =(498337.48-55397.42)*1.15493*A5 -> 506449.12 | G68: =+D68-E68-F68 -> 5668224.7
B69: MFHR000002 Labor | D69: 0 | E69: 0 | F69: 0 | G69: =+D69-E69-F69 -> 0
B70: MFHR000003 Class/Comp | D70: 0 | E70: 0 | F70: 0 | G70: =+D70-E70-F70 -> 0
B71: MFHR000004 E&D | D71: 0 | E71: 0 | F71: 0 | G71: =+D71-E71-F71 -> 0
B72: MFHR000005 Diversity | D72: 0 | E72: 0 | F72: 0 | G72: =+D72-E72-F72 -> 0
B73: MFHR000006 Benefits | D73: 0 | E73: 0 | F73: 0 | G73: =+D73-E73-F73 -> 0
A74: HR UTILITIES
B75: MFHR000007 Utilities | D75: =694271*1.15493*A5 -> 793816.06 | E75: 0 | F75: 0 | G75: =+D75-E75-F75 -> 793816.06
A76: HR SAFETY
B77: MFHR000008 Safety | D77: =455855.52*1.15493*A5 -> 521216.4 | E77: 0 | F77: 0 | G77: =+D77-E77-F77 -> 521216.4
A78: HR ADMIN
B79: MFHR000009 Admin | D79: =690843.92*1.15493*A5 -> 789897.6 | E79: 0 | F79: 0 | G79: =+D79-E79-F79 -> 789897.6
A80: OEM
B81: PSEO000000000000/FREO000004 | D81: =112785*1.027 -> 115830.19 | E81: 0 | F81: 0 | G81: =+D81-E81-F81 -> 115830.19
A82: OFFICE OF EQUITY
D83: =(1645705*A5*0)+860000 -> 860000 | E83: 0 | F83: 0 | G83: =+D83-E83-F83 -> 860000
A84: POEM
B85: EMEM Emergency Management | D85: =1723697.01*1.231430397*A5 -> 2101386.8 | E85: =17000*1.231430397*A5 -> 20724.974 | F85: =2035.5*1.231430397*A5 -> 2481.5108 | G85: =+D85-E85-F85 -> 2078180.3
B88: Subtotals | C88: $ | D88: =SUM(D13:D87) -> 52258688 | E88: =SUM(E13:E87) -> 3486574.8 | F88: =SUM(F13:F87) -> 1380869.7 | G88: =SUM(G13:G87) -> 47391243
B91: SPECIFIC ALLOCATIONS: | G91: 0
B93: City-Wide Cost Allocation | G93: =+G88-G91 -> 47391243

Sheet SCH D
A1: Schedule D | B1: FY 13-14 G.F. Overhead | AM1: SPECIAL | AN1: FY 11/12 | AQ1: FY 2013/14 | AS1: INCREASE
B2: BASED ON TARGET AMOUNTS | J2: OMF/ | M2: PUBLIC | P2: OMF | V2: BUREAU | W2: CITY | AC2: BUREAU TOTAL | AG2: CITY-WIDE | AK2: OFFICE OF | AM2: APPROPS | AN2: TOTAL | AQ2: OVERHEAD | AS2: (DECREASE)
A3: =NOW() -> 41276.678 | G3: AUDITOR | J3: FINANCIAL | K3: OMF | M3: INVOLVEMENT | O3: OMF | P3: ACCOUNTING | V3: ALLOCATION | W3: COUNCIL | X3: POEM | Y3: OMF | Z3: ATTORNEY | AA3: PURCHASING | AB3: AUDITOR | AC3: BEFORE | AD3: BUREAU | AE3: PLANNING | AG3: I & R | AI3: OEM | AK3: EQUITY | AL3: SPECIAL | AM3: COUNCIL | AN3: ALLOCATION | AO3: ADJUSTMENTS | AQ3: FOR PROPOSED | AS3: ACTUAL
C4: CITY | E4: AUDIT | F4: RECORDS | G4: SPECIFIC | H4: CITY | J4: SERVICES | K4: FINANCIAL | L4: OMF | M4: BEST | O4: ACCOUNTING | P4: AP WITH | R4: HR | S4: HR | T4: HR | U4: HR | V4: BEFORE | W4: INDIRECT | X4: INDIRECT | Y4: INDIRECT | Z4: INDIRECT | AA4: INDIRECT | AB4: INDIRECT | AC4: OTHER COST | AD4: OF | AE4: INDIRECT | AF4: CITY WIDE | AG4: INDIRECT | AI4: INDIRECT | AJ4: OFFICE OF | AK4: INDIRECT | AL4: APPROPS | AM4: INDIRECT | AN4: ALL | AO4: FOR BUDGET | AP4: ADJ | AQ4: BUDGET USING | AS4: OVER
A5: SAP Fund | B5: OPERATING BUREAUS/FUNDS | C5: ATTORNEY | D5: AUDITOR | E5: SERVICES | F5: MANAGEMENT | G5: ALLOCATIONS | H5: COUNCIL | I5: PURCHASING | J5: ADMIN | K5: PLANNING | L5: GRANTS | M5: PRACTICES | N5: ACCOUNTING | O5: PAYROLL | P5: DISCOUNT | Q5: POEM | R5: ORG 41..49 | S5: ORG 50 | T5: ORG 51 | U5: ORG 52 | V5: INDIRECT | W5: ALLOCATION | X5: ALLOCATION | Y5: ALLOCATION | Z5: ALLOCATION | AA5: ALLOCATION | AB5: ALLOCATION | AC5: ALLOCATIONS | AD5: PLANNING | AE5: ALLOCATION | AF5: I & R | AG5: ALLOCATION | AH5: OEM | AI5: ALLOCATION | AJ5: EQUITY | AK5: ALLOCATION | AL5: COUNCIL | AM5: ALLOCATION | AN5: BUREAUS | AO5: PURPOSES | AP5: CODE | AQ5: TARGET NOS. | AS5: BUDGET
A8: =ALLOCATION!A12 -> 100000 | B8: =ALLOCATION!C12 -> Portland Police Bureau | C8: ='ACTUAL EXP'!$G$13*(ALLOCATION!P12) -> 782391.97 | D8: =(SUM('ACTUAL EXP'!$G$15,'ACTUAL EXP'!$G$17:$G$19,'ACTUAL EXP'!$G$22))*ALLOCATION!P12 -> 1261876.2 | E8: =(('ACTUAL EXP'!$G$25)*(ALLOCATION!P12)) -> 0 | F8: ='ACTUAL EXP'!$G$28*ALLOCATION!P12 -> 0 | G8: ='ACTUAL EXP'!$G$16+'ACTUAL EXP'!$G$20*0.25 -> 0 | H8: =SUM('ACTUAL EXP'!$G$30:$G$35)*ALLOCATION!P12 -> 1132568.1 | I8: =SUM('ACTUAL EXP'!$G$43:$G$47)*ALLOCATION!P12 -> 684105.74 | J8: =(SUM('ACTUAL EXP'!$G$49:$G$50)*ALLOCATION!P12*0.5)+(SUM('ACTUAL EXP'!$G$49:$G$50)*ALLOCATION!P12*0.5) -> 328177.86 | K8: =SUM('ACTUAL EXP'!$G$52:$G$53)*ALLOCATION!P12 -> 346346.06 | L8: =SUM('ACTUAL EXP'!$G$54:$G$54)*ALLOCATION!P12 -> 47229.008 | M8: =SUM('ACTUAL EXP'!$G$21:$G$21)*ALLOCATION!P12 -> 14553.768 | N8: =SUM('ACTUAL EXP'!$G$58:$G$62)*0.39*ALLOCATION!P12 -> 231787.54 | O8: =SUM('ACTUAL EXP'!$G$58:$G$62)*0.27*ALLOCATION!P12 -> 160468.3 | P8: =SUM('ACTUAL EXP'!$G$58:$G$62)*0.34*ALLOCATION!P12 -> 202071.19 | Q8: ='ACTUAL EXP'!$G$85*ALLOCATION!P12 -> 307565.07 | R8: =SUM('ACTUAL EXP'!$G$68:$G$73)*ALLOCATION!P12 -> 838881.95 | S8: =SUM('ACTUAL EXP'!$G$75)*ALLOCATION!P12 -> 117482.63 | T8: =SUM('ACTUAL EXP'!$G$77)*ALLOCATION!P12 -> 77138.62 | U8: =SUM('ACTUAL EXP'!$G$79)*ALLOCATION!P12 -> 116902.71 | V8: =SUM(C8:U8) -> 6649546.7 | W8: =-(H8/$H$111)*($W$117) -> 59889.802 | X8: =-(Q8/$Q$111)*($X$118) -> 43850.657 | Y8: =-(SUM(J8:O8,R8:U8)/SUM($J$111:$O$111,$R$111:$U$111))*$Y$119 -> 139817.76 | Z8: =-(C8/$C$111)*($Z$120) -> 57347.624 | AA8: =-(I8/$I$111)*($AA$121) -> 22326.431 | AB8: =-(SUM(D8:G8)/SUM($D$111:$G$111))*SUM($AB$117:$AB$122) -> 48581.033 | AC8: =SUM(V8:AB8) -> 7021360 | AD8: =SUM('ACTUAL EXP'!$G$37:$G$39)*ALLOCATION!P12 -> 137554.25 | AE8: =(AD8/$AD$111)*SUM($AD$117:$AD$122) -> 7691.4266 | AF8: =SUM('ACTUAL EXP'!$G$41)*ALLOCATION!P12 -> 41154.754 | AG8: =(AF8/$AF$111)*SUM($AF$117:$AF$122) -> 2301.1922 | AH8: =SUM('ACTUAL EXP'!$G$81)*ALLOCATION!P12 -> 17142.556 | AI8: =(AH8/$AH$111)*SUM($AH$117:$AH$122) -> 958.53607 | AJ8: =SUM('ACTUAL EXP'!$G$83)*ALLOCATION!P12 -> 127277.68 | AK8: =(AJ8/$AH$111)*SUM($AH$117:$AH$122) -> 7116.806 | AL8: =SUM('ACTUAL EXP'!$G$64:$G$66)*ALLOCATION!P12 -> 41100.015 | AM8: =(AL8/$AL$111)*SUM($AL$117:$AL$122) -> 2298.1314 | AN8: =SUM(AC8:AM8) -> 7405955.4 | AQ8: =SUM(AO8,AN8) -> 7405955.4 | AS8: =AQ8-AR8 -> 7405955.4
A9: =ALLOCATION!A13 -> 214000 | B9: =ALLOCATION!C13 -> Campaign Finance | C9: ='ACTUAL EXP'!$G$13*(ALLOCATION!P13) -> 0 | D9: =(SUM('ACTUAL EXP'!$G$15,'ACTUAL EXP'!$G$17:$G$19,'ACTUAL EXP'!$G$22))*ALLOCATION!P13 -> 0 | E9: =(('ACTUAL EXP'!$G$25)*(ALLOCATION!P13)) -> 0 | F9: ='ACTUAL EXP'!$G$28*ALLOCATION!P13 -> 0 | G9: 0 | H9: =SUM('ACTUAL EXP'!$G$30:$G$35)*ALLOCATION!P13 -> 0 | I9: =SUM('ACTUAL EXP'!$G$43:$G$47)*ALLOCATION!P13 -> 0 | J9: =(SUM('ACTUAL EXP'!$G$49:$G$50)*ALLOCATION!P13*0.5)+(SUM('ACTUAL EXP'!$G$49:$G$50)*ALLOCATION!P13*0.5) -> 0 | K9: =SUM('ACTUAL EXP'!$G$52:$G$53)*ALLOCATION!P13 -> 0 | L9: =SUM('ACTUAL EXP'!$G$54:$G$54)*ALLOCATION!P13 -> 0 | M9: =SUM('ACTUAL EXP'!$G$21:$G$21)*ALLOCATION!P13 -> 0 | N9: =SUM('ACTUAL EXP'!$G$58:$G$62)*0.39*ALLOCATION!P13 -> 0 | O9: =SUM('ACTUAL EXP'!$G$58:$G$62)*0.27*ALLOCATION!P13 -> 0 | P9: =SUM('ACTUAL EXP'!$G$58:$G$62)*0.34*ALLOCATION!P13 -> 0 | Q9: ='ACTUAL EXP'!$G$85*ALLOCATION!P13 -> 0 | R9: =SUM('ACTUAL EXP'!$G$68:$G$73)*ALLOCATION!P13 -> 0 | S9: =SUM('ACTUAL EXP'!$G$75)*ALLOCATION!P13 -> 0 | T9: =SUM('ACTUAL EXP'!$G$77)*ALLOCATION!P13 -> 0 | U9: =SUM('ACTUAL EXP'!$G$79)*ALLOCATION!P13 -> 0 | V9: =SUM(C9:U9) -> 0 | W9: =-(H9/$H$111)*($W$117) -> 0 | X9: =-(Q9/$Q$111)*($X$118) -> 0 | Y9: =-(SUM(J9:O9,R9:U9)/SUM($J$111:$O$111,$R$111:$U$111))*$Y$119 -> 0 | Z9: =-(C9/$C$111)*($Z$120) -> 0 | AA9: =-(I9/$I$111)*($AA$121) -> 0 | AB9: =-(SUM(D9:G9)/SUM($D$111:$G$111))*SUM($AB$117:$AB$122) -> 0 | AC9: =SUM(V9:AB9) -> 0 | AD9: =SUM('ACTUAL EXP'!$G$37:$G$39)*ALLOCATION!P13 -> 0 | AE9: =(AD9/$AD$111)*SUM($AD$117:$AD$122) -> 0 | AF9: =SUM('ACTUAL EXP'!$G$41)*ALLOCATION!P13 -> 0 | AG9: =(AF9/$AF$111)*SUM($AF$117:$AF$122) -> 0 | AH9: =SUM('ACTUAL EXP'!$G$81)*ALLOCATION!P13 -> 0 | AI9: =(AH9/$AH$111)*SUM($AH$117:$AH$122) -> 0 | AJ9: =SUM('ACTUAL EXP'!$G$83)*ALLOCATION!P13 -> 0 | AK9: =(AJ9/$AH$111)*SUM($AH$117:$AH$122) -> 0 | AL9: =SUM('ACTUAL EXP'!$G$64:$G$66)*ALLOCATION!P13 -> 0 | AM9: =(AL9/$AL$111)*SUM($AL$117:$AL$122) -> 0 | AN9: =SUM(AC9:AM9) -> 0 | AQ9: =SUM(AO9,AN9) -> 0 | AS9: =AQ9-AR9 -> 0
A10: =ALLOCATION!A14 -> 100000 | B10: =ALLOCATION!C14 -> Portland Fire & Rescue | C10: ='ACTUAL EXP'!$G$13*(ALLOCATION!P14) -> 487642.7 | D10: =(SUM('ACTUAL EXP'!$G$15,'ACTUAL EXP'!$G$17:$G$19,'ACTUAL EXP'!$G$22))*ALLOCATION!P14 -> 786491.62 | E10: =(('ACTUAL EXP'!$G$25)*(ALLOCATION!P14)) -> 0 | F10: ='ACTUAL EXP'!$G$28*ALLOCATION!P14 -> 0 | G10: 0 | H10: =SUM('ACTUAL EXP'!$G$30:$G$35)*ALLOCATION!P14 -> 705897.54 | I10: =SUM('ACTUAL EXP'!$G$43:$G$47)*ALLOCATION!P14 -> 426383.69 | J10: =(SUM('ACTUAL EXP'!$G$49:$G$50)*ALLOCATION!P14*0.5)+(SUM('ACTUAL EXP'!$G$49:$G$50)*ALLOCATION!P14*0.5) -> 204543.94 | K10: =SUM('ACTUAL EXP'!$G$52:$G$53)*ALLOCATION!P14 -> 215867.67 | L10: =SUM('ACTUAL EXP'!$G$54:$G$54)*ALLOCATION!P14 -> 29436.5 | M10: =SUM('ACTUAL EXP'!$G$21:$G$21)*ALLOCATION!P14 -> 9070.9503 | N10: =SUM('ACTUAL EXP'!$G$58:$G$62)*0.39*ALLOCATION!P14 -> 144466.59 | O10: =SUM('ACTUAL EXP'!$G$58:$G$62)*0.27*ALLOCATION!P14 -> 100015.33 | P10: =SUM('ACTUAL EXP'!$G$58:$G$62)*0.34*ALLOCATION!P14 -> 125945.23 | Q10: ='ACTUAL EXP'!$G$85*ALLOCATION!P14 -> 191696.58 | R10: =SUM('ACTUAL EXP'!$G$68:$G$73)*ALLOCATION!P14 -> 522851.3 | S10: =SUM('ACTUAL EXP'!$G$75)*ALLOCATION!P14 -> 73223.59 | T10: =SUM('ACTUAL EXP'!$G$77)*ALLOCATION!P14 -> 48078.312 | U10: =SUM('ACTUAL EXP'!$G$79)*ALLOCATION!P14 -> 72862.142 | V10: =SUM(C10:U10) -> 4144473.7 | W10: =-(H10/$H$111)*($W$117) -> 37327.614 | X10: =-(Q10/$Q$111)*($X$118) -> 27330.87 | Y10: =-(SUM(J10:O10,R10:U10)/SUM($J$111:$O$111,$R$111:$U$111))*$Y$119 -> 87144.439 | Z10: =-(C10/$C$111)*($Z$120) -> 35743.146 | AA10: =-(I10/$I$111)*($AA$121) -> 13915.431 | AB10: =-(SUM(D10:G10)/SUM($D$111:$G$111))*SUM($AB$117:$AB$122) -> 30279.179 | AC10: =SUM(V10:AB10) -> 4376214.4 | AD10: =SUM('ACTUAL EXP'!$G$37:$G$39)*ALLOCATION!P14 -> 85733.66 | AE10: =(AD10/$AD$111)*SUM($AD$117:$AD$122) -> 4793.8479 | AF10: =SUM('ACTUAL EXP'!$G$41)*ALLOCATION!P14 -> 25650.59 | AG10: =(AF10/$AF$111)*SUM($AF$117:$AF$122) -> 1434.2678 | AH10: =SUM('ACTUAL EXP'!$G$81)*ALLOCATION!P14 -> 10684.468 | AI10: =(AH10/$AH$111)*SUM($AH$117:$AH$122) -> 597.42832 | AJ10: =SUM('ACTUAL EXP'!$G$83)*ALLOCATION!P14 -> 79328.563 | AK10: =(AJ10/$AH$111)*SUM($AH$117:$AH$122) -> 4435.7031 | AL10: =SUM('ACTUAL EXP'!$G$64:$G$66)*ALLOCATION!P14 -> 25616.472 | AM10: =(AL10/$AL$111)*SUM($AL$117:$AL$122) -> 1432.3601 | AN10: =SUM(AC10:AM10) -> 4615921.7 | AQ10: =SUM(AO10,AN10) -> 4615921.7 | AS10: =AQ10-AR10 -> 4615921.7
A11: =ALLOCATION!A15 -> 100000 | B11: =ALLOCATION!C15 -> Portland Parks & Recreation | C11: ='ACTUAL EXP'!$G$13*(ALLOCATION!P15) -> 423560.45 | D11: =(SUM('ACTUAL EXP'!$G$15,'ACTUAL EXP'!$G$17:$G$19,'ACTUAL EXP'!$G$22))*ALLOCATION!P15 -> 683136.94 | E11: =(('ACTUAL EXP'!$G$25)*(ALLOCATION!P15)) -> 0 | F11: ='ACTUAL EXP'!$G$28*ALLOCATION!P15 -> 0 | G11: 0 | H11: =SUM('ACTUAL EXP'!$G$30:$G$35)*ALLOCATION!P15 -> 613133.91 | I11: =SUM('ACTUAL EXP'!$G$43:$G$47)*ALLOCATION!P15 -> 370351.62 | J11: =(SUM('ACTUAL EXP'!$G$49:$G$50)*ALLOCATION!P15*0.5)+(SUM('ACTUAL EXP'!$G$49:$G$50)*ALLOCATION!P15*0.5) -> 177664.35 | K11: =SUM('ACTUAL EXP'!$G$52:$G$53)*ALLOCATION!P15 -> 187500 | L11: =SUM('ACTUAL EXP'!$G$54:$G$54)*ALLOCATION!P15 -> 25568.181 | M11: =SUM('ACTUAL EXP'!$G$21:$G$21)*ALLOCATION!P15 -> 7878.9157 | N11: =SUM('ACTUAL EXP'!$G$58:$G$62)*0.39*ALLOCATION!P15 -> 125481.9 | O11: =SUM('ACTUAL EXP'!$G$58:$G$62)*0.27*ALLOCATION!P15 -> 86872.086 | P11: =SUM('ACTUAL EXP'!$G$58:$G$62)*0.34*ALLOCATION!P15 -> 109394.48 | Q11: ='ACTUAL EXP'!$G$85*ALLOCATION!P15 -> 166505.28 | R11: =SUM('ACTUAL EXP'!$G$68:$G$73)*ALLOCATION!P15 -> 454142.2 | S11: =SUM('ACTUAL EXP'!$G$75)*ALLOCATION!P15 -> 63601.108 | T11: =SUM('ACTUAL EXP'!$G$77)*ALLOCATION!P15 -> 41760.229 | U11: =SUM('ACTUAL EXP'!$G$79)*ALLOCATION!P15 -> 63287.159 | V11: =SUM(C11:U11) -> 3599838.8 | W11: =-(H11/$H$111)*($W$117) -> 32422.305 | X11: =-(Q11/$Q$111)*($X$118) -> 23739.257 | Y11: =-(SUM(J11:O11,R11:U11)/SUM($J$111:$O$111,$R$111:$U$111))*$Y$119 -> 75692.586 | Z11: =-(C11/$C$111)*($Z$120) -> 31046.056 | AA11: =-(I11/$I$111)*($AA$121) -> 12086.772 | AB11: =-(SUM(D11:G11)/SUM($D$111:$G$111))*SUM($AB$117:$AB$122) -> 26300.122 | AC11: =SUM(V11:AB11) -> 3801125.9 | AD11: =SUM('ACTUAL EXP'!$G$37:$G$39)*ALLOCATION!P15 -> 74467.201 | AE11: =(AD11/$AD$111)*SUM($AD$117:$AD$122) -> 4163.8772 | AF11: =SUM('ACTUAL EXP'!$G$41)*ALLOCATION!P15 -> 22279.787 | AG11: =(AF11/$AF$111)*SUM($AF$117:$AF$122) -> 1245.7873 | AH11: =SUM('ACTUAL EXP'!$G$81)*ALLOCATION!P15 -> 9280.3977 | AI11: =(AH11/$AH$111)*SUM($AH$117:$AH$122) -> 518.91888 | AJ11: =SUM('ACTUAL EXP'!$G$83)*ALLOCATION!P15 -> 68903.812 | AK11: =(AJ11/$AH$111)*SUM($AH$117:$AH$122) -> 3852.7971 | AL11: =SUM('ACTUAL EXP'!$G$64:$G$66)*ALLOCATION!P15 -> 22250.152 | AM11: =(AL11/$AL$111)*SUM($AL$117:$AL$122) -> 1244.1303 | AN11: =SUM(AC11:AM11) -> 4009332.8 | AO11: =-AO72-AO73 -> 475.7093 | AP11: K | AQ11: =SUM(AO11,AN11) -> 4009808.5 | AS11: =AQ11-AR11 -> 4009808.5
A12: =ALLOCATION!A16 -> 600000 | B12: =ALLOCATION!C16 -> Sewer System Op | C12: ='ACTUAL EXP'!$G$13*(ALLOCATION!P16) -> 571790.39 | D12: =(SUM('ACTUAL EXP'!$G$15,'ACTUAL EXP'!$G$17:$G$19,'ACTUAL EXP'!$G$22))*ALLOCATION!P16 -> 922208.72 | E12: =(('ACTUAL EXP'!$G$25)*(ALLOCATION!P16)) -> 0 | F12: ='ACTUAL EXP'!$G$28*ALLOCATION!P16 -> 0 | G12: 0 | H12: =SUM('ACTUAL EXP'!$G$30:$G$35)*ALLOCATION!P16 -> 827707.31 | I12: =SUM('ACTUAL EXP'!$G$43:$G$47)*ALLOCATION!P16 -> 499960.51 | J12: =(SUM('ACTUAL EXP'!$G$49:$G$50)*ALLOCATION!P16*0.5)+(SUM('ACTUAL EXP'!$G$49:$G$50)*ALLOCATION!P16*0.5) -> 239840.07 | K12: =SUM('ACTUAL EXP'!$G$52:$G$53)*ALLOCATION!P16 -> 253117.82 | L12: =SUM('ACTUAL EXP'!$G$54:$G$54)*ALLOCATION!P16 -> 34516.066 | M12: =SUM('ACTUAL EXP'!$G$21:$G$21)*ALLOCATION!P16 -> 10636.235 | N12: =SUM('ACTUAL EXP'!$G$58:$G$62)*0.39*ALLOCATION!P16 -> 169395.77 | O12: =SUM('ACTUAL EXP'!$G$58:$G$62)*0.27*ALLOCATION!P16 -> 117273.99 | P12: =SUM('ACTUAL EXP'!$G$58:$G$62)*0.34*ALLOCATION!P16 -> 147678.36 | Q12: ='ACTUAL EXP'!$G$85*ALLOCATION!P16 -> 224775.76 | R12: =SUM('ACTUAL EXP'!$G$68:$G$73)*ALLOCATION!P16 -> 613074.59 | S12: =SUM('ACTUAL EXP'!$G$75)*ALLOCATION!P16 -> 85859.062 | T12: =SUM('ACTUAL EXP'!$G$77)*ALLOCATION!P16 -> 56374.711 | U12: =SUM('ACTUAL EXP'!$G$79)*ALLOCATION!P16 -> 85435.242 | V12: =SUM(C12:U12) -> 4859644.6 | W12: =-(H12/$H$111)*($W$117) -> 43768.871 | X12: =-(Q12/$Q$111)*($X$118) -> 32047.088 | Y12: =-(SUM(J12:O12,R12:U12)/SUM($J$111:$O$111,$R$111:$U$111))*$Y$119 -> 102182.09 | Z12: =-(C12/$C$111)*($Z$120) -> 41910.988 | AA12: =-(I12/$I$111)*($AA$121) -> 16316.679 | AB12: =-(SUM(D12:G12)/SUM($D$111:$G$111))*SUM($AB$117:$AB$122) -> 35504.158 | AC12: =SUM(V12:AB12) -> 5131374.5 | AD12: =SUM('ACTUAL EXP'!$G$37:$G$39)*ALLOCATION!P16 -> 100527.87 | AE12: =(AD12/$AD$111)*SUM($AD$117:$AD$122) -> 5621.0749 | AF12: =SUM('ACTUAL EXP'!$G$41)*ALLOCATION!P16 -> 30076.859 | AG12: =(AF12/$AF$111)*SUM($AF$117:$AF$122) -> 1681.7652 | AH12: =SUM('ACTUAL EXP'!$G$81)*ALLOCATION!P16 -> 12528.182 | AI12: =(AH12/$AH$111)*SUM($AH$117:$AH$122) -> 700.52063 | AJ12: =SUM('ACTUAL EXP'!$G$83)*ALLOCATION!P16 -> 93017.51 | AK12: =(AJ12/$AH$111)*SUM($AH$117:$AH$122) -> 5201.1286 | AL12: =SUM('ACTUAL EXP'!$G$64:$G$66)*ALLOCATION!P16 -> 30036.854 | AM12: =(AL12/$AL$111)*SUM($AL$117:$AL$122) -> 1679.5283 | AN12: =SUM(AC12:AM12) -> 5412445.8 | AO12: =-AO17-AO18-AO23-AO24-AO25 -> 1659579.5 | AP12: A | AQ12: =SUM(AO12,AN12) -> 7072025.3 | AS12: =AQ12-AR12 -> 7072025.3
A13: =ALLOCATION!A17 -> 608000 | B13: =ALLOCATION!C17 -> Envtl Remediation | C13: ='ACTUAL EXP'!$G$13*(ALLOCATION!P17) -> 17979 | D13: =(SUM('ACTUAL EXP'!$G$15,'ACTUAL EXP'!$G$17:$G$19,'ACTUAL EXP'!$G$22))*ALLOCATION!P17 -> 28997.323 | E13: =(('ACTUAL EXP'!$G$25)*(ALLOCATION!P17)) -> 0 | F13: ='ACTUAL EXP'!$G$28*ALLOCATION!P17 -> 0 | G13: 0 | H13: =SUM('ACTUAL EXP'!$G$30:$G$35)*ALLOCATION!P17 -> 26025.883 | I13: =SUM('ACTUAL EXP'!$G$43:$G$47)*ALLOCATION!P17 -> 15720.429 | J13: =(SUM('ACTUAL EXP'!$G$49:$G$50)*ALLOCATION!P17*0.5)+(SUM('ACTUAL EXP'!$G$49:$G$50)*ALLOCATION!P17*0.5) -> 7541.3732 | K13: =SUM('ACTUAL EXP'!$G$52:$G$53)*ALLOCATION!P17 -> 7958.8699 | L13: =SUM('ACTUAL EXP'!$G$54:$G$54)*ALLOCATION!P17 -> 1085.3004 | M13: =SUM('ACTUAL EXP'!$G$21:$G$21)*ALLOCATION!P17 -> 334.43876 | N13: =SUM('ACTUAL EXP'!$G$58:$G$62)*0.39*ALLOCATION!P17 -> 5326.3688 | O13: =SUM('ACTUAL EXP'!$G$58:$G$62)*0.27*ALLOCATION!P17 -> 3687.4861 | P13: =SUM('ACTUAL EXP'!$G$58:$G$62)*0.34*ALLOCATION!P17 -> 4643.501 | Q13: ='ACTUAL EXP'!$G$85*ALLOCATION!P17 -> 7067.7009 | R13: =SUM('ACTUAL EXP'!$G$68:$G$73)*ALLOCATION!P17 -> 19277.113 | S13: =SUM('ACTUAL EXP'!$G$75)*ALLOCATION!P17 -> 2699.6958 | T13: =SUM('ACTUAL EXP'!$G$77)*ALLOCATION!P17 -> 1772.6093 | U13: =SUM('ACTUAL EXP'!$G$79)*ALLOCATION!P17 -> 2686.3695 | V13: =SUM(C13:U13) -> 152803.46 | W13: =-(H13/$H$111)*($W$117) -> 1376.2396 | X13: =-(Q13/$Q$111)*($X$118) -> 1007.6675 | Y13: =-(SUM(J13:O13,R13:U13)/SUM($J$111:$O$111,$R$111:$U$111))*$Y$119 -> 3212.9465 | Z13: =-(C13/$C$111)*($Z$120) -> 1317.8215 | AA13: =-(I13/$I$111)*($AA$121) -> 513.0509 | AB13: =-(SUM(D13:G13)/SUM($D$111:$G$111))*SUM($AB$117:$AB$122) -> 1116.3693 | AC13: =SUM(V13:AB13) -> 161347.56 | AD13: =SUM('ACTUAL EXP'!$G$37:$G$39)*ALLOCATION!P17 -> 3160.9321 | AE13: =(AD13/$AD$111)*SUM($AD$117:$AD$122) -> 176.74537 | AF13: =SUM('ACTUAL EXP'!$G$41)*ALLOCATION!P17 -> 945.71694 | AG13: =(AF13/$AF$111)*SUM($AF$117:$AF$122) -> 52.880318 | AH13: =SUM('ACTUAL EXP'!$G$81)*ALLOCATION!P17 -> 393.92789 | AI13: =(AH13/$AH$111)*SUM($AH$117:$AH$122) -> 22.026709 | AJ13: =SUM('ACTUAL EXP'!$G$83)*ALLOCATION!P17 -> 2924.7813 | AK13: =(AJ13/$AH$111)*SUM($AH$117:$AH$122) -> 163.54086 | AL13: =SUM('ACTUAL EXP'!$G$64:$G$66)*ALLOCATION!P17 -> 944.45905 | AM13: =(AL13/$AL$111)*SUM($AL$117:$AL$122) -> 52.809982 | AN13: =SUM(AC13:AM13) -> 170185.38 | AQ13: =SUM(AO13,AN13) -> 170185.38 | AS13: =AQ13-AR13 -> 170185.38
A14: =ALLOCATION!A18 -> 605000 | B14: =ALLOCATION!C18 -> Solid Waste Mgt | C14: ='ACTUAL EXP'!$G$13*(ALLOCATION!P18) -> 19865.587 | D14: =(SUM('ACTUAL EXP'!$G$15,'ACTUAL EXP'!$G$17:$G$19,'ACTUAL EXP'!$G$22))*ALLOCATION!P18 -> 32040.093 | E14: =(('ACTUAL EXP'!$G$25)*(ALLOCATION!P18)) -> 0 | F14: ='ACTUAL EXP'!$G$28*ALLOCATION!P18 -> 0 | G14: 0 | H14: =SUM('ACTUAL EXP'!$G$30:$G$35)*ALLOCATION!P18 -> 28756.852 | I14: =SUM('ACTUAL EXP'!$G$43:$G$47)*ALLOCATION!P18 -> 17370.017 | J14: =(SUM('ACTUAL EXP'!$G$49:$G$50)*ALLOCATION!P18*0.5)+(SUM('ACTUAL EXP'!$G$49:$G$50)*ALLOCATION!P18*0.5) -> 8332.7104 | K14: =SUM('ACTUAL EXP'!$G$52:$G$53)*ALLOCATION!P18 -> 8794.0162 | L14: =SUM('ACTUAL EXP'!$G$54:$G$54)*ALLOCATION!P18 -> 1199.184 | M14: =SUM('ACTUAL EXP'!$G$21:$G$21)*ALLOCATION!P18 -> 369.53234 | N14: =SUM('ACTUAL EXP'!$G$58:$G$62)*0.39*ALLOCATION!P18 -> 5885.2795 | O14: =SUM('ACTUAL EXP'!$G$58:$G$62)*0.27*ALLOCATION!P18 -> 4074.4243 | P14: =SUM('ACTUAL EXP'!$G$58:$G$62)*0.34*ALLOCATION!P18 -> 5130.7565 | Q14: ='ACTUAL EXP'!$G$85*ALLOCATION!P18 -> 7809.3344 | R14: =SUM('ACTUAL EXP'!$G$68:$G$73)*ALLOCATION!P18 -> 21299.914 | S14: =SUM('ACTUAL EXP'!$G$75)*ALLOCATION!P18 -> 2982.9823 | T14: =SUM('ACTUAL EXP'!$G$77)*ALLOCATION!P18 -> 1958.6141 | U14: =SUM('ACTUAL EXP'!$G$79)*ALLOCATION!P18 -> 2968.2577 | V14: =SUM(C14:U14) -> 168837.55 | W14: =-(H14/$H$111)*($W$117) -> 1520.6522 | X14: =-(Q14/$Q$111)*($X$118) -> 1113.4049 | Y14: =-(SUM(J14:O14,R14:U14)/SUM($J$111:$O$111,$R$111:$U$111))*$Y$119 -> 3550.0899 | Z14: =-(C14/$C$111)*($Z$120) -> 1456.1042 | AA14: =-(I14/$I$111)*($AA$121) -> 566.88676 | AB14: =-(SUM(D14:G14)/SUM($D$111:$G$111))*SUM($AB$117:$AB$122) -> 1233.5131 | AC14: =SUM(V14:AB14) -> 178278.21 | AD14: =SUM('ACTUAL EXP'!$G$37:$G$39)*ALLOCATION!P18 -> 3492.6175 | AE14: =(AD14/$AD$111)*SUM($AD$117:$AD$122) -> 195.29176 | AF14: =SUM('ACTUAL EXP'!$G$41)*ALLOCATION!P18 -> 1044.9536 | AG14: =(AF14/$AF$111)*SUM($AF$117:$AF$122) -> 58.429196 | AH14: =SUM('ACTUAL EXP'!$G$81)*ALLOCATION!P18 -> 435.26384 | AI14: =(AH14/$AH$111)*SUM($AH$117:$AH$122) -> 24.338033 | AJ14: =SUM('ACTUAL EXP'!$G$83)*ALLOCATION!P18 -> 3231.6867 | AK14: =(AJ14/$AH$111)*SUM($AH$117:$AH$122) -> 180.70166 | AL14: =SUM('ACTUAL EXP'!$G$64:$G$66)*ALLOCATION!P18 -> 1043.5638 | AM14: =(AL14/$AL$111)*SUM($AL$117:$AL$122) -> 58.35148 | AN14: =SUM(AC14:AM14) -> 188043.4 | AQ14: =SUM(AO14,AN14) -> 188043.4 | AS14: =AQ14-AR14 -> 188043.4
A15: =ALLOCATION!A19 -> 200000 | B15: =ALLOCATION!C19 -> Transportation Op | C15: ='ACTUAL EXP'!$G$13*(ALLOCATION!P19) -> 693005.94 | D15: =(SUM('ACTUAL EXP'!$G$15,'ACTUAL EXP'!$G$17:$G$19,'ACTUAL EXP'!$G$22))*ALLOCATION!P19 -> 1117710.5 | E15: =(('ACTUAL EXP'!$G$25)*(ALLOCATION!P19)) -> 0 | F15: ='ACTUAL EXP'!$G$28*ALLOCATION!P19 -> 0 | G15: ='ACTUAL EXP'!$G$20*0.25 -> 0 | H15: =SUM('ACTUAL EXP'!$G$30:$G$35)*ALLOCATION!P19 -> 1003175.5 | I15: =SUM('ACTUAL EXP'!$G$43:$G$47)*ALLOCATION!P19 -> 605948.63 | J15: =(SUM('ACTUAL EXP'!$G$49:$G$50)*ALLOCATION!P19*0.5)+(SUM('ACTUAL EXP'!$G$49:$G$50)*ALLOCATION!P19*0.5) -> 290684.48 | K15: =SUM('ACTUAL EXP'!$G$52:$G$53)*ALLOCATION!P19 -> 306777.02 | L15: =SUM('ACTUAL EXP'!$G$54:$G$54)*ALLOCATION!P19 -> 41833.23 | M15: =SUM('ACTUAL EXP'!$G$21:$G$21)*ALLOCATION!P19 -> 12891.042 | N15: =SUM('ACTUAL EXP'!$G$58:$G$62)*0.39*ALLOCATION!P19 -> 205306.48 | O15: =SUM('ACTUAL EXP'!$G$58:$G$62)*0.27*ALLOCATION!P19 -> 142135.25 | P15: =SUM('ACTUAL EXP'!$G$58:$G$62)*0.34*ALLOCATION!P19 -> 178985.13 | Q15: ='ACTUAL EXP'!$G$85*ALLOCATION!P19 -> 272426.64 | R15: =SUM('ACTUAL EXP'!$G$68:$G$73)*ALLOCATION!P19 -> 743042.1 | S15: =SUM('ACTUAL EXP'!$G$75)*ALLOCATION!P19 -> 104060.58 | T15: =SUM('ACTUAL EXP'!$G$77)*ALLOCATION!P19 -> 68325.755 | U15: =SUM('ACTUAL EXP'!$G$79)*ALLOCATION!P19 -> 103546.91 | V15: =SUM(C15:U15) -> 5889855.2 | W15: =-(H15/$H$111)*($W$117) -> 53047.565 | X15: =-(Q15/$Q$111)*($X$118) -> 38840.846 | Y15: =-(SUM(J15:O15,R15:U15)/SUM($J$111:$O$111,$R$111:$U$111))*$Y$119 -> 123843.98 | Z15: =-(C15/$C$111)*($Z$120) -> 50795.823 | AA15: =-(I15/$I$111)*($AA$121) -> 19775.7 | AB15: =-(SUM(D15:G15)/SUM($D$111:$G$111))*SUM($AB$117:$AB$122) -> 43030.79 | AC15: =SUM(V15:AB15) -> 6219189.9 | AD15: =SUM('ACTUAL EXP'!$G$37:$G$39)*ALLOCATION!P19 -> 121839.07 | AE15: =(AD15/$AD$111)*SUM($AD$117:$AD$122) -> 6812.7033 | AF15: =SUM('ACTUAL EXP'!$G$41)*ALLOCATION!P19 -> 36452.942 | AG15: =(AF15/$AF$111)*SUM($AF$117:$AF$122) -> 2038.2876 | AH15: =SUM('ACTUAL EXP'!$G$81)*ALLOCATION!P19 -> 15184.068 | AI15: =(AH15/$AH$111)*SUM($AH$117:$AH$122) -> 849.02609 | AJ15: =SUM('ACTUAL EXP'!$G$83)*ALLOCATION!P19 -> 112736.57 | AK15: =(AJ15/$AH$111)*SUM($AH$117:$AH$122) -> 6303.7314 | AL15: =SUM('ACTUAL EXP'!$G$64:$G$66)*ALLOCATION!P19 -> 36404.456 | AM15: =(AL15/$AL$111)*SUM($AL$117:$AL$122) -> 2035.5765 | AN15: =SUM(AC15:AM15) -> 6559846.3 | AO15: =-AO16-AO100 -> 4818.9997 | AP15: C | AQ15: =SUM(AO15,AN15) -> 6564665.3 | AS15: =AQ15-AR15 -> 6564665.3
A16: =ALLOCATION!A20 -> 212000 | B16: =ALLOCATION!C20 -> Transportation Resv | C16: ='ACTUAL EXP'!$G$13*(ALLOCATION!P20) -> 0 | D16: =(SUM('ACTUAL EXP'!$G$15,'ACTUAL EXP'!$G$17:$G$19,'ACTUAL EXP'!$G$22))*ALLOCATION!P20 -> 0 | E16: =(('ACTUAL EXP'!$G$25)*(ALLOCATION!P20)) -> 0 | F16: ='ACTUAL EXP'!$G$28*ALLOCATION!P20 -> 0 | G16: 0 | H16: =SUM('ACTUAL EXP'!$G$30:$G$35)*ALLOCATION!P20 -> 0 | I16: =SUM('ACTUAL EXP'!$G$43:$G$47)*ALLOCATION!P20 -> 0 | J16: =(SUM('ACTUAL EXP'!$G$49:$G$50)*ALLOCATION!P20*0.5)+(SUM('ACTUAL EXP'!$G$49:$G$50)*ALLOCATION!P20*0.5) -> 0 | K16: =SUM('ACTUAL EXP'!$G$52:$G$53)*ALLOCATION!P20 -> 0 | L16: =SUM('ACTUAL EXP'!$G$54:$G$54)*ALLOCATION!P20 -> 0 | M16: =SUM('ACTUAL EXP'!$G$21:$G$21)*ALLOCATION!P20 -> 0 | N16: =SUM('ACTUAL EXP'!$G$58:$G$62)*0.39*ALLOCATION!P20 -> 0 | O16: =SUM('ACTUAL EXP'!$G$58:$G$62)*0.27*ALLOCATION!P20 -> 0 | P16: =SUM('ACTUAL EXP'!$G$58:$G$62)*0.34*ALLOCATION!P20 -> 0 | Q16: ='ACTUAL EXP'!$G$85*ALLOCATION!P20 -> 0 | R16: =SUM('ACTUAL EXP'!$G$68:$G$73)*ALLOCATION!P20 -> 0 | S16: =SUM('ACTUAL EXP'!$G$75)*ALLOCATION!P20 -> 0 | T16: =SUM('ACTUAL EXP'!$G$77)*ALLOCATION!P20 -> 0 | U16: =SUM('ACTUAL EXP'!$G$79)*ALLOCATION!P20 -> 0 | V16: =SUM(C16:U16) -> 0 | W16: =-(H16/$H$111)*($W$117) -> 0 | X16: =-(Q16/$Q$111)*($X$118) -> 0 | Y16: =-(SUM(J16:O16,R16:U16)/SUM($J$111:$O$111,$R$111:$U$111))*$Y$119 -> 0 | Z16: =-(C16/$C$111)*($Z$120) -> 0 | AA16: =-(I16/$I$111)*($AA$121) -> 0 | AB16: =-(SUM(D16:G16)/SUM($D$111:$G$111))*SUM($AB$117:$AB$122) -> 0 | AC16: =SUM(V16:AB16) -> 0 | AD16: =SUM('ACTUAL EXP'!$G$37:$G$39)*ALLOCATION!P20 -> 0 | AE16: =(AD16/$AD$111)*SUM($AD$117:$AD$122) -> 0 | AF16: =SUM('ACTUAL EXP'!$G$41)*ALLOCATION!P20 -> 0 | AG16: =(AF16/$AF$111)*SUM($AF$117:$AF$122) -> 0 | AH16: =SUM('ACTUAL EXP'!$G$81)*ALLOCATION!P20 -> 0 | AI16: =(AH16/$AH$111)*SUM($AH$117:$AH$122) -> 0 | AJ16: =SUM('ACTUAL EXP'!$G$83)*ALLOCATION!P20 -> 0 | AK16: =(AJ16/$AH$111)*SUM($AH$117:$AH$122) -> 0 | AL16: =SUM('ACTUAL EXP'!$G$64:$G$66)*ALLOCATION!P20 -> 0 | AM16: =(AL16/$AL$111)*SUM($AL$117:$AL$122) -> 0 | AN16: =SUM(AC16:AM16) -> 0 | AO16: =-AN16 -> 0 | AP16: (C) | AQ16: =SUM(AO16,AN16) -> 0 | AS16: =AQ16-AR16 -> 0
A17: =ALLOCATION!A21 -> 614000 | B17: =ALLOCATION!C21 -> Sewer System Constr | C17: ='ACTUAL EXP'!$G$13*(ALLOCATION!P21) -> 104370.64 | D17: =(SUM('ACTUAL EXP'!$G$15,'ACTUAL EXP'!$G$17:$G$19,'ACTUAL EXP'!$G$22))*ALLOCATION!P21 -> 168333.57 | E17: =(('ACTUAL EXP'!$G$25)*(ALLOCATION!P21)) -> 0 | F17: ='ACTUAL EXP'!$G$28*ALLOCATION!P21 -> 0 | G17: 0 | H17: =SUM('ACTUAL EXP'!$G$30:$G$35)*ALLOCATION!P21 -> 151083.94 | I17: =SUM('ACTUAL EXP'!$G$43:$G$47)*ALLOCATION!P21 -> 91259.317 | J17: =(SUM('ACTUAL EXP'!$G$49:$G$50)*ALLOCATION!P21*0.5)+(SUM('ACTUAL EXP'!$G$49:$G$50)*ALLOCATION!P21*0.5) -> 43778.74 | K17: =SUM('ACTUAL EXP'!$G$52:$G$53)*ALLOCATION!P21 -> 46202.367 | L17: =SUM('ACTUAL EXP'!$G$54:$G$54)*ALLOCATION!P21 -> 6300.3228 | M17: =SUM('ACTUAL EXP'!$G$21:$G$21)*ALLOCATION!P21 -> 1941.4644 | N17: =SUM('ACTUAL EXP'!$G$58:$G$62)*0.39*ALLOCATION!P21 -> 30920.326 | O17: =SUM('ACTUAL EXP'!$G$58:$G$62)*0.27*ALLOCATION!P21 -> 21406.379 | P17: =SUM('ACTUAL EXP'!$G$58:$G$62)*0.34*ALLOCATION!P21 -> 26956.181 | Q17: ='ACTUAL EXP'!$G$85*ALLOCATION!P21 -> 41029.005 | R17: =SUM('ACTUAL EXP'!$G$68:$G$73)*ALLOCATION!P21 -> 111906.37 | S17: =SUM('ACTUAL EXP'!$G$75)*ALLOCATION!P21 -> 15672.116 | T17: =SUM('ACTUAL EXP'!$G$77)*ALLOCATION!P21 -> 10290.248 | U17: =SUM('ACTUAL EXP'!$G$79)*ALLOCATION!P21 -> 15594.755 | V17: =SUM(C17:U17) -> 887045.75 | W17: =-(H17/$H$111)*($W$117) -> 7989.2656 | X17: =-(Q17/$Q$111)*($X$118) -> 5849.6527 | Y17: =-(SUM(J17:O17,R17:U17)/SUM($J$111:$O$111,$R$111:$U$111))*$Y$119 -> 18651.609 | Z17: =-(C17/$C$111)*($Z$120) -> 7650.1404 | AA17: =-(I17/$I$111)*($AA$121) -> 2978.3332 | AB17: =-(SUM(D17:G17)/SUM($D$111:$G$111))*SUM($AB$117:$AB$122) -> 6480.6822 | AC17: =SUM(V17:AB17) -> 936645.43 | AD17: =SUM('ACTUAL EXP'!$G$37:$G$39)*ALLOCATION!P21 -> 18349.659 | AE17: =(AD17/$AD$111)*SUM($AD$117:$AD$122) -> 1026.0319 | AF17: =SUM('ACTUAL EXP'!$G$41)*ALLOCATION!P21 -> 5490.0208 | AG17: =(AF17/$AF$111)*SUM($AF$117:$AF$122) -> 306.97773 | AH17: =SUM('ACTUAL EXP'!$G$81)*ALLOCATION!P21 -> 2286.8072 | AI17: =(AH17/$AH$111)*SUM($AH$117:$AH$122) -> 127.86817 | AJ17: =SUM('ACTUAL EXP'!$G$83)*ALLOCATION!P21 -> 16978.77 | AK17: =(AJ17/$AH$111)*SUM($AH$117:$AH$122) -> 949.37787 | AL17: =SUM('ACTUAL EXP'!$G$64:$G$66)*ALLOCATION!P21 -> 5482.7186 | AM17: =(AL17/$AL$111)*SUM($AL$117:$AL$122) -> 306.56943 | AN17: =SUM(AC17:AM17) -> 987950.23 | AO17: =-AN17 -> -987950.23 | AP17: (A) | AQ17: =SUM(AO17,AN17) -> 0 | AS17: =AQ17-AR17 -> 0 | AT17: LEGEND FOR
A18: =ALLOCATION!A22 -> 609000 | B18: =ALLOCATION!C22 -> Sewer Sys Debt Rdmpt | C18: ='ACTUAL EXP'!$G$13*(ALLOCATION!P22) -> 70953.354 | D18: =(SUM('ACTUAL EXP'!$G$15,'ACTUAL EXP'!$G$17:$G$19,'ACTUAL EXP'!$G$22))*ALLOCATION!P22 -> 114436.69 | E18: =(('ACTUAL EXP'!$G$25)*(ALLOCATION!P22)) -> 0 | F18: ='ACTUAL EXP'!$G$28*ALLOCATION!P22 -> 0 | G18: 0 | H18: =SUM('ACTUAL EXP'!$G$30:$G$35)*ALLOCATION!P22 -> 102710.03 | I18: =SUM('ACTUAL EXP'!$G$43:$G$47)*ALLOCATION!P22 -> 62039.999 | J18: =(SUM('ACTUAL EXP'!$G$49:$G$50)*ALLOCATION!P22*0.5)+(SUM('ACTUAL EXP'!$G$49:$G$50)*ALLOCATION!P22*0.5) -> 29761.706 | K18: =SUM('ACTUAL EXP'!$G$52:$G$53)*ALLOCATION!P22 -> 31409.339 | L18: =SUM('ACTUAL EXP'!$G$54:$G$54)*ALLOCATION!P22 -> 4283.0917 | M18: =SUM('ACTUAL EXP'!$G$21:$G$21)*ALLOCATION!P22 -> 1319.8482 | N18: =SUM('ACTUAL EXP'!$G$58:$G$62)*0.39*ALLOCATION!P22 -> 21020.286 | O18: =SUM('ACTUAL EXP'!$G$58:$G$62)*0.27*ALLOCATION!P22 -> 14552.506 | P18: =SUM('ACTUAL EXP'!$G$58:$G$62)*0.34*ALLOCATION!P22 -> 18325.378 | Q18: ='ACTUAL EXP'!$G$85*ALLOCATION!P22 -> 27892.379 | R18: =SUM('ACTUAL EXP'!$G$68:$G$73)*ALLOCATION!P22 -> 76076.302 | S18: =SUM('ACTUAL EXP'!$G$75)*ALLOCATION!P22 -> 10654.234 | T18: =SUM('ACTUAL EXP'!$G$77)*ALLOCATION!P22 -> 6995.5266 | U18: =SUM('ACTUAL EXP'!$G$79)*ALLOCATION!P22 -> 10601.642 | V18: =SUM(C18:U18) -> 603032.32 | W18: =-(H18/$H$111)*($W$117) -> 5431.2704 | X18: =-(Q18/$Q$111)*($X$118) -> 3976.7167 | Y18: =-(SUM(J18:O18,R18:U18)/SUM($J$111:$O$111,$R$111:$U$111))*$Y$119 -> 12679.756 | Z18: =-(C18/$C$111)*($Z$120) -> 5200.726 | AA18: =-(I18/$I$111)*($AA$121) -> 2024.7334 | AB18: =-(SUM(D18:G18)/SUM($D$111:$G$111))*SUM($AB$117:$AB$122) -> 4405.7038 | AC18: =SUM(V18:AB18) -> 636751.23 | AD18: =SUM('ACTUAL EXP'!$G$37:$G$39)*ALLOCATION!P22 -> 12474.483 | AE18: =(AD18/$AD$111)*SUM($AD$117:$AD$122) -> 697.51805 | AF18: =SUM('ACTUAL EXP'!$G$41)*ALLOCATION!P22 -> 3732.2314 | AG18: =(AF18/$AF$111)*SUM($AF$117:$AF$122) -> 208.68991 | AH18: =SUM('ACTUAL EXP'!$G$81)*ALLOCATION!P22 -> 1554.6195 | AI18: =(AH18/$AH$111)*SUM($AH$117:$AH$122) -> 86.927464 | AJ18: =SUM('ACTUAL EXP'!$G$83)*ALLOCATION!P22 -> 11542.524 | AK18: =(AJ18/$AH$111)*SUM($AH$117:$AH$122) -> 645.407 | AL18: =SUM('ACTUAL EXP'!$G$64:$G$66)*ALLOCATION!P22 -> 3727.2672 | AM18: =(AL18/$AL$111)*SUM($AL$117:$AL$122) -> 208.41233 | AN18: =SUM(AC18:AM18) -> 671629.31 | AO18: =-AN18 -> -671629.31 | AP18: (A) | AQ18: =SUM(AO18,AN18) -> 0 | AS18: =AQ18-AR18 -> 0 | AT18: ADJUSTMENT
A19: =ALLOCATION!A23 -> 602000 | B19: =ALLOCATION!C23 -> Water | C19: ='ACTUAL EXP'!$G$13*(ALLOCATION!P23) -> 431550.26 | D19: =(SUM('ACTUAL EXP'!$G$15,'ACTUAL EXP'!$G$17:$G$19,'ACTUAL EXP'!$G$22))*ALLOCATION!P23 -> 696023.26 | E19: =(('ACTUAL EXP'!$G$25)*(ALLOCATION!P23)) -> 0 | F19: ='ACTUAL EXP'!$G$28*ALLOCATION!P23 -> 0 | G19: 0 | H19: =SUM('ACTUAL EXP'!$G$30:$G$35)*ALLOCATION!P23 -> 624699.74 | I19: =SUM('ACTUAL EXP'!$G$43:$G$47)*ALLOCATION!P23 -> 377337.73 | J19: =(SUM('ACTUAL EXP'!$G$49:$G$50)*ALLOCATION!P23*0.5)+(SUM('ACTUAL EXP'!$G$49:$G$50)*ALLOCATION!P23*0.5) -> 181015.71 | K19: =SUM('ACTUAL EXP'!$G$52:$G$53)*ALLOCATION!P23 -> 191036.89 | L19: =SUM('ACTUAL EXP'!$G$54:$G$54)*ALLOCATION!P23 -> 26050.486 | M19: =SUM('ACTUAL EXP'!$G$21:$G$21)*ALLOCATION!P23 -> 8027.5393 | N19: =SUM('ACTUAL EXP'!$G$58:$G$62)*0.39*ALLOCATION!P23 -> 127848.92 | O19: =SUM('ACTUAL EXP'!$G$58:$G$62)*0.27*ALLOCATION!P23 -> 88510.794 | P19: =SUM('ACTUAL EXP'!$G$58:$G$62)*0.34*ALLOCATION!P23 -> 111458.04 | Q19: ='ACTUAL EXP'!$G$85*ALLOCATION!P23 -> 169646.15 | R19: =SUM('ACTUAL EXP'!$G$68:$G$73)*ALLOCATION!P23 -> 462708.89 | S19: =SUM('ACTUAL EXP'!$G$75)*ALLOCATION!P23 -> 64800.845 | T19: =SUM('ACTUAL EXP'!$G$77)*ALLOCATION!P23 -> 42547.972 | U19: =SUM('ACTUAL EXP'!$G$79)*ALLOCATION!P23 -> 64480.973 | V19: =SUM(C19:U19) -> 3667744.2 | W19: =-(H19/$H$111)*($W$117) -> 33033.902 | X19: =-(Q19/$Q$111)*($X$118) -> 24187.061 | Y19: =-(SUM(J19:O19,R19:U19)/SUM($J$111:$O$111,$R$111:$U$111))*$Y$119 -> 77120.411 | Z19: =-(C19/$C$111)*($Z$120) -> 31631.692 | AA19: =-(I19/$I$111)*($AA$121) -> 12314.77 | AB19: =-(SUM(D19:G19)/SUM($D$111:$G$111))*SUM($AB$117:$AB$122) -> 26796.233 | AC19: =SUM(V19:AB19) -> 3872828.3 | AD19: =SUM('ACTUAL EXP'!$G$37:$G$39)*ALLOCATION!P23 -> 75871.91 | AE19: =(AD19/$AD$111)*SUM($AD$117:$AD$122) -> 4242.4223 | AF19: =SUM('ACTUAL EXP'!$G$41)*ALLOCATION!P23 -> 22700.06 | AG19: =(AF19/$AF$111)*SUM($AF$117:$AF$122) -> 1269.2872 | AH19: =SUM('ACTUAL EXP'!$G$81)*ALLOCATION!P23 -> 9455.4581 | AI19: =(AH19/$AH$111)*SUM($AH$117:$AH$122) -> 528.70749 | AJ19: =SUM('ACTUAL EXP'!$G$83)*ALLOCATION!P23 -> 70203.577 | AK19: =(AJ19/$AH$111)*SUM($AH$117:$AH$122) -> 3925.4742 | AL19: =SUM('ACTUAL EXP'!$G$64:$G$66)*ALLOCATION!P23 -> 22669.867 | AM19: =(AL19/$AL$111)*SUM($AL$117:$AL$122) -> 1267.5989 | AN19: =SUM(AC19:AM19) -> 4084962.6 | AO19: =-AO20-AO21-AO74-AO87 -> 448283.38 | AP19: B | AQ19: =SUM(AO19,AN19) -> 4533246 | AS19: =AQ19-AR19 -> 4533246 | AT19: CODE
A20: =ALLOCATION!A24 -> 615000 | B20: =ALLOCATION!C24 -> Water Construction | C20: ='ACTUAL EXP'!$G$13*(ALLOCATION!P24) -> 34083.28 | D20: =(SUM('ACTUAL EXP'!$G$15,'ACTUAL EXP'!$G$17:$G$19,'ACTUAL EXP'!$G$22))*ALLOCATION!P24 -> 54971.015 | E20: =(('ACTUAL EXP'!$G$25)*(ALLOCATION!P24)) -> 0 | F20: ='ACTUAL EXP'!$G$28*ALLOCATION!P24 -> 0 | G20: 0 | H20: =SUM('ACTUAL EXP'!$G$30:$G$35)*ALLOCATION!P24 -> 49337.975 | I20: =SUM('ACTUAL EXP'!$G$43:$G$47)*ALLOCATION!P24 -> 29801.645 | J20: =(SUM('ACTUAL EXP'!$G$49:$G$50)*ALLOCATION!P24*0.5)+(SUM('ACTUAL EXP'!$G$49:$G$50)*ALLOCATION!P24*0.5) -> 14296.386 | K20: =SUM('ACTUAL EXP'!$G$52:$G$53)*ALLOCATION!P24 -> 15087.846 | L20: =SUM('ACTUAL EXP'!$G$54:$G$54)*ALLOCATION!P24 -> 2057.4336 | M20: =SUM('ACTUAL EXP'!$G$21:$G$21)*ALLOCATION!P24 -> 634.00465 | N20: =SUM('ACTUAL EXP'!$G$58:$G$62)*0.39*ALLOCATION!P24 -> 10097.342 | O20: =SUM('ACTUAL EXP'!$G$58:$G$62)*0.27*ALLOCATION!P24 -> 6990.4677 | P20: =SUM('ACTUAL EXP'!$G$58:$G$62)*0.34*ALLOCATION!P24 -> 8802.8112 | Q20: ='ACTUAL EXP'!$G$85*ALLOCATION!P24 -> 13398.433 | R20: =SUM('ACTUAL EXP'!$G$68:$G$73)*ALLOCATION!P24 -> 36544.148 | S20: =SUM('ACTUAL EXP'!$G$75)*ALLOCATION!P24 -> 5117.8867 | T20: =SUM('ACTUAL EXP'!$G$77)*ALLOCATION!P24 -> 3360.3836 | U20: =SUM('ACTUAL EXP'!$G$79)*ALLOCATION!P24 -> 5092.6237 | V20: =SUM(C20:U20) -> 289673.68 | W20: =-(H20/$H$111)*($W$117) -> 2608.9748 | X20: =-(Q20/$Q$111)*($X$118) -> 1910.2627 | Y20: =-(SUM(J20:O20,R20:U20)/SUM($J$111:$O$111,$R$111:$U$111))*$Y$119 -> 6090.87 | Z20: =-(C20/$C$111)*($Z$120) -> 2498.23 | AA20: =-(I20/$I$111)*($AA$121) -> 972.60456 | AB20: =-(SUM(D20:G20)/SUM($D$111:$G$111))*SUM($AB$117:$AB$122) -> 2116.3317 | AC20: =SUM(V20:AB20) -> 305870.96 | AD20: =SUM('ACTUAL EXP'!$G$37:$G$39)*ALLOCATION!P24 -> 5992.265 | AE20: =(AD20/$AD$111)*SUM($AD$117:$AD$122) -> 335.06101 | AF20: =SUM('ACTUAL EXP'!$G$41)*ALLOCATION!P24 -> 1792.8213 | AG20: =(AF20/$AF$111)*SUM($AF$117:$AF$122) -> 100.24666 | AH20: =SUM('ACTUAL EXP'!$G$81)*ALLOCATION!P24 -> 746.77982 | AI20: =(AH20/$AH$111)*SUM($AH$117:$AH$122) -> 41.756632 | AJ20: =SUM('ACTUAL EXP'!$G$83)*ALLOCATION!P24 -> 5544.5875 | AK20: =(AJ20/$AH$111)*SUM($AH$117:$AH$122) -> 310.02886 | AL20: =SUM('ACTUAL EXP'!$G$64:$G$66)*ALLOCATION!P24 -> 1790.4367 | AM20: =(AL20/$AL$111)*SUM($AL$117:$AL$122) -> 100.11332 | AN20: =SUM(AC20:AM20) -> 322625.05 | AO20: =-AN20 -> -322625.05 | AP20: (B) | AQ20: =SUM(AO20,AN20) -> 0 | AS20: =AQ20-AR20 -> 0 | AT20: COLUMN
A21: =ALLOCATION!A25 -> 612000 | B21: =ALLOCATION!C25 -> Water Bond Sinking | C21: ='ACTUAL EXP'!$G$13*(ALLOCATION!P25) -> 13275.001 | D21: =(SUM('ACTUAL EXP'!$G$15,'ACTUAL EXP'!$G$17:$G$19,'ACTUAL EXP'!$G$22))*ALLOCATION!P25 -> 21410.507 | E21: =(('ACTUAL EXP'!$G$25)*(ALLOCATION!P25)) -> 0 | F21: ='ACTUAL EXP'!$G$28*ALLOCATION!P25 -> 0 | G21: 0 | H21: =SUM('ACTUAL EXP'!$G$30:$G$35)*ALLOCATION!P25 -> 19216.51 | I21: =SUM('ACTUAL EXP'!$G$43:$G$47)*ALLOCATION!P25 -> 11607.359 | J21: =(SUM('ACTUAL EXP'!$G$49:$G$50)*ALLOCATION!P25*0.5)+(SUM('ACTUAL EXP'!$G$49:$G$50)*ALLOCATION!P25*0.5) -> 5568.2595 | K21: =SUM('ACTUAL EXP'!$G$52:$G$53)*ALLOCATION!P25 -> 5876.523 | L21: =SUM('ACTUAL EXP'!$G$54:$G$54)*ALLOCATION!P25 -> 801.34405 | M21: =SUM('ACTUAL EXP'!$G$21:$G$21)*ALLOCATION!P25 -> 246.9367 | N21: =SUM('ACTUAL EXP'!$G$58:$G$62)*0.39*ALLOCATION!P25 -> 3932.7856 | O21: =SUM('ACTUAL EXP'!$G$58:$G$62)*0.27*ALLOCATION!P25 -> 2722.6977 | P21: =SUM('ACTUAL EXP'!$G$58:$G$62)*0.34*ALLOCATION!P25 -> 3428.5823 | Q21: ='ACTUAL EXP'!$G$85*ALLOCATION!P25 -> 5218.5182 | R21: =SUM('ACTUAL EXP'!$G$68:$G$73)*ALLOCATION!P25 -> 14233.478 | S21: =SUM('ACTUAL EXP'!$G$75)*ALLOCATION!P25 -> 1993.3514 | T21: =SUM('ACTUAL EXP'!$G$77)*ALLOCATION!P25 -> 1308.8264 | U21: =SUM('ACTUAL EXP'!$G$79)*ALLOCATION!P25 -> 1983.5117 | V21: =SUM(C21:U21) -> 112824.19 | W21: =-(H21/$H$111)*($W$117) -> 1016.1623 | X21: =-(Q21/$Q$111)*($X$118) -> 744.02289 | Y21: =-(SUM(J21:O21,R21:U21)/SUM($J$111:$O$111,$R$111:$U$111))*$Y$119 -> 2372.3159 | Z21: =-(C21/$C$111)*($Z$120) -> 973.02863 | AA21: =-(I21/$I$111)*($AA$121) -> 378.81703 | AB21: =-(SUM(D21:G21)/SUM($D$111:$G$111))*SUM($AB$117:$AB$122) -> 824.28412 | AC21: =SUM(V21:AB21) -> 119132.82 | AD21: =SUM('ACTUAL EXP'!$G$37:$G$39)*ALLOCATION!P25 -> 2333.9106 | AE21: =(AD21/$AD$111)*SUM($AD$117:$AD$122) -> 130.50198 | AF21: =SUM('ACTUAL EXP'!$G$41)*ALLOCATION!P25 -> 698.28097 | AG21: =(AF21/$AF$111)*SUM($AF$117:$AF$122) -> 39.04479 | AH21: =SUM('ACTUAL EXP'!$G$81)*ALLOCATION!P25 -> 290.86118 | AI21: =(AH21/$AH$111)*SUM($AH$117:$AH$122) -> 16.263674 | AJ21: =SUM('ACTUAL EXP'!$G$83)*ALLOCATION!P25 -> 2159.5459 | AK21: =(AJ21/$AH$111)*SUM($AH$117:$AH$122) -> 120.75227 | AL21: =SUM('ACTUAL EXP'!$G$64:$G$66)*ALLOCATION!P25 -> 697.35219 | AM21: =(AL21/$AL$111)*SUM($AL$117:$AL$122) -> 38.992857 | AN21: =SUM(AC21:AM21) -> 125658.33 | AO21: =-AN21 -> -125658.33 | AP21: (B) | AQ21: =SUM(AO21,AN21) -> 0 | AS21: =AQ21-AR21 -> 0
A22: =ALLOCATION!A26 -> 607000 | B22: =ALLOCATION!C26 -> Spectator Fac Op | C22: ='ACTUAL EXP'!$G$13*(ALLOCATION!P26) -> 20902.107 | D22: =(SUM('ACTUAL EXP'!$G$15,'ACTUAL EXP'!$G$17:$G$19,'ACTUAL EXP'!$G$22))*ALLOCATION!P26 -> 33711.839 | E22: =(('ACTUAL EXP'!$G$25)*(ALLOCATION!P26)) -> 0 | F22: ='ACTUAL EXP'!$G$28*ALLOCATION!P26 -> 0 | G22: 0 | H22: =SUM('ACTUAL EXP'!$G$30:$G$35)*ALLOCATION!P26 -> 30257.289 | I22: =SUM('ACTUAL EXP'!$G$43:$G$47)*ALLOCATION!P26 -> 18276.327 | J22: =(SUM('ACTUAL EXP'!$G$49:$G$50)*ALLOCATION!P26*0.5)+(SUM('ACTUAL EXP'!$G$49:$G$50)*ALLOCATION!P26*0.5) -> 8767.4836 | K22: =SUM('ACTUAL EXP'!$G$52:$G$53)*ALLOCATION!P26 -> 9252.8589 | L22: =SUM('ACTUAL EXP'!$G$54:$G$54)*ALLOCATION!P26 -> 1261.7535 | M22: =SUM('ACTUAL EXP'!$G$21:$G$21)*ALLOCATION!P26 -> 388.81331 | N22: =SUM('ACTUAL EXP'!$G$58:$G$62)*0.39*ALLOCATION!P26 -> 6192.3539 | O22: =SUM('ACTUAL EXP'!$G$58:$G$62)*0.27*ALLOCATION!P26 -> 4287.0142 | P22: =SUM('ACTUAL EXP'!$G$58:$G$62)*0.34*ALLOCATION!P26 -> 5398.4624 | Q22: ='ACTUAL EXP'!$G$85*ALLOCATION!P26 -> 8216.7996 | R22: =SUM('ACTUAL EXP'!$G$68:$G$73)*ALLOCATION!P26 -> 22411.273 | S22: =SUM('ACTUAL EXP'!$G$75)*ALLOCATION!P26 -> 3138.6245 | T22: =SUM('ACTUAL EXP'!$G$77)*ALLOCATION!P26 -> 2060.8081 | U22: =SUM('ACTUAL EXP'!$G$79)*ALLOCATION!P26 -> 3123.1315 | V22: =SUM(C22:U22) -> 177646.94 | W22: =-(H22/$H$111)*($W$117) -> 1599.9948 | X22: =-(Q22/$Q$111)*($X$118) -> 1171.4986 | Y22: =-(SUM(J22:O22,R22:U22)/SUM($J$111:$O$111,$R$111:$U$111))*$Y$119 -> 3735.3218 | Z22: =-(C22/$C$111)*($Z$120) -> 1532.0788 | AA22: =-(I22/$I$111)*($AA$121) -> 596.46503 | AB22: =-(SUM(D22:G22)/SUM($D$111:$G$111))*SUM($AB$117:$AB$122) -> 1297.8737 | AC22: =SUM(V22:AB22) -> 187580.17 | AD22: =SUM('ACTUAL EXP'!$G$37:$G$39)*ALLOCATION!P26 -> 3674.8507 | AE22: =(AD22/$AD$111)*SUM($AD$117:$AD$122) -> 205.48143 | AF22: =SUM('ACTUAL EXP'!$G$41)*ALLOCATION!P26 -> 1099.4759 | AG22: =(AF22/$AF$111)*SUM($AF$117:$AF$122) -> 61.477838 | AH22: =SUM('ACTUAL EXP'!$G$81)*ALLOCATION!P26 -> 457.97446 | AI22: =(AH22/$AH$111)*SUM($AH$117:$AH$122) -> 25.607911 | AJ22: =SUM('ACTUAL EXP'!$G$83)*ALLOCATION!P26 -> 3400.3054 | AK22: =(AJ22/$AH$111)*SUM($AH$117:$AH$122) -> 190.13007 | AL22: =SUM('ACTUAL EXP'!$G$64:$G$66)*ALLOCATION!P26 -> 1098.0135 | AM22: =(AL22/$AL$111)*SUM($AL$117:$AL$122) -> 61.396066 | AN22: =SUM(AC22:AM22) -> 197854.88 | AQ22: =SUM(AO22,AN22) -> 197854.88 | AS22: =AQ22-AR22 -> 197854.88 | AT22: (A) Env. Svcs.
A23: =ALLOCATION!A27 -> 617000 | B23: =ALLOCATION!C27 -> Sewer Sys Rate Stblt | C23: ='ACTUAL EXP'!$G$13*(ALLOCATION!P27) -> 0 | D23: =(SUM('ACTUAL EXP'!$G$15,'ACTUAL EXP'!$G$17:$G$19,'ACTUAL EXP'!$G$22))*ALLOCATION!P27 -> 0 | E23: =(('ACTUAL EXP'!$G$25)*(ALLOCATION!P27)) -> 0 | F23: ='ACTUAL EXP'!$G$28*ALLOCATION!P27 -> 0 | G23: 0 | H23: =SUM('ACTUAL EXP'!$G$30:$G$35)*ALLOCATION!P27 -> 0 | I23: =SUM('ACTUAL EXP'!$G$43:$G$47)*ALLOCATION!P27 -> 0 | J23: =(SUM('ACTUAL EXP'!$G$49:$G$50)*ALLOCATION!P27*0.5)+(SUM('ACTUAL EXP'!$G$49:$G$50)*ALLOCATION!P27*0.5) -> 0 | K23: =SUM('ACTUAL EXP'!$G$52:$G$53)*ALLOCATION!P27 -> 0 | L23: =SUM('ACTUAL EXP'!$G$54:$G$54)*ALLOCATION!P27 -> 0 | M23: =SUM('ACTUAL EXP'!$G$21:$G$21)*ALLOCATION!P27 -> 0 | N23: =SUM('ACTUAL EXP'!$G$58:$G$62)*0.39*ALLOCATION!P27 -> 0 | O23: =SUM('ACTUAL EXP'!$G$58:$G$62)*0.27*ALLOCATION!P27 -> 0 | P23: =SUM('ACTUAL EXP'!$G$58:$G$62)*0.34*ALLOCATION!P27 -> 0 | Q23: ='ACTUAL EXP'!$G$85*ALLOCATION!P27 -> 0 | R23: =SUM('ACTUAL EXP'!$G$68:$G$73)*ALLOCATION!P27 -> 0 | S23: =SUM('ACTUAL EXP'!$G$75)*ALLOCATION!P27 -> 0 | T23: =SUM('ACTUAL EXP'!$G$77)*ALLOCATION!P27 -> 0 | U23: =SUM('ACTUAL EXP'!$G$79)*ALLOCATION!P27 -> 0 | V23: =SUM(C23:U23) -> 0 | W23: =-(H23/$H$111)*($W$117) -> 0 | X23: =-(Q23/$Q$111)*($X$118) -> 0 | Y23: =-(SUM(J23:O23,R23:U23)/SUM($J$111:$O$111,$R$111:$U$111))*$Y$119 -> 0 | Z23: =-(C23/$C$111)*($Z$120) -> 0 | AA23: =-(I23/$I$111)*($AA$121) -> 0 | AB23: =-(SUM(D23:G23)/SUM($D$111:$G$111))*SUM($AB$117:$AB$122) -> 0 | AC23: =SUM(V23:AB23) -> 0 | AD23: =SUM('ACTUAL EXP'!$G$37:$G$39)*ALLOCATION!P27 -> 0 | AE23: =(AD23/$AD$111)*SUM($AD$117:$AD$122) -> 0 | AF23: =SUM('ACTUAL EXP'!$G$41)*ALLOCATION!P27 -> 0 | AG23: =(AF23/$AF$111)*SUM($AF$117:$AF$122) -> 0 | AH23: =SUM('ACTUAL EXP'!$G$81)*ALLOCATION!P27 -> 0 | AI23: =(AH23/$AH$111)*SUM($AH$117:$AH$122) -> 0 | AJ23: =SUM('ACTUAL EXP'!$G$83)*ALLOCATION!P27 -> 0 | AK23: =(AJ23/$AH$111)*SUM($AH$117:$AH$122) -> 0 | AL23: =SUM('ACTUAL EXP'!$G$64:$G$66)*ALLOCATION!P27 -> 0 | AM23: =(AL23/$AL$111)*SUM($AL$117:$AL$122) -> 0 | AN23: =SUM(AC23:AM23) -> 0 | AO23: =-AN23 -> 0 | AP23: (A) | AQ23: =SUM(AO23,AN23) -> 0 | AS23: =AQ23-AR23 -> 0 | AT23: (B) Water
A24: =ALLOCATION!A28 -> 619000 | B24: =ALLOCATION!C28 -> Sewer Sys Safety Net | C24: ='ACTUAL EXP'!$G$13*(ALLOCATION!P28) -> 0 | D24: =(SUM('ACTUAL EXP'!$G$15,'ACTUAL EXP'!$G$17:$G$19,'ACTUAL EXP'!$G$22))*ALLOCATION!P28 -> 0 | E24: =(('ACTUAL EXP'!$G$25)*(ALLOCATION!P28)) -> 0 | F24: ='ACTUAL EXP'!$G$28*ALLOCATION!P28 -> 0 | G24: 0 | H24: =SUM('ACTUAL EXP'!$G$30:$G$35)*ALLOCATION!P28 -> 0 | I24: =SUM('ACTUAL EXP'!$G$43:$G$47)*ALLOCATION!P28 -> 0 | J24: =(SUM('ACTUAL EXP'!$G$49:$G$50)*ALLOCATION!P28*0.5)+(SUM('ACTUAL EXP'!$G$49:$G$50)*ALLOCATION!P28*0.5) -> 0 | K24: =SUM('ACTUAL EXP'!$G$52:$G$53)*ALLOCATION!P28 -> 0 | L24: =SUM('ACTUAL EXP'!$G$54:$G$54)*ALLOCATION!P28 -> 0 | M24: =SUM('ACTUAL EXP'!$G$21:$G$21)*ALLOCATION!P28 -> 0 | N24: =SUM('ACTUAL EXP'!$G$58:$G$62)*0.39*ALLOCATION!P28 -> 0 | O24: =SUM('ACTUAL EXP'!$G$58:$G$62)*0.27*ALLOCATION!P28 -> 0 | P24: =SUM('ACTUAL EXP'!$G$58:$G$62)*0.34*ALLOCATION!P28 -> 0 | Q24: ='ACTUAL EXP'!$G$85*ALLOCATION!P28 -> 0 | R24: =SUM('ACTUAL EXP'!$G$68:$G$73)*ALLOCATION!P28 -> 0 | S24: =SUM('ACTUAL EXP'!$G$75)*ALLOCATION!P28 -> 0 | T24: =SUM('ACTUAL EXP'!$G$77)*ALLOCATION!P28 -> 0 | U24: =SUM('ACTUAL EXP'!$G$79)*ALLOCATION!P28 -> 0 | V24: =SUM(C24:U24) -> 0 | W24: =-(H24/$H$111)*($W$117) -> 0 | X24: =-(Q24/$Q$111)*($X$118) -> 0 | Y24: =-(SUM(J24:O24,R24:U24)/SUM($J$111:$O$111,$R$111:$U$111))*$Y$119 -> 0 | Z24: =-(C24/$C$111)*($Z$120) -> 0 | AA24: =-(I24/$I$111)*($AA$121) -> 0 | AB24: =-(SUM(D24:G24)/SUM($D$111:$G$111))*SUM($AB$117:$AB$122) -> 0 | AC24: =SUM(V24:AB24) -> 0 | AD24: =SUM('ACTUAL EXP'!$G$37:$G$39)*ALLOCATION!P28 -> 0 | AE24: =(AD24/$AD$111)*SUM($AD$117:$AD$122) -> 0 | AF24: =SUM('ACTUAL EXP'!$G$41)*ALLOCATION!P28 -> 0 | AG24: =(AF24/$AF$111)*SUM($AF$117:$AF$122) -> 0 | AH24: =SUM('ACTUAL EXP'!$G$81)*ALLOCATION!P28 -> 0 | AI24: =(AH24/$AH$111)*SUM($AH$117:$AH$122) -> 0 | AJ24: =SUM('ACTUAL EXP'!$G$83)*ALLOCATION!P28 -> 0 | AK24: =(AJ24/$AH$111)*SUM($AH$117:$AH$122) -> 0 | AL24: =SUM('ACTUAL EXP'!$G$64:$G$66)*ALLOCATION!P28 -> 0 | AM24: =(AL24/$AL$111)*SUM($AL$117:$AL$122) -> 0 | AN24: =SUM(AC24:AM24) -> 0 | AO24: =-AN24 -> 0 | AP24: (A) | AQ24: =SUM(AO24,AN24) -> 0 | AS24: =AQ24-AR24 -> 0 | AT24: (C) PDOT
A25: =ALLOCATION!A29 -> 620000 | B25: =ALLOCATION!C29 -> Sewer Revolving Loan | C25: ='ACTUAL EXP'!$G$13*(ALLOCATION!P29) -> 0 | D25: =(SUM('ACTUAL EXP'!$G$15,'ACTUAL EXP'!$G$17:$G$19,'ACTUAL EXP'!$G$22))*ALLOCATION!P29 -> 0 | E25: =(('ACTUAL EXP'!$G$25)*(ALLOCATION!P29)) -> 0 | F25: ='ACTUAL EXP'!$G$28*ALLOCATION!P29 -> 0 | G25: 0 | H25: =SUM('ACTUAL EXP'!$G$30:$G$35)*ALLOCATION!P29 -> 0 | I25: =SUM('ACTUAL EXP'!$G$43:$G$47)*ALLOCATION!P29 -> 0 | J25: =(SUM('ACTUAL EXP'!$G$49:$G$50)*ALLOCATION!P29*0.5)+(SUM('ACTUAL EXP'!$G$49:$G$50)*ALLOCATION!P29*0.5) -> 0 | K25: =SUM('ACTUAL EXP'!$G$52:$G$53)*ALLOCATION!P29 -> 0 | L25: =SUM('ACTUAL EXP'!$G$54:$G$54)*ALLOCATION!P29 -> 0 | M25: =SUM('ACTUAL EXP'!$G$21:$G$21)*ALLOCATION!P29 -> 0 | N25: =SUM('ACTUAL EXP'!$G$58:$G$62)*0.39*ALLOCATION!P29 -> 0 | O25: =SUM('ACTUAL EXP'!$G$58:$G$62)*0.27*ALLOCATION!P29 -> 0 | P25: =SUM('ACTUAL EXP'!$G$58:$G$62)*0.34*ALLOCATION!P29 -> 0 | Q25: ='ACTUAL EXP'!$G$85*ALLOCATION!P29 -> 0 | R25: =SUM('ACTUAL EXP'!$G$68:$G$73)*ALLOCATION!P29 -> 0 | S25: =SUM('ACTUAL EXP'!$G$75)*ALLOCATION!P29 -> 0 | T25: =SUM('ACTUAL EXP'!$G$77)*ALLOCATION!P29 -> 0 | U25: =SUM('ACTUAL EXP'!$G$79)*ALLOCATION!P29 -> 0 | V25: =SUM(C25:U25) -> 0 | W25: =-(H25/$H$111)*($W$117) -> 0 | X25: =-(Q25/$Q$111)*($X$118) -> 0 | Y25: =-(SUM(J25:O25,R25:U25)/SUM($J$111:$O$111,$R$111:$U$111))*$Y$119 -> 0 | Z25: =-(C25/$C$111)*($Z$120) -> 0 | AA25: =-(I25/$I$111)*($AA$121) -> 0 | AB25: =-(SUM(D25:G25)/SUM($D$111:$G$111))*SUM($AB$117:$AB$122) -> 0 | AC25: =SUM(V25:AB25) -> 0 | AD25: =SUM('ACTUAL EXP'!$G$37:$G$39)*ALLOCATION!P29 -> 0 | AE25: =(AD25/$AD$111)*SUM($AD$117:$AD$122) -> 0 | AF25: =SUM('ACTUAL EXP'!$G$41)*ALLOCATION!P29 -> 0 | AG25: =(AF25/$AF$111)*SUM($AF$117:$AF$122) -> 0 | AH25: =SUM('ACTUAL EXP'!$G$81)*ALLOCATION!P29 -> 0 | AI25: =(AH25/$AH$111)*SUM($AH$117:$AH$122) -> 0 | AJ25: =SUM('ACTUAL EXP'!$G$83)*ALLOCATION!P29 -> 0 | AK25: =(AJ25/$AH$111)*SUM($AH$117:$AH$122) -> 0 | AL25: =SUM('ACTUAL EXP'!$G$64:$G$66)*ALLOCATION!P29 -> 0 | AM25: =(AL25/$AL$111)*SUM($AL$117:$AL$122) -> 0 | AN25: =SUM(AC25:AM25) -> 0 | AO25: =-AN25 -> 0 | AP25: (A) | AQ25: =SUM(AO25,AN25) -> 0 | AS25: =AQ25-AR25 -> 0 | AT25: (D) FPD&R
A26: =ALLOCATION!A30 -> 802000 | B26: =ALLOCATION!C30 -> F&P Suppl Retir Rsrv | C26: ='ACTUAL EXP'!$G$13*(ALLOCATION!P30) -> 0 | D26: =(SUM('ACTUAL EXP'!$G$15,'ACTUAL EXP'!$G$17:$G$19,'ACTUAL EXP'!$G$22))*ALLOCATION!P30 -> 0 | E26: =(('ACTUAL EXP'!$G$25)*(ALLOCATION!P30)) -> 0 | F26: ='ACTUAL EXP'!$G$28*ALLOCATION!P30 -> 0 | G26: 0 | H26: =SUM('ACTUAL EXP'!$G$30:$G$35)*ALLOCATION!P30 -> 0 | I26: =SUM('ACTUAL EXP'!$G$43:$G$47)*ALLOCATION!P30 -> 0 | J26: =(SUM('ACTUAL EXP'!$G$49:$G$50)*ALLOCATION!P30*0.5)+(SUM('ACTUAL EXP'!$G$49:$G$50)*ALLOCATION!P30*0.5) -> 0 | K26: =SUM('ACTUAL EXP'!$G$52:$G$53)*ALLOCATION!P30 -> 0 | L26: =SUM('ACTUAL EXP'!$G$54:$G$54)*ALLOCATION!P30 -> 0 | M26: =SUM('ACTUAL EXP'!$G$21:$G$21)*ALLOCATION!P30 -> 0 | N26: =SUM('ACTUAL EXP'!$G$58:$G$62)*0.39*ALLOCATION!P30 -> 0 | O26: =SUM('ACTUAL EXP'!$G$58:$G$62)*0.27*ALLOCATION!P30 -> 0 | P26: =SUM('ACTUAL EXP'!$G$58:$G$62)*0.34*ALLOCATION!P30 -> 0 | Q26: ='ACTUAL EXP'!$G$85*ALLOCATION!P30 -> 0 | R26: =SUM('ACTUAL EXP'!$G$68:$G$73)*ALLOCATION!P30 -> 0 | S26: =SUM('ACTUAL EXP'!$G$75)*ALLOCATION!P30 -> 0 | T26: =SUM('ACTUAL EXP'!$G$77)*ALLOCATION!P30 -> 0 | U26: =SUM('ACTUAL EXP'!$G$79)*ALLOCATION!P30 -> 0 | V26: =SUM(C26:U26) -> 0 | W26: =-(H26/$H$111)*($W$117) -> 0 | X26: =-(Q26/$Q$111)*($X$118) -> 0 | Y26: =-(SUM(J26:O26,R26:U26)/SUM($J$111:$O$111,$R$111:$U$111))*$Y$119 -> 0 | Z26: =-(C26/$C$111)*($Z$120) -> 0 | AA26: =-(I26/$I$111)*($AA$121) -> 0 | AB26: =-(SUM(D26:G26)/SUM($D$111:$G$111))*SUM($AB$117:$AB$122) -> 0 | AC26: =SUM(V26:AB26) -> 0 | AD26: =SUM('ACTUAL EXP'!$G$37:$G$39)*ALLOCATION!P30 -> 0 | AE26: =(AD26/$AD$111)*SUM($AD$117:$AD$122) -> 0 | AF26: =SUM('ACTUAL EXP'!$G$41)*ALLOCATION!P30 -> 0 | AG26: =(AF26/$AF$111)*SUM($AF$117:$AF$122) -> 0 | AH26: =SUM('ACTUAL EXP'!$G$81)*ALLOCATION!P30 -> 0 | AI26: =(AH26/$AH$111)*SUM($AH$117:$AH$122) -> 0 | AJ26: =SUM('ACTUAL EXP'!$G$83)*ALLOCATION!P30 -> 0 | AK26: =(AJ26/$AH$111)*SUM($AH$117:$AH$122) -> 0 | AL26: =SUM('ACTUAL EXP'!$G$64:$G$66)*ALLOCATION!P30 -> 0 | AM26: =(AL26/$AL$111)*SUM($AL$117:$AL$122) -> 0 | AN26: =SUM(AC26:AM26) -> 0 | AO26: =-AN26 -> 0 | AP26: (Z) | AQ26: =SUM(AO26,AN26) -> 0 | AS26: =AQ26-AR26 -> 0 | AT26: (E) PDC
A27: =ALLOCATION!A31 -> 800000 | B27: =ALLOCATION!C31 -> FPDR | C27: ='ACTUAL EXP'!$G$13*(ALLOCATION!P31) -> 10235.021 | D27: =(SUM('ACTUAL EXP'!$G$15,'ACTUAL EXP'!$G$17:$G$19,'ACTUAL EXP'!$G$22))*ALLOCATION!P31 -> 16507.493 | E27: =(('ACTUAL EXP'!$G$25)*(ALLOCATION!P31)) -> 0 | F27: ='ACTUAL EXP'!$G$28*ALLOCATION!P31 -> 0 | G27: 0 | H27: =SUM('ACTUAL EXP'!$G$30:$G$35)*ALLOCATION!P31 -> 14815.922 | I27: =SUM('ACTUAL EXP'!$G$43:$G$47)*ALLOCATION!P31 -> 8949.2697 | J27: =(SUM('ACTUAL EXP'!$G$49:$G$50)*ALLOCATION!P31*0.5)+(SUM('ACTUAL EXP'!$G$49:$G$50)*ALLOCATION!P31*0.5) -> 4293.126 | K27: =SUM('ACTUAL EXP'!$G$52:$G$53)*ALLOCATION!P31 -> 4530.7971 | L27: =SUM('ACTUAL EXP'!$G$54:$G$54)*ALLOCATION!P31 -> 617.83596 | M27: =SUM('ACTUAL EXP'!$G$21:$G$21)*ALLOCATION!P31 -> 190.3881 | N27: =SUM('ACTUAL EXP'!$G$58:$G$62)*0.39*ALLOCATION!P31 -> 3032.1762 | O27: =SUM('ACTUAL EXP'!$G$58:$G$62)*0.27*ALLOCATION!P31 -> 2099.1989 | P27: =SUM('ACTUAL EXP'!$G$58:$G$62)*0.34*ALLOCATION!P31 -> 2643.4357 | Q27: ='ACTUAL EXP'!$G$85*ALLOCATION!P31 -> 4023.4756 | R27: =SUM('ACTUAL EXP'!$G$68:$G$73)*ALLOCATION!P31 -> 10974.006 | S27: =SUM('ACTUAL EXP'!$G$75)*ALLOCATION!P31 -> 1536.8732 | T27: =SUM('ACTUAL EXP'!$G$77)*ALLOCATION!P31 -> 1009.1047 | U27: =SUM('ACTUAL EXP'!$G$79)*ALLOCATION!P31 -> 1529.2868 | V27: =SUM(C27:U27) -> 86987.41 | W27: =-(H27/$H$111)*($W$117) -> 783.46074 | X27: =-(Q27/$Q$111)*($X$118) -> 573.64137 | Y27: =-(SUM(J27:O27,R27:U27)/SUM($J$111:$O$111,$R$111:$U$111))*$Y$119 -> 1829.0547 | Z27: =-(C27/$C$111)*($Z$120) -> 750.20471 | AA27: =-(I27/$I$111)*($AA$121) -> 292.06779 | AB27: =-(SUM(D27:G27)/SUM($D$111:$G$111))*SUM($AB$117:$AB$122) -> 635.52275 | AC27: =SUM(V27:AB27) -> 91851.362 | AD27: =SUM('ACTUAL EXP'!$G$37:$G$39)*ALLOCATION!P31 -> 1799.4442 | AE27: =(AD27/$AD$111)*SUM($AD$117:$AD$122) -> 100.61698 | AF27: =SUM('ACTUAL EXP'!$G$41)*ALLOCATION!P31 -> 538.37436 | AG27: =(AF27/$AF$111)*SUM($AF$117:$AF$122) -> 30.103518 | AH27: =SUM('ACTUAL EXP'!$G$81)*ALLOCATION!P31 -> 224.25386 | AI27: =(AH27/$AH$111)*SUM($AH$117:$AH$122) -> 12.539286 | AJ27: =SUM('ACTUAL EXP'!$G$83)*ALLOCATION!P31 -> 1665.0091 | AK27: =(AJ27/$AH$111)*SUM($AH$117:$AH$122) -> 93.099958 | AL27: =SUM('ACTUAL EXP'!$G$64:$G$66)*ALLOCATION!P31 -> 537.65828 | AM27: =(AL27/$AL$111)*SUM($AL$117:$AL$122) -> 30.063478 | AN27: =SUM(AC27:AM27) -> 96882.525 | AO27: =-AO28 -> 0 | AP27: D | AQ27: =SUM(AO27,AN27) -> 96882.525 | AS27: =AQ27-AR27 -> 96882.525 | AT27: (F) Fire
A28: =ALLOCATION!A32 -> 801000 | B28: =ALLOCATION!C32 -> FPDR Reserve | C28: ='ACTUAL EXP'!$G$13*(ALLOCATION!P32) -> 0 | D28: =(SUM('ACTUAL EXP'!$G$15,'ACTUAL EXP'!$G$17:$G$19,'ACTUAL EXP'!$G$22))*ALLOCATION!P32 -> 0 | E28: =(('ACTUAL EXP'!$G$25)*(ALLOCATION!P32)) -> 0 | F28: ='ACTUAL EXP'!$G$28*ALLOCATION!P32 -> 0 | G28: 0 | H28: =SUM('ACTUAL EXP'!$G$30:$G$35)*ALLOCATION!P32 -> 0 | I28: =SUM('ACTUAL EXP'!$G$43:$G$47)*ALLOCATION!P32 -> 0 | J28: =(SUM('ACTUAL EXP'!$G$49:$G$50)*ALLOCATION!P32*0.5)+(SUM('ACTUAL EXP'!$G$49:$G$50)*ALLOCATION!P32*0.5) -> 0 | K28: =SUM('ACTUAL EXP'!$G$52:$G$53)*ALLOCATION!P32 -> 0 | L28: =SUM('ACTUAL EXP'!$G$54:$G$54)*ALLOCATION!P32 -> 0 | M28: =SUM('ACTUAL EXP'!$G$21:$G$21)*ALLOCATION!P32 -> 0 | N28: =SUM('ACTUAL EXP'!$G$58:$G$62)*0.39*ALLOCATION!P32 -> 0 | O28: =SUM('ACTUAL EXP'!$G$58:$G$62)*0.27*ALLOCATION!P32 -> 0 | P28: =SUM('ACTUAL EXP'!$G$58:$G$62)*0.34*ALLOCATION!P32 -> 0 | Q28: ='ACTUAL EXP'!$G$85*ALLOCATION!P32 -> 0 | R28: =SUM('ACTUAL EXP'!$G$68:$G$73)*ALLOCATION!P32 -> 0 | S28: =SUM('ACTUAL EXP'!$G$75)*ALLOCATION!P32 -> 0 | T28: =SUM('ACTUAL EXP'!$G$77)*ALLOCATION!P32 -> 0 | U28: =SUM('ACTUAL EXP'!$G$79)*ALLOCATION!P32 -> 0 | V28: =SUM(C28:U28) -> 0 | W28: =-(H28/$H$111)*($W$117) -> 0 | X28: =-(Q28/$Q$111)*($X$118) -> 0 | Y28: =-(SUM(J28:O28,R28:U28)/SUM($J$111:$O$111,$R$111:$U$111))*$Y$119 -> 0 | Z28: =-(C28/$C$111)*($Z$120) -> 0 | AA28: =-(I28/$I$111)*($AA$121) -> 0 | AB28: =-(SUM(D28:G28)/SUM($D$111:$G$111))*SUM($AB$117:$AB$122) -> 0 | AC28: =SUM(V28:AB28) -> 0 | AD28: =SUM('ACTUAL EXP'!$G$37:$G$39)*ALLOCATION!P32 -> 0 | AE28: =(AD28/$AD$111)*SUM($AD$117:$AD$122) -> 0 | AF28: =SUM('ACTUAL EXP'!$G$41)*ALLOCATION!P32 -> 0 | AG28: =(AF28/$AF$111)*SUM($AF$117:$AF$122) -> 0 | AH28: =SUM('ACTUAL EXP'!$G$81)*ALLOCATION!P32 -> 0 | AI28: =(AH28/$AH$111)*SUM($AH$117:$AH$122) -> 0 | AJ28: =SUM('ACTUAL EXP'!$G$83)*ALLOCATION!P32 -> 0 | AK28: =(AJ28/$AH$111)*SUM($AH$117:$AH$122) -> 0 | AL28: =SUM('ACTUAL EXP'!$G$64:$G$66)*ALLOCATION!P32 -> 0 | AM28: =(AL28/$AL$111)*SUM($AL$117:$AL$122) -> 0 | AN28: =SUM(AC28:AM28) -> 0 | AO28: =-AN28 -> 0 | AP28: (D) | AQ28: =SUM(AO28,AN28) -> 0 | AS28: =AQ28-AR28 -> 0 | AT28: (G) Golf
A29: =ALLOCATION!A33 -> 211000 | B29: =ALLOCATION!C33 -> Spec Fin & Resource | C29: ='ACTUAL EXP'!$G$13*(ALLOCATION!P33) -> 0 | D29: =(SUM('ACTUAL EXP'!$G$15,'ACTUAL EXP'!$G$17:$G$19,'ACTUAL EXP'!$G$22))*ALLOCATION!P33 -> 0 | E29: =(('ACTUAL EXP'!$G$25)*(ALLOCATION!P33)) -> 0 | F29: ='ACTUAL EXP'!$G$28*ALLOCATION!P33 -> 0 | G29: 0 | H29: =SUM('ACTUAL EXP'!$G$30:$G$35)*ALLOCATION!P33 -> 0 | I29: =SUM('ACTUAL EXP'!$G$43:$G$47)*ALLOCATION!P33 -> 0 | J29: =(SUM('ACTUAL EXP'!$G$49:$G$50)*ALLOCATION!P33*0.5)+(SUM('ACTUAL EXP'!$G$49:$G$50)*ALLOCATION!P33*0.5) -> 0 | K29: =SUM('ACTUAL EXP'!$G$52:$G$53)*ALLOCATION!P33 -> 0 | L29: =SUM('ACTUAL EXP'!$G$54:$G$54)*ALLOCATION!P33 -> 0 | M29: =SUM('ACTUAL EXP'!$G$21:$G$21)*ALLOCATION!P33 -> 0 | N29: =SUM('ACTUAL EXP'!$G$58:$G$62)*0.39*ALLOCATION!P33 -> 0 | O29: =SUM('ACTUAL EXP'!$G$58:$G$62)*0.27*ALLOCATION!P33 -> 0 | P29: =SUM('ACTUAL EXP'!$G$58:$G$62)*0.34*ALLOCATION!P33 -> 0 | Q29: ='ACTUAL EXP'!$G$85*ALLOCATION!P33 -> 0 | R29: =SUM('ACTUAL EXP'!$G$68:$G$73)*ALLOCATION!P33 -> 0 | S29: =SUM('ACTUAL EXP'!$G$75)*ALLOCATION!P33 -> 0 | T29: =SUM('ACTUAL EXP'!$G$77)*ALLOCATION!P33 -> 0 | U29: =SUM('ACTUAL EXP'!$G$79)*ALLOCATION!P33 -> 0 | V29: =SUM(C29:U29) -> 0 | W29: =-(H29/$H$111)*($W$117) -> 0 | X29: =-(Q29/$Q$111)*($X$118) -> 0 | Y29: =-(SUM(J29:O29,R29:U29)/SUM($J$111:$O$111,$R$111:$U$111))*$Y$119 -> 0 | Z29: =-(C29/$C$111)*($Z$120) -> 0 | AA29: =-(I29/$I$111)*($AA$121) -> 0 | AB29: =-(SUM(D29:G29)/SUM($D$111:$G$111))*SUM($AB$117:$AB$122) -> 0 | AC29: =SUM(V29:AB29) -> 0 | AD29: =SUM('ACTUAL EXP'!$G$37:$G$39)*ALLOCATION!P33 -> 0 | AE29: =(AD29/$AD$111)*SUM($AD$117:$AD$122) -> 0 | AF29: =SUM('ACTUAL EXP'!$G$41)*ALLOCATION!P33 -> 0 | AG29: =(AF29/$AF$111)*SUM($AF$117:$AF$122) -> 0 | AH29: =SUM('ACTUAL EXP'!$G$81)*ALLOCATION!P33 -> 0 | AI29: =(AH29/$AH$111)*SUM($AH$117:$AH$122) -> 0 | AJ29: =SUM('ACTUAL EXP'!$G$83)*ALLOCATION!P33 -> 0 | AK29: =(AJ29/$AH$111)*SUM($AH$117:$AH$122) -> 0 | AL29: =SUM('ACTUAL EXP'!$G$64:$G$66)*ALLOCATION!P33 -> 0 | AM29: =(AL29/$AL$111)*SUM($AL$117:$AL$122) -> 0 | AN29: =SUM(AC29:AM29) -> 0 | AO29: =-AN29 -> 0 | AP29: (Z) | AQ29: =SUM(AO29,AN29) -> 0 | AS29: =AQ29-AR29 -> 0 | AT29: (H) Hydro
A30: =ALLOCATION!A34 -> 217000 | B30: =ALLOCATION!C34 -> Grants | C30: ='ACTUAL EXP'!$G$13*(ALLOCATION!P34) -> 0 | D30: =(SUM('ACTUAL EXP'!$G$15,'ACTUAL EXP'!$G$17:$G$19,'ACTUAL EXP'!$G$22))*ALLOCATION!P34 -> 0 | E30: =(('ACTUAL EXP'!$G$25)*(ALLOCATION!P34)) -> 0 | F30: ='ACTUAL EXP'!$G$28*ALLOCATION!P34 -> 0 | G30: 0 | H30: =SUM('ACTUAL EXP'!$G$30:$G$35)*ALLOCATION!P34 -> 0 | I30: =SUM('ACTUAL EXP'!$G$43:$G$47)*ALLOCATION!P34 -> 0 | J30: =(SUM('ACTUAL EXP'!$G$49:$G$50)*ALLOCATION!P34*0.5)+(SUM('ACTUAL EXP'!$G$49:$G$50)*ALLOCATION!P34*0.5) -> 0 | K30: =SUM('ACTUAL EXP'!$G$52:$G$53)*ALLOCATION!P34 -> 0 | L30: =SUM('ACTUAL EXP'!$G$54:$G$54)*ALLOCATION!P34 -> 0 | M30: =SUM('ACTUAL EXP'!$G$21:$G$21)*ALLOCATION!P34 -> 0 | N30: =SUM('ACTUAL EXP'!$G$58:$G$62)*0.39*ALLOCATION!P34 -> 0 | O30: =SUM('ACTUAL EXP'!$G$58:$G$62)*0.27*ALLOCATION!P34 -> 0 | P30: =SUM('ACTUAL EXP'!$G$58:$G$62)*0.34*ALLOCATION!P34 -> 0 | Q30: ='ACTUAL EXP'!$G$85*ALLOCATION!P34 -> 0 | R30: =SUM('ACTUAL EXP'!$G$68:$G$73)*ALLOCATION!P34 -> 0 | S30: =SUM('ACTUAL EXP'!$G$75)*ALLOCATION!P34 -> 0 | T30: =SUM('ACTUAL EXP'!$G$77)*ALLOCATION!P34 -> 0 | U30: =SUM('ACTUAL EXP'!$G$79)*ALLOCATION!P34 -> 0 | V30: =SUM(C30:U30) -> 0 | W30: =-(H30/$H$111)*($W$117) -> 0 | X30: =-(Q30/$Q$111)*($X$118) -> 0 | Y30: =-(SUM(J30:O30,R30:U30)/SUM($J$111:$O$111,$R$111:$U$111))*$Y$119 -> 0 | Z30: =-(C30/$C$111)*($Z$120) -> 0 | AA30: =-(I30/$I$111)*($AA$121) -> 0 | AB30: =-(SUM(D30:G30)/SUM($D$111:$G$111))*SUM($AB$117:$AB$122) -> 0 | AC30: =SUM(V30:AB30) -> 0 | AD30: =SUM('ACTUAL EXP'!$G$37:$G$39)*ALLOCATION!P34 -> 0 | AE30: =(AD30/$AD$111)*SUM($AD$117:$AD$122) -> 0 | AF30: =SUM('ACTUAL EXP'!$G$41)*ALLOCATION!P34 -> 0 | AG30: =(AF30/$AF$111)*SUM($AF$117:$AF$122) -> 0 | AH30: =SUM('ACTUAL EXP'!$G$81)*ALLOCATION!P34 -> 0 | AI30: =(AH30/$AH$111)*SUM($AH$117:$AH$122) -> 0 | AJ30: =SUM('ACTUAL EXP'!$G$83)*ALLOCATION!P34 -> 0 | AK30: =(AJ30/$AH$111)*SUM($AH$117:$AH$122) -> 0 | AL30: =SUM('ACTUAL EXP'!$G$64:$G$66)*ALLOCATION!P34 -> 0 | AM30: =(AL30/$AL$111)*SUM($AL$117:$AL$122) -> 0 | AN30: =SUM(AC30:AM30) -> 0 | AO30: =-AN30 -> 0 | AP30: (Z) | AQ30: =SUM(AO30,AN30) -> 0 | AS30: =AQ30-AR30 -> 0 | AT30: (I) Parking
A31: =ALLOCATION!A35 -> 853000 | B31: =ALLOCATION!C35 -> PDC Accounts | C31: ='ACTUAL EXP'!$G$13*(ALLOCATION!P35) -> 15510.888 | D31: =(SUM('ACTUAL EXP'!$G$15,'ACTUAL EXP'!$G$17:$G$19,'ACTUAL EXP'!$G$22))*ALLOCATION!P35 -> 25016.643 | E31: =(('ACTUAL EXP'!$G$25)*(ALLOCATION!P35)) -> 0 | F31: ='ACTUAL EXP'!$G$28*ALLOCATION!P35 -> 0 | G31: 0 | H31: =SUM('ACTUAL EXP'!$G$30:$G$35)*ALLOCATION!P35 -> 22453.115 | I31: =SUM('ACTUAL EXP'!$G$43:$G$47)*ALLOCATION!P35 -> 13562.368 | J31: =(SUM('ACTUAL EXP'!$G$49:$G$50)*ALLOCATION!P35*0.5)+(SUM('ACTUAL EXP'!$G$49:$G$50)*ALLOCATION!P35*0.5) -> 6506.1123 | K31: =SUM('ACTUAL EXP'!$G$52:$G$53)*ALLOCATION!P35 -> 6866.2962 | L31: =SUM('ACTUAL EXP'!$G$54:$G$54)*ALLOCATION!P35 -> 936.31311 | M31: =SUM('ACTUAL EXP'!$G$21:$G$21)*ALLOCATION!P35 -> 288.52784 | N31: =SUM('ACTUAL EXP'!$G$58:$G$62)*0.39*ALLOCATION!P35 -> 4595.1782 | O31: =SUM('ACTUAL EXP'!$G$58:$G$62)*0.27*ALLOCATION!P35 -> 3181.2772 | P31: =SUM('ACTUAL EXP'!$G$58:$G$62)*0.34*ALLOCATION!P35 -> 4006.0528 | Q31: ='ACTUAL EXP'!$G$85*ALLOCATION!P35 -> 6097.4646 | R31: =SUM('ACTUAL EXP'!$G$68:$G$73)*ALLOCATION!P35 -> 16630.8 | S31: =SUM('ACTUAL EXP'!$G$75)*ALLOCATION!P35 -> 2329.0883 | T31: =SUM('ACTUAL EXP'!$G$77)*ALLOCATION!P35 -> 1529.2699 | U31: =SUM('ACTUAL EXP'!$G$79)*ALLOCATION!P35 -> 2317.5914 | V31: =SUM(C31:U31) -> 131826.99 | W31: =-(H31/$H$111)*($W$117) -> 1187.3128 | X31: =-(Q31/$Q$111)*($X$118) -> 869.33744 | Y31: =-(SUM(J31:O31,R31:U31)/SUM($J$111:$O$111,$R$111:$U$111))*$Y$119 -> 2771.8812 | Z31: =-(C31/$C$111)*($Z$120) -> 1136.9142 | AA31: =-(I31/$I$111)*($AA$121) -> 442.62056 | AB31: =-(SUM(D31:G31)/SUM($D$111:$G$111))*SUM($AB$117:$AB$122) -> 963.11695 | AC31: =SUM(V31:AB31) -> 139198.17 | AD31: =SUM('ACTUAL EXP'!$G$37:$G$39)*ALLOCATION!P35 -> 2727.0073 | AE31: =(AD31/$AD$111)*SUM($AD$117:$AD$122) -> 152.48221 | AF31: =SUM('ACTUAL EXP'!$G$41)*ALLOCATION!P35 -> 815.89129 | AG31: =(AF31/$AF$111)*SUM($AF$117:$AF$122) -> 45.62104 | AH31: =SUM('ACTUAL EXP'!$G$81)*ALLOCATION!P35 -> 339.85046 | AI31: =(AH31/$AH$111)*SUM($AH$117:$AH$122) -> 19.002938 | AJ31: =SUM('ACTUAL EXP'!$G$83)*ALLOCATION!P35 -> 2523.2746 | AK31: =(AJ31/$AH$111)*SUM($AH$117:$AH$122) -> 141.09038 | AL31: =SUM('ACTUAL EXP'!$G$64:$G$66)*ALLOCATION!P35 -> 814.80607 | AM31: =(AL31/$AL$111)*SUM($AL$117:$AL$122) -> 45.560359 | AN31: =SUM(AC31:AM31) -> 146822.76 | AQ31: =SUM(AO31,AN31) -> 146822.76 | AS31: =AQ31-AR31 -> 146822.76 | AT31: (K) Parks
A32: =ALLOCATION!A36 -> 204000 | B32: =ALLOCATION!C36 -> Property Mgt License | C32: ='ACTUAL EXP'!$G$13*(ALLOCATION!P36) -> 17352.072 | D32: =(SUM('ACTUAL EXP'!$G$15,'ACTUAL EXP'!$G$17:$G$19,'ACTUAL EXP'!$G$22))*ALLOCATION!P36 -> 27986.185 | E32: =(('ACTUAL EXP'!$G$25)*(ALLOCATION!P36)) -> 0 | F32: ='ACTUAL EXP'!$G$28*ALLOCATION!P36 -> 0 | G32: 0 | H32: =SUM('ACTUAL EXP'!$G$30:$G$35)*ALLOCATION!P36 -> 25118.359 | I32: =SUM('ACTUAL EXP'!$G$43:$G$47)*ALLOCATION!P36 -> 15172.257 | J32: =(SUM('ACTUAL EXP'!$G$49:$G$50)*ALLOCATION!P36*0.5)+(SUM('ACTUAL EXP'!$G$49:$G$50)*ALLOCATION!P36*0.5) -> 7278.4051 | K32: =SUM('ACTUAL EXP'!$G$52:$G$53)*ALLOCATION!P36 -> 7681.3437 | L32: =SUM('ACTUAL EXP'!$G$54:$G$54)*ALLOCATION!P36 -> 1047.456 | M32: =SUM('ACTUAL EXP'!$G$21:$G$21)*ALLOCATION!P36 -> 322.77686 | N32: =SUM('ACTUAL EXP'!$G$58:$G$62)*0.39*ALLOCATION!P36 -> 5140.6381 | O32: =SUM('ACTUAL EXP'!$G$58:$G$62)*0.27*ALLOCATION!P36 -> 3558.9033 | P32: =SUM('ACTUAL EXP'!$G$58:$G$62)*0.34*ALLOCATION!P36 -> 4481.5819 | Q32: ='ACTUAL EXP'!$G$85*ALLOCATION!P36 -> 6821.2498 | R32: =SUM('ACTUAL EXP'!$G$68:$G$73)*ALLOCATION!P36 -> 18604.919 | S32: =SUM('ACTUAL EXP'!$G$75)*ALLOCATION!P36 -> 2605.5572 | T32: =SUM('ACTUAL EXP'!$G$77)*ALLOCATION!P36 -> 1710.7983 | U32: =SUM('ACTUAL EXP'!$G$79)*ALLOCATION!P36 -> 2592.6956 | V32: =SUM(C32:U32) -> 147475.2 | W32: =-(H32/$H$111)*($W$117) -> 1328.25 | X32: =-(Q32/$Q$111)*($X$118) -> 972.5301 | Y32: =-(SUM(J32:O32,R32:U32)/SUM($J$111:$O$111,$R$111:$U$111))*$Y$119 -> 3100.9108 | Z32: =-(C32/$C$111)*($Z$120) -> 1271.869 | AA32: =-(I32/$I$111)*($AA$121) -> 495.16079 | AB32: =-(SUM(D32:G32)/SUM($D$111:$G$111))*SUM($AB$117:$AB$122) -> 1077.4415 | AC32: =SUM(V32:AB32) -> 155721.36 | AD32: =SUM('ACTUAL EXP'!$G$37:$G$39)*ALLOCATION!P36 -> 3050.7103 | AE32: =(AD32/$AD$111)*SUM($AD$117:$AD$122) -> 170.58225 | AF32: =SUM('ACTUAL EXP'!$G$41)*ALLOCATION!P36 -> 912.73974 | AG32: =(AF32/$AF$111)*SUM($AF$117:$AF$122) -> 51.036378 | AH32: =SUM('ACTUAL EXP'!$G$81)*ALLOCATION!P36 -> 380.1916 | AI32: =(AH32/$AH$111)*SUM($AH$117:$AH$122) -> 21.258637 | AJ32: =SUM('ACTUAL EXP'!$G$83)*ALLOCATION!P36 -> 2822.794 | AK32: =(AJ32/$AH$111)*SUM($AH$117:$AH$122) -> 157.83818 | AL32: =SUM('ACTUAL EXP'!$G$64:$G$66)*ALLOCATION!P36 -> 911.52571 | AM32: =(AL32/$AL$111)*SUM($AL$117:$AL$122) -> 50.968495 | AN32: =SUM(AC32:AM32) -> 164251.01 | AQ32: =SUM(AO32,AN32) -> 164251.01 | AS32: =AQ32-AR32 -> 164251.01 | AT32: (L) LID
A33: =ALLOCATION!A37 -> 201000 | B33: =ALLOCATION!C37 -> Assessmnt Collection | C33: ='ACTUAL EXP'!$G$13*(ALLOCATION!P37) -> 1.2390339 | D33: =(SUM('ACTUAL EXP'!$G$15,'ACTUAL EXP'!$G$17:$G$19,'ACTUAL EXP'!$G$22))*ALLOCATION!P37 -> 1.9983684 | E33: =(('ACTUAL EXP'!$G$25)*(ALLOCATION!P37)) -> 0 | F33: ='ACTUAL EXP'!$G$28*ALLOCATION!P37 -> 0 | G33: 0 | H33: =SUM('ACTUAL EXP'!$G$30:$G$35)*ALLOCATION!P37 -> 1.7935898 | I33: =SUM('ACTUAL EXP'!$G$43:$G$47)*ALLOCATION!P37 -> 1.083383 | J33: =(SUM('ACTUAL EXP'!$G$49:$G$50)*ALLOCATION!P37*0.5)+(SUM('ACTUAL EXP'!$G$49:$G$50)*ALLOCATION!P37*0.5) -> 0.51971837 | K33: =SUM('ACTUAL EXP'!$G$52:$G$53)*ALLOCATION!P37 -> 0.54849042 | L33: =SUM('ACTUAL EXP'!$G$54:$G$54)*ALLOCATION!P37 -> 0.074794148 | M33: =SUM('ACTUAL EXP'!$G$21:$G$21)*ALLOCATION!P37 -> 0.023048053 | N33: =SUM('ACTUAL EXP'!$G$58:$G$62)*0.39*ALLOCATION!P37 -> 0.36706999 | O33: =SUM('ACTUAL EXP'!$G$58:$G$62)*0.27*ALLOCATION!P37 -> 0.25412538 | P33: =SUM('ACTUAL EXP'!$G$58:$G$62)*0.34*ALLOCATION!P37 -> 0.32000973 | Q33: ='ACTUAL EXP'!$G$85*ALLOCATION!P37 -> 0.48707496 | R33: =SUM('ACTUAL EXP'!$G$68:$G$73)*ALLOCATION!P37 -> 1.3284941 | S33: =SUM('ACTUAL EXP'!$G$75)*ALLOCATION!P37 -> 0.1860512 | T33: =SUM('ACTUAL EXP'!$G$77)*ALLOCATION!P37 -> 0.12216046 | U33: =SUM('ACTUAL EXP'!$G$79)*ALLOCATION!P37 -> 0.1851328 | V33: =SUM(C33:U33) -> 10.530545 | W33: =-(H33/$H$111)*($W$117) -> 0.094844396 | X33: =-(Q33/$Q$111)*($X$118) -> 0.069444027 | Y33: =-(SUM(J33:O33,R33:U33)/SUM($J$111:$O$111,$R$111:$U$111))*$Y$119 -> 0.22142218 | Z33: =-(C33/$C$111)*($Z$120) -> 0.090818479 | AA33: =-(I33/$I$111)*($AA$121) -> 0.035357219 | AB33: =-(SUM(D33:G33)/SUM($D$111:$G$111))*SUM($AB$117:$AB$122) -> 0.07693528 | AC33: =SUM(V33:AB33) -> 11.119366 | AD33: =SUM('ACTUAL EXP'!$G$37:$G$39)*ALLOCATION!P37 -> 0.21783758 | AE33: =(AD33/$AD$111)*SUM($AD$117:$AD$122) -> 0.012180516 | AF33: =SUM('ACTUAL EXP'!$G$41)*ALLOCATION!P37 -> 0.065174665 | AG33: =(AF33/$AF$111)*SUM($AF$117:$AF$122) -> 0.0036442796 | AH33: =SUM('ACTUAL EXP'!$G$81)*ALLOCATION!P37 -> 0.027147783 | AI33: =(AH33/$AH$111)*SUM($AH$117:$AH$122) -> 0.0015179842 | AJ33: =SUM('ACTUAL EXP'!$G$83)*ALLOCATION!P37 -> 0.2015631 | AK33: =(AJ33/$AH$111)*SUM($AH$117:$AH$122) -> 0.011270519 | AL33: =SUM('ACTUAL EXP'!$G$64:$G$66)*ALLOCATION!P37 -> 0.065087977 | AM33: =(AL33/$AL$111)*SUM($AL$117:$AL$122) -> 0.0036394324 | AN33: =SUM(AC33:AM33) -> 11.72843 | AQ33: =SUM(AO33,AN33) -> 11.72843 | AS33: =AQ33-AR33 -> 11.72843 | AT33: (M) General Svcs.
A34: =ALLOCATION!A38 -> 209000 | B34: =ALLOCATION!C38 -> Convention & Tourism | C34: ='ACTUAL EXP'!$G$13*(ALLOCATION!P38) -> 6003.3094 | D34: =(SUM('ACTUAL EXP'!$G$15,'ACTUAL EXP'!$G$17:$G$19,'ACTUAL EXP'!$G$22))*ALLOCATION!P38 -> 9682.4017 | E34: =(('ACTUAL EXP'!$G$25)*(ALLOCATION!P38)) -> 0 | F34: ='ACTUAL EXP'!$G$28*ALLOCATION!P38 -> 0 | G34: 0 | H34: =SUM('ACTUAL EXP'!$G$30:$G$35)*ALLOCATION!P38 -> 8690.2178 | I34: =SUM('ACTUAL EXP'!$G$43:$G$47)*ALLOCATION!P38 -> 5249.1572 | J34: =(SUM('ACTUAL EXP'!$G$49:$G$50)*ALLOCATION!P38*0.5)+(SUM('ACTUAL EXP'!$G$49:$G$50)*ALLOCATION!P38*0.5) -> 2518.1153 | K34: =SUM('ACTUAL EXP'!$G$52:$G$53)*ALLOCATION!P38 -> 2657.5203 | L34: =SUM('ACTUAL EXP'!$G$54:$G$54)*ALLOCATION!P38 -> 362.38913 | M34: =SUM('ACTUAL EXP'!$G$21:$G$21)*ALLOCATION!P38 -> 111.67135 | N34: =SUM('ACTUAL EXP'!$G$58:$G$62)*0.39*ALLOCATION!P38 -> 1778.5104 | O34: =SUM('ACTUAL EXP'!$G$58:$G$62)*0.27*ALLOCATION!P38 -> 1231.2765 | P34: =SUM('ACTUAL EXP'!$G$58:$G$62)*0.34*ALLOCATION!P38 -> 1550.4963 | Q34: ='ACTUAL EXP'!$G$85*ALLOCATION!P38 -> 2359.953 | R34: =SUM('ACTUAL EXP'!$G$68:$G$73)*ALLOCATION!P38 -> 6436.7581 | S34: =SUM('ACTUAL EXP'!$G$75)*ALLOCATION!P38 -> 901.44661 | T34: =SUM('ACTUAL EXP'!$G$77)*ALLOCATION!P38 -> 591.88618 | U34: =SUM('ACTUAL EXP'!$G$79)*ALLOCATION!P38 -> 896.99686 | V34: =SUM(C34:U34) -> 51022.106 | W34: =-(H34/$H$111)*($W$117) -> 459.53566 | X34: =-(Q34/$Q$111)*($X$118) -> 336.46697 | Y34: =-(SUM(J34:O34,R34:U34)/SUM($J$111:$O$111,$R$111:$U$111))*$Y$119 -> 1072.8245 | Z34: =-(C34/$C$111)*($Z$120) -> 440.02947 | AA34: =-(I34/$I$111)*($AA$121) -> 171.31115 | AB34: =-(SUM(D34:G34)/SUM($D$111:$G$111))*SUM($AB$117:$AB$122) -> 372.76324 | AC34: =SUM(V34:AB34) -> 53875.037 | AD34: =SUM('ACTUAL EXP'!$G$37:$G$39)*ALLOCATION!P38 -> 1055.4565 | AE34: =(AD34/$AD$111)*SUM($AD$117:$AD$122) -> 59.016471 | AF34: =SUM('ACTUAL EXP'!$G$41)*ALLOCATION!P38 -> 315.78126 | AG34: =(AF34/$AF$111)*SUM($AF$117:$AF$122) -> 17.657094 | AH34: =SUM('ACTUAL EXP'!$G$81)*ALLOCATION!P38 -> 131.53518 | AI34: =(AH34/$AH$111)*SUM($AH$117:$AH$122) -> 7.3548666 | AJ34: =SUM('ACTUAL EXP'!$G$83)*ALLOCATION!P38 -> 976.60418 | AK34: =(AJ34/$AH$111)*SUM($AH$117:$AH$122) -> 54.607396 | AL34: =SUM('ACTUAL EXP'!$G$64:$G$66)*ALLOCATION!P38 -> 315.36124 | AM34: =(AL34/$AL$111)*SUM($AL$117:$AL$122) -> 17.633609 | AN34: =SUM(AC34:AM34) -> 56826.045 | AQ34: =SUM(AO34,AN34) -> 56826.045 | AS34: =AQ34-AR34 -> 56826.045 | AT34: (o) Pub safe/BOEC
A35: =ALLOCATION!A39 -> 215000 | B35: =ALLOCATION!C39 -> Parks Local Opt Levy | C35: ='ACTUAL EXP'!$G$13*(ALLOCATION!P39) -> 1017.6776 | D35: =(SUM('ACTUAL EXP'!$G$15,'ACTUAL EXP'!$G$17:$G$19,'ACTUAL EXP'!$G$22))*ALLOCATION!P39 -> 1641.3552 | E35: =(('ACTUAL EXP'!$G$25)*(ALLOCATION!P39)) -> 0 | F35: ='ACTUAL EXP'!$G$28*ALLOCATION!P39 -> 0 | G35: 0 | H35: =SUM('ACTUAL EXP'!$G$30:$G$35)*ALLOCATION!P39 -> 1473.1607 | I35: =SUM('ACTUAL EXP'!$G$43:$G$47)*ALLOCATION!P39 -> 889.83412 | J35: =(SUM('ACTUAL EXP'!$G$49:$G$50)*ALLOCATION!P39*0.5)+(SUM('ACTUAL EXP'!$G$49:$G$50)*ALLOCATION!P39*0.5) -> 426.86947 | K35: =SUM('ACTUAL EXP'!$G$52:$G$53)*ALLOCATION!P39 -> 450.50132 | L35: =SUM('ACTUAL EXP'!$G$54:$G$54)*ALLOCATION!P39 -> 61.431998 | M35: =SUM('ACTUAL EXP'!$G$21:$G$21)*ALLOCATION!P39 -> 18.930464 | N35: =SUM('ACTUAL EXP'!$G$58:$G$62)*0.39*ALLOCATION!P39 -> 301.49207 | O35: =SUM('ACTUAL EXP'!$G$58:$G$62)*0.27*ALLOCATION!P39 -> 208.72528 | P35: =SUM('ACTUAL EXP'!$G$58:$G$62)*0.34*ALLOCATION!P39 -> 262.83924 | Q35: ='ACTUAL EXP'!$G$85*ALLOCATION!P39 -> 400.05787 | R35: =SUM('ACTUAL EXP'!$G$68:$G$73)*ALLOCATION!P39 -> 1091.1555 | S35: =SUM('ACTUAL EXP'!$G$75)*ALLOCATION!P39 -> 152.81271 | T35: =SUM('ACTUAL EXP'!$G$77)*ALLOCATION!P39 -> 100.33621 | U35: =SUM('ACTUAL EXP'!$G$79)*ALLOCATION!P39 -> 152.05839 | V35: =SUM(C35:U35) -> 8649.2382 | W35: =-(H35/$H$111)*($W$117) -> 77.900222 | X35: =-(Q35/$Q$111)*($X$118) -> 57.037689 | Y35: =-(SUM(J35:O35,R35:U35)/SUM($J$111:$O$111,$R$111:$U$111))*$Y$119 -> 181.86459 | Z35: =-(C35/$C$111)*($Z$120) -> 74.593545 | AA35: =-(I35/$I$111)*($AA$121) -> 29.040569 | AB35: =-(SUM(D35:G35)/SUM($D$111:$G$111))*SUM($AB$117:$AB$122) -> 63.190612 | AC35: =SUM(V35:AB35) -> 9132.8654 | AD35: =SUM('ACTUAL EXP'!$G$37:$G$39)*ALLOCATION!P39 -> 178.92039 | AE35: =(AD35/$AD$111)*SUM($AD$117:$AD$122) -> 10.004438 | AF35: =SUM('ACTUAL EXP'!$G$41)*ALLOCATION!P39 -> 53.531058 | AG35: =(AF35/$AF$111)*SUM($AF$117:$AF$122) -> 2.9932205 | AH35: =SUM('ACTUAL EXP'!$G$81)*ALLOCATION!P39 -> 22.297768 | AI35: =(AH35/$AH$111)*SUM($AH$117:$AH$122) -> 1.2467928 | AJ35: =SUM('ACTUAL EXP'!$G$83)*ALLOCATION!P39 -> 165.55338 | AK35: =(AJ35/$AH$111)*SUM($AH$117:$AH$122) -> 9.2570144 | AL35: =SUM('ACTUAL EXP'!$G$64:$G$66)*ALLOCATION!P39 -> 53.459857 | AM35: =(AL35/$AL$111)*SUM($AL$117:$AL$122) -> 2.9892393 | AN35: =SUM(AC35:AM35) -> 9633.1186 | AQ35: =SUM(AO35,AN35) -> 9633.1186 | AS35: =AQ35-AR35 -> 9633.1186 | AT35: (Z) General Fund
A36: =ALLOCATION!A40 -> 216000 | B36: =ALLOCATION!C40 -> Children Investment | C36: ='ACTUAL EXP'!$G$13*(ALLOCATION!P40) -> 27634.38 | D36: =(SUM('ACTUAL EXP'!$G$15,'ACTUAL EXP'!$G$17:$G$19,'ACTUAL EXP'!$G$22))*ALLOCATION!P40 -> 44569.945 | E36: =(('ACTUAL EXP'!$G$25)*(ALLOCATION!P40)) -> 0 | F36: ='ACTUAL EXP'!$G$28*ALLOCATION!P40 -> 0 | G36: 0 | H36: =SUM('ACTUAL EXP'!$G$30:$G$35)*ALLOCATION!P40 -> 40002.733 | I36: =SUM('ACTUAL EXP'!$G$43:$G$47)*ALLOCATION!P40 -> 24162.873 | J36: =(SUM('ACTUAL EXP'!$G$49:$G$50)*ALLOCATION!P40*0.5)+(SUM('ACTUAL EXP'!$G$49:$G$50)*ALLOCATION!P40*0.5) -> 11591.366 | K36: =SUM('ACTUAL EXP'!$G$52:$G$53)*ALLOCATION!P40 -> 12233.074 | L36: =SUM('ACTUAL EXP'!$G$54:$G$54)*ALLOCATION!P40 -> 1668.1464 | M36: =SUM('ACTUAL EXP'!$G$21:$G$21)*ALLOCATION!P40 -> 514.04458 | N36: =SUM('ACTUAL EXP'!$G$58:$G$62)*0.39*ALLOCATION!P40 -> 8186.8233 | O36: =SUM('ACTUAL EXP'!$G$58:$G$62)*0.27*ALLOCATION!P40 -> 5667.8008 | P36: =SUM('ACTUAL EXP'!$G$58:$G$62)*0.34*ALLOCATION!P40 -> 7137.2306 | Q36: ='ACTUAL EXP'!$G$85*ALLOCATION!P40 -> 10863.314 | R36: =SUM('ACTUAL EXP'!$G$68:$G$73)*ALLOCATION!P40 -> 29629.627 | S36: =SUM('ACTUAL EXP'!$G$75)*ALLOCATION!P40 -> 4149.531 | T36: =SUM('ACTUAL EXP'!$G$77)*ALLOCATION!P40 -> 2724.5652 | U36: =SUM('ACTUAL EXP'!$G$79)*ALLOCATION!P40 -> 4129.0479 | V36: =SUM(C36:U36) -> 234864.5 | W36: =-(H36/$H$111)*($W$117) -> 2115.3304 | X36: =-(Q36/$Q$111)*($X$118) -> 1548.8218 | Y36: =-(SUM(J36:O36,R36:U36)/SUM($J$111:$O$111,$R$111:$U$111))*$Y$119 -> 4938.416 | Z36: =-(C36/$C$111)*($Z$120) -> 2025.5397 | AA36: =-(I36/$I$111)*($AA$121) -> 788.57797 | AB36: =-(SUM(D36:G36)/SUM($D$111:$G$111))*SUM($AB$117:$AB$122) -> 1715.9004 | AC36: =SUM(V36:AB36) -> 247997.09 | AD36: =SUM('ACTUAL EXP'!$G$37:$G$39)*ALLOCATION!P40 -> 4858.4681 | AE36: =(AD36/$AD$111)*SUM($AD$117:$AD$122) -> 271.66409 | AF36: =SUM('ACTUAL EXP'!$G$41)*ALLOCATION!P40 -> 1453.6015 | AG36: =(AF36/$AF$111)*SUM($AF$117:$AF$122) -> 81.278978 | AH36: =SUM('ACTUAL EXP'!$G$81)*ALLOCATION!P40 -> 605.48155 | AI36: =(AH36/$AH$111)*SUM($AH$117:$AH$122) -> 33.855856 | AJ36: =SUM('ACTUAL EXP'!$G$83)*ALLOCATION!P40 -> 4495.4956 | AK36: =(AJ36/$AH$111)*SUM($AH$117:$AH$122) -> 251.36827 | AL36: =SUM('ACTUAL EXP'!$G$64:$G$66)*ALLOCATION!P40 -> 1451.668 | AM36: =(AL36/$AL$111)*SUM($AL$117:$AL$122) -> 81.17087 | AN36: =SUM(AC36:AM36) -> 261581.14 | AO36: =-AN36+25000 -> -236581.14 | AP36: (Z) | AQ36: =SUM(AO36,AN36) -> 25000 | AS36: =AQ36-AR36 -> 25000
A37: =ALLOCATION!A41 -> 403000 | B37: =ALLOCATION!C41 -> Public Safety GO Bond Construction | C37: ='ACTUAL EXP'!$G$13*(ALLOCATION!P41) -> 4237.0777 | D37: =(SUM('ACTUAL EXP'!$G$15,'ACTUAL EXP'!$G$17:$G$19,'ACTUAL EXP'!$G$22))*ALLOCATION!P41 -> 6833.7455 | E37: =(('ACTUAL EXP'!$G$25)*(ALLOCATION!P41)) -> 0 | F37: ='ACTUAL EXP'!$G$28*ALLOCATION!P41 -> 0 | G37: 0 | H37: =SUM('ACTUAL EXP'!$G$30:$G$35)*ALLOCATION!P41 -> 6133.4717 | I37: =SUM('ACTUAL EXP'!$G$43:$G$47)*ALLOCATION!P41 -> 3704.8044 | J37: =(SUM('ACTUAL EXP'!$G$49:$G$50)*ALLOCATION!P41*0.5)+(SUM('ACTUAL EXP'!$G$49:$G$50)*ALLOCATION!P41*0.5) -> 1777.2614 | K37: =SUM('ACTUAL EXP'!$G$52:$G$53)*ALLOCATION!P41 -> 1875.6521 | L37: =SUM('ACTUAL EXP'!$G$54:$G$54)*ALLOCATION!P41 -> 255.77075 | M37: =SUM('ACTUAL EXP'!$G$21:$G$21)*ALLOCATION!P41 -> 78.816562 | N37: =SUM('ACTUAL EXP'!$G$58:$G$62)*0.39*ALLOCATION!P41 -> 1255.2555 | O37: =SUM('ACTUAL EXP'!$G$58:$G$62)*0.27*ALLOCATION!P41 -> 869.02302 | P37: =SUM('ACTUAL EXP'!$G$58:$G$62)*0.34*ALLOCATION!P41 -> 1094.3253 | Q37: ='ACTUAL EXP'!$G$85*ALLOCATION!P41 -> 1665.632 | R37: =SUM('ACTUAL EXP'!$G$68:$G$73)*ALLOCATION!P41 -> 4543.0016 | S37: =SUM('ACTUAL EXP'!$G$75)*ALLOCATION!P41 -> 636.2323 | T37: =SUM('ACTUAL EXP'!$G$77)*ALLOCATION!P41 -> 417.74755 | U37: =SUM('ACTUAL EXP'!$G$79)*ALLOCATION!P41 -> 633.09171 | V37: =SUM(C37:U37) -> 36010.909 | W37: =-(H37/$H$111)*($W$117) -> 324.33583 | X37: =-(Q37/$Q$111)*($X$118) -> 237.47514 | Y37: =-(SUM(J37:O37,R37:U37)/SUM($J$111:$O$111,$R$111:$U$111))*$Y$119 -> 757.18914 | Z37: =-(C37/$C$111)*($Z$120) -> 310.56855 | AA37: =-(I37/$I$111)*($AA$121) -> 120.90976 | AB37: =-(SUM(D37:G37)/SUM($D$111:$G$111))*SUM($AB$117:$AB$122) -> 263.09269 | AC37: =SUM(V37:AB37) -> 38024.48 | AD37: =SUM('ACTUAL EXP'!$G$37:$G$39)*ALLOCATION!P41 -> 744.93102 | AE37: =(AD37/$AD$111)*SUM($AD$117:$AD$122) -> 41.653255 | AF37: =SUM('ACTUAL EXP'!$G$41)*ALLOCATION!P41 -> 222.87536 | AG37: =(AF37/$AF$111)*SUM($AF$117:$AF$122) -> 12.462206 | AH37: =SUM('ACTUAL EXP'!$G$81)*ALLOCATION!P41 -> 92.836257 | AI37: =(AH37/$AH$111)*SUM($AH$117:$AH$122) -> 5.1909937 | AJ37: =SUM('ACTUAL EXP'!$G$83)*ALLOCATION!P41 -> 689.27779 | AK37: =(AJ37/$AH$111)*SUM($AH$117:$AH$122) -> 38.541372 | AL37: =SUM('ACTUAL EXP'!$G$64:$G$66)*ALLOCATION!P41 -> 222.57891 | AM37: =(AL37/$AL$111)*SUM($AL$117:$AL$122) -> 12.445631 | AN37: =SUM(AC37:AM37) -> 40107.273 | AQ37: =SUM(AO37,AN37) -> 40107.273 | AS37: =AQ37-AR37 -> 40107.273
A38: =ALLOCATION!A42 -> 316000 | B38: =ALLOCATION!C42 -> Willamtte Ind URA DS | C38: ='ACTUAL EXP'!$G$13*(ALLOCATION!P42) -> 410.67642 | D38: =(SUM('ACTUAL EXP'!$G$15,'ACTUAL EXP'!$G$17:$G$19,'ACTUAL EXP'!$G$22))*ALLOCATION!P42 -> 662.35701 | E38: =(('ACTUAL EXP'!$G$25)*(ALLOCATION!P42)) -> 0 | F38: ='ACTUAL EXP'!$G$28*ALLOCATION!P42 -> 0 | G38: 0 | H38: =SUM('ACTUAL EXP'!$G$30:$G$35)*ALLOCATION!P42 -> 594.48336 | I38: =SUM('ACTUAL EXP'!$G$43:$G$47)*ALLOCATION!P42 -> 359.08612 | J38: =(SUM('ACTUAL EXP'!$G$49:$G$50)*ALLOCATION!P42*0.5)+(SUM('ACTUAL EXP'!$G$49:$G$50)*ALLOCATION!P42*0.5) -> 172.26008 | K38: =SUM('ACTUAL EXP'!$G$52:$G$53)*ALLOCATION!P42 -> 181.79655 | L38: =SUM('ACTUAL EXP'!$G$54:$G$54)*ALLOCATION!P42 -> 24.790438 | M38: =SUM('ACTUAL EXP'!$G$21:$G$21)*ALLOCATION!P42 -> 7.6392518 | N38: =SUM('ACTUAL EXP'!$G$58:$G$62)*0.39*ALLOCATION!P42 -> 121.66494 | O38: =SUM('ACTUAL EXP'!$G$58:$G$62)*0.27*ALLOCATION!P42 -> 84.229577 | P38: =SUM('ACTUAL EXP'!$G$58:$G$62)*0.34*ALLOCATION!P42 -> 106.06687 | Q38: ='ACTUAL EXP'!$G$85*ALLOCATION!P42 -> 161.44046 | R38: =SUM('ACTUAL EXP'!$G$68:$G$73)*ALLOCATION!P42 -> 440.32792 | S38: =SUM('ACTUAL EXP'!$G$75)*ALLOCATION!P42 -> 61.666465 | T38: =SUM('ACTUAL EXP'!$G$77)*ALLOCATION!P42 -> 40.48995 | U38: =SUM('ACTUAL EXP'!$G$79)*ALLOCATION!P42 -> 61.362065 | V38: =SUM(C38:U38) -> 3490.3375 | W38: =-(H38/$H$111)*($W$117) -> 31.436071 | X38: =-(Q38/$Q$111)*($X$118) -> 23.017147 | Y38: =-(SUM(J38:O38,R38:U38)/SUM($J$111:$O$111,$R$111:$U$111))*$Y$119 -> 73.39014 | Z38: =-(C38/$C$111)*($Z$120) -> 30.101685 | AA38: =-(I38/$I$111)*($AA$121) -> 11.719111 | AB38: =-(SUM(D38:G38)/SUM($D$111:$G$111))*SUM($AB$117:$AB$122) -> 25.500114 | AC38: =SUM(V38:AB38) -> 3685.5018 | AD38: =SUM('ACTUAL EXP'!$G$37:$G$39)*ALLOCATION!P42 -> 72.202028 | AE38: =(AD38/$AD$111)*SUM($AD$117:$AD$122) -> 4.0372187 | AF38: =SUM('ACTUAL EXP'!$G$41)*ALLOCATION!P42 -> 21.602071 | AG38: =(AF38/$AF$111)*SUM($AF$117:$AF$122) -> 1.2078925 | AH38: =SUM('ACTUAL EXP'!$G$81)*ALLOCATION!P42 -> 8.9981029 | AI38: =(AH38/$AH$111)*SUM($AH$117:$AH$122) -> 0.5031342 | AJ38: =SUM('ACTUAL EXP'!$G$83)*ALLOCATION!P42 -> 66.807869 | AK38: =(AJ38/$AH$111)*SUM($AH$117:$AH$122) -> 3.7356012 | AL38: =SUM('ACTUAL EXP'!$G$64:$G$66)*ALLOCATION!P42 -> 21.573338 | AM38: =(AL38/$AL$111)*SUM($AL$117:$AL$122) -> 1.2062859 | AN38: =SUM(AC38:AM38) -> 3887.3753 | AO38: =-AN38 -> -3887.3753 | AP38: (Z) | AQ38: =SUM(AO38,AN38) -> 0 | AS38: =AQ38-AR38 -> 0
A39: =ALLOCATION!A43 -> 301000 | B39: =ALLOCATION!C43 -> River Dist URA DR | C39: ='ACTUAL EXP'!$G$13*(ALLOCATION!P43) -> 14205.063 | D39: =(SUM('ACTUAL EXP'!$G$15,'ACTUAL EXP'!$G$17:$G$19,'ACTUAL EXP'!$G$22))*ALLOCATION!P43 -> 22910.551 | E39: =(('ACTUAL EXP'!$G$25)*(ALLOCATION!P43)) -> 0 | F39: ='ACTUAL EXP'!$G$28*ALLOCATION!P43 -> 0 | G39: 0 | H39: =SUM('ACTUAL EXP'!$G$30:$G$35)*ALLOCATION!P43 -> 20562.84 | I39: =SUM('ACTUAL EXP'!$G$43:$G$47)*ALLOCATION!P43 -> 12420.584 | J39: =(SUM('ACTUAL EXP'!$G$49:$G$50)*ALLOCATION!P43*0.5)+(SUM('ACTUAL EXP'!$G$49:$G$50)*ALLOCATION!P43*0.5) -> 5958.378 | K39: =SUM('ACTUAL EXP'!$G$52:$G$53)*ALLOCATION!P43 -> 6288.2388 | L39: =SUM('ACTUAL EXP'!$G$54:$G$54)*ALLOCATION!P43 -> 857.48711 | M39: =SUM('ACTUAL EXP'!$G$21:$G$21)*ALLOCATION!P43 -> 264.23736 | N39: =SUM('ACTUAL EXP'!$G$58:$G$62)*0.39*ALLOCATION!P43 -> 4208.321 | O39: =SUM('ACTUAL EXP'!$G$58:$G$62)*0.27*ALLOCATION!P43 -> 2913.453 | P39: =SUM('ACTUAL EXP'!$G$58:$G$62)*0.34*ALLOCATION!P43 -> 3668.7926 | Q39: ='ACTUAL EXP'!$G$85*ALLOCATION!P43 -> 5584.1334 | R39: =SUM('ACTUAL EXP'!$G$68:$G$73)*ALLOCATION!P43 -> 15230.692 | S39: =SUM('ACTUAL EXP'!$G$75)*ALLOCATION!P43 -> 2133.0078 | T39: =SUM('ACTUAL EXP'!$G$77)*ALLOCATION!P43 -> 1400.5243 | U39: =SUM('ACTUAL EXP'!$G$79)*ALLOCATION!P43 -> 2122.4788 | V39: =SUM(C39:U39) -> 120728.78 | W39: =-(H39/$H$111)*($W$117) -> 1087.3557 | X39: =-(Q39/$Q$111)*($X$118) -> 796.14996 | Y39: =-(SUM(J39:O39,R39:U39)/SUM($J$111:$O$111,$R$111:$U$111))*$Y$119 -> 2538.523 | Z39: =-(C39/$C$111)*($Z$120) -> 1041.2001 | AA39: =-(I39/$I$111)*($AA$121) -> 405.35737 | AB39: =-(SUM(D39:G39)/SUM($D$111:$G$111))*SUM($AB$117:$AB$122) -> 882.03439 | AC39: =SUM(V39:AB39) -> 127479.4 | AD39: =SUM('ACTUAL EXP'!$G$37:$G$39)*ALLOCATION!P43 -> 2497.4269 | AE39: =(AD39/$AD$111)*SUM($AD$117:$AD$122) -> 139.64509 | AF39: =SUM('ACTUAL EXP'!$G$41)*ALLOCATION!P43 -> 747.20331 | AG39: =(AF39/$AF$111)*SUM($AF$117:$AF$122) -> 41.780311 | AH39: =SUM('ACTUAL EXP'!$G$81)*ALLOCATION!P43 -> 311.23924 | AI39: =(AH39/$AH$111)*SUM($AH$117:$AH$122) -> 17.403125 | AJ39: =SUM('ACTUAL EXP'!$G$83)*ALLOCATION!P43 -> 2310.8461 | AK39: =(AJ39/$AH$111)*SUM($AH$117:$AH$122) -> 129.21231 | AL39: =SUM('ACTUAL EXP'!$G$64:$G$66)*ALLOCATION!P43 -> 746.20946 | AM39: =(AL39/$AL$111)*SUM($AL$117:$AL$122) -> 41.72474 | AN39: =SUM(AC39:AM39) -> 134462.09 | AO39: =-AN39 -> -134462.09 | AP39: (Z) | AQ39: =SUM(AO39,AN39) -> 0 | AS39: =AQ39-AR39 -> 0
A40: =ALLOCATION!A44 -> 302000 | B40: =ALLOCATION!C44 -> Bonded Dbt Int&Sinkg | C40: ='ACTUAL EXP'!$G$13*(ALLOCATION!P44) -> 3968.5711 | D40: =(SUM('ACTUAL EXP'!$G$15,'ACTUAL EXP'!$G$17:$G$19,'ACTUAL EXP'!$G$22))*ALLOCATION!P44 -> 6400.6862 | E40: =(('ACTUAL EXP'!$G$25)*(ALLOCATION!P44)) -> 0 | F40: ='ACTUAL EXP'!$G$28*ALLOCATION!P44 -> 0 | G40: 0 | H40: =SUM('ACTUAL EXP'!$G$30:$G$35)*ALLOCATION!P44 -> 5744.7893 | I40: =SUM('ACTUAL EXP'!$G$43:$G$47)*ALLOCATION!P44 -> 3470.0283 | J40: =(SUM('ACTUAL EXP'!$G$49:$G$50)*ALLOCATION!P44*0.5)+(SUM('ACTUAL EXP'!$G$49:$G$50)*ALLOCATION!P44*0.5) -> 1664.6351 | K40: =SUM('ACTUAL EXP'!$G$52:$G$53)*ALLOCATION!P44 -> 1756.7907 | L40: =SUM('ACTUAL EXP'!$G$54:$G$54)*ALLOCATION!P44 -> 239.56237 | M40: =SUM('ACTUAL EXP'!$G$21:$G$21)*ALLOCATION!P44 -> 73.821901 | N40: =SUM('ACTUAL EXP'!$G$58:$G$62)*0.39*ALLOCATION!P44 -> 1175.709 | O40: =SUM('ACTUAL EXP'!$G$58:$G$62)*0.27*ALLOCATION!P44 -> 813.95242 | P40: =SUM('ACTUAL EXP'!$G$58:$G$62)*0.34*ALLOCATION!P44 -> 1024.9771 | Q40: ='ACTUAL EXP'!$G$85*ALLOCATION!P44 -> 1560.0797 | R40: =SUM('ACTUAL EXP'!$G$68:$G$73)*ALLOCATION!P44 -> 4255.1084 | S40: =SUM('ACTUAL EXP'!$G$75)*ALLOCATION!P44 -> 595.91381 | T40: =SUM('ACTUAL EXP'!$G$77)*ALLOCATION!P44 -> 391.27459 | U40: =SUM('ACTUAL EXP'!$G$79)*ALLOCATION!P44 -> 592.97224 | V40: =SUM(C40:U40) -> 33728.872 | W40: =-(H40/$H$111)*($W$117) -> 303.78244 | X40: =-(Q40/$Q$111)*($X$118) -> 222.42617 | Y40: =-(SUM(J40:O40,R40:U40)/SUM($J$111:$O$111,$R$111:$U$111))*$Y$119 -> 709.20553 | Z40: =-(C40/$C$111)*($Z$120) -> 290.8876 | AA40: =-(I40/$I$111)*($AA$121) -> 113.24762 | AB40: =-(SUM(D40:G40)/SUM($D$111:$G$111))*SUM($AB$117:$AB$122) -> 246.42032 | AC40: =SUM(V40:AB40) -> 35614.842 | AD40: =SUM('ACTUAL EXP'!$G$37:$G$39)*ALLOCATION!P44 -> 697.72422 | AE40: =(AD40/$AD$111)*SUM($AD$117:$AD$122) -> 39.013659 | AF40: =SUM('ACTUAL EXP'!$G$41)*ALLOCATION!P44 -> 208.75159 | AG40: =(AF40/$AF$111)*SUM($AF$117:$AF$122) -> 11.672468 | AH40: =SUM('ACTUAL EXP'!$G$81)*ALLOCATION!P44 -> 86.953157 | AI40: =(AH40/$AH$111)*SUM($AH$117:$AH$122) -> 4.8620368 | AJ40: =SUM('ACTUAL EXP'!$G$83)*ALLOCATION!P44 -> 645.59777 | AK40: =(AJ40/$AH$111)*SUM($AH$117:$AH$122) -> 36.098978 | AL40: =SUM('ACTUAL EXP'!$G$64:$G$66)*ALLOCATION!P44 -> 208.47393 | AM40: =(AL40/$AL$111)*SUM($AL$117:$AL$122) -> 11.656942 | AN40: =SUM(AC40:AM40) -> 37565.647 | AO40: =-AN40 -> -37565.647 | AP40: (Z) | AQ40: =SUM(AO40,AN40) -> 0 | AS40: =AQ40-AR40 -> 0
A41: =ALLOCATION!A45 -> 303000 | B41: =ALLOCATION!C45 -> DTWF Renwl Bd Sink | C41: ='ACTUAL EXP'!$G$13*(ALLOCATION!P45) -> 4781.7525 | D41: =(SUM('ACTUAL EXP'!$G$15,'ACTUAL EXP'!$G$17:$G$19,'ACTUAL EXP'!$G$22))*ALLOCATION!P45 -> 7712.221 | E41: =(('ACTUAL EXP'!$G$25)*(ALLOCATION!P45)) -> 0 | F41: ='ACTUAL EXP'!$G$28*ALLOCATION!P45 -> 0 | G41: 0 | H41: =SUM('ACTUAL EXP'!$G$30:$G$35)*ALLOCATION!P45 -> 6921.9273 | I41: =SUM('ACTUAL EXP'!$G$43:$G$47)*ALLOCATION!P45 -> 4181.0556 | J41: =(SUM('ACTUAL EXP'!$G$49:$G$50)*ALLOCATION!P45*0.5)+(SUM('ACTUAL EXP'!$G$49:$G$50)*ALLOCATION!P45*0.5) -> 2005.7278 | K41: =SUM('ACTUAL EXP'!$G$52:$G$53)*ALLOCATION!P45 -> 2116.7665 | L41: =SUM('ACTUAL EXP'!$G$54:$G$54)*ALLOCATION!P45 -> 288.64998 | M41: =SUM('ACTUAL EXP'!$G$21:$G$21)*ALLOCATION!P45 -> 88.948402 | N41: =SUM('ACTUAL EXP'!$G$58:$G$62)*0.39*ALLOCATION!P45 -> 1416.6181 | O41: =SUM('ACTUAL EXP'!$G$58:$G$62)*0.27*ALLOCATION!P45 -> 980.73561 | P41: =SUM('ACTUAL EXP'!$G$58:$G$62)*0.34*ALLOCATION!P45 -> 1235.0004 | Q41: ='ACTUAL EXP'!$G$85*ALLOCATION!P45 -> 1879.7484 | R41: =SUM('ACTUAL EXP'!$G$68:$G$73)*ALLOCATION!P45 -> 5127.0028 | S41: =SUM('ACTUAL EXP'!$G$75)*ALLOCATION!P45 -> 718.01973 | T41: =SUM('ACTUAL EXP'!$G$77)*ALLOCATION!P45 -> 471.44884 | U41: =SUM('ACTUAL EXP'!$G$79)*ALLOCATION!P45 -> 714.47542 | V41: =SUM(C41:U41) -> 40640.098 | W41: =-(H41/$H$111)*($W$117) -> 366.02908 | X41: =-(Q41/$Q$111)*($X$118) -> 268.00248 | Y41: =-(SUM(J41:O41,R41:U41)/SUM($J$111:$O$111,$R$111:$U$111))*$Y$119 -> 854.52553 | Z41: =-(C41/$C$111)*($Z$120) -> 350.49202 | AA41: =-(I41/$I$111)*($AA$121) -> 136.45266 | AB41: =-(SUM(D41:G41)/SUM($D$111:$G$111))*SUM($AB$117:$AB$122) -> 296.91316 | AC41: =SUM(V41:AB41) -> 42912.513 | AD41: =SUM('ACTUAL EXP'!$G$37:$G$39)*ALLOCATION!P45 -> 840.69163 | AE41: =(AD41/$AD$111)*SUM($AD$117:$AD$122) -> 47.007766 | AF41: =SUM('ACTUAL EXP'!$G$41)*ALLOCATION!P45 -> 251.52591 | AG41: =(AF41/$AF$111)*SUM($AF$117:$AF$122) -> 14.064219 | AH41: =SUM('ACTUAL EXP'!$G$81)*ALLOCATION!P45 -> 104.77032 | AI41: =(AH41/$AH$111)*SUM($AH$117:$AH$122) -> 5.8582941 | AJ41: =SUM('ACTUAL EXP'!$G$83)*ALLOCATION!P45 -> 777.8842 | AK41: =(AJ41/$AH$111)*SUM($AH$117:$AH$122) -> 43.495851 | AL41: =SUM('ACTUAL EXP'!$G$64:$G$66)*ALLOCATION!P45 -> 251.19135 | AM41: =(AL41/$AL$111)*SUM($AL$117:$AL$122) -> 14.045512 | AN41: =SUM(AC41:AM41) -> 45263.048 | AO41: =-AN41 -> -45263.048 | AP41: (Z) | AQ41: =SUM(AO41,AN41) -> 0 | AS41: =AQ41-AR41 -> 0
A42: =ALLOCATION!A46 -> 305000 | B42: =ALLOCATION!C46 -> Pension Debt Rdmpt | C42: ='ACTUAL EXP'!$G$13*(ALLOCATION!P46) -> 1529.6075 | D42: =(SUM('ACTUAL EXP'!$G$15,'ACTUAL EXP'!$G$17:$G$19,'ACTUAL EXP'!$G$22))*ALLOCATION!P46 -> 2467.0183 | E42: =(('ACTUAL EXP'!$G$25)*(ALLOCATION!P46)) -> 0 | F42: ='ACTUAL EXP'!$G$28*ALLOCATION!P46 -> 0 | G42: 0 | H42: =SUM('ACTUAL EXP'!$G$30:$G$35)*ALLOCATION!P46 -> 2214.2158 | I42: =SUM('ACTUAL EXP'!$G$43:$G$47)*ALLOCATION!P46 -> 1337.454 | J42: =(SUM('ACTUAL EXP'!$G$49:$G$50)*ALLOCATION!P46*0.5)+(SUM('ACTUAL EXP'!$G$49:$G$50)*ALLOCATION!P46*0.5) -> 641.60079 | K42: =SUM('ACTUAL EXP'!$G$52:$G$53)*ALLOCATION!P46 -> 677.12035 | L42: =SUM('ACTUAL EXP'!$G$54:$G$54)*ALLOCATION!P46 -> 92.334593 | M42: =SUM('ACTUAL EXP'!$G$21:$G$21)*ALLOCATION!P46 -> 28.453196 | N42: =SUM('ACTUAL EXP'!$G$58:$G$62)*0.39*ALLOCATION!P46 -> 453.15387 | O42: =SUM('ACTUAL EXP'!$G$58:$G$62)*0.27*ALLOCATION!P46 -> 313.72191 | P42: =SUM('ACTUAL EXP'!$G$58:$G$62)*0.34*ALLOCATION!P46 -> 395.05722 | Q42: ='ACTUAL EXP'!$G$85*ALLOCATION!P46 -> 601.30196 | R42: =SUM('ACTUAL EXP'!$G$68:$G$73)*ALLOCATION!P46 -> 1640.0476 | S42: =SUM('ACTUAL EXP'!$G$75)*ALLOCATION!P46 -> 229.68323 | T42: =SUM('ACTUAL EXP'!$G$77)*ALLOCATION!P46 -> 150.80908 | U42: =SUM('ACTUAL EXP'!$G$79)*ALLOCATION!P46 -> 228.54946 | V42: =SUM(C42:U42) -> 13000.129 | W42: =-(H42/$H$111)*($W$117) -> 117.08695 | X42: =-(Q42/$Q$111)*($X$118) -> 85.729782 | Y42: =-(SUM(J42:O42,R42:U42)/SUM($J$111:$O$111,$R$111:$U$111))*$Y$119 -> 273.34929 | Z42: =-(C42/$C$111)*($Z$120) -> 112.11689 | AA42: =-(I42/$I$111)*($AA$121) -> 43.649062 | AB42: =-(SUM(D42:G42)/SUM($D$111:$G$111))*SUM($AB$117:$AB$122) -> 94.977855 | AC42: =SUM(V42:AB42) -> 13727.039 | AD42: =SUM('ACTUAL EXP'!$G$37:$G$39)*ALLOCATION!P46 -> 268.92404 | AE42: =(AD42/$AD$111)*SUM($AD$117:$AD$122) -> 15.037046 | AF42: =SUM('ACTUAL EXP'!$G$41)*ALLOCATION!P46 -> 80.459185 | AG42: =(AF42/$AF$111)*SUM($AF$117:$AF$122) -> 4.4989225 | AH42: =SUM('ACTUAL EXP'!$G$81)*ALLOCATION!P46 -> 33.51438 | AI42: =(AH42/$AH$111)*SUM($AH$117:$AH$122) -> 1.8739762 | AJ42: =SUM('ACTUAL EXP'!$G$83)*ALLOCATION!P46 -> 248.83293 | AK42: =(AJ42/$AH$111)*SUM($AH$117:$AH$122) -> 13.913639 | AL42: =SUM('ACTUAL EXP'!$G$64:$G$66)*ALLOCATION!P46 -> 80.352166 | AM42: =(AL42/$AL$111)*SUM($AL$117:$AL$122) -> 4.4929385 | AN42: =SUM(AC42:AM42) -> 14478.938 | AO42: =-AN42 -> -14478.938 | AP42: (Z) | AQ42: =SUM(AO42,AN42) -> 0 | AS42: =AQ42-AR42 -> 0
A43: =ALLOCATION!A47 -> 306000 | B43: =ALLOCATION!C47 -> SO Park Block Rdmpt | C43: ='ACTUAL EXP'!$G$13*(ALLOCATION!P47) -> 3369.9264 | D43: =(SUM('ACTUAL EXP'!$G$15,'ACTUAL EXP'!$G$17:$G$19,'ACTUAL EXP'!$G$22))*ALLOCATION!P47 -> 5435.1657 | E43: =(('ACTUAL EXP'!$G$25)*(ALLOCATION!P47)) -> 0 | F43: ='ACTUAL EXP'!$G$28*ALLOCATION!P47 -> 0 | G43: 0 | H43: =SUM('ACTUAL EXP'!$G$30:$G$35)*ALLOCATION!P47 -> 4878.2084 | I43: =SUM('ACTUAL EXP'!$G$43:$G$47)*ALLOCATION!P47 -> 2946.587 | J43: =(SUM('ACTUAL EXP'!$G$49:$G$50)*ALLOCATION!P47*0.5)+(SUM('ACTUAL EXP'!$G$49:$G$50)*ALLOCATION!P47*0.5) -> 1413.5309 | K43: =SUM('ACTUAL EXP'!$G$52:$G$53)*ALLOCATION!P47 -> 1491.7852 | L43: =SUM('ACTUAL EXP'!$G$54:$G$54)*ALLOCATION!P47 -> 203.42525 | M43: =SUM('ACTUAL EXP'!$G$21:$G$21)*ALLOCATION!P47 -> 62.686132 | N43: =SUM('ACTUAL EXP'!$G$58:$G$62)*0.39*ALLOCATION!P47 -> 998.35756 | O43: =SUM('ACTUAL EXP'!$G$58:$G$62)*0.27*ALLOCATION!P47 -> 691.17062 | P43: =SUM('ACTUAL EXP'!$G$58:$G$62)*0.34*ALLOCATION!P47 -> 870.363 | Q43: ='ACTUAL EXP'!$G$85*ALLOCATION!P47 -> 1324.7473 | R43: =SUM('ACTUAL EXP'!$G$68:$G$73)*ALLOCATION!P47 -> 3613.2406 | S43: =SUM('ACTUAL EXP'!$G$75)*ALLOCATION!P47 -> 506.02235 | T43: =SUM('ACTUAL EXP'!$G$77)*ALLOCATION!P47 -> 332.25222 | U43: =SUM('ACTUAL EXP'!$G$79)*ALLOCATION!P47 -> 503.52451 | V43: =SUM(C43:U43) -> 28640.993 | W43: =-(H43/$H$111)*($W$117) -> 257.95795 | X43: =-(Q43/$Q$111)*($X$118) -> 188.87398 | Y43: =-(SUM(J43:O43,R43:U43)/SUM($J$111:$O$111,$R$111:$U$111))*$Y$119 -> 602.22442 | Z43: =-(C43/$C$111)*($Z$120) -> 247.00825 | AA43: =-(I43/$I$111)*($AA$121) -> 96.164623 | AB43: =-(SUM(D43:G43)/SUM($D$111:$G$111))*SUM($AB$117:$AB$122) -> 209.2487 | AC43: =SUM(V43:AB43) -> 30242.471 | AD43: =SUM('ACTUAL EXP'!$G$37:$G$39)*ALLOCATION!P47 -> 592.47502 | AE43: =(AD43/$AD$111)*SUM($AD$117:$AD$122) -> 33.128588 | AF43: =SUM('ACTUAL EXP'!$G$41)*ALLOCATION!P47 -> 177.26216 | AG43: =(AF43/$AF$111)*SUM($AF$117:$AF$122) -> 9.9117178 | AH43: =SUM('ACTUAL EXP'!$G$81)*ALLOCATION!P47 -> 73.836586 | AI43: =(AH43/$AH$111)*SUM($AH$117:$AH$122) -> 4.128616 | AJ43: =SUM('ACTUAL EXP'!$G$83)*ALLOCATION!P47 -> 548.21166 | AK43: =(AJ43/$AH$111)*SUM($AH$117:$AH$122) -> 30.653577 | AL43: =SUM('ACTUAL EXP'!$G$64:$G$66)*ALLOCATION!P47 -> 177.02639 | AM43: =(AL43/$AL$111)*SUM($AL$117:$AL$122) -> 9.8985343 | AN43: =SUM(AC43:AM43) -> 31899.004 | AO43: =-AN43 -> -31899.004 | AP43: (Z) | AQ43: =SUM(AO43,AN43) -> 0 | AS43: =AQ43-AR43 -> 0
A44: =ALLOCATION!A48 -> 310000 | B44: =ALLOCATION!C48 -> Cntrl E Ind Distr DS | C44: ='ACTUAL EXP'!$G$13*(ALLOCATION!P48) -> 3452.1134 | D44: =(SUM('ACTUAL EXP'!$G$15,'ACTUAL EXP'!$G$17:$G$19,'ACTUAL EXP'!$G$22))*ALLOCATION!P48 -> 5567.7206 | E44: =(('ACTUAL EXP'!$G$25)*(ALLOCATION!P48)) -> 0 | F44: ='ACTUAL EXP'!$G$28*ALLOCATION!P48 -> 0 | G44: 0 | H44: =SUM('ACTUAL EXP'!$G$30:$G$35)*ALLOCATION!P48 -> 4997.1801 | I44: =SUM('ACTUAL EXP'!$G$43:$G$47)*ALLOCATION!P48 -> 3018.4495 | J44: =(SUM('ACTUAL EXP'!$G$49:$G$50)*ALLOCATION!P48*0.5)+(SUM('ACTUAL EXP'!$G$49:$G$50)*ALLOCATION!P48*0.5) -> 1448.0046 | K44: =SUM('ACTUAL EXP'!$G$52:$G$53)*ALLOCATION!P48 -> 1528.1674 | L44: =SUM('ACTUAL EXP'!$G$54:$G$54)*ALLOCATION!P48 -> 208.38646 | M44: =SUM('ACTUAL EXP'!$G$21:$G$21)*ALLOCATION!P48 -> 64.214945 | N44: =SUM('ACTUAL EXP'!$G$58:$G$62)*0.39*ALLOCATION!P48 -> 1022.7059 | O44: =SUM('ACTUAL EXP'!$G$58:$G$62)*0.27*ALLOCATION!P48 -> 708.02715 | P44: =SUM('ACTUAL EXP'!$G$58:$G$62)*0.34*ALLOCATION!P48 -> 891.58975 | Q44: ='ACTUAL EXP'!$G$85*ALLOCATION!P48 -> 1357.0557 | R44: =SUM('ACTUAL EXP'!$G$68:$G$73)*ALLOCATION!P48 -> 3701.3617 | S44: =SUM('ACTUAL EXP'!$G$75)*ALLOCATION!P48 -> 518.36342 | T44: =SUM('ACTUAL EXP'!$G$77)*ALLOCATION!P48 -> 340.35532 | U44: =SUM('ACTUAL EXP'!$G$79)*ALLOCATION!P48 -> 515.80466 | V44: =SUM(C44:U44) -> 29339.501 | W44: =-(H44/$H$111)*($W$117) -> 264.24912 | X44: =-(Q44/$Q$111)*($X$118) -> 193.48031 | Y44: =-(SUM(J44:O44,R44:U44)/SUM($J$111:$O$111,$R$111:$U$111))*$Y$119 -> 616.9117 | Z44: =-(C44/$C$111)*($Z$120) -> 253.03238 | AA44: =-(I44/$I$111)*($AA$121) -> 98.509922 | AB44: =-(SUM(D44:G44)/SUM($D$111:$G$111))*SUM($AB$117:$AB$122) -> 214.35194 | AC44: =SUM(V44:AB44) -> 30980.036 | AD44: =SUM('ACTUAL EXP'!$G$37:$G$39)*ALLOCATION!P48 -> 606.92453 | AE44: =(AD44/$AD$111)*SUM($AD$117:$AD$122) -> 33.936541 | AF44: =SUM('ACTUAL EXP'!$G$41)*ALLOCATION!P48 -> 181.5853 | AG44: =(AF44/$AF$111)*SUM($AF$117:$AF$122) -> 10.153449 | AH44: =SUM('ACTUAL EXP'!$G$81)*ALLOCATION!P48 -> 75.637341 | AI44: =(AH44/$AH$111)*SUM($AH$117:$AH$122) -> 4.2293063 | AJ44: =SUM('ACTUAL EXP'!$G$83)*ALLOCATION!P48 -> 561.58166 | AK44: =(AJ44/$AH$111)*SUM($AH$117:$AH$122) -> 31.401168 | AL44: =SUM('ACTUAL EXP'!$G$64:$G$66)*ALLOCATION!P48 -> 181.34377 | AM44: =(AL44/$AL$111)*SUM($AL$117:$AL$122) -> 10.139944 | AN44: =SUM(AC44:AM44) -> 32676.969 | AO44: =-AN44 -> -32676.969 | AP44: (Z) | AQ44: =SUM(AO44,AN44) -> 0 | AS44: =AQ44-AR44 -> 0
A45: =ALLOCATION!A49 -> 307000 | B45: =ALLOCATION!C49 -> Airport Way Dbt Srvc | C45: ='ACTUAL EXP'!$G$13*(ALLOCATION!P49) -> 2620.4957 | D45: =(SUM('ACTUAL EXP'!$G$15,'ACTUAL EXP'!$G$17:$G$19,'ACTUAL EXP'!$G$22))*ALLOCATION!P49 -> 4226.4508 | E45: =(('ACTUAL EXP'!$G$25)*(ALLOCATION!P49)) -> 0 | F45: ='ACTUAL EXP'!$G$28*ALLOCATION!P49 -> 0 | G45: 0 | H45: =SUM('ACTUAL EXP'!$G$30:$G$35)*ALLOCATION!P49 -> 3793.3541 | I45: =SUM('ACTUAL EXP'!$G$43:$G$47)*ALLOCATION!P49 -> 2291.3018 | J45: =(SUM('ACTUAL EXP'!$G$49:$G$50)*ALLOCATION!P49*0.5)+(SUM('ACTUAL EXP'!$G$49:$G$50)*ALLOCATION!P49*0.5) -> 1099.1788 | K45: =SUM('ACTUAL EXP'!$G$52:$G$53)*ALLOCATION!P49 -> 1160.0302 | L45: =SUM('ACTUAL EXP'!$G$54:$G$54)*ALLOCATION!P49 -> 158.18594 | M45: =SUM('ACTUAL EXP'!$G$21:$G$21)*ALLOCATION!P49 -> 48.745497 | N45: =SUM('ACTUAL EXP'!$G$58:$G$62)*0.39*ALLOCATION!P49 -> 776.33496 | O45: =SUM('ACTUAL EXP'!$G$58:$G$62)*0.27*ALLOCATION!P49 -> 537.46266 | P45: =SUM('ACTUAL EXP'!$G$58:$G$62)*0.34*ALLOCATION!P49 -> 676.80484 | Q45: ='ACTUAL EXP'!$G$85*ALLOCATION!P49 -> 1030.1396 | R45: =SUM('ACTUAL EXP'!$G$68:$G$73)*ALLOCATION!P49 -> 2809.6997 | S45: =SUM('ACTUAL EXP'!$G$75)*ALLOCATION!P49 -> 393.48912 | T45: =SUM('ACTUAL EXP'!$G$77)*ALLOCATION!P49 -> 258.36336 | U45: =SUM('ACTUAL EXP'!$G$79)*ALLOCATION!P49 -> 391.54677 | V45: =SUM(C45:U45) -> 22271.584 | W45: =-(H45/$H$111)*($W$117) -> 200.59123 | X45: =-(Q45/$Q$111)*($X$118) -> 146.8707 | Y45: =-(SUM(J45:O45,R45:U45)/SUM($J$111:$O$111,$R$111:$U$111))*$Y$119 -> 468.29702 | Z45: =-(C45/$C$111)*($Z$120) -> 192.07661 | AA45: =-(I45/$I$111)*($AA$121) -> 74.778778 | AB45: =-(SUM(D45:G45)/SUM($D$111:$G$111))*SUM($AB$117:$AB$122) -> 162.71433 | AC45: =SUM(V45:AB45) -> 23516.913 | AD45: =SUM('ACTUAL EXP'!$G$37:$G$39)*ALLOCATION!P49 -> 460.71577 | AE45: =(AD45/$AD$111)*SUM($AD$117:$AD$122) -> 25.761193 | AF45: =SUM('ACTUAL EXP'!$G$41)*ALLOCATION!P49 -> 137.84121 | AG45: =(AF45/$AF$111)*SUM($AF$117:$AF$122) -> 7.7074721 | AH45: =SUM('ACTUAL EXP'!$G$81)*ALLOCATION!P49 -> 57.416225 | AI45: =(AH45/$AH$111)*SUM($AH$117:$AH$122) -> 3.2104619 | AJ45: =SUM('ACTUAL EXP'!$G$83)*ALLOCATION!P49 -> 426.29604 | AK45: =(AJ45/$AH$111)*SUM($AH$117:$AH$122) -> 23.836593 | AL45: =SUM('ACTUAL EXP'!$G$64:$G$66)*ALLOCATION!P49 -> 137.65787 | AM45: =(AL45/$AL$111)*SUM($AL$117:$AL$122) -> 7.6972204 | AN45: =SUM(AC45:AM45) -> 24805.053 | AO45: =-AN45 -> -24805.053 | AP45: (Z) | AQ45: =SUM(AO45,AN45) -> 0 | AS45: =AQ45-AR45 -> 0
A46: =ALLOCATION!A50 -> 312000 | B46: =ALLOCATION!C50 -> Convention Cntr ADS | C46: ='ACTUAL EXP'!$G$13*(ALLOCATION!P50) -> 5982.2638 | D46: =(SUM('ACTUAL EXP'!$G$15,'ACTUAL EXP'!$G$17:$G$19,'ACTUAL EXP'!$G$22))*ALLOCATION!P50 -> 9648.4584 | E46: =(('ACTUAL EXP'!$G$25)*(ALLOCATION!P50)) -> 0 | F46: ='ACTUAL EXP'!$G$28*ALLOCATION!P50 -> 0 | G46: 0 | H46: =SUM('ACTUAL EXP'!$G$30:$G$35)*ALLOCATION!P50 -> 8659.7528 | I46: =SUM('ACTUAL EXP'!$G$43:$G$47)*ALLOCATION!P50 -> 5230.7554 | J46: =(SUM('ACTUAL EXP'!$G$49:$G$50)*ALLOCATION!P50*0.5)+(SUM('ACTUAL EXP'!$G$49:$G$50)*ALLOCATION!P50*0.5) -> 2509.2876 | K46: =SUM('ACTUAL EXP'!$G$52:$G$53)*ALLOCATION!P50 -> 2648.2039 | L46: =SUM('ACTUAL EXP'!$G$54:$G$54)*ALLOCATION!P50 -> 361.11872 | M46: =SUM('ACTUAL EXP'!$G$21:$G$21)*ALLOCATION!P50 -> 111.27987 | N46: =SUM('ACTUAL EXP'!$G$58:$G$62)*0.39*ALLOCATION!P50 -> 1772.2756 | O46: =SUM('ACTUAL EXP'!$G$58:$G$62)*0.27*ALLOCATION!P50 -> 1226.96 | P46: =SUM('ACTUAL EXP'!$G$58:$G$62)*0.34*ALLOCATION!P50 -> 1545.0608 | Q46: ='ACTUAL EXP'!$G$85*ALLOCATION!P50 -> 2351.6798 | R46: =SUM('ACTUAL EXP'!$G$68:$G$73)*ALLOCATION!P50 -> 6414.193 | S46: =SUM('ACTUAL EXP'!$G$75)*ALLOCATION!P50 -> 898.28644 | T46: =SUM('ACTUAL EXP'!$G$77)*ALLOCATION!P50 -> 589.81123 | U46: =SUM('ACTUAL EXP'!$G$79)*ALLOCATION!P50 -> 893.85229 | V46: =SUM(C46:U46) -> 50843.24 | W46: =-(H46/$H$111)*($W$117) -> 457.92468 | X46: =-(Q46/$Q$111)*($X$118) -> 335.28743 | Y46: =-(SUM(J46:O46,R46:U46)/SUM($J$111:$O$111,$R$111:$U$111))*$Y$119 -> 1069.0635 | Z46: =-(C46/$C$111)*($Z$120) -> 438.48688 | AA46: =-(I46/$I$111)*($AA$121) -> 170.71059 | AB46: =-(SUM(D46:G46)/SUM($D$111:$G$111))*SUM($AB$117:$AB$122) -> 371.45646 | AC46: =SUM(V46:AB46) -> 53686.169 | AD46: =SUM('ACTUAL EXP'!$G$37:$G$39)*ALLOCATION!P50 -> 1051.7565 | AE46: =(AD46/$AD$111)*SUM($AD$117:$AD$122) -> 58.809579 | AF46: =SUM('ACTUAL EXP'!$G$41)*ALLOCATION!P50 -> 314.67424 | AG46: =(AF46/$AF$111)*SUM($AF$117:$AF$122) -> 17.595194 | AH46: =SUM('ACTUAL EXP'!$G$81)*ALLOCATION!P50 -> 131.07406 | AI46: =(AH46/$AH$111)*SUM($AH$117:$AH$122) -> 7.3290829 | AJ46: =SUM('ACTUAL EXP'!$G$83)*ALLOCATION!P50 -> 973.18053 | AK46: =(AJ46/$AH$111)*SUM($AH$117:$AH$122) -> 54.41596 | AL46: =SUM('ACTUAL EXP'!$G$64:$G$66)*ALLOCATION!P50 -> 314.25569 | AM46: =(AL46/$AL$111)*SUM($AL$117:$AL$122) -> 17.571791 | AN46: =SUM(AC46:AM46) -> 56626.832 | AO46: =-AN46 -> -56626.832 | AP46: (Z) | AQ46: =SUM(AO46,AN46) -> 0 | AS46: =AQ46-AR46 -> 0
A47: =ALLOCATION!A51 -> 309000 | B47: =ALLOCATION!C51 -> Lents Twn Ctr URA DR | C47: ='ACTUAL EXP'!$G$13*(ALLOCATION!P51) -> 4846.867 | D47: =(SUM('ACTUAL EXP'!$G$15,'ACTUAL EXP'!$G$17:$G$19,'ACTUAL EXP'!$G$22))*ALLOCATION!P51 -> 7817.2404 | E47: =(('ACTUAL EXP'!$G$25)*(ALLOCATION!P51)) -> 0 | F47: ='ACTUAL EXP'!$G$28*ALLOCATION!P51 -> 0 | G47: 0 | H47: =SUM('ACTUAL EXP'!$G$30:$G$35)*ALLOCATION!P51 -> 7016.1851 | I47: =SUM('ACTUAL EXP'!$G$43:$G$47)*ALLOCATION!P51 -> 4237.9902 | J47: =(SUM('ACTUAL EXP'!$G$49:$G$50)*ALLOCATION!P51*0.5)+(SUM('ACTUAL EXP'!$G$49:$G$50)*ALLOCATION!P51*0.5) -> 2033.0403 | K47: =SUM('ACTUAL EXP'!$G$52:$G$53)*ALLOCATION!P51 -> 2145.5911 | L47: =SUM('ACTUAL EXP'!$G$54:$G$54)*ALLOCATION!P51 -> 292.58061 | M47: =SUM('ACTUAL EXP'!$G$21:$G$21)*ALLOCATION!P51 -> 90.159638 | N47: =SUM('ACTUAL EXP'!$G$58:$G$62)*0.39*ALLOCATION!P51 -> 1435.9086 | O47: =SUM('ACTUAL EXP'!$G$58:$G$62)*0.27*ALLOCATION!P51 -> 994.09057 | P47: =SUM('ACTUAL EXP'!$G$58:$G$62)*0.34*ALLOCATION!P51 -> 1251.8177 | Q47: ='ACTUAL EXP'!$G$85*ALLOCATION!P51 -> 1905.3454 | R47: =SUM('ACTUAL EXP'!$G$68:$G$73)*ALLOCATION!P51 -> 5196.8187 | S47: =SUM('ACTUAL EXP'!$G$75)*ALLOCATION!P51 -> 727.79721 | T47: =SUM('ACTUAL EXP'!$G$77)*ALLOCATION!P51 -> 477.86869 | U47: =SUM('ACTUAL EXP'!$G$79)*ALLOCATION!P51 -> 724.20464 | V47: =SUM(C47:U47) -> 41193.506 | W47: =-(H47/$H$111)*($W$117) -> 371.0134 | X47: =-(Q47/$Q$111)*($X$118) -> 271.65195 | Y47: =-(SUM(J47:O47,R47:U47)/SUM($J$111:$O$111,$R$111:$U$111))*$Y$119 -> 866.16184 | Z47: =-(C47/$C$111)*($Z$120) -> 355.26477 | AA47: =-(I47/$I$111)*($AA$121) -> 138.31078 | AB47: =-(SUM(D47:G47)/SUM($D$111:$G$111))*SUM($AB$117:$AB$122) -> 300.95631 | AC47: =SUM(V47:AB47) -> 43496.865 | AD47: =SUM('ACTUAL EXP'!$G$37:$G$39)*ALLOCATION!P51 -> 852.13957 | AE47: =(AD47/$AD$111)*SUM($AD$117:$AD$122) -> 47.647884 | AF47: =SUM('ACTUAL EXP'!$G$41)*ALLOCATION!P51 -> 254.951 | AG47: =(AF47/$AF$111)*SUM($AF$117:$AF$122) -> 14.255735 | AH47: =SUM('ACTUAL EXP'!$G$81)*ALLOCATION!P51 -> 106.19701 | AI47: =(AH47/$AH$111)*SUM($AH$117:$AH$122) -> 5.9380681 | AJ47: =SUM('ACTUAL EXP'!$G$83)*ALLOCATION!P51 -> 788.47686 | AK47: =(AJ47/$AH$111)*SUM($AH$117:$AH$122) -> 44.088146 | AL47: =SUM('ACTUAL EXP'!$G$64:$G$66)*ALLOCATION!P51 -> 254.6119 | AM47: =(AL47/$AL$111)*SUM($AL$117:$AL$122) -> 14.236774 | AN47: =SUM(AC47:AM47) -> 45879.408 | AO47: =-AN47 -> -45879.408 | AP47: (Z) | AQ47: =SUM(AO47,AN47) -> 0 | AS47: =AQ47-AR47 -> 0
A48: =ALLOCATION!A52 -> 313000 | B48: =ALLOCATION!C52 -> N Macadam URA DR | C48: ='ACTUAL EXP'!$G$13*(ALLOCATION!P52) -> 7289.0984 | D48: =(SUM('ACTUAL EXP'!$G$15,'ACTUAL EXP'!$G$17:$G$19,'ACTUAL EXP'!$G$22))*ALLOCATION!P52 -> 11756.179 | E48: =(('ACTUAL EXP'!$G$25)*(ALLOCATION!P52)) -> 0 | F48: ='ACTUAL EXP'!$G$28*ALLOCATION!P52 -> 0 | G48: 0 | H48: =SUM('ACTUAL EXP'!$G$30:$G$35)*ALLOCATION!P52 -> 10551.489 | I48: =SUM('ACTUAL EXP'!$G$43:$G$47)*ALLOCATION!P52 -> 6373.4219 | J48: =(SUM('ACTUAL EXP'!$G$49:$G$50)*ALLOCATION!P52*0.5)+(SUM('ACTUAL EXP'!$G$49:$G$50)*ALLOCATION!P52*0.5) -> 3057.4454 | K48: =SUM('ACTUAL EXP'!$G$52:$G$53)*ALLOCATION!P52 -> 3226.7081 | L48: =SUM('ACTUAL EXP'!$G$54:$G$54)*ALLOCATION!P52 -> 440.00565 | M48: =SUM('ACTUAL EXP'!$G$21:$G$21)*ALLOCATION!P52 -> 135.58913 | N48: =SUM('ACTUAL EXP'!$G$58:$G$62)*0.39*ALLOCATION!P52 -> 2159.4319 | O48: =SUM('ACTUAL EXP'!$G$58:$G$62)*0.27*ALLOCATION!P52 -> 1494.9913 | P48: =SUM('ACTUAL EXP'!$G$58:$G$62)*0.34*ALLOCATION!P52 -> 1882.5816 | Q48: ='ACTUAL EXP'!$G$85*ALLOCATION!P52 -> 2865.4078 | R48: =SUM('ACTUAL EXP'!$G$68:$G$73)*ALLOCATION!P52 -> 7815.3832 | S48: =SUM('ACTUAL EXP'!$G$75)*ALLOCATION!P52 -> 1094.5185 | T48: =SUM('ACTUAL EXP'!$G$77)*ALLOCATION!P52 -> 718.65639 | U48: =SUM('ACTUAL EXP'!$G$79)*ALLOCATION!P52 -> 1089.1157 | V48: =SUM(C48:U48) -> 61950.023 | W48: =-(H48/$H$111)*($W$117) -> 557.95903 | X48: =-(Q48/$Q$111)*($X$118) -> 408.53149 | Y48: =-(SUM(J48:O48,R48:U48)/SUM($J$111:$O$111,$R$111:$U$111))*$Y$119 -> 1302.6021 | Z48: =-(C48/$C$111)*($Z$120) -> 534.275 | AA48: =-(I48/$I$111)*($AA$121) -> 208.00258 | AB48: =-(SUM(D48:G48)/SUM($D$111:$G$111))*SUM($AB$117:$AB$122) -> 452.60169 | AC48: =SUM(V48:AB48) -> 65413.995 | AD48: =SUM('ACTUAL EXP'!$G$37:$G$39)*ALLOCATION!P52 -> 1281.5143 | AE48: =(AD48/$AD$111)*SUM($AD$117:$AD$122) -> 71.656622 | AF48: =SUM('ACTUAL EXP'!$G$41)*ALLOCATION!P52 -> 383.4153 | AG48: =(AF48/$AF$111)*SUM($AF$117:$AF$122) -> 21.438892 | AH48: =SUM('ACTUAL EXP'!$G$81)*ALLOCATION!P52 -> 159.70739 | AI48: =(AH48/$AH$111)*SUM($AH$117:$AH$122) -> 8.9301322 | AJ48: =SUM('ACTUAL EXP'!$G$83)*ALLOCATION!P52 -> 1185.7733 | AK48: =(AJ48/$AH$111)*SUM($AH$117:$AH$122) -> 66.30321 | AL48: =SUM('ACTUAL EXP'!$G$64:$G$66)*ALLOCATION!P52 -> 382.90532 | AM48: =(AL48/$AL$111)*SUM($AL$117:$AL$122) -> 21.410376 | AN48: =SUM(AC48:AM48) -> 68997.049 | AO48: =-AN48 -> -68997.049 | AP48: (Z) | AQ48: =SUM(AO48,AN48) -> 0 | AS48: =AQ48-AR48 -> 0
A49: =ALLOCATION!A53 -> 314000 | B49: =ALLOCATION!C53 -> Special Prjt Dbt Svc | C49: ='ACTUAL EXP'!$G$13*(ALLOCATION!P53) -> 3024.8203 | D49: =(SUM('ACTUAL EXP'!$G$15,'ACTUAL EXP'!$G$17:$G$19,'ACTUAL EXP'!$G$22))*ALLOCATION!P53 -> 4878.5633 | E49: =(('ACTUAL EXP'!$G$25)*(ALLOCATION!P53)) -> 0 | F49: ='ACTUAL EXP'!$G$28*ALLOCATION!P53 -> 0 | G49: 0 | H49: =SUM('ACTUAL EXP'!$G$30:$G$35)*ALLOCATION!P53 -> 4378.6428 | I49: =SUM('ACTUAL EXP'!$G$43:$G$47)*ALLOCATION!P53 -> 2644.8341 | J49: =(SUM('ACTUAL EXP'!$G$49:$G$50)*ALLOCATION!P53*0.5)+(SUM('ACTUAL EXP'!$G$49:$G$50)*ALLOCATION!P53*0.5) -> 1268.7746 | K49: =SUM('ACTUAL EXP'!$G$52:$G$53)*ALLOCATION!P53 -> 1339.015 | L49: =SUM('ACTUAL EXP'!$G$54:$G$54)*ALLOCATION!P53 -> 182.59295 | M49: =SUM('ACTUAL EXP'!$G$21:$G$21)*ALLOCATION!P53 -> 56.266595 | N49: =SUM('ACTUAL EXP'!$G$58:$G$62)*0.39*ALLOCATION!P53 -> 896.11815 | O49: =SUM('ACTUAL EXP'!$G$58:$G$62)*0.27*ALLOCATION!P53 -> 620.38949 | P49: =SUM('ACTUAL EXP'!$G$58:$G$62)*0.34*ALLOCATION!P53 -> 781.23121 | Q49: ='ACTUAL EXP'!$G$85*ALLOCATION!P53 -> 1189.0831 | R49: =SUM('ACTUAL EXP'!$G$68:$G$73)*ALLOCATION!P53 -> 3243.2172 | S49: =SUM('ACTUAL EXP'!$G$75)*ALLOCATION!P53 -> 454.20181 | T49: =SUM('ACTUAL EXP'!$G$77)*ALLOCATION!P53 -> 298.22707 | U49: =SUM('ACTUAL EXP'!$G$79)*ALLOCATION!P53 -> 451.95977 | V49: =SUM(C49:U49) -> 25707.937 | W49: =-(H49/$H$111)*($W$117) -> 231.54109 | X49: =-(Q49/$Q$111)*($X$118) -> 169.53185 | Y49: =-(SUM(J49:O49,R49:U49)/SUM($J$111:$O$111,$R$111:$U$111))*$Y$119 -> 540.55206 | Z49: =-(C49/$C$111)*($Z$120) -> 221.71273 | AA49: =-(I49/$I$111)*($AA$121) -> 86.316634 | AB49: =-(SUM(D49:G49)/SUM($D$111:$G$111))*SUM($AB$117:$AB$122) -> 187.82004 | AC49: =SUM(V49:AB49) -> 27145.412 | AD49: =SUM('ACTUAL EXP'!$G$37:$G$39)*ALLOCATION!P53 -> 531.80107 | AE49: =(AD49/$AD$111)*SUM($AD$117:$AD$122) -> 29.735969 | AF49: =SUM('ACTUAL EXP'!$G$41)*ALLOCATION!P53 -> 159.10917 | AG49: =(AF49/$AF$111)*SUM($AF$117:$AF$122) -> 8.8966825 | AH49: =SUM('ACTUAL EXP'!$G$81)*ALLOCATION!P53 -> 66.275157 | AI49: =(AH49/$AH$111)*SUM($AH$117:$AH$122) -> 3.7058143 | AJ49: =SUM('ACTUAL EXP'!$G$83)*ALLOCATION!P53 -> 492.07062 | AK49: =(AJ49/$AH$111)*SUM($AH$117:$AH$122) -> 27.514417 | AL49: =SUM('ACTUAL EXP'!$G$64:$G$66)*ALLOCATION!P53 -> 158.89754 | AM49: =(AL49/$AL$111)*SUM($AL$117:$AL$122) -> 8.884849 | AN49: =SUM(AC49:AM49) -> 28632.303 | AO49: =-AN49 -> -28632.303 | AP49: (Z) | AQ49: =SUM(AO49,AN49) -> 0 | AS49: =AQ49-AR49 -> 0
A50: =ALLOCATION!A54 -> 315000 | B50: =ALLOCATION!C54 -> Gateway URA DR | C50: ='ACTUAL EXP'!$G$13*(ALLOCATION!P54) -> 1578.8771 | D50: =(SUM('ACTUAL EXP'!$G$15,'ACTUAL EXP'!$G$17:$G$19,'ACTUAL EXP'!$G$22))*ALLOCATION!P54 -> 2546.4826 | E50: =(('ACTUAL EXP'!$G$25)*(ALLOCATION!P54)) -> 0 | F50: ='ACTUAL EXP'!$G$28*ALLOCATION!P54 -> 0 | G50: 0 | H50: =SUM('ACTUAL EXP'!$G$30:$G$35)*ALLOCATION!P54 -> 2285.5371 | I50: =SUM('ACTUAL EXP'!$G$43:$G$47)*ALLOCATION!P54 -> 1380.5343 | J50: =(SUM('ACTUAL EXP'!$G$49:$G$50)*ALLOCATION!P54*0.5)+(SUM('ACTUAL EXP'!$G$49:$G$50)*ALLOCATION!P54*0.5) -> 662.26717 | K50: =SUM('ACTUAL EXP'!$G$52:$G$53)*ALLOCATION!P54 -> 698.93084 | L50: =SUM('ACTUAL EXP'!$G$54:$G$54)*ALLOCATION!P54 -> 95.30875 | M50: =SUM('ACTUAL EXP'!$G$21:$G$21)*ALLOCATION!P54 -> 29.369692 | N50: =SUM('ACTUAL EXP'!$G$58:$G$62)*0.39*ALLOCATION!P54 -> 467.75025 | O50: =SUM('ACTUAL EXP'!$G$58:$G$62)*0.27*ALLOCATION!P54 -> 323.8271 | P50: =SUM('ACTUAL EXP'!$G$58:$G$62)*0.34*ALLOCATION!P54 -> 407.78227 | Q50: ='ACTUAL EXP'!$G$85*ALLOCATION!P54 -> 620.67029 | R50: =SUM('ACTUAL EXP'!$G$68:$G$73)*ALLOCATION!P54 -> 1692.8746 | S50: =SUM('ACTUAL EXP'!$G$75)*ALLOCATION!P54 -> 237.08148 | T50: =SUM('ACTUAL EXP'!$G$77)*ALLOCATION!P54 -> 155.66673 | U50: =SUM('ACTUAL EXP'!$G$79)*ALLOCATION!P54 -> 235.91119 | V50: =SUM(C50:U50) -> 13418.871 | W50: =-(H50/$H$111)*($W$117) -> 120.8584 | X50: =-(Q50/$Q$111)*($X$118) -> 88.491194 | Y50: =-(SUM(J50:O50,R50:U50)/SUM($J$111:$O$111,$R$111:$U$111))*$Y$119 -> 282.15405 | Z50: =-(C50/$C$111)*($Z$120) -> 115.72825 | AA50: =-(I50/$I$111)*($AA$121) -> 45.055027 | AB50: =-(SUM(D50:G50)/SUM($D$111:$G$111))*SUM($AB$117:$AB$122) -> 98.037154 | AC50: =SUM(V50:AB50) -> 14169.196 | AD50: =SUM('ACTUAL EXP'!$G$37:$G$39)*ALLOCATION!P54 -> 277.58626 | AE50: =(AD50/$AD$111)*SUM($AD$117:$AD$122) -> 15.521399 | AF50: =SUM('ACTUAL EXP'!$G$41)*ALLOCATION!P54 -> 83.050828 | AG50: =(AF50/$AF$111)*SUM($AF$117:$AF$122) -> 4.6438357 | AH50: =SUM('ACTUAL EXP'!$G$81)*ALLOCATION!P54 -> 34.5939 | AI50: =(AH50/$AH$111)*SUM($AH$117:$AH$122) -> 1.9343382 | AJ50: =SUM('ACTUAL EXP'!$G$83)*ALLOCATION!P54 -> 256.848 | AK50: =(AJ50/$AH$111)*SUM($AH$117:$AH$122) -> 14.361807 | AL50: =SUM('ACTUAL EXP'!$G$64:$G$66)*ALLOCATION!P54 -> 82.940362 | AM50: =(AL50/$AL$111)*SUM($AL$117:$AL$122) -> 4.637659 | AN50: =SUM(AC50:AM50) -> 14945.314 | AO50: =-AN50 -> -14945.314 | AP50: (Z) | AQ50: =SUM(AO50,AN50) -> 0 | AS50: =AQ50-AR50 -> 0
A51: =ALLOCATION!A55 -> 213000 | B51: =ALLOCATION!C55 -> Housing Investment | C51: ='ACTUAL EXP'!$G$13*(ALLOCATION!P55) -> 23133.688 | D51: =(SUM('ACTUAL EXP'!$G$15,'ACTUAL EXP'!$G$17:$G$19,'ACTUAL EXP'!$G$22))*ALLOCATION!P55 -> 37311.031 | E51: =(('ACTUAL EXP'!$G$25)*(ALLOCATION!P55)) -> 0 | F51: ='ACTUAL EXP'!$G$28*ALLOCATION!P55 -> 0 | G51: 0 | H51: =SUM('ACTUAL EXP'!$G$30:$G$35)*ALLOCATION!P55 -> 33487.661 | I51: =SUM('ACTUAL EXP'!$G$43:$G$47)*ALLOCATION!P55 -> 20227.571 | J51: =(SUM('ACTUAL EXP'!$G$49:$G$50)*ALLOCATION!P55*0.5)+(SUM('ACTUAL EXP'!$G$49:$G$50)*ALLOCATION!P55*0.5) -> 9703.5304 | K51: =SUM('ACTUAL EXP'!$G$52:$G$53)*ALLOCATION!P55 -> 10240.726 | L51: =SUM('ACTUAL EXP'!$G$54:$G$54)*ALLOCATION!P55 -> 1396.4626 | M51: =SUM('ACTUAL EXP'!$G$21:$G$21)*ALLOCATION!P55 -> 430.32437 | N51: =SUM('ACTUAL EXP'!$G$58:$G$62)*0.39*ALLOCATION!P55 -> 6853.4709 | O51: =SUM('ACTUAL EXP'!$G$58:$G$62)*0.27*ALLOCATION!P55 -> 4744.7107 | P51: =SUM('ACTUAL EXP'!$G$58:$G$62)*0.34*ALLOCATION!P55 -> 5974.8208 | Q51: ='ACTUAL EXP'!$G$85*ALLOCATION!P55 -> 9094.0535 | R51: =SUM('ACTUAL EXP'!$G$68:$G$73)*ALLOCATION!P55 -> 24803.978 | S51: =SUM('ACTUAL EXP'!$G$75)*ALLOCATION!P55 -> 3473.7149 | T51: =SUM('ACTUAL EXP'!$G$77)*ALLOCATION!P55 -> 2280.8271 | U51: =SUM('ACTUAL EXP'!$G$79)*ALLOCATION!P55 -> 3456.5678 | V51: =SUM(C51:U51) -> 196613.14 | W51: =-(H51/$H$111)*($W$117) -> 1770.8157 | X51: =-(Q51/$Q$111)*($X$118) -> 1296.5719 | Y51: =-(SUM(J51:O51,R51:U51)/SUM($J$111:$O$111,$R$111:$U$111))*$Y$119 -> 4134.1176 | Z51: =-(C51/$C$111)*($Z$120) -> 1695.6489 | AA51: =-(I51/$I$111)*($AA$121) -> 660.1457 | AB51: =-(SUM(D51:G51)/SUM($D$111:$G$111))*SUM($AB$117:$AB$122) -> 1436.4392 | AC51: =SUM(V51:AB51) -> 207606.88 | AD51: =SUM('ACTUAL EXP'!$G$37:$G$39)*ALLOCATION!P55 -> 4067.1905 | AE51: =(AD51/$AD$111)*SUM($AD$117:$AD$122) -> 227.41934 | AF51: =SUM('ACTUAL EXP'!$G$41)*ALLOCATION!P55 -> 1216.8597 | AG51: =(AF51/$AF$111)*SUM($AF$117:$AF$122) -> 68.041424 | AH51: =SUM('ACTUAL EXP'!$G$81)*ALLOCATION!P55 -> 506.8694 | AI51: =(AH51/$AH$111)*SUM($AH$117:$AH$122) -> 28.3419 | AJ51: =SUM('ACTUAL EXP'!$G$83)*ALLOCATION!P55 -> 3763.3337 | AK51: =(AJ51/$AH$111)*SUM($AH$117:$AH$122) -> 210.42901 | AL51: =SUM('ACTUAL EXP'!$G$64:$G$66)*ALLOCATION!P55 -> 1215.2412 | AM51: =(AL51/$AL$111)*SUM($AL$117:$AL$122) -> 67.950922 | AN51: =SUM(AC51:AM51) -> 218978.55 | AQ51: =SUM(AO51,AN51) -> 218978.55 | AS51: =AQ51-AR51 -> 218978.55
A52: =ALLOCATION!A56 -> 210000 | B52: =ALLOCATION!C56 -> General Reserve | C52: ='ACTUAL EXP'!$G$13*(ALLOCATION!P56) -> 0 | D52: =(SUM('ACTUAL EXP'!$G$15,'ACTUAL EXP'!$G$17:$G$19,'ACTUAL EXP'!$G$22))*ALLOCATION!P56 -> 0 | E52: =(('ACTUAL EXP'!$G$25)*(ALLOCATION!P56)) -> 0 | F52: ='ACTUAL EXP'!$G$28*ALLOCATION!P56 -> 0 | G52: 0 | H52: =SUM('ACTUAL EXP'!$G$30:$G$35)*ALLOCATION!P56 -> 0 | I52: =SUM('ACTUAL EXP'!$G$43:$G$47)*ALLOCATION!P56 -> 0 | J52: =(SUM('ACTUAL EXP'!$G$49:$G$50)*ALLOCATION!P56*0.5)+(SUM('ACTUAL EXP'!$G$49:$G$50)*ALLOCATION!P56*0.5) -> 0 | K52: =SUM('ACTUAL EXP'!$G$52:$G$53)*ALLOCATION!P56 -> 0 | L52: =SUM('ACTUAL EXP'!$G$54:$G$54)*ALLOCATION!P56 -> 0 | M52: =SUM('ACTUAL EXP'!$G$21:$G$21)*ALLOCATION!P56 -> 0 | N52: =SUM('ACTUAL EXP'!$G$58:$G$62)*0.39*ALLOCATION!P56 -> 0 | O52: =SUM('ACTUAL EXP'!$G$58:$G$62)*0.27*ALLOCATION!P56 -> 0 | P52: =SUM('ACTUAL EXP'!$G$58:$G$62)*0.34*ALLOCATION!P56 -> 0 | Q52: ='ACTUAL EXP'!$G$85*ALLOCATION!P56 -> 0 | R52: =SUM('ACTUAL EXP'!$G$68:$G$73)*ALLOCATION!P56 -> 0 | S52: =SUM('ACTUAL EXP'!$G$75)*ALLOCATION!P56 -> 0 | T52: =SUM('ACTUAL EXP'!$G$77)*ALLOCATION!P56 -> 0 | U52: =SUM('ACTUAL EXP'!$G$79)*ALLOCATION!P56 -> 0 | V52: =SUM(C52:U52) -> 0 | W52: =-(H52/$H$111)*($W$117) -> 0 | X52: =-(Q52/$Q$111)*($X$118) -> 0 | Y52: =-(SUM(J52:O52,R52:U52)/SUM($J$111:$O$111,$R$111:$U$111))*$Y$119 -> 0 | Z52: =-(C52/$C$111)*($Z$120) -> 0 | AA52: =-(I52/$I$111)*($AA$121) -> 0 | AB52: =-(SUM(D52:G52)/SUM($D$111:$G$111))*SUM($AB$117:$AB$122) -> 0 | AC52: =SUM(V52:AB52) -> 0 | AD52: =SUM('ACTUAL EXP'!$G$37:$G$39)*ALLOCATION!P56 -> 0 | AE52: =(AD52/$AD$111)*SUM($AD$117:$AD$122) -> 0 | AF52: =SUM('ACTUAL EXP'!$G$41)*ALLOCATION!P56 -> 0 | AG52: =(AF52/$AF$111)*SUM($AF$117:$AF$122) -> 0 | AH52: =SUM('ACTUAL EXP'!$G$81)*ALLOCATION!P56 -> 0 | AI52: =(AH52/$AH$111)*SUM($AH$117:$AH$122) -> 0 | AJ52: =SUM('ACTUAL EXP'!$G$83)*ALLOCATION!P56 -> 0 | AK52: =(AJ52/$AH$111)*SUM($AH$117:$AH$122) -> 0 | AL52: =SUM('ACTUAL EXP'!$G$64:$G$66)*ALLOCATION!P56 -> 0 | AM52: =(AL52/$AL$111)*SUM($AL$117:$AL$122) -> 0 | AN52: =SUM(AC52:AM52) -> 0 | AO52: =-AN52 -> 0 | AP52: (Z) | AQ52: =SUM(AO52,AN52) -> 0 | AS52: =AQ52-AR52 -> 0
A53: =ALLOCATION!A57 -> 304000 | B53: =ALLOCATION!C57 -> Interstate C Dbt Svc | C53: ='ACTUAL EXP'!$G$13*(ALLOCATION!P57) -> 6658.0062 | D53: =(SUM('ACTUAL EXP'!$G$15,'ACTUAL EXP'!$G$17:$G$19,'ACTUAL EXP'!$G$22))*ALLOCATION!P57 -> 10738.326 | E53: =(('ACTUAL EXP'!$G$25)*(ALLOCATION!P57)) -> 0 | F53: ='ACTUAL EXP'!$G$28*ALLOCATION!P57 -> 0 | G53: 0 | H53: =SUM('ACTUAL EXP'!$G$30:$G$35)*ALLOCATION!P57 -> 9637.9381 | I53: =SUM('ACTUAL EXP'!$G$43:$G$47)*ALLOCATION!P57 -> 5821.6092 | J53: =(SUM('ACTUAL EXP'!$G$49:$G$50)*ALLOCATION!P57*0.5)+(SUM('ACTUAL EXP'!$G$49:$G$50)*ALLOCATION!P57*0.5) -> 2792.7309 | K53: =SUM('ACTUAL EXP'!$G$52:$G$53)*ALLOCATION!P57 -> 2947.3388 | L53: =SUM('ACTUAL EXP'!$G$54:$G$54)*ALLOCATION!P57 -> 401.90984 | M53: =SUM('ACTUAL EXP'!$G$21:$G$21)*ALLOCATION!P57 -> 123.84978 | N53: =SUM('ACTUAL EXP'!$G$58:$G$62)*0.39*ALLOCATION!P57 -> 1972.4677 | O53: =SUM('ACTUAL EXP'!$G$58:$G$62)*0.27*ALLOCATION!P57 -> 1365.5545 | P53: =SUM('ACTUAL EXP'!$G$58:$G$62)*0.34*ALLOCATION!P57 -> 1719.5872 | Q53: ='ACTUAL EXP'!$G$85*ALLOCATION!P57 -> 2617.32 | R53: =SUM('ACTUAL EXP'!$G$68:$G$73)*ALLOCATION!P57 -> 7138.7251 | S53: =SUM('ACTUAL EXP'!$G$75)*ALLOCATION!P57 -> 999.75476 | T53: =SUM('ACTUAL EXP'!$G$77)*ALLOCATION!P57 -> 656.43492 | U53: =SUM('ACTUAL EXP'!$G$79)*ALLOCATION!P57 -> 994.81974 | V53: =SUM(C53:U53) -> 56586.372 | W53: =-(H53/$H$111)*($W$117) -> 509.65078 | X53: =-(Q53/$Q$111)*($X$118) -> 373.16071 | Y53: =-(SUM(J53:O53,R53:U53)/SUM($J$111:$O$111,$R$111:$U$111))*$Y$119 -> 1189.8224 | Z53: =-(C53/$C$111)*($Z$120) -> 488.01732 | AA53: =-(I53/$I$111)*($AA$121) -> 189.99366 | AB53: =-(SUM(D53:G53)/SUM($D$111:$G$111))*SUM($AB$117:$AB$122) -> 413.41531 | AC53: =SUM(V53:AB53) -> 59750.432 | AD53: =SUM('ACTUAL EXP'!$G$37:$G$39)*ALLOCATION!P57 -> 1170.5604 | AE53: =(AD53/$AD$111)*SUM($AD$117:$AD$122) -> 65.452571 | AF53: =SUM('ACTUAL EXP'!$G$41)*ALLOCATION!P57 -> 350.2191 | AG53: =(AF53/$AF$111)*SUM($AF$117:$AF$122) -> 19.582706 | AH53: =SUM('ACTUAL EXP'!$G$81)*ALLOCATION!P57 -> 145.87988 | AI53: =(AH53/$AH$111)*SUM($AH$117:$AH$122) -> 8.1569589 | AJ53: =SUM('ACTUAL EXP'!$G$83)*ALLOCATION!P57 -> 1083.1087 | AK53: =(AJ53/$AH$111)*SUM($AH$117:$AH$122) -> 60.562659 | AL53: =SUM('ACTUAL EXP'!$G$64:$G$66)*ALLOCATION!P57 -> 349.75327 | AM53: =(AL53/$AL$111)*SUM($AL$117:$AL$122) -> 19.556659 | AN53: =SUM(AC53:AM53) -> 63023.265 | AO53: =-AN53 -> -63023.265 | AP53: (Z) | AQ53: =SUM(AO53,AN53) -> 0 | AS53: =AQ53-AR53 -> 0
A54: =ALLOCATION!A58 -> 100000 | B54: =ALLOCATION!C58 -> General Fund Contingency | C54: ='ACTUAL EXP'!$G$13*(ALLOCATION!P58) -> 0 | D54: =(SUM('ACTUAL EXP'!$G$15,'ACTUAL EXP'!$G$17:$G$19,'ACTUAL EXP'!$G$22))*ALLOCATION!P58 -> 0 | E54: =(('ACTUAL EXP'!$G$25)*(ALLOCATION!P58)) -> 0 | F54: ='ACTUAL EXP'!$G$28*ALLOCATION!P58 -> 0 | G54: 0 | H54: =SUM('ACTUAL EXP'!$G$30:$G$35)*ALLOCATION!P58 -> 0 | I54: =SUM('ACTUAL EXP'!$G$43:$G$47)*ALLOCATION!P58 -> 0 | J54: =(SUM('ACTUAL EXP'!$G$49:$G$50)*ALLOCATION!P58*0.5)+(SUM('ACTUAL EXP'!$G$49:$G$50)*ALLOCATION!P58*0.5) -> 0 | K54: =SUM('ACTUAL EXP'!$G$52:$G$53)*ALLOCATION!P58 -> 0 | L54: =SUM('ACTUAL EXP'!$G$54:$G$54)*ALLOCATION!P58 -> 0 | M54: =SUM('ACTUAL EXP'!$G$21:$G$21)*ALLOCATION!P58 -> 0 | N54: =SUM('ACTUAL EXP'!$G$58:$G$62)*0.39*ALLOCATION!P58 -> 0 | O54: =SUM('ACTUAL EXP'!$G$58:$G$62)*0.27*ALLOCATION!P58 -> 0 | P54: =SUM('ACTUAL EXP'!$G$58:$G$62)*0.34*ALLOCATION!P58 -> 0 | Q54: ='ACTUAL EXP'!$G$85*ALLOCATION!P58 -> 0 | R54: =SUM('ACTUAL EXP'!$G$68:$G$73)*ALLOCATION!P58 -> 0 | S54: =SUM('ACTUAL EXP'!$G$75)*ALLOCATION!P58 -> 0 | T54: =SUM('ACTUAL EXP'!$G$77)*ALLOCATION!P58 -> 0 | U54: =SUM('ACTUAL EXP'!$G$79)*ALLOCATION!P58 -> 0 | V54: =SUM(C54:U54) -> 0 | W54: =-(H54/$H$111)*($W$117) -> 0 | X54: =-(Q54/$Q$111)*($X$118) -> 0 | Y54: =-(SUM(J54:O54,R54:U54)/SUM($J$111:$O$111,$R$111:$U$111))*$Y$119 -> 0 | Z54: =-(C54/$C$111)*($Z$120) -> 0 | AA54: =-(I54/$I$111)*($AA$121) -> 0 | AB54: =-(SUM(D54:G54)/SUM($D$111:$G$111))*SUM($AB$117:$AB$122) -> 0 | AC54: =SUM(V54:AB54) -> 0 | AD54: =SUM('ACTUAL EXP'!$G$37:$G$39)*ALLOCATION!P58 -> 0 | AE54: =(AD54/$AD$111)*SUM($AD$117:$AD$122) -> 0 | AF54: =SUM('ACTUAL EXP'!$G$41)*ALLOCATION!P58 -> 0 | AG54: =(AF54/$AF$111)*SUM($AF$117:$AF$122) -> 0 | AH54: =SUM('ACTUAL EXP'!$G$81)*ALLOCATION!P58 -> 0 | AI54: =(AH54/$AH$111)*SUM($AH$117:$AH$122) -> 0 | AJ54: =SUM('ACTUAL EXP'!$G$83)*ALLOCATION!P58 -> 0 | AK54: =(AJ54/$AH$111)*SUM($AH$117:$AH$122) -> 0 | AL54: =SUM('ACTUAL EXP'!$G$64:$G$66)*ALLOCATION!P58 -> 0 | AM54: =(AL54/$AL$111)*SUM($AL$117:$AL$122) -> 0 | AN54: =SUM(AC54:AM54) -> 0 | AO54: =-AN54 -> 0 | AP54: (Z) | AQ54: =SUM(AO54,AN54) -> 0 | AS54: =AQ54-AR54 -> 0
A55: =ALLOCATION!A59 -> 100000 | B55: =ALLOCATION!C59 -> Gen Fund Reimb Expenditures | C55: ='ACTUAL EXP'!$G$13*(ALLOCATION!P59) -> 0 | D55: =(SUM('ACTUAL EXP'!$G$15,'ACTUAL EXP'!$G$17:$G$19,'ACTUAL EXP'!$G$22))*ALLOCATION!P59 -> 0 | E55: =(('ACTUAL EXP'!$G$25)*(ALLOCATION!P59)) -> 0 | F55: ='ACTUAL EXP'!$G$28*ALLOCATION!P59 -> 0 | G55: 0 | H55: =SUM('ACTUAL EXP'!$G$30:$G$35)*ALLOCATION!P59 -> 0 | I55: =SUM('ACTUAL EXP'!$G$43:$G$47)*ALLOCATION!P59 -> 0 | J55: =(SUM('ACTUAL EXP'!$G$49:$G$50)*ALLOCATION!P59*0.5)+(SUM('ACTUAL EXP'!$G$49:$G$50)*ALLOCATION!P59*0.5) -> 0 | K55: =SUM('ACTUAL EXP'!$G$52:$G$53)*ALLOCATION!P59 -> 0 | L55: =SUM('ACTUAL EXP'!$G$54:$G$54)*ALLOCATION!P59 -> 0 | M55: =SUM('ACTUAL EXP'!$G$21:$G$21)*ALLOCATION!P59 -> 0 | N55: =SUM('ACTUAL EXP'!$G$58:$G$62)*0.39*ALLOCATION!P59 -> 0 | O55: =SUM('ACTUAL EXP'!$G$58:$G$62)*0.27*ALLOCATION!P59 -> 0 | P55: =SUM('ACTUAL EXP'!$G$58:$G$62)*0.34*ALLOCATION!P59 -> 0 | Q55: ='ACTUAL EXP'!$G$85*ALLOCATION!P59 -> 0 | R55: =SUM('ACTUAL EXP'!$G$68:$G$73)*ALLOCATION!P59 -> 0 | S55: =SUM('ACTUAL EXP'!$G$75)*ALLOCATION!P59 -> 0 | T55: =SUM('ACTUAL EXP'!$G$77)*ALLOCATION!P59 -> 0 | U55: =SUM('ACTUAL EXP'!$G$79)*ALLOCATION!P59 -> 0 | V55: =SUM(C55:U55) -> 0 | W55: =-(H55/$H$111)*($W$117) -> 0 | X55: =-(Q55/$Q$111)*($X$118) -> 0 | Y55: =-(SUM(J55:O55,R55:U55)/SUM($J$111:$O$111,$R$111:$U$111))*$Y$119 -> 0 | Z55: =-(C55/$C$111)*($Z$120) -> 0 | AA55: =-(I55/$I$111)*($AA$121) -> 0 | AB55: =-(SUM(D55:G55)/SUM($D$111:$G$111))*SUM($AB$117:$AB$122) -> 0 | AC55: =SUM(V55:AB55) -> 0 | AD55: =SUM('ACTUAL EXP'!$G$37:$G$39)*ALLOCATION!P59 -> 0 | AE55: =(AD55/$AD$111)*SUM($AD$117:$AD$122) -> 0 | AF55: =SUM('ACTUAL EXP'!$G$41)*ALLOCATION!P59 -> 0 | AG55: =(AF55/$AF$111)*SUM($AF$117:$AF$122) -> 0 | AH55: =SUM('ACTUAL EXP'!$G$81)*ALLOCATION!P59 -> 0 | AI55: =(AH55/$AH$111)*SUM($AH$117:$AH$122) -> 0 | AJ55: =SUM('ACTUAL EXP'!$G$83)*ALLOCATION!P59 -> 0 | AK55: =(AJ55/$AH$111)*SUM($AH$117:$AH$122) -> 0 | AL55: =SUM('ACTUAL EXP'!$G$64:$G$66)*ALLOCATION!P59 -> 0 | AM55: =(AL55/$AL$111)*SUM($AL$117:$AL$122) -> 0 | AN55: =SUM(AC55:AM55) -> 0 | AO55: =-AN55 -> 0 | AP55: (Z) | AQ55: =SUM(AO55,AN55) -> 0 | AS55: =AQ55-AR55 -> 0 | AT55: LEGEND FOR
A56: =ALLOCATION!A60 -> 100000 | B56: =ALLOCATION!C60 -> General Fund Transfers | C56: ='ACTUAL EXP'!$G$13*(ALLOCATION!P60) -> 0 | D56: =(SUM('ACTUAL EXP'!$G$15,'ACTUAL EXP'!$G$17:$G$19,'ACTUAL EXP'!$G$22))*ALLOCATION!P60 -> 0 | E56: =(('ACTUAL EXP'!$G$25)*(ALLOCATION!P60)) -> 0 | F56: ='ACTUAL EXP'!$G$28*ALLOCATION!P60 -> 0 | G56: 0 | H56: =SUM('ACTUAL EXP'!$G$30:$G$35)*ALLOCATION!P60 -> 0 | I56: =SUM('ACTUAL EXP'!$G$43:$G$47)*ALLOCATION!P60 -> 0 | J56: =(SUM('ACTUAL EXP'!$G$49:$G$50)*ALLOCATION!P60*0.5)+(SUM('ACTUAL EXP'!$G$49:$G$50)*ALLOCATION!P60*0.5) -> 0 | K56: =SUM('ACTUAL EXP'!$G$52:$G$53)*ALLOCATION!P60 -> 0 | L56: =SUM('ACTUAL EXP'!$G$54:$G$54)*ALLOCATION!P60 -> 0 | M56: =SUM('ACTUAL EXP'!$G$21:$G$21)*ALLOCATION!P60 -> 0 | N56: =SUM('ACTUAL EXP'!$G$58:$G$62)*0.39*ALLOCATION!P60 -> 0 | O56: =SUM('ACTUAL EXP'!$G$58:$G$62)*0.27*ALLOCATION!P60 -> 0 | P56: =SUM('ACTUAL EXP'!$G$58:$G$62)*0.34*ALLOCATION!P60 -> 0 | Q56: ='ACTUAL EXP'!$G$85*ALLOCATION!P60 -> 0 | R56: =SUM('ACTUAL EXP'!$G$68:$G$73)*ALLOCATION!P60 -> 0 | S56: =SUM('ACTUAL EXP'!$G$75)*ALLOCATION!P60 -> 0 | T56: =SUM('ACTUAL EXP'!$G$77)*ALLOCATION!P60 -> 0 | U56: =SUM('ACTUAL EXP'!$G$79)*ALLOCATION!P60 -> 0 | V56: =SUM(C56:U56) -> 0 | W56: =-(H56/$H$111)*($W$117) -> 0 | X56: =-(Q56/$Q$111)*($X$118) -> 0 | Y56: =-(SUM(J56:O56,R56:U56)/SUM($J$111:$O$111,$R$111:$U$111))*$Y$119 -> 0 | Z56: =-(C56/$C$111)*($Z$120) -> 0 | AA56: =-(I56/$I$111)*($AA$121) -> 0 | AB56: =-(SUM(D56:G56)/SUM($D$111:$G$111))*SUM($AB$117:$AB$122) -> 0 | AC56: =SUM(V56:AB56) -> 0 | AD56: =SUM('ACTUAL EXP'!$G$37:$G$39)*ALLOCATION!P60 -> 0 | AE56: =(AD56/$AD$111)*SUM($AD$117:$AD$122) -> 0 | AF56: =SUM('ACTUAL EXP'!$G$41)*ALLOCATION!P60 -> 0 | AG56: =(AF56/$AF$111)*SUM($AF$117:$AF$122) -> 0 | AH56: =SUM('ACTUAL EXP'!$G$81)*ALLOCATION!P60 -> 0 | AI56: =(AH56/$AH$111)*SUM($AH$117:$AH$122) -> 0 | AJ56: =SUM('ACTUAL EXP'!$G$83)*ALLOCATION!P60 -> 0 | AK56: =(AJ56/$AH$111)*SUM($AH$117:$AH$122) -> 0 | AL56: =SUM('ACTUAL EXP'!$G$64:$G$66)*ALLOCATION!P60 -> 0 | AM56: =(AL56/$AL$111)*SUM($AL$117:$AL$122) -> 0 | AN56: =SUM(AC56:AM56) -> 0 | AO56: =-AN56 -> 0 | AP56: (Z) | AQ56: =SUM(AO56,AN56) -> 0 | AS56: =AQ56-AR56 -> 0 | AT56: ADJUSTMENT
