Workbook

Sheet Instructivo
B1: INSTRUCTIVO ELABORACION PRESUPUESTO
B3: Para el diligenciamiento del presupuesto favor tener presente las siguientes instrucciones:
A5: Observación General: | B5: Por motivos presupuestales y con el fin que tanto el Receptor Principal (CHF) y las EE, manejen los mismos terminos en cuanto a la ejecución presupuestal, se hace la claridad que este presupuesto se debe preparar trimestralmente y teniendo en cuenta la vigencia aprobada por el fondo mundial. Para esto se hace necesario aclarar algunos parametros a tener en cuenta en la elaboracion de este presupuesto: El año 1 del proyecto VIH abarca el período (Abril1, 2011-Marzo31,2012). Por tanto El trimestre 4 del año 1 para este ejercicio es el período comprendido Enero1-Marzo31,2012 El año 2 del proyecto VIH abarca el período (Abril1, 2012-Marzo31,2013).
B7: RECURSO HUMANO
B9: Esta representado en el recurso humano administrativo y programatico, mediante los siguientes cargos:
B10: Coordinador
B11: Profesionales en Salud Sexual y Reproductiva
B12: Técnicos en Salud Sexual y Reproductiva (SSR)
B13: Contador
B14: Asistente de Información
B15: Apoyo a la Direccion o Representación Legal (esta posición corresponde como su nombre lo indica a un apoyo a la representación legal y estará representado por un valor no superior al 2% del total del presupuesto asignado a la entidad ejecutora sin incluir los rubros de destinación especifica y no deberá ser mayor al salario u honorario mensual de esa posición en su organización. Para ello deberán enviar a CHF soporte del pago mensual o contrato para validar el valor cobrado al proyecto.
A17: Hipotesis | B17: Deberán registrar la manera como se obtiene el costo presupuestado, teniendo en cuenta los rangos mencionados en los términos de referencia
A18: Unidad de Medida | B18: Deberán registrar la unidad de medida con la que se presupuesto, ej (si es salario, o contrato prestacion servicios, jornal, etc)
A19: Costo unitario | B19: Deberán registrar el valor trimestral del salario u honorario de la posición presupuestada (ej: tomar el salario u honorario mensual de los profesionales en salud y multiplicarlo por 3)
A20: Cantidad trimestre xx | B20: Se deberar colocar el numero de posiciones que requieren para esa línea que estan presupuestando.
B23: MONITOREO Y EVALUACION
A24: Hipotesis | B24: Deberán registrar la manera como obtuvieron los costos unitarios presupuestados por las 4 líneas solicitadas (Viaticos, Desplazamientos, Actividades de Gestión y Actividades Servicios Comunitarios )
A25: Unidad de Medida | B25: Deberán registrar la unidad medida con la que realizaron el presupuesto, es decir, para viaticos: el valor viatico por municipio, para desplazamientos será el costo del trayecto ida y vuelta, para las actividades de gestión, sera costo reunión, para las actividades de servicios comunitarios , la unidad de medida será fondo actividades y este será determinado una vez identifiquen la actividad a realizar y estará sujeta a aprobación por parte de CHF)
A26: Costo unitario | B26: Viaticos y Desplazamientos : estarán sujetos a las políticas y procedimientos de su organización, y deberán detallar en esta línea el costo por viaje. Para el caso de las Actividades de Gestión, el costo unitario es $30.000 mensuales Para las Actividades de Servicios Comunitarios el valor mensual será de $200.000 y deberan multiplicarlo por 3, pues la unidad es trimestral y estará sujeto a las propuestas que envien para aprobación de CHF
A27: Cantidad trimestre xx | B27: Para el tema de viajes y desplazamientos, deberán registrar el numero de viajes a realizar . Para las actividades de gestion y las actividades de servicios comunitarios la cantidad es 1, puesto que el costo unitario es trimestral y se presupuesto una sóla por actividad por mes .
B30: PLANIFICACION Y ADMINISTRACION
A31: Hipotesis | B31: Deberán insertar tantas filas como itmes a presupuestar (ej: arriendo, servicios públicos .. Los descritos en el presupuesto)
A32: Unidad de Medida | B32: La unidad de medida sera la correspondiente al rubro en mención, (ej: para arriendo, la unidad de medida será apoyo mensual arriendo, etc…)
A33: Costo unitario | B33: El costo unitario es el valor trimestral de la línea presupuestada, (ej: arriendo, sera el valor mensual por este concepto por 3 meses)
A34: Cantidad trimestre xx | B34: La cantidad será 1 pues el costo unitario esta dado en trimestres.
B36: DESTINACION ESPECIFICA
B37: Estas son partidas que tienen actividades y costos fijos, los cuales son immodificables. Cualquier exceso en el desarrollo de las actividades deberan ser asumidos por la Entidad Ejecutora.
B39: BRIGADAS
B40: Corresponde al costo entregado al lider comunitario para realizar brigadas . Este costo es dado por CHF y no podrá ser utilizado en otro concepto.
B42: ASISTENCIA TECNICA SERVICIO COMUNITARIO
B43: Corresponde a $36.000 por hora para realizar visitas de fortalecimiento y capacitación a los servicios comunitarios en las necesidades identificadas en la evaluación de necesidades. El primera año serán visitas de 24 horas por servicio comunitario pues es el inicio del proceso y el segundo año serán visitas de 12 horas las cuales son de seguimiento y refuerzo. Este costo es dado por CHF y no podrá ser utilizado en otro concepto.
B45: ENCUENTROS PARA CAMPAÑAS ALTERNATIVAS
B46: Es un costo para realizar de manera creativa y alternativa campañas para la movilización social en torno a la prevención del VIH y la promoción de la solidaridad frente a los grupos clave. Este costo es dado por CHF y no podrá ser utilizado en otro concepto.
B48: ENCUENTROS GRUPOS CLAVE
B49: Este costo incluye un apoyo para las reuniones el cual esta dado en agua, café, apoyo alquiler salón.
B51: INCENTIVOS
B52: Este costo corresponde a un apoyo de 3 meses para vincular laboralmente a las mujeres beneficiadas del proyecto. Este costo es dado por CHF y no podrá ser utilizado en otro concepto.
A54: Tope Presupuestal | B54: Es es el presupuesto asignado por cada rubro del presupuesto aprobado por departamento o unión de departamentos. Como su nombre lo indica es el limite prespuestal hasta el cual debe llegar la entidad ejecutora proponente.

Sheet Summary Ant-Choco
A1: PRESUPUESTO ENTIDADES EJECUTORAS
A2: ANTIOQUIA y CHOCO
A4: Nombre Entidad Ejecutora:
A6: Detalle | B6: Presupuesto Total | C6: Tope Presupuestal
A7: Recurso Humano | B7: =+'Fase I Antio-Choco'!AH4 -> 0 | C7: =+'Fase I Antio-Choco'!AI4 -> 622607089
A8: Monitoreo y Evaluación | B8: =+'Fase I Antio-Choco'!AH11 -> 0 | C8: =+'Fase I Antio-Choco'!AI11 -> 186782123
A9: Planeación y Administración | B9: =+'Fase I Antio-Choco'!AH28 -> 0 | C9: =+'Fase I Antio-Choco'!AI28 -> 80049491
A10: Total Rubros de Funcionamiento | B10: =SUM(B7:B9) -> 0 | C10: =SUM(C7:C9) -> 889438703
A12: Destinación Específica | B12: =+'Fase I Antio-Choco'!AH39 -> 279396135 | C12: =+'Fase I Antio-Choco'!AI39 -> 279396135
A13: Total Destinación Específica | B13: =+B12 -> 279396135 | C13: =+C12 -> 279396135
A14: PRESUPUESTO TOTAL | B14: =+B10+B13 -> 279396135 | C14: =+C10+C13 -> 1168834838
A19: XXXXXX
A20: REPRESENTANTE LEGAL

Sheet Fase I Antio-Choco
A1: PRESUPUESTO DETALLADO
A2: No | B2: No de Objetivo: Crear capacidad comunitaria para la adopción de comportamientos seguros, la reducción de la vulnerabilidad social al VIH y el empoderamiento de los grupos clave priorizados | C2: Área de prestación de servicios (APS) | D2: Macro-Categoría | E2: Tarea | F2: Sub -Tarea | G2: Descripción / Hipotesis | H2: Año 1 | I2: Año 2 | M2: Responsable de la ejecución | N2: Tipo de entidad ejecutora | O2: Categorías de costos | P2: Unidad de medida año 1 | Q2: Costo unitario año 1 (valor trimestre) | R2: Cantidad Trimestre 4 | S2: Importe total Trimestre 4 | T2: Cantidad total Año 1 | U2: Total Año 1 | V2: Unidad de medida año 2 | W2: Costo unitario año 2 (valor trimestre) | X2: Cantidad Trimestre 1 año 2 | Y2: Importe total Trimestre 1 año 2 | Z2: Cantidad Trimestre 2 año 2 | AA2: Importe total Trimestre 2 año 2 | AB2: Cantidad Trimestre 3 año 2 | AC2: Importe total Trimestre 3 año 2 | AD2: Cantidad Trimestre 4 año 2 | AE2: Importe total Trimestre 4 año 2 | AF2: Cantidad total Año 2 | AG2: Total Año 2 | AH2: COSTO TOTAL | AI2: Tope Presupuestal
C3: SDA | D3: Activity | H3: T4 | I3: T1 | J3: T2 | K3: T3 | L3: T4
A4: RECURSO HUMANO | AH4: =SUM(AH5:AH10) -> 0 | AI4: 622607089
A5: 7 | B5: 1 | C5: Refuerzo de la sociedad civil | D5: 1.1 Implementar estrategias de promoción de la demanda de asesoría y prueba voluntaria (APV) y de comunicación para el cambio de comportamiento (CCC) | E5: 1.1.5 Identificar y formar líderes pares de los grupos clave priorizados para que actúen como formadores e integren los equipos locales de promoción de la salud y prevención del VIH e ITS | F5: Costo recurso humano administración de la entidad ejecutora | G5: Contador | M5: Entidad Ejecutora | N5: ONG/OBC/Sector Académico | O5: Recursos Humanos | P5: Salario / Honorario | S5: =+R5*Q5 -> 0 | T5: =+R5 -> 0 | U5: =S5 -> 0 | V5: Salario / Honorario | Y5: =+W5*X5 -> 0 | AA5: =+Z5*W5 -> 0 | AC5: =+AB5*W5 -> 0 | AE5: =+AD5*W5 -> 0 | AF5: =+X5+Z5+AB5+AD5 -> 0 | AG5: =+Y5+AA5+AC5+AE5 -> 0 | AH5: =+U5+AG5 -> 0
A6: 7 | B6: 1 | G6: Apoyo a la Dirección o Representación Legal | M6: Entidad Ejecutora | N6: ONG/OBC/Sector Académico | O6: Recursos Humanos | P6: Salario / Honorario | S6: =+R6*Q6 -> 0 | T6: =+R6 -> 0 | U6: =S6 -> 0 | V6: Salario / Honorario | Y6: =+W6*X6 -> 0 | AA6: =+Z6*W6 -> 0 | AC6: =+AB6*W6 -> 0 | AE6: =+AD6*W6 -> 0 | AF6: =+X6+Z6+AB6+AD6 -> 0 | AG6: =+Y6+AA6+AC6+AE6 -> 0 | AH6: =+U6+AG6 -> 0
A7: 7 | B7: 1 | G7: Asistente de Información | M7: Entidad Ejecutora | N7: ONG/OBC/Sector Académico | O7: Recursos Humanos | P7: Salario / Honorario | S7: =+R7*Q7 -> 0 | T7: =+R7 -> 0 | U7: =S7 -> 0 | V7: Salario / Honorario | Y7: =+W7*X7 -> 0 | AA7: =+Z7*W7 -> 0 | AC7: =+AB7*W7 -> 0 | AE7: =+AD7*W7 -> 0 | AF7: =+X7+Z7+AB7+AD7 -> 0 | AG7: =+Y7+AA7+AC7+AE7 -> 0 | AH7: =+U7+AG7 -> 0
A8: 11 | B8: 1 | C8: Refuerzo de la sociedad civil | F8: Costo recurso humano programatico de la entidad ejecutora | G8: Coordinador | M8: Entidad Ejecutora | N8: ONG/OBC/Sector Académico | O8: Recursos Humanos | P8: Salario / Honorario | S8: =+R8*Q8 -> 0 | T8: =+R8 -> 0 | U8: =S8 -> 0 | V8: Salario / Honorario | Y8: =+W8*X8 -> 0 | AA8: =+Z8*W8 -> 0 | AC8: =+AB8*W8 -> 0 | AE8: =+AD8*W8 -> 0 | AF8: =+X8+Z8+AB8+AD8 -> 0 | AG8: =+Y8+AA8+AC8+AE8 -> 0 | AH8: =+U8+AG8 -> 0
A9: 11 | B9: 1 | C9: Refuerzo de la sociedad civil | G9: Profesionales en Salud Sexual y Reproductiva (SSR) | M9: Entidad Ejecutora | N9: ONG/OBC/Sector Académico | O9: Recursos Humanos | P9: Salario / Honorario | S9: =+R9*Q9 -> 0 | T9: =+R9 -> 0 | U9: =S9 -> 0 | V9: Salario / Honorario | Y9: =+W9*X9 -> 0 | AA9: =+Z9*W9 -> 0 | AC9: =+AB9*W9 -> 0 | AE9: =+AD9*W9 -> 0 | AF9: =+X9+Z9+AB9+AD9 -> 0 | AG9: =+Y9+AA9+AC9+AE9 -> 0 | AH9: =+U9+AG9 -> 0
A10: 11 | B10: 1 | C10: Refuerzo de la sociedad civil | G10: Técnicos en Salud Sexual y Reproductiva (SSR) | M10: Entidad Ejecutora | N10: ONG/OBC/Sector Académico | O10: Recursos Humanos | P10: Salario / Honorario | S10: =+R10*Q10 -> 0 | T10: =+R10 -> 0 | U10: =S10 -> 0 | V10: Salario / Honorario | Y10: =+W10*X10 -> 0 | AA10: =+Z10*W10 -> 0 | AC10: =+AB10*W10 -> 0 | AE10: =+AD10*W10 -> 0 | AF10: =+X10+Z10+AB10+AD10 -> 0 | AG10: =+Y10+AA10+AC10+AE10 -> 0 | AH10: =+U10+AG10 -> 0
A11: MONITOREO Y EVALUACION | AH11: =SUM(AH12:AH27) -> 0 | AI11: 186782123
A12: 13 | B12: 1 | C12: Refuerzo de la sociedad civil | D12: 1.1 Implementar estrategias de promoción de la demanda de asesoría y prueba voluntaria (APV) y de comunicación para el cambio de comportamiento (CCC) | E12: 1.1.5 Identificar y formar líderes pares de los grupos clave priorizados para que actúen como formadores e integren los equipos locales de promoción de la salud y prevención del VIH e ITS | F12: Este costo incluye: 1. Viaticos y desplazamientos a los municipios de influencia asignados. 2. Actividades de gestion municipal y departamental para la sostenibilidad de las iniciativas. 3. Actividades en los servicios comunitarios para el encuentro con las comunidades, generación de confianza con las poblaciones priorizadas, actividades de escucha, reducción del estigma y la discriminaciòn, entre otras (Ejm: chocolatadas, teatro o cine al parque, actividades de trueque, acciones sanatorias de apoyo en situaciòn de alta vulnerabilidad para estabilizar a las poblaciones, entre otras) | G12: Viaticos por municipio | M12: Entidad Ejecutora | N12: ONG/OBC/Sector Académico | O12: Monitoreo y evaluación | P12: Viatico | R12: =+SUM(R13:R18) -> 0 | S12: =+SUM(S13:S18) -> 0 | T12: =+SUM(T13:T18) -> 0 | U12: =S12 -> 0 | V12: Viatico | X12: =+SUM(X13:X18) -> 0 | Y12: =+SUM(Y13:Y18) -> 0 | Z12: =+SUM(Z13:Z18) -> 0 | AA12: =+SUM(AA13:AA18) -> 0 | AB12: =+SUM(AB13:AB18) -> 0 | AC12: =+SUM(AC13:AC18) -> 0 | AD12: =+SUM(AD13:AD18) -> 0 | AE12: =+SUM(AE13:AE18) -> 0 | ... AG12: =+SUM(AG13:AG18) -> 0 | AH12: =+U12+AG12 -> 0
G13: Medellin | S13: =+R13*Q13 -> 0 | T13: =+R13 -> 0 | U13: =+S13 -> 0 | Y13: =+W13*X13 -> 0 | AA13: =+$W13*Z13 -> 0 | AC13: =+$W13*AB13 -> 0 | AE13: =+$W13*AD13 -> 0 | AF13: =+X13+Z13+AB13+AD13 -> 0 | AG13: =+Y13+AA13+AC13+AE13 -> 0
G14: Apartado | S14: =+R14*Q14 -> 0 | T14: =+R14 -> 0 | U14: =+S14 -> 0 | Y14: =+W14*X14 -> 0 | AA14: =+$W14*Z14 -> 0 | AC14: =+$W14*AB14 -> 0 | AE14: =+$W14*AD14 -> 0 | AF14: =+X14+Z14+AB14+AD14 -> 0 | AG14: =+Y14+AA14+AC14+AE14 -> 0
G15: Carmen de Viboral | S15: =+R15*Q15 -> 0 | T15: =+R15 -> 0 | U15: =+S15 -> 0 | Y15: =+W15*X15 -> 0 | AA15: =+$W15*Z15 -> 0 | AC15: =+$W15*AB15 -> 0 | AE15: =+$W15*AD15 -> 0 | AF15: =+X15+Z15+AB15+AD15 -> 0 | AG15: =+Y15+AA15+AC15+AE15 -> 0
G16: Quibdo | S16: =+R16*Q16 -> 0 | T16: =+R16 -> 0 | U16: =+S16 -> 0 | Y16: =+W16*X16 -> 0 | AA16: =+$W16*Z16 -> 0 | AC16: =+$W16*AB16 -> 0 | AE16: =+$W16*AD16 -> 0 | AF16: =+X16+Z16+AB16+AD16 -> 0 | AG16: =+Y16+AA16+AC16+AE16 -> 0
G17: Bahia Solano | S17: =+R17*Q17 -> 0 | T17: =+R17 -> 0 | U17: =+S17 -> 0 | Y17: =+W17*X17 -> 0 | AA17: =+$W17*Z17 -> 0 | AC17: =+$W17*AB17 -> 0 | AE17: =+$W17*AD17 -> 0 | AF17: =+X17+Z17+AB17+AD17 -> 0 | AG17: =+Y17+AA17+AC17+AE17 -> 0
G18: Itsmina | S18: =+R18*Q18 -> 0 | T18: =+R18 -> 0 | U18: =+S18 -> 0 | Y18: =+W18*X18 -> 0 | AA18: =+$W18*Z18 -> 0 | AC18: =+$W18*AB18 -> 0 | AE18: =+$W18*AD18 -> 0 | AF18: =+X18+Z18+AB18+AD18 -> 0 | AG18: =+Y18+AA18+AC18+AE18 -> 0
A19: 13 | B19: 1 | C19: Refuerzo de la sociedad civil | G19: Desplazamientos por municipio | M19: Entidad Ejecutora | N19: ONG/OBC/Sector Académico | O19: Monitoreo y evaluación | P19: Desplazamiento | R19: =+SUM(R20:R25) -> 0 | S19: =+SUM(S20:S25) -> 0 | T19: =+R19 -> 0 | U19: =S19 -> 0 | V19: Desplazamiento | X19: =+SUM(X20:X25) -> 0 | Y19: =+SUM(Y20:Y25) -> 0 | Z19: =+SUM(Z20:Z25) -> 0 | AA19: =+SUM(AA20:AA25) -> 0 | AB19: =+SUM(AB20:AB25) -> 0 | AC19: =+AB19*W19 -> 0 | AD19: =+SUM(AD20:AD25) -> 0 | AE19: =+SUM(AE20:AE25) -> 0 | AF19: =+SUM(AF20:AF25) -> 0 | AG19: =+SUM(AG20:AG25) -> 0 | AH19: =+U19+AG19 -> 0
G20: Medellin | S20: =+R20*Q20 -> 0 | T20: =+R20 -> 0 | U20: =+S20 -> 0 | Y20: =+W20*X20 -> 0 | AA20: =+$W20*Z20 -> 0 | AC20: =+$W20*AB20 -> 0 | AE20: =+$W20*AD20 -> 0 | AF20: =+X20+Z20+AB20+AD20 -> 0 | AG20: =+Y20+AA20+AC20+AE20 -> 0
G21: Apartado | S21: =+R21*Q21 -> 0 | T21: =+R21 -> 0 | U21: =+S21 -> 0 | Y21: =+W21*X21 -> 0 | AA21: =+$W21*Z21 -> 0 | AC21: =+$W21*AB21 -> 0 | AE21: =+$W21*AD21 -> 0 | AF21: =+X21+Z21+AB21+AD21 -> 0 | AG21: =+Y21+AA21+AC21+AE21 -> 0
G22: Carmen de Viboral | S22: =+R22*Q22 -> 0 | T22: =+R22 -> 0 | U22: =+S22 -> 0 | Y22: =+W22*X22 -> 0 | AA22: =+$W22*Z22 -> 0 | AC22: =+$W22*AB22 -> 0 | AE22: =+$W22*AD22 -> 0 | AF22: =+X22+Z22+AB22+AD22 -> 0 | AG22: =+Y22+AA22+AC22+AE22 -> 0
G23: Quibdo | S23: =+R23*Q23 -> 0 | T23: =+R23 -> 0 | U23: =+S23 -> 0 | Y23: =+W23*X23 -> 0 | AA23: =+$W23*Z23 -> 0 | AC23: =+$W23*AB23 -> 0 | AE23: =+$W23*AD23 -> 0 | AF23: =+X23+Z23+AB23+AD23 -> 0 | AG23: =+Y23+AA23+AC23+AE23 -> 0
G24: Bahia Solano | S24: =+R24*Q24 -> 0 | T24: =+R24 -> 0 | U24: =+S24 -> 0 | Y24: =+W24*X24 -> 0 | AA24: =+$W24*Z24 -> 0 | AC24: =+$W24*AB24 -> 0 | AE24: =+$W24*AD24 -> 0 | AF24: =+X24+Z24+AB24+AD24 -> 0 | AG24: =+Y24+AA24+AC24+AE24 -> 0
G25: Itsmina | S25: =+R25*Q25 -> 0 | T25: =+R25 -> 0 | U25: =+S25 -> 0 | Y25: =+W25*X25 -> 0 | AA25: =+$W25*Z25 -> 0 | AC25: =+$W25*AB25 -> 0 | AE25: =+$W25*AD25 -> 0 | AF25: =+X25+Z25+AB25+AD25 -> 0 | AG25: =+Y25+AA25+AC25+AE25 -> 0
A26: 13 | B26: 1 | C26: Refuerzo de la sociedad civil | G26: Actividades de Gestión | M26: Entidad Ejecutora | N26: ONG/OBC/Sector Académico | O26: Monitoreo y evaluación | P26: Costo reunión | S26: =+R26*Q26 -> 0 | T26: =+R26 -> 0 | U26: =S26 -> 0 | V26: Costo reunión | Y26: =+W26*X26 -> 0 | AA26: =+Z26*W26 -> 0 | AC26: =+AB26*W26 -> 0 | AE26: =+AD26*W26 -> 0 | AF26: =+X26+Z26+AB26+AD26 -> 0 | AG26: =+Y26+AA26+AC26+AE26 -> 0 | AH26: =+U26+AG26 -> 0
A27: 13 | B27: 1 | C27: Refuerzo de la sociedad civil | G27: Actividades Servicios Comunitarios | M27: Entidad Ejecutora | N27: ONG/OBC/Sector Académico | O27: Monitoreo y evaluación | P27: Actividades | S27: =+R27*Q27 -> 0 | T27: =+R27 -> 0 | U27: =S27 -> 0 | V27: Actividades | Y27: =+W27*X27 -> 0 | AA27: =+Z27*W27 -> 0 | AC27: =+AB27*W27 -> 0 | AE27: =+AD27*W27 -> 0 | AF27: =+X27+Z27+AB27+AD27 -> 0 | AG27: =+Y27+AA27+AC27+AE27 -> 0 | AH27: =+U27+AG27 -> 0
A28: PLANIFICACION Y ADMINISTRACION | AH28: =SUM(AH29) -> 0 | AI28: =97838265-17788774 -> 80049491
A29: 8 | B29: 1 | C29: Refuerzo de la sociedad civil | D29: 1.1 Implementar estrategias de promoción de la demanda de asesoría y prueba voluntaria (APV) y de comunicación para el cambio de comportamiento (CCC) | E29: 1.1.5 Identificar y formar líderes pares de los grupos clave priorizados para que actúen como formadores e integren los equipos locales de promoción de la salud y prevención del VIH e ITS | F29: Este costo incluye los Costos Administrativos (como, Arriendo, servicios públicos, Comunicaciones, impresiones, fotocopias, papelería, correos, gastos bancarios, seguros, mantenimiento y reparaciones, servicios generales, entre otros). | M29: Entidad Ejecutora | N29: ONG/OBC/Sector Académico | O29: Planificación y Administración | S29: =+R29*Q29 -> 0 | T29: =+R29 -> 0 | U29: =S29 -> 0 | Y29: =+W29*X29 -> 0 | AA29: =+Z29*W29 -> 0 | AC29: =+AB29*W29 -> 0 | AE29: =+AD29*W29 -> 0 | AF29: =+X29+Z29+AB29+AD29 -> 0 | AG29: =+Y29+AA29+AC29+AE29 -> 0 | AH29: =+U29+AG29 -> 0
A30: TOTAL RUBROS DE FUNCIONAMIENTO | AH30: =+AH4+AH11+AH28 -> 0 | AI30: =+AI4+AI11+AI28 -> 889438703
AH31: =SUM(AH7:AH29) -> 0
A32: DESTINACION ESPECIFICA
A33: 6 | B33: 1 | C33: CCC (Comunicación para Cambio de Comportamiento)- Medios de comunicación | D33: 1.1 Implementar estrategias de promoción de la demanda de asesoría y prueba voluntaria (APV) y de comunicación para el cambio de comportamiento (CCC) | E33: 1.1.4 Implementar acciones de CCC y de promoción de demanda de APV en medios alternativos y cara-a-cara (outreach) para transformar conductas sexuales de riesgo, promover el uso consistente y adecuado del condón y divulgar servicios y rutas de derechos a los grupos clave | F33: Este costo esta representado por brigadas de acercamiento a los grupos clave en sus entornos naturales | G33: Costo por brigada. El costo asignado por brigada es de $15,355. Incluye alimentación y transporte | M33: Entidad Ejecutora | N33: ONG/OBC/Sector Académico | O33: Capacitación | P33: costo por brigada | Q33: =15355 -> 15355 | R33: 547 | S33: =+R33*Q33 -> 8399185 | T33: =+R33 -> 547 | U33: =S33 -> 8399185 | V33: costo por brigada | W33: =+Q33 -> 15355 | X33: 547 | Y33: =+W33*X33 -> 8399185 | Z33: 547 | AA33: =+Z33*W33 -> 8399185 | AB33: =+Z33 -> 547 | AC33: =+AB33*W33 -> 8399185 | AD33: 549 | AE33: =+AD33*W33 -> 8429895 | AF33: =+X33+Z33+AB33+AD33 -> 2190 | AG33: =+Y33+AA33+AC33+AE33 -> 33627450 | AH33: =+U33+AG33 -> 42026635
A34: 34 | B34: 1 | C34: Refuerzo de las capacidades institucionales | D34: 1.3 Crear y fortalecer servicios comunitarios y/o redes comunitarias tipo A para la prevención del VIH/Sida /ITS, la promoción y referencia a APV, la educación en derechos y el empoderamiento de los grupos clave | E34: 1.3.5 Diseñar e implementar un plan de mejoramiento de capacidades locativas, de dotación y del recurso humano en los servicios comunitarios tipo A para la implementación efectiva de estrategias de CCC, promoción de la demanda de APV, educación en derechos, educación de pares | F34: Desarrollo de asistencia técnica a los servicios comunitarios tipo A asignados en temas identificados en la evaluación de necesidades | G34: Costo por servicio comunitario de 24 horas (valor hora $36.000) | M34: Entidad Ejecutora | N34: ONG/OBC/Sector Académico | O34: Asistencia técnica y gerencial | P34: Costo por hora asistencia tecnica | S34: =+R34*Q34 -> 0 | T34: =+R34 -> 0 | U34: =S34 -> 0 | V34: Costo por hora asistencia tecnica | W34: =36000*24 -> 864000 | X34: 10 | Y34: =+W34*X34 -> 8640000 | Z34: 11 | AA34: =+Z34*W34 -> 9504000 | AC34: =+AB34*W34 -> 0 | AD34: =+AB34 -> 0 | AE34: =+AD34*W34 -> 0 | AF34: =+X34+Z34+AB34+AD34 -> 21 | AG34: =+Y34+AA34+AC34+AE34 -> 18144000 | AH34: =+U34+AG34 -> 18144000
A35: 35 | B35: 1 | C35: Refuerzo de las capacidades institucionales | D35: 1.3 Crear y fortalecer servicios comunitarios y/o redes comunitarias tipo A para la prevención del VIH/Sida /ITS, la promoción y referencia a APV, la educación en derechos y el empoderamiento de los grupos clave | E35: 1.3.5 Diseñar e implementar un plan de mejoramiento de capacidades locativas, de dotación y del recurso humano en los servicios comunitarios tipo A para la implementación efectiva de estrategias de CCC, promoción de la demanda de APV, educación en derechos, educación de pares | F35: Desarrollo de asistencia técnica a los servicios comunitarios tipo A asignados en temas identificados en la evaluación de necesidades | G35: Costo por servicio comunitario de 12 horas (valor hora $36.000) | M35: Entidad Ejecutora | N35: ONG/OBC/Sector Académico | O35: Asistencia técnica y gerencial | P35: Costo por hora asistencia tecnica | S35: =+R35*Q35 -> 0 | T35: =+R35 -> 0 | U35: =S35 -> 0 | V35: Costo por hora asistencia tecnica | W35: =36000*12 -> 432000 | Y35: =+W35*X35 -> 0 | Z35: =+X35 -> 0 | AA35: =+Z35*W35 -> 0 | AB35: 21 | AC35: =+AB35*W35 -> 9072000 | AD35: =+AB35 -> 21 | AE35: =+AD35*W35 -> 9072000 | AF35: =+X35+Z35+AB35+AD35 -> 42 | AG35: =+Y35+AA35+AC35+AE35 -> 18144000 | AH35: =+U35+AG35 -> 18144000
A36: 43 | B36: 1 | C36: Reducción del estigma en todas las circunstancias | D36: 1.4 Implementar estrategias de movilización social para la reducción del estigma y la discriminación, la incidencia política y el agenciamiento social | E36: 1.4.3 Implementar estrategias de comunicación y movilización social del nivel nacional y local (radio, medios alternativos y cara- a-cara) para la sensibilización de las comunidades para la reducción de estigma y discriminación | F36: Desarrollo de campañas locales en medios alternativos desarrolladas en eventos comunitarios para la movilización social en torno a la prevención del VIH y la promoción de la solidaridad frente a los grupos clave | G36: Este costo incluye campañas locales en medios alternativos | M36: Entidad Ejecutora | N36: ONG/OBC/Sector Académico | O36: Material de comunicación | P36: Costo por campaña | S36: =+R36*Q36 -> 0 | T36: =+R36 -> 0 | U36: =S36 -> 0 | V36: Costo por campaña | W36: 5000000 | X36: =+R36 -> 0 | Y36: =+W36*X36 -> 0 | Z36: 1 | AA36: =+Z36*W36 -> 5000000 | AC36: =+AB36*W36 -> 0 | AD36: 1 | AE36: =+AD36*W36 -> 5000000 | AF36: =+X36+Z36+AB36+AD36 -> 2 | AG36: =+Y36+AA36+AC36+AE36 -> 10000000 | AH36: =+U36+AG36 -> 10000000
A37: 46 | B37: 1 | C37: Refuerzo de la sociedad civil | D37: 1.4 Implementar estrategias de movilización social para la reducción del estigma y la discriminación, la incidencia política y el agenciamiento social | E37: 1.4.4 Implementar acciones de fortalecimiento de la capacidad de ciudadana y agenciamiento social de los grupos clave, a través de educación en derechos, empoderamiento y apoyo social | F37: Desarrollo de encuentros quincenales en los servicios comunitarios tipo A para educar en derechos, participación y ciudadanía a los grupos clave. | G37: Este costo incluye un apoyo al encuentro para agua, café y apoyo alquiler salón de reunión | M37: Entidad Ejecutora | N37: ONG/OBC/Sector Académico | O37: Capacitación | P37: Costo por encuentro | S37: =+R37*Q37 -> 0 | T37: =+R37 -> 0 | U37: =S37 -> 0 | V37: Costo por encuentro | W37: 100000 | X37: 26 | Y37: =+W37*X37 -> 2600000 | Z37: 26 | AA37: =+Z37*W37 -> 2600000 | AB37: =+Z37 -> 26 | AC37: =+AB37*W37 -> 2600000 | AD37: 28 | AE37: =+AD37*W37 -> 2800000 | AF37: =+X37+Z37+AB37+AD37 -> 106 | AG37: =+Y37+AA37+AC37+AE37 -> 10600000 | AH37: =+U37+AG37 -> 10600000
A38: 12 | B38: 1 | C38: Refuerzo de la sociedad civil | D38: 1.1 Implementar estrategias de promoción de la demanda de asesoría y prueba voluntaria (APV) y de comunicación para el cambio de comportamiento (CCC) | E38: 1.1.5 Identificar y formar líderes pares de los grupos clave priorizados para que actúen como formadores e integren los equipos locales de promoción de la salud y prevención del VIH e ITS | F38: Costos administrativos, de operación y programaticos de la entidade ejecutora para el trabajo con servicios comunitarios para la identificación, selección, capacitación y seguimiento de lideres pares. Costos de prevención y promoción de APV, CCC, Uso de Condón, Reducción de Estigma y discriminación y seguimiento a tratamientos | G38: Costo Líderes pares de las Entidades Ejecutoras para los temas de prevención, diagnostico y tratamiento | M38: Entidad Ejecutora | N38: ONG/OBC/Sector Académico | O38: Monitoreo y evaluación | P38: Costo Incentivo Lideres Pares | Q38: =150000*3 -> 450000 | R38: 21 | S38: =+R38*Q38 -> 9450000 | T38: =+R38 -> 21 | U38: =S38 -> 9450000 | V38: =+P38 -> Costo Incentivo Lideres Pares | W38: =154500*3 -> 463500 | X38: 21 | Y38: =+W38*X38 -> 9733500 | Z38: =21+95 -> 116 | AA38: =+Z38*W38 -> 53766000 | AB38: =+Z38 -> 116 | AC38: =+AB38*W38 -> 53766000 | AD38: 116 | AE38: =+AD38*W38 -> 53766000 | AF38: =+X38+Z38+AB38+AD38 -> 369 | AG38: =+Y38+AA38+AC38+AE38 -> 171031500 | AH38: =+U38+AG38 -> 180481500
A39: TOTAL DESTINACION ESPECIFICA | AH39: =SUM(AH33:AH38) -> 279396135 | AI39: =+AH39 -> 279396135
A40: TOTAL PRESUPUESTO | AI40: =+AI30+AI39 -> 1168834838

Sheet Summary Bog
A1: PRESUPUESTO ENTIDADES EJECUTORAS
A2: BOGOTA
A4: Nombre Entidad Ejecutora:
A6: Detalle | B6: Presupuesto Total | C6: Tope Presupuestal
A7: Recurso Humano | B7: =+'Fase I Bog'!AH4 -> 0 | C7: =+'Fase I Bog'!AI4 -> 656174819
A8: Monitoreo y Evaluación | B8: =+'Fase I Bog'!AH11 -> 0 | C8: =+'Fase I Bog'!AI11 -> 196852446
A9: Planeación y Administración | B9: =+'Fase I Bog'!AH26 -> 0 | C9: =+'Fase I Bog'!AI26 -> 84365328
A10: Total Rubros de Funcionamiento | B10: =SUM(B7:B9) -> 0 | C10: =SUM(C7:C9) -> 937392593
A12: Destinación Específica | B12: =+'Fase I Bog'!AH37 -> 257295950 | C12: =+'Fase I Bog'!AI37 -> 257295950
A13: Total Destinación Específica | B13: =+B12 -> 257295950 | C13: =+C12 -> 257295950
A14: PRESUPUESTO TOTAL | B14: =+B10+B13 -> 257295950 | C14: =+C10+C13 -> 1194688543
A19: XXXXXX
A20: REPRESENTANTE LEGAL

Sheet Fase I Bog
A1: PRESUPUESTO DETALLADO
A2: No | B2: No de Objetivo: Crear capacidad comunitaria para la adopción de comportamientos seguros, la reducción de la vulnerabilidad social al VIH y el empoderamiento de los grupos clave priorizados | C2: Área de prestación de servicios (APS) | D2: Macro-Categoría | E2: Tarea | F2: Sub -Tarea | G2: Descripción / Hipotesis | H2: Año 1 | I2: Año 2 | M2: Responsable de la ejecución | N2: Tipo de entidad ejecutora | O2: Categorías de costos | P2: Unidad de medida año 1 | Q2: Costo unitario año 1 (valor trimestre) | R2: Cantidad Trimestre 4 | S2: Importe total Trimestre 4 | T2: Cantidad total Año 1 | U2: Total Año 1 | V2: Unidad de medida año 2 | W2: Costo unitario año 2 (valor trimestre) | X2: Cantidad Trimestre 1 año 2 | Y2: Importe total Trimestre 1 año 2 | Z2: Cantidad Trimestre 2 año 2 | AA2: Importe total Trimestre 2 año 2 | AB2: Cantidad Trimestre 3 año 2 | AC2: Importe total Trimestre 3 año 2 | AD2: Cantidad Trimestre 4 año 2 | AE2: Importe total Trimestre 4 año 2 | AF2: Cantidad total Año 2 | AG2: Total Año 2 | AH2: COSTO TOTAL | AI2: Tope Presupuestal
C3: SDA | D3: Activity | H3: T4 | I3: T1 | J3: T2 | K3: T3 | L3: T4
A4: RECURSO HUMANO | AH4: =SUM(AH5:AH10) -> 0 | AI4: 656174819
A5: 7 | B5: 1 | C5: Refuerzo de la sociedad civil | D5: 1.1 Implementar estrategias de promoción de la demanda de asesoría y prueba voluntaria (APV) y de comunicación para el cambio de comportamiento (CCC) | E5: 1.1.5 Identificar y formar líderes pares de los grupos clave priorizados para que actúen como formadores e integren los equipos locales de promoción de la salud y prevención del VIH e ITS | F5: Costo recurso humano administración de la entidad ejecutora | G5: Contador | M5: Entidad Ejecutora | N5: ONG/OBC/Sector Académico | O5: Recursos Humanos | P5: Salario / Honorario | S5: =+R5*Q5 -> 0 | T5: =+R5 -> 0 | U5: =S5 -> 0 | V5: Salario / Honorario | Y5: =+W5*X5 -> 0 | AA5: =+Z5*W5 -> 0 | AC5: =+AB5*W5 -> 0 | AE5: =+AD5*W5 -> 0 | AF5: =+X5+Z5+AB5+AD5 -> 0 | AG5: =+Y5+AA5+AC5+AE5 -> 0 | AH5: =+U5+AG5 -> 0
A6: 7 | B6: 1 | G6: Apoyo a la Dirección o Representación Legal | M6: Entidad Ejecutora | N6: ONG/OBC/Sector Académico | O6: Recursos Humanos | P6: Salario / Honorario | S6: =+R6*Q6 -> 0 | T6: =+R6 -> 0 | U6: =S6 -> 0 | V6: Salario / Honorario | Y6: =+W6*X6 -> 0 | AA6: =+Z6*W6 -> 0 | AC6: =+AB6*W6 -> 0 | AE6: =+AD6*W6 -> 0 | AF6: =+X6+Z6+AB6+AD6 -> 0 | AG6: =+Y6+AA6+AC6+AE6 -> 0 | AH6: =+U6+AG6 -> 0
A7: 7 | B7: 1 | G7: Asistente de Información | M7: Entidad Ejecutora | N7: ONG/OBC/Sector Académico | O7: Recursos Humanos | P7: Salario / Honorario | S7: =+R7*Q7 -> 0 | T7: =+R7 -> 0 | U7: =S7 -> 0 | V7: Salario / Honorario | Y7: =+W7*X7 -> 0 | AA7: =+Z7*W7 -> 0 | AC7: =+AB7*W7 -> 0 | AE7: =+AD7*W7 -> 0 | AF7: =+X7+Z7+AB7+AD7 -> 0 | AG7: =+Y7+AA7+AC7+AE7 -> 0 | AH7: =+U7+AG7 -> 0
A8: 11 | B8: 1 | C8: Refuerzo de la sociedad civil | F8: Costo recurso humano programatico de la entidad ejecutora | G8: Coordinador | M8: Entidad Ejecutora | N8: ONG/OBC/Sector Académico | O8: Recursos Humanos | P8: Salario / Honorario | S8: =+R8*Q8 -> 0 | T8: =+R8 -> 0 | U8: =S8 -> 0 | V8: Salario / Honorario | Y8: =+W8*X8 -> 0 | AA8: =+Z8*W8 -> 0 | AC8: =+AB8*W8 -> 0 | AE8: =+AD8*W8 -> 0 | AF8: =+X8+Z8+AB8+AD8 -> 0 | AG8: =+Y8+AA8+AC8+AE8 -> 0 | AH8: =+U8+AG8 -> 0
A9: 11 | B9: 1 | C9: Refuerzo de la sociedad civil | G9: Profesionales en Salud Sexual y Reproductiva (SSR) | M9: Entidad Ejecutora | N9: ONG/OBC/Sector Académico | O9: Recursos Humanos | P9: Salario / Honorario | S9: =+R9*Q9 -> 0 | T9: =+R9 -> 0 | U9: =S9 -> 0 | V9: Salario / Honorario | Y9: =+W9*X9 -> 0 | AA9: =+Z9*W9 -> 0 | AC9: =+AB9*W9 -> 0 | AE9: =+AD9*W9 -> 0 | AF9: =+X9+Z9+AB9+AD9 -> 0 | AG9: =+Y9+AA9+AC9+AE9 -> 0 | AH9: =+U9+AG9 -> 0
A10: 11 | B10: 1 | C10: Refuerzo de la sociedad civil | G10: Técnicos en Salud Sexual y Reproductiva (SSR) | M10: Entidad Ejecutora | N10: ONG/OBC/Sector Académico | O10: Recursos Humanos | P10: Salario / Honorario | S10: =+R10*Q10 -> 0 | T10: =+R10 -> 0 | U10: =S10 -> 0 | V10: Salario / Honorario | Y10: =+W10*X10 -> 0 | AA10: =+Z10*W10 -> 0 | AC10: =+AB10*W10 -> 0 | AE10: =+AD10*W10 -> 0 | AF10: =+X10+Z10+AB10+AD10 -> 0 | AG10: =+Y10+AA10+AC10+AE10 -> 0 | AH10: =+U10+AG10 -> 0
A11: MONITOREO Y EVALUACION | AH11: =SUM(AH12:AH25) -> 0 | AI11: 196852446
A12: 13 | B12: 1 | C12: Refuerzo de la sociedad civil | D12: 1.1 Implementar estrategias de promoción de la demanda de asesoría y prueba voluntaria (APV) y de comunicación para el cambio de comportamiento (CCC) | E12: 1.1.5 Identificar y formar líderes pares de los grupos clave priorizados para que actúen como formadores e integren los equipos locales de promoción de la salud y prevención del VIH e ITS | F12: Este costo incluye: 1. Viaticos y desplazamientos a los municipios de influencia asignados. 2. Actividades de gestion municipal y departamental para la sostenibilidad de las iniciativas. 3. Actividades en los servicios comunitarios para el encuentro con las comunidades, generación de confianza con las poblaciones priorizadas, actividades de escucha, reducción del estigma y la discriminaciòn, entre otras (Ejm: chocolatadas, teatro o cine al parque, actividades de trueque, acciones sanatorias de apoyo en situaciòn de alta vulnerabilidad para estabilizar a las poblaciones, entre otras) | G12: Viaticos por municipio | M12: Entidad Ejecutora | N12: ONG/OBC/Sector Académico | O12: Monitoreo y evaluación | P12: Viatico | R12: =+SUM(R13:R17) -> 0 | S12: =+SUM(S13:S17) -> 0 | T12: =+SUM(T13:T17) -> 0 | U12: =+SUM(U13:U17) -> 0 | V12: Viatico | X12: =+SUM(X13:X17) -> 0 | Y12: =+SUM(Y13:Y17) -> 0 | Z12: =+SUM(Z13:Z17) -> 0 | AA12: =+SUM(AA13:AA17) -> 0 | AB12: =+SUM(AB13:AB17) -> 0 | AC12: =+SUM(AC13:AC17) -> 0 | AD12: =+SUM(AD13:AD17) -> 0 | AE12: =+SUM(AE13:AE17) -> 0 | ... AG12: =+SUM(AG13:AG17) -> 0 | AH12: =+U12+AG12 -> 0
G13: Bosa | S13: =+R13*Q13 -> 0 | T13: =+R13 -> 0 | U13: =S13 -> 0 | W13: 1 | Y13: =+$W13*X13 -> 0 | AA13: =+$W13*Z13 -> 0 | AC13: =+$W13*AB13 -> 0 | AE13: =+$W13*AD13 -> 0 | AF13: =+X13+Z13+AB13+AD13 -> 0 | AG13: =+Y13+AA13+AC13+AE13 -> 0
G14: Suba | S14: =+R14*Q14 -> 0 | T14: =+R14 -> 0 | U14: =S14 -> 0 | W14: 1 | Y14: =+$W14*X14 -> 0 | AA14: =+$W14*Z14 -> 0 | AC14: =+$W14*AB14 -> 0 | AE14: =+$W14*AD14 -> 0 | AF14: =+X14+Z14+AB14+AD14 -> 0 | AG14: =+Y14+AA14+AC14+AE14 -> 0
G15: Tunjuelito | S15: =+R15*Q15 -> 0 | T15: =+R15 -> 0 | U15: =S15 -> 0 | W15: 1 | Y15: =+$W15*X15 -> 0 | AA15: =+$W15*Z15 -> 0 | AC15: =+$W15*AB15 -> 0 | AE15: =+$W15*AD15 -> 0 | AF15: =+X15+Z15+AB15+AD15 -> 0 | AG15: =+Y15+AA15+AC15+AE15 -> 0
G16: Fontibon | S16: =+R16*Q16 -> 0 | T16: =+R16 -> 0 | U16: =S16 -> 0 | W16: 1 | Y16: =+$W16*X16 -> 0 | AA16: =+$W16*Z16 -> 0 | AC16: =+$W16*AB16 -> 0 | AE16: =+$W16*AD16 -> 0 | AF16: =+X16+Z16+AB16+AD16 -> 0 | AG16: =+Y16+AA16+AC16+AE16 -> 0
G17: Kennedy
A18: 13 | B18: 1 | C18: Refuerzo de la sociedad civil | G18: Desplazamientos por municipio | M18: Entidad Ejecutora | N18: ONG/OBC/Sector Académico | O18: Monitoreo y evaluación | P18: Desplazamiento | R18: =+SUM(R19:R23) -> 0 | S18: =+SUM(S19:S23) -> 0 | T18: =+SUM(T19:T23) -> 0 | U18: =+SUM(U19:U23) -> 0 | V18: Desplazamiento | X18: =+SUM(X19:X23) -> 0 | Y18: =+SUM(Y19:Y23) -> 0 | Z18: =+SUM(Z19:Z23) -> 0 | AA18: =+SUM(AA19:AA23) -> 0 | AB18: =+SUM(AB19:AB23) -> 0 | AC18: =+SUM(AC19:AC23) -> 0 | AD18: =+SUM(AD19:AD23) -> 0 | AE18: =+SUM(AE19:AE23) -> 0 | ... AG18: =+SUM(AG19:AG23) -> 0 | AH18: =+U18+AG18 -> 0
G19: Bosa | S19: =+R19*Q19 -> 0 | T19: =+R19 -> 0 | U19: =S19 -> 0 | W19: 1 | Y19: =+$W19*X19 -> 0 | AA19: =+$W19*Z19 -> 0 | AC19: =+$W19*AB19 -> 0 | AE19: =+$W19*AD19 -> 0 | AF19: =+X19+Z19+AB19+AD19 -> 0 | AG19: =+Y19+AA19+AC19+AE19 -> 0
G20: Suba | S20: =+R20*Q20 -> 0 | T20: =+R20 -> 0 | U20: =S20 -> 0 | W20: 1 | Y20: =+$W20*X20 -> 0 | AA20: =+$W20*Z20 -> 0 | AC20: =+$W20*AB20 -> 0 | AE20: =+$W20*AD20 -> 0 | AF20: =+X20+Z20+AB20+AD20 -> 0 | AG20: =+Y20+AA20+AC20+AE20 -> 0
G21: Tunjuelito | S21: =+R21*Q21 -> 0 | T21: =+R21 -> 0 | U21: =S21 -> 0 | W21: 1 | Y21: =+$W21*X21 -> 0 | AA21: =+$W21*Z21 -> 0 | AC21: =+$W21*AB21 -> 0 | AE21: =+$W21*AD21 -> 0 | AF21: =+X21+Z21+AB21+AD21 -> 0 | AG21: =+Y21+AA21+AC21+AE21 -> 0
G22: Fontibon | S22: =+R22*Q22 -> 0 | T22: =+R22 -> 0 | U22: =S22 -> 0 | W22: 1 | Y22: =+$W22*X22 -> 0 | AA22: =+$W22*Z22 -> 0 | AC22: =+$W22*AB22 -> 0 | AE22: =+$W22*AD22 -> 0 | AF22: =+X22+Z22+AB22+AD22 -> 0 | AG22: =+Y22+AA22+AC22+AE22 -> 0
G23: Kennedy | S23: =+R23*Q23 -> 0 | T23: =+R23 -> 0 | U23: =S23 -> 0 | W23: 1 | Y23: =+$W23*X23 -> 0 | AA23: =+$W23*Z23 -> 0 | AC23: =+$W23*AB23 -> 0 | AE23: =+$W23*AD23 -> 0 | AF23: =+X23+Z23+AB23+AD23 -> 0 | AG23: =+Y23+AA23+AC23+AE23 -> 0
A24: 13 | B24: 1 | C24: Refuerzo de la sociedad civil | G24: Actividades de Gestión | M24: Entidad Ejecutora | N24: ONG/OBC/Sector Académico | O24: Monitoreo y evaluación | P24: Costo reunión | S24: =+R24*Q24 -> 0 | T24: =+R24 -> 0 | U24: =S24 -> 0 | V24: Costo reunión | Y24: =+W24*X24 -> 0 | AA24: =+Z24*W24 -> 0 | AC24: =+AB24*W24 -> 0 | AE24: =+AD24*W24 -> 0 | AF24: =+X24+Z24+AB24+AD24 -> 0 | AG24: =+Y24+AA24+AC24+AE24 -> 0 | AH24: =+U24+AG24 -> 0
A25: 13 | B25: 1 | C25: Refuerzo de la sociedad civil | G25: Actividades Servicios Comunitarios | M25: Entidad Ejecutora | N25: ONG/OBC/Sector Académico | O25: Monitoreo y evaluación | P25: Actividades | S25: =+R25*Q25 -> 0 | T25: =+R25 -> 0 | U25: =S25 -> 0 | V25: Actividades | Y25: =+W25*X25 -> 0 | AA25: =+Z25*W25 -> 0 | AC25: =+AB25*W25 -> 0 | AE25: =+AD25*W25 -> 0 | AF25: =+X25+Z25+AB25+AD25 -> 0 | AG25: =+Y25+AA25+AC25+AE25 -> 0 | AH25: =+U25+AG25 -> 0
A26: PLANIFICACION Y ADMINISTRACION | AH26: =SUM(AH27) -> 0 | AI26: 84365328
A27: 8 | B27: 1 | C27: Refuerzo de la sociedad civil | D27: 1.1 Implementar estrategias de promoción de la demanda de asesoría y prueba voluntaria (APV) y de comunicación para el cambio de comportamiento (CCC) | E27: 1.1.5 Identificar y formar líderes pares de los grupos clave priorizados para que actúen como formadores e integren los equipos locales de promoción de la salud y prevención del VIH e ITS | F27: Este costo incluye los Costos Administrativos (como, Arriendo, servicios públicos, Comunicaciones, impresiones, fotocopias, papelería, correos, gastos bancarios, seguros, mantenimiento y reparaciones, servicios generales, entre otros). | M27: Entidad Ejecutora | N27: ONG/OBC/Sector Académico | O27: Planificación y Administración | S27: =+R27*Q27 -> 0 | T27: =+R27 -> 0 | U27: =S27 -> 0 | Y27: =+W27*X27 -> 0 | AA27: =+Z27*W27 -> 0 | AC27: =+AB27*W27 -> 0 | AE27: =+AD27*W27 -> 0 | AF27: =+X27+Z27+AB27+AD27 -> 0 | AG27: =+Y27+AA27+AC27+AE27 -> 0 | AH27: =+U27+AG27 -> 0
A28: TOTAL RUBROS DE FUNCIONAMIENTO | AH28: =+AH4+AH11+AH26 -> 0 | AI28: =+AI4+AI11+AI26 -> 937392593
AH29: =SUM(AH7:AH27) -> 0
A30: DESTINACION ESPECIFICA
A31: 6 | B31: 1 | C31: CCC (Comunicación para Cambio de Comportamiento)- Medios de comunicación | D31: 1.1 Implementar estrategias de promoción de la demanda de asesoría y prueba voluntaria (APV) y de comunicación para el cambio de comportamiento (CCC) | E31: 1.1.4 Implementar acciones de CCC y de promoción de demanda de APV en medios alternativos y cara-a-cara (outreach) para transformar conductas sexuales de riesgo, promover el uso consistente y adecuado del condón y divulgar servicios y rutas de derechos a los grupos clave | F31: Este costo esta representado por brigadas de acercamiento a los grupos clave en sus entornos naturales | G31: Costo por brigada. El costo asignado por brigada es de $15,355. Incluye alimentación y transporte | M31: Entidad Ejecutora | N31: ONG/OBC/Sector Académico | O31: Capacitación | P31: costo por brigada | Q31: =15355 -> 15355 | R31: 658 | S31: =+R31*Q31 -> 10103590 | T31: =+R31 -> 658 | U31: =S31 -> 10103590 | V31: costo por brigada | W31: =+Q31 -> 15355 | X31: 658 | Y31: =+W31*X31 -> 10103590 | Z31: 658 | AA31: =+Z31*W31 -> 10103590 | AB31: =+Z31 -> 658 | AC31: =+AB31*W31 -> 10103590 | AD31: =+AB31 -> 658 | AE31: =+AD31*W31 -> 10103590 | AF31: =+X31+Z31+AB31+AD31 -> 2632 | AG31: =+Y31+AA31+AC31+AE31 -> 40414360 | AH31: =+U31+AG31 -> 50517950
A32: 34 | B32: 1 | C32: Refuerzo de las capacidades institucionales | D32: 1.3 Crear y fortalecer servicios comunitarios y/o redes comunitarias tipo A para la prevención del VIH/Sida /ITS, la promoción y referencia a APV, la educación en derechos y el empoderamiento de los grupos clave | E32: 1.3.5 Diseñar e implementar un plan de mejoramiento de capacidades locativas, de dotación y del recurso humano en los servicios comunitarios tipo A para la implementación efectiva de estrategias de CCC, promoción de la demanda de APV, educación en derechos, educación de pares | F32: Desarrollo de asistencia técnica a los servicios comunitarios tipo A asignados en temas identificados en la evaluación de necesidades | G32: Costo por servicio comunitario de 24 horas (valor hora $36.000) | M32: Entidad Ejecutora | N32: ONG/OBC/Sector Académico | O32: Asistencia técnica y gerencial | P32: Costo por hora asistencia tecnica | S32: =+R32*Q32 -> 0 | T32: =+R32 -> 0 | U32: =S32 -> 0 | V32: Costo por hora asistencia tecnica | W32: =36000*24 -> 864000 | X32: 7 | Y32: =+W32*X32 -> 6048000 | Z32: =+X32 -> 7 | AA32: =+Z32*W32 -> 6048000 | AC32: =+AB32*W32 -> 0 | AD32: =+AB32 -> 0 | AE32: =+AD32*W32 -> 0 | AF32: =+X32+Z32+AB32+AD32 -> 14 | AG32: =+Y32+AA32+AC32+AE32 -> 12096000 | AH32: =+U32+AG32 -> 12096000
A33: 35 | B33: 1 | C33: Refuerzo de las capacidades institucionales | D33: 1.3 Crear y fortalecer servicios comunitarios y/o redes comunitarias tipo A para la prevención del VIH/Sida /ITS, la promoción y referencia a APV, la educación en derechos y el empoderamiento de los grupos clave | E33: 1.3.5 Diseñar e implementar un plan de mejoramiento de capacidades locativas, de dotación y del recurso humano en los servicios comunitarios tipo A para la implementación efectiva de estrategias de CCC, promoción de la demanda de APV, educación en derechos, educación de pares | F33: Desarrollo de asistencia técnica a los servicios comunitarios tipo A asignados en temas identificados en la evaluación de necesidades | G33: Costo por servicio comunitario de 12 horas (valor hora $36.000) | M33: Entidad Ejecutora | N33: ONG/OBC/Sector Académico | O33: Asistencia técnica y gerencial | P33: Costo por hora asistencia tecnica | S33: =+R33*Q33 -> 0 | T33: =+R33 -> 0 | U33: =S33 -> 0 | V33: Costo por hora asistencia tecnica | W33: =36000*12 -> 432000 | Y33: =+W33*X33 -> 0 | Z33: =+X33 -> 0 | AA33: =+Z33*W33 -> 0 | AB33: 14 | AC33: =+AB33*W33 -> 6048000 | AD33: =+AB33 -> 14 | AE33: =+AD33*W33 -> 6048000 | AF33: =+X33+Z33+AB33+AD33 -> 28 | AG33: =+Y33+AA33+AC33+AE33 -> 12096000 | AH33: =+U33+AG33 -> 12096000
A34: 43 | B34: 1 | C34: Reducción del estigma en todas las circunstancias | D34: 1.4 Implementar estrategias de movilización social para la reducción del estigma y la discriminación, la incidencia política y el agenciamiento social | E34: 1.4.3 Implementar estrategias de comunicación y movilización social del nivel nacional y local (radio, medios alternativos y cara- a-cara) para la sensibilización de las comunidades para la reducción de estigma y discriminación | F34: Desarrollo de campañas locales en medios alternativos desarrolladas en eventos comunitarios para la movilización social en torno a la prevención del VIH y la promoción de la solidaridad frente a los grupos clave | G34: Este costo incluye campañas locales en medios alternativos | M34: Entidad Ejecutora | N34: ONG/OBC/Sector Académico | O34: Material de comunicación | P34: Costo por campaña | S34: =+R34*Q34 -> 0 | T34: =+R34 -> 0 | U34: =S34 -> 0 | V34: Costo por campaña | W34: 5000000 | X34: =+R34 -> 0 | Y34: =+W34*X34 -> 0 | Z34: 1 | AA34: =+Z34*W34 -> 5000000 | AC34: =+AB34*W34 -> 0 | AE34: =+AD34*W34 -> 0 | AF34: =+X34+Z34+AB34+AD34 -> 1 | AG34: =+Y34+AA34+AC34+AE34 -> 5000000 | AH34: =+U34+AG34 -> 5000000
A35: 46 | B35: 1 | C35: Refuerzo de la sociedad civil | D35: 1.4 Implementar estrategias de movilización social para la reducción del estigma y la discriminación, la incidencia política y el agenciamiento social | E35: 1.4.4 Implementar acciones de fortalecimiento de la capacidad de ciudadana y agenciamiento social de los grupos clave, a través de educación en derechos, empoderamiento y apoyo social | F35: Desarrollo de encuentros quincenales en los servicios comunitarios tipo A para educar en derechos, participación y ciudadanía a los grupos clave. | G35: Este costo incluye un apoyo al encuentro para agua, café y apoyo alquiler salón de reunión | M35: Entidad Ejecutora | N35: ONG/OBC/Sector Académico | O35: Capacitación | P35: Costo por encuentro | S35: =+R35*Q35 -> 0 | T35: =+R35 -> 0 | U35: =S35 -> 0 | V35: Costo por encuentro | W35: 100000 | X35: 31 | Y35: =+W35*X35 -> 3100000 | Z35: =+X35 -> 31 | AA35: =+Z35*W35 -> 3100000 | AB35: =+Z35 -> 31 | AC35: =+AB35*W35 -> 3100000 | AD35: =+AB35 -> 31 | AE35: =+AD35*W35 -> 3100000 | AF35: =+X35+Z35+AB35+AD35 -> 124 | AG35: =+Y35+AA35+AC35+AE35 -> 12400000 | AH35: =+U35+AG35 -> 12400000
A36: 12 | B36: 1 | C36: Refuerzo de la sociedad civil | D36: 1.1 Implementar estrategias de promoción de la demanda de asesoría y prueba voluntaria (APV) y de comunicación para el cambio de comportamiento (CCC) | E36: 1.1.5 Identificar y formar líderes pares de los grupos clave priorizados para que actúen como formadores e integren los equipos locales de promoción de la salud y prevención del VIH e ITS | F36: Costos administrativos, de operación y programaticos de la entidade ejecutora para el trabajo con servicios comunitarios para la identificación, selección, capacitación y seguimiento de lideres pares. Costos de prevención y promoción de APV, CCC, Uso de Condón, Reducción de Estigma y discriminación y seguimiento a tratamientos | G36: Costo Líderes pares de las Entidades Ejecutoras para los temas de prevención, diagnostico y tratamiento | M36: Entidad Ejecutora | N36: ONG/OBC/Sector Académico | O36: Monitoreo y evaluación | P36: Costo Incentivo Lideres Pares | Q36: =150000*3 -> 450000 | R36: 21 | S36: =+R36*Q36 -> 9450000 | T36: =+R36 -> 21 | U36: =S36 -> 9450000 | V36: =+P36 -> Costo Incentivo Lideres Pares | W36: =154500*3 -> 463500 | X36: 21 | Y36: =+W36*X36 -> 9733500 | Z36: 105 | AA36: =+Z36*W36 -> 48667500 | AB36: =+Z36 -> 105 | AC36: =+AB36*W36 -> 48667500 | AD36: =+AB36 -> 105 | AE36: =+AD36*W36 -> 48667500 | AF36: =+X36+Z36+AB36+AD36 -> 336 | AG36: =+Y36+AA36+AC36+AE36 -> 155736000 | AH36: =+U36+AG36 -> 165186000
A37: TOTAL DESTINACION ESPECIFICA | AH37: =SUM(AH31:AH36) -> 257295950 | AI37: =+AH37 -> 257295950
A38: TOTAL PRESUPUESTO | AI38: =+AI28+AI37 -> 1194688543

Sheet Summary Valle del Cauca
A1: PRESUPUESTO ENTIDADES EJECUTORAS
A2: VALLE DEL CAUCA
A4: Nombre Entidad Ejecutora:
A6: Detalle | B6: Presupuesto Total | C6: Tope Presupuestal
A7: Recurso Humano | B7: =+'Fase I Valle del Cauca'!AH4 -> 0 | C7: =+'Fase I Valle del Cauca'!AI4 -> 475608787
A8: Monitoreo y Evaluación | B8: =+'Fase I Valle del Cauca'!AH11 -> 0 | C8: =+'Fase I Valle del Cauca'!AI11 -> 142682633
A9: Planeación y Administración | B9: =+'Fase I Valle del Cauca'!AH26 -> 0 | C9: =+'Fase I Valle del Cauca'!AI26 -> 61149698
A10: Total Rubros de Funcionamiento | B10: =SUM(B7:B9) -> 0 | C10: =SUM(C7:C9) -> 679441118
A12: Destinación Específica | B12: =+'Fase I Valle del Cauca'!AH37 -> 198704435 | C12: =+'Fase I Valle del Cauca'!AI37 -> 198704435
A13: Total Destinación Específica | B13: =+B12 -> 198704435 | C13: =+C12 -> 198704435
A14: PRESUPUESTO TOTAL | B14: =+B10+B13 -> 198704435 | C14: =+C10+C13 -> 878145553
A19: XXXXXX
A20: REPRESENTANTE LEGAL

Sheet Fase I Valle del Cauca
A1: PRESUPUESTO DETALLADO
A2: No | B2: No de Objetivo: Crear capacidad comunitaria para la adopción de comportamientos seguros, la reducción de la vulnerabilidad social al VIH y el empoderamiento de los grupos clave priorizados | C2: Área de prestación de servicios (APS) | D2: Macro-Categoría | E2: Tarea | F2: Sub -Tarea | G2: Descripción / Hipotesis | H2: Año 1 | I2: Año 2 | M2: Responsable de la ejecución | N2: Tipo de entidad ejecutora | O2: Categorías de costos | P2: Unidad de medida año 1 | Q2: Costo unitario año 1 (valor trimestre) | R2: Cantidad Trimestre 4 | S2: Importe total Trimestre 4 | T2: Cantidad total Año 1 | U2: Total Año 1 | V2: Unidad de medida año 2 | W2: Costo unitario año 2 (valor trimestre) | X2: Cantidad Trimestre 1 año 2 | Y2: Importe total Trimestre 1 año 2 | Z2: Cantidad Trimestre 2 año 2 | AA2: Importe total Trimestre 2 año 2 | AB2: Cantidad Trimestre 3 año 2 | AC2: Importe total Trimestre 3 año 2 | AD2: Cantidad Trimestre 4 año 2 | AE2: Importe total Trimestre 4 año 2 | AF2: Cantidad total Año 2 | AG2: Total Año 2 | AH2: COSTO TOTAL | AI2: Tope Presupuestal
C3: SDA | D3: Activity | H3: T4 | I3: T1 | J3: T2 | K3: T3 | L3: T4
A4: RECURSO HUMANO | AH4: =SUM(AH5:AH10) -> 0 | AI4: 475608787
A5: 7 | B5: 1 | C5: Refuerzo de la sociedad civil | D5: 1.1 Implementar estrategias de promoción de la demanda de asesoría y prueba voluntaria (APV) y de comunicación para el cambio de comportamiento (CCC) | E5: 1.1.5 Identificar y formar líderes pares de los grupos clave priorizados para que actúen como formadores e integren los equipos locales de promoción de la salud y prevención del VIH e ITS | F5: Costo recurso humano administración de la entidad ejecutora | G5: Contador | M5: Entidad Ejecutora | N5: ONG/OBC/Sector Académico | O5: Recursos Humanos | P5: Salario / Honorario | S5: =+R5*Q5 -> 0 | T5: =+R5 -> 0 | U5: =S5 -> 0 | V5: Salario / Honorario | Y5: =+W5*X5 -> 0 | AA5: =+Z5*W5 -> 0 | AC5: =+AB5*W5 -> 0 | AE5: =+AD5*W5 -> 0 | AF5: =+X5+Z5+AB5+AD5 -> 0 | AG5: =+Y5+AA5+AC5+AE5 -> 0 | AH5: =+U5+AG5 -> 0
A6: 7 | B6: 1 | G6: Apoyo a la Dirección o Representación Legal | M6: Entidad Ejecutora | N6: ONG/OBC/Sector Académico | O6: Recursos Humanos | P6: Salario / Honorario | S6: =+R6*Q6 -> 0 | T6: =+R6 -> 0 | U6: =S6 -> 0 | V6: Salario / Honorario | Y6: =+W6*X6 -> 0 | AA6: =+Z6*W6 -> 0 | AC6: =+AB6*W6 -> 0 | AE6: =+AD6*W6 -> 0 | AF6: =+X6+Z6+AB6+AD6 -> 0 | AG6: =+Y6+AA6+AC6+AE6 -> 0 | AH6: =+U6+AG6 -> 0
A7: 7 | B7: 1 | G7: Asistente de Información | M7: Entidad Ejecutora | N7: ONG/OBC/Sector Académico | O7: Recursos Humanos | P7: Salario / Honorario | S7: =+R7*Q7 -> 0 | T7: =+R7 -> 0 | U7: =S7 -> 0 | V7: Salario / Honorario | Y7: =+W7*X7 -> 0 | AA7: =+Z7*W7 -> 0 | AC7: =+AB7*W7 -> 0 | AE7: =+AD7*W7 -> 0 | AF7: =+X7+Z7+AB7+AD7 -> 0 | AG7: =+Y7+AA7+AC7+AE7 -> 0 | AH7: =+U7+AG7 -> 0
A8: 11 | B8: 1 | C8: Refuerzo de la sociedad civil | F8: Costo recurso humano programatico de la entidad ejecutora | G8: Coordinador | M8: Entidad Ejecutora | N8: ONG/OBC/Sector Académico | O8: Recursos Humanos | P8: Salario / Honorario | S8: =+R8*Q8 -> 0 | T8: =+R8 -> 0 | U8: =S8 -> 0 | V8: Salario / Honorario | Y8: =+W8*X8 -> 0 | AA8: =+Z8*W8 -> 0 | AC8: =+AB8*W8 -> 0 | AE8: =+AD8*W8 -> 0 | AF8: =+X8+Z8+AB8+AD8 -> 0 | AG8: =+Y8+AA8+AC8+AE8 -> 0 | AH8: =+U8+AG8 -> 0
A9: 11 | B9: 1 | C9: Refuerzo de la sociedad civil | G9: Profesionales en Salud Sexual y Reproductiva (SSR) | M9: Entidad Ejecutora | N9: ONG/OBC/Sector Académico | O9: Recursos Humanos | P9: Salario / Honorario | S9: =+R9*Q9 -> 0 | T9: =+R9 -> 0 | U9: =S9 -> 0 | V9: Salario / Honorario | Y9: =+W9*X9 -> 0 | AA9: =+Z9*W9 -> 0 | AC9: =+AB9*W9 -> 0 | AE9: =+AD9*W9 -> 0 | AF9: =+X9+Z9+AB9+AD9 -> 0 | AG9: =+Y9+AA9+AC9+AE9 -> 0 | AH9: =+U9+AG9 -> 0
A10: 11 | B10: 1 | C10: Refuerzo de la sociedad civil | G10: Técnicos en Salud Sexual y Reproductiva (SSR) | M10: Entidad Ejecutora | N10: ONG/OBC/Sector Académico | O10: Recursos Humanos | P10: Salario / Honorario | S10: =+R10*Q10 -> 0 | T10: =+R10 -> 0 | U10: =S10 -> 0 | V10: Salario / Honorario | Y10: =+W10*X10 -> 0 | AA10: =+Z10*W10 -> 0 | AC10: =+AB10*W10 -> 0 | AE10: =+AD10*W10 -> 0 | AF10: =+X10+Z10+AB10+AD10 -> 0 | AG10: =+Y10+AA10+AC10+AE10 -> 0 | AH10: =+U10+AG10 -> 0
A11: MONITOREO Y EVALUACION | AH11: =SUM(AH12:AH25) -> 0 | AI11: 142682633
A12: 13 | B12: 1 | C12: Refuerzo de la sociedad civil | D12: 1.1 Implementar estrategias de promoción de la demanda de asesoría y prueba voluntaria (APV) y de comunicación para el cambio de comportamiento (CCC) | E12: 1.1.5 Identificar y formar líderes pares de los grupos clave priorizados para que actúen como formadores e integren los equipos locales de promoción de la salud y prevención del VIH e ITS | F12: Este costo incluye: 1. Viaticos y desplazamientos a los municipios de influencia asignados. 2. Actividades de gestion municipal y departamental para la sostenibilidad de las iniciativas. 3. Actividades en los servicios comunitarios para el encuentro con las comunidades, generación de confianza con las poblaciones priorizadas, actividades de escucha, reducción del estigma y la discriminaciòn, entre otras (Ejm: chocolatadas, teatro o cine al parque, actividades de trueque, acciones sanatorias de apoyo en situaciòn de alta vulnerabilidad para estabilizar a las poblaciones, entre otras) | G12: Viaticos por municipio | M12: Entidad Ejecutora | N12: ONG/OBC/Sector Académico | O12: Monitoreo y evaluación | P12: Viatico | S12: =+SUM(S13:S17) -> 0 | T12: =+SUM(T13:T17) -> 0 | U12: =+SUM(U13:U17) -> 0 | V12: Viatico | X12: =+SUM(X13:X17) -> 0 | Y12: =+SUM(Y13:Y17) -> 0 | Z12: =+SUM(Z13:Z17) -> 0 | AA12: =+SUM(AA13:AA17) -> 0 | AB12: =+SUM(AB13:AB17) -> 0 | AC12: =+SUM(AC13:AC17) -> 0 | AD12: =+SUM(AD13:AD17) -> 0 | AE12: =+SUM(AE13:AE17) -> 0 | ... AG12: =+SUM(AG13:AG17) -> 0 | AH12: =+U12+AG12 -> 0
G13: Cali | S13: =+Q13*R13 -> 0 | T13: =+R13 -> 0 | U13: =S13 -> 0 | Y13: =+W13*X13 -> 0 | AA13: =+$W13*Z13 -> 0 | AC13: =+$W13*AB13 -> 0 | AE13: =+$W13*AD13 -> 0 | AG13: =+Y13+AA13+AC13+AE13 -> 0
G14: Palmira | S14: =+Q14*R14 -> 0 | T14: =+R14 -> 0 | U14: =S14 -> 0 | Y14: =+W14*X14 -> 0 | AA14: =+$W14*Z14 -> 0 | AC14: =+$W14*AB14 -> 0 | AE14: =+$W14*AD14 -> 0 | AG14: =+Y14+AA14+AC14+AE14 -> 0
G15: Tulua | S15: =+Q15*R15 -> 0 | T15: =+R15 -> 0 | U15: =S15 -> 0 | Y15: =+W15*X15 -> 0 | AA15: =+$W15*Z15 -> 0 | AC15: =+$W15*AB15 -> 0 | AE15: =+$W15*AD15 -> 0 | AG15: =+Y15+AA15+AC15+AE15 -> 0
G16: Buga | S16: =+Q16*R16 -> 0 | T16: =+R16 -> 0 | U16: =S16 -> 0 | Y16: =+W16*X16 -> 0 | AA16: =+$W16*Z16 -> 0 | AC16: =+$W16*AB16 -> 0 | AE16: =+$W16*AD16 -> 0 | AG16: =+Y16+AA16+AC16+AE16 -> 0
G17: Buenaventura | S17: =+Q17*R17 -> 0 | T17: =+R17 -> 0 | U17: =S17 -> 0 | Y17: =+W17*X17 -> 0 | AA17: =+$W17*Z17 -> 0 | AC17: =+$W17*AB17 -> 0 | AE17: =+$W17*AD17 -> 0 | AG17: =+Y17+AA17+AC17+AE17 -> 0
A18: 13 | B18: 1 | C18: Refuerzo de la sociedad civil | G18: Desplazamientos por municipio | M18: Entidad Ejecutora | N18: ONG/OBC/Sector Académico | O18: Monitoreo y evaluación | P18: Desplazamiento | S18: =+SUM(S19:S23) -> 0 | T18: =+SUM(T19:T23) -> 0 | U18: =+SUM(U19:U23) -> 0 | V18: Desplazamiento | X18: =+SUM(X19:X23) -> 0 | Y18: =+SUM(Y19:Y23) -> 0 | Z18: =+SUM(Z19:Z23) -> 0 | AA18: =+SUM(AA19:AA23) -> 0 | AB18: =+SUM(AB19:AB23) -> 0 | AC18: =+SUM(AC19:AC23) -> 0 | AD18: =+SUM(AD19:AD23) -> 0 | AE18: =+SUM(AE19:AE23) -> 0 | ... AG18: =+SUM(AG19:AG23) -> 0 | AH18: =+U18+AG18 -> 0
G19: Cali | S19: =+Q19*R19 -> 0 | T19: =+R19 -> 0 | U19: =S19 -> 0 | Y19: =+W19*X19 -> 0 | AA19: =+$W19*Z19 -> 0 | AC19: =+$W19*AB19 -> 0 | AE19: =+$W19*AD19 -> 0 | AG19: =+Y19+AA19+AC19+AE19 -> 0
G20: Palmira | S20: =+Q20*R20 -> 0 | T20: =+R20 -> 0 | U20: =S20 -> 0 | Y20: =+W20*X20 -> 0 | AA20: =+$W20*Z20 -> 0 | AC20: =+$W20*AB20 -> 0 | AE20: =+$W20*AD20 -> 0 | AG20: =+Y20+AA20+AC20+AE20 -> 0
G21: Tulua | S21: =+Q21*R21 -> 0 | T21: =+R21 -> 0 | U21: =S21 -> 0 | Y21: =+W21*X21 -> 0 | AA21: =+$W21*Z21 -> 0 | AC21: =+$W21*AB21 -> 0 | AE21: =+$W21*AD21 -> 0 | AG21: =+Y21+AA21+AC21+AE21 -> 0
G22: Buga | S22: =+Q22*R22 -> 0 | T22: =+R22 -> 0 | U22: =S22 -> 0 | Y22: =+W22*X22 -> 0 | AA22: =+$W22*Z22 -> 0 | AC22: =+$W22*AB22 -> 0 | AE22: =+$W22*AD22 -> 0 | AG22: =+Y22+AA22+AC22+AE22 -> 0
G23: Buenaventura | S23: =+Q23*R23 -> 0 | T23: =+R23 -> 0 | U23: =S23 -> 0 | Y23: =+W23*X23 -> 0 | AA23: =+$W23*Z23 -> 0 | AC23: =+$W23*AB23 -> 0 | AE23: =+$W23*AD23 -> 0 | AG23: =+Y23+AA23+AC23+AE23 -> 0
A24: 13 | B24: 1 | C24: Refuerzo de la sociedad civil | G24: Actividades de Gestión | M24: Entidad Ejecutora | N24: ONG/OBC/Sector Académico | O24: Monitoreo y evaluación | P24: Costo reunión | S24: =+R24*Q24 -> 0 | T24: =+R24 -> 0 | U24: =S24 -> 0 | V24: Costo reunión | Y24: =+W24*X24 -> 0 | AA24: =+Z24*W24 -> 0 | AC24: =+AB24*W24 -> 0 | AE24: =+AD24*W24 -> 0 | AF24: =+X24+Z24+AB24+AD24 -> 0 | AG24: =+Y24+AA24+AC24+AE24 -> 0 | AH24: =+U24+AG24 -> 0
A25: 13 | B25: 1 | C25: Refuerzo de la sociedad civil | G25: Actividades Servicios Comunitarios | M25: Entidad Ejecutora | N25: ONG/OBC/Sector Académico | O25: Monitoreo y evaluación | P25: Actividades | S25: =+R25*Q25 -> 0 | T25: =+R25 -> 0 | U25: =S25 -> 0 | V25: Actividades | Y25: =+W25*X25 -> 0 | AA25: =+Z25*W25 -> 0 | AC25: =+AB25*W25 -> 0 | AE25: =+AD25*W25 -> 0 | AF25: =+X25+Z25+AB25+AD25 -> 0 | AG25: =+Y25+AA25+AC25+AE25 -> 0 | AH25: =+U25+AG25 -> 0
A26: PLANIFICACION Y ADMINISTRACION | AH26: =SUM(AH27) -> 0 | AI26: 61149698
A27: 8 | B27: 1 | C27: Refuerzo de la sociedad civil | D27: 1.1 Implementar estrategias de promoción de la demanda de asesoría y prueba voluntaria (APV) y de comunicación para el cambio de comportamiento (CCC) | E27: 1.1.5 Identificar y formar líderes pares de los grupos clave priorizados para que actúen como formadores e integren los equipos locales de promoción de la salud y prevención del VIH e ITS | F27: Este costo incluye los Costos Administrativos (como, Arriendo, servicios públicos, Comunicaciones, impresiones, fotocopias, papelería, correos, gastos bancarios, seguros, mantenimiento y reparaciones, servicios generales, entre otros). | M27: Entidad Ejecutora | N27: ONG/OBC/Sector Académico | O27: Planificación y Administración | S27: =+R27*Q27 -> 0 | T27: =+R27 -> 0 | U27: =S27 -> 0 | Y27: =+W27*X27 -> 0 | AA27: =+Z27*W27 -> 0 | AC27: =+AB27*W27 -> 0 | AE27: =+AD27*W27 -> 0 | AF27: =+X27+Z27+AB27+AD27 -> 0 | AG27: =+Y27+AA27+AC27+AE27 -> 0 | AH27: =+U27+AG27 -> 0
A28: TOTAL RUBROS DE FUNCIONAMIENTO | AH28: =+AH4+AH11+AH26 -> 0 | AI28: =+AI4+AI11+AI26 -> 679441118
AH29: =SUM(AH7:AH27) -> 0
A30: DESTINACION ESPECIFICA
A31: 6 | B31: 1 | C31: CCC (Comunicación para Cambio de Comportamiento)- Medios de comunicación | D31: 1.1 Implementar estrategias de promoción de la demanda de asesoría y prueba voluntaria (APV) y de comunicación para el cambio de comportamiento (CCC) | E31: 1.1.4 Implementar acciones de CCC y de promoción de demanda de APV en medios alternativos y cara-a-cara (outreach) para transformar conductas sexuales de riesgo, promover el uso consistente y adecuado del condón y divulgar servicios y rutas de derechos a los grupos clave | F31: Este costo esta representado por brigadas de acercamiento a los grupos clave en sus entornos naturales | G31: Costo por brigada. El costo asignado por brigada es de $15,355. Incluye alimentación y transporte | M31: Entidad Ejecutora | N31: ONG/OBC/Sector Académico | O31: Capacitación | P31: costo por brigada | Q31: =15355 -> 15355 | R31: 419 | S31: =+R31*Q31 -> 6433745 | T31: =+R31 -> 419 | U31: =S31 -> 6433745 | V31: costo por brigada | W31: =+Q31 -> 15355 | X31: 419 | Y31: =+W31*X31 -> 6433745 | Z31: 419 | AA31: =+Z31*W31 -> 6433745 | AB31: =+Z31 -> 419 | AC31: =+AB31*W31 -> 6433745 | AD31: 421 | AE31: =+AD31*W31 -> 6464455 | AF31: =+X31+Z31+AB31+AD31 -> 1678 | AG31: =+Y31+AA31+AC31+AE31 -> 25765690 | AH31: =+U31+AG31 -> 32199435
A32: 34 | B32: 1 | C32: Refuerzo de las capacidades institucionales | D32: 1.3 Crear y fortalecer servicios comunitarios y/o redes comunitarias tipo A para la prevención del VIH/Sida /ITS, la promoción y referencia a APV, la educación en derechos y el empoderamiento de los grupos clave | E32: 1.3.5 Diseñar e implementar un plan de mejoramiento de capacidades locativas, de dotación y del recurso humano en los servicios comunitarios tipo A para la implementación efectiva de estrategias de CCC, promoción de la demanda de APV, educación en derechos, educación de pares | F32: Desarrollo de asistencia técnica a los servicios comunitarios tipo A asignados en temas identificados en la evaluación de necesidades | G32: Costo por servicio comunitario de 24 horas (valor hora $36.000) | M32: Entidad Ejecutora | N32: ONG/OBC/Sector Académico | O32: Asistencia técnica y gerencial | P32: Costo por hora asistencia tecnica | S32: =+R32*Q32 -> 0 | T32: =+R32 -> 0 | U32: =S32 -> 0 | V32: Costo por hora asistencia tecnica | W32: =36000*24 -> 864000 | X32: 6 | Y32: =+W32*X32 -> 5184000 | Z32: 7 | AA32: =+Z32*W32 -> 6048000 | AC32: =+AB32*W32 -> 0 | AD32: =+AB32 -> 0 | AE32: =+AD32*W32 -> 0 | AF32: =+X32+Z32+AB32+AD32 -> 13 | AG32: =+Y32+AA32+AC32+AE32 -> 11232000 | AH32: =+U32+AG32 -> 11232000
A33: 35 | B33: 1 | C33: Refuerzo de las capacidades institucionales | D33: 1.3 Crear y fortalecer servicios comunitarios y/o redes comunitarias tipo A para la prevención del VIH/Sida /ITS, la promoción y referencia a APV, la educación en derechos y el empoderamiento de los grupos clave | E33: 1.3.5 Diseñar e implementar un plan de mejoramiento de capacidades locativas, de dotación y del recurso humano en los servicios comunitarios tipo A para la implementación efectiva de estrategias de CCC, promoción de la demanda de APV, educación en derechos, educación de pares | F33: Desarrollo de asistencia técnica a los servicios comunitarios tipo A asignados en temas identificados en la evaluación de necesidades | G33: Costo por servicio comunitario de 12 horas (valor hora $36.000) | M33: Entidad Ejecutora | N33: ONG/OBC/Sector Académico | O33: Asistencia técnica y gerencial | P33: Costo por hora asistencia tecnica | S33: =+R33*Q33 -> 0 | T33: =+R33 -> 0 | U33: =S33 -> 0 | V33: Costo por hora asistencia tecnica | W33: =36000*12 -> 432000 | Y33: =+W33*X33 -> 0 | Z33: =+X33 -> 0 | AA33: =+Z33*W33 -> 0 | AB33: 13 | AC33: =+AB33*W33 -> 5616000 | AD33: =+AB33 -> 13 | AE33: =+AD33*W33 -> 5616000 | AF33: =+X33+Z33+AB33+AD33 -> 26 | AG33: =+Y33+AA33+AC33+AE33 -> 11232000 | AH33: =+U33+AG33 -> 11232000
A34: 43 | B34: 1 | C34: Reducción del estigma en todas las circunstancias | D34: 1.4 Implementar estrategias de movilización social para la reducción del estigma y la discriminación, la incidencia política y el agenciamiento social | E34: 1.4.3 Implementar estrategias de comunicación y movilización social del nivel nacional y local (radio, medios alternativos y cara- a-cara) para la sensibilización de las comunidades para la reducción de estigma y discriminación | F34: Desarrollo de campañas locales en medios alternativos desarrolladas en eventos comunitarios para la movilización social en torno a la prevención del VIH y la promoción de la solidaridad frente a los grupos clave | G34: Este costo incluye campañas locales en medios alternativos | M34: Entidad Ejecutora | N34: ONG/OBC/Sector Académico | O34: Material de comunicación | P34: Costo por campaña | S34: =+R34*Q34 -> 0 | T34: =+R34 -> 0 | U34: =S34 -> 0 | V34: Costo por campaña | W34: 5000000 | X34: =+R34 -> 0 | Y34: =+W34*X34 -> 0 | Z34: 1 | AA34: =+Z34*W34 -> 5000000 | AC34: =+AB34*W34 -> 0 | AE34: =+AD34*W34 -> 0 | AF34: =+X34+Z34+AB34+AD34 -> 1 | AG34: =+Y34+AA34+AC34+AE34 -> 5000000 | AH34: =+U34+AG34 -> 5000000
A35: 46 | B35: 1 | C35: Refuerzo de la sociedad civil | D35: 1.4 Implementar estrategias de movilización social para la reducción del estigma y la discriminación, la incidencia política y el agenciamiento social | E35: 1.4.4 Implementar acciones de fortalecimiento de la capacidad de ciudadana y agenciamiento social de los grupos clave, a través de educación en derechos, empoderamiento y apoyo social | F35: Desarrollo de encuentros quincenales en los servicios comunitarios tipo A para educar en derechos, participación y ciudadanía a los grupos clave. | G35: Este costo incluye un apoyo al encuentro para agua, café y apoyo alquiler salón de reunión | M35: Entidad Ejecutora | N35: ONG/OBC/Sector Académico | O35: Capacitación | P35: Costo por encuentro | S35: =+R35*Q35 -> 0 | T35: =+R35 -> 0 | U35: =S35 -> 0 | V35: Costo por encuentro | W35: 100000 | X35: 20 | Y35: =+W35*X35 -> 2000000 | Z35: =+X35 -> 20 | AA35: =+Z35*W35 -> 2000000 | AB35: =+Z35 -> 20 | AC35: =+AB35*W35 -> 2000000 | AD35: 21 | AE35: =+AD35*W35 -> 2100000 | AF35: =+X35+Z35+AB35+AD35 -> 81 | AG35: =+Y35+AA35+AC35+AE35 -> 8100000 | AH35: =+U35+AG35 -> 8100000
A36: 12 | B36: 1 | C36: Refuerzo de la sociedad civil | D36: 1.1 Implementar estrategias de promoción de la demanda de asesoría y prueba voluntaria (APV) y de comunicación para el cambio de comportamiento (CCC) | E36: 1.1.5 Identificar y formar líderes pares de los grupos clave priorizados para que actúen como formadores e integren los equipos locales de promoción de la salud y prevención del VIH e ITS | F36: Costos administrativos, de operación y programaticos de la entidade ejecutora para el trabajo con servicios comunitarios para la identificación, selección, capacitación y seguimiento de lideres pares. Costos de prevención y promoción de APV, CCC, Uso de Condón, Reducción de Estigma y discriminación y seguimiento a tratamientos | G36: Costo Líderes pares de las Entidades Ejecutoras para los temas de prevención, diagnostico y tratamiento | M36: Entidad Ejecutora | N36: ONG/OBC/Sector Académico | O36: Monitoreo y evaluación | P36: Costo Incentivo Lideres Pares | Q36: =150000*3 -> 450000 | R36: 17 | S36: =+R36*Q36 -> 7650000 | T36: =+R36 -> 17 | U36: =S36 -> 7650000 | V36: =+P36 -> Costo Incentivo Lideres Pares | W36: =154500*3 -> 463500 | X36: =+R36 -> 17 | Y36: =+W36*X36 -> 7879500 | Z36: 83 | AA36: =+Z36*W36 -> 38470500 | AB36: =+Z36 -> 83 | AC36: =+AB36*W36 -> 38470500 | AD36: =+AB36 -> 83 | AE36: =+AD36*W36 -> 38470500 | AF36: =+X36+Z36+AB36+AD36 -> 266 | AG36: =+Y36+AA36+AC36+AE36 -> 123291000 | AH36: =+U36+AG36 -> 130941000
A37: TOTAL DESTINACION ESPECIFICA | AH37: =SUM(AH31:AH36) -> 198704435 | AI37: =+AH37 -> 198704435
A38: TOTAL PRESUPUESTO | AI38: =+AI28+AI37 -> 878145553

Sheet Summary Atlantico
A1: PRESUPUESTO ENTIDADES EJECUTORAS
A2: ATLANTICO
A4: Nombre Entidad Ejecutora:
A6: Detalle | B6: Presupuesto Total | C6: Tope Presupuestal
A7: Recurso Humano | B7: =+'[1]Fase I Valle del Cauca'!AH4 -> 0 | C7: =+'Fase I Atlantico'!AI4 -> 292025707
A8: Monitoreo y Evaluación | B8: =+'[1]Fase I Valle del Cauca'!AH11 -> 0 | C8: =+'Fase I Atlantico'!AI11 -> 87607708
A9: Planeación y Administración | B9: =+'[1]Fase I Valle del Cauca'!AH16 -> 0 | C9: =+'Fase I Atlantico'!AI24 -> 37546163
A10: Total Rubros de Funcionamiento | B10: =SUM(B7:B9) -> 0 | C10: =SUM(C7:C9) -> 417179578
A12: Destinación Específica | B12: =+'Fase I Atlantico'!AH35 -> 129081725 | C12: =+'Fase I Atlantico'!AI35 -> 129081725
A13: Total Destinación Específica | B13: =+B12 -> 129081725 | C13: =+C12 -> 129081725
A14: PRESUPUESTO TOTAL | B14: =+B10+B13 -> 129081725 | C14: =+C10+C13 -> 546261303
A19: XXXXXX
A20: REPRESENTANTE LEGAL

Sheet Fase I Atlantico
A1: PRESUPUESTO DETALLADO
A2: No | B2: No de Objetivo: Crear capacidad comunitaria para la adopción de comportamientos seguros, la reducción de la vulnerabilidad social al VIH y el empoderamiento de los grupos clave priorizados | C2: Área de prestación de servicios (APS) | D2: Macro-Categoría | E2: Tarea | F2: Sub -Tarea | G2: Descripción / Hipotesis | H2: Año 1 | I2: Año 2 | M2: Responsable de la ejecución | N2: Tipo de entidad ejecutora | O2: Categorías de costos | P2: Unidad de medida año 1 | Q2: Costo unitario año 1 (valor trimestre) | R2: Cantidad Trimestre 4 | S2: Importe total Trimestre 4 | T2: Cantidad total Año 1 | U2: Total Año 1 | V2: Unidad de medida año 2 | W2: Costo unitario año 2 (valor trimestre) | X2: Cantidad Trimestre 1 año 2 | Y2: Importe total Trimestre 1 año 2 | Z2: Cantidad Trimestre 2 año 2 | AA2: Importe total Trimestre 2 año 2 | AB2: Cantidad Trimestre 3 año 2 | AC2: Importe total Trimestre 3 año 2 | AD2: Cantidad Trimestre 4 año 2 | AE2: Importe total Trimestre 4 año 2 | AF2: Cantidad total Año 2 | AG2: Total Año 2 | AH2: COSTO TOTAL | AI2: Tope Presupuestal
C3: SDA | D3: Activity | H3: T4 | I3: T1 | J3: T2 | K3: T3 | L3: T4
A4: RECURSO HUMANO | AH4: =SUM(AH5:AH10) -> 0 | AI4: 292025707
A5: 7 | B5: 1 | C5: Refuerzo de la sociedad civil | D5: 1.1 Implementar estrategias de promoción de la demanda de asesoría y prueba voluntaria (APV) y de comunicación para el cambio de comportamiento (CCC) | E5: 1.1.5 Identificar y formar líderes pares de los grupos clave priorizados para que actúen como formadores e integren los equipos locales de promoción de la salud y prevención del VIH e ITS | F5: Costo recurso humano administración de la entidad ejecutora | G5: Contador | M5: Entidad Ejecutora | N5: ONG/OBC/Sector Académico | O5: Recursos Humanos | P5: Salario / Honorario | S5: =+R5*Q5 -> 0 | T5: =+R5 -> 0 | U5: =S5 -> 0 | V5: Salario / Honorario | Y5: =+W5*X5 -> 0 | AA5: =+Z5*W5 -> 0 | AC5: =+AB5*W5 -> 0 | AE5: =+AD5*W5 -> 0 | AF5: =+X5+Z5+AB5+AD5 -> 0 | AG5: =+Y5+AA5+AC5+AE5 -> 0 | AH5: =+U5+AG5 -> 0
A6: 7 | B6: 1 | G6: Apoyo a la Dirección o Representación Legal | M6: Entidad Ejecutora | N6: ONG/OBC/Sector Académico | O6: Recursos Humanos | P6: Salario / Honorario | S6: =+R6*Q6 -> 0 | T6: =+R6 -> 0 | U6: =S6 -> 0 | V6: Salario / Honorario | Y6: =+W6*X6 -> 0 | AA6: =+Z6*W6 -> 0 | AC6: =+AB6*W6 -> 0 | AE6: =+AD6*W6 -> 0 | AF6: =+X6+Z6+AB6+AD6 -> 0 | AG6: =+Y6+AA6+AC6+AE6 -> 0 | AH6: =+U6+AG6 -> 0
A7: 7 | B7: 1 | G7: Asistente de Información | M7: Entidad Ejecutora | N7: ONG/OBC/Sector Académico | O7: Recursos Humanos | P7: Salario / Honorario | S7: =+R7*Q7 -> 0 | T7: =+R7 -> 0 | U7: =S7 -> 0 | V7: Salario / Honorario | Y7: =+W7*X7 -> 0 | AA7: =+Z7*W7 -> 0 | AC7: =+AB7*W7 -> 0 | AE7: =+AD7*W7 -> 0 | AF7: =+X7+Z7+AB7+AD7 -> 0 | AG7: =+Y7+AA7+AC7+AE7 -> 0 | AH7: =+U7+AG7 -> 0
A8: 11 | B8: 1 | C8: Refuerzo de la sociedad civil | F8: Costo recurso humano programatico de la entidad ejecutora | G8: Coordinador | M8: Entidad Ejecutora | N8: ONG/OBC/Sector Académico | O8: Recursos Humanos | P8: Salario / Honorario | S8: =+R8*Q8 -> 0 | T8: =+R8 -> 0 | U8: =S8 -> 0 | V8: Salario / Honorario | Y8: =+W8*X8 -> 0 | AA8: =+Z8*W8 -> 0 | AC8: =+AB8*W8 -> 0 | AE8: =+AD8*W8 -> 0 | AF8: =+X8+Z8+AB8+AD8 -> 0 | AG8: =+Y8+AA8+AC8+AE8 -> 0 | AH8: =+U8+AG8 -> 0
A9: 11 | B9: 1 | C9: Refuerzo de la sociedad civil | G9: Profesionales en Salud Sexual y Reproductiva (SSR) | M9: Entidad Ejecutora | N9: ONG/OBC/Sector Académico | O9: Recursos Humanos | P9: Salario / Honorario | S9: =+R9*Q9 -> 0 | T9: =+R9 -> 0 | U9: =S9 -> 0 | V9: Salario / Honorario | Y9: =+W9*X9 -> 0 | AA9: =+Z9*W9 -> 0 | AC9: =+AB9*W9 -> 0 | AE9: =+AD9*W9 -> 0 | AF9: =+X9+Z9+AB9+AD9 -> 0 | AG9: =+Y9+AA9+AC9+AE9 -> 0 | AH9: =+U9+AG9 -> 0
A10: 11 | B10: 1 | C10: Refuerzo de la sociedad civil | G10: Técnicos en Salud Sexual y Reproductiva (SSR) | M10: Entidad Ejecutora | N10: ONG/OBC/Sector Académico | O10: Recursos Humanos | P10: Salario / Honorario | S10: =+R10*Q10 -> 0 | T10: =+R10 -> 0 | U10: =S10 -> 0 | V10: Salario / Honorario | Y10: =+W10*X10 -> 0 | AA10: =+Z10*W10 -> 0 | AC10: =+AB10*W10 -> 0 | AE10: =+AD10*W10 -> 0 | AF10: =+X10+Z10+AB10+AD10 -> 0 | AG10: =+Y10+AA10+AC10+AE10 -> 0 | AH10: =+U10+AG10 -> 0
A11: MONITOREO Y EVALUACION | AH11: =SUM(AH12:AH23) -> 0 | AI11: 87607708
A12: 13 | B12: 1 | C12: Refuerzo de la sociedad civil | D12: 1.1 Implementar estrategias de promoción de la demanda de asesoría y prueba voluntaria (APV) y de comunicación para el cambio de comportamiento (CCC) | E12: 1.1.5 Identificar y formar líderes pares de los grupos clave priorizados para que actúen como formadores e integren los equipos locales de promoción de la salud y prevención del VIH e ITS | F12: Este costo incluye: 1. Viaticos y desplazamientos a los municipios de influencia asignados. 2. Actividades de gestion municipal y departamental para la sostenibilidad de las iniciativas. 3. Actividades en los servicios comunitarios para el encuentro con las comunidades, generación de confianza con las poblaciones priorizadas, actividades de escucha, reducción del estigma y la discriminaciòn, entre otras (Ejm: chocolatadas, teatro o cine al parque, actividades de trueque, acciones sanatorias de apoyo en situaciòn de alta vulnerabilidad para estabilizar a las poblaciones, entre otras) | G12: Viaticos por municipio | M12: Entidad Ejecutora | N12: ONG/OBC/Sector Académico | O12: Monitoreo y evaluación | P12: Viatico | S12: =+SUM(S13:S16) -> 0 | T12: =+SUM(T13:T16) -> 0 | U12: =+SUM(U13:U16) -> 0 | V12: Viatico | X12: =+SUM(X13:X16) -> 0 | Y12: =+SUM(Y13:Y16) -> 0 | Z12: =+SUM(Z13:Z16) -> 0 | AA12: =+SUM(AA13:AA16) -> 0 | AB12: =+SUM(AB13:AB16) -> 0 | AC12: =+SUM(AC13:AC16) -> 0 | AD12: =+SUM(AD13:AD16) -> 0 | AE12: =+SUM(AE13:AE16) -> 0 | ... AG12: =+SUM(AG13:AG16) -> 0 | AH12: =+U12+AG12 -> 0
G13: Barranquilla | S13: =+Q13*R13 -> 0 | T13: =+R13 -> 0 | U13: =S13 -> 0 | Y13: =+$W13*X13 -> 0 | AA13: =+$W13*Z13 -> 0 | AC13: =+$W13*AB13 -> 0 | AE13: =+$W13*AD13 -> 0 | AG13: =+Y13+AA13+AC13+AE13 -> 0
G14: Soledad | S14: =+Q14*R14 -> 0 | T14: =+R14 -> 0 | U14: =S14 -> 0 | Y14: =+$W14*X14 -> 0 | AA14: =+$W14*Z14 -> 0 | AC14: =+$W14*AB14 -> 0 | AE14: =+$W14*AD14 -> 0 | AG14: =+Y14+AA14+AC14+AE14 -> 0
G15: Malambo | S15: =+Q15*R15 -> 0 | T15: =+R15 -> 0 | U15: =S15 -> 0 | Y15: =+$W15*X15 -> 0 | AA15: =+$W15*Z15 -> 0 | AC15: =+$W15*AB15 -> 0 | AE15: =+$W15*AD15 -> 0 | AG15: =+Y15+AA15+AC15+AE15 -> 0
G16: Sabanalarga | S16: =+Q16*R16 -> 0 | T16: =+R16 -> 0 | U16: =S16 -> 0 | Y16: =+$W16*X16 -> 0 | AA16: =+$W16*Z16 -> 0 | AC16: =+$W16*AB16 -> 0 | AE16: =+$W16*AD16 -> 0 | AG16: =+Y16+AA16+AC16+AE16 -> 0
A17: 13 | B17: 1 | C17: Refuerzo de la sociedad civil | G17: Desplazamientos por municipio | M17: Entidad Ejecutora | N17: ONG/OBC/Sector Académico | O17: Monitoreo y evaluación | P17: Desplazamiento | S17: =+SUM(S18:S21) -> 0 | T17: =+SUM(T18:T21) -> 0 | U17: =+SUM(U18:U21) -> 0 | V17: Desplazamiento | Y17: =+SUM(Y18:Y21) -> 0 | Z17: =+SUM(Z18:Z21) -> 0 | AA17: =+SUM(AA18:AA21) -> 0 | AB17: =+SUM(AB18:AB21) -> 0 | AC17: =+SUM(AC18:AC21) -> 0 | AD17: =+SUM(AD18:AD21) -> 0 | AE17: =+SUM(AE18:AE21) -> 0 | AF17: =+SUM(AF18:AF21) -> 0 | AG17: =+SUM(AG18:AG21) -> 0 | AH17: =+U17+AG17 -> 0
G18: Barranquilla | S18: =+Q18*R18 -> 0 | T18: =+R18 -> 0 | U18: =S18 -> 0 | Y18: =+$W18*X18 -> 0 | AA18: =+$W18*Z18 -> 0 | AC18: =+$W18*AB18 -> 0 | AE18: =+$W18*AD18 -> 0 | AG18: =+Y18+AA18+AC18+AE18 -> 0
G19: Soledad | S19: =+Q19*R19 -> 0 | T19: =+R19 -> 0 | U19: =S19 -> 0 | Y19: =+$W19*X19 -> 0 | AA19: =+$W19*Z19 -> 0 | AC19: =+$W19*AB19 -> 0 | AE19: =+$W19*AD19 -> 0 | AG19: =+Y19+AA19+AC19+AE19 -> 0
G20: Malambo | S20: =+Q20*R20 -> 0 | T20: =+R20 -> 0 | U20: =S20 -> 0 | Y20: =+$W20*X20 -> 0 | AA20: =+$W20*Z20 -> 0 | AC20: =+$W20*AB20 -> 0 | AE20: =+$W20*AD20 -> 0 | AG20: =+Y20+AA20+AC20+AE20 -> 0
G21: Sabanalarga | S21: =+Q21*R21 -> 0 | T21: =+R21 -> 0 | U21: =S21 -> 0 | Y21: =+$W21*X21 -> 0 | AA21: =+$W21*Z21 -> 0 | AC21: =+$W21*AB21 -> 0 | AE21: =+$W21*AD21 -> 0 | AG21: =+Y21+AA21+AC21+AE21 -> 0
A22: 13 | B22: 1 | C22: Refuerzo de la sociedad civil | G22: Actividades de Gestión | M22: Entidad Ejecutora | N22: ONG/OBC/Sector Académico | O22: Monitoreo y evaluación | P22: Costo reunión | S22: =+R22*Q22 -> 0 | T22: =+R22 -> 0 | U22: =S22 -> 0 | V22: Costo reunión | Y22: =+W22*X22 -> 0 | AA22: =+Z22*W22 -> 0 | AC22: =+AB22*W22 -> 0 | AE22: =+AD22*W22 -> 0 | AF22: =+X22+Z22+AB22+AD22 -> 0 | AG22: =+Y22+AA22+AC22+AE22 -> 0 | AH22: =+U22+AG22 -> 0
A23: 13 | B23: 1 | C23: Refuerzo de la sociedad civil | G23: Actividades Servicios Comunitarios | M23: Entidad Ejecutora | N23: ONG/OBC/Sector Académico | O23: Monitoreo y evaluación | P23: Actividades | S23: =+R23*Q23 -> 0 | T23: =+R23 -> 0 | U23: =S23 -> 0 | V23: Actividades | Y23: =+W23*X23 -> 0 | AA23: =+Z23*W23 -> 0 | AC23: =+AB23*W23 -> 0 | AE23: =+AD23*W23 -> 0 | AF23: =+X23+Z23+AB23+AD23 -> 0 | AG23: =+Y23+AA23+AC23+AE23 -> 0 | AH23: =+U23+AG23 -> 0
A24: PLANIFICACION Y ADMINISTRACION | AH24: =SUM(AH25) -> 0 | AI24: 37546163
A25: 8 | B25: 1 | C25: Refuerzo de la sociedad civil | D25: 1.1 Implementar estrategias de promoción de la demanda de asesoría y prueba voluntaria (APV) y de comunicación para el cambio de comportamiento (CCC) | E25: 1.1.5 Identificar y formar líderes pares de los grupos clave priorizados para que actúen como formadores e integren los equipos locales de promoción de la salud y prevención del VIH e ITS | F25: Este costo incluye los Costos Administrativos (como, Arriendo, servicios públicos, Comunicaciones, impresiones, fotocopias, papelería, correos, gastos bancarios, seguros, mantenimiento y reparaciones, servicios generales, entre otros). | M25: Entidad Ejecutora | N25: ONG/OBC/Sector Académico | O25: Planificación y Administración | S25: =+R25*Q25 -> 0 | T25: =+R25 -> 0 | U25: =S25 -> 0 | Y25: =+W25*X25 -> 0 | AA25: =+Z25*W25 -> 0 | AC25: =+AB25*W25 -> 0 | AE25: =+AD25*W25 -> 0 | AF25: =+X25+Z25+AB25+AD25 -> 0 | AG25: =+Y25+AA25+AC25+AE25 -> 0 | AH25: =+U25+AG25 -> 0
A26: TOTAL RUBROS DE FUNCIONAMIENTO | AH26: =+AH4+AH11+AH24 -> 0 | AI26: =+AI4+AI11+AI24 -> 417179578
AH27: =SUM(AH7:AH25) -> 0
A28: DESTINACION ESPECIFICA
A29: 6 | B29: 1 | C29: CCC (Comunicación para Cambio de Comportamiento)- Medios de comunicación | D29: 1.1 Implementar estrategias de promoción de la demanda de asesoría y prueba voluntaria (APV) y de comunicación para el cambio de comportamiento (CCC) | E29: 1.1.4 Implementar acciones de CCC y de promoción de demanda de APV en medios alternativos y cara-a-cara (outreach) para transformar conductas sexuales de riesgo, promover el uso consistente y adecuado del condón y divulgar servicios y rutas de derechos a los grupos clave | F29: Este costo esta representado por brigadas de acercamiento a los grupos clave en sus entornos naturales | G29: Costo por brigada. El costo asignado por brigada es de $15,355. Incluye alimentación y transporte | M29: Entidad Ejecutora | N29: ONG/OBC/Sector Académico | O29: Capacitación | P29: costo por brigada | Q29: =15355 -> 15355 | R29: =1295*0.2 -> 259 | S29: =+R29*Q29 -> 3976945 | T29: =+R29 -> 259 | U29: =S29 -> 3976945 | V29: costo por brigada | W29: =+Q29 -> 15355 | X29: 259 | Y29: =+W29*X29 -> 3976945 | Z29: 259 | AA29: =+Z29*W29 -> 3976945 | AB29: =+Z29 -> 259 | AC29: =+AB29*W29 -> 3976945 | AD29: =+AB29 -> 259 | AE29: =+AD29*W29 -> 3976945 | AF29: =+X29+Z29+AB29+AD29 -> 1036 | AG29: =+Y29+AA29+AC29+AE29 -> 15907780 | AH29: =+U29+AG29 -> 19884725
A30: 34 | B30: 1 | C30: Refuerzo de las capacidades institucionales | D30: 1.3 Crear y fortalecer servicios comunitarios y/o redes comunitarias tipo A para la prevención del VIH/Sida /ITS, la promoción y referencia a APV, la educación en derechos y el empoderamiento de los grupos clave | E30: 1.3.5 Diseñar e implementar un plan de mejoramiento de capacidades locativas, de dotación y del recurso humano en los servicios comunitarios tipo A para la implementación efectiva de estrategias de CCC, promoción de la demanda de APV, educación en derechos, educación de pares | F30: Desarrollo de asistencia técnica a los servicios comunitarios tipo A asignados en temas identificados en la evaluación de necesidades | G30: Costo por servicio comunitario de 24 horas (valor hora $36.000) | M30: Entidad Ejecutora | N30: ONG/OBC/Sector Académico | O30: Asistencia técnica y gerencial | P30: Costo por hora asistencia tecnica | S30: =+R30*Q30 -> 0 | T30: =+R30 -> 0 | U30: =S30 -> 0 | V30: Costo por hora asistencia tecnica | W30: =36000*24 -> 864000 | X30: 4 | Y30: =+W30*X30 -> 3456000 | Z30: 5 | AA30: =+Z30*W30 -> 4320000 | AC30: =+AB30*W30 -> 0 | AD30: =+AB30 -> 0 | AE30: =+AD30*W30 -> 0 | AF30: =+X30+Z30+AB30+AD30 -> 9 | AG30: =+Y30+AA30+AC30+AE30 -> 7776000 | AH30: =+U30+AG30 -> 7776000
A31: 35 | B31: 1 | C31: Refuerzo de las capacidades institucionales | D31: 1.3 Crear y fortalecer servicios comunitarios y/o redes comunitarias tipo A para la prevención del VIH/Sida /ITS, la promoción y referencia a APV, la educación en derechos y el empoderamiento de los grupos clave | E31: 1.3.5 Diseñar e implementar un plan de mejoramiento de capacidades locativas, de dotación y del recurso humano en los servicios comunitarios tipo A para la implementación efectiva de estrategias de CCC, promoción de la demanda de APV, educación en derechos, educación de pares | F31: Desarrollo de asistencia técnica a los servicios comunitarios tipo A asignados en temas identificados en la evaluación de necesidades | G31: Costo por servicio comunitario de 12 horas (valor hora $36.000) | M31: Entidad Ejecutora | N31: ONG/OBC/Sector Académico | O31: Asistencia técnica y gerencial | P31: Costo por hora asistencia tecnica | S31: =+R31*Q31 -> 0 | T31: =+R31 -> 0 | U31: =S31 -> 0 | V31: Costo por hora asistencia tecnica | W31: =36000*12 -> 432000 | Y31: =+W31*X31 -> 0 | Z31: =+X31 -> 0 | AA31: =+Z31*W31 -> 0 | AB31: 9 | AC31: =+AB31*W31 -> 3888000 | AD31: =+AB31 -> 9 | AE31: =+AD31*W31 -> 3888000 | AF31: =+X31+Z31+AB31+AD31 -> 18 | AG31: =+Y31+AA31+AC31+AE31 -> 7776000 | AH31: =+U31+AG31 -> 7776000
A32: 43 | B32: 1 | C32: Reducción del estigma en todas las circunstancias | D32: 1.4 Implementar estrategias de movilización social para la reducción del estigma y la discriminación, la incidencia política y el agenciamiento social | E32: 1.4.3 Implementar estrategias de comunicación y movilización social del nivel nacional y local (radio, medios alternativos y cara- a-cara) para la sensibilización de las comunidades para la reducción de estigma y discriminación | F32: Desarrollo de campañas locales en medios alternativos desarrolladas en eventos comunitarios para la movilización social en torno a la prevención del VIH y la promoción de la solidaridad frente a los grupos clave | G32: Este costo incluye campañas locales en medios alternativos | M32: Entidad Ejecutora | N32: ONG/OBC/Sector Académico | O32: Material de comunicación | P32: Costo por campaña | S32: =+R32*Q32 -> 0 | T32: =+R32 -> 0 | U32: =S32 -> 0 | V32: Costo por campaña | W32: 5000000 | X32: =+R32 -> 0 | Y32: =+W32*X32 -> 0 | Z32: 1 | AA32: =+Z32*W32 -> 5000000 | AC32: =+AB32*W32 -> 0 | AE32: =+AD32*W32 -> 0 | AF32: =+X32+Z32+AB32+AD32 -> 1 | AG32: =+Y32+AA32+AC32+AE32 -> 5000000 | AH32: =+U32+AG32 -> 5000000
A33: 46 | B33: 1 | C33: Refuerzo de la sociedad civil | D33: 1.4 Implementar estrategias de movilización social para la reducción del estigma y la discriminación, la incidencia política y el agenciamiento social | E33: 1.4.4 Implementar acciones de fortalecimiento de la capacidad de ciudadana y agenciamiento social de los grupos clave, a través de educación en derechos, empoderamiento y apoyo social | F33: Desarrollo de encuentros quincenales en los servicios comunitarios tipo A para educar en derechos, participación y ciudadanía a los grupos clave. | G33: Este costo incluye un apoyo al encuentro para agua, café y apoyo alquiler salón de reunión | M33: Entidad Ejecutora | N33: ONG/OBC/Sector Académico | O33: Capacitación | P33: Costo por encuentro | S33: =+R33*Q33 -> 0 | T33: =+R33 -> 0 | U33: =S33 -> 0 | V33: Costo por encuentro | W33: 100000 | X33: 12 | Y33: =+W33*X33 -> 1200000 | Z33: =+X33 -> 12 | AA33: =+Z33*W33 -> 1200000 | AB33: =+Z33 -> 12 | AC33: =+AB33*W33 -> 1200000 | AD33: 13 | AE33: =+AD33*W33 -> 1300000 | AF33: =+X33+Z33+AB33+AD33 -> 49 | AG33: =+Y33+AA33+AC33+AE33 -> 4900000 | AH33: =+U33+AG33 -> 4900000
A34: 12 | B34: 1 | C34: Refuerzo de la sociedad civil | D34: 1.1 Implementar estrategias de promoción de la demanda de asesoría y prueba voluntaria (APV) y de comunicación para el cambio de comportamiento (CCC) | E34: 1.1.5 Identificar y formar líderes pares de los grupos clave priorizados para que actúen como formadores e integren los equipos locales de promoción de la salud y prevención del VIH e ITS | F34: Costos administrativos, de operación y programaticos de la entidade ejecutora para el trabajo con servicios comunitarios para la identificación, selección, capacitación y seguimiento de lideres pares. Costos de prevención y promoción de APV, CCC, Uso de Condón, Reducción de Estigma y discriminación y seguimiento a tratamientos | G34: Costo Líderes pares de las Entidades Ejecutoras para los temas de prevención, diagnostico y tratamiento | M34: Entidad Ejecutora | N34: ONG/OBC/Sector Académico | O34: Monitoreo y evaluación | P34: Costo Incentivo Lideres Pares | Q34: =150000*3 -> 450000 | R34: 11 | S34: =+R34*Q34 -> 4950000 | T34: =+R34 -> 11 | U34: =S34 -> 4950000 | V34: =+P34 -> Costo Incentivo Lideres Pares | W34: =154500*3 -> 463500 | X34: =+R34 -> 11 | Y34: =+W34*X34 -> 5098500 | Z34: =42+11 -> 53 | AA34: =+Z34*W34 -> 24565500 | AB34: =+Z34 -> 53 | AC34: =+AB34*W34 -> 24565500 | AD34: =+AB34 -> 53 | AE34: =+AD34*W34 -> 24565500 | AF34: =+X34+Z34+AB34+AD34 -> 170 | AG34: =+Y34+AA34+AC34+AE34 -> 78795000 | AH34: =+U34+AG34 -> 83745000
A35: TOTAL DESTINACION ESPECIFICA | AH35: =SUM(AH29:AH34) -> 129081725 | AI35: =+AH35 -> 129081725
A36: TOTAL PRESUPUESTO | AI36: =+AI26+AI35 -> 546261303

Sheet Summary Eje Cafetero
A1: PRESUPUESTO ENTIDADES EJECUTORAS
A2: EJE CAFETERO
A4: Nombre Entidad Ejecutora:
A6: Detalle | B6: Presupuesto Total | C6: Tope Presupuestal
A7: Recurso Humano | B7: =+'[1]Fase I Valle del Cauca'!AH4 -> 0 | C7: =+'Fase I Eje Cafetero'!AI4 -> 241622788
A8: Monitoreo y Evaluación | B8: =+'[1]Fase I Valle del Cauca'!AH11 -> 0 | C8: =+'Fase I Eje Cafetero'!AI11 -> 72486830
A9: Planeación y Administración | B9: =+'[1]Fase I Valle del Cauca'!AH16 -> 0 | C9: =+'Fase I Eje Cafetero'!AI40 -> 31065782
A10: Total Rubros de Funcionamiento | B10: =SUM(B7:B9) -> 0 | C10: =SUM(C7:C9) -> 345175400
A12: Destinación Específica | B12: =+'Fase I Eje Cafetero'!AH51 -> 134111025 | C12: =+'Fase I Eje Cafetero'!AI51 -> 134111025
A13: Total Destinación Específica | B13: =+B12 -> 134111025 | C13: =+C12 -> 134111025
A14: PRESUPUESTO TOTAL | B14: =+B10+B13 -> 134111025 | C14: =+C10+C13 -> 479286425
A19: XXXXXX
A20: REPRESENTANTE LEGAL

Sheet Fase I Eje Cafetero
A1: PRESUPUESTO DETALLADO
A2: No | B2: No de Objetivo: Crear capacidad comunitaria para la adopción de comportamientos seguros, la reducción de la vulnerabilidad social al VIH y el empoderamiento de los grupos clave priorizados | C2: Área de prestación de servicios (APS) | D2: Macro-Categoría | E2: Tarea | F2: Sub -Tarea | G2: Descripción / Hipotesis | H2: Año 1 | I2: Año 2 | M2: Responsable de la ejecución | N2: Tipo de entidad ejecutora | O2: Categorías de costos | P2: Unidad de medida año 1 | Q2: Costo unitario año 1 (valor trimestre) | R2: Cantidad Trimestre 4 | S2: Importe total Trimestre 4 | T2: Cantidad total Año 1 | U2: Total Año 1 | V2: Unidad de medida año 2 | W2: Costo unitario año 2 (valor trimestre) | X2: Cantidad Trimestre 1 año 2 | Y2: Importe total Trimestre 1 año 2 | Z2: Cantidad Trimestre 2 año 2 | AA2: Importe total Trimestre 2 año 2 | AB2: Cantidad Trimestre 3 año 2 | AC2: Importe total Trimestre 3 año 2 | AD2: Cantidad Trimestre 4 año 2 | AE2: Importe total Trimestre 4 año 2 | AF2: Cantidad total Año 2 | AG2: Total Año 2 | AH2: COSTO TOTAL | AI2: Tope Presupuestal
C3: SDA | D3: Activity | H3: T4 | I3: T1 | J3: T2 | K3: T3 | L3: T4
A4: RECURSO HUMANO | AH4: =SUM(AH5:AH10) -> 0 | AI4: 241622788
A5: 7 | B5: 1 | C5: Refuerzo de la sociedad civil | D5: 1.1 Implementar estrategias de promoción de la demanda de asesoría y prueba voluntaria (APV) y de comunicación para el cambio de comportamiento (CCC) | E5: 1.1.5 Identificar y formar líderes pares de los grupos clave priorizados para que actúen como formadores e integren los equipos locales de promoción de la salud y prevención del VIH e ITS | F5: Costo recurso humano administración de la entidad ejecutora | G5: Contador | M5: Entidad Ejecutora | N5: ONG/OBC/Sector Académico | O5: Recursos Humanos | P5: Salario / Honorario | S5: =+R5*Q5 -> 0 | T5: =+R5 -> 0 | U5: =S5 -> 0 | V5: Salario / Honorario | Y5: =+W5*X5 -> 0 | AA5: =+Z5*W5 -> 0 | AC5: =+AB5*W5 -> 0 | AE5: =+AD5*W5 -> 0 | AF5: =+X5+Z5+AB5+AD5 -> 0 | AG5: =+Y5+AA5+AC5+AE5 -> 0 | AH5: =+U5+AG5 -> 0
A6: 7 | B6: 1 | G6: Apoyo a la Dirección o Representación Legal | M6: Entidad Ejecutora | N6: ONG/OBC/Sector Académico | O6: Recursos Humanos | P6: Salario / Honorario | S6: =+R6*Q6 -> 0 | T6: =+R6 -> 0 | U6: =S6 -> 0 | V6: Salario / Honorario | Y6: =+W6*X6 -> 0 | AA6: =+Z6*W6 -> 0 | AC6: =+AB6*W6 -> 0 | AE6: =+AD6*W6 -> 0 | AF6: =+X6+Z6+AB6+AD6 -> 0 | AG6: =+Y6+AA6+AC6+AE6 -> 0 | AH6: =+U6+AG6 -> 0
A7: 7 | B7: 1 | G7: Asistente de Información | M7: Entidad Ejecutora | N7: ONG/OBC/Sector Académico | O7: Recursos Humanos | P7: Salario / Honorario | S7: =+R7*Q7 -> 0 | T7: =+R7 -> 0 | U7: =S7 -> 0 | V7: Salario / Honorario | Y7: =+W7*X7 -> 0 | AA7: =+Z7*W7 -> 0 | AC7: =+AB7*W7 -> 0 | AE7: =+AD7*W7 -> 0 | AF7: =+X7+Z7+AB7+AD7 -> 0 | AG7: =+Y7+AA7+AC7+AE7 -> 0 | AH7: =+U7+AG7 -> 0
A8: 11 | B8: 1 | C8: Refuerzo de la sociedad civil | F8: Costo recurso humano programatico de la entidad ejecutora | G8: Coordinador | M8: Entidad Ejecutora | N8: ONG/OBC/Sector Académico | O8: Recursos Humanos | P8: Salario / Honorario | S8: =+R8*Q8 -> 0 | T8: =+R8 -> 0 | U8: =S8 -> 0 | V8: Salario / Honorario | Y8: =+W8*X8 -> 0 | AA8: =+Z8*W8 -> 0 | AC8: =+AB8*W8 -> 0 | AE8: =+AD8*W8 -> 0 | AF8: =+X8+Z8+AB8+AD8 -> 0 | AG8: =+Y8+AA8+AC8+AE8 -> 0 | AH8: =+U8+AG8 -> 0
A9: 11 | B9: 1 | C9: Refuerzo de la sociedad civil | G9: Profesionales en Salud Sexual y Reproductiva (SSR) | M9: Entidad Ejecutora | N9: ONG/OBC/Sector Académico | O9: Recursos Humanos | P9: Salario / Honorario | S9: =+R9*Q9 -> 0 | T9: =+R9 -> 0 | U9: =S9 -> 0 | V9: Salario / Honorario | Y9: =+W9*X9 -> 0 | AA9: =+Z9*W9 -> 0 | AC9: =+AB9*W9 -> 0 | AE9: =+AD9*W9 -> 0 | AF9: =+X9+Z9+AB9+AD9 -> 0 | AG9: =+Y9+AA9+AC9+AE9 -> 0 | AH9: =+U9+AG9 -> 0
A10: 11 | B10: 1 | C10: Refuerzo de la sociedad civil | G10: Técnicos en Salud Sexual y Reproductiva (SSR) | M10: Entidad Ejecutora | N10: ONG/OBC/Sector Académico | O10: Recursos Humanos | P10: Salario / Honorario | S10: =+R10*Q10 -> 0 | T10: =+R10 -> 0 | U10: =S10 -> 0 | V10: Salario / Honorario | Y10: =+W10*X10 -> 0 | AA10: =+Z10*W10 -> 0 | AC10: =+AB10*W10 -> 0 | AE10: =+AD10*W10 -> 0 | AF10: =+X10+Z10+AB10+AD10 -> 0 | AG10: =+Y10+AA10+AC10+AE10 -> 0 | AH10: =+U10+AG10 -> 0
A11: MONITOREO Y EVALUACION | AH11: =SUM(AH12:AH39) -> 0 | AI11: 72486830
A12: 13 | B12: 1 | C12: Refuerzo de la sociedad civil | D12: 1.1 Implementar estrategias de promoción de la demanda de asesoría y prueba voluntaria (APV) y de comunicación para el cambio de comportamiento (CCC) | E12: 1.1.5 Identificar y formar líderes pares de los grupos clave priorizados para que actúen como formadores e integren los equipos locales de promoción de la salud y prevención del VIH e ITS | F12: Este costo incluye: 1. Viaticos y desplazamientos a los municipios de influencia asignados. 2. Actividades de gestion municipal y departamental para la sostenibilidad de las iniciativas. 3. Actividades en los servicios comunitarios para el encuentro con las comunidades, generación de confianza con las poblaciones priorizadas, actividades de escucha, reducción del estigma y la discriminaciòn, entre otras (Ejm: chocolatadas, teatro o cine al parque, actividades de trueque, acciones sanatorias de apoyo en situaciòn de alta vulnerabilidad para estabilizar a las poblaciones, entre otras) | G12: Viaticos por municipio | M12: Entidad Ejecutora | N12: ONG/OBC/Sector Académico | O12: Monitoreo y evaluación | P12: Viatico | S12: =+SUM(S13:S24) -> 0 | T12: =+SUM(T13:T24) -> 0 | U12: =+SUM(U13:U24) -> 0 | V12: Viatico | X12: =+SUM(X13:X24) -> 0 | Y12: =+SUM(Y13:Y24) -> 0 | Z12: =+SUM(Z13:Z24) -> 0 | AA12: =+SUM(AA13:AA24) -> 0 | AB12: =+SUM(AB13:AB24) -> 0 | AC12: =+SUM(AC13:AC24) -> 0 | AD12: =+SUM(AD13:AD24) -> 0 | AE12: =+SUM(AE13:AE24) -> 0 | ... AG12: =+SUM(AG13:AG24) -> 0 | AH12: =+U12+AG12 -> 0
G13: Anserma | S13: =+Q13*R13 -> 0 | T13: =+R13 -> 0 | U13: =+S13 -> 0 | Y13: =+$W13*X13 -> 0 | AA13: =+$W13*Z13 -> 0 | AC13: =+$W13*AB13 -> 0 | AE13: =+$W13*AD13 -> 0 | AF13: =+X13+Z13+AB13+AD13 -> 0 | AG13: =+Y13+AA13+AC13+AE13 -> 0
G14: Chinchina | S14: =+Q14*R14 -> 0 | T14: =+R14 -> 0 | U14: =+S14 -> 0 | Y14: =+$W14*X14 -> 0 | AA14: =+$W14*Z14 -> 0 | AC14: =+$W14*AB14 -> 0 | AE14: =+$W14*AD14 -> 0 | AF14: =+X14+Z14+AB14+AD14 -> 0 | AG14: =+Y14+AA14+AC14+AE14 -> 0
G15: La Dorada | S15: =+Q15*R15 -> 0 | T15: =+R15 -> 0 | U15: =+S15 -> 0 | Y15: =+$W15*X15 -> 0 | AA15: =+$W15*Z15 -> 0 | AC15: =+$W15*AB15 -> 0 | AE15: =+$W15*AD15 -> 0 | AF15: =+X15+Z15+AB15+AD15 -> 0 | AG15: =+Y15+AA15+AC15+AE15 -> 0
G16: Manizales | S16: =+Q16*R16 -> 0 | T16: =+R16 -> 0 | U16: =+S16 -> 0 | Y16: =+$W16*X16 -> 0 | AA16: =+$W16*Z16 -> 0 | AC16: =+$W16*AB16 -> 0 | AE16: =+$W16*AD16 -> 0 | AF16: =+X16+Z16+AB16+AD16 -> 0 | AG16: =+Y16+AA16+AC16+AE16 -> 0
G17: Armenia | S17: =+Q17*R17 -> 0 | T17: =+R17 -> 0 | U17: =+S17 -> 0 | Y17: =+$W17*X17 -> 0 | AA17: =+$W17*Z17 -> 0 | AC17: =+$W17*AB17 -> 0 | AE17: =+$W17*AD17 -> 0 | AF17: =+X17+Z17+AB17+AD17 -> 0 | AG17: =+Y17+AA17+AC17+AE17 -> 0
G18: Calarca | S18: =+Q18*R18 -> 0 | T18: =+R18 -> 0 | U18: =+S18 -> 0 | Y18: =+$W18*X18 -> 0 | AA18: =+$W18*Z18 -> 0 | AC18: =+$W18*AB18 -> 0 | AE18: =+$W18*AD18 -> 0 | AF18: =+X18+Z18+AB18+AD18 -> 0 | AG18: =+Y18+AA18+AC18+AE18 -> 0
G19: Circasia | S19: =+Q19*R19 -> 0 | T19: =+R19 -> 0 | U19: =+S19 -> 0 | Y19: =+$W19*X19 -> 0 | AA19: =+$W19*Z19 -> 0 | AC19: =+$W19*AB19 -> 0 | AE19: =+$W19*AD19 -> 0 | AF19: =+X19+Z19+AB19+AD19 -> 0 | AG19: =+Y19+AA19+AC19+AE19 -> 0
G20: Montenegro | S20: =+Q20*R20 -> 0 | T20: =+R20 -> 0 | U20: =+S20 -> 0 | Y20: =+$W20*X20 -> 0 | AA20: =+$W20*Z20 -> 0 | AC20: =+$W20*AB20 -> 0 | AE20: =+$W20*AD20 -> 0 | AF20: =+X20+Z20+AB20+AD20 -> 0 | AG20: =+Y20+AA20+AC20+AE20 -> 0
G21: Dosquebradas | S21: =+Q21*R21 -> 0 | T21: =+R21 -> 0 | U21: =+S21 -> 0 | Y21: =+$W21*X21 -> 0 | AA21: =+$W21*Z21 -> 0 | AC21: =+$W21*AB21 -> 0 | AE21: =+$W21*AD21 -> 0 | AF21: =+X21+Z21+AB21+AD21 -> 0 | AG21: =+Y21+AA21+AC21+AE21 -> 0
G22: La Virginia | S22: =+Q22*R22 -> 0 | T22: =+R22 -> 0 | U22: =+S22 -> 0 | Y22: =+$W22*X22 -> 0 | AA22: =+$W22*Z22 -> 0 | AC22: =+$W22*AB22 -> 0 | AE22: =+$W22*AD22 -> 0 | AF22: =+X22+Z22+AB22+AD22 -> 0 | AG22: =+Y22+AA22+AC22+AE22 -> 0
G23: Pereira | S23: =+Q23*R23 -> 0 | T23: =+R23 -> 0 | U23: =+S23 -> 0 | Y23: =+$W23*X23 -> 0 | AA23: =+$W23*Z23 -> 0 | AC23: =+$W23*AB23 -> 0 | AE23: =+$W23*AD23 -> 0 | AF23: =+X23+Z23+AB23+AD23 -> 0 | AG23: =+Y23+AA23+AC23+AE23 -> 0
G24: Santa Rosa de Cabal | S24: =+Q24*R24 -> 0 | T24: =+R24 -> 0 | U24: =+S24 -> 0 | Y24: =+$W24*X24 -> 0 | AA24: =+$W24*Z24 -> 0 | AC24: =+$W24*AB24 -> 0 | AE24: =+$W24*AD24 -> 0 | AF24: =+X24+Z24+AB24+AD24 -> 0 | AG24: =+Y24+AA24+AC24+AE24 -> 0
A25: 13 | B25: 1 | C25: Refuerzo de la sociedad civil | G25: Desplazamientos por municipio | M25: Entidad Ejecutora | N25: ONG/OBC/Sector Académico | O25: Monitoreo y evaluación | P25: Desplazamiento | S25: =+SUM(S26:S37) -> 0 | T25: =+SUM(T26:T37) -> 0 | U25: =+SUM(U26:U37) -> 0 | V25: Desplazamiento | X25: =+SUM(X26:X37) -> 0 | Y25: =+SUM(Y26:Y37) -> 0 | Z25: =+SUM(Z26:Z37) -> 0 | AA25: =+SUM(AA26:AA37) -> 0 | AB25: =+SUM(AB26:AB37) -> 0 | AC25: =+SUM(AC26:AC37) -> 0 | AD25: =+SUM(AD26:AD37) -> 0 | AE25: =+SUM(AE26:AE37) -> 0 | AF25: =+SUM(AF26:AF37) -> 0 | AG25: =+Y25+AA25+AC25+AE25 -> 0 | AH25: =+U25+AG25 -> 0
G26: Anserma | S26: =+Q26*R26 -> 0 | T26: =+R26 -> 0 | U26: =+S26 -> 0 | Y26: =+$W26*X26 -> 0 | AA26: =+$W26*Z26 -> 0 | AC26: =+$W26*AB26 -> 0 | AE26: =+$W26*AD26 -> 0 | AF26: =+X26+Z26+AB26+AD26 -> 0 | AG26: =+Y26+AA26+AC26+AE26 -> 0
G27: Chinchina | S27: =+Q27*R27 -> 0 | T27: =+R27 -> 0 | U27: =+S27 -> 0 | Y27: =+$W27*X27 -> 0 | AA27: =+$W27*Z27 -> 0 | AC27: =+$W27*AB27 -> 0 | AE27: =+$W27*AD27 -> 0 | AF27: =+X27+Z27+AB27+AD27 -> 0 | AG27: =+Y27+AA27+AC27+AE27 -> 0
G28: La Dorada | S28: =+Q28*R28 -> 0 | T28: =+R28 -> 0 | U28: =+S28 -> 0 | Y28: =+$W28*X28 -> 0 | AA28: =+$W28*Z28 -> 0 | AC28: =+$W28*AB28 -> 0 | AE28: =+$W28*AD28 -> 0 | AF28: =+X28+Z28+AB28+AD28 -> 0 | AG28: =+Y28+AA28+AC28+AE28 -> 0
G29: Manizales | S29: =+Q29*R29 -> 0 | T29: =+R29 -> 0 | U29: =+S29 -> 0 | Y29: =+$W29*X29 -> 0 | AA29: =+$W29*Z29 -> 0 | AC29: =+$W29*AB29 -> 0 | AE29: =+$W29*AD29 -> 0 | AF29: =+X29+Z29+AB29+AD29 -> 0 | AG29: =+Y29+AA29+AC29+AE29 -> 0
G30: Armenia | S30: =+Q30*R30 -> 0 | T30: =+R30 -> 0 | U30: =+S30 -> 0 | Y30: =+$W30*X30 -> 0 | AA30: =+$W30*Z30 -> 0 | AC30: =+$W30*AB30 -> 0 | AE30: =+$W30*AD30 -> 0 | AF30: =+X30+Z30+AB30+AD30 -> 0 | AG30: =+Y30+AA30+AC30+AE30 -> 0
G31: Calarca | S31: =+Q31*R31 -> 0 | T31: =+R31 -> 0 | U31: =+S31 -> 0 | Y31: =+$W31*X31 -> 0 | AA31: =+$W31*Z31 -> 0 | AC31: =+$W31*AB31 -> 0 | AE31: =+$W31*AD31 -> 0 | AF31: =+X31+Z31+AB31+AD31 -> 0 | AG31: =+Y31+AA31+AC31+AE31 -> 0
G32: Circasia | S32: =+Q32*R32 -> 0 | T32: =+R32 -> 0 | U32: =+S32 -> 0 | Y32: =+$W32*X32 -> 0 | AA32: =+$W32*Z32 -> 0 | AC32: =+$W32*AB32 -> 0 | AE32: =+$W32*AD32 -> 0 | AF32: =+X32+Z32+AB32+AD32 -> 0 | AG32: =+Y32+AA32+AC32+AE32 -> 0
G33: Montenegro | S33: =+Q33*R33 -> 0 | T33: =+R33 -> 0 | U33: =+S33 -> 0 | Y33: =+$W33*X33 -> 0 | AA33: =+$W33*Z33 -> 0 | AC33: =+$W33*AB33 -> 0 | AE33: =+$W33*AD33 -> 0 | AF33: =+X33+Z33+AB33+AD33 -> 0 | AG33: =+Y33+AA33+AC33+AE33 -> 0
G34: Dosquebradas | S34: =+Q34*R34 -> 0 | T34: =+R34 -> 0 | U34: =+S34 -> 0 | Y34: =+$W34*X34 -> 0 | AA34: =+$W34*Z34 -> 0 | AC34: =+$W34*AB34 -> 0 | AE34: =+$W34*AD34 -> 0 | AF34: =+X34+Z34+AB34+AD34 -> 0 | AG34: =+Y34+AA34+AC34+AE34 -> 0
G35: La Virginia | S35: =+Q35*R35 -> 0 | T35: =+R35 -> 0 | U35: =+S35 -> 0 | Y35: =+$W35*X35 -> 0 | AA35: =+$W35*Z35 -> 0 | AC35: =+$W35*AB35 -> 0 | AE35: =+$W35*AD35 -> 0 | AF35: =+X35+Z35+AB35+AD35 -> 0 | AG35: =+Y35+AA35+AC35+AE35 -> 0
G36: Pereira | S36: =+Q36*R36 -> 0 | T36: =+R36 -> 0 | U36: =+S36 -> 0 | Y36: =+$W36*X36 -> 0 | AA36: =+$W36*Z36 -> 0 | AC36: =+$W36*AB36 -> 0 | AE36: =+$W36*AD36 -> 0 | AF36: =+X36+Z36+AB36+AD36 -> 0 | AG36: =+Y36+AA36+AC36+AE36 -> 0
G37: Santa Rosa de Cabal | S37: =+Q37*R37 -> 0 | T37: =+R37 -> 0 | U37: =+S37 -> 0 | Y37: =+$W37*X37 -> 0 | AA37: =+$W37*Z37 -> 0 | AC37: =+$W37*AB37 -> 0 | AE37: =+$W37*AD37 -> 0 | AF37: =+X37+Z37+AB37+AD37 -> 0 | AG37: =+Y37+AA37+AC37+AE37 -> 0
A38: 13 | B38: 1 | C38: Refuerzo de la sociedad civil | G38: Actividades de Gestión | M38: Entidad Ejecutora | N38: ONG/OBC/Sector Académico | O38: Monitoreo y evaluación | P38: Costo reunión | S38: =+R38*Q38 -> 0 | T38: =+R38 -> 0 | U38: =S38 -> 0 | V38: Costo reunión | Y38: =+W38*X38 -> 0 | AA38: =+Z38*W38 -> 0 | AC38: =+AB38*W38 -> 0 | AE38: =+AD38*W38 -> 0 | AF38: =+X38+Z38+AB38+AD38 -> 0 | AG38: =+Y38+AA38+AC38+AE38 -> 0 | AH38: =+U38+AG38 -> 0
A39: 13 | B39: 1 | C39: Refuerzo de la sociedad civil | G39: Actividades Servicios Comunitarios | M39: Entidad Ejecutora | N39: ONG/OBC/Sector Académico | O39: Monitoreo y evaluación | P39: Actividades | S39: =+R39*Q39 -> 0 | T39: =+R39 -> 0 | U39: =S39 -> 0 | V39: Actividades | Y39: =+W39*X39 -> 0 | AA39: =+Z39*W39 -> 0 | AC39: =+AB39*W39 -> 0 | AE39: =+AD39*W39 -> 0 | AF39: =+X39+Z39+AB39+AD39 -> 0 | AG39: =+Y39+AA39+AC39+AE39 -> 0 | AH39: =+U39+AG39 -> 0
A40: PLANIFICACION Y ADMINISTRACION | AH40: =SUM(AH41) -> 0 | AI40: 31065782
A41: 8 | B41: 1 | C41: Refuerzo de la sociedad civil | D41: 1.1 Implementar estrategias de promoción de la demanda de asesoría y prueba voluntaria (APV) y de comunicación para el cambio de comportamiento (CCC) | E41: 1.1.5 Identificar y formar líderes pares de los grupos clave priorizados para que actúen como formadores e integren los equipos locales de promoción de la salud y prevención del VIH e ITS | F41: Este costo incluye los Costos Administrativos (como, Arriendo, servicios públicos, Comunicaciones, impresiones, fotocopias, papelería, correos, gastos bancarios, seguros, mantenimiento y reparaciones, servicios generales, entre otros). | M41: Entidad Ejecutora | N41: ONG/OBC/Sector Académico | O41: Planificación y Administración | S41: =+R41*Q41 -> 0 | T41: =+R41 -> 0 | U41: =S41 -> 0 | Y41: =+W41*X41 -> 0 | AA41: =+Z41*W41 -> 0 | AC41: =+AB41*W41 -> 0 | AE41: =+AD41*W41 -> 0 | AF41: =+X41+Z41+AB41+AD41 -> 0 | AG41: =+Y41+AA41+AC41+AE41 -> 0 | AH41: =+U41+AG41 -> 0
A42: TOTAL RUBROS DE FUNCIONAMIENTO | AH42: =+AH4+AH11+AH40 -> 0 | AI42: =+AI4+AI11+AI40 -> 345175400
AH43: =SUM(AH7:AH41) -> 0
A44: DESTINACION ESPECIFICA
A45: 6 | B45: 1 | C45: CCC (Comunicación para Cambio de Comportamiento)- Medios de comunicación | D45: 1.1 Implementar estrategias de promoción de la demanda de asesoría y prueba voluntaria (APV) y de comunicación para el cambio de comportamiento (CCC) | E45: 1.1.4 Implementar acciones de CCC y de promoción de demanda de APV en medios alternativos y cara-a-cara (outreach) para transformar conductas sexuales de riesgo, promover el uso consistente y adecuado del condón y divulgar servicios y rutas de derechos a los grupos clave | F45: Este costo esta representado por brigadas de acercamiento a los grupos clave en sus entornos naturales | G45: Costo por brigada. El costo asignado por brigada es de $15,355. Incluye alimentación y transporte | M45: Entidad Ejecutora | N45: ONG/OBC/Sector Académico | O45: Capacitación | P45: costo por brigada | Q45: =15355 -> 15355 | R45: =955*0.2 -> 191 | S45: =+R45*Q45 -> 2932805 | T45: =+R45 -> 191 | U45: =S45 -> 2932805 | V45: costo por brigada | W45: =+Q45 -> 15355 | X45: 191 | Y45: =+W45*X45 -> 2932805 | Z45: 191 | AA45: =+Z45*W45 -> 2932805 | AB45: =+Z45 -> 191 | AC45: =+AB45*W45 -> 2932805 | AD45: =+AB45 -> 191 | AE45: =+AD45*W45 -> 2932805 | AF45: =+X45+Z45+AB45+AD45 -> 764 | AG45: =+Y45+AA45+AC45+AE45 -> 11731220 | AH45: =+U45+AG45 -> 14664025
A46: 34 | B46: 1 | C46: Refuerzo de las capacidades institucionales | D46: 1.3 Crear y fortalecer servicios comunitarios y/o redes comunitarias tipo A para la prevención del VIH/Sida /ITS, la promoción y referencia a APV, la educación en derechos y el empoderamiento de los grupos clave | E46: 1.3.5 Diseñar e implementar un plan de mejoramiento de capacidades locativas, de dotación y del recurso humano en los servicios comunitarios tipo A para la implementación efectiva de estrategias de CCC, promoción de la demanda de APV, educación en derechos, educación de pares | F46: Desarrollo de asistencia técnica a los servicios comunitarios tipo A asignados en temas identificados en la evaluación de necesidades | G46: Costo por servicio comunitario de 24 horas (valor hora $36.000) | M46: Entidad Ejecutora | N46: ONG/OBC/Sector Académico | O46: Asistencia técnica y gerencial | P46: Costo por hora asistencia tecnica | S46: =+R46*Q46 -> 0 | T46: =+R46 -> 0 | U46: =S46 -> 0 | V46: Costo por hora asistencia tecnica | W46: =36000*24 -> 864000 | X46: 7 | Y46: =+W46*X46 -> 6048000 | Z46: 6 | AA46: =+Z46*W46 -> 5184000 | AC46: =+AB46*W46 -> 0 | AD46: =+AB46 -> 0 | AE46: =+AD46*W46 -> 0 | AF46: =+X46+Z46+AB46+AD46 -> 13 | AG46: =+Y46+AA46+AC46+AE46 -> 11232000 | AH46: =+U46+AG46 -> 11232000
A47: 35 | B47: 1 | C47: Refuerzo de las capacidades institucionales | D47: 1.3 Crear y fortalecer servicios comunitarios y/o redes comunitarias tipo A para la prevención del VIH/Sida /ITS, la promoción y referencia a APV, la educación en derechos y el empoderamiento de los grupos clave | E47: 1.3.5 Diseñar e implementar un plan de mejoramiento de capacidades locativas, de dotación y del recurso humano en los servicios comunitarios tipo A para la implementación efectiva de estrategias de CCC, promoción de la demanda de APV, educación en derechos, educación de pares | F47: Desarrollo de asistencia técnica a los servicios comunitarios tipo A asignados en temas identificados en la evaluación de necesidades | G47: Costo por servicio comunitario de 12 horas (valor hora $36.000) | M47: Entidad Ejecutora | N47: ONG/OBC/Sector Académico | O47: Asistencia técnica y gerencial | P47: Costo por hora asistencia tecnica | S47: =+R47*Q47 -> 0 | T47: =+R47 -> 0 | U47: =S47 -> 0 | V47: Costo por hora asistencia tecnica | W47: =36000*12 -> 432000 | Y47: =+W47*X47 -> 0 | Z47: =+X47 -> 0 | AA47: =+Z47*W47 -> 0 | AB47: 13 | AC47: =+AB47*W47 -> 5616000 | AD47: =+AB47 -> 13 | AE47: =+AD47*W47 -> 5616000 | AF47: =+X47+Z47+AB47+AD47 -> 26 | AG47: =+Y47+AA47+AC47+AE47 -> 11232000 | AH47: =+U47+AG47 -> 11232000
A48: 43 | B48: 1 | C48: Reducción del estigma en todas las circunstancias | D48: 1.4 Implementar estrategias de movilización social para la reducción del estigma y la discriminación, la incidencia política y el agenciamiento social | E48: 1.4.3 Implementar estrategias de comunicación y movilización social del nivel nacional y local (radio, medios alternativos y cara- a-cara) para la sensibilización de las comunidades para la reducción de estigma y discriminación | F48: Desarrollo de campañas locales en medios alternativos desarrolladas en eventos comunitarios para la movilización social en torno a la prevención del VIH y la promoción de la solidaridad frente a los grupos clave | G48: Este costo incluye campañas locales en medios alternativos | M48: Entidad Ejecutora | N48: ONG/OBC/Sector Académico | O48: Material de comunicación | P48: Costo por campaña | S48: =+R48*Q48 -> 0 | T48: =+R48 -> 0 | U48: =S48 -> 0 | V48: Costo por campaña | W48: 5000000 | X48: =+R48 -> 0 | Y48: =+W48*X48 -> 0 | Z48: 1 | AA48: =+Z48*W48 -> 5000000 | AC48: =+AB48*W48 -> 0 | AD48: 2 | AE48: =+AD48*W48 -> 10000000 | AF48: =+X48+Z48+AB48+AD48 -> 3 | AG48: =+Y48+AA48+AC48+AE48 -> 15000000 | AH48: =+U48+AG48 -> 15000000
A49: 46 | B49: 1 | C49: Refuerzo de la sociedad civil | D49: 1.4 Implementar estrategias de movilización social para la reducción del estigma y la discriminación, la incidencia política y el agenciamiento social | E49: 1.4.4 Implementar acciones de fortalecimiento de la capacidad de ciudadana y agenciamiento social de los grupos clave, a través de educación en derechos, empoderamiento y apoyo social | F49: Desarrollo de encuentros quincenales en los servicios comunitarios tipo A para educar en derechos, participación y ciudadanía a los grupos clave. | G49: Este costo incluye un apoyo al encuentro para agua, café y apoyo alquiler salón de reunión | M49: Entidad Ejecutora | N49: ONG/OBC/Sector Académico | O49: Capacitación | P49: Costo por encuentro | S49: =+R49*Q49 -> 0 | T49: =+R49 -> 0 | U49: =S49 -> 0 | V49: Costo por encuentro | W49: 100000 | X49: 9 | Y49: =+W49*X49 -> 900000 | Z49: =+X49 -> 9 | AA49: =+Z49*W49 -> 900000 | AB49: =+Z49 -> 9 | AC49: =+AB49*W49 -> 900000 | AD49: 11 | AE49: =+AD49*W49 -> 1100000 | AF49: =+X49+Z49+AB49+AD49 -> 38 | AG49: =+Y49+AA49+AC49+AE49 -> 3800000 | AH49: =+U49+AG49 -> 3800000
A50: 12 | B50: 1 | C50: Refuerzo de la sociedad civil | D50: 1.1 Implementar estrategias de promoción de la demanda de asesoría y prueba voluntaria (APV) y de comunicación para el cambio de comportamiento (CCC) | E50: 1.1.5 Identificar y formar líderes pares de los grupos clave priorizados para que actúen como formadores e integren los equipos locales de promoción de la salud y prevención del VIH e ITS | F50: Costos administrativos, de operación y programaticos de la entidade ejecutora para el trabajo con servicios comunitarios para la identificación, selección, capacitación y seguimiento de lideres pares. Costos de prevención y promoción de APV, CCC, Uso de Condón, Reducción de Estigma y discriminación y seguimiento a tratamientos | G50: Costo Líderes pares de las Entidades Ejecutoras para los temas de prevención, diagnostico y tratamiento | M50: Entidad Ejecutora | N50: ONG/OBC/Sector Académico | O50: Monitoreo y evaluación | P50: Costo Incentivo Lideres Pares | Q50: =150000*3 -> 450000 | R50: 11 | S50: =+R50*Q50 -> 4950000 | T50: =+R50 -> 11 | U50: =S50 -> 4950000 | V50: =+P50 -> Costo Incentivo Lideres Pares | W50: =154500*3 -> 463500 | X50: =+R50 -> 11 | Y50: =+W50*X50 -> 5098500 | Z50: =38+11 -> 49 | AA50: =+Z50*W50 -> 22711500 | AB50: =+Z50 -> 49 | AC50: =+AB50*W50 -> 22711500 | AD50: =+AB50 -> 49 | AE50: =+AD50*W50 -> 22711500 | AF50: =+X50+Z50+AB50+AD50 -> 158 | AG50: =+Y50+AA50+AC50+AE50 -> 73233000 | AH50: =+U50+AG50 -> 78183000
A51: TOTAL DESTINACION ESPECIFICA | AH51: =SUM(AH45:AH50) -> 134111025 | AI51: =+AH51 -> 134111025
A52: TOTAL PRESUPUESTO | AI52: =+AI42+AI51 -> 479286425

Sheet Summary MAG-Guajira
A1: PRESUPUESTO ENTIDADES EJECUTORAS
A2: MAGDALENA Y GUAJIRA
A4: Nombre Entidad Ejecutora:
A6: Detalle | B6: Presupuesto Total | C6: Tope Presupuestal
A7: Recurso Humano | B7: =+'[1]Fase I Valle del Cauca'!AH4 -> 0 | C7: =+'Fase I MAG-Guajira'!AI4 -> 234559238
A8: Monitoreo y Evaluación | B8: =+'[1]Fase I Valle del Cauca'!AH11 -> 0 | C8: =+'Fase I MAG-Guajira'!AI11 -> 70367776
A9: Planeación y Administración | B9: =+'[1]Fase I Valle del Cauca'!AH16 -> 0 | C9: =+'Fase I MAG-Guajira'!AI28 -> 30157612
A10: Total Rubros de Funcionamiento | B10: =SUM(B7:B9) -> 0 | C10: =SUM(C7:C9) -> 335084626
A12: Destinación Específica | B12: =+'Fase I MAG-Guajira'!AH39 -> 109441075 | C12: =+'Fase I MAG-Guajira'!AI39 -> 109441075
A13: Total Destinación Específica | B13: =+B12 -> 109441075 | C13: =+C12 -> 109441075
A14: PRESUPUESTO TOTAL | B14: =+B10+B13 -> 109441075 | C14: =+C10+C13 -> 444525701
A19: XXXXXX
A20: REPRESENTANTE LEGAL

Sheet Fase I MAG-Guajira
A1: PRESUPUESTO DETALLADO
A2: No | B2: No de Objetivo: Crear capacidad comunitaria para la adopción de comportamientos seguros, la reducción de la vulnerabilidad social al VIH y el empoderamiento de los grupos clave priorizados | C2: Área de prestación de servicios (APS) | D2: Macro-Categoría | E2: Tarea | F2: Sub -Tarea | G2: Descripción / Hipotesis | H2: Año 1 | I2: Año 2 | M2: Responsable de la ejecución | N2: Tipo de entidad ejecutora | O2: Categorías de costos | P2: Unidad de medida año 1 | Q2: Costo unitario año 1 (valor trimestre) | R2: Cantidad Trimestre 4 | S2: Importe total Trimestre 4 | T2: Cantidad total Año 1 | U2: Total Año 1 | V2: Unidad de medida año 2 | W2: Costo unitario año 2 (valor trimestre) | X2: Cantidad Trimestre 1 año 2 | Y2: Importe total Trimestre 1 año 2 | Z2: Cantidad Trimestre 2 año 2 | AA2: Importe total Trimestre 2 año 2 | AB2: Cantidad Trimestre 3 año 2 | AC2: Importe total Trimestre 3 año 2 | AD2: Cantidad Trimestre 4 año 2 | AE2: Importe total Trimestre 4 año 2 | AF2: Cantidad total Año 2 | AG2: Total Año 2 | AH2: COSTO TOTAL | AI2: Tope Presupuestal
C3: SDA | D3: Activity | H3: T4 | I3: T1 | J3: T2 | K3: T3 | L3: T4
A4: RECURSO HUMANO | AH4: =SUM(AH5:AH10) -> 0 | AI4: 234559238
A5: 7 | B5: 1 | C5: Refuerzo de la sociedad civil | D5: 1.1 Implementar estrategias de promoción de la demanda de asesoría y prueba voluntaria (APV) y de comunicación para el cambio de comportamiento (CCC) | E5: 1.1.5 Identificar y formar líderes pares de los grupos clave priorizados para que actúen como formadores e integren los equipos locales de promoción de la salud y prevención del VIH e ITS | F5: Costo recurso humano administración de la entidad ejecutora | G5: Contador | M5: Entidad Ejecutora | N5: ONG/OBC/Sector Académico | O5: Recursos Humanos | P5: Salario / Honorario | S5: =+R5*Q5 -> 0 | T5: =+R5 -> 0 | U5: =S5 -> 0 | V5: Salario / Honorario | Y5: =+W5*X5 -> 0 | AA5: =+Z5*W5 -> 0 | AC5: =+AB5*W5 -> 0 | AE5: =+AD5*W5 -> 0 | AF5: =+X5+Z5+AB5+AD5 -> 0 | AG5: =+Y5+AA5+AC5+AE5 -> 0 | AH5: =+U5+AG5 -> 0
A6: 7 | B6: 1 | G6: Apoyo a la Dirección o Representación Legal | M6: Entidad Ejecutora | N6: ONG/OBC/Sector Académico | O6: Recursos Humanos | P6: Salario / Honorario | S6: =+R6*Q6 -> 0 | T6: =+R6 -> 0 | U6: =S6 -> 0 | V6: Salario / Honorario | Y6: =+W6*X6 -> 0 | AA6: =+Z6*W6 -> 0 | AC6: =+AB6*W6 -> 0 | AE6: =+AD6*W6 -> 0 | AF6: =+X6+Z6+AB6+AD6 -> 0 | AG6: =+Y6+AA6+AC6+AE6 -> 0 | AH6: =+U6+AG6 -> 0
A7: 7 | B7: 1 | G7: Asistente de Información | M7: Entidad Ejecutora | N7: ONG/OBC/Sector Académico | O7: Recursos Humanos | P7: Salario / Honorario | S7: =+R7*Q7 -> 0 | T7: =+R7 -> 0 | U7: =S7 -> 0 | V7: Salario / Honorario | Y7: =+W7*X7 -> 0 | AA7: =+Z7*W7 -> 0 | AC7: =+AB7*W7 -> 0 | AE7: =+AD7*W7 -> 0 | AF7: =+X7+Z7+AB7+AD7 -> 0 | AG7: =+Y7+AA7+AC7+AE7 -> 0 | AH7: =+U7+AG7 -> 0
A8: 11 | B8: 1 | C8: Refuerzo de la sociedad civil | F8: Costo recurso humano programatico de la entidad ejecutora | G8: Coordinador | M8: Entidad Ejecutora | N8: ONG/OBC/Sector Académico | O8: Recursos Humanos | P8: Salario / Honorario | S8: =+R8*Q8 -> 0 | T8: =+R8 -> 0 | U8: =S8 -> 0 | V8: Salario / Honorario | Y8: =+W8*X8 -> 0 | AA8: =+Z8*W8 -> 0 | AC8: =+AB8*W8 -> 0 | AE8: =+AD8*W8 -> 0 | AF8: =+X8+Z8+AB8+AD8 -> 0 | AG8: =+Y8+AA8+AC8+AE8 -> 0 | AH8: =+U8+AG8 -> 0
A9: 11 | B9: 1 | C9: Refuerzo de la sociedad civil | G9: Profesionales en Salud Sexual y Reproductiva (SSR) | M9: Entidad Ejecutora | N9: ONG/OBC/Sector Académico | O9: Recursos Humanos | P9: Salario / Honorario | S9: =+R9*Q9 -> 0 | T9: =+R9 -> 0 | U9: =S9 -> 0 | V9: Salario / Honorario | Y9: =+W9*X9 -> 0 | AA9: =+Z9*W9 -> 0 | AC9: =+AB9*W9 -> 0 | AE9: =+AD9*W9 -> 0 | AF9: =+X9+Z9+AB9+AD9 -> 0 | AG9: =+Y9+AA9+AC9+AE9 -> 0 | AH9: =+U9+AG9 -> 0
A10: 11 | B10: 1 | C10: Refuerzo de la sociedad civil | G10: Técnicos en Salud Sexual y Reproductiva (SSR) | M10: Entidad Ejecutora | N10: ONG/OBC/Sector Académico | O10: Recursos Humanos | P10: Salario / Honorario | S10: =+R10*Q10 -> 0 | T10: =+R10 -> 0 | U10: =S10 -> 0 | V10: Salario / Honorario | Y10: =+W10*X10 -> 0 | AA10: =+Z10*W10 -> 0 | AC10: =+AB10*W10 -> 0 | AE10: =+AD10*W10 -> 0 | AF10: =+X10+Z10+AB10+AD10 -> 0 | AG10: =+Y10+AA10+AC10+AE10 -> 0 | AH10: =+U10+AG10 -> 0
A11: MONITOREO Y EVALUACION | AH11: =SUM(AH12:AH27) -> 0 | AI11: 70367776
A12: 13 | B12: 1 | C12: Refuerzo de la sociedad civil | D12: 1.1 Implementar estrategias de promoción de la demanda de asesoría y prueba voluntaria (APV) y de comunicación para el cambio de comportamiento (CCC) | E12: 1.1.5 Identificar y formar líderes pares de los grupos clave priorizados para que actúen como formadores e integren los equipos locales de promoción de la salud y prevención del VIH e ITS | F12: Este costo incluye: 1. Viaticos y desplazamientos a los municipios de influencia asignados. 2. Actividades de gestion municipal y departamental para la sostenibilidad de las iniciativas. 3. Actividades en los servicios comunitarios para el encuentro con las comunidades, generación de confianza con las poblaciones priorizadas, actividades de escucha, reducción del estigma y la discriminaciòn, entre otras (Ejm: chocolatadas, teatro o cine al parque, actividades de trueque, acciones sanatorias de apoyo en situaciòn de alta vulnerabilidad para estabilizar a las poblaciones, entre otras) | G12: Viaticos por municipio | M12: Entidad Ejecutora | N12: ONG/OBC/Sector Académico | O12: Monitoreo y evaluación | P12: Viatico | S12: =+SUM(S13:S18) -> 0 | T12: =+SUM(T13:T18) -> 0 | U12: =+SUM(U13:U18) -> 0 | V12: Viatico | X12: =+SUM(X13:X18) -> 0 | Y12: =+SUM(Y13:Y18) -> 0 | Z12: =+SUM(Z13:Z18) -> 0 | AA12: =+SUM(AA13:AA18) -> 0 | AB12: =+SUM(AB13:AB18) -> 0 | AC12: =+SUM(AC13:AC18) -> 0 | AD12: =+SUM(AD13:AD18) -> 0 | AE12: =+SUM(AE13:AE18) -> 0 | ... AG12: =+SUM(AG13:AG18) -> 0 | AH12: =+U12+AG12 -> 0
G13: Riohacha | S13: =+Q13*R13 -> 0 | T13: =+R13 -> 0 | U13: =+S13 -> 0 | Y13: =+$W13*X13 -> 0 | AA13: =+$W13*Z13 -> 0 | AC13: =+$W13*AB13 -> 0 | AE13: =+$W13*AD13 -> 0 | AF13: =+X13+Z13+AB13+AD13 -> 0 | AG13: =+Y13+AA13+AC13+AE13 -> 0
G14: Maicao | S14: =+Q14*R14 -> 0 | T14: =+R14 -> 0 | U14: =+S14 -> 0 | Y14: =+$W14*X14 -> 0 | AA14: =+$W14*Z14 -> 0 | AC14: =+$W14*AB14 -> 0 | AE14: =+$W14*AD14 -> 0 | AF14: =+X14+Z14+AB14+AD14 -> 0 | AG14: =+Y14+AA14+AC14+AE14 -> 0
G15: Uribia | S15: =+Q15*R15 -> 0 | T15: =+R15 -> 0 | U15: =+S15 -> 0 | Y15: =+$W15*X15 -> 0 | AA15: =+$W15*Z15 -> 0 | AC15: =+$W15*AB15 -> 0 | AE15: =+$W15*AD15 -> 0 | AF15: =+X15+Z15+AB15+AD15 -> 0 | AG15: =+Y15+AA15+AC15+AE15 -> 0
G16: Santa Marta | S16: =+Q16*R16 -> 0 | T16: =+R16 -> 0 | U16: =+S16 -> 0 | Y16: =+$W16*X16 -> 0 | AA16: =+$W16*Z16 -> 0 | AC16: =+$W16*AB16 -> 0 | AE16: =+$W16*AD16 -> 0 | AF16: =+X16+Z16+AB16+AD16 -> 0 | AG16: =+Y16+AA16+AC16+AE16 -> 0
G17: Cienaga | S17: =+Q17*R17 -> 0 | T17: =+R17 -> 0 | U17: =+S17 -> 0 | Y17: =+$W17*X17 -> 0 | AA17: =+$W17*Z17 -> 0 | AC17: =+$W17*AB17 -> 0 | AE17: =+$W17*AD17 -> 0 | AF17: =+X17+Z17+AB17+AD17 -> 0 | AG17: =+Y17+AA17+AC17+AE17 -> 0
G18: Zona Bananera | S18: =+Q18*R18 -> 0 | T18: =+R18 -> 0 | U18: =+S18 -> 0 | Y18: =+$W18*X18 -> 0 | AA18: =+$W18*Z18 -> 0 | AC18: =+$W18*AB18 -> 0 | AE18: =+$W18*AD18 -> 0 | AF18: =+X18+Z18+AB18+AD18 -> 0 | AG18: =+Y18+AA18+AC18+AE18 -> 0
A19: 13 | B19: 1 | C19: Refuerzo de la sociedad civil | G19: Desplazamientos por municipio | M19: Entidad Ejecutora | N19: ONG/OBC/Sector Académico | O19: Monitoreo y evaluación | P19: Desplazamiento | S19: =+SUM(S20:S25) -> 0 | T19: =+SUM(T20:T25) -> 0 | U19: =+SUM(U20:U25) -> 0 | V19: Desplazamiento | X19: =+SUM(X20:X25) -> 0 | Y19: =+SUM(Y20:Y25) -> 0 | Z19: =+SUM(Z20:Z25) -> 0 | AA19: =+SUM(AA20:AA25) -> 0 | AB19: =+SUM(AB20:AB25) -> 0 | AC19: =+SUM(AC20:AC25) -> 0 | AD19: =+SUM(AD20:AD25) -> 0 | AE19: =+SUM(AE20:AE25) -> 0 | ... AG19: =+SUM(AG20:AG25) -> 0 | AH19: =+U19+AG19 -> 0
G20: Riohacha | S20: =+Q20*R20 -> 0 | T20: =+R20 -> 0 | U20: =+S20 -> 0 | Y20: =+$W20*X20 -> 0 | AA20: =+$W20*Z20 -> 0 | AC20: =+$W20*AB20 -> 0 | AE20: =+$W20*AD20 -> 0 | AF20: =+X20+Z20+AB20+AD20 -> 0 | AG20: =+Y20+AA20+AC20+AE20 -> 0
G21: Maicao | S21: =+Q21*R21 -> 0 | T21: =+R21 -> 0 | U21: =+S21 -> 0 | Y21: =+$W21*X21 -> 0 | AA21: =+$W21*Z21 -> 0 | AC21: =+$W21*AB21 -> 0 | AE21: =+$W21*AD21 -> 0 | AF21: =+X21+Z21+AB21+AD21 -> 0 | AG21: =+Y21+AA21+AC21+AE21 -> 0
G22: Uribia | S22: =+Q22*R22 -> 0 | T22: =+R22 -> 0 | U22: =+S22 -> 0 | Y22: =+$W22*X22 -> 0 | AA22: =+$W22*Z22 -> 0 | AC22: =+$W22*AB22 -> 0 | AE22: =+$W22*AD22 -> 0 | AF22: =+X22+Z22+AB22+AD22 -> 0 | AG22: =+Y22+AA22+AC22+AE22 -> 0
G23: Santa Marta | S23: =+Q23*R23 -> 0 | T23: =+R23 -> 0 | U23: =+S23 -> 0 | Y23: =+$W23*X23 -> 0 | AA23: =+$W23*Z23 -> 0 | AC23: =+$W23*AB23 -> 0 | AE23: =+$W23*AD23 -> 0 | AF23: =+X23+Z23+AB23+AD23 -> 0 | AG23: =+Y23+AA23+AC23+AE23 -> 0
G24: Cienaga | S24: =+Q24*R24 -> 0 | T24: =+R24 -> 0 | U24: =+S24 -> 0 | Y24: =+$W24*X24 -> 0 | AA24: =+$W24*Z24 -> 0 | AC24: =+$W24*AB24 -> 0 | AE24: =+$W24*AD24 -> 0 | AF24: =+X24+Z24+AB24+AD24 -> 0 | AG24: =+Y24+AA24+AC24+AE24 -> 0
G25: Zona Bananera | S25: =+Q25*R25 -> 0 | T25: =+R25 -> 0 | U25: =+S25 -> 0 | Y25: =+$W25*X25 -> 0 | AA25: =+$W25*Z25 -> 0 | AC25: =+$W25*AB25 -> 0 | AE25: =+$W25*AD25 -> 0 | AF25: =+X25+Z25+AB25+AD25 -> 0 | AG25: =+Y25+AA25+AC25+AE25 -> 0
A26: 13 | B26: 1 | C26: Refuerzo de la sociedad civil | G26: Actividades de Gestión | M26: Entidad Ejecutora | N26: ONG/OBC/Sector Académico | O26: Monitoreo y evaluación | P26: Costo reunión | S26: =+R26*Q26 -> 0 | T26: =+R26 -> 0 | U26: =S26 -> 0 | V26: Costo reunión | Y26: =+W26*X26 -> 0 | AA26: =+Z26*W26 -> 0 | AC26: =+AB26*W26 -> 0 | AE26: =+AD26*W26 -> 0 | AF26: =+X26+Z26+AB26+AD26 -> 0 | AG26: =+Y26+AA26+AC26+AE26 -> 0 | AH26: =+U26+AG26 -> 0
A27: 13 | B27: 1 | C27: Refuerzo de la sociedad civil | G27: Actividades Servicios Comunitarios | M27: Entidad Ejecutora | N27: ONG/OBC/Sector Académico | O27: Monitoreo y evaluación | P27: Actividades | S27: =+R27*Q27 -> 0 | T27: =+R27 -> 0 | U27: =S27 -> 0 | V27: Actividades | Y27: =+W27*X27 -> 0 | AA27: =+Z27*W27 -> 0 | AC27: =+AB27*W27 -> 0 | AE27: =+AD27*W27 -> 0 | AF27: =+X27+Z27+AB27+AD27 -> 0 | AG27: =+Y27+AA27+AC27+AE27 -> 0 | AH27: =+U27+AG27 -> 0
A28: PLANIFICACION Y ADMINISTRACION | AH28: =SUM(AH29) -> 0 | AI28: 30157612
A29: 8 | B29: 1 | C29: Refuerzo de la sociedad civil | D29: 1.1 Implementar estrategias de promoción de la demanda de asesoría y prueba voluntaria (APV) y de comunicación para el cambio de comportamiento (CCC) | E29: 1.1.5 Identificar y formar líderes pares de los grupos clave priorizados para que actúen como formadores e integren los equipos locales de promoción de la salud y prevención del VIH e ITS | F29: Este costo incluye los Costos Administrativos (como, Arriendo, servicios públicos, Comunicaciones, impresiones, fotocopias, papelería, correos, gastos bancarios, seguros, mantenimiento y reparaciones, servicios generales, entre otros). | M29: Entidad Ejecutora | N29: ONG/OBC/Sector Académico | O29: Planificación y Administración | S29: =+R29*Q29 -> 0 | T29: =+R29 -> 0 | U29: =S29 -> 0 | Y29: =+W29*X29 -> 0 | AA29: =+Z29*W29 -> 0 | AC29: =+AB29*W29 -> 0 | AE29: =+AD29*W29 -> 0 | AF29: =+X29+Z29+AB29+AD29 -> 0 | AG29: =+Y29+AA29+AC29+AE29 -> 0 | AH29: =+U29+AG29 -> 0
A30: TOTAL RUBROS DE FUNCIONAMIENTO | AH30: =+AH4+AH11+AH28 -> 0 | AI30: =+AI4+AI11+AI28 -> 335084626
AH31: =SUM(AH7:AH29) -> 0
A32: DESTINACION ESPECIFICA
A33: 6 | B33: 1 | C33: CCC (Comunicación para Cambio de Comportamiento)- Medios de comunicación | D33: 1.1 Implementar estrategias de promoción de la demanda de asesoría y prueba voluntaria (APV) y de comunicación para el cambio de comportamiento (CCC) | E33: 1.1.4 Implementar acciones de CCC y de promoción de demanda de APV en medios alternativos y cara-a-cara (outreach) para transformar conductas sexuales de riesgo, promover el uso consistente y adecuado del condón y divulgar servicios y rutas de derechos a los grupos clave | F33: Este costo esta representado por brigadas de acercamiento a los grupos clave en sus entornos naturales | G33: Costo por brigada. El costo asignado por brigada es de $15,355. Incluye alimentación y transporte | M33: Entidad Ejecutora | N33: ONG/OBC/Sector Académico | O33: Capacitación | P33: costo por brigada | Q33: =15355 -> 15355 | R33: =965*0.2 -> 193 | S33: =+R33*Q33 -> 2963515 | T33: =+R33 -> 193 | U33: =S33 -> 2963515 | V33: costo por brigada | W33: =+Q33 -> 15355 | X33: 193 | Y33: =+W33*X33 -> 2963515 | Z33: 193 | AA33: =+Z33*W33 -> 2963515 | AB33: =+Z33 -> 193 | AC33: =+AB33*W33 -> 2963515 | AD33: =+AB33 -> 193 | AE33: =+AD33*W33 -> 2963515 | AF33: =+X33+Z33+AB33+AD33 -> 772 | AG33: =+Y33+AA33+AC33+AE33 -> 11854060 | AH33: =+U33+AG33 -> 14817575
A34: 34 | B34: 1 | C34: Refuerzo de las capacidades institucionales | D34: 1.3 Crear y fortalecer servicios comunitarios y/o redes comunitarias tipo A para la prevención del VIH/Sida /ITS, la promoción y referencia a APV, la educación en derechos y el empoderamiento de los grupos clave | E34: 1.3.5 Diseñar e implementar un plan de mejoramiento de capacidades locativas, de dotación y del recurso humano en los servicios comunitarios tipo A para la implementación efectiva de estrategias de CCC, promoción de la demanda de APV, educación en derechos, educación de pares | F34: Desarrollo de asistencia técnica a los servicios comunitarios tipo A asignados en temas identificados en la evaluación de necesidades | G34: Costo por servicio comunitario de 24 horas (valor hora $36.000) | M34: Entidad Ejecutora | N34: ONG/OBC/Sector Académico | O34: Asistencia técnica y gerencial | P34: Costo por hora asistencia tecnica | S34: =+R34*Q34 -> 0 | T34: =+R34 -> 0 | U34: =S34 -> 0 | V34: Costo por hora asistencia tecnica | W34: =36000*24 -> 864000 | X34: 4 | Y34: =+W34*X34 -> 3456000 | Z34: 4 | AA34: =+Z34*W34 -> 3456000 | AC34: =+AB34*W34 -> 0 | AD34: =+AB34 -> 0 | AE34: =+AD34*W34 -> 0 | AF34: =+X34+Z34+AB34+AD34 -> 8 | AG34: =+Y34+AA34+AC34+AE34 -> 6912000 | AH34: =+U34+AG34 -> 6912000
A35: 35 | B35: 1 | C35: Refuerzo de las capacidades institucionales | D35: 1.3 Crear y fortalecer servicios comunitarios y/o redes comunitarias tipo A para la prevención del VIH/Sida /ITS, la promoción y referencia a APV, la educación en derechos y el empoderamiento de los grupos clave | E35: 1.3.5 Diseñar e implementar un plan de mejoramiento de capacidades locativas, de dotación y del recurso humano en los servicios comunitarios tipo A para la implementación efectiva de estrategias de CCC, promoción de la demanda de APV, educación en derechos, educación de pares | F35: Desarrollo de asistencia técnica a los servicios comunitarios tipo A asignados en temas identificados en la evaluación de necesidades | G35: Costo por servicio comunitario de 12 horas (valor hora $36.000) | M35: Entidad Ejecutora | N35: ONG/OBC/Sector Académico | O35: Asistencia técnica y gerencial | P35: Costo por hora asistencia tecnica | S35: =+R35*Q35 -> 0 | T35: =+R35 -> 0 | U35: =S35 -> 0 | V35: Costo por hora asistencia tecnica | W35: =36000*12 -> 432000 | Y35: =+W35*X35 -> 0 | Z35: =+X35 -> 0 | AA35: =+Z35*W35 -> 0 | AB35: 8 | AC35: =+AB35*W35 -> 3456000 | AD35: =+AB35 -> 8 | AE35: =+AD35*W35 -> 3456000 | AF35: =+X35+Z35+AB35+AD35 -> 16 | AG35: =+Y35+AA35+AC35+AE35 -> 6912000 | AH35: =+U35+AG35 -> 6912000
A36: 43 | B36: 1 | C36: Reducción del estigma en todas las circunstancias | D36: 1.4 Implementar estrategias de movilización social para la reducción del estigma y la discriminación, la incidencia política y el agenciamiento social | E36: 1.4.3 Implementar estrategias de comunicación y movilización social del nivel nacional y local (radio, medios alternativos y cara- a-cara) para la sensibilización de las comunidades para la reducción de estigma y discriminación | F36: Desarrollo de campañas locales en medios alternativos desarrolladas en eventos comunitarios para la movilización social en torno a la prevención del VIH y la promoción de la solidaridad frente a los grupos clave | G36: Este costo incluye campañas locales en medios alternativos | M36: Entidad Ejecutora | N36: ONG/OBC/Sector Académico | O36: Material de comunicación | P36: Costo por campaña | S36: =+R36*Q36 -> 0 | T36: =+R36 -> 0 | U36: =S36 -> 0 | V36: Costo por campaña | W36: 5000000 | X36: =+R36 -> 0 | Y36: =+W36*X36 -> 0 | Z36: 1 | AA36: =+Z36*W36 -> 5000000 | AC36: =+AB36*W36 -> 0 | AD36: 1 | AE36: =+AD36*W36 -> 5000000 | AF36: =+X36+Z36+AB36+AD36 -> 2 | AG36: =+Y36+AA36+AC36+AE36 -> 10000000 | AH36: =+U36+AG36 -> 10000000
A37: 46 | B37: 1 | C37: Refuerzo de la sociedad civil | D37: 1.4 Implementar estrategias de movilización social para la reducción del estigma y la discriminación, la incidencia política y el agenciamiento social | E37: 1.4.4 Implementar acciones de fortalecimiento de la capacidad de ciudadana y agenciamiento social de los grupos clave, a través de educación en derechos, empoderamiento y apoyo social | F37: Desarrollo de encuentros quincenales en los servicios comunitarios tipo A para educar en derechos, participación y ciudadanía a los grupos clave. | G37: Este costo incluye un apoyo al encuentro para agua, café y apoyo alquiler salón de reunión | M37: Entidad Ejecutora | N37: ONG/OBC/Sector Académico | O37: Capacitación | P37: Costo por encuentro | S37: =+R37*Q37 -> 0 | T37: =+R37 -> 0 | U37: =S37 -> 0 | V37: Costo por encuentro | W37: 100000 | X37: 9 | Y37: =+W37*X37 -> 900000 | Z37: =+X37 -> 9 | AA37: =+Z37*W37 -> 900000 | AB37: =+Z37 -> 9 | AC37: =+AB37*W37 -> 900000 | AD37: 10 | AE37: =+AD37*W37 -> 1000000 | AF37: =+X37+Z37+AB37+AD37 -> 37 | AG37: =+Y37+AA37+AC37+AE37 -> 3700000 | AH37: =+U37+AG37 -> 3700000
A38: 12 | B38: 1 | C38: Refuerzo de la sociedad civil | D38: 1.1 Implementar estrategias de promoción de la demanda de asesoría y prueba voluntaria (APV) y de comunicación para el cambio de comportamiento (CCC) | E38: 1.1.5 Identificar y formar líderes pares de los grupos clave priorizados para que actúen como formadores e integren los equipos locales de promoción de la salud y prevención del VIH e ITS | F38: Costos administrativos, de operación y programaticos de la entidade ejecutora para el trabajo con servicios comunitarios para la identificación, selección, capacitación y seguimiento de lideres pares. Costos de prevención y promoción de APV, CCC, Uso de Condón, Reducción de Estigma y discriminación y seguimiento a tratamientos | G38: Costo Líderes pares de las Entidades Ejecutoras para los temas de prevención, diagnostico y tratamiento | M38: Entidad Ejecutora | N38: ONG/OBC/Sector Académico | O38: Monitoreo y evaluación | P38: Costo Incentivo Lideres Pares | Q38: =150000*3 -> 450000 | R38: 8 | S38: =+R38*Q38 -> 3600000 | T38: =+R38 -> 8 | U38: =S38 -> 3600000 | V38: =+P38 -> Costo Incentivo Lideres Pares | W38: =154500*3 -> 463500 | X38: =+R38 -> 8 | Y38: =+W38*X38 -> 3708000 | Z38: =8+35 -> 43 | AA38: =+Z38*W38 -> 19930500 | AB38: =+Z38 -> 43 | AC38: =+AB38*W38 -> 19930500 | AD38: =+AB38 -> 43 | AE38: =+AD38*W38 -> 19930500 | AF38: =+X38+Z38+AB38+AD38 -> 137 | AG38: =+Y38+AA38+AC38+AE38 -> 63499500 | AH38: =+U38+AG38 -> 67099500
A39: TOTAL DESTINACION ESPECIFICA | AH39: =SUM(AH33:AH38) -> 109441075 | AI39: =+AH39 -> 109441075
A40: TOTAL PRESUPUESTO | AI40: =+AI30+AI39 -> 444525701

Sheet Summary Sucre
A1: PRESUPUESTO ENTIDADES EJECUTORAS
A2: SUCRE
A4: Nombre Entidad Ejecutora:
A6: Detalle | B6: Presupuesto Total | C6: Tope Presupuestal
A7: Recurso Humano | B7: =+'[1]Fase I Valle del Cauca'!AH4 -> 0 | C7: =+'Fase I Sucre'!AI4 -> 236285113
A8: Monitoreo y Evaluación | B8: =+'[1]Fase I Valle del Cauca'!AH11 -> 0 | C8: =+'Fase I Sucre'!AI11 -> 70885532
A9: Planeación y Administración | B9: =+'[1]Fase I Valle del Cauca'!AH16 -> 0 | C9: =+'Fase I Sucre'!AI24 -> 30379517
A10: Total Rubros de Funcionamiento | B10: =SUM(B7:B9) -> 0 | C10: =SUM(C7:C9) -> 337550162
A12: Destinación Específica | B12: =+'Fase I Sucre'!AH35 -> 108834120 | C12: =+'Fase I Sucre'!AI35 -> 108834120
A13: Total Destinación Específica | B13: =+B12 -> 108834120 | C13: =+C12 -> 108834120
A14: PRESUPUESTO TOTAL | B14: =+B10+B13 -> 108834120 | C14: =+C10+C13 -> 446384282
A19: XXXXXX
A20: REPRESENTANTE LEGAL

Sheet Fase I Sucre
A1: PRESUPUESTO DETALLADO
A2: No | B2: No de Objetivo: Crear capacidad comunitaria para la adopción de comportamientos seguros, la reducción de la vulnerabilidad social al VIH y el empoderamiento de los grupos clave priorizados | C2: Área de prestación de servicios (APS) | D2: Macro-Categoría | E2: Tarea | F2: Sub -Tarea | G2: Descripción / Hipotesis | H2: Año 1 | I2: Año 2 | M2: Responsable de la ejecución | N2: Tipo de entidad ejecutora | O2: Categorías de costos | P2: Unidad de medida año 1 | Q2: Costo unitario año 1 (valor trimestre) | R2: Cantidad Trimestre 4 | S2: Importe total Trimestre 4 | T2: Cantidad total Año 1 | U2: Total Año 1 | V2: Unidad de medida año 2 | W2: Costo unitario año 2 (valor trimestre) | X2: Cantidad Trimestre 1 año 2 | Y2: Importe total Trimestre 1 año 2 | Z2: Cantidad Trimestre 2 año 2 | AA2: Importe total Trimestre 2 año 2 | AB2: Cantidad Trimestre 3 año 2 | AC2: Importe total Trimestre 3 año 2 | AD2: Cantidad Trimestre 4 año 2 | AE2: Importe total Trimestre 4 año 2 | AF2: Cantidad total Año 2 | AG2: Total Año 2 | AH2: COSTO TOTAL | AI2: Tope Presupuestal
C3: SDA | D3: Activity | H3: T4 | I3: T1 | J3: T2 | K3: T3 | L3: T4
A4: RECURSO HUMANO | AH4: =SUM(AH5:AH10) -> 0 | AI4: 236285113
A5: 7 | B5: 1 | C5: Refuerzo de la sociedad civil | D5: 1.1 Implementar estrategias de promoción de la demanda de asesoría y prueba voluntaria (APV) y de comunicación para el cambio de comportamiento (CCC) | E5: 1.1.5 Identificar y formar líderes pares de los grupos clave priorizados para que actúen como formadores e integren los equipos locales de promoción de la salud y prevención del VIH e ITS | F5: Costo recurso humano administración de la entidad ejecutora | G5: Contador | M5: Entidad Ejecutora | N5: ONG/OBC/Sector Académico | O5: Recursos Humanos | P5: Salario / Honorario | S5: =+R5*Q5 -> 0 | T5: =+R5 -> 0 | U5: =S5 -> 0 | V5: Salario / Honorario | Y5: =+W5*X5 -> 0 | AA5: =+Z5*W5 -> 0 | AC5: =+AB5*W5 -> 0 | AE5: =+AD5*W5 -> 0 | AF5: =+X5+Z5+AB5+AD5 -> 0 | AG5: =+Y5+AA5+AC5+AE5 -> 0 | AH5: =+U5+AG5 -> 0
A6: 7 | B6: 1 | G6: Apoyo a la Dirección o Representación Legal | M6: Entidad Ejecutora | N6: ONG/OBC/Sector Académico | O6: Recursos Humanos | P6: Salario / Honorario | S6: =+R6*Q6 -> 0 | T6: =+R6 -> 0 | U6: =S6 -> 0 | V6: Salario / Honorario | Y6: =+W6*X6 -> 0 | AA6: =+Z6*W6 -> 0 | AC6: =+AB6*W6 -> 0 | AE6: =+AD6*W6 -> 0 | AF6: =+X6+Z6+AB6+AD6 -> 0 | AG6: =+Y6+AA6+AC6+AE6 -> 0 | AH6: =+U6+AG6 -> 0
A7: 7 | B7: 1 | G7: Asistente de Información | M7: Entidad Ejecutora | N7: ONG/OBC/Sector Académico | O7: Recursos Humanos | P7: Salario / Honorario | S7: =+R7*Q7 -> 0 | T7: =+R7 -> 0 | U7: =S7 -> 0 | V7: Salario / Honorario | Y7: =+W7*X7 -> 0 | AA7: =+Z7*W7 -> 0 | AC7: =+AB7*W7 -> 0 | AE7: =+AD7*W7 -> 0 | AF7: =+X7+Z7+AB7+AD7 -> 0 | AG7: =+Y7+AA7+AC7+AE7 -> 0 | AH7: =+U7+AG7 -> 0
A8: 11 | B8: 1 | C8: Refuerzo de la sociedad civil | F8: Costo recurso humano programatico de la entidad ejecutora | G8: Coordinador | M8: Entidad Ejecutora | N8: ONG/OBC/Sector Académico | O8: Recursos Humanos | P8: Salario / Honorario | S8: =+R8*Q8 -> 0 | T8: =+R8 -> 0 | U8: =S8 -> 0 | V8: Salario / Honorario | Y8: =+W8*X8 -> 0 | AA8: =+Z8*W8 -> 0 | AC8: =+AB8*W8 -> 0 | AE8: =+AD8*W8 -> 0 | AF8: =+X8+Z8+AB8+AD8 -> 0 | AG8: =+Y8+AA8+AC8+AE8 -> 0 | AH8: =+U8+AG8 -> 0
A9: 11 | B9: 1 | C9: Refuerzo de la sociedad civil | G9: Profesionales en Salud Sexual y Reproductiva (SSR) | M9: Entidad Ejecutora | N9: ONG/OBC/Sector Académico | O9: Recursos Humanos | P9: Salario / Honorario | S9: =+R9*Q9 -> 0 | T9: =+R9 -> 0 | U9: =S9 -> 0 | V9: Salario / Honorario | Y9: =+W9*X9 -> 0 | AA9: =+Z9*W9 -> 0 | AC9: =+AB9*W9 -> 0 | AE9: =+AD9*W9 -> 0 | AF9: =+X9+Z9+AB9+AD9 -> 0 | AG9: =+Y9+AA9+AC9+AE9 -> 0 | AH9: =+U9+AG9 -> 0
A10: 11 | B10: 1 | C10: Refuerzo de la sociedad civil | G10: Técnicos en Salud Sexual y Reproductiva (SSR) | M10: Entidad Ejecutora | N10: ONG/OBC/Sector Académico | O10: Recursos Humanos | P10: Salario / Honorario | S10: =+R10*Q10 -> 0 | T10: =+R10 -> 0 | U10: =S10 -> 0 | V10: Salario / Honorario | Y10: =+W10*X10 -> 0 | AA10: =+Z10*W10 -> 0 | AC10: =+AB10*W10 -> 0 | AE10: =+AD10*W10 -> 0 | AF10: =+X10+Z10+AB10+AD10 -> 0 | AG10: =+Y10+AA10+AC10+AE10 -> 0 | AH10: =+U10+AG10 -> 0
A11: MONITOREO Y EVALUACION | AH11: =SUM(AH12:AH23) -> 0 | AI11: 70885532
A12: 13 | B12: 1 | C12: Refuerzo de la sociedad civil | D12: 1.1 Implementar estrategias de promoción de la demanda de asesoría y prueba voluntaria (APV) y de comunicación para el cambio de comportamiento (CCC) | E12: 1.1.5 Identificar y formar líderes pares de los grupos clave priorizados para que actúen como formadores e integren los equipos locales de promoción de la salud y prevención del VIH e ITS | F12: Este costo incluye: 1. Viaticos y desplazamientos a los municipios de influencia asignados. 2. Actividades de gestion municipal y departamental para la sostenibilidad de las iniciativas. 3. Actividades en los servicios comunitarios para el encuentro con las comunidades, generación de confianza con las poblaciones priorizadas, actividades de escucha, reducción del estigma y la discriminaciòn, entre otras (Ejm: chocolatadas, teatro o cine al parque, actividades de trueque, acciones sanatorias de apoyo en situaciòn de alta vulnerabilidad para estabilizar a las poblaciones, entre otras) | G12: Viaticos por municipio | M12: Entidad Ejecutora | N12: ONG/OBC/Sector Académico | O12: Monitoreo y evaluación | P12: Viatico | R12: =+SUM(R13:R16) -> 0 | S12: =+SUM(S13:S16) -> 0 | T12: =+SUM(T13:T16) -> 0 | U12: =+SUM(U13:U16) -> 0 | V12: Viatico | X12: =+SUM(X13:X16) -> 0 | Y12: =+SUM(Y13:Y16) -> 0 | Z12: =+SUM(Z13:Z16) -> 0 | AA12: =+SUM(AA13:AA16) -> 0 | AB12: =+SUM(AB13:AB16) -> 0 | AC12: =+SUM(AC13:AC16) -> 0 | AD12: =+SUM(AD13:AD16) -> 0 | AE12: =+SUM(AE13:AE16) -> 0 | ... AG12: =+SUM(AG13:AG16) -> 0 | AH12: =+U12+AG12 -> 0
G13: Sincelejo | S13: =+R13*Q13 -> 0 | T13: =+R13 -> 0 | U13: =S13 -> 0 | Y13: =+$W13*X13 -> 0 | AA13: =+$W13*Z13 -> 0 | AC13: =+$W13*AB13 -> 0 | AE13: =+$W13*AD13 -> 0 | AF13: =+X13+Z13+AB13+AD13 -> 0 | AG13: =+Y13+AA13+AC13+AE13 -> 0
G14: Corozal | S14: =+R14*Q14 -> 0 | T14: =+R14 -> 0 | U14: =S14 -> 0 | Y14: =+$W14*X14 -> 0 | AA14: =+$W14*Z14 -> 0 | AC14: =+$W14*AB14 -> 0 | AE14: =+$W14*AD14 -> 0 | AF14: =+X14+Z14+AB14+AD14 -> 0 | AG14: =+Y14+AA14+AC14+AE14 -> 0
G15: San Marcos | S15: =+R15*Q15 -> 0 | T15: =+R15 -> 0 | U15: =S15 -> 0 | Y15: =+$W15*X15 -> 0 | AA15: =+$W15*Z15 -> 0 | AC15: =+$W15*AB15 -> 0 | AE15: =+$W15*AD15 -> 0 | AF15: =+X15+Z15+AB15+AD15 -> 0 | AG15: =+Y15+AA15+AC15+AE15 -> 0
G16: San Onofre | S16: =+R16*Q16 -> 0 | T16: =+R16 -> 0 | U16: =S16 -> 0 | Y16: =+$W16*X16 -> 0 | AA16: =+$W16*Z16 -> 0 | AC16: =+$W16*AB16 -> 0 | AE16: =+$W16*AD16 -> 0 | AF16: =+X16+Z16+AB16+AD16 -> 0 | AG16: =+Y16+AA16+AC16+AE16 -> 0
A17: 13 | B17: 1 | C17: Refuerzo de la sociedad civil | G17: Desplazamientos por municipio | M17: Entidad Ejecutora | N17: ONG/OBC/Sector Académico | O17: Monitoreo y evaluación | P17: Desplazamiento | R17: =+SUM(R18:R21) -> 0 | S17: =+SUM(S18:S21) -> 0 | T17: =+SUM(T18:T21) -> 0 | U17: =+SUM(U18:U21) -> 0 | V17: Desplazamiento | X17: =+SUM(X18:X21) -> 0 | Y17: =+SUM(Y18:Y21) -> 0 | Z17: =+SUM(Z18:Z21) -> 0 | AA17: =+SUM(AA18:AA21) -> 0 | AB17: =+SUM(AB18:AB21) -> 0 | AC17: =+SUM(AC18:AC21) -> 0 | AD17: =+SUM(AD18:AD21) -> 0 | AE17: =+SUM(AE18:AE21) -> 0 | ... AG17: =+SUM(AG18:AG21) -> 0 | AH17: =+U17+AG17 -> 0
G18: Sincelejo | S18: =+R18*Q18 -> 0 | T18: =+R18 -> 0 | U18: =S18 -> 0 | Y18: =+$W18*X18 -> 0 | AA18: =+$W18*Z18 -> 0 | AC18: =+$W18*AB18 -> 0 | AE18: =+$W18*AD18 -> 0 | AF18: =+X18+Z18+AB18+AD18 -> 0 | AG18: =+Y18+AA18+AC18+AE18 -> 0
G19: Corozal | S19: =+R19*Q19 -> 0 | T19: =+R19 -> 0 | U19: =S19 -> 0 | Y19: =+$W19*X19 -> 0 | AA19: =+$W19*Z19 -> 0 | AC19: =+$W19*AB19 -> 0 | AE19: =+$W19*AD19 -> 0 | AF19: =+X19+Z19+AB19+AD19 -> 0 | AG19: =+Y19+AA19+AC19+AE19 -> 0
G20: San Marcos | S20: =+R20*Q20 -> 0 | T20: =+R20 -> 0 | U20: =S20 -> 0 | Y20: =+$W20*X20 -> 0 | AA20: =+$W20*Z20 -> 0 | AC20: =+$W20*AB20 -> 0 | AE20: =+$W20*AD20 -> 0 | AF20: =+X20+Z20+AB20+AD20 -> 0 | AG20: =+Y20+AA20+AC20+AE20 -> 0
G21: San Onofre | S21: =+R21*Q21 -> 0 | T21: =+R21 -> 0 | U21: =S21 -> 0 | Y21: =+$W21*X21 -> 0 | AA21: =+$W21*Z21 -> 0 | AC21: =+$W21*AB21 -> 0 | AE21: =+$W21*AD21 -> 0 | AG21: =+Y21+AA21+AC21+AE21 -> 0
A22: 13 | B22: 1 | C22: Refuerzo de la sociedad civil | G22: Actividades de Gestión | M22: Entidad Ejecutora | N22: ONG/OBC/Sector Académico | O22: Monitoreo y evaluación | P22: Costo reunión | S22: =+R22*Q22 -> 0 | T22: =+R22 -> 0 | U22: =S22 -> 0 | V22: Costo reunión | Y22: =+W22*X22 -> 0 | AA22: =+Z22*W22 -> 0 | AC22: =+AB22*W22 -> 0 | AE22: =+AD22*W22 -> 0 | AF22: =+X22+Z22+AB22+AD22 -> 0 | AG22: =+Y22+AA22+AC22+AE22 -> 0 | AH22: =+U22+AG22 -> 0
A23: 13 | B23: 1 | C23: Refuerzo de la sociedad civil | G23: Actividades Servicios Comunitarios | M23: Entidad Ejecutora | N23: ONG/OBC/Sector Académico | O23: Monitoreo y evaluación | P23: Actividades | S23: =+R23*Q23 -> 0 | T23: =+R23 -> 0 | U23: =S23 -> 0 | V23: Actividades | Y23: =+W23*X23 -> 0 | AA23: =+Z23*W23 -> 0 | AC23: =+AB23*W23 -> 0 | AE23: =+AD23*W23 -> 0 | AF23: =+X23+Z23+AB23+AD23 -> 0 | AG23: =+Y23+AA23+AC23+AE23 -> 0 | AH23: =+U23+AG23 -> 0
A24: PLANIFICACION Y ADMINISTRACION | AH24: =SUM(AH25) -> 0 | AI24: 30379517
A25: 8 | B25: 1 | C25: Refuerzo de la sociedad civil | D25: 1.1 Implementar estrategias de promoción de la demanda de asesoría y prueba voluntaria (APV) y de comunicación para el cambio de comportamiento (CCC) | E25: 1.1.5 Identificar y formar líderes pares de los grupos clave priorizados para que actúen como formadores e integren los equipos locales de promoción de la salud y prevención del VIH e ITS | F25: Este costo incluye los Costos Administrativos (como, Arriendo, servicios públicos, Comunicaciones, impresiones, fotocopias, papelería, correos, gastos bancarios, seguros, mantenimiento y reparaciones, servicios generales, entre otros). | M25: Entidad Ejecutora | N25: ONG/OBC/Sector Académico | O25: Planificación y Administración | S25: =+R25*Q25 -> 0 | T25: =+R25 -> 0 | U25: =S25 -> 0 | Y25: =+W25*X25 -> 0 | AA25: =+Z25*W25 -> 0 | AC25: =+AB25*W25 -> 0 | AE25: =+AD25*W25 -> 0 | AF25: =+X25+Z25+AB25+AD25 -> 0 | AG25: =+Y25+AA25+AC25+AE25 -> 0 | AH25: =+U25+AG25 -> 0
A26: TOTAL RUBROS DE FUNCIONAMIENTO | AH26: =+AH4+AH11+AH24 -> 0 | AI26: =+AI4+AI11+AI24 -> 337550162
AH27: =SUM(AH7:AH25) -> 0
A28: DESTINACION ESPECIFICA
A29: 6 | B29: 1 | C29: CCC (Comunicación para Cambio de Comportamiento)- Medios de comunicación | D29: 1.1 Implementar estrategias de promoción de la demanda de asesoría y prueba voluntaria (APV) y de comunicación para el cambio de comportamiento (CCC) | E29: 1.1.4 Implementar acciones de CCC y de promoción de demanda de APV en medios alternativos y cara-a-cara (outreach) para transformar conductas sexuales de riesgo, promover el uso consistente y adecuado del condón y divulgar servicios y rutas de derechos a los grupos clave | F29: Este costo esta representado por brigadas de acercamiento a los grupos clave en sus entornos naturales | G29: Costo por brigada. El costo asignado por brigada es de $15,355. Incluye alimentación y transporte | M29: Entidad Ejecutora | N29: ONG/OBC/Sector Académico | O29: Capacitación | P29: costo por brigada | Q29: =15355 -> 15355 | R29: 209 | S29: =+R29*Q29 -> 3209195 | T29: =+R29 -> 209 | U29: =S29 -> 3209195 | V29: costo por brigada | W29: =+Q29 -> 15355 | X29: 209 | Y29: =+W29*X29 -> 3209195 | Z29: 209 | AA29: =+Z29*W29 -> 3209195 | AB29: =+Z29 -> 209 | AC29: =+AB29*W29 -> 3209195 | AD29: 208 | AE29: =+AD29*W29 -> 3193840 | AF29: =+X29+Z29+AB29+AD29 -> 835 | AG29: =+Y29+AA29+AC29+AE29 -> 12821425 | AH29: =+U29+AG29 -> 16030620
A30: 34 | B30: 1 | C30: Refuerzo de las capacidades institucionales | D30: 1.3 Crear y fortalecer servicios comunitarios y/o redes comunitarias tipo A para la prevención del VIH/Sida /ITS, la promoción y referencia a APV, la educación en derechos y el empoderamiento de los grupos clave | E30: 1.3.5 Diseñar e implementar un plan de mejoramiento de capacidades locativas, de dotación y del recurso humano en los servicios comunitarios tipo A para la implementación efectiva de estrategias de CCC, promoción de la demanda de APV, educación en derechos, educación de pares | F30: Desarrollo de asistencia técnica a los servicios comunitarios tipo A asignados en temas identificados en la evaluación de necesidades | G30: Costo por servicio comunitario de 24 horas (valor hora $36.000) | M30: Entidad Ejecutora | N30: ONG/OBC/Sector Académico | O30: Asistencia técnica y gerencial | P30: Costo por hora asistencia tecnica | S30: =+R30*Q30 -> 0 | T30: =+R30 -> 0 | U30: =S30 -> 0 | V30: Costo por hora asistencia tecnica | W30: =36000*24 -> 864000 | X30: 4 | Y30: =+W30*X30 -> 3456000 | Z30: 3 | AA30: =+Z30*W30 -> 2592000 | AC30: =+AB30*W30 -> 0 | AD30: =+AB30 -> 0 | AE30: =+AD30*W30 -> 0 | AF30: =+X30+Z30+AB30+AD30 -> 7 | AG30: =+Y30+AA30+AC30+AE30 -> 6048000 | AH30: =+U30+AG30 -> 6048000
A31: 35 | B31: 1 | C31: Refuerzo de las capacidades institucionales | D31: 1.3 Crear y fortalecer servicios comunitarios y/o redes comunitarias tipo A para la prevención del VIH/Sida /ITS, la promoción y referencia a APV, la educación en derechos y el empoderamiento de los grupos clave | E31: 1.3.5 Diseñar e implementar un plan de mejoramiento de capacidades locativas, de dotación y del recurso humano en los servicios comunitarios tipo A para la implementación efectiva de estrategias de CCC, promoción de la demanda de APV, educación en derechos, educación de pares | F31: Desarrollo de asistencia técnica a los servicios comunitarios tipo A asignados en temas identificados en la evaluación de necesidades | G31: Costo por servicio comunitario de 12 horas (valor hora $36.000) | M31: Entidad Ejecutora | N31: ONG/OBC/Sector Académico | O31: Asistencia técnica y gerencial | P31: Costo por hora asistencia tecnica | S31: =+R31*Q31 -> 0 | T31: =+R31 -> 0 | U31: =S31 -> 0 | V31: Costo por hora asistencia tecnica | W31: =36000*12 -> 432000 | Y31: =+W31*X31 -> 0 | Z31: =+X31 -> 0 | AA31: =+Z31*W31 -> 0 | AB31: 7 | AC31: =+AB31*W31 -> 3024000 | AD31: =+AB31 -> 7 | AE31: =+AD31*W31 -> 3024000 | AF31: =+X31+Z31+AB31+AD31 -> 14 | AG31: =+Y31+AA31+AC31+AE31 -> 6048000 | AH31: =+U31+AG31 -> 6048000
A32: 43 | B32: 1 | C32: Reducción del estigma en todas las circunstancias | D32: 1.4 Implementar estrategias de movilización social para la reducción del estigma y la discriminación, la incidencia política y el agenciamiento social | E32: 1.4.3 Implementar estrategias de comunicación y movilización social del nivel nacional y local (radio, medios alternativos y cara- a-cara) para la sensibilización de las comunidades para la reducción de estigma y discriminación | F32: Desarrollo de campañas locales en medios alternativos desarrolladas en eventos comunitarios para la movilización social en torno a la prevención del VIH y la promoción de la solidaridad frente a los grupos clave | G32: Este costo incluye campañas locales en medios alternativos | M32: Entidad Ejecutora | N32: ONG/OBC/Sector Académico | O32: Material de comunicación | P32: Costo por campaña | S32: =+R32*Q32 -> 0 | T32: =+R32 -> 0 | U32: =S32 -> 0 | V32: Costo por campaña | W32: 5000000 | X32: =+R32 -> 0 | Y32: =+W32*X32 -> 0 | Z32: 1 | AA32: =+Z32*W32 -> 5000000 | AC32: =+AB32*W32 -> 0 | AD32: 0 | AE32: =+AD32*W32 -> 0 | AF32: =+X32+Z32+AB32+AD32 -> 1 | AG32: =+Y32+AA32+AC32+AE32 -> 5000000 | AH32: =+U32+AG32 -> 5000000
A33: 46 | B33: 1 | C33: Refuerzo de la sociedad civil | D33: 1.4 Implementar estrategias de movilización social para la reducción del estigma y la discriminación, la incidencia política y el agenciamiento social | E33: 1.4.4 Implementar acciones de fortalecimiento de la capacidad de ciudadana y agenciamiento social de los grupos clave, a través de educación en derechos, empoderamiento y apoyo social | F33: Desarrollo de encuentros quincenales en los servicios comunitarios tipo A para educar en derechos, participación y ciudadanía a los grupos clave. | G33: Este costo incluye un apoyo al encuentro para agua, café y apoyo alquiler salón de reunión | M33: Entidad Ejecutora | N33: ONG/OBC/Sector Académico | O33: Capacitación | P33: Costo por encuentro | S33: =+R33*Q33 -> 0 | T33: =+R33 -> 0 | U33: =S33 -> 0 | V33: Costo por encuentro | W33: 100000 | X33: 10 | Y33: =+W33*X33 -> 1000000 | Z33: =+X33 -> 10 | AA33: =+Z33*W33 -> 1000000 | AB33: =+Z33 -> 10 | AC33: =+AB33*W33 -> 1000000 | AD33: 10 | AE33: =+AD33*W33 -> 1000000 | AF33: =+X33+Z33+AB33+AD33 -> 40 | AG33: =+Y33+AA33+AC33+AE33 -> 4000000 | AH33: =+U33+AG33 -> 4000000
A34: 12 | B34: 1 | C34: Refuerzo de la sociedad civil | D34: 1.1 Implementar estrategias de promoción de la demanda de asesoría y prueba voluntaria (APV) y de comunicación para el cambio de comportamiento (CCC) | E34: 1.1.5 Identificar y formar líderes pares de los grupos clave priorizados para que actúen como formadores e integren los equipos locales de promoción de la salud y prevención del VIH e ITS | F34: Costos administrativos, de operación y programaticos de la entidade ejecutora para el trabajo con servicios comunitarios para la identificación, selección, capacitación y seguimiento de lideres pares. Costos de prevención y promoción de APV, CCC, Uso de Condón, Reducción de Estigma y discriminación y seguimiento a tratamientos | G34: Costo Líderes pares de las Entidades Ejecutoras para los temas de prevención, diagnostico y tratamiento | M34: Entidad Ejecutora | N34: ONG/OBC/Sector Académico | O34: Monitoreo y evaluación | P34: Costo Incentivo Lideres Pares | Q34: =150000*3 -> 450000 | R34: 10 | S34: =+R34*Q34 -> 4500000 | T34: =+R34 -> 10 | U34: =S34 -> 4500000 | V34: =+P34 -> Costo Incentivo Lideres Pares | W34: =154500*3 -> 463500 | X34: =+R34 -> 10 | Y34: =+W34*X34 -> 4635000 | Z34: 45 | AA34: =+Z34*W34 -> 20857500 | AB34: =+Z34 -> 45 | AC34: =+AB34*W34 -> 20857500 | AD34: =+AB34 -> 45 | AE34: =+AD34*W34 -> 20857500 | AF34: =+X34+Z34+AB34+AD34 -> 145 | AG34: =+Y34+AA34+AC34+AE34 -> 67207500 | AH34: =+U34+AG34 -> 71707500
A35: TOTAL DESTINACION ESPECIFICA | AH35: =SUM(AH29:AH34) -> 108834120 | AI35: =+AH35 -> 108834120
A36: TOTAL PRESUPUESTO | AI36: =+AI26+AI35 -> 446384282

Sheet Summary Bolivar
A1: PRESUPUESTO ENTIDADES EJECUTORAS
A2: BOLIVAR
A4: Nombre Entidad Ejecutora:
A6: Detalle | B6: Presupuesto Total | C6: Tope Presupuestal
A7: Recurso Humano | B7: =+'[1]Fase I Valle del Cauca'!AH4 -> 0 | C7: =+'Fase I Bolivar'!AI4 -> 210518654
A8: Monitoreo y Evaluación | B8: =+'[1]Fase I Valle del Cauca'!AH11 -> 0 | C8: =+'Fase I Bolivar'!AI11 -> 63155601
A9: Planeación y Administración | B9: =+'[1]Fase I Valle del Cauca'!AH16 -> 0 | C9: =+'Fase I Bolivar'!AI24 -> 27066691
A10: Total Rubros de Funcionamiento | B10: =SUM(B7:B9) -> 0 | C10: =SUM(C7:C9) -> 300740946
A12: Destinación Específica | B12: =+'Fase I Bolivar'!AH35 -> 93855490 | C12: =+'Fase I Bolivar'!AI35 -> 93855490
A13: Total Destinación Específica | B13: =+B12 -> 93855490 | C13: =+C12 -> 93855490
A14: PRESUPUESTO TOTAL | B14: =+B10+B13 -> 93855490 | C14: =+C10+C13 -> 394596436
A19: XXXXXX
A20: REPRESENTANTE LEGAL

Sheet Fase I Bolivar
A1: PRESUPUESTO DETALLADO
A2: No | B2: No de Objetivo: Crear capacidad comunitaria para la adopción de comportamientos seguros, la reducción de la vulnerabilidad social al VIH y el empoderamiento de los grupos clave priorizados | C2: Área de prestación de servicios (APS) | D2: Macro-Categoría | E2: Tarea | F2: Sub -Tarea | G2: Descripción / Hipotesis | H2: Año 1 | I2: Año 2 | M2: Responsable de la ejecución | N2: Tipo de entidad ejecutora | O2: Categorías de costos | P2: Unidad de medida año 1 | Q2: Costo unitario año 1 (valor trimestre) | R2: Cantidad Trimestre 4 | S2: Importe total Trimestre 4 | T2: Cantidad total Año 1 | U2: Total Año 1 | V2: Unidad de medida año 2 | W2: Costo unitario año 2 (valor trimestre) | X2: Cantidad Trimestre 1 año 2 | Y2: Importe total Trimestre 1 año 2 | Z2: Cantidad Trimestre 2 año 2 | AA2: Importe total Trimestre 2 año 2 | AB2: Cantidad Trimestre 3 año 2 | AC2: Importe total Trimestre 3 año 2 | AD2: Cantidad Trimestre 4 año 2 | AE2: Importe total Trimestre 4 año 2 | AF2: Cantidad total Año 2 | AG2: Total Año 2 | AH2: COSTO TOTAL | AI2: Tope Presupuestal
C3: SDA | D3: Activity | H3: T4 | I3: T1 | J3: T2 | K3: T3 | L3: T4
A4: RECURSO HUMANO | AH4: =SUM(AH5:AH10) -> 0 | AI4: 210518654
A5: 7 | B5: 1 | C5: Refuerzo de la sociedad civil | D5: 1.1 Implementar estrategias de promoción de la demanda de asesoría y prueba voluntaria (APV) y de comunicación para el cambio de comportamiento (CCC) | E5: 1.1.5 Identificar y formar líderes pares de los grupos clave priorizados para que actúen como formadores e integren los equipos locales de promoción de la salud y prevención del VIH e ITS | F5: Costo recurso humano administración de la entidad ejecutora | G5: Contador | M5: Entidad Ejecutora | N5: ONG/OBC/Sector Académico | O5: Recursos Humanos | P5: Salario / Honorario | S5: =+R5*Q5 -> 0 | T5: =+R5 -> 0 | U5: =S5 -> 0 | V5: Salario / Honorario | Y5: =+W5*X5 -> 0 | AA5: =+Z5*W5 -> 0 | AC5: =+AB5*W5 -> 0 | AE5: =+AD5*W5 -> 0 | AF5: =+X5+Z5+AB5+AD5 -> 0 | AG5: =+Y5+AA5+AC5+AE5 -> 0 | AH5: =+U5+AG5 -> 0
A6: 7 | B6: 1 | G6: Apoyo a la Dirección o Representación Legal | M6: Entidad Ejecutora | N6: ONG/OBC/Sector Académico | O6: Recursos Humanos | P6: Salario / Honorario | S6: =+R6*Q6 -> 0 | T6: =+R6 -> 0 | U6: =S6 -> 0 | V6: Salario / Honorario | Y6: =+W6*X6 -> 0 | AA6: =+Z6*W6 -> 0 | AC6: =+AB6*W6 -> 0 | AE6: =+AD6*W6 -> 0 | AF6: =+X6+Z6+AB6+AD6 -> 0 | AG6: =+Y6+AA6+AC6+AE6 -> 0 | AH6: =+U6+AG6 -> 0
A7: 7 | B7: 1 | G7: Asistente de Información | M7: Entidad Ejecutora | N7: ONG/OBC/Sector Académico | O7: Recursos Humanos | P7: Salario / Honorario | S7: =+R7*Q7 -> 0 | T7: =+R7 -> 0 | U7: =S7 -> 0 | V7: Salario / Honorario | Y7: =+W7*X7 -> 0 | AA7: =+Z7*W7 -> 0 | AC7: =+AB7*W7 -> 0 | AE7: =+AD7*W7 -> 0 | AF7: =+X7+Z7+AB7+AD7 -> 0 | AG7: =+Y7+AA7+AC7+AE7 -> 0 | AH7: =+U7+AG7 -> 0
A8: 11 | B8: 1 | C8: Refuerzo de la sociedad civil | F8: Costo recurso humano programatico de la entidad ejecutora | G8: Coordinador | M8: Entidad Ejecutora | N8: ONG/OBC/Sector Académico | O8: Recursos Humanos | P8: Salario / Honorario | S8: =+R8*Q8 -> 0 | T8: =+R8 -> 0 | U8: =S8 -> 0 | V8: Salario / Honorario | Y8: =+W8*X8 -> 0 | AA8: =+Z8*W8 -> 0 | AC8: =+AB8*W8 -> 0 | AE8: =+AD8*W8 -> 0 | AF8: =+X8+Z8+AB8+AD8 -> 0 | AG8: =+Y8+AA8+AC8+AE8 -> 0 | AH8: =+U8+AG8 -> 0
A9: 11 | B9: 1 | C9: Refuerzo de la sociedad civil | G9: Profesionales en Salud Sexual y Reproductiva (SSR) | M9: Entidad Ejecutora | N9: ONG/OBC/Sector Académico | O9: Recursos Humanos | P9: Salario / Honorario | S9: =+R9*Q9 -> 0 | T9: =+R9 -> 0 | U9: =S9 -> 0 | V9: Salario / Honorario | Y9: =+W9*X9 -> 0 | AA9: =+Z9*W9 -> 0 | AC9: =+AB9*W9 -> 0 | AE9: =+AD9*W9 -> 0 | AF9: =+X9+Z9+AB9+AD9 -> 0 | AG9: =+Y9+AA9+AC9+AE9 -> 0 | AH9: =+U9+AG9 -> 0
A10: 11 | B10: 1 | C10: Refuerzo de la sociedad civil | G10: Técnicos en Salud Sexual y Reproductiva (SSR) | M10: Entidad Ejecutora | N10: ONG/OBC/Sector Académico | O10: Recursos Humanos | P10: Salario / Honorario | S10: =+R10*Q10 -> 0 | T10: =+R10 -> 0 | U10: =S10 -> 0 | V10: Salario / Honorario | Y10: =+W10*X10 -> 0 | AA10: =+Z10*W10 -> 0 | AC10: =+AB10*W10 -> 0 | AE10: =+AD10*W10 -> 0 | AF10: =+X10+Z10+AB10+AD10 -> 0 | AG10: =+Y10+AA10+AC10+AE10 -> 0 | AH10: =+U10+AG10 -> 0
A11: MONITOREO Y EVALUACION | AH11: =SUM(AH12:AH23) -> 0 | AI11: 63155601
A12: 13 | B12: 1 | C12: Refuerzo de la sociedad civil | D12: 1.1 Implementar estrategias de promoción de la demanda de asesoría y prueba voluntaria (APV) y de comunicación para el cambio de comportamiento (CCC) | E12: 1.1.5 Identificar y formar líderes pares de los grupos clave priorizados para que actúen como formadores e integren los equipos locales de promoción de la salud y prevención del VIH e ITS | F12: Este costo incluye: 1. Viaticos y desplazamientos a los municipios de influencia asignados. 2. Actividades de gestion municipal y departamental para la sostenibilidad de las iniciativas. 3. Actividades en los servicios comunitarios para el encuentro con las comunidades, generación de confianza con las poblaciones priorizadas, actividades de escucha, reducción del estigma y la discriminaciòn, entre otras (Ejm: chocolatadas, teatro o cine al parque, actividades de trueque, acciones sanatorias de apoyo en situaciòn de alta vulnerabilidad para estabilizar a las poblaciones, entre otras) | G12: Viaticos por municipio | M12: Entidad Ejecutora | N12: ONG/OBC/Sector Académico | O12: Monitoreo y evaluación | P12: Viatico | R12: =+SUM(R13:R16) -> 0 | S12: =+SUM(S13:S16) -> 0 | T12: =+SUM(T13:T16) -> 0 | U12: =+SUM(U13:U16) -> 0 | V12: Viatico | X12: =+SUM(X13:X16) -> 0 | Y12: =+SUM(Y13:Y16) -> 0 | Z12: =+SUM(Z13:Z16) -> 0 | AA12: =+SUM(AA13:AA16) -> 0 | AB12: =+SUM(AB13:AB16) -> 0 | AC12: =+SUM(AC13:AC16) -> 0 | AD12: =+SUM(AD13:AD16) -> 0 | AE12: =+SUM(AE13:AE16) -> 0 | ... AG12: =+SUM(AG13:AG16) -> 0 | AH12: =+U12+AG12 -> 0
G13: Cartagena | S13: =+Q13*R13 -> 0 | T13: =+R13 -> 0 | U13: =S13 -> 0 | W13: 1 | Y13: =+$W13*X13 -> 0 | AA13: =+$W13*Z13 -> 0 | AC13: =+$W13*AB13 -> 0 | AE13: =+$W13*AD13 -> 0 | AF13: =+X13+Z13+AB13+AD13 -> 0 | AG13: =+Y13+AA13+AC13+AE13 -> 0
G14: Magangue | S14: =+Q14*R14 -> 0 | T14: =+R14 -> 0 | U14: =S14 -> 0 | W14: 1 | Y14: =+$W14*X14 -> 0 | AA14: =+$W14*Z14 -> 0 | AC14: =+$W14*AB14 -> 0 | AE14: =+$W14*AD14 -> 0 | AF14: =+X14+Z14+AB14+AD14 -> 0 | AG14: =+Y14+AA14+AC14+AE14 -> 0
G15: Carmen de Bolivar | S15: =+Q15*R15 -> 0 | T15: =+R15 -> 0 | U15: =S15 -> 0 | W15: 1 | Y15: =+$W15*X15 -> 0 | AA15: =+$W15*Z15 -> 0 | AC15: =+$W15*AB15 -> 0 | AE15: =+$W15*AD15 -> 0 | AF15: =+X15+Z15+AB15+AD15 -> 0 | AG15: =+Y15+AA15+AC15+AE15 -> 0
G16: Arjona | S16: =+Q16*R16 -> 0 | T16: =+R16 -> 0 | U16: =S16 -> 0 | W16: 1 | Y16: =+$W16*X16 -> 0 | AA16: =+$W16*Z16 -> 0 | AC16: =+$W16*AB16 -> 0 | AE16: =+$W16*AD16 -> 0 | AF16: =+X16+Z16+AB16+AD16 -> 0 | AG16: =+Y16+AA16+AC16+AE16 -> 0
A17: 13 | B17: 1 | C17: Refuerzo de la sociedad civil | G17: Desplazamientos por municipio | M17: Entidad Ejecutora | N17: ONG/OBC/Sector Académico | O17: Monitoreo y evaluación | P17: Desplazamiento | R17: =+SUM(R18:R21) -> 0 | S17: =+SUM(S18:S21) -> 0 | T17: =+SUM(T18:T21) -> 0 | U17: =+SUM(U18:U21) -> 0 | V17: Desplazamiento | X17: =+SUM(X18:X21) -> 0 | Y17: =+SUM(Y18:Y21) -> 0 | Z17: =+SUM(Z18:Z21) -> 0 | AA17: =+SUM(AA18:AA21) -> 0 | AB17: =+SUM(AB18:AB21) -> 0 | AC17: =+SUM(AC18:AC21) -> 0 | AD17: =+SUM(AD18:AD21) -> 0 | AE17: =+SUM(AE18:AE21) -> 0 | ... AG17: =+SUM(AG18:AG21) -> 0 | AH17: =+U17+AG17 -> 0
G18: Cartagena | S18: =+Q18*R18 -> 0 | T18: =+R18 -> 0 | U18: =S18 -> 0 | W18: 1 | Y18: =+$W18*X18 -> 0 | AA18: =+$W18*Z18 -> 0 | AC18: =+$W18*AB18 -> 0 | AE18: =+$W18*AD18 -> 0 | AF18: =+X18+Z18+AB18+AD18 -> 0 | AG18: =+Y18+AA18+AC18+AE18 -> 0
G19: Magangue | S19: =+Q19*R19 -> 0 | T19: =+R19 -> 0 | U19: =S19 -> 0 | W19: 1 | Y19: =+$W19*X19 -> 0 | AA19: =+$W19*Z19 -> 0 | AC19: =+$W19*AB19 -> 0 | AE19: =+$W19*AD19 -> 0 | AF19: =+X19+Z19+AB19+AD19 -> 0 | AG19: =+Y19+AA19+AC19+AE19 -> 0
G20: Carmen de Bolivar | S20: =+Q20*R20 -> 0 | T20: =+R20 -> 0 | U20: =S20 -> 0 | W20: 1 | Y20: =+$W20*X20 -> 0 | AA20: =+$W20*Z20 -> 0 | AC20: =+$W20*AB20 -> 0 | AE20: =+$W20*AD20 -> 0 | AF20: =+X20+Z20+AB20+AD20 -> 0 | AG20: =+Y20+AA20+AC20+AE20 -> 0
G21: Arjona | S21: =+Q21*R21 -> 0 | T21: =+R21 -> 0 | U21: =S21 -> 0 | W21: 1 | Y21: =+$W21*X21 -> 0 | AA21: =+$W21*Z21 -> 0 | AC21: =+$W21*AB21 -> 0 | AE21: =+$W21*AD21 -> 0 | AF21: =+X21+Z21+AB21+AD21 -> 0 | AG21: =+Y21+AA21+AC21+AE21 -> 0
A22: 13 | B22: 1 | C22: Refuerzo de la sociedad civil | G22: Actividades de Gestión | M22: Entidad Ejecutora | N22: ONG/OBC/Sector Académico | O22: Monitoreo y evaluación | P22: Costo reunión | S22: =+R22*Q22 -> 0 | T22: =+R22 -> 0 | U22: =S22 -> 0 | V22: Costo reunión | Y22: =+W22*X22 -> 0 | AA22: =+Z22*W22 -> 0 | AC22: =+AB22*W22 -> 0 | AE22: =+AD22*W22 -> 0 | AF22: =+X22+Z22+AB22+AD22 -> 0 | AG22: =+Y22+AA22+AC22+AE22 -> 0 | AH22: =+U22+AG22 -> 0
A23: 13 | B23: 1 | C23: Refuerzo de la sociedad civil | G23: Actividades Servicios Comunitarios | M23: Entidad Ejecutora | N23: ONG/OBC/Sector Académico | O23: Monitoreo y evaluación | P23: Actividades | S23: =+R23*Q23 -> 0 | T23: =+R23 -> 0 | U23: =S23 -> 0 | V23: Actividades | Y23: =+W23*X23 -> 0 | AA23: =+Z23*W23 -> 0 | AC23: =+AB23*W23 -> 0 | AE23: =+AD23*W23 -> 0 | AF23: =+X23+Z23+AB23+AD23 -> 0 | AG23: =+Y23+AA23+AC23+AE23 -> 0 | AH23: =+U23+AG23 -> 0
A24: PLANIFICACION Y ADMINISTRACION | AH24: =SUM(AH25) -> 0 | AI24: 27066691
A25: 8 | B25: 1 | C25: Refuerzo de la sociedad civil | D25: 1.1 Implementar estrategias de promoción de la demanda de asesoría y prueba voluntaria (APV) y de comunicación para el cambio de comportamiento (CCC) | E25: 1.1.5 Identificar y formar líderes pares de los grupos clave priorizados para que actúen como formadores e integren los equipos locales de promoción de la salud y prevención del VIH e ITS | F25: Este costo incluye los Costos Administrativos (como, Arriendo, servicios públicos, Comunicaciones, impresiones, fotocopias, papelería, correos, gastos bancarios, seguros, mantenimiento y reparaciones, servicios generales, entre otros). | M25: Entidad Ejecutora | N25: ONG/OBC/Sector Académico | O25: Planificación y Administración | S25: =+R25*Q25 -> 0 | T25: =+R25 -> 0 | U25: =S25 -> 0 | Y25: =+W25*X25 -> 0 | AA25: =+Z25*W25 -> 0 | AC25: =+AB25*W25 -> 0 | AE25: =+AD25*W25 -> 0 | AF25: =+X25+Z25+AB25+AD25 -> 0 | AG25: =+Y25+AA25+AC25+AE25 -> 0 | AH25: =+U25+AG25 -> 0
A26: TOTAL RUBROS DE FUNCIONAMIENTO | AH26: =+AH4+AH11+AH24 -> 0 | AI26: =+AI4+AI11+AI24 -> 300740946
AH27: =SUM(AH7:AH25) -> 0
A28: DESTINACION ESPECIFICA
A29: 6 | B29: 1 | C29: CCC (Comunicación para Cambio de Comportamiento)- Medios de comunicación | D29: 1.1 Implementar estrategias de promoción de la demanda de asesoría y prueba voluntaria (APV) y de comunicación para el cambio de comportamiento (CCC) | E29: 1.1.4 Implementar acciones de CCC y de promoción de demanda de APV en medios alternativos y cara-a-cara (outreach) para transformar conductas sexuales de riesgo, promover el uso consistente y adecuado del condón y divulgar servicios y rutas de derechos a los grupos clave | F29: Este costo esta representado por brigadas de acercamiento a los grupos clave en sus entornos naturales | G29: Costo por brigada. El costo asignado por brigada es de $15,355. Incluye alimentación y transporte | M29: Entidad Ejecutora | N29: ONG/OBC/Sector Académico | O29: Capacitación | P29: costo por brigada | Q29: =15355 -> 15355 | R29: 188 | S29: =+R29*Q29 -> 2886740 | T29: =+R29 -> 188 | U29: =S29 -> 2886740 | V29: costo por brigada | W29: =+Q29 -> 15355 | X29: 188 | Y29: =+W29*X29 -> 2886740 | Z29: 188 | AA29: =+Z29*W29 -> 2886740 | AB29: =+Z29 -> 188 | AC29: =+AB29*W29 -> 2886740 | AD29: 186 | AE29: =+AD29*W29 -> 2856030 | AF29: =+X29+Z29+AB29+AD29 -> 750 | AG29: =+Y29+AA29+AC29+AE29 -> 11516250 | AH29: =+U29+AG29 -> 14402990
A30: 34 | B30: 1 | C30: Refuerzo de las capacidades institucionales | D30: 1.3 Crear y fortalecer servicios comunitarios y/o redes comunitarias tipo A para la prevención del VIH/Sida /ITS, la promoción y referencia a APV, la educación en derechos y el empoderamiento de los grupos clave | E30: 1.3.5 Diseñar e implementar un plan de mejoramiento de capacidades locativas, de dotación y del recurso humano en los servicios comunitarios tipo A para la implementación efectiva de estrategias de CCC, promoción de la demanda de APV, educación en derechos, educación de pares | F30: Desarrollo de asistencia técnica a los servicios comunitarios tipo A asignados en temas identificados en la evaluación de necesidades | G30: Costo por servicio comunitario de 24 horas (valor hora $36.000) | M30: Entidad Ejecutora | N30: ONG/OBC/Sector Académico | O30: Asistencia técnica y gerencial | P30: Costo por hora asistencia tecnica | S30: =+R30*Q30 -> 0 | T30: =+R30 -> 0 | U30: =S30 -> 0 | V30: Costo por hora asistencia tecnica | W30: =36000*24 -> 864000 | X30: 4 | Y30: =+W30*X30 -> 3456000 | Z30: 3 | AA30: =+Z30*W30 -> 2592000 | AC30: =+AB30*W30 -> 0 | AD30: =+AB30 -> 0 | AE30: =+AD30*W30 -> 0 | AF30: =+X30+Z30+AB30+AD30 -> 7 | AG30: =+Y30+AA30+AC30+AE30 -> 6048000 | AH30: =+U30+AG30 -> 6048000
A31: 35 | B31: 1 | C31: Refuerzo de las capacidades institucionales | D31: 1.3 Crear y fortalecer servicios comunitarios y/o redes comunitarias tipo A para la prevención del VIH/Sida /ITS, la promoción y referencia a APV, la educación en derechos y el empoderamiento de los grupos clave | E31: 1.3.5 Diseñar e implementar un plan de mejoramiento de capacidades locativas, de dotación y del recurso humano en los servicios comunitarios tipo A para la implementación efectiva de estrategias de CCC, promoción de la demanda de APV, educación en derechos, educación de pares | F31: Desarrollo de asistencia técnica a los servicios comunitarios tipo A asignados en temas identificados en la evaluación de necesidades | G31: Costo por servicio comunitario de 12 horas (valor hora $36.000) | M31: Entidad Ejecutora | N31: ONG/OBC/Sector Académico | O31: Asistencia técnica y gerencial | P31: Costo por hora asistencia tecnica | S31: =+R31*Q31 -> 0 | T31: =+R31 -> 0 | U31: =S31 -> 0 | V31: Costo por hora asistencia tecnica | W31: =36000*12 -> 432000 | Y31: =+W31*X31 -> 0 | Z31: =+X31 -> 0 | AA31: =+Z31*W31 -> 0 | AB31: 7 | AC31: =+AB31*W31 -> 3024000 | AD31: =+AB31 -> 7 | AE31: =+AD31*W31 -> 3024000 | AF31: =+X31+Z31+AB31+AD31 -> 14 | AG31: =+Y31+AA31+AC31+AE31 -> 6048000 | AH31: =+U31+AG31 -> 6048000
A32: 43 | B32: 1 | C32: Reducción del estigma en todas las circunstancias | D32: 1.4 Implementar estrategias de movilización social para la reducción del estigma y la discriminación, la incidencia política y el agenciamiento social | E32: 1.4.3 Implementar estrategias de comunicación y movilización social del nivel nacional y local (radio, medios alternativos y cara- a-cara) para la sensibilización de las comunidades para la reducción de estigma y discriminación | F32: Desarrollo de campañas locales en medios alternativos desarrolladas en eventos comunitarios para la movilización social en torno a la prevención del VIH y la promoción de la solidaridad frente a los grupos clave | G32: Este costo incluye campañas locales en medios alternativos | M32: Entidad Ejecutora | N32: ONG/OBC/Sector Académico | O32: Material de comunicación | P32: Costo por campaña | S32: =+R32*Q32 -> 0 | T32: =+R32 -> 0 | U32: =S32 -> 0 | V32: Costo por campaña | W32: 5000000 | X32: =+R32 -> 0 | Y32: =+W32*X32 -> 0 | Z32: 1 | AA32: =+Z32*W32 -> 5000000 | AC32: =+AB32*W32 -> 0 | AD32: 0 | AE32: =+AD32*W32 -> 0 | AF32: =+X32+Z32+AB32+AD32 -> 1 | AG32: =+Y32+AA32+AC32+AE32 -> 5000000 | AH32: =+U32+AG32 -> 5000000
A33: 46 | B33: 1 | C33: Refuerzo de la sociedad civil | D33: 1.4 Implementar estrategias de movilización social para la reducción del estigma y la discriminación, la incidencia política y el agenciamiento social | E33: 1.4.4 Implementar acciones de fortalecimiento de la capacidad de ciudadana y agenciamiento social de los grupos clave, a través de educación en derechos, empoderamiento y apoyo social | F33: Desarrollo de encuentros quincenales en los servicios comunitarios tipo A para educar en derechos, participación y ciudadanía a los grupos clave. | G33: Este costo incluye un apoyo al encuentro para agua, café y apoyo alquiler salón de reunión | M33: Entidad Ejecutora | N33: ONG/OBC/Sector Académico | O33: Capacitación | P33: Costo por encuentro | S33: =+R33*Q33 -> 0 | T33: =+R33 -> 0 | U33: =S33 -> 0 | V33: Costo por encuentro | W33: 100000 | X33: 9 | Y33: =+W33*X33 -> 900000 | Z33: =+X33 -> 9 | AA33: =+Z33*W33 -> 900000 | AB33: =+Z33 -> 9 | AC33: =+AB33*W33 -> 900000 | AD33: =+AB33 -> 9 | AE33: =+AD33*W33 -> 900000 | AF33: =+X33+Z33+AB33+AD33 -> 36 | AG33: =+Y33+AA33+AC33+AE33 -> 3600000 | AH33: =+U33+AG33 -> 3600000
A34: 12 | B34: 1 | C34: Refuerzo de la sociedad civil | D34: 1.1 Implementar estrategias de promoción de la demanda de asesoría y prueba voluntaria (APV) y de comunicación para el cambio de comportamiento (CCC) | E34: 1.1.5 Identificar y formar líderes pares de los grupos clave priorizados para que actúen como formadores e integren los equipos locales de promoción de la salud y prevención del VIH e ITS | F34: Costos administrativos, de operación y programaticos de la entidade ejecutora para el trabajo con servicios comunitarios para la identificación, selección, capacitación y seguimiento de lideres pares. Costos de prevención y promoción de APV, CCC, Uso de Condón, Reducción de Estigma y discriminación y seguimiento a tratamientos | G34: Costo Líderes pares de las Entidades Ejecutoras para los temas de prevención, diagnostico y tratamiento | M34: Entidad Ejecutora | N34: ONG/OBC/Sector Académico | O34: Monitoreo y evaluación | P34: Costo Incentivo Lideres Pares | Q34: =150000*3 -> 450000 | R34: 8 | S34: =+R34*Q34 -> 3600000 | T34: =+R34 -> 8 | U34: =S34 -> 3600000 | V34: =+P34 -> Costo Incentivo Lideres Pares | W34: =154500*3 -> 463500 | X34: =+R34 -> 8 | Y34: =+W34*X34 -> 3708000 | Z34: =8+29 -> 37 | AA34: =+Z34*W34 -> 17149500 | AB34: =+Z34 -> 37 | AC34: =+AB34*W34 -> 17149500 | AD34: =+AB34 -> 37 | AE34: =+AD34*W34 -> 17149500 | AF34: =+X34+Z34+AB34+AD34 -> 119 | AG34: =+Y34+AA34+AC34+AE34 -> 55156500 | AH34: =+U34+AG34 -> 58756500
A35: TOTAL DESTINACION ESPECIFICA | AH35: =SUM(AH29:AH34) -> 93855490 | AI35: =+AH35 -> 93855490
A36: TOTAL PRESUPUESTO | AI36: =+AI26+AI35 -> 394596436

Sheet Summary Santander
A1: PRESUPUESTO ENTIDADES EJECUTORAS
A2: SANTANDER
A4: Nombre Entidad Ejecutora:
A6: Detalle | B6: Presupuesto Total | C6: Tope Presupuestal
A7: Recurso Humano | B7: =+'[1]Fase I Valle del Cauca'!AH4 -> 0 | C7: =+'Fase I Santander'!AI4 -> 199943826
A8: Monitoreo y Evaluación | B8: =+'[1]Fase I Valle del Cauca'!AH11 -> 0 | C8: =+'Fase I Santander'!AI11 -> 59983149
A9: Planeación y Administración | B9: =+'[1]Fase I Valle del Cauca'!AH16 -> 0 | C9: =+'Fase I Santander'!AI24 -> 25707069
A10: Total Rubros de Funcionamiento | B10: =SUM(B7:B9) -> 0 | C10: =SUM(C7:C9) -> 285634044
A12: Destinación Específica | B12: =+'Fase I Santander'!AH35 -> 92842980 | C12: =+'Fase I Santander'!AI35 -> 92842980
A13: Total Destinación Específica | B13: =+B12 -> 92842980 | C13: =+C12 -> 92842980
A14: PRESUPUESTO TOTAL | B14: =+B10+B13 -> 92842980 | C14: =+C10+C13 -> 378477024
A19: XXXXXX
A20: REPRESENTANTE LEGAL

Sheet Fase I Santander
A1: PRESUPUESTO DETALLADO
A2: No | B2: No de Objetivo: Crear capacidad comunitaria para la adopción de comportamientos seguros, la reducción de la vulnerabilidad social al VIH y el empoderamiento de los grupos clave priorizados | C2: Área de prestación de servicios (APS) | D2: Macro-Categoría | E2: Tarea | F2: Sub -Tarea | G2: Descripción / Hipotesis | H2: Año 1 | I2: Año 2 | M2: Responsable de la ejecución | N2: Tipo de entidad ejecutora | O2: Categorías de costos | P2: Unidad de medida año 1 | Q2: Costo unitario año 1 (valor trimestre) | R2: Cantidad Trimestre 4 | S2: Importe total Trimestre 4 | T2: Cantidad total Año 1 | U2: Total Año 1 | V2: Unidad de medida año 2 | W2: Costo unitario año 2 (valor trimestre) | X2: Cantidad Trimestre 1 año 2 | Y2: Importe total Trimestre 1 año 2 | Z2: Cantidad Trimestre 2 año 2 | AA2: Importe total Trimestre 2 año 2 | AB2: Cantidad Trimestre 3 año 2 | AC2: Importe total Trimestre 3 año 2 | AD2: Cantidad Trimestre 4 año 2 | AE2: Importe total Trimestre 4 año 2 | AF2: Cantidad total Año 2 | AG2: Total Año 2 | AH2: COSTO TOTAL | AI2: Tope Presupuestal
C3: SDA | D3: Activity | H3: T4 | I3: T1 | J3: T2 | K3: T3 | L3: T4
A4: RECURSO HUMANO | AH4: =SUM(AH5:AH10) -> 0 | AI4: 199943826
A5: 7 | B5: 1 | C5: Refuerzo de la sociedad civil | D5: 1.1 Implementar estrategias de promoción de la demanda de asesoría y prueba voluntaria (APV) y de comunicación para el cambio de comportamiento (CCC) | E5: 1.1.5 Identificar y formar líderes pares de los grupos clave priorizados para que actúen como formadores e integren los equipos locales de promoción de la salud y prevención del VIH e ITS | F5: Costo recurso humano administración de la entidad ejecutora | G5: Contador | M5: Entidad Ejecutora | N5: ONG/OBC/Sector Académico | O5: Recursos Humanos | P5: Salario / Honorario | S5: =+R5*Q5 -> 0 | T5: =+R5 -> 0 | U5: =S5 -> 0 | V5: Salario / Honorario | Y5: =+W5*X5 -> 0 | AA5: =+Z5*W5 -> 0 | AC5: =+AB5*W5 -> 0 | AE5: =+AD5*W5 -> 0 | AF5: =+X5+Z5+AB5+AD5 -> 0 | AG5: =+Y5+AA5+AC5+AE5 -> 0 | AH5: =+U5+AG5 -> 0
A6: 7 | B6: 1 | G6: Apoyo a la Dirección o Representación Legal | M6: Entidad Ejecutora | N6: ONG/OBC/Sector Académico | O6: Recursos Humanos | P6: Salario / Honorario | S6: =+R6*Q6 -> 0 | T6: =+R6 -> 0 | U6: =S6 -> 0 | V6: Salario / Honorario | Y6: =+W6*X6 -> 0 | AA6: =+Z6*W6 -> 0 | AC6: =+AB6*W6 -> 0 | AE6: =+AD6*W6 -> 0 | AF6: =+X6+Z6+AB6+AD6 -> 0 | AG6: =+Y6+AA6+AC6+AE6 -> 0 | AH6: =+U6+AG6 -> 0
A7: 7 | B7: 1 | G7: Asistente de Información | M7: Entidad Ejecutora | N7: ONG/OBC/Sector Académico | O7: Recursos Humanos | P7: Salario / Honorario | S7: =+R7*Q7 -> 0 | T7: =+R7 -> 0 | U7: =S7 -> 0 | V7: Salario / Honorario | Y7: =+W7*X7 -> 0 | AA7: =+Z7*W7 -> 0 | AC7: =+AB7*W7 -> 0 | AE7: =+AD7*W7 -> 0 | AF7: =+X7+Z7+AB7+AD7 -> 0 | AG7: =+Y7+AA7+AC7+AE7 -> 0 | AH7: =+U7+AG7 -> 0
A8: 11 | B8: 1 | C8: Refuerzo de la sociedad civil | F8: Costo recurso humano programatico de la entidad ejecutora | G8: Coordinador | M8: Entidad Ejecutora | N8: ONG/OBC/Sector Académico | O8: Recursos Humanos | P8: Salario / Honorario | S8: =+R8*Q8 -> 0 | T8: =+R8 -> 0 | U8: =S8 -> 0 | V8: Salario / Honorario | Y8: =+W8*X8 -> 0 | AA8: =+Z8*W8 -> 0 | AC8: =+AB8*W8 -> 0 | AE8: =+AD8*W8 -> 0 | AF8: =+X8+Z8+AB8+AD8 -> 0 | AG8: =+Y8+AA8+AC8+AE8 -> 0 | AH8: =+U8+AG8 -> 0
A9: 11 | B9: 1 | C9: Refuerzo de la sociedad civil | G9: Profesionales en Salud Sexual y Reproductiva (SSR) | M9: Entidad Ejecutora | N9: ONG/OBC/Sector Académico | O9: Recursos Humanos | P9: Salario / Honorario | S9: =+R9*Q9 -> 0 | T9: =+R9 -> 0 | U9: =S9 -> 0 | V9: Salario / Honorario | Y9: =+W9*X9 -> 0 | AA9: =+Z9*W9 -> 0 | AC9: =+AB9*W9 -> 0 | AE9: =+AD9*W9 -> 0 | AF9: =+X9+Z9+AB9+AD9 -> 0 | AG9: =+Y9+AA9+AC9+AE9 -> 0 | AH9: =+U9+AG9 -> 0
A10: 11 | B10: 1 | C10: Refuerzo de la sociedad civil | G10: Técnicos en Salud Sexual y Reproductiva (SSR) | M10: Entidad Ejecutora | N10: ONG/OBC/Sector Académico | O10: Recursos Humanos | P10: Salario / Honorario | S10: =+R10*Q10 -> 0 | T10: =+R10 -> 0 | U10: =S10 -> 0 | V10: Salario / Honorario | Y10: =+W10*X10 -> 0 | AA10: =+Z10*W10 -> 0 | AC10: =+AB10*W10 -> 0 | AE10: =+AD10*W10 -> 0 | AF10: =+X10+Z10+AB10+AD10 -> 0 | AG10: =+Y10+AA10+AC10+AE10 -> 0 | AH10: =+U10+AG10 -> 0
A11: MONITOREO Y EVALUACION | AH11: =SUM(AH12:AH23) -> 0 | AI11: 59983149
A12: 13 | B12: 1 | C12: Refuerzo de la sociedad civil | D12: 1.1 Implementar estrategias de promoción de la demanda de asesoría y prueba voluntaria (APV) y de comunicación para el cambio de comportamiento (CCC) | E12: 1.1.5 Identificar y formar líderes pares de los grupos clave priorizados para que actúen como formadores e integren los equipos locales de promoción de la salud y prevención del VIH e ITS | F12: Este costo incluye: 1. Viaticos y desplazamientos a los municipios de influencia asignados. 2. Actividades de gestion municipal y departamental para la sostenibilidad de las iniciativas. 3. Actividades en los servicios comunitarios para el encuentro con las comunidades, generación de confianza con las poblaciones priorizadas, actividades de escucha, reducción del estigma y la discriminaciòn, entre otras (Ejm: chocolatadas, teatro o cine al parque, actividades de trueque, acciones sanatorias de apoyo en situaciòn de alta vulnerabilidad para estabilizar a las poblaciones, entre otras) | G12: Viaticos por municipio | M12: Entidad Ejecutora | N12: ONG/OBC/Sector Académico | O12: Monitoreo y evaluación | P12: Viatico | R12: =+SUM(R13:R16) -> 0 | S12: =+SUM(S13:S16) -> 0 | T12: =+SUM(T13:T16) -> 0 | U12: =+SUM(U13:U16) -> 0 | V12: Viatico | X12: =+SUM(X13:X16) -> 0 | Y12: =+SUM(Y13:Y16) -> 0 | Z12: =+SUM(Z13:Z16) -> 0 | AA12: =+SUM(AA13:AA16) -> 0 | AB12: =+SUM(AB13:AB16) -> 0 | AC12: =+SUM(AC13:AC16) -> 0 | AD12: =+SUM(AD13:AD16) -> 0 | AE12: =+SUM(AE13:AE16) -> 0 | ... AG12: =+SUM(AG13:AG16) -> 0 | AH12: =+U12+AG12 -> 0
G13: Bucaramanga | S13: =+R13*Q13 -> 0 | T13: =+R13 -> 0 | U13: =S13 -> 0 | W13: 1 | Y13: =+$W13*X13 -> 0 | AA13: =+$W13*Z13 -> 0 | AC13: =+$W13*AB13 -> 0 | AE13: =+$W13*AD13 -> 0 | AF13: =+X13+Z13+AB13+AD13 -> 0 | AG13: =+Y13+AA13+AC13+AE13 -> 0
G14: Barrancabermeja | S14: =+R14*Q14 -> 0 | T14: =+R14 -> 0 | U14: =S14 -> 0 | W14: 1 | Y14: =+$W14*X14 -> 0 | AA14: =+$W14*Z14 -> 0 | AC14: =+$W14*AB14 -> 0 | AE14: =+$W14*AD14 -> 0 | AF14: =+X14+Z14+AB14+AD14 -> 0 | AG14: =+Y14+AA14+AC14+AE14 -> 0
G15: Floridablanca | S15: =+R15*Q15 -> 0 | T15: =+R15 -> 0 | U15: =S15 -> 0 | W15: 1 | Y15: =+$W15*X15 -> 0 | AA15: =+$W15*Z15 -> 0 | AC15: =+$W15*AB15 -> 0 | AE15: =+$W15*AD15 -> 0 | AF15: =+X15+Z15+AB15+AD15 -> 0 | AG15: =+Y15+AA15+AC15+AE15 -> 0
G16: San Gil | S16: =+R16*Q16 -> 0 | T16: =+R16 -> 0 | U16: =S16 -> 0 | W16: 1 | Y16: =+$W16*X16 -> 0 | AA16: =+$W16*Z16 -> 0 | AC16: =+$W16*AB16 -> 0 | AE16: =+$W16*AD16 -> 0 | AF16: =+X16+Z16+AB16+AD16 -> 0 | AG16: =+Y16+AA16+AC16+AE16 -> 0
A17: 13 | B17: 1 | C17: Refuerzo de la sociedad civil | G17: Desplazamientos por municipio | M17: Entidad Ejecutora | N17: ONG/OBC/Sector Académico | O17: Monitoreo y evaluación | P17: Desplazamiento | R17: =+SUM(R18:R21) -> 0 | S17: =+SUM(S18:S21) -> 0 | T17: =+SUM(T18:T21) -> 0 | U17: =+SUM(U18:U21) -> 0 | V17: Desplazamiento | X17: =+SUM(X18:X21) -> 0 | Y17: =+SUM(Y18:Y21) -> 0 | Z17: =+SUM(Z18:Z21) -> 0 | AA17: =+SUM(AA18:AA21) -> 0 | AB17: =+SUM(AB18:AB21) -> 0 | AC17: =+SUM(AC18:AC21) -> 0 | AD17: =+SUM(AD18:AD21) -> 0 | AE17: =+SUM(AE18:AE21) -> 0 | ... AG17: =+SUM(AG18:AG21) -> 0 | AH17: =+U17+AG17 -> 0
G18: Bucaramanga | S18: =+R18*Q18 -> 0 | T18: =+R18 -> 0 | U18: =S18 -> 0 | W18: 1 | Y18: =+$W18*X18 -> 0 | AA18: =+$W18*Z18 -> 0 | AC18: =+$W18*AB18 -> 0 | AE18: =+$W18*AD18 -> 0 | AF18: =+X18+Z18+AB18+AD18 -> 0 | AG18: =+Y18+AA18+AC18+AE18 -> 0
G19: Barrancabermeja | S19: =+R19*Q19 -> 0 | T19: =+R19 -> 0 | U19: =S19 -> 0 | W19: 1 | Y19: =+$W19*X19 -> 0 | AA19: =+$W19*Z19 -> 0 | AC19: =+$W19*AB19 -> 0 | AE19: =+$W19*AD19 -> 0 | AF19: =+X19+Z19+AB19+AD19 -> 0 | AG19: =+Y19+AA19+AC19+AE19 -> 0
G20: Floridablanca | S20: =+R20*Q20 -> 0 | T20: =+R20 -> 0 | U20: =S20 -> 0 | W20: 1 | Y20: =+$W20*X20 -> 0 | AA20: =+$W20*Z20 -> 0 | AC20: =+$W20*AB20 -> 0 | AE20: =+$W20*AD20 -> 0 | AF20: =+X20+Z20+AB20+AD20 -> 0 | AG20: =+Y20+AA20+AC20+AE20 -> 0
G21: San Gil | S21: =+R21*Q21 -> 0 | T21: =+R21 -> 0 | U21: =S21 -> 0 | W21: 1 | Y21: =+$W21*X21 -> 0 | AA21: =+$W21*Z21 -> 0 | AC21: =+$W21*AB21 -> 0 | AE21: =+$W21*AD21 -> 0 | AF21: =+X21+Z21+AB21+AD21 -> 0 | AG21: =+Y21+AA21+AC21+AE21 -> 0
A22: 13 | B22: 1 | C22: Refuerzo de la sociedad civil | G22: Actividades de Gestión | M22: Entidad Ejecutora | N22: ONG/OBC/Sector Académico | O22: Monitoreo y evaluación | P22: Costo reunión | S22: =+R22*Q22 -> 0 | T22: =+R22 -> 0 | U22: =S22 -> 0 | V22: Costo reunión | Y22: =+W22*X22 -> 0 | AA22: =+Z22*W22 -> 0 | AC22: =+AB22*W22 -> 0 | AE22: =+AD22*W22 -> 0 | AF22: =+X22+Z22+AB22+AD22 -> 0 | AG22: =+Y22+AA22+AC22+AE22 -> 0 | AH22: =+U22+AG22 -> 0
A23: 13 | B23: 1 | C23: Refuerzo de la sociedad civil | G23: Actividades Servicios Comunitarios | M23: Entidad Ejecutora | N23: ONG/OBC/Sector Académico | O23: Monitoreo y evaluación | P23: Actividades | S23: =+R23*Q23 -> 0 | T23: =+R23 -> 0 | U23: =S23 -> 0 | V23: Actividades | Y23: =+W23*X23 -> 0 | AA23: =+Z23*W23 -> 0 | AC23: =+AB23*W23 -> 0 | AE23: =+AD23*W23 -> 0 | AF23: =+X23+Z23+AB23+AD23 -> 0 | AG23: =+Y23+AA23+AC23+AE23 -> 0 | AH23: =+U23+AG23 -> 0
A24: PLANIFICACION Y ADMINISTRACION | AH24: =SUM(AH25) -> 0 | AI24: 25707069
A25: 8 | B25: 1 | C25: Refuerzo de la sociedad civil | D25: 1.1 Implementar estrategias de promoción de la demanda de asesoría y prueba voluntaria (APV) y de comunicación para el cambio de comportamiento (CCC) | E25: 1.1.5 Identificar y formar líderes pares de los grupos clave priorizados para que actúen como formadores e integren los equipos locales de promoción de la salud y prevención del VIH e ITS | F25: Este costo incluye los Costos Administrativos (como, Arriendo, servicios públicos, Comunicaciones, impresiones, fotocopias, papelería, correos, gastos bancarios, seguros, mantenimiento y reparaciones, servicios generales, entre otros). | M25: Entidad Ejecutora | N25: ONG/OBC/Sector Académico | O25: Planificación y Administración | S25: =+R25*Q25 -> 0 | T25: =+R25 -> 0 | U25: =S25 -> 0 | Y25: =+W25*X25 -> 0 | AA25: =+Z25*W25 -> 0 | AC25: =+AB25*W25 -> 0 | AE25: =+AD25*W25 -> 0 | AF25: =+X25+Z25+AB25+AD25 -> 0 | AG25: =+Y25+AA25+AC25+AE25 -> 0 | AH25: =+U25+AG25 -> 0
A26: TOTAL RUBROS DE FUNCIONAMIENTO | AH26: =+AH4+AH11+AH24 -> 0 | AI26: =+AI4+AI11+AI24 -> 285634044
AH27: =SUM(AH7:AH25) -> 0
A28: DESTINACION ESPECIFICA
A29: 6 | B29: 1 | C29: CCC (Comunicación para Cambio de Comportamiento)- Medios de comunicación | D29: 1.1 Implementar estrategias de promoción de la demanda de asesoría y prueba voluntaria (APV) y de comunicación para el cambio de comportamiento (CCC) | E29: 1.1.4 Implementar acciones de CCC y de promoción de demanda de APV en medios alternativos y cara-a-cara (outreach) para transformar conductas sexuales de riesgo, promover el uso consistente y adecuado del condón y divulgar servicios y rutas de derechos a los grupos clave | F29: Este costo esta representado por brigadas de acercamiento a los grupos clave en sus entornos naturales | G29: Costo por brigada. El costo asignado por brigada es de $15,355. Incluye alimentación y transporte | M29: Entidad Ejecutora | N29: ONG/OBC/Sector Académico | O29: Capacitación | P29: costo por brigada | Q29: =15355 -> 15355 | R29: 175 | S29: =+R29*Q29 -> 2687125 | T29: =+R29 -> 175 | U29: =S29 -> 2687125 | V29: costo por brigada | W29: =+Q29 -> 15355 | X29: 175 | Y29: =+W29*X29 -> 2687125 | Z29: 175 | AA29: =+Z29*W29 -> 2687125 | AB29: =+Z29 -> 175 | AC29: =+AB29*W29 -> 2687125 | AD29: 176 | AE29: =+AD29*W29 -> 2702480 | AF29: =+X29+Z29+AB29+AD29 -> 701 | AG29: =+Y29+AA29+AC29+AE29 -> 10763855 | AH29: =+U29+AG29 -> 13450980
A30: 34 | B30: 1 | C30: Refuerzo de las capacidades institucionales | D30: 1.3 Crear y fortalecer servicios comunitarios y/o redes comunitarias tipo A para la prevención del VIH/Sida /ITS, la promoción y referencia a APV, la educación en derechos y el empoderamiento de los grupos clave | E30: 1.3.5 Diseñar e implementar un plan de mejoramiento de capacidades locativas, de dotación y del recurso humano en los servicios comunitarios tipo A para la implementación efectiva de estrategias de CCC, promoción de la demanda de APV, educación en derechos, educación de pares | F30: Desarrollo de asistencia técnica a los servicios comunitarios tipo A asignados en temas identificados en la evaluación de necesidades | G30: Costo por servicio comunitario de 24 horas (valor hora $36.000) | M30: Entidad Ejecutora | N30: ONG/OBC/Sector Académico | O30: Asistencia técnica y gerencial | P30: Costo por hora asistencia tecnica | S30: =+R30*Q30 -> 0 | T30: =+R30 -> 0 | U30: =S30 -> 0 | V30: Costo por hora asistencia tecnica | W30: =36000*24 -> 864000 | X30: 3 | Y30: =+W30*X30 -> 2592000 | Z30: 3 | AA30: =+Z30*W30 -> 2592000 | AC30: =+AB30*W30 -> 0 | AD30: =+AB30 -> 0 | AE30: =+AD30*W30 -> 0 | AF30: =+X30+Z30+AB30+AD30 -> 6 | AG30: =+Y30+AA30+AC30+AE30 -> 5184000 | AH30: =+U30+AG30 -> 5184000
A31: 35 | B31: 1 | C31: Refuerzo de las capacidades institucionales | D31: 1.3 Crear y fortalecer servicios comunitarios y/o redes comunitarias tipo A para la prevención del VIH/Sida /ITS, la promoción y referencia a APV, la educación en derechos y el empoderamiento de los grupos clave | E31: 1.3.5 Diseñar e implementar un plan de mejoramiento de capacidades locativas, de dotación y del recurso humano en los servicios comunitarios tipo A para la implementación efectiva de estrategias de CCC, promoción de la demanda de APV, educación en derechos, educación de pares | F31: Desarrollo de asistencia técnica a los servicios comunitarios tipo A asignados en temas identificados en la evaluación de necesidades | G31: Costo por servicio comunitario de 12 horas (valor hora $36.000) | M31: Entidad Ejecutora | N31: ONG/OBC/Sector Académico | O31: Asistencia técnica y gerencial | P31: Costo por hora asistencia tecnica | S31: =+R31*Q31 -> 0 | T31: =+R31 -> 0 | U31: =S31 -> 0 | V31: Costo por hora asistencia tecnica | W31: =36000*12 -> 432000 | Y31: =+W31*X31 -> 0 | Z31: =+X31 -> 0 | AA31: =+Z31*W31 -> 0 | AB31: 6 | AC31: =+AB31*W31 -> 2592000 | AD31: =+AB31 -> 6 | AE31: =+AD31*W31 -> 2592000 | AF31: =+X31+Z31+AB31+AD31 -> 12 | AG31: =+Y31+AA31+AC31+AE31 -> 5184000 | AH31: =+U31+AG31 -> 5184000
A32: 43 | B32: 1 | C32: Reducción del estigma en todas las circunstancias | D32: 1.4 Implementar estrategias de movilización social para la reducción del estigma y la discriminación, la incidencia política y el agenciamiento social | E32: 1.4.3 Implementar estrategias de comunicación y movilización social del nivel nacional y local (radio, medios alternativos y cara- a-cara) para la sensibilización de las comunidades para la reducción de estigma y discriminación | F32: Desarrollo de campañas locales en medios alternativos desarrolladas en eventos comunitarios para la movilización social en torno a la prevención del VIH y la promoción de la solidaridad frente a los grupos clave | G32: Este costo incluye campañas locales en medios alternativos | M32: Entidad Ejecutora | N32: ONG/OBC/Sector Académico | O32: Material de comunicación | P32: Costo por campaña | S32: =+R32*Q32 -> 0 | T32: =+R32 -> 0 | U32: =S32 -> 0 | V32: Costo por campaña | W32: 5000000 | X32: =+R32 -> 0 | Y32: =+W32*X32 -> 0 | Z32: 1 | AA32: =+Z32*W32 -> 5000000 | AC32: =+AB32*W32 -> 0 | AD32: 0 | AE32: =+AD32*W32 -> 0 | AF32: =+X32+Z32+AB32+AD32 -> 1 | AG32: =+Y32+AA32+AC32+AE32 -> 5000000 | AH32: =+U32+AG32 -> 5000000
A33: 46 | B33: 1 | C33: Refuerzo de la sociedad civil | D33: 1.4 Implementar estrategias de movilización social para la reducción del estigma y la discriminación, la incidencia política y el agenciamiento social | E33: 1.4.4 Implementar acciones de fortalecimiento de la capacidad de ciudadana y agenciamiento social de los grupos clave, a través de educación en derechos, empoderamiento y apoyo social | F33: Desarrollo de encuentros quincenales en los servicios comunitarios tipo A para educar en derechos, participación y ciudadanía a los grupos clave. | G33: Este costo incluye un apoyo al encuentro para agua, café y apoyo alquiler salón de reunión | M33: Entidad Ejecutora | N33: ONG/OBC/Sector Académico | O33: Capacitación | P33: Costo por encuentro | S33: =+R33*Q33 -> 0 | T33: =+R33 -> 0 | U33: =S33 -> 0 | V33: Costo por encuentro | W33: 100000 | X33: 8 | Y33: =+W33*X33 -> 800000 | Z33: =+X33 -> 8 | AA33: =+Z33*W33 -> 800000 | AB33: =+Z33 -> 8 | AC33: =+AB33*W33 -> 800000 | AD33: 10 | AE33: =+AD33*W33 -> 1000000 | AF33: =+X33+Z33+AB33+AD33 -> 34 | AG33: =+Y33+AA33+AC33+AE33 -> 3400000 | AH33: =+U33+AG33 -> 3400000
A34: 12 | B34: 1 | C34: Refuerzo de la sociedad civil | D34: 1.1 Implementar estrategias de promoción de la demanda de asesoría y prueba voluntaria (APV) y de comunicación para el cambio de comportamiento (CCC) | E34: 1.1.5 Identificar y formar líderes pares de los grupos clave priorizados para que actúen como formadores e integren los equipos locales de promoción de la salud y prevención del VIH e ITS | F34: Costos administrativos, de operación y programaticos de la entidade ejecutora para el trabajo con servicios comunitarios para la identificación, selección, capacitación y seguimiento de lideres pares. Costos de prevención y promoción de APV, CCC, Uso de Condón, Reducción de Estigma y discriminación y seguimiento a tratamientos | G34: Costo Líderes pares de las Entidades Ejecutoras para los temas de prevención, diagnostico y tratamiento | M34: Entidad Ejecutora | N34: ONG/OBC/Sector Académico | O34: Monitoreo y evaluación | P34: Costo Incentivo Lideres Pares | Q34: =150000*3 -> 450000 | R34: 7 | S34: =+R34*Q34 -> 3150000 | T34: =+R34 -> 7 | U34: =S34 -> 3150000 | V34: =+P34 -> Costo Incentivo Lideres Pares | W34: =154500*3 -> 463500 | X34: =+R34 -> 7 | Y34: =+W34*X34 -> 3244500 | Z34: =7+32 -> 39 | AA34: =+Z34*W34 -> 18076500 | AB34: =+Z34 -> 39 | AC34: =+AB34*W34 -> 18076500 | AD34: =+AB34 -> 39 | AE34: =+AD34*W34 -> 18076500 | AF34: =+X34+Z34+AB34+AD34 -> 124 | AG34: =+Y34+AA34+AC34+AE34 -> 57474000 | AH34: =+U34+AG34 -> 60624000
A35: TOTAL DESTINACION ESPECIFICA | AH35: =SUM(AH29:AH34) -> 92842980 | AI35: =+AH35 -> 92842980
A36: TOTAL PRESUPUESTO | AI36: =+AI26+AI35 -> 378477024

Sheet Summary Meta
A1: PRESUPUESTO ENTIDADES EJECUTORAS
A2: META
A4: Nombre Entidad Ejecutora:
A6: Detalle | B6: Presupuesto Total | C6: Tope Presupuestal
A7: Recurso Humano | B7: =+'[1]Fase I Valle del Cauca'!AH4 -> 0 | C7: =+'Fase I Meta'!AI4 -> 161646435
A8: Monitoreo y Evaluación | B8: =+'[1]Fase I Valle del Cauca'!AH11 -> 0 | C8: =+'Fase I Meta'!AI11 -> 48493931
A9: Planeación y Administración | B9: =+'[1]Fase I Valle del Cauca'!AH16 -> 0 | C9: =+'Fase I Meta'!AI24 -> 20783115
A10: Total Rubros de Funcionamiento | B10: =SUM(B7:B9) -> 0 | C10: =SUM(C7:C9) -> 230923481
A12: Destinación Específica | B12: =+'Fase I Meta'!AH35 -> 79031695 | C12: =+'Fase I Meta'!AI35 -> 79031695
A13: Total Destinación Específica | B13: =+B12 -> 79031695 | C13: =+C12 -> 79031695
A14: PRESUPUESTO TOTAL | B14: =+B10+B13 -> 79031695 | C14: =+C10+C13 -> 309955176
A19: XXXXXX
A20: REPRESENTANTE LEGAL

Sheet Fase I Meta
A1: PRESUPUESTO DETALLADO
A2: No | B2: No de Objetivo: Crear capacidad comunitaria para la adopción de comportamientos seguros, la reducción de la vulnerabilidad social al VIH y el empoderamiento de los grupos clave priorizados | C2: Área de prestación de servicios (APS) | D2: Macro-Categoría | E2: Tarea | F2: Sub -Tarea | G2: Descripción / Hipotesis | H2: Año 1 | I2: Año 2 | M2: Responsable de la ejecución | N2: Tipo de entidad ejecutora | O2: Categorías de costos | P2: Unidad de medida año 1 | Q2: Costo unitario año 1 (valor trimestre) | R2: Cantidad Trimestre 4 | S2: Importe total Trimestre 4 | T2: Cantidad total Año 1 | U2: Total Año 1 | V2: Unidad de medida año 2 | W2: Costo unitario año 2 (valor trimestre) | X2: Cantidad Trimestre 1 año 2 | Y2: Importe total Trimestre 1 año 2 | Z2: Cantidad Trimestre 2 año 2 | AA2: Importe total Trimestre 2 año 2 | AB2: Cantidad Trimestre 3 año 2 | AC2: Importe total Trimestre 3 año 2 | AD2: Cantidad Trimestre 4 año 2 | AE2: Importe total Trimestre 4 año 2 | AF2: Cantidad total Año 2 | AG2: Total Año 2 | AH2: COSTO TOTAL | AI2: Tope Presupuestal
C3: SDA | D3: Activity | H3: T4 | I3: T1 | J3: T2 | K3: T3 | L3: T4
A4: RECURSO HUMANO | AH4: =SUM(AH5:AH10) -> 0 | AI4: 161646435
A5: 7 | B5: 1 | C5: Refuerzo de la sociedad civil | D5: 1.1 Implementar estrategias de promoción de la demanda de asesoría y prueba voluntaria (APV) y de comunicación para el cambio de comportamiento (CCC) | E5: 1.1.5 Identificar y formar líderes pares de los grupos clave priorizados para que actúen como formadores e integren los equipos locales de promoción de la salud y prevención del VIH e ITS | F5: Costo recurso humano administración de la entidad ejecutora | G5: Contador | M5: Entidad Ejecutora | N5: ONG/OBC/Sector Académico | O5: Recursos Humanos | P5: Salario / Honorario | S5: =+R5*Q5 -> 0 | T5: =+R5 -> 0 | U5: =S5 -> 0 | V5: Salario / Honorario | Y5: =+W5*X5 -> 0 | AA5: =+Z5*W5 -> 0 | AC5: =+AB5*W5 -> 0 | AE5: =+AD5*W5 -> 0 | AF5: =+X5+Z5+AB5+AD5 -> 0 | AG5: =+Y5+AA5+AC5+AE5 -> 0 | AH5: =+U5+AG5 -> 0
A6: 7 | B6: 1 | G6: Apoyo a la Dirección o Representación Legal | M6: Entidad Ejecutora | N6: ONG/OBC/Sector Académico | O6: Recursos Humanos | P6: Salario / Honorario | S6: =+R6*Q6 -> 0 | T6: =+R6 -> 0 | U6: =S6 -> 0 | V6: Salario / Honorario | Y6: =+W6*X6 -> 0 | AA6: =+Z6*W6 -> 0 | AC6: =+AB6*W6 -> 0 | AE6: =+AD6*W6 -> 0 | AF6: =+X6+Z6+AB6+AD6 -> 0 | AG6: =+Y6+AA6+AC6+AE6 -> 0 | AH6: =+U6+AG6 -> 0
A7: 7 | B7: 1 | G7: Asistente de Información | M7: Entidad Ejecutora | N7: ONG/OBC/Sector Académico | O7: Recursos Humanos | P7: Salario / Honorario | S7: =+R7*Q7 -> 0 | T7: =+R7 -> 0 | U7: =S7 -> 0 | V7: Salario / Honorario | Y7: =+W7*X7 -> 0 | AA7: =+Z7*W7 -> 0 | AC7: =+AB7*W7 -> 0 | AE7: =+AD7*W7 -> 0 | AF7: =+X7+Z7+AB7+AD7 -> 0 | AG7: =+Y7+AA7+AC7+AE7 -> 0 | AH7: =+U7+AG7 -> 0
A8: 11 | B8: 1 | C8: Refuerzo de la sociedad civil | F8: Costo recurso humano programatico de la entidad ejecutora | G8: Coordinador | M8: Entidad Ejecutora | N8: ONG/OBC/Sector Académico | O8: Recursos Humanos | P8: Salario / Honorario | S8: =+R8*Q8 -> 0 | T8: =+R8 -> 0 | U8: =S8 -> 0 | V8: Salario / Honorario | Y8: =+W8*X8 -> 0 | AA8: =+Z8*W8 -> 0 | AC8: =+AB8*W8 -> 0 | AE8: =+AD8*W8 -> 0 | AF8: =+X8+Z8+AB8+AD8 -> 0 | AG8: =+Y8+AA8+AC8+AE8 -> 0 | AH8: =+U8+AG8 -> 0
A9: 11 | B9: 1 | C9: Refuerzo de la sociedad civil | G9: Profesionales en Salud Sexual y Reproductiva (SSR) | M9: Entidad Ejecutora | N9: ONG/OBC/Sector Académico | O9: Recursos Humanos | P9: Salario / Honorario | S9: =+R9*Q9 -> 0 | T9: =+R9 -> 0 | U9: =S9 -> 0 | V9: Salario / Honorario | Y9: =+W9*X9 -> 0 | AA9: =+Z9*W9 -> 0 | AC9: =+AB9*W9 -> 0 | AE9: =+AD9*W9 -> 0 | AF9: =+X9+Z9+AB9+AD9 -> 0 | AG9: =+Y9+AA9+AC9+AE9 -> 0 | AH9: =+U9+AG9 -> 0
A10: 11 | B10: 1 | C10: Refuerzo de la sociedad civil | G10: Técnicos en Salud Sexual y Reproductiva (SSR) | M10: Entidad Ejecutora | N10: ONG/OBC/Sector Académico | O10: Recursos Humanos | P10: Salario / Honorario | S10: =+R10*Q10 -> 0 | T10: =+R10 -> 0 | U10: =S10 -> 0 | V10: Salario / Honorario | Y10: =+W10*X10 -> 0 | AA10: =+Z10*W10 -> 0 | AC10: =+AB10*W10 -> 0 | AE10: =+AD10*W10 -> 0 | AF10: =+X10+Z10+AB10+AD10 -> 0 | AG10: =+Y10+AA10+AC10+AE10 -> 0 | AH10: =+U10+AG10 -> 0
A11: MONITOREO Y EVALUACION | AH11: =SUM(AH12:AH23) -> 0 | AI11: 48493931
A12: 13 | B12: 1 | C12: Refuerzo de la sociedad civil | D12: 1.1 Implementar estrategias de promoción de la demanda de asesoría y prueba voluntaria (APV) y de comunicación para el cambio de comportamiento (CCC) | E12: 1.1.5 Identificar y formar líderes pares de los grupos clave priorizados para que actúen como formadores e integren los equipos locales de promoción de la salud y prevención del VIH e ITS | F12: Este costo incluye: 1. Viaticos y desplazamientos a los municipios de influencia asignados. 2. Actividades de gestion municipal y departamental para la sostenibilidad de las iniciativas. 3. Actividades en los servicios comunitarios para el encuentro con las comunidades, generación de confianza con las poblaciones priorizadas, actividades de escucha, reducción del estigma y la discriminaciòn, entre otras (Ejm: chocolatadas, teatro o cine al parque, actividades de trueque, acciones sanatorias de apoyo en situaciòn de alta vulnerabilidad para estabilizar a las poblaciones, entre otras) | G12: Viaticos por municipio | M12: Entidad Ejecutora | N12: ONG/OBC/Sector Académico | O12: Monitoreo y evaluación | P12: Viatico | S12: =+SUM(S13:S16) -> 0 | T12: =+SUM(T13:T16) -> 0 | U12: =+SUM(U13:U16) -> 0 | V12: Viatico | X12: =+SUM(X13:X16) -> 0 | Y12: =+SUM(Y13:Y16) -> 0 | Z12: =+SUM(Z13:Z16) -> 0 | AA12: =+SUM(AA13:AA16) -> 0 | AB12: =+SUM(AB13:AB16) -> 0 | AC12: =+SUM(AC13:AC16) -> 0 | AD12: =+SUM(AD13:AD16) -> 0 | AE12: =+SUM(AE13:AE16) -> 0 | ... AG12: =+SUM(AG13:AG16) -> 0 | AH12: =+U12+AG12 -> 0
G13: Villavicencio | S13: =+R13*Q13 -> 0 | T13: =+R13 -> 0 | U13: =S13 -> 0 | Y13: =+$W13*X13 -> 0 | AA13: =+$W13*Z13 -> 0 | AC13: =+$W13*AB13 -> 0 | AE13: =+$W13*AD13 -> 0 | AF13: =+X13+Z13+AB13+AD13 -> 0 | AG13: =+Y13+AA13+AC13+AE13 -> 0
G14: Acacias | S14: =+R14*Q14 -> 0 | T14: =+R14 -> 0 | U14: =S14 -> 0 | Y14: =+$W14*X14 -> 0 | AA14: =+$W14*Z14 -> 0 | AC14: =+$W14*AB14 -> 0 | AE14: =+$W14*AD14 -> 0 | AF14: =+X14+Z14+AB14+AD14 -> 0 | AG14: =+Y14+AA14+AC14+AE14 -> 0
G15: Granada | S15: =+R15*Q15 -> 0 | T15: =+R15 -> 0 | U15: =S15 -> 0 | Y15: =+$W15*X15 -> 0 | AA15: =+$W15*Z15 -> 0 | AC15: =+$W15*AB15 -> 0 | AE15: =+$W15*AD15 -> 0 | AF15: =+X15+Z15+AB15+AD15 -> 0 | AG15: =+Y15+AA15+AC15+AE15 -> 0
G16: San Martin | S16: =+R16*Q16 -> 0 | T16: =+R16 -> 0 | U16: =S16 -> 0 | Y16: =+$W16*X16 -> 0 | AA16: =+$W16*Z16 -> 0 | AC16: =+$W16*AB16 -> 0 | AE16: =+$W16*AD16 -> 0 | AF16: =+X16+Z16+AB16+AD16 -> 0 | AG16: =+Y16+AA16+AC16+AE16 -> 0
A17: 13 | B17: 1 | C17: Refuerzo de la sociedad civil | G17: Desplazamientos por municipio | M17: Entidad Ejecutora | N17: ONG/OBC/Sector Académico | O17: Monitoreo y evaluación | P17: Desplazamiento | S17: =+SUM(S18:S21) -> 0 | T17: =+SUM(T18:T21) -> 0 | U17: =+SUM(U18:U21) -> 0 | V17: Desplazamiento | X17: =+SUM(X18:X21) -> 0 | Y17: =+SUM(Y18:Y21) -> 0 | Z17: =+SUM(Z18:Z21) -> 0 | AA17: =+SUM(AA18:AA21) -> 0 | AB17: =+SUM(AB18:AB21) -> 0 | AC17: =+SUM(AC18:AC21) -> 0 | AD17: =+SUM(AD18:AD21) -> 0 | AE17: =+SUM(AE18:AE21) -> 0 | ... AG17: =+SUM(AG18:AG21) -> 0 | AH17: =+U17+AG17 -> 0
G18: Villavicencio | S18: =+R18*Q18 -> 0 | T18: =+R18 -> 0 | U18: =S18 -> 0 | Y18: =+$W18*X18 -> 0 | AA18: =+$W18*Z18 -> 0 | AC18: =+$W18*AB18 -> 0 | AE18: =+$W18*AD18 -> 0 | AF18: =+X18+Z18+AB18+AD18 -> 0 | AG18: =+Y18+AA18+AC18+AE18 -> 0
G19: Acacias | S19: =+R19*Q19 -> 0 | T19: =+R19 -> 0 | U19: =S19 -> 0 | Y19: =+$W19*X19 -> 0 | AA19: =+$W19*Z19 -> 0 | AC19: =+$W19*AB19 -> 0 | AE19: =+$W19*AD19 -> 0 | AF19: =+X19+Z19+AB19+AD19 -> 0 | AG19: =+Y19+AA19+AC19+AE19 -> 0
G20: Granada | S20: =+R20*Q20 -> 0 | T20: =+R20 -> 0 | U20: =S20 -> 0 | Y20: =+$W20*X20 -> 0 | AA20: =+$W20*Z20 -> 0 | AC20: =+$W20*AB20 -> 0 | AE20: =+$W20*AD20 -> 0 | AF20: =+X20+Z20+AB20+AD20 -> 0 | AG20: =+Y20+AA20+AC20+AE20 -> 0
G21: San Martin | S21: =+R21*Q21 -> 0 | T21: =+R21 -> 0 | U21: =S21 -> 0 | Y21: =+$W21*X21 -> 0 | AA21: =+$W21*Z21 -> 0 | AC21: =+$W21*AB21 -> 0 | AE21: =+$W21*AD21 -> 0 | AF21: =+X21+Z21+AB21+AD21 -> 0 | AG21: =+Y21+AA21+AC21+AE21 -> 0
A22: 13 | B22: 1 | C22: Refuerzo de la sociedad civil | G22: Actividades de Gestión | M22: Entidad Ejecutora | N22: ONG/OBC/Sector Académico | O22: Monitoreo y evaluación | P22: Costo reunión | S22: =+R22*Q22 -> 0 | T22: =+R22 -> 0 | U22: =S22 -> 0 | V22: Costo reunión | Y22: =+W22*X22 -> 0 | AA22: =+Z22*W22 -> 0 | AC22: =+AB22*W22 -> 0 | AE22: =+AD22*W22 -> 0 | AF22: =+X22+Z22+AB22+AD22 -> 0 | AG22: =+Y22+AA22+AC22+AE22 -> 0 | AH22: =+U22+AG22 -> 0
A23: 13 | B23: 1 | C23: Refuerzo de la sociedad civil | G23: Actividades Servicios Comunitarios | M23: Entidad Ejecutora | N23: ONG/OBC/Sector Académico | O23: Monitoreo y evaluación | P23: Actividades | S23: =+R23*Q23 -> 0 | T23: =+R23 -> 0 | U23: =S23 -> 0 | V23: Actividades | Y23: =+W23*X23 -> 0 | AA23: =+Z23*W23 -> 0 | AC23: =+AB23*W23 -> 0 | AE23: =+AD23*W23 -> 0 | AF23: =+X23+Z23+AB23+AD23 -> 0 | AG23: =+Y23+AA23+AC23+AE23 -> 0 | AH23: =+U23+AG23 -> 0
A24: PLANIFICACION Y ADMINISTRACION | AH24: =SUM(AH25) -> 0 | AI24: 20783115
A25: 8 | B25: 1 | C25: Refuerzo de la sociedad civil | D25: 1.1 Implementar estrategias de promoción de la demanda de asesoría y prueba voluntaria (APV) y de comunicación para el cambio de comportamiento (CCC) | E25: 1.1.5 Identificar y formar líderes pares de los grupos clave priorizados para que actúen como formadores e integren los equipos locales de promoción de la salud y prevención del VIH e ITS | F25: Este costo incluye los Costos Administrativos (como, Arriendo, servicios públicos, Comunicaciones, impresiones, fotocopias, papelería, correos, gastos bancarios, seguros, mantenimiento y reparaciones, servicios generales, entre otros). | M25: Entidad Ejecutora | N25: ONG/OBC/Sector Académico | O25: Planificación y Administración | S25: =+R25*Q25 -> 0 | T25: =+R25 -> 0 | U25: =S25 -> 0 | Y25: =+W25*X25 -> 0 | AA25: =+Z25*W25 -> 0 | AC25: =+AB25*W25 -> 0 | AE25: =+AD25*W25 -> 0 | AF25: =+X25+Z25+AB25+AD25 -> 0 | AG25: =+Y25+AA25+AC25+AE25 -> 0 | AH25: =+U25+AG25 -> 0
A26: TOTAL RUBROS DE FUNCIONAMIENTO | AH26: =+AH4+AH11+AH24 -> 0 | AI26: =+AI4+AI11+AI24 -> 230923481
AH27: =SUM(AH7:AH25) -> 0
A28: DESTINACION ESPECIFICA
A29: 6 | B29: 1 | C29: CCC (Comunicación para Cambio de Comportamiento)- Medios de comunicación | D29: 1.1 Implementar estrategias de promoción de la demanda de asesoría y prueba voluntaria (APV) y de comunicación para el cambio de comportamiento (CCC) | E29: 1.1.4 Implementar acciones de CCC y de promoción de demanda de APV en medios alternativos y cara-a-cara (outreach) para transformar conductas sexuales de riesgo, promover el uso consistente y adecuado del condón y divulgar servicios y rutas de derechos a los grupos clave | F29: Este costo esta representado por brigadas de acercamiento a los grupos clave en sus entornos naturales | G29: Costo por brigada. El costo asignado por brigada es de $15,355. Incluye alimentación y transporte | M29: Entidad Ejecutora | N29: ONG/OBC/Sector Académico | O29: Capacitación | P29: costo por brigada | Q29: =15355 -> 15355 | R29: 142 | S29: =+R29*Q29 -> 2180410 | T29: =+R29 -> 142 | U29: =S29 -> 2180410 | V29: costo por brigada | W29: =+Q29 -> 15355 | X29: 142 | Y29: =+W29*X29 -> 2180410 | Z29: 142 | AA29: =+Z29*W29 -> 2180410 | AB29: 142 | AC29: =+AB29*W29 -> 2180410 | AD29: 141 | AE29: =+AD29*W29 -> 2165055 | AF29: =+X29+Z29+AB29+AD29 -> 567 | AG29: =+Y29+AA29+AC29+AE29 -> 8706285 | AH29: =+U29+AG29 -> 10886695
A30: 34 | B30: 1 | C30: Refuerzo de las capacidades institucionales | D30: 1.3 Crear y fortalecer servicios comunitarios y/o redes comunitarias tipo A para la prevención del VIH/Sida /ITS, la promoción y referencia a APV, la educación en derechos y el empoderamiento de los grupos clave | E30: 1.3.5 Diseñar e implementar un plan de mejoramiento de capacidades locativas, de dotación y del recurso humano en los servicios comunitarios tipo A para la implementación efectiva de estrategias de CCC, promoción de la demanda de APV, educación en derechos, educación de pares | F30: Desarrollo de asistencia técnica a los servicios comunitarios tipo A asignados en temas identificados en la evaluación de necesidades | G30: Costo por servicio comunitario de 24 horas (valor hora $36.000) | M30: Entidad Ejecutora | N30: ONG/OBC/Sector Académico | O30: Asistencia técnica y gerencial | P30: Costo por hora asistencia tecnica | S30: =+R30*Q30 -> 0 | T30: =+R30 -> 0 | U30: =S30 -> 0 | V30: Costo por hora asistencia tecnica | W30: =36000*24 -> 864000 | X30: 3 | Y30: =+W30*X30 -> 2592000 | Z30: 3 | AA30: =+Z30*W30 -> 2592000 | AC30: =+AB30*W30 -> 0 | AD30: =+AB30 -> 0 | AE30: =+AD30*W30 -> 0 | AF30: =+X30+Z30+AB30+AD30 -> 6 | AG30: =+Y30+AA30+AC30+AE30 -> 5184000 | AH30: =+U30+AG30 -> 5184000
