Workbook

Sheet 1415T 022414
A1: MISSION COLLEGE
A2: Responsibility | B2: Contact Info. | C2: Fixed Cost Description | D2: Explanation for Adjustments | E2: Criteria | F2: Account Number | G2: Final Budget 2013-14 | H2: Working Budget 2013-14 | I2: Actuals 2013-14 as of 2/28/14 | J2: Budget Adjust. Incr / (Decr) | K2: Tent Budget 2014-15
C3: Academic Senate - Supplies/Materials | F3: 100_206200_6750_54210_819 | G3: 1000 | J3: 0 | K3: =G3+J3 -> 1000
C4: Academic Senate - non teaching stipends | F4: 100_206200_6750_51450_819 | K4: =G4+J4 -> 0
C5: Academic Senate - benefits | F5: 100_206200_6750_53xxx_819 | K5: =G5+J5 -> 0
C6: Academic Senate - dues membership & fee | F6: 100_206200_6750_55910_819 | G6: 0 | H6: 2100 | I6: 2051 | K6: =G6+J6 -> 0
C7: Academic Senate - Travel & Conference | F7: 100_206200_6750_55200_819 | G7: 3000 | H7: 1900 | I7: 1704 | J7: 0 | K7: =G7+J7 -> 3000
C8: Academic Senate President Stipend | E8: C | F8: 100_206200_6750_51450_819 | G8: 5000 | H8: 5000 | I8: 1999 | J8: 0 | K8: =G8+J8 -> 5000 | L8: =K8*11.123% -> 556.15
C9: Academic Senate President - benefits | D9: at 11.123% | E9: C | F9: 100_206200_6750_53XXX_819 | G9: 0 | H9: 0 | I9: 58 | J9: 556 | K9: =G9+J9 -> 556
A10: Senates | B10: Worku Negash | C10: Academic Senate | E10: C | F10: Multiple account numbers | G10: =SUM(G3:G9) -> 9000 | H10: =SUM(H3:H9) -> 9000 | I10: =SUM(I3:I9) -> 5812 | J10: =SUM(J3:J9) -> 556 | K10: =G10+J10 -> 9556
C11: Classified Senate - Hrly classified Salary | F11: 100_206300_6750_52310_819 | G11: 1000 | H11: 1000 | J11: 0 | K11: =G11+J11 -> 1000
C12: Classified Senate - Supplies/Materials | F12: 100_206300_6750_54210_819 | G12: 500 | H12: 500 | J12: 0 | K12: =G12+J12 -> 500
C13: Classified Senate - Food Services | F13: 100_206300_6750_55115_819 | G13: 1500 | H13: 1500 | J13: 0 | K13: =G13+J13 -> 1500
C14: Classified Senate - Travel & Conference | F14: 100_206300_6750_55205_819 | G14: 1500 | H14: 1500 | J14: 0 | K14: =G14+J14 -> 1500
A15: Senates | B15: Worku Negash | C15: Classified Senate | E15: C | F15: Multiple account numbers | G15: =SUM(G11:G14) -> 4500 | H15: =SUM(H11:H14) -> 4500 | J15: =SUM(J11:J14) -> 0 | K15: =G15+J15 -> 4500
A16: Faculty Travel | B16: Worku Negash | C16: Faculty Travel & Conference | D16: 14.4 FT Faculty | E16: D | F16: 100_290100_6600_55210_819 | G16: 29000 | H16: 29000 | I16: 21824 | J16: -200 | K16: =G16+J16 -> 28800
A17: VP Admin. Services | B17: Worku Negash | C17: Tenure Faculty - Salary | D17: 2 faculty @ 5,500 each | E17: D | F17: 100_220910_4900_51310_819 | G17: 0 | J17: 11000 | K17: =G17+J17 -> 11000
A18: VP Admin. Services | C18: Tenure Faculty - Benefits | D18: at 11.123% | E18: D | F18: 100_220910_4900_53xxx_819 | J18: 1224 | K18: =G18+J18 -> 1224
A19: Dean of Instr, Lib. St/LA | C19: Tricore, Link + Consortium, Library Maintenance | D19: Increase in cost | E19: A | F19: 100_230000_6120_55510_819 | G19: 37594 | H19: 37594 | I19: 37326 | J19: 250 | K19: =G19+J19 -> 37844
A20: VP Admin. Services | B20: Worku Negash | C20: Insurance for Athletics | E20: C | F20: 100_220000_6440_55940_819 | G20: 39654 | H20: 39654 | I20: 39654 | K20: =G20+J20 -> 39654 | L20: =K20-I20 -> 0
A21: VP Admin. Services | C21: Insurance for Students | E21: C | F21: 100_220000_6440_55940_819 | G21: 34057 | H21: 34057 | K21: =G21+J21 -> 34057
A22: Athletics | B22: Worku Negash | C22: Coaches Stipends | E22: D | F22: 100_220000_6770_51450_819 | G22: 15000 | H22: 15000 | I22: 6009 | K22: =G22+J22 -> 15000
A23: Athletics | C23: Coaches Benefits | D23: at 11.123% | E23: D | F23: 100_220000_6770_53xxx_819 | G23: 0 | H23: 0 | I23: 0 | J23: 1668 | K23: =G23+J23 -> 1668 | L23: =K22*11.123% -> 1668.45
A24: College President | C24: Accreditation - Non Teach Stipends | E24: C | F24: 100_200700_6090_51450_819 | G24: 0 | H24: 8500 | I24: 9810 | K24: =G24+J24 -> 0
A25: College President | C25: Accreditation - Hrly Classified Salary | E25: C | F25: 100_200700_6090_52310_819 | H25: 1000 | I25: 323 | K25: =G25+J25 -> 0
A26: College President | C26: Accreditation - Benefits | E26: C | F26: 100_200700_6090_53xxx_819 | I26: 1088 | K26: =G26+J26 -> 0
A27: College President | C27: Accreditation - Supplies/Materials | D27: Move to college's oper. budget | E27: C | F27: 100_200700_6090_54210_819 | G27: 10000 | H27: 1500 | I27: 2260 | J27: -10000 | K27: =G27+J27 -> 0
A28: College President | C28: Accreditation - Foods | E28: C | F28: 100_200700_6090_55115_819 | G28: 0 | H28: 150 | K28: =G28+J28 -> 0
A29: College President | C29: Accreditation - Travel, Conference | E29: C | F29: 100_200700_6090_55205_819 | H29: 15000 | K29: =G29+J29 -> 0
A30: College President | C30: Accreditation - Printing | E30: C | F30: 100_200700_6090_55300_819 | H30: 8000 | I30: 223 | K30: =G30+J30 -> 0
A31: College President | B31: Worku Negash | C31: Accreditation - Dues, Memberships & Fees | D31: decrease in FTES | E31: C | F31: 100_200700_6090_55910_819 | G31: 19137 | H31: 19137 | I31: 19137 | J31: -286 | K31: =G31+J31 -> 18851
A32: College President | C32: Accreditation | D32: Dues, Membership | E32: C | F32: Multiple account numbers | G32: =SUM(G24:G31) -> 29137 | H32: =SUM(H24:H31) -> 53287 | I32: =SUM(I24:I31) -> 32841 | J32: =SUM(J24:J31) -> -10286 | K32: =G32+J32 -> 18851
A33: VP Admin. Services | B33: Linda Francis/Virginia | C33: Categorical Program: Transfer Out, Fringe Benefits | D33: Increase funding level | E33: C | F33: 100_220001_7310_57300_819 | G33: 340397 | H33: 340397 | I33: 218683 | J33: 73603 | K33: =G33+J33 -> 414000
A34: VP Admin. Services | B34: Linda Francis/Virginia | C34: Financial Aid Match: SEOG & Fed Work Study | D34: Increase funding level | E34: C | F34: 100_220002_7310_57300_819 | G34: 81876 | H34: 81876 | J34: 12910 | K34: =G34+J34 -> 94786
A35: VP Admin. Services | C35: HigherOne | D35: Increase in cost | E35: F | F35: 100_220900_6490_55160_819 | G35: 2500 | H35: 2500 | I35: 2625 | J35: 125 | K35: =G35+J35 -> 2625
A36: VP Admin. Services | B36: Worku Negash | C36: Astra Schedule | E36: A | F36: 100_220007_6010_55500_819 | G36: 9950 | H36: 37299 | I36: 18242 | K36: =G36+J36 -> 9950
A37: VP Admin. Services | C37: LaserFiche | E37: A | F37: 100_220007_6010_55500_819 | G37: 8160 | K37: =G37+J37 -> 8160
A38: VP Admin. Services | C38: Form Fusion | D38: Increase in cost | E38: A | F38: 100_220007_6010_55500_819 | G38: 949 | J38: 38 | K38: =G38+J38 -> 987
A39: VP Admin. Services | B39: Worku Negash | C39: Curricunet | E39: A | F39: 100_220000_6010_55160_819 | G39: 11800 | H39: 11800 | I39: 11800 | K39: =G39+J39 -> 11800
A40: VP Admin. Services | B40: Worku Negash | C40: Curricunet (Governet) Meta upgrade - one time | E40: A | F40: 100_220000_6010_55160_819 | G40: 0 | H40: 0 | I40: 0 | J40: 15000 | K40: =G40+J40 -> 15000
A41: VP Admin. Services | B41: Ron Smith | C41: SARS Software Products -Counseling Sched System | E41: A | F41: 100_220004_6150_55500_819 | G41: 6500 | H41: 6500 | I41: 0 | K41: =G41+J41 -> 6500
A42: VP Admin. Services | B42: Ron Smith | C42: Angel | D42: Renewal rate adj for 2 yr contract | E42: A | F42: 100_220005_6150_55500_819 | G42: 82626 | H42: 82626 | I42: 82626 | J42: 4131 | K42: =G42+J42 -> 86757
A43: VP Admin. Services | B43: Ron Smith | C43: CCCApply / BOGS (Student-Right-to-know) | D43: State funded | E43: A | F43: 100_220006_6150_55500_819 | G43: 15609 | H43: 15609 | I43: 11400 | J43: -15609 | K43: =G43+J43 -> 0 | L43: =SUM(G44,J44) -> 851051
F44: Total Mission College | G44: =SUM(G10,G15:G22,G32:G43) -> 758309 | H44: =SUM(H10,H15:H22,H32:H43) -> 800699 | I44: =SUM(I10,I15:I22,I32:I43) -> 488842 | J44: =SUM(J10,J15:J22,J32:J43) -> 92742 | K44: =SUM(K10,K15:K22,K32:K43) -> 851051
A46: WEST VALLEY COLLEGE
A47: Responsibility | B47: Contact Info. | C47: Fixed Cost Description | D47: Explanation for Adjustments | E47: Criteria | F47: Account Number | G47: Final Budget 2013-14 | H47: Working Budget 2013-14 | I47: Actuals 2013-14 as of 2/28/14 | J47: Budget Adjust. Incr / (Decr) | K47: Tent Budget 2014-15
C48: Academic Senate | F48: 100_119304_6750_55115_819 | G48: 1100 | H48: 1100 | I48: 0 | J48: 0 | K48: =G48+J48 -> 1100
C49: Academic Senate | F49: 100_119304_6750_55200_819 | G49: 3300 | H49: 3300 | I49: 0 | J49: 0 | K49: =G49+J49 -> 3300
C50: Academic Senate - Stipends | F50: 100_119100_6030_51450_819 | H50: 5000 | I50: 5000 | J50: 0 | K50: =G50+J50 -> 0
C51: Academic Senate President Stipend | D51: for July & June at 2,500 ea. | E51: C | F51: 100_119304_6750_51450_819 | G51: 5000 | K51: =G51+J51 -> 5000
C52: Academic Senate President benefits | D52: at 11.123% | E52: C | F52: 100_119304_6750_53xxx_819 | J52: 556 | K52: =G52+J52 -> 556 | L52: =K51*11.123% -> 556.15
A53: Senates | B53: Michael Renzi | C53: Academic Senate | E53: C | F53: Multiple account numbers | G53: =SUM(G48:G51) -> 9400 | H53: =SUM(H48:H51) -> 9400 | I53: =SUM(I48:I51) -> 5000 | J53: =SUM(J48:J52) -> 556 | K53: =G53+J53 -> 9956
C54: Classified Senate | F54: 100_119305_6750_55115_819 | G54: 3660 | H54: 3660 | I54: 442 | J54: 0 | K54: =G54+J54 -> 3660
C55: Classified Senate | F55: 100_119305_6750_55160_819 | G55: 440 | H55: 440 | J55: 0 | K55: =G55+J55 -> 440
C56: Classified Senate | F56: 100_119305_6750_55200_819 | G56: 300 | H56: 300 | J56: 0 | K56: =G56+J56 -> 300
A57: Senates | B57: Michael Renzi | C57: Classified Senate | E57: C | F57: Multiple account numbers | G57: =SUM(G54:G56) -> 4400 | H57: =SUM(H54:H56) -> 4400 | I57: =SUM(I54:I56) -> 442 | J57: =SUM(J54:J56) -> 0 | K57: =G57+J57 -> 4400
A58: VP Admin. Services | B58: Michael Renzi | C58: Faculty Travel & Conference | D58: 166 FT Faculty | E58: D | F58: 100_103201_6010_55210_819 | G58: 33200 | H58: 33200 | I58: 5491 | K58: =G58+J58 -> 33200
A59: VP Admin. Services | B59: Michael Renzi | C59: Tenure Faculty - Salary | E59: D | F59: 100_103251_4900_51310_819 | K59: =G59+J59 -> 0
A60: VP Admin. Services | B60: Michael Renzi | C60: Tenure Faculty - Benefits | E60: D | F60: 100_103251_4900_53XXX_819 | G60: 0 | H60: 0 | I60: 0 | J60: 0 | K60: =G60+J60 -> 0
A61: Dean Learning Center | B61: Michael Renzi | C61: Tricore, Link + Consortium, Library Maintenance | D61: Increase in cost | E61: A | F61: 100_106100_6120_55510_819 | G61: 40155 | H61: 40155 | I61: 39339 | J61: 2345 | K61: =G61+J61 -> 42500
A62: VP Admin. Services | B62: Michael Renzi | C62: Insurance for Athletics | E62: C | F62: 100_115200_6960_55940_819 | G62: 79263 | H62: 79263 | I62: 79263 | K62: =G62+J62 -> 79263
A63: VP Admin. Services | B63: Michael Renzi | C63: Insurance for Students | E63: C | F63: 100_103200_6440_55940_819 | G63: 31305 | H63: 31305 | I63: 31305 | K63: =G63+J63 -> 31305
A64: Athletics | B64: Michael Renzi | C64: Coaches Stipends | E64: D | F64: 100_115200_6960_51450_819 | G64: 22161 | H64: 22161 | I64: 10399 | K64: =G64+J64 -> 22161
A65: Athletics | C65: Coaches Benefits | D65: at 11.123% | E65: D | F65: 100_115200_6960_53xxx_819 | G65: 2465 | H65: 2465 | K65: =G65+J65 -> 2465
A66: College President | C66: Accreditation - Dues, Memberships & Fees | D66: decrease in FTES | E66: C | F66: 100_100100_6090_55910_819 | G66: 22159 | H66: 22159 | I66: 22159 | J66: -3308 | K66: =G66+J66 -> 18851
A67: College President | B67: Michael Renzi | C67: Accreditation - Hourly Classified | D67: move to college's oper.budget | E67: C | F67: 100_100100_6090_52350_819 | G67: 8650 | J67: -8650 | K67: =G67+J67 -> 0
A68: College President | B68: Michael Renzi | C68: Accreditation - Supplies/Materials | D68: move to college's oper. budget | E68: C | F68: 100_100100_6090_54210_819 | G68: 1350 | H68: 12080 | I68: 1075 | J68: -1350 | K68: =G68+J68 -> 0
A69: College President | B69: Linda Francis/Virginia | C69: Accreditation - Travel, Conference | E69: C | F69: 100_100100_6090_55200_819 | H69: 16500 | I69: 10146 | K69: =G69+J69 -> 0
A70: College President | B70: Linda Francis/Virginia | C70: Accreditation -Duplicating | E70: C | F70: 100_100100_6090_54240_819 | H70: 3500 | I70: 1546 | K70: =G70+J70 -> 0
A71: College President | C71: Accreditation - Food | E71: C | F71: 100_100100_6090_55115_819 | H71: 625 | I71: 0 | K71: =G71+J71 -> 0
A72: College President | C72: Accreditation - equipment | E72: C | F72: 100_100100_6090_56400_819 | K72: =G72+J72 -> 0
A73: College President | C73: Accreditation | D73: Dues, Membership | E73: C | F73: Multiple account numbers | G73: =SUM(G66:G72) -> 32159 | H73: =SUM(H66:H72) -> 54864 | I73: =SUM(I66:I72) -> 34926 | J73: =SUM(J66:J72) -> -13308 | K73: =G73+J73 -> 18851
A74: VP Admin. Services | B74: Michael Renzi | C74: Categorical Program: Transfer Out, Fringe Benefits | E74: C | F74: 100_103203_7310_57300_819 | G74: 468710 | H74: 468710 | I74: 468710 | K74: =G74+J74 -> 468710
A75: VP Admin. Services | B75: Michael Renzi | C75: Financial Aid Match: SEOG, Fed Work Study | E75: C | F75: 100_103204_7310_57300_819 | G75: 89345 | H75: 89345 | I75: 0 | K75: =G75+J75 -> 89345
A76: VP Admin. Services | B76: Ron Smith | C76: HigherOne | D76: Increase in cost | E76: F | F76: 100_102000_6490_55160_819 | G76: 2500 | H76: 2500 | I76: 2625 | J76: 125 | K76: =G76+J76 -> 2625
A77: VP Admin. Services | B77: Ron Smith | C77: Astra Schedule | E77: A | F77: 100_103209_6010_55500_819 | G77: 9950 | H77: 19057 | I77: 0 | K77: =G77+J77 -> 9950
A78: VP Admin. Services | C78: LaserFiche Avante | E78: A | F78: 100_103209_6010_55500_819 | G78: 8160 | K78: =G78+J78 -> 8160
A79: VP Admin. Services | C79: FormFusion | D79: Increase in cost | E79: A | F79: 100_103209_6010_55500_819 | G79: 949 | J79: 38 | K79: =G79+J79 -> 987
A80: VP Admin. Services | B80: Ron Smith | C80: Curricunet | E80: A | F80: 100_101000_6010_55160_819 | G80: 7800 | H80: 7800 | I80: 7800 | K80: =G80+J80 -> 7800
A81: VP Admin. Services | C81: Curricunet (Governet) Meta upgrade - one time | E81: A | F81: 100_101000_6010_55160_819 | G81: 0 | H81: 0 | I81: 0 | J81: 15000 | K81: =G81+J81 -> 15000
A82: VP Admin. Services | B82: Michael Renzi | C82: SARS Software Products -Counseling Sched System | E82: A | F82: 100_103206_6150_55500_819 | G82: 6500 | H82: 6500 | I82: 0 | K82: =G82+J82 -> 6500
A83: VP Admin. Services | C83: Angel | E83: A | F83: 100_103207_6150_55500_819 | G83: 82626 | H83: 82626 | I83: 82626 | K83: =G83+J83 -> 82626
A84: VP Admin. Services | C84: CCCApply / BOGS (Student-Right-to-know) | D84: State funded | E84: A | F84: 100_103208_6150_55500_819 | G84: 15609 | H84: 15609 | I84: 11400 | J84: -15609 | K84: =G84+J84 -> 0
A85: Campbell Center | C85: Campbell Center Lease | D85: move to college's oper. budget | F85: 100_131000_6470_55520_819 | G85: 34000 | H85: 34000 | I85: 34000 | J85: -34000 | K85: =G85+J85 -> 0
B86: Michael Renzi | C86: NISOD-Salary | F86: 100_119303_6750_51450_819 | G86: 4400 | J86: -4400 | K86: =G86+J86 -> 0
C87: NISOD-Food Services | F87: 100_119303_6750_55115_819 | G87: 1100 | H87: 5500 | I87: 2206 | J87: -1100 | K87: =G87+J87 -> 0
C88: NISOD-Travel for faculty to go to Texas | F88: 100_119303_6750_55200_819 | G88: 3300 | H88: 3300 | J88: -3300 | K88: =G88+J88 -> 0
A89: Senates/ VP of Admin. Services | C89: Professional Development | D89: move to college's oper. budget | F89: Multiple account numbers | G89: =SUM(G86:G88) -> 8800 | H89: =SUM(H86:H88) -> 8800 | I89: =SUM(I86:I88) -> 2206 | J89: =SUM(J86:J88) -> -8800 | K89: =G89+J89 -> 0 | L89: =SUM(G90,J90) -> 933339
F90: Total West Valley College | G90: =SUM(G53,G57:G64,G73:G85,G89) -> 986992 | H90: =SUM(H53,H57:H64,H73:H85,H89) -> 1009695 | I90: =SUM(I53,I57:I64,I73:I85,I89) -> 815532 | J90: =SUM(J53,J57:J64,J73:J85,J89) -> -53653 | K90: =SUM(K53,K57:K64,K73:K85,K89) -> 933339
A94: DISTRICT WIDE
A95: Responsibility | B95: Contact Info. | C95: Fixed Cost Description | D95: Explanation for Adjustments | E95: Criteria | F95: Account Number | G95: Final Budget 2013-14 | H95: Working Budget 2013-14 | I95: Actuals 2013-14 as of 2/28/14 | J95: Budget Adjust. Incr / (Decr) | K95: Tent Budget 2014-15
A96: VC Admin Serv | B96: Linda Francis | C96: Cal Grant Interest Payment | E96: C | F96: 100_304170_6720_55185_819 | G96: 2000 | H96: 2000 | I96: 1666 | K96: =G96+J96 -> 2000
A97: VC Admin Serv | B97: Linda Francis | C97: NDSL Collection Admin Costs (Perkins Loans) | D97: Realign budget per actual | E97: F | F97: 100_304170_6720_55185_819 | G97: 2500 | H97: 2500 | I97: 2218 | K97: =G97+J97 -> 2500
A98: VC Admin Serv | B98: Linda Francis | C98: Mngr/Conf/Supr SERP Premium 5 of 5 yrs | D98: 5 yr contract completed | E98: D | F98: 100_304168_6740_53710_819 | G98: 193709 | H98: 193709 | I98: =VLOOKUP(F98,'[1]Cognos Feb 14, 2014'!$A:$I,7) -> 193708.68 | J98: -193709 | K98: =G98+J98 -> 0
C99: Utilities, Mission College - Electricity | F99: 100_304020_6570_55800_819 | G99: 607482 | H99: 607482 | I99: 436691 | K99: =G99+J99 -> 607482
C100: Utilities, Mission College - Gas | F100: 100_304020_6570_55811_819 | G100: 148560 | H100: 148560 | I100: =VLOOKUP(F100,'[1]Cognos Feb 14, 2014'!$A:$I,7) -> 103427.72 | K100: =G100+J100 -> 148560
C101: Utilities, Mission College - Trash | F101: 100_304020_6570_55820_819 | G101: 36515.5 | H101: 36516 | I101: 14600 | K101: =G101+J101 -> 36515.5
C102: Utilities, Mission College - Water | F102: 100_304020_6570_55840_819 | G102: 85236 | H102: 85236 | I102: 59213 | K102: =G102+J102 -> 85236
C103: Utilities, Mission College - Sewer | F103: 100_304020_6570_55850_819 | G103: 29964 | H103: 29964 | I103: 15947 | K103: =G103+J103 -> 29964
A104: VC Admin Serv | B104: Linda Francis | C104: Utilities, Mission College | D104: Realign budget per actual | E104: E | F104: Multiple account numbers | G104: =SUM(G99:G103) -> 907757.5 | H104: =SUM(H99:H103) -> 907758 | I104: =SUM(I99:I103) -> 629878.72 | J104: =SUM(J99:J103) -> 0 | K104: =G104+J104 -> 907757.5
...

Sheet 1314A 071013
B1: MISSION COLLEGE | D1: MISSION COLLEGE
B2: Budget | I2: Final Budget | J2: 0.92307692 | K2: Actual Exp | M2: Available | N2: 13/14 | O2: Budget Adjust. | P2: Final Budget | Q2: Budget Adjust.
B3: Responsibility | C3: Contact Info. | D3: Fixed Cost Description | F3: Explanation for Adjustments | G3: Criteria | H3: Account Number | I3: 2012-13 | J3: Working Bud | K3: as of 7/10/13 | L3: Encumb. | M3: Budget | N3: Tnt. Budget | O3: Incr / (Decr) | P3: 2013-14 | Q3: Incr/(Decr)
D4: Academic Senate - Supplies/Materials | H4: 100_206200_6750_54210_819 | I4: 1000 | J4: =VLOOKUP(H4,'Datetel Jul 10, 2013'!A:F,6,0) -> 372 | K4: =VLOOKUP(H4,'Datetel Jul 10, 2013'!A:G,7,0) -> 371.39 | L4: =VLOOKUP(H4,'Datetel Jul 10, 2013'!A:I,8,0) -> 0 | M4: =J4-K4-L4 -> 0.61
D5: Academic Senate - Travel & Conference | H5: 100_206200_6750_55200_819 | I5: 3000 | J5: =VLOOKUP(H5,'Datetel Jul 10, 2013'!A:F,6,0)+SUM('Datetel Jul 10, 2013'!F139:F143) -> 3628 | K5: =VLOOKUP(H5,'Datetel Jul 10, 2013'!A:G,7,0) -> 2717.25 | L5: =VLOOKUP(H5,'Datetel Jul 10, 2013'!A:I,8,0) -> 0 | M5: =J5-K5-L5 -> 910.75
B6: Senates | C6: Worku Negash | D6: Academic Senate | G6: C | H6: Multiple account numbers | I6: 4000 | J6: =SUM(J4:J5) -> 4000 | K6: =SUM(K4:K5) -> 3088.64 | L6: =SUM(L4:L5) -> 0 | M6: =J6-K6-L6 -> 911.36 | N6: 4000 | P6: =N6+O6 -> 4000 | Q6: =P6-I6 -> 0
D7: Classified Senate - Hrly classified Salary | H7: 100_206300_6750_52310_819 | I7: 1000 | J7: =VLOOKUP(H7,'Datetel Jul 10, 2013'!A:F,6,0) -> 0 | K7: =VLOOKUP(H7,'Datetel Jul 10, 2013'!A:G,7,0) -> 0 | L7: =VLOOKUP(H7,'Datetel Jul 10, 2013'!A:I,8,0) -> 0 | M7: =J7-K7-L7 -> 0 | P7: =N7+O7 -> 0 | Q7: =O7+P7 -> 0
D8: Classified Senate - Supplies/Materials | H8: 100_206300_6750_54210_819 | I8: 500 | J8: =VLOOKUP(H8,'Datetel Jul 10, 2013'!A:F,6,0) -> 300 | K8: =VLOOKUP(H8,'Datetel Jul 10, 2013'!A:G,7,0) -> 204.23 | L8: =VLOOKUP(H8,'Datetel Jul 10, 2013'!A:I,8,0) -> 0 | M8: =J8-K8-L8 -> 95.77 | P8: =N8+O8 -> 0 | Q8: =O8+P8 -> 0
D9: Classified Senate - Food Services | H9: 100_206300_6750_55115_819 | I9: 1500 | J9: =VLOOKUP(H9,'Datetel Jul 10, 2013'!A:F,6,0) -> 1000 | K9: =VLOOKUP(H9,'Datetel Jul 10, 2013'!A:G,7,0) -> 800 | L9: =VLOOKUP(H9,'Datetel Jul 10, 2013'!A:I,8,0) -> 0 | M9: =J9-K9-L9 -> 200 | P9: =N9+O9 -> 0 | Q9: =O9+P9 -> 0
D10: Classified Senate - Travel & Conference | H10: 100_206300_6750_55205_819 | I10: 1500 | J10: =VLOOKUP(H10,'Datetel Jul 10, 2013'!A:F,6,0) -> 3247 | K10: =VLOOKUP(H10,'Datetel Jul 10, 2013'!A:G,7,0) -> 3246.43 | L10: =VLOOKUP(H10,'Datetel Jul 10, 2013'!A:I,8,0) -> 0 | M10: =J10-K10-L10 -> 0.57 | P10: =N10+O10 -> 0 | Q10: =O10+P10 -> 0
B11: Senates | C11: Worku Negash | D11: Classified Senate | G11: C | H11: Multiple account numbers | I11: 4500 | J11: =SUM(J7:J10) -> 4547 | K11: =SUM(K7:K10) -> 4250.66 | L11: =SUM(L7:L10) -> 0 | M11: =J11-K11-L11 -> 296.34 | N11: 4500 | P11: =N11+O11 -> 4500 | Q11: =P11-I11 -> 0
B12: Senate | D12: Academic Senate President Stipend | G12: C | H12: 100_206200_6750_51450_819 | N12: 5000 | P12: =N12+O12 -> 5000 | Q12: =P12-I12 -> 5000
B13: Faculty Travel | C13: Worku Negash | D13: Faculty Travel & Conference | G13: E | H13: 100_290100_6600_55210_819 | I13: 28800 | J13: =VLOOKUP(H13,'Datetel Jul 10, 2013'!A:F,6,0) -> 28800 | K13: =VLOOKUP(H13,'Datetel Jul 10, 2013'!A:G,7,0) -> 22961.92 | L13: =VLOOKUP(H13,'Datetel Jul 10, 2013'!A:I,8,0) -> 0 | M13: =J13-K13-L13 -> 5838.08 | N13: 29000 | P13: =N13+O13 -> 29000 | Q13: =P13-I13 -> 200
B14: VP Admin. Services | C14: Worku Negash | D14: Tenure Faculty | G14: E | H14: 100_220910_4900_51310_819 | I14: 16500 | J14: =VLOOKUP(H14,'Datetel Jul 10, 2013'!A:F,6,0) -> 16500 | K14: =VLOOKUP(H14,'Datetel Jul 10, 2013'!A:G,7,0) -> 16500 | L14: =VLOOKUP(H14,'Datetel Jul 10, 2013'!A:I,8,0) -> 0 | M14: =J14-K14-L14 -> 0 | N14: 0 | P14: =N14+O14 -> 0 | Q14: =P14-I14 -> -16500
B15: Dean of Instr, Lib. St/LA | C15: Worku Negash | D15: Tricore, Link + Consortium, Library Maintenance | G15: A | H15: 100_290200_6110_55510_819 | I15: 37594 | J15: =VLOOKUP(H15,'Datetel Jul 10, 2013'!A:F,6,0) -> 37971 | K15: =VLOOKUP(H15,'Datetel Jul 10, 2013'!A:G,7,0) -> 37812.03 | L15: =VLOOKUP(H15,'Datetel Jul 10, 2013'!A:I,8,0) -> 53.97 | M15: =J15-K15-L15 -> 105 | N15: 37594 | P15: =N15+O15 -> 37594 | Q15: =P15-I15 -> 0
B16: Dean of Instr, Lib. St/LA | D16: Turnkey Server Migration (One-Time) | G16: A | H16: 100_230000_6120_55510_819 | I16: 4877 | J16: =VLOOKUP(H16,'Datetel Jul 10, 2013'!A:F,6,0) -> 4500 | K16: =VLOOKUP(H16,'Datetel Jul 10, 2013'!A:G,7,0) -> 4500 | L16: =VLOOKUP(H16,'Datetel Jul 10, 2013'!A:I,8,0) -> 0 | M16: =J16-K16-L16 -> 0 | N16: 0 | P16: =N16+O16 -> 0 | Q16: =P16-I16 -> -4877
B17: VP Admin. Services | C17: Worku Negash | D17: Insurance for PE and Athletics Students | G17: C, D | H17: 100_220000_6440_55940_819 | I17: 73711 | J17: =VLOOKUP(H17,'Datetel Jul 10, 2013'!A:F,6,0) -> 73711 | K17: =VLOOKUP(H17,'Datetel Jul 10, 2013'!A:G,7,0) -> 72921.12 | L17: =VLOOKUP(H17,'Datetel Jul 10, 2013'!A:I,8,0) -> 0 | M17: =J17-K17-L17 -> 789.88 | N17: 73711 | P17: =N17+O17 -> 73711 | Q17: =P17-I17 -> 0
B18: VP Admin. Services | C18: Worku Negash | D18: Coaches Stipends (Negotiated Item) | G18: E | H18: 100_220000_6770_51450_819 | I18: 15000 | J18: =VLOOKUP(H18,'Datetel Jul 10, 2013'!A:F,6,0)+SUM('Datetel Jul 10, 2013'!F152:F156) -> 14487 | K18: =SUM('Datetel Jul 10, 2013'!G151:G156) -> 14416.9 | L18: =VLOOKUP(H18,'Datetel Jul 10, 2013'!A:I,8,0) -> 0 | M18: =J18-K18-L18 -> 70.1 | N18: 15000 | P18: =N18+O18 -> 15000 | Q18: =P18-I18 -> 0
B19: College President | D19: Accreditation - Supplies/Materials | G19: C | H19: 100_200700_6090_51450_819 | I19: 0 | J19: =VLOOKUP(H19,'Datetel Jul 10, 2013'!A:F,6,0) -> 11686 | K19: =VLOOKUP(H19,'Datetel Jul 10, 2013'!A:G,7,0) -> 12291.36 | L19: =VLOOKUP(H19,'Datetel Jul 10, 2013'!A:I,8,0) -> 0 | M19: =J19-K19-L19 -> -605.36 | N19: 0 | O19: 8500 | P19: =N19+O19 -> 8500 | Q19: =P19-I19 -> 8500
B20: College President | D20: Accreditation - Supplies/Materials | G20: C | H20: 100_200700_6090_54210_819 | I20: 10000 | J20: =VLOOKUP(H20,'Datetel Jul 10, 2013'!A:F,6,0) -> 1500 | K20: =VLOOKUP(H20,'Datetel Jul 10, 2013'!A:G,7,0) -> 183.64 | L20: =VLOOKUP(H20,'Datetel Jul 10, 2013'!A:I,8,0) -> 0 | M20: =J20-K20-L20 -> 1316.36 | N20: 10000 | O20: -8500 | P20: =N20+O20 -> 1500 | Q20: =P20-I20 -> -8500
B21: College President | D21: Accreditation - PT Faculty Non Teaching Stipend | G21: C | H21: 100_200700_6090_51450_819 | J21: =VLOOKUP(H21,'Datetel Jul 10, 2013'!A:F,6,0)+1327 -> 13013 | K21: =VLOOKUP(H21,'Datetel Jul 10, 2013'!A:G,7,0) -> 12291.36 | L21: =VLOOKUP(H21,'Datetel Jul 10, 2013'!A:I,8,0) -> 0 | M21: =J21-K21-L21 -> 721.64 | N21: 0 | P21: =N21+O21 -> 0 | Q21: =P21-I21 -> 0
B22: College President | C22: Worku Negash | D22: Accreditation - Dues, Memberships & Fees | F22: Incr due to Evaluation visit | G22: C | H22: 100_200700_6090_55910_819 | I22: 17453 | J22: =VLOOKUP(H22,'Datetel Jul 10, 2013'!A:F,6,0) -> 17453 | K22: =VLOOKUP(H22,'Datetel Jul 10, 2013'!A:G,7,0)+'Datetel Jul 10, 2013'!G133+'Datetel Jul 10, 2013'!G134+'Datetel Jul 10, 2013'!G135+'Datetel Jul 10, 2013'!G136 -> 16964.86 | L22: =VLOOKUP(H22,'Datetel Jul 10, 2013'!A:I,8,0) -> 0 | M22: =J22-K22-L22 -> 488.14 | N22: 17453 | O22: =19137-N22 -> 1684 | P22: =N22+O22 -> 19137 | Q22: =P22-I22 -> 1684
B23: VP Admin. Services | C23: Linda Francis/Virginia | D23: Categorical Program: Transfer Out, Fringe Benefits | G23: C | H23: 100_220001_7310_57300_819 | I23: 340397 | J23: =VLOOKUP(H23,'Datetel Jul 10, 2013'!A:F,6,0) -> 340397 | K23: =VLOOKUP(H23,'Datetel Jul 10, 2013'!A:G,7,0) -> 320394.85 | L23: =VLOOKUP(H23,'Datetel Jul 10, 2013'!A:I,8,0) -> 0 | M23: =J23-K23-L23 -> 20002.15 | N23: 340397 | P23: =N23+O23 -> 340397 | Q23: =P23-I23 -> 0
B24: VP Admin. Services | C24: Linda Francis/Virginia | D24: Financial Aid Match: SEOG & Fed Work Study | G24: C | H24: 100_220002_7310_57300_819 | I24: 88013 | J24: =VLOOKUP(H24,'Datetel Jul 10, 2013'!A:F,6,0) -> 88013 | K24: =VLOOKUP(H24,'Datetel Jul 10, 2013'!A:G,7,0) -> 0 | L24: =VLOOKUP(H24,'Datetel Jul 10, 2013'!A:I,8,0) -> 0 | M24: =J24-K24-L24 -> 88013 | N24: 88013 | O24: =81876-88013 -> -6137 | P24: =N24+O24 -> 81876 | Q24: =P24-I24 -> -6137
B25: VP Admin. Services | D25: HigherOne | G25: D | H25: 100_220900_6490_55160_819 | I25: 2500 | J25: =VLOOKUP(H25,'Datetel Jul 10, 2013'!A:F,6,0) -> 2500 | K25: =VLOOKUP(H25,'Datetel Jul 10, 2013'!A:G,7,0) -> 2500 | L25: =VLOOKUP(H25,'Datetel Jul 10, 2013'!A:I,8,0) -> 0 | M25: =J25-K25-L25 -> 0 | N25: 2500 | P25: =N25+O25 -> 2500 | Q25: =P25-I25 -> 0
B26: VP Admin. Services | C26: Worku Negash | D26: Astra Schedule/LaserFiche Avante/FormFusion | G26: A | H26: 100_220007_6010_55500_819 | I26: 19057 | J26: =VLOOKUP(H26,'Datetel Jul 10, 2013'!A:F,6,0) -> 19057 | K26: =VLOOKUP(H26,'Datetel Jul 10, 2013'!A:G,7,0) -> 18110 | L26: =VLOOKUP(H26,'Datetel Jul 10, 2013'!A:I,8,0) -> 0 | M26: =J26-K26-L26 -> 947 | N26: 19057 | P26: =N26+O26 -> 19057 | Q26: =P26-I26 -> 0
B27: VP Admin. Services | C27: Worku Negash | D27: Curricunet | F27: Incr. MC for SLO module | G27: A | H27: 100_220000_6010_55160_819 | I27: 7479 | J27: =VLOOKUP(H27,'Datetel Jul 10, 2013'!A:F,6,0) -> 7479 | K27: =VLOOKUP(H27,'Datetel Jul 10, 2013'!A:G,7,0) -> 7479 | L27: =VLOOKUP(H27,'Datetel Jul 10, 2013'!A:I,8,0) -> 0 | M27: =J27-K27-L27 -> 0 | N27: 7479 | O27: 4321 | P27: =N27+O27 -> 11800 | Q27: =P27-I27 -> 4321
B28: VP Admin. Services | C28: Ron Smith | D28: SARS Software Products -Counseling Sched System | G28: A | H28: 100_220004_6150_55500_819 | I28: 6500 | J28: =VLOOKUP(H28,'Datetel Jul 10, 2013'!A:F,6,0) -> 6453 | K28: =VLOOKUP(H28,'Datetel Jul 10, 2013'!A:G,7,0) -> 6255 | L28: =VLOOKUP(H28,'Datetel Jul 10, 2013'!A:I,8,0) -> 0 | M28: =J28-K28-L28 -> 198 | N28: 6500 | P28: =N28+O28 -> 6500 | Q28: =P28-I28 -> 0
B29: VP Admin. Services | C29: Ron Smith | D29: Angel | F29: Renewal rate adj for 2 yr contr. | G29: A | H29: 100_220005_6150_55500_819 | I29: 78691 | J29: =VLOOKUP(H29,'Datetel Jul 10, 2013'!A:F,6,0) -> 78691 | K29: =VLOOKUP(H29,'Datetel Jul 10, 2013'!A:G,7,0) -> 78691.63 | L29: =VLOOKUP(H29,'Datetel Jul 10, 2013'!A:I,8,0) -> 0 | M29: =J29-K29-L29 -> -0.63 | N29: 83413 | O29: =(165252/2)-83413 -> -787 | P29: =N29+O29 -> 82626 | Q29: =P29-I29 -> 3935
B30: VP Admin. Services | C30: Ron Smith | D30: CCCApply / BOGS (Student-Right-to-know) | G30: A | H30: 100_220006_6150_55500_819 | I30: 15609 | J30: =VLOOKUP(H30,'Datetel Jul 10, 2013'!A:F,6,0) -> 15609 | K30: =VLOOKUP(H30,'Datetel Jul 10, 2013'!A:G,7,0) -> 11514.1 | L30: =VLOOKUP(H30,'Datetel Jul 10, 2013'!A:I,8,0) -> 4099.9 | M30: =J30-K30-L30 -> -5 | N30: 15609 | P30: =N30+O30 -> 15609 | Q30: =P30-I30 -> 0
H31: Total Mission College | I31: =SUM(I6,I11,I12:I30) -> 770681 | J31: =SUM(J6,J11,J13:J30) -> 786367 | K31: =SUM(K6,K11,K13:K30) -> 663127.07 | L31: =SUM(L6,L11,L13:L30) -> 4153.87 | M31: =SUM(M6,M11,M13:M30) -> 119086.06 | N31: =SUM(N6,N11,N12:N30) -> 759226 | O31: =SUM(O6,O11,O12:O30) -> -919 | P31: =SUM(P6,P11,P12:P30) -> 758307 | Q31: =SUM(Q6,Q11,Q12:Q30) -> -12374
M32: 412305
B33: WEST VALLEY COLLEGE | D33: WEST VALLEY COLLEGE
B34: Budget | I34: 0.92307692 | J34: 0.92307692 | K34: Actual Exp | M34: Available | N34: 13/14 | O34: Budget Adjust. | P34: 13/14 | Q34: 13/14
B35: Responsibility | C35: Contact Info. | D35: Fixed Cost Description | E35: Detail Description | F35: Explanation for Adjustments | G35: Criteria | H35: Account Number | I35: Adopt Bud | J35: Working Bud | K35: as of 7/10/13 | L35: Encumb. | M35: Budget | N35: Tnt. Budget | O35: Incr / (Decr) | P35: Adopt Budget | Q35: Adopt Budget
D36: Academic Senate | H36: 100_119304_6750_55115_819 | I36: 1100 | J36: =VLOOKUP(H36,'Datetel Jul 10, 2013'!A:F,6,0) -> 1100 | K36: =VLOOKUP(H36,'Datetel Jul 10, 2013'!A:G,7,0) -> 0 | L36: =VLOOKUP(H36,'Datetel Jul 10, 2013'!A:I,8,0) -> 0 | M36: =J36-K36-L36 -> 1100
D37: Academic Senate | H37: 100_119304_6750_55200_819 | I37: 3300 | J37: =VLOOKUP(H37,'Datetel Jul 10, 2013'!A:F,6,0) -> 3300 | K37: =VLOOKUP(H37,'Datetel Jul 10, 2013'!A:G,7,0) -> 0 | L37: =VLOOKUP(H37,'Datetel Jul 10, 2013'!A:I,8,0) -> 0 | M37: =J37-K37-L37 -> 3300
B38: Senates | C38: Michael Renzi | D38: Academic Senate | G38: C | H38: Multiple account numbers | I38: 4400 | J38: =SUM(J36:J37) -> 4400 | K38: =SUM(K36:K37) -> 0 | L38: =SUM(L36:L37) -> 0 | M38: =J38-K38-L38 -> 4400 | N38: 4400 | P38: =N38+O38 -> 4400 | Q38: =P38-I38 -> 0
D39: Classified Senate | H39: 100_119305_6750_55115_819 | I39: 660 | J39: =VLOOKUP(H39,'Datetel Jul 10, 2013'!A:F,6,0) -> 3660 | K39: =VLOOKUP(H39,'Datetel Jul 10, 2013'!A:G,7,0) -> 3033.84 | L39: =VLOOKUP(H39,'Datetel Jul 10, 2013'!A:I,8,0) -> 0 | M39: =J39-K39-L39 -> 626.16 | P39: =N39+O39 -> 0 | Q39: =P39-I39 -> -660
D40: Classified Senate | H40: 100_119305_6750_55160_819 | I40: 440 | J40: =VLOOKUP(H40,'Datetel Jul 10, 2013'!A:F,6,0) -> 440 | K40: =VLOOKUP(H40,'Datetel Jul 10, 2013'!A:G,7,0) -> 440.02 | L40: =VLOOKUP(H40,'Datetel Jul 10, 2013'!A:I,8,0) -> 0 | M40: =J40-K40-L40 -> -0.02 | P40: =N40+O40 -> 0 | Q40: =P40-I40 -> -440
D41: Classified Senate | H41: 100_119305_6750_55200_819 | I41: 3300 | J41: =VLOOKUP(H41,'Datetel Jul 10, 2013'!A:F,6,0) -> 300 | K41: =VLOOKUP(H41,'Datetel Jul 10, 2013'!A:G,7,0) -> 274.48 | L41: =VLOOKUP(H41,'Datetel Jul 10, 2013'!A:I,8,0) -> 0 | M41: =J41-K41-L41 -> 25.52 | P41: =N41+O41 -> 0 | Q41: =P41-I41 -> -3300
B42: Senates | C42: Michael Renzi | D42: Classified Senate | G42: C | H42: Multiple account numbers | I42: 4400 | J42: =SUM(J39:J41) -> 4400 | K42: =SUM(K39:K41) -> 3748.34 | L42: =SUM(L39:L41) -> 0 | M42: =J42-K42-L42 -> 651.66 | N42: 4400 | P42: =N42+O42 -> 4400 | Q42: =P42-I42 -> 0
B43: Senate | D43: Academic Senate President Stipend | G43: C | H43: 100_119304_6750_51450_819 | N43: 5000 | P43: =N43+O43 -> 5000 | Q43: =P43-I43 -> 5000
B44: VP Admin. Services | C44: Michael Renzi | D44: Faculty Travel & Conference | G44: E | H44: 100_103201_6010_55210_819 | I44: 33200 | J44: 33200 | K44: =SUM('Datetel Jul 10, 2013'!G16:G55) -> 12426.09 | L44: =VLOOKUP(H44,'Datetel Jul 10, 2013'!A:I,8,0) -> 0 | M44: =J44-K44-L44 -> 20773.91 | N44: 33200 | P44: =N44+O44 -> 33200 | Q44: =P44-I44 -> 0
B45: VP Admin. Services | C45: Michael Renzi | D45: Tenure Faculty | G45: E | H45: 100_103251_4900_51310_819 | I45: 27500 | J45: =VLOOKUP(H45,'Datetel Jul 10, 2013'!A:F,6,0) -> 27500 | K45: =VLOOKUP(H45,'Datetel Jul 10, 2013'!A:G,7,0) -> 27500 | L45: =VLOOKUP(H45,'Datetel Jul 10, 2013'!A:I,8,0) -> 0 | M45: =J45-K45-L45 -> 0 | N45: 0 | P45: =N45+O45 -> 0 | Q45: =P45-I45 -> -27500
B46: Dean Learning Center | C46: Michael Renzi | D46: Tricore, Link + Consortium, Library Maintenance | E46: Consolidated budget for Link+ and other costs | G46: A | H46: 100_106100_6120_55510_819 | I46: 40155 | J46: 40155 | K46: =VLOOKUP(H46,'Datetel Jul 10, 2013'!A:G,7,0)-K47 -> 39679.56 | L46: =VLOOKUP(H46,'Datetel Jul 10, 2013'!A:I,8,0) -> 830.44 | M46: =J46-K46-L46 -> -355 | N46: 40155 | P46: =N46+O46 -> 40155 | Q46: =P46-I46 -> 0
B47: Dean Learning Center | C47: Michael Renzi | D47: Turnkey Server Migration (One-Time) | E47: Consolidated budget for Link+ and other costs | G47: A | H47: 100_106100_6120_55510_819 | I47: 4877 | J47: 4877 | K47: 4500 | L47: 0 | M47: =J47-K47-L47 -> 377 | N47: 0 | P47: =N47+O47 -> 0 | Q47: =P47-I47 -> -4877
B48: Physical Education Division | C48: Michael Renzi | D48: Athletics Insurance for PE and Athletics Students | E48: Base from Final Budget. Increased from FY11 | G48: C, D | H48: 100_115200_6960_55940_819 | I48: 110568 | J48: =VLOOKUP(H48,'Datetel Jul 10, 2013'!A:F,6,0) -> 109382 | K48: =VLOOKUP(H48,'Datetel Jul 10, 2013'!A:G,7,0) -> 109381.68 | L48: =VLOOKUP(H48,'Datetel Jul 10, 2013'!A:I,8,0) -> 0 | M48: =J48-K48-L48 -> 0.32 | N48: 110568 | P48: =N48+O48 -> 110568 | Q48: =P48-I48 -> 0
D49: Student Insurance | H49: 100_103200_6440_55940_819
B50: Physical Education Division | C50: Michael Renzi | D50: Coaches Stipends (Negotiated Item) | G50: E | H50: 100_115200_6960_51450_819 | I50: 24625 | J50: 25811 | K50: =SUM('Datetel Jul 10, 2013'!G64:G70) -> 24377.14 | L50: =VLOOKUP(H50,'Datetel Jul 10, 2013'!A:I,8,0) -> 0 | M50: =J50-K50-L50 -> 1433.86 | N50: 24625 | P50: =N50+O50 -> 24625 | Q50: =P50-I50 -> 0
B51: College President | C51: Michael Renzi | D51: Accreditation - Dues, Memberships & Fees | F51: Incr fee & Evaluation visit | G51: C | H51: 100_100100_6090_55910_819 | I51: 18953 | J51: =VLOOKUP(H51,'Datetel Jul 10, 2013'!A:F,6,0) -> 18940 | K51: =VLOOKUP(H51,'Datetel Jul 10, 2013'!A:G,7,0) -> 18326 | L51: =VLOOKUP(H51,'Datetel Jul 10, 2013'!A:I,8,0) -> 0 | M51: =J51-K51-L51 -> 614 | N51: 19137 | O51: =22159-19137 -> 3022 | P51: =N51+O51 -> 22159 | Q51: =P51-I51 -> 3206
B52: College President | D52: Accreditation - Hourly Classified | G52: C | H52: 100_100100_6090_52350_819 | J52: 7299 | K52: =SUM('Datetel Jul 10, 2013'!G3:G9) -> 10948.32 | L52: =VLOOKUP(H52,'Datetel Jul 10, 2013'!A:I,8,0) -> 0 | M52: =J52-K52-L52 -> -3649.32 | N52: 8650 | P52: =N52+O52 -> 8650 | Q52: =P52-I52 -> 8650
B53: College President | C53: Michael Renzi | D53: Accreditation - Supplies/Materials | G53: C | H53: 100_100100_6090_54210_819 | I53: 10000 | J53: =VLOOKUP(H53,'Datetel Jul 10, 2013'!A:F,6,0) -> 1374 | K53: =VLOOKUP(H53,'Datetel Jul 10, 2013'!A:G,7,0) -> 955.06 | L53: =VLOOKUP(H53,'Datetel Jul 10, 2013'!A:I,8,0) -> 0.13 | M53: =J53-K53-L53 -> 418.81 | N53: 1350 | P53: =N53+O53 -> 1350 | Q53: =P53-I53 -> -8650
B54: College President | C54: Michael Renzi | D54: Accreditation - equipment | G54: C | H54: 100_100100_6090_56400_819 | J54: 1340 | K54: =VLOOKUP(H54,'Datetel Jul 10, 2013'!A:G,7,0) -> 1330.92 | M54: =J54-K54-L54 -> 9.08 | N54: 0 | P54: =N54+O54 -> 0 | Q54: =P54-I54 -> 0
B55: VP Admin. Services | C55: Linda Francis/Virginia | D55: Categorical Program: Transfer Out, Fringe Benefits | G55: C | H55: 100_103203_7310_57300_819 | I55: 468710 | J55: =VLOOKUP(H55,'Datetel Jul 10, 2013'!A:F,6,0) -> 468710 | K55: =VLOOKUP(H55,'Datetel Jul 10, 2013'!A:G,7,0) -> 468710 | L55: =VLOOKUP(H55,'Datetel Jul 10, 2013'!A:I,8,0) -> 0 | M55: =J55-K55-L55 -> 0 | N55: 468710 | P55: =N55+O55 -> 468710 | Q55: =P55-I55 -> 0
B56: VP Admin. Services | C56: Linda Francis/Virginia | D56: Financial Aid Match: SEOG, Fed Work Study | G56: C | H56: 100_103204_7310_57300_819 | I56: 89345 | J56: =VLOOKUP(H56,'Datetel Jul 10, 2013'!A:F,6,0) -> 89345 | K56: =VLOOKUP(H56,'Datetel Jul 10, 2013'!A:G,7,0) -> 0 | L56: =VLOOKUP(H56,'Datetel Jul 10, 2013'!A:I,8,0) -> 0 | M56: =J56-K56-L56 -> 89345 | N56: 89345 | P56: =N56+O56 -> 89345 | Q56: =P56-I56 -> 0
B57: VP Admin. Services | D57: HigherOne | G57: D | H57: 100_102000_6490_55160_819 | I57: 2500 | J57: =VLOOKUP(H57,'Datetel Jul 10, 2013'!A:F,6,0) -> 2500 | K57: =VLOOKUP(H57,'Datetel Jul 10, 2013'!A:G,7,0) -> 2500 | L57: =VLOOKUP(H57,'Datetel Jul 10, 2013'!A:I,8,0) -> 0 | M57: =J57-K57-L57 -> 0 | N57: 2500 | P57: =N57+O57 -> 2500 | Q57: =P57-I57 -> 0
B58: VP Admin. Services | C58: Michael Renzi | D58: Astra Schedule/LaserFiche Avante/FormFusion | G58: A | H58: 100_103209_6010_55500_819 | I58: 19057 | J58: =VLOOKUP(H58,'Datetel Jul 10, 2013'!A:F,6,0) -> 19057 | K58: =VLOOKUP(H58,'Datetel Jul 10, 2013'!A:G,7,0) -> 18110 | L58: =VLOOKUP(H58,'Datetel Jul 10, 2013'!A:I,8,0) -> 0 | M58: =J58-K58-L58 -> 947 | N58: 19057 | P58: =N58+O58 -> 19057 | Q58: =P58-I58 -> 0
B59: VP Admin. Services | C59: Michael Renzi | D59: Curricunet | F59: Increase in contract | G59: A | H59: 100_101000_6010_55160_819 | I59: 7479 | J59: =VLOOKUP(H59,'Datetel Jul 10, 2013'!A:F,6,0) -> 7479 | K59: =VLOOKUP(H59,'Datetel Jul 10, 2013'!A:G,7,0) -> 7479 | L59: =VLOOKUP(H59,'Datetel Jul 10, 2013'!A:I,8,0) -> 0 | M59: =J59-K59-L59 -> 0 | N59: 7479 | O59: 321 | P59: =N59+O59 -> 7800 | Q59: =P59-I59 -> 321
B60: VP Admin. Services | C60: Ron Smith | D60: SARS Software Products -Counseling Sched System | G60: A | H60: 100_103206_6150_55500_819 | I60: 6500 | J60: =VLOOKUP(H60,'Datetel Jul 10, 2013'!A:F,6,0) -> 6500 | K60: =VLOOKUP(H60,'Datetel Jul 10, 2013'!A:G,7,0) -> 6255 | L60: =VLOOKUP(H60,'Datetel Jul 10, 2013'!A:I,8,0) -> 0 | M60: =J60-K60-L60 -> 245 | N60: 6500 | P60: =N60+O60 -> 6500 | Q60: =P60-I60 -> 0
B61: VP Admin. Services | C61: Ron Smith | D61: Angel | F61: Renewal rate adj for 2 yr contr. | G61: A | H61: 100_103207_6150_55500_819 | I61: 78691 | J61: =VLOOKUP(H61,'Datetel Jul 10, 2013'!A:F,6,0) -> 78691 | K61: =VLOOKUP(H61,'Datetel Jul 10, 2013'!A:G,7,0) -> 78690.63 | L61: =VLOOKUP(H61,'Datetel Jul 10, 2013'!A:I,8,0) -> 0 | M61: =J61-K61-L61 -> 0.37 | N61: 83413 | O61: =(165252/2)-83413 -> -787 | P61: =N61+O61 -> 82626 | Q61: =P61-I61 -> 3935
B62: VP Admin. Services | C62: Ron Smith | D62: CCCApply / BOGS (Student-Right-to-know) | G62: A | H62: 100_103208_6150_55500_819 | I62: 15609 | J62: =VLOOKUP(H62,'Datetel Jul 10, 2013'!A:F,6,0) -> 15609 | K62: =VLOOKUP(H62,'Datetel Jul 10, 2013'!A:G,7,0) -> 15614 | L62: =VLOOKUP(H62,'Datetel Jul 10, 2013'!A:I,8,0) -> 0 | M62: =J62-K62-L62 -> -5 | N62: 15609 | P62: =N62+O62 -> 15609 | Q62: =P62-I62 -> 0
B63: Campbell Center | C63: Michael Renzi | D63: Campbell Center Lease | G63: D | H63: 100_131000_6470_55520_819 | I63: 34000 | J63: =VLOOKUP(H63,'Datetel Jul 10, 2013'!A:F,6,0) -> 34000 | K63: =VLOOKUP(H63,'Datetel Jul 10, 2013'!A:G,7,0) -> 34000 | L63: =VLOOKUP(H63,'Datetel Jul 10, 2013'!A:I,8,0) -> 0 | M63: =J63-K63-L63 -> 0 | N63: 34000 | P63: =N63+O63 -> 34000 | Q63: =P63-I63 -> 0
D64: NISOD-Salary | H64: 100_119303_6750_51450_819 | I64: 4400 | J64: =VLOOKUP(H64,'Datetel Jul 10, 2013'!A:F,6,0) -> 699 | K64: =VLOOKUP(H64,'Datetel Jul 10, 2013'!A:G,7,0) -> 0 | L64: =VLOOKUP(H64,'Datetel Jul 10, 2013'!A:I,8,0) -> 0 | M64: =J64-K64-L64 -> 699 | N64: 4400 | P64: =N64+O64 -> 4400 | Q64: =P64-I64 -> 0
D65: NISOD-Food Services | H65: 100_119303_6750_55115_819 | I65: 1100 | J65: =VLOOKUP(H65,'Datetel Jul 10, 2013'!A:F,6,0) -> 5718 | K65: =VLOOKUP(H65,'Datetel Jul 10, 2013'!A:G,7,0) -> 5564.7 | L65: =VLOOKUP(H65,'Datetel Jul 10, 2013'!A:I,8,0) -> 0 | M65: =J65-K65-L65 -> 153.3 | N65: 1100 | P65: =N65+O65 -> 1100 | Q65: =P65-I65 -> 0
D66: NISOD-Travel for faculty to go to Texas | H66: 100_119303_6750_55200_819 | I66: 3300 | J66: =VLOOKUP(H66,'Datetel Jul 10, 2013'!A:F,6,0) -> 2383 | K66: =VLOOKUP(H66,'Datetel Jul 10, 2013'!A:G,7,0) -> 924.08 | L66: =VLOOKUP(H66,'Datetel Jul 10, 2013'!A:I,8,0) -> 0 | M66: =J66-K66-L66 -> 1458.92 | N66: 3300 | P66: =N66+O66 -> 3300 | Q66: =P66-I66 -> 0
B67: Senates/ VP of Admin. Services | C67: Michael Renzi | D67: Professional Development | G67: C | H67: Multiple account numbers | I67: 8800 | J67: =SUM(J64:J66) -> 8800 | K67: =SUM(K64:K66) -> 6488.78 | L67: =SUM(L64:L66) -> 0 | M67: =J67-K67-L67 -> 2311.22 | N67: 8800 | P67: =N67+O67 -> 8800 | Q67: =P67-I67 -> 0
H68: Total West Valley College | I68: =SUM(I38,I42,I43:I63,I67) -> 1009369 | J68: =SUM(J38,J42,J43:J63,J67) -> 1009369 | K68: =SUM(K38,K42,K43:K63,K67) -> 891020.52 | L68: =SUM(L38,L42,L43:L63,L67) -> 830.57 | M68: =SUM(M38,M42,M43:M63,M67) -> 117517.91 | N68: =SUM(N38,N42,N43:N63,N67) -> 986898 | O68: =SUM(O38,O42,O43:O63,O67) -> 2556 | P68: =SUM(P38,P42,P43:P63,P67) -> 989454 | Q68: =SUM(Q38,Q42,Q43:Q63,Q67) -> -19915
M69: =SUM(I68,L68) -> 1010199.6
B70: DISTRICT WIDE | D70: DISTRICT WIDE
B71: Budget | I71: 0.92307692 | J71: 0.92307692 | K71: Actual Exp | M71: Available | N71: 13/14 | O71: Budget Adjust. | P71: 13/14 | Q71: 13/14
B72: Responsibility | C72: Contact Info. | D72: Fixed Cost Description | F72: Explanation for Adjustments | G72: Criteria | H72: Account Number | I72: Adopt Bud | J72: Working Bud | K72: as of 7/10/13 | L72: Encumb. | M72: Budget | N72: Tnt. Budget | O72: Incr / (Decr) | P72: Adopt Budget | Q72: Adopt Budget
A73: DW | B73: VC Admin Serv | C73: Linda Francis | D73: Cal Grant Interest Payment | G73: C | H73: 100_304170_6720_55185_819 | I73: 4500 | J73: 4500 | K73: =VLOOKUP(H73,'Datetel Jul 10, 2013'!A:G,7,0)-K74 -> 4228.09 | L73: =VLOOKUP(H73,'Datetel Jul 10, 2013'!A:I,8,0) -> 271.97 | M73: =J73-K73-L73 -> -0.06 | N73: 2000 | P73: =N73+O73 -> 2000 | Q73: =P73-I73 -> -2500
A74: DW | B74: VC Admin Serv | C74: Linda Francis | D74: NDSL Collection Admin Costs (Perkins Loans) | F74: Realign budget per actual | G74: G | H74: 100_304170_6720_55185_819 | I74: 5000 | J74: 5000 | K74: 1341 | L74: 0 | M74: =J74-K74-L74 -> 3659 | N74: 5000 | O74: -2500 | P74: =N74+O74 -> 2500 | Q74: =P74-I74 -> -2500
A75: DW | B75: VC Admin Serv | C75: Linda Francis | D75: Faculty SERP Premium 5 of 5 yrs | G75: E | H75: 100_304168_5900_53710_819 | I75: 47825 | J75: =VLOOKUP(H75,'Datetel Jul 10, 2013'!A:F,6,0) -> 47825 | K75: =VLOOKUP(H75,'Datetel Jul 10, 2013'!A:G,7,0) -> 47825 | L75: =VLOOKUP(H75,'Datetel Jul 10, 2013'!A:I,8,0) -> 0 | M75: =J75-K75-L75 -> 0 | N75: 0 | P75: =N75+O75 -> 0 | Q75: =P75-I75 -> -47825
A76: DW | B76: VC Admin Serv | C76: Linda Francis | D76: Mngr/Conf/Supr SERP Premium 5 of 5 yrs | G76: E | H76: 100_304168_6740_53710_819 | I76: 196910 | J76: =VLOOKUP(H76,'Datetel Jul 10, 2013'!A:F,6,0) -> 196910 | K76: =VLOOKUP(H76,'Datetel Jul 10, 2013'!A:G,7,0) -> 193708.68 | L76: =VLOOKUP(H76,'Datetel Jul 10, 2013'!A:I,8,0) -> 0 | M76: =J76-K76-L76 -> 3201.32 | N76: 193709 | P76: =N76+O76 -> 193709 | Q76: =P76-I76 -> -3201
A77: DW | D77: Utilities, Mission College - Utilities | H77: 100_304020_6570_55800_819 | I77: 627482 | J77: =VLOOKUP(H77,'Datetel Jul 10, 2013'!A:F,6,0) -> 627482 | K77: =VLOOKUP(H77,'Datetel Jul 10, 2013'!A:G,7,0) -> 557686.19 | L77: =VLOOKUP(H77,'Datetel Jul 10, 2013'!A:I,8,0) -> 0 | M77: =J77-K77-L77 -> 69795.81 | N77: 627482 | O77: -20000 | P77: =N77+O77 -> 607482 | Q77: =P77-I77 -> -20000
A78: DW | D78: Utilities, Mission College - Gas | H78: 100_304020_6570_55811_819 | I78: 121560 | J78: =VLOOKUP(H78,'Datetel Jul 10, 2013'!A:F,6,0) -> 121560 | K78: =VLOOKUP(H78,'Datetel Jul 10, 2013'!A:G,7,0) -> 149524.62 | L78: =VLOOKUP(H78,'Datetel Jul 10, 2013'!A:I,8,0) -> 0 | M78: =J78-K78-L78 -> -27964.62 | N78: 121560 | O78: 27000 | P78: =N78+O78 -> 148560 | Q78: =P78-I78 -> 27000
A79: DW | D79: Utilities, Mission College - Trash | H79: 100_304020_6570_55820_819 | I79: 30757.5 | J79: =VLOOKUP(H79,'Datetel Jul 10, 2013'!A:F,6,0) -> 30758 | K79: =VLOOKUP(H79,'Datetel Jul 10, 2013'!A:G,7,0) -> 20792.02 | L79: =VLOOKUP(H79,'Datetel Jul 10, 2013'!A:I,8,0) -> 9965.98 | M79: =J79-K79-L79 -> 0 | N79: 30757.5 | O79: 5758 | P79: =N79+O79 -> 36515.5 | Q79: =P79-I79 -> 5758
A80: DW | D80: Utilities, Mission College - Water | H80: 100_304020_6570_55840_819 | I80: 55236 | J80: =VLOOKUP(H80,'Datetel Jul 10, 2013'!A:F,6,0) -> 55236 | K80: =VLOOKUP(H80,'Datetel Jul 10, 2013'!A:G,7,0) -> 86688.04 | L80: =VLOOKUP(H80,'Datetel Jul 10, 2013'!A:I,8,0) -> 0 | M80: =J80-K80-L80 -> -31452.04 | N80: 55236 | O80: 30000 | P80: =N80+O80 -> 85236 | Q80: =P80-I80 -> 30000
A81: DW | D81: Utilities, Mission College - Sewer | H81: 100_304020_6570_55850_819 | I81: 14964 | J81: =VLOOKUP(H81,'Datetel Jul 10, 2013'!A:F,6,0) -> 14964 | K81: =VLOOKUP(H81,'Datetel Jul 10, 2013'!A:G,7,0) -> 27676.86 | L81: =VLOOKUP(H81,'Datetel Jul 10, 2013'!A:I,8,0) -> 0 | M81: =J81-K81-L81 -> -12712.86 | N81: 14964 | O81: 15000 | P81: =N81+O81 -> 29964 | Q81: =P81-I81 -> 15000
A82: DW | B82: VC Admin Serv | C82: Linda Francis | D82: Utilities, Mission College | F82: Realign budget per actual | G82: F | H82: Multiple account numbers | I82: =SUM(I77:I81) -> 849999.5 | J82: =SUM(J77:J81) -> 850000 | K82: =SUM(K77:K81) -> 842367.73 | L82: =SUM(L77:L81) -> 9965.98 | M82: =SUM(M77:M81) -> -2333.71 | N82: =SUM(N77:N81) -> 849999.5 | O82: =SUM(O77:O81) -> 57758 | P82: =SUM(P77:P81) -> 907757.5 | Q82: =P82-I82 -> 57758
A83: DW | D83: Utilities, West Valley College - Utilities | H83: 100_304010_6570_55800_819 | I83: 606962.73 | J83: =VLOOKUP(H83,'Datetel Jul 10, 2013'!A:F,6,0) -> 605563 | K83: =VLOOKUP(H83,'Datetel Jul 10, 2013'!A:G,7,0) -> 789154.26 | L83: =VLOOKUP(H83,'Datetel Jul 10, 2013'!A:I,8,0) -> 0 | M83: =J83-K83-L83 -> -183591.26 | N83: 606962.73 | O83: 180000 | P83: =N83+O83 -> 786962.73 | Q83: =P83-I83 -> 180000
A84: DW | D84: Utilities, West Valley College - Gas | H84: 100_304010_6570_55811_819 | I84: 159484.5 | J84: =VLOOKUP(H84,'Datetel Jul 10, 2013'!A:F,6,0) -> 159485 | K84: =VLOOKUP(H84,'Datetel Jul 10, 2013'!A:G,7,0) -> 151040.07 | L84: =VLOOKUP(H84,'Datetel Jul 10, 2013'!A:I,8,0) -> 0 | M84: =J84-K84-L84 -> 8444.93 | N84: 159484.5 | O84: -8000 | P84: =N84+O84 -> 151484.5 | Q84: =P84-I84 -> -8000
A85: DW | D85: Utilities, West Valley College - Trash | H85: 100_304010_6570_55820_819 | I85: 21421.32 | J85: =VLOOKUP(H85,'Datetel Jul 10, 2013'!A:F,6,0) -> 21421 | K85: =VLOOKUP(H85,'Datetel Jul 10, 2013'!A:G,7,0) -> 15176.79 | L85: =VLOOKUP(H85,'Datetel Jul 10, 2013'!A:I,8,0) -> 6244.21 | M85: =J85-K85-L85 -> 0 | N85: 21421.32 | O85: -3421 | P85: =N85+O85 -> 18000.32 | Q85: =P85-I85 -> -3421
A86: DW | D86: Utilities, West Valley College - Water | H86: 100_304010_6570_55840_819 | I86: 137895.45 | J86: =VLOOKUP(H86,'Datetel Jul 10, 2013'!A:F,6,0) -> 137895 | K86: =VLOOKUP(H86,'Datetel Jul 10, 2013'!A:G,7,0) -> 173566.99 | L86: =VLOOKUP(H86,'Datetel Jul 10, 2013'!A:I,8,0) -> 0 | M86: =J86-K86-L86 -> -35671.99 | N86: 137895.45 | O86: 35000 | P86: =N86+O86 -> 172895.45 | Q86: =P86-I86 -> 35000
A87: DW | D87: Utilities, West Valley College - Sewer | E87: Sewer ( One payment each year) | H87: 100_304010_6570_55850_819 | I87: 74236 | J87: =VLOOKUP(H87,'Datetel Jul 10, 2013'!A:F,6,0) -> 74236 | K87: =VLOOKUP(H87,'Datetel Jul 10, 2013'!A:G,7,0) -> 37559.97 | L87: =VLOOKUP(H87,'Datetel Jul 10, 2013'!A:I,8,0) -> 0 | M87: =J87-K87-L87 -> 36676.03 | N87: 74236 | O87: -36000 | P87: =N87+O87 -> 38236 | Q87: =P87-I87 -> -36000
A88: DW | B88: VC Admin Serv | C88: Linda Francis | D88: Utilities, West Valley College | F88: Realign budget per actual | G88: F | H88: Multiple account numbers | I88: =SUM(I83:I87) -> 1000000 | J88: =SUM(J83:J87) -> 998600 | K88: =SUM(K83:K87) -> 1166498.1 | L88: =SUM(L83:L87) -> 6244.21 | M88: =SUM(M83:M87) -> -174142.29 | N88: =SUM(N83:N87) -> 1000000 | O88: =SUM(O83:O87) -> 167579 | P88: =SUM(P83:P87) -> 1167579 | Q88: =P88-I88 -> 167579
A89: DW | B89: VC Admin Serv | D89: Debt Service for LRB 2011 - Solar Project | G89: F,G | H89: 100_304190_7310_57300_819 | I89: 150000 | J89: 150000 | K89: 0 | L89: =VLOOKUP(H89,'Datetel Jul 10, 2013'!A:I,8,0) -> 0 | M89: =J89-K89-L89 -> 150000 | N89: 150000 | O89: -150000 | P89: =N89+O89 -> 0 | Q89: =P89-I89 -> -150000
A90: DW | B90: VC Admin Serv | C90: Linda Francis | D90: ACE-Negotiated 0.92% of COLA Health Benefit Reserve | G90: E | H90: 100_304169_7310_57300_819 | I90: 398419 | J90: =VLOOKUP(H90,'Datetel Jul 10, 2013'!A:F,6,0) -> 398419 | K90: =VLOOKUP(H90,'Datetel Jul 10, 2013'!A:G,7,0) -> 398419 | L90: =VLOOKUP(H90,'Datetel Jul 10, 2013'!A:I,8,0) -> 0 | M90: =J90-K90-L90 -> 0 | N90: 398419 | P90: =N90+O90 -> 398419 | Q90: =P90-I90 -> 0
A91: DW | B91: VC Admin Serv | D91: Analytic - Budget & Position Control | G91: F | H91: 100_304190_6720_55160_819 | I91: 15480 | J91: =VLOOKUP(H91,'Datetel Jul 10, 2013'!A:F,6,0) -> 15480 | K91: =VLOOKUP(H91,'Datetel Jul 10, 2013'!A:G,7,0) -> 15480 | L91: =VLOOKUP(H91,'Datetel Jul 10, 2013'!A:I,8,0) -> 0 | M91: =J91-K91-L91 -> 0 | N91: 15480 | P91: =N91+O91 -> 15480 | Q91: =P91-I91 -> 0
A92: DW | B92: Chancellor | C92: Linda Francis | D92: Elections/Redistricting Board Election | F92: Change in Trustee election/cost per yr | G92: D | H92: 100_300130_6600_55180_819 | I92: 190925 | J92: =VLOOKUP(H92,'Datetel Jul 10, 2013'!A:F,6,0) -> 190925 | K92: =VLOOKUP(H92,'Datetel Jul 10, 2013'!A:G,7,0) -> 77888.95 | L92: =VLOOKUP(H92,'Datetel Jul 10, 2013'!A:I,8,0) -> 0 | M92: =J92-K92-L92 -> 113036.05 | N92: 95462 | O92: =60000-N92 -> -35462 | P92: =N92+O92 -> 60000 | Q92: =P92-I92 -> -130925
A93: DW | B93: VC Admin Serv | C93: Ed Maduli/Christina | D93: Emergency Preparedness Services | G93: B | H93: 100_304180_6770_52350_819 | I93: 40000 | J93: =VLOOKUP(H93,'Datetel Jul 10, 2013'!A:F,6,0)+2000 -> 40000 | K93: =VLOOKUP(H93,'Datetel Jul 10, 2013'!A:G,7,0)+'Datetel Jul 10, 2013'!G207+'Datetel Jul 10, 2013'!G209+'Datetel Jul 10, 2013'!G210+'Datetel Jul 10, 2013'!G211 -> 28490.43 | L93: =VLOOKUP(H93,'Datetel Jul 10, 2013'!A:I,8,0) -> 0 | M93: =J93-K93-L93 -> 11509.57 | N93: 40000 | P93: =N93+O93 -> 40000 | Q93: =P93-I93 -> 0
A94: DW | D94: Bank Service Charges | F94: collection agency | H94: 100_304197_6720_55185_819 | I94: 0 | J94: 0 | K94: =VLOOKUP(H94,'Datetel Jul 10, 2013'!A:G,7,0) -> 10.46 | L94: =VLOOKUP(H94,'Datetel Jul 10, 2013'!A:I,8,0) -> 0 | M94: =J94-K94-L94 -> -10.46 | N94: 0 | P94: =N94+O94 -> 0 | Q94: =P94-I94 -> 0
D95: Bank Service Charges | F95: Over | H95: 100_304170_6720_55592_819 | I95: 0 | J95: 0 | K95: =VLOOKUP(H95,'Datetel Jul 10, 2013'!A:G,7,0) -> -81 | M95: =J95-K95-L95 -> 81 | N95: 0 | P95: =N95+O95 -> 0 | Q95: =P95-I95 -> 0
A96: DW | D96: Bank Service Charges | F96: Bank charges | H96: 100_304170_6720_55593_819 | I96: 15000 | J96: =VLOOKUP(H96,'Datetel Jul 10, 2013'!A:F,6,0) -> 15000 | K96: =VLOOKUP(H96,'Datetel Jul 10, 2013'!A:G,7,0) -> 34814.36 | L96: =VLOOKUP(H96,'Datetel Jul 10, 2013'!A:I,8,0) -> 0 | M96: =J96-K96-L96 -> -19814.36 | N96: 15000 | O96: 5000 | P96: =N96+O96 -> 20000 | Q96: =P96-I96 -> 5000
A97: DW | D97: Bank Service Charges | F97: E Commerce charges | H97: 100_304170_6720_55595_819 | I97: 165000 | J97: =VLOOKUP(H97,'Datetel Jul 10, 2013'!A:F,6,0) -> 165000 | K97: =VLOOKUP(H97,'Datetel Jul 10, 2013'!A:G,7,0) -> 163353.78 | L97: =VLOOKUP(H97,'Datetel Jul 10, 2013'!A:I,8,0) -> 0 | M97: =J97-K97-L97 -> 1646.22 | N97: 165000 | P97: =N97+O97 -> 165000 | Q97: =P97-I97 -> 0
A98: DW | B98: VC Admin Serv | C98: Linda Francis/Susan | D98: Bank Service Charges | G98: G | H98: Multiple account numbers | I98: =SUM(I94:I97) -> 180000 | J98: =SUM(J94:J97) -> 180000 | K98: =SUM(K94:K97) -> 198097.6 | L98: =SUM(L94:L97) -> 0 | M98: =SUM(M94:M97) -> -18097.6 | N98: =SUM(N94:N97) -> 180000 | O98: =SUM(O94:O97) -> 5000 | P98: =SUM(P94:P97) -> 185000 | Q98: =P98-I98 -> 5000
A99: DW | B99: VC Admin Serv | C99: Linda Francis | D99: Retiree Medical Benefits | G99: E | H99: 100_304190_7310_57300_819 | I99: 7822000 | J99: 7822000 | K99: =VLOOKUP(H99,'Datetel Jul 10, 2013'!A:G,7,0) -> 7822000 | L99: =VLOOKUP(H99,'Datetel Jul 10, 2013'!A:I,8,0) -> 0 | M99: =J99-K99-L99 -> 0 | N99: 7822000 | P99: =N99+O99 -> 7822000 | Q99: =P99-I99 -> 0
A100: DW | B100: Dir of General Serv | C100: Brigit Espinosa | D100: Property/Liability Insurance | F100: Adj per insurance renewal rate | G100: D | H100: 100_309600_6770_55940_819 | I100: 639644 | J100: 639644 | K100: 639644 | L100: 0 | M100: =J100-K100-L100 -> 0 | N100: 703608.4 | O100: =668833-N100 -> -34775.4 | P100: =N100+O100 -> 668833 | Q100: =P100-I100 -> 29189
...

Sheet 1314T 032913
B1: MISSION COLLEGE
B2: Budget | I2: 0.92307692 | J2: 0.92307692 | K2: Actual Exp | M2: Available | N2: Budget Adjust. | O2: 13/14
B3: Responsibility | C3: Contact Info. | D3: Fixed Cost Description | F3: Explanation for Adjustments | G3: Criteria | H3: Account Number | I3: Adopt Bud | J3: Working Bud | K3: as of 2/28/13 | L3: Encumb. | M3: Budget | N3: Incr / (Decr) | O3: Tnt. Budget
D4: Academic Senate - Supplies/Materials | H4: 100_206200_6750_54210_819 | I4: 1000 | J4: =VLOOKUP(H4,'Datetel Feb 28, 2013'!A:F,6,0) -> 1000 | K4: =VLOOKUP(H4,'Datetel Feb 28, 2013'!A:G,7,0) -> 163.62 | L4: =VLOOKUP(H4,'Datetel Feb 28, 2013'!A:I,8,0) -> 0 | M4: =J4-K4-L4 -> 836.38
D5: Academic Senate - Travel & Conference | H5: 100_206200_6750_55200_819 | I5: 3000 | J5: =VLOOKUP(H5,'Datetel Feb 28, 2013'!A:F,6,0) -> 3000 | K5: =VLOOKUP(H5,'Datetel Feb 28, 2013'!A:G,7,0) -> 1067.25 | L5: =VLOOKUP(H5,'Datetel Feb 28, 2013'!A:I,8,0) -> 0 | M5: =J5-K5-L5 -> 1932.75
B6: Senates | C6: Worku Negash | D6: Academic Senate | G6: C | H6: Multiple account numbers | I6: 4000 | J6: =SUM(J4:J5) -> 4000 | K6: =SUM(K4:K5) -> 1230.87 | L6: =SUM(L4:L5) -> 0 | M6: =J6-K6-L6 -> 2769.13 | O6: =J6 -> 4000
D7: Classified Senate - Hrly classified Salary | H7: 100_206300_6750_52310_819 | I7: 1000 | J7: =VLOOKUP(H7,'Datetel Feb 28, 2013'!A:F,6,0) -> 1000 | K7: =VLOOKUP(H7,'Datetel Feb 28, 2013'!A:G,7,0) -> 0 | L7: =VLOOKUP(H7,'Datetel Feb 28, 2013'!A:I,8,0) -> 0 | M7: =J7-K7-L7 -> 1000
D8: Classified Senate - Supplies/Materials | H8: 100_206300_6750_54210_819 | I8: 500 | J8: =VLOOKUP(H8,'Datetel Feb 28, 2013'!A:F,6,0) -> 500 | K8: =VLOOKUP(H8,'Datetel Feb 28, 2013'!A:G,7,0) -> 0 | L8: =VLOOKUP(H8,'Datetel Feb 28, 2013'!A:I,8,0) -> 0 | M8: =J8-K8-L8 -> 500
D9: Classified Senate - Food Services | H9: 100_206300_6750_55115_819 | I9: 1500 | J9: =VLOOKUP(H9,'Datetel Feb 28, 2013'!A:F,6,0) -> 1500 | K9: =VLOOKUP(H9,'Datetel Feb 28, 2013'!A:G,7,0) -> 0 | L9: =VLOOKUP(H9,'Datetel Feb 28, 2013'!A:I,8,0) -> 0 | M9: =J9-K9-L9 -> 1500
D10: Classified Senate - Travel & Conference | H10: 100_206300_6750_55205_819 | I10: 1500 | J10: =VLOOKUP(H10,'Datetel Feb 28, 2013'!A:F,6,0) -> 1500 | K10: =VLOOKUP(H10,'Datetel Feb 28, 2013'!A:G,7,0) -> 197.05 | L10: =VLOOKUP(H10,'Datetel Feb 28, 2013'!A:I,8,0) -> 0 | M10: =J10-K10-L10 -> 1302.95
B11: Senates | C11: Worku Negash | D11: Classified Senate | G11: C | H11: Multiple account numbers | I11: 4500 | J11: =SUM(J7:J10) -> 4500 | K11: =SUM(K7:K10) -> 197.05 | L11: =SUM(L7:L10) -> 0 | M11: =J11-K11-L11 -> 4302.95 | O11: =J11 -> 4500
B12: Senate | D12: Academic Senate President Stipend | F12: FY 13/14 Jul/Jun | G12: C | H12: 100_206200_6750_51450_819 | N12: 5000 | O12: =I12+N12 -> 5000
B13: Faculty Travel | C13: Worku Negash | D13: Faculty Travel & Conference | F13: ACE 145 @ 200 | G13: E | H13: 100_290100_6600_55210_819 | I13: 28800 | J13: =VLOOKUP(H13,'Datetel Feb 28, 2013'!A:F,6,0) -> 28800 | K13: =VLOOKUP(H13,'Datetel Feb 28, 2013'!A:G,7,0) -> 7802.44 | L13: =VLOOKUP(H13,'Datetel Feb 28, 2013'!A:I,8,0) -> 0 | M13: =J13-K13-L13 -> 20997.56 | N13: 200 | O13: =I13+N13 -> 29000
B14: VP Admin. Services | C14: Worku Negash | D14: Tenure Faculty | F14: No tenure bonus for 13/14 | G14: E | H14: 100_220910_4900_51310_819 | I14: 16500 | J14: =VLOOKUP(H14,'Datetel Feb 28, 2013'!A:F,6,0) -> 16500 | K14: =VLOOKUP(H14,'Datetel Feb 28, 2013'!A:G,7,0) -> 16500 | L14: =VLOOKUP(H14,'Datetel Feb 28, 2013'!A:I,8,0) -> 0 | M14: =J14-K14-L14 -> 0 | N14: -16500 | O14: =I14+N14 -> 0
B15: Dean of Instr, Lib. St/LA | C15: Worku Negash | D15: Tricore, Link + Consortium, Library Maintenance | G15: A | H15: 100_290200_6110_55510_819 | I15: 37594 | J15: =VLOOKUP(H15,'Datetel Feb 28, 2013'!A:F,6,0) -> 37971 | K15: =VLOOKUP(H15,'Datetel Feb 28, 2013'!A:G,7,0) -> 36427.35 | L15: =VLOOKUP(H15,'Datetel Feb 28, 2013'!A:I,8,0) -> 1438.65 | M15: =J15-K15-L15 -> 105 | O15: =I15+N15 -> 37594
B16: Dean of Instr, Lib. St/LA | D16: Turnkey Server Migration (One-Time) | F16: one-time cost for FY 12/13 | G16: A | H16: 100_230000_6120_55510_819 | I16: 4877 | J16: =VLOOKUP(H16,'Datetel Feb 28, 2013'!A:F,6,0) -> 4500 | K16: =VLOOKUP(H16,'Datetel Feb 28, 2013'!A:G,7,0) -> 4500 | L16: =VLOOKUP(H16,'Datetel Feb 28, 2013'!A:I,8,0) -> 0 | M16: =J16-K16-L16 -> 0 | N16: -4877 | O16: =I16+N16 -> 0
B17: VP Admin. Services | C17: Worku Negash | D17: Insurance for PE and Athletics Students | G17: C, D | H17: 100_220000_6440_55940_819 | I17: 73711 | J17: =VLOOKUP(H17,'Datetel Feb 28, 2013'!A:F,6,0) -> 73711 | K17: =VLOOKUP(H17,'Datetel Feb 28, 2013'!A:G,7,0) -> 72921.12 | L17: =VLOOKUP(H17,'Datetel Feb 28, 2013'!A:I,8,0) -> 0 | M17: =J17-K17-L17 -> 789.88 | O17: =I17+N17 -> 73711
B18: VP Admin. Services | C18: Worku Negash | D18: Coaches Stipends (Negotiated Item) | G18: E | H18: 100_220000_6770_51450_819 | I18: 15000 | J18: =VLOOKUP(H18,'Datetel Feb 28, 2013'!A:F,6,0) -> 15000 | K18: =SUM('Datetel Feb 28, 2013'!G145:G150) -> 4748.27 | L18: =VLOOKUP(H18,'Datetel Feb 28, 2013'!A:I,8,0) -> 0 | M18: =J18-K18-L18 -> 10251.73 | O18: =I18+N18 -> 15000
B19: College President | D19: Accreditation - Supplies/Materials | F19: Accreditation preparation | G19: C | H19: 100_200700_6090_54210_819 | I19: 10000 | J19: =VLOOKUP(H19,'Datetel Feb 28, 2013'!A:F,6,0) -> 1500 | K19: =VLOOKUP(H19,'Datetel Feb 28, 2013'!A:G,7,0) -> 176.12 | L19: =VLOOKUP(H19,'Datetel Feb 28, 2013'!A:I,8,0) -> 0 | M19: =J19-K19-L19 -> 1323.88 | O19: =I19+N19 -> 10000
B20: College President | D20: Accreditation - PT Faculty Non Teaching Stipend | G20: C | H20: 100_200700_6090_51450_819 | J20: =VLOOKUP(H20,'Datetel Feb 28, 2013'!A:F,6,0) -> 8500 | K20: =VLOOKUP(H20,'Datetel Feb 28, 2013'!A:G,7,0) -> 1817.64 | L20: =VLOOKUP(H20,'Datetel Feb 28, 2013'!A:I,8,0) -> 0 | M20: =J20-K20-L20 -> 6682.36 | O20: =I20+N20 -> 0
B21: College President | C21: Worku Negash | D21: Accreditation - Dues, Memberships & Fees | G21: C | H21: 100_200700_6090_55910_819 | I21: 17453 | J21: =VLOOKUP(H21,'Datetel Feb 28, 2013'!A:F,6,0) -> 17453 | K21: =VLOOKUP(H21,'Datetel Feb 28, 2013'!A:G,7,0)+'Datetel Feb 28, 2013'!G132+'Datetel Feb 28, 2013'!G133+'Datetel Feb 28, 2013'!G134+'Datetel Feb 28, 2013'!G135 -> 15800.35 | L21: =VLOOKUP(H21,'Datetel Feb 28, 2013'!A:I,8,0) -> 0 | M21: =J21-K21-L21 -> 1652.65 | O21: =I21+N21 -> 17453
B22: VP Admin. Services | C22: Linda Francis/Virginia | D22: Categorical Program: Transfer Out, Fringe Benefits | G22: C | H22: 100_220001_7310_57300_819 | I22: 340397 | J22: =VLOOKUP(H22,'Datetel Feb 28, 2013'!A:F,6,0) -> 340397 | K22: =VLOOKUP(H22,'Datetel Feb 28, 2013'!A:G,7,0) -> 242743.92 | L22: =VLOOKUP(H22,'Datetel Feb 28, 2013'!A:I,8,0) -> 0 | M22: =J22-K22-L22 -> 97653.08 | O22: =I22+N22 -> 340397
B23: VP Admin. Services | C23: Linda Francis/Virginia | D23: Financial Aid Match: SEOG & Fed Work Study | G23: C | H23: 100_220002_7310_57300_819 | I23: 88013 | J23: =VLOOKUP(H23,'Datetel Feb 28, 2013'!A:F,6,0) -> 88013 | K23: =VLOOKUP(H23,'Datetel Feb 28, 2013'!A:G,7,0) -> 0 | L23: =VLOOKUP(H23,'Datetel Feb 28, 2013'!A:I,8,0) -> 0 | M23: =J23-K23-L23 -> 88013 | O23: =I23+N23 -> 88013
B24: VP Admin. Services | D24: HigherOne | G24: D | H24: 100_220900_6490_55160_819 | I24: 2500 | J24: =VLOOKUP(H24,'Datetel Feb 28, 2013'!A:F,6,0) -> 2500 | K24: =VLOOKUP(H24,'Datetel Feb 28, 2013'!A:G,7,0) -> 2500 | L24: =VLOOKUP(H24,'Datetel Feb 28, 2013'!A:I,8,0) -> 0 | M24: =J24-K24-L24 -> 0 | O24: =I24+N24 -> 2500
B25: Dir of Information Syst | C25: Worku Negash | D25: Astra Schedule/LaserFiche Avante/FormFusion | G25: A | H25: 100_220007_6010_55500_819 | I25: 19057 | J25: =VLOOKUP(H25,'Datetel Feb 28, 2013'!A:F,6,0) -> 19057 | K25: =VLOOKUP(H25,'Datetel Feb 28, 2013'!A:G,7,0) -> 8160 | L25: =VLOOKUP(H25,'Datetel Feb 28, 2013'!A:I,8,0) -> 0 | M25: =J25-K25-L25 -> 10897 | O25: =I25+N25 -> 19057
B26: Dir of Information Syst | C26: Worku Negash | D26: Curricunet | G26: A | H26: 100_220000_6010_55160_819 | I26: 7479 | J26: =VLOOKUP(H26,'Datetel Feb 28, 2013'!A:F,6,0) -> 7479 | K26: =VLOOKUP(H26,'Datetel Feb 28, 2013'!A:G,7,0) -> 7479 | L26: =VLOOKUP(H26,'Datetel Feb 28, 2013'!A:I,8,0) -> 0 | M26: =J26-K26-L26 -> 0 | O26: =I26+N26 -> 7479
B27: Dir of Information Syst | C27: Ron Smith | D27: SARS Software Products -Counseling Sched System | G27: A | H27: 100_220004_6150_55500_819 | I27: 6500 | J27: =VLOOKUP(H27,'Datetel Feb 28, 2013'!A:F,6,0) -> 6500 | K27: =VLOOKUP(H27,'Datetel Feb 28, 2013'!A:G,7,0) -> 6255 | L27: =VLOOKUP(H27,'Datetel Feb 28, 2013'!A:I,8,0) -> 0 | M27: =J27-K27-L27 -> 245 | O27: =I27+N27 -> 6500
B28: Dir of Information Syst | C28: Ron Smith | D28: Angel | F28: renewal increase 6% | G28: A | H28: 100_220005_6150_55500_819 | I28: 78691 | J28: =VLOOKUP(H28,'Datetel Feb 28, 2013'!A:F,6,0) -> 78691 | K28: =VLOOKUP(H28,'Datetel Feb 28, 2013'!A:G,7,0) -> 78691.63 | L28: =VLOOKUP(H28,'Datetel Feb 28, 2013'!A:I,8,0) -> 0 | M28: =J28-K28-L28 -> -0.63 | N28: 4722 | O28: =I28+N28 -> 83413
B29: Dir of Information Syst | C29: Ron Smith | D29: CCCApply / BOGS (Student-Right-to-know) | G29: A | H29: 100_220006_6150_55500_819 | I29: 15609 | J29: =VLOOKUP(H29,'Datetel Feb 28, 2013'!A:F,6,0) -> 15609 | K29: =VLOOKUP(H29,'Datetel Feb 28, 2013'!A:G,7,0) -> 11514.1 | L29: =VLOOKUP(H29,'Datetel Feb 28, 2013'!A:I,8,0) -> 4099.9 | M29: =J29-K29-L29 -> -5 | O29: =I29+N29 -> 15609
H30: Total Mission College | I30: =SUM(I6,I11,I12:I29) -> 770681 | J30: =SUM(J6,J11,J13:J29) -> 770681 | K30: =SUM(K6,K11,K13:K29) -> 519464.86 | L30: =SUM(L6,L11,L13:L29) -> 5538.55 | M30: =SUM(M6,M11,M13:M29) -> 245677.59 | N30: =SUM(N6,N11,N12:N29) -> -11455 | O30: =SUM(O6,O11,O12:O29) -> 759226
M31: 412305
B32: WEST VALLEY COLLEGE
B33: Budget | I33: 0.92307692 | J33: 0.92307692 | K33: Actual Exp | M33: Available | N33: Budget Adjust. | O33: 13/14
B34: Responsibility | C34: Contact Info. | D34: Fixed Cost Description | E34: Detail Description | F34: Explanation for Adjustments | G34: Criteria | H34: Account Number | I34: Adopt Bud | J34: Working Bud | K34: as of 2/28/13 | L34: Encumb. | M34: Budget | N34: Incr / (Decr) | O34: Tnt. Budget
D35: Academic Senate -to be funded from other source | H35: 100_119304_6750_55115_819 | I35: 1100 | J35: =VLOOKUP(H35,'Datetel Feb 28, 2013'!A:F,6,0) -> 1100 | K35: =VLOOKUP(H35,'Datetel Feb 28, 2013'!A:G,7,0) -> 0 | L35: =VLOOKUP(H35,'Datetel Feb 28, 2013'!A:I,8,0) -> 0 | M35: =J35-K35-L35 -> 1100
D36: Academic Senate -to be funded from other source | H36: 100_119304_6750_55200_819 | I36: 3300 | J36: =VLOOKUP(H36,'Datetel Feb 28, 2013'!A:F,6,0) -> 3300 | K36: =VLOOKUP(H36,'Datetel Feb 28, 2013'!A:G,7,0) -> 0 | L36: =VLOOKUP(H36,'Datetel Feb 28, 2013'!A:I,8,0) -> 0 | M36: =J36-K36-L36 -> 3300
B37: Senates | C37: Michael Renzi | D37: Academic Senate | G37: C | H37: Multiple account numbers | I37: 4400 | J37: =SUM(J35:J36) -> 4400 | K37: =SUM(K35:K36) -> 0 | L37: =SUM(L35:L36) -> 0 | M37: =J37-K37-L37 -> 4400 | O37: =I37 -> 4400 | R37: =0.4*24464 -> 9785.6
D38: Classified Senate | H38: 100_119305_6750_55115_819 | I38: 660 | J38: =VLOOKUP(H38,'Datetel Feb 28, 2013'!A:F,6,0) -> 3660 | K38: =VLOOKUP(H38,'Datetel Feb 28, 2013'!A:G,7,0) -> 452.71 | L38: =VLOOKUP(H38,'Datetel Feb 28, 2013'!A:I,8,0) -> 0 | M38: =J38-K38-L38 -> 3207.29
D39: Classified Senate | H39: 100_119305_6750_55160_819 | I39: 440 | J39: =VLOOKUP(H39,'Datetel Feb 28, 2013'!A:F,6,0) -> 440 | K39: =VLOOKUP(H39,'Datetel Feb 28, 2013'!A:G,7,0) -> 0 | L39: =VLOOKUP(H39,'Datetel Feb 28, 2013'!A:I,8,0) -> 0 | M39: =J39-K39-L39 -> 440
D40: Classified Senate | H40: 100_119305_6750_55200_819 | I40: 3300 | J40: =VLOOKUP(H40,'Datetel Feb 28, 2013'!A:F,6,0) -> 300 | K40: =VLOOKUP(H40,'Datetel Feb 28, 2013'!A:G,7,0) -> 85 | L40: =VLOOKUP(H40,'Datetel Feb 28, 2013'!A:I,8,0) -> 0 | M40: =J40-K40-L40 -> 215
B41: Senates | C41: Michael Renzi | D41: Classified Senate | G41: C | H41: Multiple account numbers | I41: 4400 | J41: =SUM(J38:J40) -> 4400 | K41: =SUM(K38:K40) -> 537.71 | L41: =SUM(L38:L40) -> 0 | M41: =J41-K41-L41 -> 3862.29 | O41: =I41 -> 4400
B42: Senate | D42: Academic Senate President Stipend | F42: FY 13/14 Jul/Jun | G42: C | H42: 100_119304_6750_51450_819 | N42: 5000 | O42: =I42+N42 -> 5000
B43: VP Admin. Services | C43: Michael Renzi | D43: Faculty Travel & Conference | F43: ACE 166 @ 200 | G43: E | H43: 100_103201_6010_55210_819 | I43: 33200 | J43: 33200 | K43: =SUM('Datetel Feb 28, 2013'!G15:G54) -> 3243.3 | L43: =VLOOKUP(H43,'Datetel Feb 28, 2013'!A:I,8,0) -> 0 | M43: =J43-K43-L43 -> 29956.7 | O43: =I43+N43 -> 33200
B44: VP Admin. Services | C44: Michael Renzi | D44: Tenure Faculty | F44: No tenure bonus for 13/14 | G44: E | H44: 100_103251_4900_51310_819 | I44: 27500 | J44: =VLOOKUP(H44,'Datetel Feb 28, 2013'!A:F,6,0) -> 27500 | K44: =VLOOKUP(H44,'Datetel Feb 28, 2013'!A:G,7,0) -> 0 | L44: =VLOOKUP(H44,'Datetel Feb 28, 2013'!A:I,8,0) -> 0 | M44: =J44-K44-L44 -> 27500 | N44: -27500 | O44: =I44+N44 -> 0
B45: Dean Learning Center | C45: Michael Renzi | D45: Tricore, Link + Consortium, Library Maintenance | E45: Consolidated budget for Link+ and other costs | G45: A | H45: 100_106100_6120_55510_819 | I45: 40155 | J45: 40155 | K45: =VLOOKUP(H45,'Datetel Feb 28, 2013'!A:G,7,0)-K46 -> 38145.91 | L45: =VLOOKUP(H45,'Datetel Feb 28, 2013'!A:I,8,0) -> 2364.09 | M45: =J45-K45-L45 -> -355 | O45: =I45+N45 -> 40155
B46: Dean Learning Center | C46: Michael Renzi | D46: Turnkey Server Migration (One-Time) | E46: Consolidated budget for Link+ and other costs | F46: one-time cost for FY 12/13 | G46: A | H46: 100_106100_6120_55510_819 | I46: 4877 | J46: 4877 | K46: 4500 | L46: 0 | M46: =J46-K46-L46 -> 377 | N46: =-I46 -> -4877 | O46: =I46+N46 -> 0
B47: Physical Education Division | C47: Michael Renzi | D47: Insurance for PE and Athletics Students | E47: Base from Final Budget. Increased from FY11 | G47: C, D | H47: 100_115200_6960_55940_819 | I47: 110568 | J47: =VLOOKUP(H47,'Datetel Feb 28, 2013'!A:F,6,0) -> 109382 | K47: =VLOOKUP(H47,'Datetel Feb 28, 2013'!A:G,7,0) -> 109381.68 | L47: =VLOOKUP(H47,'Datetel Feb 28, 2013'!A:I,8,0) -> 0 | M47: =J47-K47-L47 -> 0.32 | O47: =I47+N47 -> 110568
B48: Physical Education Division | C48: Michael Renzi | D48: Coaches Stipends (Negotiated Item) | G48: E | H48: 100_115200_6960_51450_819 | I48: 24625 | J48: 25811 | K48: =SUM('Datetel Feb 28, 2013'!G63:G69) -> 10874.64 | L48: =VLOOKUP(H48,'Datetel Feb 28, 2013'!A:I,8,0) -> 0 | M48: =J48-K48-L48 -> 14936.36 | O48: =I48+N48 -> 24625
B49: College President | C49: Michael Renzi | D49: Accreditation - Dues, Memberships & Fees | G49: C | H49: 100_100100_6090_55910_819 | I49: 18953 | J49: =VLOOKUP(H49,'Datetel Feb 28, 2013'!A:F,6,0) -> 18953 | K49: =VLOOKUP(H49,'Datetel Feb 28, 2013'!A:G,7,0) -> 18326 | L49: =VLOOKUP(H49,'Datetel Feb 28, 2013'!A:I,8,0) -> 0 | M49: =J49-K49-L49 -> 627 | N49: =2000+(17137-18953) -> 184 | O49: =I49+N49 -> 19137
B50: College President | D50: Accreditation - Hourly Classified | G50: C | H50: 100_100100_6090_52350_819 | J50: 7299 | K50: =SUM('Datetel Feb 28, 2013'!G3:G9) -> 492.66 | L50: =VLOOKUP(H50,'Datetel Feb 28, 2013'!A:I,8,0) -> 0 | M50: =J50-K50-L50 -> 6806.34 | N50: 8650 | O50: =I50+N50 -> 8650
B51: College President | C51: Michael Renzi | D51: Accreditation - Supplies/Materials | G51: C | H51: 100_100100_6090_54210_819 | I51: 10000 | J51: =VLOOKUP(H51,'Datetel Feb 28, 2013'!A:F,6,0) -> 2701 | K51: =VLOOKUP(H51,'Datetel Feb 28, 2013'!A:G,7,0) -> 99 | L51: =VLOOKUP(H51,'Datetel Feb 28, 2013'!A:I,8,0) -> 0 | M51: =J51-K51-L51 -> 2602 | N51: -8650 | O51: =I51+N51 -> 1350
B52: VP Admin. Services | C52: Linda Francis/Virginia | D52: Categorical Program: Transfer Out, Fringe Benefits | G52: C | H52: 100_103203_7310_57300_819 | I52: 468710 | J52: =VLOOKUP(H52,'Datetel Feb 28, 2013'!A:F,6,0) -> 468710 | K52: =VLOOKUP(H52,'Datetel Feb 28, 2013'!A:G,7,0) -> 0 | L52: =VLOOKUP(H52,'Datetel Feb 28, 2013'!A:I,8,0) -> 0 | M52: =J52-K52-L52 -> 468710 | O52: =I52+N52 -> 468710
B53: VP Admin. Services | C53: Linda Francis/Virginia | D53: Financial Aid Match: SEOG, Fed Work Study | G53: C | H53: 100_103204_7310_57300_819 | I53: 89345 | J53: =VLOOKUP(H53,'Datetel Feb 28, 2013'!A:F,6,0) -> 89345 | K53: =VLOOKUP(H53,'Datetel Feb 28, 2013'!A:G,7,0) -> 0 | L53: =VLOOKUP(H53,'Datetel Feb 28, 2013'!A:I,8,0) -> 0 | M53: =J53-K53-L53 -> 89345 | O53: =I53+N53 -> 89345
B54: VP Admin. Services | D54: HigherOne | G54: D | H54: 100_102000_6490_55160_819 | I54: 2500 | J54: =VLOOKUP(H54,'Datetel Feb 28, 2013'!A:F,6,0) -> 2500 | K54: =VLOOKUP(H54,'Datetel Feb 28, 2013'!A:G,7,0) -> 2500 | L54: =VLOOKUP(H54,'Datetel Feb 28, 2013'!A:I,8,0) -> 0 | M54: =J54-K54-L54 -> 0 | O54: =I54+N54 -> 2500
B55: Dir of Information Syst | C55: Michael Renzi | D55: Astra Schedule/LaserFiche Avante/FormFusion | G55: A | H55: 100_103209_6010_55500_819 | I55: 19057 | J55: =VLOOKUP(H55,'Datetel Feb 28, 2013'!A:F,6,0) -> 19057 | K55: =VLOOKUP(H55,'Datetel Feb 28, 2013'!A:G,7,0) -> 8160 | L55: =VLOOKUP(H55,'Datetel Feb 28, 2013'!A:I,8,0) -> 0 | M55: =J55-K55-L55 -> 10897 | O55: =I55+N55 -> 19057
B56: Dir of Information Syst | C56: Michael Renzi | D56: Curricunet | G56: A | H56: 100_101000_6010_55160_819 | I56: 7479 | J56: =VLOOKUP(H56,'Datetel Feb 28, 2013'!A:F,6,0) -> 7479 | K56: =VLOOKUP(H56,'Datetel Feb 28, 2013'!A:G,7,0) -> 7479 | L56: =VLOOKUP(H56,'Datetel Feb 28, 2013'!A:I,8,0) -> 0 | M56: =J56-K56-L56 -> 0 | O56: =I56+N56 -> 7479
B57: Dir of Information Syst | C57: Ron Smith | D57: SARS Software Products -Counseling Sched System | G57: A | H57: 100_103206_6150_55500_819 | I57: 6500 | J57: =VLOOKUP(H57,'Datetel Feb 28, 2013'!A:F,6,0) -> 6500 | K57: =VLOOKUP(H57,'Datetel Feb 28, 2013'!A:G,7,0) -> 6255 | L57: =VLOOKUP(H57,'Datetel Feb 28, 2013'!A:I,8,0) -> 0 | M57: =J57-K57-L57 -> 245 | O57: =I57+N57 -> 6500
B58: Dir of Information Syst | C58: Ron Smith | D58: Angel | F58: renewal increase 6% | G58: A | H58: 100_103207_6150_55500_819 | I58: 78691 | J58: =VLOOKUP(H58,'Datetel Feb 28, 2013'!A:F,6,0) -> 78691 | K58: =VLOOKUP(H58,'Datetel Feb 28, 2013'!A:G,7,0) -> 78690.63 | L58: =VLOOKUP(H58,'Datetel Feb 28, 2013'!A:I,8,0) -> 0 | M58: =J58-K58-L58 -> 0.37 | N58: 4722 | O58: =I58+N58 -> 83413
B59: Dir of Information Syst | C59: Ron Smith | D59: CCCApply / BOGS (Student-Right-to-know) | G59: A | H59: 100_103208_6150_55500_819 | I59: 15609 | J59: =VLOOKUP(H59,'Datetel Feb 28, 2013'!A:F,6,0) -> 15609 | K59: =VLOOKUP(H59,'Datetel Feb 28, 2013'!A:G,7,0) -> 15614 | L59: =VLOOKUP(H59,'Datetel Feb 28, 2013'!A:I,8,0) -> 0 | M59: =J59-K59-L59 -> -5 | O59: =I59+N59 -> 15609
B60: Campbell Center | C60: Michael Renzi | D60: Campbell Center Lease | G60: D | H60: 100_131000_6470_55520_819 | I60: 34000 | J60: =VLOOKUP(H60,'Datetel Feb 28, 2013'!A:F,6,0) -> 34000 | K60: =VLOOKUP(H60,'Datetel Feb 28, 2013'!A:G,7,0) -> 34000 | L60: =VLOOKUP(H60,'Datetel Feb 28, 2013'!A:I,8,0) -> 0 | M60: =J60-K60-L60 -> 0 | O60: =I60+N60 -> 34000
D61: NISOD-Salary | H61: 100_119303_6720_51450_819 | I61: 4400 | J61: =VLOOKUP(H61,'Datetel Feb 28, 2013'!A:F,6,0) -> 4400 | K61: =VLOOKUP(H61,'Datetel Feb 28, 2013'!A:G,7,0) -> 0 | L61: =VLOOKUP(H61,'Datetel Feb 28, 2013'!A:I,8,0) -> 0 | M61: =J61-K61-L61 -> 4400 | O61: =I61+N61 -> 4400
D62: NISOD-Food Services | H62: 100_119303_6750_55115_819 | I62: 1100 | J62: =VLOOKUP(H62,'Datetel Feb 28, 2013'!A:F,6,0) -> 1100 | K62: =VLOOKUP(H62,'Datetel Feb 28, 2013'!A:G,7,0) -> 1025.63 | L62: =VLOOKUP(H62,'Datetel Feb 28, 2013'!A:I,8,0) -> 0 | M62: =J62-K62-L62 -> 74.37 | O62: =I62+N62 -> 1100
D63: NISOD-Travel for faculty to go to Texas | H63: 100_119303_6750_55200_819 | I63: 3300 | J63: =VLOOKUP(H63,'Datetel Feb 28, 2013'!A:F,6,0) -> 3300 | K63: =VLOOKUP(H63,'Datetel Feb 28, 2013'!A:G,7,0) -> 0 | L63: =VLOOKUP(H63,'Datetel Feb 28, 2013'!A:I,8,0) -> 0 | M63: =J63-K63-L63 -> 3300 | O63: =I63+N63 -> 3300
B64: Senates/ VP of Admin. Services | C64: Michael Renzi | D64: Professional Development | G64: C | H64: Multiple account numbers | I64: 8800 | J64: =SUM(J61:J63) -> 8800 | K64: =SUM(K61:K63) -> 1025.63 | L64: =SUM(L61:L63) -> 0 | M64: =J64-K64-L64 -> 7774.37 | O64: =I64+N64 -> 8800
H65: Total West Valley College | I65: =SUM(I37,I41,I42:I60,I64) -> 1009369 | J65: =SUM(J37,J41,J42:J60,J64) -> 1009369 | K65: =SUM(K37,K41,K42:K60,K64) -> 339325.16 | L65: =SUM(L37,L41,L42:L60,L64) -> 2364.09 | M65: =SUM(M37,M41,M42:M60,M64) -> 667679.75 | N65: =SUM(N37,N41,N42:N60,N64) -> -22471 | O65: =SUM(O37,O41,O42:O60,O64) -> 986898
M66: =SUM(I65,L65) -> 1011733.1
B67: DISTRICT WIDE
B68: Budget | I68: 0.92307692 | J68: 0.92307692 | K68: Actual Exp | M68: Available | N68: Budget Adjust. | O68: 13/14
B69: Responsibility | C69: Contact Info. | D69: Fixed Cost Description | F69: Explanation for Adjustments | G69: Criteria | H69: Account Number | I69: Adopt Bud | J69: Working Bud | K69: as of 2/28/13 | L69: Encumb. | M69: Budget | N69: Incr / (Decr) | O69: Tnt. Budget
A70: DW | B70: VC Admin Serv | C70: Linda Francis | D70: Cal Grant Interest Payment | F70: reduction due to change in process | G70: C | H70: 100_304170_6720_55185_819 | I70: 4500 | J70: 4500 | K70: =VLOOKUP(H70,'Datetel Feb 28, 2013'!A:G,7,0)-K71 -> 2304.63 | L70: =VLOOKUP(H70,'Datetel Feb 28, 2013'!A:I,8,0) -> 2195.43 | M70: =J70-K70-L70 -> -0.06 | N70: -2500 | O70: =I70+N70 -> 2000 | P70: =I70-J70 -> 0 | R70: =SUMIF('Datetel Feb 28, 2013'!A:A,'1314T 032913'!H70,'Datetel Feb 28, 2013'!I:I) -> 3658.94 | S70: =M70-R70 -> -3659
A71: DW | B71: VC Admin Serv | C71: Linda Francis | D71: NDSL Collection Admin Costs (Perkins Loans) | G71: G | H71: 100_304170_6720_55185_819 | I71: 5000 | J71: 5000 | K71: 1341 | L71: 0 | M71: =J71-K71-L71 -> 3659 | O71: =I71+N71 -> 5000 | P71: =I71-J71 -> 0 | R71: =SUMIF('Datetel Feb 28, 2013'!A:A,'1314T 032913'!H71,'Datetel Feb 28, 2013'!I:I) -> 3658.94 | S71: =M71-R71 -> 0.06
A72: DW | B72: VC Admin Serv | C72: Linda Francis | D72: Faculty SERP Premium 5 of 5 yrs | F72: Final payment made in 12/13 | G72: E | H72: 100_304168_5900_53710_819 | I72: 47825 | J72: =VLOOKUP(H72,'Datetel Feb 28, 2013'!A:F,6,0) -> 47825 | K72: =VLOOKUP(H72,'Datetel Feb 28, 2013'!A:G,7,0) -> 47825 | L72: =VLOOKUP(H72,'Datetel Feb 28, 2013'!A:I,8,0) -> 0 | M72: =J72-K72-L72 -> 0 | N72: -47825 | O72: =I72+N72 -> 0 | P72: =I72-J72 -> 0 | R72: =SUMIF('Datetel Feb 28, 2013'!A:A,'1314T 032913'!H72,'Datetel Feb 28, 2013'!I:I) -> 0 | S72: =M72-R72 -> 0
A73: DW | B73: VC Admin Serv | C73: Linda Francis | D73: Mngr/Conf/Supr SERP Premium 5 of 5 yrs | F73: Final payment amount for 13/14 | G73: E | H73: 100_304168_6740_53710_819 | I73: 196910 | J73: =VLOOKUP(H73,'Datetel Feb 28, 2013'!A:F,6,0) -> 196910 | K73: =VLOOKUP(H73,'Datetel Feb 28, 2013'!A:G,7,0) -> 193708.68 | L73: =VLOOKUP(H73,'Datetel Feb 28, 2013'!A:I,8,0) -> 0 | M73: =J73-K73-L73 -> 3201.32 | N73: -3201 | O73: =I73+N73 -> 193709 | P73: =I73-J73 -> 0 | R73: =SUMIF('Datetel Feb 28, 2013'!A:A,'1314T 032913'!H73,'Datetel Feb 28, 2013'!I:I) -> 3201.32 | S73: =M73-R73 -> 0
A74: DW | D74: Utilities, Mission College - Utilities | H74: 100_304020_6570_55800_819 | I74: 627482 | J74: =VLOOKUP(H74,'Datetel Feb 28, 2013'!A:F,6,0) -> 627482 | K74: =VLOOKUP(H74,'Datetel Feb 28, 2013'!A:G,7,0) -> 401750.09 | L74: =VLOOKUP(H74,'Datetel Feb 28, 2013'!A:I,8,0) -> 0 | M74: =J74-K74-L74 -> 225731.91 | O74: =I74+N74 -> 627482 | P74: =I74-J74 -> 0 | R74: =SUMIF('Datetel Feb 28, 2013'!A:A,'1314T 032913'!H74,'Datetel Feb 28, 2013'!I:I) -> 225731.91 | S74: =M74-R74 -> 0
A75: DW | D75: Utilities, Mission College - Gas | H75: 100_304020_6570_55811_819 | I75: 121560 | J75: =VLOOKUP(H75,'Datetel Feb 28, 2013'!A:F,6,0) -> 121560 | K75: =VLOOKUP(H75,'Datetel Feb 28, 2013'!A:G,7,0) -> 79487.16 | L75: =VLOOKUP(H75,'Datetel Feb 28, 2013'!A:I,8,0) -> 0 | M75: =J75-K75-L75 -> 42072.84 | O75: =I75+N75 -> 121560 | P75: =I75-J75 -> 0 | R75: =SUMIF('Datetel Feb 28, 2013'!A:A,'1314T 032913'!H75,'Datetel Feb 28, 2013'!I:I) -> 42072.84 | S75: =M75-R75 -> 0
A76: DW | D76: Utilities, Mission College - Trash | H76: 100_304020_6570_55820_819 | I76: 30757.5 | J76: =VLOOKUP(H76,'Datetel Feb 28, 2013'!A:F,6,0) -> 30758 | K76: =VLOOKUP(H76,'Datetel Feb 28, 2013'!A:G,7,0) -> 12690.2 | L76: =VLOOKUP(H76,'Datetel Feb 28, 2013'!A:I,8,0) -> 18067.8 | M76: =J76-K76-L76 -> 0 | O76: =I76+N76 -> 30757.5 | P76: =I76-J76 -> -0.5 | R76: =SUMIF('Datetel Feb 28, 2013'!A:A,'1314T 032913'!H76,'Datetel Feb 28, 2013'!I:I) -> 0 | S76: =M76-R76 -> 0
A77: DW | D77: Utilities, Mission College - Water | H77: 100_304020_6570_55840_819 | I77: 55236 | J77: =VLOOKUP(H77,'Datetel Feb 28, 2013'!A:F,6,0) -> 55236 | K77: =VLOOKUP(H77,'Datetel Feb 28, 2013'!A:G,7,0) -> 51826.17 | L77: =VLOOKUP(H77,'Datetel Feb 28, 2013'!A:I,8,0) -> 0 | M77: =J77-K77-L77 -> 3409.83 | O77: =I77+N77 -> 55236 | P77: =I77-J77 -> 0 | R77: =SUMIF('Datetel Feb 28, 2013'!A:A,'1314T 032913'!H77,'Datetel Feb 28, 2013'!I:I) -> 3409.83 | S77: =M77-R77 -> 0
A78: DW | D78: Utilities, Mission College - Sewer | H78: 100_304020_6570_55850_819 | I78: 14964 | J78: =VLOOKUP(H78,'Datetel Feb 28, 2013'!A:F,6,0) -> 14964 | K78: =VLOOKUP(H78,'Datetel Feb 28, 2013'!A:G,7,0) -> 16443.25 | L78: =VLOOKUP(H78,'Datetel Feb 28, 2013'!A:I,8,0) -> 0 | M78: =J78-K78-L78 -> -1479.25 | O78: =I78+N78 -> 14964 | P78: =I78-J78 -> 0 | R78: =SUMIF('Datetel Feb 28, 2013'!A:A,'1314T 032913'!H78,'Datetel Feb 28, 2013'!I:I) -> -1479.25 | S78: =M78-R78 -> 0
A79: DW | B79: VC Admin Serv | C79: Linda Francis | D79: Utilities, Mission College | G79: F | H79: Multiple account numbers | I79: =SUM(I74:I78) -> 849999.5 | J79: =SUM(J74:J78) -> 850000 | K79: =SUM(K74:K78) -> 562196.87 | L79: =SUM(L74:L78) -> 18067.8 | M79: =SUM(M74:M78) -> 269735.33 | O79: =I79+N79 -> 849999.5 | P79: =I79-J79 -> -0.5 | R79: =SUMIF('Datetel Feb 28, 2013'!A:A,'1314T 032913'!H79,'Datetel Feb 28, 2013'!I:I) -> 0 | S79: =M79-R79 -> 269735.33
A80: DW | D80: Utilities, West Valley College - Utilities | H80: 100_304010_6570_55800_819 | I80: 606962.73 | J80: =VLOOKUP(H80,'Datetel Feb 28, 2013'!A:F,6,0) -> 605563 | K80: =VLOOKUP(H80,'Datetel Feb 28, 2013'!A:G,7,0) -> 544146.42 | L80: =VLOOKUP(H80,'Datetel Feb 28, 2013'!A:I,8,0) -> 0 | M80: =J80-K80-L80 -> 61416.58 | O80: =I80+N80 -> 606962.73 | P80: =I80-J80 -> 1399.73 | R80: =SUMIF('Datetel Feb 28, 2013'!A:A,'1314T 032913'!H80,'Datetel Feb 28, 2013'!I:I) -> 61416.58 | S80: =M80-R80 -> 0
A81: DW | D81: Utilities, West Valley College - Gas | H81: 100_304010_6570_55811_819 | I81: 159484.5 | J81: =VLOOKUP(H81,'Datetel Feb 28, 2013'!A:F,6,0) -> 159485 | K81: =VLOOKUP(H81,'Datetel Feb 28, 2013'!A:G,7,0) -> 88794.9 | L81: =VLOOKUP(H81,'Datetel Feb 28, 2013'!A:I,8,0) -> 0 | M81: =J81-K81-L81 -> 70690.1 | O81: =I81+N81 -> 159484.5 | P81: =I81-J81 -> -0.5 | R81: =SUMIF('Datetel Feb 28, 2013'!A:A,'1314T 032913'!H81,'Datetel Feb 28, 2013'!I:I) -> 70690.1 | S81: =M81-R81 -> 0
A82: DW | D82: Utilities, West Valley College - Trash | H82: 100_304010_6570_55820_819 | I82: 21421.32 | J82: =VLOOKUP(H82,'Datetel Feb 28, 2013'!A:F,6,0) -> 21421 | K82: =VLOOKUP(H82,'Datetel Feb 28, 2013'!A:G,7,0) -> 8617.66 | L82: =VLOOKUP(H82,'Datetel Feb 28, 2013'!A:I,8,0) -> 12803.34 | M82: =J82-K82-L82 -> 0 | O82: =I82+N82 -> 21421.32 | P82: =I82-J82 -> 0.32 | R82: =SUMIF('Datetel Feb 28, 2013'!A:A,'1314T 032913'!H82,'Datetel Feb 28, 2013'!I:I) -> 0 | S82: =M82-R82 -> 0
A83: DW | D83: Utilities, West Valley College - Water | H83: 100_304010_6570_55840_819 | I83: 137895.45 | J83: =VLOOKUP(H83,'Datetel Feb 28, 2013'!A:F,6,0) -> 137895 | K83: =VLOOKUP(H83,'Datetel Feb 28, 2013'!A:G,7,0) -> 99395.09 | L83: =VLOOKUP(H83,'Datetel Feb 28, 2013'!A:I,8,0) -> 0 | M83: =J83-K83-L83 -> 38499.91 | O83: =I83+N83 -> 137895.45 | P83: =I83-J83 -> 0.45 | R83: =SUMIF('Datetel Feb 28, 2013'!A:A,'1314T 032913'!H83,'Datetel Feb 28, 2013'!I:I) -> 38499.91 | S83: =M83-R83 -> 0
A84: DW | D84: Utilities, West Valley College - Sewer | E84: Sewer ( One payment each year) | H84: 100_304010_6570_55850_819 | I84: 74236 | J84: =VLOOKUP(H84,'Datetel Feb 28, 2013'!A:F,6,0) -> 74236 | K84: =VLOOKUP(H84,'Datetel Feb 28, 2013'!A:G,7,0) -> 37559.97 | L84: =VLOOKUP(H84,'Datetel Feb 28, 2013'!A:I,8,0) -> 0 | M84: =J84-K84-L84 -> 36676.03 | O84: =I84+N84 -> 74236 | P84: =I84-J84 -> 0 | R84: =SUMIF('Datetel Feb 28, 2013'!A:A,'1314T 032913'!H84,'Datetel Feb 28, 2013'!I:I) -> 36676.03 | S84: =M84-R84 -> 0
A85: DW | B85: VC Admin Serv | C85: Linda Francis | D85: Utilities, West Valley College | G85: F | H85: Multiple account numbers | I85: =SUM(I80:I84) -> 1000000 | J85: =SUM(J80:J84) -> 998600 | K85: =SUM(K80:K84) -> 778514.04 | L85: =SUM(L80:L84) -> 12803.34 | M85: =SUM(M80:M84) -> 207282.62 | O85: =I85+N85 -> 1000000 | R85: =SUMIF('Datetel Feb 28, 2013'!A:A,'1314T 032913'!H85,'Datetel Feb 28, 2013'!I:I) -> 0 | S85: =M85-R85 -> 207282.62
A86: DW | B86: VC Admin Serv | D86: Debt Service for LRB 2011 - Solar Project | G86: F,G | H86: 100_304197_7310_57300_819 | I86: 150000 | J86: =VLOOKUP(H86,'Datetel Feb 28, 2013'!A:F,6,0) -> 150000 | K86: =VLOOKUP(H86,'Datetel Feb 28, 2013'!A:G,7,0) -> 0 | L86: =VLOOKUP(H86,'Datetel Feb 28, 2013'!A:I,8,0) -> 0 | M86: =J86-K86-L86 -> 150000 | O86: =I86+N86 -> 150000 | P86: =I86-J86 -> 0 | R86: =SUMIF('Datetel Feb 28, 2013'!A:A,'1314T 032913'!H86,'Datetel Feb 28, 2013'!I:I) -> 150000 | S86: =M86-R86 -> 0
A87: DW | B87: VC Admin Serv | C87: Linda Francis | D87: ACE-Negotiated 0.92% of COLA Health Benefit Reserve | G87: E | H87: 100_304169_7310_57300_819 | I87: 398419 | J87: =VLOOKUP(H87,'Datetel Feb 28, 2013'!A:F,6,0) -> 398419 | K87: =VLOOKUP(H87,'Datetel Feb 28, 2013'!A:G,7,0) -> 398419 | L87: =VLOOKUP(H87,'Datetel Feb 28, 2013'!A:I,8,0) -> 0 | M87: =J87-K87-L87 -> 0 | O87: =I87+N87 -> 398419 | P87: =I87-J87 -> 0 | R87: =SUMIF('Datetel Feb 28, 2013'!A:A,'1314T 032913'!H87,'Datetel Feb 28, 2013'!I:I) -> 0 | S87: =M87-R87 -> 0
A88: DW | B88: VC Admin Serv | D88: Analytic - Budget & Position Control | G88: F | H88: 100_304190_6720_55160_819 | I88: 15480 | J88: =VLOOKUP(H88,'Datetel Feb 28, 2013'!A:F,6,0) -> 15480 | K88: =VLOOKUP(H88,'Datetel Feb 28, 2013'!A:G,7,0) -> 15480 | L88: =VLOOKUP(H88,'Datetel Feb 28, 2013'!A:I,8,0) -> 0 | M88: =J88-K88-L88 -> 0 | O88: =I88+N88 -> 15480 | P88: =I88-J88 -> 0 | R88: =SUMIF('Datetel Feb 28, 2013'!A:A,'1314T 032913'!H88,'Datetel Feb 28, 2013'!I:I) -> 0 | S88: =M88-R88 -> 0
A89: DW | B89: Chancellor | C89: Linda Francis | D89: Elections/Redistricting Board Election | F89: Change in Trustee election/cost per yr | G89: D | H89: 100_300130_6600_55180_819 | I89: 190925 | J89: =VLOOKUP(H89,'Datetel Feb 28, 2013'!A:F,6,0) -> 190925 | K89: =VLOOKUP(H89,'Datetel Feb 28, 2013'!A:G,7,0) -> 77888.95 | L89: =VLOOKUP(H89,'Datetel Feb 28, 2013'!A:I,8,0) -> 0 | M89: =J89-K89-L89 -> 113036.05 | N89: =190925/-2 -> -95462.5 | O89: =I89+N89 -> 95462.5 | P89: =I89-J89 -> 0 | R89: =SUMIF('Datetel Feb 28, 2013'!A:A,'1314T 032913'!H89,'Datetel Feb 28, 2013'!I:I) -> 113036.05 | S89: =M89-R89 -> 0
A90: DW | B90: VC Admin Serv | C90: Ed Maduli/Christina | D90: Emergency Preparedness Services | G90: B | H90: 100_304180_6770_52350_819 | I90: 40000 | J90: =VLOOKUP(H90,'Datetel Feb 28, 2013'!A:F,6,0)+2000 -> 40000 | K90: =VLOOKUP(H90,'Datetel Feb 28, 2013'!A:G,7,0)+'Datetel Feb 28, 2013'!G201+'Datetel Feb 28, 2013'!G203+'Datetel Feb 28, 2013'!G204+'Datetel Feb 28, 2013'!G205 -> 14212.7 | L90: =VLOOKUP(H90,'Datetel Feb 28, 2013'!A:I,8,0) -> 0 | M90: =J90-K90-L90 -> 25787.3 | O90: =I90+N90 -> 40000 | P90: =I90-J90 -> 0 | R90: 26567.61 | S90: =M90-R90 -> -780.31
A91: DW | D91: Bank Service Charges | F91: collection agency | H91: 100_304197_6720_55185_819 | I91: 0 | J91: 0 | K91: =VLOOKUP(H91,'Datetel Feb 28, 2013'!A:G,7,0) -> 10.46 | L91: =VLOOKUP(H91,'Datetel Feb 28, 2013'!A:I,8,0) -> 0 | M91: =J91-K91-L91 -> -10.46 | O91: =I91+N91 -> 0 | P91: =I91-J91 -> 0 | R91: =SUMIF('Datetel Feb 28, 2013'!A:A,'1314T 032913'!H91,'Datetel Feb 28, 2013'!I:I) -> -10.46 | S91: =M91-R91 -> 0
D92: Bank Service Charges | F92: Over | H92: 100_304170_6720_55592_819 | I92: 0 | J92: 0 | K92: =VLOOKUP(H92,'Datetel Feb 28, 2013'!A:G,7,0) -> -81 | M92: =J92-K92-L92 -> 81 | O92: =I92+N92 -> 0
A93: DW | D93: Bank Service Charges | F93: Bank charges | H93: 100_304170_6720_55593_819 | I93: 15000 | J93: =VLOOKUP(H93,'Datetel Feb 28, 2013'!A:F,6,0) -> 15000 | K93: =VLOOKUP(H93,'Datetel Feb 28, 2013'!A:G,7,0) -> 16710.48 | L93: =VLOOKUP(H93,'Datetel Feb 28, 2013'!A:I,8,0) -> 0 | M93: =J93-K93-L93 -> -1710.48 | O93: =I93+N93 -> 15000 | P93: =I93-J93 -> 0 | R93: =SUMIF('Datetel Feb 28, 2013'!A:A,'1314T 032913'!H93,'Datetel Feb 28, 2013'!I:I) -> -1710.48 | S93: =M93-R93 -> 0
A94: DW | D94: Bank Service Charges | F94: E Commerce charges | H94: 100_304170_6720_55595_819 | I94: 165000 | J94: =VLOOKUP(H94,'Datetel Feb 28, 2013'!A:F,6,0) -> 165000 | K94: =VLOOKUP(H94,'Datetel Feb 28, 2013'!A:G,7,0) -> 119128.01 | L94: =VLOOKUP(H94,'Datetel Feb 28, 2013'!A:I,8,0) -> 0 | M94: =J94-K94-L94 -> 45871.99 | O94: =I94+N94 -> 165000 | P94: =I94-J94 -> 0 | R94: =SUMIF('Datetel Feb 28, 2013'!A:A,'1314T 032913'!H94,'Datetel Feb 28, 2013'!I:I) -> 45871.99 | S94: =M94-R94 -> 0
A95: DW | B95: VC Admin Serv | C95: Linda Francis/Susan | D95: Bank Service Charges | G95: G | H95: Multiple account numbers | I95: =SUM(I91:I94) -> 180000 | J95: =SUM(J91:J94) -> 180000 | K95: =SUM(K91:K94) -> 135767.95 | L95: =SUM(L91:L94) -> 0 | M95: =SUM(M91:M94) -> 44232.05 | O95: =I95+N95 -> 180000 | P95: =I95-J95 -> 0 | R95: =SUMIF('Datetel Feb 28, 2013'!A:A,'1314T 032913'!H95,'Datetel Feb 28, 2013'!I:I) -> 0
A96: DW | B96: VC Admin Serv | C96: Linda Francis | D96: Retiree Medical Benefits | G96: E | H96: 100_304190_7300_57300_819 | I96: 7822000 | J96: =VLOOKUP(H96,'Datetel Feb 28, 2013'!A:F,6,0) -> 7822000 | K96: =VLOOKUP(H96,'Datetel Feb 28, 2013'!A:G,7,0) -> 3911000 | L96: =VLOOKUP(H96,'Datetel Feb 28, 2013'!A:I,8,0) -> 0 | M96: =J96-K96-L96 -> 3911000 | O96: =I96+N96 -> 7822000 | P96: =I96-J96 -> 0 | R96: =SUMIF('Datetel Feb 28, 2013'!A:A,'1314T 032913'!H96,'Datetel Feb 28, 2013'!I:I) -> 3911000 | S96: =M96-R96 -> 0
A97: DW | B97: Dir of General Serv | C97: Brigit Espinosa | D97: Property/Liability Insurance | F97: liability insurance increase in cost | G97: D | H97: 100_309600_6770_55940_819 | I97: 639644 | J97: 639644 | K97: 639644 | L97: 0 | M97: =J97-K97-L97 -> 0 | N97: =I97*0.1 -> 63964.4 | O97: =I97+N97 -> 703608.4 | P97: =I97-J97 -> 0
A98: DW | B98: Dir of General Serv | C98: Brigit Espinosa | D98: Property/Liability Insurance Deductible | G98: D | H98: 100_309600_6770_55940_819 | I98: 40000 | J98: 40000 | K98: =VLOOKUP(H98,'Datetel Feb 28, 2013'!A:G,7,0)-K97 -> 26512.87 | L98: 0 | M98: =J98-K98-L98 -> 13487.13 | O98: =I98+N98 -> 40000 | P98: =I98-J98 -> 0 | R98: =SUMIF('Datetel Feb 28, 2013'!A:A,'1314T 032913'!H98,'Datetel Feb 28, 2013'!I:I) -> 13487.13 | S98: =M98-R98 -> 0
A99: DW | B99: AVC HR | C99: Linda Francis | D99: Unfunded Banked Leave | G99: E | H99: 100_305200_4900_51316_819 | I99: 164946 | J99: =VLOOKUP(H99,'Datetel Feb 28, 2013'!A:F,6,0) -> -12266 | K99: =VLOOKUP(H99,'Datetel Feb 28, 2013'!A:G,7,0) -> 0 | L99: 0 | M99: =J99-K99-L99 -> -12266 | O99: =I99+N99 -> 164946 | P99: =I99-J99 -> 177212 | R99: =SUMIF('Datetel Feb 28, 2013'!A:A,'1314T 032913'!H99,'Datetel Feb 28, 2013'!I:I) -> -12266 | S99: =M99-R99 -> 0
A100: DW | B100: AVC HR | C100: Linda Francis | D100: FT Faculty STRS contributions for excess sick leave | G100: E | H100: 100_305200_4900_53110_819 | I100: 7500 | J100: =VLOOKUP(H100,'Datetel Feb 28, 2013'!A:F,6,0) -> 7500 | K100: =VLOOKUP(H100,'Datetel Feb 28, 2013'!A:G,7,0) -> 1224.57 | L100: =VLOOKUP(H100,'Datetel Feb 28, 2013'!A:I,8,0) -> 0 | M100: =J100-K100-L100 -> 6275.43 | O100: =I100+N100 -> 7500 | P100: =I100-J100 -> 0 | R100: =SUMIF('Datetel Feb 28, 2013'!A:A,'1314T 032913'!H100,'Datetel Feb 28, 2013'!I:I) -> 6275.43 | S100: =M100-R100 -> 0
...

Sheet 1213A 080212
B1: MISSION COLLEGE
B2: Budget | I2: 11/12 | J2: 0.91666667 | K2: Actual Exp | L2: Budget Adjust. | M2: 12/13 | N2: Budget Adjust. | O2: 12/13
B3: Responsibility | C3: Contact Info. | D3: Fixed Cost Description | F3: Explanation for Adjustments | G3: Criteria | H3: Account Number | I3: Adopt Bud | J3: Working Bud | K3: as of 6/30/12 | L3: Incr / (Decr) | M3: Tent Bud | N3: Incr / (Decr) | O3: Adopt Bud
D4: Academic Senate - Supplies/Materials | H4: 100_206200_6750_54210_819 | I4: 1000 | J4: =VLOOKUP(H4,'cognos as of Aug 2'!A:F,6,0) -> 414 | K4: =VLOOKUP(H4,'cognos as of Aug 2'!A:G,7,0) -> 250 | M4: =SUM(I4+L4) -> 1000 | P4: =VLOOKUP(H4,Sheet4!A:C,3,0) -> 0
D5: Academic Senate - Food Services | H5: 100_206200_6750_55115_819 | J5: =VLOOKUP(H5,'cognos as of Aug 2'!A:F,6,0) -> 748 | K5: =VLOOKUP(H5,'cognos as of Aug 2'!A:G,7,0) -> 700 | M5: =SUM(I5+L5) -> 0
D6: Academic Senate - Travel & Conference | H6: 100_206200_6750_55200_819 | I6: 3000 | J6: =VLOOKUP(H6,'cognos as of Aug 2'!A:F,6,0) -> 2838 | K6: =VLOOKUP(H6,'cognos as of Aug 2'!A:G,7,0) -> 2838 | M6: =SUM(I6+L6) -> 3000 | P6: =VLOOKUP(H6,Sheet4!A:C,3,0) -> 0
B7: Senates | C7: Worku Negash | D7: Academic Senate | G7: C | H7: Multiple account numbers | I7: 4000 | J7: =SUM(J4:J6) -> 4000 | K7: =SUM(K4:K6) -> 3788 | L7: =SUM(L4:L6) -> 0 | M7: =SUM(I7+L7) -> 4000 | O7: =M7+N7 -> 4000 | P7: =VLOOKUP(H7,Sheet4!A:C,3,0) -> #N/A
D8: Classified Senate - Hrly classified Salary | H8: 100_206300_6750_52310_819 | I8: 1000 | J8: =VLOOKUP(H8,'cognos as of Aug 2'!A:F,6,0) -> 0 | K8: =VLOOKUP(H8,'cognos as of Aug 2'!A:G,7,0) -> 0 | M8: =SUM(I8+L8) -> 1000 | O8: =M8+N8 -> 1000 | P8: =VLOOKUP(H8,Sheet4!A:C,3,0) -> 0
D9: Classified Senate - Supplies/Materials | H9: 100_206300_6750_54210_819 | I9: 500 | J9: =VLOOKUP(H9,'cognos as of Aug 2'!A:F,6,0) -> 375 | K9: =VLOOKUP(H9,'cognos as of Aug 2'!A:G,7,0) -> 374.5 | M9: =SUM(I9+L9) -> 500 | O9: =M9+N9 -> 500 | P9: =VLOOKUP(H9,Sheet4!A:C,3,0) -> 0
D10: Classified Senate - Food Services | H10: 100_206300_6750_55115_819 | I10: 1500 | J10: =VLOOKUP(H10,'cognos as of Aug 2'!A:F,6,0) -> 483 | K10: =VLOOKUP(H10,'cognos as of Aug 2'!A:G,7,0) -> 482.44 | M10: =SUM(I10+L10) -> 1500 | O10: =M10+N10 -> 1500 | P10: =VLOOKUP(H10,Sheet4!A:C,3,0) -> 0
D11: Classified Senate - Travel & Conference | H11: 100_206300_6750_55205_819 | I11: 1500 | J11: =VLOOKUP(H11,'cognos as of Aug 2'!A:F,6,0) -> 3642 | K11: =VLOOKUP(H11,'cognos as of Aug 2'!A:G,7,0) -> 3642 | M11: =SUM(I11+L11) -> 1500 | O11: =M11+N11 -> 1500 | P11: =VLOOKUP(H11,Sheet4!A:C,3,0) -> 0
B12: Senates | C12: Worku Negash | D12: Classified Senate | G12: C | H12: Multiple account numbers | I12: 4500 | J12: =SUM(J8:J11) -> 4500 | K12: =SUM(K8:K11) -> 4498.94 | L12: =SUM(L8:L11) -> 0 | M12: =SUM(I12+L12) -> 4500 | O12: =M12+N12 -> 4500 | P12: =VLOOKUP(H12,Sheet4!A:C,3,0) -> #N/A
B13: Faculty Travel | C13: Worku Negash | D13: Faculty Travel & Conference | G13: E | H13: 100_290100_6600_55210_819 | I13: 28800 | J13: =VLOOKUP(H13,'cognos as of Aug 2'!A:F,6,0) -> 28800 | K13: =VLOOKUP(H13,'cognos as of Aug 2'!A:G,7,0) -> 15059.32 | M13: =SUM(I13+L13) -> 28800 | O13: =M13+N13 -> 28800 | P13: =VLOOKUP(H13,Sheet4!A:C,3,0) -> 0
B14: VP Admin. Services | C14: Worku Negash | D14: Tenure Faculty | G14: E | H14: 100_220910_4900_51310_819 | I14: 11000 | J14: =VLOOKUP(H14,'cognos as of Aug 2'!A:F,6,0) -> 11000 | K14: =VLOOKUP(H14,'cognos as of Aug 2'!A:G,7,0) -> 11000 | L14: 5500 | M14: =SUM(I14+L14) -> 16500 | O14: =M14+N14 -> 16500 | P14: =VLOOKUP(H14,Sheet4!A:C,3,0) -> 0
B15: Dean of Instr, Lib. St/LA | C15: Worku Negash | D15: Tricore, Link + Consortium, Library Maintenance | G15: A | H15: 100_230000_6120_55510_819 | I15: 33700 | J15: 33700 | K15: ='cognos as of Aug 2'!G86 -> 32592.83 | L15: 3894 | M15: =SUM(I15+L15) -> 37594 | O15: =M15+N15 -> 37594 | P15: =VLOOKUP(H15,Sheet4!A:C,3,0) -> multiple
B16: Dean of Instr, Lib. St/LA | D16: Turnkey Server Migration (One-Time) | F16: additional cost | G16: A | H16: 100_230000_6120_55510_819 | L16: 2250 | M16: =SUM(I16+L16) -> 2250 | N16: 2627 | O16: =M16+N16 -> 4877 | P16: =VLOOKUP(H16,Sheet4!A:C,3,0) -> multiple
H17: 100_290200_6110_55510_819 | K17: ='cognos as of Aug 2'!G103 -> 378.87 | O17: =M17+N17 -> 0
B18: VP Admin. Services | C18: Worku Negash | D18: Insurance for PE and Athletics Students | G18: C, D | H18: 100_220000_6440_55940_819 | I18: 73711 | J18: =VLOOKUP(H18,'cognos as of Aug 2'!A:F,6,0) -> 72074 | K18: =VLOOKUP(H18,'cognos as of Aug 2'!A:G,7,0) -> 73712 | M18: =SUM(I18+L18) -> 73711 | O18: =M18+N18 -> 73711 | P18: =VLOOKUP(H18,Sheet4!A:C,3,0) -> 0
B19: VP Admin. Services | C19: Worku Negash | D19: Coaches Stipends (Negotiated Item) | G19: E | H19: 100_220000_6770_51450_819 | I19: 15000 | J19: =VLOOKUP(H19,'cognos as of Aug 2'!A:F,6,0) -> 15000 | K19: 16464.69 | M19: =SUM(I19+L19) -> 15000 | O19: =M19+N19 -> 15000 | P19: =VLOOKUP(H19,Sheet4!A:C,3,0) -> 0
B20: College President | D20: Accreditation - Supplies/Materials | F20: Accreditation preparation | G20: C | H20: 100_200700_6090_54210_819 | I20: 0 | M20: =SUM(I20+L20) -> 0 | N20: 10000 | O20: =M20+N20 -> 10000 | P20: =VLOOKUP(H20,Sheet4!A:C,3,0) -> 0
B21: College President | D21: Accreditation - Professional Services | G21: C | H21: 100_200700_6090_55120_819 | I21: 0 | M21: =SUM(I21+L21) -> 0 | O21: =M21+N21 -> 0 | P21: =VLOOKUP(H21,Sheet4!A:C,3,0) -> 0
B22: College President | C22: Worku Negash | D22: Accreditation - Dues, Memberships & Fees | G22: C | H22: 100_200700_6090_55910_819 | I22: 17453 | J22: =VLOOKUP(H22,'cognos as of Aug 2'!A:F,6,0) -> 17453 | K22: =VLOOKUP(H22,'cognos as of Aug 2'!A:G,7,0) -> 17453 | M22: =SUM(I22+L22) -> 17453 | O22: =M22+N22 -> 17453 | P22: =VLOOKUP(H22,Sheet4!A:C,3,0) -> 0
B23: VP Admin. Services | C23: Linda Francis/Virginia | D23: Categorical Program: Transfer Out, Fringe Benefits | G23: C | H23: 100_220001_7310_57300_819 | I23: 370397 | J23: =VLOOKUP(H23,'cognos as of Aug 2'!A:F,6,0) -> 370397 | K23: =VLOOKUP(H23,'cognos as of Aug 2'!A:G,7,0) -> 332322.45 | L23: -30000 | M23: =SUM(I23+L23) -> 340397 | O23: =M23+N23 -> 340397 | P23: =VLOOKUP(H23,Sheet4!A:C,3,0) -> 0
B24: VP Admin. Services | C24: Linda Francis/Virginia | D24: Financial Aid Match: SEOG & Fed Work Study | F24: annual subs. refund/FA disburs. | G24: C | H24: 100_220002_7310_57300_819 | I24: 82111 | J24: 82111 | K24: ='cognos as of Aug 2'!G77 -> 79869 | M24: =SUM(I24+L24) -> 82111 | N24: 5902 | O24: =M24+N24 -> 88013 | P24: =VLOOKUP(H24,Sheet4!A:C,3,0) -> 0
B25: VP Admin. Services | D25: HigherOne | F25: New | G25: D | H25: 100_220900_6490_55160_819 | N25: 2500 | O25: =M25+N25 -> 2500
B26: Dir of Information Syst | C26: Worku Negash | D26: Astra Schedule/LaserFiche Avante/FormFusion | G26: A | H26: 100_220007_6010_55500_819 | I26: 0 | L26: 19057 | M26: =SUM(I26+L26) -> 19057 | O26: =M26+N26 -> 19057 | P26: =VLOOKUP(H26,Sheet4!A:C,3,0) -> 0
B27: Dir of Information Syst | C27: Worku Negash | D27: Curricunet | F27: 4% rebate for 12/13 | G27: A | H27: 100_220000_6010_55160_819 | I27: 7500 | J27: =VLOOKUP(H27,'cognos as of Aug 2'!A:F,6,0) -> 7800 | K27: =VLOOKUP(H27,'cognos as of Aug 2'!A:G,7,0) -> 7800 | L27: 300 | M27: =SUM(I27+L27) -> 7800 | N27: =-642/2 -> -321 | O27: =M27+N27 -> 7479 | P27: =VLOOKUP(H27,Sheet4!A:C,3,0) -> 0
B28: Dir of Information Syst | C28: Ron Smith | D28: CLARIS Class TRACKS | G28: A | H28: 100_220003_6750_55500_819 | I28: 2343 | J28: =VLOOKUP(H28,'cognos as of Aug 2'!A:F,6,0) -> 2343 | K28: =VLOOKUP(H28,'cognos as of Aug 2'!A:G,7,0) -> 0 | L28: -2343 | M28: =SUM(I28+L28) -> 0 | O28: =M28+N28 -> 0 | P28: =VLOOKUP(H28,Sheet4!A:C,3,0) -> 0
B29: Dir of Information Syst | C29: Ron Smith | D29: SARS Software Products -Counseling Sched System | G29: A | H29: 100_220004_6150_55500_819 | I29: 5670 | J29: 5670 | K29: ='cognos as of Aug 2'!G98 -> 6204.45 | L29: 830 | M29: =SUM(I29+L29) -> 6500 | O29: =M29+N29 -> 6500 | P29: =VLOOKUP(H29,Sheet4!A:C,3,0) -> 0
B30: Dir of Information Syst | C30: Ron Smith | D30: Angel | G30: A | H30: 100_220005_6150_55500_819 | I30: 75190 | J30: =VLOOKUP(H30,'cognos as of Aug 2'!A:F,6,0) -> 76527 | K30: =VLOOKUP(H30,'cognos as of Aug 2'!A:G,7,0) -> 57394.87 | L30: 3501 | M30: =SUM(I30+L30) -> 78691 | O30: =M30+N30 -> 78691 | P30: =VLOOKUP(H30,Sheet4!A:C,3,0) -> 0
B31: Dir of Information Syst | C31: Ron Smith | D31: CCCApply / BOGS (Student-Right-to-know) | G31: A | H31: 100_220006_6150_55500_819 | I31: 11259 | J31: =VLOOKUP(H31,'cognos as of Aug 2'!A:F,6,0) -> 11259 | K31: =VLOOKUP(H31,'cognos as of Aug 2'!A:G,7,0) -> 15384 | L31: 4350 | M31: =SUM(I31+L31) -> 15609 | O31: =M31+N31 -> 15609 | P31: =VLOOKUP(H31,Sheet4!A:C,3,0) -> 0
H32: Total Mission College | I32: 742634 | J32: =SUM(J7,J12,J13:J19,J22,J23:J31) -> 742634 | K32: =SUM(K7,K12,K13:K19,K22,K23:K31) -> 673922.42 | L32: =SUM(L7,L12,L13:L19,L22,L23:L31) -> 7339 | M32: =SUM(M7,M12:M31) -> 749973 | N32: =SUM(N7,N12:N31) -> 20708 | O32: =SUM(O7,O12:O31) -> 770681
M33: =SUM(I32+L32) -> 749973
B34: WEST VALLEY COLLEGE
B35: Budget | I35: 11/12 | J35: 0.91666667 | K35: Actual Exp | L35: Budget Adjust. | M35: 12/13 | N35: Budget Adjust. | O35: 12/13
B36: Responsibility | C36: Contact Info. | D36: Fixed Cost Description | E36: Detail Description | F36: Explanation for Adjustments | G36: Criteria | H36: Account Number | I36: Adopt Bud | J36: Working Bud | K36: as of 6/30/12 | L36: Incr / (Decr) | M36: Tent Bud | N36: Incr / (Decr) | O36: Adopt Bud
D37: Academic Senate -to be funded from other source | H37: 100_119304_6750_55115_819 | I37: 1100 | J37: =VLOOKUP(H37,'cognos as of Aug 2'!A:F,6,0) -> 1100 | K37: =VLOOKUP(H37,'cognos as of Aug 2'!A:G,7,0) -> 614.73 | M37: =SUM(I37+L37) -> 1100 | P37: =VLOOKUP(H37,Sheet4!A:C,3,0) -> 0
D38: Academic Senate -to be funded from other source | H38: 100_119304_6750_55200_819 | I38: 3300 | J38: =VLOOKUP(H38,'cognos as of Aug 2'!A:F,6,0) -> 3300 | K38: =VLOOKUP(H38,'cognos as of Aug 2'!A:G,7,0) -> 3308.65 | M38: =SUM(I38+L38) -> 3300 | P38: =VLOOKUP(H38,Sheet4!A:C,3,0) -> 0
B39: Senates | C39: Michael Renzi | D39: Academic Senate | G39: C | H39: Multiple account numbers | I39: =SUM(I37:I38) -> 4400 | J39: =SUM(J37:J38) -> 4400 | K39: =SUM(K37:K38) -> 3923.38 | L39: =SUM(L37:L38) -> 0 | M39: =SUM(I39+L39) -> 4400 | O39: =M39+N39 -> 4400 | P39: =VLOOKUP(H39,Sheet4!A:C,3,0) -> #N/A
D40: Classified Senate | H40: 100_119305_6750_55115_819 | I40: 660 | J40: =VLOOKUP(H40,'cognos as of Aug 2'!A:F,6,0) -> 2000 | K40: =VLOOKUP(H40,'cognos as of Aug 2'!A:G,7,0) -> 1685.51 | M40: =SUM(I40+L40) -> 660 | O40: =M40+N40 -> 660 | P40: =VLOOKUP(H40,Sheet4!A:C,3,0) -> 0
D41: Classified Senate | H41: 100_119305_6750_55160_819 | I41: 440 | J41: =VLOOKUP(H41,'cognos as of Aug 2'!A:F,6,0) -> 100 | K41: =VLOOKUP(H41,'cognos as of Aug 2'!A:G,7,0) -> 100 | M41: =SUM(I41+L41) -> 440 | O41: =M41+N41 -> 440 | P41: =VLOOKUP(H41,Sheet4!A:C,3,0) -> 0
D42: Classified Senate | H42: 100_119305_6750_55200_819 | I42: 3300 | J42: =VLOOKUP(H42,'cognos as of Aug 2'!A:F,6,0) -> 2300 | K42: =VLOOKUP(H42,'cognos as of Aug 2'!A:G,7,0) -> 2082.52 | M42: =SUM(I42+L42) -> 3300 | O42: =M42+N42 -> 3300 | P42: =VLOOKUP(H42,Sheet4!A:C,3,0) -> 0
B43: Senates | C43: Michael Renzi | D43: Classified Senate | G43: C | H43: Multiple account numbers | I43: =SUM(I40:I42) -> 4400 | J43: =SUM(J40:J42) -> 4400 | K43: =SUM(K40:K42) -> 3868.03 | L43: =SUM(L40:L42) -> 0 | M43: =SUM(I43+L43) -> 4400 | O43: =M43+N43 -> 4400 | P43: =VLOOKUP(H43,Sheet4!A:C,3,0) -> #N/A
B44: VP Admin. Services | C44: Michael Renzi | D44: Faculty Travel & Conference | G44: E | H44: 100_103201_6010_55210_819 | I44: 33200 | J44: 33200 | K44: =SUM('cognos as of Aug 2'!G32:G72) -> 9579.56 | L44: 0 | M44: =SUM(I44+L44) -> 33200 | O44: =M44+N44 -> 33200 | P44: =VLOOKUP(H44,Sheet4!A:C,3,0) -> 0
B45: VP Admin. Services | C45: Michael Renzi | D45: Tenure Faculty | G45: E | H45: 100_103251_4900_51310_819 | I45: 11000 | J45: =VLOOKUP(H45,'cognos as of Aug 2'!A:F,6,0) -> 11000 | K45: =VLOOKUP(H45,'cognos as of Aug 2'!A:G,7,0) -> 11000 | L45: 16500 | M45: =SUM(I45+L45) -> 27500 | O45: =M45+N45 -> 27500 | P45: =VLOOKUP(H45,Sheet4!A:C,3,0) -> 0
B46: Dean Learning Center | C46: Michael Renzi | D46: Tricore, Link + Consortium, Library Maintenance | E46: Consolidated budget for Link+ and other costs | G46: A | H46: 100_106100_6120_55510_819 | I46: 36261 | J46: =VLOOKUP(H46,'cognos as of Aug 2'!A:F,6,0) -> 36261 | K46: =VLOOKUP(H46,'cognos as of Aug 2'!A:G,7,0) -> 36027.14 | L46: 3894 | M46: =SUM(I46+L46) -> 40155 | O46: =M46+N46 -> 40155 | P46: =VLOOKUP(H46,Sheet4!A:C,3,0) -> multiple
B47: Dean Learning Center | C47: Michael Renzi | D47: Turnkey Server Migration (One-Time) | E47: Consolidated budget for Link+ and other costs | F47: additional cost | G47: A | H47: 100_106100_6120_55510_819 | L47: 2250 | M47: =SUM(I47+L47) -> 2250 | N47: 2627 | O47: =M47+N47 -> 4877 | P47: =VLOOKUP(H47,Sheet4!A:C,3,0) -> multiple
B48: Physical Education Division | C48: Michael Renzi | D48: Insurance for PE and Athletics Students | E48: Base from Final Budget. Increased from FY11 | G48: C, D | H48: 100_115200_6960_55940_819 | I48: 110568 | J48: =VLOOKUP(H48,'cognos as of Aug 2'!A:F,6,0) -> 110568 | K48: =VLOOKUP(H48,'cognos as of Aug 2'!A:G,7,0) -> 110567 | M48: =SUM(I48+L48) -> 110568 | O48: =M48+N48 -> 110568 | P48: =VLOOKUP(H48,Sheet4!A:C,3,0) -> 0
B49: Physical Education Division | C49: Michael Renzi | D49: Coaches Stipends (Negotiated Item) | G49: E | H49: 100_115200_6960_51450_819 | I49: 24625 | J49: 24625 | K49: 25928.34 | M49: =SUM(I49+L49) -> 24625 | O49: =M49+N49 -> 24625 | P49: =VLOOKUP(H49,Sheet4!A:C,3,0) -> 0
B50: College President | C50: Michael Renzi | D50: Accreditation - Dues, Memberships & Fees | G50: C | H50: 100_100100_6090_55910_819 | I50: 17453 | J50: 17453 | K50: 17453 | L50: 1500 | M50: =SUM(I50+L50) -> 18953 | O50: =M50+N50 -> 18953 | P50: =VLOOKUP(H50,Sheet4!A:C,3,0) -> 0
B51: College President | C51: Michael Renzi | D51: Accreditation - Supplies/Materials | F51: Accreditation preparation | G51: C | H51: 100_100100_6090_54210_819 | I51: 0 | J51: 0 | K51: 0 | L51: 0 | M51: =SUM(I51+L51) -> 0 | N51: 10000 | O51: =M51+N51 -> 10000 | P51: =VLOOKUP(H51,Sheet4!A:C,3,0) -> #N/A
B52: VP Admin. Services | C52: Linda Francis/Virginia | D52: Categorical Program: Transfer Out, Fringe Benefits | G52: C | H52: 100_103203_7310_57300_819 | I52: 468710 | J52: 468710 | K52: 468710 | L52: 0 | M52: =SUM(I52+L52) -> 468710 | O52: =M52+N52 -> 468710 | P52: =VLOOKUP(H52,Sheet4!A:C,3,0) -> 0
B53: VP Admin. Services | C53: Linda Francis/Virginia | D53: Financial Aid Match: SEOG, Fed Work Study | G53: C | H53: 100_103204_7310_57300_819 | I53: 80125 | J53: 80125 | K53: ='cognos as of Aug 2'!G7 -> 91021.19 | L53: 0 | M53: =SUM(I53+L53) -> 80125 | N53: =89345-80125 -> 9220 | O53: =M53+N53 -> 89345 | P53: =VLOOKUP(H53,Sheet4!A:C,3,0) -> 0
B54: VP Admin. Services | D54: HigherOne | F54: New | G54: D | H54: 100_102000_6490_55160_819 | N54: 2500 | O54: =M54+N54 -> 2500
B55: Dir of Information Syst | C55: Michael Renzi | D55: Astra Schedule/LaserFiche Avante/FormFusion | G55: A | H55: 100_103209_6010_55500_819 | I55: 0 | J55: 0 | K55: 0 | L55: 19057 | M55: =SUM(I55+L55) -> 19057 | O55: =M55+N55 -> 19057 | P55: =VLOOKUP(H55,Sheet4!A:C,3,0) -> 0
B56: Dir of Information Syst | C56: Michael Renzi | D56: Curricunet | F56: 4% rebate for 12/13 | G56: A | H56: 100_101000_6010_55160_819 | I56: 7500 | J56: =VLOOKUP(H56,'cognos as of Aug 2'!A:F,6,0) -> 7800 | K56: =VLOOKUP(H56,'cognos as of Aug 2'!A:G,7,0) -> 7800 | L56: 300 | M56: =SUM(I56+L56) -> 7800 | N56: =-642/2 -> -321 | O56: =M56+N56 -> 7479 | P56: =VLOOKUP(H56,Sheet4!A:C,3,0) -> 0
B57: Dir of Information Syst | C57: Ron Smith | D57: CLARIS Class TRACKS | G57: A | H57: 100_103205_6750_55500_819 | I57: 2343 | J57: =VLOOKUP(H57,'cognos as of Aug 2'!A:F,6,0) -> 2343 | K57: =VLOOKUP(H57,'cognos as of Aug 2'!A:G,7,0) -> 0 | L57: -2343 | M57: =SUM(I57+L57) -> 0 | O57: =M57+N57 -> 0 | P57: =VLOOKUP(H57,Sheet4!A:C,3,0) -> 0
B58: Dir of Information Syst | C58: Ron Smith | D58: SARS Software Products -Counseling Sched System | G58: A | H58: 100_103206_6150_55500_819 | I58: 5670 | J58: 5670 | K58: 6204.45 | L58: 830 | M58: =SUM(I58+L58) -> 6500 | O58: =M58+N58 -> 6500 | P58: =VLOOKUP(H58,Sheet4!A:C,3,0) -> 0
B59: Dir of Information Syst | C59: Ron Smith | D59: Angel | G59: A | H59: 100_103207_6150_55500_819 | I59: 75190 | J59: =VLOOKUP(H59,'cognos as of Aug 2'!A:F,6,0) -> 76527 | K59: =VLOOKUP(H59,'cognos as of Aug 2'!A:G,7,0) -> 57394.87 | L59: 3501 | M59: =SUM(I59+L59) -> 78691 | O59: =M59+N59 -> 78691 | P59: =VLOOKUP(H59,Sheet4!A:C,3,0) -> 0
B60: Dir of Information Syst | C60: Ron Smith | D60: CCCApply / BOGS (Student-Right-to-know) | G60: A | H60: 100_103208_6150_55500_819 | I60: 11259 | J60: =VLOOKUP(H60,'cognos as of Aug 2'!A:F,6,0) -> 11259 | K60: =VLOOKUP(H60,'cognos as of Aug 2'!A:G,7,0) -> 15384 | L60: 4350 | M60: =SUM(I60+L60) -> 15609 | O60: =M60+N60 -> 15609 | P60: =VLOOKUP(H60,Sheet4!A:C,3,0) -> 0
B61: Campbell Center | C61: Michael Renzi | D61: Campbell Center Lease | G61: D | H61: 100_131000_6470_55520_819 | I61: 34000 | J61: =VLOOKUP(H61,'cognos as of Aug 2'!A:F,6,0) -> 34000 | K61: =VLOOKUP(H61,'cognos as of Aug 2'!A:G,7,0) -> 68000 | M61: =SUM(I61+L61) -> 34000 | O61: =M61+N61 -> 34000 | P61: =VLOOKUP(H61,Sheet4!A:C,3,0) -> 0
D62: NISOD-Salary | H62: 100_119303_6720_51450_819 | I62: 4400 | J62: =VLOOKUP(H62,'cognos as of Aug 2'!A:F,6,0) -> 4400 | K62: =VLOOKUP(H62,'cognos as of Aug 2'!A:G,7,0) -> 0 | M62: =SUM(I62+L62) -> 4400 | O62: =M62+N62 -> 4400 | P62: =VLOOKUP(H62,Sheet4!A:C,3,0) -> 0
D63: NISOD-Supplies | H63: 100_119303_6720_54210_819 | I63: 0 | J63: 0 | K63: 0 | M63: =SUM(I63+L63) -> 0 | O63: =M63+N63 -> 0 | P63: =VLOOKUP(H63,Sheet4!A:C,3,0) -> 0
D64: NISOD-Food Services | H64: 100_119303_6750_55115_819 | I64: 1100 | J64: =VLOOKUP(H64,'cognos as of Aug 2'!A:F,6,0) -> 2095 | K64: =VLOOKUP(H64,'cognos as of Aug 2'!A:G,7,0) -> 2094.69 | M64: =SUM(I64+L64) -> 1100 | O64: =M64+N64 -> 1100 | P64: =VLOOKUP(H64,Sheet4!A:C,3,0) -> 0
D65: NISOD-Travel for faculty to go to Texas | H65: 100_119303_6750_55200_819 | I65: 3300 | J65: =VLOOKUP(H65,'cognos as of Aug 2'!A:F,6,0) -> 2305 | K65: =VLOOKUP(H65,'cognos as of Aug 2'!A:G,7,0) -> 1200 | M65: =SUM(I65+L65) -> 3300 | P65: =VLOOKUP(H65,Sheet4!A:C,3,0) -> 0
B66: Senates/ VP of Admin. Services | C66: Michael Renzi | D66: Professional Development | G66: C | H66: Multiple account numbers | I66: 8800 | J66: =SUM(J62:J65) -> 8800 | K66: =SUM(K62:K65) -> 3294.69 | L66: =SUM(L62:L65) -> 0 | M66: =SUM(I66+L66) -> 8800 | O66: =M66+N66 -> 8800
H67: Total West Valley College | I67: 935504 | J67: =SUM(J39,J43,J44:J61,J66) -> 937141 | K67: =SUM(K39,K43,K44:K61,K66) -> 936155.65 | L67: =SUM(L39,L43,L44:L61,L66) -> 49839 | M67: =SUM(M39,M43:M61,M66) -> 985343 | N67: =SUM(N39,N43:N61,N66) -> 24026 | O67: =SUM(O39,O43:O61,O66) -> 1009369
M68: =SUM(I67,L67) -> 985343
B69: DISTRICT WIDE
B70: Budget | I70: 11/12 | J70: 0.91666667 | K70: Actual Exp | L70: Budget Adjust. | M70: 12/13 | N70: Budget Adjust. | O70: 12/13
B71: Responsibility | C71: Contact Info. | D71: Fixed Cost Description | F71: Explanation for Adjustments | G71: Criteria | H71: Account Number | I71: Adopt Bud | J71: Working Bud | K71: as of 6/30/12 | L71: Incr / (Decr) | M71: Tent Bud | N71: Incr / (Decr) | O71: Adopt Bud
B72: VC Admin Serv | C72: Linda Francis | D72: Cal Grant Interest Payment | G72: C | H72: 100_304170_6720_55185_819 | I72: 4500 | J72: 4500 | K72: =VLOOKUP(H72,'cognos as of Aug 2'!A:G,7,0)-K73 -> 3723.22 | M72: =SUM(I72+L72) -> 4500 | O72: =M72+N72 -> 4500 | P72: =VLOOKUP(H72,Sheet4!A:C,3,0) -> multiple
B73: VC Admin Serv | C73: Linda Francis | D73: NDSL Collection Admin Costs (Perkins Loans) | G73: G | H73: 100_304170_6720_55185_819 | I73: 5000 | J73: 5000 | K73: 4254.47 | M73: =SUM(I73+L73) -> 5000 | O73: =M73+N73 -> 5000 | P73: =VLOOKUP(H73,Sheet4!A:C,3,0) -> multiple
B74: VC Admin Serv | C74: Linda Francis | D74: Faculty SERP Premium 5 of 5 yrs | F74: Final payment made in 12/13 | G74: E | H74: 100_304168_5900_53710_819 | I74: 50694 | J74: =VLOOKUP(H74,'cognos as of Aug 2'!A:F,6,0) -> 47825 | K74: =VLOOKUP(H74,'cognos as of Aug 2'!A:G,7,0) -> 47825 | L74: -50694 | M74: =SUM(I74+L74) -> 0 | N74: 47825 | O74: =M74+N74 -> 47825 | P74: =VLOOKUP(H74,Sheet4!A:C,3,0) -> 0
B75: VC Admin Serv | C75: Linda Francis | D75: Mngr/Conf/Supr SERP Premium 4 of 5 yrs | G75: E | H75: 100_304168_6740_53710_819 | I75: 196910 | J75: =VLOOKUP(H75,'cognos as of Aug 2'!A:F,6,0) -> 193709 | K75: =VLOOKUP(H75,'cognos as of Aug 2'!A:G,7,0) -> 193708.68 | M75: =SUM(I75+L75) -> 196910 | O75: =M75+N75 -> 196910 | P75: =VLOOKUP(H75,Sheet4!A:C,3,0) -> 0
D76: Utilities, Mission College - Utilities | H76: 100_304020_6570_55800_819 | I76: 677482 | J76: =VLOOKUP(H76,'cognos as of Aug 2'!A:F,6,0) -> 566528 | K76: =VLOOKUP(H76,'cognos as of Aug 2'!A:G,7,0) -> 628312.12 | M76: =SUM(I76+L76) -> 677482 | N76: -50000 | O76: =M76+N76 -> 627482 | P76: =VLOOKUP(H76,Sheet4!A:C,3,0) -> 0
D77: Utilities, Mission College - Gas | H77: 100_304020_6570_55811_819 | I77: 121560 | J77: =VLOOKUP(H77,'cognos as of Aug 2'!A:F,6,0) -> 176301 | K77: =VLOOKUP(H77,'cognos as of Aug 2'!A:G,7,0) -> 175141.63 | M77: =SUM(I77+L77) -> 121560 | O77: =M77+N77 -> 121560 | P77: =VLOOKUP(H77,Sheet4!A:C,3,0) -> 0
D78: Utilities, Mission College - Trash | H78: 100_304020_6570_55820_819 | I78: 30757.5 | J78: =VLOOKUP(H78,'cognos as of Aug 2'!A:F,6,0) -> 30758 | K78: =VLOOKUP(H78,'cognos as of Aug 2'!A:G,7,0) -> 24849.29 | M78: =SUM(I78+L78) -> 30757.5 | O78: =M78+N78 -> 30757.5 | P78: =VLOOKUP(H78,Sheet4!A:C,3,0) -> 0
D79: Utilities, Mission College - Water | H79: 100_304020_6570_55840_819 | I79: 55236 | J79: =VLOOKUP(H79,'cognos as of Aug 2'!A:F,6,0) -> 63357 | K79: =VLOOKUP(H79,'cognos as of Aug 2'!A:G,7,0) -> 79920.51 | M79: =SUM(I79+L79) -> 55236 | O79: =M79+N79 -> 55236 | P79: =VLOOKUP(H79,Sheet4!A:C,3,0) -> 0
D80: Utilities, Mission College - Sewer | H80: 100_304020_6570_55850_819 | I80: 14964 | J80: =VLOOKUP(H80,'cognos as of Aug 2'!A:F,6,0) -> 23079 | K80: =VLOOKUP(H80,'cognos as of Aug 2'!A:G,7,0) -> 25640.17 | M80: =SUM(I80+L80) -> 14964 | O80: =M80+N80 -> 14964 | P80: =VLOOKUP(H80,Sheet4!A:C,3,0) -> 0
B81: VC Admin Serv | C81: Linda Francis | D81: Utilities, Mission College | G81: F | H81: Multiple account numbers | I81: 899999.5 | J81: =SUM(J76:J80) -> 860023 | K81: =SUM(K76:K80) -> 933863.72 | L81: =SUM(L76:L80) -> 0 | M81: =SUM(I81+L81) -> 899999.5 | N81: =SUM(N76:N80) -> -50000 | O81: =M81+N81 -> 849999.5 | P81: =VLOOKUP(H81,Sheet4!A:C,3,0) -> #N/A
D82: Utilities, West Valley College - Utilities | H82: 100_304010_6570_55800_819 | I82: 706962.73 | J82: =VLOOKUP(H82,'cognos as of Aug 2'!A:F,6,0) -> 579822 | K82: =VLOOKUP(H82,'cognos as of Aug 2'!A:G,7,0) -> 617431.16 | M82: =SUM(I82+L82) -> 706962.73 | N82: -100000 | O82: =M82+N82 -> 606962.73 | P82: =VLOOKUP(H82,Sheet4!A:C,3,0) -> 0
D83: Utilities, West Valley College - Gas | H83: 100_304010_6570_55811_819 | I83: 159484.5 | J83: =VLOOKUP(H83,'cognos as of Aug 2'!A:F,6,0) -> 137314 | K83: =VLOOKUP(H83,'cognos as of Aug 2'!A:G,7,0) -> 131942.06 | M83: =SUM(I83+L83) -> 159484.5 | O83: =M83+N83 -> 159484.5 | P83: =VLOOKUP(H83,Sheet4!A:C,3,0) -> 0
D84: Utilities, West Valley College - Trash | H84: 100_304010_6570_55820_819 | I84: 21421.32 | J84: =VLOOKUP(H84,'cognos as of Aug 2'!A:F,6,0) -> 21421 | K84: =VLOOKUP(H84,'cognos as of Aug 2'!A:G,7,0) -> 21590.93 | M84: =SUM(I84+L84) -> 21421.32 | O84: =M84+N84 -> 21421.32 | P84: =VLOOKUP(H84,Sheet4!A:C,3,0) -> 0
D85: Utilities, West Valley College - Water | H85: 100_304010_6570_55840_819 | I85: 137895.45 | J85: =VLOOKUP(H85,'cognos as of Aug 2'!A:F,6,0) -> 143895 | K85: =VLOOKUP(H85,'cognos as of Aug 2'!A:G,7,0) -> 166197.52 | M85: =SUM(I85+L85) -> 137895.45 | O85: =M85+N85 -> 137895.45 | P85: =VLOOKUP(H85,Sheet4!A:C,3,0) -> 0
D86: Utilities, West Valley College - Sewer | E86: Sewer ( One payment each year) | H86: 100_304010_6570_55850_819 | I86: 74236 | J86: =VLOOKUP(H86,'cognos as of Aug 2'!A:F,6,0) -> 47707 | K86: =VLOOKUP(H86,'cognos as of Aug 2'!A:G,7,0) -> 47706.54 | M86: =SUM(I86+L86) -> 74236 | O86: =M86+N86 -> 74236 | P86: =VLOOKUP(H86,Sheet4!A:C,3,0) -> 0
B87: VC Admin Serv | C87: Linda Francis | D87: Utilities, West Valley College | G87: F | H87: Multiple account numbers | I87: 1100000 | J87: =SUM(J82:J86) -> 930159 | K87: =SUM(K82:K86) -> 984868.21 | L87: =SUM(L82:L86) -> 0 | M87: =SUM(I87+L87) -> 1100000 | N87: =SUM(N82:N86) -> -100000 | O87: =M87+N87 -> 1000000 | P87: =VLOOKUP(H87,Sheet4!A:C,3,0) -> #N/A
B88: VC Admin Serv | D88: Debt Service for LRB 2011 - Solar Project | G88: F,G | H88: 100-304197-7310-57300-819 | M88: 0 | N88: 150000 | O88: =M88+N88 -> 150000
B89: VC Admin Serv | C89: Linda Francis | D89: ACE-Negotiated 0.92% of COLA Health Benefit Reserve | G89: E | H89: 100_304169_7310_57300_819 | I89: 341575 | J89: =VLOOKUP(H89,'cognos as of Aug 2'!A:F,6,0) -> 398419 | K89: =VLOOKUP(H89,'cognos as of Aug 2'!A:G,7,0) -> 398419 | L89: 56844 | M89: =SUM(I89+L89) -> 398419 | O89: =M89+N89 -> 398419 | P89: =VLOOKUP(H89,Sheet4!A:C,3,0) -> 0
B90: VC Admin Serv | D90: Analytic - Budget & Position Control | G90: F | H90: 100_304190_6720_55160_819 | L90: 15480 | M90: =SUM(I90+L90) -> 15480 | O90: =M90+N90 -> 15480 | P90: =VLOOKUP(H90,Sheet4!A:C,3,0) -> 0
A91: DS | B91: Chancellor | C91: Linda Francis | D91: Elections/Redistricting Board Election | F91: Change in Trustee election | G91: D | H91: 100_300130_6600_55180_819 | I91: 180475 | J91: =VLOOKUP(H91,'cognos as of Aug 2'!A:F,6,0) -> 180475 | K91: =VLOOKUP(H91,'cognos as of Aug 2'!A:G,7,0) -> 718054 | L91: 180475 | M91: =SUM(I91+L91) -> 360950 | N91: =190925-360950 -> -170025 | O91: =M91+N91 -> 190925 | P91: =VLOOKUP(H91,Sheet4!A:C,3,0) -> 0
A92: DS | B92: VC Admin Serv | C92: Ed Maduli/Christina | D92: Emergency Preparedness Services | G92: B | H92: 100_304180_6770_52350_819 | I92: 40000 | J92: =VLOOKUP(H92,'cognos as of Aug 2'!A:F,6,0)+3000 -> 40000 | K92: =SUM('cognos as of Aug 2'!G142:G145) -> 29176.71 | M92: =SUM(I92+L92) -> 40000 | O92: =M92+N92 -> 40000 | P92: =VLOOKUP(H92,Sheet4!A:C,3,0) -> 0
A93: DS | D93: Bank Service Charges | F93: Over | H93: 100_304170_6720_55592_819 | I93: 0 | J93: 0 | K93: =VLOOKUP(H93,'cognos as of Aug 2'!A:G,7,0) -> -231 | M93: =SUM(I93+L93) -> 0 | O93: =M93+N93 -> 0 | P93: =VLOOKUP(H93,Sheet4!A:C,3,0) -> 0
A94: DS | D94: Bank Service Charges | F94: Bank charges | H94: 100_304170_6720_55593_819 | I94: 15000 | J94: =VLOOKUP(H94,'cognos as of Aug 2'!A:F,6,0) -> 19496 | K94: =VLOOKUP(H94,'cognos as of Aug 2'!A:G,7,0) -> 24334.26 | M94: =SUM(I94+L94) -> 15000 | O94: =M94+N94 -> 15000 | P94: =VLOOKUP(H94,Sheet4!A:C,3,0) -> 0
A95: DS | D95: Bank Service Charges | F95: E Commerce charges | H95: 100_304170_6720_55595_819 | I95: 165000 | J95: =VLOOKUP(H95,'cognos as of Aug 2'!A:F,6,0) -> 165000 | K95: =VLOOKUP(H95,'cognos as of Aug 2'!A:G,7,0) -> 216651.24 | M95: =SUM(I95+L95) -> 165000 | O95: =M95+N95 -> 165000 | P95: =VLOOKUP(H95,Sheet4!A:C,3,0) -> 0
A96: DS | B96: VC Admin Serv | C96: Linda Francis/Susan | D96: Bank Service Charges | G96: G | H96: Multiple account numbers | I96: =SUM(I93:I95) -> 180000 | J96: =SUM(J93:J95) -> 184496 | K96: =SUM(K93:K95) -> 240754.5 | L96: =SUM(L93:L95) -> 0 | M96: =SUM(I96+L96) -> 180000 | O96: =M96+N96 -> 180000 | P96: =VLOOKUP(H96,Sheet4!A:C,3,0) -> #N/A
A97: DS | D97: Retiree Medical Benefits - Instructional | F97: 100-304190-7310-57300-819 | H97: Multiple account numbers | I97: 4588774 | J97: 4363909 | K97: ='cognos as of Aug 2'!G146 -> 4350648.2 | L97: -343774 | M97: =SUM(I97+L97) -> 4245000 | O97: =M97+N97 -> 4245000 | P97: =VLOOKUP(H97,Sheet4!A:C,3,0) -> #N/A
A98: DS | D98: Retiree Medical Benefits - Non Instructional | F98: Interfund Transfer to Fund 293 | H98: Multiple account numbers | I98: 3920774 | J98: 3797227 | K98: ='cognos as of Aug 2'!G148 -> 3558377.8 | L98: -343774 | M98: =SUM(I98+L98) -> 3577000 | O98: =M98+N98 -> 3577000 | P98: =VLOOKUP(H98,Sheet4!A:C,3,0) -> #N/A
A99: DS | B99: VC Admin Serv | C99: Linda Francis | D99: Retiree Medical Benefits | G99: E | H99: Multiple account numbers | I99: =SUM(I97:I98) -> 8509548 | J99: =SUM(J97:J98) -> 8161136 | K99: =SUM(K97:K98) -> 7909026 | L99: =SUM(L97:L98) -> -687548 | M99: =SUM(I99+L99) -> 7822000 | O99: =M99+N99 -> 7822000 | P99: =VLOOKUP(H99,Sheet4!A:C,3,0) -> #N/A
A100: DS | B100: Dir of General Serv | C100: Brigit Espinosa | D100: Retiree Medical Benefits | F100: Increase in cost | G100: D | H100: 100_309600_6770_55940_819 | I100: 564984 | J100: 564984 | K100: 564984 | M100: =SUM(I100+L100) -> 564984 | N100: =639644-564984 -> 74660 | O100: =M100+N100 -> 639644 | P100: =VLOOKUP(H100,Sheet4!A:C,3,0) -> multiple
...

Sheet 1213T 031712
B1: MISSION COLLEGE
B2: Budget | I2: 11/12 | J2: 0.91666667 | K2: Actual Exp | M2: Available | N2: Budget Adjust. | O2: 12/13
B3: Responsibility | C3: Contact Info. | D3: Fixed Cost Description | F3: Explanation for Adjustments | G3: Criteria | H3: Account Number | I3: Adopt Bud | J3: Working Bud | K3: as of 2/8/12 | L3: Encumb. | M3: Budget | N3: Incr / (Decr) | O3: Tent Bud
D4: Academic Senate - Supplies/Materials | H4: 100_206200_6750_54210_819 | I4: 1000 | J4: 1000 | K4: 0 | L4: 250 | M4: =J4-K4-L4 -> 750 | O4: =SUM(I4+N4) -> 1000
D5: Academic Senate - Travel & Conference | H5: 100_206200_6750_55200_819 | I5: 3000 | J5: 3000 | K5: 1637 | L5: 0 | M5: =J5-K5-L5 -> 1363 | O5: =SUM(I5+N5) -> 3000
B6: Senates | C6: Worku Negash | D6: Academic Senate | G6: C | I6: 4000 | J6: =SUM(J4:J5) -> 4000 | K6: =SUM(K4:K5) -> 1637 | L6: =SUM(L4:L5) -> 250 | M6: =SUM(M4:M5) -> 2113 | N6: =SUM(N4:N5) -> 0 | O6: =SUM(I6+N6) -> 4000
D7: Classified Senate - Hrly classified Salary | H7: 100_206300_6750_52310_819 | I7: 1000 | J7: 1000 | K7: 0 | L7: 0 | M7: =J7-K7-L7 -> 1000 | O7: =SUM(I7+N7) -> 1000
D8: Classified Senate - Supplies/Materials | H8: 100_206300_6750_54210_819 | I8: 500 | J8: 500 | K8: 0 | L8: 0 | M8: =J8-K8-L8 -> 500 | O8: =SUM(I8+N8) -> 500
D9: Classified Senate - Food Services | H9: 100_206300_6750_55115_819 | I9: 1500 | J9: 1500 | K9: 182 | L9: 0 | M9: =J9-K9-L9 -> 1318 | O9: =SUM(I9+N9) -> 1500
D10: Classified Senate - Travel & Conference | H10: 100_206300_6750_55205_819 | I10: 1500 | J10: 1500 | K10: 0 | L10: 0 | M10: =J10-K10-L10 -> 1500 | O10: =SUM(I10+N10) -> 1500
B11: Senates | C11: Worku Negash | D11: Classified Senate | G11: C | I11: 4500 | J11: =SUM(J7:J10) -> 4500 | K11: =SUM(K7:K10) -> 182 | L11: =SUM(L7:L10) -> 0 | M11: =SUM(M7:M10) -> 4318 | N11: =SUM(N7:N10) -> 0 | O11: =SUM(I11+N11) -> 4500
B12: Faculty Travel | C12: Worku Negash | D12: Faculty Travel & Conference | F12: 144 FT Faculty @ $200 each | G12: E | H12: 100_290100_6600_55210_819 | I12: 28800 | J12: 28800 | K12: 3064 | L12: 0 | M12: =J12-K12-L12 -> 25736 | O12: =SUM(I12+N12) -> 28800
B13: VP Admin. Services | C13: Worku Negash | D13: Tenure Faculty | F13: 3 Faculty will receive tenure in 12/13 FY @ $5,500 each | G13: E | H13: 100_220910_4900_51310_819 | I13: 11000 | J13: 11000 | K13: 0 | L13: 0 | M13: =J13-K13-L13 -> 11000 | N13: 5500 | O13: =SUM(I13+N13) -> 16500
B14: Dean of Instr, Lib. St/LA | C14: Worku Negash | D14: Tricore, Link + Consortium, Library Maintenance | F14: Increase in cost | G14: A | H14: 100_230000_6120_55510_819 | I14: 33700 | J14: 33700 | K14: 30824 | L14: 2993 | M14: =J14-K14-L14 -> -117 | N14: 3894 | O14: =SUM(I14+N14) -> 37594
B15: Dean of Instr, Lib. St/LA | D15: Turnkey Server Migration (One-Time) | G15: A | H15: 100_230000_6120_55510_819 | N15: 2250 | O15: =SUM(I15+N15) -> 2250
B16: VP Admin. Services | C16: Worku Negash | D16: Insurance for PE and Athletics Students | G16: C, D | H16: 100_220000_6440_55940_819 | I16: 73711 | J16: 72074 | K16: 73712 | L16: 0 | M16: =J16-K16-L16 -> -1638 | O16: =SUM(I16+N16) -> 73711
B17: VP Admin. Services | C17: Worku Negash | D17: Coaches Stipends (Negotiated Item) | G17: E | H17: 100_220000_6770_51450_819 | I17: 15000 | J17: 15000 | K17: =3750+155+54+75+59+42 -> 4135 | L17: 0 | M17: =J17-K17-L17 -> 10865 | O17: =SUM(I17+N17) -> 15000
B18: College President | D18: Accreditation - Supplies/Materials | H18: 100_200700_6090_54210_819 | I18: 0 | M18: =J18-K18-L18 -> 0 | O18: =SUM(I18+N18) -> 0
B19: College President | D19: Accreditation - Professional Services | H19: 100_200700_6090_55120_819 | I19: 0 | M19: =J19-K19-L19 -> 0 | O19: =SUM(I19+N19) -> 0
B20: College President | D20: Accreditation - Other Reassigned Time | H20: 100_200700_6090_51227_819 | I20: 0 | M20: =J20-K20-L20 -> 0 | O20: =SUM(I20+N20) -> 0
B21: College President | C21: Worku Negash | D21: Accreditation - Dues, Memberships & Fees | G21: C | H21: 100_200700_6090_55910_819 | I21: 17453 | J21: 17453 | K21: 17453 | L21: =SUM(L18:L20) -> 0 | M21: =SUM(M18:M20) -> 0 | O21: =SUM(I21+N21) -> 17453
B22: VP Admin. Services | C22: Linda Francis/Virginia | D22: Categorical Program: Transfer Out, Fringe Benefits | F22: Budget Reduction Plan | G22: C | H22: 100_220001_7310_57300_819 | I22: 370397 | J22: 370397 | K22: 93566 | L22: 0 | M22: =J22-K22-L22 -> 276831 | N22: -30000 | O22: =SUM(I22+N22) -> 340397
B23: VP Admin. Services | C23: Linda Francis/Virginia | D23: Financial Aid Match: SEOG & Fed Work Study | G23: C | H23: 100_220002_7310_57300_819 | I23: 82111 | J23: 82111 | K23: 0 | L23: 0 | M23: =J23-K23-L23 -> 82111 | O23: =SUM(I23+N23) -> 82111
B24: Dir of Information Syst | C24: Worku Negash | D24: Astra Schedule/LaserFiche Avante/FormFusion | F24: New | G24: A | H24: 100_220007_6010_55500_819 | I24: 0 | J24: 0 | K24: 0 | M24: =J24-K24-L24 -> 0 | N24: 19057 | O24: =SUM(I24+N24) -> 19057
B25: Dir of Information Syst | C25: Worku Negash | D25: Curricunet | F25: Increase in cost | G25: A | H25: 100_220000_6010_55160_819 | I25: 7500 | J25: 7800 | K25: 7800 | M25: =J25-K25-L25 -> 0 | N25: 300 | O25: =SUM(I25+N25) -> 7800
B26: Dir of Information Syst | C26: Ron Smith | D26: CLARIS Class TRACKS | F26: No longer need | G26: A | H26: 100_220003_6750_55500_819 | I26: 2343 | J26: 2343 | K26: 0 | L26: 0 | M26: =J26-K26-L26 -> 2343 | N26: -2343 | O26: =SUM(I26+N26) -> 0
B27: Dir of Information Syst | C27: Ron Smith | D27: SARS Software Products -Counseling Sched System | F27: Increase in cost | G27: A | H27: 100_220004_6150_55500_819 | I27: 5670 | J27: 5670 | K27: 6204 | L27: 0 | M27: =J27-K27-L27 -> -534 | N27: 830 | O27: =SUM(I27+N27) -> 6500
B28: Dir of Information Syst | C28: Ron Smith | D28: Angel | F28: Increase in cost | G28: A | H28: 100_220005_6150_55500_819 | I28: 75190 | J28: 76527 | K28: 76527 | L28: 0 | M28: =J28-K28-L28 -> 0 | N28: 3501 | O28: =SUM(I28+N28) -> 78691
B29: Dir of Information Syst | C29: Ron Smith | D29: CCCApply / BOGS (Student-Right-to-know) | F29: Increase in cost | G29: A | H29: 100_220006_6150_55500_819 | I29: 11259 | J29: 11259 | K29: 15384 | M29: =J29-K29-L29 -> -4125 | N29: 4350 | O29: =SUM(I29+N29) -> 15609
H30: Total Mission College | I30: 742634 | J30: =SUM(J6,J11,J12:J17,J21,J22:J29) -> 742634 | K30: =SUM(K6,K11,K12:K17,K21,K22:K29) -> 330488 | L30: =SUM(L6,L11,L12:L17,L21,L22:L29) -> 3243 | M30: =SUM(M6,M11,M12:M17,M21,M22:M29) -> 408903 | N30: =SUM(N6,N11,N12:N17,N21,N22:N29) -> 7339 | O30: =SUM(O6,O11:O29) -> 749973
O31: =SUM(I30+N30) -> 749973
B32: WEST VALLEY COLLEGE
B33: Budget | I33: 11/12 | J33: 0.91666667 | K33: Actual Exp | M33: Available | N33: Budget Adjust. | O33: 12/13
B34: Responsibility | C34: Contact Info. | D34: Fixed Cost Description | E34: Detail Description | F34: Explanation for Adjustments | G34: Criteria | H34: Account Number | I34: Adopt Bud | J34: Working Bud | K34: as of 2/8/12 | L34: Encumb. | M34: Budget | N34: Incr / (Decr) | O34: Tent Bud
D35: Academic Senate -to be funded from other source | H35: 100_119304_6750_55115_819 | I35: 1100 | J35: 1100 | K35: 615 | L35: 0 | M35: =J35-K35 -> 485 | O35: =SUM(I35+N35) -> 1100
D36: Academic Senate -to be funded from other source | H36: 100_119304_6750_55200_819 | I36: 3300 | J36: 3300 | K36: 378 | L36: 0 | M36: =J36-K36 -> 2922 | O36: =SUM(I36+N36) -> 3300
B37: Senates | C37: Michael Renzi | D37: Academic Senate | G37: C | I37: =SUM(I35:I36) -> 4400 | J37: =SUM(J35:J36) -> 4400 | K37: =SUM(K35:K36) -> 993 | L37: =SUM(L35:L36) -> 0 | M37: =SUM(M35:M36) -> 3407 | N37: =SUM(N35:N36) -> 0 | O37: =SUM(I37+N37) -> 4400
D38: Classified Senate | H38: 100_119305_6750_55115_819 | I38: 660 | J38: 660 | K38: 0 | L38: 0 | M38: =J38-K38 -> 660 | O38: =SUM(I38+N38) -> 660
D39: Classified Senate | H39: 100_119305_6750_55160_819 | I39: 440 | J39: 440 | K39: 100 | L39: 0 | M39: =J39-K39 -> 340 | O39: =SUM(I39+N39) -> 440
D40: Classified Senate | H40: 100_119305_6750_55200_819 | I40: 3300 | J40: 3300 | K40: 0 | L40: 0 | M40: =J40-K40 -> 3300 | O40: =SUM(I40+N40) -> 3300
B41: Senates | C41: Michael Renzi | D41: Classified Senate | G41: C | I41: =SUM(I38:I40) -> 4400 | J41: =SUM(J38:J40) -> 4400 | K41: =SUM(K38:K40) -> 100 | L41: =SUM(L38:L40) -> 0 | M41: =SUM(M38:M40) -> 4300 | N41: =SUM(N38:N40) -> 0 | O41: =SUM(I41+N41) -> 4400
B42: VP Admin. Services | C42: Michael Renzi | D42: Faculty Travel & Conference | F42: 166 FT Faculty @ $200 each | G42: E | H42: 100_103201_6010_55210_819 | I42: 33200 | J42: 33200 | K42: 3172 | L42: 0 | M42: =J42-K42 -> 30028 | N42: 0 | O42: =SUM(I42+N42) -> 33200
B43: VP Admin. Services | C43: Michael Renzi | D43: Tenure Faculty | F43: 5 Faculty will receive tenure in 12/13 FY @ $5,500 each | G43: E | H43: 100_103251_4900_51310_819 | I43: 11000 | J43: 11000 | K43: 0 | M43: =J43-K43 -> 11000 | N43: 16500 | O43: =SUM(I43+N43) -> 27500
B44: Dean Learning Center | C44: Michael Renzi | D44: Tricore, Link + Consortium, Library Maintenance | E44: Consolidated budget for Link+ and other costs | F44: Increase in cost | G44: A | H44: 100_106100_6120_55510_819 | I44: 36261 | J44: 36261 | K44: 34063 | L44: 2198 | M44: =J44-K44-L44 -> 0 | N44: 3894 | O44: =SUM(I44+N44) -> 40155
B45: Dean Learning Center | C45: Michael Renzi | D45: Turnkey Server Migration (One-Time) | E45: Consolidated budget for Link+ and other costs | G45: A | H45: 100_106100_6120_55510_819 | N45: 2250 | O45: =SUM(I45+N45) -> 2250
B46: Physical Education Division | C46: Michael Renzi | D46: Insurance for PE and Athletics Students | E46: Base from Final Budget. Increased from FY11 | G46: C, D | H46: 100_115200_6960_55940_819 | I46: 110568 | J46: 110568 | K46: 110567 | L46: 0 | M46: =J46-K46 -> 1 | O46: =SUM(I46+N46) -> 110568
B47: Physical Education Division | C47: Michael Renzi | D47: Coaches Stipends (Negotiated Item) | F47: $125 per day x 197 days | G47: E | H47: 100_115200_6960_51450_819 | I47: 24625 | J47: 24625 | K47: =712+125+50+158+113 -> 1158 | L47: 0 | M47: =J47-K47 -> 23467 | O47: =SUM(I47+N47) -> 24625
B48: College President | C48: Michael Renzi | D48: Accreditation - Dues, Memberships & Fees | F48: Increase in cost | G48: C | H48: 100_100100_6090_55910_819 | I48: 17453 | J48: 17453 | K48: 17453 | L48: 0 | M48: =J48-K48 -> 0 | N48: 1500 | O48: =SUM(I48+N48) -> 18953
B49: College President | C49: Michael Renzi | D49: Accreditation - Other Reassign Time | G49: C | H49: 100_100100_6090_51227_819 | I49: 0 | J49: 0 | K49: 0 | L49: 0 | M49: =J49-K49 -> 0 | N49: 0 | O49: =SUM(I49+N49) -> 0
B50: VP Admin. Services | C50: Linda Francis/Virginia | D50: Categorical Program: Transfer Out, Fringe Benefits | G50: C | H50: 100_103203_7310_57300_819 | I50: 468710 | J50: 468710 | K50: 468710 | L50: 0 | M50: =J50-K50 -> 0 | N50: 0 | O50: =SUM(I50+N50) -> 468710
B51: VP Admin. Services | C51: Linda Francis/Virginia | D51: Financial Aid Match: SEOG, Fed Work Study | G51: C | H51: 100_103204_7310_57300_819 | I51: 80125 | J51: 80125 | K51: 0 | L51: 0 | M51: =J51-K51 -> 80125 | N51: 0 | O51: =SUM(I51+N51) -> 80125
B52: Dir of Information Syst | C52: Michael Renzi | D52: Astra Schedule/LaserFiche Avante/FormFusion | F52: New | G52: A | H52: 100_103209_6010_55500_819 | I52: 0 | J52: 0 | K52: 0 | L52: 0 | M52: =J52-K52 -> 0 | N52: 19057 | O52: =SUM(I52+N52) -> 19057
B53: Dir of Information Syst | C53: Michael Renzi | D53: Curricunet | F53: Increase in cost | G53: A | H53: 100_101000_6010_55160_819 | I53: 7500 | J53: 7800 | K53: 7800 | L53: 0 | M53: =J53-K53 -> 0 | N53: 300 | O53: =SUM(I53+N53) -> 7800
B54: Dir of Information Syst | C54: Ron Smith | D54: CLARIS Class TRACKS | F54: No longer needed | G54: A | H54: 100_103205_6750_55500_819 | I54: 2343 | J54: 2343 | K54: 0 | L54: 0 | M54: =J54-K54 -> 2343 | N54: -2343 | O54: =SUM(I54+N54) -> 0
B55: Dir of Information Syst | C55: Ron Smith | D55: SARS Software Products -Counseling Sched System | F55: Increase in cost | G55: A | H55: 100_103206_6150_55500_819 | I55: 5670 | J55: 5670 | K55: 6204 | L55: 0 | M55: =J55-K55 -> -534 | N55: 830 | O55: =SUM(I55+N55) -> 6500
B56: Dir of Information Syst | C56: Ron Smith | D56: Angel | F56: Increase in cost | G56: A | H56: 100_103207_6150_55500_819 | I56: 75190 | J56: 76527 | K56: 76527 | L56: 0 | M56: =J56-K56 -> 0 | N56: 3501 | O56: =SUM(I56+N56) -> 78691
B57: Dir of Information Syst | C57: Ron Smith | D57: CCCApply / BOGS (Student-Right-to-know) | F57: Increase in cost | G57: A | H57: 100_103208_6150_55500_819 | I57: 11259 | J57: 11259 | K57: 15384 | L57: 0 | M57: =J57-K57 -> -4125 | N57: 4350 | O57: =SUM(I57+N57) -> 15609
B58: Campbell Center | C58: Michael Renzi | D58: Campbell Center Lease | G58: D | H58: 100_131000_6470_55520_819 | I58: 34000 | J58: 34000 | K58: 34000 | L58: 0 | M58: =J58-K58 -> 0 | O58: =SUM(I58+N58) -> 34000
D59: NISOD-Salary | H59: 100_119303_6720_51450_819 | I59: 4400 | J59: 4400 | K59: 0 | L59: 0 | M59: =J59-K59 -> 4400 | O59: =SUM(I59+N59) -> 4400
D60: NISOD-Supplies | H60: 100_119303_6720_54210_819 | I60: 0 | M60: =J60-K60 -> 0 | O60: =SUM(I60+N60) -> 0
D61: NISOD-Food Services | H61: 100_119303_6750_55115_819 | I61: 1100 | J61: 1100 | K61: 606.25 | L61: 0 | M61: =J61-K61 -> 493.75 | O61: =SUM(I61+N61) -> 1100
D62: NISOD-Travel for faculty to go to Texas | H62: 100_119303_6750_55200_819 | I62: 3300 | J62: 3300 | K62: 0 | L62: 0 | M62: =J62-K62 -> 3300 | O62: =SUM(I62+N62) -> 3300
B63: Senates/ VP of Admin. Services | C63: Michael Renzi | D63: Professional Development | G63: C | I63: 8800 | J63: =SUM(J59:J62) -> 8800 | K63: =SUM(K59:K62) -> 606.25 | L63: =SUM(L59:L62) -> 0 | M63: =SUM(M59:M62) -> 8193.75 | N63: =SUM(N59:N62) -> 0 | O63: =SUM(I63+N63) -> 8800
H64: Total West Valley College | I64: 935504 | J64: =SUM(J37,J41,J42:J58,J63) -> 937141 | K64: =SUM(K37,K41,K42:K58,K63) -> 776737.25 | L64: =SUM(L37,L41,L42:L58,L63) -> 2198 | M64: =SUM(M37,M41,M42:M58,M63) -> 158205.75 | N64: =SUM(N37,N41,N42:N58,N63) -> 49839 | O64: =SUM(O37,O41:O58,O63) -> 985343
O65: =SUM(I64,N64) -> 985343
B66: DISTRICT WIDE
B67: Budget | I67: 11/12 | J67: 0.91666667 | K67: Actual Exp | M67: Available | N67: Budget Adjust. | O67: 12/13
B68: Responsibility | C68: Contact Info. | D68: Fixed Cost Description | F68: Explanation for Adjustments | G68: Criteria | H68: Account Number | I68: Adopt Bud | J68: Working Bud | K68: as of 2/8/12 | L68: Encumb. | M68: Budget | N68: Incr / (Decr) | O68: Tent Bud
B69: VC Admin Serv | C69: Linda Francis | D69: Cal Grant Interest Payment | G69: C | H69: 100_304170_6720_55185_819 | I69: 4500 | J69: 4500 | K69: 2250 | L69: 0 | M69: =J69-K69-L69 -> 2250 | O69: =SUM(I69+N69) -> 4500
B70: VC Admin Serv | C70: Linda Francis | D70: NDSL Collection Admin Costs (Perkins Loans) | G70: G | H70: 100_304170_6720_55185_819 | I70: 5000 | J70: 5000 | K70: 3602 | L70: 0 | M70: =J70-K70-L70 -> 1398 | O70: =SUM(I70+N70) -> 5000
B71: VC Admin Serv | C71: Linda Francis | D71: Faculty SERP Premium 5 of 5 yrs | F71: Final payment made in 11/12 | G71: E | H71: 100_304168_5900_53710_819 | I71: 50694 | J71: 50694 | K71: 47825 | L71: 0 | M71: =J71-K71-L71 -> 2869 | N71: -50694 | O71: =SUM(I71+N71) -> 0
B72: VC Admin Serv | C72: Linda Francis | D72: Mngr/Conf/Supr SERP Premium 4 of 5 yrs | G72: E | H72: 100_304168_6740_53710_819 | I72: 196910 | J72: 196910 | K72: 193709 | L72: 0 | M72: =J72-K72-L72 -> 3201 | O72: =SUM(I72+N72) -> 196910
D73: Utilities, Mission College - Utilities | H73: 100_304020_6570_55800_819 | I73: 677482 | J73: 677482 | K73: 398602 | L73: 0 | M73: =J73-K73-L73 -> 278880 | O73: =SUM(I73+N73) -> 677482
D74: Utilities, Mission College - Gas | H74: 100_304020_6570_55811_819 | I74: 121560 | J74: 121560 | K74: 88963 | L74: 0 | M74: =J74-K74-L74 -> 32597 | O74: =SUM(I74+N74) -> 121560
D75: Utilities, Mission College - Trash | H75: 100_304020_6570_55820_819 | I75: 30757.5 | J75: 30758 | K75: 12082 | L75: 18676 | M75: =J75-K75-L75 -> 0 | O75: =SUM(I75+N75) -> 30757.5
D76: Utilities, Mission College - Water | H76: 100_304020_6570_55840_819 | I76: 55236 | J76: 55236 | K76: 40691 | L76: 0 | M76: =J76-K76-L76 -> 14545 | O76: =SUM(I76+N76) -> 55236
D77: Utilities, Mission College - Sewer | H77: 100_304020_6570_55850_819 | I77: 14964 | J77: 14964 | K77: 12567 | L77: 0 | M77: =J77-K77-L77 -> 2397 | O77: =SUM(I77+N77) -> 14964
B78: VC Admin Serv | C78: Linda Francis | D78: Utilities, Mission College | G78: F | H78: Multiple account numbers | I78: 899999.5 | J78: =SUM(J73:J77) -> 900000 | K78: =SUM(K73:K77) -> 552905 | L78: =SUM(L73:L77) -> 18676 | M78: =SUM(M73:M77) -> 328419 | N78: =SUM(N73:N77) -> 0 | O78: =SUM(I78+N78) -> 899999.5
D79: Utilities, West Valley College - Utilities | H79: 100_304010_6570_55800_819 | I79: 706962.73 | J79: 706963 | K79: 414566 | L79: 0 | M79: =J79-K79-L79 -> 292397 | O79: =SUM(I79+N79) -> 706962.73
D80: Utilities, West Valley College - Gas | H80: 100_304010_6570_55811_819 | I80: 159484.5 | J80: 159485 | K80: 58697 | L80: 0 | M80: =J80-K80-L80 -> 100788 | O80: =SUM(I80+N80) -> 159484.5
D81: Utilities, West Valley College - Trash | H81: 100_304010_6570_55820_819 | I81: 21421.32 | J81: 21421 | K81: 4136 | L81: 17285 | M81: =J81-K81-L81 -> 0 | O81: =SUM(I81+N81) -> 21421.32
D82: Utilities, West Valley College - Water | H82: 100_304010_6570_55840_819 | I82: 137895.45 | J82: 137895 | K82: 111963 | L82: 0 | M82: =J82-K82-L82 -> 25932 | O82: =SUM(I82+N82) -> 137895.45
D83: Utilities, West Valley College - Sewer | E83: Sewer ( One payment each year) | H83: 100_304010_6570_55850_819 | I83: 74236 | J83: 74236 | K83: 47707 | L83: 0 | M83: =J83-K83-L83 -> 26529 | O83: =SUM(I83+N83) -> 74236
B84: VC Admin Serv | C84: Linda Francis | D84: Utilities, West Valley College | G84: F | H84: Multiple account numbers | I84: 1100000 | J84: =SUM(J79:J83) -> 1100000 | K84: =SUM(K79:K83) -> 637069 | L84: =SUM(L79:L83) -> 17285 | M84: =SUM(M79:M83) -> 445646 | N84: =SUM(N79:N83) -> 0 | O84: =SUM(I84+N84) -> 1100000
B85: VC Admin Serv | C85: Linda Francis | D85: ACE-Negotiated 0.92% of COLA Health Benefit Reserve | G85: E | H85: 100_304169_7310_57300_819 | I85: 341575 | J85: 341575 | K85: 341575 | L85: 0 | M85: =J85-K85-L85 -> 0 | N85: 56844 | O85: =SUM(I85+N85) -> 398419
B86: VC Admin Serv | D86: Analytic - Budget & Position Control | F86: New | G86: F | H86: 100_304190_6720_55160_819 | N86: 15480 | O86: =SUM(I86+N86) -> 15480
A87: DS | B87: Chancellor | C87: Linda Francis | D87: Board Elections/Redistricting Board Election | F87: 2 year budget cycle | G87: D | H87: 100_300130_6600_55180_819 | I87: 180475 | J87: 180475 | K87: 33500 | L87: 500 | M87: =J87-K87-L87 -> 146475 | N87: 180475 | O87: =SUM(I87+N87) -> 360950
A88: DS | B88: VC Admin Serv | C88: Ed Maduli/Christina | D88: Emergency Preparedness Services | G88: B | H88: 100_304180_6770_52350_819 | I88: 40000 | J88: 40000 | K88: =4775+69+77+55+4275+72+80+57 -> 9460 | L88: 0 | M88: =J88-K88-L88 -> 30540 | O88: =SUM(I88+N88) -> 40000
A89: DS | D89: Bank Service Charges | F89: Over | H89: 100_304170_6720_55592_819 | I89: 0 | J89: 0 | K89: -195 | M89: =J89-K89-L89 -> 195 | O89: =SUM(I89+N89) -> 0
A90: DS | D90: Bank Service Charges | F90: Bank charges | H90: 100_304170_6720_55593_819 | I90: 15000 | J90: 15000 | K90: 11262 | M90: =J90-K90-L90 -> 3738 | O90: =SUM(I90+N90) -> 15000
A91: DS | D91: Bank Service Charges | F91: E Commerce charges | H91: 100_304170_6720_55595_819 | I91: 165000 | J91: 165000 | K91: 84240 | M91: =J91-K91-L91 -> 80760 | O91: =SUM(I91+N91) -> 165000
A92: DS | B92: VC Admin Serv | C92: Linda Francis/Susan | D92: Bank Service Charges | G92: G | H92: Multiple account numbers | I92: =SUM(I89:I91) -> 180000 | J92: =SUM(J89:J91) -> 180000 | K92: =SUM(K89:K91) -> 95307 | L92: =SUM(L89:L91) -> 0 | M92: =SUM(M89:M91) -> 84693 | N92: =SUM(N89:N91) -> 0 | O92: =SUM(I92+N92) -> 180000
A93: DS | D93: Retiree Medical Benefits - Instructional | F93: 100-304190-7310-57300-819 | H93: Multiple account numbers | I93: 4588774 | J93: 4588774 | K93: 2380852 | L93: 0 | M93: =J93-K93-L93 -> 2207922 | N93: -343774 | O93: =SUM(I93+N93) -> 4245000
A94: DS | D94: Retiree Medical Benefits - Non Instructional | F94: Interfund Transfer to Fund 293 | H94: Multiple account numbers | I94: 3920774 | J94: 3920774 | K94: 2038322 | L94: 0 | M94: =J94-K94-L94 -> 1882452 | N94: -343774 | O94: =SUM(I94+N94) -> 3577000
A95: DS | B95: VC Admin Serv | C95: Linda Francis | D95: Retiree Medical Benefits | F95: Stabilize cost at $7,822,000 | G95: E | H95: Multiple account numbers | I95: =SUM(I93:I94) -> 8509548 | J95: =SUM(J93:J94) -> 8509548 | K95: =SUM(K93:K94) -> 4419174 | L95: =SUM(L93:L94) -> 0 | M95: =SUM(M93:M94) -> 4090374 | N95: =SUM(N93:N94) -> -687548 | O95: =SUM(I95+N95) -> 7822000
A96: DS | B96: Dir of General Serv | C96: Brigit Espinosa | D96: Property/Liability Insurance | G96: D | H96: 100_309600_6770_55940_819 | I96: 564984 | J96: 564984 | K96: 564984 | L96: 0 | M96: =J96-K96-L96 -> 0 | O96: =SUM(I96+N96) -> 564984
A97: DS | B97: Dir of General Serv | C97: Brigit Espinosa | D97: Property/Liability Insurance Deductible | G97: D | H97: 100_309600_6770_55940_819 | I97: 40000 | J97: 40000 | K97: 5239 | L97: 0 | M97: =J97-K97-L97 -> 34761 | O97: =SUM(I97+N97) -> 40000
A98: DS | B98: AVC HR | C98: Linda Francis | D98: Unfunded Banked Leave | G98: E | H98: 100_305200_4900_51316_819 | I98: 207307 | J98: 288884 | K98: 0 | L98: 0 | M98: =J98-K98-L98 -> 288884 | O98: =SUM(I98+N98) -> 207307
A99: DS | B99: AVC HR | C99: Linda Francis | D99: FT Faculty STRS contributions for excess sick leave | G99: E | H99: 100_305200_4900_53110_819 | I99: 7500 | J99: 7500 | K99: 1066 | L99: 0 | M99: =J99-K99-L99 -> 6434 | O99: =SUM(I99+N99) -> 7500
A100: DS | B100: AVC HR | C100: Linda Francis | D100: PT Faculty Medical Benefits Reimb. ($30,000/sem. Max) | G100: E | H100: 100_305200_4900_53410_819 | I100: 60000 | J100: 60000 | K100: 30000 | L100: 0 | M100: =J100-K100-L100 -> 30000 | O100: =SUM(I100+N100) -> 60000
...

Sheet 1112Adopt
B1: MISSION COLLEGE | L1: Report on 7/18/11
B2: Budget | J2: 10/11 | K2: 0.90909091 | L2: Actual Exp | N2: Available | O2: Budget Adjust. | P2: 11/12 | Q2: Budget Adjust. | R2: 11/12
B3: Responsibility | C3: Contact Info. | D3: Fixed Cost Description | F3: Explanation for Adjustments | G3: Criteria | H3: Account Number | J3: Adopt Bud | K3: Working Bud | L3: as of 6/30/11 | M3: Encumb. | N3: Budget | O3: Incr / (Decr) | P3: Tent Bud | Q3: Incr / (Decr) | R3: Adopt Bud | T3: Actual Adjust.
D4: Academic Senate - Supplies/Materials | H4: 100_206200_6750_54210_819 | J4: 1000 | K4: 0 | L4: 0 | M4: 0 | N4: =K4-L4-M4 -> 0 | O4: 0 | P4: 1000 | Q4: 0 | R4: =SUM(P4:Q4) -> 1000 | X4: 0
D5: Academic Senate - Travel & Conference | H5: 100_206200_6750_55200_819 | J5: 3000 | K5: 4042 | L5: 3915 | M5: 0 | N5: =K5-L5-M5 -> 127 | O5: 0 | P5: 3000 | Q5: 0 | R5: =SUM(P5:Q5) -> 3000 | X5: 3914.72 | Y5: =L5-X5 -> 0.28
B6: Staff Development | C6: Worku Negash | D6: Academic Senate | G6: C | I6: X | J6: =SUM(J4:J5) -> 4000 | K6: =SUM(K4:K5) -> 4042 | L6: =SUM(L4:L5) -> 3915 | M6: =SUM(M4:M5) -> 0 | N6: =SUM(N4:N5) -> 127 | O6: 0 | P6: 4000 | Q6: 0 | R6: =SUM(P6:Q6) -> 4000 | Y6: =L6-X6 -> 3915
D7: Classified Senate - Hrly classified Salary | H7: 100_206300_6750_52310_819 | I7: X | J7: 1000 | K7: 0 | L7: 0 | M7: 0 | N7: =K7-L7-M7 -> 0 | O7: 0 | P7: 1000 | Q7: 0 | R7: =SUM(P7:Q7) -> 1000 | X7: 0 | Y7: =L7-X7 -> 0
D8: Classified Senate - Supplies/Materials | H8: 100_206300_6750_54210_819 | I8: X | J8: 500 | K8: 500 | L8: 488 | M8: 0 | N8: =K8-L8-M8 -> 12 | O8: 0 | P8: 500 | Q8: 0 | R8: =SUM(P8:Q8) -> 500 | X8: 488.48 | Y8: =L8-X8 -> -0.48
D9: Classified Senate - Food Services | H9: 100_206300_6750_55115_819 | I9: X | J9: 1500 | K9: 2500 | L9: 2500 | M9: 0 | N9: =K9-L9-M9 -> 0 | O9: 0 | P9: 1500 | Q9: 0 | R9: =SUM(P9:Q9) -> 1500 | X9: 2499.74 | Y9: =L9-X9 -> 0.26
D10: Classified Senate - Travel & Conference | H10: 100_206300_6750_55205_819 | I10: X | J10: 1500 | K10: 1500 | L10: 1500 | M10: 0 | N10: =K10-L10-M10 -> 0 | O10: 0 | P10: 1500 | Q10: 0 | R10: =SUM(P10:Q10) -> 1500 | X10: 1500 | Y10: =L10-X10 -> 0
B11: Staff Development | C11: Worku Negash | D11: Classified Senate | G11: C | J11: =SUM(J7:J10) -> 4500 | K11: =SUM(K7:K10) -> 4500 | L11: =SUM(L7:L10) -> 4488 | M11: =SUM(M7:M10) -> 0 | N11: =SUM(N7:N10) -> 12 | O11: 0 | P11: 4500 | Q11: 0 | R11: =SUM(P11:Q11) -> 4500 | Y11: =L11-X11 -> 4488
A12: DW | B12: Dir of Information Syst | C12: Worku Negash | D12: Curricunet | F12: Move from District Wide | G12: A | H12: 100_220000_6010_55160_819 | I12: X | J12: 7500 | K12: 7500 | L12: 7500 | M12: 0 | N12: =K12-L12-M12 -> 0 | O12: -7500 | P12: 0 | Q12: 7500 | R12: =SUM(P12:Q12) -> 7500 | X12: 7500 | Y12: =L12-X12 -> 0
B13: Faculty Travel | C13: Worku Negash | D13: Faculty Travel & Conference | F13: 144 FT Faculty @ $200 each | G13: E | H13: 100_290100_6600_55210_819 | I13: X | J13: 30000 | K13: 30000 | L13: 11208.73 | M13: 0 | N13: =K13-L13-M13 -> 18791.27 | O13: 0 | P13: 30000 | Q13: -1200 | R13: =SUM(P13:Q13) -> 28800 | T13: -1200 | X13: 11208.73 | Y13: =L13-X13 -> 0
B14: VP Admin. Services | C14: Worku Negash | D14: Tenure Faculty | F14: 2 Faculty will receive tenure in 11/12 FY | G14: E | H14: 100_220910_4900_51310_819 | I14: X | J14: 25000 | K14: 25000 | L14: 27500 | M14: 0 | N14: =K14-L14-M14 -> -2500 | O14: -14000 | P14: 11000 | Q14: 0 | R14: =SUM(P14:Q14) -> 11000 | S14: 11 | X14: 27500 | Y14: =L14-X14 -> 0
B15: VP Admin. Services | C15: Worku Negash | D15: Tricore, Link + Consortium, Library Maintenance | G15: A | H15: 100_220000_6120_55510_819 | I15: X | J15: 33700 | K15: 34005 | L15: 34005 | N15: =K15-L15-M15 -> 0 | O15: 0 | P15: 33700 | Q15: 0 | R15: =SUM(P15:Q15) -> 33700 | Y15: =L15-X15 -> 34005
B16: VP Admin. Services | C16: Worku Negash | D16: Insurance for PE and Athletics Students | G16: C, D | H16: 100_220000_6440_55940_819 | I16: X | J16: 28038 | K16: 28336 | L16: 28336 | M16: 0 | N16: =K16-L16-M16 -> 0 | O16: 0 | P16: 28038 | Q16: 45673 | R16: =SUM(P16:Q16) -> 73711 | T16: 45673 | X16: 28336 | Y16: =L16-X16 -> 0
B17: VP Admin. Services | C17: Worku Negash | D17: Coaches Stipends (Negotiated Item) | G17: E | H17: 100_220000_6770_51450_819 | I17: X | J17: 15000 | K17: 15000 | L17: =15000+928+218+75+107+172 -> 16500 | M17: 0 | N17: =K17-L17-M17 -> -1500 | O17: 0 | P17: 15000 | Q17: 0 | R17: =SUM(P17:Q17) -> 15000 | X17: 15000 | Y17: =L17-X17 -> 1500
D18: Accreditation - Supplies/Materials | H18: 100_200700_6090_54210_819 | I18: X | J18: 11900 | K18: 11900 | L18: 11900 | M18: 0 | N18: =K18-L18-M18 -> 0 | O18: -11900 | P18: 0 | Q18: 0 | R18: =SUM(P18:Q18) -> 0 | X18: 11899.4 | Y18: =L18-X18 -> 0.6
D19: Accreditation - Professional Services | H19: 100_200700_6090_55120_819 | I19: X | J19: 350 | K19: 700 | L19: 0 | M19: 0 | N19: =K19-L19-M19 -> 700 | O19: -350 | P19: 0 | Q19: 0 | R19: =SUM(P19:Q19) -> 0 | X19: 0 | Y19: =L19-X19 -> 0
D20: Accreditation - Other Reassigned Time | H20: 100_200700_6090_51227_819 | I20: X | J20: 2750 | K20: 2750 | L20: 0 | M20: 0 | N20: =K20-L20-M20 -> 2750 | O20: -2750 | P20: 0 | Q20: 0 | R20: =SUM(P20:Q20) -> 0 | X20: 0 | Y20: =L20-X20 -> 0
D21: Accreditation - Dues, Memberships & Fees | H21: 100_200700_6090_55910_819 | I21: X | J21: 17453 | K21: 16850 | L21: 16850 | M21: 0 | N21: =K21-L21-M21 -> 0 | O21: 0 | P21: 17453 | Q21: 0 | R21: =SUM(P21:Q21) -> 17453 | X21: 16850 | Y21: =L21-X21 -> 0
B22: College President | C22: Worku Negash | D22: Accreditation | G22: C | J22: =SUM(J18:J21) -> 32453 | K22: =SUM(K18:K21) -> 32200 | L22: =SUM(L18:L21) -> 28750 | M22: =SUM(M18:M21) -> 0 | N22: =SUM(N18:N21) -> 3450 | O22: -15000 | P22: 17453 | Q22: 0 | R22: =SUM(P22:Q22) -> 17453 | S22: 12 | Y22: =L22-X22 -> 28750
B23: Marketing and Communications | C23: Worku Negash | D23: Schedule of classes and catalog | F23: Remove from fixed cost | H23: 100_201000_6770_51450_819 | I23: X | J23: 0 | K23: 800 | L23: =364+5+15+3+4 -> 391 | M23: 0 | N23: =K23-L23-M23 -> 409 | O23: 0 | P23: 0 | Q23: 0 | R23: =SUM(P23:Q23) -> 0 | X23: 364.23 | Y23: =L23-X23 -> 26.77
B24: Marketing and Communications | C24: Worku Negash | D24: Schedule of classes and catalog | F24: Remove from fixed cost | H24: 100_201000_6770_55300_819 | I24: X | J24: 70000 | K24: =45919+12247+8392 -> 66558 | L24: =45919+12246.56+8391.94 -> 66557.5 | N24: =K24-L24-M24 -> 0.5 | O24: 0 | P24: 0 | Q24: 0 | R24: =SUM(P24:Q24) -> 0 | X24: 45918.59 | Y24: =L24-X24 -> 20638.91
B25: Marketing and Communications | C25: Worku Negash | D25: Schedule of classes and catalog | F25: Remove from fixed cost | H25: 100_201000_6770_55921_819 | I25: X | J25: 0 | K25: 2250 | L25: 2250 | M25: 0 | N25: =K25-L25-M25 -> 0 | O25: 0 | P25: 0 | Q25: 0 | R25: 0 | X25: 2250 | Y25: =L25-X25 -> 0
B26: Marketing and Communications | C26: Worku Negash | D26: Schedule of classes and catalog | F26: Remove from fixed cost | J26: =SUM(J23:J25) -> 70000 | K26: =SUM(K23:K25) -> 69608 | L26: =SUM(L23:L25) -> 69198.5 | M26: =SUM(M23:M25) -> 0 | N26: =SUM(N23:N24) -> 409.5 | O26: -70000 | P26: =SUM(P23:P24) -> 0 | Q26: =SUM(Q23:Q24) -> 0 | R26: =SUM(R23:R24) -> 0 | Y26: =L26-X26 -> 69198.5
A27: DW | B27: VC Admin Serv | C27: Linda Francis/Virginia | D27: Categorical Program: Transfer Out, Fringe Benefits | F27: Move from District Wide | G27: C | H27: 100_220001_6600_57300_819 | J27: 0 | K27: 0 | L27: 0 | M27: 0 | N27: 0 | O27: 0 | P27: 0 | Q27: =397684-27287 -> 370397 | R27: =SUM(P27:Q27) -> 370397 | T27: -27287 | X27: 779399.15 | Y27: =L27-X27 -> -779399.15
A28: DW | B28: VC Admin Serv | C28: Linda Francis/Virginia | D28: Financial Aid Match: SEOG & Fed Work Study | F28: Move from District Wide | G28: C | H28: 100_220002_6600_57300_819 | J28: 0 | K28: 0 | L28: 0 | M28: 0 | N28: =SUM(K27:K28)-L28-M28 -> 0 | O28: 0 | P28: 0 | Q28: 82111 | R28: =SUM(P28:Q28) -> 82111 | X28: 779399.15 | Y28: =L28-X28 -> -779399.15
A29: DW | B29: Dir of Information Syst | C29: Ron Smith | D29: CLARIS Class TRACKS | F29: Move from District Wide | G29: A | H29: 100_220003_6750_55500_819 | J29: 0 | K29: 0 | L29: 0 | M29: 0 | N29: 0 | O29: 0 | P29: 0 | Q29: 2343 | R29: =SUM(P29:Q29) -> 2343 | X29: 177854.54 | Y29: =L29-X29 -> -177854.54
A30: DW | B30: Dir of Information Syst | C30: Ron Smith | D30: SARS Software Products -Counseling Sched System | F30: Move from District Wide | G30: A | H30: 100_220004_6750_55500_819 | J30: 0 | K30: 0 | L30: 0 | M30: 0 | N30: =SUM(J29:J30)-L30-M30 -> 0 | O30: 0 | P30: 0 | Q30: 5670 | R30: =SUM(P30:Q30) -> 5670 | X30: 177854.54 | Y30: =L30-X30 -> -177854.54
A31: DW | B31: Dir of Information Syst | C31: Ron Smith | D31: Angel | F31: Move from District Wide | G31: A | H31: 100_220005_6150_55500_819 | J31: 0 | K31: 0 | L31: 0 | M31: 0 | N31: 0 | O31: 0 | P31: 0 | Q31: 75190 | R31: =SUM(P31:Q31) -> 75190 | X31: 113705.4 | Y31: =L31-X31 -> -113705.4
A32: DW | B32: Dir of Information Syst | C32: Ron Smith | D32: CCCApply | F32: Move from District Wide | G32: A | H32: 100_220006_6150_55500_819 | J32: 0 | K32: 0 | L32: 0 | M32: 0 | N32: =SUM(K31:K32)-L32-M32 -> 0 | O32: 0 | P32: 0 | Q32: 11259 | R32: =SUM(P32:Q32) -> 11259 | X32: 113705.4 | Y32: =L32-X32 -> -113705.4
H33: Total Mission College | J33: =SUM(J6,J11:J17,J22,J26:J32) -> 250191 | K33: =SUM(K6,K11:K17,K22,K26:K32) -> 250191 | L33: =SUM(L6,L11:L17,L22,L26:L32) -> 231401.23 | M33: =SUM(M6,M11:M17,M22,M26:M32) -> 0 | N33: =SUM(N6,N11:N17,N22,N26:N32) -> 18789.77 | O33: =SUM(O6,O11:O17,O22,O26:O32) -> -106500 | P33: =SUM(P6,P11:P17,P22,P26:P32) -> 143691 | Q33: =SUM(Q6,Q11:Q17,Q22,Q26:Q32) -> 598943 | R33: =SUM(R6,R11:R17,R22,R26:R32) -> 742634 | Y33: =L33-X33 -> 231401.23
J34: √ | O34: √ | P34: √ | Y34: =L34-X34 -> 0
B35: WEST VALLEY COLLEGE | Y35: =L35-X35 -> 0
B36: Budget | J36: 10/11 | K36: 0.90909091 | L36: Actual Exp | N36: Available | O36: Budget Adjust. | P36: 11/12 | Q36: Budget Adjust. | R36: 11/12 | Y36: =L36-X36 -> #VALUE!
B37: Responsibility | C37: Contact Info. | D37: Fixed Cost Description | E37: Detail Description | F37: Explanation for Adjustments | G37: Criteria | H37: Account Number | J37: Adopt Bud | K37: Working Bud | L37: as of 6/30/11 | M37: Encumb. | N37: Budget | O37: Incr / (Decr) | P37: Tent Bud | Q37: Incr / (Decr) | R37: Adopt Bud | Y37: =L37-X37 -> #VALUE!
D38: Academic Senate -to be funded from other source | H38: 100_119304_6750_55115_819 | I38: X | J38: 1100 | K38: 1100 | L38: 1146 | M38: 0 | N38: =K38-L38-M38 -> -46 | O38: 0 | P38: 1100 | Q38: 0 | R38: =SUM(P38:Q38) -> 1100 | X38: 1146.42 | Y38: =L38-X38 -> -0.42
D39: Academic Senate -to be funded from other source | H39: 100_119304_6750_55200_819 | I39: X | J39: 3300 | K39: 3300 | L39: 3300 | M39: 0 | N39: =K39-L39-M39 -> 0 | O39: 0 | P39: 3300 | Q39: 0 | R39: =SUM(P39:Q39) -> 3300 | X39: 3300 | Y39: =L39-X39 -> 0
B40: Senates & Staff Development | C40: Michael Renzi | D40: Academic Senate | G40: C | J40: =SUM(J38:J39) -> 4400 | K40: =SUM(K38:K39) -> 4400 | L40: =SUM(L38:L39) -> 4446 | M40: =SUM(M38:M39) -> 0 | N40: =SUM(N38:N39) -> -46 | O40: 0 | P40: 4400 | Q40: 0 | R40: =SUM(P40:Q40) -> 4400 | Y40: =L40-X40 -> 4446
D41: Classified Senate | H41: 100_119305_6750_55115_819 | I41: X | J41: 660 | K41: 2960 | L41: 2914 | M41: 0 | N41: =K41-L41-M41 -> 46 | O41: 0 | P41: 660 | Q41: 0 | R41: =SUM(P41:Q41) -> 660 | X41: 2913.58 | Y41: =L41-X41 -> 0.42
D42: Classified Senate | H42: 100_119305_6750_55160_819 | I42: X | J42: 440 | K42: 440 | L42: 440 | M42: 0 | N42: =K42-L42-M42 -> 0 | O42: 0 | P42: 440 | Q42: 0 | R42: =SUM(P42:Q42) -> 440 | X42: 440 | Y42: =L42-X42 -> 0
D43: Classified Senate | H43: 100_119305_6750_55200_819 | I43: X | J43: 3300 | K43: 1000 | L43: 1000 | M43: 0 | N43: =K43-L43-M43 -> 0 | O43: 0 | P43: 3300 | Q43: 0 | R43: =SUM(P43:Q43) -> 3300 | X43: 1000 | Y43: =L43-X43 -> 0
B44: Senates & Staff Development | C44: Michael Renzi | D44: Classified Senate | G44: C | J44: =SUM(J41:J43) -> 4400 | K44: =SUM(K41:K43) -> 4400 | L44: =SUM(L41:L43) -> 4354 | M44: =SUM(M41:M43) -> 0 | N44: =SUM(N41:N43) -> 46 | O44: 0 | P44: 4400 | Q44: 0 | R44: =SUM(P44:Q44) -> 4400 | Y44: =L44-X44 -> 4354
A45: DW | B45: Dir of Information Syst | C45: Michael Renzi | D45: Curricunet | G45: A | H45: 100_101000_6010_55160_819 | I45: X | J45: 7500 | K45: 7500 | L45: 7500 | M45: 0 | N45: =K45-L45-M45 -> 0 | O45: -7500 | P45: 0 | Q45: 7500 | R45: =SUM(P45:Q45) -> 7500 | X45: 7500 | Y45: =L45-X45 -> 0
B46: VP Admin. Services | C46: Michael Renzi | D46: Faculty Travel & Conference | F46: 166 FT Faculty @ $200 each | G46: E | H46: 100_103201_6010_55210_819 | I46: X | J46: 34000 | K46: 33600 | L46: 12863 | M46: 0 | N46: =K46-L46-M46 -> 20737 | O46: 0 | P46: 34000 | Q46: -800 | R46: =SUM(P46:Q46) -> 33200 | T46: -800 | X46: 0 | Y46: =L46-X46 -> 12863
B47: VP Admin. Services | C47: Michael Renzi | D47: Tenure Faculty | F47: 2 Faculty will receive tenure in 11/12 FY | G47: E | H47: 100_103251_4900_51310_819 | I47: X | J47: 10000 | K47: 10000 | L47: 44000 | M47: 0 | N47: =K47-L47-M47 -> -34000 | O47: 1000 | P47: 11000 | Q47: 0 | R47: =SUM(P47:Q47) -> 11000 | S47: 11 | X47: 44000 | Y47: =L47-X47 -> 0
B48: Dean Learning Center | C48: Michael Renzi | D48: Tricore, Link + Consortium, Library Maintenance | E48: Consolidated budget for Link+ and other costs | G48: A | H48: 100_106100_6120_55510_819 | I48: X | J48: 34052 | K48: 34052 | L48: =34052+9.68 -> 34061.68 | M48: 0 | N48: =K48-L48-M48 -> -9.68 | O48: 0 | P48: 34052 | Q48: 2209 | R48: =SUM(P48:Q48) -> 36261 | T48: 2209 | X48: 34052 | Y48: =L48-X48 -> 9.68
B49: Physical Education Division | C49: Michael Renzi | D49: Insurance for PE and Athletics Students | E49: Base from Final Budget. Increased from FY11 | G49: C, D | H49: 100_115200_6960_55940_819 | I49: X | J49: 73090 | K49: 73090 | L49: 73090 | M49: 0 | N49: =K49-L49-M49 -> 0 | O49: 0 | P49: 73090 | Q49: 37478 | R49: =SUM(P49:Q49) -> 110568 | T49: 37478 | X49: 73090 | Y49: =L49-X49 -> 0
B50: Physical Education Division | C50: Michael Renzi | D50: Coaches Stipends (Negotiated Item) | F50: $125 per day x 197 days | G50: E | H50: 100_115200_6960_51450_819 | I50: X | J50: 24375 | K50: 24375 | L50: =24375+1629+286.37+50+160+256 -> 26756.37 | M50: 0 | N50: =K50-L50-M50 -> -2381.37 | O50: 250 | P50: 24625 | Q50: 0 | R50: =SUM(P50:Q50) -> 24625 | X50: 24375 | Y50: =L50-X50 -> 2381.37
B51: College President | C51: Michael Renzi | D51: Accreditation - Travel & Conference | G51: C | H51: 100_100100_6090_55200_819 | I51: X | J51: 0 | K51: 17453 | L51: 17453 | M51: 0 | N51: =K51-L51-M51 -> 0 | O51: 0 | P51: 17453 | Q51: 0 | R51: =SUM(P51:Q51) -> 17453 | S51: 12 | X51: 17453 | Y51: =L51-X51 -> 0
B52: College President | C52: Michael Renzi | D52: Accreditation - Other Reassign Time | G52: C | H52: 100_100100_6090_51227_819 | J52: 17453 | K52: 0 | L52: 0 | M52: 0 | N52: =K52-L52-M52 -> 0 | O52: 0 | P52: 0 | Q52: 0 | R52: =SUM(P52:Q52) -> 0 | S52: 12 | X52: 0 | Y52: =L52-X52 -> 0
D53: Schedule of classes and catalog | H53: 100_105600_6400_55160_819 | I53: X | J53: 3860 | K53: 4360 | L53: 4335 | N53: =SUM(K53-L53-M53) -> 25 | O53: -3860 | P53: 0 | Q53: 0 | R53: =SUM(P53:Q53) -> 0 | X53: 4335 | Y53: =L53-X53 -> 0
D54: Schedule of classes and catalog | H54: 100_105600_6400_55300_819 | I54: X | J54: 78410 | K54: 77910 | L54: 66915 | N54: =SUM(K54-L54-M54) -> 10995 | O54: -78410 | P54: 0 | Q54: 0 | R54: =SUM(P54:Q54) -> 0 | X54: 66915.2 | Y54: =L54-X54 -> -0.2
B55: Dean Instruct. & Matric. | C55: Michael Renzi | D55: Schedule of classes and catalog | F55: Remove from fixed cost | J55: =SUM(J53:J54) -> 82270 | K55: =SUM(K53:K54) -> 82270 | L55: =SUM(L53:L54) -> 71250 | M55: =SUM(M53:M54) -> 0 | N55: =SUM(N53:N54) -> 11020 | O55: =SUM(O53:O54) -> -82270 | P55: =SUM(P53:P54) -> 0 | Q55: 0 | Y55: =L55-X55 -> 71250
A56: DW | B56: VC Admin Serv | C56: Linda Francis/Virginia | D56: Categorical Program: Transfer Out, Fringe Benefits | G56: C | H56: 100_103203_6600_57300_819 | J56: 0 | K56: 0 | O56: 0 | P56: 0 | Q56: =429577+39133 -> 468710 | R56: =SUM(P56:Q56) -> 468710 | T56: 39133 | X56: 779399.15 | Y56: =L56-X56 -> -779399.15
A57: DW | B57: VC Admin Serv | C57: Linda Francis/Virginia | D57: Financial Aid Match: SEOG, Fed Work Study | G57: C | H57: 100_103204_6600_57300_819 | J57: 0 | K57: 0 | L57: 0 | M57: 0 | N57: =SUM(K56:K57)-L57-M57 -> 0 | O57: 0 | P57: 0 | Q57: 80125 | R57: =SUM(P57:Q57) -> 80125 | X57: 779399.15 | Y57: =L57-X57 -> -779399.15
A58: DW | B58: Dir of Information Syst | C58: Ron Smith | D58: CLARIS Class TRACKS | G58: A | H58: 100_103205_6750_55500_819 | J58: 0 | K58: 0 | O58: 0 | P58: 0 | Q58: 2343 | R58: =SUM(P58:Q58) -> 2343 | X58: 177854.54 | Y58: =L58-X58 -> -177854.54
A59: DW | B59: Dir of Information Syst | C59: Ron Smith | D59: SARS Software Products -Counseling Sched System | G59: A | H59: 100_103206_6750_55500_819 | J59: 0 | K59: 0 | L59: 0 | M59: 0 | N59: =SUM(J58:J59)-L59-M59 -> 0 | O59: 0 | P59: 0 | Q59: 5670 | R59: =SUM(P59:Q59) -> 5670 | X59: 177854.54 | Y59: =L59-X59 -> -177854.54
A60: DW | B60: Dir of Information Syst | C60: Ron Smith | D60: Angel | G60: A | H60: 100_103207_6150_55500_819 | J60: 0 | K60: 0 | O60: 0 | P60: 0 | Q60: 75190 | R60: =SUM(P60:Q60) -> 75190 | X60: 113705.4 | Y60: =L60-X60 -> -113705.4
A61: DW | B61: Dir of Information Syst | C61: Ron Smith | D61: CCCApply | G61: A | H61: 100_103208_6150_55500_819 | J61: 0 | K61: 0 | L61: 0 | M61: 0 | N61: =SUM(K60:K61)-L61-M61 -> 0 | O61: 0 | P61: 0 | Q61: 11259 | R61: =SUM(P61:Q61) -> 11259 | X61: 113705.4 | Y61: =L61-X61 -> -113705.4
B62: Campbell Center | C62: Michael Renzi | D62: Campbell Center Lease | G62: D | H62: 100_131000_6470_55520_819 | I62: X | J62: 34000 | K62: 34000 | L62: 34000 | M62: 0 | N62: =K62-L62-M62 -> 0 | O62: 0 | P62: 34000 | Q62: 0 | R62: =SUM(P62:Q62) -> 34000 | X62: 34000 | Y62: =L62-X62 -> 0
D63: NISOD-Salary | H63: 100_119303_6720_51450_819 | I63: X | J63: 4400 | K63: 1738 | L63: =1738+58+10+5+8 -> 1819 | M63: 0 | N63: =K63-L63-M63 -> -81 | O63: 0 | P63: 4400 | Q63: 0 | R63: =SUM(P63:Q63) -> 4400 | X63: 1737.88 | Y63: =L63-X63 -> 81.12
D64: NISOD-Supplies | H64: 100_119303_6720_54210_819 | I64: X | J64: 0 | K64: 541 | L64: 541 | M64: 0 | N64: =K64-L64-M64 -> 0 | O64: 0 | P64: 0 | Q64: 0 | R64: =SUM(P64:Q64) -> 0 | X64: 540.54 | Y64: =L64-X64 -> 0.46
D65: NISOD-Food Services | H65: 100_119303_6750_55115_819 | I65: X | J65: 1100 | K65: 1859 | L65: 1859 | M65: 0 | N65: =K65-L65-M65 -> 0 | O65: 0 | P65: 1100 | Q65: 0 | R65: =SUM(P65:Q65) -> 1100 | X65: 1859 | Y65: =L65-X65 -> 0
D66: NISOD-Travel for faculty to go to Texas | H66: 100_119303_6750_55200_819 | I66: X | J66: 3300 | K66: 4662 | L66: 4662 | M66: 0 | N66: =K66-L66-M66 -> 0 | O66: 0 | P66: 3300 | Q66: 0 | R66: =SUM(P66:Q66) -> 3300 | X66: 4662 | Y66: =L66-X66 -> 0
B67: Senates & Staff Development | C67: Michael Renzi | D67: NISOD | G67: C | J67: 8800 | K67: =SUM(K63:K66) -> 8800 | L67: =SUM(L63:L66) -> 8881 | M67: =SUM(M63:M66) -> 0 | N67: =SUM(N63:N66) -> -81 | O67: =SUM(O63:O66) -> 0 | P67: 8800 | Q67: 0 | R67: =SUM(P67:Q67) -> 8800 | Y67: =L67-X67 -> 8881
H68: Total West Valley College | J68: =SUM(J40,J44:J52,J55:J62,J67) -> 334340 | K68: =SUM(K40,K44:K52,K55:K62,K67)+112152 -> 446092 | L68: =SUM(L40,L44:L52,L55:L62,L67) -> 338655.05 | M68: =SUM(M40,M44:M52,M55:M62,M67) -> 0 | N68: =SUM(N40,N44:N52,N55:N62,N67) -> -4715.05 | O68: =SUM(O40,O44:O52,O55:O62,O67) -> -88520 | P68: =SUM(P40,P44:P52,P55:P62,P67) -> 245820 | Q68: =SUM(Q40,Q44:Q52,Q55:Q62,Q67) -> 689684 | R68: =SUM(R40,R44:R52,R55:R62,R67) -> 935504 | Y68: =L68-X68 -> 338655.05
J69: √ | O69: √ | P69: √ | Y69: =L69-X69 -> 0
B70: DISTRICT WIDE | Y70: =L70-X70 -> 0
B71: Budget | J71: 10/11 | K71: 0.90909091 | L71: Actual Exp | N71: Available | O71: Budget Adjust. | P71: 11/12 | Q71: Budget Adjust. | R71: 11/12 | Y71: =L71-X71 -> #VALUE!
B72: Responsibility | C72: Contact Info. | D72: Fixed Cost Description | F72: Explanation for Adjustments | G72: Criteria | H72: Account Number | J72: Adopt Bud | K72: Working Bud | L72: as of 6/30/11 | M72: Encumb. | N72: Budget | O72: Incr / (Decr) | P72: Tent Bud | Q72: Incr / (Decr) | R72: Adopt Bud | Y72: =L72-X72 -> #VALUE!
B73: VC Admin Serv | C73: Linda Francis | D73: Cal Grant Interest Payment | F73: Revised computation method | G73: C | H73: 100_304170_6720_55185_819 | I73: X | J73: 3000 | K73: 3000 | L73: 0 | M73: 0 | O73: 1500 | P73: 4500 | Q73: 0 | R73: =SUM(P73:Q73) -> 4500 | S73: 4 | X73: 10491.2 | Y73: =L73-X73 -> -10491.2
B74: VC Admin Serv | C74: Linda Francis | D74: NDSL Collection Admin Costs (Perkins Loans) | G74: G | H74: 100_304170_6720_55185_819 | I74: X | J74: 5000 | K74: 8082 | L74: 10491 | M74: 0 | N74: =SUM(K73:K74)-L74-M74 -> 591 | O74: 0 | P74: 5000 | Q74: 0 | R74: =SUM(P74:Q74) -> 5000 | X74: 10491.2 | Y74: =L74-X74 -> -0.2
B75: VC Admin Serv | C75: Linda Francis/Virginia | D75: Categorical Program: Transfer Out, Fringe Benefits | F75: Move to campus | G75: C | H75: 100_304190_6600_57300_819 | I75: X | J75: 827261 | K75: 827261 | O75: 0 | P75: 827261 | Q75: -827261 | R75: =SUM(P75:Q75) -> 0 | X75: 779399.15 | Y75: =L75-X75 -> -779399.15
B76: VC Admin Serv | C76: Linda Francis/Virginia | D76: Financial Aid Match: SEOG & Fed Work Study | F76: Move to campus | G76: C | H76: 100_304190_6600_57300_819 | I76: X | J76: 162236 | K76: 162236 | L76: 779399 | M76: 0 | N76: =SUM(K75:K76)-L76-M76 -> 210098 | O76: 0 | P76: 162236 | Q76: -162236 | R76: =SUM(P76:Q76) -> 0 | X76: 779399.15 | Y76: =L76-X76 -> -0.15
B77: VC Admin Serv | C77: Linda Francis | D77: Faculty SERP Premium 5 of 5 yrs | G77: E | H77: 100_304168_5900_53710_819 | I77: X | J77: 50694 | K77: 47825 | L77: 47825 | M77: 0 | N77: =K77-L77-M77 -> 0 | O77: 0 | P77: 50694 | Q77: 0 | R77: =SUM(P77:Q77) -> 50694 | S77: 2 | X77: 47825 | Y77: =L77-X77 -> 0
B78: VC Admin Serv | C78: Linda Francis | D78: Management SERP Premium 3 of 5 yrs | G78: E | H78: 100_304168_6740_53710_819 | J78: 74278 | K78: 74278 | O78: 0 | P78: 74278 | Q78: 0 | R78: =SUM(P78:Q78) -> 74278 | S78: 2 | X78: 193708.68 | Y78: =L78-X78 -> -193708.68
B79: VC Admin Serv | C79: Linda Francis | D79: Confidential/Supr SERP Premium 3 of 5 yrs | G79: E | H79: 100_304168_6740_53710_819 | J79: 122632 | K79: =122632-3201 -> 119431 | L79: 193708.68 | M79: 0 | N79: =SUM(K78:K79)-L79-M79 -> 0.32 | O79: 0 | P79: 122632 | Q79: 0 | R79: =SUM(P79:Q79) -> 122632 | S79: 2 | X79: 193708.68 | Y79: =L79-X79 -> 0
D80: Utilities, Mission College - Utilities | H80: 100_304020_6570_55800_819 | I80: X | J80: 900000 | K80: 636777 | L80: 708475 | M80: 0 | N80: =K80-L80-M80 -> -71698 | O80: 0 | P80: 677482 | Q80: 0 | R80: =SUM(P80:Q80) -> 677482 | X80: 708474.66 | Y80: =L80-X80 -> 0.34
D81: Utilities, Mission College - Gas | H81: 100_304020_6570_55811_819 | I81: X | J81: 0 | K81: 161294 | L81: 161293 | M81: 0 | N81: =K81-L81-M81 -> 1 | O81: 0 | P81: 121560 | Q81: 0 | R81: =SUM(P81:Q81) -> 121560 | X81: 161293.41 | Y81: =L81-X81 -> -0.41
D82: Utilities, Mission College - Trash | H82: 100_304020_6570_55820_819 | I82: X | J82: 0 | K82: 31987 | L82: 31986 | M82: 0 | N82: =K82-L82-M82 -> 1 | O82: 0 | P82: 30757.5 | Q82: 0 | R82: =SUM(P82:Q82) -> 30757.5 | X82: 31986.49 | Y82: =L82-X82 -> -0.49
D83: Utilities, Mission College - Water | H83: 100_304020_6570_55840_819 | I83: X | J83: 0 | K83: 57498 | L83: 70317 | M83: 0 | N83: =K83-L83-M83 -> -12819 | O83: 0 | P83: 55236 | Q83: 0 | R83: =SUM(P83:Q83) -> 55236 | X83: 70316.62 | Y83: =L83-X83 -> 0.38
D84: Utilities, Mission College - Sewer | H84: 100_304020_6570_55850_819 | I84: X | J84: 0 | K84: 17427 | L84: 19219 | M84: 0 | N84: =K84-L84-M84 -> -1792 | O84: 0 | P84: 14964 | Q84: 0 | R84: =SUM(P84:Q84) -> 14964 | X84: 19219.14 | Y84: =L84-X84 -> -0.14
B85: VC Admin Serv | C85: Linda Francis | D85: Utilities, Mission College | F85: Increase in cost | G85: F | J85: =SUM(J80:J84) -> 900000 | K85: =SUM(K80:K84) -> 904983 | L85: =SUM(L80:L84) -> 991290 | M85: =SUM(M80:M84) -> 0 | N85: =SUM(N80:N84) -> -86307 | O85: 0 | P85: 899999.5 | Q85: =SUM(Q80:Q84) -> 0 | R85: =SUM(P85:Q85) -> 899999.5 | Y85: =L85-X85 -> 991290
D86: Utilities, West Valley College - Utilities | H86: 100_304010_6570_55800_819 | I86: X | J86: 1100000 | K86: 795790 | L86: 835877 | M86: 0 | N86: =K86-L86-M86 -> -40087 | O86: 0 | P86: 706962.73 | Q86: 0 | R86: =SUM(P86:Q86) -> 706962.73 | X86: 835876.88 | Y86: =L86-X86 -> 0.12
D87: Utilities, West Valley College - Gas | H87: 100_304010_6570_55811_819 | I87: X | J87: 0 | K87: 177987 | L87: 177987 | M87: 0 | N87: =K87-L87-M87 -> 0 | O87: 0 | P87: 159484.5 | Q87: 0 | R87: =SUM(P87:Q87) -> 159484.5 | X87: 177986.96 | Y87: =L87-X87 -> 0.04
D88: Utilities, West Valley College - Trash | H88: 100_304010_6570_55820_819 | I88: X | J88: 0 | K88: 23206 | L88: 23168 | M88: 0 | N88: =K88-L88-M88 -> 38 | O88: 0 | P88: 21421.32 | Q88: 0 | R88: =SUM(P88:Q88) -> 21421.32 | X88: 23168.17 | Y88: =L88-X88 -> -0.17
D89: Utilities, West Valley College - Water | H89: 100_304010_6570_55840_819 | I89: X | J89: 0 | K89: 129965 | L89: 129964 | M89: 0 | N89: =K89-L89-M89 -> 1 | O89: 0 | P89: 137895.45 | Q89: 0 | R89: =SUM(P89:Q89) -> 137895.45 | X89: 129964.31 | Y89: =L89-X89 -> -0.31
D90: Utilities, West Valley College - Sewer | E90: Sewer ( One payment each year) | H90: 100_304010_6570_55850_819 | I90: X | J90: 0 | K90: 74236 | L90: 74236 | M90: 0 | N90: =K90-L90-M90 -> 0 | O90: 0 | P90: 74236 | Q90: =L90-P90 -> 0 | R90: =SUM(P90:Q90) -> 74236 | X90: 74236.26 | Y90: =L90-X90 -> -0.26
B91: VC Admin Serv | C91: Linda Francis | D91: Utilities, West Valley College | F91: Increase in cost | G91: F | J91: =SUM(J86:J90) -> 1100000 | K91: =SUM(K86:K90) -> 1201184 | L91: =SUM(L86:L90) -> 1241232 | M91: =SUM(M86:M90) -> 0 | N91: =SUM(N86:N90) -> -40048 | O91: 0 | P91: 1100000 | Q91: =SUM(Q86:Q90) -> 0 | R91: =SUM(R86:R90) -> 1100000 | Y91: =L91-X91 -> 1241232
B92: VC Admin Serv | C92: Linda Francis | D92: ACE-Negotiated portion of COLA towards Health Benefit Increases | G92: E | H92: 100_304169_7310_57300_819 | I92: X | J92: 648948 | K92: 916411 | L92: =1314830-398419 -> 916411 | M92: 0 | N92: =K92-L92-M92 -> 0 | O92: 0 | P92: 648948 | Q92: -648948 | R92: =SUM(P92:Q92) -> 0 | T92: -648948 | X92: 1314830.2 | Y92: =L92-X92 -> -398419.2
B93: VC Admin Serv | C93: Linda Francis | D93: ACE-Negotiated 0.92% of COLA Health Benefit Reserve | G93: E | H93: 100_304169_7310_57300_819 | I93: X | J93: 398419 | K93: 398419 | L93: 398419 | M93: 0 | N93: =K93-L93-M93 -> 0 | O93: 0 | P93: 398419 | Q93: -56844 | R93: =SUM(P93:Q93) -> 341575 | T93: =Q93 -> -56844 | X93: 1314830.2 | Y93: =L93-X93 -> -916411.2
B94: VC Admin Serv | C94: Linda Francis | D94: HBA Penalty | F94: Final payment | G94: D | H94: 100_304180_6600_57130_819 | I94: X | J94: 242000 | K94: 32380 | L94: 0 | M94: 0 | N94: =K94-L94-M94 -> 32380 | O94: -242000 | P94: 0 | Q94: 0 | R94: =SUM(P94:Q94) -> 0 | X94: 0 | Y94: =L94-X94 -> 0
B95: Dir of Information Syst | C95: Worku Negash | D95: Curricunet | G95: A | H95: 100_310720_6010_55160_819 | J95: 0 | K95: 0 | L95: 0 | M95: 0 | N95: =K95-L95-M95 -> 0 | O95: 15000 | P95: 15000 | Q95: -15000 | R95: =SUM(P95:Q95) -> 0 | Y95: =L95-X95 -> 0
A96: DS | B96: Chancellor | C96: Linda Francis | D96: Board Elections/Redistricting Board Election | F96: 2 year budget cycle | G96: D | H96: 100_300130_6600_55180_819 | J96: 0 | K96: 0 | L96: 0 | M96: 0 | N96: =K96-L96-M96 -> 0 | O96: 0 | P96: 0 | Q96: 180475 | R96: =SUM(P96:Q96) -> 180475 | X96: 371130.76 | Y96: =L96-X96 -> -371130.76
A97: DS | B97: VC Admin Serv | C97: Ed Maduli/Christina | D97: Emergency Services | F97: Add - new 11/12 FY | G97: B | H97: 100_304180_6720_52350_819 | I97: X | J97: 0 | K97: 0 | M97: 0 | N97: =K97-L97-M97 -> 0 | O97: 0 | P97: 0 | Q97: 40000 | R97: =SUM(P97:Q97) -> 40000 | Y97: =L97-X97 -> 0
A98: DS | D98: Bank Service Charges | F98: Over | H98: 100_304170_6720_55592_819 | J98: 0 | K98: 0 | L98: 0 | M98: 0 | N98: 0 | O98: 0 | P98: 0 | Q98: 0 | R98: =SUM(P98:Q98) -> 0 | X98: -1420.28 | Y98: =L98-X98 -> 1420.28
A99: DS | D99: Bank Service Charges | F99: Bank charges | H99: 100_304170_6720_55593_819 | J99: 0 | K99: 0 | L99: 0 | M99: 0 | N99: 0 | O99: 0 | P99: 0 | Q99: 15000 | R99: =SUM(P99:Q99) -> 15000 | X99: 25425.75 | Y99: =L99-X99 -> -25425.75
A100: DS | D100: Bank Service Charges | F100: E Commerce charges | H100: 100_304170_6720_55595_819 | J100: 0 | K100: 0 | L100: 0 | M100: 0 | N100: =K100-L100-M100 -> 0 | O100: 0 | P100: 0 | Q100: 165000 | R100: =SUM(P100:Q100) -> 165000 | X100: 240167.3 | Y100: =L100-X100 -> -240167.3
...

Sheet Datetel Jul 10, 2013
A1: Account Number | B1: Costcenter Description | C1: Object Description | D1: Budget Responsibility Title Description | E1: Adopted Budget | F1: Working Budget | G1: Actual | H1: Encumbrance | I1: Balance
A3: 100_100100_6090_52350_819 | B3: Accreditation | C3: Hrly Class Special Services | D3: College President | E3: 0 | F3: =VLOOKUP(A3,Sheet3!A:F,6,0) -> 6000 | G3: =VLOOKUP(A3,Sheet3!A:E,5,0) -> 9000 | H3: =VLOOKUP(A3,Sheet3!A:C,3,0) -> 0 | I3: =F3-G3-H3 -> -3000
A4: 100_100100_6090_53323_819 | B4: Accreditation | C4: Medicare - Non-Instr. | D4: College President | E4: 0 | F4: =VLOOKUP(A4,Sheet3!A:F,6,0) -> 87 | G4: =VLOOKUP(A4,Sheet3!A:E,5,0) -> 130.5 | H4: =VLOOKUP(A4,Sheet3!A:C,3,0) -> 0 | I4: =F4-G4-H4 -> -43.5
A5: 100_100100_6090_53324_819 | B5: Accreditation | C5: Apple Plan - Non-Instr | D5: College President | E5: 0 | F5: =VLOOKUP(A5,Sheet3!A:F,6,0) -> 0 | G5: =VLOOKUP(A5,Sheet3!A:E,5,0) -> 0 | H5: =VLOOKUP(A5,Sheet3!A:C,3,0) -> 0 | I5: =F5-G5-H5 -> 0
A6: 100_100100_6090_53520_819 | B6: Accreditation | C6: UI - Instr. | D6: College President | E6: 0 | F6: =VLOOKUP(A6,Sheet3!A:F,6,0) -> 66 | G6: =VLOOKUP(A6,Sheet3!A:E,5,0) -> 99 | H6: =VLOOKUP(A6,Sheet3!A:C,3,0) -> 0 | I6: =F6-G6-H6 -> -33
A7: 100_100100_6090_53620_819 | B7: Accreditation | C7: Worker's Comp.-Non Instr. | D7: College President | E7: 0 | F7: =VLOOKUP(A7,Sheet3!A:F,6,0) -> 89 | G7: =VLOOKUP(A7,Sheet3!A:E,5,0) -> 133.31 | H7: =VLOOKUP(A7,Sheet3!A:C,3,0) -> 0 | I7: =F7-G7-H7 -> -44.31
A8: 100_100100_6090_53220_819 | B8: Accreditation | D8: College President | F8: =VLOOKUP(A8,Sheet3!A:F,6,0) -> 685 | G8: =VLOOKUP(A8,Sheet3!A:E,5,0) -> 1027.51 | H8: =VLOOKUP(A8,Sheet3!A:C,3,0) -> 0 | I8: =F8-G8-H8 -> -342.51
A9: 100_100100_6090_53320_819 | B9: Accreditation | D9: College President | F9: =VLOOKUP(A9,Sheet3!A:F,6,0) -> 372 | G9: =VLOOKUP(A9,Sheet3!A:E,5,0) -> 558 | H9: =VLOOKUP(A9,Sheet3!A:C,3,0) -> 0 | I9: =F9-G9-H9 -> -186
A10: 100_100100_6090_54210_819 | B10: Accreditation | C10: Non-Instr. Supplies/Materia | D10: College President | E10: 10000 | F10: =VLOOKUP(A10,Sheet3!A:F,6,0) -> 1374 | G10: =VLOOKUP(A10,Sheet3!A:E,5,0) -> 955.06 | H10: =VLOOKUP(A10,Sheet3!A:C,3,0) -> 0.13 | I10: =F10-G10-H10 -> 418.81
A11: 100_100100_6090_55910_819 | B11: Accreditation | C11: Dues, Memberships & Fees | D11: College President | E11: 18953 | F11: =VLOOKUP(A11,Sheet3!A:F,6,0) -> 18940 | G11: =VLOOKUP(A11,Sheet3!A:E,5,0) -> 18326 | H11: =VLOOKUP(A11,Sheet3!A:C,3,0) -> 0 | I11: =F11-G11-H11 -> 614
A12: 100_100100_6090_56400_819 | B12: Accreditation | C12: Dues, Memberships & Fees | D12: College President | E12: 0 | F12: =VLOOKUP(A12,Sheet3!A:F,6,0) -> 1340 | G12: =VLOOKUP(A12,Sheet3!A:E,5,0) -> 1330.92 | H12: 0 | I12: 0
A13: 100_101000_6010_55160_819 | B13: VP Instruction | C13: Contracted Services | D13: VP Instruction | E13: 7479 | F13: =VLOOKUP(A13,Sheet3!A:F,6,0) -> 7479 | G13: =VLOOKUP(A13,Sheet3!A:E,5,0) -> 7479 | H13: =VLOOKUP(A13,Sheet3!A:C,3,0) -> 0 | I13: =F13-G13-H13 -> 0
A14: 100_102000_6490_55160_819 | B14: VP Student Services | C14: Contracted Services | D14: VP Student Services | E14: 2500 | F14: =VLOOKUP(A14,Sheet3!A:F,6,0) -> 2500 | G14: =VLOOKUP(A14,Sheet3!A:E,5,0) -> 2500 | H14: =VLOOKUP(A14,Sheet3!A:C,3,0) -> 0 | I14: =F14-G14-H14 -> 0
A15: 100_103201_6010_55210_819 | B15: Faculty Travel & Conf. | C15: Cur. Year Fac. Travel & Con | D15: VP Administrative Services | E15: 33200 | F15: =VLOOKUP(A15,Sheet3!A:F,6,0) -> 0 | G15: =VLOOKUP(A15,Sheet3!A:E,5,0) -> 0 | H15: =VLOOKUP(A15,Sheet3!A:C,3,0) -> 0 | I15: =F15-G15-H15 -> 0
A16: 100_107100_0700_55210_819 | B16: WVC Instructional Computi | C16: Cur. Year Fac. Travel & Con | D16: Dean Instructional Computer Technologies | E16: 0 | F16: =VLOOKUP(A16,Sheet3!A:F,6,0) -> 360 | G16: =VLOOKUP(A16,Sheet3!A:E,5,0) -> 0 | H16: =VLOOKUP(A16,Sheet3!A:C,3,0) -> 0 | I16: =F16-G16-H16 -> 360
A17: 100_111004_2100_55210_819 | B17: Admin of Justice | C17: Cur. Year Fac. Travel & Con | D17: AAS Division | E17: 0 | F17: =VLOOKUP(A17,Sheet3!A:F,6,0) -> 400 | G17: =VLOOKUP(A17,Sheet3!A:E,5,0) -> 0 | H17: =VLOOKUP(A17,Sheet3!A:C,3,0) -> 0 | I17: =F17-G17-H17 -> 400
A18: 100_111100_0200_55210_819 | B18: Architecture | C18: Cur. Year Fac. Travel & Con | D18: AAS Division | E18: 0 | F18: =VLOOKUP(A18,Sheet3!A:F,6,0) -> 200 | G18: =VLOOKUP(A18,Sheet3!A:E,5,0) -> 0 | H18: =VLOOKUP(A18,Sheet3!A:C,3,0) -> 0 | I18: =F18-G18-H18 -> 200
A19: 100_111200_1300_55210_819 | B19: Child Study | C19: Cur. Year Fac. Travel & Con | D19: AAS Division | E19: 0 | F19: =VLOOKUP(A19,Sheet3!A:F,6,0) -> 600 | G19: =VLOOKUP(A19,Sheet3!A:E,5,0) -> 160 | H19: =VLOOKUP(A19,Sheet3!A:C,3,0) -> 0 | I19: =F19-G19-H19 -> 440
A20: 100_111400_0900_55210_819 | B20: Engineering | C20: Cur. Year Fac. Travel & Con | D20: AAS Division | E20: 0 | F20: =VLOOKUP(A20,Sheet3!A:F,6,0) -> 200 | G20: =VLOOKUP(A20,Sheet3!A:E,5,0) -> 0 | H20: =VLOOKUP(A20,Sheet3!A:C,3,0) -> 0 | I20: =F20-G20-H20 -> 200
A21: 100_111500_1300_55210_819 | B21: Fashion Design | C21: Cur. Year Fac. Travel & Con | D21: AAS Division | E21: 0 | F21: =VLOOKUP(A21,Sheet3!A:F,6,0) -> 600 | G21: =VLOOKUP(A21,Sheet3!A:E,5,0) -> 599.8 | H21: =VLOOKUP(A21,Sheet3!A:C,3,0) -> 0 | I21: =F21-G21-H21 -> 0.2
A22: 100_111600_1200_55210_819 | B22: Health Care Technology | C22: Cur. Year Fac. Travel & Con | D22: AAS Division | E22: 0 | F22: =VLOOKUP(A22,Sheet3!A:F,6,0) -> 400 | G22: =VLOOKUP(A22,Sheet3!A:E,5,0) -> 0 | H22: =VLOOKUP(A22,Sheet3!A:C,3,0) -> 0 | I22: =F22-G22-H22 -> 400
A23: 100_111700_1300_55210_819 | B23: Interior Design | C23: Cur. Year Fac. Travel & Con | D23: AAS Division | E23: 0 | F23: =VLOOKUP(A23,Sheet3!A:F,6,0) -> 800 | G23: =VLOOKUP(A23,Sheet3!A:E,5,0) -> 0 | H23: =VLOOKUP(A23,Sheet3!A:C,3,0) -> 0 | I23: =F23-G23-H23 -> 800
A24: 100_111800_1400_55210_819 | B24: Paralegal | C24: Cur. Year Fac. Travel & Con | D24: AAS Division | E24: 0 | F24: =VLOOKUP(A24,Sheet3!A:F,6,0) -> 400 | G24: =VLOOKUP(A24,Sheet3!A:E,5,0) -> 0 | H24: =VLOOKUP(A24,Sheet3!A:C,3,0) -> 0 | I24: =F24-G24-H24 -> 400
... A58: 100_103206_6150_55500_819 | B58: WVC SARS | C58: Soft. Lic./Soft. Purch. | D58: VP Administrative Services | E58: 6500 | F58: =VLOOKUP(A58,Sheet3!A:F,6,0) -> 6500 | G58: =VLOOKUP(A58,Sheet3!A:E,5,0) -> 6255 | H58: =VLOOKUP(A58,Sheet3!A:C,3,0) -> 0 | I58: =F58-G58-H58 -> 245
A59: 100_103207_6150_55500_819 | B59: WVC Angel | C59: Soft. Lic./Soft. Purch. | D59: VP Administrative Services | E59: 78691 | F59: =VLOOKUP(A59,Sheet3!A:F,6,0)-F82 -> 78691 | G59: =VLOOKUP(A59,Sheet3!A:E,5,0)-G82 -> 78690.63 | H59: =VLOOKUP(A59,Sheet3!A:C,3,0) -> 0 | I59: =F59-G59-H59 -> 0.37
A60: 100_103208_6150_55500_819 | B60: WVC CCCApply | C60: Soft. Lic./Soft. Purch. | D60: VP Administrative Services | E60: 15609 | F60: =VLOOKUP(A60,Sheet3!A:F,6,0) -> 15609 | G60: =VLOOKUP(A60,Sheet3!A:E,5,0) -> 15614 | H60: =VLOOKUP(A60,Sheet3!A:C,3,0) -> 0 | I60: =F60-G60-H60 -> -5
A61: 100_103209_6010_55500_819 | B61: Astra/LaserFiche/FormFusion | C61: Soft. Lic./Soft. Purch. | D61: VP Administrative Services | E61: 19057 | F61: =VLOOKUP(A61,Sheet3!A:F,6,0) -> 19057 | G61: =VLOOKUP(A61,Sheet3!A:E,5,0) -> 18110 | H61: =VLOOKUP(A61,Sheet3!A:C,3,0) -> 0 | I61: =F61-G61-H61 -> 947
A62: 100_103251_4900_51310_819 | B62: College Hourly-Academic | C62: PT Faculty, Teaching | D62: VP Administrative Services | E62: 27500 | F62: =VLOOKUP(A62,Sheet3!A:F,6,0) -> 27500 | G62: =VLOOKUP(A62,Sheet3!A:E,5,0) -> 27500 | H62: =VLOOKUP(A62,Sheet3!A:C,3,0) -> 0 | I62: =F62-G62-H62 -> 0
A63: 100_106100_6120_55510_819 | B63: Library | C63: Equipment Maint. & Repair | D63: Dean Learning Services | E63: 45032 | F63: =VLOOKUP(A63,Sheet3!A:F,6,0) -> 45032 | G63: =VLOOKUP(A63,Sheet3!A:E,5,0) -> 44179.56 | H63: =VLOOKUP(A63,Sheet3!A:C,3,0) -> 830.44 | I63: =F63-G63-H63 -> 22
A64: 100_115200_6960_51450_819 | B64: Intercollegiate Athletics | C64: PT Fac. Non Teach Stipends | D64: Physical Education Division | E64: 24625 | F64: =VLOOKUP(A64,Sheet3!A:F,6,0) -> 23018 | G64: =VLOOKUP(A64,Sheet3!A:E,5,0) -> 22000 | H64: =VLOOKUP(A64,Sheet3!A:C,3,0) -> 0 | I64: =F64-G64-H64 -> 1018
A65: 100_115200_6960_53120_819 | B65: Intercollegiat | F65: =VLOOKUP(A65,Sheet3!A:F,6,0) -> 1532 | G65: =VLOOKUP(A65,Sheet3!A:E,5,0) -> 1361.29 | H65: =VLOOKUP(A65,Sheet3!A:C,3,0) -> 0 | I65: =F65-G65-H65 -> 170.71
A66: 100_115200_6960_53314_819 | B66: Intercollegiat | F66: =VLOOKUP(A66,Sheet3!A:F,6,0) -> 0 | G66: =VLOOKUP(A66,Sheet3!A:E,5,0) -> 170 | H66: =VLOOKUP(A66,Sheet3!A:C,3,0) -> 0 | I66: =F66-G66-H66 -> -170
A67: 100_115200_6960_53323_819 | B67: Intercollegiat | F67: =VLOOKUP(A67,Sheet3!A:F,6,0) -> 330 | G67: =VLOOKUP(A67,Sheet3!A:E,5,0) -> 282.74 | H67: =VLOOKUP(A67,Sheet3!A:C,3,0) -> 0 | I67: =F67-G67-H67 -> 47.26
A68: 100_115200_6960_53520_819 | B68: Intercollegiat | F68: =VLOOKUP(A68,Sheet3!A:F,6,0) -> 250 | G68: =VLOOKUP(A68,Sheet3!A:E,5,0) -> 240.37 | H68: =VLOOKUP(A68,Sheet3!A:C,3,0) -> 0 | I68: =F68-G68-H68 -> 9.63
A69: 100_115200_6960_53620_819 | B69: Intercollegiat | F69: =VLOOKUP(A69,Sheet3!A:F,6,0) -> 336 | G69: =VLOOKUP(A69,Sheet3!A:E,5,0) -> 322.74 | H69: =VLOOKUP(A69,Sheet3!A:C,3,0) -> 0 | I69: =F69-G69-H69 -> 13.26
A70: 100_115200_6960_53324_819 | F70: =VLOOKUP(A70,Sheet3!A:F,6,0) -> 345 | G70: =VLOOKUP(A70,Sheet3!A:E,5,0) -> 0 | H70: =VLOOKUP(A70,Sheet3!A:C,3,0) -> 0 | I70: =F70-G70-H70 -> 345
A71: 100_115200_6960_55940_819 | B71: Intercollegiate Athletics | C71: Insurance | D71: Physical Education Division | E71: 110568 | F71: =VLOOKUP(A71,Sheet3!A:F,6,0) -> 109382 | G71: =VLOOKUP(A71,Sheet3!A:E,5,0) -> 109381.68 | H71: =VLOOKUP(A71,Sheet3!A:C,3,0) -> 0 | I71: =F71-G71-H71 -> 0.32
A72: 100_119303_6750_51450_819 | B72: WVC-NISOD | C72: PT Fac. Non Teach Stipends | D72: Senates & Staff Development | E72: 4400 | F72: =VLOOKUP(A72,Sheet3!A:F,6,0) -> 699 | G72: =VLOOKUP(A72,Sheet3!A:E,5,0) -> 0 | H72: =VLOOKUP(A72,Sheet3!A:C,3,0) -> 0 | I72: =F72-G72-H72 -> 699
A73: 100_119303_6750_55115_819 | B73: WVC-NISOD | C73: Food Services | D73: Senates & Staff Development | E73: 1100 | F73: =VLOOKUP(A73,Sheet3!A:F,6,0) -> 5718 | G73: =VLOOKUP(A73,Sheet3!A:E,5,0) -> 5564.7 | H73: =VLOOKUP(A73,Sheet3!A:C,3,0) -> 0 | I73: =F73-G73-H73 -> 153.3
A74: 100_119303_6750_55200_819 | B74: WVC-NISOD | C74: Travel, Conference | D74: Senates & Staff Development | E74: 3300 | F74: =VLOOKUP(A74,Sheet3!A:F,6,0) -> 2383 | G74: =VLOOKUP(A74,Sheet3!A:E,5,0) -> 924.08 | H74: =VLOOKUP(A74,Sheet3!A:C,3,0) -> 0 | I74: =F74-G74-H74 -> 1458.92
A75: 100_119304_6750_55115_819 | B75: WVC S.D. Academic Senate | C75: Food Services | D75: Senates & Staff Development | E75: 1100 | F75: =VLOOKUP(A75,Sheet3!A:F,6,0) -> 1100 | G75: =VLOOKUP(A75,Sheet3!A:E,5,0) -> 0 | H75: =VLOOKUP(A75,Sheet3!A:C,3,0) -> 0 | I75: =F75-G75-H75 -> 1100
A76: 100_119304_6750_55200_819 | B76: WVC S.D. Academic Senate | C76: Travel, Conference | D76: Senates & Staff Development | E76: 3300 | F76: =VLOOKUP(A76,Sheet3!A:F,6,0) -> 3300 | G76: =VLOOKUP(A76,Sheet3!A:E,5,0) -> 0 | H76: =VLOOKUP(A76,Sheet3!A:C,3,0) -> 0 | I76: =F76-G76-H76 -> 3300
A77: 100_119305_6750_55115_819 | B77: WVC S.D. Classified Senate | C77: Food Services | D77: Senates & Staff Development | E77: 3660 | F77: =VLOOKUP(A77,Sheet3!A:F,6,0) -> 3660 | G77: =VLOOKUP(A77,Sheet3!A:E,5,0) -> 3033.84 | H77: =VLOOKUP(A77,Sheet3!A:C,3,0) -> 0 | I77: =F77-G77-H77 -> 626.16
A78: 100_119305_6750_55160_819 | B78: WVC S.D. Classified Senate | C78: Contracted Services | D78: Senates & Staff Development | E78: 440 | F78: =VLOOKUP(A78,Sheet3!A:F,6,0) -> 440 | G78: =VLOOKUP(A78,Sheet3!A:E,5,0) -> 440.02 | H78: =VLOOKUP(A78,Sheet3!A:C,3,0) -> 0 | I78: =F78-G78-H78 -> -0.02
A79: 100_119305_6750_55200_819 | B79: WVC S.D. Classified Senate | C79: Travel, Conference | D79: Senates & Staff Development | E79: 300 | F79: =VLOOKUP(A79,Sheet3!A:F,6,0) -> 300 | G79: =VLOOKUP(A79,Sheet3!A:E,5,0) -> 274.48 | H79: =VLOOKUP(A79,Sheet3!A:C,3,0) -> 0 | I79: =F79-G79-H79 -> 25.52
A80: 100_131000_6470_55520_819 | B80: Campbell Center | C80: Leases | D80: Campbell Center | E80: 34000 | F80: =VLOOKUP(A80,Sheet3!A:F,6,0) -> 34000 | G80: =VLOOKUP(A80,Sheet3!A:E,5,0) -> 34000 | H80: =VLOOKUP(A80,Sheet3!A:C,3,0) -> 0 | I80: =F80-G80-H80 -> 0
D81: WVC Total | E81: =SUM(E3:E80) -> 1009369 | F81: =SUM(F3:F80) -> 1009369 | G81: =SUM(G3:G80) -> 891020.52 | H81: =SUM(H3:H80) -> 830.57 | I81: =SUM(I3:I80) -> 117508.83
A82: 100_103207_6150_55500_819 | B82: WVC Angel | C82: Soft. Lic./Soft. Purch. | D82: Prepaid | E82: 0 | F82: 19132 | G82: 19132 | H82: 0 | I82: =F82-G82-H82 -> 0
A83: 100_103200_6010_51221_818 | B83: College Admin Services Office | C83: Shared Gov Reassigned Time | D83: VP Administrative Services | E83: 26000 | F83: 26000 | G83: =VLOOKUP(A83,Sheet3!A:E,5,0) -> 0 | H83: 0 | I83: =F83-G83-H83 -> 26000
D84: WVC Total 818& 819 | E84: =E81+E82+E83 -> 1035369 | F84: =F81+F82+F83 -> 1054501 | G84: =G81+G82+G83 -> 910152.52 | H84: =H81+H82+H83 -> 830.57 | I84: =I81+I82+I83 -> 143508.83
A85: 100_103201_6010_55220_819 | B85: Faculty Travel & Conf. | C85: Prior Yr.Fac. Travel/Conf. | D85: VP Administrative Services | E85: 0 | F85: =VLOOKUP(A85,Sheet3!A:F,6,0) -> 13746 | G85: =VLOOKUP(A85,Sheet3!A:E,5,0) -> 0 | H85: =VLOOKUP(A85,Sheet3!A:C,3,0) -> 0 | I85: =F85-G85-H85 -> 13746
A86: 100_106100_6120_55220_819 | B86: Library | C86: Prior Yr.Fac. Travel/Conf. | D86: Dean Learning Services | E86: 0 | F86: =VLOOKUP(A86,Sheet3!A:F,6,0) -> 1040 | G86: =VLOOKUP(A86,Sheet3!A:E,5,0) -> 90.18 | H86: =VLOOKUP(A86,Sheet3!A:C,3,0) -> 0 | I86: =F86-G86-H86 -> 949.82
A87: 100_107100_0700_55220_819 | B87: WVC Instructional Computi | C87: Prior Yr.Fac. Travel/Conf. | D87: Dean Instructional Computer Technologies | E87: 0 | F87: =VLOOKUP(A87,Sheet3!A:F,6,0) -> 2995 | G87: =VLOOKUP(A87,Sheet3!A:E,5,0) -> 0 | H87: =VLOOKUP(A87,Sheet3!A:C,3,0) -> 0 | I87: =F87-G87-H87 -> 2995
A88: 100_111004_2100_55220_819 | B88: Admin of Justice | C88: Prior Yr.Fac. Travel/Conf. | D88: AAS Division | E88: 0 | F88: =VLOOKUP(A88,Sheet3!A:F,6,0) -> 709 | G88: =VLOOKUP(A88,Sheet3!A:E,5,0) -> 460 | H88: =VLOOKUP(A88,Sheet3!A:C,3,0) -> 0 | I88: =F88-G88-H88 -> 249
A89: 100_111100_0200_55220_819 | B89: Architecture | C89: Prior Yr.Fac. Travel/Conf. | D89: AAS Division | E89: 0 | F89: =VLOOKUP(A89,Sheet3!A:F,6,0) -> 400 | G89: =VLOOKUP(A89,Sheet3!A:E,5,0) -> 0 | H89: =VLOOKUP(A89,Sheet3!A:C,3,0) -> 0 | I89: =F89-G89-H89 -> 400
A90: 100_111200_1300_55220_819 | B90: Child Study | C90: Prior Yr.Fac. Travel/Conf. | D90: AAS Division | E90: 0 | F90: =VLOOKUP(A90,Sheet3!A:F,6,0) -> 2836 | G90: =VLOOKUP(A90,Sheet3!A:E,5,0) -> 0 | H90: =VLOOKUP(A90,Sheet3!A:C,3,0) -> 0 | I90: =F90-G90-H90 -> 2836
A91: 100_111400_0900_55220_819 | B91: Engineering | C91: Prior Yr.Fac. Travel/Conf. | D91: AAS Division | E91: 0 | F91: =VLOOKUP(A91,Sheet3!A:F,6,0) -> 1452 | G91: =VLOOKUP(A91,Sheet3!A:E,5,0) -> 0 | H91: =VLOOKUP(A91,Sheet3!A:C,3,0) -> 0 | I91: =F91-G91-H91 -> 1452
A92: 100_111600_1200_55220_819 | B92: Health Care Technology | C92: Prior Yr.Fac. Travel/Conf. | D92: AAS Division | E92: 0 | F92: =VLOOKUP(A92,Sheet3!A:F,6,0) -> 3000 | G92: =VLOOKUP(A92,Sheet3!A:E,5,0) -> 0 | H92: =VLOOKUP(A92,Sheet3!A:C,3,0) -> 0 | I92: =F92-G92-H92 -> 3000
A93: 100_111700_1300_55220_819 | B93: Interior Design | C93: Prior Yr.Fac. Travel/Conf. | D93: AAS Division | E93: 0 | F93: =VLOOKUP(A93,Sheet3!A:F,6,0) -> 1994 | G93: =VLOOKUP(A93,Sheet3!A:E,5,0) -> 0 | H93: =VLOOKUP(A93,Sheet3!A:C,3,0) -> 0 | I93: =F93-G93-H93 -> 1994
A94: 100_111800_1400_55220_819 | B94: Paralegal | C94: Prior Yr.Fac. Travel/Conf. | D94: AAS Division | E94: 0 | F94: =VLOOKUP(A94,Sheet3!A:F,6,0) -> 1800 | G94: =VLOOKUP(A94,Sheet3!A:E,5,0) -> 0 | H94: =VLOOKUP(A94,Sheet3!A:C,3,0) -> 0 | I94: =F94-G94-H94 -> 1800
A95: 100_111900_2100_55220_819 | B95: Park Mgmt | C95: Prior Yr.Fac. Travel/Conf. | D95: AAS Division | E95: 0 | F95: =VLOOKUP(A95,Sheet3!A:F,6,0) -> 1192 | G95: =VLOOKUP(A95,Sheet3!A:E,5,0) -> 470.31 | H95: =VLOOKUP(A95,Sheet3!A:C,3,0) -> 0 | I95: =F95-G95-H95 -> 721.69
A96: 100_112002_6010_55220_819 | B96: Business Division Office | C96: Prior Yr.Fac. Travel/Conf. | D96: Business Division | E96: 0 | F96: =VLOOKUP(A96,Sheet3!A:F,6,0) -> 200 | G96: =VLOOKUP(A96,Sheet3!A:E,5,0) -> 0 | H96: =VLOOKUP(A96,Sheet3!A:C,3,0) -> 0 | I96: =F96-G96-H96 -> 200
... A126: 100_118000_6010_55220_819 | B126: Student Services Division | C126: Prior Yr.Fac. Travel/Conf. | D126: Student Services Division | E126: 0 | F126: =VLOOKUP(A126,Sheet3!A:F,6,0) -> 16964 | G126: =VLOOKUP(A126,Sheet3!A:E,5,0) -> 1717.21 | H126: =VLOOKUP(A126,Sheet3!A:C,3,0) -> 0 | I126: =F126-G126-H126 -> 15246.79
E127: =SUM(E85:E126) -> 0 | F127: =SUM(F85:F126) -> 134930 | G127: =SUM(G85:G126) -> 18464.88 | H127: =SUM(H85:H126) -> 0 | I127: =SUM(I85:I126) -> 116465.12
D128: WVC Total 818 and 819 | E128: =E127+E84 -> 1035369 | F128: =F127+F84 -> 1189431 | G128: =G127+G84 -> 928617.4 | H128: =H127+H84 -> 830.57 | I128: =I127+I84 -> 259973.95
F129: 1189431
A130: 100_200700_6090_51450_819 | B130: Accreditation/Program Rev | C130: PT Fac Non Teaching Stipends | D130: MC President | E130: 0 | F130: =VLOOKUP(A130,Sheet3!A:F,6,0) -> 11686 | G130: =VLOOKUP(A130,Sheet3!A:E,5,0) -> 12291.36 | H130: =VLOOKUP(A130,Sheet3!A:C,3,0) -> 0 | I130: =F130-G130-H130 -> -605.36
A131: 100_200700_6090_54210_819 | B131: Accreditation/Program Rev | C131: Non-Instr. Supplies/Materia | D131: MC President | E131: 10000 | F131: =VLOOKUP(A131,Sheet3!A:F,6,0) -> 1500 | G131: =VLOOKUP(A131,Sheet3!A:E,5,0) -> 183.64 | H131: =VLOOKUP(A131,Sheet3!A:C,3,0) -> 0 | I131: =F131-G131-H131 -> 1316.36
A132: 100_200700_6090_55910_819 | B132: Accreditation/Program Rev | C132: Dues, Memberships & Fees | D132: MC President | E132: 17453 | F132: =VLOOKUP(A132,Sheet3!A:F,6,0) -> 17453 | G132: =VLOOKUP(A132,Sheet3!A:E,5,0) -> 15579 | H132: =VLOOKUP(A132,Sheet3!A:C,3,0) -> 0 | I132: =F132-G132-H132 -> 1874
A133: 100_200700_6090_53120_819 | B133: Accreditation/ | C133: 0 | D133: MC President | E133: 0 | F133: =VLOOKUP(A133,Sheet3!A:F,6,0) -> 848 | G133: =VLOOKUP(A133,Sheet3!A:E,5,0) -> 897.93 | H133: =VLOOKUP(A133,Sheet3!A:C,3,0) -> 0 | I133: =F133-G133-H133 -> -49.93
A134: 100_200700_6090_53323_819 | B134: Accreditation/ | C134: 0 | D134: MC President | E134: 0 | F134: =VLOOKUP(A134,Sheet3!A:F,6,0) -> 182 | G134: =VLOOKUP(A134,Sheet3!A:E,5,0) -> 176.17 | H134: =VLOOKUP(A134,Sheet3!A:C,3,0) -> 0 | I134: =F134-G134-H134 -> 5.83
A135: 100_200700_6090_53520_819 | B135: Accreditation/ | C135: 0 | D135: MC President | E135: 0 | F135: =VLOOKUP(A135,Sheet3!A:F,6,0) -> 127 | G135: =VLOOKUP(A135,Sheet3!A:E,5,0) -> 133.05 | H135: =VLOOKUP(A135,Sheet3!A:C,3,0) -> 0 | I135: =F135-G135-H135 -> -6.05
A136: 100_200700_6090_53620_819 | B136: Accreditation/ | C136: 0 | D136: MC President | E136: 0 | F136: =VLOOKUP(A136,Sheet3!A:F,6,0) -> 170 | G136: =VLOOKUP(A136,Sheet3!A:E,5,0) -> 178.71 | H136: =VLOOKUP(A136,Sheet3!A:C,3,0) -> 0 | I136: =F136-G136-H136 -> -8.71
A137: 100_206200_6750_54210_819 | B137: Academic Senate | C137: Non-Instr. Supplies/Materia | D137: Staff Development | E137: 1000 | F137: =VLOOKUP(A137,Sheet3!A:F,6,0) -> 372 | G137: =VLOOKUP(A137,Sheet3!A:E,5,0) -> 371.39 | H137: =VLOOKUP(A137,Sheet3!A:C,3,0) -> 0 | I137: =F137-G137-H137 -> 0.61
A138: 100_206200_6750_55200_819 | B138: Academic Senate | C138: Travel, Conference | D138: Staff Development | E138: 3000 | F138: =VLOOKUP(A138,Sheet3!A:F,6,0) -> 2718 | G138: =VLOOKUP(A138,Sheet3!A:E,5,0) -> 2717.25 | H138: =VLOOKUP(A138,Sheet3!A:C,3,0) -> 0 | I138: =F138-G138-H138 -> 0.75
A139: 100_206200_6750_51450_819 | B139: Academic Senat | C139: 0 | D139: 0 | E139: 0 | F139: =VLOOKUP(A139,Sheet3!A:F,6,0) -> 810 | G139: =VLOOKUP(A139,Sheet3!A:E,5,0) -> 0
A140: 100_206200_6750_53120_819 | B140: Academic Senat | C140: 0 | D140: 0 | E140: 0 | F140: =VLOOKUP(A140,Sheet3!A:F,6,0) -> 67 | G140: =VLOOKUP(A140,Sheet3!A:E,5,0) -> 0
A141: 100_206200_6750_53323_819 | B141: Academic Senat | C141: 0 | D141: 0 | E141: 0 | F141: =VLOOKUP(A141,Sheet3!A:F,6,0) -> 12 | G141: =VLOOKUP(A141,Sheet3!A:E,5,0) -> 0
A142: 100_206200_6750_53520_819 | B142: Academic Senat | C142: 0 | D142: 0 | E142: 0 | F142: =VLOOKUP(A142,Sheet3!A:F,6,0) -> 9 | G142: =VLOOKUP(A142,Sheet3!A:E,5,0) -> 0
A143: 100_206200_6750_53620_819 | B143: Academic Senat | C143: 0 | D143: 0 | E143: 0 | F143: =VLOOKUP(A143,Sheet3!A:F,6,0) -> 12 | G143: =VLOOKUP(A143,Sheet3!A:E,5,0) -> 0
A144: 100_206300_6750_52310_819 | B144: MC-Classified Senate | C144: Hourly Classified Salaries | D144: Staff Development | E144: 1000 | F144: =VLOOKUP(A144,Sheet3!A:F,6,0) -> 0 | G144: =VLOOKUP(A144,Sheet3!A:E,5,0) -> 0 | H144: =VLOOKUP(A144,Sheet3!A:C,3,0) -> 0 | I144: =F144-G144-H144 -> 0
A145: 100_206300_6750_54210_819 | B145: MC-Classified Senate | C145: Non-Instr. Supplies/Materia | D145: Staff Development | E145: 500 | F145: =VLOOKUP(A145,Sheet3!A:F,6,0) -> 300 | G145: =VLOOKUP(A145,Sheet3!A:E,5,0) -> 204.23 | H145: =VLOOKUP(A145,Sheet3!A:C,3,0) -> 0 | I145: =F145-G145-H145 -> 95.77
A146: 100_206300_6750_55115_819 | B146: MC-Classified Senate | C146: Food Services | D146: Staff Development | E146: 1500 | F146: =VLOOKUP(A146,Sheet3!A:F,6,0) -> 1000 | G146: =VLOOKUP(A146,Sheet3!A:E,5,0) -> 800 | H146: =VLOOKUP(A146,Sheet3!A:C,3,0) -> 0 | I146: =F146-G146-H146 -> 200
A147: 100_206300_6750_55205_819 | B147: MC-Classified Senate | C147: Travel, Conference- Other Intl | D147: Staff Development | E147: 1500 | F147: =VLOOKUP(A147,Sheet3!A:F,6,0) -> 3247 | G147: =VLOOKUP(A147,Sheet3!A:E,5,0) -> 3246.43 | H147: =VLOOKUP(A147,Sheet3!A:C,3,0) -> 0 | I147: =F147-G147-H147 -> 0.57
A148: 100_220000_6010_55160_819 | B148: VP Administration | C148: Contracted Services | D148: VP Admin Services | E148: 7479 | F148: =VLOOKUP(A148,Sheet3!A:F,6,0) -> 7479 | G148: =VLOOKUP(A148,Sheet3!A:E,5,0) -> 7479 | H148: =VLOOKUP(A148,Sheet3!A:C,3,0) -> 0 | I148: =F148-G148-H148 -> 0
A149: 100_220000_6120_55510_819 | B149: VP Administration | C149: Equipment Maint. & Repair | D149: VP Admin Services | E149: 0 | F149: =VLOOKUP(A149,Sheet3!A:F,6,0) -> 0 | G149: =VLOOKUP(A149,Sheet3!A:E,5,0) -> 0 | H149: =VLOOKUP(A149,Sheet3!A:C,3,0) -> 0 | I149: =F149-G149-H149 -> 0
A150: 100_220000_6440_55940_819 | B150: VP Administration | C150: Insurance | D150: VP Admin Services | E150: 73711 | F150: =VLOOKUP(A150,Sheet3!A:F,6,0) -> 73711 | G150: =VLOOKUP(A150,Sheet3!A:E,5,0) -> 72921.12 | H150: =VLOOKUP(A150,Sheet3!A:C,3,0) -> 0 | I150: =F150-G150-H150 -> 789.88
A151: 100_220000_6770_51450_819 | B151: VP Administration | C151: PT Fac. Non Teach Stipends | D151: VP Admin Services | E151: 15000 | F151: =VLOOKUP(A151,Sheet3!A:F,6,0) -> 13193 | G151: =VLOOKUP(A151,Sheet3!A:E,5,0) -> 13125 | H151: =VLOOKUP(A151,Sheet3!A:C,3,0) -> 0 | I151: =F151-G151-H151 -> 68
A152: 100_220000_6770_53314_819 | B152: VP Administration | C152: Apple Plan - Instr | D152: VP Admin Services | E152: 0 | F152: =VLOOKUP(A152,Sheet3!A:F,6,0) -> 150 | G152: =VLOOKUP(A152,Sheet3!A:E,5,0) -> 150 | H152: =VLOOKUP(A152,Sheet3!A:C,3,0) -> 0 | I152: =F152-G152-H152 -> 0
A153: 100_220000_6770_53323_819 | B153: VP Administration | C153: Medicare - Non-Instr. | D153: VP Admin Services | E153: 0 | F153: =VLOOKUP(A153,Sheet3!A:F,6,0) -> 190 | G153: =VLOOKUP(A153,Sheet3!A:E,5,0) -> 189.59 | H153: =VLOOKUP(A153,Sheet3!A:C,3,0) -> 0 | I153: =F153-G153-H153 -> 0.41
A154: 100_220000_6770_53520_819 | B154: VP Administration | C154: UI - Instr. | D154: VP Admin Services | E154: 0 | F154: =VLOOKUP(A154,Sheet3!A:F,6,0) -> 143 | G154: =VLOOKUP(A154,Sheet3!A:E,5,0) -> 142.37 | H154: =VLOOKUP(A154,Sheet3!A:C,3,0) -> 0 | I154: =F154-G154-H154 -> 0.63
A155: 100_220000_6770_53620_819 | B155: VP Administration | C155: Worker's Comp.-Non Instr. | D155: VP Admin Services | E155: 0 | F155: =VLOOKUP(A155,Sheet3!A:F,6,0) -> 192 | G155: =VLOOKUP(A155,Sheet3!A:E,5,0) -> 191.18 | H155: =VLOOKUP(A155,Sheet3!A:C,3,0) -> 0 | I155: =F155-G155-H155 -> 0.82
A156: 100_220000_6770_53120_819 | B156: VP Administrat | C156: STR's Inst. | D156: VP Admin Services | F156: =VLOOKUP(A156,Sheet3!A:F,6,0) -> 619 | G156: =VLOOKUP(A156,Sheet3!A:E,5,0) -> 618.76 | H156: =VLOOKUP(A156,Sheet3!A:C,3,0) -> 0 | I156: =F156-G156-H156 -> 0.24
A157: 100_220001_7310_57300_819 | B157: MC Categorical MOE | C157: Transfers Out | D157: VP Admin Services | E157: 340397 | F157: =VLOOKUP(A157,Sheet3!A:F,6,0) -> 340397 | G157: =VLOOKUP(A157,Sheet3!A:E,5,0) -> 320394.85 | H157: =VLOOKUP(A157,Sheet3!A:C,3,0) -> 0 | I157: =F157-G157-H157 -> 20002.15
A158: 100_220002_7310_57300_819 | B158: MC Financial Aid Match | C158: Transfers Out | D158: VP Admin Services | E158: 88013 | F158: =VLOOKUP(A158,Sheet3!A:F,6,0) -> 88013 | G158: =VLOOKUP(A158,Sheet3!A:E,5,0) -> 0 | H158: =VLOOKUP(A158,Sheet3!A:C,3,0) -> 0 | I158: =F158-G158-H158 -> 88013
A159: 100_220004_6150_55500_819 | B159: MC SARS | C159: Soft. Lic./Soft. Purch. | D159: VP Admin Services | E159: 6500 | F159: =VLOOKUP(A159,Sheet3!A:F,6,0) -> 6453 | G159: =VLOOKUP(A159,Sheet3!A:E,5,0) -> 6255 | H159: =VLOOKUP(A159,Sheet3!A:C,3,0) -> 0 | I159: =F159-G159-H159 -> 198
A160: 100_220005_6150_55500_819 | B160: MC Angel | C160: Soft. Lic./Soft. Purch. | D160: VP Admin Services | E160: 78691 | F160: =VLOOKUP(A160,Sheet3!A:F,6,0)-F170 -> 78691 | G160: =VLOOKUP(A160,Sheet3!A:E,5,0)-G170 -> 78691.63 | H160: =VLOOKUP(A160,Sheet3!A:C,3,0) -> 0 | I160: =F160-G160-H160 -> -0.63
A161: 100_220006_6150_55500_819 | B161: MC CCCApply | C161: Soft. Lic./Soft. Purch. | D161: VP Admin Services | E161: 15609 | F161: =VLOOKUP(A161,Sheet3!A:F,6,0) -> 15609 | G161: =VLOOKUP(A161,Sheet3!A:E,5,0) -> 11514.1 | H161: =VLOOKUP(A161,Sheet3!A:C,3,0) -> 4099.9 | I161: =F161-G161-H161 -> -5
A162: 100_220007_6010_55500_819 | B162: Astra/LaserFiche/FormFusion | C162: Soft. Lic./Soft. Purch. | D162: VP Admin Services | E162: 19057 | F162: =VLOOKUP(A162,Sheet3!A:F,6,0) -> 19057 | G162: =VLOOKUP(A162,Sheet3!A:E,5,0) -> 18110 | H162: =VLOOKUP(A162,Sheet3!A:C,3,0) -> 0 | I162: =F162-G162-H162 -> 947
A163: 100_220900_6490_55160_819 | B163: MC - Collegewide | C163: Contracted Services | D163: VP Admin Services | E163: 2500 | F163: =VLOOKUP(A163,Sheet3!A:F,6,0) -> 2500 | G163: =VLOOKUP(A163,Sheet3!A:E,5,0) -> 2500 | H163: =VLOOKUP(A163,Sheet3!A:C,3,0) -> 0 | I163: =F163-G163-H163 -> 0
...

Sheet Sheet2
A1: GL Account | B1: Desc | C1: YTD Encumbrances | D1: MTD Actual | E1: YTD Actual | F1: YTD Budget | G1: Available | H1: % Avail | I1: object | J1: loc
A2: 100_100100_6090_52350_819 | B2: Accreditation | C2: 0 | D2: 0 | E2: 405 | F2: 6000 | G2: 5595 | H2: 93.25 | I2: =MID(A2,17,5) -> 52350 | J2: =MID(A2,5,1) -> 1 | M2: =VLOOKUP(A2,'Datetel Feb 28, 2013'!A:A,1,0) -> 100_100100_6090_52350_819 | P2: =SUMIF('Datetel Feb 28, 2013'!A:A,Sheet2!A2,'Datetel Feb 28, 2013'!F:F) -> 6000 | Q2: =F2-P2 -> 0
A3: 100_100100_6090_53220_819 | B3: Accreditation | C3: 0 | D3: 0 | E3: 46.24 | F3: 685 | G3: 638.76 | H3: 93.25 | I3: =MID(A3,17,5) -> 53220 | J3: =MID(A3,5,1) -> 1 | M3: =VLOOKUP(A3,'Datetel Feb 28, 2013'!A:A,1,0) -> 100_100100_6090_53220_819 | P3: =SUMIF('Datetel Feb 28, 2013'!A:A,Sheet2!A3,'Datetel Feb 28, 2013'!F:F) -> 685 | Q3: =F3-P3 -> 0
A4: 100_100100_6090_53320_819 | B4: Accreditation | C4: 0 | D4: 0 | E4: 25.11 | F4: 372 | G4: 346.89 | H4: 93.25 | I4: =MID(A4,17,5) -> 53320 | J4: =MID(A4,5,1) -> 1 | M4: =VLOOKUP(A4,'Datetel Feb 28, 2013'!A:A,1,0) -> 100_100100_6090_53320_819 | P4: =SUMIF('Datetel Feb 28, 2013'!A:A,Sheet2!A4,'Datetel Feb 28, 2013'!F:F) -> 372 | Q4: =F4-P4 -> 0
A5: 100_100100_6090_53323_819 | B5: Accreditation | C5: 0 | D5: 0 | E5: 5.87 | F5: 87 | G5: 81.13 | H5: 93.25 | I5: =MID(A5,17,5) -> 53323 | J5: =MID(A5,5,1) -> 1 | M5: =VLOOKUP(A5,'Datetel Feb 28, 2013'!A:A,1,0) -> 100_100100_6090_53323_819 | P5: =SUMIF('Datetel Feb 28, 2013'!A:A,Sheet2!A5,'Datetel Feb 28, 2013'!F:F) -> 87 | Q5: =F5-P5 -> 0
A6: 100_100100_6090_53324_819 | B6: Accreditation | C6: 0 | D6: 0 | E6: 0 | F6: 0 | G6: 0 | H6: 0 | I6: =MID(A6,17,5) -> 53324 | J6: =MID(A6,5,1) -> 1 | M6: =VLOOKUP(A6,'Datetel Feb 28, 2013'!A:A,1,0) -> 100_100100_6090_53324_819 | P6: =SUMIF('Datetel Feb 28, 2013'!A:A,Sheet2!A6,'Datetel Feb 28, 2013'!F:F) -> 0 | Q6: =F6-P6 -> 0
A7: 100_100100_6090_53520_819 | B7: Accreditation | C7: 0 | D7: 0 | E7: 4.46 | F7: 66 | G7: 61.54 | H7: 93.24 | I7: =MID(A7,17,5) -> 53520 | J7: =MID(A7,5,1) -> 1 | M7: =VLOOKUP(A7,'Datetel Feb 28, 2013'!A:A,1,0) -> 100_100100_6090_53520_819 | P7: =SUMIF('Datetel Feb 28, 2013'!A:A,Sheet2!A7,'Datetel Feb 28, 2013'!F:F) -> 66 | Q7: =F7-P7 -> 0
A8: 100_100100_6090_53620_819 | B8: Accreditation | C8: 0 | D8: 0 | E8: 5.98 | F8: 89 | G8: 83.02 | H8: 93.28 | I8: =MID(A8,17,5) -> 53620 | J8: =MID(A8,5,1) -> 1 | M8: =VLOOKUP(A8,'Datetel Feb 28, 2013'!A:A,1,0) -> 100_100100_6090_53620_819 | P8: =SUMIF('Datetel Feb 28, 2013'!A:A,Sheet2!A8,'Datetel Feb 28, 2013'!F:F) -> 89 | Q8: =F8-P8 -> 0
A9: 100_100100_6090_54210_819 | B9: Accreditation | C9: 0 | D9: 0 | E9: 99 | F9: 2701 | G9: 2602 | H9: 96.33 | I9: =MID(A9,17,5) -> 54210 | J9: =MID(A9,5,1) -> 1 | M9: =VLOOKUP(A9,'Datetel Feb 28, 2013'!A:A,1,0) -> 100_100100_6090_54210_819 | P9: =SUMIF('Datetel Feb 28, 2013'!A:A,Sheet2!A9,'Datetel Feb 28, 2013'!F:F) -> 2701 | Q9: =F9-P9 -> 0
A10: 100_100100_6090_55910_819 | B10: Accreditation | C10: 0 | D10: 0 | E10: 18326 | F10: 18953 | G10: 627 | H10: 3.31 | I10: =MID(A10,17,5) -> 55910 | J10: =MID(A10,5,1) -> 1 | M10: =VLOOKUP(A10,'Datetel Feb 28, 2013'!A:A,1,0) -> 100_100100_6090_55910_819 | P10: =SUMIF('Datetel Feb 28, 2013'!A:A,Sheet2!A10,'Datetel Feb 28, 2013'!F:F) -> 18953 | Q10: =F10-P10 -> 0
A11: 100_101000_6010_55160_819 | B11: VP Instruction | C11: 0 | D11: 0 | E11: 7479 | F11: 7479 | G11: 0 | H11: 0 | I11: =MID(A11,17,5) -> 55160 | J11: =MID(A11,5,1) -> 1 | M11: =VLOOKUP(A11,'Datetel Feb 28, 2013'!A:A,1,0) -> 100_101000_6010_55160_819 | P11: =SUMIF('Datetel Feb 28, 2013'!A:A,Sheet2!A11,'Datetel Feb 28, 2013'!F:F) -> 7479 | Q11: =F11-P11 -> 0
A12: 100_102000_6490_55160_819 | B12: VP Student Ser | C12: 0 | D12: 0 | E12: 2500 | F12: 2500 | G12: 0 | H12: 0 | I12: =MID(A12,17,5) -> 55160 | J12: =MID(A12,5,1) -> 1 | M12: =VLOOKUP(A12,'Datetel Feb 28, 2013'!A:A,1,0) -> 100_102000_6490_55160_819 | P12: =SUMIF('Datetel Feb 28, 2013'!A:A,Sheet2!A12,'Datetel Feb 28, 2013'!F:F) -> 2500 | Q12: =F12-P12 -> 0
A13: 100_103200_6010_51221_818 | B13: College Admin | C13: 0 | D13: 0 | E13: 0 | F13: 26000 | G13: 26000 | H13: 100 | I13: =MID(A13,17,5) -> 51221 | J13: =MID(A13,5,1) -> 1 | M13: =VLOOKUP(A13,'Datetel Feb 28, 2013'!A:A,1,0) -> 100_103200_6010_51221_818 | P13: =SUMIF('Datetel Feb 28, 2013'!A:A,Sheet2!A13,'Datetel Feb 28, 2013'!F:F) -> 26000 | Q13: =F13-P13 -> 0
... A121: 100_131000_6470_55520_819 | B121: Campbell Cente | C121: 0 | D121: 0 | E121: 34000 | F121: 34000 | G121: 0 | H121: 0 | I121: =MID(A121,17,5) -> 55520 | J121: =MID(A121,5,1) -> 1 | M121: =VLOOKUP(A121,'Datetel Feb 28, 2013'!A:A,1,0) -> 100_131000_6470_55520_819 | P121: =SUMIF('Datetel Feb 28, 2013'!A:A,Sheet2!A121,'Datetel Feb 28, 2013'!F:F) -> 34000 | Q121: =F121-P121 -> 0
C122: =SUM(C2:C121) -> 2364.09 | D122: =SUM(D2:D121) -> 5701.63 | E122: =SUM(E2:E121) -> 366775.65 | F122: =SUM(F2:F121) -> 1189431 | G122: =SUM(G2:G121) -> 820291.26 | H122: =SUM(H2:H121) -> 9771.21 | I122: =MID(A122,17,5) | J122: =MID(A122,5,1)
I123: =MID(A123,17,5) | J123: =MID(A123,5,1)
A124: 100_200700_6090_51450_819 | B124: Accreditation/ | C124: 0 | D124: 1817.64 | E124: 1817.64 | F124: 8500 | G124: 6682.36 | H124: 78.62 | I124: =MID(A124,17,5) -> 51450 | J124: =MID(A124,5,1) -> 2 | M124: =VLOOKUP(A124,'Datetel Feb 28, 2013'!A:A,1,0) -> 100_200700_6090_51450_819 | P124: =SUMIF('Datetel Feb 28, 2013'!A:A,Sheet2!A124,'Datetel Feb 28, 2013'!F:F) -> 8500 | Q124: =F124-P124 -> 0
A125: 100_200700_6090_53120_819 | B125: Accreditation/ | C125: 0 | D125: 149.96 | E125: 149.96 | F125: 0 | G125: -149.96 | H125: 0 | I125: =MID(A125,17,5) -> 53120 | J125: =MID(A125,5,1) -> 2 | M125: =VLOOKUP(A125,'Datetel Feb 28, 2013'!A:A,1,0) -> 100_200700_6090_53120_819 | P125: =SUMIF('Datetel Feb 28, 2013'!A:A,Sheet2!A125,'Datetel Feb 28, 2013'!F:F) -> 0 | Q125: =F125-P125 -> 0
A126: 100_200700_6090_53323_819 | B126: Accreditation/ | C126: 0 | D126: 25.71 | E126: 25.71 | F126: 0 | G126: -25.71 | H126: 0 | I126: =MID(A126,17,5) -> 53323 | J126: =MID(A126,5,1) -> 2 | M126: =VLOOKUP(A126,'Datetel Feb 28, 2013'!A:A,1,0) -> 100_200700_6090_53323_819 | P126: =SUMIF('Datetel Feb 28, 2013'!A:A,Sheet2!A126,'Datetel Feb 28, 2013'!F:F) -> 0 | Q126: =F126-P126 -> 0
A127: 100_200700_6090_53520_819 | B127: Accreditation/ | C127: 0 | D127: 19.5 | E127: 19.5 | F127: 0 | G127: -19.5 | H127: 0 | I127: =MID(A127,17,5) -> 53520 | J127: =MID(A127,5,1) -> 2 | M127: =VLOOKUP(A127,'Datetel Feb 28, 2013'!A:A,1,0) -> 100_200700_6090_53520_819 | P127: =SUMIF('Datetel Feb 28, 2013'!A:A,Sheet2!A127,'Datetel Feb 28, 2013'!F:F) -> 0 | Q127: =F127-P127 -> 0
