Workbook
Name Macro1: [0]!Macro1
Name Macro2: [0]!Macro2

Sheet Sheet1
E1: 170701 | F1: ERROR!!!! PLEASE USE A VALID CODE | I1: 0 | J1: =I1 -> 0 | K1: 2 | L1: ENTER FTE FOR PART-TIME
E2: 170706 | F2: Biological Sciences-Adjunct Faculty
E3: 170707 | F3: Chemistry-Adjunct Faculty
E4: 170709 | F4: English & Foreign L-Adjunct Faculty
E5: 170710 | F5: Fine Arts-Adjunct Faculty
E6: 170711 | F6: Mathematics-Adjunct Faculty
E7: 170713 | F7: Social Sciences-Adjunct Faculty
E8: 170715 | F8: Business Administra-Adjunct Faculty
E9: 170716 | F9: Communications-Adjunct Faculty
E10: 170717 | F10: Elem. Education-Adjunct Faculty
E11: 170718 | F11: Health & Physical E-Adjunct Faculty
E12: 170720 | F12: Nursing B.S. -Adjunct Faculty
E13: 170721 | F13: Nursing M.S. -Adjunct Faculty
... E49: 182800 | F49: Social Work - Summer School
E53: ORGN CODE | F53: FUND CODE | G53: PROG CODE | I53: ORGN CODE | J53: ORGN DESCRIPTION
D54: ORGN | E54: 110103 | I54: 110103 | J54: Office of Academic Affairs - RESTRICTED
D55: ORGN | E55: 121003 | I55: 121003 | J55: Biology - RESTRICTED
D56: ORGN | E56: 122003 | I56: 122003 | J56: Chemistry - RESTRICTED
D57: ORGN | E57: 123003 | I57: 123003 | J57: Communications - RESTRICTED
D58: ORGN | E58: 124003 | I58: 124003 | J58: English & Foreign Language - RESTRICTED
D59: ORGN | E59: 125103 | I59: 125103 | J59: Fine Arts - RESTRICTED
D60: ORGN | E60: 125203 | I60: 125203 | J60: Music - RESTRICTED
D61: ORGN | E61: 125303 | I61: 125303 | J61: Humanities - RESTRICTED
D62: ORGN | E62: 125403 | I62: 125403 | J62: Speech - RESTRICTED
D63: ORGN | E63: 125503 | I63: 125503 | J63: Arts - RESTRICTED
D64: ORGN | E64: 126003 | I64: 126003 | J64: Mathematics - RESTRICTED
D65: ORGN | E65: 127003 | I65: 127003 | J65: Military Science - RESTRICTED
... D109: ORGN | E109: 400103 | I109: 400103 | J109: Student Affairs - RESTRICTED
A111: 45 | B111: ** | D111: ORGN | E111: 180100 | F111: 100000 | G111: 01 | I111: 180100 | J111: Agriculture - Summer School
A112: 46 | B112: ** | D112: ORGN | E112: 180200 | F112: 100000 | G112: 01 | I112: 180200 | J112: Home Economics - Summer School
A113: 47 | B113: ** | D113: ORGN | E113: 180300 | F113: 100000 | G113: 01 | I113: 180300 | J113: Advanced Technologies-Summer Sch
A114: 48 | B114: ** | D114: ORGN | E114: 180600 | F114: 100000 | G114: 01 | I114: 180600 | J114: Biological Sciences-Summer Sch
A115: 49 | B115: ** | D115: ORGN | E115: 180700 | F115: 100000 | G115: 01 | I115: 180700 | J115: Chemistry - Summer School
A116: 50 | B116: ** | D116: ORGN | E116: 180900 | F116: 100000 | G116: 01 | I116: 180900 | J116: English & Foreign Lang.-Summer Sch.
A117: 51 | B117: ** | D117: ORGN | E117: 181000 | F117: 100000 | G117: 01 | I117: 181000 | J117: Fine Arts - Summer School
A118: 52 | B118: ** | D118: ORGN | E118: 181100 | F118: 100000 | G118: 01 | I118: 181100 | J118: Mathematics - Summer School
A119: 53 | B119: ** | D119: ORGN | E119: 181300 | F119: 100000 | G119: 01 | I119: 181300 | J119: Social Science - Summer School
A120: 54 | B120: ** | D120: ORGN | E120: 181500 | F120: 100000 | G120: 01 | I120: 181500 | J120: Business Admini. - Summer School
A121: 55 | B121: ** | D121: ORGN | E121: 181700 | F121: 100000 | G121: 01 | I121: 181700 | J121: Elementary Education - Summer Sch.
A122: 56 | B122: ** | D122: ORGN | E122: 181800 | F122: 100000 | G122: 01 | I122: 181800 | J122: Health & Physical Educ. - Summer
... A126: 60 | B126: ** | D126: ORGN | E126: 182500 | F126: 100000 | G126: 01 | I126: 182500 | J126: Communications-Summer School
D127: ORGN | E127: 170706 | F127: Biological Sciences-Adjunct Faculty | I127: 170706 | J127: Biological Sciences-Adjunct Faculty
D128: ORGN | E128: 170707 | F128: Chemistry-Adjunct Faculty | I128: 170707 | J128: Chemistry-Adjunct Faculty
D129: ORGN | E129: 170709 | F129: English & Foreign L-Adjunct Faculty | I129: 170709 | J129: English & Foreign L-Adjunct Faculty
D130: ORGN | E130: 170710 | F130: Fine Arts-Adjunct Faculty | I130: 170710 | J130: Fine Arts-Adjunct Faculty
D131: ORGN | E131: 170711 | F131: Mathematics-Adjunct Faculty | I131: 170711 | J131: Mathematics-Adjunct Faculty
D132: ORGN | E132: 170713 | F132: Social Sciences-Adjunct Faculty | I132: 170713 | J132: Social Sciences-Adjunct Faculty
D133: ORGN | E133: 170715 | F133: Business Administra-Adjunct Faculty | I133: 170715 | J133: Business Administra-Adjunct Faculty
D134: ORGN | E134: 170716 | F134: Communications-Adjunct Faculty | I134: 170716 | J134: Communications-Adjunct Faculty
D135: ORGN | E135: 170717 | F135: Elem. Education-Adjunct Faculty | I135: 170717 | J135: Elem. Education-Adjunct Faculty
D136: ORGN | E136: 170718 | F136: Health & Physical E-Adjunct Faculty | I136: 170718 | J136: Health & Physical E-Adjunct Faculty
D137: ORGN | E137: 170720 | F137: Nursing B.S. -Adjunct Faculty | I137: 170720 | J137: Nursing B.S. -Adjunct Faculty
D138: ORGN | E138: 170721 | F138: Nursing M.S. -Adjunct Faculty | I138: 170721 | J138: Nursing M.S. -Adjunct Faculty
... D144: ORGN | E144: 170732 | F144: Human Sciences - Adjunct Faculty | I144: 170732 | J144: Human Sciences - Adjunct Faculty
A146: 82 | B146: ** | D146: ORGN | E146: 100130 | F146: 100000 | G146: 04 | I146: 100130 | J146: Faculty/Staff Convocation
A147: 131 | B147: ** | D147: ORGN | E147: 322100 | F147: 100000 | G147: 05 | I147: 322100 | J147: Athletics-Football Recruiting
A148: 132 | B148: ** | D148: ORGN | E148: 322300 | F148: 100000 | G148: 05 | I148: 322300 | J148: Athletics-Officials
A149: 136 | B149: ** | D149: ORGN | E149: 420102 | F149: 100000 | G149: 05 | I149: 420102 | J149: ASU Cheer Squad
A150: 161 | B150: ** | D150: ORGN | E150: 198100 | F150: 100000 | G150: 06 | I150: 198100 | J150: Speakers & Lectures
A151: 108 | D151: ORGN | E151: 170800 | F151: 100000 | G151: 05 | I151: 170800 | J151: Commencement
A153: 1 | C153: Home | D153: ORGN | E153: 330100 | F153: 200000 | G153: 00 | I153: 330100 | J153: Bookstore
A154: 2 | C154: Home | D154: ORGN | E154: 330200 | F154: 200000 | G154: 00 | I154: 330200 | J154: Campus Union
A155: 3 | C155: Home | D155: ORGN | E155: 330300 | F155: 200000 | G155: 00 | I155: 330300 | J155: Dining Hall
A156: 4 | C156: Home | D156: ORGN | E156: 330400 | F156: 200000 | G156: 00 | I156: 330400 | J156: Faculty Dwelling
A157: 5 | C157: Home | D157: ORGN | E157: 330500 | F157: 200000 | G157: 00 | I157: 330500 | J157: Laundry
A158: 6 | C158: Home | D158: ORGN | E158: 330600 | F158: 200000 | G158: 00 | I158: 330600 | J158: Laundromat
A159: 8 | C159: Home | D159: ORGN | E159: 430000 | F159: 200000 | G159: 00 | I159: 430000 | J159: Residence Halls/Student Housing
A160: 9 | C160: Home | D160: ORGN | E160: 440000 | F160: 200000 | G160: 00 | I160: 440000 | J160: Residence Halls/Housekeeping
A161: 10 | C161: Home | D161: ORGN | E161: 110101 | F161: 100000 | G161: 01 | I161: 110101 | J161: AYERS - Enhancement and Diversity
A162: 11 | C162: Home | D162: ORGN | E162: 120400 | F162: 100000 | G162: 01 | I162: 120400 | J162: AYERS - Master of Science, Biotech
A163: 12 | C163: Home | D163: ORGN | E163: 121000 | F163: 100000 | G163: 01 | I163: 121000 | J163: Biological Sciences
A164: 13 | C164: Home | D164: ORGN | E164: 122000 | F164: 100000 | G164: 01 | I164: 122000 | J164: Chemistry
... A193: 42 | C193: Home | D193: ORGN | E193: 170300 | F193: 100000 | G193: 01 | I193: 170300 | J193: Honors Program
A194: 63 | B194: * | C194: Home | D194: ORGN | E194: 100104 | F194: 100000 | G194: 02 | I194: 100104 | J194: Research
A195: 64 | C195: Home | D195: ORGN | E195: 130400 | F195: 100000 | G195: 02 | I195: 130400 | J195: Branch Experiment Station
A196: 65 | C196: Home | D196: ORGN | E196: 130500 | F196: 100000 | G196: 02 | I196: 130500 | J196: MS River Research
A197: 66 | C197: Home | D197: ORGN | E197: 130600 | F197: 100000 | G197: 02 | I197: 130600 | J197: Swine Development
A198: 67 | C198: Home | D198: ORGN | E198: 130700 | F198: 100000 | G198: 02 | I198: 130700 | J198: Small Farm Development Center
A199: 68 | C199: Home | D199: ORGN | E199: 130720 | F199: 100000 | G199: 02 | I199: 130720 | J199: Kemper/Winston County Incubator Pro
A200: 69 | C200: Home | D200: ORGN | E200: 130730 | F200: 100000 | G200: 02 | I200: 130730 | J200: Bolivar County Ext/Res & Tech Center
A201: 71 | C201: Home | D201: ORGN | E201: 130780 | F201: 100000 | G201: 02 | I201: 130780 | J201: Alternative Energy Center
A202: 72 | C202: Home | D202: ORGN | E202: 130850 | F202: 100000 | G202: 02 | I202: 130850 | J202: Ag Biotechnology Research Center
A203: 74 | C203: Home | D203: ORGN | E203: 130151 | F203: 100000 | G203: 03 | I203: 130151 | J203: Natural Products - Rural Co-op
A204: 75 | C204: Home | D204: ORGN | E204: 130160 | F204: 100000 | G204: 03 | I204: 130160 | J204: Natural Products - Alcorn
A205: 76 | C205: Home | D205: ORGN | E205: 130300 | F205: 100000 | G205: 03 | I205: 130300 | J205: Cooperative Extension
A206: 77 | C206: Home | D206: ORGN | E206: 130740 | F206: 100000 | G206: 03 | I206: 130740 | J206: Gulf Coast Mississippi Extension
... A238: 113 | C238: Home | D238: ORGN | E238: 320100 | F238: 100000 | G238: 05 | I238: 320100 | J238: Athletics-Administration
A239: 114 | B239: 0 | C239: Home | D239: ORGN | E239: 320200 | F239: 100000 | G239: 05 | I239: 320200 | J239: Athletics-Recruiting
A240: 115 | C240: Home | D240: ORGN | E240: 320300 | F240: 100000 | G240: 05 | I240: 320300 | J240: Athletics-Sports Information
A241: 116 | C241: Home | D241: ORGN | E241: 320400 | F241: 100000 | G241: 05 | I241: 320400 | J241: Athletics-Football
A242: 117 | C242: Home | D242: ORGN | E242: 320500 | F242: 100000 | G242: 05 | I242: 320500 | J242: Athletics-Baseball
A243: 118 | C243: Home | D243: ORGN | E243: 320600 | F243: 100000 | G243: 05 | I243: 320600 | J243: Athletics-Men's Basketball
A244: 119 | C244: Home | D244: ORGN | E244: 320700 | F244: 100000 | G244: 05 | I244: 320700 | J244: Athletics-Track
A245: 120 | C245: Home | D245: ORGN | E245: 320800 | F245: 100000 | G245: 05 | I245: 320800 | J245: Athletics-Tennis
A246: 121 | C246: Home | D246: ORGN | E246: 320900 | F246: 100000 | G246: 05 | I246: 320900 | J246: Athletics-Golf
A247: 122 | C247: Home | D247: ORGN | E247: 321000 | F247: 100000 | G247: 05 | I247: 321000 | J247: Athletics-Women's Basketball
A248: 123 | C248: Home | D248: ORGN | E248: 321100 | F248: 100000 | G248: 05 | I248: 321100 | J248: Athletics-Women's Volleyball
A249: 124 | C249: Home | D249: ORGN | E249: 321200 | F249: 100000 | G249: 05 | I249: 321200 | J249: Athletics-Women's Tennis
A250: 125 | C250: Home | D250: ORGN | E250: 321300 | F250: 100000 | G250: 05 | I250: 321300 | J250: Athletics-Women's Softball
A251: 126 | C251: Home | D251: ORGN | E251: 321500 | F251: 100000 | G251: 05 | I251: 321500 | J251: Athletics-Sports Medicine
...

Sheet Fall.Spring.ActionForm
B2: ALCORN STATE UNIVERSITY
B4: FALL & SPRING
B5: ADJUNCT & OVERLOAD ASSIGNMENT ACTION FORM
B7: This form is submitted to request a one time payment to existing faculty members/overload, *RECURRING adjunct faculty members,
B8: and staff members/2nd assignment for classes taught during the Fall or Spring Semester. Payment will be made at the close
B9: of the applicable semester.
B10: NOTE: Adjunct Faculty Members who are ORIGINAL APPOINTLENTS to the university, RECENTLY RETIRED, or need to RENEW
B11: after a break in service that extends beyond 1 year are NOT included on this form. A PAF is required by Human Resources.
B13: DEPARTMENT | H13: DATE:
B15: CHECK ONE: | E15: FALL | G15: SPRING
B17: ADJUNCT ORGANIZATION CODE: | G17: =VLOOKUP(E17,Sheet1!E1:F19,2,FALSE) -> #N/A
B19: COMMENTS:
C24: ID NUMBER | E24: FACULTY OR STAFF MEMBER | I24: AMOUNT DUE
B26: 1
B27: 2
B28: 3
B29: 4
B30: 5
B31: 6
B32: 7
B33: 8
B34: 9
B35: 10
B36: 11
B37: 12
... B45: 20
G48: TOTAL | I48: =SUM(I25:I45) -> 0
G49: Budget Office
B50: Chairperson | H50: Date:
B52: Dean | H52: Date:
B54: Area Vice President | H54: Date:

Sheet SummerAssignmentActionForm
B2: ALCORN STATE UNIVERSITY
B4: SUMMER ASSIGNMENT ACTION FORM
B6: This form is submitted to request a one time payment to existing faculty members/overload, *RECURRING adjunct faculty members,
B7: and staff members/2nd assignment for classes taught during a summer session. Payment will be made at the close of the
B8: applicable summer session.
B9: NOTE: Adjunct Faculty Members who are ORIGINAL APPOINTMENTS to the university, RECENTLY RETIRED, or need to RENEW
B10: after a break in service that extends beyond 1 year are NOT included on this form. A PAF is required by Human Resources.
B12: DEPARTMENT | K12: DATE:
B14: CHECK ONE: | D14: SUMMER I | F14: SUMMER II
B16: SUMMER ORGANIZATION CODE: | H16: =VLOOKUP(F16,Sheet1!E21:F49,2,FALSE) -> #N/A
B18: COMMENTS:
B20: ID NUMBER | D20: FACULTY/STAFF MEMBER | F20: POSITION NUMBER | H20: ANNUAL SALARY | J20: MONTHLY SALARY | L20: AMOUNT DUE | P20: For Business Office Use
A22: 1 | J22: =H22/9 -> 0 | Q22: 1
A23: 2 | J23: =H23/9 -> 0 | Q23: 2
A24: 3 | J24: =H24/9 -> 0 | Q24: 3
A25: 4 | J25: =H25/9 -> 0 | Q25: 4
A26: 5 | J26: =H26/9 -> 0 | Q26: 5
A27: 6 | J27: =H27/9 -> 0 | Q27: 6
A28: 7 | J28: =H28/9 -> 0 | Q28: 7
A29: 8 | J29: =H29/9 -> 0 | Q29: 8
A30: 9 | J30: =H30/9 -> 0 | Q30: 9
A31: 10 | J31: =H31/9 -> 0 | Q31: 10
A32: 11 | J32: =H32/9 -> 0 | Q32: 11
A33: 12 | J33: =H33/9 -> 0 | Q33: 12
... A36: 15 | J36: =H36/9 -> 0 | Q36: 15
J39: TOTAL | L39: =SUM(L21:L36) -> 0
J40: Budget Office
B41: SUMMER I
A42: If an employee WHO IS LISTED ABOVE will also be working on a project during SUMMER I, complete this section to request compensation for the portion
A43: of pay that is to be charged to RESTRICTED SOURCES.
B44: ID NUMBER | D44: FACULTY/STAFF MEMBER | F44: RESTRICTED FUND | H44: ORGN | J44: ACCT | L44: AMOUNT DUE (DAYS IN MAY) | N44: AMOUNT DUE (JUNE) | P44: TOTAL AMOUNT DUE
A45: 1 | P45: =+L45+N45 -> 0
A46: 2 | P46: =+L46+N46 -> 0
A47: 3 | P47: =+L47+N47 -> 0
A48: 4 | P48: =+L48+N48 -> 0
A49: 5 | P49: =+L49+N49 -> 0
A50: 6 | P50: =+L50+N50 -> 0
B53: SUMMER II
A54: If an employee WHO IS LISTED ABOVE will also be working on a project during SUMMER II, complete this section to request compensation for the portion
A55: of pay that is to be charged to RESTRICTED SOURCES.
B56: ID NUMBER | D56: FACULTY/STAFF MEMBER | F56: RESTRICTED FUND | H56: ORGN | J56: ACCT | L56: AMOUNT DUE (JULY) | N56: AMOUNT DUE (DAYS IN AUGUST) | P56: TOTAL AMOUNT DUE
A57: 1 | P57: =+L57+N57 -> 0
A58: 2 | P58: =+L58+N58 -> 0
A59: 3 | P59: =+L59+N59 -> 0
A60: 4 | P60: =+L60+N60 -> 0
A61: 5 | P61: =+L61+N61 -> 0
A62: 6 | P62: =+L62+N62 -> 0
N64: Grants Accountant
B65: Chairperson | J65: Date:
N66: Grants Accountant
B67: Dean | J67: Date:
B69: Area Vice President | J69: Date:
P71: 40834

Sheet PAF.OriginalRevised
B1: ALCORN STATE UNIVERSITY
B2: PERSONNEL ACTION FORM
B4: To avoid processing delays, please ensure all applicable sections are complete and accurate.
B6: Personal Data
B7: 1 | C7: Last Name | F7: Suffix | G7: First Name | K7: Middle | P7: Prefix | Q7: SSN / ID | U7: Current Date
C9: Current Date | E9: SSN | H9: Date of Birth | M9: Home Phone #
C11: Street Address | G11: City | K11: County | M11: State | W11: Zip Code
C13: Type of Action | I13: Action Dates | O13: Comments
B14: 2 | C14: Original Appointment | F14: Complete Section 4A | I14: Effective date provided by HR | N14: Use the section below for further explanation
C15: Re-Employed (break in employment) | F15: Complete Section 4A | I15: Effective date provided by HR
C16: Extension of Employment (no break) | F16: Complete Sections 4A and 4B | I16: Effective Date
C17: Promotion / Merit / Annual Inc. | F17: Complete Sections 4A and 4B | I17: Effective Date
C18: Transfer | F18: Complete Sections 4A and 4B | I18: Effective Date
C19: Release Time (Projects Only) | F19: Complete Sections 4A and 4B | I19: Effective Date
C20: Separation | F20: Complete Section 4B | I20: Last Date Worked
C21: Other (specify): | I21: Effective Date
B22: Position Data
N23: Adjunct Faculty (select for NEW Adjunct Faculty, RECENTLY RETIRED, or to RENEW former members if there has been more than 1 year break in service, otherwise include on Overload or Summer Assignment Action Form)
B24: 3 | C24: A. Position Type: | F24: Staff | I24: Faculty
C27: B. Rank, if Faculty: | F27: Instructor | I27: Assistant Professor | N27: Associate Professor | R27: Professor | T27: OR | V27: NON FACULTY
C30: C. Pay Type: | F30: 9 Months | I30: 10 Months | N30: 11 Months | R30: 12 Months | V30: Other
C33: D. Pay Frequency: | F33: Monthly | I33: Bi Weekly | N33: One Time Pay at END of the: Semester/Summer Session/Assignment
C36: E. Job Status: | F36: Full Time | H36: 2 | I36: Part-time - FTE for part-time: | L36: =Sheet1!J1 -> 0 | N36: =VLOOKUP(L36,Sheet1!K1:L1,2,FALSE) -> #N/A
C39: F. Assignment: | F39: Regular | I39: Regular (Temporary Funding Source)-End Date: | R39: Temp Employment - End Date:
C42: G. Retiree of PERS of MS? | F42: No | I42: Yes - Retirement Date:
C45: H. Total Salary: | E45: Per Year | H45: Per Hour | L45: Per Other
C48: I. HOME ORGANIZATION (or HOME DEPARTMENT): If this is a Restricted Project, Indicate a Department from the E&G printed budget's Table of Contents that most closely relates to the project, or
C49: indicate the department to which the employee's check should be distributed.
D50: Home Organization Code: | G50: =VLOOKUP(E50,Sheet1!I153:J414,2,FALSE) -> #N/A | V50: 0 | W50: 0
C52: Receiving Department
B53: 4A | C53: POSITIONS CONTAINING E&G FUNDS: budget managers should assign a position from your printed budget. If the position is temporary, an applicable pooled position number should be assigned.
C54: 100% RESTRICTED FUNDS: the position number will be assigned by a Grants & Contracts Accountant
B55: To | C55: Position Number | G55: Position Title
C57: Source of Funding (RECEIVING DEPARTMENT)
C58: E&G Budget Line # | D58: Budget Page # | F58: Fund Code | H58: Organization Code | J58: *Account Code | M58: Budget / Grant Name | S58: **Percentage of Funds | U58: Salary Amount Per Account
M59: =VLOOKUP(H59,Sheet1!I$54:J$289,2,FALSE) -> #N/A | S59: =SUM(U59/U$66) -> #DIV/0!
M60: =VLOOKUP(H60,Sheet1!I$54:J$289,2,FALSE) -> #N/A | S60: =SUM(U60/U$66) -> #DIV/0!
M61: =VLOOKUP(H61,Sheet1!I$54:J$289,2,FALSE) -> #N/A | S61: =SUM(U61/U$66) -> #DIV/0!
M62: =VLOOKUP(H62,Sheet1!I$54:J$289,2,FALSE) -> #N/A | S62: =SUM(U62/U$66) -> #DIV/0!
M63: =VLOOKUP(H63,Sheet1!I$54:J$289,2,FALSE) -> #N/A | S63: =SUM(U63/U$66) -> #DIV/0!
M64: =VLOOKUP(H64,Sheet1!I$54:J$289,2,FALSE) -> #N/A | S64: =SUM(U64/U$66) -> #DIV/0!
D66: *Account Code: Indicate 611000 for instructional compensation allotment, 612000 for all other monthly compensation, 622000 for biweekly compensation | Q66: TOTAL | S66: =SUM(S59:T64) -> #DIV/0! | U66: =SUM(U59:V64) -> 0
T67: **Percentage of funds: to be carried 2 decimal places. Do not round
C69: Releasing Department
B70: 4B | C70: Position Number | G70: Position Title
B72: From | C72: Source of Funding (RELEASING DEPARTMENT)
C73: E&G Budget Line # | D73: Budget Page # | F73: Fund Code | H73: Organization Code | J73: Account Code | M73: Budget / Grant Name | S73: **Percentage of Funds | U73: Salary Amount Per Account
M74: =VLOOKUP(H74,Sheet1!I$54:J$289,2,FALSE) -> #N/A | S74: =SUM(U74/U$81) -> #DIV/0!
M75: =VLOOKUP(H75,Sheet1!I$54:J$289,2,FALSE) -> #N/A | S75: =SUM(U75/U$81) -> #DIV/0!
M76: =VLOOKUP(H76,Sheet1!I$54:J$289,2,FALSE) -> #N/A | S76: =SUM(U76/U$81) -> #DIV/0!
M77: =VLOOKUP(H77,Sheet1!I$54:J$289,2,FALSE) -> #N/A | S77: =SUM(U77/U$81) -> #DIV/0!
M78: =VLOOKUP(H78,Sheet1!I$54:J$289,2,FALSE) -> #N/A | S78: =SUM(U78/U$81) -> #DIV/0!
M79: =VLOOKUP(H79,Sheet1!I$54:J$289,2,FALSE) -> #N/A | S79: =SUM(U79/U$81) -> #DIV/0!
Q81: TOTAL | S81: =SUM(S74:T79) -> #DIV/0! | U81: =SUM(U74:V79) -> 0
B83: Approvals
B84: 5 | C84: Funds Approval
E85: Grants and Contracts | M85: Budget Office
C86: *I UNDERSTAND THAT NO INDIVIDUAL SHALL BE ALLOWED TO START A WORK ASSIGNMENT WITHOUT PRIOR AUTHORIZATION OF HUMAN RESOURCES*
C87: Approvals Required for Section 4A (RECEIVING DEPARTMENT) | L87: Approvals Required for Section 4B (RELEASING DEPARTMENT)
C88: Budgetary Authority: | J88: Date | L88: Budgetary Authority: | V88: Date
C89: Dean or Administrative Head: | J89: Date | L89: Dean or Administrative Head: | V89: Date
C90: Area Vice President: | J90: Date | L90: Area Vice President: | V90: Date
C91: President (if applicable): | J91: Date | L91: President (if applicable): | V91: Date
B92: Approvals Required for Original Appointment/Re-Employed Only | L92: Signature (Original Appointments & Re-Employed Only)
B93: 6 | C93: Dir. of Human Resources | J93: Date | L93: Employee | V93: Date
B94: Human Resources or Payroll Use Only
B95: 7 | C95: Is Position Exempt under FLSA? | F95: Yes o No o | H95: Effective Date of Hire: | L95: Date | P95: Date to HR | S95: Date
C96: EEOC CODE: | F96: EClass: | H96: Payroll Review: | L96: Date | P96: Banner Entry Date | S96: Date

Sheet PAF
B1: ALCORN STATE UNIVERSITY
B2: PERSONNEL ACTION FORM
B5: To avoid processing delays, please ensure all applicable sections are complete and accurate.
B7: PERSONAL DATA
B8: 1 | C8: Last Name | F8: Suffix | G8: First Name | K8: Middle | P8: Prefix | Q8: SSN / ID | U8: Current Date
C10: Current Date | E10: SSN | H10: Date of Birth | M10: Home Phone #
C12: Street Address | G12: City | K12: County | M12: State | W12: Zip Code
C14: TYPE OF ACTION | I14: ACTION DATES | N14: COMMENTS
B15: 2 | C15: Original Appointment | F15: Complete Section 4A | I15: Effective date provided by HR | N15: Use the section below for further explanation
C16: Re-Employed (break in employment) | F16: Complete Section 4A | I16: Effective date provided by HR
C17: Extension of Employment (no break) | F17: Complete Sections 4A and 4B | I17: Effective Date
C18: Promotion / Merit / Annual Inc. | F18: Complete Sections 4A and 4B | I18: Effective Date
C19: Transfer | F19: Complete Sections 4A and 4B | I19: Effective Date
C20: Release Time (Projects Only) | F20: Complete Sections 4A and 4B | I20: Effective Date
C21: Separation | F21: Complete Section 4B | I21: Date Last Worked
C22: Other (specify): | I22: Effective Date
B23: POSITION DATA
N24: Adjunct Faculty (select for NEW Adjunct Faculty, RECENTLY RETIRED, or to RENEW former members if there has been more than 1 year break in service, otherwise include on Overload or Summer Assignment Action Form)
B25: 3 | C25: A. Position Type: | F25: Staff | I25: Faculty
C28: B. Rank, if Faculty: | F28: Instructor | I28: Assistant Professor | N28: Associate Professor | R28: Professor | T28: OR | V28: NON FACULTY
C31: C. Pay Type: | F31: 9 Months | I31: 10 Months | N31: 11 Months | R31: 12 Months | V31: Other
C34: D. Pay Frequency: | F34: Monthly | I34: Bi Weekly | N34: One Time Pay at END of the: Semester/Summer Session/Assignment
C37: E. Job Status: | F37: Full Time | H37: 2 | I37: Part-time - FTE for part-time: | L37: =Sheet1!J1 -> 0 | N37: =VLOOKUP(L37,Sheet1!K1:L1,2,FALSE) -> #N/A
C40: F. Assignment: | F40: Regular | I40: Regular (Temporary Funding Source)-End Date: | R40: Temp Employment - End Date:
C43: G. Retiree of PERS of MS? | F43: No | I43: Yes - Retirement Date:
C46: H. Total Salary: | E46: Per Year | H46: Per Hour | L46: Per Other
C49: I. HOME ORGANIZATION (or HOME DEPARTMENT): If this is a Restricted Project, Indicate a Department from the E&G printed budget's Table of Contents that most closely
C50: relates to the project, or indicate the department to which the employee's check should be distributed.
D51: Home Organization Code: | G51: =VLOOKUP(E51,Sheet1!I153:J414,2,FALSE) -> #N/A | V51: 0 | W51: 0
C53: RECEIVING DEPARTMENT
B54: 4A | C54: POSITIONS CONTAINING E&G FUNDS: assign a position from the printed budget. If the position is temporary, an applicable pooled position number may be assigned.
C55: 100% RESTRICTED FUNDS: the position number will be assigned by a Grants & Contracts Accountant
B56: To | C56: Position Number | G56: Position Title
C58: Source of Funding (RECEIVING DEPARTMENT)
C59: E&G Budget Line # | D59: Budget Page # | F59: Fund Code | H59: Organization Code | J59: *Account Code | M59: Budget / Grant Name | S59: **Percentage of Funds | U59: Salary Amount Per Account
M60: =VLOOKUP(H60,Sheet1!I$54:J$289,2,FALSE) -> #N/A | S60: =SUM(U60/U$67) -> #DIV/0!
M61: =VLOOKUP(H61,Sheet1!I$54:J$289,2,FALSE) -> #N/A | S61: =SUM(U61/U$67) -> #DIV/0!
M62: =VLOOKUP(H62,Sheet1!I$54:J$289,2,FALSE) -> #N/A | S62: =SUM(U62/U$67) -> #DIV/0!
M63: =VLOOKUP(H63,Sheet1!I$54:J$289,2,FALSE) -> #N/A | S63: =SUM(U63/U$67) -> #DIV/0!
M64: =VLOOKUP(H64,Sheet1!I$54:J$289,2,FALSE) -> #N/A | S64: =SUM(U64/U$67) -> #DIV/0!
M65: =VLOOKUP(H65,Sheet1!I$54:J$289,2,FALSE) -> #N/A | S65: =SUM(U65/U$67) -> #DIV/0!
C67: *Account Code: Indicate 611000 for instructional compensation allotment, 612000 for all other monthly compensation, 622000 for biweekly compensation | Q67: TOTAL | S67: =SUM(S60:T65) -> #DIV/0! | U67: =SUM(U60:V65) -> 0
T68: **Percentage of funds: to be carried 2 decimal places. Do not round
C70: RELEASING DEPARTMENT
B71: 4B | C71: Position Number | G71: Position Title
B73: From | C73: Source of Funding (RELEASING DEPARTMENT)
C74: E&G Budget Line # | D74: Budget Page # | F74: Fund Code | H74: Organization Code | J74: Account Code | M74: Budget / Grant Name | S74: **Percentage of Funds | U74: Salary Amount Per Account
M75: =VLOOKUP(H75,Sheet1!I$54:J$289,2,FALSE) -> #N/A | S75: =SUM(U75/U$82) -> #DIV/0!
M76: =VLOOKUP(H76,Sheet1!I$54:J$289,2,FALSE) -> #N/A | S76: =SUM(U76/U$82) -> #DIV/0!
M77: =VLOOKUP(H77,Sheet1!I$54:J$289,2,FALSE) -> #N/A | S77: =SUM(U77/U$82) -> #DIV/0!
M78: =VLOOKUP(H78,Sheet1!I$54:J$289,2,FALSE) -> #N/A | S78: =SUM(U78/U$82) -> #DIV/0!
M79: =VLOOKUP(H79,Sheet1!I$54:J$289,2,FALSE) -> #N/A | S79: =SUM(U79/U$82) -> #DIV/0!
M80: =VLOOKUP(H80,Sheet1!I$54:J$289,2,FALSE) -> #N/A | S80: =SUM(U80/U$82) -> #DIV/0!
Q82: TOTAL | S82: =SUM(S75:T80) -> #DIV/0! | U82: =SUM(U75:V80) -> 0
B84: APPROVALS
B85: 5 | C85: Funds Approval
E86: Grants and Contracts | M86: Budget Office
C87: *I UNDERSTAND THAT NO INDIVIDUAL SHALL BE ALLOWED TO START A WORK ASSIGNMENT WITHOUT PRIOR AUTHORIZATION OF HUMAN RESOURCES*
C88: Approvals Required for Section 4A (RECEIVING DEPARTMENT) | L88: Approvals Required for Section 4B (RELEASING DEPARTMENT)
C89: Budgetary Authority: | J89: Date | L89: Budgetary Authority: | V89: Date
C90: Dean or Administrative Head: | J90: Date | L90: Dean or Administrative Head: | V90: Date
C91: Area Vice President: | J91: Date | L91: Area Vice President: | V91: Date
C92: President (if applicable): | J92: Date | L92: President (if applicable): | V92: Date
B93: Approvals Required for Original Appointment/Re-Employed Only | L93: Signature (Original Appointments & Re-Employed Only)
C94: Dir. of Human Resources | J94: Date | L94: Employee | V94: Date
B95: Human Resources or Payroll Use Only
C96: Is Position Exempt under FLSA? | F96: Yes | G96: No | H96: Effective Date of Hire: | L96: Date | P96: Date to HR | S96: Date
C97: EEOC CODE: | F97: EClass: | H97: Payroll Review: | L97: Date | P97: Banner Entry Date | S97: Date

Sheet PAF (2)
B1: ALCORN STATE UNIVERSITY
B2: PERSONNEL ACTION FORM
B5: To avoid processing delays, please ensure all applicable sections are complete and accurate.
B7: PERSONAL DATA
B8: 1 | C8: Last Name | F8: Suffix | G8: First Name | K8: Middle | P8: Prefix | Q8: SSN / ID | U8: Current Date
C10: Current Date | E10: SSN | H10: Date of Birth | M10: Home Phone #
C12: Street Address | G12: City | K12: County | M12: State | W12: Zip Code
C14: TYPE OF ACTION | I14: ACTION DATES | N14: COMMENTS
B15: 2 | C15: Original Appointment | F15: Complete Section 4A | I15: Effective date provided by HR | N15: Use the section below for further explanation
C16: Re-Employed (break in employment) | F16: Complete Section 4A | I16: Effective date provided by HR
C17: Extension of Employment (no break) | F17: Complete Sections 4A and 4B | I17: Effective Date
C18: Promotion / Merit / Annual Inc. | F18: Complete Sections 4A and 4B | I18: Effective Date
C19: Transfer | F19: Complete Sections 4A and 4B | I19: Effective Date
C20: Release Time (Projects Only) | F20: Complete Sections 4A and 4B | I20: Effective Date
C21: Separation | F21: Complete Section 4B | I21: Date Last Worked
C22: Other (specify): | I22: Effective Date
B23: POSITION DATA
N24: Adjunct Faculty (select for NEW Adjunct Faculty, RECENTLY RETIRED, or to RENEW former members if there has been more than 1 year break in service, otherwise include on Overload or Summer Assignment Action Form)
B25: 3 | C25: A. Position Type: | F25: Staff | I25: Faculty
C28: B. Rank, if Faculty: | F28: Instructor | I28: Assistant Professor | N28: Associate Professor | R28: Professor | T28: OR | V28: NON FACULTY
C31: C. Pay Type: | F31: 9 Months | I31: 10 Months | N31: 11 Months | R31: 12 Months | V31: Other
C34: D. Pay Frequency: | F34: Monthly | I34: Bi Weekly | N34: One Time Pay at END of the: Semester/Summer Session/Assignment
C37: E. Job Status: | F37: Full Time | H37: 2 | I37: Part-time - FTE for part-time: | L37: =Sheet1!J1 -> 0 | N37: =VLOOKUP(L37,Sheet1!K1:L1,2,FALSE) -> #N/A
C40: F. Assignment: | F40: Regular | I40: Regular (Temporary Funding Source)-End Date: | R40: Temp Employment - End Date:
C43: G. Retiree of PERS of MS? | F43: No | I43: Yes - Retirement Date:
C46: H. Total Salary: | E46: Per Year | H46: Per Hour | L46: Per Other
C49: I. HOME ORGANIZATION (or HOME DEPARTMENT): If this is a Restricted Project, Indicate a Department from the E&G printed budget's Table of Contents that most closely
C50: relates to the project, or indicate the department to which the employee's check should be distributed.
D51: Home Organization Code: | G51: =VLOOKUP(E51,Sheet1!I153:J414,2,FALSE) -> #N/A | V51: 0 | W51: 0
C53: RECEIVING DEPARTMENT
B54: 4A | C54: POSITIONS CONTAINING E&G FUNDS: assign a position from the printed budget. If the position is temporary, an applicable pooled position number may be assigned.
C55: 100% RESTRICTED FUNDS: the position number will be assigned by a Grants & Contracts Accountant
B56: To | C56: Position Number | G56: Position Title
C58: Source of Funding (RECEIVING DEPARTMENT)
C59: E&G Budget Line # | D59: Budget Page # | F59: Fund Code | H59: Organization Code | J59: *Account Code | M59: Budget / Grant Name | S59: **Percentage of Funds | U59: Salary Amount Per Account
M60: =VLOOKUP(H60,Sheet1!I$54:J$289,2,FALSE) -> #N/A | S60: =SUM(U60/U$67) -> #DIV/0!
M61: =VLOOKUP(H61,Sheet1!I$54:J$289,2,FALSE) -> #N/A | S61: =SUM(U61/U$67) -> #DIV/0!
M62: =VLOOKUP(H62,Sheet1!I$54:J$289,2,FALSE) -> #N/A | S62: =SUM(U62/U$67) -> #DIV/0!
M63: =VLOOKUP(H63,Sheet1!I$54:J$289,2,FALSE) -> #N/A | S63: =SUM(U63/U$67) -> #DIV/0!
M64: =VLOOKUP(H64,Sheet1!I$54:J$289,2,FALSE) -> #N/A | S64: =SUM(U64/U$67) -> #DIV/0!
M65: =VLOOKUP(H65,Sheet1!I$54:J$289,2,FALSE) -> #N/A | S65: =SUM(U65/U$67) -> #DIV/0!
C67: *Account Code: Indicate 611000 for instructional compensation allotment, 612000 for all other monthly compensation, 622000 for biweekly compensation | Q67: TOTAL | S67: =SUM(S60:T65) -> #DIV/0! | U67: =SUM(U60:V65) -> 0
T68: **Percentage of funds: to be carried 2 decimal places. Do not round
C70: RELEASING DEPARTMENT
B71: 4B | C71: Position Number | G71: Position Title
B73: From | C73: Source of Funding (RELEASING DEPARTMENT)
C74: E&G Budget Line # | D74: Budget Page # | F74: Fund Code | H74: Organization Code | J74: Account Code | M74: Budget / Grant Name | S74: **Percentage of Funds | U74: Salary Amount Per Account
M75: =VLOOKUP(H75,Sheet1!I$54:J$289,2,FALSE) -> #N/A | S75: =SUM(U75/U$82) -> #DIV/0!
M76: =VLOOKUP(H76,Sheet1!I$54:J$289,2,FALSE) -> #N/A | S76: =SUM(U76/U$82) -> #DIV/0!
M77: =VLOOKUP(H77,Sheet1!I$54:J$289,2,FALSE) -> #N/A | S77: =SUM(U77/U$82) -> #DIV/0!
M78: =VLOOKUP(H78,Sheet1!I$54:J$289,2,FALSE) -> #N/A | S78: =SUM(U78/U$82) -> #DIV/0!
M79: =VLOOKUP(H79,Sheet1!I$54:J$289,2,FALSE) -> #N/A | S79: =SUM(U79/U$82) -> #DIV/0!
M80: =VLOOKUP(H80,Sheet1!I$54:J$289,2,FALSE) -> #N/A | S80: =SUM(U80/U$82) -> #DIV/0!
Q82: TOTAL | S82: =SUM(S75:T80) -> #DIV/0! | U82: =SUM(U75:V80) -> 0
B84: APPROVALS
B85: 5 | C85: Funds Approval
E86: Grants and Contracts | M86: Budget Office
C87: *I UNDERSTAND THAT NO INDIVIDUAL SHALL BE ALLOWED TO START A WORK ASSIGNMENT WITHOUT PRIOR AUTHORIZATION OF HUMAN RESOURCES*
C88: Approvals Required for Section 4A (RECEIVING DEPARTMENT) | L88: Approvals Required for Section 4B (RELEASING DEPARTMENT)
C89: Budgetary Authority: | J89: Date | L89: Budgetary Authority: | V89: Date
C90: Dean or Administrative Head: | J90: Date | L90: Dean or Administrative Head: | V90: Date
C91: Area Vice President: | J91: Date | L91: Area Vice President: | V91: Date
C92: President (if applicable): | J92: Date | L92: President (if applicable): | V92: Date
B93: Approvals Required for Original Appointment/Re-Employed Only | L93: Signature (Original Appointments & Re-Employed Only)
C94: Dir. of Human Resources | J94: Date | L94: Employee | V94: Date
B95: Human Resources or Payroll Use Only
C96: Is Position Exempt under FLSA? | F96: Yes | G96: No | H96: Effective Date of Hire: | L96: Date | P96: Date to HR | S96: Date
C97: EEOC CODE: | F97: EClass: | H97: Payroll Review: | L97: Date | P97: Banner Entry Date | S97: Date

Sheet PAF (3)
B1: ALCORN STATE UNIVERSITY
B2: PERSONNEL ACTION FORM
B5: To avoid processing delays, please ensure all applicable sections are complete and accurate.
B7: PERSONAL DATA
B8: 1 | C8: Last Name | F8: Suffix | G8: First Name | K8: Middle | P8: Prefix | Q8: SSN / ID | U8: Current Date
C10: Current Date | E10: SSN | H10: Date of Birth | M10: Home Phone #
C12: Street Address | G12: City | K12: County | M12: State | W12: Zip Code
C14: TYPE OF ACTION | I14: ACTION DATES | N14: COMMENTS
B15: 2 | C15: Original Appointment | F15: Complete Section 4A | I15: Effective date provided by HR | N15: Use the section below for further explanation
C16: Re-Employed (break in employment) | F16: Complete Section 4A | I16: Effective date provided by HR
C17: Extension of Employment (no break) | F17: Complete Sections 4A and 4B | I17: Effective Date
C18: Promotion / Merit / Annual Inc. | F18: Complete Sections 4A and 4B | I18: Effective Date
C19: Transfer | F19: Complete Sections 4A and 4B | I19: Effective Date
C20: Release Time (Projects Only) | F20: Complete Sections 4A and 4B | I20: Effective Date
C21: Separation | F21: Complete Section 4B | I21: Date Last Worked
C22: Other (specify): | I22: Effective Date
B23: POSITION DATA
N24: Adjunct Faculty (select for NEW Adjunct Faculty, RECENTLY RETIRED, or to RENEW former members if there has been more than 1 year break in service, otherwise include on Overload or Summer Assignment Action Form)
B25: 3 | C25: A. Position Type: | F25: Staff | I25: Faculty
C28: B. Rank, if Faculty: | F28: Instructor | I28: Assistant Professor | N28: Associate Professor | R28: Professor | T28: OR | V28: NON FACULTY
C31: C. Pay Type: | F31: 9 Months | I31: 10 Months | N31: 11 Months | R31: 12 Months | V31: Other
C34: D. Pay Frequency: | F34: Monthly | I34: Bi Weekly | N34: One Time Pay at END of the: Semester/Summer Session/Assignment
C37: E. Job Status: | F37: Full Time | H37: 2 | I37: Part-time - FTE for part-time: | L37: =Sheet1!J1 -> 0 | N37: =VLOOKUP(L37,Sheet1!K1:L1,2,FALSE) -> #N/A
C40: F. Assignment: | F40: Regular | I40: Regular (Temporary Funding Source)-End Date: | R40: Temp Employment - End Date:
C43: G. Retiree of PERS of MS? | F43: No | I43: Yes - Retirement Date:
C46: H. Total Salary: | E46: Per Year | H46: Per Hour | L46: Per Other
C49: I. HOME ORGANIZATION (or HOME DEPARTMENT): If this is a Restricted Project, Indicate a Department from the E&G printed budget's Table of Contents that most closely
C50: relates to the project, or indicate the department to which the employee's check should be distributed.
D51: Home Organization Code: | G51: =VLOOKUP(E51,Sheet1!I153:J414,2,FALSE) -> #N/A | V51: 0 | W51: 0
C53: RECEIVING DEPARTMENT
B54: 4A | C54: POSITIONS CONTAINING E&G FUNDS: assign a position from the printed budget. If the position is temporary, an applicable pooled position number may be assigned.
C55: 100% RESTRICTED FUNDS: the position number will be assigned by a Grants & Contracts Accountant
B56: To | C56: Position Number | G56: Position Title
C58: Source of Funding (RECEIVING DEPARTMENT)
C59: E&G Budget Line # | D59: Budget Page # | F59: Fund Code | H59: Organization Code | J59: *Account Code | M59: Budget / Grant Name | S59: **Percentage of Funds | U59: Salary Amount Per Account
M60: =VLOOKUP(H60,Sheet1!I$54:J$289,2,FALSE) -> #N/A | S60: =SUM(U60/U$67) -> #DIV/0!
M61: =VLOOKUP(H61,Sheet1!I$54:J$289,2,FALSE) -> #N/A | S61: =SUM(U61/U$67) -> #DIV/0!
M62: =VLOOKUP(H62,Sheet1!I$54:J$289,2,FALSE) -> #N/A | S62: =SUM(U62/U$67) -> #DIV/0!
M63: =VLOOKUP(H63,Sheet1!I$54:J$289,2,FALSE) -> #N/A | S63: =SUM(U63/U$67) -> #DIV/0!
M64: =VLOOKUP(H64,Sheet1!I$54:J$289,2,FALSE) -> #N/A | S64: =SUM(U64/U$67) -> #DIV/0!
M65: =VLOOKUP(H65,Sheet1!I$54:J$289,2,FALSE) -> #N/A | S65: =SUM(U65/U$67) -> #DIV/0!
C67: *Account Code: Indicate 611000 for instructional compensation allotment, 612000 for all other monthly compensation, 622000 for biweekly compensation | Q67: TOTAL | S67: =SUM(S60:T65) -> #DIV/0! | U67: =SUM(U60:V65) -> 0
T68: **Percentage of funds: to be carried 2 decimal places. Do not round
C70: RELEASING DEPARTMENT
B71: 4B | C71: Position Number | G71: Position Title
B73: From | C73: Source of Funding (RELEASING DEPARTMENT)
C74: E&G Budget Line # | D74: Budget Page # | F74: Fund Code | H74: Organization Code | J74: Account Code | M74: Budget / Grant Name | S74: **Percentage of Funds | U74: Salary Amount Per Account
M75: =VLOOKUP(H75,Sheet1!I$54:J$289,2,FALSE) -> #N/A | S75: =SUM(U75/U$82) -> #DIV/0!
M76: =VLOOKUP(H76,Sheet1!I$54:J$289,2,FALSE) -> #N/A | S76: =SUM(U76/U$82) -> #DIV/0!
M77: =VLOOKUP(H77,Sheet1!I$54:J$289,2,FALSE) -> #N/A | S77: =SUM(U77/U$82) -> #DIV/0!
M78: =VLOOKUP(H78,Sheet1!I$54:J$289,2,FALSE) -> #N/A | S78: =SUM(U78/U$82) -> #DIV/0!
M79: =VLOOKUP(H79,Sheet1!I$54:J$289,2,FALSE) -> #N/A | S79: =SUM(U79/U$82) -> #DIV/0!
M80: =VLOOKUP(H80,Sheet1!I$54:J$289,2,FALSE) -> #N/A | S80: =SUM(U80/U$82) -> #DIV/0!
Q82: TOTAL | S82: =SUM(S75:T80) -> #DIV/0! | U82: =SUM(U75:V80) -> 0
B84: APPROVALS
B85: 5 | C85: Funds Approval
E86: Grants and Contracts | M86: Budget Office
C87: *I UNDERSTAND THAT NO INDIVIDUAL SHALL BE ALLOWED TO START A WORK ASSIGNMENT WITHOUT PRIOR AUTHORIZATION OF HUMAN RESOURCES*
C88: Approvals Required for Section 4A (RECEIVING DEPARTMENT) | L88: Approvals Required for Section 4B (RELEASING DEPARTMENT)
C89: Budgetary Authority: | J89: Date | L89: Budgetary Authority: | V89: Date
C90: Dean or Administrative Head: | J90: Date | L90: Dean or Administrative Head: | V90: Date
C91: Area Vice President: | J91: Date | L91: Area Vice President: | V91: Date
C92: President (if applicable): | J92: Date | L92: President (if applicable): | V92: Date
B93: Approvals Required for Original Appointment/Re-Employed Only | L93: Signature (Original Appointments & Re-Employed Only)
C94: Dir. of Human Resources | J94: Date | L94: Employee | V94: Date
B95: Human Resources or Payroll Use Only
C96: Is Position Exempt under FLSA? | F96: Yes | G96: No | H96: Effective Date of Hire: | L96: Date | P96: Date to HR | S96: Date
C97: EEOC CODE: | F97: EClass: | H97: Payroll Review: | L97: Date | P97: Banner Entry Date | S97: Date

Sheet PAF (4)
B1: ALCORN STATE UNIVERSITY
B2: PERSONNEL ACTION FORM
B5: To avoid processing delays, please ensure all applicable sections are complete and accurate.
B7: PERSONAL DATA
B8: 1 | C8: Last Name | F8: Suffix | G8: First Name | K8: Middle | P8: Prefix | Q8: SSN / ID | U8: Current Date
C10: Current Date | E10: SSN | H10: Date of Birth | M10: Home Phone #
C12: Street Address | G12: City | K12: County | M12: State | W12: Zip Code
C14: TYPE OF ACTION | I14: ACTION DATES | N14: COMMENTS
B15: 2 | C15: Original Appointment | F15: Complete Section 4A | I15: Effective date provided by HR | N15: Use the section below for further explanation
C16: Re-Employed (break in employment) | F16: Complete Section 4A | I16: Effective date provided by HR
C17: Extension of Employment (no break) | F17: Complete Sections 4A and 4B | I17: Effective Date
C18: Promotion / Merit / Annual Inc. | F18: Complete Sections 4A and 4B | I18: Effective Date
C19: Transfer | F19: Complete Sections 4A and 4B | I19: Effective Date
C20: Release Time (Projects Only) | F20: Complete Sections 4A and 4B | I20: Effective Date
C21: Separation | F21: Complete Section 4B | I21: Date Last Worked
C22: Other (specify): | I22: Effective Date
B23: POSITION DATA
N24: Adjunct Faculty (select for NEW Adjunct Faculty, RECENTLY RETIRED, or to RENEW former members if there has been more than 1 year break in service, otherwise include on Overload or Summer Assignment Action Form)
B25: 3 | C25: A. Position Type: | F25: Staff | I25: Faculty
C28: B. Rank, if Faculty: | F28: Instructor | I28: Assistant Professor | N28: Associate Professor | R28: Professor | T28: OR | V28: NON FACULTY
C31: C. Pay Type: | F31: 9 Months | I31: 10 Months | N31: 11 Months | R31: 12 Months | V31: Other
C34: D. Pay Frequency: | F34: Monthly | I34: Bi Weekly | N34: One Time Pay at END of the: Semester/Summer Session/Assignment
C37: E. Job Status: | F37: Full Time | H37: 2 | I37: Part-time - FTE for part-time: | L37: =Sheet1!J1 -> 0 | N37: =VLOOKUP(L37,Sheet1!K1:L1,2,FALSE) -> #N/A
C40: F. Assignment: | F40: Regular | I40: Regular (Temporary Funding Source)-End Date: | R40: Temp Employment - End Date:
C43: G. Retiree of PERS of MS? | F43: No | I43: Yes - Retirement Date:
C46: H. Total Salary: | E46: Per Year | H46: Per Hour | L46: Per Other
C49: I. HOME ORGANIZATION (or HOME DEPARTMENT): If this is a Restricted Project, Indicate a Department from the E&G printed budget's Table of Contents that most closely
C50: relates to the project, or indicate the department to which the employee's check should be distributed.
D51: Home Organization Code: | G51: =VLOOKUP(E51,Sheet1!I153:J414,2,FALSE) -> #N/A | V51: 0 | W51: 0
C53: RECEIVING DEPARTMENT
B54: 4A | C54: POSITIONS CONTAINING E&G FUNDS: assign a position from the printed budget. If the position is temporary, an applicable pooled position number may be assigned.
C55: 100% RESTRICTED FUNDS: the position number will be assigned by a Grants & Contracts Accountant
B56: To | C56: Position Number | G56: Position Title
C58: Source of Funding (RECEIVING DEPARTMENT)
C59: E&G Budget Line # | D59: Budget Page # | F59: Fund Code | H59: Organization Code | J59: *Account Code | M59: Budget / Grant Name | S59: **Percentage of Funds | U59: Salary Amount Per Account
M60: =VLOOKUP(H60,Sheet1!I$54:J$289,2,FALSE) -> #N/A | S60: =SUM(U60/U$67) -> #DIV/0!
M61: =VLOOKUP(H61,Sheet1!I$54:J$289,2,FALSE) -> #N/A | S61: =SUM(U61/U$67) -> #DIV/0!
M62: =VLOOKUP(H62,Sheet1!I$54:J$289,2,FALSE) -> #N/A | S62: =SUM(U62/U$67) -> #DIV/0!
M63: =VLOOKUP(H63,Sheet1!I$54:J$289,2,FALSE) -> #N/A | S63: =SUM(U63/U$67) -> #DIV/0!
M64: =VLOOKUP(H64,Sheet1!I$54:J$289,2,FALSE) -> #N/A | S64: =SUM(U64/U$67) -> #DIV/0!
M65: =VLOOKUP(H65,Sheet1!I$54:J$289,2,FALSE) -> #N/A | S65: =SUM(U65/U$67) -> #DIV/0!
C67: *Account Code: Indicate 611000 for instructional compensation allotment, 612000 for all other monthly compensation, 622000 for biweekly compensation | Q67: TOTAL | S67: =SUM(S60:T65) -> #DIV/0! | U67: =SUM(U60:V65) -> 0
T68: **Percentage of funds: to be carried 2 decimal places. Do not round
C70: RELEASING DEPARTMENT
B71: 4B | C71: Position Number | G71: Position Title
B73: From | C73: Source of Funding (RELEASING DEPARTMENT)
C74: E&G Budget Line # | D74: Budget Page # | F74: Fund Code | H74: Organization Code | J74: Account Code | M74: Budget / Grant Name | S74: **Percentage of Funds | U74: Salary Amount Per Account
M75: =VLOOKUP(H75,Sheet1!I$54:J$289,2,FALSE) -> #N/A | S75: =SUM(U75/U$82) -> #DIV/0!
M76: =VLOOKUP(H76,Sheet1!I$54:J$289,2,FALSE) -> #N/A | S76: =SUM(U76/U$82) -> #DIV/0!
M77: =VLOOKUP(H77,Sheet1!I$54:J$289,2,FALSE) -> #N/A | S77: =SUM(U77/U$82) -> #DIV/0!
M78: =VLOOKUP(H78,Sheet1!I$54:J$289,2,FALSE) -> #N/A | S78: =SUM(U78/U$82) -> #DIV/0!
M79: =VLOOKUP(H79,Sheet1!I$54:J$289,2,FALSE) -> #N/A | S79: =SUM(U79/U$82) -> #DIV/0!
M80: =VLOOKUP(H80,Sheet1!I$54:J$289,2,FALSE) -> #N/A | S80: =SUM(U80/U$82) -> #DIV/0!
Q82: TOTAL | S82: =SUM(S75:T80) -> #DIV/0! | U82: =SUM(U75:V80) -> 0
B84: APPROVALS
B85: 5 | C85: Funds Approval
E86: Grants and Contracts | M86: Budget Office
C87: *I UNDERSTAND THAT NO INDIVIDUAL SHALL BE ALLOWED TO START A WORK ASSIGNMENT WITHOUT PRIOR AUTHORIZATION OF HUMAN RESOURCES*
C88: Approvals Required for Section 4A (RECEIVING DEPARTMENT) | L88: Approvals Required for Section 4B (RELEASING DEPARTMENT)
C89: Budgetary Authority: | J89: Date | L89: Budgetary Authority: | V89: Date
C90: Dean or Administrative Head: | J90: Date | L90: Dean or Administrative Head: | V90: Date
C91: Area Vice President: | J91: Date | L91: Area Vice President: | V91: Date
C92: President (if applicable): | J92: Date | L92: President (if applicable): | V92: Date
B93: Approvals Required for Original Appointment/Re-Employed Only | L93: Signature (Original Appointments & Re-Employed Only)
C94: Dir. of Human Resources | J94: Date | L94: Employee | V94: Date
B95: Human Resources or Payroll Use Only
C96: Is Position Exempt under FLSA? | F96: Yes | G96: No | H96: Effective Date of Hire: | L96: Date | P96: Date to HR | S96: Date
C97: EEOC CODE: | F97: EClass: | H97: Payroll Review: | L97: Date | P97: Banner Entry Date | S97: Date

Sheet PAF (5)
B1: ALCORN STATE UNIVERSITY
B2: PERSONNEL ACTION FORM
B5: To avoid processing delays, please ensure all applicable sections are complete and accurate.
B7: PERSONAL DATA
B8: 1 | C8: Last Name | F8: Suffix | G8: First Name | K8: Middle | P8: Prefix | Q8: SSN / ID | U8: Current Date
C10: Current Date | E10: SSN | H10: Date of Birth | M10: Home Phone #
C12: Street Address | G12: City | K12: County | M12: State | W12: Zip Code
C14: TYPE OF ACTION | I14: ACTION DATES | N14: COMMENTS
B15: 2 | C15: Original Appointment | F15: Complete Section 4A | I15: Effective date provided by HR | N15: Use the section below for further explanation
C16: Re-Employed (break in employment) | F16: Complete Section 4A | I16: Effective date provided by HR
C17: Extension of Employment (no break) | F17: Complete Sections 4A and 4B | I17: Effective Date
C18: Promotion / Merit / Annual Inc. | F18: Complete Sections 4A and 4B | I18: Effective Date
C19: Transfer | F19: Complete Sections 4A and 4B | I19: Effective Date
C20: Release Time (Projects Only) | F20: Complete Sections 4A and 4B | I20: Effective Date
C21: Separation | F21: Complete Section 4B | I21: Date Last Worked
C22: Other (specify): | I22: Effective Date
B23: POSITION DATA
N24: Adjunct Faculty (select for NEW Adjunct Faculty, RECENTLY RETIRED, or to RENEW former members if there has been more than 1 year break in service, otherwise include on Overload or Summer Assignment Action Form)
B25: 3 | C25: A. Position Type: | F25: Staff | I25: Faculty
C28: B. Rank, if Faculty: | F28: Instructor | I28: Assistant Professor | N28: Associate Professor | R28: Professor | T28: OR | V28: NON FACULTY
C31: C. Pay Type: | F31: 9 Months | I31: 10 Months | N31: 11 Months | R31: 12 Months | V31: Other
C34: D. Pay Frequency: | F34: Monthly | I34: Bi Weekly | N34: One Time Pay at END of the: Semester/Summer Session/Assignment
C37: E. Job Status: | F37: Full Time | H37: 2 | I37: Part-time - FTE for part-time: | L37: =Sheet1!J1 -> 0 | N37: =VLOOKUP(L37,Sheet1!K1:L1,2,FALSE) -> #N/A
C40: F. Assignment: | F40: Regular | I40: Regular (Temporary Funding Source)-End Date: | R40: Temp Employment - End Date:
C43: G. Retiree of PERS of MS? | F43: No | I43: Yes - Retirement Date:
C46: H. Total Salary: | E46: Per Year | H46: Per Hour | L46: Per Other
C49: I. HOME ORGANIZATION (or HOME DEPARTMENT): If this is a Restricted Project, Indicate a Department from the E&G printed budget's Table of Contents that most closely
C50: relates to the project, or indicate the department to which the employee's check should be distributed.
D51: Home Organization Code: | G51: =VLOOKUP(E51,Sheet1!I153:J414,2,FALSE) -> #N/A | V51: 0 | W51: 0
C53: RECEIVING DEPARTMENT
B54: 4A | C54: POSITIONS CONTAINING E&G FUNDS: assign a position from the printed budget. If the position is temporary, an applicable pooled position number may be assigned.
C55: 100% RESTRICTED FUNDS: the position number will be assigned by a Grants & Contracts Accountant
B56: To | C56: Position Number | G56: Position Title
C58: Source of Funding (RECEIVING DEPARTMENT)
C59: E&G Budget Line # | D59: Budget Page # | F59: Fund Code | H59: Organization Code | J59: *Account Code | M59: Budget / Grant Name | S59: **Percentage of Funds | U59: Salary Amount Per Account
M60: =VLOOKUP(H60,Sheet1!I$54:J$289,2,FALSE) -> #N/A | S60: =SUM(U60/U$67) -> #DIV/0!
M61: =VLOOKUP(H61,Sheet1!I$54:J$289,2,FALSE) -> #N/A | S61: =SUM(U61/U$67) -> #DIV/0!
M62: =VLOOKUP(H62,Sheet1!I$54:J$289,2,FALSE) -> #N/A | S62: =SUM(U62/U$67) -> #DIV/0!
M63: =VLOOKUP(H63,Sheet1!I$54:J$289,2,FALSE) -> #N/A | S63: =SUM(U63/U$67) -> #DIV/0!
M64: =VLOOKUP(H64,Sheet1!I$54:J$289,2,FALSE) -> #N/A | S64: =SUM(U64/U$67) -> #DIV/0!
M65: =VLOOKUP(H65,Sheet1!I$54:J$289,2,FALSE) -> #N/A | S65: =SUM(U65/U$67) -> #DIV/0!
C67: *Account Code: Indicate 611000 for instructional compensation allotment, 612000 for all other monthly compensation, 622000 for biweekly compensation | Q67: TOTAL | S67: =SUM(S60:T65) -> #DIV/0! | U67: =SUM(U60:V65) -> 0
T68: **Percentage of funds: to be carried 2 decimal places. Do not round
C70: RELEASING DEPARTMENT
B71: 4B | C71: Position Number | G71: Position Title
B73: From | C73: Source of Funding (RELEASING DEPARTMENT)
C74: E&G Budget Line # | D74: Budget Page # | F74: Fund Code | H74: Organization Code | J74: Account Code | M74: Budget / Grant Name | S74: **Percentage of Funds | U74: Salary Amount Per Account
M75: =VLOOKUP(H75,Sheet1!I$54:J$289,2,FALSE) -> #N/A | S75: =SUM(U75/U$82) -> #DIV/0!
M76: =VLOOKUP(H76,Sheet1!I$54:J$289,2,FALSE) -> #N/A | S76: =SUM(U76/U$82) -> #DIV/0!
M77: =VLOOKUP(H77,Sheet1!I$54:J$289,2,FALSE) -> #N/A | S77: =SUM(U77/U$82) -> #DIV/0!
M78: =VLOOKUP(H78,Sheet1!I$54:J$289,2,FALSE) -> #N/A | S78: =SUM(U78/U$82) -> #DIV/0!
M79: =VLOOKUP(H79,Sheet1!I$54:J$289,2,FALSE) -> #N/A | S79: =SUM(U79/U$82) -> #DIV/0!
M80: =VLOOKUP(H80,Sheet1!I$54:J$289,2,FALSE) -> #N/A | S80: =SUM(U80/U$82) -> #DIV/0!
Q82: TOTAL | S82: =SUM(S75:T80) -> #DIV/0! | U82: =SUM(U75:V80) -> 0
B84: APPROVALS
B85: 5 | C85: Funds Approval
E86: Grants and Contracts | M86: Budget Office
C87: *I UNDERSTAND THAT NO INDIVIDUAL SHALL BE ALLOWED TO START A WORK ASSIGNMENT WITHOUT PRIOR AUTHORIZATION OF HUMAN RESOURCES*
C88: Approvals Required for Section 4A (RECEIVING DEPARTMENT) | L88: Approvals Required for Section 4B (RELEASING DEPARTMENT)
C89: Budgetary Authority: | J89: Date | L89: Budgetary Authority: | V89: Date
C90: Dean or Administrative Head: | J90: Date | L90: Dean or Administrative Head: | V90: Date
C91: Area Vice President: | J91: Date | L91: Area Vice President: | V91: Date
C92: President (if applicable): | J92: Date | L92: President (if applicable): | V92: Date
B93: Approvals Required for Original Appointment/Re-Employed Only | L93: Signature (Original Appointments & Re-Employed Only)
C94: Dir. of Human Resources | J94: Date | L94: Employee | V94: Date
B95: Human Resources or Payroll Use Only
C96: Is Position Exempt under FLSA? | F96: Yes | G96: No | H96: Effective Date of Hire: | L96: Date | P96: Date to HR | S96: Date
C97: EEOC CODE: | F97: EClass: | H97: Payroll Review: | L97: Date | P97: Banner Entry Date | S97: Date

Sheet Worksheet.Per Other
B1: ALCORN STATE UNIVERSITY
B2: Worksheet for Calculating a 'Per Other' Amount
A6: 1 | C6: ANNUAL SALARY: What is the total ANNUAL SALARY base?
A8: 2 | C8: ANNUAL MONTHS: What is the total ANNUAL NUMBER OF MONTHS for the position.
C9: * | D9: 9 for 9 month faculty
C10: * | D10: 10 for 10 month faculty
C11: * | D11: 11 for 11 month faculty
C12: * | D12: 12 for 12 month faculty, staff, and biweekly staff
A13: 3 | C13: FULL MONTHS TO BE WORKED: How many FULL MONTHS will actually be worked by the employee?
A15: 4 | C15: WORKING DAYS (beginning month): How many WORKING DAYS are in the partial beginning month? (Count the number of weekdays
C16: in the month by including holidays and excluding Saturday and Sunday.)
A18: 5 | C18: ACTUAL DAYS WORKED (1st month): If the employee will not work a full first month, how many DAYS are expected to be ACTUALLY WORKED?
A20: 6 | C20: WORKING DAYS (final month): How many WORKING DAYS are in the partial ending month? (Count the number of weekdays in the
C21: month by including holidays and excluding Saturday and Sunday.)
A23: 7 | C23: ACTUAL DAYS TO WORK (final month): If the employee will not work a full last month, how many DAYS are expected to be ACTUALLY WORKED?
C27: =B6/B8 -> #DIV/0! | D27: Monthly salary
C30: =SUM(B13*C27) -> #DIV/0! | D30: Pay for actual full months the employee will work
C31: =IF(B18=0,0,(C27/B15)*B18) -> 0 | D31: Partial beginning month - pay for actual days
C32: =IF(B23=0,0,(C27/B20)*B23) -> 0 | D32: Partial ending month - pay for actual days
C34: =SUM(C30:C33) -> #DIV/0! | D34: TOTAL This is the per other amount for Section 3-H of the PAF
