Workbook

Sheet REPORT 1 - APPROP Summary 
K1: PERCENT | M1: DIFFERENCE
H2: CURRENT | I2: PROPOSED | J2: DIFFERENCE | K2: CHANGE | L2: ADM | M2: PER ADM
G4: COMBINED REVENUE BY STRATA:
F6: 1 | G6: STATE | H6: =SUM(H9:H16) -> 9.0516897e+09 | I6: =SUM(I9:I16) -> 9.6855618e+09 | J6: =I6-H6 -> 6.3387204e+08 | K6: =IF(H6=0,0,J6/H6) -> 0.070028034 | L6: =SUM(L9:L16) -> 830024.43 | M6: =IF(L6=0,0,J6/L6) -> 763.67877
F7: 2 | G7: Metro Districts | H7: =SUM(H9:H11) -> 4.8470231e+09 | I7: =SUM(I9:I11) -> 5.1712581e+09 | J7: =SUM(J9:J11) -> 3.2423501e+08 | K7: =IF(H7=0,0,J7/H7) -> 0.066893637 | L7: =SUM(L9:L11) -> 422598.17 | M7: =IF(L7=0,0,J7/L7) -> 767.24186
F8: 3 | G8: Rural Districts | H8: =H6-H7-H16 -H15 -> 3.6858128e+09 | I8: =I6-I7-I16 -I15 -> 3.9626027e+09 | J8: =J6-J7-J16 -J15 -> 2.7678986e+08 | K8: =IF(H8=0,0,J8/H8) -> 0.075096016 | L8: =L6-L7-L15 -> 365649.26 | M8: =IF(L8=0,0,J8/L8) -> 756.98187
F9: 4 | G9: MPLS & ST PAUL | H9: =[1]Details!EL29 -> 9.9222065e+08 | I9: =[1]Details!EV29 -> 1.0516698e+09 | J9: =I9-H9 -> 59449126 | K9: =IF(H9=0,0,J9/H9) -> 0.059915228 | L9: =SUM([1]Details!K29:P29) -> 72789.15 | M9: =IF(L9=0,0,J9/L9) -> 816.7306
F10: =F9+1 -> 5 | G10: OTHER METRO, INNER | H10: =[1]Details!EL30 -> 9.9343092e+08 | I10: =[1]Details!EV30 -> 1.0675921e+09 | J10: =I10-H10 -> 74161138 | K10: =IF(H10=0,0,J10/H10) -> 0.07465153 | L10: =SUM([1]Details!K30:P30) -> 86993.02 | M10: =IF(L10=0,0,J10/L10) -> 852.49527
F11: =F10+1 -> 6 | G11: OTHER METRO, OUTER | H11: =[1]Details!EL31 -> 2.8613716e+09 | I11: =[1]Details!EV31 -> 3.0519963e+09 | J11: =I11-H11 -> 1.9062474e+08 | K11: =IF(H11=0,0,J11/H11) -> 0.06662006 | L11: =SUM([1]Details!K31:P31) -> 262816 | M11: =IF(L11=0,0,J11/L11) -> 725.31636
F12: =F11+1 -> 7 | G12: NONMET>=2K | H12: =[1]Details!EL32 -> 1.8421584e+09 | I12: =[1]Details!EV32 -> 1.9853958e+09 | J12: =I12-H12 -> 1.4323737e+08 | K12: =IF(H12=0,0,J12/H12) -> 0.077755189 | L12: =SUM([1]Details!K32:P32) -> 184386.4 | M12: =IF(L12=0,0,J12/L12) -> 776.83264
F13: =F12+1 -> 8 | G13: NONMET 1K-2K | H13: =[1]Details!EL33 -> 9.2173666e+08 | I13: =[1]Details!EV33 -> 9.8992407e+08 | J13: =I13-H13 -> 68187412 | K13: =IF(H13=0,0,J13/H13) -> 0.073977107 | L13: =SUM([1]Details!K33:P33) -> 93852 | M13: =IF(L13=0,0,J13/L13) -> 726.54191
F14: =F13+1 -> 9 | G14: NONMET < 1K | H14: =[1]Details!EL34 -> 9.2191778e+08 | I14: =[1]Details!EV34 -> 9.8728285e+08 | J14: =I14-H14 -> 65365075 | K14: =IF(H14=0,0,J14/H14) -> 0.070901198 | L14: =SUM([1]Details!K34:P34) -> 87410.86 | M14: =IF(L14=0,0,J14/L14) -> 747.79124
F15: =F14+1 -> 10 | G15: CHARTER | H15: =[1]Details!EL35 -> 4.2604333e+08 | I15: =[1]Details!EV35 -> 4.581314e+08 | J15: =I15-H15 -> 32088075 | K15: =IF(H15=0,0,J15/H15) -> 0.075316458 | L15: =SUM([1]Details!K35:P35) -> 41777 | M15: =IF(L15=0,0,J15/L15) -> 768.07991
F16: =F15+1 -> 11 | G16: NONCHARTER FUDGE, COOPS, S DAKOTA | H16: =[1]Details!EL36 -> 92810443 | I16: =[1]Details!EV36 -> 93569535 | J16: =I16-H16 -> 759092.17 | K16: =IF(H16=0,0,J16/H16) -> 0.0081789522 | L16: =SUM([1]Details!K36:P36) -> 0 | M16: =IF(L16=0,0,J16/L16) -> 0
F17: 12
F18: 13 | G18: COMBINED LEVIES BY STRATA:
F20: 14 | G20: STATE | H20: =SUM(H23:H30) -> 1.9737978e+09 | I20: =SUM(I23:I30) -> 1.9737978e+09 | J20: =I20-H20 -> 0.13811946 | K20: =IF(H20=0,0,J20/H20) -> 6.99765e-11 | L20: =L6 -> 830024.43 | M20: =IF(L20=0,0,J20/L20) -> 1.6640409e-07
F21: 15 | G21: Metro Districts | H21: =H23+H24+H25 -> 1.2936581e+09 | I21: =I23+I24+I25 -> 1.2938339e+09 | J21: =J23+J24+J25 -> 175840.5 | K21: =IF(H21=0,0,J21/H21) -> 0.00013592502 | L21: =L23+L24+L25 -> 422598.17 | M21: =IF(L21=0,0,J21/L21) -> 0.41609384
F22: 16 | G22: Rural Districts | H22: =H20-H21 -> 6.8013968e+08 | I22: =I20-I21 -> 6.7996384e+08 | J22: =J20-J21 -> -175840.36 | K22: =IF(H22=0,0,J22/H22) -> -0.00025853566 | L22: =L20-L21 -> 407426.26 | M22: =IF(L22=0,0,J22/L22) -> -0.43158818
F23: 17 | G23: MPLS & ST PAUL | H23: =[1]Details!EP29 -> 2.2316893e+08 | I23: =[1]Details!ES29 -> 2.2811797e+08 | J23: =I23-H23 -> 4949043.1 | K23: =IF(H23=0,0,J23/H23) -> 0.022176219 | L23: =L9 -> 72789.15 | M23: =IF(L23=0,0,J23/L23) -> 67.991494
F24: =F23+1 -> 18 | G24: OTHER METRO, INNER | H24: =[1]Details!EP30 -> 2.8869509e+08 | I24: =[1]Details!ES30 -> 2.9539178e+08 | J24: =I24-H24 -> 6696691.9 | K24: =IF(H24=0,0,J24/H24) -> 0.023196418 | L24: =L10 -> 86993.02 | M24: =IF(L24=0,0,J24/L24) -> 76.979646
F25: =F24+1 -> 19 | G25: OTHER METRO, OUTER | H25: =[1]Details!EP31 -> 7.8179407e+08 | I25: =[1]Details!ES31 -> 7.7032418e+08 | J25: =I25-H25 -> -11469895 | K25: =IF(H25=0,0,J25/H25) -> -0.014671248 | L25: =L11 -> 262816 | M25: =IF(L25=0,0,J25/L25) -> -43.642299
F26: =F25+1 -> 20 | G26: NONMET>=2K | H26: =[1]Details!EP32 -> 3.4655251e+08 | I26: =[1]Details!ES32 -> 3.4216217e+08 | J26: =I26-H26 -> -4390335.9 | K26: =IF(H26=0,0,J26/H26) -> -0.012668602 | L26: =L12 -> 184386.4 | M26: =IF(L26=0,0,J26/L26) -> -23.810519
F27: =F26+1 -> 21 | G27: NONMET 1K-2K | H27: =[1]Details!EP33 -> 1.6527069e+08 | I27: =[1]Details!ES33 -> 1.6594046e+08 | J27: =I27-H27 -> 669769.23 | K27: =IF(H27=0,0,J27/H27) -> 0.004052559 | L27: =L13 -> 93852 | M27: =IF(L27=0,0,J27/L27) -> 7.1364407
F28: =F27+1 -> 22 | G28: NONMET < 1K | H28: =[1]Details!EP34 -> 1.676566e+08 | I28: =[1]Details!ES34 -> 1.7192435e+08 | J28: =I28-H28 -> 4267758.5 | K28: =IF(H28=0,0,J28/H28) -> 0.025455357 | L28: =L14 -> 87410.86 | M28: =IF(L28=0,0,J28/L28) -> 48.824122
F29: =F28+1 -> 23 | G29: CHARTER | H29: =[1]Details!EP35 -> 0 | I29: =[1]Details!ES35 -> 0 | J29: =I29-H29 -> 0 | K29: =IF(H29=0,0,J29/H29) -> 0 | L29: =L15 -> 41777 | M29: =IF(L29=0,0,J29/L29) -> 0
F30: =F29+1 -> 24 | G30: NONCHARTER FUDGE, COOPS, S DAKOTA | H30: =[1]Details!EP36 -> 659887.44 | I30: =[1]Details!ES36 -> -63144.78 | J30: =I30-H30 -> -723032.22 | K30: =IF(H30=0,0,J30/H30) -> -1.0956902 | L30: =L16 -> 0 | M30: =IF(L30=0,0,J30/L30) -> 0
F31: 25
F32: 26 | G32: REVENUE BY FUNDING COMPONENT:
F34: 27 | G34: BASIC | H34: =[1]Details!V27 -> 5.0008227e+09 | I34: =[1]Details!AW27 -> 5520204270 | J34: =I34-H34 -> 5.1938154e+08 | K34: =IF(H34=0,0,J34/H34) -> 0.10385922 | L34: =$L$6 -> 830024.43 | M34: =IF(L34=0,0,J34/L34) -> 625.74248
F35: =F34+1 -> 28 | G35: DECLINING ENROLLMENT | H35: 0 | I35: =[1]Details!AX27 -> 9507183.8 | J35: =I35-H35 -> 9507183.8 | K35: =IF(H35=0,0,J35/H35) -> 0 | L35: =$L$6 -> 830024.43 | M35: =IF(L35=0,0,J35/L35) -> 11.454101
F36: =F35+1 -> 29 | G36: GIFTED & TALENTED | H36: =[1]Details!W27 -> 11487342 | I36: 0 | J36: =I36-H36 -> -11487342 | K36: =IF(H36=0,0,J36/H36) -> -1 | L36: =$L$6 -> 830024.43 | M36: =IF(L36=0,0,J36/L36) -> -13.839763
F37: =F36+1 -> 30 | G37: EXTENDED TIME | H37: =[1]Details!X27 -> 72139677 | I37: =[1]Details!BE27 -> 0 | J37: =I37-H37 -> -72139677 | K37: =IF(H37=0,0,J37/H37) -> -1 | L37: =$L$6 -> 830024.43 | M37: =IF(L37=0,0,J37/L37) -> -86.912715
F38: =F37+1 -> 31 | G38: COMPENSATORY INCLUDING CURRENT PILOT | H38: =[1]Details!Y27 -> 4.5635981e+08 | I38: =[1]Details!BF27 -> 5.460968e+08 | J38: =I38-H38 -> 89736988 | K38: =IF(H38=0,0,J38/H38) -> 0.19663648 | L38: =$L$6 -> 830024.43 | M38: =IF(L38=0,0,J38/L38) -> 108.11367
F39: =F38+1 -> 32 | G39: LEP REGULAR | H39: =[1]Details!Z27 -> 33577243 | I39: =[1]Details!AZ27 -> 36962037 | J39: =I39-H39 -> 3384794 | K39: =IF(H39=0,0,J39/H39) -> 0.10080619 | L39: =$L$6 -> 830024.43 | M39: =IF(L39=0,0,J39/L39) -> 4.077945
F40: =F39+1 -> 33 | G40: LEP CONCENTRATION | H40: =[1]Details!AA27 -> 8953592.5 | I40: =[1]Details!BD27 -> 12976506 | J40: =I40-H40 -> 4022913.1 | K40: =IF(H40=0,0,J40/H40) -> 0.44930715 | L40: =$L$6 -> 830024.43 | M40: =IF(L40=0,0,J40/L40) -> 4.8467407
F41: =F40+1 -> 34 | G41: SPARSITY | H41: =[1]Details!AB27 -> 25040627 | I41: =[1]Details!BG27 -> 26138900 | J41: =I41-H41 -> 1098273.2 | K41: =IF(H41=0,0,J41/H41) -> 0.043859651 | L41: =$L$6 -> 830024.43 | M41: =IF(L41=0,0,J41/L41) -> 1.3231817
F42: =F41+1 -> 35 | G42: SMALL SCHOOLS | H42: =[1]Details!AC27 -> 15727607 | I42: =[1]Details!AY27 -> 15733460 | J42: =I42-H42 -> 5853.0997 | K42: =IF(H42=0,0,J42/H42) -> 0.0003721545 | L42: =$L$6 -> 830024.43 | M42: =IF(L42=0,0,J42/L42) -> 0.0070517198
F43: =F42+1 -> 36 | G43: TRANSPORTATION SPARSITY | H43: =[1]Details!AD27 -> 61050314 | I43: =[1]Details!BM27 -> 63959706 | J43: =I43-H43 -> 2909392 | K43: =IF(H43=0,0,J43/H43) -> 0.047655644 | L43: =$L$6 -> 830024.43 | M43: =IF(L43=0,0,J43/L43) -> 3.5051884
F44: =F43+1 -> 37 | G44: EQUITY | H44: =[1]Details!AE27 -> 93683395 | I44: =[1]Details!CK27 -> 54232545 | J44: =I44-H44 -> -39450849 | K44: =IF(H44=0,0,J44/H44) -> -0.42110824 | L44: =$L$6 -> 830024.43 | M44: =IF(L44=0,0,J44/L44) -> -47.529745
F45: =F44+1 -> 38 | G45: TRANSITION | H45: =[1]Details!AF27 -> 29777252 | I45: =[1]Details!ET27 -> 793606.67 | J45: =I45-H45 -> -28983645 | K45: =IF(H45=0,0,J45/H45) -> -0.97334856 | L45: =$L$6 -> 830024.43 | M45: =IF(L45=0,0,J45/L45) -> -34.919027
F46: =F45+1 -> 39 | G46: OPERATING CAPITAL | H46: =[1]Details!AG27 -> 1.9741382e+08 | I46: =[1]Details!BQ27 -> 1.9743869e+08 | J46: =I46-H46 -> 24863.532 | K46: =IF(H46=0,0,J46/H46) -> 0.00012594626 | L46: =$L$6 -> 830024.43 | M46: =IF(L46=0,0,J46/L46) -> 0.029955181
F47: =F46+1 -> 40 | G47: Q COMP | H47: =[1]Details!AH27 -> 63679791 | I47: =[1]Details!DG27 -> 63679791 | J47: =I47-H47 -> 0 | K47: =IF(H47=0,0,J47/H47) -> 0 | L47: =$L$6 -> 830024.43 | M47: =IF(L47=0,0,J47/L47) -> 0
F48: =F47+1 -> 41 | G48: OPTIONS: REFERENDUM AID | H48: =[1]Details!AJ27 -> 524829.87 | I48: =[1]Details!DL27 -> 2553241.4 | J48: =I48-H48 -> 2028411.5 | K48: =IF(H48=0,0,J48/H48) -> 3.8648934 | L48: =$L$6 -> 830024.43 | M48: =IF(L48=0,0,J48/L48) -> 2.4437974
F49: =F48+1 -> 42 | G49: OPTIONS: CHARTER TRANSPORTATION | H49: =[1]Details!AK27 -> -299052.72 | I49: =H49 -> -299052.72 | J49: =I49-H49 -> 0 | K49: =IF(H49=0,0,J49/H49) -> 0 | L49: =$L$6 -> 830024.43 | M49: =IF(L49=0,0,J49/L49) -> 0
F50: =F49+1 -> 43 | G50: OPTIONS: FARIBAULT | H50: =[1]Details!AL27 -> -1173414.9 | I50: =H50 -> -1173414.9 | J50: =I50-H50 -> 0 | K50: =IF(H50=0,0,J50/H50) -> 0 | L50: =$L$6 -> 830024.43 | M50: =IF(L50=0,0,J50/L50) -> 0
F51: =F50+1 -> 44 | G51: PENSION | H51: =[1]Details!AM27 -> -31058527 | I51: =[1]Details!BT27 -> 7069609.6 | J51: =I51-H51 -> 38128137 | K51: =IF(H51=0,0,J51/H51) -> -1.2276222 | L51: =$L$6 -> 830024.43 | M51: =IF(L51=0,0,J51/L51) -> 45.936163
F52: =F51+1 -> 45 | G52: INTEGRATION | H52: =[1]Details!BU27 -> 97376462 | I52: =[1]Details!BY27 -> 1.0148786e+08 | J52: =I52-H52 -> 4111394 | K52: =IF(H52=0,0,J52/H52) -> 0.042221641 | L52: =$L$6 -> 830024.43 | M52: =IF(L52=0,0,J52/L52) -> 4.953341
F53: =F52+1 -> 46 | G53: ALL DAY KINDERGARTEN | H53: 0 | I53: =[1]Details!CA27 -> 62999080 | J53: =I53-H53 -> 62999080 | K53: =IF(H53=0,0,J53/H53) -> 0 | L53: =$L$6 -> 830024.43 | M53: =IF(L53=0,0,J53/L53) -> 75.900273
F54: =F53+1 -> 47 | G54: LITERACY INCENTIVE AID | H54: =[1]Details!CJ27 -> 48585000 | I54: =[1]Details!CJ27 -> 48585000 | J54: =I54-H54 -> 0 | K54: =IF(H54=0,0,J54/H54) -> 0 | L54: =$L$6 -> 830024.43 | M54: =IF(L54=0,0,J54/L54) -> 0
F55: =F54+1 -> 48 | G55: SAFE SCHOOLS LEVY | H55: =[1]Details!BW27 -> 29454100 | I55: 0 | J55: =I55-H55 -> -29454100 | K55: =IF(H55=0,0,J55/H55) -> -1 | L55: =$L$6 -> 830024.43 | M55: =IF(L55=0,0,J55/L55) -> -35.485823
F56: =F55+1 -> 49 | G56: COMBINED SPECIAL EDUCATION | H56: =[1]Details!CB27 -> 9.6589214e+08 | I56: =[1]Details!CC27 -> 1.1604575e+09 | J56: =I56-H56 -> 1.9456533e+08 | K56: =IF(H56=0,0,J56/H56) -> 0.20143588 | L56: =$L$6 -> 830024.43 | M56: =IF(L56=0,0,J56/L56) -> 234.40917
F57: =F56+1 -> 50 | G57: CHARTER SCHOOL LEASE AID | H57: =[1]Details!CD27 -> 49975643 | I57: =[1]Details!CE27 -> 49967709 | J57: =I57-H57 -> -7933.29 | K57: =IF(H57=0,0,J57/H57) -> -0.00015874313 | L57: =$L$6 -> 830024.43 | M57: =IF(L57=0,0,J57/L57) -> -0.0095578994
F58: =F57+1 -> 51 | G58: REFERENDUM | H58: =[1]Details!AI27 -> 8.5897711e+08 | I58: =[1]Details!CF27 -> 4.48805e+08 | J58: =I58-H58 -> -4.1017211e+08 | K58: =IF(H58=0,0,J58/H58) -> -0.47751227 | L58: =$L$6 -> 830024.43 | M58: =IF(L58=0,0,J58/L58) -> -494.16871
F59: =F58+1 -> 52 | G59: REGIONAL COST ADJUSTMENT FROM REFERENDUM | H59: 0 | I59: =[1]Details!CG27 -> 2.0613499e+08 | J59: =I59-H59 -> 2.0613499e+08 | K59: =IF(H59=0,0,J59/H59) -> 0 | L59: =$L$6 -> 830024.43 | M59: =IF(L59=0,0,J59/L59) -> 248.3481
F60: =F69+1 -> 62 | G60: REGIONAL COST ADJUSTMENT NEW DOLLARS | H60: 0 | I60: =[1]Details!CH27 -> 53144144 | J60: =I60-H60 -> 53144144 | K60: =IF(H60=0,0,J60/H60) -> 0 | L60: =$L$6 -> 830024.43 | M60: =IF(L60=0,0,J60/L60) -> 64.027205
F61: =F59+1 -> 53 | G61: LEVY FOR ICE ARENA | H61: =[1]Details!CN27 -> 1809300 | I61: =[1]Details!DC27 -> 1809300 | J61: =I61-H61 -> 0 | K61: =IF(H61=0,0,J61/H61) -> 0 | L61: =$L$6 -> 830024.43 | M61: =IF(L61=0,0,J61/L61) -> 0
F62: =F61+1 -> 54 | G62: LEVY FOR SWIMMING POOLS | H62: =[1]Details!CP27 -> 536000 | I62: =[1]Details!DD27 -> 536000 | J62: =I62-H62 -> 0 | K62: =IF(H62=0,0,J62/H62) -> 0 | L62: =$L$6 -> 830024.43 | M62: =IF(L62=0,0,J62/L62) -> 0
F63: =F62+1 -> 55 | G63: LEVY FOR TREE GROWTH | H63: =[1]Details!CQ27 -> 631700 | I63: =[1]Details!DE27 -> 631700 | J63: =I63-H63 -> 0 | K63: =IF(H63=0,0,J63/H63) -> 0 | L63: =$L$6 -> 830024.43 | M63: =IF(L63=0,0,J63/L63) -> 0 | Q63: =O63/[1]Details!AQ27 -> 0
F64: =F63+1 -> 56 | G64: LEASE LEVY (NON-INTERMEDIATE) | H64: =[1]Details!DM27 -> 44557360 | I64: =[1]Details!DN27 -> 44557360 | J64: =I64-H64 -> 0 | K64: =IF(H64=0,0,J64/H64) -> 0 | L64: =$L$6 -> 830024.43 | M64: =IF(L64=0,0,J64/L64) -> 0
F65: =F64+1 -> 57 | G65: HEALTH & SAFETY | H65: =[1]Details!DO27 -> 56294162 | I65: =[1]Details!DP27 -> 0 | J65: =I65-H65 -> -56294162 | K65: =IF(H65=0,0,J65/H65) -> -1 | L65: =$L$6 -> 830024.43 | M65: =IF(L65=0,0,J65/L65) -> -67.822296
F66: =F65+1 -> 58 | G66: DEBT EXCLUDING ALT FACILITIES | H66: =[1]Details!DS27-[1]Details!ED27 -> 6.4007568e+08 | I66: =[1]Details!DT27-[1]Details!ED27 -> 6.4007568e+08 | J66: =I66-H66 -> 0 | K66: =IF(H66=0,0,J66/H66) -> 0 | L66: =$L$6 -> 830024.43 | M66: =IF(L66=0,0,J66/L66) -> 0
F67: =F66+1 -> 59 | G67: DEFERRED MAINTENANCE | H67: =[1]Details!DW27 -> 26096486 | I67: =[1]Details!DY27 -> 93437343 | J67: =I67-H67 -> 67340856 | K67: =IF(H67=0,0,J67/H67) -> 2.5804568 | L67: =$L$6 -> 830024.43 | M67: =IF(L67=0,0,J67/L67) -> 81.131174
F68: =F67+1 -> 60 | G68: ALTERNATIVE FACILITIES PAY AS YOU GO | H68: =[1]Details!EA27 -> 62373415 | I68: =[1]Details!EE27 -> 85711117 | J68: =I68-H68 -> 23337702 | K68: =IF(H68=0,0,J68/H68) -> 0.37416104 | L68: =$L$6 -> 830024.43 | M68: =IF(L68=0,0,J68/L68) -> 28.116885
F69: =F68+1 -> 61 | G69: ALTERNATIVE FACILITIES DEBT SERVICE | H69: =[1]Details!EC27 -> 131348154 | I69: =[1]Details!EG27 -> 131348154 | J69: =I69-H69 -> 0 | K69: =IF(H69=0,0,J69/H69) -> 0 | L69: =$L$6 -> 830024.43 | M69: =IF(L69=0,0,J69/L69) -> 0
F70: =F69+1 -> 62 | G70: TOTAL ABOVE | H70: =SUM(H34:H69) -> 9.0516897e+09 | I70: =SUM(I34:I69) -> 9.6855618e+09 | J70: =SUM(J34:J69) -> 6.3387204e+08 | K70: =IF(H70=0,0,J70/H70) -> 0.070028034 | L70: =$L$6 -> 830024.43 | M70: =IF(L70=0,0,J70/L70) -> 763.67877
H71: Total $ | I71: Percent | J71: $ / ADM
G72: Proposed Revenue Increase After Full Phase-In | H72: 6.3387204e+08 | I72: 0.070028034 | J72: 763.67877
G73: Annual Increase with 4 year phase-in | H73: 1.5846801e+08 | I73: 0.017507008 | J73: 190.91969
G74: Annual Increase with 5year phase-in | H74: 1.2677441e+08 | I74: 0.014005607 | J74: 152.73575
G75: Annual Increase with 6 year phase-in | H75: 1.0564534e+08 | I75: 0.011671339 | J75: 127.2798
G79: Aid Entitlement Change from Current Law | H79: FY 2015 | I79: FY 2016 | J79: FY 2017 | K79: FY 2018 | L79: FY 2019 | M79: FY 2020
G80: 4 Year Phase-in | H80: =H73 -> 1.5846801e+08 | I80: =H80*2 -> 3.1693602e+08 | J80: =H80*3 -> 4.7540403e+08 | K80: =H80*4 -> 6.3387204e+08 | L80: =K80 -> 6.3387204e+08 | M80: =L80 -> 6.3387204e+08
G81: 5 Year Phase-in | H81: =H74 -> 1.2677441e+08 | I81: =H81*2 -> 2.5354881e+08 | J81: =H81*3 -> 3.8032322e+08 | K81: =H81*4 -> 5.0709763e+08 | L81: =H81*5 -> 6.3387204e+08 | M81: =L81 -> 6.3387204e+08
G82: 6 Year Phase-in | H82: =H75 -> 1.0564534e+08 | I82: =H82*2 -> 2.1129068e+08 | J82: =H82*3 -> 3.1693602e+08 | K82: =H82*4 -> 4.2258136e+08 | L82: =H82*5 -> 5.282267e+08 | M82: =H82*6 -> 6.3387204e+08
G84: Appropriation Cost @ 82.5% Pay Schedule | H84: FY 2015 | I84: FY 2016 | J84: FY 2017 | K84: FY 2018 | L84: FY 2019 | M84: FY 2020 | O84: 0.825 | P84: =1-O84 -> 0.175
G85: 4 Year Phase-in | H85: =H80*$O$84 -> 1.3073611e+08 | I85: =I80*$O$84+H80*$P$84 -> 2.8920412e+08 | J85: =J80*$O$84+I80*$P$84 -> 4.4767213e+08 | K85: =K80*$O$84+J80*$P$84 -> 6.0614013e+08 | L85: =L80*$O$84+K80*$P$84 -> 6.3387204e+08 | M85: =M80*$O$84+L80*$P$84 -> 6.3387204e+08
G86: 5 Year Phase-in | H86: =H81*$O$84 -> 1.0458889e+08 | I86: =I81*$O$84+H81*$P$84 -> 2.3136329e+08 | J86: =J81*$O$84+I81*$P$84 -> 3.581377e+08 | K86: =K81*$O$84+J81*$P$84 -> 4.8491211e+08 | L86: =L81*$O$84+K81*$P$84 -> 6.1168652e+08 | M86: =M81*$O$84+L81*$P$84 -> 6.3387204e+08
G87: 6 Year Phase-in | H87: =H82*$O$84 -> 87157405 | I87: =I82*$O$84+H82*$P$84 -> 1.9280274e+08 | J87: =J82*$O$84+I82*$P$84 -> 2.9844808e+08 | K87: =K82*$O$84+J82*$P$84 -> 4.0409342e+08 | L87: =L82*$O$84+K82*$P$84 -> 5.0973876e+08 | M87: =M82*$O$84+L82*$P$84 -> 6.153841e+08
G89: Comparison with Previous Biennium: | H89: FY 2012 | I89: FY 2013 | J89: Added in FY 13 over FY 2013
G90: Aid Entitlement Increase over Base | H90: 53820475 | I90: 191259583 | J90: =I90-H90 -> 137439108
G97: LEVIES, RMV
F98: =F70+1 -> 63 | G98: GENERAL | H98: 0 | I98: =[1]Details!DI27 -> 2.9293606e+08 | J98: =I98-H98 -> 2.9293606e+08 | K98: =IF(H98=0,0,J98/H98) -> 0 | L98: =$L$6 -> 830024.43 | M98: =IF(L98=0,0,J98/L98) -> 352.92463
F99: =F98+1 -> 64 | G99: REFERENDUM | H99: =[1]Details!CU27 -> 7.6441898e+08 | I99: =[1]Details!CY27 -> 3.6433042e+08 | J99: =I99-H99 -> -4.0008857e+08 | K99: =IF(H99=0,0,J99/H99) -> -0.5233891 | L99: =$L$6 -> 830024.43 | M99: =IF(L99=0,0,J99/L99) -> -482.02023
F100: =F99+1 -> 65 | G100: EQUITY | H100: =[1]Details!CX27 -> 73599986 | I100: =[1]Details!DA27 -> 35711824 | J100: =I100-H100 -> -37888162 | K100: =IF(H100=0,0,J100/H100) -> -0.51478491 | L100: =$L$6 -> 830024.43 | M100: =IF(L100=0,0,J100/L100) -> -45.647045
F101: =F100+1 -> 66 | G101: TRANSITION | H101: =[1]Details!CW27 -> 23474332 | I101: 0 | J101: =I101-H101 -> -23474332 | K101: =IF(H101=0,0,J101/H101) -> -1 | L101: =$L$6 -> 830024.43 | M101: =IF(L101=0,0,J101/L101) -> -28.281495
F102: =F101+1 -> 67 | G102: REGIONAL COST ADJUSTMENT | H102: 0 | I102: =[1]Details!DB27 -> 1.68515e+08 | J102: =I102-H102 -> 1.68515e+08 | K102: =IF(H102=0,0,J102/H102) -> 0 | L102: =$L$6 -> 830024.43 | M102: =IF(L102=0,0,J102/L102) -> 203.02414
G105: LEVIES, NTC
F106: =F102+1 -> 68 | G106: GENERAL | H106: 0 | I106: =[1]Details!DJ27 -> 1.8462343e+08 | J106: =I106-H106 -> 1.8462343e+08 | K106: =IF(H106=0,0,J106/H106) -> 0 | L106: =$L$6 -> 830024.43 | M106: =IF(L106=0,0,J106/L106) -> 222.43132 | O106: =SUM(J107:J119) -> -1.8462343e+08
F107: =F106+1 -> 69 | G107: OPERATING CAPITAL | H107: =[1]Details!CV27 -> 1.1405029e+08 | I107: 0 | J107: =I107-H107 -> -1.1405029e+08 | K107: =IF(H107=0,0,J107/H107) -> -1 | L107: =$L$6 -> 830024.43 | M107: =IF(L107=0,0,J107/L107) -> -137.40594
F108: =F107+1 -> 70 | G108: INTEGRATION | H108: =[1]Details!BV27 -> 29788452 | I108: 0 | J108: =I108-H108 -> -29788452 | K108: =IF(H108=0,0,J108/H108) -> -1 | L108: =$L$6 -> 830024.43 | M108: =IF(L108=0,0,J108/L108) -> -35.888644
F109: =F108+1 -> 71 | G109: Q COMP | H109: =[1]Details!DF27 -> 17053254 | I109: =[1]Details!DH27 -> 17135585 | J109: =I109-H109 -> 82331.14 | K109: =IF(H109=0,0,J109/H109) -> 0.0048278846 | L109: =$L$6 -> 830024.43 | M109: =IF(L109=0,0,J109/L109) -> 0.099191225
F110: =F109+1 -> 72 | G110: SAFE SCHOOLS | H110: =H55 -> 29454100 | I110: =I55 -> 0 | J110: =I110-H110 -> -29454100 | K110: =IF(H110=0,0,J110/H110) -> -1 | L110: =$L$6 -> 830024.43 | M110: =IF(L110=0,0,J110/L110) -> -35.485823
F111: =F110+1 -> 73 | G111: ICE ARENA | H111: =H61 -> 1809300 | I111: =I61 -> 1809300 | J111: =I111-H111 -> 0 | K111: =IF(H111=0,0,J111/H111) -> 0 | L111: =$L$6 -> 830024.43 | M111: =IF(L111=0,0,J111/L111) -> 0
F112: =F111+1 -> 74 | G112: SWIMMING POOLS | H112: =H62 -> 536000 | I112: =I62 -> 536000 | J112: =I112-H112 -> 0 | K112: =IF(H112=0,0,J112/H112) -> 0 | L112: =$L$6 -> 830024.43 | M112: =IF(L112=0,0,J112/L112) -> 0
F113: =F112+1 -> 75 | G113: TREE GROWTH | H113: =H63 -> 631700 | I113: =I63 -> 631700 | J113: =I113-H113 -> 0 | K113: =IF(H113=0,0,J113/H113) -> 0 | L113: =$L$6 -> 830024.43 | M113: =IF(L113=0,0,J113/L113) -> 0
F114: =F113+1 -> 76 | G114: LEASE LEVY (NON-INTERMEDIATE) | H114: =[1]Details!DM27 -> 44557360 | I114: =[1]Details!DN27 -> 44557360 | J114: =I114-H114 -> 0 | K114: =IF(H114=0,0,J114/H114) -> 0 | L114: =$L$6 -> 830024.43 | M114: =IF(L114=0,0,J114/L114) -> 0
F115: =F114+1 -> 77 | G115: HEALTH & SAFETY LEVY | H115: =[1]Details!DQ27 -> 56201200 | I115: =[1]Details!DR27 -> 0 | J115: =I115-H115 -> -56201200 | K115: =IF(H115=0,0,J115/H115) -> -1 | L115: =$L$6 -> 830024.43 | M115: =IF(L115=0,0,J115/L115) -> -67.710296
F116: =F115+1 -> 78 | G116: DEBT LEVY Excluding Alt Facilities | H116: =[1]Details!DU27-[1]Details!ED27 -> 6.2120611e+08 | I116: =[1]Details!DV27-[1]Details!EH27 -> 6.1081063e+08 | J116: =I116-H116 -> -10395484 | K116: =IF(H116=0,0,J116/H116) -> -0.016734355 | L116: =$L$6 -> 830024.43 | M116: =IF(L116=0,0,J116/L116) -> -12.52431
F117: =F116+1 -> 79 | G117: DEFERRED MAINTENANCE | H117: =[1]Details!DX27 -> 22581198 | I117: =[1]Details!DZ27 -> 54427257 | J117: =I117-H117 -> 31846059 | K117: =IF(H117=0,0,J117/H117) -> 1.4102909 | L117: =$L$6 -> 830024.43 | M117: =IF(L117=0,0,J117/L117) -> 38.367617
...

Sheet REPORT 2 - Summary
K1: PERCENT | M1: DIFFERENCE
H2: CURRENT | I2: PROPOSED | J2: DIFFERENCE | K2: CHANGE | L2: ADM | M2: PER ADM
G4: COMBINED REVENUE BY STRATA:
F6: 1 | G6: STATE | H6: 9.0516897e+09 | I6: 9.6855618e+09 | J6: 6.3387204e+08 | K6: 0.070028034 | L6: 830024.43 | M6: 763.67877
F7: 2 | G7: Metro Districts | H7: 4.8470231e+09 | I7: 5.1712581e+09 | J7: 3.2423501e+08 | K7: 0.066893637 | L7: 422598.17 | M7: 767.24186
F8: 3 | G8: Rural Districts | H8: 3.6858128e+09 | I8: 3.9626027e+09 | J8: 2.7678986e+08 | K8: 0.075096016 | L8: 365649.26 | M8: 756.98187
F9: 4 | G9: MPLS & ST PAUL | H9: 9.9222065e+08 | I9: 1.0516698e+09 | J9: 59449126 | K9: 0.059915228 | L9: 72789.15 | M9: 816.7306
F10: =F9+1 -> 5 | G10: OTHER METRO, INNER | H10: 9.9343092e+08 | I10: 1.0675921e+09 | J10: 74161138 | K10: 0.07465153 | L10: 86993.02 | M10: 852.49527
F11: =F10+1 -> 6 | G11: OTHER METRO, OUTER | H11: 2.8613716e+09 | I11: 3.0519963e+09 | J11: 1.9062474e+08 | K11: 0.06662006 | L11: 262816 | M11: 725.31636
F12: =F11+1 -> 7 | G12: NONMET>=2K | H12: 1.8421584e+09 | I12: 1.9853958e+09 | J12: 1.4323737e+08 | K12: 0.077755189 | L12: 184386.4 | M12: 776.83264
F13: =F12+1 -> 8 | G13: NONMET 1K-2K | H13: 9.2173666e+08 | I13: 9.8992407e+08 | J13: 68187412 | K13: 0.073977107 | L13: 93852 | M13: 726.54191
F14: =F13+1 -> 9 | G14: NONMET < 1K | H14: 9.2191778e+08 | I14: 9.8728285e+08 | J14: 65365075 | K14: 0.070901198 | L14: 87410.86 | M14: 747.79124
F15: =F14+1 -> 10 | G15: CHARTER | H15: 4.2604333e+08 | I15: 4.581314e+08 | J15: 32088075 | K15: 0.075316458 | L15: 41777 | M15: 768.07991
F16: =F15+1 -> 11 | G16: NONCHARTER FUDGE, COOPS, S DAKOTA | H16: 92810443 | I16: 93569535 | J16: 759092.17 | K16: 0.0081789522 | L16: 0 | M16: 0
F17: 12
F18: 13 | G18: COMBINED LEVIES BY STRATA:
F20: 14 | G20: STATE | H20: 1.9737978e+09 | I20: 1.9737978e+09 | J20: 0.13811946 | K20: 6.99765e-11 | L20: 830024.43 | M20: 1.6640409e-07
F21: 15 | G21: Metro Districts | H21: 1.2936581e+09 | I21: 1.2938339e+09 | J21: 175840.5 | K21: 0.00013592502 | L21: 422598.17 | M21: 0.41609384
F22: 16 | G22: Rural Districts | H22: 6.8013968e+08 | I22: 6.7996384e+08 | J22: -175840.36 | K22: -0.00025853566 | L22: 407426.26 | M22: -0.43158818
F23: 17 | G23: MPLS & ST PAUL | H23: 2.2316893e+08 | I23: 2.2811797e+08 | J23: 4949043.1 | K23: 0.022176219 | L23: 72789.15 | M23: 67.991494
F24: =F23+1 -> 18 | G24: OTHER METRO, INNER | H24: 2.8869509e+08 | I24: 2.9539178e+08 | J24: 6696691.9 | K24: 0.023196418 | L24: 86993.02 | M24: 76.979646
F25: =F24+1 -> 19 | G25: OTHER METRO, OUTER | H25: 7.8179407e+08 | I25: 7.7032418e+08 | J25: -11469895 | K25: -0.014671248 | L25: 262816 | M25: -43.642299
F26: =F25+1 -> 20 | G26: NONMET>=2K | H26: 3.4655251e+08 | I26: 3.4216217e+08 | J26: -4390335.9 | K26: -0.012668602 | L26: 184386.4 | M26: -23.810519
F27: =F26+1 -> 21 | G27: NONMET 1K-2K | H27: 1.6527069e+08 | I27: 1.6594046e+08 | J27: 669769.23 | K27: 0.004052559 | L27: 93852 | M27: 7.1364407
F28: =F27+1 -> 22 | G28: NONMET < 1K | H28: 1.676566e+08 | I28: 1.7192435e+08 | J28: 4267758.5 | K28: 0.025455357 | L28: 87410.86 | M28: 48.824122
F29: =F28+1 -> 23 | G29: CHARTER | H29: 0 | I29: 0 | J29: 0 | K29: 0 | L29: 41777 | M29: 0
F30: =F29+1 -> 24 | G30: NONCHARTER FUDGE, COOPS, S DAKOTA | H30: 659887.44 | I30: -63144.78 | J30: -723032.22 | K30: -1.0956902 | L30: 0 | M30: 0
F31: 25
F32: 26 | G32: REVENUE BY FUNDING COMPONENT:
F34: 27 | G34: BASIC | H34: 5.0008227e+09 | I34: 5520204270 | J34: 5.1938154e+08 | K34: 0.10385922 | L34: 830024.43 | M34: 625.74248
F35: =F34+1 -> 28 | G35: DECLINING ENROLLMENT | H35: 0 | I35: 9507183.8 | J35: 9507183.8 | K35: 0 | L35: 830024.43 | M35: 11.454101
F36: =F35+1 -> 29 | G36: GIFTED & TALENTED | H36: 11487342 | I36: 0 | J36: -11487342 | K36: -1 | L36: 830024.43 | M36: -13.839763
F37: =F36+1 -> 30 | G37: EXTENDED TIME | H37: 72139677 | I37: 0 | J37: -72139677 | K37: -1 | L37: 830024.43 | M37: -86.912715
F38: =F37+1 -> 31 | G38: COMPENSATORY INCLUDING CURRENT PILOT | H38: 4.5635981e+08 | I38: 5.460968e+08 | J38: 89736988 | K38: 0.19663648 | L38: 830024.43 | M38: 108.11367
F39: =F38+1 -> 32 | G39: LEP REGULAR | H39: 33577243 | I39: 36962037 | J39: 3384794 | K39: 0.10080619 | L39: 830024.43 | M39: 4.077945
F40: =F39+1 -> 33 | G40: LEP CONCENTRATION | H40: 8953592.5 | I40: 12976506 | J40: 4022913.1 | K40: 0.44930715 | L40: 830024.43 | M40: 4.8467407
F41: =F40+1 -> 34 | G41: SPARSITY | H41: 25040627 | I41: 26138900 | J41: 1098273.2 | K41: 0.043859651 | L41: 830024.43 | M41: 1.3231817
F42: =F41+1 -> 35 | G42: SMALL SCHOOLS | H42: 15727607 | I42: 15733460 | J42: 5853.0997 | K42: 0.0003721545 | L42: 830024.43 | M42: 0.0070517198
F43: =F42+1 -> 36 | G43: TRANSPORTATION SPARSITY | H43: 61050314 | I43: 63959706 | J43: 2909392 | K43: 0.047655644 | L43: 830024.43 | M43: 3.5051884
F44: =F43+1 -> 37 | G44: EQUITY | H44: 93683395 | I44: 54232545 | J44: -39450849 | K44: -0.42110824 | L44: 830024.43 | M44: -47.529745
F45: =F44+1 -> 38 | G45: TRANSITION | H45: 29777252 | I45: 793606.67 | J45: -28983645 | K45: -0.97334856 | L45: 830024.43 | M45: -34.919027
F46: =F45+1 -> 39 | G46: OPERATING CAPITAL | H46: 1.9741382e+08 | I46: 1.9743869e+08 | J46: 24863.532 | K46: 0.00012594626 | L46: 830024.43 | M46: 0.029955181
... F59: =F58+1 -> 52 | G59: REGIONAL COST ADJUSTMENT FROM REFERENDUM | H59: 0 | I59: 2.0613499e+08 | J59: 2.0613499e+08 | K59: 0 | L59: 830024.43 | M59: 248.3481
F60: =F69+1 -> 62 | G60: REGIONAL COST ADJUSTMENT NEW DOLLARS | H60: 0 | I60: 53144144 | J60: 53144144 | K60: 0 | L60: 830024.43 | M60: 64.027205
F61: =F59+1 -> 53 | G61: LEVY FOR ICE ARENA | H61: 1809300 | I61: 1809300 | J61: 0 | K61: 0 | L61: 830024.43 | M61: 0
F62: =F61+1 -> 54 | G62: LEVY FOR SWIMMING POOLS | H62: 536000 | I62: 536000 | J62: 0 | K62: 0 | L62: 830024.43 | M62: 0
F63: =F62+1 -> 55 | G63: LEVY FOR TREE GROWTH | H63: 631700 | I63: 631700 | J63: 0 | K63: 0 | L63: 830024.43 | M63: 0 | Q63: =O63/[1]Details!AQ27 -> 0
F64: =F63+1 -> 56 | G64: LEASE LEVY (NON-INTERMEDIATE) | H64: 44557360 | I64: 44557360 | J64: 0 | K64: 0 | L64: 830024.43 | M64: 0
F65: =F64+1 -> 57 | G65: HEALTH & SAFETY | H65: 56294162 | I65: 0 | J65: -56294162 | K65: -1 | L65: 830024.43 | M65: -67.822296
F66: =F65+1 -> 58 | G66: DEBT EXCLUDING ALT FACILITIES | H66: 6.4007568e+08 | I66: 6.4007568e+08 | J66: 0 | K66: 0 | L66: 830024.43 | M66: 0
F67: =F66+1 -> 59 | G67: DEFERRED MAINTENANCE | H67: 26096486 | I67: 93437343 | J67: 67340856 | K67: 2.5804568 | L67: 830024.43 | M67: 81.131174
F68: =F67+1 -> 60 | G68: ALTERNATIVE FACILITIES PAY AS YOU GO | H68: 62373415 | I68: 85711117 | J68: 23337702 | K68: 0.37416104 | L68: 830024.43 | M68: 28.116885
F69: =F68+1 -> 61 | G69: ALTERNATIVE FACILITIES DEBT SERVICE | H69: 131348154 | I69: 131348154 | J69: 0 | K69: 0 | L69: 830024.43 | M69: 0
F70: =F69+1 -> 62 | G70: TOTAL ABOVE | H70: 9.0516897e+09 | I70: 9.6855618e+09 | J70: 6.3387204e+08 | K70: 0.070028034 | L70: 830024.43 | M70: 763.67877
G72: LEVIES, RMV
F73: =F70+1 -> 63 | G73: GENERAL | H73: 0 | I73: 2.9293606e+08 | J73: 2.9293606e+08 | K73: 0 | L73: 830024.43 | M73: 352.92463
F74: =F73+1 -> 64 | G74: REFERENDUM | H74: 7.6441898e+08 | I74: 3.6433042e+08 | J74: -4.0008857e+08 | K74: -0.5233891 | L74: 830024.43 | M74: -482.02023
F75: =F74+1 -> 65 | G75: EQUITY | H75: 73599986 | I75: 35711824 | J75: -37888162 | K75: -0.51478491 | L75: 830024.43 | M75: -45.647045
F76: =F75+1 -> 66 | G76: TRANSITION | H76: 23474332 | I76: 0 | J76: -23474332 | K76: -1 | L76: 830024.43 | M76: -28.281495
F77: =F76+1 -> 67 | G77: REGIONAL COST ADJUSTMENT | H77: 0 | I77: 1.68515e+08 | J77: 1.68515e+08 | K77: 0 | L77: 830024.43 | M77: 203.02414
G80: LEVIES, NTC
F81: =F77+1 -> 68 | G81: GENERAL | H81: 0 | I81: 1.8462343e+08 | J81: 1.8462343e+08 | K81: 0 | L81: 830024.43 | M81: 222.43132 | O81: =SUM(J82:J94) -> -1.8462343e+08
F82: =F81+1 -> 69 | G82: OPERATING CAPITAL | H82: 1.1405029e+08 | I82: 0 | J82: -1.1405029e+08 | K82: -1 | L82: 830024.43 | M82: -137.40594
F83: =F82+1 -> 70 | G83: INTEGRATION | H83: 29788452 | I83: 0 | J83: -29788452 | K83: -1 | L83: 830024.43 | M83: -35.888644
F84: =F83+1 -> 71 | G84: Q COMP | H84: 17053254 | I84: 17135585 | J84: 82331.14 | K84: 0.0048278846 | L84: 830024.43 | M84: 0.099191225
F85: =F84+1 -> 72 | G85: SAFE SCHOOLS | H85: 29454100 | I85: 0 | J85: -29454100 | K85: -1 | L85: 830024.43 | M85: -35.485823
F86: =F85+1 -> 73 | G86: ICE ARENA | H86: 1809300 | I86: 1809300 | J86: 0 | K86: 0 | L86: 830024.43 | M86: 0
F87: =F86+1 -> 74 | G87: SWIMMING POOLS | H87: 536000 | I87: 536000 | J87: 0 | K87: 0 | L87: 830024.43 | M87: 0
F88: =F87+1 -> 75 | G88: TREE GROWTH | H88: 631700 | I88: 631700 | J88: 0 | K88: 0 | L88: 830024.43 | M88: 0
F89: =F88+1 -> 76 | G89: LEASE LEVY (NON-INTERMEDIATE) | H89: 44557360 | I89: 44557360 | J89: 0 | K89: 0 | L89: 830024.43 | M89: 0
F90: =F89+1 -> 77 | G90: HEALTH & SAFETY LEVY | H90: 56201200 | I90: 0 | J90: -56201200 | K90: -1 | L90: 830024.43 | M90: -67.710296
F91: =F90+1 -> 78 | G91: DEBT LEVY Excluding Alt Facilities | H91: 6.2120611e+08 | I91: 6.1081063e+08 | J91: -10395484 | K91: -0.016734355 | L91: 830024.43 | M91: -12.52431
F92: =F91+1 -> 79 | G92: DEFERRED MAINTENANCE | H92: 22581198 | I92: 54427257 | J92: 31846059 | K92: 1.4102909 | L92: 830024.43 | M92: 38.367617
F93: =F92+1 -> 80 | G93: ALTERNATIVE FACILITIES PAY AS YOU GO | H93: 59543588 | I93: 82881290 | J93: 23337702 | K93: 0.39194315 | L93: 830024.43 | M93: 28.116885
F94: =F93+1 -> 81 | G94: ALTERNATIVE FACILITIES DEBT SERVICE | H94: 114891917 | I94: 114891917 | J94: 0 | K94: 0 | L94: 830024.43 | M94: 0
F96: =F94+1 -> 82 | G96: LEVY TOTAL, RMV | H96: 8.614933e+08 | I96: 8.614933e+08 | J96: 0 | K96: 0 | L96: 830024.43 | M96: 0
F97: =F96+1 -> 83 | G97: LEVY TOTAL, NTC | H97: 1.1123045e+09 | I97: 1.1123045e+09 | J97: 0 | K97: 0 | L97: 830024.43 | M97: 0
F98: =F97+1 -> 84 | G98: =+"LEVY TOTAL, COMBINED = ("&+F96&")+("&+F97&") =" -> LEVY TOTAL, COMBINED = (82)+(83) = | H98: 1.9737978e+09 | I98: 1.9737978e+09 | J98: 0 | K98: 0 | L98: 830024.43 | M98: 0
F100: =F98+1 -> 85 | G100: EXTENDED TIME PLUS COMPENSATORY | H100: 5.2849949e+08 | I100: 5.460968e+08 | J100: 17597310 | K100: 0.033296741 | L100: 830024.43 | M100: 21.200955
G101: EQUALIZED STATE AID
F103: =F98+1 -> 85 | G103: =+"REFERENDUM = ("&+F58&")-("&+F74&") =" -> REFERENDUM = (51)-(64) = | H103: 94558123 | I103: 84474583 | J103: -10083540 | K103: -0.10663853 | L103: 830024.43 | M103: -12.148485
F104: =F103+1 -> 86 | G104: =+"EQUITY = ("&+F44&")-("&+F75&") =" -> EQUITY = (37)-(65) = | H104: 20083409 | I104: 18520722 | J104: -1562687 | K104: -0.07780985 | L104: 830024.43 | M104: -1.8827
F105: =F104+1 -> 87 | G105: =+"TRANSITION = ("&+F45&")-("&+F76&") =" -> TRANSITION = (38)-(66) = | H105: 6302920.1 | I105: 793606.67 | J105: -5509313.5 | K105: -0.87408905 | L105: 830024.43 | M105: -6.6375317
F106: =F105+1 -> 88 | G106: =+"REGIONAL COST ADJUSTMENT = ("&+F59&")-("&+F77&") =" -> REGIONAL COST ADJUSTMENT = (52)-(67) = | H106: 0 | I106: 37619990 | J106: 37619990 | K106: 0 | L106: 830024.43 | M106: 45.323955
F107: =F106+1 -> 89 | G107: =+"OPERATING CAPITAL = ("&+F46&")-("&+F82&") =" -> OPERATING CAPITAL = (39)-(69) = | H107: 83363536 | I107: 1.9743869e+08 | J107: 1.1407515e+08 | K107: 1.3684059 | L107: 830024.43 | M107: 137.4359
F108: =F107+1 -> 90 | G108: =+"INTEGRATION = ("&+F52&")-("&+F83&") =" -> INTEGRATION = (45)-(70) = | H108: 67588010 | I108: 1.0148786e+08 | J108: 33899846 | K108: 0.50156597 | L108: 830024.43 | M108: 40.841985
F109: =F108+1 -> 91 | G109: =+"Q COMP = ("&+F47&")-("&+F84&") =" -> Q COMP = (40)-(71) = | H109: 46626537 | I109: 46544206 | J109: -82331.14 | K109: -0.0017657571 | L109: 830024.43 | M109: -0.099191225
F110: =F109+1 -> 92 | G110: =+"DEBT AID = ("&+F66&")-("&+F91&") =" -> DEBT AID = (58)-(78) = | H110: 18869564 | I110: 29265047 | J110: 10395484 | K110: 0.55091278 | L110: 830024.43 | M110: 12.52431
F111: =F110+1 -> 93 | G111: =+"DEFERRED MAINTENANCE = ("&+F67&")-("&+F92&") =" -> DEFERRED MAINTENANCE = (59)-(79) = | H111: 3515288.2 | I111: 39010085 | J111: 35494797 | K111: 10.097265 | L111: 830024.43 | M111: 42.763557
F112: =F111+1 -> 94 | G112: =+"ALTERNATIVE FACILITIES = [("&+F68&")+("&+F69&")]-[("&+F93&")+("&+F94&")] =" -> ALTERNATIVE FACILITIES = [(60)+(61)]-[(80)+(81)] = | H112: 19286064 | I112: 19286064 | J112: 0 | K112: 0 | L112: 830024.43 | M112: 0
F114: FUNDING PROPOSAL, FALL 2012
F116: PARAMETERS: | H116: CURRENT | I116: PROPOSED
F118: 1 | G118: WEIGHT, PRE-K | H118: 1.25 | I118: 1
F119: =F118+1 -> 2 | G119: WEIGHT, HANDICAPPED K | H119: 1 | I119: 1
F120: =F119+1 -> 3 | G120: WEIGHT, REGULAR K | H120: 0.612 | I120: 0.5
F123: =F120+1 -> 4 | G123: WEIGHT, GRADES 1-3 | H123: 1.115 | I123: 1
F124: =F123+1 -> 5 | G124: WEIGHT, GRADES 4-6 | H124: 1.06 | I124: 1
F125: =F124+1 -> 6 | G125: WEIGHT, GRADES 7-12 | H125: 1.3 | I125: 1.2
F126: =F125+1 -> 7 | G126: FORMULA ALLOWANCE | H126: 5224 | I126: 6300
F127: =F126+1 -> 8 | G127: DECLINING PUPIL MULTIPLIER | H127: N/A | I127: 0.28
...

Sheet REPORT 3 - REVENUE PER ADM
A2: Basic | D2: 1 | E2: 1
A3: Transition | D3: =D2+1 -> 2 | E3: 2
A4: Refer | D4: =D3+1 -> 3 | E4: 3
A5: Regional adj | D5: =D4+1 -> 4 | E5: 4
A6: Equity | D6: =D5+1 -> 5 | E6: 5
A7: Compensatory/ext | D7: =D6+1 -> 6 | E7: 6
A8: Integr | D8: =D7+1 -> 7 | E8: 7
A9: sp ed | D9: =D8+1 -> 8 | E9: 8
A10: all day K | D10: =D9+1 -> 9 | E10: 9
A11: pension | D11: =D10+1 -> 10 | E11: 10
A12: facilities | D12: =D11+1 -> 11 | E12: 11
A13: lease aid | D13: =D12+1 -> 12 | E13: 12
A14: Other | D14: 13 | E14: 13
A16: Category (1 to 12): | F16: 11 | G16: 21 | H16: 31 | I16: 41 | J16: 51 | K16: 61 | L16: 71 | M16: 81 | N16: 91 | O16: 101 | P16: 111 | Q16: 121 | R16: 131 | S16: Total | U16: 11 | V16: 21 | W16: 31 | X16: 41 | Y16: 51 | Z16: 61 | AA16: 71 | AB16: 81 | AC16: 91 | AD16: 101 | AE16: 111 | AF16: 121 | AG16: 131 | AH16: Total
A18: Revenue, current
A19: Revenue, proposed
A20: Levy, current
A21: Levy, proposed
A28: Revenue per Student Impact
F29: Current Law | U29: Working Group Recommendation | AI29: Change: Working Group Recommendation vs Current Law
G31: Tran- | H31: Refer- | I31: Region | K31: Comp/ | L31: Inte- | M31: Spec | N31: All Day | Q31: Small/ | V31: Tran- | W31: Refer- | X31: Region | Z31: Comp/ | AA31: Inte- | AB31: Spec | AC31: All Day | AF31: Small/ | AJ31: Tran- | AK31: Refer- | AL31: Region | AN31: Comp/ | AO31: Inte- | AP31: Spec | AQ31: All Day | AT31: Small/
D32: Strata | E32: ADM | F32: Basic | G32: sition | H32: endum | I32: Adjust | J32: Equity | K32: Ex Time | L32: gration | M32: Educ | N32: Kinder | O32: Pension | P32: Facilities | Q32: Sparsity | R32: Other | S32: Total | U32: Basic | V32: sition | W32: endum | X32: Adjust | Y32: Equity | Z32: Ex Time | AA32: gration | AB32: Educ | AC32: Kinder | AD32: Pension | AE32: Facilities | AF32: Sparsity | AG32: Other | AH32: Total | AI32: Basic | AJ32: sition | AK32: endum | AL32: Adjust | AM32: Equity | AN32: Ex Time | AO32: gration | AP32: Educ | AQ32: Kinder | AR32: Pension | AS32: Facilities | AT32: Sparsity | AU32: Other | AV32: Total
A34: TOTAL | E34: 830024.43 | F34: 6024.9103 | G34: 35.875151 | H34: 1035.514 | I34: 0 | J34: 112.86824 | K34: 687.96809 | L34: 117.31759 | M34: 1163.6912 | N34: 0 | O34: -37.418811 | P34: 1458.3667 | Q34: 122.66934 | R34: 183.56745 | S34: 10905.329 | U34: 6662.1069 | V34: 0 | W34: 543.78911 | X34: 312.3753 | Y34: 65.338493 | Z34: 718.09373 | AA34: 122.27093 | AB34: 1398.1004 | AC34: 75.900273 | AD34: 8.5173512 | AE34: 1499.8129 | AF34: 127.50476 | AG34: 134.24186 | AH34: 11668.052 | AI34: 637.19658 | AJ34: -35.875151 | AK34: -491.72492 | AL34: 312.3753 | AM34: -47.529745 | AN34: 30.12564 | AO34: 4.953341 | AP34: 234.40917 | AQ34: 75.900273 | AR34: 45.936163 | AS34: 41.446161 | AT34: 4.8354219 | AU34: -49.325586 | AV34: 762.72265
A36: MPLS & ST PAUL | D36: 1 | E36: 72789.15 | F36: 5947.0218 | G36: 231.28637 | H36: 1379.1883 | I36: 0 | J36: 52.366578 | K36: 2162.3078 | L36: 512.32197 | M36: 1629.9803 | N36: 0 | O36: 20.949171 | P36: 1596.7826 | Q36: 0.28460107 | R36: 98.946518 | S36: 13631.436 | U36: 6559.0448 | V36: 0 | W36: 881.6925 | X36: 546.62116 | Y36: 41.133786 | Z36: 2119.2133 | AA36: 454.8561 | AB36: 1997.2489 | AC36: 140.86003 | AD36: 57.855196 | AE36: 1596.5418 | AF36: 0.35398023 | AG36: 52.745133 | AH36: 14448.167 | AI36: 612.02295 | AJ36: -231.28637 | AK36: -497.49578 | AL36: 546.62116 | AM36: -11.232792 | AN36: -43.094457 | AO36: -57.465875 | AP36: 367.26855 | AQ36: 140.86003 | AR36: 36.906025 | AS36: -0.24082788 | AT36: 0.069379159 | AU36: -46.201384 | AV36: 816.7306
A37: OTHER METRO, INNER | D37: 2 | E37: 86993.02 | F37: 6049.2168 | G37: 11.863302 | H37: 1506.9788 | I37: 0 | J37: 106.88803 | K37: 685.085 | L37: 149.97014 | M37: 947.07476 | N37: 0 | O37: -44.664197 | P37: 1710.1174 | Q37: 0.28949185 | R37: 296.84286 | S37: 11419.662 | U37: 6692.524 | V37: 0 | W37: 802.16525 | X37: 526.35098 | Y37: 48.983868 | Z37: 714.20775 | AA37: 210.93115 | AB37: 1240.6007 | AC37: 67.316334 | AD37: 3.3011559 | AE37: 1725.865 | AF37: 0.53313277 | AG37: 239.37833 | AH37: 12272.158 | AI37: 643.30722 | AJ37: -11.863302 | AK37: -704.81358 | AL37: 526.35098 | AM37: -57.904159 | AN37: 29.122749 | AO37: 60.961011 | AP37: 293.52598 | AQ37: 67.316334 | AR37: 47.965353 | AS37: 15.747583 | AT37: 0.24364093 | AU37: -57.464536 | AV37: 852.49527
A38: OTHER METRO, OUTER | D38: 3 | E38: 262816 | F38: 6051.2173 | G38: 14.649334 | H38: 1383.961 | I38: 0 | J38: 116.84737 | K38: 354.86809 | L38: 106.36151 | M38: 1090.265 | N38: 0 | O38: -38.290187 | P38: 1558.6255 | Q38: 15.592639 | R38: 233.25922 | S38: 10887.357 | U38: 6694.9774 | V38: 0 | W38: 680.879 | X38: 511.43875 | Y38: 57.49813 | Z38: 356.28426 | AA38: 120.55569 | AB38: 1350.213 | AC38: 55.096468 | AD38: 4.793845 | AE38: 1583.588 | AF38: 17.801011 | AG38: 179.54757 | AH38: 11612.673 | AI38: 643.76007 | AJ38: -14.649334 | AK38: -703.08196 | AL38: 511.43875 | AM38: -59.349241 | AN38: 1.416164 | AO38: 14.194184 | AP38: 259.94802 | AQ38: 55.096468 | AR38: 43.084032 | AS38: 24.962479 | AT38: 2.2083723 | AU38: -53.711649 | AV38: 725.31636
A39: NONMET>=2K | D39: 4 | E39: 184386.4 | F39: 6022.4272 | G39: 17.502578 | H39: 662.09161 | I39: 0 | J39: 119.45888 | K39: 553.28547 | L39: 66.666778 | M39: 1028.1147 | N39: 0 | O39: -39.57889 | P39: 1326.964 | Q39: 87.286969 | R39: 146.53052 | S39: 9990.7499 | U39: 6658.1754 | V39: 0 | W39: 222.42455 | X39: 213.07371 | Y39: 89.736736 | Z39: 575.12424 | AA39: 68.706051 | AB39: 1274.9298 | AC39: 74.476327 | AD39: 6.03347 | AE39: 1392.4213 | AF39: 93.491056 | AG39: 98.989785 | AH39: 10767.583 | AI39: 635.74828 | AJ39: -17.502578 | AK39: -439.66706 | AL39: 213.07371 | AM39: -29.722147 | AN39: 21.838765 | AO39: 2.0392728 | AP39: 246.81505 | AQ39: 74.476327 | AR39: 45.61236 | AS39: 65.457314 | AT39: 6.2040877 | AU39: -47.540733 | AV39: 776.83264
A40: NONMET 1K-2K | D40: 5 | E40: 93852 | F40: 6037.4354 | G40: 18.885207 | H40: 645.09281 | I40: 0 | J40: 132.38943 | K40: 505.86286 | L40: 35.73445 | M40: 821.6177 | N40: 0 | O40: -51.366996 | P40: 1302.8341 | Q40: 224.51172 | R40: 148.17553 | S40: 9821.1723 | U40: 6678.9449 | V40: 0 | W40: 395.09346 | X40: 0 | Y40: 77.593539 | Z40: 575.327 | AA40: 29.257324 | AB40: 994.45154 | AC40: 70.652511 | AD40: 1.3432247 | AE40: 1390.5626 | AF40: 232.52861 | AG40: 101.95951 | AH40: 10547.714 | AI40: 641.50943 | AJ40: -18.885207 | AK40: -249.99935 | AL40: 0 | AM40: -54.795893 | AN40: 69.464135 | AO40: -6.4771264 | AP40: 172.83384 | AQ40: 70.652511 | AR40: 52.71022 | AS40: 87.728501 | AT40: 8.0168848 | AU40: -46.216029 | AV40: 726.54191
A41: NONMET < 1K | D41: 6 | E41: 87410.86 | F41: 6047.1302 | G41: 16.691605 | H41: 903.92694 | I41: 0 | J41: 122.95166 | K41: 588.21203 | L41: 39.342049 | M41: 842.89341 | N41: 0 | O41: -56.92338 | P41: 1249.9292 | Q41: 664.83984 | R41: 127.95427 | S41: 10546.948 | U41: 6690.1857 | V41: 0 | W41: 661.31721 | X41: 0 | Y41: 61.519882 | Z41: 694.61955 | AA41: 33.536389 | AB41: 989.39051 | AC41: 79.672446 | AD41: 0.83225631 | AE41: 1320.8001 | AF41: 681.5007 | AG41: 81.364338 | AH41: 11294.739 | AI41: 643.0555 | AJ41: -16.691605 | AK41: -242.60974 | AL41: 0 | AM41: -61.43178 | AN41: 106.40752 | AO41: -5.80566 | AP41: 146.4971 | AQ41: 79.672446 | AR41: 57.755636 | AS41: 70.870896 | AT41: 16.66086 | AU41: -46.589937 | AV41: 747.79124
A42: CHARTER | D42: 7 | E42: 41777 | F42: 5880.8383 | G42: 38.330434 | H42: 63.463119 | I42: 0 | J42: 111.66163 | K42: 1432.9529 | L42: 0 | M42: 1096.5327 | N42: 0 | O42: -36.867817 | P42: 1427.7326 | Q42: 57.328852 | R42: 126.06278 | S42: 10198.035 | U42: 6492.3254 | V42: 1.6893135 | W42: 61.115958 | X42: 0 | Y42: 63.664709 | Z42: 1561.9442 | AA42: 0 | AB42: 1072.3055 | AC42: 114.3836 | AD42: 0 | AE42: 1427.5068 | AF42: 58.625916 | AG42: 112.55397 | AH42: 10966.115 | AI42: 611.48714 | AJ42: -36.641121 | AK42: -2.347161 | AL42: 0 | AM42: -47.996922 | AN42: 128.99126 | AO42: 0 | AP42: -24.227157 | AQ42: 114.3836 | AR42: 36.867817 | AS42: -0.2257923 | AT42: 1.2970644 | AU42: -13.508817 | AV42: 768.07991
A43: NONCHARTER FUDGE | D43: 8 | E43: 0 | F43: 0 | G43: 0 | H43: 0 | I43: 0 | J43: 0 | K43: 0 | L43: 0 | M43: 0 | N43: 0 | O43: 0 | P43: 0 | Q43: 0 | R43: 0 | S43: 0 | U43: 0 | V43: 0 | W43: 0 | X43: 0 | Y43: 0 | Z43: 0 | AA43: 0 | AB43: 0 | AC43: 0 | AD43: 0 | AE43: 0 | AF43: 0 | AG43: 0 | AH43: 0 | AI43: 0 | AJ43: 0 | AK43: 0 | AL43: 0 | AM43: 0 | AN43: 0 | AO43: 0 | AP43: 0 | AQ43: 0 | AR43: 0 | AS43: 0 | AT43: 0 | AU43: 0 | AV43: 0
A45: 1 | B45: 1 | C45: AITKIN | D45: 5 | E45: 1226.43 | F45: 6094.6454 | G45: 47.284835 | H45: 0.067985943 | I45: 0 | J45: 237.87026 | K45: 649.88693 | L45: 0 | M45: 743.32649 | N45: 0 | O45: -49.438843 | P45: 366.6106 | Q45: 434.89176 | R45: 106.36899 | S45: 8631.5144 | U45: 6754.4827 | V45: 0 | W45: 0 | X45: 0 | Y45: 106.20011 | Z45: 766.40944 | AA45: 0 | AB45: 940.45486 | AC45: 116.08291 | AD45: 0 | AE45: 492.2828 | AF45: 444.62666 | AG45: 56.921031 | AH45: 9677.4605 | AI45: 659.83735 | AJ45: -47.284835 | AK45: -0.067985943 | AL45: 0 | AM45: -131.67015 | AN45: 116.52251 | AO45: 0 | AP45: 197.12837 | AQ45: 116.08291 | AR45: 49.438843 | AS45: 125.6722 | AT45: 9.7349054 | AU45: -49.447959 | AV45: 1045.9462
A46: 1.2 | B46: 3 | C46: MINNEAPOLIS | D46: 1 | E46: 34128.01 | F46: 5907.1578 | G46: 201.27086 | H46: 1957.5098 | I46: 0 | J46: 52.015555 | K46: 2055.2737 | L46: 537.43163 | M46: 1755.329 | N46: 0 | O46: 39.276702 | P46: 1991.3035 | Q46: 0.28269331 | R46: 102.46679 | S46: 14599.318 | U46: 6509.7729 | V46: 0 | W46: 1435.4773 | X46: 540.47472 | Y46: 0.79563883 | Z46: 1967.2812 | AA46: 456.88724 | AB46: 2098.4376 | AC46: 148.93078 | AD46: 75.906018 | AE46: 1990.8268 | AF46: 0.3513211 | AG46: 56.320048 | AH46: 15281.462 | AI46: 602.61507 | AJ46: -201.27086 | AK46: -522.03253 | AL46: 540.47472 | AM46: -51.219916 | AN46: -87.992537 | AO46: -80.544384 | AP46: 343.10856 | AQ46: 148.93078 | AR46: 36.629316 | AS46: -0.47662903 | AT46: 0.068627793 | AU46: -46.146745 | AV46: 682.14349
A47: 2 | B47: 1 | C47: HILL CITY | D47: 6 | E47: 276.11 | F47: 6091.2926 | G47: 55.665822 | H47: 0 | I47: 0 | J47: 159.27283 | K47: 1169.898 | L47: 0 | M47: 1190.2784 | N47: 0 | O47: -73.402376 | P47: 1144.1859 | Q47: 1926.5936 | R47: 95.676035 | S47: 11759.461 | U47: 6731.9166 | V47: 0 | W47: 0 | X47: 0 | Y47: 106.84872 | Z47: 1372.8155 | AA47: 0 | AB47: 1381.1181 | AC47: 116.30972 | AD47: 0 | AE47: 1240.532 | AF47: 1940.7016 | AG47: 47.911376 | AH47: 12938.154 | AI47: 640.62395 | AJ47: -55.665822 | AK47: 0 | AL47: 0 | AM47: -52.424106 | AN47: 202.91757 | AO47: 0 | AP47: 190.83973 | AQ47: 116.30972 | AR47: 73.402376 | AS47: 96.346104 | AT47: 14.107996 | AU47: -47.764659 | AV47: 1178.6929
A48: 4 | B48: 1 | C48: MCGREGOR | D48: 6 | E48: 399.46 | F48: 5907.8306 | G48: 0 | H48: 0 | I48: 0 | J48: 174.41193 | K48: 1409.7762 | L48: 0 | M48: 444.94824 | N48: 0 | O48: -79.288139 | P48: 2393.6624 | Q48: 2192.7228 | R48: 111.53725 | S48: 12555.601 | U48: 6538.3042 | V48: 0 | W48: 0 | X48: 0 | Y48: 103.78261 | Z48: 1621.6668 | AA48: 0 | AB48: 741.27016 | AC48: 105.13091 | AD48: 0 | AE48: 2394.1759 | AF48: 2261.5377 | AG48: 65.946202 | AH48: 13831.814 | AI48: 630.47364 | AJ48: 0 | AK48: 0 | AL48: 0 | AM48: -70.629325 | AN48: 211.89053 | AO48: 0 | AP48: 296.32192 | AQ48: 105.13091 | AR48: 79.288139 | AS48: 0.51348965 | AT48: 68.814971 | AU48: -45.591048 | AV48: 1276.2132
A49: 6 | B49: 3 | C49: SOUTH ST. PAUL | D49: 2 | E49: 3308.17 | F49: 5993.4108 | G49: 31.733871 | H49: 1071.3359 | I49: 0 | J49: 137.40158 | K49: 671.07207 | L49: 145.72775 | M49: 887.40397 | N49: 0 | O49: -39.222649 | P49: 917.04267 | Q49: 0.28682021 | R49: 376.15451 | S49: 10192.347 | U49: 6625.2134 | V49: 0 | W49: 368.47344 | X49: 529.78722 | Y49: 78.622779 | Z49: 723.16684 | AA49: 174.90385 | AB49: 1226.7047 | AC49: 84.52309 | AD49: 0 | AE49: 969.45896 | AF49: 0.35680452 | AG49: 319.39355 | AH49: 11100.605 | AI49: 631.80255 | AJ49: -31.733871 | AK49: -702.86245 | AL49: 529.78722 | AM49: -58.778802 | AN49: 52.094772 | AO49: 29.1761 | AP49: 339.30073 | AQ49: 84.52309 | AR49: 39.222649 | AS49: 52.416284 | AT49: 0.069984312 | AU49: -56.760965 | AV49: 908.2573
A50: 11 | B50: 1 | C50: ANOKA-HENNEPIN | D50: 3 | E50: 37509.62 | F50: 6076.4802 | G50: 34.058067 | H50: 1526.7649 | I50: 0 | J50: 106.99851 | K50: 492.69643 | L50: 143.29749 | M50: 1266.3077 | N50: 0 | O50: -43.091876 | P50: 1002.819 | Q50: 0.29079633 | R50: 107.74767 | S50: 10714.369 | U50: 6722.6816 | V50: 0 | W50: 815.15941 | X50: 533.53623 | Y50: 48.297694 | Z50: 451.87884 | AA50: 132.88777 | AB50: 1506.1641 | AC50: 72.248166 | AD50: 0 | AE50: 1002.8914 | AF50: 0.36217936 | AG50: 58.622471 | AH50: 11344.73 | AI50: 646.20137 | AJ50: -34.058067 | AK50: -711.60552 | AL50: 533.53623 | AM50: -58.700817 | AN50: -40.81759 | AO50: -10.409725 | AP50: 239.8564 | AQ50: 72.248166 | AR50: 43.091876 | AS50: 0.072377148 | AT50: 0.071383021 | AU50: -49.125195 | AV50: 630.36091
A51: 12 | B51: 1 | C51: CENTENNIAL | D51: 3 | E51: 6410.17 | F51: 6064.2186 | G51: 0 | H51: 1023.4069 | I51: 0 | J51: 143.23292 | K51: 148.91559 | L51: 0 | M51: 1274.218 | N51: 0 | O51: -39.655207 | P51: 1555.907 | Q51: 0.29020915 | R51: 292.0133 | S51: 10462.547 | U51: 6712.7497 | V51: 0 | W51: 280.53359 | X51: 527.45099 | Y51: 86.087934 | Z51: 177.17942 | AA51: 0 | AB51: 1566.9181 | AC51: 44.212819 | AD51: 0 | AE51: 1698.2128 | AF51: 0.36082818 | AG51: 232.67688 | AH51: 11326.383 | AI51: 648.53113 | AJ51: 0 | AK51: -742.87328 | AL51: 527.45099 | AM51: -57.144985 | AN51: 28.26383 | AO51: 0 | AP51: 292.70016 | AQ51: 44.212819 | AR51: 39.655207 | AS51: 142.30574 | AT51: 0.070619032 | AU51: -59.336423 | AV51: 863.83582
A52: 13 | B52: 1 | C52: COLUMBIA HEIGHTS | D52: 2 | E52: 3035.96 | F52: 5968.1717 | G52: 0 | H52: 1149.6578 | I52: 0 | J52: 129.39702 | K52: 1973.2724 | L52: 184.65714 | M52: 1122.1153 | N52: 0 | O52: -48.669541 | P52: 1454.7616 | Q52: 0.28561312 | R52: 104.29889 | S52: 12037.948 | U52: 6587.6332 | V52: 0 | W52: 417.69777 | X52: 551.13549 | Y52: 74.730052 | Z52: 2270.5706 | AA52: 368.48574 | AB52: 1486.6013 | AC52: 160.31861 | AD52: 0 | AE52: 1457.287 | AF52: 0.35552181 | AG52: 50.859787 | AH52: 13425.675 | AI52: 619.46153 | AJ52: 0 | AK52: -731.96006 | AL52: 551.13549 | AM52: -54.666972 | AN52: 297.29823 | AO52: 183.82861 | AP52: 364.48595 | AQ52: 160.31861 | AR52: 48.669541 | AS52: 2.5254586 | AT52: 0.069908694 | AU52: -53.439103 | AV52: 1387.7272
A53: 14 | B53: 1 | C53: FRIDLEY | D53: 3 | E53: 2997.43 | F53: 6037.6908 | G53: 0 | H53: 963.06627 | I53: 0 | J53: 147.12826 | K53: 1125.3869 | L53: 147.82754 | M53: 1394.457 | N53: 0 | O53: -48.860464 | P53: 1361.696 | Q53: 0.28894086 | R53: 353.18642 | S53: 11481.868 | U53: 6673.1327 | V53: 0 | W53: 221.61156 | X53: 542.16458 | Y53: 90.093343 | Z53: 1225.1083 | AA53: 228.19136 | AB53: 1695.7449 | AC53: 109.00763 | AD53: 0 | AE53: 1402.5022 | AF53: 0.36013852 | AG53: 305.80279 | AH53: 12493.72 | AI53: 635.44188 | AJ53: 0 | AK53: -741.45471 | AL53: 542.16458 | AM53: -57.034917 | AN53: 99.721488 | AO53: 80.363817 | AP53: 301.28785 | AQ53: 109.00763 | AR53: 48.860464 | AS53: 40.806239 | AT53: 0.071197659 | AU53: -47.383632 | AV53: 1011.8519
A54: 15 | B54: 1 | C54: ST. FRANCIS | D54: 3 | E54: 4908.56 | F54: 6114.4797 | G54: 12.008913 | H54: 476.32345 | I54: 0 | J54: 180.54336 | K54: 289.14575 | L54: 0 | M54: 1154.4632 | N54: 0 | O54: -42.859745 | P54: 1556.6395 | Q54: 68.600622 | R54: 389.91426 | S54: 10199.259 | U54: 6773.4847 | V54: 0 | W54: 0 | X54: 274.56298 | Y54: 106.76043 | Z54: 374.85114 | AA54: 0 | AB54: 1397.7211 | AC54: 67.092415 | AD54: 0 | AE54: 1676.1312 | AF54: 79.290975 | AG54: 340.22214 | AH54: 11090.117 | AI54: 659.00498 | AJ54: -12.008913 | AK54: -476.32345 | AL54: 274.56298 | AM54: -73.782922 | AN54: 85.70539 | AO54: 0 | AP54: 243.25789 | AQ54: 67.092415 | AR54: 42.859745 | AS54: 119.49167 | AT54: 10.690353 | AU54: -49.692117 | AV54: 890.85802
A55: 16 | B55: 1 | C55: SPRING LAKE PARK | D55: 3 | E55: 5097.1 | F55: 5980.0457 | G55: 51.718695 | H55: 964.52253 | I55: 0 | J55: 143.37686 | K55: 630.37451 | L55: 96.013219 | M55: 717.94605 | N55: 0 | O55: -33.887658 | P55: 2302.8013 | Q55: 0.28618234 | R55: 379.63511 | S55: 11232.832 | U55: 6606.8486 | V55: 0 | W55: 282.15438 | X55: 527.61023 | Y55: 84.716729 | Z55: 601.67021 | AA55: 166.41384 | AB55: 908.6413 | AC55: 63.685914 | AD55: 3.2929372 | AE55: 2360.8126 | AF55: 0.35655961 | AG55: 325.59676 | AH55: 11931.8 | AI55: 626.80294 | AJ55: -51.718695 | AK55: -682.36815 | AL55: 527.61023 | AM55: -58.66013 | AN55: -28.704298 | AO55: 70.400618 | AP55: 190.69525 | AQ55: 63.685914 | AR55: 37.180595 | AS55: 58.011327 | AT55: 0.070377273 | AU55: -54.038355 | AV55: 698.96764
A56: 22 | B56: 1 | C56: DETROIT LAKES | D56: 4 | E56: 2862.5 | F56: 6030.1659 | G56: 9.6270253 | H56: 515.27146 | I56: 0 | J56: 134.45515 | K56: 679.19845 | L56: 99.960258 | M56: 1144.5241 | N56: 0 | O56: -52.847396 | P56: 673.47152 | Q56: 140.12286 | R56: 106.52378 | S56: 9480.473 | U56: 6668.5803 | V56: 0 | W56: 0 | X56: 243.25635 | Y56: 105.85048 | Z56: 512.58793 | AA56: 92.223455 | AB56: 1347.4724 | AC56: 67.610385 | AD56: 0 | AE56: 795.18934 | AF56: 143.16277 | AG56: 59.011259 | AH56: 10034.945 | AI56: 638.41441 | AJ56: -9.6270253 | AK56: -515.27146 | AL56: 243.25635 | AM56: -28.604674 | AN56: -166.61052 | AO56: -7.7368028 | AP56: 202.94827 | AQ56: 67.610385 | AR56: 52.847396 | AS56: 121.71782 | AT56: 3.0399127 | AU56: -47.512517 | AV56: 554.47155
... A529: 6666 | B529: 8 | C529: FUDGE, DISTRICTS | D529: 8 | E529: 0 | F529: 0 | G529: 0 | H529: 0 | I529: 0 | J529: 0 | K529: 0 | L529: 0 | M529: 0 | N529: 0 | O529: 0 | P529: 0 | Q529: 0 | R529: 0 | S529: 0 | U529: 0 | V529: 0 | W529: 0 | X529: 0 | Y529: 0 | Z529: 0 | AA529: 0 | AB529: 0 | AC529: 0 | AD529: 0 | AE529: 0 | AF529: 0 | AG529: 0 | AH529: 0 | AI529: 0 | AJ529: 0 | AK529: 0 | AL529: 0 | AM529: 0 | AN529: 0 | AO529: 0 | AP529: 0 | AQ529: 0 | AR529: 0 | AS529: 0 | AT529: 0 | AU529: 0 | AV529: 5.7429054e-06
B530: 9 | C530: FUDGE, CHARTERS | D530: 7 | E530: 0 | F530: 0 | G530: 0 | H530: 0 | I530: 0 | J530: 0 | K530: 0 | L530: 0 | M530: 0 | N530: 0 | O530: 0 | P530: 0 | Q530: 0 | R530: 0 | S530: 0 | U530: 0 | V530: 0 | W530: 0 | X530: 0 | Y530: 0 | Z530: 0 | AA530: 0 | AB530: 0 | AC530: 0 | AD530: 0 | AE530: 0 | AF530: 0 | AG530: 0 | AH530: 0 | AI530: 0 | AJ530: 0 | AK530: 0 | AL530: 0 | AM530: 0 | AN530: 0 | AO530: 0 | AP530: 0 | AQ530: 0 | AR530: 0 | AS530: 0 | AT530: 0 | AU530: 0 | AV530: 3.383573e-06
A531: 8888 | B531: 8 | C531: FUDGE, OTHER | D531: 8 | E531: 0 | F531: 0 | G531: 0 | H531: 0 | I531: 0 | J531: 0 | K531: 0 | L531: 0 | M531: 0 | N531: 0 | O531: 0 | P531: 0 | Q531: 0 | R531: 0 | S531: 0 | U531: 0 | V531: 0 | W531: 0 | X531: 0 | Y531: 0 | Z531: 0 | AA531: 0 | AB531: 0 | AC531: 0 | AD531: 0 | AE531: 0 | AF531: 0 | AG531: 0 | AH531: 0 | AI531: 0 | AJ531: 0 | AK531: 0 | AL531: 0 | AM531: 0 | AN531: 0 | AO531: 0 | AP531: 0 | AQ531: 0 | AR531: 0 | AS531: 0 | AT531: 0 | AU531: 0 | AV531: 2.6402639e-06

Sheet REPORT 4 - PROPERTY TAX
A2: PARAMETERS
A3: PARAMETERS
A4: PARAMETERS
A5: PARAMETERS
A6: PARAMETERS
A7: PARAMETERS
A8: PARAMETERS
A9: PARAMETERS
A11: Revenue, current
A12: Revenue, proposed
A13: Levy, current | I13: #REF!
A14: Levy, proposed | L14: #REF!
E16: A | F16: B | G16: ED | H16: EE | I16: EF | J16: EG | K16: EH | L16: EI | U16: M | V16: N | AF16: I | AH16: O
AH18: Approx Tax | AK18: Exclusion is $30,400 minus 9% of value over $76,000
AH19: Impact on
AH20: 150000 | AK20: Value | AL20: 76000 | AM20: =AH20 -> 150000 | AN20: =AM20-AL20 -> 74000
AH21: Resid Value | AK21: 0.4 | AL21: =AL20*$AK21 -> 30400 | AM21: =AL21-0.09*AN20 -> 23740
E22: Tax Bases | G22: Current School Taxes | J22: Working Group Recommendation | M22: Change: Working Group - Current | Q22: Tax Rates | W22: Rough Approximation of Tax on $150,000 Homestead | AH22: =+"= "&+U16&" *" -> = M * | AK22: Net value | AL22: =AL20-AL21 -> 45600 | AM22: =AM20-AM21 -> 126260
Q23: Current Law | S23: Working Group | U23: Change | W23: Current Law | Z23: Working Group | AC23: Change | AH23: =AM23 -> 1262.6 | AK23: NTC | AL23: =AL22*0.01 -> 456 | AM23: =AM22*0.01 -> 1262.6
G24: RMV | H24: NTC | I24: Combined | J24: RMV | K24: NTC | L24: Combined | M24: RMV | N24: NTC | O24: Combined | P24: Percent | Q24: NTC | R24: RMV | S24: NTC | T24: RMV | U24: NTC | V24: RMV | W24: NTC | X24: RMV | Y24: Total | Z24: NTC | AA24: RMV | AB24: Total | AC24: NTC | AD24: RMV | AE24: Total | AF24: Alt Fac Aid | AH24: =+"+ "&+V16&" *" -> + N *
D25: Strata | E25: ANTC | F25: RMV | G25: Levy | H25: Levy | I25: Levy | J25: Levy | K25: Levy | L25: Levy | M25: Levy | N25: Levy | O25: Levy | P25: Change | Q25: Tax Rate | R25: Tax Rate | S25: Tax Rate | T25: Tax Rate | U25: Tax Rate | V25: Tax Rate | W25: Levies | X25: Levies | Y25: Levies | Z25: Levies | AA25: Levies | AB25: Levies | AC25: Levies | AD25: Levies | AE25: Levies | AF25: Realloc | AH25: =AH20 -> 150000
C27: TOTAL | E27: 5809934989 | F27: 446467719794 | G27: 8.614933e+08 | H27: 1.1123045e+09 | I27: 1.9737978e+09 | J27: 8.614933e+08 | K27: 1.1123045e+09 | L27: 1.9737978e+09 | M27: 0 | N27: 0.13811898 | O27: 0.13812184 | P27: 6.9977708e-11 | Q27: 0.19144869 | R27: 0.0019295758 | S27: 0.19144869 | T27: 0.0019295758 | U27: 2.37729e-11 | V27: 0 | W27: 241.72312 | X27: 192.95758 | Y27: 434.6807 | Z27: 241.72312 | AA27: 192.95758 | AB27: 434.6807 | AC27: 3.0015656e-08 | AD27: 0 | AE27: 3.0015826e-08 | AF27: =SUM(AF38:AF524) -> 0.13811943 | AG27: =Q27*AH$23+R27*AH$25 -> 531.15949 | AH27: =U27*$AH$23+V27*$AH$25 -> 3.0015664e-08
A29: MPLS & ST PAUL | D29: 1 | E29: 629854107 | F29: 54702053930 | G29: 1.1166462e+08 | H29: 1.1150431e+08 | I29: 2.2316893e+08 | J29: 1.2429691e+08 | K29: 1.0382106e+08 | L29: 2.2811797e+08 | M29: 12632294 | N29: -7683250.8 | O29: 4949043.1 | P29: 0.022176219 | Q29: 0.17703196 | R29: 0.002041324 | S29: 0.1648335 | T29: 0.0022722531 | U29: -0.012198461 | V29: 0.00023092906 | W29: 223.52056 | X29: 204.1324 | Y29: 427.65296 | Z29: 208.11878 | AA29: 227.22531 | AB29: 435.34409 | AC29: -15.401777 | AD29: 23.092906 | AE29: 7.691129 | AF29: =SUMIF($D$38:$D$524,$D29,AF$38:AF$524) -> -67392.962 | AG29: =Q29*AH$23+R29*AH$25 -> 529.71916 | AH29: =U29*$AH$23+V29*$AH$25 -> 19.237582 | AI29: =AG29+AH29 -> 548.95674
A30: OTHER METRO, INNER | D30: 2 | E30: 708687241 | F30: 64040730650 | G30: 1.3626344e+08 | H30: 1.5243165e+08 | I30: 2.8869509e+08 | J30: 1.420605e+08 | K30: 1.5333128e+08 | L30: 2.9539178e+08 | M30: 5797058.7 | N30: 899633.23 | O30: 6696691.9 | P30: 0.023196418 | Q30: 0.21509016 | R30: 0.0021277621 | S30: 0.21635959 | T30: 0.0022182835 | U30: 0.0012694362 | V30: 9.0521433e-05 | W30: 271.57283 | X30: 212.77621 | Y30: 484.34904 | Z30: 273.17562 | AA30: 221.82835 | AB30: 495.00397 | AC30: 1.6027901 | AD30: 9.0521433 | AE30: 10.654933 | AF30: =SUMIF($D$38:$D$524,$D30,AF$38:AF$524) -> 900000 | AG30: =Q30*AH$23+R30*AH$25 -> 590.73715 | AH30: =U30*$AH$23+V30*$AH$25 -> 15.181005 | AI30: =AG30+AH30 -> 605.91815
A31: OTHER METRO, OUTER | D31: 3 | E31: 1845195167 | F31: 167005606150 | G31: 3.7876676e+08 | H31: 4.0302731e+08 | I31: 7.8179407e+08 | J31: 3.6732661e+08 | K31: 4.0299757e+08 | L31: 7.7032418e+08 | M31: -11440149 | N31: -29745.951 | O31: -11469895 | P31: -0.014671248 | Q31: 0.21841988 | R31: 0.0022679883 | S31: 0.21840376 | T31: 0.0021994867 | U31: -1.6120761e-05 | V31: -6.8501584e-05 | W31: 275.77694 | X31: 226.79883 | Y31: 502.57577 | Z31: 275.75659 | AA31: 219.94867 | AB31: 495.70526 | AC31: -0.020354073 | AD31: -6.8501584 | AE31: -6.8705125 | AF31: =SUMIF($D$38:$D$524,$D31,AF$38:AF$524) -> -341654.64 | AG31: =Q31*AH$23+R31*AH$25 -> 615.97519 | AH31: =U31*$AH$23+V31*$AH$25 -> -10.295592 | AI31: =AG31+AH31 -> 605.6796
A32: NONMET>=2K | D32: 4 | E32: 1124049513 | F32: 90056082950 | G32: 1.2264149e+08 | H32: 2.2391101e+08 | I32: 3.4655251e+08 | J32: 1.2148112e+08 | K32: 2.2068104e+08 | L32: 3.4216217e+08 | M32: -1160367.7 | N32: -3229968.2 | O32: -4390335.9 | P32: -0.012668602 | Q32: 0.19920031 | R32: 0.0013618346 | S32: 0.1963268 | T32: 0.0013489497 | U32: -0.0028735106 | V32: -1.2884945e-05 | W32: 251.51031 | X32: 136.18346 | Y32: 387.69378 | Z32: 247.88222 | AA32: 134.89497 | AB32: 382.77719 | AC32: -3.6280945 | AD32: -1.2884945 | AE32: -4.916589 | AF32: =SUMIF($D$38:$D$524,$D32,AF$38:AF$524) -> -490952.26 | AG32: =Q32*AH$23+R32*AH$25 -> 455.78551 | AH32: =U32*$AH$23+V32*$AH$25 -> -5.5608362 | AI32: =AG32+AH32 -> 450.22467
A33: NONMET 1K-2K | D33: 5 | E33: 648164533 | F33: 38252675709 | G33: 50760914 | H33: 1.1450978e+08 | I33: 1.6527069e+08 | J33: 48789200 | K33: 1.1715126e+08 | L33: 1.6594046e+08 | M33: -1971713.4 | N33: 2641482.6 | O33: 669769.23 | P33: 0.004052559 | Q33: 0.17666777 | R33: 0.0013269899 | S33: 0.18074309 | T33: 0.0012754454 | U33: 0.0040753273 | V33: -5.1544456e-05 | W33: 223.06072 | X33: 132.69899 | Y33: 355.75971 | Z33: 228.20623 | AA33: 127.54454 | AB33: 355.75077 | AC33: 5.1455082 | AD33: -5.1544456 | AE33: -0.0089374013 | AF33: =SUMIF($D$38:$D$524,$D33,AF$38:AF$524) -> 0 | AG33: =Q33*AH$23+R33*AH$25 -> 422.1092 | AH33: =U33*$AH$23+V33*$AH$25 -> -2.5861602 | AI33: =AG33+AH33 -> 419.52304
A34: NONMET < 1K | D34: 6 | E34: 853984428 | F34: 32410570405 | G34: 61396076 | H34: 1.0626052e+08 | I34: 1.676566e+08 | J34: 57538953 | K34: 1.143854e+08 | L34: 1.7192435e+08 | M34: -3857123 | N34: 8124881.5 | O34: 4267758.5 | P34: 0.025455357 | Q34: 0.12442911 | R34: 0.0018943226 | S34: 0.13394319 | T34: 0.0017753144 | U34: 0.0095140863 | V34: -0.00011900818 | W34: 157.10419 | X34: 189.43226 | Y34: 346.53645 | Z34: 169.11668 | AA34: 177.53144 | AB34: 346.64812 | AC34: 12.012485 | AD34: -11.900818 | AE34: 0.1116672 | AF34: =SUMIF($D$38:$D$524,$D34,AF$38:AF$524) -> 0 | AG34: =Q34*AH$23+R34*AH$25 -> 441.25258 | AH34: =U34*$AH$23+V34*$AH$25 -> -5.8387419 | AI34: =AG34+AH34 -> 435.41384
A35: CHARTER | D35: 7 | E35: 0 | F35: 0 | G35: 0 | H35: 0 | I35: 0 | J35: 0 | K35: 0 | L35: 0 | M35: 0 | N35: 0 | O35: 0 | P35: #DIV/0! | Q35: #DIV/0! | R35: #DIV/0! | S35: #DIV/0! | T35: #DIV/0! | U35: #DIV/0! | V35: #DIV/0! | W35: #DIV/0! | X35: #DIV/0! | Y35: #DIV/0! | Z35: #DIV/0! | AA35: #DIV/0! | AB35: #DIV/0! | AC35: #DIV/0! | AD35: #DIV/0! | AE35: #DIV/0! | AF35: =SUMIF($D$38:$D$524,$D35,AF$38:AF$524) -> 0 | AG35: =Q35*AH$23+R35*AH$25 -> #DIV/0! | AH35: =U35*$AH$23+V35*$AH$25 -> #DIV/0! | AI35: =AG35+AH35 -> #DIV/0!
A36: NONCHARTER FUDGE | D36: 8 | E36: 0 | F36: 0 | G36: 0 | H36: 659887.44 | I36: 659887.44 | J36: 0 | K36: -63144.78 | L36: -63144.78 | M36: 0 | N36: -723032.22 | O36: -723032.22 | P36: -1.0956902 | Q36: #DIV/0! | R36: #DIV/0! | S36: #DIV/0! | T36: #DIV/0! | U36: #DIV/0! | V36: #DIV/0! | W36: #DIV/0! | X36: #DIV/0! | Y36: #DIV/0! | Z36: #DIV/0! | AA36: #DIV/0! | AB36: #DIV/0! | AC36: #DIV/0! | AD36: #DIV/0! | AE36: #DIV/0! | AF36: =SUMIF($D$38:$D$524,$D36,AF$38:AF$524) -> 0 | AG36: =Q36*AH$23+R36*AH$25 -> #DIV/0! | AH36: =U36*$AH$23+V36*$AH$25 -> #DIV/0! | AI36: =AG36+AH36 -> #DIV/0!
A38: 1 | B38: 1 | C38: AITKIN | D38: 5 | E38: 18259188 | F38: 832399770 | G38: 349806.14 | H38: 493777.8 | I38: 843583.94 | J38: 670435.27 | K38: 882874.92 | L38: 1553310.2 | M38: 320629.13 | N38: 389097.12 | O38: 709726.25 | P38: 0.84132262 | Q38: 0.027042703 | R38: 0.00042023815 | S38: 0.048352365 | T38: 0.00080542462 | U38: 0.021309662 | V38: 0.00038518647 | W38: 34.144117 | X38: 42.023815 | Y38: 76.167932 | Z38: 61.049696 | AA38: 80.542462 | AB38: 141.59216 | AC38: 26.905579 | AD38: 38.518647 | AE38: 65.424226 | AF38: =-SUMIF('[1]Alt Fac'!$A$18:$A$139,'REPORT 4 - PROPERTY TAX'!A38,'[1]Alt Fac'!$U$18:$U$139) -> 0 | AG38: =Q38*AH$23+R38*AH$25 -> 97.179839 | AH38: =U38*$AH$23+V38*$AH$25 -> 84.683549 | AI38: =AG38+AH38 -> 181.86339
A39: 1.2 | B39: 3 | C39: MINNEAPOLIS | D39: 1 | E39: 388311447 | F39: 34734592730 | G39: 75438187 | H39: 64403597 | I39: 1.3984178e+08 | J39: 85912922 | K39: 58876387 | L39: 1.4478931e+08 | M39: 10474736 | N39: -5527209.9 | O39: 4947525.6 | P39: 0.035379452 | Q39: 0.16585552 | R39: 0.002171846 | S39: 0.15162156 | T39: 0.002473411 | U39: -0.014233961 | V39: 0.00030156494 | W39: 209.40918 | X39: 217.1846 | Y39: 426.59378 | Z39: 191.43738 | AA39: 247.3411 | AB39: 438.77848 | AC39: -17.971799 | AD39: 30.156494 | AE39: 12.184696 | AF39: =-SUMIF('[1]Alt Fac'!$A$18:$A$139,'REPORT 4 - PROPERTY TAX'!A39,'[1]Alt Fac'!$U$18:$U$139) -> -2218396.1 | AG39: =Q39*AH$23+R39*AH$25 -> 535.18608 | AH39: =U39*$AH$23+V39*$AH$25 -> 27.262943 | AI39: =AG39+AH39 -> 562.44902
A40: 2 | B40: 1 | C40: HILL CITY | D40: 6 | E40: 1589511 | F40: 81131225 | G40: 36295.8 | H40: 290515.58 | I40: 326811.38 | J40: 65345.088 | K40: 302537 | L40: 367882.09 | M40: 29049.288 | N40: 12021.421 | O40: 41070.709 | P40: 0.12567099 | Q40: 0.18277041 | R40: 0.00044737153 | S40: 0.19033338 | T40: 0.00080542464 | U40: 0.007562968 | V40: 0.00035805312 | W40: 230.76592 | X40: 44.737153 | Y40: 275.50307 | Z40: 240.31492 | AA40: 80.542464 | AB40: 320.85739 | AC40: 9.5490034 | AD40: 35.805312 | AE40: 45.354315 | AF40: =-SUMIF('[1]Alt Fac'!$A$18:$A$139,'REPORT 4 - PROPERTY TAX'!A40,'[1]Alt Fac'!$U$18:$U$139) -> 0 | AG40: =Q40*AH$23+R40*AH$25 -> 297.87165 | AH40: =U40*$AH$23+V40*$AH$25 -> 63.256971 | AI40: =AG40+AH40 -> 361.12862
A41: 4 | B41: 1 | C41: MCGREGOR | D41: 6 | E41: 9847758 | F41: 324940018 | G41: 69670.59 | H41: 968963.17 | I41: 1038633.8 | J41: 254656.4 | K41: 1176714.6 | L41: 1431371 | M41: 184985.81 | N41: 207751.41 | O41: 392737.22 | P41: 0.37812869 | Q41: 0.098394291 | R41: 0.00021441062 | S41: 0.11949061 | T41: 0.00078370279 | U41: 0.021096315 | V41: 0.00056929217 | W41: 124.23263 | X41: 21.441062 | Y41: 145.67369 | Z41: 150.86884 | AA41: 78.370279 | AB41: 229.23912 | AC41: 26.636208 | AD41: 56.929217 | AE41: 83.565425 | AF41: =-SUMIF('[1]Alt Fac'!$A$18:$A$139,'REPORT 4 - PROPERTY TAX'!A41,'[1]Alt Fac'!$U$18:$U$139) -> 0 | AG41: =Q41*AH$23+R41*AH$25 -> 156.39422 | AH41: =U41*$AH$23+V41*$AH$25 -> 112.03003 | AI41: =AG41+AH41 -> 268.42426
A42: 6 | B42: 3 | C42: SOUTH ST. PAUL | D42: 2 | E42: 15767204 | F42: 1329568050 | G42: 3479364.5 | H42: 2995297.1 | I42: 6474661.6 | J42: 2512140.9 | K42: 2623860.5 | L42: 5136001.4 | M42: -967223.58 | N42: -371436.64 | O42: -1338660.2 | P42: -0.20675369 | Q42: 0.18997009 | R42: 0.0026169134 | S42: 0.16641254 | T42: 0.0018894414 | U42: -0.023557546 | V42: -0.00072747204 | W42: 239.85623 | X42: 261.69134 | Y42: 501.54758 | Z42: 210.11248 | AA42: 188.94414 | AB42: 399.05662 | AC42: -29.743758 | AD42: -72.747204 | AE42: -102.49096 | AF42: =-SUMIF('[1]Alt Fac'!$A$18:$A$139,'REPORT 4 - PROPERTY TAX'!A42,'[1]Alt Fac'!$U$18:$U$139) -> 0 | AG42: =Q42*AH$23+R42*AH$25 -> 632.39325 | AH42: =U42*$AH$23+V42*$AH$25 -> -138.86456 | AI42: =AG42+AH42 -> 493.52869
A43: 11 | B43: 1 | C43: ANOKA-HENNEPIN | D43: 3 | E43: 187404610 | F43: 17436117350 | G43: 54540513 | H43: 34667660 | I43: 89208173 | J43: 43863641 | K43: 34464834 | L43: 78328475 | M43: -10676872 | N43: -202826.63 | O43: -10879699 | P43: -0.12195854 | Q43: 0.1849883 | R43: 0.0031280194 | S43: 0.18390601 | T43: 0.0025156771 | U43: -0.0010822926 | V43: -0.00061234228 | W43: 233.56623 | X43: 312.80194 | Y43: 546.36817 | Z43: 232.19973 | AA43: 251.56771 | AB43: 483.76743 | AC43: -1.3665027 | AD43: -61.234228 | AE43: -62.600731 | AF43: =-SUMIF('[1]Alt Fac'!$A$18:$A$139,'REPORT 4 - PROPERTY TAX'!A43,'[1]Alt Fac'!$U$18:$U$139) -> 610295 | AG43: =Q43*AH$23+R43*AH$25 -> 702.76913 | AH43: =U43*$AH$23+V43*$AH$25 -> -93.217845 | AI43: =AG43+AH43 -> 609.55129
A44: 12 | B44: 1 | C44: CENTENNIAL | D44: 3 | E44: 28966785 | F44: 2673246800 | G44: 6472474.3 | H44: 9196163.1 | I44: 15668637 | J44: 4729318.4 | K44: 9111819 | L44: 13841137 | M44: -1743155.9 | N44: -84344.122 | O44: -1827500 | P44: -0.11663427 | Q44: 0.31747269 | R44: 0.0024212034 | S44: 0.31456094 | T44: 0.001769129 | U44: -0.002911753 | V44: -0.00065207445 | W44: 400.84102 | X44: 242.12034 | Y44: 642.96136 | Z44: 397.16464 | AA44: 176.9129 | AB44: 574.07754 | AC44: -3.6763793 | AD44: -65.207445 | AE44: -68.883824 | AF44: =-SUMIF('[1]Alt Fac'!$A$18:$A$139,'REPORT 4 - PROPERTY TAX'!A44,'[1]Alt Fac'!$U$18:$U$139) -> 0 | AG44: =Q44*AH$23+R44*AH$25 -> 764.02153 | AH44: =U44*$AH$23+V44*$AH$25 -> -101.48755 | AI44: =AG44+AH44 -> 662.53398
A45: 13 | B45: 1 | C45: COLUMBIA HEIGHTS | D45: 2 | E45: 19762462 | F45: 1729165900 | G45: 3616710.8 | H45: 4321302.5 | I45: 7938013.3 | J45: 3383044.5 | K45: 3974560.1 | L45: 7357604.5 | M45: -233666.35 | N45: -346742.43 | O45: -580408.78 | P45: -0.073117638 | Q45: 0.21866215 | R45: 0.0020915927 | S45: 0.20111664 | T45: 0.0019564603 | U45: -0.017545508 | V45: -0.00013513241 | W45: 276.08283 | X45: 209.15927 | Y45: 485.24211 | Z45: 253.92988 | AA45: 195.64603 | AB45: 449.57591 | AC45: -22.152958 | AD45: -13.513241 | AE45: -35.666199 | AF45: =-SUMIF('[1]Alt Fac'!$A$18:$A$139,'REPORT 4 - PROPERTY TAX'!A45,'[1]Alt Fac'!$U$18:$U$139) -> 0 | AG45: =Q45*AH$23+R45*AH$25 -> 589.82174 | AH45: =U45*$AH$23+V45*$AH$25 -> -42.422819 | AI45: =AG45+AH45 -> 547.39892
A46: 14 | B46: 1 | C46: FRIDLEY | D46: 3 | E46: 13615367 | F46: 1131944200 | G46: 2874947.2 | H46: 3958773.5 | I46: 6833720.7 | J46: 1916053.5 | K46: 3495443.6 | L46: 5411497.1 | M46: -958893.65 | N46: -463329.97 | O46: -1422223.6 | P46: -0.20811849 | Q46: 0.29075776 | R46: 0.0025398312 | S46: 0.25672783 | T46: 0.0016927102 | U46: -0.034029928 | V46: -0.00084712096 | W46: 367.11074 | X46: 253.98312 | Y46: 621.09386 | Z46: 324.14455 | AA46: 169.27102 | AB46: 493.41558 | AC46: -42.966188 | AD46: -84.712096 | AE46: -127.67828 | AF46: =-SUMIF('[1]Alt Fac'!$A$18:$A$139,'REPORT 4 - PROPERTY TAX'!A46,'[1]Alt Fac'!$U$18:$U$139) -> 0 | AG46: =Q46*AH$23+R46*AH$25 -> 748.08542 | AH46: =U46*$AH$23+V46*$AH$25 -> -170.03433 | AI46: =AG46+AH46 -> 578.05109
A47: 15 | B47: 1 | C47: ST. FRANCIS | D47: 3 | E47: 27669124 | F47: 2375466900 | G47: 2532537.4 | H47: 7545139.3 | I47: 10077677 | J47: 2471545.6 | K47: 7717772.8 | L47: 10189318 | M47: -60991.897 | N47: 172633.59 | O47: 111641.7 | P47: 0.011078119 | Q47: 0.27269166 | R47: 0.001066122 | S47: 0.27893087 | T47: 0.0010404462 | U47: 0.0062392143 | V47: -2.5675751e-05 | W47: 344.30049 | X47: 106.6122 | Y47: 450.91268 | Z47: 352.17812 | AA47: 104.04462 | AB47: 456.22274 | AC47: 7.877632 | AD47: -2.5675751 | AE47: 5.3100569 | AF47: =-SUMIF('[1]Alt Fac'!$A$18:$A$139,'REPORT 4 - PROPERTY TAX'!A47,'[1]Alt Fac'!$U$18:$U$139) -> 0 | AG47: =Q47*AH$23+R47*AH$25 -> 504.21878 | AH47: =U47*$AH$23+V47*$AH$25 -> 4.0262693 | AI47: =AG47+AH47 -> 508.24505
A48: 16 | B48: 1 | C48: SPRING LAKE PARK | D48: 3 | E48: 36240993 | F48: 3124028600 | G48: 5908960.6 | H48: 12102804 | I48: 18011765 | J48: 5547209.4 | K48: 12003898 | L48: 17551107 | M48: -361751.22 | N48: -98906.532 | O48: -460657.75 | P48: -0.025575381 | Q48: 0.33395344 | R48: 0.0018914554 | S48: 0.3312243 | T48: 0.001775659 | U48: -0.0027291342 | V48: -0.00011579639 | W48: 421.64961 | X48: 189.14554 | Y48: 610.79514 | Z48: 418.2038 | AA48: 177.5659 | AB48: 595.7697 | AC48: -3.4458048 | AD48: -11.579639 | AE48: -15.025443 | AF48: =-SUMIF('[1]Alt Fac'!$A$18:$A$139,'REPORT 4 - PROPERTY TAX'!A48,'[1]Alt Fac'!$U$18:$U$139) -> 0 | AG48: =Q48*AH$23+R48*AH$25 -> 705.36791 | AH48: =U48*$AH$23+V48*$AH$25 -> -20.815263 | AI48: =AG48+AH48 -> 684.55265
A49: 22 | B49: 1 | C49: DETROIT LAKES | D49: 4 | E49: 20668172 | F49: 1391529800 | G49: 1710613.9 | H49: 1842850.9 | I49: 3553464.8 | J49: 1527759.1 | K49: 1969642 | L49: 3497401.1 | M49: -182854.8 | N49: 126791.12 | O49: -56063.685 | P49: -0.015777189 | Q49: 0.08916371 | R49: 0.0012293045 | S49: 0.095298317 | T49: 0.0010978989 | U49: 0.0061346073 | V49: -0.0001314056 | W49: 112.5781 | X49: 122.93045 | Y49: 235.50855 | Z49: 120.32365 | AA49: 109.78989 | AB49: 230.11355 | AC49: 7.7455552 | AD49: -13.14056 | AE49: -5.3950045 | AF49: =-SUMIF('[1]Alt Fac'!$A$18:$A$139,'REPORT 4 - PROPERTY TAX'!A49,'[1]Alt Fac'!$U$18:$U$139) -> 0 | AG49: =Q49*AH$23+R49*AH$25 -> 296.97378 | AH49: =U49*$AH$23+V49*$AH$25 -> -11.965284 | AI49: =AG49+AH49 -> 285.00849
... A373: 2905 | B373: 1 | C373: TRI-CITY | D373: 5 | E373: 11827712 | F373: 876260225 | G373: 999821.89 | H373: 4047878 | I373: 5047699.9 | J373: 1045653.2 | K373: 3997077.4 | L373: 5042730.6 | M373: 45831.347 | N373: -50800.676 | O373: -4969.3283 | P373: -0.0009844738 | Q373: 0.34223678 | R373: 0.0011410102 | S373: 0.33794172 | T373: 0.0011933136 | U373: -0.0042950552 | V373: 5.2303352e-05 | W373: 432.10816 | X373: 114.10102 | Y373: 546.20918 | Z373: 426.68522 | AA373: 119.33136 | AB373: 546.01658 | AC373: -5.4229367 | AD373: 5.2303352 | AE373: -0.19260143 | AF373: =-SUMIF('[1]Alt Fac'!$A$18:$A$139,'REPORT 4 - PROPERTY TAX'!A373,'[1]Alt Fac'!$U$18:$U$139) -> 0 | AG373: =Q373*AH$23+R373*AH$25 -> 603.25969 | AH373: =U373*$AH$23+V373*$AH$25 -> 2.4225662 | AI373: =AG373+AH373 -> 605.68226
A374: 4000 | B374: 7 | C374: CITY ACADEMY | D374: 7 | E374: 0 | F374: 0 | G374: 0 | H374: 0 | I374: 0 | J374: 0 | K374: 0 | L374: 0 | M374: 0 | N374: 0 | O374: 0 | P374: #DIV/0! | Q374: 0 | R374: 0 | S374: 0 | T374: 0 | U374: 0 | V374: 0 | W374: 0 | X374: 0 | Y374: 0 | Z374: 0 | AA374: 0 | AB374: 0 | AC374: 0 | AD374: 0 | AE374: 0 | AF374: =-SUMIF('[1]Alt Fac'!$A$18:$A$139,'REPORT 4 - PROPERTY TAX'!A374,'[1]Alt Fac'!$U$18:$U$139) -> 0 | AG374: =Q374*AH$23+R374*AH$25 -> 0 | AH374: =U374*$AH$23+V374*$AH$25 -> 0 | AI374: =AG374+AH374 -> 0
A375: 4001 | B375: 7 | C375: BLUFFVIEW MONTESSORI | D375: 7 | E375: 0 | F375: 0 | G375: 0 | H375: 0 | I375: 0 | J375: 0 | K375: 0 | L375: 0 | M375: 0 | N375: 0 | O375: 0 | P375: #DIV/0! | Q375: 0 | R375: 0 | S375: 0 | T375: 0 | U375: 0 | V375: 0 | W375: 0 | X375: 0 | Y375: 0 | Z375: 0 | AA375: 0 | AB375: 0 | AC375: 0 | AD375: 0 | AE375: 0 | AF375: =-SUMIF('[1]Alt Fac'!$A$18:$A$139,'REPORT 4 - PROPERTY TAX'!A375,'[1]Alt Fac'!$U$18:$U$139) -> 0 | AG375: =Q375*AH$23+R375*AH$25 -> 0 | AH375: =U375*$AH$23+V375*$AH$25 -> 0 | AI375: =AG375+AH375 -> 0
A376: 4003 | B376: 7 | C376: NEW HEIGHTS SCHOOL, INC. | D376: 7 | E376: 0 | F376: 0 | G376: 0 | H376: 0 | I376: 0 | J376: 0 | K376: 0 | L376: 0 | M376: 0 | N376: 0 | O376: 0 | P376: #DIV/0! | Q376: 0 | R376: 0 | S376: 0 | T376: 0 | U376: 0 | V376: 0 | W376: 0 | X376: 0 | Y376: 0 | Z376: 0 | AA376: 0 | AB376: 0 | AC376: 0 | AD376: 0 | AE376: 0 | AF376: =-SUMIF('[1]Alt Fac'!$A$18:$A$139,'REPORT 4 - PROPERTY TAX'!A376,'[1]Alt Fac'!$U$18:$U$139) -> 0 | AG376: =Q376*AH$23+R376*AH$25 -> 0 | AH376: =U376*$AH$23+V376*$AH$25 -> 0 | AI376: =AG376+AH376 -> 0
A377: 4004 | B377: 7 | C377: CEDAR RIVERSIDE COMMUNITY SCHOOL | D377: 7 | E377: 0 | F377: 0 | G377: 0 | H377: 0 | I377: 0 | J377: 0 | K377: 0 | L377: 0 | M377: 0 | N377: 0 | O377: 0 | P377: #DIV/0! | Q377: 0 | R377: 0 | S377: 0 | T377: 0 | U377: 0 | V377: 0 | W377: 0 | X377: 0 | Y377: 0 | Z377: 0 | AA377: 0 | AB377: 0 | AC377: 0 | AD377: 0 | AE377: 0 | AF377: =-SUMIF('[1]Alt Fac'!$A$18:$A$139,'REPORT 4 - PROPERTY TAX'!A377,'[1]Alt Fac'!$U$18:$U$139) -> 0 | AG377: =Q377*AH$23+R377*AH$25 -> 0 | AH377: =U377*$AH$23+V377*$AH$25 -> 0 | AI377: =AG377+AH377 -> 0
A378: 4005 | B378: 7 | C378: METRO DEAF SCHOOL | D378: 7 | E378: 0 | F378: 0 | G378: 0 | H378: 0 | I378: 0 | J378: 0 | K378: 0 | L378: 0 | M378: 0 | N378: 0 | O378: 0 | P378: #DIV/0! | Q378: 0 | R378: 0 | S378: 0 | T378: 0 | U378: 0 | V378: 0 | W378: 0 | X378: 0 | Y378: 0 | Z378: 0 | AA378: 0 | AB378: 0 | AC378: 0 | AD378: 0 | AE378: 0 | AF378: =-SUMIF('[1]Alt Fac'!$A$18:$A$139,'REPORT 4 - PROPERTY TAX'!A378,'[1]Alt Fac'!$U$18:$U$139) -> 0 | AG378: =Q378*AH$23+R378*AH$25 -> 0 | AH378: =U378*$AH$23+V378*$AH$25 -> 0 | AI378: =AG378+AH378 -> 0
A379: 4007 | B379: 7 | C379: MINNESOTA NEW COUNTRY SCHOOL | D379: 7 | E379: 0 | F379: 0 | G379: 0 | H379: 0 | I379: 0 | J379: 0 | K379: 0 | L379: 0 | M379: 0 | N379: 0 | O379: 0 | P379: #DIV/0! | Q379: 0 | R379: 0 | S379: 0 | T379: 0 | U379: 0 | V379: 0 | W379: 0 | X379: 0 | Y379: 0 | Z379: 0 | AA379: 0 | AB379: 0 | AC379: 0 | AD379: 0 | AE379: 0 | AF379: =-SUMIF('[1]Alt Fac'!$A$18:$A$139,'REPORT 4 - PROPERTY TAX'!A379,'[1]Alt Fac'!$U$18:$U$139) -> 0 | AG379: =Q379*AH$23+R379*AH$25 -> 0 | AH379: =U379*$AH$23+V379*$AH$25 -> 0 | AI379: =AG379+AH379 -> 0
A380: 4008 | B380: 7 | C380: PACT CHARTER SCHOOL | D380: 7 | E380: 0 | F380: 0 | G380: 0 | H380: 0 | I380: 0 | J380: 0 | K380: 0 | L380: 0 | M380: 0 | N380: 0 | O380: 0 | P380: #DIV/0! | Q380: 0 | R380: 0 | S380: 0 | T380: 0 | U380: 0 | V380: 0 | W380: 0 | X380: 0 | Y380: 0 | Z380: 0 | AA380: 0 | AB380: 0 | AC380: 0 | AD380: 0 | AE380: 0 | AF380: =-SUMIF('[1]Alt Fac'!$A$18:$A$139,'REPORT 4 - PROPERTY TAX'!A380,'[1]Alt Fac'!$U$18:$U$139) -> 0 | AG380: =Q380*AH$23+R380*AH$25 -> 0 | AH380: =U380*$AH$23+V380*$AH$25 -> 0 | AI380: =AG380+AH380 -> 0
A381: 4011 | B381: 7 | C381: NEW VISIONS CHARTER SCHOOL | D381: 7 | E381: 0 | F381: 0 | G381: 0 | H381: 0 | I381: 0 | J381: 0 | K381: 0 | L381: 0 | M381: 0 | N381: 0 | O381: 0 | P381: #DIV/0! | Q381: 0 | R381: 0 | S381: 0 | T381: 0 | U381: 0 | V381: 0 | W381: 0 | X381: 0 | Y381: 0 | Z381: 0 | AA381: 0 | AB381: 0 | AC381: 0 | AD381: 0 | AE381: 0 | AF381: =-SUMIF('[1]Alt Fac'!$A$18:$A$139,'REPORT 4 - PROPERTY TAX'!A381,'[1]Alt Fac'!$U$18:$U$139) -> 0 | AG381: =Q381*AH$23+R381*AH$25 -> 0 | AH381: =U381*$AH$23+V381*$AH$25 -> 0 | AI381: =AG381+AH381 -> 0
A382: 4015 | B382: 7 | C382: COMMUNITY OF PEACE ACADEMY | D382: 7 | E382: 0 | F382: 0 | G382: 0 | H382: 0 | I382: 0 | J382: 0 | K382: 0 | L382: 0 | M382: 0 | N382: 0 | O382: 0 | P382: #DIV/0! | Q382: 0 | R382: 0 | S382: 0 | T382: 0 | U382: 0 | V382: 0 | W382: 0 | X382: 0 | Y382: 0 | Z382: 0 | AA382: 0 | AB382: 0 | AC382: 0 | AD382: 0 | AE382: 0 | AF382: =-SUMIF('[1]Alt Fac'!$A$18:$A$139,'REPORT 4 - PROPERTY TAX'!A382,'[1]Alt Fac'!$U$18:$U$139) -> 0 | AG382: =Q382*AH$23+R382*AH$25 -> 0 | AH382: =U382*$AH$23+V382*$AH$25 -> 0 | AI382: =AG382+AH382 -> 0
A383: 4016 | B383: 7 | C383: WORLD LEARNER CHARTER SCHOOL | D383: 7 | E383: 0 | F383: 0 | G383: 0 | H383: 0 | I383: 0 | J383: 0 | K383: 0 | L383: 0 | M383: 0 | N383: 0 | O383: 0 | P383: #DIV/0! | Q383: 0 | R383: 0 | S383: 0 | T383: 0 | U383: 0 | V383: 0 | W383: 0 | X383: 0 | Y383: 0 | Z383: 0 | AA383: 0 | AB383: 0 | AC383: 0 | AD383: 0 | AE383: 0 | AF383: =-SUMIF('[1]Alt Fac'!$A$18:$A$139,'REPORT 4 - PROPERTY TAX'!A383,'[1]Alt Fac'!$U$18:$U$139) -> 0 | AG383: =Q383*AH$23+R383*AH$25 -> 0 | AH383: =U383*$AH$23+V383*$AH$25 -> 0 | AI383: =AG383+AH383 -> 0
A384: 4017 | B384: 7 | C384: MINNESOTA TRANSITIONS CHARTER SCH | D384: 7 | E384: 0 | F384: 0 | G384: 0 | H384: 0 | I384: 0 | J384: 0 | K384: 0 | L384: 0 | M384: 0 | N384: 0 | O384: 0 | P384: #DIV/0! | Q384: 0 | R384: 0 | S384: 0 | T384: 0 | U384: 0 | V384: 0 | W384: 0 | X384: 0 | Y384: 0 | Z384: 0 | AA384: 0 | AB384: 0 | AC384: 0 | AD384: 0 | AE384: 0 | AF384: =-SUMIF('[1]Alt Fac'!$A$18:$A$139,'REPORT 4 - PROPERTY TAX'!A384,'[1]Alt Fac'!$U$18:$U$139) -> 0 | AG384: =Q384*AH$23+R384*AH$25 -> 0 | AH384: =U384*$AH$23+V384*$AH$25 -> 0 | AI384: =AG384+AH384 -> 0
A385: 4018 | B385: 7 | C385: ACHIEVE LANGUAGE ACADEMY | D385: 7 | E385: 0 | F385: 0 | G385: 0 | H385: 0 | I385: 0 | J385: 0 | K385: 0 | L385: 0 | M385: 0 | N385: 0 | O385: 0 | P385: #DIV/0! | Q385: 0 | R385: 0 | S385: 0 | T385: 0 | U385: 0 | V385: 0 | W385: 0 | X385: 0 | Y385: 0 | Z385: 0 | AA385: 0 | AB385: 0 | AC385: 0 | AD385: 0 | AE385: 0 | AF385: =-SUMIF('[1]Alt Fac'!$A$18:$A$139,'REPORT 4 - PROPERTY TAX'!A385,'[1]Alt Fac'!$U$18:$U$139) -> 0 | AG385: =Q385*AH$23+R385*AH$25 -> 0 | AH385: =U385*$AH$23+V385*$AH$25 -> 0 | AI385: =AG385+AH385 -> 0
... A521: 4209 | B521: 7 | C521: THE MASTERY SCHOOL | D521: 7 | E521: 0 | F521: 0 | G521: 0 | H521: 0 | I521: 0 | J521: 0 | K521: 0 | L521: 0 | M521: 0 | N521: 0 | O521: 0 | P521: #DIV/0! | Q521: 0 | R521: 0 | S521: 0 | T521: 0 | U521: 0 | V521: 0 | W521: 0 | X521: 0 | Y521: 0 | Z521: 0 | AA521: 0 | AB521: 0 | AC521: 0 | AD521: 0 | AE521: 0 | AF521: =-SUMIF('[1]Alt Fac'!$A$18:$A$139,'REPORT 4 - PROPERTY TAX'!A521,'[1]Alt Fac'!$U$18:$U$139) -> 0 | AG521: =Q521*AH$23+R521*AH$25 -> 0 | AH521: =U521*$AH$23+V521*$AH$25 -> 0 | AI521: =AG521+AH521 -> 0
A522: 6666 | B522: 8 | C522: FUDGE, DISTRICTS | D522: 8 | E522: 0 | F522: 0 | G522: 0 | H522: 659887.44 | I522: 659887.44 | J522: 0 | K522: -63144.78 | L522: -63144.78 | M522: 0 | N522: -723032.22 | O522: -723032.22 | P522: -1.0956902 | Q522: 0 | R522: 0 | S522: 0 | T522: 0 | U522: 0 | V522: 0 | W522: 0 | X522: 0 | Y522: 0 | Z522: 0 | AA522: 0 | AB522: 0 | AC522: 0 | AD522: 0 | AE522: 0 | AF522: =-SUMIF('[1]Alt Fac'!$A$18:$A$139,'REPORT 4 - PROPERTY TAX'!A522,'[1]Alt Fac'!$U$18:$U$139) -> 0 | AG522: =Q522*AH$23+R522*AH$25 -> 0 | AH522: =U522*$AH$23+V522*$AH$25 -> 0 | AI522: =AG522+AH522 -> 0
A523: 7777 | B523: 9 | C523: FUDGE, CHARTERS | D523: 7 | E523: 0 | F523: 0 | G523: 0 | H523: 0 | I523: 0 | J523: 0 | K523: 0 | L523: 0 | M523: 0 | N523: 0 | O523: 0 | P523: #DIV/0! | Q523: 0 | R523: 0 | S523: 0 | T523: 0 | U523: 0 | V523: 0 | W523: 0 | X523: 0 | Y523: 0 | Z523: 0 | AA523: 0 | AB523: 0 | AC523: 0 | AD523: 0 | AE523: 0 | AF523: =-SUMIF('[1]Alt Fac'!$A$18:$A$139,'REPORT 4 - PROPERTY TAX'!A523,'[1]Alt Fac'!$U$18:$U$139) -> 0 | AG523: =Q523*AH$23+R523*AH$25 -> 0 | AH523: =U523*$AH$23+V523*$AH$25 -> 0 | AI523: =AG523+AH523 -> 0
A524: 8888 | B524: 8 | C524: FUDGE, OTHER | D524: 8 | E524: 0 | F524: 0 | G524: 0 | H524: 0 | I524: 0 | J524: 0 | K524: 0 | L524: 0 | M524: 0 | N524: 0 | O524: 0 | P524: #DIV/0! | Q524: 0 | R524: 0 | S524: 0 | T524: 0 | U524: 0 | V524: 0 | W524: 0 | X524: 0 | Y524: 0 | Z524: 0 | AA524: 0 | AB524: 0 | AC524: 0 | AD524: 0 | AE524: 0 | AF524: =-SUMIF('[1]Alt Fac'!$A$18:$A$139,'REPORT 4 - PROPERTY TAX'!A524,'[1]Alt Fac'!$U$18:$U$139) -> 0 | AG524: =Q524*AH$23+R524*AH$25 -> 0 | AH524: =U524*$AH$23+V524*$AH$25 -> 0 | AI524: =AG524+AH524 -> 0
A525: 9999 | B525: 0 | C525: STATE TOTAL | D525: 0 | E525: 0 | F525: 0 | G525: 8.614933e+08 | H525: 1.1123045e+09 | I525: 1.9737978e+09 | J525: 8.614933e+08 | K525: 1.1123045e+09 | L525: 1.9737978e+09 | P525: 0 | Q525: #DIV/0! | R525: #DIV/0! | S525: #DIV/0! | T525: #DIV/0! | U525: #DIV/0! | V525: #DIV/0! | W525: #DIV/0! | X525: #DIV/0! | Y525: #DIV/0! | Z525: #DIV/0! | AA525: #DIV/0! | AB525: #DIV/0! | AC525: #DIV/0! | AD525: #DIV/0! | AE525: #DIV/0! | AF525: =-SUMIF('[1]Alt Fac'!$A$18:$A$139,'REPORT 4 - PROPERTY TAX'!A525,'[1]Alt Fac'!$U$18:$U$139) -> 0 | AG525: =Q525*AH$23+R525*AH$25 -> #DIV/0! | AH525: =U525*$AH$23+V525*$AH$25 -> #DIV/0! | AI525: =AG525+AH525 -> #DIV/0!

Sheet REPORT 5 - DEFERRED MAINTENANCE
A1: MDE / School Finance Division | R1: Note: Corrections made since November 11 Run | Y1: Revised | Z1: 41253
A2: PARAMETERS
A3: PARAMETERS
A4: PARAMETERS
A5: PARAMETERS
A6: PARAMETERS
A7: PARAMETERS
A8: PARAMETERS
A9: PARAMETERS
A11: Revenue, current | F11: 1 | G11: 1 | I11: 1 | J11: 1
A12: Revenue, proposed | H12: 1 | K12: 1 | L12: 1
A13: Levy, current
A14: Levy, proposed
F16: DH | G16: DP | H16: DR | I16: DV | J16: DT | K16: DV | L16: DX
C18: =[1]Summary!I179 -> 230 | P18: REPORT # 5: FACILITIES DEFERRED MAINTENANCE AND HEALTH & SAFETY ANALYSIS
P19: ALTERNATIVE FORMULA FUNDED AT $34 MILLION
F21: CURRENT | G21: CURRENT | H21: PROPOSED | I21: CURRENT | J21: CURRENT | K21: PROPOSED | L21: PROPOSED | M21: CURRENT | N21: PROPOSED | P21: CURRENT | U21: WORKING GROUP RECOMMENDATION
F24: 5 Year Avg | I24: Alt Facility | J24: Alt Facility | K24: Alt Facility | L24: Alt Facility | M24: Total | N24: Total | P24: 5 Yr Avg | R24: Alt Facility | S24: Alt Facility | T24: H&S + | V24: Alt Facility | W24: Alt Facility | X24: H&S +
F25: Health | G25: Deferred | H25: Deferred | I25: PAYG Levy | J25: Debt | K25: PAYG Levy | L25: Debt | M25: H&S + | N25: H&S + | P25: Health | Q25: Deferred | R25: PAYG Levy | S25: Debt | T25: Def Maint + | U25: Deferred | V25: PAYG Levy | W25: Debt | X25: Def Maint + | Y25: REVENUE | Z25: REVENUE
F26: & Safety | G26: Maint | H26: Maint | I26: 5 Yr Ave | J26: Service | K26: 5 Yr Ave | L26: Service | M26: Def Maint + | N26: Def Maint + | P26: & Safety | Q26: Maint | R26: 5 Yr Ave | S26: Service | T26: Alt Fac Rev | U26: Maint | V26: 5 Yr Ave | W26: Service | X26: Alt Fac Rev | Y26: CHANGE | Z26: CHANGE
D27: Strata | E27: ADM | F27: Revenue | G27: Revenue | H27: Revenue | I27: Revenue | J27: Revenue | K27: Revenue | L27: Revenue | M27: Alt Fac Rev | N27: Alt Fac Rev | P27: Revenue | Q27: Revenue | R27: Revenue | S27: Revenue | T27: PER ADM | U27: Revenue | V27: Revenue | W27: Revenue | X27: PER ADM | Y27: PER ADM
C29: TOTAL | E29: 830024.43 | F29: 56294162 | G29: 26096486 | H29: 93437343 | I29: 62373415 | J29: 131348154 | K29: 85711117 | L29: 131348154 | M29: 2.7611222e+08 | N29: 3.1049661e+08 | P29: 67.822296 | Q29: 31.440625 | R29: 75.146481 | S29: 158.24613 | T29: 332.65553 | U29: 112.5718 | V29: 103.26337 | W29: 158.24613 | X29: 374.08129 | Y29: 41.425764 | Z29: 34384396
A31: MPLS & ST PAUL | D31: 1 | E31: 72789.15 | F31: 6659096.2 | G31: 0 | H31: 0 | I31: 12599179 | J31: 35204134 | K31: 19258275 | L31: 35204134 | M31: 54462409 | N31: 54462409 | P31: 91.484736 | Q31: 0 | R31: 173.09144 | S31: 483.64535 | T31: 748.22152 | U31: 0 | V31: 264.57617 | W31: 483.64535 | X31: 748.22152 | Y31: 0 | Z31: 0
A32: OTHER METRO, INNER | D32: 2 | E32: 86993.02 | F32: 7030757.5 | G32: 1614622.5 | H32: 5665646.8 | I32: 11897285 | J32: 25093699 | K32: 16224636 | L32: 25093699 | M32: 45636364 | N32: 46983982 | P32: 80.819788 | Q32: 18.560368 | R32: 136.76137 | S32: 288.45646 | T32: 524.59799 | U32: 65.127602 | V32: 186.50503 | W32: 288.45646 | X32: 540.0891 | Y32: 15.491106 | Z32: 1347618.1
A33: OTHER METRO, OUTER | D33: 3 | E33: 262816 | F33: 15132715 | G33: 4642745.6 | H33: 16428196 | I33: 24355737 | J33: 36917072 | K33: 34282647 | L33: 36917072 | M33: 81048269 | N33: 87627915 | P33: 57.579123 | Q33: 17.665384 | R33: 92.6722 | S33: 140.46737 | T33: 308.38408 | U33: 62.508356 | V33: 130.44353 | W33: 140.46737 | X33: 333.41926 | Y33: 25.03518 | Z33: 6579645.8
A34: NONMET>=2K | D34: 4 | E34: 184386.4 | F34: 11565001 | G34: 8381392.6 | H34: 29564347 | I34: 12847466 | J34: 17933266 | K34: 15271810 | L34: 17933266 | M34: 50727126 | N34: 62769423 | P34: 62.72155 | Q34: 45.45559 | R34: 69.676866 | S34: 97.259158 | T34: 275.11316 | U34: 160.33909 | V34: 82.825037 | W34: 97.259158 | X34: 340.42328 | Y34: 65.310118 | Z34: 12042297
A35: NONMET 1K-2K | D35: 5 | E35: 93852 | F35: 6835493.5 | G35: 5975096.4 | H35: 21045769 | I35: 218079.47 | J35: 9375826 | K35: 218079.47 | L35: 9375826 | M35: 22404495 | N35: 30639675 | P35: 72.832689 | Q35: 63.665094 | R35: 2.3236529 | S35: 99.900119 | T35: 238.72156 | U35: 224.24423 | V35: 2.3236529 | W35: 99.900119 | X35: 326.468 | Y35: 87.746444 | Z35: 8235179.3
A36: NONMET < 1K | D36: 6 | E36: 87410.86 | F36: 9071099.3 | G36: 5482629.4 | H36: 20733384 | I36: 455668.98 | J36: 6824157 | K36: 455668.98 | L36: 6824157 | M36: 21833555 | N36: 28013210 | P36: 103.77543 | Q36: 62.72252 | R36: 5.2129561 | S36: 78.069899 | T36: 249.7808 | U36: 237.1946 | V36: 5.2129561 | W36: 78.069899 | X36: 320.47745 | Y36: 70.696651 | Z36: 6179655.1
A37: CHARTER | D37: 7 | E37: 41777 | F37: 0 | G37: 0 | H37: 0 | I37: 0 | J37: 0 | K37: 0 | L37: 0 | M37: 0 | N37: 0 | P37: 0 | Q37: 0 | R37: 0 | S37: 0 | T37: 0 | U37: 0 | V37: 0 | W37: 0 | X37: 0 | Y37: 0 | Z37: 0
A38: NONCHARTER FUDGE | D38: 8 | E38: 0 | F38: 0 | G38: 0 | H38: #REF! | I38: #REF! | J38: #REF! | K38: #REF! | L38: #REF! | M38: #REF! | N38: #REF! | P38: #DIV/0! | Q38: #DIV/0! | R38: #REF! | S38: #REF! | U38: #REF! | V38: #REF! | W38: #REF! | Z38: #REF!
A40: 1 | B40: 1 | C40: AITKIN | D40: 5 | E40: 1226.43 | F40: 57793.238 | G40: 85849.8 | H40: 299568.1 | I40: 0 | J40: 0 | K40: 0 | L40: 0 | M40: 143643.04 | N40: 299568.1 | P40: 47.123144 | Q40: 69.999755 | R40: 0 | S40: 0 | T40: 117.1229 | U40: 244.26025 | V40: 0 | W40: 0 | X40: 244.26025 | Y40: 127.13735 | Z40: 155925.06
A41: 1.2 | B41: 3 | C41: MINNEAPOLIS | D41: 1 | E41: 34128.01 | F41: 2544235.3 | G41: 0 | H41: 0 | I41: 12599179 | J41: 26770896 | K41: 15143414 | L41: 26770896 | M41: 41914310 | N41: 41914310 | P41: 74.54977 | Q41: 0 | R41: 369.17414 | S41: 784.42593 | T41: 1228.1498 | U41: 0 | V41: 443.72391 | W41: 784.42593 | X41: 1228.1498 | Y41: 0 | Z41: 0
A42: 2 | B42: 1 | C42: HILL CITY | D42: 6 | E42: 276.11 | F42: 10171.828 | G42: 14614.69 | H42: 51336.852 | I42: 0 | J42: 0 | K42: 0 | L42: 0 | M42: 24786.518 | N42: 51336.852 | P42: 36.839767 | Q42: 52.930681 | R42: 0 | S42: 0 | T42: 89.770448 | U42: 185.92898 | V42: 0 | W42: 0 | X42: 185.92898 | Y42: 96.158536 | Z42: 26550.333
A43: 4 | B43: 1 | C43: MCGREGOR | D43: 6 | E43: 399.46 | F43: 126666.55 | G43: 27105 | H43: 153771.55 | I43: 0 | J43: 0 | K43: 0 | L43: 0 | M43: 153771.55 | N43: 153771.55 | P43: 317.09445 | Q43: 67.854103 | R43: 0 | S43: 0 | T43: 384.94855 | U43: 384.94855 | V43: 0 | W43: 0 | X43: 384.94855 | Y43: 0 | Z43: 0
A44: 6 | B44: 3 | C44: SOUTH ST. PAUL | D44: 2 | E44: 3308.17 | F44: 396672.98 | G44: 227724.6 | H44: 798484.1 | I44: 0 | J44: 0 | K44: 0 | L44: 0 | M44: 624397.58 | N44: 798484.1 | P44: 119.90707 | Q44: 68.837031 | R44: 0 | S44: 0 | T44: 188.7441 | U44: 241.36731 | V44: 0 | W44: 0 | X44: 241.36731 | Y44: 52.623207 | Z44: 174086.52
A45: 11 | B45: 1 | C45: ANOKA-HENNEPIN | D45: 3 | E45: 37509.62 | F45: 2467020.1 | G45: 0 | H45: 0 | I45: 1872901.5 | J45: 3506957 | K45: 4339921.6 | L45: 3506957 | M45: 7846878.6 | N45: 7846878.6 | P45: 65.77033 | Q45: 0 | R45: 49.93123 | S45: 93.494869 | T45: 209.19643 | U45: 0 | V45: 115.70156 | W45: 93.494869 | X45: 209.19643 | Y45: 0 | Z45: 0
A46: 12 | B46: 1 | C46: CENTENNIAL | D46: 3 | E46: 6410.17 | F46: 132880.75 | G46: 418151.23 | H46: 1465413.8 | I46: 0 | J46: 418978 | K46: 0 | L46: 418978 | M46: 970009.98 | N46: 1884391.8 | P46: 20.729676 | Q46: 65.232472 | R46: 0 | S46: 65.361449 | T46: 151.3236 | U46: 228.60763 | V46: 0 | W46: 65.361449 | X46: 293.96908 | Y46: 142.64548 | Z46: 914381.81
A47: 13 | B47: 1 | C47: COLUMBIA HEIGHTS | D47: 2 | E47: 3035.96 | F47: 513965.69 | G47: 208106.4 | H47: 730151.1 | I47: 240000 | J47: 0 | K47: 240000 | L47: 0 | M47: 962072.09 | N47: 970151.1 | P47: 169.29264 | Q47: 68.547148 | R47: 79.052425 | S47: 0 | T47: 316.89221 | U47: 240.5009 | V47: 79.052425 | W47: 0 | X47: 319.55332 | Y47: 2.6611062 | Z47: 8079.012
A48: 14 | B48: 1 | C48: FRIDLEY | D48: 3 | E48: 2997.43 | F48: 400693.81 | G48: 207858.6 | H48: 730240.8 | I48: 10125 | J48: 1503259 | K48: 10125 | L48: 1503259 | M48: 2121936.4 | N48: 2243624.8 | P48: 133.67912 | Q48: 69.345606 | R48: 3.3778937 | S48: 501.51597 | T48: 707.91859 | U48: 243.6223 | V48: 3.3778937 | W48: 501.51597 | X48: 748.51616 | Y48: 40.597576 | Z48: 121688.39
A49: 15 | B49: 1 | C49: ST. FRANCIS | D49: 3 | E49: 4908.56 | F49: 184234.36 | G49: 310540.05 | H49: 1085795.9 | I49: 0 | J49: 973143 | K49: 0 | L49: 973143 | M49: 1467917.4 | N49: 2058938.9 | P49: 37.533281 | Q49: 63.265001 | R49: 0 | S49: 198.25427 | T49: 299.05256 | U49: 221.20457 | V49: 0 | W49: 198.25427 | X49: 419.45884 | Y49: 120.40629 | Z49: 591021.49
A50: 16 | B50: 1 | C50: SPRING LAKE PARK | D50: 3 | E50: 5097.1 | F50: 497324.71 | G50: 315278.17 | H50: 1107192.1 | I50: 286390.4 | J50: 694280 | K50: 286390.4 | L50: 694280 | M50: 1793273.3 | N50: 2087862.5 | P50: 97.57013 | Q50: 61.854421 | R50: 56.186929 | S50: 136.21079 | T50: 351.82227 | U50: 217.22 | V50: 56.186929 | W50: 136.21079 | X50: 409.61771 | Y50: 57.795447 | Z50: 294589.17
A51: 22 | B51: 1 | C51: DETROIT LAKES | D51: 4 | E51: 2862.5 | F51: 151396.38 | G51: 198254.4 | H51: 696893.1 | I51: 0 | J51: 0 | K51: 0 | L51: 0 | M51: 349650.78 | N51: 696893.1 | P51: 52.889566 | Q51: 69.259179 | R51: 0 | S51: 0 | T51: 122.14875 | U51: 243.4561 | V51: 0 | W51: 0 | X51: 243.4561 | Y51: 121.30736 | Z51: 347242.32
... A277: 813 | B277: 1 | C277: LAKE CITY | D277: 5 | E277: 1227.39 | F277: 60071.982 | G277: 84972 | H277: 299048.3 | I277: 20041 | J277: 541634 | K277: 20041 | L277: 541634 | M277: 706718.98 | N277: 860723.3 | P277: 48.942864 | Q277: 69.229829 | R277: 16.328143 | S277: 441.28924 | T277: 575.79008 | U277: 243.6457 | V277: 16.328143 | W277: 441.28924 | X277: 701.26309 | Y277: 125.47301 | Z277: 154004.32
A278: 815 | B278: 2 | C278: PRINSBURG | D278: 6 | E278: 0 | F278: 0 | G278: 0 | H278: 0 | I278: 0 | J278: 0 | K278: 0 | L278: 0 | M278: 0 | N278: 0 | Z278: 0
A279: 818 | B279: 1 | C279: VERNDALE | D279: 6 | E279: 483.8 | F279: 18387.914 | G279: 33774 | H279: 118723.7 | I279: 0 | J279: 0 | K279: 0 | L279: 0 | M279: 52161.914 | N279: 118723.7 | P279: 38.007263 | Q279: 69.809839 | R279: 0 | S279: 0 | T279: 107.8171 | U279: 245.39831 | V279: 0 | W279: 0 | X279: 245.39831 | Y279: 137.5812 | Z279: 66561.786
A280: 820 | B280: 1 | C280: SEBEKA | D280: 6 | E280: 503.2 | F280: 27338.438 | G280: 35250 | H280: 122838.4 | I280: 0 | J280: 0 | K280: 0 | L280: 0 | M280: 62588.438 | N280: 122838.4 | P280: 54.329169 | Q280: 70.051669 | R280: 0 | S280: 0 | T280: 124.38084 | U280: 244.11447 | V280: 0 | W280: 0 | X280: 244.11447 | Y280: 119.73363 | Z280: 60249.962
A281: 821 | B281: 1 | C281: MENAHGA | D281: 6 | E281: 898.46 | F281: 35756.66 | G281: 49054.868 | H281: 171822.54 | I281: 0 | J281: 90222 | K281: 0 | L281: 90222 | M281: 175033.53 | N281: 262044.54 | P281: 39.797721 | Q281: 54.598833 | R281: 0 | S281: 100.41849 | T281: 194.81505 | U281: 191.24117 | V281: 0 | W281: 100.41849 | X281: 291.65966 | Y281: 96.844615 | Z281: 87011.013
A282: 829 | B282: 1 | C282: WASECA | D282: 5 | E282: 1839.45 | F282: 299169.36 | G282: 128521.8 | H282: 452380.1 | I282: 0 | J282: 269184 | K282: 0 | L282: 269184 | M282: 696875.16 | N282: 721564.1 | P282: 162.64066 | Q282: 69.869689 | R282: 0 | S282: 146.33939 | T282: 378.84974 | U282: 245.93226 | V282: 0 | W282: 146.33939 | X282: 392.27166 | Y282: 13.421914 | Z282: 24688.94
A283: 831 | B283: 1 | C283: FOREST LAKE | D283: 3 | E283: 6908.09 | F283: 503357.19 | G283: 459060.55 | H283: 1613667 | I283: 301800 | J283: 0 | K283: 301800 | L283: 0 | M283: 1264217.7 | N283: 1915467 | P283: 72.864887 | Q283: 66.452602 | R283: 43.687908 | S283: 0 | T283: 183.0054 | U283: 233.59091 | V283: 43.687908 | W283: 0 | X283: 277.27881 | Y283: 94.273417 | Z283: 651249.25
A284: 832 | B284: 1 | C284: MAHTOMEDI | D284: 3 | E284: 3290.28 | F284: 102497.96 | G284: 213761.15 | H284: 753231.12 | I284: 0 | J284: 58572 | K284: 0 | L284: 58572 | M284: 374831.11 | N284: 811803.12 | P284: 31.151745 | Q284: 64.967464 | R284: 0 | S284: 17.801524 | T284: 113.92073 | U284: 228.92615 | V284: 0 | W284: 17.801524 | X284: 246.72767 | Y284: 132.80694 | Z284: 436972.01
A285: 833 | B285: 1 | C285: SOUTH WASHINGTON | D285: 2 | E285: 17546.68 | F285: 879665.59 | G285: 0 | H285: 0 | I285: 1331447.4 | J285: 1113239 | K285: 2211113 | L285: 1113239 | M285: 3324352 | N285: 3324352 | P285: 50.132879 | Q285: 0 | R285: 75.880303 | S285: 63.444424 | T285: 189.45761 | U285: 0 | V285: 126.01318 | W285: 63.444424 | X285: 189.45761 | Y285: 0 | Z285: 0
A286: 834 | B286: 1 | C286: STILLWATER | D286: 3 | E286: 8639.2 | F286: 502408.72 | G286: 0 | H286: 0 | I286: 2710550.2 | J286: 5358028 | K286: 3212958.9 | L286: 5358028 | M286: 8570986.9 | N286: 8570986.9 | P286: 58.154542 | Q286: 0 | R286: 313.75014 | S286: 620.19956 | T286: 992.10424 | U286: 0 | V286: 371.90468 | W286: 620.19956 | X286: 992.10424 | Y286: 0 | Z286: 0
A287: 836 | B287: 1 | C287: BUTTERFIELD | D287: 6 | E287: 213.39 | F287: 86099.39 | G287: 15046.2 | H287: 101145.59 | I287: 0 | J287: 0 | K287: 0 | L287: 0 | M287: 101145.59 | N287: 101145.59 | P287: 403.48372 | Q287: 70.510333 | R287: 0 | S287: 0 | T287: 473.99405 | U287: 473.99405 | V287: 0 | W287: 0 | X287: 473.99405 | Y287: 0 | Z287: 0
A288: 837 | B288: 1 | C288: MADELIA | D288: 6 | E288: 530.16 | F288: 81221.84 | G288: 37164.6 | H288: 131003.4 | I288: 0 | J288: 237117 | K288: 0 | L288: 237117 | M288: 355503.44 | N288: 368120.4 | P288: 153.2025 | Q288: 70.100724 | R288: 0 | S288: 447.25555 | T288: 670.55877 | U288: 247.10163 | V288: 0 | W288: 447.25555 | X288: 694.35718 | Y288: 23.7984 | Z288: 12616.96
A289: 840 | B289: 1 | C289: ST. JAMES | D289: 5 | E289: 1042.47 | F289: 186219.57 | G289: 72948 | H289: 259167.57 | I289: 0 | J289: 269010 | K289: 0 | L289: 269010 | M289: 528177.57 | N289: 528177.57 | P289: 178.63302 | Q289: 69.976114 | R289: 0 | S289: 258.05059 | T289: 506.65973 | U289: 248.60914 | V289: 0 | W289: 258.05059 | X289: 506.65973 | Y289: 0 | Z289: 0
A290: 846 | B290: 1 | C290: BRECKENRIDGE | D290: 6 | E290: 701.17 | F290: 46362.814 | G290: 49600.8 | H290: 172957.7 | I290: 0 | J290: 0 | K290: 0 | L290: 0 | M290: 95963.614 | N290: 172957.7 | P290: 66.122073 | Q290: 70.740049 | R290: 0 | S290: 0 | T290: 136.86212 | U290: 246.67014 | V290: 0 | W290: 0 | X290: 246.67014 | Y290: 109.80802 | Z290: 76994.086
... A523: 4209 | B523: 7 | C523: THE MASTERY SCHOOL | D523: 7 | E523: 150 | F523: 0 | G523: 0 | H523: 0 | I523: 0 | J523: 0 | K523: 0 | L523: 0 | M523: 0 | N523: 0 | P523: 0 | Q523: 0 | R523: 0 | S523: 0 | T523: 0 | U523: 0 | V523: 0 | W523: 0 | X523: 0 | Y523: 0 | Z523: 0
A524: 6666 | B524: 8 | C524: FUDGE, DISTRICTS | D524: 8 | E524: 0 | F524: 0 | G524: 0 | H524: 0 | I524: 0 | J524: 0 | K524: 0 | L524: 0 | M524: 0 | N524: 0 | P524: #DIV/0! | Q524: #DIV/0! | R524: #DIV/0! | S524: #DIV/0! | T524: #DIV/0! | U524: #DIV/0! | V524: #DIV/0! | W524: #DIV/0! | X524: #DIV/0! | Y524: #DIV/0! | Z524: 0
A525: 7777 | B525: 9 | C525: FUDGE, CHARTERS | D525: 7 | E525: 0 | F525: 0 | G525: 0 | H525: 0 | I525: 0 | J525: 0 | K525: 0 | L525: 0 | M525: 0 | N525: 0 | P525: #DIV/0! | Q525: #DIV/0! | R525: #DIV/0! | S525: #DIV/0! | T525: #DIV/0! | U525: #DIV/0! | V525: #DIV/0! | W525: #DIV/0! | X525: #DIV/0! | Y525: #DIV/0! | Z525: 0
A526: 8888 | B526: 8 | C526: FUDGE, OTHER | D526: 8 | E526: 0 | F526: 0 | G526: 0 | H526: 0 | I526: 0 | J526: 0 | K526: 0 | L526: 0 | M526: 0 | N526: 0 | P526: #DIV/0! | Q526: #DIV/0! | R526: #DIV/0! | S526: #DIV/0! | T526: #DIV/0! | U526: #DIV/0! | V526: #DIV/0! | W526: #DIV/0! | X526: #DIV/0! | Y526: #DIV/0! | Z526: 0
A527: 9999 | B527: 0 | C527: STATE TOTAL | D527: 0 | F527: 56294162 | G527: 26096486 | H527: 93437343 | I527: 62373415 | J527: 131348154 | K527: 85711117 | L527: 131348154

Sheet REPORT 6 - CHARTER LEASE AID
D3: 1.25 | E3: 1 | F3: 0.612 | G3: 1.115 | H3: 1.06 | I3: 1.3
D4: 1 | E4: 1 | F4: 0.5 | G4: 1 | H4: 1 | I4: 1.2 | S4: 1314
A5: Corrected Data as of 12 / 06/2012 | S5: or 90%
D6: A | E6: B | F6: C | G6: D | H6: E | I6: F | J6: G | K6: H | L6: I | M6: J | N6: K | O6: L | P6: M | Q6: N | R6: O | S6: P | T6: Q | U6: R
A7: Lease Aid formula @ $1,314/new PU
N8: Current | O8: Current | Q8: Proposed | R8: Proposed
D9: FY 2013 | E9: FY 2013 | F9: FY 2013 | G9: FY 2013 | H9: FY 2013 | I9: FY 2013 | J9: FY 2013 | L9: Current | M9: Proposed | P9: Current | S9: Proposed | T9: Change | U9: Change
D10: ADM | E10: ADM | F10: ADM | G10: ADM | H10: ADM | I10: ADM | J10: ADM | K10: Lease | L10: Pupil | M10: Pupil | N10: = H * | O10: = I * | P10: Revenue | S10: Revenue | T10: In | U10: Per
D11: Pre-K | E11: H-K | F11: Reg-K | G11: 1-3 | H11: 4-6 | I11: 7-12 | J11: Total | K11: Amout | L11: Units | M11: Units | N11: 0.9 | O11: 1200 | Q11: 0.9 | R11: 1314 | T11: Revenue | U11: ADM
C13: TOTAL | D13: =SUM(D15:D162) -> 13 | E13: =SUM(E15:E162) -> 94 | F13: =SUM(F15:F162) -> 4041 | G13: =SUM(G15:G162) -> 11367 | H13: =SUM(H15:H162) -> 10060 | I13: =SUM(I15:I162) -> 16219 | J13: =SUM(J15:J162) -> 41794 | K13: 60197414 | L13: 47005.98 | M13: 43017.3 | N13: 54177673 | O13: 56407176 | P13: 49975643 | Q13: 54177673 | R13: 56524732 | S13: 49967709 | T13: -7933.29 | U13: -0.18981887
A15: 4000 | B15: 7 | C15: CITY ACADEMY | D15: 0 | E15: 0 | F15: 0 | G15: 0 | H15: 0 | I15: 110 | J15: =SUM(D15:I15) -> 110 | K15: 60000 | L15: 143 | M15: 132 | N15: 54000 | O15: 171600 | P15: 54000 | Q15: 54000 | R15: 173448 | S15: 54000 | T15: 0 | U15: 0
A16: 4001 | B16: 7 | C16: BLUFFVIEW MONTESSORI | D16: 0 | E16: 0 | F16: 25 | G16: 71 | H16: 73 | I16: 43 | J16: =SUM(D16:I16) -> 212 | K16: 395705 | L16: 227.75 | M16: 208.1 | N16: 356134.5 | O16: 273300 | P16: 273300 | Q16: 356134.5 | R16: 273443.4 | S16: 273443.4 | T16: 143.4 | U16: 0.67641509
A17: 4003 | B17: 7 | C17: NEW HEIGHTS SCHOOL, INC. | D17: 0 | E17: 0 | F17: 4 | G17: 20 | H17: 24 | I17: 74 | J17: =SUM(D17:I17) -> 122 | K17: 195075 | L17: 146.39 | M17: 134.8 | N17: 175567.5 | O17: 175668 | P17: 175567.5 | Q17: 175567.5 | R17: 177127.2 | S17: 175567.5 | T17: 0 | U17: 0
A18: 4004 | B18: 7 | C18: CEDAR RIVERSIDE COMMUNITY SCHO | D18: 0 | E18: 0 | F18: 20 | G18: 58 | H18: 40 | I18: 27 | J18: =SUM(D18:I18) -> 145 | K18: 213079.49 | L18: 154.41 | M18: 140.4 | N18: 191771.54 | O18: 185292 | P18: 185292 | Q18: 191771.54 | R18: 184485.6 | S18: 184485.6 | T18: -806.4 | U18: -5.5613793
A19: 4005 | B19: 7 | C19: METRO DEAF CHARTER SCHOOL | D19: 13 | E19: 9 | F19: 0 | G19: 12 | H19: 12 | I19: 29 | J19: =SUM(D19:I19) -> 75 | K19: 525300 | L19: 89.05 | M19: 80.8 | N19: 472770 | O19: 106860 | P19: 106860 | Q19: 472770 | R19: 106171.2 | S19: 106171.2 | T19: -688.8 | U19: -9.184
A20: 4007 | B20: 7 | C20: MINNESOTA NEW COUNTRY SCHOOL | D20: 0 | E20: 0 | F20: 0 | G20: 0 | H20: 6 | I20: 106 | J20: =SUM(D20:I20) -> 112 | K20: 201057.46 | L20: 144.16 | M20: 133.2 | N20: 180951.71 | O20: 172992 | P20: 172992 | Q20: 180951.71 | R20: 175024.8 | S20: 175024.8 | T20: 2032.8 | U20: 18.15
A21: 4008 | B21: 7 | C21: PACT CHARTER SCHOOL | D21: 0 | E21: 0 | F21: 40 | G21: 144 | H21: 157 | I21: 271 | J21: =SUM(D21:I21) -> 612 | K21: 900306.88 | L21: 703.76 | M21: 646.2 | N21: 810276.19 | O21: 844512 | P21: 810276.19 | Q21: 810276.19 | R21: 849106.8 | S21: 810276.19 | T21: 0 | U21: 0
A22: 4011 | B22: 7 | C22: NEW VISIONS CHARTER SCHOOL | D22: 0 | E22: 1 | F22: 24 | G22: 76 | H22: 75 | I22: 34 | J22: =SUM(D22:I22) -> 210 | K22: 403300 | L22: 224.13 | M22: 204.8 | N22: 362970 | O22: 268956 | P22: 268956 | Q22: 362970 | R22: 269107.2 | S22: 269107.2 | T22: 151.2 | U22: 0.72
A23: 4015 | B23: 7 | C23: COMMUNITY OF PEACE ACADEMY | D23: 0 | E23: 0 | F23: 54 | G23: 158 | H23: 155 | I23: 417 | J23: =SUM(D23:I23) -> 784 | K23: 1339000 | L23: 915.62 | M23: 840.4 | N23: 1205100 | O23: 1098744 | P23: 1098744 | Q23: 1205100 | R23: 1104285.6 | S23: 1104285.6 | T23: 5541.6 | U23: 7.0683673
A24: 4016 | B24: 7 | C24: WORLD LEARNER CHARTER SCHOOL | D24: 0 | E24: 0 | F24: 0 | G24: 79 | H24: 84 | I24: 43 | J24: =SUM(D24:I24) -> 206 | K24: 310700 | L24: 233.03 | M24: 214.6 | N24: 279630 | O24: 279636 | P24: 279630 | Q24: 279630 | R24: 281984.4 | S24: 279630 | T24: 0 | U24: 0
A25: 4017 | B25: 7 | C25: MINNESOTA TRANSITIONS CHARTER | D25: 0 | E25: 0 | F25: 95 | G25: 337 | H25: 409 | I25: 2283 | J25: =SUM(D25:I25) -> 3124 | K25: 2818488.7 | L25: 3835.34 | M25: 3533.1 | N25: 2536639.8 | O25: 4602408 | P25: 2536639.8 | Q25: 2536639.8 | R25: 4642493.4 | S25: 2536639.8 | T25: 0 | U25: 0
A26: 4018 | B26: 7 | C26: ACHIEVE LANGUAGE ACADEMY | D26: 0 | E26: 0 | F26: 48 | G26: 144 | H26: 135 | I26: 83 | J26: =SUM(D26:I26) -> 410 | K26: 628376.59 | L26: 440.94 | M26: 402.6 | N26: 565538.93 | O26: 529128 | P26: 529128 | Q26: 565538.93 | R26: 529016.4 | S26: 529016.4 | T26: -111.6 | U26: -0.27219512
... A162: 4209 | B162: 7 | C162: THE MASTERY SCHOOL | D162: 0 | E162: 0 | F162: 67 | G162: 98 | H162: 0 | I162: 0 | J162: =SUM(D162:I162) -> 165 | K162: 250000 | L162: 150.27 | M162: 131.5 | N162: 225000 | O162: 180324 | P162: 180324 | Q162: 225000 | R162: 172791 | S162: 172791 | T162: -7533 | U162: -45.654545
