Workbook
Name AcadDept: Worksheet!$F$70:$F$95
Name Address_1: Database!$M$2
Name Address_2: Database!$N$2
Name AdminRes: Worksheet!$C$37:$C$38
Name AppendixB: 'APPENDIX B'!$A$7:$A$72
Name AppendixF: 'Appendix F'!$A$6:$A$216
Name Beginning_Date: Database!$AD$2
Name Check10: 'E Recomend'!#REF!
Name Check11: 'E Recomend'!#REF!
Name Check6: 'E Recomend'!$A$49
Name Check7: 'E Recomend'!#REF!
Name Check8: 'E Recomend'!$D$49
Name Check9: 'E Recomend'!$F$49
Name CIP: 'CIP codes (2)'!$B$2:$B$67
Name CIPCode: 'CIP codes (2)'!$A$2:$A$67
Name CIPCode: 'CIP codes'!$A$2:$A$67
Name CIPDescript: 'CIP codes (2)'!$B$2:$B$67
Name CIPDescript: 'CIP codes'!$B$2:$B$67
Name City: Database!$O$2
Name CollegeSchool: Worksheet!$E$340:$E$362
Name Contract_Period: Database!$AC$2
Name Country: Worksheet!$F$101:$F$337
Name country_into_link: Sheet5!#REF!
Name country_phone_link: Sheet5!#REF!
Name CountryCode: Worksheet!$G$101:$G$337
Name DegreeType: Worksheet!$B$50:$B$55
Name Department: Database!$K$2
Name Depts: Worksheet!$E$379:$E$412
Name Disabled: Worksheet!$D$31:$D$32
Name Dropdown1: 'Worksheet K'!$E$30
Name email: Database!$AB$2
Name End_Date: Database!$AE$2
Name Equity: Database!$S$2
Name ERecType: Worksheet!$B$368:$B$376
Name EthnicOrigin: Worksheet!$F$31:$F$40
Name First_Name: Database!$C$2
Name FTE: Database!$J$2
Name Gender: Worksheet!$E$31:$E$32
Name HighestDegree: 'Highest Degree'!$A$4:$A$272
Name Hours_to_teach: Database!$AF$2
Name I9Received: Worksheet!$A$42:$A$43
Name ID: Database!$A$2
Name Last_Name: Database!$D$2
Name Mandated_Raise: Database!$R$2
Name Merit: Database!$F$2
Name OLE_LINK3: Clauses!$B$48
Name OLE_LINK5: Clauses!$B$20
Name Other: Database!$V$2
Name Percent_Increase: Database!$Y$2
Name PIN: Database!$Q$2
Name Pos: Database!$B$2
Name Prevailing_Salary: Database!$E$2
Name Promotion: Database!$T$2
Name Rank: Database!$Z$2
Name Salutation: Database!$I$2
Name School_College: Database!$L$2
Name Schools: Worksheet!$E$340:$E$357
Name SourceFunds: Worksheet!$E$61:$E$63
Name SS: Database!$H$2
Name State: Database!$P$2

Sheet Start
E29: email to : epaservices@nccu.edu

Sheet E Recomend
A1: EPA RECOMMENDATION FOR PERSONNEL ACTION | F1: E-Rec Type
F2: 1 or more years break in service employee is considered new
A3: If you are currently employed with any North Carolina State agency you need to complete the Dual Employment form, in place of the E-Rec.
A4: General Prospect & Diversity Data
A5: Name & Title of Prospective Employee: | H5: SS# :
C6: Title | D6: First Name | E6: Middle Initial | F6: Last Name
A8: Address 1: | F8: Address 2:
A9: City: | F9: State: | I9: Zip:
A10: Country | F10: Country Code:
A11: Telephone (primary): | F11: Telephone (other):
A12: Email: | F12: Date of Birth:
G13: mm/dd/yy
A14: Veteran: | D14: Disabled: | G14: Gender:
A16: Ethnic Origin
A18: Has The Prospective Employee ever been Employed by an UNC Campus, NCCU or another State agency?
A19: =IF(Worksheet!D15<4,"New employment-Full employment package is needed","")
A21: If Response is "Yes", please give the Prospect's last place of employment.
A23: Position and Offer Data
A24: College/School/Institute: | G24: Academic Department:
A26: Department:
A28: Proposed Appointment Type?
A30: Proposed Rank | F30: Date Tenure Track Began:
A32: =IF(Worksheet!D16=4,"Is/Will the employee be tenured?",IF(Worksheet!D16=5,"Is/Will the employee be tenured?", IF(Worksheet!D16=6,"Is/Will the employee be tenured?",IF(Worksheet!$I$15>6,"The primary purpose of this position is non-facuty in the area of:","Does the Position have any Administrative or Research duties beyond that normally expected of Faculty?")))) -> Does the Position have any Administrative or Research duties beyond that normally expected of Faculty?
A34: If Administrative or Research, Proposed Title?
A35: =IF(Worksheet!$H$15=11,"For your unit this rank is equivalent to what tenure track or non tenure track faculty rank?",IF(Worksheet!$H$15=12,"For your unit this rank is equivalent to what tenure track or non tenure track faculty rank?","")) | E35: Must have title
A36: Proposed Salary: | G36: CIP Code for Depart.
C37: If full-time with benefits use annualized salary
A38: Department Rank for Administrator:
A40: =IF(Worksheet!I15>=4, " Contract Period for the Administrative Appointment","Annual Service Obligation for Faculty Appointment") -> Annual Service Obligation for Faculty Appointment | F40: Type of Tenure Track Contract
A44: New Hires Only
A45: Highest Degree Earned: | F45: Name of Institution
F46: Date of Degree:
A48: Date Degree was Awarded: | E48: State of Degree: | G48: or Country | I48: Major:
A50: Budget Data
A52: Source of Funds | E52: =IF(Worksheet!$M$15>=2," For Non-State funds identify the source of the Grant funds?","") -> For Non-State funds identify the source of the Grant funds?
A54: Position Number | B54: Banner# | C54: Fund# | E54: Org# | F54: Account# | G54: Amount | H54: Percentage of Time | I54: FTE | W54: Dept Org#
A55: 17185 | B55: 617185 | C55: 201010 | E55: 10034 | F55: 1310 | G55: 15000 | H55: 0.5 | I55: 1 | W55: 10705
G56: 0
G57: 0
G58: 0
A59: Stipend will need FTE also
G60: 0
F61: Total | G61: =SUM(G56:G58)+G60 -> 0 | H61: =SUM(H56:H58) -> 0 | I61: =SUM(I56:J58) -> 0
F63: =IF(G61>1,"> 100%-Check","") | G63: =IF(H61>1,">1 FTE-Check","")
A65: Employment Period
C66: Start (i.e. July 1, 2011) | F66: End (i.e.June 30, 2012)
A68: Stipend Period
C69: Start (i.e. July 1, 2011) | F69: End (i.e.June 30, 2012)
B70: =IF(C71<setup!A6,IF('E Recomend'!F71>=setup!A6,"This contract crosses fiscal years.Check funding carefully.",""),"")
C71: =C65 | F71: =F65
A72: Teaching Assignment | G72: Amount of Release Time (in credit hours) | I72: Reason for Release Time
A73: Course Number | B73: Credit Hours | C73: FTE | D73: Course Number | E73: Credit Hours | F73: FTE | G73: 0
B74: 0 | C74: 0 | E74: 0 | F74: 0
B75: 0 | C75: 0 | E75: 0 | F75: 0
B76: 0 | C76: 0 | E76: 0 | F76: 0
B77: 0 | C77: 0 | E77: 0 | F77: 0
B78: 0 | C78: 0 | E78: 0 | F78: 0
B79: 0 | C79: 0 | E79: 0 | F79: 0
A80: Total | B80: =SUM(B74:B79,E74:E79) -> 0 | C80: =SUM(C74:C79,F74:F79) -> 0
A82: Project/Grant Title and Number
D83: Title | G83: Number
A84: Duration of Project/Grant | F84: to
D85: Start (i.e. July 1, 2011) | G85: End (i.e.June 30, 2012)
A86: Comments
B88: Above must give an explanation for stipend or need for additional funds
A89: Preparer Contact Information (type information only)
A90: Name: | E90: Phone#: | H90: Email:
A92: Approval Signatures Below
A95: Principal Investigator | D95: Date | G95: Title III | L95: 6843 | M95: ABOU-CHACRA, RANIM | P95: =#REF! -> #REF! | Q95: =VLOOKUP(P95,$L$98:$M$562,2,FALSE) -> #REF! | W95: Date
A98: Chair/Director | D98: Date | G98: Provost/Vice Chancellor | L98: 6843 | M98: ABOU-CHACRA, RANIM | P98: =#REF! -> #REF! | Q98: =VLOOKUP(P98,$L$98:$M$562,2,FALSE) -> #REF! | W98: Date
L99: 4170 | M99: ABRAHAM, SOLOMON | P99: =#REF! -> #REF! | Q99: =VLOOKUP(P99,$L$98:$M$562,2,FALSE) -> #REF!
A101: Dean | D101: Date | G101: Chancellor | L101: 6843 | M101: ABOU-CHACRA, RANIM | P101: =#REF! -> #REF! | Q101: =VLOOKUP(P101,$L$98:$M$562,2,FALSE) -> #REF! | W101: Date
L102: 2582 | M102: AICHER JR, JOSEPH R
L103: 1233 | M103: ALEXANDER, PEGGY W
A104: Budget/Contracts/Grants Officer | D104: Date | G104: Comptroller | L104: 1309 | M104: ALLEN, BEVERLY J | W104: Date
L105: 3934 | M105: ALLEN, EDWARD N
A107: HR Only
A109: I-9 received | C109: Data Info | E109: Crime Check | G109: Tax Forms | L109: 6182 | M109: ALSTON III, JOHNNY
L111: 4130 | M111: ANSPAUGH, SHERYL
L112: 4349 | M112: APPLEGATE, KATHERI
L113: 4349 | M113: APPLEGATE, KATHEIN
L114: 9119 | M114: ASBERRY, DARRELL R
L115: 2366 | M115: AWUMEY, EMMANUEL M
L116: 2575 | M116: BACON, ELLEN H
L117: 2575 | M117: BACON, ELLEN H
L118: 3020 | M118: BAILEY, CANDACE L
L119: 824 | M119: BAILEY, EDRINA
L120: 3077 | M120: BAINES, TYRONE R
L121: 5672 | M121: BALDWIN, ETTA
L122: 3083 | M122: BALLARD, ROBERT M
... L562: 0 | M562: Type in Pass code

Sheet Worksheet
A1: 2 | B1: 3 | C1: 1 | D1: 1 | G1: 2 | H1: 1 | I1: 6 | K1: =IF(Database!AG2=4,1, IF(Database!AG2=8,1,0)) -> 0
C2: 1
C10: 2
C11: 3
A13: 1 | B13: 3
A14: Vet status | B14: disable | C14: Etnicity | D14: Current Employment | F14: state Agency/UNC | H14: Proposed rank | I14: Proposed status | J14: type of appt | K14: Proposed rank | M14: source of funds | N14: contract period | O14: Adm. Or research duties | P14: The replacement is needed because
A15: 2 | B15: 2 | C15: 0 | D15: 4 | F15: 27 | H15: 1 | I15: 2 | J15: 1 | K15: 1 | M15: 2 | N15: 1 | O15: 1 | P15: 6
A17: Gender | N17: other
A18: 1 | N18: ='E Recomend'!I40
N20: =IF(N15=7,N18,N15) -> 1
I23: faculty
A30: Title | C30: Veteran | D30: Disabled | E30: Gender | F30: Ethnic Origin
A31: Atty | C31: No | D31: No | E31: Female | F31: 1 = Nonresident Alien
A32: Dr | C32: Yes | D32: Yes | E32: Male | F32: 2 = Race and Ethnicity Unknown
A33: Miss | F33: 3 = Hispanics of any race
A34: Mr | F34: 4 = American Indiam or Alaska Native (For non-Hispanics only)
A35: Mrs | F35: 5 = Asian (For non-Hispanics only)
A36: Ms | C36: AdminResearch | F36: 6 = Black or African American (For non-Hispanics only)
A37: Prof | C37: No | F37: 7 = Native Hawaiian or Other Pacific Islander (For non-Hispanics only)
A38: Rev | C38: Yes | F38: 8 = White (For non-Hispanics only)
F39: 9 = Two or more races
F40: Unknown
A41: I-9 Received
A42: No
A43: Yes | F43: Currently Employed by State agency?
F44: No, not employed with any state entity as an employee
F45: Yes, the prospect was employed by another State Agency
F46: Yes, the prospect was employed by another campus in the UNC System
F47: Yes, the prospect within the past 3 months was employed at NCCU
B49: TYPES OF DEGREES | F49: Department:
B50: Certificates
B51: Associate's degree
B52: Bachelor's degree
B53: Master's degree
B54: Doctoral degree
B55: Professional degree
E60: Source of Funds
E61: Grant
E62: State
E63: Non-state
F69: Academic Departments
F70: Aerospace Studies
F71: Art
E72: State | F72: Biology
E73: Alabama | F73: Chemistry
E74: Alaska | F74: Criminal Justice
E75: Arizona | F75: Dean
E76: Arkansas | F76: English & Mass Communications
E77: California | F77: Environmental, Earth & Geospatial Sciences
E78: Colorado | F78: Global Studies
E79: Connecticut | F79: History
E80: Delaware | F80: Human Sciences
E81: Florida | F81: Mathematics & Computer Science
E82: Georgia | F82: Military Science
E83: Hawaii | F83: Modern Foreign Languages
... E95: Minnesota | F95: Theatre/Drama
E96: Mississippi
E97: Missouri
E98: Montana
E99: Nebraska
E100: Nevada | F100: Country | G100: Country Code
E101: New Hampshire | F101: Afghanistan | G101: AF / AFG
E102: New Jersey | F102: Albania | G102: AL / ALB
E103: New Mexico | F103: Algeria | G103: DZ / DZA
E104: New York | F104: American Samoa | G104: AS / ASM
E105: North Carolina | F105: Andorra | G105: AD / AND
E106: North Dakota | F106: Angola | G106: AO / AGO
E107: Ohio | F107: Anguilla | G107: AI / AIA
E108: Oklahoma | F108: Antarctica | G108: AQ / ATA
E109: Oregon | F109: Antigua and Barbuda | G109: AG / ATG
E110: Pennsylvania | F110: Argentina | G110: AR / ARG
E111: Rhode Island | F111: Armenia | G111: AM / ARM
... E122: Wyoming | F122: Belize | G122: BZ / BLZ
F123: Benin | G123: BJ / BEN
F124: Bermuda | G124: BM / BMU
F125: Bhutan | G125: BT / BTN
F126: Bolivia | G126: BO / BOL
F127: Bosnia and Herzegovina | G127: BA / BIH
F128: Botswana | G128: BW / BWA
F129: Brazil | G129: BR / BRA
F130: British Indian Ocean Territory | G130: IO / IOT
F131: British Virgin Islands | G131: VG / VGB
F132: Brunei | G132: BN / BRN
F133: Bulgaria | G133: BG / BGR
F134: Burkina Faso | G134: BF / BFA
... F337: Zimbabwe | G337: ZW / ZWE
E339: College/School
E340: Behavioral & Social Sciences
E341: Biomanufacturing Research Institute and Technology Enterprise (BRITE)
E342: Biomedical Biotechnical Research Institute (BBRI)
E343: Biotechnological & Pharmaceutical Law
E344: Business
E345: Center for Innovation in Health Disparities Research
E346: Centers for Research Excellence in Science and Technology (CREST)
E347: Dispute Resolution Institute
E348: Distance Education
E349: Division of Extended Studies
E350: Education
... E362: University College
B367: E-Rec Type
...

Sheet Sheet1
A1: Gender | B1: Race | C1: Tenure Status
A2: Female | B2: American Indian or Alaska Native and Black or African American not Hispanic or Latino | C2: Tenured Faculty
A3: Male | B3: American Indian or Alaska Native and White not Hispanic or Latino | C3: Tenure Track Faculty - Probationary Appointment
B4: American Indian or Alaska Native not Hispanic or Latino | C4: Non-Tenure Track Faculty
A5: next fiscal year | B5: Asian and White not Hispanic or Latino | C5: SAAO I with Faculty Rank (VC's, Deans,Dir. Of Library)
A6: 38534 | B6: Asian not Hispanic or Latino | C6: SAAO II with Faculty Rank (Asst/Assoc.VC's, Asst/Assoc. Deans, Unit Dir.)
B7: Black or African American and White not Hispanic or Latino | C7: Other EPA with Faculty Rank (Tutors,Librarians,Researchers, Coaches, Counselors, etc.)
B8: Black or African American not Hispanic or Latino | C8: SAAO I at will (VC's, Deans,Dir. Of Library)
B9: Native Hawaiian or Other Pacific Islander not Hispanic or Latino | C9: SAAO II at will (Asst/Assoc.VC's, Asst/Assoc. Deans, Unit Dir.)
B10: White Hispanic or Latino | C10: Other EPA at will (Tutors,Librarians,Researchers, Coaches, Counselors, etc.)
B11: White Not Hispanic or Latino | C11: SAAO I Fixed Term (VC's, Deans,Dir. Of Library)
B12: Unknown | C12: SAAO II Fixed Term (Asst/Assoc.VC's, Asst/Assoc. Deans, Unit Dir.)
C13: Other EPA Fixed Term (Tutors,Librarians,Researchers, Coaches, Counselors, etc.)
A14: Veteran: | B14: School | C14: No, not employed with any state entity as an employee
A15: YES | B15: Arts and Sciences | C15: Yes, the prospect is currently employed by another State Agency
A16: NO | B16: Business | C16: Yes,the prospect is currently employed by another campus in the UNC System
A17: Administrative Position | B17: Education | C17: Yes, the prospect is currently or within past 3 months was employed at NCCU
A18: Research Position | B18: Law
A19: Instructional Position | B19: Library and Information Science
A20: =IF(Worksheet!$I$15=3,A16,IF(Worksheet!$I$15<3,"NO",IF(Worksheet!$I$15=4,C2,IF(Worksheet!$I$15=5,C2,IF(Worksheet!$I$15=6,C2,IF(Worksheet!$I$15>=7,"",A17)))))) -> NO
A21: =IF(Worksheet!$I$15=3,A15,IF(Worksheet!$I$15<3,"YES",IF(Worksheet!$I$15=4,C3,IF(Worksheet!$I$15=5,C3,IF(Worksheet!$I$15=6,C3,IF(Worksheet!$I$15>=7,"",A17)))))) -> YES | B21: Instructor | C21: First of the allowable 2 one year contracts | D21: =IF(Worksheet!I15=1,"",IF(Worksheet!I15>3,"",IF(Worksheet!I15=3,"Fixed Term Appointment",IF(Worksheet!$H$15=4,setup!C25,IF(Worksheet!$H$15=3,setup!C21,IF(Worksheet!$H$15=2,setup!C21,"The First of the allowable 7 one year contracts")))))) -> The First of the allowable 7 one year contracts
A22: =IF(Worksheet!$I$15=3,"",IF(Worksheet!$I$15<3,"Chair",IF(Worksheet!$I$15=4,C4,IF(Worksheet!$I$15=5,C4,IF(Worksheet!$I$15=6,C4,IF(Worksheet!$I$15>=7,"",A17)))))) -> Chair | B22: Assistant Professor | C22: Second of the allowable 2 one year contracts | D22: =IF(Worksheet!I15=1,"",IF(Worksheet!I15>=3,"",IF(Worksheet!$H$15=4,"",IF(Worksheet!$H$15=3,setup!C22,IF(Worksheet!$H$15=2,setup!C22,"The Second of the allowable 7 one year contracts"))))) -> The Second of the allowable 7 one year contracts
B23: Associate Professor | C23: First of the allowable 2 three year contracts | D23: =IF(Worksheet!I15=1,"",IF(Worksheet!I15>=3,"",IF(Worksheet!$H$15=4,"",IF(Worksheet!$H$15=3,C25,IF(Worksheet!$H$15=2,setup!C23,"The Third of the allowable 7 one year contracts"))))) -> The Third of the allowable 7 one year contracts
B24: Professor | C24: Second of the allowable 2 three year contracts | D24: =IF(Worksheet!I15=1,"",IF(Worksheet!I15>=3,"",IF(Worksheet!$H$15=4,"",IF(Worksheet!$H$15=3,"",IF(Worksheet!$H$15=2,setup!C24,"The Fourth of the allowable 7 one year contracts"))))) -> The Fourth of the allowable 7 one year contracts
A25: Adjunct Lecturer | B25: Adjunct Instructor | C25: The allowable three year contract | D25: =IF(Worksheet!I15=1,"",IF(Worksheet!I15>=3,"",IF(Worksheet!$H$15=1,"The Fifth of the allowable 7 one year contracts",""))) -> The Fifth of the allowable 7 one year contracts
A26: Lecturer/Visiting Lecturer | B26: Adjunct Assistant Professor | D26: =IF(Worksheet!I15=1,"",IF(Worksheet!I15>=3,"",IF(Worksheet!$H$15=1,"The Sixth of the allowable 7 one year contracts",""))) -> The Sixth of the allowable 7 one year contracts
A27: Adjunct Preceptor | B27: Adjunct Associate Professor | D27: =IF(Worksheet!I15=1,"",IF(Worksheet!I15>=3,"",IF(Worksheet!$H$15=1,"The Seventh of the allowable 7 one year contracts",""))) -> The Seventh of the allowable 7 one year contracts
A28: Faculty Preceptor | B28: Adjunct Professor | F28: =VLOOKUP(G28,G29:H46,2,FALSE) -> Instructor | G28: =Worksheet!H15 -> 1
A29: Instructor/Tutor/Counselor | B29: Visiting Instructor | G29: 1 | H29: =C30 -> Instructor
A30: Research Assistant Professor | B30: Visiting Assistant Professor | C30: =IF(Worksheet!$I$15=1,B22,IF(Worksheet!$I$15=3,B25,IF(Worksheet!$I$15>=7,"No Rank",B21))) -> Instructor | G30: 2 | H30: =C31 -> Assistant Professor
A31: Research Associate Professor | B31: Visiting Associate Professor | C31: =IF(Worksheet!$I$15=1,B23,IF(Worksheet!$I$15=3,B26,IF(Worksheet!$I$15>=7,"",B22))) -> Assistant Professor | G31: 3 | H31: =C32 -> Associate Professor
A32: Research Professor | B32: Visiting Professor | C32: =IF(Worksheet!$I$15=1,B24,IF(Worksheet!$I$15=3,B27,IF(Worksheet!$I$15>=7,"",B23))) -> Associate Professor | G32: 4 | H32: =C33 -> Professor
A33: Artists/Writers in Residence | C33: =IF(Worksheet!$I$15=1,"",IF(Worksheet!$I$15=3,B28,IF(Worksheet!$I$15>=7,"",B24))) -> Professor | G33: 5 | H33: =C34
B34: 12-Month Appointment | C34: =IF(Worksheet!$I$15<3,"",IF(Worksheet!$I$15=3,B29,IF(Worksheet!$I$15>=7,"",B29))) | G34: 6 | H34: =C35
B35: Fall Semester Only | C35: =IF(Worksheet!$I$15<3,"",IF(Worksheet!$I$15=3,B30,IF(Worksheet!$I$15>=7,"",B30))) | G35: 7 | H35: =C36
B36: Spring Semester Only | C36: =IF(Worksheet!$I$15<3,"",IF(Worksheet!$I$15=3,B31,IF(Worksheet!$I$15>=7,"",B31))) | G36: 8 | H36: =C37
B37: Other (please specify) | C37: =IF(Worksheet!$I$15<3,"",IF(Worksheet!$I$15=3,B32,IF(Worksheet!$I$15>=7,"",B32))) | G37: 9 | H37: =C38
C38: =IF(Worksheet!$I$15<=2,"",IF(Worksheet!$I$15>=7,"",A25)) | G38: 10 | H38: =C39
B39: Faculty: Probationary Tenure Track Appointment | C39: =IF(Worksheet!$I$15<=2,"",IF(Worksheet!$I$15>=7,"",A26)) | G39: 11 | H39: =C40
B40: Faculty: Temporary/Fixed Term Appointment | C40: =IF(Worksheet!$I$15<=2,"",IF(Worksheet!$I$15>=7,"",A27)) | G40: 12 | H40: =C41
B41: Faculty: Non-Tenure Track Appointment | C41: =IF(Worksheet!$I$15<=2,"",IF(Worksheet!$I$15>=7,"",A28)) | G41: 13 | H41: =C42
B42: Faculty: Part-Time Appointment Only | C42: =IF(Worksheet!$I$15<=2,"",IF(Worksheet!$I$15>=7,"",A29)) | G42: 14 | H42: =C43
B43: Faculty: Permanent Tenure | C43: =IF(Worksheet!$I$15<=2,"",IF(Worksheet!$I$15>=7,"",A30)) | G43: 15 | H43: =C44
B44: Replacement for a Regular Faculty member on Leave | C44: =IF(Worksheet!$I$15<=2,"",IF(Worksheet!$I$15>=7,"",A31)) | G44: 16 | H44: =C45
B45: EPA Non-Faculty | C45: =IF(Worksheet!$I$15<=2,"",IF(Worksheet!$I$15>=7,"",A32)) | G45: 17 | H45: =C46
B46: Part-Time EPA Non-Faculty | C46: =IF(Worksheet!$I$15<=2,"",IF(Worksheet!$I$15>=7,"",A33))
B47: DUAL EMPLOYMENT (Specify the state agency)
B48: Graduate Student Assistant
B49: Senior Academic and Administrative Officer
B51: Research | E51: begin | F51: end
B52: Administrative Duties | C52: 9 month Academic Year Appointment | D52: =IF(Worksheet!$I$15=1,"Permanent",IF(Worksheet!$I$15=7,"At Will",IF(Worksheet!$I$15=8,"At Will",IF(Worksheet!$I$15=9,"At Will",setup!C52)))) -> 9 month Academic Year Appointment | E52: 38575
B53: Coach/Assistant Coach | C53: 10-Month Appointment | D53: =IF(Worksheet!$I$15=1,"",IF(Worksheet!$I$15=7,"",IF(Worksheet!$I$15=8,"",IF(Worksheet!$I$15=9,"",IF(Worksheet!$I$15=3,C56,setup!C53))))) -> 10-Month Appointment | E53: 38575
B54: Other (please specify) | C54: 11-Month Appointment | D54: =IF(Worksheet!$I$15=1,"",IF(Worksheet!$I$15=7,"",IF(Worksheet!$I$15=8,"",IF(Worksheet!$I$15=9,"",IF(Worksheet!$I$15=3,C57,setup!C54))))) -> 11-Month Appointment | E54: 38575
B55: Not Applicable | C55: Fiscal 12-Month Appointment | D55: =IF(Worksheet!$I$15=1,"",IF(Worksheet!$I$15=7,"",IF(Worksheet!$I$15=8,"",IF(Worksheet!$I$15=9,"",IF(Worksheet!$I$15=3,C58,setup!C55))))) -> Fiscal 12-Month Appointment | E55: July 1 2005
C56: Fall Semester Only | D56: =IF(Worksheet!$I$15=1,"",IF(Worksheet!$I$15=2,"",IF(Worksheet!$I$15=7,"",IF(Worksheet!$I$15=8,"",IF(Worksheet!$I$15=9,"",IF(Worksheet!$I$15=3,"",C56)))))) | E56: 38579
B57: A new position | C57: Spring Semester Only | D57: =IF(Worksheet!$I$15=1,"",IF(Worksheet!$I$15=2,"",IF(Worksheet!$I$15=7,"",IF(Worksheet!$I$15=8,"",IF(Worksheet!$I$15=9,"",IF(Worksheet!$I$15=3,"",C57)))))) | E57: January 3,2006
B58: A replacement position | C58: Other (please specify) | D58: =IF(Worksheet!$I$15=1,"",IF(Worksheet!$I$15=2,"",IF(Worksheet!$I$15=7,"",IF(Worksheet!$I$15=8,"",IF(Worksheet!$I$15=9,"",IF(Worksheet!$I$15=3,"",C58))))))
B59: The incumbent resigned | D59: =IF(Worksheet!$I$15=4,"At Will",IF(Worksheet!$I$15=5,"At Will",IF(Worksheet!$I$15=6,"At Will",IF(Worksheet!I15>=10,"",""))))
B60: The incumbent is on leave
B61: The incumbent has retired | C61: At Will
B62: The incumbent has been released
B63: The incumbent has been transferred
B64: Not applicable
C65: State Funds
B66: Days for Benefits | C66: Grant Funds
B67: 270 | C67: State and Grant Funds
B69: Professor
B70: Associate Professor
B71: Assistant Professor
B72: Instructor
B73: Visiting/Adjunct Professor
B74: Visiting/Adjunct Associate Professor
B75: Visiting/Adjunct Assistant Professor
B76: Visiting/Adjunct Instructor
B77: Clinical Professor
B78: Clinical Associate Professor
B79: Clinical Assistant Professor
B80: Clinical Instructor
... B132: Not Applicable

Sheet CIP codes
A1: CIP Codes | B1: CIP Description
A2: 030104 | B2: Environmental Science (NEW) | D2: 66 | E2: 1 | F2: =CONCATENATE(A2,B2) -> 030104Environmental Science (NEW)
A3: 090102 | B3: Mass Communication/ Media Studies | E3: 2 | F3: =CONCATENATE(A3,B3) -> 090102Mass Communication/ Media Studies
A4: 110401 | B4: Information Science/Studies | E4: 3 | F4: =CONCATENATE(A4,B4) -> 110401Information Science/Studies
A5: 110701 | B5: Computer Science | E5: 4 | F5: =CONCATENATE(A5,B5) -> 110701Computer Science
A6: 130301 | B6: Curriculum and Instruction | E6: 5 | F6: =CONCATENATE(A6,B6) -> 130301Curriculum and Instruction
A7: 130409 | B7: Secondary School Administration/Principalship (NEW) | E7: 6 | F7: =CONCATENATE(A7,B7) -> 130409Secondary School Administration/Principalship (NEW)
A8: 130501 | B8: Educational/Instructional Media Design | E8: 7 | F8: =CONCATENATE(A8,B8) -> 130501Educational/Instructional Media Design
A9: 131001 | B9: Special Education and Teaching- General | E9: 8 | F9: =CONCATENATE(A9,B9) -> 131001Special Education and Teaching- General
A10: 131005 | B10: Education/Teaching of Individuals with Emotional Disturbances | E10: 9 | F10: =CONCATENATE(A10,B10) -> 131005Education/Teaching of Individuals with Emotional Disturbances
A11: 131006 | B11: Education/Teaching of Individuals with Mental Retardation | E11: 10 | F11: =CONCATENATE(A11,B11) -> 131006Education/Teaching of Individuals with Mental Retardation
A12: 131009 | B12: Education/Teaching of Individuals with Vision Impairments Including Blindness | E12: 11 | F12: =CONCATENATE(A12,B12) -> 131009Education/Teaching of Individuals with Vision Impairments Including Blindness
A13: 131011 | B13: Education/Teaching of Individuals with Specific Learning Disabilities | E13: 12 | F13: =CONCATENATE(A13,B13) -> 131011Education/Teaching of Individuals with Specific Learning Disabilities
A14: 131101 | B14: Counselor Education/School Counseling and Guidance Services | E14: 13 | F14: =CONCATENATE(A14,B14) -> 131101Counselor Education/School Counseling and Guidance Services
A15: 131102 | B15: College Student Counseling and Personnel Services | E15: 14 | F15: =CONCATENATE(A15,B15) -> 131102College Student Counseling and Personnel Services
... A66: 540101 | B66: History- General | E66: 65 | F66: =CONCATENATE(A66,B66) -> 540101History- General
B67: No Choice | E67: 66
F70: =VLOOKUP(D2,E2:F68,2,FALSE)

Sheet CIP codes (2)
A1: CIP Codes | B1: CIP Description
A2: 030104 | B2: 030104 Environmental Science (NEW) | D2: 66 | E2: 1 | F2: =CONCATENATE(A2,B2) -> 030104030104 Environmental Science (NEW)
A3: 090102 | B3: 090102 Mass Communication/ Media Studies | E3: 2 | F3: =CONCATENATE(A3,B3) -> 090102090102 Mass Communication/ Media Studies
A4: 110401 | B4: 110401 Information Science/Studies | E4: 3 | F4: =CONCATENATE(A4,B4) -> 110401110401 Information Science/Studies
A5: 110701 | B5: 110701 Computer Science | E5: 4 | F5: =CONCATENATE(A5,B5) -> 110701110701 Computer Science
A6: 130301 | B6: 130301 Curriculum and Instruction | E6: 5 | F6: =CONCATENATE(A6,B6) -> 130301130301 Curriculum and Instruction
A7: 130409 | B7: 130409 Secondary School Administration/Principalship (NEW) | E7: 6 | F7: =CONCATENATE(A7,B7) -> 130409130409 Secondary School Administration/Principalship (NEW)
A8: 130501 | B8: 130501 Educational/Instructional Media Design | E8: 7 | F8: =CONCATENATE(A8,B8) -> 130501130501 Educational/Instructional Media Design
A9: 131001 | B9: 131001 Special Education and Teaching- General | E9: 8 | F9: =CONCATENATE(A9,B9) -> 131001131001 Special Education and Teaching- General
A10: 131005 | B10: 131005 Education/Teaching of Individuals with Emotional Disturbances | E10: 9 | F10: =CONCATENATE(A10,B10) -> 131005131005 Education/Teaching of Individuals with Emotional Disturbances
A11: 131006 | B11: 131006 Education/Teaching of Individuals with Mental Retardation | E11: 10 | F11: =CONCATENATE(A11,B11) -> 131006131006 Education/Teaching of Individuals with Mental Retardation
A12: 131009 | B12: 131009 Education/Teaching of Individuals with Vision Impairments Including Blindness | E12: 11 | F12: =CONCATENATE(A12,B12) -> 131009131009 Education/Teaching of Individuals with Vision Impairments Including Blindness
A13: 131011 | B13: 131011 Education/Teaching of Individuals with Specific Learning Disabilities | E13: 12 | F13: =CONCATENATE(A13,B13) -> 131011131011 Education/Teaching of Individuals with Specific Learning Disabilities
A14: 131101 | B14: 131101 Counselor Education/School Counseling and Guidance Services | E14: 13 | F14: =CONCATENATE(A14,B14) -> 131101131101 Counselor Education/School Counseling and Guidance Services
A15: 131102 | B15: 131102 College Student Counseling and Personnel Services | E15: 14 | F15: =CONCATENATE(A15,B15) -> 131102131102 College Student Counseling and Personnel Services
... A66: 540101 | B66: 540101 History- General | E66: 65 | F66: =CONCATENATE(A66,B66) -> 540101540101 History- General
B67: No Choice | E67: 66
F70: =VLOOKUP(D2,E2:F68,2,FALSE)

Sheet Database
A1: ID | B1: Pos # | C1: First Name | D1: Last Name | E1: Prevailing Salary | F1: Merit | G1: Tag | H1: SS# | I1: Salutation | J1: FTE | K1: Department | L1: School/College | M1: Address 1 | N1: Address 2 | O1: City | P1: State | Q1: PIN | R1: Mandated Raise | S1: Equity | T1: Promotion | U1: Stipend | V1: Other | W1: Total Salary | X1: Year | Y1: Percent Increase | Z1: Rank | AA1: Track | AB1: email | AC1: Contract Period | AD1: Beginning Date | AE1: End Date | AF1: Hours to teach | AG1: Type of Appointment | AH1: CIP Code | AI1: Ethnicity | AJ1: middle initial
B2: ='E Recomend'!A56 -> 0 | C2: ='E Recomend'!D5 | D2: ='E Recomend'!F5 | E2: ='E Recomend'!#REF! -> #REF! | H2: ='E Recomend'!H5 -> SS# : | I2: ='E Recomend'!D5 | J2: ='E Recomend'!H61 -> 0 | K2: ='E Recomend'!B26 | L2: ='E Recomend'!J24 -> 0 | M2: ='E Recomend'!B8 | N2: ='E Recomend'!B9 -> 0 | O2: ='E Recomend'!#REF! -> #REF! | P2: ='E Recomend'!G9 -> 0 | U2: ='E Recomend'!F60 -> 0 | W2: =SUM(U2:V2,R2,E2,F2) -> #REF! | Z2: =Worksheet!$H$15 -> 1 | AB2: ='E Recomend'!#REF! -> #REF! | AC2: =Worksheet!N20 -> 1 | AD2: ='E Recomend'!C65 | AE2: ='E Recomend'!F65 | AF2: ='E Recomend'!B79 -> 0 | AG2: =Worksheet!$J$15 -> 1 | AH2: ='E Recomend'!H43 | AI2: =Worksheet!$C$15 -> 0 | AJ2: ='E Recomend'!E5

Sheet setup
A1: Gender | B1: Race | C1: Tenure Status
A2: Female | B2: American Indian or Alaska Native and Black or African American not Hispanic or Latino | C2: Tenured Faculty
A3: Male | B3: American Indian or Alaska Native and White not Hispanic or Latino | C3: Tenure Track Faculty - Probationary Appointment
B4: American Indian or Alaska Native not Hispanic or Latino | C4: Non-Tenure Track Faculty
A5: next fiscal year | B5: Asian and White not Hispanic or Latino | C5: SAAO I with Faculty Rank (VC's, Deans,Dir. Of Library)
A6: 38534 | B6: Asian not Hispanic or Latino | C6: SAAO II with Faculty Rank (Asst/Assoc.VC's, Asst/Assoc. Deans, Unit Dir.)
B7: Black or African American and White not Hispanic or Latino | C7: Other EPA with Faculty Rank (Tutors,Librarians,Researchers, Coaches, Counselors, etc.)
B8: Black or African American not Hispanic or Latino | C8: SAAO I at will (VC's, Deans,Dir. Of Library)
B9: Native Hawaiian or Other Pacific Islander not Hispanic or Latino | C9: SAAO II at will (Asst/Assoc.VC's, Asst/Assoc. Deans, Unit Dir.)
B10: White Hispanic or Latino | C10: Other EPA at will (Tutors,Librarians,Researchers, Coaches, Counselors, etc.)
B11: White Not Hispanic or Latino | C11: SAAO I Fixed Term (VC's, Deans,Dir. Of Library)
B12: Unknown | C12: SAAO II Fixed Term (Asst/Assoc.VC's, Asst/Assoc. Deans, Unit Dir.)
C13: Other EPA Fixed Term (Tutors,Librarians,Researchers, Coaches, Counselors, etc.)
A14: Veteran: | B14: School | C14: No, not employed with any state entity as an employee
A15: YES | B15: Arts and Sciences | C15: Yes, the prospect is currently employed by another State Agency
A16: NO | B16: Business | C16: Yes,the prospect is currently employed by another campus in the UNC System
A17: Administrative Position | B17: Education | C17: Yes, the prospect is currently or within past 3 months was employed at NCCU
A18: Research Position | B18: Law
A19: Instructional Position | B19: Library and Information Science
A20: =IF(Worksheet!$I$15=3,A16,IF(Worksheet!$I$15<3,"NO",IF(Worksheet!$I$15=4,C2,IF(Worksheet!$I$15=5,C2,IF(Worksheet!$I$15=6,C2,IF(Worksheet!$I$15>=7,"",A17)))))) -> NO
A21: =IF(Worksheet!$I$15=3,A15,IF(Worksheet!$I$15<3,"YES",IF(Worksheet!$I$15=4,C3,IF(Worksheet!$I$15=5,C3,IF(Worksheet!$I$15=6,C3,IF(Worksheet!$I$15>=7,"",A17)))))) -> YES | B21: Instructor | C21: First of the allowable 2 one year contracts | D21: =IF(Worksheet!I15=1,"",IF(Worksheet!I15>3,"",IF(Worksheet!I15=3,"Fixed Term Appointment",IF(Worksheet!$H$15=4,setup!C25,IF(Worksheet!$H$15=3,setup!C21,IF(Worksheet!$H$15=2,setup!C21,"The First of the allowable 7 one year contracts")))))) -> The First of the allowable 7 one year contracts
A22: =IF(Worksheet!$I$15=3,"",IF(Worksheet!$I$15<3,"Chair",IF(Worksheet!$I$15=4,C4,IF(Worksheet!$I$15=5,C4,IF(Worksheet!$I$15=6,C4,IF(Worksheet!$I$15>=7,"",A17)))))) -> Chair | B22: Assistant Professor | C22: Second of the allowable 2 one year contracts | D22: =IF(Worksheet!I15=1,"",IF(Worksheet!I15>=3,"",IF(Worksheet!$H$15=4,"",IF(Worksheet!$H$15=3,setup!C22,IF(Worksheet!$H$15=2,setup!C22,"The Second of the allowable 7 one year contracts"))))) -> The Second of the allowable 7 one year contracts
B23: Associate Professor | C23: First of the allowable 2 three year contracts | D23: =IF(Worksheet!I15=1,"",IF(Worksheet!I15>=3,"",IF(Worksheet!$H$15=4,"",IF(Worksheet!$H$15=3,C25,IF(Worksheet!$H$15=2,setup!C23,"The Third of the allowable 7 one year contracts"))))) -> The Third of the allowable 7 one year contracts
B24: Professor | C24: Second of the allowable 2 three year contracts | D24: =IF(Worksheet!I15=1,"",IF(Worksheet!I15>=3,"",IF(Worksheet!$H$15=4,"",IF(Worksheet!$H$15=3,"",IF(Worksheet!$H$15=2,setup!C24,"The Fourth of the allowable 7 one year contracts"))))) -> The Fourth of the allowable 7 one year contracts
A25: Adjunct Lecturer | B25: Adjunct Instructor | C25: The allowable three year contract | D25: =IF(Worksheet!I15=1,"",IF(Worksheet!I15>=3,"",IF(Worksheet!$H$15=1,"The Fifth of the allowable 7 one year contracts",""))) -> The Fifth of the allowable 7 one year contracts
A26: Lecturer/Visiting Lecturer | B26: Adjunct Assistant Professor | D26: =IF(Worksheet!I15=1,"",IF(Worksheet!I15>=3,"",IF(Worksheet!$H$15=1,"The Sixth of the allowable 7 one year contracts",""))) -> The Sixth of the allowable 7 one year contracts
A27: Adjunct Preceptor | B27: Adjunct Associate Professor | D27: =IF(Worksheet!I15=1,"",IF(Worksheet!I15>=3,"",IF(Worksheet!$H$15=1,"The Seventh of the allowable 7 one year contracts",""))) -> The Seventh of the allowable 7 one year contracts
A28: Faculty Preceptor | B28: Adjunct Professor | F28: =VLOOKUP(G28,G29:H46,2,FALSE) -> Instructor | G28: =Worksheet!H15 -> 1
A29: Instructor/Tutor/Counselor | B29: Visiting Instructor | G29: 1 | H29: =C30 -> Instructor
A30: Research Assistant Professor | B30: Visiting Assistant Professor | C30: =IF(Worksheet!$I$15=1,B22,IF(Worksheet!$I$15=3,B25,IF(Worksheet!$I$15>=7,"No Rank",B21))) -> Instructor | G30: 2 | H30: =C31 -> Assistant Professor
A31: Research Associate Professor | B31: Visiting Associate Professor | C31: =IF(Worksheet!$I$15=1,B23,IF(Worksheet!$I$15=3,B26,IF(Worksheet!$I$15>=7,"",B22))) -> Assistant Professor | G31: 3 | H31: =C32 -> Associate Professor
A32: Research Professor | B32: Visiting Professor | C32: =IF(Worksheet!$I$15=1,B24,IF(Worksheet!$I$15=3,B27,IF(Worksheet!$I$15>=7,"",B23))) -> Associate Professor | G32: 4 | H32: =C33 -> Professor
A33: Artists/Writers in Residence | C33: =IF(Worksheet!$I$15=1,"",IF(Worksheet!$I$15=3,B28,IF(Worksheet!$I$15>=7,"",B24))) -> Professor | G33: 5 | H33: =C34
B34: 12-Month Appointment | C34: =IF(Worksheet!$I$15<3,"",IF(Worksheet!$I$15=3,B29,IF(Worksheet!$I$15>=7,"",B29))) | G34: 6 | H34: =C35
B35: Fall Semester Only | C35: =IF(Worksheet!$I$15<3,"",IF(Worksheet!$I$15=3,B30,IF(Worksheet!$I$15>=7,"",B30))) | G35: 7 | H35: =C36
B36: Spring Semester Only | C36: =IF(Worksheet!$I$15<3,"",IF(Worksheet!$I$15=3,B31,IF(Worksheet!$I$15>=7,"",B31))) | G36: 8 | H36: =C37
B37: Other (please specify) | C37: =IF(Worksheet!$I$15<3,"",IF(Worksheet!$I$15=3,B32,IF(Worksheet!$I$15>=7,"",B32))) | G37: 9 | H37: =C38
C38: =IF(Worksheet!$I$15<=2,"",IF(Worksheet!$I$15>=7,"",A25)) | G38: 10 | H38: =C39
B39: Faculty: Probationary Tenure Track Appointment | C39: =IF(Worksheet!$I$15<=2,"",IF(Worksheet!$I$15>=7,"",A26)) | G39: 11 | H39: =C40
B40: Faculty: Temporary/Fixed Term Appointment | C40: =IF(Worksheet!$I$15<=2,"",IF(Worksheet!$I$15>=7,"",A27)) | G40: 12 | H40: =C41
B41: Faculty: Non-Tenure Track Appointment | C41: =IF(Worksheet!$I$15<=2,"",IF(Worksheet!$I$15>=7,"",A28)) | G41: 13 | H41: =C42
B42: Faculty: Part-Time Appointment Only | C42: =IF(Worksheet!$I$15<=2,"",IF(Worksheet!$I$15>=7,"",A29)) | G42: 14 | H42: =C43
B43: Faculty: Permanent Tenure | C43: =IF(Worksheet!$I$15<=2,"",IF(Worksheet!$I$15>=7,"",A30)) | G43: 15 | H43: =C44
B44: Replacement for a Regular Faculty member on Leave | C44: =IF(Worksheet!$I$15<=2,"",IF(Worksheet!$I$15>=7,"",A31)) | G44: 16 | H44: =C45
B45: EPA Non-Faculty | C45: =IF(Worksheet!$I$15<=2,"",IF(Worksheet!$I$15>=7,"",A32)) | G45: 17 | H45: =C46
B46: Part-Time EPA Non-Faculty | C46: =IF(Worksheet!$I$15<=2,"",IF(Worksheet!$I$15>=7,"",A33))
B47: DUAL EMPLOYMENT (Specify the state agency)
B48: Graduate Student Assistant
B49: Senior Academic and Administrative Officer
B51: Research | E51: begin | F51: end
B52: Administrative Duties | C52: 9 month Academic Year Appointment | D52: =IF(Worksheet!$I$15=1,"Permanent",IF(Worksheet!$I$15=7,"At Will",IF(Worksheet!$I$15=8,"At Will",IF(Worksheet!$I$15=9,"At Will",setup!C52)))) -> 9 month Academic Year Appointment | E52: 38575
B53: Coach/Assistant Coach | C53: 10-Month Appointment | D53: =IF(Worksheet!$I$15=1,"",IF(Worksheet!$I$15=7,"",IF(Worksheet!$I$15=8,"",IF(Worksheet!$I$15=9,"",IF(Worksheet!$I$15=3,C56,setup!C53))))) -> 10-Month Appointment | E53: 38575
B54: Other (please specify) | C54: 11-Month Appointment | D54: =IF(Worksheet!$I$15=1,"",IF(Worksheet!$I$15=7,"",IF(Worksheet!$I$15=8,"",IF(Worksheet!$I$15=9,"",IF(Worksheet!$I$15=3,C57,setup!C54))))) -> 11-Month Appointment | E54: 38575
B55: Not Applicable | C55: Fiscal 12-Month Appointment | D55: =IF(Worksheet!$I$15=1,"",IF(Worksheet!$I$15=7,"",IF(Worksheet!$I$15=8,"",IF(Worksheet!$I$15=9,"",IF(Worksheet!$I$15=3,C58,setup!C55))))) -> Fiscal 12-Month Appointment | E55: July 1 2005
C56: Fall Semester Only | D56: =IF(Worksheet!$I$15=1,"",IF(Worksheet!$I$15=2,"",IF(Worksheet!$I$15=7,"",IF(Worksheet!$I$15=8,"",IF(Worksheet!$I$15=9,"",IF(Worksheet!$I$15=3,"",C56)))))) | E56: 38579
B57: A new position | C57: Spring Semester Only | D57: =IF(Worksheet!$I$15=1,"",IF(Worksheet!$I$15=2,"",IF(Worksheet!$I$15=7,"",IF(Worksheet!$I$15=8,"",IF(Worksheet!$I$15=9,"",IF(Worksheet!$I$15=3,"",C57)))))) | E57: January 3,2006
B58: A replacement position | C58: Other (please specify) | D58: =IF(Worksheet!$I$15=1,"",IF(Worksheet!$I$15=2,"",IF(Worksheet!$I$15=7,"",IF(Worksheet!$I$15=8,"",IF(Worksheet!$I$15=9,"",IF(Worksheet!$I$15=3,"",C58))))))
B59: The incumbent resigned | D59: =IF(Worksheet!$I$15=4,"At Will",IF(Worksheet!$I$15=5,"At Will",IF(Worksheet!$I$15=6,"At Will",IF(Worksheet!I15>=10,"",""))))
B60: The incumbent is on leave
B61: The incumbent has retired | C61: At Will
B62: The incumbent has been released
B63: The incumbent has been transferred
B64: Not applicable
C65: State Funds
B66: Days for Benefits | C66: Grant Funds
B67: 270 | C67: State and Grant Funds
B69: Professor
B70: Associate Professor
B71: Assistant Professor
B72: Instructor
B73: Visiting/Adjunct Professor
B74: Visiting/Adjunct Associate Professor
B75: Visiting/Adjunct Assistant Professor
B76: Visiting/Adjunct Instructor
B77: Clinical Professor
B78: Clinical Associate Professor
B79: Clinical Assistant Professor
B80: Clinical Instructor
... B132: Not Applicable

Sheet Worksheet K
C1: Intro | E1: Type of appointment | F1: Contract Period | G1: Salary | H1: Duties | I1: Benf. | J1: General
A2: Determining Options (in E recommend)
A3: App. Type | B3: =E3 -> 2 | C3: =Worksheet!I15 -> 2 | E3: =C3 -> 2
A4: Rank | B4: =Worksheet!H15 -> 1
A5: Contract Period | B5: =Worksheet!$N$15 -> 1 | E5: =Worksheet!$N$15 -> 1
A6: Administrative/Tenure Status | B6: =Worksheet!$O$15 -> 1 | C6: =Worksheet!O15 -> 1 | E6: =Worksheet!$O$15 -> 1
A7: Admin Stipend | B7: =IF('E Recomend'!F60>0,1,0) -> 0
A8: Type of tenure track contract | B8: =Worksheet!J15 -> 1
A9: Funding | B9: =Worksheet!M15 -> 2
A10: release | B10: ='E Recomend'!F73 -> FTE
A11: benefit f56
A12: CONTRACT PERIOD | B12: =IF(Worksheet!$N$15<=2,1,IF(Worksheet!$N$15=4,2,IF(Worksheet!$N$15=3,2,0))) -> 1 | D12: =CONCATENATE(B3,B5) -> 21 | E12: =CONCATENATE(B4,B8) -> 11 | H12: =CONCATENATE(B6,B3) -> 12
A13: FULL TIME | B13: =IF('E Recomend'!H61>=0.75,1,0) -> 0 | E13: =CONCATENATE(B3,B6) -> 21
A14: BENEFITS | B14: =SUM(B12:B13) -> 1 | C14: =C15 -> 1310 | E14: =IF(N28>0,N28,IF(Q28>0,Q28,IF(T28>0,T28,IF(W28>0,W28,"")))) -> I1 | F14: =IF(Worksheet!I15=1,"9 months",IF(Worksheet!N15=1,"9 months",IF(Worksheet!N15=2,"10 months",IF(Worksheet!N15=3,"11 months",IF(Worksheet!N15=4,"12 months",IF(Worksheet!N15=5,"4.5 (Fall Semester)",IF(Worksheet!N15=6,"4.5 (Spring Semester)",IF(Worksheet!N15=7,"Other","At Will")))))))) -> 9 months | G14: =IF(B7=1,"Stipend",IF(B9=1,"Salary","Grant")) -> Grant | H14: =H15 -> D5 | I14: =IF(B14=3,"LEAVE",IF(B14=2,"BENEFITS","NO BENEFITS")) -> NO BENEFITS
C15: =IF(B3>3,C16,IF(B3<=3,IF(B6=1,1310,IF(B6>1,1311,"")))) -> 1310 | D15: TENURE AND NON TRACK faculty | H15: =IF(H12="32","D3",IF(H12="31","D3",H16)) -> D5
C16: =IF(B3=4,1111,IF(B3=5,1111,IF(B3=7,1110,IF(B3=8,1110,IF(B3=10,1110,IF(B3=11,1110,C17)))))) -> 1310 | D16: INSTRUCTORSPROB. | F16: Codes | H16: =IF(B10>0,"D5",IF(B3<=2,"FACULTY DUTY",IF(B3=3,"D6",IF(B3>=7,"ADM DUTY","FACULTY ADM DUTY")))) -> D5
C17: =IF(B3=6,"EPA FACULTY",IF(B3=9,"EPA",IF(B3=12,"EPA",C15))) -> 1310 | F17: Tenured
E18: =IF(E12="17","I7",IF(E12="21","P1",IF(E12="22","P2",IF(E12="23","P3",IF(E12="24","P4",IF(E12="41","P5",E19)))))) -> 0 | F18: 9m
E19: =IF(B3=4,"EPA Tenured",IF(B3=5,"EPA Tenured",IF(B3=6,"EPA Tenured",E15))) -> 0 | F19: 10m
F20: 11m
F21: 12m
C22: I1 | F22: Fall
F23: Spring
F24: Other
F25: At Will
N26: PROBTIOARY AND TENURE | Q26: NON TENURE | T26: EPA | X26: TENURE
N28: =IF(B3=2,VLOOKUP(O28,O29:P46,2,FALSE),0) -> I1 | O28: =(B3*100)+(B4*10)+B8 -> 211 | Q28: =IF(B3>=7,VLOOKUP(R28,R29:S59,2,FALSE),IF(B3=3,VLOOKUP(R28,R29:S59,2,FALSE),0)) -> 0 | R28: =(B3*1000)+B5 -> 2001 | T28: =IF(B3<=3,0,IF(B3<=6,VLOOKUP(U28,U29:V37,2,FALSE),0)) -> 0 | U28: =(B3*100)+B6 -> 201 | W28: =IF(B3=1,VLOOKUP(X28,X29:Y32,2,FALSE),0) -> 0 | X28: =(B3*10)+B4 -> 21
O29: 221 | P29: P1 | R29: 7001 | S29: AW1 | U29: 401 | V29: TEN2 | X29: 11 | Y29: TEN
O30: 231 | P30: P1 | R30: 8001 | S30: AW1 | U30: 501 | V30: TEN2 | X30: 12 | Y30: TEN
O31: 222 | P31: P2 | R31: 9001 | S31: AW1 | U31: 601 | V31: TEN2 | X31: 13 | Y31: TEN
B32: Contract Clauses | D32: Main Salary | E32: =SUM('E Recomend'!F56:F58) -> 0 | O32: 232 | P32: P2 | R32: 3001 | S32: FT1 | U32: 402 | V32: TEN3
B33: =C14 -> 1310 | O33: 223 | P33: P3 | R33: 3002 | S33: FT2 | U33: 502 | V33: TEN3
B34: =E14 -> I1 | O34: 224 | P34: P4 | R34: 3003 | S34: FT3 | U34: 602 | V34: TEN3
B35: =F14 -> 9 months | O35: 233 | P35: P41 | R35: 3004 | S35: FT4 | U35: 403 | V35: FT4
B36: =G14 -> Grant | O36: 241 | P36: P5 | R36: 10004 | S36: FT5 | U36: 503 | V36: FT4
B37: =H14 -> D5 | O37: 211 | P37: I1 | R37: 11004 | S37: FT5 | U37: 603 | V37: FT4
B38: =I14 -> NO BENEFITS | O38: 212 | P38: I2 | R38: 12004 | S38: FT5
O39: 213 | P39: I3 | R39: 10001 | S39: FT4
O40: 214 | P40: I4 | R40: 10002 | S40: FT4
O41: 215 | P41: I5 | R41: 10003 | S41: FT4
O42: 216 | P42: I6 | R42: 10005 | S42: FT4
O43: 217 | P43: I7 | R43: 10006 | S43: FT4
R44: 10007 | S44: FT4
R45: 11001 | S45: FT4
R46: 11002 | S46: FT4
R47: 11003 | S47: FT4
R48: 11005 | S48: FT4
R49: 11006 | S49: FT4
R50: 11007 | S50: FT4
R51: 12001 | S51: FT4
R52: 12002 | S52: FT4
R53: 12003 | S53: FT4
R54: 12005 | S54: FT4
R55: 12006 | S55: FT4
R56: 12007 | S56: FT4

Sheet Clauses
H2: =CONCATENATE('E Recomend'!C5,I1,'E Recomend'!D5,I1,'E Recomend'!E5,I1,'E Recomend'!F5)
H3: ='E Recomend'!B8 | I3: ,
H4: =CONCATENATE('E Recomend'!#REF!,I3," ",'E Recomend'!G9,I1,'E Recomend'!#REF!) -> #REF!
B5: Clause | C5: variables | D5: Punctuation | F5: ='Worksheet K'!B33 -> 1310 | G5: Complete clause Intro
H6: =VLOOKUP(F5,F7:G12,2,FALSE) -> You are, by this document, offered an appointment to the faculty of North Carolina Central University. This appointment is subject to the pertinent provisions of the North Carolina Central University Tenure Policies and Regulations and Chapter Six of the Code of the University of North Carolina. Your appointment is to the faculty rank of Instructor. Your faculty appointment is in the Department of within the College of 0.
A7: faculty | B7: You are, by this document, offered an appointment to the faculty of North Carolina Central University. This appointment is subject to the pertinent provisions of the North Carolina Central University Tenure Policies and Regulations and Chapter Six of the Code of the University of North Carolina. Your appointment is to the faculty rank of | C7: =setup!F28 -> Instructor | D7: . | F7: 1310 | G7: =CONCATENATE(B7,C7,". ",B8," ",C8,D8) -> You are, by this document, offered an appointment to the faculty of North Carolina Central University. This appointment is subject to the pertinent provisions of the North Carolina Central University Tenure Policies and Regulations and Chapter Six of the Code of the University of North Carolina. Your appointment is to the faculty rank of Instructor. Your faculty appointment is in the Department of within the College of 0. | H7: =VLOOKUP(F24,F25:G47,2,FALSE) -> This is a probationary appointment for a one (1) academic year period. This appointment constitutes the 1st of the allowable seven (7) one-year terms for your tenure track rank. The period of service for fulltime faculty is each academic year, which is generally defined in practices as commencing on the date of the Faculty Institute and ending the Friday next following the commencement ceremony in May for the academic year. The period covered by this appointment will be from August 11, 2005 to May 12, 2006.
B8: =B10 -> Your faculty appointment is in the Department of | C8: =IF(C11=FALSE,CONCATENATE('E Recomend'!B26," within the College of ",C10),C10) -> within the College of 0 | D8: . | F8: 1311 | G8: =CONCATENATE(B9,C9,D9," ",B10," ",C8,D10,B12," ",C12,D12,B13 ) -> You are, by this document, offered an appointment to the faculty of North Carolina Central University. This appointment is subject to the pertinent provisions of the North Carolina Central University Tenure Policies and Regulations and Chapter Six of the Code of the University of North Carolina. Your appointment is to the faculty rank of Instructor. Your faculty appointment is in the Department of within the College of 0. In addition to your faculty appointment, you are hereby offered an appointment as the . Your duties in that appointment are described in the position description and are incorporated by reference. | H8: =IF(F24=F46,I46,"")
A9: FACULTY ADM | B9: You are, by this document, offered an appointment to the faculty of North Carolina Central University. This appointment is subject to the pertinent provisions of the North Carolina Central University Tenure Policies and Regulations and Chapter Six of the Code of the University of North Carolina. Your appointment is to the faculty rank of | C9: =C7 -> Instructor | D9: . | F9: 1110 | G9: =CONCATENATE(B14," ",C14,D14) -> This is to offer you an appointment as a Senior Academic or Administrative Officer (hereafter SAO) at North Carolina Central University. This offer is tendered subject to the Code of the University of North Carolina and the Board of Governors of the University of North Carolina regulations on Senior Academic and Administrative Officers as adopted November 14, 1986 and as modified. The position title is . | H9: =VLOOKUP(F48,F49:G51,2,FALSE) -> Your total salary will be $Total .00 for 9 months service per year. This salary will be reviewed and may be adjusted each year in accordance with the standing policies of NCCU and the Board of Governors. Your position is financed by non-appropriated funds through the . The continuation of the position, and your continued presence in it, depend upon the availability of these funds.
B10: =IF(C11=FALSE,"Your faculty appointment is in the Department of ","Your faculty appointment is in the School of") -> Your faculty appointment is in the Department of | C10: ='E Recomend'!J24 -> 0 | D10: . | F10: 1111 | G10: =CONCATENATE(B15,C15,D15,B17,C17,D17," ",B18," ",C18,D18) -> This is to offer you an appointment as a Senior Academic or Administrative Officer (hereafter SAO) at North Carolina Central University. This offer is tendered subject to the Code of the University of North Carolina and the Board of Governors of the University of North Carolina regulations on Senior Academic and Administrative Officers as adopted November 14, 1986 and as modified. These policies shall determine the terms and conditions of employment particularly in the event there is a conflict that is not addressed in this document. The position title is . Further you are, by this document, offered an appointment to the faculty of North Carolina Central University. This appointment is subject to the pertinent provisions of the North Carolina Central University Tenure Policies and Regulations and Chapter Six of the Code of the University of North Carolina. Your appointment is to the faculty rank of Instructor. Your faculty appointment is in the Department of within the College of 0. | H10: =VLOOKUP(F53,F54:G58,2,FALSE) -> Your primary duty will be teaching, but you will also be expected to advise students and participate in the normal functioning of your Department and School. This means that, among other responsibilities, you will be expected to participate in the Faculty Institute, all University convocations and commencement ceremonies. In addition you shall evaluate and grade students' in a timely manner and maintain regularly scheduled office hours in order to advise and assist students.
C11: =ISNONTEXT('E Recomend'!B26) -> FALSE | F11: =A19 -> EPA | G11: =CONCATENATE(Text15,C19,D19) -> This is to offer you an appointment as an Employee Exempt from the State Personnel Act with no faculty Appointment (hereafter EPA Non-Faculty) at North Carolina Central University. This offer is tendered subject to the Code of the University of North Carolina and the Board of Governors of the University of North Carolina Personnel Policies for Designated Employees Exempt from the State Personnel Act, dated February 18, 1994, as originally adopted and subsequent revision. The position title is . | H11: =VLOOKUP(F53,H54:I59,2,FALSE) -> The expectations inherent in the tenure rules of the University include satisfactory completion of the requisite formal education, demonstration of professional competence, display of developed collegiality, and potential for future contribution, consistent with the needs and resources of the University. This contract is governed by the pertinent provisions of the North Carolina Central University Tenure Policies and Regulations, Chapter Six of the Code of The University of North Carolina and the Patent and Copyright Policies of North Carolina Central University. The incidents of tenure applicable to your rank are, by reference, incorporated herein. Tenure is granted by the Board of Governors upon recommendation through the administrative channels of the University. Tenure, if granted, is in North Carolina Central University only, not in the University of North Carolina.
B12: In addition to your faculty appointment, you are hereby offered an appointment as the | C12: ='E Recomend'!C36 | D12: . | F12: EPA Faculty | G12: =CONCATENATE(OLE_LINK5,C20,D20,B22,C22,D22,B23," ",C23,D23) -> This is to offer you an appointment as an Employee Exempt from the State Personnel Act at North Carolina Central University. This offer is tendered subject to the Code of the University of North Carolina and the Board of Governors of the University of North Carolina Personnel Policies for Designated Employees Exempt from the State Personnel Act, dated February 18, 1994, as originally adopted and subsequent revision. These policies shall determine the terms and conditions of employment particularly in the event there is a conflict that is not addressed in this document. The position title is . Further you are, by this document, offered an appointment to the faculty of North Carolina Central University. This appointment is subject to the pertinent provisions of the North Carolina Central University Tenure Policies and Regulations and Chapter Six of the Code of the University of North Carolina. Your appointment is to the faculty rank of Instructor.Your faculty appointment is in the Department of within the College of 0. | H12: =VLOOKUP(F53,J54:K59,2,FALSE) -> The normal class load is 12 credit hours per semester, and classes may be scheduled in the evenings and on the weekends.
B13: Your duties in that appointment are described in the position description and are incorporated by reference. | H13: =VLOOKUP(F53,L54:M59,2,FALSE) -> In consideration of the additional responsibilities assigned by this contract beyond the typical faculty duties, the university hereby reduces your faculty workload by FTE credit hours. This reduction shall remain in effect for the duration of this contract period except in the event that the duties assigned in addition to the faculty duties are voluntarily or involuntarily removed from your responsibility
A14: SAAO | B14: This is to offer you an appointment as a Senior Academic or Administrative Officer (hereafter SAO) at North Carolina Central University. This offer is tendered subject to the Code of the University of North Carolina and the Board of Governors of the University of North Carolina regulations on Senior Academic and Administrative Officers as adopted November 14, 1986 and as modified. The position title is | C14: =C12 | D14: . | H14: =VLOOKUP(F60,F61:G63,2,FALSE) -> Consistent with the applicable provisions of Administrative Code and the law of the state of North Carolina, this position is not eligibility for benefits.
A15: SAAO Faculty | B15: This is to offer you an appointment as a Senior Academic or Administrative Officer (hereafter SAO) at North Carolina Central University. This offer is tendered subject to the Code of the University of North Carolina and the Board of Governors of the University of North Carolina regulations on Senior Academic and Administrative Officers as adopted November 14, 1986 and as modified. These policies shall determine the terms and conditions of employment particularly in the event there is a conflict that is not addressed in this document. The position title is | C15: =C14 | D15: .
B17: Further you are, by this document, offered an appointment to the faculty of North Carolina Central University. This appointment is subject to the pertinent provisions of the North Carolina Central University Tenure Policies and Regulations and Chapter Six of the Code of the University of North Carolina. Your appointment is to the faculty rank of | C17: =C7 -> Instructor | D17: .
B18: =B10 -> Your faculty appointment is in the Department of | C18: =C8 -> within the College of 0 | D18: .
A19: EPA | B19: This is to offer you an appointment as an Employee Exempt from the State Personnel Act with no faculty Appointment (hereafter EPA Non-Faculty) at North Carolina Central University. This offer is tendered subject to the Code of the University of North Carolina and the Board of Governors of the University of North Carolina Personnel Policies for Designated Employees Exempt from the State Personnel Act, dated February 18, 1994, as originally adopted and subsequent revision. The position title is | C19: =C15 | D19: .
A20: EPA Faculty | B20: This is to offer you an appointment as an Employee Exempt from the State Personnel Act at North Carolina Central University. This offer is tendered subject to the Code of the University of North Carolina and the Board of Governors of the University of North Carolina Personnel Policies for Designated Employees Exempt from the State Personnel Act, dated February 18, 1994, as originally adopted and subsequent revision. These policies shall determine the terms and conditions of employment particularly in the event there is a conflict that is not addressed in this document. The position title is | C20: =C19 | D20: .
B22: Further you are, by this document, offered an appointment to the faculty of North Carolina Central University. This appointment is subject to the pertinent provisions of the North Carolina Central University Tenure Policies and Regulations and Chapter Six of the Code of the University of North Carolina. Your appointment is to the faculty rank of | C22: =C17 -> Instructor | D22: .
B23: =B8 -> Your faculty appointment is in the Department of | C23: =C18 -> within the College of 0 | D23: .
B24: Clause | C24: variables | D24: Punctuation | F24: ='Worksheet K'!B34 -> I1 | G24: Complete clause Type of appointment
A25: P1 | B25: This is a probationary appointment for a one (1) academic year period. This appointment constitutes the 1st of the allowable two (2) one-year terms for your tenure track rank. The period of service for fulltime faculty is each academic year, which is generally defined in practices as commencing on the date of the Faculty Institute and ending the Friday next following the commencement ceremony in May for the academic year. The period covered by this appointment will be from August 11, 2005 to May 12, 2006. | F25: P1 | G25: =B25 -> This is a probationary appointment for a one (1) academic year period. This appointment constitutes the 1st of the allowable two (2) one-year terms for your tenure track rank. The period of service for fulltime faculty is each academic year, which is generally defined in practices as commencing on the date of the Faculty Institute and ending the Friday next following the commencement ceremony in May for the academic year. The period covered by this appointment will be from August 11, 2005 to May 12, 2006.
A26: P2 | B26: This is a probationary appointment for a one (1) academic year period. This appointment constitutes the 2nd of the allowable two (2) one-year terms for your tenure track rank. The period of service for fulltime faculty is each academic year, which is generally defined in practices as commencing on the date of the Faculty Institute and ending the Friday next following the commencement ceremony in May for the academic year. The period covered by this appointment will be from August 11, 2005 to May 12, 2006. | F26: P2 | G26: =B26 -> This is a probationary appointment for a one (1) academic year period. This appointment constitutes the 2nd of the allowable two (2) one-year terms for your tenure track rank. The period of service for fulltime faculty is each academic year, which is generally defined in practices as commencing on the date of the Faculty Institute and ending the Friday next following the commencement ceremony in May for the academic year. The period covered by this appointment will be from August 11, 2005 to May 12, 2006.
A27: P3 | B27: This is a probationary appointment for a three (3) academic year period. This appointment constitutes the 1st of the allowable two (2) three-year terms for your tenure track rank. The period of service for fulltime faculty is each academic year, which is generally defined in practices as commencing on the date of the Faculty Institute and ending the Friday next following the commencement ceremony in May for the academic year. The period covered by this appointment will be from August 11, 2005 to the Friday next following the commencement ceremony in May 2008. | F27: P3 | G27: =B27 -> This is a probationary appointment for a three (3) academic year period. This appointment constitutes the 1st of the allowable two (2) three-year terms for your tenure track rank. The period of service for fulltime faculty is each academic year, which is generally defined in practices as commencing on the date of the Faculty Institute and ending the Friday next following the commencement ceremony in May for the academic year. The period covered by this appointment will be from August 11, 2005 to the Friday next following the commencement ceremony in May 2008.
A28: P4 | B28: This is a probationary appointment for a three (3) academic year period. This appointment constitutes the 2nd of the allowable two (2) three-year terms for your tenure track rank. The period of service for fulltime faculty is each academic year, which is generally defined in practices as commencing on the date of the Faculty Institute and ending the Friday next following the commencement ceremony in May for the academic year. The period covered by this appointment will be from August 11, 2005 to the Friday next following the commencement ceremony in May 2008 | F28: P4 | G28: This is a probationary appointment for a three (3) academic year period. This appointment constitutes the 2nd of the allowable two (2) three-year terms for your tenure track rank. The period of service for fulltime faculty is each academic year, which is generally defined in practices as commencing on the date of the Faculty Institute and ending the Friday next following the commencement ceremony in May for the academic year. The period covered by this appointment will be from August 11, 2005 to the Friday next following the commencement ceremony in May 2008
A29: P41 | B29: This is a probationary appointment for a three (3) academic year period. This appointment constitutes the allowable three-year terms for your tenure track rank. The period of service for fulltime faculty is each academic year, which is generally defined in practices as commencing on the date of the Faculty Institute and ending the Friday next following the commencement ceremony in May for the academic year. The period covered by this appointment will be from August 11, 2005 to the Friday next following the commencement ceremony in May 2008. | F29: P41 | G29: This is a probationary appointment for a three (3) academic year period. This appointment constitutes the allowable three-year term for your tenure track rank. The period of service for fulltime faculty is each academic year, which is generally defined in practices as commencing on the date of the Faculty Institute and ending the Friday next following the commencement ceremony in May for the academic year. The period covered by this appointment will be from August 11, 2005 to the Friday next following the commencement ceremony in May 2008.
A30: P5 | B30: This is a probationary appointment for a three (3) academic year period. This appointment constitutes the allowable three-year terms for your tenure track rank. The period of service for fulltime faculty is each academic year, which is generally defined in practices as commencing on the date of the Faculty Institute and ending the Friday next following the commencement ceremony in May for the academic year. The period covered by this appointment will be from August 11, 2005 to the Friday next following the commencement ceremony in May 2008. | F30: P5 | G30: This is a probationary appointment for a three (3) academic year period. This appointment constitutes the allowable three-year term for your tenure track rank. The period of service for fulltime faculty is each academic year, which is generally defined in practices as commencing on the date of the Faculty Institute and ending the Friday next following the commencement ceremony in May for the academic year. The period covered by this appointment will be from August 11, 2005 to the Friday next following the commencement ceremony in May 2008.
A31: I1 | B31: This is a probationary appointment for a one (1) academic year period. This appointment constitutes the 1st of the allowable seven (7) one-year terms for your tenure track rank. The period of service for fulltime faculty is each academic year, which is generally defined in practices as commencing on the date of the Faculty Institute and ending the Friday next following the commencement ceremony in May for the academic year. The period covered by this appointment will be from August 11, 2005 to May 12, 2006. | F31: I1 | G31: This is a probationary appointment for a one (1) academic year period. This appointment constitutes the 1st of the allowable seven (7) one-year terms for your tenure track rank. The period of service for fulltime faculty is each academic year, which is generally defined in practices as commencing on the date of the Faculty Institute and ending the Friday next following the commencement ceremony in May for the academic year. The period covered by this appointment will be from August 11, 2005 to May 12, 2006.
A32: I2 | B32: This is a probationary appointment for a one (1) academic year period. This appointment constitutes the 2nd of the allowable seven (7) one-year terms for your tenure track rank. The period of service for fulltime faculty is each academic year, which is generally defined in practices as commencing on the date of the Faculty Institute and ending the Friday next following the commencement ceremony in May for the academic year. The period covered by this appointment will be from August 11, 2005 to May 12, 2006. | F32: I2 | G32: This is a probationary appointment for a one (1) academic year period. This appointment constitutes the 2nd of the allowable seven (7) one-year terms for your tenure track rank. The period of service for fulltime faculty is each academic year, which is generally defined in practices as commencing on the date of the Faculty Institute and ending the Friday next following the commencement ceremony in May for the academic year. The period covered by this appointment will be from August 11, 2005 to May 12, 2006.
A33: I3 | B33: This is a probationary appointment for a one (1) academic year period. This appointment constitutes the 3rd of the allowable seven (7) one-year terms for your tenure track rank. The period of service for fulltime faculty is each academic year, which is generally defined in practices as commencing on the date of the Faculty Institute and ending the Friday next following the commencement ceremony in May for the academic year. The period covered by this appointment will be from August 11, 2005 to May 12, 2006. | F33: I3 | G33: This is a probationary appointment for a one (1) academic year period. This appointment constitutes the 3rd of the allowable seven (7) one-year terms for your tenure track rank. The period of service for fulltime faculty is each academic year, which is generally defined in practices as commencing on the date of the Faculty Institute and ending the Friday next following the commencement ceremony in May for the academic year. The period covered by this appointment will be from August 11, 2005 to May 12, 2006.
A34: I4 | B34: This is a probationary appointment for a one (1) academic year period. This appointment constitutes the 4th of the allowable seven (7) one-year terms for your tenure track rank. The period of service for fulltime faculty is each academic year, which is generally defined in practices as commencing on the date of the Faculty Institute and ending the Friday next following the commencement ceremony in May for the academic year. The period covered by this appointment will be from August 11, 2005 to May 12, 2006. | F34: I4 | G34: This is a probationary appointment for a one (1) academic year period. This appointment constitutes the 4th of the allowable seven (7) one-year terms for your tenure track rank. The period of service for fulltime faculty is each academic year, which is generally defined in practices as commencing on the date of the Faculty Institute and ending the Friday next following the commencement ceremony in May for the academic year. The period covered by this appointment will be from August 11, 2005 to May 12, 2006.
A35: I5 | B35: This is a probationary appointment for a one (1) academic year period. This appointment constitutes the 5th of the allowable seven (7) one-year terms for your tenure track rank. The period of service for fulltime faculty is each academic year, which is generally defined in practices as commencing on the date of the Faculty Institute and ending the Friday next following the commencement ceremony in May for the academic year. The period covered by this appointment will be from August 11, 2005 to May 12, 2006. | F35: I5 | G35: This is a probationary appointment for a one (1) academic year period. This appointment constitutes the 5th of the allowable seven (7) one-year terms for your tenure track rank. The period of service for fulltime faculty is each academic year, which is generally defined in practices as commencing on the date of the Faculty Institute and ending the Friday next following the commencement ceremony in May for the academic year. The period covered by this appointment will be from August 11, 2005 to May 12, 2006.
A36: I6 | B36: This is a probationary appointment for a one (1) academic year period. This appointment constitutes the 6th of the allowable seven (7) one-year terms for your tenure track rank. The period of service for fulltime faculty is each academic year, which is generally defined in practices as commencing on the date of the Faculty Institute and ending the Friday next following the commencement ceremony in May for the academic year. The period covered by this appointment will be from August 11, 2005 to May 12, 2006. | F36: I6 | G36: This is a probationary appointment for a one (1) academic year period. This appointment constitutes the 6th of the allowable seven (7) one-year terms for your tenure track rank. The period of service for fulltime faculty is each academic year, which is generally defined in practices as commencing on the date of the Faculty Institute and ending the Friday next following the commencement ceremony in May for the academic year. The period covered by this appointment will be from August 11, 2005 to May 12, 2006.
A37: I7 | B37: This is a probationary appointment for a one (1) academic year period. This appointment constitutes the 7th of the allowable seven (7) one-year terms for your tenure track rank. The period of service for fulltime faculty is each academic year, which is generally defined in practices as commencing on the date of the Faculty Institute and ending the Friday next following the commencement ceremony in May for the academic year. The period covered by this appointment will be from August 11, 2005 to May 12, 2006. | F37: I7 | G37: This is a probationary appointment for a one (1) academic year period. This appointment constitutes the 7th of the allowable seven (7) one-year terms for your tenure track rank. The period of service for fulltime faculty is each academic year, which is generally defined in practices as commencing on the date of the Faculty Institute and ending the Friday next following the commencement ceremony in May for the academic year. The period covered by this appointment will be from August 11, 2005 to May 12, 2006.
A38: TEN | B38: Your faculty appointment is conferred with Permanent Tenure. Thus your faculty services will commence on August 11, 2005 and continues consistent with the provisions of the NCCU Tenure Policies and Regulations and Chapter Six of the Code of the University of North Carolina. The conferral of permanent tenure grants to members of the faculty a continuing faculty contract. The period of service for tenured faculty is each academic year, which is generally defined in practices as commencing on the date of the Faculty Institute and ending the Friday next following the commencement ceremony in May for the academic year. | F38: TEN | G38: Your faculty appointment is conferred with Permanent Tenure. Thus your faculty services will commence on August 11, 2005 and continues consistent with the provisions of the NCCU Tenure Policies and Regulations and Chapter Six of the Code of the University of North Carolina. The conferral of permanent tenure grants to members of the faculty a continuing faculty contract. The period of service for tenured faculty is each academic year on a continuing basis. An academic year is generally defined in practices as commencing on the date of the Faculty Institute and ending the Friday next following the commencement ceremony in May for the academic year.
A39: AW1 | B39: Your employment shall commence on | D39: . | F39: AW1 | G39: =CONCATENATE("Your employment shall commence on"," ",'E Recomend'!C65,C39,D39,B40) -> Your employment shall commence on . This position is categorized as employment at will and is subject to discontinuation at anytime at the discretion of the Chancellor.
B40: This position is categorized as employment at will and is subject to discontinuation at anytime at the discretion of the Chancellor.
A41: FT5 | B41: This is a non-tenure track appointment for a fixed term of one fiscal year. The period covered by this appointment will be from July 1, 2005 to June 30, 2006 | F41: FT5 | G41: =B41 -> This is a non-tenure track appointment for a fixed term of one fiscal year. The period covered by this appointment will be from July 1, 2005 to June 30, 2006
A42: FT1 | B42: This is a non-tenure track appointment for a fixed term of one academic year. The period covered by this appointment will be from August 11, 2005 to May 12, 2006. | F42: FT1 | G42: =B42 -> This is a non-tenure track appointment for a fixed term of one academic year. The period covered by this appointment will be from August 11, 2005 to May 12, 2006.
A43: FT2 | B43: This is a non-tenure track appointment for the Fall academic semester. The period covered by this appointment will be from August 11, 2005 to December 22, 2005. | F43: FT2 | G43: =B43 -> This is a non-tenure track appointment for the Fall academic semester. The period covered by this appointment will be from August 11, 2005 to December 22, 2005.
A44: FT3 | B44: This is a non-tenure track appointment for Spring academic semester. The period covered by this appointment will be from January 3, 2006 to the Friday next following the commencement ceremony in May 12, 2006. | F44: FT3 | G44: =B44 -> This is a non-tenure track appointment for Spring academic semester. The period covered by this appointment will be from January 3, 2006 to the Friday next following the commencement ceremony in May 12, 2006.
A45: FT4 | B45: This appointment is for a fixed term. The period of service covered by this appointment will commence on and end on . | F45: FT4 | G45: =B45 -> This appointment is for a fixed term. The period of service covered by this appointment will commence on and end on .
A46: TEN2 | B46: =CONCATENATE("Your employment shall commence on "," ",'E Recomend'!C65, "."," ","With regards to your faculty appointment, you have been conferred with permanent tenure." ) -> Your employment shall commence on . With regards to your faculty appointment, you have been conferred with permanent tenure. | F46: TEN2 | G46: =B46 -> Your employment shall commence on . With regards to your faculty appointment, you have been conferred with permanent tenure. | H46: =F46 -> TEN2 | I46: Thus your faculty service continues consistent with the provisions of the NCCU Tenure Policies and Regulations and Chapter Six of the Code of the University of North Carolina.
A47: TEN3 | B47: With regards to your faculty appointment, this is a probationary appointment for a academic year period. This appointment constitutes the of the allowable year terms for your tenure track rank. With regards to your administrative, instructional or research appointment, this position is categorized as employment at will. The continuation of this portion of your appointment is subject discontinuation at anytime at the discretion of the Chancellor. | F47: TEN3 | G47: =B47 -> With regards to your faculty appointment, this is a probationary appointment for a academic year period. This appointment constitutes the of the allowable year terms for your tenure track rank. With regards to your administrative, instructional or research appointment, this position is categorized as employment at will. The continuation of this portion of your appointment is subject discontinuation at anytime at the discretion of the Chancellor.
B48: Clause | C48: variables | D48: Punctuation | F48: ='Worksheet K'!B36 -> Grant | G48: Complete CLAUSE SALARY
F49: Salary | G49: =CONCATENATE("Your total salary will be $",'E Recomend'!F61,".00 ","for"," ",'Worksheet K'!B35," ","service per year. This salary will be reviewed and may be adjusted each year in accordance with the standing policies of NCCU and the Board of Governors.") -> Your total salary will be $Total .00 for 9 months service per year. This salary will be reviewed and may be adjusted each year in accordance with the standing policies of NCCU and the Board of Governors.
B50: =CONCATENATE("Your total salary will be $",C50,".00 ","for"," ",'Worksheet K'!B35," ","service per year.") -> Your total salary will be $Total .00 for 9 months service per year. | C50: ='E Recomend'!F61 -> Total | F50: Stipend | G50: =CONCATENATE(B50,B51,B52) -> Your total salary will be $Total .00 for 9 months service per year. Your total salary is comprised of a base salary associated with your appointment as a member of the faculty and an administrative stipend associated with your appointment as .Your based salary associated with your faculty appointment is $0.00. Your administrative stipend of $.00 is associated with your SAAO appointment. Since your administrative stipend is associated with your position as you can expect to receive the stipend as long as you serve in your administrative position. When you leave the Office, the stipend will be automatically detached from your salary. The detachment will be without evaluation and without appeal.
B51: =CONCATENATE(" Your total salary is comprised of a base salary associated with your appointment as a member of the faculty and an administrative stipend associated with your appointment as"," ",'E Recomend'!C36,".") -> Your total salary is comprised of a base salary associated with your appointment as a member of the faculty and an administrative stipend associated with your appointment as . | F51: Grant | G51: =CONCATENATE(G49," ","Your position is financed by non-appropriated funds through the ",'E Recomend'!G52,". ","The continuation of the position, and your continued presence in it, depend upon the availability of these funds.") -> Your total salary will be $Total .00 for 9 months service per year. This salary will be reviewed and may be adjusted each year in accordance with the standing policies of NCCU and the Board of Governors. Your position is financed by non-appropriated funds through the . The continuation of the position, and your continued presence in it, depend upon the availability of these funds.
B52: =CONCATENATE("Your based salary associated with your faculty appointment is"," ","$",'Worksheet K'!E32,".00."," ","Your administrative stipend of"," $",'E Recomend'!F60,".00 ","is associated with your SAAO appointment. Since your administrative stipend is associated with your position as"," ",'E Recomend'!C36," ","you can expect to receive the stipend as long as you serve in your administrative position. When you leave the Office, the stipend will be automatically detached from your salary. The detachment will be without evaluation and without appeal.") -> Your based salary associated with your faculty appointment is $0.00. Your administrative stipend of $.00 is associated with your SAAO appointment. Since your administrative stipend is associated with your position as you can expect to receive the stipend as long as you serve in your administrative position. When you leave the Office, the stipend will be automatically detached from your salary. The detachment will be without evaluation and without appeal.
B53: Clause | C53: variables | D53: Punctuation | F53: ='Worksheet K'!B37 -> D5 | G53: Complete duties | H53: ADD DUTIES
F54: FACULTY DUTY | G54: Your primary duty will be teaching, but you will also be expected to advise students and participate in the normal functioning of your Department and School. This means that, among other responsibilities, you will be expected to participate in the Faculty Institute, all University convocations and commencement ceremonies. In addition you shall evaluate and grade students' in a timely manner and maintain regularly scheduled office hours in order to advise and assist students. The normal class load is 12 credit hours per semester, and classes may be scheduled in the evenings and on the weekends. However, the number of course hours may vary. | H54: =$F54 -> FACULTY DUTY | I54: =K56 -> The expectations inherent in the tenure rules of the University include satisfactory completion of the requisite formal education, demonstration of professional competence, display of developed collegiality, and potential for future contribution, consistent with the needs and resources of the University. This contract is governed by the pertinent provisions of the North Carolina Central University Tenure Policies and Regulations, Chapter Six of the Code of The University of North Carolina and the Patent and Copyright Policies of North Carolina Central University. The incidents of tenure applicable to your rank are, by reference, incorporated herein. Tenure is granted by the Board of Governors upon recommendation through the administrative channels of the University. Tenure, if granted, is in North Carolina Central University only, not in the University of North Carolina. | J54: =$F54 -> FACULTY DUTY | L54: =$F54 -> FACULTY DUTY
F55: ADM DUTY | G55: =CONCATENATE("With respect to your appointment as ",'E Recomend'!C36,", ","the duties of your position are contained within the job description as it exists or may be modified. That description is incorporated by reference herein.") -> With respect to your appointment as , the duties of your position are contained within the job description as it exists or may be modified. That description is incorporated by reference herein. | H55: =$F55 -> ADM DUTY | J55: =$F55 -> ADM DUTY | L55: =$F55 -> ADM DUTY
F56: D3 | G56: As the Departmental Chair or a Program Director, the duties of your position are contained within the job description and policies as they exist or may be modified. Those documents are incorporated by reference herein. | H56: =$F56 -> D3 | I56: As a member of the faculty you will also be expected to advise students and participate in the normal functioning of your Department and School. This means that, among other responsibilities, you will be expected to participate in the Faculty Institute, all University convocations and commencement ceremonies. In addition you shall evaluate and grade students' in a timely manner and maintain regularly scheduled office hours in order to advise and assist students. | J56: =$F56 -> D3 | K56: The expectations inherent in the tenure rules of the University include satisfactory completion of the requisite formal education, demonstration of professional competence, display of developed collegiality, and potential for future contribution, consistent with the needs and resources of the University. This contract is governed by the pertinent provisions of the North Carolina Central University Tenure Policies and Regulations, Chapter Six of the Code of The University of North Carolina and the Patent and Copyright Policies of North Carolina Central University. The incidents of tenure applicable to your rank are, by reference, incorporated herein. Tenure is granted by the Board of Governors upon recommendation through the administrative channels of the University. Tenure, if granted, is in North Carolina Central University only, not in the University of North Carolina. | L56: =$F56 -> D3 | M56: The normal class load is 12 credit hours per semester, and classes may be scheduled in the evenings and on the weekends. In consideration of the additional responsibilities as Chairs/Director of an academic department or program, the university hereby reduces your faculty workload by six (6) credit hours. This reduction shall remain in effect for the duration of this contract period except in the event that the duties of Chairs/Director are voluntarily or involuntarily removed from your responsibility.
F57: FACULTY ADM DUTY | G57: =G55 -> With respect to your appointment as , the duties of your position are contained within the job description as it exists or may be modified. That description is incorporated by reference herein. | H57: =$F57 -> FACULTY ADM DUTY | I57: Regarding your teaching duty you will also be expected to advise students and participate in the normal functioning of your Department and School. This means that, among other responsibilities, you will be expected to participate in the Faculty Institute, all University convocations and commencement ceremonies. In addition you shall evaluate and grade students' in a timely manner and maintain regularly scheduled office hours in order to advise and assist students. The normal class load is 12 credit hours per semester, and classes may be scheduled in the evenings and on the weekends. However, in recognition of your other duties, the number of course hours will vary. | J57: =$F57 -> FACULTY ADM DUTY | K57: The expectations inherent in the tenure rules of the University include satisfactory completion of the requisite formal education, demonstration of professional competence, display of developed collegiality, and potential for future contribution, consistent with the needs and resources of the University. This contract is governed by the pertinent provisions of the North Carolina Central University Tenure Policies and Regulations, Chapter Six of the Code of The University of North Carolina and the Patent and Copyright Policies of North Carolina Central University. The incidents of tenure applicable to your rank are, by reference, incorporated herein. Tenure is granted by the Board of Governors upon recommendation through the administrative channels of the University. Tenure, if granted, is in North Carolina Central University only, not in the University of North Carolina. | L57: =$F57 -> FACULTY ADM DUTY
F58: D5 | G58: Your primary duty will be teaching, but you will also be expected to advise students and participate in the normal functioning of your Department and School. This means that, among other responsibilities, you will be expected to participate in the Faculty Institute, all University convocations and commencement ceremonies. In addition you shall evaluate and grade students' in a timely manner and maintain regularly scheduled office hours in order to advise and assist students. | H58: =$F58 -> D5 | I58: =K56 -> The expectations inherent in the tenure rules of the University include satisfactory completion of the requisite formal education, demonstration of professional competence, display of developed collegiality, and potential for future contribution, consistent with the needs and resources of the University. This contract is governed by the pertinent provisions of the North Carolina Central University Tenure Policies and Regulations, Chapter Six of the Code of The University of North Carolina and the Patent and Copyright Policies of North Carolina Central University. The incidents of tenure applicable to your rank are, by reference, incorporated herein. Tenure is granted by the Board of Governors upon recommendation through the administrative channels of the University. Tenure, if granted, is in North Carolina Central University only, not in the University of North Carolina. | J58: =$F58 -> D5 | K58: The normal class load is 12 credit hours per semester, and classes may be scheduled in the evenings and on the weekends. | L58: =$F58 -> D5 | M58: =CONCATENATE("In consideration of the additional responsibilities assigned by this contract beyond the typical faculty duties, the university hereby reduces your faculty workload by ",'E Recomend'!F73," credit hours. This reduction shall remain in effect for the duration of this contract period except in the event that the duties assigned in addition to the faculty duties are voluntarily or involuntarily removed from your responsibility" ) -> In consideration of the additional responsibilities assigned by this contract beyond the typical faculty duties, the university hereby reduces your faculty workload by FTE credit hours. This reduction shall remain in effect for the duration of this contract period except in the event that the duties assigned in addition to the faculty duties are voluntarily or involuntarily removed from your responsibility
F59: D6 | G59: Your primary duty will be teaching, but you will also be expected to participate in some of the normal functioning of your Department and School for non-tenure track faculty. | H59: =F59 -> D6 | I59: The expectations inherent in the employment of non-tenure track faculty at the University include satisfactory completion of the requisite formal education, demonstration of professional competence, display of developed collegiality, the evaluation and grading of students in a timely manner, and the maintenance of student conference hours in order to discuss with students grade appeals or provide advise on other academic issues. | J59: =$F59 -> D6 | K59: This contract is governed by the pertinent provisions of the North Carolina Central University Tenure Policies and Regulations, Chapter Six of the Code of The University of North Carolina and the Patent and Copyright Policies of North Carolina Central University. | L59: =$F59 -> D6
B60: Clause | C60: variables | D60: Punctuation | F60: ='Worksheet K'!B38 -> NO BENEFITS | G60: Complete duties | H60: ADD DUTIES
F61: LEAVE | G61: Consistent with the applicable provisions of the Administrative Code and the law of the state of North Carolina, this position includes eligibility for the State Health Plan, an employer supported retirement plan as well as other supplemental benefits. In accordance with the policies of the Board of Governors of the University of North Carolina, you may be eligible for leave including annual leave, sick leave, University Holidays and Family and Medical Leave.
F62: BENEFITS | G62: Consistent with the applicable provisions of the Administrative Code and the law of the state of North Carolina, this position includes eligibility for the State Health Plan, an employer supported retirement plan as well as other supplemental benefits.
F63: NO BENEFITS | G63: Consistent with the applicable provisions of Administrative Code and the law of the state of North Carolina, this position is not eligibility for benefits.

Sheet K
A2: North Carolina Central University
A3: Offer of Contract
A5: =CONCATENATE(Clauses!H2)
A6: =Clauses!H3
A7: =Clauses!H4 -> #REF!
A10: =Clauses!H6 -> You are, by this document, offered an appointment to the faculty of North Carolina Central University. This appointment is subject to the pertinent provisions of the North Carolina Central University Tenure Policies and Regulations and Chapter Six of the Code of the University of North Carolina. Your appointment is to the faculty rank of Instructor. Your faculty appointment is in the Department of within the College of 0.
A12: =Clauses!H7 -> This is a probationary appointment for a one (1) academic year period. This appointment constitutes the 1st of the allowable seven (7) one-year terms for your tenure track rank. The period of service for fulltime faculty is each academic year, which is generally defined in practices as commencing on the date of the Faculty Institute and ending the Friday next following the commencement ceremony in May for the academic year. The period covered by this appointment will be from August 11, 2005 to May 12, 2006.
A13: =Clauses!H8
A14: =Clauses!H9 -> Your total salary will be $Total .00 for 9 months service per year. This salary will be reviewed and may be adjusted each year in accordance with the standing policies of NCCU and the Board of Governors. Your position is financed by non-appropriated funds through the . The continuation of the position, and your continued presence in it, depend upon the availability of these funds.
A16: =Clauses!G54 -> Your primary duty will be teaching, but you will also be expected to advise students and participate in the normal functioning of your Department and School. This means that, among other responsibilities, you will be expected to participate in the Faculty Institute, all University convocations and commencement ceremonies. In addition you shall evaluate and grade students' in a timely manner and maintain regularly scheduled office hours in order to advise and assist students. The normal class load is 12 credit hours per semester, and classes may be scheduled in the evenings and on the weekends. However, the number of course hours may vary.
A18: =Clauses!H11 -> The expectations inherent in the tenure rules of the University include satisfactory completion of the requisite formal education, demonstration of professional competence, display of developed collegiality, and potential for future contribution, consistent with the needs and resources of the University. This contract is governed by the pertinent provisions of the North Carolina Central University Tenure Policies and Regulations, Chapter Six of the Code of The University of North Carolina and the Patent and Copyright Policies of North Carolina Central University. The incidents of tenure applicable to your rank are, by reference, incorporated herein. Tenure is granted by the Board of Governors upon recommendation through the administrative channels of the University. Tenure, if granted, is in North Carolina Central University only, not in the University of North Carolina.
A19: =IF(Clauses!H12<=0,"",Clauses!H12) -> The normal class load is 12 credit hours per semester, and classes may be scheduled in the evenings and on the weekends.
A20: =IF(Clauses!H13<=0,"",Clauses!H13) -> In consideration of the additional responsibilities assigned by this contract beyond the typical faculty duties, the university hereby reduces your faculty workload by FTE credit hours. This reduction shall remain in effect for the duration of this contract period except in the event that the duties assigned in addition to the faculty duties are voluntarily or involuntarily removed from your responsibility
A21: =Clauses!H14 -> Consistent with the applicable provisions of Administrative Code and the law of the state of North Carolina, this position is not eligibility for benefits.
A22: =Clauses!H15
A25: Kwesi E. Aggrey, Ph.D.
A26: Provost and Vice Chancellor for Academic Affairs
A27: Date
A29: The signature below indicates acceptance of the terms of the contract.
A31: =Clauses!H2
A32: Date
A33: STATE APPROPRIATIONS
A34: =CONCATENATE("Budget Item no.",'E Recomend'!B56) -> Budget Item no.
A35: ='E Recomend'!B58 -> 0
A36: ='E Recomend'!#REF! -> #REF!
A37: ='E Recomend'!#REF! -> #REF!
A38: =CONCATENATE("Position no.",'E Recomend'!A56) -> Position no.
A39: ='E Recomend'!A58 -> 0
A40: ='E Recomend'!#REF! -> #REF!
A41: ='E Recomend'!#REF! -> #REF!

Sheet APPENDIX B
A1: APPENDIX B: Alphabetic Listing of the Administrative Title Code Table 1
A2: Showing the Chair Flag, Code, Number of Occurances, and Title
A3: From the Fall 2008 PDF
A4: North Carolina Central University
A6: Code Administrative Title
A7: 051 Academic Advisor
A8: 038 Acting Chairman
A9: 041 Acting Director
A10: 043 Affirmative Action Officer
A11: 044 Archivist
A12: 026 Assistant Coach
A13: 007 Assistant Dean
... A72: 002 Vice Chancellor

Sheet Appendix F
A1: APPENDIX F: Alphabetic Listing of the Function Code Table 1
A2: Showing Rank Granting Dept Flag, and Number of Occurances of Home Departments,
A3: Depts of Rank, and Functions. From the Fall 2008 PDF
A4: North Carolina Central University
A5: Code Department Title
A6: 0010721 Academic Advising
A7: 2630000 Academic Computing Center
A8: 2700000 Academic Services
A9: 0010405 Academic Support Center
A10: 2130000 Academic Support Program
A11: 2300502 Accounting
A12: 4130000 Accounting Operations (Travel)
... A216: 0040041 V/C Student Affairs

Sheet Highest Degree
A1: Highest Earned Degree Abbreviations 1
A2: Sorted by Title
A3: Abbr Title Level
A4: ABD: "ALL BUT DISSERTATION" 3
A5: AAS: ASSOCIATE IN APPLIED SCIENCE 5
A6: AA: ASSOCIATE IN ARTS 5
A7: AS: ASSOCIATE IN SCIENCES 5
A8: BSHE: BACHELOR OF SCIENCE IN HOME ECONOMICS 4
A9: BSIE: BACHELOR OF SCIENCE IN INDUSTRIAL ENGINEERING 4
A10: BSIM: BACHELOR OF SCIENCE IN INDUSTRIAL MANAGEMENT 4
A11: BARCH: BACHELOR OF ARCHITECTURE 4
A12: AB: BACHELOR OF ARTS 4
... A272: SSP: SPECIALIST IN SCHOOL PSYCHOLOGY 7

Sheet Sheet5
