Workbook
Name Boards: #REF!
Name Boards: #REF!
Name Boards: #REF!

Sheet Start Here
A1: Welcome to the West Virginia Farm and Ranch Land Protection Program (FRPP) Application Matrix
A2: Please enter the below basic information to start the application.
A3: Information from this page will auto-complete information in the following tabs.
A4: Each tab is set for quick printing as needed.
A5: On all tabs, only complete the yellow highlighted areas.
A8: Entity Name:
A9: County Name:
A10: Contact Name:
A11: Contact Title:
A12: Contact Email:
A13: Contact Phone:
A14: Contact Address: | D14: Example | E14: 123 My Street
E15: Somewhere, WV 2XXXX
A17: Chairman Name:
A18: Chairman Email:
A19: Chairman Phone:
A20: Chairman Address: | D20: Example | E20: 123 My Street
E21: Somewhere, WV 2XXXX
A23: Date of Application:
A25: 2nd Entity Name:
A26: County Name:
A27: Contact Name:
A28: Contact Title:
A29: Contact Email:
A30: Contact Phone:
A31: Contact Address: | D31: Example | E31: 123 My Street
E32: Somewhere, WV 2XXXX
A34: Participant Name: | D34: All names on the Deed | I34: Choose the most common crop type on the application
A35: 2nd Participant: | E35: must be listed. | I35: Choose the most common livestock type on the application
A36: 3rd Participant: | D36: All other names here.
A37: Executor | D37: Contact if different then name on deed
A39: Participant Phone:
A40: Mailing Address: | D40: Example | E40: 123 My Street
E41: Somewhere, WV 2XXXX
A42: Physical Address: | D42: Example | E42: 123 My Street
A43: (If different) | E43: Somewhere, WV 2XXXX
A44: Google Map Link:
C80: West Virginia Agricultural Land Protection Authority | D80: WV | G80: Barley | H80: Aquaculture
C81: Berkeley County Farmland Protection Board | D81: Berkeley | G81: Berries | H81: Beef
C82: Fayette County Farmland Protection Board | D82: Fayette | G82: Coffee | H82: Bees
C83: Grant County Farmland Protection Board | D83: Grant | G83: Corn | H83: Bison
C84: Greenbrier County Farmland Protection Board | D84: Greenbrier | G84: Cotton | H84: Dairy
C85: Hampshire County Farmland Protection Board | D85: Hampshire | G85: Forage/Hay | H85: Deer
C86: Hardy County Farmland Protection Board | D86: Hardy | G86: Fruits | H86: Elk
C87: Jefferson County Farmland Protection Board | D87: Jefferson | G87: Ginseng | H87: Goats
C88: Lincoln County Farmland Protection Board | D88: Lincoln | G88: Grapes | H88: Horses
C89: Marshall County Farmland Protection Board | D89: Marshall | G89: Grass Seed | H89: Llamas
C90: Mineral County Farmland Protection Board | D90: Mineral | G90: No Crops | H90: Mules
C91: Monroe County Farmland Protection Board | D91: Monroe | G91: Nuts | H91: No Livestock
... C96: Preston County Farmland Protection Board | D96: Preston | G96: Peanuts | H96: Swine
C97: Roane County Farmland Protection Board | D97: Roane | G97: Potatoes
C98: Summers County Farmland Protection Board | D98: Summers | G98: Rice
C99: Upshur County Farmland Protection Board | D99: Upshur | G99: Sod
G100: Sorghum
G101: Soybeans
G102: Sugar Beets
G103: Sugar Maple
G104: Sugarcane
G105: Tobacco
G106: Trees
G107: Vegetables
G108: Wheat

Sheet Entity Checklist
A1: Farm and Ranch Land Protection Program (FRPP)
A2: Entity Application Checklist
A4: Entity: | C4: Contact Name:
A5: ='Start Here'!C8 -> 0 | C5: ='Start Here'!C10 -> 0
A6: Date: | C6: Phone No:
A7: ='Start Here'!C23 -> 0 | C7: ='Start Here'!C13 -> 0
A8: Please submit all information in a three ring binder using this checklist as the table of contents
A9: Primary Entity Information (The Entity that will be Accepting the Federal Contribution)
A10: 1. Evidence of an established entity (state or local government statute or ordinance or non-governmental organization mission statement attached). | C10: Enclose Exhibit A:
C11: Program documentation.
A12: 2. Evidence of a commitment to long-term conservation of agricultural or ranch lands through the use of voluntary conservation easements that protect farm lands from conversion to nonagricultural uses (list of easements acquired and held by the cooperating entity). | C12: Enclose Exhibit B:
C13: A list of closed conservation easements in the county or area
C14: Date of most recent monitoring of each easement.
C15: Entity which monitored each easement
A16: 3. Provide evidence of the entity’s policies related to title searches, title insurance and appraisal standards. | C16: Enclose Exhibit C:
C17: Policy for obtaining appraisals from a certified general appraiser using the UASFLA (Yellow Book) standard | E17: Use RFP approved by Authority and Assoc
C18: Policy for title searches and title insurance obtained for all easements.
A19: 4. Evidence of staff capability dedicated to easement monitoring and stewardship. | C19: Enclose Exhibit D:
C20: Full-time staff
C21: Part-time staff
C22: Contract staff and/or land trusts monitoring the easement
C23: Volunteers assigned to monitor easements for your entity.
A24: 5. Evidence of the availability of funds equal to at least 50 percent of the estimated fair market value of the conservation easement (including landowner donation)(State or local government appropriation or statement from non-government organization that funds are available attached). | C24: Enclose Exhibit E:
C25: Financial Position (Tab WV-300-24) completed and signed.
A26: 6. Landowner Parcel information. | C26: Enclose Exhibit F-
C27: Farm and Ranchland Protection Program- Landowner - Parcel Application
C28: Most recent county parcel application
A29: 7. Property Location is necessary for hazardous materials review and other application documentation. | C29: Enclose Exhibit G-
C30: Parcel Contact Information
A31: 8. Attach county location map of all protected parcels and indicate the location of this parcel. Indicate on the map any protected properties within a mile of the offered parcel. | C31: Enclose Exhibit H:
C32: Shape files
A33: 9. Agree to use the Model Deed of Conservation Easement | C33: Entity Signature
A34: Secondary Entity Information –Including NGO's (non-profit organizations such as land trusts) or governmental organizations
A35: Entity: | C35: Contact Name:
A36: ='Start Here'!C25 -> 0 | C36: ='Start Here'!C27 -> 0
A37: Date: | C37: Phone No:
A38: ='Start Here'!C23 -> 0 | C38: ='Start Here'!C30 -> 0
A39: Please submit all information in a three ring binder using this checklist as the table of contents
A40: A. Evidence of an established entity (state or local government statute or ordinance or non-governmental organization mission statement attached). | C40: Enclose Exhibit A:
C41: Program documentation.
C42: Entity documentation (state or local government statute or ordinance or non-governmental organization mission statement attached)
A43: B. Evidence of a commitment to long-term conservation of agricultural or ranch lands through the use of voluntary conservation easements that protect farm lands from conversion to nonagricultural uses (list of easements acquired and held by the cooperating entity). | C43: Enclose Exhibit B:
C44: A list of closed conservation easements in the county or area
C45: Date of most recent monitoring of each easement.
C46: Entity which monitored each easement
A47: C. Provide evidence of the entity’s policies related to title searches, title insurance and appraisal standards. | C47: Enclose Exhibit C:
C48: Policy for obtaining appraisals from a certified general appraiser using the UASFLA (Yellow Book) standard
C49: Policy for title searches and title insurance obtained for all easements.
A50: D. Evidence of staff capability dedicated to easement monitoring and stewardship. | C50: Enclose Exhibit D:
C51: Full-time staff
C52: Part-time staff
C53: Contract staff and/or land trusts monitoring the easement
C54: Volunteers assigned to monitor easements for your entity.
A55: E. Evidence of the availability of funds equal to at least 50 percent of the estimated fair market value of the conservation easement (including landowner donation)(State or local government appropriation or statement from non-government organization that funds are available attached). | C55: Enclose Exhibit E:
C56: Financial Position (Tab 2nd Entity WV-300-24) completed and signed.
A57: F. Attach county location map of all protected parcels and indicate the location of this parcel. Indicate on the map any protected properties within a mile of the offered parcel. | C57: Enclose Exhibit H:
C58: Shape files
A59: G. Agree to use the Model Deed of Conservation Easement | C59: Entity Signature

Sheet Financial Position
A1: Farm & Ranch Land Protection Program (FRPP)
A2: Financial Position
A6: Entity: | B6: ='Start Here'!C8 -> 0
A7: County: | B7: ='Start Here'!C9 -> 0
A8: ='Entity Checklist'!A6 -> Date: | B8: ='Start Here'!C23 -> 0
A10: Cash and Investments
A11: Easement Commitments
A12: Uncommitted funds currently available | E12: =E10-E11 -> 0
A14: Estimated Operations next 12 Months:
A16: Transfer Tax Revenues
A17: Administrative & Overhead
A18: Other Easement Commitments Planned
A19: Net available | E19: =E16-(E17+E18) -> 0
A21: Available for USDA Match | E21: =E12+E19 -> 0
A25: Print Name: | C25: ='Start Here'!C10 -> 0 | E25: Title: | F25: ='Start Here'!C11 -> 0
A27: Phone: | C27: ='Start Here'!C13 -> 0 | E27: E-Mail: | F27: ='Start Here'!C12 -> 0
A30: Signature: | F30: Date: | G30: ='Start Here'!C23 -> 0

Sheet 2nd Entity Financial Position
A1: Farm & Ranch Land Protection Program (FRPP)
A2: Financial Position
A6: Entity: | B6: ='Start Here'!C25 -> 0
A7: County: | B7: ='Start Here'!C26 -> 0
A8: ='Entity Checklist'!A6 -> Date: | B8: ='Start Here'!C23 -> 0
A10: Cash and Investments
A11: Easement Commitments
A12: Uncommitted funds currently available | E12: =E10-E11 -> 0
A14: Estimated Operations next 12 Months:
A16: Transfer Tax Revenues
A17: Administrative & Overhead
A18: Other Easement Commitments Planned
A19: Net available | E19: =E16-(E17+E18) -> 0
A21: Available for USDA Match | E21: =E12+E19 -> 0
A25: Print Name: | C25: ='Start Here'!C27 -> 0 | E25: Title: | F25: ='Start Here'!C28 -> 0
A27: Phone: | C27: ='Start Here'!C30 -> 0 | E27: E-Mail: | F27: ='Start Here'!C29 -> 0
A30: Signature: | F30: Date: | G30: ='Start Here'!C23 -> 0

Sheet Parcel Application
A1: Farm and Ranch Land Protection Program (FRPP)
A2: Landowner - Parcel Application
A4: Participant Name | G4: Entity
A5: ='Start Here'!C34 -> 0 | G5: ='Start Here'!C8 -> 0
A6: Date: | G6: County
A7: ='Start Here'!C23 -> 0 | G7: ='Start Here'!C9 -> 0
A9: This application is to be submitted with the WV-300-25 (Rev. 11/2011)
A11: 1 | B11: Entity or Entities Associated with the Parcel: | G11: =G5 -> 0
G12: ='Start Here'!C25 -> 0
A14: 2 | B14: Name(s) of the landowners of the parcel as stated in the deed: (All names on the deed must become Farm Bill Eligible) | G14: =A5 -> 0
G15: ='Start Here'!C35 -> 0
G16: ='Start Here'!C36 -> 0
A17: 3 | B17: If a partnership or corporation, names of all partners or shareholders. Power of attorney or authorized agent if needed. (please attach)
A20: 4 | B20: Physical Address of the parcel: (required for Phase I) | G20: Mailing Address of landowner(s):
B21: ='Start Here'!C42 -> 0 | G21: ='Start Here'!C40 -> 0
B22: ='Start Here'!C43 -> 0 | G22: ='Start Here'!C41 -> 0
A23: 5 | B23: Legal Description of the parcel. (Attach copy of deed, deeds or will) | G23: Deed Book(s)
G24: Page Number(s)
G25: Tax Map
G26: Parcel Number
A27: 6 | B27: Size of the parcel in acres offered for easement. | I27: Notes
C28: Easement (Including Exhibit B & D) | G28: 0 | H28: Acres
C29: Residential Dwelling (Exhibit B) | G29: 0 | H29: Acres | I29: 2 ac max per & subject to easement
C30: Retained Development (Exhibit D) | G30: 0 | H30: Acres | I30: 2 ac max per & subject to easement
C31: Locally Funded Only Area | G31: 0 | H31: Acres | I31: Not funded by NRCS contribution
I32: Not subject to the easement
C33: Donated Area | G33: 0 | H33: Acres | I33: Not funded by NRCS contribution
C34: Exception Area | G34: 0 | H34: Acres | I34: Will be subdivided prior to closing - not funded.
C35: Area offered to NRCS | G35: =G28 -> 0 | H35: Acres | I35: NRCS Easement
C36: Total Area of Easement | G36: =SUM(G28+G33) -> 0 | H36: Acres
C37: Total Farm Size | G37: =SUM(G28+G31+G33+G34) -> 0 | H37: Acres
A38: 7 | B38: FSA and NRCS Forms, including: Conservation Program Application (NRCS-CPA-1200); Payment Eligibility Form (Form CCC-526); Highly Erodible Land (Form AD-1026); Freedom of Information Forms; and AGI Certification (Form specific for year) | G38: Please complete these at the local FSA service center for Farm Bill Program eligibility.
G39: Update AGI each year enrolled in program.
A40: 8 | B40: Maps of the parcel showing the proposed NRCS easement area. | G40: Attach legible color aerial photo, tax map and soil map with table identifying the prime/unique/statewide/locally important soils.
A41: 9 | B41: Acres of the prime, unique, or Statewide and locally important soil in the proposed NRCS area. (Attach soils map and table) | H41: Prime: | J41: 0 | K41: Acres
H42: Unique: | J42: 0 | K42: Acres
H43: Statewide: | J43: 0 | K43: Acres
H44: Locally Important: | J44: 0 | K44: Acres
H45: Total: | J45: =SUM(J41+J42+J43+J44) -> 0 | K45: Acres
G46: Percent of Proposed NRCS area | J46: =SUM(J45/G35) -> #DIV/0!
G47: **Check copies of the soils reports
A48: 10 | B48: Analysis of proposed NRCS easement area: Cropland, pastureland, hayland, rangeland, wetland forest, non-wetland forest, non-forested wetlands, and incidental land. | G48: Cropland: | J48: 0 | K48: Acres
G49: Pastureland: | J49: 0 | K49: Acres
G50: Hayland: | J50: 0 | K50: Acres
G51: Forested Wetland: | J51: 0 | K51: Acres
G52: Forested (Non-Wetland): | J52: 0 | K52: Acres
B53: Timber Management Plan Required: | F53: =IF(C55+E55 >= 1, "Yes", "No") -> Yes | G53: Wetland (Non-Forested): | J53: 0 | K53: Acres
B54: Forest Eligibility | F54: =IF(B55 >=F55, "Ineligible", "Eligible") -> Ineligible | G54: Incidental land: | J54: 0 | K54: Acres
B55: =SUM(J51+J52) -> 0 | C55: =IF(B55 >=40, 1, 0) -> 0 | D55: =SUM(G35*20%) -> 0 | E55: =IF(B55 >= D55, 1, 0) -> 1 | F55: =SUM(G35*66%) -> 0 | G55: NRCS easement area | J55: =SUM(J48:J54) -> 0 | K55: Total Acres
C56: 40 acres | D56: 20 per | G56: **Total acres should match question #6 | K56: =IF(G35 =J55, 1, 0) -> 1
A57: 11 | B57: Impervious surface to proposed NRCS easement area and any additional requested. | G57: Max square footage allowed (2% of easement) | K57: =SUM((G36*0.02)*43560) -> 0
G58: Estimated current square footage | K58: 0
G59: Requested additional for future building(sq ft) | K59: 0
G60: Estimated total sq ft for easement | K60: =SUM(K58+K59) -> 0
A61: 12 | B61: Ownership of mineral rights for the proposed NRCS easement area, as well as any developmental or non-developmental gas leases, and intent to subordinate. (Attach copy of all leases and geologic assessment report). | G61: Check all that apply | J61: Yes | K61: No
G62: Severed mineral rights.
G63: Will this be subordinated?
G64: Developmental gas lease.
G65: Will this be subordinated?
G66: Non-developmental gas lease.
G67: Geologic Assessment Report
A68: 13 | B68: Historical resources proposed to be protected; a brief description of the site’s significance and documentation of the site’s listing on the Federal or State register. | G68: Attach documentation of Federal or State historical resources. Name(s) of sites, if none leave blank.
B70: State Register
A71: 14 | B71: Archaeological resources proposed to be protected; a brief description of the site’s significance and documentation of the site’s listing on the Federal or State register. | G71: Attach documentation of archeological resources. Name(s) of sites, if none leave blank.
A74: 15 | B74: Documentation on existence of rare, threatened and endangered species (plants or animals) from U. S. Fish and Wildlife or WV DNR. | G74: Attach documentation of rare, threatened and endangered species. Name(s) of species, if none leave blank.
B76: Rare, Threatened and Endangered Species List
A77: 16 | B77: Existence of year-round streams and/or springs. | G77: Attach documentation of year-round stream(s) and/or spring(s) on the parcel. Name(s) of streams or springs, if none leave blank.
A81: 17 | B81: Existence of cave(s) (as defined by the National Speleological Society), sinkholes and/or Karst topography. | G81: Attach documentation of the cave(s) and indicate if named as well as sinkholes and/or Karst topography. If none leave blank.
A84: 18 | B84: Offer amount per acre | G84: 0
A85: 19 | B85: Total offer amount for easement | G85: 0
A86: 20 | B86: Agree to use the Model Deed of Conservation Easement | G86: Model Deed of Conservation Easement
B91: Landowner Signature | H91: Date
A93: NOTE: The purpose of this application is to supply information required under the USDA-NRCS Federal Farm and Ranchland Protection Program that is necessary for your local farmland protection board to apply on your behalf. You may not apply directly to the USDA-NRCS. This application must be returned to your local county farmland protection board. The USDA-NRCS will complete the hazardous waste review on the property prior to funding approval.

Sheet Ranking Factors
A1: Farm and Ranch Land Protection Program (FRPP)
A2: Ranking Factors
A4: Participant Name: | B4: Entity:
A5: ='Start Here'!C34 -> 0 | B5: ='Start Here'!C8 -> 0
A6: Date: | B6: County:
A7: ='Start Here'!C23 -> 0 | B7: ='Start Here'!C9 -> 0
A8: National Factors
A9: Ranking Factor and Scaling | C9: Maximum | D9: Points
A10: 1. Percent of prime, unique, and important farmland in the parcel to be protected (0 points for 50 percent or less, 2 points for every percent above 50 percent) | C10: 100 | D10: =IF(D11 =E11, C11, 0) -> #DIV/0!
A11: (Eligibility Criteria) | B11: ='Parcel Application'!J46 -> #DIV/0! | C11: =SUM((B11-0.5)*2)*100 -> #DIV/0! | D11: =IF(C11 <0, 0, C11) -> #DIV/0! | E11: =IF(C11 >100, 100, C11) -> #DIV/0!
A12: 2. Percent of cropland, pastureland, grassland in the parcel to be protected (0 points for 33 percent or less, 1.5 points for every percent above 33 percent) | C12: 100 | D12: =IF(C13 =D13, E12, 0) -> #DIV/0! | E12: =IF(D13 >100, 100, D13) -> #DIV/0! | F12: =SUM((B13-0.33)*1.5)*100 -> #DIV/0!
A13: (Eligibility Criteria) | B13: =SUM('Parcel Application'!J48:J50)/'Parcel Application'!G35 -> #DIV/0! | C13: =IF(B13 <=0.33, 0, D13) -> #DIV/0! | D13: =IF(B13 >0.33, F12, 0) -> #DIV/0!
A14: 3. Ratio of the total acres of land in the parcel to be protected to average farm size in the county according to the most recent USDA Census of Agriculture (www.agcensus.usda.gov) (0 points for a ratio of 0.5 or less; 20 points for a ratio of 0.5 and 1.0; 20 points plus 1 point per acre for a ratio of 1.0 or greater) | C14: 200 | D14: =IF(F14 <=0, 0, F14) -> #DIV/0! | E14: =IF(C15 + D15 =40, 'Parcel Application'!G36-H122+D15,C15) -> #DIV/0! | F14: =IF(E14 >200, 200, E14) -> #DIV/0!
B15: =('Parcel Application'!G36/'Ranking Factors'!H122) -> #DIV/0! | C15: =IF(B15 >0.5, 20, 0) -> #DIV/0! | D15: =IF(B15 >1, 20, 0) -> #DIV/0!
A16: 4. Decrease in the percentage of acreage of farm and ranch land in the county in which the parcel is located between the last two USDA Censuses of Agriculture (www.agcensus.usda.gov) (0 points for decrease of 0 percent or less, 1 point for every percent of decrease up to 9.9 percent. 0 points for decrease of more than 10 percent) | C16: 10 | D16: =IF(C17 =D17, B17, 0) -> 0
B17: =(100-I122) -> 100 | C17: =IF(B17 >0, B17, 0) -> 100 | D17: =IF(B17 <9.9, B17, 0) -> 0
A18: 5. Percent population growth in the county as documented by the United States Census (www.census.gov) (0 points for growth rate less than state growth rate, 5 points for growth rate 1 to 1.66 times state growth rate, 10 points for growth rate 1.67 to 2.33 times state growth rate, 15 points for growth rate 2.34 to 3 times state growth rate, 0 points for growth rate greater than 3 times state growth rate) | C18: 15 | D18: =E132 -> 0
A19: 6. Population density (population per square mile) as documented by the most recent United States Census (www.census.gov) (0 points for population density less than state population density, 10 points for population density of 1 to 2 times state population density, 15 points for population density of 2 to 3 times state population density, 5 points for population density of more than 3 times state population density) | C19: 15 | D19: =I132 -> 0
A20: Sub-total Points for National Ranking Factors | C20: =C10+C12+C14+C16+C18+C19 -> 440 | D20: =SUM(D10+D12+D14+D16+D18+D19) -> #DIV/0!
A22: Other National Criteria with no Mandate
A23: 7. Proximity of the parcel to other protected land, including military installations (0 points for no protected land within one mile of the boundaries of the parcel, 20 points for each protected parcel within one mile of the boundaries of the parcel) List protected land. (If none, leave blank)
C24: 20 | D24: =IF(A24 >0, 20, 0) -> 0
C25: 20 | D25: =IF(A25 >0, 20, 0) -> 0
C26: 20 | D26: =IF(A26 >0, 20, 0) -> 0
A27: 8. Proximity of the parcel to other agricultural operations and infrastructure (0 points for less than 250 acres of protected land within one mile of the boundaries of the parcel, 0 points for 250-500 acres of protected land within one mile of the boundaries of the parcel, 0 points for 500 acres or more of protected land within one mile of the boundaries of the parcel) | C27: 0 | D27: 0
A28: Sub-total Points for all National Ranking Factors | C28: =C20+C24+C25+C26 -> 500 | D28: =SUM(D20+D24+D25+D26+D27) -> #DIV/0!
A29: State Ranking Factors
A30: Multifunctional Benefits
A31: 1. Archaeological | C31: 20 | D31: =IF('Parcel Application'!G72 >0, 20, 0) -> 0 | E31: =IF(B7="Jefferson", 0,0) -> 0
A32: 2. Historic | C32: 20 | D32: =IF('Parcel Application'!G69 >0, 20, 0) -> 0 | E32: =IF(B7="Morgan", 0,0) -> 0
A33: Environmental Diversity | E33: =IF(B7="Berkeley", 0,0) -> 0
A34: 1. Endangered and/or threatened species | C34: 20 | D34: =IF('Parcel Application'!G75 >0, 20, 0) -> 0 | E34: =IF(B7="Mineral", 0,0) -> 0
A35: 2. Major Streams and/or Natural Springs | C35: 20 | D35: =IF('Parcel Application'!G79 >0, 20, 0) -> 0 | E35: =IF(B7="Monroe", 0,0) -> 0
A36: 3. Caves and sink-holes | C36: 20 | D36: =IF('Parcel Application'!G82 >0, 20, 0) -> 0 | E36: =IF(B7="Hampshire", 0,0) -> 0
A37: Parcel Factors | E37: =IF(B7="Hardy", 0,0) -> 0
A38: 1. Priority of farm in county ranking (total number of points available for all applications by an entity in annual offering is 100) | C38: 100 | D38: 0 | E38: =IF(B7="Grant", 0,0) -> 0
A39: 2. Chesapeake Bay Area | C39: 0 | D39: =SUM(E31:E39) -> 0 | E39: =IF(B7="Pendleton", 0,0) -> 0
A40: 3. Size relative to average farm size for the county | C40: 25 | D40: =IF(G41 <=0, 0, G41) -> 0
A41: (1 point for each acre greater than average farm size) | F41: ='Parcel Application'!G36-'Ranking Factors'!H122 -> 0 | G41: =IF(F41 >25, 25, F41) -> 0
A42: 4. Total farm offered for easement | C42: 25 | D42: =IF('Parcel Application'!G37 ='Parcel Application'!G36, 25, 0) -> 25
A43: 5. Prime, unique and important soils (1 point per acre) | C43: 250 | D43: =IF('Parcel Application'!J45 >250, 250, 'Parcel Application'!J45) -> 0
A44: Sub-Total Points for State Ranking Factors | C44: =C31+C32+C34+C35+C36+C38+C40+C42+C43+C39 -> 500 | D44: =SUM(D31+D32+D34+D35+D36+D38+D40+D42+D43) -> 25
A46: Total Points for National and State Ranking Factors | C46: =C28+C44 -> 1000 | D46: =SUM(D28+D44) -> #DIV/0!
A48: NRCS Office Use Only
A50: NRCS Employee Name: _______________________________________ Date:_______________
A52: NRCS Employee Name: _______________________________________ Date:______________
A54: NRCS Employee Name: _______________________________________ Date:______________
F101: 2.5 | G101: 77.1
A102: County Name | B102: Average Size 2002 | C102: 2007 | D102: Acres 02 | E102: Acres 07 | F102: Growth | G102: Per Sq | H102: Q3 | I102: Q4 | J102: Q5 | K102: Q6
A103: Berkeley | B103: 113 | C103: 90 | D103: 76393 | E103: 75102 | F103: 37.2 | G103: 324.4 | H103: =IF(B7 =A103, C103, 0) -> 0 | I103: =IF(B7 = "Berkeley", (E103/D103)*100, 0) -> 0 | J103: =IF(B7 = A103, F103-F101, 0) -> 0 | K103: =IF(B7 = A103, G103, 0) -> 0
A104: Fayette | B104: 101 | C104: 101 | D104: 24154 | E104: 26677 | F104: -3.2 | G104: 69.6 | H104: =IF(B7 ="Fayette", C104, 0) -> 0 | I104: =IF(B7 = "Fayette", (E104/D104)*100, 0) -> 0 | J104: =IF(B7 = A104, F104-F101, 0) -> 0 | K104: =IF(B7 = A104, G104, 0) -> 0
A105: Grant | B105: 302 | C105: 231 | D105: 107653 | E105: 108839 | F105: 5.6 | G105: 25 | H105: =IF(B7 ="Grant", C105, 0) -> 0 | I105: =IF(B7 = "Grant", (E105/D105)*100, 0) -> 0 | J105: =IF(B7 = A105, F105-F101, 0) -> 0 | K105: =IF(B7 = A105, G105, 0) -> 0
A106: Greenbrier | B106: 246 | C106: 201 | D106: 192599 | E106: 176995 | F106: 3 | G106: 34.8 | H106: =IF(B7 ="Greenbrier", C106, 0) -> 0 | I106: =IF(B7 = "Greenbrier", (E106/D106)*100, 0) -> 0 | J106: =IF(B7 = A106, F106-F101, 0) -> 0 | K106: =IF(B7 = A106, G106, 0) -> 0
A107: Hampshire | B107: 218 | C107: 191 | D107: 138617 | E107: 129190 | F107: 18.6 | G107: 37.4 | H107: =IF(B7 ="Hampshire", C107, 0) -> 0 | I107: =IF(B7 = "Hampshire", (E107/D107)*100, 0) -> 0 | J107: =IF(B7 = A107, F107-F101, 0) -> 0 | K107: =IF(B7 = A107, G107, 0) -> 0
A108: Hardy | B108: 274 | C108: 261 | D108: 128425 | E108: 134357 | F108: 10.7 | G108: 24.1 | H108: =IF(B7 ="Hardy", C108, 0) -> 0 | I108: =IF(B7 = "Hardy", (E108/D108)*100, 0) -> 0 | J108: =IF(B7 = A108, F108-F101, 0) -> 0 | K108: =IF(B7 = A108, G108, 0) -> 0
A109: Jefferson | B109: 152 | C109: 132 | D109: 71880 | E109: 72091 | F109: 26.8 | G109: 255.2 | H109: =IF(B7 =A109, C109, 0) -> 0 | I109: =IF(B7 = "Jefferson", (E109/D109)*100, 0) -> 0 | J109: =IF(B7 = A109, F109-F101, 0) -> 0 | K109: =IF(B7 = A109, G109, 0) -> 0
A110: Lincoln | B110: 144 | C110: 151 | D110: 34935 | E110: 32393 | F110: -1.8 | G110: 49.7 | H110: =IF(B7 ="Lincoln", C110, 0) -> 0 | I110: =IF(B7 = "Lincoln", (E110/D110)*100, 0) -> 0 | J110: =IF(B7 = A110, F110-F101, 0) -> 0 | K110: =IF(B7 = A110, G110, 0) -> 0
A111: Marshall | B111: 128 | C111: 127 | D111: 90568 | E111: 95814 | F111: -6.8 | G111: 108.4 | H111: =IF(B7 =A111, C111, 0) -> 0 | I111: =IF(B7 = A111, (E111/D111)*100, 0) -> 0 | J111: =IF(B7 = A111, F111-F101, 0) -> 0 | K111: =IF(B7 = A111, G111, 0) -> 0
A112: Mineral | B112: 174 | C112: 158 | D112: 80986 | E112: 77957 | F112: 4.2 | G112: 86.1 | H112: =IF(B7 ="Mineral", C112, 0) -> 0 | I112: =IF(B7 = "Mineral", (E112/D112)*100, 0) -> 0 | J112: =IF(B7 = A112, F112-F101, 0) -> 0 | K112: =IF(B7 = A112, G112, 0) -> 0
A113: Monroe | B113: 213 | C113: 188 | D113: 145054 | E113: 132859 | F113: -7.4 | G113: 28.6 | H113: =IF(B7 ="Monroe", C113, 0) -> 0 | I113: =IF(B7 = "Monroe", (E113/D113)*100, 0) -> 0 | J113: =IF(B7 = A113, F113-F101, 0) -> 0 | K113: =IF(B7 = A113, G113, 0) -> 0
A114: Morgan | B114: 129 | C114: 106 | D114: 22953 | E114: 22440 | F114: 17.4 | G114: 76.6 | H114: =IF(B7 ="Morgan", C114, 0) -> 0 | I114: =IF(B7 = "Morgan", (E114/D114)*100, 0) -> 0 | J114: =IF(B7 = A114, F114-F101, 0) -> 0 | K114: =IF(B7 = A114, G114, 0) -> 0
A115: Nicholas | B115: 132 | C115: 118 | D115: 43922 | E115: 51332 | F115: -1.2 | G115: 40.6 | H115: =IF(B7 ="Nicholas", C115, 0) -> 0 | I115: =IF(B7 = "Nicholas", (E115/D115)*100, 0) -> 0 | J115: =IF(B7 = A115, F115-F101, 0) -> 0 | K115: =IF(B7 = A115, G115, 0) -> 0
A116: Pendleton | B116: 313 | C116: 283 | D116: 170634 | E116: 169876 | F116: -6.1 | G116: 11.1 | H116: =IF(B7 ="Pendleton", C116, 0) -> 0 | I116: =IF(B7 = "Pendleton", (E116/D116)*100, 0) -> 0 | J116: =IF(B7 = A116, F116-F101, 0) -> 0 | K116: =IF(B7 = A116, G116, 0) -> 0
A117: Pocahontas | B117: 327 | C117: 313 | D117: 123103 | E117: 121878 | F117: -4.5 | G117: 9.3 | H117: =IF(B7 ="Pocahontas", C117, 0) -> 0 | I117: =IF(B7 = "Pocahontas", (E117/D117)*100, 0) -> 0 | J117: =IF(B7 = A117, F117-F101, 0) -> 0 | K117: =IF(B7 = A117, G117, 0) -> 0
A118: Preston | B118: 155 | C118: 145 | D118: 142296 | E118: 152276 | F118: 14.3 | G118: 51.7 | H118: =IF(B7 ="Preston", C118, 0) -> 0 | I118: =IF(B7 = "Preston", (E118/D118)*100, 0) -> 0 | J118: =IF(B7 = A118, F118-F101, 0) -> 0 | K118: =IF(B7 = A118, G118, 0) -> 0
A119: Roane | B119: 184 | C119: 174 | D119: 99078 | E119: 117517 | F119: -3.4 | G119: 30.9 | H119: =IF(B7 =A119, C119, 0) -> 0 | I119: =IF(B7 =A119, (E119/D119)*100, 0) -> 0 | J119: =IF(B7 = A119, F119-F101, 0) -> 0 | K119: =IF(B7 = A119, G119, 0) -> 0
A120: Summers | B120: 175 | C120: 156 | D120: 54645 | E120: 59628 | F120: 7.1 | G120: 38.6 | H120: =IF(B7 ="Summers", C120, 0) -> 0 | I120: =IF(B7 = "Summers", (E120/D120)*100, 0) -> 0 | J120: =IF(B7 = A120, F120-F101, 0) -> 0 | K120: =IF(B7 = A120, G120, 0) -> 0
A121: Upshur | B121: 145 | C121: 141 | D121: 69458 | E121: 70882 | F121: 3.6 | G121: 68.4 | H121: =IF(B7 =A121, C121, 0) -> 0 | I121: =IF(B7 = A121, (E121/D121)*100, 0) -> 0 | J121: =IF(B7 = A121, F121-F101, 0) -> 0 | K121: =IF(B7 = A121, G121, 0) -> 0
H122: =SUM(H103:H121) -> 0 | I122: =SUM(I103:I121) -> 0 | J122: =SUM(J103:J121) -> 0 | K122: =SUM(K103:K121) -> 0
C126: Q5 Calcs | G126: Q6 Calcs
C128: =F101*1 -> 2.5 | D128: =AND(J122<=C128) -> TRUE | E128: =IF(D128 =TRUE, 0, 0) -> 0 | G128: =G101*1 -> 77.1 | H128: =AND(K122<=G128) -> TRUE | I128: =IF(H128 =TRUE, 0, 0) -> 0
C129: =F101*1.66 -> 4.15 | D129: =AND(J122 <=C129, J122>C128) -> FALSE | E129: =IF(D129 =TRUE, 5, 0) -> 0 | G129: =G101*2 -> 154.2 | H129: =AND(K122 <=G129, K122>G128) -> FALSE | I129: =IF(H129 =TRUE, 10, 0) -> 0
C130: =F101*2.33 -> 5.825 | D130: =AND(J122<=C130, J122>C129) -> FALSE | E130: =IF(D130 =TRUE, 10, 0) -> 0 | G130: =G101*3 -> 231.3 | H130: =AND(K122<=G130, K122>G129) -> FALSE | I130: =IF(H130 =TRUE, 15, 0) -> 0
C131: =F101*3 -> 7.5 | D131: =AND(J122<=C131, J122>C130) -> FALSE | E131: =IF(D131 =TRUE, 15, 0) -> 0 | G131: =G101*3 -> 231.3 | H131: =AND(K122>=G131) -> FALSE | I131: =IF(H131 =TRUE, 5, 0) -> 0
E132: =SUM(E128:E131) -> 0 | I132: =SUM(I128:I131) -> 0

Sheet Appraiser and Surveyor Info
A1: Farm and Ranch Land Protection Program (FRPP)
A2: Appraiser and Surveyor Summary Information
A3: 1 | B3: Entity or Entities Associated with the Parcel: | G3: ='Parcel Application'!G11:K11 -> 0
G4: ='Parcel Application'!G12:K12 -> 0
G5: ='Parcel Application'!G13:K13 -> 0
A6: 2 | B6: Name(s) of the landowners of the parcel as stated in the deed: (All names on the deed must become Farm Bill Eligible) | G6: ='Parcel Application'!G14:K14 -> 0
G7: ='Start Here'!C35 -> 0
G8: ='Start Here'!C36 -> 0
A9: 3 | B9: If a partnership or corporation, names of all partners or shareholders. Power of attorney or authorized agent if needed. (please attach) | G9: ='Parcel Application'!G17:K17 -> 0
G10: ='Parcel Application'!G18:K18 -> 0
G11: ='Parcel Application'!G19:K19 -> 0
A12: 4 | B12: Physical Address of the parcel: (required for Phase I) | G12: Mailing Address of landowner(s):
B13: ='Start Here'!C42 -> 0 | G13: ='Start Here'!C40 -> 0
B14: ='Start Here'!C43 -> 0 | G14: ='Start Here'!C41 -> 0
A15: 5 | B15: Legal Description of the parcel. (Attach copy of deed, deeds or will) | G15: Deed Book(s) | I15: ='Parcel Application'!I23:K23 -> 0
G16: Page Number(s) | I16: ='Parcel Application'!I24:K24 -> 0
G17: Tax Map | I17: ='Parcel Application'!I25:K25 -> 0
G18: Parcel Number | I18: ='Parcel Application'!I26:K26 -> 0
A19: 6 | B19: Size of the parcel in acres offered for easement. | I19: Notes
C20: Easement (Including Exhibit B & D) | G20: ='Parcel Application'!G28 -> 0 | H20: Acres
C21: Residential Dwelling (Exhibit B) | G21: ='Parcel Application'!G29 -> 0 | H21: Acres | I21: 2 ac max per & subject to easement
C22: Retained Development (Exhibit D) | G22: ='Parcel Application'!G30 -> 0 | H22: Acres | I22: 2 ac max per & subject to easement
C23: Locally Funded Only Area | G23: ='Parcel Application'!G31 -> 0 | H23: Acres | I23: Not funded by NRCS contribution
C24: Donated Area | G24: ='Parcel Application'!G33 -> 0 | H24: Acres | I24: Not funded by NRCS contribution
C25: Exception Area | G25: ='Parcel Application'!G34 -> 0 | H25: Acres | I25: Will be subdivided prior to closing - not funded.
C26: Area offered to NRCS | G26: =G20 -> 0 | H26: Acres | I26: NRCS Easement
C27: Total Area of Easement | G27: =SUM(G20+G24) -> 0 | H27: Acres
C28: Total Farm Size | G28: =SUM(G20+G23+G24+G25) -> 0 | H28: Acres
