Workbook

Sheet Cover

Sheet Introduction
A4: American Indian Higher Education Consortium
A5: American Indian Measures for Success (AIHEC-AIMS)
A7: AIMS Key Indicator System 2012 (AKIS 2012)

Sheet INSTRUCTIONS
A1: American Indian Higher Education Consortium
A2: American Indian Measures for Success (AIMS)
A4: AIMS-Key Indicator System 2012 (AKIS-2012)
A6: INSTRUCTIONS

Sheet 1.1a Overall Instit. Profile
A1: Institution | B1: =B5 -> Oglala Lakota College | K1: degree
A2: Indicator 1: Overall Institution Profile | K2: 4-year & master's
A3: Table 1.1a: Institution Profile, Contact Information, and Data Sources / AY 2011-12 | K3: 4-year& doctoral
A4: Institution Profile | K4: 4-year undergraduate
A5: Institution Name | B5: Oglala Lakota College | G5: Web Address | H5: www.olc.edu | K5: 2-year
A6: Address 1 | B6: Piya Wiconi - Three Mile Creek Road | G6: Highest Degree Offered | H6: 4-year & master's | I6: Academic Term | J6: semester
A7: Address 2 | B7: P.O. Box 490 | G7: Year Founded | H7: 1971 | I7: Land Granted Status | J7: yes | K7: academic term
A8: City | B8: Kyle | C8: State | D8: SD | E8: Zip | F8: 57752 | G8: Chartering Tribe | H8: Oglala Sioux Tribal Council | K8: quarter
A9: Telephone | B9: 605-455-6000 | G9: Operational Funding Source(s) | H9: Title I | K9: semester
A10: Main Campus Location | B10: Piya Wiconi - Three Mile Creek | C10: On/Off Reservation | G10: on | H10: Administrative Headquarters
A11: Additional Location (town, state) | B11: Allen, SD | C11: On/Off Reservation | G11: on | H11: Instructional Site
A12: Additional Location (town, state) | B12: Batesland, SD | C12: On/Off Reservation | G12: on | H12: Instructional Site
A13: Additional Location (town, state) | B13: Eagle Butte, SD | C13: On/Off Reservation | G13: on | H13: Instructional Site
A14: Additional Location (town, state) | B14: Manderson, SD | C14: On/Off Reservation | G14: on | H14: Instructional Site
A15: Additional Location (town, state) | B15: Martin, SD | C15: On/Off Reservation | G15: on | H15: Instructional Site
A16: Additional Location (town, state) | B16: Oglala, SD | C16: On/Off Reservation | G16: on | H16: Instructional Site
A17: Additional Location (town, state) | B17: Pine Ridge, SD | C17: On/Off Reservation | G17: on | H17: Instructional Site
A18: Additional Location (town, state) | B18: Porcupine, SD | C18: On/Off Reservation | G18: on | H18: Instructional Site
A19: Additional Location (town, state) | B19: Rapid City, SD | C19: On/Off Reservation | G19: off | H19: Instructional Site
A20: Additional Location (town, state) | B20: Wanblee, SD | C20: On/Off Reservation | G20: on | H20: Instructional Site
A21: Additional Location (town, state) | B21: Kyle, SD | C21: On/Off Reservation | G21: on | H21: Instructional Site
A22: Person(s) Responsible for this Report | K22: trimester
A23: Name | B23: Title | D23: Telephone | G23: Email Address | K23: other
A24: Ursula R. Gaertner | B24: Vice President for Instruction | D24: 605-455-6035 | H24: ugaertner@olc.edu
K25: land granted status
K26: yes
A27: Data Sources | K27: no
D28: Person(s) Responsible | G28: Notes
A29: Indicator 1: Overall Institution Profile | D29: Ursula Gaertner | K29: location
A30: Indicator 2: Financial Resources and Student Costs | D30: Eric Christensen | G30: Eric provided the information but resigned effective September 30, 2012 | K30: on reservation
A31: Indicator 3: Physical Resources | D31: Eric Christensen | G31: Eric provided the information but resigned effective September 30, 2012 | K31: off reservation
A32: Indicator 4: Student Enrollment and Graduation by Major Group | D32: Leslie Mesteth
A33: Indicator 5: Course Enrollment and Completion | D33: Leslie Mesteth
A34: Indicator 6: Student Activities | D34: Billi Hornbeck
A35: Indicator 7: Personnel Demographics, Professional Development, Research, and Outcomes | D35: Faith Richards
A36: Indicator 8: Students with Disabilities Enrollment and Graduation | D36: Leslie Heathershaw
A37: Notes: At the request of the Cheyenne River Sioux Tribe in Eagle Butte, SD, OLC also operates an Instructional Site at that location. Some functions are combined into one position.
A39: Please certify that your institution's President has seen and approved this submission.
A40: Thomas Shortbull, President | D40: Ursula R. Gaertner | H40: 41257
A41: President's Name & Signature | D41: Certified By | H41: Date

Sheet 1.1b Administration
A1: Institution | B1: ='1.1a Overall Instit. Profile'!$B$1 -> Oglala Lakota College
A2: Indicator 1: Overall Institution Profile
A3: Table 1.1b: Administration / AY 2012-13
A4: Please list the following administrators as of October 15, 2012 -- CURRENT Administration.
A5: Position | B5: Name | C5: Title | D5: Telephone | E5: E-mail
A6: President | B6: Thomas Shortbull | C6: President | D6: 605-455-6020 | E6: tshortb@olc.edu
A7: Assistant to President | B7: Diane Winters | C7: Assistant to President | D7: 605-455-6020 | E7: dwinters@olc.edu
A8: Chief Financial/ Business Officer | B8: vacant
A9: Chief Academic Officer | B9: Ursula R. Gaertner | C9: Vice President for Instruction | D9: 605-455-6035 | E9: ugaertner@olc.edu
A10: Chief Student Service Officer | B10: Billi Hornbeck | C10: Student Support Service Coordinator | D10: 605-455-6037 | E10: bhornbeck@olc.edu
A11: Registrar | B11: Leslie Mesteth | C11: Registrar | D11: 605-455-6033 | E11: lmesteth@olc.edu
A12: Financial Aid Officer | B12: Billi Hornbeck | C12: Financial Aid Officer | D12: 605-455-6037 | E12: bhornbeck@olc.edu
A13: Info. Tech. (MIS) | B13: Clifford DeLong | C13: Director, Infroamtion Technology | D13: 605-455-6079 | E13: cdelong@olc.edu
A14: Institutional Research | B14: vacant
A15: Assessment Officer | B15: vacant
A16: Development/Fundraising | B16: Marilyn Pourier | C16: Director of Development | D16: 605-455-6045 | E16: mpourier@olc.edu
A17: Office of Sponsored Programs | B17: N.A.
A18: Public Relations/ Communications | B18: Marilyn Pourier | C18: Director of Development | D18: 605-455-6045 | E18: mpourier@olc.edu
A19: Faculty Development Officer | B19: Ursula R. Gaertner | C19: Vice President for Instruction | D19: 605-455-6035 | E19: ugaertner@olc.edu

Sheet 1.2a Institution Profile
A1: Institution | D1: ='1.1a Overall Instit. Profile'!$B$1 -> Oglala Lakota College
A2: Indicator 1: Overall Institution Profile
A3: Table 1.2a: Institution Indian Student Count, Full Time Equivalent, and Tribal Affiliations / AY 2011-12
A4: Please enter the institution's Indian Student Count and Full time Equivalent (FTE) and five largest tribal affiliations of enrolled students.
A5: Student ISC and FTE Counts
B6: AY 2003-04 | E6: AY 2004-05 | H6: AY 2005-06 | K6: AY 2006-07 | N6: AY 2007-08
B7: Total | E7: Total | H7: Total | K7: Total | N7: Total
B8: 1126.4 | E8: 1202.51 | H8: 1131.51 | K8: 1069.8 | N8: 1069.63
B9: AY 2008-09
B10: Total
B11: 1046.35
A12: Full Time Equivalent (FTE)
C13: AY 2003-04 | H13: AY 2004-05 | M13: AY 2005-06
A14: American Indian | C14: Non-Indian | E14: FTE | F14: American Indian | H14: Non-Indian | J14: FTE | K14: American Indian | M14: Non-Indian
A15: M | B15: F | C15: M | D15: F | E15: Total | F15: M | G15: F | H15: M | I15: F | J15: Total | K15: M | L15: F | M15: M | N15: F
A16: 0 | B16: 0 | C16: 0 | D16: 0 | E16: =SUM(A16:D16) -> 0 | F16: 0 | G16: 0 | H16: 0 | I16: 0 | J16: =SUM(F16:I16) -> 0 | K16: 0 | L16: 0 | M16: 0 | N16: 0
C17: AY 2006-07 | H17: AY 2007-08 | M17: AY 2008-09
A18: American Indian | C18: Non-Indian | E18: FTE | F18: American Indian | H18: Non-Indian | J18: FTE | K18: American Indian | M18: Non-Indian
A19: M | B19: F | C19: M | D19: F | E19: Total | F19: M | G19: F | H19: M | I19: F | J19: Total | K19: M | L19: F | M19: M | N19: F
A20: 0 | B20: 0 | C20: 0 | D20: 0 | E20: =SUM(A20:D20) -> 0 | F20: 0 | G20: 0 | H20: 0 | I20: 0 | J20: =SUM(F20:I20) -> 0 | K20: 0 | L20: 0 | M20: 0 | N20: 0
A21: AY 2011-12 | C21: Part-Time AI Students | D21: Part-Time Non-AI Students | E21: Full-Time AI Students | F21: Full-Time Non-AI Students | G21: Part-Time AI Credits | H21: Part-Time Non-AI Credits | I21: Full-Time AI Credits | J21: Full-Time Non-AI Credits | K21: CEU AI Credits TOTAL | L21: ISC (see note) | M21: FTE (see note)
A22: Summer 2011 | C22: 172 | D22: 8 | E22: 21 | F22: 0 | G22: 891 | H22: 42 | I22: 282 | J22: 0 | K22: 25.9
A23: Fall 2011 | C23: 629 | D23: 67 | E23: 957 | F23: 35 | G23: 3961 | H23: 360 | I23: 11965 | J23: 439 | K23: 18.33
A24: Winter 2012 | C24: n.a. | D24: n.a. | E24: n.a. | F24: n.a. | G24: n.a. | H24: n.a. | I24: n.a. | J24: n.a. | K24: n.a.
A25: Spring 2012 | C25: 685 | D25: 81 | E25: 1016 | F25: 33 | G25: 4202 | H25: 382 | I25: 12805 | J25: 429 | K25: 23.13
A26: TOTAL | C26: =SUM(C22:C25) -> 1486 | D26: =SUM(D22:D25) -> 156 | E26: =SUM(E22:E25) -> 1994 | F26: =SUM(F22:F25) -> 68 | G26: =SUM(G22:G25) -> 9054 | H26: =SUM(H22:H25) -> 784 | I26: =SUM(I22:I25) -> 25052 | J26: =SUM(J22:J25) -> 868 | K26: =SUM(K22:K25) -> 67.36 | L26: =(SUM(G26,I26,)/24)+(K26*0.1) -> 1427.8193 | M26: =SUM(G26:J26)/24 -> 1489.9167
A27: ISC-- See glossary for full definition. ISC=((FTAICR+PTAICR)/24)+CEUs (or divided by 36 if on a quarter system), where CEUs used in calculation are limited to 10 percent.
A28: FTE--The sum of credits enrolled in by all students divided by 24 equals the full-time equivalency. FTE=(FTCR+PTCR)/24 (or divided by 36 if on a quarter system).
C29: Part-Time AI Students | D29: Part-Time Non-AI Students | E29: Full-Time AI Students | F29: Full-Time Non-AI Students | G29: Part-Time AI Credits | H29: Part-Time Non-AI Credits | I29: Full-Time AI Credits | J29: Full-Time Non-AI Credits | K29: CEU AI Credits TOTAL
A30: Fall 2012 | C30: 637 | D30: 60 | E30: 863 | F30: 29 | G30: 4050 | H30: 315 | I30: 10693 | J30: 378 | K30: 67.36
I31: Tribal Affiliations of Faculty, Staff, and Administrators at Tribal College
A32: Five Largest Tribal Affiliations of Students Enrolled at Tribal College
A33: Please list the five largest federally recognized tribes served by your institution. Total should not exceed total number of American Indian students enrolled (please see Table 4.2). | I33: Please list all federally recognized tribes for faculty, staff, and administrators represented at your institution. If more space is needed, please insert more lines.
A34: Fall 2011 (October 15, 2011) | I34: Oglala Sioux Tribe 115
A35: Tribe | F35: # Enrolled | G35: % of Enrollment | I35: Cheyenne River Sioux Tribe 6
A36: Oglala Sioux Tribe | F36: 1036 | G36: =SUM(F36/SUM('4.2 Major Group Totals'!D$10:'4.2 Major Group Totals'!E$10)) -> 0.64669164 | I36: Rosebud Sioux Tribe 3
A37: Cheyenne River Sioux Tribe | F37: 273 | G37: =SUM(F37/SUM('4.2 Major Group Totals'!D$10:'4.2 Major Group Totals'!E$10)) -> 0.17041199 | I37: Cherokee 1
A38: Rosebud Sioux Tribe | F38: 69 | G38: =SUM(F38/SUM('4.2 Major Group Totals'!D$10:'4.2 Major Group Totals'!E$10)) -> 0.043071161 | I38: Pueblo 1
A39: Standing Rock Sioux Tribe | F39: 36 | G39: =SUM(F39/SUM('4.2 Major Group Totals'!D$10:'4.2 Major Group Totals'!E$10)) -> 0.02247191 | I39: Tribe unknown 2
A40: Navajo Tribe | F40: 13 | G40: =SUM(F40/SUM('4.2 Major Group Totals'!D$10:'4.2 Major Group Totals'!E$10)) -> 0.0081148564

Sheet 1.2b Institutionial Narrative
A1: Institution | B1: ='1.1a Overall Instit. Profile'!$B$1 -> Oglala Lakota College | C1: ='1.1a Overall Instit. Profile'!$B$1 -> Oglala Lakota College | D1: ='1.1a Overall Instit. Profile'!$B$1 -> Oglala Lakota College | E1: ='1.1a Overall Instit. Profile'!$B$1 -> Oglala Lakota College | F1: ='1.1a Overall Instit. Profile'!$B$1 -> Oglala Lakota College | G1: ='1.1a Overall Instit. Profile'!$B$1 -> Oglala Lakota College | H1: ='1.1a Overall Instit. Profile'!$B$1 -> Oglala Lakota College | I1: ='1.1a Overall Instit. Profile'!$B$1 -> Oglala Lakota College | J1: ='1.1a Overall Instit. Profile'!$B$1 -> Oglala Lakota College
A2: Indicator 1: Overall Institution Profile
A3: Table 1.2b: Institutional Narrative / AY 2011-12
A4: Please insert a profile/description of your institution. Include, but do not limit the profile to, details about the institution’s location, land mass, population, establishment, programs, and what makes the institution unique. (See sample documents for examples.)
A5: Pine Ridge Reservation in South Dakota was established in 1889 after breaking up the Great Sioux Nation in 1868. The Pine Ridge Reservation has a population of 32,892 persons (HUD, 2012) who live in an area of over 3,648 square miles (larger than Delaware and Rhode Island together). The Bureau of Indian Affairs in its latest report, estimates that there are 46,855 members enrolled in the Oglala Sioux (Lakota) Tribe who live in the service area, which includes the Pine Ridge Reservation, Rapid City, and adjacent areas (BIA Labor Force Report, 2005). The only major city within a couple of hours driving distance from Pine Ridge is Rapid City (population 78,000). Chadron, Gordon and Rushville, NE are all within an hour of the southern Reservation boundary. None have a population over 5,000. The Pine Ridge Reservation has a representative government operating under a 1936 Indian Reorganization Act constitution. The legislative body is the 19 member Oglala Sioux Tribal Council. President and Vice-President are elected at large, and there is a five member Executive board. The Tribe is regarded as a sovereign nation according to US laws and treaties. The Tribe charters independent organizations like Oglala Lakota College, Oglala Sioux Department of Public Safety and Oglala Sioux (Lakota) Housing. The reservation is divided into nine districts with each having an elected district government and each electing representatives to the Tribal Council (www.oglalalakotanation.org). The state of South Dakota has divided the reservation into counties: Shannon is entirely within the reservation. Bennett and Jackson counties include three of the reservation districts and state jurisdiction areas as well. Distance, weather conditions, and the lack of serviceable automobiles are major transportation barriers with which reservation residents contend. Public transportation has just started on the reservation, and has limited service. Isolated homes and communities are served by gravel roads. Many homes on the reservation are inaccessible during periods of blizzards or heavy rain. Poverty has always been a feature of the Pine Ridge population. According to the 2010 U.S. Census, the Oglala Lakota per capita income was $7,772 and the poverty level was 53.5% for Shannon County, (four times the national average). The median income of residents in Shannon County from 2006 to 2010 was $24,392, almost half of that of the median of the country as a whole (US Census, Quickfacts). The number of persons living in a housing unit is nearly double the national median. It is common for multiple families to live in a two bedroom house. 87% of K/12 students on the Reservation receive free or reduced price lunches. 16.1% of adults over 25 are college graduates compared with 25.3% of the US population (US Census, Quickfacts). The BIA (2012a) gives the unemployment rate on the Reservation to be 89% with 34% of those employed still living below the poverty line. The State of South Dakota Office of Tribal Relations says that in 2000 33.4% of the labor force was unemployed, and that in 2005, 89% of Oglala Lakota tribal members were unemployed (SD Tribal Relations). This variation in numbers is the results of different definitions of unemployment as used by the US Census and other agencies. The Indian Health Service (IHS) US Department of Health and Human Services Report – Regional Differences in Indian Health 2002-2003 - the latest data collected - showed that the Aberdeen Area (which includes the Reservation) had the following death rates above the US average. Alcohol related +1290% Tuberculosis + 262% Homicide + 87% Heart disease + 50% Suicide + 212% Diabetes + 514% Native Americans smoke at twice the rate (46.5%) of other races, and infant mortality is over double that of the US average (Argus Leader (2007). Alcoholism affects 85% of families on the reservation (Woodward, 2012). Life expectancy for males on the reservation is 56.5 years and women 66 years (Kukarni et al, 2011). Scores on the standardized tests given as part of the federal No Child Left Behind effort in Spring 2011showed all students in South Dakota were 75% proficient in reading while 48% of Native Americans were proficient. The same ratio was true for math. 83% of all students starting the 9th grade graduated from high school in South Dakota, while 49% of Native-Americans did (Achievement Gap, 2012). OLC started offering classes at Mother Butler Center in Rapid City, SD at the request of the Indian community in 1985. In 1990 OLC built the He Sapa Instructional Center and has expanded the building twice since then. Many people from the Pine Ridge and Cheyenne River Reservation move to Rapid City for jobs and housing. The US Census put the Indian population of Rapid City at about 12,000 but as with the Reservation, Indian people are undercounted in the Census.
A8: Please share one or two significant challenges faced by your institution in AY 2011-12 (e.g., faculty changes, natural disaster, funding cuts, etc.).
A9: 1. Time spent on the road; all OLC faculty drive significatn distance4s to get to their classes and to the main administrative site. Many employees have a round trip of 180 to 200 miles a day. Traveling in bad weather is hazardous. 2. Student attendance in classes is a challenge; OLC policy allows four absenses (between 25 and 30% of the semester); homework is not turned in on time.

Sheet 1.3a First Time Students
A1: Institution | D1: ='1.1a Overall Instit. Profile'!$B$1 -> Oglala Lakota College
A2: Indicator 1: Overall Institution Profile
A3: Table 1.3a: First Time Entering Students Demographics / AY 2011-12
A4: Please enter the institution's first time entering student enrollment, background, and characteristics, including first-time freshman and transfer-in students. All data on this page are for the first time entering students only- not the entire institution.
A5: Time period: AY 2011 (Summer 2011 to Spring 2012)
A6: First Time Entering Student Enrollment
D7: American Indian | F7: Non-Indian | H7: Total | L7: Number of students who are | R7: American Indian | T7: Non-Indian
D8: M | E8: F | F8: M | G8: F | H8: M | I8: F | J8: Total | R8: M | S8: F | T8: M | U8: F
A9: Full Time | D9: 165 | E9: 202 | F9: 2 | G9: 3 | H9: =SUM(D9,F9) -> 167 | I9: =SUM(E9,G9) -> 205 | J9: =SUM(H9:I9) -> 372 | L9: Single - No Children | R9: 120 | S9: 145 | T9: 1 | U9: 6
A10: Part Time | D10: 43 | E10: 59 | F10: 3 | G10: 9 | H10: =SUM(D10,F10) -> 46 | I10: =SUM(E10,G10) -> 68 | J10: =SUM(H10:I10) -> 114 | L10: Single with dependent children | R10: 67 | S10: 92 | T10: 2 | U10: 3
A11: Total | D11: =SUM(D9:D10) -> 208 | E11: =SUM(E9:E10) -> 261 | F11: =SUM(F9:F10) -> 5 | G11: =SUM(G9:G10) -> 12 | H11: =SUM(D11,F11) -> 213 | I11: =SUM(E11,G11) -> 273 | J11: =SUM(H11:I11) -> 486 | L11: Married - No Children | R11: 5 | S11: 5 | T11: 0 | U11: 0
L12: Married with dependent children | R12: 18 | S12: 22 | T12: 0 | U12: 0
A13: First Time Entering Students Pre-College Preparation | L13: Responsible for elderly family members in home | R13: m | S13: m | T13: m | U13: m
A14: Number of students who | F14: American Indian | H14: Non-Indian | J14: Total
F15: M | G15: F | H15: M | I15: F | L15: Number of students who are | R15: American Indian | T15: Non-Indian
A16: Graduated High School with Diploma | F16: 142 | G16: 191 | H16: 2 | I16: 9 | J16: =SUM(H16:I16) -> 11 | R16: M | S16: F | T16: M | U16: F
B17: Number of HS graduates who graduated from | L17: First Generation Students | R17: m | S17: m | T17: m | U17: m
B18: Public High School not located on a reservation | F18: 0 | G18: 0 | H18: 0 | I18: o | J18: =SUM(H18:I18) -> 0 | L18: Not First Generation Students | R18: m | S18: m | T18: m | U18: m
B19: Reservation-based public High School | F19: 11 | G19: 33 | H19: 1 | I19: 2 | J19: =SUM(H19:I19) -> 3
B20: BIA school | F20: 44 | G20: 49 | H20: 0 | I20: 0 | J20: =SUM(H20:I20) -> 0 | L20: Primary residence is | R20: American Indian | T20: Non-Indian
B21: Tribal or Contract High School | F21: 33 | G21: 30 | H21: 0 | I21: 0 | J21: =SUM(H21:I21) -> 0 | R21: M | S21: F | T21: M | U21: F
B22: Other High School | F22: 54 | G22: 79 | H22: 1 | I22: 7 | J22: =SUM(H22:I22) -> 8 | L22: On / near reservation (within 60 miles) | R22: m | S22: m | T22: m | U22: m
A23: Earned GED | F23: 61 | G23: 55 | H23: 2 | I23: 3 | J23: =SUM(H23:I23) -> 5 | L23: In-State | R23: 206 | S23: 258 | T23: 5 | U23: 11
A24: Enrolled under Ability to Benefit provision | F24: 0 | G24: 0 | H24: 0 | I24: 0 | J24: =SUM(H24:I24) -> 0 | L24: Out-of-State | R24: 0 | S24: 0 | T24: 2 | U24: 4
A25: Dual enrolled High School and College | F25: 6 | G25: 14 | H25: 1 | I25: 0 | J25: =SUM(H25:I25) -> 1
A26: Have No High School Diploma or GED | F26: 0 | G26: 0 | H26: 0 | I26: 0 | J26: =SUM(H26:I26) -> 0 | L26: Financial Background | R26: American Indian | T26: Non-Indian
R27: M | S27: F | T27: M | U27: F
A28: Age range of students | L28: Average family income ($) in student's household | R28: 13328 | S28: 12797 | T28: 3000 | U28: 34482
A29: Number of students who are: | D29: 15-17 | E29: 18-21 | F29: 22-24 | G29: 25-34 | H29: 35-49 | I29: 50-64 | J29: 65 & over | L29: # of students employed less than 20 hrs/week (excluding work / study) | R29: m | S29: m | T29: m | U29: m
A30: American Indian | C30: M | D30: 3 | E30: 96 | F30: 34 | G30: 43 | H30: 26 | I30: 5 | J30: 1 | L30: # of students employed 20 or more hrs/week (excluding work / study) | R30: m | S30: m | T30: m | U30: m
C31: F | D31: 14 | E31: 125 | F31: 38 | G31: 45 | H31: 31 | I31: 6 | J31: 2 | L31: Number of students eligible for federal financial aid | R31: 75 | S31: 120 | T31: 1 | U31: 1
A32: Non-Indian | C32: M | D32: 1 | E32: 0 | F32: 2 | G32: 0 | H32: 1 | I32: 0 | J32: 1 | L32: Number of students in need, but not eligible for federal financial aid | R32: 4 | S32: 4 | T32: 0 | U32: 0
C33: F | D33: 0 | E33: 2 | F33: 4 | G33: 1 | H33: 5 | I33: 0 | J33: 0
L34: Number of students who | R34: American Indian | T34: Non-Indian
A35: Speakers of American Indian Languages | E35: None | F35: Limited | G35: Conversa-tional | H35: Fluent | R35: M | S35: F | T35: M | U35: F
A36: American Indian | C36: M | E36: 178 | F36: 33 | G36: m | H36: m | L36: Are Veterans | R36: 16 | S36: 11 | T36: 2 | U36: 1
C37: F | E37: 228 | F37: 30 | G37: m | H37: m | L37: Participated in a Head Start Program | R37: m | S37: m | T37: m | U37: m
A38: Non-Indian | C38: M | E38: 5 | F38: m | G38: m | H38: m
C39: F | E39: 12 | F39: m | G39: m | H39: m
A41: Skill Assessment / Placement Test Results
C42: Reading | G42: Writing / Composition | K42: Mathematics | O42: Science
B43: Test Name | C43: Accuplacer | G43: Accuplacer | K43: Accuplacer | O43: Accuplacer
C44: American Indian | E44: Non-Indian | G44: American Indian | I44: Non-Indian | K44: American Indian | M44: Non-Indian | O44: American Indian | Q44: Non-Indian
C45: M | D45: F | E45: M | F45: F | G45: M | H45: F | I45: M | J45: F | K45: M | L45: F | M45: M | N45: F | O45: M | P45: F | Q45: M | R45: F
A46: Number of students | B46: Taking Test | C46: 186 | D46: 269 | E46: 8 | F46: 10 | G46: 183 | H46: 268 | I46: 7 | J46: 10 | K46: 215 | L46: 312 | M46: 8 | N46: 12 | O46: n.a. | P46: n.a. | Q46: n.a. | R46: n.a.
B47: Placed in Remedial /Developmental Course Based on Test Results | C47: 84 | D47: 146 | E47: 3 | F47: 0 | G47: 83 | H47: 145 | I47: 3 | J47: 0 | K47: 214 | L47: 210 | M47: 4 | N47: 5 | O47: n.a. | P47: n.a. | Q47: n.a. | R47: n.a.
A49: Please note if any data collected is from a sample of students (e.g. financial background data is only from students who applied for financial aid).
A52: Notes:
A53: Re. Speakers of American Indian languages: the numbers reflect Yes/No answers only.

Sheet 1.3b General Student Pop
A1: Institution | D1: ='1.1a Overall Instit. Profile'!$B$1 -> Oglala Lakota College
A2: Indicator 1: Overall Institution Profile
A3: Table 1.3b: General Student Population Demographics / AY 2011-12
A4: Time period: Fall 2011 (October 15, 2011)
A5: Please enter the institution's general student population background, and characteristics, including first-time entering students.
A6: Age range of students
A7: Number of students who are: | D7: 15-17 | E7: 18-21 | F7: 22-24 | G7: 25-34 | H7: 35-49 | I7: 50-64 | J7: 65 & over
A8: American Indian | C8: M | D8: 0 | E8: 115 | F8: 83 | G8: 185 | H8: 119 | I8: 27 | J8: 2
C9: F | D9: 7 | E9: 206 | F9: 157 | G9: 341 | H9: 233 | I9: 100 | J9: 11
A10: Non-Indian | C10: M | D10: 1 | E10: 2 | F10: 4 | G10: 10 | H10: 10 | I10: 5 | J10: 2
C11: F | D11: 0 | E11: 6 | F11: 7 | G11: 20 | H11: 22 | I11: 12 | J11: 1
A13: Speakers of American Indian Languages | E13: None | F13: Limited | G13: Conversational | H13: Fluent
A14: American Indian | C14: M | E14: 444 | F14: 87 | G14: m | H14: m
C15: F | E15: 913 | F15: 142 | G15: m | H15: m
A16: Non-Indian | C16: M | E16: 34 | F16: m | G16: m | H16: m
C17: F | E17: 66 | F17: 2 | G17: m | H17: m
A19: Number of students who are | G19: American Indian | I19: Non-Indian
G20: M | H20: F | I20: M | J20: F
A21: Single - No Children | G21: 255 | H21: 335 | I21: 15 | J21: 20
A22: Single with dependent children | G22: 209 | H22: 556 | I22: 7 | J22: 18
A23: Married - No Children | G23: 8 | H23: 16 | I23: 3 | J23: 5
A24: Married with dependent children | G24: 59 | H24: 148 | I24: 9 | J24: 25
A25: Responsible for elderly family members in home | G25: m | H25: m | I25: m | J25: m
A27: Number of students who are | G27: American Indian | I27: Non-Indian
G28: M | H28: F | I28: M | J28: F
A29: First Generation Students | G29: m | H29: m | I29: m | J29: m
A30: Not First Generation Students | G30: m | H30: m | I30: m | J30: m
A32: Primary residence is | G32: American Indian | I32: Non-Indian
G33: M | H33: F | I33: M | J33: F
A34: On / near reservation (within 60 miles) | G34: m | H34: m | I34: m | J34: m
A35: In-State | G35: 527 | H35: 1037 | I35: 30 | J35: 58
A36: Out-of-State | G36: 4 | H36: 18 | I36: 4 | J36: 10
A38: Financial Background | G38: American Indian | I38: Non-Indian
G39: M | H39: F | I39: M | J39: F
A40: Average family income ($) in student's household | G40: 11743 | H40: 13019 | I40: 14903 | J40: 21099
A41: Number of students employed less than 20 hrs/week (excluding work / study) | G41: m | H41: m | I41: m | J41: m
A42: Number of students employed 20 or more hrs/week (excluding work / study) | G42: m | H42: m | I42: m | J42: m
A43: Number of students eligible for financial aid | G43: 381 | H43: 741 | I43: 16 | J43: 33
A44: Number of students in need, but not eligible for financial aid | G44: 47 | H44: 99 | I44: 0 | J44: 3
A46: Number of students who | G46: American Indian | I46: Non-Indian
G47: M | H47: F | I47: M | J47: F
A48: Are Veterans | G48: 13 | H48: 11 | I48: 2 | J48: 0
A50: Notes:
A51: Re. Speakers of American Indian Languages: the numbers represent yes/no answers. Numbers on student's household income reflect only students who completed a FAFSA.

Sheet 1.4 Institution Retention
A1: Institution | B1: ='1.1a Overall Instit. Profile'!$B$1 -> Oglala Lakota College
A2: Indicator 1: Overall Institution Profile
A3: Table 1.4: Institution Student Retention and Completion
A4: Please enter the total number of students entering the institution for the first time in fall 2009, including transfers.
A5: First-time entering students in fall 2009 | B5: 205
A6: Returned in fall 2011 | B6: 74
A7: Graduated in AY 2011-12 | B7: 6 | C7: # of Certificates | D7: 0 | E7: # of Associate's | F7: 6 | G7: # of Bachelor's | H7: 0 | I7: # of Master's | J7: 0
A8: Transferred to another college or university in AY 2011-12 | B8: 0 | D8: # of graduates who returned to pursue another certificate or degree** | I8: 6
A9: Withdrew or stopped out in AY 2011-12 | B9: 149
A10: Other Exclusions in 2011-12* | B10: 0
A11: Returned in fall 2012 | B11: 56
A13: Please enter the total number of students entering the institution for the first time in fall 2010, including transfers.
A14: First-time entering students in fall 2010 | B14: 228
A15: Returned in fall 2011 | B15: 96
A16: Graduated in AY 2011-12 | B16: 0 | C16: # of Certificates | D16: 0 | E16: # of Associate's | F16: 0 | G16: # of Bachelor's | H16: 0 | I16: # of Master's | J16: 0
A17: Transferred to another college or university in AY 2011-12 | B17: 0 | D17: # of graduates who returned to pursue another certificate or degree** | I17: 0
A18: Withdrew or stopped out in AY 2011-12 | B18: 164
A19: Other Exclusions in 2011-12* | B19: 0
A20: Returned in fall 2012 | B20: 64
A22: Please enter the total number of students entering the institution for the first time in fall 2011, including transfers.
A23: First-time entering students in fall 2011 | B23: 218
A24: Graduated in AY 2011-12 | B24: 0 | C24: # of Certificates | D24: 0 | E24: # of Associate's | F24: 0 | G24: # of Bachelor's | H24: 0 | I24: # of Master's | J24: 0
A25: Transferred to another college or university in AY 2011-12 | B25: 0 | D25: # of graduates who returned to pursue another certificate or degree** | I25: 0
A26: Withdrew or stopped out in AY 2011-12 | B26: 121
A27: Other Exclusions in 2011-12* | B27: 0
A28: Returned in fall 2012 | B28: 97
A29: * Exclusions include students who are deceased, permanently disabled, have joined armed forces, and are on official church missions. ** Please note that these graduates should not be counted as returning in fall 2012 students for purposes of retention. Once they've graduated, they are not longer first-time students.
A31: Successful Course Completion
A32: Please enter the total number of students.
B33: Non-Degree Seeking or Undeclared | F33: Certificate or Degree-Seeking | J33: Total
B34: Summer 2011 | C34: Fall 2011 | D34: Winter 2011 | E34: Spring 2012 | F34: Summer 2011 | G34: Fall 2011 | H34: Winter 2011 | I34: Spring 2012 | J34: Non-Degree Total | K34: Certificate/Degree Total | L34: AY 11-12 Total
A35: Total Number of Course Enrollments* | B35: 90 | C35: 475 | D35: n.a. | E35: 500 | F35: 495 | G35: 6297 | H35: n.a. | I35: 6503 | J35: =SUM(B35:G35) -> 7857 | K35: =SUM(F35:I35) -> 13295 | L35: =SUM(J35:K35) -> 21152
A36: Total Number of Successful Course Completions** | B36: 39 | C36: 128 | D36: n.a. | E36: 150 | F36: 447 | G36: 4104 | H36: n.a. | I36: 4069 | J36: =SUM(B36:F36) -> 764 | K36: =SUM(F36:I36) -> 8620 | L36: =SUM(J36:K36) -> 9384
A37: Successful Course Completion Rate | B37: =B36/B35 -> 0.43333333 | C37: =C36/C35 -> 0.26947368 | D37: =D36/D35 -> #VALUE! | E37: =E36/E35 -> 0.3 | F37: =F36/F35 -> 0.9030303 | G37: =G36/G35 -> 0.65173892 | H37: =H36/H35 -> #VALUE! | I37: =I36/I35 -> 0.62571121 | ... L37: =L36/L35 -> 0.44364599
A38: * This will count students multiple times.
A39: ** Successful completion means passing with a grade of A, B, C, CR (credit), or P (pass)
A41: NOTES

Sheet 1.5 Community Education
B1: Institution | C1: ='1.1a Overall Instit. Profile'!$B$1 -> Oglala Lakota College
A2: Indicator 1: Overall Institution Profile
A3: Table 1.5: Community Education Participation / AY 2011-12
A4: Please enter the institution's participation in community education programs
A5: Community Education Participation: (Summer 2011 - Spring 2012)
A6: Target Audience | B6: Program Name | C6: Funding Source | D6: Number of Participants
A7: Elementary (K-8)
A18: Secondary (9-12)
B31: Program Name | C31: Funding Source | D31: Number of Participants | E31: Type of Community Education
A32: Adult | E32: Employment Specific Training | F32: Other Adult Community Education*
B33: Community/Continuing Education Department | C33: BIA/ABE | D33: 665 | E33: 266 | F33: G.E.D.
B34: Nursing Department - Certified Nursing Assistant | C34: no cost to students | D34: 22 | E34: 22 | F34: Nursing Assistant
B35: Credit where Credit is Due | C35: Lakota Fund | D35: 10 | E35: 0 | F35: Banking
B36: Financial Literacy | C36: Lakota Fund | D36: 16 | F36: Budgeting
B37: Tax Preparation | C37: Lakota Fund | D37: 25 | F37: Taxes
B38: Home Buyers Class | C38: Lakota Fund | D38: 10 | F38: Home buyers
B39: Job Corps | C39: Job Corps | D39: 50 | F39: Workplace development
B40: Public Safety | C40: Oglala Sioux Tribe | D40: 15 | E40: 15
B41: Mind/Body Medicine | C41: none | D41: 6 | F41: Physical well being
B42: Strong Heart | C42: Indian Health Service | D42: 30 | F42: Heart health
B43: OST Fire Department | C43: Oglala Sioux Tribe | D43: 15 | E43: 15 | F43: Prevention
B44: Maza Ska | C44: Oglala Sioux Tribe | D44: 20 | F44: Money Management
B45: Tom Boy Tools | C45: none | D45: 15 | F45: development
B46: Obama Care | C46: Soc. Security Admiln. | D46: 20 | F46: Health Care
B47: Northern PlainsTrib C HB | C47: n.a. | D47: 1350 | F47: Cancer Awareness
B48: Diabetic Screening | C48: n.a. | D48: 140 | F48: Screening & Education
B49: Diabetic & Nutritional Program | C49: n.a. | D49: 32 | F49: Nutrition $ Wellness
B50: HIS Wellness Lectures | C50: n.a. | D50: 120 | F50: Flu Shots
B51: HIS Education Program | C51: n.a. | D51: 250 | F51: General Information
B52: Veteran's Vol Program | C52: n.a. | D52: 50 | F52: Veteran's Benefit by VA
D61: =SUM(D7:D60) -> 2861
A62: * Computer skills, financial literacy, parenting skills, etc.
A63: Notes:
A64: Attachment for tab 1.5 for the Math & Science department and the Agriculture Extension Department

Sheet 2.1 Student Tuition & Costs
A1: Institution | C1: ='1.1a Overall Instit. Profile'!B1 -> Oglala Lakota College
A2: Indicator 2: Financial Resources and Student Costs
A3: Table 2.1: Student Tuition, Financial Aid, and Costs / AY 2011-12
A4: Please enter the tuition cost per credit hour, the total amount of financial aid received and the number of students receiving aid, and undergraduate student costs.
A5: Sources and Amount of Financial Aid | D5: AY 11-12
A6: American Indian College Fund Scholarship | C6: Total Dollar Amount | D6: 154132
C7: Total Number of Recipients | D7: 291
A8: American Indian College Fund Full Circle Scholarship | C8: Total Dollar Amount | D8: 131500
C9: Total Number of Recipients | D9: 46
A10: Federal Pell Grants | C10: Total Dollar Amount | D10: 5216170
C11: Total Number of Recipients | D11: 1519
A12: Federal Supplemental Educational Opportunity Grant | C12: Total Dollar Amount | D12: 88400
C13: Total Number of Recipients | D13: 203
A14: Direct Federal Student Loans | C14: Total Dollar Amount | D14: 0
C15: Total Number of Recipients | D15: 0
A16: State Scholarships/Grants | C16: Total Dollar Amount | D16: 65599
C17: Total Number of Recipients | D17: 152
A18: Academic Competitiveness Grant | C18: Total Dollar Amount | D18: 0
C19: Total Number of Recipients | D19: 0
A20: School-to-Work | C20: Total Dollar Amount | D20: 0
C21: Total Number of Recipients | D21: 0
A22: Tribal Scholarships | C22: Total Dollar Amount | D22: 847479
C23: Total Number of Recipients | D23: 407
A24: TCU-based Tuition Waiver/Discount | C24: Total Dollar Amount | D24: 23477
C25: Total Number of Recipients | D25: 39
A26: Other Scholarships | C26: Total Dollar Amount | D26: 759645
C27: Total Number of Recipients | D27: 1358
A28: Federal College Work Study | C28: Total Dollar Amount | D28: 82599
C29: Total Number of Recipients | D29: 64
A30: State Work Study | C30: Total Dollar Amount | D30: 0
C31: Total Number of Recipients | D31: 0
A32: Institutional Work Study | C32: Total Dollar Amount | D32: 0
C33: Total Number of Recipients | D33: 0
A35: Cost per Credit Hour (CURRENT Academic Year):
A36: Undergraduate American Indian, In-State | C36: 80
A37: Undergraduate American Indian, Out-of-State | C37: 80
A38: Undergraduate Non-Indian, In-State | C38: 98
A39: Undergraduate Non-Indian, Out-of-State | C39: 98
A40: Graduate American Indian, In-State | C40: 115
A41: Graduate American Indian, Out-of-State | C41: 115
A42: Graduate Non-Indian, In-State | C42: 115
A43: Graduate Non-Indian, Out-of-State | C43: 115
A44: Average Full Time Undergraduate American Indian Student Costs for One Academic Year | D44: CURRENT Year
A45: Tuition and Fees (Full-Time) | D45: 2396
A46: Room and Board | D46: 5400
A47: Books and Supplies | D47: 1200
A48: Other Expenses | D48: 4850
A49: Total Student Costs | D49: =SUM(D35:D48) -> 13846
A51: Notes:

Sheet 2.2 Non-Fed Operational Funding
A1: Institution | C1: ='1.1a Overall Instit. Profile'!B1 -> Oglala Lakota College
A2: Indicator 2: Financial Resources and Student Costs
A3: Table 2.2: Non-Federal Operational Funding / AY 2011-12
A4: Tribal Funding
A5: Current Academic Year (AY 12-13) Operational Funding from the Tribe (non-scholarship) | D5: 0
A6: Current Academic Year (AY 12-13) Construction Funding from the Tribe | D6: 0
A7: State Funding
A8: Current Fiscal Year (FY 12-13) Operational Funding Received from the State (Perkins money) | D8: 78000
A9: Current Fiscal Year (FY 12-13) Non-Beneficiary Funding Received from the State | D9: 0

Sheet 3.1 Academic Building
A1: Institution | B1: ='1.1a Overall Instit. Profile'!B1 -> Oglala Lakota College
A2: Indicator 3: Physical Resources
A3: Table 3.1: Building Facilities
A4: Please briefly summarize the institution's buildings. Identify building usage by main function. Reproduce this work sheet as needed. If building is used for multiple purposes (e.g. classroom and laboratory) please list building name as many times as necessary and identify total square feet for each main function.
A5: Does your institution have daycare or other early childhood learning facilities? | C5: yes
A6: If so, how many children are served? | B6: Main Campus | C6: Age range | D6: m | F6: What is the cost to attend? | G6: m
A7: Whose children attend (Students, Faculty/Staff, General Community)? | B7: Students, General Community | F7: Who operates the facility? (TCU, Tribe, Independent non-tribal organization) | H7: Oglala Sioux Tribe
A8: Do TCU students work in the facility? | B8: m
A9: If so, in what capacity? Please place an X by response(s).
A10: Interns, teaching aides, or other capacity tied to the students' studies | C10: m | D10: Hired employees | F10: m | G10: Volunteers | H10: m
A11: Existing Buildings
A12: Building Name | B12: Campus Site | C12: Year Built / Acquired | D12: No. of Stories | E12: Total sq. ft. | F12: Main Function | G12: Own / Lease | H12: Note | J12: Campus Site
A13: Piya Wiconi | B13: Main Campus | C13: 1980 | D13: 2 | E13: 24800 | F13: Administration/Office | G13: Own | J13: Main Campus
A14: Pine Ridge House 1 | B14: Satellite Site | C14: 1939 | D14: 1 | E14: 1700 | F14: Auxiliary | G14: Own | J14: Branch Campus
A15: Pine Ridge House 2 | B15: Satellite Site | C15: 1939 | D15: 1 | E15: 1700 | F15: Auxiliary | G15: Own | J15: Satellite Site
A16: Classrooms | B16: Satellite Site | C16: 1970 | D16: 1 | E16: 3080 | F16: Classroom | G16: Own
A17: Martin Building | B17: Satellite Site | C17: 1947 | D17: 1 | E17: 2500 | F17: Auxiliary | G17: Own | J17: Main Function
A18: Voc-Ed Building Metal Building | B18: Main Campus | C18: 1981 | D18: 1 | E18: 8400 | F18: Administration/Office | G18: Own | J18: Administration/Office
A19: Wooden Building | B19: Main Campus | C19: 1988 | D19: 1 | E19: 2100 | F19: Administration/Office | G19: Own | J19: Auxiliary
A20: Kyle Center | B20: Satellite Site | C20: 1994 | D20: 1 | E20: m | F20: Administration/Office | G20: Own | J20: Classroom
A21: Batesland Center | B21: Satellite Site | C21: 1994 | D21: 1 | E21: 5000 | F21: Administration/Office | G21: Own | J21: Cultural Center/Museum
A22: Porcupine Center | B22: Satellite Site | C22: 1997 | D22: 1 | E22: 6582 | F22: Classroom | G22: Own | J22: Distance Learning
A23: Pine Ridge Center | B23: Satellite Site | C23: 1997 | D23: 1 | E23: 12150 | F23: Classroom | G23: Own | J23: Laboratory
A24: Manderson Center | B24: Satellite Site | C24: 1998 | D24: 1 | E24: m | F24: Classroom | G24: Own | J24: Library
A25: Wanblee Center | B25: Satellite Site | C25: 1998 | D25: 1 | E25: m | F25: Classroom | G25: Own | J25: Research
A26: Oglala Center | B26: Satellite Site | C26: 1998 | D26: 1 | E26: m | F26: Classroom | G26: Own | J26: Residence
A27: Allen Center | B27: Satellite Site | C27: 1999 | D27: 1 | E27: m | F27: Classroom | G27: Own | J27: Student Services/Recreation
A28: Martin Center | B28: Satellite Site | C28: 1999 | D28: 1 | E28: m | F28: Classroom | G28: Own
A29: Rapid City Center | B29: Satellite Site | C29: 1999 | D29: 1 | E29: m | F29: Classroom | G29: Own | J29: Own/Lease
A30: Kyle Center Addition | B30: Satellite Site | C30: 2001 | D30: 1 | E30: m | F30: Classroom | G30: Own | J30: Assigned by Tribe
A31: Pine Ridge Log Cabin | B31: Satellite Site | C31: m | D31: 1 | E31: 4526 | F31: Auxiliary | G31: Own | J31: Donated
A32: Nursing Dorm | B32: Satellite Site | C32: 2003 | D32: 1 | E32: m | F32: Residence | G32: Own | J32: Lease/Rent
A33: Lakota Center for Science & Technology | B33: Main Campus | C33: 2003 | D33: 1 | E33: 6000 | F33: Laboratory | G33: Own | J33: Own
A34: Nursing Building | B34: Satellite Site | C34: 2004 | D34: 1 | E34: 8000 | F34: Classroom | G34: Own
A35: Pine Ridge College Center Expansion | B35: Satellite Site | C35: 2004 | D35: 1 | E35: 4500 | F35: Classroom | G35: Own
A36: He Sapa College Center Expansion | B36: Satellite Site | C36: 2006 | D36: 1 | E36: 6500 | F36: Classroom | G36: Own
A37: Cheyenne River College Center | B37: Satellite Site | C37: 2000 | D37: 1 | E37: 25000 | F37: Classroom | G37: Assigned by Tribe
A38: Pine Ridge Dorms | B38: Satellite Site | C38: 2006 | D38: 1 | E38: 4200 | F38: Residence | G38: Own
A39: Pole Barn Building | B39: Main Campus | C39: 2008 | D39: 1 | E39: 2040 | F39: Administration/Office | G39: Own
A40: Bookstore | B40: Main Campus | C40: 2008 | D40: 1 | E40: 3625 | F40: Administration/Office | G40: Own
A41: Batesland Head Start | B41: Satellite Site | C41: 2008 | D41: 1 | E41: 1680 | F41: Classroom | G41: Own
A42: Wanblee Head Start | B42: Satellite Site | C42: 2008 | D42: 1 | E42: 2576 | F42: Classroom | G42: Own
A43: Pejuta Haka Dorms | B43: Satellite Site | C43: 2009 | D43: 1 | E43: 9000 | F43: Residence | G43: Own
A44: Martin Head Start | B44: Satellite Site | C44: 2009 | D44: 1 | E44: 2591 | F44: Classroom | G44: Own
A45: Manderson Head Start | B45: Satellite Site | C45: 2009 | D45: 1 | E45: 3200 | F45: Classroom | G45: Own
A46: Multipurpose Building | B46: Main Campus | C46: 2010 | D46: 1 | E46: 14733 | F46: Student Services/Recreation | G46: Own | H46: Gymnasium
A47: Auto Technology Building | B47: Satellite Site | C47: 2011 | D47: 1 | E47: 8400 | F47: Classroom | G47: Own
A48: Rapid City Center #2 | B48: Satellite Site | C48: 2011 | D48: 2 | E48: 4850 | F48: Classroom | G48: Own
A63: Notes:

Sheet 3.2 Library Fac & Res Equipment
A1: Institution | D1: ='1.1a Overall Instit. Profile'!B1 -> Oglala Lakota College
A2: Indicator 3: Physical Resources | N2: Inter-Library System
A3: Table 3.2: Library Facilities / AY 2011-12 | N3: Computer Lab w/ Internet
A4: Please briefly summarize the current status of library facilities. | N4: <select one>
A5: Library Facility | N5: Yes
A6: Library Name | C6: Total sq. ft. | D6: Year Built / Remodeled | E6: Volumes | F6: Periodicals | H6: Catalogue On-line Access | I6: Inter-Library System | J6: Computer Lab w/ Internet | K6: Community Library Status | L6: Community Learning Center | N6: No
F7: Print | G7: Electronic
A8: Woksape Tipi | C8: 18000 | D8: 1997 | E8: 49000 | F8: 60 | G8: 80* | H8: Yes | I8: Yes | J8: Yes | K8: Community Library | L8: Yes | N8: Community Library Status
N9: <select one>
N10: Community Library
A11: Special Cultural Collections: Please briefly describe any cultural or tribal museum/archival collections housed in library or other building.
A12: Museum, Archival Collections; - Lakota Artifacts (e.g. head dresses, pipes, moccasins), - manuscripts, microfilm, video, audio, photographs, maps, posters, rare books, publications covering broad spectrum of Lakota history, society, culture, and institutions; - institutional records of Oglala Lakota College and Oglala Sioux Tribe; - Artwork by Oglala Lakota artists (contemporary).
A13: Library Improvements / Acquisitions during academic year
A14: AY 11-12 | B14: m
A15: Notes:
A16: * w/3000+ titles

Sheet 3.3 Research Equipment
A1: Institution | B1: ='1.1a Overall Instit. Profile'!B1 -> Oglala Lakota College
A2: Indicator 3: Physical Resources
A3: Table 3.3: Instructional/ Research Equipment and Facilities Acquired /AY 2011-12
A4: Please enter major instructional/ research equipment and facilities acquired during the academic year
A5: Major Instructional/ Research Equipment and Facilities Acquisition
B6: AY 11-12
A7: Equipment or Facility Name | B7: Oglala Lakota College Center for Science and Technology
A8: Purchase Cost | B8: 436697
A9: Number of Units | B9: 22 museum cabinets, 5 hoods, 8 cabinets, 2 sinks, 2 tables, UV disinfector, labor, miscelleaneous
A10: Purpose | B10: Laboratory renovations and Tribal Reposistory
A11: Equipment or Facility Name | B11: Department of Math, Science, and Technology
A12: Purchase Cost | B12: $4,900 + installation
A13: Number of Units | B13: 1
A14: Purpose | B14: Multi-site polycom and smart board for departmental use
A15: Equipment or Facility Name | B15: Piya Wiconi Campus, 3 instructional sites, Rapid City server station
A16: Purchase Cost | B16: 140000
A17: Number of Units | B17: 1 and various and multiple
A18: Purpose | B18: Polycom bridge and upgrades to computing infrastructure
A19: Equipment or Facility Name
A20: Purchase Cost
A21: Number of Units
A22: Purpose
A23: Equipment or Facility Name
A24: Purchase Cost
A25: Number of Units
A26: Purpose
A27: Equipment or Facility Name
A28: Purchase Cost
A29: Number of Units
A30: Purpose
... A87: Notes:
A88: 0

Sheet 4.1 Majors
B1: Institution | C1: ='1.1a Overall Instit. Profile'!$B$1 -> Oglala Lakota College | E1: Major Group ID/Major Groups
A2: Indicator 4: Student Enrollment and Graduation by Major Group | E2: AC - Accounting
A3: Table 4.1: Major Groups | E3: AG - Agriculture and Farming
A4: Please identify your institution's specific majors and degrees offered by major group. If you have additional majors, please add them as needed. | E4: AL - American Indian Languages
A5: Major Groups | E5: AS - American Indian Studies
A6: I.D. | B6: Major Groups | C6: Specific Majors (and Degrees Offered) | E6: AR - Art
A7: AC | B7: Accounting | C7: Accounting (AA) | E7: AU - Automotive Technology
A8: AL | B8: American Indian Languages | C8: Lakota Language (CT) | E8: BI - Biology
A9: AS | B9: American Indian Studies | C9: Lakota Studies (AA, BA); K-12 Lakota Studies Education (BS); Tribal Law (AA); | E9: BT - Building Trades
A10: AR | B10: Art | C10: Fine Art (AA) | E10: BU - Business
A11: AU | B11: Automotive Technology | C11: Automotive Technology (AAS) | E11: CH - Chemistry
A12: BT | B12: Building Trades | C12: Electrical Technology (AAS); General Construction (CT, AAS); Plumbing Technology (CT, AAS), HVAC ((AAS) | E12: CS - Computer Science
A13: BU | B13: Business | C13: Business Administration (BS); Business (AA), Entrepreneurship (AAS) | E13: CT - Computer Technology
A14: CS | B14: Computer Science | C14: Information Technology (AA, BS) | E14: CL - Corrections/Law Enforcement
A15: EA | B15: Education-Paraprofessional | C15: Child Development Associate (CT); Early Childhood (AA); Elementary Education (AA) | E15: EA - Education-Paraprofessional
A16: EO | B16: Education-Professional | C16: Early Childhood (BA); K-8 Elementary Education (BS); K-12:Lakota Studeis (BS), 7-12 Secondary Education Physical Science (BS), | E16: EO - Education-Professional
A17: ES | B17: Environmental Science/Natural Resources | C17: Natural Science (BS), Natural Reources (AA, BS), Science, Eng., Math (SEM) (AA); Life Science, (AA) | E17: EN - English
... A28: UN | B28: Undeclared/Nondeclared | C28: Undeclared (Core) | E28: NU - Nursing
E29: OA - Office Administration/Technology
E30: PA - Paralegal
E31: PE - Pre-Engineering/Engineering
E32: PV - Pre-Veterinary Science
E33: SC - Science
E34: SS - Social Science
A35: Notes: | E35: VC - Vocational/Career Programs
E36: UN - Undeclared/Nondeclared
E37: MS - Master Degree Programs

Sheet 4.2(AC) Major Group Enroll-Grad
A1: Institution | D1: ='1.1a Overall Instit. Profile'!B1 -> Oglala Lakota College
A2: Indicator 4: Student Enrollment and Graduation by Major Group
A3: Table 4.2(AC): Major Group Fall Enrollment, Graduation & Post-Graduate / AY 2011-12
B4: Major Group | C4: AC - Accounting
B5: Please enter the number of students enrolled in this major group for the fall semester.
F6: Fall 2011 (October 15, 2011)
B7: Fall Enrollment (Snapshot) | D7: American Indian | F7: Non-Indian
D8: M | E8: F | F8: M | G8: F | H8: Total
C9: Full Time | D9: 0 | E9: 0 | F9: 0 | G9: 0 | H9: =SUM(D9:G9) -> 0
C10: Part Time | D10: 0 | E10: 1 | F10: 0 | G10: 0 | H10: =SUM(D10:G10) -> 1
C11: Total | D11: =SUM(D9:D10) -> 0 | E11: =SUM(E9:E10) -> 1 | F11: =SUM(F9:F10) -> 0 | G11: =SUM(G9:G10) -> 0 | H11: =SUM(D11:G11) -> 1
B12: Please enter the number of diploma, certificates, and degrees earned in this major group. Also enter the number of students who were admitted to a 4 year (Associate degree graduates), or graduate school (Bachelor's degree graduates). Lastly, enter the number of all graduating students(certificate or degree) who secured gainful employment after graduation.
F13: July 1, 2011- June 30, 2012
B14: Graduation | D14: American Indian | F14: Non-Indian
D15: M | E15: F | F15: M | G15: F | H15: Total
A16: Apprenticeship/Occupational Program | D16: na | E16: na | F16: na | G16: na | H16: =SUM(D16:G16) -> 0
B17: App. graduates admitted to a college program | D17: na | E17: na | F17: na | G17: na | H17: =SUM(D17:G17) -> 0
A18: Diploma | D18: na | E18: na | F18: na | G18: na | H18: =SUM(D18:G18) -> 0
B19: Dip. graduates admitted to a college program | D19: na | E19: na | F19: na | G19: na | H19: =SUM(D19:G19) -> 0
A20: Certificate | D20: na | E20: na | F20: na | G20: na | H20: =SUM(D20:G20) -> 0
B21: Cert. graduates admitted to a college program | D21: na | E21: na | F21: na | G21: na | H21: =SUM(D21:G21) -> 0
A22: Associate Degree | D22: 1 | E22: 3 | F22: 0 | G22: 0 | H22: =SUM(D22:G22) -> 4
B23: Assoc. graduates admitted to four-year program | D23: 0 | E23: 0 | F23: 0 | G23: 0 | H23: =SUM(D23:G23) -> 0
A24: Bachelor's Degree | D24: na | E24: na | F24: na | G24: na | H24: =SUM(D24:G24) -> 0
B25: Bach. graduates admitted to graduate school | D25: na | E25: na | F25: na | G25: na | H25: =SUM(D25:G25) -> 0
A26: Master's Degree | D26: na | E26: na | F26: na | G26: na | H26: =SUM(D26:G26) -> 0
A27: Gainfully Employed after graduation | D27: m | E27: m | F27: m | G27: m | H27: =SUM(D27:G27) -> 0
A28: Graduates who completed remedial courses during their time at the TCU | D28: m | E28: m | F28: m | G28: m | H28: =SUM(D28:G28) -> 0
A29: Graduates who received A*CF support at some point during their coursework | D29: m | E29: m | F29: m | G29: m | H29: =SUM(D29:G29) -> 0
A31: Notes:
A32: Graduates are not tracked after graduation. Graduates who took remedial courses are not tracked. Graduates who received ACF are not tracked.

Sheet 4.2(AG) Major Group Enroll-Grad
A1: Institution | D1: ='1.1a Overall Instit. Profile'!B1 -> Oglala Lakota College
A2: Indicator 4: Student Enrollment and Graduation by Major Group
A3: Table 4.2(AG): Major Group Fall Enrollment, Graduation & Post-Graduate / AY 20010-11
B4: Major Group | C4: AG - Agriculture and Farming
B5: Please enter the number of students enrolled in this major group for the fall semester.
F6: Fall 2011 (October 15, 2011)
B7: Fall Enrollment (Snapshot) | D7: American Indian | F7: Non-Indian
D8: M | E8: F | F8: M | G8: F | H8: Total
C9: Full Time | D9: na | E9: na | F9: na | G9: na | H9: =SUM(D9:G9) -> 0
C10: Part Time | D10: na | E10: na | F10: na | G10: na | H10: =SUM(D10:G10) -> 0
C11: Total | D11: =SUM(D9:D10) -> 0 | E11: =SUM(E9:E10) -> 0 | F11: =SUM(F9:F10) -> 0 | G11: =SUM(G9:G10) -> 0 | H11: =SUM(D11:G11) -> 0
B12: Please enter the number of diploma, certificates, and degrees earned in this major group. Also enter the number of students who were admitted to a 4 year (Associate degree graduates), or graduate school (Bachelor's degree graduates). Lastly, enter the number of all graduating students(certificate or degree) who secured gainful employment after graduation.
F13: July 1, 2011- June 30, 2012
B14: Graduation | D14: American Indian | F14: Non-Indian
D15: M | E15: F | F15: M | G15: F | H15: Total
A16: Apprenticeship/Occupational Program | D16: na | E16: na | F16: na | G16: na | H16: =SUM(D16:G16) -> 0
B17: App. graduates admitted to a college program | D17: na | E17: na | F17: na | G17: na | H17: =SUM(D17:G17) -> 0
A18: Diploma | D18: na | E18: na | F18: na | G18: na | H18: =SUM(D18:G18) -> 0
B19: Dip. graduates admitted to a college program | D19: na | E19: na | F19: na | G19: na | H19: =SUM(D19:G19) -> 0
A20: Certificate | D20: na | E20: na | F20: na | G20: na | H20: =SUM(D20:G20) -> 0
B21: Cert. graduates admitted to a college program | D21: na | E21: na | F21: na | G21: na | H21: =SUM(D21:G21) -> 0
A22: Associate Degree | D22: na | E22: na | F22: na | G22: na | H22: =SUM(D22:G22) -> 0
B23: Assoc. graduates admitted to four-year program | D23: na | E23: na | F23: na | G23: na | H23: =SUM(D23:G23) -> 0
A24: Bachelor's Degree | D24: na | E24: na | F24: na | G24: na | H24: =SUM(D24:G24) -> 0
B25: Bach. graduates admitted to graduate school | D25: na | E25: na | F25: na | G25: na | H25: =SUM(D25:G25) -> 0
A26: Master's Degree | D26: na | E26: na | F26: na | G26: na | H26: =SUM(D26:G26) -> 0
A27: Gainfully Employed after graduation | D27: na | E27: na | F27: na | G27: na | H27: =SUM(D27:G27) -> 0
A28: Graduates who completed remedial courses during their time at the TCU | D28: na | E28: na | F28: na | G28: na | H28: =SUM(D28:G28) -> 0
A29: Graduates who received A*CF support at some point during their coursework | D29: na | E29: na | F29: na | G29: na | H29: =SUM(D29:G29) -> 0
A31: Notes:

Sheet 4.2(AL) Major Group Enroll-Grad
A1: Institution | D1: ='1.1a Overall Instit. Profile'!B1 -> Oglala Lakota College
A2: Indicator 4: Student Enrollment and Graduation by Major Group
A3: Table 4.2(AL): Major Group Fall Enrollment, Graduation & Post-Graduate / AY 2011-12
B4: Major Group | C4: AL - American Indian Languages
B5: Please enter the number of students enrolled in this major group for the fall semester.
F6: Fall 2011 (October 15, 2011)
B7: Fall Enrollment (Snapshot) | D7: American Indian | F7: Non-Indian
D8: M | E8: F | F8: M | G8: F | H8: Total
C9: Full Time | D9: 0 | E9: 0 | F9: 0 | G9: 0 | H9: =SUM(D9:G9) -> 0
C10: Part Time | D10: 1 | E10: 0 | F10: 0 | G10: 0 | H10: =SUM(D10:G10) -> 1
C11: Total | D11: =SUM(D9:D10) -> 1 | E11: =SUM(E9:E10) -> 0 | F11: =SUM(F9:F10) -> 0 | G11: =SUM(G9:G10) -> 0 | H11: =SUM(D11:G11) -> 1
B12: Please enter the number of diploma, certificates, and degrees earned in this major group. Also enter the number of students who were admitted to a 4 year (Associate degree graduates), or graduate school (Bachelor's degree graduates). Lastly, enter the number of all graduating students(certificate or degree) who secured gainful employment after graduation.
F13: July 1, 2011- June 30, 2012
B14: Graduation | D14: American Indian | F14: Non-Indian
D15: M | E15: F | F15: M | G15: F | H15: Total
A16: Apprenticeship/Occupational Program | D16: na | E16: na | F16: na | G16: na | H16: =SUM(D16:G16) -> 0
B17: App. graduates admitted to a college program | D17: na | E17: na | F17: na | G17: na | H17: =SUM(D17:G17) -> 0
A18: Diploma | D18: na | E18: na | F18: na | G18: na | H18: =SUM(D18:G18) -> 0
B19: Dip. graduates admitted to a college program | D19: na | E19: na | F19: na | G19: na | H19: =SUM(D19:G19) -> 0
A20: Certificate | D20: 1 | E20: 0 | F20: 0 | G20: 0 | H20: =SUM(D20:G20) -> 1
B21: Cert. graduates admitted to a college program | D21: 0 | E21: 0 | F21: 0 | G21: 0 | H21: =SUM(D21:G21) -> 0
A22: Associate Degree | D22: na | E22: na | F22: na | G22: na | H22: =SUM(D22:G22) -> 0
B23: Assoc. graduates admitted to four-year program | D23: na | E23: na | F23: na | G23: na | H23: =SUM(D23:G23) -> 0
A24: Bachelor's Degree | D24: na | E24: na | F24: na | G24: na | H24: =SUM(D24:G24) -> 0
B25: Bach. graduates admitted to graduate school | D25: na | E25: na | F25: na | G25: na | H25: =SUM(D25:G25) -> 0
A26: Master's Degree | D26: na | E26: na | F26: na | G26: na | H26: =SUM(D26:G26) -> 0
A27: Gainfully Employed after graduation | D27: m | E27: m | F27: m | G27: m | H27: =SUM(D27:G27) -> 0
A28: Graduates who completed remedial courses during their time at the TCU | D28: m | E28: m | F28: m | G28: m | H28: =SUM(D28:G28) -> 0
A29: Graduates who received A*CF support at some point during their coursework | D29: m | E29: m | F29: m | G29: m | H29: =SUM(D29:G29) -> 0
A31: Notes:
A32: Students are not tracked after graduation. OLC does not offer apprenticeships, associate or bachelor degrees in Lakota language.

Sheet 4.2(AS) Major Group Enroll-Grad
A1: Institution | D1: ='1.1a Overall Instit. Profile'!B1 -> Oglala Lakota College
A2: Indicator 4: Student Enrollment and Graduation by Major Group
A3: Table 4.2(AS): Major Group Fall Enrollment, Graduation & Post-Graduate / AY 2011-12
B4: Major Group | C4: AS - American Indian Studies
B5: Please enter the number of students enrolled in this major group for the fall semester.
F6: Fall 2011 (October 15, 2011)
B7: Fall Enrollment (Snapshot) | D7: American Indian | F7: Non-Indian
D8: M | E8: F | F8: M | G8: F | H8: Total
C9: Full Time | D9: 33 | E9: 40 | F9: 0 | G9: 0 | H9: =SUM(D9:G9) -> 73
C10: Part Time | D10: 15 | E10: 24 | F10: 1 | G10: 1 | H10: =SUM(D10:G10) -> 41
C11: Total | D11: =SUM(D9:D10) -> 48 | E11: =SUM(E9:E10) -> 64 | F11: =SUM(F9:F10) -> 1 | G11: =SUM(G9:G10) -> 1 | H11: =SUM(D11:G11) -> 114
B12: Please enter the number of diploma, certificates, and degrees earned in this major group. Also enter the number of students who were admitted to a 4 year (Associate degree graduates), or graduate school (Bachelor's degree graduates). Lastly, enter the number of all graduating students(certificate or degree) who secured gainful employment after graduation.
F13: July 1, 2011- June 30, 2012
B14: Graduation | D14: American Indian | F14: Non-Indian
D15: M | E15: F | F15: M | G15: F | H15: Total
A16: Apprenticeship/Occupational Program | D16: na | E16: na | F16: na | G16: na | H16: =SUM(D16:G16) -> 0
B17: App. graduates admitted to a college program | D17: na | E17: na | F17: na | G17: na | H17: =SUM(D17:G17) -> 0
A18: Diploma | D18: na | E18: na | F18: na | G18: na | H18: =SUM(D18:G18) -> 0
B19: Dip. graduates admitted to a college program | D19: na | E19: na | F19: na | G19: na | H19: =SUM(D19:G19) -> 0
A20: Certificate | D20: na | E20: na | F20: na | G20: na | H20: =SUM(D20:G20) -> 0
B21: Cert. graduates admitted to a college program | D21: na | E21: na | F21: na | G21: na | H21: =SUM(D21:G21) -> 0
A22: Associate Degree | D22: 7 | E22: 14 | F22: 0 | G22: 1 | H22: =SUM(D22:G22) -> 22
B23: Assoc. graduates admitted to four-year program | D23: 0 | E23: 0 | F23: 0 | G23: 0 | H23: =SUM(D23:G23) -> 0
A24: Bachelor's Degree | D24: 4 | E24: 3 | F24: 0 | G24: 1 | H24: =SUM(D24:G24) -> 8
B25: Bach. graduates admitted to graduate school | D25: 0 | E25: 0 | F25: 0 | G25: 0 | H25: =SUM(D25:G25) -> 0
A26: Master's Degree | D26: na | E26: na | F26: na | G26: na | H26: =SUM(D26:G26) -> 0
A27: Gainfully Employed after graduation | D27: m | E27: m | F27: m | G27: m | H27: =SUM(D27:G27) -> 0
A28: Graduates who completed remedial courses during their time at the TCU | D28: m | E28: m | F28: m | G28: m | H28: =SUM(D28:G28) -> 0
A29: Graduates who received A*CF support at some point during their coursework | D29: m | E29: m | F29: m | G29: m | H29: =SUM(D29:G29) -> 0
A31: Notes:
A32: OLC does not offer apprenticeships, Diplomas, or Certificates or a master's degree in this discipline. OLC does not track graduates, nor who received ACF or took remedial courses.

Sheet 4.2(AR) Major Group Enroll-Grad
A1: Institution | D1: ='1.1a Overall Instit. Profile'!B1 -> Oglala Lakota College
A2: Indicator 4: Student Enrollment and Graduation by Major Group
A3: Table 4.2(AR): Major Group Fall Enrollment, Graduation & Post-Graduate / AY 2011-12
B4: Major Group | C4: AR - Art
B5: Please enter the number of students enrolled in this major group for the fall semester.
F6: Fall 2011 (October 15, 2011)
B7: Fall Enrollment (Snapshot) | D7: American Indian | F7: Non-Indian
D8: M | E8: F | F8: M | G8: F | H8: Total
C9: Full Time | D9: 9 | E9: 12 | F9: 0 | G9: 0 | H9: =SUM(D9:G9) -> 21
C10: Part Time | D10: 4 | E10: 0 | F10: 0 | G10: 0 | H10: =SUM(D10:G10) -> 4
C11: Total | D11: =SUM(D9:D10) -> 13 | E11: =SUM(E9:E10) -> 12 | F11: =SUM(F9:F10) -> 0 | G11: =SUM(G9:G10) -> 0 | H11: =SUM(D11:G11) -> 25
B12: Please enter the number of diploma, certificates, and degrees earned in this major group. Also enter the number of students who were admitted to a 4 year (Associate degree graduates), or graduate school (Bachelor's degree graduates). Lastly, enter the number of all graduating students(certificate or degree) who secured gainful employment after graduation.
F13: July 1, 2011- June 30, 2012
B14: Graduation | D14: American Indian | F14: Non-Indian
D15: M | E15: F | F15: M | G15: F | H15: Total
A16: Apprenticeship/Occupational Program | D16: na | E16: na | F16: na | G16: na | H16: =SUM(D16:G16) -> 0
B17: App. graduates admitted to a college program | D17: na | E17: na | F17: na | G17: na | H17: =SUM(D17:G17) -> 0
A18: Diploma | D18: na | E18: na | F18: na | G18: na | H18: =SUM(D18:G18) -> 0
B19: Dip. graduates admitted to a college program | D19: na | E19: na | F19: na | G19: na | H19: =SUM(D19:G19) -> 0
A20: Certificate | D20: na | E20: na | F20: na | G20: na | H20: =SUM(D20:G20) -> 0
B21: Cert. graduates admitted to a college program | D21: na | E21: na | F21: na | G21: na | H21: =SUM(D21:G21) -> 0
A22: Associate Degree | D22: 0 | E22: 1 | F22: 0 | G22: 0 | H22: =SUM(D22:G22) -> 1
B23: Assoc. graduates admitted to four-year program | D23: 0 | E23: 0 | F23: 0 | G23: 0 | H23: =SUM(D23:G23) -> 0
A24: Bachelor's Degree | D24: na | E24: na | F24: na | G24: na | H24: =SUM(D24:G24) -> 0
B25: Bach. graduates admitted to graduate school | D25: na | E25: na | F25: na | G25: na | H25: =SUM(D25:G25) -> 0
A26: Master's Degree | D26: na | E26: na | F26: na | G26: na | H26: =SUM(D26:G26) -> 0
A27: Gainfully Employed after graduation | D27: m | E27: m | F27: m | G27: m | H27: =SUM(D27:G27) -> 0
A28: Graduates who completed remedial courses during their time at the TCU | D28: m | E28: m | F28: m | G28: m | H28: =SUM(D28:G28) -> 0
A29: Graduates who received A*CF support at some point during their coursework | D29: m | E29: m | F29: m | G29: m | H29: =SUM(D29:G29) -> 0
A31: Notes:
A32: OLC does not offer apprenticeships, diplomas certificates bachelor's degrees or master's degrees in this discipline. OLC does not track graduates, remedial courses or ACF recipients.

Sheet 4.2(AU) Major Group Enroll-Grad
A1: Institution | D1: ='1.1a Overall Instit. Profile'!B1 -> Oglala Lakota College
A2: Indicator 4: Student Enrollment and Graduation by Major Group
A3: Table 4.2(AU): Major Group Fall Enrollment, Graduation & Post-Graduate / AY 20010-11
B4: Major Group | C4: AU - Automotive
B5: Please enter the number of students enrolled in this major group for the fall semester.
F6: Fall 2011 (October 15, 2011)
B7: Fall Enrollment (Snapshot) | D7: American Indian | F7: Non-Indian
D8: M | E8: F | F8: M | G8: F | H8: Total
C9: Full Time | D9: na | E9: na | F9: na | G9: na | H9: =SUM(D9:G9) -> 0
C10: Part Time | D10: na | E10: na | F10: na | G10: na | H10: =SUM(D10:G10) -> 0
C11: Total | D11: =SUM(D9:D10) -> 0 | E11: =SUM(E9:E10) -> 0 | F11: =SUM(F9:F10) -> 0 | G11: =SUM(G9:G10) -> 0 | H11: =SUM(D11:G11) -> 0
B12: Please enter the number of diploma, certificates, and degrees earned in this major group. Also enter the number of students who were admitted to a 4 year (Associate degree graduates), or graduate school (Bachelor's degree graduates). Lastly, enter the number of all graduating students(certificate or degree) who secured gainful employment after graduation.
F13: July 1, 2011- June 30, 2012
B14: Graduation | D14: American Indian | F14: Non-Indian
D15: M | E15: F | F15: M | G15: F | H15: Total
A16: Apprenticeship/Occupational Program | D16: na | E16: na | F16: na | G16: na | H16: =SUM(D16:G16) -> 0
B17: App. graduates admitted to a college program | D17: na | E17: na | F17: na | G17: na | H17: =SUM(D17:G17) -> 0
A18: Diploma | D18: na | E18: na | F18: na | G18: na | H18: =SUM(D18:G18) -> 0
B19: Dip. graduates admitted to a college program | D19: na | E19: na | F19: na | G19: na | H19: =SUM(D19:G19) -> 0
A20: Certificate | D20: na | E20: na | F20: na | G20: na | H20: =SUM(D20:G20) -> 0
B21: Cert. graduates admitted to a college program | D21: na | E21: na | F21: na | G21: na | H21: =SUM(D21:G21) -> 0
A22: Associate Degree | D22: na | E22: na | F22: na | G22: na | H22: =SUM(D22:G22) -> 0
B23: Assoc. graduates admitted to four-year program | D23: na | E23: na | F23: na | G23: na | H23: =SUM(D23:G23) -> 0
A24: Bachelor's Degree | D24: na | E24: na | F24: na | G24: na | H24: =SUM(D24:G24) -> 0
B25: Bach. graduates admitted to graduate school | D25: na | E25: na | F25: na | G25: na | H25: =SUM(D25:G25) -> 0
A26: Master's Degree | D26: na | E26: na | F26: na | G26: na | H26: =SUM(D26:G26) -> 0
A27: Gainfully Employed after graduation | D27: na | E27: na | F27: na | G27: na | H27: =SUM(D27:G27) -> 0
A28: Graduates who completed remedial courses during their time at the TCU | D28: na | E28: na | F28: na | G28: na | H28: =SUM(D28:G28) -> 0
A29: Graduates who received A*CF support at some point during their coursework | D29: na | E29: na | F29: na | G29: na | H29: =SUM(D29:G29) -> 0
A31: Notes:

Sheet 4.2(BI) Major Group Enroll-Grad
A1: Institution | D1: ='1.1a Overall Instit. Profile'!B1 -> Oglala Lakota College
A2: Indicator 4: Student Enrollment and Graduation by Major Group
A3: Table 4.2(BI): Major Group Fall Enrollment, Graduation & Post-Graduate / AY 20010-11
B4: Major Group | C4: BI - Biology
B5: Please enter the number of students enrolled in this major group for the fall semester.
F6: Fall 2011 (October 15, 2011)
B7: Fall Enrollment (Snapshot) | D7: American Indian | F7: Non-Indian
D8: M | E8: F | F8: M | G8: F | H8: Total
C9: Full Time | D9: na | E9: na | F9: na | G9: na | H9: =SUM(D9:G9) -> 0
C10: Part Time | D10: na | E10: na | F10: na | G10: na | H10: =SUM(D10:G10) -> 0
C11: Total | D11: =SUM(D9:D10) -> 0 | E11: =SUM(E9:E10) -> 0 | F11: =SUM(F9:F10) -> 0 | G11: =SUM(G9:G10) -> 0 | H11: =SUM(D11:G11) -> 0
B12: Please enter the number of diploma, certificates, and degrees earned in this major group. Also enter the number of students who were admitted to a 4 year (Associate degree graduates), or graduate school (Bachelor's degree graduates). Lastly, enter the number of all graduating students(certificate or degree) who secured gainful employment after graduation.
F13: July 1, 2011- June 30, 2012
B14: Graduation | D14: American Indian | F14: Non-Indian
D15: M | E15: F | F15: M | G15: F | H15: Total
A16: Apprenticeship/Occupational Program | D16: na | E16: na | F16: na | G16: na | H16: =SUM(D16:G16) -> 0
B17: App. graduates admitted to a college program | D17: na | E17: na | F17: na | G17: na | H17: =SUM(D17:G17) -> 0
A18: Diploma | D18: na | E18: na | F18: na | G18: na | H18: =SUM(D18:G18) -> 0
B19: Dip. graduates admitted to a college program | D19: na | E19: na | F19: na | G19: na | H19: =SUM(D19:G19) -> 0
A20: Certificate | D20: na | E20: na | F20: na | G20: na | H20: =SUM(D20:G20) -> 0
B21: Cert. graduates admitted to a college program | D21: na | E21: na | F21: na | G21: na | H21: =SUM(D21:G21) -> 0
A22: Associate Degree | D22: na | E22: na | F22: na | G22: na | H22: =SUM(D22:G22) -> 0
B23: Assoc. graduates admitted to four-year program | D23: na | E23: na | F23: na | G23: na | H23: =SUM(D23:G23) -> 0
A24: Bachelor's Degree | D24: na | E24: na | F24: na | G24: na | H24: =SUM(D24:G24) -> 0
B25: Bach. graduates admitted to graduate school | D25: na | E25: na | F25: na | G25: na | H25: =SUM(D25:G25) -> 0
A26: Master's Degree | D26: na | E26: na | F26: na | G26: na | H26: =SUM(D26:G26) -> 0
A27: Gainfully Employed after graduation | D27: na | E27: na | F27: na | G27: na | H27: =SUM(D27:G27) -> 0
A28: Graduates who completed remedial courses during their time at the TCU | D28: na | E28: na | F28: na | G28: na | H28: =SUM(D28:G28) -> 0
A29: Graduates who received A*CF support at some point during their coursework | D29: na | E29: na | F29: na | G29: na | H29: =SUM(D29:G29) -> 0
A31: Notes:

Sheet 4.2(BT) Major Group Enroll-Grad
A1: Institution | D1: ='1.1a Overall Instit. Profile'!B1 -> Oglala Lakota College
A2: Indicator 4: Student Enrollment and Graduation by Major Group
A3: Table 4.2(BT): Major Group Fall Enrollment, Graduation & Post-Graduate / AY 2011-12
B4: Major Group | C4: BT - Building Trades
B5: Please enter the number of students enrolled in this major group for the fall semester.
F6: Fall 2011 (October 15, 2011)
B7: Fall Enrollment (Snapshot) | D7: American Indian | F7: Non-Indian
D8: M | E8: F | F8: M | G8: F | H8: Total
C9: Full Time | D9: 25 | E9: 0 | F9: 0 | G9: 0 | H9: =SUM(D9:G9) -> 25
C10: Part Time | D10: 17 | E10: 4 | F10: 0 | H10: =SUM(D10:G10) -> 21
C11: Total | D11: =SUM(D9:D10) -> 42 | E11: =SUM(E9:E10) -> 4 | F11: =SUM(F9:F10) -> 0 | G11: =SUM(G9:G10) -> 0 | H11: =SUM(D11:G11) -> 46
B12: Please enter the number of diploma, certificates, and degrees earned in this major group. Also enter the number of students who were admitted to a 4 year (Associate degree graduates), or graduate school (Bachelor's degree graduates). Lastly, enter the number of all graduating students(certificate or degree) who secured gainful employment after graduation.
F13: July 1, 2011- June 30, 2012
B14: Graduation | D14: American Indian | F14: Non-Indian
D15: M | E15: F | F15: M | G15: F | H15: Total
A16: Apprenticeship/Occupational Program | D16: na | E16: na | F16: na | G16: na | H16: =SUM(D16:G16) -> 0
B17: App. graduates admitted to a college program | D17: na | E17: na | F17: na | G17: na | H17: =SUM(D17:G17) -> 0
A18: Diploma | D18: na | E18: na | F18: na | G18: na | H18: =SUM(D18:G18) -> 0
B19: Dip. graduates admitted to a college program | D19: na | E19: na | F19: na | G19: na | H19: =SUM(D19:G19) -> 0
A20: Certificate | D20: 3 | E20: 0 | F20: 0 | G20: 0 | H20: =SUM(D20:G20) -> 3
B21: Cert. graduates admitted to a college program | D21: 0 | E21: 0 | F21: 0 | G21: 0 | H21: =SUM(D21:G21) -> 0
A22: Associate Degree | D22: 4 | E22: 0 | F22: 0 | G22: 0 | H22: =SUM(D22:G22) -> 4
B23: Assoc. graduates admitted to four-year program | D23: 0 | E23: 0 | F23: 0 | G23: 0 | H23: =SUM(D23:G23) -> 0
A24: Bachelor's Degree | D24: na | E24: na | F24: na | G24: na | H24: =SUM(D24:G24) -> 0
B25: Bach. graduates admitted to graduate school | D25: na | E25: na | F25: na | G25: na | H25: =SUM(D25:G25) -> 0
A26: Master's Degree | D26: na | E26: na | F26: na | G26: na | H26: =SUM(D26:G26) -> 0
A27: Gainfully Employed after graduation | D27: m | E27: m | F27: m | G27: m | H27: =SUM(D27:G27) -> 0
A28: Graduates who completed remedial courses during their time at the TCU | D28: m | E28: m | F28: m | G28: m | H28: =SUM(D28:G28) -> 0
A29: Graduates who received A*CF support at some point during their coursework | D29: m | E29: m | F29: m | G29: m | H29: =SUM(D29:G29) -> 0
A31: Apprenticeships, diplomas, bachelor's or master's degrees are not offered in this discilplien. Graduates are not tracked on the dimensions stated.

Sheet 4.2(BU) Major Group Enroll-Grad
A1: Institution | D1: ='1.1a Overall Instit. Profile'!B1 -> Oglala Lakota College
A2: Indicator 4: Student Enrollment and Graduation by Major Group
A3: Table 4.2(BU): Major Group Fall Enrollment, Graduation & Post-Graduate / AY 2011-12
B4: Major Group | C4: BU - Business
B5: Please enter the number of students enrolled in this major group for the fall semester.
F6: Fall 2011 (October 15, 2011)
B7: Fall Enrollment (Snapshot) | D7: American Indian | F7: Non-Indian
D8: M | E8: F | F8: M | G8: F | H8: Total
C9: Full Time | D9: 101 | E9: 134 | F9: 0 | G9: 2 | H9: =SUM(D9:G9) -> 237
C10: Part Time | D10: 32 | E10: 69 | F10: 1 | G10: 2 | H10: =SUM(D10:G10) -> 104
C11: Total | D11: =SUM(D9:D10) -> 133 | E11: =SUM(E9:E10) -> 203 | F11: =SUM(F9:F10) -> 1 | G11: =SUM(G9:G10) -> 4 | H11: =SUM(D11:G11) -> 341
B12: Please enter the number of diploma, certificates, and degrees earned in this major group. Also enter the number of students who were admitted to a 4 year (Associate degree graduates), or graduate school (Bachelor's degree graduates). Lastly, enter the number of all graduating students(certificate or degree) who secured gainful employment after graduation.
F13: July 1, 2011- June 30, 2012
B14: Graduation | D14: American Indian | F14: Non-Indian
D15: M | E15: F | F15: M | G15: F | H15: Total
A16: Apprenticeship/Occupational Program | D16: na | E16: na | F16: na | G16: na | H16: =SUM(D16:G16) -> 0
B17: App. graduates admitted to a college program | D17: na | E17: na | F17: na | G17: na | H17: =SUM(D17:G17) -> 0
A18: Diploma | D18: na | E18: na | F18: na | G18: na | H18: =SUM(D18:G18) -> 0
B19: Dip. graduates admitted to a college program | D19: na | E19: na | F19: na | G19: na | H19: =SUM(D19:G19) -> 0
A20: Certificate | D20: na | E20: na | F20: na | G20: na | H20: =SUM(D20:G20) -> 0
B21: Cert. graduates admitted to a college program | D21: na | E21: na | F21: na | G21: na | H21: =SUM(D21:G21) -> 0
A22: Associate Degree | D22: 7 | E22: 11 | F22: 0 | G22: 0 | H22: =SUM(D22:G22) -> 18
B23: Assoc. graduates admitted to four-year program | D23: 0 | E23: 0 | F23: 0 | G23: 0 | H23: =SUM(D23:G23) -> 0
A24: Bachelor's Degree | D24: 2 | E24: 3 | F24: 1 | H24: =SUM(D24:G24) -> 6
B25: Bach. graduates admitted to graduate school | D25: 0 | E25: 0 | F25: 0 | G25: 0 | H25: =SUM(D25:G25) -> 0
A26: Master's Degree | D26: na | E26: na | F26: na | G26: na | H26: =SUM(D26:G26) -> 0
A27: Gainfully Employed after graduation | D27: m | E27: m | F27: m | G27: m | H27: =SUM(D27:G27) -> 0
A28: Graduates who completed remedial courses during their time at the TCU | D28: m | E28: m | F28: m | G28: m | H28: =SUM(D28:G28) -> 0
A29: Graduates who received A*CF support at some point during their coursework | D29: m | E29: m | F29: m | G29: m | H29: =SUM(D29:G29) -> 0
A31: Notes:
A32: Graduates are not tracked after graduation. Graduates who took remedial courses are not tracked. Graduates who received ACF are not tracked. We do not offer apprenticeship, diploma, certificates, or master's degrees in this discipline.

Sheet 4.2(CH) Major Group Enroll-Grad
A1: Institution | D1: ='1.1a Overall Instit. Profile'!B1 -> Oglala Lakota College
A2: Indicator 4: Student Enrollment and Graduation by Major Group
A3: Table 4.2(CH): Major Group Fall Enrollment, Graduation & Post-Graduate / AY 20010-11
B4: Major Group | C4: CH - Chemistry
B5: Please enter the number of students enrolled in this major group for the fall semester.
F6: Fall 2011 (October 15, 2011)
B7: Fall Enrollment (Snapshot) | D7: American Indian | F7: Non-Indian
D8: M | E8: F | F8: M | G8: F | H8: Total
C9: Full Time | D9: na | E9: na | F9: na | G9: na | H9: =SUM(D9:G9) -> 0
C10: Part Time | D10: na | E10: na | F10: na | G10: na | H10: =SUM(D10:G10) -> 0
C11: Total | D11: =SUM(D9:D10) -> 0 | E11: =SUM(E9:E10) -> 0 | F11: =SUM(F9:F10) -> 0 | G11: =SUM(G9:G10) -> 0 | H11: =SUM(D11:G11) -> 0
B12: Please enter the number of diploma, certificates, and degrees earned in this major group. Also enter the number of students who were admitted to a 4 year (Associate degree graduates), or graduate school (Bachelor's degree graduates). Lastly, enter the number of all graduating students(certificate or degree) who secured gainful employment after graduation.
F13: July 1, 2011- June 30, 2012
B14: Graduation | D14: American Indian | F14: Non-Indian
D15: M | E15: F | F15: M | G15: F | H15: Total
A16: Apprenticeship/Occupational Program | D16: na | E16: na | F16: na | G16: na | H16: =SUM(D16:G16) -> 0
B17: App. graduates admitted to a college program | D17: na | E17: na | F17: na | G17: na | H17: =SUM(D17:G17) -> 0
A18: Diploma | D18: na | E18: na | F18: na | G18: na | H18: =SUM(D18:G18) -> 0
B19: Dip. graduates admitted to a college program | D19: na | E19: na | F19: na | G19: na | H19: =SUM(D19:G19) -> 0
A20: Certificate | D20: na | E20: na | F20: na | G20: na | H20: =SUM(D20:G20) -> 0
B21: Cert. graduates admitted to a college program | D21: na | E21: na | F21: na | G21: na | H21: =SUM(D21:G21) -> 0
A22: Associate Degree | D22: na | E22: na | F22: na | G22: na | H22: =SUM(D22:G22) -> 0
B23: Assoc. graduates admitted to four-year program | D23: na | E23: na | F23: na | G23: na | H23: =SUM(D23:G23) -> 0
A24: Bachelor's Degree | D24: na | E24: na | F24: na | G24: na | H24: =SUM(D24:G24) -> 0
B25: Bach. graduates admitted to graduate school | D25: na | E25: na | F25: na | G25: na | H25: =SUM(D25:G25) -> 0
A26: Master's Degree | D26: na | E26: na | F26: na | G26: na | H26: =SUM(D26:G26) -> 0
A27: Gainfully Employed after graduation | D27: na | E27: na | F27: na | G27: na | H27: =SUM(D27:G27) -> 0
A28: Graduates who completed remedial courses during their time at the TCU | D28: na | E28: na | F28: na | G28: na | H28: =SUM(D28:G28) -> 0
A29: Graduates who received A*CF support at some point during their coursework | D29: na | E29: na | F29: na | G29: na | H29: =SUM(D29:G29) -> 0
A31: Notes:

Sheet 4.2(CS) Major Group Enroll-Grad
A1: Institution | D1: ='1.1a Overall Instit. Profile'!B1 -> Oglala Lakota College
A2: Indicator 4: Student Enrollment and Graduation by Major Group
A3: Table 4.2(CS): Major Group Fall Enrollment, Graduation & Post-Graduate / AY 2011-12
B4: Major Group | C4: CS - Computer Science
B5: Please enter the number of students enrolled in this major group for the fall semester.
F6: Fall 2011 (October 15, 2011)
B7: Fall Enrollment (Snapshot) | D7: American Indian | F7: Non-Indian
D8: M | E8: F | F8: M | G8: F | H8: Total
C9: Full Time | D9: 21 | E9: 19 | F9: 2 | G9: 0 | H9: =SUM(D9:G9) -> 42
C10: Part Time | D10: 14 | E10: 9 | F10: 0 | G10: 0 | H10: =SUM(D10:G10) -> 23
C11: Total | D11: =SUM(D9:D10) -> 35 | E11: =SUM(E9:E10) -> 28 | F11: =SUM(F9:F10) -> 2 | G11: =SUM(G9:G10) -> 0 | H11: =SUM(D11:G11) -> 65
B12: Please enter the number of diploma, certificates, and degrees earned in this major group. Also enter the number of students who were admitted to a 4 year (Associate degree graduates), or graduate school (Bachelor's degree graduates). Lastly, enter the number of all graduating students(certificate or degree) who secured gainful employment after graduation.
F13: July 1, 2011- June 30, 2012
B14: Graduation | D14: American Indian | F14: Non-Indian
D15: M | E15: F | F15: M | G15: F | H15: Total
A16: Apprenticeship/Occupational Program | D16: na | E16: na | F16: na | G16: na | H16: =SUM(D16:G16) -> 0
B17: App. graduates admitted to a college program | D17: na | E17: na | F17: na | G17: na | H17: =SUM(D17:G17) -> 0
A18: Diploma | D18: na | E18: na | F18: na | G18: na | H18: =SUM(D18:G18) -> 0
B19: Dip. graduates admitted to a college program | D19: na | E19: na | F19: na | G19: na | H19: =SUM(D19:G19) -> 0
A20: Certificate | D20: na | E20: na | F20: na | G20: na | H20: =SUM(D20:G20) -> 0
B21: Cert. graduates admitted to a college program | D21: na | E21: na | F21: na | G21: na | H21: =SUM(D21:G21) -> 0
A22: Associate Degree | D22: 0 | E22: 0 | F22: 0 | G22: 0 | H22: =SUM(D22:G22) -> 0
B23: Assoc. graduates admitted to four-year program | D23: 0 | E23: 0 | F23: 0 | G23: 0 | H23: =SUM(D23:G23) -> 0
A24: Bachelor's Degree | D24: 2 | E24: 0 | F24: 0 | G24: 0 | H24: =SUM(D24:G24) -> 2
B25: Bach. graduates admitted to graduate school | D25: 0 | E25: 0 | F25: 0 | G25: 0 | H25: =SUM(D25:G25) -> 0
A26: Master's Degree | D26: na | E26: na | F26: na | G26: na | H26: =SUM(D26:G26) -> 0
A27: Gainfully Employed after graduation | D27: m | E27: m | F27: m | G27: m | H27: =SUM(D27:G27) -> 0
A28: Graduates who completed remedial courses during their time at the TCU | D28: m | E28: m | F28: m | G28: m | H28: =SUM(D28:G28) -> 0
A29: Graduates who received A*CF support at some point during their coursework | D29: m | E29: m | F29: m | G29: m | H29: =SUM(D29:G29) -> 0
A31: Notes:
A32: N"NA" denotes program is not offered. Graduates are not tracked.

Sheet 4.2(CT) Major Group Enroll-Grad
A1: Institution | D1: ='1.1a Overall Instit. Profile'!B1 -> Oglala Lakota College
A2: Indicator 4: Student Enrollment and Graduation by Major Group
A3: Table 4.2(CT): Major Group Fall Enrollment, Graduation & Post-Graduate / AY 2010-11
B4: Major Group | C4: CT - Computer Technology
B5: Please enter the number of students enrolled in this major group for the fall semester.
F6: Fall 2011 (October 15, 2011)
B7: Fall Enrollment (Snapshot) | D7: American Indian | F7: Non-Indian
D8: M | E8: F | F8: M | G8: F | H8: Total
C9: Full Time | D9: na | E9: na | F9: na | G9: na | H9: =SUM(D9:G9) -> 0
C10: Part Time | D10: na | E10: na | F10: na | G10: na | H10: =SUM(D10:G10) -> 0
C11: Total | D11: =SUM(D9:D10) -> 0 | E11: =SUM(E9:E10) -> 0 | F11: =SUM(F9:F10) -> 0 | G11: =SUM(G9:G10) -> 0 | H11: =SUM(D11:G11) -> 0
B12: Please enter the number of diploma, certificates, and degrees earned in this major group. Also enter the number of students who were admitted to a 4 year (Associate degree graduates), or graduate school (Bachelor's degree graduates). Lastly, enter the number of all graduating students(certificate or degree) who secured gainful employment after graduation.
F13: July 1, 2011- June 30, 2012
B14: Graduation | D14: American Indian | F14: Non-Indian
D15: M | E15: F | F15: M | G15: F | H15: Total
A16: Apprenticeship/Occupational Program | D16: na | E16: na | F16: na | G16: na | H16: =SUM(D16:G16) -> 0
B17: App. graduates admitted to a college program | D17: na | E17: na | F17: na | G17: na | H17: =SUM(D17:G17) -> 0
A18: Diploma | D18: na | E18: na | F18: na | G18: na | H18: =SUM(D18:G18) -> 0
B19: Dip. graduates admitted to a college program | D19: na | E19: na | F19: na | G19: na | H19: =SUM(D19:G19) -> 0
A20: Certificate | D20: na | E20: na | F20: na | G20: na | H20: =SUM(D20:G20) -> 0
B21: Cert. graduates admitted to a college program | D21: na | E21: na | F21: na | G21: na | H21: =SUM(D21:G21) -> 0
A22: Associate Degree | D22: na | E22: na | F22: na | G22: na | H22: =SUM(D22:G22) -> 0
B23: Assoc. graduates admitted to four-year program | D23: na | E23: na | F23: na | G23: na | H23: =SUM(D23:G23) -> 0
A24: Bachelor's Degree | D24: na | E24: na | F24: na | G24: na | H24: =SUM(D24:G24) -> 0
B25: Bach. graduates admitted to graduate school | D25: na | E25: na | F25: na | G25: na | H25: =SUM(D25:G25) -> 0
A26: Master's Degree | D26: na | E26: na | F26: na | G26: na | H26: =SUM(D26:G26) -> 0
A27: Gainfully Employed after graduation | D27: na | E27: na | F27: na | G27: na | H27: =SUM(D27:G27) -> 0
A28: Graduates who completed remedial courses during their time at the TCU | D28: na | E28: na | F28: na | G28: na | H28: =SUM(D28:G28) -> 0
A29: Graduates who received A*CF support at some point during their coursework | D29: na | E29: na | F29: na | G29: na | H29: =SUM(D29:G29) -> 0
A31: Notes:

Sheet 4.2(CL) Major Group Enroll-Grad
A1: Institution | D1: ='1.1a Overall Instit. Profile'!B1 -> Oglala Lakota College
A2: Indicator 4: Student Enrollment and Graduation by Major Group
A3: Table 4.2(CL): Major Group Fall Enrollment, Graduation & Post-Graduate / AY 2010-11
B4: Major Group | C4: CL - Corrections/Law Enforcement
B5: Please enter the number of students enrolled in this major group for the fall semester.
F6: Fall 2011 (October 15, 2011)
B7: Fall Enrollment (Snapshot) | D7: American Indian | F7: Non-Indian
D8: M | E8: F | F8: M | G8: F | H8: Total
C9: Full Time | D9: na | E9: na | F9: na | G9: na | H9: =SUM(D9:G9) -> 0
C10: Part Time | D10: na | E10: na | F10: na | G10: na | H10: =SUM(D10:G10) -> 0
C11: Total | D11: =SUM(D9:D10) -> 0 | E11: =SUM(E9:E10) -> 0 | F11: =SUM(F9:F10) -> 0 | G11: =SUM(G9:G10) -> 0 | H11: =SUM(D11:G11) -> 0
B12: Please enter the number of diploma, certificates, and degrees earned in this major group. Also enter the number of students who were admitted to a 4 year (Associate degree graduates), or graduate school (Bachelor's degree graduates). Lastly, enter the number of all graduating students(certificate or degree) who secured gainful employment after graduation.
F13: July 1, 2011- June 30, 2012
B14: Graduation | D14: American Indian | F14: Non-Indian
D15: M | E15: F | F15: M | G15: F | H15: Total
A16: Apprenticeship/Occupational Program | D16: na | E16: na | F16: na | G16: na | H16: =SUM(D16:G16) -> 0
B17: App. graduates admitted to a college program | D17: na | E17: na | F17: na | G17: na | H17: =SUM(D17:G17) -> 0
A18: Diploma | D18: na | E18: na | F18: na | G18: na | H18: =SUM(D18:G18) -> 0
B19: Dip. graduates admitted to a college program | D19: na | E19: na | F19: na | G19: na | H19: =SUM(D19:G19) -> 0
A20: Certificate | D20: na | E20: na | F20: na | G20: na | H20: =SUM(D20:G20) -> 0
B21: Cert. graduates admitted to a college program | D21: na | E21: na | F21: na | G21: na | H21: =SUM(D21:G21) -> 0
A22: Associate Degree | D22: na | E22: na | F22: na | G22: na | H22: =SUM(D22:G22) -> 0
B23: Assoc. graduates admitted to four-year program | D23: na | E23: na | F23: na | G23: na | H23: =SUM(D23:G23) -> 0
A24: Bachelor's Degree | D24: na | E24: na | F24: na | G24: na | H24: =SUM(D24:G24) -> 0
B25: Bach. graduates admitted to graduate school | D25: na | E25: na | F25: na | G25: na | H25: =SUM(D25:G25) -> 0
A26: Master's Degree | D26: na | E26: na | F26: na | G26: na | H26: =SUM(D26:G26) -> 0
A27: Gainfully Employed after graduation | D27: na | E27: na | F27: na | G27: na | H27: =SUM(D27:G27) -> 0
A28: Graduates who completed remedial courses during their time at the TCU | D28: na | E28: na | F28: na | G28: na | H28: =SUM(D28:G28) -> 0
A29: Graduates who received A*CF support at some point during their coursework | D29: na | E29: na | F29: na | G29: na | H29: =SUM(D29:G29) -> 0
A31: Notes:

Sheet 4.2(EA) Major Group Enroll-Grad
A1: Institution | D1: ='1.1a Overall Instit. Profile'!B1 -> Oglala Lakota College
A2: Indicator 4: Student Enrollment and Graduation by Major Group
A3: Table 4.2(EA): Major Group Fall Enrollment, Graduation & Post-Graduate / AY 2011-12
B4: Major Group | C4: EA - Education - Paraprofessional
B5: Please enter the number of students enrolled in this major group for the fall semester.
F6: Fall 2011 (October 15, 2011)
B7: Fall Enrollment (Snapshot) | D7: American Indian | F7: Non-Indian
D8: M | E8: F | F8: M | G8: F | H8: Total
C9: Full Time | D9: 6 | E9: 20 | F9: 0 | G9: 0 | H9: =SUM(D9:G9) -> 26
C10: Part Time | D10: 10 | E10: 27 | F10: 1 | G10: 1 | H10: =SUM(D10:G10) -> 39
C11: Total | D11: =SUM(D9:D10) -> 16 | E11: =SUM(E9:E10) -> 47 | F11: =SUM(F9:F10) -> 1 | G11: =SUM(G9:G10) -> 1 | H11: =SUM(D11:G11) -> 65
B12: Please enter the number of diploma, certificates, and degrees earned in this major group. Also enter the number of students who were admitted to a 4 year (Associate degree graduates), or graduate school (Bachelor's degree graduates). Lastly, enter the number of all graduating students(certificate or degree) who secured gainful employment after graduation.
F13: July 1, 2011- June 30, 2012
B14: Graduation | D14: American Indian | F14: Non-Indian
D15: M | E15: F | F15: M | G15: F | H15: Total
A16: Apprenticeship/Occupational Program | D16: na | E16: na | F16: na | G16: na | H16: =SUM(D16:G16) -> 0
B17: App. graduates admitted to a college program | D17: na | E17: na | F17: na | G17: na | H17: =SUM(D17:G17) -> 0
A18: Diploma | D18: na | E18: na | F18: na | G18: na | H18: =SUM(D18:G18) -> 0
B19: Dip. graduates admitted to a college program | D19: na | E19: na | F19: na | G19: na | H19: =SUM(D19:G19) -> 0
A20: Certificate | D20: 0 | E20: 0 | F20: 0 | G20: 0 | H20: =SUM(D20:G20) -> 0
B21: Cert. graduates admitted to a college program | D21: 0 | E21: 0 | F21: 0 | G21: 0 | H21: =SUM(D21:G21) -> 0
A22: Associate Degree | D22: 3 | E22: 19 | F22: 0 | G22: 1 | H22: =SUM(D22:G22) -> 23
B23: Assoc. graduates admitted to four-year program | D23: 0 | E23: 0 | F23: 0 | G23: 0 | H23: =SUM(D23:G23) -> 0
A24: Bachelor's Degree | D24: na | E24: na | F24: na | G24: na | H24: =SUM(D24:G24) -> 0
B25: Bach. graduates admitted to graduate school | D25: na | E25: na | F25: na | G25: na | H25: =SUM(D25:G25) -> 0
A26: Master's Degree | D26: na | E26: na | F26: na | G26: na | H26: =SUM(D26:G26) -> 0
A27: Gainfully Employed after graduation | D27: m | E27: m | F27: m | G27: m | H27: =SUM(D27:G27) -> 0
A28: Graduates who completed remedial courses during their time at the TCU | D28: m | E28: m | F28: m | G28: m | H28: =SUM(D28:G28) -> 0
A29: Graduates who received A*CF support at some point during their coursework | D29: m | E29: m | F29: m | G29: m | H29: =SUM(D29:G29) -> 0
A31: Notes:
A32: NA denotes that the program is not offered. We do not track graduates.

Sheet 4.2(EO) Major Group Enroll-Grad
A1: Institution | D1: ='1.1a Overall Instit. Profile'!B1 -> Oglala Lakota College
A2: Indicator 4: Student Enrollment and Graduation by Major Group
A3: 19
B4: Major Group | C4: EO - Education - Professional
B5: Please enter the number of students enrolled in this major group for the fall semester.
F6: Fall 2011 (October 15, 2011)
B7: Fall Enrollment (Snapshot) | D7: American Indian | F7: Non-Indian
D8: M | E8: F | F8: M | G8: F | H8: Total
C9: Full Time | D9: 19 | E9: 75 | F9: 0 | G9: 4 | H9: =SUM(D9:G9) -> 98
C10: Part Time | D10: 10 | E10: 74 | F10: 1 | G10: 5 | H10: =SUM(D10:G10) -> 90
C11: Total | D11: =SUM(D9:D10) -> 29 | E11: =SUM(E9:E10) -> 149 | F11: =SUM(F9:F10) -> 1 | G11: =SUM(G9:G10) -> 9 | H11: =SUM(D11:G11) -> 188
B12: Please enter the number of diploma, certificates, and degrees earned in this major group. Also enter the number of students who were admitted to a 4 year (Associate degree graduates), or graduate school (Bachelor's degree graduates). Lastly, enter the number of all graduating students(certificate or degree) who secured gainful employment after graduation.
F13: July 1, 2011- June 30, 2012
B14: Graduation | D14: American Indian | F14: Non-Indian
D15: M | E15: F | F15: M | G15: F | H15: Total
A16: Apprenticeship/Occupational Program | D16: na | E16: na | F16: na | G16: na | H16: =SUM(D16:G16) -> 0
B17: App. graduates admitted to a college program | D17: na | E17: na | F17: na | G17: na | H17: =SUM(D17:G17) -> 0
A18: Diploma | D18: na | E18: na | F18: na | G18: na | H18: =SUM(D18:G18) -> 0
B19: Dip. graduates admitted to a college program | D19: na | E19: na | F19: na | G19: na | H19: =SUM(D19:G19) -> 0
A20: Certificate | D20: na | E20: na | F20: na | G20: na | H20: =SUM(D20:G20) -> 0
B21: Cert. graduates admitted to a college program | D21: na | E21: na | F21: na | G21: na | H21: =SUM(D21:G21) -> 0
A22: Associate Degree | D22: na | E22: na | F22: na | G22: na | H22: =SUM(D22:G22) -> 0
B23: Assoc. graduates admitted to four-year program | D23: na | E23: na | F23: na | G23: na | H23: =SUM(D23:G23) -> 0
A24: Bachelor's Degree | D24: 3 | E24: 13 | F24: 0 | G24: 0 | H24: =SUM(D24:G24) -> 16
B25: Bach. graduates admitted to graduate school | D25: 0 | E25: 0 | F25: 0 | G25: 0 | H25: =SUM(D25:G25) -> 0
A26: Master's Degree | D26: na | E26: na | F26: na | G26: na | H26: =SUM(D26:G26) -> 0
A27: Gainfully Employed after graduation | D27: m | E27: m | F27: m | G27: m | H27: =SUM(D27:G27) -> 0
A28: Graduates who completed remedial courses during their time at the TCU | D28: m | E28: m | F28: m | G28: m | H28: =SUM(D28:G28) -> 0
A29: Graduates who received A*CF support at some point during their coursework | D29: m | E29: m | F29: m | G29: m | H29: =SUM(D29:G29) -> 0
A31: Notes:
A32: NA denotes, program is not offered. We do not track graduates.

Sheet 4.2(EN) Major Group Enroll-Grad
A1: Institution | D1: ='1.1a Overall Instit. Profile'!B1 -> Oglala Lakota College
A2: Indicator 4: Student Enrollment and Graduation by Major Group
A3: Table 4.2(EN): Major Group Fall Enrollment, Graduation & Post-Graduate / AY 20010-11
B4: Major Group | C4: EN - English
B5: Please enter the number of students enrolled in this major group for the fall semester.
F6: Fall 2011 (October 15, 2011)
B7: Fall Enrollment (Snapshot) | D7: American Indian | F7: Non-Indian
D8: M | E8: F | F8: M | G8: F | H8: Total
C9: Full Time | D9: na | E9: na | F9: na | G9: na | H9: =SUM(D9:G9) -> 0
C10: Part Time | D10: na | E10: na | F10: na | G10: na | H10: =SUM(D10:G10) -> 0
C11: Total | D11: =SUM(D9:D10) -> 0 | E11: =SUM(E9:E10) -> 0 | F11: =SUM(F9:F10) -> 0 | G11: =SUM(G9:G10) -> 0 | H11: =SUM(D11:G11) -> 0
B12: Please enter the number of diploma, certificates, and degrees earned in this major group. Also enter the number of students who were admitted to a 4 year (Associate degree graduates), or graduate school (Bachelor's degree graduates). Lastly, enter the number of all graduating students(certificate or degree) who secured gainful employment after graduation.
F13: July 1, 2011- June 30, 2012
B14: Graduation | D14: American Indian | F14: Non-Indian
D15: M | E15: F | F15: M | G15: F | H15: Total
A16: Apprenticeship/Occupational Program | D16: na | E16: na | F16: na | G16: na | H16: =SUM(D16:G16) -> 0
B17: App. graduates admitted to a college program | D17: na | E17: na | F17: na | G17: na | H17: =SUM(D17:G17) -> 0
A18: Diploma | D18: na | E18: na | F18: na | G18: na | H18: =SUM(D18:G18) -> 0
B19: Dip. graduates admitted to a college program | D19: na | E19: na | F19: na | G19: na | H19: =SUM(D19:G19) -> 0
A20: Certificate | D20: na | E20: na | F20: na | G20: na | H20: =SUM(D20:G20) -> 0
B21: Cert. graduates admitted to a college program | D21: na | E21: na | F21: na | G21: na | H21: =SUM(D21:G21) -> 0
A22: Associate Degree | D22: na | E22: na | F22: na | G22: na | H22: =SUM(D22:G22) -> 0
B23: Assoc. graduates admitted to four-year program | D23: na | E23: na | F23: na | G23: na | H23: =SUM(D23:G23) -> 0
A24: Bachelor's Degree | D24: na | E24: na | F24: na | G24: na | H24: =SUM(D24:G24) -> 0
B25: Bach. graduates admitted to graduate school | D25: na | E25: na | F25: na | G25: na | H25: =SUM(D25:G25) -> 0
A26: Master's Degree | D26: na | E26: na | F26: na | G26: na | H26: =SUM(D26:G26) -> 0
A27: Gainfully Employed after graduation | D27: na | E27: na | F27: na | G27: na | H27: =SUM(D27:G27) -> 0
A28: Graduates who completed remedial courses during their time at the TCU | D28: na | E28: na | F28: na | G28: na | H28: =SUM(D28:G28) -> 0
A29: Graduates who received A*CF support at some point during their coursework | D29: na | E29: na | F29: na | G29: na | H29: =SUM(D29:G29) -> 0
A31: Notes:

Sheet 4.2(ES) Major Group Enroll-Grad
A1: Institution | D1: ='1.1a Overall Instit. Profile'!B1 -> Oglala Lakota College
A2: Indicator 4: Student Enrollment and Graduation by Major Group
A3: Table 4.2(ES): Major Group Fall Enrollment, Graduation & Post-Graduate / AY 2011-12
B4: Major Group | C4: ES - Environmental Science/Natural Resources
B5: Please enter the number of students enrolled in this major group for the fall semester.
F6: Fall 2011 (October 15, 2011)
B7: Fall Enrollment (Snapshot) | D7: American Indian | F7: Non-Indian
D8: M | E8: F | F8: M | G8: F | H8: Total
C9: Full Time | D9: 28 | E9: 21 | F9: 1 | G9: 2 | H9: =SUM(D9:G9) -> 52
C10: Part Time | D10: 11 | E10: 3 | F10: 1 | G10: 1 | H10: =SUM(D10:G10) -> 16
C11: Total | D11: =SUM(D9:D10) -> 39 | E11: =SUM(E9:E10) -> 24 | F11: =SUM(F9:F10) -> 2 | G11: =SUM(G9:G10) -> 3 | H11: =SUM(D11:G11) -> 68
B12: Please enter the number of diploma, certificates, and degrees earned in this major group. Also enter the number of students who were admitted to a 4 year (Associate degree graduates), or graduate school (Bachelor's degree graduates). Lastly, enter the number of all graduating students(certificate or degree) who secured gainful employment after graduation.
F13: July 1, 2011- June 30, 2012
B14: Graduation | D14: American Indian | F14: Non-Indian
D15: M | E15: F | F15: M | G15: F | H15: Total
A16: Apprenticeship/Occupational Program | D16: na | E16: na | F16: na | G16: na | H16: =SUM(D16:G16) -> 0
B17: App. graduates admitted to a college program | D17: na | E17: na | F17: na | G17: na | H17: =SUM(D17:G17) -> 0
A18: Diploma | D18: na | E18: na | F18: na | G18: na | H18: =SUM(D18:G18) -> 0
B19: Dip. graduates admitted to a college program | D19: na | E19: na | F19: na | G19: na | H19: =SUM(D19:G19) -> 0
A20: Certificate | D20: na | E20: na | F20: na | G20: na | H20: =SUM(D20:G20) -> 0
B21: Cert. graduates admitted to a college program | D21: na | E21: na | F21: na | G21: na | H21: =SUM(D21:G21) -> 0
A22: Associate Degree | D22: 1 | E22: 1 | F22: 0 | G22: 0 | H22: =SUM(D22:G22) -> 2
B23: Assoc. graduates admitted to four-year program | D23: 0 | E23: 0 | F23: 0 | G23: 0 | H23: =SUM(D23:G23) -> 0
A24: Bachelor's Degree | D24: 1 | E24: 1 | F24: 1 | G24: 2 | H24: =SUM(D24:G24) -> 5
B25: Bach. graduates admitted to graduate school | D25: 0 | E25: 0 | F25: 0 | G25: 0 | H25: =SUM(D25:G25) -> 0
A26: Master's Degree | D26: na | E26: na | F26: na | G26: na | H26: =SUM(D26:G26) -> 0
A27: Gainfully Employed after graduation | D27: m | E27: m | F27: m | G27: m | H27: =SUM(D27:G27) -> 0
A28: Graduates who completed remedial courses during their time at the TCU | D28: m | E28: m | F28: m | G28: m | H28: =SUM(D28:G28) -> 0
A29: Graduates who received A*CF support at some point during their coursework | D29: m | E29: m | F29: m | G29: m | H29: =SUM(D29:G29) -> 0
A31: Notes:
A32: NA denotes we do not offer the program. Graduates are not tracked.

Sheet 4.2(GE) Major Group Enroll-Grad
A1: Institution | D1: ='1.1a Overall Instit. Profile'!B1 -> Oglala Lakota College
A2: Indicator 4: Student Enrollment and Graduation by Major Group
A3: Table 4.2(GE): Major Group Fall Enrollment, Graduation & Post-Graduate / AY 20010-11
B4: Major Group | C4: GE - Geography
B5: Please enter the number of students enrolled in this major group for the fall semester.
F6: Fall 2011 (October 15, 2011)
B7: Fall Enrollment (Snapshot) | D7: American Indian | F7: Non-Indian
D8: M | E8: F | F8: M | G8: F | H8: Total
C9: Full Time | D9: na | E9: na | F9: na | G9: na | H9: =SUM(D9:G9) -> 0
C10: Part Time | D10: na | E10: na | F10: na | G10: na | H10: =SUM(D10:G10) -> 0
C11: Total | D11: =SUM(D9:D10) -> 0 | E11: =SUM(E9:E10) -> 0 | F11: =SUM(F9:F10) -> 0 | G11: =SUM(G9:G10) -> 0 | H11: =SUM(D11:G11) -> 0
B12: Please enter the number of diploma, certificates, and degrees earned in this major group. Also enter the number of students who were admitted to a 4 year (Associate degree graduates), or graduate school (Bachelor's degree graduates). Lastly, enter the number of all graduating students(certificate or degree) who secured gainful employment after graduation.
F13: July 1, 2011- June 30, 2012
B14: Graduation | D14: American Indian | F14: Non-Indian
D15: M | E15: F | F15: M | G15: F | H15: Total
A16: Apprenticeship/Occupational Program | D16: na | E16: na | F16: na | G16: na | H16: =SUM(D16:G16) -> 0
B17: App. graduates admitted to a college program | D17: na | E17: na | F17: na | G17: na | H17: =SUM(D17:G17) -> 0
A18: Diploma | D18: na | E18: na | F18: na | G18: na | H18: =SUM(D18:G18) -> 0
B19: Dip. graduates admitted to a college program | D19: na | E19: na | F19: na | G19: na | H19: =SUM(D19:G19) -> 0
A20: Certificate | D20: na | E20: na | F20: na | G20: na | H20: =SUM(D20:G20) -> 0
B21: Cert. graduates admitted to a college program | D21: na | E21: na | F21: na | G21: na | H21: =SUM(D21:G21) -> 0
A22: Associate Degree | D22: na | E22: na | F22: na | G22: na | H22: =SUM(D22:G22) -> 0
B23: Assoc. graduates admitted to four-year program | D23: na | E23: na | F23: na | G23: na | H23: =SUM(D23:G23) -> 0
A24: Bachelor's Degree | D24: na | E24: na | F24: na | G24: na | H24: =SUM(D24:G24) -> 0
B25: Bach. graduates admitted to graduate school | D25: na | E25: na | F25: na | G25: na | H25: =SUM(D25:G25) -> 0
A26: Master's Degree | D26: na | E26: na | F26: na | G26: na | H26: =SUM(D26:G26) -> 0
A27: Gainfully Employed after graduation | D27: na | E27: na | F27: na | G27: na | H27: =SUM(D27:G27) -> 0
A28: Graduates who completed remedial courses during their time at the TCU | D28: na | E28: na | F28: na | G28: na | H28: =SUM(D28:G28) -> 0
A29: Graduates who received A*CF support at some point during their coursework | D29: na | E29: na | F29: na | G29: na | H29: =SUM(D29:G29) -> 0
A31: Notes:

Sheet 4.2(HC) Major Group Enroll-Grad
A1: Institution | D1: ='1.1a Overall Instit. Profile'!B1 -> Oglala Lakota College
A2: Indicator 4: Student Enrollment and Graduation by Major Group
A3: Table 4.2(HC): Major Group Fall Enrollment, Graduation & Post-Graduate / AY 2010-11
B4: Major Group | C4: HC - Health Careers
B5: Please enter the number of students enrolled in this major group for the fall semester.
F6: Fall 2011 (October 15, 2011)
B7: Fall Enrollment (Snapshot) | D7: American Indian | F7: Non-Indian
D8: M | E8: F | F8: M | G8: F | H8: Total
C9: Full Time | D9: na | E9: na | F9: na | G9: na | H9: =SUM(D9:G9) -> 0
C10: Part Time | D10: na | E10: na | F10: na | G10: na | H10: =SUM(D10:G10) -> 0
C11: Total | D11: =SUM(D9:D10) -> 0 | E11: =SUM(E9:E10) -> 0 | F11: =SUM(F9:F10) -> 0 | G11: =SUM(G9:G10) -> 0 | H11: =SUM(D11:G11) -> 0
B12: Please enter the number of diploma, certificates, and degrees earned in this major group. Also enter the number of students who were admitted to a 4 year (Associate degree graduates), or graduate school (Bachelor's degree graduates). Lastly, enter the number of all graduating students(certificate or degree) who secured gainful employment after graduation.
F13: July 1, 2011- June 30, 2012
B14: Graduation | D14: American Indian | F14: Non-Indian
D15: M | E15: F | F15: M | G15: F | H15: Total
A16: Apprenticeship/Occupational Program | D16: na | E16: na | F16: na | G16: na | H16: =SUM(D16:G16) -> 0
B17: App. graduates admitted to a college program | D17: na | E17: na | F17: na | G17: na | H17: =SUM(D17:G17) -> 0
A18: Diploma | D18: na | E18: na | F18: na | G18: na | H18: =SUM(D18:G18) -> 0
B19: Dip. graduates admitted to a college program | D19: na | E19: na | F19: na | G19: na | H19: =SUM(D19:G19) -> 0
A20: Certificate | D20: na | E20: na | F20: na | G20: na | H20: =SUM(D20:G20) -> 0
B21: Cert. graduates admitted to a college program | D21: na | E21: na | F21: na | G21: na | H21: =SUM(D21:G21) -> 0
A22: Associate Degree | D22: na | E22: na | F22: na | G22: na | H22: =SUM(D22:G22) -> 0
B23: Assoc. graduates admitted to four-year program | D23: na | E23: na | F23: na | G23: na | H23: =SUM(D23:G23) -> 0
A24: Bachelor's Degree | D24: na | E24: na | F24: na | G24: na | H24: =SUM(D24:G24) -> 0
B25: Bach. graduates admitted to graduate school | D25: na | E25: na | F25: na | G25: na | H25: =SUM(D25:G25) -> 0
A26: Master's Degree | D26: na | E26: na | F26: na | G26: na | H26: =SUM(D26:G26) -> 0
A27: Gainfully Employed after graduation | D27: na | E27: na | F27: na | G27: na | H27: =SUM(D27:G27) -> 0
A28: Graduates who completed remedial courses during their time at the TCU | D28: na | E28: na | F28: na | G28: na | H28: =SUM(D28:G28) -> 0
A29: Graduates who received A*CF support at some point during their coursework | D29: na | E29: na | F29: na | G29: na | H29: =SUM(D29:G29) -> 0
A31: Notes:

Sheet 4.2(HI) Major Group Enroll-Grad
A1: Institution | D1: ='1.1a Overall Instit. Profile'!B1 -> Oglala Lakota College
A2: Indicator 4: Student Enrollment and Graduation by Major Group
A3: Table 4.2(HI): Major Group Fall Enrollment, Graduation & Post-Graduate / AY 2011-12
B4: Major Group | C4: HI - Hospitality Industry
B5: Please enter the number of students enrolled in this major group for the fall semester.
F6: Fall 2011 (October 15, 2011)
B7: Fall Enrollment (Snapshot) | D7: American Indian | F7: Non-Indian
D8: M | E8: F | F8: M | G8: F | H8: Total
C9: Full Time | D9: 1 | E9: 0 | F9: 0 | G9: 0 | H9: =SUM(D9:G9) -> 1
C10: Part Time | D10: 1 | E10: 4 | F10: 0 | G10: 0 | H10: =SUM(D10:G10) -> 5
C11: Total | D11: =SUM(D9:D10) -> 2 | E11: =SUM(E9:E10) -> 4 | F11: =SUM(F9:F10) -> 0 | G11: =SUM(G9:G10) -> 0 | H11: =SUM(D11:G11) -> 6
B12: Please enter the number of diploma, certificates, and degrees earned in this major group. Also enter the number of students who were admitted to a 4 year (Associate degree graduates), or graduate school (Bachelor's degree graduates). Lastly, enter the number of all graduating students(certificate or degree) who secured gainful employment after graduation.
F13: July 1, 2011- June 30, 2012
B14: Graduation | D14: American Indian | F14: Non-Indian
D15: M | E15: F | F15: M | G15: F | H15: Total
A16: Apprenticeship/Occupational Program | D16: na | E16: na | F16: na | G16: na | H16: =SUM(D16:G16) -> 0
B17: App. graduates admitted to a college program | D17: na | E17: na | F17: na | G17: na | H17: =SUM(D17:G17) -> 0
A18: Diploma | D18: na | E18: na | F18: na | G18: na | H18: =SUM(D18:G18) -> 0
B19: Dip. graduates admitted to a college program | D19: na | E19: na | F19: na | G19: na | H19: =SUM(D19:G19) -> 0
A20: Certificate | D20: 0 | E20: 0 | F20: 0 | G20: 0 | H20: =SUM(D20:G20) -> 0
B21: Cert. graduates admitted to a college program | D21: 0 | E21: 0 | F21: 0 | G21: 0 | H21: =SUM(D21:G21) -> 0
A22: Associate Degree | D22: 0 | E22: 1 | F22: 0 | G22: 0 | H22: =SUM(D22:G22) -> 1
B23: Assoc. graduates admitted to four-year program | D23: 0 | E23: 0 | F23: 0 | G23: 0 | H23: =SUM(D23:G23) -> 0
A24: Bachelor's Degree | D24: na | E24: na | F24: na | G24: na | H24: =SUM(D24:G24) -> 0
B25: Bach. graduates admitted to graduate school | D25: na | E25: na | F25: na | G25: na | H25: =SUM(D25:G25) -> 0
A26: Master's Degree | D26: na | E26: na | F26: na | G26: na | H26: =SUM(D26:G26) -> 0
A27: Gainfully Employed after graduation | D27: m | E27: m | F27: m | G27: m | H27: =SUM(D27:G27) -> 0
A28: Graduates who completed remedial courses during their time at the TCU | D28: m | E28: m | F28: m | G28: m | H28: =SUM(D28:G28) -> 0
A29: Graduates who received A*CF support at some point during their coursework | D29: m | E29: m | F29: m | G29: m | H29: =SUM(D29:G29) -> 0
A31: Notes:
A32: NA denotes we do not offer the program. Graduates are not tracked.

Sheet 4.2(HS) Major Group Enroll-Grad
A1: Institution | D1: ='1.1a Overall Instit. Profile'!B1 -> Oglala Lakota College
A2: Indicator 4: Student Enrollment and Graduation by Major Group
A3: Table 4.2(HS): Major Group Fall Enrollment, Graduation & Post-Graduate / AY 2011-12
B4: Major Group | C4: HS - Human Services | E4: Social Work/CDC
B5: Please enter the number of students enrolled in this major group for the fall semester.
F6: Fall 2011 (October 15, 2011)
B7: Fall Enrollment (Snapshot) | D7: American Indian | F7: Non-Indian
D8: M | E8: F | F8: M | G8: F | H8: Total
C9: Full Time | D9: 24 | E9: 71 | F9: 6 | G9: 7 | H9: =SUM(D9:G9) -> 108
C10: Part Time | D10: 13 | E10: 39 | F10: 0 | G10: 3 | H10: =SUM(D10:G10) -> 55
C11: Total | D11: =SUM(D9:D10) -> 37 | E11: =SUM(E9:E10) -> 110 | F11: =SUM(F9:F10) -> 6 | G11: =SUM(G9:G10) -> 10 | H11: =SUM(D11:G11) -> 163
B12: Please enter the number of diploma, certificates, and degrees earned in this major group. Also enter the number of students who were admitted to a 4 year (Associate degree graduates), or graduate school (Bachelor's degree graduates). Lastly, enter the number of all graduating students(certificate or degree) who secured gainful employment after graduation.
F13: July 1, 2011- June 30, 2012
B14: Graduation | D14: American Indian | F14: Non-Indian
D15: M | E15: F | F15: M | G15: F | H15: Total
A16: Apprenticeship/Occupational Program | D16: na | E16: na | F16: na | G16: na | H16: =SUM(D16:G16) -> 0
B17: App. graduates admitted to a college program | D17: na | E17: na | F17: na | G17: na | H17: =SUM(D17:G17) -> 0
A18: Diploma | D18: na | E18: na | F18: na | G18: na | H18: =SUM(D18:G18) -> 0
B19: Dip. graduates admitted to a college program | D19: na | E19: na | F19: na | G19: na | H19: =SUM(D19:G19) -> 0
A20: Certificate | D20: na | E20: na | F20: na | G20: na | H20: =SUM(D20:G20) -> 0
B21: Cert. graduates admitted to a college program | D21: na | E21: na | F21: na | G21: na | H21: =SUM(D21:G21) -> 0
A22: Associate Degree | D22: 1 | E22: 4 | F22: 0 | G22: 1 | H22: =SUM(D22:G22) -> 6
B23: Assoc. graduates admitted to four-year program | D23: 0 | E23: 0 | F23: 0 | G23: 0 | H23: =SUM(D23:G23) -> 0
A24: Bachelor's Degree | D24: 2 | E24: 3 | F24: 1 | G24: 0 | H24: =SUM(D24:G24) -> 6
B25: Bach. graduates admitted to graduate school | D25: 0 | E25: 0 | F25: 0 | G25: 0 | H25: =SUM(D25:G25) -> 0
A26: Master's Degree | D26: na | E26: na | F26: na | G26: na | H26: =SUM(D26:G26) -> 0
A27: Gainfully Employed after graduation | D27: m | E27: m | F27: m | G27: m | H27: =SUM(D27:G27) -> 0
A28: Graduates who completed remedial courses during their time at the TCU | D28: m | E28: m | F28: m | G28: m | H28: =SUM(D28:G28) -> 0
A29: Graduates who received A*CF support at some point during their coursework | D29: m | E29: m | F29: m | G29: m | H29: =SUM(D29:G29) -> 0
A31: Notes:
A32: NA denotes we do not have the program. We do not track graduates.

Sheet 4.2(IP) Major Group Enroll-Grad
A1: Institution | D1: ='1.1a Overall Instit. Profile'!B1 -> Oglala Lakota College
A2: Indicator 4: Student Enrollment and Graduation by Major Group
A3: Table 4.2(IP): Major Group Fall Enrollment, Graduation & Post-Graduate / AY 20010-11
B4: Major Group | C4: IP - Individualized Program
B5: Please enter the number of students enrolled in this major group for the fall semester.
F6: Fall 2011 (October 15, 2011)
B7: Fall Enrollment (Snapshot) | D7: American Indian | F7: Non-Indian
D8: M | E8: F | F8: M | G8: F | H8: Total
C9: Full Time | D9: na | E9: na | F9: na | G9: na | H9: =SUM(D9:G9) -> 0
C10: Part Time | D10: na | E10: na | F10: na | G10: na | H10: =SUM(D10:G10) -> 0
C11: Total | D11: =SUM(D9:D10) -> 0 | E11: =SUM(E9:E10) -> 0 | F11: =SUM(F9:F10) -> 0 | G11: =SUM(G9:G10) -> 0 | H11: =SUM(D11:G11) -> 0
B12: Please enter the number of diploma, certificates, and degrees earned in this major group. Also enter the number of students who were admitted to a 4 year (Associate degree graduates), or graduate school (Bachelor's degree graduates). Lastly, enter the number of all graduating students(certificate or degree) who secured gainful employment after graduation.
F13: July 1, 2011- June 30, 2012
B14: Graduation | D14: American Indian | F14: Non-Indian
D15: M | E15: F | F15: M | G15: F | H15: Total
A16: Apprenticeship/Occupational Program | D16: na | E16: na | F16: na | G16: na | H16: =SUM(D16:G16) -> 0
B17: App. graduates admitted to a college program | D17: na | E17: na | F17: na | G17: na | H17: =SUM(D17:G17) -> 0
A18: Diploma | D18: na | E18: na | F18: na | G18: na | H18: =SUM(D18:G18) -> 0
B19: Dip. graduates admitted to a college program | D19: na | E19: na | F19: na | G19: na | H19: =SUM(D19:G19) -> 0
A20: Certificate | D20: na | E20: na | F20: na | G20: na | H20: =SUM(D20:G20) -> 0
B21: Cert. graduates admitted to a college program | D21: na | E21: na | F21: na | G21: na | H21: =SUM(D21:G21) -> 0
A22: Associate Degree | D22: na | E22: na | F22: na | G22: na | H22: =SUM(D22:G22) -> 0
B23: Assoc. graduates admitted to four-year program | D23: na | E23: na | F23: na | G23: na | H23: =SUM(D23:G23) -> 0
A24: Bachelor's Degree | D24: na | E24: na | F24: na | G24: na | H24: =SUM(D24:G24) -> 0
B25: Bach. graduates admitted to graduate school | D25: na | E25: na | F25: na | G25: na | H25: =SUM(D25:G25) -> 0
A26: Master's Degree | D26: na | E26: na | F26: na | G26: na | H26: =SUM(D26:G26) -> 0
A27: Gainfully Employed after graduation | D27: na | E27: na | F27: na | G27: na | H27: =SUM(D27:G27) -> 0
A28: Graduates who completed remedial courses during their time at the TCU | D28: na | E28: na | F28: na | G28: na | H28: =SUM(D28:G28) -> 0
A29: Graduates who received A*CF support at some point during their coursework | D29: na | E29: na | F29: na | G29: na | H29: =SUM(D29:G29) -> 0
A31: Notes:

Sheet 4.2(LA) Major Group Enroll-Grad
A1: Institution | D1: ='1.1a Overall Instit. Profile'!B1 -> Oglala Lakota College
A2: Indicator 4: Student Enrollment and Graduation by Major Group
A3: Table 4.2(LA): Major Group Fall Enrollment, Graduation & Post-Graduate / AY 2011-12
B4: Major Group | C4: LA Liberal Studies
B5: Please enter the number of students enrolled in this major group for the fall semester.
F6: Fall 2011 (October 15, 2011)
B7: Fall Enrollment (Snapshot) | D7: American Indian | F7: Non-Indian
D8: M | E8: F | F8: M | G8: F | H8: Total
C9: Full Time | D9: 7 | E9: 7 | F9: 0 | G9: 0 | H9: =SUM(D9:G9) -> 14
C10: Part Time | D10: 2 | E10: 5 | F10: 0 | G10: 0 | H10: =SUM(D10:G10) -> 7
C11: Total | D11: =SUM(D9:D10) -> 9 | E11: =SUM(E9:E10) -> 12 | F11: =SUM(F9:F10) -> 0 | G11: =SUM(G9:G10) -> 0 | H11: =SUM(D11:G11) -> 21
B12: Please enter the number of diploma, certificates, and degrees earned in this major group. Also enter the number of students who were admitted to a 4 year (Associate degree graduates), or graduate school (Bachelor's degree graduates). Lastly, enter the number of all graduating students(certificate or degree) who secured gainful employment after graduation.
F13: July 1, 2011- June 30, 2012
B14: Graduation | D14: American Indian | F14: Non-Indian
D15: M | E15: F | F15: M | G15: F | H15: Total
A16: Apprenticeship/Occupational Program | D16: na | E16: na | F16: na | G16: na | H16: =SUM(D16:G16) -> 0
B17: App. graduates admitted to a college program | D17: na | E17: na | F17: na | G17: na | H17: =SUM(D17:G17) -> 0
A18: Diploma | D18: na | E18: na | F18: na | G18: na | H18: =SUM(D18:G18) -> 0
B19: Dip. graduates admitted to a college program | D19: na | E19: na | F19: na | G19: na | H19: =SUM(D19:G19) -> 0
A20: Certificate | D20: na | E20: na | F20: na | G20: na | H20: =SUM(D20:G20) -> 0
B21: Cert. graduates admitted to a college program | D21: na | E21: na | F21: na | G21: na | H21: =SUM(D21:G21) -> 0
A22: Associate Degree | D22: 6 | E22: 18 | F22: 0 | G22: 2 | H22: =SUM(D22:G22) -> 26
B23: Assoc. graduates admitted to four-year program | D23: 0 | E23: 0 | F23: 0 | G23: 0 | H23: =SUM(D23:G23) -> 0
A24: Bachelor's Degree | D24: 0 | E24: 0 | F24: 0 | G24: 0 | H24: =SUM(D24:G24) -> 0
B25: Bach. graduates admitted to graduate school | D25: 0 | E25: 0 | F25: 0 | G25: 0 | H25: =SUM(D25:G25) -> 0
A26: Master's Degree | D26: na | E26: na | F26: na | G26: na | H26: =SUM(D26:G26) -> 0
A27: Gainfully Employed after graduation | D27: m | E27: m | F27: m | G27: m | H27: =SUM(D27:G27) -> 0
A28: Graduates who completed remedial courses during their time at the TCU | D28: m | E28: m | F28: m | G28: m | H28: =SUM(D28:G28) -> 0
A29: Graduates who received A*CF support at some point during their coursework | D29: m | E29: m | F29: m | G29: m | H29: =SUM(D29:G29) -> 0
A31: Notes:
A32: NA denotes we do not offer the program. We do not track graduates.

Sheet 4.2(LS) Major Group Enroll-Grad
A1: Institution | D1: ='1.1a Overall Instit. Profile'!B1 -> Oglala Lakota College
A2: Indicator 4: Student Enrollment and Graduation by Major Group
A3: Table 4.2(LS): Major Group Fall Enrollment, Graduation & Post-Graduate / AY 2011-12
B4: Major Group | C4: LS - Life Sciences
B5: Please enter the number of students enrolled in this major group for the fall semester.
F6: Fall 2011 (October 15, 2011)
B7: Fall Enrollment (Snapshot) | D7: American Indian | F7: Non-Indian
D8: M | E8: F | F8: M | G8: F | H8: Total
C9: Full Time | D9: 1 | E9: 1 | F9: 0 | G9: 1 | H9: =SUM(D9:G9) -> 3
C10: Part Time | D10: 2 | E10: 1 | F10: 0 | G10: 0 | H10: =SUM(D10:G10) -> 3
C11: Total | D11: =SUM(D9:D10) -> 3 | E11: =SUM(E9:E10) -> 2 | F11: =SUM(F9:F10) -> 0 | G11: =SUM(G9:G10) -> 1 | H11: =SUM(D11:G11) -> 6
B12: Please enter the number of diploma, certificates, and degrees earned in this major group. Also enter the number of students who were admitted to a 4 year (Associate degree graduates), or graduate school (Bachelor's degree graduates). Lastly, enter the number of all graduating students(certificate or degree) who secured gainful employment after graduation.
F13: July 1, 2011- June 30, 2012
B14: Graduation | D14: American Indian | F14: Non-Indian
D15: M | E15: F | F15: M | G15: F | H15: Total
A16: Apprenticeship/Occupational Program | D16: na | E16: na | F16: na | G16: na | H16: =SUM(D16:G16) -> 0
B17: App. graduates admitted to a college program | D17: na | E17: na | F17: na | G17: na | H17: =SUM(D17:G17) -> 0
A18: Diploma | D18: na | E18: na | F18: na | G18: na | H18: =SUM(D18:G18) -> 0
B19: Dip. graduates admitted to a college program | D19: na | E19: na | F19: na | G19: na | H19: =SUM(D19:G19) -> 0
A20: Certificate | D20: na | E20: na | F20: na | G20: na | H20: =SUM(D20:G20) -> 0
B21: Cert. graduates admitted to a college program | D21: na | E21: na | F21: na | G21: na | H21: =SUM(D21:G21) -> 0
A22: Associate Degree | D22: 0 | E22: 0 | F22: 0 | G22: 0 | H22: =SUM(D22:G22) -> 0
B23: Assoc. graduates admitted to four-year program | D23: 0 | E23: 0 | F23: 0 | G23: 0 | H23: =SUM(D23:G23) -> 0
A24: Bachelor's Degree | D24: na | E24: na | F24: na | G24: na | H24: =SUM(D24:G24) -> 0
B25: Bach. graduates admitted to graduate school | D25: na | E25: na | F25: na | G25: na | H25: =SUM(D25:G25) -> 0
A26: Master's Degree | D26: na | E26: na | F26: na | G26: na | H26: =SUM(D26:G26) -> 0
A27: Gainfully Employed after graduation | D27: m | E27: m | F27: m | G27: m | H27: =SUM(D27:G27) -> 0
A28: Graduates who completed remedial courses during their time at the TCU | D28: m | E28: m | F28: m | G28: m | H28: =SUM(D28:G28) -> 0
A29: Graduates who received A*CF support at some point during their coursework | D29: m | E29: m | F29: m | G29: m | H29: =SUM(D29:G29) -> 0
A31: Notes:
A32: NA denotes we do not offer the program. We do not track graduates.

Sheet 4.2(MA) Major Group Enroll-Grad
A1: Institution | D1: ='1.1a Overall Instit. Profile'!B1 -> Oglala Lakota College
A2: Indicator 4: Student Enrollment and Graduation by Major Group
A3: Table 4.2(MA): Major Group Fall Enrollment, Graduation & Post-Graduate / AY 20010-11
B4: Major Group | C4: MA - Mathematics
B5: Please enter the number of students enrolled in this major group for the fall semester.
F6: Fall 2011 (October 15, 2011)
B7: Fall Enrollment (Snapshot) | D7: American Indian | F7: Non-Indian
D8: M | E8: F | F8: M | G8: F | H8: Total
C9: Full Time | D9: na | E9: na | F9: na | G9: na | H9: =SUM(D9:G9) -> 0
C10: Part Time | D10: na | E10: na | F10: na | G10: na | H10: =SUM(D10:G10) -> 0
C11: Total | D11: =SUM(D9:D10) -> 0 | E11: =SUM(E9:E10) -> 0 | F11: =SUM(F9:F10) -> 0 | G11: =SUM(G9:G10) -> 0 | H11: =SUM(D11:G11) -> 0
B12: Please enter the number of diploma, certificates, and degrees earned in this major group. Also enter the number of students who were admitted to a 4 year (Associate degree graduates), or graduate school (Bachelor's degree graduates). Lastly, enter the number of all graduating students(certificate or degree) who secured gainful employment after graduation.
F13: July 1, 2011- June 30, 2012
B14: Graduation | D14: American Indian | F14: Non-Indian
D15: M | E15: F | F15: M | G15: F | H15: Total
A16: Apprenticeship/Occupational Program | D16: na | E16: na | F16: na | G16: na | H16: =SUM(D16:G16) -> 0
B17: App. graduates admitted to a college program | D17: na | E17: na | F17: na | G17: na | H17: =SUM(D17:G17) -> 0
A18: Diploma | D18: na | E18: na | F18: na | G18: na | H18: =SUM(D18:G18) -> 0
B19: Dip. graduates admitted to a college program | D19: na | E19: na | F19: na | G19: na | H19: =SUM(D19:G19) -> 0
A20: Certificate | D20: na | E20: na | F20: na | G20: na | H20: =SUM(D20:G20) -> 0
B21: Cert. graduates admitted to a college program | D21: na | E21: na | F21: na | G21: na | H21: =SUM(D21:G21) -> 0
A22: Associate Degree | D22: na | E22: na | F22: na | G22: na | H22: =SUM(D22:G22) -> 0
B23: Assoc. graduates admitted to four-year program | D23: na | E23: na | F23: na | G23: na | H23: =SUM(D23:G23) -> 0
A24: Bachelor's Degree | D24: na | E24: na | F24: na | G24: na | H24: =SUM(D24:G24) -> 0
B25: Bach. graduates admitted to graduate school | D25: na | E25: na | F25: na | G25: na | H25: =SUM(D25:G25) -> 0
A26: Master's Degree | D26: na | E26: na | F26: na | G26: na | H26: =SUM(D26:G26) -> 0
A27: Gainfully Employed after graduation | D27: na | E27: na | F27: na | G27: na | H27: =SUM(D27:G27) -> 0
A28: Graduates who completed remedial courses during their time at the TCU | D28: na | E28: na | F28: na | G28: na | H28: =SUM(D28:G28) -> 0
A29: Graduates who received A*CF support at some point during their coursework | D29: na | E29: na | F29: na | G29: na | H29: =SUM(D29:G29) -> 0
A31: Notes:

Sheet 4.2(NS) Major Group Enroll-Grad
A1: Institution | D1: ='1.1a Overall Instit. Profile'!B1 -> Oglala Lakota College
A2: Indicator 4: Student Enrollment and Graduation by Major Group
A3: Table 4.2(NS): Major Group Fall Enrollment, Graduation & Post-Graduate / AY 20010-11
B4: Major Group | C4: NS - Natural Science
B5: Please enter the number of students enrolled in this major group for the fall semester.
F6: Fall 2011 (October 15, 2011)
B7: Fall Enrollment (Snapshot) | D7: American Indian | F7: Non-Indian
D8: M | E8: F | F8: M | G8: F | H8: Total
C9: Full Time | D9: na | E9: na | F9: na | G9: na | H9: =SUM(D9:G9) -> 0
C10: Part Time | D10: na | E10: na | F10: na | G10: na | H10: =SUM(D10:G10) -> 0
C11: Total | D11: =SUM(D9:D10) -> 0 | E11: =SUM(E9:E10) -> 0 | F11: =SUM(F9:F10) -> 0 | G11: =SUM(G9:G10) -> 0 | H11: =SUM(D11:G11) -> 0
B12: Please enter the number of diploma, certificates, and degrees earned in this major group. Also enter the number of students who were admitted to a 4 year (Associate degree graduates), or graduate school (Bachelor's degree graduates). Lastly, enter the number of all graduating students(certificate or degree) who secured gainful employment after graduation.
F13: July 1, 2011- June 30, 2012
B14: Graduation | D14: American Indian | F14: Non-Indian
D15: M | E15: F | F15: M | G15: F | H15: Total
A16: Apprenticeship/Occupational Program | D16: na | E16: na | F16: na | G16: na | H16: =SUM(D16:G16) -> 0
B17: App. graduates admitted to a college program | D17: na | E17: na | F17: na | G17: na | H17: =SUM(D17:G17) -> 0
A18: Diploma | D18: na | E18: na | F18: na | G18: na | H18: =SUM(D18:G18) -> 0
B19: Dip. graduates admitted to a college program | D19: na | E19: na | F19: na | G19: na | H19: =SUM(D19:G19) -> 0
A20: Certificate | D20: na | E20: na | F20: na | G20: na | H20: =SUM(D20:G20) -> 0
B21: Cert. graduates admitted to a college program | D21: na | E21: na | F21: na | G21: na | H21: =SUM(D21:G21) -> 0
A22: Associate Degree | D22: na | E22: na | F22: na | G22: na | H22: =SUM(D22:G22) -> 0
B23: Assoc. graduates admitted to four-year program | D23: na | E23: na | F23: na | G23: na | H23: =SUM(D23:G23) -> 0
A24: Bachelor's Degree | D24: na | E24: na | F24: na | G24: na | H24: =SUM(D24:G24) -> 0
B25: Bach. graduates admitted to graduate school | D25: na | E25: na | F25: na | G25: na | H25: =SUM(D25:G25) -> 0
A26: Master's Degree | D26: na | E26: na | F26: na | G26: na | H26: =SUM(D26:G26) -> 0
A27: Gainfully Employed after graduation | D27: na | E27: na | F27: na | G27: na | H27: =SUM(D27:G27) -> 0
A28: Graduates who completed remedial courses during their time at the TCU | D28: na | E28: na | F28: na | G28: na | H28: =SUM(D28:G28) -> 0
A29: Graduates who received A*CF support at some point during their coursework | D29: na | E29: na | F29: na | G29: na | H29: =SUM(D29:G29) -> 0
A31: Notes:

Sheet 4.2(NU) Major Group Enroll-Grad
A1: Institution | D1: ='1.1a Overall Instit. Profile'!B1 -> Oglala Lakota College
A2: Indicator 4: Student Enrollment and Graduation by Major Group
A3: Table 4.2(NU): Major Group Fall Enrollment, Graduation & Post-Graduate / AY 2011-12
B4: Major Group | C4: NU - Nursing
B5: Please enter the number of students enrolled in this major group for the fall semester.
F6: Fall 2011 (October 15, 2011)
B7: Fall Enrollment (Snapshot) | D7: American Indian | F7: Non-Indian
D8: M | E8: F | F8: M | G8: F | H8: Total
C9: Full Time | D9: 9 | E9: 139 | F9: 2 | G9: 5 | H9: =SUM(D9:G9) -> 155
C10: Part Time | D10: 2 | E10: 62 | F10: 2 | G10: 2 | H10: =SUM(D10:G10) -> 68
C11: Total | D11: =SUM(D9:D10) -> 11 | E11: =SUM(E9:E10) -> 201 | F11: =SUM(F9:F10) -> 4 | G11: =SUM(G9:G10) -> 7 | H11: =SUM(D11:G11) -> 223
B12: Please enter the number of diploma, certificates, and degrees earned in this major group. Also enter the number of students who were admitted to a 4 year (Associate degree graduates), or graduate school (Bachelor's degree graduates). Lastly, enter the number of all graduating students(certificate or degree) who secured gainful employment after graduation.
F13: July 1, 2011- June 30, 2012
B14: Graduation | D14: American Indian | F14: Non-Indian
D15: M | E15: F | F15: M | G15: F | H15: Total
A16: Apprenticeship/Occupational Program | D16: na | E16: na | F16: na | G16: na | H16: =SUM(D16:G16) -> 0
B17: App. graduates admitted to a college program | D17: na | E17: na | F17: na | G17: na | H17: =SUM(D17:G17) -> 0
A18: Diploma | D18: na | E18: na | F18: na | G18: na | H18: =SUM(D18:G18) -> 0
B19: Dip. graduates admitted to a college program | D19: na | E19: na | F19: na | G19: na | H19: =SUM(D19:G19) -> 0
A20: Certificate | D20: na | E20: na | F20: na | G20: na | H20: =SUM(D20:G20) -> 0
B21: Cert. graduates admitted to a college program | D21: na | E21: na | F21: na | G21: na | H21: =SUM(D21:G21) -> 0
A22: Associate Degree | D22: 0 | E22: 9 | F22: 0 | G22: 2 | H22: =SUM(D22:G22) -> 11
B23: Assoc. graduates admitted to four-year program | D23: 0 | E23: 0 | F23: 0 | G23: 0 | H23: =SUM(D23:G23) -> 0
A24: Bachelor's Degree | D24: na | E24: na | F24: na | G24: na | H24: =SUM(D24:G24) -> 0
B25: Bach. graduates admitted to graduate school | D25: na | E25: na | F25: na | G25: na | H25: =SUM(D25:G25) -> 0
A26: Master's Degree | D26: na | E26: na | F26: na | G26: na | H26: =SUM(D26:G26) -> 0
A27: Gainfully Employed after graduation | D27: m | E27: m | F27: m | G27: m | H27: =SUM(D27:G27) -> 0
A28: Graduates who completed remedial courses during their time at the TCU | D28: m | E28: m | F28: m | G28: m | H28: =SUM(D28:G28) -> 0
A29: Graduates who received A*CF support at some point during their coursework | D29: m | E29: m | F29: m | G29: m | H29: =SUM(D29:G29) -> 0
A31: Notes:
A32: NA denotes we do not offer the program. We do not track graduates.

Sheet 4.2(OA) Major Group Enroll-Grad
A1: Institution | D1: ='1.1a Overall Instit. Profile'!B1 -> Oglala Lakota College
A2: Indicator 4: Student Enrollment and Graduation by Major Group
A3: Table 4.2(OA): Major Group Fall Enrollment, Graduation & Post-Graduate / AY 2011-12
B4: Major Group | C4: OA - Office Administration
B5: Please enter the number of students enrolled in this major group for the fall semester.
F6: Fall 2011 (October 15, 2011)
B7: Fall Enrollment (Snapshot) | D7: American Indian | F7: Non-Indian
D8: M | E8: F | F8: M | G8: F | H8: Total
C9: Full Time | D9: 2 | E9: 21 | F9: 0 | G9: 0 | H9: =SUM(D9:G9) -> 23
C10: Part Time | D10: 5 | E10: 16 | F10: 0 | G10: 0 | H10: =SUM(D10:G10) -> 21
C11: Total | D11: =SUM(D9:D10) -> 7 | E11: =SUM(E9:E10) -> 37 | F11: =SUM(F9:F10) -> 0 | G11: =SUM(G9:G10) -> 0 | H11: =SUM(D11:G11) -> 44
B12: Please enter the number of diploma, certificates, and degrees earned in this major group. Also enter the number of students who were admitted to a 4 year (Associate degree graduates), or graduate school (Bachelor's degree graduates). Lastly, enter the number of all graduating students(certificate or degree) who secured gainful employment after graduation.
F13: July 1, 2011- June 30, 2012
B14: Graduation | D14: American Indian | F14: Non-Indian
D15: M | E15: F | F15: M | G15: F | H15: Total
A16: Apprenticeship/Occupational Program | D16: na | E16: na | F16: na | G16: na | H16: =SUM(D16:G16) -> 0
B17: App. graduates admitted to a college program | D17: na | E17: na | F17: na | G17: na | H17: =SUM(D17:G17) -> 0
A18: Diploma | D18: na | E18: na | F18: na | G18: na | H18: =SUM(D18:G18) -> 0
B19: Dip. graduates admitted to a college program | D19: na | E19: na | F19: na | G19: na | H19: =SUM(D19:G19) -> 0
A20: Certificate | D20: 1 | E20: 3 | F20: 0 | G20: 0 | H20: =SUM(D20:G20) -> 4
B21: Cert. graduates admitted to a college program | D21: 0 | E21: 0 | F21: 0 | G21: 0 | H21: =SUM(D21:G21) -> 0
A22: Associate Degree | D22: 0 | E22: 1 | F22: 0 | G22: 0 | H22: =SUM(D22:G22) -> 1
B23: Assoc. graduates admitted to four-year program | D23: 0 | E23: 0 | F23: 0 | G23: 0 | H23: =SUM(D23:G23) -> 0
A24: Bachelor's Degree | D24: na | E24: 0 | F24: na | G24: na | H24: =SUM(D24:G24) -> 0
B25: Bach. graduates admitted to graduate school | D25: na | E25: na | F25: na | G25: na | H25: =SUM(D25:G25) -> 0
A26: Master's Degree | D26: na | E26: na | F26: na | G26: na | H26: =SUM(D26:G26) -> 0
A27: Gainfully Employed after graduation | D27: m | E27: m | F27: m | G27: m | H27: =SUM(D27:G27) -> 0
A28: Graduates who completed remedial courses during their time at the TCU | D28: m | E28: m | F28: m | G28: m | H28: =SUM(D28:G28) -> 0
A29: Graduates who received A*CF support at some point during their coursework | D29: m | E29: m | F29: m | G29: m | H29: =SUM(D29:G29) -> 0
A31: Notes:
A32: NA denotes we do not offer the program. We do not track graduates.

Sheet 4.2(PA) Major Group Enroll-Grad
A1: Institution | D1: ='1.1a Overall Instit. Profile'!B1 -> Oglala Lakota College
A2: Indicator 4: Student Enrollment and Graduation by Major Group
A3: Table 4.2(PA): Major Group Fall Enrollment, Graduation & Post-Graduate / AY 20010-11
B4: Major Group | C4: PA - Paralegal
B5: Please enter the number of students enrolled in this major group for the fall semester.
F6: Fall 2011 (October 15, 2011)
B7: Fall Enrollment (Snapshot) | D7: American Indian | F7: Non-Indian
D8: M | E8: F | F8: M | G8: F | H8: Total
C9: Full Time | D9: na | E9: na | F9: na | G9: na | H9: =SUM(D9:G9) -> 0
C10: Part Time | D10: na | E10: na | F10: na | G10: na | H10: =SUM(D10:G10) -> 0
C11: Total | D11: =SUM(D9:D10) -> 0 | E11: =SUM(E9:E10) -> 0 | F11: =SUM(F9:F10) -> 0 | G11: =SUM(G9:G10) -> 0 | H11: =SUM(D11:G11) -> 0
B12: Please enter the number of diploma, certificates, and degrees earned in this major group. Also enter the number of students who were admitted to a 4 year (Associate degree graduates), or graduate school (Bachelor's degree graduates). Lastly, enter the number of all graduating students(certificate or degree) who secured gainful employment after graduation.
F13: July 1, 2011- June 30, 2012
B14: Graduation | D14: American Indian | F14: Non-Indian
D15: M | E15: F | F15: M | G15: F | H15: Total
A16: Apprenticeship/Occupational Program | D16: na | E16: na | F16: na | G16: na | H16: =SUM(D16:G16) -> 0
B17: App. graduates admitted to a college program | D17: na | E17: na | F17: na | G17: na | H17: =SUM(D17:G17) -> 0
A18: Diploma | D18: na | E18: na | F18: na | G18: na | H18: =SUM(D18:G18) -> 0
B19: Dip. graduates admitted to a college program | D19: na | E19: na | F19: na | G19: na | H19: =SUM(D19:G19) -> 0
A20: Certificate | D20: na | E20: na | F20: na | G20: na | H20: =SUM(D20:G20) -> 0
B21: Cert. graduates admitted to a college program | D21: na | E21: na | F21: na | G21: na | H21: =SUM(D21:G21) -> 0
A22: Associate Degree | D22: na | E22: na | F22: na | G22: na | H22: =SUM(D22:G22) -> 0
B23: Assoc. graduates admitted to four-year program | D23: na | E23: na | F23: na | G23: na | H23: =SUM(D23:G23) -> 0
A24: Bachelor's Degree | D24: na | E24: na | F24: na | G24: na | H24: =SUM(D24:G24) -> 0
B25: Bach. graduates admitted to graduate school | D25: na | E25: na | F25: na | G25: na | H25: =SUM(D25:G25) -> 0
A26: Master's Degree | D26: na | E26: na | F26: na | G26: na | H26: =SUM(D26:G26) -> 0
A27: Gainfully Employed after graduation | D27: na | E27: na | F27: na | G27: na | H27: =SUM(D27:G27) -> 0
A28: Graduates who completed remedial courses during their time at the TCU | D28: na | E28: na | F28: na | G28: na | H28: =SUM(D28:G28) -> 0
A29: Graduates who received A*CF support at some point during their coursework | D29: na | E29: na | F29: na | G29: na | H29: =SUM(D29:G29) -> 0
A31: Notes:

Sheet 4.2(PE) Major Group Enroll-Grad
A1: Institution | D1: ='1.1a Overall Instit. Profile'!B1 -> Oglala Lakota College
A2: Indicator 4: Student Enrollment and Graduation by Major Group
A3: Table 4.2(PE): Major Group Fall Enrollment, Graduation & Post-Graduate / AY 20010-11
B4: Major Group | C4: PE - Pre-Engineering/Engineering
B5: Please enter the number of students enrolled in this major group for the fall semester.
F6: Fall 2011 (October 15, 2011)
B7: Fall Enrollment (Snapshot) | D7: American Indian | F7: Non-Indian
D8: M | E8: F | F8: M | G8: F | H8: Total
C9: Full Time | D9: na | E9: na | F9: na | G9: na | H9: =SUM(D9:G9) -> 0
C10: Part Time | D10: na | E10: na | F10: na | G10: na | H10: =SUM(D10:G10) -> 0
C11: Total | D11: =SUM(D9:D10) -> 0 | E11: =SUM(E9:E10) -> 0 | F11: =SUM(F9:F10) -> 0 | G11: =SUM(G9:G10) -> 0 | H11: =SUM(D11:G11) -> 0
B12: Please enter the number of diploma, certificates, and degrees earned in this major group. Also enter the number of students who were admitted to a 4 year (Associate degree graduates), or graduate school (Bachelor's degree graduates). Lastly, enter the number of all graduating students(certificate or degree) who secured gainful employment after graduation.
F13: July 1, 2011- June 30, 2012
B14: Graduation | D14: American Indian | F14: Non-Indian
D15: M | E15: F | F15: M | G15: F | H15: Total
A16: Apprenticeship/Occupational Program | D16: na | E16: na | F16: na | G16: na | H16: =SUM(D16:G16) -> 0
B17: App. graduates admitted to a college program | D17: na | E17: na | F17: na | G17: na | H17: =SUM(D17:G17) -> 0
A18: Diploma | D18: na | E18: na | F18: na | G18: na | H18: =SUM(D18:G18) -> 0
B19: Dip. graduates admitted to a college program | D19: na | E19: na | F19: na | G19: na | H19: =SUM(D19:G19) -> 0
A20: Certificate | D20: na | E20: na | F20: na | G20: na | H20: =SUM(D20:G20) -> 0
B21: Cert. graduates admitted to a college program | D21: na | E21: na | F21: na | G21: na | H21: =SUM(D21:G21) -> 0
A22: Associate Degree | D22: na | E22: na | F22: na | G22: na | H22: =SUM(D22:G22) -> 0
B23: Assoc. graduates admitted to four-year program | D23: na | E23: na | F23: na | G23: na | H23: =SUM(D23:G23) -> 0
A24: Bachelor's Degree | D24: na | E24: na | F24: na | G24: na | H24: =SUM(D24:G24) -> 0
B25: Bach. graduates admitted to graduate school | D25: na | E25: na | F25: na | G25: na | H25: =SUM(D25:G25) -> 0
A26: Master's Degree | D26: na | E26: na | F26: na | G26: na | H26: =SUM(D26:G26) -> 0
A27: Gainfully Employed after graduation | D27: na | E27: na | F27: na | G27: na | H27: =SUM(D27:G27) -> 0
A28: Graduates who completed remedial courses during their time at the TCU | D28: na | E28: na | F28: na | G28: na | H28: =SUM(D28:G28) -> 0
A29: Graduates who received A*CF support at some point during their coursework | D29: na | E29: na | F29: na | G29: na | H29: =SUM(D29:G29) -> 0
A31: Notes:

Sheet 4.2(PV) Major Group Enroll-Grad
A1: Institution | D1: ='1.1a Overall Instit. Profile'!B1 -> Oglala Lakota College
A2: Indicator 4: Student Enrollment and Graduation by Major Group
A3: Table 4.2(PV): Major Group Fall Enrollment, Graduation & Post-Graduate / AY 20010-11
B4: Major Group | C4: PV - Pre-Veterinary
B5: Please enter the number of students enrolled in this major group for the fall semester.
F6: Fall 2011 (October 15, 2011)
B7: Fall Enrollment (Snapshot) | D7: American Indian | F7: Non-Indian
D8: M | E8: F | F8: M | G8: F | H8: Total
C9: Full Time | D9: na | E9: na | F9: na | G9: na | H9: =SUM(D9:G9) -> 0
C10: Part Time | D10: na | E10: na | F10: na | G10: na | H10: =SUM(D10:G10) -> 0
C11: Total | D11: =SUM(D9:D10) -> 0 | E11: =SUM(E9:E10) -> 0 | F11: =SUM(F9:F10) -> 0 | G11: =SUM(G9:G10) -> 0 | H11: =SUM(D11:G11) -> 0
B12: Please enter the number of diploma, certificates, and degrees earned in this major group. Also enter the number of students who were admitted to a 4 year (Associate degree graduates), or graduate school (Bachelor's degree graduates). Lastly, enter the number of all graduating students(certificate or degree) who secured gainful employment after graduation.
F13: July 1, 2011- June 30, 2012
B14: Graduation | D14: American Indian | F14: Non-Indian
D15: M | E15: F | F15: M | G15: F | H15: Total
A16: Apprenticeship/Occupational Program | D16: na | E16: na | F16: na | G16: na | H16: =SUM(D16:G16) -> 0
B17: App. graduates admitted to a college program | D17: na | E17: na | F17: na | G17: na | H17: =SUM(D17:G17) -> 0
A18: Diploma | D18: na | E18: na | F18: na | G18: na | H18: =SUM(D18:G18) -> 0
B19: Dip. graduates admitted to a college program | D19: na | E19: na | F19: na | G19: na | H19: =SUM(D19:G19) -> 0
A20: Certificate | D20: na | E20: na | F20: na | G20: na | H20: =SUM(D20:G20) -> 0
B21: Cert. graduates admitted to a college program | D21: na | E21: na | F21: na | G21: na | H21: =SUM(D21:G21) -> 0
A22: Associate Degree | D22: na | E22: na | F22: na | G22: na | H22: =SUM(D22:G22) -> 0
B23: Assoc. graduates admitted to four-year program | D23: na | E23: na | F23: na | G23: na | H23: =SUM(D23:G23) -> 0
A24: Bachelor's Degree | D24: na | E24: na | F24: na | G24: na | H24: =SUM(D24:G24) -> 0
B25: Bach. graduates admitted to graduate school | D25: na | E25: na | F25: na | G25: na | H25: =SUM(D25:G25) -> 0
A26: Master's Degree | D26: na | E26: na | F26: na | G26: na | H26: =SUM(D26:G26) -> 0
A27: Gainfully Employed after graduation | D27: na | E27: na | F27: na | G27: na | H27: =SUM(D27:G27) -> 0
A28: Graduates who completed remedial courses during their time at the TCU | D28: na | E28: na | F28: na | G28: na | H28: =SUM(D28:G28) -> 0
A29: Graduates who received A*CF support at some point during their coursework | D29: na | E29: na | F29: na | G29: na | H29: =SUM(D29:G29) -> 0
A31: Notes:

Sheet 4.2(SC) Major Group Enroll-Grad
A1: Institution | D1: ='1.1a Overall Instit. Profile'!B1 -> Oglala Lakota College
A2: Indicator 4: Student Enrollment and Graduation by Major Group
A3: Table 4.2(SC): Major Group Fall Enrollment, Graduation & Post-Graduate / AY 2011-12
B4: Major Group | C4: SC - Science
B5: Please enter the number of students enrolled in this major group for the fall semester.
F6: Fall 2011 (October 15, 2011)
B7: Fall Enrollment (Snapshot) | D7: American Indian | F7: Non-Indian
D8: M | E8: F | F8: M | G8: F | H8: Total
C9: Full Time | D9: 0 | E9: 0 | F9: 0 | G9: 0 | H9: =SUM(D9:G9) -> 0
C10: Part Time | D10: 0 | E10: 0 | F10: 0 | G10: 0 | H10: =SUM(D10:G10) -> 0
C11: Total | D11: =SUM(D9:D10) -> 0 | E11: =SUM(E9:E10) -> 0 | F11: =SUM(F9:F10) -> 0 | G11: =SUM(G9:G10) -> 0 | H11: =SUM(D11:G11) -> 0
B12: Please enter the number of diploma, certificates, and degrees earned in this major group. Also enter the number of students who were admitted to a 4 year (Associate degree graduates), or graduate school (Bachelor's degree graduates). Lastly, enter the number of all graduating students(certificate or degree) who secured gainful employment after graduation.
F13: July 1, 2011- June 30, 2012
B14: Graduation | D14: American Indian | F14: Non-Indian
D15: M | E15: F | F15: M | G15: F | H15: Total
A16: Apprenticeship/Occupational Program | D16: na | E16: na | F16: na | G16: na | H16: =SUM(D16:G16) -> 0
B17: App. graduates admitted to a college program | D17: na | E17: na | F17: na | G17: na | H17: =SUM(D17:G17) -> 0
A18: Diploma | D18: na | E18: na | F18: na | G18: na | H18: =SUM(D18:G18) -> 0
B19: Dip. graduates admitted to a college program | D19: na | E19: na | F19: na | G19: na | H19: =SUM(D19:G19) -> 0
A20: Certificate | D20: na | E20: na | F20: na | G20: na | H20: =SUM(D20:G20) -> 0
B21: Cert. graduates admitted to a college program | D21: na | E21: na | F21: na | G21: na | H21: =SUM(D21:G21) -> 0
A22: Associate Degree | D22: 0 | E22: 0 | F22: 0 | G22: 0 | H22: =SUM(D22:G22) -> 0
B23: Assoc. graduates admitted to four-year program | D23: 0 | E23: 0 | F23: 0 | G23: 0 | H23: =SUM(D23:G23) -> 0
A24: Bachelor's Degree | D24: 0 | E24: 0 | F24: 0 | G24: 0 | H24: =SUM(D24:G24) -> 0
B25: Bach. graduates admitted to graduate school | D25: 0 | E25: 0 | F25: 0 | G25: 0 | H25: =SUM(D25:G25) -> 0
A26: Master's Degree | D26: na | E26: na | F26: na | G26: na | H26: =SUM(D26:G26) -> 0
A27: Gainfully Employed after graduation | D27: m | E27: m | F27: m | G27: m | H27: =SUM(D27:G27) -> 0
A28: Graduates who completed remedial courses during their time at the TCU | D28: m | E28: m | F28: m | G28: m | H28: =SUM(D28:G28) -> 0
A29: Graduates who received A*CF support at some point during their coursework | D29: m | E29: m | F29: m | G29: m | H29: =SUM(D29:G29) -> 0
A31: Notes:
A32: We do not have any majors in this program and do not track graduates in the areas noted.

Sheet 4.2(SS) Major Group Enroll-Grad
A1: Institution | D1: ='1.1a Overall Instit. Profile'!B1 -> Oglala Lakota College
A2: Indicator 4: Student Enrollment and Graduation by Major Group
A3: Table 4.2(SS): Major Group Fall Enrollment, Graduation & Post-Graduate / AY 2011-12
B4: Major Group | C4: SS - Social Science
B5: Please enter the number of students enrolled in this major group for the fall semester.
F6: Fall 2011 (October 15, 2011)
B7: Fall Enrollment (Snapshot) | D7: American Indian | F7: Non-Indian
D8: M | E8: F | F8: M | G8: F | H8: Total
C9: Full Time | D9: 30 | E9: 41 | F9: 1 | G9: 2 | H9: =SUM(D9:G9) -> 74
C10: Part Time | D10: 11 | E10: 23 | F10: 1 | G10: 3 | H10: =SUM(D10:G10) -> 38
C11: Total | D11: =SUM(D9:D10) -> 41 | E11: =SUM(E9:E10) -> 64 | F11: =SUM(F9:F10) -> 2 | G11: =SUM(G9:G10) -> 5 | H11: =SUM(D11:G11) -> 112
B12: Please enter the number of diploma, certificates, and degrees earned in this major group. Also enter the number of students who were admitted to a 4 year (Associate degree graduates), or graduate school (Bachelor's degree graduates). Lastly, enter the number of all graduating students(certificate or degree) who secured gainful employment after graduation.
F13: July 1, 2011- June 30, 2012
B14: Graduation | D14: American Indian | F14: Non-Indian
D15: M | E15: F | F15: M | G15: F | H15: Total
A16: Apprenticeship/Occupational Program | D16: na | E16: na | F16: na | G16: na | H16: =SUM(D16:G16) -> 0
B17: App. graduates admitted to a college program | D17: na | E17: na | F17: na | G17: na | H17: =SUM(D17:G17) -> 0
A18: Diploma | D18: na | E18: na | F18: na | G18: na | H18: =SUM(D18:G18) -> 0
B19: Dip. graduates admitted to a college program | D19: na | E19: na | F19: na | G19: na | H19: =SUM(D19:G19) -> 0
A20: Certificate | D20: na | E20: na | F20: na | G20: na | H20: =SUM(D20:G20) -> 0
B21: Cert. graduates admitted to a college program | D21: na | E21: na | F21: na | G21: na | H21: =SUM(D21:G21) -> 0
A22: Associate Degree | D22: 0 | E22: 1 | F22: 0 | G22: 0 | H22: =SUM(D22:G22) -> 1
B23: Assoc. graduates admitted to four-year program | D23: 0 | E23: 0 | F23: 0 | G23: 0 | H23: =SUM(D23:G23) -> 0
A24: Bachelor's Degree | D24: 0 | E24: 6 | F24: 1 | G24: 0 | H24: =SUM(D24:G24) -> 7
B25: Bach. graduates admitted to graduate school | D25: 0 | E25: 0 | F25: 0 | G25: 0 | H25: =SUM(D25:G25) -> 0
A26: Master's Degree | D26: na | E26: na | F26: na | G26: na | H26: =SUM(D26:G26) -> 0
A27: Gainfully Employed after graduation | D27: m | E27: m | F27: m | G27: m | H27: =SUM(D27:G27) -> 0
A28: Graduates who completed remedial courses during their time at the TCU | D28: m | E28: m | F28: m | G28: m | H28: =SUM(D28:G28) -> 0
A29: Graduates who received A*CF support at some point during their coursework | D29: m | E29: m | F29: m | G29: m | H29: =SUM(D29:G29) -> 0
A31: Notes:
A32: NA denotes that we do not offer the program. We do not track graduates.

Sheet 4.2(VC) Major Group Enroll-Grad
A1: Institution | D1: ='1.1a Overall Instit. Profile'!B1 -> Oglala Lakota College
A2: Indicator 4: Student Enrollment and Graduation by Major Group
A3: Table 4.2(VC): Major Group Fall Enrollment, Graduation & Post-Graduate / AY 2011-12
B4: Major Group | C4: VC - Vocational
B5: Please enter the number of students enrolled in this major group for the fall semester.
F6: Fall 2011 (October 15, 2011)
B7: Fall Enrollment (Snapshot) | D7: American Indian | F7: Non-Indian
D8: M | E8: F | F8: M | G8: F | H8: Total
C9: Full Time | D9: 12 | E9: 2 | F9: 0 | G9: 0 | H9: =SUM(D9:G9) -> 14
C10: Part Time | D10: 4 | E10: 2 | F10: 0 | G10: 0 | H10: =SUM(D10:G10) -> 6
C11: Total | D11: =SUM(D9:D10) -> 16 | E11: =SUM(E9:E10) -> 4 | F11: =SUM(F9:F10) -> 0 | G11: =SUM(G9:G10) -> 0 | H11: =SUM(D11:G11) -> 20
B12: Please enter the number of diploma, certificates, and degrees earned in this major group. Also enter the number of students who were admitted to a 4 year (Associate degree graduates), or graduate school (Bachelor's degree graduates). Lastly, enter the number of all graduating students(certificate or degree) who secured gainful employment after graduation.
F13: July 1, 2011- June 30, 2012
B14: Graduation | D14: American Indian | F14: Non-Indian
D15: M | E15: F | F15: M | G15: F | H15: Total
A16: Apprenticeship/Occupational Program | D16: na | E16: na | F16: na | G16: na | H16: =SUM(D16:G16) -> 0
B17: App. graduates admitted to a college program | D17: na | E17: na | F17: na | G17: na | H17: =SUM(D17:G17) -> 0
A18: Diploma | D18: na | E18: na | F18: na | G18: na | H18: =SUM(D18:G18) -> 0
B19: Dip. graduates admitted to a college program | D19: na | E19: na | F19: na | G19: na | H19: =SUM(D19:G19) -> 0
A20: Certificate | D20: 0 | E20: 0 | F20: 0 | G20: 0 | H20: =SUM(D20:G20) -> 0
B21: Cert. graduates admitted to a college program | D21: 0 | E21: 0 | F21: 0 | G21: 0 | H21: =SUM(D21:G21) -> 0
A22: Associate Degree | D22: 0 | E22: 0 | F22: 0 | G22: 0 | H22: =SUM(D22:G22) -> 0
B23: Assoc. graduates admitted to four-year program | D23: 0 | E23: 0 | F23: 0 | G23: 0 | H23: =SUM(D23:G23) -> 0
A24: Bachelor's Degree | D24: na | E24: na | F24: na | G24: na | H24: =SUM(D24:G24) -> 0
B25: Bach. graduates admitted to graduate school | D25: na | E25: na | F25: na | G25: na | H25: =SUM(D25:G25) -> 0
A26: Master's Degree | D26: na | E26: na | F26: na | G26: na | H26: =SUM(D26:G26) -> 0
A27: Gainfully Employed after graduation | D27: m | E27: m | F27: m | G27: m | H27: =SUM(D27:G27) -> 0
A28: Graduates who completed remedial courses during their time at the TCU | D28: m | E28: m | F28: m | G28: m | H28: =SUM(D28:G28) -> 0
A29: Graduates who received A*CF support at some point during their coursework | D29: m | E29: m | F29: m | G29: m | H29: =SUM(D29:G29) -> 0
A31: Notes:
A32: NA denotes we do not have the program. We do not track graduates.

Sheet 4.2(UK) Major Group Enroll-Grad
A1: Institution | D1: ='1.1a Overall Instit. Profile'!B1 -> Oglala Lakota College
A2: Indicator 4: Student Enrollment and Graduation by Major Group
A3: Table 4.2(UK): Major Group Fall Enrollment, Graduation & Post-Graduate / AY 20010-11
B4: Major Group | C4: UK - Unknown
B5: Please enter the number of students enrolled in this major group for the fall semester.
F6: Fall 2011 (October 15, 2011)
B7: Fall Enrollment (Snapshot) | D7: American Indian | F7: Non-Indian
D8: M | E8: F | F8: M | G8: F | H8: Total
C9: Full Time | D9: na | E9: na | F9: na | G9: na | H9: =SUM(D9:G9) -> 0
C10: Part Time | D10: na | E10: na | F10: na | G10: na | H10: =SUM(D10:G10) -> 0
C11: Total | D11: =SUM(D9:D10) -> 0 | E11: =SUM(E9:E10) -> 0 | F11: =SUM(F9:F10) -> 0 | G11: =SUM(G9:G10) -> 0 | H11: =SUM(D11:G11) -> 0
B12: Please enter the number of diploma, certificates, and degrees earned in this major group. Also enter the number of students who were admitted to a 4 year (Associate degree graduates), or graduate school (Bachelor's degree graduates). Lastly, enter the number of all graduating students(certificate or degree) who secured gainful employment after graduation.
F13: July 1, 2011- June 30, 2012
B14: Graduation | D14: American Indian | F14: Non-Indian
D15: M | E15: F | F15: M | G15: F | H15: Total
A16: Apprenticeship/Occupational Program | D16: na | E16: na | F16: na | G16: na | H16: =SUM(D16:G16) -> 0
B17: App. graduates admitted to a college program | D17: na | E17: na | F17: na | G17: na | H17: =SUM(D17:G17) -> 0
A18: Diploma | D18: na | E18: na | F18: na | G18: na | H18: =SUM(D18:G18) -> 0
B19: Dip. graduates admitted to a college program | D19: na | E19: na | F19: na | G19: na | H19: =SUM(D19:G19) -> 0
A20: Certificate | D20: na | E20: na | F20: na | G20: na | H20: =SUM(D20:G20) -> 0
B21: Cert. graduates admitted to a college program | D21: na | E21: na | F21: na | G21: na | H21: =SUM(D21:G21) -> 0
A22: Associate Degree | D22: na | E22: na | F22: na | G22: na | H22: =SUM(D22:G22) -> 0
B23: Assoc. graduates admitted to four-year program | D23: na | E23: na | F23: na | G23: na | H23: =SUM(D23:G23) -> 0
A24: Bachelor's Degree | D24: na | E24: na | F24: na | G24: na | H24: =SUM(D24:G24) -> 0
B25: Bach. graduates admitted to graduate school | D25: na | E25: na | F25: na | G25: na | H25: =SUM(D25:G25) -> 0
A26: Master's Degree | D26: na | E26: na | F26: na | G26: na | H26: =SUM(D26:G26) -> 0
A27: Gainfully Employed after graduation | D27: na | E27: na | F27: na | G27: na | H27: =SUM(D27:G27) -> 0
A28: Graduates who completed remedial courses during their time at the TCU | D28: na | E28: na | F28: na | G28: na | H28: =SUM(D28:G28) -> 0
A29: Graduates who received A*CF support at some point during their coursework | D29: na | E29: na | F29: na | G29: na | H29: =SUM(D29:G29) -> 0
A31: Notes:

Sheet 4.2(UN) Major Group Enroll-Grad
A1: Institution | D1: ='1.1a Overall Instit. Profile'!B1 -> Oglala Lakota College
A2: Indicator 4: Student Enrollment and Graduation by Major Group
A3: Table 4.2(UN): Major Group Fall Enrollment, Graduation & Post-Graduate / AY 2011-12
B4: Major Group | C4: UN - Undeclared/Nondeclared
B5: Please enter the number of students enrolled in this major group for the fall semester.
F6: Fall 2011 (October 15, 2011)
B7: Fall Enrollment (Snapshot) | D7: American Indian | F7: Non-Indian
D8: M | E8: F | F8: M | G8: F | H8: Total
C9: Full Time | D9: 11 | E9: 17 | F9: 10 | G9: 1 | H9: =SUM(D9:G9) -> 39
C10: Part Time | D10: 25 | E10: 38 | F10: 0 | G10: 22 | H10: =SUM(D10:G10) -> 85
C11: Total | D11: =SUM(D9:D10) -> 36 | E11: =SUM(E9:E10) -> 55 | F11: =SUM(F9:F10) -> 10 | G11: =SUM(G9:G10) -> 23 | H11: =SUM(D11:G11) -> 124
B12: Please enter the number of diploma, certificates, and degrees earned in this major group. Also enter the number of students who were admitted to a 4 year (Associate degree graduates), or graduate school (Bachelor's degree graduates). Lastly, enter the number of all graduating students(certificate or degree) who secured gainful employment after graduation.
F13: July 1, 2011- June 30, 2012
B14: Graduation | D14: American Indian | F14: Non-Indian
D15: M | E15: F | F15: M | G15: F | H15: Total
A16: Apprenticeship/Occupational Program | D16: na | E16: na | F16: na | G16: na | H16: =SUM(D16:G16) -> 0
B17: App. graduates admitted to a college program | D17: na | E17: na | F17: na | G17: na | H17: =SUM(D17:G17) -> 0
A18: Diploma | D18: na | E18: na | F18: na | G18: na | H18: =SUM(D18:G18) -> 0
B19: Dip. graduates admitted to a college program | D19: na | E19: na | F19: na | G19: na | H19: =SUM(D19:G19) -> 0
A20: Certificate | D20: na | E20: na | F20: na | G20: na | H20: =SUM(D20:G20) -> 0
B21: Cert. graduates admitted to a college program | D21: na | E21: na | F21: na | G21: na | H21: =SUM(D21:G21) -> 0
A22: Associate Degree | D22: na | E22: na | F22: na | G22: na | H22: =SUM(D22:G22) -> 0
B23: Assoc. graduates admitted to four-year program | D23: na | E23: na | F23: na | G23: na | H23: =SUM(D23:G23) -> 0
A24: Bachelor's Degree | D24: na | E24: na | F24: na | G24: na | H24: =SUM(D24:G24) -> 0
B25: Bach. graduates admitted to graduate school | D25: na | E25: na | F25: na | G25: na | H25: =SUM(D25:G25) -> 0
A26: Master's Degree | D26: na | E26: na | F26: na | G26: na | H26: =SUM(D26:G26) -> 0
A27: Gainfully Employed after graduation | D27: na | E27: na | F27: na | G27: na | H27: =SUM(D27:G27) -> 0
A28: Graduates who completed remedial courses during their time at the TCU | D28: na | E28: na | F28: na | G28: na | H28: =SUM(D28:G28) -> 0
A29: Graduates who received A*CF support at some point during their coursework | D29: na | E29: na | F29: na | G29: na | H29: =SUM(D29:G29) -> 0
A31: Notes:
A32: Core students - undergraduate undecided; Undeclared - graduate students

Sheet 4.2(MS) Major Group Enroll-Grad
A1: Institution | D1: ='1.1a Overall Instit. Profile'!B1 -> Oglala Lakota College
A2: Indicator 4: Student Enrollment and Graduation by Major Group
A3: Table 4.2(MS): Major Group Fall Enrollment, Graduation & Post-Graduate / AY 20010-11
B4: Major Group | C4: MS - Master's
B5: Please enter the number of students enrolled in this major group for the fall semester.
F6: Fall 2011 (October 15, 2011)
B7: Fall Enrollment (Snapshot) | D7: American Indian | F7: Non-Indian
D8: M | E8: F | F8: M | G8: F | H8: Total
C9: Full Time | D9: 2 | E9: 12 | F9: 0 | G9: 1 | H9: =SUM(D9:G9) -> 15
C10: Part Time | D10: 14 | E10: 35 | F10: 1 | G10: 2 | H10: =SUM(D10:G10) -> 52
C11: Total | D11: =SUM(D9:D10) -> 16 | E11: =SUM(E9:E10) -> 47 | F11: =SUM(F9:F10) -> 1 | G11: =SUM(G9:G10) -> 3 | H11: =SUM(D11:G11) -> 67
B12: Please enter the number of diploma, certificates, and degrees earned in this major group. Also enter the number of students who were admitted to a 4 year (Associate degree graduates), or graduate school (Bachelor's degree graduates). Lastly, enter the number of all graduating students(certificate or degree) who secured gainful employment after graduation.
F13: July 1, 2011- June 30, 2012
B14: Graduation | D14: American Indian | F14: Non-Indian
D15: M | E15: F | F15: M | G15: F | H15: Total
A16: Apprenticeship/Occupational Program | D16: na | E16: na | F16: na | G16: na | H16: =SUM(D16:G16) -> 0
B17: App. graduates admitted to a college program | D17: na | E17: na | F17: na | G17: na | H17: =SUM(D17:G17) -> 0
A18: Diploma | D18: na | E18: na | F18: na | G18: na | H18: =SUM(D18:G18) -> 0
B19: Dip. graduates admitted to a college program | D19: na | E19: na | F19: na | G19: na | H19: =SUM(D19:G19) -> 0
A20: Certificate | D20: na | E20: na | F20: na | G20: na | H20: =SUM(D20:G20) -> 0
B21: Cert. graduates admitted to a college program | D21: na | E21: na | F21: na | G21: na | H21: =SUM(D21:G21) -> 0
A22: Associate Degree | D22: na | E22: na | F22: na | G22: na | H22: =SUM(D22:G22) -> 0
B23: Assoc. graduates admitted to four-year program | D23: na | E23: na | F23: na | G23: na | H23: =SUM(D23:G23) -> 0
A24: Bachelor's Degree | D24: na | E24: na | F24: na | G24: na | H24: =SUM(D24:G24) -> 0
B25: Bach. graduates admitted to graduate school | D25: na | E25: na | F25: na | G25: na | H25: =SUM(D25:G25) -> 0
A26: Master's Degree | D26: 5 | E26: 8 | F26: 0 | G26: 1 | H26: =SUM(D26:G26) -> 14
A27: Gainfully Employed after graduation | D27: m | E27: m | F27: m | G27: m | H27: =SUM(D27:G27) -> 0
A28: Graduates who completed remedial courses during their time at the TCU | D28: m | E28: m | F28: m | G28: m | H28: =SUM(D28:G28) -> 0
A29: Graduates who received A*CF support at some point during their coursework | D29: m | E29: m | F29: m | G29: m | H29: =SUM(D29:G29) -> 0
A31: Notes:
A32: We do not track graduates.

Sheet 4.2 Major Group Totals
A1: Institution | D1: ='1.1a Overall Instit. Profile'!B1 -> Oglala Lakota College
A2: Indicator 4: Student Enrollment and Graduation by Major Group
A3: Table 4.2: Major Group Fall Enrollment, Graduation & Post-Graduate Totals / AY 2011-12
A4: Please enter the number of students enrolled in this major group for the fall semester. DO NOT CHANGE THE FORMULAS ON THIS PAGE.
F5: Fall 2011 (October 15, 2011)
B6: Fall Enrollment (Snapshot) | D6: American Indian | F6: Non-Indian
D7: M | E7: F | F7: M | G7: F | H7: Total
C8: Full Time | D8: =SUM('4.2(AC) Major Group Enroll-Grad:4.2(MS) Major Group Enroll-Grad'!D9) -> 341 | E8: =SUM('4.2(AC) Major Group Enroll-Grad:4.2(MS) Major Group Enroll-Grad'!E9) -> 632 | F8: =SUM('4.2(AC) Major Group Enroll-Grad:4.2(MS) Major Group Enroll-Grad'!F9) -> 22 | G8: =SUM('4.2(AC) Major Group Enroll-Grad:4.2(MS) Major Group Enroll-Grad'!G9) -> 25 | H8: =SUM(D8:G8) -> 1020
C9: Part Time | D9: =SUM('4.2(AC) Major Group Enroll-Grad:4.2(MS) Major Group Enroll-Grad'!D10) -> 193 | E9: =SUM('4.2(AC) Major Group Enroll-Grad:4.2(MS) Major Group Enroll-Grad'!E10) -> 436 | F9: =SUM('4.2(AC) Major Group Enroll-Grad:4.2(MS) Major Group Enroll-Grad'!F10) -> 9 | G9: =SUM('4.2(AC) Major Group Enroll-Grad:4.2(MS) Major Group Enroll-Grad'!G10) -> 42 | H9: =SUM(D9:G9) -> 680
C10: Total | D10: =SUM(D8:D9) -> 534 | E10: =SUM(E8:E9) -> 1068 | F10: =SUM(F8:F9) -> 31 | G10: =SUM(G8:G9) -> 67 | H10: =SUM(D10:G10) -> 1700
A11: Please enter the number of diploma, certificates, and degrees earned in this major group. Also enter the number of students graduating with degrees who earned a GPA of 3.0 or above, and the number who were admitted to a 4 year (Associate degree graduates), or graduate school (Bachelor's degree graduates). Lastly, enter the number of all graduating students(certificate or degree) who secured employment after graduation.
F12: July 1, 2011 - June 30, 2012
B13: Graduation | D13: American Indian | F13: Non-Indian
D14: M | E14: F | F14: M | G14: F | H14: Total
A15: Apprenticeship/Occupational Program | D15: =SUM('4.2(AC) Major Group Enroll-Grad:4.2(MS) Major Group Enroll-Grad'!D16) -> 0 | E15: =SUM('4.2(AC) Major Group Enroll-Grad:4.2(MS) Major Group Enroll-Grad'!E16) -> 0 | F15: =SUM('4.2(AC) Major Group Enroll-Grad:4.2(MS) Major Group Enroll-Grad'!F16) -> 0 | G15: =SUM('4.2(AC) Major Group Enroll-Grad:4.2(MS) Major Group Enroll-Grad'!G16) -> 0 | H15: =SUM(D15:G15) -> 0
B16: App. graduates admitted to a college program | D16: =SUM('4.2(AC) Major Group Enroll-Grad:4.2(MS) Major Group Enroll-Grad'!D17) -> 0 | E16: =SUM('4.2(AC) Major Group Enroll-Grad:4.2(MS) Major Group Enroll-Grad'!E17) -> 0 | F16: =SUM('4.2(AC) Major Group Enroll-Grad:4.2(MS) Major Group Enroll-Grad'!F17) -> 0 | G16: =SUM('4.2(AC) Major Group Enroll-Grad:4.2(MS) Major Group Enroll-Grad'!G17) -> 0 | H16: =SUM(D16:G16) -> 0
A17: Diploma | D17: =SUM('4.2(AC) Major Group Enroll-Grad:4.2(MS) Major Group Enroll-Grad'!D18) -> 0 | E17: =SUM('4.2(AC) Major Group Enroll-Grad:4.2(MS) Major Group Enroll-Grad'!E18) -> 0 | F17: =SUM('4.2(AC) Major Group Enroll-Grad:4.2(MS) Major Group Enroll-Grad'!F18) -> 0 | G17: =SUM('4.2(AC) Major Group Enroll-Grad:4.2(MS) Major Group Enroll-Grad'!G18) -> 0 | H17: =SUM(D17:G17) -> 0
B18: Dip. graduates admitted to a college program | D18: =SUM('4.2(AC) Major Group Enroll-Grad:4.2(MS) Major Group Enroll-Grad'!D19) -> 0 | E18: =SUM('4.2(AC) Major Group Enroll-Grad:4.2(MS) Major Group Enroll-Grad'!E19) -> 0 | F18: =SUM('4.2(AC) Major Group Enroll-Grad:4.2(MS) Major Group Enroll-Grad'!F19) -> 0 | G18: =SUM('4.2(AC) Major Group Enroll-Grad:4.2(MS) Major Group Enroll-Grad'!G19) -> 0 | H18: =SUM(D18:G18) -> 0
A19: Certificate | D19: =SUM('4.2(AC) Major Group Enroll-Grad:4.2(MS) Major Group Enroll-Grad'!D20) -> 5 | E19: =SUM('4.2(AC) Major Group Enroll-Grad:4.2(MS) Major Group Enroll-Grad'!E20) -> 3 | F19: =SUM('4.2(AC) Major Group Enroll-Grad:4.2(MS) Major Group Enroll-Grad'!F20) -> 0 | G19: =SUM('4.2(AC) Major Group Enroll-Grad:4.2(MS) Major Group Enroll-Grad'!G20) -> 0 | H19: =SUM(D19:G19) -> 8
B20: Cert. graduates admitted to a college program | D20: =SUM('4.2(AC) Major Group Enroll-Grad:4.2(MS) Major Group Enroll-Grad'!D21) -> 0 | E20: =SUM('4.2(AC) Major Group Enroll-Grad:4.2(MS) Major Group Enroll-Grad'!E21) -> 0 | F20: =SUM('4.2(AC) Major Group Enroll-Grad:4.2(MS) Major Group Enroll-Grad'!F21) -> 0 | G20: =SUM('4.2(AC) Major Group Enroll-Grad:4.2(MS) Major Group Enroll-Grad'!G21) -> 0 | H20: =SUM(D20:G20) -> 0
A21: Associate Degree | D21: =SUM('4.2(AC) Major Group Enroll-Grad:4.2(MS) Major Group Enroll-Grad'!D22) -> 30 | E21: =SUM('4.2(AC) Major Group Enroll-Grad:4.2(MS) Major Group Enroll-Grad'!E22) -> 83 | F21: =SUM('4.2(AC) Major Group Enroll-Grad:4.2(MS) Major Group Enroll-Grad'!F22) -> 0 | G21: =SUM('4.2(AC) Major Group Enroll-Grad:4.2(MS) Major Group Enroll-Grad'!G22) -> 7 | H21: =SUM(D21:G21) -> 120
B22: Assoc. graduates admitted to four-year program | D22: =SUM('4.2(AC) Major Group Enroll-Grad:4.2(MS) Major Group Enroll-Grad'!D23) -> 0 | E22: =SUM('4.2(AC) Major Group Enroll-Grad:4.2(MS) Major Group Enroll-Grad'!E23) -> 0 | F22: =SUM('4.2(AC) Major Group Enroll-Grad:4.2(MS) Major Group Enroll-Grad'!F23) -> 0 | G22: =SUM('4.2(AC) Major Group Enroll-Grad:4.2(MS) Major Group Enroll-Grad'!G23) -> 0 | H22: =SUM(D22:G22) -> 0
A23: Bachelor's Degree | D23: =SUM('4.2(AC) Major Group Enroll-Grad:4.2(MS) Major Group Enroll-Grad'!D24) -> 14 | E23: =SUM('4.2(AC) Major Group Enroll-Grad:4.2(MS) Major Group Enroll-Grad'!E24) -> 29 | F23: =SUM('4.2(AC) Major Group Enroll-Grad:4.2(MS) Major Group Enroll-Grad'!F24) -> 4 | G23: =SUM('4.2(AC) Major Group Enroll-Grad:4.2(MS) Major Group Enroll-Grad'!G24) -> 3 | H23: =SUM(D23:G23) -> 50
B24: Bach. graduates admitted to graduate school | D24: =SUM('4.2(AC) Major Group Enroll-Grad:4.2(MS) Major Group Enroll-Grad'!D25) -> 0 | E24: =SUM('4.2(AC) Major Group Enroll-Grad:4.2(MS) Major Group Enroll-Grad'!E25) -> 0 | F24: =SUM('4.2(AC) Major Group Enroll-Grad:4.2(MS) Major Group Enroll-Grad'!F25) -> 0 | G24: =SUM('4.2(AC) Major Group Enroll-Grad:4.2(MS) Major Group Enroll-Grad'!G25) -> 0 | H24: =SUM(D24:G24) -> 0
A25: Master's Degree | D25: =SUM('4.2(AC) Major Group Enroll-Grad:4.2(MS) Major Group Enroll-Grad'!D26) -> 5 | E25: =SUM('4.2(AC) Major Group Enroll-Grad:4.2(MS) Major Group Enroll-Grad'!E26) -> 8 | F25: =SUM('4.2(AC) Major Group Enroll-Grad:4.2(MS) Major Group Enroll-Grad'!F26) -> 0 | G25: =SUM('4.2(AC) Major Group Enroll-Grad:4.2(MS) Major Group Enroll-Grad'!G26) -> 1 | H25: =SUM(D25:G25) -> 14
A26: Gainfully Employed after graduation | D26: =SUM('4.2(AC) Major Group Enroll-Grad:4.2(MS) Major Group Enroll-Grad'!D27) -> 0 | E26: =SUM('4.2(AC) Major Group Enroll-Grad:4.2(MS) Major Group Enroll-Grad'!E27) -> 0 | F26: =SUM('4.2(AC) Major Group Enroll-Grad:4.2(MS) Major Group Enroll-Grad'!F27) -> 0 | G26: =SUM('4.2(AC) Major Group Enroll-Grad:4.2(MS) Major Group Enroll-Grad'!G27) -> 0 | H26: =SUM(D26:G26) -> 0
A27: Graduates who completed remedial courses during their time at the TCU | D27: =SUM('4.2(AC) Major Group Enroll-Grad:4.2(MS) Major Group Enroll-Grad'!D28) -> 0 | E27: =SUM('4.2(AC) Major Group Enroll-Grad:4.2(MS) Major Group Enroll-Grad'!E28) -> 0 | F27: =SUM('4.2(AC) Major Group Enroll-Grad:4.2(MS) Major Group Enroll-Grad'!F28) -> 0 | G27: =SUM('4.2(AC) Major Group Enroll-Grad:4.2(MS) Major Group Enroll-Grad'!G28) -> 0 | H27: =SUM(D27:G27) -> 0
A28: Graduates who received A*CF support at some point during their coursework | D28: =SUM('4.2(AC) Major Group Enroll-Grad:4.2(MS) Major Group Enroll-Grad'!D29) -> 0 | E28: =SUM('4.2(AC) Major Group Enroll-Grad:4.2(MS) Major Group Enroll-Grad'!E29) -> 0 | F28: =SUM('4.2(AC) Major Group Enroll-Grad:4.2(MS) Major Group Enroll-Grad'!F29) -> 0 | G28: =SUM('4.2(AC) Major Group Enroll-Grad:4.2(MS) Major Group Enroll-Grad'!G29) -> 0 | H28: =SUM(D28:G28) -> 0
A30: Did your institution experience an increase or decrease in enrollment of 25% or more? If so, explain why.
A31: No
A33: Notes:

Sheet 5.1 Academic Core Curriculum
A1: Institution | B1: ='1.1a Overall Instit. Profile'!B1 -> Oglala Lakota College
A2: Indicator 5: Course Enrollment and Completion
A3: Table 5.1: Academic Core Curriculum Courses
A4: Please identify your institution's specific Academic Program's Core Curriculum courses required for all students in 2 or 4 year program. Enter 'nr' if the course is not required. Please add additional academic core curriculum courses in the spaces provided.
A5: Course | B5: Course ID(s) | C5: Course Title(s) | D5: Credits Given
A6: English Composition I | B6: ENGL 103 | C6: Freshman English I | D6: 3
A7: English Composition II | B7: ENGL 113 | C7: Freshman English II | D7: 3
A8: Communications | B8: SPCM 103 | C8: Speech Communications | D8: 3
A9: College Mathematics | B9: MATH 103 | C9: Elementary Algebra | D9: 3
A10: Introduction to Computers | B10: MIS 113 | C10: Applied Information Processing | D10: 3
A11: Native American Studies | B11: LAK 103 | C11: Lakota Language I | D11: 3
A12: Lakota Language II | B12: LAK 233 | C12: Lakota Language II | D12: 3
A13: Lakota Culture | B13: LSOC 103 | C13: Lakota Culture | D13: 3
A14: College Success | B14: COSU 103 | C14: College Success - not required | D14: 3
A17: Notes:

Sheet 5.2 Acad Course Enroll & Comp
A1: Institution | B1: ='1.1a Overall Instit. Profile'!B1 -> Oglala Lakota College
A2: Indicator 5: Course Enrollment and Completion
A3: Table 5.2: Academic Core Curriculum Course Enrollment and Successful Completion / AY 2011-12
A4: Please enter Course Enrollment and Successful Completion data (passed with grade 'C' or better) for the courses listed in Table 5.1. Enter 'no' if the course is not offered that semester/quarter, or 'nr' if course is not required.
A5: Academic Core Curriculum Course Enrollment and Successful Completion
A6: Course | B6: Number of Students | C6: AY 2011-12
C7: Summer 11 | G7: Fall 11 | K7: Winter 12 | O7: Spring 12
C8: American Indian | E8: Non-Indian | G8: American Indian | I8: Non-Indian | K8: American Indian | M8: Non-Indian | O8: American Indian | Q8: Non-Indian
C9: M | D9: F | E9: M | F9: F | G9: M | H9: F | I9: M | J9: F | K9: M | L9: F | M9: M | N9: F | O9: M | P9: F | Q9: M | R9: F
B10: Enrolled | C10: 0 | D10: 0 | E10: 0 | F10: 0 | G10: 88 | H10: 144 | I10: 1 | J10: 3 | K10: na | L10: na | M10: na | N10: na | O10: 81 | P10: 122 | Q10: 1 | R10: 5
A11: ='5.1 Academic Core Curriculum'!A6 -> English Composition I | B11: Success Comp. | C11: 0 | D11: 0 | E11: 0 | F11: 0 | G11: 51 | H11: 95 | I11: 1 | J11: 1 | K11: na | L11: na | M11: na | N11: na | O11: 32 | P11: 73 | Q11: 1 | R11: 3
B12: Withdrew | C12: 0 | D12: 0 | E12: 0 | F12: 0 | G12: 37 | H12: 49 | I12: 0 | J12: 2 | K12: na | L12: na | M12: na | N12: na | O12: 49 | P12: 49 | Q12: 0 | R12: 2
B13: Enrolled | C13: 1 | D13: 4 | E13: 0 | F13: 1 | G13: 61 | H13: 100 | I13: 0 | J13: 5 | K13: na | L13: na | M13: na | N13: na | O13: 59 | P13: 149 | Q13: 2 | R13: 4
A14: ='5.1 Academic Core Curriculum'!A7 -> English Composition II | B14: Success Comp. | C14: 1 | D14: 3 | E14: 0 | F14: 1 | G14: 21 | H14: 51 | I14: 0 | J14: 5 | K14: na | L14: na | M14: na | N14: na | O14: 26 | P14: 81 | Q14: 1 | R14: 3
B15: Withdrew | C15: 0 | D15: 1 | E15: 9 | F15: 0 | G15: 40 | H15: 49 | I15: 0 | J15: 0 | K15: na | L15: na | M15: na | N15: na | O15: 33 | P15: 68 | Q15: 1 | R15: 1
B16: Enrolled | C16: 4 | D16: 4 | E16: 0 | F16: 1 | G16: 88 | H16: 156 | I16: 1 | J16: 4 | K16: na | L16: na | M16: na | N16: na | O16: 93 | P16: 152 | Q16: 2 | R16: 6
A17: ='5.1 Academic Core Curriculum'!A8 -> Communications | B17: Success Comp. | C17: 4 | D17: 4 | E17: 0 | F17: 1 | G17: 53 | H17: 46 | I17: 1 | J17: 4 | K17: na | L17: na | M17: na | N17: na | O17: 47 | P17: 91 | Q17: 2 | R17: 5
B18: Withdrew | C18: 0 | D18: 0 | E18: 0 | F18: 0 | G18: 35 | H18: 60 | I18: 0 | J18: 0 | K18: na | L18: na | M18: na | N18: na | O18: 46 | P18: 61 | Q18: 0 | R18: 1
B19: Enrolled | C19: 2 | D19: 8 | E19: 0 | F19: 0 | G19: 67 | H19: 128 | I19: 1 | J19: 4 | K19: na | L19: na | M19: na | N19: na | O19: 56 | P19: 132 | Q19: 1 | R19: 2
A20: ='5.1 Academic Core Curriculum'!A9 -> College Mathematics | B20: Success Comp. | C20: 2 | D20: 8 | E20: 0 | F20: 0 | G20: 29 | H20: 72 | I20: 0 | J20: 2 | K20: na | L20: na | M20: na | N20: na | O20: 18 | P20: 55 | Q20: 0 | R20: 1
B21: Withdrew | C21: 0 | D21: 0 | E21: 0 | F21: 0 | G21: 38 | H21: 56 | I21: 1 | J21: 2 | K21: na | L21: na | M21: na | N21: na | O21: 38 | P21: 77 | Q21: 1 | R21: 1
B22: Enrolled | C22: 5 | D22: 11 | E22: 0 | F22: 0 | G22: 78 | H22: 117 | I22: 0 | J22: 1 | K22: na | L22: na | M22: na | N22: na | O22: 87 | P22: 140 | Q22: 0 | R22: 5
A23: ='5.1 Academic Core Curriculum'!A10 -> Introduction to Computers | B23: Success Comp. | C23: 3 | D23: 10 | E23: 0 | F23: 0 | G23: 42 | H23: 61 | I23: 0 | J23: 0 | K23: na | L23: na | M23: na | N23: na | O23: 38 | P23: 71 | Q23: 0 | R23: 4
B24: Withdrew | C24: 2 | D24: 1 | E24: 0 | F24: 0 | G24: 36 | H24: 56 | I24: 0 | J24: 1 | K24: na | L24: na | M24: na | N24: na | O24: 49 | P24: 69 | Q24: 0 | R24: 1
B25: Enrolled | C25: 5 | D25: 10 | E25: 0 | F25: 0 | G25: 140 | H25: 212 | I25: 4 | J25: 8 | K25: na | L25: na | M25: na | N25: na | O25: 97 | P25: 125 | Q25: 2 | R25: 10
A26: ='5.1 Academic Core Curriculum'!A11 -> Native American Studies | B26: Success Comp. | C26: 5 | D26: 10 | E26: 0 | F26: 0 | G26: 75 | H26: 133 | I26: 2 | J26: 6 | K26: na | L26: na | M26: na | N26: na | O26: 43 | P26: 74 | Q26: 2 | R26: 10
B27: Withdrew | C27: 0 | D27: 0 | E27: 0 | F27: 0 | G27: 65 | H27: 79 | I27: 2 | J27: 2 | K27: na | L27: na | M27: na | N27: na | O27: 54 | P27: 51 | Q27: 0 | R27: 0
B28: Enrolled | C28: 1 | D28: 7 | E28: 0 | F28: 0 | G28: 31 | H28: 71 | I28: 0 | J28: 3 | K28: na | L28: na | M28: na | N28: na | O28: 49 | P28: 100 | Q28: 1 | R28: 3
A29: =IF('5.1 Academic Core Curriculum'!A12=0,"",'5.1 Academic Core Curriculum'!A12) -> Lakota Language II | B29: Success Comp. | C29: 1 | D29: 7 | E29: 0 | F29: 0 | G29: 19 | H29: 51 | I29: 0 | J29: 3 | K29: na | L29: na | M29: na | N29: na | O29: 34 | P29: 70 | Q29: 1 | R29: 1
B30: Withdrew | C30: 0 | D30: 0 | E30: 0 | F30: 0 | G30: 12 | H30: 20 | I30: 0 | J30: 0 | K30: na | L30: na | M30: na | N30: na | O30: 15 | P30: 30 | Q30: 0 | R30: 2
B31: Enrolled | C31: 5 | D31: 13 | E31: 0 | F31: 0 | G31: 97 | H31: 167 | I31: 10 | J31: 10 | K31: na | L31: na | M31: na | N31: na | O31: 94 | P31: 133 | Q31: 1 | R31: 2
A32: =IF('5.1 Academic Core Curriculum'!A13=0,"",'5.1 Academic Core Curriculum'!A13) -> Lakota Culture | B32: Success Comp. | C32: 5 | D32: 13 | E32: 0 | F32: 0 | G32: 55 | H32: 111 | I32: 8 | J32: 10 | K32: na | L32: na | M32: na | N32: na | O32: 34 | P32: 66 | Q32: 1 | R32: 1
B33: Withdrew | C33: 0 | D33: 0 | E33: 0 | F33: 0 | G33: 42 | H33: 56 | I33: 2 | J33: 0 | K33: na | L33: na | M33: na | N33: na | O33: 60 | P33: 67 | Q33: 0 | R33: 1
B34: Enrolled | C34: 0 | D34: 0 | E34: 0 | F34: 0 | G34: 0 | H34: 0 | I34: 0 | J34: 0 | K34: na | L34: na | M34: na | N34: na | O34: 0 | P34: 0 | Q34: 0 | R34: 0
A35: =IF('5.1 Academic Core Curriculum'!A14=0,"",'5.1 Academic Core Curriculum'!A14) -> College Success | B35: Success Comp. | C35: 0 | D35: 0 | E35: 0 | F35: 0 | G35: 0 | H35: 0 | I35: 0 | J35: 0 | K35: na | L35: na | M35: na | N35: na | O35: 0 | P35: 0 | Q35: 0 | R35: 0
B36: Withdrew | C36: 0 | D36: 0 | E36: 0 | F36: 0 | G36: 0 | H36: 0 | I36: 0 | J36: 0 | K36: na | L36: na | M36: na | N36: na | O36: 0 | P36: 0 | Q36: 0 | R36: 0
B37: Enrolled | K37: na | L37: na | M37: na | N37: na
A38: =IF('5.1 Academic Core Curriculum'!A15=0,"",'5.1 Academic Core Curriculum'!A15) | B38: Success Comp. | K38: na | L38: na | M38: na | N38: na
B39: Withdrew | K39: na | L39: na | M39: na | N39: na
B40: Enrolled | K40: na | L40: na | M40: na | N40: na
A41: =IF('5.1 Academic Core Curriculum'!A16=0,"",'5.1 Academic Core Curriculum'!A16) | B41: Success Comp. | K41: na | L41: na | M41: na | N41: na
B42: Withdrew | K42: na | L42: na | M42: na | N42: na
A44: Notes:
A45: College Success is no longer required. We do not have a winter semester.

Sheet 5.3 Vocational Core Curriculum
A1: Institution | B1: ='1.1a Overall Instit. Profile'!B1 -> Oglala Lakota College
A2: Indicator 5: Course Enrollment and Completion
A3: Table 5.3: Vocational Core Curriculum Courses
A4: Please identify your institution's specific Vocational Program's Core Curriculum courses required for diploma / certificate program. Enter 'nr' if the course is not required. Please add additional vocational core curriculum courses in the spaces provided.
A5: Course | B5: Course ID(s) | C5: Course Title(s) | D5: Credits Given
A6: English Composition I | B6: ENGL 103 | C6: Freshman English I | D6: 3
A7: English Composition II | B7: ENGL 113 | C7: only required for Office Technology | D7: 3
A8: Communications | B8: SPCM 103 | C8: Speech Communications | D8: 3
A9: General Mathematics | B9: MATH103, OMATH113,CMATH153 | C9: Elementary Algebra, Occupational Math, Consumer Math (Any one of these courses meet the requirement). | D9: 3
A10: Introduction to Computers | B10: na | C10: na | D10: na
A11: Native American Studies | B11: LAK 103 | C11: Lakota Language I | D11: 3
A12: College Success | B12: COSU 103 | C12: College Success -not required | D12: 3
A17: Notes:
A18: Recorded with Academic Core

Sheet 5.4 Voc Course Enroll & Comp
A1: Institution | B1: ='1.1a Overall Instit. Profile'!B1 -> Oglala Lakota College
A2: Indicator 5: Course Enrollment and Completion
A3: Table 5.4: Vocational Core Curriculum Course Enrollment and Successful Completion / AY 2011-12
A4: Please enter Course Enrollment and Successful Completion data (passed with grade 'C' or better) for the courses listed in Table 5.3. Enter 'no' if the course is not offered that semester / quarter, or 'nr' if course is not required.
A5: Vocational Core Curriculum Course Enrollment and Successful Completion
A6: Course | B6: Number of Students | C6: AY 2011-12
C7: Summer 11 | G7: Fall 11 | K7: Winter 12 | O7: Spring 12
C8: American Indian | E8: Non-Indian | G8: American Indian | I8: Non-Indian | K8: American Indian | M8: Non-Indian | O8: American Indian | Q8: Non-Indian
C9: M | D9: F | E9: M | F9: F | G9: M | H9: F | I9: M | J9: F | K9: M | L9: F | M9: M | N9: F | O9: M | P9: F | Q9: M | R9: F
B10: Enrolled | C10: na | D10: na | E10: na | F10: na | G10: na | H10: na | I10: na | J10: na | K10: na | L10: na | M10: na | N10: na | O10: na | P10: na | Q10: na | R10: na
A11: ='5.3 Vocational Core Curriculum'!A6 -> English Composition I | B11: Success Comp. | C11: na | D11: na | E11: na | F11: na | G11: na | H11: na | I11: na | J11: na | K11: na | L11: na | M11: na | N11: na | O11: na | P11: na | Q11: na | R11: na
B12: Withdrew | C12: na | D12: na | E12: na | F12: na | G12: na | H12: na | I12: na | J12: na | K12: na | L12: na | M12: na | N12: na | O12: na | P12: na | Q12: na | R12: na
B13: Enrolled | C13: na | D13: na | E13: na | F13: na | G13: na | H13: na | I13: na | J13: na | K13: na | L13: na | M13: na | N13: na | O13: na | P13: na | Q13: na | R13: na
A14: ='5.3 Vocational Core Curriculum'!A7 -> English Composition II | B14: Success Comp. | C14: na | D14: na | E14: na | F14: na | G14: na | H14: na | I14: na | J14: na | K14: na | L14: na | M14: na | N14: na | O14: na | P14: na | Q14: na | R14: na
B15: Withdrew | C15: na | D15: na | E15: na | F15: na | G15: na | H15: na | I15: na | J15: na | K15: na | L15: na | M15: na | N15: na | O15: na | P15: na | Q15: na | R15: na
B16: Enrolled | C16: na | D16: na | E16: na | F16: na | G16: na | H16: na | I16: na | J16: na | K16: na | L16: na | M16: na | N16: na | O16: na | P16: na | Q16: na | R16: na
A17: ='5.3 Vocational Core Curriculum'!A8 -> Communications | B17: Success Comp. | C17: na | D17: na | E17: na | F17: na | G17: na | H17: na | I17: na | J17: na | K17: na | L17: na | M17: na | N17: na | O17: na | P17: na | Q17: na | R17: na
B18: Withdrew | C18: na | D18: na | E18: na | F18: na | G18: na | H18: na | I18: na | J18: na | K18: na | L18: na | M18: na | N18: na | O18: na | P18: na | Q18: na | R18: na
B19: Enrolled | C19: na | D19: na | E19: na | F19: na | G19: na | H19: na | I19: na | J19: na | K19: na | L19: na | M19: na | N19: na | O19: na | P19: na | Q19: na | R19: na
A20: ='5.3 Vocational Core Curriculum'!A9 -> General Mathematics | B20: Success Comp. | C20: na | D20: na | E20: na | F20: na | G20: na | H20: na | I20: na | J20: na | K20: na | L20: na | M20: na | N20: na | O20: na | P20: na | Q20: na | R20: na
B21: Withdrew | C21: na | D21: na | E21: na | F21: na | G21: na | H21: na | I21: na | J21: na | K21: na | L21: na | M21: na | N21: na | O21: na | P21: na | Q21: na | R21: na
B22: Enrolled | C22: na | D22: na | E22: na | F22: na | G22: na | H22: na | I22: na | J22: na | K22: na | L22: na | M22: na | N22: na | O22: na | P22: na | Q22: na | R22: na
A23: ='5.3 Vocational Core Curriculum'!A10 -> Introduction to Computers | B23: Success Comp. | C23: na | D23: na | E23: na | F23: na | G23: na | H23: na | I23: na | J23: na | K23: na | L23: na | M23: na | N23: na | O23: na | P23: na | Q23: na | R23: na
B24: Withdrew | C24: na | D24: na | E24: na | F24: na | G24: na | H24: na | I24: na | J24: na | K24: na | L24: na | M24: na | N24: na | O24: na | P24: na | Q24: na | R24: na
B25: Enrolled | C25: na | D25: na | E25: na | F25: na | G25: na | H25: na | I25: na | J25: na | K25: na | L25: na | M25: na | N25: na | O25: na | P25: na | Q25: na | R25: na
A26: ='5.3 Vocational Core Curriculum'!A11 -> Native American Studies | B26: Success Comp. | C26: na | D26: na | E26: na | F26: na | G26: na | H26: na | I26: na | J26: na | K26: na | L26: na | M26: na | N26: na | O26: na | P26: na | Q26: na | R26: na
B27: Withdrew | C27: na | D27: na | E27: na | F27: na | G27: na | H27: na | I27: na | J27: na | K27: na | L27: na | M27: na | N27: na | O27: na | P27: na | Q27: na | R27: na
B28: Enrolled | C28: na | D28: na | E28: na | F28: na | G28: na | H28: na | I28: na | J28: na | K28: na | L28: na | M28: na | N28: na | O28: na | P28: na | Q28: na | R28: na
A29: =IF('5.3 Vocational Core Curriculum'!A12=0,"",'5.3 Vocational Core Curriculum'!A12) -> College Success | B29: Success Comp. | C29: na | D29: na | E29: na | F29: na | G29: na | H29: na | I29: na | J29: na | K29: na | L29: na | M29: na | N29: na | O29: na | P29: na | Q29: na | R29: na
B30: Withdrew | C30: na | D30: na | E30: na | F30: na | G30: na | H30: na | I30: na | J30: na | K30: na | L30: na | M30: na | N30: na | O30: na | P30: na | Q30: na | R30: na
B31: Enrolled | C31: na | D31: na | E31: na | F31: na | G31: na | H31: na | I31: na | J31: na | K31: na | L31: na | M31: na | N31: na | O31: na | P31: na | Q31: na | R31: na
A32: =IF('5.3 Vocational Core Curriculum'!A13=0,"",'5.3 Vocational Core Curriculum'!A13) | B32: Success Comp. | C32: na | D32: na | E32: na | F32: na | G32: na | H32: na | I32: na | J32: na | K32: na | L32: na | M32: na | N32: na | O32: na | P32: na | Q32: na | R32: na
B33: Withdrew | C33: na | D33: na | E33: na | F33: na | G33: na | H33: na | I33: na | J33: na | K33: na | L33: na | M33: na | N33: na | O33: na | P33: na | Q33: na | R33: na
B34: Enrolled | C34: na | D34: na | E34: na | F34: na | G34: na | H34: na | I34: na | J34: na | K34: na | L34: na | M34: na | N34: na | O34: na | P34: na | Q34: na | R34: na
A35: =IF('5.3 Vocational Core Curriculum'!A14=0,"",'5.3 Vocational Core Curriculum'!A14) | B35: Success Comp. | C35: na | D35: na | E35: na | F35: na | G35: na | H35: na | I35: na | J35: na | K35: na | L35: na | M35: na | N35: na | O35: na | P35: na | Q35: na | R35: na
B36: Withdrew | C36: na | D36: na | E36: na | F36: na | G36: na | H36: na | I36: na | J36: na | K36: na | L36: na | M36: na | N36: na | O36: na | P36: na | Q36: na | R36: na
B37: Enrolled | C37: na | D37: na | E37: na | F37: na | G37: na | H37: na | I37: na | J37: na | K37: na | L37: na | M37: na | N37: na | O37: na | P37: na | Q37: na | R37: na
A38: =IF('5.3 Vocational Core Curriculum'!A15=0,"",'5.3 Vocational Core Curriculum'!A15) | B38: Success Comp. | C38: na | D38: na | E38: na | F38: na | G38: na | H38: na | I38: na | J38: na | K38: na | L38: na | M38: na | N38: na | O38: na | P38: na | Q38: na | R38: na
B39: Withdrew | C39: na | D39: na | E39: na | F39: na | G39: na | H39: na | I39: na | J39: na | K39: na | L39: na | M39: na | N39: na | O39: na | P39: na | Q39: na | R39: na
B40: Enrolled | C40: na | D40: na | E40: na | F40: na | G40: na | H40: na | I40: na | J40: na | K40: na | L40: na | M40: na | N40: na | O40: na | P40: na | Q40: na | R40: na
A41: =IF('5.3 Vocational Core Curriculum'!A16=0,"",'5.3 Vocational Core Curriculum'!A16) | B41: Success Comp. | C41: na | D41: na | E41: na | F41: na | G41: na | H41: na | I41: na | J41: na | K41: na | L41: na | M41: na | N41: na | O41: na | P41: na | Q41: na | R41: na
B42: Withdrew | C42: na | D42: na | E42: na | F42: na | G42: na | H42: na | I42: na | J42: na | K42: na | L42: na | M42: na | N42: na | O42: na | P42: na | Q42: na | R42: na
A44: Notes:
A45: Recorded with Academic Core

Sheet 5.5 & 5.6 Remedial-Dev Courses
A1: Institution | B1: ='1.1a Overall Instit. Profile'!B1 -> Oglala Lakota College
A2: Indicator 5: Course Enrollment and Completion
A3: Table 5.5: Remedial/Developmental Courses
A4: Please identify your institution's specific Remedial/Developmental courses. Enter 'no' if the course is not offered.
A5: Course | B5: Course ID(s) | E5: Course Title(s) | Q5: Credits Given
A6: Reading | B6: RW 083 | E6: Introduction to College Reading and Writing | Q6: 3
A7: Writing/Composition | B7: RW 093 | E7: Transition to Reading and Writing | Q7: 3
A8: Mathematics | B8: Math 083/093 | E8: Basic Math 1 & 2 | Q8: 6
A9: Science | B9: na | E9: na | Q9: na
A10: Table 5.6: Remedial/Developmental Course Enrollment and Successful Completion / AY 2011-12
A11: Please enter Course Enrollment and Successful Completion data (passed with grade 'C' or better). Enter 'no' if the course is not offered that semester / quarter, or 'nr' if course is not required.
A12: Remedial/Developmental Course Enrollment and Successful Completion
A13: Course | B13: Number of Students | C13: AY 2011-12
C14: Summer 11 | G14: Fall 11 | K14: Winter 12 | O14: Spring 12
C15: American Indian | E15: Non-Indian | G15: American Indian | I15: Non-Indian | K15: American Indian | M15: Non-Indian | O15: American Indian | Q15: Non-Indian
C16: M | D16: F | E16: M | F16: F | G16: M | H16: F | I16: M | J16: F | K16: M | L16: F | M16: M | N16: F | O16: M | P16: F | Q16: M | R16: F
B17: Enrolled | C17: 5 | D17: 5 | E17: 0 | F17: 0 | G17: 34 | H17: 59 | I17: 1 | J17: 0 | K17: na | L17: na | M17: na | N17: na | O17: 66 | P17: 73 | Q17: 0 | R17: 0
A18: =A6 -> Reading | B18: Success Comp. | C18: 2 | D18: 3 | E18: 0 | F18: 0 | G18: 13 | H18: 21 | I18: 1 | J18: 0 | K18: na | L18: na | M18: na | N18: na | O18: 23 | P18: 28 | Q18: 0 | R18: 0
B19: Withdrew | C19: 3 | D19: 2 | E19: 0 | F19: 0 | G19: 21 | H19: 38 | I19: 0 | J19: 0 | K19: na | L19: na | M19: na | N19: na | O19: 43 | P19: 45 | Q19: 0 | R19: 0
B20: Enrolled | C20: 0 | D20: 0 | E20: 0 | F20: 0 | G20: 33 | H20: 53 | I20: 0 | J20: 0 | K20: na | L20: na | M20: na | N20: na | O20: 41 | P20: 49 | Q20: 0 | R20: 0
A21: =A7 -> Writing/Composition | B21: Success Comp. | C21: 0 | D21: 0 | E21: 0 | F21: 0 | G21: 9 | H21: 24 | I21: 0 | J21: 0 | K21: na | L21: na | M21: na | N21: na | O21: 9 | P21: 16 | Q21: 0 | R21: 0
B22: Withdrew | C22: 0 | D22: 0 | E22: 0 | F22: 0 | G22: 24 | H22: 29 | I22: 0 | J22: 0 | K22: na | L22: na | M22: na | N22: na | O22: 32 | P22: 33 | Q22: 0 | R22: 0
B23: Enrolled | C23: 6 | D23: 15 | E23: 0 | F23: 0 | G23: 139 | H23: 239 | I23: 3 | J23: 3 | K23: na | L23: na | M23: na | N23: na | O23: 152 | P23: 221 | Q23: 2 | R23: 8
A24: =A8 -> Mathematics | B24: Success Comp. | C24: 4 | D24: 14 | E24: 0 | F24: 0 | G24: 32 | H24: 97 | I24: 1 | J24: 2 | K24: na | L24: na | M24: na | N24: na | O24: 45 | P24: 89 | Q24: 1 | R24: 7
B25: Withdrew | C25: 4 | D25: 1 | E25: 0 | F25: 0 | G25: 107 | H25: 142 | I25: 2 | J25: 1 | K25: na | L25: na | M25: na | N25: na | O25: 107 | P25: 132 | Q25: 1 | R25: 1
B26: Enrolled | C26: na | D26: na | E26: na | F26: na | G26: na | H26: na | I26: na | J26: na | K26: na | L26: na | M26: na | N26: na | O26: na | P26: na | Q26: na | R26: na
A27: =A9 -> Science | B27: Success Comp. | C27: na | D27: na | E27: na | F27: na | G27: na | H27: na | I27: na | J27: na | K27: na | L27: na | M27: na | N27: na | O27: na | P27: na | Q27: na | R27: na
B28: Withdrew | C28: na | D28: na | E28: na | F28: na | G28: na | H28: na | I28: na | J28: na | K28: na | L28: na | M28: na | N28: na | O28: na | P28: na | Q28: na | R28: na
A30: Notes:
A31: We do not offer remedial classes in science. We do not have a winter semester.

Sheet 5.7 Distance Learning
A1: Institution | C1: ='1.1a Overall Instit. Profile'!B1 -> Oglala Lakota College
A2: Indicator 5: Course Enrollment and Completion
A3: Table 5.7: Online and Distance Course Enrollment and Successful Completion / AY 2011-12
A4: Please enter Online and Distance Course Information.
A5: Please list the top five online and distance courses.
A6: We only offer around 12 courses via online per semester. Only 300 & 400 level courses are offered on line. We do not have distance education other than pictel classes and these are not tracked separately.
A11: II. Online Courses - Please enter the number of students enrolled in courses offered by your institution via the internet asynchronously, and the number of those students who passed.
A12: Online courses were NOT offered in 2011-12:
A13: Number of | C13: AY 2011-12
C14: Summer 11 | D14: Fall 11 | E14: Winter 12 | F14: Spring 12
A15: Courses Offered | C15: 0 | D15: 11 | E15: na | F15: 13
A16: American Indian Students Enrolled1 | B16: M | C16: 0 | D16: 28 | E16: na | F16: 41
B17: F | C17: 0 | D17: 141 | E17: na | F17: 160
A18: Non-Indian Students Enrolled1 | B18: M | C18: 0 | D18: 4 | E18: na | F18: 2
B19: F | C19: 0 | D19: 6 | E19: na | F19: 7
A20: American Indian Students Passed2 | B20: M | C20: 0 | D20: 11 | E20: na | F20: 17
B21: F | C21: 0 | D21: 52 | E21: na | F21: 71
A22: Non-Indian Students Passed2 | B22: M | C22: 0 | D22: 2 | E22: na | F22: 2
B23: F | C23: 0 | D23: 3 | E23: na | F23: 6
A24: American Indian Students Withdrew | B24: M | C24: 0 | D24: 17 | E24: na | F24: 24
B25: F | C25: 0 | D25: 89 | E25: na | F25: 89
A26: Non-Indian Students Withdrew | B26: M | C26: 0 | D26: 2 | E26: na | F26: 0
B27: F | C27: 0 | D27: 3 | E27: na | F27: 1
A28: Faculty Teaching Online Courses3 | C28: 0 | D28: 6 | E28: na | F28: 7
A29: III. Distance Courses Provided by Your Campus - Please enter the number of students enrolled in courses offered by your campus via satellite, interactive television, internet etc. to other campuses or institutions synchronously, and the number of those students who passed.
A30: Distance courses were NOT provided BY your campus in 2011-12: | E30: m
A31: Number of | C31: AY 2011-12
C32: Summer 11 | D32: Fall 11 | E32: Winter 12 | F32: Spring 12
A33: Courses Offered | C33: m | D33: m | E33: na | F33: m
A34: American Indian Students Enrolled1 | B34: M | C34: m | D34: m | E34: na | F34: m
B35: F | C35: m | D35: m | E35: na | F35: m
A36: Non-Indian Students Enrolled1 | B36: M | C36: m | D36: m | E36: na | F36: m
B37: F | C37: m | D37: m | E37: na | F37: m
A38: American Indian Students Passed2 | B38: M | C38: m | D38: m | E38: na | F38: m
B39: F | C39: m | D39: m | E39: na | F39: m
A40: Non-Indian Students Passed2 | B40: M | C40: m | D40: m | E40: na | F40: m
B41: F | C41: m | D41: m | E41: na | F41: m
A42: American Indian Students Withdrew | B42: M | C42: m | D42: m | E42: na | F42: m
B43: F | C43: m | D43: m | E43: na | F43: m
A44: Non-Indian Students Withdrew | B44: M | C44: m | D44: m | E44: na | F44: m
B45: F | C45: m | D45: m | E45: na | F45: m
A46: Faculty Teaching Distance Courses3 | C46: m | D46: m | E46: na | F46: m
A47: Sites Courses sent to | C47: m | D47: m | E47: na | F47: m
A48: IV. Distance Courses Provided to Your Campus - Please enter the number of students enrolled in courses offered on your campus synchronously taken via satellite, interactive television, internet etc. by external providers, and the number of those students who passed.
A49: Distance courses were NOT provided TO your campus in 2011-12: | E49: none
A50: Number of | C50: AY 2011-12
C51: Summer 11 | D51: Fall 11 | E51: Winter 12 | F51: Spring 12
A52: Courses Offered | C52: 0 | D52: 0 | E52: na | F52: 0
A53: American Indian Students Enrolled1 | B53: M | C53: 0 | D53: 0 | E53: na | F53: 0
B54: F | C54: 0 | D54: 0 | E54: na | F54: 0
A55: Non-Indian Students Enrolled1 | B55: M | C55: 0 | D55: 0 | E55: na | F55: 0
B56: F | C56: 0 | D56: 0 | E56: na | F56: 0
A57: American Indian Students Passed2 | B57: M | C57: 0 | D57: 0 | E57: na | F57: 0
B58: F | C58: 0 | D58: 0 | E58: na | F58: 0
A59: Non-Indian Students Passed2 | B59: M | C59: 0 | D59: 0 | E59: na | F59: 0
B60: F | C60: 0 | D60: 0 | E60: na | F60: 0
A61: American Indian Students Withdrew | B61: M | C61: 0 | D61: 0 | E61: na | F61: 0
B62: F | C62: 0 | D62: 0 | E62: na | F62: 0
A63: Non-Indian Students Withdrew | B63: M | C63: 0 | D63: 0 | E63: na | F63: 0
B64: F | C64: 0 | D64: 0 | E64: na | F64: 0
A65: 1 Headcount of all students taking Distance Learning Courses through your institution.
A66: 2 Passed with grade 'C' or better.
A67: 3 Each faculty member (both FT and PT) is counted once (no duplicates).
A68: Notes:
A69: We do not have a winter semester; we do not track distance Courses separately.

Sheet 6.1 Student Research
A1: Institution | B1: ='1.1a Overall Instit. Profile'!B1 -> Oglala Lakota College
A2: Indicator 6: Student Activities
A3: Table 6.1: Student Academic Research and Extracurricular Activities / AY 2011-12
A4: Please indicate if any students were involved in the activity. If yes, enter number of students (or m, if number is missing) participating in institution or grant supported activities during the academic year July 1, 2011 - June 30, 2012. If no, enter zero. DO NOT LEAVE SPACES BLANK.
A5: Academic Development Activities
A6: Students who | C6: Number
A7: Attended Orientation | C7: 359
A8: Attended high school Bridge program | C8: 0
A9: Participated in faculty/alumni mentoring program | C9: 3
A10: Participated in service learning program | C10: 57
A11: Participated in First Year Experience program | C11: 22
A12: Received tutoring | C12: 235
A13: Academic Awards
A14: Students who | C14: Number
A15: Received academic award(s) from your college | C15: 3066
A16: Received academic award(s) from outside college | C16: 146
A17: Research, Teaching and Active Learning Activities
A18: Students who | C18: Number
A19: Have been a Research Assistant/Involved in Independent Research | C19: 62
A20: Participated in on-campus research internship | C20: 36
A21: Participated in off-campus research internship (including summer programs) | C21: 36
A22: Participated in an International Learning Experience | C22: 3
A23: Served as a Peer Tutor | C23: 35
A24: Financial Support
A25: Students who | C25: Number
A26: Received financial support (federal, tribal, state, TCU, or A*CF need-based) | C26: 1594
A27: Received merit scholarships | C27: 3071
A28: Received athletic scholarships | C28: 2
A29: Participated in work-study program | C29: 90
A30: Extracurricular Activities
A31: Students who | C31: Number
A32: Presented or competed at a national conference (oral, poster, etc.) | C32: 14
A33: Involved in student government or other leadership program | C33: 6
A34: Participated in student clubs, including chapters of national organizations | C34: 19
A35: Participated in organized athletic programs on campus | C35: 45
A36: Career Development
A37: Students who | C37: Number
A38: Received career advising (including seminars and workshops) | C38: 335
A39: Participated in non-research internship program( term, summer, etc.) | C39: 76
A40: Notes:

Sheet 6.2 Student Comm Act
A1: Institution | C1: ='1.1a Overall Instit. Profile'!B1 -> Oglala Lakota College
A2: Indicator 6: Student Activities
A3: Table 6.2(11): Student Community and Cultural Activities, and Student Services as a Result or Based on College Experience / AY 2011-12
A4: Please indicate if any students were involved in the activity. If yes, enter number of students (or m, if missing) participating in institution or grant supported activities during the academic year July 1, 2011 - June 30, 2012. If no, enter zero. DO NOT LEAVE SPACES BLANK.
A5: Service to the Community
A6: Students who | D6: Number
A7: Participated in organized community service volunteer activities (other than service learning program) | D7: 146
A8: Participated in tribal boards or community organizations | D8: 40
A9: Volunteered to help with community cultural events, including powwows | D9: 214
A10: Participated in culturally relevant activities on campus, other than academic courses | D10: 199
A11: Student Services Offered
A12: Students who received | D12: Number
A13: Daycare services (number of children served) | D13: 9
A14: Housing (on-campus dorms) | D14: 25
A15: Parenting skills classes and workshops | D15: 6
A16: Transportation services (bus, van service, gas cards, etc.) | D16: 298
A17: Financial literacy education programs and workshops | D17: 322
A18: Health/wellness services, including behavioral health counseling | D18: 50
A19: Please list health/wellness services offered (e.g., diabetes screening, suicide prevention counseling, hearing and vision testing, nutrtition counseling, etc.):
A20: CPR/First Aid, ASSIST Training (Suiicide Prevention) Hant Virus, Housing maintenance, Emergency Preparedness, Flu Shots, Immunizations for children and families, use of exercise equipment,wellness lectures, diabetic screening, cancer awareness, physical therapy, stress and wellness, voter registration, absentee ballot, change of address, canning workshops, community clean-up, highway/housing clean-up, animal care.
A21: Notes:

Sheet 6.3 TCU Community Partnerships
A1: Institution | C1: ='1.1a Overall Instit. Profile'!B1 -> Oglala Lakota College
A2: Indicator 6: Student Activities
A3: Table 6.3: TCU Community Partnerships / AY 2011-12
A4: Place a yes or no in each box indicating the TCU’s community partnerships with K-12, tribal, and other entities.
A5: Does the TCU partner with:
A6: Local K-12 system on education reform | D6: yes
A7: Tribe
B8: Economic development planning | D8: yes
B9: Community/social development | D9: yes
A10: IHS or other organizations on health/wellness | D10: yes
A11: Industry/business (including Tribe)
B12: Job training | D12: yes
B13: Economic development opportunities | D13: yes
A14: List top 3 employers on the reservation or in the TCU's service area (if TCU not located on a reservation).
A15: Shannon County schools, Oglala Sioux Tribe, Indian Health Service, Oglala Lakota College, Federal Government,
A16: List services TCU provides to tribe/community (non-academic), e.g., bus service, public housing, etc.
A17: Youth activities, business of art training, communication skills, climage change preparation training, meeting room, training space for community, Native American Research Centers for Health, National Institute for Health Biomedical Research Infrastructure Network, school districts, tribal programs
A18: Notes:

Sheet 7.1 Personnel Demographics
A1: Institution | B1: ='1.1a Overall Instit. Profile'!B1 -> Oglala Lakota College
A2: Indicator 7: Personnel Demographics, Professional Development, Research, and Outcomes
A3: Table 7.1: Personnel Demographics / AY 2011-12
A4: Please note that an individual should only be counted once in the following four tables.
A5: Number of Individuals Who Are Faculty Only | D5: AY 2011-12
B6: American Indian | D6: Non-Indian | F6: Total
B7: M | C7: F | D7: M | E7: F
A8: Full Time Faculty | B8: 14 | C8: 16 | D8: 18 | E8: 21 | F8: =SUM(B8:E8) -> 69
A9: Part Time/Adjunct Faculty | B9: 13 | C9: 31 | D9: 15 | E9: 37 | F9: =SUM(B9:E9) -> 96
A10: Visiting Faculty | B10: 0 | C10: 0 | D10: 0 | E10: 0 | F10: =SUM(B10:E10) -> 0
A11: Total Headcount | B11: =SUM(B8:B10) -> 27 | C11: =SUM(C8:C10) -> 47 | D11: =SUM(D8:D10) -> 33 | E11: =SUM(E8:E10) -> 58 | F11: =SUM(F8:F10) -> 165
A13: Number of Individuals Who Are Administrators Only | D13: AY 2011-12
B14: American Indian | D14: Non-Indian | F14: Total
B15: M | C15: F | D15: M | E15: F
A16: Full Time | B16: 2 | C16: 15 | D16: 1 | E16: 2 | F16: =SUM(B16:E16) -> 20
A17: Part Time | B17: 0 | C17: 0 | D17: 0 | E17: 0 | F17: =SUM(B17:E17) -> 0
A18: Total Headcount | B18: =SUM(B15:B17) -> 2 | C18: =SUM(C15:C17) -> 15 | D18: =SUM(D15:D17) -> 1 | E18: =SUM(E15:E17) -> 2 | F18: =SUM(F15:F17) -> 20
A20: Number of Individuals Who Are Staff Only | D20: AY 2011-12
B21: American Indian | D21: Non-Indian | F21: Total
B22: M | C22: F | D22: M | E22: F
A23: Full Time | B23: 17 | C23: 68 | D23: 4 | E23: 9 | F23: =SUM(B23:E23) -> 98
A24: Part Time | B24: 29 | C24: 27 | D24: 6 | E24: 4 | F24: =SUM(B24:E24) -> 66
A25: Total Headcount | B25: =SUM(B22:B24) -> 46 | C25: =SUM(C22:C24) -> 95 | D25: =SUM(D22:D24) -> 10 | E25: =SUM(E22:E24) -> 13 | F25: =SUM(F22:F24) -> 164
A27: Number of Individuals Who Are Both Faculty and Administrators/Staff | D27: AY 2011-12
B28: American Indian | D28: Non-Indian | F28: Total
B29: M | C29: F | D29: M | E29: F
A30: Full Time | B30: 0 | C30: 0 | D30: 0 | E30: 0 | F30: =SUM(B30:E30) -> 0
A31: Part Time / Adjunct | B31: 0 | C31: 0 | D31: 0 | E31: 0 | F31: =SUM(B31:E31) -> 0
A32: Visiting | B32: 0 | C32: 0 | D32: 0 | E32: 0 | F32: =SUM(B32:E32) -> 0
A33: Total Headcount | B33: =SUM(B30:B32) -> 0 | C33: =SUM(C30:C32) -> 0 | D33: =SUM(D30:D32) -> 0 | E33: =SUM(E30:E32) -> 0 | F33: =SUM(F30:F32) -> 0
A35: We do not have employees that combine three functions.

Sheet 7.2 Fac Prof Demographics
A1: Institution | D1: ='1.1a Overall Instit. Profile'!B1 -> Oglala Lakota College
A2: Indicator 7: Personnel Demographics, Professional Development, Research, and Outcomes
A3: Table 7.2: Faculty, Teaching Staff, and Administrator Professional Demographics / AY 2011-12
A4: Please enter Faculty, Teaching Staff, and Administrator degrees held, salary, and teaching load.
A5: Full Time Faculty - Highest Degree Held | E5: AY 2011-12
C6: American Indian | E6: Non-Indian | G6: Total
C7: M | D7: F | E7: M | F7: F
A8: No Degree - Expert in Field | C8: 3 | D8: 0 | E8: 0 | F8: 0 | G8: =SUM(C8:F8) -> 3
A9: Associate | C9: 1 | D9: 0 | E9: 0 | F9: 0 | G9: =SUM(C9:F9) -> 1
A10: Bachelors | C10: 4 | D10: 3 | E10: 2 | F10: 0 | G10: =SUM(C10:F10) -> 9
A11: Masters | C11: 4 | D11: 11 | E11: 9 | F11: 18 | G11: =SUM(C11:F11) -> 42
A12: Doctorate | C12: 1 | D12: 2 | E12: 6 | F12: 3 | G12: =SUM(C12:F12) -> 12
A13: Other | C13: 1 | D13: 0 | E13: 1 | F13: 0 | G13: =SUM(C13:F13) -> 2
A14: Total | C14: =SUM(C8:C13) -> 14 | D14: =SUM(D8:D13) -> 16 | E14: =SUM(E8:E13) -> 18 | F14: =SUM(F8:F13) -> 21 | G14: =SUM(G8:G13) -> 69
A15: Graduated from a TCU | C15: m | D15: m | E15: m | F15: m | G15: =SUM(C15:F15) -> 0
A17: Part Time Faculty - Highest Degree Held | E17: AY 2011-12
C18: American Indian | E18: Non-Indian | G18: Total
C19: M | D19: F | E19: M | F19: F
A20: No Degree - Expert in Field | C20: 1 | D20: 4 | E20: 0 | F20: 0 | G20: =SUM(C20:F20) -> 5
A21: Associate | C21: 1 | D21: 2 | E21: 0 | F21: 0 | G21: =SUM(C21:F21) -> 3
A22: Bachelors | C22: 10 | D22: 25 | E22: 4 | F22: 5 | G22: =SUM(C22:F22) -> 44
A23: Masters | C23: 9 | D23: 10 | E23: 11 | F23: 16 | G23: =SUM(C23:F23) -> 46
A24: Doctorate | C24: 2 | D24: 4 | E24: 8 | F24: 2 | G24: =SUM(C24:F24) -> 16
A25: Other | C25: 0 | D25: 0 | E25: 0 | F25: 0 | G25: =SUM(C25:F25) -> 0
A26: Total | C26: =SUM(C20:C25) -> 23 | D26: =SUM(D20:D25) -> 45 | E26: =SUM(E20:E25) -> 23 | F26: =SUM(F20:F25) -> 23 | G26: =SUM(G20:G25) -> 114
A27: Graduated from a TCU | C27: m | D27: m | E27: m | F27: m | G27: =SUM(C27:F27) -> 0
A29: Visiting Faculty - Highest Degree Held | E29: AY 2011-12
C30: American Indian | E30: Non-Indian | G30: Total
C31: M | D31: F | E31: M | F31: F
A32: No Degree - Expert in Field | C32: 0 | D32: 0 | E32: 0 | F32: 0 | G32: =SUM(C32:F32) -> 0
