Workbook

Sheet Summary
A1: Community and Technical Colleges, Report of Fundable Operating Expenses, Fiscal Year (FY) 2003
A2: Summary of Expense divided Contact Hours
A3: Contact Hours for fall 2002 and spring and summer 2003
A4: Fund | B4: Total Expense by Discipline | D4: Contact Hours | E4: Expense | F4: Expense per Contact Hour
A5: 1 | B5: Agriculture | D5: =D36 -> 1453684 | E5: =E36+E67+IFERROR($E$105/$D$105*D5,0) -> 11467160 | F5: =F36+F67+$F$105 -> 7.18
A6: 2 | B6: Architecture and Precision Production Trades | D6: =D37 -> 5177312 | E6: =E37+E68+IFERROR($E$105/$D$105*D6,0) -> 39964845 | F6: =F37+F68+$F$105 -> 7.31
A7: 3 | B7: Biology, Physical Sciences, and Science Technology | D7: =D38 -> 24397771 | E7: =E38+E69+IFERROR($E$105/$D$105*D7,0) -> 1.5302773e+08 | F7: =F38+F69+$F$105 -> 5.86
A8: 4 | B8: Business Management, Marketing, and Administrative Services | D8: =D39 -> 17218154 | E8: =E39+E70+IFERROR($E$105/$D$105*D8,0) -> 1.2136754e+08 | F8: =F39+F70+$F$105 -> 6.69
A9: 5 | B9: Career Pilot | D9: =D40 -> 246311 | E9: =E40+E71+IFERROR($E$105/$D$105*D9,0) -> 4756451.7 | F9: =F40+F71+$F$105 -> 13.77
A10: 6 | B10: Communications | D10: =D41 -> 2136055 | E10: =E41+E72+IFERROR($E$105/$D$105*D10,0) -> 19691532 | F10: =F41+F72+$F$105 -> 7.21
A11: 7 | B11: Computer and Information Sciences | D11: =D42 -> 13099478 | E11: =E42+E73+IFERROR($E$105/$D$105*D11,0) -> 1.0402098e+08 | F11: =F42+F73+$F$105 -> 6.94
A12: 8 | B12: Construction Trades | D12: =D43 -> 2308884 | E12: =E43+E74+IFERROR($E$105/$D$105*D12,0) -> 17328739 | F12: =F43+F74+$F$105 -> 7.36
A13: 9 | B13: Consumer and Homemaking Education | D13: =D44 -> 8616348 | E13: =E44+E75+IFERROR($E$105/$D$105*D13,0) -> 52268890 | F13: =F44+F75+$F$105 -> 5.49
A14: 10 | B14: Engineering | D14: =D45 -> 133459 | E14: =E45+E76+IFERROR($E$105/$D$105*D14,0) -> 1669985.7 | F14: =F45+F76+$F$105 -> 8.92
A15: 11 | B15: Engineering Related | D15: =D46 -> 5809798 | E15: =E46+E77+IFERROR($E$105/$D$105*D15,0) -> 47059576 | F15: =F46+F77+$F$105 -> 7.23
A16: 12 | B16: English Language, Lit, Philosophy, Humanities, & Interdisciplinary | D16: =D47 -> 40067445 | E16: =E47+E78+IFERROR($E$105/$D$105*D16,0) -> 2.6192029e+08 | F16: =F47+F78+$F$105 -> 5.83
... A30: 26 | B30: Visual and Performing Arts | D30: =D61 -> 11252211 | E30: =E61+E92+IFERROR($E$105/$D$105*D30,0) -> 90047895 | F30: =F61+F92+$F$105 -> 7.18
A31: 28 | B31: Developmental Education - Math | D31: =D62 -> 0 | E31: =E62+E93+IFERROR($E$105/$D$105*D31,0) -> 0
A32: 29 | B32: Developmental Education - Reading/Writing | D32: =D63 -> 0 | E32: =E63+E94+IFERROR($E$105/$D$105*D32,0) -> 0
B33: Total | D33: =SUM(D5:D32) -> 244475951 | E33: =SUM(E5:E32) -> 1.6735867e+09 | F33: =F64+F95+$F$105 -> 6.37
A35: Fund | B35: Departmental Operating Expense by Discipline | D35: Contact Hours | E35: Expense | F35: Expense per Contact Hour
A36: 1 | B36: Agriculture | D36: =SUM('1:57'!D36) -> 1453684 | E36: =SUM('1:57'!E36) -> 2143915 | F36: =ROUND(MEDIAN('1:57'!F36),2) -> 0.83
A37: 2 | B37: Architecture and Precision Production Trades | D37: =SUM('1:57'!D37) -> 5177312 | E37: =SUM('1:57'!E37) -> 6365960 | F37: =ROUND(MEDIAN('1:57'!F37),2) -> 1.1
A38: 3 | B38: Biology, Physical Sciences, and Science Technology | D38: =SUM('1:57'!D38) -> 24397771 | E38: =SUM('1:57'!E38) -> 15911781 | F38: =ROUND(MEDIAN('1:57'!F38),2) -> 0.42
A39: 4 | B39: Business Management, Marketing, and Administrative Services | D39: =SUM('1:57'!D39) -> 17218154 | E39: =SUM('1:57'!E39) -> 16118594 | F39: =ROUND(MEDIAN('1:57'!F39),2) -> 0.66
A40: 5 | B40: Career Pilot | D40: =SUM('1:57'!D40) -> 246311 | E40: =SUM('1:57'!E40) -> 2344165 | F40: =ROUND(MEDIAN('1:57'!F40),2) -> 3.76
A41: 6 | B41: Communications | D41: =SUM('1:57'!D41) -> 2136055 | E41: =SUM('1:57'!E41) -> 6239768 | F41: =ROUND(MEDIAN('1:57'!F41),2) -> 1.05
A42: 7 | B42: Computer and Information Sciences | D42: =SUM('1:57'!D42) -> 13099478 | E42: =SUM('1:57'!E42) -> 19134340 | F42: =ROUND(MEDIAN('1:57'!F42),2) -> 0.8
A43: 8 | B43: Construction Trades | D43: =SUM('1:57'!D43) -> 2308884 | E43: =SUM('1:57'!E43) -> 3781358 | F43: =ROUND(MEDIAN('1:57'!F43),2) -> 1.04
A44: 9 | B44: Consumer and Homemaking Education | D44: =SUM('1:57'!D44) -> 8616348 | E44: =SUM('1:57'!E44) -> 6592363 | F44: =ROUND(MEDIAN('1:57'!F44),2) -> 0.59
A45: 10 | B45: Engineering | D45: =SUM('1:57'!D45) -> 133459 | E45: =SUM('1:57'!E45) -> 297288 | F45: =ROUND(MEDIAN('1:57'!F45),2) -> 0.98
A46: 11 | B46: Engineering Related | D46: =SUM('1:57'!D46) -> 5809798 | E46: =SUM('1:57'!E46) -> 7856737 | F46: =ROUND(MEDIAN('1:57'!F46),2) -> 0.91
A47: 12 | B47: English Language, Lit, Philosophy, Humanities, & Interdisciplinary | D47: =SUM('1:57'!D47) -> 40067445 | E47: =SUM('1:57'!E47) -> 20882179 | F47: =ROUND(MEDIAN('1:57'!F47),2) -> 0.33
... A61: 26 | B61: Visual and Performing Arts | D61: =SUM('1:57'!D61) -> 11252211 | E61: =SUM('1:57'!E61) -> 11229779 | F61: =ROUND(MEDIAN('1:57'!F61),2) -> 0.84
A62: 28 | B62: Developmental Education - Math | D62: =SUM('1:57'!D62) -> 0 | E62: =SUM('1:57'!E62) -> 0
A63: 29 | B63: Developmental Education - Reading/Writing | D63: =SUM('1:57'!D63) -> 0 | E63: =SUM('1:57'!E63) -> 0
C64: Total | D64: =SUM(D36:D63) -> 244475951 | E64: =SUM(E36:E63) -> 192319415 | F64: =ROUND(MEDIAN('1:57'!F64),2) -> 0.66
A66: Fund | B66: Faculty Salaries by Discipline | D66: Contact Hours | E66: Expense | F66: Expense per Contact Hour
A67: 1 | B67: Agriculture | D67: =D36 -> 1453684 | E67: =SUM('1:57'!E67) -> 4699157 | F67: =ROUND(MEDIAN('1:57'!F67),2) -> 3.41
A68: 2 | B68: Architecture and Precision Production Trades | D68: =D37 -> 5177312 | E68: =SUM('1:57'!E68) -> 17130142 | F68: =ROUND(MEDIAN('1:57'!F68),2) -> 3.27
A69: 3 | B69: Biology, Physical Sciences, and Science Technology | D69: =D38 -> 24397771 | E69: =SUM('1:57'!E69) -> 59507986 | F69: =ROUND(MEDIAN('1:57'!F69),2) -> 2.5
A70: 4 | B70: Business Management, Marketing, and Administrative Services | D70: =D39 -> 17218154 | E70: =SUM('1:57'!E70) -> 50478945 | F70: =ROUND(MEDIAN('1:57'!F70),2) -> 3.09
A71: 5 | B71: Career Pilot | D71: =D40 -> 246311 | E71: =SUM('1:57'!E71) -> 1628785 | F71: =ROUND(MEDIAN('1:57'!F71),2) -> 7.07
A72: 6 | B72: Communications | D72: =D41 -> 2136055 | E72: =SUM('1:57'!E72) -> 6657091 | F72: =ROUND(MEDIAN('1:57'!F72),2) -> 3.22
A73: 7 | B73: Computer and Information Sciences | D73: =D42 -> 13099478 | E73: =SUM('1:57'!E73) -> 43217922 | F73: =ROUND(MEDIAN('1:57'!F73),2) -> 3.2
A74: 8 | B74: Construction Trades | D74: =D43 -> 2308884 | E74: =SUM('1:57'!E74) -> 6202949 | F74: =ROUND(MEDIAN('1:57'!F74),2) -> 3.38
A75: 9 | B75: Consumer and Homemaking Education | D75: =D44 -> 8616348 | E75: =SUM('1:57'!E75) -> 18268400 | F75: =ROUND(MEDIAN('1:57'!F75),2) -> 1.96
A76: 10 | B76: Engineering | D76: =D45 -> 133459 | E76: =SUM('1:57'!E76) -> 948172 | F76: =ROUND(MEDIAN('1:57'!F76),2) -> 5
A77: 11 | B77: Engineering Related | D77: =D46 -> 5809798 | E77: =SUM('1:57'!E77) -> 20722193 | F77: =ROUND(MEDIAN('1:57'!F77),2) -> 3.38
A78: 12 | B78: English Language, Lit, Philosophy, Humanities, & Interdisciplinary | D78: =D47 -> 40067445 | E78: =SUM('1:57'!E78) -> 113585785 | F78: =ROUND(MEDIAN('1:57'!F78),2) -> 2.56
... A92: 26 | B92: Visual and Performing Arts | D92: =D61 -> 11252211 | E92: =SUM('1:57'!E92) -> 43025455 | F92: =ROUND(MEDIAN('1:57'!F92),2) -> 3.4
A93: 28 | B93: Developmental Education - Math | D93: =D62 -> 0 | E93: =SUM('1:57'!E93) -> 0
A94: 29 | B94: Developmental Education - Reading/Writing | D94: =D63 -> 0 | E94: =SUM('1:57'!E94) -> 0
C95: Total | D95: =SUM(D67:D94) -> 244475951 | E95: =SUM(E67:E94) -> 703602770 | F95: =ROUND(MEDIAN('1:57'!F95),2) -> 2.77
B97: Allocated Administrative Expense | D97: Contact Hours | E97: Expense | F97: Expense per Contact Hour
B98: Institutional Support | E98: =SUM('1:57'!E98) -> 343301642 | F98: =ROUND(MEDIAN('1:57'!F98),2) -> 1.42
B99: Student Services | E99: =SUM('1:57'!E99) -> 164343744 | F99: =ROUND(MEDIAN('1:57'!F99),2) -> 0.56
B100: Library | E100: =SUM('1:57'!E100) -> 61680740 | F100: =ROUND(MEDIAN('1:57'!F100),2) -> 0.2
B101: Instructional Administration | E101: =SUM('1:57'!E101) -> 98629611 | F101: =ROUND(MEDIAN('1:57'!F101),2) -> 0.31
B102: Organized Activities | E102: =SUM('1:57'!E102) -> 3121343 | F102: =ROUND(MEDIAN('1:57'!F102),2) -> 0.06
B103: Equipment Depreciation | E103: =SUM('1:57'!E103) -> 1e-05 | F103: =ROUND(MEDIAN('1:57'!F103),2) -> 0
B104: Local Benefits | E104: =SUM('1:57'!E104) -> 106587409 | F104: =ROUND(MEDIAN('1:57'!F104),2) -> 0.39
C105: Total | D105: =D95 -> 244475951 | E105: =SUM(E98:E104) -> 7.7766449e+08 | F105: =SUM(F98:F104) -> 2.94
B107: Annual Financial Report - Schedule B
B108: Unrestricted - Educational Activities | C108: Salaries and Wages | D108: Local Benefits | E108: Other Expenses | F108: Total
B109: Instruction | C109: =SUM('1:57'!C109) -> 703602770 | D109: =SUM('1:57'!D109) -> 0 | E109: =SUM('1:57'!E109) -> 0 | F109: =SUM('1:57'!F109) -> 703602770
B110: Research | C110: =SUM('1:57'!C110) -> 0 | D110: =SUM('1:57'!D110) -> 0 | E110: =SUM('1:57'!E110) -> 0 | F110: =SUM('1:57'!F110) -> 0
B111: Public Service | C111: =SUM('1:57'!C111) -> 0 | D111: =SUM('1:57'!D111) -> 0 | E111: =SUM('1:57'!E111) -> 0 | F111: =SUM('1:57'!F111) -> 0
B112: Academic Support | C112: =SUM('1:57'!C112) -> 0 | D112: =SUM('1:57'!D112) -> 0 | E112: =SUM('1:57'!E112) -> 0 | F112: =SUM('1:57'!F112) -> 0
B113: Student Services | C113: =SUM('1:57'!C113) -> 0 | D113: =SUM('1:57'!D113) -> 0 | E113: =SUM('1:57'!E113) -> 0 | F113: =SUM('1:57'!F113) -> 0
B114: Instructional Support | C114: =SUM('1:57'!C114) -> 0 | D114: =SUM('1:57'!D114) -> 0 | E114: =SUM('1:57'!E114) -> 0 | F114: =SUM('1:57'!F114) -> 0
B115: Operation and Maintenance of Plant | C115: =SUM('1:57'!C115) -> 0 | D115: =SUM('1:57'!D115) -> 0 | E115: =SUM('1:57'!E115) -> 0 | F115: =SUM('1:57'!F115) -> 0
B116: Scholarships and Fellowships | C116: =SUM('1:57'!C116) -> 0 | D116: =SUM('1:57'!D116) -> 0 | E116: =SUM('1:57'!E116) -> 3121343 | F116: =SUM('1:57'!F116) -> 3121343
B117: Other | C117: =SUM('1:57'!C117) -> 0 | D117: =SUM('1:57'!D117) -> 106587409 | E117: =SUM('1:57'!E117) -> 0 | F117: =SUM('1:57'!F117) -> 106587409
B118: Total | C118: =SUM(C109:C116) -> 703602770 | D118: =SUM(D109:D116) -> 0 | E118: =SUM(E109:E116) -> 3121343 | F118: =SUM(F109:F116) -> 706724113
B120: Depreciation Expense - Equipment | C120: =SUM('1:57'!C120) -> 0 | D120: =SUM('1:57'!D120) -> 0 | E120: =SUM('1:57'!E120) -> 1e-05 | F120: =SUM('1:57'!F120) -> 1e-05
A122: Each year, the Texas Higher Education Coordinating Board revises the Texas Public Community and Technical Colleges Expense per Contact Hour Rates used in its Instruction and Operations Formula Funding Recommendation to the Legislative Budget Board (LBB). The Report of Fundable Operating Expenses (RFOE), completed by the institutions, collects departmental operating expense, faculty salaries, institutional support, student services, academic support, research, scholarships and fellowships, equipment depreciation, and local benefits for input into this summary using Annual Financial Report (AFR) Schedule B, which ties to the AFR Statement of Revenues, Expenses and Changes in Net Assets (SRECNA). The RFOE subcategorizes the expenditures collected in Schedule B funded with unrestricted funds, totals them for all institutions, and divides them by the statewide contact hours to determine rates by discipline.

Sheet Rate History
A1: =Summary!A1 -> Community and Technical Colleges, Report of Fundable Operating Expenses, Fiscal Year (FY) 2003
A2: Rate History | I2: Year over Year Change
A3: Fund | B3: Expense per Contact Hour by Discipline | C3: 2003 | D3: 2002 | E3: 2001 | F3: 2000 | G3: 1999 | I3: 2003 | J3: 2002 | K3: 2001 | L3: 2000
A4: 1 | B4: Agriculture | C4: =Summary!F5 -> 7.18 | D4: 7.58 | E4: 7 | F4: 6.67 | G4: 6.81 | I4: =IFERROR(C4/D4-1,"") -> -0.052770449 | J4: =IFERROR(D4/E4-1,"") -> 0.082857143 | K4: =IFERROR(E4/F4-1,"") -> 0.049475262 | L4: =IFERROR(F4/G4-1,"") -> -0.020558003
A5: 2 | B5: Architecture and Precision Production Trades | C5: =Summary!F6 -> 7.31 | D5: 7.27 | E5: 7.56 | F5: 6.83 | G5: 6.64 | I5: =IFERROR(C5/D5-1,"") -> 0.0055020633 | J5: =IFERROR(D5/E5-1,"") -> -0.038359788 | K5: =IFERROR(E5/F5-1,"") -> 0.10688141 | L5: =IFERROR(F5/G5-1,"") -> 0.028614458
A6: 3 | B6: Biology, Physical Sciences, and Science Technology | C6: =Summary!F7 -> 5.86 | D6: 6.04 | E6: 5.9 | F6: 5.69 | G6: 5.51 | I6: =IFERROR(C6/D6-1,"") -> -0.029801325 | J6: =IFERROR(D6/E6-1,"") -> 0.023728814 | K6: =IFERROR(E6/F6-1,"") -> 0.036906854 | L6: =IFERROR(F6/G6-1,"") -> 0.032667877
A7: 4 | B7: Business Management, Marketing, and Administrative Services | C7: =Summary!F8 -> 6.69 | D7: 6.46 | E7: 6.07 | F7: 6.13 | G7: 6.22 | I7: =IFERROR(C7/D7-1,"") -> 0.035603715 | J7: =IFERROR(D7/E7-1,"") -> 0.064250412 | K7: =IFERROR(E7/F7-1,"") -> -0.0097879282 | L7: =IFERROR(F7/G7-1,"") -> -0.014469453
A8: 5 | B8: Career Pilot | C8: =Summary!F9 -> 13.77 | D8: 11.03 | E8: 16.04 | F8: 19.42 | G8: 18.69 | I8: =IFERROR(C8/D8-1,"") -> 0.24841342 | J8: =IFERROR(D8/E8-1,"") -> -0.31234414 | K8: =IFERROR(E8/F8-1,"") -> -0.17404737 | L8: =IFERROR(F8/G8-1,"") -> 0.03905832
A9: 6 | B9: Communications | C9: =Summary!F10 -> 7.21 | D9: 7.26 | E9: 6.99 | F9: 9.21 | G9: 8.21 | I9: =IFERROR(C9/D9-1,"") -> -0.0068870523 | J9: =IFERROR(D9/E9-1,"") -> 0.038626609 | K9: =IFERROR(E9/F9-1,"") -> -0.24104235 | L9: =IFERROR(F9/G9-1,"") -> 0.12180268
A10: 7 | B10: Computer and Information Sciences | C10: =Summary!F11 -> 6.94 | D10: 6.92 | E10: 6.69 | F10: 6.32 | G10: 5.44 | I10: =IFERROR(C10/D10-1,"") -> 0.0028901734 | J10: =IFERROR(D10/E10-1,"") -> 0.034379671 | K10: =IFERROR(E10/F10-1,"") -> 0.058544304 | L10: =IFERROR(F10/G10-1,"") -> 0.16176471
A11: 8 | B11: Construction Trades | C11: =Summary!F12 -> 7.36 | D11: 6.75 | E11: 6.12 | F11: 6.42 | G11: 5.99 | I11: =IFERROR(C11/D11-1,"") -> 0.09037037 | J11: =IFERROR(D11/E11-1,"") -> 0.10294118 | K11: =IFERROR(E11/F11-1,"") -> -0.046728972 | L11: =IFERROR(F11/G11-1,"") -> 0.071786311
A12: 9 | B12: Consumer and Homemaking Education | C12: =Summary!F13 -> 5.49 | D12: 5.51 | E12: 5.52 | F12: 5.14 | G12: 5.35 | I12: =IFERROR(C12/D12-1,"") -> -0.0036297641 | J12: =IFERROR(D12/E12-1,"") -> -0.0018115942 | K12: =IFERROR(E12/F12-1,"") -> 0.073929961 | L12: =IFERROR(F12/G12-1,"") -> -0.039252336
A13: 10 | B13: Engineering | C13: =Summary!F14 -> 8.92 | D13: 8.54 | E13: 11.49 | F13: 9.83 | G13: 7.64 | I13: =IFERROR(C13/D13-1,"") -> 0.044496487 | J13: =IFERROR(D13/E13-1,"") -> -0.256745 | K13: =IFERROR(E13/F13-1,"") -> 0.1688708 | L13: =IFERROR(F13/G13-1,"") -> 0.28664921
A14: 11 | B14: Engineering Related | C14: =Summary!F15 -> 7.23 | D14: 6.89 | E14: 6.58 | F14: 6.71 | G14: 6.42 | I14: =IFERROR(C14/D14-1,"") -> 0.04934688 | J14: =IFERROR(D14/E14-1,"") -> 0.047112462 | K14: =IFERROR(E14/F14-1,"") -> -0.019374069 | L14: =IFERROR(F14/G14-1,"") -> 0.04517134
A15: 12 | B15: English Language, Lit, Philosophy, Humanities, & Interdisciplinary | C15: =Summary!F16 -> 5.83 | D15: 5.94 | E15: 5.75 | F15: 5.68 | G15: 5.26 | I15: =IFERROR(C15/D15-1,"") -> -0.018518519 | J15: =IFERROR(D15/E15-1,"") -> 0.033043478 | K15: =IFERROR(E15/F15-1,"") -> 0.012323944 | L15: =IFERROR(F15/G15-1,"") -> 0.079847909
... A31: 29 | B31: Developmental Education - Reading/Writing | C31: =Summary!F32 -> 0 | D31: 0 | E31: 0 | F31: 0 | G31: 0 | I31: =IFERROR(C31/D31-1,"") | J31: =IFERROR(D31/E31-1,"") | K31: =IFERROR(E31/F31-1,"") | L31: =IFERROR(F31/G31-1,"")
B32: Average | C32: =AVERAGE(C4:C31) -> 6.9428571 | D32: =AVERAGE(D4:D31) -> 7.0071429 | E32: =AVERAGE(E4:E31) -> 7.0107143 | F32: =AVERAGE(F4:F31) -> 7.0171429 | G32: =AVERAGE(G4:G31) -> 6.5617857 | I32: =IFERROR(C32/D32-1,"") -> -0.0091743119 | J32: =IFERROR(D32/E32-1,"") -> -0.00050942435 | K32: =IFERROR(E32/F32-1,"") -> -0.00091612378 | L32: =IFERROR(F32/G32-1,"") -> 0.069395308
B33: Median | C33: =MEDIAN(C4:C31) -> 6.995 | D33: =MEDIAN(D4:D31) -> 6.905 | E33: =MEDIAN(E4:E31) -> 6.69 | F33: =MEDIAN(F4:F31) -> 6.69 | G33: =MEDIAN(G4:G31) -> 6.32 | I33: =IFERROR(C33/D33-1,"") -> 0.013034033 | J33: =IFERROR(D33/E33-1,"") -> 0.032137519 | K33: =IFERROR(E33/F33-1,"") -> 0 | L33: =IFERROR(F33/G33-1,"") -> 0.058544304
B34: Standard Deviation | C34: =STDEV(C4:C31) -> 2.7509808 | D34: =STDEV(D4:D31) -> 2.6772026 | E34: =STDEV(E4:E31) -> 3.0868058 | F34: =STDEV(F4:F31) -> 3.4645516 | G34: =STDEV(G4:G31) -> 3.2525364 | I34: =IFERROR(C34/D34-1,"") -> 0.027557936 | J34: =IFERROR(D34/E34-1,"") -> -0.13269483 | K34: =IFERROR(E34/F34-1,"") -> -0.10903165 | L34: =IFERROR(F34/G34-1,"") -> 0.065184562

Sheet FTSE Summary
A1: =Summary!A1 -> Community and Technical Colleges, Report of Fundable Operating Expenses, Fiscal Year (FY) 2003
A2: Average Total Expenditure per Full-Time Student Equivalent (FTSE)
A3: Institution | B3: Annual State Funded Semester Credit Hours | C3: Total FTSE | D3: Total Expenditure | E3: Average Expenditure per FTSE
A4: Alamo | B4: 937642 | C4: =B4/30 -> 31254.733 | D4: ='1'!$E$33 -> 1.4244558e+08 | E4: =IFERROR(D4/C4,"") -> 4557.5684
A5: Alvin | B5: 99534 | C5: =B5/30 -> 3317.8 | D5: ='2'!$E$33 -> 16388766 | E5: =IFERROR(D5/C5,"") -> 4939.6486
A6: Amarillo | B6: 176266 | C6: =B6/30 -> 5875.5333 | D6: ='3'!$E$33 -> 30374840 | E6: =IFERROR(D6/C6,"") -> 5169.7162
A7: Angelina | B7: 104820 | C7: =B7/30 -> 3494 | D7: ='4'!$E$33 -> 11784710 | E7: =IFERROR(D7/C7,"") -> 3372.842
A8: Austin | B8: 576968 | C8: =B8/30 -> 19232.267 | D8: ='5'!$E$33 -> 90033991 | E8: =IFERROR(D8/C8,"") -> 4681.403
A9: Blinn | B9: 313619 | C9: =B9/30 -> 10453.967 | D9: ='6'!$E$33 -> 31537669 | E9: =IFERROR(D9/C9,"") -> 3016.8136
A10: Brazosport | B10: 69794 | C10: =B10/30 -> 2326.4667 | D10: ='7'!$E$33 -> 11264114 | E10: =IFERROR(D10/C10,"") -> 4841.7259
A11: Central Texas | B11: 233899 | C11: =B11/30 -> 7796.6333 | D11: ='8'!$E$33 -> 28479940 | E11: =IFERROR(D11/C11,"") -> 3652.851
A12: Cisco | B12: 65749 | C12: =B12/30 -> 2191.6333 | D12: ='9'!$E$33 -> 5709200 | E12: =IFERROR(D12/C12,"") -> 2604.9978
A13: Clarendon | B13: 20192 | C13: =B13/30 -> 673.06667 | D13: ='10'!$E$33 -> 2960451 | E13: =IFERROR(D13/C13,"") -> 4398.4514
A14: Coastal Bend | B14: 77831 | C14: =B14/30 -> 2594.3667 | D14: ='11'!$E$33 -> 10871274 | E14: =IFERROR(D14/C14,"") -> 4190.3383
A15: College Of The Mainland | B15: 77885 | C15: =B15/30 -> 2596.1667 | D15: ='12'!$E$33 -> 16899288 | E15: =IFERROR(D15/C15,"") -> 6509.3232
A16: Collin | B16: 319356 | C16: =B16/30 -> 10645.2 | D16: ='13'!$E$33 -> 44821329 | E16: =IFERROR(D16/C16,"") -> 4210.4732
A17: Dallas | B17: 1127974 | C17: =B17/30 -> 37599.133 | D17: ='14'!$E$33 -> 1.8229215e+08 | E17: =IFERROR(D17/C17,"") -> 4848.3071
A18: Del Mar | B18: 222402 | C18: =B18/30 -> 7413.4 | D18: ='15'!$E$33 -> 45788300 | E18: =IFERROR(D18/C18,"") -> 6176.4238
A19: El Paso | B19: 422079 | C19: =B19/30 -> 14069.3 | D19: ='16'!$E$33 -> 62585427 | E19: =IFERROR(D19/C19,"") -> 4448.3682
A20: Frank Phillips | B20: 26266 | C20: =B20/30 -> 875.53333 | D20: ='17'!$E$33 -> 4835883 | E20: =IFERROR(D20/C20,"") -> 5523.3568
A21: Galveston | B21: 42732 | C21: =B21/30 -> 1424.4 | D21: ='18'!$E$33 -> 9697114 | E21: =IFERROR(D21/C21,"") -> 6807.8587
A22: Grayson | B22: 79353 | C22: =B22/30 -> 2645.1 | D22: ='19'!$E$33 -> 9836812 | E22: =IFERROR(D22/C22,"") -> 3718.8809
A23: Hill | B23: 64451 | C23: =B23/30 -> 2148.3667 | D23: ='20'!$E$33 -> 7715563 | E23: =IFERROR(D23/C23,"") -> 3591.3623
A24: Houston | B24: 777341 | C24: =B24/30 -> 25911.367 | D24: ='21'!$E$33 -> 1.5008447e+08 | E24: =IFERROR(D24/C24,"") -> 5792.2252
A25: Howard | B25: 56174 | C25: =B25/30 -> 1872.4667 | D25: ='22'!$E$33 -> 13649317 | E25: =IFERROR(D25/C25,"") -> 7289.4846
A26: Kilgore | B26: 108677 | C26: =B26/30 -> 3622.5667 | D26: ='23'!$E$33 -> 16036109 | E26: =IFERROR(D26/C26,"") -> 4426.7257
A27: Laredo | B27: 158108 | C27: =B27/30 -> 5270.2667 | D27: ='24'!$E$33 -> 24781083 | E27: =IFERROR(D27/C27,"") -> 4702.0549
A28: Lee | B28: 129653 | C28: =B28/30 -> 4321.7667 | D28: ='25'!$E$33 -> 22440330 | E28: =IFERROR(D28/C28,"") -> 5192.3974
A29: Lonestar | B29: 625611 | C29: =B29/30 -> 20853.7 | D29: ='26'!$E$33 -> 95199422 | E29: =IFERROR(D29/C29,"") -> 4565.1094
A30: Mclennan | B30: 153965 | C30: =B30/30 -> 5132.1667 | D30: ='27'!$E$33 -> 21526573 | E30: =IFERROR(D30/C30,"") -> 4194.4415
A31: Midland | B31: 104040 | C31: =B31/30 -> 3468 | D31: ='28'!$E$33 -> 18714675 | E31: =IFERROR(D31/C31,"") -> 5396.3884
A32: Navarro | B32: 121632 | C32: =B32/30 -> 4054.4 | D32: ='29'!$E$33 -> 13432088 | E32: =IFERROR(D32/C32,"") -> 3312.9657
A33: North Central Texas | B33: 122817 | C33: =B33/30 -> 4093.9 | D33: ='30'!$E$33 -> 10944802 | E33: =IFERROR(D33/C33,"") -> 2673.4415
A34: Northeast Texas | B34: 54488 | C34: =B34/30 -> 1816.2667 | D34: ='31'!$E$33 -> 7044285 | E34: =IFERROR(D34/C34,"") -> 3878.442
A35: Odessa | B35: 101046 | C35: =B35/30 -> 3368.2 | D35: ='32'!$E$33 -> 15638498 | E35: =IFERROR(D35/C35,"") -> 4642.9838
A36: Panola | B36: 40517 | C36: =B36/30 -> 1350.5667 | D36: ='33'!$E$33 -> 7648703 | E36: =IFERROR(D36/C36,"") -> 5663.3287
A37: Paris | B37: 80121 | C37: =B37/30 -> 2670.7 | D37: ='34'!$E$33 -> 13377921 | E37: =IFERROR(D37/C37,"") -> 5009.144
A38: Ranger | B38: 20490 | C38: =B38/30 -> 683 | D38: ='35'!$E$33 -> 2698348 | E38: =IFERROR(D38/C38,"") -> 3950.7291
A39: San Jacinto | B39: 456117 | C39: =B39/30 -> 15203.9 | D39: ='36'!$E$33 -> 68488942 | E39: =IFERROR(D39/C39,"") -> 4504.6956
A40: South Plains | B40: 192571 | C40: =B40/30 -> 6419.0333 | D40: ='37'!$E$33 -> 23387310 | E40: =IFERROR(D40/C40,"") -> 3643.4318
A41: South Texas | B41: 303465 | C41: =B41/30 -> 10115.5 | D41: ='38'!$E$33 -> 42436095 | E41: =IFERROR(D41/C41,"") -> 4195.1555
A42: Southwest Texas | B42: 88349 | C42: =B42/30 -> 2944.9667 | D42: ='39'!$E$33 -> 12560512 | E42: =IFERROR(D42/C42,"") -> 4265.0778
A43: Tarrant | B43: 637769 | C43: =B43/30 -> 21258.967 | D43: ='40'!$E$33 -> 88881670 | E43: =IFERROR(D43/C43,"") -> 4180.9026
A44: Temple | B44: 72844 | C44: =B44/30 -> 2428.1333 | D44: ='41'!$E$33 -> 11505858 | E44: =IFERROR(D44/C44,"") -> 4738.561
A45: Texarkana | B45: 78825 | C45: =B45/30 -> 2627.5 | D45: ='42'!$E$33 -> 13071569 | E45: =IFERROR(D45/C45,"") -> 4974.9073
A46: Texas Southmost | B46: 165724 | C46: =B46/30 -> 5524.1333 | D46: ='43'!$E$33 -> 26810377 | E46: =IFERROR(D46/C46,"") -> 4853.3182
A47: Trinity Valley | B47: 129129 | C47: =B47/30 -> 4304.3 | D47: ='44'!$E$33 -> 14988810 | E47: =IFERROR(D47/C47,"") -> 3482.2875
A48: Tyler | B48: 208883 | C48: =B48/30 -> 6962.7667 | D48: ='45'!$E$33 -> 26888895 | E48: =IFERROR(D48/C48,"") -> 3861.8119
A49: Vernon | B49: 59075 | C49: =B49/30 -> 1969.1667 | D49: ='46'!$E$33 -> 7831299 | E49: =IFERROR(D49/C49,"") -> 3976.961
A50: Victoria | B50: 78595 | C50: =B50/30 -> 2619.8333 | D50: ='47'!$E$33 -> 12605215 | E50: =IFERROR(D50/C50,"") -> 4811.4568
A51: Weatherford | B51: 79421 | C51: =B51/30 -> 2647.3667 | D51: ='48'!$E$33 -> 11934437 | E51: =IFERROR(D51/C51,"") -> 4508.0408
A52: Western Texas | B52: 30712 | C52: =B52/30 -> 1023.7333 | D52: ='49'!$E$33 -> 5189446 | E52: =IFERROR(D52/C52,"") -> 5069.1384
A53: Wharton | B53: 124368 | C53: =B53/30 -> 4145.6 | D53: ='50'!$E$33 -> 18066033 | E53: =IFERROR(D53/C53,"") -> 4357.8814
A54: TSTC-Harlingen | B54: 105916 | C54: =B54/30 -> 3530.5333 | D54: ='51'!$E$33 -> 18130551 | E54: =IFERROR(D54/C54,"") -> 5135.3575
A55: TSTC-West Texas | B55: 51489 | C55: =B55/30 -> 1716.3 | D55: ='52'!$E$33 -> 11967327 | E55: =IFERROR(D55/C55,"") -> 6972.7478
A56: TSTC-Marshall | B56: 18238 | C56: =B56/30 -> 607.93333 | D56: ='53'!$E$33 -> 4718585 | E56: =IFERROR(D56/C56,"") -> 7761.6817
A57: TSTC-Waco | B57: 129620 | C57: =B57/30 -> 4320.6667 | D57: ='54'!$E$33 -> 27711036 | E57: =IFERROR(D57/C57,"") -> 6413.6019
A58: Lamar-IOT | B58: 53096 | C58: =B58/30 -> 1769.8667 | D58: ='55'!$E$33 -> 10192869 | E58: =IFERROR(D58/C58,"") -> 5759.1169
A59: Lamar-Orange | B59: 36360 | C59: =B59/30 -> 1212 | D59: ='56'!$E$33 -> 5876647 | E59: =IFERROR(D59/C59,"") -> 4848.7186
A60: Lamar-Port Arthur | B60: 52637 | C60: =B60/30 -> 1754.5667 | D60: ='57'!$E$33 -> 10804164 | E60: =IFERROR(D60/C60,"") -> 6157.7392
A61: Total for Instutions Reporting Expense | B61: =SUMIF(D4:D60,">0",B4:B60) -> 10866695 | C61: =B61/30 -> 362223.17 | D61: =SUM(D4:D60) -> 1.6735867e+09 | E61: =IFERROR(D61/C61,"") -> 4620.3193

Sheet Discipline Summary
A1: =Summary!A1 -> Community and Technical Colleges, Report of Fundable Operating Expenses, Fiscal Year (FY) 2003
A2: Discipline Summary of Expense per Contact Hour by Institution
A3: Institution | B3: AG | C3: ARCH | D3: SCI | E3: BA | F3: CP | G3: COMM | H3: CS | I3: CNSTR | J3: HE | K3: ENG | L3: ENGR | M3: LA | N3: FL | O3: HODA | P3: HODH | Q3: HOO | R3: HORT | S3: NUR | T3: MATH | U3: AUTO | V3: MECH | W3: ELECT | X3: PE | Y3: PA | Z3: SS | AA3: FA | AB3: DEM | AC3: DER | AD3: Total
A4: Alamo | B4: ='1'!$F$5 -> 5.78 | C4: ='1'!$F$6 -> 7.22 | D4: ='1'!$F$7 -> 7.47 | E4: ='1'!$F$8 -> 8.53 | F4: ='1'!$F$9 -> 14.18 | G4: ='1'!$F$10 -> 8.26 | H4: ='1'!$F$11 -> 8.58 | I4: ='1'!$F$12 -> 8.13 | J4: ='1'!$F$13 -> 7.65 | K4: ='1'!$F$14 -> 19.93 | L4: ='1'!$F$15 -> 14.68 | M4: ='1'!$F$16 -> 6.65 | N4: ='1'!$F$17 -> 7.91 | O4: ='1'!$F$18 -> 12.13 | P4: ='1'!$F$19 | Q4: ='1'!$F$20 -> 7.39 | R4: ='1'!$F$21 -> 15.14 | S4: ='1'!$F$22 -> 8.41 | T4: ='1'!$F$23 -> 6.76 | U4: ='1'!$F$24 -> 4.82 | V4: ='1'!$F$25 -> 11.88 | W4: ='1'!$F$26 -> 3.87 | X4: ='1'!$F$27 -> 8.27 | Y4: ='1'!$F$28 -> 6.52 | Z4: ='1'!$F$29 -> 6.81 | AA4: ='1'!$F$30 -> 9.46 | AB4: ='1'!$F$31 | AC4: ='1'!$F$32 | AD4: ='1'!$F$33 -> 7.55
A5: Alvin | B5: ='2'!$F$5 -> 5.26 | C5: ='2'!$F$6 -> 7.07 | D5: ='2'!$F$7 -> 6.59 | E5: ='2'!$F$8 -> 7.42 | F5: ='2'!$F$9 | G5: ='2'!$F$10 -> 6.5 | H5: ='2'!$F$11 -> 6.37 | I5: ='2'!$F$12 | J5: ='2'!$F$13 -> 6.81 | K5: ='2'!$F$14 | L5: ='2'!$F$15 -> 5.45 | M5: ='2'!$F$16 -> 6.96 | N5: ='2'!$F$17 -> 7.63 | O5: ='2'!$F$18 -> 10.25 | P5: ='2'!$F$19 | Q5: ='2'!$F$20 -> 7.11 | R5: ='2'!$F$21 -> 11.59 | S5: ='2'!$F$22 -> 6.63 | T5: ='2'!$F$23 -> 5.84 | U5: ='2'!$F$24 -> 5.14 | V5: ='2'!$F$25 | W5: ='2'!$F$26 | X5: ='2'!$F$27 -> 7.76 | Y5: ='2'!$F$28 -> 6.05 | Z5: ='2'!$F$29 -> 6.2 | AA5: ='2'!$F$30 -> 8.54 | AB5: ='2'!$F$31 | AC5: ='2'!$F$32 | AD5: ='2'!$F$33 -> 6.84
A6: Amarillo | B6: ='3'!$F$5 -> 6.42 | C6: ='3'!$F$6 -> 6.96 | D6: ='3'!$F$7 -> 6.14 | E6: ='3'!$F$8 -> 6.8 | F6: ='3'!$F$9 | G6: ='3'!$F$10 -> 6.89 | H6: ='3'!$F$11 -> 6.67 | I6: ='3'!$F$12 -> 7.23 | J6: ='3'!$F$13 -> 5.74 | K6: ='3'!$F$14 -> 6.12 | L6: ='3'!$F$15 -> 6.71 | M6: ='3'!$F$16 -> 6.99 | N6: ='3'!$F$17 -> 7.09 | O6: ='3'!$F$18 -> 7.46 | P6: ='3'!$F$19 -> 7.68 | Q6: ='3'!$F$20 -> 7.6 | R6: ='3'!$F$21 -> 7.65 | S6: ='3'!$F$22 -> 7.3 | T6: ='3'!$F$23 -> 6.18 | U6: ='3'!$F$24 -> 6.97 | V6: ='3'!$F$25 -> 6.97 | W6: ='3'!$F$26 -> 6.83 | X6: ='3'!$F$27 -> 5.26 | Y6: ='3'!$F$28 -> 7.66 | Z6: ='3'!$F$29 -> 5.42 | AA6: ='3'!$F$30 -> 6.91 | AB6: ='3'!$F$31 | AC6: ='3'!$F$32 | AD6: ='3'!$F$33 -> 6.66
A7: Angelina | B7: ='4'!$F$5 -> 3.38 | C7: ='4'!$F$6 -> 7.02 | D7: ='4'!$F$7 -> 4.35 | E7: ='4'!$F$8 -> 5.31 | F7: ='4'!$F$9 | G7: ='4'!$F$10 -> 5.78 | H7: ='4'!$F$11 -> 7.82 | I7: ='4'!$F$12 -> 7.69 | J7: ='4'!$F$13 -> 5.14 | K7: ='4'!$F$14 -> 8.19 | L7: ='4'!$F$15 -> 7.69 | M7: ='4'!$F$16 -> 4.13 | N7: ='4'!$F$17 -> 4.62 | O7: ='4'!$F$18 -> 6.6 | P7: ='4'!$F$19 | Q7: ='4'!$F$20 -> 5.07 | R7: ='4'!$F$21 -> 8.48 | S7: ='4'!$F$22 -> 3.52 | T7: ='4'!$F$23 -> 4.19 | U7: ='4'!$F$24 -> 8.76 | V7: ='4'!$F$25 -> 6.76 | W7: ='4'!$F$26 -> 5.95 | X7: ='4'!$F$27 -> 5.88 | Y7: ='4'!$F$28 -> 3.95 | Z7: ='4'!$F$29 -> 3.74 | AA7: ='4'!$F$30 -> 5.47 | AB7: ='4'!$F$31 | AC7: ='4'!$F$32 | AD7: ='4'!$F$33 -> 4.82
A8: Austin | B8: ='5'!$F$5 -> 8.27 | C8: ='5'!$F$6 -> 11.07 | D8: ='5'!$F$7 -> 7.78 | E8: ='5'!$F$8 -> 9.09 | F8: ='5'!$F$9 | G8: ='5'!$F$10 -> 9.26 | H8: ='5'!$F$11 -> 8.62 | I8: ='5'!$F$12 -> 10.8 | J8: ='5'!$F$13 -> 9.02 | K8: ='5'!$F$14 -> 17.7 | L8: ='5'!$F$15 -> 12.5 | M8: ='5'!$F$16 -> 7.42 | N8: ='5'!$F$17 -> 6.71 | O8: ='5'!$F$18 -> 12.9 | P8: ='5'!$F$19 | Q8: ='5'!$F$20 -> 10.04 | R8: ='5'!$F$21 | S8: ='5'!$F$22 -> 12.16 | T8: ='5'!$F$23 -> 6.77 | U8: ='5'!$F$24 -> 10.51 | V8: ='5'!$F$25 -> 8.59 | W8: ='5'!$F$26 -> 9.11 | X8: ='5'!$F$27 -> 7.68 | Y8: ='5'!$F$28 -> 8.55 | Z8: ='5'!$F$29 -> 6.1 | AA8: ='5'!$F$30 -> 9.01 | AB8: ='5'!$F$31 | AC8: ='5'!$F$32 | AD8: ='5'!$F$33 -> 7.85
A9: Blinn | B9: ='6'!$F$5 -> 6.72 | C9: ='6'!$F$6 -> 22.29 | D9: ='6'!$F$7 -> 4.21 | E9: ='6'!$F$8 -> 6.61 | F9: ='6'!$F$9 | G9: ='6'!$F$10 -> 4.82 | H9: ='6'!$F$11 -> 8.16 | I9: ='6'!$F$12 -> 20.08 | J9: ='6'!$F$13 -> 3.37 | K9: ='6'!$F$14 | L9: ='6'!$F$15 -> 23.56 | M9: ='6'!$F$16 -> 5.78 | N9: ='6'!$F$17 -> 4.71 | O9: ='6'!$F$18 -> 9.13 | P9: ='6'!$F$19 -> 18.38 | Q9: ='6'!$F$20 -> 4.21 | R9: ='6'!$F$21 | S9: ='6'!$F$22 -> 6.76 | T9: ='6'!$F$23 -> 5.26 | U9: ='6'!$F$24 -> 21.21 | V9: ='6'!$F$25 | W9: ='6'!$F$26 | X9: ='6'!$F$27 -> 5.94 | Y9: ='6'!$F$28 -> 3.72 | Z9: ='6'!$F$29 -> 4.38 | AA9: ='6'!$F$30 -> 6.42 | AB9: ='6'!$F$31 | AC9: ='6'!$F$32 | AD9: ='6'!$F$33 -> 5.19
A10: Brazosport | B10: ='7'!$F$5 | C10: ='7'!$F$6 -> 6.78 | D10: ='7'!$F$7 -> 6.91 | E10: ='7'!$F$8 -> 8.5 | F10: ='7'!$F$9 | G10: ='7'!$F$10 -> 6.13 | H10: ='7'!$F$11 -> 8.02 | I10: ='7'!$F$12 -> 7.2 | J10: ='7'!$F$13 -> 5.39 | K10: ='7'!$F$14 | L10: ='7'!$F$15 -> 5.75 | M10: ='7'!$F$16 -> 6.49 | N10: ='7'!$F$17 -> 12.28 | O10: ='7'!$F$18 | P10: ='7'!$F$19 | Q10: ='7'!$F$20 -> 9.37 | R10: ='7'!$F$21 | S10: ='7'!$F$22 -> 7.98 | T10: ='7'!$F$23 -> 6.04 | U10: ='7'!$F$24 -> 10.09 | V10: ='7'!$F$25 -> 9.61 | W10: ='7'!$F$26 | X10: ='7'!$F$27 -> 7.85 | Y10: ='7'!$F$28 -> 6 | Z10: ='7'!$F$29 -> 6.6 | AA10: ='7'!$F$30 -> 9.1 | AB10: ='7'!$F$31 | AC10: ='7'!$F$32 | AD10: ='7'!$F$33 -> 7.01
A11: Central Texas | B11: ='8'!$F$5 -> 5.18 | C11: ='8'!$F$6 -> 6.53 | D11: ='8'!$F$7 -> 6.01 | E11: ='8'!$F$8 -> 6.01 | F11: ='8'!$F$9 -> 30.96 | G11: ='8'!$F$10 -> 4.41 | H11: ='8'!$F$11 -> 4.13 | I11: ='8'!$F$12 -> 4.64 | J11: ='8'!$F$13 -> 4.39 | K11: ='8'!$F$14 | L11: ='8'!$F$15 -> 4.7 | M11: ='8'!$F$16 -> 4.93 | N11: ='8'!$F$17 -> 4.83 | O11: ='8'!$F$18 -> 8.64 | P11: ='8'!$F$19 | Q11: ='8'!$F$20 -> 8.24 | R11: ='8'!$F$21 | S11: ='8'!$F$22 -> 7.24 | T11: ='8'!$F$23 -> 4.45 | U11: ='8'!$F$24 -> 6.91 | V11: ='8'!$F$25 -> 6.16 | W11: ='8'!$F$26 -> 4.88 | X11: ='8'!$F$27 -> 6.26 | Y11: ='8'!$F$28 -> 4.28 | Z11: ='8'!$F$29 -> 4.08 | AA11: ='8'!$F$30 -> 5.37 | AB11: ='8'!$F$31 | AC11: ='8'!$F$32 | AD11: ='8'!$F$33 -> 5.26
A12: Cisco | B12: ='9'!$F$5 -> 8.86 | C12: ='9'!$F$6 -> 5.36 | D12: ='9'!$F$7 -> 3.28 | E12: ='9'!$F$8 -> 3.54 | F12: ='9'!$F$9 | G12: ='9'!$F$10 | H12: ='9'!$F$11 -> 4.64 | I12: ='9'!$F$12 -> 5.39 | J12: ='9'!$F$13 -> 3.4 | K12: ='9'!$F$14 | L12: ='9'!$F$15 -> 5.36 | M12: ='9'!$F$16 -> 3.67 | N12: ='9'!$F$17 -> 5.74 | O12: ='9'!$F$18 -> 6.5 | P12: ='9'!$F$19 | Q12: ='9'!$F$20 -> 3.61 | R12: ='9'!$F$21 | S12: ='9'!$F$22 -> 4.16 | T12: ='9'!$F$23 -> 3.82 | U12: ='9'!$F$24 -> 4.77 | V12: ='9'!$F$25 -> 2.71 | W12: ='9'!$F$26 -> 44.81 | X12: ='9'!$F$27 -> 9.42 | Y12: ='9'!$F$28 -> 7.02 | Z12: ='9'!$F$29 -> 3.17 | AA12: ='9'!$F$30 -> 7 | AB12: ='9'!$F$31 | AC12: ='9'!$F$32 | AD12: ='9'!$F$33 -> 4.2
A13: Clarendon | B13: ='10'!$F$5 -> 10.33 | C13: ='10'!$F$6 -> 6.47 | D13: ='10'!$F$7 -> 5.25 | E13: ='10'!$F$8 -> 8.79 | F13: ='10'!$F$9 | G13: ='10'!$F$10 -> 6.33 | H13: ='10'!$F$11 -> 7.75 | I13: ='10'!$F$12 | J13: ='10'!$F$13 -> 3.82 | K13: ='10'!$F$14 | L13: ='10'!$F$15 -> 6.48 | M13: ='10'!$F$16 -> 6.1 | N13: ='10'!$F$17 -> 4.32 | O13: ='10'!$F$18 | P13: ='10'!$F$19 | Q13: ='10'!$F$20 -> 3.97 | R13: ='10'!$F$21 | S13: ='10'!$F$22 -> 6.48 | T13: ='10'!$F$23 -> 4.63 | U13: ='10'!$F$24 | V13: ='10'!$F$25 | W13: ='10'!$F$26 | X13: ='10'!$F$27 -> 11.65 | Y13: ='10'!$F$28 -> 6.02 | Z13: ='10'!$F$29 -> 5.7 | AA13: ='10'!$F$30 -> 6.97 | AB13: ='10'!$F$31 | AC13: ='10'!$F$32 | AD13: ='10'!$F$33 -> 6.54
A14: Coastal Bend | B14: ='11'!$F$5 -> 3.06 | C14: ='11'!$F$6 -> 4.95 | D14: ='11'!$F$7 -> 5.14 | E14: ='11'!$F$8 -> 6.66 | F14: ='11'!$F$9 | G14: ='11'!$F$10 -> 4.63 | H14: ='11'!$F$11 -> 4.63 | I14: ='11'!$F$12 -> 4.91 | J14: ='11'!$F$13 -> 5.01 | K14: ='11'!$F$14 | L14: ='11'!$F$15 -> 3.82 | M14: ='11'!$F$16 -> 4.86 | N14: ='11'!$F$17 -> 5.41 | O14: ='11'!$F$18 -> 4.41 | P14: ='11'!$F$19 -> 10.18 | Q14: ='11'!$F$20 -> 3.91 | R14: ='11'!$F$21 | S14: ='11'!$F$22 -> 4.49 | T14: ='11'!$F$23 -> 4.25 | U14: ='11'!$F$24 -> 5.64 | V14: ='11'!$F$25 -> 21.61 | W14: ='11'!$F$26 -> 5.05 | X14: ='11'!$F$27 -> 4.9 | Y14: ='11'!$F$28 -> 7.44 | Z14: ='11'!$F$29 -> 4.61 | AA14: ='11'!$F$30 -> 6.94 | AB14: ='11'!$F$31 | AC14: ='11'!$F$32 | AD14: ='11'!$F$33 -> 5.02
A15: College Of The Mainland | B15: ='12'!$F$5 -> 12.62 | C15: ='12'!$F$6 -> 22.57 | D15: ='12'!$F$7 -> 7.95 | E15: ='12'!$F$8 -> 10.84 | F15: ='12'!$F$9 | G15: ='12'!$F$10 -> 58.86 | H15: ='12'!$F$11 -> 15.65 | I15: ='12'!$F$12 -> 9.81 | J15: ='12'!$F$13 -> 11.42 | K15: ='12'!$F$14 | L15: ='12'!$F$15 -> 10.1 | M15: ='12'!$F$16 -> 8.38 | N15: ='12'!$F$17 -> 8.21 | O15: ='12'!$F$18 -> 33.22 | P15: ='12'!$F$19 | Q15: ='12'!$F$20 -> 9.12 | R15: ='12'!$F$21 | S15: ='12'!$F$22 | T15: ='12'!$F$23 -> 7.89 | U15: ='12'!$F$24 | V15: ='12'!$F$25 -> 22.93 | W15: ='12'!$F$26 | X15: ='12'!$F$27 -> 10.67 | Y15: ='12'!$F$28 -> 8.07 | Z15: ='12'!$F$29 -> 8.56 | AA15: ='12'!$F$30 -> 12.22 | AB15: ='12'!$F$31 | AC15: ='12'!$F$32 | AD15: ='12'!$F$33 -> 10.12
A16: Collin | B16: ='13'!$F$5 -> 5.74 | C16: ='13'!$F$6 -> 9.98 | D16: ='13'!$F$7 -> 5.96 | E16: ='13'!$F$8 -> 7.4 | F16: ='13'!$F$9 -> 7.87 | G16: ='13'!$F$10 -> 7.36 | H16: ='13'!$F$11 -> 5.89 | I16: ='13'!$F$12 -> 7.87 | J16: ='13'!$F$13 -> 6.1 | K16: ='13'!$F$14 | L16: ='13'!$F$15 -> 12 | M16: ='13'!$F$16 -> 6.01 | N16: ='13'!$F$17 -> 6.79 | O16: ='13'!$F$18 -> 9.23 | P16: ='13'!$F$19 -> 19.95 | Q16: ='13'!$F$20 -> 6.62 | R16: ='13'!$F$21 -> 9.33 | S16: ='13'!$F$22 | T16: ='13'!$F$23 -> 5.11 | U16: ='13'!$F$24 | V16: ='13'!$F$25 | W16: ='13'!$F$26 -> 6.28 | X16: ='13'!$F$27 -> 7.42 | Y16: ='13'!$F$28 -> 8.24 | Z16: ='13'!$F$29 -> 5.18 | AA16: ='13'!$F$30 -> 8.28 | AB16: ='13'!$F$31 | AC16: ='13'!$F$32 | AD16: ='13'!$F$33 -> 6.37
A17: Dallas | B17: ='14'!$F$5 -> 15.4 | C17: ='14'!$F$6 -> 5.44 | D17: ='14'!$F$7 -> 6.4 | E17: ='14'!$F$8 -> 7.39 | F17: ='14'!$F$9 -> 9.74 | G17: ='14'!$F$10 -> 11.86 | H17: ='14'!$F$11 -> 8.52 | I17: ='14'!$F$12 -> 13.7 | J17: ='14'!$F$13 -> 5.45 | K17: ='14'!$F$14 -> 5.71 | L17: ='14'!$F$15 -> 5.57 | M17: ='14'!$F$16 -> 6.93 | N17: ='14'!$F$17 -> 6.81 | O17: ='14'!$F$18 -> 10.96 | P17: ='14'!$F$19 | Q17: ='14'!$F$20 -> 6.97 | R17: ='14'!$F$21 -> 31.43 | S17: ='14'!$F$22 -> 11.37 | T17: ='14'!$F$23 -> 6.01 | U17: ='14'!$F$24 -> 8.94 | V17: ='14'!$F$25 -> 5.29 | W17: ='14'!$F$26 -> 32.09 | X17: ='14'!$F$27 -> 8.1 | Y17: ='14'!$F$28 -> 5.78 | Z17: ='14'!$F$29 -> 5.88 | AA17: ='14'!$F$30 -> 8.54 | AB17: ='14'!$F$31 | AC17: ='14'!$F$32 | AD17: ='14'!$F$33 -> 7.02
A18: Del Mar | B18: ='15'!$F$5 | C18: ='15'!$F$6 -> 6.93 | D18: ='15'!$F$7 -> 7.47 | E18: ='15'!$F$8 -> 8.74 | F18: ='15'!$F$9 | G18: ='15'!$F$10 -> 8.17 | H18: ='15'!$F$11 -> 7.88 | I18: ='15'!$F$12 -> 6.26 | J18: ='15'!$F$13 -> 7.58 | K18: ='15'!$F$14 -> 7.54 | L18: ='15'!$F$15 -> 8.1 | M18: ='15'!$F$16 -> 9.02 | N18: ='15'!$F$17 -> 7.59 | O18: ='15'!$F$18 -> 9.65 | P18: ='15'!$F$19 -> 14.19 | Q18: ='15'!$F$20 -> 7.98 | R18: ='15'!$F$21 -> 13.29 | S18: ='15'!$F$22 -> 9.44 | T18: ='15'!$F$23 -> 7.74 | U18: ='15'!$F$24 -> 8.32 | V18: ='15'!$F$25 -> 7.99 | W18: ='15'!$F$26 -> 8.56 | X18: ='15'!$F$27 -> 8.09 | Y18: ='15'!$F$28 -> 7.02 | Z18: ='15'!$F$29 -> 7.58 | AA18: ='15'!$F$30 -> 11.76 | AB18: ='15'!$F$31 | AC18: ='15'!$F$32 | AD18: ='15'!$F$33 -> 8.31
A19: El Paso | B19: ='16'!$F$5 | C19: ='16'!$F$6 -> 19.8 | D19: ='16'!$F$7 -> 6.16 | E19: ='16'!$F$8 -> 6.58 | F19: ='16'!$F$9 | G19: ='16'!$F$10 -> 19.34 | H19: ='16'!$F$11 -> 8.26 | I19: ='16'!$F$12 | J19: ='16'!$F$13 -> 4.61 | K19: ='16'!$F$14 | L19: ='16'!$F$15 | M19: ='16'!$F$16 -> 7.09 | N19: ='16'!$F$17 -> 8.78 | O19: ='16'!$F$18 -> 14.18 | P19: ='16'!$F$19 -> 14.19 | Q19: ='16'!$F$20 -> 9.84 | R19: ='16'!$F$21 | S19: ='16'!$F$22 | T19: ='16'!$F$23 -> 5.8 | U19: ='16'!$F$24 -> 10.71 | V19: ='16'!$F$25 | W19: ='16'!$F$26 -> 6.09 | X19: ='16'!$F$27 -> 15.65 | Y19: ='16'!$F$28 -> 7.04 | Z19: ='16'!$F$29 -> 6.15 | AA19: ='16'!$F$30 -> 6.59 | AB19: ='16'!$F$31 | AC19: ='16'!$F$32 | AD19: ='16'!$F$33 -> 7.02
A20: Frank Phillips | B20: ='17'!$F$5 -> 8.14 | C20: ='17'!$F$6 -> 4.12 | D20: ='17'!$F$7 -> 7.29 | E20: ='17'!$F$8 -> 5.47 | F20: ='17'!$F$9 | G20: ='17'!$F$10 | H20: ='17'!$F$11 -> 11.63 | I20: ='17'!$F$12 -> 16.84 | J20: ='17'!$F$13 -> 4.81 | K20: ='17'!$F$14 | L20: ='17'!$F$15 -> 4 | M20: ='17'!$F$16 -> 4.89 | N20: ='17'!$F$17 -> 5.21 | O20: ='17'!$F$18 | P20: ='17'!$F$19 | Q20: ='17'!$F$20 -> 7.76 | R20: ='17'!$F$21 | S20: ='17'!$F$22 -> 9.26 | T20: ='17'!$F$23 -> 5.06 | U20: ='17'!$F$24 -> 5.87 | V20: ='17'!$F$25 -> 8.89 | W20: ='17'!$F$26 -> 21 | X20: ='17'!$F$27 -> 8.33 | Y20: ='17'!$F$28 -> 6.71 | Z20: ='17'!$F$29 -> 6.22 | AA20: ='17'!$F$30 -> 6.45 | AB20: ='17'!$F$31 | AC20: ='17'!$F$32 | AD20: ='17'!$F$33 -> 6.65
A21: Galveston | B21: ='18'!$F$5 | C21: ='18'!$F$6 -> 7.48 | D21: ='18'!$F$7 -> 8.08 | E21: ='18'!$F$8 -> 10.57 | F21: ='18'!$F$9 | G21: ='18'!$F$10 -> 1087.17 | H21: ='18'!$F$11 -> 12.64 | I21: ='18'!$F$12 | J21: ='18'!$F$13 -> 9.58 | K21: ='18'!$F$14 | L21: ='18'!$F$15 -> 27.33 | M21: ='18'!$F$16 -> 6.71 | N21: ='18'!$F$17 -> 5.69 | O21: ='18'!$F$18 -> 10.87 | P21: ='18'!$F$19 | Q21: ='18'!$F$20 -> 8.45 | R21: ='18'!$F$21 | S21: ='18'!$F$22 -> 8.65 | T21: ='18'!$F$23 -> 6.06 | U21: ='18'!$F$24 | V21: ='18'!$F$25 -> 15.39 | W21: ='18'!$F$26 | X21: ='18'!$F$27 -> 9.42 | Y21: ='18'!$F$28 -> 6.72 | Z21: ='18'!$F$29 -> 7.53 | AA21: ='18'!$F$30 -> 8.82 | AB21: ='18'!$F$31 | AC21: ='18'!$F$32 | AD21: ='18'!$F$33 -> 8.36
A22: Grayson | B22: ='19'!$F$5 -> 6.4 | C22: ='19'!$F$6 -> 7.84 | D22: ='19'!$F$7 -> 4.71 | E22: ='19'!$F$8 -> 6.29 | F22: ='19'!$F$9 | G22: ='19'!$F$10 -> 2.41 | H22: ='19'!$F$11 -> 7.46 | I22: ='19'!$F$12 | J22: ='19'!$F$13 -> 4.24 | K22: ='19'!$F$14 -> 2.41 | L22: ='19'!$F$15 -> 6.38 | M22: ='19'!$F$16 -> 5.22 | N22: ='19'!$F$17 -> 6.69 | O22: ='19'!$F$18 -> 7.75 | P22: ='19'!$F$19 | Q22: ='19'!$F$20 -> 6.13 | R22: ='19'!$F$21 | S22: ='19'!$F$22 -> 5.74 | T22: ='19'!$F$23 -> 4.69 | U22: ='19'!$F$24 -> 9.47 | V22: ='19'!$F$25 | W22: ='19'!$F$26 -> 7.52 | X22: ='19'!$F$27 -> 10.85 | Y22: ='19'!$F$28 -> 14.74 | Z22: ='19'!$F$29 -> 4.68 | AA22: ='19'!$F$30 -> 5.91 | AB22: ='19'!$F$31 | AC22: ='19'!$F$32 | AD22: ='19'!$F$33 -> 5.77
A23: Hill | B23: ='20'!$F$5 -> 7.86 | C23: ='20'!$F$6 -> 6.08 | D23: ='20'!$F$7 -> 4.3 | E23: ='20'!$F$8 -> 2.89 | F23: ='20'!$F$9 | G23: ='20'!$F$10 -> 11.62 | H23: ='20'!$F$11 -> 5.39 | I23: ='20'!$F$12 -> 13.74 | J23: ='20'!$F$13 -> 3.47 | K23: ='20'!$F$14 | L23: ='20'!$F$15 -> 6.05 | M23: ='20'!$F$16 -> 4.03 | N23: ='20'!$F$17 -> 4.31 | O23: ='20'!$F$18 | P23: ='20'!$F$19 | Q23: ='20'!$F$20 -> 3.62 | R23: ='20'!$F$21 | S23: ='20'!$F$22 -> 6.05 | T23: ='20'!$F$23 -> 3.84 | U23: ='20'!$F$24 -> 6.06 | V23: ='20'!$F$25 | W23: ='20'!$F$26 -> 39.92 | X23: ='20'!$F$27 -> 6.09 | Y23: ='20'!$F$28 -> 5.03 | Z23: ='20'!$F$29 -> 4.23 | AA23: ='20'!$F$30 -> 4.93 | AB23: ='20'!$F$31 | AC23: ='20'!$F$32 | AD23: ='20'!$F$33 -> 4.5
A24: Houston | B24: ='21'!$F$5 -> 8.13 | C24: ='21'!$F$6 -> 5.57 | D24: ='21'!$F$7 -> 7.13 | E24: ='21'!$F$8 -> 7.63 | F24: ='21'!$F$9 | G24: ='21'!$F$10 -> 13.93 | H24: ='21'!$F$11 -> 23.62 | I24: ='21'!$F$12 -> 7.42 | J24: ='21'!$F$13 -> 7.3 | K24: ='21'!$F$14 -> 11.93 | L24: ='21'!$F$15 -> 12.23 | M24: ='21'!$F$16 -> 7.12 | N24: ='21'!$F$17 -> 7.45 | O24: ='21'!$F$18 -> 12.58 | P24: ='21'!$F$19 | Q24: ='21'!$F$20 -> 8.51 | R24: ='21'!$F$21 -> 16.04 | S24: ='21'!$F$22 -> 11.69 | T24: ='21'!$F$23 -> 6.9 | U24: ='21'!$F$24 -> 9.74 | V24: ='21'!$F$25 -> 10.93 | W24: ='21'!$F$26 -> 23.41 | X24: ='21'!$F$27 -> 11.46 | Y24: ='21'!$F$28 -> 12.31 | Z24: ='21'!$F$29 -> 6.76 | AA24: ='21'!$F$30 -> 9.09 | AB24: ='21'!$F$31 | AC24: ='21'!$F$32 | AD24: ='21'!$F$33 -> 8.26
A25: Howard | B25: ='22'!$F$5 -> 6.7 | C25: ='22'!$F$6 -> 5.82 | D25: ='22'!$F$7 -> 6.74 | E25: ='22'!$F$8 -> 5.5 | F25: ='22'!$F$9 | G25: ='22'!$F$10 -> 3.6 | H25: ='22'!$F$11 -> 6.3 | I25: ='22'!$F$12 -> 6 | J25: ='22'!$F$13 -> 5.53 | K25: ='22'!$F$14 -> 8.31 | L25: ='22'!$F$15 -> 6.39 | M25: ='22'!$F$16 -> 5.35 | N25: ='22'!$F$17 -> 7.08 | O25: ='22'!$F$18 -> 12.62 | P25: ='22'!$F$19 -> 14.31 | Q25: ='22'!$F$20 -> 6.06 | R25: ='22'!$F$21 -> 8.88 | S25: ='22'!$F$22 -> 7.72 | T25: ='22'!$F$23 -> 5.72 | U25: ='22'!$F$24 -> 5.52 | V25: ='22'!$F$25 -> 5.16 | W25: ='22'!$F$26 -> 3.94 | X25: ='22'!$F$27 -> 13.67 | Y25: ='22'!$F$28 -> 4.65 | Z25: ='22'!$F$29 -> 5.18 | AA25: ='22'!$F$30 -> 6.87 | AB25: ='22'!$F$31 | AC25: ='22'!$F$32 | AD25: ='22'!$F$33 -> 6.07
A26: Kilgore | B26: ='23'!$F$5 -> 9.12 | C26: ='23'!$F$6 -> 6.07 | D26: ='23'!$F$7 -> 5.29 | E26: ='23'!$F$8 -> 5.2 | F26: ='23'!$F$9 | G26: ='23'!$F$10 -> 12.16 | H26: ='23'!$F$11 -> 4.64 | I26: ='23'!$F$12 -> 7.82 | J26: ='23'!$F$13 -> 3.44 | K26: ='23'!$F$14 -> 29.84 | L26: ='23'!$F$15 -> 5.92 | M26: ='23'!$F$16 -> 4.46 | N26: ='23'!$F$17 -> 9.36 | O26: ='23'!$F$18 -> 7.95 | P26: ='23'!$F$19 | Q26: ='23'!$F$20 -> 5.53 | R26: ='23'!$F$21 | S26: ='23'!$F$22 -> 5.03 | T26: ='23'!$F$23 -> 4.17 | U26: ='23'!$F$24 -> 5.66 | V26: ='23'!$F$25 -> 10.21 | W26: ='23'!$F$26 | X26: ='23'!$F$27 -> 6.79 | Y26: ='23'!$F$28 -> 7.06 | Z26: ='23'!$F$29 -> 4.1 | AA26: ='23'!$F$30 -> 6.01 | AB26: ='23'!$F$31 | AC26: ='23'!$F$32 | AD26: ='23'!$F$33 -> 5.27
A27: Laredo | B27: ='24'!$F$5 | C27: ='24'!$F$6 | D27: ='24'!$F$7 -> 7.1 | E27: ='24'!$F$8 -> 8.02 | F27: ='24'!$F$9 | G27: ='24'!$F$10 -> 6.76 | H27: ='24'!$F$11 -> 7.65 | I27: ='24'!$F$12 -> 11.49 | J27: ='24'!$F$13 | K27: ='24'!$F$14 | L27: ='24'!$F$15 | M27: ='24'!$F$16 -> 7.9 | N27: ='24'!$F$17 -> 7.43 | O27: ='24'!$F$18 -> 12.76 | P27: ='24'!$F$19 | Q27: ='24'!$F$20 -> 8.94 | R27: ='24'!$F$21 | S27: ='24'!$F$22 -> 10.84 | T27: ='24'!$F$23 -> 6.61 | U27: ='24'!$F$24 -> 9.17 | V27: ='24'!$F$25 | W27: ='24'!$F$26 -> 7.65 | X27: ='24'!$F$27 -> 6.46 | Y27: ='24'!$F$28 -> 7.74 | Z27: ='24'!$F$29 -> 6.21 | AA27: ='24'!$F$30 -> 8.08 | AB27: ='24'!$F$31 | AC27: ='24'!$F$32 | AD27: ='24'!$F$33 -> 7.65
A28: Lee | B28: ='25'!$F$5 -> 5.83 | C28: ='25'!$F$6 -> 22.83 | D28: ='25'!$F$7 -> 7.79 | E28: ='25'!$F$8 -> 7.07 | F28: ='25'!$F$9 -> 12.89 | G28: ='25'!$F$10 -> 5.12 | H28: ='25'!$F$11 -> 8.12 | I28: ='25'!$F$12 -> 5.79 | J28: ='25'!$F$13 -> 8.17 | K28: ='25'!$F$14 | L28: ='25'!$F$15 | M28: ='25'!$F$16 -> 8.96 | N28: ='25'!$F$17 -> 8.48 | O28: ='25'!$F$18 -> 9.6 | P28: ='25'!$F$19 | Q28: ='25'!$F$20 -> 8.32 | R28: ='25'!$F$21 | S28: ='25'!$F$22 -> 9.81 | T28: ='25'!$F$23 -> 7.97 | U28: ='25'!$F$24 -> 6.03 | V28: ='25'!$F$25 -> 6.03 | W28: ='25'!$F$26 -> 6.22 | X28: ='25'!$F$27 -> 7.94 | Y28: ='25'!$F$28 -> 7.77 | Z28: ='25'!$F$29 -> 7.06 | AA28: ='25'!$F$30 -> 9.02 | AB28: ='25'!$F$31 | AC28: ='25'!$F$32 | AD28: ='25'!$F$33 -> 7.72
A29: Lonestar | B29: ='26'!$F$5 -> 7.23 | C29: ='26'!$F$6 -> 9.25 | D29: ='26'!$F$7 -> 7.12 | E29: ='26'!$F$8 -> 8.74 | F29: ='26'!$F$9 -> 11.77 | G29: ='26'!$F$10 -> 7.56 | H29: ='26'!$F$11 -> 8.29 | I29: ='26'!$F$12 -> 8.83 | J29: ='26'!$F$13 -> 6.29 | K29: ='26'!$F$14 -> 8.83 | L29: ='26'!$F$15 -> 8.83 | M29: ='26'!$F$16 -> 7.02 | N29: ='26'!$F$17 -> 5.98 | O29: ='26'!$F$18 -> 12.76 | P29: ='26'!$F$19 | Q29: ='26'!$F$20 -> 7.08 | R29: ='26'!$F$21 -> 13.13 | S29: ='26'!$F$22 -> 7.85 | T29: ='26'!$F$23 -> 6.14 | U29: ='26'!$F$24 -> 7.22 | V29: ='26'!$F$25 -> 12.09 | W29: ='26'!$F$26 -> 11.77 | X29: ='26'!$F$27 -> 7.94 | Y29: ='26'!$F$28 -> 7.8 | Z29: ='26'!$F$29 -> 6.17 | AA29: ='26'!$F$30 -> 8.3 | AB29: ='26'!$F$31 | AC29: ='26'!$F$32 | AD29: ='26'!$F$33 -> 7.17
A30: Mclennan | B30: ='27'!$F$5 | C30: ='27'!$F$6 -> 59.51 | D30: ='27'!$F$7 -> 4.55 | E30: ='27'!$F$8 -> 5.24 | F30: ='27'!$F$9 | G30: ='27'!$F$10 -> 4.24 | H30: ='27'!$F$11 -> 11.37 | I30: ='27'!$F$12 -> 26.68 | J30: ='27'!$F$13 -> 7.69 | K30: ='27'!$F$14 | L30: ='27'!$F$15 | M30: ='27'!$F$16 -> 5.78 | N30: ='27'!$F$17 -> 4.8 | O30: ='27'!$F$18 -> 8.87 | P30: ='27'!$F$19 | Q30: ='27'!$F$20 -> 6.2 | R30: ='27'!$F$21 -> 7.26 | S30: ='27'!$F$22 -> 4.73 | T30: ='27'!$F$23 -> 4.72 | U30: ='27'!$F$24 | V30: ='27'!$F$25 -> 2.36 | W30: ='27'!$F$26 | X30: ='27'!$F$27 -> 8.36 | Y30: ='27'!$F$28 -> 7.28 | Z30: ='27'!$F$29 -> 3.94 | AA30: ='27'!$F$30 -> 6.31 | AB30: ='27'!$F$31 | AC30: ='27'!$F$32 | AD30: ='27'!$F$33 -> 6.04
A31: Midland | B31: ='28'!$F$5 -> 10.54 | C31: ='28'!$F$6 -> 8.94 | D31: ='28'!$F$7 -> 6.33 | E31: ='28'!$F$8 -> 7.65 | F31: ='28'!$F$9 -> 13.8 | G31: ='28'!$F$10 -> 15.39 | H31: ='28'!$F$11 -> 7.72 | I31: ='28'!$F$12 | J31: ='28'!$F$13 -> 5.52 | K31: ='28'!$F$14 -> 4.66 | L31: ='28'!$F$15 -> 11.06 | M31: ='28'!$F$16 -> 7.55 | N31: ='28'!$F$17 -> 6.48 | O31: ='28'!$F$18 -> 9.85 | P31: ='28'!$F$19 | Q31: ='28'!$F$20 -> 8.51 | R31: ='28'!$F$21 -> 10.98 | S31: ='28'!$F$22 -> 10.95 | T31: ='28'!$F$23 -> 6.7 | U31: ='28'!$F$24 -> 8.2 | V31: ='28'!$F$25 -> 13.75 | W31: ='28'!$F$26 | X31: ='28'!$F$27 -> 11.28 | Y31: ='28'!$F$28 -> 6.78 | Z31: ='28'!$F$29 -> 6.65 | AA31: ='28'!$F$30 -> 8.68 | AB31: ='28'!$F$31 | AC31: ='28'!$F$32 | AD31: ='28'!$F$33 -> 7.84
A32: Navarro | B32: ='29'!$F$5 -> 11.12 | C32: ='29'!$F$6 -> 4.74 | D32: ='29'!$F$7 -> 4.25 | E32: ='29'!$F$8 -> 4.6 | F32: ='29'!$F$9 | G32: ='29'!$F$10 -> 6.95 | H32: ='29'!$F$11 -> 4.54 | I32: ='29'!$F$12 -> 4.08 | J32: ='29'!$F$13 -> 4.4 | K32: ='29'!$F$14 -> 14.44 | L32: ='29'!$F$15 -> 3.91 | M32: ='29'!$F$16 -> 4.35 | N32: ='29'!$F$17 -> 3.92 | O32: ='29'!$F$18 -> 8.56 | P32: ='29'!$F$19 | Q32: ='29'!$F$20 -> 5.42 | R32: ='29'!$F$21 | S32: ='29'!$F$22 -> 5.63 | T32: ='29'!$F$23 -> 4.48 | U32: ='29'!$F$24 | V32: ='29'!$F$25 -> 7.06 | W32: ='29'!$F$26 | X32: ='29'!$F$27 -> 5.27 | Y32: ='29'!$F$28 -> 5.84 | Z32: ='29'!$F$29 -> 4.33 | AA32: ='29'!$F$30 -> 6.03 | AB32: ='29'!$F$31 | AC32: ='29'!$F$32 | AD32: ='29'!$F$33 -> 4.87
A33: North Central Texas | B33: ='30'!$F$5 -> 8.43 | C33: ='30'!$F$6 -> 9.45 | D33: ='30'!$F$7 -> 4.03 | E33: ='30'!$F$8 -> 4.23 | F33: ='30'!$F$9 | G33: ='30'!$F$10 -> 22.77 | H33: ='30'!$F$11 -> 7.53 | I33: ='30'!$F$12 | J33: ='30'!$F$13 -> 3.3 | K33: ='30'!$F$14 | L33: ='30'!$F$15 -> 3.48 | M33: ='30'!$F$16 -> 4.54 | N33: ='30'!$F$17 -> 5.6 | O33: ='30'!$F$18 -> 6.1 | P33: ='30'!$F$19 | Q33: ='30'!$F$20 -> 6.53 | R33: ='30'!$F$21 | S33: ='30'!$F$22 -> 4.77 | T33: ='30'!$F$23 -> 3.98 | U33: ='30'!$F$24 | V33: ='30'!$F$25 | W33: ='30'!$F$26 | X33: ='30'!$F$27 -> 5.91 | Y33: ='30'!$F$28 -> 5.81 | Z33: ='30'!$F$29 -> 3.7 | AA33: ='30'!$F$30 -> 4.79 | AB33: ='30'!$F$31 | AC33: ='30'!$F$32 | AD33: ='30'!$F$33 -> 4.66
A34: Northeast Texas | B34: ='31'!$F$5 -> 5.9 | C34: ='31'!$F$6 -> 33.16 | D34: ='31'!$F$7 -> 3.15 | E34: ='31'!$F$8 -> 6.23 | F34: ='31'!$F$9 | G34: ='31'!$F$10 -> 12.56 | H34: ='31'!$F$11 -> 7.55 | I34: ='31'!$F$12 -> 112.33 | J34: ='31'!$F$13 -> 3.95 | K34: ='31'!$F$14 | L34: ='31'!$F$15 | M34: ='31'!$F$16 -> 5.33 | N34: ='31'!$F$17 -> 6.88 | O34: ='31'!$F$18 -> 9.08 | P34: ='31'!$F$19 | Q34: ='31'!$F$20 -> 4.12 | R34: ='31'!$F$21 | S34: ='31'!$F$22 -> 7 | T34: ='31'!$F$23 -> 5.71 | U34: ='31'!$F$24 -> 9.11 | V34: ='31'!$F$25 -> 9.11 | W34: ='31'!$F$26 -> 8.43 | X34: ='31'!$F$27 -> 5.79 | Y34: ='31'!$F$28 -> 7.31 | Z34: ='31'!$F$29 -> 4.87 | AA34: ='31'!$F$30 -> 9.28 | AB34: ='31'!$F$31 | AC34: ='31'!$F$32 | AD34: ='31'!$F$33 -> 6.37
A35: Odessa | B35: ='32'!$F$5 -> 7.03 | C35: ='32'!$F$6 -> 7.48 | D35: ='32'!$F$7 -> 5.09 | E35: ='32'!$F$8 -> 6.19 | F35: ='32'!$F$9 | G35: ='32'!$F$10 -> 6.81 | H35: ='32'!$F$11 -> 5.87 | I35: ='32'!$F$12 -> 6.29 | J35: ='32'!$F$13 -> 5.71 | K35: ='32'!$F$14 -> 7.01 | L35: ='32'!$F$15 -> 6.79 | M35: ='32'!$F$16 -> 5.24 | N35: ='32'!$F$17 -> 5.73 | O35: ='32'!$F$18 -> 9.22 | P35: ='32'!$F$19 | Q35: ='32'!$F$20 -> 6.9 | R35: ='32'!$F$21 -> 10.81 | S35: ='32'!$F$22 -> 5.77 | T35: ='32'!$F$23 -> 5.5 | U35: ='32'!$F$24 -> 7.64 | V35: ='32'!$F$25 -> 7.51 | W35: ='32'!$F$26 -> 7.73 | X35: ='32'!$F$27 -> 5.35 | Y35: ='32'!$F$28 -> 5.62 | Z35: ='32'!$F$29 -> 5.46 | AA35: ='32'!$F$30 -> 9.04 | AB35: ='32'!$F$31 | AC35: ='32'!$F$32 | AD35: ='32'!$F$33 -> 6.07
A36: Panola | B36: ='33'!$F$5 -> 11.35 | C36: ='33'!$F$6 -> 10.94 | D36: ='33'!$F$7 -> 6.53 | E36: ='33'!$F$8 -> 10.1 | F36: ='33'!$F$9 | G36: ='33'!$F$10 -> 13.02 | H36: ='33'!$F$11 -> 9.11 | I36: ='33'!$F$12 -> 6.81 | J36: ='33'!$F$13 -> 7.02 | K36: ='33'!$F$14 | L36: ='33'!$F$15 -> 28.98 | M36: ='33'!$F$16 -> 6.69 | N36: ='33'!$F$17 -> 8.12 | O36: ='33'!$F$18 -> 11.28 | P36: ='33'!$F$19 | Q36: ='33'!$F$20 -> 8.55 | R36: ='33'!$F$21 | S36: ='33'!$F$22 -> 7.27 | T36: ='33'!$F$23 -> 7.44 | U36: ='33'!$F$24 | V36: ='33'!$F$25 | W36: ='33'!$F$26 -> 36.13 | X36: ='33'!$F$27 -> 7.45 | Y36: ='33'!$F$28 -> 7.57 | Z36: ='33'!$F$29 -> 6.5 | AA36: ='33'!$F$30 -> 9.15 | AB36: ='33'!$F$31 | AC36: ='33'!$F$32 | AD36: ='33'!$F$33 -> 8.01
A37: Paris | B37: ='34'!$F$5 -> 11.15 | C37: ='34'!$F$6 -> 7.73 | D37: ='34'!$F$7 -> 5.17 | E37: ='34'!$F$8 -> 5.6 | F37: ='34'!$F$9 | G37: ='34'!$F$10 -> 28.84 | H37: ='34'!$F$11 -> 5.3 | I37: ='34'!$F$12 | J37: ='34'!$F$13 -> 7.64 | K37: ='34'!$F$14 | L37: ='34'!$F$15 -> 5.87 | M37: ='34'!$F$16 -> 5.93 | N37: ='34'!$F$17 -> 5.54 | O37: ='34'!$F$18 -> 12.88 | P37: ='34'!$F$19 | Q37: ='34'!$F$20 -> 4.85 | R37: ='34'!$F$21 | S37: ='34'!$F$22 -> 8.94 | T37: ='34'!$F$23 -> 4.96 | U37: ='34'!$F$24 | V37: ='34'!$F$25 -> 18.93 | W37: ='34'!$F$26 -> 7.47 | X37: ='34'!$F$27 -> 6.01 | Y37: ='34'!$F$28 -> 3.78 | Z37: ='34'!$F$29 -> 5.35 | AA37: ='34'!$F$30 -> 7.14 | AB37: ='34'!$F$31 | AC37: ='34'!$F$32 | AD37: ='34'!$F$33 -> 6.16
A38: Ranger | B38: ='35'!$F$5 | C38: ='35'!$F$6 -> 6.74 | D38: ='35'!$F$7 -> 4.68 | E38: ='35'!$F$8 -> 6.84 | F38: ='35'!$F$9 | G38: ='35'!$F$10 -> 3.5 | H38: ='35'!$F$11 -> 5.82 | I38: ='35'!$F$12 | J38: ='35'!$F$13 -> 5.34 | K38: ='35'!$F$14 | L38: ='35'!$F$15 | M38: ='35'!$F$16 -> 5.14 | N38: ='35'!$F$17 -> 19.71 | O38: ='35'!$F$18 | P38: ='35'!$F$19 | Q38: ='35'!$F$20 -> 5 | R38: ='35'!$F$21 | S38: ='35'!$F$22 -> 4.92 | T38: ='35'!$F$23 -> 5.52 | U38: ='35'!$F$24 -> 9.89 | V38: ='35'!$F$25 | W38: ='35'!$F$26 | X38: ='35'!$F$27 -> 12.93 | Y38: ='35'!$F$28 | Z38: ='35'!$F$29 -> 4.23 | AA38: ='35'!$F$30 -> 6.31 | AB38: ='35'!$F$31 | AC38: ='35'!$F$32 | AD38: ='35'!$F$33 -> 5.88
A39: San Jacinto | B39: ='36'!$F$5 -> 12.47 | C39: ='36'!$F$6 -> 5.02 | D39: ='36'!$F$7 -> 5.91 | E39: ='36'!$F$8 -> 6.85 | F39: ='36'!$F$9 -> 19.02 | G39: ='36'!$F$10 -> 9.43 | H39: ='36'!$F$11 -> 7.93 | I39: ='36'!$F$12 -> 4.93 | J39: ='36'!$F$13 -> 6.94 | K39: ='36'!$F$14 -> 11.74 | L39: ='36'!$F$15 -> 10.89 | M39: ='36'!$F$16 -> 6.45 | N39: ='36'!$F$17 -> 6.13 | O39: ='36'!$F$18 -> 8.76 | P39: ='36'!$F$19 | Q39: ='36'!$F$20 -> 8 | R39: ='36'!$F$21 -> 9.72 | S39: ='36'!$F$22 -> 6.76 | T39: ='36'!$F$23 -> 6.26 | U39: ='36'!$F$24 -> 8.55 | V39: ='36'!$F$25 -> 11.13 | W39: ='36'!$F$26 -> 3.94 | X39: ='36'!$F$27 -> 7.53 | Y39: ='36'!$F$28 -> 7.27 | Z39: ='36'!$F$29 -> 5.88 | AA39: ='36'!$F$30 -> 7.51 | AB39: ='36'!$F$31 | AC39: ='36'!$F$32 | AD39: ='36'!$F$33 -> 6.89
A40: South Plains | B40: ='37'!$F$5 -> 9.92 | C40: ='37'!$F$6 -> 8.27 | D40: ='37'!$F$7 -> 4.98 | E40: ='37'!$F$8 -> 7.02 | F40: ='37'!$F$9 | G40: ='37'!$F$10 -> 6.74 | H40: ='37'!$F$11 -> 4.78 | I40: ='37'!$F$12 -> 5.88 | J40: ='37'!$F$13 -> 4.93 | K40: ='37'!$F$14 -> 11.66 | L40: ='37'!$F$15 -> 8.31 | M40: ='37'!$F$16 -> 5.04 | N40: ='37'!$F$17 -> 4.92 | O40: ='37'!$F$18 -> 6.77 | P40: ='37'!$F$19 | Q40: ='37'!$F$20 -> 6.1 | R40: ='37'!$F$21 -> 6.42 | S40: ='37'!$F$22 -> 5.38 | T40: ='37'!$F$23 -> 5.59 | U40: ='37'!$F$24 -> 4.97 | V40: ='37'!$F$25 -> 20.39 | W40: ='37'!$F$26 -> 26.44 | X40: ='37'!$F$27 -> 7.77 | Y40: ='37'!$F$28 -> 6.97 | Z40: ='37'!$F$29 -> 4.92 | AA40: ='37'!$F$30 -> 7.96 | AB40: ='37'!$F$31 | AC40: ='37'!$F$32 | AD40: ='37'!$F$33 -> 5.78
A41: South Texas | B41: ='38'!$F$5 -> 6.41 | C41: ='38'!$F$6 -> 9.83 | D41: ='38'!$F$7 -> 6.43 | E41: ='38'!$F$8 -> 9.67 | F41: ='38'!$F$9 | G41: ='38'!$F$10 | H41: ='38'!$F$11 -> 7.66 | I41: ='38'!$F$12 | J41: ='38'!$F$13 -> 8.37 | K41: ='38'!$F$14 -> 8.4 | L41: ='38'!$F$15 -> 5.57 | M41: ='38'!$F$16 -> 6.11 | N41: ='38'!$F$17 -> 6.55 | O41: ='38'!$F$18 -> 8.67 | P41: ='38'!$F$19 | Q41: ='38'!$F$20 -> 7.9 | R41: ='38'!$F$21 | S41: ='38'!$F$22 -> 8.05 | T41: ='38'!$F$23 -> 5.68 | U41: ='38'!$F$24 -> 8.49 | V41: ='38'!$F$25 -> 10.74 | W41: ='38'!$F$26 -> 39.19 | X41: ='38'!$F$27 -> 10.35 | Y41: ='38'!$F$28 -> 7.32 | Z41: ='38'!$F$29 -> 5.78 | AA41: ='38'!$F$30 -> 6.28 | AB41: ='38'!$F$31 | AC41: ='38'!$F$32 | AD41: ='38'!$F$33 -> 6.88
A42: Southwest Texas | B42: ='39'!$F$5 -> 12.47 | C42: ='39'!$F$6 -> 29.36 | D42: ='39'!$F$7 -> 5.33 | E42: ='39'!$F$8 -> 7.28 | F42: ='39'!$F$9 -> 12.45 | G42: ='39'!$F$10 -> 7.5 | H42: ='39'!$F$11 -> 4.26 | I42: ='39'!$F$12 -> 9.92 | J42: ='39'!$F$13 -> 6.06 | K42: ='39'!$F$14 | L42: ='39'!$F$15 -> 10.64 | M42: ='39'!$F$16 -> 5.76 | N42: ='39'!$F$17 -> 6.78 | O42: ='39'!$F$18 | P42: ='39'!$F$19 | Q42: ='39'!$F$20 -> 9.73 | R42: ='39'!$F$21 | S42: ='39'!$F$22 -> 7.49 | T42: ='39'!$F$23 -> 5.02 | U42: ='39'!$F$24 -> 6.76 | V42: ='39'!$F$25 -> 20.4 | W42: ='39'!$F$26 -> 14.02 | X42: ='39'!$F$27 -> 6.65 | Y42: ='39'!$F$28 -> 7.91 | Z42: ='39'!$F$29 -> 5.2 | AA42: ='39'!$F$30 -> 5.7 | AB42: ='39'!$F$31 | AC42: ='39'!$F$32 | AD42: ='39'!$F$33 -> 6.22
A43: Tarrant | B43: ='40'!$F$5 -> 11.44 | C43: ='40'!$F$6 -> 6.35 | D43: ='40'!$F$7 -> 6.55 | E43: ='40'!$F$8 -> 7.16 | F43: ='40'!$F$9 -> 19.25 | G43: ='40'!$F$10 -> 12.88 | H43: ='40'!$F$11 -> 7.39 | I43: ='40'!$F$12 -> 4.79 | J43: ='40'!$F$13 -> 6.73 | K43: ='40'!$F$14 -> 30.17 | L43: ='40'!$F$15 -> 9.6 | M43: ='40'!$F$16 -> 6.59 | N43: ='40'!$F$17 -> 6.81 | O43: ='40'!$F$18 -> 12.4 | P43: ='40'!$F$19 -> 15.87 | Q43: ='40'!$F$20 -> 7.18 | R43: ='40'!$F$21 -> 16.12 | S43: ='40'!$F$22 | T43: ='40'!$F$23 -> 6.5 | U43: ='40'!$F$24 -> 7.95 | V43: ='40'!$F$25 -> 5.94 | W43: ='40'!$F$26 -> 3.92 | X43: ='40'!$F$27 -> 7.63 | Y43: ='40'!$F$28 -> 10.09 | Z43: ='40'!$F$29 -> 5.98 | AA43: ='40'!$F$30 -> 8.11 | AB43: ='40'!$F$31 | AC43: ='40'!$F$32 | AD43: ='40'!$F$33 -> 6.96
A44: Temple | B44: ='41'!$F$5 -> 5.18 | C44: ='41'!$F$6 -> 10.48 | D44: ='41'!$F$7 -> 5.56 | E44: ='41'!$F$8 -> 5.31 | F44: ='41'!$F$9 | G44: ='41'!$F$10 -> 4.19 | H44: ='41'!$F$11 -> 6.36 | I44: ='41'!$F$12 -> 8.22 | J44: ='41'!$F$13 -> 5.53 | K44: ='41'!$F$14 -> 16.31 | L44: ='41'!$F$15 -> 6.06 | M44: ='41'!$F$16 -> 5.5 | N44: ='41'!$F$17 -> 6.59 | O44: ='41'!$F$18 -> 9.37 | P44: ='41'!$F$19 -> 18.61 | Q44: ='41'!$F$20 -> 7.74 | R44: ='41'!$F$21 -> 13.66 | S44: ='41'!$F$22 -> 7.28 | T44: ='41'!$F$23 -> 6.59 | U44: ='41'!$F$24 -> 8.12 | V44: ='41'!$F$25 | W44: ='41'!$F$26 | X44: ='41'!$F$27 -> 5.83 | Y44: ='41'!$F$28 -> 5.15 | Z44: ='41'!$F$29 -> 5.4 | AA44: ='41'!$F$30 -> 9.56 | AB44: ='41'!$F$31 | AC44: ='41'!$F$32 | AD44: ='41'!$F$33 -> 6.63
A45: Texarkana | B45: ='42'!$F$5 -> 9.44 | C45: ='42'!$F$6 -> 4.8 | D45: ='42'!$F$7 -> 5.31 | E45: ='42'!$F$8 -> 6.22 | F45: ='42'!$F$9 | G45: ='42'!$F$10 -> 6.32 | H45: ='42'!$F$11 -> 6.19 | I45: ='42'!$F$12 -> 5.54 | J45: ='42'!$F$13 -> 4.91 | K45: ='42'!$F$14 -> 5.4 | L45: ='42'!$F$15 -> 4.92 | M45: ='42'!$F$16 -> 5.46 | N45: ='42'!$F$17 -> 5.43 | O45: ='42'!$F$18 -> 7.42 | P45: ='42'!$F$19 -> 5.2 | Q45: ='42'!$F$20 -> 7.42 | R45: ='42'!$F$21 | S45: ='42'!$F$22 -> 4.89 | T45: ='42'!$F$23 -> 4.78 | U45: ='42'!$F$24 -> 5.16 | V45: ='42'!$F$25 -> 6.62 | W45: ='42'!$F$26 -> 4.61 | X45: ='42'!$F$27 -> 4 | Y45: ='42'!$F$28 -> 6.48 | Z45: ='42'!$F$29 -> 5.05 | AA45: ='42'!$F$30 -> 4.64 | AB45: ='42'!$F$31 | AC45: ='42'!$F$32 | AD45: ='42'!$F$33 -> 5.46
A46: Texas Southmost | B46: ='43'!$F$5 | C46: ='43'!$F$6 -> 9.6 | D46: ='43'!$F$7 -> 6.16 | E46: ='43'!$F$8 -> 7.12 | F46: ='43'!$F$9 | G46: ='43'!$F$10 | H46: ='43'!$F$11 -> 6.19 | I46: ='43'!$F$12 -> 5.91 | J46: ='43'!$F$13 -> 4.67 | K46: ='43'!$F$14 -> 49.27 | L46: ='43'!$F$15 -> 8.98 | M46: ='43'!$F$16 -> 12.77 | N46: ='43'!$F$17 -> 4.66 | O46: ='43'!$F$18 -> 7.47 | P46: ='43'!$F$19 | Q46: ='43'!$F$20 -> 14.44 | R46: ='43'!$F$21 -> 13.73 | S46: ='43'!$F$22 -> 5 | T46: ='43'!$F$23 -> 4.85 | U46: ='43'!$F$24 -> 6.76 | V46: ='43'!$F$25 -> 6.88 | W46: ='43'!$F$26 | X46: ='43'!$F$27 -> 7.34 | Y46: ='43'!$F$28 -> 10.44 | Z46: ='43'!$F$29 -> 4.81 | AA46: ='43'!$F$30 -> 8.26 | AB46: ='43'!$F$31 | AC46: ='43'!$F$32 | AD46: ='43'!$F$33 -> 7.77
A47: Trinity Valley | B47: ='44'!$F$5 -> 5.06 | C47: ='44'!$F$6 -> 4.91 | D47: ='44'!$F$7 -> 4.85 | E47: ='44'!$F$8 -> 6.43 | F47: ='44'!$F$9 | G47: ='44'!$F$10 -> 6.37 | H47: ='44'!$F$11 -> 3.74 | I47: ='44'!$F$12 -> 3.54 | J47: ='44'!$F$13 -> 4.05 | K47: ='44'!$F$14 | L47: ='44'!$F$15 -> 3.7 | M47: ='44'!$F$16 -> 4.78 | N47: ='44'!$F$17 -> 4.92 | O47: ='44'!$F$18 -> 6.22 | P47: ='44'!$F$19 | Q47: ='44'!$F$20 -> 4.2 | R47: ='44'!$F$21 | S47: ='44'!$F$22 -> 5.2 | T47: ='44'!$F$23 -> 4.73 | U47: ='44'!$F$24 -> 4.33 | V47: ='44'!$F$25 | W47: ='44'!$F$26 | X47: ='44'!$F$27 -> 5.58 | Y47: ='44'!$F$28 -> 3.89 | Z47: ='44'!$F$29 -> 4.56 | AA47: ='44'!$F$30 -> 5.8 | AB47: ='44'!$F$31 | AC47: ='44'!$F$32 | AD47: ='44'!$F$33 -> 4.73
A48: Tyler | B48: ='45'!$F$5 -> 3.75 | C48: ='45'!$F$6 -> 9.81 | D48: ='45'!$F$7 -> 5.01 | E48: ='45'!$F$8 -> 4.05 | F48: ='45'!$F$9 | G48: ='45'!$F$10 -> 7.32 | H48: ='45'!$F$11 -> 11.31 | I48: ='45'!$F$12 | J48: ='45'!$F$13 -> 4.21 | K48: ='45'!$F$14 -> 2.54 | L48: ='45'!$F$15 -> 4.15 | M48: ='45'!$F$16 -> 4.82 | N48: ='45'!$F$17 -> 6.03 | O48: ='45'!$F$18 -> 7.84 | P48: ='45'!$F$19 -> 12.22 | Q48: ='45'!$F$20 -> 5.39 | R48: ='45'!$F$21 -> 7.32 | S48: ='45'!$F$22 -> 5.66 | T48: ='45'!$F$23 -> 4.97 | U48: ='45'!$F$24 -> 7.5 | V48: ='45'!$F$25 -> 35.91 | W48: ='45'!$F$26 -> 2.61 | X48: ='45'!$F$27 -> 8.63 | Y48: ='45'!$F$28 -> 4.19 | Z48: ='45'!$F$29 -> 4.81 | AA48: ='45'!$F$30 -> 7.53 | AB48: ='45'!$F$31 | AC48: ='45'!$F$32 | AD48: ='45'!$F$33 -> 5.67
A49: Vernon | B49: ='46'!$F$5 -> 5.99 | C49: ='46'!$F$6 -> 9.29 | D49: ='46'!$F$7 -> 4.72 | E49: ='46'!$F$8 -> 5.02 | F49: ='46'!$F$9 | G49: ='46'!$F$10 | H49: ='46'!$F$11 -> 4.83 | I49: ='46'!$F$12 | J49: ='46'!$F$13 -> 4.13 | K49: ='46'!$F$14 | L49: ='46'!$F$15 -> 4.25 | M49: ='46'!$F$16 -> 5.12 | N49: ='46'!$F$17 -> 4.77 | O49: ='46'!$F$18 -> 6.45 | P49: ='46'!$F$19 | Q49: ='46'!$F$20 -> 3.94 | R49: ='46'!$F$21 | S49: ='46'!$F$22 -> 5.25 | T49: ='46'!$F$23 -> 4.89 | U49: ='46'!$F$24 -> 7.11 | V49: ='46'!$F$25 -> 6.93 | W49: ='46'!$F$26 -> 4.32 | X49: ='46'!$F$27 -> 5.2 | Y49: ='46'!$F$28 -> 4.97 | Z49: ='46'!$F$29 -> 4.46 | AA49: ='46'!$F$30 -> 5.17 | AB49: ='46'!$F$31 | AC49: ='46'!$F$32 | AD49: ='46'!$F$33 -> 5.04
A50: Victoria | B50: ='47'!$F$5 -> 6.73 | C50: ='47'!$F$6 -> 6.93 | D50: ='47'!$F$7 -> 6.73 | E50: ='47'!$F$8 -> 6.76 | F50: ='47'!$F$9 | G50: ='47'!$F$10 -> 8.05 | H50: ='47'!$F$11 -> 8.05 | I50: ='47'!$F$12 -> 21.23 | J50: ='47'!$F$13 -> 3.84 | K50: ='47'!$F$14 | L50: ='47'!$F$15 -> 5.32 | M50: ='47'!$F$16 -> 6.54 | N50: ='47'!$F$17 -> 6.88 | O50: ='47'!$F$18 -> 12.25 | P50: ='47'!$F$19 | Q50: ='47'!$F$20 -> 5.26 | R50: ='47'!$F$21 -> 9.08 | S50: ='47'!$F$22 -> 6.6 | T50: ='47'!$F$23 -> 6.65 | U50: ='47'!$F$24 | V50: ='47'!$F$25 -> 16.47 | W50: ='47'!$F$26 | X50: ='47'!$F$27 -> 7.71 | Y50: ='47'!$F$28 -> 6.94 | Z50: ='47'!$F$29 -> 5.78 | AA50: ='47'!$F$30 -> 9.09 | AB50: ='47'!$F$31 | AC50: ='47'!$F$32 | AD50: ='47'!$F$33 -> 6.88
A51: Weatherford | B51: ='48'!$F$5 -> 6.3 | C51: ='48'!$F$6 -> 3.66 | D51: ='48'!$F$7 -> 4.34 | E51: ='48'!$F$8 -> 5.98 | F51: ='48'!$F$9 | G51: ='48'!$F$10 -> 6.79 | H51: ='48'!$F$11 -> 4.73 | I51: ='48'!$F$12 -> 3.66 | J51: ='48'!$F$13 -> 4.84 | K51: ='48'!$F$14 | L51: ='48'!$F$15 -> 5.86 | M51: ='48'!$F$16 -> 5.13 | N51: ='48'!$F$17 -> 4.94 | O51: ='48'!$F$18 -> 9.45 | P51: ='48'!$F$19 | Q51: ='48'!$F$20 -> 4.92 | R51: ='48'!$F$21 -> 7.15 | S51: ='48'!$F$22 -> 5.82 | T51: ='48'!$F$23 -> 5.53 | U51: ='48'!$F$24 | V51: ='48'!$F$25 -> 8.34 | W51: ='48'!$F$26 | X51: ='48'!$F$27 -> 6.25 | Y51: ='48'!$F$28 -> 5.93 | Z51: ='48'!$F$29 -> 4.67 | AA51: ='48'!$F$30 -> 7.2 | AB51: ='48'!$F$31 | AC51: ='48'!$F$32 | AD51: ='48'!$F$33 -> 5.42
A52: Western Texas | B52: ='49'!$F$5 -> 8.22 | C52: ='49'!$F$6 -> 8.02 | D52: ='49'!$F$7 -> 8.15 | E52: ='49'!$F$8 -> 7.61 | F52: ='49'!$F$9 | G52: ='49'!$F$10 -> 12.11 | H52: ='49'!$F$11 -> 9.53 | I52: ='49'!$F$12 | J52: ='49'!$F$13 -> 6.06 | K52: ='49'!$F$14 | L52: ='49'!$F$15 -> 6.21 | M52: ='49'!$F$16 -> 6.59 | N52: ='49'!$F$17 -> 8.1 | O52: ='49'!$F$18 | P52: ='49'!$F$19 | Q52: ='49'!$F$20 -> 14.63 | R52: ='49'!$F$21 | S52: ='49'!$F$22 -> 7.27 | T52: ='49'!$F$23 -> 6.89 | U52: ='49'!$F$24 -> 5.92 | V52: ='49'!$F$25 | W52: ='49'!$F$26 | X52: ='49'!$F$27 -> 9.18 | Y52: ='49'!$F$28 -> 19.03 | Z52: ='49'!$F$29 -> 6.45 | AA52: ='49'!$F$30 -> 8.61 | AB52: ='49'!$F$31 | AC52: ='49'!$F$32 | AD52: ='49'!$F$33 -> 7.59
A53: Wharton | B53: ='50'!$F$5 -> 10.1 | C53: ='50'!$F$6 -> 9.62 | D53: ='50'!$F$7 -> 6.64 | E53: ='50'!$F$8 -> 6.22 | F53: ='50'!$F$9 | G53: ='50'!$F$10 | H53: ='50'!$F$11 -> 9.04 | I53: ='50'!$F$12 | J53: ='50'!$F$13 -> 6.68 | K53: ='50'!$F$14 | L53: ='50'!$F$15 -> 8.69 | M53: ='50'!$F$16 -> 6.88 | N53: ='50'!$F$17 -> 6.32 | O53: ='50'!$F$18 -> 9.57 | P53: ='50'!$F$19 -> 12.76 | Q53: ='50'!$F$20 -> 8.18 | R53: ='50'!$F$21 | S53: ='50'!$F$22 -> 8.8 | T53: ='50'!$F$23 -> 6.81 | U53: ='50'!$F$24 -> 7.1 | V53: ='50'!$F$25 | W53: ='50'!$F$26 | X53: ='50'!$F$27 -> 7.2 | Y53: ='50'!$F$28 -> 8.31 | Z53: ='50'!$F$29 -> 6.06 | AA53: ='50'!$F$30 -> 8.24 | AB53: ='50'!$F$31 | AC53: ='50'!$F$32 | AD53: ='50'!$F$33 -> 7.18
A54: TSTC-Harlingen | B54: ='51'!$F$5 -> 6.78 | C54: ='51'!$F$6 -> 6.44 | D54: ='51'!$F$7 -> 5.82 | E54: ='51'!$F$8 -> 5.08 | F54: ='51'!$F$9 | G54: ='51'!$F$10 -> 5.79 | H54: ='51'!$F$11 -> 6.88 | I54: ='51'!$F$12 -> 12.76 | J54: ='51'!$F$13 -> 5.21 | K54: ='51'!$F$14 | L54: ='51'!$F$15 -> 6.39 | M54: ='51'!$F$16 -> 5.67 | N54: ='51'!$F$17 -> 4.21 | O54: ='51'!$F$18 -> 4.14 | P54: ='51'!$F$19 -> 8.62 | Q54: ='51'!$F$20 -> 7.57 | R54: ='51'!$F$21 | S54: ='51'!$F$22 | T54: ='51'!$F$23 -> 5.39 | U54: ='51'!$F$24 -> 6.16 | V54: ='51'!$F$25 -> 6.29 | W54: ='51'!$F$26 -> 6.34 | X54: ='51'!$F$27 | Y54: ='51'!$F$28 -> 4.27 | Z54: ='51'!$F$29 -> 5.05 | AA54: ='51'!$F$30 -> 5.79 | AB54: ='51'!$F$31 | AC54: ='51'!$F$32 | AD54: ='51'!$F$33 -> 5.94
A55: TSTC-West Texas | B55: ='52'!$F$5 | C55: ='52'!$F$6 -> 7.14 | D55: ='52'!$F$7 -> 8.1 | E55: ='52'!$F$8 -> 5.96 | F55: ='52'!$F$9 -> 87.95 | G55: ='52'!$F$10 -> 5.48 | H55: ='52'!$F$11 -> 5.97 | I55: ='52'!$F$12 -> 5.92 | J55: ='52'!$F$13 -> 6.72 | K55: ='52'!$F$14 | L55: ='52'!$F$15 -> 8.99 | M55: ='52'!$F$16 -> 5.83 | N55: ='52'!$F$17 -> 6.64 | O55: ='52'!$F$18 -> 7.28 | P55: ='52'!$F$19 | Q55: ='52'!$F$20 -> 4.67 | R55: ='52'!$F$21 -> 8.45 | S55: ='52'!$F$22 -> 5.16 | T55: ='52'!$F$23 -> 6.78 | U55: ='52'!$F$24 -> 5.95 | V55: ='52'!$F$25 -> 6.8 | W55: ='52'!$F$26 -> 8.95 | X55: ='52'!$F$27 | Y55: ='52'!$F$28 -> 5.03 | Z55: ='52'!$F$29 -> 5.23 | AA55: ='52'!$F$30 -> 6.91 | AB55: ='52'!$F$31 | AC55: ='52'!$F$32 | AD55: ='52'!$F$33 -> 6.2
A56: TSTC-Marshall | B56: ='53'!$F$5 -> 10.31 | C56: ='53'!$F$6 -> 10.31 | D56: ='53'!$F$7 -> 10.31 | E56: ='53'!$F$8 -> 7.07 | F56: ='53'!$F$9 | G56: ='53'!$F$10 -> 10.31 | H56: ='53'!$F$11 -> 7.07 | I56: ='53'!$F$12 -> 10.31 | J56: ='53'!$F$13 | K56: ='53'!$F$14 | L56: ='53'!$F$15 -> 10.31 | M56: ='53'!$F$16 -> 8.34 | N56: ='53'!$F$17 | O56: ='53'!$F$18 | P56: ='53'!$F$19 | Q56: ='53'!$F$20 | R56: ='53'!$F$21 | S56: ='53'!$F$22 | T56: ='53'!$F$23 -> 8.34 | U56: ='53'!$F$24 -> 9.69 | V56: ='53'!$F$25 -> 9.69 | W56: ='53'!$F$26 -> 10.31 | X56: ='53'!$F$27 | Y56: ='53'!$F$28 -> 7.07 | Z56: ='53'!$F$29 -> 7.35 | AA56: ='53'!$F$30 -> 7.07 | AB56: ='53'!$F$31 | AC56: ='53'!$F$32 | AD56: ='53'!$F$33 -> 9.08
A57: TSTC-Waco | B57: ='54'!$F$5 -> 6.95 | C57: ='54'!$F$6 -> 6.4 | D57: ='54'!$F$7 -> 7.76 | E57: ='54'!$F$8 -> 3.29 | F57: ='54'!$F$9 -> 18.92 | G57: ='54'!$F$10 -> 6.2 | H57: ='54'!$F$11 -> 9.12 | I57: ='54'!$F$12 -> 8.46 | J57: ='54'!$F$13 -> 6.21 | K57: ='54'!$F$14 -> 9.56 | L57: ='54'!$F$15 -> 8.73 | M57: ='54'!$F$16 -> 6.36 | N57: ='54'!$F$17 -> 4.92 | O57: ='54'!$F$18 -> 5.15 | P57: ='54'!$F$19 | Q57: ='54'!$F$20 -> 3.44 | R57: ='54'!$F$21 | S57: ='54'!$F$22 | T57: ='54'!$F$23 -> 6.41 | U57: ='54'!$F$24 -> 5.88 | V57: ='54'!$F$25 -> 6.27 | W57: ='54'!$F$26 -> 3.1 | X57: ='54'!$F$27 -> 10.57 | Y57: ='54'!$F$28 -> 3.3 | Z57: ='54'!$F$29 -> 6.55 | AA57: ='54'!$F$30 -> 6.23 | AB57: ='54'!$F$31 | AC57: ='54'!$F$32 | AD57: ='54'!$F$33 -> 6.91
A58: Lamar-IOT | B58: ='55'!$F$5 | C58: ='55'!$F$6 -> 8.46 | D58: ='55'!$F$7 -> 8.46 | E58: ='55'!$F$8 -> 8.46 | F58: ='55'!$F$9 | G58: ='55'!$F$10 | H58: ='55'!$F$11 -> 8.46 | I58: ='55'!$F$12 -> 8.46 | J58: ='55'!$F$13 -> 8.46 | K58: ='55'!$F$14 | L58: ='55'!$F$15 -> 8.46 | M58: ='55'!$F$16 -> 8.46 | N58: ='55'!$F$17 | O58: ='55'!$F$18 | P58: ='55'!$F$19 -> 8.46 | Q58: ='55'!$F$20 -> 8.46 | R58: ='55'!$F$21 -> 8.46 | S58: ='55'!$F$22 | T58: ='55'!$F$23 -> 8.46 | U58: ='55'!$F$24 -> 8.46 | V58: ='55'!$F$25 -> 8.46 | W58: ='55'!$F$26 -> 8.46 | X58: ='55'!$F$27 | Y58: ='55'!$F$28 -> 8.46 | Z58: ='55'!$F$29 -> 8.46 | AA58: ='55'!$F$30 -> 8.46 | AB58: ='55'!$F$31 | AC58: ='55'!$F$32 | AD58: ='55'!$F$33 -> 8.46
A59: Lamar-Orange | B59: ='56'!$F$5 -> 7.57 | C59: ='56'!$F$6 | D59: ='56'!$F$7 -> 7.57 | E59: ='56'!$F$8 -> 7.57 | F59: ='56'!$F$9 | G59: ='56'!$F$10 -> 7.57 | H59: ='56'!$F$11 -> 7.57 | I59: ='56'!$F$12 | J59: ='56'!$F$13 -> 7.57 | K59: ='56'!$F$14 | L59: ='56'!$F$15 -> 7.57 | M59: ='56'!$F$16 -> 7.57 | N59: ='56'!$F$17 -> 7.57 | O59: ='56'!$F$18 -> 7.57 | P59: ='56'!$F$19 | Q59: ='56'!$F$20 -> 7.95 | R59: ='56'!$F$21 | S59: ='56'!$F$22 -> 7.57 | T59: ='56'!$F$23 -> 7.57 | U59: ='56'!$F$24 | V59: ='56'!$F$25 | W59: ='56'!$F$26 | X59: ='56'!$F$27 -> 7.57 | Y59: ='56'!$F$28 -> 7.57 | Z59: ='56'!$F$29 -> 7.57 | AA59: ='56'!$F$30 -> 7.57 | AB59: ='56'!$F$31 | AC59: ='56'!$F$32 | AD59: ='56'!$F$33 -> 7.6
A60: Lamar-Port Arthur | B60: ='57'!$F$5 | C60: ='57'!$F$6 -> 7.95 | D60: ='57'!$F$7 -> 7.95 | E60: ='57'!$F$8 -> 7.95 | F60: ='57'!$F$9 | G60: ='57'!$F$10 -> 7.95 | H60: ='57'!$F$11 -> 7.95 | I60: ='57'!$F$12 -> 7.95 | J60: ='57'!$F$13 -> 7.95 | K60: ='57'!$F$14 | L60: ='57'!$F$15 -> 7.95 | M60: ='57'!$F$16 -> 7.95 | N60: ='57'!$F$17 -> 7.95 | O60: ='57'!$F$18 -> 7.95 | P60: ='57'!$F$19 | Q60: ='57'!$F$20 -> 7.95 | R60: ='57'!$F$21 | S60: ='57'!$F$22 -> 7.95 | T60: ='57'!$F$23 -> 7.95 | U60: ='57'!$F$24 -> 7.95 | V60: ='57'!$F$25 -> 7.95 | W60: ='57'!$F$26 -> 7.95 | X60: ='57'!$F$27 -> 7.95 | Y60: ='57'!$F$28 -> 7.95 | Z60: ='57'!$F$29 -> 7.95 | AA60: ='57'!$F$30 -> 7.95 | AB60: ='57'!$F$31 | AC60: ='57'!$F$32 | AD60: ='57'!$F$33 -> 7.95
A61: Total | B61: =Summary!$F$5 -> 7.18 | C61: =Summary!$F$6 -> 7.31 | D61: =Summary!$F$7 -> 5.86 | E61: =Summary!$F$8 -> 6.69 | F61: =Summary!$F$9 -> 13.77 | G61: =Summary!$F$10 -> 7.21 | H61: =Summary!$F$11 -> 6.94 | I61: =Summary!$F$12 -> 7.36 | J61: =Summary!$F$13 -> 5.49 | K61: =Summary!$F$14 -> 8.92 | L61: =Summary!$F$15 -> 7.23 | M61: =Summary!$F$16 -> 5.83 | N61: =Summary!$F$17 -> 6.14 | O61: =Summary!$F$18 -> 8.9 | P61: =Summary!$F$19 -> 12.53 | Q61: =Summary!$F$20 -> 6.78 | R61: =Summary!$F$21 -> 10.03 | S61: =Summary!$F$22 -> 6.54 | T61: =Summary!$F$23 -> 5.56 | U61: =Summary!$F$24 -> 7.05 | V61: =Summary!$F$25 -> 8.3 | W61: =Summary!$F$26 -> 7.14 | X61: =Summary!$F$27 -> 6.88 | Y61: =Summary!$F$28 -> 6.22 | Z61: =Summary!$F$29 -> 5.36 | AA61: =Summary!$F$30 -> 7.18 | AD61: =Summary!$F$33 -> 6.37
A62: Average (Excluding zero values) | B62: =AVERAGE(B$4:B$60) -> 7.9791304 | C62: =AVERAGE(C$4:C$60) -> 10.233455 | D62: =AVERAGE(D$4:D$60) -> 6.1235088 | E62: =AVERAGE(E$4:E$60) -> 6.7780702 | F62: =AVERAGE(F$4:F$60) -> 21.566667 | G62: =AVERAGE(G$4:G$60) -> 31.2802 | H62: =AVERAGE(H$4:H$60) -> 7.6692982 | I62: =AVERAGE(I$4:I$60) -> 11.316905 | ... AA62: =AVERAGE(AA$4:AA$60) -> 7.5163158 | AD62: =AVERAGE(AD$4:AD$60) -> 6.6024561
A63: High | B63: =MAX(B$4:B$60) -> 15.4 | C63: =MAX(C$4:C$60) -> 59.51 | D63: =MAX(D$4:D$60) -> 10.31 | E63: =MAX(E$4:E$60) -> 10.84 | F63: =MAX(F$4:F$60) -> 87.95 | G63: =MAX(G$4:G$60) -> 1087.17 | H63: =MAX(H$4:H$60) -> 23.62 | I63: =MAX(I$4:I$60) -> 112.33 | ... AA63: =MAX(AA$4:AA$60) -> 12.22 | AD63: =MAX(AD$4:AD$60) -> 10.12
A64: Low (Excluding zero values) | B64: =MIN(B$4:B$60) -> 3.06 | C64: =MIN(C$4:C$60) -> 3.66 | D64: =MIN(D$4:D$60) -> 3.15 | E64: =MIN(E$4:E$60) -> 2.89 | F64: =MIN(F$4:F$60) -> 7.87 | G64: =MIN(G$4:G$60) -> 2.41 | H64: =MIN(H$4:H$60) -> 3.74 | I64: =MIN(I$4:I$60) -> 3.54 | ... AA64: =MIN(AA$4:AA$60) -> 4.64 | AD64: =MIN(AD$4:AD$60) -> 4.2
A65: Median (Excluding zero values) | B65: =MEDIAN(B$4:B$60) -> 7.4 | C65: =MEDIAN(C$4:C$60) -> 7.48 | D65: =MEDIAN(D$4:D$60) -> 6.16 | E65: =MEDIAN(E$4:E$60) -> 6.8 | F65: =MEDIAN(F$4:F$60) -> 13.99 | G65: =MEDIAN(G$4:G$60) -> 7.34 | H65: =MEDIAN(H$4:H$60) -> 7.57 | I65: =MEDIAN(I$4:I$60) -> 7.755 | ... AA65: =MEDIAN(AA$4:AA$60) -> 7.51 | AD65: =MEDIAN(AD$4:AD$60) -> 6.65
B67: Discipline | L67: Discipline | V67: Discipline
B68: AG - Agriculture | L68: ENGR - Engineering Related | V68: MECH - Mechanics and Repairers - Diesel, Aviation Mechanics, and Transportation Workers
B69: ARCH - Architecture and Precision Production Trades | L69: LA - English Language, Lit, Philosophy, Humanities, & Interdisciplinary | V69: ELECT - Mechanics and Repairers - Electronics
B70: SCI - Biology, Physical Sciences, and Science Technology | L70: FL - Foreign Languages | V70: PE - Physical Education and Fitness
B71: BA - Business Management, Marketing, and Administrative Services | L71: HODA - Health Occupations - Dental Assistants, Medical Lab, and Assoc. Degree Nursing | V71: PA - Protective Services and Public Administration
B72: CP - Career Pilot | L72: HODH - Health Occupations - Dental Hygiene | V72: SS - Psychology, Social Sciences, and History
B73: COMM - Communications | L73: HOO - Health Occupations - Other | V73: FA - Visual and Performing Arts
B74: CS - Computer and Information Sciences | L74: HORT - Health Occupations - Respiratory Therapy
B75: CNSTR - Construction Trades | L75: NUR - Health Occupations - Vocational Nursing | V75: DEM - Developmental Education - Math
B76: HE - Consumer and Homemaking Education | L76: MATH - Mathematics | V76: DER - Developmental Education - Reading/Writing
B77: ENG - Engineering | L77: AUTO - Mechanics and Repairers - Automotive | V77: Total - All Disciplines

Sheet Discipline Analysis
A1: =Summary!A1 -> Community and Technical Colleges, Report of Fundable Operating Expenses, Fiscal Year (FY) 2003
A2: Discipline Analysis by Institution | X2: Discipline
A3: 29 | X3: Agriculture
X4: Architecture and Precision Production Trades
A5: Institution | B5: Contact Hours | C5: Total | E5: Faculty Salaries | G5: Library | I5: Institutional Support | K5: Student Services | M5: Departmental Operating Expense | O5: Instructional Administration | Q5: Organized Activities | S5: Equipment Depreciation | U5: Local Benefits | X5: Biology, Physical Sciences, and Science Technology
C6: Expense | D6: per Hour | E6: Expense | F6: per Hour | G6: Expense | H6: per Hour | I6: Expense | J6: per Hour | K6: Expense | L6: per Hour | M6: Expense | N6: per Hour | O6: Expense | P6: per Hour | Q6: Expense | R6: per Hour | S6: Expense | T6: per Hour | U6: Expense | V6: per Hour | X6: Business Management, Marketing, and Administrative Services
A7: Alamo | B7: =OFFSET('1'!$D$4,$A$3,0) -> 18861353 | C7: =OFFSET('1'!$E$4,$A$3,0) -> 1.4244558e+08 | D7: =OFFSET('1'!$F$4,$A$3,0) -> 7.55 | E7: =OFFSET('1'!$E$66,$A$3,0) -> 64902131 | F7: =OFFSET('1'!$F$66,$A$3,0) -> 3.44 | G7: =IFERROR('1'!$F$100*'Discipline Analysis'!$B7,"") -> 5847019.4 | H7: ='1'!$F$100 -> 0.31 | I7: =IFERROR('1'!$F$98*'Discipline Analysis'!$B7,"") -> 25651440 | J7: ='1'!$F$98 -> 1.36 | K7: =IFERROR('1'!$F$99*'Discipline Analysis'!$B7,"") -> 15089082 | L7: ='1'!$F$99 -> 0.8 | M7: =OFFSET('1'!$E$35,$A$3,0) -> 10718146 | N7: =OFFSET('1'!$F$35,$A$3,0) -> 0.57 | O7: =IFERROR('1'!$F$101*'Discipline Analysis'!$B7,"") -> 8298995.3 | P7: ='1'!$F$101 -> 0.44 | Q7: =IFERROR('1'!$F$102*'Discipline Analysis'!$B7,"") -> 377227.06 | R7: ='1'!$F$102 -> 0.02 | S7: =IFERROR('1'!$F$103*'Discipline Analysis'!$B7,"") -> 0 | T7: ='1'!$F$103 -> 0 | U7: =IFERROR('1'!$F$104*'Discipline Analysis'!$B7,"") -> 11694039 | V7: ='1'!$F$104 -> 0.62 | X7: Career Pilot
A8: Alvin | B8: =OFFSET('2'!$D$4,$A$3,0) -> 2395700 | C8: =OFFSET('2'!$E$4,$A$3,0) -> 16388766 | D8: =OFFSET('2'!$F$4,$A$3,0) -> 6.84 | E8: =OFFSET('2'!$E$66,$A$3,0) -> 7270811 | F8: =OFFSET('2'!$F$66,$A$3,0) -> 3.03 | G8: =IFERROR('2'!$F$100*'Discipline Analysis'!$B8,"") -> 479140 | H8: ='2'!$F$100 -> 0.2 | I8: =IFERROR('2'!$F$98*'Discipline Analysis'!$B8,"") -> 4120604 | J8: ='2'!$F$98 -> 1.72 | K8: =IFERROR('2'!$F$99*'Discipline Analysis'!$B8,"") -> 1317635 | L8: ='2'!$F$99 -> 0.55 | M8: =OFFSET('2'!$E$35,$A$3,0) -> 1592853 | N8: =OFFSET('2'!$F$35,$A$3,0) -> 0.66 | O8: =IFERROR('2'!$F$101*'Discipline Analysis'!$B8,"") -> 862452 | P8: ='2'!$F$101 -> 0.36 | Q8: =IFERROR('2'!$F$102*'Discipline Analysis'!$B8,"") | R8: ='2'!$F$102 | S8: =IFERROR('2'!$F$103*'Discipline Analysis'!$B8,"") | T8: ='2'!$F$103 | U8: =IFERROR('2'!$F$104*'Discipline Analysis'!$B8,"") -> 742667 | V8: ='2'!$F$104 -> 0.31 | X8: Communications
A9: Amarillo | B9: =OFFSET('3'!$D$4,$A$3,0) -> 4557502 | C9: =OFFSET('3'!$E$4,$A$3,0) -> 30374840 | D9: =OFFSET('3'!$F$4,$A$3,0) -> 6.66 | E9: =OFFSET('3'!$E$66,$A$3,0) -> 12143913 | F9: =OFFSET('3'!$F$66,$A$3,0) -> 2.66 | G9: =IFERROR('3'!$F$100*'Discipline Analysis'!$B9,"") -> 1093800.5 | H9: ='3'!$F$100 -> 0.24 | I9: =IFERROR('3'!$F$98*'Discipline Analysis'!$B9,"") -> 6790678 | J9: ='3'!$F$98 -> 1.49 | K9: =IFERROR('3'!$F$99*'Discipline Analysis'!$B9,"") -> 2688926.2 | L9: ='3'!$F$99 -> 0.59 | M9: =OFFSET('3'!$E$35,$A$3,0) -> 3477282 | N9: =OFFSET('3'!$F$35,$A$3,0) -> 0.76 | O9: =IFERROR('3'!$F$101*'Discipline Analysis'!$B9,"") -> 1184950.5 | P9: ='3'!$F$101 -> 0.26 | Q9: =IFERROR('3'!$F$102*'Discipline Analysis'!$B9,"") -> 319025.14 | R9: ='3'!$F$102 -> 0.07 | S9: =IFERROR('3'!$F$103*'Discipline Analysis'!$B9,"") | T9: ='3'!$F$103 | U9: =IFERROR('3'!$F$104*'Discipline Analysis'!$B9,"") -> 2643351.2 | V9: ='3'!$F$104 -> 0.58 | X9: Computer and Information Sciences
A10: Angelina | B10: =OFFSET('4'!$D$4,$A$3,0) -> 2446951 | C10: =OFFSET('4'!$E$4,$A$3,0) -> 11784710 | D10: =OFFSET('4'!$F$4,$A$3,0) -> 4.82 | E10: =OFFSET('4'!$E$66,$A$3,0) -> 6677243 | F10: =OFFSET('4'!$F$66,$A$3,0) -> 2.73 | G10: =IFERROR('4'!$F$100*'Discipline Analysis'!$B10,"") -> 342573.14 | H10: ='4'!$F$100 -> 0.14 | I10: =IFERROR('4'!$F$98*'Discipline Analysis'!$B10,"") -> 1541579.1 | J10: ='4'!$F$98 -> 0.63 | K10: =IFERROR('4'!$F$99*'Discipline Analysis'!$B10,"") -> 685146.28 | L10: ='4'!$F$99 -> 0.28 | M10: =OFFSET('4'!$E$35,$A$3,0) -> 839955 | N10: =OFFSET('4'!$F$35,$A$3,0) -> 0.34 | O10: =IFERROR('4'!$F$101*'Discipline Analysis'!$B10,"") -> 1296884 | P10: ='4'!$F$101 -> 0.53 | Q10: =IFERROR('4'!$F$102*'Discipline Analysis'!$B10,"") | R10: ='4'!$F$102 | S10: =IFERROR('4'!$F$103*'Discipline Analysis'!$B10,"") | T10: ='4'!$F$103 | U10: =IFERROR('4'!$F$104*'Discipline Analysis'!$B10,"") -> 367042.65 | V10: ='4'!$F$104 -> 0.15 | X10: Construction Trades
A11: Austin | B11: =OFFSET('5'!$D$4,$A$3,0) -> 11470713 | C11: =OFFSET('5'!$E$4,$A$3,0) -> 90033991 | D11: =OFFSET('5'!$F$4,$A$3,0) -> 7.85 | E11: =OFFSET('5'!$E$66,$A$3,0) -> 40874224 | F11: =OFFSET('5'!$F$66,$A$3,0) -> 3.56 | G11: =IFERROR('5'!$F$100*'Discipline Analysis'!$B11,"") -> 2523556.9 | H11: ='5'!$F$100 -> 0.22 | I11: =IFERROR('5'!$F$98*'Discipline Analysis'!$B11,"") -> 17894312 | J11: ='5'!$F$98 -> 1.56 | K11: =IFERROR('5'!$F$99*'Discipline Analysis'!$B11,"") -> 7685377.7 | L11: ='5'!$F$99 -> 0.67 | M11: =OFFSET('5'!$E$35,$A$3,0) -> 6573136 | N11: =OFFSET('5'!$F$35,$A$3,0) -> 0.57 | O11: =IFERROR('5'!$F$101*'Discipline Analysis'!$B11,"") -> 11011884 | P11: ='5'!$F$101 -> 0.96 | Q11: =IFERROR('5'!$F$102*'Discipline Analysis'!$B11,"") | R11: ='5'!$F$102 | S11: =IFERROR('5'!$F$103*'Discipline Analysis'!$B11,"") | T11: ='5'!$F$103 | U11: =IFERROR('5'!$F$104*'Discipline Analysis'!$B11,"") -> 3441213.9 | V11: ='5'!$F$104 -> 0.3 | X11: Consumer and Homemaking Education
A12: Blinn | B12: =OFFSET('6'!$D$4,$A$3,0) -> 6073151 | C12: =OFFSET('6'!$E$4,$A$3,0) -> 31537669 | D12: =OFFSET('6'!$F$4,$A$3,0) -> 5.19 | E12: =OFFSET('6'!$E$66,$A$3,0) -> 15468195 | F12: =OFFSET('6'!$F$66,$A$3,0) -> 2.55 | G12: =IFERROR('6'!$F$100*'Discipline Analysis'!$B12,"") -> 1032435.7 | H12: ='6'!$F$100 -> 0.17 | I12: =IFERROR('6'!$F$98*'Discipline Analysis'!$B12,"") -> 4190474.2 | J12: ='6'!$F$98 -> 0.69 | K12: =IFERROR('6'!$F$99*'Discipline Analysis'!$B12,"") -> 2732918 | L12: ='6'!$F$99 -> 0.45 | M12: =OFFSET('6'!$E$35,$A$3,0) -> 3094687 | N12: =OFFSET('6'!$F$35,$A$3,0) -> 0.51 | O12: =IFERROR('6'!$F$101*'Discipline Analysis'!$B12,"") -> 2550723.4 | P12: ='6'!$F$101 -> 0.42 | Q12: =IFERROR('6'!$F$102*'Discipline Analysis'!$B12,"") | R12: ='6'!$F$102 | S12: =IFERROR('6'!$F$103*'Discipline Analysis'!$B12,"") | T12: ='6'!$F$103 | U12: =IFERROR('6'!$F$104*'Discipline Analysis'!$B12,"") -> 2550723.4 | V12: ='6'!$F$104 -> 0.42 | X12: Engineering
A13: Brazosport | B13: =OFFSET('7'!$D$4,$A$3,0) -> 1607150 | C13: =OFFSET('7'!$E$4,$A$3,0) -> 11264114 | D13: =OFFSET('7'!$F$4,$A$3,0) -> 7.01 | E13: =OFFSET('7'!$E$66,$A$3,0) -> 4755920 | F13: =OFFSET('7'!$F$66,$A$3,0) -> 2.96 | G13: =IFERROR('7'!$F$100*'Discipline Analysis'!$B13,"") -> 610717 | H13: ='7'!$F$100 -> 0.38 | I13: =IFERROR('7'!$F$98*'Discipline Analysis'!$B13,"") -> 2844655.5 | J13: ='7'!$F$98 -> 1.77 | K13: =IFERROR('7'!$F$99*'Discipline Analysis'!$B13,"") -> 1125005 | L13: ='7'!$F$99 -> 0.7 | M13: =OFFSET('7'!$E$35,$A$3,0) -> 1160087 | N13: =OFFSET('7'!$F$35,$A$3,0) -> 0.72 | O13: =IFERROR('7'!$F$101*'Discipline Analysis'!$B13,"") -> 321430 | P13: ='7'!$F$101 -> 0.2 | Q13: =IFERROR('7'!$F$102*'Discipline Analysis'!$B13,"") | R13: ='7'!$F$102 | S13: =IFERROR('7'!$F$103*'Discipline Analysis'!$B13,"") | T13: ='7'!$F$103 | U13: =IFERROR('7'!$F$104*'Discipline Analysis'!$B13,"") -> 433930.5 | V13: ='7'!$F$104 -> 0.27 | X13: Engineering Related
A14: Central Texas | B14: =OFFSET('8'!$D$4,$A$3,0) -> 5416865 | C14: =OFFSET('8'!$E$4,$A$3,0) -> 28479940 | D14: =OFFSET('8'!$F$4,$A$3,0) -> 5.26 | E14: =OFFSET('8'!$E$66,$A$3,0) -> 9680820 | F14: =OFFSET('8'!$F$66,$A$3,0) -> 1.79 | G14: =IFERROR('8'!$F$100*'Discipline Analysis'!$B14,"") -> 920867.05 | H14: ='8'!$F$100 -> 0.17 | I14: =IFERROR('8'!$F$98*'Discipline Analysis'!$B14,"") -> 7746116.9 | J14: ='8'!$F$98 -> 1.43 | K14: =IFERROR('8'!$F$99*'Discipline Analysis'!$B14,"") -> 2925107.1 | L14: ='8'!$F$99 -> 0.54 | M14: =OFFSET('8'!$E$35,$A$3,0) -> 3397070 | N14: =OFFSET('8'!$F$35,$A$3,0) -> 0.63 | O14: =IFERROR('8'!$F$101*'Discipline Analysis'!$B14,"") -> 325011.9 | P14: ='8'!$F$101 -> 0.06 | Q14: =IFERROR('8'!$F$102*'Discipline Analysis'!$B14,"") -> 162505.95 | R14: ='8'!$F$102 -> 0.03 | S14: =IFERROR('8'!$F$103*'Discipline Analysis'!$B14,"") | T14: ='8'!$F$103 | U14: =IFERROR('8'!$F$104*'Discipline Analysis'!$B14,"") -> 3304287.6 | V14: ='8'!$F$104 -> 0.61 | X14: English Language, Lit, Philosophy, Humanities, & Interdisciplinary
A15: Cisco | B15: =OFFSET('9'!$D$4,$A$3,0) -> 1358099 | C15: =OFFSET('9'!$E$4,$A$3,0) -> 5709200 | D15: =OFFSET('9'!$F$4,$A$3,0) -> 4.2 | E15: =OFFSET('9'!$E$66,$A$3,0) -> 3167320 | F15: =OFFSET('9'!$F$66,$A$3,0) -> 2.33 | G15: =IFERROR('9'!$F$100*'Discipline Analysis'!$B15,"") -> 176552.87 | H15: ='9'!$F$100 -> 0.13 | I15: =IFERROR('9'!$F$98*'Discipline Analysis'!$B15,"") -> 1072898.2 | J15: ='9'!$F$98 -> 0.79 | K15: =IFERROR('9'!$F$99*'Discipline Analysis'!$B15,"") -> 624725.54 | L15: ='9'!$F$99 -> 0.46 | M15: =OFFSET('9'!$E$35,$A$3,0) -> 270635 | N15: =OFFSET('9'!$F$35,$A$3,0) -> 0.2 | O15: =IFERROR('9'!$F$101*'Discipline Analysis'!$B15,"") -> 217295.84 | P15: ='9'!$F$101 -> 0.16 | Q15: =IFERROR('9'!$F$102*'Discipline Analysis'!$B15,"") | R15: ='9'!$F$102 | S15: =IFERROR('9'!$F$103*'Discipline Analysis'!$B15,"") | T15: ='9'!$F$103 | U15: =IFERROR('9'!$F$104*'Discipline Analysis'!$B15,"") -> 190133.86 | V15: ='9'!$F$104 -> 0.14 | X15: Foreign Languages
A16: Clarendon | B16: =OFFSET('10'!$D$4,$A$3,0) -> 452668 | C16: =OFFSET('10'!$E$4,$A$3,0) -> 2960451 | D16: =OFFSET('10'!$F$4,$A$3,0) -> 6.54 | E16: =OFFSET('10'!$E$66,$A$3,0) -> 1374066 | F16: =OFFSET('10'!$F$66,$A$3,0) -> 3.04 | G16: =IFERROR('10'!$F$100*'Discipline Analysis'!$B16,"") -> 95060.28 | H16: ='10'!$F$100 -> 0.21 | I16: =IFERROR('10'!$F$98*'Discipline Analysis'!$B16,"") -> 751428.88 | J16: ='10'!$F$98 -> 1.66 | K16: =IFERROR('10'!$F$99*'Discipline Analysis'!$B16,"") -> 298760.88 | L16: ='10'!$F$99 -> 0.66 | M16: =OFFSET('10'!$E$35,$A$3,0) -> 182011 | N16: =OFFSET('10'!$F$35,$A$3,0) -> 0.4 | O16: =IFERROR('10'!$F$101*'Discipline Analysis'!$B16,"") -> 153907.12 | P16: ='10'!$F$101 -> 0.34 | Q16: =IFERROR('10'!$F$102*'Discipline Analysis'!$B16,"") | R16: ='10'!$F$102 | S16: =IFERROR('10'!$F$103*'Discipline Analysis'!$B16,"") | T16: ='10'!$F$103 | U16: =IFERROR('10'!$F$104*'Discipline Analysis'!$B16,"") -> 104113.64 | V16: ='10'!$F$104 -> 0.23 | X16: Health Occupations - Dental Assistants, Medical Lab, and Assoc. Degree Nursing
A17: Coastal Bend | B17: =OFFSET('11'!$D$4,$A$3,0) -> 2165992 | C17: =OFFSET('11'!$E$4,$A$3,0) -> 10871274 | D17: =OFFSET('11'!$F$4,$A$3,0) -> 5.02 | E17: =OFFSET('11'!$E$66,$A$3,0) -> 5227816 | F17: =OFFSET('11'!$F$66,$A$3,0) -> 2.41 | G17: =IFERROR('11'!$F$100*'Discipline Analysis'!$B17,"") -> 584817.84 | H17: ='11'!$F$100 -> 0.27 | I17: =IFERROR('11'!$F$98*'Discipline Analysis'!$B17,"") -> 2014372.6 | J17: ='11'!$F$98 -> 0.93 | K17: =IFERROR('11'!$F$99*'Discipline Analysis'!$B17,"") -> 823076.96 | L17: ='11'!$F$99 -> 0.38 | M17: =OFFSET('11'!$E$35,$A$3,0) -> 971794 | N17: =OFFSET('11'!$F$35,$A$3,0) -> 0.45 | O17: =IFERROR('11'!$F$101*'Discipline Analysis'!$B17,"") -> 801417.04 | P17: ='11'!$F$101 -> 0.37 | Q17: =IFERROR('11'!$F$102*'Discipline Analysis'!$B17,"") | R17: ='11'!$F$102 | S17: =IFERROR('11'!$F$103*'Discipline Analysis'!$B17,"") | T17: ='11'!$F$103 | U17: =IFERROR('11'!$F$104*'Discipline Analysis'!$B17,"") -> 454858.32 | V17: ='11'!$F$104 -> 0.21 | X17: Health Occupations - Dental Hygiene
A18: College Of The Mainland | B18: =OFFSET('12'!$D$4,$A$3,0) -> 1670139 | C18: =OFFSET('12'!$E$4,$A$3,0) -> 16899288 | D18: =OFFSET('12'!$F$4,$A$3,0) -> 10.12 | E18: =OFFSET('12'!$E$66,$A$3,0) -> 6143655 | F18: =OFFSET('12'!$F$66,$A$3,0) -> 3.68 | G18: =IFERROR('12'!$F$100*'Discipline Analysis'!$B18,"") -> 668055.6 | H18: ='12'!$F$100 -> 0.4 | I18: =IFERROR('12'!$F$98*'Discipline Analysis'!$B18,"") -> 4492673.9 | J18: ='12'!$F$98 -> 2.69 | K18: =IFERROR('12'!$F$99*'Discipline Analysis'!$B18,"") -> 1720243.2 | L18: ='12'!$F$99 -> 1.03 | M18: =OFFSET('12'!$E$35,$A$3,0) -> 1650735 | N18: =OFFSET('12'!$F$35,$A$3,0) -> 0.99 | O18: =IFERROR('12'!$F$101*'Discipline Analysis'!$B18,"") -> 450937.53 | P18: ='12'!$F$101 -> 0.27 | Q18: =IFERROR('12'!$F$102*'Discipline Analysis'!$B18,"") | R18: ='12'!$F$102 | S18: =IFERROR('12'!$F$103*'Discipline Analysis'!$B18,"") | T18: ='12'!$F$103 | U18: =IFERROR('12'!$F$104*'Discipline Analysis'!$B18,"") -> 1770347.3 | V18: ='12'!$F$104 -> 1.06 | X18: Health Occupations - Other
A19: Collin | B19: =OFFSET('13'!$D$4,$A$3,0) -> 7038051 | C19: =OFFSET('13'!$E$4,$A$3,0) -> 44821329 | D19: =OFFSET('13'!$F$4,$A$3,0) -> 6.37 | E19: =OFFSET('13'!$E$66,$A$3,0) -> 16757763 | F19: =OFFSET('13'!$F$66,$A$3,0) -> 2.38 | G19: =IFERROR('13'!$F$100*'Discipline Analysis'!$B19,"") -> 2955981.4 | H19: ='13'!$F$100 -> 0.42 | I19: =IFERROR('13'!$F$98*'Discipline Analysis'!$B19,"") -> 8445661.2 | J19: ='13'!$F$98 -> 1.2 | K19: =IFERROR('13'!$F$99*'Discipline Analysis'!$B19,"") -> 4504352.6 | L19: ='13'!$F$99 -> 0.64 | M19: =OFFSET('13'!$E$35,$A$3,0) -> 7914615 | N19: =OFFSET('13'!$F$35,$A$3,0) -> 1.12 | O19: =IFERROR('13'!$F$101*'Discipline Analysis'!$B19,"") -> 2815220.4 | P19: ='13'!$F$101 -> 0.4 | Q19: =IFERROR('13'!$F$102*'Discipline Analysis'!$B19,"") | R19: ='13'!$F$102 | S19: =IFERROR('13'!$F$103*'Discipline Analysis'!$B19,"") | T19: ='13'!$F$103 | U19: =IFERROR('13'!$F$104*'Discipline Analysis'!$B19,"") -> 1407610.2 | V19: ='13'!$F$104 -> 0.2 | X19: Health Occupations - Respiratory Therapy
A20: Dallas | B20: =OFFSET('14'!$D$4,$A$3,0) -> 25958904 | C20: =OFFSET('14'!$E$4,$A$3,0) -> 1.8229215e+08 | D20: =OFFSET('14'!$F$4,$A$3,0) -> 7.02 | E20: =OFFSET('14'!$E$66,$A$3,0) -> 68400835 | F20: =OFFSET('14'!$F$66,$A$3,0) -> 2.63 | G20: =IFERROR('14'!$F$100*'Discipline Analysis'!$B20,"") -> 7528082.2 | H20: ='14'!$F$100 -> 0.29 | I20: =IFERROR('14'!$F$98*'Discipline Analysis'!$B20,"") -> 40236301 | J20: ='14'!$F$98 -> 1.55 | K20: =IFERROR('14'!$F$99*'Discipline Analysis'!$B20,"") -> 18950000 | L20: ='14'!$F$99 -> 0.73 | M20: =OFFSET('14'!$E$35,$A$3,0) -> 32071549 | N20: =OFFSET('14'!$F$35,$A$3,0) -> 1.24 | O20: =IFERROR('14'!$F$101*'Discipline Analysis'!$B20,"") -> 5970547.9 | P20: ='14'!$F$101 -> 0.23 | Q20: =IFERROR('14'!$F$102*'Discipline Analysis'!$B20,"") -> 778767.12 | R20: ='14'!$F$102 -> 0.03 | S20: =IFERROR('14'!$F$103*'Discipline Analysis'!$B20,"") | T20: ='14'!$F$103 | U20: =IFERROR('14'!$F$104*'Discipline Analysis'!$B20,"") -> 8826027.4 | V20: ='14'!$F$104 -> 0.34 | X20: Health Occupations - Vocational Nursing
A21: Del Mar | B21: =OFFSET('15'!$D$4,$A$3,0) -> 5507011 | C21: =OFFSET('15'!$E$4,$A$3,0) -> 45788300 | D21: =OFFSET('15'!$F$4,$A$3,0) -> 8.31 | E21: =OFFSET('15'!$E$66,$A$3,0) -> 20193185 | F21: =OFFSET('15'!$F$66,$A$3,0) -> 3.67 | G21: =IFERROR('15'!$F$100*'Discipline Analysis'!$B21,"") -> 2312944.6 | H21: ='15'!$F$100 -> 0.42 | I21: =IFERROR('15'!$F$98*'Discipline Analysis'!$B21,"") -> 9031498 | J21: ='15'!$F$98 -> 1.64 | K21: =IFERROR('15'!$F$99*'Discipline Analysis'!$B21,"") -> 4846169.7 | L21: ='15'!$F$99 -> 0.88 | M21: =OFFSET('15'!$E$35,$A$3,0) -> 2291446 | N21: =OFFSET('15'!$F$35,$A$3,0) -> 0.42 | O21: =IFERROR('15'!$F$101*'Discipline Analysis'!$B21,"") -> 3138996.3 | P21: ='15'!$F$101 -> 0.57 | Q21: =IFERROR('15'!$F$102*'Discipline Analysis'!$B21,"") | R21: ='15'!$F$102 | S21: =IFERROR('15'!$F$103*'Discipline Analysis'!$B21,"") | T21: ='15'!$F$103 | U21: =IFERROR('15'!$F$104*'Discipline Analysis'!$B21,"") -> 4020118 | V21: ='15'!$F$104 -> 0.73 | X21: Mathematics
A22: El Paso | B22: =OFFSET('16'!$D$4,$A$3,0) -> 8917546 | C22: =OFFSET('16'!$E$4,$A$3,0) -> 62585427 | D22: =OFFSET('16'!$F$4,$A$3,0) -> 7.02 | E22: =OFFSET('16'!$E$66,$A$3,0) -> 24672263 | F22: =OFFSET('16'!$F$66,$A$3,0) -> 2.77 | G22: =IFERROR('16'!$F$100*'Discipline Analysis'!$B22,"") -> 2496912.9 | H22: ='16'!$F$100 -> 0.28 | I22: =IFERROR('16'!$F$98*'Discipline Analysis'!$B22,"") -> 14089723 | J22: ='16'!$F$98 -> 1.58 | K22: =IFERROR('16'!$F$99*'Discipline Analysis'!$B22,"") -> 6242282.2 | L22: ='16'!$F$99 -> 0.7 | M22: =OFFSET('16'!$E$35,$A$3,0) -> 4065331 | N22: =OFFSET('16'!$F$35,$A$3,0) -> 0.46 | O22: =IFERROR('16'!$F$101*'Discipline Analysis'!$B22,"") -> 6955685.9 | P22: ='16'!$F$101 -> 0.78 | Q22: =IFERROR('16'!$F$102*'Discipline Analysis'!$B22,"") -> 178350.92 | R22: ='16'!$F$102 -> 0.02 | S22: =IFERROR('16'!$F$103*'Discipline Analysis'!$B22,"") | T22: ='16'!$F$103 | U22: =IFERROR('16'!$F$104*'Discipline Analysis'!$B22,"") -> 3923720.2 | V22: ='16'!$F$104 -> 0.44 | X22: Mechanics and Repairers - Automotive
A23: Frank Phillips | B23: =OFFSET('17'!$D$4,$A$3,0) -> 727294 | C23: =OFFSET('17'!$E$4,$A$3,0) -> 4835883 | D23: =OFFSET('17'!$F$4,$A$3,0) -> 6.65 | E23: =OFFSET('17'!$E$66,$A$3,0) -> 1656102 | F23: =OFFSET('17'!$F$66,$A$3,0) -> 2.28 | G23: =IFERROR('17'!$F$100*'Discipline Analysis'!$B23,"") -> 123639.98 | H23: ='17'!$F$100 -> 0.17 | I23: =IFERROR('17'!$F$98*'Discipline Analysis'!$B23,"") -> 1316402.1 | J23: ='17'!$F$98 -> 1.81 | K23: =IFERROR('17'!$F$99*'Discipline Analysis'!$B23,"") -> 414557.58 | L23: ='17'!$F$99 -> 0.57 | M23: =OFFSET('17'!$E$35,$A$3,0) -> 1023559 | N23: =OFFSET('17'!$F$35,$A$3,0) -> 1.41 | O23: =IFERROR('17'!$F$101*'Discipline Analysis'!$B23,"") -> 65456.46 | P23: ='17'!$F$101 -> 0.09 | Q23: =IFERROR('17'!$F$102*'Discipline Analysis'!$B23,"") | R23: ='17'!$F$102 | S23: =IFERROR('17'!$F$103*'Discipline Analysis'!$B23,"") | T23: ='17'!$F$103 | U23: =IFERROR('17'!$F$104*'Discipline Analysis'!$B23,"") -> 232734.08 | V23: ='17'!$F$104 -> 0.32 | X23: Mechanics and Repairers - Diesel, Aviation Mechanics, and Transportation Workers
A24: Galveston | B24: =OFFSET('18'!$D$4,$A$3,0) -> 1159564 | C24: =OFFSET('18'!$E$4,$A$3,0) -> 9697114 | D24: =OFFSET('18'!$F$4,$A$3,0) -> 8.36 | E24: =OFFSET('18'!$E$66,$A$3,0) -> 3795121 | F24: =OFFSET('18'!$F$66,$A$3,0) -> 3.27 | G24: =IFERROR('18'!$F$100*'Discipline Analysis'!$B24,"") -> 289891 | H24: ='18'!$F$100 -> 0.25 | I24: =IFERROR('18'!$F$98*'Discipline Analysis'!$B24,"") -> 2562636.4 | J24: ='18'!$F$98 -> 2.21 | K24: =IFERROR('18'!$F$99*'Discipline Analysis'!$B24,"") -> 579782 | L24: ='18'!$F$99 -> 0.5 | M24: =OFFSET('18'!$E$35,$A$3,0) -> 839766 | N24: =OFFSET('18'!$F$35,$A$3,0) -> 0.72 | O24: =IFERROR('18'!$F$101*'Discipline Analysis'!$B24,"") -> 869673 | P24: ='18'!$F$101 -> 0.75 | Q24: =IFERROR('18'!$F$102*'Discipline Analysis'!$B24,"") | R24: ='18'!$F$102 | S24: =IFERROR('18'!$F$103*'Discipline Analysis'!$B24,"") | T24: ='18'!$F$103 | U24: =IFERROR('18'!$F$104*'Discipline Analysis'!$B24,"") -> 765312.24 | V24: ='18'!$F$104 -> 0.66 | X24: Mechanics and Repairers - Electronics
A25: Grayson | B25: =OFFSET('19'!$D$4,$A$3,0) -> 1705587 | C25: =OFFSET('19'!$E$4,$A$3,0) -> 9836812 | D25: =OFFSET('19'!$F$4,$A$3,0) -> 5.77 | E25: =OFFSET('19'!$E$66,$A$3,0) -> 5176444 | F25: =OFFSET('19'!$F$66,$A$3,0) -> 3.03 | G25: =IFERROR('19'!$F$100*'Discipline Analysis'!$B25,"") -> 324061.53 | H25: ='19'!$F$100 -> 0.19 | I25: =IFERROR('19'!$F$98*'Discipline Analysis'!$B25,"") -> 1637363.5 | J25: ='19'!$F$98 -> 0.96 | K25: =IFERROR('19'!$F$99*'Discipline Analysis'!$B25,"") -> 903961.11 | L25: ='19'!$F$99 -> 0.53 | M25: =OFFSET('19'!$E$35,$A$3,0) -> 557260 | N25: =OFFSET('19'!$F$35,$A$3,0) -> 0.33 | O25: =IFERROR('19'!$F$101*'Discipline Analysis'!$B25,"") -> 392285.01 | P25: ='19'!$F$101 -> 0.23 | Q25: =IFERROR('19'!$F$102*'Discipline Analysis'!$B25,"") | R25: ='19'!$F$102 | S25: =IFERROR('19'!$F$103*'Discipline Analysis'!$B25,"") | T25: ='19'!$F$103 | U25: =IFERROR('19'!$F$104*'Discipline Analysis'!$B25,"") -> 852793.5 | V25: ='19'!$F$104 -> 0.5 | X25: Physical Education and Fitness
A26: Hill | B26: =OFFSET('20'!$D$4,$A$3,0) -> 1716447 | C26: =OFFSET('20'!$E$4,$A$3,0) -> 7715563 | D26: =OFFSET('20'!$F$4,$A$3,0) -> 4.5 | E26: =OFFSET('20'!$E$66,$A$3,0) -> 3728620 | F26: =OFFSET('20'!$F$66,$A$3,0) -> 2.17 | G26: =IFERROR('20'!$F$100*'Discipline Analysis'!$B26,"") -> 532098.57 | H26: ='20'!$F$100 -> 0.31 | I26: =IFERROR('20'!$F$98*'Discipline Analysis'!$B26,"") -> 1458979.9 | J26: ='20'!$F$98 -> 0.85 | K26: =IFERROR('20'!$F$99*'Discipline Analysis'!$B26,"") -> 1012703.7 | L26: ='20'!$F$99 -> 0.59 | M26: =OFFSET('20'!$E$35,$A$3,0) -> 415044 | N26: =OFFSET('20'!$F$35,$A$3,0) -> 0.24 | O26: =IFERROR('20'!$F$101*'Discipline Analysis'!$B26,"") -> 360453.87 | P26: ='20'!$F$101 -> 0.21 | Q26: =IFERROR('20'!$F$102*'Discipline Analysis'!$B26,"") | R26: ='20'!$F$102 | S26: =IFERROR('20'!$F$103*'Discipline Analysis'!$B26,"") | T26: ='20'!$F$103 | U26: =IFERROR('20'!$F$104*'Discipline Analysis'!$B26,"") -> 188809.17 | V26: ='20'!$F$104 -> 0.11 | X26: Protective Services and Public Administration
A27: Houston | B27: =OFFSET('21'!$D$4,$A$3,0) -> 18161611 | C27: =OFFSET('21'!$E$4,$A$3,0) -> 1.5008447e+08 | D27: =OFFSET('21'!$F$4,$A$3,0) -> 8.26 | E27: =OFFSET('21'!$E$66,$A$3,0) -> 55100315 | F27: =OFFSET('21'!$F$66,$A$3,0) -> 3.03 | G27: =IFERROR('21'!$F$100*'Discipline Analysis'!$B27,"") -> 3813938.3 | H27: ='21'!$F$100 -> 0.21 | I27: =IFERROR('21'!$F$98*'Discipline Analysis'!$B27,"") -> 39229080 | J27: ='21'!$F$98 -> 2.16 | K27: =IFERROR('21'!$F$99*'Discipline Analysis'!$B27,"") -> 20704237 | L27: ='21'!$F$99 -> 1.14 | M27: =OFFSET('21'!$E$35,$A$3,0) -> 23223062 | N27: =OFFSET('21'!$F$35,$A$3,0) -> 1.28 | O27: =IFERROR('21'!$F$101*'Discipline Analysis'!$B27,"") -> 2905857.8 | P27: ='21'!$F$101 -> 0.16 | Q27: =IFERROR('21'!$F$102*'Discipline Analysis'!$B27,"") | R27: ='21'!$F$102 | S27: =IFERROR('21'!$F$103*'Discipline Analysis'!$B27,"") | T27: ='21'!$F$103 | U27: =IFERROR('21'!$F$104*'Discipline Analysis'!$B27,"") -> 5266867.2 | V27: ='21'!$F$104 -> 0.29 | X27: Psychology, Social Sciences, and History
A28: Howard | B28: =OFFSET('22'!$D$4,$A$3,0) -> 2248517 | C28: =OFFSET('22'!$E$4,$A$3,0) -> 13649317 | D28: =OFFSET('22'!$F$4,$A$3,0) -> 6.07 | E28: =OFFSET('22'!$E$66,$A$3,0) -> 5274558 | F28: =OFFSET('22'!$F$66,$A$3,0) -> 2.35 | G28: =IFERROR('22'!$F$100*'Discipline Analysis'!$B28,"") -> 179881.36 | H28: ='22'!$F$100 -> 0.08 | I28: =IFERROR('22'!$F$98*'Discipline Analysis'!$B28,"") -> 4182241.6 | J28: ='22'!$F$98 -> 1.86 | K28: =IFERROR('22'!$F$99*'Discipline Analysis'!$B28,"") -> 899406.8 | L28: ='22'!$F$99 -> 0.4 | M28: =OFFSET('22'!$E$35,$A$3,0) -> 1621363 | N28: =OFFSET('22'!$F$35,$A$3,0) -> 0.72 | O28: =IFERROR('22'!$F$101*'Discipline Analysis'!$B28,"") -> 584614.42 | P28: ='22'!$F$101 -> 0.26 | Q28: =IFERROR('22'!$F$102*'Discipline Analysis'!$B28,"") | R28: ='22'!$F$102 | S28: =IFERROR('22'!$F$103*'Discipline Analysis'!$B28,"") | T28: ='22'!$F$103 | U28: =IFERROR('22'!$F$104*'Discipline Analysis'!$B28,"") -> 899406.8 | V28: ='22'!$F$104 -> 0.4 | X28: Visual and Performing Arts
A29: Kilgore | B29: =OFFSET('23'!$D$4,$A$3,0) -> 3045509 | C29: =OFFSET('23'!$E$4,$A$3,0) -> 16036109 | D29: =OFFSET('23'!$F$4,$A$3,0) -> 5.27 | E29: =OFFSET('23'!$E$66,$A$3,0) -> 7636409 | F29: =OFFSET('23'!$F$66,$A$3,0) -> 2.51 | G29: =IFERROR('23'!$F$100*'Discipline Analysis'!$B29,"") -> 365461.08 | H29: ='23'!$F$100 -> 0.12 | I29: =IFERROR('23'!$F$98*'Discipline Analysis'!$B29,"") -> 2893233.5 | J29: ='23'!$F$98 -> 0.95 | K29: =IFERROR('23'!$F$99*'Discipline Analysis'!$B29,"") -> 1096383.2 | L29: ='23'!$F$99 -> 0.36 | M29: =OFFSET('23'!$E$35,$A$3,0) -> 1653173 | N29: =OFFSET('23'!$F$35,$A$3,0) -> 0.54 | O29: =IFERROR('23'!$F$101*'Discipline Analysis'!$B29,"") -> 1675030 | P29: ='23'!$F$101 -> 0.55 | Q29: =IFERROR('23'!$F$102*'Discipline Analysis'!$B29,"") | R29: ='23'!$F$102 | S29: =IFERROR('23'!$F$103*'Discipline Analysis'!$B29,"") | T29: ='23'!$F$103 | U29: =IFERROR('23'!$F$104*'Discipline Analysis'!$B29,"") -> 730922.16 | V29: ='23'!$F$104 -> 0.24 | X29: Developmental Education - Math
A30: Laredo | B30: =OFFSET('24'!$D$4,$A$3,0) -> 3237360 | C30: =OFFSET('24'!$E$4,$A$3,0) -> 24781083 | D30: =OFFSET('24'!$F$4,$A$3,0) -> 7.65 | E30: =OFFSET('24'!$E$66,$A$3,0) -> 11592282 | F30: =OFFSET('24'!$F$66,$A$3,0) -> 3.58 | G30: =IFERROR('24'!$F$100*'Discipline Analysis'!$B30,"") -> 1003581.6 | H30: ='24'!$F$100 -> 0.31 | I30: =IFERROR('24'!$F$98*'Discipline Analysis'!$B30,"") -> 4694172 | J30: ='24'!$F$98 -> 1.45 | K30: =IFERROR('24'!$F$99*'Discipline Analysis'!$B30,"") -> 2687008.8 | L30: ='24'!$F$99 -> 0.83 | M30: =OFFSET('24'!$E$35,$A$3,0) -> 1397202 | N30: =OFFSET('24'!$F$35,$A$3,0) -> 0.43 | O30: =IFERROR('24'!$F$101*'Discipline Analysis'!$B30,"") -> 809340 | P30: ='24'!$F$101 -> 0.25 | Q30: =IFERROR('24'!$F$102*'Discipline Analysis'!$B30,"") | R30: ='24'!$F$102 | S30: =IFERROR('24'!$F$103*'Discipline Analysis'!$B30,"") | T30: ='24'!$F$103 | U30: =IFERROR('24'!$F$104*'Discipline Analysis'!$B30,"") -> 2589888 | V30: ='24'!$F$104 -> 0.8 | X30: Developmental Education - Reading/Writing
A31: Lee | B31: =OFFSET('25'!$D$4,$A$3,0) -> 2907731 | C31: =OFFSET('25'!$E$4,$A$3,0) -> 22440330 | D31: =OFFSET('25'!$F$4,$A$3,0) -> 7.72 | E31: =OFFSET('25'!$E$66,$A$3,0) -> 10648895 | F31: =OFFSET('25'!$F$66,$A$3,0) -> 3.66 | G31: =IFERROR('25'!$F$100*'Discipline Analysis'!$B31,"") -> 668778.13 | H31: ='25'!$F$100 -> 0.23 | I31: =IFERROR('25'!$F$98*'Discipline Analysis'!$B31,"") -> 5117606.6 | J31: ='25'!$F$98 -> 1.76 | K31: =IFERROR('25'!$F$99*'Discipline Analysis'!$B31,"") -> 1453865.5 | L31: ='25'!$F$99 -> 0.5 | M31: =OFFSET('25'!$E$35,$A$3,0) -> 1372191 | N31: =OFFSET('25'!$F$35,$A$3,0) -> 0.47 | O31: =IFERROR('25'!$F$101*'Discipline Analysis'!$B31,"") -> 1221247 | P31: ='25'!$F$101 -> 0.42 | Q31: =IFERROR('25'!$F$102*'Discipline Analysis'!$B31,"") | R31: ='25'!$F$102 | S31: =IFERROR('25'!$F$103*'Discipline Analysis'!$B31,"") | T31: ='25'!$F$103 | U31: =IFERROR('25'!$F$104*'Discipline Analysis'!$B31,"") -> 1948179.8 | V31: ='25'!$F$104 -> 0.67 | X31: All Disciplines
A32: Lonestar | B32: =OFFSET('26'!$D$4,$A$3,0) -> 13273833 | C32: =OFFSET('26'!$E$4,$A$3,0) -> 95199422 | D32: =OFFSET('26'!$F$4,$A$3,0) -> 7.17 | E32: =OFFSET('26'!$E$66,$A$3,0) -> 39479297 | F32: =OFFSET('26'!$F$66,$A$3,0) -> 2.97 | G32: =IFERROR('26'!$F$100*'Discipline Analysis'!$B32,"") -> 4645841.5 | H32: ='26'!$F$100 -> 0.35 | I32: =IFERROR('26'!$F$98*'Discipline Analysis'!$B32,"") -> 15795861 | J32: ='26'!$F$98 -> 1.19 | K32: =IFERROR('26'!$F$99*'Discipline Analysis'!$B32,"") -> 9822636.4 | L32: ='26'!$F$99 -> 0.74 | M32: =OFFSET('26'!$E$35,$A$3,0) -> 10408643 | N32: =OFFSET('26'!$F$35,$A$3,0) -> 0.78 | O32: =IFERROR('26'!$F$101*'Discipline Analysis'!$B32,"") -> 10619066 | P32: ='26'!$F$101 -> 0.8 | Q32: =IFERROR('26'!$F$102*'Discipline Analysis'!$B32,"") | R32: ='26'!$F$102 | S32: =IFERROR('26'!$F$103*'Discipline Analysis'!$B32,"") | T32: ='26'!$F$103 | U32: =IFERROR('26'!$F$104*'Discipline Analysis'!$B32,"") -> 4380364.9 | V32: ='26'!$F$104 -> 0.33
A33: Mclennan | B33: =OFFSET('27'!$D$4,$A$3,0) -> 3565950 | C33: =OFFSET('27'!$E$4,$A$3,0) -> 21526573 | D33: =OFFSET('27'!$F$4,$A$3,0) -> 6.04 | E33: =OFFSET('27'!$E$66,$A$3,0) -> 10277429 | F33: =OFFSET('27'!$F$66,$A$3,0) -> 2.88 | G33: =IFERROR('27'!$F$100*'Discipline Analysis'!$B33,"") -> 1069785 | H33: ='27'!$F$100 -> 0.3 | I33: =IFERROR('27'!$F$98*'Discipline Analysis'!$B33,"") -> 4564416 | J33: ='27'!$F$98 -> 1.28 | K33: =IFERROR('27'!$F$99*'Discipline Analysis'!$B33,"") -> 1533358.5 | L33: ='27'!$F$99 -> 0.43 | M33: =OFFSET('27'!$E$35,$A$3,0) -> 2816752 | N33: =OFFSET('27'!$F$35,$A$3,0) -> 0.79 | O33: =IFERROR('27'!$F$101*'Discipline Analysis'!$B33,"") -> 499233 | P33: ='27'!$F$101 -> 0.14 | Q33: =IFERROR('27'!$F$102*'Discipline Analysis'!$B33,"") | R33: ='27'!$F$102 | S33: =IFERROR('27'!$F$103*'Discipline Analysis'!$B33,"") | T33: ='27'!$F$103 | U33: =IFERROR('27'!$F$104*'Discipline Analysis'!$B33,"") -> 784509 | V33: ='27'!$F$104 -> 0.22
A34: Midland | B34: =OFFSET('28'!$D$4,$A$3,0) -> 2388257 | C34: =OFFSET('28'!$E$4,$A$3,0) -> 18714675 | D34: =OFFSET('28'!$F$4,$A$3,0) -> 7.84 | E34: =OFFSET('28'!$E$66,$A$3,0) -> 7790777 | F34: =OFFSET('28'!$F$66,$A$3,0) -> 3.26 | G34: =IFERROR('28'!$F$100*'Discipline Analysis'!$B34,"") -> 453768.83 | H34: ='28'!$F$100 -> 0.19 | I34: =IFERROR('28'!$F$98*'Discipline Analysis'!$B34,"") -> 2674847.8 | J34: ='28'!$F$98 -> 1.12 | K34: =IFERROR('28'!$F$99*'Discipline Analysis'!$B34,"") -> 1432954.2 | L34: ='28'!$F$99 -> 0.6 | M34: =OFFSET('28'!$E$35,$A$3,0) -> 1768990 | N34: =OFFSET('28'!$F$35,$A$3,0) -> 0.74 | O34: =IFERROR('28'!$F$101*'Discipline Analysis'!$B34,"") -> 2603200.1 | P34: ='28'!$F$101 -> 1.09 | Q34: =IFERROR('28'!$F$102*'Discipline Analysis'!$B34,"") -> 286590.84 | R34: ='28'!$F$102 -> 0.12 | S34: =IFERROR('28'!$F$103*'Discipline Analysis'!$B34,"") | T34: ='28'!$F$103 | U34: =IFERROR('28'!$F$104*'Discipline Analysis'!$B34,"") -> 1719545 | V34: ='28'!$F$104 -> 0.72
A35: Navarro | B35: =OFFSET('29'!$D$4,$A$3,0) -> 2757812 | C35: =OFFSET('29'!$E$4,$A$3,0) -> 13432088 | D35: =OFFSET('29'!$F$4,$A$3,0) -> 4.87 | E35: =OFFSET('29'!$E$66,$A$3,0) -> 6627612 | F35: =OFFSET('29'!$F$66,$A$3,0) -> 2.4 | G35: =IFERROR('29'!$F$100*'Discipline Analysis'!$B35,"") -> 413671.8 | H35: ='29'!$F$100 -> 0.15 | I35: =IFERROR('29'!$F$98*'Discipline Analysis'!$B35,"") -> 2151093.4 | J35: ='29'!$F$98 -> 0.78 | K35: =IFERROR('29'!$F$99*'Discipline Analysis'!$B35,"") -> 1406484.1 | L35: ='29'!$F$99 -> 0.51 | M35: =OFFSET('29'!$E$35,$A$3,0) -> 539461 | N35: =OFFSET('29'!$F$35,$A$3,0) -> 0.2 | O35: =IFERROR('29'!$F$101*'Discipline Analysis'!$B35,"") -> 1075546.7 | P35: ='29'!$F$101 -> 0.39 | Q35: =IFERROR('29'!$F$102*'Discipline Analysis'!$B35,"") -> 193046.84 | R35: ='29'!$F$102 -> 0.07 | S35: =IFERROR('29'!$F$103*'Discipline Analysis'!$B35,"") | T35: ='29'!$F$103 | U35: =IFERROR('29'!$F$104*'Discipline Analysis'!$B35,"") -> 1020390.4 | V35: ='29'!$F$104 -> 0.37
A36: North Central Texas | B36: =OFFSET('30'!$D$4,$A$3,0) -> 2350358 | C36: =OFFSET('30'!$E$4,$A$3,0) -> 10944802 | D36: =OFFSET('30'!$F$4,$A$3,0) -> 4.66 | E36: =OFFSET('30'!$E$66,$A$3,0) -> 5342498 | F36: =OFFSET('30'!$F$66,$A$3,0) -> 2.27 | G36: =IFERROR('30'!$F$100*'Discipline Analysis'!$B36,"") -> 399560.86 | H36: ='30'!$F$100 -> 0.17 | I36: =IFERROR('30'!$F$98*'Discipline Analysis'!$B36,"") -> 1715761.3 | J36: ='30'!$F$98 -> 0.73 | K36: =IFERROR('30'!$F$99*'Discipline Analysis'!$B36,"") -> 869632.46 | L36: ='30'!$F$99 -> 0.37 | M36: =OFFSET('30'!$E$35,$A$3,0) -> 1044429 | N36: =OFFSET('30'!$F$35,$A$3,0) -> 0.44 | O36: =IFERROR('30'!$F$101*'Discipline Analysis'!$B36,"") -> 1034157.5 | P36: ='30'!$F$101 -> 0.44 | Q36: =IFERROR('30'!$F$102*'Discipline Analysis'!$B36,"") | R36: ='30'!$F$102 | S36: =IFERROR('30'!$F$103*'Discipline Analysis'!$B36,"") | T36: ='30'!$F$103 | U36: =IFERROR('30'!$F$104*'Discipline Analysis'!$B36,"") -> 540582.34 | V36: ='30'!$F$104 -> 0.23
A37: Northeast Texas | B37: =OFFSET('31'!$D$4,$A$3,0) -> 1105856 | C37: =OFFSET('31'!$E$4,$A$3,0) -> 7044285 | D37: =OFFSET('31'!$F$4,$A$3,0) -> 6.37 | E37: =OFFSET('31'!$E$66,$A$3,0) -> 3643005 | F37: =OFFSET('31'!$F$66,$A$3,0) -> 3.29 | G37: =IFERROR('31'!$F$100*'Discipline Analysis'!$B37,"") -> 254346.88 | H37: ='31'!$F$100 -> 0.23 | I37: =IFERROR('31'!$F$98*'Discipline Analysis'!$B37,"") -> 1703018.2 | J37: ='31'!$F$98 -> 1.54 | K37: =IFERROR('31'!$F$99*'Discipline Analysis'!$B37,"") -> 486576.64 | L37: ='31'!$F$99 -> 0.44 | M37: =OFFSET('31'!$E$35,$A$3,0) -> 387304 | N37: =OFFSET('31'!$F$35,$A$3,0) -> 0.35 | O37: =IFERROR('31'!$F$101*'Discipline Analysis'!$B37,"") -> 210112.64 | P37: ='31'!$F$101 -> 0.19 | Q37: =IFERROR('31'!$F$102*'Discipline Analysis'!$B37,"") -> 66351.36 | R37: ='31'!$F$102 -> 0.06 | S37: =IFERROR('31'!$F$103*'Discipline Analysis'!$B37,"") | T37: ='31'!$F$103 | U37: =IFERROR('31'!$F$104*'Discipline Analysis'!$B37,"") -> 287522.56 | V37: ='31'!$F$104 -> 0.26
A38: Odessa | B38: =OFFSET('32'!$D$4,$A$3,0) -> 2575268 | C38: =OFFSET('32'!$E$4,$A$3,0) -> 15638498 | D38: =OFFSET('32'!$F$4,$A$3,0) -> 6.07 | E38: =OFFSET('32'!$E$66,$A$3,0) -> 7230448 | F38: =OFFSET('32'!$F$66,$A$3,0) -> 2.81 | G38: =IFERROR('32'!$F$100*'Discipline Analysis'!$B38,"") -> 489300.92 | H38: ='32'!$F$100 -> 0.19 | I38: =IFERROR('32'!$F$98*'Discipline Analysis'!$B38,"") -> 2472257.3 | J38: ='32'!$F$98 -> 0.96 | K38: =IFERROR('32'!$F$99*'Discipline Analysis'!$B38,"") -> 1313386.7 | L38: ='32'!$F$99 -> 0.51 | M38: =OFFSET('32'!$E$35,$A$3,0) -> 1348623 | N38: =OFFSET('32'!$F$35,$A$3,0) -> 0.52 | O38: =IFERROR('32'!$F$101*'Discipline Analysis'!$B38,"") -> 1210376 | P38: ='32'!$F$101 -> 0.47 | Q38: =IFERROR('32'!$F$102*'Discipline Analysis'!$B38,"") -> 334784.84 | R38: ='32'!$F$102 -> 0.13 | S38: =IFERROR('32'!$F$103*'Discipline Analysis'!$B38,"") | T38: ='32'!$F$103 | U38: =IFERROR('32'!$F$104*'Discipline Analysis'!$B38,"") -> 1236128.6 | V38: ='32'!$F$104 -> 0.48
A39: Panola | B39: =OFFSET('33'!$D$4,$A$3,0) -> 954745 | C39: =OFFSET('33'!$E$4,$A$3,0) -> 7648703 | D39: =OFFSET('33'!$F$4,$A$3,0) -> 8.01 | E39: =OFFSET('33'!$E$66,$A$3,0) -> 3211587 | F39: =OFFSET('33'!$F$66,$A$3,0) -> 3.36 | G39: =IFERROR('33'!$F$100*'Discipline Analysis'!$B39,"") -> 324613.3 | H39: ='33'!$F$100 -> 0.34 | I39: =IFERROR('33'!$F$98*'Discipline Analysis'!$B39,"") -> 1384380.2 | J39: ='33'!$F$98 -> 1.45 | K39: =IFERROR('33'!$F$99*'Discipline Analysis'!$B39,"") -> 553752.1 | L39: ='33'!$F$99 -> 0.58 | M39: =OFFSET('33'!$E$35,$A$3,0) -> 847391 | N39: =OFFSET('33'!$F$35,$A$3,0) -> 0.89 | O39: =IFERROR('33'!$F$101*'Discipline Analysis'!$B39,"") -> 696963.85 | P39: ='33'!$F$101 -> 0.73 | Q39: =IFERROR('33'!$F$102*'Discipline Analysis'!$B39,"") | R39: ='33'!$F$102 | S39: =IFERROR('33'!$F$103*'Discipline Analysis'!$B39,"") | T39: ='33'!$F$103 | U39: =IFERROR('33'!$F$104*'Discipline Analysis'!$B39,"") -> 630131.7 | V39: ='33'!$F$104 -> 0.66
A40: Paris | B40: =OFFSET('34'!$D$4,$A$3,0) -> 2170679 | C40: =OFFSET('34'!$E$4,$A$3,0) -> 13377921 | D40: =OFFSET('34'!$F$4,$A$3,0) -> 6.16 | E40: =OFFSET('34'!$E$66,$A$3,0) -> 3841278 | F40: =OFFSET('34'!$F$66,$A$3,0) -> 1.77 | G40: =IFERROR('34'!$F$100*'Discipline Analysis'!$B40,"") -> 412429.01 | H40: ='34'!$F$100 -> 0.19 | I40: =IFERROR('34'!$F$98*'Discipline Analysis'!$B40,"") -> 4862321 | J40: ='34'!$F$98 -> 2.24 | K40: =IFERROR('34'!$F$99*'Discipline Analysis'!$B40,"") -> 672910.49 | L40: ='34'!$F$99 -> 0.31 | M40: =OFFSET('34'!$E$35,$A$3,0) -> 2138681 | N40: =OFFSET('34'!$F$35,$A$3,0) -> 0.99 | O40: =IFERROR('34'!$F$101*'Discipline Analysis'!$B40,"") -> 520962.96 | P40: ='34'!$F$101 -> 0.24 | Q40: =IFERROR('34'!$F$102*'Discipline Analysis'!$B40,"") -> 21706.79 | R40: ='34'!$F$102 -> 0.01 | S40: =IFERROR('34'!$F$103*'Discipline Analysis'!$B40,"") | T40: ='34'!$F$103 | U40: =IFERROR('34'!$F$104*'Discipline Analysis'!$B40,"") -> 889978.39 | V40: ='34'!$F$104 -> 0.41
A41: Ranger | B41: =OFFSET('35'!$D$4,$A$3,0) -> 458984 | C41: =OFFSET('35'!$E$4,$A$3,0) -> 2698348 | D41: =OFFSET('35'!$F$4,$A$3,0) -> 5.88 | E41: =OFFSET('35'!$E$66,$A$3,0) -> 1268593 | F41: =OFFSET('35'!$F$66,$A$3,0) -> 2.76 | G41: =IFERROR('35'!$F$100*'Discipline Analysis'!$B41,"") -> 91796.8 | H41: ='35'!$F$100 -> 0.2 | I41: =IFERROR('35'!$F$98*'Discipline Analysis'!$B41,"") -> 803222 | J41: ='35'!$F$98 -> 1.75 | K41: =IFERROR('35'!$F$99*'Discipline Analysis'!$B41,"") -> 266210.72 | L41: ='35'!$F$99 -> 0.58 | M41: =OFFSET('35'!$E$35,$A$3,0) -> 137948 | N41: =OFFSET('35'!$F$35,$A$3,0) -> 0.3 | O41: =IFERROR('35'!$F$101*'Discipline Analysis'!$B41,"") -> 133105.36 | P41: ='35'!$F$101 -> 0.29 | Q41: =IFERROR('35'!$F$102*'Discipline Analysis'!$B41,"") | R41: ='35'!$F$102 | S41: =IFERROR('35'!$F$103*'Discipline Analysis'!$B41,"") | T41: ='35'!$F$103 | U41: =IFERROR('35'!$F$104*'Discipline Analysis'!$B41,"") | V41: ='35'!$F$104
A42: San Jacinto | B42: =OFFSET('36'!$D$4,$A$3,0) -> 9944283 | C42: =OFFSET('36'!$E$4,$A$3,0) -> 68488942 | D42: =OFFSET('36'!$F$4,$A$3,0) -> 6.89 | E42: =OFFSET('36'!$E$66,$A$3,0) -> 31110180 | F42: =OFFSET('36'!$F$66,$A$3,0) -> 3.13 | G42: =IFERROR('36'!$F$100*'Discipline Analysis'!$B42,"") -> 1988856.6 | H42: ='36'!$F$100 -> 0.2 | I42: =IFERROR('36'!$F$98*'Discipline Analysis'!$B42,"") -> 12529797 | J42: ='36'!$F$98 -> 1.26 | K42: =IFERROR('36'!$F$99*'Discipline Analysis'!$B42,"") -> 6960998.1 | L42: ='36'!$F$99 -> 0.7 | M42: =OFFSET('36'!$E$35,$A$3,0) -> 7016386 | N42: =OFFSET('36'!$F$35,$A$3,0) -> 0.71 | O42: =IFERROR('36'!$F$101*'Discipline Analysis'!$B42,"") -> 4176598.9 | P42: ='36'!$F$101 -> 0.42 | Q42: =IFERROR('36'!$F$102*'Discipline Analysis'!$B42,"") | R42: ='36'!$F$102 | S42: =IFERROR('36'!$F$103*'Discipline Analysis'!$B42,"") | T42: ='36'!$F$103 | U42: =IFERROR('36'!$F$104*'Discipline Analysis'!$B42,"") -> 4773255.8 | V42: ='36'!$F$104 -> 0.48
A43: South Plains | B43: =OFFSET('37'!$D$4,$A$3,0) -> 4049744 | C43: =OFFSET('37'!$E$4,$A$3,0) -> 23387310 | D43: =OFFSET('37'!$F$4,$A$3,0) -> 5.78 | E43: =OFFSET('37'!$E$66,$A$3,0) -> 11883334 | F43: =OFFSET('37'!$F$66,$A$3,0) -> 2.93 | G43: =IFERROR('37'!$F$100*'Discipline Analysis'!$B43,"") -> 485969.28 | H43: ='37'!$F$100 -> 0.12 | I43: =IFERROR('37'!$F$98*'Discipline Analysis'!$B43,"") -> 2672831 | J43: ='37'!$F$98 -> 0.66 | K43: =IFERROR('37'!$F$99*'Discipline Analysis'!$B43,"") -> 2551338.7 | L43: ='37'!$F$99 -> 0.63 | M43: =OFFSET('37'!$E$35,$A$3,0) -> 1736601 | N43: =OFFSET('37'!$F$35,$A$3,0) -> 0.43 | O43: =IFERROR('37'!$F$101*'Discipline Analysis'!$B43,"") -> 890943.68 | P43: ='37'!$F$101 -> 0.22 | Q43: =IFERROR('37'!$F$102*'Discipline Analysis'!$B43,"") -> 283482.08 | R43: ='37'!$F$102 -> 0.07 | S43: =IFERROR('37'!$F$103*'Discipline Analysis'!$B43,"") | T43: ='37'!$F$103 | U43: =IFERROR('37'!$F$104*'Discipline Analysis'!$B43,"") -> 2834820.8 | V43: ='37'!$F$104 -> 0.7
A44: South Texas | B44: =OFFSET('38'!$D$4,$A$3,0) -> 6168422 | C44: =OFFSET('38'!$E$4,$A$3,0) -> 42436095 | D44: =OFFSET('38'!$F$4,$A$3,0) -> 6.88 | E44: =OFFSET('38'!$E$66,$A$3,0) -> 18495275 | F44: =OFFSET('38'!$F$66,$A$3,0) -> 3 | G44: =IFERROR('38'!$F$100*'Discipline Analysis'!$B44,"") -> 1110316 | H44: ='38'!$F$100 -> 0.18 | I44: =IFERROR('38'!$F$98*'Discipline Analysis'!$B44,"") -> 9190948.8 | J44: ='38'!$F$98 -> 1.49 | K44: =IFERROR('38'!$F$99*'Discipline Analysis'!$B44,"") -> 3639369 | L44: ='38'!$F$99 -> 0.59 | M44: =OFFSET('38'!$E$35,$A$3,0) -> 4208958 | N44: =OFFSET('38'!$F$35,$A$3,0) -> 0.68 | O44: =IFERROR('38'!$F$101*'Discipline Analysis'!$B44,"") -> 1912210.8 | P44: ='38'!$F$101 -> 0.31 | Q44: =IFERROR('38'!$F$102*'Discipline Analysis'!$B44,"") | R44: ='38'!$F$102 | S44: =IFERROR('38'!$F$103*'Discipline Analysis'!$B44,"") | T44: ='38'!$F$103 | U44: =IFERROR('38'!$F$104*'Discipline Analysis'!$B44,"") -> 3947790.1 | V44: ='38'!$F$104 -> 0.64
A45: Southwest Texas | B45: =OFFSET('39'!$D$4,$A$3,0) -> 2018805 | C45: =OFFSET('39'!$E$4,$A$3,0) -> 12560512 | D45: =OFFSET('39'!$F$4,$A$3,0) -> 6.22 | E45: =OFFSET('39'!$E$66,$A$3,0) -> 5417535 | F45: =OFFSET('39'!$F$66,$A$3,0) -> 2.68 | G45: =IFERROR('39'!$F$100*'Discipline Analysis'!$B45,"") -> 504701.25 | H45: ='39'!$F$100 -> 0.25 | I45: =IFERROR('39'!$F$98*'Discipline Analysis'!$B45,"") -> 2866703.1 | J45: ='39'!$F$98 -> 1.42 | K45: =IFERROR('39'!$F$99*'Discipline Analysis'!$B45,"") -> 847898.1 | L45: ='39'!$F$99 -> 0.42 | M45: =OFFSET('39'!$E$35,$A$3,0) -> 1473900 | N45: =OFFSET('39'!$F$35,$A$3,0) -> 0.73 | O45: =IFERROR('39'!$F$101*'Discipline Analysis'!$B45,"") -> 1069966.7 | P45: ='39'!$F$101 -> 0.53 | Q45: =IFERROR('39'!$F$102*'Discipline Analysis'!$B45,"") | R45: ='39'!$F$102 | S45: =IFERROR('39'!$F$103*'Discipline Analysis'!$B45,"") | T45: ='39'!$F$103 | U45: =IFERROR('39'!$F$104*'Discipline Analysis'!$B45,"") -> 383572.95 | V45: ='39'!$F$104 -> 0.19
A46: Tarrant | B46: =OFFSET('40'!$D$4,$A$3,0) -> 12762002 | C46: =OFFSET('40'!$E$4,$A$3,0) -> 88881670 | D46: =OFFSET('40'!$F$4,$A$3,0) -> 6.96 | E46: =OFFSET('40'!$E$66,$A$3,0) -> 34433710 | F46: =OFFSET('40'!$F$66,$A$3,0) -> 2.7 | G46: =IFERROR('40'!$F$100*'Discipline Analysis'!$B46,"") -> 5104800.8 | H46: ='40'!$F$100 -> 0.4 | I46: =IFERROR('40'!$F$98*'Discipline Analysis'!$B46,"") -> 15059162 | J46: ='40'!$F$98 -> 1.18 | K46: =IFERROR('40'!$F$99*'Discipline Analysis'!$B46,"") -> 9316261.5 | L46: ='40'!$F$99 -> 0.73 | M46: =OFFSET('40'!$E$35,$A$3,0) -> 11489984 | N46: =OFFSET('40'!$F$35,$A$3,0) -> 0.9 | O46: =IFERROR('40'!$F$101*'Discipline Analysis'!$B46,"") -> 3700980.6 | P46: ='40'!$F$101 -> 0.29 | Q46: =IFERROR('40'!$F$102*'Discipline Analysis'!$B46,"") | R46: ='40'!$F$102 | S46: =IFERROR('40'!$F$103*'Discipline Analysis'!$B46,"") | T46: ='40'!$F$103 | U46: =IFERROR('40'!$F$104*'Discipline Analysis'!$B46,"") -> 9826741.5 | V46: ='40'!$F$104 -> 0.77
A47: Temple | B47: =OFFSET('41'!$D$4,$A$3,0) -> 1734470 | C47: =OFFSET('41'!$E$4,$A$3,0) -> 11505858 | D47: =OFFSET('41'!$F$4,$A$3,0) -> 6.63 | E47: =OFFSET('41'!$E$66,$A$3,0) -> 5305267 | F47: =OFFSET('41'!$F$66,$A$3,0) -> 3.06 | G47: =IFERROR('41'!$F$100*'Discipline Analysis'!$B47,"") -> 329549.3 | H47: ='41'!$F$100 -> 0.19 | I47: =IFERROR('41'!$F$98*'Discipline Analysis'!$B47,"") -> 2740462.6 | J47: ='41'!$F$98 -> 1.58 | K47: =IFERROR('41'!$F$99*'Discipline Analysis'!$B47,"") -> 693788 | L47: ='41'!$F$99 -> 0.4 | M47: =OFFSET('41'!$E$35,$A$3,0) -> 1334828 | N47: =OFFSET('41'!$F$35,$A$3,0) -> 0.77 | O47: =IFERROR('41'!$F$101*'Discipline Analysis'!$B47,"") -> 346894 | P47: ='41'!$F$101 -> 0.2 | Q47: =IFERROR('41'!$F$102*'Discipline Analysis'!$B47,"") | R47: ='41'!$F$102 | S47: =IFERROR('41'!$F$103*'Discipline Analysis'!$B47,"") | T47: ='41'!$F$103 | U47: =IFERROR('41'!$F$104*'Discipline Analysis'!$B47,"") -> 763166.8 | V47: ='41'!$F$104 -> 0.44
A48: Texarkana | B48: =OFFSET('42'!$D$4,$A$3,0) -> 2392177 | C48: =OFFSET('42'!$E$4,$A$3,0) -> 13071569 | D48: =OFFSET('42'!$F$4,$A$3,0) -> 5.46 | E48: =OFFSET('42'!$E$66,$A$3,0) -> 6249014 | F48: =OFFSET('42'!$F$66,$A$3,0) -> 2.61 | G48: =IFERROR('42'!$F$100*'Discipline Analysis'!$B48,"") -> 406670.09 | H48: ='42'!$F$100 -> 0.17 | I48: =IFERROR('42'!$F$98*'Discipline Analysis'!$B48,"") -> 3181595.4 | J48: ='42'!$F$98 -> 1.33 | K48: =IFERROR('42'!$F$99*'Discipline Analysis'!$B48,"") -> 621966.02 | L48: ='42'!$F$99 -> 0.26 | M48: =OFFSET('42'!$E$35,$A$3,0) -> 808050 | N48: =OFFSET('42'!$F$35,$A$3,0) -> 0.34 | O48: =IFERROR('42'!$F$101*'Discipline Analysis'!$B48,"") -> 765496.64 | P48: ='42'!$F$101 -> 0.32 | Q48: =IFERROR('42'!$F$102*'Discipline Analysis'!$B48,"") | R48: ='42'!$F$102 | S48: =IFERROR('42'!$F$103*'Discipline Analysis'!$B48,"") | T48: ='42'!$F$103 | U48: =IFERROR('42'!$F$104*'Discipline Analysis'!$B48,"") -> 1052557.9 | V48: ='42'!$F$104 -> 0.44
A49: Texas Southmost | B49: =OFFSET('43'!$D$4,$A$3,0) -> 3448559 | C49: =OFFSET('43'!$E$4,$A$3,0) -> 26810377 | D49: =OFFSET('43'!$F$4,$A$3,0) -> 7.77 | E49: =OFFSET('43'!$E$66,$A$3,0) -> 8093074 | F49: =OFFSET('43'!$F$66,$A$3,0) -> 2.35 | G49: =IFERROR('43'!$F$100*'Discipline Analysis'!$B49,"") -> 620740.62 | H49: ='43'!$F$100 -> 0.18 | I49: =IFERROR('43'!$F$98*'Discipline Analysis'!$B49,"") -> 5724607.9 | J49: ='43'!$F$98 -> 1.66 | K49: =IFERROR('43'!$F$99*'Discipline Analysis'!$B49,"") -> 3517530.2 | L49: ='43'!$F$99 -> 1.02 | M49: =OFFSET('43'!$E$35,$A$3,0) -> 2653174 | N49: =OFFSET('43'!$F$35,$A$3,0) -> 0.77 | O49: =IFERROR('43'!$F$101*'Discipline Analysis'!$B49,"") -> 2931275.1 | P49: ='43'!$F$101 -> 0.85 | Q49: =IFERROR('43'!$F$102*'Discipline Analysis'!$B49,"") | R49: ='43'!$F$102 | S49: =IFERROR('43'!$F$103*'Discipline Analysis'!$B49,"") | T49: ='43'!$F$103 | U49: =IFERROR('43'!$F$104*'Discipline Analysis'!$B49,"") -> 3241645.5 | V49: ='43'!$F$104 -> 0.94
A50: Trinity Valley | B50: =OFFSET('44'!$D$4,$A$3,0) -> 3167969 | C50: =OFFSET('44'!$E$4,$A$3,0) -> 14988810 | D50: =OFFSET('44'!$F$4,$A$3,0) -> 4.73 | E50: =OFFSET('44'!$E$66,$A$3,0) -> 7212605 | F50: =OFFSET('44'!$F$66,$A$3,0) -> 2.28 | G50: =IFERROR('44'!$F$100*'Discipline Analysis'!$B50,"") -> 601914.11 | H50: ='44'!$F$100 -> 0.19 | I50: =IFERROR('44'!$F$98*'Discipline Analysis'!$B50,"") -> 2280937.7 | J50: ='44'!$F$98 -> 0.72 | K50: =IFERROR('44'!$F$99*'Discipline Analysis'!$B50,"") -> 1330547 | L50: ='44'!$F$99 -> 0.42 | M50: =OFFSET('44'!$E$35,$A$3,0) -> 805084 | N50: =OFFSET('44'!$F$35,$A$3,0) -> 0.25 | O50: =IFERROR('44'!$F$101*'Discipline Analysis'!$B50,"") -> 918711.01 | P50: ='44'!$F$101 -> 0.29 | Q50: =IFERROR('44'!$F$102*'Discipline Analysis'!$B50,"") -> 253437.52 | R50: ='44'!$F$102 -> 0.08 | S50: =IFERROR('44'!$F$103*'Discipline Analysis'!$B50,"") | T50: ='44'!$F$103 | U50: =IFERROR('44'!$F$104*'Discipline Analysis'!$B50,"") -> 1583984.5 | V50: ='44'!$F$104 -> 0.5
A51: Tyler | B51: =OFFSET('45'!$D$4,$A$3,0) -> 4738921 | C51: =OFFSET('45'!$E$4,$A$3,0) -> 26888895 | D51: =OFFSET('45'!$F$4,$A$3,0) -> 5.67 | E51: =OFFSET('45'!$E$66,$A$3,0) -> 12425371 | F51: =OFFSET('45'!$F$66,$A$3,0) -> 2.62 | G51: =IFERROR('45'!$F$100*'Discipline Analysis'!$B51,"") -> 853005.78 | H51: ='45'!$F$100 -> 0.18 | I51: =IFERROR('45'!$F$98*'Discipline Analysis'!$B51,"") -> 4454585.7 | J51: ='45'!$F$98 -> 0.94 | K51: =IFERROR('45'!$F$99*'Discipline Analysis'!$B51,"") -> 3222466.3 | L51: ='45'!$F$99 -> 0.68 | M51: =OFFSET('45'!$E$35,$A$3,0) -> 3355426 | N51: =OFFSET('45'!$F$35,$A$3,0) -> 0.71 | O51: =IFERROR('45'!$F$101*'Discipline Analysis'!$B51,"") -> 1184730.2 | P51: ='45'!$F$101 -> 0.25 | Q51: =IFERROR('45'!$F$102*'Discipline Analysis'!$B51,"") | R51: ='45'!$F$102 | S51: =IFERROR('45'!$F$103*'Discipline Analysis'!$B51,"") | T51: ='45'!$F$103 | U51: =IFERROR('45'!$F$104*'Discipline Analysis'!$B51,"") -> 1421676.3 | V51: ='45'!$F$104 -> 0.3
A52: Vernon | B52: =OFFSET('46'!$D$4,$A$3,0) -> 1553039 | C52: =OFFSET('46'!$E$4,$A$3,0) -> 7831299 | D52: =OFFSET('46'!$F$4,$A$3,0) -> 5.04 | E52: =OFFSET('46'!$E$66,$A$3,0) -> 3578746 | F52: =OFFSET('46'!$F$66,$A$3,0) -> 2.3 | G52: =IFERROR('46'!$F$100*'Discipline Analysis'!$B52,"") -> 326138.19 | H52: ='46'!$F$100 -> 0.21 | I52: =IFERROR('46'!$F$98*'Discipline Analysis'!$B52,"") -> 1382204.7 | J52: ='46'!$F$98 -> 0.89 | K52: =IFERROR('46'!$F$99*'Discipline Analysis'!$B52,"") -> 807580.28 | L52: ='46'!$F$99 -> 0.52 | M52: =OFFSET('46'!$E$35,$A$3,0) -> 526612 | N52: =OFFSET('46'!$F$35,$A$3,0) -> 0.34 | O52: =IFERROR('46'!$F$101*'Discipline Analysis'!$B52,"") -> 1180309.6 | P52: ='46'!$F$101 -> 0.76 | Q52: =IFERROR('46'!$F$102*'Discipline Analysis'!$B52,"") -> 15530.39 | R52: ='46'!$F$102 -> 0.01 | S52: =IFERROR('46'!$F$103*'Discipline Analysis'!$B52,"") | T52: ='46'!$F$103 | U52: =IFERROR('46'!$F$104*'Discipline Analysis'!$B52,"") | V52: ='46'!$F$104
A53: Victoria | B53: =OFFSET('47'!$D$4,$A$3,0) -> 1832313 | C53: =OFFSET('47'!$E$4,$A$3,0) -> 12605215 | D53: =OFFSET('47'!$F$4,$A$3,0) -> 6.88 | E53: =OFFSET('47'!$E$66,$A$3,0) -> 6177890 | F53: =OFFSET('47'!$F$66,$A$3,0) -> 3.37 | G53: =IFERROR('47'!$F$100*'Discipline Analysis'!$B53,"") -> 604663.29 | H53: ='47'!$F$100 -> 0.33 | I53: =IFERROR('47'!$F$98*'Discipline Analysis'!$B53,"") -> 2107159.9 | J53: ='47'!$F$98 -> 1.15 | K53: =IFERROR('47'!$F$99*'Discipline Analysis'!$B53,"") -> 1026095.3 | L53: ='47'!$F$99 -> 0.56 | M53: =OFFSET('47'!$E$35,$A$3,0) -> 1127825 | N53: =OFFSET('47'!$F$35,$A$3,0) -> 0.62 | O53: =IFERROR('47'!$F$101*'Discipline Analysis'!$B53,"") -> 476401.38 | P53: ='47'!$F$101 -> 0.26 | Q53: =IFERROR('47'!$F$102*'Discipline Analysis'!$B53,"") | R53: ='47'!$F$102 | S53: =IFERROR('47'!$F$103*'Discipline Analysis'!$B53,"") | T53: ='47'!$F$103 | U53: =IFERROR('47'!$F$104*'Discipline Analysis'!$B53,"") -> 1081064.7 | V53: ='47'!$F$104 -> 0.59
A54: Weatherford | B54: =OFFSET('48'!$D$4,$A$3,0) -> 2203299 | C54: =OFFSET('48'!$E$4,$A$3,0) -> 11934437 | D54: =OFFSET('48'!$F$4,$A$3,0) -> 5.42 | E54: =OFFSET('48'!$E$66,$A$3,0) -> 5330285 | F54: =OFFSET('48'!$F$66,$A$3,0) -> 2.42 | G54: =IFERROR('48'!$F$100*'Discipline Analysis'!$B54,"") -> 418626.81 | H54: ='48'!$F$100 -> 0.19 | I54: =IFERROR('48'!$F$98*'Discipline Analysis'!$B54,"") -> 3128684.6 | J54: ='48'!$F$98 -> 1.42 | K54: =IFERROR('48'!$F$99*'Discipline Analysis'!$B54,"") -> 947418.57 | L54: ='48'!$F$99 -> 0.43 | M54: =OFFSET('48'!$E$35,$A$3,0) -> 1548692 | N54: =OFFSET('48'!$F$35,$A$3,0) -> 0.7 | O54: =IFERROR('48'!$F$101*'Discipline Analysis'!$B54,"") -> 440659.8 | P54: ='48'!$F$101 -> 0.2 | Q54: =IFERROR('48'!$F$102*'Discipline Analysis'!$B54,"") | R54: ='48'!$F$102 | S54: =IFERROR('48'!$F$103*'Discipline Analysis'!$B54,"") | T54: ='48'!$F$103 | U54: =IFERROR('48'!$F$104*'Discipline Analysis'!$B54,"") -> 132197.94 | V54: ='48'!$F$104 -> 0.06
A55: Western Texas | B55: =OFFSET('49'!$D$4,$A$3,0) -> 683936 | C55: =OFFSET('49'!$E$4,$A$3,0) -> 5189446 | D55: =OFFSET('49'!$F$4,$A$3,0) -> 7.59 | E55: =OFFSET('49'!$E$66,$A$3,0) -> 1863538 | F55: =OFFSET('49'!$F$66,$A$3,0) -> 2.72 | G55: =IFERROR('49'!$F$100*'Discipline Analysis'!$B55,"") -> 88911.68 | H55: ='49'!$F$100 -> 0.13 | I55: =IFERROR('49'!$F$98*'Discipline Analysis'!$B55,"") -> 1785073 | J55: ='49'!$F$98 -> 2.61 | K55: =IFERROR('49'!$F$99*'Discipline Analysis'!$B55,"") -> 348807.36 | L55: ='49'!$F$99 -> 0.51 | M55: =OFFSET('49'!$E$35,$A$3,0) -> 326247 | N55: =OFFSET('49'!$F$35,$A$3,0) -> 0.48 | O55: =IFERROR('49'!$F$101*'Discipline Analysis'!$B55,"") -> 718132.8 | P55: ='49'!$F$101 -> 1.05 | Q55: =IFERROR('49'!$F$102*'Discipline Analysis'!$B55,"") | R55: ='49'!$F$102 | S55: =IFERROR('49'!$F$103*'Discipline Analysis'!$B55,"") | T55: ='49'!$F$103 | U55: =IFERROR('49'!$F$104*'Discipline Analysis'!$B55,"") -> 54714.88 | V55: ='49'!$F$104 -> 0.08
A56: Wharton | B56: =OFFSET('50'!$D$4,$A$3,0) -> 2517164 | C56: =OFFSET('50'!$E$4,$A$3,0) -> 18066033 | D56: =OFFSET('50'!$F$4,$A$3,0) -> 7.18 | E56: =OFFSET('50'!$E$66,$A$3,0) -> 6713709 | F56: =OFFSET('50'!$F$66,$A$3,0) -> 2.67 | G56: =IFERROR('50'!$F$100*'Discipline Analysis'!$B56,"") -> 453089.52 | H56: ='50'!$F$100 -> 0.18 | I56: =IFERROR('50'!$F$98*'Discipline Analysis'!$B56,"") -> 6292910 | J56: ='50'!$F$98 -> 2.5 | K56: =IFERROR('50'!$F$99*'Discipline Analysis'!$B56,"") -> 1107552.2 | L56: ='50'!$F$99 -> 0.44 | M56: =OFFSET('50'!$E$35,$A$3,0) -> 815595 | N56: =OFFSET('50'!$F$35,$A$3,0) -> 0.32 | O56: =IFERROR('50'!$F$101*'Discipline Analysis'!$B56,"") -> 1233410.4 | P56: ='50'!$F$101 -> 0.49 | Q56: =IFERROR('50'!$F$102*'Discipline Analysis'!$B56,"") | R56: ='50'!$F$102 | S56: =IFERROR('50'!$F$103*'Discipline Analysis'!$B56,"") | T56: ='50'!$F$103 | U56: =IFERROR('50'!$F$104*'Discipline Analysis'!$B56,"") -> 1434783.5 | V56: ='50'!$F$104 -> 0.57
A57: TSTC-Harlingen | B57: =OFFSET('51'!$D$4,$A$3,0) -> 3054722 | C57: =OFFSET('51'!$E$4,$A$3,0) -> 18130551 | D57: =OFFSET('51'!$F$4,$A$3,0) -> 5.94 | E57: =OFFSET('51'!$E$66,$A$3,0) -> 7678778 | F57: =OFFSET('51'!$F$66,$A$3,0) -> 2.51 | G57: =IFERROR('51'!$F$100*'Discipline Analysis'!$B57,"") -> 458208.3 | H57: ='51'!$F$100 -> 0.15 | I57: =IFERROR('51'!$F$98*'Discipline Analysis'!$B57,"") -> 3421288.6 | J57: ='51'!$F$98 -> 1.12 | K57: =IFERROR('51'!$F$99*'Discipline Analysis'!$B57,"") -> 1374624.9 | L57: ='51'!$F$99 -> 0.45 | M57: =OFFSET('51'!$E$35,$A$3,0) -> 4031260 | N57: =OFFSET('51'!$F$35,$A$3,0) -> 1.32 | O57: =IFERROR('51'!$F$101*'Discipline Analysis'!$B57,"") -> 458208.3 | P57: ='51'!$F$101 -> 0.15 | Q57: =IFERROR('51'!$F$102*'Discipline Analysis'!$B57,"") | R57: ='51'!$F$102 | S57: =IFERROR('51'!$F$103*'Discipline Analysis'!$B57,"") | T57: ='51'!$F$103 | U57: =IFERROR('51'!$F$104*'Discipline Analysis'!$B57,"") -> 733133.28 | V57: ='51'!$F$104 -> 0.24
A58: TSTC-West Texas | B58: =OFFSET('52'!$D$4,$A$3,0) -> 1930928 | C58: =OFFSET('52'!$E$4,$A$3,0) -> 11967327 | D58: =OFFSET('52'!$F$4,$A$3,0) -> 6.2 | E58: =OFFSET('52'!$E$66,$A$3,0) -> 5063887 | F58: =OFFSET('52'!$F$66,$A$3,0) -> 2.62 | G58: =IFERROR('52'!$F$100*'Discipline Analysis'!$B58,"") -> 173783.52 | H58: ='52'!$F$100 -> 0.09 | I58: =IFERROR('52'!$F$98*'Discipline Analysis'!$B58,"") -> 2143330.1 | J58: ='52'!$F$98 -> 1.11 | K58: =IFERROR('52'!$F$99*'Discipline Analysis'!$B58,"") -> 1428886.7 | L58: ='52'!$F$99 -> 0.74 | M58: =OFFSET('52'!$E$35,$A$3,0) -> 2486914 | N58: =OFFSET('52'!$F$35,$A$3,0) -> 1.29 | O58: =IFERROR('52'!$F$101*'Discipline Analysis'!$B58,"") -> 270329.92 | P58: ='52'!$F$101 -> 0.14 | Q58: =IFERROR('52'!$F$102*'Discipline Analysis'!$B58,"") | R58: ='52'!$F$102 | S58: =IFERROR('52'!$F$103*'Discipline Analysis'!$B58,"") | T58: ='52'!$F$103 | U58: =IFERROR('52'!$F$104*'Discipline Analysis'!$B58,"") -> 405494.88 | V58: ='52'!$F$104 -> 0.21
A59: TSTC-Marshall | B59: =OFFSET('53'!$D$4,$A$3,0) -> 519896 | C59: =OFFSET('53'!$E$4,$A$3,0) -> 4718585 | D59: =OFFSET('53'!$F$4,$A$3,0) -> 9.08 | E59: =OFFSET('53'!$E$66,$A$3,0) -> 1649770 | F59: =OFFSET('53'!$F$66,$A$3,0) -> 3.17 | G59: =IFERROR('53'!$F$100*'Discipline Analysis'!$B59,"") -> 135172.96 | H59: ='53'!$F$100 -> 0.26 | I59: =IFERROR('53'!$F$98*'Discipline Analysis'!$B59,"") -> 1102179.5 | J59: ='53'!$F$98 -> 2.12 | K59: =IFERROR('53'!$F$99*'Discipline Analysis'!$B59,"") -> 530293.92 | L59: ='53'!$F$99 -> 1.02 | M59: =OFFSET('53'!$E$35,$A$3,0) -> 705282 | N59: =OFFSET('53'!$F$35,$A$3,0) -> 1.36 | O59: =IFERROR('53'!$F$101*'Discipline Analysis'!$B59,"") -> 467906.4 | P59: ='53'!$F$101 -> 0.9 | Q59: =IFERROR('53'!$F$102*'Discipline Analysis'!$B59,"") | R59: ='53'!$F$102 | S59: =IFERROR('53'!$F$103*'Discipline Analysis'!$B59,"") | T59: ='53'!$F$103 | U59: =IFERROR('53'!$F$104*'Discipline Analysis'!$B59,"") -> 129974 | V59: ='53'!$F$104 -> 0.25
A60: TSTC-Waco | B60: =OFFSET('54'!$D$4,$A$3,0) -> 4009159 | C60: =OFFSET('54'!$E$4,$A$3,0) -> 27711036 | D60: =OFFSET('54'!$F$4,$A$3,0) -> 6.91 | E60: =OFFSET('54'!$E$66,$A$3,0) -> 12273038 | F60: =OFFSET('54'!$F$66,$A$3,0) -> 3.06 | G60: =IFERROR('54'!$F$100*'Discipline Analysis'!$B60,"") -> 441007.49 | H60: ='54'!$F$100 -> 0.11 | I60: =IFERROR('54'!$F$98*'Discipline Analysis'!$B60,"") -> 4049250.6 | J60: ='54'!$F$98 -> 1.01 | K60: =IFERROR('54'!$F$99*'Discipline Analysis'!$B60,"") -> 1804121.6 | L60: ='54'!$F$99 -> 0.45 | M60: =OFFSET('54'!$E$35,$A$3,0) -> 7426882 | N60: =OFFSET('54'!$F$35,$A$3,0) -> 1.85 | O60: =IFERROR('54'!$F$101*'Discipline Analysis'!$B60,"") -> 761740.21 | P60: ='54'!$F$101 -> 0.19 | Q60: =IFERROR('54'!$F$102*'Discipline Analysis'!$B60,"") | R60: ='54'!$F$102 | S60: =IFERROR('54'!$F$103*'Discipline Analysis'!$B60,"") | T60: ='54'!$F$103 | U60: =IFERROR('54'!$F$104*'Discipline Analysis'!$B60,"") -> 962198.16 | V60: ='54'!$F$104 -> 0.24
A61: Lamar-IOT | B61: =OFFSET('55'!$D$4,$A$3,0) -> 1204320 | C61: =OFFSET('55'!$E$4,$A$3,0) -> 10192869 | D61: =OFFSET('55'!$F$4,$A$3,0) -> 8.46 | E61: =OFFSET('55'!$E$66,$A$3,0) -> 4696028 | F61: =OFFSET('55'!$F$66,$A$3,0) -> 3.9 | G61: =IFERROR('55'!$F$100*'Discipline Analysis'!$B61,"") -> 240864 | H61: ='55'!$F$100 -> 0.2 | I61: =IFERROR('55'!$F$98*'Discipline Analysis'!$B61,"") -> 1613788.8 | J61: ='55'!$F$98 -> 1.34 | K61: =IFERROR('55'!$F$99*'Discipline Analysis'!$B61,"") -> 722592 | L61: ='55'!$F$99 -> 0.6 | M61: =OFFSET('55'!$E$35,$A$3,0) -> 2064129 | N61: =OFFSET('55'!$F$35,$A$3,0) -> 1.71 | O61: =IFERROR('55'!$F$101*'Discipline Analysis'!$B61,"") -> 361296 | P61: ='55'!$F$101 -> 0.3 | Q61: =IFERROR('55'!$F$102*'Discipline Analysis'!$B61,"") | R61: ='55'!$F$102 | S61: =IFERROR('55'!$F$103*'Discipline Analysis'!$B61,"") | T61: ='55'!$F$103 | U61: =IFERROR('55'!$F$104*'Discipline Analysis'!$B61,"") -> 505814.4 | V61: ='55'!$F$104 -> 0.42
A62: Lamar-Orange | B62: =OFFSET('56'!$D$4,$A$3,0) -> 773472 | C62: =OFFSET('56'!$E$4,$A$3,0) -> 5876647 | D62: =OFFSET('56'!$F$4,$A$3,0) -> 7.6 | E62: =OFFSET('56'!$E$66,$A$3,0) -> 2559060 | F62: =OFFSET('56'!$F$66,$A$3,0) -> 3.31 | G62: =IFERROR('56'!$F$100*'Discipline Analysis'!$B62,"") -> 603308.16 | H62: ='56'!$F$100 -> 0.78 | I62: =IFERROR('56'!$F$98*'Discipline Analysis'!$B62,"") -> 1276228.8 | J62: ='56'!$F$98 -> 1.65 | K62: =IFERROR('56'!$F$99*'Discipline Analysis'!$B62,"") -> 464083.2 | L62: ='56'!$F$99 -> 0.6 | M62: =OFFSET('56'!$E$35,$A$3,0) -> 351094 | N62: =OFFSET('56'!$F$35,$A$3,0) -> 0.45 | O62: =IFERROR('56'!$F$101*'Discipline Analysis'!$B62,"") -> 371266.56 | P62: ='56'!$F$101 -> 0.48 | Q62: =IFERROR('56'!$F$102*'Discipline Analysis'!$B62,"") | R62: ='56'!$F$102 | S62: =IFERROR('56'!$F$103*'Discipline Analysis'!$B62,"") | T62: ='56'!$F$103 | U62: =IFERROR('56'!$F$104*'Discipline Analysis'!$B62,"") -> 255245.76 | V62: ='56'!$F$104 -> 0.33
A63: Lamar-Port Arthur | B63: =OFFSET('57'!$D$4,$A$3,0) -> 1359194 | C63: =OFFSET('57'!$E$4,$A$3,0) -> 10804164 | D63: =OFFSET('57'!$F$4,$A$3,0) -> 7.95 | E63: =OFFSET('57'!$E$66,$A$3,0) -> 4361246 | F63: =OFFSET('57'!$F$66,$A$3,0) -> 3.21 | G63: =IFERROR('57'!$F$100*'Discipline Analysis'!$B63,"") -> 516493.72 | H63: ='57'!$F$100 -> 0.38 | I63: =IFERROR('57'!$F$98*'Discipline Analysis'!$B63,"") -> 2310629.8 | J63: ='57'!$F$98 -> 1.7 | K63: =IFERROR('57'!$F$99*'Discipline Analysis'!$B63,"") -> 638821.18 | L63: ='57'!$F$99 -> 0.47 | M63: =OFFSET('57'!$E$35,$A$3,0) -> 2214318 | N63: =OFFSET('57'!$F$35,$A$3,0) -> 1.63 | O63: =IFERROR('57'!$F$101*'Discipline Analysis'!$B63,"") -> 231062.98 | P63: ='57'!$F$101 -> 0.17 | Q63: =IFERROR('57'!$F$102*'Discipline Analysis'!$B63,"") | R63: ='57'!$F$102 | S63: =IFERROR('57'!$F$103*'Discipline Analysis'!$B63,"") | T63: ='57'!$F$103 | U63: =IFERROR('57'!$F$104*'Discipline Analysis'!$B63,"") -> 530085.66 | V63: ='57'!$F$104 -> 0.39
A64: Total | B64: =OFFSET(Summary!$D$4,$A$3,0) -> 244475951 | C64: =OFFSET(Summary!$E$4,$A$3,0) -> 1.6735867e+09 | D64: =MEDIAN(D7:D63) -> 6.65 | E64: =OFFSET(Summary!$E$66,$A$3,0) -> 703602770 | F64: =MEDIAN(F7:F63) -> 2.77 | G64: =Summary!$F$100*B64 -> 48895190 | H64: =MEDIAN(H7:H63) -> 0.2 | I64: =Summary!$F$98*'Discipline Analysis'!B64 -> 3.4715585e+08 | J64: =MEDIAN(J7:J63) -> 1.42 | K64: =Summary!$F$99*'Discipline Analysis'!B64 -> 1.3690653e+08 | L64: =MEDIAN(L7:L63) -> 0.56 | M64: =OFFSET(Summary!$E$35,$A$3,0) -> 192319415 | N64: =MEDIAN(N7:N63) -> 0.66 | O64: =IFERROR(Summary!$F$101*'Discipline Analysis'!B64,"") -> 75787545 | P64: =MEDIAN(P7:P63) -> 0.31 | Q64: =Summary!$F$102*'Discipline Analysis'!B64 -> 14668557 | R64: =MEDIAN(R7:R63) -> 0.06 | S64: =Summary!$F$103*'Discipline Analysis'!B64 -> 0 | T64: =MEDIAN(T7:T63) -> 0 | U64: =Summary!$F$104*'Discipline Analysis'!B64 -> 95345621 | V64: =MEDIAN(V7:V63) -> 0.39

Sheet Neutral
A1: =Summary!A1 -> Community and Technical Colleges, Report of Fundable Operating Expenses, Fiscal Year (FY) 2003
A2: Percent of Rates to Maintain Funding Total
A3: This calculation is completed to indicate the relative change in financing assuming the legislature were to fund the institutions at the same total as the previous biennium. The percent funded used against the current rates is adjusted so that the total funded for all institutions is equal to the previous biennium's percent funded.
A4: Institution | B4: ="FY 2004 - 2005 Rates @ "&TEXT(B5,"0.00%")&" (Using FY 2003 CH)" -> FY 2004 - 2005 Rates @ 55.39% (Using FY 2003 CH) | C4: ="Annual Budget Neutral Percent Funded "&TEXT(C5,"0.00%")&" (Using FY 2003 CH)" -> Annual Budget Neutral Percent Funded 55.93% (Using FY 2003 CH) | D4: Difference | E4: Percent Change
A5: Percent of Rates Funded | B5: 0.55391904 | C5: 0.55930859 | D5: =C5-B5 -> 0.0053895453
A6: Alamo Community College District | B6: =$B$5*('Rate History'!$D$4*SUMIF(Data!$G:$G,Neutral!$A6,Data!$CU:$CU)+'Rate History'!$D$5*SUMIF(Data!$G:$G,Neutral!$A6,Data!$CV:$CV)+'Rate History'!$D$6*SUMIF(Data!$G:$G,Neutral!$A6,Data!$CW:$CW)+'Rate History'!$D$7*SUMIF(Data!$G:$G,Neutral!$A6,Data!$CX:$CX)+'Rate History'!$D$8*SUMIF(Data!$G:$G,Neutral!$A6,Data!$CY:$CY)+'Rate History'!$D$9*SUMIF(Data!$G:$G,Neutral!$A6,Data!$CZ:$CZ)+'Rate History'!$D$10*SUMIF(Data!$G:$G,Neutral!$A6,Data!$DA:$DA)+'Rate History'!$D$11*SUMIF(Data!$G:$G,Neutral!$A6,Data!$DB:$DB)+'Rate History'!$D$12*SUMIF(Data!$G:$G,Neutral!$A6,Data!$DC:$DC)+'Rate History'!$D$13*SUMIF(Data!$G:$G,Neutral!$A6,Data!$DD:$DD)+'Rate History'!$D$14*SUMIF(Data!$G:$G,Neutral!$A6,Data!$DE:$DE)+'Rate History'!$D$15*SUMIF(Data!$G:$G,Neutral!$A6,Data!$DF:$DF)+'Rate History'!$D$16*SUMIF(Data!$G:$G,Neutral!$A6,Data!$DG:$DG)+'Rate History'!$D$17*SUMIF(Data!$G:$G,Neutral!$A6,Data!$DH:$DH)+'Rate History'!$D$18*SUMIF(Data!$G:$G,Neutral!$A6,Data!$DI:$DI)+'Rate History'!$D$19*SUMIF(Data!$G:$G,Neutral!$A6,Data!$DJ:$DJ)+'Rate History'!$D$20*SUMIF(Data!$G:$G,Neutral!$A6,Data!$DK:$DK)+'Rate History'!$D$21*SUMIF(Data!$G:$G,Neutral!$A6,Data!$DL:$DL)+'Rate History'!$D$22*SUMIF(Data!$G:$G,Neutral!$A6,Data!$DM:$DM)+'Rate History'!$D$23*SUMIF(Data!$G:$G,Neutral!$A6,Data!$DN:$DN)+'Rate History'!$D$24*SUMIF(Data!$G:$G,Neutral!$A6,Data!$DO:$DO)+'Rate History'!$D$25*SUMIF(Data!$G:$G,Neutral!$A6,Data!$DP:$DP)+'Rate History'!$D$26*SUMIF(Data!$G:$G,Neutral!$A6,Data!$DQ:$DQ)+'Rate History'!$D$27*SUMIF(Data!$G:$G,Neutral!$A6,Data!$DR:$DR)+'Rate History'!$D$28*SUMIF(Data!$G:$G,Neutral!$A6,Data!$DS:$DS)+'Rate History'!$D$29*SUMIF(Data!$G:$G,Neutral!$A6,Data!$DT:$DT)+'Rate History'!$D$30*SUMIF(Data!$G:$G,Neutral!$A6,Data!$DV:$DV)+'Rate History'!$D$31*SUMIF(Data!$G:$G,Neutral!$A6,Data!$DW:$DW)) -> 64851053 | C6: =$C$5*('Rate History'!$C$4*SUMIF(Data!$G:$G,Neutral!$A6,Data!$CU:$CU)+'Rate History'!$C$5*SUMIF(Data!$G:$G,Neutral!$A6,Data!$CV:$CV)+'Rate History'!$C$6*SUMIF(Data!$G:$G,Neutral!$A6,Data!$CW:$CW)+'Rate History'!$C$7*SUMIF(Data!$G:$G,Neutral!$A6,Data!$CX:$CX)+'Rate History'!$C$8*SUMIF(Data!$G:$G,Neutral!$A6,Data!$CY:$CY)+'Rate History'!$C$9*SUMIF(Data!$G:$G,Neutral!$A6,Data!$CZ:$CZ)+'Rate History'!$C$10*SUMIF(Data!$G:$G,Neutral!$A6,Data!$DA:$DA)+'Rate History'!$C$11*SUMIF(Data!$G:$G,Neutral!$A6,Data!$DB:$DB)+'Rate History'!$C$12*SUMIF(Data!$G:$G,Neutral!$A6,Data!$DC:$DC)+'Rate History'!$C$13*SUMIF(Data!$G:$G,Neutral!$A6,Data!$DD:$DD)+'Rate History'!$C$14*SUMIF(Data!$G:$G,Neutral!$A6,Data!$DE:$DE)+'Rate History'!$C$15*SUMIF(Data!$G:$G,Neutral!$A6,Data!$DF:$DF)+'Rate History'!$C$16*SUMIF(Data!$G:$G,Neutral!$A6,Data!$DG:$DG)+'Rate History'!$C$17*SUMIF(Data!$G:$G,Neutral!$A6,Data!$DH:$DH)+'Rate History'!$C$18*SUMIF(Data!$G:$G,Neutral!$A6,Data!$DI:$DI)+'Rate History'!$C$19*SUMIF(Data!$G:$G,Neutral!$A6,Data!$DJ:$DJ)+'Rate History'!$C$20*SUMIF(Data!$G:$G,Neutral!$A6,Data!$DK:$DK)+'Rate History'!$C$21*SUMIF(Data!$G:$G,Neutral!$A6,Data!$DL:$DL)+'Rate History'!$C$22*SUMIF(Data!$G:$G,Neutral!$A6,Data!$DM:$DM)+'Rate History'!$C$23*SUMIF(Data!$G:$G,Neutral!$A6,Data!$DN:$DN)+'Rate History'!$C$24*SUMIF(Data!$G:$G,Neutral!$A6,Data!$DO:$DO)+'Rate History'!$C$25*SUMIF(Data!$G:$G,Neutral!$A6,Data!$DP:$DP)+'Rate History'!$C$26*SUMIF(Data!$G:$G,Neutral!$A6,Data!$DQ:$DQ)+'Rate History'!$C$27*SUMIF(Data!$G:$G,Neutral!$A6,Data!$DR:$DR)+'Rate History'!$C$28*SUMIF(Data!$G:$G,Neutral!$A6,Data!$DS:$DS)+'Rate History'!$C$29*SUMIF(Data!$G:$G,Neutral!$A6,Data!$DT:$DT)+'Rate History'!$C$30*SUMIF(Data!$G:$G,Neutral!$A6,Data!$DV:$DV)+'Rate History'!$C$31*SUMIF(Data!$G:$G,Neutral!$A6,Data!$DW:$DW)) -> 64767177 | D6: =C6-B6 -> -83876.102 | E6: =IFERROR(D6/B6,"") -> -0.0012933653
A7: Alvin Community College | B7: =$B$5*('Rate History'!$D$4*SUMIF(Data!$G:$G,Neutral!$A7,Data!$CU:$CU)+'Rate History'!$D$5*SUMIF(Data!$G:$G,Neutral!$A7,Data!$CV:$CV)+'Rate History'!$D$6*SUMIF(Data!$G:$G,Neutral!$A7,Data!$CW:$CW)+'Rate History'!$D$7*SUMIF(Data!$G:$G,Neutral!$A7,Data!$CX:$CX)+'Rate History'!$D$8*SUMIF(Data!$G:$G,Neutral!$A7,Data!$CY:$CY)+'Rate History'!$D$9*SUMIF(Data!$G:$G,Neutral!$A7,Data!$CZ:$CZ)+'Rate History'!$D$10*SUMIF(Data!$G:$G,Neutral!$A7,Data!$DA:$DA)+'Rate History'!$D$11*SUMIF(Data!$G:$G,Neutral!$A7,Data!$DB:$DB)+'Rate History'!$D$12*SUMIF(Data!$G:$G,Neutral!$A7,Data!$DC:$DC)+'Rate History'!$D$13*SUMIF(Data!$G:$G,Neutral!$A7,Data!$DD:$DD)+'Rate History'!$D$14*SUMIF(Data!$G:$G,Neutral!$A7,Data!$DE:$DE)+'Rate History'!$D$15*SUMIF(Data!$G:$G,Neutral!$A7,Data!$DF:$DF)+'Rate History'!$D$16*SUMIF(Data!$G:$G,Neutral!$A7,Data!$DG:$DG)+'Rate History'!$D$17*SUMIF(Data!$G:$G,Neutral!$A7,Data!$DH:$DH)+'Rate History'!$D$18*SUMIF(Data!$G:$G,Neutral!$A7,Data!$DI:$DI)+'Rate History'!$D$19*SUMIF(Data!$G:$G,Neutral!$A7,Data!$DJ:$DJ)+'Rate History'!$D$20*SUMIF(Data!$G:$G,Neutral!$A7,Data!$DK:$DK)+'Rate History'!$D$21*SUMIF(Data!$G:$G,Neutral!$A7,Data!$DL:$DL)+'Rate History'!$D$22*SUMIF(Data!$G:$G,Neutral!$A7,Data!$DM:$DM)+'Rate History'!$D$23*SUMIF(Data!$G:$G,Neutral!$A7,Data!$DN:$DN)+'Rate History'!$D$24*SUMIF(Data!$G:$G,Neutral!$A7,Data!$DO:$DO)+'Rate History'!$D$25*SUMIF(Data!$G:$G,Neutral!$A7,Data!$DP:$DP)+'Rate History'!$D$26*SUMIF(Data!$G:$G,Neutral!$A7,Data!$DQ:$DQ)+'Rate History'!$D$27*SUMIF(Data!$G:$G,Neutral!$A7,Data!$DR:$DR)+'Rate History'!$D$28*SUMIF(Data!$G:$G,Neutral!$A7,Data!$DS:$DS)+'Rate History'!$D$29*SUMIF(Data!$G:$G,Neutral!$A7,Data!$DT:$DT)+'Rate History'!$D$30*SUMIF(Data!$G:$G,Neutral!$A7,Data!$DV:$DV)+'Rate History'!$D$31*SUMIF(Data!$G:$G,Neutral!$A7,Data!$DW:$DW)) -> 8613359.7 | C7: =$C$5*('Rate History'!$C$4*SUMIF(Data!$G:$G,Neutral!$A7,Data!$CU:$CU)+'Rate History'!$C$5*SUMIF(Data!$G:$G,Neutral!$A7,Data!$CV:$CV)+'Rate History'!$C$6*SUMIF(Data!$G:$G,Neutral!$A7,Data!$CW:$CW)+'Rate History'!$C$7*SUMIF(Data!$G:$G,Neutral!$A7,Data!$CX:$CX)+'Rate History'!$C$8*SUMIF(Data!$G:$G,Neutral!$A7,Data!$CY:$CY)+'Rate History'!$C$9*SUMIF(Data!$G:$G,Neutral!$A7,Data!$CZ:$CZ)+'Rate History'!$C$10*SUMIF(Data!$G:$G,Neutral!$A7,Data!$DA:$DA)+'Rate History'!$C$11*SUMIF(Data!$G:$G,Neutral!$A7,Data!$DB:$DB)+'Rate History'!$C$12*SUMIF(Data!$G:$G,Neutral!$A7,Data!$DC:$DC)+'Rate History'!$C$13*SUMIF(Data!$G:$G,Neutral!$A7,Data!$DD:$DD)+'Rate History'!$C$14*SUMIF(Data!$G:$G,Neutral!$A7,Data!$DE:$DE)+'Rate History'!$C$15*SUMIF(Data!$G:$G,Neutral!$A7,Data!$DF:$DF)+'Rate History'!$C$16*SUMIF(Data!$G:$G,Neutral!$A7,Data!$DG:$DG)+'Rate History'!$C$17*SUMIF(Data!$G:$G,Neutral!$A7,Data!$DH:$DH)+'Rate History'!$C$18*SUMIF(Data!$G:$G,Neutral!$A7,Data!$DI:$DI)+'Rate History'!$C$19*SUMIF(Data!$G:$G,Neutral!$A7,Data!$DJ:$DJ)+'Rate History'!$C$20*SUMIF(Data!$G:$G,Neutral!$A7,Data!$DK:$DK)+'Rate History'!$C$21*SUMIF(Data!$G:$G,Neutral!$A7,Data!$DL:$DL)+'Rate History'!$C$22*SUMIF(Data!$G:$G,Neutral!$A7,Data!$DM:$DM)+'Rate History'!$C$23*SUMIF(Data!$G:$G,Neutral!$A7,Data!$DN:$DN)+'Rate History'!$C$24*SUMIF(Data!$G:$G,Neutral!$A7,Data!$DO:$DO)+'Rate History'!$C$25*SUMIF(Data!$G:$G,Neutral!$A7,Data!$DP:$DP)+'Rate History'!$C$26*SUMIF(Data!$G:$G,Neutral!$A7,Data!$DQ:$DQ)+'Rate History'!$C$27*SUMIF(Data!$G:$G,Neutral!$A7,Data!$DR:$DR)+'Rate History'!$C$28*SUMIF(Data!$G:$G,Neutral!$A7,Data!$DS:$DS)+'Rate History'!$C$29*SUMIF(Data!$G:$G,Neutral!$A7,Data!$DT:$DT)+'Rate History'!$C$30*SUMIF(Data!$G:$G,Neutral!$A7,Data!$DV:$DV)+'Rate History'!$C$31*SUMIF(Data!$G:$G,Neutral!$A7,Data!$DW:$DW)) -> 8599589.8 | D7: =C7-B7 -> -13769.908 | E7: =IFERROR(D7/B7,"") -> -0.0015986686
A8: Amarillo College | B8: =$B$5*('Rate History'!$D$4*SUMIF(Data!$G:$G,Neutral!$A8,Data!$CU:$CU)+'Rate History'!$D$5*SUMIF(Data!$G:$G,Neutral!$A8,Data!$CV:$CV)+'Rate History'!$D$6*SUMIF(Data!$G:$G,Neutral!$A8,Data!$CW:$CW)+'Rate History'!$D$7*SUMIF(Data!$G:$G,Neutral!$A8,Data!$CX:$CX)+'Rate History'!$D$8*SUMIF(Data!$G:$G,Neutral!$A8,Data!$CY:$CY)+'Rate History'!$D$9*SUMIF(Data!$G:$G,Neutral!$A8,Data!$CZ:$CZ)+'Rate History'!$D$10*SUMIF(Data!$G:$G,Neutral!$A8,Data!$DA:$DA)+'Rate History'!$D$11*SUMIF(Data!$G:$G,Neutral!$A8,Data!$DB:$DB)+'Rate History'!$D$12*SUMIF(Data!$G:$G,Neutral!$A8,Data!$DC:$DC)+'Rate History'!$D$13*SUMIF(Data!$G:$G,Neutral!$A8,Data!$DD:$DD)+'Rate History'!$D$14*SUMIF(Data!$G:$G,Neutral!$A8,Data!$DE:$DE)+'Rate History'!$D$15*SUMIF(Data!$G:$G,Neutral!$A8,Data!$DF:$DF)+'Rate History'!$D$16*SUMIF(Data!$G:$G,Neutral!$A8,Data!$DG:$DG)+'Rate History'!$D$17*SUMIF(Data!$G:$G,Neutral!$A8,Data!$DH:$DH)+'Rate History'!$D$18*SUMIF(Data!$G:$G,Neutral!$A8,Data!$DI:$DI)+'Rate History'!$D$19*SUMIF(Data!$G:$G,Neutral!$A8,Data!$DJ:$DJ)+'Rate History'!$D$20*SUMIF(Data!$G:$G,Neutral!$A8,Data!$DK:$DK)+'Rate History'!$D$21*SUMIF(Data!$G:$G,Neutral!$A8,Data!$DL:$DL)+'Rate History'!$D$22*SUMIF(Data!$G:$G,Neutral!$A8,Data!$DM:$DM)+'Rate History'!$D$23*SUMIF(Data!$G:$G,Neutral!$A8,Data!$DN:$DN)+'Rate History'!$D$24*SUMIF(Data!$G:$G,Neutral!$A8,Data!$DO:$DO)+'Rate History'!$D$25*SUMIF(Data!$G:$G,Neutral!$A8,Data!$DP:$DP)+'Rate History'!$D$26*SUMIF(Data!$G:$G,Neutral!$A8,Data!$DQ:$DQ)+'Rate History'!$D$27*SUMIF(Data!$G:$G,Neutral!$A8,Data!$DR:$DR)+'Rate History'!$D$28*SUMIF(Data!$G:$G,Neutral!$A8,Data!$DS:$DS)+'Rate History'!$D$29*SUMIF(Data!$G:$G,Neutral!$A8,Data!$DT:$DT)+'Rate History'!$D$30*SUMIF(Data!$G:$G,Neutral!$A8,Data!$DV:$DV)+'Rate History'!$D$31*SUMIF(Data!$G:$G,Neutral!$A8,Data!$DW:$DW)) -> 16617843 | C8: =$C$5*('Rate History'!$C$4*SUMIF(Data!$G:$G,Neutral!$A8,Data!$CU:$CU)+'Rate History'!$C$5*SUMIF(Data!$G:$G,Neutral!$A8,Data!$CV:$CV)+'Rate History'!$C$6*SUMIF(Data!$G:$G,Neutral!$A8,Data!$CW:$CW)+'Rate History'!$C$7*SUMIF(Data!$G:$G,Neutral!$A8,Data!$CX:$CX)+'Rate History'!$C$8*SUMIF(Data!$G:$G,Neutral!$A8,Data!$CY:$CY)+'Rate History'!$C$9*SUMIF(Data!$G:$G,Neutral!$A8,Data!$CZ:$CZ)+'Rate History'!$C$10*SUMIF(Data!$G:$G,Neutral!$A8,Data!$DA:$DA)+'Rate History'!$C$11*SUMIF(Data!$G:$G,Neutral!$A8,Data!$DB:$DB)+'Rate History'!$C$12*SUMIF(Data!$G:$G,Neutral!$A8,Data!$DC:$DC)+'Rate History'!$C$13*SUMIF(Data!$G:$G,Neutral!$A8,Data!$DD:$DD)+'Rate History'!$C$14*SUMIF(Data!$G:$G,Neutral!$A8,Data!$DE:$DE)+'Rate History'!$C$15*SUMIF(Data!$G:$G,Neutral!$A8,Data!$DF:$DF)+'Rate History'!$C$16*SUMIF(Data!$G:$G,Neutral!$A8,Data!$DG:$DG)+'Rate History'!$C$17*SUMIF(Data!$G:$G,Neutral!$A8,Data!$DH:$DH)+'Rate History'!$C$18*SUMIF(Data!$G:$G,Neutral!$A8,Data!$DI:$DI)+'Rate History'!$C$19*SUMIF(Data!$G:$G,Neutral!$A8,Data!$DJ:$DJ)+'Rate History'!$C$20*SUMIF(Data!$G:$G,Neutral!$A8,Data!$DK:$DK)+'Rate History'!$C$21*SUMIF(Data!$G:$G,Neutral!$A8,Data!$DL:$DL)+'Rate History'!$C$22*SUMIF(Data!$G:$G,Neutral!$A8,Data!$DM:$DM)+'Rate History'!$C$23*SUMIF(Data!$G:$G,Neutral!$A8,Data!$DN:$DN)+'Rate History'!$C$24*SUMIF(Data!$G:$G,Neutral!$A8,Data!$DO:$DO)+'Rate History'!$C$25*SUMIF(Data!$G:$G,Neutral!$A8,Data!$DP:$DP)+'Rate History'!$C$26*SUMIF(Data!$G:$G,Neutral!$A8,Data!$DQ:$DQ)+'Rate History'!$C$27*SUMIF(Data!$G:$G,Neutral!$A8,Data!$DR:$DR)+'Rate History'!$C$28*SUMIF(Data!$G:$G,Neutral!$A8,Data!$DS:$DS)+'Rate History'!$C$29*SUMIF(Data!$G:$G,Neutral!$A8,Data!$DT:$DT)+'Rate History'!$C$30*SUMIF(Data!$G:$G,Neutral!$A8,Data!$DV:$DV)+'Rate History'!$C$31*SUMIF(Data!$G:$G,Neutral!$A8,Data!$DW:$DW)) -> 16544928 | D8: =C8-B8 -> -72915.089 | E8: =IFERROR(D8/B8,"") -> -0.0043877589
A9: Angelina College | B9: =$B$5*('Rate History'!$D$4*SUMIF(Data!$G:$G,Neutral!$A9,Data!$CU:$CU)+'Rate History'!$D$5*SUMIF(Data!$G:$G,Neutral!$A9,Data!$CV:$CV)+'Rate History'!$D$6*SUMIF(Data!$G:$G,Neutral!$A9,Data!$CW:$CW)+'Rate History'!$D$7*SUMIF(Data!$G:$G,Neutral!$A9,Data!$CX:$CX)+'Rate History'!$D$8*SUMIF(Data!$G:$G,Neutral!$A9,Data!$CY:$CY)+'Rate History'!$D$9*SUMIF(Data!$G:$G,Neutral!$A9,Data!$CZ:$CZ)+'Rate History'!$D$10*SUMIF(Data!$G:$G,Neutral!$A9,Data!$DA:$DA)+'Rate History'!$D$11*SUMIF(Data!$G:$G,Neutral!$A9,Data!$DB:$DB)+'Rate History'!$D$12*SUMIF(Data!$G:$G,Neutral!$A9,Data!$DC:$DC)+'Rate History'!$D$13*SUMIF(Data!$G:$G,Neutral!$A9,Data!$DD:$DD)+'Rate History'!$D$14*SUMIF(Data!$G:$G,Neutral!$A9,Data!$DE:$DE)+'Rate History'!$D$15*SUMIF(Data!$G:$G,Neutral!$A9,Data!$DF:$DF)+'Rate History'!$D$16*SUMIF(Data!$G:$G,Neutral!$A9,Data!$DG:$DG)+'Rate History'!$D$17*SUMIF(Data!$G:$G,Neutral!$A9,Data!$DH:$DH)+'Rate History'!$D$18*SUMIF(Data!$G:$G,Neutral!$A9,Data!$DI:$DI)+'Rate History'!$D$19*SUMIF(Data!$G:$G,Neutral!$A9,Data!$DJ:$DJ)+'Rate History'!$D$20*SUMIF(Data!$G:$G,Neutral!$A9,Data!$DK:$DK)+'Rate History'!$D$21*SUMIF(Data!$G:$G,Neutral!$A9,Data!$DL:$DL)+'Rate History'!$D$22*SUMIF(Data!$G:$G,Neutral!$A9,Data!$DM:$DM)+'Rate History'!$D$23*SUMIF(Data!$G:$G,Neutral!$A9,Data!$DN:$DN)+'Rate History'!$D$24*SUMIF(Data!$G:$G,Neutral!$A9,Data!$DO:$DO)+'Rate History'!$D$25*SUMIF(Data!$G:$G,Neutral!$A9,Data!$DP:$DP)+'Rate History'!$D$26*SUMIF(Data!$G:$G,Neutral!$A9,Data!$DQ:$DQ)+'Rate History'!$D$27*SUMIF(Data!$G:$G,Neutral!$A9,Data!$DR:$DR)+'Rate History'!$D$28*SUMIF(Data!$G:$G,Neutral!$A9,Data!$DS:$DS)+'Rate History'!$D$29*SUMIF(Data!$G:$G,Neutral!$A9,Data!$DT:$DT)+'Rate History'!$D$30*SUMIF(Data!$G:$G,Neutral!$A9,Data!$DV:$DV)+'Rate History'!$D$31*SUMIF(Data!$G:$G,Neutral!$A9,Data!$DW:$DW)) -> 8778096 | C9: =$C$5*('Rate History'!$C$4*SUMIF(Data!$G:$G,Neutral!$A9,Data!$CU:$CU)+'Rate History'!$C$5*SUMIF(Data!$G:$G,Neutral!$A9,Data!$CV:$CV)+'Rate History'!$C$6*SUMIF(Data!$G:$G,Neutral!$A9,Data!$CW:$CW)+'Rate History'!$C$7*SUMIF(Data!$G:$G,Neutral!$A9,Data!$CX:$CX)+'Rate History'!$C$8*SUMIF(Data!$G:$G,Neutral!$A9,Data!$CY:$CY)+'Rate History'!$C$9*SUMIF(Data!$G:$G,Neutral!$A9,Data!$CZ:$CZ)+'Rate History'!$C$10*SUMIF(Data!$G:$G,Neutral!$A9,Data!$DA:$DA)+'Rate History'!$C$11*SUMIF(Data!$G:$G,Neutral!$A9,Data!$DB:$DB)+'Rate History'!$C$12*SUMIF(Data!$G:$G,Neutral!$A9,Data!$DC:$DC)+'Rate History'!$C$13*SUMIF(Data!$G:$G,Neutral!$A9,Data!$DD:$DD)+'Rate History'!$C$14*SUMIF(Data!$G:$G,Neutral!$A9,Data!$DE:$DE)+'Rate History'!$C$15*SUMIF(Data!$G:$G,Neutral!$A9,Data!$DF:$DF)+'Rate History'!$C$16*SUMIF(Data!$G:$G,Neutral!$A9,Data!$DG:$DG)+'Rate History'!$C$17*SUMIF(Data!$G:$G,Neutral!$A9,Data!$DH:$DH)+'Rate History'!$C$18*SUMIF(Data!$G:$G,Neutral!$A9,Data!$DI:$DI)+'Rate History'!$C$19*SUMIF(Data!$G:$G,Neutral!$A9,Data!$DJ:$DJ)+'Rate History'!$C$20*SUMIF(Data!$G:$G,Neutral!$A9,Data!$DK:$DK)+'Rate History'!$C$21*SUMIF(Data!$G:$G,Neutral!$A9,Data!$DL:$DL)+'Rate History'!$C$22*SUMIF(Data!$G:$G,Neutral!$A9,Data!$DM:$DM)+'Rate History'!$C$23*SUMIF(Data!$G:$G,Neutral!$A9,Data!$DN:$DN)+'Rate History'!$C$24*SUMIF(Data!$G:$G,Neutral!$A9,Data!$DO:$DO)+'Rate History'!$C$25*SUMIF(Data!$G:$G,Neutral!$A9,Data!$DP:$DP)+'Rate History'!$C$26*SUMIF(Data!$G:$G,Neutral!$A9,Data!$DQ:$DQ)+'Rate History'!$C$27*SUMIF(Data!$G:$G,Neutral!$A9,Data!$DR:$DR)+'Rate History'!$C$28*SUMIF(Data!$G:$G,Neutral!$A9,Data!$DS:$DS)+'Rate History'!$C$29*SUMIF(Data!$G:$G,Neutral!$A9,Data!$DT:$DT)+'Rate History'!$C$30*SUMIF(Data!$G:$G,Neutral!$A9,Data!$DV:$DV)+'Rate History'!$C$31*SUMIF(Data!$G:$G,Neutral!$A9,Data!$DW:$DW)) -> 8720193 | D9: =C9-B9 -> -57902.966 | E9: =IFERROR(D9/B9,"") -> -0.0065963013
A10: Austin Community College | B10: =$B$5*('Rate History'!$D$4*SUMIF(Data!$G:$G,Neutral!$A10,Data!$CU:$CU)+'Rate History'!$D$5*SUMIF(Data!$G:$G,Neutral!$A10,Data!$CV:$CV)+'Rate History'!$D$6*SUMIF(Data!$G:$G,Neutral!$A10,Data!$CW:$CW)+'Rate History'!$D$7*SUMIF(Data!$G:$G,Neutral!$A10,Data!$CX:$CX)+'Rate History'!$D$8*SUMIF(Data!$G:$G,Neutral!$A10,Data!$CY:$CY)+'Rate History'!$D$9*SUMIF(Data!$G:$G,Neutral!$A10,Data!$CZ:$CZ)+'Rate History'!$D$10*SUMIF(Data!$G:$G,Neutral!$A10,Data!$DA:$DA)+'Rate History'!$D$11*SUMIF(Data!$G:$G,Neutral!$A10,Data!$DB:$DB)+'Rate History'!$D$12*SUMIF(Data!$G:$G,Neutral!$A10,Data!$DC:$DC)+'Rate History'!$D$13*SUMIF(Data!$G:$G,Neutral!$A10,Data!$DD:$DD)+'Rate History'!$D$14*SUMIF(Data!$G:$G,Neutral!$A10,Data!$DE:$DE)+'Rate History'!$D$15*SUMIF(Data!$G:$G,Neutral!$A10,Data!$DF:$DF)+'Rate History'!$D$16*SUMIF(Data!$G:$G,Neutral!$A10,Data!$DG:$DG)+'Rate History'!$D$17*SUMIF(Data!$G:$G,Neutral!$A10,Data!$DH:$DH)+'Rate History'!$D$18*SUMIF(Data!$G:$G,Neutral!$A10,Data!$DI:$DI)+'Rate History'!$D$19*SUMIF(Data!$G:$G,Neutral!$A10,Data!$DJ:$DJ)+'Rate History'!$D$20*SUMIF(Data!$G:$G,Neutral!$A10,Data!$DK:$DK)+'Rate History'!$D$21*SUMIF(Data!$G:$G,Neutral!$A10,Data!$DL:$DL)+'Rate History'!$D$22*SUMIF(Data!$G:$G,Neutral!$A10,Data!$DM:$DM)+'Rate History'!$D$23*SUMIF(Data!$G:$G,Neutral!$A10,Data!$DN:$DN)+'Rate History'!$D$24*SUMIF(Data!$G:$G,Neutral!$A10,Data!$DO:$DO)+'Rate History'!$D$25*SUMIF(Data!$G:$G,Neutral!$A10,Data!$DP:$DP)+'Rate History'!$D$26*SUMIF(Data!$G:$G,Neutral!$A10,Data!$DQ:$DQ)+'Rate History'!$D$27*SUMIF(Data!$G:$G,Neutral!$A10,Data!$DR:$DR)+'Rate History'!$D$28*SUMIF(Data!$G:$G,Neutral!$A10,Data!$DS:$DS)+'Rate History'!$D$29*SUMIF(Data!$G:$G,Neutral!$A10,Data!$DT:$DT)+'Rate History'!$D$30*SUMIF(Data!$G:$G,Neutral!$A10,Data!$DV:$DV)+'Rate History'!$D$31*SUMIF(Data!$G:$G,Neutral!$A10,Data!$DW:$DW)) -> 39234162 | C10: =$C$5*('Rate History'!$C$4*SUMIF(Data!$G:$G,Neutral!$A10,Data!$CU:$CU)+'Rate History'!$C$5*SUMIF(Data!$G:$G,Neutral!$A10,Data!$CV:$CV)+'Rate History'!$C$6*SUMIF(Data!$G:$G,Neutral!$A10,Data!$CW:$CW)+'Rate History'!$C$7*SUMIF(Data!$G:$G,Neutral!$A10,Data!$CX:$CX)+'Rate History'!$C$8*SUMIF(Data!$G:$G,Neutral!$A10,Data!$CY:$CY)+'Rate History'!$C$9*SUMIF(Data!$G:$G,Neutral!$A10,Data!$CZ:$CZ)+'Rate History'!$C$10*SUMIF(Data!$G:$G,Neutral!$A10,Data!$DA:$DA)+'Rate History'!$C$11*SUMIF(Data!$G:$G,Neutral!$A10,Data!$DB:$DB)+'Rate History'!$C$12*SUMIF(Data!$G:$G,Neutral!$A10,Data!$DC:$DC)+'Rate History'!$C$13*SUMIF(Data!$G:$G,Neutral!$A10,Data!$DD:$DD)+'Rate History'!$C$14*SUMIF(Data!$G:$G,Neutral!$A10,Data!$DE:$DE)+'Rate History'!$C$15*SUMIF(Data!$G:$G,Neutral!$A10,Data!$DF:$DF)+'Rate History'!$C$16*SUMIF(Data!$G:$G,Neutral!$A10,Data!$DG:$DG)+'Rate History'!$C$17*SUMIF(Data!$G:$G,Neutral!$A10,Data!$DH:$DH)+'Rate History'!$C$18*SUMIF(Data!$G:$G,Neutral!$A10,Data!$DI:$DI)+'Rate History'!$C$19*SUMIF(Data!$G:$G,Neutral!$A10,Data!$DJ:$DJ)+'Rate History'!$C$20*SUMIF(Data!$G:$G,Neutral!$A10,Data!$DK:$DK)+'Rate History'!$C$21*SUMIF(Data!$G:$G,Neutral!$A10,Data!$DL:$DL)+'Rate History'!$C$22*SUMIF(Data!$G:$G,Neutral!$A10,Data!$DM:$DM)+'Rate History'!$C$23*SUMIF(Data!$G:$G,Neutral!$A10,Data!$DN:$DN)+'Rate History'!$C$24*SUMIF(Data!$G:$G,Neutral!$A10,Data!$DO:$DO)+'Rate History'!$C$25*SUMIF(Data!$G:$G,Neutral!$A10,Data!$DP:$DP)+'Rate History'!$C$26*SUMIF(Data!$G:$G,Neutral!$A10,Data!$DQ:$DQ)+'Rate History'!$C$27*SUMIF(Data!$G:$G,Neutral!$A10,Data!$DR:$DR)+'Rate History'!$C$28*SUMIF(Data!$G:$G,Neutral!$A10,Data!$DS:$DS)+'Rate History'!$C$29*SUMIF(Data!$G:$G,Neutral!$A10,Data!$DT:$DT)+'Rate History'!$C$30*SUMIF(Data!$G:$G,Neutral!$A10,Data!$DV:$DV)+'Rate History'!$C$31*SUMIF(Data!$G:$G,Neutral!$A10,Data!$DW:$DW)) -> 39293592 | D10: =C10-B10 -> 59430.187 | E10: =IFERROR(D10/B10,"") -> 0.0015147561
A11: Blinn College | B11: =$B$5*('Rate History'!$D$4*SUMIF(Data!$G:$G,Neutral!$A11,Data!$CU:$CU)+'Rate History'!$D$5*SUMIF(Data!$G:$G,Neutral!$A11,Data!$CV:$CV)+'Rate History'!$D$6*SUMIF(Data!$G:$G,Neutral!$A11,Data!$CW:$CW)+'Rate History'!$D$7*SUMIF(Data!$G:$G,Neutral!$A11,Data!$CX:$CX)+'Rate History'!$D$8*SUMIF(Data!$G:$G,Neutral!$A11,Data!$CY:$CY)+'Rate History'!$D$9*SUMIF(Data!$G:$G,Neutral!$A11,Data!$CZ:$CZ)+'Rate History'!$D$10*SUMIF(Data!$G:$G,Neutral!$A11,Data!$DA:$DA)+'Rate History'!$D$11*SUMIF(Data!$G:$G,Neutral!$A11,Data!$DB:$DB)+'Rate History'!$D$12*SUMIF(Data!$G:$G,Neutral!$A11,Data!$DC:$DC)+'Rate History'!$D$13*SUMIF(Data!$G:$G,Neutral!$A11,Data!$DD:$DD)+'Rate History'!$D$14*SUMIF(Data!$G:$G,Neutral!$A11,Data!$DE:$DE)+'Rate History'!$D$15*SUMIF(Data!$G:$G,Neutral!$A11,Data!$DF:$DF)+'Rate History'!$D$16*SUMIF(Data!$G:$G,Neutral!$A11,Data!$DG:$DG)+'Rate History'!$D$17*SUMIF(Data!$G:$G,Neutral!$A11,Data!$DH:$DH)+'Rate History'!$D$18*SUMIF(Data!$G:$G,Neutral!$A11,Data!$DI:$DI)+'Rate History'!$D$19*SUMIF(Data!$G:$G,Neutral!$A11,Data!$DJ:$DJ)+'Rate History'!$D$20*SUMIF(Data!$G:$G,Neutral!$A11,Data!$DK:$DK)+'Rate History'!$D$21*SUMIF(Data!$G:$G,Neutral!$A11,Data!$DL:$DL)+'Rate History'!$D$22*SUMIF(Data!$G:$G,Neutral!$A11,Data!$DM:$DM)+'Rate History'!$D$23*SUMIF(Data!$G:$G,Neutral!$A11,Data!$DN:$DN)+'Rate History'!$D$24*SUMIF(Data!$G:$G,Neutral!$A11,Data!$DO:$DO)+'Rate History'!$D$25*SUMIF(Data!$G:$G,Neutral!$A11,Data!$DP:$DP)+'Rate History'!$D$26*SUMIF(Data!$G:$G,Neutral!$A11,Data!$DQ:$DQ)+'Rate History'!$D$27*SUMIF(Data!$G:$G,Neutral!$A11,Data!$DR:$DR)+'Rate History'!$D$28*SUMIF(Data!$G:$G,Neutral!$A11,Data!$DS:$DS)+'Rate History'!$D$29*SUMIF(Data!$G:$G,Neutral!$A11,Data!$DT:$DT)+'Rate History'!$D$30*SUMIF(Data!$G:$G,Neutral!$A11,Data!$DV:$DV)+'Rate History'!$D$31*SUMIF(Data!$G:$G,Neutral!$A11,Data!$DW:$DW)) -> 20309317 | C11: =$C$5*('Rate History'!$C$4*SUMIF(Data!$G:$G,Neutral!$A11,Data!$CU:$CU)+'Rate History'!$C$5*SUMIF(Data!$G:$G,Neutral!$A11,Data!$CV:$CV)+'Rate History'!$C$6*SUMIF(Data!$G:$G,Neutral!$A11,Data!$CW:$CW)+'Rate History'!$C$7*SUMIF(Data!$G:$G,Neutral!$A11,Data!$CX:$CX)+'Rate History'!$C$8*SUMIF(Data!$G:$G,Neutral!$A11,Data!$CY:$CY)+'Rate History'!$C$9*SUMIF(Data!$G:$G,Neutral!$A11,Data!$CZ:$CZ)+'Rate History'!$C$10*SUMIF(Data!$G:$G,Neutral!$A11,Data!$DA:$DA)+'Rate History'!$C$11*SUMIF(Data!$G:$G,Neutral!$A11,Data!$DB:$DB)+'Rate History'!$C$12*SUMIF(Data!$G:$G,Neutral!$A11,Data!$DC:$DC)+'Rate History'!$C$13*SUMIF(Data!$G:$G,Neutral!$A11,Data!$DD:$DD)+'Rate History'!$C$14*SUMIF(Data!$G:$G,Neutral!$A11,Data!$DE:$DE)+'Rate History'!$C$15*SUMIF(Data!$G:$G,Neutral!$A11,Data!$DF:$DF)+'Rate History'!$C$16*SUMIF(Data!$G:$G,Neutral!$A11,Data!$DG:$DG)+'Rate History'!$C$17*SUMIF(Data!$G:$G,Neutral!$A11,Data!$DH:$DH)+'Rate History'!$C$18*SUMIF(Data!$G:$G,Neutral!$A11,Data!$DI:$DI)+'Rate History'!$C$19*SUMIF(Data!$G:$G,Neutral!$A11,Data!$DJ:$DJ)+'Rate History'!$C$20*SUMIF(Data!$G:$G,Neutral!$A11,Data!$DK:$DK)+'Rate History'!$C$21*SUMIF(Data!$G:$G,Neutral!$A11,Data!$DL:$DL)+'Rate History'!$C$22*SUMIF(Data!$G:$G,Neutral!$A11,Data!$DM:$DM)+'Rate History'!$C$23*SUMIF(Data!$G:$G,Neutral!$A11,Data!$DN:$DN)+'Rate History'!$C$24*SUMIF(Data!$G:$G,Neutral!$A11,Data!$DO:$DO)+'Rate History'!$C$25*SUMIF(Data!$G:$G,Neutral!$A11,Data!$DP:$DP)+'Rate History'!$C$26*SUMIF(Data!$G:$G,Neutral!$A11,Data!$DQ:$DQ)+'Rate History'!$C$27*SUMIF(Data!$G:$G,Neutral!$A11,Data!$DR:$DR)+'Rate History'!$C$28*SUMIF(Data!$G:$G,Neutral!$A11,Data!$DS:$DS)+'Rate History'!$C$29*SUMIF(Data!$G:$G,Neutral!$A11,Data!$DT:$DT)+'Rate History'!$C$30*SUMIF(Data!$G:$G,Neutral!$A11,Data!$DV:$DV)+'Rate History'!$C$31*SUMIF(Data!$G:$G,Neutral!$A11,Data!$DW:$DW)) -> 20312978 | D11: =C11-B11 -> 3660.7654 | E11: =IFERROR(D11/B11,"") -> 0.00018025054
A12: Brazosport College | B12: =$B$5*('Rate History'!$D$4*SUMIF(Data!$G:$G,Neutral!$A12,Data!$CU:$CU)+'Rate History'!$D$5*SUMIF(Data!$G:$G,Neutral!$A12,Data!$CV:$CV)+'Rate History'!$D$6*SUMIF(Data!$G:$G,Neutral!$A12,Data!$CW:$CW)+'Rate History'!$D$7*SUMIF(Data!$G:$G,Neutral!$A12,Data!$CX:$CX)+'Rate History'!$D$8*SUMIF(Data!$G:$G,Neutral!$A12,Data!$CY:$CY)+'Rate History'!$D$9*SUMIF(Data!$G:$G,Neutral!$A12,Data!$CZ:$CZ)+'Rate History'!$D$10*SUMIF(Data!$G:$G,Neutral!$A12,Data!$DA:$DA)+'Rate History'!$D$11*SUMIF(Data!$G:$G,Neutral!$A12,Data!$DB:$DB)+'Rate History'!$D$12*SUMIF(Data!$G:$G,Neutral!$A12,Data!$DC:$DC)+'Rate History'!$D$13*SUMIF(Data!$G:$G,Neutral!$A12,Data!$DD:$DD)+'Rate History'!$D$14*SUMIF(Data!$G:$G,Neutral!$A12,Data!$DE:$DE)+'Rate History'!$D$15*SUMIF(Data!$G:$G,Neutral!$A12,Data!$DF:$DF)+'Rate History'!$D$16*SUMIF(Data!$G:$G,Neutral!$A12,Data!$DG:$DG)+'Rate History'!$D$17*SUMIF(Data!$G:$G,Neutral!$A12,Data!$DH:$DH)+'Rate History'!$D$18*SUMIF(Data!$G:$G,Neutral!$A12,Data!$DI:$DI)+'Rate History'!$D$19*SUMIF(Data!$G:$G,Neutral!$A12,Data!$DJ:$DJ)+'Rate History'!$D$20*SUMIF(Data!$G:$G,Neutral!$A12,Data!$DK:$DK)+'Rate History'!$D$21*SUMIF(Data!$G:$G,Neutral!$A12,Data!$DL:$DL)+'Rate History'!$D$22*SUMIF(Data!$G:$G,Neutral!$A12,Data!$DM:$DM)+'Rate History'!$D$23*SUMIF(Data!$G:$G,Neutral!$A12,Data!$DN:$DN)+'Rate History'!$D$24*SUMIF(Data!$G:$G,Neutral!$A12,Data!$DO:$DO)+'Rate History'!$D$25*SUMIF(Data!$G:$G,Neutral!$A12,Data!$DP:$DP)+'Rate History'!$D$26*SUMIF(Data!$G:$G,Neutral!$A12,Data!$DQ:$DQ)+'Rate History'!$D$27*SUMIF(Data!$G:$G,Neutral!$A12,Data!$DR:$DR)+'Rate History'!$D$28*SUMIF(Data!$G:$G,Neutral!$A12,Data!$DS:$DS)+'Rate History'!$D$29*SUMIF(Data!$G:$G,Neutral!$A12,Data!$DT:$DT)+'Rate History'!$D$30*SUMIF(Data!$G:$G,Neutral!$A12,Data!$DV:$DV)+'Rate History'!$D$31*SUMIF(Data!$G:$G,Neutral!$A12,Data!$DW:$DW)) -> 5537904 | C12: =$C$5*('Rate History'!$C$4*SUMIF(Data!$G:$G,Neutral!$A12,Data!$CU:$CU)+'Rate History'!$C$5*SUMIF(Data!$G:$G,Neutral!$A12,Data!$CV:$CV)+'Rate History'!$C$6*SUMIF(Data!$G:$G,Neutral!$A12,Data!$CW:$CW)+'Rate History'!$C$7*SUMIF(Data!$G:$G,Neutral!$A12,Data!$CX:$CX)+'Rate History'!$C$8*SUMIF(Data!$G:$G,Neutral!$A12,Data!$CY:$CY)+'Rate History'!$C$9*SUMIF(Data!$G:$G,Neutral!$A12,Data!$CZ:$CZ)+'Rate History'!$C$10*SUMIF(Data!$G:$G,Neutral!$A12,Data!$DA:$DA)+'Rate History'!$C$11*SUMIF(Data!$G:$G,Neutral!$A12,Data!$DB:$DB)+'Rate History'!$C$12*SUMIF(Data!$G:$G,Neutral!$A12,Data!$DC:$DC)+'Rate History'!$C$13*SUMIF(Data!$G:$G,Neutral!$A12,Data!$DD:$DD)+'Rate History'!$C$14*SUMIF(Data!$G:$G,Neutral!$A12,Data!$DE:$DE)+'Rate History'!$C$15*SUMIF(Data!$G:$G,Neutral!$A12,Data!$DF:$DF)+'Rate History'!$C$16*SUMIF(Data!$G:$G,Neutral!$A12,Data!$DG:$DG)+'Rate History'!$C$17*SUMIF(Data!$G:$G,Neutral!$A12,Data!$DH:$DH)+'Rate History'!$C$18*SUMIF(Data!$G:$G,Neutral!$A12,Data!$DI:$DI)+'Rate History'!$C$19*SUMIF(Data!$G:$G,Neutral!$A12,Data!$DJ:$DJ)+'Rate History'!$C$20*SUMIF(Data!$G:$G,Neutral!$A12,Data!$DK:$DK)+'Rate History'!$C$21*SUMIF(Data!$G:$G,Neutral!$A12,Data!$DL:$DL)+'Rate History'!$C$22*SUMIF(Data!$G:$G,Neutral!$A12,Data!$DM:$DM)+'Rate History'!$C$23*SUMIF(Data!$G:$G,Neutral!$A12,Data!$DN:$DN)+'Rate History'!$C$24*SUMIF(Data!$G:$G,Neutral!$A12,Data!$DO:$DO)+'Rate History'!$C$25*SUMIF(Data!$G:$G,Neutral!$A12,Data!$DP:$DP)+'Rate History'!$C$26*SUMIF(Data!$G:$G,Neutral!$A12,Data!$DQ:$DQ)+'Rate History'!$C$27*SUMIF(Data!$G:$G,Neutral!$A12,Data!$DR:$DR)+'Rate History'!$C$28*SUMIF(Data!$G:$G,Neutral!$A12,Data!$DS:$DS)+'Rate History'!$C$29*SUMIF(Data!$G:$G,Neutral!$A12,Data!$DT:$DT)+'Rate History'!$C$30*SUMIF(Data!$G:$G,Neutral!$A12,Data!$DV:$DV)+'Rate History'!$C$31*SUMIF(Data!$G:$G,Neutral!$A12,Data!$DW:$DW)) -> 5610713 | D12: =C12-B12 -> 72809.022 | E12: =IFERROR(D12/B12,"") -> 0.013147397
A13: Central Texas College | B13: =$B$5*('Rate History'!$D$4*SUMIF(Data!$G:$G,Neutral!$A13,Data!$CU:$CU)+'Rate History'!$D$5*SUMIF(Data!$G:$G,Neutral!$A13,Data!$CV:$CV)+'Rate History'!$D$6*SUMIF(Data!$G:$G,Neutral!$A13,Data!$CW:$CW)+'Rate History'!$D$7*SUMIF(Data!$G:$G,Neutral!$A13,Data!$CX:$CX)+'Rate History'!$D$8*SUMIF(Data!$G:$G,Neutral!$A13,Data!$CY:$CY)+'Rate History'!$D$9*SUMIF(Data!$G:$G,Neutral!$A13,Data!$CZ:$CZ)+'Rate History'!$D$10*SUMIF(Data!$G:$G,Neutral!$A13,Data!$DA:$DA)+'Rate History'!$D$11*SUMIF(Data!$G:$G,Neutral!$A13,Data!$DB:$DB)+'Rate History'!$D$12*SUMIF(Data!$G:$G,Neutral!$A13,Data!$DC:$DC)+'Rate History'!$D$13*SUMIF(Data!$G:$G,Neutral!$A13,Data!$DD:$DD)+'Rate History'!$D$14*SUMIF(Data!$G:$G,Neutral!$A13,Data!$DE:$DE)+'Rate History'!$D$15*SUMIF(Data!$G:$G,Neutral!$A13,Data!$DF:$DF)+'Rate History'!$D$16*SUMIF(Data!$G:$G,Neutral!$A13,Data!$DG:$DG)+'Rate History'!$D$17*SUMIF(Data!$G:$G,Neutral!$A13,Data!$DH:$DH)+'Rate History'!$D$18*SUMIF(Data!$G:$G,Neutral!$A13,Data!$DI:$DI)+'Rate History'!$D$19*SUMIF(Data!$G:$G,Neutral!$A13,Data!$DJ:$DJ)+'Rate History'!$D$20*SUMIF(Data!$G:$G,Neutral!$A13,Data!$DK:$DK)+'Rate History'!$D$21*SUMIF(Data!$G:$G,Neutral!$A13,Data!$DL:$DL)+'Rate History'!$D$22*SUMIF(Data!$G:$G,Neutral!$A13,Data!$DM:$DM)+'Rate History'!$D$23*SUMIF(Data!$G:$G,Neutral!$A13,Data!$DN:$DN)+'Rate History'!$D$24*SUMIF(Data!$G:$G,Neutral!$A13,Data!$DO:$DO)+'Rate History'!$D$25*SUMIF(Data!$G:$G,Neutral!$A13,Data!$DP:$DP)+'Rate History'!$D$26*SUMIF(Data!$G:$G,Neutral!$A13,Data!$DQ:$DQ)+'Rate History'!$D$27*SUMIF(Data!$G:$G,Neutral!$A13,Data!$DR:$DR)+'Rate History'!$D$28*SUMIF(Data!$G:$G,Neutral!$A13,Data!$DS:$DS)+'Rate History'!$D$29*SUMIF(Data!$G:$G,Neutral!$A13,Data!$DT:$DT)+'Rate History'!$D$30*SUMIF(Data!$G:$G,Neutral!$A13,Data!$DV:$DV)+'Rate History'!$D$31*SUMIF(Data!$G:$G,Neutral!$A13,Data!$DW:$DW)) -> 19054233 | C13: =$C$5*('Rate History'!$C$4*SUMIF(Data!$G:$G,Neutral!$A13,Data!$CU:$CU)+'Rate History'!$C$5*SUMIF(Data!$G:$G,Neutral!$A13,Data!$CV:$CV)+'Rate History'!$C$6*SUMIF(Data!$G:$G,Neutral!$A13,Data!$CW:$CW)+'Rate History'!$C$7*SUMIF(Data!$G:$G,Neutral!$A13,Data!$CX:$CX)+'Rate History'!$C$8*SUMIF(Data!$G:$G,Neutral!$A13,Data!$CY:$CY)+'Rate History'!$C$9*SUMIF(Data!$G:$G,Neutral!$A13,Data!$CZ:$CZ)+'Rate History'!$C$10*SUMIF(Data!$G:$G,Neutral!$A13,Data!$DA:$DA)+'Rate History'!$C$11*SUMIF(Data!$G:$G,Neutral!$A13,Data!$DB:$DB)+'Rate History'!$C$12*SUMIF(Data!$G:$G,Neutral!$A13,Data!$DC:$DC)+'Rate History'!$C$13*SUMIF(Data!$G:$G,Neutral!$A13,Data!$DD:$DD)+'Rate History'!$C$14*SUMIF(Data!$G:$G,Neutral!$A13,Data!$DE:$DE)+'Rate History'!$C$15*SUMIF(Data!$G:$G,Neutral!$A13,Data!$DF:$DF)+'Rate History'!$C$16*SUMIF(Data!$G:$G,Neutral!$A13,Data!$DG:$DG)+'Rate History'!$C$17*SUMIF(Data!$G:$G,Neutral!$A13,Data!$DH:$DH)+'Rate History'!$C$18*SUMIF(Data!$G:$G,Neutral!$A13,Data!$DI:$DI)+'Rate History'!$C$19*SUMIF(Data!$G:$G,Neutral!$A13,Data!$DJ:$DJ)+'Rate History'!$C$20*SUMIF(Data!$G:$G,Neutral!$A13,Data!$DK:$DK)+'Rate History'!$C$21*SUMIF(Data!$G:$G,Neutral!$A13,Data!$DL:$DL)+'Rate History'!$C$22*SUMIF(Data!$G:$G,Neutral!$A13,Data!$DM:$DM)+'Rate History'!$C$23*SUMIF(Data!$G:$G,Neutral!$A13,Data!$DN:$DN)+'Rate History'!$C$24*SUMIF(Data!$G:$G,Neutral!$A13,Data!$DO:$DO)+'Rate History'!$C$25*SUMIF(Data!$G:$G,Neutral!$A13,Data!$DP:$DP)+'Rate History'!$C$26*SUMIF(Data!$G:$G,Neutral!$A13,Data!$DQ:$DQ)+'Rate History'!$C$27*SUMIF(Data!$G:$G,Neutral!$A13,Data!$DR:$DR)+'Rate History'!$C$28*SUMIF(Data!$G:$G,Neutral!$A13,Data!$DS:$DS)+'Rate History'!$C$29*SUMIF(Data!$G:$G,Neutral!$A13,Data!$DT:$DT)+'Rate History'!$C$30*SUMIF(Data!$G:$G,Neutral!$A13,Data!$DV:$DV)+'Rate History'!$C$31*SUMIF(Data!$G:$G,Neutral!$A13,Data!$DW:$DW)) -> 19165591 | D13: =C13-B13 -> 111358.32 | E13: =IFERROR(D13/B13,"") -> 0.0058442824
A14: Cisco Junior College | B14: =$B$5*('Rate History'!$D$4*SUMIF(Data!$G:$G,Neutral!$A14,Data!$CU:$CU)+'Rate History'!$D$5*SUMIF(Data!$G:$G,Neutral!$A14,Data!$CV:$CV)+'Rate History'!$D$6*SUMIF(Data!$G:$G,Neutral!$A14,Data!$CW:$CW)+'Rate History'!$D$7*SUMIF(Data!$G:$G,Neutral!$A14,Data!$CX:$CX)+'Rate History'!$D$8*SUMIF(Data!$G:$G,Neutral!$A14,Data!$CY:$CY)+'Rate History'!$D$9*SUMIF(Data!$G:$G,Neutral!$A14,Data!$CZ:$CZ)+'Rate History'!$D$10*SUMIF(Data!$G:$G,Neutral!$A14,Data!$DA:$DA)+'Rate History'!$D$11*SUMIF(Data!$G:$G,Neutral!$A14,Data!$DB:$DB)+'Rate History'!$D$12*SUMIF(Data!$G:$G,Neutral!$A14,Data!$DC:$DC)+'Rate History'!$D$13*SUMIF(Data!$G:$G,Neutral!$A14,Data!$DD:$DD)+'Rate History'!$D$14*SUMIF(Data!$G:$G,Neutral!$A14,Data!$DE:$DE)+'Rate History'!$D$15*SUMIF(Data!$G:$G,Neutral!$A14,Data!$DF:$DF)+'Rate History'!$D$16*SUMIF(Data!$G:$G,Neutral!$A14,Data!$DG:$DG)+'Rate History'!$D$17*SUMIF(Data!$G:$G,Neutral!$A14,Data!$DH:$DH)+'Rate History'!$D$18*SUMIF(Data!$G:$G,Neutral!$A14,Data!$DI:$DI)+'Rate History'!$D$19*SUMIF(Data!$G:$G,Neutral!$A14,Data!$DJ:$DJ)+'Rate History'!$D$20*SUMIF(Data!$G:$G,Neutral!$A14,Data!$DK:$DK)+'Rate History'!$D$21*SUMIF(Data!$G:$G,Neutral!$A14,Data!$DL:$DL)+'Rate History'!$D$22*SUMIF(Data!$G:$G,Neutral!$A14,Data!$DM:$DM)+'Rate History'!$D$23*SUMIF(Data!$G:$G,Neutral!$A14,Data!$DN:$DN)+'Rate History'!$D$24*SUMIF(Data!$G:$G,Neutral!$A14,Data!$DO:$DO)+'Rate History'!$D$25*SUMIF(Data!$G:$G,Neutral!$A14,Data!$DP:$DP)+'Rate History'!$D$26*SUMIF(Data!$G:$G,Neutral!$A14,Data!$DQ:$DQ)+'Rate History'!$D$27*SUMIF(Data!$G:$G,Neutral!$A14,Data!$DR:$DR)+'Rate History'!$D$28*SUMIF(Data!$G:$G,Neutral!$A14,Data!$DS:$DS)+'Rate History'!$D$29*SUMIF(Data!$G:$G,Neutral!$A14,Data!$DT:$DT)+'Rate History'!$D$30*SUMIF(Data!$G:$G,Neutral!$A14,Data!$DV:$DV)+'Rate History'!$D$31*SUMIF(Data!$G:$G,Neutral!$A14,Data!$DW:$DW)) -> 4676226.3 | C14: =$C$5*('Rate History'!$C$4*SUMIF(Data!$G:$G,Neutral!$A14,Data!$CU:$CU)+'Rate History'!$C$5*SUMIF(Data!$G:$G,Neutral!$A14,Data!$CV:$CV)+'Rate History'!$C$6*SUMIF(Data!$G:$G,Neutral!$A14,Data!$CW:$CW)+'Rate History'!$C$7*SUMIF(Data!$G:$G,Neutral!$A14,Data!$CX:$CX)+'Rate History'!$C$8*SUMIF(Data!$G:$G,Neutral!$A14,Data!$CY:$CY)+'Rate History'!$C$9*SUMIF(Data!$G:$G,Neutral!$A14,Data!$CZ:$CZ)+'Rate History'!$C$10*SUMIF(Data!$G:$G,Neutral!$A14,Data!$DA:$DA)+'Rate History'!$C$11*SUMIF(Data!$G:$G,Neutral!$A14,Data!$DB:$DB)+'Rate History'!$C$12*SUMIF(Data!$G:$G,Neutral!$A14,Data!$DC:$DC)+'Rate History'!$C$13*SUMIF(Data!$G:$G,Neutral!$A14,Data!$DD:$DD)+'Rate History'!$C$14*SUMIF(Data!$G:$G,Neutral!$A14,Data!$DE:$DE)+'Rate History'!$C$15*SUMIF(Data!$G:$G,Neutral!$A14,Data!$DF:$DF)+'Rate History'!$C$16*SUMIF(Data!$G:$G,Neutral!$A14,Data!$DG:$DG)+'Rate History'!$C$17*SUMIF(Data!$G:$G,Neutral!$A14,Data!$DH:$DH)+'Rate History'!$C$18*SUMIF(Data!$G:$G,Neutral!$A14,Data!$DI:$DI)+'Rate History'!$C$19*SUMIF(Data!$G:$G,Neutral!$A14,Data!$DJ:$DJ)+'Rate History'!$C$20*SUMIF(Data!$G:$G,Neutral!$A14,Data!$DK:$DK)+'Rate History'!$C$21*SUMIF(Data!$G:$G,Neutral!$A14,Data!$DL:$DL)+'Rate History'!$C$22*SUMIF(Data!$G:$G,Neutral!$A14,Data!$DM:$DM)+'Rate History'!$C$23*SUMIF(Data!$G:$G,Neutral!$A14,Data!$DN:$DN)+'Rate History'!$C$24*SUMIF(Data!$G:$G,Neutral!$A14,Data!$DO:$DO)+'Rate History'!$C$25*SUMIF(Data!$G:$G,Neutral!$A14,Data!$DP:$DP)+'Rate History'!$C$26*SUMIF(Data!$G:$G,Neutral!$A14,Data!$DQ:$DQ)+'Rate History'!$C$27*SUMIF(Data!$G:$G,Neutral!$A14,Data!$DR:$DR)+'Rate History'!$C$28*SUMIF(Data!$G:$G,Neutral!$A14,Data!$DS:$DS)+'Rate History'!$C$29*SUMIF(Data!$G:$G,Neutral!$A14,Data!$DT:$DT)+'Rate History'!$C$30*SUMIF(Data!$G:$G,Neutral!$A14,Data!$DV:$DV)+'Rate History'!$C$31*SUMIF(Data!$G:$G,Neutral!$A14,Data!$DW:$DW)) -> 4663527.3 | D14: =C14-B14 -> -12698.963 | E14: =IFERROR(D14/B14,"") -> -0.0027156433
A15: Clarendon College | B15: =$B$5*('Rate History'!$D$4*SUMIF(Data!$G:$G,Neutral!$A15,Data!$CU:$CU)+'Rate History'!$D$5*SUMIF(Data!$G:$G,Neutral!$A15,Data!$CV:$CV)+'Rate History'!$D$6*SUMIF(Data!$G:$G,Neutral!$A15,Data!$CW:$CW)+'Rate History'!$D$7*SUMIF(Data!$G:$G,Neutral!$A15,Data!$CX:$CX)+'Rate History'!$D$8*SUMIF(Data!$G:$G,Neutral!$A15,Data!$CY:$CY)+'Rate History'!$D$9*SUMIF(Data!$G:$G,Neutral!$A15,Data!$CZ:$CZ)+'Rate History'!$D$10*SUMIF(Data!$G:$G,Neutral!$A15,Data!$DA:$DA)+'Rate History'!$D$11*SUMIF(Data!$G:$G,Neutral!$A15,Data!$DB:$DB)+'Rate History'!$D$12*SUMIF(Data!$G:$G,Neutral!$A15,Data!$DC:$DC)+'Rate History'!$D$13*SUMIF(Data!$G:$G,Neutral!$A15,Data!$DD:$DD)+'Rate History'!$D$14*SUMIF(Data!$G:$G,Neutral!$A15,Data!$DE:$DE)+'Rate History'!$D$15*SUMIF(Data!$G:$G,Neutral!$A15,Data!$DF:$DF)+'Rate History'!$D$16*SUMIF(Data!$G:$G,Neutral!$A15,Data!$DG:$DG)+'Rate History'!$D$17*SUMIF(Data!$G:$G,Neutral!$A15,Data!$DH:$DH)+'Rate History'!$D$18*SUMIF(Data!$G:$G,Neutral!$A15,Data!$DI:$DI)+'Rate History'!$D$19*SUMIF(Data!$G:$G,Neutral!$A15,Data!$DJ:$DJ)+'Rate History'!$D$20*SUMIF(Data!$G:$G,Neutral!$A15,Data!$DK:$DK)+'Rate History'!$D$21*SUMIF(Data!$G:$G,Neutral!$A15,Data!$DL:$DL)+'Rate History'!$D$22*SUMIF(Data!$G:$G,Neutral!$A15,Data!$DM:$DM)+'Rate History'!$D$23*SUMIF(Data!$G:$G,Neutral!$A15,Data!$DN:$DN)+'Rate History'!$D$24*SUMIF(Data!$G:$G,Neutral!$A15,Data!$DO:$DO)+'Rate History'!$D$25*SUMIF(Data!$G:$G,Neutral!$A15,Data!$DP:$DP)+'Rate History'!$D$26*SUMIF(Data!$G:$G,Neutral!$A15,Data!$DQ:$DQ)+'Rate History'!$D$27*SUMIF(Data!$G:$G,Neutral!$A15,Data!$DR:$DR)+'Rate History'!$D$28*SUMIF(Data!$G:$G,Neutral!$A15,Data!$DS:$DS)+'Rate History'!$D$29*SUMIF(Data!$G:$G,Neutral!$A15,Data!$DT:$DT)+'Rate History'!$D$30*SUMIF(Data!$G:$G,Neutral!$A15,Data!$DV:$DV)+'Rate History'!$D$31*SUMIF(Data!$G:$G,Neutral!$A15,Data!$DW:$DW)) -> 1572938.8 | C15: =$C$5*('Rate History'!$C$4*SUMIF(Data!$G:$G,Neutral!$A15,Data!$CU:$CU)+'Rate History'!$C$5*SUMIF(Data!$G:$G,Neutral!$A15,Data!$CV:$CV)+'Rate History'!$C$6*SUMIF(Data!$G:$G,Neutral!$A15,Data!$CW:$CW)+'Rate History'!$C$7*SUMIF(Data!$G:$G,Neutral!$A15,Data!$CX:$CX)+'Rate History'!$C$8*SUMIF(Data!$G:$G,Neutral!$A15,Data!$CY:$CY)+'Rate History'!$C$9*SUMIF(Data!$G:$G,Neutral!$A15,Data!$CZ:$CZ)+'Rate History'!$C$10*SUMIF(Data!$G:$G,Neutral!$A15,Data!$DA:$DA)+'Rate History'!$C$11*SUMIF(Data!$G:$G,Neutral!$A15,Data!$DB:$DB)+'Rate History'!$C$12*SUMIF(Data!$G:$G,Neutral!$A15,Data!$DC:$DC)+'Rate History'!$C$13*SUMIF(Data!$G:$G,Neutral!$A15,Data!$DD:$DD)+'Rate History'!$C$14*SUMIF(Data!$G:$G,Neutral!$A15,Data!$DE:$DE)+'Rate History'!$C$15*SUMIF(Data!$G:$G,Neutral!$A15,Data!$DF:$DF)+'Rate History'!$C$16*SUMIF(Data!$G:$G,Neutral!$A15,Data!$DG:$DG)+'Rate History'!$C$17*SUMIF(Data!$G:$G,Neutral!$A15,Data!$DH:$DH)+'Rate History'!$C$18*SUMIF(Data!$G:$G,Neutral!$A15,Data!$DI:$DI)+'Rate History'!$C$19*SUMIF(Data!$G:$G,Neutral!$A15,Data!$DJ:$DJ)+'Rate History'!$C$20*SUMIF(Data!$G:$G,Neutral!$A15,Data!$DK:$DK)+'Rate History'!$C$21*SUMIF(Data!$G:$G,Neutral!$A15,Data!$DL:$DL)+'Rate History'!$C$22*SUMIF(Data!$G:$G,Neutral!$A15,Data!$DM:$DM)+'Rate History'!$C$23*SUMIF(Data!$G:$G,Neutral!$A15,Data!$DN:$DN)+'Rate History'!$C$24*SUMIF(Data!$G:$G,Neutral!$A15,Data!$DO:$DO)+'Rate History'!$C$25*SUMIF(Data!$G:$G,Neutral!$A15,Data!$DP:$DP)+'Rate History'!$C$26*SUMIF(Data!$G:$G,Neutral!$A15,Data!$DQ:$DQ)+'Rate History'!$C$27*SUMIF(Data!$G:$G,Neutral!$A15,Data!$DR:$DR)+'Rate History'!$C$28*SUMIF(Data!$G:$G,Neutral!$A15,Data!$DS:$DS)+'Rate History'!$C$29*SUMIF(Data!$G:$G,Neutral!$A15,Data!$DT:$DT)+'Rate History'!$C$30*SUMIF(Data!$G:$G,Neutral!$A15,Data!$DV:$DV)+'Rate History'!$C$31*SUMIF(Data!$G:$G,Neutral!$A15,Data!$DW:$DW)) -> 1564707.8 | D15: =C15-B15 -> -8231.0001 | E15: =IFERROR(D15/B15,"") -> -0.0052328799
A16: Coastal Bend College | B16: =$B$5*('Rate History'!$D$4*SUMIF(Data!$G:$G,Neutral!$A16,Data!$CU:$CU)+'Rate History'!$D$5*SUMIF(Data!$G:$G,Neutral!$A16,Data!$CV:$CV)+'Rate History'!$D$6*SUMIF(Data!$G:$G,Neutral!$A16,Data!$CW:$CW)+'Rate History'!$D$7*SUMIF(Data!$G:$G,Neutral!$A16,Data!$CX:$CX)+'Rate History'!$D$8*SUMIF(Data!$G:$G,Neutral!$A16,Data!$CY:$CY)+'Rate History'!$D$9*SUMIF(Data!$G:$G,Neutral!$A16,Data!$CZ:$CZ)+'Rate History'!$D$10*SUMIF(Data!$G:$G,Neutral!$A16,Data!$DA:$DA)+'Rate History'!$D$11*SUMIF(Data!$G:$G,Neutral!$A16,Data!$DB:$DB)+'Rate History'!$D$12*SUMIF(Data!$G:$G,Neutral!$A16,Data!$DC:$DC)+'Rate History'!$D$13*SUMIF(Data!$G:$G,Neutral!$A16,Data!$DD:$DD)+'Rate History'!$D$14*SUMIF(Data!$G:$G,Neutral!$A16,Data!$DE:$DE)+'Rate History'!$D$15*SUMIF(Data!$G:$G,Neutral!$A16,Data!$DF:$DF)+'Rate History'!$D$16*SUMIF(Data!$G:$G,Neutral!$A16,Data!$DG:$DG)+'Rate History'!$D$17*SUMIF(Data!$G:$G,Neutral!$A16,Data!$DH:$DH)+'Rate History'!$D$18*SUMIF(Data!$G:$G,Neutral!$A16,Data!$DI:$DI)+'Rate History'!$D$19*SUMIF(Data!$G:$G,Neutral!$A16,Data!$DJ:$DJ)+'Rate History'!$D$20*SUMIF(Data!$G:$G,Neutral!$A16,Data!$DK:$DK)+'Rate History'!$D$21*SUMIF(Data!$G:$G,Neutral!$A16,Data!$DL:$DL)+'Rate History'!$D$22*SUMIF(Data!$G:$G,Neutral!$A16,Data!$DM:$DM)+'Rate History'!$D$23*SUMIF(Data!$G:$G,Neutral!$A16,Data!$DN:$DN)+'Rate History'!$D$24*SUMIF(Data!$G:$G,Neutral!$A16,Data!$DO:$DO)+'Rate History'!$D$25*SUMIF(Data!$G:$G,Neutral!$A16,Data!$DP:$DP)+'Rate History'!$D$26*SUMIF(Data!$G:$G,Neutral!$A16,Data!$DQ:$DQ)+'Rate History'!$D$27*SUMIF(Data!$G:$G,Neutral!$A16,Data!$DR:$DR)+'Rate History'!$D$28*SUMIF(Data!$G:$G,Neutral!$A16,Data!$DS:$DS)+'Rate History'!$D$29*SUMIF(Data!$G:$G,Neutral!$A16,Data!$DT:$DT)+'Rate History'!$D$30*SUMIF(Data!$G:$G,Neutral!$A16,Data!$DV:$DV)+'Rate History'!$D$31*SUMIF(Data!$G:$G,Neutral!$A16,Data!$DW:$DW)) -> 7763983.8 | C16: =$C$5*('Rate History'!$C$4*SUMIF(Data!$G:$G,Neutral!$A16,Data!$CU:$CU)+'Rate History'!$C$5*SUMIF(Data!$G:$G,Neutral!$A16,Data!$CV:$CV)+'Rate History'!$C$6*SUMIF(Data!$G:$G,Neutral!$A16,Data!$CW:$CW)+'Rate History'!$C$7*SUMIF(Data!$G:$G,Neutral!$A16,Data!$CX:$CX)+'Rate History'!$C$8*SUMIF(Data!$G:$G,Neutral!$A16,Data!$CY:$CY)+'Rate History'!$C$9*SUMIF(Data!$G:$G,Neutral!$A16,Data!$CZ:$CZ)+'Rate History'!$C$10*SUMIF(Data!$G:$G,Neutral!$A16,Data!$DA:$DA)+'Rate History'!$C$11*SUMIF(Data!$G:$G,Neutral!$A16,Data!$DB:$DB)+'Rate History'!$C$12*SUMIF(Data!$G:$G,Neutral!$A16,Data!$DC:$DC)+'Rate History'!$C$13*SUMIF(Data!$G:$G,Neutral!$A16,Data!$DD:$DD)+'Rate History'!$C$14*SUMIF(Data!$G:$G,Neutral!$A16,Data!$DE:$DE)+'Rate History'!$C$15*SUMIF(Data!$G:$G,Neutral!$A16,Data!$DF:$DF)+'Rate History'!$C$16*SUMIF(Data!$G:$G,Neutral!$A16,Data!$DG:$DG)+'Rate History'!$C$17*SUMIF(Data!$G:$G,Neutral!$A16,Data!$DH:$DH)+'Rate History'!$C$18*SUMIF(Data!$G:$G,Neutral!$A16,Data!$DI:$DI)+'Rate History'!$C$19*SUMIF(Data!$G:$G,Neutral!$A16,Data!$DJ:$DJ)+'Rate History'!$C$20*SUMIF(Data!$G:$G,Neutral!$A16,Data!$DK:$DK)+'Rate History'!$C$21*SUMIF(Data!$G:$G,Neutral!$A16,Data!$DL:$DL)+'Rate History'!$C$22*SUMIF(Data!$G:$G,Neutral!$A16,Data!$DM:$DM)+'Rate History'!$C$23*SUMIF(Data!$G:$G,Neutral!$A16,Data!$DN:$DN)+'Rate History'!$C$24*SUMIF(Data!$G:$G,Neutral!$A16,Data!$DO:$DO)+'Rate History'!$C$25*SUMIF(Data!$G:$G,Neutral!$A16,Data!$DP:$DP)+'Rate History'!$C$26*SUMIF(Data!$G:$G,Neutral!$A16,Data!$DQ:$DQ)+'Rate History'!$C$27*SUMIF(Data!$G:$G,Neutral!$A16,Data!$DR:$DR)+'Rate History'!$C$28*SUMIF(Data!$G:$G,Neutral!$A16,Data!$DS:$DS)+'Rate History'!$C$29*SUMIF(Data!$G:$G,Neutral!$A16,Data!$DT:$DT)+'Rate History'!$C$30*SUMIF(Data!$G:$G,Neutral!$A16,Data!$DV:$DV)+'Rate History'!$C$31*SUMIF(Data!$G:$G,Neutral!$A16,Data!$DW:$DW)) -> 7807538.8 | D16: =C16-B16 -> 43554.921 | E16: =IFERROR(D16/B16,"") -> 0.0056098675
A17: College of the Mainland Community College District | B17: =$B$5*('Rate History'!$D$4*SUMIF(Data!$G:$G,Neutral!$A17,Data!$CU:$CU)+'Rate History'!$D$5*SUMIF(Data!$G:$G,Neutral!$A17,Data!$CV:$CV)+'Rate History'!$D$6*SUMIF(Data!$G:$G,Neutral!$A17,Data!$CW:$CW)+'Rate History'!$D$7*SUMIF(Data!$G:$G,Neutral!$A17,Data!$CX:$CX)+'Rate History'!$D$8*SUMIF(Data!$G:$G,Neutral!$A17,Data!$CY:$CY)+'Rate History'!$D$9*SUMIF(Data!$G:$G,Neutral!$A17,Data!$CZ:$CZ)+'Rate History'!$D$10*SUMIF(Data!$G:$G,Neutral!$A17,Data!$DA:$DA)+'Rate History'!$D$11*SUMIF(Data!$G:$G,Neutral!$A17,Data!$DB:$DB)+'Rate History'!$D$12*SUMIF(Data!$G:$G,Neutral!$A17,Data!$DC:$DC)+'Rate History'!$D$13*SUMIF(Data!$G:$G,Neutral!$A17,Data!$DD:$DD)+'Rate History'!$D$14*SUMIF(Data!$G:$G,Neutral!$A17,Data!$DE:$DE)+'Rate History'!$D$15*SUMIF(Data!$G:$G,Neutral!$A17,Data!$DF:$DF)+'Rate History'!$D$16*SUMIF(Data!$G:$G,Neutral!$A17,Data!$DG:$DG)+'Rate History'!$D$17*SUMIF(Data!$G:$G,Neutral!$A17,Data!$DH:$DH)+'Rate History'!$D$18*SUMIF(Data!$G:$G,Neutral!$A17,Data!$DI:$DI)+'Rate History'!$D$19*SUMIF(Data!$G:$G,Neutral!$A17,Data!$DJ:$DJ)+'Rate History'!$D$20*SUMIF(Data!$G:$G,Neutral!$A17,Data!$DK:$DK)+'Rate History'!$D$21*SUMIF(Data!$G:$G,Neutral!$A17,Data!$DL:$DL)+'Rate History'!$D$22*SUMIF(Data!$G:$G,Neutral!$A17,Data!$DM:$DM)+'Rate History'!$D$23*SUMIF(Data!$G:$G,Neutral!$A17,Data!$DN:$DN)+'Rate History'!$D$24*SUMIF(Data!$G:$G,Neutral!$A17,Data!$DO:$DO)+'Rate History'!$D$25*SUMIF(Data!$G:$G,Neutral!$A17,Data!$DP:$DP)+'Rate History'!$D$26*SUMIF(Data!$G:$G,Neutral!$A17,Data!$DQ:$DQ)+'Rate History'!$D$27*SUMIF(Data!$G:$G,Neutral!$A17,Data!$DR:$DR)+'Rate History'!$D$28*SUMIF(Data!$G:$G,Neutral!$A17,Data!$DS:$DS)+'Rate History'!$D$29*SUMIF(Data!$G:$G,Neutral!$A17,Data!$DT:$DT)+'Rate History'!$D$30*SUMIF(Data!$G:$G,Neutral!$A17,Data!$DV:$DV)+'Rate History'!$D$31*SUMIF(Data!$G:$G,Neutral!$A17,Data!$DW:$DW)) -> 5636642.5 | C17: =$C$5*('Rate History'!$C$4*SUMIF(Data!$G:$G,Neutral!$A17,Data!$CU:$CU)+'Rate History'!$C$5*SUMIF(Data!$G:$G,Neutral!$A17,Data!$CV:$CV)+'Rate History'!$C$6*SUMIF(Data!$G:$G,Neutral!$A17,Data!$CW:$CW)+'Rate History'!$C$7*SUMIF(Data!$G:$G,Neutral!$A17,Data!$CX:$CX)+'Rate History'!$C$8*SUMIF(Data!$G:$G,Neutral!$A17,Data!$CY:$CY)+'Rate History'!$C$9*SUMIF(Data!$G:$G,Neutral!$A17,Data!$CZ:$CZ)+'Rate History'!$C$10*SUMIF(Data!$G:$G,Neutral!$A17,Data!$DA:$DA)+'Rate History'!$C$11*SUMIF(Data!$G:$G,Neutral!$A17,Data!$DB:$DB)+'Rate History'!$C$12*SUMIF(Data!$G:$G,Neutral!$A17,Data!$DC:$DC)+'Rate History'!$C$13*SUMIF(Data!$G:$G,Neutral!$A17,Data!$DD:$DD)+'Rate History'!$C$14*SUMIF(Data!$G:$G,Neutral!$A17,Data!$DE:$DE)+'Rate History'!$C$15*SUMIF(Data!$G:$G,Neutral!$A17,Data!$DF:$DF)+'Rate History'!$C$16*SUMIF(Data!$G:$G,Neutral!$A17,Data!$DG:$DG)+'Rate History'!$C$17*SUMIF(Data!$G:$G,Neutral!$A17,Data!$DH:$DH)+'Rate History'!$C$18*SUMIF(Data!$G:$G,Neutral!$A17,Data!$DI:$DI)+'Rate History'!$C$19*SUMIF(Data!$G:$G,Neutral!$A17,Data!$DJ:$DJ)+'Rate History'!$C$20*SUMIF(Data!$G:$G,Neutral!$A17,Data!$DK:$DK)+'Rate History'!$C$21*SUMIF(Data!$G:$G,Neutral!$A17,Data!$DL:$DL)+'Rate History'!$C$22*SUMIF(Data!$G:$G,Neutral!$A17,Data!$DM:$DM)+'Rate History'!$C$23*SUMIF(Data!$G:$G,Neutral!$A17,Data!$DN:$DN)+'Rate History'!$C$24*SUMIF(Data!$G:$G,Neutral!$A17,Data!$DO:$DO)+'Rate History'!$C$25*SUMIF(Data!$G:$G,Neutral!$A17,Data!$DP:$DP)+'Rate History'!$C$26*SUMIF(Data!$G:$G,Neutral!$A17,Data!$DQ:$DQ)+'Rate History'!$C$27*SUMIF(Data!$G:$G,Neutral!$A17,Data!$DR:$DR)+'Rate History'!$C$28*SUMIF(Data!$G:$G,Neutral!$A17,Data!$DS:$DS)+'Rate History'!$C$29*SUMIF(Data!$G:$G,Neutral!$A17,Data!$DT:$DT)+'Rate History'!$C$30*SUMIF(Data!$G:$G,Neutral!$A17,Data!$DV:$DV)+'Rate History'!$C$31*SUMIF(Data!$G:$G,Neutral!$A17,Data!$DW:$DW)) -> 5640503.3 | D17: =C17-B17 -> 3860.8006 | E17: =IFERROR(D17/B17,"") -> 0.00068494686
... A62: Lamar State College-Port Arthur | B62: =$B$5*('Rate History'!$D$4*SUMIF(Data!$G:$G,Neutral!$A62,Data!$CU:$CU)+'Rate History'!$D$5*SUMIF(Data!$G:$G,Neutral!$A62,Data!$CV:$CV)+'Rate History'!$D$6*SUMIF(Data!$G:$G,Neutral!$A62,Data!$CW:$CW)+'Rate History'!$D$7*SUMIF(Data!$G:$G,Neutral!$A62,Data!$CX:$CX)+'Rate History'!$D$8*SUMIF(Data!$G:$G,Neutral!$A62,Data!$CY:$CY)+'Rate History'!$D$9*SUMIF(Data!$G:$G,Neutral!$A62,Data!$CZ:$CZ)+'Rate History'!$D$10*SUMIF(Data!$G:$G,Neutral!$A62,Data!$DA:$DA)+'Rate History'!$D$11*SUMIF(Data!$G:$G,Neutral!$A62,Data!$DB:$DB)+'Rate History'!$D$12*SUMIF(Data!$G:$G,Neutral!$A62,Data!$DC:$DC)+'Rate History'!$D$13*SUMIF(Data!$G:$G,Neutral!$A62,Data!$DD:$DD)+'Rate History'!$D$14*SUMIF(Data!$G:$G,Neutral!$A62,Data!$DE:$DE)+'Rate History'!$D$15*SUMIF(Data!$G:$G,Neutral!$A62,Data!$DF:$DF)+'Rate History'!$D$16*SUMIF(Data!$G:$G,Neutral!$A62,Data!$DG:$DG)+'Rate History'!$D$17*SUMIF(Data!$G:$G,Neutral!$A62,Data!$DH:$DH)+'Rate History'!$D$18*SUMIF(Data!$G:$G,Neutral!$A62,Data!$DI:$DI)+'Rate History'!$D$19*SUMIF(Data!$G:$G,Neutral!$A62,Data!$DJ:$DJ)+'Rate History'!$D$20*SUMIF(Data!$G:$G,Neutral!$A62,Data!$DK:$DK)+'Rate History'!$D$21*SUMIF(Data!$G:$G,Neutral!$A62,Data!$DL:$DL)+'Rate History'!$D$22*SUMIF(Data!$G:$G,Neutral!$A62,Data!$DM:$DM)+'Rate History'!$D$23*SUMIF(Data!$G:$G,Neutral!$A62,Data!$DN:$DN)+'Rate History'!$D$24*SUMIF(Data!$G:$G,Neutral!$A62,Data!$DO:$DO)+'Rate History'!$D$25*SUMIF(Data!$G:$G,Neutral!$A62,Data!$DP:$DP)+'Rate History'!$D$26*SUMIF(Data!$G:$G,Neutral!$A62,Data!$DQ:$DQ)+'Rate History'!$D$27*SUMIF(Data!$G:$G,Neutral!$A62,Data!$DR:$DR)+'Rate History'!$D$28*SUMIF(Data!$G:$G,Neutral!$A62,Data!$DS:$DS)+'Rate History'!$D$29*SUMIF(Data!$G:$G,Neutral!$A62,Data!$DT:$DT)+'Rate History'!$D$30*SUMIF(Data!$G:$G,Neutral!$A62,Data!$DV:$DV)+'Rate History'!$D$31*SUMIF(Data!$G:$G,Neutral!$A62,Data!$DW:$DW)) -> 4853729.4 | C62: =$C$5*('Rate History'!$C$4*SUMIF(Data!$G:$G,Neutral!$A62,Data!$CU:$CU)+'Rate History'!$C$5*SUMIF(Data!$G:$G,Neutral!$A62,Data!$CV:$CV)+'Rate History'!$C$6*SUMIF(Data!$G:$G,Neutral!$A62,Data!$CW:$CW)+'Rate History'!$C$7*SUMIF(Data!$G:$G,Neutral!$A62,Data!$CX:$CX)+'Rate History'!$C$8*SUMIF(Data!$G:$G,Neutral!$A62,Data!$CY:$CY)+'Rate History'!$C$9*SUMIF(Data!$G:$G,Neutral!$A62,Data!$CZ:$CZ)+'Rate History'!$C$10*SUMIF(Data!$G:$G,Neutral!$A62,Data!$DA:$DA)+'Rate History'!$C$11*SUMIF(Data!$G:$G,Neutral!$A62,Data!$DB:$DB)+'Rate History'!$C$12*SUMIF(Data!$G:$G,Neutral!$A62,Data!$DC:$DC)+'Rate History'!$C$13*SUMIF(Data!$G:$G,Neutral!$A62,Data!$DD:$DD)+'Rate History'!$C$14*SUMIF(Data!$G:$G,Neutral!$A62,Data!$DE:$DE)+'Rate History'!$C$15*SUMIF(Data!$G:$G,Neutral!$A62,Data!$DF:$DF)+'Rate History'!$C$16*SUMIF(Data!$G:$G,Neutral!$A62,Data!$DG:$DG)+'Rate History'!$C$17*SUMIF(Data!$G:$G,Neutral!$A62,Data!$DH:$DH)+'Rate History'!$C$18*SUMIF(Data!$G:$G,Neutral!$A62,Data!$DI:$DI)+'Rate History'!$C$19*SUMIF(Data!$G:$G,Neutral!$A62,Data!$DJ:$DJ)+'Rate History'!$C$20*SUMIF(Data!$G:$G,Neutral!$A62,Data!$DK:$DK)+'Rate History'!$C$21*SUMIF(Data!$G:$G,Neutral!$A62,Data!$DL:$DL)+'Rate History'!$C$22*SUMIF(Data!$G:$G,Neutral!$A62,Data!$DM:$DM)+'Rate History'!$C$23*SUMIF(Data!$G:$G,Neutral!$A62,Data!$DN:$DN)+'Rate History'!$C$24*SUMIF(Data!$G:$G,Neutral!$A62,Data!$DO:$DO)+'Rate History'!$C$25*SUMIF(Data!$G:$G,Neutral!$A62,Data!$DP:$DP)+'Rate History'!$C$26*SUMIF(Data!$G:$G,Neutral!$A62,Data!$DQ:$DQ)+'Rate History'!$C$27*SUMIF(Data!$G:$G,Neutral!$A62,Data!$DR:$DR)+'Rate History'!$C$28*SUMIF(Data!$G:$G,Neutral!$A62,Data!$DS:$DS)+'Rate History'!$C$29*SUMIF(Data!$G:$G,Neutral!$A62,Data!$DT:$DT)+'Rate History'!$C$30*SUMIF(Data!$G:$G,Neutral!$A62,Data!$DV:$DV)+'Rate History'!$C$31*SUMIF(Data!$G:$G,Neutral!$A62,Data!$DW:$DW)) -> 4866363.1 | D62: =C62-B62 -> 12633.706 | E62: =IFERROR(D62/B62,"") -> 0.0026028863
A63: Total | B63: =SUM(B5:B62) -> 8.1130964e+08 | C63: =SUM(C6:C62) -> 8.1130964e+08 | D63: =C63-B63 -> 2.6226044e-06 | E63: =IFERROR(D63/B63,"") -> 3.2325567e-15

Sheet 1
A1: =Summary!A1 -> Community and Technical Colleges, Report of Fundable Operating Expenses, Fiscal Year (FY) 2003
A2: 003607 | B2: =VLOOKUP(A2,Data!A:G,7,0) -> Alamo Community College District
F3: =IFERROR(VLOOKUP(A2,Data!A:C,3,0),"0") -> 1
A4: Fund | B4: Total Expense by Discipline | D4: Contact Hours | E4: Expense | F4: Expense per Contact Hour
A5: 1 | B5: Agriculture | D5: =D36 -> 59180 | E5: =E36+E67+IFERROR($E$105/$D$105*D5,0) -> 341927.28 | F5: =IF(OR(D5=0,E5=0),"",ROUND(E5/D5,2)) -> 5.78
A6: 2 | B6: Architecture and Precision Production Trades | D6: =D37 -> 216765 | E6: =E37+E68+IFERROR($E$105/$D$105*D6,0) -> 1565901 | F6: =IF(OR(D6=0,E6=0),"",ROUND(E6/D6,2)) -> 7.22
A7: 3 | B7: Biology, Physical Sciences, and Science Technology | D7: =D38 -> 1864000 | E7: =E38+E69+IFERROR($E$105/$D$105*D7,0) -> 13932744 | F7: =IF(OR(D7=0,E7=0),"",ROUND(E7/D7,2)) -> 7.47
A8: 4 | B8: Business Management, Marketing, and Administrative Services | D8: =D39 -> 937188 | E8: =E39+E70+IFERROR($E$105/$D$105*D8,0) -> 7990845.9 | F8: =IF(OR(D8=0,E8=0),"",ROUND(E8/D8,2)) -> 8.53
A9: 5 | B9: Career Pilot | D9: =D40 -> 18912 | E9: =E40+E71+IFERROR($E$105/$D$105*D9,0) -> 268182.75 | F9: =IF(OR(D9=0,E9=0),"",ROUND(E9/D9,2)) -> 14.18
A10: 6 | B10: Communications | D10: =D41 -> 196034 | E10: =E41+E72+IFERROR($E$105/$D$105*D10,0) -> 1619013.6 | F10: =IF(OR(D10=0,E10=0),"",ROUND(E10/D10,2)) -> 8.26
A11: 7 | B11: Computer and Information Sciences | D11: =D42 -> 813693 | E11: =E42+E73+IFERROR($E$105/$D$105*D11,0) -> 6983481.2 | F11: =IF(OR(D11=0,E11=0),"",ROUND(E11/D11,2)) -> 8.58
A12: 8 | B12: Construction Trades | D12: =D43 -> 83328 | E12: =E43+E74+IFERROR($E$105/$D$105*D12,0) -> 677203.04 | F12: =IF(OR(D12=0,E12=0),"",ROUND(E12/D12,2)) -> 8.13
A13: 9 | B13: Consumer and Homemaking Education | D13: =D44 -> 562426 | E13: =E44+E75+IFERROR($E$105/$D$105*D13,0) -> 4300742.4 | F13: =IF(OR(D13=0,E13=0),"",ROUND(E13/D13,2)) -> 7.65
A14: 10 | B14: Engineering | D14: =D45 -> 10032 | E14: =E45+E76+IFERROR($E$105/$D$105*D14,0) -> 199894.13 | F14: =IF(OR(D14=0,E14=0),"",ROUND(E14/D14,2)) -> 19.93
A15: 11 | B15: Engineering Related | D15: =D46 -> 242999 | E15: =E46+E77+IFERROR($E$105/$D$105*D15,0) -> 3567838.4 | F15: =IF(OR(D15=0,E15=0),"",ROUND(E15/D15,2)) -> 14.68
A16: 12 | B16: English Language, Lit, Philosophy, Humanities, & Interdisciplinary | D16: =D47 -> 3581392 | E16: =E47+E78+IFERROR($E$105/$D$105*D16,0) -> 23814233 | F16: =IF(OR(D16=0,E16=0),"",ROUND(E16/D16,2)) -> 6.65
... A32: 29 | B32: Developmental Education - Reading/Writing | D32: =D63 -> 0 | E32: =E63+E94+IFERROR($E$105/$D$105*D32,0) -> 0 | F32: =IF(OR(D32=0,E32=0),"",ROUND(E32/D32,2))
C33: Total | D33: =SUM(D5:D32) -> 18861353 | E33: =SUM(E5:E32) -> 1.4244558e+08 | F33: =IF(OR(D33=0,E33=0),"",ROUND(E33/D33,2)) -> 7.55
A35: Fund | B35: Departmental Operating Expense by Discipline | D35: Contact Hours | E35: Expense | F35: Expense per Contact Hour
A36: 1 | B36: Agriculture | D36: =IF(F3="1",SUMIF(Data!A:A,$A$2,Data!CU:CU),0) -> 59180 | E36: =IF(F3="1",SUMIF(Data!$A:$A,$A$2,Data!IO:IO),0) -> 39766 | F36: =IF(OR(D36=0,E36=0),"",ROUND(E36/D36,2)) -> 0.67
A37: 2 | B37: Architecture and Precision Production Trades | D37: =IF(F3="1",SUMIF(Data!A:A,$A$2,Data!CV:CV),0) -> 216765 | E37: =IF(F3="1",SUMIF(Data!$A:$A,$A$2,Data!IP:IP),0) -> 120386 | F37: =IF(OR(D37=0,E37=0),"",ROUND(E37/D37,2)) -> 0.56
A38: 3 | B38: Biology, Physical Sciences, and Science Technology | D38: =IF(F3="1",SUMIF(Data!A:A,$A$2,Data!CW:CW),0) -> 1864000 | E38: =IF($F$3="1",SUMIF(Data!$A:$A,$A$2,Data!IQ:IQ),0) -> 1265244 | F38: =IF(OR(D38=0,E38=0),"",ROUND(E38/D38,2)) -> 0.68
A39: 4 | B39: Business Management, Marketing, and Administrative Services | D39: =IF(F3="1",SUMIF(Data!A:A,$A$2,Data!CX:CX),0) -> 937188 | E39: =IF($F$3="1",SUMIF(Data!$A:$A,$A$2,Data!IR:IR),0) -> 697796 | F39: =IF(OR(D39=0,E39=0),"",ROUND(E39/D39,2)) -> 0.74
A40: 5 | B40: Career Pilot | D40: =IF(F3="1",SUMIF(Data!A:A,$A$2,Data!CY:CY),0) -> 18912 | E40: =IF($F$3="1",SUMIF(Data!$A:$A,$A$2,Data!IS:IS),0) -> 71110 | F40: =IF(OR(D40=0,E40=0),"",ROUND(E40/D40,2)) -> 3.76
A41: 6 | B41: Communications | D41: =IF(F3="1",SUMIF(Data!A:A,$A$2,Data!CZ:CZ),0) -> 196034 | E41: =IF($F$3="1",SUMIF(Data!$A:$A,$A$2,Data!IT:IT),0) -> 294971 | F41: =IF(OR(D41=0,E41=0),"",ROUND(E41/D41,2)) -> 1.5
A42: 7 | B42: Computer and Information Sciences | D42: =IF(F3="1",SUMIF(Data!A:A,$A$2,Data!DA:DA),0) -> 813693 | E42: =IF($F$3="1",SUMIF(Data!$A:$A,$A$2,Data!IU:IU),0) -> 714243 | F42: =IF(OR(D42=0,E42=0),"",ROUND(E42/D42,2)) -> 0.88
A43: 8 | B43: Construction Trades | D43: =IF(F3="1",SUMIF(Data!A:A,$A$2,Data!DB:DB),0) -> 83328 | E43: =IF($F$3="1",SUMIF(Data!$A:$A,$A$2,Data!IV:IV),0) -> 62567 | F43: =IF(OR(D43=0,E43=0),"",ROUND(E43/D43,2)) -> 0.75
A44: 9 | B44: Consumer and Homemaking Education | D44: =IF(F3="1",SUMIF(Data!A:A,$A$2,Data!DC:DC),0) -> 562426 | E44: =IF($F$3="1",SUMIF(Data!$A:$A,$A$2,Data!IW:IW),0) -> 505219 | F44: =IF(OR(D44=0,E44=0),"",ROUND(E44/D44,2)) -> 0.9
A45: 10 | B45: Engineering | D45: =IF(F3="1",SUMIF(Data!A:A,$A$2,Data!DD:DD),0) -> 10032 | E45: =IF($F$3="1",SUMIF(Data!$A:$A,$A$2,Data!IX:IX),0) -> 44438 | F45: =IF(OR(D45=0,E45=0),"",ROUND(E45/D45,2)) -> 4.43
A46: 11 | B46: Engineering Related | D46: =IF(F3="1",SUMIF(Data!A:A,$A$2,Data!DE:DE),0) -> 242999 | E46: =IF($F$3="1",SUMIF(Data!$A:$A,$A$2,Data!IY:IY),0) -> 520220 | F46: =IF(OR(D46=0,E46=0),"",ROUND(E46/D46,2)) -> 2.14
A47: 12 | B47: English Language, Lit, Philosophy, Humanities, & Interdisciplinary | D47: =IF(F3="1",SUMIF(Data!A:A,$A$2,Data!DF:DF),0) -> 3581392 | E47: =IF($F$3="1",SUMIF(Data!$A:$A,$A$2,Data!IZ:IZ),0) -> 1135167 | F47: =IF(OR(D47=0,E47=0),"",ROUND(E47/D47,2)) -> 0.32
A48: 13 | B48: Foreign Languages | D48: =IF(F3="1",SUMIF(Data!A:A,$A$2,Data!DG:DG),0) -> 392000 | E48: =IF($F$3="1",SUMIF(Data!$A:$A,$A$2,Data!JA:JA),0) -> 251261 | F48: =IF(OR(D48=0,E48=0),"",ROUND(E48/D48,2)) -> 0.64
A49: 14 | B49: Health Occupations - Dental Assistants, Medical Lab, and Assoc. Degree Nursing | D49: =IF(F3="1",SUMIF(Data!A:A,$A$2,Data!DH:DH),0) -> 420078 | E49: =IF($F$3="1",SUMIF(Data!$A:$A,$A$2,Data!JB:JB),0) -> 481545 | F49: =IF(OR(D49=0,E49=0),"",ROUND(E49/D49,2)) -> 1.15
A50: 15 | B50: Health Occupations - Dental Hygiene | D50: =IF(F3="1",SUMIF(Data!A:A,$A$2,Data!DI:DI),0) -> 0 | E50: =IF($F$3="1",SUMIF(Data!$A:$A,$A$2,Data!JC:JC),0) -> 0 | F50: =IF(OR(D50=0,E50=0),"",ROUND(E50/D50,2))
A51: 16 | B51: Health Occupations - Other | D51: =IF(F3="1",SUMIF(Data!A:A,$A$2,Data!DJ:DJ),0) -> 710433 | E51: =IF($F$3="1",SUMIF(Data!$A:$A,$A$2,Data!JD:JD),0) -> 523342 | F51: =IF(OR(D51=0,E51=0),"",ROUND(E51/D51,2)) -> 0.74
A52: 17 | B52: Health Occupations - Respiratory Therapy | D52: =IF(F3="1",SUMIF(Data!A:A,$A$2,Data!DK:DK),0) -> 27856 | E52: =IF($F$3="1",SUMIF(Data!$A:$A,$A$2,Data!JE:JE),0) -> 7072 | F52: =IF(OR(D52=0,E52=0),"",ROUND(E52/D52,2)) -> 0.25
A53: 18 | B53: Health Occupations - Vocational Nursing | D53: =IF(F3="1",SUMIF(Data!A:A,$A$2,Data!DL:DL),0) -> 284820 | E53: =IF($F$3="1",SUMIF(Data!$A:$A,$A$2,Data!JF:JF),0) -> 173227 | F53: =IF(OR(D53=0,E53=0),"",ROUND(E53/D53,2)) -> 0.61
A54: 19 | B54: Mathematics | D54: =IF(F3="1",SUMIF(Data!A:A,$A$2,Data!DM:DM),0) -> 3029078 | E54: =IF($F$3="1",SUMIF(Data!$A:$A,$A$2,Data!JG:JG),0) -> 835288 | F54: =IF(OR(D54=0,E54=0),"",ROUND(E54/D54,2)) -> 0.28
A55: 20 | B55: Mechanics and Repairers - Automotive | D55: =IF(F3="1",SUMIF(Data!A:A,$A$2,Data!DN:DN),0) -> 270484 | E55: =IF($F$3="1",SUMIF(Data!$A:$A,$A$2,Data!JH:JH),0) -> 106823 | F55: =IF(OR(D55=0,E55=0),"",ROUND(E55/D55,2)) -> 0.39
A56: 21 | B56: Mechanics and Repairers - Diesel, Aviation Mechanics, and Transportation Workers | D56: =IF(F3="1",SUMIF(Data!A:A,$A$2,Data!DO:DO),0) -> 236316 | E56: =IF($F$3="1",SUMIF(Data!$A:$A,$A$2,Data!JI:JI),0) -> 602896 | F56: =IF(OR(D56=0,E56=0),"",ROUND(E56/D56,2)) -> 2.55
A57: 22 | B57: Mechanics and Repairers - Electronics | D57: =IF(F3="1",SUMIF(Data!A:A,$A$2,Data!DP:DP),0) -> 2160 | E57: =IF($F$3="1",SUMIF(Data!$A:$A,$A$2,Data!JJ:JJ),0) -> 549 | F57: =IF(OR(D57=0,E57=0),"",ROUND(E57/D57,2)) -> 0.25
A58: 23 | B58: Physical Education and Fitness | D58: =IF(F3="1",SUMIF(Data!A:A,$A$2,Data!DQ:DQ),0) -> 454686 | E58: =IF($F$3="1",SUMIF(Data!$A:$A,$A$2,Data!JK:JK),0) -> 345689 | F58: =IF(OR(D58=0,E58=0),"",ROUND(E58/D58,2)) -> 0.76
A59: 24 | B59: Protective Services and Public Administration | D59: =IF(F3="1",SUMIF(Data!A:A,$A$2,Data!DR:DR),0) -> 460180 | E59: =IF($F$3="1",SUMIF(Data!$A:$A,$A$2,Data!JL:JL),0) -> 149900 | F59: =IF(OR(D59=0,E59=0),"",ROUND(E59/D59,2)) -> 0.33
A60: 25 | B60: Psychology, Social Sciences, and History | D60: =IF(F3="1",SUMIF(Data!A:A,$A$2,Data!DS:DS),0) -> 3077320 | E60: =IF($F$3="1",SUMIF(Data!$A:$A,$A$2,Data!JM:JM),0) -> 866658 | F60: =IF(OR(D60=0,E60=0),"",ROUND(E60/D60,2)) -> 0.28
A61: 26 | B61: Visual and Performing Arts | D61: =IF(F3="1",SUMIF(Data!A:A,$A$2,Data!DT:DT),0) -> 909993 | E61: =IF($F$3="1",SUMIF(Data!$A:$A,$A$2,Data!JN:JN),0) -> 902769 | F61: =IF(OR(D61=0,E61=0),"",ROUND(E61/D61,2)) -> 0.99
A62: 28 | B62: Developmental Education - Math | D62: =IF(F3="1",SUMIF(Data!A:A,$A$2,Data!DV:DV),0) -> 0 | E62: =IF($F$3="1",SUMIF(Data!$A:$A,$A$2,Data!JP:JP),0) -> 0 | F62: =IF(OR(D62=0,E62=0),"",ROUND(E62/D62,2))
A63: 29 | B63: Developmental Education - Reading/Writing | D63: =IF(F3="1",SUMIF(Data!A:A,$A$2,Data!DW:DW),0) -> 0 | E63: =IF($F$3="1",SUMIF(Data!$A:$A,$A$2,Data!JQ:JQ),0) -> 0 | F63: =IF(OR(D63=0,E63=0),"",ROUND(E63/D63,2))
C64: Total | D64: =SUM(D36:D63) -> 18861353 | E64: =SUM(E36:E63) -> 10718146 | F64: =IF(OR(D64=0,E64=0),"",ROUND(E64/D64,2)) -> 0.57
A66: Fund | B66: Faculty Salaries by Discipline | D66: Contact Hours | E66: Expense | F66: Expense per Contact Hour
A67: 1 | B67: Agriculture | D67: =D36 -> 59180 | E67: =IF(F3="1",SUMIF(Data!A:A,$A$2,Data!DY:DY),0) -> 92488 | F67: =IF(OR(D67=0,E67=0),"",ROUND(E67/D67,2)) -> 1.56
A68: 2 | B68: Architecture and Precision Production Trades | D68: =D37 -> 216765 | E68: =IF(F3="1",SUMIF(Data!A:A,$A$2,Data!DZ:DZ),0) -> 677522 | F68: =IF(OR(D68=0,E68=0),"",ROUND(E68/D68,2)) -> 3.13
A69: 3 | B69: Biology, Physical Sciences, and Science Technology | D69: =D38 -> 1864000 | E69: =IF(F3="1",SUMIF(Data!A:A,$A$2,Data!EA:EA),0) -> 6063394 | F69: =IF(OR(D69=0,E69=0),"",ROUND(E69/D69,2)) -> 3.25
A70: 4 | B70: Business Management, Marketing, and Administrative Services | D70: =D39 -> 937188 | E70: =IF(F3="1",SUMIF(Data!A:A,$A$2,Data!EB:EB),0) -> 3972616 | F70: =IF(OR(D70=0,E70=0),"",ROUND(E70/D70,2)) -> 4.24
A71: 5 | B71: Career Pilot | D71: =D40 -> 18912 | E71: =IF(F3="1",SUMIF(Data!A:A,$A$2,Data!EC:EC),0) -> 130068 | F71: =IF(OR(D71=0,E71=0),"",ROUND(E71/D71,2)) -> 6.88
A72: 6 | B72: Communications | D72: =D41 -> 196034 | E72: =IF(F3="1",SUMIF(Data!A:A,$A$2,Data!ED:ED),0) -> 629499 | F72: =IF(OR(D72=0,E72=0),"",ROUND(E72/D72,2)) -> 3.21
A73: 7 | B73: Computer and Information Sciences | D73: =D42 -> 813693 | E73: =IF(F3="1",SUMIF(Data!A:A,$A$2,Data!EE:EE),0) -> 3386344 | F73: =IF(OR(D73=0,E73=0),"",ROUND(E73/D73,2)) -> 4.16
A74: 8 | B74: Construction Trades | D74: =D43 -> 83328 | E74: =IF(F3="1",SUMIF(Data!A:A,$A$2,Data!EF:EF),0) -> 319407 | F74: =IF(OR(D74=0,E74=0),"",ROUND(E74/D74,2)) -> 3.83
A75: 9 | B75: Consumer and Homemaking Education | D75: =D44 -> 562426 | E75: =IF(F3="1",SUMIF(Data!A:A,$A$2,Data!EG:EG),0) -> 1802862 | F75: =IF(OR(D75=0,E75=0),"",ROUND(E75/D75,2)) -> 3.21
A76: 10 | B76: Engineering | D76: =D45 -> 10032 | E76: =IF(F3="1",SUMIF(Data!A:A,$A$2,Data!EH:EH),0) -> 119913 | F76: =IF(OR(D76=0,E76=0),"",ROUND(E76/D76,2)) -> 11.95
A77: 11 | B77: Engineering Related | D77: =D46 -> 242999 | E77: =IF(F3="1",SUMIF(Data!A:A,$A$2,Data!EI:EI),0) -> 2186679 | F77: =IF(OR(D77=0,E77=0),"",ROUND(E77/D77,2)) -> 9
A78: 12 | B78: English Language, Lit, Philosophy, Humanities, & Interdisciplinary | D78: =D47 -> 3581392 | E78: =IF(F3="1",SUMIF(Data!A:A,$A$2,Data!EJ:EJ),0) -> 9990283 | F78: =IF(OR(D78=0,E78=0),"",ROUND(E78/D78,2)) -> 2.79
A79: 13 | B79: Foreign Languages | D79: =D48 -> 392000 | E79: =IF(F3="1",SUMIF(Data!A:A,$A$2,Data!EK:EK),0) -> 1462262 | F79: =IF(OR(D79=0,E79=0),"",ROUND(E79/D79,2)) -> 3.73
A80: 14 | B80: Health Occupations - Dental Assistants, Medical Lab, and Assoc. Degree Nursing | D80: =D49 -> 420078 | E80: =IF(F3="1",SUMIF(Data!A:A,$A$2,Data!EL:EL),0) -> 3127357 | F80: =IF(OR(D80=0,E80=0),"",ROUND(E80/D80,2)) -> 7.44
A81: 15 | B81: Health Occupations - Dental Hygiene | D81: =D50 -> 0 | E81: =IF(F3="1",SUMIF(Data!A:A,$A$2,Data!EM:EM),0) -> 0 | F81: =IF(OR(D81=0,E81=0),"",ROUND(E81/D81,2))
A82: 16 | B82: Health Occupations - Other | D82: =D51 -> 710433 | E82: =IF(F3="1",SUMIF(Data!A:A,$A$2,Data!EN:EN),0) -> 2206688 | F82: =IF(OR(D82=0,E82=0),"",ROUND(E82/D82,2)) -> 3.11
A83: 17 | B83: Health Occupations - Respiratory Therapy | D83: =D52 -> 27856 | E83: =IF(F3="1",SUMIF(Data!A:A,$A$2,Data!EO:EO),0) -> 316019 | F83: =IF(OR(D83=0,E83=0),"",ROUND(E83/D83,2)) -> 11.34
A84: 18 | B84: Health Occupations - Vocational Nursing | D84: =D53 -> 284820 | E84: =IF(F3="1",SUMIF(Data!A:A,$A$2,Data!EP:EP),0) -> 1211915 | F84: =IF(OR(D84=0,E84=0),"",ROUND(E84/D84,2)) -> 4.26
A85: 19 | B85: Mathematics | D85: =D54 -> 3029078 | E85: =IF(F3="1",SUMIF(Data!A:A,$A$2,Data!EQ:EQ),0) -> 8894644 | F85: =IF(OR(D85=0,E85=0),"",ROUND(E85/D85,2)) -> 2.94
A86: 20 | B86: Mechanics and Repairers - Automotive | D86: =D55 -> 270484 | E86: =IF(F3="1",SUMIF(Data!A:A,$A$2,Data!ER:ER),0) -> 238493 | F86: =IF(OR(D86=0,E86=0),"",ROUND(E86/D86,2)) -> 0.88
A87: 21 | B87: Mechanics and Repairers - Diesel, Aviation Mechanics, and Transportation Workers | D87: =D56 -> 236316 | E87: =IF(F3="1",SUMIF(Data!A:A,$A$2,Data!ES:ES),0) -> 1366924 | F87: =IF(OR(D87=0,E87=0),"",ROUND(E87/D87,2)) -> 5.78
A88: 22 | B88: Mechanics and Repairers - Electronics | D88: =D57 -> 2160 | E88: =IF(F3="1",SUMIF(Data!A:A,$A$2,Data!ET:ET),0) -> 155 | F88: =IF(OR(D88=0,E88=0),"",ROUND(E88/D88,2)) -> 0.07
A89: 23 | B89: Physical Education and Fitness | D89: =D58 -> 454686 | E89: =IF(F3="1",SUMIF(Data!A:A,$A$2,Data!EU:EU),0) -> 1805502 | F89: =IF(OR(D89=0,E89=0),"",ROUND(E89/D89,2)) -> 3.97
A90: 24 | B90: Protective Services and Public Administration | D90: =D59 -> 460180 | E90: =IF(F3="1",SUMIF(Data!A:A,$A$2,Data!EV:EV),0) -> 1220032 | F90: =IF(OR(D90=0,E90=0),"",ROUND(E90/D90,2)) -> 2.65
A91: 25 | B91: Psychology, Social Sciences, and History | D91: =D60 -> 3077320 | E91: =IF(F3="1",SUMIF(Data!A:A,$A$2,Data!EW:EW),0) -> 9198271 | F91: =IF(OR(D91=0,E91=0),"",ROUND(E91/D91,2)) -> 2.99
A92: 26 | B92: Visual and Performing Arts | D92: =D61 -> 909993 | E92: =IF(F3="1",SUMIF(Data!A:A,$A$2,Data!EX:EX),0) -> 4482794 | F92: =IF(OR(D92=0,E92=0),"",ROUND(E92/D92,2)) -> 4.93
A93: 28 | B93: Developmental Education - Math | D93: =D62 -> 0 | E93: =IF(F3="1",SUMIF(Data!A:A,$A$2,Data!EZ:EZ),0) -> 0 | F93: =IF(OR(D93=0,E93=0),"",ROUND(E93/D93,2))
A94: 29 | B94: Developmental Education - Reading/Writing | D94: =D63 -> 0 | E94: =IF(F3="1",SUMIF(Data!A:A,$A$2,Data!FA:FA),0) -> 0 | F94: =IF(OR(D94=0,E94=0),"",ROUND(E94/D94,2))
C95: Total | D95: =SUM(D67:D94) -> 18861353 | E95: =SUM(E67:E94) -> 64902131 | F95: =IF(OR(D95=0,E95=0),"",ROUND(E95/D95,2)) -> 3.44
B97: Allocated Administrative Expense | D97: Contact Hours | E97: Expense | F97: Expense per Contact Hour
B98: Institutional Support | E98: =IF(F3="1",SUMIF(Data!A:A,$A$2,Data!AH:AH),0) -> 25583934 | F98: =IF(OR(E98=0,E98=0),"",ROUND(E98/$D$105,2)) -> 1.36
B99: Student Services | E99: =IF(F3="1",SUMIF(Data!A:A,$A$2,Data!AI:AI),0) -> 15149317 | F99: =IF(OR(E99=0,E99=0),"",ROUND(E99/$D$105,2)) -> 0.8
B100: Library | E100: =IF(F3="1",SUMIF(Data!A:A,$A$2,Data!AJ:AJ),0) -> 5818338 | F100: =IF(OR(E100=0,E100=0),"",ROUND(E100/$D$105,2)) -> 0.31
B101: Instructional Administration | E101: =IF(F3="1",SUMIF(Data!A:A,$A$2,Data!AK:AK),0) -> 8243683 | F101: =IF(OR(E101=0,E101=0),"",ROUND(E101/$D$105,2)) -> 0.44
B102: Organized Activities | E102: =IF(F3="1",SUMIF(Data!A:A,$A$2,Data!AL:AL),0) -> 305249 | F102: =IF(OR(E102=0,E102=0),"",ROUND(E102/$D$105,2)) -> 0.02
B103: Equipment Depreciation | E103: =IF(F3="1",SUMIF(Data!A:A,$A$2,Data!AM:AM),0) -> 1e-05 | F103: =IF(OR(E103=0,E103=0),"",ROUND(E103/$D$105,2)) -> 0
B104: Local Benefits | E104: =IF(F3="1",SUMIF(Data!A:A,$A$2,Data!Q:Q),0) -> 11724786 | F104: =IF(OR(E104=0,E104=0),"",ROUND(E104/$D$105,2)) -> 0.62
C105: Total | D105: =D95 -> 18861353 | E105: =SUM(E98:E104) -> 66825307 | F105: =IF($D$105=0,"",ROUND(E105/$D$105,2)) -> 3.54
B107: Annual Financial Report - Schedule B
B108: Unrestricted - Educational Activities | C108: Salaries and Wages | D108: Local Benefits | E108: Other Expenses | F108: Total
B109: Instruction | C109: =E95+IF(F3="1",SUMIF(Data!$A:$A,$A$2,Data!GF:GF),0) -> 64902131 | D109: =IF(F3="1",SUMIF(Data!$A:$A,$A$2,Data!HJ:HJ),0) -> 0 | E109: =IF(F3="1",SUMIF(Data!$A:$A,$A$2,Data!IN:IN),0) -> 0 | F109: =SUM(C109:E109) -> 64902131
B110: Research | C110: =IF(F3="1",SUMIF(Data!A:A,$A$2,Data!W:W),0) -> 0 | E110: =IF(F3="1",SUMIF(Data!A:A,$A$2,Data!W:W),0) -> 0 | F110: =SUM(C110:E110) -> 0
B111: Public Service | C111: =IF(F3="1",SUMIF(Data!A:A,$A$2,Data!AS:AS),0) -> 0 | E111: =IF(F3="1",SUMIF(Data!A:A,$A$2,Data!AX:AX),0) -> 0 | F111: =SUM(C111:E111) -> 0
B112: Academic Support | C112: =IF(F3="1",SUMIF(Data!A:A,$A$2,Data!V:V),0) -> 0 | E112: =IF(F3="1",SUMIF(Data!A:A,$A$2,Data!AC:AC),0) -> 0 | F112: =SUM(C112:E112) -> 0
B113: Student Services | C113: =IF(F3="1",SUMIF(Data!A:A,$A$2,Data!U:U),0) -> 0 | E113: =IF(F3="1",SUMIF(Data!A:A,$A$2,Data!AB:AB),0) -> 0 | F113: =SUM(C113:E113) -> 0
B114: Instructional Support | C114: =IF(F3="1",SUMIF(Data!A:A,$A$2,Data!T:T),0) -> 0 | E114: =IF(F3="1",SUMIF(Data!A:A,$A$2,Data!AA:AA),0) -> 0 | F114: =SUM(C114:E114) -> 0
B115: Operation and Maintenance of Plant | C115: =IF(F3="1",SUMIF(Data!A:A,$A$2,Data!BI:BI),0) -> 0 | D115: =IF(F3="1",SUMIF(Data!A:A,$A$2,Data!BL:BL),0) -> 0 | E115: =IF(F3="1",SUMIF(Data!A:A,$A$2,Data!BU:BU),0) -> 0 | F115: =SUM(C115:E115) -> 0
B116: Scholarships and Fellowships | C116: =IF(F3="1",SUMIF(Data!A:A,$A$2,Data!X:X),0) -> 0 | E116: =E102 -> 305249 | F116: =SUM(C116:E116) -> 305249
B117: Other | D117: =IF(F3="1",SUMIF(Data!A:A,$A$2,Data!Q:Q),0) -> 11724786 | F117: =SUM(C117:E117) -> 11724786
B118: Total | C118: =SUM(C109:C116) -> 64902131 | D118: =SUM(D109:D116) -> 0 | E118: =SUM(E109:E116) -> 305249 | F118: =SUM(F109:F116) -> 65207380
B120: Depreciation Expense - Equipment | E120: =IF(F3="1",SUMIF(Data!A:A,$A$2,Data!AM:AM),0) -> 1e-05 | F120: =SUM(C120:E120) -> 1e-05
...

Sheet 2
A1: =Summary!A1 -> Community and Technical Colleges, Report of Fundable Operating Expenses, Fiscal Year (FY) 2003
A2: 003539 | B2: =VLOOKUP(A2,Data!A:G,7,0) -> Alvin Community College
F3: =IFERROR(VLOOKUP(A2,Data!A:C,3,0),"0") -> 1
A4: Fund | B4: Total Expense by Discipline | D4: Contact Hours | E4: Expense | F4: Expense per Contact Hour
A5: 1 | B5: Agriculture | D5: =D36 -> 34128 | E5: =E36+E67+IFERROR($E$105/$D$105*D5,0) -> 179435.02 | F5: =IF(OR(D5=0,E5=0),"",ROUND(E5/D5,2)) -> 5.26
A6: 2 | B6: Architecture and Precision Production Trades | D6: =D37 -> 72986 | E6: =E37+E68+IFERROR($E$105/$D$105*D6,0) -> 515720.37 | F6: =IF(OR(D6=0,E6=0),"",ROUND(E6/D6,2)) -> 7.07
A7: 3 | B7: Biology, Physical Sciences, and Science Technology | D7: =D38 -> 217216 | E7: =E38+E69+IFERROR($E$105/$D$105*D7,0) -> 1430857.3 | F7: =IF(OR(D7=0,E7=0),"",ROUND(E7/D7,2)) -> 6.59
A8: 4 | B8: Business Management, Marketing, and Administrative Services | D8: =D39 -> 248013 | E8: =E39+E70+IFERROR($E$105/$D$105*D8,0) -> 1840900.4 | F8: =IF(OR(D8=0,E8=0),"",ROUND(E8/D8,2)) -> 7.42
A9: 5 | B9: Career Pilot | D9: =D40 -> 0 | E9: =E40+E71+IFERROR($E$105/$D$105*D9,0) -> 0 | F9: =IF(OR(D9=0,E9=0),"",ROUND(E9/D9,2))
A10: 6 | B10: Communications | D10: =D41 -> 55866 | E10: =E41+E72+IFERROR($E$105/$D$105*D10,0) -> 363276.96 | F10: =IF(OR(D10=0,E10=0),"",ROUND(E10/D10,2)) -> 6.5
A11: 7 | B11: Computer and Information Sciences | D11: =D42 -> 236456 | E11: =E42+E73+IFERROR($E$105/$D$105*D11,0) -> 1505111.9 | F11: =IF(OR(D11=0,E11=0),"",ROUND(E11/D11,2)) -> 6.37
A12: 8 | B12: Construction Trades | D12: =D43 -> 0 | E12: =E43+E74+IFERROR($E$105/$D$105*D12,0) -> 0 | F12: =IF(OR(D12=0,E12=0),"",ROUND(E12/D12,2))
A13: 9 | B13: Consumer and Homemaking Education | D13: =D44 -> 42510 | E13: =E44+E75+IFERROR($E$105/$D$105*D13,0) -> 289654.61 | F13: =IF(OR(D13=0,E13=0),"",ROUND(E13/D13,2)) -> 6.81
A14: 10 | B14: Engineering | D14: =D45 -> 0 | E14: =E45+E76+IFERROR($E$105/$D$105*D14,0) -> 0 | F14: =IF(OR(D14=0,E14=0),"",ROUND(E14/D14,2))
A15: 11 | B15: Engineering Related | D15: =D46 -> 48280 | E15: =E46+E77+IFERROR($E$105/$D$105*D15,0) -> 263277.68 | F15: =IF(OR(D15=0,E15=0),"",ROUND(E15/D15,2)) -> 5.45
A16: 12 | B16: English Language, Lit, Philosophy, Humanities, & Interdisciplinary | D16: =D47 -> 263288 | E16: =E47+E78+IFERROR($E$105/$D$105*D16,0) -> 1832332.5 | F16: =IF(OR(D16=0,E16=0),"",ROUND(E16/D16,2)) -> 6.96
... A32: 29 | B32: Developmental Education - Reading/Writing | D32: =D63 -> 0 | E32: =E63+E94+IFERROR($E$105/$D$105*D32,0) -> 0 | F32: =IF(OR(D32=0,E32=0),"",ROUND(E32/D32,2))
