Workbook
Name CREATION: #REF!
Name CREATION: #REF!
Name CREATION: #REF!
Name CREATION: #REF!
Name CREATION: #REF!
Name HELP: #REF!
Name HELP: #REF!
Name HELP: #REF!
Name HELP: #REF!
Name HELP: #REF!
Name Print_Area_MI: 'FEB04 TEMPLATE'!$A$1:$F$69
Name Print_Area_MI: 'TRA RED FOR CHT'!$A$1:$G$12

Sheet Pupil Data
A1: Pupil Data: FEB 2011 CSA VS. NOV 2010 CSA
C3: School District | D3: SD Fudge | E3: Charter Sch | F3: CH Fudge | G3: Subtotal | H3: Private Alt | I3: College PSEO | J3: Total
A5: FEB 2011 FORECAST
A7: AADM-1.0
B8: FY 2003 | C8: 817235 | D8: 0 | E8: 11991 | F8: 0 | G8: =SUM(C8:F8) -> 829226 | H8: 2331 | I8: 3669 | J8: =SUM(G8:I8) -> 835226
B9: FY 2004 | C9: 810532 | D9: 0 | E9: 13948 | F9: 0 | G9: =SUM(C9:F9) -> 824480 | H9: 2013 | I9: 3331 | J9: =SUM(G9:I9) -> 829824
B10: FY 2005 | C10: 803304 | D10: 0 | E10: 17121 | F10: 0 | G10: =SUM(C10:F10) -> 820425 | H10: 1975 | I10: 3443 | J10: =SUM(G10:I10) -> 825843
B11: FY 2006 | C11: 801109 | D11: 0 | E11: 20307 | F11: 0 | G11: =SUM(C11:F11) -> 821416 | H11: 1898 | I11: 3229 | J11: =SUM(G11:I11) -> 826543
B12: FY 2007 | C12: 798335 | D12: 405 | E12: 23588 | F12: 0 | G12: =SUM(C12:F12) -> 822328 | H12: 1701 | I12: 3168 | J12: =SUM(G12:I12) -> 827197
B13: FY 2008 | C13: 791357 | D13: 326 | E13: 27753 | F13: 0 | G13: =SUM(C13:F13) -> 819436 | H13: 1389 | I13: 2930 | J13: =SUM(G13:I13) -> 823755
B14: FY 2009 | C14: 784790 | D14: 240 | E14: 31687 | F14: 0 | G14: =SUM(C14:F14) -> 816717 | H14: 1266 | I14: 3038 | J14: =SUM(G14:I14) -> 821021
B15: FY 2010 | C15: 783128 | D15: 0 | E15: 34463 | F15: 0 | G15: =SUM(C15:F15) -> 817591 | H15: 1243 | I15: 3089 | J15: =SUM(G15:I15) -> 821923
B16: FY 2011 | C16: 780826 | D16: 1613 | E16: 37204 | F16: 0 | G16: =SUM(C16:F16) -> 819643 | H16: 1409 | I16: =I15 -> 3089 | J16: =SUM(G16:I16) -> 824141
B17: FY 2012 | C17: 777060 | D17: 6127 | E17: 39724 | F17: 1746 | G17: =SUM(C17:F17) -> 824657 | H17: =H16 -> 1409 | I17: =I16 -> 3089 | J17: =SUM(G17:I17) -> 829155
B18: FY 2013 | C18: 773087 | D18: 13683 | E18: 40819 | F18: 4932 | G18: =SUM(C18:F18) -> 832521 | H18: =H17 -> 1409 | I18: =I17 -> 3089 | J18: =SUM(G18:I18) -> 837019 | K18: =SUM(J8:J18) -> 9101647
B19: FY 2014 | C19: 770380 | D19: 20057 | E19: 40819 | F19: 9551 | G19: =SUM(C19:F19) -> 840807 | H19: =H18 -> 1409 | I19: =I18 -> 3089 | J19: =SUM(G19:I19) -> 845305
B20: FY 2015 | C20: 768720 | D20: 24650 | E20: 40819 | F20: 14535 | G20: =SUM(C20:F20) -> 848724 | H20: =H19 -> 1409 | I20: =I19 -> 3089 | J20: =SUM(G20:I20) -> 853222
A21: AWADM-1.0
B22: FY 2003 | C22: 945648 | D22: 0 | E22: 13552 | F22: 0 | G22: =SUM(C22:F22) -> 959200 | H22: 2956 | I22: 4770 | J22: =SUM(G22:I22) -> 966926
B23: FY 2004 | C23: 937828 | D23: 0 | E23: 15841 | F23: 0 | G23: =SUM(C23:F23) -> 953669 | H23: 2550 | I23: 4330 | J23: =SUM(G23:I23) -> 960549
B24: FY 2005 | C24: 930314 | D24: 0 | E24: 19451 | F24: 0 | G24: =SUM(C24:F24) -> 949765 | H24: 2499 | I24: 4477 | J24: =SUM(G24:I24) -> 956741
B25: FY 2006 | C25: 927594 | D25: 0 | E25: 22936 | F25: 0 | G25: =SUM(C25:F25) -> 950530 | H25: 2397 | I25: 4198 | J25: =SUM(G25:I25) -> 957125
B26: FY 2007 | C26: 924184 | D26: 0 | E26: 26680 | F26: 0 | G26: =SUM(C26:F26) -> 950864 | H26: 2166 | I26: 4119 | J26: =SUM(G26:I26) -> 957149
B27: FY 2008 | C27: 918166 | D27: 388 | E27: 31619 | F27: 0 | G27: =SUM(C27:F27) -> 950173 | H27: 1787 | I27: 3808 | J27: =SUM(G27:I27) -> 955768
B28: FY 2009 | C28: 908899 | D28: 274 | E28: 36020 | F28: 0 | G28: =SUM(C28:F28) -> 945193 | H28: 1619 | I28: 3949 | J28: =SUM(G28:I28) -> 950761
B29: FY 2010 | C29: 905826 | D29: 0 | E29: 39107 | F29: 0 | G29: =SUM(C29:F29) -> 944933 | H29: 1586 | I29: 4015 | J29: =SUM(G29:I29) -> 950534
B30: FY 2011 | C30: 901859 | D30: 1839 | E30: 42157 | F30: 0 | G30: =SUM(C30:F30) -> 945855 | H30: 1795 | I30: =I29 -> 4015 | J30: =SUM(G30:I30) -> 951665
B31: FY 2012 | C31: 896895 | D31: 6113 | E31: 45224 | F31: 1767 | G31: =SUM(C31:F31) -> 949999 | H31: =H30 -> 1795 | I31: =I30 -> 4015 | J31: =SUM(G31:I31) -> 955809
B32: FY 2013 | C32: 891855 | D32: 14471 | E32: 46516 | F32: 5325 | G32: =SUM(C32:F32) -> 958167 | H32: =H31 -> 1795 | I32: =I31 -> 4015 | J32: =SUM(G32:I32) -> 963977 | K32: =SUM(J22:J32) -> 10527004
B33: FY 2014 | C33: 888543 | D33: 22468 | E33: 46516 | F33: 10559 | G33: =SUM(C33:F33) -> 968086 | H33: =H32 -> 1795 | I33: =I32 -> 4015 | J33: =SUM(G33:I33) -> 973896
B34: FY 2015 | C34: 886378 | D34: 28835 | E34: 46516 | F34: 16206 | G34: =SUM(C34:F34) -> 977935 | H34: =H33 -> 1795 | I34: =I33 -> 4015 | J34: =SUM(G34:I34) -> 983745
A35: AMCPU-1.0
B36: FY 2003 | C36: 948532 | D36: 0 | E36: 13614 | F36: 0 | G36: =SUM(C36:F36) -> 962146 | H36: 2956 | I36: 4770 | J36: =SUM(G36:I36) -> 969872
B37: FY 2004 | C37: 941129 | D37: 0 | E37: 15967 | F37: 0 | G37: =SUM(C37:F37) -> 957096 | H37: 2550 | I37: 4330 | J37: =SUM(G37:I37) -> 963976
B38: FY 2005 | C38: 933497 | D38: 0 | E38: 19538 | F38: 0 | G38: =SUM(C38:F38) -> 953035 | H38: 2499 | I38: 4477 | J38: =SUM(G38:I38) -> 960011
B39: FY 2006 | C39: 929990 | D39: 0 | E39: 23051 | F39: 0 | G39: =SUM(C39:F39) -> 953041 | H39: 2397 | I39: 4198 | J39: =SUM(G39:I39) -> 959636
B40: FY 2007 | C40: 926532 | D40: 0 | E40: 26756 | F40: 0 | G40: =SUM(C40:F40) -> 953288 | H40: 2397 | I40: 4198 | J40: =SUM(G40:I40) -> 959883
B41: FY 2008 | C41: 921287 | D41: 412 | E41: 31733 | F41: 0 | G41: =SUM(C41:F41) -> 953432 | H41: =H27 -> 1787 | I41: =I27 -> 3808 | J41: =SUM(G41:I41) -> 959027 | K41: 956680.63
B42: FY 2009 | C42: 912029 | D42: 301 | E42: 36257 | F42: 0 | G42: =SUM(C42:F42) -> 948587 | H42: =H28 -> 1619 | I42: =I28 -> 3949 | J42: =SUM(G42:I42) -> 954155 | K42: =G41-K41 -> -3248.63
B43: FY 2010 | C43: 907892 | D43: 0 | E43: 39318 | F43: 0 | G43: =SUM(C43:F43) -> 947210 | H43: =H29 -> 1586 | I43: =I29 -> 4015 | J43: =SUM(G43:I43) -> 952811
B44: FY 2011 | C44: 904209 | D44: 1563 | E44: 42325 | F44: 0 | G44: =SUM(C44:F44) -> 948097 | H44: =H30 -> 1795 | I44: =I30 -> 4015 | J44: =SUM(G44:I44) -> 953907
B45: FY 2012 | C45: 898958 | D45: 5534 | E45: 45353 | F45: 1825 | G45: =SUM(C45:F45) -> 951670 | H45: =H31 -> 1795 | I45: =I31 -> 4015 | J45: =SUM(G45:I45) -> 957480
B46: FY 2013 | C46: 893802 | D46: 13604 | E46: 46614 | F46: 5434 | G46: =SUM(C46:F46) -> 959454 | H46: =H32 -> 1795 | I46: =I32 -> 4015 | J46: =SUM(G46:I46) -> 965264 | K46: =C46+D46 -> 907406
B47: FY 2014 | C47: 890261 | D47: 21835 | E47: 46516 | F47: 10786 | G47: =SUM(C47:F47) -> 969398 | H47: =H33 -> 1795 | I47: =I33 -> 4015 | J47: =SUM(G47:I47) -> 975208 | K47: =C47+D47 -> 912096
B48: FY 2015 | C48: 887894 | D48: 28409 | E48: 46516 | F48: 16456 | G48: =SUM(C48:F48) -> 979275 | H48: =H34 -> 1795 | I48: =I34 -> 4015 | J48: =SUM(G48:I48) -> 985085 | K48: =C48+D48 -> 916303
A50: ADM-1.0
B51: FY 2003 | C51: 829233 | D51: 0 | E51: NA | F51: NA | G51: =SUM(C51:F51) -> 829233 | H51: 2331 | I51: 3669 | J51: =SUM(G51:I51) -> 835233
B52: FY 2004 | C52: 824483 | D52: 0 | E52: NA | F52: NA | G52: =SUM(C52:F52) -> 824483 | H52: 2013 | I52: 3331 | J52: =SUM(G52:I52) -> 829827
B53: FY 2005 | C53: 820425 | D53: 0 | E53: NA | F53: NA | G53: =SUM(C53:F53) -> 820425 | H53: 1975 | I53: 3443 | J53: =SUM(G53:I53) -> 825843
B54: FY 2006 | C54: 821417 | D54: 0 | E54: NA | F54: NA | G54: =SUM(C54:F54) -> 821417 | H54: 1898 | I54: 3229 | J54: =SUM(G54:I54) -> 826544
B55: FY 2007 | C55: 821841 | D55: 487 | E55: NA | F55: NA | G55: =SUM(C55:F55) -> 822328 | H55: 1701 | I55: 3168 | J55: =SUM(G55:I55) -> 827197
B56: FY 2008 | C56: 818978 | D56: 458 | E56: NA | F56: NA | G56: =SUM(C56:F56) -> 819436 | H56: =H13 -> 1389 | I56: =I13 -> 2930 | J56: =SUM(G56:I56) -> 823755
B57: FY 2009 | C57: 816234 | D57: 482 | E57: NA | F57: NA | G57: =SUM(C57:F57) -> 816716 | H57: =H14 -> 1266 | I57: =I14 -> 3038 | J57: =SUM(G57:I57) -> 821020
B58: FY 2010 | C58: 817599 | D58: -8 | E58: NA | F58: NA | G58: =SUM(C58:F58) -> 817591 | H58: =H15 -> 1243 | I58: =I15 -> 3089 | J58: =SUM(G58:I58) -> 821923
B59: FY 2011 | C59: 802433 | D59: 17210 | E59: NA | F59: NA | G59: =SUM(C59:F59) -> 819643 | H59: =H16 -> 1409 | I59: =I16 -> 3089 | J59: =SUM(G59:I59) -> 824141
B60: FY 2012 | C60: 797027 | D60: 27631 | E60: 0 | F60: 0 | G60: =SUM(C60:F60) -> 824658 | H60: =H17 -> 1409 | I60: =I17 -> 3089 | J60: =SUM(G60:I60) -> 829156
B61: FY 2013 | C61: 794534 | D61: 37987 | E61: 0 | F61: 0 | G61: =SUM(C61:F61) -> 832521 | H61: =H18 -> 1409 | I61: =I18 -> 3089 | J61: =SUM(G61:I61) -> 837019 | K61: =SUM(J51:J61) -> 9101658
B62: FY 2014 | C62: 793331 | D62: 47475 | E62: 0 | F62: 0 | G62: =SUM(C62:F62) -> 840806 | H62: =H19 -> 1409 | I62: =I19 -> 3089 | J62: =SUM(G62:I62) -> 845304
B63: FY 2015 | C63: 793474 | D63: 55250 | E63: 0 | F63: 0 | G63: =SUM(C63:F63) -> 848724 | H63: =H20 -> 1409 | I63: =I20 -> 3089 | J63: =SUM(G63:I63) -> 853222
A64: WADM-1.0
B65: FY 2003 | C65: 959208 | D65: 0 | E65: NA | F65: NA | G65: =SUM(C65:F65) -> 959208 | H65: 2956 | I65: 4770 | J65: =SUM(G65:I65) -> 966934
B66: FY 2004 | C66: 953673 | D66: 0 | E66: NA | F66: NA | G66: =SUM(C66:F66) -> 953673 | H66: 2550 | I66: 4330 | J66: =SUM(G66:I66) -> 960553
B67: FY 2005 | C67: 949765 | D67: 0 | E67: NA | F67: NA | G67: =SUM(C67:F67) -> 949765 | H67: 2499 | I67: 4477 | J67: =SUM(G67:I67) -> 956741
B68: FY 2006 | C68: 950532 | D68: 0 | E68: NA | F68: NA | G68: =SUM(C68:F68) -> 950532 | H68: 2397 | I68: 4198 | J68: =SUM(G68:I68) -> 957127
B69: FY 2007 | C69: 950863 | D69: 0 | E69: NA | F69: NA | G69: =SUM(C69:F69) -> 950863 | H69: 2166 | I69: 4119 | J69: =SUM(G69:I69) -> 957148
B70: FY 2008 | C70: 949624 | D70: 562 | E70: NA | F70: NA | G70: =SUM(C70:F70) -> 950186 | H70: =H27 -> 1787 | I70: =I27 -> 3808 | J70: =SUM(G70:I70) -> 955781
B71: FY 2009 | C71: 944635 | D71: 558 | E71: NA | F71: NA | G71: =SUM(C71:F71) -> 945193 | H71: =H28 -> 1619 | I71: =I28 -> 3949 | J71: =SUM(G71:I71) -> 950761
B72: FY 2010 | C72: 944947 | D72: -14 | E72: NA | F72: NA | G72: =SUM(C72:F72) -> 944933 | H72: =H29 -> 1586 | I72: =I29 -> 4015 | J72: =SUM(G72:I72) -> 950534
B73: FY 2011 | C73: 926292 | D73: 19562 | E73: NA | F73: NA | G73: =SUM(C73:F73) -> 945854 | H73: =H30 -> 1795 | I73: =I30 -> 4015 | J73: =SUM(G73:I73) -> 951664
B74: FY 2012 | C74: 919153 | D74: 30847 | E74: NA | F74: NA | G74: =SUM(C74:F74) -> 950000 | H74: =H31 -> 1795 | I74: =I31 -> 4015 | J74: =SUM(G74:I74) -> 955810
B75: FY 2013 | C75: 915925 | D75: 42243 | E75: NA | F75: NA | G75: =SUM(C75:F75) -> 958168 | H75: =H32 -> 1795 | I75: =I32 -> 4015 | J75: =SUM(G75:I75) -> 963978 | K75: =SUM(J65:J75) -> 10527031
B76: FY 2014 | C76: 914430 | D76: 53656 | E76: NA | F76: NA | G76: =SUM(C76:F76) -> 968086 | H76: =H33 -> 1795 | I76: =I33 -> 4015 | J76: =SUM(G76:I76) -> 973896
B77: FY 2015 | C77: 914605 | D77: 63331 | E77: NA | F77: NA | G77: =SUM(C77:F77) -> 977936 | H77: =H34 -> 1795 | I77: =I34 -> 4015 | J77: =SUM(G77:I77) -> 983746
A78: RMCPU-1.0
B79: FY 2003 | C79: 961493 | D79: 0 | E79: NA | F79: NA | G79: =SUM(C79:F79) -> 961493 | H79: 2956 | I79: 4770 | J79: =SUM(G79:I79) -> 969219
B80: FY 2004 | C80: 956408 | D80: 0 | E80: NA | F80: NA | G80: =SUM(C80:F80) -> 956408 | H80: 2550 | I80: 4330 | J80: =SUM(G80:I80) -> 963288
B81: FY 2005 | C81: 952266 | D81: 0 | E81: NA | F81: NA | G81: =SUM(C81:F81) -> 952266 | H81: 2499 | I81: 4477 | J81: =SUM(G81:I81) -> 959242
B82: FY 2006 | C82: 952292 | D82: 0 | E82: NA | F82: NA | G82: =SUM(C82:F82) -> 952292 | H82: 2397 | I82: 4198 | J82: =SUM(G82:I82) -> 958887
B83: FY 2007 | C83: 952429 | D83: 0 | E83: NA | F83: NA | G83: =SUM(C83:F83) -> 952429 | H83: 2166 | I83: 4119 | J83: =SUM(G83:I83) -> 958714
B84: FY 2008 | C84: 951696 | D84: 564 | E84: NA | F84: NA | G84: =SUM(C84:F84) -> 952260 | H84: =H70 -> 1787 | I84: =I70 -> 3808 | J84: =SUM(G84:I84) -> 957855
B85: FY 2009 | C85: 946916 | D85: 560 | E85: NA | F85: NA | G85: =SUM(C85:F85) -> 947476 | H85: =H71 -> 1619 | I85: =I71 -> 3949 | J85: =SUM(G85:I85) -> 953044
B86: FY 2010 | C86: 946306 | D86: -14 | E86: NA | F86: NA | G86: =SUM(C86:F86) -> 946292 | H86: =H72 -> 1586 | I86: =I72 -> 4015 | J86: =SUM(G86:I86) -> 951893
B87: FY 2011 | C87: 931691 | D87: 17105 | E87: NA | F87: NA | G87: =SUM(C87:F87) -> 948796 | H87: =H73 -> 1795 | I87: =I73 -> 4015 | J87: =SUM(G87:I87) -> 954606
B88: FY 2012 | C88: 921542 | D88: 29570 | E88: NA | F88: NA | G88: =SUM(C88:F88) -> 951112 | H88: =H74 -> 1795 | I88: =I74 -> 4015 | J88: =SUM(G88:I88) -> 956922
B89: FY 2013 | C89: 917713 | D89: 41256 | E89: NA | F89: NA | G89: =SUM(C89:F89) -> 958969 | H89: =H75 -> 1795 | I89: =I75 -> 4015 | J89: =SUM(G89:I89) -> 964779
B90: FY 2014 | C90: 915975 | D90: 52920 | E90: NA | F90: NA | G90: =SUM(C90:F90) -> 968895 | H90: =H76 -> 1795 | I90: =I76 -> 4015 | J90: =SUM(G90:I90) -> 974705
B91: FY 2015 | C91: 915941 | D91: 62812 | E91: NA | F91: NA | G91: =SUM(C91:F91) -> 978753 | H91: =H77 -> 1795 | I91: =I77 -> 4015 | J91: =SUM(G91:I91) -> 984563
A93: XADM
B94: FY 2003 | C94: 10032 | D94: 0 | E94: 164 | F94: 0 | G94: =SUM(C94:F94) -> 10196 | H94: 93 | I94: 0 | J94: =SUM(G94:I94) -> 10289
B95: FY 2004 | C95: 8953 | D95: 0 | E95: 162 | F95: 0 | G95: =SUM(C95:F95) -> 9115 | H95: 100 | I95: 0 | J95: =SUM(G95:I95) -> 9215
B96: FY 2005 | C96: 9661 | D96: 0 | E96: 166 | F96: 0 | G96: =SUM(C96:F96) -> 9827 | H96: 99 | I96: 0 | J96: =SUM(G96:I96) -> 9926
B97: FY 2006 | C97: 9732 | D97: 0 | E97: 168 | F97: 0 | G97: =SUM(C97:F97) -> 9900 | H97: 89 | I97: 0 | J97: =SUM(G97:I97) -> 9989
B98: FY 2007 | C98: 10274 | D98: 0 | E98: 208 | F98: 0 | G98: =SUM(C98:F98) -> 10482 | H98: 97 | I98: 0 | J98: =SUM(G98:I98) -> 10579
B99: FY 2008 | C99: 10940 | D99: 0 | E99: 294 | F99: 0 | G99: =SUM(C99:F99) -> 11234 | H99: 74 | I99: 0 | J99: =SUM(G99:I99) -> 11308
B100: FY 2009 | C100: 11181 | D100: 0 | E100: 305 | F100: 0 | G100: =SUM(C100:F100) -> 11486 | H100: 88 | I100: 0 | J100: =SUM(G100:I100) -> 11574
B101: FY 2010 | C101: 11881 | D101: 0 | E101: 394 | F101: 0 | G101: =SUM(C101:F101) -> 12275 | H101: 76 | I101: 0 | J101: =SUM(G101:I101) -> 12351
B102: FY 2011 | C102: 9930 | D102: 2611 | E102: 370 | F102: 64 | G102: =SUM(C102:F102) -> 12975 | H102: =H101 -> 76 | I102: 0 | J102: =SUM(G102:I102) -> 13051
B103: FY 2012 | C103: 9976 | D103: 3266 | E103: 328 | F103: 146 | G103: =SUM(C103:F103) -> 13716 | H103: =H102 -> 76 | I103: 0 | J103: =SUM(G103:I103) -> 13792
B104: FY 2013 | C104: 9877 | D104: 4128 | E104: 307 | F104: 207 | G104: =SUM(C104:F104) -> 14519 | H104: =H103 -> 76 | I104: 0 | J104: =SUM(G104:I104) -> 14595
B105: FY 2014 | C105: 9349 | D105: 5435 | E105: 305 | F105: 249 | G105: =SUM(C105:F105) -> 15338 | H105: =H104 -> 76 | I105: 0 | J105: =SUM(G105:I105) -> 15414
...

Sheet SUMMARY-ALL YEARS
A1: FEB 2011 VS. NOV 2010
A3: FEBRUARY 2011 FORECAST | D3: FY 2003 | E3: FY 2004 | F3: FY 2005 | G3: FY 2006 | H3: FY 2007 | I3: FY 2008 | J3: FY 2009 | K3: FY 2010 | L3: FY 2011 | M3: FY 2012 | N3: FY 2013 | O3: FY 2014 | P3: FY 2015
A5: 1 | B5: AMCPU | D5: ='FY 2003'!I5 -> 962146 | E5: ='FY 2004'!I5 -> 957096 | F5: ='FY 2005'!I5 -> 953035 | G5: ='FY 2006'!I5 -> 953041 | H5: ='FY 2007'!I5 -> 953288 | I5: ='FY 2008'!I5 -> 953432 | J5: ='FY 2009'!$I5 -> 948587 | K5: ='FY 2010'!$J5 -> 947210 | L5: ='FY 2011'!$J5 -> 948097 | M5: ='FY 2012'!$J5 -> 951670 | N5: ='FY 2013'!$J5 -> 959454 | O5: ='FY 2014'!$J5 -> 969398 | P5: ='FY 2015'!$J5 -> 979275
B7: REVENUES
A8: =A5+1 -> 2 | B8: Basic | D8: ='FY 2003'!I8 -> 4490060320 | E8: ='FY 2004'!I8 -> 4403575277 | F8: ='FY 2005'!I8 -> 4384973848 | G8: ='FY 2006'!I8 -> 4558383720 | H8: ='FY 2007'!I8 -> 4741676895 | I8: ='FY 2008'!I8 -> 4837724471 | J8: ='FY 2009'!$I8 -> 4.8605747e+09 | K8: ='FY 2010'!$J8 -> 4853494920 | L8: ='FY 2011'!$J8 -> 4858048057 | M8: ='FY 2012'!$J8 -> 4876357232 | N8: ='FY 2013'!$J8 -> 4916240193 | O8: ='FY 2014'!$J8 -> 4967199144 | P8: ='FY 2015'!$J8 -> 5017805352
A9: =A8+1 -> 3 | B9: Additional $51 | F9: 0 | G9: 0 | H9: 0 | I9: 0 | J9: ='FY 2009'!$I9 -> 48378085 | K9: 0 | L9: 0 | M9: 0 | N9: 0 | O9: 0 | P9: 0
A10: =A9+1 -> 4 | B10: Gifted & Talented | D10: ='FY 2003'!I9 -> 0 | E10: ='FY 2004'!I9 -> 0 | F10: ='FY 2005'!I9 -> 0 | G10: ='FY 2006'!I9 -> 3812154 | H10: ='FY 2007'!I9 -> 8579632 | I10: ='FY 2008'!I9 -> 11441209 | J10: ='FY 2009'!$I10 -> 11383079 | K10: ='FY 2010'!$J9 -> 11365913 | L10: ='FY 2011'!$J9 -> 11377163 | M10: ='FY 2012'!$J9 -> 11420040 | N10: ='FY 2013'!$J9 -> 11513446 | O10: ='FY 2014'!$J9 -> 11632780 | P10: ='FY 2015'!$J9 -> 11751302
A11: =A10+1 -> 5 | B11: Extended time | D11: ='FY 2003'!I10 -> 0 | E11: ='FY 2004'!I10 -> 50351550 | F11: ='FY 2005'!I10 -> 52327357 | G11: ='FY 2006'!I10 -> 52766200 | H11: ='FY 2007'!I10 -> 55436989 | I11: ='FY 2008'!I10 -> 59590817 | J11: ='FY 2009'!$I11 -> 60995641 | K11: ='FY 2010'!$J10 -> 64565373 | L11: ='FY 2011'!$J10 -> 69073025 | M11: ='FY 2012'!$J10 -> 71777949 | N11: ='FY 2013'!$J10 -> 76066766 | O11: ='FY 2014'!$J10 -> 80441305 | P11: ='FY 2015'!$J10 -> 84903317
B12: Basic Skills:
A13: =A11+1 -> 6 | C13: Compensatory | D13: ='FY 2003'!I12 -> 262694686 | E13: ='FY 2004'!I12 -> 249146954 | F13: ='FY 2005'!I12 -> 2.650745e+08 | G13: ='FY 2006'!I12 -> 292547478 | H13: ='FY 2007'!I12 -> 315471905 | I13: ='FY 2008'!I12 -> 333928094 | J13: ='FY 2009'!$I13 -> 3.4851069e+08 | K13: ='FY 2010'!$J12 -> 361157268 | L13: ='FY 2011'!$J12 -> 414260438 | M13: ='FY 2012'!$J12 -> 432960450 | N13: ='FY 2013'!$J12 -> 452559914 | O13: ='FY 2014'!$J12 -> 473621032 | P13: ='FY 2015'!$J12 -> 495561060
A14: =A13+1 -> 7 | C14: LEP | D14: ='FY 2003'!I13 -> 36857227 | E14: ='FY 2004'!I13 -> 28818713 | F14: ='FY 2005'!I13 -> 29477721 | G14: ='FY 2006'!I13 -> 30912658 | H14: ='FY 2007'!I13 -> 31474254 | I14: ='FY 2008'!I13 -> 32316781 | J14: ='FY 2009'!$I14 -> 32058187 | K14: ='FY 2010'!$J13 -> 31807937 | L14: ='FY 2011'!$J13 -> 31673120 | M14: ='FY 2012'!$J13 -> 31709920 | N14: ='FY 2013'!$J13 -> 31866994 | O14: ='FY 2014'!$J13 -> 32179350 | P14: ='FY 2015'!$J13 -> 32479973
A15: =A14+1 -> 8 | C15: LEP Concentration | D15: ='FY 2003'!I14 -> 9779108 | E15: ='FY 2004'!I14 -> 7276758 | F15: ='FY 2005'!I14 -> 7434285 | G15: ='FY 2006'!I14 -> 7883168 | H15: ='FY 2007'!I14 -> 8057613 | I15: ='FY 2008'!I14 -> 8306508 | J15: ='FY 2009'!$I15 -> 8316835 | K15: ='FY 2010'!$J14 -> 8258276 | L15: ='FY 2011'!$J14 -> 8387524 | M15: ='FY 2012'!$J14 -> 8406807 | N15: ='FY 2013'!$J14 -> 8500212 | O15: ='FY 2014'!$J14 -> 8579432 | P15: ='FY 2015'!$J14 -> 8651657
A16: =A15+1 -> 9 | B16: Sparsity | D16: ='FY 2003'!I15 -> 16471551 | E16: ='FY 2004'!I15 -> 16909578 | F16: ='FY 2005'!I15 -> 17548649 | G16: ='FY 2006'!I15 -> 18853061 | H16: ='FY 2007'!I15 -> 20254233 | I16: ='FY 2008'!I15 -> 21637534 | J16: ='FY 2009'!$I16 -> 22898807 | K16: ='FY 2010'!$J15 -> 23368633 | L16: ='FY 2011'!$J15 -> 23511161 | M16: ='FY 2012'!$J15 -> 24128678 | N16: ='FY 2013'!$J15 -> 24366756 | O16: ='FY 2014'!$J15 -> 24637073 | P16: ='FY 2015'!$J15 -> 25012252
A17: =A16+1 -> 10 | B17: Transport Sparsity | D17: ='FY 2003'!I16 -> 56478364 | E17: ='FY 2004'!I16 -> 55913098 | F17: ='FY 2005'!I16 -> 55511195 | G17: ='FY 2006'!I16 -> 57332807 | H17: ='FY 2007'!I16 -> 59221788 | I17: ='FY 2008'!I16 -> 60083765 | J17: ='FY 2009'!$I17 -> 60159097 | K17: ='FY 2010'!$J16 -> 59833229 | L17: ='FY 2011'!$J16 -> 60371479 | M17: ='FY 2012'!$J16 -> 60249583 | N17: ='FY 2013'!$J16 -> 60009213 | O17: ='FY 2014'!$J16 -> 59809879 | P17: ='FY 2015'!$J16 -> 59683844
A18: =A17+1 -> 11 | B18: Training & Experience | D18: ='FY 2003'!I17 -> 25114308 | E18: ='FY 2004'!I17 -> 18869558 | F18: ='FY 2005'!I17 -> 12876818 | G18: ='FY 2006'!I17 -> 8213502 | H18: ='FY 2007'!I17 -> 4354428 | I18: ='FY 2008'!I17 -> 2146056 | J18: ='FY 2009'!$I18 -> 1207447.6 | K18: ='FY 2010'!$J17 -> 675850 | L18: ='FY 2011'!$J17 -> 373228 | M18: ='FY 2012'!$J17 -> 223163 | N18: ='FY 2013'!$J17 -> 158920 | O18: ='FY 2014'!$J17 -> 128753 | P18: ='FY 2015'!$J17 -> 104189
A19: =A18+1 -> 12 | B19: Late Contract Penalty | D19: ='FY 2003'!I18 -> 0 | E19: ='FY 2004'!I18 -> 0 | F19: ='FY 2005'!I18 -> 0 | G19: ='FY 2006'!I18 -> -344932 | H19: ='FY 2007'!I18 -> 0 | I19: ='FY 2008'!I18 -> -730496 | J19: ='FY 2009'!$I19 -> 0 | K19: ='FY 2010'!$J18 -> -2507070 | L19: ='FY 2011'!$J18 -> 0 | M19: ='FY 2012'!$J18 -> -700000 | N19: ='FY 2013'!$J18 -> 0 | O19: ='FY 2014'!$J18 -> -700000 | P19: ='FY 2015'!$J18 -> 0
A20: =A19+1 -> 13 | B20: One-time Reduction | H20: 0 | I20: 0 | J20: 0 | K20: ='FY 2010'!$J19 -> -500000000 | L20: 0 | M20: 0 | N20: 0 | O20: 0 | P20: 0
A21: =A20+1 -> 14 | B21: Operating Capital | D21: ='FY 2003'!I19 -> 198438434 | E21: ='FY 2004'!I19 -> 194217096 | F21: ='FY 2005'!I19 -> 193697081 | G21: ='FY 2006'!I19 -> 194018388 | H21: ='FY 2007'!I19 -> 194117024 | I21: ='FY 2008'!I19 -> 194635565 | J21: ='FY 2009'!$I20 -> 1.9429911e+08 | K21: ='FY 2010'!$J20 -> 194409760 | L21: ='FY 2011'!$J19 -> 194612210 | M21: ='FY 2012'!$J19 -> 195303133 | N21: ='FY 2013'!$J19 -> 196865845 | O21: ='FY 2014'!$J19 -> 198885121 | P21: ='FY 2015'!$J19 -> 200893938
A22: =A21+1 -> 15 | B22: Equity | D22: ='FY 2003'!I20 -> 34642490 | E22: ='FY 2004'!I20 -> 32112369 | F22: ='FY 2005'!I20 -> 41731237 | G22: ='FY 2006'!I20 -> 50999434 | H22: ='FY 2007'!I20 -> 94274069 | I22: ='FY 2008'!I20 -> 95708805 | J22: ='FY 2009'!$I21 -> 93361990 | K22: ='FY 2010'!$J21 -> 92518770 | L22: ='FY 2011'!$J20 -> 92334012 | M22: ='FY 2012'!$J20 -> 93367180 | N22: ='FY 2013'!$J20 -> 94481702 | O22: ='FY 2014'!$J20 -> 96337072 | P22: ='FY 2015'!$J20 -> 98582671
A23: =A22+1 -> 16 | B23: Transition | D23: ='FY 2003'!I21 -> 0 | E23: ='FY 2004'!I21 -> 31986524 | F23: ='FY 2005'!I21 -> 31326609 | G23: ='FY 2006'!I21 -> 31033742 | H23: ='FY 2007'!I21 -> 30462514 | I23: ='FY 2008'!I21 -> 30143318 | J23: ='FY 2009'!$I22 -> 29711997 | K23: ='FY 2010'!$J22 -> 29453149 | L23: ='FY 2011'!$J21 -> 29215443 | M23: ='FY 2012'!$J21 -> 29101965 | N23: ='FY 2013'!$J21 -> 29294337 | O23: ='FY 2014'!$J21 -> 29613757 | P23: ='FY 2015'!$J21 -> 29884371
A24: =A23+1 -> 17 | B24: Q Comp | D24: ='FY 2003'!I22 -> 0 | E24: ='FY 2004'!I22 -> 0 | F24: ='FY 2005'!I22 -> 0 | G24: ='FY 2006'!I22 -> 16348850 | H24: ='FY 2007'!I22 -> 48603714 | I24: ='FY 2008'!I22 -> 60763648 | J24: ='FY 2009'!$I23 -> 63348360 | K24: ='FY 2010'!$J23 -> 58291520 | L24: ='FY 2011'!$J22 -> 63056932 | M24: ='FY 2012'!$J22 -> 79031161 | N24: ='FY 2013'!$J22 -> 81908545 | O24: ='FY 2014'!$J22 -> 83976748 | P24: ='FY 2015'!$J22 -> 86016276
A25: =A24+1 -> 18 | B25: Referendum Revenue | D25: ='FY 2003'!I23 -> 291708358 | E25: ='FY 2004'!I23 -> 426336542 | F25: ='FY 2005'!I23 -> 504721085 | G25: ='FY 2006'!I23 -> 534314512 | H25: ='FY 2007'!I23 -> 598966155 | I25: ='FY 2008'!I23 -> 644192179 | J25: ='FY 2009'!$I24 -> 7.2056718e+08 | K25: ='FY 2010'!$J24 -> 781675140 | L25: ='FY 2011'!$J23 -> 804832265 | M25: ='FY 2012'!$J23 -> 822497449 | N25: ='FY 2013'!$J23 -> 895212966 | O25: ='FY 2014'!$J23 -> 945891076 | P25: ='FY 2015'!$J23 -> 1016293443
B26: Alternative Attendance Adj:
A27: =A25+1 -> 19 | C27: Open Enroll/Charter Refer | D27: ='FY 2003'!I25 -> 1341221 | E27: ='FY 2004'!I25 -> -679857 | F27: ='FY 2005'!I25 -> -1089963.9 | G27: ='FY 2006'!I25 -> -895441.79 | H27: ='FY 2007'!I25 -> -885672 | I27: ='FY 2008'!I25 -> -181964 | J27: ='FY 2009'!$I26 -> 262096 | K27: ='FY 2010'!$J26 -> 607348 | L27: ='FY 2011'!$J25 -> 657596 | M27: ='FY 2012'!$J25 -> 309694 | N27: ='FY 2013'!$J25 -> -191472 | O27: ='FY 2014'!$J25 -> -284009 | P27: ='FY 2015'!$J25 -> -369316
A28: =A27+1 -> 20 | C28: Charter Basic Transport | D28: ='FY 2003'!I26 -> -1804253 | E28: ='FY 2004'!I26 -> 1059 | F28: ='FY 2005'!I26 -> 0 | G28: ='FY 2006'!I26 -> 0.44 | H28: ='FY 2007'!I26 -> 0 | I28: ='FY 2008'!I26 -> 0 | J28: ='FY 2009'!$I27 -> -0.0099999995 | K28: ='FY 2010'!$J27 -> 0 | L28: ='FY 2011'!$J26 -> 32 | M28: ='FY 2012'!$J26 -> -780 | N28: ='FY 2013'!$J26 -> 745 | O28: ='FY 2014'!$J26 -> 99 | P28: ='FY 2015'!$J26 -> 99
A29: =A28+1 -> 21 | C29: Charter Ext TimeTransport | D29: ='FY 2003'!I27 -> 0 | E29: ='FY 2004'!I27 -> 0 | F29: ='FY 2005'!I27 -> 0 | G29: ='FY 2006'!I27 -> -0.18 | H29: ='FY 2007'!I27 -> 0 | I29: ='FY 2008'!I27 -> 0 | J29: ='FY 2009'!$I28 -> 0 | K29: ='FY 2010'!$J28 -> 0 | L29: ='FY 2011'!$J27 -> 777 | M29: ='FY 2012'!$J27 -> 0 | N29: ='FY 2013'!$J27 -> 0 | O29: ='FY 2014'!$J27 -> 0 | P29: ='FY 2015'!$J27 -> 0
A30: =A29+1 -> 22 | C30: Charter Transport Sparsity | D30: ='FY 2003'!I28 -> 0 | E30: ='FY 2004'!I28 -> 0 | F30: ='FY 2005'!I28 -> 0 | G30: ='FY 2006'!I28 -> 0.44 | H30: ='FY 2007'!I28 -> 0 | I30: ='FY 2008'!I28 -> 0 | J30: ='FY 2009'!$I29 -> -0.01 | K30: ='FY 2010'!$J29 -> 4 | L30: ='FY 2011'!$J28 -> 165 | M30: ='FY 2012'!$J28 -> 29792 | N30: ='FY 2013'!$J28 -> 45882 | O30: ='FY 2014'!$J28 -> 51212 | P30: ='FY 2015'!$J28 -> 54447
A31: =A30+1 -> 23 | C31: Faribault Alternative Attend Adj | D31: 0 | E31: 0 | F31: 0 | G31: ='FY 2006'!I29 -> 0 | H31: ='FY 2007'!$I29 -> -398 | I31: ='FY 2008'!$I29 -> -355.18 | J31: ='FY 2009'!$I30 -> -461.16 | K31: ='FY 2010'!$J30 -> -449 | L31: ='FY 2011'!$J29 -> -195 | M31: ='FY 2012'!$J29 -> -195 | N31: ='FY 2013'!$J29 -> -195 | O31: ='FY 2014'!$J29 -> -195 | P31: ='FY 2015'!$J29 -> -195
A34: =A31+1 -> 24 | B34: TOTAL REVENUE | D34: =SUM(D8:D31) -> 5421781814 | E34: =SUM(E8:E31) -> 5514835219 | F34: =SUM(F8:F31) -> 5.5956104e+09 | G34: =SUM(G8:G31) -> 5.8561793e+09 | H34: =SUM(H8:H31) -> 6210065143 | I34: =SUM(I8:I31) -> 6.3917059e+09 | J34: =SUM(J8:J31) -> 6.5560328e+09 | K34: =SUM(K8:K31) -> 6068975571 | ... P34: =SUM(P8:P31) -> 7167308680
B36: LEVIES
A37: =A34+1 -> 25 | B37: Operating Capital Levy | D37: ='FY 2003'!I33 -> 0 | E37: ='FY 2004'!I33 -> 0 | F37: ='FY 2005'!I33 -> 40007254 | G37: ='FY 2006'!I34 -> 44268155 | H37: ='FY 2007'!I34 -> 101934454 | I37: ='FY 2008'!I34 -> 111830374 | J37: ='FY 2009'!$I35 -> 1.2125304e+08 | K37: ='FY 2010'!$J35 -> 124276595 | L37: ='FY 2011'!$J34 -> 124623859 | M37: ='FY 2012'!$J34 -> 120033819 | N37: ='FY 2013'!$J34 -> 113554245 | O37: ='FY 2014'!$J34 -> 113404094 | P37: ='FY 2015'!$J34 -> 114314879
A38: =A37+1 -> 26 | B38: Equity Levy | D38: ='FY 2003'!I34 -> 0 | E38: ='FY 2004'!I34 -> 0 | F38: ='FY 2005'!I34 -> 22380297 | G38: ='FY 2006'!I35 -> 25083314 | H38: ='FY 2007'!I35 -> 63740065 | I38: ='FY 2008'!I35 -> 70604296 | J38: ='FY 2009'!$I36 -> 73701614 | K38: ='FY 2010'!$J36 -> 75798743 | L38: ='FY 2011'!$J35 -> 76305360 | M38: ='FY 2012'!$J35 -> 75373928 | N38: ='FY 2013'!$J35 -> 73497205 | O38: ='FY 2014'!$J35 -> 74047041 | P38: ='FY 2015'!$J35 -> 75353828
A39: =A38+1 -> 27 | B39: Transition Levy | D39: ='FY 2003'!I35 -> 0 | E39: ='FY 2004'!I35 -> 0 | F39: ='FY 2005'!I35 -> 18540609 | G39: ='FY 2006'!I36 -> 20383544 | H39: ='FY 2007'!I36 -> 21830489 | I39: ='FY 2008'!I36 -> 23010395 | J39: ='FY 2009'!$I37 -> 24292897 | K39: ='FY 2010'!$J37 -> 25195534 | L39: ='FY 2011'!$J36 -> 25244531 | M39: ='FY 2012'!$J36 -> 24570084 | N39: ='FY 2013'!$J36 -> 23754209 | O39: ='FY 2014'!$J36 -> 23723108 | P39: ='FY 2015'!$J36 -> 23821586
A40: =A39+1 -> 28 | B40: Q Comp | D40: ='FY 2003'!I36 -> 0 | E40: ='FY 2004'!I36 -> 0 | F40: ='FY 2005'!I36 -> 0 | G40: ='FY 2006'!I37 -> 0 | H40: ='FY 2007'!I37 -> 9695468 | I40: ='FY 2008'!I37 -> 12779741 | J40: ='FY 2009'!$I38 -> 13353371 | K40: ='FY 2010'!$J38 -> 16807134 | L40: ='FY 2011'!$J37 -> 18158004 | M40: ='FY 2012'!$J37 -> 22046270 | N40: ='FY 2013'!$J37 -> 21813521 | O40: ='FY 2014'!$J37 -> 22270667 | P40: ='FY 2015'!$J37 -> 22847474
A41: =A40+1 -> 29 | B41: Referendum Levy | D41: ='FY 2003'!I37 -> 224945858 | E41: ='FY 2004'!I37 -> 351087875 | F41: ='FY 2005'!I37 -> 379954471 | G41: ='FY 2006'!I38 -> 410867894 | H41: ='FY 2007'!I38 -> 482421730 | I41: ='FY 2008'!I38 -> 540184289 | J41: ='FY 2009'!$I39 -> 6.3533353e+08 | K41: ='FY 2010'!$J39 -> 712334239 | L41: ='FY 2011'!$J38 -> 737629396 | M41: ='FY 2012'!$J38 -> 745650749 | N41: ='FY 2013'!$J38 -> 801706175 | O41: ='FY 2014'!$J38 -> 847429732 | P41: ='FY 2015'!$J38 -> 914688821
A43: =A41+1 -> 30 | B43: TOTAL LEVY | D43: =SUM(D37:D41) -> 224945858 | E43: =SUM(E37:E41) -> 351087875 | F43: =SUM(F37:F41) -> 460882631 | G43: =SUM(G37:G41) -> 500602907 | H43: =SUM(H37:H41) -> 679622206 | I43: =SUM(I37:I41) -> 758409095 | J43: =SUM(J37:J41) -> 8.6793445e+08 | K43: =SUM(K37:K41) -> 954412245 | ... P43: =SUM(P37:P41) -> 1151026588
B45: AID ENTITLEMENTS
A46: =A43+1 -> 31 | B46: Basic | D46: =D8 -> 4490060320 | E46: =E8 -> 4403575277 | F46: =F8 -> 4384973848 | G46: =G8 -> 4558383720 | H46: =H8 -> 4741676895 | I46: =I8 -> 4837724471 | J46: =J8 -> 4.8605747e+09 | K46: =K8 -> 4853494920 | ... P46: =P8 -> 5017805352
A47: =A46+1 -> 32 | B47: Additional $51 | F47: =F9 -> 0 | G47: =G9 -> 0 | H47: =H9 -> 0 | I47: =I9 -> 0 | J47: =J9 -> 48378085 | K47: =K9 -> 0 | L47: =L9 -> 0 | M47: =M9 -> 0 | ... P47: =P9 -> 0
A48: =A47+1 -> 33 | B48: Gifted & Talented | D48: =D10 -> 0 | E48: =E10 -> 0 | F48: =F10 -> 0 | G48: =G10 -> 3812154 | H48: =H10 -> 8579632 | I48: =I10 -> 11441209 | J48: =J10 -> 11383079 | K48: =K10 -> 11365913 | ... P48: =P10 -> 11751302
A49: =A48+1 -> 34 | B49: Extended time | D49: =D11 -> 0 | E49: =E11 -> 50351550 | F49: =F11 -> 52327357 | G49: =G11 -> 52766200 | H49: =H11 -> 55436989 | I49: =I11 -> 59590817 | J49: =J11 -> 60995641 | K49: =K11 -> 64565373 | ... P49: =P11 -> 84903317
B50: Basic Skills:
A51: =A49+1 -> 35 | C51: Compensatory | D51: =D13 -> 262694686 | E51: =E13 -> 249146954 | F51: =F13 -> 2.650745e+08 | G51: =G13 -> 292547478 | H51: =H13 -> 315471905 | I51: =I13 -> 333928094 | J51: =J13 -> 3.4851069e+08 | K51: =K13 -> 361157268 | ... P51: =P13 -> 495561060
A52: =A51+1 -> 36 | C52: LEP | D52: =D14 -> 36857227 | E52: =E14 -> 28818713 | F52: =F14 -> 29477721 | G52: =G14 -> 30912658 | H52: =H14 -> 31474254 | I52: =I14 -> 32316781 | J52: =J14 -> 32058187 | K52: =K14 -> 31807937 | ... P52: =P14 -> 32479973
A53: =A52+1 -> 37 | C53: LEP Concentration | D53: =D15 -> 9779108 | E53: =E15 -> 7276758 | F53: =F15 -> 7434285 | G53: =G15 -> 7883168 | H53: =H15 -> 8057613 | I53: =I15 -> 8306508 | J53: =J15 -> 8316835 | K53: =K15 -> 8258276 | ... P53: =P15 -> 8651657
A54: =A53+1 -> 38 | B54: Sparsity | D54: =D16 -> 16471551 | E54: =E16 -> 16909578 | F54: =F16 -> 17548649 | G54: =G16 -> 18853061 | H54: =H16 -> 20254233 | I54: =I16 -> 21637534 | J54: =J16 -> 22898807 | K54: =K16 -> 23368633 | ... P54: =P16 -> 25012252
A55: =A54+1 -> 39 | B55: Transport Sparsity | D55: =D17 -> 56478364 | E55: =E17 -> 55913098 | F55: =F17 -> 55511195 | G55: =G17 -> 57332807 | H55: =H17 -> 59221788 | I55: =I17 -> 60083765 | J55: =J17 -> 60159097 | K55: =K17 -> 59833229 | ... P55: =P17 -> 59683844
A56: =A55+1 -> 40 | B56: Training & Experience | D56: =D18 -> 25114308 | E56: =E18 -> 18869558 | F56: =F18 -> 12876818 | G56: =G18 -> 8213502 | H56: =H18 -> 4354428 | I56: =I18 -> 2146056 | J56: =J18 -> 1207447.6 | K56: =K18 -> 675850 | ... P56: =P18 -> 104189
A57: =A56+1 -> 41 | B57: Late Contract Penalty | D57: =D19 -> 0 | E57: =E19 -> 0 | F57: =F19 -> 0 | G57: =G19 -> -344932 | H57: =H19 -> 0 | I57: =I19 -> -730496 | J57: =J19 -> 0 | K57: =K19 -> -2507070 | ... P57: =P19 -> 0
A58: =A57+1 -> 42 | B58: One-time Reduction | H58: 0 | I58: 0 | J58: 0 | K58: ='FY 2010'!$J55 -> -500000000 | L58: 0 | M58: 0 | N58: 0 | O58: 0 | P58: 0
A59: =A58+1 -> 43 | B59: Operating Capital | D59: =D21-D37 -> 198438434 | E59: =E21-E37 -> 194217096 | F59: =F21-F37 -> 153689827 | G59: =G21-G37 -> 149750233 | H59: =H21-H37 -> 92182570 | I59: =I21-I37 -> 82805191 | J59: =J21-J37 -> 73046067 | K59: =K21-K37 -> 70133165 | ... P59: =P21-P37 -> 86579059
A60: =A59+1 -> 44 | B60: Equity | D60: =D22-D38 -> 34642490 | E60: =E22-E38 -> 32112369 | F60: =F22-F38 -> 19350940 | G60: =G22-G38 -> 25916120 | H60: =H22-H38 -> 30534004 | I60: =I22-I38 -> 25104509 | J60: =J22-J38 -> 19660376 | K60: =K22-K38 -> 16720027 | ... P60: =P22-P38 -> 23228843
A61: =A60+1 -> 45 | B61: Transition | D61: =D23-D39 -> 0 | E61: =E23-E39 -> 31986524 | F61: =F23-F39 -> 12786000 | G61: =G23-G39 -> 10650198 | H61: =H23-H39 -> 8632025 | I61: =I23-I39 -> 7132923 | J61: =J23-J39 -> 5419100.7 | K61: =K23-K39 -> 4257615 | ... P61: =P23-P39 -> 6062785
A62: =A61+1 -> 46 | B62: Q Comp | D62: =D24-D40 -> 0 | E62: =E24-E40 -> 0 | F62: =F24-F40 -> 0 | G62: =G24-G40 -> 16348850 | H62: =H24-H40 -> 38908246 | I62: =I24-I40 -> 47983907 | J62: =J24-J40 -> 49994989 | K62: =K24-K40 -> 41484386 | ... P62: =P24-P40 -> 63168802
A63: =A62+1 -> 47 | B63: Referendum Equalization Aid | D63: =D25-D41-D64 -> 58417206 | E63: =E25-E41-E64 -> 67208298 | F63: =F25-F41-F64 -> 116067762 | G63: =G25-G41-G64 -> 114774019 | H63: =H25-H41-H64 -> 107935161 | I63: =I25-I41-I64 -> 95398626 | J63: =J25-J41-J64 -> 76645863 | K63: =K25-K41-K64 -> 60722235 | ... P63: =P25-P41-P64 -> 93081981
A64: =A63+1 -> 48 | B64: Tax Base Replacement Aid | D64: ='FY 2003'!I58 -> 8345294 | E64: ='FY 2004'!I58 -> 8040369 | F64: ='FY 2005'!I58 -> 8698852 | G64: ='FY 2006'!I59 -> 8672599 | H64: ='FY 2007'!I59 -> 8609264 | I64: ='FY 2008'!I59 -> 8609264 | J64: ='FY 2009'!$I61 -> 8587791.7 | K64: ='FY 2010'!$J61 -> 8618666 | L64: ='FY 2011'!$J59 -> 8593182 | M64: ='FY 2012'!$J59 -> 8501953 | N64: ='FY 2013'!$J59 -> 8522641 | O64: ='FY 2014'!$J59 -> 8522641 | P64: ='FY 2015'!$J59 -> 8522641
B65: Alternative Attendance Adj:
A66: =A64+1 -> 49 | C66: Open Enroll/Charter Refer | D66: ='FY 2003'!I60 -> 1341221 | E66: ='FY 2004'!I60 -> -679857 | F66: ='FY 2005'!I60 -> -1089963.9 | G66: ='FY 2006'!I61 -> -895441.79 | H66: ='FY 2007'!I61 -> -885672 | I66: ='FY 2008'!I61 -> -181964 | J66: ='FY 2009'!$I63 -> 262096 | K66: ='FY 2010'!$J63 -> 607348 | L66: ='FY 2011'!$J61 -> 657596 | M66: ='FY 2012'!$J61 -> 309694 | N66: ='FY 2013'!$J61 -> -191472 | O66: ='FY 2014'!$J61 -> -284009 | P66: ='FY 2015'!$J61 -> -369316
A67: =A66+1 -> 50 | C67: Charter Basic Transport | D67: ='FY 2003'!I61 -> -1804253 | E67: ='FY 2004'!I61 -> 1059 | F67: ='FY 2005'!I61 -> 0 | G67: ='FY 2006'!I62 -> 0.44 | H67: ='FY 2007'!I62 -> 0 | I67: ='FY 2008'!I62 -> 0 | J67: ='FY 2009'!$I64 -> -0.0099999995 | K67: ='FY 2010'!$J64 -> 0 | L67: ='FY 2011'!$J62 -> 32 | M67: ='FY 2012'!$J62 -> -780 | N67: ='FY 2013'!$J62 -> 745 | O67: ='FY 2014'!$J62 -> 99 | P67: ='FY 2015'!$J62 -> 99
A68: =A67+1 -> 51 | C68: Charter Ext TimeTransport | D68: ='FY 2003'!I62 -> 0 | E68: ='FY 2004'!I62 -> 0 | F68: ='FY 2005'!I62 -> 0 | G68: ='FY 2006'!I63 -> -0.18 | H68: ='FY 2007'!I63 -> 0 | I68: ='FY 2008'!I63 -> 0 | J68: ='FY 2009'!$I65 -> 0 | K68: ='FY 2010'!$J65 -> 0 | L68: ='FY 2011'!$J63 -> 777 | M68: ='FY 2012'!$J63 -> 0 | N68: ='FY 2013'!$J63 -> 0 | O68: ='FY 2014'!$J63 -> 0 | P68: ='FY 2015'!$J63 -> 0
A69: =A68+1 -> 52 | C69: Charter Transport Sparsity | D69: ='FY 2003'!I63 -> 0 | E69: ='FY 2004'!I63 -> 0 | F69: ='FY 2005'!I63 -> 0 | G69: ='FY 2006'!I64 -> 0.44 | H69: ='FY 2007'!I64 -> 0 | I69: ='FY 2008'!I64 -> 0 | J69: ='FY 2009'!$I66 -> -0.01 | K69: ='FY 2010'!$J66 -> 4 | L69: ='FY 2011'!$J64 -> 165 | M69: ='FY 2012'!$J64 -> 29792 | N69: ='FY 2013'!$J64 -> 45882 | O69: ='FY 2014'!$J64 -> 51212 | P69: ='FY 2015'!$J64 -> 54447
A70: =A69+1 -> 53 | C70: Faribault Alternative Attend Adj | D70: 0 | E70: 0 | F70: 0 | G70: ='FY 2006'!I65 -> 0 | H70: ='FY 2007'!$I65 -> -398 | I70: ='FY 2008'!$I65 -> -355.18 | J70: ='FY 2009'!$I67 -> -461.16 | K70: ='FY 2010'!$J67 -> -449 | L70: ='FY 2011'!$J65 -> -195 | M70: ='FY 2012'!$J65 -> -195 | N70: ='FY 2013'!$J65 -> -195 | O70: ='FY 2014'!$J65 -> -195 | P70: ='FY 2015'!$J65 -> -195
A72: =A70+1 -> 54 | B72: TOTAL AID ENTITLEMENT | D72: =SUM(D46:D70) -> 5196835956 | E72: =SUM(E46:E70) -> 5163747344 | F72: =SUM(F46:F70) -> 5.1347278e+09 | G72: =SUM(G46:G70) -> 5.3555764e+09 | H72: =SUM(H46:H70) -> 5530442937 | I72: =SUM(I46:I70) -> 5.6332968e+09 | J72: =SUM(J46:J70) -> 5.6880984e+09 | K72: =SUM(K46:K70) -> 5114563326 | ... P72: =SUM(P46:P70) -> 6016282092
A73: =A72+1 -> 55 | B73: General Ed Entitlement (IDEAS) | D73: =D72-D64 -> 5188490662 | E73: =E72-E64 -> 5155706975 | F73: =F72-F64 -> 5.1260289e+09 | G73: =G72-G64 -> 5.3469038e+09 | H73: =H72-H64 -> 5521833673 | I73: =I72 -> 5.6332968e+09 | J73: =J72 -> 5.6880984e+09 | K73: =K72 -> 5114563326 | L73: =L72 -> 5679823282 | M73: =M72 -> 5748498371 | N73: =N72 -> 5844575414 | O73: =O72 -> 5931124987 | P73: =P72 -> 6016282092
A74: =A73+1 -> 56 | B74: Tax Base Repl Entitlemt (thru FY07) | D74: =D64 -> 8345294 | E74: =E64 -> 8040369 | F74: =F64 -> 8698852 | G74: =G64 -> 8672599 | H74: =H64 -> 8609264 | I74: na | J74: na | K74: na | L74: na | M74: na | N74: na | O74: na | P74: na
A76: =A74+1 -> 57 | B76: TRA Reduction | D76: ='FY 2003'!I69 -> -46570547 | E76: ='FY 2004'!I69 -> -46686661 | F76: ='FY 2005'!I69 -> -46733667 | G76: ='FY 2006'!I71 -> -46807695 | H76: ='FY 2007'!I71 -> -46967505 | I76: ='FY 2008'!I71 -> -30637836 | J76: ='FY 2009'!$I73 -> -30753090 | K76: ='FY 2010'!$J73 -> -30827862 | L76: ='FY 2011'!$J71 -> -30929256 | M76: ='FY 2012'!$J71 -> -31089936 | N76: ='FY 2013'!$J71 -> -31243295 | O76: ='FY 2014'!$J71 -> -31405216 | P76: ='FY 2015'!$J71 -> -31579486
A78: NOVEMBER 2010 FORECAST | D78: FY 2003 | E78: FY 2004 | F78: FY 2005 | G78: FY 2006 | H78: FY 2007 | I78: FY 2008 | J78: FY 2009 | K78: FY 2010 | L78: FY 2011 | M78: FY 2012 | N78: FY 2013 | O78: FY 2014 | P78: FY 2015
A80: 1 | B80: AMCPU | D80: ='FY 2003'!I73 -> 962146 | E80: ='FY 2004'!I73 -> 957096 | F80: ='FY 2005'!I73 -> 953035 | G80: ='FY 2006'!I75 -> 953041 | H80: ='FY 2007'!I75 -> 953288 | I80: ='FY 2008'!I75 -> 953432 | J80: ='FY 2009'!$I77 -> 948587 | K80: ='FY 2010'!$J77 -> 947786 | L80: ='FY 2011'!$J75 -> 949439 | M80: ='FY 2012'!$J75 -> 953192 | N80: ='FY 2013'!$J75 -> 961193 | O80: ='FY 2014'!$J75 -> 971195 | P80: ='FY 2015'!$J75 -> 982011
B82: REVENUES
A83: =A80+1 -> 2 | B83: Basic | D83: ='FY 2003'!I76 -> 4490060320 | E83: ='FY 2004'!I76 -> 4403575277 | F83: ='FY 2005'!I76 -> 4384973848 | G83: ='FY 2006'!I78 -> 4558383720 | H83: ='FY 2007'!I78 -> 4741676895 | I83: ='FY 2008'!I78 -> 4837724471 | J83: ='FY 2009'!$I80 -> 4.8605747e+09 | K83: ='FY 2010'!$J80 -> 4857031966 | L83: ='FY 2011'!$J78 -> 4864927024 | M83: ='FY 2012'!$J78 -> 4884153655 | N83: ='FY 2013'!$J78 -> 4925154001 | O83: ='FY 2014'!$J78 -> 4976401793 | P83: ='FY 2015'!$J78 -> 5031822360
A84: =A83+1 -> 3 | B84: Additional $51 | D84: 0 | E84: 0 | F84: 0 | G84: 0 | H84: 0 | I84: 0 | J84: ='FY 2009'!$I81 -> 48378085 | K84: 0 | L84: 0 | M84: 0 | N84: 0 | O84: 0 | P84: 0
A85: =A84+1 -> 4 | B85: Gifted & Talented | D85: ='FY 2003'!I77 -> 0 | E85: ='FY 2004'!I77 -> 0 | F85: ='FY 2005'!I77 -> 0 | G85: ='FY 2006'!I79 -> 3812154 | H85: ='FY 2007'!I79 -> 8579632 | I85: ='FY 2008'!I79 -> 11441209 | J85: ='FY 2009'!$I82 -> 11383079 | K85: ='FY 2010'!$J81 -> 11374782 | L85: ='FY 2011'!$J79 -> 11393282 | M85: ='FY 2012'!$J79 -> 11438304 | N85: ='FY 2013'!$J79 -> 11534322 | O85: ='FY 2014'!$J79 -> 11654338 | P85: ='FY 2015'!$J79 -> 11784125
A86: =A85+1 -> 5 | B86: Extended time | D86: ='FY 2003'!I78 -> 0 | E86: ='FY 2004'!I78 -> 50351550 | F86: ='FY 2005'!I78 -> 52327357 | G86: ='FY 2006'!I80 -> 52766200 | H86: ='FY 2007'!I80 -> 55436989 | I86: ='FY 2008'!I80 -> 59590817 | J86: ='FY 2009'!$I83 -> 60995641 | K86: ='FY 2010'!$J82 -> 64754980 | L86: ='FY 2011'!$J80 -> 69226284 | M86: ='FY 2012'!$J80 -> 71911146 | N86: ='FY 2013'!$J80 -> 76200979 | O86: ='FY 2014'!$J80 -> 80574826 | P86: ='FY 2015'!$J80 -> 85121499
B87: Basic Skills:
A88: =A86+1 -> 6 | C88: Compensatory | D88: ='FY 2003'!I80 -> 262694686 | E88: ='FY 2004'!I80 -> 249146954 | F88: ='FY 2005'!I80 -> 2.650745e+08 | G88: ='FY 2006'!I82 -> 292547478 | H88: ='FY 2007'!I82 -> 315471905 | I88: ='FY 2008'!I82 -> 333928094 | J88: ='FY 2009'!$I85 -> 3.4851069e+08 | K88: ='FY 2010'!$J84 -> 361172148 | L88: ='FY 2011'!$J82 -> 414257707 | M88: ='FY 2012'!$J82 -> 437710623 | N88: ='FY 2013'!$J82 -> 457014819 | O88: ='FY 2014'!$J82 -> 478412432 | P88: ='FY 2015'!$J82 -> 500648390
A89: =A88+1 -> 7 | C89: LEP | D89: ='FY 2003'!I81 -> 36857227 | E89: ='FY 2004'!I81 -> 28818713 | F89: ='FY 2005'!I81 -> 29477721 | G89: ='FY 2006'!I83 -> 30912658 | H89: ='FY 2007'!I83 -> 31474254 | I89: ='FY 2008'!I83 -> 32316781 | J89: ='FY 2009'!$I86 -> 32058187 | K89: ='FY 2010'!$J85 -> 31812431 | L89: ='FY 2011'!$J83 -> 31727803 | M89: ='FY 2012'!$J83 -> 31763646 | N89: ='FY 2013'!$J83 -> 31922542 | O89: ='FY 2014'!$J83 -> 32235883 | P89: ='FY 2015'!$J83 -> 32595183
A90: =A89+1 -> 8 | C90: LEP Concentration | D90: ='FY 2003'!I82 -> 9779108 | E90: ='FY 2004'!I82 -> 7276758 | F90: ='FY 2005'!I82 -> 7434285 | G90: ='FY 2006'!I84 -> 7883168 | H90: ='FY 2007'!I84 -> 8057613 | I90: ='FY 2008'!I84 -> 8306508 | J90: ='FY 2009'!$I87 -> 8316835 | K90: ='FY 2010'!$J86 -> 8256617 | L90: ='FY 2011'!$J84 -> 8398467 | M90: ='FY 2012'!$J84 -> 8420986 | N90: ='FY 2013'!$J84 -> 8520070 | O90: ='FY 2014'!$J84 -> 8605364 | P90: ='FY 2015'!$J84 -> 8699484
A91: =A90+1 -> 9 | B91: Sparsity | D91: ='FY 2003'!I83 -> 16471551 | E91: ='FY 2004'!I83 -> 16909578 | F91: ='FY 2005'!I83 -> 17548649 | G91: ='FY 2006'!I85 -> 18853061 | H91: ='FY 2007'!I85 -> 20254233 | I91: ='FY 2008'!I85 -> 21637534 | J91: ='FY 2009'!$I88 -> 22898807 | K91: ='FY 2010'!$J87 -> 23367792 | L91: ='FY 2011'!$J85 -> 23450255 | M91: ='FY 2012'!$J85 -> 24120153 | N91: ='FY 2013'!$J85 -> 24365026 | O91: ='FY 2014'!$J85 -> 24718117 | P91: ='FY 2015'!$J85 -> 25112230
A92: =A91+1 -> 10 | B92: Transport Sparsity | D92: ='FY 2003'!I84 -> 56478364 | E92: ='FY 2004'!I84 -> 55913098 | F92: ='FY 2005'!I84 -> 55511195 | G92: ='FY 2006'!I86 -> 57332807 | H92: ='FY 2007'!I86 -> 59221788 | I92: ='FY 2008'!I86 -> 60083765 | J92: ='FY 2009'!$I89 -> 60159097 | K92: ='FY 2010'!$J88 -> 59886680 | L92: ='FY 2011'!$J86 -> 60310630 | M92: ='FY 2012'!$J86 -> 60119927 | N92: ='FY 2013'!$J86 -> 59879890 | O92: ='FY 2014'!$J86 -> 54545193 | P92: ='FY 2015'!$J86 -> 54382296
A93: =A92+1 -> 11 | B93: Training & Experience | D93: ='FY 2003'!I85 -> 25114308 | E93: ='FY 2004'!I85 -> 18869558 | F93: ='FY 2005'!I85 -> 12876818 | G93: ='FY 2006'!I87 -> 8213502 | H93: ='FY 2007'!I87 -> 4354428 | I93: ='FY 2008'!I87 -> 2146056 | J93: ='FY 2009'!$I90 -> 1207447.6 | K93: ='FY 2010'!$J89 -> 676135 | L93: ='FY 2011'!$J87 -> 372409 | M93: ='FY 2012'!$J87 -> 221683 | N93: ='FY 2013'!$J87 -> 157376 | O93: ='FY 2014'!$J87 -> 127229 | P93: ='FY 2015'!$J87 -> 102766
A94: =A93+1 -> 12 | B94: Late Contract Penalty | D94: ='FY 2003'!I86 -> 0 | E94: ='FY 2004'!I86 -> 0 | F94: ='FY 2005'!I86 -> 0 | G94: ='FY 2006'!I88 -> -344932 | H94: ='FY 2007'!I88 -> 0 | I94: ='FY 2008'!I88 -> -730496 | J94: ='FY 2009'!$I91 -> 0 | K94: ='FY 2010'!$J90 -> -2505728 | L94: ='FY 2011'!$J88 -> 0 | M94: ='FY 2012'!$J88 -> -700000 | N94: ='FY 2013'!$J88 -> 0 | O94: ='FY 2014'!$J88 -> -700000 | P94: ='FY 2015'!$J88 -> 0
A95: =A94+1 -> 13 | B95: One-time Reduction | H95: 0 | I95: 0 | J95: 0 | K95: ='FY 2010'!$J91 -> -500000000 | L95: 0 | M95: 0 | N95: 0 | O95: 0 | P95: 0
A96: =A95+1 -> 14 | B96: Operating Capital | D96: ='FY 2003'!I87 -> 198438434 | E96: ='FY 2004'!I87 -> 194217096 | F96: ='FY 2005'!I87 -> 193697081 | G96: ='FY 2006'!I89 -> 194018388 | H96: ='FY 2007'!I89 -> 194117024 | I96: ='FY 2008'!I89 -> 194635565 | J96: ='FY 2009'!$I92 -> 1.9429911e+08 | K96: ='FY 2010'!$J92 -> 194556865 | L96: ='FY 2011'!$J89 -> 194883547 | M96: ='FY 2012'!$J89 -> 195614651 | N96: ='FY 2013'!$J89 -> 197226538 | O96: ='FY 2014'!$J89 -> 199264643 | P96: ='FY 2015'!$J89 -> 201474978
A97: =A96+1 -> 15 | B97: Equity | D97: ='FY 2003'!I88 -> 34642490 | E97: ='FY 2004'!I88 -> 32112369 | F97: ='FY 2005'!I88 -> 41731237 | G97: ='FY 2006'!I90 -> 50999434 | H97: ='FY 2007'!I90 -> 94274069 | I97: ='FY 2008'!I90 -> 95708805 | J97: ='FY 2009'!$I93 -> 93361990 | K97: ='FY 2010'!$J93 -> 92597190 | L97: ='FY 2011'!$J90 -> 92389473 | M97: ='FY 2012'!$J90 -> 94004026 | N97: ='FY 2013'!$J90 -> 94785794 | O97: ='FY 2014'!$J90 -> 95424221 | P97: ='FY 2015'!$J90 -> 97120793
A98: =A97+1 -> 16 | B98: Transition | D98: ='FY 2003'!I89 -> 0 | E98: ='FY 2004'!I89 -> 31986524 | F98: ='FY 2005'!I89 -> 31326609 | G98: ='FY 2006'!I91 -> 31033742 | H98: ='FY 2007'!I91 -> 30462514 | I98: ='FY 2008'!I91 -> 30143318 | J98: ='FY 2009'!$I94 -> 29711997 | K98: ='FY 2010'!$J94 -> 29474077 | L98: ='FY 2011'!$J91 -> 29230926 | M98: ='FY 2012'!$J91 -> 29122829 | N98: ='FY 2013'!$J91 -> 29417364 | O98: ='FY 2014'!$J91 -> 29971862 | P98: ='FY 2015'!$J91 -> 30488402
A99: =A98+1 -> 17 | B99: Q Comp | D99: ='FY 2003'!I90 -> 0 | E99: ='FY 2004'!I90 -> 0 | F99: ='FY 2005'!I90 -> 0 | G99: ='FY 2006'!I92 -> 16348850 | H99: ='FY 2007'!I92 -> 48603714 | I99: ='FY 2008'!I92 -> 60763648 | J99: ='FY 2009'!$I95 -> 63348360 | K99: ='FY 2010'!$J95 -> 58293197 | L99: ='FY 2011'!$J92 -> 64869028 | M99: ='FY 2012'!$J92 -> 79865157 | N99: ='FY 2013'!$J92 -> 82648038 | O99: ='FY 2014'!$J92 -> 84427081 | P99: ='FY 2015'!$J92 -> 86325972
A100: =A99+1 -> 18 | B100: Referendum Revenue | D100: ='FY 2003'!I91 -> 291708358 | E100: ='FY 2004'!I91 -> 426336542 | F100: ='FY 2005'!I91 -> 504721085 | G100: ='FY 2006'!I93 -> 534314512 | H100: ='FY 2007'!I93 -> 598966155 | I100: ='FY 2008'!I93 -> 644192179 | J100: ='FY 2009'!$I96 -> 7.2056718e+08 | K100: ='FY 2010'!$J96 -> 782245992 | L100: ='FY 2011'!$J93 -> 805394833 | M100: ='FY 2012'!$J93 -> 822570396 | N100: ='FY 2013'!$J93 -> 895199708 | O100: ='FY 2014'!$J93 -> 945763982 | P100: ='FY 2015'!$J93 -> 1016465502
B101: Alternative Attendance Adj:
A102: =A100+1 -> 19 | C102: Open Enroll/Charter Refer | D102: ='FY 2003'!I93 -> 1341221 | E102: ='FY 2004'!I93 -> -679857 | F102: ='FY 2005'!I93 -> -1089963.9 | G102: ='FY 2006'!I95 -> -895441.79 | H102: ='FY 2007'!I95 -> -885672 | I102: ='FY 2008'!I95 -> -181964 | J102: ='FY 2009'!$I98 -> 262096 | K102: ='FY 2010'!$J98 -> 623081 | L102: ='FY 2011'!$J95 -> 752179 | M102: ='FY 2012'!$J95 -> 523272 | N102: ='FY 2013'!$J95 -> 7554 | O102: ='FY 2014'!$J95 -> -212305 | P102: ='FY 2015'!$J95 -> -371775
A103: =A102+1 -> 20 | C103: Charter Basic Transport | D103: ='FY 2003'!I94 -> -1804253 | E103: ='FY 2004'!I94 -> 1059 | F103: ='FY 2005'!I94 -> 0 | G103: ='FY 2006'!I96 -> 0.44 | H103: ='FY 2007'!I96 -> 0 | I103: ='FY 2008'!I96 -> 0 | J103: ='FY 2009'!$I99 -> -0.0099999995 | K103: ='FY 2010'!$J99 -> 1 | L103: ='FY 2011'!$J96 -> 15735 | M103: ='FY 2012'!$J96 -> -703 | N103: ='FY 2013'!$J96 -> -466 | O103: ='FY 2014'!$J96 -> -375 | P103: ='FY 2015'!$J96 -> -375
A104: =A103+1 -> 21 | C104: Charter Ext TimeTransport | D104: ='FY 2003'!I95 -> 0 | E104: ='FY 2004'!I95 -> 0 | F104: ='FY 2005'!I95 -> 0 | G104: ='FY 2006'!I97 -> -0.18 | H104: ='FY 2007'!I97 -> 0 | I104: ='FY 2008'!I97 -> 0 | J104: ='FY 2009'!$I100 -> 0 | K104: ='FY 2010'!$J100 -> 0 | L104: ='FY 2011'!$J97 -> 0 | M104: ='FY 2012'!$J97 -> 0 | N104: ='FY 2013'!$J97 -> 0 | O104: ='FY 2014'!$J97 -> 0 | P104: ='FY 2015'!$J97 -> 0
A105: =A104+1 -> 22 | C105: Charter Transport Sparsity | D105: ='FY 2003'!I96 -> 0 | E105: ='FY 2004'!I96 -> 0 | F105: ='FY 2005'!I96 -> 0 | G105: ='FY 2006'!I98 -> 0.44 | H105: ='FY 2007'!I98 -> 0 | I105: ='FY 2008'!I98 -> 0 | J105: ='FY 2009'!$I101 -> -0.01 | K105: ='FY 2010'!$J101 -> 4 | L105: ='FY 2011'!$J98 -> -890 | M105: ='FY 2012'!$J98 -> 20619 | N105: ='FY 2013'!$J98 -> 35506 | O105: ='FY 2014'!$J98 -> 9736 | P105: ='FY 2015'!$J98 -> 13239
A106: =A105+1 -> 23 | C106: Faribault Alternative Attend Adj | D106: 0 | E106: 0 | F106: 0 | G106: ='FY 2006'!I99 -> 0 | H106: ='FY 2007'!$I99 -> -398 | I106: ='FY 2008'!$I99 -> -355.18 | J106: ='FY 2009'!$I102 -> -461.16 | K106: ='FY 2010'!$J102 -> 54640 | L106: ='FY 2011'!$J99 -> -196 | M106: ='FY 2012'!$J99 -> -196 | N106: ='FY 2013'!$J99 -> -196 | O106: ='FY 2014'!$J99 -> -196 | P106: ='FY 2015'!$J99 -> -196
A108: =A106+1 -> 24 | B108: TOTAL REVENUE | D108: =SUM(D83:D105) -> 5421781814 | E108: =SUM(E83:E105) -> 5514835219 | F108: =SUM(F83:F106) -> 5.5956104e+09 | G108: =SUM(G83:G106) -> 5.8561793e+09 | H108: =SUM(H83:H106) -> 6210065143 | I108: =SUM(I83:I106) -> 6.3917059e+09 | J108: =SUM(J83:J106) -> 6.5560328e+09 | K108: =SUM(K83:K106) -> 6073672850 | L108: =SUM(L83:L106) -> 6671598496 | M108: =SUM(M83:M106) -> 6750880174 | ... P108: =SUM(P83:P106) -> 7181784873
B110: LEVIES
A111: =A108+1 -> 25 | B111: Operating Capital Levy | D111: ='FY 2003'!I101 -> 0 | E111: ='FY 2004'!I101 -> 0 | F111: ='FY 2005'!I101 -> 40007254 | G111: ='FY 2006'!I104 -> 44268155 | H111: ='FY 2007'!I104 -> 101934454 | I111: ='FY 2008'!I104 -> 111830374 | J111: ='FY 2009'!$I107 -> 1.2125304e+08 | K111: ='FY 2010'!$J107 -> 124372672 | L111: ='FY 2011'!$J104 -> 124597747 | M111: ='FY 2012'!$J104 -> 119995993 | N111: ='FY 2013'!$J104 -> 117136021 | O111: ='FY 2014'!$J104 -> 117326405 | P111: ='FY 2015'!$J104 -> 118314714
A112: =A111+1 -> 26 | B112: Equity Levy | D112: ='FY 2003'!I102 -> 0 | E112: ='FY 2004'!I102 -> 0 | F112: ='FY 2005'!I102 -> 22380297 | G112: ='FY 2006'!I105 -> 25083314 | H112: ='FY 2007'!I105 -> 63740065 | I112: ='FY 2008'!I105 -> 70604296 | J112: ='FY 2009'!$I108 -> 73701614 | K112: ='FY 2010'!$J108 -> 75869421 | L112: ='FY 2011'!$J105 -> 76264279 | M112: ='FY 2012'!$J105 -> 75800227 | N112: ='FY 2013'!$J105 -> 73781262 | O112: ='FY 2014'!$J105 -> 73269758 | P112: ='FY 2015'!$J105 -> 74124161
A113: =A112+1 -> 27 | B113: Transition Levy | D113: ='FY 2003'!I103 -> 0 | E113: ='FY 2004'!I103 -> 0 | F113: ='FY 2005'!I103 -> 18540609 | G113: ='FY 2006'!I106 -> 20383544 | H113: ='FY 2007'!I106 -> 21830489 | I113: ='FY 2008'!I106 -> 23010395 | J113: ='FY 2009'!$I109 -> 24292897 | K113: ='FY 2010'!$J109 -> 25223249 | L113: ='FY 2011'!$J106 -> 25220381 | M113: ='FY 2012'!$J106 -> 24544379 | N113: ='FY 2013'!$J106 -> 23904838 | O113: ='FY 2014'!$J106 -> 24071979 | P113: ='FY 2015'!$J106 -> 24361982
A114: =A113+1 -> 28 | B114: Q Comp | D114: ='FY 2003'!I104 -> 0 | E114: ='FY 2004'!I104 -> 0 | F114: ='FY 2005'!I104 -> 0 | G114: ='FY 2006'!I107 -> 0 | H114: ='FY 2007'!I107 -> 9695468 | I114: ='FY 2008'!I107 -> 12779741 | J114: ='FY 2009'!$I110 -> 13353371 | K114: ='FY 2010'!$J110 -> 16808313 | L114: ='FY 2011'!$J107 -> 18764129 | M114: ='FY 2012'!$J107 -> 23054916 | N114: ='FY 2013'!$J107 -> 23061489 | O114: ='FY 2014'!$J107 -> 23474200 | P114: ='FY 2015'!$J107 -> 23994024
A115: =A114+1 -> 29 | B115: Referendum Levy | D115: ='FY 2003'!I105 -> 224945858 | E115: ='FY 2004'!I105 -> 351087875 | F115: ='FY 2005'!I105 -> 379954471 | G115: ='FY 2006'!I108 -> 410867894 | H115: ='FY 2007'!I108 -> 482421730 | I115: ='FY 2008'!I108 -> 540184289 | J115: ='FY 2009'!$I111 -> 6.3533353e+08 | K115: ='FY 2010'!$J111 -> 712846777 | L115: ='FY 2011'!$J108 -> 738357903 | M115: ='FY 2012'!$J108 -> 745759060 | N115: ='FY 2013'!$J108 -> 802617290 | O115: ='FY 2014'!$J108 -> 847746647 | P115: ='FY 2015'!$J108 -> 914711468
...

Sheet FEB04 TEMPLATE
A1: GENERAL ED REVENUE PROJECTIONS: FY 2002
A2: NOVEMBER 2003 FORECAST VS END OF SESSION 2003
B4: AMCPU: | C4: DISTRICT | D4: CHARTER | E4: TOTAL
B5: DEPT. ESTIMATE | C5: 968211 | D5: 0 | E5: =C5+D5 -> 968211
B6: DIST. ESTIMATE | C6: 967747 | D6: 0 | E6: =C6+D6 -> 967747
B7: ADJUSTMENT | C7: =C5-C6 -> 464 | D7: =D5-D6 -> 0 | E7: =E5-E6 -> 464
C8: AID | D8: LEVY | E8: TOTAL | F8: /PU
A9: NOVEMBER | B9: A. BASIC | E9: BSREV$$ | F9: =E9/C$6 -> 0
A10: FORECAST | B10: B. EXTENDED TIME | E10: EXDAYR$$
A11: 2003 | B11: C. BASIC SKILLS | F11: =E11/C$6 -> 0
B12: * COMPENSATORY | E12: CPSREV$$
B13: * LEP | E13: LEPREV$$
B14: * LEP CONC | E14: LEPCRV$$
B15: * AOM | E15: AOMREV$$
B16: D. SPARSITY | E16: TOTSRS$$ | F16: =E16/C$6 -> 0
B17: E. TRANSPORT SPARSITY | E17: TSRSRV$$ | F17: =E17/C$6 -> 0
B18: F. OPER CAPITAL | C18: CEXAID$$ | D18: CEXLVY$$ | E18: OCEXRV$$ | F18: =E18/C$6 -> 0
B19: G. TRAIN & EXPER | E19: TNEREV$$ | F19: =E19/C$6 -> 0
B20: H. EQUITY | C20: EQAID$$ | D20: EQLVY$$ | E20: EQREV$$ | F20: =E20/C$6 -> 0
B21: I. REDUCTION
B22: J. A THROUGH H | C22: TOTAID$$ | D22: TOTLVY$$ | E22: TOTREV$$ | F22: =E22/C$6 -> 0
B23: K. TRANSITION | C23: TRSAID$$ | D23: TRSLVY$$ | E23: TRSREV$$ | F23: =E23/C$6 -> 0
B24: L. SUPPLEMENTAL | C24: SLPAID$$ | D24: SLPLVY$$ | E24: SLPREV$$ | F24: =E24/C$6 -> 0
B25: M. REFERENDUM | C25: REFAID$$ | D25: RFLVYN$$ | E25: REFREV$$ | F25: =E25/C$6 -> 0
B26: N. TAX BSE REPL | C26: REPAID$$
B27: O. ALT ATT ADJ | C27: OPTADJ$$ | E27: OPTADJ$$ | F27: =E27/C$6 -> 0
B28: P. I+J+K+L+M+N | C28: GRDAID$$ | D28: GRDLVY$$ | E28: GRDREV$$ | F28: =E28/C$6 -> 0
A29: END OF | B29: A. BASIC | E29: BSREV4E | F29: =E29/D$6 -> #DIV/0!
A30: SESSION | B30: B. EXTENDED TIME | E30: EXDAYR4E
A31: 2003 | B31: C. BASIC SKILLS | F31: =E31/D$6 -> #DIV/0!
B32: * COMPENSATORY | E32: CPSREV4E
B33: * LEP | E33: LEPREV4E
B34: * LEP CONC | E34: LEPCRV4E
B35: * AOM | E35: AOMREV4E
B36: D. SPARSITY | E36: TOTSRS4E | F36: =E36/D$6 -> #DIV/0!
B37: E. TRANSPORT SPARSITY | E37: TSRSRV4E | F37: =E37/D$6 -> #DIV/0!
B38: F. OPER CAPITAL | C38: CEXAID4E | D38: CEXLVY4E | E38: OCEXRV4E | F38: =E38/D$6 -> #DIV/0!
B39: G. TRAIN & EXPER | E39: TNEREV4E | F39: =E39/D$6 -> #DIV/0!
B40: H. EQUITY | C40: EQAID4E | D40: EQLVY4E | E40: EQREV4E | F40: =E40/D$6 -> #DIV/0!
B41: I. REDUCTION
B42: J. A THROUGH H | C42: TOTAID4E | D42: TOTLVY4E | E42: TOTREV4E | F42: =E42/D$6 -> #DIV/0!
B43: K. TRANSITION | C43: TRSAID4E | D43: TRSLVY4E | E43: TRSREV4E | F43: =E43/D$6 -> #DIV/0!
B44: L. SUPPLEMENTAL | C44: SLPAID4E | D44: SLPLVY4E | E44: SLPREV4E | F44: =E44/D$6 -> #DIV/0!
B45: M. REFERENDUM | C45: REFAID4E | D45: RFLVYN4E | E45: REFREV4E | F45: =E45/D$6 -> #DIV/0!
B46: N. TAX BSE REPL | C46: REPAID4E
B47: O. ALT ATT ADJ | C47: OPTADJ4E | E47: OPTADJ4E | F47: =E47/D$6 -> #DIV/0!
B48: P. I+J+K+L+M+N | C48: GRDAID4E | D48: GRDLVY4E | E48: GRDREV4E | F48: =E48/D$6 -> #DIV/0!
A49: DIFF. | B49: A. BASIC | E49: BSREVDF | F49: N/A
B50: B. EXTENDED TIME | E50: EXDAYRDF
B51: C. BASIC SKILLS | F51: N/A
B52: * COMPENSATORY | E52: CPSREVDF
B53: * LEP | E53: LEPREVDF
B54: * LEP CONC | E54: LEPCRVDF
B55: * AOM | E55: AOMREVDF
B56: D. SPARSITY | E56: TOTSRSDF | F56: N/A
B57: E. TRANSPORT SPARSITY | E57: TSRSRVDF | F57: N/A
B58: F. OPER CAPITAL | C58: CEXAIDDF | D58: CEXLVYDF | E58: OCEXRVDF | F58: N/A
B59: G. TRAIN & EXPER | E59: TNEREVDF | F59: N/A
B60: H. EQUITY | C60: EQAIDDF | D60: EQLVYDF | E60: EQREVDF | F60: N/A
B61: I. REDUCTION
B62: J. A THROUGH H | C62: TOTAIDDF | D62: TOTLVYDF | E62: TOTREVDF | F62: N/A
B63: K. TRANSITION | C63: TRSAIDDF | D63: TRSLVYDF | E63: TRSREVDF | F63: N/A
B64: L. SUPPLEMENTAL | C64: SLPAIDDF | D64: SLPLVYDF | E64: SLPREVDF | F64: N/A
B65: M. REFERENDUM | C65: REFAIDDF | D65: RFLVYNDF | E65: REFREVDF | F65: N/A
B66: N. TAX BSE REPL | C66: REPAIDDF
B67: O. ALT ATT ADJ | C67: OPTADJDF | E67: OPTADJDF | F67: N/A
B68: P. I+J+K+L+M+N | C68: GRDAIDDF | D68: GRDLVYDF | E68: GRDREVDF | F68: N/A

Sheet SUMMARY-Approp Table
A1: FEB 2011 VS. NOV 2010
A3: FEBRUARY 2011 FORECAST | D3: FY 2003 | E3: FY 2004 | F3: FY 2005 | G3: FY 2006 | H3: FY 2007 | I3: FY 2008 | J3: FY 2009 | K3: FY 2010 | L3: FY 2011 | M3: FY 2012 | N3: FY 2013 | O3: FY 2014 | P3: FY 2015 | Q3: 2008-09 | R3: 2010-11 | S3: 2012-13 | T3: 2014-15 | U3: Chg from 2008-09 | V3: % chg | W3: Chg from 2010-11 | X3: % chg | Y3: Chg from 2012-13 | Z3: % chg
A5: 1 | B5: AMCPU | D5: ='FY 2003'!I5 -> 962146 | E5: ='FY 2004'!I5 -> 957096 | F5: ='FY 2005'!I5 -> 953035 | G5: ='FY 2006'!I5 -> 953041 | H5: ='FY 2007'!I5 -> 953288 | I5: ='FY 2008'!I5 -> 953432 | J5: ='FY 2009'!$I5 -> 948587 | K5: ='FY 2010'!$J5 -> 947210 | L5: ='FY 2011'!$J5 -> 948097 | M5: ='FY 2012'!$J5 -> 951670 | N5: ='FY 2013'!$J5 -> 959454 | O5: ='FY 2014'!$J5 -> 969398 | P5: ='FY 2015'!$J5 -> 979275
B7: REVENUES
A8: =A5+1 -> 2 | B8: Basic | D8: ='FY 2003'!I8 -> 4490060320 | E8: ='FY 2004'!I8 -> 4403575277 | F8: =ROUND('SUMMARY-ALL YEARS'!F8/1000,1) -> 4384973.8 | G8: =ROUND('SUMMARY-ALL YEARS'!G8/1000,1) -> 4558383.7 | H8: =ROUND('SUMMARY-ALL YEARS'!H8/1000,1) -> 4741676.9 | I8: =ROUND('SUMMARY-ALL YEARS'!I8/1000,1) -> 4837724.5 | J8: =ROUND('SUMMARY-ALL YEARS'!J8/1000,1) -> 4860574.7 | K8: =ROUND('SUMMARY-ALL YEARS'!K8/1000,1) -> 4853494.9 | L8: =ROUND('SUMMARY-ALL YEARS'!L8/1000,1) -> 4858048.1 | M8: =ROUND('SUMMARY-ALL YEARS'!M8/1000,1) -> 4876357.2 | ... P8: =ROUND('SUMMARY-ALL YEARS'!P8/1000,1) -> 5017805.4 | Q8: =SUM(I8:J8) -> 9698299.2 | R8: =SUM(K8:L8) -> 9711543 | S8: =SUM(M8:N8) -> 9792597.4 | T8: =SUM(O8:P8) -> 9985004.5 | U8: =R8-Q8 -> 13243.8 | V8: =U8/Q8 -> 0.0013655796 | W8: =S8-R8 -> 81054.4 | X8: =W8/R8 -> 0.0083461917 | Y8: =T8-S8 -> 192407.1 | Z8: =Y8/S8 -> 0.019648219
A9: =A8+1 -> 3 | B9: Additional $51 | F9: 0 | G9: 0 | H9: 0 | I9: 0 | J9: =ROUND('SUMMARY-ALL YEARS'!J9/1000,1) -> 48378.1 | K9: 0 | L9: 0 | M9: 0 | N9: 0 | O9: 0 | P9: 0 | Q9: =SUM(I9:J9) -> 48378.1 | R9: =SUM(K9:L9) -> 0 | S9: =SUM(M9:N9) -> 0 | T9: =SUM(O9:P9) -> 0 | U9: =R9-Q9 -> -48378.1 | V9: =U9/Q9 -> -1 | W9: =S9-R9 -> 0 | X9: =W9/R9 -> #DIV/0! | Y9: =T9-S9 -> 0 | Z9: =Y9/S9 -> #DIV/0!
A10: =A9+1 -> 4 | B10: Gifted & Talented | D10: ='FY 2003'!I9 -> 0 | E10: ='FY 2004'!I9 -> 0 | F10: =ROUND('SUMMARY-ALL YEARS'!F10/1000,1) -> 0 | G10: =ROUND('SUMMARY-ALL YEARS'!G10/1000,1) -> 3812.2 | H10: =ROUND('SUMMARY-ALL YEARS'!H10/1000,1) -> 8579.6 | I10: =ROUND('SUMMARY-ALL YEARS'!I10/1000,1) -> 11441.2 | J10: =ROUND('SUMMARY-ALL YEARS'!J10/1000,1) -> 11383.1 | K10: =ROUND('SUMMARY-ALL YEARS'!K10/1000,1) -> 11365.9 | L10: =ROUND('SUMMARY-ALL YEARS'!L10/1000,1) -> 11377.2 | M10: =ROUND('SUMMARY-ALL YEARS'!M10/1000,1) -> 11420 | ... P10: =ROUND('SUMMARY-ALL YEARS'!P10/1000,1) -> 11751.3 | Q10: =SUM(I10:J10) -> 22824.3 | R10: =SUM(K10:L10) -> 22743.1 | S10: =SUM(M10:N10) -> 22933.4 | T10: =SUM(O10:P10) -> 23384.1 | U10: =R10-Q10 -> -81.2 | V10: =U10/Q10 -> -0.0035576118 | W10: =S10-R10 -> 190.3 | X10: =W10/R10 -> 0.008367373 | Y10: =T10-S10 -> 450.7 | Z10: =Y10/S10 -> 0.019652559
A11: =A10+1 -> 5 | B11: Extended time | D11: ='FY 2003'!I10 -> 0 | E11: ='FY 2004'!I10 -> 50351550 | F11: =ROUND('SUMMARY-ALL YEARS'!F11/1000,1) -> 52327.4 | G11: =ROUND('SUMMARY-ALL YEARS'!G11/1000,1) -> 52766.2 | H11: =ROUND('SUMMARY-ALL YEARS'!H11/1000,1) -> 55437 | I11: =ROUND('SUMMARY-ALL YEARS'!I11/1000,1) -> 59590.8 | J11: =ROUND('SUMMARY-ALL YEARS'!J11/1000,1) -> 60995.6 | K11: =ROUND('SUMMARY-ALL YEARS'!K11/1000,1) -> 64565.4 | L11: =ROUND('SUMMARY-ALL YEARS'!L11/1000,1) -> 69073 | M11: =ROUND('SUMMARY-ALL YEARS'!M11/1000,1) -> 71777.9 | ... P11: =ROUND('SUMMARY-ALL YEARS'!P11/1000,1) -> 84903.3 | Q11: =SUM(I11:J11) -> 120586.4 | R11: =SUM(K11:L11) -> 133638.4 | S11: =SUM(M11:N11) -> 147844.7 | T11: =SUM(O11:P11) -> 165344.6 | U11: =R11-Q11 -> 13052 | V11: =U11/Q11 -> 0.10823774 | W11: =S11-R11 -> 14206.3 | X11: =W11/R11 -> 0.10630403 | Y11: =T11-S11 -> 17499.9 | Z11: =Y11/S11 -> 0.11836677
B12: Basic Skills:
A13: =A11+1 -> 6 | C13: Compensatory | D13: ='FY 2003'!I12 -> 262694686 | E13: ='FY 2004'!I12 -> 249146954 | F13: =ROUND('SUMMARY-ALL YEARS'!F13/1000,1) -> 265074.5 | G13: =ROUND('SUMMARY-ALL YEARS'!G13/1000,1) -> 292547.5 | H13: =ROUND('SUMMARY-ALL YEARS'!H13/1000,1) -> 315471.9 | I13: =ROUND('SUMMARY-ALL YEARS'!I13/1000,1) -> 333928.1 | J13: =ROUND('SUMMARY-ALL YEARS'!J13/1000,1) -> 348510.7 | K13: =ROUND('SUMMARY-ALL YEARS'!K13/1000,1) -> 361157.3 | L13: =ROUND('SUMMARY-ALL YEARS'!L13/1000,1) -> 414260.4 | M13: =ROUND('SUMMARY-ALL YEARS'!M13/1000,1) -> 432960.5 | ... P13: =ROUND('SUMMARY-ALL YEARS'!P13/1000,1) -> 495561.1 | Q13: =SUM(I13:J13) -> 682438.8 | R13: =SUM(K13:L13) -> 775417.7 | S13: =SUM(M13:N13) -> 885520.4 | T13: =SUM(O13:P13) -> 969182.1 | U13: =R13-Q13 -> 92978.9 | V13: =U13/Q13 -> 0.13624504 | W13: =S13-R13 -> 110102.7 | X13: =W13/R13 -> 0.14199147 | Y13: =T13-S13 -> 83661.7 | Z13: =Y13/S13 -> 0.094477439
A14: =A13+1 -> 7 | C14: LEP | D14: ='FY 2003'!I13 -> 36857227 | E14: ='FY 2004'!I13 -> 28818713 | F14: =ROUND('SUMMARY-ALL YEARS'!F14/1000,1) -> 29477.7 | G14: =ROUND('SUMMARY-ALL YEARS'!G14/1000,1) -> 30912.7 | H14: =ROUND('SUMMARY-ALL YEARS'!H14/1000,1) -> 31474.3 | I14: =ROUND('SUMMARY-ALL YEARS'!I14/1000,1) -> 32316.8 | J14: =ROUND('SUMMARY-ALL YEARS'!J14/1000,1) -> 32058.2 | K14: =ROUND('SUMMARY-ALL YEARS'!K14/1000,1) -> 31807.9 | L14: =ROUND('SUMMARY-ALL YEARS'!L14/1000,1) -> 31673.1 | M14: =ROUND('SUMMARY-ALL YEARS'!M14/1000,1) -> 31709.9 | ... P14: =ROUND('SUMMARY-ALL YEARS'!P14/1000,1) -> 32480 | Q14: =SUM(I14:J14) -> 64375 | R14: =SUM(K14:L14) -> 63481 | S14: =SUM(M14:N14) -> 63576.9 | T14: =SUM(O14:P14) -> 64659.4 | U14: =R14-Q14 -> -894 | V14: =U14/Q14 -> -0.013887379 | W14: =S14-R14 -> 95.9 | X14: =W14/R14 -> 0.0015106882 | Y14: =T14-S14 -> 1082.5 | Z14: =Y14/S14 -> 0.017026624
A15: =A14+1 -> 8 | C15: LEP Concentration | D15: ='FY 2003'!I14 -> 9779108 | E15: ='FY 2004'!I14 -> 7276758 | F15: =ROUND('SUMMARY-ALL YEARS'!F15/1000,1) -> 7434.3 | G15: =ROUND('SUMMARY-ALL YEARS'!G15/1000,1) -> 7883.2 | H15: =ROUND('SUMMARY-ALL YEARS'!H15/1000,1) -> 8057.6 | I15: =ROUND('SUMMARY-ALL YEARS'!I15/1000,1) -> 8306.5 | J15: =ROUND('SUMMARY-ALL YEARS'!J15/1000,1) -> 8316.8 | K15: =ROUND('SUMMARY-ALL YEARS'!K15/1000,1) -> 8258.3 | L15: =ROUND('SUMMARY-ALL YEARS'!L15/1000,1) -> 8387.5 | M15: =ROUND('SUMMARY-ALL YEARS'!M15/1000,1) -> 8406.8 | ... P15: =ROUND('SUMMARY-ALL YEARS'!P15/1000,1) -> 8651.7 | Q15: =SUM(I15:J15) -> 16623.3 | R15: =SUM(K15:L15) -> 16645.8 | S15: =SUM(M15:N15) -> 16907 | T15: =SUM(O15:P15) -> 17231.1 | U15: =R15-Q15 -> 22.5 | V15: =U15/Q15 -> 0.0013535219 | W15: =S15-R15 -> 261.2 | X15: =W15/R15 -> 0.015691646 | Y15: =T15-S15 -> 324.1 | Z15: =Y15/S15 -> 0.019169575
A16: =A15+1 -> 9 | B16: Sparsity | D16: ='FY 2003'!I15 -> 16471551 | E16: ='FY 2004'!I15 -> 16909578 | F16: =ROUND('SUMMARY-ALL YEARS'!F16/1000,1) -> 17548.6 | G16: =ROUND('SUMMARY-ALL YEARS'!G16/1000,1) -> 18853.1 | H16: =ROUND('SUMMARY-ALL YEARS'!H16/1000,1) -> 20254.2 | I16: =ROUND('SUMMARY-ALL YEARS'!I16/1000,1) -> 21637.5 | J16: =ROUND('SUMMARY-ALL YEARS'!J16/1000,1) -> 22898.8 | K16: =ROUND('SUMMARY-ALL YEARS'!K16/1000,1) -> 23368.6 | L16: =ROUND('SUMMARY-ALL YEARS'!L16/1000,1) -> 23511.2 | M16: =ROUND('SUMMARY-ALL YEARS'!M16/1000,1) -> 24128.7 | ... P16: =ROUND('SUMMARY-ALL YEARS'!P16/1000,1) -> 25012.3 | Q16: =SUM(I16:J16) -> 44536.3 | R16: =SUM(K16:L16) -> 46879.8 | S16: =SUM(M16:N16) -> 48495.5 | T16: =SUM(O16:P16) -> 49649.4 | U16: =R16-Q16 -> 2343.5 | V16: =U16/Q16 -> 0.052619998 | W16: =S16-R16 -> 1615.7 | X16: =W16/R16 -> 0.034464737 | Y16: =T16-S16 -> 1153.9 | Z16: =Y16/S16 -> 0.02379396
A17: =A16+1 -> 10 | B17: Transport Sparsity | D17: ='FY 2003'!I16 -> 56478364 | E17: ='FY 2004'!I16 -> 55913098 | F17: =ROUND('SUMMARY-ALL YEARS'!F17/1000,1) -> 55511.2 | G17: =ROUND('SUMMARY-ALL YEARS'!G17/1000,1) -> 57332.8 | H17: =ROUND('SUMMARY-ALL YEARS'!H17/1000,1) -> 59221.8 | I17: =ROUND('SUMMARY-ALL YEARS'!I17/1000,1) -> 60083.8 | J17: =ROUND('SUMMARY-ALL YEARS'!J17/1000,1) -> 60159.1 | K17: =ROUND('SUMMARY-ALL YEARS'!K17/1000,1) -> 59833.2 | L17: =ROUND('SUMMARY-ALL YEARS'!L17/1000,1) -> 60371.5 | M17: =ROUND('SUMMARY-ALL YEARS'!M17/1000,1) -> 60249.6 | ... P17: =ROUND('SUMMARY-ALL YEARS'!P17/1000,1) -> 59683.8 | Q17: =SUM(I17:J17) -> 120242.9 | R17: =SUM(K17:L17) -> 120204.7 | S17: =SUM(M17:N17) -> 120258.8 | T17: =SUM(O17:P17) -> 119493.7 | U17: =R17-Q17 -> -38.2 | V17: =U17/Q17 -> -0.00031769028 | W17: =S17-R17 -> 54.1 | X17: =W17/R17 -> 0.0004500656 | Y17: =T17-S17 -> -765.1 | Z17: =Y17/S17 -> -0.0063621124
A18: =A17+1 -> 11 | B18: Training & Experience | D18: ='FY 2003'!I17 -> 25114308 | E18: ='FY 2004'!I17 -> 18869558 | F18: =ROUND('SUMMARY-ALL YEARS'!F18/1000,1) -> 12876.8 | G18: =ROUND('SUMMARY-ALL YEARS'!G18/1000,1) -> 8213.5 | H18: =ROUND('SUMMARY-ALL YEARS'!H18/1000,1) -> 4354.4 | I18: =ROUND('SUMMARY-ALL YEARS'!I18/1000,1) -> 2146.1 | J18: =ROUND('SUMMARY-ALL YEARS'!J18/1000,1) -> 1207.4 | K18: =ROUND('SUMMARY-ALL YEARS'!K18/1000,1) -> 675.9 | L18: =ROUND('SUMMARY-ALL YEARS'!L18/1000,1) -> 373.2 | M18: =ROUND('SUMMARY-ALL YEARS'!M18/1000,1) -> 223.2 | ... P18: =ROUND('SUMMARY-ALL YEARS'!P18/1000,1) -> 104.2 | Q18: =SUM(I18:J18) -> 3353.5 | R18: =SUM(K18:L18) -> 1049.1 | S18: =SUM(M18:N18) -> 382.1 | T18: =SUM(O18:P18) -> 233 | U18: =R18-Q18 -> -2304.4 | V18: =U18/Q18 -> -0.68716267 | W18: =S18-R18 -> -667 | X18: =W18/R18 -> -0.63578305 | Y18: =T18-S18 -> -149.1 | Z18: =Y18/S18 -> -0.39021199
A19: =A18+1 -> 12 | B19: Late Contract Penalty | D19: ='FY 2003'!I18 -> 0 | E19: ='FY 2004'!I18 -> 0 | F19: =ROUND('SUMMARY-ALL YEARS'!F19/1000,1) -> 0 | G19: =ROUND('SUMMARY-ALL YEARS'!G19/1000,1) -> -344.9 | H19: =ROUND('SUMMARY-ALL YEARS'!H19/1000,1) -> 0 | I19: =ROUND('SUMMARY-ALL YEARS'!I19/1000,1) -> -730.5 | J19: =ROUND('SUMMARY-ALL YEARS'!J19/1000,1) -> 0 | K19: =ROUND('SUMMARY-ALL YEARS'!K19/1000,1) -> -2507.1 | L19: =ROUND('SUMMARY-ALL YEARS'!L19/1000,1) -> 0 | M19: =ROUND('SUMMARY-ALL YEARS'!M19/1000,1) -> -700 | ... P19: =ROUND('SUMMARY-ALL YEARS'!P19/1000,1) -> 0 | Q19: =SUM(I19:J19) -> -730.5 | R19: =SUM(K19:L19) -> -2507.1 | S19: =SUM(M19:N19) -> -700 | T19: =SUM(O19:P19) -> -700 | U19: =R19-Q19 -> -1776.6 | V19: =U19/Q19 -> 2.4320329 | W19: =S19-R19 -> 1807.1 | X19: =W19/R19 -> -0.72079295 | Y19: =T19-S19 -> 0 | Z19: =Y19/S19 -> 0
A20: =A19+1 -> 13 | B20: One-time Reduction | H20: 0 | I20: 0 | J20: 0 | K20: =ROUND('SUMMARY-ALL YEARS'!K20/1000,1) -> -500000 | L20: 0 | M20: 0 | N20: 0 | O20: 0 | P20: 0 | Q20: =SUM(I20:J20) -> 0 | R20: =SUM(K20:L20) -> -500000 | S20: =SUM(M20:N20) -> 0 | T20: =SUM(O20:P20) -> 0 | U20: =R20-Q20 -> -500000 | V20: =U20/Q20 -> #DIV/0! | W20: =S20-R20 -> 500000 | X20: =W20/R20 -> -1 | Y20: =T20-S20 -> 0 | Z20: =Y20/S20 -> #DIV/0!
A21: =A20+1 -> 14 | B21: Operating Capital | D21: ='FY 2003'!I19 -> 198438434 | E21: ='FY 2004'!I19 -> 194217096 | F21: =ROUND('SUMMARY-ALL YEARS'!F21/1000,1) -> 193697.1 | G21: =ROUND('SUMMARY-ALL YEARS'!G21/1000,1) -> 194018.4 | H21: =ROUND('SUMMARY-ALL YEARS'!H21/1000,1) -> 194117 | I21: =ROUND('SUMMARY-ALL YEARS'!I21/1000,1) -> 194635.6 | J21: =ROUND('SUMMARY-ALL YEARS'!J21/1000,1) -> 194299.1 | K21: =ROUND('SUMMARY-ALL YEARS'!K21/1000,1) -> 194409.8 | L21: =ROUND('SUMMARY-ALL YEARS'!L21/1000,1) -> 194612.2 | M21: =ROUND('SUMMARY-ALL YEARS'!M21/1000,1) -> 195303.1 | ... P21: =ROUND('SUMMARY-ALL YEARS'!P21/1000,1) -> 200893.9 | Q21: =SUM(I21:J21) -> 388934.7 | R21: =SUM(K21:L21) -> 389022 | S21: =SUM(M21:N21) -> 392168.9 | T21: =SUM(O21:P21) -> 399779 | U21: =R21-Q21 -> 87.3 | V21: =U21/Q21 -> 0.00022445927 | W21: =S21-R21 -> 3146.9 | X21: =W21/R21 -> 0.0080892597 | Y21: =T21-S21 -> 7610.1 | Z21: =Y21/S21 -> 0.019405159
A22: =A21+1 -> 15 | B22: Equity | D22: ='FY 2003'!I20 -> 34642490 | E22: ='FY 2004'!I20 -> 32112369 | F22: =ROUND('SUMMARY-ALL YEARS'!F22/1000,1) -> 41731.2 | G22: =ROUND('SUMMARY-ALL YEARS'!G22/1000,1) -> 50999.4 | H22: =ROUND('SUMMARY-ALL YEARS'!H22/1000,1) -> 94274.1 | I22: =ROUND('SUMMARY-ALL YEARS'!I22/1000,1) -> 95708.8 | J22: =ROUND('SUMMARY-ALL YEARS'!J22/1000,1) -> 93362 | K22: =ROUND('SUMMARY-ALL YEARS'!K22/1000,1) -> 92518.8 | L22: =ROUND('SUMMARY-ALL YEARS'!L22/1000,1) -> 92334 | M22: =ROUND('SUMMARY-ALL YEARS'!M22/1000,1) -> 93367.2 | ... P22: =ROUND('SUMMARY-ALL YEARS'!P22/1000,1) -> 98582.7 | Q22: =SUM(I22:J22) -> 189070.8 | R22: =SUM(K22:L22) -> 184852.8 | S22: =SUM(M22:N22) -> 187848.9 | T22: =SUM(O22:P22) -> 194919.8 | U22: =R22-Q22 -> -4218 | V22: =U22/Q22 -> -0.022309103 | W22: =S22-R22 -> 2996.1 | X22: =W22/R22 -> 0.016208031 | Y22: =T22-S22 -> 7070.9 | Z22: =Y22/S22 -> 0.037641424
A23: =A22+1 -> 16 | B23: Transition | D23: ='FY 2003'!I21 -> 0 | E23: ='FY 2004'!I21 -> 31986524 | F23: =ROUND('SUMMARY-ALL YEARS'!F23/1000,1) -> 31326.6 | G23: =ROUND('SUMMARY-ALL YEARS'!G23/1000,1) -> 31033.7 | H23: =ROUND('SUMMARY-ALL YEARS'!H23/1000,1) -> 30462.5 | I23: =ROUND('SUMMARY-ALL YEARS'!I23/1000,1) -> 30143.3 | J23: =ROUND('SUMMARY-ALL YEARS'!J23/1000,1) -> 29712 | K23: =ROUND('SUMMARY-ALL YEARS'!K23/1000,1) -> 29453.1 | L23: =ROUND('SUMMARY-ALL YEARS'!L23/1000,1) -> 29215.4 | M23: =ROUND('SUMMARY-ALL YEARS'!M23/1000,1) -> 29102 | ... P23: =ROUND('SUMMARY-ALL YEARS'!P23/1000,1) -> 29884.4 | Q23: =SUM(I23:J23) -> 59855.3 | R23: =SUM(K23:L23) -> 58668.5 | S23: =SUM(M23:N23) -> 58396.3 | T23: =SUM(O23:P23) -> 59498.2 | U23: =R23-Q23 -> -1186.8 | V23: =U23/Q23 -> -0.019827818 | W23: =S23-R23 -> -272.2 | X23: =W23/R23 -> -0.0046396277 | Y23: =T23-S23 -> 1101.9 | Z23: =Y23/S23 -> 0.018869346
A24: =A23+1 -> 17 | B24: Q Comp | D24: ='FY 2003'!I22 -> 0 | E24: ='FY 2004'!I22 -> 0 | F24: =ROUND('SUMMARY-ALL YEARS'!F24/1000,1) -> 0 | G24: =ROUND('SUMMARY-ALL YEARS'!G24/1000,1) -> 16348.9 | H24: =ROUND('SUMMARY-ALL YEARS'!H24/1000,1) -> 48603.7 | I24: =ROUND('SUMMARY-ALL YEARS'!I24/1000,1) -> 60763.6 | J24: =ROUND('SUMMARY-ALL YEARS'!J24/1000,1) -> 63348.4 | K24: =ROUND('SUMMARY-ALL YEARS'!K24/1000,1) -> 58291.5 | L24: =ROUND('SUMMARY-ALL YEARS'!L24/1000,1) -> 63056.9 | M24: =ROUND('SUMMARY-ALL YEARS'!M24/1000,1) -> 79031.2 | ... P24: =ROUND('SUMMARY-ALL YEARS'!P24/1000,1) -> 86016.3 | Q24: =SUM(I24:J24) -> 124112 | R24: =SUM(K24:L24) -> 121348.4 | S24: =SUM(M24:N24) -> 160939.7 | T24: =SUM(O24:P24) -> 169993 | U24: =R24-Q24 -> -2763.6 | V24: =U24/Q24 -> -0.022266985 | W24: =S24-R24 -> 39591.3 | X24: =W24/R24 -> 0.32626141 | Y24: =T24-S24 -> 9053.3 | Z24: =Y24/S24 -> 0.056252746
A25: =A24+1 -> 18 | B25: Referendum Revenue | D25: ='FY 2003'!I23 -> 291708358 | E25: ='FY 2004'!I23 -> 426336542 | F25: =ROUND('SUMMARY-ALL YEARS'!F25/1000,1) -> 504721.1 | G25: =ROUND('SUMMARY-ALL YEARS'!G25/1000,1) -> 534314.5 | H25: =ROUND('SUMMARY-ALL YEARS'!H25/1000,1) -> 598966.2 | I25: =ROUND('SUMMARY-ALL YEARS'!I25/1000,1) -> 644192.2 | J25: =ROUND('SUMMARY-ALL YEARS'!J25/1000,1) -> 720567.2 | K25: =ROUND('SUMMARY-ALL YEARS'!K25/1000,1) -> 781675.1 | L25: =ROUND('SUMMARY-ALL YEARS'!L25/1000,1) -> 804832.3 | M25: =ROUND('SUMMARY-ALL YEARS'!M25/1000,1) -> 822497.4 | ... P25: =ROUND('SUMMARY-ALL YEARS'!P25/1000,1) -> 1016293.4 | Q25: =SUM(I25:J25) -> 1364759.4 | R25: =SUM(K25:L25) -> 1586507.4 | S25: =SUM(M25:N25) -> 1717710.4 | T25: =SUM(O25:P25) -> 1962184.5 | U25: =R25-Q25 -> 221748 | V25: =U25/Q25 -> 0.16248139 | W25: =S25-R25 -> 131203 | X25: =W25/R25 -> 0.082699268 | Y25: =T25-S25 -> 244474.1 | Z25: =Y25/S25 -> 0.14232556
B27: Alternative Attendance Adj:
A28: =A25+1 -> 19 | C28: All Categories | D28: ='FY 2003'!I25 -> 1341221 | E28: ='FY 2004'!I25 -> -679857 | F28: =ROUND(SUM('SUMMARY-ALL YEARS'!F27:F31)/1000,1) -> -1090 | G28: =ROUND(SUM('SUMMARY-ALL YEARS'!G27:G31)/1000,1) -> -895.4 | H28: =ROUND(SUM('SUMMARY-ALL YEARS'!H27:H31)/1000,1) -> -886.1 | I28: =ROUND(SUM('SUMMARY-ALL YEARS'!I27:I31)/1000,1) -> -182.3 | J28: =ROUND(SUM('SUMMARY-ALL YEARS'!J27:J31)/1000,1) -> 261.6 | K28: =ROUND(SUM('SUMMARY-ALL YEARS'!K27:K31)/1000,1) -> 606.9 | L28: =ROUND(SUM('SUMMARY-ALL YEARS'!L27:L31)/1000,1) -> 658.4 | M28: =ROUND(SUM('SUMMARY-ALL YEARS'!M27:M31)/1000,1) -> 338.5 | ... P28: =ROUND(SUM('SUMMARY-ALL YEARS'!P27:P31)/1000,1) -> -315 | Q28: =SUM(I28:J28) -> 79.3 | R28: =SUM(K28:L28) -> 1265.3 | S28: =SUM(M28:N28) -> 193.5 | T28: =SUM(O28:P28) -> -547.9 | U28: =R28-Q28 -> 1186 | V28: =U28/Q28 -> 14.955864 | W28: =S28-R28 -> -1071.8 | X28: =W28/R28 -> -0.84707184 | Y28: =T28-S28 -> -741.4 | Z28: =Y28/S28 -> -3.8315245
A29: =A28+1 -> 20 | D29: ='FY 2003'!I26 -> -1804253 | E29: ='FY 2004'!I26 -> 1059 | F29: 0 | G29: 0 | H29: 0 | I29: 0 | J29: 0 | K29: 0 | L29: 0 | M29: 0 | N29: 0 | O29: 0 | P29: 0
A30: =A29+1 -> 21 | D30: ='FY 2003'!I27 -> 0 | E30: ='FY 2004'!I27 -> 0 | F30: 0 | G30: 0 | H30: 0 | I30: 0 | J30: 0 | K30: 0 | L30: 0 | M30: 0 | N30: 0 | O30: 0 | P30: 0
A31: =A30+1 -> 22 | D31: ='FY 2003'!I28 -> 0 | E31: ='FY 2004'!I28 -> 0 | F31: 0 | G31: 0 | H31: 0 | I31: 0 | J31: 0 | K31: 0 | L31: 0 | M31: 0 | N31: 0 | O31: 0 | P31: 0
A32: =A31+1 -> 23 | D32: 0 | E32: 0 | F32: 0 | G32: 0 | H32: 0 | I32: 0 | J32: 0 | K32: 0 | L32: 0 | M32: 0 | N32: 0 | O32: 0 | P32: 0
A34: =A32+1 -> 24 | B34: TOTAL REVENUE | D34: =SUM(D8:D32) -> 5421781814 | E34: =SUM(E8:E32) -> 5514835219 | F34: =SUM(F8:F32) -> 5595610.3 | G34: =SUM(G8:G32) -> 5856179.5 | H34: =SUM(H8:H32) -> 6210065.1 | I34: =SUM(I8:I32) -> 6391706 | J34: =SUM(J8:J32) -> 6556032.8 | K34: =SUM(K8:K32) -> 6068975.5 | ... P34: =SUM(P8:P32) -> 7167308.8 | Q34: =SUM(I34:J34) -> 12947739 | R34: =SUM(K34:L34) -> 12730760 | S34: =SUM(M34:N34) -> 13615074 | T34: =SUM(O34:P34) -> 14179308 | U34: =R34-Q34 -> -216978.9 | V34: =U34/Q34 -> -0.016758054 | W34: =S34-R34 -> 884314 | X34: =W34/R34 -> 0.069462782 | Y34: =T34-S34 -> 564234.6 | Z34: =Y34/S34 -> 0.041441905
B36: LEVIES
A37: =A34+1 -> 25 | B37: Operating Capital Levy | D37: ='FY 2003'!I33 -> 0 | E37: ='FY 2004'!I33 -> 0 | F37: =ROUND('SUMMARY-ALL YEARS'!F37/1000,1) -> 40007.3 | G37: =ROUND('SUMMARY-ALL YEARS'!G37/1000,1) -> 44268.2 | H37: =ROUND('SUMMARY-ALL YEARS'!H37/1000,1) -> 101934.5 | I37: =ROUND('SUMMARY-ALL YEARS'!I37/1000,1) -> 111830.4 | J37: =ROUND('SUMMARY-ALL YEARS'!J37/1000,1) -> 121253 | K37: =ROUND('SUMMARY-ALL YEARS'!K37/1000,1) -> 124276.6 | L37: =ROUND('SUMMARY-ALL YEARS'!L37/1000,1) -> 124623.9 | M37: =ROUND('SUMMARY-ALL YEARS'!M37/1000,1) -> 120033.8 | ... P37: =ROUND('SUMMARY-ALL YEARS'!P37/1000,1) -> 114314.9 | Q37: =SUM(I37:J37) -> 233083.4 | R37: =SUM(K37:L37) -> 248900.5 | S37: =SUM(M37:N37) -> 233588 | T37: =SUM(O37:P37) -> 227719 | U37: =R37-Q37 -> 15817.1 | V37: =U37/Q37 -> 0.067860259 | W37: =S37-R37 -> -15312.5 | X37: =W37/R37 -> -0.061520567 | Y37: =T37-S37 -> -5869 | Z37: =Y37/S37 -> -0.025125435
A38: =A37+1 -> 26 | B38: Equity Levy | D38: ='FY 2003'!I34 -> 0 | E38: ='FY 2004'!I34 -> 0 | F38: =ROUND('SUMMARY-ALL YEARS'!F38/1000,1) -> 22380.3 | G38: =ROUND('SUMMARY-ALL YEARS'!G38/1000,1) -> 25083.3 | H38: =ROUND('SUMMARY-ALL YEARS'!H38/1000,1) -> 63740.1 | I38: =ROUND('SUMMARY-ALL YEARS'!I38/1000,1) -> 70604.3 | J38: =ROUND('SUMMARY-ALL YEARS'!J38/1000,1) -> 73701.6 | K38: =ROUND('SUMMARY-ALL YEARS'!K38/1000,1) -> 75798.7 | L38: =ROUND('SUMMARY-ALL YEARS'!L38/1000,1) -> 76305.4 | M38: =ROUND('SUMMARY-ALL YEARS'!M38/1000,1) -> 75373.9 | ... P38: =ROUND('SUMMARY-ALL YEARS'!P38/1000,1) -> 75353.8 | Q38: =SUM(I38:J38) -> 144305.9 | R38: =SUM(K38:L38) -> 152104.1 | S38: =SUM(M38:N38) -> 148871.1 | T38: =SUM(O38:P38) -> 149400.8 | U38: =R38-Q38 -> 7798.2 | V38: =U38/Q38 -> 0.054039371 | W38: =S38-R38 -> -3233 | X38: =W38/R38 -> -0.02125518 | Y38: =T38-S38 -> 529.7 | Z38: =Y38/S38 -> 0.0035581117
A39: =A38+1 -> 27 | B39: Transition Levy | D39: ='FY 2003'!I35 -> 0 | E39: ='FY 2004'!I35 -> 0 | F39: =ROUND('SUMMARY-ALL YEARS'!F39/1000,1) -> 18540.6 | G39: =ROUND('SUMMARY-ALL YEARS'!G39/1000,1) -> 20383.5 | H39: =ROUND('SUMMARY-ALL YEARS'!H39/1000,1) -> 21830.5 | I39: =ROUND('SUMMARY-ALL YEARS'!I39/1000,1) -> 23010.4 | J39: =ROUND('SUMMARY-ALL YEARS'!J39/1000,1) -> 24292.9 | K39: =ROUND('SUMMARY-ALL YEARS'!K39/1000,1) -> 25195.5 | L39: =ROUND('SUMMARY-ALL YEARS'!L39/1000,1) -> 25244.5 | M39: =ROUND('SUMMARY-ALL YEARS'!M39/1000,1) -> 24570.1 | ... P39: =ROUND('SUMMARY-ALL YEARS'!P39/1000,1) -> 23821.6 | Q39: =SUM(I39:J39) -> 47303.3 | R39: =SUM(K39:L39) -> 50440 | S39: =SUM(M39:N39) -> 48324.3 | T39: =SUM(O39:P39) -> 47544.7 | U39: =R39-Q39 -> 3136.7 | V39: =U39/Q39 -> 0.066310384 | W39: =S39-R39 -> -2115.7 | X39: =W39/R39 -> -0.041944885 | Y39: =T39-S39 -> -779.6 | Z39: =Y39/S39 -> -0.01613267
A40: =A39+1 -> 28 | B40: Q Comp | D40: ='FY 2003'!I36 -> 0 | E40: ='FY 2004'!I36 -> 0 | F40: =ROUND('SUMMARY-ALL YEARS'!F40/1000,1) -> 0 | G40: =ROUND('SUMMARY-ALL YEARS'!G40/1000,1) -> 0 | H40: =ROUND('SUMMARY-ALL YEARS'!H40/1000,1) -> 9695.5 | I40: =ROUND('SUMMARY-ALL YEARS'!I40/1000,1) -> 12779.7 | J40: =ROUND('SUMMARY-ALL YEARS'!J40/1000,1) -> 13353.4 | K40: =ROUND('SUMMARY-ALL YEARS'!K40/1000,1) -> 16807.1 | L40: =ROUND('SUMMARY-ALL YEARS'!L40/1000,1) -> 18158 | M40: =ROUND('SUMMARY-ALL YEARS'!M40/1000,1) -> 22046.3 | ... P40: =ROUND('SUMMARY-ALL YEARS'!P40/1000,1) -> 22847.5 | Q40: =SUM(I40:J40) -> 26133.1 | R40: =SUM(K40:L40) -> 34965.1 | S40: =SUM(M40:N40) -> 43859.8 | T40: =SUM(O40:P40) -> 45118.2 | U40: =R40-Q40 -> 8832 | V40: =U40/Q40 -> 0.3379622 | W40: =S40-R40 -> 8894.7 | X40: =W40/R40 -> 0.25438795 | Y40: =T40-S40 -> 1258.4 | Z40: =Y40/S40 -> 0.028691421
A41: =A40+1 -> 29 | B41: Referendum Levy | D41: ='FY 2003'!I37 -> 224945858 | E41: ='FY 2004'!I37 -> 351087875 | F41: =ROUND('SUMMARY-ALL YEARS'!F41/1000,1) -> 379954.5 | G41: =ROUND('SUMMARY-ALL YEARS'!G41/1000,1) -> 410867.9 | H41: =ROUND('SUMMARY-ALL YEARS'!H41/1000,1) -> 482421.7 | I41: =ROUND('SUMMARY-ALL YEARS'!I41/1000,1) -> 540184.3 | J41: =ROUND('SUMMARY-ALL YEARS'!J41/1000,1) -> 635333.5 | K41: =ROUND('SUMMARY-ALL YEARS'!K41/1000,1) -> 712334.2 | L41: =ROUND('SUMMARY-ALL YEARS'!L41/1000,1) -> 737629.4 | M41: =ROUND('SUMMARY-ALL YEARS'!M41/1000,1) -> 745650.7 | ... P41: =ROUND('SUMMARY-ALL YEARS'!P41/1000,1) -> 914688.8 | Q41: =SUM(I41:J41) -> 1175517.8 | R41: =SUM(K41:L41) -> 1449963.6 | S41: =SUM(M41:N41) -> 1547356.9 | T41: =SUM(O41:P41) -> 1762118.5 | U41: =R41-Q41 -> 274445.8 | V41: =U41/Q41 -> 0.23346801 | W41: =S41-R41 -> 97393.3 | X41: =W41/R41 -> 0.067169479 | Y41: =T41-S41 -> 214761.6 | Z41: =Y41/S41 -> 0.13879254
A43: =A41+1 -> 30 | B43: TOTAL LEVY | D43: =SUM(D37:D41) -> 224945858 | E43: =SUM(E37:E41) -> 351087875 | F43: =SUM(F37:F41) -> 460882.7 | G43: =SUM(G37:G41) -> 500602.9 | H43: =SUM(H37:H41) -> 679622.3 | I43: =SUM(I37:I41) -> 758409.1 | J43: =SUM(J37:J41) -> 867934.4 | K43: =SUM(K37:K41) -> 954412.1 | ... P43: =SUM(P37:P41) -> 1151026.6 | Q43: =SUM(I43:J43) -> 1626343.5 | R43: =SUM(K43:L43) -> 1936373.3 | S43: =SUM(M43:N43) -> 2022000.1 | T43: =SUM(O43:P43) -> 2231901.2 | U43: =R43-Q43 -> 310029.8 | V43: =U43/Q43 -> 0.19062996 | W43: =S43-R43 -> 85626.8 | X43: =W43/R43 -> 0.044220192 | Y43: =T43-S43 -> 209901.1 | Z43: =Y43/S43 -> 0.10380865
B45: AID ENTITLEMENTS
A46: =A43+1 -> 31 | B46: Basic | D46: =D8 -> 4490060320 | E46: =E8 -> 4403575277 | F46: =F8 -> 4384973.8 | G46: =G8 -> 4558383.7 | H46: =H8 -> 4741676.9 | I46: =I8 -> 4837724.5 | J46: =J8 -> 4860574.7 | K46: =K8 -> 4853494.9 | ... P46: =P8 -> 5017805.4 | Q46: =SUM(I46:J46) -> 9698299.2 | R46: =SUM(K46:L46) -> 9711543 | S46: =SUM(M46:N46) -> 9792597.4 | T46: =SUM(O46:P46) -> 9985004.5 | U46: =R46-Q46 -> 13243.8 | V46: =U46/Q46 -> 0.0013655796 | W46: =S46-R46 -> 81054.4 | X46: =W46/R46 -> 0.0083461917 | Y46: =T46-S46 -> 192407.1 | Z46: =Y46/S46 -> 0.019648219
A47: =A46+1 -> 32 | B47: Additional $51 | G47: =G9 -> 0 | H47: =H9 -> 0 | I47: =I9 -> 0 | J47: =J9 -> 48378.1 | K47: =K9 -> 0 | L47: =L9 -> 0 | M47: =M9 -> 0 | N47: =N9 -> 0 | ... P47: =P9 -> 0 | Q47: =SUM(I47:J47) -> 48378.1 | R47: =SUM(K47:L47) -> 0 | S47: =SUM(M47:N47) -> 0 | T47: =SUM(O47:P47) -> 0 | U47: =R47-Q47 -> -48378.1 | V47: =U47/Q47 -> -1 | W47: =S47-R47 -> 0 | X47: =W47/R47 -> #DIV/0! | Y47: =T47-S47 -> 0 | Z47: =Y47/S47 -> #DIV/0!
A48: =A47+1 -> 33 | B48: Gifted & Talented | D48: =D10 -> 0 | E48: =E10 -> 0 | F48: =F10 -> 0 | G48: =G10 -> 3812.2 | H48: =H10 -> 8579.6 | I48: =I10 -> 11441.2 | J48: =J10 -> 11383.1 | K48: =K10 -> 11365.9 | ... P48: =P10 -> 11751.3 | Q48: =SUM(I48:J48) -> 22824.3 | R48: =SUM(K48:L48) -> 22743.1 | S48: =SUM(M48:N48) -> 22933.4 | T48: =SUM(O48:P48) -> 23384.1 | U48: =R48-Q48 -> -81.2 | V48: =U48/Q48 -> -0.0035576118 | W48: =S48-R48 -> 190.3 | X48: =W48/R48 -> 0.008367373 | Y48: =T48-S48 -> 450.7 | Z48: =Y48/S48 -> 0.019652559
A49: =A48+1 -> 34 | B49: Extended time | D49: =D11 -> 0 | E49: =E11 -> 50351550 | F49: =F11 -> 52327.4 | G49: =G11 -> 52766.2 | H49: =H11 -> 55437 | I49: =I11 -> 59590.8 | J49: =J11 -> 60995.6 | K49: =K11 -> 64565.4 | ... P49: =P11 -> 84903.3 | Q49: =SUM(I49:J49) -> 120586.4 | R49: =SUM(K49:L49) -> 133638.4 | S49: =SUM(M49:N49) -> 147844.7 | T49: =SUM(O49:P49) -> 165344.6 | U49: =R49-Q49 -> 13052 | V49: =U49/Q49 -> 0.10823774 | W49: =S49-R49 -> 14206.3 | X49: =W49/R49 -> 0.10630403 | Y49: =T49-S49 -> 17499.9 | Z49: =Y49/S49 -> 0.11836677
B50: Basic Skills:
A51: =A49+1 -> 35 | C51: Compensatory | D51: =D13 -> 262694686 | E51: =E13 -> 249146954 | F51: =F13 -> 265074.5 | G51: =G13 -> 292547.5 | H51: =H13 -> 315471.9 | I51: =I13 -> 333928.1 | J51: =J13 -> 348510.7 | K51: =K13 -> 361157.3 | ... P51: =P13 -> 495561.1 | Q51: =SUM(I51:J51) -> 682438.8 | R51: =SUM(K51:L51) -> 775417.7 | S51: =SUM(M51:N51) -> 885520.4 | T51: =SUM(O51:P51) -> 969182.1 | U51: =R51-Q51 -> 92978.9 | V51: =U51/Q51 -> 0.13624504 | W51: =S51-R51 -> 110102.7 | X51: =W51/R51 -> 0.14199147 | Y51: =T51-S51 -> 83661.7 | Z51: =Y51/S51 -> 0.094477439
A52: =A51+1 -> 36 | C52: LEP | D52: =D14 -> 36857227 | E52: =E14 -> 28818713 | F52: =F14 -> 29477.7 | G52: =G14 -> 30912.7 | H52: =H14 -> 31474.3 | I52: =I14 -> 32316.8 | J52: =J14 -> 32058.2 | K52: =K14 -> 31807.9 | ... P52: =P14 -> 32480 | Q52: =SUM(I52:J52) -> 64375 | R52: =SUM(K52:L52) -> 63481 | S52: =SUM(M52:N52) -> 63576.9 | T52: =SUM(O52:P52) -> 64659.4 | U52: =R52-Q52 -> -894 | V52: =U52/Q52 -> -0.013887379 | W52: =S52-R52 -> 95.9 | X52: =W52/R52 -> 0.0015106882 | Y52: =T52-S52 -> 1082.5 | Z52: =Y52/S52 -> 0.017026624
A53: =A52+1 -> 37 | C53: LEP Concentration | D53: =D15 -> 9779108 | E53: =E15 -> 7276758 | F53: =F15 -> 7434.3 | G53: =G15 -> 7883.2 | H53: =H15 -> 8057.6 | I53: =I15 -> 8306.5 | J53: =J15 -> 8316.8 | K53: =K15 -> 8258.3 | ... P53: =P15 -> 8651.7 | Q53: =SUM(I53:J53) -> 16623.3 | R53: =SUM(K53:L53) -> 16645.8 | S53: =SUM(M53:N53) -> 16907 | T53: =SUM(O53:P53) -> 17231.1 | U53: =R53-Q53 -> 22.5 | V53: =U53/Q53 -> 0.0013535219 | W53: =S53-R53 -> 261.2 | X53: =W53/R53 -> 0.015691646 | Y53: =T53-S53 -> 324.1 | Z53: =Y53/S53 -> 0.019169575
A54: =A53+1 -> 38 | B54: Sparsity | D54: =D16 -> 16471551 | E54: =E16 -> 16909578 | F54: =F16 -> 17548.6 | G54: =G16 -> 18853.1 | H54: =H16 -> 20254.2 | I54: =I16 -> 21637.5 | J54: =J16 -> 22898.8 | K54: =K16 -> 23368.6 | ... P54: =P16 -> 25012.3 | Q54: =SUM(I54:J54) -> 44536.3 | R54: =SUM(K54:L54) -> 46879.8 | S54: =SUM(M54:N54) -> 48495.5 | T54: =SUM(O54:P54) -> 49649.4 | U54: =R54-Q54 -> 2343.5 | V54: =U54/Q54 -> 0.052619998 | W54: =S54-R54 -> 1615.7 | X54: =W54/R54 -> 0.034464737 | Y54: =T54-S54 -> 1153.9 | Z54: =Y54/S54 -> 0.02379396
A55: =A54+1 -> 39 | B55: Transport Sparsity | D55: =D17 -> 56478364 | E55: =E17 -> 55913098 | F55: =F17 -> 55511.2 | G55: =G17 -> 57332.8 | H55: =H17 -> 59221.8 | I55: =I17 -> 60083.8 | J55: =J17 -> 60159.1 | K55: =K17 -> 59833.2 | ... P55: =P17 -> 59683.8 | Q55: =SUM(I55:J55) -> 120242.9 | R55: =SUM(K55:L55) -> 120204.7 | S55: =SUM(M55:N55) -> 120258.8 | T55: =SUM(O55:P55) -> 119493.7 | U55: =R55-Q55 -> -38.2 | V55: =U55/Q55 -> -0.00031769028 | W55: =S55-R55 -> 54.1 | X55: =W55/R55 -> 0.0004500656 | Y55: =T55-S55 -> -765.1 | Z55: =Y55/S55 -> -0.0063621124
A56: =A55+1 -> 40 | B56: Training & Experience | D56: =D18 -> 25114308 | E56: =E18 -> 18869558 | F56: =F18 -> 12876.8 | G56: =G18 -> 8213.5 | H56: =H18 -> 4354.4 | I56: =I18 -> 2146.1 | J56: =J18 -> 1207.4 | K56: =K18 -> 675.9 | ... P56: =P18 -> 104.2 | Q56: =SUM(I56:J56) -> 3353.5 | R56: =SUM(K56:L56) -> 1049.1 | S56: =SUM(M56:N56) -> 382.1 | T56: =SUM(O56:P56) -> 233 | U56: =R56-Q56 -> -2304.4 | V56: =U56/Q56 -> -0.68716267 | W56: =S56-R56 -> -667 | X56: =W56/R56 -> -0.63578305 | Y56: =T56-S56 -> -149.1 | Z56: =Y56/S56 -> -0.39021199
A57: =A56+1 -> 41 | B57: Late Contract Penalty | D57: =D19 -> 0 | E57: =E19 -> 0 | F57: =F19 -> 0 | G57: =G19 -> -344.9 | H57: =H19 -> 0 | I57: =I19 -> -730.5 | J57: =J19 -> 0 | K57: =K19 -> -2507.1 | ... P57: =P19 -> 0 | Q57: =SUM(I57:J57) -> -730.5 | R57: =SUM(K57:L57) -> -2507.1 | S57: =SUM(M57:N57) -> -700 | T57: =SUM(O57:P57) -> -700 | U57: =R57-Q57 -> -1776.6 | V57: =U57/Q57 -> 2.4320329 | W57: =S57-R57 -> 1807.1 | X57: =W57/R57 -> -0.72079295 | Y57: =T57-S57 -> 0 | Z57: =Y57/S57 -> 0
A58: =A57+1 -> 42 | B58: One-time Reduction | H58: 0 | I58: 0 | J58: 0 | K58: =K20 -> -500000 | L58: 0 | M58: 0 | N58: 0 | O58: 0 | P58: 0 | Q58: =SUM(I58:J58) -> 0 | R58: =SUM(K58:L58) -> -500000 | S58: =SUM(M58:N58) -> 0 | T58: =SUM(O58:P58) -> 0 | U58: =R58-Q58 -> -500000 | V58: =U58/Q58 -> #DIV/0! | W58: =S58-R58 -> 500000 | X58: =W58/R58 -> -1 | Y58: =T58-S58 -> 0 | Z58: =Y58/S58 -> #DIV/0!
A59: =A58+1 -> 43 | B59: Operating Capital | D59: =D21-D37 -> 198438434 | E59: =E21-E37 -> 194217096 | F59: =F21-F37 -> 153689.8 | G59: =G21-G37 -> 149750.2 | H59: =H21-H37 -> 92182.5 | I59: =I21-I37 -> 82805.2 | J59: =J21-J37 -> 73046.1 | K59: =K21-K37 -> 70133.2 | ... P59: =P21-P37 -> 86579 | Q59: =SUM(I59:J59) -> 155851.3 | R59: =SUM(K59:L59) -> 140121.5 | S59: =SUM(M59:N59) -> 158580.9 | T59: =SUM(O59:P59) -> 172060 | U59: =R59-Q59 -> -15729.8 | V59: =U59/Q59 -> -0.10092826 | W59: =S59-R59 -> 18459.4 | X59: =W59/R59 -> 0.13173853 | Y59: =T59-S59 -> 13479.1 | Z59: =Y59/S59 -> 0.084998256
A60: =A59+1 -> 44 | B60: Equity | D60: =D22-D38 -> 34642490 | E60: =E22-E38 -> 32112369 | F60: =F22-F38 -> 19350.9 | G60: =G22-G38 -> 25916.1 | H60: =H22-H38 -> 30534 | I60: =I22-I38 -> 25104.5 | J60: =J22-J38 -> 19660.4 | K60: =K22-K38 -> 16720.1 | ... P60: =P22-P38 -> 23228.9 | Q60: =SUM(I60:J60) -> 44764.9 | R60: =SUM(K60:L60) -> 32748.7 | S60: =SUM(M60:N60) -> 38977.8 | T60: =SUM(O60:P60) -> 45519 | U60: =R60-Q60 -> -12016.2 | V60: =U60/Q60 -> -0.26842906 | W60: =S60-R60 -> 6229.1 | X60: =W60/R60 -> 0.19020908 | Y60: =T60-S60 -> 6541.2 | Z60: =Y60/S60 -> 0.1678186
A61: =A60+1 -> 45 | B61: Transition | D61: =D23-D39 -> 0 | E61: =E23-E39 -> 31986524 | F61: =F23-F39 -> 12786 | G61: =G23-G39 -> 10650.2 | H61: =H23-H39 -> 8632 | I61: =I23-I39 -> 7132.9 | J61: =J23-J39 -> 5419.1 | K61: =K23-K39 -> 4257.6 | ... P61: =P23-P39 -> 6062.8 | Q61: =SUM(I61:J61) -> 12552 | R61: =SUM(K61:L61) -> 8228.5 | S61: =SUM(M61:N61) -> 10072 | T61: =SUM(O61:P61) -> 11953.5 | U61: =R61-Q61 -> -4323.5 | V61: =U61/Q61 -> -0.3444471 | W61: =S61-R61 -> 1843.5 | X61: =W61/R61 -> 0.2240384 | Y61: =T61-S61 -> 1881.5 | Z61: =Y61/S61 -> 0.186805
A62: =A61+1 -> 46 | B62: Q Comp | D62: =D24-D40 -> 0 | E62: =E24-E40 -> 0 | F62: =F24-F40 -> 0 | G62: =G24-G40 -> 16348.9 | H62: =H24-H40 -> 38908.2 | I62: =I24-I40 -> 47983.9 | J62: =J24-J40 -> 49995 | K62: =K24-K40 -> 41484.4 | ... P62: =P24-P40 -> 63168.8 | Q62: =SUM(I62:J62) -> 97978.9 | R62: =SUM(K62:L62) -> 86383.3 | S62: =SUM(M62:N62) -> 117079.9 | T62: =SUM(O62:P62) -> 124874.8 | U62: =R62-Q62 -> -11595.6 | V62: =U62/Q62 -> -0.11834793 | W62: =S62-R62 -> 30696.6 | X62: =W62/R62 -> 0.35535341 | Y62: =T62-S62 -> 7794.9 | Z62: =Y62/S62 -> 0.066577611
A63: =A62+1 -> 47 | B63: Referendum Equalization Aid | D63: =D25-D41-D64 -> 58417206 | E63: =E25-E41-E64 -> 67208298 | F63: =F25-F41-F64 -> 116067.7 | G63: =G25-G41-G64 -> 114774 | H63: =H25-H41-H64 -> 107935.2 | I63: =I25-I41-I64 -> 95398.6 | J63: =J25-J41-J64 -> 76645.9 | K63: =K25-K41-K64 -> 60722.2 | ... P63: =P25-P41-P64 -> 93082 | Q63: =SUM(I63:J63) -> 172044.5 | R63: =SUM(K63:L63) -> 119331.9 | S63: =SUM(M63:N63) -> 153328.9 | T63: =SUM(O63:P63) -> 183020.8 | U63: =R63-Q63 -> -52712.6 | V63: =U63/Q63 -> -0.30638934 | W63: =S63-R63 -> 33997 | X63: =W63/R63 -> 0.28489448 | Y63: =T63-S63 -> 29691.9 | Z63: =Y63/S63 -> 0.19364843
A64: =A63+1 -> 48 | B64: Tax Base Replacement Aid | D64: ='FY 2003'!I58 -> 8345294 | E64: ='FY 2004'!I58 -> 8040369 | F64: =ROUND('SUMMARY-ALL YEARS'!F64/1000,1) -> 8698.9 | G64: =ROUND('SUMMARY-ALL YEARS'!G64/1000,1) -> 8672.6 | H64: =ROUND('SUMMARY-ALL YEARS'!H64/1000,1) -> 8609.3 | I64: =ROUND('SUMMARY-ALL YEARS'!I64/1000,1) -> 8609.3 | J64: =ROUND('SUMMARY-ALL YEARS'!J64/1000,1) -> 8587.8 | K64: =ROUND('SUMMARY-ALL YEARS'!K64/1000,1) -> 8618.7 | L64: =ROUND('SUMMARY-ALL YEARS'!L64/1000,1) -> 8593.2 | M64: =ROUND('SUMMARY-ALL YEARS'!M64/1000,1) -> 8502 | ... P64: =ROUND('SUMMARY-ALL YEARS'!P64/1000,1) -> 8522.6 | Q64: =SUM(I64:J64) -> 17197.1 | R64: =SUM(K64:L64) -> 17211.9 | S64: =SUM(M64:N64) -> 17024.6 | T64: =SUM(O64:P64) -> 17045.2 | U64: =R64-Q64 -> 14.8 | V64: =U64/Q64 -> 0.00086061022 | W64: =S64-R64 -> -187.3 | X64: =W64/R64 -> -0.010882006 | Y64: =T64-S64 -> 20.6 | Z64: =Y64/S64 -> 0.0012100137
B65: Alternative Attendance Adj:
A66: =A64+1 -> 49 | C66: All Categories | D66: ='FY 2003'!I60 -> 1341221 | E66: ='FY 2004'!I60 -> -679857 | F66: =F28 -> -1090 | G66: =G28 -> -895.4 | H66: =H28 -> -886.1 | I66: =I28 -> -182.3 | J66: =J28 -> 261.6 | K66: =K28 -> 606.9 | L66: =L28 -> 658.4 | M66: =M28 -> 338.5 | ... P66: =P28 -> -315 | Q66: =SUM(I66:J66) -> 79.3 | R66: =SUM(K66:L66) -> 1265.3 | S66: =SUM(M66:N66) -> 193.5 | T66: =SUM(O66:P66) -> -547.9 | U66: =R66-Q66 -> 1186 | V66: =U66/Q66 -> 14.955864 | W66: =S66-R66 -> -1071.8 | X66: =W66/R66 -> -0.84707184 | Y66: =T66-S66 -> -741.4 | Z66: =Y66/S66 -> -3.8315245
A67: =A66+1 -> 50 | D67: ='FY 2003'!I61 -> -1804253 | E67: ='FY 2004'!I61 -> 1059 | F67: ='FY 2005'!I61 -> 0 | G67: ='FY 2005'!J61 -> 0 | H67: ='FY 2005'!K61 -> 0 | I67: ='FY 2005'!L61 -> 0 | J67: ='FY 2005'!M61 -> 0 | K67: ='FY 2005'!N61 -> 0 | L67: ='FY 2005'!O61 -> 0 | M67: ='FY 2005'!P61 -> 0 | ... P67: ='FY 2005'!S61 -> 0
A68: =A67+1 -> 51 | D68: ='FY 2003'!I62 -> 0 | E68: ='FY 2004'!I62 -> 0 | F68: ='FY 2005'!I62 -> 0 | G68: ='FY 2005'!J62 -> 0 | H68: ='FY 2005'!K62 -> 0 | I68: ='FY 2005'!L62 -> 0 | J68: ='FY 2005'!M62 -> 0 | K68: ='FY 2005'!N62 -> 0 | L68: ='FY 2005'!O62 -> 0 | M68: ='FY 2005'!P62 -> 0 | ... P68: ='FY 2005'!S62 -> 0
A69: =A68+1 -> 52 | D69: ='FY 2003'!I63 -> 0 | E69: ='FY 2004'!I63 -> 0 | F69: ='FY 2005'!I63 -> 0 | G69: ='FY 2005'!J63 -> 0 | H69: ='FY 2005'!K63 -> 0 | I69: ='FY 2005'!L63 -> 0 | J69: ='FY 2005'!M63 -> 0 | K69: ='FY 2005'!N63 -> 0 | L69: ='FY 2005'!O63 -> 0 | M69: ='FY 2005'!P63 -> 0 | ... P69: ='FY 2005'!S63 -> 0
A70: =A69+1 -> 53 | D70: 0 | E70: 0 | F70: 0 | G70: 0 | H70: 0 | I70: 0 | J70: 0 | K70: 0 | L70: 0 | M70: 0 | N70: 0 | O70: 0 | P70: 0
A72: =A70+1 -> 54 | B72: TOTAL AID ENTITLEMENT | D72: =SUM(D46:D70) -> 5196835956 | E72: =SUM(E46:E70) -> 5163747344 | F72: =SUM(F46:F70) -> 5134727.6 | G72: =SUM(G46:G70) -> 5355576.6 | H72: =SUM(H46:H70) -> 5530442.8 | I72: =SUM(I46:I70) -> 5633296.9 | J72: =SUM(J46:J70) -> 5688098.4 | K72: =SUM(K46:K70) -> 5114563.4 | ... P72: =SUM(P46:P70) -> 6016282.2 | Q72: =SUM(I72:J72) -> 11321395 | R72: =SUM(K72:L72) -> 10794387 | S72: =SUM(M72:N72) -> 11593074 | T72: =SUM(O72:P72) -> 11947407 | U72: =R72-Q72 -> -527008.7 | V72: =U72/Q72 -> -0.046549801 | W72: =S72-R72 -> 798687.2 | X72: =W72/R72 -> 0.073990976 | Y72: =T72-S72 -> 354333.5 | Z72: =Y72/S72 -> 0.030564241
A73: =A72+1 -> 55 | B73: General Ed Entitlement (IDEAS) | D73: =D72-D64 -> 5188490662 | E73: =E72-E64 -> 5155706975 | F73: =F72-F64 -> 5126028.7 | G73: =G72-G64 -> 5346904 | H73: =H72-H64 -> 5521833.5 | I73: =I72 -> 5633296.9 | J73: =J72 -> 5688098.4 | K73: =K72 -> 5114563.4 | L73: =L72 -> 5679823.2 | M73: =M72 -> 5748498.4 | N73: =N72 -> 5844575.4 | O73: =O72 -> 5931125.1 | P73: =P72 -> 6016282.2 | Q73: =SUM(I73:J73) -> 11321395 | R73: =SUM(K73:L73) -> 10794387 | S73: =SUM(M73:N73) -> 11593074 | T73: =SUM(O73:P73) -> 11947407 | U73: =R73-Q73 -> -527008.7 | V73: =U73/Q73 -> -0.046549801 | W73: =S73-R73 -> 798687.2 | X73: =W73/R73 -> 0.073990976 | Y73: =T73-S73 -> 354333.5 | Z73: =Y73/S73 -> 0.030564241
A74: =A73+1 -> 56 | B74: Tax Base Repl Entitlemt (thru FY07) | D74: =D64 -> 8345294 | E74: =E64 -> 8040369 | F74: =F64 -> 8698.9 | G74: =G64 -> 8672.6 | H74: =H64 -> 8609.3 | I74: na | J74: na | K74: na | L74: na | M74: na | N74: na | O74: na | P74: na
A76: =A74+1 -> 57 | B76: TRA Reduction | D76: ='FY 2003'!I69 -> -46570547 | E76: ='FY 2004'!I69 -> -46686661 | F76: =ROUND('SUMMARY-ALL YEARS'!F76/1000,1) -> -46733.7 | G76: =ROUND('SUMMARY-ALL YEARS'!G76/1000,1) -> -46807.7 | H76: =ROUND('SUMMARY-ALL YEARS'!H76/1000,1) -> -46967.5 | I76: =ROUND('SUMMARY-ALL YEARS'!I76/1000,1) -> -30637.8 | J76: =ROUND('SUMMARY-ALL YEARS'!J76/1000,1) -> -30753.1 | K76: =ROUND('SUMMARY-ALL YEARS'!K76/1000,1) -> -30827.9 | L76: =ROUND('SUMMARY-ALL YEARS'!L76/1000,1) -> -30929.3 | M76: =ROUND('SUMMARY-ALL YEARS'!M76/1000,1) -> -31089.9 | ... P76: =ROUND('SUMMARY-ALL YEARS'!P76/1000,1) -> -31579.5 | Q76: =SUM(I76:J76) -> -61390.9 | R76: =SUM(K76:L76) -> -61757.2 | S76: =SUM(M76:N76) -> -62333.2 | T76: =SUM(O76:P76) -> -62984.7 | U76: =R76-Q76 -> -366.3 | V76: =U76/Q76 -> 0.0059666824 | W76: =S76-R76 -> -576 | X76: =W76/R76 -> 0.0093268477 | Y76: =T76-S76 -> -651.5 | Z76: =Y76/S76 -> 0.010451894
A78: NOVEMBER 2010 FORECAST | D78: FY 2003 | E78: FY 2004 | F78: FY 2005 | G78: FY 2006 | H78: FY 2007 | I78: FY 2008 | J78: FY 2009 | K78: FY 2010 | L78: FY 2011 | M78: FY 2012 | N78: FY 2013 | O78: FY 2014 | P78: FY 2015 | Q78: 2008-09 | R78: 2010-11 | S78: 2012-13 | T78: 2014-15 | U78: Chg from 2008-09 | V78: % chg | W78: Chg from 2010-11 | X78: % chg | Y78: Chg from 2012-13 | Z78: % chg
A80: 1 | B80: AMCPU | D80: ='FY 2003'!I73 -> 962146 | E80: ='FY 2004'!I73 -> 957096 | F80: ='FY 2005'!I73 -> 953035 | G80: ='FY 2006'!I75 -> 953041 | H80: ='FY 2007'!I75 -> 953288 | I80: ='FY 2008'!I75 -> 953432 | J80: ='FY 2009'!$I77 -> 948587 | K80: ='FY 2010'!$J77 -> 947786 | L80: ='FY 2011'!$J75 -> 949439 | M80: ='FY 2012'!$J75 -> 953192 | N80: ='FY 2013'!$J75 -> 961193 | O80: ='FY 2014'!$J75 -> 971195 | P80: ='FY 2015'!$J75 -> 982011
B82: REVENUES
A83: =A80+1 -> 2 | B83: Basic | D83: ='FY 2003'!I76 -> 4490060320 | E83: ='FY 2004'!I76 -> 4403575277 | F83: =ROUND('SUMMARY-ALL YEARS'!F83/1000,1) -> 4384973.8 | G83: =ROUND('SUMMARY-ALL YEARS'!G83/1000,1) -> 4558383.7 | H83: =ROUND('SUMMARY-ALL YEARS'!H83/1000,1) -> 4741676.9 | I83: =ROUND('SUMMARY-ALL YEARS'!I83/1000,1) -> 4837724.5 | J83: =ROUND('SUMMARY-ALL YEARS'!J83/1000,1) -> 4860574.7 | K83: =ROUND('SUMMARY-ALL YEARS'!K83/1000,1) -> 4857032 | L83: =ROUND('SUMMARY-ALL YEARS'!L83/1000,1) -> 4864927 | M83: =ROUND('SUMMARY-ALL YEARS'!M83/1000,1) -> 4884153.7 | ... P83: =ROUND('SUMMARY-ALL YEARS'!P83/1000,1) -> 5031822.4 | Q83: =SUM(I83:J83) -> 9698299.2 | R83: =SUM(K83:L83) -> 9721959 | S83: =SUM(M83:N83) -> 9809307.7 | T83: =SUM(O83:P83) -> 10008224 | U83: =R83-Q83 -> 23659.8 | V83: =U83/Q83 -> 0.0024395824 | W83: =S83-R83 -> 87348.7 | X83: =W83/R83 -> 0.008984681 | Y83: =T83-S83 -> 198916.5 | Z83: =Y83/S83 -> 0.020278342
A84: =A83+1 -> 3 | B84: Additional $51 | G84: =ROUND('SUMMARY-ALL YEARS'!G84/1000,1) -> 0 | H84: =ROUND('SUMMARY-ALL YEARS'!H84/1000,1) -> 0 | I84: =ROUND('SUMMARY-ALL YEARS'!I84/1000,1) -> 0 | J84: =ROUND('SUMMARY-ALL YEARS'!J84/1000,1) -> 48378.1 | K84: =ROUND('SUMMARY-ALL YEARS'!K84/1000,1) -> 0 | L84: =ROUND('SUMMARY-ALL YEARS'!L84/1000,1) -> 0 | M84: =ROUND('SUMMARY-ALL YEARS'!M84/1000,1) -> 0 | N84: =ROUND('SUMMARY-ALL YEARS'!N84/1000,1) -> 0 | ... P84: =ROUND('SUMMARY-ALL YEARS'!P84/1000,1) -> 0 | Q84: =SUM(I84:J84) -> 48378.1 | R84: =SUM(K84:L84) -> 0 | S84: =SUM(M84:N84) -> 0 | T84: =SUM(O84:P84) -> 0 | U84: =R84-Q84 -> -48378.1 | V84: =U84/Q84 -> -1 | W84: =S84-R84 -> 0 | X84: =W84/R84 -> #DIV/0! | Y84: =T84-S84 -> 0 | Z84: =Y84/S84 -> #DIV/0!
A85: =A84+1 -> 4 | B85: Gifted & Talented | D85: ='FY 2003'!I77 -> 0 | E85: ='FY 2004'!I77 -> 0 | F85: =ROUND('SUMMARY-ALL YEARS'!F85/1000,1) -> 0 | G85: =ROUND('SUMMARY-ALL YEARS'!G85/1000,1) -> 3812.2 | H85: =ROUND('SUMMARY-ALL YEARS'!H85/1000,1) -> 8579.6 | I85: =ROUND('SUMMARY-ALL YEARS'!I85/1000,1) -> 11441.2 | J85: =ROUND('SUMMARY-ALL YEARS'!J85/1000,1) -> 11383.1 | K85: =ROUND('SUMMARY-ALL YEARS'!K85/1000,1) -> 11374.8 | L85: =ROUND('SUMMARY-ALL YEARS'!L85/1000,1) -> 11393.3 | M85: =ROUND('SUMMARY-ALL YEARS'!M85/1000,1) -> 11438.3 | ... P85: =ROUND('SUMMARY-ALL YEARS'!P85/1000,1) -> 11784.1 | Q85: =SUM(I85:J85) -> 22824.3 | R85: =SUM(K85:L85) -> 22768.1 | S85: =SUM(M85:N85) -> 22972.6 | T85: =SUM(O85:P85) -> 23438.4 | U85: =R85-Q85 -> -56.2 | V85: =U85/Q85 -> -0.002462288 | W85: =S85-R85 -> 204.5 | X85: =W85/R85 -> 0.008981865 | Y85: =T85-S85 -> 465.8 | Z85: =Y85/S85 -> 0.020276329
A86: =A85+1 -> 5 | B86: Extended time | D86: ='FY 2003'!I78 -> 0 | E86: ='FY 2004'!I78 -> 50351550 | F86: =ROUND('SUMMARY-ALL YEARS'!F86/1000,1) -> 52327.4 | G86: =ROUND('SUMMARY-ALL YEARS'!G86/1000,1) -> 52766.2 | H86: =ROUND('SUMMARY-ALL YEARS'!H86/1000,1) -> 55437 | I86: =ROUND('SUMMARY-ALL YEARS'!I86/1000,1) -> 59590.8 | J86: =ROUND('SUMMARY-ALL YEARS'!J86/1000,1) -> 60995.6 | K86: =ROUND('SUMMARY-ALL YEARS'!K86/1000,1) -> 64755 | L86: =ROUND('SUMMARY-ALL YEARS'!L86/1000,1) -> 69226.3 | M86: =ROUND('SUMMARY-ALL YEARS'!M86/1000,1) -> 71911.1 | ... P86: =ROUND('SUMMARY-ALL YEARS'!P86/1000,1) -> 85121.5 | Q86: =SUM(I86:J86) -> 120586.4 | R86: =SUM(K86:L86) -> 133981.3 | S86: =SUM(M86:N86) -> 148112.1 | T86: =SUM(O86:P86) -> 165696.3 | U86: =R86-Q86 -> 13394.9 | V86: =U86/Q86 -> 0.11108135 | W86: =S86-R86 -> 14130.8 | X86: =W86/R86 -> 0.10546845 | Y86: =T86-S86 -> 17584.2 | Z86: =Y86/S86 -> 0.11872224
B87: Basic Skills:
A88: =A86+1 -> 6 | C88: Compensatory | D88: ='FY 2003'!I80 -> 262694686 | E88: ='FY 2004'!I80 -> 249146954 | F88: =ROUND('SUMMARY-ALL YEARS'!F88/1000,1) -> 265074.5 | G88: =ROUND('SUMMARY-ALL YEARS'!G88/1000,1) -> 292547.5 | H88: =ROUND('SUMMARY-ALL YEARS'!H88/1000,1) -> 315471.9 | I88: =ROUND('SUMMARY-ALL YEARS'!I88/1000,1) -> 333928.1 | J88: =ROUND('SUMMARY-ALL YEARS'!J88/1000,1) -> 348510.7 | K88: =ROUND('SUMMARY-ALL YEARS'!K88/1000,1) -> 361172.1 | L88: =ROUND('SUMMARY-ALL YEARS'!L88/1000,1) -> 414257.7 | M88: =ROUND('SUMMARY-ALL YEARS'!M88/1000,1) -> 437710.6 | ... P88: =ROUND('SUMMARY-ALL YEARS'!P88/1000,1) -> 500648.4 | Q88: =SUM(I88:J88) -> 682438.8 | R88: =SUM(K88:L88) -> 775429.8 | S88: =SUM(M88:N88) -> 894725.4 | T88: =SUM(O88:P88) -> 979060.8 | U88: =R88-Q88 -> 92991 | V88: =U88/Q88 -> 0.13626277 | W88: =S88-R88 -> 119295.6 | X88: =W88/R88 -> 0.15384449 | Y88: =T88-S88 -> 84335.4 | Z88: =Y88/S88 -> 0.094258417
A89: =A88+1 -> 7 | C89: LEP | D89: ='FY 2003'!I81 -> 36857227 | E89: ='FY 2004'!I81 -> 28818713 | F89: =ROUND('SUMMARY-ALL YEARS'!F89/1000,1) -> 29477.7 | G89: =ROUND('SUMMARY-ALL YEARS'!G89/1000,1) -> 30912.7 | H89: =ROUND('SUMMARY-ALL YEARS'!H89/1000,1) -> 31474.3 | I89: =ROUND('SUMMARY-ALL YEARS'!I89/1000,1) -> 32316.8 | J89: =ROUND('SUMMARY-ALL YEARS'!J89/1000,1) -> 32058.2 | K89: =ROUND('SUMMARY-ALL YEARS'!K89/1000,1) -> 31812.4 | L89: =ROUND('SUMMARY-ALL YEARS'!L89/1000,1) -> 31727.8 | M89: =ROUND('SUMMARY-ALL YEARS'!M89/1000,1) -> 31763.6 | ... P89: =ROUND('SUMMARY-ALL YEARS'!P89/1000,1) -> 32595.2 | Q89: =SUM(I89:J89) -> 64375 | R89: =SUM(K89:L89) -> 63540.2 | S89: =SUM(M89:N89) -> 63686.1 | T89: =SUM(O89:P89) -> 64831.1 | U89: =R89-Q89 -> -834.8 | V89: =U89/Q89 -> -0.012967767 | W89: =S89-R89 -> 145.9 | X89: =W89/R89 -> 0.0022961841 | Y89: =T89-S89 -> 1145 | Z89: =Y89/S89 -> 0.017978805
A90: =A89+1 -> 8 | C90: LEP Concentration | D90: ='FY 2003'!I82 -> 9779108 | E90: ='FY 2004'!I82 -> 7276758 | F90: =ROUND('SUMMARY-ALL YEARS'!F90/1000,1) -> 7434.3 | G90: =ROUND('SUMMARY-ALL YEARS'!G90/1000,1) -> 7883.2 | H90: =ROUND('SUMMARY-ALL YEARS'!H90/1000,1) -> 8057.6 | I90: =ROUND('SUMMARY-ALL YEARS'!I90/1000,1) -> 8306.5 | J90: =ROUND('SUMMARY-ALL YEARS'!J90/1000,1) -> 8316.8 | K90: =ROUND('SUMMARY-ALL YEARS'!K90/1000,1) -> 8256.6 | L90: =ROUND('SUMMARY-ALL YEARS'!L90/1000,1) -> 8398.5 | M90: =ROUND('SUMMARY-ALL YEARS'!M90/1000,1) -> 8421 | ... P90: =ROUND('SUMMARY-ALL YEARS'!P90/1000,1) -> 8699.5 | Q90: =SUM(I90:J90) -> 16623.3 | R90: =SUM(K90:L90) -> 16655.1 | S90: =SUM(M90:N90) -> 16941.1 | T90: =SUM(O90:P90) -> 17304.9 | U90: =R90-Q90 -> 31.8 | V90: =U90/Q90 -> 0.0019129776 | W90: =S90-R90 -> 286 | X90: =W90/R90 -> 0.017171917 | Y90: =T90-S90 -> 363.8 | Z90: =Y90/S90 -> 0.021474402
A91: =A90+1 -> 9 | B91: Sparsity | D91: ='FY 2003'!I83 -> 16471551 | E91: ='FY 2004'!I83 -> 16909578 | F91: =ROUND('SUMMARY-ALL YEARS'!F91/1000,1) -> 17548.6 | G91: =ROUND('SUMMARY-ALL YEARS'!G91/1000,1) -> 18853.1 | H91: =ROUND('SUMMARY-ALL YEARS'!H91/1000,1) -> 20254.2 | I91: =ROUND('SUMMARY-ALL YEARS'!I91/1000,1) -> 21637.5 | J91: =ROUND('SUMMARY-ALL YEARS'!J91/1000,1) -> 22898.8 | K91: =ROUND('SUMMARY-ALL YEARS'!K91/1000,1) -> 23367.8 | L91: =ROUND('SUMMARY-ALL YEARS'!L91/1000,1) -> 23450.3 | M91: =ROUND('SUMMARY-ALL YEARS'!M91/1000,1) -> 24120.2 | ... P91: =ROUND('SUMMARY-ALL YEARS'!P91/1000,1) -> 25112.2 | Q91: =SUM(I91:J91) -> 44536.3 | R91: =SUM(K91:L91) -> 46818.1 | S91: =SUM(M91:N91) -> 48485.2 | T91: =SUM(O91:P91) -> 49830.3 | U91: =R91-Q91 -> 2281.8 | V91: =U91/Q91 -> 0.051234611 | W91: =S91-R91 -> 1667.1 | X91: =W91/R91 -> 0.035608023 | Y91: =T91-S91 -> 1345.1 | Z91: =Y91/S91 -> 0.027742486
A92: =A91+1 -> 10 | B92: Transport Sparsity | D92: ='FY 2003'!I84 -> 56478364 | E92: ='FY 2004'!I84 -> 55913098 | F92: =ROUND('SUMMARY-ALL YEARS'!F92/1000,1) -> 55511.2 | G92: =ROUND('SUMMARY-ALL YEARS'!G92/1000,1) -> 57332.8 | H92: =ROUND('SUMMARY-ALL YEARS'!H92/1000,1) -> 59221.8 | I92: =ROUND('SUMMARY-ALL YEARS'!I92/1000,1) -> 60083.8 | J92: =ROUND('SUMMARY-ALL YEARS'!J92/1000,1) -> 60159.1 | K92: =ROUND('SUMMARY-ALL YEARS'!K92/1000,1) -> 59886.7 | L92: =ROUND('SUMMARY-ALL YEARS'!L92/1000,1) -> 60310.6 | M92: =ROUND('SUMMARY-ALL YEARS'!M92/1000,1) -> 60119.9 | ... P92: =ROUND('SUMMARY-ALL YEARS'!P92/1000,1) -> 54382.3 | Q92: =SUM(I92:J92) -> 120242.9 | R92: =SUM(K92:L92) -> 120197.3 | S92: =SUM(M92:N92) -> 119999.8 | T92: =SUM(O92:P92) -> 108927.5 | U92: =R92-Q92 -> -45.6 | V92: =U92/Q92 -> -0.00037923237 | W92: =S92-R92 -> -197.5 | X92: =W92/R92 -> -0.0016431318 | Y92: =T92-S92 -> -11072.3 | Z92: =Y92/S92 -> -0.09226932
A93: =A92+1 -> 11 | B93: Training & Experience | D93: ='FY 2003'!I85 -> 25114308 | E93: ='FY 2004'!I85 -> 18869558 | F93: =ROUND('SUMMARY-ALL YEARS'!F93/1000,1) -> 12876.8 | G93: =ROUND('SUMMARY-ALL YEARS'!G93/1000,1) -> 8213.5 | H93: =ROUND('SUMMARY-ALL YEARS'!H93/1000,1) -> 4354.4 | I93: =ROUND('SUMMARY-ALL YEARS'!I93/1000,1) -> 2146.1 | J93: =ROUND('SUMMARY-ALL YEARS'!J93/1000,1) -> 1207.4 | K93: =ROUND('SUMMARY-ALL YEARS'!K93/1000,1) -> 676.1 | L93: =ROUND('SUMMARY-ALL YEARS'!L93/1000,1) -> 372.4 | M93: =ROUND('SUMMARY-ALL YEARS'!M93/1000,1) -> 221.7 | ... P93: =ROUND('SUMMARY-ALL YEARS'!P93/1000,1) -> 102.8 | Q93: =SUM(I93:J93) -> 3353.5 | R93: =SUM(K93:L93) -> 1048.5 | S93: =SUM(M93:N93) -> 379.1 | T93: =SUM(O93:P93) -> 230 | U93: =R93-Q93 -> -2305 | V93: =U93/Q93 -> -0.68734158 | W93: =S93-R93 -> -669.4 | X93: =W93/R93 -> -0.63843586 | Y93: =T93-S93 -> -149.1 | Z93: =Y93/S93 -> -0.39329992
A94: =A93+1 -> 12 | B94: Late Contract Penalty | D94: ='FY 2003'!I86 -> 0 | E94: ='FY 2004'!I86 -> 0 | F94: =ROUND('SUMMARY-ALL YEARS'!F94/1000,1) -> 0 | G94: =ROUND('SUMMARY-ALL YEARS'!G94/1000,1) -> -344.9 | H94: =ROUND('SUMMARY-ALL YEARS'!H94/1000,1) -> 0 | I94: =ROUND('SUMMARY-ALL YEARS'!I94/1000,1) -> -730.5 | J94: =ROUND('SUMMARY-ALL YEARS'!J94/1000,1) -> 0 | K94: =ROUND('SUMMARY-ALL YEARS'!K94/1000,1) -> -2505.7 | L94: =ROUND('SUMMARY-ALL YEARS'!L94/1000,1) -> 0 | M94: =ROUND('SUMMARY-ALL YEARS'!M94/1000,1) -> -700 | ... P94: =ROUND('SUMMARY-ALL YEARS'!P94/1000,1) -> 0 | Q94: =SUM(I94:J94) -> -730.5 | R94: =SUM(K94:L94) -> -2505.7 | S94: =SUM(M94:N94) -> -700 | T94: =SUM(O94:P94) -> -700 | U94: =R94-Q94 -> -1775.2 | V94: =U94/Q94 -> 2.4301164 | W94: =S94-R94 -> 1805.7 | X94: =W94/R94 -> -0.72063695 | Y94: =T94-S94 -> 0 | Z94: =Y94/S94 -> 0
A95: =A94+1 -> 13 | B95: One-time Reduction | H95: 0 | I95: 0 | J95: 0 | K95: =ROUND('SUMMARY-ALL YEARS'!K95/1000,1) -> -500000 | L95: 0 | M95: 0 | N95: 0 | O95: 0 | P95: 0 | Q95: =SUM(I95:J95) -> 0 | R95: =SUM(K95:L95) -> -500000 | S95: =SUM(M95:N95) -> 0 | T95: =SUM(O95:P95) -> 0 | U95: =R95-Q95 -> -500000 | V95: =U95/Q95 -> #DIV/0! | W95: =S95-R95 -> 500000 | X95: =W95/R95 -> -1 | Y95: =T95-S95 -> 0 | Z95: =Y95/S95 -> #DIV/0!
A96: =A95+1 -> 14 | B96: Operating Capital | D96: ='FY 2003'!I87 -> 198438434 | E96: ='FY 2004'!I87 -> 194217096 | F96: =ROUND('SUMMARY-ALL YEARS'!F96/1000,1) -> 193697.1 | G96: =ROUND('SUMMARY-ALL YEARS'!G96/1000,1) -> 194018.4 | H96: =ROUND('SUMMARY-ALL YEARS'!H96/1000,1) -> 194117 | I96: =ROUND('SUMMARY-ALL YEARS'!I96/1000,1) -> 194635.6 | J96: =ROUND('SUMMARY-ALL YEARS'!J96/1000,1) -> 194299.1 | K96: =ROUND('SUMMARY-ALL YEARS'!K96/1000,1) -> 194556.9 | L96: =ROUND('SUMMARY-ALL YEARS'!L96/1000,1) -> 194883.5 | M96: =ROUND('SUMMARY-ALL YEARS'!M96/1000,1) -> 195614.7 | ... P96: =ROUND('SUMMARY-ALL YEARS'!P96/1000,1) -> 201475 | Q96: =SUM(I96:J96) -> 388934.7 | R96: =SUM(K96:L96) -> 389440.4 | S96: =SUM(M96:N96) -> 392841.2 | T96: =SUM(O96:P96) -> 400739.6 | U96: =R96-Q96 -> 505.7 | V96: =U96/Q96 -> 0.0013002183 | W96: =S96-R96 -> 3400.8 | X96: =W96/R96 -> 0.0087325301 | Y96: =T96-S96 -> 7898.4 | Z96: =Y96/S96 -> 0.020105834
A97: =A96+1 -> 15 | B97: Equity | D97: ='FY 2003'!I88 -> 34642490 | E97: ='FY 2004'!I88 -> 32112369 | F97: =ROUND('SUMMARY-ALL YEARS'!F97/1000,1) -> 41731.2 | G97: =ROUND('SUMMARY-ALL YEARS'!G97/1000,1) -> 50999.4 | H97: =ROUND('SUMMARY-ALL YEARS'!H97/1000,1) -> 94274.1 | I97: =ROUND('SUMMARY-ALL YEARS'!I97/1000,1) -> 95708.8 | J97: =ROUND('SUMMARY-ALL YEARS'!J97/1000,1) -> 93362 | K97: =ROUND('SUMMARY-ALL YEARS'!K97/1000,1) -> 92597.2 | L97: =ROUND('SUMMARY-ALL YEARS'!L97/1000,1) -> 92389.5 | M97: =ROUND('SUMMARY-ALL YEARS'!M97/1000,1) -> 94004 | ... P97: =ROUND('SUMMARY-ALL YEARS'!P97/1000,1) -> 97120.8 | Q97: =SUM(I97:J97) -> 189070.8 | R97: =SUM(K97:L97) -> 184986.7 | S97: =SUM(M97:N97) -> 188789.8 | T97: =SUM(O97:P97) -> 192545 | U97: =R97-Q97 -> -4084.1 | V97: =U97/Q97 -> -0.021600903 | W97: =S97-R97 -> 3803.1 | X97: =W97/R97 -> 0.020558775 | Y97: =T97-S97 -> 3755.2 | Z97: =Y97/S97 -> 0.019890905
A98: =A97+1 -> 16 | B98: Transition | D98: ='FY 2003'!I89 -> 0 | E98: ='FY 2004'!I89 -> 31986524 | F98: =ROUND('SUMMARY-ALL YEARS'!F98/1000,1) -> 31326.6 | G98: =ROUND('SUMMARY-ALL YEARS'!G98/1000,1) -> 31033.7 | H98: =ROUND('SUMMARY-ALL YEARS'!H98/1000,1) -> 30462.5 | I98: =ROUND('SUMMARY-ALL YEARS'!I98/1000,1) -> 30143.3 | J98: =ROUND('SUMMARY-ALL YEARS'!J98/1000,1) -> 29712 | K98: =ROUND('SUMMARY-ALL YEARS'!K98/1000,1) -> 29474.1 | L98: =ROUND('SUMMARY-ALL YEARS'!L98/1000,1) -> 29230.9 | M98: =ROUND('SUMMARY-ALL YEARS'!M98/1000,1) -> 29122.8 | ... P98: =ROUND('SUMMARY-ALL YEARS'!P98/1000,1) -> 30488.4 | Q98: =SUM(I98:J98) -> 59855.3 | R98: =SUM(K98:L98) -> 58705 | S98: =SUM(M98:N98) -> 58540.2 | T98: =SUM(O98:P98) -> 60460.3 | U98: =R98-Q98 -> -1150.3 | V98: =U98/Q98 -> -0.019218014 | W98: =S98-R98 -> -164.8 | X98: =W98/R98 -> -0.0028072566 | Y98: =T98-S98 -> 1920.1 | Z98: =Y98/S98 -> 0.032799683
A99: =A98+1 -> 17 | B99: Q Comp | D99: ='FY 2003'!I90 -> 0 | E99: ='FY 2004'!I90 -> 0 | F99: =ROUND('SUMMARY-ALL YEARS'!F99/1000,1) -> 0 | G99: =ROUND('SUMMARY-ALL YEARS'!G99/1000,1) -> 16348.9 | H99: =ROUND('SUMMARY-ALL YEARS'!H99/1000,1) -> 48603.7 | I99: =ROUND('SUMMARY-ALL YEARS'!I99/1000,1) -> 60763.6 | J99: =ROUND('SUMMARY-ALL YEARS'!J99/1000,1) -> 63348.4 | K99: =ROUND('SUMMARY-ALL YEARS'!K99/1000,1) -> 58293.2 | L99: =ROUND('SUMMARY-ALL YEARS'!L99/1000,1) -> 64869 | M99: =ROUND('SUMMARY-ALL YEARS'!M99/1000,1) -> 79865.2 | ... P99: =ROUND('SUMMARY-ALL YEARS'!P99/1000,1) -> 86326 | Q99: =SUM(I99:J99) -> 124112 | R99: =SUM(K99:L99) -> 123162.2 | S99: =SUM(M99:N99) -> 162513.2 | T99: =SUM(O99:P99) -> 170753.1 | U99: =R99-Q99 -> -949.8 | V99: =U99/Q99 -> -0.0076527652 | W99: =S99-R99 -> 39351 | X99: =W99/R99 -> 0.3195055 | Y99: =T99-S99 -> 8239.9 | Z99: =Y99/S99 -> 0.050702958
A100: =A99+1 -> 18 | B100: Referendum Revenue | D100: ='FY 2003'!I91 -> 291708358 | E100: ='FY 2004'!I91 -> 426336542 | F100: =ROUND('SUMMARY-ALL YEARS'!F100/1000,1) -> 504721.1 | G100: =ROUND('SUMMARY-ALL YEARS'!G100/1000,1) -> 534314.5 | H100: =ROUND('SUMMARY-ALL YEARS'!H100/1000,1) -> 598966.2 | I100: =ROUND('SUMMARY-ALL YEARS'!I100/1000,1) -> 644192.2 | J100: =ROUND('SUMMARY-ALL YEARS'!J100/1000,1) -> 720567.2 | K100: =ROUND('SUMMARY-ALL YEARS'!K100/1000,1) -> 782246 | L100: =ROUND('SUMMARY-ALL YEARS'!L100/1000,1) -> 805394.8 | M100: =ROUND('SUMMARY-ALL YEARS'!M100/1000,1) -> 822570.4 | ... P100: =ROUND('SUMMARY-ALL YEARS'!P100/1000,1) -> 1016465.5 | Q100: =SUM(I100:J100) -> 1364759.4 | R100: =SUM(K100:L100) -> 1587640.8 | S100: =SUM(M100:N100) -> 1717770.1 | T100: =SUM(O100:P100) -> 1962229.5 | U100: =R100-Q100 -> 222881.4 | V100: =U100/Q100 -> 0.16331186 | W100: =S100-R100 -> 130129.3 | X100: =W100/R100 -> 0.081963943 | Y100: =T100-S100 -> 244459.4 | Z100: =Y100/S100 -> 0.14231206
B101: Alternative Attendance Adj:
A102: =A100+1 -> 19 | C102: All Categories | D102: ='FY 2003'!I93 -> 1341221 | E102: ='FY 2004'!I93 -> -679857 | F102: ='FY 2005'!I93 -> -1089963.9 | G102: =ROUND(SUM('SUMMARY-ALL YEARS'!G102:G106)/1000,1) -> -895.4 | H102: =ROUND(SUM('SUMMARY-ALL YEARS'!H102:H106)/1000,1) -> -886.1 | I102: =ROUND(SUM('SUMMARY-ALL YEARS'!I102:I106)/1000,1) -> -182.3 | J102: =ROUND(SUM('SUMMARY-ALL YEARS'!J102:J106)/1000,1) -> 261.6 | K102: =ROUND(SUM('SUMMARY-ALL YEARS'!K102:K106)/1000,1) -> 677.7 | L102: =ROUND(SUM('SUMMARY-ALL YEARS'!L102:L106)/1000,1) -> 766.8 | M102: =ROUND(SUM('SUMMARY-ALL YEARS'!M102:M106)/1000,1) -> 543 | N102: =ROUND(SUM('SUMMARY-ALL YEARS'!N102:N106)/1000,1) -> 42.4 | ... P102: =ROUND(SUM('SUMMARY-ALL YEARS'!P102:P106)/1000,1) -> -359.1 | Q102: =SUM(I102:J102) -> 79.3 | R102: =SUM(K102:L102) -> 1444.5 | S102: =SUM(M102:N102) -> 585.4 | T102: =SUM(O102:P102) -> -562.2 | U102: =R102-Q102 -> 1365.2 | V102: =U102/Q102 -> 17.215637 | W102: =S102-R102 -> -859.1 | X102: =W102/R102 -> -0.59473866 | Y102: =T102-S102 -> -1147.6 | Z102: =Y102/S102 -> -1.960369
A103: =A102+1 -> 20 | D103: ='FY 2003'!I94 -> -1804253 | E103: ='FY 2004'!I94 -> 1059 | F103: ='FY 2005'!I94 -> 0 | G103: 0 | H103: 0 | I103: 0 | J103: 0 | K103: 0 | L103: 0 | M103: 0 | N103: 0 | O103: 0 | P103: 0 | Q103: =SUM(I103:J103) -> 0 | R103: =SUM(K103:L103) -> 0 | S103: =SUM(M103:N103) -> 0 | T103: =SUM(O103:P103) -> 0
A104: =A103+1 -> 21 | D104: ='FY 2003'!I95 -> 0 | E104: ='FY 2004'!I95 -> 0 | F104: ='FY 2005'!I95 -> 0 | G104: 0 | H104: 0 | I104: 0 | J104: 0 | K104: 0 | L104: 0 | M104: 0 | N104: 0 | O104: 0 | P104: 0 | Q104: =SUM(I104:J104) -> 0 | R104: =SUM(K104:L104) -> 0 | S104: =SUM(M104:N104) -> 0 | T104: =SUM(O104:P104) -> 0
A105: =A104+1 -> 22 | D105: ='FY 2003'!I96 -> 0 | E105: ='FY 2004'!I96 -> 0 | F105: ='FY 2005'!I96 -> 0 | G105: 0 | H105: 0 | I105: 0 | J105: 0 | K105: 0 | L105: 0 | M105: 0 | N105: 0 | O105: 0 | P105: 0 | Q105: =SUM(I105:J105) -> 0 | R105: =SUM(K105:L105) -> 0 | S105: =SUM(M105:N105) -> 0 | T105: =SUM(O105:P105) -> 0
A106: =A105+1 -> 23 | D106: 0 | E106: 0 | F106: 0 | G106: 0 | H106: 0 | I106: 0 | J106: 0 | K106: 0 | L106: 0 | M106: 0 | N106: 0 | O106: 0 | P106: 0 | Q106: =SUM(I106:J106) -> 0 | R106: =SUM(K106:L106) -> 0 | S106: =SUM(M106:N106) -> 0 | T106: =SUM(O106:P106) -> 0
A108: =A106+1 -> 24 | B108: TOTAL REVENUE | D108: =SUM(D83:D105) -> 5421781814 | E108: =SUM(E83:E105) -> 5514835219 | F108: =SUM(F83:F106) -> 4506736.4 | G108: =SUM(G83:G106) -> 5856179.5 | H108: =SUM(H83:H106) -> 6210065.1 | I108: =SUM(I83:I106) -> 6391706 | J108: =SUM(J83:J106) -> 6556032.8 | K108: =SUM(K83:K106) -> 6073672.9 | L108: =SUM(L83:L106) -> 6671598.4 | M108: =SUM(M83:M106) -> 6750880.2 | ... P108: =SUM(P83:P106) -> 7181785 | Q108: =SUM(I108:J108) -> 12947739 | R108: =SUM(K108:L108) -> 12745271 | S108: =SUM(M108:N108) -> 13644949 | T108: =SUM(O108:P108) -> 14203009 | U108: =R108-Q108 -> -202467.5 | V108: =U108/Q108 -> -0.015637286 | W108: =S108-R108 -> 899677.7 | X108: =W108/R108 -> 0.070589137 | Y108: =T108-S108 -> 558059.8 | Z108: =Y108/S108 -> 0.040898636
B110: LEVIES
A111: =A108+1 -> 25 | B111: Operating Capital Levy | D111: ='FY 2003'!I101 -> 0 | E111: ='FY 2004'!I101 -> 0 | F111: =ROUND('SUMMARY-ALL YEARS'!F111/1000,1) -> 40007.3 | G111: =ROUND('SUMMARY-ALL YEARS'!G111/1000,1) -> 44268.2 | H111: =ROUND('SUMMARY-ALL YEARS'!H111/1000,1) -> 101934.5 | I111: =ROUND('SUMMARY-ALL YEARS'!I111/1000,1) -> 111830.4 | J111: =ROUND('SUMMARY-ALL YEARS'!J111/1000,1) -> 121253 | K111: =ROUND('SUMMARY-ALL YEARS'!K111/1000,1) -> 124372.7 | L111: =ROUND('SUMMARY-ALL YEARS'!L111/1000,1) -> 124597.7 | M111: =ROUND('SUMMARY-ALL YEARS'!M111/1000,1) -> 119996 | ... P111: =ROUND('SUMMARY-ALL YEARS'!P111/1000,1) -> 118314.7 | Q111: =SUM(I111:J111) -> 233083.4 | R111: =SUM(K111:L111) -> 248970.4 | S111: =SUM(M111:N111) -> 237132 | T111: =SUM(O111:P111) -> 235641.1 | U111: =R111-Q111 -> 15887 | V111: =U111/Q111 -> 0.068160152 | W111: =S111-R111 -> -11838.4 | X111: =W111/R111 -> -0.047549428 | Y111: =T111-S111 -> -1490.9 | Z111: =Y111/S111 -> -0.0062872156
A112: =A111+1 -> 26 | B112: Equity Levy | D112: ='FY 2003'!I102 -> 0 | E112: ='FY 2004'!I102 -> 0 | F112: =ROUND('SUMMARY-ALL YEARS'!F112/1000,1) -> 22380.3 | G112: =ROUND('SUMMARY-ALL YEARS'!G112/1000,1) -> 25083.3 | H112: =ROUND('SUMMARY-ALL YEARS'!H112/1000,1) -> 63740.1 | I112: =ROUND('SUMMARY-ALL YEARS'!I112/1000,1) -> 70604.3 | J112: =ROUND('SUMMARY-ALL YEARS'!J112/1000,1) -> 73701.6 | K112: =ROUND('SUMMARY-ALL YEARS'!K112/1000,1) -> 75869.4 | L112: =ROUND('SUMMARY-ALL YEARS'!L112/1000,1) -> 76264.3 | M112: =ROUND('SUMMARY-ALL YEARS'!M112/1000,1) -> 75800.2 | ... P112: =ROUND('SUMMARY-ALL YEARS'!P112/1000,1) -> 74124.2 | Q112: =SUM(I112:J112) -> 144305.9 | R112: =SUM(K112:L112) -> 152133.7 | S112: =SUM(M112:N112) -> 149581.5 | T112: =SUM(O112:P112) -> 147394 | U112: =R112-Q112 -> 7827.8 | V112: =U112/Q112 -> 0.05424449 | W112: =S112-R112 -> -2552.2 | X112: =W112/R112 -> -0.016776033 | Y112: =T112-S112 -> -2187.5 | Z112: =Y112/S112 -> -0.014624135
A113: =A112+1 -> 27 | B113: Transition Levy | D113: ='FY 2003'!I103 -> 0 | E113: ='FY 2004'!I103 -> 0 | F113: =ROUND('SUMMARY-ALL YEARS'!F113/1000,1) -> 18540.6 | G113: =ROUND('SUMMARY-ALL YEARS'!G113/1000,1) -> 20383.5 | H113: =ROUND('SUMMARY-ALL YEARS'!H113/1000,1) -> 21830.5 | I113: =ROUND('SUMMARY-ALL YEARS'!I113/1000,1) -> 23010.4 | J113: =ROUND('SUMMARY-ALL YEARS'!J113/1000,1) -> 24292.9 | K113: =ROUND('SUMMARY-ALL YEARS'!K113/1000,1) -> 25223.2 | L113: =ROUND('SUMMARY-ALL YEARS'!L113/1000,1) -> 25220.4 | M113: =ROUND('SUMMARY-ALL YEARS'!M113/1000,1) -> 24544.4 | ... P113: =ROUND('SUMMARY-ALL YEARS'!P113/1000,1) -> 24362 | Q113: =SUM(I113:J113) -> 47303.3 | R113: =SUM(K113:L113) -> 50443.6 | S113: =SUM(M113:N113) -> 48449.2 | T113: =SUM(O113:P113) -> 48434 | U113: =R113-Q113 -> 3140.3 | V113: =U113/Q113 -> 0.066386489 | W113: =S113-R113 -> -1994.4 | X113: =W113/R113 -> -0.039537226 | Y113: =T113-S113 -> -15.2 | Z113: =Y113/S113 -> -0.00031373067
A114: =A113+1 -> 28 | B114: Q Comp | D114: ='FY 2003'!I104 -> 0 | E114: ='FY 2004'!I104 -> 0 | F114: =ROUND('SUMMARY-ALL YEARS'!F114/1000,1) -> 0 | G114: =ROUND('SUMMARY-ALL YEARS'!G114/1000,1) -> 0 | H114: =ROUND('SUMMARY-ALL YEARS'!H114/1000,1) -> 9695.5 | I114: =ROUND('SUMMARY-ALL YEARS'!I114/1000,1) -> 12779.7 | J114: =ROUND('SUMMARY-ALL YEARS'!J114/1000,1) -> 13353.4 | K114: =ROUND('SUMMARY-ALL YEARS'!K114/1000,1) -> 16808.3 | L114: =ROUND('SUMMARY-ALL YEARS'!L114/1000,1) -> 18764.1 | M114: =ROUND('SUMMARY-ALL YEARS'!M114/1000,1) -> 23054.9 | ... P114: =ROUND('SUMMARY-ALL YEARS'!P114/1000,1) -> 23994 | Q114: =SUM(I114:J114) -> 26133.1 | R114: =SUM(K114:L114) -> 35572.4 | S114: =SUM(M114:N114) -> 46116.4 | T114: =SUM(O114:P114) -> 47468.2 | U114: =R114-Q114 -> 9439.3 | V114: =U114/Q114 -> 0.36120093 | W114: =S114-R114 -> 10544 | X114: =W114/R114 -> 0.29640958 | Y114: =T114-S114 -> 1351.8 | Z114: =Y114/S114 -> 0.029312782
A115: =A114+1 -> 29 | B115: Referendum Levy | D115: ='FY 2003'!I105 -> 224945858 | E115: ='FY 2004'!I105 -> 351087875 | F115: =ROUND('SUMMARY-ALL YEARS'!F115/1000,1) -> 379954.5 | G115: =ROUND('SUMMARY-ALL YEARS'!G115/1000,1) -> 410867.9 | H115: =ROUND('SUMMARY-ALL YEARS'!H115/1000,1) -> 482421.7 | I115: =ROUND('SUMMARY-ALL YEARS'!I115/1000,1) -> 540184.3 | J115: =ROUND('SUMMARY-ALL YEARS'!J115/1000,1) -> 635333.5 | K115: =ROUND('SUMMARY-ALL YEARS'!K115/1000,1) -> 712846.8 | L115: =ROUND('SUMMARY-ALL YEARS'!L115/1000,1) -> 738357.9 | M115: =ROUND('SUMMARY-ALL YEARS'!M115/1000,1) -> 745759.1 | ... P115: =ROUND('SUMMARY-ALL YEARS'!P115/1000,1) -> 914711.5 | Q115: =SUM(I115:J115) -> 1175517.8 | R115: =SUM(K115:L115) -> 1451204.7 | S115: =SUM(M115:N115) -> 1548376.4 | T115: =SUM(O115:P115) -> 1762458.1 | U115: =R115-Q115 -> 275686.9 | V115: =U115/Q115 -> 0.2345238 | W115: =S115-R115 -> 97171.7 | X115: =W115/R115 -> 0.066959334 | Y115: =T115-S115 -> 214081.7 | Z115: =Y115/S115 -> 0.13826205
...

Sheet FY 2003
A1: FY 2003: FEB 2007 VS. NOV 2006 CSA
A3: FEBRUARY 2007 FORECAST | D3: School District | E3: New Refer | F3: SD Fudge | G3: Charter Sch | H3: CH Fudge | I3: Total
A5: 1 | B5: AMCPU | D5: ='Pupil Data'!C36 -> 948532 | E5: 0 | F5: ='Pupil Data'!D36 -> 0 | G5: ='Pupil Data'!E36 -> 13614 | H5: ='Pupil Data'!F36 -> 0 | I5: =SUM(D5:H5) -> 962146
B7: REVENUES
A8: =A5+1 -> 2 | B8: Basic | D8: 4426308266 | E8: 0 | F8: 0 | G8: 63752054 | H8: 0 | I8: =SUM(D8:H8) -> 4490060320
A9: =A8+1 -> 3 | B9: Gifted & Talented | D9: 0 | E9: 0 | F9: 0 | G9: 0 | H9: 0 | I9: =SUM(D9:H9) -> 0
A10: =A9+1 -> 4 | B10: Extended time | D10: 0 | E10: 0 | F10: 0 | G10: 0 | H10: 0 | I10: =SUM(D10:H10) -> 0
B11: Basic Skills:
A12: =A10+1 -> 5 | C12: Compensatory | D12: 250666023 | E12: 0 | F12: 0 | G12: 12028663 | H12: 0 | I12: =SUM(D12:H12) -> 262694686
A13: =A12+1 -> 6 | C13: LEP | D13: 35700072 | E13: 0 | F13: 0 | G13: 1157155 | H13: 0 | I13: =SUM(D13:H13) -> 36857227
A14: =A13+1 -> 7 | C14: LEP Concentration | D14: 9436234 | E14: 0 | F14: 0 | G14: 342874 | H14: 0 | I14: =SUM(D14:H14) -> 9779108
A15: =A14+1 -> 8 | B15: Sparsity | D15: 16237664 | E15: 0 | F15: 0 | G15: 233887 | H15: 0 | I15: =SUM(D15:H15) -> 16471551
A16: =A15+1 -> 9 | B16: Transport Sparsity | D16: 56116444 | E16: 0 | F16: 0 | G16: 361920 | H16: 0 | I16: =SUM(D16:H16) -> 56478364
A17: =A16+1 -> 10 | B17: Training & Experience | D17: 24757826 | E17: 0 | F17: 0 | G17: 356482 | H17: 0 | I17: =SUM(D17:H17) -> 25114308
A18: =A17+1 -> 11 | B18: Late Contract Penalty | D18: 0 | E18: 0 | F18: 0 | G18: 0 | H18: 0 | I18: =SUM(D18:H18) -> 0
A19: =A18+1 -> 12 | B19: Operating Capital | D19: 195620930 | E19: 0 | F19: 0 | G19: 2817504 | H19: 0 | I19: =SUM(D19:H19) -> 198438434
A20: =A19+1 -> 13 | B20: Equity | D20: 34150600 | E20: 0 | F20: 0 | G20: 491890 | H20: 0 | I20: =SUM(D20:H20) -> 34642490
A21: =A20+1 -> 14 | B21: Transition | D21: 0 | E21: 0 | F21: 0 | G21: 0 | H21: 0 | I21: =SUM(D21:H21) -> 0
A22: =A21+1 -> 15 | B22: Q Comp | D22: 0 | E22: 0 | F22: 0 | G22: 0 | H22: 0 | I22: =SUM(D22:H22) -> 0
A23: =A22+1 -> 16 | B23: Referendum Revenue | D23: 291708358 | E23: 0 | F23: 0 | G23: 0 | H23: 0 | I23: =SUM(D23:H23) -> 291708358
B24: Alternative Attendance Adj:
A25: =A23+1 -> 17 | C25: Open Enroll/Charter Refer | D25: 824218 | E25: 0 | F25: 0 | G25: 517003 | H25: 0 | I25: =SUM(D25:H25) -> 1341221
A26: =A25+1 -> 18 | C26: Charter Basic Transport | D26: 0 | E26: 0 | F26: 0 | G26: -1804253 | H26: 0 | I26: =SUM(D26:H26) -> -1804253
A27: =A26+1 -> 19 | C27: Charter Ext TimeTransport | D27: 0 | E27: 0 | F27: 0 | G27: 0 | H27: 0 | I27: =SUM(D27:H27) -> 0
A28: =A27+1 -> 20 | C28: Charter Transport Sparsity | D28: 0 | E28: 0 | F28: 0 | G28: 0 | H28: 0 | I28: =SUM(D28:H28) -> 0
A30: =A28+1 -> 21 | B30: TOTAL REVENUE | D30: =SUM(D8:D28) -> 5341526635 | E30: =SUM(E8:E28) -> 0 | F30: =SUM(F8:F28) -> 0 | G30: =SUM(G8:G28) -> 80255179 | H30: =SUM(H8:H28) -> 0 | I30: =SUM(I8:I28) -> 5421781814
B32: LEVIES
A33: =A30+1 -> 22 | B33: Operating Capital Levy | D33: 0 | E33: 0 | F33: 0 | G33: 0 | H33: 0 | I33: =SUM(D33:H33) -> 0
A34: =A33+1 -> 23 | B34: Equity Levy | D34: 0 | E34: 0 | F34: 0 | G34: 0 | H34: 0 | I34: =SUM(D34:H34) -> 0
A35: =A34+1 -> 24 | B35: Transition Levy | D35: 0 | E35: 0 | F35: 0 | G35: 0 | H35: 0 | I35: =SUM(D35:H35) -> 0
A36: =A35+1 -> 25 | B36: Q Comp | D36: 0 | E36: 0 | F36: 0 | G36: 0 | H36: 0 | I36: =SUM(D36:H36) -> 0
A37: =A36+1 -> 26 | B37: Referendum Levy | D37: 224945858 | E37: 0 | F37: 0 | G37: 0 | H37: 0 | I37: =SUM(D37:H37) -> 224945858
A39: =A37+1 -> 27 | B39: TOTAL LEVY | D39: =SUM(D33:D37) -> 224945858 | E39: =SUM(E33:E37) -> 0 | F39: =SUM(F33:F37) -> 0 | G39: =SUM(G33:G37) -> 0 | H39: =SUM(H33:H37) -> 0 | I39: =SUM(I33:I37) -> 224945858
B41: AID ENTITLEMENTS
A42: =A39+1 -> 28 | B42: Basic | D42: =D8 -> 4426308266 | E42: =E8 -> 0 | F42: =F8 -> 0 | G42: =G8 -> 63752054 | H42: =H8 -> 0 | I42: =SUM(D42:H42) -> 4490060320
A43: =A42+1 -> 29 | B43: Gifted & Talented | D43: =D9 -> 0 | E43: =E9 -> 0 | F43: =F9 -> 0 | G43: =G9 -> 0 | H43: =H9 -> 0 | I43: =SUM(D43:H43) -> 0
A44: =A43+1 -> 30 | B44: Extended time | D44: =D10 -> 0 | E44: =E10 -> 0 | F44: =F10 -> 0 | G44: =G10 -> 0 | H44: =H10 -> 0 | I44: =SUM(D44:H44) -> 0
B45: Basic Skills:
A46: =A44+1 -> 31 | C46: Compensatory | D46: =D12 -> 250666023 | E46: =E12 -> 0 | F46: =F12 -> 0 | G46: =G12 -> 12028663 | H46: =H12 -> 0 | I46: =SUM(D46:H46) -> 262694686
A47: =A46+1 -> 32 | C47: LEP | D47: =D13 -> 35700072 | E47: =E13 -> 0 | F47: =F13 -> 0 | G47: =G13 -> 1157155 | H47: =H13 -> 0 | I47: =SUM(D47:H47) -> 36857227
A48: =A47+1 -> 33 | C48: LEP Concentration | D48: =D14 -> 9436234 | E48: =E14 -> 0 | F48: =F14 -> 0 | G48: =G14 -> 342874 | H48: =H14 -> 0 | I48: =SUM(D48:H48) -> 9779108
A49: =A48+1 -> 34 | B49: Sparsity | D49: =D15 -> 16237664 | E49: =E15 -> 0 | F49: =F15 -> 0 | G49: =G15 -> 233887 | H49: =H15 -> 0 | I49: =SUM(D49:H49) -> 16471551
A50: =A49+1 -> 35 | B50: Transport Sparsity | D50: =D16 -> 56116444 | E50: =E16 -> 0 | F50: =F16 -> 0 | G50: =G16 -> 361920 | H50: =H16 -> 0 | I50: =SUM(D50:H50) -> 56478364
A51: =A50+1 -> 36 | B51: Training & Experience | D51: =D17 -> 24757826 | E51: =E17 -> 0 | F51: =F17 -> 0 | G51: =G17 -> 356482 | H51: =H17 -> 0 | I51: =SUM(D51:H51) -> 25114308
A52: =A51+1 -> 37 | B52: Late Contract Penalty | D52: =D18 -> 0 | E52: =E18 -> 0 | F52: =F18 -> 0 | G52: =G18 -> 0 | H52: =H18 -> 0 | I52: =SUM(D52:H52) -> 0
A53: =A52+1 -> 38 | B53: Operating Capital | D53: =D19-D33 -> 195620930 | E53: =E19-E33 -> 0 | F53: =F19-F33 -> 0 | G53: =G19-G33 -> 2817504 | H53: =H19-H33 -> 0 | I53: =SUM(D53:H53) -> 198438434
A54: =A53+1 -> 39 | B54: Equity | D54: =D20-D34 -> 34150600 | E54: =E20-E34 -> 0 | F54: =F20-F34 -> 0 | G54: =G20-G34 -> 491890 | H54: =H20-H34 -> 0 | I54: =SUM(D54:H54) -> 34642490
A55: =A54+1 -> 40 | B55: Transition | D55: =D21-D35 -> 0 | E55: =E21-E35 -> 0 | F55: =F21-F35 -> 0 | G55: =G21-G35 -> 0 | H55: =H21-H35 -> 0 | I55: =SUM(D55:H55) -> 0
A56: =A55+1 -> 41 | B56: Q Comp | D56: =D22-D36 -> 0 | E56: =E22-E36 -> 0 | F56: =F22-F36 -> 0 | G56: =G22-G36 -> 0 | H56: =H22-H36 -> 0 | I56: =SUM(D56:H56) -> 0
A57: =A56+1 -> 42 | B57: Referendum Equalization Aid | D57: =D23-D37-D58 -> 58417206 | E57: =E23-E37-E58 -> 0 | F57: =F23-F37-F58 -> 0 | G57: =G23-G37-G58 -> 0 | H57: =H23-H37-H58 -> 0 | I57: =SUM(D57:H57) -> 58417206
A58: =A57+1 -> 43 | B58: Tax Base Replacement Aid | D58: 8345294 | E58: 0 | F58: 0 | G58: 0 | H58: 0 | I58: =SUM(D58:H58) -> 8345294
B59: Alternative Attendance Adj:
A60: =A58+1 -> 44 | C60: Open Enroll/Charter Refer | D60: =D25 -> 824218 | E60: =E25 -> 0 | F60: =F25 -> 0 | G60: =G25 -> 517003 | H60: =H25 -> 0 | I60: =SUM(D60:H60) -> 1341221
A61: =A60+1 -> 45 | C61: Charter Basic Transport | D61: =D26 -> 0 | E61: =E26 -> 0 | F61: =F26 -> 0 | G61: =G26 -> -1804253 | H61: =H26 -> 0 | I61: =SUM(D61:H61) -> -1804253
A62: =A61+1 -> 46 | C62: Charter Ext TimeTransport | D62: =D27 -> 0 | E62: =E27 -> 0 | F62: =F27 -> 0 | G62: =G27 -> 0 | H62: =H27 -> 0 | I62: =SUM(D62:H62) -> 0
A63: =A62+1 -> 47 | C63: Charter Transport Sparsity | D63: =D28 -> 0 | E63: =E28 -> 0 | F63: =F28 -> 0 | G63: =G28 -> 0 | H63: =H28 -> 0 | I63: =SUM(D63:H63) -> 0
A65: =A63+1 -> 48 | B65: TOTAL AID ENTITLEMENT | D65: =SUM(D42:D63) -> 5116580777 | E65: =SUM(E42:E63) -> 0 | F65: =SUM(F42:F63) -> 0 | G65: =SUM(G42:G63) -> 80255179 | H65: =SUM(H42:H63) -> 0 | I65: =SUM(I42:I63) -> 5196835956
A66: =A65+1 -> 49 | B66: General Ed Entitlement | D66: =D65-D58 -> 5108235483 | E66: =E65-E58 -> 0 | F66: =F65-F58 -> 0 | G66: =G65-G58 -> 80255179 | H66: =H65-H58 -> 0 | I66: =I65-I58 -> 5188490662
A67: =A66+1 -> 50 | B67: Tax Base Replacement Entitlement | D67: =D58 -> 8345294 | E67: =E58 -> 0 | F67: =F58 -> 0 | G67: =G58 -> 0 | H67: =H58 -> 0 | I67: =I58 -> 8345294
A69: =A67+1 -> 51 | B69: TRA Reduction | D69: -45908384 | E69: 0 | F69: 0 | G69: =-46570547-D69 -> -662163 | H69: 0 | I69: =SUM(D69:H69) -> -46570547
A71: NOVEMBER 2006 FORECAST | D71: School District | E71: New Refer | F71: SD Fudge | G71: Charter Sch | H71: CH Fudge | I71: Total
A73: 1 | B73: AMCPU | D73: ='Pupil Data'!C197 -> 948532 | E73: 0 | F73: ='Pupil Data'!D197 -> 0 | G73: ='Pupil Data'!E197 -> 13614 | H73: ='Pupil Data'!F197 -> 0 | I73: =SUM(D73:H73) -> 962146
B75: REVENUES
A76: =A73+1 -> 2 | B76: Basic | D76: 4426308266 | E76: 0 | F76: 0 | G76: 63752054 | H76: 0 | I76: =SUM(D76:H76) -> 4490060320
A77: =A76+1 -> 3 | B77: Gifted & Talented | D77: 0 | E77: 0 | F77: 0 | G77: 0 | H77: 0 | I77: =SUM(D77:H77) -> 0
A78: =A77+1 -> 4 | B78: Extended time | D78: 0 | E78: 0 | F78: 0 | G78: 0 | H78: 0 | I78: =SUM(D78:H78) -> 0
B79: Basic Skills:
A80: =A78+1 -> 5 | C80: Compensatory | D80: 250666023 | E80: 0 | F80: 0 | G80: 12028663 | H80: 0 | I80: =SUM(D80:H80) -> 262694686
A81: =A80+1 -> 6 | C81: LEP | D81: 35700072 | E81: 0 | F81: 0 | G81: 1157155 | H81: 0 | I81: =SUM(D81:H81) -> 36857227
A82: =A81+1 -> 7 | C82: LEP Concentration | D82: 9436234 | E82: 0 | F82: 0 | G82: 342874 | H82: 0 | I82: =SUM(D82:H82) -> 9779108
A83: =A82+1 -> 8 | B83: Sparsity | D83: 16237664 | E83: 0 | F83: 0 | G83: 233887 | H83: 0 | I83: =SUM(D83:H83) -> 16471551
A84: =A83+1 -> 9 | B84: Transport Sparsity | D84: 56116444 | E84: 0 | F84: 0 | G84: 361920 | H84: 0 | I84: =SUM(D84:H84) -> 56478364
A85: =A84+1 -> 10 | B85: Training & Experience | D85: 24757826 | E85: 0 | F85: 0 | G85: 356482 | H85: 0 | I85: =SUM(D85:H85) -> 25114308
A86: =A85+1 -> 11 | B86: Late Contract Penalty | D86: 0 | E86: 0 | F86: 0 | G86: 0 | H86: 0 | I86: =SUM(D86:H86) -> 0
A87: =A86+1 -> 12 | B87: Operating Capital | D87: 195620930 | E87: 0 | F87: 0 | G87: 2817504 | H87: 0 | I87: =SUM(D87:H87) -> 198438434
A88: =A87+1 -> 13 | B88: Equity | D88: 34150600 | E88: 0 | F88: 0 | G88: 491890 | H88: 0 | I88: =SUM(D88:H88) -> 34642490
A89: =A88+1 -> 14 | B89: Transition | D89: 0 | E89: 0 | F89: 0 | G89: 0 | H89: 0 | I89: =SUM(D89:H89) -> 0
A90: =A89+1 -> 15 | B90: Q Comp | D90: 0 | E90: 0 | F90: 0 | G90: 0 | H90: 0 | I90: =SUM(D90:H90) -> 0
A91: =A90+1 -> 16 | B91: Referendum Revenue | D91: 291708358 | E91: 0 | F91: 0 | G91: 0 | H91: 0 | I91: =SUM(D91:H91) -> 291708358
B92: Alternative Attendance Adj:
A93: =A91+1 -> 17 | C93: Open Enroll/Charter Refer | D93: 824218 | E93: 0 | F93: 0 | G93: 517003 | H93: 0 | I93: =SUM(D93:H93) -> 1341221
A94: =A93+1 -> 18 | C94: Charter Basic Transport | D94: 0 | E94: 0 | F94: 0 | G94: -1804253 | H94: 0 | I94: =SUM(D94:H94) -> -1804253
A95: =A94+1 -> 19 | C95: Charter Ext TimeTransport | D95: 0 | E95: 0 | F95: 0 | G95: 0 | H95: 0 | I95: =SUM(D95:H95) -> 0
A96: =A95+1 -> 20 | C96: Charter Transport Sparsity | D96: 0 | E96: 0 | F96: 0 | G96: 0 | H96: 0 | I96: =SUM(D96:H96) -> 0
A98: =A96+1 -> 21 | B98: TOTAL REVENUE | D98: =SUM(D76:D96) -> 5341526635 | E98: =SUM(E76:E96) -> 0 | F98: =SUM(F76:F96) -> 0 | G98: =SUM(G76:G96) -> 80255179 | H98: =SUM(H76:H96) -> 0 | I98: =SUM(I76:I96) -> 5421781814
B100: LEVIES
A101: =A98+1 -> 22 | B101: Operating Capital Levy | D101: 0 | E101: 0 | F101: 0 | G101: 0 | H101: 0 | I101: =SUM(D101:H101) -> 0
A102: =A101+1 -> 23 | B102: Equity Levy | D102: 0 | E102: 0 | F102: 0 | G102: 0 | H102: 0 | I102: =SUM(D102:H102) -> 0
A103: =A102+1 -> 24 | B103: Transition Levy | D103: 0 | E103: 0 | F103: 0 | G103: 0 | H103: 0 | I103: =SUM(D103:H103) -> 0
A104: =A103+1 -> 25 | B104: Q Comp | D104: 0 | E104: 0 | F104: 0 | G104: 0 | H104: 0 | I104: =SUM(D104:H104) -> 0
A105: =A104+1 -> 26 | B105: Referendum Levy | D105: 224945858 | E105: 0 | F105: 0 | G105: 0 | H105: 0 | I105: =SUM(D105:H105) -> 224945858
A107: =A105+1 -> 27 | B107: TOTAL LEVY | D107: =SUM(D101:D105) -> 224945858 | E107: =SUM(E101:E105) -> 0 | F107: =SUM(F101:F105) -> 0 | G107: =SUM(G101:G105) -> 0 | H107: =SUM(H101:H105) -> 0 | I107: =SUM(I101:I105) -> 224945858
B109: AID ENTITLEMENTS
A110: =A107+1 -> 28 | B110: Basic | D110: =D76 -> 4426308266 | E110: =E76 -> 0 | F110: =F76 -> 0 | G110: =G76 -> 63752054 | H110: =H76 -> 0 | I110: =SUM(D110:H110) -> 4490060320
A111: =A110+1 -> 29 | B111: Gifted & Talented | D111: =D77 -> 0 | E111: =E77 -> 0 | F111: =F77 -> 0 | G111: =G77 -> 0 | H111: =H77 -> 0 | I111: =SUM(D111:H111) -> 0
A112: =A111+1 -> 30 | B112: Extended time | D112: =D78 -> 0 | E112: =E78 -> 0 | F112: =F78 -> 0 | G112: =G78 -> 0 | H112: =H78 -> 0 | I112: =SUM(D112:H112) -> 0
B113: Basic Skills:
A114: =A112+1 -> 31 | C114: Compensatory | D114: =D80 -> 250666023 | E114: =E80 -> 0 | F114: =F80 -> 0 | G114: =G80 -> 12028663 | H114: =H80 -> 0 | I114: =SUM(D114:H114) -> 262694686
A115: =A114+1 -> 32 | C115: LEP | D115: =D81 -> 35700072 | E115: =E81 -> 0 | F115: =F81 -> 0 | G115: =G81 -> 1157155 | H115: =H81 -> 0 | I115: =SUM(D115:H115) -> 36857227
A116: =A115+1 -> 33 | C116: LEP Concentration | D116: =D82 -> 9436234 | E116: =E82 -> 0 | F116: =F82 -> 0 | G116: =G82 -> 342874 | H116: =H82 -> 0 | I116: =SUM(D116:H116) -> 9779108
...

Sheet FY 2004
A1: FY 2004: FEB 2007 VS. NOV 2006 CSA
A3: FEBRUARY 2007 FORECAST | D3: School District | E3: New Refer | F3: SD Fudge | G3: Charter Sch | H3: CH Fudge | I3: Total
A5: 1 | B5: AMCPU | D5: ='Pupil Data'!C37 -> 941129 | E5: 0 | F5: ='Pupil Data'!D37 -> 0 | G5: ='Pupil Data'!E37 -> 15967 | H5: ='Pupil Data'!F37 -> 0 | I5: =SUM(D5:H5) -> 957096
B7: REVENUES
A8: =A5+1 -> 2 | B8: Basic | D8: 4330167150 | E8: 0 | F8: 0 | G8: 73408127 | H8: 0 | I8: =SUM(D8:H8) -> 4403575277
A9: =A8+1 -> 3 | B9: Gifted & Talented | D9: 0 | E9: 0 | F9: 0 | G9: 0 | H9: 0 | I9: =SUM(D9:H9) -> 0
A10: =A9+1 -> 4 | B10: Extended time | D10: 49465489 | E10: 0 | F10: 0 | G10: 886061 | H10: 0 | I10: =SUM(D10:H10) -> 50351550
B11: Basic Skills:
A12: =A10+1 -> 5 | C12: Compensatory | D12: 235489836 | E12: 0 | F12: 0 | G12: 13657118 | H12: 0 | I12: =SUM(D12:H12) -> 249146954
A13: =A12+1 -> 6 | C13: LEP | D13: 27431166 | E13: 0 | F13: 0 | G13: 1387547 | H13: 0 | I13: =SUM(D13:H13) -> 28818713
A14: =A13+1 -> 7 | C14: LEP Concentration | D14: 6822038 | E14: 0 | F14: 0 | G14: 454720 | H14: 0 | I14: =SUM(D14:H14) -> 7276758
A15: =A14+1 -> 8 | B15: Sparsity | D15: 16628454 | E15: 0 | F15: 0 | G15: 281124 | H15: 0 | I15: =SUM(D15:H15) -> 16909578
A16: =A15+1 -> 9 | B16: Transport Sparsity | D16: 55468090 | E16: 0 | F16: 0 | G16: 445008 | H16: 0 | I16: =SUM(D16:H16) -> 55913098
A17: =A16+1 -> 10 | B17: Training & Experience | D17: 18554929 | E17: 0 | F17: 0 | G17: 314629 | H17: 0 | I17: =SUM(D17:H17) -> 18869558
A18: =A17+1 -> 11 | B18: Late Contract Penalty | D18: 0 | E18: 0 | F18: 0 | G18: 0 | H18: 0 | I18: =SUM(D18:H18) -> 0
A19: =A18+1 -> 12 | B19: Operating Capital | D19: 190979544 | E19: 0 | F19: 0 | G19: 3237552 | H19: 0 | I19: =SUM(D19:H19) -> 194217096
A20: =A19+1 -> 13 | B20: Equity | D20: 31577083 | E20: 0 | F20: 0 | G20: 535286 | H20: 0 | I20: =SUM(D20:H20) -> 32112369
A21: =A20+1 -> 14 | B21: Transition | D21: 31095752 | E21: 0 | F21: 0 | G21: 890772 | H21: 0 | I21: =SUM(D21:H21) -> 31986524
A22: =A21+1 -> 15 | B22: Q Comp | D22: 0 | E22: 0 | F22: 0 | G22: 0 | H22: 0 | I22: =SUM(D22:H22) -> 0
A23: =A22+1 -> 16 | B23: Referendum Revenue | D23: 426336542 | E23: 0 | F23: 0 | G23: 0 | H23: 0 | I23: =SUM(D23:H23) -> 426336542
B24: Alternative Attendance Adj:
A25: =A23+1 -> 17 | C25: Open Enroll/Charter Refer | D25: -1687931 | E25: 0 | F25: 0 | G25: 1008074 | H25: 0 | I25: =SUM(D25:H25) -> -679857
A26: =A25+1 -> 18 | C26: Charter Basic Transport | D26: 2039421 | E26: 0 | F26: 0 | G26: -2038362 | H26: 0 | I26: =SUM(D26:H26) -> 1059
A27: =A26+1 -> 19 | C27: Charter Ext TimeTransport | D27: 0 | E27: 0 | F27: 0 | G27: 0 | H27: 0 | I27: =SUM(D27:H27) -> 0
A28: =A27+1 -> 20 | C28: Charter Transport Sparsity | D28: 0 | E28: 0 | F28: 0 | G28: 0 | H28: 0 | I28: =SUM(D28:H28) -> 0
A30: =A28+1 -> 21 | B30: TOTAL REVENUE | D30: =SUM(D8:D28) -> 5420367563 | E30: =SUM(E8:E28) -> 0 | F30: =SUM(F8:F28) -> 0 | G30: =SUM(G8:G28) -> 94467656 | H30: =SUM(H8:H28) -> 0 | I30: =SUM(I8:I28) -> 5514835219
B32: LEVIES
A33: =A30+1 -> 22 | B33: Operating Capital Levy | D33: 0 | E33: 0 | F33: 0 | G33: 0 | H33: 0 | I33: =SUM(D33:H33) -> 0
A34: =A33+1 -> 23 | B34: Equity Levy | D34: 0 | E34: 0 | F34: 0 | G34: 0 | H34: 0 | I34: =SUM(D34:H34) -> 0
A35: =A34+1 -> 24 | B35: Transition Levy | D35: 0 | E35: 0 | F35: 0 | G35: 0 | H35: 0 | I35: =SUM(D35:H35) -> 0
A36: =A35+1 -> 25 | B36: Q Comp | D36: 0 | E36: 0 | F36: 0 | G36: 0 | H36: 0 | I36: =SUM(D36:H36) -> 0
A37: =A36+1 -> 26 | B37: Referendum Levy | D37: 351087875 | E37: 0 | F37: 0 | G37: 0 | H37: 0 | I37: =SUM(D37:H37) -> 351087875
A39: =A37+1 -> 27 | B39: TOTAL LEVY | D39: =SUM(D33:D37) -> 351087875 | E39: =SUM(E33:E37) -> 0 | F39: =SUM(F33:F37) -> 0 | G39: =SUM(G33:G37) -> 0 | H39: =SUM(H33:H37) -> 0 | I39: =SUM(I33:I37) -> 351087875
B41: AID ENTITLEMENTS
A42: =A39+1 -> 28 | B42: Basic | D42: =D8 -> 4330167150 | E42: =E8 -> 0 | F42: =F8 -> 0 | G42: =G8 -> 73408127 | H42: =H8 -> 0 | I42: =SUM(D42:H42) -> 4403575277
A43: =A42+1 -> 29 | B43: Gifted & Talented | D43: =D9 -> 0 | E43: =E9 -> 0 | F43: =F9 -> 0 | G43: =G9 -> 0 | H43: =H9 -> 0 | I43: =SUM(D43:H43) -> 0
A44: =A43+1 -> 30 | B44: Extended time | D44: =D10 -> 49465489 | E44: =E10 -> 0 | F44: =F10 -> 0 | G44: =G10 -> 886061 | H44: =H10 -> 0 | I44: =SUM(D44:H44) -> 50351550
B45: Basic Skills:
A46: =A44+1 -> 31 | C46: Compensatory | D46: =D12 -> 235489836 | E46: =E12 -> 0 | F46: =F12 -> 0 | G46: =G12 -> 13657118 | H46: =H12 -> 0 | I46: =SUM(D46:H46) -> 249146954
A47: =A46+1 -> 32 | C47: LEP | D47: =D13 -> 27431166 | E47: =E13 -> 0 | F47: =F13 -> 0 | G47: =G13 -> 1387547 | H47: =H13 -> 0 | I47: =SUM(D47:H47) -> 28818713
A48: =A47+1 -> 33 | C48: LEP Concentration | D48: =D14 -> 6822038 | E48: =E14 -> 0 | F48: =F14 -> 0 | G48: =G14 -> 454720 | H48: =H14 -> 0 | I48: =SUM(D48:H48) -> 7276758
A49: =A48+1 -> 34 | B49: Sparsity | D49: =D15 -> 16628454 | E49: =E15 -> 0 | F49: =F15 -> 0 | G49: =G15 -> 281124 | H49: =H15 -> 0 | I49: =SUM(D49:H49) -> 16909578
A50: =A49+1 -> 35 | B50: Transport Sparsity | D50: =D16 -> 55468090 | E50: =E16 -> 0 | F50: =F16 -> 0 | G50: =G16 -> 445008 | H50: =H16 -> 0 | I50: =SUM(D50:H50) -> 55913098
A51: =A50+1 -> 36 | B51: Training & Experience | D51: =D17 -> 18554929 | E51: =E17 -> 0 | F51: =F17 -> 0 | G51: =G17 -> 314629 | H51: =H17 -> 0 | I51: =SUM(D51:H51) -> 18869558
A52: =A51+1 -> 37 | B52: Late Contract Penalty | D52: =D18 -> 0 | E52: =E18 -> 0 | F52: =F18 -> 0 | G52: =G18 -> 0 | H52: =H18 -> 0 | I52: =SUM(D52:H52) -> 0
A53: =A52+1 -> 38 | B53: Operating Capital | D53: =D19-D33 -> 190979544 | E53: =E19-E33 -> 0 | F53: =F19-F33 -> 0 | G53: =G19-G33 -> 3237552 | H53: =H19-H33 -> 0 | I53: =SUM(D53:H53) -> 194217096
A54: =A53+1 -> 39 | B54: Equity | D54: =D20-D34 -> 31577083 | E54: =E20-E34 -> 0 | F54: =F20-F34 -> 0 | G54: =G20-G34 -> 535286 | H54: =H20-H34 -> 0 | I54: =SUM(D54:H54) -> 32112369
A55: =A54+1 -> 40 | B55: Transition | D55: =D21-D35 -> 31095752 | E55: =E21-E35 -> 0 | F55: =F21-F35 -> 0 | G55: =G21-G35 -> 890772 | H55: =H21-H35 -> 0 | I55: =SUM(D55:H55) -> 31986524
A56: =A55+1 -> 41 | B56: Q Comp | D56: =D22-D36 -> 0 | E56: =E22-E36 -> 0 | F56: =F22-F36 -> 0 | G56: =G22-G36 -> 0 | H56: =H22-H36 -> 0 | I56: =SUM(D56:H56) -> 0
A57: =A56+1 -> 42 | B57: Referendum Equalization Aid | D57: =D23-D37-D58 -> 67208298 | E57: =E23-E37-E58 -> 0 | F57: =F23-F37-F58 -> 0 | G57: =G23-G37-G58 -> 0 | H57: =H23-H37-H58 -> 0 | I57: =SUM(D57:H57) -> 67208298
A58: =A57+1 -> 43 | B58: Tax Base Replacement Aid | D58: 8040369 | E58: 0 | F58: 0 | G58: 0 | H58: 0 | I58: =SUM(D58:H58) -> 8040369
B59: Alternative Attendance Adj:
A60: =A58+1 -> 44 | C60: Open Enroll/Charter Refer | D60: =D25 -> -1687931 | E60: =E25 -> 0 | F60: =F25 -> 0 | G60: =G25 -> 1008074 | H60: =H25 -> 0 | I60: =SUM(D60:H60) -> -679857
A61: =A60+1 -> 45 | C61: Charter Basic Transport | D61: =D26 -> 2039421 | E61: =E26 -> 0 | F61: =F26 -> 0 | G61: =G26 -> -2038362 | H61: =H26 -> 0 | I61: =SUM(D61:H61) -> 1059
A62: =A61+1 -> 46 | C62: Charter Ext TimeTransport | D62: =D27 -> 0 | E62: =E27 -> 0 | F62: =F27 -> 0 | G62: =G27 -> 0 | H62: =H27 -> 0 | I62: =SUM(D62:H62) -> 0
A63: =A62+1 -> 47 | C63: Charter Transport Sparsity | D63: =D28 -> 0 | E63: =E28 -> 0 | F63: =F28 -> 0 | G63: =G28 -> 0 | H63: =H28 -> 0 | I63: =SUM(D63:H63) -> 0
A65: =A63+1 -> 48 | B65: TOTAL AID ENTITLEMENT | D65: =SUM(D42:D63) -> 5069279688 | E65: =SUM(E42:E63) -> 0 | F65: =SUM(F42:F63) -> 0 | G65: =SUM(G42:G63) -> 94467656 | H65: =SUM(H42:H63) -> 0 | I65: =SUM(I42:I63) -> 5163747344
A66: =A65+1 -> 49 | B66: General Ed Entitlement | D66: =D65-D58 -> 5061239319 | E66: =E65-E58 -> 0 | F66: =F65-F58 -> 0 | G66: =G65-G58 -> 94467656 | H66: =H65-H58 -> 0 | I66: =I65-I58 -> 5155706975
A67: =A66+1 -> 50 | B67: Tax Base Replacement Entitlement | D67: =D58 -> 8040369 | E67: =E58 -> 0 | F67: =F58 -> 0 | G67: =G58 -> 0 | H67: =H58 -> 0 | I67: =I58 -> 8040369
A69: =A67+1 -> 51 | B69: TRA Reduction | D69: -45908384 | E69: 0 | F69: 0 | G69: -778277 | H69: 0 | I69: =SUM(D69:H69) -> -46686661
A71: NOVEMBER 2006 FORECAST | D71: School District | E71: New Refer | F71: SD Fudge | G71: Charter Sch | H71: CH Fudge | I71: Total
A73: 1 | B73: AMCPU | D73: ='Pupil Data'!C198 -> 941129 | E73: 0 | F73: ='Pupil Data'!D198 -> 0 | G73: ='Pupil Data'!E198 -> 15967 | H73: ='Pupil Data'!F198 -> 0 | I73: =SUM(D73:H73) -> 957096
B75: REVENUES
A76: =A73+1 -> 2 | B76: Basic | D76: 4330167150 | E76: 0 | F76: 0 | G76: 73408127 | H76: 0 | I76: =SUM(D76:H76) -> 4403575277
A77: =A76+1 -> 3 | B77: Gifted & Talented | D77: 0 | E77: 0 | F77: 0 | G77: 0 | H77: 0 | I77: =SUM(D77:H77) -> 0
A78: =A77+1 -> 4 | B78: Extended time | D78: 49465489 | E78: 0 | F78: 0 | G78: 886061 | H78: 0 | I78: =SUM(D78:H78) -> 50351550
B79: Basic Skills:
A80: =A78+1 -> 5 | C80: Compensatory | D80: 235489836 | E80: 0 | F80: 0 | G80: 13657118 | H80: 0 | I80: =SUM(D80:H80) -> 249146954
A81: =A80+1 -> 6 | C81: LEP | D81: 27431166 | E81: 0 | F81: 0 | G81: 1387547 | H81: 0 | I81: =SUM(D81:H81) -> 28818713
A82: =A81+1 -> 7 | C82: LEP Concentration | D82: 6822038 | E82: 0 | F82: 0 | G82: 454720 | H82: 0 | I82: =SUM(D82:H82) -> 7276758
A83: =A82+1 -> 8 | B83: Sparsity | D83: 16628454 | E83: 0 | F83: 0 | G83: 281124 | H83: 0 | I83: =SUM(D83:H83) -> 16909578
A84: =A83+1 -> 9 | B84: Transport Sparsity | D84: 55468090 | E84: 0 | F84: 0 | G84: 445008 | H84: 0 | I84: =SUM(D84:H84) -> 55913098
A85: =A84+1 -> 10 | B85: Training & Experience | D85: 18554929 | E85: 0 | F85: 0 | G85: 314629 | H85: 0 | I85: =SUM(D85:H85) -> 18869558
A86: =A85+1 -> 11 | B86: Late Contract Penalty | D86: 0 | E86: 0 | F86: 0 | G86: 0 | H86: 0 | I86: =SUM(D86:H86) -> 0
A87: =A86+1 -> 12 | B87: Operating Capital | D87: 190979544 | E87: 0 | F87: 0 | G87: 3237552 | H87: 0 | I87: =SUM(D87:H87) -> 194217096
A88: =A87+1 -> 13 | B88: Equity | D88: 31577083 | E88: 0 | F88: 0 | G88: 535286 | H88: 0 | I88: =SUM(D88:H88) -> 32112369
A89: =A88+1 -> 14 | B89: Transition | D89: 31095752 | E89: 0 | F89: 0 | G89: 890772 | H89: 0 | I89: =SUM(D89:H89) -> 31986524
A90: =A89+1 -> 15 | B90: Q Comp | D90: 0 | E90: 0 | F90: 0 | G90: 0 | H90: 0 | I90: =SUM(D90:H90) -> 0
A91: =A90+1 -> 16 | B91: Referendum Revenue | D91: 426336542 | E91: 0 | F91: 0 | G91: 0 | H91: 0 | I91: =SUM(D91:H91) -> 426336542
B92: Alternative Attendance Adj:
A93: =A91+1 -> 17 | C93: Open Enroll/Charter Refer | D93: -1687931 | E93: 0 | F93: 0 | G93: 1008074 | H93: 0 | I93: =SUM(D93:H93) -> -679857
A94: =A93+1 -> 18 | C94: Charter Basic Transport | D94: 2039421 | E94: 0 | F94: 0 | G94: -2038362 | H94: 0 | I94: =SUM(D94:H94) -> 1059
A95: =A94+1 -> 19 | C95: Charter Ext TimeTransport | D95: 0 | E95: 0 | F95: 0 | G95: 0 | H95: 0 | I95: =SUM(D95:H95) -> 0
A96: =A95+1 -> 20 | C96: Charter Transport Sparsity | D96: 0 | E96: 0 | F96: 0 | G96: 0 | H96: 0 | I96: =SUM(D96:H96) -> 0
A98: =A96+1 -> 21 | B98: TOTAL REVENUE | D98: =SUM(D76:D96) -> 5420367563 | E98: =SUM(E76:E96) -> 0 | F98: =SUM(F76:F96) -> 0 | G98: =SUM(G76:G96) -> 94467656 | H98: =SUM(H76:H96) -> 0 | I98: =SUM(I76:I96) -> 5514835219
B100: LEVIES
A101: =A98+1 -> 22 | B101: Operating Capital Levy | D101: 0 | E101: 0 | F101: 0 | G101: 0 | H101: 0 | I101: =SUM(D101:H101) -> 0
A102: =A101+1 -> 23 | B102: Equity Levy | D102: 0 | E102: 0 | F102: 0 | G102: 0 | H102: 0 | I102: =SUM(D102:H102) -> 0
A103: =A102+1 -> 24 | B103: Transition Levy | D103: 0 | E103: 0 | F103: 0 | G103: 0 | H103: 0 | I103: =SUM(D103:H103) -> 0
A104: =A103+1 -> 25 | B104: Q Comp | D104: 0 | E104: 0 | F104: 0 | G104: 0 | H104: 0 | I104: =SUM(D104:H104) -> 0
A105: =A104+1 -> 26 | B105: Referendum Levy | D105: 351087875 | E105: 0 | F105: 0 | G105: 0 | H105: 0 | I105: =SUM(D105:H105) -> 351087875
A107: =A105+1 -> 27 | B107: TOTAL LEVY | D107: =SUM(D101:D105) -> 351087875 | E107: =SUM(E101:E105) -> 0 | F107: =SUM(F101:F105) -> 0 | G107: =SUM(G101:G105) -> 0 | H107: =SUM(H101:H105) -> 0 | I107: =SUM(I101:I105) -> 351087875
B109: AID ENTITLEMENTS
A110: =A107+1 -> 28 | B110: Basic | D110: =D76 -> 4330167150 | E110: =E76 -> 0 | F110: =F76 -> 0 | G110: =G76 -> 73408127 | H110: =H76 -> 0 | I110: =SUM(D110:H110) -> 4403575277
A111: =A110+1 -> 29 | B111: Gifted & Talented | D111: =D77 -> 0 | E111: =E77 -> 0 | F111: =F77 -> 0 | G111: =G77 -> 0 | H111: =H77 -> 0 | I111: =SUM(D111:H111) -> 0
A112: =A111+1 -> 30 | B112: Extended time | D112: =D78 -> 49465489 | E112: =E78 -> 0 | F112: =F78 -> 0 | G112: =G78 -> 886061 | H112: =H78 -> 0 | I112: =SUM(D112:H112) -> 50351550
B113: Basic Skills:
A114: =A112+1 -> 31 | C114: Compensatory | D114: =D80 -> 235489836 | E114: =E80 -> 0 | F114: =F80 -> 0 | G114: =G80 -> 13657118 | H114: =H80 -> 0 | I114: =SUM(D114:H114) -> 249146954
A115: =A114+1 -> 32 | C115: LEP | D115: =D81 -> 27431166 | E115: =E81 -> 0 | F115: =F81 -> 0 | G115: =G81 -> 1387547 | H115: =H81 -> 0 | I115: =SUM(D115:H115) -> 28818713
A116: =A115+1 -> 33 | C116: LEP Concentration | D116: =D82 -> 6822038 | E116: =E82 -> 0 | F116: =F82 -> 0 | G116: =G82 -> 454720 | H116: =H82 -> 0 | I116: =SUM(D116:H116) -> 7276758
...

Sheet FY 2005
A1: FY 2005: FINAL
A3: FEBRUARY 2007 FORECAST | D3: School District | E3: New Refer | F3: SD Fudge | G3: Charter Sch | H3: CH Fudge | I3: Total
A5: 1 | B5: AMCPU | D5: ='Pupil Data'!C38 -> 933497 | E5: 0 | F5: ='Pupil Data'!D38 -> 0 | G5: ='Pupil Data'!E38 -> 19538 | H5: ='Pupil Data'!F38 -> 0 | I5: =SUM(D5:H5) -> 953035
B7: REVENUES
A8: =A5+1 -> 2 | B8: Basic | D8: 4295078866 | E8: 0 | F8: 0 | G8: 89894982 | H8: 0 | I8: =SUM(D8:H8) -> 4384973848
A9: =A8+1 -> 3 | B9: Gifted & Talented | D9: 0 | E9: 0 | F9: 0 | G9: 0 | H9: 0 | I9: =SUM(D9:H9) -> 0
A10: =A9+1 -> 4 | B10: Extended time | D10: 51404903 | E10: 0 | F10: 0 | G10: 922454 | H10: 0 | I10: =SUM(D10:H10) -> 52327357
B11: Basic Skills:
A12: =A10+1 -> 5 | C12: Compensatory | D12: 2.4805985e+08 | E12: 0 | F12: 0 | G12: 17014654 | H12: 0 | I12: =SUM(D12:H12) -> 2.650745e+08
A13: =A12+1 -> 6 | C13: LEP | D13: 27623554 | E13: 0 | F13: 0 | G13: 1854167 | H13: 0 | I13: =SUM(D13:H13) -> 29477721
A14: =A13+1 -> 7 | C14: LEP Concentration | D14: 6850350 | E14: 0 | F14: 0 | G14: 583935 | H14: 0 | I14: =SUM(D14:H14) -> 7434285
A15: =A14+1 -> 8 | B15: Sparsity | D15: 17189203 | E15: 0 | F15: 0 | G15: 359446 | H15: 0 | I15: =SUM(D15:H15) -> 17548649
A16: =A15+1 -> 9 | B16: Transport Sparsity | D16: 55015180 | E16: 0 | F16: 0 | G16: 496015 | H16: 0 | I16: =SUM(D16:H16) -> 55511195
A17: =A16+1 -> 10 | B17: Training & Experience | D17: 12612785 | E17: 0 | F17: 0 | G17: 264033 | H17: 0 | I17: =SUM(D17:H17) -> 12876818
A18: =A17+1 -> 11 | B18: Late Contract Penalty | D18: 0 | E18: 0 | F18: 0 | G18: 0 | H18: 0 | I18: =SUM(D18:H18) -> 0
A19: =A18+1 -> 12 | B19: Operating Capital | D19: 189726063 | E19: 0 | F19: 0 | G19: 3971018 | H19: 0 | I19: =SUM(D19:H19) -> 193697081
A20: =A19+1 -> 13 | B20: Equity | D20: 40875645 | E20: 0 | F20: 0 | G20: 855592 | H20: 0 | I20: =SUM(D20:H20) -> 41731237
A21: =A20+1 -> 14 | B21: Transition | D21: 30347062 | E21: 0 | F21: 0 | G21: 979547 | H21: 0 | I21: =SUM(D21:H21) -> 31326609
A22: =A21+1 -> 15 | B22: Q Comp | D22: 0 | E22: 0 | F22: 0 | G22: 0 | H22: 0 | I22: =SUM(D22:H22) -> 0
A23: =A22+1 -> 16 | B23: Referendum Revenue | D23: 504721085 | E23: =E58 -> 0 | F23: 0 | G23: 0 | H23: 0 | I23: =SUM(D23:H23) -> 504721085
B24: Alternative Attendance Adj:
A25: =A23+1 -> 17 | C25: Open Enroll/Charter Refer | D25: -3408464.9 | E25: 0 | F25: 0 | G25: 2318501 | H25: 0 | I25: =SUM(D25:H25) -> -1089963.9
A26: =A25+1 -> 18 | C26: Charter Basic Transport | D26: =2300872-D28 -> 1987072 | E26: 0 | F26: 0 | G26: -1987072 | H26: 0 | I26: =SUM(D26:H26) -> 0
A27: =A26+1 -> 19 | C27: Charter Ext TimeTransport | D27: 0 | E27: 0 | F27: 0 | G27: 0 | H27: 0 | I27: =SUM(D27:H27) -> 0
A28: =A27+1 -> 20 | C28: Charter Transport Sparsity | D28: 313800 | E28: 0 | F28: 0 | G28: -313800 | H28: 0 | I28: =SUM(D28:H28) -> 0
A30: =A28+1 -> 21 | B30: TOTAL REVENUE | D30: =SUM(D8:D28) -> 5.478397e+09 | E30: =SUM(E8:E28) -> 0 | F30: =SUM(F8:F28) -> 0 | G30: =SUM(G8:G28) -> 117213472 | H30: =SUM(H8:H28) -> 0 | I30: =SUM(I8:I28) -> 5.5956104e+09
B32: LEVIES
A33: =A30+1 -> 22 | B33: Operating Capital Levy | D33: 40007254 | E33: 0 | F33: 0 | G33: 0 | H33: 0 | I33: =SUM(D33:H33) -> 40007254
A34: =A33+1 -> 23 | B34: Equity Levy | D34: 22380297 | E34: 0 | F34: 0 | G34: 0 | H34: 0 | I34: =SUM(D34:H34) -> 22380297
A35: =A34+1 -> 24 | B35: Transition Levy | D35: 18540609 | E35: 0 | F35: 0 | G35: 0 | H35: 0 | I35: =SUM(D35:H35) -> 18540609
A36: =A35+1 -> 25 | B36: Q Comp | D36: 0 | E36: 0 | F36: 0 | G36: 0 | H36: 0 | I36: =SUM(D36:H36) -> 0
A37: =A36+1 -> 26 | B37: Referendum Levy | D37: 379954471 | E37: 0 | F37: 0 | G37: 0 | H37: 0 | I37: =SUM(D37:H37) -> 379954471
A39: =A37+1 -> 27 | B39: TOTAL LEVY | D39: =SUM(D33:D37) -> 460882631 | E39: =SUM(E33:E37) -> 0 | F39: =SUM(F33:F37) -> 0 | G39: =SUM(G33:G37) -> 0 | H39: =SUM(H33:H37) -> 0 | I39: =SUM(I33:I37) -> 460882631
B41: AID ENTITLEMENTS
A42: =A39+1 -> 28 | B42: Basic | D42: =D8 -> 4295078866 | E42: =E8 -> 0 | F42: =F8 -> 0 | G42: =G8 -> 89894982 | H42: =H8 -> 0 | I42: =SUM(D42:H42) -> 4384973848
A43: =A42+1 -> 29 | B43: Gifted & Talented | D43: =D9 -> 0 | E43: =E9 -> 0 | F43: =F9 -> 0 | G43: =G9 -> 0 | H43: =H9 -> 0 | I43: =SUM(D43:H43) -> 0
A44: =A43+1 -> 30 | B44: Extended time | D44: =D10 -> 51404903 | E44: =E10 -> 0 | F44: =F10 -> 0 | G44: =G10 -> 922454 | H44: =H10 -> 0 | I44: =SUM(D44:H44) -> 52327357
B45: Basic Skills:
A46: =A44+1 -> 31 | C46: Compensatory | D46: =D12 -> 2.4805985e+08 | E46: =E12 -> 0 | F46: =F12 -> 0 | G46: =G12 -> 17014654 | H46: =H12 -> 0 | I46: =SUM(D46:H46) -> 2.650745e+08
A47: =A46+1 -> 32 | C47: LEP | D47: =D13 -> 27623554 | E47: =E13 -> 0 | F47: =F13 -> 0 | G47: =G13 -> 1854167 | H47: =H13 -> 0 | I47: =SUM(D47:H47) -> 29477721
A48: =A47+1 -> 33 | C48: LEP Concentration | D48: =D14 -> 6850350 | E48: =E14 -> 0 | F48: =F14 -> 0 | G48: =G14 -> 583935 | H48: =H14 -> 0 | I48: =SUM(D48:H48) -> 7434285
A49: =A48+1 -> 34 | B49: Sparsity | D49: =D15 -> 17189203 | E49: =E15 -> 0 | F49: =F15 -> 0 | G49: =G15 -> 359446 | H49: =H15 -> 0 | I49: =SUM(D49:H49) -> 17548649
A50: =A49+1 -> 35 | B50: Transport Sparsity | D50: =D16 -> 55015180 | E50: =E16 -> 0 | F50: =F16 -> 0 | G50: =G16 -> 496015 | H50: =H16 -> 0 | I50: =SUM(D50:H50) -> 55511195
A51: =A50+1 -> 36 | B51: Training & Experience | D51: =D17 -> 12612785 | E51: =E17 -> 0 | F51: =F17 -> 0 | G51: =G17 -> 264033 | H51: =H17 -> 0 | I51: =SUM(D51:H51) -> 12876818
A52: =A51+1 -> 37 | B52: Late Contract Penalty | D52: =D18 -> 0 | E52: =E18 -> 0 | F52: =F18 -> 0 | G52: =G18 -> 0 | H52: =H18 -> 0 | I52: =SUM(D52:H52) -> 0
A53: =A52+1 -> 38 | B53: Operating Capital | D53: =D19-D33 -> 149718809 | E53: =E19-E33 -> 0 | F53: =F19-F33 -> 0 | G53: =G19-G33 -> 3971018 | H53: =H19-H33 -> 0 | I53: =SUM(D53:H53) -> 153689827
A54: =A53+1 -> 39 | B54: Equity | D54: =D20-D34 -> 18495348 | E54: =E20-E34 -> 0 | F54: =F20-F34 -> 0 | G54: =G20-G34 -> 855592 | H54: =H20-H34 -> 0 | I54: =SUM(D54:H54) -> 19350940
A55: =A54+1 -> 40 | B55: Transition | D55: =D21-D35 -> 11806453 | E55: =E21-E35 -> 0 | F55: =F21-F35 -> 0 | G55: =G21-G35 -> 979547 | H55: =H21-H35 -> 0 | I55: =SUM(D55:H55) -> 12786000
A56: =A55+1 -> 41 | B56: Q Comp | D56: =D22-D36 -> 0 | E56: =E22-E36 -> 0 | F56: =F22-F36 -> 0 | G56: =G22-G36 -> 0 | H56: =H22-H36 -> 0 | I56: =SUM(D56:H56) -> 0
A57: =A56+1 -> 42 | B57: Referendum Equalization Aid | D57: =D23-D37-D58 -> 116067762 | E57: =E23-E37-E58 -> 0 | F57: =F23-F37-F58 -> 0 | G57: =G23-G37-G58 -> 0 | H57: =H23-H37-H58 -> 0 | I57: =SUM(D57:H57) -> 116067762
A58: =A57+1 -> 43 | B58: Tax Base Replacement Aid | D58: 8698852 | E58: 0 | F58: 0 | G58: 0 | H58: 0 | I58: =SUM(D58:H58) -> 8698852
B59: Alternative Attendance Adj:
A60: =A58+1 -> 44 | C60: Open Enroll/Charter Refer | D60: =D25 -> -3408464.9 | E60: =E25 -> 0 | F60: =F25 -> 0 | G60: =G25 -> 2318501 | H60: =H25 -> 0 | I60: =SUM(D60:H60) -> -1089963.9
A61: =A60+1 -> 45 | C61: Charter Basic Transport | D61: =D26 -> 1987072 | E61: =E26 -> 0 | F61: =F26 -> 0 | G61: =G26 -> -1987072 | H61: =H26 -> 0 | I61: =SUM(D61:H61) -> 0
A62: =A61+1 -> 46 | C62: Charter Ext TimeTransport | D62: =D27 -> 0 | E62: =E27 -> 0 | F62: =F27 -> 0 | G62: =G27 -> 0 | H62: =H27 -> 0 | I62: =SUM(D62:H62) -> 0
A63: =A62+1 -> 47 | C63: Charter Transport Sparsity | D63: =D28 -> 313800 | E63: =E28 -> 0 | F63: =F28 -> 0 | G63: =G28 -> -313800 | H63: =H28 -> 0 | I63: =SUM(D63:H63) -> 0
A65: =A63+1 -> 48 | B65: TOTAL AID ENTITLEMENT | D65: =SUM(D42:D63) -> 5.0175143e+09 | E65: =SUM(E42:E63) -> 0 | F65: =SUM(F42:F63) -> 0 | G65: =SUM(G42:G63) -> 117213472 | H65: =SUM(H42:H63) -> 0 | I65: =SUM(I42:I63) -> 5.1347278e+09
A66: =A65+1 -> 49 | B66: General Ed Entitlement | D66: =D65-D58 -> 5.0088155e+09 | E66: =E65-E58 -> 0 | F66: =F65-F58 -> 0 | G66: =G65-G58 -> 117213472 | H66: =H65-H58 -> 0 | I66: =I65-I58 -> 5.1260289e+09
A67: =A66+1 -> 50 | B67: Tax Base Replacement Entitlement | D67: =D58 -> 8698852 | E67: =E58 -> 0 | F67: =F58 -> 0 | G67: =G58 -> 0 | H67: =H58 -> 0 | I67: =I58 -> 8698852
A69: =A67+1 -> 51 | B69: TRA Reduction | D69: -45775518 | E69: 0 | F69: 0 | G69: -958149 | H69: 0 | I69: =SUM(D69:H69) -> -46733667
A71: FEBRUARY 2007 FORECAST | D71: School District | E71: New Refer | F71: SD Fudge | G71: Charter Sch | H71: CH Fudge | I71: Total
A73: 1 | B73: AMCPU | D73: ='Pupil Data'!C199 -> 933497 | E73: 0 | F73: ='Pupil Data'!D199 -> 0 | G73: ='Pupil Data'!E199 -> 19538 | H73: ='Pupil Data'!F199 -> 0 | I73: =SUM(D73:H73) -> 953035
B75: REVENUES
A76: =A73+1 -> 2 | B76: Basic | D76: 4295078866 | E76: 0 | F76: 0 | G76: 89894982 | H76: 0 | I76: =SUM(D76:H76) -> 4384973848
A77: =A76+1 -> 3 | B77: Gifted & Talented | D77: 0 | E77: 0 | F77: 0 | G77: 0 | H77: 0 | I77: =SUM(D77:H77) -> 0
A78: =A77+1 -> 4 | B78: Extended time | D78: 51404903 | E78: 0 | F78: 0 | G78: 922454 | H78: 0 | I78: =SUM(D78:H78) -> 52327357
B79: Basic Skills:
A80: =A78+1 -> 5 | C80: Compensatory | D80: 2.4805985e+08 | E80: 0 | F80: 0 | G80: 17014654 | H80: 0 | I80: =SUM(D80:H80) -> 2.650745e+08
A81: =A80+1 -> 6 | C81: LEP | D81: 27623554 | E81: 0 | F81: 0 | G81: 1854167 | H81: 0 | I81: =SUM(D81:H81) -> 29477721
A82: =A81+1 -> 7 | C82: LEP Concentration | D82: 6850350 | E82: 0 | F82: 0 | G82: 583935 | H82: 0 | I82: =SUM(D82:H82) -> 7434285
A83: =A82+1 -> 8 | B83: Sparsity | D83: 17189203 | E83: 0 | F83: 0 | G83: 359446 | H83: 0 | I83: =SUM(D83:H83) -> 17548649
A84: =A83+1 -> 9 | B84: Transport Sparsity | D84: 55015180 | E84: 0 | F84: 0 | G84: 496015 | H84: 0 | I84: =SUM(D84:H84) -> 55511195
A85: =A84+1 -> 10 | B85: Training & Experience | D85: 12612785 | E85: 0 | F85: 0 | G85: 264033 | H85: 0 | I85: =SUM(D85:H85) -> 12876818
A86: =A85+1 -> 11 | B86: Late Contract Penalty | D86: 0 | E86: 0 | F86: 0 | G86: 0 | H86: 0 | I86: =SUM(D86:H86) -> 0
A87: =A86+1 -> 12 | B87: Operating Capital | D87: 189726063 | E87: 0 | F87: 0 | G87: 3971018 | H87: 0 | I87: =SUM(D87:H87) -> 193697081
A88: =A87+1 -> 13 | B88: Equity | D88: 40875645 | E88: 0 | F88: 0 | G88: 855592 | H88: 0 | I88: =SUM(D88:H88) -> 41731237
A89: =A88+1 -> 14 | B89: Transition | D89: 30347062 | E89: 0 | F89: 0 | G89: 979547 | H89: 0 | I89: =SUM(D89:H89) -> 31326609
A90: =A89+1 -> 15 | B90: Q Comp | D90: 0 | E90: 0 | F90: 0 | G90: 0 | H90: 0 | I90: =SUM(D90:H90) -> 0
A91: =A90+1 -> 16 | B91: Referendum Revenue | D91: 504721085 | E91: =E126 -> 0 | F91: 0 | G91: 0 | H91: 0 | I91: =SUM(D91:H91) -> 504721085
B92: Alternative Attendance Adj:
A93: =A91+1 -> 17 | C93: Open Enroll/Charter Refer | D93: -3408464.9 | E93: 0 | F93: 0 | G93: 2318501 | H93: 0 | I93: =SUM(D93:H93) -> -1089963.9
A94: =A93+1 -> 18 | C94: Charter Basic Transport | D94: =2300872-D96 -> 1987072 | E94: 0 | F94: 0 | G94: -1987072 | H94: 0 | I94: =SUM(D94:H94) -> 0
A95: =A94+1 -> 19 | C95: Charter Ext TimeTransport | D95: 0 | E95: 0 | F95: 0 | G95: 0 | H95: 0 | I95: =SUM(D95:H95) -> 0
A96: =A95+1 -> 20 | C96: Charter Transport Sparsity | D96: 313800 | E96: 0 | F96: 0 | G96: -313800 | H96: 0 | I96: =SUM(D96:H96) -> 0
A98: =A96+1 -> 21 | B98: TOTAL REVENUE | D98: =SUM(D76:D96) -> 5.478397e+09 | E98: =SUM(E76:E96) -> 0 | F98: =SUM(F76:F96) -> 0 | G98: =SUM(G76:G96) -> 117213472 | H98: =SUM(H76:H96) -> 0 | I98: =SUM(I76:I96) -> 5.5956104e+09
B100: LEVIES
A101: =A98+1 -> 22 | B101: Operating Capital Levy | D101: 40007254 | E101: 0 | F101: 0 | G101: 0 | H101: 0 | I101: =SUM(D101:H101) -> 40007254
A102: =A101+1 -> 23 | B102: Equity Levy | D102: 22380297 | E102: 0 | F102: 0 | G102: 0 | H102: 0 | I102: =SUM(D102:H102) -> 22380297
A103: =A102+1 -> 24 | B103: Transition Levy | D103: 18540609 | E103: 0 | F103: 0 | G103: 0 | H103: 0 | I103: =SUM(D103:H103) -> 18540609
A104: =A103+1 -> 25 | B104: Q Comp | D104: 0 | E104: 0 | F104: 0 | G104: 0 | H104: 0 | I104: =SUM(D104:H104) -> 0
A105: =A104+1 -> 26 | B105: Referendum Levy | D105: 379954471 | E105: 0 | F105: 0 | G105: 0 | H105: 0 | I105: =SUM(D105:H105) -> 379954471
A107: =A105+1 -> 27 | B107: TOTAL LEVY | D107: =SUM(D101:D105) -> 460882631 | E107: =SUM(E101:E105) -> 0 | F107: =SUM(F101:F105) -> 0 | G107: =SUM(G101:G105) -> 0 | H107: =SUM(H101:H105) -> 0 | I107: =SUM(I101:I105) -> 460882631
B109: AID ENTITLEMENTS
A110: =A107+1 -> 28 | B110: Basic | D110: =D76 -> 4295078866 | E110: =E76 -> 0 | F110: =F76 -> 0 | G110: =G76 -> 89894982 | H110: =H76 -> 0 | I110: =SUM(D110:H110) -> 4384973848
A111: =A110+1 -> 29 | B111: Gifted & Talented | D111: =D77 -> 0 | E111: =E77 -> 0 | F111: =F77 -> 0 | G111: =G77 -> 0 | H111: =H77 -> 0 | I111: =SUM(D111:H111) -> 0
A112: =A111+1 -> 30 | B112: Extended time | D112: =D78 -> 51404903 | E112: =E78 -> 0 | F112: =F78 -> 0 | G112: =G78 -> 922454 | H112: =H78 -> 0 | I112: =SUM(D112:H112) -> 52327357
B113: Basic Skills:
A114: =A112+1 -> 31 | C114: Compensatory | D114: =D80 -> 2.4805985e+08 | E114: =E80 -> 0 | F114: =F80 -> 0 | G114: =G80 -> 17014654 | H114: =H80 -> 0 | I114: =SUM(D114:H114) -> 2.650745e+08
A115: =A114+1 -> 32 | C115: LEP | D115: =D81 -> 27623554 | E115: =E81 -> 0 | F115: =F81 -> 0 | G115: =G81 -> 1854167 | H115: =H81 -> 0 | I115: =SUM(D115:H115) -> 29477721
A116: =A115+1 -> 33 | C116: LEP Concentration | D116: =D82 -> 6850350 | E116: =E82 -> 0 | F116: =F82 -> 0 | G116: =G82 -> 583935 | H116: =H82 -> 0 | I116: =SUM(D116:H116) -> 7434285
...

Sheet SUMMARY-Mike's Special Pupil
A1: SUMMARY FOR SPECIAL PUPIL AID: FEBRRUARY 2008 CSA
A3: FEBRUARY 2008 FORECAST | D3: FY 2003 | E3: FY 2004 | F3: FY 2005 | G3: FY 2006 | H3: FY 2007 | I3: FY 2008 | J3: FY 2009 | K3: FY 2010 | L3: FY 2011
A5: 1 | B5: AMCPU | D5: ='FY 2003'!I5 -> 962146 | E5: ='FY 2004'!I5 -> 957096 | F5: ='FY 2005'!I5 -> 953035 | G5: ='FY 2006'!I5 -> 953041 | H5: ='FY 2007'!I5 -> 953288 | I5: ='FY 2008'!I5 -> 953432 | J5: ='FY 2009'!$I5 -> 948587 | K5: ='FY 2010'!$J5 -> 947210 | L5: ='FY 2011'!$J5 -> 948097
B7: REVENUES
A8: =A5+1 -> 2 | B8: Basic | D8: ='FY 2003'!I8 -> 4490060320 | E8: ='FY 2004'!I8 -> 4403575277 | F8: ='FY 2005'!I8 -> 4384973848 | G8: ='FY 2006'!I8 -> 4558383720 | H8: ='FY 2007'!I8 -> 4741676895 | I8: ='FY 2008'!I8 -> 4837724471 | J8: ='FY 2009'!$I8 -> 4.8605747e+09 | K8: ='FY 2010'!$J8 -> 4853494920 | L8: ='FY 2011'!$J8 -> 4858048057
A9: =A8+1 -> 3 | B9: Gifted & Talented | D9: ='FY 2003'!I9 -> 0 | E9: ='FY 2004'!I9 -> 0 | F9: ='FY 2005'!I9 -> 0 | G9: ='FY 2006'!I9 -> 3812154 | H9: ='FY 2007'!I9 -> 8579632 | I9: ='FY 2008'!I9 -> 11441209 | J9: ='FY 2009'!$I10 -> 11383079 | K9: ='FY 2010'!$J9 -> 11365913 | L9: ='FY 2011'!$J9 -> 11377163
A10: =A9+1 -> 4 | B10: Extended time | D10: ='FY 2003'!I10 -> 0 | E10: ='FY 2004'!I10 -> 50351550 | F10: ='FY 2005'!I10 -> 52327357 | G10: ='FY 2006'!I10 -> 52766200 | H10: ='FY 2007'!I10 -> 55436989 | I10: ='FY 2008'!I10 -> 59590817 | J10: ='FY 2009'!$I11 -> 60995641 | K10: ='FY 2010'!$J10 -> 64565373 | L10: ='FY 2011'!$J10 -> 69073025
B11: Basic Skills:
A12: =A10+1 -> 5 | C12: Compensatory | D12: ='FY 2003'!I12 -> 262694686 | E12: ='FY 2004'!I12 -> 249146954 | F12: ='FY 2005'!I12 -> 2.650745e+08 | G12: ='FY 2006'!I12 -> 292547478 | H12: ='FY 2007'!I12 -> 315471905 | I12: ='FY 2008'!I12 -> 333928094 | J12: ='FY 2009'!$I13 -> 3.4851069e+08 | K12: ='FY 2010'!$J12 -> 361157268 | L12: ='FY 2011'!$J12 -> 414260438
A13: =A12+1 -> 6 | C13: LEP | D13: ='FY 2003'!I13 -> 36857227 | E13: ='FY 2004'!I13 -> 28818713 | F13: ='FY 2005'!I13 -> 29477721 | G13: ='FY 2006'!I13 -> 30912658 | H13: ='FY 2007'!I13 -> 31474254 | I13: ='FY 2008'!I13 -> 32316781 | J13: ='FY 2009'!$I14 -> 32058187 | K13: ='FY 2010'!$J13 -> 31807937 | L13: ='FY 2011'!$J13 -> 31673120
A14: =A13+1 -> 7 | C14: LEP Concentration | D14: ='FY 2003'!I14 -> 9779108 | E14: ='FY 2004'!I14 -> 7276758 | F14: ='FY 2005'!I14 -> 7434285 | G14: ='FY 2006'!I14 -> 7883168 | H14: ='FY 2007'!I14 -> 8057613 | I14: ='FY 2008'!I14 -> 8306508 | J14: ='FY 2009'!$I15 -> 8316835 | K14: ='FY 2010'!$J14 -> 8258276 | L14: ='FY 2011'!$J14 -> 8387524
A15: =A14+1 -> 8 | B15: Sparsity | D15: ='FY 2003'!I15 -> 16471551 | E15: ='FY 2004'!I15 -> 16909578 | F15: ='FY 2005'!I15 -> 17548649 | G15: ='FY 2006'!I15 -> 18853061 | H15: ='FY 2007'!I15 -> 20254233 | I15: ='FY 2008'!I15 -> 21637534 | J15: ='FY 2009'!$I16 -> 22898807 | K15: ='FY 2010'!$J15 -> 23368633 | L15: ='FY 2011'!$J15 -> 23511161
A16: =A15+1 -> 9 | B16: Transport Sparsity | D16: ='FY 2003'!I16 -> 56478364 | E16: ='FY 2004'!I16 -> 55913098 | F16: ='FY 2005'!I16 -> 55511195 | G16: ='FY 2006'!I16 -> 57332807 | H16: ='FY 2007'!I16 -> 59221788 | I16: ='FY 2008'!I16 -> 60083765 | J16: ='FY 2009'!$I17 -> 60159097 | K16: ='FY 2010'!$J16 -> 59833229 | L16: ='FY 2011'!$J16 -> 60371479
A17: =A16+1 -> 10 | B17: Training & Experience | D17: ='FY 2003'!I17 -> 25114308 | E17: ='FY 2004'!I17 -> 18869558 | F17: ='FY 2005'!I17 -> 12876818 | G17: ='FY 2006'!I17 -> 8213502 | H17: ='FY 2007'!I17 -> 4354428 | I17: ='FY 2008'!I17 -> 2146056 | J17: ='FY 2009'!$I18 -> 1207447.6 | K17: ='FY 2010'!$J17 -> 675850 | L17: ='FY 2011'!$J17 -> 373228
A18: =A17+1 -> 11 | B18: Late Contract Penalty | D18: ='FY 2003'!I18 -> 0 | E18: ='FY 2004'!I18 -> 0 | F18: ='FY 2005'!I18 -> 0 | G18: ='FY 2006'!I18 -> -344932 | H18: ='FY 2007'!I18 -> 0 | I18: ='FY 2008'!I18 -> -730496 | J18: ='FY 2009'!$I19 -> 0 | K18: ='FY 2010'!$J18 -> -2507070 | L18: ='FY 2011'!$J18 -> 0
A19: =A18+1 -> 12 | B19: Operating Capital | D19: ='FY 2003'!I19 -> 198438434 | E19: ='FY 2004'!I19 -> 194217096 | F19: ='FY 2005'!I19 -> 193697081 | G19: ='FY 2006'!I19 -> 194018388 | H19: ='FY 2007'!I19 -> 194117024 | I19: ='FY 2008'!I19 -> 194635565 | J19: ='FY 2009'!$I20 -> 1.9429911e+08 | K19: ='FY 2010'!$J20 -> 194409760 | L19: ='FY 2011'!$J19 -> 194612210
A20: =A19+1 -> 13 | B20: Equity | D20: ='FY 2003'!I20 -> 34642490 | E20: ='FY 2004'!I20 -> 32112369 | F20: ='FY 2005'!I20 -> 41731237 | G20: ='FY 2006'!I20 -> 50999434 | H20: ='FY 2007'!I20 -> 94274069 | I20: ='FY 2008'!I20 -> 95708805 | J20: ='FY 2009'!$I21 -> 93361990 | K20: ='FY 2010'!$J21 -> 92518770 | L20: ='FY 2011'!$J20 -> 92334012
A21: =A20+1 -> 14 | B21: Transition | D21: ='FY 2003'!I21 -> 0 | E21: ='FY 2004'!I21 -> 31986524 | F21: ='FY 2005'!I21 -> 31326609 | G21: ='FY 2006'!I21 -> 31033742 | H21: ='FY 2007'!I21 -> 30462514 | I21: ='FY 2008'!I21 -> 30143318 | J21: ='FY 2009'!$I22 -> 29711997 | K21: ='FY 2010'!$J22 -> 29453149 | L21: ='FY 2011'!$J21 -> 29215443
A22: =A21+1 -> 15 | B22: Q Comp | D22: ='FY 2003'!I22 -> 0 | E22: ='FY 2004'!I22 -> 0 | F22: ='FY 2005'!I22 -> 0 | G22: ='FY 2006'!I22 -> 16348850 | H22: ='FY 2007'!I22 -> 48603714 | I22: ='FY 2008'!I22 -> 60763648 | J22: ='FY 2009'!$I23 -> 63348360 | K22: ='FY 2010'!$J23 -> 58291520 | L22: ='FY 2011'!$J22 -> 63056932
A23: =A22+1 -> 16 | B23: Referendum Revenue | D23: ='FY 2003'!I23 -> 291708358 | E23: ='FY 2004'!I23 -> 426336542 | F23: ='FY 2005'!I23 -> 504721085 | G23: ='FY 2006'!I23 -> 534314512 | H23: ='FY 2007'!I23 -> 598966155 | I23: ='FY 2008'!I23 -> 644192179 | J23: ='FY 2009'!$I24 -> 7.2056718e+08 | K23: ='FY 2010'!$J24 -> 781675140 | L23: ='FY 2011'!$J23 -> 804832265
B24: Alternative Attendance Adj:
A25: =A23+1 -> 17 | C25: Open Enroll/Charter Refer | D25: ='FY 2003'!I25 -> 1341221 | E25: ='FY 2004'!I25 -> -679857 | F25: ='FY 2005'!I25 -> -1089963.9 | G25: ='FY 2006'!I25 -> -895441.79 | H25: ='FY 2007'!I25 -> -885672 | I25: ='FY 2008'!I25 -> -181964 | J25: ='FY 2009'!$I26 -> 262096 | K25: ='FY 2010'!$J26 -> 607348 | L25: ='FY 2011'!$J25 -> 657596
A26: =A25+1 -> 18 | C26: Charter Basic Transport | D26: ='FY 2003'!I26 -> -1804253 | E26: ='FY 2004'!I26 -> 1059 | F26: ='FY 2005'!I26 -> 0 | G26: ='FY 2006'!I26 -> 0.44 | H26: ='FY 2007'!I26 -> 0 | I26: ='FY 2008'!I26 -> 0 | J26: ='FY 2009'!$I27 -> -0.0099999995 | K26: ='FY 2010'!$J27 -> 0 | L26: ='FY 2011'!$J26 -> 32
A27: =A26+1 -> 19 | C27: Charter Ext TimeTransport | D27: ='FY 2003'!I27 -> 0 | E27: ='FY 2004'!I27 -> 0 | F27: ='FY 2005'!I27 -> 0 | G27: ='FY 2006'!I27 -> -0.18 | H27: ='FY 2007'!I27 -> 0 | I27: ='FY 2008'!I27 -> 0 | J27: ='FY 2009'!$I28 -> 0 | K27: ='FY 2010'!$J28 -> 0 | L27: ='FY 2011'!$J27 -> 777
A28: =A27+1 -> 20 | C28: Charter Transport Sparsity | D28: ='FY 2003'!I28 -> 0 | E28: ='FY 2004'!I28 -> 0 | F28: ='FY 2005'!I28 -> 0 | G28: ='FY 2006'!I28 -> 0.44 | H28: ='FY 2007'!I28 -> 0 | I28: ='FY 2008'!I28 -> 0 | J28: ='FY 2009'!$I29 -> -0.01 | K28: ='FY 2010'!$J29 -> 4 | L28: ='FY 2011'!$J28 -> 165
A29: =A28+1 -> 21 | C29: Faribault Alternative Attend Adj | D29: 0 | E29: 0 | F29: 0 | G29: ='FY 2006'!I29 -> 0 | H29: ='FY 2007'!$I29 -> -398 | I29: ='FY 2008'!$I29 -> -355.18 | J29: ='FY 2009'!$I30 -> -461.16 | K29: ='FY 2010'!$J30 -> -449 | L29: ='FY 2011'!$J29 -> -195
A31: =A29+1 -> 22 | B31: TOTAL REVENUE | D31: =SUM(D8:D29) -> 5421781814 | E31: =SUM(E8:E29) -> 5514835219 | F31: =SUM(F8:F29) -> 5.5956104e+09 | G31: =SUM(G8:G29) -> 5.8561793e+09 | H31: =SUM(H8:H29) -> 6210065143 | I31: =SUM(I8:I29) -> 6.3917059e+09 | J31: =SUM(J8:J29) -> 6.5076547e+09 | K31: =SUM(K8:K29) -> 6568975571 | L31: =SUM(L8:L29) -> 6661784432
B33: LEVIES
A34: =A31+1 -> 23 | B34: Operating Capital Levy | D34: ='FY 2003'!I33 -> 0 | E34: ='FY 2004'!I33 -> 0 | F34: ='FY 2005'!I33 -> 40007254 | G34: ='FY 2006'!I34 -> 44268155 | H34: ='FY 2007'!I34 -> 101934454 | I34: ='FY 2008'!I34 -> 111830374 | J34: ='FY 2009'!$I35 -> 1.2125304e+08 | K34: ='FY 2010'!$J35 -> 124276595 | L34: ='FY 2011'!$J34 -> 124623859
A35: =A34+1 -> 24 | B35: Equity Levy | D35: ='FY 2003'!I34 -> 0 | E35: ='FY 2004'!I34 -> 0 | F35: ='FY 2005'!I34 -> 22380297 | G35: ='FY 2006'!I35 -> 25083314 | H35: ='FY 2007'!I35 -> 63740065 | I35: ='FY 2008'!I35 -> 70604296 | J35: ='FY 2009'!$I36 -> 73701614 | K35: ='FY 2010'!$J36 -> 75798743 | L35: ='FY 2011'!$J35 -> 76305360
A36: =A35+1 -> 25 | B36: Transition Levy | D36: ='FY 2003'!I35 -> 0 | E36: ='FY 2004'!I35 -> 0 | F36: ='FY 2005'!I35 -> 18540609 | G36: ='FY 2006'!I36 -> 20383544 | H36: ='FY 2007'!I36 -> 21830489 | I36: ='FY 2008'!I36 -> 23010395 | J36: ='FY 2009'!$I37 -> 24292897 | K36: ='FY 2010'!$J37 -> 25195534 | L36: ='FY 2011'!$J36 -> 25244531
A37: =A36+1 -> 26 | B37: Q Comp | D37: ='FY 2003'!I36 -> 0 | E37: ='FY 2004'!I36 -> 0 | F37: ='FY 2005'!I36 -> 0 | G37: ='FY 2006'!I37 -> 0 | H37: ='FY 2007'!I37 -> 9695468 | I37: ='FY 2008'!I37 -> 12779741 | J37: ='FY 2009'!$I38 -> 13353371 | K37: ='FY 2010'!$J38 -> 16807134 | L37: ='FY 2011'!$J37 -> 18158004
A38: =A37+1 -> 27 | B38: Referendum Levy | D38: ='FY 2003'!I37 -> 224945858 | E38: ='FY 2004'!I37 -> 351087875 | F38: ='FY 2005'!I37 -> 379954471 | G38: ='FY 2006'!I38 -> 410867894 | H38: ='FY 2007'!I38 -> 482421730 | I38: ='FY 2008'!I38 -> 540184289 | J38: ='FY 2009'!$I39 -> 6.3533353e+08 | K38: ='FY 2010'!$J39 -> 712334239 | L38: ='FY 2011'!$J38 -> 737629396
A40: =A38+1 -> 28 | B40: TOTAL LEVY | D40: =SUM(D34:D38) -> 224945858 | E40: =SUM(E34:E38) -> 351087875 | F40: =SUM(F34:F38) -> 460882631 | G40: =SUM(G34:G38) -> 500602907 | H40: =SUM(H34:H38) -> 679622206 | I40: =SUM(I34:I38) -> 758409095 | J40: =SUM(J34:J38) -> 8.6793445e+08 | K40: =SUM(K34:K38) -> 954412245 | L40: =SUM(L34:L38) -> 981961150
B42: AID ENTITLEMENTS
A43: =A40+1 -> 29 | B43: Basic | D43: =D8 -> 4490060320 | E43: =E8 -> 4403575277 | F43: =F8 -> 4384973848 | G43: =G8 -> 4558383720 | H43: =H8 -> 4741676895 | I43: =I8 -> 4837724471 | J43: =J8 -> 4.8605747e+09 | K43: =K8 -> 4853494920 | L43: =L8 -> 4858048057
A44: =A43+1 -> 30 | B44: Gifted & Talented | D44: =D9 -> 0 | E44: =E9 -> 0 | F44: =F9 -> 0 | G44: =G9 -> 3812154 | H44: =H9 -> 8579632 | I44: =I9 -> 11441209 | J44: =J9 -> 11383079 | K44: =K9 -> 11365913 | L44: =L9 -> 11377163
A45: =A44+1 -> 31 | B45: Extended time | D45: =D10 -> 0 | E45: =E10 -> 50351550 | F45: =F10 -> 52327357 | G45: =G10 -> 52766200 | H45: =H10 -> 55436989 | I45: =I10 -> 59590817 | J45: =J10 -> 60995641 | K45: =K10 -> 64565373 | L45: =L10 -> 69073025
B46: Basic Skills:
A47: =A45+1 -> 32 | C47: Compensatory | D47: =D12 -> 262694686 | E47: =E12 -> 249146954 | F47: =F12 -> 2.650745e+08 | G47: =G12 -> 292547478 | H47: =H12 -> 315471905 | I47: =I12 -> 333928094 | J47: =J12 -> 3.4851069e+08 | K47: =K12 -> 361157268 | L47: =L12 -> 414260438
A48: =A47+1 -> 33 | C48: LEP | D48: =D13 -> 36857227 | E48: =E13 -> 28818713 | F48: =F13 -> 29477721 | G48: =G13 -> 30912658 | H48: =H13 -> 31474254 | I48: =I13 -> 32316781 | J48: =J13 -> 32058187 | K48: =K13 -> 31807937 | L48: =L13 -> 31673120
A49: =A48+1 -> 34 | C49: LEP Concentration | D49: =D14 -> 9779108 | E49: =E14 -> 7276758 | F49: =F14 -> 7434285 | G49: =G14 -> 7883168 | H49: =H14 -> 8057613 | I49: =I14 -> 8306508 | J49: =J14 -> 8316835 | K49: =K14 -> 8258276 | L49: =L14 -> 8387524
A50: =A49+1 -> 35 | B50: Sparsity | D50: =D15 -> 16471551 | E50: =E15 -> 16909578 | F50: =F15 -> 17548649 | G50: =G15 -> 18853061 | H50: =H15 -> 20254233 | I50: =I15 -> 21637534 | J50: =J15 -> 22898807 | K50: =K15 -> 23368633 | L50: =L15 -> 23511161
A51: =A50+1 -> 36 | B51: Transport Sparsity | D51: =D16 -> 56478364 | E51: =E16 -> 55913098 | F51: =F16 -> 55511195 | G51: =G16 -> 57332807 | H51: =H16 -> 59221788 | I51: =I16 -> 60083765 | J51: =J16 -> 60159097 | K51: =K16 -> 59833229 | L51: =L16 -> 60371479
A52: =A51+1 -> 37 | B52: Training & Experience | D52: =D17 -> 25114308 | E52: =E17 -> 18869558 | F52: =F17 -> 12876818 | G52: =G17 -> 8213502 | H52: =H17 -> 4354428 | I52: =I17 -> 2146056 | J52: =J17 -> 1207447.6 | K52: =K17 -> 675850 | L52: =L17 -> 373228
A53: =A52+1 -> 38 | B53: Late Contract Penalty | D53: =D18 -> 0 | E53: =E18 -> 0 | F53: =F18 -> 0 | G53: =G18 -> -344932 | H53: =H18 -> 0 | I53: =I18 -> -730496 | J53: =J18 -> 0 | K53: =K18 -> -2507070 | L53: =L18 -> 0
A54: =A53+1 -> 39 | B54: Operating Capital | D54: =D19-D34 -> 198438434 | E54: =E19-E34 -> 194217096 | F54: =F19-F34 -> 153689827 | G54: =G19-G34 -> 149750233 | H54: =H19-H34 -> 92182570 | I54: =I19-I34 -> 82805191 | J54: =J19-J34 -> 73046067 | K54: =K19-K34 -> 70133165 | L54: =L19-L34 -> 69988351
A55: =A54+1 -> 40 | B55: Equity | D55: =D20-D35 -> 34642490 | E55: =E20-E35 -> 32112369 | F55: =F20-F35 -> 19350940 | G55: =G20-G35 -> 25916120 | H55: =H20-H35 -> 30534004 | I55: =I20-I35 -> 25104509 | J55: =J20-J35 -> 19660376 | K55: =K20-K35 -> 16720027 | L55: =L20-L35 -> 16028652
A56: =A55+1 -> 41 | B56: Transition | D56: =D21-D36 -> 0 | E56: =E21-E36 -> 31986524 | F56: =F21-F36 -> 12786000 | G56: =G21-G36 -> 10650198 | H56: =H21-H36 -> 8632025 | I56: =I21-I36 -> 7132923 | J56: =J21-J36 -> 5419100.7 | K56: =K21-K36 -> 4257615 | L56: =L21-L36 -> 3970912
A57: =A56+1 -> 42 | B57: Q Comp | D57: =D22-D37 -> 0 | E57: =E22-E37 -> 0 | F57: =F22-F37 -> 0 | G57: =G22-G37 -> 16348850 | H57: =H22-H37 -> 38908246 | I57: =I22-I37 -> 47983907 | J57: =J22-J37 -> 49994989 | K57: =K22-K37 -> 41484386 | L57: =L22-L37 -> 44898928
A58: =A57+1 -> 43 | B58: Referendum Equalization Aid | D58: =D23-D38-D59 -> 58417206 | E58: =E23-E38-E59 -> 67208298 | F58: =F23-F38-F59 -> 116067762 | G58: =G23-G38-G59 -> 114774019 | H58: =H23-H38-H59 -> 107935161 | I58: =I23-I38-I59 -> 95398626 | J58: =J23-J38-J59 -> 76645863 | K58: =K23-K38-K59 -> 60722235 | L58: =L23-L38-L59 -> 58609687
A59: =A58+1 -> 44 | B59: Tax Base Replacement Aid | D59: ='FY 2003'!I58 -> 8345294 | E59: ='FY 2004'!I58 -> 8040369 | F59: ='FY 2005'!I58 -> 8698852 | G59: ='FY 2006'!I59 -> 8672599 | H59: ='FY 2007'!I59 -> 8609264 | I59: ='FY 2008'!I59 -> 8609264 | J59: ='FY 2009'!$I61 -> 8587791.7 | K59: ='FY 2010'!$J61 -> 8618666 | L59: ='FY 2011'!$J59 -> 8593182
B60: Alternative Attendance Adj:
A61: =A59+1 -> 45 | C61: Open Enroll/Charter Refer | D61: ='FY 2003'!I60 -> 1341221 | E61: ='FY 2004'!I60 -> -679857 | F61: ='FY 2005'!I60 -> -1089963.9 | G61: ='FY 2006'!I61 -> -895441.79 | H61: ='FY 2007'!I61 -> -885672 | I61: ='FY 2008'!I61 -> -181964 | J61: ='FY 2009'!$I63 -> 262096 | K61: ='FY 2010'!$J63 -> 607348 | L61: ='FY 2011'!$J61 -> 657596
A62: =A61+1 -> 46 | C62: Charter Basic Transport | D62: ='FY 2003'!I61 -> -1804253 | E62: ='FY 2004'!I61 -> 1059 | F62: ='FY 2005'!I61 -> 0 | G62: ='FY 2006'!I62 -> 0.44 | H62: ='FY 2007'!I62 -> 0 | I62: ='FY 2008'!I62 -> 0 | J62: ='FY 2009'!$I64 -> -0.0099999995 | K62: ='FY 2010'!$J64 -> 0 | L62: ='FY 2011'!$J62 -> 32
A63: =A62+1 -> 47 | C63: Charter Ext TimeTransport | D63: ='FY 2003'!I62 -> 0 | E63: ='FY 2004'!I62 -> 0 | F63: ='FY 2005'!I62 -> 0 | G63: ='FY 2006'!I63 -> -0.18 | H63: ='FY 2007'!I63 -> 0 | I63: ='FY 2008'!I63 -> 0 | J63: ='FY 2009'!$I65 -> 0 | K63: ='FY 2010'!$J65 -> 0 | L63: ='FY 2011'!$J63 -> 777
A64: =A63+1 -> 48 | C64: Charter Transport Sparsity | D64: ='FY 2003'!I63 -> 0 | E64: ='FY 2004'!I63 -> 0 | F64: ='FY 2005'!I63 -> 0 | G64: ='FY 2006'!I64 -> 0.44 | H64: ='FY 2007'!I64 -> 0 | I64: ='FY 2008'!I64 -> 0 | J64: ='FY 2009'!$I66 -> -0.01 | K64: ='FY 2010'!$J66 -> 4 | L64: ='FY 2011'!$J64 -> 165
A65: =A64+1 -> 49 | C65: Faribault Alternative Attend Adj | D65: 0 | E65: 0 | F65: 0 | G65: ='FY 2006'!I65 -> 0 | H65: ='FY 2007'!$I65 -> -398 | I65: ='FY 2008'!$I65 -> -355.18 | J65: ='FY 2009'!$I67 -> -461.16 | K65: ='FY 2010'!$J67 -> -449 | L65: ='FY 2011'!$J65 -> -195
A67: =A65+1 -> 50 | B67: TOTAL AID ENTITLEMENT | D67: =SUM(D43:D65) -> 5196835956 | E67: =SUM(E43:E65) -> 5163747344 | F67: =SUM(F43:F65) -> 5.1347278e+09 | G67: =SUM(G43:G65) -> 5.3555764e+09 | H67: =SUM(H43:H65) -> 5530442937 | I67: =SUM(I43:I65) -> 5.6332968e+09 | J67: =SUM(J43:J65) -> 5.6397203e+09 | K67: =SUM(K43:K65) -> 5614563326 | L67: =SUM(L43:L65) -> 5679823282
A68: =A67+1 -> 51 | B68: General Ed Entitlement | D68: =D67-D59 -> 5188490662 | E68: =E67-E59 -> 5155706975 | F68: =F67-F59 -> 5.1260289e+09 | G68: =G67-G59 -> 5.3469038e+09 | H68: =H67-H59 -> 5521833673 | I68: =I67-I59 -> 5.6246876e+09 | J68: =J67-J59 -> 5.6311325e+09 | K68: =K67-K59 -> 5605944660 | L68: =L67-L59 -> 5671230100
A69: =A68+1 -> 52 | B69: Tax Base Replacement Entitlement | D69: =D59 -> 8345294 | E69: =E59 -> 8040369 | F69: =F59 -> 8698852 | G69: =G59 -> 8672599 | H69: =H59 -> 8609264 | I69: =I59 -> 8609264 | J69: =J59 -> 8587791.7 | K69: =K59 -> 8618666 | L69: =L59 -> 8593182
A71: =A69+1 -> 53 | B71: TRA Reduction | D71: ='FY 2003'!I69 -> -46570547 | E71: ='FY 2004'!I69 -> -46686661 | F71: ='FY 2005'!I69 -> -46733667 | G71: ='FY 2006'!I71 -> -46807695 | H71: ='FY 2007'!I71 -> -46967505 | I71: ='FY 2008'!I71 -> -30637836 | J71: ='FY 2009'!$I73 -> -30753090 | K71: ='FY 2010'!$J73 -> -30827862 | L71: ='FY 2011'!$J71 -> -30929256
A73: =A71+1 -> 54 | B73: Total Revenue = (22) + (53) = | F73: =F31+F71 -> 5.5488768e+09 | G73: =G31+G71 -> 5.8093716e+09 | H73: =H31+H71 -> 6163097638 | I73: =I31+I71 -> 6.3610681e+09 | J73: =J31+J71 -> 6.4769017e+09 | K73: =K31+K71 -> 6538147709 | L73: =L31+L71 -> 6630855176
A74: =A73+1 -> 55 | B74: Total Aid = (54) - (28) = | F74: =F73-F40 -> 5.0879941e+09 | G74: =G73-G40 -> 5.3087687e+09 | H74: =H73-H40 -> 5483475432 | I74: =I73-I40 -> 5.602659e+09 | J74: =J73-J40 -> 5.6089672e+09 | K74: =K73-K40 -> 5583735464 | L74: =L73-L40 -> 5648894026
A76: =A74+1 -> 56 | B76: Current Year Adjusted Pupil Units | F76: ='Pupil Data'!G24 -> 949765 | G76: ='Pupil Data'!G25 -> 950530 | H76: ='Pupil Data'!G26 -> 950864 | I76: ='Pupil Data'!G27 -> 950173 | J76: ='Pupil Data'!G28 -> 945193 | K76: ='Pupil Data'!G29 -> 944933 | L76: ='Pupil Data'!G30 -> 945855
A78: =A76+1 -> 57 | B78: Aid per Pupil Unit = (55) / (56) = | F78: =ROUND(F74/F76,2) -> 5357.11 | G78: =ROUND(G74/G76,2) -> 5585.06 | H78: =ROUND(H74/H76,2) -> 5766.83 | I78: =ROUND(I74/I76,2) -> 5896.46 | J78: =ROUND(J74/J76,2) -> 5934.2 | K78: =ROUND(K74/K76,2) -> 5909.13 | L78: =ROUND(L74/L76,2) -> 5972.26

Sheet CORRECTED-Mike's Special Pupil
A1: SUMMARY FOR SPECIAL PUPIL AID: FEBRRUARY 2008 CSA
A3: FEBRUARY 2008 FORECAST | D3: FY 2003 | E3: FY 2004 | F3: FY 2006 | G3: FY 2007 | H3: FY 2008 | I3: FY 2009 | J3: FY 2010 | K3: FY 2011 | L3: FY 2012
A5: 1 | B5: AMCPU | D5: ='FY 2003'!I5 -> 962146 | E5: ='FY 2004'!I5 -> 957096 | F5: ='FY 2006'!I5 -> 953041 | G5: ='FY 2007'!I5 -> 953288 | H5: ='FY 2008'!I5 -> 953432 | I5: ='FY 2009'!$I5 -> 948587 | J5: ='FY 2010'!$J5 -> 947210 | K5: ='FY 2011'!$J5 -> 948097
B7: REVENUES
A8: =A5+1 -> 2 | B8: Basic | D8: ='FY 2003'!I8 -> 4490060320 | E8: ='FY 2004'!I8 -> 4403575277 | F8: ='FY 2006'!I8-'FY 2006'!G8-'FY 2006'!H8 -> 4448158911 | G8: ='FY 2007'!I8-'FY 2007'!G8-'FY 2007'!H8 -> 4608596779 | H8: ='FY 2008'!I8-'FY 2008'!G8-'FY 2008'!H8 -> 4676709149 | I8: ='FY 2009'!$I8-'FY 2009'!G8-'FY 2009'!H8 -> 4.6748038e+09 | J8: ='FY 2010'!$J8-'FY 2010'!G8-'FY 2010'!I8 -> 4652117979 | K8: ='FY 2011'!$J8-'FY 2011'!G8-'FY 2011'!I8 -> 4641176290
A9: =A8+1 -> 3 | B9: Gifted & Talented | D9: ='FY 2003'!I9 -> 0 | E9: ='FY 2004'!I9 -> 0 | F9: ='FY 2006'!I9-'FY 2006'!G9-'FY 2006'!H9 -> 3719974 | G9: ='FY 2007'!I9 -> 8579632 | H9: ='FY 2008'!I9 -> 11441209 | I9: ='FY 2009'!$I10 -> 11383079 | J9: ='FY 2010'!$J9 -> 11365913 | K9: ='FY 2011'!$J9 -> 11377163
A10: =A9+1 -> 4 | B10: Extended time | D10: ='FY 2003'!I10 -> 0 | E10: ='FY 2004'!I10 -> 50351550 | F10: ='FY 2006'!I10-'FY 2006'!G10-'FY 2006'!H10 -> 51811953 | G10: ='FY 2007'!I10 -> 55436989 | H10: ='FY 2008'!I10 -> 59590817 | I10: ='FY 2009'!$I11 -> 60995641 | J10: ='FY 2010'!$J10 -> 64565373 | K10: ='FY 2011'!$J10 -> 69073025
B11: Basic Skills:
A12: =A10+1 -> 5 | C12: Compensatory | D12: ='FY 2003'!I12 -> 262694686 | E12: ='FY 2004'!I12 -> 249146954 | F12: ='FY 2006'!I12-'FY 2006'!G12-'FY 2006'!H12 -> 271753985 | G12: ='FY 2007'!I12 -> 315471905 | H12: ='FY 2008'!I12 -> 333928094 | I12: ='FY 2009'!$I13 -> 3.4851069e+08 | J12: ='FY 2010'!$J12 -> 361157268 | K12: ='FY 2011'!$J12 -> 414260438
A13: =A12+1 -> 6 | C13: LEP | D13: ='FY 2003'!I13 -> 36857227 | E13: ='FY 2004'!I13 -> 28818713 | F13: ='FY 2006'!I13-'FY 2006'!G13-'FY 2006'!H13 -> 28357728 | G13: ='FY 2007'!I13 -> 31474254 | H13: ='FY 2008'!I13 -> 32316781 | I13: ='FY 2009'!$I14 -> 32058187 | J13: ='FY 2010'!$J13 -> 31807937 | K13: ='FY 2011'!$J13 -> 31673120
A14: =A13+1 -> 7 | C14: LEP Concentration | D14: ='FY 2003'!I14 -> 9779108 | E14: ='FY 2004'!I14 -> 7276758 | F14: ='FY 2006'!I14-'FY 2006'!G14-'FY 2006'!H14 -> 7045250 | G14: ='FY 2007'!I14 -> 8057613 | H14: ='FY 2008'!I14 -> 8306508 | I14: ='FY 2009'!$I15 -> 8316835 | J14: ='FY 2010'!$J14 -> 8258276 | K14: ='FY 2011'!$J14 -> 8387524
A15: =A14+1 -> 8 | B15: Sparsity | D15: ='FY 2003'!I15 -> 16471551 | E15: ='FY 2004'!I15 -> 16909578 | F15: ='FY 2006'!I15-'FY 2006'!G15-'FY 2006'!H15 -> 18397203 | G15: ='FY 2007'!I15 -> 20254233 | H15: ='FY 2008'!I15 -> 21637534 | I15: ='FY 2009'!$I16 -> 22898807 | J15: ='FY 2010'!$J15 -> 23368633 | K15: ='FY 2011'!$J15 -> 23511161
A16: =A15+1 -> 9 | B16: Transport Sparsity | D16: ='FY 2003'!I16 -> 56478364 | E16: ='FY 2004'!I16 -> 55913098 | F16: ='FY 2006'!I16-'FY 2006'!G16-'FY 2006'!H16 -> 56687280 | G16: ='FY 2007'!I16 -> 59221788 | H16: ='FY 2008'!I16 -> 60083765 | I16: ='FY 2009'!$I17 -> 60159097 | J16: ='FY 2010'!$J16 -> 59833229 | K16: ='FY 2011'!$J16 -> 60371479
A17: =A16+1 -> 10 | B17: Training & Experience | D17: ='FY 2003'!I17 -> 25114308 | E17: ='FY 2004'!I17 -> 18869558 | F17: ='FY 2006'!I17-'FY 2006'!G17-'FY 2006'!H17 -> 8014853 | G17: ='FY 2007'!I17 -> 4354428 | H17: ='FY 2008'!I17 -> 2146056 | I17: ='FY 2009'!$I18 -> 1207447.6 | J17: ='FY 2010'!$J17 -> 675850 | K17: ='FY 2011'!$J17 -> 373228
A18: =A17+1 -> 11 | B18: Late Contract Penalty | D18: ='FY 2003'!I18 -> 0 | E18: ='FY 2004'!I18 -> 0 | F18: ='FY 2006'!I18-'FY 2006'!G18-'FY 2006'!H18 -> -344932 | G18: ='FY 2007'!I18 -> 0 | H18: ='FY 2008'!I18 -> -730496 | I18: ='FY 2009'!$I19 -> 0 | J18: ='FY 2010'!$J18 -> -2507070 | K18: ='FY 2011'!$J18 -> 0
A19: =A18+1 -> 12 | B19: Operating Capital | D19: ='FY 2003'!I19 -> 198438434 | E19: ='FY 2004'!I19 -> 194217096 | F19: ='FY 2006'!I19-'FY 2006'!G19-'FY 2006'!H19 -> 189326862 | G19: ='FY 2007'!I19 -> 194117024 | H19: ='FY 2008'!I19 -> 194635565 | I19: ='FY 2009'!$I20 -> 1.9429911e+08 | J19: ='FY 2010'!$J20 -> 194409760 | K19: ='FY 2011'!$J19 -> 194612210
A20: =A19+1 -> 13 | B20: Equity | D20: ='FY 2003'!I20 -> 34642490 | E20: ='FY 2004'!I20 -> 32112369 | F20: ='FY 2006'!I20-'FY 2006'!G20-'FY 2006'!H20 -> 49766290 | G20: ='FY 2007'!I20 -> 94274069 | H20: ='FY 2008'!I20 -> 95708805 | I20: ='FY 2009'!$I21 -> 93361990 | J20: ='FY 2010'!$J21 -> 92518770 | K20: ='FY 2011'!$J20 -> 92334012
A21: =A20+1 -> 14 | B21: Transition | D21: ='FY 2003'!I21 -> 0 | E21: ='FY 2004'!I21 -> 31986524 | F21: ='FY 2006'!I21-'FY 2006'!G21-'FY 2006'!H21 -> 29975351 | G21: ='FY 2007'!I21 -> 30462514 | H21: ='FY 2008'!I21 -> 30143318 | I21: ='FY 2009'!$I22 -> 29711997 | J21: ='FY 2010'!$J22 -> 29453149 | K21: ='FY 2011'!$J21 -> 29215443
A22: =A21+1 -> 15 | B22: Q Comp | D22: ='FY 2003'!I22 -> 0 | E22: ='FY 2004'!I22 -> 0 | F22: ='FY 2006'!I22-'FY 2006'!G22-'FY 2006'!H22 -> 16096910 | G22: ='FY 2007'!I22 -> 48603714 | H22: ='FY 2008'!I22 -> 60763648 | I22: ='FY 2009'!$I23 -> 63348360 | J22: ='FY 2010'!$J23 -> 58291520 | K22: ='FY 2011'!$J22 -> 63056932
A23: =A22+1 -> 16 | B23: Referendum Revenue | D23: ='FY 2003'!I23 -> 291708358 | E23: ='FY 2004'!I23 -> 426336542 | F23: ='FY 2006'!I23-'FY 2006'!G23-'FY 2006'!H23 -> 534314512 | G23: ='FY 2007'!I23 -> 598966155 | H23: ='FY 2008'!I23 -> 644192179 | I23: ='FY 2009'!$I24 -> 7.2056718e+08 | J23: ='FY 2010'!$J24 -> 781675140 | K23: ='FY 2011'!$J23 -> 804832265
B24: Alternative Attendance Adj:
A25: =A23+1 -> 17 | C25: Open Enroll/Charter Refer | D25: ='FY 2003'!I25 -> 1341221 | E25: ='FY 2004'!I25 -> -679857 | F25: ='FY 2006'!I25-'FY 2006'!G25-'FY 2006'!H25 -> -3077997.8 | G25: ='FY 2007'!I25 -> -885672 | H25: ='FY 2008'!I25 -> -181964 | I25: ='FY 2009'!$I26 -> 262096 | J25: ='FY 2010'!$J26 -> 607348 | K25: ='FY 2011'!$J25 -> 657596
A26: =A25+1 -> 18 | C26: Charter Basic Transport | D26: ='FY 2003'!I26 -> -1804253 | E26: ='FY 2004'!I26 -> 1059 | F26: ='FY 2006'!I26-'FY 2006'!G26-'FY 2006'!H26 -> 1946553.4 | G26: ='FY 2007'!I26 -> 0 | H26: ='FY 2008'!I26 -> 0 | I26: ='FY 2009'!$I27 -> -0.0099999995 | J26: ='FY 2010'!$J27 -> 0 | K26: ='FY 2011'!$J26 -> 32
A27: =A26+1 -> 19 | C27: Charter Ext TimeTransport | D27: ='FY 2003'!I27 -> 0 | E27: ='FY 2004'!I27 -> 0 | F27: ='FY 2006'!I27-'FY 2006'!G27-'FY 2006'!H27 -> 33079.82 | G27: ='FY 2007'!I27 -> 0 | H27: ='FY 2008'!I27 -> 0 | I27: ='FY 2009'!$I28 -> 0 | J27: ='FY 2010'!$J28 -> 0 | K27: ='FY 2011'!$J27 -> 777
A28: =A27+1 -> 20 | C28: Charter Transport Sparsity | D28: ='FY 2003'!I28 -> 0 | E28: ='FY 2004'!I28 -> 0 | F28: ='FY 2006'!I28-'FY 2006'!G28-'FY 2006'!H28 -> 437202.44 | G28: ='FY 2007'!I28 -> 0 | H28: ='FY 2008'!I28 -> 0 | I28: ='FY 2009'!$I29 -> -0.01 | J28: ='FY 2010'!$J29 -> 4 | K28: ='FY 2011'!$J28 -> 165
A29: =A28+1 -> 21 | C29: Faribault Alternative Attend Adj | D29: 0 | E29: 0 | F29: ='FY 2006'!I29-'FY 2006'!G29-'FY 2006'!H29 -> 0 | G29: ='FY 2007'!$I29 -> -398 | H29: ='FY 2008'!$I29 -> -355.18 | I29: ='FY 2009'!$I30 -> -461.16 | J29: ='FY 2010'!$J30 -> -449 | K29: ='FY 2011'!$J29 -> -195
A31: =A29+1 -> 22 | B31: TOTAL REVENUE | D31: =SUM(D8:D29) -> 5421781814 | E31: =SUM(E8:E29) -> 5514835219 | F31: =SUM(F8:F29) -> 5.712421e+09 | G31: =SUM(G8:G29) -> 6076985027 | H31: =SUM(H8:H29) -> 6.2306906e+09 | I31: =SUM(I8:I29) -> 6.3218838e+09 | J31: =SUM(J8:J29) -> 6367598630 | K31: =SUM(K8:K29) -> 6444912665
B33: LEVIES
A34: =A31+1 -> 23 | B34: Operating Capital Levy | D34: ='FY 2003'!I33 -> 0 | E34: ='FY 2004'!I33 -> 0 | F34: ='FY 2006'!I34-'FY 2006'!G34-'FY 2006'!H34 -> 44268155 | G34: ='FY 2007'!I34 -> 101934454 | H34: ='FY 2008'!I34 -> 111830374 | I34: ='FY 2009'!$I35 -> 1.2125304e+08 | J34: ='FY 2010'!$J35 -> 124276595 | K34: ='FY 2011'!$J34 -> 124623859
A35: =A34+1 -> 24 | B35: Equity Levy | D35: ='FY 2003'!I34 -> 0 | E35: ='FY 2004'!I34 -> 0 | F35: ='FY 2006'!I35-'FY 2006'!G35-'FY 2006'!H35 -> 25083314 | G35: ='FY 2007'!I35 -> 63740065 | H35: ='FY 2008'!I35 -> 70604296 | I35: ='FY 2009'!$I36 -> 73701614 | J35: ='FY 2010'!$J36 -> 75798743 | K35: ='FY 2011'!$J35 -> 76305360
A36: =A35+1 -> 25 | B36: Transition Levy | D36: ='FY 2003'!I35 -> 0 | E36: ='FY 2004'!I35 -> 0 | F36: ='FY 2006'!I36-'FY 2006'!G36-'FY 2006'!H36 -> 20383544 | G36: ='FY 2007'!I36 -> 21830489 | H36: ='FY 2008'!I36 -> 23010395 | I36: ='FY 2009'!$I37 -> 24292897 | J36: ='FY 2010'!$J37 -> 25195534 | K36: ='FY 2011'!$J36 -> 25244531
A37: =A36+1 -> 26 | B37: Q Comp | D37: ='FY 2003'!I36 -> 0 | E37: ='FY 2004'!I36 -> 0 | F37: ='FY 2006'!I37-'FY 2006'!G37-'FY 2006'!H37 -> 0 | G37: ='FY 2007'!I37 -> 9695468 | H37: ='FY 2008'!I37 -> 12779741 | I37: ='FY 2009'!$I38 -> 13353371 | J37: ='FY 2010'!$J38 -> 16807134 | K37: ='FY 2011'!$J37 -> 18158004
A38: =A37+1 -> 27 | B38: Referendum Levy | D38: ='FY 2003'!I37 -> 224945858 | E38: ='FY 2004'!I37 -> 351087875 | F38: ='FY 2006'!I38-'FY 2006'!G38-'FY 2006'!H38 -> 410867894 | G38: ='FY 2007'!I38 -> 482421730 | H38: ='FY 2008'!I38 -> 540184289 | I38: ='FY 2009'!$I39 -> 6.3533353e+08 | J38: ='FY 2010'!$J39 -> 712334239 | K38: ='FY 2011'!$J38 -> 737629396
A40: =A38+1 -> 28 | B40: TOTAL LEVY | D40: =SUM(D34:D38) -> 224945858 | E40: =SUM(E34:E38) -> 351087875 | F40: =SUM(F34:F38) -> 500602907 | G40: =SUM(G34:G38) -> 679622206 | H40: =SUM(H34:H38) -> 758409095 | I40: =SUM(I34:I38) -> 8.6793445e+08 | J40: =SUM(J34:J38) -> 954412245 | K40: =SUM(K34:K38) -> 981961150
B42: AID ENTITLEMENTS
A43: =A40+1 -> 29 | B43: Basic | D43: =D8 -> 4490060320 | E43: =E8 -> 4403575277 | F43: =F8 -> 4448158911 | G43: =G8 -> 4608596779 | H43: =H8 -> 4676709149 | I43: =I8 -> 4.6748038e+09 | J43: =J8 -> 4652117979 | K43: =K8 -> 4641176290
A44: =A43+1 -> 30 | B44: Gifted & Talented | D44: =D9 -> 0 | E44: =E9 -> 0 | F44: =F9 -> 3719974 | G44: =G9 -> 8579632 | H44: =H9 -> 11441209 | I44: =I9 -> 11383079 | J44: =J9 -> 11365913 | K44: =K9 -> 11377163
A45: =A44+1 -> 31 | B45: Extended time | D45: =D10 -> 0 | E45: =E10 -> 50351550 | F45: =F10 -> 51811953 | G45: =G10 -> 55436989 | H45: =H10 -> 59590817 | I45: =I10 -> 60995641 | J45: =J10 -> 64565373 | K45: =K10 -> 69073025
B46: Basic Skills:
A47: =A45+1 -> 32 | C47: Compensatory | D47: =D12 -> 262694686 | E47: =E12 -> 249146954 | F47: =F12 -> 271753985 | G47: =G12 -> 315471905 | H47: =H12 -> 333928094 | I47: =I12 -> 3.4851069e+08 | J47: =J12 -> 361157268 | K47: =K12 -> 414260438
A48: =A47+1 -> 33 | C48: LEP | D48: =D13 -> 36857227 | E48: =E13 -> 28818713 | F48: =F13 -> 28357728 | G48: =G13 -> 31474254 | H48: =H13 -> 32316781 | I48: =I13 -> 32058187 | J48: =J13 -> 31807937 | K48: =K13 -> 31673120
A49: =A48+1 -> 34 | C49: LEP Concentration | D49: =D14 -> 9779108 | E49: =E14 -> 7276758 | F49: =F14 -> 7045250 | G49: =G14 -> 8057613 | H49: =H14 -> 8306508 | I49: =I14 -> 8316835 | J49: =J14 -> 8258276 | K49: =K14 -> 8387524
A50: =A49+1 -> 35 | B50: Sparsity | D50: =D15 -> 16471551 | E50: =E15 -> 16909578 | F50: =F15 -> 18397203 | G50: =G15 -> 20254233 | H50: =H15 -> 21637534 | I50: =I15 -> 22898807 | J50: =J15 -> 23368633 | K50: =K15 -> 23511161
A51: =A50+1 -> 36 | B51: Transport Sparsity | D51: =D16 -> 56478364 | E51: =E16 -> 55913098 | F51: =F16 -> 56687280 | G51: =G16 -> 59221788 | H51: =H16 -> 60083765 | I51: =I16 -> 60159097 | J51: =J16 -> 59833229 | K51: =K16 -> 60371479
A52: =A51+1 -> 37 | B52: Training & Experience | D52: =D17 -> 25114308 | E52: =E17 -> 18869558 | F52: =F17 -> 8014853 | G52: =G17 -> 4354428 | H52: =H17 -> 2146056 | I52: =I17 -> 1207447.6 | J52: =J17 -> 675850 | K52: =K17 -> 373228
A53: =A52+1 -> 38 | B53: Late Contract Penalty | D53: =D18 -> 0 | E53: =E18 -> 0 | F53: =F18 -> -344932 | G53: =G18 -> 0 | H53: =H18 -> -730496 | I53: =I18 -> 0 | J53: =J18 -> -2507070 | K53: =K18 -> 0
A54: =A53+1 -> 39 | B54: Operating Capital | D54: =D19-D34 -> 198438434 | E54: =E19-E34 -> 194217096 | F54: =F19-F34 -> 145058707 | G54: =G19-G34 -> 92182570 | H54: =H19-H34 -> 82805191 | I54: =I19-I34 -> 73046067 | J54: =J19-J34 -> 70133165 | K54: =K19-K34 -> 69988351
A55: =A54+1 -> 40 | B55: Equity | D55: =D20-D35 -> 34642490 | E55: =E20-E35 -> 32112369 | F55: =F20-F35 -> 24682976 | G55: =G20-G35 -> 30534004 | H55: =H20-H35 -> 25104509 | I55: =I20-I35 -> 19660376 | J55: =J20-J35 -> 16720027 | K55: =K20-K35 -> 16028652
A56: =A55+1 -> 41 | B56: Transition | D56: =D21-D36 -> 0 | E56: =E21-E36 -> 31986524 | F56: =F21-F36 -> 9591807 | G56: =G21-G36 -> 8632025 | H56: =H21-H36 -> 7132923 | I56: =I21-I36 -> 5419100.7 | J56: =J21-J36 -> 4257615 | K56: =K21-K36 -> 3970912
A57: =A56+1 -> 42 | B57: Q Comp | D57: =D22-D37 -> 0 | E57: =E22-E37 -> 0 | F57: =F22-F37 -> 16096910 | G57: =G22-G37 -> 38908246 | H57: =H22-H37 -> 47983907 | I57: =I22-I37 -> 49994989 | J57: =J22-J37 -> 41484386 | K57: =K22-K37 -> 44898928
A58: =A57+1 -> 43 | B58: Referendum Equalization Aid | D58: =D23-D38-D59 -> 58417206 | E58: =E23-E38-E59 -> 67208298 | F58: =F23-F38-F59 -> 114774019 | G58: =G23-G38-G59 -> 107935161 | H58: =H23-H38-H59 -> 95398626 | I58: =I23-I38-I59 -> 76645863 | J58: =J23-J38-J59 -> 60722235 | K58: =K23-K38-K59 -> 58609687
A59: =A58+1 -> 44 | B59: Tax Base Replacement Aid | D59: ='FY 2003'!I58 -> 8345294 | E59: ='FY 2004'!I58 -> 8040369 | F59: ='FY 2006'!I59-'FY 2006'!G59-'FY 2006'!H59 -> 8672599 | G59: ='FY 2007'!I59 -> 8609264 | H59: ='FY 2008'!I59 -> 8609264 | I59: ='FY 2009'!$I61 -> 8587791.7 | J59: ='FY 2010'!$J61 -> 8618666 | K59: ='FY 2011'!$J59 -> 8593182
B60: Alternative Attendance Adj:
A61: =A59+1 -> 45 | C61: Open Enroll/Charter Refer | D61: ='FY 2003'!I60 -> 1341221 | E61: ='FY 2004'!I60 -> -679857 | F61: =F25 -> -3077997.8 | G61: ='FY 2007'!I61 -> -885672 | H61: ='FY 2008'!I61 -> -181964 | I61: ='FY 2009'!$I63 -> 262096 | J61: ='FY 2010'!$J63 -> 607348 | K61: ='FY 2011'!$J61 -> 657596
A62: =A61+1 -> 46 | C62: Charter Basic Transport | D62: ='FY 2003'!I61 -> -1804253 | E62: ='FY 2004'!I61 -> 1059 | F62: =F26 -> 1946553.4 | G62: ='FY 2007'!I62 -> 0 | H62: ='FY 2008'!I62 -> 0 | I62: ='FY 2009'!$I64 -> -0.0099999995 | J62: ='FY 2010'!$J64 -> 0 | K62: ='FY 2011'!$J62 -> 32
A63: =A62+1 -> 47 | C63: Charter Ext TimeTransport | D63: ='FY 2003'!I62 -> 0 | E63: ='FY 2004'!I62 -> 0 | F63: =F27 -> 33079.82 | G63: ='FY 2007'!I63 -> 0 | H63: ='FY 2008'!I63 -> 0 | I63: ='FY 2009'!$I65 -> 0 | J63: ='FY 2010'!$J65 -> 0 | K63: ='FY 2011'!$J63 -> 777
A64: =A63+1 -> 48 | C64: Charter Transport Sparsity | D64: ='FY 2003'!I63 -> 0 | E64: ='FY 2004'!I63 -> 0 | F64: =F28 -> 437202.44 | G64: ='FY 2007'!I64 -> 0 | H64: ='FY 2008'!I64 -> 0 | I64: ='FY 2009'!$I66 -> -0.01 | J64: ='FY 2010'!$J66 -> 4 | K64: ='FY 2011'!$J64 -> 165
A65: =A64+1 -> 49 | C65: Faribault Alternative Attend Adj | D65: 0 | E65: 0 | F65: =F29 -> 0 | G65: ='FY 2007'!$I65 -> -398 | H65: ='FY 2008'!$I65 -> -355.18 | I65: ='FY 2009'!$I67 -> -461.16 | J65: ='FY 2010'!$J67 -> -449 | K65: ='FY 2011'!$J65 -> -195
A67: =A65+1 -> 50 | B67: TOTAL AID ENTITLEMENT | D67: =SUM(D43:D65) -> 5196835956 | E67: =SUM(E43:E65) -> 5163747344 | F67: =SUM(F43:F65) -> 5.2118181e+09 | G67: =SUM(G43:G65) -> 5397362821 | H67: =SUM(H43:H65) -> 5.4722815e+09 | I67: =SUM(I43:I65) -> 5.4539494e+09 | J67: =SUM(J43:J65) -> 5413186385 | K67: =SUM(K43:K65) -> 5462951515
A68: =A67+1 -> 51 | B68: General Ed Entitlement | D68: =D67-D59 -> 5188490662 | E68: =E67-E59 -> 5155706975 | F68: =F67-F59 -> 5.2031455e+09 | G68: =G67-G59 -> 5388753557 | H68: =H67-H59 -> 5.4636723e+09 | I68: =I67-I59 -> 5.4453616e+09 | J68: =J67-J59 -> 5404567719 | K68: =K67-K59 -> 5454358333
A69: =A68+1 -> 52 | B69: Tax Base Replacement Entitlement | D69: =D59 -> 8345294 | E69: =E59 -> 8040369 | F69: =F59 -> 8672599 | G69: =G59 -> 8609264 | H69: =H59 -> 8609264 | I69: =I59 -> 8587791.7 | J69: =J59 -> 8618666 | K69: =K59 -> 8593182
A71: =A69+1 -> 53 | B71: TRA Reduction | D71: ='FY 2003'!I69 -> -46570547 | E71: ='FY 2004'!I69 -> -46686661 | F71: ='FY 2006'!I71-'FY 2006'!G71-'FY 2006'!H71 -> -45675930 | G71: ='FY 2007'!I71 -> -46967505 | H71: ='FY 2008'!I71 -> -30637836 | I71: ='FY 2009'!$I73 -> -30753090 | J71: ='FY 2010'!$J73 -> -30827862 | K71: ='FY 2011'!$J71 -> -30929256
A73: =A71+1 -> 54 | B73: Total Revenue = (22) + (53) = | F73: =F31+F71 -> 5.666745e+09 | G73: =G31+G71 -> 6030017522 | H73: =H31+H71 -> 6.2000528e+09 | I73: =I31+I71 -> 6.2911307e+09 | J73: =J31+J71 -> 6336770768 | K73: =K31+K71 -> 6413983409
A74: =A73+1 -> 55 | B74: Total Aid = (54) - (28) = | F74: =F73-F40 -> 5.1661421e+09 | G74: =G73-G40 -> 5350395316 | H74: =H73-H40 -> 5.4416437e+09 | I74: =I73-I40 -> 5.4231963e+09 | J74: =J73-J40 -> 5382358523 | K74: =K73-K40 -> 5432022259
A76: =A74+1 -> 56 | B76: Current Year Adjusted Pupil Units | F76: ='Pupil Data'!C25+'Pupil Data'!D25 -> 927594 | G76: ='Pupil Data'!C26+'Pupil Data'!D26 -> 924184 | H76: ='Pupil Data'!C27+'Pupil Data'!D27 -> 918554 | I76: ='Pupil Data'!C28+'Pupil Data'!D28 -> 909173 | J76: ='Pupil Data'!C29+'Pupil Data'!D29 -> 905826 | K76: ='Pupil Data'!C30+'Pupil Data'!D30 -> 903698
A78: =A76+1 -> 57 | B78: Aid per Pupil Unit = (55) / (56) = | F78: =ROUND(F74/F76,2) -> 5569.4 | G78: =ROUND(G74/G76,2) -> 5789.32 | H78: =ROUND(H74/H76,2) -> 5924.14 | I78: =ROUND(I74/I76,2) -> 5964.98 | J78: =ROUND(J74/J76,2) -> 5941.93 | K78: =ROUND(K74/K76,2) -> 6010.88
F80: 5585.06 | G80: 5766.83 | H80: 5892.35 | I80: 5951.66 | J80: 5934.15 | K80: 5924.21
F81: =F78-F80 -> -15.66 | G81: =G78-G80 -> 22.49 | H81: =H78-H80 -> 31.79 | I81: =I78-I80 -> 13.32 | J81: =J78-J80 -> 7.78 | K81: =K78-K80 -> 86.67
A84: NOVEMBER 2010 FORECAST
B85: Based on history files and pay11 levy | I85: 5951 | J85: 5866 | K85: 5907 | L85: 5960

Sheet Test Change
A1: NOV 2009 VS. EOS 2009
A3: NOVEMBER 2009 FORECAST | D3: FY 2003 | E3: FY 2004 | F3: FY 2005 | G3: FY 2006 | H3: FY 2007 | I3: FY 2008 | J3: FY 2009 | K3: FY 2010 | L3: FY 2011 | M3: FY 2012 | N3: FY 2013 | O3: 2008-09 | P3: 2010-11 | Q3: 2012-13 | R3: Chg from 2008-09 | S3: % chg | T3: Chg from 2010-11 | U3: % chg
A5: 1 | B5: AMCPU | D5: ='FY 2003'!I5 -> 962146 | E5: ='FY 2004'!I5 -> 957096 | F5: ='FY 2005'!I5 -> 953035 | G5: ='FY 2006'!I5 -> 953041 | H5: ='FY 2007'!I5 -> 953288 | I5: ='FY 2008'!I5 -> 953432 | J5: ='FY 2009'!$I5 -> 948587 | K5: ='FY 2010'!$J5 -> 947210 | L5: ='FY 2011'!$J5 -> 948097 | M5: ='FY 2012'!$J5 -> 951670 | N5: ='FY 2013'!$J5 -> 959454
B7: REVENUES
A8: =A5+1 -> 2 | B8: Basic | D8: ='FY 2003'!I8 -> 4490060320 | E8: ='FY 2004'!I8 -> 4403575277 | F8: =ROUND('SUMMARY-ALL YEARS'!F8/1000,1) -> 4384973.8 | G8: =ROUND('SUMMARY-ALL YEARS'!G8/1000,1) -> 4558383.7 | H8: =ROUND('SUMMARY-ALL YEARS'!H8/1000,1) -> 4741676.9 | I8: =ROUND('SUMMARY-ALL YEARS'!I8/1000,1) -> 4837724.5 | J8: =ROUND('SUMMARY-ALL YEARS'!J8/1000,1) -> 4860574.7 | K8: =ROUND('SUMMARY-ALL YEARS'!K8/1000,1) -> 4853494.9 | L8: =ROUND('SUMMARY-ALL YEARS'!L8/1000,1) -> 4858048.1 | M8: =ROUND('SUMMARY-ALL YEARS'!M8/1000,1) -> 4876357.2 | N8: =ROUND('SUMMARY-ALL YEARS'!N8/1000,1) -> 4916240.2 | O8: =SUM(I8:J8) -> 9698299.2 | P8: =SUM(K8:L8) -> 9711543 | Q8: =SUM(M8:N8) -> 9792597.4 | R8: =P8-O8 -> 13243.8 | S8: =R8/O8 -> 0.0013655796 | T8: =Q8-P8 -> 81054.4 | U8: =T8/P8 -> 0.0083461917
A9: =A8+1 -> 3 | B9: Additional $51 | F9: 0 | G9: 0 | H9: 0 | I9: 0 | J9: =ROUND('SUMMARY-ALL YEARS'!J9/1000,1) -> 48378.1 | K9: 0 | L9: 0 | M9: 0 | N9: 0 | O9: =SUM(I9:J9) -> 48378.1 | P9: =SUM(K9:L9) -> 0 | Q9: =SUM(M9:N9) -> 0 | R9: =P9-O9 -> -48378.1 | S9: =R9/O9 -> -1 | T9: =Q9-P9 -> 0 | U9: =T9/P9 -> #DIV/0!
A10: =A9+1 -> 4 | B10: Gifted & Talented | D10: ='FY 2003'!I9 -> 0 | E10: ='FY 2004'!I9 -> 0 | F10: =ROUND('SUMMARY-ALL YEARS'!F10/1000,1) -> 0 | G10: =ROUND('SUMMARY-ALL YEARS'!G10/1000,1) -> 3812.2 | H10: =ROUND('SUMMARY-ALL YEARS'!H10/1000,1) -> 8579.6 | I10: =ROUND('SUMMARY-ALL YEARS'!I10/1000,1) -> 11441.2 | J10: =ROUND('SUMMARY-ALL YEARS'!J10/1000,1) -> 11383.1 | K10: =ROUND('SUMMARY-ALL YEARS'!K10/1000,1) -> 11365.9 | L10: =ROUND('SUMMARY-ALL YEARS'!L10/1000,1) -> 11377.2 | M10: =ROUND('SUMMARY-ALL YEARS'!M10/1000,1) -> 11420 | N10: =ROUND('SUMMARY-ALL YEARS'!N10/1000,1) -> 11513.4 | O10: =SUM(I10:J10) -> 22824.3 | P10: =SUM(K10:L10) -> 22743.1 | Q10: =SUM(M10:N10) -> 22933.4 | R10: =P10-O10 -> -81.2 | S10: =R10/O10 -> -0.0035576118 | T10: =Q10-P10 -> 190.3 | U10: =T10/P10 -> 0.008367373
A11: =A10+1 -> 5 | B11: Extended time | D11: ='FY 2003'!I10 -> 0 | E11: ='FY 2004'!I10 -> 50351550 | F11: =ROUND('SUMMARY-ALL YEARS'!F11/1000,1) -> 52327.4 | G11: =ROUND('SUMMARY-ALL YEARS'!G11/1000,1) -> 52766.2 | H11: =ROUND('SUMMARY-ALL YEARS'!H11/1000,1) -> 55437 | I11: =ROUND('SUMMARY-ALL YEARS'!I11/1000,1) -> 59590.8 | J11: =ROUND('SUMMARY-ALL YEARS'!J11/1000,1) -> 60995.6 | K11: =ROUND('SUMMARY-ALL YEARS'!K11/1000,1) -> 64565.4 | L11: =ROUND('SUMMARY-ALL YEARS'!L11/1000,1) -> 69073 | M11: =ROUND('SUMMARY-ALL YEARS'!M11/1000,1) -> 71777.9 | N11: =ROUND('SUMMARY-ALL YEARS'!N11/1000,1) -> 76066.8 | O11: =SUM(I11:J11) -> 120586.4 | P11: =SUM(K11:L11) -> 133638.4 | Q11: =SUM(M11:N11) -> 147844.7 | R11: =P11-O11 -> 13052 | S11: =R11/O11 -> 0.10823774 | T11: =Q11-P11 -> 14206.3 | U11: =T11/P11 -> 0.10630403
B12: Basic Skills:
A13: =A11+1 -> 6 | C13: Compensatory | D13: ='FY 2003'!I12 -> 262694686 | E13: ='FY 2004'!I12 -> 249146954 | F13: =ROUND('SUMMARY-ALL YEARS'!F13/1000,1) -> 265074.5 | G13: =ROUND('SUMMARY-ALL YEARS'!G13/1000,1) -> 292547.5 | H13: =ROUND('SUMMARY-ALL YEARS'!H13/1000,1) -> 315471.9 | I13: =ROUND('SUMMARY-ALL YEARS'!I13/1000,1) -> 333928.1 | J13: =ROUND('SUMMARY-ALL YEARS'!J13/1000,1) -> 348510.7 | K13: =ROUND('SUMMARY-ALL YEARS'!K13/1000,1) -> 361157.3 | L13: =ROUND('SUMMARY-ALL YEARS'!L13/1000,1) -> 414260.4 | M13: =ROUND('SUMMARY-ALL YEARS'!M13/1000,1) -> 432960.5 | N13: =ROUND('SUMMARY-ALL YEARS'!N13/1000,1) -> 452559.9 | O13: =SUM(I13:J13) -> 682438.8 | P13: =SUM(K13:L13) -> 775417.7 | Q13: =SUM(M13:N13) -> 885520.4 | R13: =P13-O13 -> 92978.9 | S13: =R13/O13 -> 0.13624504 | T13: =Q13-P13 -> 110102.7 | U13: =T13/P13 -> 0.14199147
A14: =A13+1 -> 7 | C14: LEP | D14: ='FY 2003'!I13 -> 36857227 | E14: ='FY 2004'!I13 -> 28818713 | F14: =ROUND('SUMMARY-ALL YEARS'!F14/1000,1) -> 29477.7 | G14: =ROUND('SUMMARY-ALL YEARS'!G14/1000,1) -> 30912.7 | H14: =ROUND('SUMMARY-ALL YEARS'!H14/1000,1) -> 31474.3 | I14: =ROUND('SUMMARY-ALL YEARS'!I14/1000,1) -> 32316.8 | J14: =ROUND('SUMMARY-ALL YEARS'!J14/1000,1) -> 32058.2 | K14: =ROUND('SUMMARY-ALL YEARS'!K14/1000,1) -> 31807.9 | L14: =ROUND('SUMMARY-ALL YEARS'!L14/1000,1) -> 31673.1 | M14: =ROUND('SUMMARY-ALL YEARS'!M14/1000,1) -> 31709.9 | N14: =ROUND('SUMMARY-ALL YEARS'!N14/1000,1) -> 31867 | O14: =SUM(I14:J14) -> 64375 | P14: =SUM(K14:L14) -> 63481 | Q14: =SUM(M14:N14) -> 63576.9 | R14: =P14-O14 -> -894 | S14: =R14/O14 -> -0.013887379 | T14: =Q14-P14 -> 95.9 | U14: =T14/P14 -> 0.0015106882
A15: =A14+1 -> 8 | C15: LEP Concentration | D15: ='FY 2003'!I14 -> 9779108 | E15: ='FY 2004'!I14 -> 7276758 | F15: =ROUND('SUMMARY-ALL YEARS'!F15/1000,1) -> 7434.3 | G15: =ROUND('SUMMARY-ALL YEARS'!G15/1000,1) -> 7883.2 | H15: =ROUND('SUMMARY-ALL YEARS'!H15/1000,1) -> 8057.6 | I15: =ROUND('SUMMARY-ALL YEARS'!I15/1000,1) -> 8306.5 | J15: =ROUND('SUMMARY-ALL YEARS'!J15/1000,1) -> 8316.8 | K15: =ROUND('SUMMARY-ALL YEARS'!K15/1000,1) -> 8258.3 | L15: =ROUND('SUMMARY-ALL YEARS'!L15/1000,1) -> 8387.5 | M15: =ROUND('SUMMARY-ALL YEARS'!M15/1000,1) -> 8406.8 | N15: =ROUND('SUMMARY-ALL YEARS'!N15/1000,1) -> 8500.2 | O15: =SUM(I15:J15) -> 16623.3 | P15: =SUM(K15:L15) -> 16645.8 | Q15: =SUM(M15:N15) -> 16907 | R15: =P15-O15 -> 22.5 | S15: =R15/O15 -> 0.0013535219 | T15: =Q15-P15 -> 261.2 | U15: =T15/P15 -> 0.015691646
A16: =A15+1 -> 9 | B16: Sparsity | D16: ='FY 2003'!I15 -> 16471551 | E16: ='FY 2004'!I15 -> 16909578 | F16: =ROUND('SUMMARY-ALL YEARS'!F16/1000,1) -> 17548.6 | G16: =ROUND('SUMMARY-ALL YEARS'!G16/1000,1) -> 18853.1 | H16: =ROUND('SUMMARY-ALL YEARS'!H16/1000,1) -> 20254.2 | I16: =ROUND('SUMMARY-ALL YEARS'!I16/1000,1) -> 21637.5 | J16: =ROUND('SUMMARY-ALL YEARS'!J16/1000,1) -> 22898.8 | K16: =ROUND('SUMMARY-ALL YEARS'!K16/1000,1) -> 23368.6 | L16: =ROUND('SUMMARY-ALL YEARS'!L16/1000,1) -> 23511.2 | M16: =ROUND('SUMMARY-ALL YEARS'!M16/1000,1) -> 24128.7 | N16: =ROUND('SUMMARY-ALL YEARS'!N16/1000,1) -> 24366.8 | O16: =SUM(I16:J16) -> 44536.3 | P16: =SUM(K16:L16) -> 46879.8 | Q16: =SUM(M16:N16) -> 48495.5 | R16: =P16-O16 -> 2343.5 | S16: =R16/O16 -> 0.052619998 | T16: =Q16-P16 -> 1615.7 | U16: =T16/P16 -> 0.034464737
A17: =A16+1 -> 10 | B17: Transport Sparsity | D17: ='FY 2003'!I16 -> 56478364 | E17: ='FY 2004'!I16 -> 55913098 | F17: =ROUND('SUMMARY-ALL YEARS'!F17/1000,1) -> 55511.2 | G17: =ROUND('SUMMARY-ALL YEARS'!G17/1000,1) -> 57332.8 | H17: =ROUND('SUMMARY-ALL YEARS'!H17/1000,1) -> 59221.8 | I17: =ROUND('SUMMARY-ALL YEARS'!I17/1000,1) -> 60083.8 | J17: =ROUND('SUMMARY-ALL YEARS'!J17/1000,1) -> 60159.1 | K17: =ROUND('SUMMARY-ALL YEARS'!K17/1000,1) -> 59833.2 | L17: =ROUND('SUMMARY-ALL YEARS'!L17/1000,1) -> 60371.5 | M17: =ROUND('SUMMARY-ALL YEARS'!M17/1000,1) -> 60249.6 | N17: =ROUND('SUMMARY-ALL YEARS'!N17/1000,1) -> 60009.2 | O17: =SUM(I17:J17) -> 120242.9 | P17: =SUM(K17:L17) -> 120204.7 | Q17: =SUM(M17:N17) -> 120258.8 | R17: =P17-O17 -> -38.2 | S17: =R17/O17 -> -0.00031769028 | T17: =Q17-P17 -> 54.1 | U17: =T17/P17 -> 0.0004500656
A18: =A17+1 -> 11 | B18: Training & Experience | D18: ='FY 2003'!I17 -> 25114308 | E18: ='FY 2004'!I17 -> 18869558 | F18: =ROUND('SUMMARY-ALL YEARS'!F18/1000,1) -> 12876.8 | G18: =ROUND('SUMMARY-ALL YEARS'!G18/1000,1) -> 8213.5 | H18: =ROUND('SUMMARY-ALL YEARS'!H18/1000,1) -> 4354.4 | I18: =ROUND('SUMMARY-ALL YEARS'!I18/1000,1) -> 2146.1 | J18: =ROUND('SUMMARY-ALL YEARS'!J18/1000,1) -> 1207.4 | K18: =ROUND('SUMMARY-ALL YEARS'!K18/1000,1) -> 675.9 | L18: =ROUND('SUMMARY-ALL YEARS'!L18/1000,1) -> 373.2 | M18: =ROUND('SUMMARY-ALL YEARS'!M18/1000,1) -> 223.2 | N18: =ROUND('SUMMARY-ALL YEARS'!N18/1000,1) -> 158.9 | O18: =SUM(I18:J18) -> 3353.5 | P18: =SUM(K18:L18) -> 1049.1 | Q18: =SUM(M18:N18) -> 382.1 | R18: =P18-O18 -> -2304.4 | S18: =R18/O18 -> -0.68716267 | T18: =Q18-P18 -> -667 | U18: =T18/P18 -> -0.63578305
A19: =A18+1 -> 12 | B19: Late Contract Penalty | D19: ='FY 2003'!I18 -> 0 | E19: ='FY 2004'!I18 -> 0 | F19: =ROUND('SUMMARY-ALL YEARS'!F19/1000,1) -> 0 | G19: =ROUND('SUMMARY-ALL YEARS'!G19/1000,1) -> -344.9 | H19: =ROUND('SUMMARY-ALL YEARS'!H19/1000,1) -> 0 | I19: =ROUND('SUMMARY-ALL YEARS'!I19/1000,1) -> -730.5 | J19: =ROUND('SUMMARY-ALL YEARS'!J19/1000,1) -> 0 | K19: =ROUND('SUMMARY-ALL YEARS'!K19/1000,1) -> -2507.1 | L19: =ROUND('SUMMARY-ALL YEARS'!L19/1000,1) -> 0 | M19: =ROUND('SUMMARY-ALL YEARS'!M19/1000,1) -> -700 | N19: =ROUND('SUMMARY-ALL YEARS'!N19/1000,1) -> 0 | O19: =SUM(I19:J19) -> -730.5 | P19: =SUM(K19:L19) -> -2507.1 | Q19: =SUM(M19:N19) -> -700 | R19: =P19-O19 -> -1776.6 | S19: =R19/O19 -> 2.4320329 | T19: =Q19-P19 -> 1807.1 | U19: =T19/P19 -> -0.72079295
