Workbook
Name _int70: #REF!
Name _int80: #REF!
Name abc: #REF!
Name bdrms: #REF!
Name bdrms2: #REF!
Name down100: #REF!
Name down70: #REF!
Name tdc: #REF!
Name units: #REF!

Sheet Instructions
A1: Instructions for Completing the Rental Project Spreadsheets
A3: This workbook contains spreadsheets for the 2014 NOFA application: Replacement Unit Analysis, Development Budget, Operating Budget, Financial Summary and Unit Size and Affordability Worksheet. You may use our provided 30-Year Proforma worksheet, or provide your own in Excel. If these are not the right budgets for your project, please open the "Ownership Project Spreadsheets" workbook.
A5: Submitting your budgets:
A6: Hard (paper) copy: must be submitted as the appropriate exhibit in your application.
A7: Electronic copy: must be submitted with your application, either on disk (preferred) or via email to cmorales@oaklandnet.com.
A9: Filling out your budgets:
A10: The budget worksheets have been protected. Applicants should fill in light green cells. Other cells cannot be modified. In the budgets, gray shading signifies uses for which particular sources of funds are not expected to be used.
A12: Use the TAB key to navigate through the worksheet: it will bring your cursor only to those cells that need entries. Excel will calculate totals for each row and column of figures in the "total" cells.
A14: We recognize that each project is unique and may have special costs not included in the standard budget. Use the "other" lines in each category when appropriate (be sure to fill in what the "other" cost is).
A16: If the proposal includes market-rate units, fill in the applicable columns. If you expect management costs for affordable and non-affordable units to differ, provide a detailed description of how and why. Note that additional information about financing sources for the affordable and market-rate portions of the project is required in the description of Construction and Permanent financing elsewhere in the application.
A18: An example Unit Size and Affordability worksheet is included for your reference.
A20: You should be able to manipulate the print settings if necessary; please try to print on as few pages as is readable.
A22: If you have questions, or have special circumstances and need to further manipulate the spreadsheets, please contact Housing Development Staff.

Sheet Ex. 10 - Repl. Unit Analysis
A1: Exhibit 10: Residential Deplacement and Replacement Unit Analysis
A2: [Project Name]
A3: 2014-15 Housing Development NOFA
A5: This worksheet must be completed if any of the current site use is residential, even if all existing units are currently vacant. Complete chart according to the current uses, not your proposal. Each unit must be on a separate line. Add lines if necessary.
A7: Proposal Includes Substantial Renovation: | D7: No/Yes
A8: Proposal Includes Demolition and New Construction: | E8: No/Yes
A10: Current Configuration of Site
A12: Number of Residential Buildings:
A13: Total Number of Units:
A15: Unit Number | B15: Number of Bedrooms | C15: Monthly Gross Rent | D15: Household Size | E15: Household Income | F15: Check one | J15: Is Unit Currently Occupied? | K15: Is Unit Accessible?
F16: Under 30% AMI | G16: Under 50% AMI | H16: Under 80% AMI | I16: Market Rate
A31: Summary
C32: # units with annual rents ≤ 30% of 30% AMI
C33: # units with annual rents ≤ 30% of 50% AMI
C34: # units with annual rents ≤ 30% of 80% AMI
C35: # units with annual rents ≤ 30% of 120% AMI
C36: # market rate units

Sheet Ex. 22 - Development Budget
A1: 22. Development Budget (Rental)
A3: Project Name
B4: Total | C4: Affordable Portion | D4: Market Rate Portion
A5: Total Square Feet
A6: # of Units
A7: Total # of Bedrooms
A8: * assume 1 person per SRO, 1.5 per bedroom or studio
A10: Rental Projects | B10: Entire Project | C10: Affordable Portion | D10: Market Rate Portion | E10: Commercial Portion | F10: Affordable Units Sources
A11: Item | B11: Total Costs | C11: Residential Costs | D11: Residential Costs | E11: Commercial Costs | F11: City Development Funds | G11: Other Sources Total
A12: 1. Acquisition*
A13: Option Payments | B13: =SUM(C13:E13) -> 0
A14: Acquisition* | B14: =SUM(C14:E14) -> 0
A15: Total Acquisition | B15: =SUM(B13:B14) -> 0 | C15: =SUM(C13:C14) -> 0 | D15: =SUM(D13:D14) -> 0 | E15: =SUM(E13:E14) -> 0 | F15: =SUM(F13:F14) -> 0 | G15: =SUM(G13:G14) -> 0
A17: 2. Off-Site Improvements** | B17: =SUM(C17:E17) -> 0
A19: 3. Hard Costs
A20: Demolition/Site Clearance | B20: =SUM(C20:E20) -> 0
A21: Construction | B21: =SUM(C21:E21) -> 0
A22: Contingency | B22: =SUM(C22:E22) -> 0
A23: Other:___________________________ | B23: =SUM(C23:E23) -> 0
A24: Other:___________________________ | B24: =SUM(C24:E24) -> 0
A25: Total Hard Costs | B25: =SUM(B20:B24) -> 0 | C25: =SUM(C20:C24) -> 0 | D25: =SUM(D20:D24) -> 0 | E25: =SUM(E20:E24) -> 0 | F25: =SUM(F20:F24) -> 0 | G25: =SUM(G20:G24) -> 0
A27: 4. Soft Costs
A28: Appraisal | B28: =SUM(C28:E28) -> 0
A29: Architecture/Engineering | B29: =SUM(C29:E29) -> 0
A30: Survey | B30: =SUM(C30:E30) -> 0
A31: Construction Bond Premium | B31: =SUM(C31:E31) -> 0
A32: Construction Testing/Inspection | B32: =SUM(C32:E32) -> 0
A33: Soils Report/Geological Survey | B33: =SUM(C33:E33) -> 0
A34: Environmental: Phase I, II, lead, asbestos | B34: =SUM(C34:E34) -> 0
A35: Environmental Review: CEQA/NEPA | B35: =SUM(C35:E35) -> 0
A36: Plan Check | B36: =SUM(C36:E36) -> 0
A37: Permits & Fees | B37: =SUM(C37:E37) -> 0
A38: Accounting/Audit/Tax Prep./Cost Cert. | B38: =SUM(C38:E38) -> 0
A39: Legal | B39: =SUM(C39:E39) -> 0
... A47: Other:___________________________ | B47: =SUM(C47:E47) -> 0
A48: Total Soft Costs | B48: =SUM(B28:B47) -> 0 | C48: =SUM(C28:C47) -> 0 | D48: =SUM(D28:D47) -> 0 | E48: =SUM(E28:E47) -> 0 | F48: =SUM(F28:F47) -> 0 | G48: =SUM(G28:G47) -> 0
A50: 5. Carrying Costs
A51: Property Taxes During Construction | B51: =SUM(C51:E51) -> 0
A52: Insurance During Construction | B52: =SUM(C52:E52) -> 0
A53: City Loan Fee (2% of Current Loan Request) | B53: =IF(F84=0,F83*0.02,F85*0.02) -> 0
A54: City Loan Fee (1% of Previous Award) | B54: =0.01*F84 -> 0
A55: Construction Loan Fees | B55: =SUM(C55:E55) -> 0
A56: Construction Loan Interest | B56: =SUM(C56:E56) -> 0
A57: Bridge Loan Interest | B57: =SUM(C57:E57) -> 0
A58: Other:___________________________ | B58: =SUM(C58:E58) -> 0
A59: Other:___________________________ | B59: =SUM(C59:E59) -> 0
A60: Total Carrying Costs | B60: =SUM(B51:B59) -> 0 | C60: =SUM(C51:C59) -> 0 | D60: =SUM(D51:D59) -> 0 | E60: =SUM(E51:E59) -> 0 | F60: =SUM(F51:F59) -> 0 | G60: =SUM(G51:G59) -> 0
A62: 6. Syndication Costs
A63: Syndication Accounting | B63: =SUM(C63:E63) -> 0
A64: Syndication Legal | B64: =SUM(C64:E64) -> 0
A65: Syndication Consultant Fees | B65: =SUM(C65:E65) -> 0
A66: LIHTC Fees | B66: =SUM(C66:E66) -> 0
A67: Other:___________________________ | B67: =SUM(C67:E67) -> 0
A68: Other:___________________________ | B68: =SUM(C68:E68) -> 0
A69: Total Syndication Costs | B69: =SUM(B63:B68) -> 0 | C69: =SUM(C63:C68) -> 0 | D69: =SUM(D63:D68) -> 0 | E69: =SUM(E63:E68) -> 0 | F69: =SUM(F63:F68) -> 0 | G69: =SUM(G63:G68) -> 0
A71: 7. Capitalization of Reserves
A72: Vacancy Loss Reserve (18 months) | B72: =SUM(C72:E72) -> 0
A73: Operating Reserve (long term)** | B73: =SUM(C73:E73) -> 0
A74: Replacement Reserve** | B74: =SUM(C74:E74) -> 0
A75: Other_______________________ | B75: =SUM(C75:E75) -> 0
A76: Other_______________________ | B76: =SUM(C76:E76) -> 0
A77: Total Reserves | B77: =SUM(B72:B76) -> 0 | C77: =SUM(C72:C76) -> 0 | D77: =SUM(D72:D76) -> 0 | E77: =SUM(E72:E76) -> 0 | F77: =SUM(F72:F72,F76) -> 0 | G77: =SUM(G72:G76) -> 0
A79: 8. Developer Fee | B79: =SUM(C79:E79) -> 0
A81: 9. Furnishings/Other____________** | B81: =SUM(C81:E81) -> 0
A83: Total Project Costs | B83: =(B81+B79+B77+B69+B60+B48+B25+B17+B15) -> 0 | C83: =(C81+C79+C77+C69+C60+C48+C25+C17+C15) -> 0 | D83: =(D81+D79+D77+D69+D60+D48+D25+D17+D15) -> 0 | E83: =(E81+E79+E77+E69+E60+E48+E25+E17+E15) -> 0 | F83: =(F81+F79+F77+F69+F60+F48+F25+F17+F15) -> 0 | G83: =(G81+G79+G77+G69+G60+G48+G25+G17+G15) -> 0
A84: Previous City Funding***
A85: Current Request for City Funds | F85: =F83-F84 -> 0
A86: Total Project Costs Per Unit | B86: =B83/B6 -> #DIV/0! | C86: =C83/C6 -> #DIV/0! | D86: =D83/D6 -> #DIV/0! | E86: =E83/B6 -> #DIV/0! | F86: =F83/C6 -> #DIV/0! | G86: =G83/C6 -> #DIV/0!
A87: Total Project Costs Per Sq. Foot | B87: =B83/B5 -> #DIV/0! | C87: =C83/C5 -> #DIV/0! | D87: =D83/D5 -> #DIV/0! | E87: =E83/B5 -> #DIV/0! | F87: =F83/C5 -> #DIV/0! | G87: =G83/C5 -> #DIV/0!
A89: *If property has been donated, include the value of the donated property, and show as a source of funds in the financial summary.
A90: **This item is ineligible for HOME funding but may be an eligible cost if no HOME funds are awarded.
A91: *** Do not include predevelopment loans

Sheet Ex. 23 - Operating Budget
A1: 23. Operating Budget (Rental)
A3: Project Name
A4: Total Square Feet
A5: # of Units
A6: Total # of Bedrooms
A7: Operating Expenses | B7: HUD Number | C7: Total Annual | D7: Per Unit Cost
A8: Management
A9: Management Fee | B9: 6320 | D9: =C9/$B$5 -> #DIV/0!
A10: Administrative Rent Free Unit | B10: 6331 | D10: =C10/$B$5 -> #DIV/0!
A11: sub-total Management Expenses: | C11: =SUM(C9:C10) -> 0 | D11: =SUM(D9:D10) -> #DIV/0!
A12: Administration
A13: Seminars & Training | B13: 6203 | D13: =C13/$B$5 -> #DIV/0!
A14: Advertising | B14: 6210 | D14: =C14/$B$5 -> #DIV/0!
A15: Office Supplies | B15: 6311 | D15: =C15/$B$5 -> #DIV/0!
A16: Office Rent | B16: 6312 | D16: =C16/$B$5 -> #DIV/0!
A17: Computer Charges | B17: 6314 | D17: =C17/$B$5 -> #DIV/0!
A18: Legal | B18: 6210 | D18: =C18/$B$5 -> #DIV/0!
A19: Other Professional Fees | B19: 6349 | D19: =C19/$B$5 -> #DIV/0!
A20: Audit | B20: 6350 | D20: =C20/$B$5 -> #DIV/0!
A21: Bookkeeping | B21: 6351 | D21: =C21/$B$5 -> #DIV/0!
A22: Telephone (office, fax, data, entry system) | B22: 6360 | D22: =C22/$B$5 -> #DIV/0!
A23: Bad Debts | B23: 6370 | D23: =C23/$B$5 -> #DIV/0!
A24: Social/Dues/Travel/Equip. maint. | B24: 6390 | D24: =C24/$B$5 -> #DIV/0!
... A28: Other:___________________________ | B28: 6390 | D28: =C28/$B$5 -> #DIV/0!
A29: sub-total Administration Expenses: | C29: =SUM(C13:C28) -> 0 | D29: =SUM(D13:D28) -> #DIV/0!
A30: Personnel
A31: On-Site Manager(s) | B31: 6330 | D31: =C31/$B$5 -> #DIV/0!
A32: Desk Clerk/Security | B32: 6530 | D32: =C32/$B$5 -> #DIV/0!
A33: Grounds, Janitorial, Repairs and Maintenance | B33: 6540 | D33: =C33/$B$5 -> #DIV/0!
A34: Payroll Taxes | B34: 6711 | D34: =C34/$B$5 -> #DIV/0!
A35: Worker's Compensation | B35: 6722 | D35: =C35/$B$5 -> #DIV/0!
A36: Health Benefits | B36: 6723 | D36: =C36/$B$5 -> #DIV/0!
A37: Retirement Benefits | D37: =C37/$B$5 -> #DIV/0!
A38: Unemployment Insurance | D38: =C38/$B$5 -> #DIV/0!
A39: Other Salary/Benefit Expenses | B39: 6540 | D39: =C39/$B$5 -> #DIV/0!
A40: sub-total Personnel Expenses: | C40: =SUM(C31:C39) -> 0 | D40: =SUM(D31:D39) -> #DIV/0!
A41: Taxes, Licenses and Permits
A42: Real Estate Taxes | B42: 6710 | D42: =C42/$B$5 -> #DIV/0!
A43: Miscellaneous Taxes, Licenses, and Permits | B43: 6719 | D43: =C43/$B$5 -> #DIV/0!
A44: sub-total Taxes, License and Permit Expenses: | C44: =SUM(C42:C43) -> 0 | D44: =SUM(D42:D43) -> #DIV/0!
A45: Insurance
A46: Property and Liability Insurance | B46: 6720 | D46: =C46/$B$5 -> #DIV/0!
A47: Fidelity Bond Insurance | B47: 6721 | D47: =C47/$B$5 -> #DIV/0!
A48: Other Insurance | B48: 6729 | D48: =C48/$B$5 -> #DIV/0!
A49: sub-total Insurance Expenses: | C49: =SUM(C46:C48) -> 0 | D49: =SUM(D46:D48) -> #DIV/0!
A50: Utilities
A51: Electricity | B51: 6450 | D51: =C51/$B$5 -> #DIV/0!
A52: Water | B52: 6451 | D52: =C52/$B$5 -> #DIV/0!
A53: Gas | B53: 6452 | D53: =C53/$B$5 -> #DIV/0!
A54: Sewer | B54: 6453 | D54: =C54/$B$5 -> #DIV/0!
A55: Trash Removal | B55: 6525 | D55: =C55/$B$5 -> #DIV/0!
A56: sub-total Utilities Expenses: | C56: =SUM(C51:C55) -> 0 | D56: =SUM(D51:D55) -> #DIV/0!
A57: Maintenance
A58: Cleaning Supplies | B58: 6515 | D58: =C58/$B$5 -> #DIV/0!
A59: Contract Cleaning | B59: 6517 | D59: =C59/$B$5 -> #DIV/0!
A60: Pest Control | B60: 6519 | D60: =C60/$B$5 -> #DIV/0!
A61: Security | B61: 6533 | D61: =C61/$B$5 -> #DIV/0!
A62: Fire Alarm Expense (incl. phone) | B62: 6534 | D62: =C62/$B$5 -> #DIV/0!
A63: Grounds, Repairs & Maintenance | B63: 6537 | D63: =C63/$B$5 -> #DIV/0!
A64: Grounds, Repairs & Maintenance Supplies | B64: 6541 | D64: =C64/$B$5 -> #DIV/0!
A65: Elevator Maintenance (incl. phone) | B65: 6545 | D65: =C65/$B$5 -> #DIV/0!
A66: Plumbing, Electrical, HVAC Maintenance | B66: 6546 | D66: =C66/$B$5 -> #DIV/0!
A67: Painting and Decorating | B67: 6561 | D67: =C67/$B$5 -> #DIV/0!
A68: Exterior Paining | B68: 6565 | D68: =C68/$B$5 -> #DIV/0!
A69: Furniture | D69: =C69/$B$5 -> #DIV/0!
A70: Window Covering & Carpeting | B70: 6566 | D70: =C70/$B$5 -> #DIV/0!
A71: Vehicle and Maintenance Equipment Operation and Repairs | B71: 6571 | D71: =C71/$B$5 -> #DIV/0!
A72: Cable/Tools | D72: =C72/$B$5 -> #DIV/0!
A73: Miscellaneous Operating & Maintenance | B73: 6590 | D73: =C73/$B$5 -> #DIV/0!
A74: sub-total Maintenance Expenses: | C74: =SUM(C58:C73) -> 0 | D74: =SUM(D58:D73) -> #DIV/0!
A75: Services
A76: Social Service Coordination* | D76: =C76/$B$5 -> #DIV/0!
A77: sub-total Services Expenses: | C77: =SUM(C76) -> 0 | D77: =SUM(D76) -> #DIV/0!
A78: Total Operating Expenses | C78: =SUM(C74,C56,C49,C44,C40,C29,C11,C77) -> 0 | D78: =SUM(D74,D56,D49,D44,D40,D29,D11,D77) -> #DIV/0!
A81: Reserves, Debt Service, & Fees | C81: Total Annual | D81: Per Unit Cost
A82: Reserves
A83: Operating Reserve Deposit | D83: =C83/$B$5 -> #DIV/0!
A84: Replacement Reserve Deposit | D84: =C84/$B$5 -> #DIV/0!
A85: Other: _________________________ | D85: =C85/$B$5 -> #DIV/0!
A86: sub-total Reserve Deposits: | C86: =SUM(C83:C85) -> 0 | D86: =SUM(D83:D85) -> #DIV/0!
A87: Debt Service
A88: Lender:___________________________ | D88: =C88/$B$5 -> #DIV/0!
A89: Lender:___________________________ | D89: =C89/$B$5 -> #DIV/0!
A90: Lender:___________________________ | D90: =C90/$B$5 -> #DIV/0!
A91: sub-total Debt Service: | C91: =SUM(C88:C90) -> 0 | D91: =SUM(D88:D90) -> #DIV/0!
A92: Other Fees
A93: Deferred Developer Fee | D93: =C93/$B$5 -> #DIV/0!
A94: Partnership/Asset Management Fee** | D94: =C94/$B$5 -> #DIV/0!
A95: City of Oakland Monitoring Fee | C95: =B5*100 -> 0 | D95: =C95/$B$5 -> #DIV/0!
A96: sub-total Other Fees: | C96: =SUM(C93:C94) -> 0 | D96: =SUM(D93:D95) -> #DIV/0!
A97: * Social Service Coordination is an eligible operating cost. Direct Social Service provision cannot be funded by operations unless it is a requirement of another funding source.
A98: ** Review the Developer Fee Guidelines for allowable Partnership and Asset Management Fees.

Sheet Exhibit 24 - 30 Year Proforma
A1: Exhibit 24: 30 Year Proforma (use this worksheet or submit your own worksheet in Excel)
A3: Project Name
A4: # of Units
A5: Total # of Bedrooms
C10: 2016 | D10: =C10+1 -> 2017 | E10: =D10+1 -> 2018 | F10: =E10+1 -> 2019 | G10: =F10+1 -> 2020 | H10: =G10+1 -> 2021 | I10: =H10+1 -> 2022 | J10: =I10+1 -> 2023 | K10: =J10+1 -> 2024 | ... AF10: =AE10+1 -> 2045
B11: Inflation Factor | C11: 1 | D11: =C11+1 -> 2 | E11: =D11+1 -> 3 | F11: =E11+1 -> 4 | G11: =F11+1 -> 5 | H11: =G11+1 -> 6 | I11: =H11+1 -> 7 | J11: =I11+1 -> 8 | K11: =J11+1 -> 9 | ... AF11: =AE11+1 -> 30
A12: Total Rental Income | B12: 0.025 | C12: ='Ex 26 - Unit Affordability'!M42 -> 0 | D12: =$C$12*(1+$B$12) -> 0 | E12: =D12*(1+$B$12) -> 0 | F12: =E12*(1+$B$12) -> 0 | G12: =F12*(1+$B$12) -> 0 | H12: =G12*(1+$B$12) -> 0 | I12: =H12*(1+$B$12) -> 0 | J12: =I12*(1+$B$12) -> 0 | K12: =J12*(1+$B$12) -> 0 | L12: =K12*(1+$B$12) -> 0 | ... AF12: =AE12*(1+$B$12) -> 0
A13: Other: laundry | B13: 0 | D13: =$C$13*(1+$B$13) -> 0 | E13: =$C$13*(1+$B$13) -> 0 | F13: =$C$13*(1+$B$13) -> 0 | G13: =$C$13*(1+$B$13) -> 0 | H13: =$C$13*(1+$B$13) -> 0 | I13: =$C$13*(1+$B$13) -> 0 | J13: =$C$13*(1+$B$13) -> 0 | K13: =$C$13*(1+$B$13) -> 0 | ... AF13: =$C$13*(1+$B$13) -> 0
A14: Other: vending | D14: =$C$14*(1+$B$14) -> 0 | E14: =D14*(1+$B$14) -> 0 | F14: =E14*(1+$B$14) -> 0 | G14: =F14*(1+$B$14) -> 0 | H14: =G14*(1+$B$14) -> 0 | I14: =H14*(1+$B$14) -> 0 | J14: =I14*(1+$B$14) -> 0 | K14: =J14*(1+$B$14) -> 0 | L14: =K14*(1+$B$14) -> 0 | ... AF14: =AE14*(1+$B$14) -> 0
A15: Other: | D15: =$C$15*(1+$B$15) -> 0 | E15: =D15*(1+$B$15) -> 0 | F15: =E15*(1+$B$15) -> 0 | G15: =F15*(1+$B$15) -> 0 | H15: =G15*(1+$B$15) -> 0 | I15: =H15*(1+$B$15) -> 0 | J15: =I15*(1+$B$15) -> 0 | K15: =J15*(1+$B$15) -> 0 | L15: =K15*(1+$B$15) -> 0 | ... AF15: =AE15*(1+$B$15) -> 0
A16: Other: | D16: =$C$16*(1+$B$16) -> 0 | E16: =D16*(1+$B$16) -> 0 | F16: =E16*(1+$B$16) -> 0 | G16: =F16*(1+$B$16) -> 0 | H16: =G16*(1+$B$16) -> 0 | I16: =H16*(1+$B$16) -> 0 | J16: =I16*(1+$B$16) -> 0 | K16: =J16*(1+$B$16) -> 0 | L16: =K16*(1+$B$16) -> 0 | ... AF16: =AE16*(1+$B$16) -> 0
A17: TOTAL GROSS POTENTIAL REVENUE | C17: =SUM(C12:C16) -> 0 | D17: =SUM(D12:D16) -> 0 | E17: =SUM(E12:E16) -> 0 | F17: =SUM(F12:F16) -> 0 | G17: =SUM(G12:G16) -> 0 | H17: =SUM(H12:H16) -> 0 | I17: =SUM(I12:I16) -> 0 | J17: =SUM(J12:J16) -> 0 | ... AF17: =SUM(AF12:AF16) -> 0
A19: Vacancy (5%, or 10% for special needs/SRO) | B19: 0.05 | C19: =C12*$B$19 -> 0 | D19: =D12*$B$19 -> 0 | E19: =E12*$B$19 -> 0 | F19: =F12*$B$19 -> 0 | G19: =G12*$B$19 -> 0 | H19: =H12*$B$19 -> 0 | I19: =I12*$B$19 -> 0 | J19: =J12*$B$19 -> 0 | ... AF19: =AF12*$B$19 -> 0
A21: EFFECTIVE GROSS INCOME | C21: =C17-C19 -> 0 | D21: =D17-D19 -> 0 | E21: =E17-E19 -> 0 | F21: =F17-F19 -> 0 | G21: =G17-G19 -> 0 | H21: =H17-H19 -> 0 | I21: =I17-I19 -> 0 | J21: =J17-J19 -> 0 | ... AF21: =AF17-AF19 -> 0
A23: Operating Expenses | B23: 0.035 | C23: ='Ex. 23 - Operating Budget'!C78 -> 0 | D23: =C23*(1+$B$23) -> 0 | E23: =D23*(1+$B$23) -> 0 | F23: =E23*(1+$B$23) -> 0 | G23: =F23*(1+$B$23) -> 0 | H23: =G23*(1+$B$23) -> 0 | I23: =H23*(1+$B$23) -> 0 | J23: =I23*(1+$B$23) -> 0 | K23: =J23*(1+$B$23) -> 0 | ... AF23: =AE23*(1+$B$23) -> 0
A24: Other: | C24: 0 | D24: =$C$24*(1+$B$24) -> 0 | E24: =D24*(1+$B$24) -> 0 | F24: =E24*(1+$B$24) -> 0 | G24: =F24*(1+$B$24) -> 0 | H24: =G24*(1+$B$24) -> 0 | I24: =H24*(1+$B$24) -> 0 | J24: =I24*(1+$B$24) -> 0 | K24: =J24*(1+$B$24) -> 0 | L24: =K24*(1+$B$24) -> 0 | ... AF24: =AE24*(1+$B$24) -> 0
A25: Other: | C25: 0 | D25: =$C$25*(1+$B$25) -> 0 | E25: =D25*(1+$B$25) -> 0 | F25: =E25*(1+$B$25) -> 0 | G25: =F25*(1+$B$25) -> 0 | H25: =G25*(1+$B$25) -> 0 | I25: =H25*(1+$B$25) -> 0 | J25: =I25*(1+$B$25) -> 0 | K25: =J25*(1+$B$25) -> 0 | L25: =K25*(1+$B$25) -> 0 | ... AF25: =AE25*(1+$B$25) -> 0
A26: Other: | C26: 0 | D26: =$C$26*(1+$B$26) -> 0 | E26: =D26*(1+$B$26) -> 0 | F26: =E26*(1+$B$26) -> 0 | G26: =F26*(1+$B$26) -> 0 | H26: =G26*(1+$B$26) -> 0 | I26: =H26*(1+$B$26) -> 0 | J26: =I26*(1+$B$26) -> 0 | K26: =J26*(1+$B$26) -> 0 | L26: =K26*(1+$B$26) -> 0 | ... AF26: =AE26*(1+$B$26) -> 0
A27: NET OPERATING INCOME | C27: =C21-(C23+C24+C25+C26) -> 0 | D27: =D21-(D23+D24+D25+D26) -> 0 | E27: =E21-(E23+E24+E25+E26) -> 0 | F27: =F21-(F23+F24+F25+F26) -> 0 | G27: =G21-(G23+G24+G25+G26) -> 0 | H27: =H21-(H23+H24+H25+H26) -> 0 | I27: =I21-(I23+I24+I25+I26) -> 0 | J27: =J21-(J23+J24+J25+J26) -> 0 | ... AF27: =AF21-(AF23+AF24+AF25+AF26) -> 0
A29: (Less Debt Service) | C29: ='Ex. 23 - Operating Budget'!C91 -> 0 | D29: =$C$29 -> 0 | E29: =$C$29 -> 0 | F29: =$C$29 -> 0 | G29: =$C$29 -> 0 | H29: =$C$29 -> 0 | I29: =$C$29 -> 0 | J29: =$C$29 -> 0 | K29: =$C$29 -> 0 | ... AF29: =$C$29 -> 0
A30: (Less Operating Reserves) | C30: ='Ex. 23 - Operating Budget'!C83 -> 0 | D30: =$C$30 -> 0 | E30: =$C$30 -> 0 | F30: =$C$30 -> 0 | G30: =$C$30 -> 0 | H30: =$C$30 -> 0 | I30: =$C$30 -> 0 | J30: =$C$30 -> 0 | K30: =$C$30 -> 0 | ... AF30: =$C$30 -> 0
A31: (Less Replacement Reserves) | C31: ='Ex. 23 - Operating Budget'!C84 -> 0 | D31: =$C$31 -> 0 | E31: =$C$31 -> 0 | F31: =$C$31 -> 0 | G31: =$C$31 -> 0 | H31: =$C$31 -> 0 | I31: =$C$31 -> 0 | J31: =$C$31 -> 0 | K31: =$C$31 -> 0 | ... AF31: =$C$31 -> 0
A32: (Less Partnership/Asset Management Fee - if applicable) | B32: 0.03 | C32: ='Ex. 23 - Operating Budget'!C94 -> 0 | D32: =$C$32*(1+$B$32) -> 0 | E32: =$D$32*(1+$B$32) -> 0 | F32: =$E$32*(1+$B$32) -> 0 | G32: =$F$32*(1+$B$32) -> 0 | H32: =$G$32*(1+$B$32) -> 0 | I32: =$H$32*(1+$B$32) -> 0 | J32: =$I$32*(1+$B$32) -> 0 | K32: =$J$32*(1+$B$32) -> 0 | L32: =$K$32*(1+$B$32) -> 0 | M32: =$L$32*(1+$B$32) -> 0 | N32: =$M$32*(1+$B$32) -> 0 | O32: =$N$32*(1+$B$32) -> 0 | P32: =$O$32*(1+$B$32) -> 0 | Q32: =$P$32*(1+$B$32) -> 0 | R32: =$Q$32*(1+$B$32) -> 0 | S32: =$R$32*(1+$B$32) -> 0 | T32: =$S$32*(1+$B$32) -> 0 | U32: =$T$32*(1+$B$32) -> 0 | V32: =$U$32*(1+$B$32) -> 0 | W32: =$V$32*(1+$B$32) -> 0 | X32: =$W$32*(1+$B$32) -> 0 | Y32: =$X$32*(1+$B$32) -> 0 | Z32: =$Y$32*(1+$B$32) -> 0 | AA32: =$Z$32*(1+$B$32) -> 0 | AB32: =$AA$32*(1+$B$32) -> 0 | AC32: =$AB$32*(1+$B$32) -> 0 | AD32: =$AC$32*(1+$B$32) -> 0 | AE32: =$AD$32*(1+$B$32) -> 0 | AF32: =$AE$32*(1+$B$32) -> 0
A33: (Less City of Oakland Monitoring Fee) | C33: =B4*100 -> 0 | D33: =B4*100 -> 0 | E33: =B4*100 -> 0 | F33: =B4*100 -> 0 | G33: =B4*100 -> 0 | H33: =B4*100 -> 0 | I33: =B4*100 -> 0 | J33: =B4*100 -> 0 | K33: =B4*100 -> 0 | L33: =B4*100 -> 0 | M33: =B4*100 -> 0 | N33: =B4*100 -> 0 | O33: =B4*100 -> 0 | P33: =B4*100 -> 0 | Q33: =B4*100 -> 0 | R33: =B4*100 -> 0 | S33: =B4*100 -> 0 | T33: =B4*100 -> 0 | U33: =B4*100 -> 0 | V33: =B4*100 -> 0 | W33: =B4*100 -> 0 | X33: =B4*100 -> 0 | Y33: =B4*100 -> 0 | Z33: =B4*100 -> 0 | AA33: =B4*100 -> 0 | AB33: =B4*100 -> 0 | AC33: =B4*100 -> 0 | AD33: =B4*100 -> 0 | AE33: =B4*100 -> 0 | AF33: =B4*100 -> 0
A34: Other: | D34: =$C$34*(1+$B$34) -> 0 | E34: =D34*(1+$B$34) -> 0 | F34: =E34*(1+$B$34) -> 0 | G34: =F34*(1+$B$34) -> 0 | H34: =G34*(1+$B$34) -> 0 | I34: =H34*(1+$B$34) -> 0 | J34: =I34*(1+$B$34) -> 0 | K34: =J34*(1+$B$34) -> 0 | L34: =K34*(1+$B$34) -> 0 | ... AF34: =AE34*(1+$B$34) -> 0
A35: Other: | D35: =$C$35*(1+$B$35) -> 0 | E35: =D35*(1+$B$35) -> 0 | F35: =E35*(1+$B$35) -> 0 | G35: =F35*(1+$B$35) -> 0 | H35: =G35*(1+$B$35) -> 0 | I35: =H35*(1+$B$35) -> 0 | J35: =I35*(1+$B$35) -> 0 | K35: =J35*(1+$B$35) -> 0 | L35: =K35*(1+$B$35) -> 0 | ... AF35: =AE35*(1+$B$35) -> 0
A36: Other: | D36: =$C$36*(1+$B$36) -> 0 | E36: =D36*(1+$B$36) -> 0 | F36: =E36*(1+$B$36) -> 0 | G36: =F36*(1+$B$36) -> 0 | H36: =G36*(1+$B$36) -> 0 | I36: =H36*(1+$B$36) -> 0 | J36: =I36*(1+$B$36) -> 0 | K36: =J36*(1+$B$36) -> 0 | L36: =K36*(1+$B$36) -> 0 | ... AF36: =AE36*(1+$B$36) -> 0
A37: CASH FLOW | C37: =C27-(C29+C30+C31+C32+C34+C35+C36+C33) -> 0 | D37: =D27-(D29+D30+D31+D32+D34+D35+D36+D33) -> 0 | E37: =E27-(E29+E30+E31+E32+E34+E35+E36+E33) -> 0 | F37: =F27-(F29+F30+F31+F32+F34+F35+F36+F33) -> 0 | G37: =G27-(G29+G30+G31+G32+G34+G35+G36+G33) -> 0 | H37: =H27-(H29+H30+H31+H32+H34+H35+H36+H33) -> 0 | I37: =I27-(I29+I30+I31+I32+I34+I35+I36+I33) -> 0 | J37: =J27-(J29+J30+J31+J32+J34+J35+J36+J33) -> 0 | ... AF37: =AF27-(AF29+AF30+AF31+AF32+AF34+AF35+AF36+AF33) -> 0
A40: Does Cash Flow Drop Below Zero? | B40: =IF(COUNTIF(C37:AF37,"<0"),"YES","NO") -> NO
A41: If yes, provide a detailed explanation as to why the cash flow is negative and what precautionary measure will be taken to ensure the feasibility of the project.

Sheet Exhibit 25 - Financial Summ 
A1: Exhibit 25: Financial Summary Worksheet
A2: ='Ex. 10 - Repl. Unit Analysis'!A2:K2 -> [Project Name]
A3: 2014-15 Housing Development NOFA
B5: Entire Project | C5: Affordable Portion | D5: Market Rate Portion | E5: Commercial Portion
A6: Total Number of Units, including manager's unit(s) | B6: =C6+D6 -> 0
A7: Total Number of Bedrooms | B7: =C7+D7 -> 0
A9: Known and Anticipated Sources (Residential Portion Only) | B9: Total | C9: Affordable Portion Total | D9: Market Rate Portion Total | E9: Commercial Portion Total | F9: Per Unit | G9: Per Bedroom
A10: Previous City Funding1 | B10: =C10 -> 0 | F10: =B10/$C$6 -> #DIV/0! | G10: =B10/$C$7 -> #DIV/0!
A11: Current Request for City Funds | B11: =C11 -> 0 | F11: =B11/$C$6 -> #DIV/0! | G11: =B11/$C$7 -> #DIV/0!
A12: Subtotal City Funds | B12: =SUM(B10:B11) -> 0 | C12: =SUM(C10:C11) -> 0 | F12: =B12/$C$6 -> #DIV/0! | G12: =B12/$C$7 -> #DIV/0!
A13: Funding Source: _______________ | B13: =SUM(C13:E13) -> 0 | F13: =B13/$C$6 -> #DIV/0! | G13: =B13/$C$7 -> #DIV/0!
A14: Funding Source: _______________ | B14: =SUM(C14:E14) -> 0 | F14: =B14/$C$6 -> #DIV/0! | G14: =B14/$C$7 -> #DIV/0!
A15: Funding Source: _______________ | B15: =SUM(C15:E15) -> 0 | F15: =B15/$C$6 -> #DIV/0! | G15: =B15/$C$7 -> #DIV/0!
A16: Funding Source: _______________ | B16: =SUM(C16:E16) -> 0 | F16: =B16/$C$6 -> #DIV/0! | G16: =B16/$C$7 -> #DIV/0!
A17: Funding Source: _______________ | B17: =SUM(C17:E17) -> 0 | F17: =B17/$C$6 -> #DIV/0! | G17: =B17/$C$7 -> #DIV/0!
A18: Funding Source: _______________ | B18: =SUM(C18:E18) -> 0 | F18: =B18/$C$6 -> #DIV/0! | G18: =B18/$C$7 -> #DIV/0!
A19: Funding Source: _______________ | B19: =SUM(C19:E19) -> 0 | F19: =B19/$C$6 -> #DIV/0! | G19: =B19/$C$7 -> #DIV/0!
A20: Subtotal Non-City Funds | B20: =SUM(B13:B19) -> 0 | C20: =SUM(C13:C19) -> 0 | D20: =SUM(D13:D19) -> 0 | E20: =SUM(E13:E19) -> 0 | F20: =B20/$C$6 -> #DIV/0! | G20: =B20/$C$7 -> #DIV/0!
A21: Total Development Cost | B21: =B12+B20 -> 0 | C21: =C12+C20 -> 0 | D21: =D20 -> 0 | E21: =E20 -> 0 | F21: =B21/$C$6 -> #DIV/0! | G21: =B21/$C$7 -> #DIV/0!
A22: City funds % of TDC (Affordable Portion Only) | C22: =C12/C21 -> #DIV/0!
A23: Site Acquisition cost2 (all sources) | B23: =SUM(C23:D23) -> 0 | F23: =B23/$C$6 -> #DIV/0! | G23: =B23/$C$7 -> #DIV/0!
A24: TDC less Site Acquisition cost | B24: =B21-B23 -> 0 | C24: =C21-C23 -> 0 | D24: =D21-D23 -> 0 | E24: =E21-E23 -> 0 | F24: =B24/$C$6 -> #DIV/0! | G24: =B24/$C$7 -> #DIV/0!
A26: 1 Do not include City predevelopment loans.
A27: 2 Includes option payments, acquisition, and holding costs directly related to acquisition. Include value of donated property as a source.
A28: 3 Shaded cells represent ineligible uses of City funds

Sheet Ex 26 - Unit Affordability
A1: Exhibit 26: Unit Size and Affordability Worksheet (Rental)
A2: [Project Name]
A3: 2014-15 Housing Development NOFA
A4: Enter one type of unit per row; add rows if necessary.
A6: 1. Rental: Affordable Units
A7: Indicate percentage of AMI used to calculate rents (e.g., 30% of 50% of AMI) | B7: # of Units | C7: Unit Type (#BR / #Bath) | D7: Square Footage | E7: Maximum Tenant Income* | F7: Per Unit Monthly Rent (Estimated Tenant Contribution) | G7: Name of subsidy that is applied to the unit (If any) | H7: Per Unit Amount of Subsidy Applied To The Unit (If Any) | I7: Per Unit Rent Received** | J7: Total Monthly Rent for Unit Type** | K7: Per Unit Monthly Utility Allowances* | L7: Total Gross Monthly Payment Per Unit (Incl. Utilities) | M7: Accessible Unit? (Mobility, Visual/Hearing, etc)
I8: =F8+H8 -> 0 | J8: =(F8+H8)*B8 -> 0 | L8: =F8+H8+K8 -> 0
I9: =F9+H9 -> 0 | J9: =(F9+H9)*B9 -> 0 | L9: =F9+H9+K9 -> 0
I10: =F10+H10 -> 0 | J10: =(F10+H10)*B10 -> 0 | L10: =F10+H10+K10 -> 0
I11: =F11+H11 -> 0 | J11: =(F11+H11)*B11 -> 0 | L11: =F11+H11+K11 -> 0
I12: =F12+H12 -> 0 | J12: =(F12+H12)*B12 -> 0 | L12: =F12+H12+K12 -> 0
I13: =F13+H13 -> 0 | J13: =(F13+H13)*B13 -> 0 | L13: =F13+H13+K13 -> 0
I14: =F14+H14 -> 0 | J14: =(F14+H14)*B14 -> 0 | L14: =F14+H14+K14 -> 0
I15: =F15+H15 -> 0 | J15: =(F15+H15)*B15 -> 0 | L15: =F15+H15+K15 -> 0
I16: =F16+H16 -> 0 | J16: =(F16+H16)*B16 -> 0 | L16: =F16+H16+K16 -> 0
I17: =F17+H17 -> 0 | J17: =(F17+H17)*B17 -> 0 | L17: =F17+H17+K17 -> 0
I18: =F18+H18 -> 0 | J18: =(F18+H18)*B18 -> 0 | L18: =F18+H18+K18 -> 0
I19: =F19+H19 -> 0 | J19: =(F19+H19)*B19 -> 0 | L19: =F19+H19+K19 -> 0
I20: =F20+H20 -> 0 | J20: =(F20+H20)*B20 -> 0 | L20: =F20+H20+K20 -> 0
A21: Total # Units | B21: =SUM(B8:B20) -> 0 | I21: Total Monthly Rental Income | J21: =SUM(J8:J20) -> 0 | L21: ↑
A23: 2. Managers' Units***
A24: Indicate percentage of AMI used to calculate rents (e.g., 30% of 50% of AMI) | B24: # of Units | C24: Unit Type (#BR / #Bath) | D24: Square Footage | I24: Proposed Monthly Rent | J24: Total Monthly Rents | L24: Rents in this column may not exceed Maximum Rents Per Addendum, Income, Rent & Housing Payment Limits
J25: =I25*B25 -> 0
J26: =I26*B26 -> 0
J27: =I27*B27 -> 0
A28: Total # Units | B28: =SUM(B25:B27) -> 0 | I28: Total Monthly Rental Income | J28: =SUM(J25:J27) -> 0
A30: 3. Market Rate Units
B31: # of Units | C31: Unit Type (#BR / #Bath) | D31: Square Footage | I31: Proposed Monthly Rent | J31: Total Monthly Rents
J32: =I32*B32 -> 0
J33: =I33*B33 -> 0
J34: =I34*B34 -> 0
A35: Total # Units | B35: =SUM(B32:B34) -> 0 | I35: Total Monthly Rental Income | J35: =SUM(J32:J34) -> 0
A37: 4. Affordability Summary/City Restrictions | L37: 5. Annual Rental Revenue
A38: This summary reflects the rent restrictions according to the City's requirements only and won't necessarily match the actual rent structure detailed in table 1 above. | L38: Total Monthly Rents for ALL units | M38: =J35+J28+J21 -> 0
A39: =SUM(B35,B28,B21) -> 0 | B39: Total Project Units | E39: % of Units
D40: % units with annual rents ≤ 30% of 30% AMI | M40: x12
D41: % units with annual rents ≤ 30% of 60% AMI
L42: Total Annual Rents for ALL Units | M42: =M38*12 -> 0
A43: 6. Tenant-Paid Utility Breakdown | F43: 7. Unit Type Summary
A44: Indicate which utilites will be paid by tenant (T) and which utilities will be paid by landlord (L).
B45: Gas | C45: Electric | F45: Unit Type | G45: # of Units | H45: # of Special Needs Units | I45: # of Homeless Units
A46: Space Heating | F46: SRO
A47: Lighting | F47: Studio
A48: Cooking | F48: 1 bedroom
A49: Hot Water | F49: 2 bedroom
A50: Water | F50: 3 bedroom
A51: Garbage | F51: 4 bedroom
A53: * See Addendum: "Income, Rent, Utility Allowance, Housing Payments Limits" for current utility allowances and rents.
A54: ** Including project-based rental assistance from Section 8, Public Housing ACC, HOPWA, Shelter Plus Care or similar project-based assistance.
A55: *** Rent for manager's unit(s) should be listed as income here and an expense on the operating budget.

Sheet Unit Affordability Example
A1: Exhibit 26: Unit Size and Affordability Worksheet (Rental)
A2: Sample
A3: 2014-15 Housing Development NOFA
A4: Enter one type of unit per row; add rows if necessary.
A6: 1. Rental: Affordable Units
A7: Indicate percentage of AMI used to calculate rents (e.g., 30% of 50% of AMI) | B7: # of Units | C7: Unit Type (#BR / #Bath) | D7: Square Footage | E7: Maximum Tenant Income* | F7: Per Unit Monthly Rent (Estimated Tenant Contribution) | G7: Name of subsidy that is applied to the unit (If any) | H7: Per Unit Amount of Subsidy Applied To The Unit (If Any) | I7: Per Unit Rent Received** | J7: Total Monthly Rent for Unit Type** | K7: Per Unit Monthly Utility Allowances* | L7: Total Gross Monthly Payment Per Unit (Incl. Utilities) | M7: Accessible Unit? (Mobility, Visual/Hearing, etc)
A8: 30% of 30% AMI | B8: 10 | C8: 2/1 | D8: 900 | E8: 0.3 | F8: 400 | G8: PBS8 | H8: 500 | I8: =F8+H8 -> 900 | J8: =(F8+H8)*B8 -> 9000 | K8: 90 | L8: =F8+H8+K8 -> 990 | M8: Mobility
A9: 30% of 50% AMI | B9: 20 | C9: 1/1 | D9: 500 | E9: 0.5 | F9: 700 | H9: 0 | I9: =F9+H9 -> 700 | J9: =(F9+H9)*B9 -> 14000 | K9: 70 | L9: =F9+H9+K9 -> 770 | M9: Visual/Hearing
A10: 30% of 50% AMI | B10: 20 | C10: 2/1 | D10: 900 | E10: 0.5 | F10: 650 | G10: PBS8 | H10: 250 | I10: =F10+H10 -> 900 | J10: =(F10+H10)*B10 -> 18000 | K10: 90 | L10: =F10+H10+K10 -> 990
I11: =F11+H11 -> 0 | J11: =(F11+H11)*B11 -> 0 | L11: =F11+H11+K11 -> 0
I12: =F12+H12 -> 0 | J12: =(F12+H12)*B12 -> 0 | L12: =F12+H12+K12 -> 0
I13: =F13+H13 -> 0 | J13: =(F13+H13)*B13 -> 0 | L13: =F13+H13+K13 -> 0
I14: =F14+H14 -> 0 | J14: =(F14+H14)*B14 -> 0 | L14: =F14+H14+K14 -> 0
I15: =F15+H15 -> 0 | J15: =(F15+H15)*B15 -> 0 | L15: =F15+H15+K15 -> 0
I16: =F16+H16 -> 0 | J16: =(F16+H16)*B16 -> 0 | L16: =F16+H16+K16 -> 0
A17: Total # Units | B17: =SUM(B8:B16) -> 50 | I17: Total Monthly Rental Income | J17: =SUM(J8:J16) -> 41000 | L17: ↑
A19: 2. Managers' Units***
A20: Indicate percentage of AMI used to calculate rents (e.g., 30% of 50% of AMI) | B20: # of Units | C20: Unit Type (#BR / #Bath) | D20: Square Footage | I20: Proposed Monthly Rent | J20: Total Monthly Rents | L20: Rents in this column may not exceed Maximum Rents Per Addendum, Income, Rent & Housing Payment Limits
B21: 1 | C21: 2/2 | D21: 1300 | I21: 1300 | J21: =I21*B21 -> 1300
J22: =I22*B22 -> 0
J23: =I23*B23 -> 0
A24: Total # Units | B24: =SUM(B21:B23) -> 1 | I24: Total Monthly Rental Income | J24: =SUM(J21:J23) -> 1300
A26: 3. Market Rate Units
B27: # of Units | C27: Unit Type (#BR / #Bath) | D27: Square Footage | I27: Proposed Monthly Rent | J27: Total Monthly Rents
J28: =I28*B28 -> 0
J29: =I29*B29 -> 0
J30: =I30*B30 -> 0
A31: Total # Units | B31: =SUM(B28:B30) -> 0 | I31: Total Monthly Rental Income | J31: =SUM(J28:J30) -> 0
A33: 4. Affordability Summary/City Restrictions | L33: 5. Annual Rental Revenue
A34: This summary reflects the rent restrictions according to the City's requirements only and won't necessarily match the actual rent structure detailed in table 1 above. | L34: Total Monthly Rents for ALL units | M34: =J31+J24+J17 -> 42300
A35: =SUM(B31,B24,B17) -> 51 | B35: Total Project Units | E35: % of Units
D36: % units with annual rents ≤ 30% of 30% AMI | E36: =10/50 -> 0.2 | M36: x12
D37: % units with annual rents ≤ 30% of 60% AMI | E37: =40/50 -> 0.8
L38: Total Annual Rents for ALL Units | M38: =M34*12 -> 507600
A39: 6. Tenant-Paid Utility Breakdown | F39: 7. Unit Type Summary
A40: Indicate which utilites will be paid by tenant (T) and which utilities will be paid by landlord (L).
B41: Gas | C41: Electric | F41: Unit Type | G41: # of Units | H41: # of Special Needs Units | I41: # of Homeless Units
A42: Space Heating | C42: T | F42: SRO
A43: Lighting | C43: T | F43: Studio
A44: Cooking | C44: T | F44: 1 bedroom | G44: 25 | H44: 10 | I44: 5
A45: Hot Water | B45: L | F45: 2 bedroom | G45: 25 | H45: 10 | I45: 5
A46: Water | B46: L | F46: 3 bedroom
A47: Garbage | B47: L | F47: 4 bedroom
A49: * See Addendum: "Income, Rent, Utility Allowance, Housing Payments Limits" for current utility allowances and rents.
A50: ** Including project-based rental assistance from Section 8, Public Housing ACC, HOPWA, Shelter Plus Care or similar project-based assistance.
A51: *** Rent for manager's unit(s) should be listed as income here and an expense on the operating budget.

Sheet Sheet1
