Workbook

Sheet Summary
A1: Community and Technical Colleges, Report of Fundable Operating Expenses, Fiscal Year (FY) 2012
A2: Summary of Expense divided Contact Hours
A3: Contact Hours for fall 2011 and spring and summer 2012
A4: Fund | B4: Total Expense by Discipline | D4: Contact Hours | E4: Expense | F4: Expense per Contact Hour
A5: 1 | B5: Agriculture | D5: =D36 -> 1622682 | E5: =E36+E67+IFERROR($E$105/$D$105*D5,0) -> 14698531 | F5: =IFERROR(E5/D5,"") -> 9.058171
A6: 2 | B6: Architecture and Precision Production Trades | D6: =D37 -> 4408564 | E6: =E37+E68+IFERROR($E$105/$D$105*D6,0) -> 41437241 | F6: =IFERROR(E6/D6,"") -> 9.3992604
A7: 3 | B7: Biology, Physical Sciences, and Science Technology | D7: =D38 -> 38841237 | E7: =E38+E69+IFERROR($E$105/$D$105*D7,0) -> 3.031945e+08 | F7: =IFERROR(E7/D7,"") -> 7.805995
A8: 4 | B8: Business Management, Marketing, and Administrative Services | D8: =D39 -> 21395229 | E8: =E39+E70+IFERROR($E$105/$D$105*D8,0) -> 1.6629155e+08 | F8: =IFERROR(E8/D8,"") -> 7.7723659
A9: 5 | B9: Career Pilot | D9: =D40 -> 198523 | E9: =E40+E71+IFERROR($E$105/$D$105*D9,0) -> 5811341.2 | F9: =IFERROR(E9/D9,"") -> 29.272886
A10: 6 | B10: Communications | D10: =D41 -> 3948618 | E10: =E41+E72+IFERROR($E$105/$D$105*D10,0) -> 34998289 | F10: =IFERROR(E10/D10,"") -> 8.8634273
A11: 7 | B11: Computer and Information Sciences | D11: =D42 -> 12167284 | E11: =E42+E73+IFERROR($E$105/$D$105*D11,0) -> 1.1539888e+08 | F11: =IFERROR(E11/D11,"") -> 9.4843582
A12: 8 | B12: Construction Trades | D12: =D43 -> 1877680 | E12: =E43+E74+IFERROR($E$105/$D$105*D12,0) -> 17801770 | F12: =IFERROR(E12/D12,"") -> 9.4807263
A13: 9 | B13: Consumer and Homemaking Education | D13: =D44 -> 10305568 | E13: =E44+E75+IFERROR($E$105/$D$105*D13,0) -> 85748387 | F13: =IFERROR(E13/D13,"") -> 8.3205882
A14: 10 | B14: Engineering | D14: =D45 -> 275947 | E14: =E45+E76+IFERROR($E$105/$D$105*D14,0) -> 4317775.5 | F14: =IFERROR(E14/D14,"") -> 15.647119
A15: 11 | B15: Engineering Related | D15: =D46 -> 8000857 | E15: =E46+E77+IFERROR($E$105/$D$105*D15,0) -> 70430093 | F15: =IFERROR(E15/D15,"") -> 8.8028186
A16: 12 | B16: English Language, Lit, Philosophy, Humanities, & Interdisciplinary | D16: =D47 -> 34525850 | E16: =E47+E78+IFERROR($E$105/$D$105*D16,0) -> 2.9311839e+08 | F16: =IFERROR(E16/D16,"") -> 8.4898241
... A32: 29 | B32: Developmental Education - Reading/Writing | D32: =D63 -> 16713968 | E32: =E63+E94+IFERROR($E$105/$D$105*D32,0) -> 1.2580564e+08 | F32: =IFERROR(E32/D32,"") -> 7.5269762
B33: Total | D33: =SUM(D5:D32) -> 320121176 | E33: =SUM(E5:E32) -> 2696113474 | F33: =IFERROR(E33/D33,"") -> 8.4221653
A35: Fund | B35: Departmental Operating Expense by Discipline | D35: Contact Hours | E35: Expense | F35: Expense per Contact Hour
A36: 1 | B36: Agriculture | D36: =SUM('1:57'!D36) -> 1622682 | E36: =SUM('1:57'!E36) -> 3193312 | F36: =IFERROR(E36/D36,"") -> 1.9679222
A37: 2 | B37: Architecture and Precision Production Trades | D37: =SUM('1:57'!D37) -> 4408564 | E37: =SUM('1:57'!E37) -> 8584755 | F37: =IFERROR(E37/D37,"") -> 1.9472905
A38: 3 | B38: Biology, Physical Sciences, and Science Technology | D38: =SUM('1:57'!D38) -> 38841237 | E38: =SUM('1:57'!E38) -> 43857452 | F38: =IFERROR(E38/D38,"") -> 1.1291466
A39: 4 | B39: Business Management, Marketing, and Administrative Services | D39: =SUM('1:57'!D39) -> 21395229 | E39: =SUM('1:57'!E39) -> 24714644 | F39: =IFERROR(E39/D39,"") -> 1.1551474
A40: 5 | B40: Career Pilot | D40: =SUM('1:57'!D40) -> 198523 | E40: =SUM('1:57'!E40) -> 3353138 | F40: =IFERROR(E40/D40,"") -> 16.890426
A41: 6 | B41: Communications | D41: =SUM('1:57'!D41) -> 3948618 | E41: =SUM('1:57'!E41) -> 9450129 | F41: =IFERROR(E41/D41,"") -> 2.3932751
A42: 7 | B42: Computer and Information Sciences | D42: =SUM('1:57'!D42) -> 12167284 | E42: =SUM('1:57'!E42) -> 21169024 | F42: =IFERROR(E42/D42,"") -> 1.7398315
A43: 8 | B43: Construction Trades | D43: =SUM('1:57'!D43) -> 1877680 | E43: =SUM('1:57'!E43) -> 4109900 | F43: =IFERROR(E43/D43,"") -> 2.1888181
A44: 9 | B44: Consumer and Homemaking Education | D44: =SUM('1:57'!D44) -> 10305568 | E44: =SUM('1:57'!E44) -> 16817152 | F44: =IFERROR(E44/D44,"") -> 1.6318511
A45: 10 | B45: Engineering | D45: =SUM('1:57'!D45) -> 275947 | E45: =SUM('1:57'!E45) -> 855492 | F45: =IFERROR(E45/D45,"") -> 3.100204
A46: 11 | B46: Engineering Related | D46: =SUM('1:57'!D46) -> 8000857 | E46: =SUM('1:57'!E46) -> 14710708 | F46: =IFERROR(E46/D46,"") -> 1.8386415
A47: 12 | B47: English Language, Lit, Philosophy, Humanities, & Interdisciplinary | D47: =SUM('1:57'!D47) -> 34525850 | E47: =SUM('1:57'!E47) -> 38273619 | F47: =IFERROR(E47/D47,"") -> 1.1085497
... A63: 29 | B63: Developmental Education - Reading/Writing | D63: =SUM('1:57'!D63) -> 16713968 | E63: =SUM('1:57'!E63) -> 12942992 | F63: =IFERROR(E63/D63,"") -> 0.77438176
C64: Total | D64: =SUM(D36:D63) -> 320121176 | E64: =SUM(E36:E63) -> 409822393 | F64: =IFERROR(E64/D64,"") -> 1.2802102
A66: Fund | B66: Faculty Salaries by Discipline | D66: Contact Hours | E66: Expense | F66: Expense per Contact Hour
A67: 1 | B67: Agriculture | D67: =D36 -> 1622682 | E67: =SUM('1:57'!E67) -> 5259237 | F67: =IFERROR(E67/D67,"") -> 3.2410768
A68: 2 | B68: Architecture and Precision Production Trades | D68: =D37 -> 4408564 | E68: =SUM('1:57'!E68) -> 15883165 | F68: =IFERROR(E68/D68,"") -> 3.6027979
A69: 3 | B69: Biology, Physical Sciences, and Science Technology | D69: =D38 -> 38841237 | E69: =SUM('1:57'!E69) -> 109830449 | F69: =IFERROR(E69/D69,"") -> 2.8276764
A70: 4 | B70: Business Management, Marketing, and Administrative Services | D70: =D39 -> 21395229 | E70: =SUM('1:57'!E70) -> 59222988 | F70: =IFERROR(E70/D70,"") -> 2.7680465
A71: 5 | B71: Career Pilot | D71: =D40 -> 198523 | E71: =SUM('1:57'!E71) -> 1694054 | F71: =IFERROR(E71/D71,"") -> 8.5332883
A72: 6 | B72: Communications | D72: =D41 -> 3948618 | E72: =SUM('1:57'!E72) -> 10349250 | F72: =IFERROR(E72/D72,"") -> 2.6209803
A73: 7 | B73: Computer and Information Sciences | D73: =D42 -> 12167284 | E73: =SUM('1:57'!E73) -> 47395887 | F73: =IFERROR(E73/D73,"") -> 3.8953547
A74: 8 | B74: Construction Trades | D74: =D43 -> 1877680 | E74: =SUM('1:57'!E74) -> 6464357 | F74: =IFERROR(E74/D74,"") -> 3.4427362
A75: 9 | B75: Consumer and Homemaking Education | D75: =D44 -> 10305568 | E75: =SUM('1:57'!E75) -> 29263332 | F75: =IFERROR(E75/D75,"") -> 2.8395652
A76: 10 | B76: Engineering | D76: =D45 -> 275947 | E76: =SUM('1:57'!E76) -> 2400116 | F76: =IFERROR(E76/D76,"") -> 8.6977427
A77: 11 | B77: Engineering Related | D77: =D46 -> 8000857 | E77: =SUM('1:57'!E77) -> 24922710 | F77: =IFERROR(E77/D77,"") -> 3.1150051
A78: 12 | B78: English Language, Lit, Philosophy, Humanities, & Interdisciplinary | D78: =D47 -> 34525850 | E78: =SUM('1:57'!E78) -> 121948839 | F78: =IFERROR(E78/D78,"") -> 3.5321024
... A94: 29 | B94: Developmental Education - Reading/Writing | D94: =D63 -> 16713968 | E94: =SUM('1:57'!E94) -> 48527710 | F94: =IFERROR(E94/D94,"") -> 2.9034225
C95: Total | D95: =SUM(D67:D94) -> 320121176 | E95: =SUM(E67:E94) -> 1054089623 | F95: =IFERROR(E95/D95,"") -> 3.2927832
B97: Allocated Administrative Expense | D97: Contact Hours | E97: Expense | F97: Expense per Contact Hour
B98: Institutional Support | E98: =SUM('1:57'!E98) -> 495297014 | F98: =IFERROR(E98/$D$95,"") -> 1.5472173
B99: Student Services | E99: =SUM('1:57'!E99) -> 278545033 | F99: =IFERROR(E99/$D$95,"") -> 0.87012373
B100: Academic Support | E100: =SUM('1:57'!E100) -> 255996327 | F100: =IFERROR(E100/$D$95,"") -> 0.7996857
B101: Research | E101: =SUM('1:57'!E101) -> 569268 | F101: =IFERROR(E101/$D$95,"") -> 0.0017782891
B102: Scholarships and Fellowships | E102: =SUM('1:57'!E102) -> 22457861 | F102: =IFERROR(E102/$D$95,"") -> 0.07015425
B103: Equipment Depreciation | E103: =SUM('1:57'!E103) -> 58806953 | F103: =IFERROR(E103/$D$95,"") -> 0.18370216
B104: Local Benefits | E104: =SUM('1:57'!E104) -> 120529002 | F104: =IFERROR(E104/$D$95,"") -> 0.37651056
C105: Total | D105: =D95 -> 320121176 | E105: =SUM(E98:E104) -> 1232201458 | F105: =IFERROR(E105/$D$95,"") -> 3.849172
B107: Annual Financial Report - Schedule B
B108: Unrestricted - Educational Activities | C108: Salaries and Wages | D108: Local Benefits | E108: Other Expenses | F108: Total
B109: Instruction | C109: =SUM('1:57'!C109) -> 1186386937 | D109: =SUM('1:57'!D109) -> 147731339 | E109: =SUM('1:57'!E109) -> 133579894 | F109: =SUM('1:57'!F109) -> 1467698170
B110: Research | C110: =SUM('1:57'!C110) -> 443384 | D110: =SUM('1:57'!D110) -> 0 | E110: =SUM('1:57'!E110) -> 125884 | F110: =SUM('1:57'!F110) -> 569268
B111: Public Service | C111: =SUM('1:57'!C111) -> 58019978 | D111: =SUM('1:57'!D111) -> 0 | E111: =SUM('1:57'!E111) -> 31959713 | F111: =SUM('1:57'!F111) -> 89979691
B112: Academic Support | C112: =SUM('1:57'!C112) -> 199453868 | D112: =SUM('1:57'!D112) -> 0 | E112: =SUM('1:57'!E112) -> 56542459 | F112: =SUM('1:57'!F112) -> 255996327
B113: Student Services | C113: =SUM('1:57'!C113) -> 220739251 | D113: =SUM('1:57'!D113) -> 0 | E113: =SUM('1:57'!E113) -> 57805782 | F113: =SUM('1:57'!F113) -> 278545033
B114: Instructional Support | C114: =SUM('1:57'!C114) -> 308936629 | D114: =SUM('1:57'!D114) -> 0 | E114: =SUM('1:57'!E114) -> 186360385 | F114: =SUM('1:57'!F114) -> 495297014
B115: Operation and Maintenance of Plant | C115: =SUM('1:57'!C115) -> 93619629 | D115: =SUM('1:57'!D115) -> 25697992 | E115: =SUM('1:57'!E115) -> 295004183 | F115: =SUM('1:57'!F115) -> 414321804
B116: Scholarships and Fellowships | C116: =SUM('1:57'!C116) -> 267302 | D116: =SUM('1:57'!D116) -> 0 | E116: =SUM('1:57'!E116) -> 22190559 | F116: =SUM('1:57'!F116) -> 22457861
B117: Other | C117: =SUM('1:57'!C117) -> 0 | D117: =SUM('1:57'!D117) -> 120529002 | E117: =SUM('1:57'!E117) -> 0 | F117: =SUM('1:57'!F117) -> 120529002
B118: Total | C118: =SUM(C109:C117) -> 2067866978 | D118: =SUM(D109:D117) -> 293958333 | E118: =SUM(E109:E117) -> 783568859 | F118: =SUM(F109:F117) -> 3145394170
B120: Depreciation Expense - Equipment | C120: =SUM('1:57'!C120) -> 0 | D120: =SUM('1:57'!D120) -> 0 | E120: =SUM('1:57'!E120) -> 82050493 | F120: =SUM('1:57'!F120) -> 82050493
B121: Total | C121: =SUM(C120:C120) -> 0 | D121: =SUM(D120:D120) -> 0 | E121: =SUM(E120:E120) -> 82050493 | F121: =SUM(F120:F120) -> 82050493
B122: Study Total | F122: =F118+F121 -> 3227444663
A124: Each year, the Texas Higher Education Coordinating Board revises the Texas Public Community and Technical Colleges Expense per Contact Hour Rates used in its Instruction and Operations Formula Funding Recommendation to the Legislative Budget Board (LBB). The Report of Fundable Operating Expenses (RFOE), completed by the institutions, collects departmental operating expense, faculty salaries, institutional support, student services, academic support, research, scholarships and fellowships, equipment depreciation, and local benefits for input into this summary using Annual Financial Report (AFR) Schedule B, which ties to the AFR Statement of Revenues, Expenses and Changes in Net Assets (SRECNA). The RFOE subcategorizes the expenditures collected in Schedule B funded with unrestricted funds, totals them for all institutions, and divides them by the statewide contact hours to determine rates by discipline.

Sheet Rate History
A1: =Summary!A1 -> Community and Technical Colleges, Report of Fundable Operating Expenses, Fiscal Year (FY) 2012
A2: Rate History | R2: Year over Year Change
A3: Fund | B3: Expense per Contact Hour by Discipline | C3: 2012 | D3: 2011 | E3: 2010 | F3: 2009 | G3: 2008 | H3: 2007 | I3: 2006 | J3: 2005 | K3: 2004 | L3: 2003 | M3: 2002 | N3: 2001 | O3: 2000 | P3: 1999 | R3: 2012 | S3: 2011 | T3: 2010 | U3: 2009 | V3: 2008 | W3: 2007 | X3: 2006 | Y3: 2005 | Z3: 2004 | AA3: 2003 | AB3: 2002 | AC3: 2001 | AD3: 2000
A4: 1 | B4: Agriculture | C4: =Summary!F5 -> 9.058171 | D4: 8.6593499 | E4: =[1]Summary!F5 -> 8.3546442 | F4: 8.9459924 | G4: 7.7 | H4: 7.37 | J4: 7.25 | K4: 9.82 | L4: 7.18 | M4: 7.58 | N4: 7 | O4: 6.67 | P4: 6.81 | R4: =IFERROR(C4/D4-1,"") -> 0.046056706 | S4: =IFERROR(D4/E4-1,"") -> 0.036471411 | T4: =IFERROR(E4/F4-1,"") -> -0.066102019 | U4: =IFERROR(F4/G4-1,"") -> 0.16181719 | V4: =IFERROR(G4/H4-1,"") -> 0.044776119 | W4: =IFERROR(H4/I4-1,"") | X4: =IFERROR(I4/J4-1,"") -> -1 | Y4: =IFERROR(J4/K4-1,"") -> -0.26171079 | ... AD4: =IFERROR(O4/P4-1,"") -> -0.020558003
A5: 2 | B5: Architecture and Precision Production Trades | C5: =Summary!F6 -> 9.3992604 | D5: 9.1845421 | E5: =[1]Summary!F6 -> 9.1518481 | F5: 9.8950421 | G5: 8.88 | H5: 10.29 | J5: 8.82 | K5: 11.31 | L5: 7.31 | M5: 7.27 | N5: 7.56 | O5: 6.83 | P5: 6.64 | R5: =IFERROR(C5/D5-1,"") -> 0.023378221 | S5: =IFERROR(D5/E5-1,"") -> 0.0035723939 | T5: =IFERROR(E5/F5-1,"") -> -0.075107712 | U5: =IFERROR(F5/G5-1,"") -> 0.11430654 | V5: =IFERROR(G5/H5-1,"") -> -0.13702624 | W5: =IFERROR(H5/I5-1,"") | X5: =IFERROR(I5/J5-1,"") -> -1 | Y5: =IFERROR(J5/K5-1,"") -> -0.22015915 | ... AD5: =IFERROR(O5/P5-1,"") -> 0.028614458
A6: 3 | B6: Biology, Physical Sciences, and Science Technology | C6: =Summary!F7 -> 7.805995 | D6: 7.4925174 | E6: =[1]Summary!F7 -> 7.4246458 | F6: 7.7869597 | G6: 6.85 | H6: 6.65 | J6: 6.19 | K6: 7.98 | L6: 5.86 | M6: 6.04 | N6: 5.9 | O6: 5.69 | P6: 5.51 | R6: =IFERROR(C6/D6-1,"") -> 0.041838759 | S6: =IFERROR(D6/E6-1,"") -> 0.0091413881 | T6: =IFERROR(E6/F6-1,"") -> -0.046528286 | U6: =IFERROR(F6/G6-1,"") -> 0.13678244 | V6: =IFERROR(G6/H6-1,"") -> 0.030075188 | W6: =IFERROR(H6/I6-1,"") | X6: =IFERROR(I6/J6-1,"") -> -1 | Y6: =IFERROR(J6/K6-1,"") -> -0.22431078 | ... AD6: =IFERROR(O6/P6-1,"") -> 0.032667877
A7: 4 | B7: Business Management, Marketing, and Administrative Services | C7: =Summary!F8 -> 7.7723659 | D7: 7.45609 | E7: =[1]Summary!F8 -> 7.5459726 | F7: 7.9514488 | G7: 7.11 | H7: 6.97 | J7: 6.58 | K7: 8.86 | L7: 6.69 | M7: 6.46 | N7: 6.07 | O7: 6.13 | P7: 6.22 | R7: =IFERROR(C7/D7-1,"") -> 0.042418463 | S7: =IFERROR(D7/E7-1,"") -> -0.011911328 | T7: =IFERROR(E7/F7-1,"") -> -0.050994005 | U7: =IFERROR(F7/G7-1,"") -> 0.11834723 | V7: =IFERROR(G7/H7-1,"") -> 0.020086083 | W7: =IFERROR(H7/I7-1,"") | X7: =IFERROR(I7/J7-1,"") -> -1 | Y7: =IFERROR(J7/K7-1,"") -> -0.25733634 | ... AD7: =IFERROR(O7/P7-1,"") -> -0.014469453
A8: 5 | B8: Career Pilot | C8: =Summary!F9 -> 29.272886 | D8: 32.970588 | E8: =[1]Summary!F9 -> 31.732203 | F8: 35.064016 | G8: 33.87 | H8: 30.76 | J8: 23.45 | K8: 25.28 | L8: 13.77 | M8: 11.03 | N8: 16.04 | O8: 19.42 | P8: 18.69 | R8: =IFERROR(C8/D8-1,"") -> -0.11215153 | S8: =IFERROR(D8/E8-1,"") -> 0.039026116 | T8: =IFERROR(E8/F8-1,"") -> -0.095020844 | U8: =IFERROR(F8/G8-1,"") -> 0.035252899 | V8: =IFERROR(G8/H8-1,"") -> 0.10110533 | W8: =IFERROR(H8/I8-1,"") | X8: =IFERROR(I8/J8-1,"") -> -1 | Y8: =IFERROR(J8/K8-1,"") -> -0.072389241 | ... AD8: =IFERROR(O8/P8-1,"") -> 0.03905832
A9: 6 | B9: Communications | C9: =Summary!F10 -> 8.8634273 | D9: 8.8221233 | E9: =[1]Summary!F10 -> 8.5415949 | F9: 8.913555 | G9: 7.65 | H9: 7.3 | J9: 7.3 | K9: 10.01 | L9: 7.21 | M9: 7.26 | N9: 6.99 | O9: 9.21 | P9: 8.21 | R9: =IFERROR(C9/D9-1,"") -> 0.0046818681 | S9: =IFERROR(D9/E9-1,"") -> 0.032842631 | T9: =IFERROR(E9/F9-1,"") -> -0.041729716 | U9: =IFERROR(F9/G9-1,"") -> 0.16517059 | V9: =IFERROR(G9/H9-1,"") -> 0.047945205 | W9: =IFERROR(H9/I9-1,"") | X9: =IFERROR(I9/J9-1,"") -> -1 | Y9: =IFERROR(J9/K9-1,"") -> -0.27072927 | ... AD9: =IFERROR(O9/P9-1,"") -> 0.12180268
A10: 7 | B10: Computer and Information Sciences | C10: =Summary!F11 -> 9.4843582 | D10: 9.2148507 | E10: =[1]Summary!F11 -> 9.0091907 | F10: 9.8773789 | G10: 8.52 | H10: 8.44 | J10: 7.57 | K10: 9.93 | L10: 6.94 | M10: 6.92 | N10: 6.69 | O10: 6.32 | P10: 5.44 | R10: =IFERROR(C10/D10-1,"") -> 0.029247076 | S10: =IFERROR(D10/E10-1,"") -> 0.022827808 | T10: =IFERROR(E10/F10-1,"") -> -0.087896624 | U10: =IFERROR(F10/G10-1,"") -> 0.15931678 | V10: =IFERROR(G10/H10-1,"") -> 0.009478673 | W10: =IFERROR(H10/I10-1,"") | X10: =IFERROR(I10/J10-1,"") -> -1 | Y10: =IFERROR(J10/K10-1,"") -> -0.23766365 | ... AD10: =IFERROR(O10/P10-1,"") -> 0.16176471
A11: 8 | B11: Construction Trades | C11: =Summary!F12 -> 9.4807263 | D11: 9.4265511 | E11: =[1]Summary!F12 -> 9.1499254 | F11: 10.673804 | G11: 8.03 | H11: 7.77 | J11: 8.2 | K11: 10.92 | L11: 7.36 | M11: 6.75 | N11: 6.12 | O11: 6.42 | P11: 5.99 | R11: =IFERROR(C11/D11-1,"") -> 0.0057470876 | S11: =IFERROR(D11/E11-1,"") -> 0.030232561 | T11: =IFERROR(E11/F11-1,"") -> -0.14276812 | U11: =IFERROR(F11/G11-1,"") -> 0.32924089 | V11: =IFERROR(G11/H11-1,"") -> 0.033462033 | W11: =IFERROR(H11/I11-1,"") | X11: =IFERROR(I11/J11-1,"") -> -1 | Y11: =IFERROR(J11/K11-1,"") -> -0.24908425 | ... AD11: =IFERROR(O11/P11-1,"") -> 0.071786311
A12: 9 | B12: Consumer and Homemaking Education | C12: =Summary!F13 -> 8.3205882 | D12: 7.5205661 | E12: =[1]Summary!F13 -> 7.5340118 | F12: 7.7785582 | G12: 6.75 | H12: 6.49 | J12: 6.14 | K12: 8.08 | L12: 5.49 | M12: 5.51 | N12: 5.52 | O12: 5.14 | P12: 5.35 | R12: =IFERROR(C12/D12-1,"") -> 0.1063779 | S12: =IFERROR(D12/E12-1,"") -> -0.001784662 | T12: =IFERROR(E12/F12-1,"") -> -0.03143852 | U12: =IFERROR(F12/G12-1,"") -> 0.15237899 | V12: =IFERROR(G12/H12-1,"") -> 0.040061633 | W12: =IFERROR(H12/I12-1,"") | X12: =IFERROR(I12/J12-1,"") -> -1 | Y12: =IFERROR(J12/K12-1,"") -> -0.24009901 | ... AD12: =IFERROR(O12/P12-1,"") -> -0.039252336
A13: 10 | B13: Engineering | C13: =Summary!F14 -> 15.647119 | D13: 14.989516 | E13: =[1]Summary!F14 -> 10.569021 | F13: 11.277206 | G13: 7.86 | H13: 7.53 | J13: 10.3 | K13: 11.38 | L13: 8.92 | M13: 8.54 | N13: 11.49 | O13: 9.83 | P13: 7.64 | R13: =IFERROR(C13/D13-1,"") -> 0.043870843 | S13: =IFERROR(D13/E13-1,"") -> 0.41825015 | T13: =IFERROR(E13/F13-1,"") -> -0.062797855 | U13: =IFERROR(F13/G13-1,"") -> 0.43475898 | V13: =IFERROR(G13/H13-1,"") -> 0.043824701 | W13: =IFERROR(H13/I13-1,"") | X13: =IFERROR(I13/J13-1,"") -> -1 | Y13: =IFERROR(J13/K13-1,"") -> -0.094903339 | ... AD13: =IFERROR(O13/P13-1,"") -> 0.28664921
A14: 11 | B14: Engineering Related | C14: =Summary!F15 -> 8.8028186 | D14: 8.2751104 | E14: =[1]Summary!F15 -> 8.1538555 | F14: 8.4264374 | G14: 7.41 | H14: 7.09 | J14: 6.82 | K14: 9.52 | L14: 7.23 | M14: 6.89 | N14: 6.58 | O14: 6.71 | P14: 6.42 | R14: =IFERROR(C14/D14-1,"") -> 0.063770529 | S14: =IFERROR(D14/E14-1,"") -> 0.014870862 | T14: =IFERROR(E14/F14-1,"") -> -0.032348416 | U14: =IFERROR(F14/G14-1,"") -> 0.13717104 | V14: =IFERROR(G14/H14-1,"") -> 0.045133992 | W14: =IFERROR(H14/I14-1,"") | X14: =IFERROR(I14/J14-1,"") -> -1 | Y14: =IFERROR(J14/K14-1,"") -> -0.28361345 | ... AD14: =IFERROR(O14/P14-1,"") -> 0.04517134
A15: 12 | B15: English Language, Lit, Philosophy, Humanities, & Interdisciplinary | C15: =Summary!F16 -> 8.4898241 | D15: 8.1700753 | E15: =[1]Summary!F16 -> 7.8328441 | F15: 8.2593827 | G15: 7.31 | H15: 7.08 | J15: 6.48 | K15: 8.33 | L15: 5.83 | M15: 5.94 | N15: 5.75 | O15: 5.68 | P15: 5.26 | R15: =IFERROR(C15/D15-1,"") -> 0.039136571 | S15: =IFERROR(D15/E15-1,"") -> 0.043053489 | T15: =IFERROR(E15/F15-1,"") -> -0.051642922 | U15: =IFERROR(F15/G15-1,"") -> 0.12987452 | V15: =IFERROR(G15/H15-1,"") -> 0.032485876 | W15: =IFERROR(H15/I15-1,"") | X15: =IFERROR(I15/J15-1,"") -> -1 | Y15: =IFERROR(J15/K15-1,"") -> -0.22208884 | ... AD15: =IFERROR(O15/P15-1,"") -> 0.079847909
... A31: 29 | B31: Developmental Education - Reading/Writing | C31: =Summary!F32 -> 7.5269762 | D31: 7.0255507 | E31: =[1]Summary!F32 -> 0 | F31: 0 | G31: 0 | H31: 0 | J31: 0 | K31: 0 | L31: 0 | M31: 0 | N31: 0 | O31: 0 | P31: 0 | R31: =IFERROR(C31/D31-1,"") -> 0.071371699 | S31: =IFERROR(D31/E31-1,"") | T31: =IFERROR(E31/F31-1,"") | U31: =IFERROR(F31/G31-1,"") | V31: =IFERROR(G31/H31-1,"") | W31: =IFERROR(H31/I31-1,"") | X31: =IFERROR(I31/J31-1,"") | Y31: =IFERROR(J31/K31-1,"") | ... AD31: =IFERROR(O31/P31-1,"")
B32: Average | C32: =AVERAGE(C4:C31) -> 10.458596 | D32: =AVERAGE(D4:D31) -> 10.221252 | E32: =AVERAGE(E4:E31) -> 9.374184 | F32: =AVERAGE(F4:F31) -> 9.871227 | G32: =AVERAGE(G4:G31) -> 8.67 | H32: =AVERAGE(H4:H31) -> 8.4635714 | J32: =AVERAGE(J4:J31) -> 7.7992857 | K32: =AVERAGE(K4:K31) -> 9.7525 | L32: =AVERAGE(L4:L31) -> 6.9428571 | M32: =AVERAGE(M4:M31) -> 7.0071429 | N32: =AVERAGE(N4:N31) -> 7.0107143 | O32: =AVERAGE(O4:O31) -> 7.0171429 | P32: =AVERAGE(P4:P31) -> 6.5617857 | R32: =IFERROR(C32/D32-1,"") -> 0.023220596 | S32: =IFERROR(D32/E32-1,"") -> 0.090361818 | T32: =IFERROR(E32/F32-1,"") -> -0.050352708 | U32: =IFERROR(F32/G32-1,"") -> 0.13854982 | V32: =IFERROR(G32/H32-1,"") -> 0.024390244 | W32: =IFERROR(H32/I32-1,"") | X32: =IFERROR(I32/J32-1,"") -> -1 | Y32: =IFERROR(J32/K32-1,"") -> -0.20027832 | ... AD32: =IFERROR(O32/P32-1,"") -> 0.069395308
B33: Median | C33: =MEDIAN(C4:C31) -> 9.2287157 | D33: =MEDIAN(D4:D31) -> 8.8781082 | E33: =MEDIAN(E4:E31) -> 8.8678181 | F33: =MEDIAN(F4:F31) -> 9.3311851 | G33: =MEDIAN(G4:G31) -> 7.78 | H33: =MEDIAN(H4:H31) -> 7.525 | J33: =MEDIAN(J4:J31) -> 7.345 | K33: =MEDIAN(K4:K31) -> 9.615 | L33: =MEDIAN(L4:L31) -> 6.995 | M33: =MEDIAN(M4:M31) -> 6.905 | N33: =MEDIAN(N4:N31) -> 6.69 | O33: =MEDIAN(O4:O31) -> 6.69 | P33: =MEDIAN(P4:P31) -> 6.32 | R33: =IFERROR(C33/D33-1,"") -> 0.039491244 | S33: =IFERROR(D33/E33-1,"") -> 0.0011603792 | T33: =IFERROR(E33/F33-1,"") -> -0.049657886 | U33: =IFERROR(F33/G33-1,"") -> 0.19938111 | V33: =IFERROR(G33/H33-1,"") -> 0.033887043 | W33: =IFERROR(H33/I33-1,"") | X33: =IFERROR(I33/J33-1,"") -> -1 | Y33: =IFERROR(J33/K33-1,"") -> -0.23608944 | ... AD33: =IFERROR(O33/P33-1,"") -> 0.058544304
B34: Standard Deviation | C34: =STDEV(C4:C31) -> 4.5646175 | D34: =STDEV(D4:D31) -> 5.1894911 | E34: =STDEV(E4:E31) -> 5.450075 | F34: =STDEV(F4:F31) -> 5.9203334 | G34: =STDEV(G4:G31) -> 5.7536855 | H34: =STDEV(H4:H31) -> 5.2587227 | J34: =STDEV(J4:J31) -> 4.1137528 | K34: =STDEV(K4:K31) -> 4.4105653 | L34: =STDEV(L4:L31) -> 2.7509808 | M34: =STDEV(M4:M31) -> 2.6772026 | N34: =STDEV(N4:N31) -> 3.0868058 | O34: =STDEV(O4:O31) -> 3.4645516 | P34: =STDEV(P4:P31) -> 3.2525364 | R34: =IFERROR(C34/D34-1,"") -> -0.12041134 | S34: =IFERROR(D34/E34-1,"") -> -0.047812889 | T34: =IFERROR(E34/F34-1,"") -> -0.079431073 | U34: =IFERROR(F34/G34-1,"") -> 0.028963686 | V34: =IFERROR(G34/H34-1,"") -> 0.094122236 | W34: =IFERROR(H34/I34-1,"") | X34: =IFERROR(I34/J34-1,"") -> -1 | Y34: =IFERROR(J34/K34-1,"") -> -0.067295782 | ... AD34: =IFERROR(O34/P34-1,"") -> 0.065184562

Sheet FTSE Summary
A1: =Summary!A1 -> Community and Technical Colleges, Report of Fundable Operating Expenses, Fiscal Year (FY) 2012
A2: Average Total Expenditure per Full-Time Student Equivalent (FTSE)
A3: Institution | B3: Annual State Funded Semester Credit Hours | C3: Total FTSE | D3: Total Expenditure | E3: Average Expenditure per FTSE
A4: Alamo | B4: 1152210 | C4: =B4/30 -> 38407 | D4: ='1'!$E$33 -> 209097769 | E4: =IFERROR(D4/C4,"") -> 5444.262
A5: Alvin | B5: 102531 | C5: =B5/30 -> 3417.7 | D5: ='2'!$E$33 -> 23163486 | E5: =IFERROR(D5/C5,"") -> 6777.5071
A6: Amarillo | B6: 204401 | C6: =B6/30 -> 6813.3667 | D6: ='3'!$E$33 -> 42811410 | E6: =IFERROR(D6/C6,"") -> 6283.4443
A7: Angelina | B7: 110577 | C7: =B7/30 -> 3685.9 | D7: ='4'!$E$33 -> 16986394 | E7: =IFERROR(D7/C7,"") -> 4608.4793
A8: Austin | B8: 807288 | C8: =B8/30 -> 26909.6 | D8: ='5'!$E$33 -> 186729556 | E8: =IFERROR(D8/C8,"") -> 6939.1428
A9: Blinn | B9: 401913 | C9: =B9/30 -> 13397.1 | D9: ='6'!$E$33 -> 50415846 | E9: =IFERROR(D9/C9,"") -> 3763.191
A10: Brazosport | B10: 79245 | C10: =B10/30 -> 2641.5 | D10: ='7'!$E$33 -> 17727779 | E10: =IFERROR(D10/C10,"") -> 6711.2546
A11: Central Texas | B11: 316196 | C11: =B11/30 -> 10539.867 | D11: ='8'!$E$33 -> 45639875 | E11: =IFERROR(D11/C11,"") -> 4330.2137
A12: Cisco | B12: 89266 | C12: =B12/30 -> 2975.5333 | D12: ='9'!$E$33 -> 11535601 | E12: =IFERROR(D12/C12,"") -> 3876.8179
A13: Clarendon | B13: 32284 | C13: =B13/30 -> 1076.1333 | D13: ='10'!$E$33 -> 4943342 | E13: =IFERROR(D13/C13,"") -> 4593.6148
A14: Coastal Bend | B14: 72723 | C14: =B14/30 -> 2424.1 | D14: ='11'!$E$33 -> 16124744 | E14: =IFERROR(D14/C14,"") -> 6651.8477
A15: College Of The Mainland | B15: 84095 | C15: =B15/30 -> 2803.1667 | D15: ='12'!$E$33 -> 27041085 | E15: =IFERROR(D15/C15,"") -> 9646.6205
A16: Collin | B16: 533689 | C16: =B16/30 -> 17789.633 | D16: ='13'!$E$33 -> 80980073 | E16: =IFERROR(D16/C16,"") -> 4552.0934
A17: Dallas | B17: 1402650 | C17: =B17/30 -> 46755 | D17: ='14'!$E$33 -> 2.4382815e+08 | E17: =IFERROR(D17/C17,"") -> 5215.0176
A18: Del Mar | B18: 221332 | C18: =B18/30 -> 7377.7333 | D18: ='15'!$E$33 -> 55245804 | E18: =IFERROR(D18/C18,"") -> 7488.1812
A19: El Paso | B19: 573271 | C19: =B19/30 -> 19109.033 | D19: ='16'!$E$33 -> 93518766 | E19: =IFERROR(D19/C19,"") -> 4893.9559
A20: Frank Phillips | B20: 20815 | C20: =B20/30 -> 693.83333 | D20: ='17'!$E$33 -> 5960329 | E20: =IFERROR(D20/C20,"") -> 8590.4333
A21: Galveston | B21: 46907 | C21: =B21/30 -> 1563.5667 | D21: ='18'!$E$33 -> 12223267 | E21: =IFERROR(D21/C21,"") -> 7817.5541
A22: Grayson | B22: 111186 | C22: =B22/30 -> 3706.2 | D22: ='19'!$E$33 -> 17909955 | E22: =IFERROR(D22/C22,"") -> 4832.4308
A23: Hill | B23: 93510 | C23: =B23/30 -> 3117 | D23: ='20'!$E$33 -> 13657092 | E23: =IFERROR(D23/C23,"") -> 4381.486
A24: Houston | B24: 1154606 | C24: =B24/30 -> 38486.867 | D24: ='21'!$E$33 -> 193030817 | E24: =IFERROR(D24/C24,"") -> 5015.4984
A25: Howard | B25: 82200 | C25: =B25/30 -> 2740 | D25: ='22'!$E$33 -> 18554773 | E25: =IFERROR(D25/C25,"") -> 6771.815
A26: Kilgore | B26: 134874 | C26: =B26/30 -> 4495.8 | D26: ='23'!$E$33 -> 24659540 | E26: =IFERROR(D26/C26,"") -> 5485.0171
A27: Laredo | B27: 184628 | C27: =B27/30 -> 6154.2667 | D27: ='24'!$E$33 -> 40632446 | E27: =IFERROR(D27/C27,"") -> 6602.3213
A28: Lee | B28: 129970 | C28: =B28/30 -> 4332.3333 | D28: ='25'!$E$33 -> 29010292 | E28: =IFERROR(D28/C28,"") -> 6696.2281
A29: Lonestar | B29: 1158780 | C29: =B29/30 -> 38626 | D29: ='26'!$E$33 -> 2.0700706e+08 | E29: =IFERROR(D29/C29,"") -> 5359.2673
A30: Mclennan | B30: 215595 | C30: =B30/30 -> 7186.5 | D30: ='27'!$E$33 -> 42200548 | E30: =IFERROR(D30/C30,"") -> 5872.1976
A31: Midland | B31: 119553 | C31: =B31/30 -> 3985.1 | D31: ='28'!$E$33 -> 29785137 | E31: =IFERROR(D31/C31,"") -> 7474.1254
A32: Navarro | B32: 236739 | C32: =B32/30 -> 7891.3 | D32: ='29'!$E$33 -> 27300540 | E32: =IFERROR(D32/C32,"") -> 3459.5745
A33: North Central Texas | B33: 189523 | C33: =B33/30 -> 6317.4333 | D33: ='30'!$E$33 -> 23292997 | E33: =IFERROR(D33/C33,"") -> 3687.0982
A34: Northeast Texas | B34: 72930 | C34: =B34/30 -> 2431 | D34: ='31'!$E$33 -> 11625103 | E34: =IFERROR(D34/C34,"") -> 4782.0251
A35: Odessa | B35: 95324 | C35: =B35/30 -> 3177.4667 | D35: ='32'!$E$33 -> 26076034 | E35: =IFERROR(D35/C35,"") -> 8206.5484
A36: Panola | B36: 52818 | C36: =B36/30 -> 1760.6 | D36: ='33'!$E$33 -> 11034987 | E36: =IFERROR(D36/C36,"") -> 6267.7422
A37: Paris | B37: 125940 | C37: =B37/30 -> 4198 | D37: ='34'!$E$33 -> 16489054 | E37: =IFERROR(D37/C37,"") -> 3927.8356
A38: Ranger | B38: 38899 | C38: =B38/30 -> 1296.6333 | D38: ='35'!$E$33 -> 4578438 | E38: =IFERROR(D38/C38,"") -> 3531.0198
A39: San Jacinto | B39: 590220 | C39: =B39/30 -> 19674 | D39: ='36'!$E$33 -> 1.1044721e+08 | E39: =IFERROR(D39/C39,"") -> 5613.8667
A40: South Plains | B40: 213116 | C40: =B40/30 -> 7103.8667 | D40: ='37'!$E$33 -> 37245853 | E40: =IFERROR(D40/C40,"") -> 5243.0394
A41: South Texas | B41: 551799 | C41: =B41/30 -> 18393.3 | D41: ='38'!$E$33 -> 87208268 | E41: =IFERROR(D41/C41,"") -> 4741.3062
A42: Southwest Texas | B42: 103498 | C42: =B42/30 -> 3449.9333 | D42: ='39'!$E$33 -> 19784522 | E42: =IFERROR(D42/C42,"") -> 5734.7549
A43: Tarrant | B43: 974520 | C43: =B43/30 -> 32484 | D43: ='40'!$E$33 -> 177328874 | E43: =IFERROR(D43/C43,"") -> 5458.9605
A44: Temple | B44: 118213 | C44: =B44/30 -> 3940.4333 | D44: ='41'!$E$33 -> 20556550 | E44: =IFERROR(D44/C44,"") -> 5216.8247
A45: Texarkana | B45: 83208 | C45: =B45/30 -> 2773.6 | D45: ='42'!$E$33 -> 17543374 | E45: =IFERROR(D45/C45,"") -> 6325.1276
A46: Texas Southmost | B46: 172893 | C46: =B46/30 -> 5763.1 | D46: ='43'!$E$33 -> 46641859 | E46: =IFERROR(D46/C46,"") -> 8093.1893
A47: Trinity Valley | B47: 159127 | C47: =B47/30 -> 5304.2333 | D47: ='44'!$E$33 -> 24327503 | E47: =IFERROR(D47/C47,"") -> 4586.4315
A48: Tyler | B48: 252643 | C48: =B48/30 -> 8421.4333 | D48: ='45'!$E$33 -> 48326939 | E48: =IFERROR(D48/C48,"") -> 5738.5646
A49: Vernon | B49: 66164 | C49: =B49/30 -> 2205.4667 | D49: ='46'!$E$33 -> 12898183 | E49: =IFERROR(D49/C49,"") -> 5848.2784
A50: Victoria | B50: 84413 | C50: =B50/30 -> 2813.7667 | D50: ='47'!$E$33 -> 20263083 | E50: =IFERROR(D50/C50,"") -> 7201.4084
A51: Weatherford | B51: 112950 | C51: =B51/30 -> 3765 | D51: ='48'!$E$33 -> 24375471 | E51: =IFERROR(D51/C51,"") -> 6474.2287
A52: Western Texas | B52: 48120 | C52: =B52/30 -> 1604 | D52: ='49'!$E$33 -> 7821075 | E52: =IFERROR(D52/C52,"") -> 4875.9819
A53: Wharton | B53: 146130 | C53: =B53/30 -> 4871 | D53: ='50'!$E$33 -> 25547424 | E53: =IFERROR(D53/C53,"") -> 5244.8007
A54: TSTC-Harlingen | B54: 122241 | C54: =B54/30 -> 4074.7 | D54: ='51'!$E$33 -> 25076145 | E54: =IFERROR(D54/C54,"") -> 6154.1083
A55: TSTC-West Texas | B55: 23761 | C55: =B55/30 -> 792.03333 | D55: ='52'!$E$33 -> 12484223 | E55: =IFERROR(D55/C55,"") -> 15762.244
A56: TSTC-Marshall | B56: 19267 | C56: =B56/30 -> 642.23333 | D56: ='53'!$E$33 -> 5373180 | E56: =IFERROR(D56/C56,"") -> 8366.3985
A57: TSTC-Waco | B57: 140668 | C57: =B57/30 -> 4688.9333 | D57: ='54'!$E$33 -> 41635811 | E57: =IFERROR(D57/C57,"") -> 8879.5912
A58: Lamar-IOT | B58: 61789 | C58: =B58/30 -> 2059.6333 | D58: ='55'!$E$33 -> 21767538 | E58: =IFERROR(D58/C58,"") -> 10568.647
A59: Lamar-Orange | B59: 53098 | C59: =B59/30 -> 1769.9333 | D59: ='56'!$E$33 -> 12972935 | E59: =IFERROR(D59/C59,"") -> 7329.6179
A60: Lamar-Port Arthur | B60: 61119 | C60: =B60/30 -> 2037.3 | D60: ='57'!$E$33 -> 15669364 | E60: =IFERROR(D60/C60,"") -> 7691.2404
A61: Total for Instutions Reporting Expense | B61: =SUMIF(D4:D60,">0",B4:B60) -> 14607425 | C61: =B61/30 -> 486914.17 | D61: =SUM(D4:D60) -> 2696113474 | E61: =IFERROR(D61/C61,"") -> 5537.1432

Sheet Discipline Summary
A1: =Summary!A1 -> Community and Technical Colleges, Report of Fundable Operating Expenses, Fiscal Year (FY) 2012
A2: Discipline Summary of Expense per Contact Hour by Institution
A3: Institution | B3: AG | C3: ARCH | D3: SCI | E3: BA | F3: CP | G3: COMM | H3: CS | I3: CNSTR | J3: HE | K3: ENG | L3: ENGR | M3: LA | N3: FL | O3: HODA | P3: HODH | Q3: HOO | R3: HORT | S3: NUR | T3: MATH | U3: AUTO | V3: MECH | W3: ELECT | X3: PE | Y3: PA | Z3: SS | AA3: FA | AB3: DEM | AC3: DER | AD3: Total
A4: Alamo | B4: ='1'!$F$5 -> 6.5219432 | C4: ='1'!$F$6 -> 10.071416 | D4: ='1'!$F$7 -> 8.7560484 | E4: ='1'!$F$8 -> 9.128574 | F4: ='1'!$F$9 -> 36.093933 | G4: ='1'!$F$10 -> 8.848294 | H4: ='1'!$F$11 -> 11.964128 | I4: ='1'!$F$12 -> 9.2635351 | J4: ='1'!$F$13 -> 8.6868189 | K4: ='1'!$F$14 -> 16.0307 | L4: ='1'!$F$15 -> 10.990392 | M4: ='1'!$F$16 -> 8.5975772 | N4: ='1'!$F$17 -> 8.2445898 | O4: ='1'!$F$18 -> 16.117754 | P4: ='1'!$F$19 | Q4: ='1'!$F$20 -> 9.9100058 | R4: ='1'!$F$21 -> 13.76094 | S4: ='1'!$F$22 -> 13.507538 | T4: ='1'!$F$23 -> 8.178886 | U4: ='1'!$F$24 -> 9.9351227 | V4: ='1'!$F$25 -> 8.6963294 | W4: ='1'!$F$26 -> 6.3442274 | X4: ='1'!$F$27 -> 9.5827268 | Y4: ='1'!$F$28 -> 8.5695727 | Z4: ='1'!$F$29 -> 7.7354521 | AA4: ='1'!$F$30 -> 9.8060239 | AB4: ='1'!$F$31 -> 7.611667 | AC4: ='1'!$F$32 -> 8.1002669 | AD4: ='1'!$F$33 -> 8.9002933
A5: Alvin | B5: ='2'!$F$5 -> 10.343713 | C5: ='2'!$F$6 -> 11.070997 | D5: ='2'!$F$7 -> 6.4783442 | E5: ='2'!$F$8 -> 9.0742023 | F5: ='2'!$F$9 -> 4.1040666 | G5: ='2'!$F$10 -> 13.130688 | H5: ='2'!$F$11 -> 18.943358 | I5: ='2'!$F$12 -> 4.5883911 | J5: ='2'!$F$13 -> 9.1492701 | K5: ='2'!$F$14 | L5: ='2'!$F$15 -> 13.268211 | M5: ='2'!$F$16 -> 8.0579116 | N5: ='2'!$F$17 -> 7.6928692 | O5: ='2'!$F$18 -> 12.199741 | P5: ='2'!$F$19 | Q5: ='2'!$F$20 -> 10.766218 | R5: ='2'!$F$21 -> 19.243442 | S5: ='2'!$F$22 -> 12.595659 | T5: ='2'!$F$23 -> 8.8350715 | U5: ='2'!$F$24 -> 10.765599 | V5: ='2'!$F$25 | W5: ='2'!$F$26 -> 4.3634062 | X5: ='2'!$F$27 -> 13.901829 | Y5: ='2'!$F$28 -> 9.5590831 | Z5: ='2'!$F$29 -> 8.1644058 | AA5: ='2'!$F$30 -> 15.1414 | AB5: ='2'!$F$31 -> 8.5828599 | AC5: ='2'!$F$32 -> 9.9382504 | AD5: ='2'!$F$33 -> 9.7497831
A6: Amarillo | B6: ='3'!$F$5 -> 8.696281 | C6: ='3'!$F$6 -> 10.009047 | D6: ='3'!$F$7 -> 8.0919282 | E6: ='3'!$F$8 -> 8.4139606 | F6: ='3'!$F$9 -> 10.010037 | G6: ='3'!$F$10 -> 8.9330666 | H6: ='3'!$F$11 -> 8.3377964 | I6: ='3'!$F$12 -> 10.042889 | J6: ='3'!$F$13 -> 7.4299042 | K6: ='3'!$F$14 -> 8.091396 | L6: ='3'!$F$15 -> 9.2023274 | M6: ='3'!$F$16 -> 8.6678078 | N6: ='3'!$F$17 -> 8.0658455 | O6: ='3'!$F$18 -> 10.200288 | P6: ='3'!$F$19 -> 8.5941653 | Q6: ='3'!$F$20 -> 8.6723012 | R6: ='3'!$F$21 -> 8.6188041 | S6: ='3'!$F$22 -> 10.525112 | T6: ='3'!$F$23 -> 8.3249001 | U6: ='3'!$F$24 -> 10.009041 | V6: ='3'!$F$25 -> 10.05203 | W6: ='3'!$F$26 -> 9.5722389 | X6: ='3'!$F$27 -> 6.358428 | Y6: ='3'!$F$28 -> 8.703965 | Z6: ='3'!$F$29 -> 6.5972224 | AA6: ='3'!$F$30 -> 8.0290018 | AB6: ='3'!$F$31 -> 8.324896 | AC6: ='3'!$F$32 -> 8.6678101 | AD6: ='3'!$F$33 -> 8.4342468
A7: Angelina | B7: ='4'!$F$5 | C7: ='4'!$F$6 -> 8.6595054 | D7: ='4'!$F$7 -> 5.6761265 | E7: ='4'!$F$8 -> 6.5461664 | F7: ='4'!$F$9 -> 12.005646 | G7: ='4'!$F$10 -> 11.765993 | H7: ='4'!$F$11 -> 13.644237 | I7: ='4'!$F$12 -> 7.1030541 | J7: ='4'!$F$13 -> 7.2103076 | K7: ='4'!$F$14 -> 206.75044 | L7: ='4'!$F$15 -> 7.1060966 | M7: ='4'!$F$16 -> 5.7577061 | N7: ='4'!$F$17 -> 5.6233817 | O7: ='4'!$F$18 -> 9.0435833 | P7: ='4'!$F$19 | Q7: ='4'!$F$20 -> 8.1622339 | R7: ='4'!$F$21 -> 12.534675 | S7: ='4'!$F$22 -> 5.5744461 | T7: ='4'!$F$23 -> 6.8765963 | U7: ='4'!$F$24 -> 6.2911925 | V7: ='4'!$F$25 -> 8.7493722 | W7: ='4'!$F$26 -> 7.0997676 | X7: ='4'!$F$27 -> 7.6610487 | Y7: ='4'!$F$28 -> 6.6466965 | Z7: ='4'!$F$29 -> 5.8939433 | AA7: ='4'!$F$30 -> 7.6294205 | AB7: ='4'!$F$31 -> 6.8766858 | AC7: ='4'!$F$32 -> 5.731069 | AD7: ='4'!$F$33 -> 6.8336158
A8: Austin | B8: ='5'!$F$5 -> 8.2986123 | C8: ='5'!$F$6 -> 17.564607 | D8: ='5'!$F$7 -> 11.589608 | E8: ='5'!$F$8 -> 10.14773 | F8: ='5'!$F$9 | G8: ='5'!$F$10 -> 8.3980086 | H8: ='5'!$F$11 -> 16.975317 | I8: ='5'!$F$12 -> 5.7469094 | J8: ='5'!$F$13 -> 15.014823 | K8: ='5'!$F$14 -> 15.694387 | L8: ='5'!$F$15 -> 13.30228 | M8: ='5'!$F$16 -> 10.442438 | N8: ='5'!$F$17 -> 10.358199 | O8: ='5'!$F$18 -> 17.820209 | P8: ='5'!$F$19 -> 35.264738 | Q8: ='5'!$F$20 -> 16.143989 | R8: ='5'!$F$21 | S8: ='5'!$F$22 -> 20.208627 | T8: ='5'!$F$23 -> 9.6479515 | U8: ='5'!$F$24 -> 16.331196 | V8: ='5'!$F$25 -> 23.903615 | W8: ='5'!$F$26 -> 37.308562 | X8: ='5'!$F$27 -> 10.244921 | Y8: ='5'!$F$28 -> 9.5013883 | Z8: ='5'!$F$29 -> 9.0710837 | AA8: ='5'!$F$30 -> 15.081343 | AB8: ='5'!$F$31 -> 9.7502305 | AC8: ='5'!$F$32 -> 10.752457 | AD8: ='5'!$F$33 -> 11.470022
A9: Blinn | B9: ='6'!$F$5 -> 8.0617658 | C9: ='6'!$F$6 -> 10.53795 | D9: ='6'!$F$7 -> 4.8068864 | E9: ='6'!$F$8 -> 6.8141194 | F9: ='6'!$F$9 | G9: ='6'!$F$10 -> 3.5824527 | H9: ='6'!$F$11 -> 16.115688 | I9: ='6'!$F$12 -> 8.9368365 | J9: ='6'!$F$13 -> 3.5209144 | K9: ='6'!$F$14 | L9: ='6'!$F$15 -> 7.4676269 | M9: ='6'!$F$16 -> 6.6750958 | N9: ='6'!$F$17 -> 7.0192074 | O9: ='6'!$F$18 -> 14.715109 | P9: ='6'!$F$19 -> 26.100696 | Q9: ='6'!$F$20 -> 8.9428308 | R9: ='6'!$F$21 | S9: ='6'!$F$22 -> 11.013357 | T9: ='6'!$F$23 -> 5.9320671 | U9: ='6'!$F$24 -> 8.9345607 | V9: ='6'!$F$25 -> 8.9370282 | W9: ='6'!$F$26 -> 8.9369284 | X9: ='6'!$F$27 -> 7.8143595 | Y9: ='6'!$F$28 -> 9.8782838 | Z9: ='6'!$F$29 -> 4.9999061 | AA9: ='6'!$F$30 -> 6.7609019 | AB9: ='6'!$F$31 -> 5.9320691 | AC9: ='6'!$F$32 -> 6.6750965 | AD9: ='6'!$F$33 -> 6.3978721
A10: Brazosport | B10: ='7'!$F$5 -> 6.5153114 | C10: ='7'!$F$6 -> 9.9731761 | D10: ='7'!$F$7 -> 9.9269028 | E10: ='7'!$F$8 -> 11.875574 | F10: ='7'!$F$9 | G10: ='7'!$F$10 -> 5.3472496 | H10: ='7'!$F$11 -> 11.003575 | I10: ='7'!$F$12 -> 10.045943 | J10: ='7'!$F$13 -> 9.9116179 | K10: ='7'!$F$14 | L10: ='7'!$F$15 -> 8.8611876 | M10: ='7'!$F$16 -> 9.699947 | N10: ='7'!$F$17 -> 9.5648787 | O10: ='7'!$F$18 -> 13.845884 | P10: ='7'!$F$19 | Q10: ='7'!$F$20 -> 13.77261 | R10: ='7'!$F$21 | S10: ='7'!$F$22 -> 18.197155 | T10: ='7'!$F$23 -> 9.0123541 | U10: ='7'!$F$24 -> 11.064539 | V10: ='7'!$F$25 | W10: ='7'!$F$26 -> 8.7963568 | X10: ='7'!$F$27 | Y10: ='7'!$F$28 -> 9.2388388 | Z10: ='7'!$F$29 -> 10.225757 | AA10: ='7'!$F$30 -> 12.252516 | AB10: ='7'!$F$31 -> 9.01235 | AC10: ='7'!$F$32 -> 9.6998649 | AD10: ='7'!$F$33 -> 10.332891
A11: Central Texas | B11: ='8'!$F$5 -> 5.7119477 | C11: ='8'!$F$6 -> 5.8323166 | D11: ='8'!$F$7 -> 6.2577389 | E11: ='8'!$F$8 -> 6.2865037 | F11: ='8'!$F$9 -> 41.533857 | G11: ='8'!$F$10 -> 28.21467 | H11: ='8'!$F$11 -> 6.8412521 | I11: ='8'!$F$12 -> 4.3478174 | J11: ='8'!$F$13 -> 9.9888424 | K11: ='8'!$F$14 -> 5.7542575 | L11: ='8'!$F$15 -> 4.2116307 | M11: ='8'!$F$16 -> 6.8497965 | N11: ='8'!$F$17 -> 5.8936348 | O11: ='8'!$F$18 -> 10.987729 | P11: ='8'!$F$19 | Q11: ='8'!$F$20 -> 12.174939 | R11: ='8'!$F$21 | S11: ='8'!$F$22 -> 10.247112 | T11: ='8'!$F$23 -> 6.4059484 | U11: ='8'!$F$24 -> 8.5084939 | V11: ='8'!$F$25 -> 5.9643143 | W11: ='8'!$F$26 -> 5.8709123 | X11: ='8'!$F$27 -> 6.7574153 | Y11: ='8'!$F$28 -> 6.4786476 | Z11: ='8'!$F$29 -> 5.1611214 | AA11: ='8'!$F$30 -> 5.6828897 | AB11: ='8'!$F$31 -> 4.7115101 | AC11: ='8'!$F$32 -> 4.8669308 | AD11: ='8'!$F$33 -> 6.6203312
A12: Cisco | B12: ='9'!$F$5 -> 11.946924 | C12: ='9'!$F$6 -> 9.2203759 | D12: ='9'!$F$7 -> 5.389229 | E12: ='9'!$F$8 -> 5.0979898 | F12: ='9'!$F$9 | G12: ='9'!$F$10 | H12: ='9'!$F$11 -> 14.848485 | I12: ='9'!$F$12 -> 7.6692086 | J12: ='9'!$F$13 -> 5.1136507 | K12: ='9'!$F$14 | L12: ='9'!$F$15 -> 5.7386365 | M12: ='9'!$F$16 -> 6.0010827 | N12: ='9'!$F$17 -> 4.1988797 | O12: ='9'!$F$18 -> 8.4617609 | P12: ='9'!$F$19 | Q12: ='9'!$F$20 -> 5.4367112 | R12: ='9'!$F$21 -> 8.7814972 | S12: ='9'!$F$22 -> 9.6208145 | T12: ='9'!$F$23 -> 5.1189859 | U12: ='9'!$F$24 -> 6.6310422 | V12: ='9'!$F$25 | W12: ='9'!$F$26 -> 5.4383284 | X12: ='9'!$F$27 -> 13.510841 | Y12: ='9'!$F$28 -> 7.6038052 | Z12: ='9'!$F$29 -> 5.1075796 | AA12: ='9'!$F$30 -> 6.6554998 | AB12: ='9'!$F$31 -> 6.7314656 | AC12: ='9'!$F$32 -> 6.665598 | AD12: ='9'!$F$33 -> 6.3060055
A13: Clarendon | B13: ='10'!$F$5 -> 8.5934687 | C13: ='10'!$F$6 -> 7.2038554 | D13: ='10'!$F$7 -> 5.8444132 | E13: ='10'!$F$8 -> 8.6928727 | F13: ='10'!$F$9 | G13: ='10'!$F$10 | H13: ='10'!$F$11 -> 9.9000799 | I13: ='10'!$F$12 | J13: ='10'!$F$13 -> 5.4085988 | K13: ='10'!$F$14 | L13: ='10'!$F$15 -> 6.3912039 | M13: ='10'!$F$16 -> 5.7354621 | N13: ='10'!$F$17 -> 5.1206133 | O13: ='10'!$F$18 | P13: ='10'!$F$19 | Q13: ='10'!$F$20 -> 4.8647356 | R13: ='10'!$F$21 | S13: ='10'!$F$22 -> 7.2720723 | T13: ='10'!$F$23 -> 7.5989367 | U13: ='10'!$F$24 | V13: ='10'!$F$25 | W13: ='10'!$F$26 | X13: ='10'!$F$27 -> 11.740245 | Y13: ='10'!$F$28 -> 6.2144003 | Z13: ='10'!$F$29 -> 5.4998383 | AA13: ='10'!$F$30 -> 5.3235885 | AB13: ='10'!$F$31 -> 6.152708 | AC13: ='10'!$F$32 -> 5.4460515 | AD13: ='10'!$F$33 -> 6.7304978
A14: Coastal Bend | B14: ='11'!$F$5 -> 9.2544136 | C14: ='11'!$F$6 -> 9.584667 | D14: ='11'!$F$7 -> 8.1919752 | E14: ='11'!$F$8 -> 9.3606409 | F14: ='11'!$F$9 | G14: ='11'!$F$10 -> 15.439995 | H14: ='11'!$F$11 -> 9.6319645 | I14: ='11'!$F$12 | J14: ='11'!$F$13 -> 9.796438 | K14: ='11'!$F$14 | L14: ='11'!$F$15 -> 9.1432381 | M14: ='11'!$F$16 -> 7.239567 | N14: ='11'!$F$17 -> 7.156023 | O14: ='11'!$F$18 -> 29.16995 | P14: ='11'!$F$19 -> 19.149286 | Q14: ='11'!$F$20 -> 9.4056519 | R14: ='11'!$F$21 | S14: ='11'!$F$22 -> 9.8764023 | T14: ='11'!$F$23 -> 8.2581282 | U14: ='11'!$F$24 -> 8.7434833 | V14: ='11'!$F$25 -> 10.04911 | W14: ='11'!$F$26 -> 14.812097 | X14: ='11'!$F$27 -> 10.411058 | Y14: ='11'!$F$28 -> 10.201589 | Z14: ='11'!$F$29 -> 7.3183201 | AA14: ='11'!$F$30 -> 8.678719 | AB14: ='11'!$F$31 -> 8.039914 | AC14: ='11'!$F$32 -> 7.8750191 | AD14: ='11'!$F$33 -> 9.1202529
A15: College Of The Mainland | B15: ='12'!$F$5 -> 27.725463 | C15: ='12'!$F$6 -> 21.11428 | D15: ='12'!$F$7 -> 10.315733 | E15: ='12'!$F$8 -> 10.871102 | F15: ='12'!$F$9 | G15: ='12'!$F$10 -> 13.800268 | H15: ='12'!$F$11 -> 19.187868 | I15: ='12'!$F$12 -> 8.7445736 | J15: ='12'!$F$13 -> 16.446824 | K15: ='12'!$F$14 | L15: ='12'!$F$15 -> 7.3759759 | M15: ='12'!$F$16 -> 15.090014 | N15: ='12'!$F$17 -> 13.011413 | O15: ='12'!$F$18 -> 17.05091 | P15: ='12'!$F$19 | Q15: ='12'!$F$20 -> 14.650519 | R15: ='12'!$F$21 | S15: ='12'!$F$22 -> 18.380482 | T15: ='12'!$F$23 -> 14.037207 | U15: ='12'!$F$24 | V15: ='12'!$F$25 | W15: ='12'!$F$26 -> 10.84756 | X15: ='12'!$F$27 -> 12.409324 | Y15: ='12'!$F$28 -> 16.570437 | Z15: ='12'!$F$29 -> 11.416778 | AA15: ='12'!$F$30 -> 16.032004 | AB15: ='12'!$F$31 -> 10.772026 | AC15: ='12'!$F$32 -> 14.81608 | AD15: ='12'!$F$33 -> 13.421712
A16: Collin | B16: ='13'!$F$5 -> 6.3280943 | C16: ='13'!$F$6 -> 3.3940303 | D16: ='13'!$F$7 -> 7.5241072 | E16: ='13'!$F$8 -> 6.4857674 | F16: ='13'!$F$9 -> 3.3910226 | G16: ='13'!$F$10 -> 5.2722709 | H16: ='13'!$F$11 -> 7.8063402 | I16: ='13'!$F$12 -> 3.3902604 | J16: ='13'!$F$13 -> 6.4130349 | K16: ='13'!$F$14 -> 19.385347 | L16: ='13'!$F$15 -> 8.9248148 | M16: ='13'!$F$16 -> 6.9754622 | N16: ='13'!$F$17 -> 5.1330632 | O16: ='13'!$F$18 -> 20.447108 | P16: ='13'!$F$19 -> 22.990522 | Q16: ='13'!$F$20 -> 5.6195968 | R16: ='13'!$F$21 -> 18.951789 | S16: ='13'!$F$22 | T16: ='13'!$F$23 -> 6.5740788 | U16: ='13'!$F$24 | V16: ='13'!$F$25 -> 3.3916752 | W16: ='13'!$F$26 -> 3.3916144 | X16: ='13'!$F$27 -> 7.8020781 | Y16: ='13'!$F$28 -> 9.5425776 | Z16: ='13'!$F$29 -> 6.3718372 | AA16: ='13'!$F$30 -> 8.6325457 | AB16: ='13'!$F$31 -> 6.476204 | AC16: ='13'!$F$32 -> 7.2586729 | AD16: ='13'!$F$33 -> 7.217813
A17: Dallas | B17: ='14'!$F$5 -> 17.093046 | C17: ='14'!$F$6 -> 8.8055314 | D17: ='14'!$F$7 -> 7.5475849 | E17: ='14'!$F$8 -> 7.5111984 | F17: ='14'!$F$9 -> 16.81923 | G17: ='14'!$F$10 -> 8.9873231 | H17: ='14'!$F$11 -> 7.5715205 | I17: ='14'!$F$12 -> 13.049596 | J17: ='14'!$F$13 -> 7.1326407 | K17: ='14'!$F$14 -> 9.7679608 | L17: ='14'!$F$15 -> 6.5220504 | M17: ='14'!$F$16 -> 9.8651015 | N17: ='14'!$F$17 -> 6.9070911 | O17: ='14'!$F$18 -> 11.357149 | P17: ='14'!$F$19 | Q17: ='14'!$F$20 -> 7.7047482 | R17: ='14'!$F$21 -> 18.172187 | S17: ='14'!$F$22 -> 18.06386 | T17: ='14'!$F$23 -> 6.7948826 | U17: ='14'!$F$24 -> 9.439785 | V17: ='14'!$F$25 -> 5.2808973 | W17: ='14'!$F$26 -> 9.6455626 | X17: ='14'!$F$27 -> 9.5846671 | Y17: ='14'!$F$28 -> 7.1046935 | Z17: ='14'!$F$29 -> 6.586765 | AA17: ='14'!$F$30 -> 8.3085216 | AB17: ='14'!$F$31 -> 7.2419807 | AC17: ='14'!$F$32 -> 5.6653704 | AD17: ='14'!$F$33 -> 7.6776755
A18: Del Mar | B18: ='15'!$F$5 -> 5.3016629 | C18: ='15'!$F$6 -> 8.0079287 | D18: ='15'!$F$7 -> 8.2802773 | E18: ='15'!$F$8 -> 10.479156 | F18: ='15'!$F$9 | G18: ='15'!$F$10 -> 10.466116 | H18: ='15'!$F$11 -> 10.158772 | I18: ='15'!$F$12 -> 5.1560122 | J18: ='15'!$F$13 -> 9.516769 | K18: ='15'!$F$14 -> 6.4454946 | L18: ='15'!$F$15 -> 8.9607028 | M18: ='15'!$F$16 -> 12.312635 | N18: ='15'!$F$17 -> 8.6884305 | O18: ='15'!$F$18 -> 14.179397 | P18: ='15'!$F$19 -> 19.432521 | Q18: ='15'!$F$20 -> 11.027284 | R18: ='15'!$F$21 -> 15.974721 | S18: ='15'!$F$22 -> 14.528481 | T18: ='15'!$F$23 -> 10.685502 | U18: ='15'!$F$24 -> 12.863142 | V18: ='15'!$F$25 -> 8.7395647 | W18: ='15'!$F$26 -> 10.0525 | X18: ='15'!$F$27 -> 9.5642065 | Y18: ='15'!$F$28 -> 11.888675 | Z18: ='15'!$F$29 -> 8.5509666 | AA18: ='15'!$F$30 -> 9.7081155 | AB18: ='15'!$F$31 -> 10.946995 | AC18: ='15'!$F$32 -> 10.649169 | AD18: ='15'!$F$33 -> 10.223075
A19: El Paso | B19: ='16'!$F$5 -> 5.6357007 | C19: ='16'!$F$6 -> 7.4389768 | D19: ='16'!$F$7 -> 6.6305458 | E19: ='16'!$F$8 -> 10.063899 | F19: ='16'!$F$9 | G19: ='16'!$F$10 -> 14.518709 | H19: ='16'!$F$11 -> 7.8215325 | I19: ='16'!$F$12 -> 9.720769 | J19: ='16'!$F$13 -> 8.157025 | K19: ='16'!$F$14 -> 7.3200106 | L19: ='16'!$F$15 -> 7.5501585 | M19: ='16'!$F$16 -> 7.1053402 | N19: ='16'!$F$17 -> 8.129902 | O19: ='16'!$F$18 -> 16.127969 | P19: ='16'!$F$19 -> 26.942426 | Q19: ='16'!$F$20 -> 11.066422 | R19: ='16'!$F$21 -> 15.591998 | S19: ='16'!$F$22 -> 11.229051 | T19: ='16'!$F$23 -> 7.0607968 | U19: ='16'!$F$24 -> 7.8739234 | V19: ='16'!$F$25 -> 16.286018 | W19: ='16'!$F$26 -> 11.598481 | X19: ='16'!$F$27 -> 18.301662 | Y19: ='16'!$F$28 -> 7.568605 | Z19: ='16'!$F$29 -> 6.3949222 | AA19: ='16'!$F$30 -> 7.8974745 | AB19: ='16'!$F$31 -> 6.4156479 | AC19: ='16'!$F$32 -> 7.764393 | AD19: ='16'!$F$33 -> 7.7743912
A20: Frank Phillips | B20: ='17'!$F$5 -> 15.544913 | C20: ='17'!$F$6 -> 10.203326 | D20: ='17'!$F$7 -> 10.293752 | E20: ='17'!$F$8 -> 10.940532 | F20: ='17'!$F$9 | G20: ='17'!$F$10 | H20: ='17'!$F$11 -> 8.9805256 | I20: ='17'!$F$12 -> 6.1869172 | J20: ='17'!$F$13 -> 10.043164 | K20: ='17'!$F$14 | L20: ='17'!$F$15 -> 10.170192 | M20: ='17'!$F$16 -> 9.9343835 | N20: ='17'!$F$17 -> 9.5377983 | O20: ='17'!$F$18 -> 13.284825 | P20: ='17'!$F$19 | Q20: ='17'!$F$20 -> 10.424881 | R20: ='17'!$F$21 | S20: ='17'!$F$22 -> 10.39145 | T20: ='17'!$F$23 -> 10.395487 | U20: ='17'!$F$24 | V20: ='17'!$F$25 -> 5.6022772 | W20: ='17'!$F$26 -> 53.084035 | X20: ='17'!$F$27 -> 9.5952375 | Y20: ='17'!$F$28 -> 7.7219064 | Z20: ='17'!$F$29 -> 10.035405 | AA20: ='17'!$F$30 -> 8.0933068 | AB20: ='17'!$F$31 -> 10.730399 | AC20: ='17'!$F$32 -> 10.389857 | AD20: ='17'!$F$33 -> 10.174648
A21: Galveston | B21: ='18'!$F$5 -> 10.647999 | C21: ='18'!$F$6 -> 11.157174 | D21: ='18'!$F$7 -> 10.279924 | E21: ='18'!$F$8 -> 10.09986 | F21: ='18'!$F$9 | G21: ='18'!$F$10 | H21: ='18'!$F$11 -> 12.762953 | I21: ='18'!$F$12 | J21: ='18'!$F$13 -> 11.072514 | K21: ='18'!$F$14 | L21: ='18'!$F$15 -> 13.285666 | M21: ='18'!$F$16 -> 9.8377772 | N21: ='18'!$F$17 -> 7.3267775 | O21: ='18'!$F$18 -> 19.156557 | P21: ='18'!$F$19 | Q21: ='18'!$F$20 -> 11.648394 | R21: ='18'!$F$21 | S21: ='18'!$F$22 -> 14.027333 | T21: ='18'!$F$23 -> 10.931916 | U21: ='18'!$F$24 -> 16.522114 | V21: ='18'!$F$25 -> 13.181114 | W21: ='18'!$F$26 | X21: ='18'!$F$27 -> 14.700029 | Y21: ='18'!$F$28 -> 11.637956 | Z21: ='18'!$F$29 -> 9.3734096 | AA21: ='18'!$F$30 -> 11.642538 | AB21: ='18'!$F$31 -> 8.8317656 | AC21: ='18'!$F$32 -> 11.956623 | AD21: ='18'!$F$33 -> 11.389891
A22: Grayson | B22: ='19'!$F$5 -> 7.1008676 | C22: ='19'!$F$6 -> 6.8135853 | D22: ='19'!$F$7 -> 6.8170116 | E22: ='19'!$F$8 -> 8.0608432 | F22: ='19'!$F$9 | G22: ='19'!$F$10 | H22: ='19'!$F$11 -> 7.4416932 | I22: ='19'!$F$12 -> 4.7867777 | J22: ='19'!$F$13 -> 6.7449536 | K22: ='19'!$F$14 -> 11.031388 | L22: ='19'!$F$15 -> 9.3387826 | M22: ='19'!$F$16 -> 5.6226884 | N22: ='19'!$F$17 -> 8.1240671 | O22: ='19'!$F$18 -> 10.01487 | P22: ='19'!$F$19 | Q22: ='19'!$F$20 -> 8.2002769 | R22: ='19'!$F$21 | S22: ='19'!$F$22 -> 7.1351984 | T22: ='19'!$F$23 -> 6.2582833 | U22: ='19'!$F$24 -> 8.214931 | V22: ='19'!$F$25 -> 2.9305107 | W22: ='19'!$F$26 -> 10.74754 | X22: ='19'!$F$27 -> 3.5285075 | Y22: ='19'!$F$28 -> 7.4728657 | Z22: ='19'!$F$29 -> 5.9061961 | AA22: ='19'!$F$30 -> 6.8648886 | AB22: ='19'!$F$31 -> 5.5141334 | AC22: ='19'!$F$32 -> 6.882798 | AD22: ='19'!$F$33 -> 7.0353753
A23: Hill | B23: ='20'!$F$5 -> 8.1165648 | C23: ='20'!$F$6 -> 7.0960201 | D23: ='20'!$F$7 -> 5.969324 | E23: ='20'!$F$8 -> 3.4086908 | F23: ='20'!$F$9 | G23: ='20'!$F$10 -> 4.7929674 | H23: ='20'!$F$11 -> 17.426127 | I23: ='20'!$F$12 -> 12.759504 | J23: ='20'!$F$13 -> 5.5724691 | K23: ='20'!$F$14 -> 4.4976457 | L23: ='20'!$F$15 -> 4.8068957 | M23: ='20'!$F$16 -> 4.948342 | N23: ='20'!$F$17 -> 4.6522589 | O23: ='20'!$F$18 -> 8.3489928 | P23: ='20'!$F$19 | Q23: ='20'!$F$20 -> 6.8251232 | R23: ='20'!$F$21 | S23: ='20'!$F$22 -> 8.0498258 | T23: ='20'!$F$23 -> 4.8088858 | U23: ='20'!$F$24 -> 7.5052634 | V23: ='20'!$F$25 | W23: ='20'!$F$26 | X23: ='20'!$F$27 -> 11.433846 | Y23: ='20'!$F$28 -> 6.4165167 | Z23: ='20'!$F$29 -> 5.1109359 | AA23: ='20'!$F$30 -> 6.1848954 | AB23: ='20'!$F$31 -> 4.7164463 | AC23: ='20'!$F$32 -> 4.9205893 | AD23: ='20'!$F$33 -> 5.9307518
A24: Houston | B24: ='21'!$F$5 -> 6.8367271 | C24: ='21'!$F$6 -> 10.007252 | D24: ='21'!$F$7 -> 6.9735462 | E24: ='21'!$F$8 -> 6.3981656 | F24: ='21'!$F$9 | G24: ='21'!$F$10 -> 5.999455 | H24: ='21'!$F$11 -> 14.628804 | I24: ='21'!$F$12 -> 8.752119 | J24: ='21'!$F$13 -> 7.0158781 | K24: ='21'!$F$14 -> 6.6994726 | L24: ='21'!$F$15 -> 6.6994763 | M24: ='21'!$F$16 -> 8.0386044 | N24: ='21'!$F$17 -> 7.1070843 | O24: ='21'!$F$18 -> 10.458052 | P24: ='21'!$F$19 -> 18.060693 | Q24: ='21'!$F$20 -> 9.4792134 | R24: ='21'!$F$21 -> 18.074046 | S24: ='21'!$F$22 -> 12.329301 | T24: ='21'!$F$23 -> 6.7621515 | U24: ='21'!$F$24 -> 8.569123 | V24: ='21'!$F$25 -> 14.131471 | W24: ='21'!$F$26 -> 7.7067216 | X24: ='21'!$F$27 -> 10.156315 | Y24: ='21'!$F$28 -> 10.355787 | Z24: ='21'!$F$29 -> 6.4047737 | AA24: ='21'!$F$30 -> 8.0180562 | AB24: ='21'!$F$31 -> 6.7621522 | AC24: ='21'!$F$32 -> 8.0386044 | AD24: ='21'!$F$33 -> 7.4988708
A25: Howard | B25: ='22'!$F$5 -> 9.0880857 | C25: ='22'!$F$6 -> 6.0773495 | D25: ='22'!$F$7 -> 7.5509798 | E25: ='22'!$F$8 -> 7.5800023 | F25: ='22'!$F$9 -> 7.7403414 | G25: ='22'!$F$10 -> 6.106786 | H25: ='22'!$F$11 -> 9.5263176 | I25: ='22'!$F$12 -> 5.6855803 | J25: ='22'!$F$13 -> 8.2532399 | K25: ='22'!$F$14 | L25: ='22'!$F$15 -> 6.6918256 | M25: ='22'!$F$16 -> 7.3693608 | N25: ='22'!$F$17 -> 7.4756774 | O25: ='22'!$F$18 -> 15.006583 | P25: ='22'!$F$19 -> 21.673264 | Q25: ='22'!$F$20 -> 7.116626 | R25: ='22'!$F$21 -> 18.228912 | S25: ='22'!$F$22 -> 9.7851472 | T25: ='22'!$F$23 -> 8.7576328 | U25: ='22'!$F$24 -> 6.092292 | V25: ='22'!$F$25 -> 6.5687017 | W25: ='22'!$F$26 -> 5.3949366 | X25: ='22'!$F$27 -> 38.317242 | Y25: ='22'!$F$28 -> 6.2193037 | Z25: ='22'!$F$29 -> 6.6422507 | AA25: ='22'!$F$30 -> 9.0028362 | AB25: ='22'!$F$31 -> 7.0959567 | AC25: ='22'!$F$32 -> 7.1072658 | AD25: ='22'!$F$33 -> 7.865038
A26: Kilgore | B26: ='23'!$F$5 -> 5.1687223 | C26: ='23'!$F$6 -> 6.8380901 | D26: ='23'!$F$7 -> 7.3545665 | E26: ='23'!$F$8 -> 6.5467961 | F26: ='23'!$F$9 | G26: ='23'!$F$10 -> 11.211345 | H26: ='23'!$F$11 -> 6.8611077 | I26: ='23'!$F$12 -> 45.535125 | J26: ='23'!$F$13 -> 6.012862 | K26: ='23'!$F$14 -> 12.765463 | L26: ='23'!$F$15 -> 6.6784019 | M26: ='23'!$F$16 -> 6.7265379 | N26: ='23'!$F$17 -> 8.2311738 | O26: ='23'!$F$18 -> 9.3255158 | P26: ='23'!$F$19 | Q26: ='23'!$F$20 -> 7.5770462 | R26: ='23'!$F$21 | S26: ='23'!$F$22 -> 7.2167159 | T26: ='23'!$F$23 -> 6.0796865 | U26: ='23'!$F$24 -> 8.2867696 | V26: ='23'!$F$25 -> 5.1459559 | W26: ='23'!$F$26 -> 3.1009279 | X26: ='23'!$F$27 -> 8.8290602 | Y26: ='23'!$F$28 -> 7.819075 | Z26: ='23'!$F$29 -> 5.7285441 | AA26: ='23'!$F$30 -> 8.1207731 | AB26: ='23'!$F$31 -> 6.2166172 | AC26: ='23'!$F$32 -> 5.0206017 | AD26: ='23'!$F$33 -> 6.9945526
A27: Laredo | B27: ='24'!$F$5 -> 5.386017 | C27: ='24'!$F$6 -> 5.386017 | D27: ='24'!$F$7 -> 9.7457455 | E27: ='24'!$F$8 -> 10.857436 | F27: ='24'!$F$9 | G27: ='24'!$F$10 -> 8.0217047 | H27: ='24'!$F$11 -> 13.758038 | I27: ='24'!$F$12 -> 30.892489 | J27: ='24'!$F$13 -> 5.386017 | K27: ='24'!$F$14 | L27: ='24'!$F$15 -> 5.386017 | M27: ='24'!$F$16 -> 14.367375 | N27: ='24'!$F$17 -> 33.020467 | O27: ='24'!$F$18 -> 17.030067 | P27: ='24'!$F$19 | Q27: ='24'!$F$20 -> 10.459222 | R27: ='24'!$F$21 | S27: ='24'!$F$22 -> 19.750446 | T27: ='24'!$F$23 -> 9.7240793 | U27: ='24'!$F$24 -> 10.081239 | V27: ='24'!$F$25 -> 12.051543 | W27: ='24'!$F$26 -> 17.965047 | X27: ='24'!$F$27 -> 12.415977 | Y27: ='24'!$F$28 -> 10.599319 | Z27: ='24'!$F$29 -> 8.0949392 | AA27: ='24'!$F$30 -> 12.013273 | AB27: ='24'!$F$31 -> 9.7237984 | AC27: ='24'!$F$32 -> 8.0159158 | AD27: ='24'!$F$33 -> 10.788772
A28: Lee | B28: ='25'!$F$5 -> 6.1735628 | C28: ='25'!$F$6 -> 13.355632 | D28: ='25'!$F$7 -> 8.4029531 | E28: ='25'!$F$8 -> 9.4532329 | F28: ='25'!$F$9 -> 15.644658 | G28: ='25'!$F$10 -> 10.005484 | H28: ='25'!$F$11 -> 11.061245 | I28: ='25'!$F$12 -> 13.585678 | J28: ='25'!$F$13 -> 7.6856358 | K28: ='25'!$F$14 | L28: ='25'!$F$15 -> 8.7059293 | M28: ='25'!$F$16 -> 11.535144 | N28: ='25'!$F$17 -> 14.066331 | O28: ='25'!$F$18 -> 14.512986 | P28: ='25'!$F$19 | Q28: ='25'!$F$20 -> 12.804973 | R28: ='25'!$F$21 | S28: ='25'!$F$22 -> 11.863625 | T28: ='25'!$F$23 -> 9.0823779 | U28: ='25'!$F$24 -> 7.8444383 | V28: ='25'!$F$25 -> 9.4036719 | W28: ='25'!$F$26 -> 4.4066008 | X28: ='25'!$F$27 -> 19.610136 | Y28: ='25'!$F$28 -> 7.2448301 | Z28: ='25'!$F$29 -> 8.25761 | AA28: ='25'!$F$30 -> 11.486209 | AB28: ='25'!$F$31 -> 8.7009646 | AC28: ='25'!$F$32 -> 9.7367419 | AD28: ='25'!$F$33 -> 10.044798
A29: Lonestar | B29: ='26'!$F$5 -> 6.7729659 | C29: ='26'!$F$6 -> 10.378859 | D29: ='26'!$F$7 -> 8.0207125 | E29: ='26'!$F$8 -> 8.5341 | F29: ='26'!$F$9 -> 9.6312361 | G29: ='26'!$F$10 -> 7.0583943 | H29: ='26'!$F$11 -> 8.6744007 | I29: ='26'!$F$12 -> 9.5013367 | J29: ='26'!$F$13 -> 9.3043779 | K29: ='26'!$F$14 | L29: ='26'!$F$15 -> 10.000561 | M29: ='26'!$F$16 -> 8.8413176 | N29: ='26'!$F$17 -> 7.498634 | O29: ='26'!$F$18 -> 13.178399 | P29: ='26'!$F$19 -> 23.070413 | Q29: ='26'!$F$20 -> 10.901054 | R29: ='26'!$F$21 -> 14.421637 | S29: ='26'!$F$22 -> 10.496624 | T29: ='26'!$F$23 -> 8.7797363 | U29: ='26'!$F$24 -> 9.2528018 | V29: ='26'!$F$25 -> 11.600873 | W29: ='26'!$F$26 -> 9.9390635 | X29: ='26'!$F$27 -> 8.7495642 | Y29: ='26'!$F$28 -> 8.6003874 | Z29: ='26'!$F$29 -> 7.3754692 | AA29: ='26'!$F$30 -> 9.9387695 | AB29: ='26'!$F$31 -> 6.590473 | AC29: ='26'!$F$32 -> 7.3342293 | AD29: ='26'!$F$33 -> 8.4013413
A30: Mclennan | B30: ='27'!$F$5 -> 10.810868 | C30: ='27'!$F$6 | D30: ='27'!$F$7 -> 7.1721217 | E30: ='27'!$F$8 -> 8.8585347 | F30: ='27'!$F$9 | G30: ='27'!$F$10 -> 3.8564796 | H30: ='27'!$F$11 -> 11.965887 | I30: ='27'!$F$12 -> 3.1763993 | J30: ='27'!$F$13 -> 11.829414 | K30: ='27'!$F$14 -> 3.0653067 | L30: ='27'!$F$15 -> 13.171487 | M30: ='27'!$F$16 -> 10.290766 | N30: ='27'!$F$17 -> 7.0613589 | O30: ='27'!$F$18 -> 15.951753 | P30: ='27'!$F$19 | Q30: ='27'!$F$20 -> 9.95925 | R30: ='27'!$F$21 -> 12.152206 | S30: ='27'!$F$22 -> 8.4202799 | T30: ='27'!$F$23 -> 8.4633112 | U30: ='27'!$F$24 | V30: ='27'!$F$25 -> 13.534588 | W30: ='27'!$F$26 -> 3.0696794 | X30: ='27'!$F$27 -> 8.8221794 | Y30: ='27'!$F$28 -> 8.2147938 | Z30: ='27'!$F$29 -> 6.4959354 | AA30: ='27'!$F$30 -> 10.697654 | AB30: ='27'!$F$31 -> 8.0424318 | AC30: ='27'!$F$32 -> 3.7716615 | AD30: ='27'!$F$33 -> 8.9204867
A31: Midland | B31: ='28'!$F$5 -> 9.4961276 | C31: ='28'!$F$6 -> 10.340389 | D31: ='28'!$F$7 -> 10.024933 | E31: ='28'!$F$8 -> 9.02221 | F31: ='28'!$F$9 -> 98.679214 | G31: ='28'!$F$10 -> 27.305379 | H31: ='28'!$F$11 -> 15.38693 | I31: ='28'!$F$12 -> 6.2902899 | J31: ='28'!$F$13 -> 12.240151 | K31: ='28'!$F$14 -> 5.7586635 | L31: ='28'!$F$15 -> 16.422991 | M31: ='28'!$F$16 -> 9.9138903 | N31: ='28'!$F$17 -> 6.4499435 | O31: ='28'!$F$18 -> 13.029904 | P31: ='28'!$F$19 | Q31: ='28'!$F$20 -> 11.321056 | R31: ='28'!$F$21 -> 14.295897 | S31: ='28'!$F$22 -> 11.331994 | T31: ='28'!$F$23 -> 10.003144 | U31: ='28'!$F$24 -> 17.305238 | V31: ='28'!$F$25 -> 19.644836 | W31: ='28'!$F$26 -> 13.244941 | X31: ='28'!$F$27 -> 11.342409 | Y31: ='28'!$F$28 -> 8.8115274 | Z31: ='28'!$F$29 -> 9.1445063 | AA31: ='28'!$F$30 -> 11.381972 | AB31: ='28'!$F$31 -> 9.6018845 | AC31: ='28'!$F$32 -> 9.5629899 | AD31: ='28'!$F$33 -> 10.449426
A32: Navarro | B32: ='29'!$F$5 -> 10.61014 | C32: ='29'!$F$6 -> 3.8267987 | D32: ='29'!$F$7 -> 4.7690485 | E32: ='29'!$F$8 -> 5.8223744 | F32: ='29'!$F$9 | G32: ='29'!$F$10 -> 6.4593493 | H32: ='29'!$F$11 -> 4.1775792 | I32: ='29'!$F$12 -> 7.4598755 | J32: ='29'!$F$13 -> 2.8211081 | K32: ='29'!$F$14 -> 2.8944708 | L32: ='29'!$F$15 -> 4.6049975 | M32: ='29'!$F$16 -> 5.2291646 | N32: ='29'!$F$17 -> 3.7754211 | O32: ='29'!$F$18 -> 9.2016734 | P32: ='29'!$F$19 | Q32: ='29'!$F$20 -> 5.1039519 | R32: ='29'!$F$21 | S32: ='29'!$F$22 -> 7.8885853 | T32: ='29'!$F$23 -> 5.7836594 | U32: ='29'!$F$24 | V32: ='29'!$F$25 -> 2.6651552 | W32: ='29'!$F$26 -> 4.6124842 | X32: ='29'!$F$27 -> 5.3492164 | Y32: ='29'!$F$28 -> 4.4335319 | Z32: ='29'!$F$29 -> 4.8268825 | AA32: ='29'!$F$30 -> 5.6561068 | AB32: ='29'!$F$31 -> 4.6608651 | AC32: ='29'!$F$32 -> 4.2700681 | AD32: ='29'!$F$33 -> 4.9226315
A33: North Central Texas | B33: ='30'!$F$5 -> 8.1300939 | C33: ='30'!$F$6 -> 17.354871 | D33: ='30'!$F$7 -> 5.8422062 | E33: ='30'!$F$8 -> 4.9642061 | F33: ='30'!$F$9 | G33: ='30'!$F$10 -> 6.7558766 | H33: ='30'!$F$11 -> 14.781138 | I33: ='30'!$F$12 | J33: ='30'!$F$13 -> 5.8518481 | K33: ='30'!$F$14 | L33: ='30'!$F$15 -> 5.7642024 | M33: ='30'!$F$16 -> 6.6918392 | N33: ='30'!$F$17 -> 4.8115991 | O33: ='30'!$F$18 -> 9.6745379 | P33: ='30'!$F$19 | Q33: ='30'!$F$20 -> 8.4734791 | R33: ='30'!$F$21 | S33: ='30'!$F$22 -> 7.348304 | T33: ='30'!$F$23 -> 5.2872987 | U33: ='30'!$F$24 | V33: ='30'!$F$25 -> 10.837079 | W33: ='30'!$F$26 -> 7.0273071 | X33: ='30'!$F$27 -> 6.7045524 | Y33: ='30'!$F$28 -> 6.9071539 | Z33: ='30'!$F$29 -> 5.3445277 | AA33: ='30'!$F$30 -> 6.2744781 | AB33: ='30'!$F$31 -> 5.9548644 | AC33: ='30'!$F$32 -> 6.6070668 | AD33: ='30'!$F$33 -> 6.3247154
A34: Northeast Texas | B34: ='31'!$F$5 -> 16.912566 | C34: ='31'!$F$6 -> 6.2442586 | D34: ='31'!$F$7 -> 7.3298568 | E34: ='31'!$F$8 -> 7.21419 | F34: ='31'!$F$9 | G34: ='31'!$F$10 -> 12.749562 | H34: ='31'!$F$11 -> 11.987734 | I34: ='31'!$F$12 -> 10.501106 | J34: ='31'!$F$13 -> 5.6752674 | K34: ='31'!$F$14 | L34: ='31'!$F$15 -> 12.959875 | M34: ='31'!$F$16 -> 5.880576 | N34: ='31'!$F$17 -> 8.0679425 | O34: ='31'!$F$18 -> 8.4445349 | P34: ='31'!$F$19 -> 16.280953 | Q34: ='31'!$F$20 -> 8.8984827 | R34: ='31'!$F$21 | S34: ='31'!$F$22 -> 11.950779 | T34: ='31'!$F$23 -> 7.7694006 | U34: ='31'!$F$24 -> 12.533184 | V34: ='31'!$F$25 | W34: ='31'!$F$26 | X34: ='31'!$F$27 -> 6.1278944 | Y34: ='31'!$F$28 -> 9.2179678 | Z34: ='31'!$F$29 -> 5.9811002 | AA34: ='31'!$F$30 -> 9.559986 | AB34: ='31'!$F$31 -> 4.8910674 | AC34: ='31'!$F$32 -> 6.1299668 | AD34: ='31'!$F$33 -> 7.5647327
A35: Odessa | B35: ='32'!$F$5 -> 9.4216299 | C35: ='32'!$F$6 -> 12.330741 | D35: ='32'!$F$7 -> 9.7287775 | E35: ='32'!$F$8 -> 11.708731 | F35: ='32'!$F$9 | G35: ='32'!$F$10 -> 6.179641 | H35: ='32'!$F$11 -> 6.7683258 | I35: ='32'!$F$12 -> 6.4667529 | J35: ='32'!$F$13 -> 9.7228169 | K35: ='32'!$F$14 | L35: ='32'!$F$15 -> 10.56465 | M35: ='32'!$F$16 -> 10.707443 | N35: ='32'!$F$17 -> 10.838546 | O35: ='32'!$F$18 -> 14.974901 | P35: ='32'!$F$19 | Q35: ='32'!$F$20 -> 12.922722 | R35: ='32'!$F$21 | S35: ='32'!$F$22 -> 11.12038 | T35: ='32'!$F$23 -> 10.699444 | U35: ='32'!$F$24 -> 7.9617306 | V35: ='32'!$F$25 -> 28.05475 | W35: ='32'!$F$26 -> 13.55785 | X35: ='32'!$F$27 -> 10.692568 | Y35: ='32'!$F$28 -> 12.464223 | Z35: ='32'!$F$29 -> 9.3588625 | AA35: ='32'!$F$30 -> 11.039387 | AB35: ='32'!$F$31 -> 9.6302227 | AC35: ='32'!$F$32 -> 11.709524 | AD35: ='32'!$F$33 -> 10.931152
A36: Panola | B36: ='33'!$F$5 -> 19.512195 | C36: ='33'!$F$6 -> 15.61884 | D36: ='33'!$F$7 -> 7.3282486 | E36: ='33'!$F$8 -> 8.9492674 | F36: ='33'!$F$9 | G36: ='33'!$F$10 -> 24.75804 | H36: ='33'!$F$11 -> 11.099293 | I36: ='33'!$F$12 -> 12.662287 | J36: ='33'!$F$13 -> 6.682898 | K36: ='33'!$F$14 | L36: ='33'!$F$15 -> 6.2360171 | M36: ='33'!$F$16 -> 8.2336753 | N36: ='33'!$F$17 -> 9.0611184 | O36: ='33'!$F$18 -> 13.503623 | P36: ='33'!$F$19 | Q36: ='33'!$F$20 -> 9.0284371 | R36: ='33'!$F$21 | S36: ='33'!$F$22 -> 9.1874923 | T36: ='33'!$F$23 -> 13.536777 | U36: ='33'!$F$24 -> 12.6634 | V36: ='33'!$F$25 -> 35.704441 | W36: ='33'!$F$26 -> 19.512382 | X36: ='33'!$F$27 -> 9.5275866 | Y36: ='33'!$F$28 -> 8.1253463 | Z36: ='33'!$F$29 -> 6.7474025 | AA36: ='33'!$F$30 -> 9.2294536 | AB36: ='33'!$F$31 -> 6.5822207 | AC36: ='33'!$F$32 -> 6.5822102 | AD36: ='33'!$F$33 -> 8.9573771
A37: Paris | B37: ='34'!$F$5 | C37: ='34'!$F$6 -> 6.8438596 | D37: ='34'!$F$7 -> 4.4116518 | E37: ='34'!$F$8 -> 4.357372 | F37: ='34'!$F$9 | G37: ='34'!$F$10 -> 5.5845942 | H37: ='34'!$F$11 -> 4.9235552 | I37: ='34'!$F$12 -> 8.2591193 | J37: ='34'!$F$13 -> 6.3922439 | K37: ='34'!$F$14 -> 8.2585055 | L37: ='34'!$F$15 -> 4.0666074 | M37: ='34'!$F$16 -> 5.2124593 | N37: ='34'!$F$17 -> 5.0421167 | O37: ='34'!$F$18 -> 11.659048 | P37: ='34'!$F$19 | Q37: ='34'!$F$20 -> 6.7608943 | R37: ='34'!$F$21 | S37: ='34'!$F$22 -> 8.3979495 | T37: ='34'!$F$23 -> 6.6808038 | U37: ='34'!$F$24 | V37: ='34'!$F$25 -> 8.2585994 | W37: ='34'!$F$26 | X37: ='34'!$F$27 -> 5.958247 | Y37: ='34'!$F$28 -> 6.4550925 | Z37: ='34'!$F$29 -> 5.0350167 | AA37: ='34'!$F$30 -> 5.9445659 | AB37: ='34'!$F$31 -> 4.2713312 | AC37: ='34'!$F$32 -> 6.0281624 | AD37: ='34'!$F$33 -> 5.4778599
A38: Ranger | B38: ='35'!$F$5 -> 5.5042266 | C38: ='35'!$F$6 -> 4.288402 | D38: ='35'!$F$7 -> 4.2908284 | E38: ='35'!$F$8 -> 5.7470148 | F38: ='35'!$F$9 | G38: ='35'!$F$10 | H38: ='35'!$F$11 -> 3.7116888 | I38: ='35'!$F$12 | J38: ='35'!$F$13 -> 4.5205315 | K38: ='35'!$F$14 | L38: ='35'!$F$15 -> 11.86155 | M38: ='35'!$F$16 -> 5.0904863 | N38: ='35'!$F$17 -> 4.7595685 | O38: ='35'!$F$18 -> 11.216066 | P38: ='35'!$F$19 | Q38: ='35'!$F$20 -> 3.5683804 | R38: ='35'!$F$21 | S38: ='35'!$F$22 -> 4.595866 | T38: ='35'!$F$23 -> 4.92645 | U38: ='35'!$F$24 | V38: ='35'!$F$25 -> 2.8400044 | W38: ='35'!$F$26 | X38: ='35'!$F$27 -> 14.458223 | Y38: ='35'!$F$28 -> 2.6058348 | Z38: ='35'!$F$29 -> 3.2021446 | AA38: ='35'!$F$30 -> 5.0566189 | AB38: ='35'!$F$31 -> 4.5957696 | AC38: ='35'!$F$32 -> 4.5413951 | AD38: ='35'!$F$33 -> 5.1007269
A39: San Jacinto | B39: ='36'!$F$5 -> 4.5951511 | C39: ='36'!$F$6 -> 7.6513921 | D39: ='36'!$F$7 -> 7.2386345 | E39: ='36'!$F$8 -> 7.2359245 | F39: ='36'!$F$9 -> 23.312448 | G39: ='36'!$F$10 -> 7.4562139 | H39: ='36'!$F$11 -> 9.423425 | I39: ='36'!$F$12 -> 4.9824822 | J39: ='36'!$F$13 -> 9.5288752 | K39: ='36'!$F$14 -> 1305.4685 | L39: ='36'!$F$15 -> 8.0038967 | M39: ='36'!$F$16 -> 7.6614864 | N39: ='36'!$F$17 -> 7.7941974 | O39: ='36'!$F$18 -> 11.518159 | P39: ='36'!$F$19 | Q39: ='36'!$F$20 -> 10.973496 | R39: ='36'!$F$21 -> 11.626409 | S39: ='36'!$F$22 -> 11.283653 | T39: ='36'!$F$23 -> 8.0991814 | U39: ='36'!$F$24 -> 10.850504 | V39: ='36'!$F$25 -> 9.740499 | W39: ='36'!$F$26 -> 6.5026573 | X39: ='36'!$F$27 -> 8.4375081 | Y39: ='36'!$F$28 -> 9.3715154 | Z39: ='36'!$F$29 -> 7.7156204 | AA39: ='36'!$F$30 -> 9.9451672 | AB39: ='36'!$F$31 -> 8.0991811 | AC39: ='36'!$F$32 -> 7.6614853 | AD39: ='36'!$F$33 -> 8.5203562
A40: South Plains | B40: ='37'!$F$5 -> 12.932416 | C40: ='37'!$F$6 -> 9.5337086 | D40: ='37'!$F$7 -> 6.7269633 | E40: ='37'!$F$8 -> 6.0943626 | F40: ='37'!$F$9 | G40: ='37'!$F$10 -> 10.400987 | H40: ='37'!$F$11 -> 23.643843 | I40: ='37'!$F$12 -> 7.2514743 | J40: ='37'!$F$13 -> 6.4628175 | K40: ='37'!$F$14 -> 17.628085 | L40: ='37'!$F$15 -> 10.18552 | M40: ='37'!$F$16 -> 6.0704197 | N40: ='37'!$F$17 -> 7.1117507 | O40: ='37'!$F$18 -> 10.444058 | P40: ='37'!$F$19 | Q40: ='37'!$F$20 -> 13.093648 | R40: ='37'!$F$21 -> 8.0578668 | S40: ='37'!$F$22 -> 4.4671854 | T40: ='37'!$F$23 -> 6.4563734 | U40: ='37'!$F$24 -> 6.7993831 | V40: ='37'!$F$25 -> 5.9898657 | W40: ='37'!$F$26 -> 14.896114 | X40: ='37'!$F$27 -> 12.762079 | Y40: ='37'!$F$28 -> 4.6928877 | Z40: ='37'!$F$29 -> 7.537152 | AA40: ='37'!$F$30 -> 12.22181 | AB40: ='37'!$F$31 -> 6.8250084 | AC40: ='37'!$F$32 -> 13.176033 | AD40: ='37'!$F$33 -> 7.9040838
A41: South Texas | B41: ='38'!$F$5 -> 8.0078461 | C41: ='38'!$F$6 -> 9.2313712 | D41: ='38'!$F$7 -> 7.0958636 | E41: ='38'!$F$8 -> 5.4692808 | F41: ='38'!$F$9 | G41: ='38'!$F$10 -> 9.9075686 | H41: ='38'!$F$11 -> 6.2978875 | I41: ='38'!$F$12 -> 21.873346 | J41: ='38'!$F$13 -> 10.627261 | K41: ='38'!$F$14 -> 8.763618 | L41: ='38'!$F$15 -> 6.5729646 | M41: ='38'!$F$16 -> 8.2562885 | N41: ='38'!$F$17 -> 6.3685691 | O41: ='38'!$F$18 -> 10.990508 | P41: ='38'!$F$19 | Q41: ='38'!$F$20 -> 9.9928138 | R41: ='38'!$F$21 -> 13.420341 | S41: ='38'!$F$22 -> 12.377717 | T41: ='38'!$F$23 -> 5.964135 | U41: ='38'!$F$24 -> 7.6869663 | V41: ='38'!$F$25 -> 7.0414158 | W41: ='38'!$F$26 -> 8.1558468 | X41: ='38'!$F$27 -> 9.4225904 | Y41: ='38'!$F$28 -> 6.3974811 | Z41: ='38'!$F$29 -> 6.9879915 | AA41: ='38'!$F$30 -> 7.3990488 | AB41: ='38'!$F$31 -> 7.9236049 | AC41: ='38'!$F$32 -> 7.0077785 | AD41: ='38'!$F$33 -> 7.5128629
A42: Southwest Texas | B42: ='39'!$F$5 -> 9.612078 | C42: ='39'!$F$6 -> 9.8855417 | D42: ='39'!$F$7 -> 8.170478 | E42: ='39'!$F$8 -> 8.9438627 | F42: ='39'!$F$9 | G42: ='39'!$F$10 -> 9.4174484 | H42: ='39'!$F$11 -> 6.4894165 | I42: ='39'!$F$12 -> 10.464158 | J42: ='39'!$F$13 -> 8.0607988 | K42: ='39'!$F$14 -> 10.07973 | L42: ='39'!$F$15 -> 8.3789725 | M42: ='39'!$F$16 -> 10.169535 | N42: ='39'!$F$17 -> 4.2227465 | O42: ='39'!$F$18 -> 19.242638 | P42: ='39'!$F$19 | Q42: ='39'!$F$20 -> 11.148038 | R42: ='39'!$F$21 | S42: ='39'!$F$22 -> 12.009939 | T42: ='39'!$F$23 -> 11.702302 | U42: ='39'!$F$24 -> 10.004696 | V42: ='39'!$F$25 -> 13.666847 | W42: ='39'!$F$26 -> 9.6491741 | X42: ='39'!$F$27 -> 8.96249 | Y42: ='39'!$F$28 -> 7.4061866 | Z42: ='39'!$F$29 -> 7.2293162 | AA42: ='39'!$F$30 -> 7.4053241 | AB42: ='39'!$F$31 -> 7.7376537 | AC42: ='39'!$F$32 -> 5.940144 | AD42: ='39'!$F$33 -> 8.5703898
A43: Tarrant | B43: ='40'!$F$5 -> 9.5758977 | C43: ='40'!$F$6 -> 16.762403 | D43: ='40'!$F$7 -> 8.6453516 | E43: ='40'!$F$8 -> 7.5437235 | F43: ='40'!$F$9 | G43: ='40'!$F$10 -> 9.2052372 | H43: ='40'!$F$11 -> 10.768519 | I43: ='40'!$F$12 -> 9.230697 | J43: ='40'!$F$13 -> 9.0502276 | K43: ='40'!$F$14 -> 10.466238 | L43: ='40'!$F$15 -> 10.967165 | M43: ='40'!$F$16 -> 8.6537598 | N43: ='40'!$F$17 -> 8.4253715 | O43: ='40'!$F$18 -> 17.519542 | P43: ='40'!$F$19 -> 28.235599 | Q43: ='40'!$F$20 -> 13.852161 | R43: ='40'!$F$21 -> 20.786264 | S43: ='40'!$F$22 | T43: ='40'!$F$23 -> 8.4876819 | U43: ='40'!$F$24 -> 13.027537 | V43: ='40'!$F$25 -> 10.711202 | W43: ='40'!$F$26 -> 4.8471864 | X43: ='40'!$F$27 -> 9.8222297 | Y43: ='40'!$F$28 -> 14.26084 | Z43: ='40'!$F$29 -> 7.8523913 | AA43: ='40'!$F$30 -> 10.375684 | AB43: ='40'!$F$31 -> 8.4876815 | AC43: ='40'!$F$32 -> 8.6537596 | AD43: ='40'!$F$33 -> 9.1626
A44: Temple | B44: ='41'!$F$5 -> 8.22282 | C44: ='41'!$F$6 | D44: ='41'!$F$7 -> 7.6743114 | E44: ='41'!$F$8 -> 5.6002261 | F44: ='41'!$F$9 | G44: ='41'!$F$10 -> 11.350088 | H44: ='41'!$F$11 -> 8.3452637 | I44: ='41'!$F$12 | J44: ='41'!$F$13 -> 7.7326938 | K44: ='41'!$F$14 | L44: ='41'!$F$15 -> 17.500049 | M44: ='41'!$F$16 -> 7.2345084 | N44: ='41'!$F$17 -> 7.3540435 | O44: ='41'!$F$18 -> 10.422909 | P44: ='41'!$F$19 -> 23.41455 | Q44: ='41'!$F$20 -> 8.6099921 | R44: ='41'!$F$21 -> 9.8917807 | S44: ='41'!$F$22 -> 9.7454322 | T44: ='41'!$F$23 -> 8.2699682 | U44: ='41'!$F$24 | V44: ='41'!$F$25 -> 8.5568623 | W44: ='41'!$F$26 -> 8.6993278 | X44: ='41'!$F$27 -> 6.7791836 | Y44: ='41'!$F$28 -> 7.4450525 | Z44: ='41'!$F$29 -> 6.8137063 | AA44: ='41'!$F$30 -> 9.78159 | AB44: ='41'!$F$31 -> 6.8961324 | AC44: ='41'!$F$32 -> 6.8012153 | AD44: ='41'!$F$33 -> 7.9738085
A45: Texarkana | B45: ='42'!$F$5 -> 7.464961 | C45: ='42'!$F$6 -> 6.4091816 | D45: ='42'!$F$7 -> 8.2839308 | E45: ='42'!$F$8 -> 6.6701873 | F45: ='42'!$F$9 | G45: ='42'!$F$10 -> 12.173639 | H45: ='42'!$F$11 -> 4.251465 | I45: ='42'!$F$12 -> 8.3947667 | J45: ='42'!$F$13 -> 6.812735 | K45: ='42'!$F$14 | L45: ='42'!$F$15 -> 5.7689917 | M45: ='42'!$F$16 -> 5.4046392 | N45: ='42'!$F$17 -> 7.2833648 | O45: ='42'!$F$18 -> 14.720616 | P45: ='42'!$F$19 -> 9.9097747 | Q45: ='42'!$F$20 -> 8.5515076 | R45: ='42'!$F$21 | S45: ='42'!$F$22 -> 9.0701582 | T45: ='42'!$F$23 -> 6.7541627 | U45: ='42'!$F$24 -> 7.9317006 | V45: ='42'!$F$25 -> 18.798558 | W45: ='42'!$F$26 -> 5.5425147 | X45: ='42'!$F$27 -> 4.6473842 | Y45: ='42'!$F$28 -> 6.4284086 | Z45: ='42'!$F$29 -> 7.210187 | AA45: ='42'!$F$30 -> 10.32245 | AB45: ='42'!$F$31 -> 5.7460798 | AC45: ='42'!$F$32 -> 5.578605 | AD45: ='42'!$F$33 -> 7.5607172
A46: Texas Southmost | B46: ='43'!$F$5 -> 12.602875 | C46: ='43'!$F$6 -> 9.3259647 | D46: ='43'!$F$7 -> 11.287838 | E46: ='43'!$F$8 -> 19.373998 | F46: ='43'!$F$9 | G46: ='43'!$F$10 -> 8.5182127 | H46: ='43'!$F$11 -> 12.920707 | I46: ='43'!$F$12 -> 13.763491 | J46: ='43'!$F$13 -> 28.555495 | K46: ='43'!$F$14 -> 102.23352 | L46: ='43'!$F$15 -> 14.103195 | M46: ='43'!$F$16 -> 10.77048 | N46: ='43'!$F$17 -> 10.856793 | O46: ='43'!$F$18 -> 18.26263 | P46: ='43'!$F$19 | Q46: ='43'!$F$20 -> 17.862177 | R46: ='43'!$F$21 -> 20.595128 | S46: ='43'!$F$22 -> 17.643204 | T46: ='43'!$F$23 -> 9.9267868 | U46: ='43'!$F$24 -> 13.720274 | V46: ='43'!$F$25 | W46: ='43'!$F$26 -> 13.452609 | X46: ='43'!$F$27 -> 11.684336 | Y46: ='43'!$F$28 -> 10.74219 | Z46: ='43'!$F$29 -> 10.675715 | AA46: ='43'!$F$30 -> 14.721044 | AB46: ='43'!$F$31 -> 9.8913028 | AC46: ='43'!$F$32 -> 9.6580051 | AD46: ='43'!$F$33 -> 12.948357
A47: Trinity Valley | B47: ='44'!$F$5 -> 7.8140659 | C47: ='44'!$F$6 -> 5.2532903 | D47: ='44'!$F$7 -> 6.3188192 | E47: ='44'!$F$8 -> 7.0533247 | F47: ='44'!$F$9 | G47: ='44'!$F$10 -> 10.598295 | H47: ='44'!$F$11 -> 4.0622698 | I47: ='44'!$F$12 -> 5.6857308 | J47: ='44'!$F$13 -> 6.2437656 | K47: ='44'!$F$14 | L47: ='44'!$F$15 -> 5.7797332 | M47: ='44'!$F$16 -> 6.2158107 | N47: ='44'!$F$17 -> 5.5913248 | O47: ='44'!$F$18 -> 8.1808253 | P47: ='44'!$F$19 | Q47: ='44'!$F$20 -> 5.9878833 | R47: ='44'!$F$21 | S47: ='44'!$F$22 -> 7.2555233 | T47: ='44'!$F$23 -> 6.5027221 | U47: ='44'!$F$24 -> 6.126876 | V47: ='44'!$F$25 | W47: ='44'!$F$26 -> 4.4425543 | X47: ='44'!$F$27 -> 7.7831891 | Y47: ='44'!$F$28 -> 6.5233353 | Z47: ='44'!$F$29 -> 5.9226956 | AA47: ='44'!$F$30 -> 8.4823029 | AB47: ='44'!$F$31 -> 6.7342147 | AC47: ='44'!$F$32 -> 7.658264 | AD47: ='44'!$F$33 -> 6.4755124
A48: Tyler | B48: ='45'!$F$5 -> 6.2845056 | C48: ='45'!$F$6 -> 9.4125176 | D48: ='45'!$F$7 -> 7.7084879 | E48: ='45'!$F$8 -> 6.8974982 | F48: ='45'!$F$9 | G48: ='45'!$F$10 -> 14.114253 | H48: ='45'!$F$11 -> 9.7846546 | I48: ='45'!$F$12 -> 7.1633113 | J48: ='45'!$F$13 -> 8.0526518 | K48: ='45'!$F$14 -> 6.6256971 | L48: ='45'!$F$15 -> 8.3939382 | M48: ='45'!$F$16 -> 8.252576 | N48: ='45'!$F$17 -> 6.9037252 | O48: ='45'!$F$18 -> 10.752521 | P48: ='45'!$F$19 -> 17.150528 | Q48: ='45'!$F$20 -> 9.4305177 | R48: ='45'!$F$21 -> 11.041528 | S48: ='45'!$F$22 -> 7.9499102 | T48: ='45'!$F$23 -> 7.982446 | U48: ='45'!$F$24 -> 8.9389164 | V48: ='45'!$F$25 -> 6.6122801 | W48: ='45'!$F$26 -> 6.6228118 | X48: ='45'!$F$27 -> 14.034901 | Y48: ='45'!$F$28 -> 8.6450866 | Z48: ='45'!$F$29 -> 7.6884445 | AA48: ='45'!$F$30 -> 10.100022 | AB48: ='45'!$F$31 -> 8.6675577 | AC48: ='45'!$F$32 -> 6.5599846 | AD48: ='45'!$F$33 -> 8.4830775
A49: Vernon | B49: ='46'!$F$5 -> 9.6765442 | C49: ='46'!$F$6 -> 8.8643707 | D49: ='46'!$F$7 -> 6.9999116 | E49: ='46'!$F$8 -> 7.4606222 | F49: ='46'!$F$9 | G49: ='46'!$F$10 | H49: ='46'!$F$11 -> 7.4845297 | I49: ='46'!$F$12 -> 6.6091361 | J49: ='46'!$F$13 -> 8.2179337 | K49: ='46'!$F$14 | L49: ='46'!$F$15 -> 6.6090544 | M49: ='46'!$F$16 -> 7.8967054 | N49: ='46'!$F$17 -> 7.3972992 | O49: ='46'!$F$18 -> 8.0851765 | P49: ='46'!$F$19 | Q49: ='46'!$F$20 -> 7.3927989 | R49: ='46'!$F$21 | S49: ='46'!$F$22 -> 7.9305174 | T49: ='46'!$F$23 -> 9.3020941 | U49: ='46'!$F$24 -> 9.2254269 | V49: ='46'!$F$25 | W49: ='46'!$F$26 -> 31.892564 | X49: ='46'!$F$27 -> 7.459426 | Y49: ='46'!$F$28 -> 7.8960614 | Z49: ='46'!$F$29 -> 7.4740515 | AA49: ='46'!$F$30 -> 7.1527222 | AB49: ='46'!$F$31 -> 7.0265149 | AC49: ='46'!$F$32 -> 7.5226222 | AD49: ='46'!$F$33 -> 7.7827751
A50: Victoria | B50: ='47'!$F$5 -> 8.905787 | C50: ='47'!$F$6 -> 10.035268 | D50: ='47'!$F$7 -> 9.4123568 | E50: ='47'!$F$8 -> 8.0401062 | F50: ='47'!$F$9 | G50: ='47'!$F$10 -> 12.688477 | H50: ='47'!$F$11 -> 15.182219 | I50: ='47'!$F$12 -> 61.629306 | J50: ='47'!$F$13 -> 8.1535505 | K50: ='47'!$F$14 | L50: ='47'!$F$15 -> 7.9773534 | M50: ='47'!$F$16 -> 10.055811 | N50: ='47'!$F$17 -> 7.3577145 | O50: ='47'!$F$18 -> 13.747781 | P50: ='47'!$F$19 | Q50: ='47'!$F$20 -> 11.015033 | R50: ='47'!$F$21 -> 16.254578 | S50: ='47'!$F$22 -> 11.840839 | T50: ='47'!$F$23 -> 11.596383 | U50: ='47'!$F$24 | V50: ='47'!$F$25 -> 16.015253 | W50: ='47'!$F$26 -> 6.0869446 | X50: ='47'!$F$27 -> 9.4222803 | Y50: ='47'!$F$28 -> 13.846661 | Z50: ='47'!$F$29 -> 8.3209963 | AA50: ='47'!$F$30 -> 13.06557 | AB50: ='47'!$F$31 -> 8.840755 | AC50: ='47'!$F$32 -> 8.8154518 | AD50: ='47'!$F$33 -> 10.44722
A51: Weatherford | B51: ='48'!$F$5 -> 11.286221 | C51: ='48'!$F$6 -> 11.488428 | D51: ='48'!$F$7 -> 8.0690671 | E51: ='48'!$F$8 -> 8.2412505 | F51: ='48'!$F$9 | G51: ='48'!$F$10 -> 10.326191 | H51: ='48'!$F$11 -> 7.9750239 | I51: ='48'!$F$12 -> 12.16981 | J51: ='48'!$F$13 -> 11.164596 | K51: ='48'!$F$14 | L51: ='48'!$F$15 -> 13.605959 | M51: ='48'!$F$16 -> 9.0045018 | N51: ='48'!$F$17 -> 9.165126 | O51: ='48'!$F$18 -> 14.984635 | P51: ='48'!$F$19 | Q51: ='48'!$F$20 -> 9.6998883 | R51: ='48'!$F$21 -> 11.529515 | S51: ='48'!$F$22 -> 11.140602 | T51: ='48'!$F$23 -> 11.35803 | U51: ='48'!$F$24 -> 11.381925 | V51: ='48'!$F$25 -> 18.635162 | W51: ='48'!$F$26 -> 8.2450815 | X51: ='48'!$F$27 -> 7.2931166 | Y51: ='48'!$F$28 -> 9.3396783 | Z51: ='48'!$F$29 -> 7.7031476 | AA51: ='48'!$F$30 -> 10.796046 | AB51: ='48'!$F$31 -> 7.8010142 | AC51: ='48'!$F$32 -> 10.989637 | AD51: ='48'!$F$33 -> 9.4545595
A52: Western Texas | B52: ='49'!$F$5 -> 7.613134 | C52: ='49'!$F$6 -> 8.2390264 | D52: ='49'!$F$7 -> 5.4939707 | E52: ='49'!$F$8 -> 7.6811163 | F52: ='49'!$F$9 | G52: ='49'!$F$10 -> 5.480441 | H52: ='49'!$F$11 -> 5.8620283 | I52: ='49'!$F$12 -> 6.0222652 | J52: ='49'!$F$13 -> 7.7704588 | K52: ='49'!$F$14 | L52: ='49'!$F$15 -> 3.6582557 | M52: ='49'!$F$16 -> 6.0191321 | N52: ='49'!$F$17 -> 4.7354119 | O52: ='49'!$F$18 | P52: ='49'!$F$19 | Q52: ='49'!$F$20 -> 6.729143 | R52: ='49'!$F$21 | S52: ='49'!$F$22 -> 9.1673069 | T52: ='49'!$F$23 -> 5.6322658 | U52: ='49'!$F$24 | V52: ='49'!$F$25 -> 3.6582557 | W52: ='49'!$F$26 -> 6.4603973 | X52: ='49'!$F$27 -> 10.290644 | Y52: ='49'!$F$28 -> 4.8564228 | Z52: ='49'!$F$29 -> 6.507306 | AA52: ='49'!$F$30 -> 8.5234474 | AB52: ='49'!$F$31 -> 6.9883857 | AC52: ='49'!$F$32 -> 5.5123081 | AD52: ='49'!$F$33 -> 6.407398
A53: Wharton | B53: ='50'!$F$5 -> 11.485947 | C53: ='50'!$F$6 -> 7.4772195 | D53: ='50'!$F$7 -> 7.9738688 | E53: ='50'!$F$8 -> 6.1844844 | F53: ='50'!$F$9 | G53: ='50'!$F$10 -> 9.9134037 | H53: ='50'!$F$11 -> 11.762945 | I53: ='50'!$F$12 -> 14.341683 | J53: ='50'!$F$13 -> 8.3562579 | K53: ='50'!$F$14 | L53: ='50'!$F$15 -> 8.5131501 | M53: ='50'!$F$16 -> 7.7295332 | N53: ='50'!$F$17 -> 9.3984673 | O53: ='50'!$F$18 -> 17.479268 | P53: ='50'!$F$19 -> 21.276748 | Q53: ='50'!$F$20 -> 10.2318 | R53: ='50'!$F$21 | S53: ='50'!$F$22 -> 11.241997 | T53: ='50'!$F$23 -> 8.1825832 | U53: ='50'!$F$24 -> 8.6927651 | V53: ='50'!$F$25 | W53: ='50'!$F$26 -> 12.377241 | X53: ='50'!$F$27 -> 9.5079956 | Y53: ='50'!$F$28 -> 11.611071 | Z53: ='50'!$F$29 -> 7.3386008 | AA53: ='50'!$F$30 -> 9.6200079 | AB53: ='50'!$F$31 -> 5.1538771 | AC53: ='50'!$F$32 -> 9.4043469 | AD53: ='50'!$F$33 -> 8.6705042
A54: TSTC-Harlingen | B54: ='51'!$F$5 -> 11.118418 | C54: ='51'!$F$6 -> 10.719789 | D54: ='51'!$F$7 -> 7.3579653 | E54: ='51'!$F$8 -> 6.2594867 | F54: ='51'!$F$9 | G54: ='51'!$F$10 -> 14.680424 | H54: ='51'!$F$11 -> 13.271456 | I54: ='51'!$F$12 -> 27.247386 | J54: ='51'!$F$13 -> 8.8541448 | K54: ='51'!$F$14 -> 38.785206 | L54: ='51'!$F$15 -> 7.626606 | M54: ='51'!$F$16 -> 8.8140858 | N54: ='51'!$F$17 -> 6.8898523 | O54: ='51'!$F$18 -> 9.4325493 | P54: ='51'!$F$19 -> 13.596348 | Q54: ='51'!$F$20 -> 15.361738 | R54: ='51'!$F$21 | S54: ='51'!$F$22 -> 10.738149 | T54: ='51'!$F$23 -> 8.458419 | U54: ='51'!$F$24 -> 7.7353426 | V54: ='51'!$F$25 -> 8.84034 | W54: ='51'!$F$26 -> 7.3014067 | X54: ='51'!$F$27 -> 8.5537125 | Y54: ='51'!$F$28 -> 7.4417014 | Z54: ='51'!$F$29 -> 5.7030524 | AA54: ='51'!$F$30 -> 5.8481354 | AB54: ='51'!$F$31 -> 8.0363103 | AC54: ='51'!$F$32 -> 8.8540533 | AD54: ='51'!$F$33 -> 8.4842508
A55: TSTC-West Texas | B55: ='52'!$F$5 -> 18.37239 | C55: ='52'!$F$6 -> 18.373001 | D55: ='52'!$F$7 | E55: ='52'!$F$8 -> 13.309819 | F55: ='52'!$F$9 | G55: ='52'!$F$10 -> 18.372997 | H55: ='52'!$F$11 -> 13.309826 | I55: ='52'!$F$12 -> 18.372724 | J55: ='52'!$F$13 -> 18.372969 | K55: ='52'!$F$14 | L55: ='52'!$F$15 -> 21.619405 | M55: ='52'!$F$16 -> 133.87055 | N55: ='52'!$F$17 -> 133.86882 | O55: ='52'!$F$18 -> 17.296041 | P55: ='52'!$F$19 | Q55: ='52'!$F$20 -> 17.296015 | R55: ='52'!$F$21 | S55: ='52'!$F$22 -> 17.29601 | T55: ='52'!$F$23 -> 133.87139 | U55: ='52'!$F$24 -> 14.865357 | V55: ='52'!$F$25 -> 14.865386 | W55: ='52'!$F$26 -> 18.373151 | X55: ='52'!$F$27 -> 10.821203 | Y55: ='52'!$F$28 -> 13.309629 | Z55: ='52'!$F$29 -> 133.87079 | AA55: ='52'!$F$30 -> 13.309798 | AB55: ='52'!$F$31 -> 10.824239 | AC55: ='52'!$F$32 -> 10.823219 | AD55: ='52'!$F$33 -> 17.338861
A56: TSTC-Marshall | B56: ='53'!$F$5 | C56: ='53'!$F$6 -> 13.567753 | D56: ='53'!$F$7 -> 8.3791849 | E56: ='53'!$F$8 -> 8.6321618 | F56: ='53'!$F$9 | G56: ='53'!$F$10 -> 9.4687753 | H56: ='53'!$F$11 -> 8.6321346 | I56: ='53'!$F$12 -> 9.4689778 | J56: ='53'!$F$13 | K56: ='53'!$F$14 | L56: ='53'!$F$15 -> 11.624167 | M56: ='53'!$F$16 -> 8.3537293 | N56: ='53'!$F$17 | O56: ='53'!$F$18 | P56: ='53'!$F$19 | Q56: ='53'!$F$20 -> 9.4691996 | R56: ='53'!$F$21 | S56: ='53'!$F$22 | T56: ='53'!$F$23 -> 8.5828801 | U56: ='53'!$F$24 -> 12.073371 | V56: ='53'!$F$25 -> 12.073003 | W56: ='53'!$F$26 -> 9.4689906 | X56: ='53'!$F$27 | Y56: ='53'!$F$28 | Z56: ='53'!$F$29 -> 8.0040937 | AA56: ='53'!$F$30 -> 8.6318715 | AB56: ='53'!$F$31 -> 14.808315 | AC56: ='53'!$F$32 -> 14.622586 | AD56: ='53'!$F$33 -> 10.494
A57: TSTC-Waco | B57: ='54'!$F$5 -> 13.549518 | C57: ='54'!$F$6 -> 9.5823043 | D57: ='54'!$F$7 -> 10.655088 | E57: ='54'!$F$8 -> 7.4461328 | F57: ='54'!$F$9 -> 27.916217 | G57: ='54'!$F$10 -> 7.955162 | H57: ='54'!$F$11 -> 8.6416508 | I57: ='54'!$F$12 -> 8.4913548 | J57: ='54'!$F$13 -> 16.409549 | K57: ='54'!$F$14 | L57: ='54'!$F$15 -> 12.324895 | M57: ='54'!$F$16 -> 8.0222941 | N57: ='54'!$F$17 -> 12.29771 | O57: ='54'!$F$18 -> 8.7019416 | P57: ='54'!$F$19 | Q57: ='54'!$F$20 -> 8.240224 | R57: ='54'!$F$21 | S57: ='54'!$F$22 | T57: ='54'!$F$23 -> 9.6561224 | U57: ='54'!$F$24 -> 10.684033 | V57: ='54'!$F$25 -> 10.208018 | W57: ='54'!$F$26 -> 7.6496687 | X57: ='54'!$F$27 | Y57: ='54'!$F$28 -> 13.531545 | Z57: ='54'!$F$29 -> 11.336283 | AA57: ='54'!$F$30 -> 12.911439 | AB57: ='54'!$F$31 -> 9.6108739 | AC57: ='54'!$F$32 -> 8.0325229 | AD57: ='54'!$F$33 -> 10.356587
A58: Lamar-IOT | B58: ='55'!$F$5 | C58: ='55'!$F$6 -> 14.451394 | D58: ='55'!$F$7 -> 14.451398 | E58: ='55'!$F$8 -> 14.451403 | F58: ='55'!$F$9 | G58: ='55'!$F$10 | H58: ='55'!$F$11 -> 14.451414 | I58: ='55'!$F$12 -> 14.451376 | J58: ='55'!$F$13 -> 14.451411 | K58: ='55'!$F$14 | L58: ='55'!$F$15 -> 14.451398 | M58: ='55'!$F$16 -> 14.45141 | N58: ='55'!$F$17 | O58: ='55'!$F$18 -> 14.451399 | P58: ='55'!$F$19 -> 14.451375 | Q58: ='55'!$F$20 -> 14.4514 | R58: ='55'!$F$21 -> 14.451374 | S58: ='55'!$F$22 | T58: ='55'!$F$23 -> 14.451418 | U58: ='55'!$F$24 -> 14.451227 | V58: ='55'!$F$25 -> 14.451392 | W58: ='55'!$F$26 -> 14.451379 | X58: ='55'!$F$27 | Y58: ='55'!$F$28 -> 14.45141 | Z58: ='55'!$F$29 -> 14.451399 | AA58: ='55'!$F$30 -> 14.451393 | AB58: ='55'!$F$31 -> 14.451409 | AC58: ='55'!$F$32 -> 14.451409 | AD58: ='55'!$F$33 -> 14.451401
A59: Lamar-Orange | B59: ='56'!$F$5 -> 11.139481 | C59: ='56'!$F$6 -> 6.1164046 | D59: ='56'!$F$7 -> 11.023691 | E59: ='56'!$F$8 -> 11.085758 | F59: ='56'!$F$9 | G59: ='56'!$F$10 -> 6.1164046 | H59: ='56'!$F$11 -> 11.000635 | I59: ='56'!$F$12 -> 11.139842 | J59: ='56'!$F$13 -> 10.78836 | K59: ='56'!$F$14 | L59: ='56'!$F$15 -> 10.438357 | M59: ='56'!$F$16 -> 11.283371 | N59: ='56'!$F$17 -> 10.97402 | O59: ='56'!$F$18 -> 11.095774 | P59: ='56'!$F$19 | Q59: ='56'!$F$20 -> 11.050592 | R59: ='56'!$F$21 | S59: ='56'!$F$22 -> 11.136496 | T59: ='56'!$F$23 -> 11.105814 | U59: ='56'!$F$24 | V59: ='56'!$F$25 -> 6.1164046 | W59: ='56'!$F$26 -> 10.755828 | X59: ='56'!$F$27 -> 11.140313 | Y59: ='56'!$F$28 -> 10.633181 | Z59: ='56'!$F$29 -> 11.068383 | AA59: ='56'!$F$30 -> 10.88738 | AB59: ='56'!$F$31 -> 11.140413 | AC59: ='56'!$F$32 -> 9.7603368 | AD59: ='56'!$F$33 -> 11.046963
A60: Lamar-Port Arthur | B60: ='57'!$F$5 | C60: ='57'!$F$6 -> 9.0322562 | D60: ='57'!$F$7 -> 9.0321426 | E60: ='57'!$F$8 -> 9.0321378 | F60: ='57'!$F$9 | G60: ='57'!$F$10 -> 9.0321928 | H60: ='57'!$F$11 -> 9.0321474 | I60: ='57'!$F$12 -> 9.0321392 | J60: ='57'!$F$13 -> 9.0321483 | K60: ='57'!$F$14 | L60: ='57'!$F$15 -> 9.0321443 | M60: ='57'!$F$16 -> 9.0321503 | N60: ='57'!$F$17 -> 9.0321503 | O60: ='57'!$F$18 -> 9.0321418 | P60: ='57'!$F$19 | Q60: ='57'!$F$20 -> 9.0321588 | R60: ='57'!$F$21 | S60: ='57'!$F$22 -> 9.0321471 | T60: ='57'!$F$23 -> 9.0321372 | U60: ='57'!$F$24 -> 9.0321434 | V60: ='57'!$F$25 -> 9.0321493 | W60: ='57'!$F$26 -> 9.0320631 | X60: ='57'!$F$27 -> 9.0320944 | Y60: ='57'!$F$28 -> 9.0320781 | Z60: ='57'!$F$29 -> 9.0321501 | AA60: ='57'!$F$30 -> 9.0321613 | AB60: ='57'!$F$31 -> 9.032114 | AC60: ='57'!$F$32 -> 9.0321762 | AD60: ='57'!$F$33 -> 9.0321458
A61: Total | B61: =Summary!$F$5 -> 9.058171 | C61: =Summary!$F$6 -> 9.3992604 | D61: =Summary!$F$7 -> 7.805995 | E61: =Summary!$F$8 -> 7.7723659 | F61: =Summary!$F$9 -> 29.272886 | G61: =Summary!$F$10 -> 8.8634273 | H61: =Summary!$F$11 -> 9.4843582 | I61: =Summary!$F$12 -> 9.4807263 | J61: =Summary!$F$13 -> 8.3205882 | K61: =Summary!$F$14 -> 15.647119 | L61: =Summary!$F$15 -> 8.8028186 | M61: =Summary!$F$16 -> 8.4898241 | N61: =Summary!$F$17 -> 7.6018114 | O61: =Summary!$F$18 -> 12.792348 | P61: =Summary!$F$19 -> 19.29682 | Q61: =Summary!$F$20 -> 10.131872 | R61: =Summary!$F$21 -> 13.98859 | S61: =Summary!$F$22 -> 10.163486 | T61: =Summary!$F$23 -> 7.8012228 | U61: =Summary!$F$24 -> 9.6927806 | V61: =Summary!$F$25 -> 10.457594 | W61: =Summary!$F$26 -> 8.7283742 | X61: =Summary!$F$27 -> 9.4341489 | Y61: =Summary!$F$28 -> 8.6783557 | Z61: =Summary!$F$29 -> 7.1628616 | AA61: =Summary!$F$30 -> 9.5586722 | AB61: =Summary!$F$31 -> 7.42723 | AC61: =Summary!$F$32 -> 7.5269762 | AD61: =Summary!$F$33 -> 8.4221653
A62: Average (Excluding zero values) | B62: =AVERAGE(B$4:B$60) -> 9.7600514 | C62: =AVERAGE(C$4:C$60) -> 9.7102311 | D62: =AVERAGE(D$4:D$60) -> 7.8859457 | E62: =AVERAGE(E$4:E$60) -> 8.3171909 | F62: =AVERAGE(F$4:F$60) -> 23.6063 | G62: =AVERAGE(G$4:G$60) -> 10.422991 | H62: =AVERAGE(H$4:H$60) -> 10.688925 | I62: =AVERAGE(I$4:I$60) -> 11.531228 | ... AD62: =AVERAGE(AD$4:AD$60) -> 8.7905624
A63: High | B63: =MAX(B$4:B$60) -> 27.725463 | C63: =MAX(C$4:C$60) -> 21.11428 | D63: =MAX(D$4:D$60) -> 14.451398 | E63: =MAX(E$4:E$60) -> 19.373998 | F63: =MAX(F$4:F$60) -> 98.679214 | G63: =MAX(G$4:G$60) -> 28.21467 | H63: =MAX(H$4:H$60) -> 23.643843 | I63: =MAX(I$4:I$60) -> 61.629306 | ... AD63: =MAX(AD$4:AD$60) -> 17.338861
A64: Low (Excluding zero values) | B64: =MIN(B$4:B$60) -> 4.5951511 | C64: =MIN(C$4:C$60) -> 3.3940303 | D64: =MIN(D$4:D$60) -> 4.2908284 | E64: =MIN(E$4:E$60) -> 3.4086908 | F64: =MIN(F$4:F$60) -> 3.3910226 | G64: =MIN(G$4:G$60) -> 3.5824527 | H64: =MIN(H$4:H$60) -> 3.7116888 | I64: =MIN(I$4:I$60) -> 3.1763993 | ... AD64: =MIN(AD$4:AD$60) -> 4.9226315
A65: Median (Excluding zero values) | B65: =MEDIAN(B$4:B$60) -> 8.801034 | C65: =MEDIAN(C$4:C$60) -> 9.4125176 | D65: =MEDIAN(D$4:D$60) -> 7.6126456 | E65: =MEDIAN(E$4:E$60) -> 8.0401062 | F65: =MEDIAN(F$4:F$60) -> 15.644658 | G65: =MEDIAN(G$4:G$60) -> 9.4174484 | H65: =MEDIAN(H$4:H$60) -> 9.9000799 | I65: =MEDIAN(I$4:I$60) -> 8.9368365 | ... AD65: =MEDIAN(AD$4:AD$60) -> 8.4842508
B67: Discipline | L67: Discipline | V67: Discipline
B68: AG - Agriculture | L68: ENGR - Engineering Related | V68: MECH - Mechanics and Repairers - Diesel, Aviation Mechanics, and Transportation Workers
B69: ARCH - Architecture and Precision Production Trades | L69: LA - English Language, Lit, Philosophy, Humanities, & Interdisciplinary | V69: ELECT - Mechanics and Repairers - Electronics
B70: SCI - Biology, Physical Sciences, and Science Technology | L70: FL - Foreign Languages | V70: PE - Physical Education and Fitness
B71: BA - Business Management, Marketing, and Administrative Services | L71: HODA - Health Occupations - Dental Assistants, Medical Lab, and Assoc. Degree Nursing | V71: PA - Protective Services and Public Administration
B72: CP - Career Pilot | L72: HODH - Health Occupations - Dental Hygiene | V72: SS - Psychology, Social Sciences, and History
B73: COMM - Communications | L73: HOO - Health Occupations - Other | V73: FA - Visual and Performing Arts
B74: CS - Computer and Information Sciences | L74: HORT - Health Occupations - Respiratory Therapy
B75: CNSTR - Construction Trades | L75: NUR - Health Occupations - Vocational Nursing | V75: DEM - Developmental Education - Math
B76: HE - Consumer and Homemaking Education | L76: MATH - Mathematics | V76: DER - Developmental Education - Reading/Writing
B77: ENG - Engineering | L77: AUTO - Mechanics and Repairers - Automotive | V77: Total - All Disciplines

Sheet Discipline Analysis
A1: =Summary!A1 -> Community and Technical Colleges, Report of Fundable Operating Expenses, Fiscal Year (FY) 2012
A2: Discipline Analysis by Institution | X2: Discipline
A3: 1 | X3: Agriculture
X4: Architecture and Precision Production Trades
A5: Institution | B5: Contact Hours | C5: Total | E5: Faculty Salaries | G5: Academic Support | I5: Institutional Support | K5: Student Services | M5: Departmental Operating Expense | O5: Research | Q5: Scholarships and Fellowships | S5: Equipment Depreciation | U5: Local Benefits | X5: Biology, Physical Sciences, and Science Technology
C6: Expense | D6: per Hour | E6: Expense | F6: per Hour | G6: Expense | H6: per Hour | I6: Expense | J6: per Hour | K6: Expense | L6: per Hour | M6: Expense | N6: per Hour | O6: Expense | P6: per Hour | Q6: Expense | R6: per Hour | S6: Expense | T6: per Hour | U6: Expense | V6: per Hour | X6: Business Management, Marketing, and Administrative Services
A7: Alamo | B7: =OFFSET('1'!$D$4,$A$3,0) -> 88855 | C7: =OFFSET('1'!$E$4,$A$3,0) -> 579507.26 | D7: =IFERROR(C7/$B7,"") -> 6.5219432 | E7: =OFFSET('1'!$E$66,$A$3,0) -> 115581 | F7: =IFERROR(E7/$B7,"") -> 1.3007822 | G7: ='1'!$F$100*B7 -> 68826.942 | H7: =IFERROR(G7/$B7,"") -> 0.77459841 | I7: ='1'!$F$98*'Discipline Analysis'!B7 -> 167105.78 | J7: =IFERROR(I7/$B7,"") -> 1.880657 | K7: ='1'!$F$99*'Discipline Analysis'!B7 -> 80983.005 | L7: =IFERROR(K7/$B7,"") -> 0.91140628 | M7: =OFFSET('1'!$E$35,$A$3,0) -> 90393 | N7: =IFERROR(M7/$B7,"") -> 1.0173091 | O7: ='1'!$F$101*'Discipline Analysis'!B7 -> 0 | P7: =IFERROR(O7/$B7,"") -> 0 | Q7: ='1'!$F$102*'Discipline Analysis'!B7 -> 1134.326 | R7: =IFERROR(Q7/$B7,"") -> 0.012766034 | S7: ='1'!$F$103*'Discipline Analysis'!B7 -> 18389.218 | T7: =IFERROR(S7/$B7,"") -> 0.20695761 | U7: ='1'!$F$104*'Discipline Analysis'!B7 -> 37093.991 | V7: =IFERROR(U7/$B7,"") -> 0.41746656 | X7: Career Pilot
A8: Alvin | B8: =OFFSET('2'!$D$4,$A$3,0) -> 1152 | C8: =OFFSET('2'!$E$4,$A$3,0) -> 11915.957 | D8: =IFERROR(C8/$B8,"") -> 10.343713 | E8: =OFFSET('2'!$E$66,$A$3,0) -> 6395 | F8: =IFERROR(E8/$B8,"") -> 5.5512153 | G8: ='2'!$F$100*B8 -> 1387.9903 | H8: =IFERROR(G8/$B8,"") -> 1.2048527 | I8: ='2'!$F$98*'Discipline Analysis'!B8 -> 1572.1803 | J8: =IFERROR(I8/$B8,"") -> 1.3647398 | K8: ='2'!$F$99*'Discipline Analysis'!B8 -> 997.74475 | L8: =IFERROR(K8/$B8,"") -> 0.86609787 | M8: =OFFSET('2'!$E$35,$A$3,0) -> 1013 | N8: =IFERROR(M8/$B8,"") -> 0.87934028 | O8: ='2'!$F$101*'Discipline Analysis'!B8 -> 0 | P8: =IFERROR(O8/$B8,"") -> 0 | Q8: ='2'!$F$102*'Discipline Analysis'!B8 -> 0 | R8: =IFERROR(Q8/$B8,"") -> 0 | S8: ='2'!$F$103*'Discipline Analysis'!B8 -> 185.56074 | T8: =IFERROR(S8/$B8,"") -> 0.16107703 | U8: ='2'!$F$104*'Discipline Analysis'!B8 -> 364.48139 | V8: =IFERROR(U8/$B8,"") -> 0.31639009 | X8: Communications
A9: Amarillo | B9: =OFFSET('3'!$D$4,$A$3,0) -> 13888 | C9: =OFFSET('3'!$E$4,$A$3,0) -> 120773.95 | D9: =IFERROR(C9/$B9,"") -> 8.696281 | E9: =OFFSET('3'!$E$66,$A$3,0) -> 42588 | F9: =IFERROR(E9/$B9,"") -> 3.0665323 | G9: ='3'!$F$100*B9 -> 5744.2271 | H9: =IFERROR(G9/$B9,"") -> 0.41361082 | I9: ='3'!$F$98*'Discipline Analysis'!B9 -> 26815.348 | J9: =IFERROR(I9/$B9,"") -> 1.9308286 | K9: ='3'!$F$99*'Discipline Analysis'!B9 -> 8391.6467 | L9: =IFERROR(K9/$B9,"") -> 0.60423724 | M9: =OFFSET('3'!$E$35,$A$3,0) -> 24761 | N9: =IFERROR(M9/$B9,"") -> 1.7829061 | O9: ='3'!$F$101*'Discipline Analysis'!B9 -> 0 | P9: =IFERROR(O9/$B9,"") -> 0 | Q9: ='3'!$F$102*'Discipline Analysis'!B9 -> 0 | R9: =IFERROR(Q9/$B9,"") -> 0 | S9: ='3'!$F$103*'Discipline Analysis'!B9 -> 4602.2098 | T9: =IFERROR(S9/$B9,"") -> 0.33138031 | U9: ='3'!$F$104*'Discipline Analysis'!B9 -> 7871.518 | V9: =IFERROR(U9/$B9,"") -> 0.56678557 | X9: Computer and Information Sciences
A10: Angelina | B10: =OFFSET('4'!$D$4,$A$3,0) -> 0 | C10: =OFFSET('4'!$E$4,$A$3,0) -> 0 | D10: =IFERROR(C10/$B10,"") | E10: =OFFSET('4'!$E$66,$A$3,0) -> 0 | F10: =IFERROR(E10/$B10,"") | G10: ='4'!$F$100*B10 -> 0 | H10: =IFERROR(G10/$B10,"") | I10: ='4'!$F$98*'Discipline Analysis'!B10 -> 0 | J10: =IFERROR(I10/$B10,"") | K10: ='4'!$F$99*'Discipline Analysis'!B10 -> 0 | L10: =IFERROR(K10/$B10,"") | M10: =OFFSET('4'!$E$35,$A$3,0) -> 0 | N10: =IFERROR(M10/$B10,"") | O10: ='4'!$F$101*'Discipline Analysis'!B10 -> 0 | P10: =IFERROR(O10/$B10,"") | Q10: ='4'!$F$102*'Discipline Analysis'!B10 -> 0 | R10: =IFERROR(Q10/$B10,"") | S10: ='4'!$F$103*'Discipline Analysis'!B10 -> 0 | T10: =IFERROR(S10/$B10,"") | U10: ='4'!$F$104*'Discipline Analysis'!B10 -> 0 | V10: =IFERROR(U10/$B10,"") | X10: Construction Trades
A11: Austin | B11: =OFFSET('5'!$D$4,$A$3,0) -> 67324 | C11: =OFFSET('5'!$E$4,$A$3,0) -> 558695.78 | D11: =IFERROR(C11/$B11,"") -> 8.2986123 | E11: =OFFSET('5'!$E$66,$A$3,0) -> 143811 | F11: =IFERROR(E11/$B11,"") -> 2.136103 | G11: ='5'!$F$100*B11 -> 87780.875 | H11: =IFERROR(G11/$B11,"") -> 1.3038571 | I11: ='5'!$F$98*'Discipline Analysis'!B11 -> 126827.81 | J11: =IFERROR(I11/$B11,"") -> 1.8838425 | K11: ='5'!$F$99*'Discipline Analysis'!B11 -> 87474.898 | L11: =IFERROR(K11/$B11,"") -> 1.2993123 | M11: =OFFSET('5'!$E$35,$A$3,0) -> 71570 | N11: =IFERROR(M11/$B11,"") -> 1.0630681 | O11: ='5'!$F$101*'Discipline Analysis'!B11 -> 0 | P11: =IFERROR(O11/$B11,"") -> 0 | Q11: ='5'!$F$102*'Discipline Analysis'!B11 -> 0 | R11: =IFERROR(Q11/$B11,"") -> 0 | S11: ='5'!$F$103*'Discipline Analysis'!B11 -> 13497.833 | T11: =IFERROR(S11/$B11,"") -> 0.20049066 | U11: ='5'!$F$104*'Discipline Analysis'!B11 -> 27733.357 | V11: =IFERROR(U11/$B11,"") -> 0.41193864 | X11: Consumer and Homemaking Education
A12: Blinn | B12: =OFFSET('6'!$D$4,$A$3,0) -> 76304 | C12: =OFFSET('6'!$E$4,$A$3,0) -> 615144.98 | D12: =IFERROR(C12/$B12,"") -> 8.0617658 | E12: =OFFSET('6'!$E$66,$A$3,0) -> 374165 | F12: =IFERROR(E12/$B12,"") -> 4.9036092 | G12: ='6'!$F$100*B12 -> 32433.937 | H12: =IFERROR(G12/$B12,"") -> 0.42506208 | I12: ='6'!$F$98*'Discipline Analysis'!B12 -> 61085.265 | J12: =IFERROR(I12/$B12,"") -> 0.80055129 | K12: ='6'!$F$99*'Discipline Analysis'!B12 -> 41474.408 | L12: =IFERROR(K12/$B12,"") -> 0.54354173 | M12: =OFFSET('6'!$E$35,$A$3,0) -> 83474 | N12: =IFERROR(M12/$B12,"") -> 1.0939662 | O12: ='6'!$F$101*'Discipline Analysis'!B12 -> 0 | P12: =IFERROR(O12/$B12,"") -> 0 | Q12: ='6'!$F$102*'Discipline Analysis'!B12 -> 5419.106 | R12: =IFERROR(Q12/$B12,"") -> 0.071019947 | S12: ='6'!$F$103*'Discipline Analysis'!B12 -> 9769.6205 | T12: =IFERROR(S12/$B12,"") -> 0.1280355 | U12: ='6'!$F$104*'Discipline Analysis'!B12 -> 7323.6423 | V12: =IFERROR(U12/$B12,"") -> 0.095979795 | X12: Engineering
A13: Brazosport | B13: =OFFSET('7'!$D$4,$A$3,0) -> 10752 | C13: =OFFSET('7'!$E$4,$A$3,0) -> 70052.628 | D13: =IFERROR(C13/$B13,"") -> 6.5153114 | E13: =OFFSET('7'!$E$66,$A$3,0) -> 9870 | F13: =IFERROR(E13/$B13,"") -> 0.91796875 | G13: ='7'!$F$100*B13 -> 8925.984 | H13: =IFERROR(G13/$B13,"") -> 0.83016964 | I13: ='7'!$F$98*'Discipline Analysis'!B13 -> 29173.171 | J13: =IFERROR(I13/$B13,"") -> 2.7132785 | K13: ='7'!$F$99*'Discipline Analysis'!B13 -> 11001.901 | L13: =IFERROR(K13/$B13,"") -> 1.0232423 | M13: =OFFSET('7'!$E$35,$A$3,0) -> 2689 | N13: =IFERROR(M13/$B13,"") -> 0.25009301 | O13: ='7'!$F$101*'Discipline Analysis'!B13 -> 0 | P13: =IFERROR(O13/$B13,"") -> 0 | Q13: ='7'!$F$102*'Discipline Analysis'!B13 -> 617.05092 | R13: =IFERROR(Q13/$B13,"") -> 0.057389409 | S13: ='7'!$F$103*'Discipline Analysis'!B13 -> 2277.8073 | T13: =IFERROR(S13/$B13,"") -> 0.21184963 | U13: ='7'!$F$104*'Discipline Analysis'!B13 -> 5497.7137 | V13: =IFERROR(U13/$B13,"") -> 0.5113201 | X13: Engineering Related
A14: Central Texas | B14: =OFFSET('8'!$D$4,$A$3,0) -> 87104 | C14: =OFFSET('8'!$E$4,$A$3,0) -> 497533.49 | D14: =IFERROR(C14/$B14,"") -> 5.7119477 | E14: =OFFSET('8'!$E$66,$A$3,0) -> 169607 | F14: =IFERROR(E14/$B14,"") -> 1.9471781 | G14: ='8'!$F$100*B14 -> 31775.65 | H14: =IFERROR(G14/$B14,"") -> 0.36480127 | I14: ='8'!$F$98*'Discipline Analysis'!B14 -> 109312.14 | J14: =IFERROR(I14/$B14,"") -> 1.2549612 | K14: ='8'!$F$99*'Discipline Analysis'!B14 -> 57429.276 | L14: =IFERROR(K14/$B14,"") -> 0.65931848 | M14: =OFFSET('8'!$E$35,$A$3,0) -> 96339 | N14: =IFERROR(M14/$B14,"") -> 1.1060227 | O14: ='8'!$F$101*'Discipline Analysis'!B14 -> 0 | P14: =IFERROR(O14/$B14,"") -> 0 | Q14: ='8'!$F$102*'Discipline Analysis'!B14 -> 0 | R14: =IFERROR(Q14/$B14,"") -> 0 | S14: ='8'!$F$103*'Discipline Analysis'!B14 -> 10570.155 | T14: =IFERROR(S14/$B14,"") -> 0.12135097 | U14: ='8'!$F$104*'Discipline Analysis'!B14 -> 22500.273 | V14: =IFERROR(U14/$B14,"") -> 0.25831504 | X14: English Language, Lit, Philosophy, Humanities, & Interdisciplinary
A15: Cisco | B15: =OFFSET('9'!$D$4,$A$3,0) -> 5744 | C15: =OFFSET('9'!$E$4,$A$3,0) -> 68623.131 | D15: =IFERROR(C15/$B15,"") -> 11.946924 | E15: =OFFSET('9'!$E$66,$A$3,0) -> 46000 | F15: =IFERROR(E15/$B15,"") -> 8.0083565 | G15: ='9'!$F$100*B15 -> 2555.5547 | H15: =IFERROR(G15/$B15,"") -> 0.44490856 | I15: ='9'!$F$98*'Discipline Analysis'!B15 -> 6895.4979 | J15: =IFERROR(I15/$B15,"") -> 1.2004697 | K15: ='9'!$F$99*'Discipline Analysis'!B15 -> 3984.1946 | L15: =IFERROR(K15/$B15,"") -> 0.69362719 | M15: =OFFSET('9'!$E$35,$A$3,0) -> 5469 | N15: =IFERROR(M15/$B15,"") -> 0.95212396 | O15: ='9'!$F$101*'Discipline Analysis'!B15 -> 0 | P15: =IFERROR(O15/$B15,"") -> 0 | Q15: ='9'!$F$102*'Discipline Analysis'!B15 -> 0 | R15: =IFERROR(Q15/$B15,"") -> 0 | S15: ='9'!$F$103*'Discipline Analysis'!B15 -> 907.82194 | T15: =IFERROR(S15/$B15,"") -> 0.15804699 | U15: ='9'!$F$104*'Discipline Analysis'!B15 -> 2811.0622 | V15: =IFERROR(U15/$B15,"") -> 0.48939105 | X15: Foreign Languages
A16: Clarendon | B16: =OFFSET('10'!$D$4,$A$3,0) -> 40736 | C16: =OFFSET('10'!$E$4,$A$3,0) -> 350063.54 | D16: =IFERROR(C16/$B16,"") -> 8.5934687 | E16: =OFFSET('10'!$E$66,$A$3,0) -> 173596 | F16: =IFERROR(E16/$B16,"") -> 4.2614886 | G16: ='10'!$F$100*B16 -> 19487.993 | H16: =IFERROR(G16/$B16,"") -> 0.47839732 | I16: ='10'!$F$98*'Discipline Analysis'!B16 -> 51444.779 | J16: =IFERROR(I16/$B16,"") -> 1.2628824 | K16: ='10'!$F$99*'Discipline Analysis'!B16 -> 22151.059 | L16: =IFERROR(K16/$B16,"") -> 0.54377108 | M16: =OFFSET('10'!$E$35,$A$3,0) -> 51982 | N16: =IFERROR(M16/$B16,"") -> 1.2760703 | O16: ='10'!$F$101*'Discipline Analysis'!B16 -> 0 | P16: =IFERROR(O16/$B16,"") -> 0 | Q16: ='10'!$F$102*'Discipline Analysis'!B16 -> 0 | R16: =IFERROR(Q16/$B16,"") -> 0 | S16: ='10'!$F$103*'Discipline Analysis'!B16 -> 26492.829 | T16: =IFERROR(S16/$B16,"") -> 0.6503542 | U16: ='10'!$F$104*'Discipline Analysis'!B16 -> 4908.8813 | V16: =IFERROR(U16/$B16,"") -> 0.12050475 | X16: Health Occupations - Dental Assistants, Medical Lab, and Assoc. Degree Nursing
A17: Coastal Bend | B17: =OFFSET('11'!$D$4,$A$3,0) -> 7956 | C17: =OFFSET('11'!$E$4,$A$3,0) -> 73628.114 | D17: =IFERROR(C17/$B17,"") -> 9.2544136 | E17: =OFFSET('11'!$E$66,$A$3,0) -> 33493 | F17: =IFERROR(E17/$B17,"") -> 4.2097788 | G17: ='11'!$F$100*B17 -> 4050.8161 | H17: =IFERROR(G17/$B17,"") -> 0.50915235 | I17: ='11'!$F$98*'Discipline Analysis'!B17 -> 23078.621 | J17: =IFERROR(I17/$B17,"") -> 2.900782 | K17: ='11'!$F$99*'Discipline Analysis'!B17 -> 3472.8995 | L17: =IFERROR(K17/$B17,"") -> 0.43651326 | M17: =OFFSET('11'!$E$35,$A$3,0) -> 5707 | N17: =IFERROR(M17/$B17,"") -> 0.71732026 | O17: ='11'!$F$101*'Discipline Analysis'!B17 -> 0 | P17: =IFERROR(O17/$B17,"") -> 0 | Q17: ='11'!$F$102*'Discipline Analysis'!B17 -> 911.97126 | R17: =IFERROR(Q17/$B17,"") -> 0.11462686 | S17: ='11'!$F$103*'Discipline Analysis'!B17 -> 2484.6809 | T17: =IFERROR(S17/$B17,"") -> 0.31230278 | U17: ='11'!$F$104*'Discipline Analysis'!B17 -> 429.12536 | V17: =IFERROR(U17/$B17,"") -> 0.053937325 | X17: Health Occupations - Dental Hygiene
A18: College Of The Mainland | B18: =OFFSET('12'!$D$4,$A$3,0) -> 4104 | C18: =OFFSET('12'!$E$4,$A$3,0) -> 113785.3 | D18: =IFERROR(C18/$B18,"") -> 27.725463 | E18: =OFFSET('12'!$E$66,$A$3,0) -> 61078 | F18: =IFERROR(E18/$B18,"") -> 14.882554 | G18: ='12'!$F$100*B18 -> 4446.8924 | H18: =IFERROR(G18/$B18,"") -> 1.0835508 | I18: ='12'!$F$98*'Discipline Analysis'!B18 -> 12450.958 | J18: =IFERROR(I18/$B18,"") -> 3.0338592 | K18: ='12'!$F$99*'Discipline Analysis'!B18 -> 5951.8141 | L18: =IFERROR(K18/$B18,"") -> 1.4502471 | M18: =OFFSET('12'!$E$35,$A$3,0) -> 24571 | N18: =IFERROR(M18/$B18,"") -> 5.9870858 | O18: ='12'!$F$101*'Discipline Analysis'!B18 -> 0 | P18: =IFERROR(O18/$B18,"") -> 0 | Q18: ='12'!$F$102*'Discipline Analysis'!B18 -> 0 | R18: =IFERROR(Q18/$B18,"") -> 0 | S18: ='12'!$F$103*'Discipline Analysis'!B18 -> 612.28162 | T18: =IFERROR(S18/$B18,"") -> 0.14919143 | U18: ='12'!$F$104*'Discipline Analysis'!B18 -> 4674.354 | V18: =IFERROR(U18/$B18,"") -> 1.1389752 | X18: Health Occupations - Other
A19: Collin | B19: =OFFSET('13'!$D$4,$A$3,0) -> 112466 | C19: =OFFSET('13'!$E$4,$A$3,0) -> 711695.45 | D19: =IFERROR(C19/$B19,"") -> 6.3280943 | E19: =OFFSET('13'!$E$66,$A$3,0) -> 261437 | F19: =IFERROR(E19/$B19,"") -> 2.324587 | G19: ='13'!$F$100*B19 -> 79621.093 | H19: =IFERROR(G19/$B19,"") -> 0.70795701 | I19: ='13'!$F$98*'Discipline Analysis'!B19 -> 125227.23 | J19: =IFERROR(I19/$B19,"") -> 1.1134674 | K19: ='13'!$F$99*'Discipline Analysis'!B19 -> 71295.954 | L19: =IFERROR(K19/$B19,"") -> 0.63393341 | M19: =OFFSET('13'!$E$35,$A$3,0) -> 133682 | N19: =IFERROR(M19/$B19,"") -> 1.1886437 | O19: ='13'!$F$101*'Discipline Analysis'!B19 -> 0 | P19: =IFERROR(O19/$B19,"") -> 0 | Q19: ='13'!$F$102*'Discipline Analysis'!B19 -> 0 | R19: =IFERROR(Q19/$B19,"") -> 0 | S19: ='13'!$F$103*'Discipline Analysis'!B19 -> 21984.383 | T19: =IFERROR(S19/$B19,"") -> 0.19547581 | U19: ='13'!$F$104*'Discipline Analysis'!B19 -> 18447.793 | V19: =IFERROR(U19/$B19,"") -> 0.16402996 | X19: Health Occupations - Respiratory Therapy
A20: Dallas | B20: =OFFSET('14'!$D$4,$A$3,0) -> 78312 | C20: =OFFSET('14'!$E$4,$A$3,0) -> 1338590.6 | D20: =IFERROR(C20/$B20,"") -> 17.093046 | E20: =OFFSET('14'!$E$66,$A$3,0) -> 489422 | F20: =IFERROR(E20/$B20,"") -> 6.2496425 | G20: ='14'!$F$100*B20 -> 34466.63 | H20: =IFERROR(G20/$B20,"") -> 0.44011939 | I20: ='14'!$F$98*'Discipline Analysis'!B20 -> 118012.45 | J20: =IFERROR(I20/$B20,"") -> 1.5069524 | K20: ='14'!$F$99*'Discipline Analysis'!B20 -> 67549.881 | L20: =IFERROR(K20/$B20,"") -> 0.86257382 | M20: =OFFSET('14'!$E$35,$A$3,0) -> 595820 | N20: =IFERROR(M20/$B20,"") -> 7.6082848 | O20: ='14'!$F$101*'Discipline Analysis'!B20 -> 0 | P20: =IFERROR(O20/$B20,"") -> 0 | Q20: ='14'!$F$102*'Discipline Analysis'!B20 -> 0 | R20: =IFERROR(Q20/$B20,"") -> 0 | S20: ='14'!$F$103*'Discipline Analysis'!B20 -> 8131.6274 | T20: =IFERROR(S20/$B20,"") -> 0.10383629 | U20: ='14'!$F$104*'Discipline Analysis'!B20 -> 25188 | V20: =IFERROR(U20/$B20,"") -> 0.32163653 | X20: Health Occupations - Vocational Nursing
A21: Del Mar | B21: =OFFSET('15'!$D$4,$A$3,0) -> 272 | C21: =OFFSET('15'!$E$4,$A$3,0) -> 1442.0523 | D21: =IFERROR(C21/$B21,"") -> 5.3016629 | E21: =OFFSET('15'!$E$66,$A$3,0) -> 93 | F21: =IFERROR(E21/$B21,"") -> 0.34191176 | G21: ='15'!$F$100*B21 -> 184.99697 | H21: =IFERROR(G21/$B21,"") -> 0.68013594 | I21: ='15'!$F$98*'Discipline Analysis'!B21 -> 639.88702 | J21: =IFERROR(I21/$B21,"") -> 2.3525258 | K21: ='15'!$F$99*'Discipline Analysis'!B21 -> 178.89976 | L21: =IFERROR(K21/$B21,"") -> 0.6577197 | M21: =OFFSET('15'!$E$35,$A$3,0) -> 165 | N21: =IFERROR(M21/$B21,"") -> 0.60661765 | O21: ='15'!$F$101*'Discipline Analysis'!B21 -> 0 | P21: =IFERROR(O21/$B21,"") -> 0 | Q21: ='15'!$F$102*'Discipline Analysis'!B21 -> 0 | R21: =IFERROR(Q21/$B21,"") -> 0 | S21: ='15'!$F$103*'Discipline Analysis'!B21 -> 0 | T21: =IFERROR(S21/$B21,"") -> 0 | U21: ='15'!$F$104*'Discipline Analysis'!B21 -> 180.26856 | V21: =IFERROR(U21/$B21,"") -> 0.66275206 | X21: Mathematics
A22: El Paso | B22: =OFFSET('16'!$D$4,$A$3,0) -> 6000 | C22: =OFFSET('16'!$E$4,$A$3,0) -> 33814.204 | D22: =IFERROR(C22/$B22,"") -> 5.6357007 | E22: =OFFSET('16'!$E$66,$A$3,0) -> 5692 | F22: =IFERROR(E22/$B22,"") -> 0.94866667 | G22: ='16'!$F$100*B22 -> 6940.0929 | H22: =IFERROR(G22/$B22,"") -> 1.1566822 | I22: ='16'!$F$98*'Discipline Analysis'!B22 -> 8738.8546 | J22: =IFERROR(I22/$B22,"") -> 1.4564758 | K22: ='16'!$F$99*'Discipline Analysis'!B22 -> 3776.8762 | L22: =IFERROR(K22/$B22,"") -> 0.62947936 | M22: =OFFSET('16'!$E$35,$A$3,0) -> 5180 | N22: =IFERROR(M22/$B22,"") -> 0.86333333 | O22: ='16'!$F$101*'Discipline Analysis'!B22 -> 21.791693 | P22: =IFERROR(O22/$B22,"") -> 0.0036319489 | Q22: ='16'!$F$102*'Discipline Analysis'!B22 -> 1009.1271 | R22: =IFERROR(Q22/$B22,"") -> 0.16818786 | S22: ='16'!$F$103*'Discipline Analysis'!B22 -> 541.77614 | T22: =IFERROR(S22/$B22,"") -> 0.090296023 | U22: ='16'!$F$104*'Discipline Analysis'!B22 -> 1913.6857 | V22: =IFERROR(U22/$B22,"") -> 0.31894761 | X22: Mechanics and Repairers - Automotive
A23: Frank Phillips | B23: =OFFSET('17'!$D$4,$A$3,0) -> 12608 | C23: =OFFSET('17'!$E$4,$A$3,0) -> 195990.27 | D23: =IFERROR(C23/$B23,"") -> 15.544913 | E23: =OFFSET('17'!$E$66,$A$3,0) -> 96356 | F23: =IFERROR(E23/$B23,"") -> 7.6424492 | G23: ='17'!$F$100*B23 -> 2834.4228 | H23: =IFERROR(G23/$B23,"") -> 0.22481146 | I23: ='17'!$F$98*'Discipline Analysis'!B23 -> 27777.494 | J23: =IFERROR(I23/$B23,"") -> 2.2031642 | K23: ='17'!$F$99*'Discipline Analysis'!B23 -> 6252.4748 | L23: =IFERROR(K23/$B23,"") -> 0.49591329 | M23: =OFFSET('17'!$E$35,$A$3,0) -> 50221 | N23: =IFERROR(M23/$B23,"") -> 3.9832646 | O23: ='17'!$F$101*'Discipline Analysis'!B23 -> 0 | P23: =IFERROR(O23/$B23,"") -> 0 | Q23: ='17'!$F$102*'Discipline Analysis'!B23 -> 2673.2183 | R23: =IFERROR(Q23/$B23,"") -> 0.21202556 | S23: ='17'!$F$103*'Discipline Analysis'!B23 -> 4673.424 | T23: =IFERROR(S23/$B23,"") -> 0.37067132 | U23: ='17'!$F$104*'Discipline Analysis'!B23 -> 5202.235 | V23: =IFERROR(U23/$B23,"") -> 0.41261382 | X23: Mechanics and Repairers - Diesel, Aviation Mechanics, and Transportation Workers
A24: Galveston | B24: =OFFSET('18'!$D$4,$A$3,0) -> 26208 | C24: =OFFSET('18'!$E$4,$A$3,0) -> 279062.76 | D24: =IFERROR(C24/$B24,"") -> 10.647999 | E24: =OFFSET('18'!$E$66,$A$3,0) -> 83434 | F24: =IFERROR(E24/$B24,"") -> 3.1835317 | G24: ='18'!$F$100*B24 -> 24696.111 | H24: =IFERROR(G24/$B24,"") -> 0.94231192 | I24: ='18'!$F$98*'Discipline Analysis'!B24 -> 73705.458 | J24: =IFERROR(I24/$B24,"") -> 2.8123267 | K24: ='18'!$F$99*'Discipline Analysis'!B24 -> 38549.938 | L24: =IFERROR(K24/$B24,"") -> 1.4709225 | M24: =OFFSET('18'!$E$35,$A$3,0) -> 30594 | N24: =IFERROR(M24/$B24,"") -> 1.1673535 | O24: ='18'!$F$101*'Discipline Analysis'!B24 -> 0 | P24: =IFERROR(O24/$B24,"") -> 0 | Q24: ='18'!$F$102*'Discipline Analysis'!B24 -> 0 | R24: =IFERROR(Q24/$B24,"") -> 0 | S24: ='18'!$F$103*'Discipline Analysis'!B24 -> 8934.5765 | T24: =IFERROR(S24/$B24,"") -> 0.34091028 | U24: ='18'!$F$104*'Discipline Analysis'!B24 -> 19148.675 | V24: =IFERROR(U24/$B24,"") -> 0.73064236 | X24: Mechanics and Repairers - Electronics
A25: Grayson | B25: =OFFSET('19'!$D$4,$A$3,0) -> 12104 | C25: =OFFSET('19'!$E$4,$A$3,0) -> 85948.901 | D25: =IFERROR(C25/$B25,"") -> 7.1008676 | E25: =OFFSET('19'!$E$66,$A$3,0) -> 25852 | F25: =IFERROR(E25/$B25,"") -> 2.1358229 | G25: ='19'!$F$100*B25 -> 5996.3226 | H25: =IFERROR(G25/$B25,"") -> 0.49540009 | I25: ='19'!$F$98*'Discipline Analysis'!B25 -> 16333.539 | J25: =IFERROR(I25/$B25,"") -> 1.3494332 | K25: ='19'!$F$99*'Discipline Analysis'!B25 -> 7389.3976 | L25: =IFERROR(K25/$B25,"") -> 0.6104922 | M25: =OFFSET('19'!$E$35,$A$3,0) -> 24626 | N25: =IFERROR(M25/$B25,"") -> 2.034534 | O25: ='19'!$F$101*'Discipline Analysis'!B25 -> 0 | P25: =IFERROR(O25/$B25,"") -> 0 | Q25: ='19'!$F$102*'Discipline Analysis'!B25 -> 0 | R25: =IFERROR(Q25/$B25,"") -> 0 | S25: ='19'!$F$103*'Discipline Analysis'!B25 -> 2213.0869 | T25: =IFERROR(S25/$B25,"") -> 0.1828393 | U25: ='19'!$F$104*'Discipline Analysis'!B25 -> 3538.555 | V25: =IFERROR(U25/$B25,"") -> 0.29234592 | X25: Physical Education and Fitness
A26: Hill | B26: =OFFSET('20'!$D$4,$A$3,0) -> 15376 | C26: =OFFSET('20'!$E$4,$A$3,0) -> 124800.3 | D26: =IFERROR(C26/$B26,"") -> 8.1165648 | E26: =OFFSET('20'!$E$66,$A$3,0) -> 64690 | F26: =IFERROR(E26/$B26,"") -> 4.207206 | G26: ='20'!$F$100*B26 -> 7537.7194 | H26: =IFERROR(G26/$B26,"") -> 0.49022629 | I26: ='20'!$F$98*'Discipline Analysis'!B26 -> 18862.918 | J26: =IFERROR(I26/$B26,"") -> 1.2267767 | K26: ='20'!$F$99*'Discipline Analysis'!B26 -> 8793.6621 | L26: =IFERROR(K26/$B26,"") -> 0.57190831 | M26: =OFFSET('20'!$E$35,$A$3,0) -> 15460 | N26: =IFERROR(M26/$B26,"") -> 1.0054631 | O26: ='20'!$F$101*'Discipline Analysis'!B26 -> 0 | P26: =IFERROR(O26/$B26,"") -> 0 | Q26: ='20'!$F$102*'Discipline Analysis'!B26 -> 0 | R26: =IFERROR(Q26/$B26,"") -> 0 | S26: ='20'!$F$103*'Discipline Analysis'!B26 -> 2248.6832 | T26: =IFERROR(S26/$B26,"") -> 0.14624631 | U26: ='20'!$F$104*'Discipline Analysis'!B26 -> 7207.3178 | V26: =IFERROR(U26/$B26,"") -> 0.46873815 | X26: Protective Services and Public Administration
A27: Houston | B27: =OFFSET('21'!$D$4,$A$3,0) -> 97632 | C27: =OFFSET('21'!$E$4,$A$3,0) -> 667483.34 | D27: =IFERROR(C27/$B27,"") -> 6.8367271 | E27: =OFFSET('21'!$E$66,$A$3,0) -> 217287 | F27: =IFERROR(E27/$B27,"") -> 2.2255715 | G27: ='21'!$F$100*B27 -> 59491.615 | H27: =IFERROR(G27/$B27,"") -> 0.60934545 | I27: ='21'!$F$98*'Discipline Analysis'!B27 -> 176079.97 | J27: =IFERROR(I27/$B27,"") -> 1.8035068 | K27: ='21'!$F$99*'Discipline Analysis'!B27 -> 94771.021 | L27: =IFERROR(K27/$B27,"") -> 0.97069629 | M27: =OFFSET('21'!$E$35,$A$3,0) -> 87686 | N27: =IFERROR(M27/$B27,"") -> 0.89812766 | O27: ='21'!$F$101*'Discipline Analysis'!B27 -> 0 | P27: =IFERROR(O27/$B27,"") -> 0 | Q27: ='21'!$F$102*'Discipline Analysis'!B27 -> 0 | R27: =IFERROR(Q27/$B27,"") -> 0 | S27: ='21'!$F$103*'Discipline Analysis'!B27 -> 14837.578 | T27: =IFERROR(S27/$B27,"") -> 0.15197454 | U27: ='21'!$F$104*'Discipline Analysis'!B27 -> 17330.151 | V27: =IFERROR(U27/$B27,"") -> 0.17750482 | X27: Psychology, Social Sciences, and History
A28: Howard | B28: =OFFSET('22'!$D$4,$A$3,0) -> 43069 | C28: =OFFSET('22'!$E$4,$A$3,0) -> 391414.76 | D28: =IFERROR(C28/$B28,"") -> 9.0880857 | E28: =OFFSET('22'!$E$66,$A$3,0) -> 151254 | F28: =IFERROR(E28/$B28,"") -> 3.5118995 | G28: ='22'!$F$100*B28 -> 19741.14 | H28: =IFERROR(G28/$B28,"") -> 0.45836078 | I28: ='22'!$F$98*'Discipline Analysis'!B28 -> 77844.819 | J28: =IFERROR(I28/$B28,"") -> 1.8074443 | K28: ='22'!$F$99*'Discipline Analysis'!B28 -> 30675.717 | L28: =IFERROR(K28/$B28,"") -> 0.71224587 | M28: =OFFSET('22'!$E$35,$A$3,0) -> 72442 | N28: =IFERROR(M28/$B28,"") -> 1.6819987 | O28: ='22'!$F$101*'Discipline Analysis'!B28 -> 0 | P28: =IFERROR(O28/$B28,"") -> 0 | Q28: ='22'!$F$102*'Discipline Analysis'!B28 -> 795.11152 | R28: =IFERROR(Q28/$B28,"") -> 0.018461342 | S28: ='22'!$F$103*'Discipline Analysis'!B28 -> 7789.4567 | T28: =IFERROR(S28/$B28,"") -> 0.18085994 | U28: ='22'!$F$104*'Discipline Analysis'!B28 -> 30872.519 | V28: =IFERROR(U28/$B28,"") -> 0.71681532 | X28: Visual and Performing Arts
A29: Kilgore | B29: =OFFSET('23'!$D$4,$A$3,0) -> 18040 | C29: =OFFSET('23'!$E$4,$A$3,0) -> 93243.75 | D29: =IFERROR(C29/$B29,"") -> 5.1687223 | E29: =OFFSET('23'!$E$66,$A$3,0) -> 27822 | F29: =IFERROR(E29/$B29,"") -> 1.5422395 | G29: ='23'!$F$100*B29 -> 13542.499 | H29: =IFERROR(G29/$B29,"") -> 0.75069287 | I29: ='23'!$F$98*'Discipline Analysis'!B29 -> 19321.613 | J29: =IFERROR(I29/$B29,"") -> 1.0710428 | K29: ='23'!$F$99*'Discipline Analysis'!B29 -> 7860.291 | L29: =IFERROR(K29/$B29,"") -> 0.43571458 | M29: =OFFSET('23'!$E$35,$A$3,0) -> 10001 | N29: =IFERROR(M29/$B29,"") -> 0.55437916 | O29: ='23'!$F$101*'Discipline Analysis'!B29 -> 0 | P29: =IFERROR(O29/$B29,"") -> 0 | Q29: ='23'!$F$102*'Discipline Analysis'!B29 -> 1978.3576 | R29: =IFERROR(Q29/$B29,"") -> 0.10966506 | S29: ='23'!$F$103*'Discipline Analysis'!B29 -> 1455.1235 | T29: =IFERROR(S29/$B29,"") -> 0.080660949 | U29: ='23'!$F$104*'Discipline Analysis'!B29 -> 11262.866 | V29: =IFERROR(U29/$B29,"") -> 0.62432737 | X29: Developmental Education - Math
A30: Laredo | B30: =OFFSET('24'!$D$4,$A$3,0) -> 1824 | C30: =OFFSET('24'!$E$4,$A$3,0) -> 9824.095 | D30: =IFERROR(C30/$B30,"") -> 5.386017 | E30: =OFFSET('24'!$E$66,$A$3,0) -> 0 | F30: =IFERROR(E30/$B30,"") -> 0 | G30: ='24'!$F$100*B30 -> 1291.5316 | H30: =IFERROR(G30/$B30,"") -> 0.70807654 | I30: ='24'!$F$98*'Discipline Analysis'!B30 -> 4664.4486 | J30: =IFERROR(I30/$B30,"") -> 2.5572635 | K30: ='24'!$F$99*'Discipline Analysis'!B30 -> 1891.7381 | L30: =IFERROR(K30/$B30,"") -> 1.0371371 | M30: =OFFSET('24'!$E$35,$A$3,0) -> 0 | N30: =IFERROR(M30/$B30,"") -> 0 | O30: ='24'!$F$101*'Discipline Analysis'!B30 -> 0 | P30: =IFERROR(O30/$B30,"") -> 0 | Q30: ='24'!$F$102*'Discipline Analysis'!B30 -> 106.86553 | R30: =IFERROR(Q30/$B30,"") -> 0.058588559 | S30: ='24'!$F$103*'Discipline Analysis'!B30 -> 507.20336 | T30: =IFERROR(S30/$B30,"") -> 0.27807202 | U30: ='24'!$F$104*'Discipline Analysis'!B30 -> 1362.3078 | V30: =IFERROR(U30/$B30,"") -> 0.74687926 | X30: Developmental Education - Reading/Writing
A31: Lee | B31: =OFFSET('25'!$D$4,$A$3,0) -> 51232 | C31: =OFFSET('25'!$E$4,$A$3,0) -> 316283.97 | D31: =IFERROR(C31/$B31,"") -> 6.1735628 | E31: =OFFSET('25'!$E$66,$A$3,0) -> 66062 | F31: =IFERROR(E31/$B31,"") -> 1.2894675 | G31: ='25'!$F$100*B31 -> 44101.788 | H31: =IFERROR(G31/$B31,"") -> 0.86082502 | I31: ='25'!$F$98*'Discipline Analysis'!B31 -> 118168.86 | J31: =IFERROR(I31/$B31,"") -> 2.306544 | K31: ='25'!$F$99*'Discipline Analysis'!B31 -> 37953.503 | L31: =IFERROR(K31/$B31,"") -> 0.74081634 | M31: =OFFSET('25'!$E$35,$A$3,0) -> 24463 | N31: =IFERROR(M31/$B31,"") -> 0.47749453 | O31: ='25'!$F$101*'Discipline Analysis'!B31 -> 0 | P31: =IFERROR(O31/$B31,"") -> 0 | Q31: ='25'!$F$102*'Discipline Analysis'!B31 -> 0 | R31: =IFERROR(Q31/$B31,"") -> 0 | S31: ='25'!$F$103*'Discipline Analysis'!B31 -> 0 | T31: =IFERROR(S31/$B31,"") -> 0 | U31: ='25'!$F$104*'Discipline Analysis'!B31 -> 25534.817 | V31: =IFERROR(U31/$B31,"") -> 0.49841539 | X31: All Disciplines
A32: Lonestar | B32: =OFFSET('26'!$D$4,$A$3,0) -> 80500 | C32: =OFFSET('26'!$E$4,$A$3,0) -> 545223.76 | D32: =IFERROR(C32/$B32,"") -> 6.7729659 | E32: =OFFSET('26'!$E$66,$A$3,0) -> 151133 | F32: =IFERROR(E32/$B32,"") -> 1.8774286 | G32: ='26'!$F$100*B32 -> 125277.33 | H32: =IFERROR(G32/$B32,"") -> 1.5562401 | I32: ='26'!$F$98*'Discipline Analysis'!B32 -> 75709.015 | J32: =IFERROR(I32/$B32,"") -> 0.94048465 | K32: ='26'!$F$99*'Discipline Analysis'!B32 -> 97638.899 | L32: =IFERROR(K32/$B32,"") -> 1.2129056 | M32: =OFFSET('26'!$E$35,$A$3,0) -> 30411 | N32: =IFERROR(M32/$B32,"") -> 0.3777764 | O32: ='26'!$F$101*'Discipline Analysis'!B32 -> 0 | P32: =IFERROR(O32/$B32,"") -> 0 | Q32: ='26'!$F$102*'Discipline Analysis'!B32 -> 0 | R32: =IFERROR(Q32/$B32,"") -> 0 | S32: ='26'!$F$103*'Discipline Analysis'!B32 -> 31538.586 | T32: =IFERROR(S32/$B32,"") -> 0.39178368 | U32: ='26'!$F$104*'Discipline Analysis'!B32 -> 33515.926 | V32: =IFERROR(U32/$B32,"") -> 0.4163469
A33: Mclennan | B33: =OFFSET('27'!$D$4,$A$3,0) -> 52640 | C33: =OFFSET('27'!$E$4,$A$3,0) -> 569084.08 | D33: =IFERROR(C33/$B33,"") -> 10.810868 | E33: =OFFSET('27'!$E$66,$A$3,0) -> 137135 | F33: =IFERROR(E33/$B33,"") -> 2.6051482 | G33: ='27'!$F$100*B33 -> 22566.397 | H33: =IFERROR(G33/$B33,"") -> 0.42869294 | I33: ='27'!$F$98*'Discipline Analysis'!B33 -> 79207.942 | J33: =IFERROR(I33/$B33,"") -> 1.5047101 | K33: ='27'!$F$99*'Discipline Analysis'!B33 -> 27526.785 | L33: =IFERROR(K33/$B33,"") -> 0.52292525 | M33: =OFFSET('27'!$E$35,$A$3,0) -> 273145 | N33: =IFERROR(M33/$B33,"") -> 5.1889248 | O33: ='27'!$F$101*'Discipline Analysis'!B33 -> 0 | P33: =IFERROR(O33/$B33,"") -> 0 | Q33: ='27'!$F$102*'Discipline Analysis'!B33 -> 18875.723 | R33: =IFERROR(Q33/$B33,"") -> 0.35858137 | S33: ='27'!$F$103*'Discipline Analysis'!B33 -> 0 | T33: =IFERROR(S33/$B33,"") -> 0 | U33: ='27'!$F$104*'Discipline Analysis'!B33 -> 10627.232 | V33: =IFERROR(U33/$B33,"") -> 0.20188512
A34: Midland | B34: =OFFSET('28'!$D$4,$A$3,0) -> 4416 | C34: =OFFSET('28'!$E$4,$A$3,0) -> 41934.9 | D34: =IFERROR(C34/$B34,"") -> 9.4961276 | E34: =OFFSET('28'!$E$66,$A$3,0) -> 16737 | F34: =IFERROR(E34/$B34,"") -> 3.7900815 | G34: ='28'!$F$100*B34 -> 7282.3505 | H34: =IFERROR(G34/$B34,"") -> 1.649083 | I34: ='28'!$F$98*'Discipline Analysis'!B34 -> 6648.3643 | J34: =IFERROR(I34/$B34,"") -> 1.5055173 | K34: ='28'!$F$99*'Discipline Analysis'!B34 -> 3506.3106 | L34: =IFERROR(K34/$B34,"") -> 0.79400149 | M34: =OFFSET('28'!$E$35,$A$3,0) -> 3649 | N34: =IFERROR(M34/$B34,"") -> 0.82631341 | O34: ='28'!$F$101*'Discipline Analysis'!B34 -> 0 | P34: =IFERROR(O34/$B34,"") -> 0 | Q34: ='28'!$F$102*'Discipline Analysis'!B34 -> 25.791937 | R34: =IFERROR(Q34/$B34,"") -> 0.0058405653 | S34: ='28'!$F$103*'Discipline Analysis'!B34 -> 1058.8482 | T34: =IFERROR(S34/$B34,"") -> 0.23977541 | U34: ='28'!$F$104*'Discipline Analysis'!B34 -> 3027.234 | V34: =IFERROR(U34/$B34,"") -> 0.68551496
A35: Navarro | B35: =OFFSET('29'!$D$4,$A$3,0) -> 17408 | C35: =OFFSET('29'!$E$4,$A$3,0) -> 184701.31 | D35: =IFERROR(C35/$B35,"") -> 10.61014 | E35: =OFFSET('29'!$E$66,$A$3,0) -> 115959 | F35: =IFERROR(E35/$B35,"") -> 6.6612477 | G35: ='29'!$F$100*B35 -> 8928.7471 | H35: =IFERROR(G35/$B35,"") -> 0.51291056 | I35: ='29'!$F$98*'Discipline Analysis'!B35 -> 13876.727 | J35: =IFERROR(I35/$B35,"") -> 0.79714652 | K35: ='29'!$F$99*'Discipline Analysis'!B35 -> 8622.9258 | L35: =IFERROR(K35/$B35,"") -> 0.49534271 | M35: =OFFSET('29'!$E$35,$A$3,0) -> 32351 | N35: =IFERROR(M35/$B35,"") -> 1.8583984 | O35: ='29'!$F$101*'Discipline Analysis'!B35 -> 0 | P35: =IFERROR(O35/$B35,"") -> 0 | Q35: ='29'!$F$102*'Discipline Analysis'!B35 -> 0 | R35: =IFERROR(Q35/$B35,"") -> 0 | S35: ='29'!$F$103*'Discipline Analysis'!B35 -> 653.20131 | T35: =IFERROR(S35/$B35,"") -> 0.037523053 | U35: ='29'!$F$104*'Discipline Analysis'!B35 -> 4309.7098 | V35: =IFERROR(U35/$B35,"") -> 0.24757065
A36: North Central Texas | B36: =OFFSET('30'!$D$4,$A$3,0) -> 89952 | C36: =OFFSET('30'!$E$4,$A$3,0) -> 731318.21 | D36: =IFERROR(C36/$B36,"") -> 8.1300939 | E36: =OFFSET('30'!$E$66,$A$3,0) -> 238984 | F36: =IFERROR(E36/$B36,"") -> 2.6567947 | G36: ='30'!$F$100*B36 -> 52406.447 | H36: =IFERROR(G36/$B36,"") -> 0.58260457 | I36: ='30'!$F$98*'Discipline Analysis'!B36 -> 101169.9 | J36: =IFERROR(I36/$B36,"") -> 1.1247098 | K36: ='30'!$F$99*'Discipline Analysis'!B36 -> 40843.648 | L36: =IFERROR(K36/$B36,"") -> 0.45406048 | M36: =OFFSET('30'!$E$35,$A$3,0) -> 269259 | N36: =IFERROR(M36/$B36,"") -> 2.9933631 | O36: ='30'!$F$101*'Discipline Analysis'!B36 -> 2630.5965 | P36: =IFERROR(O36/$B36,"") -> 0.029244447 | Q36: ='30'!$F$102*'Discipline Analysis'!B36 -> 0 | R36: =IFERROR(Q36/$B36,"") -> 0 | S36: ='30'!$F$103*'Discipline Analysis'!B36 -> 9953.1232 | T36: =IFERROR(S36/$B36,"") -> 0.11064927 | U36: ='30'!$F$104*'Discipline Analysis'!B36 -> 16071.496 | V36: =IFERROR(U36/$B36,"") -> 0.17866746
A37: Northeast Texas | B37: =OFFSET('31'!$D$4,$A$3,0) -> 21312 | C37: =OFFSET('31'!$E$4,$A$3,0) -> 360440.6 | D37: =IFERROR(C37/$B37,"") -> 16.912566 | E37: =OFFSET('31'!$E$66,$A$3,0) -> 182335 | F37: =IFERROR(E37/$B37,"") -> 8.5555086 | G37: ='31'!$F$100*B37 -> 9683.227 | H37: =IFERROR(G37/$B37,"") -> 0.45435562 | I37: ='31'!$F$98*'Discipline Analysis'!B37 -> 35547.861 | J37: =IFERROR(I37/$B37,"") -> 1.667974 | K37: ='31'!$F$99*'Discipline Analysis'!B37 -> 11539.725 | L37: =IFERROR(K37/$B37,"") -> 0.54146608 | M37: =OFFSET('31'!$E$35,$A$3,0) -> 115698 | N37: =IFERROR(M37/$B37,"") -> 5.4287725 | O37: ='31'!$F$101*'Discipline Analysis'!B37 -> 0 | P37: =IFERROR(O37/$B37,"") -> 0 | Q37: ='31'!$F$102*'Discipline Analysis'!B37 -> 0 | R37: =IFERROR(Q37/$B37,"") -> 0 | S37: ='31'!$F$103*'Discipline Analysis'!B37 -> 0 | T37: =IFERROR(S37/$B37,"") -> 0 | U37: ='31'!$F$104*'Discipline Analysis'!B37 -> 5636.783 | V37: =IFERROR(U37/$B37,"") -> 0.26448869
A38: Odessa | B38: =OFFSET('32'!$D$4,$A$3,0) -> 20336 | C38: =OFFSET('32'!$E$4,$A$3,0) -> 191598.26 | D38: =IFERROR(C38/$B38,"") -> 9.4216299 | E38: =OFFSET('32'!$E$66,$A$3,0) -> 65521 | F38: =IFERROR(E38/$B38,"") -> 3.2219217 | G38: ='32'!$F$100*B38 -> 22056.864 | H38: =IFERROR(G38/$B38,"") -> 1.0846216 | I38: ='32'!$F$98*'Discipline Analysis'!B38 -> 39162.801 | J38: =IFERROR(I38/$B38,"") -> 1.9257868 | K38: ='32'!$F$99*'Discipline Analysis'!B38 -> 18703.658 | L38: =IFERROR(K38/$B38,"") -> 0.91973143 | M38: =OFFSET('32'!$E$35,$A$3,0) -> 18211 | N38: =IFERROR(M38/$B38,"") -> 0.89550551 | O38: ='32'!$F$101*'Discipline Analysis'!B38 -> 0 | P38: =IFERROR(O38/$B38,"") -> 0 | Q38: ='32'!$F$102*'Discipline Analysis'!B38 -> 5589.5891 | R38: =IFERROR(Q38/$B38,"") -> 0.27486178 | S38: ='32'!$F$103*'Discipline Analysis'!B38 -> 6462.8215 | T38: =IFERROR(S38/$B38,"") -> 0.317802 | U38: ='32'!$F$104*'Discipline Analysis'!B38 -> 15890.531 | V38: =IFERROR(U38/$B38,"") -> 0.78139904
A39: Panola | B39: =OFFSET('33'!$D$4,$A$3,0) -> 5760 | C39: =OFFSET('33'!$E$4,$A$3,0) -> 112390.24 | D39: =IFERROR(C39/$B39,"") -> 19.512195 | E39: =OFFSET('33'!$E$66,$A$3,0) -> 41932 | F39: =IFERROR(E39/$B39,"") -> 7.2798611 | G39: ='33'!$F$100*B39 -> 7824.6518 | H39: =IFERROR(G39/$B39,"") -> 1.3584465 | I39: ='33'!$F$98*'Discipline Analysis'!B39 -> 7921.3092 | J39: =IFERROR(I39/$B39,"") -> 1.3752273 | K39: ='33'!$F$99*'Discipline Analysis'!B39 -> 4040.099 | L39: =IFERROR(K39/$B39,"") -> 0.70140607 | M39: =OFFSET('33'!$E$35,$A$3,0) -> 47490 | N39: =IFERROR(M39/$B39,"") -> 8.2447917 | O39: ='33'!$F$101*'Discipline Analysis'!B39 -> 0 | P39: =IFERROR(O39/$B39,"") -> 0 | Q39: ='33'!$F$102*'Discipline Analysis'!B39 -> 0 | R39: =IFERROR(Q39/$B39,"") -> 0 | S39: ='33'!$F$103*'Discipline Analysis'!B39 -> 0 | T39: =IFERROR(S39/$B39,"") -> 0 | U39: ='33'!$F$104*'Discipline Analysis'!B39 -> 3182.1846 | V39: =IFERROR(U39/$B39,"") -> 0.55246261
A40: Paris | B40: =OFFSET('34'!$D$4,$A$3,0) -> 0 | C40: =OFFSET('34'!$E$4,$A$3,0) -> 0 | D40: =IFERROR(C40/$B40,"") | E40: =OFFSET('34'!$E$66,$A$3,0) -> 0 | F40: =IFERROR(E40/$B40,"") | G40: ='34'!$F$100*B40 -> 0 | H40: =IFERROR(G40/$B40,"") | I40: ='34'!$F$98*'Discipline Analysis'!B40 -> 0 | J40: =IFERROR(I40/$B40,"") | K40: ='34'!$F$99*'Discipline Analysis'!B40 -> 0 | L40: =IFERROR(K40/$B40,"") | M40: =OFFSET('34'!$E$35,$A$3,0) -> 0 | N40: =IFERROR(M40/$B40,"") | O40: ='34'!$F$101*'Discipline Analysis'!B40 -> 0 | P40: =IFERROR(O40/$B40,"") | Q40: ='34'!$F$102*'Discipline Analysis'!B40 -> 0 | R40: =IFERROR(Q40/$B40,"") | S40: ='34'!$F$103*'Discipline Analysis'!B40 -> 0 | T40: =IFERROR(S40/$B40,"") | U40: ='34'!$F$104*'Discipline Analysis'!B40 -> 0 | V40: =IFERROR(U40/$B40,"")
A41: Ranger | B41: =OFFSET('35'!$D$4,$A$3,0) -> 4176 | C41: =OFFSET('35'!$E$4,$A$3,0) -> 22985.65 | D41: =IFERROR(C41/$B41,"") -> 5.5042266 | E41: =OFFSET('35'!$E$66,$A$3,0) -> 11250 | F41: =IFERROR(E41/$B41,"") -> 2.6939655 | G41: ='35'!$F$100*B41 -> 1975.5636 | H41: =IFERROR(G41/$B41,"") -> 0.47307557 | I41: ='35'!$F$98*'Discipline Analysis'!B41 -> 4033.8419 | J41: =IFERROR(I41/$B41,"") -> 0.9659583 | K41: ='35'!$F$99*'Discipline Analysis'!B41 -> 1448.2581 | L41: =IFERROR(K41/$B41,"") -> 0.34680511 | M41: =OFFSET('35'!$E$35,$A$3,0) -> 3511 | N41: =IFERROR(M41/$B41,"") -> 0.8407567 | O41: ='35'!$F$101*'Discipline Analysis'!B41 -> 0 | P41: =IFERROR(O41/$B41,"") -> 0 | Q41: ='35'!$F$102*'Discipline Analysis'!B41 -> 0 | R41: =IFERROR(Q41/$B41,"") -> 0 | S41: ='35'!$F$103*'Discipline Analysis'!B41 -> 0 | T41: =IFERROR(S41/$B41,"") -> 0 | U41: ='35'!$F$104*'Discipline Analysis'!B41 -> 766.9868 | V41: =IFERROR(U41/$B41,"") -> 0.18366542
A42: San Jacinto | B42: =OFFSET('36'!$D$4,$A$3,0) -> 17136 | C42: =OFFSET('36'!$E$4,$A$3,0) -> 78742.509 | D42: =IFERROR(C42/$B42,"") -> 4.5951511 | E42: =OFFSET('36'!$E$66,$A$3,0) -> 7296 | F42: =IFERROR(E42/$B42,"") -> 0.42577031 | G42: ='36'!$F$100*B42 -> 11506.743 | H42: =IFERROR(G42/$B42,"") -> 0.6714953 | I42: ='36'!$F$98*'Discipline Analysis'!B42 -> 36617.016 | J42: =IFERROR(I42/$B42,"") -> 2.1368473 | K42: ='36'!$F$99*'Discipline Analysis'!B42 -> 13067.977 | L42: =IFERROR(K42/$B42,"") -> 0.7626037 | M42: =OFFSET('36'!$E$35,$A$3,0) -> 821 | N42: =IFERROR(M42/$B42,"") -> 0.047910831 | O42: ='36'!$F$101*'Discipline Analysis'!B42 -> 0 | P42: =IFERROR(O42/$B42,"") -> 0 | Q42: ='36'!$F$102*'Discipline Analysis'!B42 -> 0 | R42: =IFERROR(Q42/$B42,"") -> 0 | S42: ='36'!$F$103*'Discipline Analysis'!B42 -> 4282.1711 | T42: =IFERROR(S42/$B42,"") -> 0.24989327 | U42: ='36'!$F$104*'Discipline Analysis'!B42 -> 5151.6019 | V42: =IFERROR(U42/$B42,"") -> 0.30063036
A43: South Plains | B43: =OFFSET('37'!$D$4,$A$3,0) -> 35608 | C43: =OFFSET('37'!$E$4,$A$3,0) -> 460497.48 | D43: =IFERROR(C43/$B43,"") -> 12.932416 | E43: =OFFSET('37'!$E$66,$A$3,0) -> 256783 | F43: =IFERROR(E43/$B43,"") -> 7.2113851 | G43: ='37'!$F$100*B43 -> 13995.705 | H43: =IFERROR(G43/$B43,"") -> 0.39304945 | I43: ='37'!$F$98*'Discipline Analysis'!B43 -> 28709.746 | J43: =IFERROR(I43/$B43,"") -> 0.80627236 | K43: ='37'!$F$99*'Discipline Analysis'!B43 -> 31879.316 | L43: =IFERROR(K43/$B43,"") -> 0.89528522 | M43: =OFFSET('37'!$E$35,$A$3,0) -> 101788 | N43: =IFERROR(M43/$B43,"") -> 2.8585711 | O43: ='37'!$F$101*'Discipline Analysis'!B43 -> 0 | P43: =IFERROR(O43/$B43,"") -> 0 | Q43: ='37'!$F$102*'Discipline Analysis'!B43 -> 747.30094 | R43: =IFERROR(Q43/$B43,"") -> 0.020986883 | S43: ='37'!$F$103*'Discipline Analysis'!B43 -> 7745.8371 | T43: =IFERROR(S43/$B43,"") -> 0.21753081 | U43: ='37'!$F$104*'Discipline Analysis'!B43 -> 18848.578 | V43: =IFERROR(U43/$B43,"") -> 0.52933548
A44: South Texas | B44: =OFFSET('38'!$D$4,$A$3,0) -> 8160 | C44: =OFFSET('38'!$E$4,$A$3,0) -> 65344.024 | D44: =IFERROR(C44/$B44,"") -> 8.0078461 | E44: =OFFSET('38'!$E$66,$A$3,0) -> 23186 | F44: =IFERROR(E44/$B44,"") -> 2.8414216 | G44: ='38'!$F$100*B44 -> 5353.8445 | H44: =IFERROR(G44/$B44,"") -> 0.65610839 | I44: ='38'!$F$98*'Discipline Analysis'!B44 -> 11622.496 | J44: =IFERROR(I44/$B44,"") -> 1.4243255 | K44: ='38'!$F$99*'Discipline Analysis'!B44 -> 5211.3914 | L44: =IFERROR(K44/$B44,"") -> 0.63865091 | M44: =OFFSET('38'!$E$35,$A$3,0) -> 15835 | N44: =IFERROR(M44/$B44,"") -> 1.9405637 | O44: ='38'!$F$101*'Discipline Analysis'!B44 -> 0 | P44: =IFERROR(O44/$B44,"") -> 0 | Q44: ='38'!$F$102*'Discipline Analysis'!B44 -> 0 | R44: =IFERROR(Q44/$B44,"") -> 0 | S44: ='38'!$F$103*'Discipline Analysis'!B44 -> 1620.0177 | T44: =IFERROR(S44/$B44,"") -> 0.19853158 | U44: ='38'!$F$104*'Discipline Analysis'!B44 -> 2515.2749 | V44: =IFERROR(U44/$B44,"") -> 0.30824447
A45: Southwest Texas | B45: =OFFSET('39'!$D$4,$A$3,0) -> 23520 | C45: =OFFSET('39'!$E$4,$A$3,0) -> 226076.07 | D45: =IFERROR(C45/$B45,"") -> 9.612078 | E45: =OFFSET('39'!$E$66,$A$3,0) -> 107542 | F45: =IFERROR(E45/$B45,"") -> 4.5723639 | G45: ='39'!$F$100*B45 -> 22757.367 | H45: =IFERROR(G45/$B45,"") -> 0.96757512 | I45: ='39'!$F$98*'Discipline Analysis'!B45 -> 39545.212 | J45: =IFERROR(I45/$B45,"") -> 1.681344 | K45: ='39'!$F$99*'Discipline Analysis'!B45 -> 16014.239 | L45: =IFERROR(K45/$B45,"") -> 0.6808775 | M45: =OFFSET('39'!$E$35,$A$3,0) -> 28418 | N45: =IFERROR(M45/$B45,"") -> 1.2082483 | O45: ='39'!$F$101*'Discipline Analysis'!B45 -> 0 | P45: =IFERROR(O45/$B45,"") -> 0 | Q45: ='39'!$F$102*'Discipline Analysis'!B45 -> 0 | R45: =IFERROR(Q45/$B45,"") -> 0 | S45: ='39'!$F$103*'Discipline Analysis'!B45 -> 3331.6147 | T45: =IFERROR(S45/$B45,"") -> 0.14165028 | U45: ='39'!$F$104*'Discipline Analysis'!B45 -> 8467.6418 | V45: =IFERROR(U45/$B45,"") -> 0.36001878
A46: Tarrant | B46: =OFFSET('40'!$D$4,$A$3,0) -> 30584 | C46: =OFFSET('40'!$E$4,$A$3,0) -> 292869.25 | D46: =IFERROR(C46/$B46,"") -> 9.5758977 | E46: =OFFSET('40'!$E$66,$A$3,0) -> 95632 | F46: =IFERROR(E46/$B46,"") -> 3.1268637 | G46: ='40'!$F$100*B46 -> 27569.251 | H46: =IFERROR(G46/$B46,"") -> 0.90142725 | I46: ='40'!$F$98*'Discipline Analysis'!B46 -> 39161.154 | J46: =IFERROR(I46/$B46,"") -> 1.2804458 | K46: ='40'!$F$99*'Discipline Analysis'!B46 -> 30060.218 | L46: =IFERROR(K46/$B46,"") -> 0.982874 | M46: =OFFSET('40'!$E$35,$A$3,0) -> 77400 | N46: =IFERROR(M46/$B46,"") -> 2.530735 | O46: ='40'!$F$101*'Discipline Analysis'!B46 -> 0 | P46: =IFERROR(O46/$B46,"") -> 0 | Q46: ='40'!$F$102*'Discipline Analysis'!B46 -> 2129.643 | R46: =IFERROR(Q46/$B46,"") -> 0.069632585 | S46: ='40'!$F$103*'Discipline Analysis'!B46 -> 3451.1601 | T46: =IFERROR(S46/$B46,"") -> 0.11284201 | U46: ='40'!$F$104*'Discipline Analysis'!B46 -> 17465.828 | V46: =IFERROR(U46/$B46,"") -> 0.57107728
A47: Temple | B47: =OFFSET('41'!$D$4,$A$3,0) -> 12416 | C47: =OFFSET('41'!$E$4,$A$3,0) -> 102094.53 | D47: =IFERROR(C47/$B47,"") -> 8.22282 | E47: =OFFSET('41'!$E$66,$A$3,0) -> 43097 | F47: =IFERROR(E47/$B47,"") -> 3.4710857 | G47: ='41'!$F$100*B47 -> 9453.5759 | H47: =IFERROR(G47/$B47,"") -> 0.76140269 | I47: ='41'!$F$98*'Discipline Analysis'!B47 -> 20347.822 | J47: =IFERROR(I47/$B47,"") -> 1.6388387 | K47: ='41'!$F$99*'Discipline Analysis'!B47 -> 6784.8435 | L47: =IFERROR(K47/$B47,"") -> 0.54645969 | M47: =OFFSET('41'!$E$35,$A$3,0) -> 15469 | N47: =IFERROR(M47/$B47,"") -> 1.2458924 | O47: ='41'!$F$101*'Discipline Analysis'!B47 -> 0 | P47: =IFERROR(O47/$B47,"") -> 0 | Q47: ='41'!$F$102*'Discipline Analysis'!B47 -> 0 | R47: =IFERROR(Q47/$B47,"") -> 0 | S47: ='41'!$F$103*'Discipline Analysis'!B47 -> 1476.4008 | T47: =IFERROR(S47/$B47,"") -> 0.11891114 | U47: ='41'!$F$104*'Discipline Analysis'!B47 -> 5465.8913 | V47: =IFERROR(U47/$B47,"") -> 0.44022965
A48: Texarkana | B48: =OFFSET('42'!$D$4,$A$3,0) -> 880 | C48: =OFFSET('42'!$E$4,$A$3,0) -> 6569.1657 | D48: =IFERROR(C48/$B48,"") -> 7.464961 | E48: =OFFSET('42'!$E$66,$A$3,0) -> 2376 | F48: =IFERROR(E48/$B48,"") -> 2.7 | G48: ='42'!$F$100*B48 -> 550.90585 | H48: =IFERROR(G48/$B48,"") -> 0.62602938 | I48: ='42'!$F$98*'Discipline Analysis'!B48 -> 1402.5974 | J48: =IFERROR(I48/$B48,"") -> 1.5938607 | K48: ='42'!$F$99*'Discipline Analysis'!B48 -> 591.40547 | L48: =IFERROR(K48/$B48,"") -> 0.67205167 | M48: =OFFSET('42'!$E$35,$A$3,0) -> 1156 | N48: =IFERROR(M48/$B48,"") -> 1.3136364 | O48: ='42'!$F$101*'Discipline Analysis'!B48 -> 0 | P48: =IFERROR(O48/$B48,"") -> 0 | Q48: ='42'!$F$102*'Discipline Analysis'!B48 -> 0 | R48: =IFERROR(Q48/$B48,"") -> 0 | S48: ='42'!$F$103*'Discipline Analysis'!B48 -> 216.32994 | T48: =IFERROR(S48/$B48,"") -> 0.24582948 | U48: ='42'!$F$104*'Discipline Analysis'!B48 -> 275.927 | V48: =IFERROR(U48/$B48,"") -> 0.31355341
A49: Texas Southmost | B49: =OFFSET('43'!$D$4,$A$3,0) -> 19632 | C49: =OFFSET('43'!$E$4,$A$3,0) -> 247419.63 | D49: =IFERROR(C49/$B49,"") -> 12.602875 | E49: =OFFSET('43'!$E$66,$A$3,0) -> 30872 | F49: =IFERROR(E49/$B49,"") -> 1.5725346 | G49: ='43'!$F$100*B49 -> 27427.939 | H49: =IFERROR(G49/$B49,"") -> 1.3971037 | I49: ='43'!$F$98*'Discipline Analysis'!B49 -> 40252.024 | J49: =IFERROR(I49/$B49,"") -> 2.0503272 | K49: ='43'!$F$99*'Discipline Analysis'!B49 -> 40287.395 | L49: =IFERROR(K49/$B49,"") -> 2.0521289 | M49: =OFFSET('43'!$E$35,$A$3,0) -> 82860 | N49: =IFERROR(M49/$B49,"") -> 4.2206601 | O49: ='43'!$F$101*'Discipline Analysis'!B49 -> 0 | P49: =IFERROR(O49/$B49,"") -> 0 | Q49: ='43'!$F$102*'Discipline Analysis'!B49 -> 12861.979 | R49: =IFERROR(Q49/$B49,"") -> 0.6551538 | S49: ='43'!$F$103*'Discipline Analysis'!B49 -> 0 | T49: =IFERROR(S49/$B49,"") -> 0 | U49: ='43'!$F$104*'Discipline Analysis'!B49 -> 12858.295 | V49: =IFERROR(U49/$B49,"") -> 0.65496614
A50: Trinity Valley | B50: =OFFSET('44'!$D$4,$A$3,0) -> 60832 | C50: =OFFSET('44'!$E$4,$A$3,0) -> 475345.26 | D50: =IFERROR(C50/$B50,"") -> 7.8140659 | E50: =OFFSET('44'!$E$66,$A$3,0) -> 227129 | F50: =IFERROR(E50/$B50,"") -> 3.7337092 | G50: ='44'!$F$100*B50 -> 60360.61 | H50: =IFERROR(G50/$B50,"") -> 0.99225095 | I50: ='44'!$F$98*'Discipline Analysis'!B50 -> 47961.351 | J50: =IFERROR(I50/$B50,"") -> 0.78842305 | K50: ='44'!$F$99*'Discipline Analysis'!B50 -> 35437.849 | L50: =IFERROR(K50/$B50,"") -> 0.58255276 | M50: =OFFSET('44'!$E$35,$A$3,0) -> 69931 | N50: =IFERROR(M50/$B50,"") -> 1.1495759 | O50: ='44'!$F$101*'Discipline Analysis'!B50 -> 0 | P50: =IFERROR(O50/$B50,"") -> 0 | Q50: ='44'!$F$102*'Discipline Analysis'!B50 -> 21.309075 | R50: =IFERROR(Q50/$B50,"") -> 0.00035029384 | S50: ='44'!$F$103*'Discipline Analysis'!B50 -> 9966.4939 | T50: =IFERROR(S50/$B50,"") -> 0.16383637 | U50: ='44'!$F$104*'Discipline Analysis'!B50 -> 24537.642 | V50: =IFERROR(U50/$B50,"") -> 0.40336735
A51: Tyler | B51: =OFFSET('45'!$D$4,$A$3,0) -> 37040 | C51: =OFFSET('45'!$E$4,$A$3,0) -> 232778.09 | D51: =IFERROR(C51/$B51,"") -> 6.2845056 | E51: =OFFSET('45'!$E$66,$A$3,0) -> 51829 | F51: =IFERROR(E51/$B51,"") -> 1.3992711 | G51: ='45'!$F$100*B51 -> 14099.69 | H51: =IFERROR(G51/$B51,"") -> 0.38066118 | I51: ='45'!$F$98*'Discipline Analysis'!B51 -> 47607.393 | J51: =IFERROR(I51/$B51,"") -> 1.2852968 | K51: ='45'!$F$99*'Discipline Analysis'!B51 -> 42360.884 | L51: =IFERROR(K51/$B51,"") -> 1.1436524 | M51: =OFFSET('45'!$E$35,$A$3,0) -> 37189 | N51: =IFERROR(M51/$B51,"") -> 1.0040227 | O51: ='45'!$F$101*'Discipline Analysis'!B51 -> 0 | P51: =IFERROR(O51/$B51,"") -> 0 | Q51: ='45'!$F$102*'Discipline Analysis'!B51 -> 8699.7574 | R51: =IFERROR(Q51/$B51,"") -> 0.23487466 | S51: ='45'!$F$103*'Discipline Analysis'!B51 -> 6434.3859 | T51: =IFERROR(S51/$B51,"") -> 0.17371452 | U51: ='45'!$F$104*'Discipline Analysis'!B51 -> 24557.976 | V51: =IFERROR(U51/$B51,"") -> 0.66301232
A52: Vernon | B52: =OFFSET('46'!$D$4,$A$3,0) -> 9952 | C52: =OFFSET('46'!$E$4,$A$3,0) -> 96300.968 | D52: =IFERROR(C52/$B52,"") -> 9.6765442 | E52: =OFFSET('46'!$E$66,$A$3,0) -> 45531 | F52: =IFERROR(E52/$B52,"") -> 4.5750603 | G52: ='46'!$F$100*B52 -> 13720.713 | H52: =IFERROR(G52/$B52,"") -> 1.378689 | I52: ='46'!$F$98*'Discipline Analysis'!B52 -> 15146.557 | J52: =IFERROR(I52/$B52,"") -> 1.5219611 | K52: ='46'!$F$99*'Discipline Analysis'!B52 -> 8009.2296 | L52: =IFERROR(K52/$B52,"") -> 0.80478593 | M52: =OFFSET('46'!$E$35,$A$3,0) -> 9746 | N52: =IFERROR(M52/$B52,"") -> 0.97930064 | O52: ='46'!$F$101*'Discipline Analysis'!B52 -> 0 | P52: =IFERROR(O52/$B52,"") -> 0 | Q52: ='46'!$F$102*'Discipline Analysis'!B52 -> 0 | R52: =IFERROR(Q52/$B52,"") -> 0 | S52: ='46'!$F$103*'Discipline Analysis'!B52 -> 484.27691 | T52: =IFERROR(S52/$B52,"") -> 0.048661265 | U52: ='46'!$F$104*'Discipline Analysis'!B52 -> 3663.1919 | V52: =IFERROR(U52/$B52,"") -> 0.36808601
A53: Victoria | B53: =OFFSET('47'!$D$4,$A$3,0) -> 10944 | C53: =OFFSET('47'!$E$4,$A$3,0) -> 97464.933 | D53: =IFERROR(C53/$B53,"") -> 8.905787 | E53: =OFFSET('47'!$E$66,$A$3,0) -> 33805 | F53: =IFERROR(E53/$B53,"") -> 3.0889072 | G53: ='47'!$F$100*B53 -> 11784.534 | H53: =IFERROR(G53/$B53,"") -> 1.0768032 | I53: ='47'!$F$98*'Discipline Analysis'!B53 -> 24496.949 | J53: =IFERROR(I53/$B53,"") -> 2.2383908 | K53: ='47'!$F$99*'Discipline Analysis'!B53 -> 8937.0656 | L53: =IFERROR(K53/$B53,"") -> 0.81661783 | M53: =OFFSET('47'!$E$35,$A$3,0) -> 5581 | N53: =IFERROR(M53/$B53,"") -> 0.5099598 | O53: ='47'!$F$101*'Discipline Analysis'!B53 -> 0 | P53: =IFERROR(O53/$B53,"") -> 0 | Q53: ='47'!$F$102*'Discipline Analysis'!B53 -> 2692.6106 | R53: =IFERROR(Q53/$B53,"") -> 0.24603533 | S53: ='47'!$F$103*'Discipline Analysis'!B53 -> 3982.8351 | T53: =IFERROR(S53/$B53,"") -> 0.36392865 | U53: ='47'!$F$104*'Discipline Analysis'!B53 -> 6184.9379 | V53: =IFERROR(U53/$B53,"") -> 0.56514418
A54: Weatherford | B54: =OFFSET('48'!$D$4,$A$3,0) -> 31072 | C54: =OFFSET('48'!$E$4,$A$3,0) -> 350685.46 | D54: =IFERROR(C54/$B54,"") -> 11.286221 | E54: =OFFSET('48'!$E$66,$A$3,0) -> 113207 | F54: =IFERROR(E54/$B54,"") -> 3.6433767 | G54: ='48'!$F$100*B54 -> 19349.992 | H54: =IFERROR(G54/$B54,"") -> 0.6227469 | I54: ='48'!$F$98*'Discipline Analysis'!B54 -> 74367.888 | J54: =IFERROR(I54/$B54,"") -> 2.3934052 | K54: ='48'!$F$99*'Discipline Analysis'!B54 -> 22122.002 | L54: =IFERROR(K54/$B54,"") -> 0.71195937 | M54: =OFFSET('48'!$E$35,$A$3,0) -> 105192 | N54: =IFERROR(M54/$B54,"") -> 3.3854274 | O54: ='48'!$F$101*'Discipline Analysis'!B54 -> 0 | P54: =IFERROR(O54/$B54,"") -> 0 | Q54: ='48'!$F$102*'Discipline Analysis'!B54 -> 0 | R54: =IFERROR(Q54/$B54,"") -> 0 | S54: ='48'!$F$103*'Discipline Analysis'!B54 -> 7119.3427 | T54: =IFERROR(S54/$B54,"") -> 0.22912406 | U54: ='48'!$F$104*'Discipline Analysis'!B54 -> 9327.2367 | V54: =IFERROR(U54/$B54,"") -> 0.30018141
A55: Western Texas | B55: =OFFSET('49'!$D$4,$A$3,0) -> 64736 | C55: =OFFSET('49'!$E$4,$A$3,0) -> 492843.84 | D55: =IFERROR(C55/$B55,"") -> 7.613134 | E55: =OFFSET('49'!$E$66,$A$3,0) -> 218074 | F55: =IFERROR(E55/$B55,"") -> 3.3686666 | G55: ='49'!$F$100*B55 -> 30533.101 | H55: =IFERROR(G55/$B55,"") -> 0.47165567 | I55: ='49'!$F$98*'Discipline Analysis'!B55 -> 135438.68 | J55: =IFERROR(I55/$B55,"") -> 2.0921695 | K55: ='49'!$F$99*'Discipline Analysis'!B55 -> 30447.132 | L55: =IFERROR(K55/$B55,"") -> 0.47032767 | M55: =OFFSET('49'!$E$35,$A$3,0) -> 37949 | N55: =IFERROR(M55/$B55,"") -> 0.58621169 | O55: ='49'!$F$101*'Discipline Analysis'!B55 -> 0 | P55: =IFERROR(O55/$B55,"") -> 0 | Q55: ='49'!$F$102*'Discipline Analysis'!B55 -> 20205.63 | R55: =IFERROR(Q55/$B55,"") -> 0.31212356 | S55: ='49'!$F$103*'Discipline Analysis'!B55 -> 1263.4485 | T55: =IFERROR(S55/$B55,"") -> 0.019516939 | U55: ='49'!$F$104*'Discipline Analysis'!B55 -> 18932.848 | V55: =IFERROR(U55/$B55,"") -> 0.29246243
A56: Wharton | B56: =OFFSET('50'!$D$4,$A$3,0) -> 4400 | C56: =OFFSET('50'!$E$4,$A$3,0) -> 50538.167 | D56: =IFERROR(C56/$B56,"") -> 11.485947 | E56: =OFFSET('50'!$E$66,$A$3,0) -> 25343 | F56: =IFERROR(E56/$B56,"") -> 5.7597727 | G56: ='50'!$F$100*B56 -> 3156.0147 | H56: =IFERROR(G56/$B56,"") -> 0.71727607 | I56: ='50'!$F$98*'Discipline Analysis'!B56 -> 8219.0383 | J56: =IFERROR(I56/$B56,"") -> 1.8679632 | K56: ='50'!$F$99*'Discipline Analysis'!B56 -> 2709.8809 | L56: =IFERROR(K56/$B56,"") -> 0.61588203 | M56: =OFFSET('50'!$E$35,$A$3,0) -> 7400 | N56: =IFERROR(M56/$B56,"") -> 1.6818182 | O56: ='50'!$F$101*'Discipline Analysis'!B56 -> 0 | P56: =IFERROR(O56/$B56,"") -> 0 | Q56: ='50'!$F$102*'Discipline Analysis'!B56 -> 1071.4767 | R56: =IFERROR(Q56/$B56,"") -> 0.24351742 | S56: ='50'!$F$103*'Discipline Analysis'!B56 -> 1016.823 | T56: =IFERROR(S56/$B56,"") -> 0.23109614 | U56: ='50'!$F$104*'Discipline Analysis'!B56 -> 1621.9331 | V56: =IFERROR(U56/$B56,"") -> 0.36862115
A57: TSTC-Harlingen | B57: =OFFSET('51'!$D$4,$A$3,0) -> 28592 | C57: =OFFSET('51'!$E$4,$A$3,0) -> 317897.8 | D57: =IFERROR(C57/$B57,"") -> 11.118418 | E57: =OFFSET('51'!$E$66,$A$3,0) -> 86768 | F57: =IFERROR(E57/$B57,"") -> 3.034695 | G57: ='51'!$F$100*B57 -> 18726.907 | H57: =IFERROR(G57/$B57,"") -> 0.65497016 | I57: ='51'!$F$98*'Discipline Analysis'!B57 -> 30100.804 | J57: =IFERROR(I57/$B57,"") -> 1.0527701 | K57: ='51'!$F$99*'Discipline Analysis'!B57 -> 33484.981 | L57: =IFERROR(K57/$B57,"") -> 1.1711311 | M57: =OFFSET('51'!$E$35,$A$3,0) -> 115580 | N57: =IFERROR(M57/$B57,"") -> 4.0423895 | O57: ='51'!$F$101*'Discipline Analysis'!B57 -> 2027.2713 | P57: =IFERROR(O57/$B57,"") -> 0.070903444 | Q57: ='51'!$F$102*'Discipline Analysis'!B57 -> 15670.575 | R57: =IFERROR(Q57/$B57,"") -> 0.54807551 | S57: ='51'!$F$103*'Discipline Analysis'!B57 -> 12565.816 | T57: =IFERROR(S57/$B57,"") -> 0.43948713 | U57: ='51'!$F$104*'Discipline Analysis'!B57 -> 2973.4467 | V57: =IFERROR(U57/$B57,"") -> 0.10399576
A58: TSTC-West Texas | B58: =OFFSET('52'!$D$4,$A$3,0) -> 7248 | C58: =OFFSET('52'!$E$4,$A$3,0) -> 133163.08 | D58: =IFERROR(C58/$B58,"") -> 18.37239 | E58: =OFFSET('52'!$E$66,$A$3,0) -> 39558 | F58: =IFERROR(E58/$B58,"") -> 5.4577815 | G58: ='52'!$F$100*B58 -> 13741.89 | H58: =IFERROR(G58/$B58,"") -> 1.8959562 | I58: ='52'!$F$98*'Discipline Analysis'!B58 -> 17180.617 | J58: =IFERROR(I58/$B58,"") -> 2.3703942 | K58: ='52'!$F$99*'Discipline Analysis'!B58 -> 24389.74 | L58: =IFERROR(K58/$B58,"") -> 3.3650304 | M58: =OFFSET('52'!$E$35,$A$3,0) -> 22874 | N58: =IFERROR(M58/$B58,"") -> 3.1559051 | O58: ='52'!$F$101*'Discipline Analysis'!B58 -> 0 | P58: =IFERROR(O58/$B58,"") -> 0 | Q58: ='52'!$F$102*'Discipline Analysis'!B58 -> 6936.7347 | R58: =IFERROR(Q58/$B58,"") -> 0.957055 | S58: ='52'!$F$103*'Discipline Analysis'!B58 -> 7292.1314 | T58: =IFERROR(S58/$B58,"") -> 1.0060888 | U58: ='52'!$F$104*'Discipline Analysis'!B58 -> 1189.9676 | V58: =IFERROR(U58/$B58,"") -> 0.16417875
A59: TSTC-Marshall | B59: =OFFSET('53'!$D$4,$A$3,0) -> 0 | C59: =OFFSET('53'!$E$4,$A$3,0) -> 0 | D59: =IFERROR(C59/$B59,"") | E59: =OFFSET('53'!$E$66,$A$3,0) -> 0 | F59: =IFERROR(E59/$B59,"") | G59: ='53'!$F$100*B59 -> 0 | H59: =IFERROR(G59/$B59,"") | I59: ='53'!$F$98*'Discipline Analysis'!B59 -> 0 | J59: =IFERROR(I59/$B59,"") | K59: ='53'!$F$99*'Discipline Analysis'!B59 -> 0 | L59: =IFERROR(K59/$B59,"") | M59: =OFFSET('53'!$E$35,$A$3,0) -> 0 | N59: =IFERROR(M59/$B59,"") | O59: ='53'!$F$101*'Discipline Analysis'!B59 -> 0 | P59: =IFERROR(O59/$B59,"") | Q59: ='53'!$F$102*'Discipline Analysis'!B59 -> 0 | R59: =IFERROR(Q59/$B59,"") | S59: ='53'!$F$103*'Discipline Analysis'!B59 -> 0 | T59: =IFERROR(S59/$B59,"") | U59: ='53'!$F$104*'Discipline Analysis'!B59 -> 0 | V59: =IFERROR(U59/$B59,"")
A60: TSTC-Waco | B60: =OFFSET('54'!$D$4,$A$3,0) -> 43328 | C60: =OFFSET('54'!$E$4,$A$3,0) -> 587073.51 | D60: =IFERROR(C60/$B60,"") -> 13.549518 | E60: =OFFSET('54'!$E$66,$A$3,0) -> 221409 | F60: =IFERROR(E60/$B60,"") -> 5.1100674 | G60: ='54'!$F$100*B60 -> 50810.338 | H60: =IFERROR(G60/$B60,"") -> 1.1726906 | I60: ='54'!$F$98*'Discipline Analysis'!B60 -> 52894.912 | J60: =IFERROR(I60/$B60,"") -> 1.2208021 | K60: ='54'!$F$99*'Discipline Analysis'!B60 -> 59570.133 | L60: =IFERROR(K60/$B60,"") -> 1.3748646 | M60: =OFFSET('54'!$E$35,$A$3,0) -> 154095 | N60: =IFERROR(M60/$B60,"") -> 3.5564762 | O60: ='54'!$F$101*'Discipline Analysis'!B60 -> 0 | P60: =IFERROR(O60/$B60,"") -> 0 | Q60: ='54'!$F$102*'Discipline Analysis'!B60 -> 32365.972 | R60: =IFERROR(Q60/$B60,"") -> 0.74699899 | S60: ='54'!$F$103*'Discipline Analysis'!B60 -> 12007.349 | T60: =IFERROR(S60/$B60,"") -> 0.27712678 | U60: ='54'!$F$104*'Discipline Analysis'!B60 -> 3920.8029 | V60: =IFERROR(U60/$B60,"") -> 0.090491204
A61: Lamar-IOT | B61: =OFFSET('55'!$D$4,$A$3,0) -> 0 | C61: =OFFSET('55'!$E$4,$A$3,0) -> 0 | D61: =IFERROR(C61/$B61,"") | E61: =OFFSET('55'!$E$66,$A$3,0) -> 0 | F61: =IFERROR(E61/$B61,"") | G61: ='55'!$F$100*B61 -> 0 | H61: =IFERROR(G61/$B61,"") | I61: ='55'!$F$98*'Discipline Analysis'!B61 -> 0 | J61: =IFERROR(I61/$B61,"") | K61: ='55'!$F$99*'Discipline Analysis'!B61 -> 0 | L61: =IFERROR(K61/$B61,"") | M61: =OFFSET('55'!$E$35,$A$3,0) -> 0 | N61: =IFERROR(M61/$B61,"") | O61: ='55'!$F$101*'Discipline Analysis'!B61 -> 0 | P61: =IFERROR(O61/$B61,"") | Q61: ='55'!$F$102*'Discipline Analysis'!B61 -> 0 | R61: =IFERROR(Q61/$B61,"") | S61: ='55'!$F$103*'Discipline Analysis'!B61 -> 0 | T61: =IFERROR(S61/$B61,"") | U61: ='55'!$F$104*'Discipline Analysis'!B61 -> 0 | V61: =IFERROR(U61/$B61,"")
A62: Lamar-Orange | B62: =OFFSET('56'!$D$4,$A$3,0) -> 1040 | C62: =OFFSET('56'!$E$4,$A$3,0) -> 11585.061 | D62: =IFERROR(C62/$B62,"") -> 11.139481 | E62: =OFFSET('56'!$E$66,$A$3,0) -> 3229 | F62: =IFERROR(E62/$B62,"") -> 3.1048077 | G62: ='56'!$F$100*B62 -> 1897.9222 | H62: =IFERROR(G62/$B62,"") -> 1.8249252 | I62: ='56'!$F$98*'Discipline Analysis'!B62 -> 1952.2149 | J62: =IFERROR(I62/$B62,"") -> 1.8771297 | K62: ='56'!$F$99*'Discipline Analysis'!B62 -> 1080.665 | L62: =IFERROR(K62/$B62,"") -> 1.039101 | M62: =OFFSET('56'!$E$35,$A$3,0) -> 1995 | N62: =IFERROR(M62/$B62,"") -> 1.9182692 | O62: ='56'!$F$101*'Discipline Analysis'!B62 -> 0 | P62: =IFERROR(O62/$B62,"") -> 0 | Q62: ='56'!$F$102*'Discipline Analysis'!B62 -> 395.75906 | R62: =IFERROR(Q62/$B62,"") -> 0.38053756 | S62: ='56'!$F$103*'Discipline Analysis'!B62 -> 0 | T62: =IFERROR(S62/$B62,"") -> 0 | U62: ='56'!$F$104*'Discipline Analysis'!B62 -> 1034.4995 | V62: =IFERROR(U62/$B62,"") -> 0.99471109
A63: Lamar-Port Arthur | B63: =OFFSET('57'!$D$4,$A$3,0) -> 0 | C63: =OFFSET('57'!$E$4,$A$3,0) -> 0 | D63: =IFERROR(C63/$B63,"") | E63: =OFFSET('57'!$E$66,$A$3,0) -> 0 | F63: =IFERROR(E63/$B63,"") | G63: ='57'!$F$100*B63 -> 0 | H63: =IFERROR(G63/$B63,"") | I63: ='57'!$F$98*'Discipline Analysis'!B63 -> 0 | J63: =IFERROR(I63/$B63,"") | K63: ='57'!$F$99*'Discipline Analysis'!B63 -> 0 | L63: =IFERROR(K63/$B63,"") | M63: =OFFSET('57'!$E$35,$A$3,0) -> 0 | N63: =IFERROR(M63/$B63,"") | O63: ='57'!$F$101*'Discipline Analysis'!B63 -> 0 | P63: =IFERROR(O63/$B63,"") | Q63: ='57'!$F$102*'Discipline Analysis'!B63 -> 0 | R63: =IFERROR(Q63/$B63,"") | S63: ='57'!$F$103*'Discipline Analysis'!B63 -> 0 | T63: =IFERROR(S63/$B63,"") | U63: ='57'!$F$104*'Discipline Analysis'!B63 -> 0 | V63: =IFERROR(U63/$B63,"")
A64: Total | B64: =OFFSET(Summary!$D$4,$A$3,0) -> 1622682 | C64: =OFFSET(Summary!$E$4,$A$3,0) -> 14698531 | D64: =IFERROR(C64/$B64,"") -> 9.058171 | E64: =OFFSET(Summary!$E$66,$A$3,0) -> 5259237 | F64: =IFERROR(E64/$B64,"") -> 3.2410768 | G64: =Summary!$F$100*B64 -> 1297635.6 | H64: =IFERROR(G64/$B64,"") -> 0.7996857 | I64: =Summary!$F$98*'Discipline Analysis'!B64 -> 2510641.6 | J64: =IFERROR(I64/$B64,"") -> 1.5472173 | K64: =Summary!$F$99*'Discipline Analysis'!B64 -> 1411934.1 | L64: =IFERROR(K64/$B64,"") -> 0.87012373 | M64: =OFFSET(Summary!$E$35,$A$3,0) -> 3193312 | N64: =IFERROR(M64/$B64,"") -> 1.9679222 | O64: =Summary!$F$101*'Discipline Analysis'!B64 -> 2885.5977 | P64: =IFERROR(O64/$B64,"") -> 0.0017782891 | Q64: =Summary!$F$102*'Discipline Analysis'!B64 -> 113838.04 | R64: =IFERROR(Q64/$B64,"") -> 0.07015425 | S64: =Summary!$F$103*'Discipline Analysis'!B64 -> 298090.2 | T64: =IFERROR(S64/$B64,"") -> 0.18370216 | U64: =Summary!$F$104*'Discipline Analysis'!B64 -> 610956.9 | V64: =IFERROR(U64/$B64,"") -> 0.37651056

Sheet Neutral
A1: =Summary!A1 -> Community and Technical Colleges, Report of Fundable Operating Expenses, Fiscal Year (FY) 2012
A2: Percent of Rates to Maintain Funding Total
A3: This calculation is completed to indicate the relative change in financing assuming the legislature were to fund the institutions at the same total as the previous biennium. The percent funded used against the current rates is adjusted so that the total funded for all institutions is equal to the previous biennium's percent funded.
A4: Institution | B4: ="FY 2012 - 2013 Rates @ "&TEXT(B5,"0.00%")&" (Using FY 2012 CH)" -> FY 2012 - 2013 Rates @ 35.86% (Using FY 2012 CH) | C4: ="Annual Budget Neutral Percent Funded "&TEXT(C5,"0.00%")&" (Using FY 2012 CH)" -> Annual Budget Neutral Percent Funded 34.29% (Using FY 2012 CH) | D4: Difference | E4: Percent Change
A5: Percent of Rates Funded | B5: 0.35862939 | C5: 0.34286102 | D5: =C5-B5 -> -0.015768365
A6: Alamo Community College District | B6: =$B$5*('Rate History'!$D$4*SUMIF(Data!$G:$G,Neutral!$A6,Data!$CU:$CU)+'Rate History'!$D$5*SUMIF(Data!$G:$G,Neutral!$A6,Data!$CV:$CV)+'Rate History'!$D$6*SUMIF(Data!$G:$G,Neutral!$A6,Data!$CW:$CW)+'Rate History'!$D$7*SUMIF(Data!$G:$G,Neutral!$A6,Data!$CX:$CX)+'Rate History'!$D$8*SUMIF(Data!$G:$G,Neutral!$A6,Data!$CY:$CY)+'Rate History'!$D$9*SUMIF(Data!$G:$G,Neutral!$A6,Data!$CZ:$CZ)+'Rate History'!$D$10*SUMIF(Data!$G:$G,Neutral!$A6,Data!$DA:$DA)+'Rate History'!$D$11*SUMIF(Data!$G:$G,Neutral!$A6,Data!$DB:$DB)+'Rate History'!$D$12*SUMIF(Data!$G:$G,Neutral!$A6,Data!$DC:$DC)+'Rate History'!$D$13*SUMIF(Data!$G:$G,Neutral!$A6,Data!$DD:$DD)+'Rate History'!$D$14*SUMIF(Data!$G:$G,Neutral!$A6,Data!$DE:$DE)+'Rate History'!$D$15*SUMIF(Data!$G:$G,Neutral!$A6,Data!$DF:$DF)+'Rate History'!$D$16*SUMIF(Data!$G:$G,Neutral!$A6,Data!$DG:$DG)+'Rate History'!$D$17*SUMIF(Data!$G:$G,Neutral!$A6,Data!$DH:$DH)+'Rate History'!$D$18*SUMIF(Data!$G:$G,Neutral!$A6,Data!$DI:$DI)+'Rate History'!$D$19*SUMIF(Data!$G:$G,Neutral!$A6,Data!$DJ:$DJ)+'Rate History'!$D$20*SUMIF(Data!$G:$G,Neutral!$A6,Data!$DK:$DK)+'Rate History'!$D$21*SUMIF(Data!$G:$G,Neutral!$A6,Data!$DL:$DL)+'Rate History'!$D$22*SUMIF(Data!$G:$G,Neutral!$A6,Data!$DM:$DM)+'Rate History'!$D$23*SUMIF(Data!$G:$G,Neutral!$A6,Data!$DN:$DN)+'Rate History'!$D$24*SUMIF(Data!$G:$G,Neutral!$A6,Data!$DO:$DO)+'Rate History'!$D$25*SUMIF(Data!$G:$G,Neutral!$A6,Data!$DP:$DP)+'Rate History'!$D$26*SUMIF(Data!$G:$G,Neutral!$A6,Data!$DQ:$DQ)+'Rate History'!$D$27*SUMIF(Data!$G:$G,Neutral!$A6,Data!$DR:$DR)+'Rate History'!$D$28*SUMIF(Data!$G:$G,Neutral!$A6,Data!$DS:$DS)+'Rate History'!$D$29*SUMIF(Data!$G:$G,Neutral!$A6,Data!$DT:$DT)+'Rate History'!$D$30*SUMIF(Data!$G:$G,Neutral!$A6,Data!$DV:$DV)+'Rate History'!$D$31*SUMIF(Data!$G:$G,Neutral!$A6,Data!$DW:$DW)) -> 66889939 | C6: =$C$5*('Rate History'!$C$4*SUMIF(Data!$G:$G,Neutral!$A6,Data!$CU:$CU)+'Rate History'!$C$5*SUMIF(Data!$G:$G,Neutral!$A6,Data!$CV:$CV)+'Rate History'!$C$6*SUMIF(Data!$G:$G,Neutral!$A6,Data!$CW:$CW)+'Rate History'!$C$7*SUMIF(Data!$G:$G,Neutral!$A6,Data!$CX:$CX)+'Rate History'!$C$8*SUMIF(Data!$G:$G,Neutral!$A6,Data!$CY:$CY)+'Rate History'!$C$9*SUMIF(Data!$G:$G,Neutral!$A6,Data!$CZ:$CZ)+'Rate History'!$C$10*SUMIF(Data!$G:$G,Neutral!$A6,Data!$DA:$DA)+'Rate History'!$C$11*SUMIF(Data!$G:$G,Neutral!$A6,Data!$DB:$DB)+'Rate History'!$C$12*SUMIF(Data!$G:$G,Neutral!$A6,Data!$DC:$DC)+'Rate History'!$C$13*SUMIF(Data!$G:$G,Neutral!$A6,Data!$DD:$DD)+'Rate History'!$C$14*SUMIF(Data!$G:$G,Neutral!$A6,Data!$DE:$DE)+'Rate History'!$C$15*SUMIF(Data!$G:$G,Neutral!$A6,Data!$DF:$DF)+'Rate History'!$C$16*SUMIF(Data!$G:$G,Neutral!$A6,Data!$DG:$DG)+'Rate History'!$C$17*SUMIF(Data!$G:$G,Neutral!$A6,Data!$DH:$DH)+'Rate History'!$C$18*SUMIF(Data!$G:$G,Neutral!$A6,Data!$DI:$DI)+'Rate History'!$C$19*SUMIF(Data!$G:$G,Neutral!$A6,Data!$DJ:$DJ)+'Rate History'!$C$20*SUMIF(Data!$G:$G,Neutral!$A6,Data!$DK:$DK)+'Rate History'!$C$21*SUMIF(Data!$G:$G,Neutral!$A6,Data!$DL:$DL)+'Rate History'!$C$22*SUMIF(Data!$G:$G,Neutral!$A6,Data!$DM:$DM)+'Rate History'!$C$23*SUMIF(Data!$G:$G,Neutral!$A6,Data!$DN:$DN)+'Rate History'!$C$24*SUMIF(Data!$G:$G,Neutral!$A6,Data!$DO:$DO)+'Rate History'!$C$25*SUMIF(Data!$G:$G,Neutral!$A6,Data!$DP:$DP)+'Rate History'!$C$26*SUMIF(Data!$G:$G,Neutral!$A6,Data!$DQ:$DQ)+'Rate History'!$C$27*SUMIF(Data!$G:$G,Neutral!$A6,Data!$DR:$DR)+'Rate History'!$C$28*SUMIF(Data!$G:$G,Neutral!$A6,Data!$DS:$DS)+'Rate History'!$C$29*SUMIF(Data!$G:$G,Neutral!$A6,Data!$DT:$DT)+'Rate History'!$C$30*SUMIF(Data!$G:$G,Neutral!$A6,Data!$DV:$DV)+'Rate History'!$C$31*SUMIF(Data!$G:$G,Neutral!$A6,Data!$DW:$DW)) -> 66890056 | D6: =C6-B6 -> 117.47431 | E6: =IFERROR(D6/B6,"") -> 1.756233e-06
A7: Alvin Community College | B7: =$B$5*('Rate History'!$D$4*SUMIF(Data!$G:$G,Neutral!$A7,Data!$CU:$CU)+'Rate History'!$D$5*SUMIF(Data!$G:$G,Neutral!$A7,Data!$CV:$CV)+'Rate History'!$D$6*SUMIF(Data!$G:$G,Neutral!$A7,Data!$CW:$CW)+'Rate History'!$D$7*SUMIF(Data!$G:$G,Neutral!$A7,Data!$CX:$CX)+'Rate History'!$D$8*SUMIF(Data!$G:$G,Neutral!$A7,Data!$CY:$CY)+'Rate History'!$D$9*SUMIF(Data!$G:$G,Neutral!$A7,Data!$CZ:$CZ)+'Rate History'!$D$10*SUMIF(Data!$G:$G,Neutral!$A7,Data!$DA:$DA)+'Rate History'!$D$11*SUMIF(Data!$G:$G,Neutral!$A7,Data!$DB:$DB)+'Rate History'!$D$12*SUMIF(Data!$G:$G,Neutral!$A7,Data!$DC:$DC)+'Rate History'!$D$13*SUMIF(Data!$G:$G,Neutral!$A7,Data!$DD:$DD)+'Rate History'!$D$14*SUMIF(Data!$G:$G,Neutral!$A7,Data!$DE:$DE)+'Rate History'!$D$15*SUMIF(Data!$G:$G,Neutral!$A7,Data!$DF:$DF)+'Rate History'!$D$16*SUMIF(Data!$G:$G,Neutral!$A7,Data!$DG:$DG)+'Rate History'!$D$17*SUMIF(Data!$G:$G,Neutral!$A7,Data!$DH:$DH)+'Rate History'!$D$18*SUMIF(Data!$G:$G,Neutral!$A7,Data!$DI:$DI)+'Rate History'!$D$19*SUMIF(Data!$G:$G,Neutral!$A7,Data!$DJ:$DJ)+'Rate History'!$D$20*SUMIF(Data!$G:$G,Neutral!$A7,Data!$DK:$DK)+'Rate History'!$D$21*SUMIF(Data!$G:$G,Neutral!$A7,Data!$DL:$DL)+'Rate History'!$D$22*SUMIF(Data!$G:$G,Neutral!$A7,Data!$DM:$DM)+'Rate History'!$D$23*SUMIF(Data!$G:$G,Neutral!$A7,Data!$DN:$DN)+'Rate History'!$D$24*SUMIF(Data!$G:$G,Neutral!$A7,Data!$DO:$DO)+'Rate History'!$D$25*SUMIF(Data!$G:$G,Neutral!$A7,Data!$DP:$DP)+'Rate History'!$D$26*SUMIF(Data!$G:$G,Neutral!$A7,Data!$DQ:$DQ)+'Rate History'!$D$27*SUMIF(Data!$G:$G,Neutral!$A7,Data!$DR:$DR)+'Rate History'!$D$28*SUMIF(Data!$G:$G,Neutral!$A7,Data!$DS:$DS)+'Rate History'!$D$29*SUMIF(Data!$G:$G,Neutral!$A7,Data!$DT:$DT)+'Rate History'!$D$30*SUMIF(Data!$G:$G,Neutral!$A7,Data!$DV:$DV)+'Rate History'!$D$31*SUMIF(Data!$G:$G,Neutral!$A7,Data!$DW:$DW)) -> 7017591.7 | C7: =$C$5*('Rate History'!$C$4*SUMIF(Data!$G:$G,Neutral!$A7,Data!$CU:$CU)+'Rate History'!$C$5*SUMIF(Data!$G:$G,Neutral!$A7,Data!$CV:$CV)+'Rate History'!$C$6*SUMIF(Data!$G:$G,Neutral!$A7,Data!$CW:$CW)+'Rate History'!$C$7*SUMIF(Data!$G:$G,Neutral!$A7,Data!$CX:$CX)+'Rate History'!$C$8*SUMIF(Data!$G:$G,Neutral!$A7,Data!$CY:$CY)+'Rate History'!$C$9*SUMIF(Data!$G:$G,Neutral!$A7,Data!$CZ:$CZ)+'Rate History'!$C$10*SUMIF(Data!$G:$G,Neutral!$A7,Data!$DA:$DA)+'Rate History'!$C$11*SUMIF(Data!$G:$G,Neutral!$A7,Data!$DB:$DB)+'Rate History'!$C$12*SUMIF(Data!$G:$G,Neutral!$A7,Data!$DC:$DC)+'Rate History'!$C$13*SUMIF(Data!$G:$G,Neutral!$A7,Data!$DD:$DD)+'Rate History'!$C$14*SUMIF(Data!$G:$G,Neutral!$A7,Data!$DE:$DE)+'Rate History'!$C$15*SUMIF(Data!$G:$G,Neutral!$A7,Data!$DF:$DF)+'Rate History'!$C$16*SUMIF(Data!$G:$G,Neutral!$A7,Data!$DG:$DG)+'Rate History'!$C$17*SUMIF(Data!$G:$G,Neutral!$A7,Data!$DH:$DH)+'Rate History'!$C$18*SUMIF(Data!$G:$G,Neutral!$A7,Data!$DI:$DI)+'Rate History'!$C$19*SUMIF(Data!$G:$G,Neutral!$A7,Data!$DJ:$DJ)+'Rate History'!$C$20*SUMIF(Data!$G:$G,Neutral!$A7,Data!$DK:$DK)+'Rate History'!$C$21*SUMIF(Data!$G:$G,Neutral!$A7,Data!$DL:$DL)+'Rate History'!$C$22*SUMIF(Data!$G:$G,Neutral!$A7,Data!$DM:$DM)+'Rate History'!$C$23*SUMIF(Data!$G:$G,Neutral!$A7,Data!$DN:$DN)+'Rate History'!$C$24*SUMIF(Data!$G:$G,Neutral!$A7,Data!$DO:$DO)+'Rate History'!$C$25*SUMIF(Data!$G:$G,Neutral!$A7,Data!$DP:$DP)+'Rate History'!$C$26*SUMIF(Data!$G:$G,Neutral!$A7,Data!$DQ:$DQ)+'Rate History'!$C$27*SUMIF(Data!$G:$G,Neutral!$A7,Data!$DR:$DR)+'Rate History'!$C$28*SUMIF(Data!$G:$G,Neutral!$A7,Data!$DS:$DS)+'Rate History'!$C$29*SUMIF(Data!$G:$G,Neutral!$A7,Data!$DT:$DT)+'Rate History'!$C$30*SUMIF(Data!$G:$G,Neutral!$A7,Data!$DV:$DV)+'Rate History'!$C$31*SUMIF(Data!$G:$G,Neutral!$A7,Data!$DW:$DW)) -> 7024015.6 | D7: =C7-B7 -> 6423.958 | E7: =IFERROR(D7/B7,"") -> 0.00091540778
A8: Amarillo College | B8: =$B$5*('Rate History'!$D$4*SUMIF(Data!$G:$G,Neutral!$A8,Data!$CU:$CU)+'Rate History'!$D$5*SUMIF(Data!$G:$G,Neutral!$A8,Data!$CV:$CV)+'Rate History'!$D$6*SUMIF(Data!$G:$G,Neutral!$A8,Data!$CW:$CW)+'Rate History'!$D$7*SUMIF(Data!$G:$G,Neutral!$A8,Data!$CX:$CX)+'Rate History'!$D$8*SUMIF(Data!$G:$G,Neutral!$A8,Data!$CY:$CY)+'Rate History'!$D$9*SUMIF(Data!$G:$G,Neutral!$A8,Data!$CZ:$CZ)+'Rate History'!$D$10*SUMIF(Data!$G:$G,Neutral!$A8,Data!$DA:$DA)+'Rate History'!$D$11*SUMIF(Data!$G:$G,Neutral!$A8,Data!$DB:$DB)+'Rate History'!$D$12*SUMIF(Data!$G:$G,Neutral!$A8,Data!$DC:$DC)+'Rate History'!$D$13*SUMIF(Data!$G:$G,Neutral!$A8,Data!$DD:$DD)+'Rate History'!$D$14*SUMIF(Data!$G:$G,Neutral!$A8,Data!$DE:$DE)+'Rate History'!$D$15*SUMIF(Data!$G:$G,Neutral!$A8,Data!$DF:$DF)+'Rate History'!$D$16*SUMIF(Data!$G:$G,Neutral!$A8,Data!$DG:$DG)+'Rate History'!$D$17*SUMIF(Data!$G:$G,Neutral!$A8,Data!$DH:$DH)+'Rate History'!$D$18*SUMIF(Data!$G:$G,Neutral!$A8,Data!$DI:$DI)+'Rate History'!$D$19*SUMIF(Data!$G:$G,Neutral!$A8,Data!$DJ:$DJ)+'Rate History'!$D$20*SUMIF(Data!$G:$G,Neutral!$A8,Data!$DK:$DK)+'Rate History'!$D$21*SUMIF(Data!$G:$G,Neutral!$A8,Data!$DL:$DL)+'Rate History'!$D$22*SUMIF(Data!$G:$G,Neutral!$A8,Data!$DM:$DM)+'Rate History'!$D$23*SUMIF(Data!$G:$G,Neutral!$A8,Data!$DN:$DN)+'Rate History'!$D$24*SUMIF(Data!$G:$G,Neutral!$A8,Data!$DO:$DO)+'Rate History'!$D$25*SUMIF(Data!$G:$G,Neutral!$A8,Data!$DP:$DP)+'Rate History'!$D$26*SUMIF(Data!$G:$G,Neutral!$A8,Data!$DQ:$DQ)+'Rate History'!$D$27*SUMIF(Data!$G:$G,Neutral!$A8,Data!$DR:$DR)+'Rate History'!$D$28*SUMIF(Data!$G:$G,Neutral!$A8,Data!$DS:$DS)+'Rate History'!$D$29*SUMIF(Data!$G:$G,Neutral!$A8,Data!$DT:$DT)+'Rate History'!$D$30*SUMIF(Data!$G:$G,Neutral!$A8,Data!$DV:$DV)+'Rate History'!$D$31*SUMIF(Data!$G:$G,Neutral!$A8,Data!$DW:$DW)) -> 15391155 | C8: =$C$5*('Rate History'!$C$4*SUMIF(Data!$G:$G,Neutral!$A8,Data!$CU:$CU)+'Rate History'!$C$5*SUMIF(Data!$G:$G,Neutral!$A8,Data!$CV:$CV)+'Rate History'!$C$6*SUMIF(Data!$G:$G,Neutral!$A8,Data!$CW:$CW)+'Rate History'!$C$7*SUMIF(Data!$G:$G,Neutral!$A8,Data!$CX:$CX)+'Rate History'!$C$8*SUMIF(Data!$G:$G,Neutral!$A8,Data!$CY:$CY)+'Rate History'!$C$9*SUMIF(Data!$G:$G,Neutral!$A8,Data!$CZ:$CZ)+'Rate History'!$C$10*SUMIF(Data!$G:$G,Neutral!$A8,Data!$DA:$DA)+'Rate History'!$C$11*SUMIF(Data!$G:$G,Neutral!$A8,Data!$DB:$DB)+'Rate History'!$C$12*SUMIF(Data!$G:$G,Neutral!$A8,Data!$DC:$DC)+'Rate History'!$C$13*SUMIF(Data!$G:$G,Neutral!$A8,Data!$DD:$DD)+'Rate History'!$C$14*SUMIF(Data!$G:$G,Neutral!$A8,Data!$DE:$DE)+'Rate History'!$C$15*SUMIF(Data!$G:$G,Neutral!$A8,Data!$DF:$DF)+'Rate History'!$C$16*SUMIF(Data!$G:$G,Neutral!$A8,Data!$DG:$DG)+'Rate History'!$C$17*SUMIF(Data!$G:$G,Neutral!$A8,Data!$DH:$DH)+'Rate History'!$C$18*SUMIF(Data!$G:$G,Neutral!$A8,Data!$DI:$DI)+'Rate History'!$C$19*SUMIF(Data!$G:$G,Neutral!$A8,Data!$DJ:$DJ)+'Rate History'!$C$20*SUMIF(Data!$G:$G,Neutral!$A8,Data!$DK:$DK)+'Rate History'!$C$21*SUMIF(Data!$G:$G,Neutral!$A8,Data!$DL:$DL)+'Rate History'!$C$22*SUMIF(Data!$G:$G,Neutral!$A8,Data!$DM:$DM)+'Rate History'!$C$23*SUMIF(Data!$G:$G,Neutral!$A8,Data!$DN:$DN)+'Rate History'!$C$24*SUMIF(Data!$G:$G,Neutral!$A8,Data!$DO:$DO)+'Rate History'!$C$25*SUMIF(Data!$G:$G,Neutral!$A8,Data!$DP:$DP)+'Rate History'!$C$26*SUMIF(Data!$G:$G,Neutral!$A8,Data!$DQ:$DQ)+'Rate History'!$C$27*SUMIF(Data!$G:$G,Neutral!$A8,Data!$DR:$DR)+'Rate History'!$C$28*SUMIF(Data!$G:$G,Neutral!$A8,Data!$DS:$DS)+'Rate History'!$C$29*SUMIF(Data!$G:$G,Neutral!$A8,Data!$DT:$DT)+'Rate History'!$C$30*SUMIF(Data!$G:$G,Neutral!$A8,Data!$DV:$DV)+'Rate History'!$C$31*SUMIF(Data!$G:$G,Neutral!$A8,Data!$DW:$DW)) -> 15438272 | D8: =C8-B8 -> 47117.316 | E8: =IFERROR(D8/B8,"") -> 0.0030613243
A9: Angelina College | B9: =$B$5*('Rate History'!$D$4*SUMIF(Data!$G:$G,Neutral!$A9,Data!$CU:$CU)+'Rate History'!$D$5*SUMIF(Data!$G:$G,Neutral!$A9,Data!$CV:$CV)+'Rate History'!$D$6*SUMIF(Data!$G:$G,Neutral!$A9,Data!$CW:$CW)+'Rate History'!$D$7*SUMIF(Data!$G:$G,Neutral!$A9,Data!$CX:$CX)+'Rate History'!$D$8*SUMIF(Data!$G:$G,Neutral!$A9,Data!$CY:$CY)+'Rate History'!$D$9*SUMIF(Data!$G:$G,Neutral!$A9,Data!$CZ:$CZ)+'Rate History'!$D$10*SUMIF(Data!$G:$G,Neutral!$A9,Data!$DA:$DA)+'Rate History'!$D$11*SUMIF(Data!$G:$G,Neutral!$A9,Data!$DB:$DB)+'Rate History'!$D$12*SUMIF(Data!$G:$G,Neutral!$A9,Data!$DC:$DC)+'Rate History'!$D$13*SUMIF(Data!$G:$G,Neutral!$A9,Data!$DD:$DD)+'Rate History'!$D$14*SUMIF(Data!$G:$G,Neutral!$A9,Data!$DE:$DE)+'Rate History'!$D$15*SUMIF(Data!$G:$G,Neutral!$A9,Data!$DF:$DF)+'Rate History'!$D$16*SUMIF(Data!$G:$G,Neutral!$A9,Data!$DG:$DG)+'Rate History'!$D$17*SUMIF(Data!$G:$G,Neutral!$A9,Data!$DH:$DH)+'Rate History'!$D$18*SUMIF(Data!$G:$G,Neutral!$A9,Data!$DI:$DI)+'Rate History'!$D$19*SUMIF(Data!$G:$G,Neutral!$A9,Data!$DJ:$DJ)+'Rate History'!$D$20*SUMIF(Data!$G:$G,Neutral!$A9,Data!$DK:$DK)+'Rate History'!$D$21*SUMIF(Data!$G:$G,Neutral!$A9,Data!$DL:$DL)+'Rate History'!$D$22*SUMIF(Data!$G:$G,Neutral!$A9,Data!$DM:$DM)+'Rate History'!$D$23*SUMIF(Data!$G:$G,Neutral!$A9,Data!$DN:$DN)+'Rate History'!$D$24*SUMIF(Data!$G:$G,Neutral!$A9,Data!$DO:$DO)+'Rate History'!$D$25*SUMIF(Data!$G:$G,Neutral!$A9,Data!$DP:$DP)+'Rate History'!$D$26*SUMIF(Data!$G:$G,Neutral!$A9,Data!$DQ:$DQ)+'Rate History'!$D$27*SUMIF(Data!$G:$G,Neutral!$A9,Data!$DR:$DR)+'Rate History'!$D$28*SUMIF(Data!$G:$G,Neutral!$A9,Data!$DS:$DS)+'Rate History'!$D$29*SUMIF(Data!$G:$G,Neutral!$A9,Data!$DT:$DT)+'Rate History'!$D$30*SUMIF(Data!$G:$G,Neutral!$A9,Data!$DV:$DV)+'Rate History'!$D$31*SUMIF(Data!$G:$G,Neutral!$A9,Data!$DW:$DW)) -> 7434671.6 | C9: =$C$5*('Rate History'!$C$4*SUMIF(Data!$G:$G,Neutral!$A9,Data!$CU:$CU)+'Rate History'!$C$5*SUMIF(Data!$G:$G,Neutral!$A9,Data!$CV:$CV)+'Rate History'!$C$6*SUMIF(Data!$G:$G,Neutral!$A9,Data!$CW:$CW)+'Rate History'!$C$7*SUMIF(Data!$G:$G,Neutral!$A9,Data!$CX:$CX)+'Rate History'!$C$8*SUMIF(Data!$G:$G,Neutral!$A9,Data!$CY:$CY)+'Rate History'!$C$9*SUMIF(Data!$G:$G,Neutral!$A9,Data!$CZ:$CZ)+'Rate History'!$C$10*SUMIF(Data!$G:$G,Neutral!$A9,Data!$DA:$DA)+'Rate History'!$C$11*SUMIF(Data!$G:$G,Neutral!$A9,Data!$DB:$DB)+'Rate History'!$C$12*SUMIF(Data!$G:$G,Neutral!$A9,Data!$DC:$DC)+'Rate History'!$C$13*SUMIF(Data!$G:$G,Neutral!$A9,Data!$DD:$DD)+'Rate History'!$C$14*SUMIF(Data!$G:$G,Neutral!$A9,Data!$DE:$DE)+'Rate History'!$C$15*SUMIF(Data!$G:$G,Neutral!$A9,Data!$DF:$DF)+'Rate History'!$C$16*SUMIF(Data!$G:$G,Neutral!$A9,Data!$DG:$DG)+'Rate History'!$C$17*SUMIF(Data!$G:$G,Neutral!$A9,Data!$DH:$DH)+'Rate History'!$C$18*SUMIF(Data!$G:$G,Neutral!$A9,Data!$DI:$DI)+'Rate History'!$C$19*SUMIF(Data!$G:$G,Neutral!$A9,Data!$DJ:$DJ)+'Rate History'!$C$20*SUMIF(Data!$G:$G,Neutral!$A9,Data!$DK:$DK)+'Rate History'!$C$21*SUMIF(Data!$G:$G,Neutral!$A9,Data!$DL:$DL)+'Rate History'!$C$22*SUMIF(Data!$G:$G,Neutral!$A9,Data!$DM:$DM)+'Rate History'!$C$23*SUMIF(Data!$G:$G,Neutral!$A9,Data!$DN:$DN)+'Rate History'!$C$24*SUMIF(Data!$G:$G,Neutral!$A9,Data!$DO:$DO)+'Rate History'!$C$25*SUMIF(Data!$G:$G,Neutral!$A9,Data!$DP:$DP)+'Rate History'!$C$26*SUMIF(Data!$G:$G,Neutral!$A9,Data!$DQ:$DQ)+'Rate History'!$C$27*SUMIF(Data!$G:$G,Neutral!$A9,Data!$DR:$DR)+'Rate History'!$C$28*SUMIF(Data!$G:$G,Neutral!$A9,Data!$DS:$DS)+'Rate History'!$C$29*SUMIF(Data!$G:$G,Neutral!$A9,Data!$DT:$DT)+'Rate History'!$C$30*SUMIF(Data!$G:$G,Neutral!$A9,Data!$DV:$DV)+'Rate History'!$C$31*SUMIF(Data!$G:$G,Neutral!$A9,Data!$DW:$DW)) -> 7446139.8 | D9: =C9-B9 -> 11468.161 | E9: =IFERROR(D9/B9,"") -> 0.0015425242
A10: Austin Community College | B10: =$B$5*('Rate History'!$D$4*SUMIF(Data!$G:$G,Neutral!$A10,Data!$CU:$CU)+'Rate History'!$D$5*SUMIF(Data!$G:$G,Neutral!$A10,Data!$CV:$CV)+'Rate History'!$D$6*SUMIF(Data!$G:$G,Neutral!$A10,Data!$CW:$CW)+'Rate History'!$D$7*SUMIF(Data!$G:$G,Neutral!$A10,Data!$CX:$CX)+'Rate History'!$D$8*SUMIF(Data!$G:$G,Neutral!$A10,Data!$CY:$CY)+'Rate History'!$D$9*SUMIF(Data!$G:$G,Neutral!$A10,Data!$CZ:$CZ)+'Rate History'!$D$10*SUMIF(Data!$G:$G,Neutral!$A10,Data!$DA:$DA)+'Rate History'!$D$11*SUMIF(Data!$G:$G,Neutral!$A10,Data!$DB:$DB)+'Rate History'!$D$12*SUMIF(Data!$G:$G,Neutral!$A10,Data!$DC:$DC)+'Rate History'!$D$13*SUMIF(Data!$G:$G,Neutral!$A10,Data!$DD:$DD)+'Rate History'!$D$14*SUMIF(Data!$G:$G,Neutral!$A10,Data!$DE:$DE)+'Rate History'!$D$15*SUMIF(Data!$G:$G,Neutral!$A10,Data!$DF:$DF)+'Rate History'!$D$16*SUMIF(Data!$G:$G,Neutral!$A10,Data!$DG:$DG)+'Rate History'!$D$17*SUMIF(Data!$G:$G,Neutral!$A10,Data!$DH:$DH)+'Rate History'!$D$18*SUMIF(Data!$G:$G,Neutral!$A10,Data!$DI:$DI)+'Rate History'!$D$19*SUMIF(Data!$G:$G,Neutral!$A10,Data!$DJ:$DJ)+'Rate History'!$D$20*SUMIF(Data!$G:$G,Neutral!$A10,Data!$DK:$DK)+'Rate History'!$D$21*SUMIF(Data!$G:$G,Neutral!$A10,Data!$DL:$DL)+'Rate History'!$D$22*SUMIF(Data!$G:$G,Neutral!$A10,Data!$DM:$DM)+'Rate History'!$D$23*SUMIF(Data!$G:$G,Neutral!$A10,Data!$DN:$DN)+'Rate History'!$D$24*SUMIF(Data!$G:$G,Neutral!$A10,Data!$DO:$DO)+'Rate History'!$D$25*SUMIF(Data!$G:$G,Neutral!$A10,Data!$DP:$DP)+'Rate History'!$D$26*SUMIF(Data!$G:$G,Neutral!$A10,Data!$DQ:$DQ)+'Rate History'!$D$27*SUMIF(Data!$G:$G,Neutral!$A10,Data!$DR:$DR)+'Rate History'!$D$28*SUMIF(Data!$G:$G,Neutral!$A10,Data!$DS:$DS)+'Rate History'!$D$29*SUMIF(Data!$G:$G,Neutral!$A10,Data!$DT:$DT)+'Rate History'!$D$30*SUMIF(Data!$G:$G,Neutral!$A10,Data!$DV:$DV)+'Rate History'!$D$31*SUMIF(Data!$G:$G,Neutral!$A10,Data!$DW:$DW)) -> 46302481 | C10: =$C$5*('Rate History'!$C$4*SUMIF(Data!$G:$G,Neutral!$A10,Data!$CU:$CU)+'Rate History'!$C$5*SUMIF(Data!$G:$G,Neutral!$A10,Data!$CV:$CV)+'Rate History'!$C$6*SUMIF(Data!$G:$G,Neutral!$A10,Data!$CW:$CW)+'Rate History'!$C$7*SUMIF(Data!$G:$G,Neutral!$A10,Data!$CX:$CX)+'Rate History'!$C$8*SUMIF(Data!$G:$G,Neutral!$A10,Data!$CY:$CY)+'Rate History'!$C$9*SUMIF(Data!$G:$G,Neutral!$A10,Data!$CZ:$CZ)+'Rate History'!$C$10*SUMIF(Data!$G:$G,Neutral!$A10,Data!$DA:$DA)+'Rate History'!$C$11*SUMIF(Data!$G:$G,Neutral!$A10,Data!$DB:$DB)+'Rate History'!$C$12*SUMIF(Data!$G:$G,Neutral!$A10,Data!$DC:$DC)+'Rate History'!$C$13*SUMIF(Data!$G:$G,Neutral!$A10,Data!$DD:$DD)+'Rate History'!$C$14*SUMIF(Data!$G:$G,Neutral!$A10,Data!$DE:$DE)+'Rate History'!$C$15*SUMIF(Data!$G:$G,Neutral!$A10,Data!$DF:$DF)+'Rate History'!$C$16*SUMIF(Data!$G:$G,Neutral!$A10,Data!$DG:$DG)+'Rate History'!$C$17*SUMIF(Data!$G:$G,Neutral!$A10,Data!$DH:$DH)+'Rate History'!$C$18*SUMIF(Data!$G:$G,Neutral!$A10,Data!$DI:$DI)+'Rate History'!$C$19*SUMIF(Data!$G:$G,Neutral!$A10,Data!$DJ:$DJ)+'Rate History'!$C$20*SUMIF(Data!$G:$G,Neutral!$A10,Data!$DK:$DK)+'Rate History'!$C$21*SUMIF(Data!$G:$G,Neutral!$A10,Data!$DL:$DL)+'Rate History'!$C$22*SUMIF(Data!$G:$G,Neutral!$A10,Data!$DM:$DM)+'Rate History'!$C$23*SUMIF(Data!$G:$G,Neutral!$A10,Data!$DN:$DN)+'Rate History'!$C$24*SUMIF(Data!$G:$G,Neutral!$A10,Data!$DO:$DO)+'Rate History'!$C$25*SUMIF(Data!$G:$G,Neutral!$A10,Data!$DP:$DP)+'Rate History'!$C$26*SUMIF(Data!$G:$G,Neutral!$A10,Data!$DQ:$DQ)+'Rate History'!$C$27*SUMIF(Data!$G:$G,Neutral!$A10,Data!$DR:$DR)+'Rate History'!$C$28*SUMIF(Data!$G:$G,Neutral!$A10,Data!$DS:$DS)+'Rate History'!$C$29*SUMIF(Data!$G:$G,Neutral!$A10,Data!$DT:$DT)+'Rate History'!$C$30*SUMIF(Data!$G:$G,Neutral!$A10,Data!$DV:$DV)+'Rate History'!$C$31*SUMIF(Data!$G:$G,Neutral!$A10,Data!$DW:$DW)) -> 46235561 | D10: =C10-B10 -> -66919.728 | E10: =IFERROR(D10/B10,"") -> -0.0014452731
A11: Blinn College | B11: =$B$5*('Rate History'!$D$4*SUMIF(Data!$G:$G,Neutral!$A11,Data!$CU:$CU)+'Rate History'!$D$5*SUMIF(Data!$G:$G,Neutral!$A11,Data!$CV:$CV)+'Rate History'!$D$6*SUMIF(Data!$G:$G,Neutral!$A11,Data!$CW:$CW)+'Rate History'!$D$7*SUMIF(Data!$G:$G,Neutral!$A11,Data!$CX:$CX)+'Rate History'!$D$8*SUMIF(Data!$G:$G,Neutral!$A11,Data!$CY:$CY)+'Rate History'!$D$9*SUMIF(Data!$G:$G,Neutral!$A11,Data!$CZ:$CZ)+'Rate History'!$D$10*SUMIF(Data!$G:$G,Neutral!$A11,Data!$DA:$DA)+'Rate History'!$D$11*SUMIF(Data!$G:$G,Neutral!$A11,Data!$DB:$DB)+'Rate History'!$D$12*SUMIF(Data!$G:$G,Neutral!$A11,Data!$DC:$DC)+'Rate History'!$D$13*SUMIF(Data!$G:$G,Neutral!$A11,Data!$DD:$DD)+'Rate History'!$D$14*SUMIF(Data!$G:$G,Neutral!$A11,Data!$DE:$DE)+'Rate History'!$D$15*SUMIF(Data!$G:$G,Neutral!$A11,Data!$DF:$DF)+'Rate History'!$D$16*SUMIF(Data!$G:$G,Neutral!$A11,Data!$DG:$DG)+'Rate History'!$D$17*SUMIF(Data!$G:$G,Neutral!$A11,Data!$DH:$DH)+'Rate History'!$D$18*SUMIF(Data!$G:$G,Neutral!$A11,Data!$DI:$DI)+'Rate History'!$D$19*SUMIF(Data!$G:$G,Neutral!$A11,Data!$DJ:$DJ)+'Rate History'!$D$20*SUMIF(Data!$G:$G,Neutral!$A11,Data!$DK:$DK)+'Rate History'!$D$21*SUMIF(Data!$G:$G,Neutral!$A11,Data!$DL:$DL)+'Rate History'!$D$22*SUMIF(Data!$G:$G,Neutral!$A11,Data!$DM:$DM)+'Rate History'!$D$23*SUMIF(Data!$G:$G,Neutral!$A11,Data!$DN:$DN)+'Rate History'!$D$24*SUMIF(Data!$G:$G,Neutral!$A11,Data!$DO:$DO)+'Rate History'!$D$25*SUMIF(Data!$G:$G,Neutral!$A11,Data!$DP:$DP)+'Rate History'!$D$26*SUMIF(Data!$G:$G,Neutral!$A11,Data!$DQ:$DQ)+'Rate History'!$D$27*SUMIF(Data!$G:$G,Neutral!$A11,Data!$DR:$DR)+'Rate History'!$D$28*SUMIF(Data!$G:$G,Neutral!$A11,Data!$DS:$DS)+'Rate History'!$D$29*SUMIF(Data!$G:$G,Neutral!$A11,Data!$DT:$DT)+'Rate History'!$D$30*SUMIF(Data!$G:$G,Neutral!$A11,Data!$DV:$DV)+'Rate History'!$D$31*SUMIF(Data!$G:$G,Neutral!$A11,Data!$DW:$DW)) -> 22022855 | C11: =$C$5*('Rate History'!$C$4*SUMIF(Data!$G:$G,Neutral!$A11,Data!$CU:$CU)+'Rate History'!$C$5*SUMIF(Data!$G:$G,Neutral!$A11,Data!$CV:$CV)+'Rate History'!$C$6*SUMIF(Data!$G:$G,Neutral!$A11,Data!$CW:$CW)+'Rate History'!$C$7*SUMIF(Data!$G:$G,Neutral!$A11,Data!$CX:$CX)+'Rate History'!$C$8*SUMIF(Data!$G:$G,Neutral!$A11,Data!$CY:$CY)+'Rate History'!$C$9*SUMIF(Data!$G:$G,Neutral!$A11,Data!$CZ:$CZ)+'Rate History'!$C$10*SUMIF(Data!$G:$G,Neutral!$A11,Data!$DA:$DA)+'Rate History'!$C$11*SUMIF(Data!$G:$G,Neutral!$A11,Data!$DB:$DB)+'Rate History'!$C$12*SUMIF(Data!$G:$G,Neutral!$A11,Data!$DC:$DC)+'Rate History'!$C$13*SUMIF(Data!$G:$G,Neutral!$A11,Data!$DD:$DD)+'Rate History'!$C$14*SUMIF(Data!$G:$G,Neutral!$A11,Data!$DE:$DE)+'Rate History'!$C$15*SUMIF(Data!$G:$G,Neutral!$A11,Data!$DF:$DF)+'Rate History'!$C$16*SUMIF(Data!$G:$G,Neutral!$A11,Data!$DG:$DG)+'Rate History'!$C$17*SUMIF(Data!$G:$G,Neutral!$A11,Data!$DH:$DH)+'Rate History'!$C$18*SUMIF(Data!$G:$G,Neutral!$A11,Data!$DI:$DI)+'Rate History'!$C$19*SUMIF(Data!$G:$G,Neutral!$A11,Data!$DJ:$DJ)+'Rate History'!$C$20*SUMIF(Data!$G:$G,Neutral!$A11,Data!$DK:$DK)+'Rate History'!$C$21*SUMIF(Data!$G:$G,Neutral!$A11,Data!$DL:$DL)+'Rate History'!$C$22*SUMIF(Data!$G:$G,Neutral!$A11,Data!$DM:$DM)+'Rate History'!$C$23*SUMIF(Data!$G:$G,Neutral!$A11,Data!$DN:$DN)+'Rate History'!$C$24*SUMIF(Data!$G:$G,Neutral!$A11,Data!$DO:$DO)+'Rate History'!$C$25*SUMIF(Data!$G:$G,Neutral!$A11,Data!$DP:$DP)+'Rate History'!$C$26*SUMIF(Data!$G:$G,Neutral!$A11,Data!$DQ:$DQ)+'Rate History'!$C$27*SUMIF(Data!$G:$G,Neutral!$A11,Data!$DR:$DR)+'Rate History'!$C$28*SUMIF(Data!$G:$G,Neutral!$A11,Data!$DS:$DS)+'Rate History'!$C$29*SUMIF(Data!$G:$G,Neutral!$A11,Data!$DT:$DT)+'Rate History'!$C$30*SUMIF(Data!$G:$G,Neutral!$A11,Data!$DV:$DV)+'Rate History'!$C$31*SUMIF(Data!$G:$G,Neutral!$A11,Data!$DW:$DW)) -> 22050686 | D11: =C11-B11 -> 27831.548 | E11: =IFERROR(D11/B11,"") -> 0.0012637575
A12: Brazosport College | B12: =$B$5*('Rate History'!$D$4*SUMIF(Data!$G:$G,Neutral!$A12,Data!$CU:$CU)+'Rate History'!$D$5*SUMIF(Data!$G:$G,Neutral!$A12,Data!$CV:$CV)+'Rate History'!$D$6*SUMIF(Data!$G:$G,Neutral!$A12,Data!$CW:$CW)+'Rate History'!$D$7*SUMIF(Data!$G:$G,Neutral!$A12,Data!$CX:$CX)+'Rate History'!$D$8*SUMIF(Data!$G:$G,Neutral!$A12,Data!$CY:$CY)+'Rate History'!$D$9*SUMIF(Data!$G:$G,Neutral!$A12,Data!$CZ:$CZ)+'Rate History'!$D$10*SUMIF(Data!$G:$G,Neutral!$A12,Data!$DA:$DA)+'Rate History'!$D$11*SUMIF(Data!$G:$G,Neutral!$A12,Data!$DB:$DB)+'Rate History'!$D$12*SUMIF(Data!$G:$G,Neutral!$A12,Data!$DC:$DC)+'Rate History'!$D$13*SUMIF(Data!$G:$G,Neutral!$A12,Data!$DD:$DD)+'Rate History'!$D$14*SUMIF(Data!$G:$G,Neutral!$A12,Data!$DE:$DE)+'Rate History'!$D$15*SUMIF(Data!$G:$G,Neutral!$A12,Data!$DF:$DF)+'Rate History'!$D$16*SUMIF(Data!$G:$G,Neutral!$A12,Data!$DG:$DG)+'Rate History'!$D$17*SUMIF(Data!$G:$G,Neutral!$A12,Data!$DH:$DH)+'Rate History'!$D$18*SUMIF(Data!$G:$G,Neutral!$A12,Data!$DI:$DI)+'Rate History'!$D$19*SUMIF(Data!$G:$G,Neutral!$A12,Data!$DJ:$DJ)+'Rate History'!$D$20*SUMIF(Data!$G:$G,Neutral!$A12,Data!$DK:$DK)+'Rate History'!$D$21*SUMIF(Data!$G:$G,Neutral!$A12,Data!$DL:$DL)+'Rate History'!$D$22*SUMIF(Data!$G:$G,Neutral!$A12,Data!$DM:$DM)+'Rate History'!$D$23*SUMIF(Data!$G:$G,Neutral!$A12,Data!$DN:$DN)+'Rate History'!$D$24*SUMIF(Data!$G:$G,Neutral!$A12,Data!$DO:$DO)+'Rate History'!$D$25*SUMIF(Data!$G:$G,Neutral!$A12,Data!$DP:$DP)+'Rate History'!$D$26*SUMIF(Data!$G:$G,Neutral!$A12,Data!$DQ:$DQ)+'Rate History'!$D$27*SUMIF(Data!$G:$G,Neutral!$A12,Data!$DR:$DR)+'Rate History'!$D$28*SUMIF(Data!$G:$G,Neutral!$A12,Data!$DS:$DS)+'Rate History'!$D$29*SUMIF(Data!$G:$G,Neutral!$A12,Data!$DT:$DT)+'Rate History'!$D$30*SUMIF(Data!$G:$G,Neutral!$A12,Data!$DV:$DV)+'Rate History'!$D$31*SUMIF(Data!$G:$G,Neutral!$A12,Data!$DW:$DW)) -> 4912010.3 | C12: =$C$5*('Rate History'!$C$4*SUMIF(Data!$G:$G,Neutral!$A12,Data!$CU:$CU)+'Rate History'!$C$5*SUMIF(Data!$G:$G,Neutral!$A12,Data!$CV:$CV)+'Rate History'!$C$6*SUMIF(Data!$G:$G,Neutral!$A12,Data!$CW:$CW)+'Rate History'!$C$7*SUMIF(Data!$G:$G,Neutral!$A12,Data!$CX:$CX)+'Rate History'!$C$8*SUMIF(Data!$G:$G,Neutral!$A12,Data!$CY:$CY)+'Rate History'!$C$9*SUMIF(Data!$G:$G,Neutral!$A12,Data!$CZ:$CZ)+'Rate History'!$C$10*SUMIF(Data!$G:$G,Neutral!$A12,Data!$DA:$DA)+'Rate History'!$C$11*SUMIF(Data!$G:$G,Neutral!$A12,Data!$DB:$DB)+'Rate History'!$C$12*SUMIF(Data!$G:$G,Neutral!$A12,Data!$DC:$DC)+'Rate History'!$C$13*SUMIF(Data!$G:$G,Neutral!$A12,Data!$DD:$DD)+'Rate History'!$C$14*SUMIF(Data!$G:$G,Neutral!$A12,Data!$DE:$DE)+'Rate History'!$C$15*SUMIF(Data!$G:$G,Neutral!$A12,Data!$DF:$DF)+'Rate History'!$C$16*SUMIF(Data!$G:$G,Neutral!$A12,Data!$DG:$DG)+'Rate History'!$C$17*SUMIF(Data!$G:$G,Neutral!$A12,Data!$DH:$DH)+'Rate History'!$C$18*SUMIF(Data!$G:$G,Neutral!$A12,Data!$DI:$DI)+'Rate History'!$C$19*SUMIF(Data!$G:$G,Neutral!$A12,Data!$DJ:$DJ)+'Rate History'!$C$20*SUMIF(Data!$G:$G,Neutral!$A12,Data!$DK:$DK)+'Rate History'!$C$21*SUMIF(Data!$G:$G,Neutral!$A12,Data!$DL:$DL)+'Rate History'!$C$22*SUMIF(Data!$G:$G,Neutral!$A12,Data!$DM:$DM)+'Rate History'!$C$23*SUMIF(Data!$G:$G,Neutral!$A12,Data!$DN:$DN)+'Rate History'!$C$24*SUMIF(Data!$G:$G,Neutral!$A12,Data!$DO:$DO)+'Rate History'!$C$25*SUMIF(Data!$G:$G,Neutral!$A12,Data!$DP:$DP)+'Rate History'!$C$26*SUMIF(Data!$G:$G,Neutral!$A12,Data!$DQ:$DQ)+'Rate History'!$C$27*SUMIF(Data!$G:$G,Neutral!$A12,Data!$DR:$DR)+'Rate History'!$C$28*SUMIF(Data!$G:$G,Neutral!$A12,Data!$DS:$DS)+'Rate History'!$C$29*SUMIF(Data!$G:$G,Neutral!$A12,Data!$DT:$DT)+'Rate History'!$C$30*SUMIF(Data!$G:$G,Neutral!$A12,Data!$DV:$DV)+'Rate History'!$C$31*SUMIF(Data!$G:$G,Neutral!$A12,Data!$DW:$DW)) -> 4898796 | D12: =C12-B12 -> -13214.31 | E12: =IFERROR(D12/B12,"") -> -0.002690204
A13: Central Texas College | B13: =$B$5*('Rate History'!$D$4*SUMIF(Data!$G:$G,Neutral!$A13,Data!$CU:$CU)+'Rate History'!$D$5*SUMIF(Data!$G:$G,Neutral!$A13,Data!$CV:$CV)+'Rate History'!$D$6*SUMIF(Data!$G:$G,Neutral!$A13,Data!$CW:$CW)+'Rate History'!$D$7*SUMIF(Data!$G:$G,Neutral!$A13,Data!$CX:$CX)+'Rate History'!$D$8*SUMIF(Data!$G:$G,Neutral!$A13,Data!$CY:$CY)+'Rate History'!$D$9*SUMIF(Data!$G:$G,Neutral!$A13,Data!$CZ:$CZ)+'Rate History'!$D$10*SUMIF(Data!$G:$G,Neutral!$A13,Data!$DA:$DA)+'Rate History'!$D$11*SUMIF(Data!$G:$G,Neutral!$A13,Data!$DB:$DB)+'Rate History'!$D$12*SUMIF(Data!$G:$G,Neutral!$A13,Data!$DC:$DC)+'Rate History'!$D$13*SUMIF(Data!$G:$G,Neutral!$A13,Data!$DD:$DD)+'Rate History'!$D$14*SUMIF(Data!$G:$G,Neutral!$A13,Data!$DE:$DE)+'Rate History'!$D$15*SUMIF(Data!$G:$G,Neutral!$A13,Data!$DF:$DF)+'Rate History'!$D$16*SUMIF(Data!$G:$G,Neutral!$A13,Data!$DG:$DG)+'Rate History'!$D$17*SUMIF(Data!$G:$G,Neutral!$A13,Data!$DH:$DH)+'Rate History'!$D$18*SUMIF(Data!$G:$G,Neutral!$A13,Data!$DI:$DI)+'Rate History'!$D$19*SUMIF(Data!$G:$G,Neutral!$A13,Data!$DJ:$DJ)+'Rate History'!$D$20*SUMIF(Data!$G:$G,Neutral!$A13,Data!$DK:$DK)+'Rate History'!$D$21*SUMIF(Data!$G:$G,Neutral!$A13,Data!$DL:$DL)+'Rate History'!$D$22*SUMIF(Data!$G:$G,Neutral!$A13,Data!$DM:$DM)+'Rate History'!$D$23*SUMIF(Data!$G:$G,Neutral!$A13,Data!$DN:$DN)+'Rate History'!$D$24*SUMIF(Data!$G:$G,Neutral!$A13,Data!$DO:$DO)+'Rate History'!$D$25*SUMIF(Data!$G:$G,Neutral!$A13,Data!$DP:$DP)+'Rate History'!$D$26*SUMIF(Data!$G:$G,Neutral!$A13,Data!$DQ:$DQ)+'Rate History'!$D$27*SUMIF(Data!$G:$G,Neutral!$A13,Data!$DR:$DR)+'Rate History'!$D$28*SUMIF(Data!$G:$G,Neutral!$A13,Data!$DS:$DS)+'Rate History'!$D$29*SUMIF(Data!$G:$G,Neutral!$A13,Data!$DT:$DT)+'Rate History'!$D$30*SUMIF(Data!$G:$G,Neutral!$A13,Data!$DV:$DV)+'Rate History'!$D$31*SUMIF(Data!$G:$G,Neutral!$A13,Data!$DW:$DW)) -> 20012683 | C13: =$C$5*('Rate History'!$C$4*SUMIF(Data!$G:$G,Neutral!$A13,Data!$CU:$CU)+'Rate History'!$C$5*SUMIF(Data!$G:$G,Neutral!$A13,Data!$CV:$CV)+'Rate History'!$C$6*SUMIF(Data!$G:$G,Neutral!$A13,Data!$CW:$CW)+'Rate History'!$C$7*SUMIF(Data!$G:$G,Neutral!$A13,Data!$CX:$CX)+'Rate History'!$C$8*SUMIF(Data!$G:$G,Neutral!$A13,Data!$CY:$CY)+'Rate History'!$C$9*SUMIF(Data!$G:$G,Neutral!$A13,Data!$CZ:$CZ)+'Rate History'!$C$10*SUMIF(Data!$G:$G,Neutral!$A13,Data!$DA:$DA)+'Rate History'!$C$11*SUMIF(Data!$G:$G,Neutral!$A13,Data!$DB:$DB)+'Rate History'!$C$12*SUMIF(Data!$G:$G,Neutral!$A13,Data!$DC:$DC)+'Rate History'!$C$13*SUMIF(Data!$G:$G,Neutral!$A13,Data!$DD:$DD)+'Rate History'!$C$14*SUMIF(Data!$G:$G,Neutral!$A13,Data!$DE:$DE)+'Rate History'!$C$15*SUMIF(Data!$G:$G,Neutral!$A13,Data!$DF:$DF)+'Rate History'!$C$16*SUMIF(Data!$G:$G,Neutral!$A13,Data!$DG:$DG)+'Rate History'!$C$17*SUMIF(Data!$G:$G,Neutral!$A13,Data!$DH:$DH)+'Rate History'!$C$18*SUMIF(Data!$G:$G,Neutral!$A13,Data!$DI:$DI)+'Rate History'!$C$19*SUMIF(Data!$G:$G,Neutral!$A13,Data!$DJ:$DJ)+'Rate History'!$C$20*SUMIF(Data!$G:$G,Neutral!$A13,Data!$DK:$DK)+'Rate History'!$C$21*SUMIF(Data!$G:$G,Neutral!$A13,Data!$DL:$DL)+'Rate History'!$C$22*SUMIF(Data!$G:$G,Neutral!$A13,Data!$DM:$DM)+'Rate History'!$C$23*SUMIF(Data!$G:$G,Neutral!$A13,Data!$DN:$DN)+'Rate History'!$C$24*SUMIF(Data!$G:$G,Neutral!$A13,Data!$DO:$DO)+'Rate History'!$C$25*SUMIF(Data!$G:$G,Neutral!$A13,Data!$DP:$DP)+'Rate History'!$C$26*SUMIF(Data!$G:$G,Neutral!$A13,Data!$DQ:$DQ)+'Rate History'!$C$27*SUMIF(Data!$G:$G,Neutral!$A13,Data!$DR:$DR)+'Rate History'!$C$28*SUMIF(Data!$G:$G,Neutral!$A13,Data!$DS:$DS)+'Rate History'!$C$29*SUMIF(Data!$G:$G,Neutral!$A13,Data!$DT:$DT)+'Rate History'!$C$30*SUMIF(Data!$G:$G,Neutral!$A13,Data!$DV:$DV)+'Rate History'!$C$31*SUMIF(Data!$G:$G,Neutral!$A13,Data!$DW:$DW)) -> 19957092 | D13: =C13-B13 -> -55590.099 | E13: =IFERROR(D13/B13,"") -> -0.0027777435
A14: Cisco Junior College | B14: =$B$5*('Rate History'!$D$4*SUMIF(Data!$G:$G,Neutral!$A14,Data!$CU:$CU)+'Rate History'!$D$5*SUMIF(Data!$G:$G,Neutral!$A14,Data!$CV:$CV)+'Rate History'!$D$6*SUMIF(Data!$G:$G,Neutral!$A14,Data!$CW:$CW)+'Rate History'!$D$7*SUMIF(Data!$G:$G,Neutral!$A14,Data!$CX:$CX)+'Rate History'!$D$8*SUMIF(Data!$G:$G,Neutral!$A14,Data!$CY:$CY)+'Rate History'!$D$9*SUMIF(Data!$G:$G,Neutral!$A14,Data!$CZ:$CZ)+'Rate History'!$D$10*SUMIF(Data!$G:$G,Neutral!$A14,Data!$DA:$DA)+'Rate History'!$D$11*SUMIF(Data!$G:$G,Neutral!$A14,Data!$DB:$DB)+'Rate History'!$D$12*SUMIF(Data!$G:$G,Neutral!$A14,Data!$DC:$DC)+'Rate History'!$D$13*SUMIF(Data!$G:$G,Neutral!$A14,Data!$DD:$DD)+'Rate History'!$D$14*SUMIF(Data!$G:$G,Neutral!$A14,Data!$DE:$DE)+'Rate History'!$D$15*SUMIF(Data!$G:$G,Neutral!$A14,Data!$DF:$DF)+'Rate History'!$D$16*SUMIF(Data!$G:$G,Neutral!$A14,Data!$DG:$DG)+'Rate History'!$D$17*SUMIF(Data!$G:$G,Neutral!$A14,Data!$DH:$DH)+'Rate History'!$D$18*SUMIF(Data!$G:$G,Neutral!$A14,Data!$DI:$DI)+'Rate History'!$D$19*SUMIF(Data!$G:$G,Neutral!$A14,Data!$DJ:$DJ)+'Rate History'!$D$20*SUMIF(Data!$G:$G,Neutral!$A14,Data!$DK:$DK)+'Rate History'!$D$21*SUMIF(Data!$G:$G,Neutral!$A14,Data!$DL:$DL)+'Rate History'!$D$22*SUMIF(Data!$G:$G,Neutral!$A14,Data!$DM:$DM)+'Rate History'!$D$23*SUMIF(Data!$G:$G,Neutral!$A14,Data!$DN:$DN)+'Rate History'!$D$24*SUMIF(Data!$G:$G,Neutral!$A14,Data!$DO:$DO)+'Rate History'!$D$25*SUMIF(Data!$G:$G,Neutral!$A14,Data!$DP:$DP)+'Rate History'!$D$26*SUMIF(Data!$G:$G,Neutral!$A14,Data!$DQ:$DQ)+'Rate History'!$D$27*SUMIF(Data!$G:$G,Neutral!$A14,Data!$DR:$DR)+'Rate History'!$D$28*SUMIF(Data!$G:$G,Neutral!$A14,Data!$DS:$DS)+'Rate History'!$D$29*SUMIF(Data!$G:$G,Neutral!$A14,Data!$DT:$DT)+'Rate History'!$D$30*SUMIF(Data!$G:$G,Neutral!$A14,Data!$DV:$DV)+'Rate History'!$D$31*SUMIF(Data!$G:$G,Neutral!$A14,Data!$DW:$DW)) -> 5267029.1 | C14: =$C$5*('Rate History'!$C$4*SUMIF(Data!$G:$G,Neutral!$A14,Data!$CU:$CU)+'Rate History'!$C$5*SUMIF(Data!$G:$G,Neutral!$A14,Data!$CV:$CV)+'Rate History'!$C$6*SUMIF(Data!$G:$G,Neutral!$A14,Data!$CW:$CW)+'Rate History'!$C$7*SUMIF(Data!$G:$G,Neutral!$A14,Data!$CX:$CX)+'Rate History'!$C$8*SUMIF(Data!$G:$G,Neutral!$A14,Data!$CY:$CY)+'Rate History'!$C$9*SUMIF(Data!$G:$G,Neutral!$A14,Data!$CZ:$CZ)+'Rate History'!$C$10*SUMIF(Data!$G:$G,Neutral!$A14,Data!$DA:$DA)+'Rate History'!$C$11*SUMIF(Data!$G:$G,Neutral!$A14,Data!$DB:$DB)+'Rate History'!$C$12*SUMIF(Data!$G:$G,Neutral!$A14,Data!$DC:$DC)+'Rate History'!$C$13*SUMIF(Data!$G:$G,Neutral!$A14,Data!$DD:$DD)+'Rate History'!$C$14*SUMIF(Data!$G:$G,Neutral!$A14,Data!$DE:$DE)+'Rate History'!$C$15*SUMIF(Data!$G:$G,Neutral!$A14,Data!$DF:$DF)+'Rate History'!$C$16*SUMIF(Data!$G:$G,Neutral!$A14,Data!$DG:$DG)+'Rate History'!$C$17*SUMIF(Data!$G:$G,Neutral!$A14,Data!$DH:$DH)+'Rate History'!$C$18*SUMIF(Data!$G:$G,Neutral!$A14,Data!$DI:$DI)+'Rate History'!$C$19*SUMIF(Data!$G:$G,Neutral!$A14,Data!$DJ:$DJ)+'Rate History'!$C$20*SUMIF(Data!$G:$G,Neutral!$A14,Data!$DK:$DK)+'Rate History'!$C$21*SUMIF(Data!$G:$G,Neutral!$A14,Data!$DL:$DL)+'Rate History'!$C$22*SUMIF(Data!$G:$G,Neutral!$A14,Data!$DM:$DM)+'Rate History'!$C$23*SUMIF(Data!$G:$G,Neutral!$A14,Data!$DN:$DN)+'Rate History'!$C$24*SUMIF(Data!$G:$G,Neutral!$A14,Data!$DO:$DO)+'Rate History'!$C$25*SUMIF(Data!$G:$G,Neutral!$A14,Data!$DP:$DP)+'Rate History'!$C$26*SUMIF(Data!$G:$G,Neutral!$A14,Data!$DQ:$DQ)+'Rate History'!$C$27*SUMIF(Data!$G:$G,Neutral!$A14,Data!$DR:$DR)+'Rate History'!$C$28*SUMIF(Data!$G:$G,Neutral!$A14,Data!$DS:$DS)+'Rate History'!$C$29*SUMIF(Data!$G:$G,Neutral!$A14,Data!$DT:$DT)+'Rate History'!$C$30*SUMIF(Data!$G:$G,Neutral!$A14,Data!$DV:$DV)+'Rate History'!$C$31*SUMIF(Data!$G:$G,Neutral!$A14,Data!$DW:$DW)) -> 5274259.9 | D14: =C14-B14 -> 7230.8366 | E14: =IFERROR(D14/B14,"") -> 0.0013728492
A15: Clarendon College | B15: =$B$5*('Rate History'!$D$4*SUMIF(Data!$G:$G,Neutral!$A15,Data!$CU:$CU)+'Rate History'!$D$5*SUMIF(Data!$G:$G,Neutral!$A15,Data!$CV:$CV)+'Rate History'!$D$6*SUMIF(Data!$G:$G,Neutral!$A15,Data!$CW:$CW)+'Rate History'!$D$7*SUMIF(Data!$G:$G,Neutral!$A15,Data!$CX:$CX)+'Rate History'!$D$8*SUMIF(Data!$G:$G,Neutral!$A15,Data!$CY:$CY)+'Rate History'!$D$9*SUMIF(Data!$G:$G,Neutral!$A15,Data!$CZ:$CZ)+'Rate History'!$D$10*SUMIF(Data!$G:$G,Neutral!$A15,Data!$DA:$DA)+'Rate History'!$D$11*SUMIF(Data!$G:$G,Neutral!$A15,Data!$DB:$DB)+'Rate History'!$D$12*SUMIF(Data!$G:$G,Neutral!$A15,Data!$DC:$DC)+'Rate History'!$D$13*SUMIF(Data!$G:$G,Neutral!$A15,Data!$DD:$DD)+'Rate History'!$D$14*SUMIF(Data!$G:$G,Neutral!$A15,Data!$DE:$DE)+'Rate History'!$D$15*SUMIF(Data!$G:$G,Neutral!$A15,Data!$DF:$DF)+'Rate History'!$D$16*SUMIF(Data!$G:$G,Neutral!$A15,Data!$DG:$DG)+'Rate History'!$D$17*SUMIF(Data!$G:$G,Neutral!$A15,Data!$DH:$DH)+'Rate History'!$D$18*SUMIF(Data!$G:$G,Neutral!$A15,Data!$DI:$DI)+'Rate History'!$D$19*SUMIF(Data!$G:$G,Neutral!$A15,Data!$DJ:$DJ)+'Rate History'!$D$20*SUMIF(Data!$G:$G,Neutral!$A15,Data!$DK:$DK)+'Rate History'!$D$21*SUMIF(Data!$G:$G,Neutral!$A15,Data!$DL:$DL)+'Rate History'!$D$22*SUMIF(Data!$G:$G,Neutral!$A15,Data!$DM:$DM)+'Rate History'!$D$23*SUMIF(Data!$G:$G,Neutral!$A15,Data!$DN:$DN)+'Rate History'!$D$24*SUMIF(Data!$G:$G,Neutral!$A15,Data!$DO:$DO)+'Rate History'!$D$25*SUMIF(Data!$G:$G,Neutral!$A15,Data!$DP:$DP)+'Rate History'!$D$26*SUMIF(Data!$G:$G,Neutral!$A15,Data!$DQ:$DQ)+'Rate History'!$D$27*SUMIF(Data!$G:$G,Neutral!$A15,Data!$DR:$DR)+'Rate History'!$D$28*SUMIF(Data!$G:$G,Neutral!$A15,Data!$DS:$DS)+'Rate History'!$D$29*SUMIF(Data!$G:$G,Neutral!$A15,Data!$DT:$DT)+'Rate History'!$D$30*SUMIF(Data!$G:$G,Neutral!$A15,Data!$DV:$DV)+'Rate History'!$D$31*SUMIF(Data!$G:$G,Neutral!$A15,Data!$DW:$DW)) -> 2135311.6 | C15: =$C$5*('Rate History'!$C$4*SUMIF(Data!$G:$G,Neutral!$A15,Data!$CU:$CU)+'Rate History'!$C$5*SUMIF(Data!$G:$G,Neutral!$A15,Data!$CV:$CV)+'Rate History'!$C$6*SUMIF(Data!$G:$G,Neutral!$A15,Data!$CW:$CW)+'Rate History'!$C$7*SUMIF(Data!$G:$G,Neutral!$A15,Data!$CX:$CX)+'Rate History'!$C$8*SUMIF(Data!$G:$G,Neutral!$A15,Data!$CY:$CY)+'Rate History'!$C$9*SUMIF(Data!$G:$G,Neutral!$A15,Data!$CZ:$CZ)+'Rate History'!$C$10*SUMIF(Data!$G:$G,Neutral!$A15,Data!$DA:$DA)+'Rate History'!$C$11*SUMIF(Data!$G:$G,Neutral!$A15,Data!$DB:$DB)+'Rate History'!$C$12*SUMIF(Data!$G:$G,Neutral!$A15,Data!$DC:$DC)+'Rate History'!$C$13*SUMIF(Data!$G:$G,Neutral!$A15,Data!$DD:$DD)+'Rate History'!$C$14*SUMIF(Data!$G:$G,Neutral!$A15,Data!$DE:$DE)+'Rate History'!$C$15*SUMIF(Data!$G:$G,Neutral!$A15,Data!$DF:$DF)+'Rate History'!$C$16*SUMIF(Data!$G:$G,Neutral!$A15,Data!$DG:$DG)+'Rate History'!$C$17*SUMIF(Data!$G:$G,Neutral!$A15,Data!$DH:$DH)+'Rate History'!$C$18*SUMIF(Data!$G:$G,Neutral!$A15,Data!$DI:$DI)+'Rate History'!$C$19*SUMIF(Data!$G:$G,Neutral!$A15,Data!$DJ:$DJ)+'Rate History'!$C$20*SUMIF(Data!$G:$G,Neutral!$A15,Data!$DK:$DK)+'Rate History'!$C$21*SUMIF(Data!$G:$G,Neutral!$A15,Data!$DL:$DL)+'Rate History'!$C$22*SUMIF(Data!$G:$G,Neutral!$A15,Data!$DM:$DM)+'Rate History'!$C$23*SUMIF(Data!$G:$G,Neutral!$A15,Data!$DN:$DN)+'Rate History'!$C$24*SUMIF(Data!$G:$G,Neutral!$A15,Data!$DO:$DO)+'Rate History'!$C$25*SUMIF(Data!$G:$G,Neutral!$A15,Data!$DP:$DP)+'Rate History'!$C$26*SUMIF(Data!$G:$G,Neutral!$A15,Data!$DQ:$DQ)+'Rate History'!$C$27*SUMIF(Data!$G:$G,Neutral!$A15,Data!$DR:$DR)+'Rate History'!$C$28*SUMIF(Data!$G:$G,Neutral!$A15,Data!$DS:$DS)+'Rate History'!$C$29*SUMIF(Data!$G:$G,Neutral!$A15,Data!$DT:$DT)+'Rate History'!$C$30*SUMIF(Data!$G:$G,Neutral!$A15,Data!$DV:$DV)+'Rate History'!$C$31*SUMIF(Data!$G:$G,Neutral!$A15,Data!$DW:$DW)) -> 2143751.7 | D15: =C15-B15 -> 8440.1132 | E15: =IFERROR(D15/B15,"") -> 0.0039526377
A16: Coastal Bend College | B16: =$B$5*('Rate History'!$D$4*SUMIF(Data!$G:$G,Neutral!$A16,Data!$CU:$CU)+'Rate History'!$D$5*SUMIF(Data!$G:$G,Neutral!$A16,Data!$CV:$CV)+'Rate History'!$D$6*SUMIF(Data!$G:$G,Neutral!$A16,Data!$CW:$CW)+'Rate History'!$D$7*SUMIF(Data!$G:$G,Neutral!$A16,Data!$CX:$CX)+'Rate History'!$D$8*SUMIF(Data!$G:$G,Neutral!$A16,Data!$CY:$CY)+'Rate History'!$D$9*SUMIF(Data!$G:$G,Neutral!$A16,Data!$CZ:$CZ)+'Rate History'!$D$10*SUMIF(Data!$G:$G,Neutral!$A16,Data!$DA:$DA)+'Rate History'!$D$11*SUMIF(Data!$G:$G,Neutral!$A16,Data!$DB:$DB)+'Rate History'!$D$12*SUMIF(Data!$G:$G,Neutral!$A16,Data!$DC:$DC)+'Rate History'!$D$13*SUMIF(Data!$G:$G,Neutral!$A16,Data!$DD:$DD)+'Rate History'!$D$14*SUMIF(Data!$G:$G,Neutral!$A16,Data!$DE:$DE)+'Rate History'!$D$15*SUMIF(Data!$G:$G,Neutral!$A16,Data!$DF:$DF)+'Rate History'!$D$16*SUMIF(Data!$G:$G,Neutral!$A16,Data!$DG:$DG)+'Rate History'!$D$17*SUMIF(Data!$G:$G,Neutral!$A16,Data!$DH:$DH)+'Rate History'!$D$18*SUMIF(Data!$G:$G,Neutral!$A16,Data!$DI:$DI)+'Rate History'!$D$19*SUMIF(Data!$G:$G,Neutral!$A16,Data!$DJ:$DJ)+'Rate History'!$D$20*SUMIF(Data!$G:$G,Neutral!$A16,Data!$DK:$DK)+'Rate History'!$D$21*SUMIF(Data!$G:$G,Neutral!$A16,Data!$DL:$DL)+'Rate History'!$D$22*SUMIF(Data!$G:$G,Neutral!$A16,Data!$DM:$DM)+'Rate History'!$D$23*SUMIF(Data!$G:$G,Neutral!$A16,Data!$DN:$DN)+'Rate History'!$D$24*SUMIF(Data!$G:$G,Neutral!$A16,Data!$DO:$DO)+'Rate History'!$D$25*SUMIF(Data!$G:$G,Neutral!$A16,Data!$DP:$DP)+'Rate History'!$D$26*SUMIF(Data!$G:$G,Neutral!$A16,Data!$DQ:$DQ)+'Rate History'!$D$27*SUMIF(Data!$G:$G,Neutral!$A16,Data!$DR:$DR)+'Rate History'!$D$28*SUMIF(Data!$G:$G,Neutral!$A16,Data!$DS:$DS)+'Rate History'!$D$29*SUMIF(Data!$G:$G,Neutral!$A16,Data!$DT:$DT)+'Rate History'!$D$30*SUMIF(Data!$G:$G,Neutral!$A16,Data!$DV:$DV)+'Rate History'!$D$31*SUMIF(Data!$G:$G,Neutral!$A16,Data!$DW:$DW)) -> 5272562.9 | C16: =$C$5*('Rate History'!$C$4*SUMIF(Data!$G:$G,Neutral!$A16,Data!$CU:$CU)+'Rate History'!$C$5*SUMIF(Data!$G:$G,Neutral!$A16,Data!$CV:$CV)+'Rate History'!$C$6*SUMIF(Data!$G:$G,Neutral!$A16,Data!$CW:$CW)+'Rate History'!$C$7*SUMIF(Data!$G:$G,Neutral!$A16,Data!$CX:$CX)+'Rate History'!$C$8*SUMIF(Data!$G:$G,Neutral!$A16,Data!$CY:$CY)+'Rate History'!$C$9*SUMIF(Data!$G:$G,Neutral!$A16,Data!$CZ:$CZ)+'Rate History'!$C$10*SUMIF(Data!$G:$G,Neutral!$A16,Data!$DA:$DA)+'Rate History'!$C$11*SUMIF(Data!$G:$G,Neutral!$A16,Data!$DB:$DB)+'Rate History'!$C$12*SUMIF(Data!$G:$G,Neutral!$A16,Data!$DC:$DC)+'Rate History'!$C$13*SUMIF(Data!$G:$G,Neutral!$A16,Data!$DD:$DD)+'Rate History'!$C$14*SUMIF(Data!$G:$G,Neutral!$A16,Data!$DE:$DE)+'Rate History'!$C$15*SUMIF(Data!$G:$G,Neutral!$A16,Data!$DF:$DF)+'Rate History'!$C$16*SUMIF(Data!$G:$G,Neutral!$A16,Data!$DG:$DG)+'Rate History'!$C$17*SUMIF(Data!$G:$G,Neutral!$A16,Data!$DH:$DH)+'Rate History'!$C$18*SUMIF(Data!$G:$G,Neutral!$A16,Data!$DI:$DI)+'Rate History'!$C$19*SUMIF(Data!$G:$G,Neutral!$A16,Data!$DJ:$DJ)+'Rate History'!$C$20*SUMIF(Data!$G:$G,Neutral!$A16,Data!$DK:$DK)+'Rate History'!$C$21*SUMIF(Data!$G:$G,Neutral!$A16,Data!$DL:$DL)+'Rate History'!$C$22*SUMIF(Data!$G:$G,Neutral!$A16,Data!$DM:$DM)+'Rate History'!$C$23*SUMIF(Data!$G:$G,Neutral!$A16,Data!$DN:$DN)+'Rate History'!$C$24*SUMIF(Data!$G:$G,Neutral!$A16,Data!$DO:$DO)+'Rate History'!$C$25*SUMIF(Data!$G:$G,Neutral!$A16,Data!$DP:$DP)+'Rate History'!$C$26*SUMIF(Data!$G:$G,Neutral!$A16,Data!$DQ:$DQ)+'Rate History'!$C$27*SUMIF(Data!$G:$G,Neutral!$A16,Data!$DR:$DR)+'Rate History'!$C$28*SUMIF(Data!$G:$G,Neutral!$A16,Data!$DS:$DS)+'Rate History'!$C$29*SUMIF(Data!$G:$G,Neutral!$A16,Data!$DT:$DT)+'Rate History'!$C$30*SUMIF(Data!$G:$G,Neutral!$A16,Data!$DV:$DV)+'Rate History'!$C$31*SUMIF(Data!$G:$G,Neutral!$A16,Data!$DW:$DW)) -> 5279355.5 | D16: =C16-B16 -> 6792.5938 | E16: =IFERROR(D16/B16,"") -> 0.0012882907
A17: College of the Mainland Community College District | B17: =$B$5*('Rate History'!$D$4*SUMIF(Data!$G:$G,Neutral!$A17,Data!$CU:$CU)+'Rate History'!$D$5*SUMIF(Data!$G:$G,Neutral!$A17,Data!$CV:$CV)+'Rate History'!$D$6*SUMIF(Data!$G:$G,Neutral!$A17,Data!$CW:$CW)+'Rate History'!$D$7*SUMIF(Data!$G:$G,Neutral!$A17,Data!$CX:$CX)+'Rate History'!$D$8*SUMIF(Data!$G:$G,Neutral!$A17,Data!$CY:$CY)+'Rate History'!$D$9*SUMIF(Data!$G:$G,Neutral!$A17,Data!$CZ:$CZ)+'Rate History'!$D$10*SUMIF(Data!$G:$G,Neutral!$A17,Data!$DA:$DA)+'Rate History'!$D$11*SUMIF(Data!$G:$G,Neutral!$A17,Data!$DB:$DB)+'Rate History'!$D$12*SUMIF(Data!$G:$G,Neutral!$A17,Data!$DC:$DC)+'Rate History'!$D$13*SUMIF(Data!$G:$G,Neutral!$A17,Data!$DD:$DD)+'Rate History'!$D$14*SUMIF(Data!$G:$G,Neutral!$A17,Data!$DE:$DE)+'Rate History'!$D$15*SUMIF(Data!$G:$G,Neutral!$A17,Data!$DF:$DF)+'Rate History'!$D$16*SUMIF(Data!$G:$G,Neutral!$A17,Data!$DG:$DG)+'Rate History'!$D$17*SUMIF(Data!$G:$G,Neutral!$A17,Data!$DH:$DH)+'Rate History'!$D$18*SUMIF(Data!$G:$G,Neutral!$A17,Data!$DI:$DI)+'Rate History'!$D$19*SUMIF(Data!$G:$G,Neutral!$A17,Data!$DJ:$DJ)+'Rate History'!$D$20*SUMIF(Data!$G:$G,Neutral!$A17,Data!$DK:$DK)+'Rate History'!$D$21*SUMIF(Data!$G:$G,Neutral!$A17,Data!$DL:$DL)+'Rate History'!$D$22*SUMIF(Data!$G:$G,Neutral!$A17,Data!$DM:$DM)+'Rate History'!$D$23*SUMIF(Data!$G:$G,Neutral!$A17,Data!$DN:$DN)+'Rate History'!$D$24*SUMIF(Data!$G:$G,Neutral!$A17,Data!$DO:$DO)+'Rate History'!$D$25*SUMIF(Data!$G:$G,Neutral!$A17,Data!$DP:$DP)+'Rate History'!$D$26*SUMIF(Data!$G:$G,Neutral!$A17,Data!$DQ:$DQ)+'Rate History'!$D$27*SUMIF(Data!$G:$G,Neutral!$A17,Data!$DR:$DR)+'Rate History'!$D$28*SUMIF(Data!$G:$G,Neutral!$A17,Data!$DS:$DS)+'Rate History'!$D$29*SUMIF(Data!$G:$G,Neutral!$A17,Data!$DT:$DT)+'Rate History'!$D$30*SUMIF(Data!$G:$G,Neutral!$A17,Data!$DV:$DV)+'Rate History'!$D$31*SUMIF(Data!$G:$G,Neutral!$A17,Data!$DW:$DW)) -> 5837060 | C17: =$C$5*('Rate History'!$C$4*SUMIF(Data!$G:$G,Neutral!$A17,Data!$CU:$CU)+'Rate History'!$C$5*SUMIF(Data!$G:$G,Neutral!$A17,Data!$CV:$CV)+'Rate History'!$C$6*SUMIF(Data!$G:$G,Neutral!$A17,Data!$CW:$CW)+'Rate History'!$C$7*SUMIF(Data!$G:$G,Neutral!$A17,Data!$CX:$CX)+'Rate History'!$C$8*SUMIF(Data!$G:$G,Neutral!$A17,Data!$CY:$CY)+'Rate History'!$C$9*SUMIF(Data!$G:$G,Neutral!$A17,Data!$CZ:$CZ)+'Rate History'!$C$10*SUMIF(Data!$G:$G,Neutral!$A17,Data!$DA:$DA)+'Rate History'!$C$11*SUMIF(Data!$G:$G,Neutral!$A17,Data!$DB:$DB)+'Rate History'!$C$12*SUMIF(Data!$G:$G,Neutral!$A17,Data!$DC:$DC)+'Rate History'!$C$13*SUMIF(Data!$G:$G,Neutral!$A17,Data!$DD:$DD)+'Rate History'!$C$14*SUMIF(Data!$G:$G,Neutral!$A17,Data!$DE:$DE)+'Rate History'!$C$15*SUMIF(Data!$G:$G,Neutral!$A17,Data!$DF:$DF)+'Rate History'!$C$16*SUMIF(Data!$G:$G,Neutral!$A17,Data!$DG:$DG)+'Rate History'!$C$17*SUMIF(Data!$G:$G,Neutral!$A17,Data!$DH:$DH)+'Rate History'!$C$18*SUMIF(Data!$G:$G,Neutral!$A17,Data!$DI:$DI)+'Rate History'!$C$19*SUMIF(Data!$G:$G,Neutral!$A17,Data!$DJ:$DJ)+'Rate History'!$C$20*SUMIF(Data!$G:$G,Neutral!$A17,Data!$DK:$DK)+'Rate History'!$C$21*SUMIF(Data!$G:$G,Neutral!$A17,Data!$DL:$DL)+'Rate History'!$C$22*SUMIF(Data!$G:$G,Neutral!$A17,Data!$DM:$DM)+'Rate History'!$C$23*SUMIF(Data!$G:$G,Neutral!$A17,Data!$DN:$DN)+'Rate History'!$C$24*SUMIF(Data!$G:$G,Neutral!$A17,Data!$DO:$DO)+'Rate History'!$C$25*SUMIF(Data!$G:$G,Neutral!$A17,Data!$DP:$DP)+'Rate History'!$C$26*SUMIF(Data!$G:$G,Neutral!$A17,Data!$DQ:$DQ)+'Rate History'!$C$27*SUMIF(Data!$G:$G,Neutral!$A17,Data!$DR:$DR)+'Rate History'!$C$28*SUMIF(Data!$G:$G,Neutral!$A17,Data!$DS:$DS)+'Rate History'!$C$29*SUMIF(Data!$G:$G,Neutral!$A17,Data!$DT:$DT)+'Rate History'!$C$30*SUMIF(Data!$G:$G,Neutral!$A17,Data!$DV:$DV)+'Rate History'!$C$31*SUMIF(Data!$G:$G,Neutral!$A17,Data!$DW:$DW)) -> 5847465.2 | D17: =C17-B17 -> 10405.14 | E17: =IFERROR(D17/B17,"") -> 0.0017825995
... A62: Lamar State College-Port Arthur | B62: =$B$5*('Rate History'!$D$4*SUMIF(Data!$G:$G,Neutral!$A62,Data!$CU:$CU)+'Rate History'!$D$5*SUMIF(Data!$G:$G,Neutral!$A62,Data!$CV:$CV)+'Rate History'!$D$6*SUMIF(Data!$G:$G,Neutral!$A62,Data!$CW:$CW)+'Rate History'!$D$7*SUMIF(Data!$G:$G,Neutral!$A62,Data!$CX:$CX)+'Rate History'!$D$8*SUMIF(Data!$G:$G,Neutral!$A62,Data!$CY:$CY)+'Rate History'!$D$9*SUMIF(Data!$G:$G,Neutral!$A62,Data!$CZ:$CZ)+'Rate History'!$D$10*SUMIF(Data!$G:$G,Neutral!$A62,Data!$DA:$DA)+'Rate History'!$D$11*SUMIF(Data!$G:$G,Neutral!$A62,Data!$DB:$DB)+'Rate History'!$D$12*SUMIF(Data!$G:$G,Neutral!$A62,Data!$DC:$DC)+'Rate History'!$D$13*SUMIF(Data!$G:$G,Neutral!$A62,Data!$DD:$DD)+'Rate History'!$D$14*SUMIF(Data!$G:$G,Neutral!$A62,Data!$DE:$DE)+'Rate History'!$D$15*SUMIF(Data!$G:$G,Neutral!$A62,Data!$DF:$DF)+'Rate History'!$D$16*SUMIF(Data!$G:$G,Neutral!$A62,Data!$DG:$DG)+'Rate History'!$D$17*SUMIF(Data!$G:$G,Neutral!$A62,Data!$DH:$DH)+'Rate History'!$D$18*SUMIF(Data!$G:$G,Neutral!$A62,Data!$DI:$DI)+'Rate History'!$D$19*SUMIF(Data!$G:$G,Neutral!$A62,Data!$DJ:$DJ)+'Rate History'!$D$20*SUMIF(Data!$G:$G,Neutral!$A62,Data!$DK:$DK)+'Rate History'!$D$21*SUMIF(Data!$G:$G,Neutral!$A62,Data!$DL:$DL)+'Rate History'!$D$22*SUMIF(Data!$G:$G,Neutral!$A62,Data!$DM:$DM)+'Rate History'!$D$23*SUMIF(Data!$G:$G,Neutral!$A62,Data!$DN:$DN)+'Rate History'!$D$24*SUMIF(Data!$G:$G,Neutral!$A62,Data!$DO:$DO)+'Rate History'!$D$25*SUMIF(Data!$G:$G,Neutral!$A62,Data!$DP:$DP)+'Rate History'!$D$26*SUMIF(Data!$G:$G,Neutral!$A62,Data!$DQ:$DQ)+'Rate History'!$D$27*SUMIF(Data!$G:$G,Neutral!$A62,Data!$DR:$DR)+'Rate History'!$D$28*SUMIF(Data!$G:$G,Neutral!$A62,Data!$DS:$DS)+'Rate History'!$D$29*SUMIF(Data!$G:$G,Neutral!$A62,Data!$DT:$DT)+'Rate History'!$D$30*SUMIF(Data!$G:$G,Neutral!$A62,Data!$DV:$DV)+'Rate History'!$D$31*SUMIF(Data!$G:$G,Neutral!$A62,Data!$DW:$DW)) -> 5627160.8 | C62: =$C$5*('Rate History'!$C$4*SUMIF(Data!$G:$G,Neutral!$A62,Data!$CU:$CU)+'Rate History'!$C$5*SUMIF(Data!$G:$G,Neutral!$A62,Data!$CV:$CV)+'Rate History'!$C$6*SUMIF(Data!$G:$G,Neutral!$A62,Data!$CW:$CW)+'Rate History'!$C$7*SUMIF(Data!$G:$G,Neutral!$A62,Data!$CX:$CX)+'Rate History'!$C$8*SUMIF(Data!$G:$G,Neutral!$A62,Data!$CY:$CY)+'Rate History'!$C$9*SUMIF(Data!$G:$G,Neutral!$A62,Data!$CZ:$CZ)+'Rate History'!$C$10*SUMIF(Data!$G:$G,Neutral!$A62,Data!$DA:$DA)+'Rate History'!$C$11*SUMIF(Data!$G:$G,Neutral!$A62,Data!$DB:$DB)+'Rate History'!$C$12*SUMIF(Data!$G:$G,Neutral!$A62,Data!$DC:$DC)+'Rate History'!$C$13*SUMIF(Data!$G:$G,Neutral!$A62,Data!$DD:$DD)+'Rate History'!$C$14*SUMIF(Data!$G:$G,Neutral!$A62,Data!$DE:$DE)+'Rate History'!$C$15*SUMIF(Data!$G:$G,Neutral!$A62,Data!$DF:$DF)+'Rate History'!$C$16*SUMIF(Data!$G:$G,Neutral!$A62,Data!$DG:$DG)+'Rate History'!$C$17*SUMIF(Data!$G:$G,Neutral!$A62,Data!$DH:$DH)+'Rate History'!$C$18*SUMIF(Data!$G:$G,Neutral!$A62,Data!$DI:$DI)+'Rate History'!$C$19*SUMIF(Data!$G:$G,Neutral!$A62,Data!$DJ:$DJ)+'Rate History'!$C$20*SUMIF(Data!$G:$G,Neutral!$A62,Data!$DK:$DK)+'Rate History'!$C$21*SUMIF(Data!$G:$G,Neutral!$A62,Data!$DL:$DL)+'Rate History'!$C$22*SUMIF(Data!$G:$G,Neutral!$A62,Data!$DM:$DM)+'Rate History'!$C$23*SUMIF(Data!$G:$G,Neutral!$A62,Data!$DN:$DN)+'Rate History'!$C$24*SUMIF(Data!$G:$G,Neutral!$A62,Data!$DO:$DO)+'Rate History'!$C$25*SUMIF(Data!$G:$G,Neutral!$A62,Data!$DP:$DP)+'Rate History'!$C$26*SUMIF(Data!$G:$G,Neutral!$A62,Data!$DQ:$DQ)+'Rate History'!$C$27*SUMIF(Data!$G:$G,Neutral!$A62,Data!$DR:$DR)+'Rate History'!$C$28*SUMIF(Data!$G:$G,Neutral!$A62,Data!$DS:$DS)+'Rate History'!$C$29*SUMIF(Data!$G:$G,Neutral!$A62,Data!$DT:$DT)+'Rate History'!$C$30*SUMIF(Data!$G:$G,Neutral!$A62,Data!$DV:$DV)+'Rate History'!$C$31*SUMIF(Data!$G:$G,Neutral!$A62,Data!$DW:$DW)) -> 5640689.1 | D62: =C62-B62 -> 13528.306 | E62: =IFERROR(D62/B62,"") -> 0.0024041086
A63: Total | B63: =SUM(B5:B62) -> 9.185226e+08 | C63: =SUM(C6:C62) -> 9.185226e+08 | D63: =C63-B63 -> 0 | E63: =IFERROR(D63/B63,"") -> 0

Sheet 1
A1: =Summary!A1 -> Community and Technical Colleges, Report of Fundable Operating Expenses, Fiscal Year (FY) 2012
A2: 003607 | B2: =VLOOKUP(A2,Data!A:G,7,0) -> Alamo Community College District
F3: =IFERROR(VLOOKUP(A2,Data!A:C,3,0),"0") -> 1
A4: Fund | B4: Total Expense by Discipline | D4: Contact Hours | E4: Expense | F4: Expense per Contact Hour
A5: 1 | B5: Agriculture | D5: =D36 -> 88855 | E5: =E36+E67+IFERROR($E$105/$D$105*D5,0) -> 579507.26 | F5: =IFERROR(E5/D5,"") -> 6.5219432
A6: 2 | B6: Architecture and Precision Production Trades | D6: =D37 -> 168013 | E6: =E37+E68+IFERROR($E$105/$D$105*D6,0) -> 1692128.8 | F6: =IFERROR(E6/D6,"") -> 10.071416
A7: 3 | B7: Biology, Physical Sciences, and Science Technology | D7: =D38 -> 2652208 | E7: =E38+E69+IFERROR($E$105/$D$105*D7,0) -> 23222862 | F7: =IFERROR(E7/D7,"") -> 8.7560484
A8: 4 | B8: Business Management, Marketing, and Administrative Services | D8: =D39 -> 986266 | E8: =E39+E70+IFERROR($E$105/$D$105*D8,0) -> 9003202.2 | F8: =IFERROR(E8/D8,"") -> 9.128574
A9: 5 | B9: Career Pilot | D9: =D40 -> 13328 | E9: =E40+E71+IFERROR($E$105/$D$105*D9,0) -> 481059.94 | F9: =IFERROR(E9/D9,"") -> 36.093933
A10: 6 | B10: Communications | D10: =D41 -> 290715 | E10: =E41+E72+IFERROR($E$105/$D$105*D10,0) -> 2572331.8 | F10: =IFERROR(E10/D10,"") -> 8.848294
A11: 7 | B11: Computer and Information Sciences | D11: =D42 -> 778512 | E11: =E42+E73+IFERROR($E$105/$D$105*D11,0) -> 9314217.1 | F11: =IFERROR(E11/D11,"") -> 11.964128
A12: 8 | B12: Construction Trades | D12: =D43 -> 57269 | E12: =E43+E74+IFERROR($E$105/$D$105*D12,0) -> 530513.39 | F12: =IFERROR(E12/D12,"") -> 9.2635351
A13: 9 | B13: Consumer and Homemaking Education | D13: =D44 -> 597664 | E13: =E44+E75+IFERROR($E$105/$D$105*D13,0) -> 5191798.9 | F13: =IFERROR(E13/D13,"") -> 8.6868189
A14: 10 | B14: Engineering | D14: =D45 -> 29760 | E14: =E45+E76+IFERROR($E$105/$D$105*D14,0) -> 477073.63 | F14: =IFERROR(E14/D14,"") -> 16.0307
A15: 11 | B15: Engineering Related | D15: =D46 -> 325157 | E15: =E46+E77+IFERROR($E$105/$D$105*D15,0) -> 3573602.9 | F15: =IFERROR(E15/D15,"") -> 10.990392
A16: 12 | B16: English Language, Lit, Philosophy, Humanities, & Interdisciplinary | D16: =D47 -> 2916711 | E16: =E47+E78+IFERROR($E$105/$D$105*D16,0) -> 25076648 | F16: =IFERROR(E16/D16,"") -> 8.5975772
... A32: 29 | B32: Developmental Education - Reading/Writing | D32: =D63 -> 1552928 | E32: =E63+E94+IFERROR($E$105/$D$105*D32,0) -> 12579131 | F32: =IFERROR(E32/D32,"") -> 8.1002669
C33: Total | D33: =SUM(D5:D32) -> 23493357 | E33: =SUM(E5:E32) -> 209097769 | F33: =IFERROR(E33/D33,"") -> 8.9002933
A35: Fund | B35: Departmental Operating Expense by Discipline | D35: Contact Hours | E35: Expense | F35: Expense per Contact Hour
A36: 1 | B36: Agriculture | D36: =IF(F3="1",SUMIF(Data!A:A,$A$2,Data!CU:CU),0) -> 88855 | E36: =IF(F3="1",SUMIF(Data!$A:$A,$A$2,Data!IO:IO),0) -> 90393 | F36: =IFERROR(E36/D36,"") -> 1.0173091
A37: 2 | B37: Architecture and Precision Production Trades | D37: =IF(F3="1",SUMIF(Data!A:A,$A$2,Data!CV:CV),0) -> 168013 | E37: =IF(F3="1",SUMIF(Data!$A:$A,$A$2,Data!IP:IP),0) -> 253317 | F37: =IFERROR(E37/D37,"") -> 1.5077226
A38: 3 | B38: Biology, Physical Sciences, and Science Technology | D38: =IF(F3="1",SUMIF(Data!A:A,$A$2,Data!CW:CW),0) -> 2652208 | E38: =IF(F3="1",SUMIF(Data!$A:$A,$A$2,Data!IQ:IQ),0) -> 3541146 | F38: =IFERROR(E38/D38,"") -> 1.335169
A39: 4 | B39: Business Management, Marketing, and Administrative Services | D39: =IF(F3="1",SUMIF(Data!A:A,$A$2,Data!CX:CX),0) -> 986266 | E39: =IF(F3="1",SUMIF(Data!$A:$A,$A$2,Data!IR:IR),0) -> 1483049 | F39: =IFERROR(E39/D39,"") -> 1.5037008
A40: 5 | B40: Career Pilot | D40: =IF(F3="1",SUMIF(Data!A:A,$A$2,Data!CY:CY),0) -> 13328 | E40: =IF(F3="1",SUMIF(Data!$A:$A,$A$2,Data!IS:IS),0) -> 350640 | F40: =IFERROR(E40/D40,"") -> 26.308523
A41: 6 | B41: Communications | D41: =IF(F3="1",SUMIF(Data!A:A,$A$2,Data!CZ:CZ),0) -> 290715 | E41: =IF(F3="1",SUMIF(Data!$A:$A,$A$2,Data!IT:IT),0) -> 526845 | F41: =IFERROR(E41/D41,"") -> 1.8122388
A42: 7 | B42: Computer and Information Sciences | D42: =IF(F3="1",SUMIF(Data!A:A,$A$2,Data!DA:DA),0) -> 778512 | E42: =IF(F3="1",SUMIF(Data!$A:$A,$A$2,Data!IU:IU),0) -> 1829705 | F42: =IFERROR(E42/D42,"") -> 2.3502592
A43: 8 | B43: Construction Trades | D43: =IF(F3="1",SUMIF(Data!A:A,$A$2,Data!DB:DB),0) -> 57269 | E43: =IF(F3="1",SUMIF(Data!$A:$A,$A$2,Data!IV:IV),0) -> 99792 | F43: =IFERROR(E43/D43,"") -> 1.7425134
A44: 9 | B44: Consumer and Homemaking Education | D44: =IF(F3="1",SUMIF(Data!A:A,$A$2,Data!DC:DC),0) -> 597664 | E44: =IF(F3="1",SUMIF(Data!$A:$A,$A$2,Data!IW:IW),0) -> 1253186 | F44: =IFERROR(E44/D44,"") -> 2.0968069
A45: 10 | B45: Engineering | D45: =IF(F3="1",SUMIF(Data!A:A,$A$2,Data!DD:DD),0) -> 29760 | E45: =IF(F3="1",SUMIF(Data!$A:$A,$A$2,Data!IX:IX),0) -> 103507 | F45: =IFERROR(E45/D45,"") -> 3.4780578
A46: 11 | B46: Engineering Related | D46: =IF(F3="1",SUMIF(Data!A:A,$A$2,Data!DE:DE),0) -> 325157 | E46: =IF(F3="1",SUMIF(Data!$A:$A,$A$2,Data!IY:IY),0) -> 952517 | F46: =IFERROR(E46/D46,"") -> 2.9294064
A47: 12 | B47: English Language, Lit, Philosophy, Humanities, & Interdisciplinary | D47: =IF(F3="1",SUMIF(Data!A:A,$A$2,Data!DF:DF),0) -> 2916711 | E47: =IF(F3="1",SUMIF(Data!$A:$A,$A$2,Data!IZ:IZ),0) -> 4090839 | F47: =IFERROR(E47/D47,"") -> 1.4025521
A48: 13 | B48: Foreign Languages | D48: =IF(F3="1",SUMIF(Data!A:A,$A$2,Data!DG:DG),0) -> 819776 | E48: =IF(F3="1",SUMIF(Data!$A:$A,$A$2,Data!JA:JA),0) -> 1182168 | F48: =IFERROR(E48/D48,"") -> 1.4420622
A49: 14 | B49: Health Occupations - Dental Assistants, Medical Lab, and Assoc. Degree Nursing | D49: =IF(F3="1",SUMIF(Data!A:A,$A$2,Data!DH:DH),0) -> 583044 | E49: =IF(F3="1",SUMIF(Data!$A:$A,$A$2,Data!JB:JB),0) -> 3103236 | F49: =IFERROR(E49/D49,"") -> 5.3224731
A50: 15 | B50: Health Occupations - Dental Hygiene | D50: =IF(F3="1",SUMIF(Data!A:A,$A$2,Data!DI:DI),0) -> 0 | E50: =IF(F3="1",SUMIF(Data!$A:$A,$A$2,Data!JC:JC),0) -> 0 | F50: =IFERROR(E50/D50,"")
A51: 16 | B51: Health Occupations - Other | D51: =IF(F3="1",SUMIF(Data!A:A,$A$2,Data!DJ:DJ),0) -> 787317 | E51: =IF(F3="1",SUMIF(Data!$A:$A,$A$2,Data!JD:JD),0) -> 1668313 | F51: =IFERROR(E51/D51,"") -> 2.1189851
A52: 17 | B52: Health Occupations - Respiratory Therapy | D52: =IF(F3="1",SUMIF(Data!A:A,$A$2,Data!DK:DK),0) -> 48784 | E52: =IF(F3="1",SUMIF(Data!$A:$A,$A$2,Data!JE:JE),0) -> 145335 | F52: =IFERROR(E52/D52,"") -> 2.979153
A53: 18 | B53: Health Occupations - Vocational Nursing | D53: =IF(F3="1",SUMIF(Data!A:A,$A$2,Data!DL:DL),0) -> 224528 | E53: =IF(F3="1",SUMIF(Data!$A:$A,$A$2,Data!JF:JF),0) -> 459027 | F53: =IFERROR(E53/D53,"") -> 2.0444087
A54: 19 | B54: Mathematics | D54: =IF(F3="1",SUMIF(Data!A:A,$A$2,Data!DM:DM),0) -> 1411724 | E54: =IF(F3="1",SUMIF(Data!$A:$A,$A$2,Data!JG:JG),0) -> 1844668 | F54: =IFERROR(E54/D54,"") -> 1.3066775
A55: 20 | B55: Mechanics and Repairers - Automotive | D55: =IF(F3="1",SUMIF(Data!A:A,$A$2,Data!DN:DN),0) -> 241481 | E55: =IF(F3="1",SUMIF(Data!$A:$A,$A$2,Data!JH:JH),0) -> 504075 | F55: =IFERROR(E55/D55,"") -> 2.0874313
A56: 21 | B56: Mechanics and Repairers - Diesel, Aviation Mechanics, and Transportation Workers | D56: =IF(F3="1",SUMIF(Data!A:A,$A$2,Data!DO:DO),0) -> 234299 | E56: =IF(F3="1",SUMIF(Data!$A:$A,$A$2,Data!JI:JI),0) -> 313884 | F56: =IFERROR(E56/D56,"") -> 1.3396728
A57: 22 | B57: Mechanics and Repairers - Electronics | D57: =IF(F3="1",SUMIF(Data!A:A,$A$2,Data!DP:DP),0) -> 73453 | E57: =IF(F3="1",SUMIF(Data!$A:$A,$A$2,Data!JJ:JJ),0) -> 30066 | F57: =IFERROR(E57/D57,"") -> 0.40932297
A58: 23 | B58: Physical Education and Fitness | D58: =IF(F3="1",SUMIF(Data!A:A,$A$2,Data!DQ:DQ),0) -> 727248 | E58: =IF(F3="1",SUMIF(Data!$A:$A,$A$2,Data!JK:JK),0) -> 1072949 | F58: =IFERROR(E58/D58,"") -> 1.475355
