Workbook
Name a: #REF!
Name aaa: #REF!
Name asdf: #REF!
Name asdf: #REF!
Name asdf: #REF!
Name bnm: #REF!
Name bnm: #REF!
Name bnm: #REF!
Name Initial: #REF!
Name Initial: #REF!
Name Initial: #REF!
Name MSN_MoneyCentral_Investor_Stock_Quotes: 'Holdings Pull Sheet'!$C$9:$R$47
Name portbeg: #REF!
Name portbeg: #REF!
Name portbeg: #REF!
Name qwer: #REF!
Name qwer: #REF!
Name qwer: #REF!
Name s: #REF!
Name Sheet: #REF!
Name Sheet: #REF!
Name Sheet: #REF!
Name SP: #REF!
Name SP: #REF!
Name SP: #REF!
Name spbeg: #REF!
Name spbeg: #REF!
Name spbeg: #REF!
Name vb: #REF!
Name vb: #REF!
Name vb: #REF!
Name WINBEG: #REF!
Name WINBEG: #REF!
Name WINBEG: #REF!
Name WINSP: #REF!
Name WINSP: #REF!
Name WINSP: #REF!
Name zxc: #REF!
Name zxc: #REF!
Name zxc: #REF!

Sheet Summary
L3: School Year | S3: 1 Week | Z3: Today | AG3: IPO Return since 5/02/03 | AH3: =Holdings!$I$24/Data!$D$3 -> 2.6733485
L4: IPO | M4: =Holdings!$S$24 -> 0.18318074 | S4: IPO | T4: ='V.P. of PM'!E21 -> -0.018396275 | Z4: IPO | AA4: =Holdings!$U$24 -> -0.016800915 | AG4: S&P 500 since 5/02/03 | AH4: ='Holdings Pull Sheet'!$F$14/Data!$L$3 -> 2.0731657
L6: S&P 500 | M6: =('Holdings Pull Sheet'!$F$14/Data!$L$530)-1 -> 0.16502526 | S6: S&P 500 | T6: ='V.P. of PM'!F21 -> -0.012270234 | Z6: S&P 500 | AA6: =('Holdings Pull Sheet'!$F$14/'Holdings Pull Sheet'!$G$14)-1 -> -0.020661388 | AG6: Total IPO Portfolio Value | AH6: =Holdings!$I$24 -> 61101.652
L8: Dow Jones | M8: =('Holdings Pull Sheet'!$F$12/Data!$S$530)-1 -> 0.11526509 | S8: Dow Jones | T8: =OFFSET(Data!T3,MATCH('V.P. of PM'!H3,Data!B3:B1000,0)-1,,) -> -0.0040915924 | Z8: Dow Jones | AA8: =('Holdings Pull Sheet'!$F$12/'Holdings Pull Sheet'!$G$12)-1 -> -0.019710819 | AE8: Cash Availailable | AH8: =Holdings!$I$4 -> 8050.26
AE9: % of Portfolio | AH9: =Holdings!$W$4 -> 0.13175192
C13: =Holdings!$C$5 -> Berkshire Hathaway | F13: =Holdings!$E$5 -> 137.09 | J13: =Holdings!$C$9 -> Delta Airlines | M13: =Holdings!$E$9 -> 33.71 | Q13: =Holdings!$C$13 -> Intel | T13: =Holdings!$E$13 -> 33.62 | X13: =Holdings!$C$17 -> Range Resources | AA13: =Holdings!$E$17 -> 63.46 | AE13: =Holdings!$C$21 -> Wells Fargo | AH13: =Holdings!$E$21 -> 51.12
C15: =Holdings!$D$5 -> BRK.B | E15: Today | F15: =Holdings!$U$5 -> -0.020365871 | J15: =Holdings!$D$9 -> DAL | L15: Today | M15: =Holdings!$U$9 -> -0.031600115 | Q15: =Holdings!$D$13 -> INTC | S15: Today | T15: =Holdings!$U$13 -> -0.018967027 | X15: =Holdings!$D$17 -> RRC | Z15: Today | AA15: =Holdings!$U$17 -> -0.032636877 | AE15: =Holdings!$D$21 -> WFC | AG15: Today | AH15: =Holdings!$U$21 -> -0.019750719
E16: 1 Week | F16: =Holdings!$T$5 -> 0.062219123 | L16: 1 Week | M16: =Holdings!$T$9 -> -0.090110729 | S16: 1 Week | T16: =Holdings!$T$13 -> 0.27943797 | Z16: 1 Week | AA16: =Holdings!$T$17 -> -0.28880421 | AG16: 1 Week | AH16: =Holdings!$T$21 -> 0.038410396
E17: =L3 -> School Year | F17: =Holdings!$S$5 -> 0.2210742 | L17: =$E$17 -> School Year | M17: =Holdings!$S$9 -> 0.6757893 | S17: =$E$17 -> School Year | T17: =Holdings!$S$13 -> 0.52561959 | Z17: =$E$17 -> School Year | AA17: =Holdings!$S$17 -> -0.26524604 | AG17: =$E$17 -> School Year | AH17: =Holdings!$S$21 -> 0.24902756
E18: Total Gain | F18: =Holdings!$P$5 -> 0.75144097 | L18: Total Gain | M18: =Holdings!$P$9 -> 1.0508584 | S18: Total Gain | T18: =Holdings!$P$13 -> 0.40864565 | Z18: Total Gain | AA18: =Holdings!$P$17 -> -0.26524604 | AG18: Total Gain | AH18: =Holdings!$P$21 -> 1.2920531
C20: =IF(C21=0,"NA", IF(C21<2,"Small", IF(C21<10, "Mid", IF(C21>10, "Large")))) -> Large | E20: Value | F20: =Holdings!$I$5 -> 3564.34 | J20: =IF(J21=0,"NA", IF(J21<2,"Small", IF(J21<10, "Mid", IF(J21>10, "Large")))) -> Large | L20: Value | M20: =Holdings!$I$9 -> 5090.21 | Q20: =IF(Q21=0,"NA", IF(Q21<2,"Small", IF(Q21<10, "Mid", IF(Q21>10, "Large")))) -> Large | S20: Value | T20: =Holdings!$I$13 -> 3899.92 | X20: =IF(X21=0,"NA", IF(X21<2,"Small", IF(X21<10, "Mid", IF(X21>10, "Large")))) -> Large | Z20: Value | AA20: =Holdings!$I$17 -> 2665.32 | AE20: =IF(AE21=0,"NA", IF(AE21<2,"Small", IF(AE21<10, "Mid", IF(AE21>10, "Large")))) -> Large | AG20: Value | AH20: =Holdings!$I$21 -> 2760.48
C21: =Holdings!$X$5 -> 319.36477 | E21: Cost | F21: =Holdings!$H$5 -> 2035.09 | J21: =Holdings!$X$9 -> 28.24913 | L21: Cost | M21: =Holdings!$H$9 -> 2481.99 | Q21: =Holdings!$X$13 -> 166.45262 | S21: Cost | T21: =Holdings!$H$13 -> 2768.56 | X21: =Holdings!$X$17 -> 10.700487 | Z21: Cost | AA21: =Holdings!$H$17 -> 3627.5 | AE21: =Holdings!$X$21 -> 266.97162 | AG21: Cost | AH21: =Holdings!$H$21 -> 1204.37
E23: % of Portfolio | F23: =F20/$AH$6 -> 0.058334593 | L23: % of Portfolio | M23: =M20/$AH$6 -> 0.08330724 | S23: % of Portfolio | T23: =T20/$AH$6 -> 0.063826752 | Z23: % of Portfolio | AA23: =AA20/$AH$6 -> 0.043621079 | AG23: % of Portfolio | AH23: =AH20/$AH$6 -> 0.045178484
C27: =Holdings!$C$6 -> BlackRock Global | F27: =Holdings!$E$6 -> 20.42 | J27: =Holdings!$C$10 -> Gentex | M27: =Holdings!$E$10 -> 27.61 | Q27: =Holdings!$C$14 -> Medtronic | T27: =Holdings!$E$14 -> 63.65 | X27: =Holdings!$C$18 -> Tutor Perini | AA27: =Holdings!$E$18 -> 24.07 | AE27: =Holdings!$C$22 -> Yahoo | AH27: =Holdings!$E$22 -> 41.1
C29: =Holdings!$D$6 -> MCLOX | E29: Today | F29: =Holdings!$U$6 -> -0.013561025 | J29: =Holdings!$D$10 -> GNTX | L29: Today | M29: =Holdings!$U$10 -> -0.024036762 | Q29: =Holdings!$D$14 -> MDT | S29: Today | T29: =Holdings!$U$14 -> -0.031644607 | X29: =Holdings!$D$18 -> TPC | Z29: Today | AA29: =Holdings!$U$18 -> -0.026688233 | AE29: =Holdings!$D$22 -> YHOO | AG29: Today | AH29: =Holdings!$U$22 -> 0.00048685492
E30: 1 Week | F30: =Holdings!$T$6 -> 0.029847908 | L30: 1 Week | M30: =Holdings!$T$10 -> -0.044735959 | S30: 1 Week | T30: =Holdings!$T$14 -> 0.082527699 | Z30: 1 Week | AA30: =Holdings!$T$18 -> -0.1982012 | AG30: 1 Week | AH30: =Holdings!$T$22 -> 0.12571898
E31: =$E$17 -> School Year | F31: =Holdings!$S$6 -> 0.10967687 | L31: =$E$17 -> School Year | M31: =Holdings!$S$10 -> 0.15972247 | S31: =$E$17 -> School Year | T31: =Holdings!$S$14 -> 0.20613582 | Z31: =$E$17 -> School Year | AA31: =Holdings!$S$18 -> 0.2885439 | AG31: =$E$17 -> School Year | AH31: =Holdings!$S$22 -> 0.45589798
E32: Total Gain | F32: =Holdings!$P$6 -> 0.25222698 | L32: Total Gain | M32: =Holdings!$P$10 -> 0.74589809 | S32: Total Gain | T32: =Holdings!$P$14 -> 0.38711665 | Z32: Total Gain | AA32: =Holdings!$P$18 -> 0.74912072 | AG32: Total Gain | AH32: =Holdings!$P$22 -> 0.88966386
C34: =IF(C35=0,"NA", IF(C35<2,"Small", IF(C35<10, "Mid", IF(C35>10, "Large")))) -> NA | E34: Value | F34: =Holdings!$I$6 -> 1932.7122 | J34: =IF(J35=0,"NA", IF(J35<2,"Small", IF(J35<10, "Mid", IF(J35>10, "Large")))) -> Mid | L34: Value | M34: =Holdings!$I$10 -> 2622.95 | Q34: =IF(Q35=0,"NA", IF(Q35<2,"Small", IF(Q35<10, "Mid", IF(Q35>10, "Large")))) -> Large | S34: Value | T34: =Holdings!$I$14 -> 1845.85 | X34: =IF(X35=0,"NA", IF(X35<2,"Small", IF(X35<10, "Mid", IF(X35>10, "Large")))) -> Small | Z34: Value | AA34: =Holdings!$I$18 -> 4814 | AE34: =IF(AE35=0,"NA", IF(AE35<2,"Small", IF(AE35<10, "Mid", IF(AE35>10, "Large")))) -> Large | AG34: Value | AH34: =Holdings!$I$22 -> 4110
C35: =Holdings!$X$6 -> 0 | E35: Cost | F35: =Holdings!$H$6 -> 1543.42 | J35: =Holdings!$X$10 -> 4.0367771 | L35: Cost | M35: =Holdings!$H$10 -> 1502.35 | Q35: =Holdings!$X$14 -> 62.356015 | S35: Cost | T35: =Holdings!$H$14 -> 1330.71 | X35: =Holdings!$X$18 -> 1.1691218 | Z35: Cost | AA35: =Holdings!$H$18 -> 2752.24 | AE35: =Holdings!$X$22 -> 40.878216 | AG35: Cost | AH35: =Holdings!$H$22 -> 2174.99
E37: % of Portfolio | F37: =F34/$AH$6 -> 0.031631095 | L37: % of Portfolio | M37: =M34/$AH$6 -> 0.042927644 | S37: % of Portfolio | T37: =T34/$AH$6 -> 0.030209494 | Z37: % of Portfolio | AA37: =AA34/$AH$6 -> 0.07878674 | AG37: % of Portfolio | AH37: =AH34/$AH$6 -> 0.067264957
C41: =Holdings!$C$7 -> Cemex | F41: =Holdings!$E$7 -> 12.2 | J41: =Holdings!$C$11 -> Home Depot | M41: =Holdings!$E$11 -> 93.07 | Q41: =Holdings!$C$15 -> Natural Grocers | T41: =Holdings!$E$15 -> 16.19 | X41: =Holdings!$C$19 -> Tyson Foods | AA41: =Holdings!$E$19 -> 40.96
C43: =Holdings!$D$7 -> CX | E43: Today | F43: =Holdings!$U$7 -> -0.026336792 | J43: =Holdings!$D$11 -> HD | L43: Today | M43: =Holdings!$U$11 -> -0.010840684 | Q43: =Holdings!$D$15 -> NGVC | S43: Today | T43: =Holdings!$U$15 -> -0.040876777 | X43: =Holdings!$D$19 -> TSN | Z43: Today | AA43: =Holdings!$U$19 -> -0.013487476
E44: 1 Week | F44: =Holdings!$T$7 -> -0.0079749805 | L44: 1 Week | M44: =Holdings!$T$11 -> 0.18731205 | S44: 1 Week | T44: =Holdings!$T$15 -> -0.55643836 | Z44: 1 Week | AA44: =Holdings!$T$19 -> -0.02999621
E45: =$E$17 -> School Year | F45: =Holdings!$S$7 -> 0.14409378 | L45: =$E$17 -> School Year | M45: =Holdings!$S$11 -> 0.30319975 | S45: =$E$17 -> School Year | T45: =Holdings!$S$15 -> -0.56243243 | Z45: =$E$17 -> School Year | AA45: =Holdings!$S$19 -> 0.38094724
E46: Total Gain | F46: =Holdings!$P$7 -> 0.13363449 | L46: Total Gain | M46: =Holdings!$P$11 -> 2.4021094 | S46: Total Gain | T46: =Holdings!$P$15 -> -0.17493375 | Z46: Total Gain | AA46: =Holdings!$P$19 -> 1.4943551
C48: =IF(C49=0,"NA", IF(C49<2,"Small", IF(C49<10, "Mid", IF(C49>10, "Large")))) -> Large | E48: Value | F48: =Holdings!$I$7 -> 3172 | J48: =IF(J49=0,"NA", IF(J49<2,"Small", IF(J49<10, "Mid", IF(J49>10, "Large")))) -> Large | L48: Value | M48: =Holdings!$I$11 -> 5677.27 | Q48: =IF(Q49=0,"NA", IF(Q49<2,"Small", IF(Q49<10, "Mid", IF(Q49>10, "Large")))) -> Small | S48: Value | T48: =Holdings!$I$15 -> 1214.25 | X48: =IF(X49=0,"NA", IF(X49<2,"Small", IF(X49<10, "Mid", IF(X49>10, "Large")))) -> Large | Z48: Value | AA48: =Holdings!$I$19 -> 4177.92
C49: =Holdings!$X$7 -> 14.494177 | E49: Cost | F49: =Holdings!$H$7 -> 2798.08 | J49: =Holdings!$X$11 -> 125.26492 | L49: Cost | M49: =Holdings!$H$11 -> 1668.75 | Q49: =Holdings!$X$15 -> 0.36391769 | S49: Cost | T49: =Holdings!$H$15 -> 1471.7 | X49: =Holdings!$X$19 -> 14.405563 | Z49: Cost | AA49: =Holdings!$H$19 -> 1674.95
E51: % of Portfolio | F51: =F48/$AH$6 -> 0.05191349 | L51: % of Portfolio | M51: =M48/$AH$6 -> 0.092915163 | S51: % of Portfolio | T51: =T48/$AH$6 -> 0.019872621 | Z51: % of Portfolio | AA51: =AA48/$AH$6 -> 0.068376547
C55: =Holdings!$C$8 -> Cisco | F55: =Holdings!$E$8 -> 24.19 | J55: =Holdings!$C$12 -> Immersion | M55: =Holdings!$E$12 -> 7.91 | Q55: =Holdings!$C$16 -> Perrigo | T55: =Holdings!$E$16 -> 152.39
C57: =Holdings!$D$8 -> CSCO | E57: Today | F57: =Holdings!$U$8 -> -0.019059205 | J57: =Holdings!$D$12 -> IMMR | L57: Today | M57: =Holdings!$U$12 -> -0.035365854 | Q57: =Holdings!$D$16 -> PRGO | S57: Today | T57: =Holdings!$U$16 -> 0.0063395628
E58: 1 Week | F58: =Holdings!$T$8 -> 0.057992748 | L58: 1 Week | M58: =Holdings!$T$12 -> -0.26623377 | S58: 1 Week | T58: =Holdings!$T$16 -> 0.043044692
E59: =$E$17 -> School Year | F59: =Holdings!$S$8 -> 0.043267944 | L59: =$E$17 -> School Year | M59: =Holdings!$S$12 -> -0.40926064 | S59: =$E$17 -> School Year | T59: =Holdings!$S$16 -> 0.24323883
E60: Total Gain | F60: =Holdings!$P$8 -> 0.35669132 | L60: Total Gain | M60: =Holdings!$P$12 -> -0.47430217 | S60: Total Gain | T60: =Holdings!$P$16 -> 0.24323883
C62: =IF(C63=0,"NA", IF(C63<2,"Small", IF(C63<10, "Mid", IF(C63>10, "Large")))) -> Large | E62: Value | F62: =Holdings!$I$8 -> 1693.3 | J62: =IF(J63=0,"NA", IF(J63<2,"Small", IF(J63<10, "Mid", IF(J63>10, "Large")))) -> Small | L62: Value | M62: =Holdings!$I$12 -> 1067.85 | Q62: =IF(Q63=0,"NA", IF(Q63<2,"Small", IF(Q63<10, "Mid", IF(Q63>10, "Large")))) -> Large | S62: Value | T62: =Holdings!$I$16 -> 2743.02
C63: =Holdings!$X$8 -> 123.34972 | E63: Cost | F63: =Holdings!$H$8 -> 1248.11 | J63: =Holdings!$X$12 -> 0.22590436 | L63: Cost | M63: =Holdings!$H$12 -> 2031.3 | Q63: =Holdings!$X$16 -> 20.392487 | S63: Cost | T63: =Holdings!$H$16 -> 2206.35
E65: % of Portfolio | F65: =F62/$AH$6 -> 0.027712835 | L65: % of Portfolio | M65: =M62/$AH$6 -> 0.017476614 | S65: % of Portfolio | T65: =T62/$AH$6 -> 0.04489273
C69: Bought This Year | Q69: Sold This Year
F71: Date Bought | J71: Buy Price* | L71: Current Price | M71: Change** | T71: Date Sold | X71: Sell Price* | Z71: Current Price | AA71: Change**
D72: =Holdings!C28 -> Tyson Foods | F72: =Holdings!E28 -> 41530 | J72: =Holdings!H28 -> 16.89 | L72: =Holdings!I28 -> 40.96 | M72: =L72/J72-1 -> 1.4251036 | R72: =Holdings!C34 -> Caterpillar | T72: =Holdings!E34 -> 41551 | X72: =Holdings!H34 -> 83.94 | Y72: 19.71 | Z72: =Holdings!I34 -> 93.5 | AA72: =IFERROR((Z72/X72)-1,"NA") -> 0.11389087
D73: =Holdings!C29 -> Perrigo | F73: =Holdings!E29 -> 41544 | J73: =Holdings!H29 -> 167.85 | L73: =Holdings!I29 -> 152.39 | M73: =L73/J73-1 -> -0.092106047 | R73: =Holdings!C35 -> YRC Worldwide | T73: =Holdings!E35 -> 41576 | X73: =Holdings!H35 -> 9.58 | Y73: 20.71 | Z73: =Holdings!I35 -> 17.3 | AA73: =IFERROR((Z73/X73)-1,"NA") -> 0.80584551
D74: =Holdings!C30 -> Range Resources | F74: =Holdings!E30 -> 41698 | J74: =Holdings!H30 -> 86.37 | L74: =Holdings!I30 -> 63.46 | M74: =L74/J74-1 -> -0.26525414 | R74: =Holdings!C36 -> AAPL 515 Apr19 C | T74: =Holdings!E36 -> 41614 | X74: =Holdings!H36 -> 65.8 | Y74: 21.71 | Z74: =Holdings!I36 -> 0 | AA74: =IFERROR((Z74/X74)-1,"NA") -> -1
C76: Proposed Buys This Year That Did Not Pass | Q76: Proposed Sells This Year That Did Not Pass
F78: Date Pitched | J78: Pitch Price | L78: Current Price | M78: Change* | T78: Date Pitched | X78: Pitch Price | Z78: Current Price | AA78: Change*
D79: =Holdings!$C$39 -> NA | F79: =Holdings!$E$39 -> NA | J79: =Holdings!$H$39 -> NA | L79: =Holdings!$I$39 -> NA | M79: =IFERROR((L79/J79)-1,"NA") -> NA | R79: =Holdings!C42 -> NA | T79: =Holdings!E42 -> NA | X79: =Holdings!H42 -> NA | Z79: =Holdings!I42 -> NA | AA79: =IFERROR((Z79/X79)-1,"NA") -> NA
C82: * Weighted-average Buy/Sell Price
C83: **Only incorporates change in price; Does not include commission | AF83: invest@mail.gvsu.edu | AH83: http://gvsu.edu/invest

Sheet Sortable Performnce
C3: 2013 Fall Semester Portfolio Performance
C4: Name | D4: Ticker | E4: Value | F4: % of Port | G4: Today | I4: 1 Week | J4: 2013-2014 School Year | K4: Summer 2013 | L4: Since 4/25/13 | M4: 2012-2013 School Year | N4: Since 9/6/12
C5: =Holdings!#REF! -> #REF! | D5: =IF(Holdings!#REF!=0,"NA",Holdings!#REF!) -> #REF! | E5: =Holdings!#REF! -> #REF! | F5: =Holdings!#REF! -> #REF! | G5: =Holdings!#REF! -> #REF! | H5: =(F5*G5) -> #REF! | I5: =Holdings!#REF! -> #REF! | J5: =Holdings!#REF! -> #REF! | K5: =Holdings!#REF! -> #REF! | L5: =($E5/Holdings!#REF!)-1 -> #REF! | M5: =Holdings!#REF! -> #REF! | N5: =($E5/Holdings!#REF!)-1 -> #REF!
C6: =Holdings!C9 -> Delta Airlines | D6: =IF(Holdings!D9=0,"NA",Holdings!D9) -> DAL | E6: =Holdings!I9 -> 5090.21 | F6: =Holdings!W9 -> 0.08330724 | G6: =Holdings!U9 -> -0.031600115 | H6: =(F6*G6) -> -0.0026325184 | I6: =Holdings!T9 -> -0.090110729 | J6: =Holdings!S9 -> 0.6757893 | K6: =Holdings!R9 -> 0.24309392 | L6: =($E6/Holdings!L9)-1 -> 1.0831635 | M6: =Holdings!Q9 -> -0.015507718 | N6: =($E6/Holdings!K9)-1 -> 1.0508584
C7: =Holdings!C21 -> Wells Fargo | D7: =IF(Holdings!D22=0,"NA",Holdings!D22) -> YHOO | E7: =Holdings!I21 -> 2760.48 | F7: =Holdings!W21 -> 0.045178484 | G7: =Holdings!U21 -> -0.019750719 | H7: =(F7*G7) -> -0.00089230754 | I7: =Holdings!T21 -> 0.038410396 | J7: =Holdings!S21 -> 0.24902756 | K7: =Holdings!R21 -> 0.1265926 | L7: =($E7/Holdings!L21)-1 -> 0.40714521 | M7: =Holdings!Q21 -> 0.10318505 | N7: =($E7/Holdings!K21)-1 -> 0.55234155
C8: =Holdings!C17 -> Range Resources | D8: =IF(Holdings!D18=0,"NA",Holdings!D18) -> TPC | E8: =Holdings!I17 -> 2665.32 | F8: =Holdings!W17 -> 0.043621079 | G8: =Holdings!U17 -> -0.032636877 | H8: =(F8*G8) -> -0.0014236558 | I8: =Holdings!T17 -> -0.28880421 | J8: =Holdings!S17 -> -0.26524604 | K8: =Holdings!R17 -> -0.24713715 | L8: =($E8/Holdings!L17)-1 -> -0.26524604 | M8: =Holdings!Q17 -> 0 | N8: =(($E8/Holdings!K17)-1)*(2/3) -> -0.17683069
C9: =Holdings!C16 -> Perrigo | D9: =IF(Holdings!D16=0,"NA",Holdings!D16) -> PRGO | E9: =Holdings!I16 -> 2743.02 | F9: =Holdings!W16 -> 0.04489273 | G9: =Holdings!U16 -> 0.0063395628 | H9: =(F9*G9) -> 0.00028460029 | I9: =Holdings!T16 -> 0.043044692 | J9: =Holdings!S16 -> 0.24323883 | K9: =Holdings!R16 -> 0 | L9: =($E9/Holdings!L16)-1 -> 0.24323883 | M9: =Holdings!Q16 -> 0 | N9: =($E9/Holdings!K16)-1 -> 0.24323883
C10: =Holdings!C10 -> Gentex | D10: =IF(Holdings!D10=0,"NA",Holdings!D10) -> GNTX | E10: =Holdings!I10 -> 2622.95 | F10: =Holdings!W10 -> 0.042927644 | G10: =Holdings!U10 -> -0.024036762 | H10: =(F10*G10) -> -0.0010318416 | I10: =Holdings!T10 -> -0.044735959 | J10: =Holdings!S10 -> 0.15972247 | K10: =Holdings!R10 -> 0.075185858 | L10: =($E10/Holdings!L10)-1 -> 0.2469172 | M10: =Holdings!Q10 -> 0.2598419 | N10: =($E10/Holdings!K10)-1 -> 0.57091853
C11: =Holdings!C18 -> Tutor Perini | D11: =IF(Holdings!D19=0,"NA",Holdings!D19) -> TSN | E11: =Holdings!I18 -> 4814 | F11: =Holdings!W18 -> 0.07878674 | G11: =Holdings!U18 -> -0.026688233 | H11: =(F11*G11) -> -0.0021026789 | I11: =Holdings!T18 -> -0.1982012 | J11: =Holdings!S18 -> 0.2885439 | K11: =Holdings!R18 -> 0.50130601 | L11: =($E11/Holdings!L18)-1 -> 0.93449869 | M11: =Holdings!Q18 -> 0.32758943 | N11: =($E11/Holdings!K18)-1 -> 1.56822
C12: =Holdings!C11 -> Home Depot | D12: =IF(Holdings!D11=0,"NA",Holdings!D11) -> HD | E12: =Holdings!I11 -> 5677.27 | F12: =Holdings!W11 -> 0.092915163 | G12: =Holdings!U11 -> -0.010840684 | H12: =(F12*G12) -> -0.001007264 | I12: =Holdings!T11 -> 0.18731205 | J12: =Holdings!S11 -> 0.30319975 | K12: =Holdings!R11 -> 0.0056889862 | L12: =($E12/Holdings!L11)-1 -> 0.31061363 | M12: =Holdings!Q11 -> 0.28488899 | N12: =($E12/Holdings!K11)-1 -> 0.68399302
C13: =Holdings!C13 -> Intel | D13: =IF(Holdings!D13=0,"NA",Holdings!D13) -> INTC | E13: =Holdings!I13 -> 3899.92 | F13: =Holdings!W13 -> 0.063826752 | G13: =Holdings!U13 -> -0.018967027 | H13: =(F13*G13) -> -0.0012106037 | I13: =Holdings!T13 -> 0.27943797 | J13: =Holdings!S13 -> 0.52561959 | K13: =Holdings!R13 -> -0.076673072 | L13: =($E13/Holdings!L13)-1 -> 0.40864565 | M13: =Holdings!Q13 -> 0 | N13: =($E13/Holdings!K13)-1 -> 0.40864565
C14: =Holdings!C19 -> Tyson Foods | D14: =IF(Holdings!D20=0,"NA",Holdings!D20) -> NA | E14: =Holdings!I19 -> 4177.92 | F14: =Holdings!W19 -> 0.068376547 | G14: =Holdings!U19 -> -0.013487476 | H14: =(F14*G14) -> -0.00092222703 | I14: =Holdings!T19 -> -0.02999621 | J14: =Holdings!S19 -> 0.38094724 | K14: =Holdings!R19 -> 0.20431557 | L14: =($E14/Holdings!L19)-1 -> 0.66309626 | M14: =Holdings!Q19 -> 0.50878895 | N14: =($E14/Holdings!K19)-1 -> 1.5092613
C15: =Holdings!C14 -> Medtronic | D15: =IF(Holdings!D14=0,"NA",Holdings!D14) -> MDT | E15: =Holdings!I14 -> 1845.85 | F15: =Holdings!W14 -> 0.030209494 | G15: =Holdings!U14 -> -0.031644607 | H15: =(F15*G15) -> -0.00095596756 | I15: =Holdings!T14 -> 0.082527699 | J15: =Holdings!S14 -> 0.20613582 | K15: =Holdings!R14 -> 0.15314413 | L15: =($E15/Holdings!L14)-1 -> 0.39084844 | M15: =Holdings!Q14 -> 0.14552407 | N15: =($E15/Holdings!K14)-1 -> 0.59325037
C16: =Holdings!C6 -> BlackRock Global | D16: =IF(Holdings!D6=0,"NA",Holdings!D6) -> MCLOX | E16: =Holdings!I6 -> 1932.7122 | F16: =Holdings!W6 -> 0.031631095 | G16: =Holdings!U6 -> -0.013561025 | H16: =(F16*G16) -> -0.00042895006 | I16: =Holdings!T6 -> 0.029847908 | J16: =Holdings!S6 -> 0.10967687 | K16: =Holdings!R6 -> 0.0038438462 | L16: =($E16/Holdings!L6)-1 -> 0.11394229 | M16: =Holdings!Q6 -> 0.083002976 | N16: =($E16/Holdings!K6)-1 -> 0.20640282
C17: =Holdings!C20 -> 0 | D17: =IF(Holdings!D21=0,"NA",Holdings!D21) -> WFC | E17: =Holdings!I20 -> 0 | F17: =Holdings!W20 -> 0 | G17: =Holdings!U20 -> 0 | H17: =(F17*G17) -> 0 | I17: =Holdings!T20 -> 0 | J17: =Holdings!S20 -> 0 | K17: =Holdings!R20 -> 0 | L17: =($E17/Holdings!L20)-1 -> #DIV/0! | M17: =Holdings!Q20 -> 0 | N17: =($E17/Holdings!K20)-1 -> #DIV/0!
C18: =Holdings!C15 -> Natural Grocers | D18: =IF(Holdings!D15=0,"NA",Holdings!D15) -> NGVC | E18: =Holdings!I15 -> 1214.25 | F18: =Holdings!W15 -> 0.019872621 | G18: =Holdings!U15 -> -0.040876777 | H18: =(F18*G18) -> -0.00081232872 | I18: =Holdings!T15 -> -0.55643836 | J18: =Holdings!S15 -> -0.56243243 | K18: =Holdings!R15 -> 0.48773623 | L18: =($E18/Holdings!L15)-1 -> -0.34901488 | M18: =Holdings!Q15 -> 0.26741184 | N18: =($E18/Holdings!K15)-1 -> -0.17493375
C19: =Holdings!C5 -> Berkshire Hathaway | D19: =IF(Holdings!D5=0,"NA",Holdings!D5) -> BRK.B | E19: =Holdings!I5 -> 3564.34 | F19: =Holdings!W5 -> 0.058334593 | G19: =Holdings!U5 -> -0.020365871 | H19: =(F19*G19) -> -0.0011880348 | I19: =Holdings!T5 -> 0.062219123 | J19: =Holdings!S5 -> 0.2210742 | K19: =Holdings!R5 -> 0.044663627 | L19: =($E19/Holdings!L5)-1 -> 0.2756118 | M19: =Holdings!Q5 -> 0.24285878 | N19: =($E19/Holdings!K5)-1 -> 0.58540532
C20: =Holdings!C7 -> Cemex | D20: =IF(Holdings!D7=0,"NA",Holdings!D7) -> CX | E20: =Holdings!I7 -> 3172 | F20: =Holdings!W7 -> 0.05191349 | G20: =Holdings!U7 -> -0.026336792 | H20: =(F20*G20) -> -0.0013672348 | I20: =Holdings!T7 -> -0.0079749805 | J20: =Holdings!S7 -> 0.14409378 | K20: =Holdings!R7 -> -0.0091419831 | L20: =($E20/Holdings!L7)-1 -> 0.13363449 | M20: =Holdings!Q7 -> 0 | N20: =($E20/Holdings!K7)-1 -> 0.13363449
C21: =Holdings!C8 -> Cisco | D21: =IF(Holdings!D8=0,"NA",Holdings!D8) -> CSCO | E21: =Holdings!I8 -> 1693.3 | F21: =Holdings!W8 -> 0.027712835 | G21: =Holdings!U8 -> -0.019059205 | H21: =(F21*G21) -> -0.00052818461 | I21: =Holdings!T8 -> 0.057992748 | J21: =Holdings!S8 -> 0.043267944 | K21: =Holdings!R8 -> 0.16496187 | L21: =($E21/Holdings!L8)-1 -> 0.21536738 | M21: =Holdings!Q8 -> 0.062202357 | N21: =($E21/Holdings!K8)-1 -> 0.29096609
C22: =Holdings!C12 -> Immersion | D22: =IF(Holdings!D12=0,"NA",Holdings!D12) -> IMMR | E22: =Holdings!I12 -> 1067.85 | F22: =Holdings!W12 -> 0.017476614 | G22: =Holdings!U12 -> -0.035365854 | H22: =(F22*G22) -> -0.00061807538 | I22: =Holdings!T12 -> -0.26623377 | J22: =Holdings!S12 -> -0.40926064 | K22: =Holdings!R12 -> -0.11010191 | L22: =($E22/Holdings!L12)-1 -> -0.47430217 | M22: =Holdings!Q12 -> 0 | N22: =($E22/Holdings!K12)-1 -> -0.47430217
C23: !Cash | D23: =IF(Holdings!D4=0,"NA",Holdings!D4) -> NA | E23: =Holdings!I4 -> 8050.26 | F23: =Holdings!W4 -> 0.13175192 | G23: 0 | H23: =(F23*G23) -> 0
E24: =SUM(E5:E23) -> #REF! | H24: =SUM(H5:H22) -> #REF!

Sheet Long Term Chart

Sheet Holdings
C3: Name | D3: Ticker | E3: Price | F3: Paid | G3: Shares | H3: Initial Cost | I3: Value | J3: Value 1 Week Ago | K3: Value on 9/6/12 | L3: Value on 4/25/13 | M3: Value on 9/5/13 | O3: Total Gain $ | P3: Total Gain | Q3: 2012-2013 School Year | R3: 2013 Summer | S3: 2013-2014 School Year | T3: 1 Week | U3: Today | V3: Sector | W3: Portfolio Weight | X3: Market Cap (Billions) | Z3: PE | AA3: EPS | AE3: % of Weekly Portfolio Return | AF3: % of Daily Portfolio Return
C4: Cash | E4: 1 | F4: 1 | G4: 8050.26 | H4: 0 | I4: =E4*G4 -> 8050.26 | J4: 5786.22 | K4: 4804 | L4: 4361.76 | M4: 7658.58 | V4: Cash | W4: =I4/$I$24 -> 0.13175192 | X4: 0 | Y4: Cash | Z4: 0 | AA4: 0 | AE4: 0 | AF4: =(0.01/365)*W4 -> 3.6096416e-06
C5: Berkshire Hathaway | D5: ='Holdings Pull Sheet'!B16 -> BRK.B | E5: 137.09 | F5: 77.89 | G5: 26 | H5: 2035.09 | I5: =E5*G5 -> 3564.34 | J5: 3355.56 | K5: 2248.22 | L5: 2794.22 | M5: 2919.02 | O5: =I5-H5 -> 1529.25 | P5: =(I5/H5)-1 -> 0.75144097 | Q5: =(L5/K5)-1 -> 0.24285878 | R5: =(M5/L5)-1 -> 0.044663627 | S5: =(I5/M5)-1 -> 0.2210742 | T5: =(I5/J5)-1 -> 0.062219123 | U5: =('Holdings Pull Sheet'!F16/'Holdings Pull Sheet'!G16)-1 -> -0.020365871 | V5: Financial | W5: =I5/$I$24 -> 0.058334593 | X5: ='Holdings Pull Sheet'!O16/1000000000 -> 319.36477 | Y5: =IF(X5<2,"Small", IF(X5<10, "Mid", IF(X5>10, "Large"))) -> Large | Z5: ='Holdings Pull Sheet'!Q16 -> 15.19 | AA5: ='Holdings Pull Sheet'!P16 -> 9 | AE5: =W5*T5 -> 0.0036295272 | AF5: =W5*U5 -> -0.0011880348
C6: BlackRock Global | D6: ='Holdings Pull Sheet'!B17 -> MCLOX | E6: 20.42 | F6: 17.23 | G6: 94.648 | H6: 1543.42 | I6: =E6*G6 -> 1932.7122 | J6: 1876.6967 | K6: 1602.0455 | L6: 1735.02 | M6: 1741.6891 | O6: =I6-H6 -> 389.29216 | P6: =(I6/H6)-1 -> 0.25222698 | Q6: =(L6/K6)-1 -> 0.083002976 | R6: =(M6/L6)-1 -> 0.0038438462 | S6: =(I6/M6)-1 -> 0.10967687 | T6: =(I6/J6)-1 -> 0.029847908 | U6: =('Holdings Pull Sheet'!F17/'Holdings Pull Sheet'!G17)-1 -> -0.013561025 | V6: Misc | W6: =I6/$I$24 -> 0.031631095 | X6: ='Holdings Pull Sheet'!O17/1000000000 -> 0 | Y6: Bond | Z6: ='Holdings Pull Sheet'!Q17 -> 0 | AA6: ='Holdings Pull Sheet'!P17 -> 0 | AE6: =W6*T6 -> 0.00094412201 | AF6: =W6*U6 -> -0.00042895006
C7: Cemex | D7: ='Holdings Pull Sheet'!B18 -> CX | E7: 12.2 | F7: 11.15 | G7: 260 | H7: 2798.08 | I7: =E7*G7 -> 3172 | J7: 3197.5 | K7: 2798.08 | L7: 2798.08 | M7: 2772.5 | O7: =I7-H7 -> 373.92 | P7: =(I7/H7)-1 -> 0.13363449 | Q7: =(L7/K7)-1 -> 0 | R7: =(M7/L7)-1 -> -0.0091419831 | S7: =(I7/M7)-1 -> 0.14409378 | T7: =(I7/J7)-1 -> -0.0079749805 | U7: =('Holdings Pull Sheet'!F18/'Holdings Pull Sheet'!G18)-1 -> -0.026336792 | V7: Industrials | W7: =I7/$I$24 -> 0.05191349 | X7: ='Holdings Pull Sheet'!O18/1000000000 -> 14.494177 | Y7: =IF(X7<2,"Small", IF(X7<10, "Mid", IF(X7>10, "Large"))) -> Large | Z7: ='Holdings Pull Sheet'!Q18 -> -25.33 | AA7: ='Holdings Pull Sheet'!P18 -> -6.46 | AE7: =W7*T7 -> -0.00041400907 | AF7: =W7*U7 -> -0.0013672348
C8: Cisco | D8: ='Holdings Pull Sheet'!B19 -> CSCO | E8: 24.19 | F8: 18.67 | G8: 70 | H8: 1248.11 | I8: =E8*G8 -> 1693.3 | J8: 1600.4836 | K8: 1311.6534 | L8: 1393.2413 | M8: 1623.073 | O8: =I8-H8 -> 445.19 | P8: =(I8/H8)-1 -> 0.35669132 | Q8: =(L8/K8)-1 -> 0.062202357 | R8: =(M8/L8)-1 -> 0.16496187 | S8: =(I8/M8)-1 -> 0.043267944 | T8: =(I8/J8)-1 -> 0.057992748 | U8: =('Holdings Pull Sheet'!F19/'Holdings Pull Sheet'!G19)-1 -> -0.019059205 | V8: Information Technology | W8: =I8/$I$24 -> 0.027712835 | X8: ='Holdings Pull Sheet'!O19/1000000000 -> 123.34972 | Y8: =IF(X8<2,"Small", IF(X8<10, "Mid", IF(X8>10, "Large"))) -> Large | Z8: ='Holdings Pull Sheet'!Q19 -> 16.27 | AA8: ='Holdings Pull Sheet'!P19 -> 1.49 | AE8: =W8*T8 -> 0.0016071435 | AF8: =W8*U8 -> -0.00052818461
C9: Delta Airlines | D9: ='Holdings Pull Sheet'!B20 -> DAL | E9: 33.71 | F9: 16.58 | G9: 151 | H9: 2481.99 | I9: =E9*G9 -> 5090.21 | J9: 5594.3181 | K9: 2481.99 | L9: 2443.5 | M9: 3037.5 | O9: =I9-H9 -> 2608.22 | P9: =(I9/H9)-1 -> 1.0508584 | Q9: =(L9/K9)-1 -> -0.015507718 | R9: =(M9/L9)-1 -> 0.24309392 | S9: =(I9/M9)-1 -> 0.6757893 | T9: =(I9/J9)-1 -> -0.090110729 | U9: =('Holdings Pull Sheet'!F20/'Holdings Pull Sheet'!G20)-1 -> -0.031600115 | V9: Consumer Discretionary | W9: =I9/$I$24 -> 0.08330724 | X9: ='Holdings Pull Sheet'!O20/1000000000 -> 28.24913 | Y9: =IF(X9<2,"Small", IF(X9<10, "Mid", IF(X9>10, "Large"))) -> Large | Z9: ='Holdings Pull Sheet'!Q20 -> 2.64 | AA9: ='Holdings Pull Sheet'!P20 -> 12.69 | AE9: =W9*T9 -> -0.0075068761 | AF9: =W9*U9 -> -0.0026325184
C10: Gentex | D10: ='Holdings Pull Sheet'!B21 -> GNTX | E10: 27.61 | F10: 17.06 | G10: 95 | H10: 1502.35 | I10: =E10*G10 -> 2622.95 | J10: 2745.7853 | K10: 1669.6919 | L10: 2103.5478 | M10: 2261.7049 | O10: =I10-H10 -> 1120.6 | P10: =(I10/H10)-1 -> 0.74589809 | Q10: =(L10/K10)-1 -> 0.2598419 | R10: =(M10/L10)-1 -> 0.075185858 | S10: =(I10/M10)-1 -> 0.15972247 | T10: =(I10/J10)-1 -> -0.044735959 | U10: =('Holdings Pull Sheet'!F21/'Holdings Pull Sheet'!G21)-1 -> -0.024036762 | V10: Consumer Discretionary | W10: =I10/$I$24 -> 0.042927644 | X10: ='Holdings Pull Sheet'!O21/1000000000 -> 4.0367771 | Y10: =IF(X10<2,"Small", IF(X10<10, "Mid", IF(X10>10, "Large"))) -> Mid | Z10: ='Holdings Pull Sheet'!Q21 -> 14.87 | AA10: ='Holdings Pull Sheet'!P21 -> 1.86 | AE10: =W10*T10 -> -0.0019204093 | AF10: =W10*U10 -> -0.0010318416
C11: Home Depot | D11: ='Holdings Pull Sheet'!B22 -> HD | E11: 93.07 | F11: 31.22 | G11: 61 | H11: 1668.75 | I11: =E11*G11 -> 5677.27 | J11: 4781.6157 | K11: 3371.3144 | L11: 4331.7648 | M11: 4356.4082 | O11: =I11-H11 -> 4008.52 | P11: =(I11/H11)-1 -> 2.4021094 | Q11: =(L11/K11)-1 -> 0.28488899 | R11: =(M11/L11)-1 -> 0.0056889862 | S11: =(I11/M11)-1 -> 0.30319975 | T11: =(I11/J11)-1 -> 0.18731205 | U11: =('Holdings Pull Sheet'!F22/'Holdings Pull Sheet'!G22)-1 -> -0.010840684 | V11: Consumer Discretionary | W11: =I11/$I$24 -> 0.092915163 | X11: ='Holdings Pull Sheet'!O22/1000000000 -> 125.26492 | Y11: =IF(X11<2,"Small", IF(X11<10, "Mid", IF(X11>10, "Large"))) -> Large | Z11: ='Holdings Pull Sheet'!Q22 -> 22.26 | AA11: ='Holdings Pull Sheet'!P22 -> 4.18 | AE11: =W11*T11 -> 0.01740413 | AF11: =W11*U11 -> -0.001007264
C12: Immersion | D12: ='Holdings Pull Sheet'!B23 -> IMMR | E12: 7.91 | F12: 15.05 | G12: 135 | H12: 2031.3 | I12: =E12*G12 -> 1067.85 | J12: 1455.3 | K12: 2031.3 | L12: 2031.3 | M12: 1807.65 | O12: =I12-H12 -> -963.45 | P12: =(I12/H12)-1 -> -0.47430217 | Q12: =(L12/K12)-1 -> 0 | R12: =(M12/L12)-1 -> -0.11010191 | S12: =(I12/M12)-1 -> -0.40926064 | T12: =(I12/J12)-1 -> -0.26623377 | U12: =('Holdings Pull Sheet'!F23/'Holdings Pull Sheet'!G23)-1 -> -0.035365854 | V12: Information Technology | W12: =I12/$I$24 -> 0.017476614 | X12: ='Holdings Pull Sheet'!O23/1000000000 -> 0.22590436 | Y12: =IF(X12<2,"Small", IF(X12<10, "Mid", IF(X12>10, "Large"))) -> Small | Z12: ='Holdings Pull Sheet'!Q23 -> 5.84 | AA12: ='Holdings Pull Sheet'!P23 -> 1.35 | AE12: =W12*T12 -> -0.0046528648 | AF12: =W12*U12 -> -0.00061807538
C13: Intel | D13: ='Holdings Pull Sheet'!B24 -> INTC | E13: 33.62 | F13: 24.77 | G13: 116 | H13: 2768.56 | I13: =E13*G13 -> 3899.92 | J13: 3048.1509 | K13: 2768.56 | L13: 2768.56 | M13: 2556.286 | O13: =I13-H13 -> 1131.36 | P13: =(I13/H13)-1 -> 0.40864565 | Q13: =(L13/K13)-1 -> 0 | R13: =(M13/L13)-1 -> -0.076673072 | S13: =(I13/M13)-1 -> 0.52561959 | T13: =(I13/J13)-1 -> 0.27943797 | U13: =('Holdings Pull Sheet'!F24/'Holdings Pull Sheet'!G24)-1 -> -0.018967027 | V13: Information Technology | W13: =I13/$I$24 -> 0.063826752 | X13: ='Holdings Pull Sheet'!O24/1000000000 -> 166.45262 | Y13: =IF(X13<2,"Small", IF(X13<10, "Mid", IF(X13>10, "Large"))) -> Large | Z13: ='Holdings Pull Sheet'!Q24 -> 16.68 | AA13: ='Holdings Pull Sheet'!P24 -> 2.02 | AE13: =W13*T13 -> 0.017835618 | AF13: =W13*U13 -> -0.0012106037
C14: Medtronic | D14: ='Holdings Pull Sheet'!B25 -> MDT | E14: 63.65 | F14: 46.97 | G14: 29 | H14: 1330.71 | I14: =E14*G14 -> 1845.85 | J14: 1705.1296 | K14: 1158.5436 | L14: 1327.1396 | M14: 1530.3832 | O14: =I14-H14 -> 515.14 | P14: =(I14/H14)-1 -> 0.38711665 | Q14: =(L14/K14)-1 -> 0.14552407 | R14: =(M14/L14)-1 -> 0.15314413 | S14: =(I14/M14)-1 -> 0.20613582 | T14: =(I14/J14)-1 -> 0.082527699 | U14: =('Holdings Pull Sheet'!F25/'Holdings Pull Sheet'!G25)-1 -> -0.031644607 | V14: Healthcare | W14: =I14/$I$24 -> 0.030209494 | X14: ='Holdings Pull Sheet'!O25/1000000000 -> 62.356015 | Y14: =IF(X14<2,"Small", IF(X14<10, "Mid", IF(X14>10, "Large"))) -> Large | Z14: ='Holdings Pull Sheet'!Q25 -> 21.55 | AA14: ='Holdings Pull Sheet'!P25 -> 2.95 | AE14: =W14*T14 -> 0.00249312 | AF14: =W14*U14 -> -0.00095596756
C15: Natural Grocers | D15: ='Holdings Pull Sheet'!B26 -> NGVC | E15: 16.19 | F15: 19.49 | G15: 75 | H15: 1471.7 | I15: =E15*G15 -> 1214.25 | J15: 2737.5 | K15: 1471.7 | L15: 1865.25 | M15: 2775 | O15: =I15-H15 -> -257.45 | P15: =(I15/H15)-1 -> -0.17493375 | Q15: =(L15/K15)-1 -> 0.26741184 | R15: =(M15/L15)-1 -> 0.48773623 | S15: =(I15/M15)-1 -> -0.56243243 | T15: =(I15/J15)-1 -> -0.55643836 | U15: =('Holdings Pull Sheet'!F26/'Holdings Pull Sheet'!G26)-1 -> -0.040876777 | V15: Consumer Staples | W15: =I15/$I$24 -> 0.019872621 | X15: ='Holdings Pull Sheet'!O26/1000000000 -> 0.36391769 | Y15: =IF(X15<2,"Small", IF(X15<10, "Mid", IF(X15>10, "Large"))) -> Small | Z15: ='Holdings Pull Sheet'!Q26 -> 29.08 | AA15: ='Holdings Pull Sheet'!P26 -> 0.56 | AE15: =W15*T15 -> -0.011057889 | AF15: =W15*U15 -> -0.00081232872
C16: Perrigo | D16: ='Holdings Pull Sheet'!B27 -> PRGO | E16: 152.39 | F16: 167.85 | G16: 18 | H16: 2206.35 | I16: =E16*G16 -> 2743.02 | J16: 2629.8202 | K16: 2206.35 | L16: 2206.35 | M16: 2206.35 | O16: =I16-H16 -> 536.67 | P16: =(I16/H16)-1 -> 0.24323883 | Q16: =(L16/K16)-1 -> 0 | R16: =(M16/L16)-1 -> 0 | S16: =(I16/M16)-1 -> 0.24323883 | T16: =(I16/J16)-1 -> 0.043044692 | U16: =('Holdings Pull Sheet'!F27/'Holdings Pull Sheet'!G27)-1 -> 0.0063395628 | V16: Healthcare | W16: =I16/$I$24 -> 0.04489273 | X16: ='Holdings Pull Sheet'!O27/1000000000 -> 20.392487 | Y16: =IF(X16<2,"Small", IF(X16<10, "Mid", IF(X16>10, "Large"))) -> Large | Z16: ='Holdings Pull Sheet'!Q27 -> 86.1 | AA16: ='Holdings Pull Sheet'!P27 -> 1.77 | AE16: =W16*T16 -> 0.0019323937 | AF16: =W16*U16 -> 0.00028460029
C17: Range Resources | D17: ='Holdings Pull Sheet'!B28 -> RRC | E17: 63.46 | F17: 86.37 | G17: 42 | H17: 3627.5 | I17: =E17*G17 -> 2665.32 | J17: 3747.66 | K17: 3627.5 | L17: 3627.5 | M17: 3627.5 | O17: =I17-H17 -> -962.18 | P17: =(I17/H17)-1 -> -0.26524604 | Q17: =(L17/K17)-1 -> 0 | R17: =((M17-896.49)/L17)-1 -> -0.24713715 | S17: =(I17/M17)-1 -> -0.26524604 | T17: =(I17/J17)-1 -> -0.28880421 | U17: =('Holdings Pull Sheet'!F28/'Holdings Pull Sheet'!G28)-1 -> -0.032636877 | V17: Energy | W17: =I17/$I$24 -> 0.043621079 | X17: ='Holdings Pull Sheet'!O28/1000000000 -> 10.700487 | Y17: =IF(X17<2,"Small", IF(X17<10, "Mid", IF(X17>10, "Large"))) -> Large | Z17: ='Holdings Pull Sheet'!Q28 -> 40.89 | AA17: ='Holdings Pull Sheet'!P28 -> 1.55 | AE17: =W17*T17 -> -0.012597951 | AF17: =W17*U17 -> -0.0014236558
C18: Tutor Perini | D18: ='Holdings Pull Sheet'!B29 -> TPC | E18: 24.07 | F18: 13.76 | G18: 200 | H18: 2752.24 | I18: =E18*G18 -> 4814 | J18: 6004 | K18: 1874.45 | L18: 2488.5 | M18: 3736 | O18: =I18-H18 -> 2061.76 | P18: =(I18/H18)-1 -> 0.74912072 | Q18: =(L18/K18)-1 -> 0.32758943 | R18: =(M18/L18)-1 -> 0.50130601 | S18: =(I18/M18)-1 -> 0.2885439 | T18: =(I18/J18)-1 -> -0.1982012 | U18: =('Holdings Pull Sheet'!F29/'Holdings Pull Sheet'!G29)-1 -> -0.026688233 | V18: Industrials | W18: =I18/$I$24 -> 0.07878674 | X18: ='Holdings Pull Sheet'!O29/1000000000 -> 1.1691218 | Y18: =IF(X18<2,"Small", IF(X18<10, "Mid", IF(X18>10, "Large"))) -> Small | Z18: ='Holdings Pull Sheet'!Q29 -> 11.57 | AA18: ='Holdings Pull Sheet'!P29 -> 2.08 | AE18: =W18*T18 -> -0.015615626 | AF18: =W18*U18 -> -0.0021026789
C19: Tyson Foods | D19: ='Holdings Pull Sheet'!B30 -> TSN | E19: 40.96 | F19: 16.89 | G19: 102 | H19: 1674.95 | I19: =E19*G19 -> 4177.92 | J19: 4307.1172 | K19: 1665 | L19: 2512.1336 | M19: 3025.4016 | O19: =I19-H19 -> 2502.97 | P19: =(I19/H19)-1 -> 1.4943551 | Q19: =(L19/K19)-1 -> 0.50878895 | R19: =(M19/L19)-1 -> 0.20431557 | S19: =(I19/M19)-1 -> 0.38094724 | T19: =(I19/J19)-1 -> -0.02999621 | U19: =('Holdings Pull Sheet'!F30/'Holdings Pull Sheet'!G30)-1 -> -0.013487476 | V19: Consumer Staples | W19: =I19/$I$24 -> 0.068376547 | X19: ='Holdings Pull Sheet'!O30/1000000000 -> 14.405563 | Y19: =IF(X19<2,"Small", IF(X19<10, "Mid", IF(X19>10, "Large"))) -> Large | Z19: ='Holdings Pull Sheet'!Q30 -> 14.87 | AA19: ='Holdings Pull Sheet'!P30 -> 2.75 | AE19: =W19*T19 -> -0.0020510372 | AF19: =W19*U19 -> -0.00092222703
C21: Wells Fargo | D21: ='Holdings Pull Sheet'!B32 -> WFC | E21: 51.12 | F21: 24.69 | G21: 54 | H21: 1204.37 | I21: =E21*G21 -> 2760.48 | J21: 2658.3709 | K21: 1778.2684 | L21: 1961.7592 | M21: 2210.1034 | O21: =I21-H21 -> 1556.11 | P21: =(I21/H21)-1 -> 1.2920531 | Q21: =(L21/K21)-1 -> 0.10318505 | R21: =(M21/L21)-1 -> 0.1265926 | S21: =(I21/M21)-1 -> 0.24902756 | T21: =(I21/J21)-1 -> 0.038410396 | U21: =('Holdings Pull Sheet'!F32/'Holdings Pull Sheet'!G32)-1 -> -0.019750719 | V21: Financial | W21: =I21/$I$24 -> 0.045178484 | X21: ='Holdings Pull Sheet'!O32/1000000000 -> 266.97162 | Y21: =IF(X21<2,"Small", IF(X21<10, "Mid", IF(X21>10, "Large"))) -> Large | Z21: ='Holdings Pull Sheet'!Q32 -> 12.63 | AA21: ='Holdings Pull Sheet'!P32 -> 4.05 | AE21: =W21*T21 -> 0.0017353235 | AF21: =W21*U21 -> -0.00089230754
C22: Yahoo | D22: ='Holdings Pull Sheet'!B33 -> YHOO | E22: 41.1 | F22: 21.75 | G22: 100 | H22: 2174.99 | I22: =E22*G22 -> 4110 | J22: 3651 | K22: 2174.99 | L22: 2520 | M22: 2823 | O22: =I22-H22 -> 1935.01 | P22: =(I22/H22)-1 -> 0.88966386 | Q22: =(L22/K22)-1 -> 0.15862602 | R22: =(M22/L22)-1 -> 0.1202381 | S22: =(I22/M22)-1 -> 0.45589798 | T22: =(I22/J22)-1 -> 0.12571898 | U22: =('Holdings Pull Sheet'!F33/'Holdings Pull Sheet'!G33)-1 -> 0.00048685492 | V22: Information Technology | W22: =I22/$I$24 -> 0.067264957 | X22: ='Holdings Pull Sheet'!O33/1000000000 -> 40.878216 | Y22: =IF(X22<2,"Small", IF(X22<10, "Mid", IF(X22>10, "Large"))) -> Large | Z22: ='Holdings Pull Sheet'!Q33 -> 34.59 | AA22: ='Holdings Pull Sheet'!P33 -> 1.19 | AE22: =W22*T22 -> 0.0084564818 | AF22: =W22*U22 -> 3.2748275e-05
H24: =SUM(H4:H22) -> 34520.46 | I24: =SUM(I4:I22) -> 61101.652 | J24: 62601.628 | K24: 40381.87 | L24: 46519.794 | M24: 51641.858 | O24: =SUM(O5:O22) -> 18530.932 | P24: =(I24/H24)-1 -> 0.77001269 | Q24: =(L24/K24)-1 -> 0.15199701 | R24: =(M24/L24)-1 -> 0.11010505 | S24: =(I24/M24)-1 -> 0.18318074 | T24: =(I24/J24)-1 -> -0.023960656 | U24: =AF24 -> -0.016800915 | W24: =SUM(W4:W22) -> 1 | AE24: =SUM(AE4:AE22) -> 0.00022119633 | AF24: =SUM(AF4:AF22) -> -0.016800915
C27: Bought This Year | E27: Date Bought | H27: Buy Price | I27: Current Price | J27: % Change
C28: =C19 -> Tyson Foods | D28: =D20 -> 0 | E28: =Transactions!B145 -> 41530 | H28: =F19 -> 16.89 | I28: =E19 -> 40.96 | J28: =(I28/H28)-1 -> 1.4251036
C29: =C16 -> Perrigo | D29: =D16 -> PRGO | E29: =Transactions!B147 -> 41544 | H29: =F16 -> 167.85 | I29: =E16 -> 152.39 | J29: =(I29/H29)-1 -> -0.092106047
C30: =C17 -> Range Resources | D30: =D17 -> RRC | E30: 41698 | H30: =F17 -> 86.37 | I30: =E17 -> 63.46 | J30: =(I30/H30)-1 -> -0.26525414
C33: Sold This Year | E33: Date Sold | H33: Sell Price | I33: Current Price | J33: % Change
C34: Caterpillar | D34: ='Holdings Pull Sheet'!B35 -> 0 | E34: =Transactions!B149 -> 41551 | H34: =Transactions!E149 -> 83.94 | I34: ='Holdings Pull Sheet'!F35 -> 93.5 | J34: =(I34/H34)-1 -> 0.11389087
C35: YRC Worldwide | D35: ='Holdings Pull Sheet'!B36 -> 0 | E35: =Transactions!B151 -> 41576 | H35: 9.58 | I35: ='Holdings Pull Sheet'!F36 -> 17.3 | J35: =(I35/H35)-1 -> 0.80584551
C36: AAPL 515 Apr19 C | D36: ='Holdings Pull Sheet'!B37 -> 0 | E36: =Transactions!B155 -> 41614 | H36: 65.8 | I36: ='Holdings Pull Sheet'!F37 -> 0 | J36: =(I36/H36)-1 -> -1
C38: Proposed Buys This Year | E38: Date Pitched | H38: Pitch Price | I38: Current Price | J38: % Change
C39: NA | D39: NA | E39: NA | H39: NA | I39: NA | J39: =(I39/H39)-1 -> #VALUE!
C41: Proposed Sells This Year | E41: Date Pitched | H41: Pitch Price | I41: Current Price | J41: % Change
C42: NA | D42: NA | E42: NA | H42: NA | I42: NA | J42: =(I42/H42)-1 -> #VALUE!

Sheet Holdings Pull Sheet
C5: Stock Quote Symbols | D5: $INDU,$COMP,$INX,$COMPX,BRK.B,MCLOX,CX,CSCO,DAL,GNTX,HD,IMMR,INTC,MDT,NGVC,PRGO,RRC,TPC,TSN,ULTA,WFC,YHOO,GE,CAT,YRCW,126.2.AAPL4DJC515000
C9: Stock Quotes Provided by MSN Money
C10: Click here to visit MSN Money
F11: Last | G11: Previous Close | H11: High | I11: Low | J11: Volume | K11: Change | L11: % Change | M11: 52 Wk High | N11: 52 Wk Low | O11: Market Cap | P11: EPS | Q11: P/E Ratio | R11: # Shares Out
C12: DJ Industrial Average | D12: Chart | E12: News | F12: 16659.25 | G12: 16994.22 | H12: 16989.37 | I12: 16649.04 | J12: 93214073 | K12: -334.97 | L12: -0.0197 | M12: 17350.64 | N12: 14806.39 | O12: 0 | P12: 0 | Q12: 0 | R12: 0
C13: NASDAQ Composite | D13: Chart | E13: News | F13: 4378.34 | G13: 4468.59 | H13: 4464.13 | I13: 4377.28 | J13: 0 | K13: -90.26 | L13: -0.0202 | M13: 4610.57 | N13: 3721.11 | O13: 0 | P13: 0 | Q13: 0 | R13: 0
C14: S&P 500 Index | D14: Chart | E14: News | F14: 1928.21 | G14: 1968.89 | H14: 1967.68 | I14: 1927.56 | J14: 604573274 | K14: -40.68 | L14: -0.0207 | M14: 2019.26 | N14: 1660.88 | O14: 0 | P14: 0 | Q14: 0 | R14: 0
C15: NASDAQ Composite | D15: Chart | E15: News | F15: 4378.34 | G15: 4468.59 | H15: 4464.13 | I15: 4377.28 | J15: 0 | K15: -90.26 | L15: -0.0202 | M15: 4610.57 | N15: 3721.11 | O15: 0 | P15: 0 | Q15: 0 | R15: 0
B16: BRK.B | C16: BERKSHIRE HATHAWAY CLASS B | D16: Chart | E16: News | F16: 137.09 | G16: 139.94 | H16: 140.29 | I16: 137.07 | J16: 6592808 | K16: -2.85 | L16: -0.0204 | M16: 142.45 | N16: 108.12 | O16: 319364766003 | P16: 9 | Q16: 15.19 | R16: 2334708429
B17: MCLOX | C17: BlackRock Global Allocation Inv C | D17: Chart | E17: News | F17: 19.64 | G17: 19.91 | H17: 19.64 | I17: 19.64 | J17: 0 | K17: -0.27 | L17: -0.0136 | M17: 0 | N17: 0 | O17: 0 | P17: 0 | Q17: 0 | R17: 0
B18: CX | C18: CEMEX S.A.B. DE C.V. | D18: Chart | E18: News | F18: 12.2 | G18: 12.53 | H18: 12.54 | I18: 12.07 | J18: 13180275 | K18: -0.33 | L18: -0.0263 | M18: 14.37 | N18: 9.81 | O18: 14494176889 | P18: -6.46 | Q18: -25.33 | R18: 1188047286
B19: CSCO | C19: CISCO SYSTEMS INC | D19: Chart | E19: News | F19: 24.19 | G19: 24.66 | H19: 24.64 | I19: 24.18 | J19: 29340068 | K19: -0.47 | L19: -0.0191 | M19: 26.08 | N19: 20.22 | O19: 123349724658 | P19: 1.49 | Q19: 16.27 | R19: 5099203169
B20: DAL | C20: DELTA AIR LINES Inc | D20: Chart | E20: News | F20: 33.71 | G20: 34.81 | H20: 35.94 | I20: 33.61 | J20: 28215542 | K20: -1.1 | L20: -0.0316 | M20: 42.66 | N20: 23.72 | O20: 28249129921 | P20: 12.69 | Q20: 2.64 | R20: 843005966
B21: GNTX | C21: GENTEX CORP | D21: Chart | E21: News | F21: 27.61 | G21: 28.29 | H21: 28.32 | I21: 27.36 | J21: 1397926 | K21: -0.68 | L21: -0.024 | M21: 34.41 | N21: 24.63 | O21: 4036777120 | P21: 1.86 | Q21: 14.87 | R21: 146207067
B22: HD | C22: HOME DEPOT Inc | D22: Chart | E22: News | F22: 93.07 | G22: 94.09 | H22: 94.79 | I22: 93.02 | J22: 6674794 | K22: -1.02 | L22: -0.0108 | M22: 94.79 | N22: 73.74 | O22: 125264919496 | P22: 4.18 | Q22: 22.26 | R22: 1345921559
B23: IMMR | C23: IMMERSION CORP | D23: Chart | E23: News | F23: 7.91 | G23: 8.2 | H23: 8.2 | I23: 7.9 | J23: 297585 | K23: -0.29 | L23: -0.0354 | M23: 14.72 | N23: 7.86 | O23: 225904356 | P23: 1.35 | Q23: 5.84 | R23: 28559337
B24: INTC | C24: INTEL CORP | D24: Chart | E24: News | F24: 33.62 | G24: 34.27 | H24: 34.43 | I24: 33.58 | J24: 28157325 | K24: -0.65 | L24: -0.019 | M24: 35.56 | N24: 22.48 | O24: 166452620000 | P24: 2.02 | Q24: 16.68 | R24: 4951000000
B25: MDT | C25: MEDTRONIC Inc | D25: Chart | E25: News | F25: 63.65 | G25: 65.73 | H25: 65.6 | I25: 63.64 | J25: 9472607 | K25: -2.08 | L25: -0.0316 | M25: 67.11 | N25: 52.53 | O25: 62356014852 | P25: 2.95 | Q25: 21.55 | R25: 979516413
B26: NGVC | C26: NATURAL GROCERS BY VITAMIN COTTAGE INC | D26: Chart | E26: News | F26: 16.19 | G26: 16.88 | H26: 16.73 | I26: 16.17 | J26: 69324 | K26: -0.69 | L26: -0.0409 | M26: 44.6 | N26: 15.89 | O26: 363917687 | P26: 0.56 | Q26: 29.08 | R26: 22477930
B27: PRGO | C27: PERRIGO COMPANY PLC (IRELAND) | D27: Chart | E27: News | F27: 152.39 | G27: 151.43 | H27: 153.87 | I27: 150.5 | J27: 1099984 | K27: 0.96 | L27: 0.0063 | M27: 168.39 | N27: 125.37 | O27: 20392486923 | P27: 1.77 | Q27: 86.1 | R27: 133817750
... B30: TSN | C30: TYSON FOODS Inc | D30: Chart | E30: News | F30: 40.96 | G30: 41.52 | H30: 42.1 | I30: 40.83 | J30: 3822251 | K30: -0.56 | L30: -0.0135 | M30: 44.24 | N30: 27.33 | O30: 14405562696 | P30: 2.75 | Q30: 14.87 | R30: 351698308
C31: ULTA SALON COSMETICS & FRAGRANCE Inc | D31: Chart | E31: News | F31: 114.77 | G31: 114.87 | H31: 115.75 | I31: 113.57 | J31: 750290 | K31: -0.1 | L31: -0.0009 | M31: 132.72 | N31: 80.35 | O31: 7388523500 | P31: 3.51 | Q31: 32.68 | R31: 64376784
B32: WFC | C32: WELLS FARGO & CO. | D32: Chart | E32: News | F32: 51.12 | G32: 52.15 | H32: 52.21 | I32: 51.03 | J32: 18744179 | K32: -1.03 | L32: -0.0198 | M32: 53.8 | N32: 40.07 | O32: 266971616384 | P32: 4.05 | Q32: 12.63 | R32: 5220407047
B33: YHOO | C33: YAHOO INC | D33: Chart | E33: News | F33: 41.1 | G33: 41.08 | H33: 41.25 | I33: 40.42 | J33: 33515066 | K33: 0.02 | L33: 0.0005 | M33: 44.01 | N33: 31.7 | O33: 40878215687 | P33: 1.19 | Q33: 34.59 | R33: 994603788
C34: GENERAL ELECTRIC | D34: Chart | E34: News | F34: 24.78 | G34: 25.25 | H34: 25.31 | I34: 24.73 | J34: 34012297 | K34: -0.47 | L34: -0.0186 | M34: 28.09 | N34: 23.5 | O34: 248539795987 | P34: 1.46 | Q34: 16.95 | R34: 10033903754
C35: CATERPILLAR Inc | D35: Chart | E35: News | F35: 93.5 | G35: 96.65 | H35: 96.52 | I35: 93.24 | J35: 6414828 | K35: -3.15 | L35: -0.0326 | M35: 111.46 | N35: 81.87 | O35: 58703657287 | P35: 6 | Q35: 15.58 | R35: 627846602
C36: YRC WORLDWIDE Inc | D36: Chart | E36: News | F36: 17.3 | G36: 18.91 | H36: 18.84 | I36: 16.95 | J36: 1147246 | K36: -1.61 | L36: -0.0851 | M36: 29.21 | N36: 7.06 | O36: 540487240 | P36: -7.5 | Q36: -2.31 | R36: 31242037
C38: Symbol Lookup | E38: MSN Money Home | I38: Microsoft Office Tools on the Web
C39: Find stocks, mutual funds, options, indices, and currencies. | E39: Discover MSN Money's tools, columns, and more! | I39: Get the latest from Microsoft Office
C41: Terms of Use. © 2014 Microsoft Corporation and/or its suppliers. All rights reserved.
C42: DATA PROVIDERS
C44: Copyright © 2014 Microsoft. All rights reserved.
C46: Fundamental company data and historical chart data provided by Morningstar Inc. Real-time index quotes and delayed quotes supplied by Morningstar Inc. Quotes delayed by up to 15 minutes, except where indicated otherwise. Fund summary, fund performance and dividend data provided by Morningstar Inc. Analyst recommendations provided by Zacks Investment Research. StockScouter data provided by Verus Analytics. IPO data provided by Hoover's Inc. Index membership data provided by Morningstar Inc.

Sheet Data
D1: IPO Portfolio | L1: S&P 500 Index | S1: Dow Jones Index
A2: Week # | B2: Date | D2: Portfolio Value | E2: Adjusted Portfolio Value | F2: Weekly +/- | G2: Weekly % Change | H2: Inception +/- | I2: Inception % Change | L2: S&P Close | M2: S&P Weekly % Change | N2: S&P Inception % Change | O2: Outperformed S&P 500? | P2: 1 = Yes, 0 = No | Q2: % IPO Outperforemed S&P 500 | S2: Dow Close | T2: Dow Weekly % Change | U2: Dow Inception % Change | V2: Outperformed Dow? | W2: 1 = Yes, 0 = No | X2: % IPO Outperforemed Dow | Z2: Nasdaq Close | AA2: Nasdaq Weekly % Change | AB2: Nasdaq Inception % Change
A3: 1 | B3: 37743 | D3: 22855.85 | E3: =D3 -> 22855.85 | F3: - | G3: - | H3: - | I3: - | L3: 930.08 | M3: - | N3: - | S3: 8582.68 | T3: - | U3: - | Z3: 1502.88 | AA3: - | AB3: -
A4: =A3+1 -> 2 | B4: 37750 | D4: 23075.51 | E4: =D4 -> 23075.51 | F4: =D4-D3 -> 219.66 | G4: =(D4/D3)-1 -> 0.0096106686 | H4: =D4-$D$3 -> 219.66 | I4: =(D4/$D$3)-1 -> 0.0096106686 | L4: 933.41 | M4: =(L4/L3)-1 -> 0.0035803372 | N4: =(L4/$L$3)-1 -> 0.0035803372 | O4: =IF(G4>M4,"Yes","No") -> Yes | P4: =IF(O4="Yes",1,0) -> 1 | Q4: =SUM(P4)/COUNT(P4) -> 1 | S4: 8604.6 | T4: =(S4/S3)-1 -> 0.0025539808 | U4: =(S4/$S$3)-1 -> 0.0025539808 | V4: =IF(G4>T4,"Yes","No") -> Yes | W4: =IF(V4="Yes",1,0) -> 1 | X4: =SUM(W4)/COUNT(W4) -> 1 | Z4: 1520.15 | AA4: =(Z4/Z3)-1 -> 0.01149127 | AB4: =(Z4/$Z$3)-1 -> 0.01149127
A5: =A4+1 -> 3 | B5: =B4+7 -> 37757 | D5: 23259.78 | E5: =D5 -> 23259.78 | F5: =D5-D4 -> 184.27 | G5: =(D5/D4)-1 -> 0.0079855223 | H5: =D5-$D$3 -> 403.93 | I5: =(D5/$D$3)-1 -> 0.017672937 | L5: 944.3 | M5: =(L5/L4)-1 -> 0.011666899 | N5: =(L5/$L$3)-1 -> 0.015289007 | O5: =IF(G5>M5,"Yes","No") -> No | P5: =IF(O5="Yes",1,0) -> 0 | Q5: =SUM($P$4:P5)/COUNT($P$4:P5) -> 0.5 | S5: 8678.97 | T5: =(S5/S4)-1 -> 0.0086430514 | U5: =(S5/$S$3)-1 -> 0.011219106 | V5: =IF(G5>T5,"Yes","No") -> No | W5: =IF(V5="Yes",1,0) -> 0 | X5: =SUM($W$4:W5)/COUNT($W$4:W5) -> 0.5 | Z5: 1538.53 | AA5: =(Z5/Z4)-1 -> 0.012090912 | AB5: =(Z5/$Z$3)-1 -> 0.023721122
A6: =A5+1 -> 4 | B6: =B5+7 -> 37764 | D6: 22880.42 | E6: =D6 -> 22880.42 | F6: =D6-D5 -> -379.36 | G6: =(D6/D5)-1 -> -0.016309699 | H6: =D6-$D$3 -> 24.57 | I6: =(D6/$D$3)-1 -> 0.0010749983 | L6: 921.29 | M6: =(L6/L5)-1 -> -0.024367256 | N6: =(L6/$L$3)-1 -> -0.0094507999 | O6: =IF(G6>M6,"Yes","No") -> Yes | P6: =IF(O6="Yes",1,0) -> 1 | Q6: =SUM($P$4:P6)/COUNT($P$4:P6) -> 0.66666667 | S6: 8497.59 | T6: =(S6/S5)-1 -> -0.020898793 | U6: =(S6/$S$3)-1 -> -0.0099141527 | V6: =IF(G6>T6,"Yes","No") -> Yes | W6: =IF(V6="Yes",1,0) -> 1 | X6: =SUM($W$4:W6)/COUNT($W$4:W6) -> 0.66666667 | Z6: 1483.2 | AA6: =(Z6/Z5)-1 -> -0.0359629 | AB6: =(Z6/$Z$3)-1 -> -0.013094858
A7: =A6+1 -> 5 | B7: =B6+7 -> 37771 | D7: 24142.6 | E7: =D7 -> 24142.6 | F7: =D7-D6 -> 1262.18 | G7: =(D7/D6)-1 -> 0.055164197 | H7: =D7-$D$3 -> 1286.75 | I7: =(D7/$D$3)-1 -> 0.056298497 | L7: 963.59 | M7: =(L7/L6)-1 -> 0.045913882 | N7: =(L7/$L$3)-1 -> 0.036029159 | O7: =IF(G7>M7,"Yes","No") -> Yes | P7: =IF(O7="Yes",1,0) -> 1 | Q7: =SUM($P$4:P7)/COUNT($P$4:P7) -> 0.75 | S7: 8850.26 | T7: =(S7/S6)-1 -> 0.041502355 | U7: =(S7/$S$3)-1 -> 0.031176742 | V7: =IF(G7>T7,"Yes","No") -> Yes | W7: =IF(V7="Yes",1,0) -> 1 | X7: =SUM($W$4:W7)/COUNT($W$4:W7) -> 0.75 | Z7: 1595.91 | AA7: =(Z7/Z6)-1 -> 0.0759911 | AB7: =(Z7/$Z$3)-1 -> 0.06190115
A8: =A7+1 -> 6 | B8: =B7+7 -> 37778 | D8: 24843.31 | E8: =D8 -> 24843.31 | F8: =D8-D7 -> 700.71 | G8: =(D8/D7)-1 -> 0.0290238 | H8: =D8-$D$3 -> 1987.46 | I8: =(D8/$D$3)-1 -> 0.086956293 | L8: 987.76 | M8: =(L8/L7)-1 -> 0.025083282 | N8: =(L8/$L$3)-1 -> 0.062016171 | O8: =IF(G8>M8,"Yes","No") -> Yes | P8: =IF(O8="Yes",1,0) -> 1 | Q8: =SUM($P$4:P8)/COUNT($P$4:P8) -> 0.8 | S8: 9062.79 | T8: =(S8/S7)-1 -> 0.024013984 | U8: =(S8/$S$3)-1 -> 0.055939404 | V8: =IF(G8>T8,"Yes","No") -> Yes | W8: =IF(V8="Yes",1,0) -> 1 | X8: =SUM($W$4:W8)/COUNT($W$4:W8) -> 0.8 | Z8: 1627.42 | AA8: =(Z8/Z7)-1 -> 0.019744221 | AB8: =(Z8/$Z$3)-1 -> 0.082867561
A9: =A8+1 -> 7 | B9: =B8+7 -> 37785 | D9: 24777.34 | E9: =D9 -> 24777.34 | F9: =D9-D8 -> -65.97 | G9: =(D9/D8)-1 -> -0.0026554433 | H9: =D9-$D$3 -> 1921.49 | I9: =(D9/$D$3)-1 -> 0.084069943 | L9: =995.16-6.55 -> 988.61 | M9: =(L9/L8)-1 -> 0.00086053292 | N9: =(L9/$L$3)-1 -> 0.062930071 | O9: =IF(G9>M9,"Yes","No") -> No | P9: =IF(O9="Yes",1,0) -> 0 | Q9: =SUM($P$4:P9)/COUNT($P$4:P9) -> 0.66666667 | S9: =9176.41-59.29 -> 9117.12 | T9: =(S9/S8)-1 -> 0.0059948426 | U9: =(S9/$S$3)-1 -> 0.062269594 | V9: =IF(G9>T9,"Yes","No") -> No | W9: =IF(V9="Yes",1,0) -> 0 | X9: =SUM($W$4:W9)/COUNT($W$4:W9) -> 0.66666667 | Z9: =1637.82-11.33 -> 1626.49 | AA9: =(Z9/Z8)-1 -> -0.00057145666 | AB9: =(Z9/$Z$3)-1 -> 0.082248749
A10: =A9+1 -> 8 | B10: =B9+7 -> 37792 | D10: 25072.64 | E10: =D10 -> 25072.64 | F10: =D10-D9 -> 295.3 | G10: =(D10/D9)-1 -> 0.011918148 | H10: =D10-$D$3 -> 2216.79 | I10: =(D10/$D$3)-1 -> 0.096990048 | L10: 995.69 | M10: =(L10/L9)-1 -> 0.0071615703 | N10: =(L10/$L$3)-1 -> 0.070542319 | O10: =IF(G10>M10,"Yes","No") -> Yes | P10: =IF(O10="Yes",1,0) -> 1 | Q10: =SUM($P$4:P10)/COUNT($P$4:P10) -> 0.71428571 | S10: 9200.75 | T10: =(S10/S9)-1 -> 0.0091728528 | U10: =(S10/$S$3)-1 -> 0.072013637 | V10: =IF(G10>T10,"Yes","No") -> Yes | W10: =IF(V10="Yes",1,0) -> 1 | X10: =SUM($W$4:W10)/COUNT($W$4:W10) -> 0.71428571 | Z10: 1644.72 | AA10: =(Z10/Z9)-1 -> 0.011208184 | AB10: =(Z10/$Z$3)-1 -> 0.094378793
A11: =A10+1 -> 9 | B11: =B10+7 -> 37799 | D11: 24857.12 | E11: =D11 -> 24857.12 | F11: =D11-D10 -> -215.52 | G11: =(D11/D10)-1 -> -0.008595824 | H11: =D11-$D$3 -> 2001.27 | I11: =(D11/$D$3)-1 -> 0.087560515 | L11: 976.22 | M11: =(L11/L10)-1 -> -0.019554279 | N11: =(L11/$L$3)-1 -> 0.049608636 | O11: =IF(G11>M11,"Yes","No") -> Yes | P11: =IF(O11="Yes",1,0) -> 1 | Q11: =SUM($P$4:P11)/COUNT($P$4:P11) -> 0.75 | S11: 8989.05 | T11: =(S11/S10)-1 -> -0.023008994 | U11: =(S11/$S$3)-1 -> 0.047347682 | V11: =IF(G11>T11,"Yes","No") -> Yes | W11: =IF(V11="Yes",1,0) -> 1 | X11: =SUM($W$4:W11)/COUNT($W$4:W11) -> 0.75 | Z11: 1625.26 | AA11: =(Z11/Z10)-1 -> -0.011831801 | AB11: =(Z11/$Z$3)-1 -> 0.08143032
A12: =A11+1 -> 10 | B12: =B11+7 -> 37806 | D12: 24907.37 | E12: =D12 -> 24907.37 | F12: =D12-D11 -> 50.25 | G12: =(D12/D11)-1 -> 0.0020215536 | H12: =D12-$D$3 -> 2051.52 | I12: =(D12/$D$3)-1 -> 0.089759077 | L12: 991.66 | M12: =(L12/L11)-1 -> 0.015816107 | N12: =(L12/$L$3)-1 -> 0.066209358 | O12: =IF(G12>M12,"Yes","No") -> No | P12: =IF(O12="Yes",1,0) -> 0 | Q12: =SUM($P$4:P12)/COUNT($P$4:P12) -> 0.66666667 | S12: 9070.21 | T12: =(S12/S11)-1 -> 0.0090287628 | U12: =(S12/$S$3)-1 -> 0.056803935 | V12: =IF(G12>T12,"Yes","No") -> No | W12: =IF(V12="Yes",1,0) -> 0 | X12: =SUM($W$4:W12)/COUNT($W$4:W12) -> 0.66666667 | Z12: 1663.46 | AA12: =(Z12/Z11)-1 -> 0.023503932 | AB12: =(Z12/$Z$3)-1 -> 0.10684818
A13: =A12+1 -> 11 | B13: =B12+7 -> 37813 | D13: 25578.29 | E13: =D13 -> 25578.29 | F13: =D13-D12 -> 670.92 | G13: =(D13/D12)-1 -> 0.026936606 | H13: =D13-$D$3 -> 2722.44 | I13: =(D13/$D$3)-1 -> 0.11911349 | L13: 998.14 | M13: =(L13/L12)-1 -> 0.0065344977 | N13: =(L13/$L$3)-1 -> 0.073176501 | O13: =IF(G13>M13,"Yes","No") -> Yes | P13: =IF(O13="Yes",1,0) -> 1 | Q13: =SUM($P$4:P13)/COUNT($P$4:P13) -> 0.7 | S13: 9119.59 | T13: =(S13/S12)-1 -> 0.0054441959 | U13: =(S13/$S$3)-1 -> 0.062557383 | V13: =IF(G13>T13,"Yes","No") -> Yes | W13: =IF(V13="Yes",1,0) -> 1 | X13: =SUM($W$4:W13)/COUNT($W$4:W13) -> 0.7 | Z13: 1733.93 | AA13: =(Z13/Z12)-1 -> 0.042363507 | AB13: =(Z13/$Z$3)-1 -> 0.15373816
A14: =A13+1 -> 12 | B14: =B13+7 -> 37820 | D14: 25192.44 | E14: =D14 -> 25192.44 | F14: =D14-D13 -> -385.85 | G14: =(D14/D13)-1 -> -0.015085058 | H14: =D14-$D$3 -> 2336.59 | I14: =(D14/$D$3)-1 -> 0.10223159 | L14: 993.32 | M14: =(L14/L13)-1 -> -0.0048289819 | N14: =(L14/$L$3)-1 -> 0.067994151 | O14: =IF(G14>M14,"Yes","No") -> No | P14: =IF(O14="Yes",1,0) -> 0 | Q14: =SUM($P$4:P14)/COUNT($P$4:P14) -> 0.63636364 | S14: 9188.15 | T14: =(S14/S13)-1 -> 0.0075178818 | U14: =(S14/$S$3)-1 -> 0.070545564 | V14: =IF(G14>T14,"Yes","No") -> No | W14: =IF(V14="Yes",1,0) -> 0 | X14: =SUM($W$4:W14)/COUNT($W$4:W14) -> 0.63636364 | Z14: 1708.5 | AA14: =(Z14/Z13)-1 -> -0.014666105 | AB14: =(Z14/$Z$3)-1 -> 0.13681731
A15: =A14+1 -> 13 | B15: =B14+7 -> 37827 | D15: 25421.8 | E15: =D15 -> 25421.8 | F15: =D15-D14 -> 229.36 | G15: =(D15/D14)-1 -> 0.0091043186 | H15: =D15-$D$3 -> 2565.95 | I15: =(D15/$D$3)-1 -> 0.11226666 | L15: 998.68 | M15: =(L15/L14)-1 -> 0.0053960456 | N15: =(L15/$L$3)-1 -> 0.073757096 | O15: =IF(G15>M15,"Yes","No") -> Yes | P15: =IF(O15="Yes",1,0) -> 1 | Q15: =SUM($P$4:P15)/COUNT($P$4:P15) -> 0.66666667 | S15: 9284.57 | T15: =(S15/S14)-1 -> 0.010493951 | U15: =(S15/$S$3)-1 -> 0.081779817 | V15: =IF(G15>T15,"Yes","No") -> No | W15: =IF(V15="Yes",1,0) -> 0 | X15: =SUM($W$4:W15)/COUNT($W$4:W15) -> 0.58333333 | Z15: 1730.7 | AA15: =(Z15/Z14)-1 -> 0.012993854 | AB15: =(Z15/$Z$3)-1 -> 0.15158895
A16: =A15+1 -> 14 | B16: =B15+7 -> 37834 | D16: 25266.57 | E16: =D16 -> 25266.57 | F16: =D16-D15 -> -155.23 | G16: =(D16/D15)-1 -> -0.0061061766 | H16: =D16-$D$3 -> 2410.72 | I16: =(D16/$D$3)-1 -> 0.10547497 | L16: 980.15 | M16: =(L16/L15)-1 -> -0.018554492 | N16: =(L16/$L$3)-1 -> 0.053834079 | O16: =IF(G16>M16,"Yes","No") -> Yes | P16: =IF(O16="Yes",1,0) -> 1 | Q16: =SUM($P$4:P16)/COUNT($P$4:P16) -> 0.69230769 | S16: 9153.97 | T16: =(S16/S15)-1 -> -0.014066349 | U16: =(S16/$S$3)-1 -> 0.066563125 | V16: =IF(G16>T16,"Yes","No") -> Yes | W16: =IF(V16="Yes",1,0) -> 1 | X16: =SUM($W$4:W16)/COUNT($W$4:W16) -> 0.61538462 | Z16: 1715.62 | AA16: =(Z16/Z15)-1 -> -0.0087132374 | AB16: =(Z16/$Z$3)-1 -> 0.14155488
A17: =A16+1 -> 15 | B17: =B16+7 -> 37841 | D17: 25228.34 | E17: =D17 -> 25228.34 | F17: =D17-D16 -> -38.23 | G17: =(D17/D16)-1 -> -0.0015130665 | H17: =D17-$D$3 -> 2372.49 | I17: =(D17/$D$3)-1 -> 0.10380231 | L17: 977.59 | M17: =(L17/L16)-1 -> -0.0026118451 | N17: =(L17/$L$3)-1 -> 0.051081627 | O17: =IF(G17>M17,"Yes","No") -> Yes | P17: =IF(O17="Yes",1,0) -> 1 | Q17: =SUM($P$4:P17)/COUNT($P$4:P17) -> 0.71428571 | S17: 9191.09 | T17: =(S17/S16)-1 -> 0.0040550712 | U17: =(S17/$S$3)-1 -> 0.070888114 | V17: =IF(G17>T17,"Yes","No") -> No | W17: =IF(V17="Yes",1,0) -> 0 | X17: =SUM($W$4:W17)/COUNT($W$4:W17) -> 0.57142857 | Z17: 1644.03 | AA17: =(Z17/Z16)-1 -> -0.041728355 | AB17: =(Z17/$Z$3)-1 -> 0.093919674
A18: =A17+1 -> 16 | B18: =B17+7 -> 37848 | D18: 24951.71 | E18: =D18 -> 24951.71 | F18: =D18-D17 -> -276.63 | G18: =(D18/D17)-1 -> -0.01096505 | H18: =D18-$D$3 -> 2095.86 | I18: =(D18/$D$3)-1 -> 0.091699062 | L18: 990.67 | M18: =(L18/L17)-1 -> 0.013379842 | N18: =(L18/$L$3)-1 -> 0.065144934 | O18: =IF(G18>M18,"Yes","No") -> No | P18: =IF(O18="Yes",1,0) -> 0 | Q18: =SUM($P$4:P18)/COUNT($P$4:P18) -> 0.66666667 | S18: 9321.69 | T18: =(S18/S17)-1 -> 0.014209414 | U18: =(S18/$S$3)-1 -> 0.086104806 | V18: =IF(G18>T18,"Yes","No") -> No | W18: =IF(V18="Yes",1,0) -> 0 | X18: =SUM($W$4:W18)/COUNT($W$4:W18) -> 0.53333333 | Z18: 1702.01 | AA18: =(Z18/Z17)-1 -> 0.035266996 | AB18: =(Z18/$Z$3)-1 -> 0.13249894
A19: =A18+1 -> 17 | B19: =B18+7 -> 37855 | D19: 25454.04 | E19: =D19 -> 25454.04 | F19: =D19-D18 -> 502.33 | G19: =(D19/D18)-1 -> 0.020132087 | H19: =D19-$D$3 -> 2598.19 | I19: =(D19/$D$3)-1 -> 0.11367724 | L19: 993.06 | M19: =(L19/L18)-1 -> 0.0024125087 | N19: =(L19/$L$3)-1 -> 0.067714605 | O19: =IF(G19>M19,"Yes","No") -> Yes | P19: =IF(O19="Yes",1,0) -> 1 | Q19: =SUM($P$4:P19)/COUNT($P$4:P19) -> 0.6875 | S19: 9348.87 | T19: =(S19/S18)-1 -> 0.0029157803 | U19: =(S19/$S$3)-1 -> 0.089271649 | V19: =IF(G19>T19,"Yes","No") -> Yes | W19: =IF(V19="Yes",1,0) -> 1 | X19: =SUM($W$4:W19)/COUNT($W$4:W19) -> 0.5625 | Z19: 1765.32 | AA19: =(Z19/Z18)-1 -> 0.037197196 | AB19: =(Z19/$Z$3)-1 -> 0.17462472
A20: =A19+1 -> 18 | B20: =B19+7 -> 37862 | D20: 26198.38 | E20: =D20 -> 26198.38 | F20: =D20-D19 -> 744.34 | G20: =(D20/D19)-1 -> 0.029242509 | H20: =D20-$D$3 -> 3342.53 | I20: =(D20/$D$3)-1 -> 0.14624396 | L20: 1008.01 | M20: =(L20/L19)-1 -> 0.015054478 | N20: =(L20/$L$3)-1 -> 0.083788491 | O20: =IF(G20>M20,"Yes","No") -> Yes | P20: =IF(O20="Yes",1,0) -> 1 | Q20: =SUM($P$4:P20)/COUNT($P$4:P20) -> 0.70588235 | S20: 9415.82 | T20: =(S20/S19)-1 -> 0.0071612933 | U20: =(S20/$S$3)-1 -> 0.097072243 | V20: =IF(G20>T20,"Yes","No") -> Yes | W20: =IF(V20="Yes",1,0) -> 1 | X20: =SUM($W$4:W20)/COUNT($W$4:W20) -> 0.58823529 | Z20: 1810.45 | AA20: =(Z20/Z19)-1 -> 0.02556477 | AB20: =(Z20/$Z$3)-1 -> 0.20465373
A21: =A20+1 -> 19 | B21: =B20+7 -> 37869 | D21: 26545.65 | E21: =D21 -> 26545.65 | F21: =D21-D20 -> 347.27 | G21: =(D21/D20)-1 -> 0.0132554 | H21: =D21-$D$3 -> 3689.8 | I21: =(D21/$D$3)-1 -> 0.16143788 | L21: 1021.39 | M21: =(L21/L20)-1 -> 0.013273678 | N21: =(L21/$L$3)-1 -> 0.098174351 | O21: =IF(G21>M21,"Yes","No") -> No | P21: =IF(O21="Yes",1,0) -> 0 | Q21: =SUM($P$4:P21)/COUNT($P$4:P21) -> 0.66666667 | S21: 9503.34 | T21: =(S21/S20)-1 -> 0.009294995 | U21: =(S21/$S$3)-1 -> 0.10726952 | V21: =IF(G21>T21,"Yes","No") -> Yes | W21: =IF(V21="Yes",1,0) -> 1 | X21: =SUM($W$4:W21)/COUNT($W$4:W21) -> 0.61111111 | Z21: 1858.24 | AA21: =(Z21/Z20)-1 -> 0.026396752 | AB21: =(Z21/$Z$3)-1 -> 0.23645268
... A37: =A36+1 -> 35 | B37: =B36+7 -> 37981 | D37: 29690.49 | E37: =D37 -> 29690.49 | F37: =D37-D36 -> 362.49 | G37: =(D37/D36)-1 -> 0.012359861 | H37: =D37-$D$3 -> 6834.64 | I37: =(D37/$D$3)-1 -> 0.29903241 | L37: 1095.89 | M37: =(L37/L36)-1 -> 0.0066411919 | N37: =(L37/$L$3)-1 -> 0.17827499 | O37: =IF(G37>M37,"Yes","No") -> Yes | P37: =IF(O37="Yes",1,0) -> 1 | Q37: =SUM($P$4:P37)/COUNT($P$4:P37) -> 0.67647059 | S37: 10324.67 | T37: =(S37/S36)-1 -> 0.004519265 | U37: =(S37/$S$3)-1 -> 0.20296574 | V37: =IF(G37>T37,"Yes","No") -> Yes | W37: =IF(V37="Yes",1,0) -> 1 | X37: =SUM($W$4:W37)/COUNT($W$4:W37) -> 0.61764706 | Z37: 1973.14 | AA37: =(Z37/Z36)-1 -> 0.0082370134 | AB37: =(Z37/$Z$3)-1 -> 0.31290589
A38: =A37+1 -> 36 | B38: =B37+7 -> 37988 | D38: 30649.47 | E38: =D38 -> 30649.47 | F38: =D38-D37 -> 958.98 | G38: =(D38/D37)-1 -> 0.032299231 | H38: =D38-$D$3 -> 7793.62 | I38: =(D38/$D$3)-1 -> 0.34099016 | J38: 0 | L38: 1108.48 | M38: =(L38/L37)-1 -> 0.011488379 | N38: =(L38/$L$3)-1 -> 0.19181146 | O38: =IF(G38>M38,"Yes","No") -> Yes | P38: =IF(O38="Yes",1,0) -> 1 | Q38: =SUM($P$4:P38)/COUNT($P$4:P38) -> 0.68571429 | R38: 0 | S38: 10409.85 | T38: =(S38/S37)-1 -> 0.0082501426 | U38: =(S38/$S$3)-1 -> 0.21289038 | V38: =IF(G38>T38,"Yes","No") -> Yes | W38: =IF(V38="Yes",1,0) -> 1 | X38: =SUM($W$4:W38)/COUNT($W$4:W38) -> 0.62857143 | Z38: 2006.68 | AA38: =(Z38/Z37)-1 -> 0.016998287 | AB38: =(Z38/$Z$3)-1 -> 0.33522304
A39: =A38+1 -> 37 | B39: =B38+7 -> 37995 | D39: 30712.11 | E39: =D39 -> 30712.11 | F39: =D39-D38 -> 62.64 | G39: =(D39/D38)-1 -> 0.0020437548 | H39: =D39-$D$3 -> 7856.26 | I39: =(D39/$D$3)-1 -> 0.34373082 | J39: =(E39/$E$38)-1 -> 0.0020437548 | L39: 1121.86 | M39: =(L39/L38)-1 -> 0.012070583 | N39: =(L39/$L$3)-1 -> 0.20619732 | O39: =IF(G39>M39,"Yes","No") -> No | P39: =IF(O39="Yes",1,0) -> 0 | Q39: =SUM($P$4:P39)/COUNT($P$4:P39) -> 0.66666667 | R39: =(L39/$L$38)-1 -> 0.012070583 | S39: 10458.89 | T39: =(S39/S38)-1 -> 0.0047109228 | U39: =(S39/$S$3)-1 -> 0.21860421 | V39: =IF(G39>T39,"Yes","No") -> No | W39: =IF(V39="Yes",1,0) -> 0 | X39: =SUM($W$4:W39)/COUNT($W$4:W39) -> 0.61111111 | Z39: 2086.92 | AA39: =(Z39/Z38)-1 -> 0.039986445 | AB39: =(Z39/$Z$3)-1 -> 0.38861386
A40: =A39+1 -> 38 | B40: =B39+7 -> 38002 | D40: 30500.54 | E40: =D40 -> 30500.54 | F40: =D40-D39 -> -211.57 | G40: =(D40/D39)-1 -> -0.0068888136 | H40: =D40-$D$3 -> 7644.69 | I40: =(D40/$D$3)-1 -> 0.33447411 | J40: =(E40/$E$38)-1 -> -0.0048591379 | L40: 1139.83 | M40: =(L40/L39)-1 -> 0.016018041 | N40: =(L40/$L$3)-1 -> 0.22551823 | O40: =IF(G40>M40,"Yes","No") -> No | P40: =IF(O40="Yes",1,0) -> 0 | Q40: =SUM($P$4:P40)/COUNT($P$4:P40) -> 0.64864865 | R40: =(L40/$L$38)-1 -> 0.028281972 | S40: 10600.51 | T40: =(S40/S39)-1 -> 0.013540634 | U40: =(S40/$S$3)-1 -> 0.23510489 | V40: =IF(G40>T40,"Yes","No") -> No | W40: =IF(V40="Yes",1,0) -> 0 | X40: =SUM($W$4:W40)/COUNT($W$4:W40) -> 0.59459459 | Z40: 2140.46 | AA40: =(Z40/Z39)-1 -> 0.025655032 | AB40: =(Z40/$Z$3)-1 -> 0.42423879
A41: =A40+1 -> 39 | B41: =B40+7 -> 38009 | D41: 30340.26 | E41: =D41+Holdings_Old!$E$32 -> 30340.26 | F41: =E41-D40 -> -160.28 | G41: =(E41/E40)-1 -> -0.0052549889 | H41: =E41-$D$3 -> 7484.41 | I41: =(E41/$D$3)-1 -> 0.32746146 | J41: =(E41/$E$38)-1 -> -0.010088592 | L41: 1141.55 | M41: =(L41/L40)-1 -> 0.001508997 | N41: =(L41/$L$3)-1 -> 0.22736754 | O41: =IF(G41>M41,"Yes","No") -> No | P41: =IF(O41="Yes",1,0) -> 0 | Q41: =SUM($P$4:P41)/COUNT($P$4:P41) -> 0.63157895 | R41: =(L41/$L$38)-1 -> 0.029833646 | S41: 10568.29 | T41: =(S41/S40)-1 -> -0.0030394764 | U41: =(S41/$S$3)-1 -> 0.23135081 | V41: =IF(G41>T41,"Yes","No") -> No | W41: =IF(V41="Yes",1,0) -> 0 | X41: =SUM($W$4:W41)/COUNT($W$4:W41) -> 0.57894737 | Z41: 2123.87 | AA41: =(Z41/Z40)-1 -> -0.0077506704 | AB41: =(Z41/$Z$3)-1 -> 0.41319999
A42: =A41+1 -> 40 | B42: =B41+7 -> 38016 | D42: 29390.96 | E42: =D42+Holdings_Old!$E$32 -> 29390.96 | F42: =E42-E41 -> -949.3 | G42: =(E42/E41)-1 -> -0.03128846 | H42: =E42-$D$3 -> 6535.11 | I42: =(E42/$D$3)-1 -> 0.28592724 | J42: =(E42/$E$38)-1 -> -0.041061395 | L42: 1131.13 | M42: =(L42/L41)-1 -> -0.0091279401 | N42: =(L42/$L$3)-1 -> 0.2161642 | O42: =IF(G42>M42,"Yes","No") -> No | P42: =IF(O42="Yes",1,0) -> 0 | Q42: =SUM($P$4:P42)/COUNT($P$4:P42) -> 0.61538462 | R42: =(L42/$L$38)-1 -> 0.020433386 | S42: 10488.07 | T42: =(S42/S41)-1 -> -0.007590632 | U42: =(S42/$S$3)-1 -> 0.22200408 | V42: =IF(G42>T42,"Yes","No") -> No | W42: =IF(V42="Yes",1,0) -> 0 | X42: =SUM($W$4:W42)/COUNT($W$4:W42) -> 0.56410256 | Z42: 2066.15 | AA42: =(Z42/Z41)-1 -> -0.027176805 | AB42: =(Z42/$Z$3)-1 -> 0.37479373
A43: =A42+1 -> 41 | B43: =B42+7 -> 38023 | D43: 29673.82 | E43: =D43+Holdings_Old!$E$32 -> 29673.82 | F43: =E43-E42 -> 282.86 | G43: =(E43/E42)-1 -> 0.0096240477 | H43: =E43-$D$3 -> 6817.97 | I43: =(E43/$D$3)-1 -> 0.29830306 | J43: =(E43/$E$38)-1 -> -0.031832524 | L43: 1142.76 | M43: =(L43/L42)-1 -> 0.010281754 | N43: =(L43/$L$3)-1 -> 0.2286685 | O43: =IF(G43>M43,"Yes","No") -> No | P43: =IF(O43="Yes",1,0) -> 0 | Q43: =SUM($P$4:P43)/COUNT($P$4:P43) -> 0.6 | R43: =(L43/$L$38)-1 -> 0.030925231 | S43: 10593.03 | T43: =(S43/S42)-1 -> 0.010007561 | U43: =(S43/$S$3)-1 -> 0.23423336 | V43: =IF(G43>T43,"Yes","No") -> No | W43: =IF(V43="Yes",1,0) -> 0 | X43: =SUM($W$4:W43)/COUNT($W$4:W43) -> 0.55 | Z43: 2064.01 | AA43: =(Z43/Z42)-1 -> -0.0010357428 | AB43: =(Z43/$Z$3)-1 -> 0.3733698
A44: =A43+1 -> 42 | B44: =B43+7 -> 38030 | D44: 29580.97 | E44: =D44+Holdings_Old!$E$32 -> 29580.97 | F44: =E44-E43 -> -92.85 | G44: =(E44/E43)-1 -> -0.0031290208 | H44: =E44-$D$3 -> 6725.12 | I44: =(E44/$D$3)-1 -> 0.29424064 | J44: =(E44/$E$38)-1 -> -0.034861941 | L44: 1145.81 | M44: =(L44/L43)-1 -> 0.0026689769 | N44: =(L44/$L$3)-1 -> 0.23194779 | O44: =IF(G44>M44,"Yes","No") -> No | P44: =IF(O44="Yes",1,0) -> 0 | Q44: =SUM($P$4:P44)/COUNT($P$4:P44) -> 0.58536585 | R44: =(L44/$L$38)-1 -> 0.033676747 | S44: 10628.85 | T44: =(S44/S43)-1 -> 0.0033814688 | U44: =(S44/$S$3)-1 -> 0.23840688 | V44: =IF(G44>T44,"Yes","No") -> No | W44: =IF(V44="Yes",1,0) -> 0 | X44: =SUM($W$4:W44)/COUNT($W$4:W44) -> 0.53658537 | Z44: 2053.56 | AA44: =(Z44/Z43)-1 -> -0.00506296 | AB44: =(Z44/$Z$3)-1 -> 0.36641648
A45: =A44+1 -> 43 | B45: =B44+7 -> 38037 | D45: 29455.64 | E45: =D45+Holdings_Old!$E$32 -> 29455.64 | F45: =E45-E44 -> -125.33 | G45: =(E45/E44)-1 -> -0.0042368455 | H45: =E45-$D$3 -> 6599.79 | I45: =(E45/$D$3)-1 -> 0.28875715 | J45: =(E45/$E$38)-1 -> -0.038951081 | L45: 1144.11 | M45: =(L45/L44)-1 -> -0.0014836666 | N45: =(L45/$L$3)-1 -> 0.23011999 | O45: =IF(G45>M45,"Yes","No") -> No | P45: =IF(O45="Yes",1,0) -> 0 | Q45: =SUM($P$4:P45)/COUNT($P$4:P45) -> 0.57142857 | R45: =(L45/$L$38)-1 -> 0.032143115 | S45: 10619.03 | T45: =(S45/S44)-1 -> -0.00092390052 | U45: =(S45/$S$3)-1 -> 0.23726272 | V45: =IF(G45>T45,"Yes","No") -> No | W45: =IF(V45="Yes",1,0) -> 0 | X45: =SUM($W$4:W45)/COUNT($W$4:W45) -> 0.52380952 | Z45: 2037.93 | AA45: =(Z45/Z44)-1 -> -0.0076111728 | AB45: =(Z45/$Z$3)-1 -> 0.35601645
A46: =A45+1 -> 44 | B46: =B45+7 -> 38044 | D46: 29503.45 | E46: =D46+Holdings_Old!$E$32 -> 29503.45 | F46: =E46-E45 -> 47.81 | G46: =(E46/E45)-1 -> 0.0016231187 | H46: =E46-$D$3 -> 6647.6 | I46: =(E46/$D$3)-1 -> 0.29084895 | J46: =(E46/$E$38)-1 -> -0.037391185 | L46: 1144.94 | M46: =(L46/L45)-1 -> 0.00072545472 | N46: =(L46/$L$3)-1 -> 0.23101239 | O46: =IF(G46>M46,"Yes","No") -> Yes | P46: =IF(O46="Yes",1,0) -> 1 | Q46: =SUM($P$4:P46)/COUNT($P$4:P46) -> 0.58139535 | R46: =(L46/$L$38)-1 -> 0.032891888 | S46: 10583.92 | T46: =(S46/S45)-1 -> -0.0033063284 | U46: =(S46/$S$3)-1 -> 0.23317192 | V46: =IF(G46>T46,"Yes","No") -> Yes | W46: =IF(V46="Yes",1,0) -> 1 | X46: =SUM($W$4:W46)/COUNT($W$4:W46) -> 0.53488372 | Z46: 2029.82 | AA46: =(Z46/Z45)-1 -> -0.0039795282 | AB46: =(Z46/$Z$3)-1 -> 0.35062014
A47: =A46+1 -> 45 | B47: =B46+7 -> 38051 | D47: 29619.45 | E47: =D47+Holdings_Old!$E$32 -> 29619.45 | F47: =E47-E46 -> 116 | G47: =(E47/E46)-1 -> 0.0039317436 | H47: =E47-$D$3 -> 6763.6 | I47: =(E47/$D$3)-1 -> 0.29592424 | J47: =(E47/$E$38)-1 -> -0.033606454 | L47: 1156.86 | M47: =(L47/L46)-1 -> 0.010411026 | N47: =(L47/$L$3)-1 -> 0.24382849 | O47: =IF(G47>M47,"Yes","No") -> No | P47: =IF(O47="Yes",1,0) -> 0 | Q47: =SUM($P$4:P47)/COUNT($P$4:P47) -> 0.56818182 | R47: =(L47/$L$38)-1 -> 0.043645352 | S47: 10595.55 | T47: =(S47/S46)-1 -> 0.0010988367 | U47: =(S47/$S$3)-1 -> 0.23452698 | V47: =IF(G47>T47,"Yes","No") -> Yes | W47: =IF(V47="Yes",1,0) -> 1 | X47: =SUM($W$4:W47)/COUNT($W$4:W47) -> 0.54545455 | Z47: 2047.63 | AA47: =(Z47/Z46)-1 -> 0.008774177 | AB47: =(Z47/$Z$3)-1 -> 0.36247072
A48: =A47+1 -> 46 | B48: =B47+7 -> 38058 | D48: 29016.49 | E48: =D48+Holdings_Old!$E$32 -> 29016.49 | F48: =E48-E47 -> -602.96 | G48: =(E48/E47)-1 -> -0.020356894 | H48: =E48-$D$3 -> 6160.64 | I48: =(E48/$D$3)-1 -> 0.26954325 | J48: =(E48/$E$38)-1 -> -0.053279225 | L48: 1120.57 | M48: =(L48/L47)-1 -> -0.031369396 | N48: =(L48/$L$3)-1 -> 0.20481034 | O48: =IF(G48>M48,"Yes","No") -> Yes | P48: =IF(O48="Yes",1,0) -> 1 | Q48: =SUM($P$4:P48)/COUNT($P$4:P48) -> 0.57777778 | R48: =(L48/$L$38)-1 -> 0.010906827 | S48: 10240.08 | T48: =(S48/S47)-1 -> -0.03354899 | U48: =(S48/$S$3)-1 -> 0.19310984 | V48: =IF(G48>T48,"Yes","No") -> Yes | W48: =IF(V48="Yes",1,0) -> 1 | X48: =SUM($W$4:W48)/COUNT($W$4:W48) -> 0.55555556 | Z48: 1984.73 | AA48: =(Z48/Z47)-1 -> -0.03071844 | AB48: =(Z48/$Z$3)-1 -> 0.32061775
A49: =A48+1 -> 47 | B49: =B48+7 -> 38065 | D49: 28837.81 | E49: =D49+Holdings_Old!$E$32 -> 28837.81 | F49: =E49-E48 -> -178.68 | G49: =(E49/E48)-1 -> -0.0061578778 | H49: =E49-$D$3 -> 5981.96 | I49: =(E49/$D$3)-1 -> 0.26172555 | J49: =(E49/$E$38)-1 -> -0.059109016 | L49: 1109.74 | M49: =(L49/L48)-1 -> -0.0096647242 | N49: =(L49/$L$3)-1 -> 0.19316618 | O49: =IF(G49>M49,"Yes","No") -> Yes | P49: =IF(O49="Yes",1,0) -> 1 | Q49: =SUM($P$4:P49)/COUNT($P$4:P49) -> 0.58695652 | R49: =(L49/$L$38)-1 -> 0.0011366917 | S49: 10186.6 | T49: =(S49/S48)-1 -> -0.0052226154 | U49: =(S49/$S$3)-1 -> 0.18687869 | V49: =IF(G49>T49,"Yes","No") -> No | W49: =IF(V49="Yes",1,0) -> 0 | X49: =SUM($W$4:W49)/COUNT($W$4:W49) -> 0.54347826 | Z49: 1940.47 | AA49: =(Z49/Z48)-1 -> -0.022300263 | AB49: =(Z49/$Z$3)-1 -> 0.29116762
A50: =A49+1 -> 48 | B50: =B49+7 -> 38072 | D50: 28946.8 | E50: =D50+Holdings_Old!$E$32 -> 28946.8 | F50: =E50-E49 -> 108.99 | G50: =(E50/E49)-1 -> 0.0037794132 | H50: =E50-$D$3 -> 6090.95 | I50: =(E50/$D$3)-1 -> 0.26649414 | J50: =(E50/$E$38)-1 -> -0.055553 | L50: 1108.06 | M50: =(L50/L49)-1 -> -0.0015138681 | N50: =(L50/$L$3)-1 -> 0.19135988 | O50: =IF(G50>M50,"Yes","No") -> Yes | P50: =IF(O50="Yes",1,0) -> 1 | Q50: =SUM($P$4:P50)/COUNT($P$4:P50) -> 0.59574468 | R50: =(L50/$L$38)-1 -> -0.00037889723 | S50: 10212.97 | T50: =(S50/S49)-1 -> 0.002588695 | U50: =(S50/$S$3)-1 -> 0.18995116 | V50: =IF(G50>T50,"Yes","No") -> Yes | W50: =IF(V50="Yes",1,0) -> 1 | X50: =SUM($W$4:W50)/COUNT($W$4:W50) -> 0.55319149 | Z50: 1960.02 | AA50: =(Z50/Z49)-1 -> 0.010074879 | AB50: =(Z50/$Z$3)-1 -> 0.30417598
A51: =A50+1 -> 49 | B51: =B50+7 -> 38079 | D51: 29704.21 | E51: =D51+Holdings_Old!$E$32 -> 29704.21 | F51: =E51-E50 -> 757.41 | G51: =(E51/E50)-1 -> 0.026165587 | H51: =E51-$D$3 -> 6848.36 | I51: =(E51/$D$3)-1 -> 0.2996327 | J51: =(E51/$E$38)-1 -> -0.03084099 | L51: 1141.84 | M51: =(L51/L50)-1 -> 0.030485714 | N51: =(L51/$L$3)-1 -> 0.22767934 | O51: =IF(G51>M51,"Yes","No") -> No | P51: =IF(O51="Yes",1,0) -> 0 | Q51: =SUM($P$4:P51)/COUNT($P$4:P51) -> 0.58333333 | R51: =(L51/$L$38)-1 -> 0.030095266 | S51: 10470.59 | T51: =(S51/S50)-1 -> 0.025224788 | U51: =(S51/$S$3)-1 -> 0.21996742 | V51: =IF(G51>T51,"Yes","No") -> Yes | W51: =IF(V51="Yes",1,0) -> 1 | X51: =SUM($W$4:W51)/COUNT($W$4:W51) -> 0.5625 | Z51: 2057.17 | AA51: =(Z51/Z50)-1 -> 0.049565821 | AB51: =(Z51/$Z$3)-1 -> 0.36881854
A52: =A51+1 -> 50 | B52: =B51+7 -> 38086 | D52: 29609.72 | E52: =D52+Holdings_Old!$E$32 -> 29609.72 | F52: =E52-E51 -> -94.49 | G52: =(E52/E51)-1 -> -0.0031810306 | H52: =E52-$D$3 -> 6753.87 | I52: =(E52/$D$3)-1 -> 0.29549853 | J52: =(E52/$E$38)-1 -> -0.033923915 | L52: 1139.32 | M52: =(L52/L51)-1 -> -0.0022069642 | N52: =(L52/$L$3)-1 -> 0.2249699 | O52: =IF(G52>M52,"Yes","No") -> No | P52: =IF(O52="Yes",1,0) -> 0 | Q52: =SUM($P$4:P52)/COUNT($P$4:P52) -> 0.57142857 | R52: =(L52/$L$38)-1 -> 0.027821882 | S52: 10442.03 | T52: =(S52/S51)-1 -> -0.00272764 | U52: =(S52/$S$3)-1 -> 0.21663979 | V52: =IF(G52>T52,"Yes","No") -> No | W52: =IF(V52="Yes",1,0) -> 0 | X52: =SUM($W$4:W52)/COUNT($W$4:W52) -> 0.55102041 | Z52: 2052.88 | AA52: =(Z52/Z51)-1 -> -0.0020853892 | AB52: =(Z52/$Z$3)-1 -> 0.36596402
A53: =A52+1 -> 51 | B53: =B52+7 -> 38093 | D53: 29251.01 | E53: =D53+Holdings_Old!$E$32 -> 29251.01 | F53: =E53-E52 -> -358.71 | G53: =(E53/E52)-1 -> -0.012114603 | H53: =E53-$D$3 -> 6395.16 | I53: =(E53/$D$3)-1 -> 0.27980408 | J53: =(E53/$E$38)-1 -> -0.045627543 | L53: 1134.61 | M53: =(L53/L52)-1 -> -0.0041340449 | N53: =(L53/$L$3)-1 -> 0.21990581 | O53: =IF(G53>M53,"Yes","No") -> No | P53: =IF(O53="Yes",1,0) -> 0 | Q53: =SUM($P$4:P53)/COUNT($P$4:P53) -> 0.56 | R53: =(L53/$L$38)-1 -> 0.02357282 | S53: 10451.97 | T53: =(S53/S52)-1 -> 0.00095192218 | U53: =(S53/$S$3)-1 -> 0.21779794 | V53: =IF(G53>T53,"Yes","No") -> No | W53: =IF(V53="Yes",1,0) -> 0 | X53: =SUM($W$4:W53)/COUNT($W$4:W53) -> 0.54 | Z53: 1995.74 | AA53: =(Z53/Z52)-1 -> -0.027834067 | AB53: =(Z53/$Z$3)-1 -> 0.32794368
... A69: =A68+1 -> 67 | B69: =B68+7 -> 38205 | D69: 27961.47 | E69: =D69+Holdings_Old!$E$32 -> 27961.47 | F69: =E69-E68 -> -831.06 | G69: =(E69/E68)-1 -> -0.028863737 | H69: =E69-$D$3 -> 5105.62 | I69: =(E69/$D$3)-1 -> 0.22338351 | J69: =(E69/$E$38)-1 -> -0.087701353 | L69: 1063.97 | M69: =(L69/L68)-1 -> -0.034264604 | N69: =(L69/$L$3)-1 -> 0.14395536 | O69: =IF(G69>M69,"Yes","No") -> Yes | P69: =IF(O69="Yes",1,0) -> 1 | Q69: =SUM($P$4:P69)/COUNT($P$4:P69) -> 0.57575758 | R69: =(L69/$L$38)-1 -> -0.040154085 | S69: 9815.33 | T69: =(S69/S68)-1 -> -0.031991053 | U69: =(S69/$S$3)-1 -> 0.14362064 | V69: =IF(G69>T69,"Yes","No") -> Yes | W69: =IF(V69="Yes",1,0) -> 1 | X69: =SUM($W$4:W69)/COUNT($W$4:W69) -> 0.51515152 | Z69: 1776.89 | AA69: =(Z69/Z68)-1 -> -0.058531494 | AB69: =(Z69/$Z$3)-1 -> 0.18232327
A70: =A69+1 -> 68 | B70: =B69+7 -> 38212 | D70: 27243.27 | E70: =D70+SUM(Holdings_Old!$E$32:$E$33) -> 27243.27 | F70: =E70-E69 -> -718.2 | G70: =(E70/E69)-1 -> -0.025685345 | H70: =E70-$D$3 -> 4387.42 | I70: =(E70/$D$3)-1 -> 0.19196048 | J70: =(E70/$E$38)-1 -> -0.11113406 | L70: 1064.8 | M70: =(L70/L69)-1 -> 0.00078009718 | N70: =(L70/$L$3)-1 -> 0.14484776 | O70: =IF(G70>M70,"Yes","No") -> No | P70: =IF(O70="Yes",1,0) -> 0 | Q70: =SUM($P$4:P70)/COUNT($P$4:P70) -> 0.56716418 | R70: =(L70/$L$38)-1 -> -0.039405312 | S70: 9825.35 | T70: =(S70/S69)-1 -> 0.0010208521 | U70: =(S70/$S$3)-1 -> 0.14478811 | V70: =IF(G70>T70,"Yes","No") -> No | W70: =IF(V70="Yes",1,0) -> 0 | X70: =SUM($W$4:W70)/COUNT($W$4:W70) -> 0.50746269 | Z70: 1757.22 | AA70: =(Z70/Z69)-1 -> -0.011069903 | AB70: =(Z70/$Z$3)-1 -> 0.16923507
A71: =A70+1 -> 69 | B71: =B70+7 -> 38219 | D71: 28005.92 | E71: =D71+SUM(Holdings_Old!$E$32:$E$33) -> 28005.92 | F71: =E71-E70 -> 762.65 | G71: =(E71/E70)-1 -> 0.02799407 | H71: =E71-$D$3 -> 5150.07 | I71: =(E71/$D$3)-1 -> 0.22532831 | J71: =(E71/$E$38)-1 -> -0.086251084 | L71: 1098.35 | M71: =(L71/L70)-1 -> 0.031508264 | N71: =(L71/$L$3)-1 -> 0.18091992 | O71: =IF(G71>M71,"Yes","No") -> No | P71: =IF(O71="Yes",1,0) -> 0 | Q71: =SUM($P$4:P71)/COUNT($P$4:P71) -> 0.55882353 | R71: =(L71/$L$38)-1 -> -0.0091386403 | S71: 10110.14 | T71: =(S71/S70)-1 -> 0.028985227 | U71: =(S71/$S$3)-1 -> 0.17797005 | V71: =IF(G71>T71,"Yes","No") -> No | W71: =IF(V71="Yes",1,0) -> 0 | X71: =SUM($W$4:W71)/COUNT($W$4:W71) -> 0.5 | Z71: 1838.02 | AA71: =(Z71/Z70)-1 -> 0.045981721 | AB71: =(Z71/$Z$3)-1 -> 0.22299851
A72: =A71+1 -> 70 | B72: =B71+7 -> 38226 | D72: 28262.67 | E72: =D72+SUM(Holdings_Old!$E$32:$E$33) -> 28262.67 | F72: =E72-E71 -> 256.75 | G72: =(E72/E71)-1 -> 0.0091677045 | H72: =E72-$D$3 -> 5406.82 | I72: =(E72/$D$3)-1 -> 0.23656176 | J72: =(E72/$E$38)-1 -> -0.077874104 | L72: 1107.77 | M72: =(L72/L71)-1 -> 0.0085765011 | N72: =(L72/$L$3)-1 -> 0.19104808 | O72: =IF(G72>M72,"Yes","No") -> Yes | P72: =IF(O72="Yes",1,0) -> 1 | Q72: =SUM($P$4:P72)/COUNT($P$4:P72) -> 0.56521739 | R72: =(L72/$L$38)-1 -> -0.00064051674 | S72: 10195.01 | T72: =(S72/S71)-1 -> 0.0083945425 | U72: =(S72/$S$3)-1 -> 0.18785857 | V72: =IF(G72>T72,"Yes","No") -> Yes | W72: =IF(V72="Yes",1,0) -> 1 | X72: =SUM($W$4:W72)/COUNT($W$4:W72) -> 0.50724638 | Z72: 1862.09 | AA72: =(Z72/Z71)-1 -> 0.013095614 | AB72: =(Z72/$Z$3)-1 -> 0.23901443
A73: =A72+1 -> 71 | B73: =B72+7 -> 38233 | D73: 28172.82 | E73: =D73+SUM(Holdings_Old!$E$32:$E$33) -> 28172.82 | F73: =E73-E72 -> -89.85 | G73: =(E73/E72)-1 -> -0.0031791052 | H73: =E73-$D$3 -> 5316.97 | I73: =(E73/$D$3)-1 -> 0.2326306 | J73: =(E73/$E$38)-1 -> -0.080805639 | L73: 1113.63 | M73: =(L73/L72)-1 -> 0.0052899067 | N73: =(L73/$L$3)-1 -> 0.19734862 | O73: =IF(G73>M73,"Yes","No") -> No | P73: =IF(O73="Yes",1,0) -> 0 | Q73: =SUM($P$4:P73)/COUNT($P$4:P73) -> 0.55714286 | R73: =(L73/$L$38)-1 -> 0.0046460017 | S73: 10260.2 | T73: =(S73/S72)-1 -> 0.0063943047 | U73: =(S73/$S$3)-1 -> 0.1954541 | V73: =IF(G73>T73,"Yes","No") -> No | W73: =IF(V73="Yes",1,0) -> 0 | X73: =SUM($W$4:W73)/COUNT($W$4:W73) -> 0.5 | Z73: 1844.48 | AA73: =(Z73/Z72)-1 -> -0.0094571154 | AB73: =(Z73/$Z$3)-1 -> 0.22729692
A74: =A73+1 -> 72 | B74: =B73+7 -> 38240 | D74: 28365.95 | E74: =D74+SUM(Holdings_Old!$E$32:$E$33) -> 28365.95 | F74: =E74-E73 -> 193.13 | G74: =(E74/E73)-1 -> 0.0068551888 | H74: =E74-$D$3 -> 5510.1 | I74: =(E74/$D$3)-1 -> 0.24108051 | J74: =(E74/$E$38)-1 -> -0.074504388 | L74: 1123.92 | M74: =(L74/L73)-1 -> 0.0092400528 | N74: =(L74/$L$3)-1 -> 0.20841218 | O74: =IF(G74>M74,"Yes","No") -> No | P74: =IF(O74="Yes",1,0) -> 0 | Q74: =SUM($P$4:P74)/COUNT($P$4:P74) -> 0.54929577 | R74: =(L74/$L$38)-1 -> 0.013928984 | S74: 10313.07 | T74: =(S74/S73)-1 -> 0.005152921 | U74: =(S74/$S$3)-1 -> 0.20161418 | V74: =IF(G74>T74,"Yes","No") -> Yes | W74: =IF(V74="Yes",1,0) -> 1 | X74: =SUM($W$4:W74)/COUNT($W$4:W74) -> 0.50704225 | Z74: 1894.31 | AA74: =(Z74/Z73)-1 -> 0.027015744 | AB74: =(Z74/$Z$3)-1 -> 0.26045326
A75: =A74+1 -> 73 | B75: =B74+7 -> 38247 | D75: 28529.49 | E75: =D75+SUM(Holdings_Old!$E$32:$E$33) -> 28529.49 | F75: =E75-E74 -> 163.54 | G75: =(E75/E74)-1 -> 0.005765363 | H75: =E75-$D$3 -> 5673.64 | I75: =(E75/$D$3)-1 -> 0.24823579 | J75: =(E75/$E$38)-1 -> -0.06916857 | L75: 1128.55 | M75: =(L75/L74)-1 -> 0.0041195103 | N75: =(L75/$L$3)-1 -> 0.21339025 | O75: =IF(G75>M75,"Yes","No") -> Yes | P75: =IF(O75="Yes",1,0) -> 1 | Q75: =SUM($P$4:P75)/COUNT($P$4:P75) -> 0.55555556 | R75: =(L75/$L$38)-1 -> 0.018105875 | S75: 10284.46 | T75: =(S75/S74)-1 -> -0.0027741497 | U75: =(S75/$S$3)-1 -> 0.19828072 | V75: =IF(G75>T75,"Yes","No") -> Yes | W75: =IF(V75="Yes",1,0) -> 1 | X75: =SUM($W$4:W75)/COUNT($W$4:W75) -> 0.51388889 | Z75: 1910.09 | AA75: =(Z75/Z74)-1 -> 0.0083302099 | AB75: =(Z75/$Z$3)-1 -> 0.2709531
A76: =A75+1 -> 74 | B76: =B75+7 -> 38254 | D76: 27872.35 | E76: =D76+SUM(Holdings_Old!$E$32:$E$34) -> 27872.35 | F76: =E76-E75 -> -657.14 | G76: =(E76/E75)-1 -> -0.02303371 | H76: =E76-$D$3 -> 5016.5 | I76: =(E76/$D$3)-1 -> 0.21948429 | J76: =(E76/$E$38)-1 -> -0.090609071 | L76: 1110.11 | M76: =(L76/L75)-1 -> -0.016339551 | N76: =(L76/$L$3)-1 -> 0.19356399 | O76: =IF(G76>M76,"Yes","No") -> No | P76: =IF(O76="Yes",1,0) -> 0 | Q76: =SUM($P$4:P76)/COUNT($P$4:P76) -> 0.54794521 | R76: =(L76/$L$38)-1 -> 0.0014704821 | S76: 10047.24 | T76: =(S76/S75)-1 -> -0.023065868 | U76: =(S76/$S$3)-1 -> 0.17064134 | V76: =IF(G76>T76,"Yes","No") -> Yes | W76: =IF(V76="Yes",1,0) -> 1 | X76: =SUM($W$4:W76)/COUNT($W$4:W76) -> 0.52054795 | Z76: 1879.48 | AA76: =(Z76/Z75)-1 -> -0.016025423 | AB76: =(Z76/$Z$3)-1 -> 0.25058554
A77: =A76+1 -> 75 | B77: =B76+7 -> 38261 | D77: 28443.17 | E77: =D77+SUM(Holdings_Old!$E$32:$E$34) -> 28443.17 | F77: =E77-E76 -> 570.82 | G77: =(E77/E76)-1 -> 0.020479794 | H77: =E77-$D$3 -> 5587.32 | I77: =(E77/$D$3)-1 -> 0.24445908 | J77: =(E77/$E$38)-1 -> -0.071984932 | L77: 1131.5 | M77: =(L77/L76)-1 -> 0.019268361 | N77: =(L77/$L$3)-1 -> 0.21656202 | O77: =IF(G77>M77,"Yes","No") -> Yes | P77: =IF(O77="Yes",1,0) -> 1 | Q77: =SUM($P$4:P77)/COUNT($P$4:P77) -> 0.55405405 | R77: =(L77/$L$38)-1 -> 0.020767177 | S77: 10192.65 | T77: =(S77/S76)-1 -> 0.014472631 | U77: =(S77/$S$3)-1 -> 0.1875836 | V77: =IF(G77>T77,"Yes","No") -> Yes | W77: =IF(V77="Yes",1,0) -> 1 | X77: =SUM($W$4:W77)/COUNT($W$4:W77) -> 0.52702703 | Z77: 1942.2 | AA77: =(Z77/Z76)-1 -> 0.033370932 | AB77: =(Z77/$Z$3)-1 -> 0.29231875
A78: =A77+1 -> 76 | B78: =B77+7 -> 38268 | D78: 28277.12 | E78: =D78+SUM(Holdings_Old!$E$32:$E$34) -> 28277.12 | F78: =E78-E77 -> -166.05 | G78: =(E78/E77)-1 -> -0.0058379569 | H78: =E78-$D$3 -> 5421.27 | I78: =(E78/$D$3)-1 -> 0.23719398 | J78: =(E78/$E$38)-1 -> -0.077402644 | L78: 1122.14 | M78: =(L78/L77)-1 -> -0.008272205 | N78: =(L78/$L$3)-1 -> 0.20649837 | O78: =IF(G78>M78,"Yes","No") -> Yes | P78: =IF(O78="Yes",1,0) -> 1 | Q78: =SUM($P$4:P78)/COUNT($P$4:P78) -> 0.56 | R78: =(L78/$L$38)-1 -> 0.012323181 | S78: 10055.2 | T78: =(S78/S77)-1 -> -0.013485207 | U78: =(S78/$S$3)-1 -> 0.17156879 | V78: =IF(G78>T78,"Yes","No") -> Yes | W78: =IF(V78="Yes",1,0) -> 1 | X78: =SUM($W$4:W78)/COUNT($W$4:W78) -> 0.53333333 | Z78: 1919.97 | AA78: =(Z78/Z77)-1 -> -0.011445783 | AB78: =(Z78/$Z$3)-1 -> 0.27752715
A79: =A78+1 -> 77 | B79: =B78+7 -> 38275 | D79: 28337.96 | E79: =D79+SUM(Holdings_Old!$E$32:$E$34) -> 28337.96 | F79: =E79-E78 -> 60.84 | G79: =(E79/E78)-1 -> 0.0021515628 | H79: =E79-$D$3 -> 5482.11 | I79: =(E79/$D$3)-1 -> 0.23985588 | J79: =(E79/$E$38)-1 -> -0.075417617 | L79: 1108.2 | M79: =(L79/L78)-1 -> -0.012422692 | N79: =(L79/$L$3)-1 -> 0.19151041 | O79: =IF(G79>M79,"Yes","No") -> Yes | P79: =IF(O79="Yes",1,0) -> 1 | Q79: =SUM($P$4:P79)/COUNT($P$4:P79) -> 0.56578947 | R79: =(L79/$L$38)-1 -> -0.00025259815 | S79: 9933.38 | T79: =(S79/S78)-1 -> -0.012115125 | U79: =(S79/$S$3)-1 -> 0.15737509 | V79: =IF(G79>T79,"Yes","No") -> Yes | W79: =IF(V79="Yes",1,0) -> 1 | X79: =SUM($W$4:W79)/COUNT($W$4:W79) -> 0.53947368 | Z79: 1911.5 | AA79: =(Z79/Z78)-1 -> -0.0044115273 | AB79: =(Z79/$Z$3)-1 -> 0.2718913
A80: =A79+1 -> 78 | B80: =B79+7 -> 38282 | D80: 28127.87 | E80: =D80+SUM(Holdings_Old!$E$32:$E$34) -> 28127.87 | F80: =E80-E79 -> -210.09 | G80: =(E80/E79)-1 -> -0.0074137306 | H80: =E80-$D$3 -> 5272.02 | I80: =(E80/$D$3)-1 -> 0.23066392 | J80: =(E80/$E$38)-1 -> -0.082272222 | L80: 1095.74 | M80: =(L80/L79)-1 -> -0.011243458 | N80: =(L80/$L$3)-1 -> 0.17811371 | O80: =IF(G80>M80,"Yes","No") -> Yes | P80: =IF(O80="Yes",1,0) -> 1 | Q80: =SUM($P$4:P80)/COUNT($P$4:P80) -> 0.57142857 | R80: =(L80/$L$38)-1 -> -0.011493216 | S80: 9757.81 | T80: =(S80/S79)-1 -> -0.017674749 | U80: =(S80/$S$3)-1 -> 0.13691877 | V80: =IF(G80>T80,"Yes","No") -> Yes | W80: =IF(V80="Yes",1,0) -> 1 | X80: =SUM($W$4:W80)/COUNT($W$4:W80) -> 0.54545455 | Z80: 1915.14 | AA80: =(Z80/Z79)-1 -> 0.0019042637 | AB80: =(Z80/$Z$3)-1 -> 0.27431332
A81: =A80+1 -> 79 | B81: =B80+7 -> 38289 | D81: 28846.86 | E81: =D81+SUM(Holdings_Old!$E$32:$E$34) -> 28846.86 | F81: =E81-E80 -> 718.99 | G81: =(E81/E80)-1 -> 0.02556148 | H81: =E81-$D$3 -> 5991.01 | I81: =(E81/$D$3)-1 -> 0.26212151 | J81: =(E81/$E$38)-1 -> -0.058813741 | L81: 1130.2 | M81: =(L81/L80)-1 -> 0.031449066 | N81: =(L81/$L$3)-1 -> 0.21516429 | O81: =IF(G81>M81,"Yes","No") -> No | P81: =IF(O81="Yes",1,0) -> 0 | Q81: =SUM($P$4:P81)/COUNT($P$4:P81) -> 0.56410256 | R81: =(L81/$L$38)-1 -> 0.0195944 | S81: 10027.47 | T81: =(S81/S80)-1 -> 0.027635299 | U81: =(S81/$S$3)-1 -> 0.16833786 | V81: =IF(G81>T81,"Yes","No") -> No | W81: =IF(V81="Yes",1,0) -> 0 | X81: =SUM($W$4:W81)/COUNT($W$4:W81) -> 0.53846154 | Z81: 1974.99 | AA81: =(Z81/Z80)-1 -> 0.031250979 | AB81: =(Z81/$Z$3)-1 -> 0.31413686
A82: =A81+1 -> 80 | B82: =B81+7 -> 38296 | D82: 29611.48 | E82: =D82+SUM(Holdings_Old!$E$32:$E$34) -> 29611.48 | F82: =E82-E81 -> 764.62 | G82: =(E82/E81)-1 -> 0.026506178 | H82: =E82-$D$3 -> 6755.63 | I82: =(E82/$D$3)-1 -> 0.29557553 | J82: =(E82/$E$38)-1 -> -0.033866491 | L82: 1166.17 | M82: =(L82/L81)-1 -> 0.031826225 | N82: =(L82/$L$3)-1 -> 0.25383838 | O82: =IF(G82>M82,"Yes","No") -> No | P82: =IF(O82="Yes",1,0) -> 0 | Q82: =SUM($P$4:P82)/COUNT($P$4:P82) -> 0.55696203 | R82: =(L82/$L$38)-1 -> 0.052044241 | S82: 10387.54 | T82: =(S82/S81)-1 -> 0.03590836 | U82: =(S82/$S$3)-1 -> 0.21029096 | V82: =IF(G82>T82,"Yes","No") -> No | W82: =IF(V82="Yes",1,0) -> 0 | X82: =SUM($W$4:W82)/COUNT($W$4:W82) -> 0.53164557 | Z82: 2038.94 | AA82: =(Z82/Z81)-1 -> 0.032379911 | AB82: =(Z82/$Z$3)-1 -> 0.35668849
A83: =A82+1 -> 81 | B83: =B82+7 -> 38303 | D83: 29843.74 | E83: =D83+SUM(Holdings_Old!$E$32:$E$34) -> 29843.74 | F83: =E83-E82 -> 232.26 | G83: =(E83/E82)-1 -> 0.0078435796 | H83: =E83-$D$3 -> 6987.89 | I83: =(E83/$D$3)-1 -> 0.30573748 | J83: =(E83/$E$38)-1 -> -0.026288546 | L83: 1184.17 | M83: =(L83/L82)-1 -> 0.015435142 | N83: =(L83/$L$3)-1 -> 0.27319155 | O83: =IF(G83>M83,"Yes","No") -> No | P83: =IF(O83="Yes",1,0) -> 0 | Q83: =SUM($P$4:P83)/COUNT($P$4:P83) -> 0.55 | R83: =(L83/$L$38)-1 -> 0.068282693 | S83: 10539.01 | T83: =(S83/S82)-1 -> 0.014581893 | U83: =(S83/$S$3)-1 -> 0.22793929 | V83: =IF(G83>T83,"Yes","No") -> No | W83: =IF(V83="Yes",1,0) -> 0 | X83: =SUM($W$4:W83)/COUNT($W$4:W83) -> 0.525 | Z83: 2085.34 | AA83: =(Z83/Z82)-1 -> 0.022756923 | AB83: =(Z83/$Z$3)-1 -> 0.38756255
A84: =A83+1 -> 82 | B84: =B83+7 -> 38310 | D84: 28915.95 | E84: =D84+SUM(Holdings_Old!$E$32:$E$34) -> 28915.95 | F84: =E84-E83 -> -927.79 | G84: =(E84/E83)-1 -> -0.031088262 | H84: =E84-$D$3 -> 6060.1 | I84: =(E84/$D$3)-1 -> 0.26514437 | L84: 1170.34 | M84: =(L84/L83)-1 -> -0.011679066 | N84: =(L84/$L$3)-1 -> 0.25832186 | O84: =IF(G84>M84,"Yes","No") -> No | P84: =IF(O84="Yes",1,0) -> 0 | Q84: =SUM($P$4:P84)/COUNT($P$4:P84) -> 0.54320988 | R84: =(L84/$L$38)-1 -> 0.055806149 | S84: 10456.91 | T84: =(S84/S83)-1 -> -0.0077901055 | U84: =(S84/$S$3)-1 -> 0.21837352 | V84: =IF(G84>T84,"Yes","No") -> No | W84: =IF(V84="Yes",1,0) -> 0 | X84: =SUM($W$4:W84)/COUNT($W$4:W84) -> 0.51851852 | Z84: 2070.63 | AA84: =(Z84/Z83)-1 -> -0.0070540056 | AB84: =(Z84/$Z$3)-1 -> 0.37777467
A85: =A84+1 -> 83 | B85: =B84+7 -> 38317 | D85: 29040 | E85: =D85+SUM(Holdings_Old!$E$32:$E$34) -> 29040 | F85: =E85-E84 -> 124.05 | G85: =(E85/E84)-1 -> 0.0042900199 | H85: =E85-$D$3 -> 6184.15 | I85: =(E85/$D$3)-1 -> 0.27057187 | L85: 1182.65 | M85: =(L85/L84)-1 -> 0.010518311 | N85: =(L85/$L$3)-1 -> 0.27155729 | O85: =IF(G85>M85,"Yes","No") -> No | P85: =IF(O85="Yes",1,0) -> 0 | Q85: =SUM($P$4:P85)/COUNT($P$4:P85) -> 0.53658537 | R85: =(L85/$L$38)-1 -> 0.066911446 | S85: 10522.23 | T85: =(S85/S84)-1 -> 0.0062465872 | U85: =(S85/$S$3)-1 -> 0.22598419 | V85: =IF(G85>T85,"Yes","No") -> No | W85: =IF(V85="Yes",1,0) -> 0 | X85: =SUM($W$4:W85)/COUNT($W$4:W85) -> 0.51219512 | Z85: 2101.97 | AA85: =(Z85/Z84)-1 -> 0.01513549 | AB85: =(Z85/$Z$3)-1 -> 0.39862797
A86: =A85+1 -> 84 | B86: =B85+7 -> 38324 | D86: 29543.51 | E86: =D86+SUM(Holdings_Old!$E$32:$E$34) -> 29543.51 | F86: =E86-E85 -> 503.51 | G86: =(E86/E85)-1 -> 0.017338499 | H86: =E86-$D$3 -> 6687.66 | I86: =(E86/$D$3)-1 -> 0.29260168 | L86: 1191.17 | M86: =(L86/L85)-1 -> 0.0072041601 | N86: =(L86/$L$3)-1 -> 0.28071779 | O86: =IF(G86>M86,"Yes","No") -> Yes | P86: =IF(O86="Yes",1,0) -> 1 | Q86: =SUM($P$4:P86)/COUNT($P$4:P86) -> 0.54216867 | R86: =(L86/$L$38)-1 -> 0.074597647 | S86: 10592.21 | T86: =(S86/S85)-1 -> 0.0066506815 | U86: =(S86/$S$3)-1 -> 0.23413782 | V86: =IF(G86>T86,"Yes","No") -> Yes | W86: =IF(V86="Yes",1,0) -> 1 | X86: =SUM($W$4:W86)/COUNT($W$4:W86) -> 0.51807229 | Z86: 2147.96 | AA86: =(Z86/Z85)-1 -> 0.021879475 | AB86: =(Z86/$Z$3)-1 -> 0.42922921
A87: =A86+1 -> 85 | B87: =B86+7 -> 38331 | D87: 29497.24 | E87: =D87+SUM(Holdings_Old!$E$32:$E$34) -> 29497.24 | F87: =E87-E86 -> -46.27 | G87: =(E87/E86)-1 -> -0.0015661646 | H87: =E87-$D$3 -> 6641.39 | I87: =(E87/$D$3)-1 -> 0.29057725 | L87: 1188 | M87: =(L87/L86)-1 -> -0.002661249 | N87: =(L87/$L$3)-1 -> 0.27730948 | O87: =IF(G87>M87,"Yes","No") -> Yes | P87: =IF(O87="Yes",1,0) -> 1 | Q87: =SUM($P$4:P87)/COUNT($P$4:P87) -> 0.54761905 | S87: 10543.22 | T87: =(S87/S86)-1 -> -0.0046250971 | U87: =(S87/$S$3)-1 -> 0.22842981 | V87: =IF(G87>T87,"Yes","No") -> Yes | W87: =IF(V87="Yes",1,0) -> 1 | X87: =SUM($W$4:W87)/COUNT($W$4:W87) -> 0.52380952 | Z87: 2128.07 | AA87: =(Z87/Z86)-1 -> -0.009259949 | AB87: =(Z87/$Z$3)-1 -> 0.41599462
A88: =A87+1 -> 86 | B88: =B87+7 -> 38338 | D88: 29715.39 | E88: =D88+SUM(Holdings_Old!$E$32:$E$34) -> 29715.39 | F88: =E88-E87 -> 218.15 | G88: =(E88/E87)-1 -> 0.0073956072 | H88: =E88-$D$3 -> 6859.54 | I88: =(E88/$D$3)-1 -> 0.30012185 | L88: 1194.2 | M88: =(L88/L87)-1 -> 0.0052188552 | N88: =(L88/$L$3)-1 -> 0.28397557 | O88: =IF(G88>M88,"Yes","No") -> Yes | P88: =IF(O88="Yes",1,0) -> 1 | Q88: =SUM($P$4:P88)/COUNT($P$4:P88) -> 0.55294118 | S88: 10649.92 | T88: =(S88/S87)-1 -> 0.010120248 | U88: =(S88/$S$3)-1 -> 0.24086183 | V88: =IF(G88>T88,"Yes","No") -> No | W88: =IF(V88="Yes",1,0) -> 0 | X88: =SUM($W$4:W88)/COUNT($W$4:W88) -> 0.51764706 | Z88: 2135.2 | AA88: =(Z88/Z87)-1 -> 0.0033504537 | AB88: =(Z88/$Z$3)-1 -> 0.42073885
A89: =A88+1 -> 87 | B89: =B88+7 -> 38345 | D89: 30168.52 | E89: =D89+SUM(Holdings_Old!$E$32:$E$34) -> 30168.52 | F89: =E89-E88 -> 453.13 | G89: =(E89/E88)-1 -> 0.015249001 | H89: =E89-$D$3 -> 7312.67 | I89: =(E89/$D$3)-1 -> 0.31994741 | L89: 1210.13 | M89: =(L89/L88)-1 -> 0.013339474 | N89: =(L89/$L$3)-1 -> 0.30110313 | O89: =IF(G89>M89,"Yes","No") -> Yes | P89: =IF(O89="Yes",1,0) -> 1 | Q89: =SUM($P$4:P89)/COUNT($P$4:P89) -> 0.55813953 | S89: 10827.12 | T89: =(S89/S88)-1 -> 0.016638623 | U89: =(S89/$S$3)-1 -> 0.26150806 | V89: =IF(G89>T89,"Yes","No") -> No | W89: =IF(V89="Yes",1,0) -> 0 | X89: =SUM($W$4:W89)/COUNT($W$4:W89) -> 0.51162791 | Z89: 2160.62 | AA89: =(Z89/Z88)-1 -> 0.011905208 | AB89: =(Z89/$Z$3)-1 -> 0.43765304
A90: =A89+1 -> 88 | B90: =B89+7 -> 38352 | D90: 30139.25 | E90: =D90+SUM(Holdings_Old!$E$32:$E$34) -> 30139.25 | F90: =E90-E89 -> -29.27 | G90: =(E90/E89)-1 -> -0.00097021664 | H90: =E90-$D$3 -> 7283.4 | I90: =(E90/$D$3)-1 -> 0.31866677 | L90: 1211.92 | M90: =(L90/L89)-1 -> 0.0014791799 | N90: =(L90/$L$3)-1 -> 0.3030277 | O90: =IF(G90>M90,"Yes","No") -> No | P90: =IF(O90="Yes",1,0) -> 0 | Q90: =SUM($P$4:P90)/COUNT($P$4:P90) -> 0.55172414 | S90: 10783.01 | T90: =(S90/S89)-1 -> -0.0040740289 | U90: =(S90/$S$3)-1 -> 0.25636864 | V90: =IF(G90>T90,"Yes","No") -> Yes | W90: =IF(V90="Yes",1,0) -> 1 | X90: =SUM($W$4:W90)/COUNT($W$4:W90) -> 0.51724138 | Z90: 2175.44 | AA90: =(Z90/Z89)-1 -> 0.0068591423 | AB90: =(Z90/$Z$3)-1 -> 0.44751411
A91: =A90+1 -> 89 | B91: =B90+7 -> 38359 | D91: 29517.05 | E91: =D91+SUM(Holdings_Old!$E$32:$E$34) -> 29517.05 | F91: =E91-E90 -> -622.2 | G91: =(E91/E90)-1 -> -0.020644177 | H91: =E91-$D$3 -> 6661.2 | I91: =(E91/$D$3)-1 -> 0.29144398 | L91: 1186.19 | M91: =(L91/L90)-1 -> -0.021230774 | N91: =(L91/$L$3)-1 -> 0.27536341 | O91: =IF(G91>M91,"Yes","No") -> Yes | P91: =IF(O91="Yes",1,0) -> 1 | Q91: =SUM($P$4:P91)/COUNT($P$4:P91) -> 0.55681818 | S91: 10603.96 | T91: =(S91/S90)-1 -> -0.016604826 | U91: =(S91/$S$3)-1 -> 0.23550686 | V91: =IF(G91>T91,"Yes","No") -> No | W91: =IF(V91="Yes",1,0) -> 0 | X91: =SUM($W$4:W91)/COUNT($W$4:W91) -> 0.51136364 | Z91: 2088.61 | AA91: =(Z91/Z90)-1 -> -0.039913765 | AB91: =(Z91/$Z$3)-1 -> 0.38973837
A92: =A91+1 -> 90 | B92: =B91+7 -> 38366 | D92: 29620.68 | E92: =D92+SUM(Holdings_Old!$E$32:$E$34) -> 29620.68 | F92: =E92-E91 -> 103.63 | G92: =(E92/E91)-1 -> 0.0035108522 | H92: =E92-$D$3 -> 6764.83 | I92: =(E92/$D$3)-1 -> 0.29597805 | L92: 1184.52 | M92: =(L92/L91)-1 -> -0.0014078689 | N92: =(L92/$L$3)-1 -> 0.27356787 | O92: =IF(G92>M92,"Yes","No") -> Yes | P92: =IF(O92="Yes",1,0) -> 1 | Q92: =SUM($P$4:P92)/COUNT($P$4:P92) -> 0.56179775 | S92: 10558 | T92: =(S92/S91)-1 -> -0.0043342299 | U92: =(S92/$S$3)-1 -> 0.23015189 | V92: =IF(G92>T92,"Yes","No") -> Yes | W92: =IF(V92="Yes",1,0) -> 1 | X92: =SUM($W$4:W92)/COUNT($W$4:W92) -> 0.51685393 | Z92: 2087.91 | AA92: =(Z92/Z91)-1 -> -0.00033515113 | AB92: =(Z92/$Z$3)-1 -> 0.3892726
A93: =A92+1 -> 91 | B93: =B92+7 -> 38373 | D93: 29153.36 | E93: =D93+SUM(Holdings_Old!$E$32:$E$34) -> 29153.36 | F93: =E93-E92 -> -467.32 | G93: =(E93/E92)-1 -> -0.015776815 | H93: =E93-$D$3 -> 6297.51 | I93: =(E93/$D$3)-1 -> 0.27553165 | L93: 1167.87 | M93: =(L93/L92)-1 -> -0.014056327 | N93: =(L93/$L$3)-1 -> 0.25566618 | O93: =IF(G93>M93,"Yes","No") -> No | P93: =IF(O93="Yes",1,0) -> 0 | Q93: =SUM($P$4:P93)/COUNT($P$4:P93) -> 0.55555556 | S93: 10392.99 | T93: =(S93/S92)-1 -> -0.015628907 | U93: =(S93/$S$3)-1 -> 0.21092596 | V93: =IF(G93>T93,"Yes","No") -> No | W93: =IF(V93="Yes",1,0) -> 0 | X93: =SUM($W$4:W93)/COUNT($W$4:W93) -> 0.51111111 | Z93: 2034.27 | AA93: =(Z93/Z92)-1 -> -0.025690763 | AB93: =(Z93/$Z$3)-1 -> 0.35358112
A94: =A93+1 -> 92 | B94: =B93+7 -> 38380 | D94: 29468 | E94: =D94+SUM(Holdings_Old!$E$32:$E$34) -> 29468 | F94: =E94-E93 -> 314.64 | G94: =(E94/E93)-1 -> 0.010792581 | H94: =E94-$D$3 -> 6612.15 | I94: =(E94/$D$3)-1 -> 0.28929793 | L94: 1171.36 | M94: =(L94/L93)-1 -> 0.0029883463 | N94: =(L94/$L$3)-1 -> 0.25941854 | O94: =IF(G94>M94,"Yes","No") -> Yes | P94: =IF(O94="Yes",1,0) -> 1 | Q94: =SUM($P$4:P94)/COUNT($P$4:P94) -> 0.56043956 | S94: 10427.2 | T94: =(S94/S93)-1 -> 0.0032916418 | U94: =(S94/$S$3)-1 -> 0.21491189 | V94: =IF(G94>T94,"Yes","No") -> Yes | W94: =IF(V94="Yes",1,0) -> 1 | X94: =SUM($W$4:W94)/COUNT($W$4:W94) -> 0.51648352 | Z94: 2035.83 | AA94: =(Z94/Z93)-1 -> 0.00076685986 | AB94: =(Z94/$Z$3)-1 -> 0.35461913
A95: =A94+1 -> 93 | B95: =B94+7 -> 38387 | D95: 30195.15 | E95: =D95+SUM(Holdings_Old!$E$32:$E$34) -> 30195.15 | F95: =E95-E94 -> 727.15 | G95: =(E95/E94)-1 -> 0.02467592 | H95: =E95-$D$3 -> 7339.3 | I95: =(E95/$D$3)-1 -> 0.32111254 | L95: 1203.03 | M95: =(L95/L94)-1 -> 0.027036949 | N95: =(L95/$L$3)-1 -> 0.29346938 | O95: =IF(G95>M95,"Yes","No") -> No | P95: =IF(O95="Yes",1,0) -> 0 | Q95: =SUM($P$4:P95)/COUNT($P$4:P95) -> 0.55434783 | S95: 10716.13 | T95: =(S95/S94)-1 -> 0.02770926 | U95: =(S95/$S$3)-1 -> 0.2485762 | V95: =IF(G95>T95,"Yes","No") -> No | W95: =IF(V95="Yes",1,0) -> 0 | X95: =SUM($W$4:W95)/COUNT($W$4:W95) -> 0.51086957 | Z95: 2086.66 | AA95: =(Z95/Z94)-1 -> 0.024967704 | AB95: =(Z95/$Z$3)-1 -> 0.38844086
A96: =A95+1 -> 94 | B96: =B95+7 -> 38394 | D96: 30017.11 | E96: =D96+SUM(Holdings_Old!$E$32:$E$34) -> 30017.11 | F96: =E96-E95 -> -178.04 | G96: =(E96/E95)-1 -> -0.0058963112 | H96: =E96-$D$3 -> 7161.26 | I96: =(E96/$D$3)-1 -> 0.31332285 | L96: 1205.3 | M96: =(L96/L95)-1 -> 0.0018869022 | N96: =(L96/$L$3)-1 -> 0.29591003 | O96: =IF(G96>M96,"Yes","No") -> No | P96: =IF(O96="Yes",1,0) -> 0 | Q96: =SUM($P$4:P96)/COUNT($P$4:P96) -> 0.5483871 | S96: 10796.01 | T96: =(S96/S95)-1 -> 0.0074541836 | U96: =(S96/$S$3)-1 -> 0.25788332 | V96: =IF(G96>T96,"Yes","No") -> No | W96: =IF(V96="Yes",1,0) -> 0 | X96: =SUM($W$4:W96)/COUNT($W$4:W96) -> 0.50537634 | Z96: 2076.66 | AA96: =(Z96/Z95)-1 -> -0.0047923476 | AB96: =(Z96/$Z$3)-1 -> 0.38178697
A97: =A96+1 -> 95 | B97: =B96+7 -> 38401 | D97: 30045.41 | E97: =D97+SUM(Holdings_Old!$E$32:$E$34) -> 30045.41 | F97: =E97-E96 -> 28.3 | G97: =(E97/E96)-1 -> 0.00094279563 | H97: =E97-$D$3 -> 7189.56 | I97: =(E97/$D$3)-1 -> 0.31456104 | L97: 1201.59 | M97: =(L97/L96)-1 -> -0.0030780718 | N97: =(L97/$L$3)-1 -> 0.29192113 | O97: =IF(G97>M97,"Yes","No") -> Yes | P97: =IF(O97="Yes",1,0) -> 1 | Q97: =SUM($P$4:P97)/COUNT($P$4:P97) -> 0.55319149 | S97: 10785.22 | T97: =(S97/S96)-1 -> -0.00099944331 | U97: =(S97/$S$3)-1 -> 0.25662614 | V97: =IF(G97>T97,"Yes","No") -> Yes | W97: =IF(V97="Yes",1,0) -> 1 | X97: =SUM($W$4:W97)/COUNT($W$4:W97) -> 0.5106383 | Z97: 2058.62 | AA97: =(Z97/Z96)-1 -> -0.0086870263 | AB97: =(Z97/$Z$3)-1 -> 0.36978335
A98: =A97+1 -> 96 | B98: =B97+7 -> 38408 | D98: 30331.03 | E98: =D98+SUM(Holdings_Old!$E$32:$E$34) -> 30331.03 | F98: =E98-E97 -> 285.62 | G98: =(E98/E97)-1 -> 0.0095062773 | H98: =E98-$D$3 -> 7475.18 | I98: =(E98/$D$3)-1 -> 0.32705762 | L98: 1211.37 | M98: =(L98/L97)-1 -> 0.0081392155 | N98: =(L98/$L$3)-1 -> 0.30243635 | O98: =IF(G98>M98,"Yes","No") -> Yes | P98: =IF(O98="Yes",1,0) -> 1 | Q98: =SUM($P$4:P98)/COUNT($P$4:P98) -> 0.55789474 | S98: 10841.6 | T98: =(S98/S97)-1 -> 0.0052275243 | U98: =(S98/$S$3)-1 -> 0.26319518 | V98: =IF(G98>T98,"Yes","No") -> Yes | W98: =IF(V98="Yes",1,0) -> 1 | X98: =SUM($W$4:W98)/COUNT($W$4:W98) -> 0.51578947 | Z98: 2065.4 | AA98: =(Z98/Z97)-1 -> 0.0032934684 | AB98: =(Z98/$Z$3)-1 -> 0.37429469
... A109: =A108+1 -> 107 | B109: =B108+7 -> 38485 | D109: 29673.86 | E109: =D109+SUM(Holdings_Old!$E$32:$E$34) -> 29673.86 | F109: =E109-E108 -> -159.64 | G109: =(E109/E108)-1 -> -0.0053510316 | H109: =E109-$D$3 -> 6818.01 | I109: =(E109/$D$3)-1 -> 0.29830481 | L109: 1154.05 | M109: =(L109/L108)-1 -> -0.014769283 | N109: =(L109/$L$3)-1 -> 0.24080724 | O109: =IF(G109>M109,"Yes","No") -> Yes | P109: =IF(O109="Yes",1,0) -> 1 | Q109: =SUM($P$4:P109)/COUNT($P$4:P109) -> 0.55660377 | S109: 10140.12 | T109: =(S109/S108)-1 -> -0.019842635 | U109: =(S109/$S$3)-1 -> 0.18146313 | V109: =IF(G109>T109,"Yes","No") -> Yes | W109: =IF(V109="Yes",1,0) -> 1 | X109: =SUM($W$4:W109)/COUNT($W$4:W109) -> 0.52830189 | Z109: 1976.78 | AA109: =(Z109/Z108)-1 -> 0.0047932498 | AB109: =(Z109/$Z$3)-1 -> 0.3153279
A110: =A109+1 -> 108 | B110: =B109+7 -> 38492 | D110: 30096.27 | E110: =D110+SUM(Holdings_Old!$E$32:$E$35) -> 30096.27 | F110: =E110-E109 -> 422.41 | G110: =(E110/E109)-1 -> 0.014235088 | H110: =E110-$D$3 -> 7240.42 | I110: =(E110/$D$3)-1 -> 0.31678629 | L110: 1189.28 | M110: =(L110/L109)-1 -> 0.030527274 | N110: =(L110/$L$3)-1 -> 0.2786857 | O110: =IF(G110>M110,"Yes","No") -> No | P110: =IF(O110="Yes",1,0) -> 0 | Q110: =SUM($P$4:P110)/COUNT($P$4:P110) -> 0.55140187 | S110: 10471.91 | T110: =(S110/S109)-1 -> 0.03272052 | U110: =(S110/$S$3)-1 -> 0.22012122 | V110: =IF(G110>T110,"Yes","No") -> No | W110: =IF(V110="Yes",1,0) -> 0 | X110: =SUM($W$4:W110)/COUNT($W$4:W110) -> 0.52336449 | Z110: 2046.42 | AA110: =(Z110/Z109)-1 -> 0.035229009 | AB110: =(Z110/$Z$3)-1 -> 0.3616656
A111: =A110+1 -> 109 | B111: =B110+7 -> 38499 | D111: 29882.27 | E111: =D111+SUM(Holdings_Old!$E$32:$E$35) -> 29882.27 | F111: =E111-E110 -> -214 | G111: =(E111/E110)-1 -> -0.0071105157 | H111: =E111-$D$3 -> 7026.42 | I111: =(E111/$D$3)-1 -> 0.30742326 | L111: 1198.78 | M111: =(L111/L110)-1 -> 0.0079880264 | N111: =(L111/$L$3)-1 -> 0.28889988 | O111: =IF(G111>M111,"Yes","No") -> No | P111: =IF(O111="Yes",1,0) -> 0 | Q111: =SUM($P$4:P111)/COUNT($P$4:P111) -> 0.5462963 | S111: 10542.55 | T111: =(S111/S110)-1 -> 0.0067456653 | U111: =(S111/$S$3)-1 -> 0.22835175 | V111: =IF(G111>T111,"Yes","No") -> No | W111: =IF(V111="Yes",1,0) -> 0 | X111: =SUM($W$4:W111)/COUNT($W$4:W111) -> 0.51851852 | Z111: 2075.73 | AA111: =(Z111/Z110)-1 -> 0.014322573 | AB111: =(Z111/$Z$3)-1 -> 0.38116816
A112: =A111+1 -> 110 | B112: =B111+7 -> 38506 | D112: 29745.97 | E112: =D112+SUM(Holdings_Old!$E$32:$E$35) -> 29745.97 | F112: =E112-E111 -> -136.3 | G112: =(E112/E111)-1 -> -0.0045612331 | H112: =E112-$D$3 -> 6890.12 | I112: =(E112/$D$3)-1 -> 0.3014598 | L112: 1196.02 | M112: =(L112/L111)-1 -> -0.0023023407 | N112: =(L112/$L$3)-1 -> 0.28593239 | O112: =IF(G112>M112,"Yes","No") -> No | P112: =IF(O112="Yes",1,0) -> 0 | Q112: =SUM($P$4:P112)/COUNT($P$4:P112) -> 0.5412844 | S112: 10460.97 | T112: =(S112/S111)-1 -> -0.0077381658 | U112: =(S112/$S$3)-1 -> 0.21884656 | V112: =IF(G112>T112,"Yes","No") -> Yes | W112: =IF(V112="Yes",1,0) -> 1 | X112: =SUM($W$4:W112)/COUNT($W$4:W112) -> 0.52293578 | Z112: 2071.77 | AA112: =(Z112/Z111)-1 -> -0.0019077626 | AB112: =(Z112/$Z$3)-1 -> 0.37853322
A113: =A112+1 -> 111 | B113: =B112+7 -> 38513 | D113: 30041.64 | E113: =D113+SUM(Holdings_Old!$E$32:$E$35) -> 30041.64 | F113: =E113-E112 -> 295.67 | G113: =(E113/E112)-1 -> 0.0099398339 | H113: =E113-$D$3 -> 7185.79 | I113: =(E113/$D$3)-1 -> 0.3143961 | L113: 1198.11 | M113: =(L113/L112)-1 -> 0.0017474624 | N113: =(L113/$L$3)-1 -> 0.28817951 | O113: =IF(G113>M113,"Yes","No") -> Yes | P113: =IF(O113="Yes",1,0) -> 1 | Q113: =SUM($P$4:P113)/COUNT($P$4:P113) -> 0.54545455 | S113: 10512.63 | T113: =(S113/S112)-1 -> 0.0049383566 | U113: =(S113/$S$3)-1 -> 0.22486566 | V113: =IF(G113>T113,"Yes","No") -> Yes | W113: =IF(V113="Yes",1,0) -> 1 | X113: =SUM($W$4:W113)/COUNT($W$4:W113) -> 0.52727273 | Z113: 2063 | AA113: =(Z113/Z112)-1 -> -0.0042330954 | AB113: =(Z113/$Z$3)-1 -> 0.37269775
A114: =A113+1 -> 112 | B114: =B113+7 -> 38520 | D114: 30265.92 | E114: =D114+SUM(Holdings_Old!$E$32:$E$35) -> 30265.92 | F114: =E114-E113 -> 224.28 | G114: =(E114/E113)-1 -> 0.0074656377 | H114: =E114-$D$3 -> 7410.07 | I114: =(E114/$D$3)-1 -> 0.3242089 | L114: 1216.96 | M114: =(L114/L113)-1 -> 0.015733113 | N114: =(L114/$L$3)-1 -> 0.30844659 | O114: =IF(G114>M114,"Yes","No") -> No | P114: =IF(O114="Yes",1,0) -> 0 | Q114: =SUM($P$4:P114)/COUNT($P$4:P114) -> 0.54054054 | S114: 10623.07 | T114: =(S114/S113)-1 -> 0.010505459 | U114: =(S114/$S$3)-1 -> 0.23773344 | V114: =IF(G114>T114,"Yes","No") -> No | W114: =IF(V114="Yes",1,0) -> 0 | X114: =SUM($W$4:W114)/COUNT($W$4:W114) -> 0.52252252 | Z114: 2090.11 | AA114: =(Z114/Z113)-1 -> 0.013141057 | AB114: =(Z114/$Z$3)-1 -> 0.39073645
A115: =A114+1 -> 113 | B115: =B114+7 -> 38527 | D115: 29958.18 | E115: =D115+SUM(Holdings_Old!$E$32:$E$35) -> 29958.18 | F115: =E115-E114 -> -307.74 | G115: =(E115/E114)-1 -> -0.010167872 | H115: =E115-$D$3 -> 7102.33 | I115: =(E115/$D$3)-1 -> 0.31074451 | L115: 1191.57 | M115: =(L115/L114)-1 -> -0.020863463 | N115: =(L115/$L$3)-1 -> 0.28114786 | O115: =IF(G115>M115,"Yes","No") -> Yes | P115: =IF(O115="Yes",1,0) -> 1 | Q115: =SUM($P$4:P115)/COUNT($P$4:P115) -> 0.54464286 | S115: 10297.84 | T115: =(S115/S114)-1 -> -0.030615444 | U115: =(S115/$S$3)-1 -> 0.19983968 | V115: =IF(G115>T115,"Yes","No") -> Yes | W115: =IF(V115="Yes",1,0) -> 1 | X115: =SUM($W$4:W115)/COUNT($W$4:W115) -> 0.52678571 | Z115: 2053.27 | AA115: =(Z115/Z114)-1 -> -0.017625867 | AB115: =(Z115/$Z$3)-1 -> 0.36622352
A116: =A115+1 -> 114 | B116: =B115+7 -> 38534 | D116: 30063.44 | E116: =D116+SUM(Holdings_Old!$E$32:$E$35) -> 30063.44 | F116: =E116-E115 -> 105.26 | G116: =(E116/E115)-1 -> 0.0035135646 | H116: =E116-$D$3 -> 7207.59 | I116: =(E116/$D$3)-1 -> 0.3153499 | L116: 1194.44 | M116: =(L116/L115)-1 -> 0.002408587 | N116: =(L116/$L$3)-1 -> 0.28423361 | O116: =IF(G116>M116,"Yes","No") -> Yes | P116: =IF(O116="Yes",1,0) -> 1 | Q116: =SUM($P$4:P116)/COUNT($P$4:P116) -> 0.54867257 | S116: 10303.44 | T116: =(S116/S115)-1 -> 0.00054380336 | U116: =(S116/$S$3)-1 -> 0.20049215 | V116: =IF(G116>T116,"Yes","No") -> Yes | W116: =IF(V116="Yes",1,0) -> 1 | X116: =SUM($W$4:W116)/COUNT($W$4:W116) -> 0.53097345 | Z116: 2057.37 | AA116: =(Z116/Z115)-1 -> 0.0019968148 | AB116: =(Z116/$Z$3)-1 -> 0.36895161
A117: =A116+1 -> 115 | B117: =B116+7 -> 38541 | D117: 30744.09 | E117: =D117+SUM(Holdings_Old!$E$32:$E$35) -> 30744.09 | F117: =E117-E116 -> 680.65 | G117: =(E117/E116)-1 -> 0.022640456 | H117: =E117-$D$3 -> 7888.24 | I117: =(E117/$D$3)-1 -> 0.34513002 | L117: 1211.86 | M117: =(L117/L116)-1 -> 0.01458424 | N117: =(L117/$L$3)-1 -> 0.30296319 | O117: =IF(G117>M117,"Yes","No") -> Yes | P117: =IF(O117="Yes",1,0) -> 1 | Q117: =SUM($P$4:P117)/COUNT($P$4:P117) -> 0.55263158 | S117: 10449.14 | T117: =(S117/S116)-1 -> 0.014140908 | U117: =(S117/$S$3)-1 -> 0.2174682 | V117: =IF(G117>T117,"Yes","No") -> Yes | W117: =IF(V117="Yes",1,0) -> 1 | X117: =SUM($W$4:W117)/COUNT($W$4:W117) -> 0.53508772 | Z117: 2112.88 | AA117: =(Z117/Z116)-1 -> 0.026981049 | AB117: =(Z117/$Z$3)-1 -> 0.40588736
A118: =A117+1 -> 116 | B118: =B117+7 -> 38548 | D118: 31087.04 | E118: =D118+SUM(Holdings_Old!$E$32:$E$35) -> 31087.04 | F118: =E118-E117 -> 342.95 | G118: =(E118/E117)-1 -> 0.011154989 | H118: =E118-$D$3 -> 8231.19 | I118: =(E118/$D$3)-1 -> 0.36013493 | L118: 1227.92 | M118: =(L118/L117)-1 -> 0.013252356 | N118: =(L118/$L$3)-1 -> 0.32023052 | O118: =IF(G118>M118,"Yes","No") -> No | P118: =IF(O118="Yes",1,0) -> 0 | Q118: =SUM($P$4:P118)/COUNT($P$4:P118) -> 0.54782609 | S118: 10640.83 | T118: =(S118/S117)-1 -> 0.01834505 | U118: =(S118/$S$3)-1 -> 0.23980272 | V118: =IF(G118>T118,"Yes","No") -> No | W118: =IF(V118="Yes",1,0) -> 0 | X118: =SUM($W$4:W118)/COUNT($W$4:W118) -> 0.53043478 | Z118: 2156.78 | AA118: =(Z118/Z117)-1 -> 0.020777328 | AB118: =(Z118/$Z$3)-1 -> 0.43509795
A119: =A118+1 -> 117 | B119: =B118+7 -> 38555 | D119: 31199.9 | E119: =D119+SUM(Holdings_Old!$E$32:$E$35) -> 31199.9 | F119: =E119-E118 -> 112.86 | G119: =(E119/E118)-1 -> 0.0036304518 | H119: =E119-$D$3 -> 8344.05 | I119: =(E119/$D$3)-1 -> 0.36507284 | L119: 1233.68 | M119: =(L119/L118)-1 -> 0.0046908593 | N119: =(L119/$L$3)-1 -> 0.32642353 | O119: =IF(G119>M119,"Yes","No") -> No | P119: =IF(O119="Yes",1,0) -> 0 | Q119: =SUM($P$4:P119)/COUNT($P$4:P119) -> 0.54310345 | S119: 10651.18 | T119: =(S119/S118)-1 -> 0.00097266849 | U119: =(S119/$S$3)-1 -> 0.24100864 | V119: =IF(G119>T119,"Yes","No") -> Yes | W119: =IF(V119="Yes",1,0) -> 1 | X119: =SUM($W$4:W119)/COUNT($W$4:W119) -> 0.53448276 | Z119: 2179.74 | AA119: =(Z119/Z118)-1 -> 0.010645499 | AB119: =(Z119/$Z$3)-1 -> 0.45037528
A120: =A119+1 -> 118 | B120: =B119+7 -> 38562 | D120: 31264.81 | E120: =D120+SUM(Holdings_Old!$E$32:$E$35) -> 31264.81 | F120: =E120-E119 -> 64.91 | G120: =(E120/E119)-1 -> 0.0020804554 | H120: =E120-$D$3 -> 8408.96 | I120: =(E120/$D$3)-1 -> 0.36791281 | L120: 1234.18 | M120: =(L120/L119)-1 -> 0.00040529149 | N120: =(L120/$L$3)-1 -> 0.32696112 | O120: =IF(G120>M120,"Yes","No") -> Yes | P120: =IF(O120="Yes",1,0) -> 1 | Q120: =SUM($P$4:P120)/COUNT($P$4:P120) -> 0.54700855 | S120: 10640.91 | T120: =(S120/S119)-1 -> -0.00096421242 | U120: =(S120/$S$3)-1 -> 0.23981204 | V120: =IF(G120>T120,"Yes","No") -> Yes | W120: =IF(V120="Yes",1,0) -> 1 | X120: =SUM($W$4:W120)/COUNT($W$4:W120) -> 0.53846154 | Z120: 2184.83 | AA120: =(Z120/Z119)-1 -> 0.0023351409 | AB120: =(Z120/$Z$3)-1 -> 0.45376211
A121: =A120+1 -> 119 | B121: =B120+7 -> 38569 | D121: 31130 | E121: =D121+SUM(Holdings_Old!$E$32:$E$35) -> 31130 | F121: =E121-E120 -> -134.81 | G121: =(E121/E120)-1 -> -0.0043118765 | H121: =E121-$D$3 -> 8274.15 | I121: =(E121/$D$3)-1 -> 0.36201454 | L121: 1226.42 | M121: =(L121/L120)-1 -> -0.0062875756 | N121: =(L121/$L$3)-1 -> 0.31861775 | O121: =IF(G121>M121,"Yes","No") -> Yes | P121: =IF(O121="Yes",1,0) -> 1 | Q121: =SUM($P$4:P121)/COUNT($P$4:P121) -> 0.55084746 | S121: 10558.03 | T121: =(S121/S120)-1 -> -0.0077888075 | U121: =(S121/$S$3)-1 -> 0.23015538 | V121: =IF(G121>T121,"Yes","No") -> Yes | W121: =IF(V121="Yes",1,0) -> 1 | X121: =SUM($W$4:W121)/COUNT($W$4:W121) -> 0.54237288 | Z121: 2177.91 | AA121: =(Z121/Z120)-1 -> -0.0031672945 | AB121: =(Z121/$Z$3)-1 -> 0.44915762
... A178: =A177+1 -> 176 | B178: =B177+7 -> 38968 | D178: 31337.681 | E178: =D178+SUM(Holdings_Old!$E$32:$E$35) -> 31337.681 | F178: =E178-E177 -> -124.19854 | G178: =(E178/E177)-1 -> -0.003947588 | H178: =E178-$D$3 -> 8481.8312 | I178: =(E178/$D$3)-1 -> 0.3711011 | L178: 1298.86 | M178: =(L178/L177)-1 -> -0.0092147619 | N178: =(L178/$L$3)-1 -> 0.39650353 | O178: =IF(G178>M178,"Yes","No") -> Yes | P178: =IF(O178="Yes",1,0) -> 1 | Q178: =SUM($P$4:P178)/COUNT($P$4:P178) -> 0.52571429 | S178: 11392.11 | T178: =(S178/S177)-1 -> -0.0062839373 | U178: =(S178/$S$3)-1 -> 0.32733715 | V178: =IF(G178>T178,"Yes","No") -> Yes | W178: =IF(V178="Yes",1,0) -> 1 | X178: =SUM($W$4:W178)/COUNT($W$4:W178) -> 0.52 | Z178: 2165.79 | AA178: =(Z178/Z177)-1 -> -0.01247971 | AB178: =(Z178/$Z$3)-1 -> 0.4410931
A179: =A178+1 -> 177 | B179: =B178+7 -> 38975 | D179: =31836.62388+3.49+9.2+3.42 -> 31852.734 | E179: =D179+SUM(Holdings_Old!$E$32:$E$35) -> 31852.734 | F179: =E179-E178 -> 515.05272 | G179: =(E179/E178)-1 -> 0.016435572 | H179: =E179-$D$3 -> 8996.8839 | I179: =(E179/$D$3)-1 -> 0.39363593 | L179: 1319.85 | M179: =(L179/L178)-1 -> 0.016160325 | N179: =(L179/$L$3)-1 -> 0.41907148 | O179: =IF(G179>M179,"Yes","No") -> Yes | P179: =IF(O179="Yes",1,0) -> 1 | Q179: =SUM($P$4:P179)/COUNT($P$4:P179) -> 0.52840909 | S179: 11560.77 | T179: =(S179/S178)-1 -> 0.014804983 | U179: =(S179/$S$3)-1 -> 0.34698835 | V179: =IF(G179>T179,"Yes","No") -> Yes | W179: =IF(V179="Yes",1,0) -> 1 | X179: =SUM($W$4:W179)/COUNT($W$4:W179) -> 0.52272727 | Z179: 2235.59 | AA179: =(Z179/Z178)-1 -> 0.032228425 | AB179: =(Z179/$Z$3)-1 -> 0.48753726
A180: =A179+1 -> 178 | B180: =B179+7 -> 38982 | D180: 31597.783 | E180: =D180+SUM(Holdings_Old!$E$32:$E$35) -> 31597.783 | F180: =E180-E179 -> -254.95126 | G180: =(E180/E179)-1 -> -0.0080040621 | H180: =E180-$D$3 -> 8741.9326 | I180: =(E180/$D$3)-1 -> 0.38248119 | L180: 1314.78 | M180: =(L180/L179)-1 -> -0.0038413456 | N180: =(L180/$L$3)-1 -> 0.41362033 | O180: =IF(G180>M180,"Yes","No") -> No | P180: =IF(O180="Yes",1,0) -> 0 | Q180: =SUM($P$4:P180)/COUNT($P$4:P180) -> 0.52542373 | S180: 11508.1 | T180: =(S180/S179)-1 -> -0.0045559249 | U180: =(S180/$S$3)-1 -> 0.34085158 | V180: =IF(G180>T180,"Yes","No") -> No | W180: =IF(V180="Yes",1,0) -> 0 | X180: =SUM($W$4:W180)/COUNT($W$4:W180) -> 0.51977401 | Z180: 2218.93 | AA180: =(Z180/Z179)-1 -> -0.0074521715 | AB180: =(Z180/$Z$3)-1 -> 0.47645188
A181: =A180+1 -> 179 | B181: =B180+7 -> 38989 | D181: 31628.077 | E181: =D181+SUM(Holdings_Old!$E$32:$E$35) -> 31628.077 | F181: =E181-E180 -> 30.29398 | G181: =(E181/E180)-1 -> 0.00095873753 | H181: =E181-$D$3 -> 8772.2266 | I181: =(E181/$D$3)-1 -> 0.38380662 | L181: 1335.82 | M181: =(L181/L180)-1 -> 0.016002677 | N181: =(L181/$L$3)-1 -> 0.43624204 | O181: =IF(G181>M181,"Yes","No") -> No | P181: =IF(O181="Yes",1,0) -> 0 | Q181: =SUM($P$4:P181)/COUNT($P$4:P181) -> 0.52247191 | S181: 11679.07 | T181: =(S181/S180)-1 -> 0.014856492 | U181: =(S181/$S$3)-1 -> 0.36077193 | V181: =IF(G181>T181,"Yes","No") -> No | W181: =IF(V181="Yes",1,0) -> 0 | X181: =SUM($W$4:W181)/COUNT($W$4:W181) -> 0.51685393 | Z181: 2258.43 | AA181: =(Z181/Z180)-1 -> 0.017801373 | AB181: =(Z181/$Z$3)-1 -> 0.50273475
A182: =A181+1 -> 180 | B182: =B181+7 -> 38996 | D182: 32045.752 | E182: =D182+SUM(Holdings_Old!$E$32:$E$35) -> 32045.752 | F182: =E182-E181 -> 417.67584 | G182: =(E182/E181)-1 -> 0.013205856 | H182: =E182-$D$3 -> 9189.9024 | I182: =(E182/$D$3)-1 -> 0.40208097 | L182: 1349.58 | M182: =(L182/L181)-1 -> 0.010300789 | N182: =(L182/$L$3)-1 -> 0.45103647 | O182: =IF(G182>M182,"Yes","No") -> Yes | P182: =IF(O182="Yes",1,0) -> 1 | Q182: =SUM($P$4:P182)/COUNT($P$4:P182) -> 0.52513966 | S182: 11850.21 | T182: =(S182/S181)-1 -> 0.014653564 | U182: =(S182/$S$3)-1 -> 0.38071209 | V182: =IF(G182>T182,"Yes","No") -> No | W182: =IF(V182="Yes",1,0) -> 0 | X182: =SUM($W$4:W182)/COUNT($W$4:W182) -> 0.51396648 | Z182: 2299.99 | AA182: =(Z182/Z181)-1 -> 0.018402164 | AB182: =(Z182/$Z$3)-1 -> 0.53038832
A183: =A182+1 -> 181 | B183: =B182+7 -> 39003 | D183: 32558.329 | E183: =D183+SUM(Holdings_Old!$E$32:$E$35) -> 32558.329 | F183: =E183-E182 -> 512.57647 | G183: =(E183/E182)-1 -> 0.015995145 | H183: =E183-$D$3 -> 9702.4789 | I183: =(E183/$D$3)-1 -> 0.42450746 | L183: 1365.61 | M183: =(L183/L182)-1 -> 0.011877769 | N183: =(L183/$L$3)-1 -> 0.46827155 | O183: =IF(G183>M183,"Yes","No") -> Yes | P183: =IF(O183="Yes",1,0) -> 1 | Q183: =SUM($P$4:P183)/COUNT($P$4:P183) -> 0.52777778 | S183: 11960.51 | T183: =(S183/S182)-1 -> 0.0093078519 | U183: =(S183/$S$3)-1 -> 0.39356355 | V183: =IF(G183>T183,"Yes","No") -> Yes | W183: =IF(V183="Yes",1,0) -> 1 | X183: =SUM($W$4:W183)/COUNT($W$4:W183) -> 0.51666667 | Z183: 2357.29 | AA183: =(Z183/Z182)-1 -> 0.024913152 | AB183: =(Z183/$Z$3)-1 -> 0.56851512
A184: =A183+1 -> 182 | B184: =B183+7 -> 39010 | D184: 32608.25 | E184: =D184+SUM(Holdings_Old!$E$32:$E$35) -> 32608.25 | F184: =E184-E183 -> 49.92109 | G184: =(E184/E183)-1 -> 0.0015332817 | H184: =E184-$D$3 -> 9752.4 | I184: =(E184/$D$3)-1 -> 0.42669163 | L184: 1368.58 | M184: =(L184/L183)-1 -> 0.0021748523 | N184: =(L184/$L$3)-1 -> 0.47146482 | O184: =IF(G184>M184,"Yes","No") -> No | P184: =IF(O184="Yes",1,0) -> 0 | Q184: =SUM($P$4:P184)/COUNT($P$4:P184) -> 0.52486188 | S184: 12002.37 | T184: =(S184/S183)-1 -> 0.0034998508 | U184: =(S184/$S$3)-1 -> 0.39844081 | V184: =IF(G184>T184,"Yes","No") -> No | W184: =IF(V184="Yes",1,0) -> 0 | X184: =SUM($W$4:W184)/COUNT($W$4:W184) -> 0.51381215 | Z184: 2342.3 | AA184: =(Z184/Z183)-1 -> -0.006358997 | AB184: =(Z184/$Z$3)-1 -> 0.55854093
A185: =A184+1 -> 183 | B185: =B184+7 -> 39017 | D185: 32630.82 | E185: =D185+SUM(Holdings_Old!$E$32:$E$35) -> 32630.82 | F185: =E185-E184 -> 22.57 | G185: =(E185/E184)-1 -> 0.00069215613 | H185: =E185-$D$3 -> 9774.97 | I185: =(E185/$D$3)-1 -> 0.42767913 | L185: 1377.3 | M185: =(L185/L184)-1 -> 0.0063715676 | N185: =(L185/$L$3)-1 -> 0.48084036 | O185: =IF(G185>M185,"Yes","No") -> No | P185: =IF(O185="Yes",1,0) -> 0 | Q185: =SUM($P$4:P185)/COUNT($P$4:P185) -> 0.52197802 | S185: 12090.26 | T185: =(S185/S184)-1 -> 0.0073227204 | U185: =(S185/$S$3)-1 -> 0.4086812 | V185: =IF(G185>T185,"Yes","No") -> No | W185: =IF(V185="Yes",1,0) -> 0 | X185: =SUM($W$4:W185)/COUNT($W$4:W185) -> 0.51098901 | Z185: 2350.62 | AA185: =(Z185/Z184)-1 -> 0.0035520642 | AB185: =(Z185/$Z$3)-1 -> 0.56407697
A186: =A185+1 -> 184 | B186: =B185+7 -> 39024 | D186: 32621 | E186: =D186+SUM(Holdings_Old!$E$32:$E$35) -> 32621 | F186: =E186-E185 -> -9.82 | G186: =(E186/E185)-1 -> -0.00030094248 | H186: =E186-$D$3 -> 9765.15 | I186: =(E186/$D$3)-1 -> 0.42724948 | L186: 1364.27 | M186: =(L186/L185)-1 -> -0.0094605387 | N186: =(L186/$L$3)-1 -> 0.46683081 | O186: =IF(G186>M186,"Yes","No") -> Yes | P186: =IF(O186="Yes",1,0) -> 1 | Q186: =SUM($P$4:P186)/COUNT($P$4:P186) -> 0.52459016 | S186: 11986.04 | T186: =(S186/S185)-1 -> -0.008620162 | U186: =(S186/$S$3)-1 -> 0.39653814 | V186: =IF(G186>T186,"Yes","No") -> Yes | W186: =IF(V186="Yes",1,0) -> 1 | X186: =SUM($W$4:W186)/COUNT($W$4:W186) -> 0.5136612 | Z186: 2330.79 | AA186: =(Z186/Z185)-1 -> -0.0084360722 | AB186: =(Z186/$Z$3)-1 -> 0.55088231
A187: =A186+1 -> 185 | B187: =B186+7 -> 39031 | D187: 33193.05 | E187: =D187+SUM(Holdings_Old!$E$32:$E$35) -> 33193.05 | F187: =E187-E186 -> 572.05 | G187: =(E187/E186)-1 -> 0.01753625 | H187: =E187-$D$3 -> 10337.2 | I187: =(E187/$D$3)-1 -> 0.45227808 | L187: 1380.58 | M187: =(L187/L186)-1 -> 0.011955112 | N187: =(L187/$L$3)-1 -> 0.48436694 | O187: =IF(G187>M187,"Yes","No") -> Yes | P187: =IF(O187="Yes",1,0) -> 1 | Q187: =SUM($P$4:P187)/COUNT($P$4:P187) -> 0.52717391 | S187: 12108.43 | T187: =(S187/S186)-1 -> 0.010211046 | U187: =(S187/$S$3)-1 -> 0.41079826 | V187: =IF(G187>T187,"Yes","No") -> Yes | W187: =IF(V187="Yes",1,0) -> 1 | X187: =SUM($W$4:W187)/COUNT($W$4:W187) -> 0.51630435 | Z187: 2389.72 | AA187: =(Z187/Z186)-1 -> 0.025283273 | AB187: =(Z187/$Z$3)-1 -> 0.59009369
A188: =A187+1 -> 186 | B188: =B187+7 -> 39038 | D188: 33718.23 | E188: =D188+SUM(Holdings_Old!$E$32:$E$35) -> 33718.23 | F188: =E188-E187 -> 525.18 | G188: =(E188/E187)-1 -> 0.015821987 | H188: =E188-$D$3 -> 10862.38 | I188: =(E188/$D$3)-1 -> 0.47525601 | L188: 1401.17 | M188: =(L188/L187)-1 -> 0.014914022 | N188: =(L188/$L$3)-1 -> 0.50650482 | O188: =IF(G188>M188,"Yes","No") -> Yes | P188: =IF(O188="Yes",1,0) -> 1 | Q188: =SUM($P$4:P188)/COUNT($P$4:P188) -> 0.52972973 | S188: 12342.56 | T188: =(S188/S187)-1 -> 0.019336115 | U188: =(S188/$S$3)-1 -> 0.43807762 | V188: =IF(G188>T188,"Yes","No") -> No | W188: =IF(V188="Yes",1,0) -> 0 | X188: =SUM($W$4:W188)/COUNT($W$4:W188) -> 0.51351351 | Z188: 2445.86 | AA188: =(Z188/Z187)-1 -> 0.023492292 | AB188: =(Z188/$Z$3)-1 -> 0.62744863
A189: =A188+1 -> 187 | B189: =B188+7 -> 39045 | D189: 33895 | E189: =D189+SUM(Holdings_Old!$E$32:$E$35) -> 33895 | F189: =E189-E188 -> 176.77 | G189: =(E189/E188)-1 -> 0.0052425646 | H189: =E189-$D$3 -> 11039.15 | I189: =(E189/$D$3)-1 -> 0.48299013 | L189: 1400.95 | M189: =(L189/L188)-1 -> -0.00015701164 | N189: =(L189/$L$3)-1 -> 0.50626828 | O189: =IF(G189>M189,"Yes","No") -> Yes | P189: =IF(O189="Yes",1,0) -> 1 | Q189: =SUM($P$4:P189)/COUNT($P$4:P189) -> 0.53225806 | T189: =(S189/S188)-1 -> -1 | U189: =(S189/$S$3)-1 -> -1 | V189: =IF(G189>T189,"Yes","No") -> Yes | W189: =IF(V189="Yes",1,0) -> 1 | X189: =SUM($W$4:W189)/COUNT($W$4:W189) -> 0.51612903 | Z189: 2460.26 | AA189: =(Z189/Z188)-1 -> 0.0058874997 | AB189: =(Z189/$Z$3)-1 -> 0.63703024
A190: =A189+1 -> 188 | B190: =B189+7 -> 39052 | C190: =D194-D189 -> 718 | D190: 33896 | E190: =D190+SUM(Holdings_Old!$E$32:$E$35) -> 33896 | F190: =E190-E189 -> 1 | G190: =(E190/E189)-1 -> 2.9502877e-05 | H190: =E190-$D$3 -> 11040.15 | I190: =(E190/$D$3)-1 -> 0.48303388 | L190: 1396.67 | M190: =(L190/L189)-1 -> -0.0030550698 | N190: =(L190/$L$3)-1 -> 0.50166652 | O190: =IF(G190>M190,"Yes","No") -> Yes | P190: =IF(O190="Yes",1,0) -> 1 | Q190: =SUM($P$4:P190)/COUNT($P$4:P190) -> 0.53475936 | T190: =(S190/S189)-1 -> #DIV/0! | U190: =(S190/$S$3)-1 -> -1 | V190: =IF(G190>T190,"Yes","No") -> #DIV/0! | W190: =IF(V190="Yes",1,0) -> #DIV/0! | X190: =SUM($W$4:W190)/COUNT($W$4:W190) -> #DIV/0! | Z190: 2413.21 | AA190: =(Z190/Z189)-1 -> -0.019123995 | AB190: =(Z190/$Z$3)-1 -> 0.60572368
A191: =A190+1 -> 189 | B191: =B190+7 -> 39059 | C191: =C190/4 -> 179.5 | D191: 33897 | E191: =D191+SUM(Holdings_Old!$E$32:$E$35) -> 33897 | F191: =E191-E190 -> 1 | G191: =(E191/E190)-1 -> 2.9502006e-05 | H191: =E191-$D$3 -> 11041.15 | I191: =(E191/$D$3)-1 -> 0.48307764 | L191: 1409.81 | M191: =(L191/L190)-1 -> 0.0094080921 | N191: =(L191/$L$3)-1 -> 0.51579434 | O191: =IF(G191>M191,"Yes","No") -> No | P191: =IF(O191="Yes",1,0) -> 0 | Q191: =SUM($P$4:P191)/COUNT($P$4:P191) -> 0.53191489 | T191: =(S191/S190)-1 -> #DIV/0! | U191: =(S191/$S$3)-1 -> -1 | V191: =IF(G191>T191,"Yes","No") -> #DIV/0! | W191: =IF(V191="Yes",1,0) -> #DIV/0! | X191: =SUM($W$4:W191)/COUNT($W$4:W191) -> #DIV/0! | Z191: 2437.36 | AA191: =(Z191/Z190)-1 -> 0.010007418 | AB191: =(Z191/$Z$3)-1 -> 0.62179282
A192: =A191+1 -> 190 | B192: =B191+7 -> 39066 | D192: 33898 | E192: =D192+SUM(Holdings_Old!$E$32:$E$35) -> 33898 | F192: =E192-E191 -> 1 | G192: =(E192/E191)-1 -> 2.9501136e-05 | H192: =E192-$D$3 -> 11042.15 | I192: =(E192/$D$3)-1 -> 0.48312139 | L192: 1427.08 | M192: =(L192/L191)-1 -> 0.012249878 | N192: =(L192/$L$3)-1 -> 0.53436264 | O192: =IF(G192>M192,"Yes","No") -> No | P192: =IF(O192="Yes",1,0) -> 0 | Q192: =SUM($P$4:P192)/COUNT($P$4:P192) -> 0.52910053 | T192: =(S192/S191)-1 -> #DIV/0! | U192: =(S192/$S$3)-1 -> -1 | V192: =IF(G192>T192,"Yes","No") -> #DIV/0! | W192: =IF(V192="Yes",1,0) -> #DIV/0! | X192: =SUM($W$4:W192)/COUNT($W$4:W192) -> #DIV/0! | Z192: 2457.2 | AA192: =(Z192/Z191)-1 -> 0.0081399547 | AB192: =(Z192/$Z$3)-1 -> 0.63499414
A193: =A192+1 -> 191 | B193: =B192+7 -> 39073 | D193: 33899 | E193: =D193+SUM(Holdings_Old!$E$32:$E$35) -> 33899 | F193: =E193-E192 -> 1 | G193: =(E193/E192)-1 -> 2.9500266e-05 | H193: =E193-$D$3 -> 11043.15 | I193: =(E193/$D$3)-1 -> 0.48316514 | L193: 1410.75 | M193: =(L193/L192)-1 -> -0.011442946 | N193: =(L193/$L$3)-1 -> 0.51680501 | O193: =IF(G193>M193,"Yes","No") -> Yes | P193: =IF(O193="Yes",1,0) -> 1 | Q193: =SUM($P$4:P193)/COUNT($P$4:P193) -> 0.53157895 | T193: =(S193/S192)-1 -> #DIV/0! | U193: =(S193/$S$3)-1 -> -1 | V193: =IF(G193>T193,"Yes","No") -> #DIV/0! | W193: =IF(V193="Yes",1,0) -> #DIV/0! | X193: =SUM($W$4:W193)/COUNT($W$4:W193) -> #DIV/0! | Z193: 2401.18 | AA193: =(Z193/Z192)-1 -> -0.022798307 | AB193: =(Z193/$Z$3)-1 -> 0.59771905
A194: =A193+1 -> 192 | B194: =B193+7 -> 39080 | D194: 34613 | E194: =D194+SUM(Holdings_Old!$E$32:$E$35) -> 34613 | F194: =E194-E193 -> 714 | G194: =(E194/E193)-1 -> 0.021062568 | H194: =E194-$D$3 -> 11757.15 | I194: =(E194/$D$3)-1 -> 0.51440441 | L194: 1418.03 | M194: =(L194/L193)-1 -> 0.0051603757 | N194: =(L194/$L$3)-1 -> 0.52463229 | O194: =IF(G194>M194,"Yes","No") -> Yes | P194: =IF(O194="Yes",1,0) -> 1 | Q194: =SUM($P$4:P194)/COUNT($P$4:P194) -> 0.53403141 | T194: =(S194/S193)-1 -> #DIV/0! | U194: =(S194/$S$3)-1 -> -1 | V194: =IF(G194>T194,"Yes","No") -> #DIV/0! | W194: =IF(V194="Yes",1,0) -> #DIV/0! | X194: =SUM($W$4:W194)/COUNT($W$4:W194) -> #DIV/0! | Z194: 2415.29 | AA194: =(Z194/Z193)-1 -> 0.0058762775 | AB194: =(Z194/$Z$3)-1 -> 0.60710769
A195: =A194+1 -> 193 | B195: =B194+7 -> 39087 | D195: 34614 | E195: =D195+SUM(Holdings_Old!$E$32:$E$35) -> 34614 | F195: =E195-E194 -> 1 | G195: =(E195/E194)-1 -> 2.8890879e-05 | H195: =E195-$D$3 -> 11758.15 | I195: =(E195/$D$3)-1 -> 0.51444816 | L195: 1409.26 | M195: =(L195/L194)-1 -> -0.0061846364 | N195: =(L195/$L$3)-1 -> 0.51520299 | O195: =IF(G195>M195,"Yes","No") -> Yes | P195: =IF(O195="Yes",1,0) -> 1 | Q195: =SUM($P$4:P195)/COUNT($P$4:P195) -> 0.53645833 | T195: =(S195/S194)-1 -> #DIV/0! | U195: =(S195/$S$3)-1 -> -1 | V195: =IF(G195>T195,"Yes","No") -> #DIV/0! | W195: =IF(V195="Yes",1,0) -> #DIV/0! | X195: =SUM($W$4:W195)/COUNT($W$4:W195) -> #DIV/0! | Z195: 2434.25 | AA195: =(Z195/Z194)-1 -> 0.007849989 | AB195: =(Z195/$Z$3)-1 -> 0.61972346
A196: =A195+1 -> 194 | B196: =B195+7 -> 39094 | D196: 34615 | E196: =D196+SUM(Holdings_Old!$E$32:$E$35) -> 34615 | F196: =E196-E195 -> 1 | G196: =(E196/E195)-1 -> 2.8890044e-05 | H196: =E196-$D$3 -> 11759.15 | I196: =(E196/$D$3)-1 -> 0.51449191 | L196: 1430.73 | M196: =(L196/L195)-1 -> 0.015234946 | N196: =(L196/$L$3)-1 -> 0.53828703 | O196: =IF(G196>M196,"Yes","No") -> No | P196: =IF(O196="Yes",1,0) -> 0 | Q196: =SUM($P$4:P196)/COUNT($P$4:P196) -> 0.53367876 | T196: =(S196/S195)-1 -> #DIV/0! | U196: =(S196/$S$3)-1 -> -1 | V196: =IF(G196>T196,"Yes","No") -> #DIV/0! | W196: =IF(V196="Yes",1,0) -> #DIV/0! | X196: =SUM($W$4:W196)/COUNT($W$4:W196) -> #DIV/0! | Z196: 2502.82 | AA196: =(Z196/Z195)-1 -> 0.028168841 | AB196: =(Z196/$Z$3)-1 -> 0.6653492
...

Sheet V.P. of PM
G3: Date of Reference | H3: 41725
D4: Sector | E4: $ Value | F4: % Weight | G4: Model Weight | H4: Holdings
D5: Cash | E5: =SUMIF(Holdings!$V$4:$V$21,$D5,Holdings!$I$4:$I$21) -> 8050.26 | F5: =E5/$E$17 -> 0.1360555 | G5: =IF(F5>0.2,"Overweight",IF(F5>0.125,"Slightly Overweight",IF(F5>0.08,"Equal Weight","Underweight"))) -> Slightly Overweight | H5: =(IF(D5="Cash","NA",COUNTIF(Holdings!$S$4:$V$27,'V.P. of PM'!$D5))) -> NA
D6: Bond | E6: =SUMIF(Holdings!$V$4:$V$27,$D6,Holdings!$I$4:$I$26) -> 0 | F6: =E6/$E$17 -> 0 | G6: =IF(F6>0.2,"Overweight",IF(F6>0.125,"Slightly Overweight",IF(F6>0.08,"Equal Weight","Underweight"))) -> Underweight | H6: =(IF(D6="Cash","NA",COUNTIF(Holdings!$S$4:$V$27,'V.P. of PM'!$D6))) -> 0
D7: Consumer Discretionary | E7: =SUMIF(Holdings!$V$4:$V$27,$D7,Holdings!$I$4:$I$26) -> 13390.43 | F7: =E7/$E$17 -> 0.22630843 | G7: =IF(F7>0.2,"Overweight",IF(F7>0.125,"Slightly Overweight",IF(F7>0.08,"Equal Weight","Underweight"))) -> Overweight | H7: =(IF(D7="Cash","NA",COUNTIF(Holdings!$S$4:$V$27,'V.P. of PM'!$D7))) -> 3
D8: Consumer Staples | E8: =SUMIF(Holdings!$V$4:$V$27,$D8,Holdings!$I$4:$I$26) -> 5392.17 | F8: =E8/$E$17 -> 0.091131766 | G8: =IF(F8>0.2,"Overweight",IF(F8>0.125,"Slightly Overweight",IF(F8>0.08,"Equal Weight","Underweight"))) -> Equal Weight | H8: =(IF(D8="Cash","NA",COUNTIF(Holdings!$S$4:$V$27,'V.P. of PM'!$D8))) -> 2
D9: Energy | E9: =SUMIF(Holdings!$V$4:$V$27,$D9,Holdings!$I$4:$I$26) -> 2665.32 | F9: =E9/$E$17 -> 0.045045931 | G9: =IF(F9>0.2,"Overweight",IF(F9>0.125,"Slightly Overweight",IF(F9>0.08,"Equal Weight","Underweight"))) -> Underweight | H9: =(IF(D9="Cash","NA",COUNTIF(Holdings!$S$4:$V$27,'V.P. of PM'!$D9))) -> 1
D10: Financial | E10: =SUMIF(Holdings!$V$4:$V$27,$D10,Holdings!$I$4:$I$26) -> 6324.82 | F10: =E10/$E$17 -> 0.10689426 | G10: =IF(F10>0.2,"Overweight",IF(F10>0.125,"Slightly Overweight",IF(F10>0.08,"Equal Weight","Underweight"))) -> Equal Weight | H10: =(IF(D10="Cash","NA",COUNTIF(Holdings!$S$4:$V$27,'V.P. of PM'!$D10))) -> 2
D11: Healthcare | E11: =SUMIF(Holdings!$V$4:$V$27,$D11,Holdings!$I$4:$I$26) -> 4588.87 | F11: =E11/$E$17 -> 0.077555386 | G11: =IF(F11>0.2,"Overweight",IF(F11>0.125,"Slightly Overweight",IF(F11>0.08,"Equal Weight","Underweight"))) -> Underweight | H11: =(IF(D11="Cash","NA",COUNTIF(Holdings!$S$4:$V$27,'V.P. of PM'!$D11))) -> 2
D12: Industrials | E12: =SUMIF(Holdings!$V$4:$V$27,$D12,Holdings!$I$4:$I$26) -> 7986 | F12: =E12/$E$17 -> 0.13496946 | G12: =IF(F12>0.2,"Overweight",IF(F12>0.125,"Slightly Overweight",IF(F12>0.08,"Equal Weight","Underweight"))) -> Slightly Overweight | H12: =(IF(D12="Cash","NA",COUNTIF(Holdings!$S$4:$V$27,'V.P. of PM'!$D12))) -> 2
D13: Information Technology | E13: =SUMIF(Holdings!$V$4:$V$27,$D13,Holdings!$I$4:$I$26) -> 10771.07 | F13: =E13/$E$17 -> 0.18203926 | G13: =IF(F13>0.2,"Overweight",IF(F13>0.125,"Slightly Overweight",IF(F13>0.08,"Equal Weight","Underweight"))) -> Slightly Overweight | H13: =(IF(D13="Cash","NA",COUNTIF(Holdings!$S$4:$V$27,'V.P. of PM'!$D13))) -> 4
D14: Materials | E14: =SUMIF(Holdings!$V$4:$V$27,$D14,Holdings!$I$4:$I$26) -> 0 | F14: =E14/$E$17 -> 0 | G14: =IF(F14>0.2,"Overweight",IF(F14>0.125,"Slightly Overweight",IF(F14>0.08,"Equal Weight","Underweight"))) -> Underweight | H14: =(IF(D14="Cash","NA",COUNTIF(Holdings!$S$4:$V$27,'V.P. of PM'!$D14))) -> 0
D15: Telecommunications | E15: =SUMIF(Holdings!$V$4:$V$27,$D15,Holdings!$I$4:$I$26) -> 0 | F15: =E15/$E$17 -> 0 | G15: =IF(F15>0.2,"Overweight",IF(F15>0.125,"Slightly Overweight",IF(F15>0.08,"Equal Weight","Underweight"))) -> Underweight | H15: =(IF(D15="Cash","NA",COUNTIF(Holdings!$S$4:$V$27,'V.P. of PM'!$D15))) -> 0
D16: Utilities | E16: =SUMIF(Holdings!$V$4:$V$27,$D16,Holdings!$I$4:$I$26) -> 0 | F16: =E16/$E$17 -> 0 | G16: =IF(F16>0.2,"Overweight",IF(F16>0.125,"Slightly Overweight",IF(F16>0.08,"Equal Weight","Underweight"))) -> Underweight | H16: =(IF(D16="Cash","NA",COUNTIF(Holdings!$S$4:$V$27,'V.P. of PM'!$D16))) -> 0
D17: Totals | E17: =SUM(E5:E16) -> 59168.94 | F17: =SUM(F5:F16) -> 1 | H17: =(SUM(H5:H16)) -> 16
D20: Return Period | E20: I.P.O. | F20: S&P 500 | G20: Comments
D21: 1 Week | E21: =OFFSET(Data!$G$3,MATCH($H$3,Data!$B$3:$B$1000,0)-1,,) -> -0.018396275 | F21: =OFFSET(Data!M3,MATCH(H3,Data!B3:B1000,0)-1,,) -> -0.012270234 | G21: ="IPO "&IF(E21>F21,"out-performed","under-performed")&" the S&P 500 by "&ABS(ROUND((E21-F21),4))*100&"%." -> IPO under-performed the S&P 500 by 0.61%.
D22: 1 Month | E22: =((OFFSET(Data!$D$3,MATCH($H$3,Data!$B$3:$B$1000,0)-1,,)-(OFFSET(Data!$D$3,MATCH($H$3,Data!$B$3:$B$1000,0)-5,,)))/(OFFSET(Data!$D$3,MATCH($H$3,Data!$B$3:$B$1000,0)-5,,))) -> 0.010956337 | F22: =((OFFSET(Data!$L$3,MATCH($H$3,Data!$B$3:$B$1000,0)-1,,)-(OFFSET(Data!$L$3,MATCH($H$3,Data!$B$3:$B$1000,0)-5,,)))/(OFFSET(Data!$L$3,MATCH($H$3,Data!$B$3:$B$1000,0)-5,,))) -> -0.0028312723 | G22: ="IPO "&IF(E22>F22,"out-performed","under-performed")&" the S&P 500 by "&ABS(ROUND((E22-F22),4))*100&"%." -> IPO out-performed the S&P 500 by 1.38%.
D23: 3 Month | E23: =((OFFSET(Data!$D$3,MATCH($H$3,Data!$B$3:$B$1000,0)-1,,)-(OFFSET(Data!$D$3,MATCH($H$3,Data!$B$3:$B$1000,0)-14,,)))/(OFFSET(Data!$D$3,MATCH($H$3,Data!$B$3:$B$1000,0)-14,,))) -> 0.037266376 | F23: =((OFFSET(Data!$L$3,MATCH($H$3,Data!$B$3:$B$1000,0)-1,,)-(OFFSET(Data!$L$3,MATCH($H$3,Data!$B$3:$B$1000,0)-14,,)))/(OFFSET(Data!$L$3,MATCH($H$3,Data!$B$3:$B$1000,0)-14,,))) -> 0.0038110335 | G23: ="IPO "&IF(E23>F23,"out-performed","under-performed")&" the S&P 500 by "&ABS(ROUND((E23-F23),4))*100&"%." -> IPO out-performed the S&P 500 by 3.35%.
D24: 6 Month | E24: =((OFFSET(Data!$D$3,MATCH($H$3,Data!$B$3:$B$1000,0)-1,,)-(OFFSET(Data!$D$3,MATCH($H$3,Data!$B$3:$B$1000,0)-27,,)))/(OFFSET(Data!$D$3,MATCH($H$3,Data!$B$3:$B$1000,0)-27,,))) -> 0.1523978 | F24: =((OFFSET(Data!$L$3,MATCH($H$3,Data!$B$3:$B$1000,0)-1,,)-(OFFSET(Data!$L$3,MATCH($H$3,Data!$B$3:$B$1000,0)-27,,)))/(OFFSET(Data!$L$3,MATCH($H$3,Data!$B$3:$B$1000,0)-27,,))) -> 0.088522197 | G24: ="IPO "&IF(E24>F24,"out-performed","under-performed")&" the S&P 500 by "&ABS(ROUND((E24-F24),4))*100&"%." -> IPO out-performed the S&P 500 by 6.39%.
D25: 1 Year | E25: =((OFFSET(Data!$D$3,MATCH($H$3,Data!$B$3:$B$1000,0)-1,,)-(OFFSET(Data!$D$3,MATCH($H$3,Data!$B$3:$B$1000,0)-53,,)))/(OFFSET(Data!$D$3,MATCH($H$3,Data!$B$3:$B$1000,0)-53,,))) -> 0.32818322 | F25: =((OFFSET(Data!$L$3,MATCH($H$3,Data!$B$3:$B$1000,0)-1,,)-(OFFSET(Data!$L$3,MATCH($H$3,Data!$B$3:$B$1000,0)-53,,)))/(OFFSET(Data!$L$3,MATCH($H$3,Data!$B$3:$B$1000,0)-53,,))) -> 0.17834042 | G25: ="IPO "&IF(E25>F25,"out-performed","under-performed")&" the S&P 500 by "&ABS(ROUND((E25-F25),4))*100&"%." -> IPO out-performed the S&P 500 by 14.98%.
D26: 2 Year | E26: =((OFFSET(Data!$D$3,MATCH($H$3,Data!$B$3:$B$1000,0)-1,,)-(OFFSET(Data!$D$3,MATCH($H$3,Data!$B$3:$B$1000,0)-105,,)))/(OFFSET(Data!$D$3,MATCH($H$3,Data!$B$3:$B$1000,0)-105,,))) -> 0.50363269 | F26: =((OFFSET(Data!$L$3,MATCH($H$3,Data!$B$3:$B$1000,0)-1,,)-(OFFSET(Data!$L$3,MATCH($H$3,Data!$B$3:$B$1000,0)-105,,)))/(OFFSET(Data!$L$3,MATCH($H$3,Data!$B$3:$B$1000,0)-105,,))) -> 0.32553371 | G26: ="IPO "&IF(E26>F26,"out-performed","under-performed")&" the S&P 500 by "&ABS(ROUND((E26-F26),4))*100&"%." -> IPO out-performed the S&P 500 by 17.81%.
D29: Mkt Cap | E29: Cap $ Value | G29: Cap % Weight
D30: Large | E30: =SUMIF(Holdings!$Y$4:$Y$27,$D30,Holdings!$I$4:$I$26) -> 41399.63 | G30: =E30/$E$36 -> 0.67755336
D31: Mid | E31: =SUMIF(Holdings!$Y$4:$Y$27,$D31,Holdings!$I$4:$I$26) -> 2622.95 | G31: =E31/$E$36 -> 0.042927644
D32: Small | E32: =SUMIF(Holdings!$Y$4:$Y$27,$D32,Holdings!$I$4:$I$26) -> 7096.1 | G32: =E32/$E$36 -> 0.11613598
D33: Bond | E33: =SUMIF(Holdings!$Y$4:$Y$27,$D33,Holdings!$I$4:$I$26) -> 1932.7122 | G33: =E33/$E$36 -> 0.031631095
D34: Option | E34: =SUMIF(Holdings!$Y$4:$Y$27,$D34,Holdings!$I$4:$I$26) -> 0 | G34: =E34/$E$36 -> 0
D35: Cash | E35: =SUMIF(Holdings!$Y$4:$Y$27,$D35,Holdings!$I$4:$I$26) -> 8050.26 | G35: =E35/$E$36 -> 0.13175192
D36: Total | E36: =SUM(E30:E35) -> 61101.652 | G36: =SUM(G30:G35) -> 1

Sheet Transactions
B2: Seidman I.P.O. Transaction History (starting 5/12/03)
B4: Date | C4: Type | D4: Ticker | E4: Price | F4: Shares | G4: Total Value | H4: Commission | I4: Vote
B5: 37753 | C5: SC | D5: NVDA | E5: 20.04 | F5: 30 | G5: =F5*E5 -> 601.2 | H5: 0 | I5: 1
B7: 38289 | C7: SC | D7: F | E7: 12.95 | F7: 65 | G7: =E7*F7 -> 841.75 | H7: 10.99 | I7: 0.82
B9: 38296 | C9: BO | D9: GNTX | E9: 33.1 | F9: 40 | G9: =E9*F9 -> 1324 | H9: 10.99 | I9: 0.79
B11: 38296 | C11: BO | D11: MMM | E11: 79.9 | F11: 20 | G11: =E11*F11 -> 1598 | H11: 10.99 | I11: 0.72
B13: 38408 | C13: BO | D13: QCOM | E13: 35.37 | F13: 41 | G13: =E13*F13 -> 1450.17 | H13: 10.99 | I13: 0.75
B15: 38408 | C15: SC | D15: HNP | E15: 30.65 | F15: 42 | G15: =E15*F15 -> 1287.3 | H15: 10.99 | I15: 0.84
B17: 38670 | C17: BO | D17: CEDC | E17: 27.8 | F17: 21 | G17: =F17*E17 -> 583.8 | H17: 9.99 | I17: 0.9
B19: 38744 | C19: SC | D19: LUV | E19: 16.302 | F19: 122 | G19: =E19*F19 -> 1988.844 | H19: 10.99 | I19: 0.97
B21: 38989 | C21: BO | D21: UPS | E21: 72.66 | F21: 40 | G21: =E21*F21 -> 2906.4 | H21: 10.99 | I21: =40/43 -> 0.93023256
B23: 39010 | C23: SC | D23: OPCHX | E23: 9.37 | F23: 190.132 | G23: =E23*F23 -> 1781.5368 | H23: 0 | I23: 0.98
B25: 39010 | C25: SC | D25: SAHYX | E25: 8.39 | F25: 217.855 | G25: =E25*F25 -> 1827.8035 | H25: 0 | I25: 0.84
B27: 39031 | C27: SC | D27: INTC | E27: 20.61 | F27: 50 | G27: =F27*E27 -> 1030.5 | H27: 9.99 | I27: 0.82
B29: 39115 | C29: BO | D29: CPL | E29: 41 | F29: 45 | G29: =F29*E29 -> 1845 | H29: 9.99 | I29: 0.9
B31: 39115 | C31: BO | D31: MNT | E31: 51.92 | F31: 35 | G31: =F31*E31 -> 1817.2 | H31: 9.99 | I31: 0.8
B33: 39136 | C33: SC | D33: MSFT | E33: 29.1225 | F33: 38 | G33: =F33*E33 -> 1106.655 | H33: 9.99 | I33: 0.85
B35: 39373 | C35: SC | D35: PTR | E35: 243.55 | F35: 13 | G35: =F35*E35 -> 3166.15 | H35: 9.99 | I35: 0.98
B37: 39387 | C37: BO | D37: PBW | E37: 24.53 | F37: 100 | G37: =F37*E37 -> 2453 | H37: 9.99 | I37: 0.8
B39: 39850 | C39: BO | D39: ITRI | E39: 62.69 | F39: 25 | G39: 1567.29 | H39: 9.99 | I39: 0.96
B41: 40094 | C41: SO | D41: CEDC | E41: 2.7 | F41: 100 | G41: 270 | H41: 9.99 | I41: 0.915 | J41: Sell Call
B43: 40108 | C43: SC | D43: ERTS | E43: 20.19 | F43: 22 | G43: 434.17 | H43: 9.99 | I43: 0.95
B45: 40122 | C45: BO | D45: DRI | E45: 32.72 | F45: 50 | G45: 1645.99 | H45: 9.99 | I45: 0.75
B47: 40129 | C47: SC | D47: MMM | E47: 77.22 | F47: 21 | G47: 1621.62 | H47: 9.99 | I47: 0.96
B49: 40129 | C49: SC | D49: WAG | E49: 39.06 | F49: 46 | G49: 1796.76 | H49: 9.99 | I49: 0.96
B51: 40129 | C51: BO | D51: TTEK | E51: 25.46 | F51: 60 | G51: 1527.6 | H51: 9.99 | I51: 0.68
B53: 40129 | C53: BO | D53: HCP | E53: 29.24 | F53: 52 | G53: 1520.48 | H53: 9.99 | I53: 0.73
B55: 40210 | C55: BO | D55: BRK.B | E55: 77.89 | F55: 26 | G55: =E55*F55 -> 2025.14 | H55: 9.99 | I55: 0.78
B57: 40210 | C57: SC | D57: C | E57: 3.36 | F57: 33 | G57: =E57*F57 -> 110.88 | H57: 9.99 | I57: 0.73
B59: 40214 | C59: SC | D59: PBW | E59: 9.34 | F59: 250 | G59: =E59*F59 -> 2335 | H59: 9.99 | I59: 0.78
B61: 40242 | C61: BO | D61: WMMVY | E61: 50 | F61: 25 | G61: =E61*F61 -> 1250 | H61: 9.99 | I61: 0.82
C63: BO | D63: C | E63: 1.14 | F63: 800 | G63: =E63*F63 -> 912 | J63: Buy Call
B65: 40466 | C65: SC | D65: CEDC | E65: 23.93 | F65: 100 | G65: =E65*F65 -> 2393 | H65: 9.99 | I65: 1
B67: 40466 | C67: SC | D67: CPL | E67: 74.08 | F67: 43 | G67: =E67*F67 -> 3185.44 | H67: 9.99 | I67: 0.94
B69: 40466 | C69: BO | D69: PGX | E69: 14.43 | F69: 117 | G69: =E69*F69 -> 1688.31 | H69: 9.99 | I69: 0.97
B71: 40480 | C71: BO | D71: SINA | E71: 56.3 | F71: 27 | G71: =E71*F71 -> 1520.1 | H71: 9.99 | I71: 0.93
B73: 40480 | C73: BO | D73: XRX | E73: 10.89 | F73: 100 | G73: =E73*F73 -> 1089 | H73: 9.99
B75: 40616 | C75: SC | D75: DRI | E75: 46.6 | F75: 51 | G75: =F75*E75 -> 2376.6 | H75: 9.99 | I75: 0.86
B77: 40616 | C77: BO | D77: VALE | E77: 32.16 | F77: 34 | G77: =F77*E77 -> 1093.44 | H77: 9.99 | I77: 0.88
B79: 40658 | C79: SC | D79: SINA | E79: 135.35 | F79: 27 | G79: =E79*F79 -> 3654.45 | H79: 9.99
B81: 40773 | C81: BO | D81: GLD | E81: 177.43 | F81: 9 | G81: =E81*F81 -> 1596.87 | H81: 9.99
B83: 40829 | C83: BO | D83: MCLOX | E83: 17.23 | F83: 87.057 | G83: =E83*F83 -> 1499.9921 | H83: 9.99 | I83: 0.69
B85: 40891 | C85: SC | D85: GLD | E85: 156.06 | F85: 9 | G85: =E85*F85 -> 1404.54 | H85: 9.99 | I85: -
B87: 40942 | C87: SC | D87: PFE | E87: 21.22 | F87: 41 | G87: =F87*E87 -> 870.02 | H87: 9.99
B89: 40942 | C89: BO | D89: F | E89: 12.47 | F89: 65 | G89: =F89*E89 -> 810.55 | H89: 9.99
B91: 41166 | C91: SC | D91: VALE | E91: 19.71 | F91: 36.591 | G91: 711.2 | H91: 9.99 | I91: 0.85
B93: 41173 | C93: BO | D93: TSN | E93: 16.65 | F93: 100 | G93: 1674.98 | H93: 9.99 | I93: 0.66
B95: 41215 | C95: SC | D95: CPL | E95: 23 | F95: 57.813 | G95: 1319.69 | H95: 9.99 | I95: 0.72
B97: 41215 | C97: BO | D97: TPC | E97: 12.43 | F97: 150 | G97: 1875.74 | H97: 9.99 | I97: 0.78
B99: 41222 | C99: BO | D99: CAT | E99: 83 | F99: 15 | G99: 1319.69 | H99: 9.99 | I99: 0.72
B101: 41243 | C101: BO | D101: NGVC | E101: 19.49 | F101: 75 | G101: 1471.73 | H101: 9.99 | I101: 0.96
B103: 41243 | C103: SC | D103: SYK | E103: 54.07 | F103: 41.745 | G103: 2247.11 | H103: 9.99 | I103: 0.96
B105: 41298 | C105: SC | D105: PGX | E105: 14.86 | F105: 134.993 | G105: =F105*E105 -> 2005.996 | H105: 9.99 | I105: 1
B107: 41334 | C107: BO | D107: YHOO | E107: 21.75 | F107: 100 | G107: =F107*E107 -> 2175 | H107: 9.99 | I107: =(31/40) -> 0.775
B109: 41355 | C109: SC | D109: PTR | E109: 131.71 | F109: 15.202 | G109: =F109*E109 -> 2002.2554 | H109: 9.99 | I109: 0.76
B111: 41355 | C111: SC | D111: UPS | E111: 83.3 | F111: 47.706 | G111: =F111*E111 -> 3973.9098 | H111: 9.99 | I111: 0.78
B113: 41355 | C113: BO | D113: YRCW | E113: 8.61 | F113: 300 | G113: =F113*E113 -> 2583 | H113: 9.99 | I113: 0.78
B115: 41365 | C115: SC | D115: F | E115: 13.01 | F115: 66.476 | G115: =F115*E115 -> 864.85276 | H115: 9.99 | I115: 0.76
B117: 41365 | C117: BO | D117: DAL | E117: 16.48 | F117: 150 | G117: =F117*E117 -> 2472 | H117: 9.99 | I117: 0.76
B119: 41397 | C119: SC | D119: YRCW | E119: 11.25 | F119: 100 | G119: =F119*E119 -> 1125 | H119: 9.99 | I119: -
B121: 41416 | C121: SC | D121: TTEK | E121: 28.061 | F121: 60 | G121: =F121*E121 -> 1683.66 | H121: 9.99 | I121: -
B123: 41416 | C123: SC | D123: WMMVY | E123: 28.75 | F123: 53.13 | G123: =F123*E123 -> 1527.4875 | H123: 9.99 | I123: -
B125: 41416 | C125: BO | D125: CX | E125: 11.61 | F125: 150 | G125: =F125*E125 -> 1741.5 | H125: 9.99 | I125: -
B127: 41416 | C127: BO | D127: CX | E127: 11.46 | F127: 50 | G127: =F127*E127 -> 573 | H127: 9.99 | I127: -
B129: 41416 | C129: BO | D129: TPC | E129: 17.73 | F129: 50 | G129: =F129*E129 -> 886.5 | H129: 9.99 | I129: -
B131: 41424 | C131: SC | D131: ITRI | E131: 41.2 | F131: 25 | G131: =F131*E131 -> 1030 | H131: 9.99 | I131: -
B133: 41424 | C133: BO | D133: IMMR | E133: 15.04 | F133: 135 | G133: =F133*E133 -> 2030.4 | H133: 9.99 | I133: -
B135: 41438 | C135: SC | D135: HCP | E135: 45.66 | F135: 62 | G135: =F135*E135 -> 2830.92 | H135: 9.99 | I135: -
B137: 41438 | C137: SC | D137: QCOM | E137: 61.03 | F137: 45 | G137: =F137*E137 -> 2746.35 | H137: 9.99 | I137: -
B139: 41438 | C139: SC | D139: XRX | E139: 8.86 | F139: 105 | G139: =F139*E139 -> 930.3 | H139: 9.99 | I139: -
B141: 41438 | C141: BO | D141: INTC | E141: 24.72 | F141: 112 | G141: =F141*E141 -> 2768.64 | H141: 9.99 | I141: -
B143: 41449 | C143: BO | D143: CX | E143: 9.47 | F143: 50 | G143: =F143*E143 -> 473.5 | H143: 9.99 | I143: -
B145: 41530 | C145: BO | D145: ULTA | E145: 115.4 | F145: 20 | G145: =F145*E145 -> 2308 | H145: 9.99 | I145: 0.86
B147: 41544 | C147: BO | D147: PRGO | E147: 122.58 | F147: 18 | G147: =F147*E147 -> 2206.44 | H147: 9.99 | I147: 0.86
B149: 41551 | C149: SC | D149: CAT | E149: 83.94 | F149: 15.281 | G149: =F149*E149 -> 1282.6871 | H149: 9.99 | I149: 0.7
B151: 41576 | C151: SC | D151: YRCW | E151: 9.58 | F151: 200 | G151: =F151*E151 -> 1916 | H151: 9.99 | I151: -
B153: 41586 | C153: BO | D153: AAPL | E153: 34.9 | F153: 100 | G153: =F153*E153 -> 3490 | H153: 9.99 | I153: 0.72 | J153: AAPL $515 Call
B155: 41614 | C155: SC | D155: AAPL | E155: 65.85 | F155: 100 | G155: =F155*E155 -> 6585 | H155: 9.99 | I155: 0.88 | J155: AAPL $515 Call
B157: 41698 | C157: BO | D157: RRC | E157: 86.37 | F157: 42 | G157: =F157*E157 -> 3627.54 | H157: 9.99 | I157: 0.89
D159: Types of Transactions
B160: QUE | D160: BO | E160: Buy to Open your position.
D161: BC | E161: Buy to Close your position, "covering a short sell."
D162: SO | E162: Sell to Open your position, "short selling" / options
D163: SC | E163: Sell to Close your position.

Sheet Holdings_Old
B3: Ticker | C3: Holding | E3: Price | F3: Paid | G3: Shares | H3: Value | I3: Initial Cost | J3: Value on 9/6/12 | K3: Value 1 week ago | M3: $ Total Gain | N3: % Total Gain | O3: Semester | P3: Weekly | Q3: Today | S3: Sector | U3: Portfolio % Weight | W3: Mkt Cap (Billions) | Z3: P/E Ratio | AA3: EPS | AC3: Daily Return
B4: Cash | C4: Cash | E4: 1 | F4: =E4 -> 1 | G4: 2029.73 | H4: =E4*G4 -> 2029.73 | I4: =F4*G4 -> 2029.73 | J4: 4804 | K4: 2029.73 | S4: Cash | U4: =H4/$H$27 -> #REF! | W4: - | X4: Cash | AC4: =(0.01/365)*U4 -> #REF!
B5: BRK.B | C5: ='Holdings Pull Sheet'!C16 -> BERKSHIRE HATHAWAY CLASS B | E5: ='Holdings Pull Sheet'!F16 -> 137.09 | F5: 77.89 | G5: 26 | H5: =E5*G5 -> 3564.34 | I5: =F5*ROUNDDOWN(G5,0)+9.95 -> 2035.09 | J5: 2248.22 | K5: 2287.22 | M5: =H5-I5 -> 1529.25 | N5: =(H5/I5)-1 -> 0.75144097 | O5: =(H5/J5)-1 -> 0.58540532 | P5: =(H5/K5)-1 -> 0.55837217 | Q5: =('Holdings Pull Sheet'!F16/'Holdings Pull Sheet'!G16)-1 -> -0.020365871 | S5: Financial | U5: =H5/$H$27 -> #REF! | W5: ='Holdings Pull Sheet'!O16/1000000000 -> 319.36477 | X5: =IF(W5<2,"Small", IF(W5<10, "Mid", IF(W5>10, "Large"))) -> Large | Z5: ='Holdings Pull Sheet'!Q16 -> 15.19 | AA5: ='Holdings Pull Sheet'!P16 -> 9 | AC5: =Q5*U5 -> #REF!
C6: ='Holdings Pull Sheet'!C17 -> BlackRock Global Allocation Inv C | E6: ='Holdings Pull Sheet'!F17 -> 19.64 | F6: 17.23 | G6: 89.052 | H6: =E6*G6 -> 1748.9813 | I6: =F6*ROUNDDOWN(G6,0)+9.95 -> 1543.42 | J6: 1602.0455 | K6: 1610.9507 | M6: =H6-I6 -> 205.56128 | N6: =(H6/I6)-1 -> 0.13318557 | O6: =(H6/J6)-1 -> 0.091717635 | P6: =(H6/K6)-1 -> 0.085682698 | Q6: =('Holdings Pull Sheet'!F17/'Holdings Pull Sheet'!G17)-1 -> -0.013561025 | S6: Misc | U6: =H6/$H$27 -> #REF! | W6: 0 | X6: - | Z6: 0 | AA6: 0 | AC6: =Q6*U6 -> #REF!
B7: CPL | C7: ='Holdings Pull Sheet'!C18 -> CEMEX S.A.B. DE C.V. | E7: ='Holdings Pull Sheet'!F18 -> 12.2 | F7: 83 | G7: 15 | H7: =E7*G7 -> 183 | I7: =F7*ROUNDDOWN(G7,0)+9.95 -> 1254.95 | J7: 1245 | K7: 1293.75 | M7: =H7-I7 -> -1071.95 | N7: =(H7/I7)-1 -> -0.85417746 | O7: =(H7/J7)-1 -> -0.85301205 | P7: =(H7/K7)-1 -> -0.85855072 | Q7: =('Holdings Pull Sheet'!F18/'Holdings Pull Sheet'!G18)-1 -> -0.026336792 | S7: Industrials | U7: =H7/$H$27 -> #REF! | W7: ='Holdings Pull Sheet'!O18/1000000000 -> 14.494177 | X7: =IF(W7<2,"Small", IF(W7<10, "Mid", IF(W7>10, "Large"))) -> Large | Z7: ='Holdings Pull Sheet'!Q18 -> -25.33 | AA7: ='Holdings Pull Sheet'!P18 -> -6.46 | AC7: =Q7*U7 -> #REF!
B8: GNTX | C8: ='Holdings Pull Sheet'!C19 -> CISCO SYSTEMS INC | E8: ='Holdings Pull Sheet'!F19 -> 24.19 | F8: 18.48 | G8: 67.038 | H8: =E8*G8 -> 1621.6492 | I8: =F8*ROUNDDOWN(G8,0)+9.95 -> 1248.11 | J8: 1311.6534 | K8: 1274.3924 | M8: =H8-I8 -> 373.53922 | N8: =(H8/I8)-1 -> 0.29928389 | O8: =(H8/J8)-1 -> 0.23633978 | P8: =(H8/K8)-1 -> 0.27248816 | Q8: =('Holdings Pull Sheet'!F19/'Holdings Pull Sheet'!G19)-1 -> -0.019059205 | S8: Information Technology | U8: =H8/$H$27 -> #REF! | W8: ='Holdings Pull Sheet'!O19/1000000000 -> 123.34972 | X8: =IF(W8<2,"Small", IF(W8<10, "Mid", IF(W8>10, "Large"))) -> Large | Z8: ='Holdings Pull Sheet'!Q19 -> 16.27 | AA8: ='Holdings Pull Sheet'!P19 -> 1.49 | AC8: =Q8*U8 -> #REF!
B9: HCP | C9: ='Holdings Pull Sheet'!C20 -> DELTA AIR LINES Inc | E9: ='Holdings Pull Sheet'!F20 -> 33.71 | F9: 12.47 | G9: 65.665 | H9: =E9*G9 -> 2213.5672 | I9: =F9*ROUNDDOWN(G9,0)+9.95 -> 820.5 | J9: 647.68746 | K9: 757.11745 | M9: =H9-I9 -> 1393.0672 | N9: =(H9/I9)-1 -> 1.6978271 | O9: =(H9/J9)-1 -> 2.4176471 | P9: =(H9/K9)-1 -> 1.9236774 | Q9: =('Holdings Pull Sheet'!F21/'Holdings Pull Sheet'!G21)-1 -> -0.024036762 | S9: Consumer Discretionary | U9: =H9/$H$27 -> #REF! | W9: ='Holdings Pull Sheet'!O21/1000000000 -> 4.0367771 | X9: =IF(W9<2,"Small", IF(W9<10, "Mid", IF(W9>10, "Large"))) -> Mid | Z9: ='Holdings Pull Sheet'!Q21 -> 14.87 | AA9: ='Holdings Pull Sheet'!P21 -> 1.86 | AC9: =Q9*U9 -> #REF!
B10: HD | C10: ='Holdings Pull Sheet'!C21 -> GENTEX CORP | E10: ='Holdings Pull Sheet'!F21 -> 27.61 | F10: 16.4 | G10: 91.934 | H10: =E10*G10 -> 2538.2977 | I10: =F10*ROUNDDOWN(G10,0)+9.95 -> 1502.35 | J10: 1669.6919 | K10: 1608.845 | M10: =H10-I10 -> 1035.9477 | N10: =(H10/I10)-1 -> 0.68955153 | O10: =(H10/J10)-1 -> 0.52021921 | P10: =(H10/K10)-1 -> 0.57771429 | Q10: =('Holdings Pull Sheet'!F22/'Holdings Pull Sheet'!G22)-1 -> -0.010840684 | S10: Consumer Discretionary | U10: =H10/$H$27 -> #REF! | W10: ='Holdings Pull Sheet'!O22/1000000000 -> 125.26492 | X10: =IF(W10<2,"Small", IF(W10<10, "Mid", IF(W10>10, "Large"))) -> Large | Z10: ='Holdings Pull Sheet'!Q22 -> 22.26 | AA10: ='Holdings Pull Sheet'!P22 -> 4.18 | AC10: =Q10*U10 -> #REF!
B11: ITRI | C11: ='Holdings Pull Sheet'!C22 -> HOME DEPOT Inc | E11: ='Holdings Pull Sheet'!F22 -> 93.07 | F11: 29.37 | G11: 60.269 | H11: =E11*G11 -> 5609.2358 | I11: =F11*ROUNDDOWN(G11,0)+9.95 -> 1772.15 | J11: 2834.451 | K11: 2710.2969 | M11: =H11-I11 -> 3837.0858 | N11: =(H11/I11)-1 -> 2.165215 | O11: =(H11/J11)-1 -> 0.97894966 | P11: =(H11/K11)-1 -> 1.069602 | Q11: =('Holdings Pull Sheet'!#REF!/'Holdings Pull Sheet'!#REF!)-1 -> #REF! | S11: Financial | U11: =H11/$H$27 -> #REF! | W11: ='Holdings Pull Sheet'!#REF!/1000000000 -> #REF! | X11: =IF(W11<2,"Small", IF(W11<10, "Mid", IF(W11>10, "Large"))) -> #REF! | Z11: ='Holdings Pull Sheet'!#REF! -> #REF! | AA11: ='Holdings Pull Sheet'!#REF! -> #REF! | AC11: =Q11*U11 -> #REF!
B12: MDT | C12: ='Holdings Pull Sheet'!#REF! -> #REF! | E12: ='Holdings Pull Sheet'!#REF! -> #REF! | F12: 28.6 | G12: 58.765 | H12: =E12*G12 -> #REF! | I12: =F12*ROUNDDOWN(G12,0)+9.95 -> 1668.75 | J12: 3371.3144 | K12: 3775.0636 | M12: =H12-I12 -> #REF! | N12: =(H12/I12)-1 -> #REF! | O12: =(H12/J12)-1 -> #REF! | P12: =(H12/K12)-1 -> #REF! | Q12: =('Holdings Pull Sheet'!#REF!/'Holdings Pull Sheet'!#REF!)-1 -> #REF! | S12: Consumer Discretionary | U12: =H12/$H$27 -> #REF! | W12: ='Holdings Pull Sheet'!#REF!/1000000000 -> #REF! | X12: =IF(W12<2,"Small", IF(W12<10, "Mid", IF(W12>10, "Large"))) -> #REF! | Z12: ='Holdings Pull Sheet'!#REF! -> #REF! | AA12: ='Holdings Pull Sheet'!#REF! -> #REF! | AC12: =Q12*U12 -> #REF!
B13: PFE | C13: ='Holdings Pull Sheet'!#REF! -> #REF! | E13: ='Holdings Pull Sheet'!#REF! -> #REF! | F13: 62.69 | G13: 25 | H13: =E13*G13 -> #REF! | I13: =F13*ROUNDDOWN(G13,0)+9.95 -> 1577.2 | J13: 1078.5 | K13: 1082.75 | M13: =H13-I13 -> #REF! | N13: =(H13/I13)-1 -> #REF! | O13: =(H13/J13)-1 -> #REF! | P13: =(H13/K13)-1 -> #REF! | Q13: =('Holdings Pull Sheet'!#REF!/'Holdings Pull Sheet'!#REF!)-1 -> #REF! | S13: Information Technology | U13: =H13/$H$27 -> #REF! | W13: ='Holdings Pull Sheet'!#REF!/1000000000 -> #REF! | X13: =IF(W13<2,"Small", IF(W13<10, "Mid", IF(W13>10, "Large"))) -> #REF! | Z13: ='Holdings Pull Sheet'!#REF! -> #REF! | AA13: ='Holdings Pull Sheet'!#REF! -> #REF! | AC13: =Q13*U13 -> #REF!
B14: PGX | C14: ='Holdings Pull Sheet'!#REF! -> #REF! | E14: ='Holdings Pull Sheet'!#REF! -> #REF! | F14: 47.17 | G14: 28.038 | H14: =E14*G14 -> #REF! | I14: =F14*ROUNDDOWN(G14,0)+9.95 -> 1330.71 | J14: 1158.5436 | K14: 1994.9585 | M14: =H14-I14 -> #REF! | N14: =(H14/I14)-1 -> #REF! | O14: =(H14/J14)-1 -> #REF! | P14: =(H14/K14)-1 -> #REF! | Q14: =('Holdings Pull Sheet'!#REF!/'Holdings Pull Sheet'!#REF!)-1 -> #REF! | S14: Healthcare | U14: =H14/$H$27 -> #REF! | W14: ='Holdings Pull Sheet'!#REF!/1000000000 -> #REF! | X14: =IF(W14<2,"Small", IF(W14<10, "Mid", IF(W14>10, "Large"))) -> #REF! | Z14: ='Holdings Pull Sheet'!#REF! -> #REF! | AA14: ='Holdings Pull Sheet'!#REF! -> #REF! | AC14: =Q14*U14 -> #REF!
B15: PTR | C15: ='Holdings Pull Sheet'!#REF! -> #REF! | E15: ='Holdings Pull Sheet'!#REF! -> #REF! | F15: 19.49 | G15: 75 | H15: =E15*G15 -> #REF! | I15: =F15*ROUNDDOWN(G15,0)+9.95 -> 1471.7 | J15: 1471.7 | K15: 1471.7 | M15: =H15-I15 -> #REF! | N15: =(H15/I15)-1 -> #REF! | O15: =(H15/J15)-1 -> #REF! | P15: =(H15/K15)-1 -> #REF! | Q15: =('Holdings Pull Sheet'!#REF!/'Holdings Pull Sheet'!#REF!)-1 -> #REF! | S15: Energy | U15: =H15/$H$27 -> #REF! | W15: ='Holdings Pull Sheet'!#REF!/1000000000 -> #REF! | X15: =IF(W15<2,"Small", IF(W15<10, "Mid", IF(W15>10, "Large"))) -> #REF! | Z15: ='Holdings Pull Sheet'!#REF! -> #REF! | AA15: ='Holdings Pull Sheet'!#REF! -> #REF! | AC15: =Q15*U15 -> #REF!
B16: QCOM | C16: ='Holdings Pull Sheet'!#REF! -> #REF! | E16: ='Holdings Pull Sheet'!#REF! -> #REF! | F16: 33.19 | G16: 15.202 | H16: =E16*G16 -> #REF! | I16: =F16*ROUNDDOWN(G16,0)+9.95 -> 507.8 | J16: 1781.4913 | K16: 1971.8688 | M16: =H16-I16 -> #REF! | N16: =(H16/I16)-1 -> #REF! | O16: =(H16/J16)-1 -> #REF! | P16: =(H16/K16)-1 -> #REF! | Q16: =('Holdings Pull Sheet'!#REF!/'Holdings Pull Sheet'!#REF!)-1 -> #REF! | S16: Misc | U16: =H16/$H$27 -> #REF! | W16: ='Holdings Pull Sheet'!#REF!/1000000000 -> #REF! | X16: - | Z16: ='Holdings Pull Sheet'!#REF! -> #REF! | AA16: ='Holdings Pull Sheet'!#REF! -> #REF! | AC16: =Q16*U16 -> #REF!
B17: SINA | C17: ='Holdings Pull Sheet'!#REF! -> #REF! | E17: ='Holdings Pull Sheet'!#REF! -> #REF! | F17: 14.42 | G17: 133.505 | H17: =E17*G17 -> #REF! | I17: =F17*ROUNDDOWN(G17,0)+9.95 -> 1927.81 | J17: 1947.8667 | K17: 2830.9214 | M17: =H17-I17 -> #REF! | N17: =(H17/I17)-1 -> #REF! | O17: =(H17/J17)-1 -> #REF! | P17: =(H17/K17)-1 -> #REF! | Q17: =('Holdings Pull Sheet'!#REF!/'Holdings Pull Sheet'!#REF!)-1 -> #REF! | S17: Information Technology | U17: =H17/$H$27 -> #REF! | W17: ='Holdings Pull Sheet'!#REF!/1000000000 -> #REF! | X17: =IF(W17<2,"Small", IF(W17<10, "Mid", IF(W17>10, "Large"))) -> #REF! | Z17: ='Holdings Pull Sheet'!#REF! -> #REF! | AA17: ='Holdings Pull Sheet'!#REF! -> #REF! | AC17: =Q17*U17 -> #REF!
B18: TTEK | C18: ='Holdings Pull Sheet'!#REF! -> #REF! | E18: ='Holdings Pull Sheet'!#REF! -> #REF! | F18: 35.72 | G18: 44.687 | H18: =E18*G18 -> #REF! | I18: =F18*ROUNDDOWN(G18,0)+9.95 -> 1581.63 | J18: 2787.3414 | K18: 2256.3172 | M18: =H18-I18 -> #REF! | N18: =(H18/I18)-1 -> #REF! | O18: =(H18/J18)-1 -> #REF! | P18: =(H18/K18)-1 -> #REF! | Q18: =('Holdings Pull Sheet'!#REF!/'Holdings Pull Sheet'!#REF!)-1 -> #REF! | S18: Industrials | U18: =H18/$H$27 -> #REF! | W18: ='Holdings Pull Sheet'!#REF!/1000000000 -> #REF! | X18: =IF(W18<2,"Small", IF(W18<10, "Mid", IF(W18>10, "Large"))) -> #REF! | Z18: ='Holdings Pull Sheet'!#REF! -> #REF! | AA18: ='Holdings Pull Sheet'!#REF! -> #REF! | AC18: =Q18*U18 -> #REF!
B19: SYK | C19: ='Holdings Pull Sheet'!#REF! -> #REF! | E19: ='Holdings Pull Sheet'!#REF! -> #REF! | F19: 25.46 | G19: 60 | H19: =E19*G19 -> #REF! | I19: =F19*ROUNDDOWN(G19,0)+9.95 -> 1537.55 | J19: 1630.2 | K19: 1536.6 | M19: =H19-I19 -> #REF! | N19: =(H19/I19)-1 -> #REF! | O19: =(H19/J19)-1 -> #REF! | P19: =(H19/K19)-1 -> #REF! | Q19: =('Holdings Pull Sheet'!#REF!/'Holdings Pull Sheet'!#REF!)-1 -> #REF! | S19: Industrials | U19: =H19/$H$27 -> #REF! | W19: ='Holdings Pull Sheet'!#REF!/1000000000 -> #REF! | X19: =IF(W19<2,"Small", IF(W19<10, "Mid", IF(W19>10, "Large"))) -> #REF! | Z19: ='Holdings Pull Sheet'!#REF! -> #REF! | AA19: ='Holdings Pull Sheet'!#REF! -> #REF! | AC19: =Q19*U19 -> #REF!
B20: UPS | C20: ='Holdings Pull Sheet'!#REF! -> #REF! | E20: ='Holdings Pull Sheet'!#REF! -> #REF! | F20: 12.43 | G20: 150 | H20: =E20*G20 -> #REF! | I20: =F20*ROUNDDOWN(G20,0)+9.95 -> 1874.45 | J20: 1874.45 | K20: 1933.5 | M20: =H20-I20 -> #REF! | N20: =(H20/I20)-1 -> #REF! | O20: =(H20/J20)-1 -> #REF! | P20: =(H20/K20)-1 -> #REF! | Q20: =('Holdings Pull Sheet'!#REF!/'Holdings Pull Sheet'!#REF!)-1 -> #REF! | S20: Healthcare | U20: =H20/$H$27 -> #REF! | W20: ='Holdings Pull Sheet'!#REF!/1000000000 -> #REF! | X20: =IF(W20<2,"Small", IF(W20<10, "Mid", IF(W20>10, "Large"))) -> #REF! | Z20: ='Holdings Pull Sheet'!#REF! -> #REF! | AA20: ='Holdings Pull Sheet'!#REF! -> #REF! | AC20: =Q20*U20 -> #REF!
B21: WFC | C21: ='Holdings Pull Sheet'!#REF! -> #REF! | E21: ='Holdings Pull Sheet'!#REF! -> #REF! | F21: 16.65 | G21: 100 | H21: =E21*G21 -> #REF! | I21: =F21*ROUNDDOWN(G21,0)+9.95 -> 1674.95 | J21: 1665 | K21: 1919 | M21: =H21-I21 -> #REF! | N21: =(H21/I21)-1 -> #REF! | O21: =(H21/J21)-1 -> #REF! | P21: =(H21/K21)-1 -> #REF! | Q21: =('Holdings Pull Sheet'!#REF!/'Holdings Pull Sheet'!#REF!)-1 -> #REF! | S21: Consumer Staples | U21: =H21/$H$27 -> #REF! | W21: ='Holdings Pull Sheet'!#REF!/1000000000 -> #REF! | X21: =IF(W21<2,"Small", IF(W21<10, "Mid", IF(W21>10, "Large"))) -> #REF! | Z21: ='Holdings Pull Sheet'!#REF! -> #REF! | AA21: ='Holdings Pull Sheet'!#REF! -> #REF! | AC21: =Q21*U21 -> #REF!
B22: WMMVY | C22: ='Holdings Pull Sheet'!#REF! -> #REF! | E22: ='Holdings Pull Sheet'!#REF! -> #REF! | F22: 71.52 | G22: 46.992 | H22: =E22*G22 -> #REF! | I22: =F22*ROUNDDOWN(G22,0)+9.95 -> 3299.87 | J22: 3354.1307 | K22: 3456.7315 | M22: =H22-I22 -> #REF! | N22: =(H22/I22)-1 -> #REF! | O22: =(H22/J22)-1 -> #REF! | P22: =(H22/K22)-1 -> #REF! | Q22: =('Holdings Pull Sheet'!#REF!/'Holdings Pull Sheet'!#REF!)-1 -> #REF! | S22: Industrials | U22: =H22/$H$27 -> #REF! | W22: ='Holdings Pull Sheet'!#REF!/1000000000 -> #REF! | X22: =IF(W22<2,"Small", IF(W22<10, "Mid", IF(W22>10, "Large"))) -> #REF! | Z22: ='Holdings Pull Sheet'!#REF! -> #REF! | AA22: ='Holdings Pull Sheet'!#REF! -> #REF! | AC22: =Q22*U22 -> #REF!
C23: ='Holdings Pull Sheet'!#REF! -> #REF! | E23: ='Holdings Pull Sheet'!#REF! -> #REF! | F23: 25 | G23: 52.119 | H23: =E23*G23 -> #REF! | I23: =F23*ROUNDDOWN(G23,0)+9.95 -> 1309.95 | J23: 1435.9306 | K23: 1653.2147 | M23: =H23-I23 -> #REF! | N23: =(H23/I23)-1 -> #REF! | O23: =(H23/J23)-1 -> #REF! | P23: =(H23/K23)-1 -> #REF! | Q23: =('Holdings Pull Sheet'!#REF!/'Holdings Pull Sheet'!#REF!)-1 -> #REF! | S23: Consumer Discretionary | U23: =H23/$H$27 -> #REF! | W23: ='Holdings Pull Sheet'!#REF!/1000000000 -> #REF! | X23: =IF(W23<2,"Small", IF(W23<10, "Mid", IF(W23>10, "Large"))) -> #REF! | Z23: ='Holdings Pull Sheet'!#REF! -> #REF! | AA23: ='Holdings Pull Sheet'!#REF! -> #REF! | AC23: =Q23*U23 -> #REF!
B24: CSCO | C24: ='Holdings Pull Sheet'!#REF! -> #REF! | E24: ='Holdings Pull Sheet'!#REF! -> #REF! | F24: 23.42 | G24: 51.373 | H24: =E24*G24 -> #REF! | I24: =F24*ROUNDDOWN(G24,0)+9.95 -> 1204.37 | J24: 1778.2684 | K24: 1703.5287 | M24: =H24-I24 -> #REF! | N24: =(H24/I24)-1 -> #REF! | O24: =(H24/J24)-1 -> #REF! | P24: =(H24/K24)-1 -> #REF! | Q24: =('Holdings Pull Sheet'!#REF!/'Holdings Pull Sheet'!#REF!)-1 -> #REF! | S24: Financial | U24: =H24/$H$27 -> #REF! | W24: ='Holdings Pull Sheet'!#REF!/1000000000 -> #REF! | X24: =IF(W24<2,"Small", IF(W24<10, "Mid", IF(W24>10, "Large"))) -> #REF! | Z24: ='Holdings Pull Sheet'!#REF! -> #REF! | AA24: ='Holdings Pull Sheet'!#REF! -> #REF! | AC24: =Q24*U24 -> #REF!
C25: ='Holdings Pull Sheet'!#REF! -> #REF! | E25: ='Holdings Pull Sheet'!#REF! -> #REF! | F25: 10.84 | G25: 103.821 | H25: =E25*G25 -> #REF! | I25: =F25*ROUNDDOWN(G25,0)+9.95 -> 1126.47 | J25: 792.27646 | K25: 704.94459 | M25: =H25-I25 -> #REF! | N25: =(H25/I25)-1 -> #REF! | O25: =(H25/J25)-1 -> #REF! | P25: =(H25/K25)-1 -> #REF! | Q25: =('Holdings Pull Sheet'!#REF!/'Holdings Pull Sheet'!#REF!)-1 -> #REF! | S25: Information Technology | U25: =H25/$H$27 -> #REF! | W25: ='Holdings Pull Sheet'!#REF!/1000000000 -> #REF! | X25: =IF(W25<2,"Small", IF(W25<10, "Mid", IF(W25>10, "Large"))) -> #REF! | Z25: ='Holdings Pull Sheet'!#REF! -> #REF! | AA25: ='Holdings Pull Sheet'!#REF! -> #REF! | AC25: =Q25*U25 -> #REF!
C27: Total | H27: =SUM(H4:H25) -> #REF! | I27: =SUM(I4:I25) -> 34299.51 | J27: 40381.87 | K27: =SUM(K4:K25) -> 41863.402 | M27: =H27-I27 -> #REF! | N27: =(H27/I27)-1 -> #REF! | O27: =(H27/J27)-1 -> #REF! | P27: =(H27/K27)-1 -> #REF! | Q27: =AC27 -> #REF! | U27: =SUM(U4:U25) -> #REF! | Z27: =(Z5*$U$5)+(Z7*$U$7)+(Z8*$U$8)+(Z9*$U$9)+(Z10*$U$10)+(Z11*$U$11)+(Z12*$U$12)+(Z13*$U$13)+(Z14*$U$14)+(Z15*$U$15)+(Z16*$U$16)+(Z17*$U$17)+(Z18*$U$18)+(Z19*$U$19)+(Z20*$U$20)+(Z21*$U$21)+(Z22*$U$22)+(Z23*$U$23)+(Z24*$U$24) -> #REF! | AA27: =(AA5*$U$5)+(AA7*$U$7)+(AA24*$U$24)+(AA8*$U$8)+(AA9*$U$9)+(AA10*$U$10)+(AA11*$U$11)+(AA12*$U$12)+(AA13*$U$13)+(AA14*$U$14)+(AA15*$U$15)+(AA16*$U$16)+(AA17*$AA$17)+(AA19*$AA$19)+(AA18*$U$18)+(AA20*$U$20)+(AA21*$U$21)+(AA22*$U$22)+(AA23*$U$23)+(AA25*$U$25) -> #REF! | AC27: =SUM(AC4:AC25) -> #REF!
E29: Commission Fees | X29: EPS Excluding BRK.B | AA29: =(AA7*$U$7)+(AA24*$U$24)+(AA8*$U$8)+(AA9*$U$9)+(AA10*$U$10)+(AA11*$U$11)+(AA12*$U$12)+(AA13*$U$13)+(AA14*$U$14)+(AA15*$U$15)+(AA16*$U$16)+(AA17*$U$17)+(AA19*$U$19)+(AA18*$U$18)+(AA20*$U$20)+(AA21*$U$21)+(AA22*$U$22)+(AA23*$U$23)+(AA25*$U$25) -> #REF!
X60: Portfolio Performance & Details ©
X61: Created by Kristopher "Boomer" Hoppough
X62: 616.902.0398
X63: gnar99@hotmail.com
X64: hoppougk@student.gvsu.edu

Sheet Long-Term Chart_Old

Sheet Sector Weights
A4: GICS Sector | B4: % of S&P 500 (by market capitalization %) | C4: Lower Range | D4: Upper Range | E4: Average Range
A5: Consumer Discretionary | B5: 10.1 | C5: 5.05 | D5: 15.15 | E5: 0.101
A6: Consumer Staples | B6: 11.5 | C6: 5.75 | D6: 17.25 | E6: 0.115
A7: Energy | B7: 10.7 | C7: 5.35 | D7: 16.05 | E7: 0.037
A8: Financial | B8: 16.3 | C8: 8.15 | D8: 24.45 | E8: 0.163
A9: Healthcare | B9: 12.1 | C9: 6.05 | D9: 18.15 | E9: 0.121
A10: Industrials | B10: 10.3 | C10: 5.15 | D10: 15.45 | E10: 0.103
A11: Information Technology | B11: 18.8 | C11: 9.4 | D11: 28.2 | E11: 0.188
A12: Materials | B12: 3.4 | C12: 1.7 | D12: 5.1 | E12: 0.034
A13: Telecommunications | B13: 3 | C13: 1.5 | D13: 4.5 | E13: 0.03
A14: Utilities | B14: 3.7 | C14: 1.85 | D14: 5.55 | E14: 0.037
B15: =SUM(B5:B14) -> 99.9 | C15: =SUM(C5:C14) -> 49.95 | D15: =SUM(D5:D14) -> 149.85 | E15: =SUM(E5:E14) -> 0.929

Sheet GICS Sector Allocation
