Workbook

Sheet Quarterly ProForma Results
A1: Rent-A-Center, Inc.
A2: ProForma Quarterly Financials (10Q Format)
A3: (dollars in thousands, except per share data)
A4: Updated: September 30, 2012
B6: Quarter Ended | J6: FYE | L6: Quarter Ended | T6: FYE | V6: Quarter Ended | AD6: FYE | AF6: Quarter Ended | AN6: FYE | AP6: Quarter Ended | AX6: FYE | AZ6: Quarter Ended | BH6: FYE | BJ6: Quarter Ended | BR6: FYE | BT6: Quarter Ended | CB6: FYE | CD6: Quarter Ended | CL6: FYE | CN6: Quarter Ended | CV6: FYE | CX6: Quarter Ended | DF6: FYE | DH6: Quarter Ended | DP6: FYE | DR6: Quarter Ended | DZ6: FYE | EB6: Quarter Ended | EJ6: FYE
B7: 36250 | D7: 36341 | F7: 36433 | H7: 36525 | J7: 1999 | L7: 36616 | N7: 36707 | P7: 36799 | R7: 36891 | T7: 2000 | V7: 36981 | X7: 37072 | Z7: 37164 | AB7: 37256 | AD7: 2001 | AF7: 37346 | AH7: 37437 | AJ7: 37529 | AL7: 37621 | AN7: 2002 | AP7: 37711 | AR7: 37802 | AT7: 37894 | AV7: 37986 | AX7: 2003 | AZ7: 38077 | BB7: 38168 | BD7: 38260 | BF7: 38352 | BH7: 2004 | BJ7: 38442 | BL7: 38533 | BN7: 38625 | BP7: 38717 | BR7: 2005 | BT7: 38807 | BV7: 38898 | BX7: 38990 | BZ7: 39082 | CB7: 2006 | CD7: 39172 | CF7: 39263 | CH7: 39355 | CJ7: 39447 | CL7: 2007 | CN7: =EOMONTH(CJ7,3) -> 39538 | CP7: =EOMONTH(CN7,3) -> 39629 | CR7: =EOMONTH(CP7,3) -> 39721 | CT7: =EOMONTH(CR7,3) -> 39813 | CV7: 2008 | CX7: =EOMONTH(CT7,3) -> 39903 | CZ7: =EOMONTH(CX7,3) -> 39994 | DB7: =EOMONTH(CZ7,3) -> 40086 | DD7: =EOMONTH(DB7,3) -> 40178 | DF7: =YEAR(DD7) -> 2009 | DH7: =EOMONTH(DD7,3) -> 40268 | DJ7: =EOMONTH(DH7,3) -> 40359 | DL7: =EOMONTH(DJ7,3) -> 40451 | DN7: =EOMONTH(DL7,3) -> 40543 | DP7: =YEAR(DN7) -> 2010 | DR7: =EOMONTH(DN7,3) -> 40633 | DT7: =EOMONTH(DR7,3) -> 40724 | DV7: =EOMONTH(DT7,3) -> 40816 | DX7: =EOMONTH(DV7,3) -> 40908 | DZ7: =YEAR(DX7) -> 2011 | EB7: =EOMONTH(DX7,3) -> 40999 | ED7: =EOMONTH(EB7,3) -> 41090 | EF7: =EOMONTH(ED7,3) -> 41182 | EH7: =EOMONTH(EF7,3) -> 41274 | EJ7: =YEAR(EH7) -> 2012
A8: Store Revenue:
A9: Rentals & Fees | B9: 301707 | D9: 316159 | F9: 318119.1 | H9: 334899.6 | J9: =B9+D9+F9+H9 -> 1270884.7 | L9: 350320.39 | N9: 360227 | P9: 372402 | R9: 376715 | T9: =L9+N9+P9+R9-0.4 -> 1459664 | V9: 393122.91 | X9: 409023.4 | Z9: 411241 | AB9: 437464 | AD9: =V9+X9+Z9+AB9-0.5 -> 1650850.8 | AF9: 443705 | AH9: 456149 | AJ9: 456208 | AL9: 472472 | AN9: =AF9+AH9+AJ9+AL9 -> 1828534 | AP9: 493419 | AR9: 504352 | AT9: 497881 | AV9: 503300 | AX9: =AP9+AR9+AT9+AV9 -> 1998952 | AZ9: 504290 | BB9: 520593 | BD9: 516576 | BF9: 530407 | BH9: =AZ9+BB9+BD9+BF9 -> 2071866 | BJ9: 518622 | BL9: 526639 | BN9: 516433 | BP9: 523063 | BR9: =BJ9+BL9+BN9+BP9 -> 2084757 | BT9: 520383 | BV9: 527076 | BX9: 532260 | BZ9: 594520 | CB9: =BT9+BV9+BX9+BZ9 -> 2174239 | CD9: 660113 | CF9: 662096 | CH9: 631132 | CJ9: 640720 | CL9: =CD9+CF9+CH9+CJ9 -> 2594061 | CN9: 640686 | CP9: 634618 | CR9: 621290 | CT9: 608674 | CV9: =CN9+CP9+CR9+CT9 -> 2505268 | CX9: 597607 | CZ9: 589468 | DB9: 576124 | DD9: 583650 | DF9: =CX9+CZ9+DB9+DD9 -> 2346849 | DH9: 583848 | DJ9: 586523 | DL9: 576019 | DN9: 589106 | DP9: =DH9+DJ9+DL9+DN9 -> 2335496 | DR9: 610428 | DT9: 617796 | DV9: 622474 | DX9: 646165 | DZ9: =DR9+DT9+DV9+DX9 -> 2496863 | EB9: 677981 | ED9: 658987 | EF9: 652059 | EJ9: =EB9+ED9+EF9+EH9 -> 1989027
A10: Merchandise Sales | B10: 31886 | D10: 20293 | F10: 18662.051 | H10: 17675.283 | J10: =B10+D10+F10+H10 -> 88516.334 | L10: 27339.014 | N10: 17680 | P10: 18887 | R10: 17260 | T10: =L10+N10+P10+R10 -> 81166.014 | V10: 30759.44 | X10: 20111.783 | Z10: 21569 | AB10: 22293 | AD10: =V10+X10+Z10+AB10 -> 94733.223 | AF10: 39605 | AH10: 23994 | AJ10: 24710 | AL10: 27169 | AN10: =AF10+AH10+AJ10+AL10 -> 115478 | AP10: 52664 | AR10: 32528 | AT10: 34453 | AV10: 33339 | AX10: =AP10+AR10+AT10+AV10 -> 152984 | AZ10: 59423 | BB10: 34599 | BD10: 36265 | BF10: 36307 | BH10: =AZ10+BB10+BD10+BF10 -> 166594 | BJ10: 62770 | BL10: 37498 | BN10: 39212 | BP10: 37812 | BR10: =BJ10+BL10+BN10+BP10 -> 177292 | BT10: 64163 | BV10: 38428 | BX10: 36343 | BZ10: 37020 | CB10: =BT10+BV10+BX10+BZ10 -> 175954 | CD10: 68337 | CF10: 39584 | CH10: 53574 | CJ10: 47494 | CL10: =CD10+CF10+CH10+CJ10 -> 208989 | CN10: 85339 | CP10: 55703 | CR10: 57062 | CT10: 58627 | CV10: =CN10+CP10+CR10+CT10 -> 256731 | CX10: 95782 | CZ10: 56959 | DB10: 59085 | DD10: 49805 | DF10: =CX10+CZ10+DB10+DD10 -> 261631 | DH10: 89397 | DJ10: 43031 | DL10: 44352 | DN10: 43549 | DP10: =DH10+DJ10+DL10+DN10 -> 220329 | DR10: 99266 | DT10: 50973 | DV10: 52802 | DX10: 56755 | DZ10: =DR10+DT10+DV10+DX10 -> 259796 | EB10: 122859 | ED10: 60622 | EF10: 58854 | EJ10: =EB10+ED10+EF10+EH10 -> 242335
A11: Installment Sales | J11: =B11+D11+F11+H11 -> 0 | T11: =L11+N11+P11+R11 -> 0 | AD11: =V11+X11+Z11+AB11 -> 0 | AL11: 6137 | AN11: =AF11+AH11+AJ11+AL11 -> 6137 | AP11: 6045 | AR11: 4745 | AT11: 4633 | AV11: 6780 | AX11: =AP11+AR11+AT11+AV11 -> 22203 | AZ11: 6698 | BB11: 5801 | BD11: 5469 | BF11: 6336 | BH11: =AZ11+BB11+BD11+BF11 -> 24304 | BJ11: 6584 | BL11: 6618 | BN11: 6372 | BP11: 6566 | BR11: =BJ11+BL11+BN11+BP11 -> 26140 | BT11: 5851 | BV11: 5728 | BX11: 6798 | BZ11: 8500 | CB11: =BT11+BV11+BX11+BZ11 -> 26877 | CD11: 8410 | CF11: 7646 | CH11: 8593 | CJ11: 9927 | CL11: =CD11+CF11+CH11+CJ11 -> 34576 | CN11: 9885 | CP11: 9246 | CR11: 10554 | CT11: 11508 | CV11: =CN11+CP11+CR11+CT11 -> 41193 | CX11: 12426 | CZ11: 12290 | DB11: 12983 | DD11: 15336 | DF11: =CX11+CZ11+DB11+DD11 -> 53035 | DH11: 15137 | DJ11: 14503 | DL11: 15599 | DN11: 18594 | DP11: =DH11+DJ11+DL11+DN11 -> 63833 | DR11: 16687 | DT11: 16571 | DV11: 16348 | DX11: 19011 | DZ11: =DR11+DT11+DV11+DX11 -> 68617 | EB11: 17495 | ED11: 16170 | EF11: 15560 | EJ11: =EB11+ED11+EF11+EH11 -> 49225
A12: Other | B12: 858 | D12: 462 | F12: 404.188 | H12: 452.932 | J12: =B12+D12+F12+H12 -> 2177.12 | L12: 492.11491 | N12: 502 | P12: 922 | R12: 1102 | T12: =L12+N12+P12+R12 -> 3018.1149 | V12: 1329.9978 | X12: 908.14399 | Z12: 640 | AB12: 598 | AD12: =V12+X12+Z12+AB12 -> 3476.1418 | AF12: 614 | AH12: 567 | AJ12: 561 | AL12: 847 | AN12: =AF12+AH12+AJ12+AL12 -> 2589 | AP12: 715 | AR12: 812 | AT12: 697 | AV12: 859 | AX12: =AP12+AR12+AT12+AV12 -> 3083 | AZ12: 1080 | BB12: 967 | BD12: 919 | BF12: 602 | BH12: =AZ12+BB12+BD12+BF12 -> 3568 | BJ12: 1078 | BL12: 997 | BN12: 2938 | BP12: 2889 | BR12: =BJ12+BL12+BN12+BP12 -> 7902 | BT12: 3286 | BV12: 3254 | BX12: 3723 | BZ12: 5344 | CB12: =BT12+BV12+BX12+BZ12 -> 15607 | CD12: 7176 | CF12: 6570 | CH12: 3940 | CJ12: 7796 | CL12: =CD12+CF12+CH12+CJ12 -> 25482 | CN12: 9619 | CP12: 10589 | CR12: 10704 | CT12: 11847 | CV12: =CN12+CP12+CR12+CT12 -> 42759 | CX12: 13139 | CZ12: 13443 | DB12: 15236 | DD12: 15783 | DF12: =CX12+CZ12+DB12+DD12 -> 57601 | DH12: 20336 | DJ12: 19523 | DL12: 20413 | DN12: 16270 | DP12: =DH12+DJ12+DL12+DN12 -> 76542 | DR12: 5339 | DT12: 4143 | DV12: 4147 | DX12: 4296 | DZ12: =DR12+DT12+DV12+DX12 -> 17925 | EB12: 4932 | ED12: 4537 | EF12: 2811 | EJ12: =EB12+ED12+EF12+EH12 -> 12280
A13: Total Store Revenue | B13: =SUM(B9:B12) -> 334451 | D13: =SUM(D9:D12) -> 336914 | F13: =SUM(F9:F12) -> 337185.34 | H13: =SUM(H9:H12) -> 353027.81 | J13: =SUM(J9:J12) -> 1361578.2 | L13: =SUM(L9:L12) -> 378151.52 | N13: =SUM(N9:N12) -> 378409 | P13: =SUM(P9:P12) -> 392211 | R13: =SUM(R9:R12) -> 395077 | T13: =SUM(T9:T12) -> 1543848.1 | V13: =SUM(V9:V12) -> 425212.35 | X13: =SUM(X9:X12) -> 430043.33 | Z13: =SUM(Z9:Z12) -> 433450 | AB13: =SUM(AB9:AB12) -> 460355 | AD13: =SUM(AD9:AD12) -> 1749060.2 | AF13: =SUM(AF9:AF12) -> 483924 | AH13: =SUM(AH9:AH12) -> 480710 | AJ13: =SUM(AJ9:AJ12) -> 481479 | AL13: =SUM(AL9:AL12) -> 506625 | AN13: =SUM(AN9:AN12) -> 1952738 | AP13: =SUM(AP9:AP12) -> 552843 | AR13: =SUM(AR9:AR12) -> 542437 | AT13: =SUM(AT9:AT12) -> 537664 | AV13: =SUM(AV9:AV12) -> 544278 | AX13: =SUM(AX9:AX12) -> 2177222 | AZ13: =SUM(AZ9:AZ12) -> 571491 | BB13: =SUM(BB9:BB12) -> 561960 | BD13: =SUM(BD9:BD12) -> 559229 | BF13: =SUM(BF9:BF12) -> 573652 | BH13: =SUM(BH9:BH12) -> 2266332 | BJ13: =SUM(BJ9:BJ12) -> 589054 | BL13: =SUM(BL9:BL12) -> 571752 | BN13: =SUM(BN9:BN12) -> 564955 | BP13: =SUM(BP9:BP12) -> 570330 | BR13: =SUM(BR9:BR12) -> 2296091 | BT13: =SUM(BT9:BT12) -> 593683 | BV13: =SUM(BV9:BV12) -> 574486 | BX13: =SUM(BX9:BX12) -> 579124 | BZ13: =SUM(BZ9:BZ12) -> 645384 | CB13: =SUM(CB9:CB12) -> 2392677 | CD13: =SUM(CD9:CD12) -> 744036 | CF13: =SUM(CF9:CF12) -> 715896 | CH13: =SUM(CH9:CH12) -> 697239 | CJ13: =SUM(CJ9:CJ12) -> 705937 | CL13: =SUM(CL9:CL12) -> 2863108 | CN13: =SUM(CN9:CN12) -> 745529 | CP13: =SUM(CP9:CP12) -> 710156 | CR13: =SUM(CR9:CR12) -> 699610 | CT13: =SUM(CT9:CT12) -> 690656 | CV13: =SUM(CV9:CV12) -> 2845951 | CX13: =SUM(CX9:CX12) -> 718954 | CZ13: =SUM(CZ9:CZ12) -> 672160 | DB13: =SUM(DB9:DB12) -> 663428 | DD13: =SUM(DD9:DD12) -> 664574 | DF13: =SUM(DF9:DF12) -> 2719116 | DH13: =SUM(DH9:DH12) -> 708718 | DJ13: =SUM(DJ9:DJ12) -> 663580 | DL13: =SUM(DL9:DL12) -> 656383 | DN13: =SUM(DN9:DN12) -> 667519 | DP13: =SUM(DP9:DP12) -> 2696200 | DR13: =SUM(DR9:DR12) -> 731720 | DT13: =SUM(DT9:DT12) -> 689483 | DV13: =SUM(DV9:DV12) -> 695771 | DX13: =SUM(DX9:DX12) -> 726227 | DZ13: =SUM(DZ9:DZ12) -> 2843201 | EB13: =SUM(EB9:EB12) -> 823267 | ED13: =SUM(ED9:ED12) -> 740316 | EF13: =SUM(EF9:EF12) -> 729284 | EH13: =SUM(EH9:EH12) -> 0 | EJ13: =SUM(EJ9:EJ12) -> 2292867
A15: Franchise Revenue:
A16: Merchandise Sales | B16: 8821 | D16: 13000 | F16: 11678.597 | H16: 16195.564 | J16: =B16+D16+F16+H16+0.5 -> 49695.661 | L16: 12890.63 | N16: 12321 | P16: 11143 | R16: 15414 | T16: =L16+N16+P16+R16 -> 51768.63 | V16: 13026.887 | X16: 11231.709 | Z16: 12087 | AB16: 17238 | AD16: =V16+X16+Z16+AB16 -> 53583.596 | AF16: 13253 | AH16: 12486 | AJ16: 11566 | AL16: 14209 | AN16: =AF16+AH16+AJ16+AL16 -> 51514 | AP16: 12072 | AR16: 9261 | AT16: 10754 | AV16: 12970 | AX16: =AP16+AR16+AT16+AV16 -> 45057 | AZ16: 12464 | BB16: 9668 | BD16: 8967 | BF16: 10299 | BH16: =AZ16+BB16+BD16+BF16 -> 41398 | BJ16: 11344 | BL16: 7443 | BN16: 7245 | BP16: 11762 | BR16: =BJ16+BL16+BN16+BP16 -> 37794 | BT16: 12081 | BV16: 7892 | BX16: 6779 | BZ16: 9625 | CB16: =BT16+BV16+BX16+BZ16 -> 36377 | CD16: 9925 | CF16: 6955 | CH16: 7376 | CJ16: 9973 | CL16: =CD16+CF16+CH16+CJ16 -> 34229 | CN16: 9767 | CP16: 7650 | CR16: 7969 | CT16: 7897 | CV16: =CN16+CP16+CR16+CT16 -> 33283 | CX16: 7958 | CZ16: 6251 | DB16: 6663 | DD16: 7193 | DF16: =CX16+CZ16+DB16+DD16 -> 28065 | DH16: 8425 | DJ16: 6755 | DL16: 6975 | DN16: 8420 | DP16: =DH16+DJ16+DL16+DN16 -> 30575 | DR16: 9146 | DT16: 7525 | DV16: 7250 | DX16: 10051 | DZ16: =DR16+DT16+DV16+DX16 -> 33972 | EB16: 10613 | ED16: 8022 | EF16: 8697 | EJ16: =EB16+ED16+EF16+EH16 -> 27332
A17: Royalty Income and Fees | B17: 1425 | D17: 1507 | F17: 1555.673 | H17: 1405.327 | J17: =B17+D17+F17+H17 -> 5893 | L17: 1484.0533 | N17: 1515 | P17: 1614 | R17: 1384 | T17: =L17+N17+P17+R17 -> 5997.0533 | V17: 1463.112 | X17: 1483.718 | Z17: 1537 | AB17: 1400 | AD17: =V17+X17+Z17+AB17 -> 5883.83 | AF17: 1433 | AH17: 1464 | AJ17: 1516 | AL17: 1379 | AN17: =AF17+AH17+AJ17+AL17 -> 5792 | AP17: 1491 | AR17: 1562 | AT17: 1407 | AV17: 1411 | AX17: =AP17+AR17+AT17+AV17 -> 5871 | AZ17: 1425 | BB17: 1357 | BD17: 1411 | BF17: 1332 | BH17: =AZ17+BB17+BD17+BF17 -> 5525 | BJ17: 1411 | BL17: 1383 | BN17: 1307 | BP17: 1121 | BR17: =BJ17+BL17+BN17+BP17 -> 5222 | BT17: 1211 | BV17: 1245 | BX17: 1281 | BZ17: 1117 | CB17: =BT17+BV17+BX17+BZ17 -> 4854 | CD17: 1338 | CF17: 1307 | CH17: =5086-3900 -> 1186 | CI17: (2) | CJ17: 1053 | CL17: =CD17+CF17+CH17+CJ17 -> 4884 | CM17: (2) | CN17: 1340 | CP17: 1225 | CR17: 1176 | CT17: 1197 | CV17: =CN17+CP17+CR17+CT17 -> 4938 | CX17: 1271 | CZ17: 1198 | DB17: 1160 | DD17: 1146 | DF17: =CX17+CZ17+DB17+DD17 -> 4775 | DH17: 1276 | DJ17: 1208 | DL17: 1222 | DN17: 1151 | DP17: =DH17+DJ17+DL17+DN17 -> 4857 | DR17: 1312 | DT17: 1245 | DV17: 1250 | DX17: 1204 | DZ17: =DR17+DT17+DV17+DX17 -> 5011 | EB17: 1374 | ED17: 1360 | EF17: 1333 | EJ17: =EB17+ED17+EF17+EH17 -> 4067
A19: Total Revenue | B19: =B13+B16+B17 -> 344697 | D19: =D13+D16+D17 -> 351421 | F19: =F13+F16+F17 -> 350419.61 | H19: =H13+H16+H17 -> 370628.7 | J19: =J13+J16+J17 -> 1417166.8 | L19: =L13+L16+L17 -> 392526.21 | N19: =N13+N16+N17 -> 392245 | P19: =P13+P16+P17 -> 404968 | R19: =R13+R16+R17 -> 411875 | T19: =T13+T16+T17 -> 1601613.8 | V19: =V13+V16+V17 -> 439702.34 | X19: =X13+X16+X17 -> 442758.75 | Z19: =Z13+Z16+Z17 -> 447074 | AB19: =AB13+AB16+AB17 -> 478993 | AD19: =AD13+AD16+AD17 -> 1808527.6 | AF19: =AF13+AF16+AF17 -> 498610 | AH19: =AH13+AH16+AH17 -> 494660 | AJ19: =AJ13+AJ16+AJ17 -> 494561 | AL19: =AL13+AL16+AL17 -> 522213 | AN19: =AN13+AN16+AN17 -> 2010044 | AP19: =AP13+AP16+AP17 -> 566406 | AR19: =AR13+AR16+AR17 -> 553260 | AT19: =AT13+AT16+AT17 -> 549825 | AV19: =AV13+AV16+AV17 -> 558659 | AX19: =AX13+AX16+AX17 -> 2228150 | AZ19: =AZ13+AZ16+AZ17 -> 585380 | BB19: =BB13+BB16+BB17 -> 572985 | BD19: =BD13+BD16+BD17 -> 569607 | BF19: =BF13+BF16+BF17 -> 585283 | BH19: =BH13+BH16+BH17 -> 2313255 | BJ19: =BJ13+BJ16+BJ17 -> 601809 | BL19: =BL13+BL16+BL17 -> 580578 | BN19: =BN13+BN16+BN17 -> 573507 | BP19: =BP13+BP16+BP17 -> 583213 | BR19: =BR13+BR16+BR17 -> 2339107 | BT19: =BT13+BT16+BT17 -> 606975 | BV19: =BV13+BV16+BV17 -> 583623 | BX19: =BX13+BX16+BX17 -> 587184 | BZ19: =BZ13+BZ16+BZ17 -> 656126 | CB19: =CB13+CB16+CB17 -> 2433908 | CD19: =CD13+CD16+CD17 -> 755299 | CF19: =CF13+CF16+CF17 -> 724158 | CH19: =CH13+CH16+CH17 -> 705801 | CJ19: =CJ13+CJ16+CJ17 -> 716963 | CL19: =CL13+CL16+CL17 -> 2902221 | CN19: =CN13+CN16+CN17 -> 756636 | CP19: =CP13+CP16+CP17 -> 719031 | CR19: =CR13+CR16+CR17 -> 708755 | CT19: =CT13+CT16+CT17 -> 699750 | CV19: =CV13+CV16+CV17 -> 2884172 | CX19: =CX13+CX16+CX17 -> 728183 | CZ19: =CZ13+CZ16+CZ17 -> 679609 | DB19: =DB13+DB16+DB17 -> 671251 | DD19: =DD13+DD16+DD17 -> 672913 | DF19: =DF13+DF16+DF17 -> 2751956 | DH19: =DH13+DH16+DH17 -> 718419 | DJ19: =DJ13+DJ16+DJ17 -> 671543 | DL19: =DL13+DL16+DL17 -> 664580 | DN19: =DN13+DN16+DN17 -> 677090 | DP19: =DP13+DP16+DP17 -> 2731632 | DR19: =DR13+DR16+DR17 -> 742178 | DT19: =DT13+DT16+DT17 -> 698253 | DV19: =DV13+DV16+DV17 -> 704271 | DX19: =DX13+DX16+DX17 -> 737482 | DZ19: =DZ13+DZ16+DZ17 -> 2882184 | EB19: =EB13+EB16+EB17 -> 835254 | ED19: =ED13+ED16+ED17 -> 749698 | EF19: =EF13+EF16+EF17 -> 739314 | EH19: =EH13+EH16+EH17 -> 0 | EJ19: =EJ13+EJ16+EJ17 -> 2324266
A21: Operating Expenses:
A22: Direct Store Expenses
A23: Cost of Rental and Fees | B23: 64466 | D23: 66438 | F23: 65910.653 | H23: 68671.347 | J23: =B23+D23+F23+H23 -> 265486 | L23: 71728.338 | N23: 73803 | P23: 77014 | R23: 76753 | T23: =L23+N23+P23+R23-0.4 -> 299297.94 | V23: 80812.117 | X23: 84276.018 | Z23: 86198 | AB23: 91911 | AD23: =V23+X23+Z23+AB23 -> 343197.14 | AF23: 92223 | AH23: 94354 | AJ23: 95508 | AL23: 101315 | AN23: =AF23+AH23+AJ23+AL23 -> 383400 | AP23: 106660 | AR23: 109341 | AT23: 107777 | AV23: 108918 | AX23: =AP23+AR23+AT23+AV23 -> 432696 | AZ23: 108543 | BB23: 112743 | BD23: 112582 | BF23: 116167 | BH23: =AZ23+BB23+BD23+BF23 -> 450035 | BJ23: 112468 | BL23: 114068 | BN23: 112174 | BP23: 113873 | BR23: =BJ23+BL23+BN23+BP23 -> 452583 | BT23: 112767 | BV23: 114733 | BX23: 117018 | BZ23: 131944 | CB23: =BT23+BV23+BX23+BZ23 -> 476462 | CD23: 143069 | CF23: 145927 | CH23: 140219 | CJ23: 144798 | CL23: =CD23+CF23+CH23+CJ23 -> 574013 | CN23: 146162 | CP23: 145511 | CR23: 142314 | CT23: 138913 | CV23: =CN23+CP23+CR23+CT23 -> 572900 | CX23: 135139 | CZ23: 132956 | DB23: 130183 | DD23: 131740 | DF23: =CX23+CZ23+DB23+DD23 -> 530018 | DH23: 130114 | DJ23: 129818 | DL23: 127573 | DN23: 131777 | DP23: =DH23+DJ23+DL23+DN23 -> 519282 | DR23: 135649 | DT23: 139295 | DV23: 142796 | DX23: 152753 | DZ23: =DR23+DT23+DV23+DX23 -> 570493 | EB23: 163359 | ED23: 159790 | EF23: 158805 | EJ23: =EB23+ED23+EF23+EH23 -> 481954
A24: Cost of Merchandise Sold | B24: 25916 | D24: 17422 | F24: 15664.141 | H24: 15025.125 | J24: =B24+D24+F24+H24 -> 74027.266 | L24: 22830.329 | N24: 14566 | P24: 14348 | R24: 13588 | T24: =L24+N24+P24+R24 -> 65332.329 | V24: 21555.25 | X24: 15444.749 | Z24: 17176 | AB24: 18363 | AD24: =V24+X24+Z24+AB24 -> 72538.999 | AF24: 26982 | AH24: 17497 | AJ24: 18471 | AL24: 21678 | AN24: =AF24+AH24+AJ24+AL24 -> 84628 | AP24: 36548 | AR24: 24235 | AT24: 25901 | AV24: 25599 | AX24: =AP24+AR24+AT24+AV24 -> 112283 | AZ24: 39383 | BB24: 24720 | BD24: 26978 | BF24: 28017 | BH24: =AZ24+BB24+BD24+BF24 -> 119098 | BJ24: 42067 | BL24: 28225 | BN24: 30314 | BP24: 29018 | BR24: =BJ24+BL24+BN24+BP24 -> 129624 | BT24: 44130 | BV24: 28403 | BX24: 28422 | BZ24: 30473 | CB24: =BT24+BV24+BX24+BZ24 -> 131428 | CD24: 46030 | CF24: 29948 | CH24: 41065 | CJ24: 39460 | CL24: =CD24+CF24+CH24+CJ24 -> 156503 | CN24: 63325 | CP24: 45167 | CR24: 44714 | CT24: 41389 | CV24: =CN24+CP24+CR24+CT24 -> 194595 | CX24: 65767 | CZ24: 41997 | DB24: 42940 | DD24: 37729 | DF24: =CX24+CZ24+DB24+DD24 -> 188433 | DH24: 61811 | DJ24: 32603 | DL24: 34807 | DN24: 34912 | DP24: =DH24+DJ24+DL24+DN24 -> 164133 | DR24: 68579 | DT24: 39510 | DV24: 43170 | DX24: 50595 | DZ24: =DR24+DT24+DV24+DX24 -> 201854 | EB24: 95016 | ED24: 49525 | EF24: 47497 | EJ24: =EB24+ED24+EF24+EH24 -> 192038
A25: Cost of Installment Sales | J25: =B25+D25+F25+H25 -> 0 | T25: =L25+N25+P25+R25 -> 0 | AD25: =V25+X25+Z25+AB25 -> 0 | AL25: 3776 | AN25: =AF25+AH25+AJ25+AL25 -> 3776 | AP25: 3231 | AR25: 2090 | AT25: 2120 | AV25: 3198 | AX25: =AP25+AR25+AT25+AV25 -> 10639 | AZ25: 3145 | BB25: 2477 | BD25: 2180 | BF25: 2710 | BH25: =AZ25+BB25+BD25+BF25 -> 10512 | BJ25: 2863 | BL25: 2750 | BN25: 2556 | BP25: 2720 | BR25: =BJ25+BL25+BN25+BP25 -> 10889 | BT25: 2423 | BV25: 2398 | BX25: 2856 | BZ25: 3669 | CB25: =BT25+BV25+BX25+BZ25 -> 11346 | CD25: 3545 | CF25: 3129 | CH25: 2822 | CJ25: 3774 | CL25: =CD25+CF25+CH25+CJ25 -> 13270 | CN25: 4020 | CP25: 3790 | CR25: 4065 | CT25: 4745 | CV25: =CN25+CP25+CR25+CT25 -> 16620 | CX25: 4431 | CZ25: 4259 | DB25: 4511 | DD25: 5486 | DF25: =CX25+CZ25+DB25+DD25 -> 18687 | DH25: 5426 | DJ25: 5003 | DL25: 5507 | DN25: 7367 | DP25: =DH25+DJ25+DL25+DN25 -> 23303 | DR25: 6048 | DT25: 5898 | DV25: 5655 | DX25: 7233 | DZ25: =DR25+DT25+DV25+DX25 -> 24834 | EB25: 6298 | ED25: 5728 | EF25: 5376 | EJ25: =EB25+ED25+EF25+EH25 -> 17402
A26: Salaries and Other Expenses | B26: 186430 | D26: 191682 | F26: 191803.95 | H26: 200657.05 | J26: =B26+D26+F26+H26-0.6 -> 770572.4 | L26: 208524.9 | N26: 211321 | P26: 219195 | R26: 227193 | T26: =L26+N26+P26+R26 -> 866233.9 | V26: 242218.5 | X26: 244365 | Z26: 261992 | AB26: 270826 | AD26: =V26+X26+Z26+AB26-0.5 -> 1019401 | AF26: 262619 | AH26: 264478 | AJ26: 268552 | AL26: 274616 | AN26: =AF26+AH26+AJ26+AL26 -> 1070265 | AP26: 292496 | AR26: 291726 | AT26: 296427 | AV26: 299466 | AX26: =AP26+AR26+AT26+AV26 -> 1180115 | AZ26: 309084 | BB26: 311058 | BD26: 326410 | BF26: 331374 | BH26: =AZ26+BB26+BD26+BF26 -> 1277926 | BJ26: 334041 | BL26: 332939 | BN26: =350389-4075 -> 346314 | BO26: -3 | BP26: =341391-1124 -> 340267 | BQ26: -5 | BR26: =BJ26+BL26+BN26+BP26 -> 1353561 | BS26: (3) (5) | BT26: 338771 | BV26: 333113 | BX26: 340379 | BZ26: 373174 | CB26: =BT26+BV26+BX26+BZ26 -> 1385437 | CD26: 420727 | CF26: 417114 | CH26: 422294 | CJ26: 424830 | CL26: =CD26+CF26+CH26+CJ26 -> 1684965 | CN26: 417414 | CP26: 406572 | CR26: 417354 | CT26: 410465 | CV26: =CN26+CP26+CR26+CT26 -> 1651805 | CX26: 401508 | CZ26: 384910 | DB26: 389573 | DD26: 380083 | DF26: =CX26+CZ26+DB26+DD26 -> 1556074 | DH26: 391471 | DJ26: 381121 | DL26: 389295 | DN26: 381504 | DP26: =DH26+DJ26+DL26+DN26 -> 1543391 | DR26: 397198 | DT26: 395091 | DV26: 405633 | DX26: 396558 | DZ26: =DR26+DT26+DV26+DX26 -> 1594480 | EB26: 430803 | ED26: 412035 | EF26: 412567 | EJ26: =EB26+ED26+EF26+EH26 -> 1255405
A27: Franchise Operating Expenses
A28: Cost of Merchandise Sales | B28: 8542 | D28: 12635 | F28: 11316 | H28: 15420 | J28: =B28+D28+F28+H28+0.5 -> 47913.5 | L28: 12441.322 | N28: 11793 | P28: 10815 | R28: 14675 | T28: =L28+N28+P28+R28 -> 49724.322 | V28: 12494.066 | X28: 10703.138 | Z28: 11624 | AB28: 16430 | AD28: =V28+X28+Z28+AB28 -> 51251.204 | AF28: 12653 | AH28: 11884 | AJ28: 11061 | AL28: 13587 | AN28: =AF28+AH28+AJ28+AL28 -> 49185 | AP28: 11551 | AR28: 8946 | AT28: 10298 | AV28: 12453 | AX28: =AP28+AR28+AT28+AV28 -> 43248 | AZ28: 11892 | BB28: 9214 | BD28: 8585 | BF28: 9781 | BH28: =AZ28+BB28+BD28+BF28 -> 39472 | BJ28: 10866 | BL28: 7163 | BN28: 6964 | BP28: 11326 | BR28: =BJ28+BL28+BN28+BP28 -> 36319 | BT28: 11556 | BV28: 7580 | BX28: 6523 | BZ28: 9203 | CB28: =BT28+BV28+BX28+BZ28 -> 34862 | CD28: 9487 | CF28: 6663 | CH28: 7072 | CJ28: 9511 | CL28: =CD28+CF28+CH28+CJ28 -> 32733 | CN28: 9396 | CP28: 7234 | CR28: 7640 | CT28: 7435 | CV28: =CN28+CP28+CR28+CT28 -> 31705 | CX28: 7634 | CZ28: 5975 | DB28: 6378 | DD28: 6833 | DF28: =CX28+CZ28+DB28+DD28 -> 26820 | DH28: 8068 | DJ28: 6454 | DL28: 6680 | DN28: 8040 | DP28: =DH28+DJ28+DL28+DN28 -> 29242 | DR28: 8754 | DT28: 7195 | DV28: 6926 | DX28: 9612 | DZ28: =DR28+DT28+DV28+DX28 -> 32487 | EB28: 10164 | ED28: 7682 | EF28: 8295 | EJ28: =EB28+ED28+EF28+EH28 -> 26141
A30: Significant Items | B30: 0 | D30: 0 | F30: 0 | H30: 0 | J30: =B30+D30+F30+H30 -> 0 | L30: 0 | N30: 0 | O30: (1) | P30: 0 | R30: 0 | T30: =L30+N30+P30+R30 -> 0 | U30: (1) | V30: 0 | X30: 0 | Z30: 0 | AA30: (1) | AB30: 0 | AC30: (2) | AD30: =V30+X30+Z30+AB30 -> 0 | AE30: (1)(2) | AF30: 0 | AH30: 0 | AJ30: 0 | AL30: 0 | AN30: =AF30+AH30+AJ30+AL30 -> 0 | AP30: 0 | AR30: 0 | AT30: 0 | AV30: 0 | AX30: =AP30+AR30+AT30+AV30 -> 0 | AZ30: 0 | BB30: 0 | BD30: 0 | BF30: 0 | BH30: =AZ30+BB30+BD30+BF30 -> 0 | BJ30: 0 | BK30: -1 | BL30: 0 | BN30: 0 | BO30: -4 | BP30: 0 | BQ30: -6 | BR30: =BJ30+BL30+BN30+BP30 -> 0 | BS30: (1) (4) (6) | BT30: 0 | BV30: 0 | BX30: 0 | BY30: (1) (2) | CA30: -4 | CB30: =BT30+BV30+BX30+BZ30 -> 0 | CC30: (1) (2) (4) | CD30: 0 | CE30: -1 | CF30: 0 | CH30: 0 | CJ30: 0 | CK30: (3)(4) | CL30: =CD30+CF30+CH30+CJ30 -> 0 | CM30: (1)(3)(4) | CN30: 0 | CO30: (1) | CP30: 0 | CQ30: (2) | CR30: 0 | CS30: (3) | CU30: (4)(5) | CV30: =CN30+CP30+CR30+CT30 -> 0 | CW30: (1)(2)(3)(4)(5) | CX30: 0 | CY30: (1) | CZ30: 0 | DA30: (2) | DB30: 0 | DD30: 0 | DF30: =CX30+CZ30+DB30+DD30 -> 0 | DG30: (1)(2) | DH30: 0 | DJ30: 0 | DL30: 0 | DN30: 0 | DO30: (1) | DP30: =DH30+DJ30+DL30+DN30 -> 0 | DQ30: (1) | DR30: 0 | DS30: (1)(2) | DT30: 0 | DU30: (3) | DV30: 0 | DW30: (4) | DX30: 0 | DY30: (5) | DZ30: =DR30+DT30+DV30+DX30 -> 0 | EA30: (1,2,3,4,5) | EB30: 0 | EJ30: =EB30+ED30+EF30+EH30 -> 0
A31: General & Administrative Expenses | B31: 11251 | D31: 10600 | F31: 9920 | H31: 10257.63 | J31: =B31+D31+F31+H31 -> 42028.63 | L31: 11475.058 | N31: 12006 | P31: 12708 | R31: 11904 | T31: =L31+N31+P31+R31 -> 48093.058 | V31: 12869.114 | X31: 13934.133 | Z31: 13974 | AB31: 14582 | AD31: =V31+X31+Z31+AB31 -> 55359.247 | AF31: 15117 | AH31: 15285 | AI31: (1) | AJ31: 15325 | AL31: 15569 | AN31: =AF31+AH31+AJ31+AL31 -> 61296 | AO31: (1) | AP31: 16756 | AR31: 16388 | AT31: 16617 | AV31: 16874 | AX31: =AP31+AR31+AT31+AV31 -> 66635 | AZ31: 18186 | BB31: 19392 | BD31: 18772 | BF31: 19131 | BH31: =AZ31+BB31+BD31+BF31 -> 75481 | BJ31: 19215 | BL31: 20290 | BN31: =21176 -> 21176 | BP31: 21609 | BR31: =BJ31+BL31+BN31+BP31 -> 82290 | BT31: 20958 | BV31: 21253 | BX31: 23806 | BZ31: 27539 | CB31: =BT31+BV31+BX31+BZ31 -> 93556 | CD31: 30998 | CF31: 30419 | CH31: 31701 | CJ31: 30585 | CL31: =CD31+CF31+CH31+CJ31 -> 123703 | CN31: 30949 | CP31: 32676 | CR31: 30361 | CT31: 31646 | CV31: =CN31+CP31+CR31+CT31 -> 125632 | CX31: 34275 | CZ31: 34592 | DB31: 32714 | DD31: 36045 | DF31: =CX31+CZ31+DB31+DD31 -> 137626 | DH31: 31775 | DJ31: 32173 | DL31: 30796 | DN31: 31575 | DP31: =DH31+DJ31+DL31+DN31 -> 126319 | DR31: 34553 | DT31: 32047 | DV31: 33448 | DX31: 36093 | DZ31: =DR31+DT31+DV31+DX31 -> 136141 | EB31: 36245 | ED31: 34430 | EF31: 36214 | EJ31: =EB31+ED31+EF31+EH31 -> 106889
A32: Amortization & Write-down of Intangibles | B32: 6390 | D32: 6856 | F32: 6845.349 | H32: 7024.651 | J32: =B32+D32+F32+H32 -> 27116 | L32: 6974.5302 | N32: 6955 | P32: 7168 | R32: 7205 | T32: =L32+N32+P32+R32 -> 28302.53 | V32: 7268 | X32: 7396.1364 | Z32: 7738 | AB32: 7792 | AD32: =V32+X32+Z32+AB32 -> 30194.136 | AF32: 720 | AH32: 922 | AJ32: 1557 | AL32: 1846 | AN32: =AF32+AH32+AJ32+AL32 -> 5045 | AP32: 2873 | AR32: 3296 | AT32: 3183 | AV32: 3160 | AX32: =AP32+AR32+AT32+AV32 -> 12512 | AZ32: 2488 | BB32: 3158 | BD32: 2756 | BF32: 2378 | BH32: =AZ32+BB32+BD32+BF32 -> 10780 | BJ32: 2297 | BL32: 2155 | BN32: 2259 | BO32: -3 | BP32: =1327 -> 1327 | BR32: =BJ32+BL32+BN32+BP32 -> 8038 | BS32: -3 | BT32: 886 | BV32: 950 | BX32: 1009 | BZ32: 2728 | CB32: =BT32+BV32+BX32+BZ32 -> 5573 | CD32: 4038 | CF32: 3934 | CH32: 3953 | CJ32: 3809 | CL32: =CD32+CF32+CH32+CJ32 -> 15734 | CN32: 4930 | CP32: 3662 | CR32: 3545 | CT32: 4500 | CV32: =CN32+CP32+CR32+CT32 -> 16637 | CX32: 337 | CZ32: 1506 | DB32: 585 | DD32: 415 | DF32: =CX32+CZ32+DB32+DD32 -> 2843 | DH32: 1051 | DJ32: 1540 | DL32: 529 | DN32: 134 | DP32: =DH32+DJ32+DL32+DN32 -> 3254 | DR32: 858 | DT32: 1132 | DV32: 1261 | DX32: 1424 | DZ32: =DR32+DT32+DV32+DX32 -> 4675 | EB32: 1335 | ED32: 1481 | EF32: 2447 | EJ32: =EB32+ED32+EF32+EH32 -> 5263
A34: Total Operating Expenses | B34: =SUM(B23:B32) -> 302995 | D34: =SUM(D23:D32) -> 305633 | F34: =SUM(F23:F32) -> 301460.09 | H34: =SUM(H23:H32) -> 317055.8 | J34: =SUM(J23:J32) -> 1227143.8 | L34: =SUM(L23:L32) -> 333974.48 | N34: =SUM(N23:N32) -> 330444 | P34: =SUM(P23:P32) -> 341248 | R34: =SUM(R23:R32) -> 351318 | T34: =SUM(T23:T32) -> 1356984.1 | V34: =SUM(V23:V32) -> 377217.05 | X34: =SUM(X23:X32) -> 376119.17 | Z34: =SUM(Z23:Z32) -> 398702 | AB34: =SUM(AB23:AB32) -> 419904 | AD34: =SUM(AD23:AD32) -> 1571941.7 | AF34: =SUM(AF23:AF32) -> 410314 | AH34: =SUM(AH23:AH32) -> 404420 | AJ34: =SUM(AJ23:AJ32) -> 410474 | AL34: =SUM(AL23:AL32) -> 432387 | AN34: =SUM(AN23:AN32) -> 1657595 | AP34: =SUM(AP23:AP32) -> 470115 | AR34: =SUM(AR23:AR32) -> 456022 | AT34: =SUM(AT23:AT32) -> 462323 | AV34: =SUM(AV23:AV32) -> 469668 | AX34: =SUM(AX23:AX32) -> 1858128 | AZ34: =SUM(AZ23:AZ32) -> 492721 | BB34: =SUM(BB23:BB32) -> 482762 | BD34: =SUM(BD23:BD32) -> 498263 | BE34: (1) | BF34: =SUM(BF23:BF32) -> 509558 | BH34: =SUM(BH23:BH32) -> 1983304 | BI34: (1) | BJ34: =SUM(BJ23:BJ32) -> 523817 | BL34: =SUM(BL23:BL32) -> 507590 | BN34: =SUM(BN23:BN32) -> 521757 | BP34: =SUM(BP23:BP32) -> 520140 | BR34: =SUM(BR23:BR32) -> 2073304 | BT34: =SUM(BT23:BT32) -> 531491 | BV34: =SUM(BV23:BV32) -> 508430 | BX34: =SUM(BX23:BX32) -> 520013 | BZ34: =SUM(BZ23:BZ32) -> 578730 | CB34: =SUM(CB23:CB32) -> 2138664 | CD34: =SUM(CD23:CD32) -> 657894 | CF34: =SUM(CF23:CF32) -> 637134 | CH34: =SUM(CH23:CH32) -> 649126 | CJ34: =SUM(CJ23:CJ32) -> 656767 | CL34: =SUM(CL23:CL32) -> 2600921 | CN34: =SUM(CN23:CN32) -> 676196 | CP34: =SUM(CP23:CP32) -> 644612 | CR34: =SUM(CR23:CR32) -> 649993 | CT34: =SUM(CT23:CT32) -> 639093 | CV34: =SUM(CV23:CV32) -> 2609894 | CX34: =SUM(CX23:CX32) -> 649091 | CZ34: =SUM(CZ23:CZ32) -> 606195 | DB34: =SUM(DB23:DB32) -> 606884 | DD34: =SUM(DD23:DD32) -> 598331 | DF34: =SUM(DF23:DF32) -> 2460501 | DH34: =SUM(DH23:DH32) -> 629716 | DJ34: =SUM(DJ23:DJ32) -> 588712 | DL34: =SUM(DL23:DL32) -> 595187 | DN34: =SUM(DN23:DN32) -> 595309 | DP34: =SUM(DP23:DP32) -> 2408924 | DR34: =SUM(DR23:DR32) -> 651639 | DT34: =SUM(DT23:DT32) -> 620168 | DV34: =SUM(DV23:DV32) -> 638889 | DX34: =SUM(DX23:DX32) -> 654268 | DZ34: =SUM(DZ23:DZ32) -> 2564964 | EB34: =SUM(EB23:EB32) -> 743220 | ED34: =SUM(ED23:ED32) -> 670671 | EF34: =SUM(EF23:EF32) -> 671201 | EH34: =SUM(EH23:EH32) -> 0 | EJ34: =SUM(EJ23:EJ32) -> 2085092
A36: Operating Profit | B36: =B19-B34 -> 41702 | D36: =D19-D34 -> 45788 | F36: =F19-F34 -> 48959.514 | H36: =H19-H34 -> 53572.902 | J36: =J19-J34 -> 190023.02 | L36: =L19-L34 -> 58551.729 | N36: =N19-N34 -> 61801 | P36: =P19-P34 -> 63720 | R36: =R19-R34 -> 60557 | T36: =T19-T34 -> 244629.73 | V36: =V19-V34 -> 62485.298 | X36: =X19-X34 -> 66639.579 | Z36: =Z19-Z34 -> 48372 | AB36: =AB19-AB34 -> 59089 | AD36: =AD19-AD34 -> 236585.88 | AF36: =AF19-AF34 -> 88296 | AH36: =AH19-AH34 -> 90240 | AJ36: =AJ19-AJ34 -> 84087 | AL36: =AL19-AL34 -> 89826 | AN36: =AN19-AN34 -> 352449 | AP36: =AP19-AP34 -> 96291 | AR36: =AR19-AR34 -> 97238 | AT36: =AT19-AT34 -> 87502 | AV36: =AV19-AV34 -> 88991 | AX36: =AX19-AX34 -> 370022 | AZ36: =AZ19-AZ34 -> 92659 | BB36: =BB19-BB34 -> 90223 | BD36: =BD19-BD34 -> 71344 | BF36: =BF19-BF34 -> 75725 | BH36: =BH19-BH34 -> 329951 | BJ36: =BJ19-BJ34 -> 77992 | BL36: =BL19-BL34 -> 72988 | BN36: =BN19-BN34 -> 51750 | BP36: =BP19-BP34 -> 63073 | BR36: =BR19-BR34 -> 265803 | BT36: =BT19-BT34 -> 75484 | BV36: =BV19-BV34 -> 75193 | BX36: =BX19-BX34 -> 67171 | BZ36: =BZ19-BZ34 -> 77396 | CB36: =CB19-CB34 -> 295244 | CD36: =CD19-CD34 -> 97405 | CF36: =CF19-CF34 -> 87024 | CH36: =CH19-CH34 -> 56675 | CJ36: =CJ19-CJ34 -> 60196 | CL36: =CL19-CL34 -> 301300 | CN36: =CN19-CN34 -> 80440 | CP36: =CP19-CP34 -> 74419 | CR36: =CR19-CR34 -> 58762 | CT36: =CT19-CT34 -> 60657 | CV36: =CV19-CV34 -> 274278 | CX36: =CX19-CX34 -> 79092 | CZ36: =CZ19-CZ34 -> 73414 | DB36: =DB19-DB34 -> 64367 | DD36: =DD19-DD34 -> 74582 | DF36: =DF19-DF34 -> 291455 | DH36: =DH19-DH34 -> 88703 | DJ36: =DJ19-DJ34 -> 82831 | DL36: =DL19-DL34 -> 69393 | DN36: =DN19-DN34 -> 81781 | DP36: =DP19-DP34 -> 322708 | DR36: =DR19-DR34 -> 90539 | DT36: =DT19-DT34 -> 78085 | DV36: =DV19-DV34 -> 65382 | DX36: =DX19-DX34 -> 83214 | DZ36: =DZ19-DZ34 -> 317220 | EB36: =EB19-EB34 -> 92034 | ED36: =ED19-ED34 -> 79027 | EF36: =EF19-EF34 -> 68113 | EH36: =EH19-EH34 -> 0 | EJ36: =EJ19-EJ34 -> 239174
A38: Interest Income | B38: -286 | D38: -50 | F38: -54.184 | H38: -513.383 | J38: =B38+D38+F38+H38 -> -903.567 | L38: -256.96936 | N38: -117 | P38: -720 | R38: -612 | T38: =L38+N38+P38+R38 -> -1705.9694 | V38: -361.49 | X38: -226.98483 | Z38: -282 | AB38: -223.53962 | AD38: =V38+X38+Z38+AB38 -> -1094.0144 | AF38: -723 | AH38: -705 | AJ38: -588 | AL38: -660 | AN38: =AF38+AH38+AJ38+AL38 -> -2676 | AP38: -771 | AR38: -1208 | AT38: -1305 | AV38: -1361 | AX38: =AP38+AR38+AT38+AV38 -> -4645 | AZ38: -1503 | BB38: -1488 | BD38: -1391 | BF38: -1255 | BH38: =AZ38+BB38+BD38+BF38 -> -5637 | BJ38: -1402 | BL38: -1351 | BN38: -1331 | BP38: -1408 | BR38: =BJ38+BL38+BN38+BP38 -> -5492 | BT38: -1460 | BV38: -1399 | BX38: -1335 | BZ38: -1362 | CB38: =BT38+BV38+BX38+BZ38 -> -5556 | CD38: -1761 | CF38: -1473 | CH38: -1703 | CJ38: -1890 | CL38: =CD38+CF38+CH38+CJ38 -> -6827 | CN38: -1864 | CP38: -2289 | CR38: -2073 | CT38: -2634 | CV38: =CN38+CP38+CR38+CT38 -> -8860 | CX38: -269 | CZ38: -267 | DB38: -153 | DD38: -148 | DF38: =CX38+CZ38+DB38+DD38 -> -837 | DH38: -168 | DJ38: -156 | DL38: -282 | DN38: -248 | DP38: =DH38+DJ38+DL38+DN38 -> -854 | DR38: -154 | DT38: -237 | DV38: -91 | DX38: -145 | DZ38: =DR38+DT38+DV38+DX38 -> -627 | EB38: -181 | ED38: -122 | EF38: -167 | EJ38: =EB38+ED38+EF38+EH38 -> -470
A39: Interest Expense | B39: 18642 | D39: 18865 | F39: 18717.045 | H39: 19448.752 | J39: =B39+D39+F39+H39 -> 75672.797 | L39: 19008 | N39: 18361 | P39: 18915 | R39: 18040 | T39: =L39+N39+P39+R39 -> 74324 | V39: 16510.443 | X39: 15868 | Z39: 14837 | AB39: 13659 | AD39: =V39+X39+Z39+AB39 -> 60874.443 | AF39: 15798 | AH39: 15557 | AJ39: 15301 | AL39: 15117 | AN39: =AF39+AH39+AJ39+AL39 -> 61773 | AP39: 13523 | AR39: 13070 | AT39: 11565 | AV39: 10419 | AX39: =AP39+AR39+AT39+AV39 -> 48577 | AZ39: 10359 | BB39: 10252 | BD39: 9914 | BF39: 10435 | BH39: =AZ39+BB39+BD39+BF39 -> 40960 | BJ39: 10868 | BL39: 10786 | BN39: 11802 | BP39: 12739 | BR39: =BJ39+BL39+BN39+BP39 -> 46195 | BT39: 13023 | BV39: 13301 | BX39: 13322 | BZ39: 18913 | CB39: =BT39+BV39+BX39+BZ39 -> 58559 | CD39: 24096 | CF39: 23431 | CH39: 23419 | CJ39: 23832 | CL39: =CD39+CF39+CH39+CJ39 -> 94778 | CN39: 20927 | CP39: 16739 | CR39: 15040 | CT39: 13535 | CV39: =CN39+CP39+CR39+CT39 -> 66241 | CX39: 9232 | CZ39: 8045 | DB39: 4866 | DD39: 4648 | DF39: =CX39+CZ39+DB39+DD39 -> 26791 | DH39: 6083 | DJ39: 6051 | DL39: 6085 | DN39: 8547 | DP39: =DH39+DJ39+DL39+DN39 -> 26766 | DR39: 9760 | DT39: 9613 | DV39: 8811 | DX39: 9050 | DZ39: =DR39+DT39+DV39+DX39 -> 37234 | EB39: 8977 | ED39: 8343 | EF39: 8096 | EJ39: =EB39+ED39+EF39+EH39 -> 25416
A40: Significant Items | B40: 0 | D40: 0 | F40: 0 | H40: 0 | J40: =B40+D40+F40+H40 -> 0 | L40: 0 | N40: 0 | P40: 0 | R40: 0 | T40: =L40+N40+P40+R40 -> 0 | V40: 0 | X40: 0 | Z40: 0 | AB40: 0 | AD40: =V40+X40+Z40+AB40 -> 0 | AF40: 0 | AH40: 0 | AI40: (2) | AJ40: 0 | AL40: 0 | AN40: =AF40+AH40+AJ40+AL40 -> 0 | AO40: (2) | AP40: 0 | AR40: 0 | AT40: 0 | AU40: (1) | AV40: 0 | AX40: =AP40+AR40+AT40+AV40 -> 0 | AY40: (1) | AZ40: 0 | BB40: 0 | BD40: 0 | BF40: 0 | BG40: -2 | BH40: =AZ40+BB40+BD40+BF40 -> 0 | BI40: -2 | BJ40: 0 | BL40: 0 | BN40: 0 | BP40: 0 | BR40: =BJ40+BL40+BN40+BP40 -> 0 | BT40: 0 | BV40: 0 | BX40: 0 | BY40: -3 | BZ40: 0 | CA40: -5 | CB40: =BT40+BV40+BX40+BZ40 -> 0 | CC40: (3) (5) | CD40: 0 | CF40: 0 | CH40: 0 | CJ40: 0 | CL40: =CD40+CF40+CH40+CJ40 -> 0 | CN40: 0 | CP40: 0 | CR40: 0 | CT40: 0 | CU40: (6) | CV40: =CN40+CP40+CR40+CT40 -> 0 | CW40: (6) | CX40: 0 | CZ40: 0 | DB40: 0 | DD40: 0 | DF40: =CX40+CZ40+DB40+DD40 -> 0 | DH40: 0 | DJ40: 0 | DL40: 0 | DN40: 0 | DO40: (2) | DP40: =DH40+DJ40+DL40+DN40 -> 0 | DQ40: (2) | DR40: 0 | DT40: 0 | DV40: 0 | DX40: 0 | DZ40: =DR40+DT40+DV40+DX40 -> 0 | EB40: 0 | ED40: 0 | EF40: 0 | EJ40: =EB40+ED40+EF40+EH40 -> 0
A42: Earnings Before Income Taxes | B42: =B36-B38-B39-B40 -> 23346 | D42: =D36-D38-D39-D40 -> 26973 | F42: =F36-F38-F39-F40 -> 30296.653 | H42: =H36-H38-H39-H40 -> 34637.533 | J42: =J36-J38-J39-J40 -> 115253.79 | L42: =L36-L38-L39-L40 -> 39800.698 | N42: =N36-N38-N39-N40 -> 43557 | P42: =P36-P38-P39-P40 -> 45525 | R42: =R36-R38-R39-R40 -> 43129 | T42: =T36-T38-T39-T40 -> 172011.7 | V42: =V36-V38-V39-V40 -> 46336.345 | X42: =X36-X38-X39-X40 -> 50998.563 | Z42: =Z36-Z38-Z39-Z40 -> 33817 | AB42: =AB36-AB38-AB39-AB40 -> 45653.54 | AD42: =AD36-AD38-AD39-AD40 -> 176805.45 | AF42: =AF36-AF38-AF39-AF40 -> 73221 | AH42: =AH36-AH38-AH39-AH40 -> 75388 | AJ42: =AJ36-AJ38-AJ39-AJ40 -> 69374 | AL42: =AL36-AL38-AL39-AL40 -> 75369 | AN42: =AN36-AN38-AN39-AN40 -> 293352 | AP42: =AP36-AP38-AP39-AP40 -> 83539 | AR42: =AR36-AR38-AR39-AR40 -> 85376 | AT42: =AT36-AT38-AT39-AT40 -> 77242 | AV42: =AV36-AV38-AV39-AV40 -> 79933 | AX42: =AX36-AX38-AX39-AX40 -> 326090 | AZ42: =AZ36-AZ38-AZ39-AZ40 -> 83803 | BB42: =BB36-BB38-BB39-BB40 -> 81459 | BD42: =BD36-BD38-BD39-BD40 -> 62821 | BF42: =BF36-BF38-BF39-BF40 -> 66545 | BH42: =BH36-BH38-BH39-BH40 -> 294628 | BJ42: =BJ36-BJ38-BJ39-BJ40 -> 68526 | BL42: =BL36-BL38-BL39-BL40 -> 63553 | BN42: =BN36-BN38-BN39-BN40 -> 41279 | BP42: =BP36-BP38-BP39-BP40 -> 51742 | BR42: =BR36-BR38-BR39-BR40 -> 225100 | BT42: =BT36-BT38-BT39-BT40 -> 63921 | BV42: =BV36-BV38-BV39-BV40 -> 63291 | BX42: =BX36-BX38-BX39-BX40 -> 55184 | BZ42: =BZ36-BZ38-BZ39-BZ40 -> 59845 | CB42: =CB36-CB38-CB39-CB40 -> 242241 | CD42: =CD36-CD38-CD39-CD40 -> 75070 | CF42: =CF36-CF38-CF39-CF40 -> 65066 | CH42: =CH36-CH38-CH39-CH40 -> 34959 | CJ42: =CJ36-CJ38-CJ39-CJ40 -> 38254 | CL42: =CL36-CL38-CL39-CL40 -> 213349 | CN42: =CN36-CN38-CN39-CN40 -> 61377 | CP42: =CP36-CP38-CP39-CP40 -> 59969 | CR42: =CR36-CR38-CR39-CR40 -> 45795 | CT42: =CT36-CT38-CT39-CT40 -> 49756 | CV42: =CV36-CV38-CV39-CV40 -> 216897 | CX42: =CX36-CX38-CX39-CX40 -> 70129 | CZ42: =CZ36-CZ38-CZ39-CZ40 -> 65636 | DB42: =DB36-DB38-DB39-DB40 -> 59654 | DD42: =DD36-DD38-DD39-DD40 -> 70082 | DF42: =DF36-DF38-DF39-DF40 -> 265501 | DH42: =DH36-DH38-DH39-DH40 -> 82788 | DJ42: =DJ36-DJ38-DJ39-DJ40 -> 76936 | DL42: =DL36-DL38-DL39-DL40 -> 63590 | DN42: =DN36-DN38-DN39-DN40 -> 73482 | DP42: =DP36-DP38-DP39-DP40 -> 296796 | DR42: =DR36-DR38-DR39-DR40 -> 80933 | DT42: =DT36-DT38-DT39-DT40 -> 68709 | DV42: =DV36-DV38-DV39-DV40 -> 56662 | DX42: =DX36-DX38-DX39-DX40 -> 74309 | DZ42: =DZ36-DZ38-DZ39-DZ40 -> 280613 | EB42: =EB36-EB38-EB39-EB40 -> 83238 | ED42: =ED36-ED38-ED39-ED40 -> 70806 | EF42: =EF36-EF38-EF39-EF40 -> 60184 | EH42: =EH36-EH38-EH39-EH40 -> 0 | EJ42: =EJ36-EJ38-EJ39-EJ40 -> 214228
A44: Income Tax Expense | B44: 11319 | D44: 13082 | F44: 14700 | H44: 16798.095 | J44: =B44+D44+F44+H44 -> 55899.095 | L44: 18912 | N44: 20687 | P44: 21624.375 | R44: 19513 | T44: =L44+N44+P44+R44+109 -> 80845.375 | V44: 21338 | X44: 23454 | Z44: 14883 | AB44: 19634 | AD44: =V44+X44+Z44+AB44-0.5 -> 79308.5 | AF44: 29658 | AH44: 30524 | AJ44: 27925 | AL44: 30151 | AN44: =AF44+AH44+AJ44+AL44 -> 118258 | AP44: 32580 | AR44: 33083 | AT44: 28773 | AV44: 28434 | AX44: =AP44+AR44+AT44+AV44 -> 122870 | AZ44: 31594 | BB44: 30265 | BD44: 25269 | BF44: 24831 | BH44: =AZ44+BB44+BD44+BF44 -> 111959 | BJ44: =BJ42*(28857/76526)+1 -> 25841.3 | BL44: =21811+2122 -> 23933 | BM44: -2 | BN44: 15294 | BP44: 18146 | BQ44: -7 | BR44: =BJ44+BL44+BN44+BP44 -> 83214.3 | BS44: (2) (7) | BT44: 23593 | BV44: 23448 | BX44: 18804 | BZ44: 24249 | CB44: =BT44+BV44+BX44+BZ44 -> 90094 | CD44: 27158 | CF44: 23815 | CH44: 12236 | CJ44: 10183 | CL44: =CD44+CF44+CH44+CJ44 -> 73392 | CN44: 23216 | CP44: 22228 | CR44: 16264 | CT44: 18370 | CV44: =CN44+CP44+CR44+CT44 -> 80078 | CX44: 26614 | CZ44: 24841 | DB44: 22824 | DD44: 26399 | DF44: =CX44+CZ44+DB44+DD44 -> 100678 | DH44: 31327 | DJ44: 29106 | DL44: 23093 | DN44: 27862 | DP44: =DH44+DJ44+DL44+DN44 -> 111388 | DR44: 30382 | DT44: 25734 | DV44: 20629 | DX44: 23799 | DZ44: =DR44+DT44+DV44+DX44 -> 100544 | EB44: 31297 | ED44: 26624 | EF44: 20274 | EJ44: =EB44+ED44+EF44+EH44 -> 78195
A45: Net Earnings | B45: =B42-B44 -> 12027 | D45: =D42-D44 -> 13891 | F45: =F42-F44 -> 15596.653 | H45: =H42-H44 -> 17839.438 | J45: =J42-J44 -> 59354.691 | L45: =L42-L44 -> 20888.698 | N45: =N42-N44 -> 22870 | P45: =P42-P44 -> 23900.625 | R45: =R42-R44 -> 23616 | T45: =T42-T44 -> 91166.323 | V45: =V42-V44 -> 24998.345 | X45: =X42-X44 -> 27544.563 | Z45: =Z42-Z44 -> 18934 | AB45: =AB42-AB44 -> 26019.54 | AD45: =AD42-AD44 -> 97496.948 | AF45: =AF42-AF44 -> 43563 | AH45: =AH42-AH44 -> 44864 | AJ45: =AJ42-AJ44 -> 41449 | AL45: =AL42-AL44 -> 45218 | AN45: =AN42-AN44 -> 175094 | AP45: =AP42-AP44 -> 50959 | AR45: =AR42-AR44 -> 52293 | AT45: =AT42-AT44 -> 48469 | AV45: =AV42-AV44 -> 51499 | AX45: =AX42-AX44 -> 203220 | AZ45: =AZ42-AZ44 -> 52209 | BB45: =BB42-BB44 -> 51194 | BD45: =BD42-BD44 -> 37552 | BF45: =BF42-BF44 -> 41714 | BH45: =BH42-BH44 -> 182669 | BJ45: =BJ42-BJ44 -> 42684.7 | BL45: =BL42-BL44 -> 39620 | BN45: =BN42-BN44 -> 25985 | BP45: =BP42-BP44 -> 33596 | BR45: =BR42-BR44 -> 141885.7 | BT45: =BT42-BT44 -> 40328 | BV45: =BV42-BV44 -> 39843 | BX45: =BX42-BX44 -> 36380 | BZ45: =BZ42-BZ44 -> 35596 | CB45: =CB42-CB44 -> 152147 | CD45: =CD42-CD44 -> 47912 | CF45: =CF42-CF44 -> 41251 | CH45: =CH42-CH44 -> 22723 | CJ45: =CJ42-CJ44 -> 28071 | CL45: =CL42-CL44 -> 139957 | CN45: =CN42-CN44 -> 38161 | CP45: =CP42-CP44 -> 37741 | CR45: =CR42-CR44 -> 29531 | CT45: =CT42-CT44 -> 31386 | CV45: =CV42-CV44 -> 136819 | CX45: =CX42-CX44 -> 43515 | CZ45: =CZ42-CZ44 -> 40795 | DB45: =DB42-DB44 -> 36830 | DD45: =DD42-DD44 -> 43683 | DF45: =DF42-DF44 -> 164823 | DH45: =DH42-DH44 -> 51461 | DJ45: =DJ42-DJ44 -> 47830 | DL45: =DL42-DL44 -> 40497 | DN45: =DN42-DN44 -> 45620 | DP45: =DP42-DP44 -> 185408 | DR45: =DR42-DR44 -> 50551 | DT45: =DT42-DT44 -> 42975 | DV45: =DV42-DV44 -> 36033 | DX45: =DX42-DX44 -> 50510 | DZ45: =DZ42-DZ44 -> 180069 | EB45: =EB42-EB44 -> 51941 | ED45: =ED42-ED44 -> 44182 | EF45: =EF42-EF44 -> 39910 | EH45: =EH42-EH44 -> 0 | EJ45: =EJ42-EJ44 -> 136033
A47: Preferred Dividends | B47: 2441 | D47: 2490 | F47: 2541.519 | H47: 2566.481 | J47: =B47+D47+F47+H47 -> 10039 | L47: 2554 | N47: 2579 | P47: 2631 | R47: 2656 | T47: =L47+N47+P47+R47 -> 10420 | V47: 4325 | X47: 5053 | Z47: 2709 | AB47: 3321 | AD47: =V47+X47+Z47+AB47 -> 15408 | AF47: 4992 | AH47: 3898 | AJ47: 1321 | AL47: 1 | AN47: =AF47+AH47+AJ47+AL47 -> 10212 | AP47: 0 | AR47: 0 | AT47: 0 | AV47: 0 | AX47: =AP47+AR47+AT47+AV47 -> 0 | AZ47: 0 | BB47: 0 | BD47: 0 | BF47: 0 | BH47: =AZ47+BB47+BD47+BF47 -> 0 | BJ47: 0 | BL47: 0 | BN47: 0 | BP47: 0 | BR47: =BJ47+BL47+BN47+BP47 -> 0 | BT47: 0 | BV47: 0 | BX47: 0 | BZ47: 0 | CB47: =BT47+BV47+BX47+BZ47 -> 0 | CD47: 0 | CF47: 0 | CH47: 0 | CJ47: 0 | CL47: =CD47+CF47+CH47+CJ47 -> 0 | CN47: 0 | CP47: 0 | CR47: 0 | CT47: 0 | CV47: =CN47+CP47+CR47+CT47 -> 0 | CX47: 0 | CZ47: 0 | DB47: 0 | DD47: 0 | DF47: =CX47+CZ47+DB47+DD47 -> 0 | DH47: 0 | DJ47: 0 | DL47: 0 | DN47: 0 | DP47: =DH47+DJ47+DL47+DN47 -> 0 | DR47: 0 | DT47: 0 | DZ47: =DR47+DT47+DV47+DX47 -> 0 | EB47: 0 | EJ47: =EB47+ED47+EF47+EH47 -> 0
A48: Net Earnings to Common | B48: =B45-B47 -> 9586 | D48: =D45-D47 -> 11401 | F48: =F45-F47 -> 13055.134 | H48: =H45-H47 -> 15272.957 | J48: =J45-J47 -> 49315.691 | L48: =L45-L47 -> 18334.698 | N48: =N45-N47 -> 20291 | P48: =P45-P47 -> 21269.625 | R48: =R45-R47 -> 20960 | T48: =T45-T47 -> 80746.323 | V48: =V45-V47 -> 20673.345 | X48: =X45-X47 -> 22491.563 | Z48: =Z45-Z47 -> 16225 | AB48: =AB45-AB47 -> 22698.54 | AD48: =AD45-AD47 -> 82088.948 | AF48: =AF45-AF47 -> 38571 | AH48: =AH45-AH47 -> 40966 | AJ48: =AJ45-AJ47 -> 40128 | AL48: =AL45-AL47 -> 45217 | AN48: =AN45-AN47 -> 164882 | AP48: =AP45-AP47 -> 50959 | AR48: =AR45-AR47 -> 52293 | AT48: =AT45-AT47 -> 48469 | AV48: =AV45-AV47 -> 51499 | AX48: =AX45-AX47 -> 203220 | AZ48: =AZ45-AZ47 -> 52209 | BB48: =BB45-BB47 -> 51194 | BD48: =BD45-BD47 -> 37552 | BF48: =BF45-BF47 -> 41714 | BH48: =BH45-BH47 -> 182669 | BJ48: =BJ45-BJ47 -> 42684.7 | BL48: =BL45-BL47 -> 39620 | BN48: =BN45-BN47 -> 25985 | BP48: =BP45-BP47 -> 33596 | BR48: =BR45-BR47 -> 141885.7 | BT48: =BT45-BT47 -> 40328 | BV48: =BV45-BV47 -> 39843 | BX48: =BX45-BX47 -> 36380 | BZ48: =BZ45-BZ47 -> 35596 | CB48: =CB45-CB47 -> 152147 | CD48: =CD45-CD47 -> 47912 | CF48: =CF45-CF47 -> 41251 | CH48: =CH45-CH47 -> 22723 | CJ48: =CJ45-CJ47 -> 28071 | CL48: =CL45-CL47 -> 139957 | CN48: =CN45-CN47 -> 38161 | CP48: =CP45-CP47 -> 37741 | CR48: =CR45-CR47 -> 29531 | CT48: =CT45-CT47 -> 31386 | CV48: =CV45-CV47 -> 136819 | CX48: =CX45-CX47 -> 43515 | CZ48: =CZ45-CZ47 -> 40795 | DB48: =DB45-DB47 -> 36830 | DD48: =DD45-DD47 -> 43683 | DF48: =DF45-DF47 -> 164823 | DH48: =DH45-DH47 -> 51461 | DJ48: =DJ45-DJ47 -> 47830 | DL48: =DL45-DL47 -> 40497 | DN48: =DN45-DN47 -> 45620 | DP48: =DP45-DP47 -> 185408 | DR48: =DR45-DR47 -> 50551 | DT48: =DT45-DT47 -> 42975 | DV48: =DV45-DV47 -> 36033 | DX48: =DX45-DX47 -> 50510 | DZ48: =DZ45-DZ47 -> 180069 | EB48: =EB45-EB47 -> 51941 | ED48: =ED45-ED47 -> 44182 | EF48: =EF45-EF47 -> 39910 | EH48: =EH45-EH47 -> 0 | EJ48: =EJ45-EJ47 -> 136033
A50: Basic EPS | B50: =B48/B53 -> 0.15900477 | D50: =D48/D53 -> 0.18844628 | F50: =F48/F53 -> 0.21494355 | H50: =H48/H53 -> 0.25136532 | J50: =J48/J53 -> 0.81415974 | L50: =L48/L53 -> 0.30166917 | N50: =N48/N53 -> 0.33365124 | P50: =P48/P53 -> 0.34862523 | R50: =R48/R53 -> 0.33959819 | T50: =T48/T53 -> 1.3330525 | V50: =V48/V53 -> 0.33132186 | X50: =X48/X53 -> 0.35044505 | Z50: =Z48/Z53 -> 0.24337842 | AB50: =AB48/AB53 -> 0.34804369 | AD50: =AD48/AD53 -> 1.2704318 | AF50: =AF48/AF53 -> 0.6293453 | AH50: =AH48/AH53 -> 0.6374047 | AJ50: =AJ48/AJ53 -> 0.52161705 | AL50: =AL48/AL53 -> 0.51743098 | AN50: =AN48/AN53 -> 2.2445904 | AP50: =AP48/AP53 -> 0.58412425 | AR50: =AR48/AR53 -> 0.59765136 | AT50: =AT48/AT53 -> 0.59651951 | AV50: =AV48/AV53 -> 0.63924679 | AX50: =AX48/AX53 -> 2.415289 | AZ50: =AZ48/AZ53 -> 0.65029582 | BB50: =BB48/BB53 -> 0.64424142 | BD50: =BD48/BD53 -> 0.4815038 | BF50: =BF48/BF53 -> 0.55720449 | BH50: =BH48/BH53 -> 2.3374152 | BJ50: =BJ48/BJ53 -> 0.57250329 | BL50: =BL48/BL53 -> 0.53005472 | BN50: =BN48/BN53 -> 0.35680938 | BP50: =BP48/BP53 -> 0.48034085 | BR50: =BR48/BR53 -> 1.9431539 | BT50: =BT48/BT53 -> 0.58230334 | BV50: =BV48/BV53 -> 0.57290963 | BX50: =BX48/BX53 -> 0.52114371 | BZ50: =BZ48/BZ53 -> 0.50782509 | CB50: =CB48/CB53 -> 2.1836357 | CD50: =CD48/CD53 -> 0.68167203 | CF50: =IF(ISERROR(CF48/CF53),0,(CF48/CF53)) -> 0.59080233 | CH50: =IF(ISERROR(CH48/CH53),0,(CH48/CH53)) -> 0.3344618 | CJ50: =IF(ISERROR(CJ48/CJ53),0,(CJ48/CJ53)) -> 0.4203567 | CL50: =CL48/CL53 -> 2.0370271 | CN50: =CN48/CN53 -> 0.57204317 | CP50: =IF(ISERROR(CP48/CP53),0,(CP48/CP53)) -> 0.56596785 | CR50: =IF(ISERROR(CR48/CR53),0,(CR48/CR53)) -> 0.44277018 | CT50: =IF(ISERROR(CT48/CT53),0,(CT48/CT53)) -> 0.47316529 | CV50: =CV48/CV53 -> 2.0541697 | CX50: =CX48/CX53 -> 0.65936813 | CZ50: =IF(ISERROR(CZ48/CZ53),0,(CZ48/CZ53)) -> 0.61784394 | DB50: =IF(ISERROR(DB48/DB53),0,(DB48/DB53)) -> 0.55738003 | DD50: =IF(ISERROR(DD48/DD53),0,(DD48/DD53)) -> 0.66343175 | DF50: =DF48/DF53 -> 2.497848 | DH50: =DH48/DH53 -> 0.78328437 | DJ50: =IF(ISERROR(DJ48/DJ53),0,(DJ48/DJ53)) -> 0.72530139 | DL50: =IF(ISERROR(DL48/DL53),0,(DL48/DL53)) -> 0.62213107 | DN50: =IF(ISERROR(DN48/DN53),0,(DN48/DN53)) -> 0.71641697 | DP50: =DP48/DP53 -> 2.8478742 | DR50: =DR48/DR53 -> 0.79792591 | DT50: =IF(ISERROR(DT48/DT53),0,(DT48/DT53)) -> 0.68815052 | DV50: =IF(ISERROR(DV48/DV53),0,(DV48/DV53)) -> 0.60024988 | DX50: =IF(ISERROR(DX48/DX53),0,(DX48/DX53)) -> 0.85730774 | DZ50: =DZ48/DZ53 -> 2.942905 | EB50: =EB48/EB53 -> 0.87661176 | ED50: =IF(ISERROR(ED48/ED53),0,(ED48/ED53)) -> 0.74682218 | EF50: =IF(ISERROR(EF48/EF53),0,(EF48/EF53)) -> 0.67779627 | EH50: =IF(ISERROR(EH48/EH53),0,(EH48/EH53)) -> 0 | EJ50: =EJ48/EJ53 -> 2.3018207
A51: Diluted EPS | B51: =B45/B54 -> 0.14105502 | D51: =D45/D54 -> 0.16275337 | F51: =F45/F54 -> 0.18287027 | H51: =H45/H54 -> 0.2088866 | J51: =J45/J54 -> 0.69562017 | L51: =L45/L54 -> 0.24405536 | N51: =N45/N54 -> 0.26481401 | P51: =P45/P54 -> 0.27227095 | R51: =R45/R54 -> 0.26720978 | T51: =T45/T54 -> 1.0482294 | V51: =V45/V54 -> 0.27489616 | X51: =X45/X54 -> 0.29621792 | Z51: =Z45/Z54 -> 0.20047058 | AB51: =AB45/AB54 -> 0.28155866 | AD51: =AD45/AD54 -> 1.0517754 | AF51: =AF45/AF54 -> 0.47975551 | AH51: =AH45/AH54 -> 0.48878115 | AJ51: =AJ45/AJ54 -> 0.45509593 | AL51: =AL45/AL54 -> 0.50358326 | AN51: =AN45/AN54 -> 1.9269686 | AP51: =AP45/AP54 -> 0.5672195 | AR51: =AR45/AR54 -> 0.57612031 | AT51: =AT45/AT54 -> 0.57423643 | AV51: =AV45/AV54 -> 0.61684314 | AX51: =AX45/AX54 -> 2.3302908 | AZ51: =AZ45/AZ54 -> 0.62988165 | BB51: =BB45/BB54 -> 0.62446938 | BD51: =BD45/BD54 -> 0.46982284 | BF51: =BF45/BF54 -> 0.54580188 | BH51: =BH45/BH54 -> 2.2763343 | BJ51: =BJ45/BJ54 -> 0.56110922 | BL51: =BL45/BL54 -> 0.52130893 | BN51: =BN45/BN54 -> 0.35251584 | BP51: =BP45/BP54 -> 0.47554744 | BR51: =BR45/BR54 -> 1.9145736 | BT51: =BT45/BT54 -> 0.57406406 | BV51: =BV45/BV54 -> 0.56402888 | BX51: =BX45/BX54 -> 0.51345744 | BZ51: =BZ45/BZ54 -> 0.50000702 | CB51: =CB45/CB54 -> 2.1510045 | CD51: =CD45/CD54 -> 0.67161961 | CF51: =IF(ISERROR(CF45/CF54),0,(CF45/CF54)) -> 0.58293765 | CH51: =IF(ISERROR(CH45/CH54),0,(CH45/CH54)) -> 0.33130185 | CJ51: =IF(ISERROR(CJ45/CJ54),0,(CJ45/CJ54)) -> 0.41764242 | CL51: =CL45/CL54 -> 2.0145089 | CN51: =CN45/CN54 -> 0.56808336 | CP51: =IF(ISERROR(CP45/CP54),0,(CP45/CP54)) -> 0.560288 | CR51: =IF(ISERROR(CR45/CR54),0,(CR45/CR54)) -> 0.43767136 | CT51: =IF(ISERROR(CT45/CT54),0,(CT45/CT54)) -> 0.47016703 | CV51: =CV45/CV54 -> 2.0362773 | CX51: =CX45/CX54 -> 0.65441011 | CZ51: =IF(ISERROR(CZ45/CZ54),0,(CZ45/CZ54)) -> 0.61210557 | DB51: =IF(ISERROR(DB45/DB54),0,(DB45/DB54)) -> 0.55223187 | DD51: =IF(ISERROR(DD45/DD54),0,(DD45/DD54)) -> 0.65754971 | DF51: =DF45/DF54 -> 2.4760467 | DH51: =DH45/DH54 -> 0.77365185 | DJ51: =IF(ISERROR(DJ45/DJ54),0,(DJ45/DJ54)) -> 0.71630749 | DL51: =IF(ISERROR(DL45/DL54),0,(DL45/DL54)) -> 0.61596143 | DN51: =IF(ISERROR(DN45/DN54),0,(DN45/DN54)) -> 0.70646535 | DP51: =DP45/DP54 -> 2.8133576 | DR51: =DR45/DR54 -> 0.78627201 | DT51: =IF(ISERROR(DT45/DT54),0,(DT45/DT54)) -> 0.68054412 | DV51: =IF(ISERROR(DV45/DV54),0,(DV45/DV54)) -> 0.5955474 | DX51: =IF(ISERROR(DX45/DX54),0,(DX45/DX54)) -> 0.84732684 | DZ51: =DZ45/DZ54 -> 2.9095595 | EB51: =EB45/EB54 -> 0.86662217 | ED51: =IF(ISERROR(ED45/ED54),0,(ED45/ED54)) -> 0.74158246 | EF51: =IF(ISERROR(EF45/EF54),0,(EF45/EF54)) -> 0.67288238 | EH51: =IF(ISERROR(EH45/EH54),0,(EH45/EH54)) -> 0 | EJ51: =EJ45/EJ54 -> 2.2821138
A53: Basic Shares Outstanding | B53: =24115*5/2 -> 60287.5 | D53: =24200*5/2 -> 60500 | F53: =24295*5/2 -> 60737.5 | H53: =24304*5/2 -> 60760 | J53: =24229*5/2 -> 60572.5 | L53: =24311*5/2 -> 60777.5 | N53: =24326*5/2 -> 60815 | P53: =24404*5/2 -> 61010 | R53: =24688*5/2 -> 61720 | T53: =24229*5/2 -> 60572.5 | V53: =24958.625*5/2 -> 62396.562 | X53: =25672*5/2 -> 64180 | Z53: =26666.292*5/2 -> 66665.73 | AB53: =26087*5/2 -> 65217.5 | AD53: =25846*5/2 -> 64615 | AF53: =24515*5/2 -> 61287.5 | AH53: =25708*5/2 -> 64270 | AJ53: 76930 | AL53: =34955*5/2 -> 87387.5 | AN53: =29383*5/2 -> 73457.5 | AP53: =34896*5/2 -> 87240 | AR53: =34999*5/2 -> 87497.5 | AT53: 81253 | AV53: 80562 | AX53: 84139 | AZ53: 80285 | BB53: 79464 | BD53: 77989 | BF53: 74863 | BH53: 78150 | BJ53: 74558 | BL53: 74747 | BN53: 72826 | BP53: 69942 | BR53: =AVERAGE(BJ53:BP53) -> 73018.25 | BT53: 69256 | BV53: 69545 | BX53: 69808 | BZ53: 70095 | CB53: =AVERAGE(BT53:BZ53) -> 69676 | CD53: 70286 | CF53: 69822 | CH53: 67939 | CJ53: 66779 | CL53: =AVERAGE(CD53:CJ53) -> 68706.5 | CN53: 66710 | CP53: 66684 | CR53: 66696 | CT53: 66332 | CV53: =AVERAGE(CN53:CT53) -> 66605.5 | CX53: 65995 | CZ53: 66028 | DB53: 66077 | DD53: 65844 | DF53: =AVERAGE(CX53:DD53) -> 65986 | DH53: 65699 | DJ53: 65945 | DL53: 65094 | DN53: 63678 | DP53: =AVERAGE(DH53:DN53) -> 65104 | DR53: 63353 | DT53: 62450 | DV53: 60030 | DX53: 58917 | DZ53: =AVERAGE(DR53:DX53) -> 61187.5 | EB53: 59252 | ED53: 59160 | EF53: 58882 | EJ53: =AVERAGE(EB53:EH53) -> 59098
A54: Diluted Shares Outstanding | B54: =34105.841*5/2 -> 85264.603 | D54: =34140*5/2 -> 85350 | F54: =34115.23*5/2 -> 85288.075 | H54: =34161*5/2 -> 85402.5 | J54: =34130.51775*5/2 -> 85326.294 | L54: =34236*5/2 -> 85590 | N54: =34545*5/2 -> 86362.5 | P54: =35113*5/2 -> 87782.5 | R54: =35352*5/2 -> 88380 | T54: =34788.693*5/2 -> 86971.732 | V54: =36374.964*5/2 -> 90937.41 | X54: =37195*5/2 -> 92987.5 | Z54: =37779.109*5/2 -> 94447.772 | AB54: =36965*5/2 -> 92412.5 | AD54: =37079*5/2 -> 92697.5 | AF54: =36321*5/2 -> 90802.5 | AH54: =36715*5/2 -> 91787.5 | AJ54: =36431*5/2 -> 91077.5 | AL54: =35917*5/2 -> 89792.5 | AN54: =36346*5/2 -> 90865 | AP54: =35936*5/2 -> 89840 | AR54: =36307*5/2 -> 90767.5 | AT54: 84406 | AV54: 83488 | AX54: 87208 | AZ54: 82887 | BB54: 81980 | BD54: 79928 | BF54: 76427 | BH54: 80247 | BJ54: 76072 | BL54: 76001 | BN54: 73713 | BP54: 70647 | BR54: =AVERAGE(BJ54:BP54) -> 74108.25 | BT54: 70250 | BV54: 70640 | BX54: 70853 | BZ54: 71191 | CB54: 70733 | CD54: 71338 | CF54: 70764 | CH54: 68587 | CJ54: 67213 | CL54: =AVERAGE(CD54:CJ54)-1 -> 69474.5 | CN54: 67175 | CP54: 67360 | CR54: 67473 | CT54: 66755 | CV54: =AVERAGE(CN54:CT54) -> 67190.75 | CX54: 66495 | CZ54: 66647 | DB54: 66693 | DD54: 66433 | DF54: =AVERAGE(CX54:DD54) -> 66567 | DH54: 66517 | DJ54: 66773 | DL54: 65746 | DN54: 64575 | DP54: =AVERAGE(DH54:DN54) -> 65902.75 | DR54: 64292 | DT54: 63148 | DV54: 60504 | DX54: 59611 | DZ54: =AVERAGE(DR54:DX54) -> 61888.75 | EB54: 59935 | ED54: 59578 | EF54: 59312 | EJ54: =AVERAGE(EB54:EH54) -> 59608.333
A56: Same Store Sales | B56: n/a | D56: n/a | F56: n/a | H56: n/a | L56: 0.141 | N56: 0.122 | P56: 0.14 | R56: 0.092 | T56: 0.121 | V56: 0.088 | X56: 0.087 | Z56: 0.045 | AB56: 0.097 | AD56: 0.08 | AF56: 0.077 | AH56: 0.066 | AJ56: 0.069 | AL56: 0.047 | AN56: 0.06 | AP56: 0.062 | AR56: 0.027 | AT56: 0.034 | AV56: 0.002 | AX56: 0.03 | AZ56: -0.013 | BB56: -0.023 | BD56: -0.055 | BF56: -0.037 | BH56: -0.036 | BJ56: -0.05 | BL56: -0.026 | BN56: -0.004 | BP56: -0.002 | BR56: -0.023 | BT56: 0.018 | BV56: 0.011 | BX56: 0.036 | BZ56: 0.01 | CB56: 0.019 | CD56: 0.029 | CF56: 0.027 | CH56: -0.018 | CJ56: 0.01 | CL56: 0.021 | CN56: 0.028 | CP56: 0.009 | CR56: 0.034 | CT56: 0 | CV56: 0.023 | CX56: -0.025 | CZ56: -0.062 | DB56: -0.061 | DD56: -0.032 | DF56: -0.035 | DH56: -0.005 | DJ56: 0.001 | DL56: 0.003 | DN56: 0 | DP56: -0.004 | DR56: 0.001 | DT56: -0.003 | DV56: 0.02 | DX56: 0.027 | DZ56: 0.008 | EB56: 0.071 | ED56: 0.028 | EF56: 0.012
B58: Quarter Ended | J58: FYE | L58: Quarter Ended | T58: FYE | V58: Quarter Ended | AD58: FYE | AF58: Quarter Ended | AN58: FYE | AP58: Quarter Ended | AX58: FYE | AZ58: Quarter Ended | BH58: FYE | BJ58: Quarter Ended | BR58: =BR6 -> FYE | BT58: Quarter Ended | CB58: =CB6 -> FYE | CD58: Quarter Ended | CL58: =CL6 -> FYE | CN58: Quarter Ended | CV58: =CV6 -> FYE | CX58: Quarter Ended | DF58: =DF6 -> FYE | DH58: Quarter Ended | DP58: =DP6 -> FYE | DR58: Quarter Ended | DZ58: =DZ6 -> FYE | EB58: Quarter Ended | EJ58: =EJ6 -> FYE
B59: 36250 | D59: 36341 | F59: 36433 | H59: 36525 | J59: 1999 | L59: 36616 | N59: 36707 | P59: 36799 | R59: 36891 | T59: 2000 | V59: 36981 | X59: 37072 | Z59: 37164 | AB59: 37256 | AD59: 2001 | AF59: 37346 | AH59: 37437 | AJ59: 37529 | AL59: 37621 | AN59: 2002 | AP59: 37711 | AR59: 37802 | AT59: 37894 | AV59: 37986 | AX59: 37986 | AZ59: 38077 | BB59: 38168 | BD59: 38260 | BF59: 38352 | BH59: 38352 | BJ59: =BJ7 -> 38442 | BL59: =BL7 -> 38533 | BN59: =BN7 -> 38625 | BP59: =BP7 -> 38717 | BR59: =BR7 -> 2005 | BT59: =BT7 -> 38807 | BV59: =BV7 -> 38898 | BX59: =BX7 -> 38990 | BZ59: =BZ7 -> 39082 | CB59: =CB7 -> 2006 | CD59: =CD7 -> 39172 | CF59: =CF7 -> 39263 | CH59: =CH7 -> 39355 | CJ59: =CJ7 -> 39447 | CL59: =CL7 -> 2007 | CN59: =CN7 -> 39538 | CP59: =CP7 -> 39629 | CR59: =CR7 -> 39721 | CT59: =CT7 -> 39813 | CV59: =CV7 -> 2008 | CX59: =CX7 -> 39903 | CZ59: =CZ7 -> 39994 | DB59: =DB7 -> 40086 | DD59: =DD7 -> 40178 | DF59: =DF7 -> 2009 | DH59: =DH7 -> 40268 | DJ59: =DJ7 -> 40359 | DL59: =DL7 -> 40451 | DN59: =DN7 -> 40543 | DP59: =DP7 -> 2010 | DR59: =DR7 -> 40633 | DT59: =DT7 -> 40724 | DV59: =DV7 -> 40816 | DX59: =DX7 -> 40908 | DZ59: =DZ7 -> 2011 | EB59: =EB7 -> 40999 | ED59: =ED7 -> 41090 | EF59: =EF7 -> 41182 | EH59: =EH7 -> 41274 | EJ59: =EJ7 -> 2012
A60: EBIT | B60: =B42 -> 23346 | D60: =D42 -> 26973 | F60: =F42 -> 30296.653 | H60: =H42 -> 34637.533 | J60: =J42 -> 115253.79 | L60: =L42 -> 39800.698 | N60: =N42 -> 43557 | P60: =P42 -> 45525 | R60: =R42 -> 43129 | T60: =T42 -> 172011.7 | V60: =V42 -> 46336.345 | X60: =X42 -> 50998.563 | Z60: =Z42 -> 33817 | AB60: =AB42 -> 45653.54 | AD60: =AD42 -> 176805.45 | AF60: =AF42 -> 73221 | AH60: =AH42 -> 75388 | AJ60: =AJ42 -> 69374 | AL60: =AL42 -> 75369 | AN60: =AN42 -> 293352 | AP60: =AP42 -> 83539 | AR60: =AR42 -> 85376 | AT60: =AT42 -> 77242 | AV60: =AV42 -> 79933 | AX60: =AX42 -> 326090 | AZ60: =AZ42 -> 83803 | BB60: =BB42 -> 81459 | BD60: =BD42 -> 62821 | BF60: =BF42 -> 66545 | BH60: =BH42 -> 294628 | BJ60: =BJ42 -> 68526 | BL60: =BL42 -> 63553 | BN60: =BN42 -> 41279 | BP60: =BP42 -> 51742 | BR60: =BR42 -> 225100 | BT60: =BT42 -> 63921 | BV60: =BV42 -> 63291 | BX60: =BX42 -> 55184 | BZ60: =BZ42 -> 59845 | CB60: =CB42 -> 242241 | CD60: =CD42 -> 75070 | CF60: =CF42 -> 65066 | CH60: =CH42 -> 34959 | CJ60: =CJ42 -> 38254 | CL60: =CL42 -> 213349 | CN60: =CN42 -> 61377 | CP60: =CP42 -> 59969 | CR60: =CR42 -> 45795 | CT60: =CT42 -> 49756 | CV60: =CV42 -> 216897 | CX60: =CX42 -> 70129 | CZ60: =CZ42 -> 65636 | DB60: =DB42 -> 59654 | DD60: =DD42 -> 70082 | DF60: =DF42 -> 265501 | DH60: =DH42 -> 82788 | DJ60: =DJ42 -> 76936 | DL60: =DL42 -> 63590 | DN60: =DN42 -> 73482 | DP60: =DP42 -> 296796 | DR60: =DR42 -> 80933 | DT60: =DT42 -> 68709 | DV60: =DV42 -> 56662 | DX60: =DX42 -> 74309 | DZ60: =DZ42 -> 280613 | EB60: =EB42 -> 83238 | ED60: =ED42 -> 70806 | EF60: =EF42 -> 60184 | EH60: =EH42 -> 0 | EJ60: =EJ42 -> 214228
A61: Plus: Interest Expense, net | B61: =B38+B39 -> 18356 | D61: =D38+D39 -> 18815 | F61: =F38+F39 -> 18662.861 | H61: =H38+H39 -> 18935.369 | J61: =J38+J39 -> 74769.23 | L61: =L38+L39 -> 18751.031 | N61: =N38+N39 -> 18244 | P61: =P38+P39 -> 18195 | R61: =R38+R39 -> 17428 | T61: =T38+T39 -> 72618.031 | V61: =V38+V39 -> 16148.953 | X61: =X38+X39 -> 15641.015 | Z61: =Z38+Z39 -> 14555 | AB61: =AB38+AB39 -> 13435.46 | AD61: =AD38+AD39 -> 59780.428 | AF61: =AF38+AF39 -> 15075 | AH61: =AH38+AH39 -> 14852 | AJ61: =AJ38+AJ39 -> 14713 | AL61: =AL38+AL39 -> 14457 | AN61: =AN38+AN39 -> 59097 | AP61: =AP38+AP39 -> 12752 | AR61: =AR38+AR39 -> 11862 | AT61: =AT38+AT39 -> 10260 | AV61: =AV38+AV39 -> 9058 | AX61: =AX38+AX39 -> 43932 | AZ61: =AZ38+AZ39 -> 8856 | BB61: =BB38+BB39 -> 8764 | BD61: =BD38+BD39 -> 8523 | BF61: =BF38+BF39 -> 9180 | BH61: =BH38+BH39 -> 35323 | BJ61: =BJ38+BJ39 -> 9466 | BL61: =BL38+BL39 -> 9435 | BN61: =BN38+BN39 -> 10471 | BP61: =BP38+BP39 -> 11331 | BR61: =BR38+BR39 -> 40703 | BT61: =BT38+BT39 -> 11563 | BV61: =BV38+BV39 -> 11902 | BX61: =BX38+BX39 -> 11987 | BZ61: =BZ38+BZ39 -> 17551 | CB61: =CB38+CB39 -> 53003 | CD61: =CD38+CD39 -> 22335 | CF61: =CF38+CF39 -> 21958 | CH61: =CH38+CH39 -> 21716 | CJ61: =CJ38+CJ39 -> 21942 | CL61: =CL38+CL39 -> 87951 | CN61: =CN38+CN39 -> 19063 | CP61: =CP38+CP39 -> 14450 | CR61: =CR38+CR39 -> 12967 | CT61: =CT38+CT39 -> 10901 | CV61: =CV38+CV39 -> 57381 | CX61: =CX38+CX39 -> 8963 | CZ61: =CZ38+CZ39 -> 7778 | DB61: =DB38+DB39 -> 4713 | DD61: =DD38+DD39 -> 4500 | DF61: =DF38+DF39 -> 25954 | DH61: =DH38+DH39 -> 5915 | DJ61: =DJ38+DJ39 -> 5895 | DL61: =DL38+DL39 -> 5803 | DN61: =DN38+DN39 -> 8299 | DP61: =DP38+DP39 -> 25912 | DR61: =DR38+DR39 -> 9606 | DT61: =DT38+DT39 -> 9376 | DV61: =DV38+DV39 -> 8720 | DX61: =DX38+DX39 -> 8905 | DZ61: =DZ38+DZ39 -> 36607 | EB61: =EB38+EB39 -> 8796 | ED61: =ED38+ED39 -> 8221 | EF61: =EF38+EF39 -> 7929 | EH61: =EH38+EH39 -> 0 | EJ61: =EJ38+EJ39 -> 24946
A62: Plus: Amortization | B62: =B32 -> 6390 | D62: =D32 -> 6856 | F62: =F32 -> 6845.349 | H62: =H32 -> 7024.651 | J62: =J32 -> 27116 | L62: =L32 -> 6974.5302 | N62: =N32 -> 6955 | P62: =P32 -> 7168 | R62: =R32 -> 7205 | T62: =T32 -> 28302.53 | V62: =V32 -> 7268 | X62: =X32 -> 7396.1364 | Z62: =Z32 -> 7738 | AB62: =AB32 -> 7792 | AD62: =AD32 -> 30194.136 | AF62: =AF32 -> 720 | AH62: =AH32 -> 922 | AJ62: =AJ32 -> 1557 | AL62: =AL32 -> 1846 | AN62: =AN32 -> 5045 | AP62: =AP32 -> 2873 | AR62: =AR32 -> 3296 | AT62: =AT32 -> 3183 | AV62: =AV32 -> 3160 | AX62: =AX32 -> 12512 | AZ62: =AZ32 -> 2488 | BB62: =BB32 -> 3158 | BD62: =BD32 -> 2756 | BF62: =BF32 -> 2378 | BH62: =BH32 -> 10780 | BJ62: =BJ32 -> 2297 | BL62: =BL32 -> 2155 | BN62: =BN32 -> 2259 | BP62: =BP32 -> 1327 | BR62: =BR32 -> 8038 | BT62: =BT32 -> 886 | BV62: =BV32 -> 950 | BX62: =BX32 -> 1009 | BZ62: =BZ32 -> 2728 | CB62: =CB32 -> 5573 | CD62: =CD32 -> 4038 | CF62: =CF32 -> 3934 | CH62: =CH32 -> 3953 | CJ62: =CJ32 -> 3809 | CL62: =CL32 -> 15734 | CN62: =CN32 -> 4930 | CP62: =CP32 -> 3662 | CR62: =CR32 -> 3545 | CT62: =CT32 -> 4500 | CV62: =CV32 -> 16637 | CX62: =CX32 -> 337 | CZ62: =CZ32 -> 1506 | DB62: =DB32 -> 585 | DD62: =DD32 -> 415 | DF62: =DF32 -> 2843 | DH62: =DH32 -> 1051 | DJ62: =DJ32 -> 1540 | DL62: =DL32 -> 529 | DN62: =DN32 -> 134 | DP62: =DP32 -> 3254 | DR62: =DR32 -> 858 | DT62: =DT32 -> 1132 | DV62: =DV32 -> 1261 | DX62: =DX32 -> 1424 | DZ62: =DZ32 -> 4675 | EB62: =EB32 -> 1335 | ED62: =ED32 -> 1481 | EF62: =EF32 -> 2447 | EH62: =EH32 -> 0 | EJ62: =EJ32 -> 5263
A63: Plus: Depreciation | B63: 7663 | D63: 7749 | F63: =7892-0.4 -> 7891.6 | H63: 8009.0799 | J63: =B63+D63+F63+H63 -> 31312.68 | L63: 8102.767 | N63: 8250.233 | P63: 8309 | R63: 8482 | T63: =L63+N63+P63+R63+0.4 -> 33144.4 | V63: 8804.8978 | X63: 9507.0538 | Z63: 9793.8285 | AB63: 9803.901 | AD63: =V63+X63+Z63+AB63 -> 37909.681 | AF63: 9465.574 | AH63: 9412 | AJ63: 9647 | AL63: 9834 | AN63: =AF63+AH63+AJ63+AL63 -> 38358.574 | AP63: 10120 | AR63: 10833 | AT63: 11116 | AV63: 11316 | AX63: =AP63+AR63+AT63+AV63-0.6 -> 43384.4 | AZ63: 11249 | BB63: 11834 | BD63: 12508 | BF63: 12975 | BH63: =AZ63+BB63+BD63+BF63 -> 48566 | BJ63: 13263 | BL63: 13271 | BN63: 13484 | BP63: 13364 | BR63: =BJ63+BL63+BN63+BP63 -> 53382 | BT63: 13467 | BV63: 13527 | BX63: 13486 | BZ63: 15171 | CB63: =BT63+BV63+BX63+BZ63 -> 55651 | CD63: 16927 | CF63: 17650 | CH63: 18028 | CJ63: 18674 | CL63: =CD63+CF63+CH63+CJ63 -> 71279 | CN63: 18188 | CP63: 18190 | CR63: 18191 | CT63: 18114 | CV63: =CN63+CP63+CR63+CT63 -> 72683 | CX63: 17576 | CZ63: 16557 | DB63: 16054 | DD63: 15601 | DF63: =CX63+CZ63+DB63+DD63 -> 65788 | DH63: 15721 | DJ63: 15802 | DL63: 15629 | DN63: 16258 | DP63: =DH63+DJ63+DL63+DN63 -> 63410 | DR63: 15678 | DT63: 16153 | DV63: 16107 | DX63: 17276 | DZ63: =DR63+DT63+DV63+DX63 -> 65214 | EB63: 17994 | ED63: 18338 | EF63: 18412 | EH63: 0 | EJ63: =EB63+ED63+EF63+EH63 -> 54744
A64: EBITDA | B64: =SUM(B60:B63) -> 55755 | D64: =SUM(D60:D63) -> 60393 | F64: =SUM(F60:F63) -> 63696.463 | H64: =SUM(H60:H63) -> 68606.633 | J64: =SUM(J60:J63) -> 248451.7 | L64: =SUM(L60:L63) -> 73629.026 | N64: =SUM(N60:N63) -> 77006.233 | P64: =SUM(P60:P63) -> 79197 | R64: =SUM(R60:R63) -> 76244 | T64: =SUM(T60:T63) -> 306076.66 | V64: =SUM(V60:V63) -> 78558.196 | X64: =SUM(X60:X63) -> 83542.769 | Z64: =SUM(Z60:Z63) -> 65903.828 | AB64: =SUM(AB60:AB63) -> 76684.901 | AD64: =SUM(AD60:AD63) -> 304689.69 | AF64: =SUM(AF60:AF63) -> 98481.574 | AH64: =SUM(AH60:AH63) -> 100574 | AJ64: =SUM(AJ60:AJ63) -> 95291 | AL64: =SUM(AL60:AL63) -> 101506 | AN64: =SUM(AN60:AN63) -> 395852.57 | AP64: =SUM(AP60:AP63) -> 109284 | AR64: =SUM(AR60:AR63) -> 111367 | AT64: =SUM(AT60:AT63) -> 101801 | AV64: =SUM(AV60:AV63) -> 103467 | AX64: =SUM(AX60:AX63) -> 425918.4 | AZ64: =SUM(AZ60:AZ63) -> 106396 | BB64: =SUM(BB60:BB63) -> 105215 | BD64: =SUM(BD60:BD63) -> 86608 | BF64: =SUM(BF60:BF63) -> 91078 | BH64: =SUM(BH60:BH63) -> 389297 | BJ64: =SUM(BJ60:BJ63) -> 93552 | BL64: =SUM(BL60:BL63) -> 88414 | BN64: =SUM(BN60:BN63) -> 67493 | BP64: =SUM(BP60:BP63) -> 77764 | BR64: =SUM(BR60:BR63) -> 327223 | BT64: =SUM(BT60:BT63) -> 89837 | BV64: =SUM(BV60:BV63) -> 89670 | BX64: =SUM(BX60:BX63) -> 81666 | BZ64: =SUM(BZ60:BZ63) -> 95295 | CB64: =SUM(CB60:CB63) -> 356468 | CD64: =SUM(CD60:CD63) -> 118370 | CF64: =SUM(CF60:CF63) -> 108608 | CH64: =SUM(CH60:CH63) -> 78656 | CJ64: =SUM(CJ60:CJ63) -> 82679 | CL64: =SUM(CL60:CL63) -> 388313 | CN64: =SUM(CN60:CN63) -> 103558 | CP64: =SUM(CP60:CP63) -> 96271 | CR64: =SUM(CR60:CR63) -> 80498 | CT64: =SUM(CT60:CT63) -> 83271 | CV64: =SUM(CV60:CV63) -> 363598 | CX64: =SUM(CX60:CX63) -> 97005 | CZ64: =SUM(CZ60:CZ63) -> 91477 | DB64: =SUM(DB60:DB63) -> 81006 | DD64: =SUM(DD60:DD63) -> 90598 | DF64: =SUM(DF60:DF63) -> 360086 | DH64: =SUM(DH60:DH63) -> 105475 | DJ64: =SUM(DJ60:DJ63) -> 100173 | DL64: =SUM(DL60:DL63) -> 85551 | DN64: =SUM(DN60:DN63) -> 98173 | DP64: =SUM(DP60:DP63) -> 389372 | DR64: =SUM(DR60:DR63) -> 107075 | DT64: =SUM(DT60:DT63) -> 95370 | DV64: =SUM(DV60:DV63) -> 82750 | DX64: =SUM(DX60:DX63) -> 101914 | DZ64: =SUM(DZ60:DZ63) -> 387109 | EB64: =SUM(EB60:EB63) -> 111363 | ED64: =SUM(ED60:ED63) -> 98846 | EF64: =SUM(EF60:EF63) -> 88972 | EH64: =SUM(EH60:EH63) -> 0 | EJ64: =SUM(EJ60:EJ63) -> 299181
A65: EBITDA Margin | B65: =B64/B19 -> 0.16175076 | D65: =D64/D19 -> 0.1718537 | F65: =F64/F19 -> 0.18177197 | H65: =H64/H19 -> 0.18510879 | J65: =J64/J19 -> 0.17531577 | L65: =L64/L19 -> 0.18757735 | N65: =N64/N19 -> 0.19632177 | P65: =P64/P19 -> 0.1955636 | R65: =R64/R19 -> 0.18511442 | T65: =T64/T19 -> 0.19110516 | V65: =V64/V19 -> 0.17866222 | X65: =X64/X19 -> 0.18868688 | Z65: =Z64/Z19 -> 0.14741145 | AB65: =AB64/AB19 -> 0.16009608 | AD65: =AD64/AD19 -> 0.1684739 | AF65: =AF64/AF19 -> 0.19751223 | AH65: =AH64/AH19 -> 0.20331945 | AJ65: =AJ64/AJ19 -> 0.19267795 | AL65: =AL64/AL19 -> 0.19437662 | AN65: =AN64/AN19 -> 0.19693727 | AP65: =AP64/AP19 -> 0.19294287 | AR65: =AR64/AR19 -> 0.20129234 | AT65: =AT64/AT19 -> 0.18515164 | AV65: =AV64/AV19 -> 0.185206 | AX65: =AX64/AX19 -> 0.19115338 | AZ65: =AZ64/AZ19 -> 0.18175544 | BB65: =BB64/BB19 -> 0.1836261 | BD65: =BD64/BD19 -> 0.15204869 | BF65: =BF64/BF19 -> 0.15561361 | BH65: =BH64/BH19 -> 0.1682897 | BJ65: =BJ64/BJ19 -> 0.15545131 | BL65: =BL64/BL19 -> 0.15228617 | BN65: =BN64/BN19 -> 0.1176847 | BP65: =BP64/BP19 -> 0.13333722 | BR65: =BR64/BR19 -> 0.13989228 | BT65: =BT64/BT19 -> 0.14800774 | BV65: =BV64/BV19 -> 0.1536437 | BX65: =BX64/BX19 -> 0.13908077 | BZ65: =BZ64/BZ19 -> 0.14523887 | CB65: =CB64/CB19 -> 0.14645911 | CD65: =CD64/CD19 -> 0.15671939 | CF65: =IF(ISERROR(CF64/CF19),0,(CF64/CF19)) -> 0.14997832 | CH65: =IF(ISERROR(CH64/CH19),0,(CH64/CH19)) -> 0.11144218 | CJ65: =IF(ISERROR(CJ64/CJ19),0,(CJ64/CJ19)) -> 0.11531836 | CL65: =CL64/CL19 -> 0.13379856 | CN65: =CN64/CN19 -> 0.13686634 | CP65: =IF(ISERROR(CP64/CP19),0,(CP64/CP19)) -> 0.13388992 | CR65: =IF(ISERROR(CR64/CR19),0,(CR64/CR19)) -> 0.11357662 | CT65: =IF(ISERROR(CT64/CT19),0,(CT64/CT19)) -> 0.11900107 | CV65: =CV64/CV19 -> 0.12606668 | CX65: =CX64/CX19 -> 0.13321514 | CZ65: =IF(ISERROR(CZ64/CZ19),0,(CZ64/CZ19)) -> 0.1346024 | DB65: =IF(ISERROR(DB64/DB19),0,(DB64/DB19)) -> 0.12067915 | DD65: =IF(ISERROR(DD64/DD19),0,(DD64/DD19)) -> 0.13463553 | DF65: =DF64/DF19 -> 0.1308473 | DH65: =DH64/DH19 -> 0.14681544 | DJ65: =IF(ISERROR(DJ64/DJ19),0,(DJ64/DJ19)) -> 0.14916841 | DL65: =IF(ISERROR(DL64/DL19),0,(DL64/DL19)) -> 0.12872942 | DN65: =IF(ISERROR(DN64/DN19),0,(DN64/DN19)) -> 0.14499254 | DP65: =DP64/DP19 -> 0.14254189 | DR65: =DR64/DR19 -> 0.14427132 | DT65: =IF(ISERROR(DT64/DT19),0,(DT64/DT19)) -> 0.13658373 | DV65: =IF(ISERROR(DV64/DV19),0,(DV64/DV19)) -> 0.11749738 | DX65: =IF(ISERROR(DX64/DX19),0,(DX64/DX19)) -> 0.13819185 | DZ65: =DZ64/DZ19 -> 0.13431099 | EB65: =EB64/EB19 -> 0.1333283 | ED65: =IF(ISERROR(ED64/ED19),0,(ED64/ED19)) -> 0.13184776 | EF65: =IF(ISERROR(EF64/EF19),0,(EF64/EF19)) -> 0.12034399 | EH65: =IF(ISERROR(EH64/EH19),0,(EH64/EH19)) -> 0 | EJ65: =EJ64/EJ19 -> 0.12872064
B67: Quarter Ended | J67: FYE | L67: Quarter Ended | T67: FYE | V67: Quarter Ended | AD67: FYE | AF67: Quarter Ended | AN67: FYE | AP67: Quarter Ended | AX67: FYE | AZ67: Quarter Ended | BH67: FYE | BJ67: Quarter Ended | BR67: =BR6 -> FYE | BT67: Quarter Ended | CB67: =CB6 -> FYE | CD67: Quarter Ended | CL67: =CL6 -> FYE | CN67: Quarter Ended | CV67: =CV6 -> FYE | CX67: Quarter Ended | DF67: =DF6 -> FYE | DH67: Quarter Ended | DP67: =DP6 -> FYE | DR67: Quarter Ended | DZ67: =DZ6 -> FYE | EB67: Quarter Ended | EJ67: =EJ6 -> FYE
A68: Margin Data: | B68: 36250 | D68: 36341 | F68: 36433 | H68: 36525 | J68: 1999 | L68: 36616 | N68: 36707 | P68: 36799 | R68: 36891 | T68: 2000 | V68: 36981 | X68: 37072 | Z68: 37164 | AB68: 37256 | AD68: 2001 | AF68: 37346 | AH68: 37437 | AJ68: 37529 | AL68: 37621 | AN68: 2002 | AP68: 37711 | AR68: 37802 | AT68: 37894 | AV68: 37986 | AX68: 37986 | AZ68: 38077 | BB68: 38168 | BD68: 38260 | BF68: 38352 | BH68: 38352 | BJ68: =BJ7 -> 38442 | BL68: =BL7 -> 38533 | BN68: =BN7 -> 38625 | BP68: =BP7 -> 38717 | BR68: =BR7 -> 2005 | BT68: =BT7 -> 38807 | BV68: =BV7 -> 38898 | BX68: =BX7 -> 38990 | BZ68: =BZ7 -> 39082 | CB68: =CB7 -> 2006 | CD68: =CD7 -> 39172 | CF68: =CF7 -> 39263 | CH68: =CH7 -> 39355 | CJ68: =CJ7 -> 39447 | CL68: =CL7 -> 2007 | CN68: =CN7 -> 39538 | CP68: =CP7 -> 39629 | CR68: =CR7 -> 39721 | CT68: =CT7 -> 39813 | CV68: =CV7 -> 2008 | CX68: =CX7 -> 39903 | CZ68: =CZ7 -> 39994 | DB68: =DB7 -> 40086 | DD68: =DD7 -> 40178 | DF68: =DF7 -> 2009 | DH68: =DH7 -> 40268 | DJ68: =DJ7 -> 40359 | DL68: =DL7 -> 40451 | DN68: =DN7 -> 40543 | DP68: =DP7 -> 2010 | DR68: =DR7 -> 40633 | DT68: =DT7 -> 40724 | DV68: =DV7 -> 40816 | DX68: =DX7 -> 40908 | DZ68: =DZ7 -> 2011 | EB68: =EB7 -> 40999 | ED68: =ED7 -> 41090 | EF68: =EF7 -> 41182 | EH68: =EH7 -> 41274 | EJ68: =EJ7 -> 2012
A69: Cost of rental & fees / Rental & Fee Revenue | B69: =B23/B9 -> 0.21367088 | D69: =D23/D9 -> 0.2101411 | F69: =F23/F9 -> 0.20718861 | H69: =H23/H9 -> 0.20505055 | J69: =J23/J9 -> 0.20889857 | L69: =L23/L9 -> 0.20475068 | N69: =N23/N9 -> 0.20487915 | P69: =P23/P9 -> 0.2068034 | R69: =R23/R9 -> 0.20374288 | T69: =T23/T9 -> 0.20504578 | V69: =V23/V9 -> 0.20556451 | X69: =X23/X9 -> 0.20604205 | Z69: =Z23/Z9 -> 0.20960459 | AB69: =AB23/AB9 -> 0.21009957 | AD69: =AD23/AD9 -> 0.20789107 | AF69: =AF23/AF9 -> 0.20784756 | AH69: =AH23/AH9 -> 0.20684908 | AJ69: =AJ23/AJ9 -> 0.20935187 | AL69: =AL23/AL9 -> 0.21443599 | AN69: =AN23/AN9 -> 0.20967617 | AP69: =AP23/AP9 -> 0.21616517 | AR69: =AR23/AR9 -> 0.21679502 | AT69: =AT23/AT9 -> 0.21647141 | AV69: =AV23/AV9 -> 0.21640771 | AX69: =AX23/AX9 -> 0.21646143 | AZ69: =AZ23/AZ9 -> 0.21523925 | BB69: =BB23/BB9 -> 0.21656649 | BD69: =BD23/BD9 -> 0.21793889 | BF69: =BF23/BF9 -> 0.21901483 | BH69: =BH23/BH9 -> 0.21721241 | BJ69: =BJ23/BJ9 -> 0.21685929 | BL69: =BL23/BL9 -> 0.21659619 | BN69: =BN23/BN9 -> 0.2172092 | BP69: =BP23/BP9 -> 0.21770418 | BR69: =BR23/BR9 -> 0.21709149 | BT69: =BT23/BT9 -> 0.21670001 | BV69: =BV23/BV9 -> 0.21767829 | BX69: =BX23/BX9 -> 0.2198512 | BZ69: =BZ23/BZ9 -> 0.22193366 | CB69: =CB23/CB9 -> 0.21913966 | CD69: =CD23/CD9 -> 0.2167341 | CF69: =IF(ISERROR(CF23/CF9),0,(CF23/CF9)) -> 0.22040157 | CH69: =IF(ISERROR(CH23/CH9),0,(CH23/CH9)) -> 0.22217064 | CJ69: =IF(ISERROR(CJ23/CJ9),0,(CJ23/CJ9)) -> 0.22599263 | CL69: =CL23/CL9 -> 0.22127968 | CN69: =CN23/CN9 -> 0.22813359 | CP69: =IF(ISERROR(CP23/CP9),0,(CP23/CP9)) -> 0.22928912 | CR69: =IF(ISERROR(CR23/CR9),0,(CR23/CR9)) -> 0.22906211 | CT69: =IF(ISERROR(CT23/CT9),0,(CT23/CT9)) -> 0.22822233 | CV69: =CV23/CV9 -> 0.22867813 | CX69: =CX23/CX9 -> 0.22613356 | CZ69: =IF(ISERROR(CZ23/CZ9),0,(CZ23/CZ9)) -> 0.22555253 | DB69: =IF(ISERROR(DB23/DB9),0,(DB23/DB9)) -> 0.22596351 | DD69: =IF(ISERROR(DD23/DD9),0,(DD23/DD9)) -> 0.22571747 | DF69: =DF23/DF9 -> 0.2258424 | DH69: =DH23/DH9 -> 0.22285595 | DJ69: =IF(ISERROR(DJ23/DJ9),0,(DJ23/DJ9)) -> 0.22133488 | DL69: =IF(ISERROR(DL23/DL9),0,(DL23/DL9)) -> 0.2214736 | DN69: =IF(ISERROR(DN23/DN9),0,(DN23/DN9)) -> 0.22368979 | DP69: =DP23/DP9 -> 0.22234335 | DR69: =DR23/DR9 -> 0.22221949 | DT69: =IF(ISERROR(DT23/DT9),0,(DT23/DT9)) -> 0.22547087 | DV69: =IF(ISERROR(DV23/DV9),0,(DV23/DV9)) -> 0.22940075 | DX69: =IF(ISERROR(DX23/DX9),0,(DX23/DX9)) -> 0.23639937 | DZ69: =DZ23/DZ9 -> 0.2284839 | EB69: =EB23/EB9 -> 0.24094923 | ED69: =IF(ISERROR(ED23/ED9),0,(ED23/ED9)) -> 0.24247823 | EF69: =IF(ISERROR(EF23/EF9),0,(EF23/EF9)) -> 0.24354391 | EH69: =IF(ISERROR(EH23/EH9),0,(EH23/EH9)) -> 0 | EJ69: =EJ23/EJ9 -> 0.24230641
A70: Cost of merchandise sold / Merchandise sales | B70: =B24/B10 -> 0.81277049 | D70: =D24/D10 -> 0.85852264 | F70: =F24/F10 -> 0.83935796 | H70: =H24/H10 -> 0.85006418 | J70: =J24/J10 -> 0.83631193 | L70: =L24/L10 -> 0.83508237 | N70: =N24/N10 -> 0.82386878 | P70: =P24/P10 -> 0.75967597 | R70: =R24/R10 -> 0.78725377 | T70: =T24/T10 -> 0.80492223 | V70: =V24/V10 -> 0.7007686 | X70: =X24/X10 -> 0.76794527 | Z70: =Z24/Z10 -> 0.79632806 | AB70: =AB24/AB10 -> 0.82371148 | AD70: =AD24/AD10 -> 0.76571868 | AF70: =AF24/AF10 -> 0.68127762 | AH70: =AH24/AH10 -> 0.72922397 | AJ70: =AJ24/AJ10 -> 0.74751113 | AL70: =AL24/AL10 -> 0.79789466 | AN70: =AN24/AN10 -> 0.73284955 | AP70: =AP24/AP10 -> 0.69398451 | AR70: =AR24/AR10 -> 0.74505042 | AT70: =AT24/AT10 -> 0.75177778 | AV70: =AV24/AV10 -> 0.76783947 | AX70: =AX24/AX10 -> 0.73395257 | AZ70: =AZ24/AZ10 -> 0.66275684 | BB70: =BB24/BB10 -> 0.71447152 | BD70: =BD24/BD10 -> 0.74391286 | BF70: =BF24/BF10 -> 0.77166938 | BH70: =BH24/BH10 -> 0.7148997 | BJ70: =BJ24/BJ10 -> 0.67017684 | BL70: =BL24/BL10 -> 0.75270681 | BN70: =BN24/BN10 -> 0.77307967 | BP70: =BP24/BP10 -> 0.76742833 | BR70: =BR24/BR10 -> 0.73113282 | BT70: =BT24/BT10 -> 0.68777956 | BV70: =BV24/BV10 -> 0.73912251 | BX70: =BX24/BX10 -> 0.78204881 | BZ70: =BZ24/BZ10 -> 0.82314965 | CB70: =CB24/CB10 -> 0.74694522 | CD70: =CD24/CD10 -> 0.67357361 | CF70: =IF(ISERROR(CF24/CF10),0,(CF24/CF10)) -> 0.75656831 | CH70: =IF(ISERROR(CH24/CH10),0,(CH24/CH10)) -> 0.76650987 | CJ70: =IF(ISERROR(CJ24/CJ10),0,(CJ24/CJ10)) -> 0.83084179 | CL70: =CL24/CL10 -> 0.7488576 | CN70: =CN24/CN10 -> 0.74204057 | CP70: =IF(ISERROR(CP24/CP10),0,(CP24/CP10)) -> 0.81085399 | CR70: =IF(ISERROR(CR24/CR10),0,(CR24/CR10)) -> 0.7836038 | CT70: =IF(ISERROR(CT24/CT10),0,(CT24/CT10)) -> 0.70597165 | CV70: =CV24/CV10 -> 0.75797235 | CX70: =CX24/CX10 -> 0.68663214 | CZ70: =IF(ISERROR(CZ24/CZ10),0,(CZ24/CZ10)) -> 0.73731983 | DB70: =IF(ISERROR(DB24/DB10),0,(DB24/DB10)) -> 0.7267496 | DD70: =IF(ISERROR(DD24/DD10),0,(DD24/DD10)) -> 0.75753438 | DF70: =DF24/DF10 -> 0.72022429 | DH70: =DH24/DH10 -> 0.69142141 | DJ70: =IF(ISERROR(DJ24/DJ10),0,(DJ24/DJ10)) -> 0.75766308 | DL70: =IF(ISERROR(DL24/DL10),0,(DL24/DL10)) -> 0.78478986 | DN70: =IF(ISERROR(DN24/DN10),0,(DN24/DN10)) -> 0.80167168 | DP70: =DP24/DP10 -> 0.74494506 | DR70: =DR24/DR10 -> 0.69086092 | DT70: =IF(ISERROR(DT24/DT10),0,(DT24/DT10)) -> 0.77511624 | DV70: =IF(ISERROR(DV24/DV10),0,(DV24/DV10)) -> 0.81758267 | DX70: =IF(ISERROR(DX24/DX10),0,(DX24/DX10)) -> 0.89146331 | DZ70: =DZ24/DZ10 -> 0.77697116 | EB70: =EB24/EB10 -> 0.77337436 | ED70: =IF(ISERROR(ED24/ED10),0,(ED24/ED10)) -> 0.81694764 | EF70: =IF(ISERROR(EF24/EF10),0,(EF24/EF10)) -> 0.80703096 | EH70: =IF(ISERROR(EH24/EH10),0,(EH24/EH10)) -> 0 | EJ70: =EJ24/EJ10 -> 0.79244847
A72: Store Gross Profit Margin | B72: =(B13-B23-B24-B25)/B13 -> 0.72976011 | D72: =(D13-D23-D24-D25)/D13 -> 0.75109375 | F72: =(F13-F23-F24-F25)/F13 -> 0.75807135 | H72: =(H13-H23-H24-H25)/H13 -> 0.76291819 | J72: =(J13-J23-J24-J25)/J13 -> 0.75064724 | L72: =(L13-L23-L24-L25)/L13 -> 0.74994503 | N72: =(N13-N23-N24-N25)/N13 -> 0.76647226 | P72: =(P13-P23-P24-P25)/P13 -> 0.76705906 | R72: =(R13-R23-R24-R25)/R13 -> 0.77133318 | T72: =(T13-T23-T24-T25)/T13 -> 0.76381727 | V72: =(V13-V23-V24-V25)/V13 -> 0.75925589 | X72: =(X13-X23-X24-X25)/X13 -> 0.7681146 | Z72: =(Z13-Z23-Z24-Z25)/Z13 -> 0.76150882 | AB72: =(AB13-AB23-AB24-AB25)/AB13 -> 0.76045878 | AD72: =(AD13-AD23-AD24-AD25)/AD13 -> 0.76230884 | AF72: =(AF13-AF23-AF24-AF25)/AF13 -> 0.75367 | AH72: =(AH13-AH23-AH24-AH25)/AH13 -> 0.76732125 | AJ72: =(AJ13-AJ23-AJ24-AJ25)/AJ13 -> 0.76327316 | AL72: =(AL13-AL23-AL24-AL25)/AL13 -> 0.74977745 | AN72: =(AN13-AN23-AN24-AN25)/AN13 -> 0.75838848 | AP72: =(AP13-AP23-AP24-AP25)/AP13 -> 0.73511648 | AR72: =(AR13-AR23-AR24-AR25)/AR13 -> 0.74989538 | AT72: =(AT13-AT23-AT24-AT25)/AT13 -> 0.74742962 | AV72: =(AV13-AV23-AV24-AV25)/AV13 -> 0.74697673 | AX72: =(AX13-AX23-AX24-AX25)/AX13 -> 0.74480416 | AZ72: =(AZ13-AZ23-AZ24-AZ25)/AZ13 -> 0.73565463 | BB72: =(BB13-BB23-BB24-BB25)/BB13 -> 0.75097872 | BD72: =(BD13-BD23-BD24-BD25)/BD13 -> 0.7465439 | BF72: =(BF13-BF23-BF24-BF25)/BF13 -> 0.74393186 | BH72: =(BH13-BH23-BH24-BH25)/BH13 -> 0.7442365 | BJ72: =(BJ13-BJ23-BJ24-BJ25)/BJ13 -> 0.7327953 | BL72: =(BL13-BL23-BL24-BL25)/BL13 -> 0.74631833 | BN72: =(BN13-BN23-BN24-BN25)/BN13 -> 0.74326451 | BP72: =(BP13-BP23-BP24-BP25)/BP13 -> 0.74468992 | BR72: =(BR13-BR23-BR24-BR25)/BR13 -> 0.74169316 | BT72: =(BT13-BT23-BT24-BT25)/BT13 -> 0.7316413 | BV72: =(BV13-BV23-BV24-BV25)/BV13 -> 0.74667094 | BX72: =(BX13-BX23-BX24-BX25)/BX13 -> 0.74393049 | BZ72: =(BZ13-BZ23-BZ24-BZ25)/BZ13 -> 0.74265554 | CB72: =(CB13-CB23-CB24-CB25)/CB13 -> 0.74119532 | CD72: =(CD13-CD23-CD24-CD25)/CD13 -> 0.74108242 | CF72: =IF(ISERROR((CF13-CF23-CF24-CF25)/CF13),0,(CF13-CF23-CF24-CF25)/CF13) -> 0.74995809 | CH72: =IF(ISERROR((CH13-CH23-CH24-CH25)/CH13),0,(CH13-CH23-CH24-CH25)/CH13) -> 0.73594994 | CJ72: =IF(ISERROR((CJ13-CJ23-CJ24-CJ25)/CJ13),0,(CJ13-CJ23-CJ24-CJ25)/CJ13) -> 0.73364195 | CL72: =(CL13-CL23-CL24-CL25)/CL13 -> 0.74021727 | CN72: =(CN13-CN23-CN24-CN25)/CN13 -> 0.71361677 | CP72: =IF(ISERROR((CP13-CP23-CP24-CP25)/CP13),0,(CP13-CP23-CP24-CP25)/CP13) -> 0.72616158 | CR72: =IF(ISERROR((CR13-CR23-CR24-CR25)/CR13),0,(CR13-CR23-CR24-CR25)/CR13) -> 0.72685782 | CT72: =IF(ISERROR((CT13-CT23-CT24-CT25)/CT13),0,(CT13-CT23-CT24-CT25)/CT13) -> 0.73207067 | CV72: =(CV13-CV23-CV24-CV25)/CV13 -> 0.7244805 | CX72: =(CX13-CX23-CX24-CX25)/CX13 -> 0.7143948 | CZ72: =IF(ISERROR((CZ13-CZ23-CZ24-CZ25)/CZ13),0,(CZ13-CZ23-CZ24-CZ25)/CZ13) -> 0.73337896 | DB72: =IF(ISERROR((DB13-DB23-DB24-DB25)/DB13),0,(DB13-DB23-DB24-DB25)/DB13) -> 0.73224826 | DD72: =IF(ISERROR((DD13-DD23-DD24-DD25)/DD13),0,(DD13-DD23-DD24-DD25)/DD13) -> 0.73674113 | DF72: =(DF13-DF23-DF24-DF25)/DF13 -> 0.72890528 | DH72: =(DH13-DH23-DH24-DH25)/DH13 -> 0.72153804 | DJ72: =IF(ISERROR((DJ13-DJ23-DJ24-DJ25)/DJ13),0,(DJ13-DJ23-DJ24-DJ25)/DJ13) -> 0.74769583 | DL72: =IF(ISERROR((DL13-DL23-DL24-DL25)/DL13),0,(DL13-DL23-DL24-DL25)/DL13) -> 0.74422403 | DN72: =IF(ISERROR((DN13-DN23-DN24-DN25)/DN13),0,(DN13-DN23-DN24-DN25)/DN13) -> 0.73924937 | DP72: =(DP13-DP23-DP24-DP25)/DP13 -> 0.73788369 | DR72: =(DR13-DR23-DR24-DR25)/DR13 -> 0.71262778 | DT72: =IF(ISERROR((DT13-DT23-DT24-DT25)/DT13),0,(DT13-DT23-DT24-DT25)/DT13) -> 0.73211377 | DV72: =IF(ISERROR((DV13-DV23-DV24-DV25)/DV13),0,(DV13-DV23-DV24-DV25)/DV13) -> 0.72459186 | DX72: =IF(ISERROR((DX13-DX23-DX24-DX25)/DX13),0,(DX13-DX23-DX24-DX25)/DX13) -> 0.71003419 | DZ72: =(DZ13-DZ23-DZ24-DZ25)/DZ13 -> 0.71961849 | EB72: =(EB13-EB23-EB24-EB25)/EB13 -> 0.67850892 | ED72: =IF(ISERROR((ED13-ED23-ED24-ED25)/ED13),0,(ED13-ED23-ED24-ED25)/ED13) -> 0.70952539 | EF72: =IF(ISERROR((EF13-EF23-EF24-EF25)/EF13),0,(EF13-EF23-EF24-EF25)/EF13) -> 0.70974545 | EH72: =IF(ISERROR((EH13-EH23-EH24-EH25)/EH13),0,(EH13-EH23-EH24-EH25)/EH13) -> 0 | EJ72: =(EJ13-EJ23-EJ24-EJ25)/EJ13 -> 0.69845874
A74: Salaries & other expenses / Rental & Fee Revenue | B74: =B26/B9 -> 0.61791738 | D74: =D26/D9 -> 0.60628355 | F74: =F26/F9 -> 0.60293126 | H74: =H26/H9 -> 0.59915584 | J74: =J26/J9 -> 0.60632755 | L74: =L26/L9 -> 0.59524054 | N74: =N26/N9 -> 0.58663287 | P74: =P26/P9 -> 0.58859781 | R74: =R26/R9 -> 0.60308987 | T74: =T26/T9 -> 0.59344747 | V74: =V26/V9 -> 0.61613937 | X74: =X26/X9 -> 0.59743526 | Z74: =Z26/Z9 -> 0.63707656 | AB74: =AB26/AB9 -> 0.6190818 | AD74: =AD26/AD9 -> 0.61750038 | AF74: =AF26/AF9 -> 0.59187749 | AH74: =AH26/AH9 -> 0.57980616 | AJ74: =AJ26/AJ9 -> 0.58866131 | AL74: =AL26/AL9 -> 0.58123233 | AN74: =AN26/AN9 -> 0.58531315 | AP74: =AP26/AP9 -> 0.59279436 | AR74: =AR26/AR9 -> 0.57841745 | AT74: =AT26/AT9 -> 0.59537721 | AV74: =AV26/AV9 -> 0.59500497 | AX74: =AX26/AX9 -> 0.59036685 | AZ74: =AZ26/AZ9 -> 0.61290924 | BB74: =BB26/BB9 -> 0.59750707 | BD74: =BD26/BD9 -> 0.63187217 | BF74: =BF26/BF9 -> 0.6247542 | BH74: =BH26/BH9 -> 0.61679954 | BJ74: =BJ26/BJ9 -> 0.64409339 | BL74: =BL26/BL9 -> 0.63219587 | BN74: =BN26/BN9 -> 0.67058844 | BP74: =BP26/BP9 -> 0.65052776 | BR74: =BR26/BR9 -> 0.6492656 | BT74: =BT26/BT9 -> 0.6510032 | BV74: =BV26/BV9 -> 0.63200184 | BX74: =BX26/BX9 -> 0.63949761 | BZ74: =BZ26/BZ9 -> 0.62768956 | CB74: =CB26/CB9 -> 0.63720548 | CD74: =CD26/CD9 -> 0.63735603 | CF74: =IF(ISERROR(CF26/CF9),0,(CF26/CF9)) -> 0.62999021 | CH74: =IF(ISERROR(CH26/CH9),0,(CH26/CH9)) -> 0.66910567 | CJ74: =IF(ISERROR(CJ26/CJ9),0,(CJ26/CJ9)) -> 0.66305094 | CL74: =CL26/CL9 -> 0.64954718 | CN74: =CN26/CN9 -> 0.65151104 | CP74: =IF(ISERROR(CP26/CP9),0,(CP26/CP9)) -> 0.64065627 | CR74: =IF(ISERROR(CR26/CR9),0,(CR26/CR9)) -> 0.67175393 | CT74: =IF(ISERROR(CT26/CT9),0,(CT26/CT9)) -> 0.67435935 | CV74: =CV26/CV9 -> 0.65933265 | CX74: =CX26/CX9 -> 0.6718596 | CZ74: =IF(ISERROR(CZ26/CZ9),0,(CZ26/CZ9)) -> 0.65297862 | DB74: =IF(ISERROR(DB26/DB9),0,(DB26/DB9)) -> 0.67619644 | DD74: =IF(ISERROR(DD26/DD9),0,(DD26/DD9)) -> 0.65121734 | DF74: =DF26/DF9 -> 0.6630482 | DH74: =DH26/DH9 -> 0.67050157 | DJ74: =IF(ISERROR(DJ26/DJ9),0,(DJ26/DJ9)) -> 0.64979719 | DL74: =IF(ISERROR(DL26/DL9),0,(DL26/DL9)) -> 0.67583708 | DN74: =IF(ISERROR(DN26/DN9),0,(DN26/DN9)) -> 0.64759823 | DP74: =DP26/DP9 -> 0.66084078 | DR74: =DR26/DR9 -> 0.65068771 | DT74: =IF(ISERROR(DT26/DT9),0,(DT26/DT9)) -> 0.63951693 | DV74: =IF(ISERROR(DV26/DV9),0,(DV26/DV9)) -> 0.65164649 | DX74: =IF(ISERROR(DX26/DX9),0,(DX26/DX9)) -> 0.61371012 | DZ74: =DZ26/DZ9 -> 0.63859331 | EB74: =EB26/EB9 -> 0.63542046 | ED74: =IF(ISERROR(ED26/ED9),0,(ED26/ED9)) -> 0.62525513 | EF74: =IF(ISERROR(EF26/EF9),0,(EF26/EF9)) -> 0.63271422 | EH74: =IF(ISERROR(EH26/EH9),0,(EH26/EH9)) -> 0 | EJ74: =EJ26/EJ9 -> 0.63116539
A75: Salaries & other expenses / Store revenue | B75: =B26/B13 -> 0.55742097 | D75: =D26/D13 -> 0.56893451 | F75: =F26/F13 -> 0.56883835 | H75: =H26/H13 -> 0.56838878 | J75: =J26/J13 -> 0.56594063 | L75: =L26/L13 -> 0.55143214 | N75: =N26/N13 -> 0.55844602 | P75: =P26/P13 -> 0.5588701 | R75: =R26/R13 -> 0.57506005 | T75: =T26/T13 -> 0.56108751 | V75: =V26/V13 -> 0.56964127 | X75: =X26/X13 -> 0.56823344 | Z75: =Z26/Z13 -> 0.60443419 | AB75: =AB26/AB13 -> 0.58829816 | AD75: =AD26/AD13 -> 0.58282786 | AF75: =AF26/AF13 -> 0.54268645 | AH75: =AH26/AH13 -> 0.55018202 | AJ75: =AJ26/AJ13 -> 0.55776472 | AL75: =AL26/AL13 -> 0.54204984 | AN75: =AN26/AN13 -> 0.54808428 | AP75: =AP26/AP13 -> 0.52907607 | AR75: =AR26/AR13 -> 0.53780623 | AT75: =AT26/AT13 -> 0.55132388 | AV75: =AV26/AV13 -> 0.5502078 | AX75: =AX26/AX13 -> 0.54202787 | AZ75: =AZ26/AZ13 -> 0.54083791 | BB75: =BB26/BB13 -> 0.55352338 | BD75: =BD26/BD13 -> 0.5836786 | BF75: =BF26/BF13 -> 0.57765684 | BH75: =BH26/BH13 -> 0.56387414 | BJ75: =BJ26/BJ13 -> 0.56708044 | BL75: =BL26/BL13 -> 0.58231366 | BN75: =BN26/BN13 -> 0.61299396 | BP75: =BP26/BP13 -> 0.59661424 | BR75: =BR26/BR13 -> 0.58950669 | BT75: =BT26/BT13 -> 0.57062607 | BV75: =BV26/BV13 -> 0.57984529 | BX75: =BX26/BX13 -> 0.58774805 | BZ75: =BZ26/BZ13 -> 0.5782201 | CB75: =CB26/CB13 -> 0.57903219 | CD75: =CD26/CD13 -> 0.56546592 | CF75: =IF(ISERROR(CF26/CF13),0,(CF26/CF13)) -> 0.58264608 | CH75: =IF(ISERROR(CH26/CH13),0,(CH26/CH13)) -> 0.60566606 | CJ75: =IF(ISERROR(CJ26/CJ13),0,(CJ26/CJ13)) -> 0.60179591 | CL75: =CL26/CL13 -> 0.58850906 | CN75: =CN26/CN13 -> 0.55988969 | CP75: =IF(ISERROR(CP26/CP13),0,(CP26/CP13)) -> 0.57251083 | CR75: =IF(ISERROR(CR26/CR13),0,(CR26/CR13)) -> 0.59655236 | CT75: =IF(ISERROR(CT26/CT13),0,(CT26/CT13)) -> 0.59431178 | CV75: =CV26/CV13 -> 0.58040528 | CX75: =CX26/CX13 -> 0.55846132 | CZ75: =IF(ISERROR(CZ26/CZ13),0,(CZ26/CZ13)) -> 0.57264639 | DB75: =IF(ISERROR(DB26/DB13),0,(DB26/DB13)) -> 0.58721218 | DD75: =IF(ISERROR(DD26/DD13),0,(DD26/DD13)) -> 0.57191976 | DF75: =DF26/DF13 -> 0.57227202 | DH75: =DH26/DH13 -> 0.55236497 | DJ75: =IF(ISERROR(DJ26/DJ13),0,(DJ26/DJ13)) -> 0.5743407 | DL75: =IF(ISERROR(DL26/DL13),0,(DL26/DL13)) -> 0.59309123 | DN75: =IF(ISERROR(DN26/DN13),0,(DN26/DN13)) -> 0.5715253 | DP75: =DP26/DP13 -> 0.57243194 | DR75: =DR26/DR13 -> 0.54282786 | DT75: =IF(ISERROR(DT26/DT13),0,(DT26/DT13)) -> 0.57302501 | DV75: =IF(ISERROR(DV26/DV13),0,(DV26/DV13)) -> 0.58299785 | DX75: =IF(ISERROR(DX26/DX13),0,(DX26/DX13)) -> 0.54605241 | DZ75: =DZ26/DZ13 -> 0.56080453 | EB75: =EB26/EB13 -> 0.52328467 | ED75: =IF(ISERROR(ED26/ED13),0,(ED26/ED13)) -> 0.55656639 | EF75: =IF(ISERROR(EF26/EF13),0,(EF26/EF13)) -> 0.56571514 | EH75: =IF(ISERROR(EH26/EH13),0,(EH26/EH13)) -> 0 | EJ75: =EJ26/EJ13 -> 0.54752631
A76: Store Margin | B76: =(B13-B23-B24-B25-B26)/B13 -> 0.17233915 | D76: =(D13-D23-D24-D25-D26)/D13 -> 0.18215925 | F76: =(F13-F23-F24-F25-F26)/F13 -> 0.189233 | H76: =(H13-H23-H24-H25-H26)/H13 -> 0.19452941 | J76: =(J13-J23-J24-J25-J26)/J13 -> 0.18470661 | L76: =(L13-L23-L24-L25-L26)/L13 -> 0.1985129 | N76: =(N13-N23-N24-N25-N26)/N13 -> 0.20802624 | P76: =(P13-P23-P24-P25-P26)/P13 -> 0.20818896 | R76: =(R13-R23-R24-R25-R26)/R13 -> 0.19627313 | T76: =(T13-T23-T24-T25-T26)/T13 -> 0.20272976 | V76: =(V13-V23-V24-V25-V26)/V13 -> 0.18961462 | X76: =(X13-X23-X24-X25-X26)/X13 -> 0.19988116 | Z76: =(Z13-Z23-Z24-Z25-Z26)/Z13 -> 0.15707463 | AB76: =(AB13-AB23-AB24-AB25-AB26)/AB13 -> 0.17216062 | AD76: =(AD13-AD23-AD24-AD25-AD26)/AD13 -> 0.17948098 | AF76: =(AF13-AF23-AF24-AF25-AF26)/AF13 -> 0.21098354 | AH76: =(AH13-AH23-AH24-AH25-AH26)/AH13 -> 0.21713923 | AJ76: =(AJ13-AJ23-AJ24-AJ25-AJ26)/AJ13 -> 0.20550844 | AL76: =(AL13-AL23-AL24-AL25-AL26)/AL13 -> 0.20772761 | AN76: =(AN13-AN23-AN24-AN25-AN26)/AN13 -> 0.2103042 | AP76: =(AP13-AP23-AP24-AP25-AP26)/AP13 -> 0.20604041 | AR76: =(AR13-AR23-AR24-AR25-AR26)/AR13 -> 0.21208915 | AT76: =(AT13-AT23-AT24-AT25-AT26)/AT13 -> 0.19610575 | AV76: =(AV13-AV23-AV24-AV25-AV26)/AV13 -> 0.19676893 | AX76: =(AX13-AX23-AX24-AX25-AX26)/AX13 -> 0.20277629 | AZ76: =(AZ13-AZ23-AZ24-AZ25-AZ26)/AZ13 -> 0.19481672 | BB76: =(BB13-BB23-BB24-BB25-BB26)/BB13 -> 0.19745533 | BD76: =(BD13-BD23-BD24-BD25-BD26)/BD13 -> 0.1628653 | BF76: =(BF13-BF23-BF24-BF25-BF26)/BF13 -> 0.16627502 | BH76: =(BH13-BH23-BH24-BH25-BH26)/BH13 -> 0.18036237 | BJ76: =(BJ13-BJ23-BJ24-BJ25-BJ26)/BJ13 -> 0.16571486 | BL76: =(BL13-BL23-BL24-BL25-BL26)/BL13 -> 0.16400467 | BN76: =(BN13-BN23-BN24-BN25-BN26)/BN13 -> 0.13027055 | BP76: =(BP13-BP23-BP24-BP25-BP26)/BP13 -> 0.14807568 | BR76: =(BR13-BR23-BR24-BR25-BR26)/BR13 -> 0.15218648 | BT76: =(BT13-BT23-BT24-BT25-BT26)/BT13 -> 0.16101522 | BV76: =(BV13-BV23-BV24-BV25-BV26)/BV13 -> 0.16682565 | BX76: =(BX13-BX23-BX24-BX25-BX26)/BX13 -> 0.15618244 | BZ76: =(BZ13-BZ23-BZ24-BZ25-BZ26)/BZ13 -> 0.16443544 | CB76: =(CB13-CB23-CB24-CB25-CB26)/CB13 -> 0.16216313 | CD76: =(CD13-CD23-CD24-CD25-CD26)/CD13 -> 0.1756165 | CF76: =IF(ISERROR((CF13-CF23-CF24-CF25-CF26)/CF13),0,((CF13-CF23-CF24-CF25-CF26)/CF13)) -> 0.16731201 | CH76: =IF(ISERROR((CH13-CH23-CH24-CH25-CH26)/CH13),0,((CH13-CH23-CH24-CH25-CH26)/CH13)) -> 0.13028388 | CJ76: =IF(ISERROR((CJ13-CJ23-CJ24-CJ25-CJ26)/CJ13),0,((CJ13-CJ23-CJ24-CJ25-CJ26)/CJ13)) -> 0.13184604 | CL76: =(CL13-CL23-CL24-CL25-CL26)/CL13 -> 0.15170821 | CN76: =(CN13-CN23-CN24-CN25-CN26)/CN13 -> 0.15372709 | CP76: =IF(ISERROR((CP13-CP23-CP24-CP25-CP26)/CP13),0,((CP13-CP23-CP24-CP25-CP26)/CP13)) -> 0.15365075 | CR76: =IF(ISERROR((CR13-CR23-CR24-CR25-CR26)/CR13),0,((CR13-CR23-CR24-CR25-CR26)/CR13)) -> 0.13030546 | CT76: =IF(ISERROR((CT13-CT23-CT24-CT25-CT26)/CT13),0,((CT13-CT23-CT24-CT25-CT26)/CT13)) -> 0.13775888 | CV76: =(CV13-CV23-CV24-CV25-CV26)/CV13 -> 0.14407521 | CX76: =(CX13-CX23-CX24-CX25-CX26)/CX13 -> 0.15593348 | CZ76: =IF(ISERROR((CZ13-CZ23-CZ24-CZ25-CZ26)/CZ13),0,((CZ13-CZ23-CZ24-CZ25-CZ26)/CZ13)) -> 0.16073256 | DB76: =IF(ISERROR((DB13-DB23-DB24-DB25-DB26)/DB13),0,((DB13-DB23-DB24-DB25-DB26)/DB13)) -> 0.14503609 | DD76: =IF(ISERROR((DD13-DD23-DD24-DD25-DD26)/DD13),0,((DD13-DD23-DD24-DD25-DD26)/DD13)) -> 0.16482137 | DF76: =(DF13-DF23-DF24-DF25-DF26)/DF13 -> 0.15663326 | DH76: =(DH13-DH23-DH24-DH25-DH26)/DH13 -> 0.16917307 | DJ76: =IF(ISERROR((DJ13-DJ23-DJ24-DJ25-DJ26)/DJ13),0,((DJ13-DJ23-DJ24-DJ25-DJ26)/DJ13)) -> 0.17335513 | DL76: =IF(ISERROR((DL13-DL23-DL24-DL25-DL26)/DL13),0,((DL13-DL23-DL24-DL25-DL26)/DL13)) -> 0.1511328 | DN76: =IF(ISERROR((DN13-DN23-DN24-DN25-DN26)/DN13),0,((DN13-DN23-DN24-DN25-DN26)/DN13)) -> 0.16772406 | DP76: =(DP13-DP23-DP24-DP25-DP26)/DP13 -> 0.16545175 | DR76: =(DR13-DR23-DR24-DR25-DR26)/DR13 -> 0.16979992 | DT76: =IF(ISERROR((DT13-DT23-DT24-DT25-DT26)/DT13),0,((DT13-DT23-DT24-DT25-DT26)/DT13)) -> 0.15908877 | DV76: =IF(ISERROR((DV13-DV23-DV24-DV25-DV26)/DV13),0,((DV13-DV23-DV24-DV25-DV26)/DV13)) -> 0.141594 | DX76: =IF(ISERROR((DX13-DX23-DX24-DX25-DX26)/DX13),0,((DX13-DX23-DX24-DX25-DX26)/DX13)) -> 0.16398179 | DZ76: =(DZ13-DZ23-DZ24-DZ25-DZ26)/DZ13 -> 0.15881396 | EB76: =(EB13-EB23-EB24-EB25-EB26)/EB13 -> 0.15522425 | ED76: =IF(ISERROR((ED13-ED23-ED24-ED25-ED26)/ED13),0,((ED13-ED23-ED24-ED25-ED26)/ED13)) -> 0.15295901 | EF76: =IF(ISERROR((EF13-EF23-EF24-EF25-EF26)/EF13),0,((EF13-EF23-EF24-EF25-EF26)/EF13)) -> 0.14403031 | EH76: =IF(ISERROR((EH13-EH23-EH24-EH25-EH26)/EH13),0,((EH13-EH23-EH24-EH25-EH26)/EH13)) -> 0 | EJ76: =(EJ13-EJ23-EJ24-EJ25-EJ26)/EJ13 -> 0.15093244
A78: General & Administrative / Total Revenue | B78: =B31/B19 -> 0.032640261 | D78: =D31/D19 -> 0.030163251 | F78: =F31/F19 -> 0.028308918 | H78: =H31/H19 -> 0.027676297 | J78: =J31/J19 -> 0.029656798 | L78: =L31/L19 -> 0.029233864 | N78: =N31/N19 -> 0.030608421 | P78: =P31/P19 -> 0.031380257 | R78: =R31/R19 -> 0.028901973 | T78: =T31/T19 -> 0.030027874 | V78: =V31/V19 -> 0.029267786 | X78: =X31/X19 -> 0.031471163 | Z78: =Z31/Z19 -> 0.031256571 | AB78: =AB31/AB19 -> 0.030443034 | AD78: =AD31/AD19 -> 0.03061012 | AF78: =AF31/AF19 -> 0.030318285 | AH78: =AH31/AH19 -> 0.030900012 | AJ78: =AJ31/AJ19 -> 0.030987077 | AL78: =AL31/AL19 -> 0.029813505 | AN78: =AN31/AN19 -> 0.030494855 | AP78: =AP31/AP19 -> 0.02958302 | AR78: =AR31/AR19 -> 0.029620793 | AT78: =AT31/AT19 -> 0.030222343 | AV78: =AV31/AV19 -> 0.030204472 | AX78: =AX31/AX19 -> 0.029905976 | AZ78: =AZ31/AZ19 -> 0.031066999 | BB78: =BB31/BB19 -> 0.033843818 | BD78: =BD31/BD19 -> 0.032956056 | BF78: =BF31/BF19 -> 0.032686752 | BH78: =BH31/BH19 -> 0.032629779 | BJ78: =BJ31/BJ19 -> 0.031928735 | BL78: =BL31/BL19 -> 0.034947931 | BN78: =BN31/BN19 -> 0.036923699 | BP78: =BP31/BP19 -> 0.037051643 | BR78: =BR31/BR19 -> 0.035180092 | BT78: =BT31/BT19 -> 0.034528605 | BV78: =BV31/BV19 -> 0.036415631 | BX78: =BX31/BX19 -> 0.040542658 | BZ78: =BZ31/BZ19 -> 0.041972121 | CB78: =CB31/CB19 -> 0.038438593 | CD78: =CD31/CD19 -> 0.0410407 | CF78: =IF(ISERROR(CF31/CF19),0,(CF31/CF19)) -> 0.042006026 | CH78: =IF(ISERROR(CH31/CH19),0,(CH31/CH19)) -> 0.044914926 | CJ78: =IF(ISERROR(CJ31/CJ19),0,(CJ31/CJ19)) -> 0.042659105 | CL78: =CL31/CL19 -> 0.042623563 | CN78: =CN31/CN19 -> 0.04090342 | CP78: =IF(ISERROR(CP31/CP19),0,(CP31/CP19)) -> 0.045444494 | CR78: =IF(ISERROR(CR31/CR19),0,(CR31/CR19)) -> 0.042837088 | CT78: =IF(ISERROR(CT31/CT19),0,(CT31/CT19)) -> 0.045224723 | CV78: =CV31/CV19 -> 0.043559122 | CX78: =CX31/CX19 -> 0.047069212 | CZ78: =IF(ISERROR(CZ31/CZ19),0,(CZ31/CZ19)) -> 0.050899856 | DB78: =IF(ISERROR(DB31/DB19),0,(DB31/DB19)) -> 0.048735868 | DD78: =IF(ISERROR(DD31/DD19),0,(DD31/DD19)) -> 0.053565617 | DF78: =DF31/DF19 -> 0.050010247 | DH78: =DH31/DH19 -> 0.044229064 | DJ78: =IF(ISERROR(DJ31/DJ19),0,(DJ31/DJ19)) -> 0.047909069 | DL78: =IF(ISERROR(DL31/DL19),0,(DL31/DL19)) -> 0.046339041 | DN78: =IF(ISERROR(DN31/DN19),0,(DN31/DN19)) -> 0.046633387 | DP78: =DP31/DP19 -> 0.046243052 | DR78: =DR31/DR19 -> 0.046556217 | DT78: =IF(ISERROR(DT31/DT19),0,(DT31/DT19)) -> 0.045895972 | DV78: =IF(ISERROR(DV31/DV19),0,(DV31/DV19)) -> 0.047493081 | DX78: =IF(ISERROR(DX31/DX19),0,(DX31/DX19)) -> 0.048940856 | DZ78: =DZ31/DZ19 -> 0.04723536 | EB78: =EB31/EB19 -> 0.043393986 | ED78: =IF(ISERROR(ED31/ED19),0,(ED31/ED19)) -> 0.045925159 | EF78: =IF(ISERROR(EF31/EF19),0,(EF31/EF19)) -> 0.048983247 | EH78: =IF(ISERROR(EH31/EH19),0,(EH31/EH19)) -> 0 | EJ78: =EJ31/EJ19 -> 0.045988282
A81: Balance Sheet Statistics:
A82: Rental Merchandise - On Rent | B82: 336393.21 | D82: 354723.95 | F82: 379799.42 | H82: 425468.92 | L82: 458195.24 | N82: 466779 | P82: 460921 | R82: 477095 | V82: 515394.89 | X82: 513689 | Z82: 527723.67 | AB82: 531626.98 | AF82: 544471.02 | AH82: 517500 | AJ82: 505397 | AL82: 510184 | AP82: 556415 | AR82: 530985 | AT82: 508183 | AV82: 542909 | AZ82: 557484 | BB82: 565977 | BD82: 555024 | BF82: 596447 | BJ82: 610103 | BL82: 574080 | BN82: 572224 | BP82: 588978 | BT82: 635154 | BV82: 633749 | BX82: 638091 | BZ82: 816762 | CD82: 840627 | CF82: 798285 | CH82: 728922 | CJ82: 735672 | CN82: 725204 | CP82: 676607 | CR82: 620438 | CT82: 634946 | CX82: 604558 | CZ82: 571902 | DB82: 547418 | DD82: 589066 | DH82: 586855 | DJ82: 551804 | DL82: 544308 | DN82: 655248 | DR82: 675013 | DT82: 673431 | DV82: 689975 | DX82: 766425 | EB82: 757670 | ED82: 731433 | EF82: 733724
A83: Rental Merchandise - Idle | B83: 76172.404 | D83: 101997.77 | F83: 92459.088 | H83: 105753.88 | L83: 100900.94 | N83: 116428 | P83: 113145 | R83: 110137 | V83: 110869.14 | X83: 125016 | Z83: 116670 | AB83: 122074.14 | AF83: 112073.17 | AH83: 131705 | AJ83: 119197 | AL83: 120072 | AP83: 136909 | AR83: 145345 | AT83: 135435 | AV83: 139458 | AZ83: 140418 | BB83: 169044 | BD83: 162489 | BF83: 162664 | BJ83: 181652 | BL83: 197639 | BN83: 178825 | BP83: 161702 | BT83: 157825 | BV83: 178667 | BX83: 195086 | BZ83: 239471 | CD83: 229256 | CF83: 237876 | CH83: 236782 | CJ83: 202298 | CN83: 191121 | CP83: 204472 | CR83: 213096 | CT83: 184108 | CX83: 166703 | CZ83: 179857 | DB83: 175743 | DD83: 160932 | DH83: 181984 | DJ83: 198609 | DL83: 172784 | DN83: 181606 | DR83: 180512 | DT83: 194239 | DV83: 187342 | DX83: 186768 | EB83: 185799 | ED83: 189203 | EF83: 214158
A84: Total Rental Merchandise | B84: =SUM(B82:B83) -> 412565.61 | D84: =SUM(D82:D83) -> 456721.72 | F84: =SUM(F82:F83) -> 472258.51 | H84: =SUM(H82:H83) -> 531222.8 | L84: =SUM(L82:L83) -> 559096.19 | N84: =SUM(N82:N83) -> 583207 | P84: =SUM(P82:P83) -> 574066 | R84: =SUM(R82:R83) -> 587232 | V84: =SUM(V82:V83) -> 626264.04 | X84: =SUM(X82:X83) -> 638705 | Z84: =SUM(Z82:Z83) -> 644393.67 | AB84: =SUM(AB82:AB83) -> 653701.12 | AF84: =SUM(AF82:AF83) -> 656544.18 | AH84: =SUM(AH82:AH83) -> 649205 | AJ84: =SUM(AJ82:AJ83) -> 624594 | AL84: =SUM(AL82:AL83) -> 630256 | AP84: =SUM(AP82:AP83) -> 693324 | AR84: =SUM(AR82:AR83) -> 676330 | AT84: =SUM(AT82:AT83) -> 643618 | AV84: =SUM(AV82:AV83) -> 682367 | AZ84: =SUM(AZ82:AZ83) -> 697902 | BB84: =SUM(BB82:BB83) -> 735021 | BD84: =SUM(BD82:BD83) -> 717513 | BF84: =SUM(BF82:BF83) -> 759111 | BJ84: =SUM(BJ82:BJ83) -> 791755 | BL84: =SUM(BL82:BL83) -> 771719 | BN84: =SUM(BN82:BN83) -> 751049 | BP84: =SUM(BP82:BP83) -> 750680 | BT84: =SUM(BT82:BT83) -> 792979 | BV84: =SUM(BV82:BV83) -> 812416 | BX84: =SUM(BX82:BX83) -> 833177 | BZ84: =SUM(BZ82:BZ83) -> 1056233 | CD84: =SUM(CD82:CD83) -> 1069883 | CF84: =SUM(CF82:CF83) -> 1036161 | CH84: =SUM(CH82:CH83) -> 965704 | CJ84: =SUM(CJ82:CJ83) -> 937970 | CN84: =SUM(CN82:CN83) -> 916325 | CP84: =SUM(CP82:CP83) -> 881079 | CR84: =SUM(CR82:CR83) -> 833534 | CT84: =SUM(CT82:CT83) -> 819054 | CX84: =SUM(CX82:CX83) -> 771261 | CZ84: =SUM(CZ82:CZ83) -> 751759 | DB84: =SUM(DB82:DB83) -> 723161 | DD84: =SUM(DD82:DD83) -> 749998 | DH84: =SUM(DH82:DH83) -> 768839 | DJ84: =SUM(DJ82:DJ83) -> 750413 | DL84: =SUM(DL82:DL83) -> 717092 | DN84: =SUM(DN82:DN83) -> 836854 | DR84: =SUM(DR82:DR83) -> 855525 | DT84: =SUM(DT82:DT83) -> 867670 | DV84: =SUM(DV82:DV83) -> 877317 | DX84: =SUM(DX82:DX83) -> 953193 | EB84: =SUM(EB82:EB83) -> 943469 | ED84: =SUM(ED82:ED83) -> 920636 | EF84: =SUM(EF82:EF83) -> 947882 | EH84: =SUM(EH82:EH83) -> 0
A85: Idle as % of Total Merchandise | B85: =B83/B84 -> 0.18463101 | D85: =D83/D84 -> 0.22332586 | F85: =F83/F84 -> 0.19578067 | H85: =H83/H84 -> 0.19907631 | L85: =L83/L84 -> 0.18047153 | N85: =N83/N84 -> 0.19963409 | P85: =P83/P84 -> 0.19709406 | R85: =R83/R84 -> 0.18755279 | V85: =V83/V84 -> 0.17703259 | X85: =X83/X84 -> 0.19573355 | Z85: =Z83/Z84 -> 0.18105392 | AB85: =AB83/AB84 -> 0.18674305 | AF85: =AF83/AF84 -> 0.17070164 | AH85: =AH83/AH84 -> 0.2028712 | AJ85: =AJ83/AJ84 -> 0.19083917 | AL85: =AL83/AL84 -> 0.19051306 | AP85: =AP83/AP84 -> 0.19746756 | AR85: =AR83/AR84 -> 0.21490249 | AT85: =AT83/AT84 -> 0.21042761 | AV85: =AV83/AV84 -> 0.20437389 | AZ85: =AZ83/AZ84 -> 0.20120017 | BB85: =BB83/BB84 -> 0.22998527 | BD85: =BD83/BD84 -> 0.2264614 | BF85: =BF83/BF84 -> 0.21428223 | BJ85: =BJ83/BJ84 -> 0.22942956 | BL85: =BL83/BL84 -> 0.25610229 | BN85: =BN83/BN84 -> 0.23810031 | BP85: =BP83/BP84 -> 0.21540736 | BT85: =BT83/BT84 -> 0.19902797 | BV85: =BV83/BV84 -> 0.21992058 | BX85: =BX83/BX84 -> 0.23414713 | BZ85: =BZ83/BZ84 -> 0.22672176 | CD85: =CD83/CD84 -> 0.21428137 | CF85: =IF(ISERROR(CF83/CF84),0,(CF83/CF84)) -> 0.22957436 | CH85: =IF(ISERROR(CH83/CH84),0,(CH83/CH84)) -> 0.24519107 | CJ85: =IF(ISERROR(CJ83/CJ84),0,(CJ83/CJ84)) -> 0.21567641 | CN85: =CN83/CN84 -> 0.20857338 | CP85: =IF(ISERROR(CP83/CP84),0,(CP83/CP84)) -> 0.23207 | CR85: =IF(ISERROR(CR83/CR84),0,(CR83/CR84)) -> 0.25565364 | CT85: =IF(ISERROR(CT83/CT84),0,(CT83/CT84)) -> 0.22478127 | CX85: =CX83/CX84 -> 0.21614343 | CZ85: =IF(ISERROR(CZ83/CZ84),0,(CZ83/CZ84)) -> 0.23924822 | DB85: =IF(ISERROR(DB83/DB84),0,(DB83/DB84)) -> 0.24302057 | DD85: =IF(ISERROR(DD83/DD84),0,(DD83/DD84)) -> 0.21457657 | DH85: =DH83/DH84 -> 0.23669975 | DJ85: =IF(ISERROR(DJ83/DJ84),0,(DJ83/DJ84)) -> 0.26466626 | DL85: =IF(ISERROR(DL83/DL84),0,(DL83/DL84)) -> 0.24095095 | DN85: =IF(ISERROR(DN83/DN84),0,(DN83/DN84)) -> 0.21701037 | DR85: =DR83/DR84 -> 0.21099559 | DT85: =IF(ISERROR(DT83/DT84),0,(DT83/DT84)) -> 0.22386276 | DV85: =IF(ISERROR(DV83/DV84),0,(DV83/DV84)) -> 0.21353969 | DX85: =IF(ISERROR(DX83/DX84),0,(DX83/DX84)) -> 0.19593933 | EB85: =EB83/EB84 -> 0.19693175 | ED85: =IF(ISERROR(ED83/ED84),0,(ED83/ED84)) -> 0.20551336 | EF85: =IF(ISERROR(EF83/EF84),0,(EF83/EF84)) -> 0.22593319 | EH85: =IF(ISERROR(EH83/EH84),0,(EH83/EH84)) -> 0
L87: 2000 Notes | V87: 2001 Notes | AF87: 2002 Notes | AP87: 2003 Notes | AZ87: 2004 Notes | BJ87: 2005 Notes | BT87: 2006 Notes | CD87: 2007 Notes | CN87: 2008 Notes | CX87: 2009 Notes | DH87: 2010 Notes | DR87: 2011 Notes | EB87: 2012 Notes
L88: (1) 2Q00 & FY200 xxcludes non-recurring legal reversion of $22.4 million associated | V88: (1) 3Q01 & FY2001 excludes $16.0 million non-recurring litigation charge associated | AF88: (1) 2Q02 & FY2002 excludes $2.0 million pre-tax legal charge associated with the | AP88: (1) 3Q'03 & FY 2003 excludes the effects of a pre-tax finance charge of $7.512 million | AZ88: (1) 3Q'04 and FY 2004 excludes the effects of $47.0 million in pre-tax charges associated | BJ88: (1) 1Q'05 excludes the effects of an $8.0 million pre-tax credit associated with the | BT88: (1) 3Q'06 excludes the effects of a $10.4 million pre-tax expense associated with the | CD88: (1) 1Q'07 excludes the effects of a $51.3 million pre-tax litigation expense associated with the | CN88: (1) 1Q'08 excludes the effects of a $2.9 million pre-tax restructuring expense as part of the | CX88: (1) 1Q'08 excludes the effects of a $3.0 million pre-tax litigation credit related to the | DH88: (1) Q4'10 excludes the effects of an $18.9 million pre-tax impairment charge related to | DR88: (1) Q1'11 excludes the effects of an $7.3 million pre-tax impairment charge related to
L89: with the 1999 settlement of three class action lawsuits in the State of New Jersey | V89: with the settlement in principle of an asserted class action lawsuit pending in the | AF89: settlement of class action gender discrimination lawsuits. | AP89: associated with the recapitalization of the Company. | AZ89: with the Griego/Carrillo litigation and $4.2 million in pre-tax charges associated with | BJ89: litigation reversion. | BT89: settlement with the California Attorney General. | CD89: prospective settlement in the Perez case. | CN89: December 3, 2007 announced restructuring plan. | CX89: Hilda Perez matter. | DH89: the discontinuation of the financial services business. | DR89: the discontinuation of the financial services business.
V90: state of Missouri. | AF90: (2) 2Q02 & FY2002 excludes $2.909 million pre-tax charge associated with the early | AP90: (2) Basic and Diluted EPS is adjusted through 1998 to reflect the | AZ90: refinancing of the Company's senior credit facility. | BJ90: (2) 2Q'05 excludes the effects of a $2.0 million tax audit reserve credit associated | BT90: (2) 3Q'06 excludes the effects of a $4.95 million pre-tax expense associated with the | CD90: (2) 3Q'07 excludes the effects of a $3.9 million in franchise royalty income for the settlement | CN90: (2) 2Q'08 excludes the effects of a $0.015 million pre-tax restructuring credit as part of the | CX90: (2) 2Q'09 excludes the effects of a $1.9 million pre-tax litigation credit related to the | DH90: (2) Q4'10 excludes the effects of a $3.1 million pre-tax financing expense related to the | DR90: (2) Q1'11 excludes the effects of a $2.8 million pre-tax litigation expense related to the
V91: (2) 4Q01 & FY2001 excludes $36.0 million non-recurring litigation charge associated | AF91: retirement of debt. | AP91: 5-for-2 stock split that took effect on September 2, 2003. | AZ91: (2) 4Q'04 and FY 2004 excludes the effects of $7.9 million in one-time other income | BJ91: with the examination and favorable resolution of the Company's 1998 and 1999 | BT91: settlement of the Burdusis/French/Corso litigation. | CD91: with five affiliated ColorTyme franchisees. | CN91: December 3, 2007 announced restructuring plan. | CX91: Hilda Perez matter. | DH91: write-off of unamortized financing costs. | DR91: prospective settlement of wage & hour claims in California.
V92: with the settlement in principle of all remaining asserted class action lawsuits | AZ92: associated with the sale of charged-off accounts. | BJ92: federal tax returns. | BT92: (3) 3Q'06 excludes the effects of a $2.2 million pre-tax expense associated with the | CD92: (3) 4Q'07 excludes the effects of a $38.7 million pre-tax restructuring expense as part of the | CN92: (3) 3Q'08 excludes the effects of a $0.213 million pre-tax restructuring expense as part of | DR92: (3) Q2'11 excludes the effects of a $4.9 million pre-tax restructuring charge related to
V93: pending in the state of Missouri. | BJ93: (3) 3Q'05 excludes the effects of a $7.7 million in pre-tax expense related to the | BT93: refinancing of the Company's senior credit facility. | CD93: December 3, 2007 announced store consolidation plan and other restructuring items. | CN93: the December 3, 2007 announced restructuring plan. | DR93: the lease terminations regarding The Rental Store acquisition.
BJ94: damage caused by Hurricanes Katrina & Rita. | BT94: (4) 4Q'06 excludes the effects of a $58 million pre-tax associated with the litigation | CD94: (4) 4Q'07 excludes the effects of a $11.0 million pre-tax expense associated with the prospective | CN94: (4) 4Q'08 excludes effects of a $4.6 million pre-tax litigation credit related to the Hilda Perez | DR94: (4) Q3'11 excludes the effects of a $7.6 million pre-tax restructuring charge related to
BJ95: (4) 3Q'05 excludes the effects of a $13.0 million pre-tax restructuring expenses as part | BT95: expense with respect to the Perez case. | CD95: settlement of the Shafer/Johnson matter. | CN95: and Shafer/Johnson matters. | DR95: the closure of eight Home Choice and 24 RAC Limited stores.
BJ96: of the store consolidation plan announced September 6, 2005. | BT96: (5) 4Q'06 excludes the effects of a $2.6 million pre-tax expense for refinancing of the | CN96: (5) 4Q'08 excludes the effects of a $1.4 million pre-tax restructuring expense as part of the | DR96: (5) Q4'11 excludes the effects of a $1.4 million pre-tax restructuring charge related to
BJ97: (5) 4Q05 excludes the effects of a $1.1 million in pre-tax expense related to the damage | BT97: Company's senior credit facility. | CN97: December 3, 2007 announced restructuring plan. | DR97: the acquisition in November 2011 of 58 rent-to-own stores.
BJ98: caused by Hurricanes Katrina, Rita and Wilma. | CN98: (6) 4Q'08 excludes the effect of a $4.3 million pre-tax gain on the extinguishment of debt.
BJ99: (6) 4Q'05 excludes the effects of a $2.1 million pre-tax restructuring expense as part of
BJ100: the store consoldiation plan announced September 6, 2005.
BJ101: (7) 4Q'05 excludes the effects of a $3.7 million state tax reserve credit for a reserve
BJ102: adjustment due to a change in estimate related to potential loss exposures.

Sheet EPS Contribution
A1: Rent-A-Center, Inc.
A2: Proforma Diluted EPS Quarterly Contribution 2009 - Q3 2012
C5: 1Q | F5: 2Q | I5: 3Q | L5: 4Q | O5: Annual | Q5: STORES BY SEGMENT
A6: Year | C6: Diluted EPS | D6: % of Total | F6: Diluted EPS | G6: % of Total | I6: Diluted EPS | J6: % of Total | L6: Diluted EPS | M6: % of Total | O6: Diluted EPS | Q6: CORE US (1)(2) | R6: RACA | S6: MEX | T6: CAN | U6: TOTAL
A7: 2009 | C7: ='Quarterly ProForma Results'!CX51 -> 0.65441011 | D7: =C7/O7 -> 0.26429635 | F7: ='Quarterly ProForma Results'!CZ51 -> 0.61210557 | G7: =F7/O7 -> 0.24721084 | I7: ='Quarterly ProForma Results'!DB51 -> 0.55223187 | J7: =I7/O7 -> 0.22302967 | L7: ='Quarterly ProForma Results'!DD51 -> 0.65754971 | M7: =L7/O7 -> 0.26556434 | O7: ='Quarterly ProForma Results'!DF51 -> 2.4760467 | Q7: 2989 | R7: 82 | S7: 0 | T7: 18 | U7: =SUM(Q7:T7) -> 3089
A8: 2010 | C8: ='Quarterly ProForma Results'!DH51 -> 0.77365185 | D8: =C8/O8 -> 0.27499236 | F8: ='Quarterly ProForma Results'!DJ51 -> 0.71630749 | G8: =F8/O8 -> 0.25460947 | I8: ='Quarterly ProForma Results'!DL51 -> 0.61596143 | J8: =I8/O8 -> 0.21894175 | L8: ='Quarterly ProForma Results'!DN51 -> 0.70646535 | M8: =L8/O8 -> 0.25111111 | O8: ='Quarterly ProForma Results'!DP51 -> 2.8133576 | Q8: 2985 | R8: 384 | S8: 5 | T8: 18 | U8: =SUM(Q8:T8) -> 3392
A9: 2011 | C9: ='Quarterly ProForma Results'!DR51 -> 0.78627201 | D9: =C9/O9 -> 0.27023747 | F9: ='Quarterly ProForma Results'!DT51 -> 0.68054412 | G9: =F9/O9 -> 0.23389937 | I9: ='Quarterly ProForma Results'!DV51 -> 0.5955474 | J9: =I9/O9 -> 0.20468645 | L9: ='Quarterly ProForma Results'!DX51 -> 0.84732684 | M9: =L9/O9 -> 0.29122169 | O9: ='Quarterly ProForma Results'!DZ51 -> 2.9095595 | Q9: 2994 | R9: 750 | S9: 52 | T9: 28 | U9: =SUM(Q9:T9) -> 3824
A10: 2012 | C10: ='Quarterly ProForma Results'!EB51 -> 0.86662217 | F10: ='Quarterly ProForma Results'!ED51 -> 0.74158246 | I10: ='Quarterly ProForma Results'!EF51 -> 0.67288238 | Q10: 2983 | R10: 882 | S10: 81 | T10: 33 | U10: =SUM(Q10:T10) -> 3979
A12: (1) Primarily includes rent-to-own stores in the U.S. & Puerto Rico and GIN/Home Choice
A13: (2) Exludes Financial Services (2009 - 353; 2010 - 111)
