Workbook

Sheet Instructions
A1: CHARTER SCHOOL BUDGET INSTRUCTIONS
A3: Per NAC 387.730:
B5: TENTATIVE budget is due to the clerk or secretary of the Charter School Governing Body and Nevada Department
C6: of Education (NDE) by April 15 annually.
B8: FINAL budget must be adopted on or before June 8 Annually. Copies of the approved final budget are then
C9: SUBMITTED by the Charter School Governing Body to NDE, Program Analyst - Fiscal Analysis Division -
C10: Legislative Counsel Bureau and the Charter School sponsor.
B12: The preferred method of submitting the Tentative and Final budgets to the NDE, is electronically.
B13: The signed cover page (Form 1) for the final budget, can be scanned and sent electronically, faxed, or mailed.
A15: FORM 1 COVER PAGE
A16: 1 | B16: Enter the name of the charter school in "Charter School - fill in the name of your school".
A17: 2 | B17: Enter the number of governmental fund types. You will most likely have one (General Fund) or two (also Special Education).
A18: 3 | B18: Enter the total estimated expenditures for governmental funds. This amount must agree with "TOTAL ALL
B19: EXPENDITURES" on Form 4 Expenses, page 10.
A20: 4 | B20: If you have a proprietary fund(s), enter the number of funds and estimated expenses. It is unusual for
B21: Charter Schools to have proprietary funds. This total must agree with "TOTAL EXPENSES" on Form 6
B22: Proprietary, page 10.
A23: 5 | B23: Fill in the certification information on the lower left side of the page, prior to submitting the tentative
B24: budget.
A25: 6 | B25: Fill in the "Scheduled Public Hearing:" information at the bottom of the page for the tentative budget.
A26: 7 | B26: Fill in the certification information on the lower portion of the page, including the board members, prior to
B27: submitting the final budget. The certification needs to be signed by the charter school principal or
B28: administrator and all members of the governing board.
A29: 8 | B29: Fill in the actual public hearing information under "Scheduled Public Hearing:" prior to submitting the
B30: final budget.
A32: FORM 2 ENROLLMENT-DSA
A33: 1 | B33: Enter data in the yellow cells only.
A34: 2 | B34: Enter the enrollments for both "Actual Year Ending 06/30/XX" (columns D/F & H/J) for categories #1-5, 7-8.
A35: 3 | B35: Enter the enrollments for "Estimated Year Ending 06/30/XX" for the budget submission year in #1-5, 7-8.
A36: 4 | B36: Enter the Hold Harmless amount in #10. You will be eligible to receive the Hold Harmless enrollments:
B37: a. IF: enrollment decreases less than 5%, use highest enrollment of current or prior year.
B38: b. IF: enrollment decreases more than 5%, use highest enrollment of current or either of the two prior
B39: consecutive years.
B40: c. IF: the Charter School is multidistrict, Hold Harmless is based on the TOTAL Statewide enrollment.
B41: d. New Charter Schools are not eligible for Hold Harmless.
A42: 5 | B42: Enter the WEIGHTED student enrollments based on School District of residence in #11. If the pupils only
B43: reside in one School District, enter the total number of students (WEIGHTED) next to that district. If they
B44: reside in more than one district, allocate the enrollment to the correct school districts. The rate for basic
B45: support will automatically calculate for you.
A46: 6 | B46: Enter an estimated "Outside Revenue" amount in #12. The prior year amounts are listed at the far right
B47: under #11 as a reference point for you.
A48: 7 | B48: #13 will calculate based on the numbers you have provided for #1-12.
A49: 8 | B49: Enter the estimated number of Special Education units. One or two Charter Schools will be awarded
B50: one unit, but you are not likely to receive any of these units. Check your awards from the prior year.
B51: The Units are legislatively determined to provide supplemental funding for special education staff.
A53: FORM 3 REVENUES
A54: 1 | B54: Fill in the amounts of revenue per revenue code in column (1) from your audited information.
A55: 2 | B55: Fill in the amounts of revenue per revenue code in column (2) from your current year estimates.
A56: 3 | B56: Fill in the amounts of revenue per revenue code in column (3) based on anticipated revenue for the school
B57: year to begin July 1 for the tentative budget.
A58: 4 | B58: Fill in the amounts of revenue per revenue code in column (4) based on the approved and adopted budget
B59: for the school year to begin July 1 for the final budget.
A60: 5 | B60: Note: there will be a limited number of revenue sources so most of the revenue codes will be blank.
A61: 6 | B61: Enter the opening balance under revenue code 8000. Column (1) will have the audited opening balance.
B62: Column (2) will have the audited ending balance from column (1). The budgeted opening balances (3)
B63: and (4) will be the anticipated ending balance for the current year, column (2).
A64: 7 | B64: Check that the "TOTAL ALL RESOURCES" amounts are correct.
A66: FORM 4 EXPENDITURES
A67: 1 | B67: Fill in the expenditure amounts, per program, in column (1) on pages 1-6, from your audited information.
A68: 2 | B68: Fill in the expenditure amounts, per program, in column (2) on pages 1-6, from your current year estimates.
A69: 3 | B69: Fill in the expenditure amounts, per program, in column (3) on pages 1-6, based on anticipated
B70: expenditures for the school year to begin July 1 for the tentative budget.
A71: 4 | B71: Fill in the expenditure amounts, per program, in column (4) on pages 1-6, based on the approved and
B72: adopted budget for the school year to begin July 1 for the final budget.
A73: 5 | B73: Fill in the remaining expenditures (Undistributed, food service, facilities and debt) in column (1) on pages
B74: 7-10, from your audited information. Do not forget to include sponsorship fees.
A75: 6 | B75: Fill in the remaining expenditures (Undistributed, food service, facilities and debt) in column (2) on pages
B76: 7-10, from your current year estimates. Do not forget to include sponsorship fees.
A77: 7 | B77: Fill in the remaining expenditures (Undistributed, food service, facilities and debt) in column (3) on pages
B78: 7-10, based on anticipated expenditures for the school year to begin July 1 for the tentative budget.
B79: Do not forget to include sponsorship fees.
A80: 8 | B80: Fill in the remaining expenditures (Undistributed, food service, facilities and debt) in column (4) on pages
B81: 7-10, based on the approved and adopted budget for the school year to begin July 1 for the final budget.
B82: Do not forget to include sponsorship fees.
A83: 9 | B83: Fill in the contingency amount under function 6300, if appropriate. Note that it is not to exceed 3% of all
B84: expenditures. This amount has been calculated for you at the bottom of page 10.
A85: 10 | B85: Fill in the ending balance under function 8000. This amount has been calculated for you at the bottom of
B86: page 10. If you do not agree, please check that all revenue and expense items have been included on
B87: Forms 3 and 4.
A88: 11 | B88: If the ending balance is less than zero, please reallocate your expenditures and/or revenues. We expect
B89: all charter schools to be fiscally responsible. A positive ending balance is required unless prior
B90: arrangements have been made, and approved by, the Deputy Superintendent of Administrative and Fiscal
B91: Services (NDE) and your sponsor.
A93: FORM 5 EXPENDITURE SUMMARY
A94: 1 | B94: This form calculates the information from Forms 3 and 4. Please check the numbers to verify that they
B95: are correct.
A97: FORM 6 PROPRIETARY OR ENTERPRISE
A98: 1 | B98: Form 6 is only filled out if you maintain proprietary or enterprise funds. This is unusual for charter schools.
A99: 2 | B99: Fill in the amounts of revenue per revenue code in column (1) from your audited information.
A100: 3 | B100: Fill in the amounts of revenue per revenue code in column (2) from your current year estimates.
A101: 4 | B101: Fill in the amounts of revenue per revenue code in column (3) based on anticipated revenue for the school
B102: year to begin July 1 for the tentative budget.
A103: 5 | B103: Fill in the amounts of revenue per revenue code in column (4) based on the approved and adopted budget
B104: for the school year to begin July 1 for the final budget.
A105: 6 | B105: Note: there will be a limited number of revenue sources so most of the revenue codes will be blank.
A106: 7 | B106: Enter the opening balance under revenue code 8000. Column (1) will have the audited opening balance.
B107: Column (2) will have the audited ending balance from column (1). The budgeted opening balances (3)
B108: and (4) will be the anticipated ending balance for the current year, column (2).
A109: 8 | B109: Check that the "TOTAL ALL RESOURCES" amounts are correct.
A110: 9 | B110: Fill in the expenditure amounts, per function, in column (1) from your audited information.
...

Sheet Form 1 Cover
A16: Charter School Budget
A20: Charter School - fill in the name of your school | F20: herewith submits the | H20: TENTATIVE or FINAL or AMENDED FINAL
A21: budget for the fiscal year ending | D21: =C138 -> June 30, 2015
A23: This budget contains | D23: governmental fund types with estimated expenditures of $ | K23: and
B24: proprietary funds with estimated expenses of $ | H24: .
A26: Per NAC 387.730:
B28: TENTATIVE budget is due to the clerk or secretary of the Charter School Governing Body and Nevada Department
C29: of Education (NDE) by April 15 annually.
B31: FINAL budget must be adopted on or before June 8 Annually. Copies of the approved final budget are
C32: SUBMITTED by the Charter School Governing Body to NDE, Legislative Council Bureau and the
C33: Charter School sponsor if other than the Department of Education.
A36: CERTIFICATION | G36: APPROVED BY THE GOVERNING BOARD
A38: I,
B39: (Print Name of Governing Board President)
B41: (Signature of Governing Board President)
B43: certify that all applicable funds and financial
B44: operations of this Local Government are
B45: listed herein
B47: Signed
B50: Dated:
A56: SCHEDULED PUBLIC HEARING:
A58: Date and Time: | G58: Publication Date
A60: Place:
J61: Form 1
J62: =C146 -> 41703
A126: Update all fiscal year reference to the appropriate fiscal year.
A130: Actual Prior Year | C130: 41455 | D130: Last day of FY | F130: - Estimated
A133: Estimated Current | C133: 2013/2014
A134: Current yr ending | C134: 41820
A137: Budget Year | C137: 2014-2015
A138: Budget yr ending | C138: June 30, 2015
A139: Budget yr ending | C139: 42185
A142: Form 6 | C142: July 1, 2014 | E142: 1st day of budget year
C143: 41821
A146: Updated on | C146: 41703 | D146: =C146 -> 41703

Sheet Form 2 Enrollment-DSA
A1: ENROLLMENT AND BASIC SUPPORT GUARANTEE INFORMATION
N2: WEIGHTED
F3: WEIGHTED | J3: WEIGHTED | N3: ESTIMATED
F4: ACTUAL PRIOR YEAR | J4: ACTUAL CURRENT YEAR | N4: YEAR
F5: ="ENDING "&TEXT('Form 1 Cover'!C130,"MM/DD/YY") -> ENDING 06/30/13 | J5: ="ENDING "&TEXT('Form 1 Cover'!C134, "MM/DD/YY") -> ENDING 06/30/14 | N5: ="ENDING "&TEXT('Form 1 Cover'!C139, "MM/DD/YY") -> ENDING 06/30/15
A7: 1. | B7: Pre-kindergarten
B8: (NRS 388.490) | E8: x .6 = | F8: =D8*0.6 -> 0 | I8: x .6 = | J8: =H8*0.6 -> 0 | M8: x .6 = | N8: =L8*0.6 -> 0
A10: 2. | B10: Kindergarten | E10: x .6 = | F10: =D10*0.6 -> 0 | I10: x .6 = | J10: =H10*0.6 -> 0 | M10: x .6 = | N10: =L10*0.6 -> 0
A12: 3. | B12: Elementary
A14: 4. | B14: Secondary
A16: 5. | B16: Ungraded
A18: 6. | B18: Subtotal | F18: =F8+F10+F12+F14+F16 -> 0 | J18: =J8+J10+J12+J14+J16 -> 0 | N18: =N8+N10+N12+N14+N16 -> 0
A20: 7. | B20: Students transported into
B21: Nevada from out-of-state
A23: 8. | B23: Students transported to
B24: another state
A26: 9. | B26: Total WEIGHTED enrollment | F26: =F18+F21-F24 -> 0 | J26: =J18+J21-J24 -> 0 | N26: =N18+N21-N24 -> 0
A28: 10. | B28: Hold Harmless
A31: 11. | B31: ="Basic support per pupil amount, Year " &PROPER(N5) -> Basic support per pupil amount, Year Ending 06/30/15 | J31: =L53 -> #DIV/0!
B32: Estimated per SB522 77th session | H32: WEIGHTED | L32: Use rates below:
B33: Fill in information for each district: | F33: ='Form 1 Cover'!C137 -> 2014-2015 | H33: ='Form 1 Cover'!C137 -> 2014-2015 | N33: Reference amounts for #12
D34: School District | F34: Rate revised 5/24/2013 | H34: Enrollment | J34: Subtotal | N34: Estimate: "Outside Revenue"
D35: Carson City | F35: 6643 | H35: 0 | J35: =F35*H35 -> 0 | N35: 1086
D36: Churchill | F36: 6629 | H36: 0 | J36: =F36*H36 -> 0 | N36: 1069
D37: Clark | F37: 5544 | H37: 0 | J37: =F37*H37 -> 0 | N37: 997
D38: Douglas | F38: 5998 | H38: 0 | J38: =F38*H38 -> 0 | N38: 2386
D39: Elko | F39: 6692 | H39: 0 | J39: =F39*H39 -> 0 | N39: 1113
D40: Esmeralda | F40: 15798 | H40: 0 | J40: =F40*H40 -> 0 | N40: 8308
D41: Eureka | F41: 100 | H41: 0 | J41: =F41*H41 -> 0 | N41: =43970-100 -> 43870
D42: Humboldt | F42: 5409 | H42: 0 | J42: =F42*H42 -> 0 | N42: 2047
D43: Lander | F43: 385 | H43: 0 | J43: =F43*H43 -> 0 | N43: =9984-100 -> 9884
D44: Lincoln | F44: 10500 | H44: 0 | J44: =F44*H44 -> 0 | N44: 1295
D45: Lyon | F45: 7186 | H45: 0 | J45: =F45*H45 -> 0 | N45: 922
D46: Mineral | F46: 9622 | H46: 0 | J46: =F46*H46 -> 0 | N46: 1683
D47: Nye | F47: 7085 | H47: 0 | J47: =F47*H47 -> 0 | N47: 1368
D48: Pershing | F48: 8738 | H48: 0 | J48: =F48*H48 -> 0 | N48: 2272
D49: Storey | F49: 8455 | H49: 0 | J49: =F49*H49 -> 0 | N49: 6494
D50: Washoe | F50: 5585 | H50: 0 | J50: =F50*H50 -> 0 | N50: 1138
D51: White Pine | F51: 7315 | H51: 0 | J51: =F51*H51 -> 0 | N51: 1902
D53: Multidistict | H53: =SUM(H35:H51) -> 0 | J53: =SUM(J35:J52) -> 0 | L53: =J53/H53 -> #DIV/0!
A55: 12. | B55: Estimated "Outside Revenue" (Supplemental Support) per pupil
B56: This is the per pupil share of local taxes, etc, from the district.
L57: Total Weighted-#9 | N57: Hold Harmless-#10
A58: 13. | B58: Total basic support for enrollee including outside revenue | L58: =N26*(J31+J55) -> #DIV/0! | N58: =N28*(J31+J55) -> #DIV/0!
A60: 14. | B60: Estimated number of special education program units | J60: (Should be 0 or 2 maximum - see prior year allotment)
G61: X | H61: 39768 | I61: amount per unit | L61: =H60*H61 -> 0
L63: Total Weighted | N63: Hold Harmless
A64: 15. | B64: TOTAL BASIC SUPPORT GUARANTEE (Number 13 +14) | L64: =L58+L61 -> #DIV/0! | N64: =N58+L61 -> #DIV/0!
A68: ="Fiscal Year "&TEXT('Form 1 Cover'!C137, "yy") -> Fiscal Year 2014-2015 | E68: Charter School | F68: ='Form 1 Cover'!A20 -> Charter School - fill in the name of your school
A70: Form 2 Enrollment - DSA | N70: ='Form 1 Cover'!$C$146 -> 41703

Sheet Form 3 Revenues
A1: Form 3 | D1: -1 | E1: -2 | F1: -3 | G1: -4 | H1: -4
E2: ESTIMATED | F2: ="BUDGET YEAR ENDING "&TEXT('Form 1 Cover'!C139, "MM/DD/YY") -> BUDGET YEAR ENDING 06/30/15
A3: ='Form 1 Cover'!A20 -> Charter School - fill in the name of your school | D3: ACTUAL PRIOR | E3: CURRENT | H3: AMENDED
C4: REVENUE | D4: YEAR ENDING | E4: YEAR ENDING | F4: TENTATIVE | G4: FINAL | H4: FINAL
D5: ='Form 1 Cover'!C130 -> 41455 | E5: ='Form 1 Cover'!C134 -> 41820 | F5: APPROVED | G5: APPROVED | H5: APPROVED
A6: 1000 | C6: LOCAL SOURCES
A7: 1100 | C7: Taxes
B8: 1110 | C8: Ad Valorem Taxes
B9: 1111 | C9: Net Proceed of Mines
B10: 1120 | C10: Sales & Use/School Support Taxes
B11: 1140 | C11: Penalties & Interest on Tax
B12: 1150 | C12: Residential Construction Tax
B13: 1190 | C13: Other
A14: 1200 | C14: Revenue from Local Govmt Units other than School Districts
A15: 1300 | C15: Tuition
B16: 1310 | C16: Tuition from Individuals
B17: 1320 | C17: Tuition-other Govt sources within State
B18: 1330 | C18: Tuition-other Govt sources out of State
A19: 1400 | C19: Transportation Fees
B20: 1410 | C20: Trans Fees from Individuals
B21: 1420 | C21: Trans Fees - other Govt within State
B22: 1430 | C22: Trans Fees - other Govt out of State
B23: 1440 | C23: Trans Fees - Other Private Sources
A24: 1500 | C24: Investment Income
A25: 1600 | C25: Food Services
B26: 1610 | C26: Daily Sales - Reimbursable Program
B27: 1620 | C27: Daily Sales - Non-Reimbursable Progrm
B28: 1630 | C28: Special Functions
B29: 1650 | C29: Daily Sales - Summer Food Program
A30: 1700 | C30: Direct Activities
A31: 1800 | C31: Community Service Activities
A32: 1900 | C32: Other Revenues
B33: 1910 | C33: Rent
B34: 1920 | C34: Donations
B35: 1930 | C35: Gains/Loss on Sales of Capital Assets
B36: 1940 | C36: Textbook Sales & Rentals
B37: 1950 | C37: Misc Revenues from Other Districts
B38: 1960 | C38: Misc Revenues from Other Local Govt
B39: 1970 | C39: Operating Revenues
B40: 1980 | C40: Refund of Prior Year's Expenditures
B41: 1990 | C41: Miscellaneous - local sources
A42: TOTAL LOCAL SOURCES | D42: =SUM(D7:D41) -> 0 | E42: =SUM(E7:E41) -> 0 | F42: =SUM(F7:F41) -> 0 | G42: =SUM(G7:G41) -> 0 | H42: =SUM(H7:H41) -> 0
A43: 3000 | C43: REVENUE FROM STATE SOURCES
A44: 3100 | C44: Unrestricted Grants-in-Aid
B45: 3110 | C45: Distributive School Account (DSA)
B46: 3115 | C46: Special Ed portion of DSA
A47: 3200 | C47: State Govt Restricted Funding
B48: 3210 | C48: Special Transportation
B49: 3220 | C49: Adult High School Diploma Program Fnd
B50: 3230 | C50: Class Size Reduction
A51: 3800 | C51: Revenue in Lieu of Taxes
A52: 3900 | C52: Revenue for/on Behalf of School Dist
A53: TOTAL STATE SOURCES | D53: =SUM(D44:D52) -> 0 | E53: =SUM(E44:E52) -> 0 | F53: =SUM(F44:F52) -> 0 | G53: =SUM(G44:G52) -> 0 | H53: =SUM(H44:H52) -> 0
A55: =A3 -> Charter School - fill in the name of your school | G55: ="Budget Fiscal Year "&TEXT('Form 1 Cover'!$C$137, "mm/dd/yy") -> Budget Fiscal Year 2014-2015
A57: Form 3 Revenues | D57: Page 1 of 2 | H57: ='Form 1 Cover'!C146 -> 41703
D58: -1 | E58: -2 | F58: -3 | G58: -4 | H58: -4
E59: ESTIMATED | F59: ="BUDGET YEAR ENDING "&TEXT('Form 1 Cover'!C196, "MM/DD/YY") -> BUDGET YEAR ENDING 01/00/00
D60: ACTUAL PRIOR | E60: CURRENT | H60: AMENDED
C61: REVENUE | D61: YEAR ENDING | E61: YEAR ENDING | F61: TENTATIVE | G61: FINAL | H61: FINAL
D62: ='Form 1 Cover'!C130 -> 41455 | E62: ='Form 1 Cover'!C134 -> 41820 | F62: APPROVED | G62: APPROVED | H62: APPROVED
A63: 4000 | C63: FEDERAL SOURCES
A64: 4100 | C64: Unrestricted Grants-in-Aid DIRECT from Fed Govt
B65: 4103 | C65: E-Rate Funds
A66: 4200 | C66: Unrestricted Grants-in-Aid from Fed Govt pass thru the State
A67: 4300 | C67: Restricted Grants-in-Aid Direct - Fed
A68: 4500 | C68: Restricted Grants-in-Aid Fed Govnt pass-thru the State
A69: 4700 | C69: Grants-in-Aid from Fed Govt Thru Other Intermediate Agencies
A70: 4800 | C70: Revenue in Lieu of Taxes
A71: 4900 | C71: Revenue for/on Behalf of School District
A72: TOTAL FEDERAL SOURCES | D72: =SUM(D64:D71) -> 0 | E72: =SUM(E64:E71) -> 0 | F72: =SUM(F64:F71) -> 0 | G72: =SUM(G64:G71) -> 0 | H72: =SUM(H64:H71) -> 0
D73: -1 | E73: -2 | F73: -3 | G73: -4 | H73: -4
E74: ESTIMATED | F74: ="BUDGET YEAR ENDING "&TEXT('Form 1 Cover'!C211, "MM/DD/YY") -> BUDGET YEAR ENDING 01/00/00
B75: OTHER RESOURCES AND | D75: ACTUAL PRIOR | E75: CURRENT | H75: AMENDED
B76: FUND BALANCE | D76: YEAR ENDING | E76: YEAR ENDING | F76: TENTATIVE | G76: FINAL | H76: FINAL
D77: =D62 -> 41455 | E77: =E62 -> 41820 | F77: APPROVED | G77: APPROVED | H77: APPROVED
A78: 5000 | C78: OTHER FINANCING SOURCES
A79: 5100 | C79: Issuance of Bonds
B80: 5110 | C80: Bond Principal
B81: 5120 | C81: Premium of Discount on the Issuance of Bonds
A82: 5200 | C82: Fund Transfers In
A83: 5300 | C83: Proceeds from the Disposal of Real or Personal Property
A84: 5400 | C84: Loan Proceeds
A85: 5500 | C85: Capital Lease Proceeds
A86: 5600 | C86: Other Long-Term Debt Proceeds
A87: 6000 | C87: Other Items
A88: 6100 | C88: Capital Contributions
A89: 6200 | C89: Amortization of Premium on Issuance of Bonds
A90: 6300 | C90: Special Items
A91: 6400 | C91: Extraordinary Items
A92: TOTAL OTHER SOURCES | D92: =SUM(D79:D91) -> 0 | E92: =SUM(E79:E91) -> 0 | F92: =SUM(F79:F91) -> 0 | G92: =SUM(G79:G91) -> 0 | H92: =SUM(H79:H91) -> 0
A93: 8000 OPENING FUND BALANCE
B94: Reserved Opening Balance
B95: Unreserved Opening Balance
A96: TOTAL OPENING FUND BALANCE | D96: =SUM(D94:D95) -> 0 | E96: =SUM(E94:E95) -> 0 | F96: =SUM(F94:F95) -> 0 | G96: =SUM(G94:G95) -> 0 | H96: =SUM(H94:H95) -> 0
B97: Prior Period Adjustments
B98: Residual Equity Transfers
A99: TOTAL ALL RESOURCES | D99: =D42+D53+D72+D92+D96 -> 0 | E99: =E42+E53+E72+E92+E96 -> 0 | F99: =F42+F53+F72+F92+F96 -> 0 | G99: =G42+G53+G72+G92+G96 -> 0 | H99: =H42+H53+H72+H92+H96 -> 0
A102: ='Form 1 Cover'!A20:E20 -> Charter School - fill in the name of your school | G102: ="Budget Fiscal Year "&TEXT('Form 1 Cover'!$C$137, "mm/dd/yy") -> Budget Fiscal Year 2014-2015
A105: Form 3 Revenues | E105: Page 2 of 2 | H105: ='Form 1 Cover'!C146 -> 41703

Sheet Form 4 Expenses
A1: ='Form 1 Cover'!A20 -> Charter School - fill in the name of your school | E1: -1 | F1: -2 | G1: -3 | H1: -4 | I1: -5
B2: Form 4 | F2: ESTIMATED | G2: ="BUDGET YEAR ENDING "&TEXT('Form 1 Cover'!C139, "MM/DD/YY") -> BUDGET YEAR ENDING 06/30/15
E3: ACTUAL PRIOR | F3: CURRENT | I3: AMENDED
B4: PROGRAM FUNCTION OBJECT | E4: YEAR ENDING | F4: YEAR ENDING | G4: TENTATIVE | H4: FINAL | I4: FINAL
E5: ='Form 1 Cover'!C130 -> 41455 | F5: ='Form 1 Cover'!C134 -> 41820 | G5: APPROVED | H5: APPROVED | I5: APPROVED
A6: 100 | C6: REGULAR PROGRAMS
B7: 1000 | D7: Instruction
C8: 100 | D8: Salaries
C9: 200 | D9: Benefits
C10: 300/400/500 Purchased Services
C11: 600 | D11: Supplies
C12: 700 | D12: Property
C13: 800 | D13: Other
B14: 2100-2600, 2900 Other Support Services
C15: 100 | D15: Salaries
C16: 200 | D16: Benefits
C17: 300/400/500 Purchased Services
C18: 600 | D18: Supplies
C19: 700 | D19: Property
C20: 800 | D20: Other
B21: 2700 Student Transportation
C22: 100 | D22: Salaries
C23: 200 | D23: Benefits
C24: 300/400/500 Purchased Services
C25: 600 | D25: Supplies
C26: 700 | D26: Property
C27: 800 | D27: Other
A28: 100 TOTAL REGULAR PROGRAMS | E28: =SUM(E8:E27) -> 0 | F28: =SUM(F8:F27) -> 0 | G28: =SUM(G8:G27) -> 0 | H28: =SUM(H8:H27) -> 0 | I28: =SUM(I8:I27) -> 0
A29: 140 | C29: Summer School for Reg Programs
B30: 1000 | D30: Instruction
C31: 100 | D31: Salaries
C32: 200 | D32: Benefits
C33: 300/400/500 Purchased Services
C34: 600 | D34: Supplies
C35: 700 | D35: Property
C36: 800 | D36: Other
B37: 2100-2600, 2900 Other Support Services
C38: 100 | D38: Salaries
C39: 200 | D39: Benefits
C40: 300/400/500 Purchased Services
C41: 600 | D41: Supplies
C42: 700 | D42: Property
C43: 800 | D43: Other
B44: 2700 Student Transportation
C45: 100 | D45: Salaries
C46: 200 | D46: Benefits
C47: 300/400/500 Purchased Services
C48: 600 | D48: Supplies
C49: 700 | D49: Property
C50: 800 | D50: Other
A51: 140 TOTAL Summer School - Reg Prog | E51: =SUM(E31:E50) -> 0 | F51: =SUM(F31:F50) -> 0 | G51: =SUM(G31:G50) -> 0 | H51: =SUM(H31:H50) -> 0 | I51: =SUM(I31:I50) -> 0
B53: ='Form 1 Cover'!A20 -> Charter School - fill in the name of your school | I53: ="Budget Fiscal Year "&TEXT('Form 1 Cover'!$C$137, "mm/dd/yy") -> Budget Fiscal Year 2014-2015
B55: Form 4 Expenditures | I55: ='Form 1 Cover'!$C$146 -> 41703
B58: ='Form 1 Cover'!A20 -> Charter School - fill in the name of your school | E58: -1 | F58: -2 | G58: -3 | H58: -4 | I58: -5
F59: ESTIMATED | G59: ="BUDGET YEAR ENDING "&TEXT('Form 1 Cover'!C194, "MM/DD/YY") -> BUDGET YEAR ENDING 01/00/00
E60: ACTUAL PRIOR | F60: CURRENT | I60: AMENDED
B61: PROGRAM FUNCTION OBJECT | E61: YEAR ENDING | F61: YEAR ENDING | G61: TENTATIVE | H61: FINAL | I61: FINAL
E62: ='Form 1 Cover'!C130 -> 41455 | F62: ='Form 1 Cover'!C134 -> 41820 | G62: APPROVED | H62: APPROVED | I62: APPROVED
A63: 200 | C63: SPECIAL PROGRAMS
B64: 1000 | D64: Instruction
C65: 100 | D65: Salaries
C66: 200 | D66: Benefits
C67: 300/400/500 Purchased Services
C68: 600 | D68: Supplies
C69: 700 | D69: Property
C70: 800 | D70: Other
B71: 2100-2600, 2900 Other Support Services
C72: 100 | D72: Salaries
C73: 200 | D73: Benefits
C74: 300/400/500 Purchased Services
C75: 600 | D75: Supplies
C76: 700 | D76: Property
C77: 800 | D77: Other
B78: 2700 Student Transportation
C79: 100 | D79: Salaries
C80: 200 | D80: Benefits
C81: 300/400/500 Purchased Services
C82: 600 | D82: Supplies
C83: 700 | D83: Property
C84: 800 | D84: Other
A85: 200 SPECIAL PROGRAMS | E85: =SUM(E65:E84) -> 0 | F85: =SUM(F65:F84) -> 0 | G85: =SUM(G65:G84) -> 0 | H85: =SUM(H65:H84) -> 0 | I85: =SUM(I65:I84) -> 0
A86: 240 | C86: Summer School for Special Programs
B87: 1000 | D87: Instruction
C88: 100 | D88: Salaries
C89: 200 | D89: Benefits
C90: 300/400/500 Purchased Services
C91: 600 | D91: Supplies
C92: 700 | D92: Property
C93: 800 | D93: Other
B94: 2100-2600, 2900 Other Support Services
C95: 100 | D95: Salaries
C96: 200 | D96: Benefits
C97: 300/400/500 Purchased Services
C98: 600 | D98: Supplies
C99: 700 | D99: Property
C100: 800 | D100: Other
B101: 2700 Student Transportation
C102: 100 | D102: Salaries
C103: 200 | D103: Benefits
C104: 300/400/500 Purchased Services
...

Sheet Form 5 Exp Summary
A1: ="TENTATIVE BUDGET "&TEXT('Form 1 Cover'!C137, "MM/DD/YY") -> TENTATIVE BUDGET 2014-2015 | C1: Obj 100 | D1: Obj 200 | E1: Obj 300-900
A2: (1) PROGRAM OR FUNCTION | C2: (2) SALARIES AND WAGES | D2: (3) EMPLOYEE BENEFITS | E2: (4) SERVICES SUPPLIES AND OTHER | F2: (5) SUB-TOTAL REQUIRE- MENTS
A3: PROGRAM EXPENDITURES
A4: 100 | B4: Regular | C4: ='Form 4 Expenses'!G8+'Form 4 Expenses'!G15+'Form 4 Expenses'!G22+'Form 4 Expenses'!G31+'Form 4 Expenses'!G38+'Form 4 Expenses'!G45 -> 0 | D4: ='Form 4 Expenses'!G9+'Form 4 Expenses'!G16+'Form 4 Expenses'!G23+'Form 4 Expenses'!G32+'Form 4 Expenses'!G39+'Form 4 Expenses'!G46 -> 0 | E4: ='Form 4 Expenses'!G28+'Form 4 Expenses'!G51-'Form 5 Exp Summary'!C4-'Form 5 Exp Summary'!D4 -> 0 | F4: =SUM(C4:E4) -> 0
A5: 200 | B5: Special | C5: ='Form 4 Expenses'!G65+'Form 4 Expenses'!G72+'Form 4 Expenses'!G79+'Form 4 Expenses'!G88+'Form 4 Expenses'!G95+'Form 4 Expenses'!G102+'Form 4 Expenses'!G122+'Form 4 Expenses'!G129+'Form 4 Expenses'!G136 -> 0 | D5: ='Form 4 Expenses'!G66+'Form 4 Expenses'!G73+'Form 4 Expenses'!G80+'Form 4 Expenses'!G89+'Form 4 Expenses'!G96+'Form 4 Expenses'!G103+'Form 4 Expenses'!G123+'Form 4 Expenses'!G130+'Form 4 Expenses'!G137 -> 0 | E5: ='Form 4 Expenses'!G85+'Form 4 Expenses'!G108+'Form 4 Expenses'!G142-'Form 5 Exp Summary'!C5-'Form 5 Exp Summary'!D5 -> 0 | F5: =SUM(C5:E5) -> 0
A6: 300 | B6: Vocational | C6: ='Form 4 Expenses'!G145+'Form 4 Expenses'!G152+'Form 4 Expenses'!G159+'Form 4 Expenses'!G180+'Form 4 Expenses'!G187+'Form 4 Expenses'!G194 -> 0 | D6: ='Form 4 Expenses'!G146+'Form 4 Expenses'!G153+'Form 4 Expenses'!G160+'Form 4 Expenses'!G181+'Form 4 Expenses'!G188+'Form 4 Expenses'!G195 -> 0 | E6: ='Form 4 Expenses'!G165+'Form 4 Expenses'!G200-'Form 5 Exp Summary'!C6-'Form 5 Exp Summary'!D6 -> 0 | F6: =SUM(C6:E6) -> 0
A7: 400 | B7: Other PK-12 | C7: ='Form 4 Expenses'!G203+'Form 4 Expenses'!G210+'Form 4 Expenses'!G217+'Form 4 Expenses'!G238+'Form 4 Expenses'!G245+'Form 4 Expenses'!G252+'Form 4 Expenses'!G261+'Form 4 Expenses'!G268+'Form 4 Expenses'!G275 -> 0 | D7: ='Form 4 Expenses'!G204+'Form 4 Expenses'!G211+'Form 4 Expenses'!G218+'Form 4 Expenses'!G239+'Form 4 Expenses'!G246+'Form 4 Expenses'!G253+'Form 4 Expenses'!G262+'Form 4 Expenses'!G269+'Form 4 Expenses'!G276 -> 0 | E7: ='Form 4 Expenses'!G223+'Form 4 Expenses'!G258+'Form 4 Expenses'!G281-'Form 5 Exp Summary'!C7-'Form 5 Exp Summary'!D7 -> 0 | F7: =SUM(C7:E7) -> 0
A8: 500 | B8: Nonpublic School | F8: =SUM(C8:E8) -> 0
A9: 600 | B9: Adult Education | F9: =SUM(C9:E9) -> 0
A10: 800 | B10: Community Services | C10: ='Form 4 Expenses'!G296+'Form 4 Expenses'!G303+'Form 4 Expenses'!G310 -> 0 | D10: ='Form 4 Expenses'!G297+'Form 4 Expenses'!G304+'Form 4 Expenses'!G311 -> 0 | E10: ='Form 4 Expenses'!G316-'Form 5 Exp Summary'!C10-'Form 5 Exp Summary'!D10 -> 0 | F10: =SUM(C10:E10) -> 0
A11: 900 | B11: Co-Curricular/Extra Curricular | C11: ='Form 4 Expenses'!G319+'Form 4 Expenses'!G326+'Form 4 Expenses'!G333 -> 0 | D11: ='Form 4 Expenses'!G320+'Form 4 Expenses'!G327+'Form 4 Expenses'!G334 -> 0 | E11: ='Form 4 Expenses'!G339-'Form 5 Exp Summary'!C11-'Form 5 Exp Summary'!D11 -> 0 | F11: =SUM(C11:E11) -> 0
A12: PROGRAM TOTALS | C12: =SUM(C4:C11) -> 0 | D12: =SUM(D4:D11) -> 0 | E12: =SUM(E4:E11) -> 0 | F12: =SUM(F4:F11) -> 0
A14: 000 | B14: Undistributed Expenditures
A15: 2000 | B15: Support Services | C15: ='Form 4 Expenses'!G351+'Form 4 Expenses'!G359+'Form 4 Expenses'!G367+'Form 4 Expenses'!G375+'Form 4 Expenses'!G383+'Form 4 Expenses'!G403+'Form 4 Expenses'!G411+'Form 4 Expenses'!G419 -> 0 | D15: ='Form 4 Expenses'!G352+'Form 4 Expenses'!G360+'Form 4 Expenses'!G368+'Form 4 Expenses'!G376+'Form 4 Expenses'!G384+'Form 4 Expenses'!G404+'Form 4 Expenses'!G412+'Form 4 Expenses'!G420 -> 0 | E15: ='Form 4 Expenses'!G426-'Form 5 Exp Summary'!C15-'Form 5 Exp Summary'!D15 -> 0 | F15: =SUM(C15:E15) -> 0
A16: 3100 | B16: Food Service | C16: ='Form 4 Expenses'!G428 -> 0 | D16: ='Form 4 Expenses'!G429 -> 0 | E16: ='Form 4 Expenses'!G434-C16-D16 -> 0 | F16: =SUM(C16:E16) -> 0
A17: 4000 | B17: Facility Acquisition and Construction | E17: ='Form 4 Expenses'!G520 -> 0 | F17: =SUM(C17:E17) -> 0
A18: 5000 | B18: Debt Service | E18: ='Form 4 Expenses'!G521 -> 0 | F18: =SUM(C18:E18) -> 0
A19: 6300 | B19: Contingency | F19: ='Form 4 Expenses'!G524 -> 0
A20: 8000 | B20: Ending Balance | F20: ='Form 4 Expenses'!G526+'Form 4 Expenses'!G527 -> 0
A21: UNDISTRIBUTED TOTALS | C21: =SUM(C15:C20) -> 0 | D21: =SUM(D15:D20) -> 0 | E21: =SUM(E15:E20) -> 0 | F21: =SUM(F15:F20) -> 0
A22: TOTAL ALL FUNDS TENTATIVE | C22: =C12+C21 -> 0 | D22: =D12+D21 -> 0 | E22: =E12+E21 -> 0 | F22: =F12+F21 -> 0
A24: ="FINAL BUDGET "&TEXT('Form 1 Cover'!C137, "MM/DD/YY") -> FINAL BUDGET 2014-2015 | C24: Obj 100 | D24: Obj 200 | E24: Obj 300-900
A25: (1) PROGRAM OR FUNCTION | C25: (2) SALARIES AND WAGES | D25: (3) EMPLOYEE BENEFITS | E25: (4) SERVICES SUPPLIES AND OTHER | F25: (5) SUB-TOTAL REQUIRE- MENTS
A26: PROGRAM EXPENDITURES
A27: 100 | B27: Regular | C27: ='Form 4 Expenses'!H8+'Form 4 Expenses'!H15+'Form 4 Expenses'!H22+'Form 4 Expenses'!H31+'Form 4 Expenses'!H38+'Form 4 Expenses'!H45 -> 0 | D27: ='Form 4 Expenses'!H9+'Form 4 Expenses'!H16+'Form 4 Expenses'!H23+'Form 4 Expenses'!H32+'Form 4 Expenses'!H39+'Form 4 Expenses'!H46 -> 0 | E27: ='Form 4 Expenses'!H28+'Form 4 Expenses'!H51-'Form 5 Exp Summary'!C27-'Form 5 Exp Summary'!D27 -> 0 | F27: =SUM(C27:E27) -> 0
A28: 200 | B28: Special | C28: ='Form 4 Expenses'!H65+'Form 4 Expenses'!H72+'Form 4 Expenses'!H79+'Form 4 Expenses'!H88+'Form 4 Expenses'!H95+'Form 4 Expenses'!H102+'Form 4 Expenses'!H122+'Form 4 Expenses'!H129+'Form 4 Expenses'!H136 -> 0 | D28: ='Form 4 Expenses'!H66+'Form 4 Expenses'!H73+'Form 4 Expenses'!H80+'Form 4 Expenses'!H89+'Form 4 Expenses'!H96+'Form 4 Expenses'!H103+'Form 4 Expenses'!H123+'Form 4 Expenses'!H130+'Form 4 Expenses'!H137 -> 0 | E28: ='Form 4 Expenses'!H85+'Form 4 Expenses'!H108+'Form 4 Expenses'!H142-'Form 5 Exp Summary'!C28-'Form 5 Exp Summary'!D28 -> 0 | F28: =SUM(C28:E28) -> 0
A29: 300 | B29: Vocational | C29: ='Form 4 Expenses'!H145+'Form 4 Expenses'!H152+'Form 4 Expenses'!H159+'Form 4 Expenses'!H180+'Form 4 Expenses'!H187+'Form 4 Expenses'!H194 -> 0 | D29: ='Form 4 Expenses'!H146+'Form 4 Expenses'!H153+'Form 4 Expenses'!H160+'Form 4 Expenses'!H181+'Form 4 Expenses'!H188+'Form 4 Expenses'!H195 -> 0 | E29: ='Form 4 Expenses'!H165+'Form 4 Expenses'!H200-'Form 5 Exp Summary'!C29-'Form 5 Exp Summary'!D29 -> 0 | F29: =SUM(C29:E29) -> 0
A30: 400 | B30: Other PK-12 | C30: ='Form 4 Expenses'!H203+'Form 4 Expenses'!H210+'Form 4 Expenses'!H217+'Form 4 Expenses'!H238+'Form 4 Expenses'!H245+'Form 4 Expenses'!H252+'Form 4 Expenses'!H261+'Form 4 Expenses'!H268+'Form 4 Expenses'!H275 -> 0 | D30: ='Form 4 Expenses'!H204+'Form 4 Expenses'!H211+'Form 4 Expenses'!H218+'Form 4 Expenses'!H239+'Form 4 Expenses'!H246+'Form 4 Expenses'!H253+'Form 4 Expenses'!H262+'Form 4 Expenses'!H269+'Form 4 Expenses'!H276 -> 0 | E30: ='Form 4 Expenses'!H223+'Form 4 Expenses'!H258+'Form 4 Expenses'!H281-'Form 5 Exp Summary'!C30-'Form 5 Exp Summary'!D30 -> 0 | F30: =SUM(C30:E30) -> 0
A31: 500 | B31: Nonpublic School | C31: 0 | D31: 0 | E31: 0 | F31: =SUM(C31:E31) -> 0
A32: 600 | B32: Adult Education | C32: 0 | D32: 0 | E32: 0 | F32: =SUM(C32:E32) -> 0
A33: 800 | B33: Community Services | C33: ='Form 4 Expenses'!H296+'Form 4 Expenses'!H303+'Form 4 Expenses'!H310 -> 0 | D33: ='Form 4 Expenses'!H297+'Form 4 Expenses'!H304+'Form 4 Expenses'!H311 -> 0 | E33: ='Form 4 Expenses'!H316-'Form 5 Exp Summary'!C33-'Form 5 Exp Summary'!D33 -> 0 | F33: =SUM(C33:E33) -> 0
A34: 900 | B34: Co-Curricular/Extra Curricular | C34: ='Form 4 Expenses'!H319+'Form 4 Expenses'!H326+'Form 4 Expenses'!H333 -> 0 | D34: ='Form 4 Expenses'!H320+'Form 4 Expenses'!H327+'Form 4 Expenses'!H334 -> 0 | E34: ='Form 4 Expenses'!H339-'Form 5 Exp Summary'!C34-'Form 5 Exp Summary'!D34 -> 0 | F34: =SUM(C34:E34) -> 0
A35: PROGRAM TOTALS | C35: =SUM(C27:C34) -> 0 | D35: =SUM(D27:D34) -> 0 | E35: =SUM(E27:E34) -> 0 | F35: =SUM(F27:F34) -> 0
A37: 000 | B37: Undistributed Expenditures
A38: 2000 | B38: Support Services | C38: ='Form 4 Expenses'!H351+'Form 4 Expenses'!H359+'Form 4 Expenses'!H367+'Form 4 Expenses'!H375+'Form 4 Expenses'!H383+'Form 4 Expenses'!H403+'Form 4 Expenses'!H411+'Form 4 Expenses'!H419 -> 0 | D38: ='Form 4 Expenses'!H352+'Form 4 Expenses'!H360+'Form 4 Expenses'!H368+'Form 4 Expenses'!H376+'Form 4 Expenses'!H384+'Form 4 Expenses'!H404+'Form 4 Expenses'!H412+'Form 4 Expenses'!H420 -> 0 | E38: ='Form 4 Expenses'!H426-'Form 5 Exp Summary'!C38-'Form 5 Exp Summary'!D38 -> 0 | F38: =SUM(C38:E38) -> 0
A39: 3100 | B39: Food Service | C39: ='Form 4 Expenses'!H428 -> 0 | D39: ='Form 4 Expenses'!H429 -> 0 | E39: ='Form 4 Expenses'!H434-'Form 5 Exp Summary'!C39-'Form 5 Exp Summary'!D39 -> 0 | F39: =SUM(C39:E39) -> 0
A40: 4000 | B40: Facility Acquisition and Construction | E40: ='Form 4 Expenses'!H520 -> 0 | F40: =SUM(C40:E40) -> 0
A41: 5000 | B41: Debt Service | E41: ='Form 4 Expenses'!H521 -> 0 | F41: =SUM(C41:E41) -> 0
A42: 6300 | B42: Contingency | F42: ='Form 4 Expenses'!H524 -> 0
A43: 8000 | B43: Ending Balance | F43: ='Form 4 Expenses'!H526+'Form 4 Expenses'!H527 -> 0
A44: UNDISTRIBUTED TOTALS | C44: =SUM(C38:C43) -> 0 | D44: =SUM(D38:D43) -> 0 | E44: =SUM(E38:E43) -> 0 | F44: =SUM(F38:F43) -> 0
A45: TOTAL ALL FUNDS FINAL BUDGET | C45: =C35+C44 -> 0 | D45: =D35+D44 -> 0 | E45: =E35+E44 -> 0 | F45: =F35+F44 -> 0
B47: ='Form 1 Cover'!A20 -> Charter School - fill in the name of your school | E47: ="Budget Fiscal Year "&TEXT('Form 1 Cover'!$C$137, "mm/dd/yy") -> Budget Fiscal Year 2014-2015
B49: Form 5 Exp Summary | C49: Page 1 of 1 | F49: ='Form 1 Cover'!$C$146 -> 41703
A51: ="FINAL AMENDED BUDGET "&TEXT('Form 1 Cover'!F130, "MM/DD/YY") -> FINAL AMENDED BUDGET - Estimated | C51: Obj 100 | D51: Obj 200 | E51: Obj 300-900
A52: (1) PROGRAM OR FUNCTION | C52: (2) SALARIES AND WAGES | D52: (3) EMPLOYEE BENEFITS | E52: (4) SERVICES SUPPLIES AND OTHER | F52: (5) SUB-TOTAL REQUIRE- MENTS
A53: PROGRAM EXPENDITURES
A54: 100 | B54: Regular | C54: ='Form 4 Expenses'!I8+'Form 4 Expenses'!I15+'Form 4 Expenses'!I22+'Form 4 Expenses'!I31+'Form 4 Expenses'!I38+'Form 4 Expenses'!I45 -> 0 | D54: ='Form 4 Expenses'!I9+'Form 4 Expenses'!I16+'Form 4 Expenses'!I23+'Form 4 Expenses'!I32+'Form 4 Expenses'!I39+'Form 4 Expenses'!I46 -> 0 | E54: ='Form 4 Expenses'!I10+'Form 4 Expenses'!I11+'Form 4 Expenses'!I12+'Form 4 Expenses'!I13+'Form 4 Expenses'!I17+'Form 4 Expenses'!I18+'Form 4 Expenses'!I19+'Form 4 Expenses'!I20+'Form 4 Expenses'!I24+'Form 4 Expenses'!I25+'Form 4 Expenses'!I26+'Form 4 Expenses'!I27+'Form 4 Expenses'!I33+'Form 4 Expenses'!I34+'Form 4 Expenses'!I35+'Form 4 Expenses'!I36+'Form 4 Expenses'!I40+'Form 4 Expenses'!I41+'Form 4 Expenses'!I42+'Form 4 Expenses'!I43+'Form 4 Expenses'!I47+'Form 4 Expenses'!I48+'Form 4 Expenses'!I49+'Form 4 Expenses'!I50 -> 0 | F54: =SUM(C54:E54) -> 0
A55: 200 | B55: Special | C55: ='Form 4 Expenses'!I65+'Form 4 Expenses'!I72+'Form 4 Expenses'!I79+'Form 4 Expenses'!I88+'Form 4 Expenses'!I95+'Form 4 Expenses'!I102+'Form 4 Expenses'!I122+'Form 4 Expenses'!I129+'Form 4 Expenses'!I136 -> 0 | D55: ='Form 4 Expenses'!I66+'Form 4 Expenses'!I73+'Form 4 Expenses'!I80+'Form 4 Expenses'!I89+'Form 4 Expenses'!I96+'Form 4 Expenses'!I103+'Form 4 Expenses'!I123+'Form 4 Expenses'!I130+'Form 4 Expenses'!I137 -> 0 | E55: ='Form 4 Expenses'!I67+'Form 4 Expenses'!I68+'Form 4 Expenses'!I69+'Form 4 Expenses'!I70+'Form 4 Expenses'!I74+'Form 4 Expenses'!I75+'Form 4 Expenses'!I76+'Form 4 Expenses'!I77+'Form 4 Expenses'!I81+'Form 4 Expenses'!I82+'Form 4 Expenses'!I83+'Form 4 Expenses'!I84+'Form 4 Expenses'!I90+'Form 4 Expenses'!I91+'Form 4 Expenses'!I92+'Form 4 Expenses'!I93+'Form 4 Expenses'!I97+'Form 4 Expenses'!I98+'Form 4 Expenses'!I99+'Form 4 Expenses'!I100+'Form 4 Expenses'!I104+'Form 4 Expenses'!I105+'Form 4 Expenses'!I106+'Form 4 Expenses'!I107+'Form 4 Expenses'!I124+'Form 4 Expenses'!I125+'Form 4 Expenses'!I126+'Form 4 Expenses'!I127+'Form 4 Expenses'!I131+'Form 4 Expenses'!I132+'Form 4 Expenses'!I133+'Form 4 Expenses'!I134+'Form 4 Expenses'!I138+'Form 4 Expenses'!I139+'Form 4 Expenses'!I140+'Form 4 Expenses'!I141 -> 0 | F55: =SUM(C55:E55) -> 0
A56: 300 | B56: Vocational | C56: ='Form 4 Expenses'!I145+'Form 4 Expenses'!I152+'Form 4 Expenses'!I159+'Form 4 Expenses'!I180+'Form 4 Expenses'!I187+'Form 4 Expenses'!I194 -> 0 | D56: ='Form 4 Expenses'!I146+'Form 4 Expenses'!I153+'Form 4 Expenses'!I160+'Form 4 Expenses'!I181+'Form 4 Expenses'!I188+'Form 4 Expenses'!I195 -> 0 | E56: ='Form 4 Expenses'!I147+'Form 4 Expenses'!I148+'Form 4 Expenses'!I149+'Form 4 Expenses'!I150+'Form 4 Expenses'!I154+'Form 4 Expenses'!I155+'Form 4 Expenses'!I156+'Form 4 Expenses'!I157+'Form 4 Expenses'!I161+'Form 4 Expenses'!I162+'Form 4 Expenses'!I163+'Form 4 Expenses'!I164+'Form 4 Expenses'!I182+'Form 4 Expenses'!I183+'Form 4 Expenses'!I184+'Form 4 Expenses'!I185+'Form 4 Expenses'!I189+'Form 4 Expenses'!I190+'Form 4 Expenses'!I191+'Form 4 Expenses'!I192+'Form 4 Expenses'!I196+'Form 4 Expenses'!I197+'Form 4 Expenses'!I198+'Form 4 Expenses'!I199 -> 0 | F56: =SUM(C56:E56) -> 0
A57: 400 | B57: Other PK-12 | C57: ='Form 4 Expenses'!I203+'Form 4 Expenses'!I210+'Form 4 Expenses'!I217+'Form 4 Expenses'!I238+'Form 4 Expenses'!I245+'Form 4 Expenses'!I252+'Form 4 Expenses'!I261+'Form 4 Expenses'!I268+'Form 4 Expenses'!I275 -> 0 | D57: ='Form 4 Expenses'!I204+'Form 4 Expenses'!I211+'Form 4 Expenses'!I218+'Form 4 Expenses'!I239+'Form 4 Expenses'!I246+'Form 4 Expenses'!I253+'Form 4 Expenses'!I262+'Form 4 Expenses'!I269+'Form 4 Expenses'!I276 -> 0 | E57: ='Form 4 Expenses'!I205+'Form 4 Expenses'!I206+'Form 4 Expenses'!I207+'Form 4 Expenses'!I208+'Form 4 Expenses'!I212+'Form 4 Expenses'!I213+'Form 4 Expenses'!I214+'Form 4 Expenses'!I215+'Form 4 Expenses'!I219+'Form 4 Expenses'!I220+'Form 4 Expenses'!I221+'Form 4 Expenses'!I222+'Form 4 Expenses'!I240+'Form 4 Expenses'!I241+'Form 4 Expenses'!I242+'Form 4 Expenses'!I243+'Form 4 Expenses'!I247+'Form 4 Expenses'!I248+'Form 4 Expenses'!I249+'Form 4 Expenses'!I250+'Form 4 Expenses'!I254+'Form 4 Expenses'!I255+'Form 4 Expenses'!I256+'Form 4 Expenses'!I257+'Form 4 Expenses'!I263+'Form 4 Expenses'!I264+'Form 4 Expenses'!I265+'Form 4 Expenses'!I266+'Form 4 Expenses'!I270+'Form 4 Expenses'!I271+'Form 4 Expenses'!I272+'Form 4 Expenses'!I273+'Form 4 Expenses'!I277+'Form 4 Expenses'!I278+'Form 4 Expenses'!I279+'Form 4 Expenses'!I280 -> 0 | F57: =SUM(C57:E57) -> 0
A58: 500 | B58: Nonpublic School | C58: 0 | D58: 0 | E58: 0 | F58: =SUM(C58:E58) -> 0
A59: 600 | B59: Adult Education | C59: 0 | D59: 0 | E59: 0 | F59: =SUM(C59:E59) -> 0
A60: 800 | B60: Community Services | C60: ='Form 4 Expenses'!I296+'Form 4 Expenses'!I303+'Form 4 Expenses'!I310 -> 0 | D60: ='Form 4 Expenses'!I297+'Form 4 Expenses'!I304+'Form 4 Expenses'!I311 -> 0 | E60: ='Form 4 Expenses'!I298+'Form 4 Expenses'!I299+'Form 4 Expenses'!I300+'Form 4 Expenses'!I301+'Form 4 Expenses'!I305+'Form 4 Expenses'!I306+'Form 4 Expenses'!I307+'Form 4 Expenses'!I308+'Form 4 Expenses'!I312+'Form 4 Expenses'!I313+'Form 4 Expenses'!I314+'Form 4 Expenses'!I315 -> 0 | F60: =SUM(C60:E60) -> 0
A61: 900 | B61: Co-Curricular/Extra Curricular | C61: ='Form 4 Expenses'!I319+'Form 4 Expenses'!I326+'Form 4 Expenses'!I333 -> 0 | D61: ='Form 4 Expenses'!I320+'Form 4 Expenses'!I327+'Form 4 Expenses'!I334 -> 0 | E61: ='Form 4 Expenses'!I321+'Form 4 Expenses'!I322+'Form 4 Expenses'!I323+'Form 4 Expenses'!I324+'Form 4 Expenses'!I328+'Form 4 Expenses'!I329+'Form 4 Expenses'!I330+'Form 4 Expenses'!I331+'Form 4 Expenses'!I335+'Form 4 Expenses'!I336+'Form 4 Expenses'!I337+'Form 4 Expenses'!I338 -> 0 | F61: =SUM(C61:E61) -> 0
A62: PROGRAM TOTALS | C62: =SUM(C54:C61) -> 0 | D62: =SUM(D54:D61) -> 0 | E62: =SUM(E54:E61) -> 0 | F62: =SUM(F54:F61) -> 0
A64: 000 | B64: Undistributed Expenditures
A65: 2000 | B65: Support Services | C65: ='Form 4 Expenses'!I351+'Form 4 Expenses'!I359+'Form 4 Expenses'!I367+'Form 4 Expenses'!I375+'Form 4 Expenses'!I383+'Form 4 Expenses'!I403+'Form 4 Expenses'!I411+'Form 4 Expenses'!I419 -> 0 | D65: ='Form 4 Expenses'!I352+'Form 4 Expenses'!I360+'Form 4 Expenses'!I368+'Form 4 Expenses'!I376+'Form 4 Expenses'!I384+'Form 4 Expenses'!I404+'Form 4 Expenses'!I412+'Form 4 Expenses'!I420 -> 0 | E65: ='Form 4 Expenses'!I353+'Form 4 Expenses'!I354+'Form 4 Expenses'!I355+'Form 4 Expenses'!I356+'Form 4 Expenses'!I361+'Form 4 Expenses'!I362+'Form 4 Expenses'!I363+'Form 4 Expenses'!I364+'Form 4 Expenses'!I369+'Form 4 Expenses'!I370+'Form 4 Expenses'!I371+'Form 4 Expenses'!I372+'Form 4 Expenses'!I377+'Form 4 Expenses'!I378+'Form 4 Expenses'!I379+'Form 4 Expenses'!I380+'Form 4 Expenses'!I385+'Form 4 Expenses'!I386+'Form 4 Expenses'!I387+'Form 4 Expenses'!I388+'Form 4 Expenses'!I405+'Form 4 Expenses'!I406+'Form 4 Expenses'!I407+'Form 4 Expenses'!I408+'Form 4 Expenses'!I413+'Form 4 Expenses'!I414+'Form 4 Expenses'!I415+'Form 4 Expenses'!I416+'Form 4 Expenses'!I421+'Form 4 Expenses'!I422+'Form 4 Expenses'!I423+'Form 4 Expenses'!I424 -> 0 | F65: =SUM(C65:E65) -> 0
A66: 3100 | B66: Food Service | C66: ='Form 4 Expenses'!I428 -> 0 | D66: ='Form 4 Expenses'!I429 -> 0 | E66: ='Form 4 Expenses'!I430+'Form 4 Expenses'!I431+'Form 4 Expenses'!I432+'Form 4 Expenses'!I433 -> 0 | F66: =SUM(C66:E66) -> 0
A67: 4000 | B67: Facility Acquisition and Construction | E67: ='Form 4 Expenses'!I520 -> 0 | F67: =SUM(C67:E67) -> 0
A68: 5000 | B68: Debt Service | E68: ='Form 4 Expenses'!I521 -> 0 | F68: =SUM(C68:E68) -> 0
A69: 6300 | B69: Contingency | F69: ='Form 4 Expenses'!I524 -> 0
A70: 8000 | B70: Ending Balance | F70: ='Form 4 Expenses'!I526+'Form 4 Expenses'!I527 -> 0
A71: UNDISTRIBUTED TOTALS | C71: =SUM(C65:C70) -> 0 | D71: =SUM(D65:D70) -> 0 | E71: =SUM(E65:E70) -> 0 | F71: =SUM(F65:F70) -> 0
A72: TOTAL FINAL AMENDED BUDGET | C72: =C62+C71 -> 0 | D72: =D62+D71 -> 0 | E72: =E62+E71 -> 0 | F72: =F62+F71 -> 0
B74: ='Form 1 Cover'!A20 -> Charter School - fill in the name of your school | E74: ="Budget Fiscal Year "&TEXT('Form 1 Cover'!$C$137, "mm/dd/yy") -> Budget Fiscal Year 2014-2015
B76: Form 5 Exp Summary | C76: Page 2 of 2 | F76: ='Form 1 Cover'!$C$146 -> 41703

Sheet Form 6 Proprietary-Enterprise
A1: Form 6 | D1: PROPRIETARY OR ENTERPRISE FUND
A3: ='Form 1 Cover'!A20 -> Charter School - fill in the name of your school
D4: -1 | E4: -2 | F4: -3 | G4: -4
B5: Fund: | E5: ESTIMATED | F5: ="BUDGET YEAR ENDING "&TEXT('Form 1 Cover'!C139, "MM/DD/YY") -> BUDGET YEAR ENDING 06/30/15
D6: ACTUAL PRIOR | E6: CURRENT
C7: REVENUE | D7: YEAR ENDING | E7: YEAR ENDING | F7: TENTATIVE | G7: FINAL
D8: ='Form 1 Cover'!C130 -> 41455 | E8: ='Form 1 Cover'!C134 -> 41820 | F8: APPROVED | G8: APPROVED
A9: 1000 | C9: LOCAL SOURCES
A10: 1300 | C10: Tuition
A11: 1400 | C11: Transportation Fees
A12: 1500 | C12: Investment Income
A13: 1600 | C13: Food Services
A14: 1700 | C14: Direct Activities
A15: 1800 | C15: Community Service Activities
A16: 1900 | C16: Other Revenues
A17: TOTAL LOCAL SOURCES | D17: =SUM(D10:D16) -> 0 | E17: =SUM(E10:E16) -> 0 | F17: =SUM(F10:F16) -> 0 | G17: =SUM(G10:G16) -> 0
A18: 3000 | C18: REVENUE FROM STATE SOURCES
A19: 3100 | C19: Unrestricted Grants-in-Aid
A20: 3200 | C20: State Govt Restricted Funding
A21: TOTAL STATE SOURCES | D21: =SUM(D19:D20) -> 0 | E21: =SUM(E19:E20) -> 0 | F21: =SUM(F19:F20) -> 0 | G21: =SUM(G19:G20) -> 0
A22: 4000 | C22: FEDERAL SOURCES
A23: 4100 | C23: Unrestricted Grants-in-Aid DIRECT from Fed Govt
A24: 4200 | C24: Unrestricted Grants-in-Aid from Fed Govt pass thru the State
A25: 4300 | C25: Restricted Grants-in-Aid Direct - Fed
A26: 4500 | C26: Restricted Grants-in-Aid Fed Govnt pass-thru the State
A27: 4700 | C27: Grants-in-Aid from Fed Govt Thru Other Intermediate Agencies
A28: TOTAL FEDERAL SOURCES | D28: =SUM(D23:D27) -> 0 | E28: =SUM(E23:E27) -> 0 | F28: =SUM(F23:F27) -> 0 | G28: =SUM(G23:G27) -> 0
A29: 5000 | C29: OTHER FINANCING SOURCES
A30: 5200 | C30: Fund Transfers In
A31: 5300 | C31: Proceeds from the Disposal of Real or Personal Property
A32: 5400 | C32: Loan Proceeds
A33: 5500 | C33: Capital Lease Proceeds
A34: 5600 | C34: Other Long-Term Debt Proceeds
A35: 6000 | C35: Other Items
A36: TOTAL OTHER SOURCES | D36: =SUM(D30:D35) -> 0 | E36: =SUM(E30:E35) -> 0 | F36: =SUM(F30:F35) -> 0 | G36: =SUM(G30:G35) -> 0
A37: 8000 OPENING FUND BALANCE
B38: Reserved Opening Balance
B39: Unreserved Opening Balance
A40: TOTAL OPENING FUND BALANCE | D40: =SUM(D38:D39) -> 0 | E40: =SUM(E38:E39) -> 0 | F40: =SUM(F38:F39) -> 0 | G40: =SUM(G38:G39) -> 0
A41: TOTAL ALL RESOURCES | D41: =D17+D21+D28+D36+D40 -> 0 | E41: =E17+E21+E28+E36+E40 -> 0 | F41: =F17+F21+F28+F36+F40 -> 0 | G41: =G17+G21+G28+G36+G40 -> 0
A43: ='Form 1 Cover'!A20 -> Charter School - fill in the name of your school | F43: ="Budget Fiscal Year "&TEXT('Form 1 Cover'!$C$137, "mm/dd/yy") -> Budget Fiscal Year 2014-2015
A45: Form 6 Proprietary/Enterprise | D45: Page 1 of 2 | G45: ='Form 1 Cover'!C146 -> 41703
A46: Form 6 Proprietary/Enterprise | D46: -1 | E46: -2 | F46: -3 | G46: -4
E47: ESTIMATED | F47: BUDGET YEAR ENDING 06/30/10
D48: ACTUAL PRIOR | E48: CURRENT
D49: YEAR ENDING | E49: YEAR ENDING | F49: TENTATIVE | G49: FINAL
B50: FUNCTION / OBJECT | D50: 39629 | E50: 39994 | F50: APPROVED | G50: APPROVED
A51: EXPENSES
B52: 1000 | C52: Instruction
C53: 100 Salaries
C54: 200 Benefits
C55: 300/400/500 Purchased Services
C56: 600 Supplies
C57: 700 Property
C58: 800 Other
B59: SUBTOTAL INSTRUCTION EXPENSES: | D59: =SUM(D53:D58) -> 0 | E59: =SUM(E53:E58) -> 0 | F59: =SUM(F53:F58) -> 0 | G59: =SUM(G53:G58) -> 0
B60: 2000 Support Services
C61: 100 Salaries
C62: 200 Benefits
C63: 300/400/500 Purchased Services
C64: 600 Supplies
C65: 700 Property
C66: 800 Other
B67: SUBTOTAL SUPPORT EXPENSES: | D67: =SUM(D61:D66) -> 0 | E67: =SUM(E61:E66) -> 0 | F67: =SUM(F61:F66) -> 0 | G67: =SUM(G61:G66) -> 0
B68: 3100 | C68: Food Service
C69: 100 Salaries
C70: 200 Benefits
C71: 300/400/500 Purchased Services
C72: 600 Supplies
C73: 700 Property
C74: 800 Other
B75: SUBTOTAL FOOD SERVICE EXPENSES: | D75: =SUM(D69:D74) -> 0 | E75: =SUM(E69:E74) -> 0 | F75: =SUM(F69:F74) -> 0 | G75: =SUM(G69:G74) -> 0
B76: 4000 | C76: Facilities Acquisition & Construction
C77: 100 Salaries
C78: 200 Benefits
C79: 300/400/500 Purchased Services
C80: 600 Supplies
C81: 700 Property
C82: 800 Other
B83: SUBTOTAL FOOD SERVICE EXPENSES: | D83: =SUM(D77:D82) -> 0 | E83: =SUM(E77:E82) -> 0 | F83: =SUM(F77:F82) -> 0 | G83: =SUM(G77:G82) -> 0
B84: 5000 | C84: Debt Service
B85: 6000 | C85: Miscellaneous
B86: SUBTOTAL OTHER SERVICES | D86: =SUM(D84:D85) -> 0 | E86: =SUM(E84:E85) -> 0 | F86: =SUM(F84:F85) -> 0 | G86: =SUM(G84:G85) -> 0
A87: TOTAL EXPENSES | D87: =D59+D67+D75+D83+D86 -> 0 | E87: =E59+E67+E75+E83+E86 -> 0 | F87: =F59+F67+F75+F83+F86 -> 0 | G87: =G59+G67+G75+G83+G86 -> 0
B88: 8000 | C88: ENDING FUND BALANCE
C89: Reserved Ending Balance
C90: Unreserved Ending Balance
B91: TOTAL ENDING FUND BALANCE | D91: =SUM(D89:D90) -> 0 | E91: =SUM(E89:E90) -> 0 | F91: =SUM(F89:F90) -> 0 | G91: =SUM(G89:G90) -> 0
A92: TOTAL APPLICATIONS | D92: =D87+D91 -> 0 | E92: =E87+E91 -> 0 | F92: =F87+F91 -> 0 | G92: =G87+G91 -> 0
A94: ='Form 1 Cover'!A20 -> Charter School - fill in the name of your school | F94: ="Budget Fiscal Year "&TEXT('Form 1 Cover'!$C$137, "mm/dd/yy") -> Budget Fiscal Year 2014-2015
A96: Form 6 Proprietary/Enterprise | D96: Page 2 of 2 | G96: ='Form 1 Cover'!C146 -> 41703
C98: CHECK -Ending fund balance should be: | D98: =D41-D87 -> 0 | E98: =E41-E87 -> 0 | F98: =F41-F87 -> 0 | G98: =G41-G87 -> 0

Sheet Form 7 Debt
A2: ='Form 1 Cover'!A20 -> Charter School - fill in the name of your school | F2: * - Type - use codes 1-11 | I2: 6 - Medium-Term Financing - Lease Purchase
F3: 1 - General Obligation Bonds | I3: 7 - Capital Leases
A4: ALL EXISTING OR PROPOSED | F4: 2 - G. O. Revenue Supported Bonds | I4: 8 - Special Assessment Bonds
F5: 3 - G. O. Special Assessment Bonds | I5: 9 - Mortgages
F6: 4 - Revenue Bonds | I6: 10 - Other (Specify Type)
F7: 5 - Medium-Term Financing | I7: 11 - Proposed (Specify Type)
A10: (1) | B10: (2) | C10: (3) | D10: (4) | E10: (5) | F10: (6) | G10: (7) | H10: (8) | I10: (9) | J10: (10) | K10: (11)
C11: Number | I11: REQUIREMENTS FOR FISCAL | K11: (9) + (10)
C12: of | H12: BEGINNING | I12: ="YEAR ENDING "&TEXT('Form 1 Cover'!C139, "MM/DD/YY") -> YEAR ENDING 06/30/15
C13: Months | D13: ORIGINAL | F13: FINAL | H13: OUTSTANDING
A14: NAME OF LOAN | B14: Type | C14: of | D14: AMOUNT OF | E14: ISSUE | F14: PAYMENT | G14: INTEREST | H14: BALANCE | I14: INTEREST | J14: PRINCIPAL | K14: ='Form 1 Cover'!C139 -> 42185
A15: List and Subtotal By Fund | B15: * | C15: TERM | D15: ISSUE | E15: DATE | F15: DATE | G15: RATE | H15: ='Form 1 Cover'!C143 -> 41821 | I15: PAYABLE | J15: PAYABLE | K15: TOTAL
A16: FUND:
K17: =I17+J17 -> 0
K18: =I18+J18 -> 0
K19: =I19+J19 -> 0
K20: =I20+J20 -> 0
K21: =I21+J21 -> 0
K22: =I22+J22 -> 0
K23: =I23+J23 -> 0
K24: =I24+J24 -> 0
K25: =I25+J25 -> 0
K26: =I26+J26 -> 0
K27: =I27+J27 -> 0
K28: =I28+J28 -> 0
... K31: =I31+J31 -> 0
A32: TOTAL ALL DEBT SERVICE | D32: =SUM(D17:D31) -> 0 | H32: =SUM(H16:H31) -> 0 | I32: =SUM(I17:I31) -> 0 | J32: =SUM(J17:J31) -> 0 | K32: =SUM(K17:K31) -> 0
A34: ='Form 1 Cover'!A20 -> Charter School - fill in the name of your school | J34: ="Budget Fiscal Year "&TEXT('Form 1 Cover'!$C$137, "mm/dd/yy") -> Budget Fiscal Year 2014-2015
A36: Form 7 INDEBTEDNESS | K36: ='Form 1 Cover'!$C$146 -> 41703

Sheet Form 8 Tuition, Transportation
B1: ='Form 1 Cover'!A20 -> Charter School - fill in the name of your school
D3: FROM DISTRICTS WITHIN NEVADA | F3: FROM DISTRICTS OUTSIDE NEVADA
A4: REPORT FOR ALL FUNDS | C4: ='Form 1 Cover'!C137 -> 2014-2015 | D4: (1) | E4: (2) | F4: (3) | G4: (4)
D5: TUITION | E5: TRANSPORTATION | F5: TUITION | G5: TRANSPORTATION
C6: Revenue | D6: 1310 NV Individual | E6: 1410 NV Individual | F6: 1310 Out-of-state Ind | G6: 1410 Out-of-state Ind
A7: REVENUES | C7: CODES | D7: 1321 NV School Dist | E7: 1421 NV School Dist | F7: 1331 Out-of-state SD | G7: 1431 Out-of-state SD
B8: Nevada Individuals | C8: 1310/1410
B9: Nevada School Districts | C9: 1321/1421
B10: Out-of-state Individuals | C10: 1310/1410
B11: Out-of-State School Districts | C11: 1331/1431
D12: =SUM(D8:D11) -> 0 | E12: =SUM(E8:E11) -> 0 | F12: =SUM(F8:F11) -> 0 | G12: =SUM(G8:G11) -> 0
D14: TO DISTRICTS WITHIN NEVADA | F14: TO DISTRICTS OUTSIDE NEVADA
A15: EXPENDITURES | C15: Object Codes | D15: 561 | E15: 511 | F15: 562 | G15: 512
B16: 100 - Regular Programs
B18: 200 - Special Programs
B20: 300 - Vocational Programs
B22: 400 - Other PK-12 Programs
B24: 500 - Nonpublic Programs
B26: 600 - Adult Programs
B27: TOTALS | D27: =SUM(D16:D26) -> 0 | E27: =SUM(E16:E26) -> 0 | F27: =SUM(F16:F26) -> 0 | G27: =SUM(G16:G26) -> 0
A29: ='Form 1 Cover'!A20 -> Charter School - fill in the name of your school | F29: ="Budget Fiscal Year "&TEXT('Form 1 Cover'!$C$137, "mm/dd/yy") -> Budget Fiscal Year 2014-2015
A33: FORM 8 - TUITION and TRANSPORTATION | G33: ='Form 1 Cover'!$C$146 -> 41703

Sheet FORM 9 Fund Transfers
A1: ='Form 1 Cover'!A20 -> Charter School - fill in the name of your school
A3: ="FUND TRANSFERS "&TEXT('Form 1 Cover'!C137, "MM/DD/YY") -> FUND TRANSFERS 2014-2015 | B3: T R A N S F E R S I N | E3: T R A N S F E R S O U T
A5: =-1 -> -1 | B5: =A5-1 -> -2 | C5: -3 | E5: =C5-1 -> -4 | F5: -5
A6: FUND TYPE | B6: FROM FUND | C6: AMOUNT | E6: TO FUND | F6: AMOUNT
A7: GENERAL FUND
A19: SUBTOTAL | B19: =SUM(B8:B18) -> 0 | C19: =SUM(C8:C18) -> 0 | E19: =SUM(E8:E18) -> 0 | F19: =SUM(F8:F18) -> 0
A20: SPECIAL REVENUE FUNDS
A32: SUBTOTAL | B32: =SUM(B21:B31) -> 0 | C32: =SUM(C21:C31) -> 0 | E32: =SUM(E21:E31) -> 0 | F32: =SUM(F21:F31) -> 0
A33: TOTAL TRANSFERS | B33: =B19+B32 -> 0 | C33: =C19+C32 -> 0 | E33: =E19+E32 -> 0 | F33: =F19+F32 -> 0
A35: ='Form 1 Cover'!A20 -> Charter School - fill in the name of your school | E35: ="Budget Fiscal Year "&TEXT('Form 1 Cover'!$C$137, "mm/dd/yy") -> Budget Fiscal Year 2014-2015
A37: FORM 9 FUND TRANSFERS | F37: ='Form 1 Cover'!$C$146 -> 41703

Sheet FORM 10 Lobby Expense
A1: ="L O B B Y E X P E N S E S "&TEXT('Form 1 Cover'!C137, "MM/DD/YY") -> L O B B Y E X P E N S E S 2014-2015
A3: Pursuant to NRS 354.600 (3), each (emphasis added) local government budget must obtain a
A4: separate statement of anticipated expenses relating to activities designed to influence the passage
A5: or defeat of legislation in an upcoming legislative session.
A9: 1. Activity:
A11: 2. Funding Source:
A13: 3. Transportation | I13: $
A15: 4. Lodging and meals | I15: $
A17: 5. Salaries and Wages | I17: $
A19: 6. Compensation to lobbyists | I19: $
A21: 7. Entertainment | I21: $
A23: 8. Supplies, equipment & facilities; other personnel and | I23: $
A24: services spent in Carson City
A26: Total | I26: $ | J26: =SUM(J13,J15,J17,J19,J21,J23) -> 0
A31: Entity:
A33: Lobbying Expense Estimate,
A36: ='Form 1 Cover'!A20 -> Charter School - fill in the name of your school | H36: ="Budget Fiscal Year "&TEXT('Form 1 Cover'!$C$137, "mm/dd/yy") -> Budget Fiscal Year 2014-2015
A40: Form 10 LOBBY EXPENSE | J40: ='Form 1 Cover'!$C$146 -> 41703

Sheet FORM 11 Cash Flow
A1: ='Form 1 Cover'!A20 -> Charter School - fill in the name of your school | F1: CASH FLOW STATEMENT
A3: ='Form 1 Cover'!C137 -> 2014-2015 | C3: PROJECTED | D3: PROJECTED | E3: PROJECTED | F3: PROJECTED | G3: PROJECTED | H3: PROJECTED | I3: PROJECTED | J3: PROJECTED | K3: PROJECTED | L3: PROJECTED | M3: PROJECTED | N3: PROJECTED | O3: Total Projected | P3: Final Approved Budget
C4: July | D4: August | E4: September | F4: October | G4: November | H4: December | I4: January | J4: February | K4: March | L4: April | M4: May | N4: June | Q4: Variance
A5: REVENUES
A6: Type:
A7: Distributive School Acct | O7: =SUM(C7:N7) -> 0 | Q7: =O7-P7 -> 0
A8: Donations | O8: =SUM(C8:N8) -> 0 | Q8: =O8-P8 -> 0
A9: Federal Grant A | O9: =SUM(C9:N9) -> 0 | Q9: =O9-P9 -> 0
O10: =SUM(C10:N10) -> 0 | Q10: =O10-P10 -> 0
O11: =SUM(C11:N11) -> 0 | Q11: =O11-P11 -> 0
O12: =SUM(C12:N12) -> 0 | Q12: =O12-P12 -> 0
O13: =SUM(C13:N13) -> 0 | Q13: =O13-P13 -> 0
O14: =SUM(C14:N14) -> 0 | Q14: =O14-P14 -> 0
A15: Total Revenues | C15: =SUM(C7:C14) -> 0 | D15: =SUM(D7:D14) -> 0 | E15: =SUM(E7:E14) -> 0 | F15: =SUM(F7:F14) -> 0 | G15: =SUM(G7:G14) -> 0 | H15: =SUM(H7:H14) -> 0 | I15: =SUM(I7:I14) -> 0 | J15: =SUM(J7:J14) -> 0 | ... Q15: =SUM(Q7:Q14) -> 0
A16: Total Revenues Y-T-D | C16: =C15 -> 0 | D16: =C16+D15 -> 0 | E16: =D16+E15 -> 0 | F16: =E16+F15 -> 0 | G16: =F16+G15 -> 0 | H16: =G16+H15 -> 0 | I16: =H16+I15 -> 0 | J16: =I16+J15 -> 0 | K16: =J16+K15 -> 0 | ... N16: =M16+N15 -> 0
A18: EXPENDITURES
A19: Salaries & Benefits
A20: Salaries | O20: =SUM(C20:N20) -> 0 | Q20: =-O20+P20 -> 0
A21: Benefits | O21: =SUM(C21:N21) -> 0 | Q21: =-O21+P21 -> 0
A22: Total Salaries & Ben | C22: =C20+C21 -> 0 | D22: =D20+D21 -> 0 | E22: =E20+E21 -> 0 | F22: =F20+F21 -> 0 | G22: =G20+G21 -> 0 | H22: =H20+H21 -> 0 | I22: =I20+I21 -> 0 | J22: =J20+J21 -> 0 | ... O22: =O20+O21 -> 0 | P22: =SUM(P20:P21) -> 0 | Q22: =SUM(Q20:Q21) -> 0
A24: Operating
A25: Supplies | O25: =SUM(C25:N25) -> 0 | Q25: =-O25+P25 -> 0
A26: Rent | O26: =SUM(C26:N26) -> 0 | Q26: =-O26+P26 -> 0
A27: Utilities | O27: =SUM(C27:N27) -> 0 | Q27: =-O27+P27 -> 0
A28: Contracts | O28: =SUM(C28:N28) -> 0 | Q28: =-O28+P28 -> 0
A29: Textbooks | O29: =SUM(C29:N29) -> 0 | Q29: =-O29+P29 -> 0
A30: Equipment | O30: =SUM(C30:N30) -> 0 | Q30: =-O30+P30 -> 0
O31: =SUM(C31:N31) -> 0 | Q31: =-O31+P31 -> 0
O32: =SUM(C32:N32) -> 0 | Q32: =-O32+P32 -> 0
O33: =SUM(C33:N33) -> 0 | Q33: =-O33+P33 -> 0
O34: =SUM(C34:N34) -> 0 | Q34: =-O34+P34 -> 0
O35: =SUM(C35:N35) -> 0 | Q35: =-O35+P35 -> 0
O36: =SUM(C36:N36) -> 0 | Q36: =-O36+P36 -> 0
O37: =SUM(C37:N37) -> 0 | Q37: =-O37+P37 -> 0
O38: =SUM(C38:N38) -> 0 | Q38: =-O38+P38 -> 0
O39: =SUM(C39:N39) -> 0 | Q39: =-O39+P39 -> 0
O40: =SUM(C40:N40) -> 0 | Q40: =-O40+P40 -> 0
O41: =SUM(C41:N41) -> 0 | Q41: =-O41+P41 -> 0
O42: =SUM(C42:N42) -> 0 | Q42: =-O42+P42 -> 0
N43: W
A44: Total Expenses | C44: =SUM(C22,C25:C42) -> 0 | D44: =SUM(D22,D25:D42) -> 0 | E44: =SUM(E22,E25:E42) -> 0 | F44: =SUM(F22,F25:F42) -> 0 | G44: =SUM(G22,G25:G42) -> 0 | H44: =SUM(H22,H25:H42) -> 0 | I44: =SUM(I22,I25:I42) -> 0 | J44: =SUM(J22,J25:J42) -> 0 | ... Q44: =SUM(Q22,Q25:Q42) -> 0
A45: Total Expenses Y-T-D | C45: =C44 -> 0 | D45: =C45+D44 -> 0 | E45: =D45+E44 -> 0 | F45: =E45+F44 -> 0 | G45: =F45+G44 -> 0 | H45: =G45+H44 -> 0 | I45: =H45+I44 -> 0 | J45: =I45+J44 -> 0 | K45: =J45+K44 -> 0 | ... N45: =M45+N44 -> 0 | O45: =N45 -> 0 | P45: =P44 -> 0 | Q45: =Q15+Q44 -> 0
A46: Percent of Budget | C46: =C45/P44 -> #DIV/0! | D46: =D45/P44 -> #DIV/0! | E46: =E45/P44 -> #DIV/0! | F46: =F45/P44 -> #DIV/0! | G46: =G45/P44 -> #DIV/0! | H46: =H45/P44 -> #DIV/0! | I46: =I45/P44 -> #DIV/0! | J46: =J45/P44 -> #DIV/0! | K46: =K45/P44 -> #DIV/0! | L46: =L45/P44 -> #DIV/0! | M46: =M45/P44 -> #DIV/0! | N46: =N45/P44 -> #DIV/0!
A48: Projected Cash Balance Statement
A50: Net change in Cash (F/B) | C50: =C15-C44 -> 0 | D50: =D15-D44 -> 0 | E50: =E15-E44 -> 0 | F50: =F15-F44 -> 0 | G50: =G15-G44 -> 0 | H50: =H15-H44 -> 0 | I50: =I15-I44 -> 0 | J50: =J15-J44 -> 0 | ... P50: =P15-P44 -> 0 | Q50: =Q15+Q44 -> 0
A52: Begin Cash Balance(F/B) | C52: 0 | D52: =C54 -> 0 | E52: =D54 -> 0 | F52: =E54 -> 0 | G52: =F54 -> 0 | H52: =G54 -> 0 | I52: =H54 -> 0 | J52: =I54 -> 0 | K52: =J54 -> 0 | ... N52: =M54 -> 0 | Q52: =O52-P52 -> 0
A54: End Cash Balance (F/B) | C54: =SUM(C50:C52) -> 0 | D54: =SUM(D50:D53) -> 0 | E54: =SUM(E50:E53) -> 0 | F54: =SUM(F50:F53) -> 0 | G54: =SUM(G50:G53) -> 0 | H54: =SUM(H50:H53) -> 0 | I54: =SUM(I50:I53) -> 0 | J54: =SUM(J50:J53) -> 0 | K54: =SUM(K50:K53) -> 0 | ... Q54: =SUM(Q50:Q53) -> 0
A56: ='Form 1 Cover'!A20 -> Charter School - fill in the name of your school | P56: ="Budget Fiscal Year "&TEXT('Form 1 Cover'!$C$137, "mm/dd/yy") -> Budget Fiscal Year 2014-2015
A58: FORM 11 CASH FLOW
