Workbook

Sheet Intro
B3: Q6 Final Proposals - Opex - HAL
B4: The spreadsheet contains analysis underpinning the CAA's final proposal opex allowance for HAL over Q6.
B5: Owner: Duncan Kernohan
B6: duncan.kernohan@caa.co.uk
B7: t: 020 7453 6210
B9: Grey denotes input cell. These cells are used to denote input data from consultancy reports and other external sources.
B10: Green text denotes cells containing parameters. These cells are usually used to include or exclude certain factors from the final proposals or to convert from a nominal to real price base.

Sheet Reg>>

Sheet HAL - Reg
B2: Heathrow - CAA Allowance | O2: Heathrow - Outturn
B4: Regulatory Accounts | C4: Q4 | F4: Q5 | K4: Q5+1 | O4: Regulatory Accounts | P4: Q4 | S4: Q5 | X4: Q5+1
B5: £m nominal | C5: 2005/06 | D5: 2006/07 | E5: 2007/08 | F5: 2008/09 | G5: 2009/10 | H5: 2010/11 | I5: 2011/12 | J5: 2012/13 | K5: 2013/14 | M5: CAGR (Q5) | O5: £m nominal | P5: 2005/06 | Q5: 2006/07 | R5: 2007/08 | S5: 2008/09 | T5: 2009/10 | U5: 2010/11 | V5: 2011/12 | W5: 2012/13 | X5: 2013/14 | Z5: CAGR (Q5)
B6: Terminal Pax | C6: =69900 -> 69900 | D6: 70300 | E6: 70700 | F6: 70400 | G6: 72500 | H6: 74500 | I6: 76200 | J6: 78200 | M6: =((J6/F6)^(1/4))-1 -> 0.02661717 | O6: Terminal Pax | P6: 67421 | Q6: 67305 | R6: 67951 | S6: 65929 | T6: 66133 | U6: 66111 | V6: 70099 | W6: 70332 | Z6: =((W6/S6)^(1/4))-1 -> 0.016293434
B7: Net Revenue from Airport Charges | C7: 543.6 | D7: 603.1 | E7: 671.7 | F7: 927.7 | G7: 1029.2 | H7: 1193.5 | I7: 1372.9 | J7: 1558.8 | M7: =((J7/F7)^(1/4))-1 -> 0.13853323 | O7: Net Revenue from Airport Charges | P7: 532.2 | Q7: 579.6 | R7: 639.7 | S7: 886.8 | T7: 955.4 | U7: 997.5 | V7: 1178.6 | W7: 1295.9 | Z7: =((W7/S7)^(1/4))-1 -> 0.099477766
B8: Other Revenue | C8: 569.6 | D8: 595.7 | E8: 624.7 | F8: 720.8 | G8: 745.8 | H8: 805.1 | I8: 856.3 | J8: 908.6 | M8: =((J8/F8)^(1/4))-1 -> 0.059593996 | O8: Other Revenue | P8: 608.9 | Q8: 616.3 | R8: 638.5 | S8: 742.9 | T8: 787.5 | U8: 856.1 | V8: 895.5 | W8: 929.5 | Z8: =((W8/S8)^(1/4))-1 -> 0.057620253
B9: Total Revenue | C9: 1113.2 | D9: 198.8 | E9: 1296.4 | F9: 1648.5 | G9: 1775 | H9: 1998.6 | I9: 2229.2 | J9: 2467.5 | M9: =((J9/F9)^(1/4))-1 -> 0.10609404 | O9: Total Revenue | P9: 1141.1 | Q9: 1195.9 | R9: 1278.2 | S9: 1629.7 | T9: 1742.9 | U9: 1853.6 | V9: 2074.1 | W9: 2225.4 | Z9: =((W9/S9)^(1/4))-1 -> 0.080998533
B10: Operating Costs | C10: 490.7 | D10: 511.9 | E10: 541.5 | F10: 876 | G10: 865.4 | H10: 912.6 | I10: 962.4 | J10: 1000.2 | M10: =((J10/F10)^(1/4))-1 -> 0.033702784 | O10: Operating Costs | P10: 554.1 | Q10: 599.8 | R10: 772.7 | S10: 969 | T10: 956.5 | U10: 950.5 | V10: 1001 | W10: 1027.7 | Z10: =((W10/S10)^(1/4))-1 -> 0.014812119
B11: Assumed Ordinary Depreciation | C11: 184.7 | D11: 196.9 | E11: 218.5 | F11: 421.1 | G11: 434 | H11: 480.1 | I11: 517.4 | J11: 572.6 | M11: =((J11/F11)^(1/4))-1 -> 0.07985769 | O11: Assumed Ordinary Depreciation | P11: 184.7 | Q11: 196.9 | R11: 218.5 | S11: 421.1 | T11: 434 | U11: 480.1 | V11: 517.4 | W11: 572.6 | Z11: =((W11/S11)^(1/4))-1 -> 0.07985769
B12: Total Expenditure | C12: 675.4 | D12: 708.8 | E12: 760 | F12: 1297.1 | G12: 1229.4 | H12: 1392.7 | I12: 1479.8 | J12: 1572.8 | M12: =((J12/F12)^(1/4))-1 -> 0.04936122 | O12: Total Expenditure | P12: 738.8 | Q12: 796.7 | R12: 991.2 | S12: 1390.1 | T12: 1390.5 | U12: 1430.6 | V12: 1518.4 | W12: 1600.3 | Z12: =((W12/S12)^(1/4))-1 -> 0.035830848
B14: Regulatory Operating Profit (Before Exceptional) | C14: 437.8 | D14: 490 | E14: 536.4 | F14: 351.4 | G14: 475.6 | H14: 605.9 | I14: 749.4 | J14: 894.7 | M14: =((J14/F14)^(1/4))-1 -> 0.2631907 | O14: Regulatory Operating Profit (Before Exceptional) | P14: 402.3 | Q14: 399.2 | R14: 287 | S14: 239.6 | T14: 352.4 | U14: 423 | V14: 555.7 | W14: 625.1 | Z14: =((W14/S14)^(1/4))-1 -> 0.27091256
B15: Exceptional | C15: 0 | D15: 0 | E15: 0 | F15: 0 | G15: 0 | H15: 0 | I15: 0 | J15: 0 | O15: Exceptional | P15: 0 | Q15: 0 | R15: 0 | S15: 0 | T15: 197.4 | U15: -115.3 | V15: 158.9 | W15: 62
B16: Regulatory Operating Profit | C16: 437.8 | D16: 490 | E16: 536.4 | F16: =F14-F15 -> 351.4 | G16: =G14-G15 -> 475.6 | H16: =H14-H15 -> 605.9 | I16: =I14-I15 -> 749.4 | J16: 894.7 | M16: =((J16/F16)^(1/4))-1 -> 0.2631907 | O16: Regulatory Operating Profit | P16: 402.3 | Q16: 399.2 | R16: 287 | S16: 239.6 | T16: 155 | U16: =U14-U15 -> 538.3 | V16: 396.8 | W16: 563.1 | Z16: =((W16/S16)^(1/4))-1 -> 0.23815404
B18: Capital Expenditure | C18: 1069 | D18: 931.3 | E18: 975.8 | F18: 1099.6 | G18: 1234.5 | H18: 1150 | I18: 1008.5 | J18: 680.4 | M18: =((J18/F18)^(1/4))-1 -> -0.1130842 | O18: Capital Expenditure | P18: 1304.5 | Q18: 1051.2 | R18: 894 | S18: 739.9 | T18: 804.3 | U18: 812 | V18: 963.5 | W18: 1209.6 | Z18: =((W18/S18)^(1/4))-1 -> 0.13075154
B20: Opening Basic RAB | C20: 6006.3 | D20: 7041.2 | E20: 8130 | F20: 9232.6 | G20: 10096.7 | H20: 11539.1 | I20: 12973.9 | J20: 13996.3 | M20: =((J20/F20)^(1/4))-1 -> 0.10961497 | O20: Opening Basic RAB | P20: 6327.5 | Q20: 7596.6 | R20: 8834.2 | S20: 9232.6 | T20: 9742.9 | U20: 10728.5 | V20: 11773 | W20: 12705.3 | Z20: =((W20/S20)^(1/4))-1 -> 0.083091696
B22: Closing Basic RAB | C22: 7041.2 | D22: 8130 | E22: 9776.3 | F22: 10096.7 | G22: 11539.1 | H22: 12973.9 | I22: 13996.3 | J22: 14523.4 | M22: =((J22/F22)^(1/4))-1 -> 0.09514648 | O22: Closing Basic RAB | P22: 7596.6 | Q22: 8834.2 | R22: 9776.3 | S22: 9742.9 | T22: 10728.5 | U22: 11773 | V22: 12705.3 | W22: 13727.9 | Z22: =((W22/S22)^(1/4))-1 -> 0.089504342
B24: Weighted average basic RAB | C24: 6514.1 | D24: 7575.4 | E24: 8937.8 | F24: 9664.7 | G24: 10817.9 | H24: 12256.5 | I24: 13485.1 | J24: 14259.9 | M24: =((J24/F24)^(1/4))-1 -> 0.10212797 | O24: Weighted average basic RAB | P24: 6950.2 | Q24: 8203.8 | R24: 9296.5 | S24: 9487.8 | T24: 10235.7 | U24: 11250.7 | V24: 12239.1 | W24: 13216.6 | Z24: =((W24/S24)^(1/4))-1 -> 0.086396996
B26: Return on weighted average basic RAB (pre-exceptional) (%) | C26: 6.7 | D26: 6.5 | E26: 6 | F26: 3.6 | G26: 4.4 | H26: 4.9 | I26: 5.6 | J26: 6.3 | M26: =((J26/F26)^(1/4))-1 -> 0.15016332 | O26: Return on weighted average basic RAB (pre-exceptional) (%) | P26: 5.8 | Q26: 4.9 | R26: 3.1 | S26: 2.5 | T26: 3.4 | U26: 3.8 | V26: 4.5 | W26: 4.7 | Z26: =((W26/S26)^(1/4))-1 -> 0.170953
B28: Return on weighted average basic RAB (%) | C28: 6.7 | D28: 6.5 | E28: 6 | F28: 3.6 | G28: 4.4 | H28: 4.9 | I28: 5.6 | J28: 6.3 | M28: =((J28/F28)^(1/4))-1 -> 0.15016332 | O28: Return on weighted average basic RAB (%) | P28: 5.8 | Q28: 4.9 | R28: 3.1 | S28: 2.5 | T28: 1.5 | U28: 4.8 | V28: 3.2 | W28: 4.3 | Z28: =((W28/S28)^(1/4))-1 -> 0.14520204
B30: Breakdown of Operating Costs - CAA Projections | C30: Q4 | F30: Q5 | K30: Q5+1 | O30: Breakdown of Operating Costs | P30: Q4 | S30: Q5 | X30: Q5+1
B31: £m nominal | C31: 2005/06 | D31: 2006/07 | E31: 2007/08 | F31: 2008/09 | G31: 2009/10 | H31: 2010/11 | I31: 2011/12 | J31: 2012/13 | K31: 2013/14 | M31: CAGR (Q5) | O31: £m nominal | P31: 2005/06 | Q31: 2006/07 | R31: 2007/08 | S31: 2008/09 | T31: 2009/10 | U31: 2010/11 | V31: 2011/12 | W31: 2012/13 | X31: 2013/14 | Z31: CAGR (Q5)
B32: Staff Costs | F32: =249.7 -> 249.7 | G32: =244.6 -> 244.6 | H32: 253.2 | I32: 261.5 | J32: =[1]Sheet1!H11/1000 -> 267.78725 | K32: 267.4 | M32: =((J32/F32)^(1/4))-1 -> 0.017636883 | O32: Staff Costs | S32: 262 | T32: 231.5 | U32: 247 | V32: 270.4 | W32: 328.4 | Z32: =((W32/S32)^(1/4))-1 -> 0.058096954
B33: Maintenance and equipment costs | F33: 72.1 | G33: 106.4 | H33: 111.4 | I33: 115.3 | J33: =[1]Sheet1!H12/1000 -> 117.97343 | K33: 124.1 | M33: =((J33/F33)^(1/4))-1 -> 0.13099905 | O33: Maintenance and equipment costs | S33: 116.6 | T33: 121.3 | U33: 105.1 | V33: 118 | W33: 126.9 | Z33: =((W33/S33)^(1/4))-1 -> 0.021388039
B34: Rent and rates | F34: 98 | G34: 97.7 | H34: 103.1 | I34: 109.3 | J34: =[1]Sheet1!H13/1000 -> 119.16631 | K34: 119.4 | M34: =((J34/F34)^(1/4))-1 -> 0.050102888 | O34: Rent and rates | S34: 104.1 | T34: 110.6 | U34: 104.2 | V34: 116.9 | W34: 128.6 | Z34: =((W34/S34)^(1/4))-1 -> 0.054259589
B35: Utility costs | F35: 91.3 | G35: 92.9 | H35: 102.4 | I35: 110.6 | J35: =[1]Sheet1!H14/1000 -> 122.32067 | K35: 122.5 | M35: =((J35/F35)^(1/4))-1 -> 0.075863724 | O35: Utility costs | S35: 83.7 | T35: 107.9 | U35: 92.7 | V35: 89.4 | W35: 86.8 | Z35: =((W35/S35)^(1/4))-1 -> 0.009133368
B36: Police costs | F36: 33.1 | G36: 35.1 | H36: 36.4 | I36: 38.9 | J36: =[1]Sheet1!H15/1000 -> 39.79575 | K36: 39.8 | M36: =((J36/F36)^(1/4))-1 -> 0.047133791 | O36: Police costs | S36: 33.6 | T36: 31.4 | U36: 28.1 | V36: 28.8 | W36: 28.3 | Z36: =((W36/S36)^(1/4))-1 -> -0.042008205
B37: Rail costs | F37: 54.2 | G37: 55.3 | H37: 59.1 | I37: 63.3 | J37: =[1]Sheet1!H16/1000 -> 67.531568 | K37: 67.6 | M37: =((J37/F37)^(1/4))-1 -> 0.056517967 | O37: Rail costs | S37: 52.2 | T37: 54.3 | U37: 57.2 | V37: 58.9 | W37: 59.1 | Z37: =((W37/S37)^(1/4))-1 -> 0.03152378
B38: Other costs | F38: 176 | G38: 129.9 | H38: 139.2 | I38: 152 | J38: =[1]Sheet1!H17/1000 -> 149.82851 | K38: 145 | M38: =((J38/F38)^(1/4))-1 -> -0.03944895 | O38: Other costs | S38: 149.3 | T38: 165.2 | U38: 148.6 | V38: 149.4 | W38: 154.2 | Z38: =((W38/S38)^(1/4))-1 -> 0.0081058652
B39: Intragroup costs | F39: 101.6 | G39: 103.5 | H39: 107.8 | I39: 111.5 | J39: =[1]Sheet1!H18/1000 -> 114.2368 | K39: 114.4 | M39: =((J39/F39)^(1/4))-1 -> 0.029741189 | O39: Intragroup costs | S39: 151.4 | T39: 137.6 | U39: 168.3 | V39: 172.6 | W39: 127.1 | Z39: =((W39/S39)^(1/4))-1 -> -0.042795087
B41: Total operating costs | F41: 876 | G41: 865.4 | H41: 912.6 | I41: 962.4 | J41: =SUM(J32:J39) -> 998.6403 | K41: 1000.2 | M41: =((J41/F41)^(1/4))-1 -> 0.033299562 | O41: Total operating costs | S41: 952.9 | T41: 959.8 | U41: 951.2 | V41: 1004.4 | W41: 1039.5 | Z41: =((W41/S41)^(1/4))-1 -> 0.021984459
B43: Exceptional operating costs | F43: 0 | G43: 0 | H43: 0 | I43: 0 | J43: 0 | K43: 0 | O43: Exceptional operating costs | S43: 25.5 | T43: 0 | U43: 0 | V43: 0 | W43: 0 | Z43: =((W43/S43)^(1/4))-1 -> -1
B44: Service Quality Rebates | F44: 0 | G44: 0 | H44: 0 | I44: 0 | J44: 0 | K44: 0 | O44: Service Quality Rebates | S44: -9.4 | T44: -3.3 | U44: -0.7 | V44: -3.4 | W44: -11.8 | Z44: =((W44/S44)^(1/4))-1 -> 0.058494336
B46: Adjusted operating costs | F46: =F41-F43-F44 -> 876 | G46: =G41-G43-G44 -> 865.4 | H46: =H41-H43-H44 -> 912.6 | I46: =I41-I43-I44 -> 962.4 | J46: =J41-J43-J44 -> 998.6403 | K46: 1000 | M46: =((J46/F46)^(1/4))-1 -> 0.033299562 | O46: Adjusted operating costs | S46: =S41+S43+S44 -> 969 | T46: =T41+T43+T44 -> 956.5 | U46: =U41+U43+U44 -> 950.5 | V46: =V41+V43+V44 -> 1001 | W46: =W10 -> 1027.7 | Z46: =((W46/S46)^(1/4))-1 -> 0.014812119
B49: Price Base Conversion to 2011/12 | C49: =RPI!$T$103/RPI!$T97 -> 1.2290597 | D49: =RPI!$T$103/RPI!$T98 -> 1.1848323 | E49: =RPI!$T$103/RPI!$T99 -> 1.1378291 | F49: =RPI!$T$103/RPI!$T100 -> 1.1050283 | G49: =RPI!$T$103/RPI!$T101 -> 1.0999923 | H49: =RPI!$T$103/RPI!$T102 -> 1.0479817 | I49: =RPI!$T$103/RPI!$T103 -> 1 | J49: =RPI!$T$103/RPI!$V104 -> 0.97002827 | O49: Price Base Conversion to 2011/12 | P49: =RPI!$T$103/RPI!$T97 -> 1.2290597 | Q49: =RPI!$T$103/RPI!$T98 -> 1.1848323 | R49: =RPI!$T$103/RPI!$T99 -> 1.1378291 | S49: =RPI!$T$103/RPI!$T100 -> 1.1050283 | T49: =RPI!$T$103/RPI!$T101 -> 1.0999923 | U49: =RPI!$T$103/RPI!$T102 -> 1.0479817 | V49: =RPI!$T$103/RPI!$T103 -> 1 | W49: =RPI!$T$103/RPI!$V104 -> 0.97002827
B51: Heathrow - CAA Allowance | O51: Heathrow - Outturn
B53: Regulatory Accounts | C53: Q4 | F53: Q5 | K53: Q5+1 | O53: Regulatory Accounts | P53: Q4 | S53: Q5 | X53: Q5+1
B54: £m 2011/12 | C54: 2005/06 | D54: 2006/07 | E54: 2007/08 | F54: 2008/09 | G54: 2009/10 | H54: 2010/11 | I54: 2011/12 | J54: 2012/13 | K54: 2013/14 | M54: CAGR (Q5) | O54: £m 2011/12 | P54: 2005/06 | Q54: 2006/07 | R54: 2007/08 | S54: 2008/09 | T54: 2009/10 | U54: 2010/11 | V54: 2011/12 | W54: 2012/13 | X54: 2013/14 | Z54: CAGR (Q5)
B55: Terminal Pax | C55: =69900 -> 69900 | D55: 70300 | E55: 70700 | F55: 70400 | G55: 72500 | H55: 74500 | I55: 76200 | J55: 76201 | M55: =((J55/F55)^(1/4))-1 -> 0.019992557 | O55: Terminal Pax | P55: 67421 | Q55: 67305 | R55: 67951 | S55: 65929 | T55: 66133 | U55: 66111 | V55: 70099 | W55: 70100 | Z55: =((W55/S55)^(1/4))-1 -> 0.015454299
B56: Net Revenue from Airport Charges | C56: =C7*C$49 -> 668.11684 | D56: =D7*D$49 -> 714.57239 | E56: =E7*E$49 -> 764.2798 | F56: =F7*F$49 -> 1025.1348 | G56: =G7*G$49 -> 1132.1121 | H56: =H7*H$49 -> 1250.7662 | I56: =I7*I$49 -> 1372.9 | J56: =J7*J$49 -> 1512.0801 | M56: =((J56/F56)^(1/4))-1 -> 0.10204278 | O56: Net Revenue from Airport Charges | P56: =P7*P$49 -> 654.10556 | Q56: =Q7*Q$49 -> 686.72883 | R56: =R7*R$49 -> 727.86927 | S56: =S7*S$49 -> 979.93912 | T56: =T7*T$49 -> 1050.9326 | U56: =U7*U$49 -> 1045.3618 | V56: =V7*V$49 -> 1178.6 | W56: =W7*W$49 -> 1257.0596 | Z56: =((W56/S56)^(1/4))-1 -> 0.064239065
B57: Other Revenue | C57: =C8*C$49 -> 700.07239 | D57: =D8*D$49 -> 705.80463 | E57: =E8*E$49 -> 710.80183 | F57: =F8*F$49 -> 796.50442 | G57: =G8*G$49 -> 820.37424 | H57: =H8*H$49 -> 843.73011 | I57: =I8*I$49 -> 856.3 | J57: =J8*J$49 -> 881.36769 | M57: =((J57/F57)^(1/4))-1 -> 0.025633586 | O57: Other Revenue | P57: =P8*P$49 -> 748.37444 | Q57: =Q8*Q$49 -> 730.21218 | R57: =R8*R$49 -> 726.50388 | S57: =S8*S$49 -> 820.92554 | T57: =T8*T$49 -> 866.24392 | U57: =U8*U$49 -> 897.17718 | V57: =V8*V$49 -> 895.5 | W57: =W8*W$49 -> 901.64128 | Z57: =((W57/S57)^(1/4))-1 -> 0.023723103
B58: Total Revenue | C58: =C9*C$49 -> 1368.1892 | D58: =D9*D$49 -> 235.54467 | E58: =E9*E$49 -> 1475.0816 | F58: =F9*F$49 -> 1821.6392 | G58: =G9*G$49 -> 1952.4863 | H58: =H9*H$49 -> 2094.4963 | I58: =I9*I$49 -> 2229.2 | J58: =J9*J$49 -> 2393.5448 | M58: =((J58/F58)^(1/4))-1 -> 0.070643286 | O58: Total Revenue | P58: =P9*P$49 -> 1402.48 | Q58: =Q9*Q$49 -> 1416.941 | R58: =R9*R$49 -> 1454.3731 | S58: =S9*S$49 -> 1800.8647 | T58: =T9*T$49 -> 1917.1765 | U58: =U9*U$49 -> 1942.539 | V58: =V9*V$49 -> 2074.1 | W58: =W9*W$49 -> 2158.7009 | Z58: =((W58/S58)^(1/4))-1 -> 0.046352099
B59: Operating Costs | C59: =C10*C$49 -> 603.09959 | D59: =D10*D$49 -> 606.51568 | E59: =E10*E$49 -> 616.13445 | F59: =F10*F$49 -> 968.00481 | G59: =G10*G$49 -> 951.93332 | H59: =H10*H$49 -> 956.38814 | I59: =I10*I$49 -> 962.4 | J59: =J10*J$49 -> 970.22227 | M59: =((J59/F59)^(1/4))-1 -> 0.00057219784 | O59: Operating Costs | P59: =P10*P$49 -> 681.02197 | Q59: =Q10*Q$49 -> 710.66244 | R59: =R10*R$49 -> 879.20054 | S59: =S10*S$49 -> 1070.7724 | T59: =T10*T$49 -> 1052.1426 | U59: =U10*U$49 -> 996.10665 | V59: =V10*V$49 -> 1001 | W59: =W10*W$49 -> 996.89805 | Z59: =((W59/S59)^(1/4))-1 -> -0.017713014
B60: Assumed Ordinary Depreciation | C60: =C11*C$49 -> 227.00732 | D60: =D11*D$49 -> 233.29349 | E60: =E11*E$49 -> 248.61566 | F60: =F11*F$49 -> 465.32743 | G60: =G11*G$49 -> 477.39665 | H60: =H11*H$49 -> 503.13604 | I60: =I11*I$49 -> 517.4 | J60: =J11*J$49 -> 555.43819 | M60: =((J60/F60)^(1/4))-1 -> 0.045247821 | O60: Assumed Ordinary Depreciation | P60: =P11*P$49 -> 227.00732 | Q60: =Q11*Q$49 -> 233.29349 | R60: =R11*R$49 -> 248.61566 | S60: =S11*S$49 -> 465.32743 | T60: =T11*T$49 -> 477.39665 | U60: =U11*U$49 -> 503.13604 | V60: =V11*V$49 -> 517.4 | W60: =W11*W$49 -> 555.43819 | Z60: =((W60/S60)^(1/4))-1 -> 0.045247821
B61: Total Expenditure | C61: =C12*C$49 -> 830.10691 | D61: =D12*D$49 -> 839.80917 | E61: =E12*E$49 -> 864.75011 | F61: =F12*F$49 -> 1433.3322 | G61: =G12*G$49 -> 1352.3305 | H61: =H12*H$49 -> 1459.5242 | I61: =I12*I$49 -> 1479.8 | J61: =J12*J$49 -> 1525.6605 | M61: =((J61/F61)^(1/4))-1 -> 0.015728774 | O61: Total Expenditure | P61: =P12*P$49 -> 908.02929 | Q61: =Q12*Q$49 -> 943.95593 | R61: =R12*R$49 -> 1127.8162 | S61: =S12*S$49 -> 1536.0999 | T61: =T12*T$49 -> 1529.5393 | U61: =U12*U$49 -> 1499.2427 | V61: =V12*V$49 -> 1518.4 | W61: =W12*W$49 -> 1552.3362 | Z61: =((W61/S61)^(1/4))-1 -> 0.0026320561
B63: Regulatory Operating Profit (Before Exceptional) | C63: =C14*C$49 -> 538.08233 | D63: =D14*D$49 -> 580.56785 | E63: =E14*E$49 -> 610.33152 | F63: =F14*F$49 -> 388.30695 | G63: =G14*G$49 -> 523.15633 | H63: =H14*H$49 -> 634.97214 | I63: =I14*I$49 -> 749.4 | J63: =J14*J$49 -> 867.88429 | M63: =((J63/F63)^(1/4))-1 -> 0.22270494 | O63: Regulatory Operating Profit (Before Exceptional) | P63: =P14*P$49 -> 494.45071 | Q63: =Q14*Q$49 -> 472.98507 | R63: =R14*R$49 -> 326.55695 | S63: =S14*S$49 -> 264.76479 | T63: =T14*T$49 -> 387.63728 | U63: =U14*U$49 -> 443.29628 | V63: =V14*V$49 -> 555.7 | W63: =W14*W$49 -> 606.36467 | Z63: =((W63/S63)^(1/4))-1 -> 0.2301793
B64: Exceptional | O64: Exceptional | P64: =P15*P$49 -> 0 | Q64: =Q15*Q$49 -> 0 | R64: =R15*R$49 -> 0 | S64: =S15*S$49 -> 0 | T64: =T15*T$49 -> 217.13848 | U64: =U15*U$49 -> -120.8323 | V64: =V15*V$49 -> 158.9 | W64: =W15*W$49 -> 60.141753
B65: Regulatory Operating Profit | C65: =C16*C$49 -> 538.08233 | D65: =D16*D$49 -> 580.56785 | E65: =E16*E$49 -> 610.33152 | F65: =F16*F$49 -> 388.30695 | G65: =G16*G$49 -> 523.15633 | H65: =H16*H$49 -> 634.97214 | I65: =I16*I$49 -> 749.4 | J65: =J16*J$49 -> 867.88429 | M65: =((J65/F65)^(1/4))-1 -> 0.22270494 | O65: Regulatory Operating Profit | P65: =P16*P$49 -> 494.45071 | Q65: =Q16*Q$49 -> 472.98507 | R65: =R16*R$49 -> 326.55695 | S65: =S16*S$49 -> 264.76479 | T65: =T16*T$49 -> 170.4988 | U65: =U16*U$49 -> 564.12858 | V65: =V16*V$49 -> 396.8 | W65: =W16*W$49 -> 546.22292 | Z65: =((W65/S65)^(1/4))-1 -> 0.19847071
B67: Capital Expenditure | C67: =C18*C$49 -> 1313.8648 | D67: =D18*D$49 -> 1103.4344 | E67: =E18*E$49 -> 1110.2936 | F67: =F18*F$49 -> 1215.0891 | G67: =G18*G$49 -> 1357.9405 | H67: =H18*H$49 -> 1205.179 | I67: =I18*I$49 -> 1008.5 | J67: =J18*J$49 -> 660.00723 | M67: =((J67/F67)^(1/4))-1 -> -0.1415102 | O67: Capital Expenditure | P67: =P18*P$49 -> 1603.3084 | Q67: =Q18*Q$49 -> 1245.4958 | R67: =R18*R$49 -> 1017.2192 | S67: =S18*S$49 -> 817.61046 | T67: =T18*T$49 -> 884.72379 | U67: =U18*U$49 -> 850.96118 | V67: =V18*V$49 -> 963.5 | W67: =W18*W$49 -> 1173.3462 | Z67: =((W67/S67)^(1/4))-1 -> 0.094510502
P68: =P19*P$49 -> 0 | Q68: =Q19*Q$49 -> 0 | R68: =R19*R$49 -> 0 | S68: =S19*S$49 -> 0 | T68: =T19*T$49 -> 0 | U68: =U19*U$49 -> 0 | V68: =V19*V$49 -> 0 | W68: =W19*W$49 -> 0
B69: Opening Basic RAB | C69: =C20*C$49 -> 7382.1012 | D69: =D20*D$49 -> 8342.6415 | E69: =E20*E$49 -> 9250.5505 | F69: =F20*F$49 -> 10202.284 | G69: =G20*G$49 -> 11106.292 | H69: =H20*H$49 -> 12092.766 | I69: =I20*I$49 -> 12973.9 | J69: =J20*J$49 -> 13576.807 | M69: =((J69/F69)^(1/4))-1 -> 0.074051364 | O69: Opening Basic RAB | P69: =P20*P$49 -> 7776.8751 | Q69: =Q20*Q$49 -> 9000.6974 | R69: =R20*R$49 -> 10051.81 | S69: =S20*S$49 -> 10202.284 | T69: =T20*T$49 -> 10717.115 | U69: =U20*U$49 -> 11243.272 | V69: =V20*V$49 -> 11773 | W69: =W20*W$49 -> 12324.5 | Z69: =((W69/S69)^(1/4))-1 -> 0.048378175
B71: Closing Basic RAB | C71: =C22*C$49 -> 8654.055 | D71: =D22*D$49 -> 9632.687 | E71: =E22*E$49 -> 11123.759 | F71: =F22*F$49 -> 11157.139 | G71: =G22*G$49 -> 12692.921 | H71: =H22*H$49 -> 13596.41 | I71: =I22*I$49 -> 13996.3 | J71: =J22*J$49 -> 14088.109 | M71: =((J71/F71)^(1/4))-1 -> 0.060046599 | O71: Closing Basic RAB | P71: =P22*P$49 -> 9336.6748 | Q71: =Q22*Q$49 -> 10467.046 | R71: =R22*R$49 -> 11123.759 | S71: =S22*S$49 -> 10766.18 | T71: =T22*T$49 -> 11801.267 | U71: =U22*U$49 -> 12337.889 | V71: =V22*V$49 -> 12705.3 | W71: =W22*W$49 -> 13316.451 | Z71: =((W71/S71)^(1/4))-1 -> 0.054585294
B73: Weighted average basic RAB | C73: =C24*C$49 -> 8006.2177 | D73: =D24*D$49 -> 8975.579 | E73: =E24*E$49 -> 10169.689 | F73: =F24*F$49 -> 10679.767 | G73: =G24*G$49 -> 11899.606 | H73: =H24*H$49 -> 12844.588 | I73: =I24*I$49 -> 13485.1 | J73: =J24*J$49 -> 13832.506 | M73: =((J73/F73)^(1/4))-1 -> 0.066804333 | O73: Weighted average basic RAB | P73: 6950.2 | Q73: 8203.8 | R73: 9296.5 | S73: 9487.8 | T73: 10235.7 | U73: 11250.7 | V73: 12239.1 | W73: 12239.1 | Z73: =((W73/S73)^(1/4))-1 -> 0.065727053
B75: Return on weighted average basic RAB (pre-exceptional) (%) | C75: 6.7 | D75: 6.5 | E75: 6 | F75: 3.6 | G75: 4.4 | H75: 4.9 | I75: 5.6 | J75: 5.6 | M75: =((J75/F75)^(1/4))-1 -> 0.11678965 | O75: Return on weighted average basic RAB (pre-exceptional) (%) | P75: 5.8 | Q75: 4.9 | R75: 3.1 | S75: 2.5 | T75: 3.4 | U75: 3.8 | V75: 4.5 | W75: 4.5 | Z75: =((W75/S75)^(1/4))-1 -> 0.15829219
B77: Return on weighted average basic RAB (%) | C77: 6.7 | D77: 6.5 | E77: 6 | F77: 3.6 | G77: 4.4 | H77: 4.9 | I77: 5.6 | J77: 5.6 | M77: =((J77/F77)^(1/4))-1 -> 0.11678965 | O77: Return on weighted average basic RAB (%) | P77: 5.8 | Q77: 4.9 | R77: 3.1 | S77: 2.5 | T77: 1.5 | U77: 4.8 | V77: 3.2 | W77: 3.2 | Z77: =((W77/S77)^(1/4))-1 -> 0.063659179
B80: Breakdown of Operating Costs - CAA Projection | C80: Q4 | F80: Q5 | K80: Q5+1 | O80: Breakdown of Operating Costs | P80: Q4 | S80: Q5 | X80: Q5+1
B81: £m 2011/12 | C81: 2005/06 | D81: 2006/07 | E81: 2007/08 | F81: 2008/09 | G81: 2009/10 | H81: 2010/11 | I81: 2011/12 | J81: 2012/13 | K81: 2013/14 | M81: CAGR (Q5) | O81: £m 2011/12 | P81: 2005/06 | Q81: 2006/07 | R81: 2007/08 | S81: 2008/09 | T81: 2009/10 | U81: 2010/11 | V81: 2011/12 | W81: 2012/13 | X81: 2013/14 | Z81: CAGR (Q5)
B82: Staff Costs | F82: =F32*F$49 -> 275.92557 | G82: =G32*G$49 -> 269.05811 | H82: =H32*H$49 -> 265.34898 | I82: =I32*I$49 -> 261.5 | J82: =J32*J$49 -> 259.7612 | M82: =((J82/F82)^(1/4))-1 -> -0.014978785 | O82: Staff Costs | S82: =S32*S$49 -> 289.51742 | T82: =T32*T$49 -> 254.64821 | U82: =U32*U$49 -> 258.85149 | V82: =V32*V$49 -> 270.4 | W82: =W32*W$49 -> 318.55728 | Z82: =((W82/S82)^(1/4))-1 -> 0.024184525
B83: Maintenance and equipment costs | F83: =F33*F$49 -> 79.672542 | G83: =G33*G$49 -> 117.03918 | H83: =H33*H$49 -> 116.74517 | I83: =I33*I$49 -> 115.3 | J83: =J33*J$49 -> 114.43757 | M83: =((J83/F83)^(1/4))-1 -> 0.094750079 | O83: Maintenance and equipment costs | S83: =S33*S$49 -> 128.8463 | T83: =T33*T$49 -> 133.42906 | U83: =U33*U$49 -> 110.14288 | V83: =V33*V$49 -> 118 | W83: =W33*W$49 -> 123.09659 | Z83: =((W83/S83)^(1/4))-1 -> -0.011347854
B84: Rent and rates | F84: =F34*F$49 -> 108.29278 | G84: =G34*G$49 -> 107.46925 | H84: =H34*H$49 -> 108.04692 | I84: =I34*I$49 -> 109.3 | J84: =J34*J$49 -> 115.59469 | M84: =((J84/F84)^(1/4))-1 -> 0.016446672 | O84: Rent and rates | S84: =S34*S$49 -> 115.03345 | T84: =T34*T$49 -> 121.65915 | U84: =U34*U$49 -> 109.1997 | V84: =V34*V$49 -> 116.9 | W84: =W34*W$49 -> 124.74564 | Z84: =((W84/S84)^(1/4))-1 -> 0.020470149
B85: Utility costs | F85: =F35*F$49 -> 100.88909 | G85: =G35*G$49 -> 102.18928 | H85: =H35*H$49 -> 107.31333 | I85: =I35*I$49 -> 110.6 | J85: =J35*J$49 -> 118.6545 | M85: =((J85/F85)^(1/4))-1 -> 0.041381862 | O85: Utility costs | S85: =S35*S$49 -> 92.490871 | T85: =T35*T$49 -> 118.68917 | U85: =U35*U$49 -> 97.147908 | V85: =V35*V$49 -> 89.4 | W85: =W35*W$49 -> 84.198454 | Z85: =((W85/S85)^(1/4))-1 -> -0.023209759
B86: Police costs | F86: =F36*F$49 -> 36.576437 | G86: =G36*G$49 -> 38.609729 | H86: =H36*H$49 -> 38.146536 | I86: =I36*I$49 -> 38.9 | J86: =J36*J$49 -> 38.603002 | M86: =((J86/F86)^(1/4))-1 -> 0.013572735 | O86: Police costs | S86: =S36*S$49 -> 37.128952 | T86: =T36*T$49 -> 34.539757 | U86: =U36*U$49 -> 29.448287 | V86: =V36*V$49 -> 28.8 | W86: =W36*W$49 -> 27.4518 | Z86: =((W86/S86)^(1/4))-1 -> -0.072712224
B87: Rail costs | F87: =F37*F$49 -> 59.892535 | G87: =G37*G$49 -> 60.829573 | H87: =H37*H$49 -> 61.935721 | I87: =I37*I$49 -> 63.3 | J87: =J37*J$49 -> 65.50753 | M87: =((J87/F87)^(1/4))-1 -> 0.022656145 | O87: Rail costs | S87: =S37*S$49 -> 57.682478 | T87: =T37*T$49 -> 59.729581 | U87: =U37*U$49 -> 59.944556 | V87: =V37*V$49 -> 58.9 | W87: =W37*W$49 -> 57.328671 | Z87: =((W87/S87)^(1/4))-1 -> -0.0015369681
B88: Other costs | F88: =F38*F$49 -> 194.48498 | G88: =G38*G$49 -> 142.889 | H88: =H38*H$49 -> 145.87906 | I88: =I38*I$49 -> 152 | J88: =J38*J$49 -> 145.33789 | M88: =((J88/F88)^(1/4))-1 -> -0.070234994 | O88: Other costs | S88: =S38*S$49 -> 164.98073 | T88: =T38*T$49 -> 181.71872 | U88: =U38*U$49 -> 155.73009 | V88: =V38*V$49 -> 149.4 | W88: =W38*W$49 -> 149.57836 | Z88: =((W88/S88)^(1/4))-1 -> -0.02420433
B89: Intragroup costs | F89: =F39*F$49 -> 112.27088 | G89: =G39*G$49 -> 113.8492 | H89: =H39*H$49 -> 112.97243 | I89: =I39*I$49 -> 111.5 | J89: =J39*J$49 -> 110.81293 | M89: =((J89/F89)^(1/4))-1 -> -0.0032624266 | O89: Intragroup costs | S89: =S39*S$49 -> 167.30129 | T89: =T39*T$49 -> 151.35894 | U89: =U39*U$49 -> 176.37533 | V89: =V39*V$49 -> 172.6 | W89: =W39*W$49 -> 123.29059 | Z89: =((W89/S89)^(1/4))-1 -> -0.073473886
B91: Total operating costs | F91: =F41*F$49 -> 968.00481 | G91: =G41*G$49 -> 951.93332 | H91: =H41*H$49 -> 956.38814 | I91: =I41*I$49 -> 962.4 | J91: =J41*J$49 -> 968.70932 | M91: =((J91/F91)^(1/4))-1 -> 0.00018189874 | O91: Total operating costs | S91: =S41*S$49 -> 1052.9815 | T91: =T41*T$49 -> 1055.7726 | U91: =U41*U$49 -> 996.84024 | V91: =V41*V$49 -> 1004.4 | W91: =W41*W$49 -> 1008.3444 | Z91: =((W91/S91)^(1/4))-1 -> -0.01077055
B93: Exceptional operating costs | F93: =F43*F$49 -> 0 | G93: =G43*G$49 -> 0 | H93: =H43*H$49 -> 0 | I93: =I43*I$49 -> 0 | J93: =J43*J$49 -> 0 | O93: Exceptional operating costs | S93: =S43*S$49 -> 28.178222 | T93: =T43*T$49 -> 0 | U93: =U43*U$49 -> 0 | V93: =V43*V$49 -> 0 | W93: =W43*W$49 -> 0 | Z93: =((W93/S93)^(1/4))-1 -> -1
B94: Service Quality Rebates | F94: =F44*F$49 -> 0 | G94: =G44*G$49 -> 0 | H94: =H44*H$49 -> 0 | I94: =I44*I$49 -> 0 | J94: =J44*J$49 -> 0 | O94: Service Quality Rebates | S94: =S44*S$49 -> -10.387266 | T94: =T44*T$49 -> -3.6299745 | U94: =U44*U$49 -> -0.73358722 | V94: =V44*V$49 -> -3.4 | W94: =W44*W$49 -> -11.446334 | Z94: =((W94/S94)^(1/4))-1 -> 0.02456917
B96: Adjusted operating costs | F96: =F46*F$49 -> 968.00481 | G96: =G46*G$49 -> 951.93332 | H96: =H46*H$49 -> 956.38814 | I96: =I46*I$49 -> 962.4 | J96: =J46*J$49 -> 968.70932 | M96: =((J96/F96)^(1/4))-1 -> 0.00018189874 | O96: Adjusted operating costs | S96: =S46*S$49 -> 1070.7724 | T96: =T46*T$49 -> 1052.1426 | U96: =U46*U$49 -> 996.10665 | V96: =V46*V$49 -> 1001 | W96: =W46*W$49 -> 996.89805 | Z96: =((W96/S96)^(1/4))-1 -> -0.017713014
B100: End

Sheet GAL - Reg
B2: Gatwick - CAA Allowance | P2: Gatwick - Outturn
B4: Regulatory Accounts | C4: Q4 | F4: Q5 | K4: Q5+1 | P4: Regulatory Accounts | Q4: Q4 | T4: Q5 | Y4: Q5+1
B5: £m nominal | C5: 2005/06 | D5: 2006/07 | E5: 2007/08 | F5: 2008/09 | G5: 2009/10 | H5: 2010/11 | I5: 2011/12 | J5: 2012/13 | K5: 2013/14 | M5: CAGR (3) | P5: £m nominal | Q5: 2005/06 | R5: 2006/07 | S5: 2007/08 | T5: 2008/09 | U5: 2009/10 | V5: 2010/11 | W5: 2011/12 | X5: 2012/13 | Y5: 2013/14 | AA5: CAGR (3)
B6: Terminal Pax | C6: 36000 | D6: 38600 | E6: 39700 | F6: 35900 | G6: 36400 | H6: 36800 | I6: 37200 | J6: 37700 | M6: =((I6/F6)^(1/4))-1 -> 0.0089325255 | P6: Terminal Pax | Q6: 32845 | R6: 34383 | S6: 35562 | T6: 33105 | U6: 32397 | V6: 31647 | W6: 33819 | X6: 34241 | AA6: =((W6/T6)^(1/3))-1 -> 0.0071381716
B7: Net Revenue from Airport Charges | C7: 165.2 | D7: 183.7 | E7: 196.7 | F7: 250.9 | G7: 270.7 | H7: 275.9 | I7: 297.7 | J7: 323.5 | M7: =((I7/F7)^(1/4))-1 -> 0.043685244 | P7: Net Revenue from Airport Charges | Q7: 153.4 | R7: 163.8 | S7: 178.3 | T7: 234.5 | U7: 241.6 | V7: 241.9 | W7: 271.3 | X7: 282.5 | AA7: =((W7/T7)^(1/3))-1 -> 0.04978972
B8: Other Revenue | C8: 203.7 | D8: 223.2 | E8: 236.7 | F8: 222.1 | G8: 224.9 | H8: 237.8 | I8: 252.2 | J8: 261.7 | M8: =((I8/F8)^(1/4))-1 -> 0.032283845 | P8: Other Revenue | Q8: 201.7 | R8: 213 | S8: 225.2 | T8: 220.3 | U8: 219.6 | V8: 217.1 | W8: 231.4 | X8: 239.2 | AA8: =((W8/T8)^(1/3))-1 -> 0.016520838
B9: Total Revenue | C9: 368.9 | D9: 406.9 | E9: 433.4 | F9: 473 | G9: 495.6 | H9: 513.7 | I9: 549.9 | J9: 585.2 | M9: =((I9/F9)^(1/4))-1 -> 0.038378398 | P9: Total Revenue | Q9: 355.1 | R9: 376.8 | S9: 403.5 | T9: 454.8 | U9: 461.2 | V9: 459 | W9: 502.7 | X9: 521.7 | AA9: =((W9/T9)^(1/3))-1 -> 0.033941919
B10: Operating Costs | C10: 195.8 | D10: 211.9 | E10: 227.7 | F10: 284.9 | G10: 284.9 | H10: 299.2 | I10: 314.8 | J10: 322.4 | M10: =((I10/F10)^(1/4))-1 -> 0.02526367 | P10: Operating Costs | Q10: 223.4 | R10: 225.4 | S10: 272.3 | T10: 282.1 | U10: 289.6 | V10: 268 | W10: 280.9 | X10: 294.2 | AA10: =((W10/T10)^(1/3))-1 -> -0.0014199522
B11: Assumed Ordinary Depreciation | C11: 63.8 | D11: 70.4 | E11: 79.8 | F11: 76.5 | G11: 81.3 | H11: 89.8 | I11: 98.1 | J11: 114.5 | M11: =((I11/F11)^(1/4))-1 -> 0.064147657 | P11: Assumed Ordinary Depreciation | Q11: 63.8 | R11: 70.4 | S11: 79.8 | T11: 76.5 | U11: 81.3 | V11: 89.8 | W11: 98.1 | X11: 114.5 | AA11: =((W11/T11)^(1/3))-1 -> 0.086431938
B12: Total Expenditure | C12: 259.6 | D12: 282.3 | E12: 307.5 | F12: 361.4 | G12: 366.2 | H12: 389 | I12: 412.9 | J12: 436.9 | M12: =((I12/F12)^(1/4))-1 -> 0.033865834 | P12: Total Expenditure | Q12: 287.2 | R12: 295.8 | S12: 352.1 | T12: 358.6 | U12: 370.9 | V12: 357.8 | W12: 379 | X12: 408.7 | AA12: =((W12/T12)^(1/3))-1 -> 0.018614002
B14: Regulatory Operating Profit (Before Exceptional) | C14: 109.3 | D14: 124.6 | E14: 125.9 | F14: 111.6 | G14: 129.4 | H14: 124.7 | I14: 137 | J14: 148.3 | M14: =((I14/F14)^(1/4))-1 -> 0.052601763 | P14: Regulatory Operating Profit (Before Exceptional) | Q14: 67.9 | R14: 81 | S14: 51.4 | T14: 96.2 | U14: 90.3 | V14: 101.2 | W14: 123.7 | X14: 113 | AA14: =((W14/T14)^(1/3))-1 -> 0.087422236
B15: Exceptional | C15: 0 | D15: 0 | E15: 0 | F15: 0 | G15: 0 | H15: 0 | I15: 0 | J15: 0 | P15: Exceptional | Q15: 0 | R15: 0 | S15: 0 | T15: 0 | U15: 120 | V15: 17 | W15: 0 | X15: 0
B16: Regulatory Operating Profit | C16: 109.3 | D16: 124.6 | E16: 125.9 | F16: 111.6 | G16: 129.4 | H16: 124.7 | I16: 137 | J16: 148 | M16: =((I16/F16)^(1/4))-1 -> 0.052601763 | P16: Regulatory Operating Profit | Q16: 67.9 | R16: 81 | S16: 51.4 | T16: 96.2 | U16: -29.7 | V16: 84.2 | W16: 123.7 | X16: 113 | AA16: =((W16/T16)^(1/3))-1 -> 0.087422236
B18: Capital Expenditure | C18: 110.2 | D18: 148.4 | E18: 177.1 | F18: 200.6 | G18: 257.7 | H18: 259.7 | I18: 167.4 | J18: 105 | M18: =((I18/F18)^(1/4))-1 -> -0.044223977 | P18: Capital Expenditure | Q18: 84.1 | R18: 101 | S18: 103.7 | T18: 104 | U18: 181.4 | V18: 232.2 | W18: 239.2 | X18: 226.7 | AA18: =((W18/T18)^(1/3))-1 -> 0.32000612
B20: Opening Basic RAB | C20: 1329.7 | D20: 1408 | E20: 1555.5 | F20: 1559.7 | G20: 1670.6 | H20: 1922 | I20: 2201.1 | J20: 2353.1 | M20: =((I20/F20)^(1/4))-1 -> 0.089932682 | P20: Opening Basic RAB | Q20: 1364.1 | R20: 1416.8 | S20: 1515.7 | T20: 1559.7 | U20: 1575.5 | V20: 1744.6 | W20: 1985.5 | X20: 2200.9 | AA20: =((W20/T20)^(1/3))-1 -> 0.08378451
B22: Closing Basic RAB | C22: 1408 | D22: 1555.5 | E22: 1559.7 | F22: 1670.6 | G22: 1922 | H22: 2201.1 | I22: 2353.1 | J22: 2425.5 | M22: =((I22/F22)^(1/4))-1 -> 0.089411553 | P22: Closing Basic RAB | Q22: 1416.8 | R22: 1515.7 | S22: 1559.7 | T22: 1575.5 | U22: 1744.6 | V22: 1985.5 | W22: 2200.9 | X22: 2391.6 | AA22: =((W22/T22)^(1/3))-1 -> 0.11787686
B24: Weighted average basic RAB | C24: 1368.1 | D24: 1480.3 | E24: 1557.6 | F24: 1615.1 | G24: 1796.3 | H24: 2061.6 | I24: 2277.1 | J24: 2389.3 | M24: =((I24/F24)^(1/4))-1 -> 0.089671699 | P24: Weighted average basic RAB | Q24: 1390 | R24: 1465.3 | S24: 1559.7 | T24: 1567.6 | U24: 1660.1 | V24: 1865.2 | W24: 2093.2 | X24: 2296.3 | AA24: =((W24/T24)^(1/3))-1 -> 0.10118044
B26: Return on weighted average basic RAB (pre-exceptional) (%) | C26: 8 | D26: 8.4 | E26: 8.1 | F26: 6.9 | G26: 7.2 | H26: 6 | I26: 6 | J26: 6.2 | P26: Return on weighted average basic RAB (pre-exceptional) (%) | Q26: 4.9 | R26: 5.5 | S26: 3.3 | T26: 6.1 | U26: 5.4 | V26: 5.4 | W26: 5.9 | X26: 4.9
B28: Return on weighted average basic RAB (%) | C28: 8 | D28: 8.4 | E28: 8.1 | F28: 6.9 | G28: 7.2 | H28: 6 | I28: 6 | J28: 6.2 | P28: Return on weighted average basic RAB (%) | Q28: 4.9 | R28: 5.5 | S28: 3.3 | T28: 6.1 | U28: -1.8 | V28: 4.5 | W28: 5.9 | X28: 4.9
B30: Breakdown of Operating Costs - CAA Projections | C30: Q4 | F30: Q5 | K30: Q5+1 | P30: Breakdown of Operating Costs | Q30: Q4 | T30: Q5 | Y30: Q5+1
B31: £m nominal | C31: 2005/06 | D31: 2006/07 | E31: 2007/08 | F31: 2008/09 | G31: 2009/10 | H31: 2010/11 | I31: 2011/12 | J31: 2012/13 | K31: 2013/14 | M31: CAGR (Q5) | P31: £m nominal | Q31: 2005/06 | R31: 2006/07 | S31: 2007/08 | T31: 2008/09 | U31: 2009/10 | V31: 2010/11 | W31: 2011/12 | X31: 2012/13 | Y31: 2013/14 | AA31: CAGR (Q5)
B32: Staff Costs | F32: 121.3 | G32: 119.7 | H32: 123.1 | I32: 127.6 | J32: 128.2 | M32: =((J32/F32)^(1/4))-1 -> 0.013927275 | P32: Staff Costs | T32: 101.3 | U32: 113.7 | V32: 128.5 | W32: 140.5 | X32: 149.1 | AA32: =((W32/T32)^(1/3))-1 -> 0.11520736
B33: Maintenance and equipment costs | F33: 25.7 | G33: 25.7 | H33: 29.1 | I33: 31.5 | J33: 32.3 | M33: =((J33/F33)^(1/4))-1 -> 0.058808331 | P33: Maintenance and equipment costs | T33: 30.2 | U33: 26.5 | V33: 25.6 | W33: 35.2 | X33: 37.1 | AA33: =((W33/T33)^(1/3))-1 -> 0.052394509
B34: Rent and rates | F34: 25.9 | G34: 26.9 | H34: 28.5 | I34: 31.7 | J34: 33.9 | M34: =((J34/F34)^(1/4))-1 -> 0.06960884 | P34: Rent and rates | T34: 24.8 | U34: 25 | V34: 22.5 | W34: 26.8 | X34: 28.2 | AA34: =((W34/T34)^(1/3))-1 -> 0.026189826
B35: Utility costs | F35: 26.6 | G35: 27 | H35: 28.8 | I35: 30.8 | J35: 32.1 | M35: =((J35/F35)^(1/4))-1 -> 0.048107549 | P35: Utility costs | T35: 26.2 | U35: 31.7 | V35: 28.2 | W35: 30.2 | X35: 27.6 | AA35: =((W35/T35)^(1/3))-1 -> 0.048500279
B36: Police costs | F36: 13.4 | G36: 13.3 | H36: 13.8 | I36: 14.3 | J36: 14.5 | M36: =((J36/F36)^(1/4))-1 -> 0.019919279 | P36: Police costs | T36: 13.8 | U36: 13.2 | V36: 13.3 | W36: 12.7 | X36: 12.2 | AA36: =((W36/T36)^(1/3))-1 -> -0.027309043
B37: Other costs | F37: 36.7 | G37: 37.7 | H37: 39.9 | I37: 41.7 | J37: 43.7 | M37: =((J37/F37)^(1/4))-1 -> 0.044609192 | P37: Other costs | T37: 52.2 | U37: 59.1 | V37: 51.5 | W37: 35.5 | X37: 40 | AA37: =((W37/T37)^(1/3))-1 -> -0.12060104
B38: Intergroup costs | F38: 35.3 | G38: 34.6 | H38: 36 | I38: 37.2 | J38: 37.7 | M38: =((J38/F38)^(1/4))-1 -> 0.016580234 | P38: Intergroup costs | T38: 41.3 | U38: 23.1 | V38: 0 | W38: 0 | X38: 0 | AA38: =((W38/T38)^(1/3))-1 -> -1
B40: Total operating costs | F40: 284.9 | G40: 284.9 | H40: 299.2 | I40: 314.8 | J40: 322.4 | M40: =((J40/F40)^(1/4))-1 -> 0.031396483 | P40: Total operating costs | T40: 289.9 | U40: 292.3 | V40: 269.6 | W40: =SUM(W32:W38) -> 280.9 | X40: 294.2 | AA40: =((W40/T40)^(1/3))-1 -> -0.010457371
B42: Exceptional operating costs | F42: 0 | G42: 0 | H42: 0 | I42: 0 | J42: 0 | P42: Exceptional operating costs | T42: -2.1 | U42: 0 | V42: 0 | W42: 0 | X42: 0
B43: Service Quality Rebates | F43: 0 | G43: 0 | H43: 0 | I43: 0 | J43: 0 | P43: Service Quality Rebates | T43: -5.6 | U43: -2.7 | V43: -1.6 | W43: 0 | X43: 0
B45: Adjusted operating costs | F45: =F40-F42-F43 -> 284.9 | G45: =G40-G42-G43 -> 284.9 | H45: =H40-H42-H43 -> 299.2 | I45: =I40-I42-I43 -> 314.8 | J45: 322 | M45: =((I45/F45)^(1/3))-1 -> 0.03382594 | P45: Adjusted operating costs | T45: =T40+T42+T43 -> 282.2 | U45: =U40+U43 -> 289.6 | V45: =V40+V43 -> 268 | W45: 280.9 | X45: 294.2 | AA45: =((W45/T45)^(1/3))-1 -> -0.001537918
B48: Price Base Conversion to 2011/12 | C48: =RPI!$X$103/RPI!$X97 -> 1.2290597 | D48: =RPI!$X$103/RPI!$X98 -> 1.1848323 | E48: =RPI!$X$103/RPI!$X99 -> 1.1378291 | F48: =RPI!$X$103/RPI!$X100 -> 1.1050283 | G48: =RPI!$X$103/RPI!$X101 -> 1.0999923 | H48: =RPI!$X$103/RPI!$X102 -> 1.0479817 | I48: =RPI!$X$103/RPI!$X103 -> 1 | J48: =RPI!$X$103/RPI!$X104 -> 0.96899225 | P48: Price Base Conversion to 2011/12 | Q48: =RPI!$X$103/RPI!$X97 -> 1.2290597 | R48: =RPI!$X$103/RPI!$X98 -> 1.1848323 | S48: =RPI!$X$103/RPI!$X99 -> 1.1378291 | T48: =RPI!$X$103/RPI!$X100 -> 1.1050283 | U48: =RPI!$X$103/RPI!$X101 -> 1.0999923 | V48: =RPI!$X$103/RPI!$X102 -> 1.0479817 | W48: =RPI!$X$103/RPI!$X103 -> 1 | X48: =RPI!$X$103/RPI!$X104 -> 0.96899225
B50: Gatwick - CAA Allowance | P50: Gatwick - Outturn
B52: Regulatory Accounts | C52: Q4 | F52: Q5 | K52: Q5+1 | P52: Regulatory Accounts | Q52: Q4 | T52: Q5 | Y52: Q5+1
B53: £m 2011/12 | C53: 2005/06 | D53: 2006/07 | E53: 2007/08 | F53: 2008/09 | G53: 2009/10 | H53: 2010/11 | I53: 2011/12 | J53: 2012/13 | K53: 2013/14 | M53: CAGR (3) | P53: £m 2011/12 | Q53: 2005/06 | R53: 2006/07 | S53: 2007/08 | T53: 2008/09 | U53: 2009/10 | V53: 2010/11 | W53: 2011/12 | X53: 2012/13 | Y53: 2013/14 | AA53: CAGR (3)
B54: Terminal Pax | C54: =C6 -> 36000 | D54: =D6 -> 38600 | E54: =E6 -> 39700 | F54: =F6 -> 35900 | G54: =G6 -> 36400 | H54: =H6 -> 36800 | I54: =I6 -> 37200 | J54: =J6 -> 37700 | M54: =((I54/F54)^(1/3))-1 -> 0.01192773 | P54: Terminal Pax | Q54: 32845 | R54: 34383 | S54: 35562 | T54: 33105 | U54: 32397 | V54: 31647 | W54: 33819 | X54: 33820 | AA54: =((W54/T54)^(1/3))-1 -> 0.0071381716
B55: Net Revenue from Airport Charges | C55: =C7*C$48 -> 203.04066 | D55: =D7*D$48 -> 217.6537 | E55: =E7*E$48 -> 223.81098 | F55: =F7*F$48 -> 277.25161 | G55: =G7*G$48 -> 297.76791 | H55: =H7*H$48 -> 289.13816 | I55: =I7*I$48 -> 297.7 | J55: =J7*J$48 -> 313.46899 | M55: =((I55/F55)^(1/3))-1 -> 0.024003846 | P55: Net Revenue from Airport Charges | Q55: =Q7*Q$48 -> 188.53776 | R55: =R7*R$48 -> 194.07554 | S55: =S7*S$48 -> 202.87493 | T55: =T7*T$48 -> 259.12914 | U55: =U7*U$48 -> 265.75813 | V55: =V7*V$48 -> 253.50679 | W55: =W7*W$48 -> 271.3 | X55: =X7*X$48 -> 273.74031 | AA55: =((W55/T55)^(1/3))-1 -> 0.015417192
B56: Other Revenue | C56: =C8*C$48 -> 250.35946 | D56: =D8*D$48 -> 264.45458 | E56: =E8*E$48 -> 269.32415 | F56: =F8*F$48 -> 245.42679 | G56: =G8*G$48 -> 247.38826 | H56: =H8*H$48 -> 249.21006 | I56: =I8*I$48 -> 252.2 | J56: =J8*J$48 -> 253.58527 | M56: =((I56/F56)^(1/3))-1 -> 0.0091158742 | P56: Other Revenue | Q56: =Q8*Q$48 -> 247.90134 | R56: =R8*R$48 -> 252.36929 | S56: =S8*S$48 -> 256.23911 | T56: =T8*T$48 -> 243.43774 | U56: =U8*U$48 -> 241.5583 | V56: =V8*V$48 -> 227.51684 | W56: =W8*W$48 -> 231.4 | X56: =X8*X$48 -> 231.78295 | AA56: =((W56/T56)^(1/3))-1 -> -0.01676239
B57: Total Revenue | C57: =C9*C$48 -> 453.40012 | D57: =D9*D$48 -> 482.10828 | E57: =E9*E$48 -> 493.13513 | F57: =F9*F$48 -> 522.6784 | G57: =G9*G$48 -> 545.15617 | H57: =H9*H$48 -> 538.34822 | I57: =I9*I$48 -> 549.9 | J57: =J9*J$48 -> 567.05426 | M57: =((I57/F57)^(1/3))-1 -> 0.017067374 | P57: Total Revenue | Q57: =Q9*Q$48 -> 436.43909 | R57: =R9*R$48 -> 446.44483 | S57: =S9*S$48 -> 459.11404 | T57: =T9*T$48 -> 502.56688 | U57: =U9*U$48 -> 507.31644 | V57: =V9*V$48 -> 481.02362 | W57: =W9*W$48 -> 502.7 | X57: =X9*X$48 -> 505.52326 | AA57: =((W57/T57)^(1/3))-1 -> 8.8284697e-05
B58: Operating Costs | C58: =C10*C$48 -> 240.64989 | D58: =D10*D$48 -> 251.06597 | E58: =E10*E$48 -> 259.08368 | F58: =F10*F$48 -> 314.82257 | G58: =G10*G$48 -> 313.3878 | H58: =H10*H$48 -> 313.55614 | I58: =I10*I$48 -> 314.8 | J58: =J10*J$48 -> 312.4031 | M58: =((I58/F58)^(1/3))-1 -> -2.3896842e-05 | P58: Operating Costs | Q58: =Q10*Q$48 -> 274.57193 | R58: =R10*R$48 -> 267.06121 | S58: =S10*S$48 -> 309.83086 | T58: =T10*T$48 -> 311.72849 | U58: =U10*U$48 -> 318.55776 | V58: =V10*V$48 -> 280.85911 | W58: =W10*W$48 -> 280.9 | X58: =X10*X$48 -> 285.07752 | AA58: =((W58/T58)^(1/3))-1 -> -0.034115757
B59: Assumed Ordinary Depreciation | C59: =C11*C$48 -> 78.414008 | D59: =D11*D$48 -> 83.412197 | E59: =E11*E$48 -> 90.798762 | F59: =F11*F$48 -> 84.534667 | G59: =G11*G$48 -> 89.429372 | H59: =H11*H$48 -> 94.108761 | I59: =I11*I$48 -> 98.1 | J59: =J11*J$48 -> 110.94961 | M59: =((I59/F59)^(1/3))-1 -> 0.05085966 | P59: Assumed Ordinary Depreciation | Q59: =Q11*Q$48 -> 78.414008 | R59: =R11*R$48 -> 83.412197 | S59: =S11*S$48 -> 90.798762 | T59: =T11*T$48 -> 84.534667 | U59: =U11*U$48 -> 89.429372 | V59: =V11*V$48 -> 94.108761 | W59: =W11*W$48 -> 98.1 | X59: =X11*X$48 -> 110.94961 | AA59: =((W59/T59)^(1/3))-1 -> 0.05085966
B60: Total Expenditure | C60: =C12*C$48 -> 319.06389 | D60: =D12*D$48 -> 334.47817 | E60: =E12*E$48 -> 349.88245 | F60: =F12*F$48 -> 399.35724 | G60: =G12*G$48 -> 402.81717 | H60: =H12*H$48 -> 407.6649 | I60: =I12*I$48 -> 412.9 | J60: =J12*J$48 -> 423.35271 | M60: =((I60/F60)^(1/3))-1 -> 0.011178379 | P60: Total Expenditure | Q60: =Q12*Q$48 -> 352.98594 | R60: =R12*R$48 -> 350.47341 | S60: =S12*S$48 -> 400.62962 | T60: =T12*T$48 -> 396.26316 | U60: =U12*U$48 -> 407.98714 | V60: =V12*V$48 -> 374.96787 | W60: =W12*W$48 -> 379 | X60: =X12*X$48 -> 396.02713 | AA60: =((W60/T60)^(1/3))-1 -> -0.014737761
B62: Regulatory Operating Profit (Before Exceptional) | C62: =C14*C$48 -> 134.33622 | D62: =D14*D$48 -> 147.63011 | E62: =E14*E$48 -> 143.25268 | F62: =F14*F$48 -> 123.32116 | G62: =G14*G$48 -> 142.339 | H62: =H14*H$48 -> 130.68332 | I62: =I14*I$48 -> 137 | J62: =J14*J$48 -> 143.70155 | M62: =((I62/F62)^(1/3))-1 -> 0.035684924 | P62: Regulatory Operating Profit (Before Exceptional) | Q62: =Q14*Q$48 -> 83.453152 | R62: =R14*R$48 -> 95.97142 | S62: =S14*S$48 -> 58.484415 | T62: =T14*T$48 -> 106.30372 | U62: =U14*U$48 -> 99.329302 | V62: =V14*V$48 -> 106.05575 | W62: =W14*W$48 -> 123.7 | X62: =X14*X$48 -> 109.49612 | AA62: =((W62/T62)^(1/3))-1 -> 0.051817533
B63: Exceptional | P63: Exceptional
B64: Regulatory Operating Profit | C64: =C16*C$48 -> 134.33622 | D64: =D16*D$48 -> 147.63011 | E64: =E16*E$48 -> 143.25268 | F64: =F16*F$48 -> 123.32116 | G64: =G16*G$48 -> 142.339 | H64: =H16*H$48 -> 130.68332 | I64: =I16*I$48 -> 137 | J64: =J16*J$48 -> 143.41085 | M64: =((I64/F64)^(1/3))-1 -> 0.035684924 | P64: Regulatory Operating Profit | Q64: =Q16*Q$48 -> 83.453152 | R64: =R16*R$48 -> 95.97142 | S64: =S16*S$48 -> 58.484415 | T64: =T16*T$48 -> 106.30372 | U64: =U16*U$48 -> -32.669771 | V64: =V16*V$48 -> 88.240063 | W64: =W16*W$48 -> 123.7 | X64: =X16*X$48 -> 109.49612 | AA64: =((W64/T64)^(1/3))-1 -> 0.051817533
B66: Capital Expenditure | C66: =C18*C$48 -> 135.44238 | D66: =D18*D$48 -> 175.82912 | E66: =E18*E$48 -> 201.50953 | F66: =F18*F$48 -> 221.66868 | G66: =G18*G$48 -> 283.46801 | H66: =H18*H$48 -> 272.16086 | I66: =I18*I$48 -> 167.4 | J66: =J18*J$48 -> 101.74419 | M66: =((I66/F66)^(1/3))-1 -> -0.089352349 | P66: Capital Expenditure | Q66: =Q18*Q$48 -> 103.36392 | R66: =R18*R$48 -> 119.66807 | S66: =S18*S$48 -> 117.99288 | T66: =T18*T$48 -> 114.92295 | U66: =U18*U$48 -> 199.5386 | V66: =V18*V$48 -> 243.34136 | W66: =W18*W$48 -> 239.2 | X66: =X18*X$48 -> 219.67054 | AA66: =((W66/T66)^(1/3))-1 -> 0.27678609
B68: Opening Basic RAB | C68: =C20*C$48 -> 1634.2807 | D68: =D20*D$48 -> 1668.2439 | E68: =E20*E$48 -> 1769.8932 | F68: =F20*F$48 -> 1723.5127 | G68: =G20*G$48 -> 1837.6471 | H68: =H20*H$48 -> 2014.2209 | I68: =I20*I$48 -> 2201.1 | J68: =J20*J$48 -> 2280.1357 | M68: =((I68/F68)^(1/3))-1 -> 0.084946769 | P68: Opening Basic RAB | Q68: =Q20*Q$48 -> 1676.5603 | R68: =R20*R$48 -> 1678.6705 | S68: =S20*S$48 -> 1724.6076 | T68: =T20*T$48 -> 1723.5127 | U68: =U20*U$48 -> 1733.0378 | V68: =V20*V$48 -> 1828.309 | W68: =W20*W$48 -> 1985.5 | X68: =X20*X$48 -> 2132.655 | AA68: =((W68/T68)^(1/3))-1 -> 0.048298916
B70: Closing Basic RAB | C70: =C22*C$48 -> 1730.516 | D70: =D22*D$48 -> 1843.0067 | E70: =E22*E$48 -> 1774.672 | F70: =F22*F$48 -> 1846.0603 | G70: =G22*G$48 -> 2114.1852 | H70: =H22*H$48 -> 2306.7126 | I70: =I22*I$48 -> 2353.1 | J70: =J22*J$48 -> 2350.2907 | M70: =((I70/F70)^(1/3))-1 -> 0.084255164 | P70: Closing Basic RAB | Q70: =Q22*Q$48 -> 1741.3318 | R70: =R22*R$48 -> 1795.8504 | S70: =S22*S$48 -> 1774.672 | T70: =T22*T$48 -> 1740.9721 | U70: =U22*U$48 -> 1919.0465 | V70: =V22*V$48 -> 2080.7678 | W70: =W22*W$48 -> 2200.9 | X70: =X22*X$48 -> 2317.4419 | AA70: =((W70/T70)^(1/3))-1 -> 0.081275006
B72: Weighted average basic RAB | C72: =C24*C$48 -> 1681.4766 | D72: =D24*D$48 -> 1753.9073 | E72: =E24*E$48 -> 1772.2826 | F72: =F24*F$48 -> 1784.7312 | G72: =G24*G$48 -> 1975.9161 | H72: =H24*H$48 -> 2160.5192 | I72: =I24*I$48 -> 2277.1 | J72: =J24*J$48 -> 2315.2132 | M72: =((I72/F72)^(1/3))-1 -> 0.084600396 | P72: Weighted average basic RAB | Q72: =Q24*Q$48 -> 1708.393 | R72: =R24*R$48 -> 1736.1348 | S72: =S24*S$48 -> 1774.672 | T72: =T24*T$48 -> 1732.2424 | U72: =U24*U$48 -> 1826.0972 | V72: =V24*V$48 -> 1954.6956 | W72: =W24*W$48 -> 2093.2 | X72: =X24*X$48 -> 2225.0969 | AA72: =((W72/T72)^(1/3))-1 -> 0.065125267
B74: Return on weighted average basic RAB (pre-exceptional) (%) | C74: =C26 -> 8 | D74: =D26 -> 8.4 | E74: =E26 -> 8.1 | F74: =F26 -> 6.9 | G74: =G26 -> 7.2 | H74: =H26 -> 6 | I74: =I26 -> 6 | J74: =J26 -> 6.2 | M74: =((I74/F74)^(1/3))-1 -> -0.045518783 | P74: Return on weighted average basic RAB (pre-exceptional) (%) | Q74: 4.9 | R74: 1465.3 | S74: 3.3 | T74: 6.1 | U74: 5.4 | V74: 5.4 | W74: 5.9 | X74: 6.9
B76: Return on weighted average basic RAB (%) | C76: =C28 -> 8 | D76: =D28 -> 8.4 | E76: =E28 -> 8.1 | F76: =F28 -> 6.9 | G76: =G28 -> 7.2 | H76: =H28 -> 6 | I76: =I28 -> 6 | J76: =J28 -> 6.2 | M76: =((I76/F76)^(1/3))-1 -> -0.045518783 | P76: Return on weighted average basic RAB (%) | Q76: 4.9 | R76: 5.5 | S76: 3.3 | T76: 6.1 | U76: -1.8 | V76: 4.5 | W76: 5.9
B78: Breakdown of Operating Costs - CAA Projections | C78: Q4 | F78: Q5 | K78: Q5+1 | P78: Breakdown of Operating Costs | Q78: Q4 | T78: Q5 | Y78: Q5+1
B79: £m 2011/12 | C79: 2005/06 | D79: 2006/07 | E79: 2007/08 | F79: 2008/09 | G79: 2009/10 | H79: 2010/11 | I79: 2011/12 | J79: 2012/13 | K79: 2013/14 | M79: CAGR (Q5) | P79: £m 2011/12 | Q79: 2005/06 | R79: 2006/07 | S79: 2007/08 | T79: 2008/09 | U79: 2009/10 | V79: 2010/11 | W79: 2011/12 | X79: 2012/13 | Y79: 2013/14 | AA79: CAGR (Q5)
B80: Staff Costs | F80: =F32*F$48 -> 134.03994 | G80: =G32*G$48 -> 131.66908 | H80: =H32*H$48 -> 129.00655 | I80: =I32*I$48 -> 127.6 | J80: =J32*J$48 -> 124.22481 | M80: =((J80/F80)^(1/4))-1 -> -0.018831653 | P80: Staff Costs | T80: =T32*T$48 -> 111.93937 | U80: =U32*U$48 -> 125.06912 | V80: =V32*V$48 -> 134.66565 | W80: =W32*W$48 -> 140.5 | X80: =X32*X$48 -> 144.47674 | AA80: =((W80/T80)^(1/3))-1 -> 0.078692907
B81: Maintenance and equipment costs | F81: =F33*F$48 -> 28.399228 | G81: =G33*G$48 -> 28.269801 | H81: =H33*H$48 -> 30.496269 | I81: =I33*I$48 -> 31.5 | J81: =J33*J$48 -> 31.29845 | M81: =((J81/F81)^(1/4))-1 -> 0.024599343 | P81: Maintenance and equipment costs | T81: =T33*T$48 -> 33.371855 | U81: =U33*U$48 -> 29.149795 | V81: =V33*V$48 -> 26.828333 | W81: =W33*W$48 -> 35.2 | X81: =X33*X$48 -> 35.949612 | AA81: =((W81/T81)^(1/3))-1 -> 0.017936695
B82: Rent and rates | F82: =F34*F$48 -> 28.620234 | G82: =G34*G$48 -> 29.589792 | H82: =H34*H$48 -> 29.86748 | I82: =I34*I$48 -> 31.7 | J82: =J34*J$48 -> 32.848837 | M82: =((J82/F82)^(1/4))-1 -> 0.035050899 | P82: Rent and rates | T82: =T34*T$48 -> 27.404702 | U82: =U34*U$48 -> 27.499807 | V82: =V34*V$48 -> 23.579589 | W82: =W34*W$48 -> 26.8 | X82: =X34*X$48 -> 27.325581 | AA82: =((W82/T82)^(1/3))-1 -> -0.007409987
B83: Utility costs | F83: =F35*F$48 -> 29.393753 | G83: =G35*G$48 -> 29.699791 | H83: =H35*H$48 -> 30.181874 | I83: =I35*I$48 -> 30.8 | J83: =J35*J$48 -> 31.104651 | M83: =((J83/F83)^(1/4))-1 -> 0.014244292 | P83: Utility costs | T83: =T35*T$48 -> 28.951742 | U83: =U35*U$48 -> 34.869755 | V83: =V35*V$48 -> 29.553085 | W83: =W35*W$48 -> 30.2 | X83: =X35*X$48 -> 26.744186 | AA83: =((W83/T83)^(1/3))-1 -> 0.014169971
B84: Police costs | F84: =F36*F$48 -> 14.80738 | G84: =G36*G$48 -> 14.629897 | H84: =H36*H$48 -> 14.462148 | I84: =I36*I$48 -> 14.3 | J84: =J36*J$48 -> 14.050388 | M84: =((J84/F84)^(1/4))-1 -> -0.013033245 | P84: Police costs | T84: =T36*T$48 -> 15.249391 | U84: =U36*U$48 -> 14.519898 | V84: =V36*V$48 -> 13.938157 | W84: =W36*W$48 -> 12.7 | X84: =X36*X$48 -> 11.821705 | AA84: =((W84/T84)^(1/3))-1 -> -0.05915718
B85: Other costs | F85: =F37*F$48 -> 40.554539 | G85: =G37*G$48 -> 41.469709 | H85: =H37*H$48 -> 41.814472 | I85: =I37*I$48 -> 41.7 | J85: =J37*J$48 -> 42.344961 | M85: =((J85/F85)^(1/4))-1 -> 0.010858964 | P85: Other costs | T85: =T37*T$48 -> 57.682478 | U85: =U37*U$48 -> 65.009543 | V85: =V37*V$48 -> 53.97106 | W85: =W37*W$48 -> 35.5 | X85: =X37*X$48 -> 38.75969 | AA85: =((W85/T85)^(1/3))-1 -> -0.14939458
B86: Intergroup costs | F86: =F38*F$48 -> 39.0075 | G86: =G38*G$48 -> 38.059733 | H86: =H38*H$48 -> 37.727343 | I86: =I38*I$48 -> 37.2 | J86: =J38*J$48 -> 36.531008 | M86: =((J86/F86)^(1/4))-1 -> -0.016264408 | P86: Intergroup costs | T86: =T38*T$48 -> 45.63767 | U86: =U38*U$48 -> 25.409822 | V86: =V38*V$48 -> 0 | W86: =W38*W$48 -> 0 | X86: =X38*X$48 -> 0 | AA86: =((W86/T86)^(1/3))-1 -> -1
B88: Total operating costs | F88: =F40*F$48 -> 314.82257 | G88: =G40*G$48 -> 313.3878 | H88: =H40*H$48 -> 313.55614 | I88: =I40*I$48 -> 314.8 | J88: =J40*J$48 -> 312.4031 | M88: =((J88/F88)^(1/4))-1 -> -0.0019268573 | P88: Total operating costs | T88: =T40*T$48 -> 320.34771 | U88: =U40*U$48 -> 321.52774 | V88: =V40*V$48 -> 282.53588 | W88: =W40*W$48 -> 280.9 | X88: =X40*X$48 -> 285.07752 | AA88: =((W88/T88)^(1/3))-1 -> -0.042857271
B90: Exceptional operating costs | F90: =F42*F$48 -> 0 | G90: =G42*G$48 -> 0 | H90: =H42*H$48 -> 0 | I90: =I42*I$48 -> 0 | J90: =J42*J$48 -> 0 | P90: Exceptional operating costs | T90: =T42*T$48 -> -2.3205595 | U90: =U42*U$48 -> 0 | V90: =V42*V$48 -> 0 | W90: =W42*W$48 -> 0 | X90: =X42*X$48 -> 0
B91: Service Quality Rebates | F91: =F43*F$48 -> 0 | G91: =G43*G$48 -> 0 | H91: =H43*H$48 -> 0 | I91: =I43*I$48 -> 0 | J91: =J43*J$48 -> 0 | P91: Service Quality Rebates | T91: =T43*T$48 -> -6.1881586 | U91: =U43*U$48 -> -2.9699791 | V91: =V43*V$48 -> -1.6767708 | W91: =W43*W$48 -> 0 | X91: =X43*X$48 -> 0
B93: Adjusted operating costs | F93: =F45*F$48 -> 314.82257 | G93: =G45*G$48 -> 313.3878 | H93: =H45*H$48 -> 313.55614 | I93: =I45*I$48 -> 314.8 | J93: =J45*J$48 -> 312.0155 | M93: =((J93/F93)^(1/4))-1 -> -0.0022365775 | P93: Adjusted operating costs | T93: =T45*T$48 -> 311.83899 | U93: =U45*U$48 -> 318.55776 | V93: =V45*V$48 -> 280.85911 | W93: =W45*W$48 -> 280.9 | X93: =X45*X$48 -> 285.07752 | AA93: =((W93/T93)^(1/3))-1 -> -0.03422986
B96: End

Sheet STAL - Reg
B2: Stansted - CAA Allowance | M2: Stansted - Outturn
B4: Regulatory Accounts | C4: Q4 | F4: Q4+1 | G4: Q5 | M4: Regulatory Accounts | N4: Q4 | Q4: Q4+1 | R4: Q5
B5: £m nominal | C5: 2005/06 | D5: 2006/07 | E5: 2007/08 | F5: 2008/09 | G5: 2009/10 | H5: 2010/11 | I5: 2011/12 | J5: 2012/13 | K5: 2013/14 | M5: £m nominal | N5: 2005/06 | O5: 2006/07 | P5: 2007/08 | Q5: 2008/09 | R5: 2009/10 | S5: 2010/11 | T5: 2011/12 | U5: 2012/13 | V5: 2013/14 | X5: CAGR (4)
B6: Terminal Pax | C6: 22237 | D6: 21100 | E6: 22300 | M6: Terminal Pax | N6: 22237 | O6: 23845 | P6: 23541 | Q6: 21635 | R6: 19758 | S6: 18308 | T6: 17847 | X6: =((T6/Q6)^(1/3))-1 -> -0.062144115
B7: Net Revenue from Airport Charges | C7: 72.5 | D7: 100.7 | E7: 113.5 | M7: Net Revenue from Airport Charges | N7: 72.5 | O7: 80.7 | P7: 138.3 | Q7: 141.1 | R7: 132.9 | S7: 121.6 | T7: 127.6 | X7: =((T7/Q7)^(1/3))-1 -> -0.032967166
B8: Other Revenue | C8: 103.1 | D8: 121.8 | E8: 132.9 | M8: Other Revenue | N8: 103.1 | O8: 108.2 | P8: 112.1 | Q8: 107.7 | R8: 103.2 | S8: 97.5 | T8: 100.4 | X8: =((T8/Q8)^(1/3))-1 -> -0.023124233
B9: Total Revenue | C9: 175.6 | D9: 222.5 | E9: 246.4 | M9: Total Revenue | N9: 175.6 | O9: 118.9 | P9: 250.4 | Q9: 248.8 | R9: 236.1 | S9: 219.1 | T9: 228 | X9: =((T9/Q9)^(1/3))-1 -> -0.028681881
B10: Operating Costs | C10: 100.5 | D10: 108.1 | E10: 116.7 | M10: Operating Costs | N10: 100.5 | O10: 114.7 | P10: 141.3 | Q10: 145.2 | R10: 132.6 | S10: 133.4 | T10: 141.5 | X10: =((T10/Q10)^(1/3))-1 -> -0.0085672189
B11: Assumed Ordinary Depreciation | C11: 36.4 | D11: 40.5 | E11: 45.9 | M11: Assumed Ordinary Depreciation | N11: 36.4 | O11: 40.5 | P11: 45.9 | Q11: 41.7 | R11: 45.5 | S11: 46.8 | T11: 45 | X11: =((T11/Q11)^(1/3))-1 -> 0.025712118
B12: Total Expenditure | C12: 136.9 | D12: 148.6 | E12: 162.6 | M12: Total Expenditure | N12: 136.9 | O12: 155.2 | P12: 187.2 | Q12: 186.9 | R12: 178.1 | S12: 180.2 | T12: 186.5 | X12: =((T12/Q12)^(1/3))-1 -> -0.00071390351
B14: Regulatory Operating Profit (Before Exceptional) | C14: 38.7 | D14: 73.9 | E14: 83.8 | M14: Regulatory Operating Profit (Before Exceptional) | N14: 38.7 | O14: 33.7 | P14: 63.2 | Q14: 61.9 | R14: 58 | S14: 38.9 | T14: 41.5 | X14: =((T14/Q14)^(1/3))-1 -> -0.12477614
B15: Exceptional | C15: 0 | D15: 0 | E15: 0 | M15: Exceptional | N15: 0 | O15: 0 | P15: 0 | Q15: 0 | R15: 39 | S15: -25.1 | T15: 32.7
B16: Regulatory Operating Profit | C16: 38.7 | D16: 73.9 | E16: 83.8 | M16: Regulatory Operating Profit | N16: 38.7 | O16: 33.7 | P16: 63.2 | Q16: 63.2 | R16: 19 | S16: 64 | T16: 8.8 | X16: =((T16/Q16)^(1/3))-1 -> -0.48169126
B18: Capital Expenditure | C18: 65.9 | D18: 91.7 | E18: 99.1 | M18: Capital Expenditure | N18: 65.9 | O18: 111.4 | P18: 110.7 | Q18: 100.4 | R18: 27.9 | S18: 20.8 | T18: 19.2 | X18: =((T18/Q18)^(1/3))-1 -> -0.42386733
B20: Opening Basic RAB | C20: 862 | D20: 1024.1 | E20: 1125.7 | M20: Opening Basic RAB | N20: 862 | O20: 912.1 | P20: 1028.3 | Q20: 1132.9 | R20: 1229.8 | S20: 1293 | T20: 1348.9 | X20: =((T20/Q20)^(1/3))-1 -> 0.059894713
B22: Closing Basic RAB | C22: 912.1 | D22: 1125.7 | E22: 1222.2 | M22: Closing Basic RAB | N22: 912.1 | O22: 1028.3 | P22: 1132.9 | Q22: 1186.1 | R22: 1266.5 | S22: 1348.9 | T22: 1359.6 | X22: =((T22/Q22)^(1/3))-1 -> 0.046557955
B24: Weighted average basic RAB | C24: 886.6 | D24: 1074 | E24: 1173.1 | M24: Weighted average basic RAB | N24: 886.6 | O24: 969.1 | P24: 1079.7 | Q24: 1159 | R24: 1248.2 | S24: 1321 | T24: 1354.2 | X24: =((T24/Q24)^(1/3))-1 -> 0.053254018
B26: Return on weighted average basic RAB (pre-exceptional) (%) | C26: 4.4 | D26: 6.9 | E26: 7.1 | M26: Return on weighted average basic RAB (pre-exceptional) (%) | N26: 4.4 | O26: 3.5 | P26: 5.9 | Q26: 5.3 | R26: 4.6 | S26: 2.9 | T26: 3.1 | X26: =((T26/Q26)^(1/3))-1 -> -0.1637003
B28: Return on weighted average basic RAB (%) | C28: 4.4 | D28: 6.9 | E28: 7.1 | M28: Return on weighted average basic RAB (%) | N28: 4.4 | O28: 3.5 | P28: 5.9 | Q28: 5.3 | R28: 1.5 | S28: 4.8 | T28: 0.6 | X28: =((T28/Q28)^(1/3))-1 -> -0.51624538
B30: Opex per pax | C30: =(C10/C6)*1000 -> 4.5194945 | D30: =(D10/D6)*1000 -> 5.1232227 | E30: =(E10/E6)*1000 -> 5.2331839 | M30: Opex per pax | N30: =(N10/N6)*1000 -> 4.5194945 | O30: =(O10/O6)*1000 -> 4.8102328 | P30: =(P10/P6)*1000 -> 6.0022939 | Q30: =(Q10/Q6)*1000 -> 6.7113474 | R30: =(R10/R6)*1000 -> 6.7112056 | S30: =(S10/S6)*1000 -> 7.2864322 | T30: =(T10/T6)*1000 -> 7.9285034
B32: Breakdown of Operating Costs - CAA Projection | C32: Q4 | F32: Q4+1 | G32: Q5 | M32: Breakdown of Operating Costs | N32: Q4 | Q32: Q4+1 | R32: Q5
B33: £m nominal | C33: 2005/06 | D33: 2006/07 | E33: 2007/08 | F33: 2008/09 | G33: 2009/10 | H33: 2010/11 | I33: 2011/12 | J33: 2012/13 | K33: 2013/14 | M33: £m nominal | N33: 2005/06 | O33: 2006/07 | P33: 2007/08 | Q33: 2008/09 | R33: 2009/10 | S33: 2010/11 | T33: 2011/12 | U33: 2012/13 | V33: 2013/14 | X33: CAGR (4)
B34: Staff Costs | M34: Staff Costs | P34: 54.5 | Q34: 51.2 | R34: 47.3 | S34: 50.4 | T34: 57 | X34: =((T34/Q34)^(1/3))-1 -> 0.036418043
B35: Maintenance and equipment costs | M35: Maintenance and equipment costs | P35: 11.8 | Q35: 9.6 | R35: 9.7 | S35: 9.2 | T35: 10.4 | X35: =((T35/Q35)^(1/3))-1 -> 0.027040025
B36: Rent and rates | M36: Rent and rates | P36: 10.8 | Q36: 11.3 | R36: 12.3 | S36: 13.5 | T36: 15 | X36: =((T36/Q36)^(1/3))-1 -> 0.09901665
B37: Utility costs | M37: Utility costs | P37: 11.8 | Q37: 13 | R37: 23.4 | S37: 19.2 | T37: 20.5 | X37: =((T37/Q37)^(1/3))-1 -> 0.16395673
B38: Police costs | M38: Police costs | P38: 7.2 | Q38: 7 | R38: 6.3 | S38: 6.7 | T38: 6.9 | X38: =((T38/Q38)^(1/3))-1 -> -0.0047847622
B39: Other costs | M39: Other costs | P39: 7.7 | Q39: 25.3 | R39: 22.2 | S39: 24.3 | T39: 22.7 | X39: =((T39/Q39)^(1/3))-1 -> -0.035501007
B40: Intragroup costs | M40: Intragroup costs | P40: 28.4 | Q40: 25.9 | R40: 12 | S40: 10.4 | T40: 9.2 | X40: =((T40/Q40)^(1/3))-1 -> -0.29178897
B42: Total operating costs | M42: Total operating costs | P42: 132.2 | Q42: 138.3 | R42: 133.2 | S42: 133.7 | T42: 141.7 | X42: =((T42/Q42)^(1/3))-1 -> 0.0081284943
B44: Exceptional operating costs | M44: Exceptional operating costs | P44: 9.1 | Q44: 6.9 | R44: 0 | S44: 0 | T44: 0 | X44: =((T44/Q44)^(1/3))-1 -> -1
B45: Service Quality Rebates | M45: Service Quality Rebates | P45: 0 | Q45: 0 | R45: -0.6 | S45: -0.3 | T45: -0.2
B47: Adjusted operating costs | M47: Adjusted operating costs | P47: 141.3 | Q47: 145.2 | R47: 132.6 | S47: 133.4 | T47: 141.5 | X47: =((T47/Q47)^(1/3))-1 -> -0.0085672189
B50: Price Base Conversion to Real 2011/12 | C50: =RPI!$T$103/RPI!$T97 -> 1.2290597 | D50: =RPI!$T$103/RPI!$T98 -> 1.1848323 | E50: =RPI!$T$103/RPI!$T99 -> 1.1378291 | F50: =RPI!$T$103/RPI!$T100 -> 1.1050283 | G50: =RPI!$T$103/RPI!$T101 -> 1.0999923 | H50: =RPI!$T$103/RPI!$T102 -> 1.0479817 | I50: =RPI!$T$103/RPI!$Z103 -> 1 | J50: =RPI!$T$103/RPI!$Z104 -> 0.9699321 | K50: =RPI!$T$103/RPI!$Z105 -> 0.94328432 | M50: Price Base Conversion to Real 2011/12 | N50: =RPI!$T$103/RPI!$T97 -> 1.2290597 | O50: =RPI!$T$103/RPI!$T98 -> 1.1848323 | P50: =RPI!$T$103/RPI!$T99 -> 1.1378291 | Q50: =RPI!$T$103/RPI!$T100 -> 1.1050283 | R50: =RPI!$T$103/RPI!$T101 -> 1.0999923 | S50: =RPI!$T$103/RPI!$T102 -> 1.0479817 | T50: =RPI!$T$103/RPI!$T103 -> 1
B52: Stansted - CAA Allowance | M52: Stansted - Outturn
B54: Regulatory Accounts | C54: Q4 | F54: Q4+1 | G54: Q5 | M54: Regulatory Accounts | N54: Q4 | Q54: Q4+1 | R54: Q5
B55: £m 2011/12 | C55: 2005/06 | D55: 2006/07 | E55: 2007/08 | F55: 2008/09 | G55: 2009/10 | H55: 2010/11 | I55: 2011/12 | J55: 2012/13 | K55: 2013/14 | M55: £m 2011/12 | N55: 2005/06 | O55: 2006/07 | P55: 2007/08 | Q55: 2008/09 | R55: 2009/10 | S55: 2010/11 | T55: 2011/12 | U55: 2012/13 | V55: 2013/14 | X55: CAGR (6)
B56: =B6 -> Terminal Pax | C56: =C6 -> 22237 | D56: =D6 -> 21100 | E56: =E6 -> 22300 | M56: =M6 -> Terminal Pax | N56: 22237 | O56: 23845 | P56: 23541 | Q56: 21635 | R56: 19758 | S56: 18308 | T56: 17847 | X56: =((T56/N56)^(1/6))-1 -> -0.035990076
B57: =B7 -> Net Revenue from Airport Charges | C57: =C7*C$50 -> 89.106827 | D57: =D7*D$50 -> 119.31262 | E57: =E7*E$50 -> 129.1436 | M57: =M7 -> Net Revenue from Airport Charges | N57: =N7*N$50 -> 89.106827 | O57: =O7*O$50 -> 95.615971 | P57: =P7*P$50 -> 157.36176 | Q57: =Q7*Q$50 -> 155.9195 | R57: =R7*R$50 -> 146.18897 | S57: =S7*S$50 -> 127.43458 | T57: =T7*T$50 -> 127.6 | X57: =((T57/N57)^(1/6))-1 -> 0.061670987
B58: =B8 -> Other Revenue | C58: =C8*C$50 -> 126.71605 | D58: =D8*D$50 -> 144.31258 | E58: =E8*E$50 -> 151.21749 | M58: =M8 -> Other Revenue | N58: =N8*N$50 -> 126.71605 | O58: =O8*O$50 -> 128.19886 | P58: =P8*P$50 -> 127.55064 | Q58: =Q8*Q$50 -> 119.01155 | R58: =R8*R$50 -> 113.5192 | S58: =S8*S$50 -> 102.17822 | T58: =T8*T$50 -> 100.4 | X58: =((T58/N58)^(1/6))-1 -> -0.038054769
B59: =B9 -> Total Revenue | C59: =C9*C$50 -> 215.82288 | D59: =D9*D$50 -> 263.6252 | E59: =E9*E$50 -> 280.36109 | M59: =M9 -> Total Revenue | N59: =N9*N$50 -> 215.82288 | O59: =O9*O$50 -> 140.87657 | P59: =P9*P$50 -> 284.9124 | Q59: =Q9*Q$50 -> 274.93105 | R59: =R9*R$50 -> 259.70818 | S59: =S9*S$50 -> 229.6128 | T59: =T9*T$50 -> 228
B60: =B10 -> Operating Costs | C60: =C10*C$50 -> 123.5205 | D60: =D10*D$50 -> 128.08038 | E60: =E10*E$50 -> 132.78466 | M60: =M10 -> Operating Costs | N60: =N10*N$50 -> 123.5205 | O60: =O10*O$50 -> 135.90027 | P60: =P10*P$50 -> 160.77525 | Q60: =Q10*Q$50 -> 160.45011 | R60: =R10*R$50 -> 145.85898 | S60: =S10*S$50 -> 139.80077 | T60: =T10*T$50 -> 141.5 | X60: =((T60/N60)^(1/6))-1 -> 0.022907197
B61: =B11 -> Assumed Ordinary Depreciation | C61: =C11*C$50 -> 44.737772 | D61: =D11*D$50 -> 47.98571 | E61: =E11*E$50 -> 52.226355 | M61: =M11 -> Assumed Ordinary Depreciation | N61: =N11*N$50 -> 44.737772 | O61: =O11*O$50 -> 47.98571 | P61: =P11*P$50 -> 52.226355 | Q61: =Q11*Q$50 -> 46.079681 | R61: =R11*R$50 -> 50.049649 | S61: =S11*S$50 -> 49.045546 | T61: =T11*T$50 -> 45
B62: =B12 -> Total Expenditure | C62: =C12*C$50 -> 168.25827 | D62: =D12*D$50 -> 176.06609 | E62: =E12*E$50 -> 185.01101 | M62: =M12 -> Total Expenditure | N62: =N12*N$50 -> 168.25827 | O62: =O12*O$50 -> 183.88598 | P62: =P12*P$50 -> 213.00161 | Q62: =Q12*Q$50 -> 206.52979 | R62: =R12*R$50 -> 195.90862 | S62: =S12*S$50 -> 188.84631 | T62: =T12*T$50 -> 186.5 | X62: =((T62/N62)^(1/6))-1 -> 0.017303181
B64: =B14 -> Regulatory Operating Profit (Before Exceptional) | C64: =C14*C$50 -> 47.56461 | D64: =D14*D$50 -> 87.559111 | E64: =E14*E$50 -> 95.350078 | M64: =M14 -> Regulatory Operating Profit (Before Exceptional) | N64: =N14*N$50 -> 47.56461 | O64: =O14*O$50 -> 39.92885 | P64: =P14*P$50 -> 71.910799 | Q64: =Q14*Q$50 -> 68.401253 | R64: =R14*R$50 -> 63.799552 | S64: =S14*S$50 -> 40.76649 | T64: =T14*T$50 -> 41.5 | X64: =((T64/N64)^(1/6))-1 -> -0.022476155
B65: =B15 -> Exceptional | C65: =C15*C$50 -> 0 | D65: =D15*D$50 -> 0 | E65: =E15*E$50 -> 0 | M65: =M15 -> Exceptional | N65: =N15*N$50 -> 0 | O65: =O15*O$50 -> 0 | P65: =P15*P$50 -> 0 | Q65: =Q15*Q$50 -> 0 | R65: =R15*R$50 -> 42.899699 | S65: =S15*S$50 -> -26.304342 | T65: =T15*T$50 -> 32.7
B66: =B16 -> Regulatory Operating Profit | C66: =C16*C$50 -> 47.56461 | D66: =D16*D$50 -> 87.559111 | E66: =E16*E$50 -> 95.350078 | M66: =M16 -> Regulatory Operating Profit | N66: =N16*N$50 -> 47.56461 | O66: =O16*O$50 -> 39.92885 | P66: =P16*P$50 -> 71.910799 | Q66: =Q16*Q$50 -> 69.83779 | R66: =R16*R$50 -> 20.899853 | S66: =S16*S$50 -> 67.070832 | T66: =T16*T$50 -> 8.8 | X66: =((T66/N66)^(1/6))-1 -> -0.24513993
B68: =B18 -> Capital Expenditure | C68: =C18*C$50 -> 80.995033 | D68: =D18*D$50 -> 108.64913 | E68: =E18*E$50 -> 112.75886 | M68: =M18 -> Capital Expenditure | N68: =N18*N$50 -> 80.995033 | O68: =O18*O$50 -> 131.99032 | P68: =P18*P$50 -> 125.95768 | Q68: =Q18*Q$50 -> 110.94484 | R68: =R18*R$50 -> 30.689784 | S68: =S18*S$50 -> 21.79802 | T68: =T18*T$50 -> 19.2 | X68: =((T68/N68)^(1/6))-1 -> -0.21330364
B70: =B20 -> Opening Basic RAB | C70: =C20*C$50 -> 1059.4494 | D70: =D20*D$50 -> 1213.3868 | E70: =E20*E$50 -> 1280.8542 | M70: =M20 -> Opening Basic RAB | N70: =N20*N$50 -> 1059.4494 | O70: =O20*O$50 -> 1080.6856 | P70: =P20*P$50 -> 1170.0297 | Q70: =Q20*Q$50 -> 1251.8866 | R70: =R20*R$50 -> 1352.7705 | S70: =S20*S$50 -> 1355.0404 | T70: =T20*T$50 -> 1348.9 | X70: =((T70/N70)^(1/6))-1 -> 0.041077961
B72: =B22 -> Closing Basic RAB | C72: =C22*C$50 -> 1121.0253 | D72: =D22*D$50 -> 1333.7658 | E72: =E22*E$50 -> 1390.6547 | M72: =M22 -> Closing Basic RAB | N72: =N22*N$50 -> 1121.0253 | O72: =O22*O$50 -> 1218.3631 | P72: =P22*P$50 -> 1289.0466 | Q72: =Q22*Q$50 -> 1310.6741 | R72: =R22*R$50 -> 1393.1402 | S72: =S22*S$50 -> 1413.6226 | T72: =T22*T$50 -> 1359.6 | X72: =((T72/N72)^(1/6))-1 -> 0.032680448
B74: =B24 -> Weighted average basic RAB | C74: =C24*C$50 -> 1089.6843 | D74: =D24*D$50 -> 1272.5099 | E74: =E24*E$50 -> 1334.7873 | M74: =M24 -> Weighted average basic RAB | N74: =N24*N$50 -> 1089.6843 | O74: =O24*O$50 -> 1148.221 | P74: =P24*P$50 -> 1228.5141 | Q74: =Q24*Q$50 -> 1280.7278 | R74: =R24*R$50 -> 1373.0104 | S74: =S24*S$50 -> 1384.3839 | T74: =T24*T$50 -> 1354.2 | X74: =((T74/N74)^(1/6))-1 -> 0.036884427
B76: =B26 -> Return on weighted average basic RAB (pre-exceptional) (%) | C76: =C26 -> 4.4 | D76: =D26 -> 6.9 | E76: =E26 -> 7.1 | M76: =M26 -> Return on weighted average basic RAB (pre-exceptional) (%) | N76: =N26 -> 4.4 | O76: =O26 -> 3.5 | P76: =P26 -> 5.9 | Q76: =Q26 -> 5.3 | R76: =R26 -> 4.6 | S76: =S26 -> 2.9 | T76: =T26 -> 3.1
B78: =B28 -> Return on weighted average basic RAB (%) | C78: =C28 -> 4.4 | D78: =D28 -> 6.9 | E78: =E28 -> 7.1 | M78: =M28 -> Return on weighted average basic RAB (%) | N78: =N28 -> 4.4 | O78: =O28 -> 3.5 | P78: =P28 -> 5.9 | Q78: =Q28 -> 5.3 | R78: =R28 -> 1.5 | S78: =S28 -> 4.8 | T78: =T28 -> 0.6
B80: =B30 -> Opex per pax | C80: =(C60/C56)*1000 -> 5.5547285 | D80: =(D60/D56)*1000 -> 6.07016 | E80: =(E60/E56)*1000 -> 5.9544688 | M80: =M30 -> Opex per pax | N80: =(N60/N56)*1000 -> 5.5547285 | O80: =(O60/O56)*1000 -> 5.6993194 | P80: =(P60/P56)*1000 -> 6.8295846 | Q80: =(Q60/Q56)*1000 -> 7.4162289 | R80: =(R60/R56)*1000 -> 7.3822743 | S80: =(S60/S56)*1000 -> 7.6360479 | T80: =(T60/T56)*1000 -> 7.9285034
B82: Breakdown of Operating Costs - CAA Projection | C82: Q4 | F82: Q4+1 | G82: Q5 | M82: Breakdown of Operating Costs | N82: Q4 | Q82: Q4+1 | R82: Q5
B83: £m 2011/12 | C83: 2005/06 | D83: 2006/07 | E83: 2007/08 | F83: 2008/09 | G83: 2009/10 | H83: 2010/11 | I83: 2011/12 | J83: 2012/13 | K83: 2013/14 | M83: £m 2011/12 | N83: 2005/06 | O83: 2006/07 | P83: 2007/08 | Q83: 2008/09 | R83: 2009/10 | S83: 2010/11 | T83: 2011/12 | U83: 2012/13 | V83: 2013/14 | X83: CAGR (4)
B84: Staff Costs | M84: Staff Costs | P84: =P34*P$50 -> 62.011686 | Q84: =Q34*Q$50 -> 56.57745 | R84: =R34*R$50 -> 52.029635 | S84: =S34*S$50 -> 52.81828 | T84: =T34*T$50 -> 57 | X84: =((T84/P84)^(1/4))-1 -> -0.020847516
B85: Maintenance and equipment costs | M85: Maintenance and equipment costs | P85: =P35*P$50 -> 13.426383 | Q85: =Q35*Q$50 -> 10.608272 | R85: =R35*R$50 -> 10.669925 | S85: =S35*S$50 -> 9.6414321 | T85: =T35*T$50 -> 10.4 | X85: =((T85/P85)^(1/4))-1 -> -0.061858011
B86: Rent and rates | M86: Rent and rates | P86: =P36*P$50 -> 12.288554 | Q86: =Q36*Q$50 -> 12.48682 | R86: =R36*R$50 -> 13.529905 | S86: =S36*S$50 -> 14.147754 | T86: =T36*T$50 -> 15 | X86: =((T86/P86)^(1/4))-1 -> 0.051108668
B87: Utility costs | M87: Utility costs | P87: =P37*P$50 -> 13.426383 | Q87: =Q37*Q$50 -> 14.365368 | R87: =R37*R$50 -> 25.739819 | S87: =S37*S$50 -> 20.12125 | T87: =T37*T$50 -> 20.5 | X87: =((T87/P87)^(1/4))-1 -> 0.11160043
B88: Police costs | M88: Police costs | P88: =P38*P$50 -> 8.1923695 | Q88: =Q38*Q$50 -> 7.7351983 | R88: =R38*R$50 -> 6.9299513 | S88: =S38*S$50 -> 7.0214777 | T88: =T38*T$50 -> 6.9 | X88: =((T88/P88)^(1/4))-1 -> -0.042012395
B89: Other costs | M89: Other costs | P89: =P39*P$50 -> 8.761284 | Q89: =Q39*Q$50 -> 27.957217 | R89: =R39*R$50 -> 24.419829 | S89: =S39*S$50 -> 25.465957 | T89: =T39*T$50 -> 22.7 | X89: =((T89/P89)^(1/4))-1 -> 0.26871631
B90: Intragroup costs | M90: Intragroup costs | P90: =P40*P$50 -> 32.314346 | Q90: =Q40*Q$50 -> 28.620234 | R90: =R40*R$50 -> 13.199907 | S90: =S40*S$50 -> 10.89901 | T90: =T40*T$50 -> 9.2 | X90: =((T90/P90)^(1/4))-1 -> -0.26953718
B92: Total operating costs | M92: Total operating costs | P92: =P42*P$50 -> 150.42101 | Q92: =Q42*Q$50 -> 152.82542 | R92: =R42*R$50 -> 146.51897 | S92: =S42*S$50 -> 140.11516 | T92: =T42*T$50 -> 141.7 | X92: =((T92/P92)^(1/4))-1 -> -0.014820559
B94: Exceptional operating costs | M94: Exceptional operating costs | P94: =P44*P$50 -> 10.354245 | Q94: =Q44*Q$50 -> 7.6246954 | R94: =R44*R$50 -> 0 | S94: =S44*S$50 -> 0 | T94: =T44*T$50 -> 0 | X94: =((T94/P94)^(1/4))-1 -> -1
B95: Service Quality Rebates | M95: Service Quality Rebates | P95: =P45*P$50 -> 0 | Q95: =Q45*Q$50 -> 0 | R95: =R45*R$50 -> -0.65999537 | S95: =S45*S$50 -> -0.31439452 | T95: =T45*T$50 -> -0.2
B97: Adjusted operating costs | M97: Adjusted operating costs | P97: =P47*P$50 -> 160.77525 | Q97: =Q47*Q$50 -> 160.45011 | R97: =R47*R$50 -> 145.85898 | S97: =S47*S$50 -> 139.80077 | T97: =T47*T$50 -> 141.5 | X97: =((T97/P97)^(1/4))-1 -> -0.031422645
B100: End

Sheet HAL>>

Sheet HAL - iBP 
B2: Heathrow - Initial Business Plan - July 2012
B4: July 2012 IBP Forecast | C4: Q5 | H4: Q5+1 | I4: Q6 | P4: July 2012 IBP Forecast - Summary | U4: July 2012 IBP Forecast - Summary
B5: £m nominal | C5: 2008/09 | D5: 2009/10 | E5: 2010/11 | F5: 2011/12 | G5: 2012/13 | H5: 2013/14 | I5: 2014/15 | J5: 2015/16 | K5: 2016/17 | L5: 2017/18 | M5: 2018/19 | P5: £m nominal | Q5: Total Q5+1 | R5: % of Total | S5: CAGR (Q5+1) | U5: £m nominal | V5: Total Q6 | W5: % of Total | X5: CAGR (Q6)
B6: Security Costs | C6: =C31*C$27 -> 158.88744 | D6: =D31*D$27 -> 152.56006 | E6: =E31*E$27 -> 154.57781 | F6: =F31*F$27 -> 162.96475 | G6: =G31*G$27 -> 161 | H6: =H31*H$27 -> 182.98556 | I6: =I31*I$27 -> 189.17557 | J6: =J31*J$27 -> 193.38711 | ... M6: =M31*M$27 -> 200.63463 | P6: Security Costs | Q6: =SUM(C6:H6) -> 972.97562 | R6: =Q6/$Q$17 -> 0.16363464 | S6: =((H6/C6)^(1/5))-1 -> 0.028644845 | U6: Security Costs | V6: =SUM(I6:M6) -> 967.10561 | W6: =V6/$V$17 -> 0.15496107 | X6: =((M6/H6)^(1/5))-1 -> 0.018586266
B7: Staff Costs - Other Operational | C7: =C32*C$27 -> 56.181193 | D7: =D32*D$27 -> 47.619904 | E7: =E32*E$27 -> 51.834474 | F7: =F32*F$27 -> 53.351555 | G7: =G32*G$27 -> 57 | H7: =H32*H$27 -> 57.24688 | I7: =I32*I$27 -> 63.058523 | J7: =J32*J$27 -> 66.273111 | ... M7: =M32*M$27 -> 68.856857 | P7: Staff Costs - Other Operational | Q7: =SUM(C7:H7) -> 323.23401 | R7: =Q7/$Q$17 -> 0.054361363 | S7: =((H7/C7)^(1/5))-1 -> 0.0037652885 | U7: Staff Costs - Other Operational | V7: =SUM(I7:M7) -> 329.944 | W7: =V7/$V$17 -> 0.052867519 | X7: =((M7/H7)^(1/5))-1 -> 0.037621769
B8: Facilities Management | C8: =C33*C$27 -> 156.25394 | D8: =D33*D$27 -> 161.37856 | E8: =E33*E$27 -> 153.65219 | F8: =F33*F$27 -> 163.93478 | G8: =G33*G$27 -> 175 | H8: =H33*H$27 -> 196.27502 | I8: =I33*I$27 -> 232.26556 | J8: =J33*J$27 -> 233.58556 | ... M8: =M33*M$27 -> 244.56056 | P8: Facilities Management | Q8: =SUM(C8:H8) -> 1006.4945 | R8: =Q8/$Q$17 -> 0.16927183 | S8: =((H8/C8)^(1/5))-1 -> 0.046662846 | U8: Facilities Management | V8: =SUM(I8:M8) -> 1185.1523 | W8: =V8/$V$17 -> 0.18989908 | X8: =((M8/H8)^(1/5))-1 -> 0.0449711
B9: Utilities | C9: =C34*C$27 -> 81.638296 | D9: =D34*D$27 -> 105.82201 | E9: =E34*E$27 -> 87.933483 | F9: =F34*F$27 -> 84.392459 | G9: =G34*G$27 -> 92 | H9: =H34*H$27 -> 95.070711 | I9: =I34*I$27 -> 107.19949 | J9: =J34*J$27 -> 109.73089 | ... M9: =M34*M$27 -> 116.34434 | P9: Utilities | Q9: =SUM(C9:H9) -> 546.85696 | R9: =Q9/$Q$17 -> 0.09197018 | S9: =((H9/C9)^(1/5))-1 -> 0.030933287 | U9: Utilities | V9: =SUM(I9:M9) -> 555.92967 | W9: =V9/$V$17 -> 0.089077609 | X9: =((M9/H9)^(1/5))-1 -> 0.041213299
B10: Rent and Rates | C10: =C35*C$27 -> 103.58407 | D10: =D35*D$27 -> 110.23126 | E10: =E35*E$27 -> 103.66895 | F10: =F35*F$27 -> 116.40339 | G10: =G35*G$27 -> 126 | H10: =H35*H$27 -> 132.89454 | I10: =I35*I$27 -> 161.85021 | J10: =J35*J$27 -> 181.43622 | ... M10: =M35*M$27 -> 198.26026 | P10: Rent and Rates | Q10: =SUM(C10:H10) -> 692.78222 | R10: =Q10/$Q$17 -> 0.11651183 | S10: =((H10/C10)^(1/5))-1 -> 0.051097085 | U10: Rent and Rates | V10: =SUM(I10:M10) -> 920.91169 | W10: =V10/$V$17 -> 0.14755933 | X10: =((M10/H10)^(1/5))-1 -> 0.083292422
B11: Central Support Services | C11: =C36*C$27 -> 107.97323 | D11: =D36*D$27 -> 97.003508 | E11: =E36*E$27 -> 115.70195 | F11: =F36*F$27 -> 119.31348 | G11: =G36*G$27 -> 143 | H11: =H36*H$27 -> 113.47149 | I11: =I36*I$27 -> 117.70924 | J11: =J36*J$27 -> 120.59533 | ... M11: =M36*M$27 -> 125.84184 | P11: Central Support Services | Q11: =SUM(C11:H11) -> 696.46366 | R11: =Q11/$Q$17 -> 0.11713097 | S11: =((H11/C11)^(1/5))-1 -> 0.0099831679 | U11: Central Support Services | V11: =SUM(I11:M11) -> 608.33165 | W11: =V11/$V$17 -> 0.097474073 | X11: =((M11/H11)^(1/5))-1 -> 0.020910472
B12: Rail | C12: =C37*C$27 -> 64.081673 | D12: =D37*D$27 -> 67.902456 | E12: =E37*E$27 -> 69.421171 | F12: =F37*F$27 -> 64.021866 | G12: =G37*G$27 -> 66 | H12: =H37*H$27 -> 68.491803 | I12: =I37*I$27 -> 63.058523 | J12: =J37*J$27 -> 64.100223 | ... M12: =M37*M$27 -> 71.231231 | P12: Rail | Q12: =SUM(C12:H12) -> 399.91897 | R12: =Q12/$Q$17 -> 0.067258209 | S12: =((H12/C12)^(1/5))-1 -> 0.013400119 | U12: Rail | V12: =SUM(I12:M12) -> 333.56974 | W12: =V12/$V$17 -> 0.053448478 | X12: =((M12/H12)^(1/5))-1 -> 0.0078742991
B13: Commercial Expenditure | C13: =C38*C$27 -> 36.868908 | D13: =D38*D$27 -> 49.383604 | E13: =E38*E$27 -> 41.652703 | F13: =F38*F$27 -> 42.681244 | G13: =G38*G$27 -> 46 | H13: =H38*H$27 -> 49.068754 | I13: =I38*I$27 -> 53.599745 | J13: =J38*J$27 -> 56.495111 | ... M13: =M38*M$27 -> 60.546546 | P13: Commercial Expenditure | Q13: =SUM(C13:H13) -> 265.65521 | R13: =Q13/$Q$17 -> 0.044677785 | S13: =((H13/C13)^(1/5))-1 -> 0.058836617 | U13: Commercial Expenditure | V13: =SUM(I13:M13) -> 285.37635 | W13: =V13/$V$17 -> 0.045726364 | X13: =((M13/H13)^(1/5))-1 -> 0.042934104
B14: Other | C14: =C39*C$27 -> 139.57515 | D14: =D39*D$27 -> 134.92306 | E14: =E39*E$27 -> 135.13988 | F14: =F39*F$27 -> 151.32441 | G14: =G39*G$27 -> 166 | H14: =H39*H$27 -> 128.80548 | I14: =I39*I$27 -> 122.96412 | J14: =J39*J$27 -> 122.76822 | ... M14: =M39*M$27 -> 132.96496 | P14: Other | Q14: =SUM(C14:H14) -> 855.76798 | R14: =Q14/$Q$17 -> 0.14392271 | S14: =((H14/C14)^(1/5))-1 -> -0.015931689 | U14: Other | V14: =SUM(I14:M14) -> 637.66503 | W14: =V14/$V$17 -> 0.10217421 | X14: =((M14/H14)^(1/5))-1 -> 0.006376708
B15: Pensions | C15: =C40*C$27 -> 30.72409 | D15: =D40*D$27 -> 22.928102 | E15: =E40*E$27 -> 30.545315 | F15: =F40*F$27 -> 34.921018 | G15: =G40*G$27 -> 32 | H15: =H40*H$27 -> 34.757034 | I15: =I40*I$27 -> 81.97608 | J15: =J40*J$27 -> 82.569778 | ... M15: =M40*M$27 -> 85.477477 | P15: Pensions | Q15: =SUM(C15:H15) -> 185.87556 | R15: =Q15/$Q$17 -> 0.031260476 | S15: =((H15/C15)^(1/5))-1 -> 0.024973736 | U15: Pensions | V15: =SUM(I15:M15) -> 416.97258 | W15: =V15/$V$17 -> 0.066812266 | X15: =((M15/H15)^(1/5))-1 -> 0.19718646
B17: Total | C17: =C42*C$27 -> 935.76799 | D17: =D42*D$27 -> 949.75253 | E17: =E42*E$27 -> 944.12792 | F17: =F42*F$27 -> 993.30895 | G17: =G42*G$27 -> 1064 | H17: =H42*H$27 -> 1059.0673 | I17: =I42*I$27 -> 1192.8571 | J17: =J42*J$27 -> 1230.9416 | ... M17: =M42*M$27 -> 1304.7187 | P17: Total | Q17: =SUM(C17:H17) -> 5946.0247 | R17: =Q17/$Q$17 -> 1 | S17: =((H17/C17)^(1/5))-1 -> 0.025064215 | U17: Total | V17: =SUM(I17:M17) -> 6240.9586 | W17: =V17/$V$17 -> 1 | X17: =((M17/H17)^(1/5))-1 -> 0.042602276
B18: Impact of T1 Closure | I18: =I43*I$27 -> 0 | J18: =J43*J$27 -> 0 | K18: =K43*K$27 -> -34.690171 | L18: =L43*L$27 -> -36.883485 | M18: =M43*M$27 -> -37.98999 | U18: Impact of T1 Closure | V18: =SUM(I18:M18) -> -109.56365
B19: SQR at 5 mins queuing in transfers | I19: =I44*I$27 -> 5.2548769 | J19: =J44*J$27 -> 5.4322223 | K19: =K44*K$27 -> 5.5951889 | L19: =L44*L$27 -> 5.7630446 | M19: =M44*M$27 -> 5.9359359 | U19: SQR at 5 mins queuing in transfers | V19: =SUM(I19:M19) -> 27.981269
B20: Increase opex saving by 0.2% | I20: =I45*I$27 -> -3.1529261 | J20: =J45*J$27 -> -5.4322223 | K20: =K45*K$27 -> -8.9523023 | L20: =L45*L$27 -> -12.678698 | M20: =M45*M$27 -> -16.620621 | U20: Increase opex saving by 0.2% | V20: =SUM(I20:M20) -> -46.836769
B21: Total Q6 after Adjustments | C21: =C46*C$27 -> 935.76799 | D21: =D46*D$27 -> 949.75253 | E21: =E46*E$27 -> 944.12792 | F21: =F46*F$27 -> 993.30895 | G21: =G46*G$27 -> 1064 | H21: =H46*H$27 -> 1059.0673 | I21: =I46*I$27 -> 1194.959 | J21: =J46*J$27 -> 1230.9416 | ... M21: =M46*M$27 -> 1256.044 | U21: Total Q6 after Adjustments | V21: =SUM(I21:M21) -> 6112.5394 | X21: =((M21/H21)^(1/5))-1 -> 0.034704323
B23: Passengers (m) | C23: 65.9 | D23: 66.1 | E23: 66.1 | F23: 70.1 | G23: 69.2 | H23: 69.1 | I23: =I48 -> 69.2 | J23: =J48 -> 70.1 | K23: =K48 -> 71.1 | L23: =L48 -> 71.8 | M23: =M48 -> 72.6 | P23: Passengers (m) | Q23: =SUM(C23:H23) -> 406.5 | S23: =((H23/C23)^(1/5))-1 -> 0.0095283664 | U23: Passengers (m) | V23: =V48 -> 354.8 | X23: =((M23/H23)^(1/5))-1 -> 0.0099310268
B24: Total opex / passenger | C24: =C21/C23 -> 14.199818 | D24: =D17/D23 -> 14.368419 | E24: =E17/E23 -> 14.283327 | F24: =F17/F23 -> 14.169885 | G24: =G17/G23 -> 15.375723 | H24: =H17/H23 -> 15.326589 | I24: =I21/I23 -> 17.268194 | J24: =J21/J23 -> 17.559794 | K24: =K21/K23 -> 16.872131 | L24: =L21/L23 -> 17.144656 | M24: =M21/M23 -> 17.300882 | P24: Total opex / passenger | Q24: =Q17/Q23 -> 14.627367 | S24: =((H24/C24)^(1/5))-1 -> 0.015389215 | U24: Total opex / passenger | V24: =V21/V23 -> 17.228127 | X24: =((M24/H24)^(1/5))-1 -> 0.024529691
B27: Price Base Conversion 2012/13 to Nominal | C27: =RPI!$T100/RPI!$V$104 -> 0.87783114 | D27: =RPI!$T101/RPI!$V$104 -> 0.88185007 | E27: =RPI!$T102/RPI!$V$104 -> 0.92561561 | F27: =RPI!$T103/RPI!$V$104 -> 0.97002827 | G27: =RPI!$V104/RPI!$V$104 -> 1 | H27: =RPI!$V105/RPI!$V$104 -> 1.0222657 | I27: =RPI!$V106/RPI!$V$104 -> 1.0509754 | J27: =RPI!$V107/RPI!$V$104 -> 1.0864445 | K27: =RPI!$V108/RPI!$V$104 -> 1.1190378 | L27: =RPI!$V109/RPI!$V$104 -> 1.1526089 | M27: =RPI!$V110/RPI!$V$104 -> 1.1871872
B29: July 2012 IBP Forecast | C29: Q5 | H29: Q5+1 | I29: Q6 | P29: July 2012 IBP Forecast - Summary | U29: July 2012 IBP Forecast - Summary
B30: £m 2012/13 prices | C30: 2008/09 | D30: 2009/10 | E30: 2010/11 | F30: 2011/12 | G30: 2012/13 | H30: 2013/14 | I30: 2014/15 | J30: 2015/16 | K30: 2016/17 | L30: 2017/18 | M30: 2018/19 | P30: £m 2012/13 prices | Q30: Total Q5+1 | R30: % of Total | S30: CAGR (Q5+1) | U30: £m 2012/13 prices | V30: Total Q6 | W30: % of Total | X30: CAGR (Q6)
B31: Security Costs | C31: 181 | D31: 173 | E31: 167 | F31: 168 | G31: 161 | H31: 179 | I31: 180 | J31: 178 | K31: 169 | L31: 169 | M31: 169 | P31: Security Costs | Q31: =SUM(C31:G31) -> 850 | R31: =Q31/$Q$42 -> 0.16187393 | S31: =((H31/C31)^(1/5))-1 -> -0.0022197777 | U31: Security Costs | V31: =SUM(I31:M31) -> 865 | W31: =V31/$V$42 -> 0.15504571 | X31: =((M31/H31)^(1/5))-1 -> -0.011431575
B32: Staff Costs - Other Operational | C32: 64 | D32: 54 | E32: 56 | F32: 55 | G32: 57 | H32: 56 | I32: 60 | J32: 61 | K32: 58 | L32: 58 | M32: 58 | P32: Staff Costs - Other Operational | Q32: =SUM(C32:G32) -> 286 | R32: =Q32/$Q$42 -> 0.054465816 | S32: =((H32/C32)^(1/5))-1 -> -0.026352819 | U32: Staff Costs - Other Operational | V32: =SUM(I32:M32) -> 295 | W32: =V32/$V$42 -> 0.05287686 | X32: =((M32/H32)^(1/5))-1 -> 0.0070429497
B33: Facilities Management | C33: 178 | D33: 183 | E33: 166 | F33: 169 | G33: 175 | H33: 192 | I33: 221 | J33: 215 | K33: 210 | L33: 208 | M33: 206 | P33: Facilities Management | Q33: =SUM(C33:G33) -> 871 | R33: =Q33/$Q$42 -> 0.16587317 | S33: =((H33/C33)^(1/5))-1 -> 0.015257591 | U33: Facilities Management | V33: =SUM(I33:M33) -> 1060 | W33: =V33/$V$42 -> 0.18999821 | X33: =((M33/H33)^(1/5))-1 -> 0.014175695
B34: Utilities | C34: 93 | D34: 120 | E34: 95 | F34: 87 | G34: 92 | H34: 93 | I34: 102 | J34: 101 | K34: 97 | L34: 99 | M34: 98 | P34: Utilities | Q34: =SUM(C34:G34) -> 487 | R34: =Q34/$Q$42 -> 0.092744239 | S34: =((H34/C34)^(1/5))-1 -> 0 | U34: Utilities | V34: =SUM(I34:M34) -> 497 | W34: =V34/$V$42 -> 0.089084065 | X34: =((M34/H34)^(1/5))-1 -> 0.010528637
B35: Rent and Rates | C35: 118 | D35: 125 | E35: 112 | F35: 120 | G35: 126 | H35: 130 | I35: 154 | J35: 167 | K35: 167 | L35: 167 | M35: 167 | P35: Rent and Rates | Q35: =SUM(C35:G35) -> 601 | R35: =Q35/$Q$42 -> 0.11445439 | S35: =((H35/C35)^(1/5))-1 -> 0.01955878 | U35: Rent and Rates | V35: =SUM(I35:M35) -> 822 | W35: =V35/$V$42 -> 0.14733823 | X35: =((M35/H35)^(1/5))-1 -> 0.051367684
B36: Central Support Services | C36: 123 | D36: 110 | E36: 125 | F36: 123 | G36: 143 | H36: 111 | I36: 112 | J36: 111 | K36: 108 | L36: 107 | M36: 106 | P36: Central Support Services | Q36: =SUM(C36:G36) -> 624 | R36: =Q36/$Q$42 -> 0.11883451 | S36: =((H36/C36)^(1/5))-1 -> -0.020321508 | U36: Central Support Services | V36: =SUM(I36:M36) -> 544 | W36: =V36/$V$42 -> 0.097508514 | X36: =((M36/H36)^(1/5))-1 -> -0.0091758639
B37: Rail | C37: 73 | D37: 77 | E37: 75 | F37: 66 | G37: 66 | H37: 67 | I37: 60 | J37: 59 | K37: 59 | L37: 60 | M37: 60 | P37: Rail | Q37: =SUM(C37:G37) -> 357 | R37: =Q37/$Q$42 -> 0.06798705 | S37: =((H37/C37)^(1/5))-1 -> -0.017007083 | U37: Rail | V37: =SUM(I37:M37) -> 298 | W37: =V37/$V$42 -> 0.05341459 | X37: =((M37/H37)^(1/5))-1 -> -0.021827859
B38: Commercial Expenditure | C38: 42 | D38: 56 | E38: 45 | F38: 44 | G38: 46 | H38: 48 | I38: 51 | J38: 52 | K38: 50 | L38: 51 | M38: 51 | P38: Commercial Expenditure | Q38: =SUM(C38:G38) -> 233 | R38: =Q38/$Q$42 -> 0.0443725 | S38: =((H38/C38)^(1/5))-1 -> 0.027066087 | U38: Commercial Expenditure | V38: =SUM(I38:M38) -> 255 | W38: =V38/$V$42 -> 0.045707116 | X38: =((M38/H38)^(1/5))-1 -> 0.012198729
B39: Other | C39: 159 | D39: 153 | E39: 146 | F39: 156 | G39: 166 | H39: 126 | I39: 117 | J39: 113 | K39: 114 | L39: 114 | M39: 112 | P39: Other | Q39: =SUM(C39:G39) -> 780 | R39: =Q39/$Q$42 -> 0.14854313 | S39: =((H39/C39)^(1/5))-1 -> -0.045458787 | U39: Other | V39: =SUM(I39:M39) -> 570 | W39: =V39/$V$42 -> 0.10216885 | X39: =((M39/H39)^(1/5))-1 -> -0.023281316
B40: Pensions | C40: 35 | D40: 26 | E40: 33 | F40: 36 | G40: 32 | H40: 34 | I40: 78 | J40: 76 | K40: 74 | L40: 73 | M40: 72 | P40: Pensions | Q40: =SUM(C40:G40) -> 162 | R40: =Q40/$Q$42 -> 0.030851266 | S40: =((H40/C40)^(1/5))-1 -> -0.0057807343 | U40: Pensions | V40: =SUM(I40:M40) -> 373 | W40: =V40/$V$42 -> 0.06685786 | X40: =((M40/H40)^(1/5))-1 -> 0.16190525
B42: Total | C42: =SUM(C31:C41) -> 1066 | D42: =SUM(D31:D41) -> 1077 | E42: =SUM(E31:E41) -> 1020 | F42: =SUM(F31:F41) -> 1024 | G42: =SUM(G31:G41) -> 1064 | H42: =SUM(H31:H41) -> 1036 | I42: =SUM(I31:I41) -> 1135 | J42: =SUM(J31:J41) -> 1133 | ... M42: =SUM(M31:M41) -> 1099 | P42: Total | Q42: =SUM(C42:G42) -> 5251 | R42: =Q42/$Q$42 -> 1 | S42: =((H42/C42)^(1/5))-1 -> -0.0056929697 | U42: Total | V42: =SUM(I42:M42) -> 5579 | W42: =V42/$V$42 -> 1 | X42: =((M42/H42)^(1/5))-1 -> 0.011876681
B43: Impact of T1 Closure | K43: -31 | L43: -32 | M43: -32 | U43: Impact of T1 Closure | V43: =SUM(I43:M43) -> -95
B44: SQR at 5 mins queuing in transfers | I44: 5 | J44: 5 | K44: 5 | L44: 5 | M44: 5 | U44: SQR at 5 mins queuing in transfers | V44: =SUM(I44:M44) -> 25
B45: Increase opex saving by 0.2% | I45: -3 | J45: -5 | K45: -8 | L45: -11 | M45: -14 | U45: Increase opex saving by 0.2% | V45: =SUM(I45:M45) -> -41
B46: Total Q6 after Adjustments | C46: =SUM(C42:C45) -> 1066 | D46: =SUM(D42:D45) -> 1077 | E46: =SUM(E42:E45) -> 1020 | F46: =SUM(F42:F45) -> 1024 | G46: =SUM(G42:G45) -> 1064 | H46: =SUM(H42:H45) -> 1036 | I46: =SUM(I42:I45) -> 1137 | J46: =SUM(J42:J45) -> 1133 | ... M46: =SUM(M42:M45) -> 1058 | U46: Total Q6 after Adjustments | V46: =SUM(I46:M46) -> 5468 | X46: =((M46/H46)^(1/5))-1 -> 0.0042114814
B48: Passengers (m) | C48: 65.9 | D48: 66.1 | E48: 66.1 | F48: 70.1 | G48: 69.2 | H48: 69.1 | I48: 69.2 | J48: 70.1 | K48: 71.1 | L48: 71.8 | M48: 72.6 | P48: Passengers (m) | Q48: =SUM(C48:H48) -> 406.5 | S48: =((H48/C48)^(1/5))-1 -> 0.0095283664 | U48: Passengers (m) | V48: =SUM(I48:M48) -> 354.8 | X48: =((M48/H48)^(1/5))-1 -> 0.0099310268
B49: Total opex / passenger | C49: =C46/C48 -> 16.176024 | D49: =D46/D48 -> 16.293495 | E49: =E46/E48 -> 15.431165 | F49: =F46/F48 -> 14.607703 | G49: =G46/G48 -> 15.375723 | H49: =H46/H48 -> 14.992764 | I49: =I46/I48 -> 16.430636 | J49: =J46/J48 -> 16.162625 | ... M49: =M46/M48 -> 14.573003 | P49: Total opex / passenger | Q49: =Q42/Q48 -> 12.917589 | S49: =((H49/C49)^(1/5))-1 -> -0.015077671 | U49: Total opex / passenger | V49: =V46/V48 -> 15.411499 | X49: =((M49/H49)^(1/5))-1 -> -0.005663303
B52: Price Base Conversion 2012/13 to 2011/12 | C52: =RPI!$T$103/RPI!$V$104 -> 0.97002827 | D52: =RPI!$T$103/RPI!$V$104 -> 0.97002827 | E52: =RPI!$T$103/RPI!$V$104 -> 0.97002827 | F52: =RPI!$T$103/RPI!$V$104 -> 0.97002827 | G52: =RPI!$T$103/RPI!$V$104 -> 0.97002827 | H52: =RPI!$T$103/RPI!$V$104 -> 0.97002827 | I52: =RPI!$T$103/RPI!$V$104 -> 0.97002827 | J52: =RPI!$T$103/RPI!$V$104 -> 0.97002827 | ... M52: =RPI!$T$103/RPI!$V$104 -> 0.97002827
B54: July 2012 IBP Forecast | C54: Q5 | H54: Q5+1 | I54: Q6 | P54: July 2012 IBP Forecast - Summary | U54: July 2012 IBP Forecast - Summary
B55: £m 2011/12 prices | C55: 2008/09 | D55: 2009/10 | E55: 2010/11 | F55: 2011/12 | G55: 2012/13 | H55: 2013/14 | I55: 2014/15 | J55: 2015/16 | K55: 2016/17 | L55: 2017/18 | M55: 2018/19 | P55: £m 2011/12 prices | Q55: Total Q5+1 | R55: % of Total | S55: CAGR (Q5+1) | U55: £m 2011/12 prices | V55: Total Q6 | W55: % of Total | X55: CAGR (Q6)
B56: Security Costs | C56: =C31*C$52 -> 175.57512 | D56: =D31*D$52 -> 167.81489 | E56: =E31*E$52 -> 161.99472 | F56: =F31*F$52 -> 162.96475 | G56: =G31*G$52 -> 156.17455 | H56: =H31*H$52 -> 173.63506 | I56: =I31*I$52 -> 174.60509 | J56: =J31*J$52 -> 172.66503 | ... M56: =M31*M$52 -> 163.93478 | P56: Security Costs | Q56: =SUM(C56:G56) -> 824.52403 | R56: =Q56/$Q$67 -> 0.16187393 | S56: =((H56/C56)^(1/5))-1 -> -0.0022197777 | U56: Security Costs | V56: =SUM(I56:M56) -> 839.07445 | W56: =V56/$V$67 -> 0.15504571 | X56: =((M56/H56)^(1/5))-1 -> -0.011431575
B57: Staff Costs - Other Operational | C57: =C32*C$52 -> 62.081809 | D57: =D32*D$52 -> 52.381527 | E57: =E32*E$52 -> 54.321583 | F57: =F32*F$52 -> 53.351555 | G57: =G32*G$52 -> 55.291611 | H57: =H32*H$52 -> 54.321583 | I57: =I32*I$52 -> 58.201696 | J57: =J32*J$52 -> 59.171724 | ... M57: =M32*M$52 -> 56.26164 | P57: Staff Costs - Other Operational | Q57: =SUM(C57:G57) -> 277.42808 | R57: =Q57/$Q$67 -> 0.054465816 | S57: =((H57/C57)^(1/5))-1 -> -0.026352819 | U57: Staff Costs - Other Operational | V57: =SUM(I57:M57) -> 286.15834 | W57: =V57/$V$67 -> 0.05287686 | X57: =((M57/H57)^(1/5))-1 -> 0.0070429497
B58: Facilities Management | C58: =C33*C$52 -> 172.66503 | D58: =D33*D$52 -> 177.51517 | E58: =E33*E$52 -> 161.02469 | F58: =F33*F$52 -> 163.93478 | G58: =G33*G$52 -> 169.75495 | H58: =H33*H$52 -> 186.24543 | I58: =I33*I$52 -> 214.37625 | J58: =J33*J$52 -> 208.55608 | ... M58: =M33*M$52 -> 199.82582 | P58: Facilities Management | Q58: =SUM(C58:G58) -> 844.89462 | R58: =Q58/$Q$67 -> 0.16587317 | S58: =((H58/C58)^(1/5))-1 -> 0.015257591 | U58: Facilities Management | V58: =SUM(I58:M58) -> 1028.23 | W58: =V58/$V$67 -> 0.18999821 | X58: =((M58/H58)^(1/5))-1 -> 0.014175695
B59: Utilities | C59: =C34*C$52 -> 90.212629 | D59: =D34*D$52 -> 116.40339 | E59: =E34*E$52 -> 92.152686 | F59: =F34*F$52 -> 84.392459 | G59: =G34*G$52 -> 89.242601 | H59: =H34*H$52 -> 90.212629 | I59: =I34*I$52 -> 98.942883 | J59: =J34*J$52 -> 97.972855 | ... M59: =M34*M$52 -> 95.06277 | P59: Utilities | Q59: =SUM(C59:G59) -> 472.40377 | R59: =Q59/$Q$67 -> 0.092744239 | S59: =((H59/C59)^(1/5))-1 -> 0 | U59: Utilities | V59: =SUM(I59:M59) -> 482.10405 | W59: =V59/$V$67 -> 0.089084065 | X59: =((M59/H59)^(1/5))-1 -> 0.010528637
B60: Rent and Rates | C60: =C35*C$52 -> 114.46334 | D60: =D35*D$52 -> 121.25353 | E60: =E35*E$52 -> 108.64317 | F60: =F35*F$52 -> 116.40339 | G60: =G35*G$52 -> 122.22356 | H60: =H35*H$52 -> 126.10367 | I60: =I35*I$52 -> 149.38435 | J60: =J35*J$52 -> 161.99472 | ... M60: =M35*M$52 -> 161.99472 | P60: Rent and Rates | Q60: =SUM(C60:G60) -> 582.98699 | R60: =Q60/$Q$67 -> 0.11445439 | S60: =((H60/C60)^(1/5))-1 -> 0.01955878 | U60: Rent and Rates | V60: =SUM(I60:M60) -> 797.36324 | W60: =V60/$V$67 -> 0.14733823 | X60: =((M60/H60)^(1/5))-1 -> 0.051367684
B61: Central Support Services | C61: =C36*C$52 -> 119.31348 | D61: =D36*D$52 -> 106.70311 | E61: =E36*E$52 -> 121.25353 | F61: =F36*F$52 -> 119.31348 | G61: =G36*G$52 -> 138.71404 | H61: =H36*H$52 -> 107.67314 | I61: =I36*I$52 -> 108.64317 | J61: =J36*J$52 -> 107.67314 | ... M61: =M36*M$52 -> 102.823 | P61: Central Support Services | Q61: =SUM(C61:G61) -> 605.29764 | R61: =Q61/$Q$67 -> 0.11883451 | S61: =((H61/C61)^(1/5))-1 -> -0.020321508 | U61: Central Support Services | V61: =SUM(I61:M61) -> 527.69538 | W61: =V61/$V$67 -> 0.097508514 | X61: =((M61/H61)^(1/5))-1 -> -0.0091758639
B62: Rail | C62: =C37*C$52 -> 70.812064 | D62: =D37*D$52 -> 74.692177 | E62: =E37*E$52 -> 72.75212 | F62: =F37*F$52 -> 64.021866 | G62: =G37*G$52 -> 64.021866 | H62: =H37*H$52 -> 64.991894 | I62: =I37*I$52 -> 58.201696 | J62: =J37*J$52 -> 57.231668 | ... M62: =M37*M$52 -> 58.201696 | P62: Rail | Q62: =SUM(C62:G62) -> 346.30009 | R62: =Q62/$Q$67 -> 0.06798705 | S62: =((H62/C62)^(1/5))-1 -> -0.017007083 | U62: Rail | V62: =SUM(I62:M62) -> 289.06842 | W62: =V62/$V$67 -> 0.05341459 | X62: =((M62/H62)^(1/5))-1 -> -0.021827859
B63: Commercial Expenditure | C63: =C38*C$52 -> 40.741187 | D63: =D38*D$52 -> 54.321583 | E63: =E38*E$52 -> 43.651272 | F63: =F38*F$52 -> 42.681244 | G63: =G38*G$52 -> 44.6213 | H63: =H38*H$52 -> 46.561357 | I63: =I38*I$52 -> 49.471442 | J63: =J38*J$52 -> 50.44147 | ... M63: =M38*M$52 -> 49.471442 | P63: Commercial Expenditure | Q63: =SUM(C63:G63) -> 226.01659 | R63: =Q63/$Q$67 -> 0.0443725 | S63: =((H63/C63)^(1/5))-1 -> 0.027066087 | U63: Commercial Expenditure | V63: =SUM(I63:M63) -> 247.35721 | W63: =V63/$V$67 -> 0.045707116 | X63: =((M63/H63)^(1/5))-1 -> 0.012198729
B64: Other | C64: =C39*C$52 -> 154.23449 | D64: =D39*D$52 -> 148.41433 | E64: =E39*E$52 -> 141.62413 | F64: =F39*F$52 -> 151.32441 | G64: =G39*G$52 -> 161.02469 | H64: =H39*H$52 -> 122.22356 | I64: =I39*I$52 -> 113.49331 | J64: =J39*J$52 -> 109.61319 | ... M64: =M39*M$52 -> 108.64317 | P64: Other | Q64: =SUM(C64:G64) -> 756.62205 | R64: =Q64/$Q$67 -> 0.14854313 | S64: =((H64/C64)^(1/5))-1 -> -0.045458787 | U64: Other | V64: =SUM(I64:M64) -> 552.91611 | W64: =V64/$V$67 -> 0.10216885 | X64: =((M64/H64)^(1/5))-1 -> -0.023281316
B65: Pensions | C65: =C40*C$52 -> 33.950989 | D65: =D40*D$52 -> 25.220735 | E65: =E40*E$52 -> 32.010933 | F65: =F40*F$52 -> 34.921018 | G65: =G40*G$52 -> 31.040905 | H65: =H40*H$52 -> 32.980961 | I65: =I40*I$52 -> 75.662205 | J65: =J40*J$52 -> 73.722148 | ... M65: =M40*M$52 -> 69.842035 | P65: Pensions | Q65: =SUM(C65:G65) -> 157.14458 | R65: =Q65/$Q$67 -> 0.030851266 | S65: =((H65/C65)^(1/5))-1 -> -0.0057807343 | U65: Pensions | V65: =SUM(I65:M65) -> 361.82054 | W65: =V65/$V$67 -> 0.06685786 | X65: =((M65/H65)^(1/5))-1 -> 0.16190525
B67: Total | C67: =C42*C$52 -> 1034.0501 | D67: =D42*D$52 -> 1044.7204 | E67: =E42*E$52 -> 989.42883 | F67: =F42*F$52 -> 993.30895 | G67: =G42*G$52 -> 1032.1101 | H67: =H42*H$52 -> 1004.9493 | I67: =I42*I$52 -> 1100.9821 | J67: =J42*J$52 -> 1099.042 | ... M67: =M42*M$52 -> 1066.0611 | P67: Total | Q67: =SUM(C67:G67) -> 5093.6184 | R67: =Q67/$Q$67 -> 1 | S67: =((H67/C67)^(1/5))-1 -> -0.0056929697 | U67: Total | V67: =SUM(I67:M67) -> 5411.7877 | W67: =V67/$V$67 -> 1 | X67: =((M67/H67)^(1/5))-1 -> 0.011876681
B68: Impact of T1 Closure | C68: =C43*C$52 -> 0 | D68: =D43*D$52 -> 0 | E68: =E43*E$52 -> 0 | F68: =F43*F$52 -> 0 | G68: =G43*G$52 -> 0 | H68: =H43*H$52 -> 0 | I68: =I43*I$52 -> 0 | J68: =J43*J$52 -> 0 | ... M68: =M43*M$52 -> -31.040905 | U68: Impact of T1 Closure | V68: =SUM(I68:M68) -> -92.152686
B69: SQR at 5 mins queuing in transfers | C69: =C44*C$52 -> 0 | D69: =D44*D$52 -> 0 | E69: =E44*E$52 -> 0 | F69: =F44*F$52 -> 0 | G69: =G44*G$52 -> 0 | H69: =H44*H$52 -> 0 | I69: =I44*I$52 -> 4.8501413 | J69: =J44*J$52 -> 4.8501413 | ... M69: =M44*M$52 -> 4.8501413 | U69: SQR at 5 mins queuing in transfers | V69: =SUM(I69:M69) -> 24.250707
B70: Increase opex saving by 0.2% | C70: =C45*C$52 -> 0 | D70: =D45*D$52 -> 0 | E70: =E45*E$52 -> 0 | F70: =F45*F$52 -> 0 | G70: =G45*G$52 -> 0 | H70: =H45*H$52 -> 0 | I70: =I45*I$52 -> -2.9100848 | J70: =J45*J$52 -> -4.8501413 | ... M70: =M45*M$52 -> -13.580396 | U70: Increase opex saving by 0.2% | V70: =SUM(I70:M70) -> -39.771159
B71: Total Q6 after Adjustments | C71: =C46*C$52 -> 1034.0501 | D71: =D46*D$52 -> 1044.7204 | E71: =E46*E$52 -> 989.42883 | F71: =F46*F$52 -> 993.30895 | G71: =G46*G$52 -> 1032.1101 | H71: =H46*H$52 -> 1004.9493 | I71: =I46*I$52 -> 1102.9221 | J71: =J46*J$52 -> 1099.042 | ... M71: =M46*M$52 -> 1026.2899 | U71: Total Q6 after Adjustments | V71: =SUM(I71:M71) -> 5304.1146 | X71: =((M71/H71)^(1/5))-1 -> 0.0042114814
B73: Passengers (m) | C73: =C48 -> 65.9 | D73: =D48 -> 66.1 | E73: =E48 -> 66.1 | F73: =F48 -> 70.1 | G73: =G48 -> 69.2 | H73: =H48 -> 69.1 | I73: =I48 -> 69.2 | J73: =J48 -> 70.1 | ... M73: =M48 -> 72.6 | P73: Passengers (m) | Q73: =SUM(C73:H73) -> 406.5 | S73: =((H73/C73)^(1/5))-1 -> 0.0095283664 | U73: Passengers (m) | V73: =SUM(I73:M73) -> 354.8 | X73: =((M73/H73)^(1/5))-1 -> 0.0099310268
B74: Total opex / passenger | C74: =C49*C$52 -> 15.691201 | D74: =D49*D$52 -> 15.80515 | E74: =E49*E$52 -> 14.968666 | F74: =F49*F$52 -> 14.169885 | G74: =G49*G$52 -> 14.914886 | H74: =H49*H$52 -> 14.543405 | I74: =I49*I$52 -> 15.938181 | J74: =J49*J$52 -> 15.678203 | ... M74: =M49*M$52 -> 14.136225 | P74: Total opex / passenger | Q74: =Q67/Q73 -> 12.530427 | S74: =((H74/C74)^(1/5))-1 -> -0.015077671 | U74: Total opex / passenger | V74: =V71/V73 -> 14.94959 | X74: =((M74/H74)^(1/5))-1 -> -0.005663303
B78: End

Sheet HAL - fBP
B2: Heathrow - Full Business Plan - January 2013
B4: January 2013 FBP Forecast | C4: Q5 | H4: Q5+1 | I4: Q6 | P4: January 2013 FBP Forecast - Summary - Q5+1 | U4: January 2013 FBP Forecast - Summary Q6
B5: £m nominal | C5: 2008/09 | D5: 2009/10 | E5: 2010/11 | F5: 2011/12 | G5: 2012/13 | H5: 2013/14 | I5: 2014/15 | J5: 2015/16 | K5: 2016/17 | L5: 2017/18 | M5: 2018/19 | P5: £m nominal | Q5: Total Q5+1 | R5: % of Total | S5: CAGR (Q5+1) | U5: £m nominal | V5: Total Q6 | W5: % of Total | X5: CAGR (Q6)
B6: =B28 -> Security Costs (includes police) | C6: =C28*C$24 -> 160.7284 | D6: =D28*D$24 -> 153.91017 | E6: =E28*E$24 -> 155.53706 | F6: =F28*F$24 -> 164.2 | G6: =G28*G$24 -> 167.4178 | H6: =H28*H$24 -> 163.8739 | I6: =I28*I$24 -> 173.35171 | J6: =J28*J$24 -> 171.47402 | ... M6: =M28*M$24 -> 162.89692 | P6: =B6 -> Security Costs (includes police) | Q6: =SUM(C6:H6) -> 965.66734 | R6: =Q6/$Q$17 -> 0.15746642 | S6: =((H6/C6)^(1/5))-1 -> 0.003883773 | U6: =P6 -> Security Costs (includes police) | V6: =SUM(I6:M6) -> 831.70118 | W6: =V6/$V$17 -> 0.13780319 | X6: =((M6/H6)^(1/5))-1 -> -0.0011952164
B7: =B29 -> Total Operational Staff | C7: =C29*C$24 -> 56.727671 | D7: =D29*D$24 -> 48.818525 | E7: =E29*E$24 -> 52.577252 | F7: =F29*F$24 -> 55.5 | G7: =G29*G$24 -> 66.183638 | H7: =H29*H$24 -> 76.404231 | I7: =I29*I$24 -> 74.324547 | J7: =J29*J$24 -> 71.456841 | ... M7: =M29*M$24 -> 71.963476 | P7: =B7 -> Total Operational Staff | Q7: =SUM(C7:H7) -> 356.21132 | R7: =Q7/$Q$17 -> 0.058085552 | S7: =((H7/C7)^(1/5))-1 -> 0.061364338 | U7: =P7 -> Total Operational Staff | V7: =SUM(I7:M7) -> 367.4493 | W7: =V7/$V$17 -> 0.060882066 | X7: =((M7/H7)^(1/5))-1 -> -0.011904446
B8: =B30 -> Facilities Management | C8: =C30*C$24 -> 155.91019 | D8: =D30*D$24 -> 161.18295 | E8: =E30*E$24 -> 150.86141 | F8: =F30*F$24 -> 161.1 | G8: =G30*G$24 -> 169.78887 | H8: =H30*H$24 -> 182.21092 | I8: =I30*I$24 -> 221.13178 | J8: =J30*J$24 -> 222.88262 | ... M8: =M30*M$24 -> 229.2306 | P8: =B8 -> Facilities Management | Q8: =SUM(C8:H8) -> 981.05433 | R8: =Q8/$Q$17 -> 0.1599755 | S8: =((H8/C8)^(1/5))-1 -> 0.031668051 | U8: =P8 -> Facilities Management | V8: =SUM(I8:M8) -> 1116.461 | W8: =V8/$V$17 -> 0.18498458 | X8: =((M8/H8)^(1/5))-1 -> 0.046983019
B9: =B31 -> Utilities | C9: =C31*C$24 -> 85.455146 | D9: =D31*D$24 -> 108.63713 | E9: =E31*E$24 -> 93.799343 | F9: =F31*F$24 -> 90.4 | G9: =G31*G$24 -> 87.523222 | H9: =H31*H$24 -> 100.53743 | I9: =I31*I$24 -> 110.72841 | J9: =J31*J$24 -> 118.04939 | ... M9: =M31*M$24 -> 129.4853 | P9: =B9 -> Utilities | Q9: =SUM(C9:H9) -> 566.35227 | R9: =Q9/$Q$17 -> 0.092352159 | S9: =((H9/C9)^(1/5))-1 -> 0.033041841 | U9: =P9 -> Utilities | V9: =SUM(I9:M9) -> 607.66167 | W9: =V9/$V$17 -> 0.10068245 | X9: =((M9/H9)^(1/5))-1 -> 0.051909894
B10: =B32 -> Rent and Rates | C10: =C32*C$24 -> 106.09165 | D10: =D32*D$24 -> 113.18261 | E10: =E32*E$24 -> 107.63546 | F10: =F32*F$24 -> 119.6 | G10: =G32*G$24 -> 130.61475 | H10: =H32*H$24 -> 131.52066 | I10: =I32*I$24 -> 151.79109 | J10: =J32*J$24 -> 159.93788 | ... M10: =M32*M$24 -> 213.56508 | P10: =B10 -> Rent and Rates | Q10: =SUM(C10:H10) -> 708.64514 | R10: =Q10/$Q$17 -> 0.11555513 | S10: =((H10/C10)^(1/5))-1 -> 0.043908788 | U10: =P10 -> Rent and Rates | V10: =SUM(I10:M10) -> 884.22362 | W10: =V10/$V$17 -> 0.14650555 | X10: =((M10/H10)^(1/5))-1 -> 0.10181137
B11: =B33 -> Other | C11: =C33*C$24 -> 141.63736 | D11: =D33*D$24 -> 136.00096 | E11: =E33*E$24 -> 135.68939 | F11: =F33*F$24 -> 148.9 | G11: =G33*G$24 -> 141.33609 | H11: =H33*H$24 -> 129.62373 | I11: =I33*I$24 -> 131.7473 | J11: =J33*J$24 -> 133.39357 | ... M11: =M33*M$24 -> 145.15082 | P11: =B11 -> Other | Q11: =SUM(C11:H11) -> 833.18752 | R11: =Q11/$Q$17 -> 0.13586361 | S11: =((H11/C11)^(1/5))-1 -> -0.017570625 | U11: =P11 -> Other | V11: =SUM(I11:M11) -> 688.26758 | W11: =V11/$V$17 -> 0.11403791 | X11: =((M11/H11)^(1/5))-1 -> 0.02288544
B12: =B34 -> Commercial | C12: =C34*C$24 -> 35.818433 | D12: =D34*D$24 -> 47.636698 | E12: =E34*E$24 -> 40.363298 | F12: =F34*F$24 -> 42.6 | G12: =G34*G$24 -> 49.070735 | H12: =H34*H$24 -> 51.322566 | I12: =I34*I$24 -> 51.572134 | J12: =J34*J$24 -> 52.976624 | ... M12: =M34*M$24 -> 59.847177 | P12: =B12 -> Commercial | Q12: =SUM(C12:H12) -> 266.81173 | R12: =Q12/$Q$17 -> 0.04350762 | S12: =((H12/C12)^(1/5))-1 -> 0.074583965 | U12: =P12 -> Commercial | V12: =SUM(I12:M12) -> 274.68601 | W12: =V12/$V$17 -> 0.04551227 | X12: =((M12/H12)^(1/5))-1 -> 0.031209869
B13: =B35 -> Rail | C13: =C35*C$24 -> 64.727727 | D13: =D35*D$24 -> 68.000478 | E13: =E35*E$24 -> 68.989751 | F13: =F35*F$24 -> 64.2 | G13: =G35*G$24 -> 65.5651 | H13: =H35*H$24 -> 66.392642 | I13: =I35*I$24 -> 62.081582 | J13: =J35*J$24 -> 63.280745 | ... M13: =M35*M$24 -> 67.312776 | P13: =B13 -> Rail | Q13: =SUM(C13:H13) -> 397.8757 | R13: =Q13/$Q$17 -> 0.064879549 | S13: =((H13/C13)^(1/5))-1 -> 0.0050922375 | U13: =P13 -> Rail | V13: =SUM(I13:M13) -> 323.81789 | W13: =V13/$V$17 -> 0.053652851 | X13: =((M13/H13)^(1/5))-1 -> 0.0027565541
B14: =B36 -> Central Support Services | C14: =C36*C$24 -> 108.72804 | D14: =D36*D$24 -> 96.273403 | E14: =E36*E$24 -> 113.93328 | F14: =F36*F$24 -> 118.9 | G14: =G36*G$24 -> 119.9965 | H14: =H36*H$24 -> 127.83218 | I14: =I36*I$24 -> 116.90406 | J14: =J36*J$24 -> 114.80135 | ... M14: =M36*M$24 -> 126.42563 | P14: =B14 -> Central Support Services | Q14: =SUM(C14:H14) -> 685.66341 | R14: =Q14/$Q$17 -> 0.11180761 | S14: =((H14/C14)^(1/5))-1 -> 0.032903459 | U14: =P14 -> Central Support Services | V14: =SUM(I14:M14) -> 599.33319 | W14: =V14/$V$17 -> 0.099302523 | X14: =((M14/H14)^(1/5))-1 -> -0.0022103715
B15: =B37 -> Pensions | C15: =C37*C$24 -> 42.091205 | D15: =D37*D$24 -> 50.909448 | E15: =E37*E$24 -> 60.020129 | F15: =F37*F$24 -> 64.1 | G15: =G37*G$24 -> 77.008065 | H15: =H37*H$24 -> 76.931157 | I15: =I37*I$24 -> 78.44165 | J15: =J37*J$24 -> 67.648796 | ... M15: =M37*M$24 -> 64.987425 | P15: =B15 -> Pensions | Q15: =SUM(C15:H15) -> 371.06 | R15: =Q15/$Q$17 -> 0.060506851 | S15: =((H15/C15)^(1/5))-1 -> 0.12818983 | U15: =P15 -> Pensions | V15: =SUM(I15:M15) -> 341.82613 | W15: =V15/$V$17 -> 0.056636605 | X15: =((M15/H15)^(1/5))-1 -> -0.033180473
B17: Total | C17: =C39*C$24 -> 957.91582 | D17: =D39*D$24 -> 984.55237 | E17: =E39*E$24 -> 979.40637 | F17: =F39*F$24 -> 1029.5 | G17: =G39*G$24 -> 1074.5048 | H17: =H39*H$24 -> 1106.6494 | I17: =I39*I$24 -> 1172.0743 | J17: =J39*J$24 -> 1175.9018 | ... M17: =M39*M$24 -> 1270.8652 | P17: =B17 -> Total | Q17: =SUM(C17:H17) -> 6132.5287 | R17: =Q17/$Q$17 -> 1 | S17: =((H17/C17)^(1/5))-1 -> 0.029287132 | U17: =P17 -> Total | V17: =SUM(I17:M17) -> 6035.4276 | W17: =V17/$V$17 -> 1 | X17: =((M17/H17)^(1/5))-1 -> 0.028058636
B19: Man Years | C19: =C55 -> 7907 | D19: =D55 -> 7406 | E19: =E55 -> 7457 | F19: =F55 -> 7464 | G19: =G55 -> 7152 | H19: =H55 -> 6893 | I19: =I55 -> 6552 | J19: =J55 -> 6362 | ... M19: =M55 -> 5797 | P19: Man Years | Q19: =SUM(C19:H19) -> 44279 | S19: =((H19/C19)^(1/5))-1 -> -0.027075123 | U19: =P19 -> Man Years | V19: =V41 -> 30616 | X19: =((M19/H19)^(1/5))-1 -> -0.034040308
B20: Passengers (m) | C20: =C42 -> 65.9 | D20: =D42 -> 66.1 | E20: =E42 -> 66.1 | F20: =F42 -> 70.067623 | G20: =G42 -> 69.6 | H20: =H42 -> 68.8 | I20: =I42 -> 69.494122 | J20: =J42 -> 70.256156 | ... M20: =M42 -> 72.602541 | P20: =B20 -> Passengers (m) | Q20: =SUM(C20:H20) -> 406.56762 | S20: =((H20/C20)^(1/5))-1 -> 0.0086502598 | U20: =P20 -> Passengers (m) | V20: =V42 -> 355.19129 | X20: =((M20/H20)^(1/5))-1 -> 0.010817324
B21: Total opex / passenger | C21: =C17/C20 -> 14.5359 | D21: =D17/D20 -> 14.894892 | E21: =E17/E20 -> 14.81704 | F21: =F17/F20 -> 14.692949 | G21: =G17/G20 -> 15.438287 | H21: =H17/H20 -> 16.085021 | I21: =I17/I20 -> 16.865804 | J21: =J17/J20 -> 16.73735 | ... M21: =M17/M20 -> 17.504418 | P21: =B21 -> Total opex / passenger | Q21: =Q17/Q20 -> 15.083662 | S21: =((H21/C21)^(1/5))-1 -> 0.020459889 | U21: =P21 -> Total opex / passenger | V21: =V17/V20 -> 16.992048 | X21: =((M21/H21)^(1/5))-1 -> 0.017056803
B24: Price Base Conversion 11/12 to Nominal | C24: =RPI!$T101/RPI!$T$103 -> 0.90909729 | D24: =RPI!$T101/RPI!$T$103 -> 0.90909729 | E24: =RPI!$T102/RPI!$T$103 -> 0.95421509 | F24: =RPI!$T103/RPI!$T$103 -> 1 | G24: =RPI!$V104/RPI!$T$103 -> 1.0308978 | H24: =RPI!$V105/RPI!$T$103 -> 1.0538515 | I24: =RPI!$V106/RPI!$T$103 -> 1.0834482 | J24: =RPI!$V107/RPI!$T$103 -> 1.1200132 | K24: =RPI!$V108/RPI!$T$103 -> 1.1536136 | L24: =RPI!$V109/RPI!$T$103 -> 1.188222 | M24: =RPI!$V110/RPI!$T$103 -> 1.2238686
B26: January 2013 FBP Forecast | C26: Q5 | H26: Q5+1 | I26: Q6 | P26: January 2013 FBP Forecast - Summary - Q5+1 | U26: January 2013 FBP Forecast - Summary Q6
B27: £m 2011/12 prices | C27: 2008/09 | D27: 2009/10 | E27: 2010/11 | F27: 2011/12 | G27: 2012/13 | H27: 2013/14 | I27: 2014/15 | J27: 2015/16 | K27: 2016/17 | L27: 2017/18 | M27: 2018/19 | P27: £m 2011/12 prices | Q27: Total Q5+1 | R27: % of Total | S27: CAGR (Q5+1) | U27: £m 2011/12 prices | V27: Total Q6 | W27: % of Total | X27: CAGR (Q6)
B28: Security Costs (includes police) | C28: 176.8 | D28: 169.3 | E28: 163 | F28: 164.2 | G28: 162.4 | H28: 155.5 | I28: 160 | J28: 153.1 | K28: 142.2 | L28: 134.6 | M28: 133.1 | P28: =B28 -> Security Costs (includes police) | Q28: =SUM(C28:H28) -> 991.2 | R28: =Q28/$Q$39 -> 0.15770883 | S28: =((H28/C28)^(1/5))-1 -> -0.025347892 | U28: =P28 -> Security Costs (includes police) | V28: =SUM(I28:M28) -> 723 | W28: =V28/$V$39 -> 0.13813527 | X28: =((M28/H28)^(1/5))-1 -> -0.030630095
B29: Total Operational Staff | C29: 62.4 | D29: 53.7 | E29: 55.1 | F29: 55.5 | G29: 64.2 | H29: 72.5 | I29: 68.6 | J29: 63.8 | K29: 69 | L29: 59 | M29: 58.8 | P29: =B29 -> Total Operational Staff | Q29: =SUM(C29:H29) -> 363.4 | R29: =Q29/$Q$39 -> 0.057820207 | S29: =((H29/C29)^(1/5))-1 -> 0.030458921 | U29: =P29 -> Total Operational Staff | V29: =SUM(I29:M29) -> 319.2 | W29: =V29/$V$39 -> 0.060985862 | X29: =((M29/H29)^(1/5))-1 -> -0.041023723
B30: Facilities Management | C30: 171.5 | D30: 177.3 | E30: 158.1 | F30: 161.1 | G30: 164.7 | H30: 172.9 | I30: 204.1 | J30: 199 | K30: 192 | L30: 186.6 | M30: 187.3 | P30: =B30 -> Facilities Management | Q30: =SUM(C30:H30) -> 1005.6 | R30: =Q30/$Q$39 -> 0.16 | S30: =((H30/C30)^(1/5))-1 -> 0.0016273479 | U30: =P30 -> Facilities Management | V30: =SUM(I30:M30) -> 969 | W30: =V30/$V$39 -> 0.18513565 | X30: =((M30/H30)^(1/5))-1 -> 0.016128323
B31: Utilities | C31: 94 | D31: 119.5 | E31: 98.3 | F31: 90.4 | G31: 84.9 | H31: 95.4 | I31: 102.2 | J31: 105.4 | K31: 106.7 | L31: 106.3 | M31: 105.8 | P31: =B31 -> Utilities | Q31: =SUM(C31:H31) -> 582.5 | R31: =Q31/$Q$39 -> 0.092680986 | S31: =((H31/C31)^(1/5))-1 -> 0.0029611348 | U31: =P31 -> Utilities | V31: =SUM(I31:M31) -> 526.4 | W31: =V31/$V$39 -> 0.10057318 | X31: =((M31/H31)^(1/5))-1 -> 0.020910002
B32: Rent and Rates | C32: 116.7 | D32: 124.5 | E32: 112.8 | F32: 119.6 | G32: 126.7 | H32: 124.8 | I32: 140.1 | J32: 142.8 | K32: 141.7 | L32: 164.5 | M32: 174.5 | P32: =B32 -> Rent and Rates | Q32: =SUM(C32:H32) -> 725.1 | R32: =Q32/$Q$39 -> 0.11536993 | S32: =((H32/C32)^(1/5))-1 -> 0.013511652 | U32: =P32 -> Rent and Rates | V32: =SUM(I32:M32) -> 763.6 | W32: =V32/$V$39 -> 0.14589224 | X32: =((M32/H32)^(1/5))-1 -> 0.069340878
B33: Other | C33: 155.8 | D33: 149.6 | E33: 142.2 | F33: 148.9 | G33: 137.1 | H33: 123 | I33: 121.6 | J33: 119.1 | K33: 118.7 | L33: 118.7 | M33: 118.6 | P33: =B33 -> Other | Q33: =SUM(C33:H33) -> 856.6 | R33: =Q33/$Q$39 -> 0.13629276 | S33: =((H33/C33)^(1/5))-1 -> -0.046177569 | U33: =P33 -> Other | V33: =SUM(I33:M33) -> 596.7 | W33: =V33/$V$39 -> 0.11400459 | X33: =((M33/H33)^(1/5))-1 -> -0.0072590983
B34: Commercial | C34: 39.4 | D34: 52.4 | E34: 42.3 | F34: 42.6 | G34: 47.6 | H34: 48.7 | I34: 47.6 | J34: 47.3 | K34: 47.4 | L34: 46.8 | M34: 48.9 | P34: =B34 -> Commercial | Q34: =SUM(C34:H34) -> 273 | R34: =Q34/$Q$39 -> 0.043436754 | S34: =((H34/C34)^(1/5))-1 -> 0.043293611 | U34: =P34 -> Commercial | V34: =SUM(I34:M34) -> 238 | W34: =V34/$V$39 -> 0.045471914 | X34: =((M34/H34)^(1/5))-1 -> 0.0008200093
B35: Rail | C35: 71.2 | D35: 74.8 | E35: 72.3 | F35: 64.2 | G35: 63.6 | H35: 63 | I35: 57.3 | J35: 56.5 | K35: 56 | L35: 56 | M35: 55 | P35: =B35 -> Rail | Q35: =SUM(C35:H35) -> 409.1 | R35: =Q35/$Q$39 -> 0.065091488 | S35: =((H35/C35)^(1/5))-1 -> -0.024174616 | U35: =P35 -> Rail | V35: =SUM(I35:M35) -> 280.8 | W35: =V35/$V$39 -> 0.053649217 | X35: =((M35/H35)^(1/5))-1 -> -0.026794784
B36: Central Support Services | C36: 119.6 | D36: 105.9 | E36: 119.4 | F36: 118.9 | G36: 116.4 | H36: 121.3 | I36: 107.9 | J36: 102.5 | K36: 103.2 | L36: 102.8 | M36: 103.3 | P36: =B36 -> Central Support Services | Q36: =SUM(C36:H36) -> 701.5 | R36: =Q36/$Q$39 -> 0.11161496 | S36: =((H36/C36)^(1/5))-1 -> 0.0028267827 | U36: =P36 -> Central Support Services | V36: =SUM(I36:M36) -> 519.7 | W36: =V36/$V$39 -> 0.099293084 | X36: =((M36/H36)^(1/5))-1 -> -0.031615334
B37: Pensions | C37: 46.3 | D37: 56 | E37: 62.9 | F37: 64.1 | G37: 74.7 | H37: 73 | I37: 72.4 | J37: 60.4 | K37: 57.1 | L37: 54.6 | M37: 53.1 | P37: =B37 -> Pensions | Q37: =SUM(C37:H37) -> 377 | R37: =Q37/$Q$39 -> 0.059984089 | S37: =((H37/C37)^(1/5))-1 -> 0.095338553 | U37: =P37 -> Pensions | V37: =SUM(I37:M37) -> 297.6 | W37: =V37/$V$39 -> 0.056858999 | X37: =((M37/H37)^(1/5))-1 -> -0.061672743
B39: Total | C39: =SUM(C28:C37) -> 1053.7 | D39: =SUM(D28:D37) -> 1083 | E39: =SUM(E28:E37) -> 1026.4 | F39: =SUM(F28:F37) -> 1029.5 | G39: =SUM(G28:G37) -> 1042.3 | H39: =SUM(H28:H37) -> 1050.1 | I39: =SUM(I28:I37) -> 1081.8 | J39: =SUM(J28:J37) -> 1049.9 | ... M39: =SUM(M28:M37) -> 1038.4 | P39: =B39 -> Total | Q39: =SUM(C39:H39) -> 6285 | R39: =Q39/$Q$39 -> 1 | S39: =((H39/C39)^(1/5))-1 -> -0.00068424218 | U39: =P39 -> Total | V39: =SUM(I39:M39) -> 5234 | W39: =V39/$V$39 -> 1 | X39: =((M39/H39)^(1/5))-1 -> -0.0022383573
B41: Man Years | C41: =C55 -> 7907 | D41: =D55 -> 7406 | E41: =E55 -> 7457 | F41: =F55 -> 7464 | G41: =G55 -> 7152 | H41: =H55 -> 6893 | I41: =I55 -> 6552 | J41: =J55 -> 6362 | ... M41: =M55 -> 5797 | P41: Man Years | Q41: =SUM(C41:H41) -> 44279 | S41: =((H41/C41)^(1/5))-1 -> -0.027075123 | U41: Man Years | V41: =SUM(I41:M41) -> 30616 | X41: =((M41/H41)^(1/5))-1 -> -0.034040308
B42: Passengers (m) | C42: 65.9 | D42: 66.1 | E42: 66.1 | F42: =[2]CA!J18 -> 70.067623 | G42: =[2]CA!K18 -> 69.6 | H42: =[2]CA!L18 -> 68.8 | I42: =[2]CA!M18 -> 69.494122 | J42: =[2]CA!N18 -> 70.256156 | K42: =[2]CA!O18 -> 71.02569 | L42: =[2]CA!P18 -> 71.812779 | M42: =[2]CA!Q18 -> 72.602541 | P42: =B42 -> Passengers (m) | Q42: =SUM(C42:H42) -> 406.56762 | S42: =((H42/C42)^(1/5))-1 -> 0.0086502598 | U42: =P42 -> Passengers (m) | V42: =SUM(I42:M42) -> 355.19129 | X42: =((M42/H42)^(1/5))-1 -> 0.010817324
B43: Total opex / passenger | C43: =C39/C42 -> 15.989378 | D43: =D39/D42 -> 16.384266 | E43: =E39/E42 -> 15.527988 | F43: =F39/F42 -> 14.692949 | G43: =G39/G42 -> 14.975575 | H43: =H39/H42 -> 15.263081 | I43: =I39/I42 -> 15.566784 | J43: =J39/J42 -> 14.943886 | ... M43: =M39/M42 -> 14.30253 | P43: =B43 -> Total opex / passenger | Q43: =Q39/Q42 -> 15.458683 | S43: =((H43/C43)^(1/5))-1 -> -0.0092544486 | U43: =P43 -> Total opex / passenger | V43: =V39/V42 -> 14.735722 | X43: =((M43/H43)^(1/5))-1 -> -0.012915965
B47: January 2013 FBP Forecast | C47: Q5 | H47: Q5+1 | I47: Q6 | P47: January 2013 FBP Forecast - Summary - Q5+1 | U47: January 2013 FBP Forecast - Summary Q6
B48: Man Years | C48: 2008/09 | D48: 2009/10 | E48: 2010/11 | F48: 2011/12 | G48: 2012/13 | H48: 2013/14 | I48: 2014/15 | J48: 2015/16 | K48: 2016/17 | L48: 2017/18 | M48: 2018/19 | P48: £m 2011/12 prices | Q48: Total Q5+1 | R48: % of Total | S48: CAGR (Q5+1) | U48: £m 2011/12 prices | V48: Total Q6 | W48: % of Total | X48: CAGR (Q6)
B49: Security | C49: " | D49: " | E49: " | F49: " | G49: " | H49: " | I49: " | J49: " | K49: " | L49: " | M49: " | P49: =B49 -> Security | Q49: " | R49: " | S49: " | U49: =P49 -> Security | V49: " | W49: " | X49: "
B50: Operations | C50: " | D50: " | E50: " | F50: " | G50: " | H50: " | I50: " | J50: " | K50: " | L50: " | M50: " | P50: =B50 -> Operations | Q50: " | R50: " | S50: " | U50: =P50 -> Operations | V50: " | W50: " | X50: "
B51: Facilities | C51: " | D51: " | E51: " | F51: " | G51: " | H51: " | I51: " | J51: " | K51: " | L51: " | M51: " | P51: =B51 -> Facilities | Q51: " | R51: " | S51: " | U51: =P51 -> Facilities | V51: " | W51: " | X51: "
B52: Commercial | C52: " | D52: " | E52: " | F52: " | G52: " | H52: " | I52: " | J52: " | K52: " | L52: " | M52: " | P52: =B52 -> Commercial | Q52: " | R52: " | S52: " | U52: =P52 -> Commercial | V52: " | W52: " | X52: "
B53: Rail | C53: " | D53: " | E53: " | F53: " | G53: " | H53: " | I53: " | J53: " | K53: " | L53: " | M53: " | P53: =B53 -> Rail | Q53: " | R53: " | S53: " | U53: =P53 -> Rail | V53: " | W53: " | X53: "
B54: Central Support | C54: " | D54: " | E54: " | F54: " | G54: " | H54: " | I54: " | J54: " | K54: " | L54: " | M54: " | P54: =B54 -> Central Support | Q54: " | R54: " | S54: " | U54: =P54 -> Central Support | V54: " | W54: " | X54: "
B55: Total | C55: 7907 | D55: 7406 | E55: 7457 | F55: 7464 | G55: 7152 | H55: 6893 | I55: 6552 | J55: 6362 | K55: 6051 | L55: 5854 | M55: 5797 | P55: =B55 -> Total | Q55: =SUM(C55:H55) -> 44279 | R55: =Q55/$Q$55 -> 1 | S55: =((H55/C55)^(1/5))-1 -> -0.027075123 | U55: =P55 -> Total | V55: =SUM(I55:M55) -> 30616 | W55: =V55/$V$55 -> 1 | X55: =((M55/H55)^(1/5))-1 -> -0.034040308
B59: HAL Business Plan with efficiency only
B61: These figures show the business plan without the impact of structural changes, but with efficiency savings and provide HAL's assessment of underlying efficiency.
B63: January 2013 FBP Forecast | C63: Q5 | H63: Q5+1 | I63: Q6 | P63: January 2013 FBP Forecast - Summary - Q5+1 | U63: January 2013 FBP Forecast - Summary Q6
B64: £m 2011/12 prices | C64: 2008/09 | D64: 2009/10 | E64: 2010/11 | F64: 2011/12 | G64: 2012/13 | H64: 2013/14 | I64: 2014/15 | J64: 2015/16 | K64: 2016/17 | L64: 2017/18 | M64: 2018/19 | P64: £m 2011/12 prices | Q64: Total Q5+1 | R64: % of Total | S64: CAGR (Q5+1) | U64: £m 2011/12 prices | V64: Total Q6 | W64: % of Total | X64: CAGR (Q6)
B65: Security Costs (includes police) | C65: 177 | D65: 169 | E65: 163 | F65: 164 | G65: 162 | H65: 156 | I65: 146 | J65: 140 | K65: 137 | L65: 134 | M65: 132 | P65: =B65 -> Security Costs (includes police) | Q65: =SUM(C65:H65) -> 991 | R65: =Q65/$Q$39 -> 0.15767701 | S65: =((H65/C65)^(1/5))-1 -> -0.024942412 | U65: =P65 -> Security Costs (includes police) | V65: =SUM(I65:M65) -> 689 | W65: =V65/$V$39 -> 0.13163928 | X65: =((M65/H65)^(1/5))-1 -> -0.03285884
B66: Total Operational Staff | C66: 62 | D66: 54 | E66: 55 | F66: 56 | G66: 64 | H66: 72 | I66: 67 | J66: 64 | K66: 66 | L66: 65 | M66: 64 | P66: =B66 -> Total Operational Staff | Q66: =SUM(C66:H66) -> 363 | R66: =Q66/$Q$39 -> 0.057756563 | S66: =((H66/C66)^(1/5))-1 -> 0.030358033 | U66: =P66 -> Total Operational Staff | V66: =SUM(I66:M66) -> 326 | W66: =V66/$V$39 -> 0.062285059 | X66: =((M66/H66)^(1/5))-1 -> -0.023281316
B67: Facilities Management | C67: 172 | D67: 177 | E67: 158 | F67: 161 | G67: 165 | H67: 173 | I67: 172 | J67: 170 | K67: 167 | L67: 167 | M67: 167 | P67: =B67 -> Facilities Management | Q67: =SUM(C67:H67) -> 1006 | R67: =Q67/$Q$39 -> 0.16006364 | S67: =((H67/C67)^(1/5))-1 -> 0.0011600959 | U67: =P67 -> Facilities Management | V67: =SUM(I67:M67) -> 843 | W67: =V67/$V$39 -> 0.16106229 | X67: =((M67/H67)^(1/5))-1 -> -0.0070346963
B68: Utilities | C68: 94 | D68: 120 | E68: 98 | F68: 90 | G68: 85 | H68: 95 | I68: 94 | J68: 94 | K68: 93 | L68: 92 | M68: 92 | P68: =B68 -> Utilities | Q68: =SUM(C68:H68) -> 582 | R68: =Q68/$Q$39 -> 0.092601432 | S68: =((H68/C68)^(1/5))-1 -> 0.0021186631 | U68: =P68 -> Utilities | V68: =SUM(I68:M68) -> 465 | W68: =V68/$V$39 -> 0.088842186 | X68: =((M68/H68)^(1/5))-1 -> -0.0063971137
B69: Rent and Rates | C69: 117 | D69: 125 | E69: 113 | F69: 120 | G69: 127 | H69: 125 | I69: 140 | J69: 143 | K69: 142 | L69: 165 | M69: 175 | P69: =B69 -> Rent and Rates | Q69: =SUM(C69:H69) -> 727 | R69: =Q69/$Q$39 -> 0.11567224 | S69: =((H69/C69)^(1/5))-1 -> 0.013315837 | U69: =P69 -> Rent and Rates | V69: =SUM(I69:M69) -> 765 | W69: =V69/$V$39 -> 0.14615972 | X69: =((M69/H69)^(1/5))-1 -> 0.069610376
B70: Other | C70: 156 | D70: 150 | E70: 142 | F70: 149 | G70: 137 | H70: 123 | I70: 123 | J70: 121 | K70: 120 | L70: 120 | M70: 120 | P70: =B70 -> Other | Q70: =SUM(C70:H70) -> 857 | R70: =Q70/$Q$39 -> 0.1363564 | S70: =((H70/C70)^(1/5))-1 -> -0.046422264 | U70: =P70 -> Other | V70: =SUM(I70:M70) -> 604 | W70: =V70/$V$39 -> 0.11539931 | X70: =((M70/H70)^(1/5))-1 -> -0.0049263481
B71: Commercial | C71: 39 | D71: 52 | E71: 42 | F71: 43 | G71: 48 | H71: 49 | I71: 48 | J71: 46 | K71: 44 | L71: 43 | M71: 42 | P71: =B71 -> Commercial | Q71: =SUM(C71:H71) -> 273 | R71: =Q71/$Q$39 -> 0.043436754 | S71: =((H71/C71)^(1/5))-1 -> 0.04670981 | U71: =P71 -> Commercial | V71: =SUM(I71:M71) -> 223 | W71: =V71/$V$39 -> 0.042606037 | X71: =((M71/H71)^(1/5))-1 -> -0.030359734
B72: Rail | C72: 71 | D72: 75 | E72: 72 | F72: 64 | G72: 64 | H72: 63 | I72: 62 | J72: 61 | K72: 61 | L72: 61 | M72: 61 | P72: =B72 -> Rail | Q72: =SUM(C72:H72) -> 409 | R72: =Q72/$Q$39 -> 0.065075577 | S72: =((H72/C72)^(1/5))-1 -> -0.023625474 | U72: =P72 -> Rail | V72: =SUM(I72:M72) -> 306 | W72: =V72/$V$39 -> 0.05846389 | X72: =((M72/H72)^(1/5))-1 -> -0.0064314019
B73: Central Support Services | C73: 120 | D73: 106 | E73: 119 | F73: 119 | G73: 116 | H73: 121 | I73: 115 | J73: 112 | K73: 110 | L73: 109 | M73: 108 | P73: =B73 -> Central Support Services | Q73: =SUM(C73:H73) -> 701 | R73: =Q73/$Q$39 -> 0.1115354 | S73: =((H73/C73)^(1/5))-1 -> 0.0016611387 | U73: =P73 -> Central Support Services | V73: =SUM(I73:M73) -> 554 | W73: =V73/$V$39 -> 0.10584639 | X73: =((M73/H73)^(1/5))-1 -> -0.022475442
B74: Pensions | C74: 46 | D74: 56 | E74: 63 | F74: 64 | G74: 75 | H74: 73 | I74: 72 | J74: 60 | K74: 57 | L74: 55 | M74: 53 | P74: =B74 -> Pensions | Q74: =SUM(C74:H74) -> 377 | R74: =Q74/$Q$39 -> 0.059984089 | S74: =((H74/C74)^(1/5))-1 -> 0.096763543 | U74: =P74 -> Pensions | V74: =SUM(I74:M74) -> 297 | W74: =V74/$V$39 -> 0.056744364 | X74: =((M74/H74)^(1/5))-1 -> -0.062026428
B76: Total | C76: =SUM(C65:C74) -> 1054 | D76: =SUM(D65:D74) -> 1084 | E76: =SUM(E65:E74) -> 1025 | F76: =SUM(F65:F74) -> 1030 | G76: =SUM(G65:G74) -> 1043 | H76: =SUM(H65:H74) -> 1050 | I76: =SUM(I65:I74) -> 1039 | J76: =SUM(J65:J74) -> 1011 | ... M76: =SUM(M65:M74) -> 1014 | P76: =B76 -> Total | Q76: =SUM(C76:H76) -> 6286 | R76: =Q76/$Q$39 -> 1.0001591 | S76: =((H76/C76)^(1/5))-1 -> -0.00076016812 | U76: =P76 -> Total | V76: =SUM(I76:M76) -> 5072 | W76: =V76/$V$39 -> 0.96904853 | X76: =((M76/H76)^(1/5))-1 -> -0.0069531659
B78: Man Years | C78: =C41 -> 7907 | D78: =D41 -> 7406 | E78: =E41 -> 7457 | F78: =F41 -> 7464 | G78: =G41 -> 7152 | H78: =H41 -> 6893 | I78: =I41 -> 6552 | J78: =J41 -> 6362 | ... M78: =M41 -> 5797 | P78: Man Years | Q78: =SUM(C78:H78) -> 44279 | S78: =((H78/C78)^(1/5))-1 -> -0.027075123 | U78: Man Years | V78: =SUM(I78:M78) -> 30616 | X78: =((M78/H78)^(1/5))-1 -> -0.034040308
B79: Passengers (m) | C79: =C42 -> 65.9 | D79: =D42 -> 66.1 | E79: =E42 -> 66.1 | F79: =F42 -> 70.067623 | G79: =G42 -> 69.6 | H79: =H42 -> 68.8 | I79: =I42 -> 69.494122 | J79: =J42 -> 70.256156 | ... M79: =M42 -> 72.602541 | P79: =B79 -> Passengers (m) | Q79: =SUM(C79:H79) -> 406.56762 | S79: =((H79/C79)^(1/5))-1 -> 0.0086502598 | U79: =P79 -> Passengers (m) | V79: =SUM(I79:M79) -> 355.19129 | X79: =((M79/H79)^(1/5))-1 -> 0.010817324
B80: Total opex / passenger | C80: =C76/C79 -> 15.99393 | D80: =D76/D79 -> 16.399395 | E80: =E76/E79 -> 15.506808 | F80: =F76/F79 -> 14.700085 | G80: =G76/G79 -> 14.985632 | H80: =H76/H79 -> 15.261628 | I80: =I76/I79 -> 14.950905 | J80: =J76/J79 -> 14.390198 | ... M80: =M76/M79 -> 13.966453 | P80: =B80 -> Total opex / passenger | Q80: =Q76/Q79 -> 15.461143 | S80: =((H80/C80)^(1/5))-1 -> -0.0093297234 | U80: =P80 -> Total opex / passenger | V80: =V76/V79 -> 14.27963 | X80: =((M80/H80)^(1/5))-1 -> -0.017580318
B83: Difference between DM and FBP
B85: These figures show the difference between the FBP, and the FBP excluding structural factors that are expected to increase costs including closure of T1, opening of T2, baggage handling improvements in T3 and T4 and enhancements to the commercial estate. The net impact of T2 opening will be £499m over Q6, this is offset by closure of T1 which will reduce costs by £179m.
B87: January 2013 FBP Forecast | C87: Q5 | H87: Q5+1 | I87: Q6 | P87: January 2013 FBP Forecast - Summary - Q5+1 | U87: January 2013 FBP Forecast - Summary Q6
B88: £m 2011/12 prices | C88: 2008/09 | D88: 2009/10 | E88: 2010/11 | F88: 2011/12 | G88: 2012/13 | H88: 2013/14 | I88: 2014/15 | J88: 2015/16 | K88: 2016/17 | L88: 2017/18 | M88: 2018/19 | P88: £m 2011/12 prices | Q88: Total Q5+1 | R88: % of Total | U88: £m 2011/12 prices | V88: Total Q6 | W88: % of Total
B89: Security Costs (includes police) | C89: =C65-C28 -> 0.2 | D89: =D65-D28 -> -0.3 | E89: =E65-E28 -> 0 | F89: =F65-F28 -> -0.2 | G89: =G65-G28 -> -0.4 | H89: =H65-H28 -> 0.5 | I89: =I65-I28 -> -14 | J89: =J65-J28 -> -13.1 | ... M89: =M65-M28 -> -1.1 | P89: =B89 -> Security Costs (includes police) | Q89: =SUM(C89:H89) -> -0.2 | R89: =Q89/$Q$39 -> -3.1821798e-05 | U89: =P89 -> Security Costs (includes police) | V89: =SUM(I89:M89) -> -34 | W89: =V89/$V$39 -> -0.0064959878
B90: Total Operational Staff | C90: =C66-C29 -> -0.4 | D90: =D66-D29 -> 0.3 | E90: =E66-E29 -> -0.1 | F90: =F66-F29 -> 0.5 | G90: =G66-G29 -> -0.2 | H90: =H66-H29 -> -0.5 | I90: =I66-I29 -> -1.6 | J90: =J66-J29 -> 0.2 | ... M90: =M66-M29 -> 5.2 | P90: =B90 -> Total Operational Staff | Q90: =SUM(C90:H90) -> -0.4 | R90: =Q90/$Q$39 -> -6.3643596e-05 | U90: =P90 -> Total Operational Staff | V90: =SUM(I90:M90) -> 6.8 | W90: =V90/$V$39 -> 0.0012991976
B91: Facilities Management | C91: =C67-C30 -> 0.5 | D91: =D67-D30 -> -0.3 | E91: =E67-E30 -> -0.1 | F91: =F67-F30 -> -0.1 | G91: =G67-G30 -> 0.3 | H91: =H67-H30 -> 0.1 | I91: =I67-I30 -> -32.1 | J91: =J67-J30 -> -29 | ... M91: =M67-M30 -> -20.3 | P91: =B91 -> Facilities Management | Q91: =SUM(C91:H91) -> 0.4 | R91: =Q91/$Q$39 -> 6.3643596e-05 | U91: =P91 -> Facilities Management | V91: =SUM(I91:M91) -> -126 | W91: =V91/$V$39 -> -0.024073366
B92: Utilities | C92: =C68-C31 -> 0 | D92: =D68-D31 -> 0.5 | E92: =E68-E31 -> -0.3 | F92: =F68-F31 -> -0.4 | G92: =G68-G31 -> 0.1 | H92: =H68-H31 -> -0.4 | I92: =I68-I31 -> -8.2 | J92: =J68-J31 -> -11.4 | ... M92: =M68-M31 -> -13.8 | P92: =B92 -> Utilities | Q92: =SUM(C92:H92) -> -0.5 | R92: =Q92/$Q$39 -> -7.9554495e-05 | U92: =P92 -> Utilities | V92: =SUM(I92:M92) -> -61.4 | W92: =V92/$V$39 -> -0.01173099
B93: Rent and Rates | C93: =C69-C32 -> 0.3 | D93: =D69-D32 -> 0.5 | E93: =E69-E32 -> 0.2 | F93: =F69-F32 -> 0.4 | G93: =G69-G32 -> 0.3 | H93: =H69-H32 -> 0.2 | I93: =I69-I32 -> -0.1 | J93: =J69-J32 -> 0.2 | ... M93: =M69-M32 -> 0.5 | P93: =B93 -> Rent and Rates | Q93: =SUM(C93:H93) -> 1.9 | R93: =Q93/$Q$39 -> 0.00030230708 | U93: =P93 -> Rent and Rates | V93: =SUM(I93:M93) -> 1.4 | W93: =V93/$V$39 -> 0.00026748185
B94: Other | C94: =C70-C33 -> 0.2 | D94: =D70-D33 -> 0.4 | E94: =E70-E33 -> -0.2 | F94: =F70-F33 -> 0.1 | G94: =G70-G33 -> -0.1 | H94: =H70-H33 -> 0 | I94: =I70-I33 -> 1.4 | J94: =J70-J33 -> 1.9 | ... M94: =M70-M33 -> 1.4 | P94: =B94 -> Other | Q94: =SUM(C94:H94) -> 0.4 | R94: =Q94/$Q$39 -> 6.3643596e-05 | U94: =P94 -> Other | V94: =SUM(I94:M94) -> 7.3 | W94: =V94/$V$39 -> 0.0013947268
B95: Commercial | C95: =C71-C34 -> -0.4 | D95: =D71-D34 -> -0.4 | E95: =E71-E34 -> -0.3 | F95: =F71-F34 -> 0.4 | G95: =G71-G34 -> 0.4 | H95: =H71-H34 -> 0.3 | I95: =I71-I34 -> 0.4 | J95: =J71-J34 -> -1.3 | ... M95: =M71-M34 -> -6.9 | P95: =B95 -> Commercial | Q95: =SUM(C95:H95) -> 0 | R95: =Q95/$Q$39 -> 0 | U95: =P95 -> Commercial | V95: =SUM(I95:M95) -> -15 | W95: =V95/$V$39 -> -0.002865877
B96: Rail | C96: =C72-C35 -> -0.2 | D96: =D72-D35 -> 0.2 | E96: =E72-E35 -> -0.3 | F96: =F72-F35 -> -0.2 | G96: =G72-G35 -> 0.4 | H96: =H72-H35 -> 0 | I96: =I72-I35 -> 4.7 | J96: =J72-J35 -> 4.5 | ... M96: =M72-M35 -> 6 | P96: =B96 -> Rail | Q96: =SUM(C96:H96) -> -0.1 | R96: =Q96/$Q$39 -> -1.5910899e-05 | U96: =P96 -> Rail | V96: =SUM(I96:M96) -> 25.2 | W96: =V96/$V$39 -> 0.0048146733
B97: Central Support Services | C97: =C73-C36 -> 0.4 | D97: =D73-D36 -> 0.1 | E97: =E73-E36 -> -0.4 | F97: =F73-F36 -> 0.1 | G97: =G73-G36 -> -0.4 | H97: =H73-H36 -> -0.3 | I97: =I73-I36 -> 7.1 | J97: =J73-J36 -> 9.5 | ... M97: =M73-M36 -> 4.7 | P97: =B97 -> Central Support Services | Q97: =SUM(C97:H97) -> -0.5 | R97: =Q97/$Q$39 -> -7.9554495e-05 | U97: =P97 -> Central Support Services | V97: =SUM(I97:M97) -> 34.3 | W97: =V97/$V$39 -> 0.0065533053
B98: Pensions | C98: =C74-C37 -> -0.3 | D98: =D74-D37 -> 0 | E98: =E74-E37 -> 0.1 | F98: =F74-F37 -> -0.1 | G98: =G74-G37 -> 0.3 | H98: =H74-H37 -> 0 | I98: =I74-I37 -> -0.4 | J98: =J74-J37 -> -0.4 | ... M98: =M74-M37 -> -0.1 | P98: =B98 -> Pensions | Q98: =SUM(C98:H98) -> 7.1054274e-15 | R98: =Q98/$Q$39 -> 1.1305374e-18 | U98: =P98 -> Pensions | V98: =SUM(I98:M98) -> -0.6 | W98: =V98/$V$39 -> -0.00011463508
C99: =C75-C38 -> 0 | D99: =D75-D38 -> 0 | E99: =E75-E38 -> 0 | F99: =F75-F38 -> 0 | G99: =G75-G38 -> 0 | H99: =H75-H38 -> 0 | I99: =I75-I38 -> 0 | J99: =J75-J38 -> 0 | ... M99: =M75-M38 -> 0
B100: Total | C100: =C76-C39 -> 0.3 | D100: =D76-D39 -> 1 | E100: =E76-E39 -> -1.4 | F100: =F76-F39 -> 0.5 | G100: =G76-G39 -> 0.7 | H100: =H76-H39 -> -0.1 | I100: =I76-I39 -> -42.8 | J100: =J76-J39 -> -38.9 | ... M100: =M76-M39 -> -24.4 | P100: =B100 -> Total | Q100: =SUM(C100:H100) -> 1 | R100: =Q100/$Q$39 -> 0.00015910899 | U100: =P100 -> Total | V100: =SUM(I100:M100) -> -162 | W100: =V100/$V$39 -> -0.030951471
C101: =C77-C40 -> 0 | D101: =D77-D40 -> 0 | E101: =E77-E40 -> 0 | F101: =F77-F40 -> 0 | G101: =G77-G40 -> 0 | H101: =H77-H40 -> 0 | I101: =I77-I40 -> 0 | J101: =J77-J40 -> 0 | ... M101: =M77-M40 -> 0
B102: Man Years | C102: =C78-C41 -> 0 | D102: =D78-D41 -> 0 | E102: =E78-E41 -> 0 | F102: =F78-F41 -> 0 | G102: =G78-G41 -> 0 | H102: =H78-H41 -> 0 | I102: =I78-I41 -> 0 | J102: =J78-J41 -> 0 | ... M102: =M78-M41 -> 0 | P102: Man Years | Q102: =SUM(C102:H102) -> 0 | U102: Man Years | V102: =SUM(I102:M102) -> 0
B103: Passengers (m) | C103: =C79-C42 -> 0 | D103: =D79-D42 -> 0 | E103: =E79-E42 -> 0 | F103: =F79-F42 -> 0 | G103: =G79-G42 -> 0 | H103: =H79-H42 -> 0 | I103: =I79-I42 -> 0 | J103: =J79-J42 -> 0 | ... M103: =M79-M42 -> 0 | P103: =B103 -> Passengers (m) | Q103: =SUM(C103:H103) -> 0 | U103: =P103 -> Passengers (m) | V103: =SUM(I103:M103) -> 0
B104: Total opex / passenger | C104: =C80-C43 -> 0.004552352 | D104: =D80-D43 -> 0.015128593 | E104: =E80-E43 -> -0.02118003 | F104: =F80-F43 -> 0.0071359635 | G104: =G80-G43 -> 0.010057471 | H104: =H80-H43 -> -0.0014534884 | I104: =I80-I43 -> -0.61587943 | J104: =J80-J43 -> -0.55368814 | ... M104: =M80-M43 -> -0.33607639 | P104: =B104 -> Total opex / passenger | U104: =P104 -> Total opex / passenger
B108: End

Sheet HAL - rBP
B2: Heathrow - Revised Business Plan - June 2013
B4: July 2013 uBP Forecast | C4: Q5 | H4: Q5+1 | I4: Q6 | P4: July 2013 uBP Forecast - Summary - Q5+1 | U4: July 2013 uBP Forecast - Summary Q6
B5: £m nominal | C5: 2008/09 | D5: 2009/10 | E5: 2010/11 | F5: 2011/12 | G5: 2012/13 | H5: 2013/14 | I5: 2014/15 | J5: 2015/16 | K5: 2016/17 | L5: 2017/18 | M5: 2018/19 | P5: £m nominal | Q5: Total Q5+1 | R5: % of Total | S5: CAGR (Q5+1) | U5: £m nominal | V5: Total Q6 | W5: % of Total | X5: CAGR (Q6)
B6: =B28 -> Security Costs (includes police) | C6: =C28*C$24 -> 160.7284 | D6: =D28*D$24 -> 153.91017 | E6: =E28*E$24 -> 155.53706 | F6: =F28*F$24 -> 164.2 | G6: =G28*G$24 -> 167.4178 | H6: =H28*H$24 -> 163.8739 | I6: =I28*I$24 -> 174.65185 | J6: =J28*J$24 -> 170.91401 | ... M6: =M28*M$24 -> 163.75363 | P6: =B6 -> Security Costs (includes police) | Q6: =SUM(C6:H6) -> 965.66734 | R6: =Q6/$Q$17 -> 0.15746642 | S6: =((H6/C6)^(1/5))-1 -> 0.003883773 | U6: =P6 -> Security Costs (includes police) | V6: =SUM(I6:M6) -> 833.19304 | W6: =V6/$V$17 -> 0.14110452 | X6: =((M6/H6)^(1/5))-1 -> -0.00014683602
B7: =B29 -> Total Operational Staff | C7: =C29*C$24 -> 56.727671 | D7: =D29*D$24 -> 48.818525 | E7: =E29*E$24 -> 52.577252 | F7: =F29*F$24 -> 55.5 | G7: =G29*G$24 -> 66.183638 | H7: =H29*H$24 -> 76.404231 | I7: =I29*I$24 -> 74.324547 | J7: =J29*J$24 -> 71.456841 | ... M7: =M29*M$24 -> 71.963476 | P7: =B7 -> Total Operational Staff | Q7: =SUM(C7:H7) -> 356.21132 | R7: =Q7/$Q$17 -> 0.058085552 | S7: =((H7/C7)^(1/5))-1 -> 0.061364338 | U7: =P7 -> Total Operational Staff | V7: =SUM(I7:M7) -> 367.4493 | W7: =V7/$V$17 -> 0.062228986 | X7: =((M7/H7)^(1/5))-1 -> -0.011904446
B8: =B30 -> Facilities Management | C8: =C30*C$24 -> 155.91019 | D8: =D30*D$24 -> 161.18295 | E8: =E30*E$24 -> 150.86141 | F8: =F30*F$24 -> 161.1 | G8: =G30*G$24 -> 169.78887 | H8: =H30*H$24 -> 182.21092 | I8: =I30*I$24 -> 207.69702 | J8: =J30*J$24 -> 201.37837 | ... M8: =M30*M$24 -> 204.998 | P8: =B8 -> Facilities Management | Q8: =SUM(C8:H8) -> 981.05433 | R8: =Q8/$Q$17 -> 0.1599755 | S8: =((H8/C8)^(1/5))-1 -> 0.031668051 | U8: =P8 -> Facilities Management | V8: =SUM(I8:M8) -> 1012.0643 | W8: =V8/$V$17 -> 0.17139708 | X8: =((M8/H8)^(1/5))-1 -> 0.023846959
B9: =B31 -> Utilities | C9: =C31*C$24 -> 85.455146 | D9: =D31*D$24 -> 108.63713 | E9: =E31*E$24 -> 93.799343 | F9: =F31*F$24 -> 90.4 | G9: =G31*G$24 -> 87.523222 | H9: =H31*H$24 -> 100.53743 | I9: =I31*I$24 -> 114.30379 | J9: =J31*J$24 -> 119.72941 | ... M9: =M31*M$24 -> 126.05847 | P9: =B9 -> Utilities | Q9: =SUM(C9:H9) -> 566.35227 | R9: =Q9/$Q$17 -> 0.092352159 | S9: =((H9/C9)^(1/5))-1 -> 0.033041841 | U9: =P9 -> Utilities | V9: =SUM(I9:M9) -> 603.13267 | W9: =V9/$V$17 -> 0.10214289 | X9: =((M9/H9)^(1/5))-1 -> 0.046282235
B10: =B32 -> Rent and Rates | C10: =C32*C$24 -> 106.09165 | D10: =D32*D$24 -> 113.18261 | E10: =E32*E$24 -> 107.63546 | F10: =F32*F$24 -> 119.6 | G10: =G32*G$24 -> 130.61475 | H10: =H32*H$24 -> 131.52066 | I10: =I32*I$24 -> 151.79109 | J10: =J32*J$24 -> 157.69786 | ... M10: =M32*M$24 -> 210.01586 | P10: =B10 -> Rent and Rates | Q10: =SUM(C10:H10) -> 708.64514 | R10: =Q10/$Q$17 -> 0.11555513 | S10: =((H10/C10)^(1/5))-1 -> 0.043908788 | U10: =P10 -> Rent and Rates | V10: =SUM(I10:M10) -> 873.14621 | W10: =V10/$V$17 -> 0.14787075 | X10: =((M10/H10)^(1/5))-1 -> 0.098124601
B11: =B33 -> Other | C11: =C33*C$24 -> 141.63736 | D11: =D33*D$24 -> 136.00096 | E11: =E33*E$24 -> 135.68939 | F11: =F33*F$24 -> 148.9 | G11: =G33*G$24 -> 141.33609 | H11: =H33*H$24 -> 129.62373 | I11: =I33*I$24 -> 130.12213 | J11: =J33*J$24 -> 131.48955 | ... M11: =M33*M$24 -> 138.90909 | P11: =B11 -> Other | Q11: =SUM(C11:H11) -> 833.18752 | R11: =Q11/$Q$17 -> 0.13586361 | S11: =((H11/C11)^(1/5))-1 -> -0.017570625 | U11: =P11 -> Other | V11: =SUM(I11:M11) -> 669.21006 | W11: =V11/$V$17 -> 0.11333336 | X11: =((M11/H11)^(1/5))-1 -> 0.013932937
B12: =B34 -> Commercial | C12: =C34*C$24 -> 35.818433 | D12: =D34*D$24 -> 47.636698 | E12: =E34*E$24 -> 40.363298 | F12: =F34*F$24 -> 42.6 | G12: =G34*G$24 -> 49.070735 | H12: =H34*H$24 -> 51.322566 | I12: =I34*I$24 -> 51.2471 | J12: =J34*J$24 -> 54.992647 | ... M12: =M34*M$24 -> 61.68298 | P12: =B12 -> Commercial | Q12: =SUM(C12:H12) -> 266.81173 | R12: =Q12/$Q$17 -> 0.04350762 | S12: =((H12/C12)^(1/5))-1 -> 0.074583965 | U12: =P12 -> Commercial | V12: =SUM(I12:M12) -> 281.84438 | W12: =V12/$V$17 -> 0.047731455 | X12: =((M12/H12)^(1/5))-1 -> 0.037460084
B13: =B35 -> Rail | C13: =C35*C$24 -> 64.727727 | D13: =D35*D$24 -> 68.000478 | E13: =E35*E$24 -> 68.989751 | F13: =F35*F$24 -> 64.2 | G13: =G35*G$24 -> 65.5651 | H13: =H35*H$24 -> 66.392642 | I13: =I35*I$24 -> 62.081582 | J13: =J35*J$24 -> 63.168744 | ... M13: =M35*M$24 -> 67.679936 | P13: =B13 -> Rail | Q13: =SUM(C13:H13) -> 397.8757 | R13: =Q13/$Q$17 -> 0.064879549 | S13: =((H13/C13)^(1/5))-1 -> 0.0050922375 | U13: =P13 -> Rail | V13: =SUM(I13:M13) -> 324.19188 | W13: =V13/$V$17 -> 0.054903171 | X13: =((M13/H13)^(1/5))-1 -> 0.0038480914
B14: =B36 -> Central Support Services | C14: =C36*C$24 -> 108.72804 | D14: =D36*D$24 -> 96.273403 | E14: =E36*E$24 -> 113.93328 | F14: =F36*F$24 -> 118.9 | G14: =G36*G$24 -> 119.9965 | H14: =H36*H$24 -> 127.83218 | I14: =I36*I$24 -> 116.90406 | J14: =J36*J$24 -> 114.80135 | ... M14: =M36*M$24 -> 126.18086 | P14: =B14 -> Central Support Services | Q14: =SUM(C14:H14) -> 685.66341 | R14: =Q14/$Q$17 -> 0.11180761 | S14: =((H14/C14)^(1/5))-1 -> 0.032903459 | U14: =P14 -> Central Support Services | V14: =SUM(I14:M14) -> 598.96613 | W14: =V14/$V$17 -> 0.10143727 | X14: =((M14/H14)^(1/5))-1 -> -0.0025970369
B15: =B37 -> Pensions | C15: =C37*C$24 -> 42.091205 | D15: =D37*D$24 -> 50.909448 | E15: =E37*E$24 -> 60.020129 | F15: =F37*F$24 -> 64.1 | G15: =G37*G$24 -> 77.008065 | H15: =H37*H$24 -> 76.931157 | I15: =I37*I$24 -> 78.44165 | J15: =J37*J$24 -> 67.536795 | ... M15: =M37*M$24 -> 64.987425 | P15: =B15 -> Pensions | Q15: =SUM(C15:H15) -> 371.06 | R15: =Q15/$Q$17 -> 0.060506851 | S15: =((H15/C15)^(1/5))-1 -> 0.12818983 | U15: =P15 -> Pensions | V15: =SUM(I15:M15) -> 341.5953 | W15: =V15/$V$17 -> 0.05785051 | X15: =((M15/H15)^(1/5))-1 -> -0.033180473
B17: Total | C17: =C39*C$24 -> 957.91582 | D17: =D39*D$24 -> 984.55237 | E17: =E39*E$24 -> 979.40637 | F17: =F39*F$24 -> 1029.5 | G17: =G39*G$24 -> 1074.5048 | H17: =H39*H$24 -> 1106.6494 | I17: =I39*I$24 -> 1161.5648 | J17: =J39*J$24 -> 1153.1656 | ... M17: =M39*M$24 -> 1236.2297 | P17: =B17 -> Total | Q17: =SUM(C17:H17) -> 6132.5287 | R17: =Q17/$Q$17 -> 1 | S17: =((H17/C17)^(1/5))-1 -> 0.029287132 | U17: =P17 -> Total | V17: =SUM(I17:M17) -> 5904.7933 | W17: =V17/$V$17 -> 1 | X17: =((M17/H17)^(1/5))-1 -> 0.022392897
B19: Man Years | C19: =C55 -> 7907 | D19: =D55 -> 7406 | E19: =E55 -> 7457 | F19: =F55 -> 7464 | G19: =G55 -> 7152 | H19: =H55 -> 6893 | I19: =I55 -> 6580 | J19: =J55 -> 6337 | ... M19: =M55 -> 5812 | P19: Man Years | Q19: =SUM(C19:H19) -> 44279 | S19: =((H19/C19)^(1/5))-1 -> -0.027075123 | U19: =P19 -> Man Years | V19: =V41 -> 30623 | X19: =((M19/H19)^(1/5))-1 -> -0.033540932
B20: Passengers (m) | C20: =C42 -> 65.9 | D20: =D42 -> 66.1 | E20: =E42 -> 66.1 | F20: =F42 -> 70.067623 | G20: =G42 -> 69.6 | H20: =H42 -> 68.8 | I20: =I42 -> 70.1 | J20: =J42 -> 70.8 | ... M20: =M42 -> 73 | P20: =B20 -> Passengers (m) | Q20: =SUM(C20:H20) -> 406.56762 | S20: =((H20/C20)^(1/5))-1 -> 0.0086502598 | U20: =P20 -> Passengers (m) | V20: =V42 -> 357.7 | X20: =((M20/H20)^(1/5))-1 -> 0.011921642
B21: Total opex / passenger | C21: =C17/C20 -> 14.5359 | D21: =D17/D20 -> 14.894892 | E21: =E17/E20 -> 14.81704 | F21: =F17/F20 -> 14.692949 | G21: =G17/G20 -> 15.438287 | H21: =H17/H20 -> 16.085021 | I21: =I17/I20 -> 16.570112 | J21: =J17/J20 -> 16.287649 | ... M21: =M17/M20 -> 16.934654 | P21: =B21 -> Total opex / passenger | Q21: =Q17/Q20 -> 15.083662 | S21: =((H21/C21)^(1/5))-1 -> 0.020459889 | U21: =P21 -> Total opex / passenger | V21: =V17/V20 -> 16.507669 | X21: =((M21/H21)^(1/5))-1 -> 0.010347891
B24: Price Base Conversion 11/12 to Nominal | C24: =RPI!$T101/RPI!$T$103 -> 0.90909729 | D24: =RPI!$T101/RPI!$T$103 -> 0.90909729 | E24: =RPI!$T102/RPI!$T$103 -> 0.95421509 | F24: =RPI!$T103/RPI!$T$103 -> 1 | G24: =RPI!$V104/RPI!$T$103 -> 1.0308978 | H24: =RPI!$V105/RPI!$T$103 -> 1.0538515 | I24: =RPI!$V106/RPI!$T$103 -> 1.0834482 | J24: =RPI!$V107/RPI!$T$103 -> 1.1200132 | K24: =RPI!$V108/RPI!$T$103 -> 1.1536136 | L24: =RPI!$V109/RPI!$T$103 -> 1.188222 | M24: =RPI!$V110/RPI!$T$103 -> 1.2238686
B26: July 2013 uBP Forecast | C26: Q5 | H26: Q5+1 | I26: Q6 | P26: July 2013 uBP Forecast - Summary - Q5+1 | U26: July 2013 uBP Forecast - Summary Q6
B27: £m 2011/12 prices | C27: 2008/09 | D27: 2009/10 | E27: 2010/11 | F27: 2011/12 | G27: 2012/13 | H27: 2013/14 | I27: 2014/15 | J27: 2015/16 | K27: 2016/17 | L27: 2017/18 | M27: 2018/19 | P27: £m 2011/12 prices | Q27: Total Q5+1 | R27: % of Total | S27: CAGR (Q5+1) | U27: £m 2011/12 prices | V27: Total Q6 | W27: % of Total | X27: CAGR (Q6)
B28: Security Costs (includes police) | C28: 176.8 | D28: 169.3 | E28: 163 | F28: 164.2 | G28: 162.4 | H28: 155.5 | I28: 161.2 | J28: 152.6 | K28: 141.8 | L28: 134.9 | M28: 133.8 | P28: =B28 -> Security Costs (includes police) | Q28: =SUM(C28:H28) -> 991.2 | R28: =Q28/$Q$39 -> 0.15770883 | S28: =((H28/C28)^(1/5))-1 -> -0.025347892 | U28: =P28 -> Security Costs (includes police) | V28: =SUM(I28:M28) -> 724.3 | W28: =V28/$V$39 -> 0.14140408 | X28: =((M28/H28)^(1/5))-1 -> -0.029612611
B29: Total Operational Staff | C29: 62.4 | D29: 53.7 | E29: 55.1 | F29: 55.5 | G29: 64.2 | H29: 72.5 | I29: 68.6 | J29: 63.8 | K29: 69 | L29: 59 | M29: 58.8 | P29: =B29 -> Total Operational Staff | Q29: =SUM(C29:H29) -> 363.4 | R29: =Q29/$Q$39 -> 0.057820207 | S29: =((H29/C29)^(1/5))-1 -> 0.030458921 | U29: =P29 -> Total Operational Staff | V29: =SUM(I29:M29) -> 319.2 | W29: =V29/$V$39 -> 0.062316973 | X29: =((M29/H29)^(1/5))-1 -> -0.041023723
B30: Facilities Management | C30: 171.5 | D30: 177.3 | E30: 158.1 | F30: 161.1 | G30: 164.7 | H30: 172.9 | I30: 191.7 | J30: 179.8 | K30: 173.5 | L30: 166.5 | M30: 167.5 | P30: =B30 -> Facilities Management | Q30: =SUM(C30:H30) -> 1005.6 | R30: =Q30/$Q$39 -> 0.16 | S30: =((H30/C30)^(1/5))-1 -> 0.0016273479 | U30: =P30 -> Facilities Management | V30: =SUM(I30:M30) -> 879 | W30: =V30/$V$39 -> 0.17160595 | X30: =((M30/H30)^(1/5))-1 -> -0.0063259149
B31: Utilities | C31: 94 | D31: 119.5 | E31: 98.3 | F31: 90.4 | G31: 84.9 | H31: 95.4 | I31: 105.5 | J31: 106.9 | K31: 105 | L31: 102.6 | M31: 103 | P31: =B31 -> Utilities | Q31: =SUM(C31:H31) -> 582.5 | R31: =Q31/$Q$39 -> 0.092680986 | S31: =((H31/C31)^(1/5))-1 -> 0.0029611348 | U31: =P31 -> Utilities | V31: =SUM(I31:M31) -> 523 | W31: =V31/$V$39 -> 0.10210456 | X31: =((M31/H31)^(1/5))-1 -> 0.01544819
B32: Rent and Rates | C32: 116.7 | D32: 124.5 | E32: 112.8 | F32: 119.6 | G32: 126.7 | H32: 124.8 | I32: 140.1 | J32: 140.8 | K32: 140 | L32: 161.7 | M32: 171.6 | P32: =B32 -> Rent and Rates | Q32: =SUM(C32:H32) -> 725.1 | R32: =Q32/$Q$39 -> 0.11536993 | S32: =((H32/C32)^(1/5))-1 -> 0.013511652 | U32: =P32 -> Rent and Rates | V32: =SUM(I32:M32) -> 754.2 | W32: =V32/$V$39 -> 0.14724142 | X32: =((M32/H32)^(1/5))-1 -> 0.065762757
B33: Other | C33: 155.8 | D33: 149.6 | E33: 142.2 | F33: 148.9 | G33: 137.1 | H33: 123 | I33: 120.1 | J33: 117.4 | K33: 115.8 | L33: 113.7 | M33: 113.5 | P33: =B33 -> Other | Q33: =SUM(C33:H33) -> 856.6 | R33: =Q33/$Q$39 -> 0.13629276 | S33: =((H33/C33)^(1/5))-1 -> -0.046177569 | U33: =P33 -> Other | V33: =SUM(I33:M33) -> 580.5 | W33: =V33/$V$39 -> 0.11333021 | X33: =((M33/H33)^(1/5))-1 -> -0.01594777
B34: Commercial | C34: 39.4 | D34: 52.4 | E34: 42.3 | F34: 42.6 | G34: 47.6 | H34: 48.7 | I34: 47.3 | J34: 49.1 | K34: 48.9 | L34: 48.4 | M34: 50.4 | P34: =B34 -> Commercial | Q34: =SUM(C34:H34) -> 273 | R34: =Q34/$Q$39 -> 0.043436754 | S34: =((H34/C34)^(1/5))-1 -> 0.043293611 | U34: =P34 -> Commercial | V34: =SUM(I34:M34) -> 244.1 | W34: =V34/$V$39 -> 0.047655304 | X34: =((M34/H34)^(1/5))-1 -> 0.0068860294
B35: Rail | C35: 71.2 | D35: 74.8 | E35: 72.3 | F35: 64.2 | G35: 63.6 | H35: 63 | I35: 57.3 | J35: 56.4 | K35: 56 | L35: 56.1 | M35: 55.3 | P35: =B35 -> Rail | Q35: =SUM(C35:H35) -> 409.1 | R35: =Q35/$Q$39 -> 0.065091488 | S35: =((H35/C35)^(1/5))-1 -> -0.024174616 | U35: =P35 -> Rail | V35: =SUM(I35:M35) -> 281.1 | W35: =V35/$V$39 -> 0.054878763 | X35: =((M35/H35)^(1/5))-1 -> -0.025735414
B36: Central Support Services | C36: 119.6 | D36: 105.9 | E36: 119.4 | F36: 118.9 | G36: 116.4 | H36: 121.3 | I36: 107.9 | J36: 102.5 | K36: 103.3 | L36: 102.6 | M36: 103.1 | P36: =B36 -> Central Support Services | Q36: =SUM(C36:H36) -> 701.5 | R36: =Q36/$Q$39 -> 0.11161496 | S36: =((H36/C36)^(1/5))-1 -> 0.0028267827 | U36: =P36 -> Central Support Services | V36: =SUM(I36:M36) -> 519.4 | W36: =V36/$V$39 -> 0.10140174 | X36: =((M36/H36)^(1/5))-1 -> -0.031990604
B37: Pensions | C37: 46.3 | D37: 56 | E37: 62.9 | F37: 64.1 | G37: 74.7 | H37: 73 | I37: 72.4 | J37: 60.3 | K37: 57.1 | L37: 54.5 | M37: 53.1 | P37: =B37 -> Pensions | Q37: =SUM(C37:H37) -> 377 | R37: =Q37/$Q$39 -> 0.059984089 | S37: =((H37/C37)^(1/5))-1 -> 0.095338553 | U37: =P37 -> Pensions | V37: =SUM(I37:M37) -> 297.4 | W37: =V37/$V$39 -> 0.058060989 | X37: =((M37/H37)^(1/5))-1 -> -0.061672743
B39: Total | C39: =SUM(C28:C37) -> 1053.7 | D39: =SUM(D28:D37) -> 1083 | E39: =SUM(E28:E37) -> 1026.4 | F39: =SUM(F28:F37) -> 1029.5 | G39: =SUM(G28:G37) -> 1042.3 | H39: =SUM(H28:H37) -> 1050.1 | I39: =SUM(I28:I37) -> 1072.1 | J39: =SUM(J28:J37) -> 1029.6 | ... M39: =SUM(M28:M37) -> 1010.1 | P39: =B39 -> Total | Q39: =SUM(C39:H39) -> 6285 | R39: =Q39/$Q$39 -> 1 | S39: =((H39/C39)^(1/5))-1 -> -0.00068424218 | U39: =P39 -> Total | V39: =SUM(I39:M39) -> 5122.2 | W39: =V39/$V$39 -> 1 | X39: =((M39/H39)^(1/5))-1 -> -0.0077371255
B41: Man Years | C41: =C55 -> 7907 | D41: =D55 -> 7406 | E41: =E55 -> 7457 | F41: =F55 -> 7464 | G41: =G55 -> 7152 | H41: =H55 -> 6893 | I41: =I55 -> 6580 | J41: =J55 -> 6337 | ... M41: =M55 -> 5812 | P41: Man Years | Q41: =SUM(C41:H41) -> 44279 | S41: =((H41/C41)^(1/5))-1 -> -0.027075123 | U41: Man Years | V41: =SUM(I41:M41) -> 30623 | X41: =((M41/H41)^(1/5))-1 -> -0.033540932
B42: Passengers (m) | C42: 65.9 | D42: 66.1 | E42: 66.1 | F42: =[2]CA!J18 -> 70.067623 | G42: =[2]CA!K18 -> 69.6 | H42: =[2]CA!L18 -> 68.8 | I42: 70.1 | J42: 70.8 | K42: 71.5 | L42: 72.3 | M42: 73 | P42: =B42 -> Passengers (m) | Q42: =SUM(C42:H42) -> 406.56762 | S42: =((H42/C42)^(1/5))-1 -> 0.0086502598 | U42: =P42 -> Passengers (m) | V42: =SUM(I42:M42) -> 357.7 | X42: =((M42/H42)^(1/5))-1 -> 0.011921642
B43: Total opex / passenger | C43: =C39/C42 -> 15.989378 | D43: =D39/D42 -> 16.384266 | E43: =E39/E42 -> 15.527988 | F43: =F39/F42 -> 14.692949 | G43: =G39/G42 -> 14.975575 | H43: =H39/H42 -> 15.263081 | I43: =I39/I42 -> 15.293866 | J43: =J39/J42 -> 14.542373 | ... M43: =M39/M42 -> 13.836986 | P43: =B43 -> Total opex / passenger | Q43: =Q39/Q42 -> 15.458683 | S43: =((H43/C43)^(1/5))-1 -> -0.0092544486 | U43: =P43 -> Total opex / passenger | V43: =V39/V42 -> 14.319821 | X43: =((M43/H43)^(1/5))-1 -> -0.019427164
B47: July 2013 uBP Forecast | C47: Q5 | H47: Q5+1 | I47: Q6 | P47: July 2013 uBP Forecast - Summary - Q5+1 | U47: July 2013 uBP Forecast - Summary Q6
B48: Man Years | C48: 2008/09 | D48: 2009/10 | E48: 2010/11 | F48: 2011/12 | G48: 2012/13 | H48: 2013/14 | I48: 2014/15 | J48: 2015/16 | K48: 2016/17 | L48: 2017/18 | M48: 2018/19 | P48: £m 2011/12 prices | Q48: Total Q5+1 | R48: % of Total | S48: CAGR (Q5+1) | U48: £m 2011/12 prices | V48: Total Q6 | W48: % of Total | X48: CAGR (Q6)
B49: Security | C49: " | D49: " | E49: " | F49: " | G49: " | H49: " | I49: " | J49: " | K49: " | L49: " | M49: " | P49: =B49 -> Security | Q49: " | R49: " | S49: " | U49: =P49 -> Security | V49: " | W49: " | X49: "
B50: Operations | C50: " | D50: " | E50: " | F50: " | G50: " | H50: " | I50: " | J50: " | K50: " | L50: " | M50: " | P50: =B50 -> Operations | Q50: " | R50: " | S50: " | U50: =P50 -> Operations | V50: " | W50: " | X50: "
B51: Facilities | C51: " | D51: " | E51: " | F51: " | G51: " | H51: " | I51: " | J51: " | K51: " | L51: " | M51: " | P51: =B51 -> Facilities | Q51: " | R51: " | S51: " | U51: =P51 -> Facilities | V51: " | W51: " | X51: "
B52: Commercial | C52: " | D52: " | E52: " | F52: " | G52: " | H52: " | I52: " | J52: " | K52: " | L52: " | M52: " | P52: =B52 -> Commercial | Q52: " | R52: " | S52: " | U52: =P52 -> Commercial | V52: " | W52: " | X52: "
B53: Rail | C53: " | D53: " | E53: " | F53: " | G53: " | H53: " | I53: " | J53: " | K53: " | L53: " | M53: " | P53: =B53 -> Rail | Q53: " | R53: " | S53: " | U53: =P53 -> Rail | V53: " | W53: " | X53: "
B54: Central Support | C54: " | D54: " | E54: " | F54: " | G54: " | H54: " | I54: " | J54: " | K54: " | L54: " | M54: " | P54: =B54 -> Central Support | Q54: " | R54: " | S54: " | U54: =P54 -> Central Support | V54: " | W54: " | X54: "
B55: Total | C55: 7907 | D55: 7406 | E55: 7457 | F55: 7464 | G55: 7152 | H55: 6893 | I55: 6580 | J55: 6337 | K55: 6034 | L55: 5860 | M55: 5812 | P55: =B55 -> Total | Q55: =SUM(C55:H55) -> 44279 | R55: =Q55/$Q$55 -> 1 | S55: =((H55/C55)^(1/5))-1 -> -0.027075123 | U55: =P55 -> Total | V55: =SUM(I55:M55) -> 30623 | W55: =V55/$V$55 -> 1 | X55: =((M55/H55)^(1/5))-1 -> -0.033540932
B58: End

Sheet HAL - aBP
B2: Heathrow - Alternative Business Plan - 19th July 2013
B4: July 2013 aBP Forecast | C4: Q5 | H4: Q5+1 | I4: Q6 | P4: July 2013 aBP Forecast - Summary - Q5+1 | U4: July 2013 aBP Forecast - Summary Q6
B5: £m nominal | C5: 2008/09 | D5: 2009/10 | E5: 2010/11 | F5: 2011/12 | G5: 2012/13 | H5: 2013/14 | I5: 2014/15 | J5: 2015/16 | K5: 2016/17 | L5: 2017/18 | M5: 2018/19 | P5: £m nominal | Q5: Total Q5+1 | R5: % of Total | S5: CAGR (Q5+1) | U5: £m nominal | V5: Total Q6 | W5: % of Total | X5: CAGR (Q6)
B6: =B28 -> Security Costs | C6: =C28*C$24 -> 160.7284 | D6: =D28*D$24 -> 153.91017 | E6: =E28*E$24 -> 155.53706 | F6: =F28*F$24 -> 164.2 | G6: =G28*G$24 -> 167.4178 | H6: =H28*H$24 -> 163.8739 | I6: =I28*I$24 -> 174.65185 | J6: =J28*J$24 -> 170.91401 | ... M6: =M28*M$24 -> 163.75363 | P6: =B6 -> Security Costs | Q6: =SUM(C6:H6) -> 965.66734 | R6: =Q6/$Q$17 -> 0.15746642 | S6: =((H6/C6)^(1/5))-1 -> 0.003883773 | U6: =P6 -> Security Costs | V6: =SUM(I6:M6) -> 833.19304 | W6: =V6/$V$17 -> 0.1411709 | X6: =((M6/H6)^(1/5))-1 -> -0.00014683602
B7: =B29 -> Total Operational Staff | C7: =C29*C$24 -> 56.727671 | D7: =D29*D$24 -> 48.818525 | E7: =E29*E$24 -> 52.577252 | F7: =F29*F$24 -> 55.5 | G7: =G29*G$24 -> 66.183638 | H7: =H29*H$24 -> 76.404231 | I7: =I29*I$24 -> 74.324547 | J7: =J29*J$24 -> 71.456841 | ... M7: =M29*M$24 -> 71.963476 | P7: =B7 -> Total Operational Staff | Q7: =SUM(C7:H7) -> 356.21132 | R7: =Q7/$Q$17 -> 0.058085552 | S7: =((H7/C7)^(1/5))-1 -> 0.061364338 | U7: =P7 -> Total Operational Staff | V7: =SUM(I7:M7) -> 367.4493 | W7: =V7/$V$17 -> 0.062258258 | X7: =((M7/H7)^(1/5))-1 -> -0.011904446
B8: =B30 -> Facilities Management | C8: =C30*C$24 -> 155.91019 | D8: =D30*D$24 -> 161.18295 | E8: =E30*E$24 -> 150.86141 | F8: =F30*F$24 -> 161.1 | G8: =G30*G$24 -> 169.78887 | H8: =H30*H$24 -> 182.21092 | I8: =I30*I$24 -> 207.1553 | J8: =J30*J$24 -> 200.81836 | ... M8: =M30*M$24 -> 204.0189 | P8: =B8 -> Facilities Management | Q8: =SUM(C8:H8) -> 981.05433 | R8: =Q8/$Q$17 -> 0.1599755 | S8: =((H8/C8)^(1/5))-1 -> 0.031668051 | U8: =P8 -> Facilities Management | V8: =SUM(I8:M8) -> 1008.8056 | W8: =V8/$V$17 -> 0.17092557 | X8: =((M8/H8)^(1/5))-1 -> 0.022867082
B9: =B31 -> Utilities | C9: =C31*C$24 -> 85.455146 | D9: =D31*D$24 -> 108.63713 | E9: =E31*E$24 -> 93.799343 | F9: =F31*F$24 -> 90.4 | G9: =G31*G$24 -> 87.523222 | H9: =H31*H$24 -> 100.53743 | I9: =I31*I$24 -> 114.30379 | J9: =J31*J$24 -> 119.72941 | ... M9: =M31*M$24 -> 126.05847 | P9: =B9 -> Utilities | Q9: =SUM(C9:H9) -> 566.35227 | R9: =Q9/$Q$17 -> 0.092352159 | S9: =((H9/C9)^(1/5))-1 -> 0.033041841 | U9: =P9 -> Utilities | V9: =SUM(I9:M9) -> 603.13267 | W9: =V9/$V$17 -> 0.10219094 | X9: =((M9/H9)^(1/5))-1 -> 0.046282235
B10: =B32 -> Rent and Rates | C10: =C32*C$24 -> 106.09165 | D10: =D32*D$24 -> 113.18261 | E10: =E32*E$24 -> 107.63546 | F10: =F32*F$24 -> 119.6 | G10: =G32*G$24 -> 130.61475 | H10: =H32*H$24 -> 131.52066 | I10: =I32*I$24 -> 151.79109 | J10: =J32*J$24 -> 157.69786 | ... M10: =M32*M$24 -> 210.01586 | P10: =B10 -> Rent and Rates | Q10: =SUM(C10:H10) -> 708.64514 | R10: =Q10/$Q$17 -> 0.11555513 | S10: =((H10/C10)^(1/5))-1 -> 0.043908788 | U10: =P10 -> Rent and Rates | V10: =SUM(I10:M10) -> 873.14621 | W10: =V10/$V$17 -> 0.14794031 | X10: =((M10/H10)^(1/5))-1 -> 0.098124601
B11: =B33 -> Other | C11: =C33*C$24 -> 141.63736 | D11: =D33*D$24 -> 136.00096 | E11: =E33*E$24 -> 135.68939 | F11: =F33*F$24 -> 148.9 | G11: =G33*G$24 -> 141.33609 | H11: =H33*H$24 -> 129.62373 | I11: =I33*I$24 -> 130.12213 | J11: =J33*J$24 -> 131.48955 | ... M11: =M33*M$24 -> 138.90909 | P11: =B11 -> Other | Q11: =SUM(C11:H11) -> 833.18752 | R11: =Q11/$Q$17 -> 0.13586361 | S11: =((H11/C11)^(1/5))-1 -> -0.017570625 | U11: =P11 -> Other | V11: =SUM(I11:M11) -> 669.21006 | W11: =V11/$V$17 -> 0.11338667 | X11: =((M11/H11)^(1/5))-1 -> 0.013932937
B12: =B34 -> Commercial | C12: =C34*C$24 -> 35.818433 | D12: =D34*D$24 -> 47.636698 | E12: =E34*E$24 -> 40.363298 | F12: =F34*F$24 -> 42.6 | G12: =G34*G$24 -> 49.070735 | H12: =H34*H$24 -> 51.322566 | I12: =I34*I$24 -> 51.2471 | J12: =J34*J$24 -> 54.992647 | ... M12: =M34*M$24 -> 61.68298 | P12: =B12 -> Commercial | Q12: =SUM(C12:H12) -> 266.81173 | R12: =Q12/$Q$17 -> 0.04350762 | S12: =((H12/C12)^(1/5))-1 -> 0.074583965 | U12: =P12 -> Commercial | V12: =SUM(I12:M12) -> 281.84438 | W12: =V12/$V$17 -> 0.047753908 | X12: =((M12/H12)^(1/5))-1 -> 0.037460084
B13: =B35 -> Rail | C13: =C35*C$24 -> 64.727727 | D13: =D35*D$24 -> 68.000478 | E13: =E35*E$24 -> 68.989751 | F13: =F35*F$24 -> 64.2 | G13: =G35*G$24 -> 65.5651 | H13: =H35*H$24 -> 66.392642 | I13: =I35*I$24 -> 62.081582 | J13: =J35*J$24 -> 63.168744 | ... M13: =M35*M$24 -> 67.679936 | P13: =B13 -> Rail | Q13: =SUM(C13:H13) -> 397.8757 | R13: =Q13/$Q$17 -> 0.064879549 | S13: =((H13/C13)^(1/5))-1 -> 0.0050922375 | U13: =P13 -> Rail | V13: =SUM(I13:M13) -> 324.19188 | W13: =V13/$V$17 -> 0.054928997 | X13: =((M13/H13)^(1/5))-1 -> 0.0038480914
B14: =B36 -> Central Support Services | C14: =C36*C$24 -> 108.72804 | D14: =D36*D$24 -> 96.273403 | E14: =E36*E$24 -> 113.93328 | F14: =F36*F$24 -> 118.9 | G14: =G36*G$24 -> 119.9965 | H14: =H36*H$24 -> 127.83218 | I14: =I36*I$24 -> 116.90406 | J14: =J36*J$24 -> 114.80135 | ... M14: =M36*M$24 -> 126.42563 | P14: =B14 -> Central Support Services | Q14: =SUM(C14:H14) -> 685.66341 | R14: =Q14/$Q$17 -> 0.11180761 | S14: =((H14/C14)^(1/5))-1 -> 0.032903459 | U14: =P14 -> Central Support Services | V14: =SUM(I14:M14) -> 599.44855 | W14: =V14/$V$17 -> 0.10156673 | X14: =((M14/H14)^(1/5))-1 -> -0.0022103715
B15: =B37 -> Pensions | C15: =C37*C$24 -> 42.091205 | D15: =D37*D$24 -> 50.909448 | E15: =E37*E$24 -> 60.020129 | F15: =F37*F$24 -> 64.1 | G15: =G37*G$24 -> 77.008065 | H15: =H37*H$24 -> 76.931157 | I15: =I37*I$24 -> 78.44165 | J15: =J37*J$24 -> 67.536795 | ... M15: =M37*M$24 -> 64.987425 | P15: =B15 -> Pensions | Q15: =SUM(C15:H15) -> 371.06 | R15: =Q15/$Q$17 -> 0.060506851 | S15: =((H15/C15)^(1/5))-1 -> 0.12818983 | U15: =P15 -> Pensions | V15: =SUM(I15:M15) -> 341.5953 | W15: =V15/$V$17 -> 0.057877723 | X15: =((M15/H15)^(1/5))-1 -> -0.033180473
B17: Total | C17: =C39*C$24 -> 957.91582 | D17: =D39*D$24 -> 984.55237 | E17: =E39*E$24 -> 979.40637 | F17: =F39*F$24 -> 1029.5 | G17: =G39*G$24 -> 1074.5048 | H17: =H39*H$24 -> 1106.6494 | I17: =I39*I$24 -> 1161.0231 | J17: =J39*J$24 -> 1152.6056 | ... M17: =M39*M$24 -> 1235.4954 | P17: =B17 -> Total | Q17: =SUM(C17:H17) -> 6132.5287 | R17: =Q17/$Q$17 -> 1 | S17: =((H17/C17)^(1/5))-1 -> 0.029287132 | U17: =P17 -> Total | V17: =SUM(I17:M17) -> 5902.017 | W17: =V17/$V$17 -> 1 | X17: =((M17/H17)^(1/5))-1 -> 0.022271408
B19: Man Years | C19: =C55 -> 7907 | D19: =D55 -> 7406 | E19: =E55 -> 7457 | F19: =F55 -> 7464 | G19: =G55 -> 7152 | H19: =H55 -> 6893 | I19: =I55 -> 6580 | J19: =J55 -> 6337 | ... M19: =M55 -> 5812 | P19: Man Years | Q19: =SUM(C19:H19) -> 44279 | S19: =((H19/C19)^(1/5))-1 -> -0.027075123 | U19: =P19 -> Man Years | V19: =V41 -> 30623 | X19: =((M19/H19)^(1/5))-1 -> -0.033540932
B20: Passengers (m) | C20: =C42 -> 65.9 | D20: =D42 -> 66.1 | E20: =E42 -> 66.1 | F20: =F42 -> 70.067623 | G20: =G42 -> 69.6 | H20: =H42 -> 68.8 | I20: =I42 -> 70.1 | J20: =J42 -> 70.8 | ... M20: =M42 -> 73 | P20: =B20 -> Passengers (m) | Q20: =SUM(C20:H20) -> 406.56762 | S20: =((H20/C20)^(1/5))-1 -> 0.0086502598 | U20: =P20 -> Passengers (m) | V20: =V42 -> 357.7 | X20: =((M20/H20)^(1/5))-1 -> 0.011921642
B21: Total opex / passenger | C21: =C17/C20 -> 14.5359 | D21: =D17/D20 -> 14.894892 | E21: =E17/E20 -> 14.81704 | F21: =F17/F20 -> 14.692949 | G21: =G17/G20 -> 15.438287 | H21: =H17/H20 -> 16.085021 | I21: =I17/I20 -> 16.562384 | J21: =J17/J20 -> 16.27974 | ... M21: =M17/M20 -> 16.924595 | P21: =B21 -> Total opex / passenger | Q21: =Q17/Q20 -> 15.083662 | S21: =((H21/C21)^(1/5))-1 -> 0.020459889 | U21: =P21 -> Total opex / passenger | V21: =V17/V20 -> 16.499908 | X21: =((M21/H21)^(1/5))-1 -> 0.010227833
B24: Price Base Conversion 11/12 to Nominal | C24: =RPI!$T101/RPI!$T$103 -> 0.90909729 | D24: =RPI!$T101/RPI!$T$103 -> 0.90909729 | E24: =RPI!$T102/RPI!$T$103 -> 0.95421509 | F24: =RPI!$T103/RPI!$T$103 -> 1 | G24: =RPI!$V104/RPI!$T$103 -> 1.0308978 | H24: =RPI!$V105/RPI!$T$103 -> 1.0538515 | I24: =RPI!$V106/RPI!$T$103 -> 1.0834482 | J24: =RPI!$V107/RPI!$T$103 -> 1.1200132 | K24: =RPI!$V108/RPI!$T$103 -> 1.1536136 | L24: =RPI!$V109/RPI!$T$103 -> 1.188222 | M24: =RPI!$V110/RPI!$T$103 -> 1.2238686
B26: July 2013 aBP Forecast | C26: Q5 | H26: Q5+1 | I26: Q6 | P26: July 2013 aBP Forecast - Summary - Q5+1 | U26: July 2013 aBP Forecast - Summary Q6
B27: £m 2011/12 prices | C27: 2008/09 | D27: 2009/10 | E27: 2010/11 | F27: 2011/12 | G27: 2012/13 | H27: 2013/14 | I27: 2014/15 | J27: 2015/16 | K27: 2016/17 | L27: 2017/18 | M27: 2018/19 | P27: £m 2011/12 prices | Q27: Total Q5+1 | R27: % of Total | S27: CAGR (Q5+1) | U27: £m 2011/12 prices | V27: Total Q6 | W27: % of Total | X27: CAGR (Q6)
B28: Security Costs | C28: 176.8 | D28: 169.3 | E28: 163 | F28: 164.2 | G28: 162.4 | H28: 155.5 | I28: 161.2 | J28: 152.6 | K28: 141.8 | L28: 134.9 | M28: 133.8 | P28: =B28 -> Security Costs | Q28: =SUM(C28:H28) -> 991.2 | R28: =Q28/$Q$39 -> 0.15770883 | S28: =((H28/C28)^(1/5))-1 -> -0.025347892 | U28: =P28 -> Security Costs | V28: =SUM(I28:M28) -> 724.3 | W28: =V28/$V$39 -> 0.14147037 | X28: =((M28/H28)^(1/5))-1 -> -0.029612611
B29: Total Operational Staff | C29: 62.4 | D29: 53.7 | E29: 55.1 | F29: 55.5 | G29: 64.2 | H29: 72.5 | I29: 68.6 | J29: 63.8 | K29: 69 | L29: 59 | M29: 58.8 | P29: =B29 -> Total Operational Staff | Q29: =SUM(C29:H29) -> 363.4 | R29: =Q29/$Q$39 -> 0.057820207 | S29: =((H29/C29)^(1/5))-1 -> 0.030458921 | U29: =P29 -> Total Operational Staff | V29: =SUM(I29:M29) -> 319.2 | W29: =V29/$V$39 -> 0.062346185 | X29: =((M29/H29)^(1/5))-1 -> -0.041023723
B30: Facilities Management | C30: 171.5 | D30: 177.3 | E30: 158.1 | F30: 161.1 | G30: 164.7 | H30: 172.9 | I30: 191.2 | J30: 179.3 | K30: 173.2 | L30: 165.8 | M30: 166.7 | P30: =B30 -> Facilities Management | Q30: =SUM(C30:H30) -> 1005.6 | R30: =Q30/$Q$39 -> 0.16 | S30: =((H30/C30)^(1/5))-1 -> 0.0016273479 | U30: =P30 -> Facilities Management | V30: =SUM(I30:M30) -> 876.2 | W30: =V30/$V$39 -> 0.1711395 | X30: =((M30/H30)^(1/5))-1 -> -0.0072769147
B31: Utilities | C31: 94 | D31: 119.5 | E31: 98.3 | F31: 90.4 | G31: 84.9 | H31: 95.4 | I31: 105.5 | J31: 106.9 | K31: 105 | L31: 102.6 | M31: 103 | P31: =B31 -> Utilities | Q31: =SUM(C31:H31) -> 582.5 | R31: =Q31/$Q$39 -> 0.092680986 | S31: =((H31/C31)^(1/5))-1 -> 0.0029611348 | U31: =P31 -> Utilities | V31: =SUM(I31:M31) -> 523 | W31: =V31/$V$39 -> 0.10215243 | X31: =((M31/H31)^(1/5))-1 -> 0.01544819
B32: Rent and Rates | C32: 116.7 | D32: 124.5 | E32: 112.8 | F32: 119.6 | G32: 126.7 | H32: 124.8 | I32: 140.1 | J32: 140.8 | K32: 140 | L32: 161.7 | M32: 171.6 | P32: =B32 -> Rent and Rates | Q32: =SUM(C32:H32) -> 725.1 | R32: =Q32/$Q$39 -> 0.11536993 | S32: =((H32/C32)^(1/5))-1 -> 0.013511652 | U32: =P32 -> Rent and Rates | V32: =SUM(I32:M32) -> 754.2 | W32: =V32/$V$39 -> 0.14731044 | X32: =((M32/H32)^(1/5))-1 -> 0.065762757
B33: Other | C33: 155.8 | D33: 149.6 | E33: 142.2 | F33: 148.9 | G33: 137.1 | H33: 123 | I33: 120.1 | J33: 117.4 | K33: 115.8 | L33: 113.7 | M33: 113.5 | P33: =B33 -> Other | Q33: =SUM(C33:H33) -> 856.6 | R33: =Q33/$Q$39 -> 0.13629276 | S33: =((H33/C33)^(1/5))-1 -> -0.046177569 | U33: =P33 -> Other | V33: =SUM(I33:M33) -> 580.5 | W33: =V33/$V$39 -> 0.11338334 | X33: =((M33/H33)^(1/5))-1 -> -0.01594777
B34: Commercial | C34: 39.4 | D34: 52.4 | E34: 42.3 | F34: 42.6 | G34: 47.6 | H34: 48.7 | I34: 47.3 | J34: 49.1 | K34: 48.9 | L34: 48.4 | M34: 50.4 | P34: =B34 -> Commercial | Q34: =SUM(C34:H34) -> 273 | R34: =Q34/$Q$39 -> 0.043436754 | S34: =((H34/C34)^(1/5))-1 -> 0.043293611 | U34: =P34 -> Commercial | V34: =SUM(I34:M34) -> 244.1 | W34: =V34/$V$39 -> 0.047677644 | X34: =((M34/H34)^(1/5))-1 -> 0.0068860294
B35: Rail | C35: 71.2 | D35: 74.8 | E35: 72.3 | F35: 64.2 | G35: 63.6 | H35: 63 | I35: 57.3 | J35: 56.4 | K35: 56 | L35: 56.1 | M35: 55.3 | P35: =B35 -> Rail | Q35: =SUM(C35:H35) -> 409.1 | R35: =Q35/$Q$39 -> 0.065091488 | S35: =((H35/C35)^(1/5))-1 -> -0.024174616 | U35: =P35 -> Rail | V35: =SUM(I35:M35) -> 281.1 | W35: =V35/$V$39 -> 0.054904488 | X35: =((M35/H35)^(1/5))-1 -> -0.025735414
B36: Central Support Services | C36: 119.6 | D36: 105.9 | E36: 119.4 | F36: 118.9 | G36: 116.4 | H36: 121.3 | I36: 107.9 | J36: 102.5 | K36: 103.3 | L36: 102.8 | M36: 103.3 | P36: =B36 -> Central Support Services | Q36: =SUM(C36:H36) -> 701.5 | R36: =Q36/$Q$39 -> 0.11161496 | S36: =((H36/C36)^(1/5))-1 -> 0.0028267827 | U36: =P36 -> Central Support Services | V36: =SUM(I36:M36) -> 519.8 | W36: =V36/$V$39 -> 0.1015274 | X36: =((M36/H36)^(1/5))-1 -> -0.031615334
B37: Pensions | C37: 46.3 | D37: 56 | E37: 62.9 | F37: 64.1 | G37: 74.7 | H37: 73 | I37: 72.4 | J37: 60.3 | K37: 57.1 | L37: 54.5 | M37: 53.1 | P37: =B37 -> Pensions | Q37: =SUM(C37:H37) -> 377 | R37: =Q37/$Q$39 -> 0.059984089 | S37: =((H37/C37)^(1/5))-1 -> 0.095338553 | U37: =P37 -> Pensions | V37: =SUM(I37:M37) -> 297.4 | W37: =V37/$V$39 -> 0.058088207 | X37: =((M37/H37)^(1/5))-1 -> -0.061672743
B39: Total | C39: =SUM(C28:C37) -> 1053.7 | D39: =SUM(D28:D37) -> 1083 | E39: =SUM(E28:E37) -> 1026.4 | F39: =SUM(F28:F37) -> 1029.5 | G39: =SUM(G28:G37) -> 1042.3 | H39: =SUM(H28:H37) -> 1050.1 | I39: =SUM(I28:I37) -> 1071.6 | J39: =SUM(J28:J37) -> 1029.1 | ... M39: =SUM(M28:M37) -> 1009.5 | P39: =B39 -> Total | Q39: =SUM(C39:H39) -> 6285 | R39: =Q39/$Q$39 -> 1 | S39: =((H39/C39)^(1/5))-1 -> -0.00068424218 | U39: =P39 -> Total | V39: =SUM(I39:M39) -> 5119.8 | W39: =V39/$V$39 -> 1 | X39: =((M39/H39)^(1/5))-1 -> -0.0078550345
B41: Man Years | C41: =C55 -> 7907 | D41: =D55 -> 7406 | E41: =E55 -> 7457 | F41: =F55 -> 7464 | G41: =G55 -> 7152 | H41: =H55 -> 6893 | I41: =I55 -> 6580 | J41: =J55 -> 6337 | ... M41: =M55 -> 5812 | P41: Man Years | Q41: =SUM(C41:H41) -> 44279 | S41: =((H41/C41)^(1/5))-1 -> -0.027075123 | U41: Man Years | V41: =SUM(I41:M41) -> 30623 | X41: =((M41/H41)^(1/5))-1 -> -0.033540932
B42: Passengers (m) | C42: 65.9 | D42: 66.1 | E42: 66.1 | F42: =[2]CA!J18 -> 70.067623 | G42: =[2]CA!K18 -> 69.6 | H42: =[2]CA!L18 -> 68.8 | I42: 70.1 | J42: 70.8 | K42: 71.5 | L42: 72.3 | M42: 73 | P42: =B42 -> Passengers (m) | Q42: =SUM(C42:H42) -> 406.56762 | S42: =((H42/C42)^(1/5))-1 -> 0.0086502598 | U42: =P42 -> Passengers (m) | V42: =SUM(I42:M42) -> 357.7 | X42: =((M42/H42)^(1/5))-1 -> 0.011921642
B43: Total opex / passenger | C43: =C39/C42 -> 15.989378 | D43: =D39/D42 -> 16.384266 | E43: =E39/E42 -> 15.527988 | F43: =F39/F42 -> 14.692949 | G43: =G39/G42 -> 14.975575 | H43: =H39/H42 -> 15.263081 | I43: =I39/I42 -> 15.286733 | J43: =J39/J42 -> 14.535311 | ... M43: =M39/M42 -> 13.828767 | P43: =B43 -> Total opex / passenger | Q43: =Q39/Q42 -> 15.458683 | S43: =((H43/C43)^(1/5))-1 -> -0.0092544486 | U43: =P43 -> Total opex / passenger | V43: =V39/V42 -> 14.313112 | X43: =((M43/H43)^(1/5))-1 -> -0.019543684
B47: July 2013 aBP Forecast | C47: Q5 | H47: Q5+1 | I47: Q6 | P47: July 2013 aBP Forecast - Summary - Q5+1 | U47: July 2013 aBP Forecast - Summary Q6
B48: Man Years | C48: 2008/09 | D48: 2009/10 | E48: 2010/11 | F48: 2011/12 | G48: 2012/13 | H48: 2013/14 | I48: 2014/15 | J48: 2015/16 | K48: 2016/17 | L48: 2017/18 | M48: 2018/19 | P48: £m 2011/12 prices | Q48: Total Q5+1 | R48: % of Total | S48: CAGR (Q5+1) | U48: £m 2011/12 prices | V48: Total Q6 | W48: % of Total | X48: CAGR (Q6)
B49: Security | C49: " | D49: " | E49: " | F49: " | G49: " | H49: " | I49: " | J49: " | K49: " | L49: " | M49: " | P49: =B49 -> Security | Q49: " | R49: " | S49: " | U49: =P49 -> Security | V49: " | W49: " | X49: "
B50: Operations | C50: " | D50: " | E50: " | F50: " | G50: " | H50: " | I50: " | J50: " | K50: " | L50: " | M50: " | P50: =B50 -> Operations | Q50: " | R50: " | S50: " | U50: =P50 -> Operations | V50: " | W50: " | X50: "
B51: Facilities | C51: " | D51: " | E51: " | F51: " | G51: " | H51: " | I51: " | J51: " | K51: " | L51: " | M51: " | P51: =B51 -> Facilities | Q51: " | R51: " | S51: " | U51: =P51 -> Facilities | V51: " | W51: " | X51: "
B52: Commercial | C52: " | D52: " | E52: " | F52: " | G52: " | H52: " | I52: " | J52: " | K52: " | L52: " | M52: " | P52: =B52 -> Commercial | Q52: " | R52: " | S52: " | U52: =P52 -> Commercial | V52: " | W52: " | X52: "
B53: Rail | C53: " | D53: " | E53: " | F53: " | G53: " | H53: " | I53: " | J53: " | K53: " | L53: " | M53: " | P53: =B53 -> Rail | Q53: " | R53: " | S53: " | U53: =P53 -> Rail | V53: " | W53: " | X53: "
B54: Central Support | C54: " | D54: " | E54: " | F54: " | G54: " | H54: " | I54: " | J54: " | K54: " | L54: " | M54: " | P54: =B54 -> Central Support | Q54: " | R54: " | S54: " | U54: =P54 -> Central Support | V54: " | W54: " | X54: "
B55: Total | C55: 7907 | D55: 7406 | E55: 7457 | F55: 7464 | G55: 7152 | H55: 6893 | I55: 6580 | J55: 6337 | K55: 6034 | L55: 5860 | M55: 5812 | P55: =B55 -> Total | Q55: =SUM(C55:H55) -> 44279 | R55: =Q55/$Q$55 -> 1 | S55: =((H55/C55)^(1/5))-1 -> -0.027075123 | U55: =P55 -> Total | V55: =SUM(I55:M55) -> 30623 | W55: =V55/$V$55 -> 1 | X55: =((M55/H55)^(1/5))-1 -> -0.033540932
B59: July 2013 aBP Forecast | C59: Q5 | H59: Q5+1 | I59: Q6
B61: Terminal Area M2 | C61: 2008/09 | D61: 2009/10 | E61: 2010/11 | F61: 2011/12 | G61: 2012/13 | H61: 2013/14 | I61: 2014/15 | J61: 2015/16 | K61: 2016/17 | L61: 2017/18 | M61: 2018/19
B62: T1 | F62: " | G62: " | H62: " | I62: " | J62: " | K62: " | L62: " | M62: "
B63: T2 | F63: " | G63: " | H63: " | I63: " | J63: " | K63: " | L63: " | M63: "
B64: T3 | F64: " | G64: " | H64: " | I64: " | J64: " | K64: " | L64: " | M64: "
B65: T4 | F65: " | G65: " | H65: " | I65: " | J65: " | K65: " | L65: " | M65: "
B66: T5 | F66: " | G66: " | H66: " | I66: " | J66: " | K66: " | L66: " | M66: "
B68: Total | F68: " | G68: " | H68: " | I68: " | J68: " | K68: " | L68: " | M68: "
B69: Change | G69: " | H69: " | I69: " | J69: " | K69: " | L69: " | M69: "
B70: % Change | G70: " | H70: " | I70: " | J70: " | K70: " | L70: " | M70: "
B72: CAA Reconcilliation
B75: Forecasts | C75: Q5 | H75: Q5+1 | I75: Q6 | U75: July 2013 aBP Forecast - Summary Q6
C76: 2008/09 | D76: 2009/10 | E76: 2010/11 | F76: 2011/12 | G76: 2012/13 | H76: 2013/14 | I76: 2014/15 | J76: 2015/16 | K76: 2016/17 | L76: 2017/18 | M76: 2018/19 | U76: £m 2011/12 prices | V76: Total Q6 | W76: % of Total | X76: CAGR (Q6)
B77: ABP Rates cost forecast | E77: 98.5 | H77: 108.8 | I77: 123.9 | J77: 126.3 | K77: 125.5 | L77: 147.6 | M77: 157.3 | U77: =B77 -> ABP Rates cost forecast | V77: =SUM(I77:M77) -> 680.6 | W77: =V77/$V$55 -> 0.022225125 | X77: =((M77/H77)^(1/5))-1 -> 0.076514702
B78: CAA Forecast | H78: =H77+'Other Opex'!E32 -> 108.8 | I78: =I77+'Other Opex'!F32 -> 123.9 | J78: =J77+'Other Opex'!G32 -> 126.3 | K78: =K77+'Other Opex'!H32 -> 125.5 | L78: =L77+'Other Opex'!I32 -> 136.9 | M78: =M77+'Other Opex'!J32 -> 136.8 | U78: =B78 -> CAA Forecast | V78: =SUM(I78:M78) -> 649.4 | W78: =V78/$V$55 -> 0.021206283 | X78: =((M78/H78)^(1/5))-1 -> 0.046866832
B81: End

Sheet CAA>>

Sheet HAL - CAA - ip
B2: Heathrow - CAA Allowance - April 2013 - Initial Proposals
B4: This sheet shows the CAA's initial proposals for HAL's opex allowance over Q6.
B6: Bottom Up Projections
B8: CAA March 2013 HAL Projections | C8: Q5 | H8: Q5+1 | I8: Q6 | P8: CAA March 2013 HAL Projections - Summary Q5+1 | V8: CAA March 2013 HAL Projections - Summary Q6
B9: £m nominal | C9: 2008/09 | D9: 2009/10 | E9: 2010/11 | F9: 2011/12 | G9: 2012/13 | H9: 2013/14 | I9: 2014/15 | J9: 2015/16 | K9: 2016/17 | L9: 2017/18 | M9: 2018/19 | P9: £m nominal | Q9: Total Q5+1 | R9: % of Total | S9: CAGR (Q5+1) | T9: Opex per Pax | V9: £m nominal | W9: Total Q6 | X9: % of Total | Y9: CAGR (Q6) | Z9: Opex per Pax | AA9: Relative to 2011/12
B10: Passengers (m) | C10: ='[3]HAL - CAA'!C10 -> 65.9 | D10: ='[3]HAL - CAA'!D10 -> 66.1 | E10: ='[3]HAL - CAA'!E10 -> 66.1 | F10: ='[3]HAL - CAA'!F10 -> 70.067623 | G10: ='[3]HAL - CAA'!G10 -> 69.6 | H10: ='[3]HAL - CAA'!H10 -> 68.8 | I10: ='[3]HAL - CAA'!I10 -> 69.494122 | J10: ='[3]HAL - CAA'!J10 -> 70.256156 | ... M10: ='[3]HAL - CAA'!M10 -> 72.602541 | P10: Passengers (m) | Q10: ='[3]HAL - CAA'!Q10 -> 406.56762 | R10: ='[3]HAL - CAA'!R10 -> 0 | S10: ='[3]HAL - CAA'!S10 -> 0.0086502598 | T10: ='[3]HAL - CAA'!T10 -> 0 | V10: Passengers (m) | W10: ='[3]HAL - CAA'!W10 -> 355.19129 | X10: ='[3]HAL - CAA'!X10 -> 0 | Y10: ='[3]HAL - CAA'!Y10 -> 0.010817324 | Z10: ='[3]HAL - CAA'!Z10 -> 0 | AA10: ='[3]HAL - CAA'!AA10 -> 0
B12: Total IBP | C12: 940.05218 | D12: 949.75253 | E12: 944.12792 | F12: 993.30895 | G12: 1064 | H12: 1056.4152 | I12: ='[3]HAL - CAA'!I12 -> 1194.959 | J12: ='[3]HAL - CAA'!J12 -> 1230.9416 | K12: ='[3]HAL - CAA'!K12 -> 1199.6085 | L12: ='[3]HAL - CAA'!L12 -> 1230.9863 | M12: ='[3]HAL - CAA'!M12 -> 1256.044 | P12: Total IBP | Q12: ='[3]HAL - CAA'!Q12 -> 5946.0317 | R12: ='[3]HAL - CAA'!R12 -> 0.97029602 | S12: ='[3]HAL - CAA'!S12 -> 0.02329964 | T12: ='[3]HAL - CAA'!T12 -> 14.624951 | V12: Total IBP | W12: ='[3]HAL - CAA'!W12 -> 6112.5394 | X12: ='[3]HAL - CAA'!X12 -> 1.0127765 | Y12: ='[3]HAL - CAA'!Y12 -> 0.035542101 | Z12: ='[3]HAL - CAA'!Z12 -> 17.209148 | AA12: ='[3]HAL - CAA'!AA12 -> 0.028820924
B13: Total FBP | C13: 957.91582 | D13: 984.55237 | E13: 979.40637 | F13: 1029.5 | G13: 1074.5048 | H13: 1103.8782 | I13: ='[3]HAL - CAA'!I13 -> 1172.0743 | J13: ='[3]HAL - CAA'!J13 -> 1175.9018 | K13: ='[3]HAL - CAA'!K13 -> 1192.8364 | L13: ='[3]HAL - CAA'!L13 -> 1223.7498 | M13: ='[3]HAL - CAA'!M13 -> 1270.8652 | P13: Total FBP | Q13: ='[3]HAL - CAA'!Q13 -> 6128.0595 | R13: ='[3]HAL - CAA'!R13 -> 1 | S13: ='[3]HAL - CAA'!S13 -> 0.028454415 | T13: ='[3]HAL - CAA'!T13 -> 15.07267 | V13: Total FBP | W13: ='[3]HAL - CAA'!W13 -> 6035.4276 | X13: ='[3]HAL - CAA'!X13 -> 1 | Y13: ='[3]HAL - CAA'!Y13 -> 0.028891032 | Z13: ='[3]HAL - CAA'!Z13 -> 16.992048 | AA13: ='[3]HAL - CAA'!AA13 -> 0.030546496
B15: Efficiency Estimate (Low Stretch) | I15: ='[3]HAL - CAA'!I15 -> -10.114094 | J15: ='[3]HAL - CAA'!J15 -> -13.950524 | K15: ='[3]HAL - CAA'!K15 -> -17.523661 | L15: ='[3]HAL - CAA'!L15 -> -21.575887 | M15: ='[3]HAL - CAA'!M15 -> -26.778831 | P15: Efficiency Estimate (Low Stretch) | Q15: ='[3]HAL - CAA'!Q15 -> 0 | R15: ='[3]HAL - CAA'!R15 -> 0 | S15: ='[3]HAL - CAA'!S15 -> 0 | T15: ='[3]HAL - CAA'!T15 -> 0 | V15: Efficiency Estimate (Low Stretch) | W15: ='[3]HAL - CAA'!W15 -> -89.942997 | X15: ='[3]HAL - CAA'!X15 -> -0.014902506 | Y15: ='[3]HAL - CAA'!Y15 -> na | Z15: ='[3]HAL - CAA'!Z15 -> -0.25322411 | AA15: ='[3]HAL - CAA'!AA15 -> na
B16: Efficiency Estimate (Mid Stretch) | I16: ='[3]HAL - CAA'!I16 -> -17.598815 | J16: ='[3]HAL - CAA'!J16 -> -22.586957 | K16: ='[3]HAL - CAA'!K16 -> -46.559357 | L16: ='[3]HAL - CAA'!L16 -> -70.535538 | M16: ='[3]HAL - CAA'!M16 -> -99.227028 | P16: Efficiency Estimate (Mid Stretch) | Q16: ='[3]HAL - CAA'!Q16 -> 0 | R16: ='[3]HAL - CAA'!R16 -> 0 | S16: ='[3]HAL - CAA'!S16 -> 0 | T16: ='[3]HAL - CAA'!T16 -> 0 | V16: Efficiency Estimate (Mid Stretch) | W16: ='[3]HAL - CAA'!W16 -> -256.50769 | X16: ='[3]HAL - CAA'!X16 -> -0.042500335 | Y16: ='[3]HAL - CAA'!Y16 -> na | Z16: ='[3]HAL - CAA'!Z16 -> -0.72216775 | AA16: ='[3]HAL - CAA'!AA16 -> na
B17: Efficiency Estimate (High Stretch) | I17: ='[3]HAL - CAA'!I17 -> -23.371688 | J17: ='[3]HAL - CAA'!J17 -> -38.346673 | K17: ='[3]HAL - CAA'!K17 -> -57.760187 | L17: ='[3]HAL - CAA'!L17 -> -90.977862 | M17: ='[3]HAL - CAA'!M17 -> -132.14427 | P17: Efficiency Estimate (High Stretch) | Q17: ='[3]HAL - CAA'!Q17 -> 0 | R17: ='[3]HAL - CAA'!R17 -> 0 | S17: ='[3]HAL - CAA'!S17 -> 0 | T17: ='[3]HAL - CAA'!T17 -> 0 | V17: Efficiency Estimate (High Stretch) | W17: ='[3]HAL - CAA'!W17 -> -342.60068 | X17: ='[3]HAL - CAA'!X17 -> -0.056764939 | Y17: ='[3]HAL - CAA'!Y17 -> na | Z17: ='[3]HAL - CAA'!Z17 -> -0.96455259 | AA17: ='[3]HAL - CAA'!AA17 -> na
B19: Opex Forecast (Low Stretch) | I19: ='[3]HAL - CAA'!I19 -> 1161.9602 | J19: ='[3]HAL - CAA'!J19 -> 1161.9513 | K19: ='[3]HAL - CAA'!K19 -> 1175.3128 | L19: ='[3]HAL - CAA'!L19 -> 1202.1739 | M19: ='[3]HAL - CAA'!M19 -> 1244.0864 | P19: Opex Forecast (Low Stretch) | Q19: ='[3]HAL - CAA'!Q19 -> 0 | R19: ='[3]HAL - CAA'!R19 -> 0 | V19: Opex Forecast (Low Stretch) | W19: ='[3]HAL - CAA'!W19 -> 5945.4846 | X19: ='[3]HAL - CAA'!X19 -> 0.98509749 | Y19: ='[3]HAL - CAA'!Y19 -> 0.024517995 | Z19: ='[3]HAL - CAA'!Z19 -> 16.738824 | AA19: ='[3]HAL - CAA'!AA19 -> 0.027415969
B20: Opex Forecast (Mid Stretch) | I20: ='[3]HAL - CAA'!I20 -> 1154.4754 | J20: ='[3]HAL - CAA'!J20 -> 1153.3149 | K20: ='[3]HAL - CAA'!K20 -> 1146.2771 | L20: ='[3]HAL - CAA'!L20 -> 1153.2143 | M20: ='[3]HAL - CAA'!M20 -> 1171.6382 | P20: Opex Forecast (Mid Stretch) | Q20: ='[3]HAL - CAA'!Q20 -> 0 | R20: ='[3]HAL - CAA'!R20 -> 0 | V20: Opex Forecast (Mid Stretch) | W20: ='[3]HAL - CAA'!W20 -> 5778.9199 | X20: ='[3]HAL - CAA'!X20 -> 0.95749966 | Y20: ='[3]HAL - CAA'!Y20 -> 0.012297553 | Z20: ='[3]HAL - CAA'!Z20 -> 16.269881 | AA20: ='[3]HAL - CAA'!AA20 -> 0.018647399
B21: Opex Forecast (High Stretch) | I21: ='[3]HAL - CAA'!I21 -> 1148.7026 | J21: ='[3]HAL - CAA'!J21 -> 1137.5552 | K21: ='[3]HAL - CAA'!K21 -> 1135.0763 | L21: ='[3]HAL - CAA'!L21 -> 1132.772 | M21: ='[3]HAL - CAA'!M21 -> 1138.7209 | P21: Opex Forecast (High Stretch) | Q21: ='[3]HAL - CAA'!Q21 -> 0 | R21: ='[3]HAL - CAA'!R21 -> 0 | V21: Opex Forecast (High Stretch) | W21: ='[3]HAL - CAA'!W21 -> 5692.8269 | X21: ='[3]HAL - CAA'!X21 -> 0.94323506 | Y21: ='[3]HAL - CAA'!Y21 -> 0.0065444194 | Z21: ='[3]HAL - CAA'!Z21 -> 16.027496 | AA21: ='[3]HAL - CAA'!AA21 -> 0.014508875
B23: Opex per pax IBP | C23: ='[3]HAL - CAA'!C23 -> 14.264828 | D23: ='[3]HAL - CAA'!D23 -> 14.368419 | E23: ='[3]HAL - CAA'!E23 -> 14.283327 | F23: ='[3]HAL - CAA'!F23 -> 14.176433 | G23: ='[3]HAL - CAA'!G23 -> 15.287356 | H23: ='[3]HAL - CAA'!H23 -> 15.331252 | I23: ='[3]HAL - CAA'!I23 -> 17.195109 | J23: ='[3]HAL - CAA'!J23 -> 17.520764 | ... M23: ='[3]HAL - CAA'!M23 -> 17.300277
B24: Opex per pax FBP | C24: ='[3]HAL - CAA'!C24 -> 14.5359 | D24: ='[3]HAL - CAA'!D24 -> 14.894892 | E24: ='[3]HAL - CAA'!E24 -> 14.81704 | F24: ='[3]HAL - CAA'!F24 -> 14.692949 | G24: ='[3]HAL - CAA'!G24 -> 15.438287 | H24: ='[3]HAL - CAA'!H24 -> 16.02006 | I24: ='[3]HAL - CAA'!I24 -> 16.865804 | J24: ='[3]HAL - CAA'!J24 -> 16.73735 | ... M24: ='[3]HAL - CAA'!M24 -> 17.504418
B26: Opex per pax (Low Stretch) | I26: ='[3]HAL - CAA'!I26 -> 16.720265 | J26: ='[3]HAL - CAA'!J26 -> 16.538783 | K26: ='[3]HAL - CAA'!K26 -> 16.547714 | L26: ='[3]HAL - CAA'!L26 -> 16.74039 | M26: ='[3]HAL - CAA'!M26 -> 17.135576
B27: Opex per pax (Mid Stretch) | I27: ='[3]HAL - CAA'!I27 -> 16.624879 | J27: ='[3]HAL - CAA'!J27 -> 16.36516 | K27: ='[3]HAL - CAA'!K27 -> 16.26446 | L27: ='[3]HAL - CAA'!L27 -> 16.257175 | M27: ='[3]HAL - CAA'!M27 -> 16.409944
B28: Opex per pax (High Stretch) | I28: ='[3]HAL - CAA'!I28 -> 16.529493 | J28: ='[3]HAL - CAA'!J28 -> 16.191537 | K28: ='[3]HAL - CAA'!K28 -> 15.981207 | L28: ='[3]HAL - CAA'!L28 -> 15.773961 | M28: ='[3]HAL - CAA'!M28 -> 15.684312
B31: Price Base Conversion 11/12 to Nominal | C31: 0.90909729 | D31: 0.90909729 | E31: 0.95421509 | F31: 1 | G31: 1.0308978 | H31: 1.0512125 | I31: 1.0834482 | J31: 1.1200132 | K31: 1.1536136 | L31: 1.188222 | M31: 1.2238686
B33: CAA March 2013 HAL Projections | C33: Q5 | H33: Q5+1 | I33: Q6 | P33: CAA March 2013 HAL Projections - Summary Q5+1 | V33: CAA March 2013 HAL Projections - Summary Q6
B34: £m 2011/12 prices | C34: 2008/09 | D34: 2009/10 | E34: 2010/11 | F34: 2011/12 | G34: 2012/13 | H34: 2013/14 | I34: 2014/15 | J34: 2015/16 | K34: 2016/17 | L34: 2017/18 | M34: 2018/19 | P34: £m 2011/12 prices | Q34: Total Q5+1 | R34: % of FBP | S34: CAGR (Q5+1) | T34: Opex per Pax | V34: £m 2011/12 prices | W34: Total Q6 | X34: % of FBP | Y34: CAGR (Q6) | Z34: Opex per Pax | AA34: Relative to 2011/12
B35: Passengers (m) | C35: ='[3]HAL - CAA'!C35 -> 65.9 | D35: ='[3]HAL - CAA'!D35 -> 66.1 | E35: ='[3]HAL - CAA'!E35 -> 66.1 | F35: ='[3]HAL - CAA'!F35 -> 70.067623 | G35: ='[3]HAL - CAA'!G35 -> 69.6 | H35: ='[3]HAL - CAA'!H35 -> 68.8 | I35: ='[3]HAL - CAA'!I35 -> 69.494122 | J35: ='[3]HAL - CAA'!J35 -> 70.256156 | ... M35: ='[3]HAL - CAA'!M35 -> 72.602541 | P35: Passengers (m) | Q35: ='[3]HAL - CAA'!Q35 -> 406.56762 | R35: ='[3]HAL - CAA'!R35 -> 0 | S35: ='[3]HAL - CAA'!S35 -> 0.0086502598 | T35: ='[3]HAL - CAA'!T35 -> 0 | V35: Passengers (m) | W35: ='[3]HAL - CAA'!W35 -> 355.19129 | X35: ='[3]HAL - CAA'!X35 -> 0 | Y35: ='[3]HAL - CAA'!Y35 -> 0.010817324 | Z35: ='[3]HAL - CAA'!Z35 -> 0 | AA35: ='[3]HAL - CAA'!AA35 -> 0
B37: Total IBP | C37: ='[3]HAL - CAA'!C37 -> 1034.0501 | D37: ='[3]HAL - CAA'!D37 -> 1044.7204 | E37: ='[3]HAL - CAA'!E37 -> 989.42883 | F37: ='[3]HAL - CAA'!F37 -> 993.30895 | G37: ='[3]HAL - CAA'!G37 -> 1032.1101 | H37: ='[3]HAL - CAA'!H37 -> 1004.9493 | I37: ='[3]HAL - CAA'!I37 -> 1102.9221 | J37: ='[3]HAL - CAA'!J37 -> 1099.042 | ... M37: ='[3]HAL - CAA'!M37 -> 1026.2899 | P37: Total IBP | Q37: ='[3]HAL - CAA'!Q37 -> 6098.5677 | R37: ='[3]HAL - CAA'!R37 -> 0.97033695 | S37: ='[3]HAL - CAA'!S37 -> -0.0056929697 | T37: ='[3]HAL - CAA'!T37 -> 15.000131 | V37: Total IBP | W37: ='[3]HAL - CAA'!W37 -> 5304.1146 | X37: ='[3]HAL - CAA'!X37 -> 1.013396 | Y37: ='[3]HAL - CAA'!Y37 -> 0.0042114814 | Z37: ='[3]HAL - CAA'!Z37 -> 14.933121 | AA37: ='[3]HAL - CAA'!AA37 -> -0.00044604033
B38: Total FBP | C38: ='[3]HAL - CAA'!C38 -> 1053.7 | D38: ='[3]HAL - CAA'!D38 -> 1083 | E38: ='[3]HAL - CAA'!E38 -> 1026.4 | F38: ='[3]HAL - CAA'!F38 -> 1029.5 | G38: ='[3]HAL - CAA'!G38 -> 1042.3 | H38: ='[3]HAL - CAA'!H38 -> 1050.1 | I38: ='[3]HAL - CAA'!I38 -> 1081.8 | J38: ='[3]HAL - CAA'!J38 -> 1049.9 | ... M38: ='[3]HAL - CAA'!M38 -> 1038.4 | P38: Total FBP | Q38: ='[3]HAL - CAA'!Q38 -> 6285 | R38: ='[3]HAL - CAA'!R38 -> 1 | S38: ='[3]HAL - CAA'!S38 -> -0.00068424218 | T38: ='[3]HAL - CAA'!T38 -> 15.458683 | V38: Total FBP | W38: ='[3]HAL - CAA'!W38 -> 5234 | X38: ='[3]HAL - CAA'!X38 -> 1 | Y38: ='[3]HAL - CAA'!Y38 -> -0.0022383573 | Z38: ='[3]HAL - CAA'!Z38 -> 14.735722 | AA38: ='[3]HAL - CAA'!AA38 -> 0.0012304449
B39: Profile of CU Efficiency | I39: 0.2 | J39: 0.4 | K39: 0.6 | L39: 0.8 | M39: 1 | Y39: ='[3]HAL - CAA'!Y39 -> 0 | Z39: ='[3]HAL - CAA'!Z39 -> 0 | AA39: ='[3]HAL - CAA'!AA39 -> 0
B40: Efficiency Estimate (Low Stretch) | I40: ='[3]HAL - CAA'!I40 -> -9.3350966 | J40: ='[3]HAL - CAA'!J40 -> -12.455678 | K40: ='[3]HAL - CAA'!K40 -> -15.190235 | L40: ='[3]HAL - CAA'!L40 -> -18.158128 | M40: ='[3]HAL - CAA'!M40 -> -21.880478 | P40: Efficiency Estimate (Low Stretch) | Q40: ='[3]HAL - CAA'!Q40 -> 0 | V40: Efficiency Estimate (Low Stretch) | W40: ='[3]HAL - CAA'!W40 -> -77.019616 | X40: ='[3]HAL - CAA'!X40 -> -0.014715249 | Y40: ='[3]HAL - CAA'!Y40 -> na | Z40: ='[3]HAL - CAA'!Z40 -> -0.21683982 | AA40: ='[3]HAL - CAA'!AA40 -> na
B41: Efficiency Estimate (Mid Stretch) | I41: ='[3]HAL - CAA'!I41 -> -16.243337 | J41: ='[3]HAL - CAA'!J41 -> -20.166688 | K41: ='[3]HAL - CAA'!K41 -> -40.359578 | L41: ='[3]HAL - CAA'!L41 -> -59.362256 | M41: ='[3]HAL - CAA'!M41 -> -81.076534 | P41: Efficiency Estimate (Mid Stretch) | Q41: ='[3]HAL - CAA'!Q41 -> 0 | V41: Efficiency Estimate (Mid Stretch) | W41: ='[3]HAL - CAA'!W41 -> -217.20839 | X41: ='[3]HAL - CAA'!X41 -> -0.041499502 | Y41: ='[3]HAL - CAA'!Y41 -> na | Z41: ='[3]HAL - CAA'!Z41 -> -0.61152512 | AA41: ='[3]HAL - CAA'!AA41 -> na
B42: Efficiency Estimate (High Stretch) | I42: ='[3]HAL - CAA'!I42 -> -21.571578 | J42: ='[3]HAL - CAA'!J42 -> -34.237698 | K42: ='[3]HAL - CAA'!K42 -> -50.068921 | L42: ='[3]HAL - CAA'!L42 -> -76.566384 | M42: ='[3]HAL - CAA'!M42 -> -107.97259 | P42: Efficiency Estimate (High Stretch) | Q42: ='[3]HAL - CAA'!Q42 -> 0 | V42: Efficiency Estimate (High Stretch) | W42: ='[3]HAL - CAA'!W42 -> -290.41717 | X42: ='[3]HAL - CAA'!X42 -> -0.055486659 | Y42: ='[3]HAL - CAA'!Y42 -> na | Z42: ='[3]HAL - CAA'!Z42 -> -0.81763597 | AA42: ='[3]HAL - CAA'!AA42 -> na
M43: ='[3]HAL - CAA'!M43 -> 0
B44: Opex Forecast (Low Stretch) | I44: ='[3]HAL - CAA'!I44 -> 1072.4649 | J44: ='[3]HAL - CAA'!J44 -> 1037.4443 | K44: ='[3]HAL - CAA'!K44 -> 1018.8098 | L44: ='[3]HAL - CAA'!L44 -> 1011.7419 | M44: ='[3]HAL - CAA'!M44 -> 1016.5195 | P44: Opex Forecast (Low Stretch) | Q44: ='[3]HAL - CAA'!Q44 -> 0 | V44: Opex Forecast (Low Stretch) | W44: ='[3]HAL - CAA'!W44 -> 5156.9804 | X44: ='[3]HAL - CAA'!X44 -> 0.98528475 | Y44: ='[3]HAL - CAA'!Y44 -> -0.0064790873 | Z44: ='[3]HAL - CAA'!Z44 -> 14.518882 | AA44: ='[3]HAL - CAA'!AA44 -> -0.0018110278
B45: Opex Forecast (Mid Stretch) | I45: ='[3]HAL - CAA'!I45 -> 1065.5567 | J45: ='[3]HAL - CAA'!J45 -> 1029.7333 | K45: ='[3]HAL - CAA'!K45 -> 993.64042 | L45: ='[3]HAL - CAA'!L45 -> 970.53774 | M45: ='[3]HAL - CAA'!M45 -> 957.32347 | P45: Opex Forecast (Mid Stretch) | Q45: ='[3]HAL - CAA'!Q45 -> 0 | V45: Opex Forecast (Mid Stretch) | W45: ='[3]HAL - CAA'!W45 -> 5016.7916 | X45: ='[3]HAL - CAA'!X45 -> 0.9585005 | Y45: ='[3]HAL - CAA'!Y45 -> -0.018329796 | Z45: ='[3]HAL - CAA'!Z45 -> 14.124197 | AA45: ='[3]HAL - CAA'!AA45 -> -0.010330158
B46: Opex Forecast (High Stretch) | I46: ='[3]HAL - CAA'!I46 -> 1060.2284 | J46: ='[3]HAL - CAA'!J46 -> 1015.6623 | K46: ='[3]HAL - CAA'!K46 -> 983.93108 | L46: ='[3]HAL - CAA'!L46 -> 953.33362 | M46: ='[3]HAL - CAA'!M46 -> 930.42741 | P46: Opex Forecast (High Stretch) | Q46: ='[3]HAL - CAA'!Q46 -> 0 | V46: Opex Forecast (High Stretch) | W46: ='[3]HAL - CAA'!W46 -> 4943.5828 | X46: ='[3]HAL - CAA'!X46 -> 0.94451334 | Y46: ='[3]HAL - CAA'!Y46 -> -0.023908867 | Z46: ='[3]HAL - CAA'!Z46 -> 13.918086 | AA46: ='[3]HAL - CAA'!AA46 -> -0.014350953
M47: ='[3]HAL - CAA'!M47 -> 0
B48: Opex per pax IBP | C48: ='[3]HAL - CAA'!C48 -> 15.691201 | D48: ='[3]HAL - CAA'!D48 -> 15.80515 | E48: ='[3]HAL - CAA'!E48 -> 14.968666 | F48: ='[3]HAL - CAA'!F48 -> 14.176433 | G48: ='[3]HAL - CAA'!G48 -> 14.829168 | H48: ='[3]HAL - CAA'!H48 -> 14.606821 | I48: ='[3]HAL - CAA'!I48 -> 15.870726 | J48: ='[3]HAL - CAA'!J48 -> 15.643356 | ... M48: ='[3]HAL - CAA'!M48 -> 14.13573
B49: Opex per pax FBP | C49: ='[3]HAL - CAA'!C49 -> 15.989378 | D49: ='[3]HAL - CAA'!D49 -> 16.384266 | E49: ='[3]HAL - CAA'!E49 -> 15.527988 | F49: ='[3]HAL - CAA'!F49 -> 14.692949 | G49: ='[3]HAL - CAA'!G49 -> 14.975575 | H49: ='[3]HAL - CAA'!H49 -> 15.263081 | I49: ='[3]HAL - CAA'!I49 -> 15.566784 | J49: ='[3]HAL - CAA'!J49 -> 14.943886 | ... M49: ='[3]HAL - CAA'!M49 -> 14.30253
B51: Opex per pax (Low Stretch) | I51: ='[3]HAL - CAA'!I51 -> 15.432455 | J51: ='[3]HAL - CAA'!J51 -> 14.766597 | K51: ='[3]HAL - CAA'!K51 -> 14.344243 | L51: ='[3]HAL - CAA'!L51 -> 14.088605 | M51: ='[3]HAL - CAA'!M51 -> 14.001156
B52: Opex per pax (Mid Stretch) | I52: ='[3]HAL - CAA'!I52 -> 15.344415 | J52: ='[3]HAL - CAA'!J52 -> 14.611578 | K52: ='[3]HAL - CAA'!K52 -> 14.098707 | L52: ='[3]HAL - CAA'!L52 -> 13.681935 | M52: ='[3]HAL - CAA'!M52 -> 13.408256
B53: Opex per pax (High Stretch) | I53: ='[3]HAL - CAA'!I53 -> 15.256376 | J53: ='[3]HAL - CAA'!J53 -> 14.45656 | K53: ='[3]HAL - CAA'!K53 -> 13.853172 | L53: ='[3]HAL - CAA'!L53 -> 13.275264 | M53: ='[3]HAL - CAA'!M53 -> 12.815356
B57: Charts
B89: Analysis of Efficiency in Mid Stretch Scenario
C91: Q5 | H91: Q5+1 | I91: Q6 | O91: Q6 Total | P91: %
B92: 2011/12 prices | C92: 2008/09 | D92: 2009/10 | E92: 2010/11 | F92: 2011/12 | G92: 2012/13 | H92: 2013/14 | I92: 2014/15 | J92: 2015/16 | K92: 2016/17 | L92: 2017/18 | M92: 2018/19
B93: FBP | C93: ='[3]HAL - CAA'!C93 -> 1053.7 | D93: ='[3]HAL - CAA'!D93 -> 1083 | E93: ='[3]HAL - CAA'!E93 -> 1026.4 | F93: ='[3]HAL - CAA'!F93 -> 1029.5 | G93: ='[3]HAL - CAA'!G93 -> 1042.3 | H93: ='[3]HAL - CAA'!H93 -> 1050.1 | I93: ='[3]HAL - CAA'!I93 -> 1081.8 | J93: ='[3]HAL - CAA'!J93 -> 1049.9 | ... M93: ='[3]HAL - CAA'!M93 -> 1038.4 | O93: ='[3]HAL - CAA'!O93 -> 5234 | P93: na
B94: Other Opex | C94: ='[3]HAL - CAA'!C94 -> 0 | D94: ='[3]HAL - CAA'!D94 -> 0 | E94: ='[3]HAL - CAA'!E94 -> 0 | F94: ='[3]HAL - CAA'!F94 -> 0 | G94: ='[3]HAL - CAA'!G94 -> 0 | H94: ='[3]HAL - CAA'!H94 -> 0 | I94: ='[3]HAL - CAA'!I94 -> -4.56 | J94: ='[3]HAL - CAA'!J94 -> -5.24 | ... M94: ='[3]HAL - CAA'!M94 -> -35.6 | O94: ='[3]HAL - CAA'!O94 -> -77.58 | P94: =O94/$O$100 -> 0.35716852
B95: MandA | C95: ='[3]HAL - CAA'!C95 -> 0 | D95: ='[3]HAL - CAA'!D95 -> 0 | E95: ='[3]HAL - CAA'!E95 -> 0 | F95: ='[3]HAL - CAA'!F95 -> 0 | G95: ='[3]HAL - CAA'!G95 -> 0 | H95: ='[3]HAL - CAA'!H95 -> 0 | I95: ='[3]HAL - CAA'!I95 -> 0.16 | J95: ='[3]HAL - CAA'!J95 -> 2.4 | ... M95: ='[3]HAL - CAA'!M95 -> -12.5 | O95: ='[3]HAL - CAA'!O95 -> -28.22 | P95: =O95/$O$100 -> 0.12992131
B96: Central Services | C96: ='[3]HAL - CAA'!C96 -> 0 | D96: ='[3]HAL - CAA'!D96 -> 0 | E96: ='[3]HAL - CAA'!E96 -> 0 | F96: ='[3]HAL - CAA'!F96 -> 0 | G96: ='[3]HAL - CAA'!G96 -> 0 | H96: ='[3]HAL - CAA'!H96 -> 0 | I96: ='[3]HAL - CAA'!I96 -> 0 | J96: ='[3]HAL - CAA'!J96 -> 0 | ... M96: ='[3]HAL - CAA'!M96 -> 0 | O96: ='[3]HAL - CAA'!O96 -> 0 | P96: =O96/$O$100 -> 0
B97: Wage efficiency | C97: ='[3]HAL - CAA'!C97 -> 0 | D97: ='[3]HAL - CAA'!D97 -> 0 | E97: ='[3]HAL - CAA'!E97 -> 0 | F97: ='[3]HAL - CAA'!F97 -> 0 | G97: ='[3]HAL - CAA'!G97 -> 0 | H97: ='[3]HAL - CAA'!H97 -> 0 | I97: ='[3]HAL - CAA'!I97 -> -5.9486787 | J97: ='[3]HAL - CAA'!J97 -> -11.487391 | ... M97: ='[3]HAL - CAA'!M97 -> -25.670704 | O97: ='[3]HAL - CAA'!O97 -> -80.113829 | P97: =O97/$O$100 -> 0.36883395
B98: Pension Efficiency | C98: ='[3]HAL - CAA'!C98 -> 0 | D98: ='[3]HAL - CAA'!D98 -> 0 | E98: ='[3]HAL - CAA'!E98 -> 0 | F98: ='[3]HAL - CAA'!F98 -> 0 | G98: ='[3]HAL - CAA'!G98 -> 0 | H98: ='[3]HAL - CAA'!H98 -> 0 | I98: ='[3]HAL - CAA'!I98 -> -4.4770237 | J98: ='[3]HAL - CAA'!J98 -> -3.0059407 | ... M98: ='[3]HAL - CAA'!M98 -> -0.2367672 | O98: ='[3]HAL - CAA'!O98 -> -10.068277 | P98: =O98/$O$100 -> 0.046353077
B99: Frontier shift | C99: ='[3]HAL - CAA'!C99 -> 0 | D99: ='[3]HAL - CAA'!D99 -> 0 | E99: ='[3]HAL - CAA'!E99 -> 0 | F99: ='[3]HAL - CAA'!F99 -> 0 | G99: ='[3]HAL - CAA'!G99 -> 0 | H99: ='[3]HAL - CAA'!H99 -> 0 | I99: ='[3]HAL - CAA'!I99 -> -1.417635 | J99: ='[3]HAL - CAA'!J99 -> -2.8333562 | ... M99: ='[3]HAL - CAA'!M99 -> -7.0690627 | O99: ='[3]HAL - CAA'!O99 -> -21.226288 | P99: =O99/$O$100 -> 0.097723146
B100: Total | C100: ='[3]HAL - CAA'!C100 -> 0 | D100: ='[3]HAL - CAA'!D100 -> 0 | E100: ='[3]HAL - CAA'!E100 -> 0 | F100: ='[3]HAL - CAA'!F100 -> 0 | G100: ='[3]HAL - CAA'!G100 -> 0 | H100: ='[3]HAL - CAA'!H100 -> 0 | I100: ='[3]HAL - CAA'!I100 -> -16.243337 | J100: ='[3]HAL - CAA'!J100 -> -20.166688 | ... M100: ='[3]HAL - CAA'!M100 -> -81.076534 | O100: ='[3]HAL - CAA'!O100 -> -217.20839 | P100: =O100/$O$100 -> 1
B101: CAA | C101: ='[3]HAL - CAA'!C101 -> 0 | D101: ='[3]HAL - CAA'!D101 -> 0 | E101: ='[3]HAL - CAA'!E101 -> 0 | F101: ='[3]HAL - CAA'!F101 -> 0 | G101: ='[3]HAL - CAA'!G101 -> 0 | H101: ='[3]HAL - CAA'!H101 -> 0 | I101: ='[3]HAL - CAA'!I101 -> 1065.5567 | J101: ='[3]HAL - CAA'!J101 -> 1029.7333 | ... M101: ='[3]HAL - CAA'!M101 -> 957.32347 | O101: ='[3]HAL - CAA'!O101 -> 5016.7916 | P101: na
C103: Q5 | H103: Q5+1 | I103: Q6 | O103: Total | P103: %
C104: 2008/09 | D104: 2009/10 | E104: 2010/11 | F104: 2011/12 | G104: 2012/13 | H104: 2013/14 | I104: 2014/15 | J104: 2015/16 | K104: 2016/17 | L104: 2017/18 | M104: 2018/19
B105: 2011/12 prices | I105: ='[3]HAL - CAA'!I105 -> 0 | J105: ='[3]HAL - CAA'!J105 -> 0 | K105: ='[3]HAL - CAA'!K105 -> 0 | L105: ='[3]HAL - CAA'!L105 -> 0 | M105: ='[3]HAL - CAA'!M105 -> 0
B106: Frontier shift | I106: ='[3]HAL - CAA'!I106 -> -1.417635 | J106: ='[3]HAL - CAA'!J106 -> -2.8333562 | K106: ='[3]HAL - CAA'!K106 -> -4.2471662 | L106: ='[3]HAL - CAA'!L106 -> -5.6590675 | M106: ='[3]HAL - CAA'!M106 -> -7.0690627 | O106: -21.226288 | P106: 0.069495342
B107: Catch up | I107: ='[3]HAL - CAA'!I107 -> -25.643337 | J107: ='[3]HAL - CAA'!J107 -> -29.966688 | K107: ='[3]HAL - CAA'!K107 -> -49.459578 | L107: ='[3]HAL - CAA'!L107 -> -54.362256 | M107: ='[3]HAL - CAA'!M107 -> -64.076534 | O107: -223.50839 | P107: 0.7317715
B108: Pessimistic forecasts | I108: ='[3]HAL - CAA'!I108 -> -4 | J108: ='[3]HAL - CAA'!J108 -> -3.6 | K108: ='[3]HAL - CAA'!K108 -> -4.3 | L108: ='[3]HAL - CAA'!L108 -> -18.4 | M108: ='[3]HAL - CAA'!M108 -> -30.4 | O108: -60.7 | P108: 0.19873316
B109: Total | I109: ='[3]HAL - CAA'!I109 -> -31.060972 | J109: ='[3]HAL - CAA'!J109 -> -36.400044 | K109: ='[3]HAL - CAA'!K109 -> -58.006744 | L109: ='[3]HAL - CAA'!L109 -> -78.421324 | M109: ='[3]HAL - CAA'!M109 -> -101.5456 | O109: -305.43468 | P109: 1
B112: Breakdown
B115: Breakdown of bottom up mid point estimate | C115: IBP | D115: FBP | E115: Wage efficiency | F115: Other opex | G115: M and A | H115: Frontier shift | I115: Pension efficiency | J115: Central support | K115: CAA | L115: BA
B116: IBP | C116: 5304.1146
B117: FBP | D117: 5234 | E117: 5153.8862 | F117: 5076.3062 | G117: 5048.0862 | H117: 5026.8599 | I117: 5016.7916 | J117: 5016.7916
B118: Wage efficiency | E118: 80.113829
B119: Other opex | F119: 77.58
B120: M and A | G120: 28.22
B121: Frontier shift | H121: 21.226288
B122: Pension efficiency | I122: 10.068277
B123: Central support | J123: 0
B124: CAA | K124: 5016.7916
B125: BA | L125: 4048.122
B138: End

Sheet HAL - CAA - fp
B2: Heathrow - CAA Projections - October 2013 - Final Proposals
B4: This sheet shows the CAA's final proposals for HAL's opex allowance in Q6.
B6: Bottom Up Projections
B8: CAA March 2013 HAL Projections | C8: Q5 | H8: Q5+1 | I8: Q6 | P8: CAA March 2013 HAL Projections - Summary Q5+1 | V8: CAA March 2013 HAL Projections - Summary Q6
B9: £m nominal | C9: 2008/09 | D9: 2009/10 | E9: 2010/11 | F9: 2011/12 | G9: 2012/13 | H9: 2013/14 | I9: 2014/15 | J9: 2015/16 | K9: 2016/17 | L9: 2017/18 | M9: 2018/19 | P9: £m nominal | Q9: Total Q5+1 | R9: % of ABP | S9: CAGR (Q5+1) | T9: Opex per Pax | V9: £m nominal | W9: Total Q6 | X9: % of ABP | Y9: CAGR (Q6) | Z9: Opex per Pax | AA9: Relative to 2012/13
B10: =B46 -> Passengers (fbp) (m) | C10: =C46 -> 65.9 | D10: =D46 -> 66.1 | E10: =E46 -> 66.1 | F10: =F46 -> 70.067623 | G10: =G46 -> 69.6 | H10: =H46 -> 68.8 | I10: =I46 -> 69.494122 | ... M10: =M46 -> 72.602541 | P10: =B10 -> Passengers (fbp) (m) | Q10: =SUM(C10:H10) -> 406.56762 | R10: =Q10/$Q$11 -> 1 | S10: =((H10/C10)^(1/5))-1 -> 0.0086502598 | V10: =P10 -> Passengers (fbp) (m) | W10: =SUM(I10:M10) -> 355.19129 | X10: =W10/$W$11 -> 0.99298655 | Y10: =((M10/H10)^(1/5))-1 -> 0.010817324 | AA10: =((M10/$G$47)^(1/6)-1) -> 0.0070640592
B11: =B47 -> Passengers (r/abp) (m) | C11: =C47 -> 65.9 | D11: =D47 -> 66.1 | E11: =E47 -> 66.1 | F11: =F47 -> 70.067623 | G11: =G47 -> 69.6 | H11: =H47 -> 68.8 | I11: =I47 -> 70.1 | ... M11: =M47 -> 73 | P11: =B11 -> Passengers (r/abp) (m) | Q11: =SUM(C11:H11) -> 406.56762 | R11: =Q11/$Q$11 -> 1 | S11: =((H11/C11)^(1/5))-1 -> 0.0086502598 | V11: =P11 -> Passengers (r/abp) (m) | W11: =SUM(I11:M11) -> 357.7 | X11: =W11/$W$11 -> 1 | Y11: =((M11/H11)^(1/5))-1 -> 0.011921642 | AA11: =((M11/$G$47)^(1/6)-1) -> 0.007980824
B13: =B49 -> Total IBP | C13: =C49*C$40 -> 940.05218 | D13: =D49*D$40 -> 949.75253 | E13: =E49*E$40 -> 944.12792 | F13: =F49*F$40 -> 993.30895 | G13: =G49*G$40 -> 1064 | H13: =H49*H$40 -> 1059.0673 | I13: =I49*I$40 -> 1194.959 | J13: =J49*J$40 -> 1230.9416 | ... M13: =M49*M$40 -> 1256.044 | P13: =B13 -> Total IBP | Q13: =SUM(C13:H13) -> 5950.3089 | R13: =Q13/$Q$15 -> 0.97028634 | S13: =((H13/C13)^(1/5))-1 -> 0.024128183 | T13: =Q13/$Q$10 -> 14.635471 | V13: =P13 -> Total IBP | W13: =SUM(I13:M13) -> 6112.5394 | X13: =W13/$W$15 -> 1.0356696 | Y13: =((M13/H13)^(1/5))-1 -> 0.034704323 | Z13: =W13/$W$10 -> 17.209148 | AA13: =((M13/$G$51)^(1/6)-1) -> 0.031577881
B14: =B50 -> Total FBP | C14: =C50*C$40 -> 957.91582 | D14: =D50*D$40 -> 984.55237 | E14: =E50*E$40 -> 979.40637 | F14: =F50*F$40 -> 1029.5 | G14: =G50*G$40 -> 1074.5048 | H14: =H50*H$40 -> 1106.6494 | I14: =I50*I$40 -> 1172.0743 | J14: =J50*J$40 -> 1175.9018 | ... M14: =M50*M$40 -> 1270.8652 | P14: =B14 -> Total FBP | Q14: =SUM(C14:H14) -> 6132.5287 | R14: =Q14/$Q$15 -> 1 | S14: =((H14/C14)^(1/5))-1 -> 0.029287132 | T14: =Q14/$Q$10 -> 15.083662 | V14: =P14 -> Total FBP | W14: =SUM(I14:M14) -> 6035.4276 | X14: =W14/$W$15 -> 1.0226042 | Y14: =((M14/H14)^(1/5))-1 -> 0.028058636 | Z14: =W14/$W$10 -> 16.992048 | AA14: =((M14/$G$51)^(1/6)-1) -> 0.033596726
B15: =B51 -> Total ABP | C15: =C51*C$40 -> 957.91582 | D15: =D51*D$40 -> 984.55237 | E15: =E51*E$40 -> 979.40637 | F15: =F51*F$40 -> 1029.5 | G15: =G51*G$40 -> 1074.5048 | H15: =H51*H$40 -> 1106.6494 | I15: =I51*I$40 -> 1161.0231 | J15: =J51*J$40 -> 1152.6056 | ... M15: =M51*M$40 -> 1235.4954 | P15: =B15 -> Total ABP | Q15: =SUM(C15:H15) -> 6132.5287 | R15: =Q15/$Q$15 -> 1 | S15: =((H15/C15)^(1/5))-1 -> 0.029287132 | T15: =Q15/$Q$10 -> 15.083662 | V15: =P15 -> Total ABP | W15: =SUM(I15:M15) -> 5902.017 | X15: =W15/$W$15 -> 1 | Y15: =((M15/H15)^(1/5))-1 -> 0.022271408 | Z15: =W15/$W$11 -> 16.499908 | AA15: =((M15/$G$51)^(1/6)-1) -> 0.028745778
B17: =B54 -> CAA - ip - Efficiency relative to FBP | I17: =I54*I$40 -> -17.598815 | J17: =J54*J$40 -> -22.586957 | K17: =K54*K$40 -> -46.559357 | L17: =L54*L$40 -> -70.535538 | M17: =M54*M$40 -> -99.227028 | P17: =B17 -> CAA - ip - Efficiency relative to FBP | Q17: =SUM(C17:H17) -> 0 | R17: =Q17/$Q$15 -> 0 | T17: =Q17/$Q$10 -> 0 | V17: =P17 -> CAA - ip - Efficiency relative to FBP | W17: =SUM(I17:M17) -> -256.50769 | X17: =W17/$W$15 -> -0.043461023 | Y17: na | Z17: =W17/$W$10 -> -0.72216775
B18: =B55 -> LACC - Efficiency relative to FBP | I18: =I55*I$40 -> -85.592408 | J18: =J55*J$40 -> -176.96208 | K18: =K55*K$40 -> -273.40642 | L18: =L55*L$40 -> -375.47815 | M18: =M55*M$40 -> -483.42812 | P18: =B18 -> LACC - Efficiency relative to FBP | Q18: =SUM(C18:H18) -> 0 | R18: =Q18/$Q$15 -> 0 | T18: =Q18/$Q$10 -> 0 | V18: =P18 -> LACC - Efficiency relative to FBP | W18: =SUM(I18:M18) -> -1394.8672 | X18: =W18/$W$15 -> -0.23633737 | Y18: na | Z18: =W18/$W$10 -> -3.9270872
R19: =Q19/$Q$15 -> 0
B20: =B57 -> CAA - fp - Efficiency - low stretch | I20: =I57*I$40 -> -13.245084 | J20: =J57*J$40 -> -21.309362 | K20: =K57*K$40 -> -27.609032 | L20: =L57*L$40 -> -45.782613 | M20: =M57*M$40 -> -64.335442 | P20: =B20 -> CAA - fp - Efficiency - low stretch | Q20: =SUM(C20:H20) -> 0 | R20: =Q20/$Q$15 -> 0 | T20: =Q20/$Q$10 -> 0 | V20: =P20 -> CAA - fp - Efficiency - low stretch | W20: =SUM(I20:M20) -> -172.28153 | X20: =W20/$W$15 -> -0.029190281 | Y20: na | Z20: =W20/$W$10 -> -0.48503873
B21: =B58 -> CAA - fp - Efficiency - mid stretch | I21: =I58*I$40 -> -15.569488 | J21: =J58*J$40 -> -25.937586 | K21: =K58*K$40 -> -34.417736 | L21: =L58*L$40 -> -54.863593 | M21: =M58*M$40 -> -75.931436 | P21: =B21 -> CAA - fp - Efficiency - mid stretch | Q21: =SUM(C21:H21) -> 0 | R21: =Q21/$Q$15 -> 0 | T21: =Q21/$Q$10 -> 0 | V21: =P21 -> CAA - fp - Efficiency - mid stretch | W21: =SUM(I21:M21) -> -206.71984 | X21: =W21/$W$15 -> -0.035025287 | Y21: na | Z21: =W21/$W$10 -> -0.58199581
B22: =B59 -> CAA - fp - Efficiency - high stretch | I22: =I59*I$40 -> -20.69342 | J22: =J59*J$40 -> -35.330628 | K22: =K59*K$40 -> -47.563285 | L22: =L59*L$40 -> -69.730407 | M22: =M59*M$40 -> -96.384377 | P22: =B22 -> CAA - fp - Efficiency - high stretch | Q22: =SUM(C22:H22) -> 0 | R22: =Q22/$Q$15 -> 0 | T22: =Q22/$Q$10 -> 0 | V22: =P22 -> CAA - fp - Efficiency - high stretch | W22: =SUM(I22:M22) -> -269.70212 | X22: =W22/$W$15 -> -0.045696601 | Y22: na | Z22: =W22/$W$10 -> -0.75931512
B24: =B61 -> CAA - ip - opex | I24: =I61*I$40 -> 1154.4754 | J24: =J61*J$40 -> 1153.3149 | K24: =K61*K$40 -> 1146.2771 | L24: =L61*L$40 -> 1153.2143 | M24: =M61*M$40 -> 1171.6382 | P24: =B24 -> CAA - ip - opex | Q24: =SUM(C24:H24) -> 0 | R24: =Q24/$Q$15 -> 0 | T24: =Q24/$Q$10 -> 0 | V24: =P24 -> CAA - ip - opex | W24: =SUM(I24:M24) -> 5778.9199 | X24: =W24/$W$15 -> 0.97914321 | Y24: =((M24/H14)^(1/5))-1 -> 0.011478581 | Z24: =W24/$W$10 -> 16.269881 | AA24: =((M24/$G$51)^(1/6)-1) -> 0.019686797
B25: =B62 -> LACC - opex | I25: =I62*I$40 -> 1086.4819 | J25: =J62*J$40 -> 998.93976 | K25: =K62*K$40 -> 919.43002 | L25: =L62*L$40 -> 848.27168 | M25: =M62*M$40 -> 787.43709 | P25: =B25 -> LACC - opex | Q25: =SUM(C25:H25) -> 0 | R25: =Q25/$Q$15 -> 0 | T25: =Q25/$Q$10 -> 0 | V25: =P25 -> LACC - opex | W25: =SUM(I25:M25) -> 4640.5604 | X25: =W25/$W$15 -> 0.78626686 | Y25: =((M25/H15)^(1/5))-1 -> -0.065797208 | Z25: =W25/$W$10 -> 13.064961 | AA25: =((M25/$G$51)^(1/6)-1) -> -0.045658401
B27: =B64 -> CAA - fp - opex - low stretch | I27: =I64*I$40 -> 1147.778 | J27: =J64*J$40 -> 1131.2962 | K27: =K64*K$40 -> 1137.656 | L27: =L64*L$40 -> 1141.8453 | M27: =M64*M$40 -> 1171.16 | P27: =B27 -> CAA - fp - opex - low stretch | Q27: =SUM(C27:H27) -> 0 | R27: =Q27/$Q$15 -> 0 | T27: =Q27/$Q$10 -> 0 | V27: =P27 -> CAA - fp - opex - low stretch | W27: =SUM(I27:M27) -> 5729.7355 | X27: =W27/$W$15 -> 0.97080972 | Y27: =((M27/H15)^(1/5))-1 -> 0.011395998 | Z27: =W27/$W$11 -> 16.018271 | AA27: =((M27/$G$51)^(1/6)-1) -> 0.019617419
B28: =B65 -> CAA - fp - opex - mid stretch | I28: =I65*I$40 -> 1145.4536 | J28: =J65*J$40 -> 1126.668 | K28: =K65*K$40 -> 1130.8473 | L28: =L65*L$40 -> 1132.7643 | M28: =M65*M$40 -> 1159.564 | P28: =B28 -> CAA - fp - opex - mid stretch | Q28: =SUM(C28:H28) -> 0 | R28: =Q28/$Q$15 -> 0 | T28: =Q28/$Q$10 -> 0 | V28: =P28 -> CAA - fp - opex - mid stretch | W28: =SUM(I28:M28) -> 5695.2972 | X28: =W28/$W$15 -> 0.96497471 | Y28: =((M28/H15)^(1/5))-1 -> 0.0093851931 | Z28: =W28/$W$11 -> 15.921994 | AA28: =((M28/$G$51)^(1/6)-1) -> 0.017927847
B29: =B66 -> CAA - fp - opex - high stretch | I29: =I66*I$40 -> 1140.3297 | J29: =J66*J$40 -> 1117.2749 | K29: =K66*K$40 -> 1117.7018 | L29: =L66*L$40 -> 1117.8975 | M29: =M66*M$40 -> 1139.111 | P29: =B29 -> CAA - fp - opex - high stretch | Q29: =SUM(C29:H29) -> 0 | R29: =Q29/$Q$15 -> 0 | T29: =Q29/$Q$10 -> 0 | V29: =P29 -> CAA - fp - opex - high stretch | W29: =SUM(I29:M29) -> 5632.3149 | X29: =W29/$W$15 -> 0.9543034 | Y29: =((M29/H15)^(1/5))-1 -> 0.0057989978 | Z29: =W29/$W$11 -> 15.745918 | AA29: =((M29/$G$51)^(1/6)-1) -> 0.014913165
B31: =B68 -> Opex per pax IBP | C31: =C68*C$40 -> 14.264828 | D31: =D68*D$40 -> 14.368419 | E31: =E68*E$40 -> 14.283327 | F31: =F68*F$40 -> 14.176433 | G31: =G68*G$40 -> 15.287356 | H31: =H68*H$40 -> 15.39342 | I31: =I68*I$40 -> 17.195109 | J31: =J68*J$40 -> 17.520764 | ... M31: =M68*M$40 -> 17.300277
B32: =B69 -> Opex per pax FBP | C32: =C69*C$40 -> 14.5359 | D32: =D69*D$40 -> 14.894892 | E32: =E69*E$40 -> 14.81704 | F32: =F69*F$40 -> 14.692949 | G32: =G69*G$40 -> 15.438287 | H32: =H69*H$40 -> 16.085021 | I32: =I69*I$40 -> 16.720032 | J32: =J69*J$40 -> 16.608783 | ... M32: =M69*M$40 -> 17.409112
B33: =B72 -> CAA - ip - opex per pax | I33: =I72*I$40 -> 16.612563 | J33: =J72*J$40 -> 16.415855 | K33: =K72*K$40 -> 16.138908 | L33: =L72*L$40 -> 16.058622 | M33: =M72*M$40 -> 16.137702
B34: =B73 -> LACC - opex per passenger | I34: =I73*I$40 -> 15.634155 | J34: =J73*J$40 -> 14.218537 | K34: =K73*K$40 -> 12.945035 | L34: =L73*L$40 -> 11.812266 | M34: =M73*M$40 -> 10.845861
B36: =B75 -> CAA - fp - opex per passenger - low stretch | I36: =I75*I$40 -> 16.373438 | J36: =J75*J$40 -> 15.97876 | K36: =K75*K$40 -> 15.911273 | L36: =L75*L$40 -> 15.793157 | M36: =M75*M$40 -> 16.043287
B37: =B76 -> CAA - fp - opex per passenger - mid stretch | I37: =I76*I$40 -> 16.34028 | J37: =J76*J$40 -> 15.91339 | K37: =K76*K$40 -> 15.816047 | L37: =L76*L$40 -> 15.667556 | M37: =M76*M$40 -> 15.884438
B38: =B77 -> CAA - fp - opex per passenger - high stretch | I38: =I77*I$40 -> 16.267185 | J38: =J77*J$40 -> 15.780719 | K38: =K77*K$40 -> 15.632193 | L38: =L77*L$40 -> 15.461929 | M38: =M77*M$40 -> 15.604261
B40: Price Base Conversion 11/12 to Nominal | C40: =RPI!$T101/RPI!$T$103 -> 0.90909729 | D40: =RPI!$T101/RPI!$T$103 -> 0.90909729 | E40: =RPI!$T102/RPI!$T$103 -> 0.95421509 | F40: =RPI!$T103/RPI!$T$103 -> 1 | G40: =RPI!$V104/RPI!$T$103 -> 1.0308978 | H40: =RPI!$V105/RPI!$T$103 -> 1.0538515 | I40: =RPI!$V106/RPI!$T$103 -> 1.0834482 | J40: =RPI!$V107/RPI!$T$103 -> 1.1200132 | K40: =RPI!$V108/RPI!$T$103 -> 1.1536136 | L40: =RPI!$V109/RPI!$T$103 -> 1.188222 | M40: =RPI!$V110/RPI!$T$103 -> 1.2238686
B42: CAA March 2013 HAL Projections | C42: Q5 | H42: Q5+1 | I42: Q6 | P42: CAA March 2013 HAL Projections - Summary Q5+1 | V42: CAA March 2013 HAL Projections - Summary Q6
B44: Include Rate Efficiency? | C44: 1 | E44: Set to 1 to include the rates revaluation efficiency (without passthrough).
B45: £m 2011/12 prices | C45: 2008/09 | D45: 2009/10 | E45: 2010/11 | F45: 2011/12 | G45: 2012/13 | H45: 2013/14 | I45: 2014/15 | J45: 2015/16 | K45: 2016/17 | L45: 2017/18 | M45: 2018/19 | P45: £m 2011/12 prices | Q45: Total Q5+1 | R45: % of ABP | S45: CAGR (Q5+1) | T45: Opex per Pax | V45: £m 2011/12 prices | W45: Total Q6 | X45: % of ABP | Y45: CAGR (Q6) | Z45: Opex per Pax | AA45: Relative to 2012/13
B46: Passengers (fbp) (m) | C46: ='HAL - fBP'!C20 -> 65.9 | D46: ='HAL - fBP'!D20 -> 66.1 | E46: ='HAL - fBP'!E20 -> 66.1 | F46: ='HAL - fBP'!F20 -> 70.067623 | G46: ='HAL - fBP'!G20 -> 69.6 | H46: ='HAL - fBP'!H20 -> 68.8 | I46: ='HAL - fBP'!I20 -> 69.494122 | J46: ='HAL - fBP'!J20 -> 70.256156 | ... M46: ='HAL - fBP'!M20 -> 72.602541 | P46: =B46 -> Passengers (fbp) (m) | Q46: =SUM(C46:H46) -> 406.56762 | R46: =Q46/$Q$47 -> 1 | S46: =((H46/C46)^(1/5))-1 -> 0.0086502598 | T46: =Q46/$Q$46 -> 1 | V46: =P46 -> Passengers (fbp) (m) | W46: =SUM(I46:M46) -> 355.19129 | X46: =W46/$W$47 -> 0.99298655 | Y46: =((M46/H46)^(1/5))-1 -> 0.010817324 | AA46: =((M46/$G$47)^(1/6)-1) -> 0.0070640592
B47: Passengers (r/abp) (m) | C47: ='HAL - rBP'!C42 -> 65.9 | D47: ='HAL - rBP'!D42 -> 66.1 | E47: ='HAL - rBP'!E42 -> 66.1 | F47: ='HAL - rBP'!F42 -> 70.067623 | G47: ='HAL - rBP'!G42 -> 69.6 | H47: ='HAL - rBP'!H42 -> 68.8 | I47: ='HAL - rBP'!I42 -> 70.1 | J47: ='HAL - rBP'!J42 -> 70.8 | ... M47: ='HAL - rBP'!M42 -> 73 | P47: =B47 -> Passengers (r/abp) (m) | Q47: =SUM(C47:H47) -> 406.56762 | R47: =Q47/$Q$47 -> 1 | S47: =((H47/C47)^(1/5))-1 -> 0.0086502598 | T47: =Q47/$Q$46 -> 1 | V47: =P47 -> Passengers (r/abp) (m) | W47: =SUM(I47:M47) -> 357.7 | X47: =W47/$W$47 -> 1 | Y47: =((M47/H47)^(1/5))-1 -> 0.011921642 | AA47: =((M47/$G$47)^(1/6)-1) -> 0.007980824
B49: Total IBP | C49: ='HAL - iBP '!C71 -> 1034.0501 | D49: ='HAL - iBP '!D71 -> 1044.7204 | E49: ='HAL - iBP '!E71 -> 989.42883 | F49: ='HAL - iBP '!F71 -> 993.30895 | G49: ='HAL - iBP '!G71 -> 1032.1101 | H49: ='HAL - iBP '!H71 -> 1004.9493 | I49: ='HAL - iBP '!I71 -> 1102.9221 | J49: ='HAL - iBP '!J71 -> 1099.042 | ... M49: ='HAL - iBP '!M71 -> 1026.2899 | P49: =B49 -> Total IBP | Q49: =SUM(C49:H49) -> 6098.5677 | R49: =Q49/$Q$51 -> 0.97033695 | S49: =((H49/C49)^(1/5))-1 -> -0.0056929697 | T49: =Q49/$Q$46 -> 15.000131 | V49: =P49 -> Total IBP | W49: =SUM(I49:M49) -> 5304.1146 | X49: =W49/$W$51 -> 1.0360003 | Y49: =((M49/H49)^(1/5))-1 -> 0.0042114814 | Z49: =W49/$W$46 -> 14.933121 | AA49: =((M49/$G$51)^(1/6)-1) -> -0.0025765984
B50: Total FBP | C50: ='HAL - fBP'!C39 -> 1053.7 | D50: ='HAL - fBP'!D39 -> 1083 | E50: ='HAL - fBP'!E39 -> 1026.4 | F50: ='HAL - fBP'!F39 -> 1029.5 | G50: ='HAL - fBP'!G39 -> 1042.3 | H50: ='HAL - fBP'!H39 -> 1050.1 | I50: ='HAL - fBP'!I39 -> 1081.8 | J50: ='HAL - fBP'!J39 -> 1049.9 | ... M50: ='HAL - fBP'!M39 -> 1038.4 | P50: =B50 -> Total FBP | Q50: =SUM(C50:H50) -> 6285 | R50: =Q50/$Q$51 -> 1 | S50: =((H50/C50)^(1/5))-1 -> -0.00068424218 | T50: =Q50/$Q$46 -> 15.458683 | V50: =P50 -> Total FBP | W50: =SUM(I50:M50) -> 5234 | X50: =W50/$W$51 -> 1.0223056 | Y50: =((M50/H50)^(1/5))-1 -> -0.0022383573 | Z50: =W50/$W$47 -> 14.632373 | AA50: =((M50/$G$51)^(1/6)-1) -> -0.00062459532
B51: Total ABP | C51: ='HAL - aBP'!C39 -> 1053.7 | D51: ='HAL - aBP'!D39 -> 1083 | E51: ='HAL - aBP'!E39 -> 1026.4 | F51: ='HAL - aBP'!F39 -> 1029.5 | G51: ='HAL - aBP'!G39 -> 1042.3 | H51: ='HAL - aBP'!H39 -> 1050.1 | I51: ='HAL - aBP'!I39 -> 1071.6 | J51: ='HAL - aBP'!J39 -> 1029.1 | ... M51: ='HAL - aBP'!M39 -> 1009.5 | P51: =B51 -> Total ABP | Q51: =SUM(C51:H51) -> 6285 | R51: =Q51/$Q$51 -> 1 | S51: =((H51/C51)^(1/5))-1 -> -0.00068424218 | T51: =Q51/$Q$46 -> 15.458683 | V51: =P51 -> Total ABP | W51: =SUM(I51:M51) -> 5119.8 | X51: =W51/$W$51 -> 1 | Y51: =((M51/H51)^(1/5))-1 -> -0.0078550345 | Z51: =W51/$W$47 -> 14.313112 | AA51: =((M51/$G$51)^(1/6)-1) -> -0.005314934
B52: Profile of CU Efficiency | I52: 0.2 | J52: 0.4 | K52: 0.6 | L52: 0.8 | M52: 1
B54: CAA - ip - Efficiency relative to FBP | I54: ='HAL - CAA - ip'!I41 -> -16.243337 | J54: ='HAL - CAA - ip'!J41 -> -20.166688 | K54: ='HAL - CAA - ip'!K41 -> -40.359578 | L54: ='HAL - CAA - ip'!L41 -> -59.362256 | M54: ='HAL - CAA - ip'!M41 -> -81.076534 | P54: =B54 -> CAA - ip - Efficiency relative to FBP | Q54: =SUM(C54:H54) -> 0 | R54: =Q54/$Q$51 -> 0 | T54: =Q54/$Q$46 -> 0 | V54: =P54 -> CAA - ip - Efficiency relative to FBP | W54: =SUM(I54:M54) -> -217.20839 | X54: =W54/$W$51 -> -0.042425172 | Y54: na | Z54: =W54/$W$47 -> -0.60723621
B55: LACC - Efficiency relative to FBP | I55: -79 | J55: -158 | K55: -237 | L55: -316 | M55: -395 | P55: =B55 -> LACC - Efficiency relative to FBP | Q55: =SUM(C55:H55) -> 0 | R55: =Q55/$Q$51 -> 0 | T55: =Q55/$Q$46 -> 0 | V55: =P55 -> LACC - Efficiency relative to FBP | W55: =SUM(I55:M55) -> -1185 | X55: =W55/$W$51 -> -0.23145435 | Y55: na | Z55: =W55/$W$47 -> -3.312832
B57: CAA - fp - Efficiency - low stretch | I57: =((Wages!L31)*I52)+'Other Opex'!F46+MandA!F34+'Frontier Shift'!N15+(Pensions!L25+Pensions!L27)+Overlays!L10 -> -12.224935 | J57: =((Wages!M31)*J52)+'Other Opex'!G46+MandA!G34+'Frontier Shift'!O15+(Pensions!M25+Pensions!M27)+Overlays!M10 -> -19.025992 | K57: =((Wages!N31)*K52)+'Other Opex'!H46+MandA!H34+'Frontier Shift'!P15+(Pensions!N25+Pensions!N27)+Overlays!N10 -> -23.932652 | L57: =((Wages!O31)*L52)+'Other Opex'!I46+MandA!I34+'Frontier Shift'!Q15+(Pensions!O25+Pensions!O27)+Overlays!O10 -> -38.530353 | M57: =((Wages!P31)*M52)+'Other Opex'!J46+MandA!J34+'Frontier Shift'!R15+(Pensions!P25+Pensions!P27)+Overlays!P10 -> -52.567277 | P57: =B57 -> CAA - fp - Efficiency - low stretch | Q57: =SUM(C57:H57) -> 0 | R57: =Q57/$Q$51 -> 0 | T57: =Q57/$Q$46 -> 0 | V57: =P57 -> CAA - fp - Efficiency - low stretch | W57: =SUM(I57:M57) -> -146.28121 | X57: =W57/$W$51 -> -0.028571665 | Y57: na | Z57: =W57/$W$47 -> -0.40894942
B58: CAA - fp - Efficiency - mid stretch | I58: =((Wages!L32)*'HAL - CAA - fp'!I52)+'Other Opex'!F46+MandA!F34+'Frontier Shift'!N15+(Pensions!L25+Pensions!L27)+Overlays!L10 -> -14.370311 | J58: =((Wages!M32)*'HAL - CAA - fp'!J52)+'Other Opex'!G46+MandA!G34+'Frontier Shift'!O15+(Pensions!M25+Pensions!M27)+Overlays!M10 -> -23.158287 | K58: =((Wages!N32)*'HAL - CAA - fp'!K52)+'Other Opex'!H46+MandA!H34+'Frontier Shift'!P15+(Pensions!N25+Pensions!N27)+Overlays!N10 -> -29.834718 | L58: =((Wages!O32)*'HAL - CAA - fp'!L52)+'Other Opex'!I46+MandA!I34+'Frontier Shift'!Q15+(Pensions!O25+Pensions!O27)+Overlays!O10 -> -46.172848 | M58: =((Wages!P32)*'HAL - CAA - fp'!M52)+'Other Opex'!J46+MandA!J34+'Frontier Shift'!R15+(Pensions!P25+Pensions!P27)+Overlays!P10 -> -62.042145 | P58: =B58 -> CAA - fp - Efficiency - mid stretch | Q58: =SUM(C58:H58) -> 0 | R58: =Q58/$Q$51 -> 0 | T58: =Q58/$Q$46 -> 0 | V58: =P58 -> CAA - fp - Efficiency - mid stretch | W58: =SUM(I58:M58) -> -175.57831 | X58: =W58/$W$51 -> -0.034293978 | Y58: na | Z58: =W58/$W$47 -> -0.49085354
