Workbook

Sheet 2013 Budget
C1: Year Ending | F1: Year Ending | G1: Budget Variance
C2: 41547 | D2: 41547 | F2: 41182 | G2: 41182
C3: Budget | F3: Approved | G3: to
C4: Draft | D4: % of Total | F4: Budget | G4: 40816
A6: 1 | B6: Revenues
A7: =A6+1 -> 2 | B7: Product & Council Shop Revenue, Net
A8: =A7+1 -> 3 | B8: Cookie Income, Net | C8: 3082394 | D8: =+C8/$C$33 -> 0.66502944 | F8: 2913327 | G8: =SUM(C8-F8) -> 169067 | H8: =G8/F8 -> 0.058032277
A9: =A8+1 -> 4 | B9: Fall Products, Net | C9: 344629.75 | D9: =+C9/$C$33 -> 0.074354197 | F9: 344630 | G9: =SUM(C9-F9) -> -0.25 | H9: =G9/F9 -> -7.2541566e-07
A10: =A9+1 -> 5 | B10: Council Shop Income, Net | C10: 180250 | D10: =+C10/$C$33 -> 0.038889109 | F10: 185250 | G10: =SUM(C10-F10) -> -5000 | H10: =G10/F10 -> -0.026990553
A11: =A10+1 -> 6 | B11: Total Product & Council Shop Revenue | C11: =SUM(C8:C10) -> 3607273.8 | D11: =SUM(D8:D10) -> 0.77827275 | F11: =SUM(F8:F10) -> 3443207 | G11: =SUM(C11-F11) -> 164066.75 | H11: =G11/F11 -> 0.047649401
A12: =A11+1 -> 7
A13: =A12+1 -> 8 | B13: Contributions | C13: 168400 | D13: =+C13/$C$33 -> 0.03633246 | F13: 129500 | G13: =SUM(C13-F13) -> 38900 | H13: =G13/F13 -> 0.3003861
A14: =A13+1 -> 9
A15: =A14+1 -> 10 | B15: Foundations & Grants
A16: =A15+1 -> 11 | B16: United Ways | C16: 85900 | D16: =+C16/$C$33 -> 0.018533007 | F16: 85900 | G16: =SUM(C16-F16) -> 0 | H16: =G16/F16 -> 0
A17: =A16+1 -> 12 | B17: Foundations & Other Grants | C17: 200000 | D17: =+C17/$C$33 -> 0.04315019 | F17: 86000 | G17: =SUM(C17-F17) -> 114000 | H17: =G17/F17 -> 1.3255814
A18: =A17+1 -> 13 | B18: Government Agency Grants | C18: 53413 | D18: =+C18/$C$33 -> 0.011523906 | F18: 50000 | G18: =SUM(C18-F18) -> 3413 | H18: =G18/F18 -> 0.06826
A19: =A18+1 -> 14 | B19: Total Foundations & Grants | C19: =SUM(C16:C18) -> 339313 | D19: =SUM(D16:D18) -> 0.073207103 | F19: =SUM(F16:F18) -> 221900 | G19: =SUM(G16:G18) -> 117413 | H19: =G19/F19 -> 0.52912573
A20: =A19+1 -> 15
A21: =A20+1 -> 16 | B21: Program Fees
A22: =A21+1 -> 17 | B22: Resident Camp Fees | C22: 206650 | D22: =+C22/$C$33 -> 0.044584934 | F22: 178750 | G22: =SUM(C22-F22) -> 27900 | H22: =G22/F22 -> 0.15608392
A23: =A22+1 -> 18 | B23: Day Camp Fees | C23: 52000 | D23: =+C23/$C$33 -> 0.01121905 | F23: 52000 | G23: =SUM(C23-F23) -> 0 | H23: =G23/F23 -> 0
A24: =A23+1 -> 19 | B24: Total Resident and Day Camp | C24: =SUM(C22:C23) -> 258650 | D24: =+C24/$C$33 -> 0.055803984 | F24: 230750 | G24: =SUM(C24-F24) -> 27900 | H24: =G24/F24 -> 0.12091008
A25: =A24+1 -> 20 | B25: Troop Camp Fees | C25: 33900 | D25: =+C25/$C$33 -> 0.0073139573 | F25: 66830 | G25: =SUM(C25-F25) -> -32930 | H25: =G25/F25 -> -0.49274278
A26: =A25+1 -> 21 | B26: Year Round Program Fees | C26: =120467+6970 -> 127437 | D26: =+C26/$C$33 -> 0.027494654 | F26: 73685 | G26: =SUM(C26-F26) -> 53752 | H26: =G26/F26 -> 0.72948361
A27: =A26+1 -> 22 | B27: Total Program Fees | C27: =SUM(C24:C26) -> 419987 | D27: =+C27/$C$33 -> 0.090612595 | F27: =SUM(F24:F26) -> 371265 | G27: =SUM(C27-F27) -> 48722 | H27: =G27/F27 -> 0.13123241
A28: =A27+1 -> 23 | B28: Fund Raising Events | C28: 80000 | D28: =+C28/$C$33 -> 0.017260076 | F28: 68150 | G28: =SUM(C28-F28) -> 11850 | H28: =G28/F28 -> 0.17388114
A29: =A28+1 -> 24 | B29: Outside Usage Group Fees | C29: 0 | D29: =+C29/$C$33 -> 0 | F29: 0 | G29: =SUM(C29-F29) -> 0
A30: =A29+1 -> 25 | B30: Rental Income | C30: 0 | D30: =+C30/$C$33 -> 0 | F30: 19200 | G30: =SUM(C30-F30) -> -19200 | H30: =G30/F30 -> -1
A31: =A30+1 -> 26 | B31: Investment Income | C31: 0 | D31: =+C31/$C$33 -> 0 | F31: 48000 | G31: =SUM(C31-F31) -> -48000 | H31: =G31/F31 -> -1
A32: =A31+1 -> 27 | B32: Donated Goods,Service & Facility | C32: 20000 | D32: =+C32/$C$33 -> 0.004315019 | F32: 38500 | H32: =G32/F32 -> 0
A33: =A32+1 -> 28 | B33: Total Revenues | C33: =C11+C13+C19+C27+C28+C29+C30+C31+C32 -> 4634973.8 | D33: =D11+D13+D19+D27+D28+D29+D30+D31+D32 -> 1 | F33: =F11+F13+F19+F27+F28+F29+F30+F31+F32 -> 4339722 | G33: =G11+G13+G19+G27+G28+G29+G30+G31+G32 -> 313751.75 | H33: =G33/F33 -> 0.072297661
A35: 29 | B35: Expenditures
A36: =A35+1 -> 30 | B36: Labor Cost
A37: =A36+1 -> 31 | B37: Salaries | C37: 2274738 | D37: =+C37/$C$84 -> 0.49143094 | F37: 1887477 | G37: =SUM(C37-F37) -> 387261 | H37: =G37/F37 -> 0.20517389
A38: =A37+1 -> 32 | B38: Seasonal Camp Staff | C38: 100000 | D38: =+C38/$C$84 -> 0.021603848 | F38: 123350 | G38: =SUM(C38-F38) -> -23350 | H38: =G38/F38 -> -0.18929874
A39: =A38+1 -> 33 | B39: Interim CEO | C39: 0 | D39: =+C39/$C$84 -> 0 | F39: 20000 | G39: =SUM(C39-F39) -> -20000 | H39: =G39/F39 -> -1
A40: =A39+1 -> 34 | B40: Employee Benefits | C40: 531103 | D40: =+C40/$C$84 -> 0.11473869 | F40: 553210 | G40: =SUM(C40-F40) -> -22107 | H40: =G40/F40 -> -0.039961317
A41: =A40+1 -> 35 | B41: Contract-Hire Services | C41: =500+5500 -> 6000 | D41: =+C41/$C$84 -> 0.0012962309 | F41: 4600 | G41: =SUM(C41-F41) -> 1400 | H41: =G41/F41 -> 0.30434783
A42: =A41+1 -> 36 | B42: Total Labor Cost | C42: =SUM(C37:C41) -> 2911841 | D42: =SUM(D37:D41) -> 0.62906971 | F42: =SUM(F37:F41) -> 2588637 | G42: =SUM(G37:G41) -> 323204 | H42: =G42/F42 -> 0.12485489
A43: =A42+1 -> 37
A44: =A43+1 -> 38 | B44: Facility Cost
A45: =A44+1 -> 39 | B45: Occupancy | C45: 207358 | D45: =+C45/$C$84 -> 0.044797307 | F45: 230926 | G45: =SUM(C45-F45) -> -23568 | H45: =G45/F45 -> -0.10205867
A46: =A45+1 -> 40 | B46: Insurance | C46: 123900 | D46: =+C46/$C$84 -> 0.026767168 | F46: 141057 | G46: =SUM(C46-F46) -> -17157 | H46: =G46/F46 -> -0.12163168
A47: =A46+1 -> 41 | B47: Interest | C47: 28200 | D47: =+C47/$C$84 -> 0.0060922852 | F47: 26300 | G47: =SUM(C47-F47) -> 1900 | H47: =G47/F47 -> 0.072243346
A48: =A47+1 -> 42 | B48: Telephone | C48: 65840 | D48: =+C48/$C$84 -> 0.014223974 | F48: 41746 | G48: =SUM(C48-F48) -> 24094 | H48: =G48/F48 -> 0.57715709
A49: =A48+1 -> 43 | B49: Equipment Rental | C49: 36614 | D49: =+C49/$C$84 -> 0.0079100329 | F49: 50650 | G49: =SUM(C49-F49) -> -14036 | H49: =G49/F49 -> -0.27711747
A50: =A49+1 -> 44 | B50: Equipment Maintenance | C50: 28600 | D50: =+C50/$C$84 -> 0.0061787006 | F50: 30930 | G50: =SUM(C50-F50) -> -2330 | H50: =G50/F50 -> -0.075331393
A51: =A50+1 -> 45 | B51: Information Technology | C51: 168000 | D51: =+C51/$C$84 -> 0.036294465 | F51: 147463 | G51: =SUM(C51-F51) -> 20537 | H51: =G51/F51 -> 0.13926883
A52: =A51+1 -> 46 | B52: Equipment < $1,000 | C52: 10250 | D52: =+C52/$C$84 -> 0.0022143944 | F52: 10350 | G52: =SUM(C52-F52) -> -100 | H52: =G52/F52 -> -0.0096618357
A53: =A52+1 -> 47 | B53: Computer Software | C53: 0 | D53: =+C53/$C$84 -> 0 | F53: 11045 | G53: =SUM(C53-F53) -> -11045 | H53: =G53/F53 -> -1
A54: =A53+1 -> 48 | B54: Total Facility Cost | C54: =SUM(C45:C53) -> 668762 | D54: =SUM(D45:D53) -> 0.14447833 | F54: =SUM(F45:F53) -> 690467 | G54: =SUM(G45:G53) -> -21705 | H54: =G54/F54 -> -0.031435246
A55: =A54+1 -> 49
A56: =A55+1 -> 50 | B56: Administrative Expense
A57: =A56+1 -> 51 | B57: Professional Fees | C57: 105300 | D57: =+C57/$C$84 -> 0.022748852 | F57: 137695 | G57: =SUM(C57-F57) -> -32395 | H57: =G57/F57 -> -0.23526635
A58: =A57+1 -> 52 | B58: Office & General Supplies | C58: 33500 | D58: =+C58/$C$84 -> 0.0072372891 | F58: 34490 | G58: =SUM(C58-F58) -> -990 | H58: =G58/F58 -> -0.028703972
A59: =A58+1 -> 53 | B59: Bank & Merchant Fees | C59: 30400 | D59: =+C59/$C$84 -> 0.0065675698 | F59: 37100 | G59: =SUM(C59-F59) -> -6700 | H59: =G59/F59 -> -0.18059299
A60: =A59+1 -> 54 | B60: Bad Debt | C60: 0 | D60: =+C60/$C$84 -> 0 | F60: 55000 | G60: =SUM(C60-F60) -> -55000 | H60: =G60/F60 -> -1
A61: =A60+1 -> 55 | B61: Total Administrative Expense | C61: =SUM(C57:C60) -> 169200 | D61: =SUM(D57:D60) -> 0.036553711 | F61: =SUM(F57:F60) -> 264285 | G61: =SUM(G57:G60) -> -95085 | H61: =G61/F61 -> -0.35978205
A62: =A61+1 -> 56
A63: =A62+1 -> 57 | B63: Program Cost
A64: =A63+1 -> 58 | B64: Program Supplies & Expense | C64: 270432 | D64: =+C64/$C$84 -> 0.058423718 | F64: 210942 | G64: =SUM(C64-F64) -> 59490 | H64: =G64/F64 -> 0.28202065
A65: =A64+1 -> 59 | B65: Food Cost | C65: 85000 | D65: =+C65/$C$84 -> 0.018363271 | F65: 93443 | G65: =SUM(C65-F65) -> -8443 | H65: =G65/F65 -> -0.090354548
A66: =A65+1 -> 60 | B66: Postage & Shipping | C66: 19000 | D66: =+C66/$C$84 -> 0.0041047311 | F66: 37823 | G66: =SUM(C66-F66) -> -18823 | H66: =G66/F66 -> -0.49766015
A67: =A66+1 -> 61 | B67: Printing & Publications | C67: 20000 | D67: =+C67/$C$84 -> 0.0043207696 | F67: 44662 | G67: =SUM(C67-F67) -> -24662 | H67: =G67/F67 -> -0.55219202
A68: =A67+1 -> 62 | B68: Transportation | C68: 25500 | D68: =+C68/$C$84 -> 0.0055089813 | F68: 23785 | G68: =SUM(C68-F68) -> 1715 | H68: =G68/F68 -> 0.072104267
A69: =A68+1 -> 63 | B69: Mileage Reimbursement | C69: 47500 | D69: =+C69/$C$84 -> 0.010261828 | F69: 60000 | G69: =SUM(C69-F69) -> -12500 | H69: =G69/F69 -> -0.20833333
A70: =A69+1 -> 64 | B70: Meetings & Special Events | C70: 91570 | D70: =+C70/$C$84 -> 0.019782644 | F70: 62135 | G70: =SUM(C70-F70) -> 29435 | H70: =G70/F70 -> 0.47372656
A71: =A70+1 -> 65 | B71: Assistance to Girls & Adults | C71: 56000 | D71: =+C71/$C$84 -> 0.012098155 | F71: 56000 | G71: =SUM(C71-F71) -> 0 | H71: =G71/F71 -> 0
A72: =A71+1 -> 66 | B72: Recruitment Expense | C72: 0 | D72: =+C72/$C$84 -> 0 | F72: 9880 | G72: =SUM(C72-F72) -> -9880 | H72: =G72/F72 -> -1
A73: =A72+1 -> 67 | B73: Total Program cost | C73: =SUM(C64:C72) -> 615002 | D73: =SUM(D64:D72) -> 0.1328641 | F73: =SUM(F64:F72) -> 598670 | G73: =SUM(G64:G72) -> 16332 | H73: =G73/F73 -> 0.027280472
A74: =A73+1 -> 68
A75: =A74+1 -> 69 | B75: Total Expenditures before Depreciation | C75: =C42+C54+C61+C73 -> 4364805 | D75: =D42+D54+D61+D73 -> 0.94296584 | F75: =F42+F54+F61+F73 -> 4142059 | G75: =G42+G54+G61+G73 -> 222746 | H75: =G75/F75 -> 0.053776636
A76: =A75+1 -> 70
A77: =A76+1 -> 71 | B77: Excess of Revenues over Expenditures
A78: =A77+1 -> 72 | B78: before Depreciation | C78: =C33-C75 -> 270168.75 | F78: =F33-F75 -> 197663 | H78: =G78/F78 -> 0
A79: =A78+1 -> 73 | B79: Depreciation Expense | C79: 264000 | D79: =+C79/$C$84 -> 0.057034159 | F79: 264800 | G79: =SUM(C79-F79) -> -800 | H79: =G79/F79 -> -0.003021148
A80: =A79+1 -> 74 | B80: Budget Surplus/(Deficit) | C80: =C78-C79 -> 6168.75 | F80: =F78-F79 -> -67137 | H80: =G80/F80 -> 0
A81: =A80+1 -> 75
A82: =A81+1 -> 76 | B82: 2010-2011 Budget Recap:
A83: =A82+1 -> 77 | B83: Total Budgeted Revenues | C83: =+C33 -> 4634973.8 | F83: =+F33 -> 4339722 | G83: =+G33 -> 313751.75 | H83: =G83/F83 -> 0.072297661
A84: =A83+1 -> 78 | B84: Total Budgeted Expenditures | C84: =+C75+C79 -> 4628805 | F84: =+F75+F79 -> 4406859 | G84: =+G75 -> 222746 | H84: =G84/F84 -> 0.050545298
A85: =A84+1 -> 79 | B85: Budget Surplus/(Deficit) | C85: =+C83-C84 -> 6168.75 | F85: =+F83-F84 -> -67137 | G85: =+G83-G84 -> 91005.75 | H85: =G85/F85 -> -1.355523

Sheet Summary by major Area
C1: Year Ending
C2: 41547 | D2: 41547
C3: Budget | F3: Admin | G3: Grant | H3: Gifts | I3: Events | J3: Product Sales/Shop | K3: Program | L3: Camp | M3: Facilities | O3: Total
C4: Draft | D4: % of Total
A6: 1 | B6: Revenues
A7: =A6+1 -> 2 | B7: Product & Council Shop Revenue, Net
A8: =A7+1 -> 3 | B8: Cookie Income, Net | C8: ='2013 Budget'!C8 -> 3082394 | D8: 0.665 | F8: 0 | G8: 0 | H8: 0 | I8: 0 | J8: ='2013 Budget'!C8 -> 3082394 | K8: 0 | L8: 0 | M8: 0 | O8: =SUM(F8:M8) -> 3082394
A9: =A8+1 -> 4 | B9: Fall Products, Net | C9: ='2013 Budget'!C9 -> 344629.75 | D9: 0.074 | F9: 0 | G9: 0 | H9: 0 | I9: 0 | J9: ='2013 Budget'!C9 -> 344629.75 | K9: 0 | L9: 0 | M9: 0 | O9: =SUM(F9:M9) -> 344629.75
A10: =A9+1 -> 5 | B10: Council Shop Income, Net | C10: ='2013 Budget'!C10 -> 180250 | D10: 0.039 | F10: 0 | G10: 0 | H10: 0 | I10: 0 | J10: ='2013 Budget'!C10 -> 180250 | K10: 0 | L10: 0 | M10: 0 | O10: =SUM(F10:M10) -> 180250 | U10: 0
A11: =A10+1 -> 6 | B11: Total Product & Council Shop Revenue | C11: =SUM(C8:C10) -> 3607273.8 | D11: =SUM(D8:D10) -> 0.778 | F11: =SUM(F8:F10) -> 0 | G11: =SUM(G8:G10) -> 0 | H11: =SUM(H8:H10) -> 0 | I11: =SUM(I8:I10) -> 0 | J11: =SUM(J8:J10) -> 3607273.8 | K11: =SUM(K8:K10) -> 0 | L11: =SUM(L8:L10) -> 0 | M11: =SUM(M8:M10) -> 0 | O11: =SUM(O8:O10) -> 3607273.8
A12: =A11+1 -> 7
A13: =A12+1 -> 8 | B13: Contributions | C13: ='2013 Budget'!C13 -> 168400 | D13: 0.036 | F13: 0 | G13: =SUM('Detail Summary'!F9) -> 0 | H13: 154400 | I13: 0 | J13: 0 | K13: 14000 | L13: 0 | M13: 0 | O13: =SUM(F13:M13) -> 168400 | Q13: =C13-O13 -> 0
A14: =A13+1 -> 9 | Q14: =C14-O14 -> 0
A15: =A14+1 -> 10 | B15: Foundations & Grants | Q15: =C15-O15 -> 0
A16: =A15+1 -> 11 | B16: United Ways | C16: =SUM(F16:M16) -> 85900 | D16: 0.019 | F16: 0 | G16: =SUM('Detail Summary'!F10) -> 85900 | H16: =SUM('Detail Summary'!G10) -> 0 | I16: 0 | J16: 0 | K16: 0 | L16: 0 | M16: 0 | O16: =SUM(F16:M16) -> 85900 | Q16: =C16-O16 -> 0
A17: =A16+1 -> 12 | B17: Foundations & Other Grants | C17: ='2013 Budget'!C17 -> 200000 | D17: 0.043 | F17: 0 | G17: 125000 | H17: 75000 | I17: 0 | J17: 0 | K17: 0 | L17: 0 | M17: 0 | O17: =SUM(F17:M17) -> 200000 | Q17: =C17-O17 -> 0
A18: =A17+1 -> 13 | B18: Government Agency Grants | C18: ='2013 Budget'!C18 -> 53413 | D18: 0.012 | F18: 0 | G18: 53413 | H18: =SUM('Detail Summary'!G15) -> 0 | I18: 0 | J18: 0 | K18: 0 | L18: 0 | M18: 0 | O18: =SUM(F18:M18) -> 53413 | Q18: =C18-O18 -> 0
A19: =A18+1 -> 14 | B19: Total Foundations & Grants | C19: =SUM(C16:C18) -> 339313 | D19: =SUM(D16:D18) -> 0.074 | F19: =SUM(F16:F18) -> 0 | G19: =SUM(G16:G18) -> 264313 | H19: =SUM(H16:H18) -> 75000 | I19: =SUM(I16:I18) -> 0 | J19: =SUM(J16:J18) -> 0 | K19: =SUM(K16:K18) -> 0 | L19: =SUM(L16:L18) -> 0 | M19: =SUM(M16:M18) -> 0 | O19: =SUM(O16:O18) -> 339313 | Q19: =C19-O19 -> 0
A20: =A19+1 -> 15 | Q20: =C20-O20 -> 0
A21: =A20+1 -> 16 | B21: Program Fees | Q21: =C21-O21 -> 0
A22: =A21+1 -> 17 | B22: Resident Camp Fees | C22: ='2013 Budget'!C22 -> 206650 | D22: 0.045 | F22: 0 | G22: 0 | H22: 0 | I22: 0 | J22: 0 | K22: 0 | L22: 206650 | M22: 0 | O22: =SUM(F22:M22) -> 206650 | Q22: =C22-O22 -> 0
A23: =A22+1 -> 18 | B23: Day Camp Fees | C23: ='2013 Budget'!C23 -> 52000 | D23: 0.011 | F23: 0 | G23: 0 | H23: 0 | I23: 0 | J23: 0 | K23: 0 | L23: 52000 | M23: 0 | O23: =SUM(F23:M23) -> 52000 | Q23: =C23-O23 -> 0
A24: =A23+1 -> 19 | B24: Total Resident and Day Camp | C24: =SUM(C22:C23) -> 258650 | D24: 0.056 | F24: =SUM(F22:F23) -> 0 | G24: =SUM(G22:G23) -> 0 | H24: =SUM(H22:H23) -> 0 | I24: =SUM(I22:I23) -> 0 | J24: =SUM(J22:J23) -> 0 | K24: =SUM(K22:K23) -> 0 | L24: =SUM(L22:L23) -> 258650 | M24: =SUM(M22:M23) -> 0 | O24: =SUM(O22:O23) -> 258650 | Q24: =C24-O24 -> 0
A25: =A24+1 -> 20 | B25: Troop Camp Fees | C25: ='2013 Budget'!C25 -> 33900 | D25: 0.007 | F25: 0 | G25: 0 | H25: 0 | I25: 0 | J25: 0 | K25: 0 | L25: 33900 | M25: 0 | O25: =SUM(F25:M25) -> 33900 | Q25: =C25-O25 -> 0
A26: =A25+1 -> 21 | B26: Year Round Program Fees | C26: ='2013 Budget'!C26 -> 127437 | D26: 0.027 | F26: 6970 | G26: =SUM('Detail Summary'!F28) -> 0 | H26: 0 | I26: 0 | J26: 0 | K26: 120467 | L26: 0 | M26: 0 | O26: =SUM(F26:M26) -> 127437 | Q26: =C26-O26 -> 0
A27: =A26+1 -> 22 | B27: Total Program Fees | C27: =SUM(C24:C26) -> 419987 | D27: 0.091 | F27: =SUM(F24:F26) -> 6970 | G27: =SUM(G24:G26) -> 0 | H27: =SUM(H24:H26) -> 0 | I27: =SUM(I24:I26) -> 0 | J27: =SUM(J24:J26) -> 0 | K27: =SUM(K24:K26) -> 120467 | L27: =SUM(L24:L26) -> 292550 | M27: =SUM(M24:M26) -> 0 | O27: =SUM(O24:O26) -> 419987 | Q27: =C27-O27 -> 0
A28: =A27+1 -> 23 | B28: Fund Raising Events | C28: ='2013 Budget'!C28 -> 80000 | D28: 0.017 | F28: 0 | G28: =SUM('Detail Summary'!F16) -> 0 | H28: 0 | I28: 80000 | J28: 0 | K28: 0 | L28: 0 | M28: 0 | O28: =SUM(F28:M28) -> 80000 | Q28: =C28-O28 -> 0
A29: =A28+1 -> 24 | B29: Outside Usage Group Fees | C29: 0 | D29: 0 | F29: 0 | G29: 0 | H29: 0 | I29: 0 | J29: 0 | K29: 0 | L29: 0 | M29: 0 | O29: =SUM(F29:M29) -> 0 | Q29: =C29-O29 -> 0
A30: =A29+1 -> 25 | B30: Rental Income | C30: 0 | D30: 0 | F30: 0 | G30: =SUM('Detail Summary'!F34) -> 0 | H30: 0 | I30: 0 | J30: 0 | K30: 0 | L30: 0 | M30: 0 | O30: =SUM(F30:M30) -> 0 | Q30: =C30-O30 -> 0
A31: =A30+1 -> 26 | B31: Investment Income | C31: 0 | D31: 0 | F31: 0 | G31: =SUM('Detail Summary'!F37:F38) -> 0 | H31: 0 | I31: 0 | J31: 0 | K31: 0 | L31: 0 | M31: 0 | O31: =SUM(F31:M31) -> 0 | Q31: =C31-O31 -> 0
A32: =A31+1 -> 27 | B32: Donated Goods,Service & Facility | C32: ='2013 Budget'!C32 -> 20000 | D32: 0.004 | F32: 0 | G32: =SUM('Detail Summary'!F11:F14) -> 0 | H32: 0 | I32: 20000 | J32: 0 | K32: 0 | L32: 0 | M32: 0 | O32: =SUM(F32:M32) -> 20000 | Q32: =C32-O32 -> 0
A33: =A32+1 -> 28 | B33: Total Revenues | C33: =C11+C13+C19+C27+C28+C29+C30+C31+C32 -> 4634973.8 | D33: =D11+D13+D19+D27+D28+D29+D30+D31+D32 -> 1 | F33: =F11+F13+F19+F27+F28+F29+F30+F31+F32 -> 6970 | G33: =G11+G13+G19+G27+G28+G29+G30+G31+G32 -> 264313 | H33: =H11+H13+H19+H27+H28+H29+H30+H31+H32 -> 229400 | I33: =I11+I13+I19+I27+I28+I29+I30+I31+I32 -> 100000 | J33: =J11+J13+J19+J27+J28+J29+J30+J31+J32 -> 3607273.8 | K33: =K11+K13+K19+K27+K28+K29+K30+K31+K32 -> 134467 | L33: =L11+L13+L19+L27+L28+L29+L30+L31+L32 -> 292550 | M33: =M11+M13+M19+M27+M28+M29+M30+M31+M32 -> 0 | O33: =O11+O13+O19+O27+O28+O29+O30+O31+O32 -> 4634973.8 | Q33: =C33-O33 -> 0
Q34: =C34-O34 -> 0
A35: 29 | B35: Expenditures | Q35: =C35-O35 -> 0
A36: =A35+1 -> 30 | B36: Labor Cost | Q36: =C36-O36 -> 0
A37: =A36+1 -> 31 | B37: Salaries | C37: ='2013 Budget'!C37 -> 2274738 | D37: =+C37/$C$84 -> 0.49143094 | F37: 2274738 | G37: =SUM('Detail Summary'!F50:F51)+SUM('Detail Summary'!F53:F54) -> 0 | H37: 0 | I37: 0 | J37: 0 | K37: 0 | L37: 0 | M37: 0 | O37: =SUM(F37:M37) -> 2274738 | Q37: =C37-O37 -> 0
A38: =A37+1 -> 32 | B38: Seasonal Camp Staff | C38: ='2013 Budget'!C38 -> 100000 | D38: =+C38/$C$84 -> 0.021603848 | F38: 0 | G38: =SUM('Detail Summary'!F52) -> 0 | H38: 0 | I38: 0 | J38: 0 | K38: 0 | L38: 100000 | M38: 0 | O38: =SUM(F38:M38) -> 100000 | Q38: =C38-O38 -> 0
A39: =A38+1 -> 33 | B39: Interim CEO | C39: ='2013 Budget'!C39 -> 0 | D39: =+C39/$C$84 -> 0 | F39: 0 | G39: =SUM('Detail Summary'!F124) -> 0 | H39: 0 | I39: 0 | J39: 0 | K39: 0 | L39: 0 | M39: 0 | O39: =SUM(F39:M39) -> 0 | Q39: =C39-O39 -> 0
A40: =A39+1 -> 34 | B40: Employee Benefits | C40: ='2013 Budget'!C40 -> 531103 | D40: =+C40/$C$84 -> 0.11473869 | F40: 512679 | G40: =SUM('Detail Summary'!F55:F62)+SUM('Detail Summary'!F64:F66) -> 0 | H40: 0 | I40: 0 | J40: 0 | K40: 0 | L40: 18424 | M40: 0 | O40: =SUM(F40:M40) -> 531103 | Q40: =C40-O40 -> 0
A41: =A40+1 -> 35 | B41: Contract-Hire Services | C41: ='2013 Budget'!C41 -> 6000 | D41: =+C41/$C$84 -> 0.0012962309 | F41: 0 | G41: =SUM('Detail Summary'!F53) -> 0 | H41: 0 | I41: 0 | J41: 6000 | K41: 0 | L41: 0 | M41: 0 | O41: =SUM(F41:M41) -> 6000 | Q41: =C41-O41 -> 0
A42: =A41+1 -> 36 | B42: Total Labor Cost | C42: =SUM(C37:C41) -> 2911841 | D42: =SUM(D37:D41) -> 0.62906971 | F42: =SUM(F37:F41) -> 2787417 | G42: =SUM(G37:G41) -> 0 | H42: =SUM(H37:H41) -> 0 | I42: =SUM(I37:I41) -> 0 | J42: =SUM(J37:J41) -> 6000 | K42: =SUM(K37:K41) -> 0 | L42: =SUM(L37:L41) -> 118424 | M42: =SUM(M37:M41) -> 0 | O42: =SUM(O37:O41) -> 2911841 | Q42: =C42-O42 -> 0
A43: =A42+1 -> 37 | Q43: =C43-O43 -> 0
A44: =A43+1 -> 38 | B44: Facility Cost | Q44: =C44-O44 -> 0
A45: =A44+1 -> 39 | B45: Occupancy | C45: ='2013 Budget'!C45 -> 207358 | D45: =+C45/$C$84 -> 0.044797307 | F45: 0 | G45: =SUM('Detail Summary'!F97:F98)+SUM('Detail Summary'!F104:F108)+SUM('Detail Summary'!F148:F149) -> 0 | H45: 0 | I45: 5060 | J45: 0 | K45: 1540 | L45: 1500 | M45: 199258 | O45: =SUM(F45:M45) -> 207358 | Q45: =C45-O45 -> 0
A46: =A45+1 -> 40 | B46: Insurance | C46: ='2013 Budget'!C46 -> 123900 | D46: =+C46/$C$84 -> 0.026767168 | F46: 6600 | G46: =SUM('Detail Summary'!F136:F140) -> 0 | H46: 0 | I46: 0 | J46: 0 | K46: 1511 | L46: 863 | M46: 114926 | O46: =SUM(F46:M46) -> 123900 | Q46: =C46-O46 -> 0
A47: =A46+1 -> 41 | B47: Interest | C47: ='2013 Budget'!C47 -> 28200 | D47: =+C47/$C$84 -> 0.0060922852 | F47: 0 | G47: =SUM('Detail Summary'!F103) -> 0 | H47: 0 | I47: 0 | J47: 0 | K47: 0 | L47: 0 | M47: 28200 | O47: =SUM(F47:M47) -> 28200 | Q47: =C47-O47 -> 0
A48: =A47+1 -> 42 | B48: Telephone | C48: ='2013 Budget'!C48 -> 65840 | D48: =+C48/$C$84 -> 0.014223974 | F48: 65840 | G48: =SUM('Detail Summary'!F91) -> 0 | H48: 0 | I48: 0 | J48: 0 | K48: 0 | L48: 0 | M48: 0 | O48: =SUM(F48:M48) -> 65840 | Q48: =C48-O48 -> 0
A49: =A48+1 -> 43 | B49: Equipment Rental | C49: ='2013 Budget'!C49 -> 36614 | D49: =+C49/$C$84 -> 0.0079100329 | F49: 27270 | G49: =SUM('Detail Summary'!F112) -> 0 | H49: 0 | I49: 1400 | J49: 1500 | K49: 0 | L49: 0 | M49: 6444 | O49: =SUM(F49:M49) -> 36614 | Q49: =C49-O49 -> 0
A50: =A49+1 -> 44 | B50: Equipment Maintenance | C50: ='2013 Budget'!C50 -> 28600 | D50: =+C50/$C$84 -> 0.0061787006 | F50: 21500 | G50: =SUM('Detail Summary'!F113+'Detail Summary'!F114+'Detail Summary'!F121) -> 0 | H50: 0 | I50: 0 | J50: 300 | K50: 0 | L50: 0 | M50: 6800 | O50: =SUM(F50:M50) -> 28600 | Q50: =C50-O50 -> 0
A51: =A50+1 -> 45 | B51: Information Technology | C51: ='2013 Budget'!C51 -> 168000 | D51: =+C51/$C$84 -> 0.036294465 | F51: 168000 | G51: =SUM('Detail Summary'!F73+'Detail Summary'!F93) -> 0 | H51: 0 | I51: 0 | J51: 0 | K51: 0 | L51: 0 | M51: 0 | O51: =SUM(F51:M51) -> 168000 | Q51: =C51-O51 -> 0
A52: =A51+1 -> 46 | B52: Equipment < $1,000 | C52: ='2013 Budget'!C52 -> 10250 | D52: =+C52/$C$84 -> 0.0022143944 | F52: 5000 | G52: =SUM('Detail Summary'!F110+'Detail Summary'!F111) -> 0 | H52: 0 | I52: 0 | J52: 250 | K52: 1200 | L52: 2800 | M52: 1000 | O52: =SUM(F52:M52) -> 10250 | Q52: =C52-O52 -> 0
A53: =A52+1 -> 47 | B53: Computer Software | C53: ='2013 Budget'!C53 -> 0 | D53: =+C53/$C$84 -> 0 | F53: 0 | G53: =SUM('Detail Summary'!F115) -> 0 | H53: 0 | I53: 0 | J53: 0 | K53: 0 | L53: 0 | M53: 0 | O53: =SUM(F53:M53) -> 0 | Q53: =C53-O53 -> 0
A54: =A53+1 -> 48 | B54: Total Facility Cost | C54: =SUM(C45:C53) -> 668762 | D54: =SUM(D45:D53) -> 0.14447833 | F54: =SUM(F45:F53) -> 294210 | G54: =SUM(G45:G53) -> 0 | H54: =SUM(H45:H53) -> 0 | I54: =SUM(I45:I53) -> 6460 | J54: =SUM(J45:J53) -> 2050 | K54: =SUM(K45:K53) -> 4251 | L54: =SUM(L45:L53) -> 5163 | M54: =SUM(M45:M53) -> 356628 | ... O54: =SUM(O45:O53) -> 668762 | Q54: =C54-O54 -> 0
A55: =A54+1 -> 49 | Q55: =C55-O55 -> 0
A56: =A55+1 -> 50 | B56: Administrative Expense | Q56: =C56-O56 -> 0
A57: =A56+1 -> 51 | B57: Professional Fees | C57: ='2013 Budget'!C57 -> 105300 | D57: =+C57/$C$84 -> 0.022748852 | F57: 66055 | G57: =SUM('Detail Summary'!F67+'Detail Summary'!F68+'Detail Summary'!F69+'Detail Summary'!F71+'Detail Summary'!F72+'Detail Summary'!F75) -> 0 | H57: 0 | I57: 26500 | J57: 500 | K57: 7245 | L57: 5000 | M57: 0 | O57: =SUM(F57:M57) -> 105300 | Q57: =C57-O57 -> 0
A58: =A57+1 -> 52 | B58: Office & General Supplies | C58: ='2013 Budget'!C58 -> 33500 | D58: =+C58/$C$84 -> 0.0072372891 | F58: 11294 | G58: =SUM('Detail Summary'!F85+'Detail Summary'!F90) -> 0 | H58: 0 | I58: 0 | J58: 9900 | K58: 10906 | L58: 1400 | M58: 0 | O58: =SUM(F58:M58) -> 33500 | Q58: =C58-O58 -> 0
A59: =A58+1 -> 53 | B59: Bank & Merchant Fees | C59: ='2013 Budget'!C59 -> 30400 | D59: =+C59/$C$84 -> 0.0065675698 | F59: 19300 | G59: =SUM('Detail Summary'!F144+'Detail Summary'!F145) -> 0 | H59: 0 | I59: 0 | J59: 11100 | K59: 0 | L59: 0 | M59: 0 | O59: =SUM(F59:M59) -> 30400 | Q59: =C59-O59 -> 0
A60: =A59+1 -> 54 | B60: Bad Debt | C60: ='2013 Budget'!C60 -> 0 | D60: =+C60/$C$84 -> 0 | F60: 0 | G60: =SUM('Detail Summary'!F146) -> 0 | H60: 0 | I60: 0 | J60: 0 | K60: 0 | L60: 0 | M60: 0 | O60: =SUM(F60:M60) -> 0 | Q60: =C60-O60 -> 0
A61: =A60+1 -> 55 | B61: Total Administrative Expense | C61: =SUM(C57:C60) -> 169200 | D61: =SUM(D57:D60) -> 0.036553711 | F61: =SUM(F57:F60) -> 96649 | G61: =SUM(G57:G60) -> 0 | H61: =SUM(H57:H60) -> 0 | I61: =SUM(I57:I60) -> 26500 | J61: =SUM(J57:J60) -> 21500 | K61: =SUM(K57:K60) -> 18151 | L61: =SUM(L57:L60) -> 6400 | M61: =SUM(M57:M60) -> 0 | ... O61: =SUM(O57:O60) -> 169200 | Q61: =C61-O61 -> 0
A62: =A61+1 -> 56 | Q62: =C62-O62 -> 0
A63: =A62+1 -> 57 | B63: Program Cost | Q63: =C63-O63 -> 0
A64: =A63+1 -> 58 | B64: Program Supplies & Expense | C64: ='2013 Budget'!C64 -> 270432 | D64: =+C64/$C$84 -> 0.058423718 | F64: 29240 | G64: =SUM('Detail Summary'!F76+'Detail Summary'!F86+'Detail Summary'!F89) -> 0 | H64: 7200 | I64: 30850 | J64: 10400 | K64: 98172 | L64: 94570 | M64: 0 | O64: =SUM(F64:M64) -> 270432 | Q64: =C64-O64 -> 0 | R64: 201217
A65: =A64+1 -> 59 | B65: Food Cost | C65: ='2013 Budget'!C65 -> 85000 | D65: =+C65/$C$84 -> 0.018363271 | F65: 6640 | G65: =SUM('Detail Summary'!F84) -> 0 | H65: 721 | I65: 14750 | J65: 3800 | K65: 22004 | L65: 37085 | M65: 0 | O65: =SUM(F65:M65) -> 85000 | Q65: =C65-O65 -> 0 | R65: 91103
A66: =A65+1 -> 60 | B66: Postage & Shipping | C66: ='2013 Budget'!C66 -> 19000 | D66: =+C66/$C$84 -> 0.0041047311 | F66: 12162 | G66: =SUM('Detail Summary'!F94:F96) -> 0 | H66: 1060 | I66: 0 | J66: 0 | K66: 4778 | L66: 1000 | M66: 0 | O66: =SUM(F66:M66) -> 19000 | Q66: =C66-O66 -> 0
A67: =A66+1 -> 61 | B67: Printing & Publications | C67: ='2013 Budget'!C67 -> 20000 | D67: =+C67/$C$84 -> 0.0043207696 | F67: 4400 | G67: =SUM('Detail Summary'!F116:F117) -> 0 | H67: 3000 | I67: 3100 | J67: 1500 | K67: 5000 | L67: 3000 | M67: 0 | O67: =SUM(F67:M67) -> 20000 | Q67: =C67-O67 -> 0 | R67: =R64-R65 -> 110114
A68: =A67+1 -> 62 | B68: Transportation | C68: ='2013 Budget'!C68 -> 25500 | D68: =+C68/$C$84 -> 0.0055089813 | F68: 7025 | G68: =SUM('Detail Summary'!F120+'Detail Summary'!F122) -> 0 | H68: 0 | I68: 0 | J68: 0 | K68: 4360 | L68: 14115 | M68: 0 | O68: =SUM(F68:M68) -> 25500 | Q68: =C68-O68 -> 0
A69: =A68+1 -> 63 | B69: Mileage Reimbursement | C69: ='2013 Budget'!C69 -> 47500 | D69: =+C69/$C$84 -> 0.010261828 | F69: 7200 | G69: =SUM('Detail Summary'!F118) -> 0 | H69: 300 | I69: 800 | J69: 3300 | K69: 34600 | L69: 1300 | M69: 0 | O69: =SUM(F69:M69) -> 47500 | Q69: =C69-O69 -> 0
A70: =A69+1 -> 64 | B70: Meetings & Special Events | C70: 91570 | D70: =+C70/$C$84 -> 0.019782644 | F70: 39838 | G70: =SUM('Detail Summary'!F123+'Detail Summary'!F127+'Detail Summary'!F128) -> 0 | H70: 250 | I70: 29436 | J70: 1800 | K70: 17747 | L70: 2500 | M70: 0 | O70: 91570 | Q70: =C70-O70 -> 0
A71: =A70+1 -> 65 | B71: Assistance to Girls & Adults | C71: ='2013 Budget'!C71 -> 56000 | D71: =+C71/$C$84 -> 0.012098155 | F71: 0 | G71: =SUM('Detail Summary'!F129) -> 0 | H71: 0 | I71: 0 | J71: 0 | K71: 51200 | L71: 4800 | M71: 0 | O71: =SUM(F71:M71) -> 56000 | Q71: =C71-O71 -> 0
A72: =A71+1 -> 66 | B72: Recruitment Expense | C72: ='2013 Budget'!C72 -> 0 | D72: =+C72/$C$84 -> 0 | F72: 0 | G72: =SUM('Detail Summary'!F150)+'Detail Summary'!F63 -> 0 | H72: 0 | I72: 0 | J72: 0 | K72: 0 | L72: 0 | M72: 0 | O72: =SUM(F72:M72) -> 0 | Q72: =C72-O72 -> 0
A73: =A72+1 -> 67 | B73: Total Program cost | C73: =SUM(C64:C72) -> 615002 | D73: =SUM(D64:D72) -> 0.1328641 | F73: =SUM(F64:F72) -> 106505 | G73: =SUM(G64:G72) -> 0 | H73: =SUM(H64:H72) -> 12531 | I73: =SUM(I64:I72) -> 78936 | J73: =SUM(J64:J72) -> 20800 | K73: =SUM(K64:K72) -> 237861 | L73: =SUM(L64:L72) -> 158370 | M73: =SUM(M64:M72) -> 0 | O73: =SUM(O64:O72) -> 615002 | Q73: =C73-O73 -> 0
A74: =A73+1 -> 68 | Q74: =C74-O74 -> 0
A75: =A74+1 -> 69 | B75: Total Expenditures before Depreciation | C75: =C42+C54+C61+C73 -> 4364805 | D75: =D42+D54+D61+D73 -> 0.94296584 | F75: =F42+F54+F61+F73 -> 3284781 | G75: =G42+G54+G61+G73 -> 0 | H75: =H42+H54+H61+H73 -> 12531 | I75: =I42+I54+I61+I73 -> 111896 | J75: =J42+J54+J61+J73 -> 50350 | K75: =K42+K54+K61+K73 -> 260263 | L75: =L42+L54+L61+L73 -> 288357 | M75: =M42+M54+M61+M73 -> 356628 | ... O75: =O42+O54+O61+O73 -> 4364805 | Q75: =C75-O75 -> 0
A76: =A75+1 -> 70 | Q76: =C76-O76 -> 0
A77: =A76+1 -> 71 | B77: Excess of Revenues over Expenditures | Q77: =C77-O77 -> 0
A78: =A77+1 -> 72 | B78: before Depreciation | C78: =C33-C75 -> 270168.75 | F78: =F33-F75 -> -3277811 | G78: =G33-G75 -> 264313 | H78: =H33-H75 -> 216869 | I78: =I33-I75 -> -11896 | J78: =J33-J75 -> 3556923.8 | K78: =K33-K75 -> -125796 | L78: =L33-L75 -> 4193 | M78: =M33-M75 -> -356628 | O78: =SUM(F78:M78) -> 270167.75 | Q78: =C78-O78 -> 1
A79: =A78+1 -> 73 | B79: Depreciation Expense | C79: 264000 | D79: =+C79/$C$84 -> 0.057034159 | F79: 264000 | G79: 0 | H79: 0 | I79: 0 | J79: 0 | K79: 0 | L79: 0 | M79: 0 | O79: =SUM(F79:M79) -> 264000 | Q79: =C79-O79 -> 0
A80: =A79+1 -> 74 | B80: Budget Surplus/(Deficit) | C80: =C78-C79 -> 6168.75 | F80: =F78-F79 -> -3541811 | G80: =G78-G79 -> 264313 | H80: =H78-H79 -> 216869 | I80: =I78-I79 -> -11896 | J80: =J78-J79 -> 3556923.8 | K80: =K78-K79 -> -125796 | L80: =L78-L79 -> 4193 | M80: =M78-M79 -> -356628 | O80: =SUM(F80:M80) -> 6167.75 | Q80: =C80-O80 -> 1
A81: =A80+1 -> 75 | Q81: =C81-O81 -> 0
A82: =A81+1 -> 76 | B82: 2010-2011 Budget Recap: | Q82: =C82-O82 -> 0
A83: =A82+1 -> 77 | B83: Total Budgeted Revenues | C83: =+C33 -> 4634973.8 | Q83: =C83-O83 -> 4634973.8
A84: =A83+1 -> 78 | B84: Total Budgeted Expenditures | C84: =+C75+C79 -> 4628805 | Q84: =C84-O84 -> 4628805
A85: =A84+1 -> 79 | B85: Budget Surplus/(Deficit) | C85: =+C83-C84 -> 6168.75 | Q85: =C85-O85 -> 6168.75
B88: Administrative Column includes strategic learning, finance business services and Hr.
B89: Special Events includes 100th different celebration activities. This is handled by their department, but is not a fund raising activity

Sheet Detail Summary
E1: e | F1: f | G1: Gifts | H1: h | I1: i | J1: j | K1: k | L1: l | N1: m
E2: Admin | F2: Grant | G2: Gifts | H2: Event | I2: Revenue (Products/Shop) | J2: Program Services | K2: Camp | L2: Facilities | N2: Total
A4: 4 | B4: 4100 | C4: Direct Contributions | E4: =SUM(#REF!) -> #REF! | G4: =SUM(#REF!) -> #REF! | H4: =SUM(#REF!) -> #REF! | I4: =SUM(#REF!) -> #REF! | J4: =SUM(#REF!+#REF!+#REF!+#REF!) -> #REF! | K4: =SUM(#REF!) -> #REF! | L4: =SUM(#REF!) -> #REF! | N4: =SUM(E4:M4) -> #REF!
A5: =+A4+1 -> 5 | B5: 4110 | C5: Individuals | E5: 0 | G5: =SUM(#REF!)+#REF! -> #REF! | H5: =SUM(#REF!) -> #REF! | I5: =SUM(#REF!) -> #REF! | J5: =SUM(#REF!+#REF!+#REF!+#REF!) -> #REF! | K5: =SUM(#REF!) -> #REF! | L5: =SUM(#REF!) -> #REF! | N5: =SUM(E5:M5) -> #REF!
A6: =+A5+1 -> 6 | B6: 4120 | C6: Corporations/Civic Groups | E6: =SUM(#REF!) -> #REF! | G6: =SUM(#REF!) -> #REF! | H6: =SUM(#REF!) -> #REF! | I6: =SUM(#REF!) -> #REF! | J6: =SUM(#REF!+#REF!+#REF!+#REF!) -> #REF! | K6: =SUM(#REF!) -> #REF! | L6: =SUM(#REF!) -> #REF! | N6: =SUM(E6:M6) -> #REF!
A7: =+A6+1 -> 7 | B7: 4130 | C7: Foundations | E7: =SUM(#REF!) -> #REF! | G7: =SUM(#REF!) -> #REF! | H7: =SUM(#REF!) -> #REF! | I7: =SUM(#REF!) -> #REF! | J7: =SUM(#REF!+#REF!+#REF!+#REF!) -> #REF! | K7: =SUM(#REF!) -> #REF! | L7: =SUM(#REF!) -> #REF! | N7: =SUM(E7:M7) -> #REF!
A8: =+A7+1 -> 8 | B8: 4140 | C8: Planned Giving | E8: =SUM(#REF!) -> #REF! | G8: =SUM(#REF!) -> #REF! | H8: =SUM(#REF!) -> #REF! | I8: =SUM(#REF!) -> #REF! | J8: =SUM(#REF!+#REF!+#REF!+#REF!) -> #REF! | K8: =SUM(#REF!) -> #REF! | L8: =SUM(#REF!) -> #REF! | N8: =SUM(E8:M8) -> #REF!
A9: =+A8+1 -> 9 | E9: =SUM(#REF!) -> #REF! | G9: =SUM(#REF!) -> #REF! | H9: =SUM(#REF!) -> #REF! | I9: =SUM(#REF!) -> #REF! | J9: =SUM(#REF!+#REF!+#REF!+#REF!) -> #REF! | K9: =SUM(#REF!) -> #REF! | L9: =SUM(#REF!) -> #REF! | N9: =SUM(E9:M9) -> #REF!
A10: =+A9+1 -> 10 | B10: 4200 | C10: United Way | E10: =SUM(#REF!) -> #REF! | F10: 85900 | H10: =SUM(#REF!) -> #REF! | I10: =SUM(#REF!) -> #REF! | J10: =SUM(#REF!+#REF!+#REF!+#REF!) -> #REF! | K10: =SUM(#REF!) -> #REF! | L10: =SUM(#REF!) -> #REF! | N10: =SUM(E10:M10) -> #REF!
A11: =+A10+1 -> 11 | B11: 4310 | C11: Donated Goods | E11: =SUM(#REF!) -> #REF! | G11: =SUM(#REF!) -> #REF! | H11: =SUM(#REF!) -> #REF! | I11: =SUM(#REF!) -> #REF! | J11: =SUM(#REF!+#REF!+#REF!+#REF!) -> #REF! | K11: =SUM(#REF!) -> #REF! | L11: =SUM(#REF!) -> #REF! | N11: =SUM(E11:M11) -> #REF!
A12: =+A11+1 -> 12 | B12: 4320 | C12: Donated Services | E12: =SUM(#REF!) -> #REF! | G12: =SUM(#REF!) -> #REF! | H12: =SUM(#REF!) -> #REF! | I12: =SUM(#REF!) -> #REF! | J12: =SUM(#REF!+#REF!+#REF!+#REF!) -> #REF! | K12: =SUM(#REF!) -> #REF! | L12: =SUM(#REF!) -> #REF! | N12: =SUM(E12:M12) -> #REF!
A13: =+A12+1 -> 13 | B13: 4330 | C13: Donated Use of Facilities | E13: =SUM(#REF!) -> #REF! | G13: =SUM(#REF!) -> #REF! | H13: =SUM(#REF!) -> #REF! | I13: =SUM(#REF!) -> #REF! | J13: =SUM(#REF!+#REF!+#REF!+#REF!) -> #REF! | K13: =SUM(#REF!) -> #REF! | L13: =SUM(#REF!) -> #REF! | N13: =SUM(E13:M13) -> #REF!
A14: =+A13+1 -> 14 | B14: 4340 | C14: Donated Assets | E14: =SUM(#REF!) -> #REF! | G14: =SUM(#REF!) -> #REF! | H14: =SUM(#REF!) -> #REF! | I14: =SUM(#REF!) -> #REF! | J14: =SUM(#REF!+#REF!+#REF!+#REF!) -> #REF! | K14: =SUM(#REF!) -> #REF! | L14: =SUM(#REF!) -> #REF! | N14: =SUM(E14:M14) -> #REF!
A15: =+A14+1 -> 15 | B15: 4400 | C15: Government Grants | E15: =SUM(#REF!) -> #REF! | F15: 50000 | H15: =SUM(#REF!) -> #REF! | I15: =SUM(#REF!) -> #REF! | J15: =SUM(#REF!+#REF!+#REF!+#REF!) -> #REF! | K15: =SUM(#REF!) -> #REF! | L15: =SUM(#REF!) -> #REF! | N15: =SUM(E15:M15) -> #REF!
A16: =+A15+1 -> 16 | B16: 4500 | C16: Special Fundraising Events | E16: =SUM(#REF!) -> #REF! | G16: =SUM(#REF!) -> #REF! | H16: =SUM(#REF!) -> #REF! | I16: =SUM(#REF!) -> #REF! | J16: =SUM(#REF!+#REF!+#REF!+#REF!) -> #REF! | K16: =SUM(#REF!) -> #REF! | L16: =SUM(#REF!) -> #REF! | N16: =SUM(E16:M16) -> #REF!
A17: =+A16+1 -> 17 | E17: =SUM(#REF!) -> #REF! | G17: =SUM(#REF!) -> #REF! | H17: =SUM(#REF!) -> #REF! | I17: =SUM(#REF!) -> #REF! | J17: =SUM(#REF!+#REF!+#REF!+#REF!) -> #REF! | K17: =SUM(#REF!) -> #REF! | L17: =SUM(#REF!) -> #REF! | N17: =SUM(E17:M17) -> #REF!
A18: =+A17+1 -> 18 | B18: 5010 | C18: Product Sales Gross | E18: =SUM(#REF!) -> #REF! | G18: =SUM(#REF!) -> #REF! | H18: =SUM(#REF!) -> #REF! | I18: =SUM(#REF!) -> #REF! | J18: =SUM(#REF!+#REF!+#REF!+#REF!) -> #REF! | K18: =SUM(#REF!) -> #REF! | L18: =SUM(#REF!) -> #REF! | N18: =SUM(E18:M18) -> #REF!
A19: =+A18+1 -> 19 | B19: 5011 | C19: Cost of Product Sales | E19: =SUM(#REF!) -> #REF! | G19: =SUM(#REF!) -> #REF! | H19: =SUM(#REF!) -> #REF! | I19: =SUM(#REF!) -> #REF! | J19: =SUM(#REF!+#REF!+#REF!+#REF!) -> #REF! | K19: =SUM(#REF!) -> #REF! | L19: =SUM(#REF!) -> #REF! | N19: =SUM(E19:M19) -> #REF!
A20: =+A19+1 -> 20 | B20: 5012 | C20: Troop/SU Proceeds | E20: =SUM(#REF!) -> #REF! | G20: =SUM(#REF!) -> #REF! | H20: =SUM(#REF!) -> #REF! | I20: =SUM(#REF!) -> #REF! | J20: =SUM(#REF!+#REF!+#REF!+#REF!) -> #REF! | K20: =SUM(#REF!) -> #REF! | L20: =SUM(#REF!) -> #REF! | N20: =SUM(E20:M20) -> #REF!
A21: =+A20+1 -> 21 | C21: Net | E21: =SUM(#REF!) -> #REF! | G21: =SUM(#REF!) -> #REF! | H21: =SUM(#REF!) -> #REF! | I21: =SUM(#REF!) -> #REF! | J21: =SUM(#REF!+#REF!+#REF!+#REF!) -> #REF! | K21: =SUM(#REF!) -> #REF! | L21: =SUM(#REF!) -> #REF! | N21: =SUM(E21:M21) -> #REF!
A22: =+A21+1 -> 22 | B22: 5110 | C22: Retail Gross Sales | E22: =SUM(#REF!) -> #REF! | G22: =SUM(#REF!) -> #REF! | H22: =SUM(#REF!) -> #REF! | I22: =SUM(#REF!) -> #REF! | J22: =SUM(#REF!+#REF!+#REF!+#REF!) -> #REF! | K22: =SUM(#REF!) -> #REF! | L22: =SUM(#REF!) -> #REF! | N22: =SUM(E22:M22) -> #REF!
A23: =+A22+1 -> 23 | B23: 5111 | C23: Cost of Sales—inventory (contra) | E23: =SUM(#REF!) -> #REF! | G23: =SUM(#REF!) -> #REF! | H23: =SUM(#REF!) -> #REF! | I23: =SUM(#REF!) -> #REF! | J23: =SUM(#REF!+#REF!+#REF!+#REF!) -> #REF! | K23: =SUM(#REF!) -> #REF! | L23: =SUM(#REF!) -> #REF! | N23: =SUM(E23:M23) -> #REF!
A24: =+A23+1 -> 24 | B24: 5112 | C24: Cost of Sales—Freight In (contra) | E24: =SUM(#REF!) -> #REF! | G24: =SUM(#REF!) -> #REF! | H24: =SUM(#REF!) -> #REF! | I24: =SUM(#REF!) -> #REF! | J24: =SUM(#REF!+#REF!+#REF!+#REF!) -> #REF! | K24: =SUM(#REF!) -> #REF! | L24: =SUM(#REF!) -> #REF! | N24: =SUM(E24:M24) -> #REF!
A25: =+A24+1 -> 25 | B25: 5113 | C25: Returns and Allowances (contra) | E25: =SUM(#REF!) -> #REF! | G25: =SUM(#REF!) -> #REF! | H25: =SUM(#REF!) -> #REF! | I25: =SUM(#REF!) -> #REF! | J25: =SUM(#REF!+#REF!+#REF!+#REF!) -> #REF! | K25: =SUM(#REF!) -> #REF! | L25: =SUM(#REF!) -> #REF! | N25: =SUM(E25:M25) -> #REF!
A26: =+A25+1 -> 26 | B26: 5114 | C26: Merchandise Discounts Taken | E26: =SUM(#REF!) -> #REF! | G26: =SUM(#REF!) -> #REF! | H26: =SUM(#REF!) -> #REF! | I26: =SUM(#REF!) -> #REF! | J26: =SUM(#REF!+#REF!+#REF!+#REF!) -> #REF! | K26: =SUM(#REF!) -> #REF! | L26: =SUM(#REF!) -> #REF! | N26: =SUM(E26:M26) -> #REF!
A27: =+A26+1 -> 27 | C27: Net Retail | E27: =SUM(#REF!) -> #REF! | G27: =SUM(#REF!) -> #REF! | H27: =SUM(#REF!) -> #REF! | I27: =SUM(#REF!) -> #REF! | J27: =SUM(#REF!+#REF!+#REF!+#REF!) -> #REF! | K27: =SUM(#REF!) -> #REF! | L27: =SUM(#REF!) -> #REF! | N27: =SUM(E27:M27) -> #REF!
A28: =+A27+1 -> 28 | B28: 5200 | C28: PROGRAM SERVICE FEES | E28: =SUM(#REF!) -> #REF! | G28: =SUM(#REF!) -> #REF! | H28: =SUM(#REF!) -> #REF! | I28: =SUM(#REF!) -> #REF! | J28: =SUM(#REF!+#REF!+#REF!+#REF!) -> #REF! | L28: =SUM(#REF!) -> #REF! | N28: =SUM(E28:M28) -> #REF!
A29: =+A28+1 -> 29 | B29: 5201 | C29: Program Revenue for Budget | E29: =SUM(#REF!) -> #REF! | G29: =SUM(#REF!) -> #REF! | H29: =SUM(#REF!) -> #REF! | I29: =SUM(#REF!) -> #REF! | J29: =SUM(#REF!+#REF!+#REF!+#REF!) -> #REF! | K29: =SUM(#REF!) -> #REF! | L29: =SUM(#REF!) -> #REF! | N29: =SUM(E29:M29) -> #REF!
A30: =+A29+1 -> 30 | B30: 5280 | C30: Government Fees and Contracts | E30: =SUM(#REF!) -> #REF! | G30: =SUM(#REF!) -> #REF! | H30: =SUM(#REF!) -> #REF! | I30: =SUM(#REF!) -> #REF! | J30: =SUM(#REF!+#REF!+#REF!+#REF!) -> #REF! | K30: =SUM(#REF!) -> #REF! | L30: =SUM(#REF!) -> #REF! | N30: =SUM(E30:M30) -> #REF!
A31: =+A30+1 -> 31 | B31: 5290 | C31: Special Event REVenue | E31: =SUM(#REF!) -> #REF! | G31: =SUM(#REF!) -> #REF! | H31: =SUM(#REF!) -> #REF! | I31: =SUM(#REF!) -> #REF! | J31: =SUM(#REF!+#REF!+#REF!+#REF!) -> #REF! | K31: =SUM(#REF!) -> #REF! | L31: =SUM(#REF!) -> #REF! | N31: =SUM(E31:M31) -> #REF!
A32: =+A31+1 -> 32 | B32: 5291 | C32: Cost of Direct Benefit to Donor | E32: =SUM(#REF!) -> #REF! | G32: =SUM(#REF!) -> #REF! | H32: =SUM(#REF!) -> #REF! | I32: =SUM(#REF!) -> #REF! | J32: =SUM(#REF!+#REF!+#REF!+#REF!) -> #REF! | K32: =SUM(#REF!) -> #REF! | L32: =SUM(#REF!) -> #REF! | N32: =SUM(E32:M32) -> #REF!
A33: =+A32+1 -> 33 | B33: 5300 | C33: RENTAL INCOME | E33: =SUM(#REF!) -> #REF! | G33: =SUM(#REF!) -> #REF! | H33: =SUM(#REF!) -> #REF! | I33: =SUM(#REF!) -> #REF! | J33: =SUM(#REF!+#REF!+#REF!+#REF!) -> #REF! | K33: =SUM(#REF!) -> #REF! | L33: =SUM(#REF!) -> #REF! | N33: =SUM(E33:M33) -> #REF!
A34: =+A33+1 -> 34 | B34: 5301 | C34: Rental Income Budget | E34: =SUM(#REF!) -> #REF! | G34: =SUM(#REF!) -> #REF! | H34: =SUM(#REF!) -> #REF! | I34: =SUM(#REF!) -> #REF! | J34: =SUM(#REF!+#REF!+#REF!+#REF!) -> #REF! | K34: =SUM(#REF!) -> #REF! | L34: =SUM(#REF!) -> #REF! | N34: =SUM(E34:M34) -> #REF!
A35: =+A34+1 -> 35 | B35: 5400 | C35: INVESTMENT INCOME | E35: =SUM(#REF!) -> #REF! | G35: =SUM(#REF!) -> #REF! | H35: =SUM(#REF!) -> #REF! | I35: =SUM(#REF!) -> #REF! | J35: =SUM(#REF!+#REF!+#REF!+#REF!) -> #REF! | K35: =SUM(#REF!) -> #REF! | L35: =SUM(#REF!) -> #REF! | N35: =SUM(E35:M35) -> #REF!
A36: =+A35+1 -> 36 | B36: 5401 | C36: Investment Income Budget | E36: =SUM(#REF!) -> #REF! | G36: =SUM(#REF!) -> #REF! | H36: =SUM(#REF!) -> #REF! | I36: =SUM(#REF!) -> #REF! | J36: =SUM(#REF!+#REF!+#REF!+#REF!) -> #REF! | K36: =SUM(#REF!) -> #REF! | L36: =SUM(#REF!) -> #REF! | N36: =SUM(E36:M36) -> #REF!
A37: =+A36+1 -> 37 | B37: 5410 | C37: Bank Interest | E37: =SUM(#REF!) -> #REF! | G37: =SUM(#REF!) -> #REF! | H37: =SUM(#REF!) -> #REF! | I37: =SUM(#REF!) -> #REF! | J37: =SUM(#REF!+#REF!+#REF!+#REF!) -> #REF! | K37: =SUM(#REF!) -> #REF! | L37: =SUM(#REF!) -> #REF! | N37: =SUM(E37:M37) -> #REF!
A38: =+A37+1 -> 38 | B38: 5415 | C38: Investment Interest and Dividends | E38: =SUM(#REF!) -> #REF! | G38: =SUM(#REF!) -> #REF! | H38: =SUM(#REF!) -> #REF! | I38: =SUM(#REF!) -> #REF! | J38: =SUM(#REF!+#REF!+#REF!+#REF!) -> #REF! | K38: =SUM(#REF!) -> #REF! | L38: =SUM(#REF!) -> #REF! | N38: =SUM(E38:M38) -> #REF!
A39: =+A38+1 -> 39 | B39: 5420 | C39: Realized Gain (or Loss) | E39: =SUM(#REF!) -> #REF! | G39: =SUM(#REF!) -> #REF! | H39: =SUM(#REF!) -> #REF! | I39: =SUM(#REF!) -> #REF! | J39: =SUM(#REF!+#REF!+#REF!+#REF!) -> #REF! | K39: =SUM(#REF!) -> #REF! | L39: =SUM(#REF!) -> #REF! | N39: =SUM(E39:M39) -> #REF!
A40: =+A39+1 -> 40 | B40: 5430 | C40: Unrealized Gain (or Loss) | E40: =SUM(#REF!) -> #REF! | G40: =SUM(#REF!) -> #REF! | H40: =SUM(#REF!) -> #REF! | I40: =SUM(#REF!) -> #REF! | J40: =SUM(#REF!+#REF!+#REF!+#REF!) -> #REF! | K40: =SUM(#REF!) -> #REF! | L40: =SUM(#REF!) -> #REF! | N40: =SUM(E40:M40) -> #REF!
... A45: =+A44+1 -> 45 | B45: 5650 | C45: Gain or Loss on Sale of Assets (Property and Equipment) | E45: =SUM(#REF!) -> #REF! | G45: =SUM(#REF!) -> #REF! | H45: =SUM(#REF!) -> #REF! | I45: =SUM(#REF!) -> #REF! | J45: =SUM(#REF!+#REF!+#REF!+#REF!) -> #REF! | K45: =SUM(#REF!) -> #REF! | L45: =SUM(#REF!) -> #REF! | N45: =SUM(E45:M45) -> #REF!
A46: =+A45+1 -> 46 | B46: 5700 | C46: Unrelated Business Income | E46: =SUM(#REF!) -> #REF! | G46: =SUM(#REF!) -> #REF! | H46: =SUM(#REF!) -> #REF! | I46: =SUM(#REF!) -> #REF! | J46: =SUM(#REF!+#REF!+#REF!+#REF!) -> #REF! | K46: 0 | L46: =SUM(#REF!) -> #REF! | N46: =SUM(E46:M46) -> #REF!
A47: =+A46+1 -> 47 | E47: =SUM(#REF!) -> #REF! | G47: =SUM(#REF!) -> #REF! | H47: =SUM(#REF!) -> #REF! | I47: =SUM(#REF!) -> #REF! | J47: =SUM(#REF!+#REF!+#REF!+#REF!) -> #REF! | K47: =SUM(#REF!) -> #REF! | L47: =SUM(#REF!) -> #REF! | N47: =SUM(E47:M47) -> #REF!
A48: =+A47+1 -> 48 | C48: Total Revenue | E48: =SUM(E4:E47) -> #REF! | F48: =SUM(F4:F47) -> 135900 | G48: =SUM(G4:G47) -> #REF! | H48: =SUM(H4:H47) -> #REF! | I48: =I21+I27 -> #REF! | J48: =SUM(J4:J47) -> #REF! | K48: =SUM(#REF!) -> #REF! | L48: =SUM(L4:L47) -> #REF! | N48: =SUM(E48:M48) -> #REF! | R48: Total Revenue | T48: =#REF! -> #REF!
A49: =+A48+1 -> 49 | E49: =SUM(#REF!) -> #REF! | G49: =SUM(#REF!) -> #REF! | H49: =SUM(#REF!) -> #REF! | I49: =SUM(#REF!) -> #REF! | J49: =SUM(#REF!+#REF!+#REF!+#REF!) -> #REF! | K49: =SUM(#REF!) -> #REF! | L49: =SUM(#REF!) -> #REF! | N49: =SUM(E49:M49) -> #REF!
A50: =+A49+1 -> 50 | B50: 7001 | C50: Regular Employees—Exempt | E50: =SUM(#REF!) -> #REF! | G50: =SUM(#REF!) -> #REF! | H50: =SUM(#REF!) -> #REF! | I50: =SUM(#REF!) -> #REF! | J50: =SUM(#REF!+#REF!+#REF!+#REF!) -> #REF! | K50: =SUM(#REF!) -> #REF! | L50: =SUM(#REF!) -> #REF! | N50: =SUM(E50:M50) -> #REF! | P50: 7001 | Q50: Regular Employees—Exempt | R50: 1336183.3 | T50: 2274738
A51: =+A50+1 -> 51 | B51: 7002 | C51: Regular Employees—Nonexempt | E51: =SUM(#REF!) -> #REF! | G51: =SUM(#REF!) -> #REF! | H51: =SUM(#REF!) -> #REF! | I51: =SUM(#REF!) -> #REF! | J51: =SUM(#REF!+#REF!+#REF!+#REF!) -> #REF! | K51: =SUM(#REF!) -> #REF! | L51: =SUM(#REF!) -> #REF! | N51: =SUM(E51:M51) -> #REF! | P51: 7002 | Q51: Regular Employees—Nonexempt | R51: 420445.42
A52: =+A51+1 -> 52 | B52: 7003 | C52: Seasonal Employees | E52: =SUM(#REF!) -> #REF! | G52: =SUM(#REF!) -> #REF! | H52: =SUM(#REF!) -> #REF! | I52: =SUM(#REF!) -> #REF! | J52: =SUM(#REF!+#REF!+#REF!+#REF!) -> #REF! | K52: =SUM(#REF!) -> #REF! | L52: =SUM(#REF!) -> #REF! | N52: =SUM(E52:M52) -> #REF! | T52: 100000
A53: =+A52+1 -> 53 | B53: 7004 | C53: Temporary Staff | E53: =SUM(#REF!) -> #REF! | G53: =SUM(#REF!) -> #REF! | H53: =SUM(#REF!) -> #REF! | I53: =SUM(#REF!) -> #REF! | J53: =SUM(#REF!+#REF!+#REF!+#REF!) -> #REF! | K53: =SUM(#REF!) -> #REF! | L53: =SUM(#REF!) -> #REF! | N53: =SUM(E53:M53) -> #REF!
A54: =+A53+1 -> 54 | B54: 7005 | C54: Rangers | E54: =SUM(#REF!) -> #REF! | G54: =SUM(#REF!) -> #REF! | H54: =SUM(#REF!) -> #REF! | I54: =SUM(#REF!) -> #REF! | J54: =SUM(#REF!+#REF!+#REF!+#REF!) -> #REF! | K54: =SUM(#REF!) -> #REF! | L54: =SUM(#REF!) -> #REF! | N54: =SUM(E54:M54) -> #REF!
A55: =+A54+1 -> 55 | B55: 7101 | C55: Health Plan Premiums | E55: =SUM(#REF!) -> #REF! | G55: =SUM(#REF!) -> #REF! | H55: =SUM(#REF!) -> #REF! | I55: =SUM(#REF!) -> #REF! | J55: =SUM(#REF!+#REF!+#REF!+#REF!) -> #REF! | K55: =SUM(#REF!) -> #REF! | L55: =SUM(#REF!) -> #REF! | N55: =SUM(E55:M55) -> #REF! | P55: 7101 | Q55: Health Plan Premiums | R55: 126043.19 | S55: =N55-T55 -> #REF! | T55: 134790 | U55: =S55/N55 -> #REF! | V55: =N55+N56+N57-T55-T56-T57 -> #REF! | W55: =V55/188600 -> #REF!
A56: =+A55+1 -> 56 | B56: 7102 | C56: Dental Plan Premiums | E56: =SUM(#REF!) -> #REF! | G56: =SUM(#REF!) -> #REF! | H56: =SUM(#REF!) -> #REF! | I56: =SUM(#REF!) -> #REF! | J56: =SUM(#REF!+#REF!+#REF!+#REF!) -> #REF! | K56: =SUM(#REF!) -> #REF! | L56: =SUM(#REF!) -> #REF! | N56: =SUM(E56:M56) -> #REF! | P56: 7102 | Q56: Dental Plan Premiums | R56: 6995.01 | S56: =N56-T56 -> #REF! | T56: 7914 | U56: =S56/N56 -> #REF!
A57: =+A56+1 -> 57 | B57: 7103 | C57: Vision Premiums | E57: =SUM(#REF!) -> #REF! | G57: =SUM(#REF!) -> #REF! | H57: =SUM(#REF!) -> #REF! | I57: =SUM(#REF!) -> #REF! | J57: =SUM(#REF!+#REF!+#REF!+#REF!) -> #REF! | K57: =SUM(#REF!) -> #REF! | L57: =SUM(#REF!) -> #REF! | N57: =SUM(E57:M57) -> #REF! | P57: 7103 | Q57: Vision Premiums | R57: 920.84 | S57: =N57-T57 -> #REF! | T57: 1021
A58: =+A57+1 -> 58 | B58: 7104 | C58: GSUSA Retirement Plan | E58: =SUM(#REF!) -> #REF! | G58: =SUM(#REF!) -> #REF! | H58: =SUM(#REF!) -> #REF! | I58: =SUM(#REF!) -> #REF! | J58: =SUM(#REF!+#REF!+#REF!+#REF!) -> #REF! | K58: =SUM(#REF!) -> #REF! | L58: =SUM(#REF!) -> #REF! | N58: =SUM(E58:M58) -> #REF! | P58: 7104 | Q58: NGSCRP Frozen Retirement Plan Payments | R58: 116994.09 | S58: =N58-T58 -> #REF! | T58: =12000*12 -> 144000 | U58: =S58/N58 -> #REF! | V58: =T58-R58 -> 27005.91 | W58: =V58/R58 -> 0.2308314
A59: =+A58+1 -> 59 | B59: 7106 | C59: Council LIfe and Accidental Death Plan | E59: =SUM(#REF!) -> #REF! | G59: =SUM(#REF!) -> #REF! | H59: =SUM(#REF!) -> #REF! | I59: =SUM(#REF!) -> #REF! | J59: =SUM(#REF!+#REF!+#REF!+#REF!) -> #REF! | K59: =SUM(#REF!) -> #REF! | L59: =SUM(#REF!) -> #REF! | N59: =SUM(E59:M59) -> #REF! | P59: 7106 | Q59: Council LIfe and Accidental Death Plan | R59: 2679.13 | S59: =N59-T59 -> #REF! | T59: 3000 | U59: =S59/N59 -> #REF!
A60: =+A59+1 -> 60 | B60: 7110 | C60: Long Term Disability Plan | E60: =SUM(#REF!) -> #REF! | G60: =SUM(#REF!) -> #REF! | H60: =SUM(#REF!) -> #REF! | I60: =SUM(#REF!) -> #REF! | J60: =SUM(#REF!+#REF!+#REF!+#REF!) -> #REF! | K60: =SUM(#REF!) -> #REF! | L60: =SUM(#REF!) -> #REF! | N60: =SUM(E60:M60) -> #REF! | P60: 7110 | Q60: Long Term Disability Plan | R60: 3045.49 | S60: =N60-T60 -> #REF! | T60: 3200 | U60: =S60/N60 -> #REF!
A61: =+A60+1 -> 61 | B61: 7120 | C61: Severance Pay | E61: =SUM(#REF!) -> #REF! | G61: =SUM(#REF!) -> #REF! | H61: =SUM(#REF!) -> #REF! | I61: =SUM(#REF!) -> #REF! | J61: =SUM(#REF!+#REF!+#REF!+#REF!) -> #REF! | K61: =SUM(#REF!) -> #REF! | L61: =SUM(#REF!) -> #REF! | N61: =SUM(E61:M61) -> #REF! | P61: 7120 | Q61: Severance Pay | R61: 26952.48 | S61: =N61-T61 -> #REF! | T61: 0
A62: =+A61+1 -> 62 | B62: 7121 | C62: Uniforms | E62: =SUM(#REF!) -> #REF! | G62: =SUM(#REF!) -> #REF! | H62: =SUM(#REF!) -> #REF! | I62: =SUM(#REF!) -> #REF! | J62: =SUM(#REF!+#REF!+#REF!+#REF!) -> #REF! | K62: =SUM(#REF!) -> #REF! | L62: =SUM(#REF!) -> #REF! | N62: =SUM(E62:M62) -> #REF! | S62: =N62-T62 -> #REF!
A63: =+A62+1 -> 63 | B63: 7122 | C63: Background Screening | E63: =SUM(#REF!) -> #REF! | G63: =SUM(#REF!) -> #REF! | H63: =SUM(#REF!) -> #REF! | I63: =SUM(#REF!) -> #REF! | J63: =SUM(#REF!+#REF!+#REF!+#REF!) -> #REF! | K63: =SUM(#REF!) -> #REF! | L63: =SUM(#REF!) -> #REF! | N63: =SUM(E63:M63) -> #REF! | P63: 7122 | Q63: Background Screening | R63: 5729.4 | S63: =N63-T63 -> #REF! | T63: 8000 | U63: =S63/N63 -> #REF!
A64: =+A63+1 -> 64 | B64: 7201 | C64: FICA | E64: =SUM(#REF!) -> #REF! | G64: =SUM(#REF!) -> #REF! | H64: =SUM(#REF!) -> #REF! | I64: =SUM(#REF!) -> #REF! | J64: =SUM(#REF!+#REF!+#REF!+#REF!) -> #REF! | K64: =SUM(#REF!) -> #REF! | L64: =SUM(#REF!) -> #REF! | N64: =SUM(E64:M64) -> #REF! | P64: 7201 | Q64: FICA | R64: 130099.65 | S64: =N64-T64 -> #REF! | T64: 180833 | U64: =S64/N64 -> #REF! | V64: =N64+N65+N66-R64-R65-R66 -> #REF! | W64: =V64/186922 -> #REF!
A65: =+A64+1 -> 65 | B65: 7202 | C65: Unemployment Ins. | E65: =SUM(#REF!) -> #REF! | G65: =SUM(#REF!) -> #REF! | H65: =SUM(#REF!) -> #REF! | I65: =SUM(#REF!) -> #REF! | J65: =SUM(#REF!+#REF!+#REF!+#REF!) -> #REF! | K65: =SUM(#REF!) -> #REF! | L65: =SUM(#REF!) -> #REF! | N65: =SUM(E65:M65) -> #REF! | P65: 7202 | Q65: Unemployment Ins. | R65: 30835.3 | S65: =N65-T65 -> #REF! | T65: 31500 | U65: =S65/N65 -> #REF!
A66: =+A65+1 -> 66 | B66: 7203 | C66: Worker's Compensation | E66: =SUM(#REF!) -> #REF! | G66: =SUM(#REF!) -> #REF! | H66: =SUM(#REF!) -> #REF! | I66: =SUM(#REF!) -> #REF! | J66: =SUM(#REF!+#REF!+#REF!+#REF!) -> #REF! | K66: =SUM(#REF!) -> #REF! | L66: =SUM(#REF!) -> #REF! | N66: =SUM(E66:M66) -> #REF! | P66: 7203 | Q66: Worker's Compensation | R66: 15938.94 | S66: =N66-T66 -> #REF! | T66: 16845 | U66: =S66/N66 -> #REF!
A67: =+A66+1 -> 67 | B67: 8001 | C67: Audit and Accounting | E67: =SUM(#REF!) -> #REF! | G67: =SUM(#REF!) -> #REF! | H67: =SUM(#REF!) -> #REF! | I67: =SUM(#REF!) -> #REF! | J67: =SUM(#REF!+#REF!+#REF!+#REF!) -> #REF! | K67: =SUM(#REF!) -> #REF! | L67: =SUM(#REF!) -> #REF! | N67: =SUM(E67:M67) -> #REF! | P67: 8001 | Q67: Audit and Accounting inactive | R67: 31722 | S67: =N67-T67 -> #REF! | T67: 29000 | U67: =S67/N67 -> #REF!
A68: =+A67+1 -> 68 | B68: 8002 | C68: Legal | E68: =SUM(#REF!) -> #REF! | G68: =SUM(#REF!) -> #REF! | H68: =SUM(#REF!) -> #REF! | I68: =SUM(#REF!) -> #REF! | J68: =SUM(#REF!+#REF!+#REF!+#REF!) -> #REF! | K68: =SUM(#REF!) -> #REF! | L68: =SUM(#REF!) -> #REF! | N68: =SUM(E68:M68) -> #REF! | P68: 8002 | Q68: Legal Moved to 8005 | R68: 8716.98 | S68: =N68-T68 -> #REF! | U68: =S68/N68 -> #REF!
A69: =+A68+1 -> 69 | B69: 8003 | C69: Lobbying | E69: =SUM(#REF!) -> #REF! | G69: =SUM(#REF!) -> #REF! | H69: =SUM(#REF!) -> #REF! | I69: =SUM(#REF!) -> #REF! | J69: =SUM(#REF!+#REF!+#REF!+#REF!) -> #REF! | K69: =SUM(#REF!) -> #REF! | L69: =SUM(#REF!) -> #REF! | N69: =SUM(E69:M69) -> #REF! | P69: 8010 | Q69: Lobbying - GSUSA Dec 2011 | R69: 17201.21 | S69: =N69-T69 -> #REF! | T69: 8000 | U69: =S69/N69 -> #REF!
A70: =+A69+1 -> 70 | B70: 8004 | C70: Fundraising Professionals | E70: =SUM(#REF!) -> #REF! | G70: =SUM(#REF!) -> #REF! | H70: =SUM(#REF!) -> #REF! | I70: =SUM(#REF!) -> #REF! | J70: =SUM(#REF!+#REF!+#REF!+#REF!) -> #REF! | K70: =SUM(#REF!) -> #REF! | L70: =SUM(#REF!) -> #REF! | N70: =SUM(E70:M70) -> #REF! | P70: 8004 | Q70: Fundraising Professionals | R70: 0 | S70: =N70-T70 -> #REF! | T70: 0
A71: =+A70+1 -> 71 | B71: 8005 | C71: Public Relations | E71: =SUM(#REF!) -> #REF! | G71: =SUM(#REF!) -> #REF! | H71: =SUM(#REF!) -> #REF! | I71: =SUM(#REF!) -> #REF! | J71: =SUM(#REF!+#REF!+#REF!+#REF!) -> #REF! | K71: =SUM(#REF!) -> #REF! | L71: =SUM(#REF!) -> #REF! | N71: =SUM(E71:M71) -> #REF! | P71: 8005 | Q71: Legal Fees - GSUSA Dec 2011 | R71: 4083.04 | S71: =N71-T71 -> #REF! | T71: 12800 | U71: =S71/N71 -> #REF!
A72: =+A71+1 -> 72 | B72: 8006 | C72: Administrative Service Fees | E72: =SUM(#REF!) -> #REF! | G72: =SUM(#REF!) -> #REF! | H72: =SUM(#REF!) -> #REF! | I72: =SUM(#REF!) -> #REF! | J72: =SUM(#REF!+#REF!+#REF!+#REF!) -> #REF! | K72: =SUM(#REF!) -> #REF! | L72: =SUM(#REF!) -> #REF! | N72: =SUM(E72:M72) -> #REF! | P72: 8006 | Q72: Administrative Service Fees | R72: 3468.66 | S72: =N72-T72 -> #REF! | U72: =S72/N72 -> #REF!
A73: =+A72+1 -> 73 | B73: 8007 | C73: Computer and Technical Consultants | E73: =SUM(#REF!) -> #REF! | G73: =SUM(#REF!) -> #REF! | H73: =SUM(#REF!) -> #REF! | I73: =SUM(#REF!) -> #REF! | J73: =SUM(#REF!+#REF!+#REF!+#REF!) -> #REF! | K73: =SUM(#REF!) -> #REF! | L73: =SUM(#REF!) -> #REF! | N73: =SUM(E73:M73) -> #REF! | P73: 8007 | Q73: Computer and Technical Consultants | R73: =64721.9+6813.59 -> 71535.49 | S73: =N73-T73 -> #REF! | T73: =14000*12 -> 168000 | U73: =S73/N73 -> #REF!
A74: =+A73+1 -> 74 | B74: 8008 | C74: Evaluation Services, Development and Measurement | E74: =SUM(#REF!) -> #REF! | G74: =SUM(#REF!) -> #REF! | H74: =SUM(#REF!) -> #REF! | I74: =SUM(#REF!) -> #REF! | J74: =SUM(#REF!+#REF!+#REF!+#REF!) -> #REF! | K74: =SUM(#REF!) -> #REF! | L74: =SUM(#REF!) -> #REF! | N74: =SUM(E74:M74) -> #REF! | P74: 8008 | Q74: Evaluation Services, Development and Measurement | R74: 200 | S74: =N74-T74 -> #REF!
A75: =+A74+1 -> 75 | B75: 8009 | C75: Program Professional Services | E75: =SUM(#REF!) -> #REF! | G75: =SUM(#REF!) -> #REF! | H75: =SUM(#REF!) -> #REF! | I75: =SUM(#REF!) -> #REF! | J75: =SUM(#REF!+#REF!+#REF!+#REF!) -> #REF! | K75: =SUM(#REF!) -> #REF! | L75: =SUM(#REF!) -> #REF! | N75: =SUM(E75:M75) -> #REF! | P75: 8009 | Q75: Program Professional Services | R75: =111588.91+2010 -> 113598.91 | S75: =N75-T75 -> #REF! | T75: =9500+4500+6000 -> 20000 | U75: =S75/N75 -> #REF!
A76: =+A75+1 -> 76 | B76: 8010 | C76: Program Fees | E76: =SUM(#REF!) -> #REF! | G76: =SUM(#REF!) -> #REF! | H76: =SUM(#REF!) -> #REF! | I76: =SUM(#REF!) -> #REF! | J76: =SUM(#REF!+#REF!+#REF!+#REF!) -> #REF! | K76: =SUM(#REF!) -> #REF! | L76: =SUM(#REF!) -> #REF! | N76: =SUM(E76:M76) -> #REF! | S76: =N76-T76 -> #REF! | U76: =S76/N76 -> #REF!
P77: 8015 | Q77: Fundraising Professionals - GSUSA Dec 2011 | S77: =N77-T77 -> 0 | T77: 0
A78: =+A76+1 -> 77 | B78: 8020 | C78: Girl Incentives | E78: =SUM(#REF!) -> #REF! | G78: =SUM(#REF!) -> #REF! | H78: =SUM(#REF!) -> #REF! | I78: =SUM(#REF!) -> #REF! | J78: =SUM(#REF!+#REF!+#REF!+#REF!) -> #REF! | K78: =SUM(#REF!) -> #REF! | L78: =SUM(#REF!) -> #REF! | N78: =SUM(E78:M78) -> #REF! | P78: 8020 | Q78: Public Relations - GSUSA Dec 2011 | R78: =22937.5+6741.5 -> 29679 | S78: =N78-T78 -> #REF! | T78: 15000 | U78: =S78/N78 -> #REF!
P79: 8030 | Q79: Computer and Technical Consultants - GSUSA Dec 2011 | R79: 0 | S79: =N79-T79 -> 0 | T79: 0 | U79: =S79/N79 -> #DIV/0!
P80: 8035 | Q80: Eval Svcs Development and Measurement - GSUSA Dec2011 | R80: 1000 | S80: =N80-T80 -> -1000 | T80: 1000 | U80: =S80/N80 -> #DIV/0!
P81: 8040 | Q81: Program Professional Services - GSUSA Dec 2011 | R81: 0 | S81: =N81-T81 -> 0 | U81: =S81/N81 -> #DIV/0!
P82: 8045 | Q82: Program Fees - GSUSA Dec 2011 | R82: 30946.27 | S82: =N82-T82 -> -23000 | T82: 23000 | U82: =S82/N82 -> #DIV/0!
P83: 8050 | Q83: Other Purchased Services - GSUSA Dec 2011 | R83: 2000 | S83: =N83-T83 -> -2000 | T83: 2000 | U83: =S83/N83 -> #DIV/0!
A84: =+A78+1 -> 78 | B84: 8110 | C84: Food and Beverages | E84: =SUM(#REF!) -> #REF! | G84: =SUM(#REF!) -> #REF! | H84: =SUM(#REF!) -> #REF! | I84: =SUM(#REF!) -> #REF! | J84: =SUM(#REF!+#REF!+#REF!+#REF!) -> #REF! | K84: =SUM(#REF!) -> #REF! | L84: =SUM(#REF!) -> #REF! | N84: =SUM(E84:M84) -> #REF! | P84: 8110 | Q84: Food and Beverages | R84: 79733.14 | S84: =N84-T84 -> #REF! | T84: 85000 | U84: =S84/N84 -> #REF!
A85: =+A84+1 -> 79 | B85: 8120 | C85: Office Stationery and Supplies | E85: =SUM(#REF!) -> #REF! | G85: =SUM(#REF!) -> #REF! | H85: =SUM(#REF!) -> #REF! | I85: =SUM(#REF!) -> #REF! | J85: =SUM(#REF!+#REF!+#REF!+#REF!) -> #REF! | K85: =SUM(#REF!) -> #REF! | L85: =SUM(#REF!) -> #REF! | N85: =SUM(E85:M85) -> #REF! | P85: 8120 | Q85: Office Stationery and Supplies | R85: 20369.52 | S85: =N85-T85 -> #REF! | T85: 25500 | U85: =S85/N85 -> #REF!
A86: =+A85+1 -> 80 | B86: 8130 | C86: Program Supplies | E86: =SUM(#REF!) -> #REF! | G86: =SUM(#REF!) -> #REF! | H86: =SUM(#REF!) -> #REF! | I86: =SUM(#REF!) -> #REF! | J86: =SUM(#REF!+#REF!+#REF!+#REF!) -> #REF! | K86: =SUM(#REF!) -> #REF! | L86: =SUM(#REF!) -> #REF! | N86: =SUM(E86:M86) -> #REF! | P86: 8130 | Q86: Program Supplies | R86: 87331.1 | S86: =N86-T86 -> #REF! | T86: 90000 | U86: =S86/N86 -> #REF!
P87: 8135 | Q87: Recognitions and Appreciation - GSUSA Dec 2011 | R87: 60449.92 | S87: =N87-T87 -> -180432 | T87: =60449+119983 -> 180432 | U87: =S87/N87 -> #DIV/0!
A88: =+A86+1 -> 81 | B88: 8140 | C88: Equestrian Supplies | E88: =SUM(#REF!) -> #REF! | G88: =SUM(#REF!) -> #REF! | H88: =SUM(#REF!) -> #REF! | I88: =SUM(#REF!) -> #REF! | J88: =SUM(#REF!+#REF!+#REF!+#REF!) -> #REF! | K88: =SUM(#REF!) -> #REF! | L88: =SUM(#REF!) -> #REF! | N88: =SUM(E88:M88) -> #REF! | S88: =N88-T88 -> #REF! | U88: =S88/N88 -> #REF!
A89: =+A88+1 -> 82 | B89: 8150 | C89: Recognition Items | E89: =SUM(#REF!) -> #REF! | G89: =SUM(#REF!) -> #REF! | H89: =SUM(#REF!) -> #REF! | I89: =SUM(#REF!) -> #REF! | J89: =SUM(#REF!+#REF!+#REF!+#REF!) -> #REF! | K89: =SUM(#REF!) -> #REF! | L89: =SUM(#REF!) -> #REF! | N89: =SUM(E89:M89) -> #REF! | P89: 8150 | Q89: Recognition Items INACTIVE | R89: 119983.46 | S89: =N89-T89 -> #REF! | T89: 0 | U89: =S89/N89 -> #REF!
A90: =+A89+1 -> 83 | B90: 8160 | C90: Marketing Items | E90: =SUM(#REF!) -> #REF! | G90: =SUM(#REF!) -> #REF! | H90: =SUM(#REF!) -> #REF! | I90: =SUM(#REF!) -> #REF! | J90: =SUM(#REF!+#REF!+#REF!+#REF!) -> #REF! | K90: =SUM(#REF!) -> #REF! | L90: =SUM(#REF!) -> #REF! | N90: =SUM(E90:M90) -> #REF! | P90: 8160 | Q90: Marketing Items | R90: 7625.63 | S90: =N90-T90 -> #REF! | T90: 8000 | U90: =S90/N90 -> #REF!
A91: =+A90+1 -> 84 | B91: 8210 | C91: Telephone | E91: =SUM(#REF!) -> #REF! | G91: =SUM(#REF!) -> #REF! | H91: =SUM(#REF!) -> #REF! | I91: =SUM(#REF!) -> #REF! | J91: =SUM(#REF!+#REF!+#REF!+#REF!) -> #REF! | K91: =SUM(#REF!) -> #REF! | L91: =SUM(#REF!) -> #REF! | N91: =SUM(E91:M91) -> #REF! | P91: 8210 | Q91: Telephone | R91: 35860.02 | S91: =N91-T91 -> #REF! | T91: 38000 | U91: =S91/N91 -> #REF! | V91: =T91+T92 -> 51920
Q92: Cell phones | S92: =N92-T92 -> -13920 | T92: =1160*12 -> 13920 | U92: =S92/N92 -> #DIV/0! | V92: =V91-N91 -> #REF! | W92: =V92/N91 -> #REF!
A93: =+A91+1 -> 85 | B93: 8215 | C93: Data Communications, Internet, Web Hosting | E93: =SUM(#REF!) -> #REF! | G93: =SUM(#REF!) -> #REF! | H93: =SUM(#REF!) -> #REF! | I93: =SUM(#REF!) -> #REF! | J93: =SUM(#REF!+#REF!+#REF!+#REF!) -> #REF! | K93: =SUM(#REF!) -> #REF! | L93: =SUM(#REF!) -> #REF! | N93: =SUM(E93:M93) -> #REF! | P93: 8215 | Q93: Data Communications, Internet, Web Hosting | R93: 14603.39 | S93: =N93-T93 -> #REF! | T93: =1160*12 -> 13920 | U93: =S93/N93 -> #REF!
A94: =+A93+1 -> 86 | B94: 8310 | C94: Postage and Freight/Shipping | E94: =SUM(#REF!) -> #REF! | G94: =SUM(#REF!) -> #REF! | H94: =SUM(#REF!) -> #REF! | I94: =SUM(#REF!) -> #REF! | J94: =SUM(#REF!+#REF!+#REF!+#REF!) -> #REF! | K94: =SUM(#REF!) -> #REF! | L94: =SUM(#REF!) -> #REF! | N94: =SUM(E94:M94) -> #REF! | P94: 8310 | Q94: Postage and Freight/Shipping | R94: 14629.3 | S94: =N94-T94 -> #REF! | T94: 17000 | U94: =S94/N94 -> #REF!
A95: =+A94+1 -> 87 | B95: 8320 | C95: Courier Services | E95: =SUM(#REF!) -> #REF! | G95: =SUM(#REF!) -> #REF! | H95: =SUM(#REF!) -> #REF! | I95: =SUM(#REF!) -> #REF! | J95: =SUM(#REF!+#REF!+#REF!+#REF!) -> #REF! | K95: =SUM(#REF!) -> #REF! | L95: =SUM(#REF!) -> #REF! | N95: =SUM(E95:M95) -> #REF! | P95: 8320 | Q95: Courier Services | R95: 2710.06 | S95: =N95-T95 -> #REF! | T95: 2000 | U95: =S95/N95 -> #REF!
A96: =+A95+1 -> 88 | B96: 8330 | C96: Contract Mailing Service | E96: =SUM(#REF!) -> #REF! | G96: =SUM(#REF!) -> #REF! | H96: =SUM(#REF!) -> #REF! | I96: =SUM(#REF!) -> #REF! | J96: =SUM(#REF!+#REF!+#REF!+#REF!) -> #REF! | K96: =SUM(#REF!) -> #REF! | L96: =SUM(#REF!) -> #REF! | N96: =SUM(E96:M96) -> #REF! | S96: =N96-T96 -> #REF! | U96: =S96/N96 -> #REF!
A97: =+A96+1 -> 89 | B97: 8410 | C97: Facility Rental | E97: =SUM(#REF!) -> #REF! | G97: =SUM(#REF!) -> #REF! | H97: =SUM(#REF!) -> #REF! | I97: =SUM(#REF!) -> #REF! | J97: =SUM(#REF!+#REF!+#REF!+#REF!) -> #REF! | K97: =SUM(#REF!) -> #REF! | L97: =SUM(#REF!) -> #REF! | N97: =SUM(E97:M97) -> #REF! | P97: 8410 | Q97: Facility Rental | R97: 3434.69 | S97: =N97-T97 -> #REF! | T97: 2000 | U97: =S97/N97 -> #REF!
A98: =+A97+1 -> 90 | B98: 8420 | C98: Utilities | E98: =SUM(#REF!) -> #REF! | G98: =SUM(#REF!) -> #REF! | H98: =SUM(#REF!) -> #REF! | I98: =SUM(#REF!) -> #REF! | J98: =SUM(#REF!+#REF!+#REF!+#REF!) -> #REF! | K98: =SUM(#REF!) -> #REF! | L98: =SUM(#REF!) -> #REF! | N98: =SUM(E98:M98) -> #REF! | P98: 8420 | Q98: Utilities INACTIVE 2012 | R98: 635.36 | S98: =N98-T98 -> #REF! | T98: 90000 | U98: =S98/N98 -> #REF! | V98: =SUM(R98:R102) -> 78595.91 | W98: =N98-V98 -> #REF!
P99: 8421 | Q99: UTIL - ELECTRIC | R99: 53353.96 | S99: =N99-T99 -> 0 | U99: =S99/N99 -> #DIV/0! | W99: =W98/N98 -> #REF!
P100: 8422 | Q100: UTIL - WATER | R100: 19762.81 | S100: =N100-T100 -> 0 | U100: =S100/N100 -> #DIV/0!
P101: 8423 | Q101: UTIL - GARBAGE | R101: 4030.96 | S101: =N101-T101 -> 0 | U101: =S101/N101 -> #DIV/0!
P102: 8424 | Q102: UTIL - NAT GAS | R102: 812.82 | S102: =N102-T102 -> 0 | U102: =S102/N102 -> #DIV/0!
A103: =+A98+1 -> 91 | B103: 8430 | C103: Mortgage Interest | E103: =SUM(#REF!) -> #REF! | G103: =SUM(#REF!) -> #REF! | H103: =SUM(#REF!) -> #REF! | I103: =SUM(#REF!) -> #REF! | J103: =SUM(#REF!+#REF!+#REF!+#REF!) -> #REF! | K103: =SUM(#REF!) -> #REF! | L103: =SUM(#REF!) -> #REF! | N103: =SUM(E103:M103) -> #REF! | P103: 8430 | Q103: Mortgage Interest INACTIVE Dec 2011 | R103: 17519.01 | S103: =N103-T103 -> #REF! | T103: 31000 | U103: =S103/N103 -> #REF!
A104: =+A103+1 -> 92 | B104: 8435 | C104: Real Estate Taxes | E104: =SUM(#REF!) -> #REF! | G104: =SUM(#REF!) -> #REF! | H104: =SUM(#REF!) -> #REF! | I104: =SUM(#REF!) -> #REF! | J104: =SUM(#REF!+#REF!+#REF!+#REF!) -> #REF! | K104: =SUM(#REF!) -> #REF! | L104: =SUM(#REF!) -> #REF! | N104: =SUM(E104:M104) -> #REF! | P104: 8435 | Q104: Real Estate Taxes | R104: 8668.54 | S104: =N104-T104 -> #REF! | T104: 9000 | U104: =S104/N104 -> #REF!
A105: =+A104+1 -> 93 | B105: 8440 | C105: Building Repairs, Maintenance, and Services | E105: =SUM(#REF!) -> #REF! | G105: =SUM(#REF!) -> #REF! | H105: =SUM(#REF!) -> #REF! | I105: =SUM(#REF!) -> #REF! | J105: =SUM(#REF!+#REF!+#REF!+#REF!) -> #REF! | K105: =SUM(#REF!) -> #REF! | L105: =SUM(#REF!) -> #REF! | N105: =SUM(E105:M105) -> #REF! | P105: 8440 | Q105: Building Repairs, Maintenance, and Services | R105: 45223.68 | S105: =N105-T105 -> #REF! | T105: =13560+6300+4800+180+3000+720+4300+20000 -> 52860 | U105: =S105/N105 -> #REF!
...
