Workbook
Name CondWeight: CIP!$G$3
Name Consequence_Ratings: Lists!$D$2:$D$12
Name Efactor: CIP!$AL$3
Name Funding_Source: Lists!$F$2:$F$11
Name Overall_Condition: Lists!$B$2:$B$12
Name Percent_Life_Left: Lists!$A$2:$A$12
Name PLifeWeight: CIP!$H$3
Name t: CIP!$I$3
Name Weight1: CIP!$I$3
Name Weight2: CIP!$J$3
Name Weight3: CIP!$K$3
Name Weight4: CIP!$L$3
Name Weight5: CIP!$M$3
Name Weight6: CIP!$N$3
Name Weight7: CIP!$O$3
Name Weight8: CIP!$P$3
Name WSum: CIP!$Q$3

Sheet CIP
A1: ="FY"& (YEAR(TODAY())+2)&"-" & (YEAR(TODAY())+6)&" CIP by Priority" -> FY2014-2018 CIP by Priority | G1: Overall Condition input | H1: % Life Left as input | I1: CONSEQUENCES OF FAILURE (IF NOT IMPLEMENTING PROGRAM) RATINGS AND WEIGHTS --0 (No Impact) to 10 (High Impact) | AC1: Threshold | AD1: Threshold | AM1: ESCALATED COSTS (Costs in FY2015-2018 are escalated 3.5% a year)
G2: Weight | H2: Weight | I2: Weight | J2: Weight | K2: Weight | L2: Weight | M2: Weight | N2: Weight | O2: Weight | P2: Weight | Q2: Sum of Weights | AC2: 0.75 | AD2: 6 | AH2: BUDGET DISTRIBUTION | AM2: Total | AN2: Total | AO2: Total | AP2: Total | AQ2: Total
G3: 2 | H3: 1 | I3: 9 | J3: 6 | K3: 8 | L3: 10 | M3: 5 | N3: 7 | O3: 6 | P3: 6 | Q3: =SUM(I3:P3) -> 57 | AH3: Escalation factor: | AL3: 0.035 | AM3: =SUM(AM5:AM329) -> 46641575 | AN3: =SUM(AN5:AN329) -> 40233912 | AO3: =SUM(AO5:AO329) -> 55880081 | AP3: =SUM(AP5:AP329) -> 41272841 | AQ3: =SUM(AQ5:AQ329) -> 37477694
A4: Priority | B4: Dept | C4: Asset Category | D4: Project Title | E4: Project Description / Justification | F4: ="Est Cost in FY"&YEAR(TODAY())+2 -> Est Cost in FY2014 | G4: Overall Condition 0: Worse to 10: Best | H4: % Life Left 0: Expired to 100: New | I4: City Operations | J4: Programs / Services | K4: Costs/ Savings Ratio | L4: Codes/ Health & Safety | M4: Property Damage | N4: Quality of Life | O4: Energy | P4: Dept. Mission or Vision | Q4: % Life Left (Dynamic) | R4: % Life Left | S4: City Operations | T4: Programs/Services | U4: Costs/Savings Ratio | V4: Health & Safety | W4: Property Damage | X4: Quality of Life | Y4: Energy | Z4: Dept. Mission or Vision | AA4: Condition Likelihood Failure | AB4: % Life Left Likelihood failure | AC4: Likelihood of Failure | AD4: Conseq. Factor | AE4: Risk Factor | AF4: Funding Source | AG4: Prior Year Funding | AH4: ="FY "&YEAR(TODAY())+2 -> FY 2014 | AI4: ="FY"&YEAR(TODAY())+3 -> FY2015 | AJ4: ="FY"&YEAR(TODAY())+4 -> FY2016 | AK4: ="FY"&YEAR(TODAY())+5 -> FY2017 | AL4: ="FY"&YEAR(TODAY())+6 -> FY2018 | AM4: =AH4 -> FY 2014 | AN4: =AI4 -> FY2015 | AO4: =AJ4 -> FY2016 | AP4: =AK4 -> FY2017 | AQ4: =AL4 -> FY2018
A5: 1 | B5: Schools | C5: Building | D5: Angier School - Renovation or Replacement | E5: $7.5M anticipated from MSBA. Renovate/ replace 92 yr old school due to poor condition, aging bldg systems and inadequate space per State Ed. MSBA required feasibility study. | F5: 35000000 | G5: 2 | H5: 0 | I5: 10 | J5: 10 | K5: 4 | L5: 6 | M5: 4 | N5: 9 | O5: 5 | P5: 10 | Q5: =(#REF!-(YEAR(TODAY())-#REF!))/#REF! -> #REF! | R5: =IFERROR(Q5,H5) -> 0 | S5: =I5*Weight1/(WSum) -> 1.5789474 | T5: =J5*Weight2/(WSum) -> 1.0526316 | U5: =K5*Weight3/(WSum) -> 0.56140351 | V5: =L5*Weight4/(WSum) -> 1.0526316 | W5: =M5*Weight5/(WSum) -> 0.35087719 | X5: =N5*Weight6/(WSum) -> 1.1052632 | Y5: =O5*Weight7/(WSum) -> 0.52631579 | Z5: =P5*Weight8/(WSum) -> 1.0526316 | AA5: =-1/10*G5+1 -> 0.8 | AB5: =IF(R5<0,0,-R5+1) -> 1 | AC5: =(AA5*CondWeight+AB5*PLifeWeight)/(CondWeight+PLifeWeight) -> 0.86666667 | AD5: =SUM(S5:Z5) -> 7.2807018 | AE5: =AD5*AC5*10 -> 63.099415 | AF5: Bonding /MSBA | AG5: 750000 | AH5: 5000000 | AI5: 16908212 | AJ5: 11668884 | AM5: =AH5 -> 5000000 | AN5: =AI5*(1+Efactor) -> 17500000 | AO5: =AJ5*(1+Efactor)^2 -> 12500000
A6: 2 | B6: Schools | C6: Building | D6: Carr School - Building Renovation | E6: Create swing space for on-going Elem. school bldg projects. Includes system and accessibility upgrades, sprinklers, sitework, windows, and roof. | F6: 12700000 | G6: 3 | H6: 0.1 | I6: 6 | J6: 10 | K6: 8 | L6: 4 | M6: 8 | N6: 8 | O6: 6 | P6: 10 | Q6: =(#REF!-(YEAR(TODAY())-#REF!))/#REF! -> #REF! | R6: =IFERROR(Q6,H6) -> 0.1 | S6: =I6*Weight1/(WSum) -> 0.94736842 | T6: =J6*Weight2/(WSum) -> 1.0526316 | U6: =K6*Weight3/(WSum) -> 1.122807 | V6: =L6*Weight4/(WSum) -> 0.70175439 | W6: =M6*Weight5/(WSum) -> 0.70175439 | X6: =N6*Weight6/(WSum) -> 0.98245614 | Y6: =O6*Weight7/(WSum) -> 0.63157895 | Z6: =P6*Weight8/(WSum) -> 1.0526316 | AA6: =-1/10*G6+1 -> 0.7 | AB6: =IF(R6<0,0,-R6+1) -> 0.9 | AC6: =(AA6*CondWeight+AB6*PLifeWeight)/(CondWeight+PLifeWeight) -> 0.76666667 | AD6: =SUM(S6:Z6) -> 7.1929825 | AE6: =AD6*AC6*10 -> 55.146199 | AF6: Bonding | AG6: 1000000 | AH6: 11700000 | AM6: =AH6 -> 11700000
A7: 3 | B7: Fire Dept | C7: Building | D7: Fire Station #3, HQs, and Wires - Renovate/Replace Newton Centre Station | E7: Station #3 needs major repairs/upgrades. Co-located w/ Fire HQs. Upgrade 60 yo systems for code compliance, access & female firefighters. | F7: 17500000 | G7: 3 | H7: 0.1 | I7: 8 | J7: 8 | K7: 5 | L7: 8 | M7: 7 | N7: 9 | O7: 3 | P7: 9 | Q7: =(#REF!-(YEAR(TODAY())-#REF!))/#REF! -> #REF! | R7: =IFERROR(Q7,H7) -> 0.1 | S7: =I7*Weight1/(WSum) -> 1.2631579 | T7: =J7*Weight2/(WSum) -> 0.84210526 | U7: =K7*Weight3/(WSum) -> 0.70175439 | V7: =L7*Weight4/(WSum) -> 1.4035088 | W7: =M7*Weight5/(WSum) -> 0.61403509 | X7: =N7*Weight6/(WSum) -> 1.1052632 | Y7: =O7*Weight7/(WSum) -> 0.31578947 | Z7: =P7*Weight8/(WSum) -> 0.94736842 | AA7: =-1/10*G7+1 -> 0.7 | AB7: =IF(R7<0,0,-R7+1) -> 0.9 | AC7: =(AA7*CondWeight+AB7*PLifeWeight)/(CondWeight+PLifeWeight) -> 0.76666667 | AD7: =SUM(S7:Z7) -> 7.1929825 | AE7: =AD7*AC7*10 -> 55.146199 | AF7: Bonding | AH7: 4000000 | AI7: 2898551 | AJ7: 7934841 | AM7: =AH7 -> 4000000 | AN7: 5000000 | AO7: =AJ7*(1+Efactor)^2 -> 8500000.1
A8: 4 | B8: DPW/ Sewer | C8: Sewer | D8: Sewer Inflow /Infiltration Project - West Newton Area | E8: Part of 12 yr $49.1 M program to remove excess inflow and infiltration into sewer system. Design (FY13) and constr (FY14) for West Newton area. | F8: 5643625 | G8: 3 | H8: 0.2 | I8: 8 | J8: 8 | K8: 8 | L8: 8 | M8: 6 | N8: 8 | O8: 0 | P8: 9 | Q8: =(#REF!-(YEAR(TODAY())-#REF!))/#REF! -> #REF! | R8: =IFERROR(Q8,H8) -> 0.2 | S8: =I8*Weight1/(WSum) -> 1.2631579 | T8: =J8*Weight2/(WSum) -> 0.84210526 | U8: =K8*Weight3/(WSum) -> 1.122807 | V8: =L8*Weight4/(WSum) -> 1.4035088 | W8: =M8*Weight5/(WSum) -> 0.52631579 | X8: =N8*Weight6/(WSum) -> 0.98245614 | Y8: =O8*Weight7/(WSum) -> 0 | Z8: =P8*Weight8/(WSum) -> 0.94736842 | AA8: =-1/10*G8+1 -> 0.7 | AB8: =IF(R8<0,0,-R8+1) -> 0.8 | AC8: =(AA8*CondWeight+AB8*PLifeWeight)/(CondWeight+PLifeWeight) -> 0.73333333 | AD8: =SUM(S8:Z8) -> 7.0877193 | AE8: =AD8*AC8*10 -> 51.976608 | AF8: Enterprise Funds | AG8: 902000 | AH8: 4741625 | AM8: =AH8 -> 4741625
A9: 5 | B9: DPW/ Water | C9: Water | D9: Replace Water Pipes to Improve Fire Flows | E9: Year two of 3 year program to replace and repair water pipes in order to meet ISO fire flow standards which are currently defficient. | F9: 3851000 | G9: 1 | H9: 0.4 | I9: 6 | J9: 6 | K9: 8 | L9: 8 | M9: 8 | N9: 6 | O9: 0 | P9: 8 | Q9: =(#REF!-(YEAR(TODAY())-#REF!))/#REF! -> #REF! | R9: =IFERROR(Q9,H9) -> 0.4 | S9: =I9*Weight1/(WSum) -> 0.94736842 | T9: =J9*Weight2/(WSum) -> 0.63157895 | U9: =K9*Weight3/(WSum) -> 1.122807 | V9: =L9*Weight4/(WSum) -> 1.4035088 | W9: =M9*Weight5/(WSum) -> 0.70175439 | X9: =N9*Weight6/(WSum) -> 0.73684211 | Y9: =O9*Weight7/(WSum) -> 0 | Z9: =P9*Weight8/(WSum) -> 0.84210526 | AA9: =-1/10*G9+1 -> 0.9 | AB9: =IF(R9<0,0,-R9+1) -> 0.6 | AC9: =(AA9*CondWeight+AB9*PLifeWeight)/(CondWeight+PLifeWeight) -> 0.8 | AD9: =SUM(S9:Z9) -> 6.3859649 | AE9: =AD9*AC9*10 -> 51.087719 | AF9: Enterprise Funds | AH9: 3851000 | AM9: =AH9 -> 3851000
A10: 6 | B10: Schools | C10: Building | D10: Remove Underground Tanks at Various Schools | E10: Remove underground tanks which are no longer needed at Memorial-Spaulding, Zervas, and Underwood Elementary Schools. | F10: 250000 | G10: 1 | H10: 0 | I10: 5 | J10: 6 | K10: 5 | L10: 10 | M10: 4 | N10: 2 | O10: 1 | P10: 8 | Q10: =(#REF!-(YEAR(TODAY())-#REF!))/#REF! -> #REF! | R10: =IFERROR(Q10,H10) -> 0 | S10: =I10*Weight1/(WSum) -> 0.78947368 | T10: =J10*Weight2/(WSum) -> 0.63157895 | U10: =K10*Weight3/(WSum) -> 0.70175439 | V10: =L10*Weight4/(WSum) -> 1.754386 | W10: =M10*Weight5/(WSum) -> 0.35087719 | X10: =N10*Weight6/(WSum) -> 0.24561404 | Y10: =O10*Weight7/(WSum) -> 0.10526316 | Z10: =P10*Weight8/(WSum) -> 0.84210526 | AA10: =-1/10*G10+1 -> 0.9 | AB10: =IF(R10<0,0,-R10+1) -> 1 | AC10: =(AA10*CondWeight+AB10*PLifeWeight)/(CondWeight+PLifeWeight) -> 0.93333333 | AD10: =SUM(S10:Z10) -> 5.4210526 | AE10: =AD10*AC10*10 -> 50.596491 | AF10: Other | AH10: 250000 | AM10: =AH10 -> 250000
A11: 7 | B11: Schools | C11: Building | D11: Lincoln Eliot School - Add Four Modular Classrooms | E11: Add modular classrooms for growing enrollment. Project includes sprinklers for the entire building as required by building code. | F11: 3000000 | G11: 2 | H11: 0 | I11: 6 | J11: 8 | K11: 6 | L11: 8 | M11: 0 | N11: 6 | O11: 0 | P11: 10 | Q11: =(#REF!-(YEAR(TODAY())-#REF!))/#REF! -> #REF! | R11: =IFERROR(Q11,H11) -> 0 | S11: =I11*Weight1/(WSum) -> 0.94736842 | T11: =J11*Weight2/(WSum) -> 0.84210526 | U11: =K11*Weight3/(WSum) -> 0.84210526 | V11: =L11*Weight4/(WSum) -> 1.4035088 | W11: =M11*Weight5/(WSum) -> 0 | X11: =N11*Weight6/(WSum) -> 0.73684211 | Y11: =O11*Weight7/(WSum) -> 0 | Z11: =P11*Weight8/(WSum) -> 1.0526316 | AA11: =-1/10*G11+1 -> 0.8 | AB11: =IF(R11<0,0,-R11+1) -> 1 | AC11: =(AA11*CondWeight+AB11*PLifeWeight)/(CondWeight+PLifeWeight) -> 0.86666667 | AD11: =SUM(S11:Z11) -> 5.8245614 | AE11: =AD11*AC11*10 -> 50.479532 | AF11: Bonding | AH11: 3000000 | AM11: =AH11 -> 3000000
A12: 8 | B12: Public Buildings | C12: Building | D12: Remove Underground Storage Tanks at City Buildings | E12: Remove tanks at Fire Station 10, City Hall, Police HQ, and Senior Center. Tanks are no longer needed. | F12: 125000 | G12: 1 | H12: 0 | I12: 5 | J12: 4 | K12: 5 | L12: 10 | M12: 5 | N12: 2 | O12: 2 | P12: 8 | Q12: =(#REF!-(YEAR(TODAY())-#REF!))/#REF! -> #REF! | R12: =IFERROR(Q12,H12) -> 0 | S12: =I12*Weight1/(WSum) -> 0.78947368 | T12: =J12*Weight2/(WSum) -> 0.42105263 | U12: =K12*Weight3/(WSum) -> 0.70175439 | V12: =L12*Weight4/(WSum) -> 1.754386 | W12: =M12*Weight5/(WSum) -> 0.43859649 | X12: =N12*Weight6/(WSum) -> 0.24561404 | Y12: =O12*Weight7/(WSum) -> 0.21052632 | Z12: =P12*Weight8/(WSum) -> 0.84210526 | AA12: =-1/10*G12+1 -> 0.9 | AB12: =IF(R12<0,0,-R12+1) -> 1 | AC12: =(AA12*CondWeight+AB12*PLifeWeight)/(CondWeight+PLifeWeight) -> 0.93333333 | AD12: =SUM(S12:Z12) -> 5.4035088 | AE12: =AD12*AC12*10 -> 50.432749 | AF12: Other | AH12: 125000 | AM12: =AH12 -> 125000
A13: 9 | B13: Fire Dept | C13: Building | D13: Fire Station #10 (Dedham Street) Renovation | E13: Project will address aging building systems, code upgrades, access and accommodations for female firefighters. | F13: 4252000 | G13: 3 | H13: 0.2 | I13: 8 | J13: 8 | K13: 5 | L13: 8 | M13: 6 | N13: 7 | O13: 4 | P13: 8 | Q13: =(#REF!-(YEAR(TODAY())-#REF!))/#REF! -> #REF! | R13: =IFERROR(Q13,H13) -> 0.2 | S13: =I13*Weight1/(WSum) -> 1.2631579 | T13: =J13*Weight2/(WSum) -> 0.84210526 | U13: =K13*Weight3/(WSum) -> 0.70175439 | V13: =L13*Weight4/(WSum) -> 1.4035088 | W13: =M13*Weight5/(WSum) -> 0.52631579 | X13: =N13*Weight6/(WSum) -> 0.85964912 | Y13: =O13*Weight7/(WSum) -> 0.42105263 | Z13: =P13*Weight8/(WSum) -> 0.84210526 | AA13: =-1/10*G13+1 -> 0.7 | AB13: =IF(R13<0,0,-R13+1) -> 0.8 | AC13: =(AA13*CondWeight+AB13*PLifeWeight)/(CondWeight+PLifeWeight) -> 0.73333333 | AD13: =SUM(S13:Z13) -> 6.8596491 | AE13: =AD13*AC13*10 -> 50.304094 | AF13: Bonding | AG13: 780000 | AH13: 3472000 | AM13: =AH13 -> 3472000
A14: 10 | B14: DPW | C14: Building | D14: Crafts Street Garage - Building Envelope & Roof Repair/ Replacemt | E14: Address active roof leaks and masonry gap. Repair flashing; replace roof with new EPDM Roof. FY13 design & ph 1 constr. FY14 phase 2 construction. | F14: 870000 | G14: 1 | H14: 0 | I14: 6 | J14: 4 | K14: 6 | L14: 7 | M14: 10 | N14: 1 | O14: 2 | P14: 7 | Q14: =(#REF!-(YEAR(TODAY())-#REF!))/#REF! -> #REF! | R14: =IFERROR(Q14,H14) -> 0 | S14: =I14*Weight1/(WSum) -> 0.94736842 | T14: =J14*Weight2/(WSum) -> 0.42105263 | U14: =K14*Weight3/(WSum) -> 0.84210526 | V14: =L14*Weight4/(WSum) -> 1.2280702 | W14: =M14*Weight5/(WSum) -> 0.87719298 | X14: =N14*Weight6/(WSum) -> 0.12280702 | Y14: =O14*Weight7/(WSum) -> 0.21052632 | Z14: =P14*Weight8/(WSum) -> 0.73684211 | AA14: =-1/10*G14+1 -> 0.9 | AB14: =IF(R14<0,0,-R14+1) -> 1 | AC14: =(AA14*CondWeight+AB14*PLifeWeight)/(CondWeight+PLifeWeight) -> 0.93333333 | AD14: =SUM(S14:Z14) -> 5.3859649 | AE14: =AD14*AC14*10 -> 50.269006 | AF14: Bonding | AG14: 260000 | AH14: 610000 | AM14: =AH14 -> 610000
A15: 11 | B15: Schools | C15: Building | D15: Cabot School - Renovation and Addition/Replacement | E15: FY14 feasibility study. Project will address aging systems, access, sprinklers, and space needs. Include cost to move to Carr and back to Cabot. Anticipate high maintenance costs on mechanical system until building is renovated. | F15: 37500000 | G15: 2 | H15: 0.1 | I15: 7 | J15: 8 | K15: 4 | L15: 6 | M15: 1 | N15: 8 | O15: 5 | P15: 8 | Q15: =(#REF!-(YEAR(TODAY())-#REF!))/#REF! -> #REF! | R15: =IFERROR(Q15,H15) -> 0.1 | S15: =I15*Weight1/(WSum) -> 1.1052632 | T15: =J15*Weight2/(WSum) -> 0.84210526 | U15: =K15*Weight3/(WSum) -> 0.56140351 | V15: =L15*Weight4/(WSum) -> 1.0526316 | W15: =M15*Weight5/(WSum) -> 0.087719298 | X15: =N15*Weight6/(WSum) -> 0.98245614 | Y15: =O15*Weight7/(WSum) -> 0.52631579 | Z15: =P15*Weight8/(WSum) -> 0.84210526 | AA15: =-1/10*G15+1 -> 0.8 | AB15: =IF(R15<0,0,-R15+1) -> 0.9 | AC15: =(AA15*CondWeight+AB15*PLifeWeight)/(CondWeight+PLifeWeight) -> 0.83333333 | AD15: =SUM(S15:Z15) -> 6 | AE15: =AD15*AC15*10 -> 50 | AF15: Bonding /MSBA | AH15: 750000 | AJ15: 14002660 | AK15: 20293711 | AM15: =AH15 -> 750000 | AO15: =AJ15*(1+Efactor)^2 -> 15000000 | AP15: =AK15*(1+Efactor)^3 -> 22500000
A16: 12 | B16: Fire Dept | C16: Large Vehicle/ Equipment | D16: Replace Fire Dept Rescue Truck and Rescue Boat | E16: Replace Special Ops. 1994 Ford (174K miles) Rescue truck needed for specialized rescue, with specialized tools and equipment. Special Ops gets taken out of service. | F16: 600000 | G16: 3 | H16: 0.1 | I16: 7 | J16: 7 | K16: 3 | L16: 10 | M16: 5 | N16: 8 | O16: 0 | P16: 10 | Q16: =(#REF!-(YEAR(TODAY())-#REF!))/#REF! -> #REF! | R16: =IFERROR(Q16,H16) -> 0.1 | S16: =I16*Weight1/(WSum) -> 1.1052632 | T16: =J16*Weight2/(WSum) -> 0.73684211 | U16: =K16*Weight3/(WSum) -> 0.42105263 | V16: =L16*Weight4/(WSum) -> 1.754386 | W16: =M16*Weight5/(WSum) -> 0.43859649 | X16: =N16*Weight6/(WSum) -> 0.98245614 | Y16: =O16*Weight7/(WSum) -> 0 | Z16: =P16*Weight8/(WSum) -> 1.0526316 | AA16: =-1/10*G16+1 -> 0.7 | AB16: =IF(R16<0,0,-R16+1) -> 0.9 | AC16: =(AA16*CondWeight+AB16*PLifeWeight)/(CondWeight+PLifeWeight) -> 0.76666667 | AD16: =SUM(S16:Z16) -> 6.4912281 | AE16: =AD16*AC16*10 -> 49.766082 | AF16: Other
A17: 13 | B17: DPW | C17: Roads/ Paving | D17: Street Paving - Cold Plane and Pave 21 Streets | E17: Streets include Lowell, Webster, Homer, Wolcott, Hawthone, Weldon, Bellevue, Summit, Lenox, Regent, Waban, Washington (2 sections), Morton, Hillside, Hunnewell, Country Club, Cross Hill, Saw Mill Brk, Carver, Randolph | F17: 2627240 | G17: 2 | H17: 0.1 | I17: 8 | J17: 8 | K17: 2 | L17: 6 | M17: 4 | N17: 9 | O17: 0 | P17: 10 | Q17: =(#REF!-(YEAR(TODAY())-#REF!))/#REF! -> #REF! | R17: =IFERROR(Q17,H17) -> 0.1 | S17: =I17*Weight1/(WSum) -> 1.2631579 | T17: =J17*Weight2/(WSum) -> 0.84210526 | U17: =K17*Weight3/(WSum) -> 0.28070175 | V17: =L17*Weight4/(WSum) -> 1.0526316 | W17: =M17*Weight5/(WSum) -> 0.35087719 | X17: =N17*Weight6/(WSum) -> 1.1052632 | Y17: =O17*Weight7/(WSum) -> 0 | Z17: =P17*Weight8/(WSum) -> 1.0526316 | AA17: =-1/10*G17+1 -> 0.8 | AB17: =IF(R17<0,0,-R17+1) -> 0.9 | AC17: =(AA17*CondWeight+AB17*PLifeWeight)/(CondWeight+PLifeWeight) -> 0.83333333 | AD17: =SUM(S17:Z17) -> 5.9473684 | AE17: =AD17*AC17*10 -> 49.561404 | AF17: Chapt 90/ Alt Funds | AH17: 2627240 | AM17: =AH17 -> 2627240
A18: 14 | B18: Schools | C18: Building | D18: Zervas and Bigelow School Electrical Upgrades | E18: Upgrades to electrical system and replace panels at Bigelow Middle School and Zervas Elemenatry School. | F18: 80000 | G18: 1 | H18: 0 | I18: 5 | J18: 8 | K18: 4 | L18: 7 | M18: 6 | N18: 5 | O18: 1 | P18: 6 | Q18: =(#REF!-(YEAR(TODAY())-#REF!))/#REF! -> #REF! | R18: =IFERROR(Q18,H18) -> 0 | S18: =I18*Weight1/(WSum) -> 0.78947368 | T18: =J18*Weight2/(WSum) -> 0.84210526 | U18: =K18*Weight3/(WSum) -> 0.56140351 | V18: =L18*Weight4/(WSum) -> 1.2280702 | W18: =M18*Weight5/(WSum) -> 0.52631579 | X18: =N18*Weight6/(WSum) -> 0.61403509 | Y18: =O18*Weight7/(WSum) -> 0.10526316 | Z18: =P18*Weight8/(WSum) -> 0.63157895 | AA18: =-1/10*G18+1 -> 0.9 | AB18: =IF(R18<0,0,-R18+1) -> 1 | AC18: =(AA18*CondWeight+AB18*PLifeWeight)/(CondWeight+PLifeWeight) -> 0.93333333 | AD18: =SUM(S18:Z18) -> 5.2982456 | AE18: =AD18*AC18*10 -> 49.450292 | AF18: Bonding | AH18: 80000 | AM18: =AH18 -> 80000
A19: 15 | B19: Schools | C19: Building | D19: Bowen School - Mechanical Upgrades | E19: Remove underground storage tank and replace or convert to gas if enough gas pressure. Leak detection system has failed. | F19: 100000 | G19: 1 | H19: 0 | I19: 5 | J19: 6 | K19: 4 | L19: 7 | M19: 6 | N19: 5 | O19: 2 | P19: 7 | Q19: =(#REF!-(YEAR(TODAY())-#REF!))/#REF! -> #REF! | R19: =IFERROR(Q19,H19) -> 0 | S19: =I19*Weight1/(WSum) -> 0.78947368 | T19: =J19*Weight2/(WSum) -> 0.63157895 | U19: =K19*Weight3/(WSum) -> 0.56140351 | V19: =L19*Weight4/(WSum) -> 1.2280702 | W19: =M19*Weight5/(WSum) -> 0.52631579 | X19: =N19*Weight6/(WSum) -> 0.61403509 | Y19: =O19*Weight7/(WSum) -> 0.21052632 | Z19: =P19*Weight8/(WSum) -> 0.73684211 | AA19: =-1/10*G19+1 -> 0.9 | AB19: =IF(R19<0,0,-R19+1) -> 1 | AC19: =(AA19*CondWeight+AB19*PLifeWeight)/(CondWeight+PLifeWeight) -> 0.93333333 | AD19: =SUM(S19:Z19) -> 5.2982456 | AE19: =AD19*AC19*10 -> 49.450292 | AF19: Bonding | AH19: 100000 | AM19: =AH19 -> 100000
A20: 16 | B20: DPW/ Water | C20: Water | D20: Clean and Line Water Pipes to Improve Water Quality | E20: Cleaning and lining of water pipes to improve water quality, ensure pipe integrity and capacity. Precedes scheduled roadway paving. | F20: 164000 | G20: 3 | H20: 0.1 | I20: 6 | J20: 6 | K20: 7 | L20: 8 | M20: 5 | N20: 8 | O20: 0 | P20: 10 | Q20: =(#REF!-(YEAR(TODAY())-#REF!))/#REF! -> #REF! | R20: =IFERROR(Q20,H20) -> 0.1 | S20: =I20*Weight1/(WSum) -> 0.94736842 | T20: =J20*Weight2/(WSum) -> 0.63157895 | U20: =K20*Weight3/(WSum) -> 0.98245614 | V20: =L20*Weight4/(WSum) -> 1.4035088 | W20: =M20*Weight5/(WSum) -> 0.43859649 | X20: =N20*Weight6/(WSum) -> 0.98245614 | Y20: =O20*Weight7/(WSum) -> 0 | Z20: =P20*Weight8/(WSum) -> 1.0526316 | AA20: =-1/10*G20+1 -> 0.7 | AB20: =IF(R20<0,0,-R20+1) -> 0.9 | AC20: =(AA20*CondWeight+AB20*PLifeWeight)/(CondWeight+PLifeWeight) -> 0.76666667 | AD20: =SUM(S20:Z20) -> 6.4385965 | AE20: =AD20*AC20*10 -> 49.362573 | AF20: Enterprise Funds | AH20: 164000 | AM20: =AH20 -> 164000
A21: 17 | B21: Public Buildings | C21: Building | D21: Energy Efficiency / Water Conservation Upgrades to City and School Buildings | E21: Project includes energy conservation measures at Library, Lincoln Eliot, Franklin, Underwood, Cabot Schools thru NSTAR preferred vendor program. | F21: 2000000 | G21: 3 | H21: 0.2 | I21: 6 | J21: 8 | K21: 8 | L21: 4 | M21: 0 | N21: 8 | O21: 10 | P21: 10 | Q21: =(#REF!-(YEAR(TODAY())-#REF!))/#REF! -> #REF! | R21: =IFERROR(Q21,H21) -> 0.2 | S21: =I21*Weight1/(WSum) -> 0.94736842 | T21: =J21*Weight2/(WSum) -> 0.84210526 | U21: =K21*Weight3/(WSum) -> 1.122807 | V21: =L21*Weight4/(WSum) -> 0.70175439 | W21: =M21*Weight5/(WSum) -> 0 | X21: =N21*Weight6/(WSum) -> 0.98245614 | Y21: =O21*Weight7/(WSum) -> 1.0526316 | Z21: =P21*Weight8/(WSum) -> 1.0526316 | AA21: =-1/10*G21+1 -> 0.7 | AB21: =IF(R21<0,0,-R21+1) -> 0.8 | AC21: =(AA21*CondWeight+AB21*PLifeWeight)/(CondWeight+PLifeWeight) -> 0.73333333 | AD21: =SUM(S21:Z21) -> 6.7017544 | AE21: =AD21*AC21*10 -> 49.146199 | AF21: Energy Stabilztn Fund | AG21: 1000000 | AH21: 1000000 | AM21: =AH21 -> 1000000
A22: 18 | B22: Senior Center | C22: Building | D22: Senior Center - Mechanical Upgrades | E22: Replace fans and air handling units. Change boiler burner to gas-fired. Replace basement fan coil unit. Improve operation & efficiency for consistent temp heating/cooling. | F22: 188000 | G22: 2 | H22: 0.1 | I22: 6 | J22: 8 | K22: 4 | L22: 6 | M22: 3 | N22: 7 | O22: 5 | P22: 8 | Q22: =(#REF!-(YEAR(TODAY())-#REF!))/#REF! -> #REF! | R22: =IFERROR(Q22,H22) -> 0.1 | S22: =I22*Weight1/(WSum) -> 0.94736842 | T22: =J22*Weight2/(WSum) -> 0.84210526 | U22: =K22*Weight3/(WSum) -> 0.56140351 | V22: =L22*Weight4/(WSum) -> 1.0526316 | W22: =M22*Weight5/(WSum) -> 0.26315789 | X22: =N22*Weight6/(WSum) -> 0.85964912 | Y22: =O22*Weight7/(WSum) -> 0.52631579 | Z22: =P22*Weight8/(WSum) -> 0.84210526 | AA22: =-1/10*G22+1 -> 0.8 | AB22: =IF(R22<0,0,-R22+1) -> 0.9 | AC22: =(AA22*CondWeight+AB22*PLifeWeight)/(CondWeight+PLifeWeight) -> 0.83333333 | AD22: =SUM(S22:Z22) -> 5.8947368 | AE22: =AD22*AC22*10 -> 49.122807 | AF22: Bonding | AH22: 188000 | AM22: =AH22 -> 188000
A23: 19 | B23: Schools | C23: Building | D23: Horace Mann - Add Classroom | E23: Additional classroom needed to address immediate space needs. Create new classroom within existing building footprint. | F23: 75000 | G23: 1 | H23: 0 | I23: 6 | J23: 8 | K23: 8 | L23: 3 | M23: 0 | N23: 8 | O23: 0 | P23: 8 | Q23: =(#REF!-(YEAR(TODAY())-#REF!))/#REF! -> #REF! | R23: =IFERROR(Q23,H23) -> 0 | S23: =I23*Weight1/(WSum) -> 0.94736842 | T23: =J23*Weight2/(WSum) -> 0.84210526 | U23: =K23*Weight3/(WSum) -> 1.122807 | V23: =L23*Weight4/(WSum) -> 0.52631579 | W23: =M23*Weight5/(WSum) -> 0 | X23: =N23*Weight6/(WSum) -> 0.98245614 | Y23: =O23*Weight7/(WSum) -> 0 | Z23: =P23*Weight8/(WSum) -> 0.84210526 | AA23: =-1/10*G23+1 -> 0.9 | AB23: =IF(R23<0,0,-R23+1) -> 1 | AC23: =(AA23*CondWeight+AB23*PLifeWeight)/(CondWeight+PLifeWeight) -> 0.93333333 | AD23: =SUM(S23:Z23) -> 5.2631579 | AE23: =AD23*AC23*10 -> 49.122807 | AF23: Other | AH23: 75000 | AM23: =AH23 -> 75000
A24: 20 | B24: DPW | C24: Roads/ Paving | D24: Repair / Improve Wales St. Bridge (Wellesley MOU) | E24: Repairs required in response to Mass DOT bridge inspection findings. Include new guardrails and bridge railings for height and impact safety requirements. Wellesley will bond their $400,000 share of cost. Approach sidewalks will be reconstructed. The approach roadway and bridge will also be cold-planed and paved. | F24: 400000 | G24: 2 | H24: 0 | I24: 5 | J24: 8 | K24: 4 | L24: 8 | M24: 7 | N24: 5 | O24: 0 | P24: 8 | Q24: =(#REF!-(YEAR(TODAY())-#REF!))/#REF! -> #REF! | R24: =IFERROR(Q24,H24) -> 0 | S24: =I24*Weight1/(WSum) -> 0.78947368 | T24: =J24*Weight2/(WSum) -> 0.84210526 | U24: =K24*Weight3/(WSum) -> 0.56140351 | V24: =L24*Weight4/(WSum) -> 1.4035088 | W24: =M24*Weight5/(WSum) -> 0.61403509 | X24: =N24*Weight6/(WSum) -> 0.61403509 | Y24: =O24*Weight7/(WSum) -> 0 | Z24: =P24*Weight8/(WSum) -> 0.84210526 | AA24: =-1/10*G24+1 -> 0.8 | AB24: =IF(R24<0,0,-R24+1) -> 1 | AC24: =(AA24*CondWeight+AB24*PLifeWeight)/(CondWeight+PLifeWeight) -> 0.86666667 | AD24: =SUM(S24:Z24) -> 5.6666667 | AE24: =AD24*AC24*10 -> 49.111111 | AF24: Chapt 90/ Alt Funds | AH24: 400000 | AM24: =AH24 -> 400000
A25: 21 | B25: DPW/ Sewer | C25: Sewer | D25: Islington Road Sewer Pump Station - Replace Pumps | E25: Sewerage is pumped to higher point and gravity fed to MWRA pipes for treatment. Replace pumps, motors and flow recorder which are at life expectancy. | F25: 100000 | G25: 3 | H25: 0.1 | I25: 6 | J25: 8 | K25: 6 | L25: 8 | M25: 4 | N25: 6 | O25: 2 | P25: 10 | Q25: =(#REF!-(YEAR(TODAY())-#REF!))/#REF! -> #REF! | R25: =IFERROR(Q25,H25) -> 0.1 | S25: =I25*Weight1/(WSum) -> 0.94736842 | T25: =J25*Weight2/(WSum) -> 0.84210526 | U25: =K25*Weight3/(WSum) -> 0.84210526 | V25: =L25*Weight4/(WSum) -> 1.4035088 | W25: =M25*Weight5/(WSum) -> 0.35087719 | X25: =N25*Weight6/(WSum) -> 0.73684211 | Y25: =O25*Weight7/(WSum) -> 0.21052632 | Z25: =P25*Weight8/(WSum) -> 1.0526316 | AA25: =-1/10*G25+1 -> 0.7 | AB25: =IF(R25<0,0,-R25+1) -> 0.9 | AC25: =(AA25*CondWeight+AB25*PLifeWeight)/(CondWeight+PLifeWeight) -> 0.76666667 | AD25: =SUM(S25:Z25) -> 6.3859649 | AE25: =AD25*AC25*10 -> 48.959064 | AF25: Enterprise Funds | AH25: 100000 | AM25: =AH25 -> 100000
A26: 22 | B26: Schools | C26: Building | D26: Ed Center - Pre-K Building Upgrades | E26: Renovate toilet rooms for Pre-school and other improvements to correct water infiltration issues and address HVAC and space needs. | F26: 1000000 | G26: 2 | H26: 0 | I26: 6 | J26: 8 | K26: 4 | L26: 6 | M26: 4 | N26: 6 | O26: 1 | P26: 10 | Q26: =(#REF!-(YEAR(TODAY())-#REF!))/#REF! -> #REF! | R26: =IFERROR(Q26,H26) -> 0 | S26: =I26*Weight1/(WSum) -> 0.94736842 | T26: =J26*Weight2/(WSum) -> 0.84210526 | U26: =K26*Weight3/(WSum) -> 0.56140351 | V26: =L26*Weight4/(WSum) -> 1.0526316 | W26: =M26*Weight5/(WSum) -> 0.35087719 | X26: =N26*Weight6/(WSum) -> 0.73684211 | Y26: =O26*Weight7/(WSum) -> 0.10526316 | Z26: =P26*Weight8/(WSum) -> 1.0526316 | AA26: =-1/10*G26+1 -> 0.8 | AB26: =IF(R26<0,0,-R26+1) -> 1 | AC26: =(AA26*CondWeight+AB26*PLifeWeight)/(CondWeight+PLifeWeight) -> 0.86666667 | AD26: =SUM(S26:Z26) -> 5.6491228 | AE26: =AD26*AC26*10 -> 48.959064 | AF26: Bonding | AH26: 1000000 | AM26: =AH26 -> 1000000
A27: 23 | B27: Parks/Rec | C27: Building | D27: Lower Falls Community Center - Accessibility/ Site Upgrades | E27: Code required project to provide accessible toilet rooms, an accessible drinking fountain, and lift for access to the lower gym level. | F27: 300000 | G27: 1 | H27: 0.1 | I27: 4 | J27: 8 | K27: 2 | L27: 10 | M27: 0 | N27: 8 | O27: 0 | P27: 9 | Q27: =(#REF!-(YEAR(TODAY())-#REF!))/#REF! -> #REF! | R27: =IFERROR(Q27,H27) -> 0.1 | S27: =I27*Weight1/(WSum) -> 0.63157895 | T27: =J27*Weight2/(WSum) -> 0.84210526 | U27: =K27*Weight3/(WSum) -> 0.28070175 | V27: =L27*Weight4/(WSum) -> 1.754386 | W27: =M27*Weight5/(WSum) -> 0 | X27: =N27*Weight6/(WSum) -> 0.98245614 | Y27: =O27*Weight7/(WSum) -> 0 | Z27: =P27*Weight8/(WSum) -> 0.94736842 | AA27: =-1/10*G27+1 -> 0.9 | AB27: =IF(R27<0,0,-R27+1) -> 0.9 | AC27: =(AA27*CondWeight+AB27*PLifeWeight)/(CondWeight+PLifeWeight) -> 0.9 | AD27: =SUM(S27:Z27) -> 5.4385965 | AE27: =AD27*AC27*10 -> 48.947368 | AF27: Bonding | AG27: 25000 | AH27: 275000 | AM27: =AH27 -> 275000
A28: 24 | B28: Schools | C28: Building | D28: Ward School - Accessible Entrance | E28: Code required project to provide accessible entrance, toilet, and water fountain. | F28: 200000 | G28: 1 | H28: 0.1 | I28: 4 | J28: 8 | K28: 2 | L28: 10 | M28: 0 | N28: 8 | O28: 0 | P28: 9 | Q28: =(#REF!-(YEAR(TODAY())-#REF!))/#REF! -> #REF! | R28: =IFERROR(Q28,H28) -> 0.1 | S28: =I28*Weight1/(WSum) -> 0.63157895 | T28: =J28*Weight2/(WSum) -> 0.84210526 | U28: =K28*Weight3/(WSum) -> 0.28070175 | V28: =L28*Weight4/(WSum) -> 1.754386 | W28: =M28*Weight5/(WSum) -> 0 | X28: =N28*Weight6/(WSum) -> 0.98245614 | Y28: =O28*Weight7/(WSum) -> 0 | Z28: =P28*Weight8/(WSum) -> 0.94736842 | AA28: =-1/10*G28+1 -> 0.9 | AB28: =IF(R28<0,0,-R28+1) -> 0.9 | AC28: =(AA28*CondWeight+AB28*PLifeWeight)/(CondWeight+PLifeWeight) -> 0.9 | AD28: =SUM(S28:Z28) -> 5.4385965 | AE28: =AD28*AC28*10 -> 48.947368 | AF28: Bonding | AH28: 200000 | AM28: =AH28 -> 200000
A29: 25 | B29: IT | C29: Information Technology | D29: Install Citywide IT Data Network | E29: IT Advisory Cmte recommends implementation of City-wide network as high priority imperative to improve speed, reliability, and security to build the framework for major improvements and expansion of the City's IT capabilities in areas such as electronic storage and retrieval, disaster recovery, integrated > data warehouse and electronic workflow systems resulting in improved > work efficiencies and expansion of services network connections. | F29: 1750000 | G29: 3 | H29: 0.2 | I29: 10 | J29: 10 | K29: 6 | L29: 6 | M29: 0 | N29: 8 | O29: 1 | P29: 10 | Q29: =(#REF!-(YEAR(TODAY())-#REF!))/#REF! -> #REF! | R29: =IFERROR(Q29,H29) -> 0.2 | S29: =I29*Weight1/(WSum) -> 1.5789474 | T29: =J29*Weight2/(WSum) -> 1.0526316 | U29: =K29*Weight3/(WSum) -> 0.84210526 | V29: =L29*Weight4/(WSum) -> 1.0526316 | W29: =M29*Weight5/(WSum) -> 0 | X29: =N29*Weight6/(WSum) -> 0.98245614 | Y29: =O29*Weight7/(WSum) -> 0.10526316 | Z29: =P29*Weight8/(WSum) -> 1.0526316 | AA29: =-1/10*G29+1 -> 0.7 | AB29: =IF(R29<0,0,-R29+1) -> 0.8 | AC29: =(AA29*CondWeight+AB29*PLifeWeight)/(CondWeight+PLifeWeight) -> 0.73333333 | AD29: =SUM(S29:Z29) -> 6.6666667 | AE29: =AD29*AC29*10 -> 48.888889 | AF29: Other | AG29: 500000 | AH29: 250000 | AI29: 250000 | AJ29: 250000 | AK29: 250000 | AL29: 250000 | AM29: =AH29 -> 250000 | AN29: =AI29*(1+Efactor) -> 258750 | AO29: =AJ29*(1+Efactor)^2 -> 267806.25 | AP29: =AK29*(1+Efactor)^3 -> 277179.47 | AQ29: =AL29*(1+Efactor)^4 -> 286880.75
A30: 26 | B30: Parks/Rec | C30: Parks / Open Space | D30: Crystal Lake - Water Filtration System | E30: Upgrade water filtration system to mitigate algea. | F30: 100000 | G30: 2 | H30: 0 | I30: 5 | J30: 8 | K30: 3 | L30: 8 | M30: 0 | N30: 9 | O30: 0 | P30: 10 | Q30: =(#REF!-(YEAR(TODAY())-#REF!))/#REF! -> #REF! | R30: =IFERROR(Q30,H30) -> 0 | S30: =I30*Weight1/(WSum) -> 0.78947368 | T30: =J30*Weight2/(WSum) -> 0.84210526 | U30: =K30*Weight3/(WSum) -> 0.42105263 | V30: =L30*Weight4/(WSum) -> 1.4035088 | W30: =M30*Weight5/(WSum) -> 0 | X30: =N30*Weight6/(WSum) -> 1.1052632 | Y30: =O30*Weight7/(WSum) -> 0 | Z30: =P30*Weight8/(WSum) -> 1.0526316 | AA30: =-1/10*G30+1 -> 0.8 | AB30: =IF(R30<0,0,-R30+1) -> 1 | AC30: =(AA30*CondWeight+AB30*PLifeWeight)/(CondWeight+PLifeWeight) -> 0.86666667 | AD30: =SUM(S30:Z30) -> 5.6140351 | AE30: =AD30*AC30*10 -> 48.654971 | AF30: Bonding | AH30: 100000 | AM30: =AH30 -> 100000
A31: 27 | B31: DPW | C31: Large Vehicle/ Equipment | D31: DPW - Replace Street Sweeper | E31: Replacement of vehicle taken out of service: Vehicle #148. Dept will not have minimum (6 ea) needed for 4 sweeps/yr efficiently. Contracting out services is alternative at great expense. | F31: 172000 | G31: 1 | H31: 0 | I31: 6 | J31: 8 | K31: 6 | L31: 5 | M31: 0 | N31: 7 | O31: 0 | P31: 8 | Q31: =(#REF!-(YEAR(TODAY())-#REF!))/#REF! -> #REF! | R31: =IFERROR(Q31,H31) -> 0 | S31: =I31*Weight1/(WSum) -> 0.94736842 | T31: =J31*Weight2/(WSum) -> 0.84210526 | U31: =K31*Weight3/(WSum) -> 0.84210526 | V31: =L31*Weight4/(WSum) -> 0.87719298 | W31: =M31*Weight5/(WSum) -> 0 | X31: =N31*Weight6/(WSum) -> 0.85964912 | Y31: =O31*Weight7/(WSum) -> 0 | Z31: =P31*Weight8/(WSum) -> 0.84210526 | AA31: =-1/10*G31+1 -> 0.9 | AB31: =IF(R31<0,0,-R31+1) -> 1 | AC31: =(AA31*CondWeight+AB31*PLifeWeight)/(CondWeight+PLifeWeight) -> 0.93333333 | AD31: =SUM(S31:Z31) -> 5.2105263 | AE31: =AD31*AC31*10 -> 48.631579 | AF31: Bonding | AH31: 172000 | AM31: =AH31 -> 172000
A32: 28 | B32: DPW/ Water | C32: Large Vehicle/ Equipment | D32: Replace 2002 Construction Truck | E32: Replacement of existing city vehicle used for construction work on City water mains and for snow removal/sanding operations. Life span of vehicles is 15 yrs. (#309) | F32: 130000 | G32: 1 | H32: 0 | I32: 6 | J32: 6 | K32: 5 | L32: 7 | M32: 4 | N32: 5 | O32: 1 | P32: 6 | Q32: =(#REF!-(YEAR(TODAY())-#REF!))/#REF! -> #REF! | R32: =IFERROR(Q32,H32) -> 0 | S32: =I32*Weight1/(WSum) -> 0.94736842 | T32: =J32*Weight2/(WSum) -> 0.63157895 | U32: =K32*Weight3/(WSum) -> 0.70175439 | V32: =L32*Weight4/(WSum) -> 1.2280702 | W32: =M32*Weight5/(WSum) -> 0.35087719 | X32: =N32*Weight6/(WSum) -> 0.61403509 | Y32: =O32*Weight7/(WSum) -> 0.10526316 | Z32: =P32*Weight8/(WSum) -> 0.63157895 | AA32: =-1/10*G32+1 -> 0.9 | AB32: =IF(R32<0,0,-R32+1) -> 1 | AC32: =(AA32*CondWeight+AB32*PLifeWeight)/(CondWeight+PLifeWeight) -> 0.93333333 | AD32: =SUM(S32:Z32) -> 5.2105263 | AE32: =AD32*AC32*10 -> 48.631579 | AF32: Enterprise Funds | AH32: 130000 | AM32: =AH32 -> 130000
A33: 29 | B33: DPW/ Sewer | C33: Sewer | D33: Elliot Street Sewer Pump Station - Repair Pumps | E33: Sewerage is pumped to higher point and gravity fed to MWRA pipes for treatment. Replace pumps and flow recorder which are at life expectancy. | F33: 100000 | G33: 2 | H33: 0.2 | I33: 6 | J33: 8 | K33: 6 | L33: 8 | M33: 4 | N33: 6 | O33: 1 | P33: 8 | Q33: =(#REF!-(YEAR(TODAY())-#REF!))/#REF! -> #REF! | R33: =IFERROR(Q33,H33) -> 0.2 | S33: =I33*Weight1/(WSum) -> 0.94736842 | T33: =J33*Weight2/(WSum) -> 0.84210526 | U33: =K33*Weight3/(WSum) -> 0.84210526 | V33: =L33*Weight4/(WSum) -> 1.4035088 | W33: =M33*Weight5/(WSum) -> 0.35087719 | X33: =N33*Weight6/(WSum) -> 0.73684211 | Y33: =O33*Weight7/(WSum) -> 0.10526316 | Z33: =P33*Weight8/(WSum) -> 0.84210526 | AA33: =-1/10*G33+1 -> 0.8 | AB33: =IF(R33<0,0,-R33+1) -> 0.8 | AC33: =(AA33*CondWeight+AB33*PLifeWeight)/(CondWeight+PLifeWeight) -> 0.8 | AD33: =SUM(S33:Z33) -> 6.0701754 | AE33: =AD33*AC33*10 -> 48.561404 | AF33: Enterprise Funds | AH33: 100000 | AM33: =AH33 -> 100000
A34: 30 | B34: DPW/ Sewer | C34: Large Vehicle/ Equipment | D34: Replace 2003 Backhoe | E34: Replacement of existing city vehicle/ equipment used in sewer line repairs and maintenance (#327). | F34: 120000 | G34: 3 | H34: 0 | I34: 6 | J34: 8 | K34: 6 | L34: 8 | M34: 4 | N34: 6 | O34: 1 | P34: 8 | Q34: =(#REF!-(YEAR(TODAY())-#REF!))/#REF! -> #REF! | R34: =IFERROR(Q34,H34) -> 0 | S34: =I34*Weight1/(WSum) -> 0.94736842 | T34: =J34*Weight2/(WSum) -> 0.84210526 | U34: =K34*Weight3/(WSum) -> 0.84210526 | V34: =L34*Weight4/(WSum) -> 1.4035088 | W34: =M34*Weight5/(WSum) -> 0.35087719 | X34: =N34*Weight6/(WSum) -> 0.73684211 | Y34: =O34*Weight7/(WSum) -> 0.10526316 | Z34: =P34*Weight8/(WSum) -> 0.84210526 | AA34: =-1/10*G34+1 -> 0.7 | AB34: =IF(R34<0,0,-R34+1) -> 1 | AC34: =(AA34*CondWeight+AB34*PLifeWeight)/(CondWeight+PLifeWeight) -> 0.8 | AD34: =SUM(S34:Z34) -> 6.0701754 | AE34: =AD34*AC34*10 -> 48.561404 | AF34: Enterprise Funds | AH34: 120000 | AM34: =AH34 -> 120000
A35: 31 | B35: DPW/ Sewer | C35: Large Vehicle/ Equipment | D35: Replace 2004 Sewer Clam Truck | E35: Replacement of damaged city vehicle/ equipment used to clean sewer catch basins and brook grates. (#330) | F35: 200000 | G35: 3 | H35: 0 | I35: 6 | J35: 8 | K35: 6 | L35: 8 | M35: 4 | N35: 6 | O35: 1 | P35: 8 | Q35: =(#REF!-(YEAR(TODAY())-#REF!))/#REF! -> #REF! | R35: =IFERROR(Q35,H35) -> 0 | S35: =I35*Weight1/(WSum) -> 0.94736842 | T35: =J35*Weight2/(WSum) -> 0.84210526 | U35: =K35*Weight3/(WSum) -> 0.84210526 | V35: =L35*Weight4/(WSum) -> 1.4035088 | W35: =M35*Weight5/(WSum) -> 0.35087719 | X35: =N35*Weight6/(WSum) -> 0.73684211 | Y35: =O35*Weight7/(WSum) -> 0.10526316 | Z35: =P35*Weight8/(WSum) -> 0.84210526 | AA35: =-1/10*G35+1 -> 0.7 | AB35: =IF(R35<0,0,-R35+1) -> 1 | AC35: =(AA35*CondWeight+AB35*PLifeWeight)/(CondWeight+PLifeWeight) -> 0.8 | AD35: =SUM(S35:Z35) -> 6.0701754 | AE35: =AD35*AC35*10 -> 48.561404 | AF35: Enterprise Funds | AH35: 200000 | AM35: =AH35 -> 200000
A36: 32 | B36: Schools | C36: Building | D36: Zervas School - Renovation and Addition/ Replacement | E36: FY14 feasibility study. Project to address space needs due to growing enrollment, bldg systems, access. Include cost to move to Carr and back to Zervas Anticipate high maintenance costs on mechanical system until building is renovated. | F36: 42500000 | G36: 3 | H36: 0 | I36: 8 | J36: 10 | K36: 4 | L36: 4 | M36: 0 | N36: 10 | O36: 2 | P36: 10 | Q36: =(#REF!-(YEAR(TODAY())-#REF!))/#REF! -> #REF! | R36: =IFERROR(Q36,H36) -> 0 | S36: =I36*Weight1/(WSum) -> 1.2631579 | T36: =J36*Weight2/(WSum) -> 1.0526316 | U36: =K36*Weight3/(WSum) -> 0.56140351 | V36: =L36*Weight4/(WSum) -> 0.70175439 | W36: =M36*Weight5/(WSum) -> 0 | X36: =N36*Weight6/(WSum) -> 1.2280702 | Y36: =O36*Weight7/(WSum) -> 0.21052632 | Z36: =P36*Weight8/(WSum) -> 1.0526316 | AA36: =-1/10*G36+1 -> 0.7 | AB36: =IF(R36<0,0,-R36+1) -> 1 | AC36: =(AA36*CondWeight+AB36*PLifeWeight)/(CondWeight+PLifeWeight) -> 0.8 | AD36: =SUM(S36:Z36) -> 6.0701754 | AE36: =AD36*AC36*10 -> 48.561404 | AF36: Bonding /MSBA | AH36: 750000 | AL36: 15250239 | AM36: =AH36 -> 750000 | AQ36: =AL36*(1+Efactor)^4 -> 17500000
A37: 33 | B37: DPW | C37: Large Vehicle/ Equipment | D37: DPW - Replace 1995 Backhoe | E37: Replacement of existing city vehicle/ equipment that is beyond useful life, used for street & sidewalk repairs. (#130). | F37: 110000 | G37: 2 | H37: 0.1 | I37: 7 | J37: 8 | K37: 6 | L37: 6 | M37: 2 | N37: 6 | O37: 0 | P37: 10 | Q37: =(#REF!-(YEAR(TODAY())-#REF!))/#REF! -> #REF! | R37: =IFERROR(Q37,H37) -> 0.1 | S37: =I37*Weight1/(WSum) -> 1.1052632 | T37: =J37*Weight2/(WSum) -> 0.84210526 | U37: =K37*Weight3/(WSum) -> 0.84210526 | V37: =L37*Weight4/(WSum) -> 1.0526316 | W37: =M37*Weight5/(WSum) -> 0.1754386 | X37: =N37*Weight6/(WSum) -> 0.73684211 | Y37: =O37*Weight7/(WSum) -> 0 | Z37: =P37*Weight8/(WSum) -> 1.0526316 | AA37: =-1/10*G37+1 -> 0.8 | AB37: =IF(R37<0,0,-R37+1) -> 0.9 | AC37: =(AA37*CondWeight+AB37*PLifeWeight)/(CondWeight+PLifeWeight) -> 0.83333333 | AD37: =SUM(S37:Z37) -> 5.8070175 | AE37: =AD37*AC37*10 -> 48.391813 | AF37: Bonding | AH37: 110000 | AM37: =AH37 -> 110000
A38: 34 | B38: DPW/ Sewer | C38: Sewer | D38: Sewer Inflow /Infiltration Project - Lower Falls Area | E38: Part of 12 yr $49.1 M program to remove excess inflow and infiltration into sewer system. Design (FY14) and constr (FY15) for Lower Falls area. | F38: 3861585 | G38: 3 | H38: 0.3 | I38: 8 | J38: 8 | K38: 8 | L38: 8 | M38: 4 | N38: 8 | O38: 0 | P38: 9 | Q38: =(#REF!-(YEAR(TODAY())-#REF!))/#REF! -> #REF! | R38: =IFERROR(Q38,H38) -> 0.3 | S38: =I38*Weight1/(WSum) -> 1.2631579 | T38: =J38*Weight2/(WSum) -> 0.84210526 | U38: =K38*Weight3/(WSum) -> 1.122807 | V38: =L38*Weight4/(WSum) -> 1.4035088 | W38: =M38*Weight5/(WSum) -> 0.35087719 | X38: =N38*Weight6/(WSum) -> 0.98245614 | Y38: =O38*Weight7/(WSum) -> 0 | Z38: =P38*Weight8/(WSum) -> 0.94736842 | AA38: =-1/10*G38+1 -> 0.7 | AB38: =IF(R38<0,0,-R38+1) -> 0.7 | AC38: =(AA38*CondWeight+AB38*PLifeWeight)/(CondWeight+PLifeWeight) -> 0.7 | AD38: =SUM(S38:Z38) -> 6.9122807 | AE38: =AD38*AC38*10 -> 48.385965 | AF38: Enterprise Funds | AH38: 523710 | AI38: 3337875 | AM38: =AH38 -> 523710 | AN38: =AI38*(1+Efactor) -> 3454700.6
A39: 35 | B39: DPW/ Water | C39: Water | D39: Replace Water Pipes to Improve Fire Flows | E39: Year three of 3 year program to replace and repair water pipes in order to meet ISO fire flow standards which are currently defficient. | F39: 4209000 | G39: 2 | H39: 0.3 | I39: 6 | J39: 6 | K39: 8 | L39: 8 | M39: 7 | N39: 6 | O39: 0 | P39: 8 | Q39: =(#REF!-(YEAR(TODAY())-#REF!))/#REF! -> #REF! | R39: =IFERROR(Q39,H39) -> 0.3 | S39: =I39*Weight1/(WSum) -> 0.94736842 | T39: =J39*Weight2/(WSum) -> 0.63157895 | U39: =K39*Weight3/(WSum) -> 1.122807 | V39: =L39*Weight4/(WSum) -> 1.4035088 | W39: =M39*Weight5/(WSum) -> 0.61403509 | X39: =N39*Weight6/(WSum) -> 0.73684211 | Y39: =O39*Weight7/(WSum) -> 0 | Z39: =P39*Weight8/(WSum) -> 0.84210526 | AA39: =-1/10*G39+1 -> 0.8 | AB39: =IF(R39<0,0,-R39+1) -> 0.7 | AC39: =(AA39*CondWeight+AB39*PLifeWeight)/(CondWeight+PLifeWeight) -> 0.76666667 | AD39: =SUM(S39:Z39) -> 6.2982456 | AE39: =AD39*AC39*10 -> 48.28655 | AF39: Enterprise Funds | AI39: 4209000 | AN39: =AI39*(1+Efactor) -> 4356315
A40: 36 | B40: Schools | C40: Building | D40: Peirce School - Mechanical Upgrades | E40: Replace one 60 yo boiler and associated systems. 2nd boiler and DDC conversion in future project. Remove underground tank. | F40: 240000 | G40: 3 | H40: 0 | I40: 6 | J40: 8 | K40: 6 | L40: 4 | M40: 3 | N40: 7 | O40: 7 | P40: 8 | Q40: =(#REF!-(YEAR(TODAY())-#REF!))/#REF! -> #REF! | R40: =IFERROR(Q40,H40) -> 0 | S40: =I40*Weight1/(WSum) -> 0.94736842 | T40: =J40*Weight2/(WSum) -> 0.84210526 | U40: =K40*Weight3/(WSum) -> 0.84210526 | V40: =L40*Weight4/(WSum) -> 0.70175439 | W40: =M40*Weight5/(WSum) -> 0.26315789 | X40: =N40*Weight6/(WSum) -> 0.85964912 | Y40: =O40*Weight7/(WSum) -> 0.73684211 | Z40: =P40*Weight8/(WSum) -> 0.84210526 | AA40: =-1/10*G40+1 -> 0.7 | AB40: =IF(R40<0,0,-R40+1) -> 1 | AC40: =(AA40*CondWeight+AB40*PLifeWeight)/(CondWeight+PLifeWeight) -> 0.8 | AD40: =SUM(S40:Z40) -> 6.0350877 | AE40: =AD40*AC40*10 -> 48.280702 | AF40: Bonding | AI40: 240000 | AN40: =AI40*(1+Efactor) -> 248400
A41: 37 | B41: DPW | C41: Roads/ Paving | D41: Sidewalk Improvements | E41: Improve pedestrian safety. Repair/replacement of sidewalks in poor condition and new sidewalks in village centers, school zones, on major roads. | F41: 150000 | G41: 2 | H41: 0 | I41: 5 | J41: 6 | K41: 2 | L41: 8 | M41: 2 | N41: 10 | O41: 0 | P41: 10 | Q41: =(#REF!-(YEAR(TODAY())-#REF!))/#REF! -> #REF! | R41: =IFERROR(Q41,H41) -> 0 | S41: =I41*Weight1/(WSum) -> 0.78947368 | T41: =J41*Weight2/(WSum) -> 0.63157895 | U41: =K41*Weight3/(WSum) -> 0.28070175 | V41: =L41*Weight4/(WSum) -> 1.4035088 | W41: =M41*Weight5/(WSum) -> 0.1754386 | X41: =N41*Weight6/(WSum) -> 1.2280702 | Y41: =O41*Weight7/(WSum) -> 0 | Z41: =P41*Weight8/(WSum) -> 1.0526316 | AA41: =-1/10*G41+1 -> 0.8 | AB41: =IF(R41<0,0,-R41+1) -> 1 | AC41: =(AA41*CondWeight+AB41*PLifeWeight)/(CondWeight+PLifeWeight) -> 0.86666667 | AD41: =SUM(S41:Z41) -> 5.5614035 | AE41: =AD41*AC41*10 -> 48.19883 | AF41: Alternate Funding | AH41: 150000 | AM41: =AH41 -> 150000
A42: 38 | B42: Library | C42: Building | D42: Newton Free Library - Mechanical Upgrades | E42: Interior air handler replacement, pneumatic DDC controls conversion, replace chiller controls, repair/restore ice tank system. | F42: 1100000 | G42: 3 | H42: 0.1 | I42: 8 | J42: 8 | K42: 6 | L42: 4 | M42: 2 | N42: 8 | O42: 6 | P42: 8 | Q42: =(#REF!-(YEAR(TODAY())-#REF!))/#REF! -> #REF! | R42: =IFERROR(Q42,H42) -> 0.1 | S42: =I42*Weight1/(WSum) -> 1.2631579 | T42: =J42*Weight2/(WSum) -> 0.84210526 | U42: =K42*Weight3/(WSum) -> 0.84210526 | V42: =L42*Weight4/(WSum) -> 0.70175439 | W42: =M42*Weight5/(WSum) -> 0.1754386 | X42: =N42*Weight6/(WSum) -> 0.98245614 | Y42: =O42*Weight7/(WSum) -> 0.63157895 | Z42: =P42*Weight8/(WSum) -> 0.84210526 | AA42: =-1/10*G42+1 -> 0.7 | AB42: =IF(R42<0,0,-R42+1) -> 0.9 | AC42: =(AA42*CondWeight+AB42*PLifeWeight)/(CondWeight+PLifeWeight) -> 0.76666667 | AD42: =SUM(S42:Z42) -> 6.2807018 | AE42: =AD42*AC42*10 -> 48.152047 | AF42: Bonding | AI42: 500000 | AJ42: 300000 | AK42: 300000 | AN42: =AI42*(1+Efactor) -> 517500 | AO42: =AJ42*(1+Efactor)^2 -> 321367.5 | AP42: =AK42*(1+Efactor)^3 -> 332615.36
A43: 39 | B43: Police | C43: Building | D43: Police Headquarters - Mechanical Upgrades | E43: Replace Roof Top Mechanical equipment that is beyond its useful life. Currently requires a lot of maintenance and service calls. | F43: 300000 | G43: 1 | H43: 0.1 | I43: 8 | J43: 4 | K43: 6 | L43: 6 | M43: 0 | N43: 4 | O43: 4 | P43: 8 | Q43: =(#REF!-(YEAR(TODAY())-#REF!))/#REF! -> #REF! | R43: =IFERROR(Q43,H43) -> 0.1 | S43: =I43*Weight1/(WSum) -> 1.2631579 | T43: =J43*Weight2/(WSum) -> 0.42105263 | U43: =K43*Weight3/(WSum) -> 0.84210526 | V43: =L43*Weight4/(WSum) -> 1.0526316 | W43: =M43*Weight5/(WSum) -> 0 | X43: =N43*Weight6/(WSum) -> 0.49122807 | Y43: =O43*Weight7/(WSum) -> 0.42105263 | Z43: =P43*Weight8/(WSum) -> 0.84210526 | AA43: =-1/10*G43+1 -> 0.9 | AB43: =IF(R43<0,0,-R43+1) -> 0.9 | AC43: =(AA43*CondWeight+AB43*PLifeWeight)/(CondWeight+PLifeWeight) -> 0.9 | AD43: =SUM(S43:Z43) -> 5.3333333 | AE43: =AD43*AC43*10 -> 48 | AF43: Bonding | AI43: 300000 | AN43: =AI43*(1+Efactor) -> 310500
A44: 40 | B44: Schools | C44: Building | D44: Horace Mann School - Exterior Masonry | E44: Concrete around building has settled and cracked in various places creating a tripping hazard. Repair to prevent further deterioration. | F44: 100000 | G44: 1 | H44: 0 | I44: 4 | J44: 7 | K44: 4 | L44: 8 | M44: 5 | N44: 4 | O44: 0 | P44: 8 | Q44: =(#REF!-(YEAR(TODAY())-#REF!))/#REF! -> #REF! | R44: =IFERROR(Q44,H44) -> 0 | S44: =I44*Weight1/(WSum) -> 0.63157895 | T44: =J44*Weight2/(WSum) -> 0.73684211 | U44: =K44*Weight3/(WSum) -> 0.56140351 | V44: =L44*Weight4/(WSum) -> 1.4035088 | W44: =M44*Weight5/(WSum) -> 0.43859649 | X44: =N44*Weight6/(WSum) -> 0.49122807 | Y44: =O44*Weight7/(WSum) -> 0 | Z44: =P44*Weight8/(WSum) -> 0.84210526 | AA44: =-1/10*G44+1 -> 0.9 | AB44: =IF(R44<0,0,-R44+1) -> 1 | AC44: =(AA44*CondWeight+AB44*PLifeWeight)/(CondWeight+PLifeWeight) -> 0.93333333 | AD44: =SUM(S44:Z44) -> 5.1052632 | AE44: =AD44*AC44*10 -> 47.649123 | AF44: Bonding | AI44: 100000 | AN44: =AI44*(1+Efactor) -> 103500
A45: 41 | B45: DPW | C45: Roads/ Paving | D45: Street Paving - Cold Plane and Pave 20 Streets | E45: Roads include Lowell, Melrose, Staniford, Freeman, Lake, Crystal, Berwick, Oak, Grove, Central, Bridge, Temple, Walnut, Linwood, Walnut Pl, Newtonville, Daniel, Ridge, Collins | F45: 3032150 | G45: 2 | H45: 0.2 | I45: 8 | J45: 8 | K45: 2 | L45: 6 | M45: 4 | N45: 9 | O45: 0 | P45: 10 | Q45: =(#REF!-(YEAR(TODAY())-#REF!))/#REF! -> #REF! | R45: =IFERROR(Q45,H45) -> 0.2 | S45: =I45*Weight1/(WSum) -> 1.2631579 | T45: =J45*Weight2/(WSum) -> 0.84210526 | U45: =K45*Weight3/(WSum) -> 0.28070175 | V45: =L45*Weight4/(WSum) -> 1.0526316 | W45: =M45*Weight5/(WSum) -> 0.35087719 | X45: =N45*Weight6/(WSum) -> 1.1052632 | Y45: =O45*Weight7/(WSum) -> 0 | Z45: =P45*Weight8/(WSum) -> 1.0526316 | AA45: =-1/10*G45+1 -> 0.8 | AB45: =IF(R45<0,0,-R45+1) -> 0.8 | AC45: =(AA45*CondWeight+AB45*PLifeWeight)/(CondWeight+PLifeWeight) -> 0.8 | AD45: =SUM(S45:Z45) -> 5.9473684 | AE45: =AD45*AC45*10 -> 47.578947 | AF45: Chapt 90/ Alt Funds | AI45: 2929614 | AN45: =AI45*(1+Efactor) -> 3032150.5
A46: 42 | B46: DPW | C46: Roads/ Paving | D46: Sidewalk Improvements -Provide ADA Access Curb Cuts | E46: Provide appropriate curb cuts to comply with federal ADA requirements and to provide safe, accessible means to and from City sidewalks. | F46: 62000 | G46: 2 | H46: 0.2 | I46: 6 | J46: 8 | K46: 4 | L46: 8 | M46: 4 | N46: 8 | O46: 0 | P46: 8 | Q46: =(#REF!-(YEAR(TODAY())-#REF!))/#REF! -> #REF! | R46: =IFERROR(Q46,H46) -> 0.2 | S46: =I46*Weight1/(WSum) -> 0.94736842 | T46: =J46*Weight2/(WSum) -> 0.84210526 | U46: =K46*Weight3/(WSum) -> 0.56140351 | V46: =L46*Weight4/(WSum) -> 1.4035088 | W46: =M46*Weight5/(WSum) -> 0.35087719 | X46: =N46*Weight6/(WSum) -> 0.98245614 | Y46: =O46*Weight7/(WSum) -> 0 | Z46: =P46*Weight8/(WSum) -> 0.84210526 | AA46: =-1/10*G46+1 -> 0.8 | AB46: =IF(R46<0,0,-R46+1) -> 0.8 | AC46: =(AA46*CondWeight+AB46*PLifeWeight)/(CondWeight+PLifeWeight) -> 0.8 | AD46: =SUM(S46:Z46) -> 5.9298246 | AE46: =AD46*AC46*10 -> 47.438596 | AF46: CDBG Eligible | AH46: 62000 | AM46: =AH46 -> 62000
A47: 43 | B47: Public Buildings | C47: Building | D47: Energy Efficiency / Water Conservation Upgrades to City and School Buildings | E47: Project includes energy conservation measures at Ward, Mason Rice, Zervas, and Williams Schools thru NSTAR preferred vendor program. | F47: 1000000 | G47: 3 | H47: 0.2 | I47: 6 | J47: 8 | K47: 7 | L47: 4 | M47: 0 | N47: 8 | O47: 9 | P47: 10 | Q47: =(#REF!-(YEAR(TODAY())-#REF!))/#REF! -> #REF! | R47: =IFERROR(Q47,H47) -> 0.2 | S47: =I47*Weight1/(WSum) -> 0.94736842 | T47: =J47*Weight2/(WSum) -> 0.84210526 | U47: =K47*Weight3/(WSum) -> 0.98245614 | V47: =L47*Weight4/(WSum) -> 0.70175439 | W47: =M47*Weight5/(WSum) -> 0 | X47: =N47*Weight6/(WSum) -> 0.98245614 | Y47: =O47*Weight7/(WSum) -> 0.94736842 | Z47: =P47*Weight8/(WSum) -> 1.0526316 | AA47: =-1/10*G47+1 -> 0.7 | AB47: =IF(R47<0,0,-R47+1) -> 0.8 | AC47: =(AA47*CondWeight+AB47*PLifeWeight)/(CondWeight+PLifeWeight) -> 0.73333333 | AD47: =SUM(S47:Z47) -> 6.4561404 | AE47: =AD47*AC47*10 -> 47.345029 | AF47: Energy Stabilztn Fund | AI47: 1000000 | AN47: =AI47*(1+Efactor) -> 1035000
A48: 44 | B48: DPW/ Sewer | C48: Sewer | D48: Sewer Inflow /Infiltration Project - Chestnut Hill Area | E48: Part of 12 yr $49.1 M program to remove excess inflow and infiltration into sewer system. Design (FY15) and constr (FY16) for Chestnut Hill area. | F48: 6510150 | G48: 4 | H48: 0.2 | I48: 8 | J48: 8 | K48: 8 | L48: 8 | M48: 6 | N48: 8 | O48: 0 | P48: 9 | Q48: =(#REF!-(YEAR(TODAY())-#REF!))/#REF! -> #REF! | R48: =IFERROR(Q48,H48) -> 0.2 | S48: =I48*Weight1/(WSum) -> 1.2631579 | T48: =J48*Weight2/(WSum) -> 0.84210526 | U48: =K48*Weight3/(WSum) -> 1.122807 | V48: =L48*Weight4/(WSum) -> 1.4035088 | W48: =M48*Weight5/(WSum) -> 0.52631579 | X48: =N48*Weight6/(WSum) -> 0.98245614 | Y48: =O48*Weight7/(WSum) -> 0 | Z48: =P48*Weight8/(WSum) -> 0.94736842 | AA48: =-1/10*G48+1 -> 0.6 | AB48: =IF(R48<0,0,-R48+1) -> 0.8 | AC48: =(AA48*CondWeight+AB48*PLifeWeight)/(CondWeight+PLifeWeight) -> 0.66666667 | AD48: =SUM(S48:Z48) -> 7.0877193 | AE48: =AD48*AC48*10 -> 47.251462 | AF48: Enterprise Funds | AI48: 1257525 | AJ48: 5252625 | AN48: =AI48*(1+Efactor) -> 1301538.4 | AO48: =AJ48*(1+Efactor)^2 -> 5626743.2
A49: 45 | B49: Schools | C49: Building | D49: Lincoln Eliot School - Plumbing Upgrades | E49: Replace deteriorated sanitary pipe, distribution, risers and vents, toilet rooms. Assess issues in FY15 to determine scope of additional work. | F49: 650000 | G49: 2 | H49: 0 | I49: 6 | J49: 8 | K49: 4 | L49: 6 | M49: 4 | N49: 6 | O49: 1 | P49: 8 | Q49: =(#REF!-(YEAR(TODAY())-#REF!))/#REF! -> #REF! | R49: =IFERROR(Q49,H49) -> 0 | S49: =I49*Weight1/(WSum) -> 0.94736842 | T49: =J49*Weight2/(WSum) -> 0.84210526 | U49: =K49*Weight3/(WSum) -> 0.56140351 | V49: =L49*Weight4/(WSum) -> 1.0526316 | W49: =M49*Weight5/(WSum) -> 0.35087719 | X49: =N49*Weight6/(WSum) -> 0.73684211 | Y49: =O49*Weight7/(WSum) -> 0.10526316 | Z49: =P49*Weight8/(WSum) -> 0.84210526 | AA49: =-1/10*G49+1 -> 0.8 | AB49: =IF(R49<0,0,-R49+1) -> 1 | AC49: =(AA49*CondWeight+AB49*PLifeWeight)/(CondWeight+PLifeWeight) -> 0.86666667 | AD49: =SUM(S49:Z49) -> 5.4385965 | AE49: =AD49*AC49*10 -> 47.134503 | AF49: Bonding | AI49: 200000 | AK49: 450000 | AN49: =AI49*(1+Efactor) -> 207000 | AP49: =AK49*(1+Efactor)^3 -> 498923.04
A50: 46 | B50: Public Buildings | C50: Building | D50: Replace Underground Storage Tanks at City Buildings | E50: Replace fuel tanks at Park bldgs and Fire Department Headquarters. Tanks are beyond their useful life expectancy. | F50: 100000 | G50: 2 | H50: 0 | I50: 5 | J50: 6 | K50: 5 | L50: 9 | M50: 5 | N50: 2 | O50: 2 | P50: 8 | Q50: =(#REF!-(YEAR(TODAY())-#REF!))/#REF! -> #REF! | R50: =IFERROR(Q50,H50) -> 0 | S50: =I50*Weight1/(WSum) -> 0.78947368 | T50: =J50*Weight2/(WSum) -> 0.63157895 | U50: =K50*Weight3/(WSum) -> 0.70175439 | V50: =L50*Weight4/(WSum) -> 1.5789474 | W50: =M50*Weight5/(WSum) -> 0.43859649 | X50: =N50*Weight6/(WSum) -> 0.24561404 | Y50: =O50*Weight7/(WSum) -> 0.21052632 | Z50: =P50*Weight8/(WSum) -> 0.84210526 | AA50: =-1/10*G50+1 -> 0.8 | AB50: =IF(R50<0,0,-R50+1) -> 1 | AC50: =(AA50*CondWeight+AB50*PLifeWeight)/(CondWeight+PLifeWeight) -> 0.86666667 | AD50: =SUM(S50:Z50) -> 5.4385965 | AE50: =AD50*AC50*10 -> 47.134503 | AF50: Bonding | AI50: 100000 | AN50: =AI50*(1+Efactor) -> 103500
A51: 47 | B51: Schools | C51: Building | D51: Horace Mann School - Electrical/ Emergency Generator | E51: Replace emergency generator with smaller unit and install battery back-up emergency egress lighting system. Upgrade elec service/ panels. | F51: 350000 | G51: 3 | H51: 0.1 | I51: 6 | J51: 8 | K51: 4 | L51: 8 | M51: 4 | N51: 8 | O51: 2 | P51: 8 | Q51: =(#REF!-(YEAR(TODAY())-#REF!))/#REF! -> #REF! | R51: =IFERROR(Q51,H51) -> 0.1 | S51: =I51*Weight1/(WSum) -> 0.94736842 | T51: =J51*Weight2/(WSum) -> 0.84210526 | U51: =K51*Weight3/(WSum) -> 0.56140351 | V51: =L51*Weight4/(WSum) -> 1.4035088 | W51: =M51*Weight5/(WSum) -> 0.35087719 | X51: =N51*Weight6/(WSum) -> 0.98245614 | Y51: =O51*Weight7/(WSum) -> 0.21052632 | Z51: =P51*Weight8/(WSum) -> 0.84210526 | AA51: =-1/10*G51+1 -> 0.7 | AB51: =IF(R51<0,0,-R51+1) -> 0.9 | AC51: =(AA51*CondWeight+AB51*PLifeWeight)/(CondWeight+PLifeWeight) -> 0.76666667 | AD51: =SUM(S51:Z51) -> 6.1403509 | AE51: =AD51*AC51*10 -> 47.076023 | AF51: Bonding | AI51: 125000 | AN51: =AI51*(1+Efactor) -> 129375
A52: 48 | B52: DPW/ Water | C52: Building | D52: DPW-Water/Utilities Department -Mechanical Upgrades | E52: Install CO/NOx detection system for garage so that the detection of gas energizes the existing exhaust fans. Install backdraft damper on fans. | F52: 75000 | G52: 3 | H52: 0 | I52: 8 | J52: 4 | K52: 6 | L52: 8 | M52: 6 | N52: 3 | O52: 2 | P52: 8 | Q52: =(#REF!-(YEAR(TODAY())-#REF!))/#REF! -> #REF! | R52: =IFERROR(Q52,H52) -> 0 | S52: =I52*Weight1/(WSum) -> 1.2631579 | T52: =J52*Weight2/(WSum) -> 0.42105263 | U52: =K52*Weight3/(WSum) -> 0.84210526 | V52: =L52*Weight4/(WSum) -> 1.4035088 | W52: =M52*Weight5/(WSum) -> 0.52631579 | X52: =N52*Weight6/(WSum) -> 0.36842105 | Y52: =O52*Weight7/(WSum) -> 0.21052632 | Z52: =P52*Weight8/(WSum) -> 0.84210526 | AA52: =-1/10*G52+1 -> 0.7 | AB52: =IF(R52<0,0,-R52+1) -> 1 | AC52: =(AA52*CondWeight+AB52*PLifeWeight)/(CondWeight+PLifeWeight) -> 0.8 | AD52: =SUM(S52:Z52) -> 5.877193 | AE52: =AD52*AC52*10 -> 47.017544 | AF52: Enterprise Funds | AI52: 75000 | AN52: =AI52*(1+Efactor) -> 77625
A53: 49 | B53: Schools | C53: Building | D53: Remove Underground Tanks at Various Schools | E53: Remove underground tanks which are no longer needed at Bigelow Middle School, NSHS, and the Ed Center. | F53: 260000 | G53: 2 | H53: 0 | I53: 5 | J53: 6 | K53: 5 | L53: 10 | M53: 4 | N53: 2 | O53: 1 | P53: 8 | Q53: =(#REF!-(YEAR(TODAY())-#REF!))/#REF! -> #REF! | R53: =IFERROR(Q53,H53) -> 0 | S53: =I53*Weight1/(WSum) -> 0.78947368 | T53: =J53*Weight2/(WSum) -> 0.63157895 | U53: =K53*Weight3/(WSum) -> 0.70175439 | V53: =L53*Weight4/(WSum) -> 1.754386 | W53: =M53*Weight5/(WSum) -> 0.35087719 | X53: =N53*Weight6/(WSum) -> 0.24561404 | Y53: =O53*Weight7/(WSum) -> 0.10526316 | Z53: =P53*Weight8/(WSum) -> 0.84210526 | AA53: =-1/10*G53+1 -> 0.8 | AB53: =IF(R53<0,0,-R53+1) -> 1 | AC53: =(AA53*CondWeight+AB53*PLifeWeight)/(CondWeight+PLifeWeight) -> 0.86666667 | AD53: =SUM(S53:Z53) -> 5.4210526 | AE53: =AD53*AC53*10 -> 46.982456 | AF53: Other | AI53: 260000 | AN53: =AI53*(1+Efactor) -> 269100
A54: 50 | B54: Fire Dept | C54: Building | D54: Fire Station #1, Newton Corner - Replace Emergency Generator | E54: Replace emergency electrical generator (30kW, 208Y/120V, 3-Phase, 4-Wire) and transfer switch which are at the end of their useful lives. | F54: 123000 | G54: 3 | H54: 0.1 | I54: 8 | J54: 4 | K54: 4 | L54: 9 | M54: 7 | N54: 6 | O54: 1 | P54: 8 | Q54: =(#REF!-(YEAR(TODAY())-#REF!))/#REF! -> #REF! | R54: =IFERROR(Q54,H54) -> 0.1 | S54: =I54*Weight1/(WSum) -> 1.2631579 | T54: =J54*Weight2/(WSum) -> 0.42105263 | U54: =K54*Weight3/(WSum) -> 0.56140351 | V54: =L54*Weight4/(WSum) -> 1.5789474 | W54: =M54*Weight5/(WSum) -> 0.61403509 | X54: =N54*Weight6/(WSum) -> 0.73684211 | Y54: =O54*Weight7/(WSum) -> 0.10526316 | Z54: =P54*Weight8/(WSum) -> 0.84210526 | AA54: =-1/10*G54+1 -> 0.7 | AB54: =IF(R54<0,0,-R54+1) -> 0.9 | AC54: =(AA54*CondWeight+AB54*PLifeWeight)/(CondWeight+PLifeWeight) -> 0.76666667 | AD54: =SUM(S54:Z54) -> 6.122807 | AE54: =AD54*AC54*10 -> 46.94152 | AF54: Bonding | AI54: 123000 | AN54: =AI54*(1+Efactor) -> 127305
A55: 51 | B55: DPW/ Sewer | C55: Sewer | D55: Quinobequin Road Sewer Pump Station - Replace Pump | E55: Sewerage pumped to higher point and gravity fed to MWRA pipes for treatment. Replace pump 1 and motors at life expectancy. | F55: 380000 | G55: 3 | H55: 0.2 | I55: 6 | J55: 8 | K55: 6 | L55: 8 | M55: 4 | N55: 6 | O55: 2 | P55: 10 | Q55: =(#REF!-(YEAR(TODAY())-#REF!))/#REF! -> #REF! | R55: =IFERROR(Q55,H55) -> 0.2 | S55: =I55*Weight1/(WSum) -> 0.94736842 | T55: =J55*Weight2/(WSum) -> 0.84210526 | U55: =K55*Weight3/(WSum) -> 0.84210526 | V55: =L55*Weight4/(WSum) -> 1.4035088 | W55: =M55*Weight5/(WSum) -> 0.35087719 | X55: =N55*Weight6/(WSum) -> 0.73684211 | Y55: =O55*Weight7/(WSum) -> 0.21052632 | Z55: =P55*Weight8/(WSum) -> 1.0526316 | AA55: =-1/10*G55+1 -> 0.7 | AB55: =IF(R55<0,0,-R55+1) -> 0.8 | AC55: =(AA55*CondWeight+AB55*PLifeWeight)/(CondWeight+PLifeWeight) -> 0.73333333 | AD55: =SUM(S55:Z55) -> 6.3859649 | AE55: =AD55*AC55*10 -> 46.830409 | AF55: Enterprise Funds | AH55: 120000 | AK55: 130000 | AL55: 130000 | AM55: =AH55 -> 120000 | AP55: =AK55*(1+Efactor)^3 -> 144133.32 | AQ55: =AL55*(1+Efactor)^4 -> 149177.99
A56: 52 | B56: DPW/ Water | C56: Large Vehicle/ Equipment | D56: Replace 2002 Construction Truck | E56: Replacement of existing city vehicle used for construction work on City water mains and for snow removal/sanding operations. Life span of vehicles is 15 yrs (#311). | F56: 130000 | G56: 3 | H56: 0.1 | I56: 6 | J56: 8 | K56: 6 | L56: 8 | M56: 4 | N56: 6 | O56: 1 | P56: 8 | Q56: =(#REF!-(YEAR(TODAY())-#REF!))/#REF! -> #REF! | R56: =IFERROR(Q56,H56) -> 0.1 | S56: =I56*Weight1/(WSum) -> 0.94736842 | T56: =J56*Weight2/(WSum) -> 0.84210526 | U56: =K56*Weight3/(WSum) -> 0.84210526 | V56: =L56*Weight4/(WSum) -> 1.4035088 | W56: =M56*Weight5/(WSum) -> 0.35087719 | X56: =N56*Weight6/(WSum) -> 0.73684211 | Y56: =O56*Weight7/(WSum) -> 0.10526316 | Z56: =P56*Weight8/(WSum) -> 0.84210526 | AA56: =-1/10*G56+1 -> 0.7 | AB56: =IF(R56<0,0,-R56+1) -> 0.9 | AC56: =(AA56*CondWeight+AB56*PLifeWeight)/(CondWeight+PLifeWeight) -> 0.76666667 | AD56: =SUM(S56:Z56) -> 6.0701754 | AE56: =AD56*AC56*10 -> 46.538012 | AF56: Enterprise Funds | AI56: 130000 | AN56: =AI56*(1+Efactor) -> 134550
A57: 53 | B57: DPW/ Storm | C57: Storm | D57: Cheesecake Brook Drainage Basin: Repair and Rebuild Retaining Wall | E57: Wall integrity is jeopardized. Project to minimize property damage due to flooding from heavy rains and compromised conveyance systems and minimize street flooding. First phase is survey. | F57: 300000 | G57: 2 | H57: 0 | I57: 4 | J57: 6 | K57: 4 | L57: 6 | M57: 8 | N57: 6 | O57: 0 | P57: 10 | Q57: =(#REF!-(YEAR(TODAY())-#REF!))/#REF! -> #REF! | R57: =IFERROR(Q57,H57) -> 0 | S57: =I57*Weight1/(WSum) -> 0.63157895 | T57: =J57*Weight2/(WSum) -> 0.63157895 | U57: =K57*Weight3/(WSum) -> 0.56140351 | V57: =L57*Weight4/(WSum) -> 1.0526316 | W57: =M57*Weight5/(WSum) -> 0.70175439 | X57: =N57*Weight6/(WSum) -> 0.73684211 | Y57: =O57*Weight7/(WSum) -> 0 | Z57: =P57*Weight8/(WSum) -> 1.0526316 | AA57: =-1/10*G57+1 -> 0.8 | AB57: =IF(R57<0,0,-R57+1) -> 1 | AC57: =(AA57*CondWeight+AB57*PLifeWeight)/(CondWeight+PLifeWeight) -> 0.86666667 | AD57: =SUM(S57:Z57) -> 5.3684211 | AE57: =AD57*AC57*10 -> 46.526316 | AF57: Enterprise Funds | AI57: 100000 | AN57: =AI57*(1+Efactor) -> 103500
A58: 54 | B58: DPW | C58: Large Vehicle/ Equipment | D58: DPW - Replace Large Construction Trucks | E58: Replace 2 vehicles taken out of service: Vehicle #73 and #40. Required for sanding fleet for snow and for construction work. | F58: 300000 | G58: 2 | H58: 0.2 | I58: 8 | J58: 8 | K58: 4 | L58: 8 | M58: 4 | N58: 6 | O58: 0 | P58: 6 | Q58: =(#REF!-(YEAR(TODAY())-#REF!))/#REF! -> #REF! | R58: =IFERROR(Q58,H58) -> 0.2 | S58: =I58*Weight1/(WSum) -> 1.2631579 | T58: =J58*Weight2/(WSum) -> 0.84210526 | U58: =K58*Weight3/(WSum) -> 0.56140351 | V58: =L58*Weight4/(WSum) -> 1.4035088 | W58: =M58*Weight5/(WSum) -> 0.35087719 | X58: =N58*Weight6/(WSum) -> 0.73684211 | Y58: =O58*Weight7/(WSum) -> 0 | Z58: =P58*Weight8/(WSum) -> 0.63157895 | AA58: =-1/10*G58+1 -> 0.8 | AB58: =IF(R58<0,0,-R58+1) -> 0.8 | AC58: =(AA58*CondWeight+AB58*PLifeWeight)/(CondWeight+PLifeWeight) -> 0.8 | AD58: =SUM(S58:Z58) -> 5.7894737 | AE58: =AD58*AC58*10 -> 46.315789 | AF58: Bonding | AI58: 300000 | AN58: =AI58*(1+Efactor) -> 310500
A59: 55 | B59: Parks/Rec | C59: Parks / Open Space | D59: Newton Centre Playground Phase V & Vi -Accessibility | E59: Add ADA compliant access route to a portion of Newton Centre Playground. Approved for CDBG funding by City Commission on Disability. | F59: 90000 | G59: 1 | H59: 0.1 | I59: 4 | J59: 9 | K59: 1 | L59: 8 | M59: 1 | N59: 8 | O59: 0 | P59: 9 | Q59: =(#REF!-(YEAR(TODAY())-#REF!))/#REF! -> #REF! | R59: =IFERROR(Q59,H59) -> 0.1 | S59: =I59*Weight1/(WSum) -> 0.63157895 | T59: =J59*Weight2/(WSum) -> 0.94736842 | U59: =K59*Weight3/(WSum) -> 0.14035088 | V59: =L59*Weight4/(WSum) -> 1.4035088 | W59: =M59*Weight5/(WSum) -> 0.087719298 | X59: =N59*Weight6/(WSum) -> 0.98245614 | Y59: =O59*Weight7/(WSum) -> 0 | Z59: =P59*Weight8/(WSum) -> 0.94736842 | AA59: =-1/10*G59+1 -> 0.9 | AB59: =IF(R59<0,0,-R59+1) -> 0.9 | AC59: =(AA59*CondWeight+AB59*PLifeWeight)/(CondWeight+PLifeWeight) -> 0.9 | AD59: =SUM(S59:Z59) -> 5.1403509 | AE59: =AD59*AC59*10 -> 46.263158 | AF59: CDBG Eligible | AH59: 45000 | AI59: 45000 | AM59: =AH59 -> 45000 | AN59: =AI59*(1+Efactor) -> 46575
A60: 56 | B60: Public Buildings | C60: Building | D60: City Hall - Plumbing and Accessiblity Improvements | E60: Upgrade toilet rooms for improved accessibility as required by code. | F60: 100000 | G60: 2 | H60: 0.1 | I60: 6 | J60: 8 | K60: 4 | L60: 7 | M60: 0 | N60: 8 | O60: 1 | P60: 8 | Q60: =(#REF!-(YEAR(TODAY())-#REF!))/#REF! -> #REF! | R60: =IFERROR(Q60,H60) -> 0.1 | S60: =I60*Weight1/(WSum) -> 0.94736842 | T60: =J60*Weight2/(WSum) -> 0.84210526 | U60: =K60*Weight3/(WSum) -> 0.56140351 | V60: =L60*Weight4/(WSum) -> 1.2280702 | W60: =M60*Weight5/(WSum) -> 0 | X60: =N60*Weight6/(WSum) -> 0.98245614 | Y60: =O60*Weight7/(WSum) -> 0.10526316 | Z60: =P60*Weight8/(WSum) -> 0.84210526 | AA60: =-1/10*G60+1 -> 0.8 | AB60: =IF(R60<0,0,-R60+1) -> 0.9 | AC60: =(AA60*CondWeight+AB60*PLifeWeight)/(CondWeight+PLifeWeight) -> 0.83333333 | AD60: =SUM(S60:Z60) -> 5.5087719 | AE60: =AD60*AC60*10 -> 45.906433 | AF60: Bonding | AI60: 100000 | AN60: =AI60*(1+Efactor) -> 103500
A61: 57 | B61: DPW | C61: Roads/ Paving | D61: Sidewalk Improvements | E61: Improve pedestrian safety. Repair/replacement of sidewalks in poor condition and new sidewalks in village centers, school zones, on major roads. | F61: 150000 | G61: 2 | H61: 0.1 | I61: 4 | J61: 6 | K61: 2 | L61: 8 | M61: 3 | N61: 10 | O61: 0 | P61: 10 | Q61: =(#REF!-(YEAR(TODAY())-#REF!))/#REF! -> #REF! | R61: =IFERROR(Q61,H61) -> 0.1 | S61: =I61*Weight1/(WSum) -> 0.63157895 | T61: =J61*Weight2/(WSum) -> 0.63157895 | U61: =K61*Weight3/(WSum) -> 0.28070175 | V61: =L61*Weight4/(WSum) -> 1.4035088 | W61: =M61*Weight5/(WSum) -> 0.26315789 | X61: =N61*Weight6/(WSum) -> 1.2280702 | Y61: =O61*Weight7/(WSum) -> 0 | Z61: =P61*Weight8/(WSum) -> 1.0526316 | AA61: =-1/10*G61+1 -> 0.8 | AB61: =IF(R61<0,0,-R61+1) -> 0.9 | AC61: =(AA61*CondWeight+AB61*PLifeWeight)/(CondWeight+PLifeWeight) -> 0.83333333 | AD61: =SUM(S61:Z61) -> 5.4912281 | AE61: =AD61*AC61*10 -> 45.760234 | AF61: Alternate Funding | AI61: 144928 | AN61: =AI61*(1+Efactor) -> 150000.48
A62: 58 | B62: DPW/ Sewer | C62: Large Vehicle/ Equipment | D62: Replace 1995 Sewer Jet Truck | E62: Replacement of vehicle/ equipment used to clear out blockages in the sewer system to prevent sewer backups. (#369). | F62: 240000 | G62: 3 | H62: 0 | I62: 6 | J62: 8 | K62: 5 | L62: 8 | M62: 4 | N62: 6 | O62: 0 | P62: 7 | Q62: =(#REF!-(YEAR(TODAY())-#REF!))/#REF! -> #REF! | R62: =IFERROR(Q62,H62) -> 0 | S62: =I62*Weight1/(WSum) -> 0.94736842 | T62: =J62*Weight2/(WSum) -> 0.84210526 | U62: =K62*Weight3/(WSum) -> 0.70175439 | V62: =L62*Weight4/(WSum) -> 1.4035088 | W62: =M62*Weight5/(WSum) -> 0.35087719 | X62: =N62*Weight6/(WSum) -> 0.73684211 | Y62: =O62*Weight7/(WSum) -> 0 | Z62: =P62*Weight8/(WSum) -> 0.73684211 | AA62: =-1/10*G62+1 -> 0.7 | AB62: =IF(R62<0,0,-R62+1) -> 1 | AC62: =(AA62*CondWeight+AB62*PLifeWeight)/(CondWeight+PLifeWeight) -> 0.8 | AD62: =SUM(S62:Z62) -> 5.7192982 | AE62: =AD62*AC62*10 -> 45.754386 | AF62: Enterprise Funds | AI62: 240000 | AN62: =AI62*(1+Efactor) -> 248400
A63: 59 | B63: DPW | C63: Roads/ Paving | D63: Traffic Light Improvements at Washingston Street Intersection (Waltham/Watertown Streets) | E63: Upgrade traffic signal and intersection on Washington St at Waltham/Watertown Sts to improve safety, visibility, and for ADA compliance. | F63: 75000 | G63: 3 | H63: 0.1 | I63: 8 | J63: 6 | K63: 2 | L63: 9 | M63: 5 | N63: 5 | O63: 1 | P63: 10 | Q63: =(#REF!-(YEAR(TODAY())-#REF!))/#REF! -> #REF! | R63: =IFERROR(Q63,H63) -> 0.1 | S63: =I63*Weight1/(WSum) -> 1.2631579 | T63: =J63*Weight2/(WSum) -> 0.63157895 | U63: =K63*Weight3/(WSum) -> 0.28070175 | V63: =L63*Weight4/(WSum) -> 1.5789474 | W63: =M63*Weight5/(WSum) -> 0.43859649 | X63: =N63*Weight6/(WSum) -> 0.61403509 | Y63: =O63*Weight7/(WSum) -> 0.10526316 | Z63: =P63*Weight8/(WSum) -> 1.0526316 | AA63: =-1/10*G63+1 -> 0.7 | AB63: =IF(R63<0,0,-R63+1) -> 0.9 | AC63: =(AA63*CondWeight+AB63*PLifeWeight)/(CondWeight+PLifeWeight) -> 0.76666667 | AD63: =SUM(S63:Z63) -> 5.9649123 | AE63: =AD63*AC63*10 -> 45.730994 | AF63: Chapt 90/ Alt Funds | AI63: 72464 | AN63: =AI63*(1+Efactor) -> 75000.24
A64: 60 | B64: Police | C64: Building | D64: Police Headquarters - Roof Repair/ Replacement | E64: Repair EPDM roof leaks. Repair copper cornice roof. Replace firing range roof. | F64: 83000 | G64: 2 | H64: 0.1 | I64: 8 | J64: 3 | K64: 6 | L64: 6 | M64: 8 | N64: 2 | O64: 2 | P64: 8 | Q64: =(#REF!-(YEAR(TODAY())-#REF!))/#REF! -> #REF! | R64: =IFERROR(Q64,H64) -> 0.1 | S64: =I64*Weight1/(WSum) -> 1.2631579 | T64: =J64*Weight2/(WSum) -> 0.31578947 | U64: =K64*Weight3/(WSum) -> 0.84210526 | V64: =L64*Weight4/(WSum) -> 1.0526316 | W64: =M64*Weight5/(WSum) -> 0.70175439 | X64: =N64*Weight6/(WSum) -> 0.24561404 | Y64: =O64*Weight7/(WSum) -> 0.21052632 | Z64: =P64*Weight8/(WSum) -> 0.84210526 | AA64: =-1/10*G64+1 -> 0.8 | AB64: =IF(R64<0,0,-R64+1) -> 0.9 | AC64: =(AA64*CondWeight+AB64*PLifeWeight)/(CondWeight+PLifeWeight) -> 0.83333333 | AD64: =SUM(S64:Z64) -> 5.4736842 | AE64: =AD64*AC64*10 -> 45.614035 | AF64: Bonding | AI64: 83000 | AN64: =AI64*(1+Efactor) -> 85905
A65: 61 | B65: DPW/ Storm | C65: Storm | D65: Repair Hammond St Drain | E65: Storm drain pipe has partially collapsed and requires repair to prevent flooding. | F65: 200000 | G65: 2 | H65: 0 | I65: 6 | J65: 6 | K65: 5 | L65: 6 | M65: 4 | N65: 6 | O65: 0 | P65: 8 | Q65: =(#REF!-(YEAR(TODAY())-#REF!))/#REF! -> #REF! | R65: =IFERROR(Q65,H65) -> 0 | S65: =I65*Weight1/(WSum) -> 0.94736842 | T65: =J65*Weight2/(WSum) -> 0.63157895 | U65: =K65*Weight3/(WSum) -> 0.70175439 | V65: =L65*Weight4/(WSum) -> 1.0526316 | W65: =M65*Weight5/(WSum) -> 0.35087719 | X65: =N65*Weight6/(WSum) -> 0.73684211 | Y65: =O65*Weight7/(WSum) -> 0 | Z65: =P65*Weight8/(WSum) -> 0.84210526 | AA65: =-1/10*G65+1 -> 0.8 | AB65: =IF(R65<0,0,-R65+1) -> 1 | AC65: =(AA65*CondWeight+AB65*PLifeWeight)/(CondWeight+PLifeWeight) -> 0.86666667 | AD65: =SUM(S65:Z65) -> 5.2631579 | AE65: =AD65*AC65*10 -> 45.614035 | AF65: Enterprise Funds | AI65: 200000 | AN65: =AI65*(1+Efactor) -> 207000
A66: 62 | B66: DPW/ Water | C66: Water | D66: Water Pump - Rebuild and Repair Dedham Street Water Pump | E66: Replace 60 hp pump in Fire Station #10; boosts water pressure in high areas of City. Pumps fill Oak Hill Tank. Coord w/construct. | F66: 100000 | G66: 2 | H66: 0.1 | I66: 6 | J66: 7 | K66: 3 | L66: 8 | M66: 2 | N66: 6 | O66: 0 | P66: 10 | Q66: =(#REF!-(YEAR(TODAY())-#REF!))/#REF! -> #REF! | R66: =IFERROR(Q66,H66) -> 0.1 | S66: =I66*Weight1/(WSum) -> 0.94736842 | T66: =J66*Weight2/(WSum) -> 0.73684211 | U66: =K66*Weight3/(WSum) -> 0.42105263 | V66: =L66*Weight4/(WSum) -> 1.4035088 | W66: =M66*Weight5/(WSum) -> 0.1754386 | X66: =N66*Weight6/(WSum) -> 0.73684211 | Y66: =O66*Weight7/(WSum) -> 0 | Z66: =P66*Weight8/(WSum) -> 1.0526316 | AA66: =-1/10*G66+1 -> 0.8 | AB66: =IF(R66<0,0,-R66+1) -> 0.9 | AC66: =(AA66*CondWeight+AB66*PLifeWeight)/(CondWeight+PLifeWeight) -> 0.83333333 | AD66: =SUM(S66:Z66) -> 5.4736842 | AE66: =AD66*AC66*10 -> 45.614035 | AF66: Enterprise Funds | AI66: 100000 | AN66: =AI66*(1+Efactor) -> 103500
A67: 63 | B67: DPW | C67: Roads/ Paving | D67: Street Paving - Cold Plane and Pave 21 Streets | E67: Streets include Vernon, Eldredge, Elmwood, Beacon, Pembroke, Durant, Hanson, Bishopsgate, Hammondswood, Monadnock, Otis, Adams, Circuit, Converse, Ruthven, Albemarle, Cottage Street | F67: 2796372 | G67: 3 | H67: 0.1 | I67: 8 | J67: 8 | K67: 2 | L67: 6 | M67: 4 | N67: 9 | O67: 0 | P67: 10 | Q67: =(#REF!-(YEAR(TODAY())-#REF!))/#REF! -> #REF! | R67: =IFERROR(Q67,H67) -> 0.1 | S67: =I67*Weight1/(WSum) -> 1.2631579 | T67: =J67*Weight2/(WSum) -> 0.84210526 | U67: =K67*Weight3/(WSum) -> 0.28070175 | V67: =L67*Weight4/(WSum) -> 1.0526316 | W67: =M67*Weight5/(WSum) -> 0.35087719 | X67: =N67*Weight6/(WSum) -> 1.1052632 | Y67: =O67*Weight7/(WSum) -> 0 | Z67: =P67*Weight8/(WSum) -> 1.0526316 | AA67: =-1/10*G67+1 -> 0.7 | AB67: =IF(R67<0,0,-R67+1) -> 0.9 | AC67: =(AA67*CondWeight+AB67*PLifeWeight)/(CondWeight+PLifeWeight) -> 0.76666667 | AD67: =SUM(S67:Z67) -> 5.9473684 | AE67: =AD67*AC67*10 -> 45.596491 | AF67: Chapt 90/ Alt Funds | AJ67: 2610443 | AO67: =AJ67*(1+Efactor)^2 -> 2796371.8
A68: 64 | B68: Public Buildings | C68: Building | D68: Energy Efficiency / Water Conservation Upgrades to City and School Buildings | E68: Project includes energy conservation measures at Countryside, Mem-Spauld and Peirce Schools and Ed Center thru NSTAR preferred vendor program. | F68: 1000000 | G68: 3 | H68: 0.2 | I68: 6 | J68: 8 | K68: 6 | L68: 4 | M68: 0 | N68: 8 | O68: 8 | P68: 10 | Q68: =(#REF!-(YEAR(TODAY())-#REF!))/#REF! -> #REF! | R68: =IFERROR(Q68,H68) -> 0.2 | S68: =I68*Weight1/(WSum) -> 0.94736842 | T68: =J68*Weight2/(WSum) -> 0.84210526 | U68: =K68*Weight3/(WSum) -> 0.84210526 | V68: =L68*Weight4/(WSum) -> 0.70175439 | W68: =M68*Weight5/(WSum) -> 0 | X68: =N68*Weight6/(WSum) -> 0.98245614 | Y68: =O68*Weight7/(WSum) -> 0.84210526 | Z68: =P68*Weight8/(WSum) -> 1.0526316 | AA68: =-1/10*G68+1 -> 0.7 | AB68: =IF(R68<0,0,-R68+1) -> 0.8 | AC68: =(AA68*CondWeight+AB68*PLifeWeight)/(CondWeight+PLifeWeight) -> 0.73333333 | AD68: =SUM(S68:Z68) -> 6.2105263 | AE68: =AD68*AC68*10 -> 45.54386 | AF68: Energy Stabilztn Fund | AJ68: 1000000 | AO68: =AJ68*(1+Efactor)^2 -> 1071225
A69: 65 | B69: DPW | C69: Roads/ Paving | D69: Sidewalk Improvements -Provide ADA Access Curb Cuts | E69: Provide appropriate curb cuts to comply with federal ADA requirements and to provide safe, accessible means to and from City sidewalks. | F69: 63500 | G69: 3 | H69: 0.1 | I69: 6 | J69: 8 | K69: 4 | L69: 8 | M69: 4 | N69: 8 | O69: 0 | P69: 8 | Q69: =(#REF!-(YEAR(TODAY())-#REF!))/#REF! -> #REF! | R69: =IFERROR(Q69,H69) -> 0.1 | S69: =I69*Weight1/(WSum) -> 0.94736842 | T69: =J69*Weight2/(WSum) -> 0.84210526 | U69: =K69*Weight3/(WSum) -> 0.56140351 | V69: =L69*Weight4/(WSum) -> 1.4035088 | W69: =M69*Weight5/(WSum) -> 0.35087719 | X69: =N69*Weight6/(WSum) -> 0.98245614 | Y69: =O69*Weight7/(WSum) -> 0 | Z69: =P69*Weight8/(WSum) -> 0.84210526 | AA69: =-1/10*G69+1 -> 0.7 | AB69: =IF(R69<0,0,-R69+1) -> 0.9 | AC69: =(AA69*CondWeight+AB69*PLifeWeight)/(CondWeight+PLifeWeight) -> 0.76666667 | AD69: =SUM(S69:Z69) -> 5.9298246 | AE69: =AD69*AC69*10 -> 45.461988 | AF69: CDBG Eligible | AI69: 63500 | AN69: =AI69*(1+Efactor) -> 65722.5
A70: 66 | B70: Fire Dept | C70: Large Vehicle/ Equipment | D70: Replace Fire Dept Pumper Truck (Engine 1) | E70: Replace Engine 1.1999 Pumper Truck which will exceed life expectancy in 2014, and replace spare engine (1992) that should no longer be used | F70: 600000 | G70: 3 | H70: 0.3 | I70: 7 | J70: 7 | K70: 3 | L70: 10 | M70: 5 | N70: 8 | O70: 0 | P70: 10 | Q70: =(#REF!-(YEAR(TODAY())-#REF!))/#REF! -> #REF! | R70: =IFERROR(Q70,H70) -> 0.3 | S70: =I70*Weight1/(WSum) -> 1.1052632 | T70: =J70*Weight2/(WSum) -> 0.73684211 | U70: =K70*Weight3/(WSum) -> 0.42105263 | V70: =L70*Weight4/(WSum) -> 1.754386 | W70: =M70*Weight5/(WSum) -> 0.43859649 | X70: =N70*Weight6/(WSum) -> 0.98245614 | Y70: =O70*Weight7/(WSum) -> 0 | Z70: =P70*Weight8/(WSum) -> 1.0526316 | AA70: =-1/10*G70+1 -> 0.7 | AB70: =IF(R70<0,0,-R70+1) -> 0.7 | AC70: =(AA70*CondWeight+AB70*PLifeWeight)/(CondWeight+PLifeWeight) -> 0.7 | AD70: =SUM(S70:Z70) -> 6.4912281 | AE70: =AD70*AC70*10 -> 45.438596 | AF70: Bonding | AJ70: 600000 | AO70: =AJ70*(1+Efactor)^2 -> 642735
A71: 67 | B71: Public Buildings | C71: Building | D71: Replace Underground Storage Tanks at City Buildings | E71: Replace fuel tanks at DPW Crafts Street Operations Center, Cabot Pk Fieldhouse, and DPW Elliot Street Operations Center. Tanks are beyond useful life. | F71: 100000 | G71: 2 | H71: 0.1 | I71: 5 | J71: 6 | K71: 5 | L71: 9 | M71: 5 | N71: 2 | O71: 2 | P71: 8 | Q71: =(#REF!-(YEAR(TODAY())-#REF!))/#REF! -> #REF! | R71: =IFERROR(Q71,H71) -> 0.1 | S71: =I71*Weight1/(WSum) -> 0.78947368 | T71: =J71*Weight2/(WSum) -> 0.63157895 | U71: =K71*Weight3/(WSum) -> 0.70175439 | V71: =L71*Weight4/(WSum) -> 1.5789474 | W71: =M71*Weight5/(WSum) -> 0.43859649 | X71: =N71*Weight6/(WSum) -> 0.24561404 | Y71: =O71*Weight7/(WSum) -> 0.21052632 | Z71: =P71*Weight8/(WSum) -> 0.84210526 | AA71: =-1/10*G71+1 -> 0.8 | AB71: =IF(R71<0,0,-R71+1) -> 0.9 | AC71: =(AA71*CondWeight+AB71*PLifeWeight)/(CondWeight+PLifeWeight) -> 0.83333333 | AD71: =SUM(S71:Z71) -> 5.4385965 | AE71: =AD71*AC71*10 -> 45.321637 | AF71: Bonding | AJ71: 100000 | AO71: =AJ71*(1+Efactor)^2 -> 107122.5
A72: 68 | B72: DPW/ Water | C72: Water | D72: Clean and Line Water Pipes to Improve Water Quality | E72: Cleaning and lining of water pipes to improve water quality, ensure pipe integrity and capacity. Precedes scheduled roadway paving. | F72: 4034180 | G72: 3 | H72: 0.3 | I72: 6 | J72: 6 | K72: 7 | L72: 8 | M72: 5 | N72: 8 | O72: 0 | P72: 10 | Q72: =(#REF!-(YEAR(TODAY())-#REF!))/#REF! -> #REF! | R72: =IFERROR(Q72,H72) -> 0.3 | S72: =I72*Weight1/(WSum) -> 0.94736842 | T72: =J72*Weight2/(WSum) -> 0.63157895 | U72: =K72*Weight3/(WSum) -> 0.98245614 | V72: =L72*Weight4/(WSum) -> 1.4035088 | W72: =M72*Weight5/(WSum) -> 0.43859649 | X72: =N72*Weight6/(WSum) -> 0.98245614 | Y72: =O72*Weight7/(WSum) -> 0 | Z72: =P72*Weight8/(WSum) -> 1.0526316 | AA72: =-1/10*G72+1 -> 0.7 | AB72: =IF(R72<0,0,-R72+1) -> 0.7 | AC72: =(AA72*CondWeight+AB72*PLifeWeight)/(CondWeight+PLifeWeight) -> 0.7 | AD72: =SUM(S72:Z72) -> 6.4385965 | AE72: =AD72*AC72*10 -> 45.070175 | AF72: Enterprise Funds | AJ72: 4034180 | AO72: =AJ72*(1+Efactor)^2 -> 4321514.5
A73: 69 | B73: Schools | C73: Building | D73: Ed Center - Electrical Upgrades | E73: Upgrade electric service, panels and sub-panels to support IT server room and other building functions. | F73: 225000 | G73: 2 | H73: 0.1 | I73: 8 | J73: 8 | K73: 2 | L73: 8 | M73: 5 | N73: 4 | O73: 0 | P73: 6 | Q73: =(#REF!-(YEAR(TODAY())-#REF!))/#REF! -> #REF! | R73: =IFERROR(Q73,H73) -> 0.1 | S73: =I73*Weight1/(WSum) -> 1.2631579 | T73: =J73*Weight2/(WSum) -> 0.84210526 | U73: =K73*Weight3/(WSum) -> 0.28070175 | V73: =L73*Weight4/(WSum) -> 1.4035088 | W73: =M73*Weight5/(WSum) -> 0.43859649 | X73: =N73*Weight6/(WSum) -> 0.49122807 | Y73: =O73*Weight7/(WSum) -> 0 | Z73: =P73*Weight8/(WSum) -> 0.63157895 | AA73: =-1/10*G73+1 -> 0.8 | AB73: =IF(R73<0,0,-R73+1) -> 0.9 | AC73: =(AA73*CondWeight+AB73*PLifeWeight)/(CondWeight+PLifeWeight) -> 0.83333333 | AD73: =SUM(S73:Z73) -> 5.3508772 | AE73: =AD73*AC73*10 -> 44.590643 | AF73: Bonding | AJ73: 225000 | AO73: =AJ73*(1+Efactor)^2 -> 241025.62
A74: 70 | B74: DPW | C74: Roads/ Paving | D74: Streetlights - Convert to Energy Efficient Fixtures (LED) | E74: Convert 140 existing high pressure sodium Rte 9 streetlights to LED lights to reduce City's carbon footprint and annual electricity budget. | F74: 100000 | G74: 3 | H74: 0 | I74: 5 | J74: 4 | K74: 8 | L74: 4 | M74: 0 | N74: 5 | O74: 8 | P74: 10 | Q74: =(#REF!-(YEAR(TODAY())-#REF!))/#REF! -> #REF! | R74: =IFERROR(Q74,H74) -> 0 | S74: =I74*Weight1/(WSum) -> 0.78947368 | T74: =J74*Weight2/(WSum) -> 0.42105263 | U74: =K74*Weight3/(WSum) -> 1.122807 | V74: =L74*Weight4/(WSum) -> 0.70175439 | W74: =M74*Weight5/(WSum) -> 0 | X74: =N74*Weight6/(WSum) -> 0.61403509 | Y74: =O74*Weight7/(WSum) -> 0.84210526 | Z74: =P74*Weight8/(WSum) -> 1.0526316 | AA74: =-1/10*G74+1 -> 0.7 | AB74: =IF(R74<0,0,-R74+1) -> 1 | AC74: =(AA74*CondWeight+AB74*PLifeWeight)/(CondWeight+PLifeWeight) -> 0.8 | AD74: =SUM(S74:Z74) -> 5.5438596 | AE74: =AD74*AC74*10 -> 44.350877 | AF74: Chapt 90/ Alt Funds | AH74: 50000 | AJ74: 46676 | AM74: =AH74 -> 50000 | AO74: =AJ74*(1+Efactor)^2 -> 50000.498
A75: 71 | B75: DPW/ Sewer | C75: Sewer | D75: Sewer Inflow /Infiltration Project - Newton Centre | E75: Part of 12 yr $49.1 M program to remove excess inflow and infiltration into sewer system. Design (FY16) and constr (FY17) for Newton Centre area. | F75: 3958875 | G75: 4 | H75: 0.3 | I75: 8 | J75: 8 | K75: 8 | L75: 8 | M75: 5 | N75: 8 | O75: 0 | P75: 9 | Q75: =(#REF!-(YEAR(TODAY())-#REF!))/#REF! -> #REF! | R75: =IFERROR(Q75,H75) -> 0.3 | S75: =I75*Weight1/(WSum) -> 1.2631579 | T75: =J75*Weight2/(WSum) -> 0.84210526 | U75: =K75*Weight3/(WSum) -> 1.122807 | V75: =L75*Weight4/(WSum) -> 1.4035088 | W75: =M75*Weight5/(WSum) -> 0.43859649 | X75: =N75*Weight6/(WSum) -> 0.98245614 | Y75: =O75*Weight7/(WSum) -> 0 | Z75: =P75*Weight8/(WSum) -> 0.94736842 | AA75: =-1/10*G75+1 -> 0.6 | AB75: =IF(R75<0,0,-R75+1) -> 0.7 | AC75: =(AA75*CondWeight+AB75*PLifeWeight)/(CondWeight+PLifeWeight) -> 0.63333333 | AD75: =SUM(S75:Z75) -> 7 | AE75: =AD75*AC75*10 -> 44.333333 | AF75: Enterprise Funds | AJ75: 569250 | AK75: 3389625 | AO75: =AJ75*(1+Efactor)^2 -> 609794.83 | AP75: =AK75*(1+Efactor)^3 -> 3758137.8
A76: 72 | B76: Schools | C76: Building | D76: Ed Center - Exterior Masonry Work | E76: Repair, repoint and clean exterior masonry. This is Phase II of work begun in FY13. | F76: 400000 | G76: 2 | H76: 0 | I76: 6 | J76: 8 | K76: 5 | L76: 4 | M76: 6 | N76: 6 | O76: 0 | P76: 6 | Q76: =(#REF!-(YEAR(TODAY())-#REF!))/#REF! -> #REF! | R76: =IFERROR(Q76,H76) -> 0 | S76: =I76*Weight1/(WSum) -> 0.94736842 | T76: =J76*Weight2/(WSum) -> 0.84210526 | U76: =K76*Weight3/(WSum) -> 0.70175439 | V76: =L76*Weight4/(WSum) -> 0.70175439 | W76: =M76*Weight5/(WSum) -> 0.52631579 | X76: =N76*Weight6/(WSum) -> 0.73684211 | Y76: =O76*Weight7/(WSum) -> 0 | Z76: =P76*Weight8/(WSum) -> 0.63157895 | AA76: =-1/10*G76+1 -> 0.8 | AB76: =IF(R76<0,0,-R76+1) -> 1 | AC76: =(AA76*CondWeight+AB76*PLifeWeight)/(CondWeight+PLifeWeight) -> 0.86666667 | AD76: =SUM(S76:Z76) -> 5.0877193 | AE76: =AD76*AC76*10 -> 44.093567 | AF76: Bonding | AJ76: 100000 | AO76: =AJ76*(1+Efactor)^2 -> 107122.5
A77: 73 | B77: Public Buildings | C77: Building | D77: City Hall - Envelope - Masonry Repairs | E77: On-going program to repair and repoint exterior masonry to preserve building envelope. Address worst areas first. | F77: 425000 | G77: 3 | H77: 0.3 | I77: 8 | J77: 6 | K77: 6 | L77: 6 | M77: 8 | N77: 6 | O77: 2 | P77: 8 | Q77: =(#REF!-(YEAR(TODAY())-#REF!))/#REF! -> #REF! | R77: =IFERROR(Q77,H77) -> 0.3 | S77: =I77*Weight1/(WSum) -> 1.2631579 | T77: =J77*Weight2/(WSum) -> 0.63157895 | U77: =K77*Weight3/(WSum) -> 0.84210526 | V77: =L77*Weight4/(WSum) -> 1.0526316 | W77: =M77*Weight5/(WSum) -> 0.70175439 | X77: =N77*Weight6/(WSum) -> 0.73684211 | Y77: =O77*Weight7/(WSum) -> 0.21052632 | Z77: =P77*Weight8/(WSum) -> 0.84210526 | AA77: =-1/10*G77+1 -> 0.7 | AB77: =IF(R77<0,0,-R77+1) -> 0.7 | AC77: =(AA77*CondWeight+AB77*PLifeWeight)/(CondWeight+PLifeWeight) -> 0.7 | AD77: =SUM(S77:Z77) -> 6.2807018 | AE77: =AD77*AC77*10 -> 43.964912 | AF77: Bonding | AJ77: 125000 | AO77: =AJ77*(1+Efactor)^2 -> 133903.12
A78: 74 | B78: Fire Dept | C78: Building | D78: Fire Station #1, Newton Corner - Replace Tanks | E78: Remove diesel and heating oil tanks, replace with tanks from Countryside Schl. Abate room. Gas conversion and and other mech. work in future renovation work. | F78: 75000 | G78: 3 | H78: 0.1 | I78: 5 | J78: 5 | K78: 9 | L78: 4 | M78: 5 | N78: 6 | O78: 6 | P78: 6 | Q78: =(#REF!-(YEAR(TODAY())-#REF!))/#REF! -> #REF! | R78: =IFERROR(Q78,H78) -> 0.1 | S78: =I78*Weight1/(WSum) -> 0.78947368 | T78: =J78*Weight2/(WSum) -> 0.52631579 | U78: =K78*Weight3/(WSum) -> 1.2631579 | V78: =L78*Weight4/(WSum) -> 0.70175439 | W78: =M78*Weight5/(WSum) -> 0.43859649 | X78: =N78*Weight6/(WSum) -> 0.73684211 | Y78: =O78*Weight7/(WSum) -> 0.63157895 | Z78: =P78*Weight8/(WSum) -> 0.63157895 | AA78: =-1/10*G78+1 -> 0.7 | AB78: =IF(R78<0,0,-R78+1) -> 0.9 | AC78: =(AA78*CondWeight+AB78*PLifeWeight)/(CondWeight+PLifeWeight) -> 0.76666667 | AD78: =SUM(S78:Z78) -> 5.7192982 | AE78: =AD78*AC78*10 -> 43.847953 | AF78: Bonding | AJ78: 75000 | AO78: =AJ78*(1+Efactor)^2 -> 80341.875
A79: 75 | B79: Schools | C79: Building | D79: FA Day School - Replace Boilers | E79: Replace two 60 year old boilers and variable air volume (VAV) coil work. | F79: 450000 | G79: 3 | H79: 0 | I79: 6 | J79: 8 | K79: 5 | L79: 4 | M79: 2 | N79: 6 | O79: 5 | P79: 8 | Q79: =(#REF!-(YEAR(TODAY())-#REF!))/#REF! -> #REF! | R79: =IFERROR(Q79,H79) -> 0 | S79: =I79*Weight1/(WSum) -> 0.94736842 | T79: =J79*Weight2/(WSum) -> 0.84210526 | U79: =K79*Weight3/(WSum) -> 0.70175439 | V79: =L79*Weight4/(WSum) -> 0.70175439 | W79: =M79*Weight5/(WSum) -> 0.1754386 | X79: =N79*Weight6/(WSum) -> 0.73684211 | Y79: =O79*Weight7/(WSum) -> 0.52631579 | Z79: =P79*Weight8/(WSum) -> 0.84210526 | AA79: =-1/10*G79+1 -> 0.7 | AB79: =IF(R79<0,0,-R79+1) -> 1 | AC79: =(AA79*CondWeight+AB79*PLifeWeight)/(CondWeight+PLifeWeight) -> 0.8 | AD79: =SUM(S79:Z79) -> 5.4736842 | AE79: =AD79*AC79*10 -> 43.789474 | AF79: Bonding | AJ79: 100000 | AK79: 350000 | AO79: =AJ79*(1+Efactor)^2 -> 107122.5 | AP79: =AK79*(1+Efactor)^3 -> 388051.26
A80: 76 | B80: DPW | C80: Large Vehicle/ Equipment | D80: DPW - Replace 1985 Excavator | E80: Replacement of existing city vehicle/ equipment used for street & sidewalk repairs. (#110) Beyond usefull life expectancy. | F80: 270000 | G80: 2 | H80: 0.2 | I80: 6 | J80: 7 | K80: 6 | L80: 7 | M80: 3 | N80: 5 | O80: 0 | P80: 8 | Q80: =(#REF!-(YEAR(TODAY())-#REF!))/#REF! -> #REF! | R80: =IFERROR(Q80,H80) -> 0.2 | S80: =I80*Weight1/(WSum) -> 0.94736842 | T80: =J80*Weight2/(WSum) -> 0.73684211 | U80: =K80*Weight3/(WSum) -> 0.84210526 | V80: =L80*Weight4/(WSum) -> 1.2280702 | W80: =M80*Weight5/(WSum) -> 0.26315789 | X80: =N80*Weight6/(WSum) -> 0.61403509 | Y80: =O80*Weight7/(WSum) -> 0 | Z80: =P80*Weight8/(WSum) -> 0.84210526 | AA80: =-1/10*G80+1 -> 0.8 | AB80: =IF(R80<0,0,-R80+1) -> 0.8 | AC80: =(AA80*CondWeight+AB80*PLifeWeight)/(CondWeight+PLifeWeight) -> 0.8 | AD80: =SUM(S80:Z80) -> 5.4736842 | AE80: =AD80*AC80*10 -> 43.789474 | AF80: Bonding | AJ80: 270000 | AO80: =AJ80*(1+Efactor)^2 -> 289230.75
A81: 77 | B81: DPW | C81: Roads/ Paving | D81: Replace Gath/Albemarle Foot Bridge | E81: Footbridge is in poor condition and is not wheelchair accessible. Footbridge is part of evacuation route for Day MS. | F81: 150000 | G81: 1 | H81: 0.1 | I81: 5 | J81: 6 | K81: 0 | L81: 8 | M81: 0 | N81: 8 | O81: 0 | P81: 10 | Q81: =(#REF!-(YEAR(TODAY())-#REF!))/#REF! -> #REF! | R81: =IFERROR(Q81,H81) -> 0.1 | S81: =I81*Weight1/(WSum) -> 0.78947368 | T81: =J81*Weight2/(WSum) -> 0.63157895 | U81: =K81*Weight3/(WSum) -> 0 | V81: =L81*Weight4/(WSum) -> 1.4035088 | W81: =M81*Weight5/(WSum) -> 0 | X81: =N81*Weight6/(WSum) -> 0.98245614 | Y81: =O81*Weight7/(WSum) -> 0 | Z81: =P81*Weight8/(WSum) -> 1.0526316 | AA81: =-1/10*G81+1 -> 0.9 | AB81: =IF(R81<0,0,-R81+1) -> 0.9 | AC81: =(AA81*CondWeight+AB81*PLifeWeight)/(CondWeight+PLifeWeight) -> 0.9 | AD81: =SUM(S81:Z81) -> 4.8596491 | AE81: =AD81*AC81*10 -> 43.736842 | AF81: CDBG Eligible | AJ81: 150000 | AO81: =AJ81*(1+Efactor)^2 -> 160683.75
A82: 78 | B82: DPW/ Sewer | C82: Sewer | D82: Prairie Avenue Sewer Pump Station | E82: Station built 1950, rehabbed in 1992. Contains 2 (5 hp) pumps. Replace wet well. | F82: 100000 | G82: 3 | H82: 0.1 | I82: 6 | J82: 8 | K82: 6 | L82: 8 | M82: 1 | N82: 6 | O82: 0 | P82: 8 | Q82: =(#REF!-(YEAR(TODAY())-#REF!))/#REF! -> #REF! | R82: =IFERROR(Q82,H82) -> 0.1 | S82: =I82*Weight1/(WSum) -> 0.94736842 | T82: =J82*Weight2/(WSum) -> 0.84210526 | U82: =K82*Weight3/(WSum) -> 0.84210526 | V82: =L82*Weight4/(WSum) -> 1.4035088 | W82: =M82*Weight5/(WSum) -> 0.087719298 | X82: =N82*Weight6/(WSum) -> 0.73684211 | Y82: =O82*Weight7/(WSum) -> 0 | Z82: =P82*Weight8/(WSum) -> 0.84210526 | AA82: =-1/10*G82+1 -> 0.7 | AB82: =IF(R82<0,0,-R82+1) -> 0.9 | AC82: =(AA82*CondWeight+AB82*PLifeWeight)/(CondWeight+PLifeWeight) -> 0.76666667 | AD82: =SUM(S82:Z82) -> 5.7017544 | AE82: =AD82*AC82*10 -> 43.71345 | AF82: Enterprise Funds | AJ82: 100000 | AO82: =AJ82*(1+Efactor)^2 -> 107122.5
A83: 79 | B83: Public Buildings | C83: Building | D83: City Hall - Mechanical Upgrades | E83: Replace condensing units. Replace and insulate ductwork and replace fans. Add mini-split A/C units in conjunction with window restoration /replacement ($100K). | F83: 425000 | G83: 3 | H83: 0.1 | I83: 7 | J83: 6 | K83: 6 | L83: 5 | M83: 4 | N83: 6 | O83: 4 | P83: 7 | Q83: =(#REF!-(YEAR(TODAY())-#REF!))/#REF! -> #REF! | R83: =IFERROR(Q83,H83) -> 0.1 | S83: =I83*Weight1/(WSum) -> 1.1052632 | T83: =J83*Weight2/(WSum) -> 0.63157895 | U83: =K83*Weight3/(WSum) -> 0.84210526 | V83: =L83*Weight4/(WSum) -> 0.87719298 | W83: =M83*Weight5/(WSum) -> 0.35087719 | X83: =N83*Weight6/(WSum) -> 0.73684211 | Y83: =O83*Weight7/(WSum) -> 0.42105263 | Z83: =P83*Weight8/(WSum) -> 0.73684211 | AA83: =-1/10*G83+1 -> 0.7 | AB83: =IF(R83<0,0,-R83+1) -> 0.9 | AC83: =(AA83*CondWeight+AB83*PLifeWeight)/(CondWeight+PLifeWeight) -> 0.76666667 | AD83: =SUM(S83:Z83) -> 5.7017544 | AE83: =AD83*AC83*10 -> 43.71345 | AF83: Bonding | AG83: 50000 | AJ83: 250000 | AK83: 125000 | AO83: =AJ83*(1+Efactor)^2 -> 267806.25 | AP83: =AK83*(1+Efactor)^3 -> 138589.73
A84: 80 | B84: Parks/Rec | C84: Building | D84: Pelligrini Park Field House - Mechanical Upgrades | E84: Replace boiler, remove underground storage tank. Convert to gas, provide new heating controls, fans and heaters in future. | F84: 250000 | G84: 2 | H84: 0.1 | I84: 6 | J84: 8 | K84: 4 | L84: 4 | M84: 2 | N84: 6 | O84: 4 | P84: 8 | Q84: =(#REF!-(YEAR(TODAY())-#REF!))/#REF! -> #REF! | R84: =IFERROR(Q84,H84) -> 0.1 | S84: =I84*Weight1/(WSum) -> 0.94736842 | T84: =J84*Weight2/(WSum) -> 0.84210526 | U84: =K84*Weight3/(WSum) -> 0.56140351 | V84: =L84*Weight4/(WSum) -> 0.70175439 | W84: =M84*Weight5/(WSum) -> 0.1754386 | X84: =N84*Weight6/(WSum) -> 0.73684211 | Y84: =O84*Weight7/(WSum) -> 0.42105263 | Z84: =P84*Weight8/(WSum) -> 0.84210526 | AA84: =-1/10*G84+1 -> 0.8 | AB84: =IF(R84<0,0,-R84+1) -> 0.9 | AC84: =(AA84*CondWeight+AB84*PLifeWeight)/(CondWeight+PLifeWeight) -> 0.83333333 | AD84: =SUM(S84:Z84) -> 5.2280702 | AE84: =AD84*AC84*10 -> 43.567251 | AF84: Bonding | AJ84: 150000 | AO84: =AJ84*(1+Efactor)^2 -> 160683.75
A85: 81 | B85: Schools | C85: Building | D85: Horace Mann School - Replace Roof | E85: Replace Total Building 1986 Built up roof area. Roof has reached its life expectancy. | F85: 375000 | G85: 3 | H85: 0 | I85: 6 | J85: 8 | K85: 4 | L85: 4 | M85: 6 | N85: 4 | O85: 5 | P85: 8 | Q85: =(#REF!-(YEAR(TODAY())-#REF!))/#REF! -> #REF! | R85: =IFERROR(Q85,H85) -> 0 | S85: =I85*Weight1/(WSum) -> 0.94736842 | T85: =J85*Weight2/(WSum) -> 0.84210526 | U85: =K85*Weight3/(WSum) -> 0.56140351 | V85: =L85*Weight4/(WSum) -> 0.70175439 | W85: =M85*Weight5/(WSum) -> 0.52631579 | X85: =N85*Weight6/(WSum) -> 0.49122807 | Y85: =O85*Weight7/(WSum) -> 0.52631579 | Z85: =P85*Weight8/(WSum) -> 0.84210526 | AA85: =-1/10*G85+1 -> 0.7 | AB85: =IF(R85<0,0,-R85+1) -> 1 | AC85: =(AA85*CondWeight+AB85*PLifeWeight)/(CondWeight+PLifeWeight) -> 0.8 | AD85: =SUM(S85:Z85) -> 5.4385965 | AE85: =AD85*AC85*10 -> 43.508772 | AF85: Bonding | AJ85: 375000 | AO85: =AJ85*(1+Efactor)^2 -> 401709.37
A86: 82 | B86: DPW | C86: Roads/ Paving | D86: Sidewalk Improvements -Provide ADA Access Curb Cuts | E86: Provide appropriate curb cuts to comply with federal ADA requirements and to provide safe, accessible means to and from City sidewalks. | F86: 63500 | G86: 3 | H86: 0.2 | I86: 6 | J86: 8 | K86: 4 | L86: 8 | M86: 4 | N86: 8 | O86: 0 | P86: 8 | Q86: =(#REF!-(YEAR(TODAY())-#REF!))/#REF! -> #REF! | R86: =IFERROR(Q86,H86) -> 0.2 | S86: =I86*Weight1/(WSum) -> 0.94736842 | T86: =J86*Weight2/(WSum) -> 0.84210526 | U86: =K86*Weight3/(WSum) -> 0.56140351 | V86: =L86*Weight4/(WSum) -> 1.4035088 | W86: =M86*Weight5/(WSum) -> 0.35087719 | X86: =N86*Weight6/(WSum) -> 0.98245614 | Y86: =O86*Weight7/(WSum) -> 0 | Z86: =P86*Weight8/(WSum) -> 0.84210526 | AA86: =-1/10*G86+1 -> 0.7 | AB86: =IF(R86<0,0,-R86+1) -> 0.8 | AC86: =(AA86*CondWeight+AB86*PLifeWeight)/(CondWeight+PLifeWeight) -> 0.73333333 | AD86: =SUM(S86:Z86) -> 5.9298246 | AE86: =AD86*AC86*10 -> 43.48538 | AF86: CDBG Eligible | AK86: 63500 | AP86: =AK86*(1+Efactor)^3 -> 70403.585
A87: 83 | B87: Schools | C87: Building | D87: Remove Underground Tanks at Various Schools | E87: Remove underground tanks which are no longer needed at Lincoln-Eliot, Pierce, and Franklin Elementary Schools. | F87: 280000 | G87: 2 | H87: 0.2 | I87: 5 | J87: 6 | K87: 5 | L87: 10 | M87: 4 | N87: 2 | O87: 1 | P87: 8 | Q87: =(#REF!-(YEAR(TODAY())-#REF!))/#REF! -> #REF! | R87: =IFERROR(Q87,H87) -> 0.2 | S87: =I87*Weight1/(WSum) -> 0.78947368 | T87: =J87*Weight2/(WSum) -> 0.63157895 | U87: =K87*Weight3/(WSum) -> 0.70175439 | V87: =L87*Weight4/(WSum) -> 1.754386 | W87: =M87*Weight5/(WSum) -> 0.35087719 | X87: =N87*Weight6/(WSum) -> 0.24561404 | Y87: =O87*Weight7/(WSum) -> 0.10526316 | Z87: =P87*Weight8/(WSum) -> 0.84210526 | AA87: =-1/10*G87+1 -> 0.8 | AB87: =IF(R87<0,0,-R87+1) -> 0.8 | AC87: =(AA87*CondWeight+AB87*PLifeWeight)/(CondWeight+PLifeWeight) -> 0.8 | AD87: =SUM(S87:Z87) -> 5.4210526 | AE87: =AD87*AC87*10 -> 43.368421 | AF87: Other | AJ87: 280000 | AO87: =AJ87*(1+Efactor)^2 -> 299943
A88: 84 | B88: Public Buildings | C88: Building | D88: City Hall - Exterior Windows & Doors | E88: Restore/Replace windows in phases to improve energy efficiency, functionality and comfort, and to preserve exterior wall. | F88: 1000000 | G88: 3 | H88: 0.1 | I88: 6 | J88: 5 | K88: 4 | L88: 4 | M88: 8 | N88: 5 | O88: 6 | P88: 8 | Q88: =(#REF!-(YEAR(TODAY())-#REF!))/#REF! -> #REF! | R88: =IFERROR(Q88,H88) -> 0.1 | S88: =I88*Weight1/(WSum) -> 0.94736842 | T88: =J88*Weight2/(WSum) -> 0.52631579 | U88: =K88*Weight3/(WSum) -> 0.56140351 | V88: =L88*Weight4/(WSum) -> 0.70175439 | W88: =M88*Weight5/(WSum) -> 0.70175439 | X88: =N88*Weight6/(WSum) -> 0.61403509 | Y88: =O88*Weight7/(WSum) -> 0.63157895 | Z88: =P88*Weight8/(WSum) -> 0.84210526 | AA88: =-1/10*G88+1 -> 0.7 | AB88: =IF(R88<0,0,-R88+1) -> 0.9 | AC88: =(AA88*CondWeight+AB88*PLifeWeight)/(CondWeight+PLifeWeight) -> 0.76666667 | AD88: =SUM(S88:Z88) -> 5.5263158 | AE88: =AD88*AC88*10 -> 42.368421 | AF88: CPA Eligible | AI88: 500000 | AJ88: 500000 | AN88: =AI88*(1+Efactor) -> 517500 | AO88: =AJ88*(1+Efactor)^2 -> 535612.5
A89: 85 | B89: DPW | C89: Roads/ Paving | D89: Traffic Light Improvements at Beacon Street and Langley Road Intersection | E89: Upgrade traffic signal and intersection at Beacon St. and Langley Rd to improve safety and visibility, and for ADA compliance. | F89: 75000 | G89: 3 | H89: 0.3 | I89: 8 | J89: 5 | K89: 3 | L89: 9 | M89: 5 | N89: 5 | O89: 1 | P89: 10 | Q89: =(#REF!-(YEAR(TODAY())-#REF!))/#REF! -> #REF! | R89: =IFERROR(Q89,H89) -> 0.3 | S89: =I89*Weight1/(WSum) -> 1.2631579 | T89: =J89*Weight2/(WSum) -> 0.52631579 | U89: =K89*Weight3/(WSum) -> 0.42105263 | V89: =L89*Weight4/(WSum) -> 1.5789474 | W89: =M89*Weight5/(WSum) -> 0.43859649 | X89: =N89*Weight6/(WSum) -> 0.61403509 | Y89: =O89*Weight7/(WSum) -> 0.10526316 | Z89: =P89*Weight8/(WSum) -> 1.0526316 | AA89: =-1/10*G89+1 -> 0.7 | AB89: =IF(R89<0,0,-R89+1) -> 0.7 | AC89: =(AA89*CondWeight+AB89*PLifeWeight)/(CondWeight+PLifeWeight) -> 0.7 | AD89: =SUM(S89:Z89) -> 6 | AE89: =AD89*AC89*10 -> 42 | AF89: Chapt 90/ Alt Funds | AJ89: 70013 | AO89: =AJ89*(1+Efactor)^2 -> 74999.676
A90: 86 | B90: DPW | C90: Roads/ Paving | D90: Sidewalk Improvements | E90: Improve pedestrian safety. Repair/replacement of sidewalks in poor condition and new sidewalks in village centers, school zones, on major roads. | F90: 150000 | G90: 3 | H90: 0.1 | I90: 4 | J90: 6 | K90: 2 | L90: 8 | M90: 2 | N90: 10 | O90: 0 | P90: 10 | Q90: =(#REF!-(YEAR(TODAY())-#REF!))/#REF! -> #REF! | R90: =IFERROR(Q90,H90) -> 0.1 | S90: =I90*Weight1/(WSum) -> 0.63157895 | T90: =J90*Weight2/(WSum) -> 0.63157895 | U90: =K90*Weight3/(WSum) -> 0.28070175 | V90: =L90*Weight4/(WSum) -> 1.4035088 | W90: =M90*Weight5/(WSum) -> 0.1754386 | X90: =N90*Weight6/(WSum) -> 1.2280702 | Y90: =O90*Weight7/(WSum) -> 0 | Z90: =P90*Weight8/(WSum) -> 1.0526316 | AA90: =-1/10*G90+1 -> 0.7 | AB90: =IF(R90<0,0,-R90+1) -> 0.9 | AC90: =(AA90*CondWeight+AB90*PLifeWeight)/(CondWeight+PLifeWeight) -> 0.76666667 | AD90: =SUM(S90:Z90) -> 5.4035088 | AE90: =AD90*AC90*10 -> 41.426901 | AF90: Alternate Funding | AJ90: 140027 | AO90: =AJ90*(1+Efactor)^2 -> 150000.42
A91: 87 | B91: Parks/Rec | C91: Large Vehicle/ Equipment | D91: Tree Crew Bucket Truck | E91: Current truck has been in service since 2004. Over 90% of Tree Work requires this truck. Without it most work could not be done. | F91: 165000 | G91: 3 | H91: 0.2 | I91: 5 | J91: 6 | K91: 6 | L91: 6 | M91: 8 | N91: 6 | O91: 0 | P91: 8 | Q91: =(#REF!-(YEAR(TODAY())-#REF!))/#REF! -> #REF! | R91: =IFERROR(Q91,H91) -> 0.2 | S91: =I91*Weight1/(WSum) -> 0.78947368 | T91: =J91*Weight2/(WSum) -> 0.63157895 | U91: =K91*Weight3/(WSum) -> 0.84210526 | V91: =L91*Weight4/(WSum) -> 1.0526316 | W91: =M91*Weight5/(WSum) -> 0.70175439 | X91: =N91*Weight6/(WSum) -> 0.73684211 | Y91: =O91*Weight7/(WSum) -> 0 | Z91: =P91*Weight8/(WSum) -> 0.84210526 | AA91: =-1/10*G91+1 -> 0.7 | AB91: =IF(R91<0,0,-R91+1) -> 0.8 | AC91: =(AA91*CondWeight+AB91*PLifeWeight)/(CondWeight+PLifeWeight) -> 0.73333333 | AD91: =SUM(S91:Z91) -> 5.5964912 | AE91: =AD91*AC91*10 -> 41.040936 | AF91: Other | AJ91: 165000 | AO91: =AJ91*(1+Efactor)^2 -> 176752.12
A92: 88 | B92: DPW/ Sewer | C92: Large Vehicle/ Equipment | D92: Replace 2001 10-Wheeler Large Capacity Construction Truck | E92: Replace vehicle/ equipmt used to haul materials for treching / backfilling for sewer line repairs. Also used for snow removal. (#365) | F92: 160000 | G92: 4 | H92: 0.1 | I92: 6 | J92: 8 | K92: 6 | L92: 8 | M92: 4 | N92: 6 | O92: 0 | P92: 7 | Q92: =(#REF!-(YEAR(TODAY())-#REF!))/#REF! -> #REF! | R92: =IFERROR(Q92,H92) -> 0.1 | S92: =I92*Weight1/(WSum) -> 0.94736842 | T92: =J92*Weight2/(WSum) -> 0.84210526 | U92: =K92*Weight3/(WSum) -> 0.84210526 | V92: =L92*Weight4/(WSum) -> 1.4035088 | W92: =M92*Weight5/(WSum) -> 0.35087719 | X92: =N92*Weight6/(WSum) -> 0.73684211 | Y92: =O92*Weight7/(WSum) -> 0 | Z92: =P92*Weight8/(WSum) -> 0.73684211 | AA92: =-1/10*G92+1 -> 0.6 | AB92: =IF(R92<0,0,-R92+1) -> 0.9 | AC92: =(AA92*CondWeight+AB92*PLifeWeight)/(CondWeight+PLifeWeight) -> 0.7 | AD92: =SUM(S92:Z92) -> 5.8596491 | AE92: =AD92*AC92*10 -> 41.017544 | AF92: Enterprise Funds | AJ92: 160000 | AO92: =AJ92*(1+Efactor)^2 -> 171396
A93: 89 | B93: DPW/ Water | C93: Large Vehicle/ Equipment | D93: Replace 2004 Construction Truck | E93: Replacement of existing city vehicle used for construction work on City water mains and for snow removal/sanding operations. Life span of vehicles is 15 yrs (#316). | F93: 130000 | G93: 3 | H93: 0.3 | I93: 6 | J93: 8 | K93: 6 | L93: 8 | M93: 4 | N93: 6 | O93: 1 | P93: 6 | Q93: =(#REF!-(YEAR(TODAY())-#REF!))/#REF! -> #REF! | R93: =IFERROR(Q93,H93) -> 0.3 | S93: =I93*Weight1/(WSum) -> 0.94736842 | T93: =J93*Weight2/(WSum) -> 0.84210526 | U93: =K93*Weight3/(WSum) -> 0.84210526 | V93: =L93*Weight4/(WSum) -> 1.4035088 | W93: =M93*Weight5/(WSum) -> 0.35087719 | X93: =N93*Weight6/(WSum) -> 0.73684211 | Y93: =O93*Weight7/(WSum) -> 0.10526316 | Z93: =P93*Weight8/(WSum) -> 0.63157895 | AA93: =-1/10*G93+1 -> 0.7 | AB93: =IF(R93<0,0,-R93+1) -> 0.7 | AC93: =(AA93*CondWeight+AB93*PLifeWeight)/(CondWeight+PLifeWeight) -> 0.7 | AD93: =SUM(S93:Z93) -> 5.8596491 | AE93: =AD93*AC93*10 -> 41.017544 | AF93: Enterprise Funds | AJ93: 130000 | AO93: =AJ93*(1+Efactor)^2 -> 139259.25
A94: 90 | B94: DPW | C94: Roads/ Paving | D94: Walnut Street (Homer Street to Route 9) - Final Design | E94: Eliminate deteriorated roadway condition and enhance public safety. Arterial minor. Federal funds for constr only. Design funded by City. | F94: 250000 | G94: 3 | H94: 0.2 | I94: 7 | J94: 6 | K94: 6 | L94: 6 | M94: 3 | N94: 6 | O94: 0 | P94: 9 | Q94: =(#REF!-(YEAR(TODAY())-#REF!))/#REF! -> #REF! | R94: =IFERROR(Q94,H94) -> 0.2 | S94: =I94*Weight1/(WSum) -> 1.1052632 | T94: =J94*Weight2/(WSum) -> 0.63157895 | U94: =K94*Weight3/(WSum) -> 0.84210526 | V94: =L94*Weight4/(WSum) -> 1.0526316 | W94: =M94*Weight5/(WSum) -> 0.26315789 | X94: =N94*Weight6/(WSum) -> 0.73684211 | Y94: =O94*Weight7/(WSum) -> 0 | Z94: =P94*Weight8/(WSum) -> 0.94736842 | AA94: =-1/10*G94+1 -> 0.7 | AB94: =IF(R94<0,0,-R94+1) -> 0.8 | AC94: =(AA94*CondWeight+AB94*PLifeWeight)/(CondWeight+PLifeWeight) -> 0.73333333 | AD94: =SUM(S94:Z94) -> 5.5789474 | AE94: =AD94*AC94*10 -> 40.912281 | AF94: Chapt 90/ Alt Funds | AJ94: 233378 | AO94: =AJ94*(1+Efactor)^2 -> 250000.35
A95: 91 | B95: DPW/ Storm | C95: Storm | D95: Rehabilitation of Forest Grove Storm System Pump Station | E95: Pump station is used for flood and mosquito control of Flowed Meadow and needs upgrades and repair work to function properly. | F95: 150000 | G95: 4 | H95: 0.2 | I95: 6 | J95: 8 | K95: 5 | L95: 8 | M95: 5 | N95: 6 | O95: 0 | P95: 10 | Q95: =(#REF!-(YEAR(TODAY())-#REF!))/#REF! -> #REF! | R95: =IFERROR(Q95,H95) -> 0.2 | S95: =I95*Weight1/(WSum) -> 0.94736842 | T95: =J95*Weight2/(WSum) -> 0.84210526 | U95: =K95*Weight3/(WSum) -> 0.70175439 | V95: =L95*Weight4/(WSum) -> 1.4035088 | W95: =M95*Weight5/(WSum) -> 0.43859649 | X95: =N95*Weight6/(WSum) -> 0.73684211 | Y95: =O95*Weight7/(WSum) -> 0 | Z95: =P95*Weight8/(WSum) -> 1.0526316 | AA95: =-1/10*G95+1 -> 0.6 | AB95: =IF(R95<0,0,-R95+1) -> 0.8 | AC95: =(AA95*CondWeight+AB95*PLifeWeight)/(CondWeight+PLifeWeight) -> 0.66666667 | AD95: =SUM(S95:Z95) -> 6.122807 | AE95: =AD95*AC95*10 -> 40.818713 | AF95: Enterprise Funds | AJ95: 150000 | AO95: =AJ95*(1+Efactor)^2 -> 160683.75
A96: 92 | B96: Schools | C96: Building | D96: Bigelow School - Mechanical Upgrades | E96: Boilers are 54 years old and beyond their useful life. Replace one boiler now and one in future year. | F96: 250000 | G96: 3 | H96: 0.1 | I96: 6 | J96: 8 | K96: 3 | L96: 4 | M96: 1 | N96: 6 | O96: 6 | P96: 9 | Q96: =(#REF!-(YEAR(TODAY())-#REF!))/#REF! -> #REF! | R96: =IFERROR(Q96,H96) -> 0.1 | S96: =I96*Weight1/(WSum) -> 0.94736842 | T96: =J96*Weight2/(WSum) -> 0.84210526 | U96: =K96*Weight3/(WSum) -> 0.42105263 | V96: =L96*Weight4/(WSum) -> 0.70175439 | W96: =M96*Weight5/(WSum) -> 0.087719298 | X96: =N96*Weight6/(WSum) -> 0.73684211 | Y96: =O96*Weight7/(WSum) -> 0.63157895 | Z96: =P96*Weight8/(WSum) -> 0.94736842 | AA96: =-1/10*G96+1 -> 0.7 | AB96: =IF(R96<0,0,-R96+1) -> 0.9 | AC96: =(AA96*CondWeight+AB96*PLifeWeight)/(CondWeight+PLifeWeight) -> 0.76666667 | AD96: =SUM(S96:Z96) -> 5.3157895 | AE96: =AD96*AC96*10 -> 40.754386 | AF96: Bonding | AK96: 250000 | AP96: =AK96*(1+Efactor)^3 -> 277179.47
A97: 93 | B97: Schools | C97: Building | D97: Brown School - Mechanical Upgrades | E97: Study options for repair /replacement. Steam system has failed. $50K/yr to address steam leaks. Hot water conversion in the next ten years ($2M). Periodically causes a mold problem. | F97: 2000000 | G97: 3 | H97: 0.3 | I97: 6 | J97: 8 | K97: 2 | L97: 6 | M97: 4 | N97: 6 | O97: 6 | P97: 9 | Q97: =(#REF!-(YEAR(TODAY())-#REF!))/#REF! -> #REF! | R97: =IFERROR(Q97,H97) -> 0.3 | S97: =I97*Weight1/(WSum) -> 0.94736842 | T97: =J97*Weight2/(WSum) -> 0.84210526 | U97: =K97*Weight3/(WSum) -> 0.28070175 | V97: =L97*Weight4/(WSum) -> 1.0526316 | W97: =M97*Weight5/(WSum) -> 0.35087719 | X97: =N97*Weight6/(WSum) -> 0.73684211 | Y97: =O97*Weight7/(WSum) -> 0.63157895 | Z97: =P97*Weight8/(WSum) -> 0.94736842 | AA97: =-1/10*G97+1 -> 0.7 | AB97: =IF(R97<0,0,-R97+1) -> 0.7 | AC97: =(AA97*CondWeight+AB97*PLifeWeight)/(CondWeight+PLifeWeight) -> 0.7 | AD97: =SUM(S97:Z97) -> 5.7894737 | AE97: =AD97*AC97*10 -> 40.526316 | AF97: Other | AK97: 50000 | AP97: =AK97*(1+Efactor)^3 -> 55435.894
A98: 94 | B98: DPW | C98: Roads/ Paving | D98: Streetlights - Gaslight Conversion for Energy Efficiency | E98: Convert 19 gas lights to electric lights on existing utility poles. Convert 56 gaslights to electric lights where no streetlight pole exists. Requires installation of conduit, electric meters, new foundations, new poles, and new light fixtures. | F98: 234000 | G98: 4 | H98: 0.2 | I98: 6 | J98: 6 | K98: 10 | L98: 2 | M98: 0 | N98: 6 | O98: 10 | P98: 9 | Q98: =(#REF!-(YEAR(TODAY())-#REF!))/#REF! -> #REF! | R98: =IFERROR(Q98,H98) -> 0.2 | S98: =I98*Weight1/(WSum) -> 0.94736842 | T98: =J98*Weight2/(WSum) -> 0.63157895 | U98: =K98*Weight3/(WSum) -> 1.4035088 | V98: =L98*Weight4/(WSum) -> 0.35087719 | W98: =M98*Weight5/(WSum) -> 0 | X98: =N98*Weight6/(WSum) -> 0.73684211 | Y98: =O98*Weight7/(WSum) -> 1.0526316 | Z98: =P98*Weight8/(WSum) -> 0.94736842 | AA98: =-1/10*G98+1 -> 0.6 | AB98: =IF(R98<0,0,-R98+1) -> 0.8 | AC98: =(AA98*CondWeight+AB98*PLifeWeight)/(CondWeight+PLifeWeight) -> 0.66666667 | AD98: =SUM(S98:Z98) -> 6.0701754 | AE98: =AD98*AC98*10 -> 40.467836 | AF98: Other
A99: 95 | B99: Public Buildings | C99: Building | D99: Energy Efficiency / Water Conservation Upgrades to City and School Buildings | E99: Project includes energy conservation measures at Horace Mann, Brown, Oak Hill and NSHS thru NSTAR preferred vendor program. | F99: 500000 | G99: 3 | H99: 0.2 | I99: 6 | J99: 8 | K99: 5 | L99: 2 | M99: 0 | N99: 8 | O99: 6 | P99: 10 | Q99: =(#REF!-(YEAR(TODAY())-#REF!))/#REF! -> #REF! | R99: =IFERROR(Q99,H99) -> 0.2 | S99: =I99*Weight1/(WSum) -> 0.94736842 | T99: =J99*Weight2/(WSum) -> 0.84210526 | U99: =K99*Weight3/(WSum) -> 0.70175439 | V99: =L99*Weight4/(WSum) -> 0.35087719 | W99: =M99*Weight5/(WSum) -> 0 | X99: =N99*Weight6/(WSum) -> 0.98245614 | Y99: =O99*Weight7/(WSum) -> 0.63157895 | Z99: =P99*Weight8/(WSum) -> 1.0526316 | AA99: =-1/10*G99+1 -> 0.7 | AB99: =IF(R99<0,0,-R99+1) -> 0.8 | AC99: =(AA99*CondWeight+AB99*PLifeWeight)/(CondWeight+PLifeWeight) -> 0.73333333 | AD99: =SUM(S99:Z99) -> 5.5087719 | AE99: =AD99*AC99*10 -> 40.397661 | AF99: Energy Stabilztn Fund | AK99: 500000 | AP99: =AK99*(1+Efactor)^3 -> 554358.94
A100: 96 | B100: DPW | C100: Building | D100: Crafts Street Garage - Mechanical Upgrades | E100: Complete roof top unit work begun in stimulus project. Replace fans, duct work, unit heaters. Provide gas detection system. | F100: 400000 | G100: 2 | H100: 0.1 | I100: 8 | J100: 4 | K100: 2 | L100: 8 | M100: 2 | N100: 2 | O100: 2 | P100: 8 | Q100: =(#REF!-(YEAR(TODAY())-#REF!))/#REF! -> #REF! | R100: =IFERROR(Q100,H100) -> 0.1 | S100: =I100*Weight1/(WSum) -> 1.2631579 | T100: =J100*Weight2/(WSum) -> 0.42105263 | U100: =K100*Weight3/(WSum) -> 0.28070175 | V100: =L100*Weight4/(WSum) -> 1.4035088 | W100: =M100*Weight5/(WSum) -> 0.1754386 | X100: =N100*Weight6/(WSum) -> 0.24561404 | Y100: =O100*Weight7/(WSum) -> 0.21052632 | Z100: =P100*Weight8/(WSum) -> 0.84210526 | AA100: =-1/10*G100+1 -> 0.8 | AB100: =IF(R100<0,0,-R100+1) -> 0.9 | AC100: =(AA100*CondWeight+AB100*PLifeWeight)/(CondWeight+PLifeWeight) -> 0.83333333 | AD100: =SUM(S100:Z100) -> 4.8421053 | AE100: =AD100*AC100*10 -> 40.350877 | AF100: Bonding | AK100: 400000 | AP100: =AK100*(1+Efactor)^3 -> 443487.15
...

Sheet Lists
A1: % Life Left | B1: Overall Condition | C1: Description | D1: Consequence | E1: Description | F1: Funding Source
A2: 0 | B2: 0 | C2: Deplorable | D2: 0 | E2: No Impact | F2: Bonding
A3: 0.1 | B3: 1 | C3: Very bad | D3: 1 | F3: Chapt 90/ Alt Funds
A4: 0.2 | B4: 2 | C4: Bad | D4: 2 | E4: Small Impact | F4: Bonding/MSBA
A5: 0.3 | B5: 3 | C5: Poor | D5: 3 | F5: CDBG Eligible
A6: 0.4 | B6: 4 | C6: Slightly below average | D6: 4 | F6: Alternate Funding
A7: 0.5 | B7: 5 | C7: Average | D7: 5 | E7: Moderate Impact | F7: CPA Eligible
A8: 0.6 | B8: 6 | C8: Slightly above average | D8: 6 | F8: Energy Stab. Fund
A9: 0.7 | B9: 7 | C9: Fair | D9: 7 | F9: Enterprise Funds
A10: 0.8 | B10: 8 | C10: Good | D10: 8 | E10: High Impact | F10: Grant
A11: 0.9 | B11: 9 | C11: Very good | D11: 9 | F11: Other
A12: 1 | B12: 10 | C12: Excellent | D12: 10 | E12: Very High Impact

Sheet 20 Year Plan
A1: City of Newton 20 Year Long Range Capital Projection | Q1: 10.9.12
A2: Cost estimates include 3.5% escalation.
A3: ASSET TYPES | D3: FY14 | E3: FY15 | F3: FY16 | G3: FY17 | H3: FY18 | I3: FY14-FY18 CIP | J3: FY19-FY23 CIP | K3: FY19-FY23 CIP | L3: FY24-FY28 CIP | M3: FY24-FY28 CIP | N3: FY29-FY33 CIP | O3: FY29-FY33 CIP | P3: 20 YEAR TOTAL | Q3: NOTES
A4: BUILDINGS
B5: SCHOOLS
B6: Carr Elementary
C7: Carr Mechanical
C8: Generation - Boiler, Chiller
C9: Generation - Air handlers
C10: Distribution
C11: Controls / EMS
C12: Underground Tanks
C13: Carr Electrical/Alt Energy
C14: Emergency Generator
C15: Switch Gear / Panels
C16: Distribution
C17: Lighting and Controls | N17: 150000 | O17: =N17*1.73 -> 259500 | P17: =SUM(I17,K17,M17,O17) -> 259500
C18: Carr Plumbing + Fire Protection
C19: Pumps
C20: Distribution
C21: Fixtures
C22: Sprinklers/Fire Alarm
C23: Carr Building Envelope
C24: Masonry/Walls
C25: Windows & Doors
C26: Roof
C27: Entrance Stairs/Ramps
C28: Carr Building Interior
C29: Stairs / Elevators
C30: Finishes (Flrs, Walls, Ceilgs) | J30: 100000 | K30: =J30*1.23 -> 123000 | P30: =SUM(I30,K30,M30,O30) -> 123000 | Q30: Gym Floor
C31: Equipment/Furnishing
C32: Other-Renovation Project | D32: =CIP!$AM$6 -> 11700000 | I32: =SUM(D32:H32) -> 11700000 | P32: =SUM(I32,K32,M32,O32) -> 11700000 | Q32: incl. roof & windows
C33: Carr Elementary | D33: =SUM(D6:D32) -> 11700000 | I33: =SUM(I6:I32) -> 11700000 | J33: =SUM(J6:J32) -> 100000 | K33: =J33*1.23 -> 123000 | N33: =SUM(N6:N32) -> 150000 | O33: =N33*1.73 -> 259500 | P33: =SUM(I33,K33,M33,O33) -> 12082500 | Q33: Carr Reno Total $12.7M
B34: Angier Elementary
C35: Mechanical
C36: Generation - Boiler, Chiller
C37: Generation - Air handlers
C38: Distribution
C39: Controls / EMS
C40: Underground Tanks
C41: Electrical/Alt Energy
C42: Emergency Generator
C43: Switch Gear / Panels
C44: Distribution
C45: Lighting and Controls | N45: 150000 | O45: =N45*1.73 -> 259500 | P45: =SUM(I45,K45,M45,O45) -> 259500
C46: Plumbing + Fire Protection
C47: Pumps
C48: Distribution
C49: Fixtures
C50: Sprinklers/Fire Alarm
C51: Building Envelope
C52: Masonry/Walls
C53: Windows & Doors
C54: Roof
C55: Entrance Stairs/Ramps
C56: Building Interior
C57: Stairs / Elevators
C58: Finishes (Flrs, Walls, Ceilgs) | L58: 100000 | M58: =L58*1.46 -> 146000 | P58: =SUM(I58,K58,M58,O58) -> 146000 | Q58: Gym Floor
C59: Equipment/Furnishing
C60: Other-Renovation/New Project | D60: =CIP!$AM$5 -> 5000000 | E60: =CIP!$AN$5 -> 17500000 | F60: =CIP!$AO$5 -> 12500000 | I60: =SUM(D60:H60) -> 35000000 | P60: =SUM(I60,K60,M60,O60) -> 35000000 | Q60: 75,000 sf x $350/sf x 1.33
C61: Angier Elementary | D61: =SUM(D60) -> 5000000 | E61: =SUM(E54:E60) -> 17500000 | F61: =SUM(F57:F60) -> 12500000 | I61: =SUM(D61:H61) -> 35000000 | L61: =SUM(L55:L60) -> 100000 | M61: =L61*1.46 -> 146000 | N61: =SUM(N35:N60) -> 150000 | O61: =N61*1.73 -> 259500 | P61: =SUM(I61,K61,M61,O61) -> 35405500 | Q61: est. $7.5M from MSBA
B62: Cabot Elementary
C63: Mechanical
C64: Generation - Boilers
C65: Generation - Air handlers
C66: Distribution | Q66: hot water conversion
C67: Controls / EMS
C68: Underground Tank & Paving
C69: Electrical/Alt Energy
C70: Emergency Generator
C71: Switch Gear / Panels
C72: Distribution
C73: Lighting and Controls
C74: Plumbing
C75: Pumps
C76: Distribution
C77: Fixtures
C78: Sprinklers/Fire Alarm
... C87: Equipment/Furnishing
C88: Other-Renovation/New Project | D88: =CIP!$AM$15 -> 750000 | F88: =CIP!$AO$15 -> 15000000 | G88: =CIP!$AP$15 -> 22500000 | I88: =SUM(D88:H88) -> 38250000 | P88: =SUM(I88,K88,M88,O88) -> 38250000 | Q88: Feas. in FY14, incls MEP
C89: Modular (4 units)
C90: Cabot Elementary | D90: =SUM(D88:D89) -> 750000 | F90: =SUM(F88:F89) -> 15000000 | G90: =SUM(G88:G89) -> 22500000 | I90: =SUM(D90:H90) -> 38250000 | P90: =SUM(I90,K90,M90,O90) -> 38250000 | Q90: est. $7.5M from MSBA
B91: Zervas Elementary
C92: Mechanical
C93: Generation - Boilers
C94: Generation - Air handlers
C95: Distribution
C96: Controls / EMS
C97: Underground Tank & Paving | Q97: in fuel tank program
C98: Electrical/Alt Energy
C99: Emergency Generator
C100: Switch Gear / Panels | D100: =CIP!$AM$18 -> 80000 | I100: =SUM(D100:H100) -> 80000 | P100: =SUM(I100,K100,M100,O100) -> 80000 | Q100: incl $50K @ Bigelow
C101: Distribution
C102: Lighting and Controls
C103: Plumbing
C104: Pumps
C105: Distribution
C106: Fixtures
C107: Sprinklers/Fire Alarm
C108: Building Envelope
...
