Workbook
Name a: #REF!
Name asdf: #REF!
Name asdf: #REF!
Name asdf: #REF!
Name bnm: #REF!
Name bnm: #REF!
Name bnm: #REF!
Name Initial: #REF!
Name Initial: #REF!
Name Initial: #REF!
Name MSN_MoneyCentral_Investor_Stock_Quotes: 'Holdings Pull Sheet'!$C$9:$R$63
Name portbeg: #REF!
Name portbeg: #REF!
Name portbeg: #REF!
Name qwer: #REF!
Name qwer: #REF!
Name qwer: #REF!
Name s: #REF!
Name Sheet: #REF!
Name Sheet: #REF!
Name Sheet: #REF!
Name SP: #REF!
Name SP: #REF!
Name SP: #REF!
Name spbeg: #REF!
Name spbeg: #REF!
Name spbeg: #REF!
Name vb: #REF!
Name vb: #REF!
Name vb: #REF!
Name WINBEG: #REF!
Name WINBEG: #REF!
Name WINBEG: #REF!
Name WINSP: #REF!
Name WINSP: #REF!
Name WINSP: #REF!
Name zxc: #REF!
Name zxc: #REF!
Name zxc: #REF!

Sheet Summary
L3: Summer | S3: 1 Week | Z3: Today | AG3: Total Value | AH3: =Holdings!$H$22 -> 51169.51
L4: IPO | M4: =Holdings!$Q$22 -> 0.09995134 | S4: IPO | T4: =Holdings!$R$22 -> 0.017372717 | Z4: IPO | AA4: =Holdings!$S$22 -> 0.017093027 | AG4: Cost Basis | AH4: =Holdings!$I$22 -> 33209.83
L6: S&P 500 | M6: =('Holdings Pull Sheet'!$F$14/Data!$L$511)-1 -> 0.032299579 | S6: S&P 500 | T6: =('Holdings Pull Sheet'!$F$14/Data!$L$517)-1 -> 0.0085672374 | Z6: S&P 500 | AA6: =('Holdings Pull Sheet'!$F$14/'Holdings Pull Sheet'!$G$14)-1 -> 0.014784313 | AG6: Return since 5/02/03 | AH6: =Holdings!$O$22 -> 1.2387927
L8: Dow Jones | M8: =('Holdings Pull Sheet'!$F$12/Data!$S$511)-1 -> 0.032330213 | S8: Dow Jones | T8: =('Holdings Pull Sheet'!$F12/Data!$S517)-1 -> 0.0090217075 | Z8: Dow Jones | AA8: =('Holdings Pull Sheet'!$F$12/'Holdings Pull Sheet'!$G$12)-1 -> 0.012060502 | AE8: Cash Availailable | AH8: =Holdings!$H$4 -> 8114.57
AE9: % of Portfolio | AH9: =Holdings!$U$4 -> 0.15858213
C13: =Holdings!$C$5 -> Berkshire Hathaway | F13: =Holdings!$E$5 -> 114.99 | J13: =Holdings!$C$9 -> Cisco | M13: =Holdings!$E$9 -> 24.35 | Q13: =Holdings!$C$13 -> Immersion | T13: =Holdings!$E$13 -> 14.91 | X13: =Holdings!$C$17 -> Tutor Perini | AA13: =Holdings!$E$17 -> 17.43 | AE13: =Holdings!$C$21 -> YRC Worldwide | AH13: =Holdings!$E$21 -> 22.6
C15: =Holdings!$D$5 -> BRK.B | E15: Today | F15: =Holdings!$S$5 -> 0.018061089 | J15: =Holdings!$D$9 -> CSCO | L15: Today | M15: =Holdings!$S$9 -> 0.015006253 | Q15: =Holdings!$D$13 -> IMMR | S15: Today | T15: =Holdings!$S$13 -> 0.044849334 | X15: =Holdings!$D$17 -> TPC | Z15: Today | AA15: =Holdings!$S$17 -> 0.013914317 | AE15: =Holdings!$D$21 -> YRCW | AG15: Today | AH15: =Holdings!$S$21 -> 0.018539977
E16: 1 Week | F16: =Holdings!$R$5 -> 0.016710875 | L16: 1 Week | M16: =Holdings!$R$9 -> -0.0081466395 | S16: 1 Week | T16: =Holdings!$R$13 -> 0.026859504 | Z16: 1 Week | AA16: =Holdings!$R$17 -> 0.004610951 | AG16: 1 Week | AH16: =Holdings!$R$21 -> 0.17219917
E17: Summer | F17: =Holdings!$Q$5 -> 0.069973016 | L17: =$E$17 -> Summer | M17: =Holdings!$Q$9 -> 0.1894654 | S17: =$E$17 -> Summer | T17: =Holdings!$Q$13 -> -0.0090828533 | Z17: =$E$17 -> Summer | AA17: =Holdings!$Q$17 -> 0.040590717 | AG17: =$E$17 -> Summer | AH17: =Holdings!$Q$21 -> 2.1875882
E18: Total Gain | F18: =Holdings!$O$5 -> 0.46909473 | L18: Total Gain | M18: =Holdings!$O$9 -> 0.32777744 | S18: Total Gain | T18: =Holdings!$O$13 -> -0.0090828533 | Z18: Total Gain | AA18: =Holdings!$O$17 -> 0.26660466 | AG18: Total Gain | AH18: =Holdings!$O$21 -> 1.6248548
C20: =IF(C21=0,"No Cap", IF(C21<2,"Small Cap", IF(C21<10, "Mid Cap", IF(C21>10, "Large Cap")))) -> Large Cap | E20: Value | F20: =Holdings!$H$5 -> 2989.74 | J20: =IF(J21=0,"No Cap", IF(J21<2,"Small Cap", IF(J21<10, "Mid Cap", IF(J21>10, "Large Cap")))) -> Large Cap | L20: Value | M20: =Holdings!$H$9 -> 1657.2123 | Q20: =IF(Q21=0,"No Cap", IF(Q21<2,"Small Cap", IF(Q21<10, "Mid Cap", IF(Q21>10, "Large Cap")))) -> Small Cap | S20: Value | T20: =Holdings!$H$13 -> 2012.85 | X20: =IF(X21=0,"No Cap", IF(X21<2,"Small Cap", IF(X21<10, "Mid Cap", IF(X21>10, "Large Cap")))) -> Small Cap | Z20: Value | AA20: =Holdings!$H$17 -> 3486 | AE20: =IF(AE21=0,"No Cap", IF(AE21<2,"Small Cap", IF(AE21<10, "Mid Cap", IF(AE21>10, "Large Cap")))) -> Small Cap | AG20: Value | AH20: =Holdings!$H$21 -> 4520
C21: =Holdings!$V$5 -> 283.48254 | E21: Cost | F21: =Holdings!$I$5 -> 2035.09 | J21: =Holdings!$V$9 -> 130.13458 | L21: Cost | M21: =Holdings!$I$9 -> 1248.11 | Q21: =Holdings!$V$13 -> 0.41595396 | S21: Cost | T21: =Holdings!$I$13 -> 2031.3 | X21: =Holdings!$V$17 -> 0.82924429 | Z21: Cost | AA21: =Holdings!$I$17 -> 2752.24 | AE21: =Holdings!$V$21 -> 0.21236904 | AG21: Cost | AH21: =Holdings!$I$21 -> 1722
E23: % of Portfolio | F23: =Holdings!$U$5 -> 0.058428154 | L23: % of Portfolio | M23: =Holdings!$U$9 -> 0.032386715 | S23: % of Portfolio | T23: =Holdings!$U$13 -> 0.039336902 | Z23: % of Portfolio | AA23: =Holdings!$U$17 -> 0.068126508 | AG23: % of Portfolio | AH23: =Holdings!$U$21 -> 0.088333854
C27: =Holdings!$C$6 -> BlackRock Global | F27: =Holdings!$E$6 -> 19.39 | J27: =Holdings!$C$10 -> Delta Airlines | M27: =Holdings!$E$10 -> 18.71 | Q27: =Holdings!$C$14 -> Intel | T27: =Holdings!$E$14 -> 24.99 | X27: =Holdings!$C$18 -> Tyson Foods | AA27: =Holdings!$E$18 -> 25.71
C29: =Holdings!$D$6 -> MCLOX | E29: Today | F29: =Holdings!$S$6 -> 0.0072727273 | J29: =Holdings!$D$10 -> DAL | L29: Today | M29: =Holdings!$S$10 -> 0.03541782 | Q29: =Holdings!$D$14 -> INTC | S29: Today | T29: =Holdings!$S$14 -> 0.021668029 | X29: =Holdings!$D$18 -> TSN | Z29: Today | AA29: =Holdings!$S$18 -> 0.034421365
E30: 1 Week | F30: =Holdings!$R$6 -> 0.0041429311 | L30: 1 Week | M30: =Holdings!$R$10 -> 0.069754145 | S30: 1 Week | T30: =Holdings!$R$14 -> 0.010951542 | Z30: 1 Week | AA30: =Holdings!$R$18 -> 0.036275695
E31: =$E$17 -> Summer | F31: =Holdings!$Q$6 -> -0.0025720165 | L31: =$E$17 -> Summer | M31: =Holdings!$Q$10 -> 0.1485574 | S31: =$E$17 -> Summer | T31: =Holdings!$Q$14 -> 0.010951542 | Z31: =$E$17 -> Summer | AA31: =Holdings!$Q$18 -> 0.033360129
E32: Total Gain | F32: =Holdings!$O$6 -> 0.12124859 | L32: Total Gain | M32: =Holdings!$O$10 -> 0.13074589 | S32: Total Gain | T32: =Holdings!$O$14 -> 0.010951542 | Z32: Total Gain | AA32: =Holdings!$O$18 -> 0.54986041
C34: =IF(C35=0,"No Cap", IF(C35<2,"Small Cap", IF(C35<10, "Mid Cap", IF(C35>10, "Large Cap")))) -> No Cap | E34: Value | F34: =Holdings!$H$6 -> 1730.5575 | J34: =IF(J35=0,"No Cap", IF(J35<2,"Small Cap", IF(J35<10, "Mid Cap", IF(J35>10, "Large Cap")))) -> Large Cap | L34: Value | M34: =Holdings!$H$10 -> 2806.5 | Q34: =IF(Q35=0,"No Cap", IF(Q35<2,"Small Cap", IF(Q35<10, "Mid Cap", IF(Q35>10, "Large Cap")))) -> Large Cap | S34: Value | T34: =Holdings!$H$14 -> 2798.88 | X34: =IF(X35=0,"No Cap", IF(X35<2,"Small Cap", IF(X35<10, "Mid Cap", IF(X35>10, "Large Cap")))) -> Mid Cap | Z34: Value | AA34: =Holdings!$H$18 -> 2595.9387
C35: =Holdings!$V$6 -> 0 | E35: Cost | F35: =Holdings!$I$6 -> 1543.42 | J35: =Holdings!$V$10 -> 16.02596 | L35: Cost | M35: =Holdings!$I$10 -> 2481.99 | Q35: =Holdings!$V$14 -> 124.22529 | S35: Cost | T35: =Holdings!$I$14 -> 2768.56 | X35: =Holdings!$V$18 -> 9.1229926 | Z35: Cost | AA35: =Holdings!$I$18 -> 1674.95
E37: % of Portfolio | F37: =Holdings!$U$6 -> 0.033820092 | L37: % of Portfolio | M37: =Holdings!$U$10 -> 0.054847115 | S37: % of Portfolio | T37: =Holdings!$U$14 -> 0.054698199 | Z37: % of Portfolio | AA37: =Holdings!$U$18 -> 0.05073214
C41: =Holdings!$C$7 -> Caterpillar | F41: =Holdings!$E$7 -> 85.14 | J41: =Holdings!$C$11 -> Gentex | M41: =Holdings!$E$11 -> 23.27 | Q41: =Holdings!$C$15 -> Medtronic | T41: =Holdings!$E$15 -> 52.78 | X41: =Holdings!$C$19 -> Wells Fargo | AA41: =Holdings!$E$19 -> 40.94
C43: =Holdings!$D$7 -> CAT | E43: Today | F43: =Holdings!$S$7 -> 0.023194328 | J43: =Holdings!$D$11 -> GNTX | L43: Today | M43: =Holdings!$S$11 -> 0.028735632 | Q43: =Holdings!$D$15 -> MDT | S43: Today | T43: =Holdings!$S$15 -> 0.022670025 | X43: =Holdings!$D$19 -> WFC | Z43: Today | AA43: =Holdings!$S$19 -> 0.01140834
E44: 1 Week | F44: =Holdings!$R$7 -> 0.013571429 | L44: 1 Week | M44: =Holdings!$R$11 -> 0.015713662 | S44: 1 Week | T44: =Holdings!$R$15 -> 0.025252525 | Z44: 1 Week | AA44: =Holdings!$R$19 -> 0.0054027505
E45: =$E$17 -> Summer | F45: =Holdings!$Q$7 -> 0.01339941 | L45: =$E$17 -> Summer | M45: =Holdings!$Q$11 -> 0.03070425 | S45: =$E$17 -> Summer | T45: =Holdings!$Q$15 -> 0.12850624 | Z45: =$E$17 -> Summer | AA45: =Holdings!$Q$19 -> 0.086963142
E46: Total Gain | F46: =Holdings!$O$7 -> 0.02931916 | L46: Total Gain | M46: =Holdings!$O$11 -> 0.44316285 | S46: Total Gain | T46: =Holdings!$O$15 -> 0.12547834 | Z46: Total Gain | AA46: =Holdings!$O$19 -> 0.77051894
C48: =IF(C49=0,"No Cap", IF(C49<2,"Small Cap", IF(C49<10, "Mid Cap", IF(C49>10, "Large Cap")))) -> Large Cap | E48: Value | F48: =Holdings!$H$7 -> 1291.7441 | J48: =IF(J49=0,"No Cap", IF(J49<2,"Small Cap", IF(J49<10, "Mid Cap", IF(J49>10, "Large Cap")))) -> Mid Cap | L48: Value | M48: =Holdings!$H$11 -> 2168.1357 | Q48: =IF(Q49=0,"No Cap", IF(Q49<2,"Small Cap", IF(Q49<10, "Mid Cap", IF(Q49>10, "Large Cap")))) -> Large Cap | S48: Value | T48: =Holdings!$H$15 -> 1497.6853 | X48: =IF(X49=0,"No Cap", IF(X49<2,"Small Cap", IF(X49<10, "Mid Cap", IF(X49>10, "Large Cap")))) -> Large Cap | Z48: Value | AA48: =Holdings!$H$19 -> 2132.3599
C49: =Holdings!$V$7 -> 55.978264 | E49: Cost | F49: =Holdings!$I$7 -> 1254.95 | J49: =Holdings!$V$11 -> 3.3411997 | L49: Cost | M49: =Holdings!$I$11 -> 1502.35 | Q49: =Holdings!$V$15 -> 53.508679 | S49: Cost | T49: =Holdings!$I$15 -> 1330.71 | X49: =Holdings!$V$19 -> 216.83408 | Z49: Cost | AA49: =Holdings!$I$19 -> 1204.37
E51: % of Portfolio | F51: =Holdings!$U$7 -> 0.02524441 | L51: % of Portfolio | M51: =Holdings!$U$11 -> 0.042371634 | S51: % of Portfolio | T51: =Holdings!$U$15 -> 0.029269096 | Z51: % of Portfolio | AA51: =Holdings!$U$19 -> 0.041672471
C55: =Holdings!$C$8 -> Cemex | F55: =Holdings!$E$8 -> 10.55 | J55: =Holdings!$C$12 -> Home Depot | M55: =Holdings!$E$12 -> 76.53 | Q55: =Holdings!$C$16 -> Natural Grocers | T55: =Holdings!$E$16 -> 27.69 | X55: =Holdings!$C$20 -> Yahoo | AA55: =Holdings!$E$20 -> 26.37
C57: =Holdings!$D$8 -> CX | E57: Today | F57: =Holdings!$S$8 -> 0.029268293 | J57: =Holdings!$D$12 -> HD | L57: Today | M57: =Holdings!$S$12 -> 0.0017015707 | Q57: =Holdings!$D$16 -> NGVC | S57: Today | T57: =Holdings!$S$16 -> 0.022670025 | X57: =Holdings!$D$20 -> YHOO | Z57: Today | AA57: =Holdings!$S$20 -> 0.016637696
E58: 1 Week | F58: =Holdings!$R$8 -> -0.026752768 | L58: 1 Week | M58: =Holdings!$R$12 -> -0.0094486151 | S58: 1 Week | T58: =Holdings!$R$16 -> 0.0355273 | Z58: 1 Week | AA58: =Holdings!$R$20 -> 0.0061045403
E59: =$E$17 -> Summer | F59: =Holdings!$Q$8 -> -0.08840328 | L59: =$E$17 -> Summer | M59: =Holdings!$Q$12 -> 0.048899539 | S59: =$E$17 -> Summer | T59: =Holdings!$Q$16 -> 0.11338963 | Z59: =$E$17 -> Summer | AA59: =Holdings!$Q$20 -> 0.046428571
E60: Total Gain | F60: =Holdings!$O$8 -> -0.08840328 | L60: Total Gain | M60: =Holdings!$O$12 -> 1.7227482 | S60: Total Gain | T60: =Holdings!$O$16 -> 0.41112319 | Z60: Total Gain | AA60: =Holdings!$O$20 -> 0.21241937
C62: =IF(C63=0,"No Cap", IF(C63<2,"Small Cap", IF(C63<10, "Mid Cap", IF(C63>10, "Large Cap")))) -> Large Cap | E62: Value | F62: =Holdings!$H$8 -> 2110 | J62: =IF(J63=0,"No Cap", IF(J63<2,"Small Cap", IF(J63<10, "Mid Cap", IF(J63>10, "Large Cap")))) -> Large Cap | L62: Value | M62: =Holdings!$H$12 -> 4543.5861 | Q62: =IF(Q63=0,"No Cap", IF(Q63<2,"Small Cap", IF(Q63<10, "Mid Cap", IF(Q63>10, "Large Cap")))) -> Small Cap | S62: Value | T62: =Holdings!$H$16 -> 2076.75 | X62: =IF(X63=0,"No Cap", IF(X63<2,"Small Cap", IF(X63<10, "Mid Cap", IF(X63>10, "Large Cap")))) -> Large Cap | Z62: Value | AA62: =Holdings!$H$20 -> 2637
C63: =Holdings!$V$8 -> 11.867495 | E63: Cost | F63: =Holdings!$I$8 -> 2314.62 | J63: =Holdings!$V$12 -> 111.79472 | L63: Cost | M63: =Holdings!$I$12 -> 1668.75 | Q63: =Holdings!$V$16 -> 0.62030918 | S63: Cost | T63: =Holdings!$I$16 -> 1471.7 | X63: =Holdings!$V$20 -> 28.549086 | Z63: Cost | AA63: =Holdings!$I$20 -> 2174.99
E65: % of Portfolio | F65: =Holdings!$U$8 -> 0.041235494 | L65: % of Portfolio | M65: =Holdings!$U$12 -> 0.088794795 | S65: % of Portfolio | T65: =Holdings!$U$16 -> 0.040585693 | Z65: % of Portfolio | AA65: =Holdings!$U$20 -> 0.051534596
C69: Bought This Year | Q69: Sold This Year
F71: Date Bought | J71: Buy Price | L71: Current Price | M71: Change* | T71: Date Sold | X71: Sell Price | Z71: Current Price | AA71: Change*
D72: =Holdings!C26 -> Tyson Foods | F72: =Holdings!E26 -> 41173 | J72: =Holdings!H26 -> 16.65 | L72: =Holdings!I26 -> 25.71 | M72: =L72/J72-1 -> 0.54414414 | R72: =Holdings!C38 -> Vale | T72: =Holdings!E38 -> 41166 | X72: =Holdings!H38 -> 19.71 | Y72: 19.71 | Z72: =Holdings!I38 -> 14.47 | AA72: =(Z72/X72)-1 -> -0.2658549
D73: =Holdings!C27 -> Tutor Perini | F73: =Holdings!E27 -> 41215 | J73: =Holdings!H27 -> 12.43 | L73: =Holdings!I27 -> 17.43 | M73: =L73/J73-1 -> 0.40225261 | R73: =Holdings!C39 -> CPFL Energia | T73: =Holdings!E39 -> 41215 | X73: =Holdings!H39 -> 23 | Y73: 20.71 | Z73: =Holdings!I39 -> 20.31 | AA73: =(Z73/X73)-1 -> -0.11695652
D74: =Holdings!C28 -> Caterpillar | F74: =Holdings!E28 -> 41222 | J74: =Holdings!H28 -> 83 | L74: =Holdings!I28 -> 85.14 | M74: =L74/J74-1 -> 0.025783133 | R74: =Holdings!C40 -> Stryker | T74: =Holdings!E40 -> 41243 | X74: =Holdings!H40 -> 54.07 | Y74: 21.71 | Z74: =Holdings!I40 -> 67.72 | AA74: =(Z74/X74)-1 -> 0.25245053
D75: =Holdings!C29 -> Natural Grocers | F75: =Holdings!E29 -> 41243 | J75: =Holdings!H29 -> 19.49 | L75: =Holdings!I29 -> 27.69 | M75: =L75/J75-1 -> 0.42072858 | R75: =Holdings!C41 -> PowerShares | T75: =Holdings!E41 -> 41299 | X75: =Holdings!H41 -> 14.86 | Y75: 21.71 | Z75: =Holdings!I41 -> 14.29 | AA75: =(Z75/X75)-1 -> -0.038358008
D76: =Holdings!C30 -> Yahoo | F76: =Holdings!E30 -> 41333 | J76: =Holdings!H30 -> 21.75 | L76: =Holdings!I30 -> 26.37 | M76: =L76/J76-1 -> 0.21241379 | R76: =Holdings!C42 -> PetroChina | T76: =Holdings!E42 -> 41355 | X76: =Holdings!H42 -> 131.71 | Y76: 21.71 | Z76: =Holdings!I42 -> 110.05 | AA76: =(Z76/X76)-1 -> -0.16445221
D77: =Holdings!C31 -> YRC Worldwide | F77: =Holdings!E31 -> 41355 | J77: =Holdings!H31 -> 8.61 | L77: =Holdings!I31 -> 22.6 | M77: =L77/J77-1 -> 1.6248548 | R77: =Holdings!C43 -> UPS | T77: =Holdings!E43 -> 41355 | X77: =Holdings!H43 -> 83.3 | Z77: =Holdings!I43 -> 86.32 | AA77: =(Z77/X77)-1 -> 0.036254502
D78: =Holdings!C32 -> Delta Airlines | F78: =Holdings!E32 -> 41362 | J78: =Holdings!H32 -> 16.48 | L78: =Holdings!I32 -> 18.71 | M78: =L78/J78-1 -> 0.13531553 | R78: =Holdings!C44 -> Ford | T78: =Holdings!E44 -> 41362 | X78: =Holdings!H44 -> 13.01 | Z78: =Holdings!I44 -> 15.58 | AA78: =(Z78/X78)-1 -> 0.19754035
D79: =Holdings!C33 -> Cemex | F79: =Holdings!E33 -> 41416 | J79: =Holdings!H33 -> 11.57 | L79: =Holdings!I33 -> 10.55 | M79: =L79/J79-1 -> -0.088159032 | R79: =Holdings!C45 -> Tetra Tech | T79: =Holdings!E45 -> 41416 | X79: =Holdings!H45 -> 28.06 | Z79: =Holdings!I45 -> 26.68 | AA79: =(Z79/X79)-1 -> -0.049180328
D80: =Holdings!C34 -> Immersion | F80: =Holdings!E34 -> 41424 | J80: =Holdings!H34 -> 15.04 | L80: =Holdings!I34 -> 14.91 | M80: =L80/J80-1 -> -0.008643617 | R80: =Holdings!C46 -> Wal Mart de Mexico | T80: =Holdings!E46 -> 41416 | X80: =Holdings!H46 -> 28.75 | Z80: =Holdings!I46 -> 28.65 | AA80: =(Z80/X80)-1 -> -0.0034782609
D81: =Holdings!C35 -> Intel | F81: =Holdings!E35 -> 41438 | J81: =Holdings!H35 -> 24.72 | L81: =Holdings!I35 -> 24.99 | M81: =L81/J81-1 -> 0.01092233 | R81: =Holdings!C47 -> Itron | T81: =Holdings!E47 -> 41424 | X81: =Holdings!H47 -> 41.2 | Z81: =Holdings!I47 -> 42.52 | AA81: =(Z81/X81)-1 -> 0.032038835
R82: =Holdings!C48 -> HCP | T82: =Holdings!E48 -> 41438 | X82: =Holdings!H48 -> 45.66 | Z82: =Holdings!I48 -> 45.99 | AA82: =(Z82/X82)-1 -> 0.0072273325
R83: =Holdings!C49 -> Qualcom | T83: =Holdings!E49 -> 41438 | X83: =Holdings!H49 -> 61.03 | Z83: =Holdings!I49 -> 61.96 | AA83: =(Z83/X83)-1 -> 0.015238407
R84: =Holdings!C50 -> Xerox | T84: =Holdings!E50 -> 41438 | X84: =Holdings!H50 -> 8.86 | Z84: =Holdings!I50 -> 9.1 | AA84: =(Z84/X84)-1 -> 0.027088036
C86: Proposed Buys This Year That Did Not Pass | Q86: Proposed Sells This Year That Did Not Pass
F88: Date Pitched | J88: Pitch Price | L88: Current Price | M88: Change* | T88: Date Pitched | X88: Pitch Price | Z88: Current Price | AA88: Change*
D89: =Holdings!$C$53 -> Disney | F89: =Holdings!$E$53 -> 41228 | J89: =Holdings!$H$53 -> 47.47 | L89: =Holdings!$I$53 -> 64.3 | M89: =(L89/J89)-1 -> 0.35453971 | R89: =Holdings!C57 -> Ford | T89: =Holdings!E57 -> 41354 | X89: =Holdings!H57 -> 13.27 | Z89: =Holdings!I57 -> 15.58 | AA89: =(Z89/X89)-1 -> 0.17407687
D90: Phillips 66 | F90: =Holdings!$E$54 -> 41299 | J90: =Holdings!$H$54 -> 56.12 | L90: =Holdings!$I$54 -> 64.51 | M90: =(L90/J90)-1 -> 0.14950107
C93: *Only incorporates change in price; Does not include commission | AF93: invest@mail.gvsu.edu | AH93: http://gvsu.edu/invest

Sheet Holdings
C3: Name | D3: Ticker | E3: Price | F3: Paid | G3: Shares | H3: Value | I3: Initial Cost | J3: Value on 9/6/12 | K3: Value on 4/25/13 | L3: Value 1 Week Ago | N3: Total Gain $ | O3: Total Gain | P3: School Year | Q3: Summer | R3: 1 Week | S3: Today | T3: Sector | U3: Portfolio Weight | V3: Market Cap (Billions) | X3: PE | Y3: EPS | AC3: % of Weekly Portfolio Return | AD3: % of Daily Portfolio Return
C4: Cash | E4: 1 | F4: 1 | G4: 8114.57 | H4: =E4*G4 -> 8114.57 | I4: 2029.73 | J4: 4804 | K4: 4361.76 | L4: 4444.5729 | T4: Cash | U4: =H4/$H$22 -> 0.15858213 | V4: 0 | X4: 0 | Y4: 0 | AC4: =(0.01/365)*U4 -> 4.344716e-06 | AD4: =(0.01/365)*U4 -> 4.344716e-06
C5: Berkshire Hathaway | D5: ='Holdings Pull Sheet'!B16 -> BRK.B | E5: ='Holdings Pull Sheet'!F16 -> 114.99 | F5: 77.89 | G5: 26 | H5: =G5*E5 -> 2989.74 | I5: 2035.09 | J5: 2248.22 | K5: 2794.22 | L5: 2940.6 | N5: =H5-I5 -> 954.65 | O5: =(H5/I5)-1 -> 0.46909473 | P5: =(H5/J5)-1 -> 0.32982535 | Q5: =(H5/K5)-1 -> 0.069973016 | R5: =(H5/L5)-1 -> 0.016710875 | S5: =('Holdings Pull Sheet'!F16/'Holdings Pull Sheet'!G16)-1 -> 0.018061089 | T5: Financial | U5: =H5/$H$22 -> 0.058428154 | V5: ='Holdings Pull Sheet'!O16/1000000000 -> 283.48254 | W5: =IF(V5<2,"Small", IF(V5<10, "Mid", IF(V5>10, "Large"))) -> Large | X5: ='Holdings Pull Sheet'!Q16 -> 17 | Y5: ='Holdings Pull Sheet'!P16 -> 9988.97 | AC5: =U5*R5 -> 0.0009763856 | AD5: =U5*S5 -> 0.0010552761
C6: BlackRock Global | D6: ='Holdings Pull Sheet'!B17 -> MCLOX | E6: ='Holdings Pull Sheet'!F17 -> 19.39 | F6: 17.23 | G6: 89.25 | H6: =G6*E6 -> 1730.5575 | I6: 1543.42 | J6: 1602.0455 | K6: 1735.02 | L6: 1723.4175 | N6: =H6-I6 -> 187.1375 | O6: =(H6/I6)-1 -> 0.12124859 | P6: =(H6/J6)-1 -> 0.080217474 | Q6: =(H6/K6)-1 -> -0.0025720165 | R6: =(H6/L6)-1 -> 0.0041429311 | S6: =('Holdings Pull Sheet'!F17/'Holdings Pull Sheet'!G17)-1 -> 0.0072727273 | T6: Misc | U6: =H6/$H$22 -> 0.033820092 | V6: ='Holdings Pull Sheet'!O17/1000000000 -> 0 | W6: =IF(V6<2,"Small", IF(V6<10, "Mid", IF(V6>10, "Large"))) -> Small | X6: ='Holdings Pull Sheet'!Q17 -> 0 | Y6: ='Holdings Pull Sheet'!P17 -> 0 | AC6: =U6*R6 -> 0.00014011431 | AD6: =U6*S6 -> 0.0002459643
C7: Caterpillar | D7: ='Holdings Pull Sheet'!B18 -> CAT | E7: ='Holdings Pull Sheet'!F18 -> 85.14 | F7: 83 | G7: 15.172 | H7: =G7*E7 -> 1291.7441 | I7: 1254.95 | J7: 1245 | K7: 1274.6643 | L7: 1274.448 | N7: =H7-I7 -> 36.79408 | O7: =(H7/I7)-1 -> 0.02931916 | P7: =(H7/J7)-1 -> 0.037545446 | Q7: =(H7/K7)-1 -> 0.01339941 | R7: =(H7/L7)-1 -> 0.013571429 | S7: =('Holdings Pull Sheet'!F18/'Holdings Pull Sheet'!G18)-1 -> 0.023194328 | T7: Industrials | U7: =H7/$H$22 -> 0.02524441 | V7: ='Holdings Pull Sheet'!O18/1000000000 -> 55.978264 | W7: =IF(V7<2,"Small", IF(V7<10, "Mid", IF(V7>10, "Large"))) -> Large | X7: ='Holdings Pull Sheet'!Q18 -> 11.2 | Y7: ='Holdings Pull Sheet'!P18 -> 7.43 | AC7: =U7*R7 -> 0.00034260271 | AD7: =U7*S7 -> 0.00058552712
C8: Cemex | D8: ='Holdings Pull Sheet'!B19 -> CX | E8: ='Holdings Pull Sheet'!F19 -> 10.55 | F8: 11.57 | G8: 200 | H8: =G8*E8 -> 2110 | I8: 2314.62 | J8: 2314.62 | K8: 2314.62 | L8: 2168 | N8: =H8-I8 -> -204.62 | O8: =(H8/I8)-1 -> -0.08840328 | P8: =(H8/J8)-1 -> -0.08840328 | Q8: =(H8/K8)-1 -> -0.08840328 | R8: =(H8/L8)-1 -> -0.026752768 | S8: =('Holdings Pull Sheet'!F19/'Holdings Pull Sheet'!G19)-1 -> 0.029268293 | T8: Industrials | U8: =H8/$H$22 -> 0.041235494 | V8: ='Holdings Pull Sheet'!O19/1000000000 -> 11.867495 | W8: =IF(V8<2,"Small", IF(V8<10, "Mid", IF(V8>10, "Large"))) -> Large | X8: ='Holdings Pull Sheet'!Q19 -> 0 | Y8: ='Holdings Pull Sheet'!P19 -> -1.03 | AC8: =U8*R8 -> -0.0011031636 | AD8: =U8*S8 -> 0.0012068925
C9: Cisco | D9: ='Holdings Pull Sheet'!B20 -> CSCO | E9: ='Holdings Pull Sheet'!F20 -> 24.35 | F9: 18.48 | G9: 68.058 | H9: =G9*E9 -> 1657.2123 | I9: 1248.11 | J9: 1311.6534 | K9: 1393.2413 | L9: 1670.8239 | N9: =H9-I9 -> 409.1023 | O9: =(H9/I9)-1 -> 0.32777744 | P9: =(H9/J9)-1 -> 0.26345295 | Q9: =(H9/K9)-1 -> 0.1894654 | R9: =(H9/L9)-1 -> -0.0081466395 | S9: =('Holdings Pull Sheet'!F20/'Holdings Pull Sheet'!G20)-1 -> 0.015006253 | T9: Information Technology | U9: =H9/$H$22 -> 0.032386715 | V9: ='Holdings Pull Sheet'!O20/1000000000 -> 130.13458 | W9: =IF(V9<2,"Small", IF(V9<10, "Mid", IF(V9>10, "Large"))) -> Large | X9: ='Holdings Pull Sheet'!Q20 -> 13.4 | Y9: ='Holdings Pull Sheet'!P20 -> 1.8 | AC9: =U9*R9 -> -0.00026384289 | AD9: =U9*S9 -> 0.00048600322
C10: Delta Airlines | D10: ='Holdings Pull Sheet'!B21 -> DAL | E10: ='Holdings Pull Sheet'!F21 -> 18.71 | F10: 16.58 | G10: 150 | H10: =G10*E10 -> 2806.5 | I10: 2481.99 | J10: 2481.99 | K10: 2443.5 | L10: 2623.5 | N10: =H10-I10 -> 324.51 | O10: =(H10/I10)-1 -> 0.13074589 | P10: =(H10/J10)-1 -> 0.13074589 | Q10: =(H10/K10)-1 -> 0.1485574 | R10: =(H10/L10)-1 -> 0.069754145 | S10: =('Holdings Pull Sheet'!F21/'Holdings Pull Sheet'!G21)-1 -> 0.03541782 | T10: Consumer Discretionary | U10: =H10/$H$22 -> 0.054847115 | V10: ='Holdings Pull Sheet'!O21/1000000000 -> 16.02596 | W10: =IF(V10<2,"Small", IF(V10<10, "Mid", IF(V10>10, "Large"))) -> Large | X10: ='Holdings Pull Sheet'!Q21 -> 17.6 | Y10: ='Holdings Pull Sheet'!P21 -> 1.05 | AC10: =U10*R10 -> 0.0038258137 | AD10: =U10*S10 -> 0.0019425652
C11: Gentex | D11: ='Holdings Pull Sheet'!B22 -> GNTX | E11: ='Holdings Pull Sheet'!F22 -> 23.27 | F11: 16.4 | G11: 93.173 | H11: =G11*E11 -> 2168.1357 | I11: 1502.35 | J11: 1669.6919 | K11: 2103.5478 | L11: 2134.5934 | N11: =H11-I11 -> 665.78571 | O11: =(H11/I11)-1 -> 0.44316285 | P11: =(H11/J11)-1 -> 0.2985244 | Q11: =(H11/K11)-1 -> 0.03070425 | R11: =(H11/L11)-1 -> 0.015713662 | S11: =('Holdings Pull Sheet'!F22/'Holdings Pull Sheet'!G22)-1 -> 0.028735632 | T11: Consumer Discretionary | U11: =H11/$H$22 -> 0.042371634 | V11: ='Holdings Pull Sheet'!O22/1000000000 -> 3.3411997 | W11: =IF(V11<2,"Small", IF(V11<10, "Mid", IF(V11>10, "Large"))) -> Mid | X11: ='Holdings Pull Sheet'!Q22 -> 19.5 | Y11: ='Holdings Pull Sheet'!P22 -> 1.17 | AC11: =U11*R11 -> 0.00066581354 | AD11: =U11*S11 -> 0.0012175757
C12: Home Depot | D12: ='Holdings Pull Sheet'!B23 -> HD | E12: ='Holdings Pull Sheet'!F23 -> 76.53 | F12: 28.6 | G12: 59.37 | H12: =G12*E12 -> 4543.5861 | I12: 1668.75 | J12: 3371.3144 | K12: 4331.7648 | L12: 4586.9262 | N12: =H12-I12 -> 2874.8361 | O12: =(H12/I12)-1 -> 1.7227482 | P12: =(H12/J12)-1 -> 0.34771947 | Q12: =(H12/K12)-1 -> 0.048899539 | R12: =(H12/L12)-1 -> -0.0094486151 | S12: =('Holdings Pull Sheet'!F23/'Holdings Pull Sheet'!G23)-1 -> 0.0017015707 | T12: Consumer Discretionary | U12: =H12/$H$22 -> 0.088794795 | V12: ='Holdings Pull Sheet'!O23/1000000000 -> 111.79472 | W12: =IF(V12<2,"Small", IF(V12<10, "Mid", IF(V12>10, "Large"))) -> Large | X12: ='Holdings Pull Sheet'!Q23 -> 24.6 | Y12: ='Holdings Pull Sheet'!P23 -> 3.16 | AC12: =U12*R12 -> -0.00083898784 | AD12: =U12*S12 -> 0.00015109062
C13: Immersion | D13: ='Holdings Pull Sheet'!B24 -> IMMR | E13: ='Holdings Pull Sheet'!F24 -> 14.91 | F13: 15.04 | G13: 135 | H13: =G13*E13 -> 2012.85 | I13: 2031.3 | J13: 2031.3 | K13: 2031.3 | L13: 1960.2 | N13: =H13-I13 -> -18.45 | O13: =(H13/I13)-1 -> -0.0090828533 | P13: =(H13/J13)-1 -> -0.0090828533 | Q13: =(H13/K13)-1 -> -0.0090828533 | R13: =(H13/L13)-1 -> 0.026859504 | S13: =('Holdings Pull Sheet'!F24/'Holdings Pull Sheet'!G24)-1 -> 0.044849334 | T13: Information Technology | U13: =H13/$H$22 -> 0.039336902 | V13: ='Holdings Pull Sheet'!O24/1000000000 -> 0.41595396 | W13: =IF(V13<2,"Small", IF(V13<10, "Mid", IF(V13>10, "Large"))) -> Small | X13: ='Holdings Pull Sheet'!Q24 -> 0 | Y13: ='Holdings Pull Sheet'!P24 -> -0.11 | AC13: =U13*R13 -> 0.0010565697 | AD13: =U13*S13 -> 0.0017642339
C14: Intel | D14: ='Holdings Pull Sheet'!B25 -> INTC | E14: ='Holdings Pull Sheet'!F25 -> 24.99 | F14: 24.72 | G14: 112 | H14: =G14*E14 -> 2798.88 | I14: 2768.56 | J14: 2768.56 | K14: 2768.56 | L14: 2768.56 | N14: =H14-I14 -> 30.32 | O14: =(H14/I14)-1 -> 0.010951542 | P14: =(H14/J14)-1 -> 0.010951542 | Q14: =(H14/K14)-1 -> 0.010951542 | R14: =(H14/L14)-1 -> 0.010951542 | S14: =('Holdings Pull Sheet'!F25/'Holdings Pull Sheet'!G25)-1 -> 0.021668029 | T14: Information Technology | U14: =H14/$H$22 -> 0.054698199 | V14: ='Holdings Pull Sheet'!O25/1000000000 -> 124.22529 | W14: =IF(V14<2,"Small", IF(V14<10, "Mid", IF(V14>10, "Large"))) -> Large | X14: ='Holdings Pull Sheet'!Q25 -> 12.3 | Y14: ='Holdings Pull Sheet'!P25 -> 2 | AC14: =U14*R14 -> 0.0005990296 | AD14: =U14*S14 -> 0.0011852022
C15: Medtronic | D15: ='Holdings Pull Sheet'!B26 -> MDT | E15: ='Holdings Pull Sheet'!F26 -> 52.78 | F15: 47.17 | G15: 28.376 | H15: =G15*E15 -> 1497.6853 | I15: 1330.71 | J15: 1158.5436 | K15: 1327.1396 | L15: 1460.7965 | N15: =H15-I15 -> 166.97528 | O15: =(H15/I15)-1 -> 0.12547834 | P15: =(H15/J15)-1 -> 0.29273106 | Q15: =(H15/K15)-1 -> 0.12850624 | R15: =(H15/L15)-1 -> 0.025252525 | S15: =('Holdings Pull Sheet'!F26/'Holdings Pull Sheet'!G26)-1 -> 0.022670025 | T15: Healthcare | U15: =H15/$H$22 -> 0.029269096 | V15: ='Holdings Pull Sheet'!O26/1000000000 -> 53.508679 | W15: =IF(V15<2,"Small", IF(V15<10, "Mid", IF(V15>10, "Large"))) -> Large | X15: ='Holdings Pull Sheet'!Q26 -> 15.4 | Y15: ='Holdings Pull Sheet'!P26 -> 3.38 | AC15: =U15*R15 -> 0.00073911858 | AD15: =U15*S15 -> 0.00066353114
C16: Natural Grocers | D16: ='Holdings Pull Sheet'!B27 -> NGVC | E16: ='Holdings Pull Sheet'!F27 -> 27.69 | F16: 19.49 | G16: 75 | H16: =G16*E16 -> 2076.75 | I16: 1471.7 | J16: 1471.7 | K16: 1865.25 | L16: 2005.5 | N16: =H16-I16 -> 605.05 | O16: =(H16/I16)-1 -> 0.41112319 | P16: =(H16/J16)-1 -> 0.41112319 | Q16: =(H16/K16)-1 -> 0.11338963 | R16: =(H16/L16)-1 -> 0.0355273 | S16: =('Holdings Pull Sheet'!F26/'Holdings Pull Sheet'!G26)-1 -> 0.022670025 | T16: Consumer Staples | U16: =H16/$H$22 -> 0.040585693 | V16: ='Holdings Pull Sheet'!O27/1000000000 -> 0.62030918 | W16: =IF(V16<2,"Small", IF(V16<10, "Mid", IF(V16>10, "Large"))) -> Small | X16: ='Holdings Pull Sheet'!Q27 -> 5.2 | Y16: ='Holdings Pull Sheet'!P27 -> 5.31 | AC16: =U16*R16 -> 0.0014419001 | AD16: =U16*S16 -> 0.00092007868
C17: Tutor Perini | D17: ='Holdings Pull Sheet'!B28 -> TPC | E17: ='Holdings Pull Sheet'!F28 -> 17.43 | F17: 13.7612 | G17: 200 | H17: =G17*E17 -> 3486 | I17: 2752.24 | J17: 1874.45 | K17: 2488.5 | L17: 3470 | N17: =H17-I17 -> 733.76 | O17: =(H17/I17)-1 -> 0.26660466 | P17: =((H17-896.49)/J17)-1 -> 0.38147723 | Q17: =((H17-896.49)/K17)-1 -> 0.040590717 | R17: =(H17/L17)-1 -> 0.004610951 | S17: =('Holdings Pull Sheet'!F27/'Holdings Pull Sheet'!G27)-1 -> 0.013914317 | T17: Industrials | U17: =H17/$H$22 -> 0.068126508 | V17: ='Holdings Pull Sheet'!O28/1000000000 -> 0.82924429 | W17: =IF(V17<2,"Small", IF(V17<10, "Mid", IF(V17>10, "Large"))) -> Small | X17: ='Holdings Pull Sheet'!Q28 -> 0 | Y17: ='Holdings Pull Sheet'!P28 -> -5.3 | AC17: =U17*R17 -> 0.00031412799 | AD17: =U17*S17 -> 0.00094793383
C18: Tyson Foods | D18: ='Holdings Pull Sheet'!B29 -> TSN | E18: ='Holdings Pull Sheet'!F29 -> 25.71 | F18: 16.65 | G18: 100.97 | H18: =G18*E18 -> 2595.9387 | I18: 1674.95 | J18: 1665 | K18: 2512.1336 | L18: 2505.0657 | N18: =H18-I18 -> 920.9887 | O18: =(H18/I18)-1 -> 0.54986041 | P18: =(H18/J18)-1 -> 0.55912234 | Q18: =(H18/K18)-1 -> 0.033360129 | R18: =(H18/L18)-1 -> 0.036275695 | S18: =('Holdings Pull Sheet'!F28/'Holdings Pull Sheet'!G28)-1 -> 0.034421365 | T18: Consumer Staples | U18: =H18/$H$22 -> 0.05073214 | V18: ='Holdings Pull Sheet'!O29/1000000000 -> 9.1229926 | W18: =IF(V18<2,"Small", IF(V18<10, "Mid", IF(V18>10, "Large"))) -> Mid | X18: ='Holdings Pull Sheet'!Q29 -> 17.5 | Y18: ='Holdings Pull Sheet'!P29 -> 1.45 | AC18: =U18*R18 -> 0.0018403436 | AD18: =U18*S18 -> 0.0017462695
C19: Wells Fargo | D19: ='Holdings Pull Sheet'!B30 -> WFC | E19: ='Holdings Pull Sheet'!F30 -> 40.94 | F19: 23.42 | G19: 52.085 | H19: =G19*E19 -> 2132.3599 | I19: 1204.37 | J19: 1778.2684 | K19: 1961.7592 | L19: 2120.9012 | N19: =H19-I19 -> 927.9899 | O19: =(H19/I19)-1 -> 0.77051894 | P19: =(H19/J19)-1 -> 0.19912148 | Q19: =(H19/K19)-1 -> 0.086963142 | R19: =(H19/L19)-1 -> 0.0054027505 | S19: =('Holdings Pull Sheet'!F29/'Holdings Pull Sheet'!G29)-1 -> 0.01140834 | T19: Financial | U19: =H19/$H$22 -> 0.041672471 | V19: ='Holdings Pull Sheet'!O30/1000000000 -> 216.83408 | W19: =IF(V19<2,"Small", IF(V19<10, "Mid", IF(V19>10, "Large"))) -> Large | X19: ='Holdings Pull Sheet'!Q30 -> 11.5 | Y19: ='Holdings Pull Sheet'!P30 -> 3.53 | AC19: =U19*R19 -> 0.00022514596 | AD19: =U19*S19 -> 0.00047541371
C20: Yahoo | D20: ='Holdings Pull Sheet'!B31 -> YHOO | E20: ='Holdings Pull Sheet'!F31 -> 26.37 | F20: 21.75 | G20: 100 | H20: =G20*E20 -> 2637 | I20: 2174.99 | J20: 2174.99 | K20: 2520 | L20: 2621 | N20: =H20-I20 -> 462.01 | O20: =(H20/I20)-1 -> 0.21241937 | P20: =(H20/J20)-1 -> 0.21241937 | Q20: =(H20/K20)-1 -> 0.046428571 | R20: =(H20/L20)-1 -> 0.0061045403 | S20: =('Holdings Pull Sheet'!F30/'Holdings Pull Sheet'!G30)-1 -> 0.016637696 | T20: Information Technology | U20: =H20/$H$22 -> 0.051534596 | V20: ='Holdings Pull Sheet'!O31/1000000000 -> 28.549086 | W20: =IF(V20<2,"Small", IF(V20<10, "Mid", IF(V20>10, "Large"))) -> Large | X20: ='Holdings Pull Sheet'!Q31 -> 7.7 | Y20: ='Holdings Pull Sheet'!P31 -> 3.41 | AC20: =U20*R20 -> 0.00031459502 | AD20: =U20*S20 -> 0.00085741692
C21: YRC Worldwide | D21: ='Holdings Pull Sheet'!B32 -> YRCW | E21: ='Holdings Pull Sheet'!F32 -> 22.6 | F21: 8.51 | G21: 200 | H21: =G21*E21 -> 4520 | I21: 1722 | J21: 1722 | K21: 1418 | L21: 3856 | N21: =H21-I21 -> 2798 | O21: =(H21/I21)-1 -> 1.6248548 | P21: =(H21/J21)-1 -> 1.6248548 | Q21: =(H21/K21)-1 -> 2.1875882 | R21: =(H21/L21)-1 -> 0.17219917 | S21: =('Holdings Pull Sheet'!F31/'Holdings Pull Sheet'!G31)-1 -> 0.018539977 | T21: Industrials | U21: =H21/$H$22 -> 0.088333854 | V21: ='Holdings Pull Sheet'!O32/1000000000 -> 0.21236904 | W21: =IF(V21<2,"Small", IF(V21<10, "Mid", IF(V21>10, "Large"))) -> Small | X21: ='Holdings Pull Sheet'!Q32 -> 0 | Y21: ='Holdings Pull Sheet'!P32 -> -14.95 | AC21: =U21*R21 -> 0.015211016 | AD21: =U21*S21 -> 0.0016377076
H22: =SUM(H4:H21) -> 51169.51 | I22: =SUM(I4:I21) -> 33209.83 | J22: 40381.87 | K22: 46519.794 | L22: 50295.736 | N22: =(H22-Data!D3) -> 28313.66 | O22: =(H22/Data!D3)-1 -> 1.2387927 | P22: =(H22/J22)-1 -> 0.26714065 | Q22: =(H22/K22)-1 -> 0.09995134 | R22: =(H22/L22)-1 -> 0.017372717 | S22: =AD22 -> 0.017093027 | U22: =SUM(U4:U21) -> 1 | AC22: =SUM(AC4:AC21) -> 0.025490927 | AD22: =SUM(AD4:AD21) -> 0.017093027
C25: Bought this Year | E25: Date Bought | H25: Buy Price | I25: Current Price | J25: % Change
C26: Tyson Foods | D26: TSN | E26: 41173 | H26: 16.65 | I26: ='Holdings Pull Sheet'!F29 -> 25.71 | J26: =(I26/H26)-1 -> 0.54414414
C27: Tutor Perini | D27: TPC | E27: 41215 | H27: 12.43 | I27: ='Holdings Pull Sheet'!F28 -> 17.43 | J27: =(I27/H27)-1 -> 0.40225261
C28: Caterpillar | D28: CAT | E28: 41222 | H28: 83 | I28: ='Holdings Pull Sheet'!F18 -> 85.14 | J28: =(I28/H28)-1 -> 0.025783133
C29: Natural Grocers | D29: NGVC | E29: 41243 | H29: 19.49 | I29: ='Holdings Pull Sheet'!F27 -> 27.69 | J29: =(I29/H29)-1 -> 0.42072858
C30: Yahoo | D30: YHOO | E30: 41333 | H30: 21.75 | I30: ='Holdings Pull Sheet'!F31 -> 26.37 | J30: =(I30/H30)-1 -> 0.21241379
C31: YRC Worldwide | D31: YRCW | E31: 41355 | H31: 8.61 | I31: ='Holdings Pull Sheet'!F32 -> 22.6 | J31: =(I31/H31)-1 -> 1.6248548
C32: Delta Airlines | D32: DAL | E32: 41362 | H32: 16.48 | I32: ='Holdings Pull Sheet'!F21 -> 18.71 | J32: =(I32/H32)-1 -> 0.13531553
C33: Cemex | D33: CX | E33: 41416 | H33: 11.57 | I33: ='Holdings Pull Sheet'!F19 -> 10.55 | J33: =(I33/H33)-1 -> -0.088159032
C34: Immersion | D34: IMMR | E34: 41424 | H34: 15.04 | I34: ='Holdings Pull Sheet'!F24 -> 14.91 | J34: =(I34/H34)-1 -> -0.008643617
C35: Intel | D35: INTC | E35: 41438 | H35: 24.72 | I35: ='Holdings Pull Sheet'!F25 -> 24.99 | J35: =(I35/H35)-1 -> 0.01092233
C37: Sold this Year | E37: Date Sold | H37: Sell Price | I37: Current Price | J37: % Change
C38: Vale | D38: VALE | E38: 41166 | H38: 19.71 | I38: ='Holdings Pull Sheet'!F34 -> 14.47 | J38: =(I38/H38)-1 -> -0.2658549
C39: CPFL Energia | D39: CPL | E39: 41215 | H39: 23 | I39: ='Holdings Pull Sheet'!F35 -> 20.31 | J39: =(I39/H39)-1 -> -0.11695652
C40: Stryker | D40: SYK | E40: 41243 | H40: 54.07 | I40: ='Holdings Pull Sheet'!F36 -> 67.72 | J40: =(I40/H40)-1 -> 0.25245053
C41: PowerShares | D41: PGX | E41: 41299 | H41: 14.86 | I41: ='Holdings Pull Sheet'!F37 -> 14.29 | J41: =(I41/H41)-1 -> -0.038358008
C42: PetroChina | D42: PTR | E42: 41355 | H42: 131.71 | I42: ='Holdings Pull Sheet'!F38 -> 110.05 | J42: =(I42/H42)-1 -> -0.16445221
C43: UPS | D43: UPS | E43: 41355 | H43: 83.3 | I43: ='Holdings Pull Sheet'!F39 -> 86.32 | J43: =(I43/H43)-1 -> 0.036254502
C44: Ford | D44: F | E44: 41362 | H44: 13.01 | I44: ='Holdings Pull Sheet'!F40 -> 15.58 | J44: =(I44/H44)-1 -> 0.19754035
C45: Tetra Tech | D45: TTEK | E45: 41416 | H45: 28.06 | I45: ='Holdings Pull Sheet'!F41 -> 26.68 | J45: =(I45/H45)-1 -> -0.049180328
C46: Wal Mart de Mexico | D46: WMMVY | E46: 41416 | H46: 28.75 | I46: ='Holdings Pull Sheet'!F42 -> 28.65 | J46: =(I46/H46)-1 -> -0.0034782609
C47: Itron | D47: ITRI | E47: 41424 | H47: 41.2 | I47: ='Holdings Pull Sheet'!F43 -> 42.52 | J47: =(I47/H47)-1 -> 0.032038835
C48: HCP | D48: HCP | E48: 41438 | H48: 45.66 | I48: ='Holdings Pull Sheet'!F44 -> 45.99 | J48: =(I48/H48)-1 -> 0.0072273325
C49: Qualcom | D49: QCOM | E49: 41438 | H49: 61.03 | I49: ='Holdings Pull Sheet'!F45 -> 61.96 | J49: =(I49/H49)-1 -> 0.015238407
C50: Xerox | D50: XRX | E50: 41438 | H50: 8.86 | I50: ='Holdings Pull Sheet'!F46 -> 9.1 | J50: =(I50/H50)-1 -> 0.027088036
C52: Proposed Buys This Year | E52: Date Pitched | H52: Pitch Price | I52: Current Price | J52: % Change
C53: Disney | D53: DIS | E53: 41228 | H53: 47.47 | I53: ='Holdings Pull Sheet'!F47 -> 64.3 | J53: =(I53/H53)-1 -> 0.35453971
C54: Phillips 66 | D54: PSX | E54: 41299 | H54: 56.12 | I54: ='Holdings Pull Sheet'!F48 -> 64.51 | J54: =(I54/H54)-1 -> 0.14950107
C56: Proposed Sells this Year | E56: Date Pitched | H56: Pitch Price | I56: Current Price | J56: % Change
C57: Ford | D57: F | E57: 41354 | H57: 13.27 | I57: ='Holdings Pull Sheet'!F40 -> 15.58 | J57: =(I57/H57)-1 -> 0.17407687

Sheet 2012 Holiday Performance
C3: Name | D3: Ticker | E3: % Change | F3: Current Price | G3: Shares | H3: 1 Week Ago | I3: Today's Value
C4: =Holdings!C16 -> Natural Grocers | D4: ='Holdings Pull Sheet'!B27 -> NGVC | E4: =I4/H4-1 -> 0.0355273 | F4: =Holdings!E16 -> 27.69 | G4: =Holdings!G16 -> 75 | H4: =Holdings!L16 -> 2005.5 | I4: =Holdings!H16 -> 2076.75
C5: =Holdings!C19 -> Wells Fargo | D5: ='Holdings Pull Sheet'!B28 -> TPC | E5: =I5/H5-1 -> 0.004610951 | F5: =Holdings!E19 -> 40.94 | G5: =Holdings!G17 -> 200 | H5: =Holdings!L17 -> 3470 | I5: =Holdings!H17 -> 3486
C6: =Holdings!#REF! -> #REF! | D6: ='Holdings Pull Sheet'!B31 -> YHOO | E6: =I6/H6-1 -> 0.0061045403 | F6: =Holdings!#REF! -> #REF! | G6: =Holdings!G20 -> 100 | H6: =Holdings!L20 -> 2621 | I6: =Holdings!H20 -> 2637
C7: =Holdings!#REF! -> #REF! | D7: ='Holdings Pull Sheet'!B42 -> WMMVY | E7: =I7/H7-1 -> #REF! | F7: =Holdings!E21 -> 22.6 | G7: =Holdings!#REF! -> #REF! | H7: =Holdings!#REF! -> #REF! | I7: =Holdings!#REF! -> #REF!
C8: =Holdings!#REF! -> #REF! | D8: ='Holdings Pull Sheet'!B44 -> HCP | E8: =I8/H8-1 -> #REF! | F8: =Holdings!E11 -> 23.27 | G8: =Holdings!#REF! -> #REF! | H8: =Holdings!#REF! -> #REF! | I8: =Holdings!#REF! -> #REF!
C9: =Holdings!C15 -> Medtronic | D9: ='Holdings Pull Sheet'!B26 -> MDT | E9: =I9/H9-1 -> 0.025252525 | F9: =Holdings!E14 -> 24.99 | G9: =Holdings!G15 -> 28.376 | H9: =Holdings!L15 -> 1460.7965 | I9: =Holdings!H15 -> 1497.6853
C10: =Holdings!C13 -> Immersion | D10: ='Holdings Pull Sheet'!B24 -> IMMR | E10: =I10/H10-1 -> 0.026859504 | F10: =Holdings!E13 -> 14.91 | G10: =Holdings!G13 -> 135 | H10: =Holdings!L13 -> 1960.2 | I10: =Holdings!H13 -> 2012.85
C11: =Holdings!#REF! -> #REF! | D11: ='Holdings Pull Sheet'!B41 -> TTEK | E11: =I11/H11-1 -> #REF! | F11: =Holdings!E18 -> 25.71 | G11: =Holdings!#REF! -> #REF! | H11: =Holdings!#REF! -> #REF! | I11: =Holdings!#REF! -> #REF!
C12: =Holdings!C21 -> YRC Worldwide | D12: ='Holdings Pull Sheet'!B30 -> WFC | E12: =I12/H12-1 -> 0.0054027505 | F12: =Holdings!E22 -> 0 | G12: =Holdings!G19 -> 52.085 | H12: =Holdings!L19 -> 2120.9012 | I12: =Holdings!H19 -> 2132.3599
C13: =Holdings!C18 -> Tyson Foods | D13: ='Holdings Pull Sheet'!B45 -> QCOM | E13: =I13/H13-1 -> #REF! | F13: =Holdings!E17 -> 17.43 | G13: =Holdings!#REF! -> #REF! | H13: =Holdings!#REF! -> #REF! | I13: =Holdings!#REF! -> #REF!
C14: =Holdings!C20 -> Yahoo | D14: ='Holdings Pull Sheet'!B29 -> TSN | E14: =I14/H14-1 -> 0.036275695 | F14: =Holdings!E20 -> 26.37 | G14: =Holdings!G18 -> 100.97 | H14: =Holdings!L18 -> 2505.0657 | I14: =Holdings!H18 -> 2595.9387
C15: =Holdings!C11 -> Gentex | D15: ='Holdings Pull Sheet'!B22 -> GNTX | E15: =I15/H15-1 -> 0.015713662 | F15: =Holdings!E10 -> 18.71 | G15: =Holdings!G11 -> 93.173 | H15: =Holdings!L11 -> 2134.5934 | I15: =Holdings!H11 -> 2168.1357
C16: =Holdings!C6 -> BlackRock Global | D16: ='Holdings Pull Sheet'!B17 -> MCLOX | E16: =I16/H16-1 -> 0.0041429311 | F16: =Holdings!E6 -> 19.39 | G16: =Holdings!G6 -> 89.25 | H16: =Holdings!L6 -> 1723.4175 | I16: =Holdings!H6 -> 1730.5575
C17: =Holdings!C12 -> Home Depot | D17: ='Holdings Pull Sheet'!B23 -> HD | E17: =I17/H17-1 -> -0.0094486151 | F17: =Holdings!E12 -> 76.53 | G17: =Holdings!G12 -> 59.37 | H17: =Holdings!L12 -> 4586.9262 | I17: =Holdings!H12 -> 4543.5861
C18: =Holdings!C5 -> Berkshire Hathaway | D18: ='Holdings Pull Sheet'!B16 -> BRK.B | E18: =I18/H18-1 -> 0.016710875 | F18: =Holdings!E5 -> 114.99 | G18: =Holdings!G5 -> 26 | H18: =Holdings!L5 -> 2940.6 | I18: =Holdings!H5 -> 2989.74
C19: =Holdings!C10 -> Delta Airlines | D19: ='Holdings Pull Sheet'!B21 -> DAL | E19: =I19/H19-1 -> 0.069754145 | F19: =Holdings!E9 -> 24.35 | G19: =Holdings!G10 -> 150 | H19: =Holdings!L10 -> 2623.5 | I19: =Holdings!H10 -> 2806.5
C20: =Holdings!C7 -> Caterpillar | D20: ='Holdings Pull Sheet'!B18 -> CAT | E20: =I20/H20-1 -> 0.013571429 | F20: =Holdings!E7 -> 85.14 | G20: =Holdings!G7 -> 15.172 | H20: =Holdings!L7 -> 1274.448 | I20: =Holdings!H7 -> 1291.7441
C21: =Holdings!C22 -> 0 | D21: ='Holdings Pull Sheet'!B46 -> XRX | E21: =I21/H21-1 -> #REF! | F21: =Holdings!#REF! -> #REF! | G21: =Holdings!G22 -> 0 | H21: =Holdings!#REF! -> #REF! | I21: =Holdings!#REF! -> #REF!
C22: =Holdings!C9 -> Cisco | D22: ='Holdings Pull Sheet'!B20 -> CSCO | E22: =I22/H22-1 -> 0.26285002 | F22: =Holdings!E8 -> 10.55 | G22: =Holdings!G9 -> 68.058 | H22: =Holdings!L9 -> 1670.8239 | I22: =Holdings!H8 -> 2110
C23: =Holdings!#REF! -> #REF! | D23: ='Holdings Pull Sheet'!B32 -> YRCW | E23: =I23/H23-1 -> #REF! | F23: =Holdings!#REF! -> #REF! | G23: =Holdings!#REF! -> #REF! | H23: =Holdings!#REF! -> #REF! | I23: =Holdings!#REF! -> #REF!
C24: =Holdings!C4 -> Cash | F24: =Holdings!E4 -> 1 | G24: =Holdings!G4 -> 8114.57 | H24: =Holdings!L4 -> 4444.5729 | I24: =Holdings!H4 -> 8114.57
H25: =Holdings!L22 -> 50295.736 | I25: =SUM(I4:J24) -> #REF!

Sheet Holdings Pull Sheet
C5: Stock Quote Symbols | D5: $INDU,$COMP,$INX,$COMPX,BRK.B,MCLOX,CAT,CX,CSCO,DAL,GNTX,HD,IMMR,INTC,MDT,NGVC,TPC,TSN,WFC,YHOO,YRCW,.C\12A21\5.0,VALE,CPL,SYK,PGX, PTR,UPS,F,TTEK,WMMVY,ITRI,HCP,QCOM,XRX,DIS,PSX
C9: Stock Quotes Provided by MSN Money
C10: Click here to visit MSN Money
F11: Last | G11: Previous Close | H11: High | I11: Low | J11: Volume | K11: Change | L11: % Change | M11: 52 Wk High | N11: 52 Wk Low | O11: Market Cap | P11: EPS | Q11: P/E Ratio | R11: # Shares Out
C12: Dow Jones Industrial Average Index | D12: Chart | E12: News | F12: 15176.08 | G12: 14995.23 | H12: 15202.27 | I12: 14953.45 | J12: 104486129 | K12: 180.85 | L12: 0.0121 | M12: 15542.4 | N12: 12450.17
C13: NASDAQ Composite Index | D13: Chart | E13: News | F13: 3445.37 | G13: 3400.43 | H13: 3451.03 | I13: 3387.61 | J13: 1583241074 | K13: 44.94 | L13: 0.0132 | M13: 3532.04 | N13: 2807.55
C14: S&P 500 INDEX | D14: Chart | E14: News | F14: 1636.36 | G14: 1612.52 | H14: 1639.25 | I14: 1608.07 | J14: 0 | K14: 23.84 | L14: 0.0148 | M14: 1687.18 | N14: 1309.27
C15: NASDAQ Composite Index | D15: Chart | E15: News | F15: 3445.37 | G15: 3400.43 | H15: 3451.03 | I15: 3387.61 | J15: 1583241074 | K15: 44.94 | L15: 0.0132 | M15: 3532.04 | N15: 2807.55
B16: BRK.B | C16: Berkshire Hathaway Ord Shs Class B | D16: Chart | E16: News | F16: 114.99 | G16: 112.95 | H16: 115.14 | I16: 112.27 | J16: 4022135 | K16: 2.04 | L16: 0.0181 | M16: 115.98 | N16: 80.24 | O16: 283482541934 | P16: 9988.97 | Q16: 17 | R16: 2465280000
B17: MCLOX | C17: BlackRock Global Allocation Inv C | D17: Chart | E17: News | F17: 19.39 | G17: 19.25 | H17: 0 | I17: 0 | J17: 0 | K17: 0.14 | L17: 0.0073 | M17: 20.05 | N17: 17.04
B18: CAT | C18: Caterpillar Inc | D18: Chart | E18: News | F18: 85.14 | G18: 83.21 | H18: 85.28 | I18: 83.19 | J18: 6353695 | K18: 1.93 | L18: 0.0232 | M18: 99.7 | N18: 78.25 | O18: 55978263985 | P18: 7.43 | Q18: 11.2 | R18: 657484900
B19: CX | C19: Cemex ADR Representing 10 Par Shs | D19: Chart | E19: News | F19: 10.55 | G19: 10.25 | H19: 10.61 | I19: 10.27 | J19: 14882948 | K19: 0.3 | L19: 0.0293 | M19: 12.57 | N19: 4.75 | O19: 11867494765 | P19: -1.03 | R19: 1124881000
B20: CSCO | C20: Cisco Systems Inc | D20: Chart | E20: News | F20: 24.35 | G20: 23.99 | H20: 24.4 | I20: 23.88 | J20: 27240075 | K20: 0.36 | L20: 0.015 | M20: 24.78 | N20: 14.96 | O20: 130134583639 | P20: 1.8 | Q20: 13.4 | R20: 5344336000
B21: DAL | C21: Delta Air Lines Inc | D21: Chart | E21: News | F21: 18.71 | G21: 18.07 | H21: 18.8 | I21: 17.91 | J21: 12372788 | K21: 0.64 | L21: 0.0354 | M21: 19.43 | N21: 8.42 | O21: 16025959908 | P21: 1.05 | Q21: 17.6 | R21: 856545200
B22: GNTX | C22: Gentex Corp | D22: Chart | E22: News | F22: 23.27 | G22: 22.62 | H22: 23.29 | I22: 22.37 | J22: 627199 | K22: 0.65 | L22: 0.0287 | M22: 25.4 | N22: 14.38 | O22: 3341199746 | P22: 1.17 | Q22: 19.5 | R22: 143584000
B23: HD | C23: Home Depot Inc | D23: Chart | E23: News | F23: 76.53 | G23: 76.4 | H23: 76.83 | I23: 76.08 | J23: 9197359 | K23: 0.13 | L23: 0.0017 | M23: 81.56 | N23: 49.77 | O23: 111794716097 | P23: 3.16 | Q23: 24.6 | R23: 1460796000
B24: IMMR | C24: Immersion Corp | D24: Chart | E24: News | F24: 14.91 | G24: 14.27 | H24: 15.04 | I24: 14.13 | J24: 479639 | K24: 0.64 | L24: 0.0448 | M24: 15.75 | N24: 4.15 | O24: 415953957 | P24: -0.11 | R24: 27897650
B25: INTC | C25: Intel Corp | D25: Chart | E25: News | F25: 24.99 | G25: 24.46 | H25: 25.01 | I25: 24.4 | J25: 27709957 | K25: 0.53 | L25: 0.0217 | M25: 27.75 | N25: 19.23 | O25: 124225288862 | P25: 2 | Q25: 12.3 | R25: 4971000000
B26: MDT | C26: Medtronic Inc | D26: Chart | E26: News | F26: 52.78 | G26: 51.61 | H26: 52.85 | I26: 51.09 | J26: 5178134 | K26: 1.17 | L26: 0.0227 | M26: 53.83 | N26: 36.91 | O26: 53508679442 | P26: 3.38 | Q26: 15.4 | R26: 1013806000
B27: NGVC | C27: Natural Grocers by Vitamin Cottage Inc | D27: Chart | E27: News | F27: 27.69 | G27: 27.31 | H27: 27.79 | I27: 27.18 | J27: 49850 | K27: 0.38 | L27: 0.0139 | M27: 30.28 | N27: 17.2 | O27: 620309177 | P27: 5.31 | Q27: 5.2 | R27: 22401920
B28: TPC | C28: Tutor Perini Corp | D28: Chart | E28: News | F28: 17.43 | G28: 16.85 | H28: 17.48 | I28: 16.79 | J28: 77506 | K28: 0.58 | L28: 0.0344 | M28: 19.38 | N28: 9.21 | O28: 829244291 | P28: -5.3 | R28: 47575690
B29: TSN | C29: Tyson Foods Inc | D29: Chart | E29: News | F29: 25.71 | G29: 25.42 | H29: 25.79 | I29: 25.37 | J29: 2340681 | K29: 0.29 | L29: 0.0114 | M29: 25.86 | N29: 14.06 | O29: 9122992637 | P29: 1.45 | Q29: 17.5 | R29: 354842200
B30: WFC | C30: Wells Fargo & Co | D30: Chart | E30: News | F30: 40.94 | G30: 40.27 | H30: 40.99 | I30: 40.2 | J30: 17378892 | K30: 0.67 | L30: 0.0166 | M30: 41.69 | N30: 31.15 | O30: 216834076507 | P30: 3.53 | Q30: 11.5 | R30: 5296387000
B31: YHOO | C31: Yahoo! Inc | D31: Chart | E31: News | F31: 26.37 | G31: 25.89 | H31: 26.46 | I31: 25.71 | J31: 9764435 | K31: 0.48 | L31: 0.0185 | M31: 27.68 | N31: 14.59 | O31: 28549085859 | P31: 3.41 | Q31: 7.7 | R31: 1082635000
B32: YRCW | C32: YRC Worldwide Inc | D32: Chart | E32: News | F32: 22.6 | G32: 21.89 | H32: 22.85 | I32: 21.63 | J32: 348230 | K32: 0.71 | L32: 0.0324 | M32: 25 | N32: 5.01 | O32: 212369040 | P32: -14.95 | R32: 9396860
C33: .C\12A21\5.0 (Invalid symbol) | D33: ??? | E33: ??? | F33: ??? | G33: ??? | H33: ??? | I33: ??? | J33: ??? | K33: ??? | L33: ??? | M33: ??? | N33: ??? | O33: ??? | P33: ??? | Q33: ??? | R33: ???
B34: VALE | C34: Vale ADR Representing One Ord Shs | D34: Chart | E34: News | F34: 14.47 | G34: 13.71 | H34: 14.52 | I34: 13.83 | J34: 24769220 | K34: 0.76 | L34: 0.0554 | M34: 21.88 | N34: 13.6 | O34: 77635950313 | P34: 0.92 | Q34: 11.2 | R34: 5365304000
B35: CPL | C35: CPFL Energia SA | D35: Chart | E35: News | F35: 20.31 | G35: 19.85 | H35: 20.31 | I35: 19.93 | J35: 222130 | K35: 0.46 | L35: 0.0232 | M35: 25.81 | N35: 19.3 | O35: 9771894244 | P35: 1.17 | Q35: 17.3 | R35: 481137100
B36: SYK | C36: Stryker Corp | D36: Chart | E36: News | F36: 67.72 | G36: 66.37 | H36: 67.79 | I36: 65.81 | J36: 783003 | K36: 1.35 | L36: 0.0203 | M36: 70 | N36: 50.04 | O36: 25602006957 | P36: 3.27 | Q36: 20.4 | R36: 378056800
B37: PGX | C37: PowerShares Preferred | D37: Chart | E37: News | F37: 14.29 | G37: 14.11 | H37: 14.33 | I37: 13.92 | J37: 2410446 | K37: 0.18 | L37: 0.0128 | M37: 15.12 | N37: 14.04
B38: PTR | C38: Petrochina ADR Representing 100 Ord Shs | D38: Chart | E38: News | F38: 110.05 | G38: 110.3 | H38: 110.36 | I38: 108.1 | J38: 153672 | K38: -0.25 | L38: -0.0023 | M38: 146.68 | N38: 109.96 | O38: 201414506035 | P38: 10.05 | Q38: 11.1 | R38: 1830209000
B39: UPS | C39: United Parcel Service Inc | D39: Chart | E39: News | F39: 86.32 | G39: 85.51 | H39: 86.48 | I39: 85.11 | J39: 2281928 | K39: 0.81 | L39: 0.0095 | M39: 89.96 | N39: 69.56 | O39: 81515549360 | P39: 0.88 | Q39: 97 | R39: 944341400
B40: F | C40: Ford Motor Co | D40: Chart | E40: News | F40: 15.58 | G40: 15.37 | H40: 15.6 | I40: 15.18 | J40: 34327479 | K40: 0.21 | L40: 0.0137 | M40: 16.09 | N40: 8.82 | O40: 61248189180 | P40: 1.48 | Q40: 10.5 | R40: 3931206000
B41: TTEK | C41: Tetra Tech Inc | D41: Chart | E41: News | F41: 26.68 | G41: 26.92 | H41: 27.15 | I41: 26.57 | J41: 425878 | K41: -0.24 | L41: -0.0089 | M41: 31.49 | N41: 23.79 | O41: 1732278526 | P41: 1.71 | Q41: 15.8 | R41: 64927980
B42: WMMVY | C42: Wal Mart ADR Rep Ser V 10 Ord Shs | D42: Chart | E42: News | F42: 28.65 | G42: 28 | H42: 28.65 | I42: 28.02 | J42: 21361 | K42: 0.65 | L42: 0.0232 | M42: 33.85 | N42: 24.52 | O42: 50732989574 | P42: 1.02 | Q42: 27.1 | R42: 1770785000
B43: ITRI | C43: Itron Inc | D43: Chart | E43: News | F43: 42.52 | G43: 42.25 | H43: 42.56 | I43: 41.91 | J43: 349182 | K43: 0.27 | L43: 0.0064 | M43: 48.42 | N43: 35.53 | O43: 1680922343 | P43: 2.14 | Q43: 19.7 | R43: 39532510
B44: HCP | C44: HCP Inc | D44: Chart | E44: News | F44: 45.99 | G44: 45.36 | H44: 46.14 | I44: 45.2 | J44: 4439546 | K44: 0.63 | L44: 0.0139 | M44: 56.06 | N44: 40.92 | O44: 20901821101 | P44: 2.02 | Q44: 23.6 | R44: 454486200
B45: QCOM | C45: Qualcomm Inc | D45: Chart | E45: News | F45: 61.96 | G45: 61.11 | H45: 62.12 | I45: 60.75 | J45: 11578784 | K45: 0.85 | L45: 0.0139 | M45: 68.5 | N45: 53.09 | O45: 107056655018 | P45: 3.56 | Q45: 17.4 | R45: 1727835000
B46: XRX | C46: Xerox Corp | D46: Chart | E46: News | F46: 9.1 | G46: 8.85 | H46: 9.13 | I46: 8.77 | J46: 6511217 | K46: 0.25 | L46: 0.0282 | M46: 9.38 | N46: 6.1 | O46: 11173917768 | P46: 0.93 | Q46: 9.8 | R46: 1227903000
B47: DIS | C47: Walt Disney Co | D47: Chart | E47: News | F47: 64.3 | G47: 62.99 | H47: 64.4 | I47: 62.52 | J47: 5584875 | K47: 1.31 | L47: 0.0208 | M47: 67.89 | N47: 45.99 | O47: 115800576096 | P47: 3.29 | Q47: 19.4 | R47: 1800942000
B48: PSX | C48: Phillips 66 | D48: Chart | E48: News | F48: 64.51 | G48: 63.31 | H48: 64.82 | I48: 62.37 | J48: 3336236 | K48: 1.2 | L48: 0.019 | M48: 70.52 | N48: 31.29 | O48: 39946683447 | P48: 7.7 | Q48: 8.3 | R48: 619232400
C50: Symbol Lookup | E50: MSN Money Home | I50: Microsoft Office Tools on the Web
C51: Find stocks, mutual funds, options, indices, and currencies. | E51: Discover MSN Money's tools, columns, and more! | I51: Get the latest from Microsoft Office
C53: Terms of Use. © 2013 Microsoft Corporation and/or its suppliers. All rights reserved.
C54: DATA PROVIDERS
C56: Copyright © 2013 Microsoft. All rights reserved.
C58: Quotes are real-time for NASDAQ, NYSE and AMEX. See delay times for other exchanges.
C60: Fundamental company data and historical chart data provided by Thomson Reuters (click for restrictions). Real-time quotes provided by BATS Exchange. Real-time index quotes and delayed quotes supplied by Interactive Data Real-Time Services. Fund summary, fund performance and dividend data provided by Morningstar Inc. Analyst recommendations provided by Zacks Investment Research. StockScouter data provided by Verus Analytics. IPO data provided by Hoover's Inc. Index membership data provided by SIX Telekurs.
C62: Japanese stock price data provided by Nomura Research Institute Ltd.; quotes delayed 20 minutes. Canadian fund data provided by CANNEX Financial Exchanges Ltd.

Sheet Data
D1: IPO Portfolio | L1: S&P 500 Index
A2: Week # | B2: Date | D2: Portfolio Value | E2: Adjusted Portfolio Value | F2: Weekly +/- | G2: Weekly % Change | H2: Inception +/- | I2: Inception % Change | L2: S&P Close | M2: S&P Weekly % Change | N2: S&P Inception % Change | O2: Outperformed S&P 500? | P2: 1 = Yes, 0 = No | Q2: % IPO Outperforemed S&P 500 | S2: Dow Close | T2: Dow Weekly % Change | U2: Dow Inception % Change | V2: Outperformed Dow? | W2: 1 = Yes, 0 = No | X2: % IPO Outperforemed Dow | Z2: Nasdaq Close | AA2: Nasdaq Weekly % Change | AB2: Nasdaq Inception % Change
A3: 1 | B3: 37743 | D3: 22855.85 | E3: =D3 -> 22855.85 | F3: - | G3: - | H3: - | I3: - | L3: 930.08 | M3: - | N3: - | S3: 8582.68 | T3: - | U3: - | Z3: 1502.88 | AA3: - | AB3: -
A4: 2 | B4: 37750 | D4: 23075.51 | E4: =D4 -> 23075.51 | F4: =D4-D3 -> 219.66 | G4: =(D4/D3)-1 -> 0.0096106686 | H4: =D4-$D$3 -> 219.66 | I4: =(D4/$D$3)-1 -> 0.0096106686 | L4: 933.41 | M4: =(L4/L3)-1 -> 0.0035803372 | N4: =(L4/$L$3)-1 -> 0.0035803372 | O4: =IF(G4>M4,"Yes","No") -> Yes | P4: =IF(O4="Yes",1,0) -> 1 | Q4: =SUM(P4)/COUNT(P4) -> 1 | S4: 8604.6 | T4: =(S4/S3)-1 -> 0.0025539808 | U4: =(S4/$S$3)-1 -> 0.0025539808 | V4: =IF(G4>T4,"Yes","No") -> Yes | W4: =IF(V4="Yes",1,0) -> 1 | Z4: 1520.15 | AA4: =(Z4/Z3)-1 -> 0.01149127 | AB4: =(Z4/$Z$3)-1 -> 0.01149127
A5: 3 | B5: =B4+7 -> 37757 | D5: 23259.78 | E5: =D5 -> 23259.78 | F5: =D5-D4 -> 184.27 | G5: =(D5/D4)-1 -> 0.0079855223 | H5: =D5-$D$3 -> 403.93 | I5: =(D5/$D$3)-1 -> 0.017672937 | L5: 944.3 | M5: =(L5/L4)-1 -> 0.011666899 | N5: =(L5/$L$3)-1 -> 0.015289007 | O5: =IF(G5>M5,"Yes","No") -> No | P5: =IF(O5="Yes",1,0) -> 0 | Q5: =SUM(P4:P5)/COUNT(P4:P5) -> 0.5 | S5: 8678.97 | T5: =(S5/S4)-1 -> 0.0086430514 | U5: =(S5/$S$3)-1 -> 0.011219106 | V5: =IF(G5>T5,"Yes","No") -> No | W5: =IF(V5="Yes",1,0) -> 0 | Z5: 1538.53 | AA5: =(Z5/Z4)-1 -> 0.012090912 | AB5: =(Z5/$Z$3)-1 -> 0.023721122
A6: 4 | B6: =B5+7 -> 37764 | D6: 22880.42 | E6: =D6 -> 22880.42 | F6: =D6-D5 -> -379.36 | G6: =(D6/D5)-1 -> -0.016309699 | H6: =D6-$D$3 -> 24.57 | I6: =(D6/$D$3)-1 -> 0.0010749983 | L6: 921.29 | M6: =(L6/L5)-1 -> -0.024367256 | N6: =(L6/$L$3)-1 -> -0.0094507999 | O6: =IF(G6>M6,"Yes","No") -> Yes | P6: =IF(O6="Yes",1,0) -> 1 | Q6: =SUM(P4:P6)/COUNT(P4:P6) -> 0.66666667 | S6: 8497.59 | T6: =(S6/S5)-1 -> -0.020898793 | U6: =(S6/$S$3)-1 -> -0.0099141527 | V6: =IF(G6>T6,"Yes","No") -> Yes | W6: =IF(V6="Yes",1,0) -> 1 | Z6: 1483.2 | AA6: =(Z6/Z5)-1 -> -0.0359629 | AB6: =(Z6/$Z$3)-1 -> -0.013094858
A7: 5 | B7: =B6+7 -> 37771 | D7: 24142.6 | E7: =D7 -> 24142.6 | F7: =D7-D6 -> 1262.18 | G7: =(D7/D6)-1 -> 0.055164197 | H7: =D7-$D$3 -> 1286.75 | I7: =(D7/$D$3)-1 -> 0.056298497 | L7: 963.59 | M7: =(L7/L6)-1 -> 0.045913882 | N7: =(L7/$L$3)-1 -> 0.036029159 | O7: =IF(G7>M7,"Yes","No") -> Yes | P7: =IF(O7="Yes",1,0) -> 1 | S7: 8850.26 | T7: =(S7/S6)-1 -> 0.041502355 | U7: =(S7/$S$3)-1 -> 0.031176742 | V7: =IF(G7>T7,"Yes","No") -> Yes | W7: =IF(V7="Yes",1,0) -> 1 | Z7: 1595.91 | AA7: =(Z7/Z6)-1 -> 0.0759911 | AB7: =(Z7/$Z$3)-1 -> 0.06190115
A8: 6 | B8: =B7+7 -> 37778 | D8: 24843.31 | E8: =D8 -> 24843.31 | F8: =D8-D7 -> 700.71 | G8: =(D8/D7)-1 -> 0.0290238 | H8: =D8-$D$3 -> 1987.46 | I8: =(D8/$D$3)-1 -> 0.086956293 | L8: 987.76 | M8: =(L8/L7)-1 -> 0.025083282 | N8: =(L8/$L$3)-1 -> 0.062016171 | O8: =IF(G8>M8,"Yes","No") -> Yes | P8: =IF(O8="Yes",1,0) -> 1 | S8: 9062.79 | T8: =(S8/S7)-1 -> 0.024013984 | U8: =(S8/$S$3)-1 -> 0.055939404 | V8: =IF(G8>T8,"Yes","No") -> Yes | W8: =IF(V8="Yes",1,0) -> 1 | Z8: 1627.42 | AA8: =(Z8/Z7)-1 -> 0.019744221 | AB8: =(Z8/$Z$3)-1 -> 0.082867561
A9: 7 | B9: =B8+7 -> 37785 | D9: 24777.34 | E9: =D9 -> 24777.34 | F9: =D9-D8 -> -65.97 | G9: =(D9/D8)-1 -> -0.0026554433 | H9: =D9-$D$3 -> 1921.49 | I9: =(D9/$D$3)-1 -> 0.084069943 | L9: =995.16-6.55 -> 988.61 | M9: =(L9/L8)-1 -> 0.00086053292 | N9: =(L9/$L$3)-1 -> 0.062930071 | O9: =IF(G9>M9,"Yes","No") -> No | P9: =IF(O9="Yes",1,0) -> 0 | S9: =9176.41-59.29 -> 9117.12 | T9: =(S9/S8)-1 -> 0.0059948426 | U9: =(S9/$S$3)-1 -> 0.062269594 | V9: =IF(G9>T9,"Yes","No") -> No | W9: =IF(V9="Yes",1,0) -> 0 | Z9: =1637.82-11.33 -> 1626.49 | AA9: =(Z9/Z8)-1 -> -0.00057145666 | AB9: =(Z9/$Z$3)-1 -> 0.082248749
A10: 8 | B10: =B9+7 -> 37792 | D10: 25072.64 | E10: =D10 -> 25072.64 | F10: =D10-D9 -> 295.3 | G10: =(D10/D9)-1 -> 0.011918148 | H10: =D10-$D$3 -> 2216.79 | I10: =(D10/$D$3)-1 -> 0.096990048 | L10: 995.69 | M10: =(L10/L9)-1 -> 0.0071615703 | N10: =(L10/$L$3)-1 -> 0.070542319 | O10: =IF(G10>M10,"Yes","No") -> Yes | P10: =IF(O10="Yes",1,0) -> 1 | S10: 9200.75 | T10: =(S10/S9)-1 -> 0.0091728528 | U10: =(S10/$S$3)-1 -> 0.072013637 | V10: =IF(G10>T10,"Yes","No") -> Yes | W10: =IF(V10="Yes",1,0) -> 1 | Z10: 1644.72 | AA10: =(Z10/Z9)-1 -> 0.011208184 | AB10: =(Z10/$Z$3)-1 -> 0.094378793
A11: 9 | B11: =B10+7 -> 37799 | D11: 24857.12 | E11: =D11 -> 24857.12 | F11: =D11-D10 -> -215.52 | G11: =(D11/D10)-1 -> -0.008595824 | H11: =D11-$D$3 -> 2001.27 | I11: =(D11/$D$3)-1 -> 0.087560515 | L11: 976.22 | M11: =(L11/L10)-1 -> -0.019554279 | N11: =(L11/$L$3)-1 -> 0.049608636 | O11: =IF(G11>M11,"Yes","No") -> Yes | P11: =IF(O11="Yes",1,0) -> 1 | S11: 8989.05 | T11: =(S11/S10)-1 -> -0.023008994 | U11: =(S11/$S$3)-1 -> 0.047347682 | V11: =IF(G11>T11,"Yes","No") -> Yes | W11: =IF(V11="Yes",1,0) -> 1 | Z11: 1625.26 | AA11: =(Z11/Z10)-1 -> -0.011831801 | AB11: =(Z11/$Z$3)-1 -> 0.08143032
A12: 10 | B12: =B11+7 -> 37806 | D12: 24907.37 | E12: =D12 -> 24907.37 | F12: =D12-D11 -> 50.25 | G12: =(D12/D11)-1 -> 0.0020215536 | H12: =D12-$D$3 -> 2051.52 | I12: =(D12/$D$3)-1 -> 0.089759077 | L12: 991.66 | M12: =(L12/L11)-1 -> 0.015816107 | N12: =(L12/$L$3)-1 -> 0.066209358 | O12: =IF(G12>M12,"Yes","No") -> No | P12: =IF(O12="Yes",1,0) -> 0 | S12: 9070.21 | T12: =(S12/S11)-1 -> 0.0090287628 | U12: =(S12/$S$3)-1 -> 0.056803935 | V12: =IF(G12>T12,"Yes","No") -> No | W12: =IF(V12="Yes",1,0) -> 0 | Z12: 1663.46 | AA12: =(Z12/Z11)-1 -> 0.023503932 | AB12: =(Z12/$Z$3)-1 -> 0.10684818
A13: 11 | B13: =B12+7 -> 37813 | D13: 25578.29 | E13: =D13 -> 25578.29 | F13: =D13-D12 -> 670.92 | G13: =(D13/D12)-1 -> 0.026936606 | H13: =D13-$D$3 -> 2722.44 | I13: =(D13/$D$3)-1 -> 0.11911349 | L13: 998.14 | M13: =(L13/L12)-1 -> 0.0065344977 | N13: =(L13/$L$3)-1 -> 0.073176501 | O13: =IF(G13>M13,"Yes","No") -> Yes | P13: =IF(O13="Yes",1,0) -> 1 | S13: 9119.59 | T13: =(S13/S12)-1 -> 0.0054441959 | U13: =(S13/$S$3)-1 -> 0.062557383 | V13: =IF(G13>T13,"Yes","No") -> Yes | W13: =IF(V13="Yes",1,0) -> 1 | Z13: 1733.93 | AA13: =(Z13/Z12)-1 -> 0.042363507 | AB13: =(Z13/$Z$3)-1 -> 0.15373816
A14: 12 | B14: =B13+7 -> 37820 | D14: 25192.44 | E14: =D14 -> 25192.44 | F14: =D14-D13 -> -385.85 | G14: =(D14/D13)-1 -> -0.015085058 | H14: =D14-$D$3 -> 2336.59 | I14: =(D14/$D$3)-1 -> 0.10223159 | L14: 993.32 | M14: =(L14/L13)-1 -> -0.0048289819 | N14: =(L14/$L$3)-1 -> 0.067994151 | O14: =IF(G14>M14,"Yes","No") -> No | P14: =IF(O14="Yes",1,0) -> 0 | S14: 9188.15 | T14: =(S14/S13)-1 -> 0.0075178818 | U14: =(S14/$S$3)-1 -> 0.070545564 | V14: =IF(G14>T14,"Yes","No") -> No | W14: =IF(V14="Yes",1,0) -> 0 | Z14: 1708.5 | AA14: =(Z14/Z13)-1 -> -0.014666105 | AB14: =(Z14/$Z$3)-1 -> 0.13681731
A15: 13 | B15: =B14+7 -> 37827 | D15: 25421.8 | E15: =D15 -> 25421.8 | F15: =D15-D14 -> 229.36 | G15: =(D15/D14)-1 -> 0.0091043186 | H15: =D15-$D$3 -> 2565.95 | I15: =(D15/$D$3)-1 -> 0.11226666 | L15: 998.68 | M15: =(L15/L14)-1 -> 0.0053960456 | N15: =(L15/$L$3)-1 -> 0.073757096 | O15: =IF(G15>M15,"Yes","No") -> Yes | P15: =IF(O15="Yes",1,0) -> 1 | S15: 9284.57 | T15: =(S15/S14)-1 -> 0.010493951 | U15: =(S15/$S$3)-1 -> 0.081779817 | V15: =IF(G15>T15,"Yes","No") -> No | W15: =IF(V15="Yes",1,0) -> 0 | Z15: 1730.7 | AA15: =(Z15/Z14)-1 -> 0.012993854 | AB15: =(Z15/$Z$3)-1 -> 0.15158895
A16: 14 | B16: =B15+7 -> 37834 | D16: 25266.57 | E16: =D16 -> 25266.57 | F16: =D16-D15 -> -155.23 | G16: =(D16/D15)-1 -> -0.0061061766 | H16: =D16-$D$3 -> 2410.72 | I16: =(D16/$D$3)-1 -> 0.10547497 | L16: 980.15 | M16: =(L16/L15)-1 -> -0.018554492 | N16: =(L16/$L$3)-1 -> 0.053834079 | O16: =IF(G16>M16,"Yes","No") -> Yes | P16: =IF(O16="Yes",1,0) -> 1 | S16: 9153.97 | T16: =(S16/S15)-1 -> -0.014066349 | U16: =(S16/$S$3)-1 -> 0.066563125 | V16: =IF(G16>T16,"Yes","No") -> Yes | W16: =IF(V16="Yes",1,0) -> 1 | Z16: 1715.62 | AA16: =(Z16/Z15)-1 -> -0.0087132374 | AB16: =(Z16/$Z$3)-1 -> 0.14155488
A17: 15 | B17: =B16+7 -> 37841 | D17: 25228.34 | E17: =D17 -> 25228.34 | F17: =D17-D16 -> -38.23 | G17: =(D17/D16)-1 -> -0.0015130665 | H17: =D17-$D$3 -> 2372.49 | I17: =(D17/$D$3)-1 -> 0.10380231 | L17: 977.59 | M17: =(L17/L16)-1 -> -0.0026118451 | N17: =(L17/$L$3)-1 -> 0.051081627 | O17: =IF(G17>M17,"Yes","No") -> Yes | P17: =IF(O17="Yes",1,0) -> 1 | S17: 9191.09 | T17: =(S17/S16)-1 -> 0.0040550712 | U17: =(S17/$S$3)-1 -> 0.070888114 | V17: =IF(G17>T17,"Yes","No") -> No | W17: =IF(V17="Yes",1,0) -> 0 | Z17: 1644.03 | AA17: =(Z17/Z16)-1 -> -0.041728355 | AB17: =(Z17/$Z$3)-1 -> 0.093919674
A18: 16 | B18: =B17+7 -> 37848 | D18: 24951.71 | E18: =D18 -> 24951.71 | F18: =D18-D17 -> -276.63 | G18: =(D18/D17)-1 -> -0.01096505 | H18: =D18-$D$3 -> 2095.86 | I18: =(D18/$D$3)-1 -> 0.091699062 | L18: 990.67 | M18: =(L18/L17)-1 -> 0.013379842 | N18: =(L18/$L$3)-1 -> 0.065144934 | O18: =IF(G18>M18,"Yes","No") -> No | P18: =IF(O18="Yes",1,0) -> 0 | S18: 9321.69 | T18: =(S18/S17)-1 -> 0.014209414 | U18: =(S18/$S$3)-1 -> 0.086104806 | V18: =IF(G18>T18,"Yes","No") -> No | W18: =IF(V18="Yes",1,0) -> 0 | Z18: 1702.01 | AA18: =(Z18/Z17)-1 -> 0.035266996 | AB18: =(Z18/$Z$3)-1 -> 0.13249894
A19: 17 | B19: =B18+7 -> 37855 | D19: 25454.04 | E19: =D19 -> 25454.04 | F19: =D19-D18 -> 502.33 | G19: =(D19/D18)-1 -> 0.020132087 | H19: =D19-$D$3 -> 2598.19 | I19: =(D19/$D$3)-1 -> 0.11367724 | L19: 993.06 | M19: =(L19/L18)-1 -> 0.0024125087 | N19: =(L19/$L$3)-1 -> 0.067714605 | O19: =IF(G19>M19,"Yes","No") -> Yes | P19: =IF(O19="Yes",1,0) -> 1 | S19: 9348.87 | T19: =(S19/S18)-1 -> 0.0029157803 | U19: =(S19/$S$3)-1 -> 0.089271649 | V19: =IF(G19>T19,"Yes","No") -> Yes | W19: =IF(V19="Yes",1,0) -> 1 | Z19: 1765.32 | AA19: =(Z19/Z18)-1 -> 0.037197196 | AB19: =(Z19/$Z$3)-1 -> 0.17462472
A20: 18 | B20: =B19+7 -> 37862 | D20: 26198.38 | E20: =D20 -> 26198.38 | F20: =D20-D19 -> 744.34 | G20: =(D20/D19)-1 -> 0.029242509 | H20: =D20-$D$3 -> 3342.53 | I20: =(D20/$D$3)-1 -> 0.14624396 | L20: 1008.01 | M20: =(L20/L19)-1 -> 0.015054478 | N20: =(L20/$L$3)-1 -> 0.083788491 | O20: =IF(G20>M20,"Yes","No") -> Yes | P20: =IF(O20="Yes",1,0) -> 1 | S20: 9415.82 | T20: =(S20/S19)-1 -> 0.0071612933 | U20: =(S20/$S$3)-1 -> 0.097072243 | V20: =IF(G20>T20,"Yes","No") -> Yes | W20: =IF(V20="Yes",1,0) -> 1 | Z20: 1810.45 | AA20: =(Z20/Z19)-1 -> 0.02556477 | AB20: =(Z20/$Z$3)-1 -> 0.20465373
A21: 19 | B21: =B20+7 -> 37869 | D21: 26545.65 | E21: =D21 -> 26545.65 | F21: =D21-D20 -> 347.27 | G21: =(D21/D20)-1 -> 0.0132554 | H21: =D21-$D$3 -> 3689.8 | I21: =(D21/$D$3)-1 -> 0.16143788 | L21: 1021.39 | M21: =(L21/L20)-1 -> 0.013273678 | N21: =(L21/$L$3)-1 -> 0.098174351 | O21: =IF(G21>M21,"Yes","No") -> No | P21: =IF(O21="Yes",1,0) -> 0 | S21: 9503.34 | T21: =(S21/S20)-1 -> 0.009294995 | U21: =(S21/$S$3)-1 -> 0.10726952 | V21: =IF(G21>T21,"Yes","No") -> Yes | W21: =IF(V21="Yes",1,0) -> 1 | Z21: 1858.24 | AA21: =(Z21/Z20)-1 -> 0.026396752 | AB21: =(Z21/$Z$3)-1 -> 0.23645268
... A37: 35 | B37: =B36+7 -> 37981 | D37: 29690.49 | E37: =D37 -> 29690.49 | F37: =D37-D36 -> 362.49 | G37: =(D37/D36)-1 -> 0.012359861 | H37: =D37-$D$3 -> 6834.64 | I37: =(D37/$D$3)-1 -> 0.29903241 | L37: 1095.89 | M37: =(L37/L36)-1 -> 0.0066411919 | N37: =(L37/$L$3)-1 -> 0.17827499 | O37: =IF(G37>M37,"Yes","No") -> Yes | P37: =IF(O37="Yes",1,0) -> 1 | S37: 10324.67 | T37: =(S37/S36)-1 -> 0.004519265 | U37: =(S37/$S$3)-1 -> 0.20296574 | V37: =IF(G37>T37,"Yes","No") -> Yes | W37: =IF(V37="Yes",1,0) -> 1 | Z37: 1973.14 | AA37: =(Z37/Z36)-1 -> 0.0082370134 | AB37: =(Z37/$Z$3)-1 -> 0.31290589
A38: 36 | B38: =B37+7 -> 37988 | D38: 30649.47 | E38: =D38 -> 30649.47 | F38: =D38-D37 -> 958.98 | G38: =(D38/D37)-1 -> 0.032299231 | H38: =D38-$D$3 -> 7793.62 | I38: =(D38/$D$3)-1 -> 0.34099016 | J38: 0 | L38: 1108.48 | M38: =(L38/L37)-1 -> 0.011488379 | N38: =(L38/$L$3)-1 -> 0.19181146 | O38: =IF(G38>M38,"Yes","No") -> Yes | P38: =IF(O38="Yes",1,0) -> 1 | R38: 0 | S38: 10409.85 | T38: =(S38/S37)-1 -> 0.0082501426 | U38: =(S38/$S$3)-1 -> 0.21289038 | V38: =IF(G38>T38,"Yes","No") -> Yes | W38: =IF(V38="Yes",1,0) -> 1 | Z38: 2006.68 | AA38: =(Z38/Z37)-1 -> 0.016998287 | AB38: =(Z38/$Z$3)-1 -> 0.33522304
A39: 37 | B39: =B38+7 -> 37995 | D39: 30712.11 | E39: =D39 -> 30712.11 | F39: =D39-D38 -> 62.64 | G39: =(D39/D38)-1 -> 0.0020437548 | H39: =D39-$D$3 -> 7856.26 | I39: =(D39/$D$3)-1 -> 0.34373082 | J39: =(E39/$E$38)-1 -> 0.0020437548 | L39: 1121.86 | M39: =(L39/L38)-1 -> 0.012070583 | N39: =(L39/$L$3)-1 -> 0.20619732 | O39: =IF(G39>M39,"Yes","No") -> No | P39: =IF(O39="Yes",1,0) -> 0 | R39: =(L39/$L$38)-1 -> 0.012070583 | S39: 10458.89 | T39: =(S39/S38)-1 -> 0.0047109228 | U39: =(S39/$S$3)-1 -> 0.21860421 | V39: =IF(G39>T39,"Yes","No") -> No | W39: =IF(V39="Yes",1,0) -> 0 | Z39: 2086.92 | AA39: =(Z39/Z38)-1 -> 0.039986445 | AB39: =(Z39/$Z$3)-1 -> 0.38861386
A40: 38 | B40: =B39+7 -> 38002 | D40: 30500.54 | E40: =D40 -> 30500.54 | F40: =D40-D39 -> -211.57 | G40: =(D40/D39)-1 -> -0.0068888136 | H40: =D40-$D$3 -> 7644.69 | I40: =(D40/$D$3)-1 -> 0.33447411 | J40: =(E40/$E$38)-1 -> -0.0048591379 | L40: 1139.83 | M40: =(L40/L39)-1 -> 0.016018041 | N40: =(L40/$L$3)-1 -> 0.22551823 | O40: =IF(G40>M40,"Yes","No") -> No | P40: =IF(O40="Yes",1,0) -> 0 | R40: =(L40/$L$38)-1 -> 0.028281972 | S40: 10600.51 | T40: =(S40/S39)-1 -> 0.013540634 | U40: =(S40/$S$3)-1 -> 0.23510489 | V40: =IF(G40>T40,"Yes","No") -> No | W40: =IF(V40="Yes",1,0) -> 0 | Z40: 2140.46 | AA40: =(Z40/Z39)-1 -> 0.025655032 | AB40: =(Z40/$Z$3)-1 -> 0.42423879
A41: 39 | B41: =B40+7 -> 38009 | D41: 30340.26 | E41: =D41+Holdings_Old!$E$32 -> 30340.26 | F41: =E41-D40 -> -160.28 | G41: =(E41/E40)-1 -> -0.0052549889 | H41: =E41-$D$3 -> 7484.41 | I41: =(E41/$D$3)-1 -> 0.32746146 | J41: =(E41/$E$38)-1 -> -0.010088592 | L41: 1141.55 | M41: =(L41/L40)-1 -> 0.001508997 | N41: =(L41/$L$3)-1 -> 0.22736754 | O41: =IF(G41>M41,"Yes","No") -> No | P41: =IF(O41="Yes",1,0) -> 0 | R41: =(L41/$L$38)-1 -> 0.029833646 | S41: 10568.29 | T41: =(S41/S40)-1 -> -0.0030394764 | U41: =(S41/$S$3)-1 -> 0.23135081 | V41: =IF(G41>T41,"Yes","No") -> No | W41: =IF(V41="Yes",1,0) -> 0 | Z41: 2123.87 | AA41: =(Z41/Z40)-1 -> -0.0077506704 | AB41: =(Z41/$Z$3)-1 -> 0.41319999
A42: 40 | B42: =B41+7 -> 38016 | D42: 29390.96 | E42: =D42+Holdings_Old!$E$32 -> 29390.96 | F42: =E42-E41 -> -949.3 | G42: =(E42/E41)-1 -> -0.03128846 | H42: =E42-$D$3 -> 6535.11 | I42: =(E42/$D$3)-1 -> 0.28592724 | J42: =(E42/$E$38)-1 -> -0.041061395 | L42: 1131.13 | M42: =(L42/L41)-1 -> -0.0091279401 | N42: =(L42/$L$3)-1 -> 0.2161642 | O42: =IF(G42>M42,"Yes","No") -> No | P42: =IF(O42="Yes",1,0) -> 0 | R42: =(L42/$L$38)-1 -> 0.020433386 | S42: 10488.07 | T42: =(S42/S41)-1 -> -0.007590632 | U42: =(S42/$S$3)-1 -> 0.22200408 | V42: =IF(G42>T42,"Yes","No") -> No | W42: =IF(V42="Yes",1,0) -> 0 | Z42: 2066.15 | AA42: =(Z42/Z41)-1 -> -0.027176805 | AB42: =(Z42/$Z$3)-1 -> 0.37479373
A43: 41 | B43: =B42+7 -> 38023 | D43: 29673.82 | E43: =D43+Holdings_Old!$E$32 -> 29673.82 | F43: =E43-E42 -> 282.86 | G43: =(E43/E42)-1 -> 0.0096240477 | H43: =E43-$D$3 -> 6817.97 | I43: =(E43/$D$3)-1 -> 0.29830306 | J43: =(E43/$E$38)-1 -> -0.031832524 | L43: 1142.76 | M43: =(L43/L42)-1 -> 0.010281754 | N43: =(L43/$L$3)-1 -> 0.2286685 | O43: =IF(G43>M43,"Yes","No") -> No | P43: =IF(O43="Yes",1,0) -> 0 | R43: =(L43/$L$38)-1 -> 0.030925231 | S43: 10593.03 | T43: =(S43/S42)-1 -> 0.010007561 | U43: =(S43/$S$3)-1 -> 0.23423336 | V43: =IF(G43>T43,"Yes","No") -> No | W43: =IF(V43="Yes",1,0) -> 0 | Z43: 2064.01 | AA43: =(Z43/Z42)-1 -> -0.0010357428 | AB43: =(Z43/$Z$3)-1 -> 0.3733698
A44: 42 | B44: =B43+7 -> 38030 | D44: 29580.97 | E44: =D44+Holdings_Old!$E$32 -> 29580.97 | F44: =E44-E43 -> -92.85 | G44: =(E44/E43)-1 -> -0.0031290208 | H44: =E44-$D$3 -> 6725.12 | I44: =(E44/$D$3)-1 -> 0.29424064 | J44: =(E44/$E$38)-1 -> -0.034861941 | L44: 1145.81 | M44: =(L44/L43)-1 -> 0.0026689769 | N44: =(L44/$L$3)-1 -> 0.23194779 | O44: =IF(G44>M44,"Yes","No") -> No | P44: =IF(O44="Yes",1,0) -> 0 | R44: =(L44/$L$38)-1 -> 0.033676747 | S44: 10628.85 | T44: =(S44/S43)-1 -> 0.0033814688 | U44: =(S44/$S$3)-1 -> 0.23840688 | V44: =IF(G44>T44,"Yes","No") -> No | W44: =IF(V44="Yes",1,0) -> 0 | Z44: 2053.56 | AA44: =(Z44/Z43)-1 -> -0.00506296 | AB44: =(Z44/$Z$3)-1 -> 0.36641648
A45: 43 | B45: =B44+7 -> 38037 | D45: 29455.64 | E45: =D45+Holdings_Old!$E$32 -> 29455.64 | F45: =E45-E44 -> -125.33 | G45: =(E45/E44)-1 -> -0.0042368455 | H45: =E45-$D$3 -> 6599.79 | I45: =(E45/$D$3)-1 -> 0.28875715 | J45: =(E45/$E$38)-1 -> -0.038951081 | L45: 1144.11 | M45: =(L45/L44)-1 -> -0.0014836666 | N45: =(L45/$L$3)-1 -> 0.23011999 | O45: =IF(G45>M45,"Yes","No") -> No | P45: =IF(O45="Yes",1,0) -> 0 | R45: =(L45/$L$38)-1 -> 0.032143115 | S45: 10619.03 | T45: =(S45/S44)-1 -> -0.00092390052 | U45: =(S45/$S$3)-1 -> 0.23726272 | V45: =IF(G45>T45,"Yes","No") -> No | W45: =IF(V45="Yes",1,0) -> 0 | Z45: 2037.93 | AA45: =(Z45/Z44)-1 -> -0.0076111728 | AB45: =(Z45/$Z$3)-1 -> 0.35601645
A46: 44 | B46: =B45+7 -> 38044 | D46: 29503.45 | E46: =D46+Holdings_Old!$E$32 -> 29503.45 | F46: =E46-E45 -> 47.81 | G46: =(E46/E45)-1 -> 0.0016231187 | H46: =E46-$D$3 -> 6647.6 | I46: =(E46/$D$3)-1 -> 0.29084895 | J46: =(E46/$E$38)-1 -> -0.037391185 | L46: 1144.94 | M46: =(L46/L45)-1 -> 0.00072545472 | N46: =(L46/$L$3)-1 -> 0.23101239 | O46: =IF(G46>M46,"Yes","No") -> Yes | P46: =IF(O46="Yes",1,0) -> 1 | R46: =(L46/$L$38)-1 -> 0.032891888 | S46: 10583.92 | T46: =(S46/S45)-1 -> -0.0033063284 | U46: =(S46/$S$3)-1 -> 0.23317192 | V46: =IF(G46>T46,"Yes","No") -> Yes | W46: =IF(V46="Yes",1,0) -> 1 | Z46: 2029.82 | AA46: =(Z46/Z45)-1 -> -0.0039795282 | AB46: =(Z46/$Z$3)-1 -> 0.35062014
A47: 45 | B47: =B46+7 -> 38051 | D47: 29619.45 | E47: =D47+Holdings_Old!$E$32 -> 29619.45 | F47: =E47-E46 -> 116 | G47: =(E47/E46)-1 -> 0.0039317436 | H47: =E47-$D$3 -> 6763.6 | I47: =(E47/$D$3)-1 -> 0.29592424 | J47: =(E47/$E$38)-1 -> -0.033606454 | L47: 1156.86 | M47: =(L47/L46)-1 -> 0.010411026 | N47: =(L47/$L$3)-1 -> 0.24382849 | O47: =IF(G47>M47,"Yes","No") -> No | P47: =IF(O47="Yes",1,0) -> 0 | R47: =(L47/$L$38)-1 -> 0.043645352 | S47: 10595.55 | T47: =(S47/S46)-1 -> 0.0010988367 | U47: =(S47/$S$3)-1 -> 0.23452698 | V47: =IF(G47>T47,"Yes","No") -> Yes | W47: =IF(V47="Yes",1,0) -> 1 | Z47: 2047.63 | AA47: =(Z47/Z46)-1 -> 0.008774177 | AB47: =(Z47/$Z$3)-1 -> 0.36247072
A48: 46 | B48: =B47+7 -> 38058 | D48: 29016.49 | E48: =D48+Holdings_Old!$E$32 -> 29016.49 | F48: =E48-E47 -> -602.96 | G48: =(E48/E47)-1 -> -0.020356894 | H48: =E48-$D$3 -> 6160.64 | I48: =(E48/$D$3)-1 -> 0.26954325 | J48: =(E48/$E$38)-1 -> -0.053279225 | L48: 1120.57 | M48: =(L48/L47)-1 -> -0.031369396 | N48: =(L48/$L$3)-1 -> 0.20481034 | O48: =IF(G48>M48,"Yes","No") -> Yes | P48: =IF(O48="Yes",1,0) -> 1 | R48: =(L48/$L$38)-1 -> 0.010906827 | S48: 10240.08 | T48: =(S48/S47)-1 -> -0.03354899 | U48: =(S48/$S$3)-1 -> 0.19310984 | V48: =IF(G48>T48,"Yes","No") -> Yes | W48: =IF(V48="Yes",1,0) -> 1 | Z48: 1984.73 | AA48: =(Z48/Z47)-1 -> -0.03071844 | AB48: =(Z48/$Z$3)-1 -> 0.32061775
A49: 47 | B49: =B48+7 -> 38065 | D49: 28837.81 | E49: =D49+Holdings_Old!$E$32 -> 28837.81 | F49: =E49-E48 -> -178.68 | G49: =(E49/E48)-1 -> -0.0061578778 | H49: =E49-$D$3 -> 5981.96 | I49: =(E49/$D$3)-1 -> 0.26172555 | J49: =(E49/$E$38)-1 -> -0.059109016 | L49: 1109.74 | M49: =(L49/L48)-1 -> -0.0096647242 | N49: =(L49/$L$3)-1 -> 0.19316618 | O49: =IF(G49>M49,"Yes","No") -> Yes | P49: =IF(O49="Yes",1,0) -> 1 | R49: =(L49/$L$38)-1 -> 0.0011366917 | S49: 10186.6 | T49: =(S49/S48)-1 -> -0.0052226154 | U49: =(S49/$S$3)-1 -> 0.18687869 | V49: =IF(G49>T49,"Yes","No") -> No | W49: =IF(V49="Yes",1,0) -> 0 | Z49: 1940.47 | AA49: =(Z49/Z48)-1 -> -0.022300263 | AB49: =(Z49/$Z$3)-1 -> 0.29116762
A50: 48 | B50: =B49+7 -> 38072 | D50: 28946.8 | E50: =D50+Holdings_Old!$E$32 -> 28946.8 | F50: =E50-E49 -> 108.99 | G50: =(E50/E49)-1 -> 0.0037794132 | H50: =E50-$D$3 -> 6090.95 | I50: =(E50/$D$3)-1 -> 0.26649414 | J50: =(E50/$E$38)-1 -> -0.055553 | L50: 1108.06 | M50: =(L50/L49)-1 -> -0.0015138681 | N50: =(L50/$L$3)-1 -> 0.19135988 | O50: =IF(G50>M50,"Yes","No") -> Yes | P50: =IF(O50="Yes",1,0) -> 1 | R50: =(L50/$L$38)-1 -> -0.00037889723 | S50: 10212.97 | T50: =(S50/S49)-1 -> 0.002588695 | U50: =(S50/$S$3)-1 -> 0.18995116 | V50: =IF(G50>T50,"Yes","No") -> Yes | W50: =IF(V50="Yes",1,0) -> 1 | Z50: 1960.02 | AA50: =(Z50/Z49)-1 -> 0.010074879 | AB50: =(Z50/$Z$3)-1 -> 0.30417598
A51: 49 | B51: =B50+7 -> 38079 | D51: 29704.21 | E51: =D51+Holdings_Old!$E$32 -> 29704.21 | F51: =E51-E50 -> 757.41 | G51: =(E51/E50)-1 -> 0.026165587 | H51: =E51-$D$3 -> 6848.36 | I51: =(E51/$D$3)-1 -> 0.2996327 | J51: =(E51/$E$38)-1 -> -0.03084099 | L51: 1141.84 | M51: =(L51/L50)-1 -> 0.030485714 | N51: =(L51/$L$3)-1 -> 0.22767934 | O51: =IF(G51>M51,"Yes","No") -> No | P51: =IF(O51="Yes",1,0) -> 0 | R51: =(L51/$L$38)-1 -> 0.030095266 | S51: 10470.59 | T51: =(S51/S50)-1 -> 0.025224788 | U51: =(S51/$S$3)-1 -> 0.21996742 | V51: =IF(G51>T51,"Yes","No") -> Yes | W51: =IF(V51="Yes",1,0) -> 1 | Z51: 2057.17 | AA51: =(Z51/Z50)-1 -> 0.049565821 | AB51: =(Z51/$Z$3)-1 -> 0.36881854
A52: 50 | B52: =B51+7 -> 38086 | D52: 29609.72 | E52: =D52+Holdings_Old!$E$32 -> 29609.72 | F52: =E52-E51 -> -94.49 | G52: =(E52/E51)-1 -> -0.0031810306 | H52: =E52-$D$3 -> 6753.87 | I52: =(E52/$D$3)-1 -> 0.29549853 | J52: =(E52/$E$38)-1 -> -0.033923915 | L52: 1139.32 | M52: =(L52/L51)-1 -> -0.0022069642 | N52: =(L52/$L$3)-1 -> 0.2249699 | O52: =IF(G52>M52,"Yes","No") -> No | P52: =IF(O52="Yes",1,0) -> 0 | R52: =(L52/$L$38)-1 -> 0.027821882 | S52: 10442.03 | T52: =(S52/S51)-1 -> -0.00272764 | U52: =(S52/$S$3)-1 -> 0.21663979 | V52: =IF(G52>T52,"Yes","No") -> No | W52: =IF(V52="Yes",1,0) -> 0 | Z52: 2052.88 | AA52: =(Z52/Z51)-1 -> -0.0020853892 | AB52: =(Z52/$Z$3)-1 -> 0.36596402
A53: 51 | B53: =B52+7 -> 38093 | D53: 29251.01 | E53: =D53+Holdings_Old!$E$32 -> 29251.01 | F53: =E53-E52 -> -358.71 | G53: =(E53/E52)-1 -> -0.012114603 | H53: =E53-$D$3 -> 6395.16 | I53: =(E53/$D$3)-1 -> 0.27980408 | J53: =(E53/$E$38)-1 -> -0.045627543 | L53: 1134.61 | M53: =(L53/L52)-1 -> -0.0041340449 | N53: =(L53/$L$3)-1 -> 0.21990581 | O53: =IF(G53>M53,"Yes","No") -> No | P53: =IF(O53="Yes",1,0) -> 0 | R53: =(L53/$L$38)-1 -> 0.02357282 | S53: 10451.97 | T53: =(S53/S52)-1 -> 0.00095192218 | U53: =(S53/$S$3)-1 -> 0.21779794 | V53: =IF(G53>T53,"Yes","No") -> No | W53: =IF(V53="Yes",1,0) -> 0 | Z53: 1995.74 | AA53: =(Z53/Z52)-1 -> -0.027834067 | AB53: =(Z53/$Z$3)-1 -> 0.32794368
... A69: 67 | B69: =B68+7 -> 38205 | D69: 27961.47 | E69: =D69+Holdings_Old!$E$32 -> 27961.47 | F69: =E69-E68 -> -831.06 | G69: =(E69/E68)-1 -> -0.028863737 | H69: =E69-$D$3 -> 5105.62 | I69: =(E69/$D$3)-1 -> 0.22338351 | J69: =(E69/$E$38)-1 -> -0.087701353 | L69: 1063.97 | M69: =(L69/L68)-1 -> -0.034264604 | N69: =(L69/$L$3)-1 -> 0.14395536 | O69: =IF(G69>M69,"Yes","No") -> Yes | P69: =IF(O69="Yes",1,0) -> 1 | R69: =(L69/$L$38)-1 -> -0.040154085 | S69: 9815.33 | T69: =(S69/S68)-1 -> -0.031991053 | U69: =(S69/$S$3)-1 -> 0.14362064 | V69: =IF(G69>T69,"Yes","No") -> Yes | W69: =IF(V69="Yes",1,0) -> 1 | Z69: 1776.89 | AA69: =(Z69/Z68)-1 -> -0.058531494 | AB69: =(Z69/$Z$3)-1 -> 0.18232327
A70: 68 | B70: =B69+7 -> 38212 | D70: 27243.27 | E70: =D70+SUM(Holdings_Old!$E$32:$E$33) -> 27243.27 | F70: =E70-E69 -> -718.2 | G70: =(E70/E69)-1 -> -0.025685345 | H70: =E70-$D$3 -> 4387.42 | I70: =(E70/$D$3)-1 -> 0.19196048 | J70: =(E70/$E$38)-1 -> -0.11113406 | L70: 1064.8 | M70: =(L70/L69)-1 -> 0.00078009718 | N70: =(L70/$L$3)-1 -> 0.14484776 | O70: =IF(G70>M70,"Yes","No") -> No | P70: =IF(O70="Yes",1,0) -> 0 | R70: =(L70/$L$38)-1 -> -0.039405312 | S70: 9825.35 | T70: =(S70/S69)-1 -> 0.0010208521 | U70: =(S70/$S$3)-1 -> 0.14478811 | V70: =IF(G70>T70,"Yes","No") -> No | W70: =IF(V70="Yes",1,0) -> 0 | Z70: 1757.22 | AA70: =(Z70/Z69)-1 -> -0.011069903 | AB70: =(Z70/$Z$3)-1 -> 0.16923507
A71: 69 | B71: =B70+7 -> 38219 | D71: 28005.92 | E71: =D71+SUM(Holdings_Old!$E$32:$E$33) -> 28005.92 | F71: =E71-E70 -> 762.65 | G71: =(E71/E70)-1 -> 0.02799407 | H71: =E71-$D$3 -> 5150.07 | I71: =(E71/$D$3)-1 -> 0.22532831 | J71: =(E71/$E$38)-1 -> -0.086251084 | L71: 1098.35 | M71: =(L71/L70)-1 -> 0.031508264 | N71: =(L71/$L$3)-1 -> 0.18091992 | O71: =IF(G71>M71,"Yes","No") -> No | P71: =IF(O71="Yes",1,0) -> 0 | R71: =(L71/$L$38)-1 -> -0.0091386403 | S71: 10110.14 | T71: =(S71/S70)-1 -> 0.028985227 | U71: =(S71/$S$3)-1 -> 0.17797005 | V71: =IF(G71>T71,"Yes","No") -> No | W71: =IF(V71="Yes",1,0) -> 0 | Z71: 1838.02 | AA71: =(Z71/Z70)-1 -> 0.045981721 | AB71: =(Z71/$Z$3)-1 -> 0.22299851
A72: 70 | B72: =B71+7 -> 38226 | D72: 28262.67 | E72: =D72+SUM(Holdings_Old!$E$32:$E$33) -> 28262.67 | F72: =E72-E71 -> 256.75 | G72: =(E72/E71)-1 -> 0.0091677045 | H72: =E72-$D$3 -> 5406.82 | I72: =(E72/$D$3)-1 -> 0.23656176 | J72: =(E72/$E$38)-1 -> -0.077874104 | L72: 1107.77 | M72: =(L72/L71)-1 -> 0.0085765011 | N72: =(L72/$L$3)-1 -> 0.19104808 | O72: =IF(G72>M72,"Yes","No") -> Yes | P72: =IF(O72="Yes",1,0) -> 1 | R72: =(L72/$L$38)-1 -> -0.00064051674 | S72: 10195.01 | T72: =(S72/S71)-1 -> 0.0083945425 | U72: =(S72/$S$3)-1 -> 0.18785857 | V72: =IF(G72>T72,"Yes","No") -> Yes | W72: =IF(V72="Yes",1,0) -> 1 | Z72: 1862.09 | AA72: =(Z72/Z71)-1 -> 0.013095614 | AB72: =(Z72/$Z$3)-1 -> 0.23901443
A73: 71 | B73: =B72+7 -> 38233 | D73: 28172.82 | E73: =D73+SUM(Holdings_Old!$E$32:$E$33) -> 28172.82 | F73: =E73-E72 -> -89.85 | G73: =(E73/E72)-1 -> -0.0031791052 | H73: =E73-$D$3 -> 5316.97 | I73: =(E73/$D$3)-1 -> 0.2326306 | J73: =(E73/$E$38)-1 -> -0.080805639 | L73: 1113.63 | M73: =(L73/L72)-1 -> 0.0052899067 | N73: =(L73/$L$3)-1 -> 0.19734862 | O73: =IF(G73>M73,"Yes","No") -> No | P73: =IF(O73="Yes",1,0) -> 0 | R73: =(L73/$L$38)-1 -> 0.0046460017 | S73: 10260.2 | T73: =(S73/S72)-1 -> 0.0063943047 | U73: =(S73/$S$3)-1 -> 0.1954541 | V73: =IF(G73>T73,"Yes","No") -> No | W73: =IF(V73="Yes",1,0) -> 0 | Z73: 1844.48 | AA73: =(Z73/Z72)-1 -> -0.0094571154 | AB73: =(Z73/$Z$3)-1 -> 0.22729692
A74: 72 | B74: =B73+7 -> 38240 | D74: 28365.95 | E74: =D74+SUM(Holdings_Old!$E$32:$E$33) -> 28365.95 | F74: =E74-E73 -> 193.13 | G74: =(E74/E73)-1 -> 0.0068551888 | H74: =E74-$D$3 -> 5510.1 | I74: =(E74/$D$3)-1 -> 0.24108051 | J74: =(E74/$E$38)-1 -> -0.074504388 | L74: 1123.92 | M74: =(L74/L73)-1 -> 0.0092400528 | N74: =(L74/$L$3)-1 -> 0.20841218 | O74: =IF(G74>M74,"Yes","No") -> No | P74: =IF(O74="Yes",1,0) -> 0 | R74: =(L74/$L$38)-1 -> 0.013928984 | S74: 10313.07 | T74: =(S74/S73)-1 -> 0.005152921 | U74: =(S74/$S$3)-1 -> 0.20161418 | V74: =IF(G74>T74,"Yes","No") -> Yes | W74: =IF(V74="Yes",1,0) -> 1 | Z74: 1894.31 | AA74: =(Z74/Z73)-1 -> 0.027015744 | AB74: =(Z74/$Z$3)-1 -> 0.26045326
A75: 73 | B75: =B74+7 -> 38247 | D75: 28529.49 | E75: =D75+SUM(Holdings_Old!$E$32:$E$33) -> 28529.49 | F75: =E75-E74 -> 163.54 | G75: =(E75/E74)-1 -> 0.005765363 | H75: =E75-$D$3 -> 5673.64 | I75: =(E75/$D$3)-1 -> 0.24823579 | J75: =(E75/$E$38)-1 -> -0.06916857 | L75: 1128.55 | M75: =(L75/L74)-1 -> 0.0041195103 | N75: =(L75/$L$3)-1 -> 0.21339025 | O75: =IF(G75>M75,"Yes","No") -> Yes | P75: =IF(O75="Yes",1,0) -> 1 | R75: =(L75/$L$38)-1 -> 0.018105875 | S75: 10284.46 | T75: =(S75/S74)-1 -> -0.0027741497 | U75: =(S75/$S$3)-1 -> 0.19828072 | V75: =IF(G75>T75,"Yes","No") -> Yes | W75: =IF(V75="Yes",1,0) -> 1 | Z75: 1910.09 | AA75: =(Z75/Z74)-1 -> 0.0083302099 | AB75: =(Z75/$Z$3)-1 -> 0.2709531
A76: 74 | B76: =B75+7 -> 38254 | D76: 27872.35 | E76: =D76+SUM(Holdings_Old!$E$32:$E$34) -> 27872.35 | F76: =E76-E75 -> -657.14 | G76: =(E76/E75)-1 -> -0.02303371 | H76: =E76-$D$3 -> 5016.5 | I76: =(E76/$D$3)-1 -> 0.21948429 | J76: =(E76/$E$38)-1 -> -0.090609071 | L76: 1110.11 | M76: =(L76/L75)-1 -> -0.016339551 | N76: =(L76/$L$3)-1 -> 0.19356399 | O76: =IF(G76>M76,"Yes","No") -> No | P76: =IF(O76="Yes",1,0) -> 0 | R76: =(L76/$L$38)-1 -> 0.0014704821 | S76: 10047.24 | T76: =(S76/S75)-1 -> -0.023065868 | U76: =(S76/$S$3)-1 -> 0.17064134 | V76: =IF(G76>T76,"Yes","No") -> Yes | W76: =IF(V76="Yes",1,0) -> 1 | Z76: 1879.48 | AA76: =(Z76/Z75)-1 -> -0.016025423 | AB76: =(Z76/$Z$3)-1 -> 0.25058554
A77: 75 | B77: =B76+7 -> 38261 | D77: 28443.17 | E77: =D77+SUM(Holdings_Old!$E$32:$E$34) -> 28443.17 | F77: =E77-E76 -> 570.82 | G77: =(E77/E76)-1 -> 0.020479794 | H77: =E77-$D$3 -> 5587.32 | I77: =(E77/$D$3)-1 -> 0.24445908 | J77: =(E77/$E$38)-1 -> -0.071984932 | L77: 1131.5 | M77: =(L77/L76)-1 -> 0.019268361 | N77: =(L77/$L$3)-1 -> 0.21656202 | O77: =IF(G77>M77,"Yes","No") -> Yes | P77: =IF(O77="Yes",1,0) -> 1 | R77: =(L77/$L$38)-1 -> 0.020767177 | S77: 10192.65 | T77: =(S77/S76)-1 -> 0.014472631 | U77: =(S77/$S$3)-1 -> 0.1875836 | V77: =IF(G77>T77,"Yes","No") -> Yes | W77: =IF(V77="Yes",1,0) -> 1 | Z77: 1942.2 | AA77: =(Z77/Z76)-1 -> 0.033370932 | AB77: =(Z77/$Z$3)-1 -> 0.29231875
A78: 76 | B78: =B77+7 -> 38268 | D78: 28277.12 | E78: =D78+SUM(Holdings_Old!$E$32:$E$34) -> 28277.12 | F78: =E78-E77 -> -166.05 | G78: =(E78/E77)-1 -> -0.0058379569 | H78: =E78-$D$3 -> 5421.27 | I78: =(E78/$D$3)-1 -> 0.23719398 | J78: =(E78/$E$38)-1 -> -0.077402644 | L78: 1122.14 | M78: =(L78/L77)-1 -> -0.008272205 | N78: =(L78/$L$3)-1 -> 0.20649837 | O78: =IF(G78>M78,"Yes","No") -> Yes | P78: =IF(O78="Yes",1,0) -> 1 | R78: =(L78/$L$38)-1 -> 0.012323181 | S78: 10055.2 | T78: =(S78/S77)-1 -> -0.013485207 | U78: =(S78/$S$3)-1 -> 0.17156879 | V78: =IF(G78>T78,"Yes","No") -> Yes | W78: =IF(V78="Yes",1,0) -> 1 | Z78: 1919.97 | AA78: =(Z78/Z77)-1 -> -0.011445783 | AB78: =(Z78/$Z$3)-1 -> 0.27752715
A79: 77 | B79: =B78+7 -> 38275 | D79: 28337.96 | E79: =D79+SUM(Holdings_Old!$E$32:$E$34) -> 28337.96 | F79: =E79-E78 -> 60.84 | G79: =(E79/E78)-1 -> 0.0021515628 | H79: =E79-$D$3 -> 5482.11 | I79: =(E79/$D$3)-1 -> 0.23985588 | J79: =(E79/$E$38)-1 -> -0.075417617 | L79: 1108.2 | M79: =(L79/L78)-1 -> -0.012422692 | N79: =(L79/$L$3)-1 -> 0.19151041 | O79: =IF(G79>M79,"Yes","No") -> Yes | P79: =IF(O79="Yes",1,0) -> 1 | R79: =(L79/$L$38)-1 -> -0.00025259815 | S79: 9933.38 | T79: =(S79/S78)-1 -> -0.012115125 | U79: =(S79/$S$3)-1 -> 0.15737509 | V79: =IF(G79>T79,"Yes","No") -> Yes | W79: =IF(V79="Yes",1,0) -> 1 | Z79: 1911.5 | AA79: =(Z79/Z78)-1 -> -0.0044115273 | AB79: =(Z79/$Z$3)-1 -> 0.2718913
A80: 78 | B80: =B79+7 -> 38282 | D80: 28127.87 | E80: =D80+SUM(Holdings_Old!$E$32:$E$34) -> 28127.87 | F80: =E80-E79 -> -210.09 | G80: =(E80/E79)-1 -> -0.0074137306 | H80: =E80-$D$3 -> 5272.02 | I80: =(E80/$D$3)-1 -> 0.23066392 | J80: =(E80/$E$38)-1 -> -0.082272222 | L80: 1095.74 | M80: =(L80/L79)-1 -> -0.011243458 | N80: =(L80/$L$3)-1 -> 0.17811371 | O80: =IF(G80>M80,"Yes","No") -> Yes | P80: =IF(O80="Yes",1,0) -> 1 | R80: =(L80/$L$38)-1 -> -0.011493216 | S80: 9757.81 | T80: =(S80/S79)-1 -> -0.017674749 | U80: =(S80/$S$3)-1 -> 0.13691877 | V80: =IF(G80>T80,"Yes","No") -> Yes | W80: =IF(V80="Yes",1,0) -> 1 | Z80: 1915.14 | AA80: =(Z80/Z79)-1 -> 0.0019042637 | AB80: =(Z80/$Z$3)-1 -> 0.27431332
A81: 79 | B81: =B80+7 -> 38289 | D81: 28846.86 | E81: =D81+SUM(Holdings_Old!$E$32:$E$34) -> 28846.86 | F81: =E81-E80 -> 718.99 | G81: =(E81/E80)-1 -> 0.02556148 | H81: =E81-$D$3 -> 5991.01 | I81: =(E81/$D$3)-1 -> 0.26212151 | J81: =(E81/$E$38)-1 -> -0.058813741 | L81: 1130.2 | M81: =(L81/L80)-1 -> 0.031449066 | N81: =(L81/$L$3)-1 -> 0.21516429 | O81: =IF(G81>M81,"Yes","No") -> No | P81: =IF(O81="Yes",1,0) -> 0 | R81: =(L81/$L$38)-1 -> 0.0195944 | S81: 10027.47 | T81: =(S81/S80)-1 -> 0.027635299 | U81: =(S81/$S$3)-1 -> 0.16833786 | V81: =IF(G81>T81,"Yes","No") -> No | W81: =IF(V81="Yes",1,0) -> 0 | Z81: 1974.99 | AA81: =(Z81/Z80)-1 -> 0.031250979 | AB81: =(Z81/$Z$3)-1 -> 0.31413686
A82: 80 | B82: =B81+7 -> 38296 | D82: 29611.48 | E82: =D82+SUM(Holdings_Old!$E$32:$E$34) -> 29611.48 | F82: =E82-E81 -> 764.62 | G82: =(E82/E81)-1 -> 0.026506178 | H82: =E82-$D$3 -> 6755.63 | I82: =(E82/$D$3)-1 -> 0.29557553 | J82: =(E82/$E$38)-1 -> -0.033866491 | L82: 1166.17 | M82: =(L82/L81)-1 -> 0.031826225 | N82: =(L82/$L$3)-1 -> 0.25383838 | O82: =IF(G82>M82,"Yes","No") -> No | P82: =IF(O82="Yes",1,0) -> 0 | R82: =(L82/$L$38)-1 -> 0.052044241 | S82: 10387.54 | T82: =(S82/S81)-1 -> 0.03590836 | U82: =(S82/$S$3)-1 -> 0.21029096 | V82: =IF(G82>T82,"Yes","No") -> No | W82: =IF(V82="Yes",1,0) -> 0 | Z82: 2038.94 | AA82: =(Z82/Z81)-1 -> 0.032379911 | AB82: =(Z82/$Z$3)-1 -> 0.35668849
A83: 81 | B83: =B82+7 -> 38303 | D83: 29843.74 | E83: =D83+SUM(Holdings_Old!$E$32:$E$34) -> 29843.74 | F83: =E83-E82 -> 232.26 | G83: =(E83/E82)-1 -> 0.0078435796 | H83: =E83-$D$3 -> 6987.89 | I83: =(E83/$D$3)-1 -> 0.30573748 | J83: =(E83/$E$38)-1 -> -0.026288546 | L83: 1184.17 | M83: =(L83/L82)-1 -> 0.015435142 | N83: =(L83/$L$3)-1 -> 0.27319155 | O83: =IF(G83>M83,"Yes","No") -> No | P83: =IF(O83="Yes",1,0) -> 0 | R83: =(L83/$L$38)-1 -> 0.068282693 | S83: 10539.01 | T83: =(S83/S82)-1 -> 0.014581893 | U83: =(S83/$S$3)-1 -> 0.22793929 | V83: =IF(G83>T83,"Yes","No") -> No | W83: =IF(V83="Yes",1,0) -> 0 | Z83: 2085.34 | AA83: =(Z83/Z82)-1 -> 0.022756923 | AB83: =(Z83/$Z$3)-1 -> 0.38756255
A84: 82 | B84: =B83+7 -> 38310 | D84: 28915.95 | E84: =D84+SUM(Holdings_Old!$E$32:$E$34) -> 28915.95 | F84: =E84-E83 -> -927.79 | G84: =(E84/E83)-1 -> -0.031088262 | H84: =E84-$D$3 -> 6060.1 | I84: =(E84/$D$3)-1 -> 0.26514437 | L84: 1170.34 | M84: =(L84/L83)-1 -> -0.011679066 | N84: =(L84/$L$3)-1 -> 0.25832186 | O84: =IF(G84>M84,"Yes","No") -> No | P84: =IF(O84="Yes",1,0) -> 0 | R84: =(L84/$L$38)-1 -> 0.055806149 | S84: 10456.91 | T84: =(S84/S83)-1 -> -0.0077901055 | U84: =(S84/$S$3)-1 -> 0.21837352 | V84: =IF(G84>T84,"Yes","No") -> No | W84: =IF(V84="Yes",1,0) -> 0 | Z84: 2070.63 | AA84: =(Z84/Z83)-1 -> -0.0070540056 | AB84: =(Z84/$Z$3)-1 -> 0.37777467
A85: 83 | B85: =B84+7 -> 38317 | D85: 29040 | E85: =D85+SUM(Holdings_Old!$E$32:$E$34) -> 29040 | F85: =E85-E84 -> 124.05 | G85: =(E85/E84)-1 -> 0.0042900199 | H85: =E85-$D$3 -> 6184.15 | I85: =(E85/$D$3)-1 -> 0.27057187 | L85: 1182.65 | M85: =(L85/L84)-1 -> 0.010518311 | N85: =(L85/$L$3)-1 -> 0.27155729 | O85: =IF(G85>M85,"Yes","No") -> No | P85: =IF(O85="Yes",1,0) -> 0 | R85: =(L85/$L$38)-1 -> 0.066911446 | S85: 10522.23 | T85: =(S85/S84)-1 -> 0.0062465872 | U85: =(S85/$S$3)-1 -> 0.22598419 | V85: =IF(G85>T85,"Yes","No") -> No | W85: =IF(V85="Yes",1,0) -> 0 | Z85: 2101.97 | AA85: =(Z85/Z84)-1 -> 0.01513549 | AB85: =(Z85/$Z$3)-1 -> 0.39862797
A86: 84 | B86: =B85+7 -> 38324 | D86: 29543.51 | E86: =D86+SUM(Holdings_Old!$E$32:$E$34) -> 29543.51 | F86: =E86-E85 -> 503.51 | G86: =(E86/E85)-1 -> 0.017338499 | H86: =E86-$D$3 -> 6687.66 | I86: =(E86/$D$3)-1 -> 0.29260168 | L86: 1191.17 | M86: =(L86/L85)-1 -> 0.0072041601 | N86: =(L86/$L$3)-1 -> 0.28071779 | O86: =IF(G86>M86,"Yes","No") -> Yes | P86: =IF(O86="Yes",1,0) -> 1 | R86: =(L86/$L$38)-1 -> 0.074597647 | S86: 10592.21 | T86: =(S86/S85)-1 -> 0.0066506815 | U86: =(S86/$S$3)-1 -> 0.23413782 | V86: =IF(G86>T86,"Yes","No") -> Yes | W86: =IF(V86="Yes",1,0) -> 1 | Z86: 2147.96 | AA86: =(Z86/Z85)-1 -> 0.021879475 | AB86: =(Z86/$Z$3)-1 -> 0.42922921
A87: 85 | B87: =B86+7 -> 38331 | D87: 29497.24 | E87: =D87+SUM(Holdings_Old!$E$32:$E$34) -> 29497.24 | F87: =E87-E86 -> -46.27 | G87: =(E87/E86)-1 -> -0.0015661646 | H87: =E87-$D$3 -> 6641.39 | I87: =(E87/$D$3)-1 -> 0.29057725 | L87: 1188 | M87: =(L87/L86)-1 -> -0.002661249 | N87: =(L87/$L$3)-1 -> 0.27730948 | O87: =IF(G87>M87,"Yes","No") -> Yes | P87: =IF(O87="Yes",1,0) -> 1 | S87: 10543.22 | T87: =(S87/S86)-1 -> -0.0046250971 | U87: =(S87/$S$3)-1 -> 0.22842981 | V87: =IF(G87>T87,"Yes","No") -> Yes | W87: =IF(V87="Yes",1,0) -> 1 | Z87: 2128.07 | AA87: =(Z87/Z86)-1 -> -0.009259949 | AB87: =(Z87/$Z$3)-1 -> 0.41599462
A88: 86 | B88: =B87+7 -> 38338 | D88: 29715.39 | E88: =D88+SUM(Holdings_Old!$E$32:$E$34) -> 29715.39 | F88: =E88-E87 -> 218.15 | G88: =(E88/E87)-1 -> 0.0073956072 | H88: =E88-$D$3 -> 6859.54 | I88: =(E88/$D$3)-1 -> 0.30012185 | L88: 1194.2 | M88: =(L88/L87)-1 -> 0.0052188552 | N88: =(L88/$L$3)-1 -> 0.28397557 | O88: =IF(G88>M88,"Yes","No") -> Yes | P88: =IF(O88="Yes",1,0) -> 1 | S88: 10649.92 | T88: =(S88/S87)-1 -> 0.010120248 | U88: =(S88/$S$3)-1 -> 0.24086183 | V88: =IF(G88>T88,"Yes","No") -> No | W88: =IF(V88="Yes",1,0) -> 0 | Z88: 2135.2 | AA88: =(Z88/Z87)-1 -> 0.0033504537 | AB88: =(Z88/$Z$3)-1 -> 0.42073885
A89: 87 | B89: =B88+7 -> 38345 | D89: 30168.52 | E89: =D89+SUM(Holdings_Old!$E$32:$E$34) -> 30168.52 | F89: =E89-E88 -> 453.13 | G89: =(E89/E88)-1 -> 0.015249001 | H89: =E89-$D$3 -> 7312.67 | I89: =(E89/$D$3)-1 -> 0.31994741 | L89: 1210.13 | M89: =(L89/L88)-1 -> 0.013339474 | N89: =(L89/$L$3)-1 -> 0.30110313 | O89: =IF(G89>M89,"Yes","No") -> Yes | P89: =IF(O89="Yes",1,0) -> 1 | S89: 10827.12 | T89: =(S89/S88)-1 -> 0.016638623 | U89: =(S89/$S$3)-1 -> 0.26150806 | V89: =IF(G89>T89,"Yes","No") -> No | W89: =IF(V89="Yes",1,0) -> 0 | Z89: 2160.62 | AA89: =(Z89/Z88)-1 -> 0.011905208 | AB89: =(Z89/$Z$3)-1 -> 0.43765304
A90: 88 | B90: =B89+7 -> 38352 | D90: 30139.25 | E90: =D90+SUM(Holdings_Old!$E$32:$E$34) -> 30139.25 | F90: =E90-E89 -> -29.27 | G90: =(E90/E89)-1 -> -0.00097021664 | H90: =E90-$D$3 -> 7283.4 | I90: =(E90/$D$3)-1 -> 0.31866677 | L90: 1211.92 | M90: =(L90/L89)-1 -> 0.0014791799 | N90: =(L90/$L$3)-1 -> 0.3030277 | O90: =IF(G90>M90,"Yes","No") -> No | P90: =IF(O90="Yes",1,0) -> 0 | S90: 10783.01 | T90: =(S90/S89)-1 -> -0.0040740289 | U90: =(S90/$S$3)-1 -> 0.25636864 | V90: =IF(G90>T90,"Yes","No") -> Yes | W90: =IF(V90="Yes",1,0) -> 1 | Z90: 2175.44 | AA90: =(Z90/Z89)-1 -> 0.0068591423 | AB90: =(Z90/$Z$3)-1 -> 0.44751411
A91: 89 | B91: =B90+7 -> 38359 | D91: 29517.05 | E91: =D91+SUM(Holdings_Old!$E$32:$E$34) -> 29517.05 | F91: =E91-E90 -> -622.2 | G91: =(E91/E90)-1 -> -0.020644177 | H91: =E91-$D$3 -> 6661.2 | I91: =(E91/$D$3)-1 -> 0.29144398 | L91: 1186.19 | M91: =(L91/L90)-1 -> -0.021230774 | N91: =(L91/$L$3)-1 -> 0.27536341 | O91: =IF(G91>M91,"Yes","No") -> Yes | P91: =IF(O91="Yes",1,0) -> 1 | S91: 10603.96 | T91: =(S91/S90)-1 -> -0.016604826 | U91: =(S91/$S$3)-1 -> 0.23550686 | V91: =IF(G91>T91,"Yes","No") -> No | W91: =IF(V91="Yes",1,0) -> 0 | Z91: 2088.61 | AA91: =(Z91/Z90)-1 -> -0.039913765 | AB91: =(Z91/$Z$3)-1 -> 0.38973837
A92: 90 | B92: =B91+7 -> 38366 | D92: 29620.68 | E92: =D92+SUM(Holdings_Old!$E$32:$E$34) -> 29620.68 | F92: =E92-E91 -> 103.63 | G92: =(E92/E91)-1 -> 0.0035108522 | H92: =E92-$D$3 -> 6764.83 | I92: =(E92/$D$3)-1 -> 0.29597805 | L92: 1184.52 | M92: =(L92/L91)-1 -> -0.0014078689 | N92: =(L92/$L$3)-1 -> 0.27356787 | O92: =IF(G92>M92,"Yes","No") -> Yes | P92: =IF(O92="Yes",1,0) -> 1 | S92: 10558 | T92: =(S92/S91)-1 -> -0.0043342299 | U92: =(S92/$S$3)-1 -> 0.23015189 | V92: =IF(G92>T92,"Yes","No") -> Yes | W92: =IF(V92="Yes",1,0) -> 1 | Z92: 2087.91 | AA92: =(Z92/Z91)-1 -> -0.00033515113 | AB92: =(Z92/$Z$3)-1 -> 0.3892726
A93: 91 | B93: =B92+7 -> 38373 | D93: 29153.36 | E93: =D93+SUM(Holdings_Old!$E$32:$E$34) -> 29153.36 | F93: =E93-E92 -> -467.32 | G93: =(E93/E92)-1 -> -0.015776815 | H93: =E93-$D$3 -> 6297.51 | I93: =(E93/$D$3)-1 -> 0.27553165 | L93: 1167.87 | M93: =(L93/L92)-1 -> -0.014056327 | N93: =(L93/$L$3)-1 -> 0.25566618 | O93: =IF(G93>M93,"Yes","No") -> No | P93: =IF(O93="Yes",1,0) -> 0 | S93: 10392.99 | T93: =(S93/S92)-1 -> -0.015628907 | U93: =(S93/$S$3)-1 -> 0.21092596 | V93: =IF(G93>T93,"Yes","No") -> No | W93: =IF(V93="Yes",1,0) -> 0 | Z93: 2034.27 | AA93: =(Z93/Z92)-1 -> -0.025690763 | AB93: =(Z93/$Z$3)-1 -> 0.35358112
A94: 92 | B94: =B93+7 -> 38380 | D94: 29468 | E94: =D94+SUM(Holdings_Old!$E$32:$E$34) -> 29468 | F94: =E94-E93 -> 314.64 | G94: =(E94/E93)-1 -> 0.010792581 | H94: =E94-$D$3 -> 6612.15 | I94: =(E94/$D$3)-1 -> 0.28929793 | L94: 1171.36 | M94: =(L94/L93)-1 -> 0.0029883463 | N94: =(L94/$L$3)-1 -> 0.25941854 | O94: =IF(G94>M94,"Yes","No") -> Yes | P94: =IF(O94="Yes",1,0) -> 1 | S94: 10427.2 | T94: =(S94/S93)-1 -> 0.0032916418 | U94: =(S94/$S$3)-1 -> 0.21491189 | V94: =IF(G94>T94,"Yes","No") -> Yes | W94: =IF(V94="Yes",1,0) -> 1 | Z94: 2035.83 | AA94: =(Z94/Z93)-1 -> 0.00076685986 | AB94: =(Z94/$Z$3)-1 -> 0.35461913
A95: 93 | B95: =B94+7 -> 38387 | D95: 30195.15 | E95: =D95+SUM(Holdings_Old!$E$32:$E$34) -> 30195.15 | F95: =E95-E94 -> 727.15 | G95: =(E95/E94)-1 -> 0.02467592 | H95: =E95-$D$3 -> 7339.3 | I95: =(E95/$D$3)-1 -> 0.32111254 | L95: 1203.03 | M95: =(L95/L94)-1 -> 0.027036949 | N95: =(L95/$L$3)-1 -> 0.29346938 | O95: =IF(G95>M95,"Yes","No") -> No | P95: =IF(O95="Yes",1,0) -> 0 | S95: 10716.13 | T95: =(S95/S94)-1 -> 0.02770926 | U95: =(S95/$S$3)-1 -> 0.2485762 | V95: =IF(G95>T95,"Yes","No") -> No | W95: =IF(V95="Yes",1,0) -> 0 | Z95: 2086.66 | AA95: =(Z95/Z94)-1 -> 0.024967704 | AB95: =(Z95/$Z$3)-1 -> 0.38844086
A96: 94 | B96: =B95+7 -> 38394 | D96: 30017.11 | E96: =D96+SUM(Holdings_Old!$E$32:$E$34) -> 30017.11 | F96: =E96-E95 -> -178.04 | G96: =(E96/E95)-1 -> -0.0058963112 | H96: =E96-$D$3 -> 7161.26 | I96: =(E96/$D$3)-1 -> 0.31332285 | L96: 1205.3 | M96: =(L96/L95)-1 -> 0.0018869022 | N96: =(L96/$L$3)-1 -> 0.29591003 | O96: =IF(G96>M96,"Yes","No") -> No | P96: =IF(O96="Yes",1,0) -> 0 | S96: 10796.01 | T96: =(S96/S95)-1 -> 0.0074541836 | U96: =(S96/$S$3)-1 -> 0.25788332 | V96: =IF(G96>T96,"Yes","No") -> No | W96: =IF(V96="Yes",1,0) -> 0 | Z96: 2076.66 | AA96: =(Z96/Z95)-1 -> -0.0047923476 | AB96: =(Z96/$Z$3)-1 -> 0.38178697
A97: 95 | B97: =B96+7 -> 38401 | D97: 30045.41 | E97: =D97+SUM(Holdings_Old!$E$32:$E$34) -> 30045.41 | F97: =E97-E96 -> 28.3 | G97: =(E97/E96)-1 -> 0.00094279563 | H97: =E97-$D$3 -> 7189.56 | I97: =(E97/$D$3)-1 -> 0.31456104 | L97: 1201.59 | M97: =(L97/L96)-1 -> -0.0030780718 | N97: =(L97/$L$3)-1 -> 0.29192113 | O97: =IF(G97>M97,"Yes","No") -> Yes | P97: =IF(O97="Yes",1,0) -> 1 | S97: 10785.22 | T97: =(S97/S96)-1 -> -0.00099944331 | U97: =(S97/$S$3)-1 -> 0.25662614 | V97: =IF(G97>T97,"Yes","No") -> Yes | W97: =IF(V97="Yes",1,0) -> 1 | Z97: 2058.62 | AA97: =(Z97/Z96)-1 -> -0.0086870263 | AB97: =(Z97/$Z$3)-1 -> 0.36978335
A98: 96 | B98: =B97+7 -> 38408 | D98: 30331.03 | E98: =D98+SUM(Holdings_Old!$E$32:$E$34) -> 30331.03 | F98: =E98-E97 -> 285.62 | G98: =(E98/E97)-1 -> 0.0095062773 | H98: =E98-$D$3 -> 7475.18 | I98: =(E98/$D$3)-1 -> 0.32705762 | L98: 1211.37 | M98: =(L98/L97)-1 -> 0.0081392155 | N98: =(L98/$L$3)-1 -> 0.30243635 | O98: =IF(G98>M98,"Yes","No") -> Yes | P98: =IF(O98="Yes",1,0) -> 1 | S98: 10841.6 | T98: =(S98/S97)-1 -> 0.0052275243 | U98: =(S98/$S$3)-1 -> 0.26319518 | V98: =IF(G98>T98,"Yes","No") -> Yes | W98: =IF(V98="Yes",1,0) -> 1 | Z98: 2065.4 | AA98: =(Z98/Z97)-1 -> 0.0032934684 | AB98: =(Z98/$Z$3)-1 -> 0.37429469
... A109: 107 | B109: =B108+7 -> 38485 | D109: 29673.86 | E109: =D109+SUM(Holdings_Old!$E$32:$E$34) -> 29673.86 | F109: =E109-E108 -> -159.64 | G109: =(E109/E108)-1 -> -0.0053510316 | H109: =E109-$D$3 -> 6818.01 | I109: =(E109/$D$3)-1 -> 0.29830481 | L109: 1154.05 | M109: =(L109/L108)-1 -> -0.014769283 | N109: =(L109/$L$3)-1 -> 0.24080724 | O109: =IF(G109>M109,"Yes","No") -> Yes | P109: =IF(O109="Yes",1,0) -> 1 | S109: 10140.12 | T109: =(S109/S108)-1 -> -0.019842635 | U109: =(S109/$S$3)-1 -> 0.18146313 | V109: =IF(G109>T109,"Yes","No") -> Yes | W109: =IF(V109="Yes",1,0) -> 1 | Z109: 1976.78 | AA109: =(Z109/Z108)-1 -> 0.0047932498 | AB109: =(Z109/$Z$3)-1 -> 0.3153279
A110: 108 | B110: =B109+7 -> 38492 | D110: 30096.27 | E110: =D110+SUM(Holdings_Old!$E$32:$E$35) -> 30096.27 | F110: =E110-E109 -> 422.41 | G110: =(E110/E109)-1 -> 0.014235088 | H110: =E110-$D$3 -> 7240.42 | I110: =(E110/$D$3)-1 -> 0.31678629 | L110: 1189.28 | M110: =(L110/L109)-1 -> 0.030527274 | N110: =(L110/$L$3)-1 -> 0.2786857 | O110: =IF(G110>M110,"Yes","No") -> No | P110: =IF(O110="Yes",1,0) -> 0 | S110: 10471.91 | T110: =(S110/S109)-1 -> 0.03272052 | U110: =(S110/$S$3)-1 -> 0.22012122 | V110: =IF(G110>T110,"Yes","No") -> No | W110: =IF(V110="Yes",1,0) -> 0 | Z110: 2046.42 | AA110: =(Z110/Z109)-1 -> 0.035229009 | AB110: =(Z110/$Z$3)-1 -> 0.3616656
A111: 109 | B111: =B110+7 -> 38499 | D111: 29882.27 | E111: =D111+SUM(Holdings_Old!$E$32:$E$35) -> 29882.27 | F111: =E111-E110 -> -214 | G111: =(E111/E110)-1 -> -0.0071105157 | H111: =E111-$D$3 -> 7026.42 | I111: =(E111/$D$3)-1 -> 0.30742326 | L111: 1198.78 | M111: =(L111/L110)-1 -> 0.0079880264 | N111: =(L111/$L$3)-1 -> 0.28889988 | O111: =IF(G111>M111,"Yes","No") -> No | P111: =IF(O111="Yes",1,0) -> 0 | S111: 10542.55 | T111: =(S111/S110)-1 -> 0.0067456653 | U111: =(S111/$S$3)-1 -> 0.22835175 | V111: =IF(G111>T111,"Yes","No") -> No | W111: =IF(V111="Yes",1,0) -> 0 | Z111: 2075.73 | AA111: =(Z111/Z110)-1 -> 0.014322573 | AB111: =(Z111/$Z$3)-1 -> 0.38116816
A112: 110 | B112: =B111+7 -> 38506 | D112: 29745.97 | E112: =D112+SUM(Holdings_Old!$E$32:$E$35) -> 29745.97 | F112: =E112-E111 -> -136.3 | G112: =(E112/E111)-1 -> -0.0045612331 | H112: =E112-$D$3 -> 6890.12 | I112: =(E112/$D$3)-1 -> 0.3014598 | L112: 1196.02 | M112: =(L112/L111)-1 -> -0.0023023407 | N112: =(L112/$L$3)-1 -> 0.28593239 | O112: =IF(G112>M112,"Yes","No") -> No | P112: =IF(O112="Yes",1,0) -> 0 | S112: 10460.97 | T112: =(S112/S111)-1 -> -0.0077381658 | U112: =(S112/$S$3)-1 -> 0.21884656 | V112: =IF(G112>T112,"Yes","No") -> Yes | W112: =IF(V112="Yes",1,0) -> 1 | Z112: 2071.77 | AA112: =(Z112/Z111)-1 -> -0.0019077626 | AB112: =(Z112/$Z$3)-1 -> 0.37853322
A113: 111 | B113: =B112+7 -> 38513 | D113: 30041.64 | E113: =D113+SUM(Holdings_Old!$E$32:$E$35) -> 30041.64 | F113: =E113-E112 -> 295.67 | G113: =(E113/E112)-1 -> 0.0099398339 | H113: =E113-$D$3 -> 7185.79 | I113: =(E113/$D$3)-1 -> 0.3143961 | L113: 1198.11 | M113: =(L113/L112)-1 -> 0.0017474624 | N113: =(L113/$L$3)-1 -> 0.28817951 | O113: =IF(G113>M113,"Yes","No") -> Yes | P113: =IF(O113="Yes",1,0) -> 1 | S113: 10512.63 | T113: =(S113/S112)-1 -> 0.0049383566 | U113: =(S113/$S$3)-1 -> 0.22486566 | V113: =IF(G113>T113,"Yes","No") -> Yes | W113: =IF(V113="Yes",1,0) -> 1 | Z113: 2063 | AA113: =(Z113/Z112)-1 -> -0.0042330954 | AB113: =(Z113/$Z$3)-1 -> 0.37269775
A114: 112 | B114: =B113+7 -> 38520 | D114: 30265.92 | E114: =D114+SUM(Holdings_Old!$E$32:$E$35) -> 30265.92 | F114: =E114-E113 -> 224.28 | G114: =(E114/E113)-1 -> 0.0074656377 | H114: =E114-$D$3 -> 7410.07 | I114: =(E114/$D$3)-1 -> 0.3242089 | L114: 1216.96 | M114: =(L114/L113)-1 -> 0.015733113 | N114: =(L114/$L$3)-1 -> 0.30844659 | O114: =IF(G114>M114,"Yes","No") -> No | P114: =IF(O114="Yes",1,0) -> 0 | S114: 10623.07 | T114: =(S114/S113)-1 -> 0.010505459 | U114: =(S114/$S$3)-1 -> 0.23773344 | V114: =IF(G114>T114,"Yes","No") -> No | W114: =IF(V114="Yes",1,0) -> 0 | Z114: 2090.11 | AA114: =(Z114/Z113)-1 -> 0.013141057 | AB114: =(Z114/$Z$3)-1 -> 0.39073645
A115: 113 | B115: =B114+7 -> 38527 | D115: 29958.18 | E115: =D115+SUM(Holdings_Old!$E$32:$E$35) -> 29958.18 | F115: =E115-E114 -> -307.74 | G115: =(E115/E114)-1 -> -0.010167872 | H115: =E115-$D$3 -> 7102.33 | I115: =(E115/$D$3)-1 -> 0.31074451 | L115: 1191.57 | M115: =(L115/L114)-1 -> -0.020863463 | N115: =(L115/$L$3)-1 -> 0.28114786 | O115: =IF(G115>M115,"Yes","No") -> Yes | P115: =IF(O115="Yes",1,0) -> 1 | S115: 10297.84 | T115: =(S115/S114)-1 -> -0.030615444 | U115: =(S115/$S$3)-1 -> 0.19983968 | V115: =IF(G115>T115,"Yes","No") -> Yes | W115: =IF(V115="Yes",1,0) -> 1 | Z115: 2053.27 | AA115: =(Z115/Z114)-1 -> -0.017625867 | AB115: =(Z115/$Z$3)-1 -> 0.36622352
A116: 114 | B116: =B115+7 -> 38534 | D116: 30063.44 | E116: =D116+SUM(Holdings_Old!$E$32:$E$35) -> 30063.44 | F116: =E116-E115 -> 105.26 | G116: =(E116/E115)-1 -> 0.0035135646 | H116: =E116-$D$3 -> 7207.59 | I116: =(E116/$D$3)-1 -> 0.3153499 | L116: 1194.44 | M116: =(L116/L115)-1 -> 0.002408587 | N116: =(L116/$L$3)-1 -> 0.28423361 | O116: =IF(G116>M116,"Yes","No") -> Yes | P116: =IF(O116="Yes",1,0) -> 1 | S116: 10303.44 | T116: =(S116/S115)-1 -> 0.00054380336 | U116: =(S116/$S$3)-1 -> 0.20049215 | V116: =IF(G116>T116,"Yes","No") -> Yes | W116: =IF(V116="Yes",1,0) -> 1 | Z116: 2057.37 | AA116: =(Z116/Z115)-1 -> 0.0019968148 | AB116: =(Z116/$Z$3)-1 -> 0.36895161
A117: 115 | B117: =B116+7 -> 38541 | D117: 30744.09 | E117: =D117+SUM(Holdings_Old!$E$32:$E$35) -> 30744.09 | F117: =E117-E116 -> 680.65 | G117: =(E117/E116)-1 -> 0.022640456 | H117: =E117-$D$3 -> 7888.24 | I117: =(E117/$D$3)-1 -> 0.34513002 | L117: 1211.86 | M117: =(L117/L116)-1 -> 0.01458424 | N117: =(L117/$L$3)-1 -> 0.30296319 | O117: =IF(G117>M117,"Yes","No") -> Yes | P117: =IF(O117="Yes",1,0) -> 1 | S117: 10449.14 | T117: =(S117/S116)-1 -> 0.014140908 | U117: =(S117/$S$3)-1 -> 0.2174682 | V117: =IF(G117>T117,"Yes","No") -> Yes | W117: =IF(V117="Yes",1,0) -> 1 | Z117: 2112.88 | AA117: =(Z117/Z116)-1 -> 0.026981049 | AB117: =(Z117/$Z$3)-1 -> 0.40588736
A118: 116 | B118: =B117+7 -> 38548 | D118: 31087.04 | E118: =D118+SUM(Holdings_Old!$E$32:$E$35) -> 31087.04 | F118: =E118-E117 -> 342.95 | G118: =(E118/E117)-1 -> 0.011154989 | H118: =E118-$D$3 -> 8231.19 | I118: =(E118/$D$3)-1 -> 0.36013493 | L118: 1227.92 | M118: =(L118/L117)-1 -> 0.013252356 | N118: =(L118/$L$3)-1 -> 0.32023052 | O118: =IF(G118>M118,"Yes","No") -> No | P118: =IF(O118="Yes",1,0) -> 0 | S118: 10640.83 | T118: =(S118/S117)-1 -> 0.01834505 | U118: =(S118/$S$3)-1 -> 0.23980272 | V118: =IF(G118>T118,"Yes","No") -> No | W118: =IF(V118="Yes",1,0) -> 0 | Z118: 2156.78 | AA118: =(Z118/Z117)-1 -> 0.020777328 | AB118: =(Z118/$Z$3)-1 -> 0.43509795
A119: 117 | B119: =B118+7 -> 38555 | D119: 31199.9 | E119: =D119+SUM(Holdings_Old!$E$32:$E$35) -> 31199.9 | F119: =E119-E118 -> 112.86 | G119: =(E119/E118)-1 -> 0.0036304518 | H119: =E119-$D$3 -> 8344.05 | I119: =(E119/$D$3)-1 -> 0.36507284 | L119: 1233.68 | M119: =(L119/L118)-1 -> 0.0046908593 | N119: =(L119/$L$3)-1 -> 0.32642353 | O119: =IF(G119>M119,"Yes","No") -> No | P119: =IF(O119="Yes",1,0) -> 0 | S119: 10651.18 | T119: =(S119/S118)-1 -> 0.00097266849 | U119: =(S119/$S$3)-1 -> 0.24100864 | V119: =IF(G119>T119,"Yes","No") -> Yes | W119: =IF(V119="Yes",1,0) -> 1 | Z119: 2179.74 | AA119: =(Z119/Z118)-1 -> 0.010645499 | AB119: =(Z119/$Z$3)-1 -> 0.45037528
A120: 118 | B120: =B119+7 -> 38562 | D120: 31264.81 | E120: =D120+SUM(Holdings_Old!$E$32:$E$35) -> 31264.81 | F120: =E120-E119 -> 64.91 | G120: =(E120/E119)-1 -> 0.0020804554 | H120: =E120-$D$3 -> 8408.96 | I120: =(E120/$D$3)-1 -> 0.36791281 | L120: 1234.18 | M120: =(L120/L119)-1 -> 0.00040529149 | N120: =(L120/$L$3)-1 -> 0.32696112 | O120: =IF(G120>M120,"Yes","No") -> Yes | P120: =IF(O120="Yes",1,0) -> 1 | S120: 10640.91 | T120: =(S120/S119)-1 -> -0.00096421242 | U120: =(S120/$S$3)-1 -> 0.23981204 | V120: =IF(G120>T120,"Yes","No") -> Yes | W120: =IF(V120="Yes",1,0) -> 1 | Z120: 2184.83 | AA120: =(Z120/Z119)-1 -> 0.0023351409 | AB120: =(Z120/$Z$3)-1 -> 0.45376211
A121: 119 | B121: =B120+7 -> 38569 | D121: 31130 | E121: =D121+SUM(Holdings_Old!$E$32:$E$35) -> 31130 | F121: =E121-E120 -> -134.81 | G121: =(E121/E120)-1 -> -0.0043118765 | H121: =E121-$D$3 -> 8274.15 | I121: =(E121/$D$3)-1 -> 0.36201454 | L121: 1226.42 | M121: =(L121/L120)-1 -> -0.0062875756 | N121: =(L121/$L$3)-1 -> 0.31861775 | O121: =IF(G121>M121,"Yes","No") -> Yes | P121: =IF(O121="Yes",1,0) -> 1 | S121: 10558.03 | T121: =(S121/S120)-1 -> -0.0077888075 | U121: =(S121/$S$3)-1 -> 0.23015538 | V121: =IF(G121>T121,"Yes","No") -> Yes | W121: =IF(V121="Yes",1,0) -> 1 | Z121: 2177.91 | AA121: =(Z121/Z120)-1 -> -0.0031672945 | AB121: =(Z121/$Z$3)-1 -> 0.44915762
... A178: 176 | B178: =B177+7 -> 38968 | D178: 31337.681 | E178: =D178+SUM(Holdings_Old!$E$32:$E$35) -> 31337.681 | F178: =E178-E177 -> -124.19854 | G178: =(E178/E177)-1 -> -0.003947588 | H178: =E178-$D$3 -> 8481.8312 | I178: =(E178/$D$3)-1 -> 0.3711011 | L178: 1298.86 | M178: =(L178/L177)-1 -> -0.0092147619 | N178: =(L178/$L$3)-1 -> 0.39650353 | O178: =IF(G178>M178,"Yes","No") -> Yes | P178: =IF(O178="Yes",1,0) -> 1 | S178: 11392.11 | T178: =(S178/S177)-1 -> -0.0062839373 | U178: =(S178/$S$3)-1 -> 0.32733715 | V178: =IF(G178>T178,"Yes","No") -> Yes | W178: =IF(V178="Yes",1,0) -> 1 | Z178: 2165.79 | AA178: =(Z178/Z177)-1 -> -0.01247971 | AB178: =(Z178/$Z$3)-1 -> 0.4410931
A179: 177 | B179: =B178+7 -> 38975 | D179: =31836.62388+3.49+9.2+3.42 -> 31852.734 | E179: =D179+SUM(Holdings_Old!$E$32:$E$35) -> 31852.734 | F179: =E179-E178 -> 515.05272 | G179: =(E179/E178)-1 -> 0.016435572 | H179: =E179-$D$3 -> 8996.8839 | I179: =(E179/$D$3)-1 -> 0.39363593 | L179: 1319.85 | M179: =(L179/L178)-1 -> 0.016160325 | N179: =(L179/$L$3)-1 -> 0.41907148 | O179: =IF(G179>M179,"Yes","No") -> Yes | P179: =IF(O179="Yes",1,0) -> 1 | S179: 11560.77 | T179: =(S179/S178)-1 -> 0.014804983 | U179: =(S179/$S$3)-1 -> 0.34698835 | V179: =IF(G179>T179,"Yes","No") -> Yes | W179: =IF(V179="Yes",1,0) -> 1 | Z179: 2235.59 | AA179: =(Z179/Z178)-1 -> 0.032228425 | AB179: =(Z179/$Z$3)-1 -> 0.48753726
A180: 178 | B180: =B179+7 -> 38982 | D180: 31597.783 | E180: =D180+SUM(Holdings_Old!$E$32:$E$35) -> 31597.783 | F180: =E180-E179 -> -254.95126 | G180: =(E180/E179)-1 -> -0.0080040621 | H180: =E180-$D$3 -> 8741.9326 | I180: =(E180/$D$3)-1 -> 0.38248119 | L180: 1314.78 | M180: =(L180/L179)-1 -> -0.0038413456 | N180: =(L180/$L$3)-1 -> 0.41362033 | O180: =IF(G180>M180,"Yes","No") -> No | P180: =IF(O180="Yes",1,0) -> 0 | S180: 11508.1 | T180: =(S180/S179)-1 -> -0.0045559249 | U180: =(S180/$S$3)-1 -> 0.34085158 | V180: =IF(G180>T180,"Yes","No") -> No | W180: =IF(V180="Yes",1,0) -> 0 | Z180: 2218.93 | AA180: =(Z180/Z179)-1 -> -0.0074521715 | AB180: =(Z180/$Z$3)-1 -> 0.47645188
A181: 179 | B181: =B180+7 -> 38989 | D181: 31628.077 | E181: =D181+SUM(Holdings_Old!$E$32:$E$35) -> 31628.077 | F181: =E181-E180 -> 30.29398 | G181: =(E181/E180)-1 -> 0.00095873753 | H181: =E181-$D$3 -> 8772.2266 | I181: =(E181/$D$3)-1 -> 0.38380662 | L181: 1335.82 | M181: =(L181/L180)-1 -> 0.016002677 | N181: =(L181/$L$3)-1 -> 0.43624204 | O181: =IF(G181>M181,"Yes","No") -> No | P181: =IF(O181="Yes",1,0) -> 0 | S181: 11679.07 | T181: =(S181/S180)-1 -> 0.014856492 | U181: =(S181/$S$3)-1 -> 0.36077193 | V181: =IF(G181>T181,"Yes","No") -> No | W181: =IF(V181="Yes",1,0) -> 0 | Z181: 2258.43 | AA181: =(Z181/Z180)-1 -> 0.017801373 | AB181: =(Z181/$Z$3)-1 -> 0.50273475
A182: 180 | B182: =B181+7 -> 38996 | D182: 32045.752 | E182: =D182+SUM(Holdings_Old!$E$32:$E$35) -> 32045.752 | F182: =E182-E181 -> 417.67584 | G182: =(E182/E181)-1 -> 0.013205856 | H182: =E182-$D$3 -> 9189.9024 | I182: =(E182/$D$3)-1 -> 0.40208097 | L182: 1349.58 | M182: =(L182/L181)-1 -> 0.010300789 | N182: =(L182/$L$3)-1 -> 0.45103647 | O182: =IF(G182>M182,"Yes","No") -> Yes | P182: =IF(O182="Yes",1,0) -> 1 | S182: 11850.21 | T182: =(S182/S181)-1 -> 0.014653564 | U182: =(S182/$S$3)-1 -> 0.38071209 | V182: =IF(G182>T182,"Yes","No") -> No | W182: =IF(V182="Yes",1,0) -> 0 | Z182: 2299.99 | AA182: =(Z182/Z181)-1 -> 0.018402164 | AB182: =(Z182/$Z$3)-1 -> 0.53038832
A183: 181 | B183: =B182+7 -> 39003 | D183: 32558.329 | E183: =D183+SUM(Holdings_Old!$E$32:$E$35) -> 32558.329 | F183: =E183-E182 -> 512.57647 | G183: =(E183/E182)-1 -> 0.015995145 | H183: =E183-$D$3 -> 9702.4789 | I183: =(E183/$D$3)-1 -> 0.42450746 | L183: 1365.61 | M183: =(L183/L182)-1 -> 0.011877769 | N183: =(L183/$L$3)-1 -> 0.46827155 | O183: =IF(G183>M183,"Yes","No") -> Yes | P183: =IF(O183="Yes",1,0) -> 1 | S183: 11960.51 | T183: =(S183/S182)-1 -> 0.0093078519 | U183: =(S183/$S$3)-1 -> 0.39356355 | V183: =IF(G183>T183,"Yes","No") -> Yes | W183: =IF(V183="Yes",1,0) -> 1 | Z183: 2357.29 | AA183: =(Z183/Z182)-1 -> 0.024913152 | AB183: =(Z183/$Z$3)-1 -> 0.56851512
A184: 182 | B184: =B183+7 -> 39010 | D184: 32608.25 | E184: =D184+SUM(Holdings_Old!$E$32:$E$35) -> 32608.25 | F184: =E184-E183 -> 49.92109 | G184: =(E184/E183)-1 -> 0.0015332817 | H184: =E184-$D$3 -> 9752.4 | I184: =(E184/$D$3)-1 -> 0.42669163 | L184: 1368.58 | M184: =(L184/L183)-1 -> 0.0021748523 | N184: =(L184/$L$3)-1 -> 0.47146482 | O184: =IF(G184>M184,"Yes","No") -> No | P184: =IF(O184="Yes",1,0) -> 0 | S184: 12002.37 | T184: =(S184/S183)-1 -> 0.0034998508 | U184: =(S184/$S$3)-1 -> 0.39844081 | V184: =IF(G184>T184,"Yes","No") -> No | W184: =IF(V184="Yes",1,0) -> 0 | Z184: 2342.3 | AA184: =(Z184/Z183)-1 -> -0.006358997 | AB184: =(Z184/$Z$3)-1 -> 0.55854093
A185: 183 | B185: =B184+7 -> 39017 | D185: 32630.82 | E185: =D185+SUM(Holdings_Old!$E$32:$E$35) -> 32630.82 | F185: =E185-E184 -> 22.57 | G185: =(E185/E184)-1 -> 0.00069215613 | H185: =E185-$D$3 -> 9774.97 | I185: =(E185/$D$3)-1 -> 0.42767913 | L185: 1377.3 | M185: =(L185/L184)-1 -> 0.0063715676 | N185: =(L185/$L$3)-1 -> 0.48084036 | O185: =IF(G185>M185,"Yes","No") -> No | P185: =IF(O185="Yes",1,0) -> 0 | S185: 12090.26 | T185: =(S185/S184)-1 -> 0.0073227204 | U185: =(S185/$S$3)-1 -> 0.4086812 | V185: =IF(G185>T185,"Yes","No") -> No | W185: =IF(V185="Yes",1,0) -> 0 | Z185: 2350.62 | AA185: =(Z185/Z184)-1 -> 0.0035520642 | AB185: =(Z185/$Z$3)-1 -> 0.56407697
A186: 184 | B186: =B185+7 -> 39024 | D186: 32621 | E186: =D186+SUM(Holdings_Old!$E$32:$E$35) -> 32621 | F186: =E186-E185 -> -9.82 | G186: =(E186/E185)-1 -> -0.00030094248 | H186: =E186-$D$3 -> 9765.15 | I186: =(E186/$D$3)-1 -> 0.42724948 | L186: 1364.27 | M186: =(L186/L185)-1 -> -0.0094605387 | N186: =(L186/$L$3)-1 -> 0.46683081 | O186: =IF(G186>M186,"Yes","No") -> Yes | P186: =IF(O186="Yes",1,0) -> 1 | S186: 11986.04 | T186: =(S186/S185)-1 -> -0.008620162 | U186: =(S186/$S$3)-1 -> 0.39653814 | V186: =IF(G186>T186,"Yes","No") -> Yes | W186: =IF(V186="Yes",1,0) -> 1 | Z186: 2330.79 | AA186: =(Z186/Z185)-1 -> -0.0084360722 | AB186: =(Z186/$Z$3)-1 -> 0.55088231
A187: 185 | B187: =B186+7 -> 39031 | D187: 33193.05 | E187: =D187+SUM(Holdings_Old!$E$32:$E$35) -> 33193.05 | F187: =E187-E186 -> 572.05 | G187: =(E187/E186)-1 -> 0.01753625 | H187: =E187-$D$3 -> 10337.2 | I187: =(E187/$D$3)-1 -> 0.45227808 | L187: 1380.58 | M187: =(L187/L186)-1 -> 0.011955112 | N187: =(L187/$L$3)-1 -> 0.48436694 | O187: =IF(G187>M187,"Yes","No") -> Yes | P187: =IF(O187="Yes",1,0) -> 1 | S187: 12108.43 | T187: =(S187/S186)-1 -> 0.010211046 | U187: =(S187/$S$3)-1 -> 0.41079826 | V187: =IF(G187>T187,"Yes","No") -> Yes | W187: =IF(V187="Yes",1,0) -> 1 | Z187: 2389.72 | AA187: =(Z187/Z186)-1 -> 0.025283273 | AB187: =(Z187/$Z$3)-1 -> 0.59009369
A188: 186 | B188: =B187+7 -> 39038 | D188: 33718.23 | E188: =D188+SUM(Holdings_Old!$E$32:$E$35) -> 33718.23 | F188: =E188-E187 -> 525.18 | G188: =(E188/E187)-1 -> 0.015821987 | H188: =E188-$D$3 -> 10862.38 | I188: =(E188/$D$3)-1 -> 0.47525601 | L188: 1401.17 | M188: =(L188/L187)-1 -> 0.014914022 | N188: =(L188/$L$3)-1 -> 0.50650482 | O188: =IF(G188>M188,"Yes","No") -> Yes | P188: =IF(O188="Yes",1,0) -> 1 | S188: 12342.56 | T188: =(S188/S187)-1 -> 0.019336115 | U188: =(S188/$S$3)-1 -> 0.43807762 | V188: =IF(G188>T188,"Yes","No") -> No | W188: =IF(V188="Yes",1,0) -> 0 | Z188: 2445.86 | AA188: =(Z188/Z187)-1 -> 0.023492292 | AB188: =(Z188/$Z$3)-1 -> 0.62744863
A189: 187 | B189: =B188+7 -> 39045 | D189: 33895 | E189: =D189+SUM(Holdings_Old!$E$32:$E$35) -> 33895 | F189: =E189-E188 -> 176.77 | G189: =(E189/E188)-1 -> 0.0052425646 | H189: =E189-$D$3 -> 11039.15 | I189: =(E189/$D$3)-1 -> 0.48299013 | L189: 1400.95 | M189: =(L189/L188)-1 -> -0.00015701164 | N189: =(L189/$L$3)-1 -> 0.50626828 | O189: =IF(G189>M189,"Yes","No") -> Yes | P189: =IF(O189="Yes",1,0) -> 1 | T189: =(S189/S188)-1 -> -1 | U189: =(S189/$S$3)-1 -> -1 | V189: =IF(G189>T189,"Yes","No") -> Yes | W189: =IF(V189="Yes",1,0) -> 1 | Z189: 2460.26 | AA189: =(Z189/Z188)-1 -> 0.0058874997 | AB189: =(Z189/$Z$3)-1 -> 0.63703024
A190: 188 | B190: =B189+7 -> 39052 | C190: =D194-D189 -> 718 | D190: 33896 | E190: =D190+SUM(Holdings_Old!$E$32:$E$35) -> 33896 | F190: =E190-E189 -> 1 | G190: =(E190/E189)-1 -> 2.9502877e-05 | H190: =E190-$D$3 -> 11040.15 | I190: =(E190/$D$3)-1 -> 0.48303388 | L190: 1396.67 | M190: =(L190/L189)-1 -> -0.0030550698 | N190: =(L190/$L$3)-1 -> 0.50166652 | O190: =IF(G190>M190,"Yes","No") -> Yes | P190: =IF(O190="Yes",1,0) -> 1 | T190: =(S190/S189)-1 -> #DIV/0! | U190: =(S190/$S$3)-1 -> -1 | V190: =IF(G190>T190,"Yes","No") -> #DIV/0! | W190: =IF(V190="Yes",1,0) -> #DIV/0! | Z190: 2413.21 | AA190: =(Z190/Z189)-1 -> -0.019123995 | AB190: =(Z190/$Z$3)-1 -> 0.60572368
A191: 189 | B191: =B190+7 -> 39059 | C191: =C190/4 -> 179.5 | D191: 33897 | E191: =D191+SUM(Holdings_Old!$E$32:$E$35) -> 33897 | F191: =E191-E190 -> 1 | G191: =(E191/E190)-1 -> 2.9502006e-05 | H191: =E191-$D$3 -> 11041.15 | I191: =(E191/$D$3)-1 -> 0.48307764 | L191: 1409.81 | M191: =(L191/L190)-1 -> 0.0094080921 | N191: =(L191/$L$3)-1 -> 0.51579434 | O191: =IF(G191>M191,"Yes","No") -> No | P191: =IF(O191="Yes",1,0) -> 0 | T191: =(S191/S190)-1 -> #DIV/0! | U191: =(S191/$S$3)-1 -> -1 | V191: =IF(G191>T191,"Yes","No") -> #DIV/0! | W191: =IF(V191="Yes",1,0) -> #DIV/0! | Z191: 2437.36 | AA191: =(Z191/Z190)-1 -> 0.010007418 | AB191: =(Z191/$Z$3)-1 -> 0.62179282
A192: 190 | B192: =B191+7 -> 39066 | D192: 33898 | E192: =D192+SUM(Holdings_Old!$E$32:$E$35) -> 33898 | F192: =E192-E191 -> 1 | G192: =(E192/E191)-1 -> 2.9501136e-05 | H192: =E192-$D$3 -> 11042.15 | I192: =(E192/$D$3)-1 -> 0.48312139 | L192: 1427.08 | M192: =(L192/L191)-1 -> 0.012249878 | N192: =(L192/$L$3)-1 -> 0.53436264 | O192: =IF(G192>M192,"Yes","No") -> No | P192: =IF(O192="Yes",1,0) -> 0 | T192: =(S192/S191)-1 -> #DIV/0! | U192: =(S192/$S$3)-1 -> -1 | V192: =IF(G192>T192,"Yes","No") -> #DIV/0! | W192: =IF(V192="Yes",1,0) -> #DIV/0! | Z192: 2457.2 | AA192: =(Z192/Z191)-1 -> 0.0081399547 | AB192: =(Z192/$Z$3)-1 -> 0.63499414
A193: 191 | B193: =B192+7 -> 39073 | D193: 33899 | E193: =D193+SUM(Holdings_Old!$E$32:$E$35) -> 33899 | F193: =E193-E192 -> 1 | G193: =(E193/E192)-1 -> 2.9500266e-05 | H193: =E193-$D$3 -> 11043.15 | I193: =(E193/$D$3)-1 -> 0.48316514 | L193: 1410.75 | M193: =(L193/L192)-1 -> -0.011442946 | N193: =(L193/$L$3)-1 -> 0.51680501 | O193: =IF(G193>M193,"Yes","No") -> Yes | P193: =IF(O193="Yes",1,0) -> 1 | T193: =(S193/S192)-1 -> #DIV/0! | U193: =(S193/$S$3)-1 -> -1 | V193: =IF(G193>T193,"Yes","No") -> #DIV/0! | W193: =IF(V193="Yes",1,0) -> #DIV/0! | Z193: 2401.18 | AA193: =(Z193/Z192)-1 -> -0.022798307 | AB193: =(Z193/$Z$3)-1 -> 0.59771905
A194: 192 | B194: =B193+7 -> 39080 | D194: 34613 | E194: =D194+SUM(Holdings_Old!$E$32:$E$35) -> 34613 | F194: =E194-E193 -> 714 | G194: =(E194/E193)-1 -> 0.021062568 | H194: =E194-$D$3 -> 11757.15 | I194: =(E194/$D$3)-1 -> 0.51440441 | L194: 1418.03 | M194: =(L194/L193)-1 -> 0.0051603757 | N194: =(L194/$L$3)-1 -> 0.52463229 | O194: =IF(G194>M194,"Yes","No") -> Yes | P194: =IF(O194="Yes",1,0) -> 1 | T194: =(S194/S193)-1 -> #DIV/0! | U194: =(S194/$S$3)-1 -> -1 | V194: =IF(G194>T194,"Yes","No") -> #DIV/0! | W194: =IF(V194="Yes",1,0) -> #DIV/0! | Z194: 2415.29 | AA194: =(Z194/Z193)-1 -> 0.0058762775 | AB194: =(Z194/$Z$3)-1 -> 0.60710769
A195: 193 | B195: =B194+7 -> 39087 | D195: 34614 | E195: =D195+SUM(Holdings_Old!$E$32:$E$35) -> 34614 | F195: =E195-E194 -> 1 | G195: =(E195/E194)-1 -> 2.8890879e-05 | H195: =E195-$D$3 -> 11758.15 | I195: =(E195/$D$3)-1 -> 0.51444816 | L195: 1409.26 | M195: =(L195/L194)-1 -> -0.0061846364 | N195: =(L195/$L$3)-1 -> 0.51520299 | O195: =IF(G195>M195,"Yes","No") -> Yes | P195: =IF(O195="Yes",1,0) -> 1 | T195: =(S195/S194)-1 -> #DIV/0! | U195: =(S195/$S$3)-1 -> -1 | V195: =IF(G195>T195,"Yes","No") -> #DIV/0! | W195: =IF(V195="Yes",1,0) -> #DIV/0! | Z195: 2434.25 | AA195: =(Z195/Z194)-1 -> 0.007849989 | AB195: =(Z195/$Z$3)-1 -> 0.61972346
A196: 194 | B196: =B195+7 -> 39094 | D196: 34615 | E196: =D196+SUM(Holdings_Old!$E$32:$E$35) -> 34615 | F196: =E196-E195 -> 1 | G196: =(E196/E195)-1 -> 2.8890044e-05 | H196: =E196-$D$3 -> 11759.15 | I196: =(E196/$D$3)-1 -> 0.51449191 | L196: 1430.73 | M196: =(L196/L195)-1 -> 0.015234946 | N196: =(L196/$L$3)-1 -> 0.53828703 | O196: =IF(G196>M196,"Yes","No") -> No | P196: =IF(O196="Yes",1,0) -> 0 | T196: =(S196/S195)-1 -> #DIV/0! | U196: =(S196/$S$3)-1 -> -1 | V196: =IF(G196>T196,"Yes","No") -> #DIV/0! | W196: =IF(V196="Yes",1,0) -> #DIV/0! | Z196: 2502.82 | AA196: =(Z196/Z195)-1 -> 0.028168841 | AB196: =(Z196/$Z$3)-1 -> 0.6653492
...

Sheet Long-Term Chart

Sheet V.P. of PM
G3: Date of Reference | H3: 40920
D4: Sector | E4: $ Value | F4: % Weight | G4: Model Weight | H4: Holdings
D5: Energy | E5: =SUMIF(Holdings_Old!$S$4:$S$25,D5,Holdings_Old!$H$4:$H$25) -> 3958.5 | F5: =E5/$E$17 -> #VALUE! | G5: =IF(F5>0.2,"Overweight",IF(F5>0.125,"Slightly Overweight",IF(F5>0.08,"Equal Weight","Underweight"))) -> #VALUE! | H5: =COUNTIF(Holdings_Old!$S$4:$S$25,'V.P. of PM'!D5) -> 1
D6: Materials | E6: =SUMIF(Holdings_Old!$S$4:$S$25,D6,Holdings_Old!$H$4:$H$25) -> 0 | F6: =E6/$E$17 -> #VALUE! | G6: =IF(F6>0.2,"Overweight",IF(F6>0.125,"Slightly Overweight",IF(F6>0.08,"Equal Weight","Underweight"))) -> #VALUE! | H6: =COUNTIF(Holdings_Old!$S$4:$S$25,'V.P. of PM'!D6) -> 0
D7: Industrials | E7: =SUMIF(Holdings_Old!$S$4:$S$25,D7,Holdings_Old!$H$4:$H$25) -> #VALUE! | F7: =E7/$E$17 -> #VALUE! | G7: =IF(F7>0.2,"Overweight",IF(F7>0.125,"Slightly Overweight",IF(F7>0.08,"Equal Weight","Underweight"))) -> #VALUE! | H7: =COUNTIF(Holdings_Old!$S$4:$S$25,'V.P. of PM'!D7) -> 4
D8: Consumer Discretionary | E8: =SUMIF(Holdings_Old!$S$4:$S$25,D8,Holdings_Old!$H$4:$H$25) -> 8570.4753 | F8: =E8/$E$17 -> #VALUE! | G8: =IF(F8>0.2,"Overweight",IF(F8>0.125,"Slightly Overweight",IF(F8>0.08,"Equal Weight","Underweight"))) -> #VALUE! | H8: =COUNTIF(Holdings_Old!$S$4:$S$25,'V.P. of PM'!D8) -> 4
D9: Consumer Staples | E9: =SUMIF(Holdings_Old!$S$4:$S$25,D9,Holdings_Old!$H$4:$H$25) -> 2260 | F9: =E9/$E$17 -> #VALUE! | G9: =IF(F9>0.2,"Overweight",IF(F9>0.125,"Slightly Overweight",IF(F9>0.08,"Equal Weight","Underweight"))) -> #VALUE! | H9: =COUNTIF(Holdings_Old!$S$4:$S$25,'V.P. of PM'!D9) -> 1
D10: Healthcare | E10: =SUMIF(Holdings_Old!$S$4:$S$25,D10,Holdings_Old!$H$4:$H$25) -> 4656.1696 | F10: =E10/$E$17 -> #VALUE! | G10: =IF(F10>0.2,"Overweight",IF(F10>0.125,"Slightly Overweight",IF(F10>0.08,"Equal Weight","Underweight"))) -> #VALUE! | H10: =COUNTIF(Holdings_Old!$S$4:$S$25,'V.P. of PM'!D10) -> 2
D11: Financial | E11: =SUMIF(Holdings_Old!$S$4:$S$25,D11,Holdings_Old!$H$4:$H$25) -> 5435.5853 | F11: =E11/$E$17 -> #VALUE! | G11: =IF(F11>0.2,"Overweight",IF(F11>0.125,"Slightly Overweight",IF(F11>0.08,"Equal Weight","Underweight"))) -> #VALUE! | H11: =COUNTIF(Holdings_Old!$S$4:$S$25,'V.P. of PM'!D11) -> 3
D12: Information Technology | E12: =SUMIF(Holdings_Old!$S$4:$S$25,D12,Holdings_Old!$H$4:$H$25) -> 10437.751 | F12: =E12/$E$17 -> #VALUE! | G12: =IF(F12>0.2,"Overweight",IF(F12>0.125,"Slightly Overweight",IF(F12>0.08,"Equal Weight","Underweight"))) -> #VALUE! | H12: =COUNTIF(Holdings_Old!$S$4:$S$25,'V.P. of PM'!D12) -> 4
D13: Telecommunications | E13: =SUMIF(Holdings_Old!$S$4:$S$25,D13,Holdings_Old!$H$4:$H$25) -> 0 | F13: =E13/$E$17 -> #VALUE! | G13: =IF(F13>0.2,"Overweight",IF(F13>0.125,"Slightly Overweight",IF(F13>0.08,"Equal Weight","Underweight"))) -> #VALUE! | H13: =COUNTIF(Holdings_Old!$S$4:$S$25,'V.P. of PM'!D13) -> 0
D14: Misc | E14: =SUMIF(Holdings_Old!$S$4:$S$25,D14,Holdings_Old!$H$4:$H$25) -> 2147.6617 | F14: =E14/$E$17 -> #VALUE! | G14: =IF(F14>0.2,"Overweight",IF(F14>0.125,"Slightly Overweight",IF(F14>0.08,"Equal Weight","Underweight"))) -> #VALUE! | H14: =COUNTIF(Holdings_Old!$S$4:$S$25,'V.P. of PM'!D14) -> 2
D15: Utilities | E15: =SUMIF(Holdings_Old!$S$4:$S$25,D15,Holdings_Old!$H$4:$H$25) -> 0 | F15: =E15/$E$17 -> #VALUE! | G15: =IF(F15>0.2,"Overweight",IF(F15>0.125,"Slightly Overweight",IF(F15>0.08,"Equal Weight","Underweight"))) -> #VALUE! | H15: =COUNTIF(Holdings_Old!$S$4:$S$25,'V.P. of PM'!D15) -> 0
D16: Cash | E16: =SUMIF(Holdings_Old!$S$4:$S$25,D16,Holdings_Old!$H$4:$H$25) -> 2029.73 | F16: =E16/$E$17 -> #VALUE! | G16: =IF(F16>0.2,"Overweight",IF(F16>0.125,"Slightly Overweight",IF(F16>0.08,"Equal Weight","Underweight"))) -> #VALUE! | H16: =COUNTIF(Holdings_Old!$S$4:$S$25,'V.P. of PM'!D16) -> 1
D17: Totals | E17: =SUM(E5:E16) -> #VALUE! | F17: =SUM(F5:F16) -> #VALUE! | H17: =SUM(H5:H16) -> 22
D20: Return Period | E20: I.P.O. | F20: S&P 500 | G20: Comments
D21: 1 Week | E21: =OFFSET(Data!G3,MATCH('V.P. of PM'!H3,Data!B3:B459,0)-1,,) -> 0.01027 | F21: =OFFSET(Data!M3,MATCH('V.P. of PM'!H3,Data!B3:B459,0)-1,,) -> 0.013843999 | G21: ="Seidman I.P.O. "&IF(E21>F21,"out-performed","under-performed")&" the S&P 500 by "&ABS(ROUND((E21-F21),4))*100&"%." -> Seidman I.P.O. under-performed the S&P 500 by 0.36%.
D22: 1 Month | E22: =((OFFSET(Data!$D$3,MATCH($H$3,Data!$B$3:$B$459,0)-1,,)-(OFFSET(Data!$D$3,MATCH($H$3,Data!$B$3:$B$459,0)-5,,)))/(OFFSET(Data!$D$3,MATCH($H$3,Data!$B$3:$B$459,0)-5,,))) -> 0.066528308 | F22: =((OFFSET(Data!$L$3,MATCH($H$3,Data!$B$3:$B$459,0)-1,,)-(OFFSET(Data!$L$3,MATCH($H$3,Data!$B$3:$B$459,0)-5,,)))/(OFFSET(Data!$L$3,MATCH($H$3,Data!$B$3:$B$459,0)-5,,))) -> 0.062181264 | G22: ="Seidman I.P.O. "&IF(E22>F22,"out-performed","under-performed")&" the S&P 500 by "&ABS(ROUND((E22-F22),4))*100&"%." -> Seidman I.P.O. out-performed the S&P 500 by 0.43%.
D23: 3 Month | E23: =((OFFSET(Data!$D$3,MATCH($H$3,Data!$B$3:$B$459,0)-1,,)-(OFFSET(Data!$D$3,MATCH($H$3,Data!$B$3:$B$459,0)-14,,)))/(OFFSET(Data!$D$3,MATCH($H$3,Data!$B$3:$B$459,0)-14,,))) -> 0.089310301 | F23: =((OFFSET(Data!$L$3,MATCH($H$3,Data!$B$3:$B$459,0)-1,,)-(OFFSET(Data!$L$3,MATCH($H$3,Data!$B$3:$B$459,0)-14,,)))/(OFFSET(Data!$L$3,MATCH($H$3,Data!$B$3:$B$459,0)-14,,))) -> 0.076300616 | G23: ="Seidman I.P.O. "&IF(E23>F23,"out-performed","under-performed")&" the S&P 500 by "&ABS(ROUND((E23-F23),4))*100&"%." -> Seidman I.P.O. out-performed the S&P 500 by 1.3%.
D24: 6 Month | E24: =((OFFSET(Data!$D$3,MATCH($H$3,Data!$B$3:$B$459,0)-1,,)-(OFFSET(Data!$D$3,MATCH($H$3,Data!$B$3:$B$459,0)-27,,)))/(OFFSET(Data!$D$3,MATCH($H$3,Data!$B$3:$B$459,0)-27,,))) -> 0.039868845 | F24: =((OFFSET(Data!$L$3,MATCH($H$3,Data!$B$3:$B$459,0)-1,,)-(OFFSET(Data!$L$3,MATCH($H$3,Data!$B$3:$B$459,0)-27,,)))/(OFFSET(Data!$L$3,MATCH($H$3,Data!$B$3:$B$459,0)-27,,))) -> -0.015682222 | G24: ="Seidman I.P.O. "&IF(E24>F24,"out-performed","under-performed")&" the S&P 500 by "&ABS(ROUND((E24-F24),4))*100&"%." -> Seidman I.P.O. out-performed the S&P 500 by 5.56%.
D25: 1 Year | E25: =((OFFSET(Data!$D$3,MATCH($H$3,Data!$B$3:$B$459,0)-1,,)-(OFFSET(Data!$D$3,MATCH($H$3,Data!$B$3:$B$459,0)-53,,)))/(OFFSET(Data!$D$3,MATCH($H$3,Data!$B$3:$B$459,0)-53,,))) -> 0.02162054 | F25: =((OFFSET(Data!$L$3,MATCH($H$3,Data!$B$3:$B$459,0)-1,,)-(OFFSET(Data!$L$3,MATCH($H$3,Data!$B$3:$B$459,0)-53,,)))/(OFFSET(Data!$L$3,MATCH($H$3,Data!$B$3:$B$459,0)-53,,))) -> 0.0017475488 | G25: ="Seidman I.P.O. "&IF(E25>F25,"out-performed","under-performed")&" the S&P 500 by "&ABS(ROUND((E25-F25),4))*100&"%." -> Seidman I.P.O. out-performed the S&P 500 by 1.99%.
D26: 2 Year | E26: =((OFFSET(Data!$D$3,MATCH($H$3,Data!$B$3:$B$459,0)-1,,)-(OFFSET(Data!$D$3,MATCH($H$3,Data!$B$3:$B$459,0)-105,,)))/(OFFSET(Data!$D$3,MATCH($H$3,Data!$B$3:$B$459,0)-105,,))) -> 0.108796 | F26: =((OFFSET(Data!$L$3,MATCH($H$3,Data!$B$3:$B$459,0)-1,,)-(OFFSET(Data!$L$3,MATCH($H$3,Data!$B$3:$B$459,0)-105,,)))/(OFFSET(Data!$L$3,MATCH($H$3,Data!$B$3:$B$459,0)-105,,))) -> 0.14037501 | G26: ="Seidman I.P.O. "&IF(E26>F26,"out-performed","under-performed")&" the S&P 500 by "&ABS(ROUND((E26-F26),4))*100&"%." -> Seidman I.P.O. under-performed the S&P 500 by 3.16%.
D29: Mkt Cap | E29: Cap $ Value | G29: Cap % Weight
D30: Large | E30: =SUMIF(Holdings_Old!X5:X25,"large",Holdings_Old!H5:H25) -> #VALUE! | G30: =E30/$E$35 -> #VALUE!
D31: Mid | E31: =SUMIF(Holdings_Old!$X$4:$X$25,"Mid",Holdings_Old!$H$4:$H$25) -> 4047.0773 | G31: =E31/$E$35 -> #VALUE!
D32: Small | E32: =SUMIF(Holdings_Old!$X$4:$X$25,"Small",Holdings_Old!$H$4:$H$25) -> 13454.671 | G32: =E32/$E$35 -> #VALUE!
D33: Bond | E33: =SUMIF(Holdings_Old!$X$4:$X$25,'V.P. of PM'!D33,Holdings_Old!$H$4:$H$25) -> 0 | G33: =E33/$E$35 -> #VALUE!
D34: Cash | E34: =SUMIF(Holdings_Old!$X$4:$X$25,'V.P. of PM'!D34,Holdings_Old!$H$4:$H$25) -> 2029.73 | G34: =E34/$E$35 -> #VALUE!
D35: Total | E35: =SUM(E30:E34) -> #VALUE! | G35: =SUM(G30:G34) -> #VALUE!

Sheet GICS Sector Allocation

Sheet Transactions
B2: Seidman I.P.O. Transaction History (starting 5/12/03)
B4: Date | C4: Type | D4: Ticker | E4: Price | F4: Shares | G4: Total Value | H4: Commission | I4: Vote | J4: Pitched By
B5: 37753 | C5: SC | D5: NVDA | E5: 20.04 | F5: 30 | G5: =F5*E5 -> 601.2 | H5: 0 | I5: 1
B7: 38289 | C7: SC | D7: F | E7: 12.95 | F7: 65 | G7: =E7*F7 -> 841.75 | H7: 10.99 | I7: 0.82
B9: 38296 | C9: BO | D9: GNTX | E9: 33.1 | F9: 40 | G9: =E9*F9 -> 1324 | H9: 10.99 | I9: 0.79
B11: 38296 | C11: BO | D11: MMM | E11: 79.9 | F11: 20 | G11: =E11*F11 -> 1598 | H11: 10.99 | I11: 0.72
B13: 38408 | C13: BO | D13: QCOM | E13: 35.37 | F13: 41 | G13: =E13*F13 -> 1450.17 | H13: 10.99 | I13: 0.75
B15: 38408 | C15: SC | D15: HNP | E15: 30.65 | F15: 42 | G15: =E15*F15 -> 1287.3 | H15: 10.99 | I15: 0.84
B17: 38670 | C17: BO | D17: CEDC | E17: 27.8 | F17: 21 | G17: =F17*E17 -> 583.8 | H17: 9.99 | I17: 0.9
B19: 38744 | C19: SC | D19: LUV | E19: 16.302 | F19: 122 | G19: =E19*F19 -> 1988.844 | H19: 10.99 | I19: 0.97
B21: 38989 | C21: BO | D21: UPS | E21: 72.66 | F21: 40 | G21: =E21*F21 -> 2906.4 | H21: 10.99 | I21: =40/43 -> 0.93023256
B23: 39010 | C23: SC | D23: OPCHX | E23: 9.37 | F23: 190.132 | G23: =E23*F23 -> 1781.5368 | H23: 0 | I23: 0.98
B25: 39010 | C25: SC | D25: SAHYX | E25: 8.39 | F25: 217.855 | G25: =E25*F25 -> 1827.8035 | H25: 0 | I25: 0.84
B27: 39031 | C27: SC | D27: INTC | E27: 20.61 | F27: 50 | G27: =F27*E27 -> 1030.5 | H27: 9.99 | I27: 0.82
B29: 39115 | C29: BO | D29: CPL | E29: 41 | F29: 45 | G29: =F29*E29 -> 1845 | H29: 9.99 | I29: 0.9
B31: 39115 | C31: BO | D31: MNT | E31: 51.92 | F31: 35 | G31: =F31*E31 -> 1817.2 | H31: 9.99 | I31: 0.8
B33: 39136 | C33: SC | D33: MSFT | E33: 29.1225 | F33: 38 | G33: =F33*E33 -> 1106.655 | H33: 9.99 | I33: 0.85
B35: 39373 | C35: SC | D35: PTR | E35: 243.55 | F35: 13 | G35: =F35*E35 -> 3166.15 | H35: 9.99 | I35: 0.98
B37: 39387 | C37: BO | D37: PBW | E37: 24.53 | F37: 100 | G37: =F37*E37 -> 2453 | H37: 9.99 | I37: 0.8
B39: 39850 | C39: BO | D39: ITRI | E39: 62.69 | F39: 25 | G39: 1567.29 | H39: 9.99 | I39: 0.96
B41: 40094 | C41: SO | D41: CEDC | E41: 2.7 | F41: 100 | G41: 270 | H41: 9.99 | I41: 0.915 | K41: Sell Call
B43: 40108 | C43: SC | D43: ERTS | E43: 20.19 | F43: 22 | G43: 434.17 | H43: 9.99 | I43: 0.95
B45: 40122 | C45: BO | D45: DRI | E45: 32.72 | F45: 50 | G45: 1645.99 | H45: 9.99 | I45: 0.75
B47: 40129 | C47: SC | D47: MMM | E47: 77.22 | F47: 21 | G47: 1621.62 | H47: 9.99 | I47: 0.96
B49: 40129 | C49: SC | D49: WAG | E49: 39.06 | F49: 46 | G49: 1796.76 | H49: 9.99 | I49: 0.96
B51: 40129 | C51: BO | D51: TTEK | E51: 25.46 | F51: 60 | G51: 1527.6 | H51: 9.99 | I51: 0.68
B53: 40129 | C53: BO | D53: HCP | E53: 29.24 | F53: 52 | G53: 1520.48 | H53: 9.99 | I53: 0.73
B55: 40210 | C55: BO | D55: BRK.B | E55: 77.89 | F55: 26 | G55: =E55*F55 -> 2025.14 | H55: 9.99 | I55: 0.78
B57: 40210 | C57: SC | D57: C | E57: 3.36 | F57: 33 | G57: =E57*F57 -> 110.88 | H57: 9.99 | I57: 0.73
B59: 40214 | C59: SC | D59: PBW | E59: 9.34 | F59: 250 | G59: =E59*F59 -> 2335 | H59: 9.99 | I59: 0.78
B61: 40242 | C61: BO | D61: WMMVY | E61: 50 | F61: 25 | G61: =E61*F61 -> 1250 | H61: 9.99 | I61: 0.82
C63: BO | D63: C | E63: 1.14 | F63: 800 | G63: =E63*F63 -> 912 | K63: Buy Call
B65: 40466 | C65: SC | D65: CEDC | E65: 23.93 | F65: 100 | G65: =E65*F65 -> 2393 | H65: 9.99 | I65: 1
B67: 40466 | C67: SC | D67: CPL | E67: 74.08 | F67: 43 | G67: =E67*F67 -> 3185.44 | H67: 9.99 | I67: 0.94
B69: 40466 | C69: BO | D69: PGX | E69: 14.43 | F69: 117 | G69: =E69*F69 -> 1688.31 | H69: 9.99 | I69: 0.97
B71: 40480 | C71: BO | D71: SINA | E71: 56.3 | F71: 27 | G71: =E71*F71 -> 1520.1 | H71: 9.99 | I71: 0.93
B73: 40480 | C73: BO | D73: XRX | E73: 10.89 | F73: 100 | G73: =E73*F73 -> 1089 | H73: 9.99
B75: 40616 | C75: SC | D75: DRI | E75: 46.6 | F75: 51 | G75: =F75*E75 -> 2376.6 | H75: 9.99 | I75: 0.86
B77: 40616 | C77: BO | D77: VALE | E77: 32.16 | F77: 34 | G77: =F77*E77 -> 1093.44 | H77: 9.99 | I77: 0.88
B79: 40658 | C79: SC | D79: SINA | E79: 135.35 | F79: 27 | G79: =E79*F79 -> 3654.45 | H79: 9.99
B81: 40773 | C81: BO | D81: GLD | E81: 177.43 | F81: 9 | G81: =E81*F81 -> 1596.87 | H81: 9.99 | J81: Will Hibler
B83: 40829 | C83: BO | D83: MCLOX | E83: 17.23 | F83: 87.057 | G83: =E83*F83 -> 1499.9921 | H83: 9.99 | I83: 0.69 | J83: Hunter Lewis
B85: 40891 | C85: SC | D85: GLD | E85: 156.06 | F85: 9 | G85: =E85*F85 -> 1404.54 | H85: 9.99 | I85: - | J85: Will Hibler
B87: 40942 | C87: SC | D87: PFE | E87: 21.22 | F87: 41 | G87: =F87*E87 -> 870.02 | H87: 9.99 | J87: E-board
B89: 40942 | C89: BO | D89: F | E89: 12.47 | F89: 65 | G89: =F89*E89 -> 810.55 | H89: 9.99 | J89: Turner Novak
B91: 41166 | C91: SC | D91: VALE | E91: 19.71 | F91: 36.591 | G91: 711.2 | H91: 9.99 | I91: 0.85 | J91: Mark Blazo
B93: 41173 | C93: BO | D93: TSN | E93: 16.65 | F93: 100 | G93: 1674.98 | H93: 9.99 | I93: 0.66 | J93: Jeff Reinis
B95: 41215 | C95: SC | D95: CPL | E95: 23 | F95: 57.813 | G95: 1319.69 | H95: 9.99 | I95: 0.72 | J95: Jake Freeland
B97: 41215 | C97: BO | D97: TPC | E97: 12.43 | F97: 150 | G97: 1875.74 | H97: 9.99 | I97: 0.78 | J97: Caleb Pols, Chelsea Behrrens, Emir Ibrahimovic, Mark Blazo
B99: 41222 | C99: BO | D99: CAT | E99: 83 | F99: 15 | G99: 1319.69 | H99: 9.99 | I99: 0.72 | J99: Eric Graverson, Pat Scheffers, Sydney Braddock, Tyler Murray
B101: 41243 | C101: BO | D101: NGVC | E101: 19.49 | F101: 75 | G101: 1471.73 | H101: 9.99 | I101: 0.96 | J101: Turner Novak
B103: 41243 | C103: SC | D103: SYK | E103: 54.07 | F103: 41.745 | G103: 2247.11 | H103: 9.99 | I103: 0.96 | J103: Turner Novak
B105: 41298 | C105: SC | D105: PGX | E105: 14.86 | F105: 134.993 | G105: =F105*E105 -> 2005.996 | H105: 9.99 | I105: 1 | J105: Jake Freeland
B107: 41334 | C107: BO | D107: YHOO | E107: 21.75 | F107: 100 | G107: =F107*E107 -> 2175 | H107: 9.99 | I107: =(31/40) -> 0.775 | J107: Turner Novak
B109: 41355 | C109: SC | D109: PTR | E109: 131.71 | F109: 15.202 | G109: =F109*E109 -> 2002.2554 | H109: 9.99 | I109: 0.76 | J109: Jake Freeland
B111: 41355 | C111: SC | D111: UPS | E111: 83.3 | F111: 47.706 | G111: =F111*E111 -> 3973.9098 | H111: 9.99 | I111: 0.78 | J111: Eric Graverson, Turner Novak
B113: 41355 | C113: BO | D113: YRCW | E113: 8.61 | F113: 300 | G113: =F113*E113 -> 2583 | H113: 9.99 | I113: 0.78 | J113: Eric Graverson, Turner Novak
B115: 41365 | C115: SC | D115: F | E115: 13.01 | F115: 66.476 | G115: =F115*E115 -> 864.85276 | H115: 9.99 | I115: 0.76 | J115: Jeff Reinis
B117: 41365 | C117: BO | D117: DAL | E117: 16.48 | F117: 150 | G117: =F117*E117 -> 2472 | H117: 9.99 | I117: 0.76 | J117: Jeff Reinis
B119: 41397 | C119: SC | D119: YRCW | E119: 11.25 | F119: 100 | G119: =F119*E119 -> 1125 | H119: 9.99 | I119: - | J119: E-board
B121: 41416 | C121: SC | D121: TTEK | E121: 28.061 | F121: 60 | G121: =F121*E121 -> 1683.66 | H121: 9.99 | I121: - | J121: E-board
B123: 41416 | C123: SC | D123: WMMVY | E123: 28.75 | F123: 53.13 | G123: =F123*E123 -> 1527.4875 | H123: 9.99 | I123: - | J123: E-board
B125: 41416 | C125: BO | D125: CX | E125: 11.61 | F125: 150 | G125: =F125*E125 -> 1741.5 | H125: 9.99 | I125: - | J125: E-board
B127: 41416 | C127: BO | D127: CX | E127: 11.46 | F127: 50 | G127: =F127*E127 -> 573 | H127: 9.99 | I127: - | J127: E-board
B129: 41416 | C129: BO | D129: TPC | E129: 17.73 | F129: 50 | G129: =F129*E129 -> 886.5 | H129: 9.99 | I129: - | J129: E-board
B131: 41424 | C131: SC | D131: ITRI | E131: 41.2 | F131: 25 | G131: =F131*E131 -> 1030 | H131: 9.99 | I131: - | J131: E-board
B133: 41424 | C133: BO | D133: IMMR | E133: 15.04 | F133: 135 | G133: =F133*E133 -> 2030.4 | H133: 9.99 | I133: - | J133: E-board
B135: 41438 | C135: SC | D135: HCP | E135: 45.66 | F135: 62 | G135: =F135*E135 -> 2830.92 | H135: 9.99 | I135: - | J135: E-board
B137: 41438 | C137: SC | D137: QCOM | E137: 61.03 | F137: 45 | G137: =F137*E137 -> 2746.35 | H137: 9.99 | I137: - | J137: E-board
B139: 41438 | C139: SC | D139: XRX | E139: 8.86 | F139: 105 | G139: =F139*E139 -> 930.3 | H139: 9.99 | I139: - | J139: E-board
B141: 41438 | C141: BO | D141: INTC | E141: 24.72 | F141: 112 | G141: =F141*E141 -> 2768.64 | H141: 9.99 | I141: - | J141: E-board
D143: Types of Transactions
B144: QUE | D144: BO | E144: Buy to Open your position.
D145: BC | E145: Buy to Close your position, "covering a short sell."
D146: SO | E146: Sell to Open your position, "short selling" / options
D147: SC | E147: Sell to Close your position.

Sheet Holdings_Old
B3: Ticker | C3: Holding | E3: Price | F3: Paid | G3: Shares | H3: Value | I3: Initial Cost | J3: Value on 9/6/12 | K3: Value 1 week ago | M3: $ Total Gain | N3: % Total Gain | O3: Semester | P3: Weekly | Q3: Today | S3: Sector | U3: Portfolio % Weight | W3: Mkt Cap (Billions) | Z3: P/E Ratio | AA3: EPS | AC3: Daily Return
B4: Cash | C4: Cash | E4: 1 | F4: =E4 -> 1 | G4: 2029.73 | H4: =E4*G4 -> 2029.73 | I4: =F4*G4 -> 2029.73 | J4: 4804 | K4: 2029.73 | S4: Cash | U4: =H4/$H$27 -> #VALUE! | W4: - | X4: Cash | AC4: =(0.01/365)*U4 -> #VALUE!
B5: BRK.B | C5: ='Holdings Pull Sheet'!C16 -> Berkshire Hathaway Ord Shs Class B | E5: ='Holdings Pull Sheet'!F16 -> 114.99 | F5: 77.89 | G5: 26 | H5: =E5*G5 -> 2989.74 | I5: =F5*ROUNDDOWN(G5,0)+9.95 -> 2035.09 | J5: 2248.22 | K5: 2287.22 | M5: =H5-I5 -> 954.65 | N5: =(H5/I5)-1 -> 0.46909473 | O5: =(H5/J5)-1 -> 0.32982535 | P5: =(H5/K5)-1 -> 0.30715016 | Q5: =('Holdings Pull Sheet'!F16/'Holdings Pull Sheet'!G16)-1 -> 0.018061089 | S5: Financial | U5: =H5/$H$27 -> #VALUE! | W5: ='Holdings Pull Sheet'!O16/1000000000 -> 283.48254 | X5: =IF(W5<2,"Small", IF(W5<10, "Mid", IF(W5>10, "Large"))) -> Large | Z5: ='Holdings Pull Sheet'!Q16 -> 17 | AA5: ='Holdings Pull Sheet'!P16 -> 9988.97 | AC5: =Q5*U5 -> #VALUE!
C6: ='Holdings Pull Sheet'!C17 -> BlackRock Global Allocation Inv C | E6: ='Holdings Pull Sheet'!F17 -> 19.39 | F6: 17.23 | G6: 89.052 | H6: =E6*G6 -> 1726.7183 | I6: =F6*ROUNDDOWN(G6,0)+9.95 -> 1543.42 | J6: 1602.0455 | K6: 1610.9507 | M6: =H6-I6 -> 183.29828 | N6: =(H6/I6)-1 -> 0.11876111 | O6: =(H6/J6)-1 -> 0.077821025 | P6: =(H6/K6)-1 -> 0.071862908 | Q6: =('Holdings Pull Sheet'!F17/'Holdings Pull Sheet'!G17)-1 -> 0.0072727273 | S6: Misc | U6: =H6/$H$27 -> #VALUE! | W6: 0 | X6: - | Z6: 0 | AA6: 0 | AC6: =Q6*U6 -> #VALUE!
B7: CPL | C7: ='Holdings Pull Sheet'!C18 -> Caterpillar Inc | E7: ='Holdings Pull Sheet'!F18 -> 85.14 | F7: 83 | G7: 15 | H7: =E7*G7 -> 1277.1 | I7: =F7*ROUNDDOWN(G7,0)+9.95 -> 1254.95 | J7: 1245 | K7: 1293.75 | M7: =H7-I7 -> 22.15 | N7: =(H7/I7)-1 -> 0.017650106 | O7: =(H7/J7)-1 -> 0.025783133 | P7: =(H7/K7)-1 -> -0.012869565 | Q7: =('Holdings Pull Sheet'!F18/'Holdings Pull Sheet'!G18)-1 -> 0.023194328 | S7: Industrials | U7: =H7/$H$27 -> #VALUE! | W7: ='Holdings Pull Sheet'!O18/1000000000 -> 55.978264 | X7: =IF(W7<2,"Small", IF(W7<10, "Mid", IF(W7>10, "Large"))) -> Large | Z7: ='Holdings Pull Sheet'!Q18 -> 11.2 | AA7: ='Holdings Pull Sheet'!P18 -> 7.43 | AC7: =Q7*U7 -> #VALUE!
B8: GNTX | C8: ='Holdings Pull Sheet'!C19 -> Cemex ADR Representing 10 Par Shs | E8: ='Holdings Pull Sheet'!F19 -> 10.55 | F8: 18.48 | G8: 67.038 | H8: =E8*G8 -> 707.2509 | I8: =F8*ROUNDDOWN(G8,0)+9.95 -> 1248.11 | J8: 1311.6534 | K8: 1274.3924 | M8: =H8-I8 -> -540.8591 | N8: =(H8/I8)-1 -> -0.43334249 | O8: =(H8/J8)-1 -> -0.46079435 | P8: =(H8/K8)-1 -> -0.44502893 | Q8: =('Holdings Pull Sheet'!F19/'Holdings Pull Sheet'!G19)-1 -> 0.029268293 | S8: Information Technology | U8: =H8/$H$27 -> #VALUE! | W8: ='Holdings Pull Sheet'!O19/1000000000 -> 11.867495 | X8: =IF(W8<2,"Small", IF(W8<10, "Mid", IF(W8>10, "Large"))) -> Large | Z8: ='Holdings Pull Sheet'!Q19 -> 0 | AA8: ='Holdings Pull Sheet'!P19 -> -1.03 | AC8: =Q8*U8 -> #VALUE!
B9: HCP | C9: ='Holdings Pull Sheet'!C20 -> Cisco Systems Inc | E9: ='Holdings Pull Sheet'!F20 -> 24.35 | F9: 12.47 | G9: 65.665 | H9: =E9*G9 -> 1598.9428 | I9: =F9*ROUNDDOWN(G9,0)+9.95 -> 820.5 | J9: 647.68746 | K9: 757.11745 | M9: =H9-I9 -> 778.44275 | N9: =(H9/I9)-1 -> 0.94874193 | O9: =(H9/J9)-1 -> 1.4686949 | P9: =(H9/K9)-1 -> 1.111882 | Q9: =('Holdings Pull Sheet'!F21/'Holdings Pull Sheet'!G21)-1 -> 0.03541782 | S9: Consumer Discretionary | U9: =H9/$H$27 -> #VALUE! | W9: ='Holdings Pull Sheet'!O21/1000000000 -> 16.02596 | X9: =IF(W9<2,"Small", IF(W9<10, "Mid", IF(W9>10, "Large"))) -> Large | Z9: ='Holdings Pull Sheet'!Q21 -> 17.6 | AA9: ='Holdings Pull Sheet'!P21 -> 1.05 | AC9: =Q9*U9 -> #VALUE!
B10: HD | C10: ='Holdings Pull Sheet'!C21 -> Delta Air Lines Inc | E10: ='Holdings Pull Sheet'!F21 -> 18.71 | F10: 16.4 | G10: 91.934 | H10: =E10*G10 -> 1720.0851 | I10: =F10*ROUNDDOWN(G10,0)+9.95 -> 1502.35 | J10: 1669.6919 | K10: 1608.845 | M10: =H10-I10 -> 217.73514 | N10: =(H10/I10)-1 -> 0.1449297 | O10: =(H10/J10)-1 -> 0.030181142 | P10: =(H10/K10)-1 -> 0.069142857 | Q10: =('Holdings Pull Sheet'!F22/'Holdings Pull Sheet'!G22)-1 -> 0.028735632 | S10: Consumer Discretionary | U10: =H10/$H$27 -> #VALUE! | W10: ='Holdings Pull Sheet'!O22/1000000000 -> 3.3411997 | X10: =IF(W10<2,"Small", IF(W10<10, "Mid", IF(W10>10, "Large"))) -> Mid | Z10: ='Holdings Pull Sheet'!Q22 -> 19.5 | AA10: ='Holdings Pull Sheet'!P22 -> 1.17 | AC10: =Q10*U10 -> #VALUE!
B11: ITRI | C11: ='Holdings Pull Sheet'!C22 -> Gentex Corp | E11: ='Holdings Pull Sheet'!F22 -> 23.27 | F11: 29.37 | G11: 60.269 | H11: =E11*G11 -> 1402.4596 | I11: =F11*ROUNDDOWN(G11,0)+9.95 -> 1772.15 | J11: 2834.451 | K11: 2710.2969 | M11: =H11-I11 -> -369.69037 | N11: =(H11/I11)-1 -> -0.20861122 | O11: =(H11/J11)-1 -> -0.50520943 | P11: =(H11/K11)-1 -> -0.48254392 | Q11: =('Holdings Pull Sheet'!F23/'Holdings Pull Sheet'!G23)-1 -> 0.0017015707 | S11: Financial | U11: =H11/$H$27 -> #VALUE! | W11: ='Holdings Pull Sheet'!O23/1000000000 -> 111.79472 | X11: =IF(W11<2,"Small", IF(W11<10, "Mid", IF(W11>10, "Large"))) -> Large | Z11: ='Holdings Pull Sheet'!Q23 -> 24.6 | AA11: ='Holdings Pull Sheet'!P23 -> 3.16 | AC11: =Q11*U11 -> #VALUE!
B12: MDT | C12: ='Holdings Pull Sheet'!C23 -> Home Depot Inc | E12: ='Holdings Pull Sheet'!F23 -> 76.53 | F12: 28.6 | G12: 58.765 | H12: =E12*G12 -> 4497.2855 | I12: =F12*ROUNDDOWN(G12,0)+9.95 -> 1668.75 | J12: 3371.3144 | K12: 3775.0636 | M12: =H12-I12 -> 2828.5355 | N12: =(H12/I12)-1 -> 1.6950025 | O12: =(H12/J12)-1 -> 0.33398576 | P12: =(H12/K12)-1 -> 0.19131382 | Q12: =('Holdings Pull Sheet'!F24/'Holdings Pull Sheet'!G24)-1 -> 0.044849334 | S12: Consumer Discretionary | U12: =H12/$H$27 -> #VALUE! | W12: ='Holdings Pull Sheet'!O24/1000000000 -> 0.41595396 | X12: =IF(W12<2,"Small", IF(W12<10, "Mid", IF(W12>10, "Large"))) -> Small | Z12: ='Holdings Pull Sheet'!Q24 -> 0 | AA12: ='Holdings Pull Sheet'!P24 -> -0.11 | AC12: =Q12*U12 -> #VALUE!
B13: PFE | C13: ='Holdings Pull Sheet'!C24 -> Immersion Corp | E13: ='Holdings Pull Sheet'!F24 -> 14.91 | F13: 62.69 | G13: 25 | H13: =E13*G13 -> 372.75 | I13: =F13*ROUNDDOWN(G13,0)+9.95 -> 1577.2 | J13: 1078.5 | K13: 1082.75 | M13: =H13-I13 -> -1204.45 | N13: =(H13/I13)-1 -> -0.76366345 | O13: =(H13/J13)-1 -> -0.65438108 | P13: =(H13/K13)-1 -> -0.6557377 | Q13: =('Holdings Pull Sheet'!F25/'Holdings Pull Sheet'!G25)-1 -> 0.021668029 | S13: Information Technology | U13: =H13/$H$27 -> #VALUE! | W13: ='Holdings Pull Sheet'!O25/1000000000 -> 124.22529 | X13: =IF(W13<2,"Small", IF(W13<10, "Mid", IF(W13>10, "Large"))) -> Large | Z13: ='Holdings Pull Sheet'!Q25 -> 12.3 | AA13: ='Holdings Pull Sheet'!P25 -> 2 | AC13: =Q13*U13 -> #VALUE!
B14: PGX | C14: ='Holdings Pull Sheet'!C25 -> Intel Corp | E14: ='Holdings Pull Sheet'!F25 -> 24.99 | F14: 47.17 | G14: 28.038 | H14: =E14*G14 -> 700.66962 | I14: =F14*ROUNDDOWN(G14,0)+9.95 -> 1330.71 | J14: 1158.5436 | K14: 1994.9585 | M14: =H14-I14 -> -630.04038 | N14: =(H14/I14)-1 -> -0.47346182 | O14: =(H14/J14)-1 -> -0.39521514 | P14: =(H14/K14)-1 -> -0.64877984 | Q14: =('Holdings Pull Sheet'!F26/'Holdings Pull Sheet'!G26)-1 -> 0.022670025 | S14: Healthcare | U14: =H14/$H$27 -> #VALUE! | W14: ='Holdings Pull Sheet'!O26/1000000000 -> 53.508679 | X14: =IF(W14<2,"Small", IF(W14<10, "Mid", IF(W14>10, "Large"))) -> Large | Z14: ='Holdings Pull Sheet'!Q26 -> 15.4 | AA14: ='Holdings Pull Sheet'!P26 -> 3.38 | AC14: =Q14*U14 -> #VALUE!
B15: PTR | C15: ='Holdings Pull Sheet'!C26 -> Medtronic Inc | E15: ='Holdings Pull Sheet'!F26 -> 52.78 | F15: 19.49 | G15: 75 | H15: =E15*G15 -> 3958.5 | I15: =F15*ROUNDDOWN(G15,0)+9.95 -> 1471.7 | J15: 1471.7 | K15: 1471.7 | M15: =H15-I15 -> 2486.8 | N15: =(H15/I15)-1 -> 1.6897466 | O15: =(H15/J15)-1 -> 1.6897466 | P15: =(H15/K15)-1 -> 1.6897466 | Q15: =('Holdings Pull Sheet'!F27/'Holdings Pull Sheet'!G27)-1 -> 0.013914317 | S15: Energy | U15: =H15/$H$27 -> #VALUE! | W15: ='Holdings Pull Sheet'!O27/1000000000 -> 0.62030918 | X15: =IF(W15<2,"Small", IF(W15<10, "Mid", IF(W15>10, "Large"))) -> Small | Z15: ='Holdings Pull Sheet'!Q27 -> 5.2 | AA15: ='Holdings Pull Sheet'!P27 -> 5.31 | AC15: =Q15*U15 -> #VALUE!
B16: QCOM | C16: ='Holdings Pull Sheet'!C27 -> Natural Grocers by Vitamin Cottage Inc | E16: ='Holdings Pull Sheet'!F27 -> 27.69 | F16: 33.19 | G16: 15.202 | H16: =E16*G16 -> 420.94338 | I16: =F16*ROUNDDOWN(G16,0)+9.95 -> 507.8 | J16: 1781.4913 | K16: 1971.8688 | M16: =H16-I16 -> -86.85662 | N16: =(H16/I16)-1 -> -0.17104494 | O16: =(H16/J16)-1 -> -0.76371292 | P16: =(H16/K16)-1 -> -0.78652567 | Q16: =('Holdings Pull Sheet'!F28/'Holdings Pull Sheet'!G28)-1 -> 0.034421365 | S16: Misc | U16: =H16/$H$27 -> #VALUE! | W16: ='Holdings Pull Sheet'!O28/1000000000 -> 0.82924429 | X16: - | Z16: ='Holdings Pull Sheet'!Q28 -> 0 | AA16: ='Holdings Pull Sheet'!P28 -> -5.3 | AC16: =Q16*U16 -> #VALUE!
B17: SINA | C17: ='Holdings Pull Sheet'!C28 -> Tutor Perini Corp | E17: ='Holdings Pull Sheet'!F28 -> 17.43 | F17: 14.42 | G17: 133.505 | H17: =E17*G17 -> 2326.9922 | I17: =F17*ROUNDDOWN(G17,0)+9.95 -> 1927.81 | J17: 1947.8667 | K17: 2830.9214 | M17: =H17-I17 -> 399.18215 | N17: =(H17/I17)-1 -> 0.20706509 | O17: =(H17/J17)-1 -> 0.19463626 | P17: =(H17/K17)-1 -> -0.17800893 | Q17: =('Holdings Pull Sheet'!F29/'Holdings Pull Sheet'!G29)-1 -> 0.01140834 | S17: Information Technology | U17: =H17/$H$27 -> #VALUE! | W17: ='Holdings Pull Sheet'!O29/1000000000 -> 9.1229926 | X17: =IF(W17<2,"Small", IF(W17<10, "Mid", IF(W17>10, "Large"))) -> Mid | Z17: ='Holdings Pull Sheet'!Q29 -> 17.5 | AA17: ='Holdings Pull Sheet'!P29 -> 1.45 | AC17: =Q17*U17 -> #VALUE!
B18: TTEK | C18: ='Holdings Pull Sheet'!C29 -> Tyson Foods Inc | E18: ='Holdings Pull Sheet'!F29 -> 25.71 | F18: 35.72 | G18: 44.687 | H18: =E18*G18 -> 1148.9028 | I18: =F18*ROUNDDOWN(G18,0)+9.95 -> 1581.63 | J18: 2787.3414 | K18: 2256.3172 | M18: =H18-I18 -> -432.72723 | N18: =(H18/I18)-1 -> -0.27359574 | O18: =(H18/J18)-1 -> -0.58781412 | P18: =(H18/K18)-1 -> -0.49080619 | Q18: =('Holdings Pull Sheet'!F30/'Holdings Pull Sheet'!G30)-1 -> 0.016637696 | S18: Industrials | U18: =H18/$H$27 -> #VALUE! | W18: ='Holdings Pull Sheet'!O30/1000000000 -> 216.83408 | X18: =IF(W18<2,"Small", IF(W18<10, "Mid", IF(W18>10, "Large"))) -> Large | Z18: ='Holdings Pull Sheet'!Q30 -> 11.5 | AA18: ='Holdings Pull Sheet'!P30 -> 3.53 | AC18: =Q18*U18 -> #VALUE!
B19: SYK | C19: ='Holdings Pull Sheet'!C30 -> Wells Fargo & Co | E19: ='Holdings Pull Sheet'!F30 -> 40.94 | F19: 25.46 | G19: 60 | H19: =E19*G19 -> 2456.4 | I19: =F19*ROUNDDOWN(G19,0)+9.95 -> 1537.55 | J19: 1630.2 | K19: 1536.6 | M19: =H19-I19 -> 918.85 | N19: =(H19/I19)-1 -> 0.59760658 | O19: =(H19/J19)-1 -> 0.50680898 | P19: =(H19/K19)-1 -> 0.5985943 | Q19: =('Holdings Pull Sheet'!F31/'Holdings Pull Sheet'!G31)-1 -> 0.018539977 | S19: Industrials | U19: =H19/$H$27 -> #VALUE! | W19: ='Holdings Pull Sheet'!O31/1000000000 -> 28.549086 | X19: =IF(W19<2,"Small", IF(W19<10, "Mid", IF(W19>10, "Large"))) -> Large | Z19: ='Holdings Pull Sheet'!Q31 -> 7.7 | AA19: ='Holdings Pull Sheet'!P31 -> 3.41 | AC19: =Q19*U19 -> #VALUE!
B20: UPS | C20: ='Holdings Pull Sheet'!C31 -> Yahoo! Inc | E20: ='Holdings Pull Sheet'!F31 -> 26.37 | F20: 12.43 | G20: 150 | H20: =E20*G20 -> 3955.5 | I20: =F20*ROUNDDOWN(G20,0)+9.95 -> 1874.45 | J20: 1874.45 | K20: 1933.5 | M20: =H20-I20 -> 2081.05 | N20: =(H20/I20)-1 -> 1.110219 | O20: =(H20/J20)-1 -> 1.110219 | P20: =(H20/K20)-1 -> 1.0457719 | Q20: =('Holdings Pull Sheet'!F32/'Holdings Pull Sheet'!G32)-1 -> 0.032434902 | S20: Healthcare | U20: =H20/$H$27 -> #VALUE! | W20: ='Holdings Pull Sheet'!O32/1000000000 -> 0.21236904 | X20: =IF(W20<2,"Small", IF(W20<10, "Mid", IF(W20>10, "Large"))) -> Small | Z20: ='Holdings Pull Sheet'!Q32 -> 0 | AA20: ='Holdings Pull Sheet'!P32 -> -14.95 | AC20: =Q20*U20 -> #VALUE!
B21: WFC | C21: ='Holdings Pull Sheet'!C32 -> YRC Worldwide Inc | E21: ='Holdings Pull Sheet'!F32 -> 22.6 | F21: 16.65 | G21: 100 | H21: =E21*G21 -> 2260 | I21: =F21*ROUNDDOWN(G21,0)+9.95 -> 1674.95 | J21: 1665 | K21: 1919 | M21: =H21-I21 -> 585.05 | N21: =(H21/I21)-1 -> 0.34929401 | O21: =(H21/J21)-1 -> 0.35735736 | P21: =(H21/K21)-1 -> 0.17769672 | Q21: =('Holdings Pull Sheet'!F33/'Holdings Pull Sheet'!G33)-1 -> #VALUE! | S21: Consumer Staples | U21: =H21/$H$27 -> #VALUE! | W21: ='Holdings Pull Sheet'!O33/1000000000 -> #VALUE! | X21: =IF(W21<2,"Small", IF(W21<10, "Mid", IF(W21>10, "Large"))) -> #VALUE! | Z21: ='Holdings Pull Sheet'!Q33 -> ??? | AA21: ='Holdings Pull Sheet'!P33 -> ??? | AC21: =Q21*U21 -> #VALUE!
B22: WMMVY | C22: ='Holdings Pull Sheet'!C33 -> .C\12A21\5.0 (Invalid symbol) | E22: ='Holdings Pull Sheet'!F33 -> ??? | F22: 71.52 | G22: 46.992 | H22: =E22*G22 -> #VALUE! | I22: =F22*ROUNDDOWN(G22,0)+9.95 -> 3299.87 | J22: 3354.1307 | K22: 3456.7315 | M22: =H22-I22 -> #VALUE! | N22: =(H22/I22)-1 -> #VALUE! | O22: =(H22/J22)-1 -> #VALUE! | P22: =(H22/K22)-1 -> #VALUE! | Q22: =('Holdings Pull Sheet'!F34/'Holdings Pull Sheet'!G34)-1 -> 0.05543399 | S22: Industrials | U22: =H22/$H$27 -> #VALUE! | W22: ='Holdings Pull Sheet'!O34/1000000000 -> 77.63595 | X22: =IF(W22<2,"Small", IF(W22<10, "Mid", IF(W22>10, "Large"))) -> Large | Z22: ='Holdings Pull Sheet'!Q34 -> 11.2 | AA22: ='Holdings Pull Sheet'!P34 -> 0.92 | AC22: =Q22*U22 -> #VALUE!
C23: ='Holdings Pull Sheet'!C34 -> Vale ADR Representing One Ord Shs | E23: ='Holdings Pull Sheet'!F34 -> 14.47 | F23: 25 | G23: 52.119 | H23: =E23*G23 -> 754.16193 | I23: =F23*ROUNDDOWN(G23,0)+9.95 -> 1309.95 | J23: 1435.9306 | K23: 1653.2147 | M23: =H23-I23 -> -555.78807 | N23: =(H23/I23)-1 -> -0.4242819 | O23: =(H23/J23)-1 -> -0.47479221 | P23: =(H23/K23)-1 -> -0.54382093 | Q23: =('Holdings Pull Sheet'!F36/'Holdings Pull Sheet'!G36)-1 -> 0.020340515 | S23: Consumer Discretionary | U23: =H23/$H$27 -> #VALUE! | W23: ='Holdings Pull Sheet'!O36/1000000000 -> 25.602007 | X23: =IF(W23<2,"Small", IF(W23<10, "Mid", IF(W23>10, "Large"))) -> Large | Z23: ='Holdings Pull Sheet'!Q36 -> 20.4 | AA23: ='Holdings Pull Sheet'!P36 -> 3.27 | AC23: =Q23*U23 -> #VALUE!
B24: CSCO | C24: ='Holdings Pull Sheet'!C35 -> CPFL Energia SA | E24: ='Holdings Pull Sheet'!F35 -> 20.31 | F24: 23.42 | G24: 51.373 | H24: =E24*G24 -> 1043.3856 | I24: =F24*ROUNDDOWN(G24,0)+9.95 -> 1204.37 | J24: 1778.2684 | K24: 1703.5287 | M24: =H24-I24 -> -160.98437 | N24: =(H24/I24)-1 -> -0.13366687 | O24: =(H24/J24)-1 -> -0.41325753 | P24: =(H24/K24)-1 -> -0.38751508 | Q24: =('Holdings Pull Sheet'!F37/'Holdings Pull Sheet'!G37)-1 -> 0.01275691 | S24: Financial | U24: =H24/$H$27 -> #VALUE! | W24: ='Holdings Pull Sheet'!O37/1000000000 -> 0 | X24: =IF(W24<2,"Small", IF(W24<10, "Mid", IF(W24>10, "Large"))) -> Small | Z24: ='Holdings Pull Sheet'!Q37 -> 0 | AA24: ='Holdings Pull Sheet'!P37 -> 0 | AC24: =Q24*U24 -> #VALUE!
C25: ='Holdings Pull Sheet'!C36 -> Stryker Corp | E25: ='Holdings Pull Sheet'!F36 -> 67.72 | F25: 10.84 | G25: 103.821 | H25: =E25*G25 -> 7030.7581 | I25: =F25*ROUNDDOWN(G25,0)+9.95 -> 1126.47 | J25: 792.27646 | K25: 704.94459 | M25: =H25-I25 -> 5904.2881 | N25: =(H25/I25)-1 -> 5.2414073 | O25: =(H25/J25)-1 -> 7.8741222 | P25: =(H25/K25)-1 -> 8.9734904 | Q25: =('Holdings Pull Sheet'!F38/'Holdings Pull Sheet'!G38)-1 -> -0.0022665458 | S25: Information Technology | U25: =H25/$H$27 -> #VALUE! | W25: ='Holdings Pull Sheet'!O38/1000000000 -> 201.41451 | X25: =IF(W25<2,"Small", IF(W25<10, "Mid", IF(W25>10, "Large"))) -> Large | Z25: ='Holdings Pull Sheet'!Q38 -> 11.1 | AA25: ='Holdings Pull Sheet'!P38 -> 10.05 | AC25: =Q25*U25 -> #VALUE!
C27: Total | H27: =SUM(H4:H25) -> #VALUE! | I27: =SUM(I4:I25) -> 34299.51 | J27: 40381.87 | K27: =SUM(K4:K25) -> 41863.402 | M27: =H27-I27 -> #VALUE! | N27: =(H27/I27)-1 -> #VALUE! | O27: =(H27/J27)-1 -> #VALUE! | P27: =(H27/K27)-1 -> #VALUE! | Q27: =AC27 -> #VALUE! | U27: =SUM(U4:U25) -> #VALUE! | Z27: =(Z5*$U$5)+(Z7*$U$7)+(Z8*$U$8)+(Z9*$U$9)+(Z10*$U$10)+(Z11*$U$11)+(Z12*$U$12)+(Z13*$U$13)+(Z14*$U$14)+(Z15*$U$15)+(Z16*$U$16)+(Z17*$U$17)+(Z18*$U$18)+(Z19*$U$19)+(Z20*$U$20)+(Z21*$U$21)+(Z22*$U$22)+(Z23*$U$23)+(Z24*$U$24) -> #VALUE! | AA27: =(AA5*$U$5)+(AA7*$U$7)+(AA24*$U$24)+(AA8*$U$8)+(AA9*$U$9)+(AA10*$U$10)+(AA11*$U$11)+(AA12*$U$12)+(AA13*$U$13)+(AA14*$U$14)+(AA15*$U$15)+(AA16*$U$16)+(AA17*$AA$17)+(AA19*$AA$19)+(AA18*$U$18)+(AA20*$U$20)+(AA21*$U$21)+(AA22*$U$22)+(AA23*$U$23)+(AA25*$U$25) -> #VALUE! | AC27: =SUM(AC4:AC25) -> #VALUE!
E29: Commission Fees | X29: EPS Excluding BRK.B | AA29: =(AA7*$U$7)+(AA24*$U$24)+(AA8*$U$8)+(AA9*$U$9)+(AA10*$U$10)+(AA11*$U$11)+(AA12*$U$12)+(AA13*$U$13)+(AA14*$U$14)+(AA15*$U$15)+(AA16*$U$16)+(AA17*$U$17)+(AA19*$U$19)+(AA18*$U$18)+(AA20*$U$20)+(AA21*$U$21)+(AA22*$U$22)+(AA23*$U$23)+(AA25*$U$25) -> #VALUE!
X60: Portfolio Performance & Details ©
X61: Created by Kristopher "Boomer" Hoppough
X62: 616.902.0398
X63: gnar99@hotmail.com
X64: hoppougk@student.gvsu.edu

Sheet Sector Weights
A9: GICS Sector | B9: Percent of S&P 500 (by market capitalization %) | C9: Lower Range | D9: Upper Range | E9: Average Range
A10: Energy | B10: 10.7 | C10: 5.35 | D10: 16.05 | E10: 0.037
A11: Materials | B11: 3.4 | C11: 1.7 | D11: 5.1 | E11: 0.034
A12: Industrials | B12: 10.3 | C12: 5.15 | D12: 15.45 | E12: 0.103
A13: Consumer Discretionary | B13: 10.1 | C13: 5.05 | D13: 15.15 | E13: 0.101
A14: Consumer Staples | B14: 11.5 | C14: 5.75 | D14: 17.25 | E14: 0.115
A15: Health Care | B15: 12.1 | C15: 6.05 | D15: 18.15 | E15: 0.121
A16: Financial | B16: 16.3 | C16: 8.15 | D16: 24.45 | E16: 0.163
A17: Information Technology | B17: 18.8 | C17: 9.4 | D17: 28.2 | E17: 0.188
A18: Telecommunication Services | B18: 3 | C18: 1.5 | D18: 4.5 | E18: 0.03
A19: Utilities | B19: 3.7 | C19: 1.85 | D19: 5.55 | E19: 0.037

Sheet Turner's Pitches
A2: Turner's Pitches
D3: Date Bought | E3: Date Sold | F3: Days Owned | G3: Paid | H3: Price | I3: Shares | J3: Cost | K3: Value | L3: Gain | M3: Annualized
C4: F | D4: 40942 | E4: 41365 | F4: =E4-D4 -> 423 | G4: 12.47 | H4: 13.01 | I4: 65 | J4: 810.55 | K4: =H4*(I4+1.476) -> 864.85276 | L4: =(K4/J4) -1 -> 0.066994954 | M4: =(365/F4)*L4 -> 0.057808885
C5: NGVC | D5: 41243 | E5: =TODAY() -> 41438 | F5: =E5-D5 -> 195 | G5: 19.49 | H5: =Holdings!E16 -> 27.69 | I5: 75 | J5: 1471.7 | K5: =H5*I5 -> 2076.75 | L5: =(K5/J5) -1 -> 0.41112319 | M5: =(365/F5)*L5 -> 0.76953828
C6: YHOO | D6: 41334 | E6: =TODAY() -> 41438 | F6: =E6-D6 -> 104 | G6: 21.75 | H6: =Holdings!#REF! -> #REF! | I6: 100 | J6: 2174.99 | K6: =H6*I6 -> #REF! | L6: =(K6/J6) -1 -> #REF! | M6: =(365/F6)*L6 -> #REF!
C7: YRCW | D7: 41355 | E7: 41397 | F7: =E7-D7 -> 42 | G7: 8.61 | H7: 11.25 | I7: 100 | J7: =G7*I7 -> 861 | K7: =H7*I7 -> 1125 | L7: =(K7/J7) -1 -> 0.30662021 | M7: =(365/F7)*L7 -> 2.6646756
C8: YRCW | D8: 41355 | E8: =TODAY() -> 41438 | F8: =E8-D8 -> 83 | G8: 8.61 | H8: =Holdings!#REF! -> #REF! | I8: 200 | J8: 1722 | K8: =H8*I8 -> #REF! | L8: =(K8/J8) -1 -> #REF! | M8: =(365/F8)*L8 -> #REF!
