Workbook

Sheet Inputs
A1: Timestamp
C3: Inputs
C4: Silver Price 2009 | E4: 12
C5: Silver price 2010 | E5: 20
C6: Silver Price 2011 | E6: 28
C7: Silver Pirce 2012 | E7: 40
C8: Silver Price 2013 | E8: 38
C9: Silver Price 2014-2015 | E9: 35
C10: Silver Price (Terminal) | E10: 22
C11: Require Rate of Return | E11: 0.06
C12: Total Resources | E12: 1160000
C13: Current Reserves | E13: 609000
C14: Net Measured/Inferred Reserves | E14: =E12-E13 -> 551000
C15: Reserve Multiple | E15: 0.5
C16: Resource Multiple | E16: 0.1
C17: Fully Diluted Shares | E17: 329000
C18: Net Debt | E18: -239000
C19: Tax Rate | E19: 0.1

Sheet Prod & Costs
C4: Silver Wheaton | H4: Royalty Costs/oz
C5: 2009 Production | F5: 17400 | H5: 2009 Purchasing Price | K5: 3.95
C6: 2010 Prodcution | F6: 27400 | H6: 2010 Purchasing Price | K6: 3.98
C7: 2011 Production | F7: 32400 | H7: 2011 Purchasing Price | K7: 4.01
C8: 2012 Production | F8: 34186 | H8: 2012 Purchasing Price | K8: 4.07
C9: 2013 Production | F9: 36200 | H9: 2013 Purchasing Price | K9: 4.14
C10: 2014 Production | F10: 38430 | H10: 2014 Purchasing Price | K10: 4.2
C11: 2015 Production | F11: 39890 | H11: 2015 Purchasing Price | K11: 4.3
C12: Terminal Production | F12: 41000 | H12: Terminal Purchasing Price | K12: 4.9
C14: Net Reserves | F14: ='Inputs'!E13-SUM('Prod & Costs'!F5:F12) -> 342094

Sheet DCF
B4: Year | D4: 2009 | F4: 2010 | H4: 2011 | J4: 2012 | L4: 2013 | N4: 2014 | P4: 2015
B5: Royalty Revenue | D5: =('Inputs'!E4*'Prod & Costs'!F5) -> 208800 | F5: =('Inputs'!E5*'Prod & Costs'!F6) -> 548000 | H5: =('Inputs'!E6*'Prod & Costs'!F7) -> 907200 | J5: =('Inputs'!E7*'Prod & Costs'!F8) -> 1367440 | L5: =('Inputs'!E8*'Prod & Costs'!F9) -> 1375600 | N5: =('Inputs'!E9*'Prod & Costs'!F10) -> 1345050 | P5: =('Inputs'!E9*'Prod & Costs'!F11) -> 1396150
B6: Purchasing Costs | D6: =('Prod & Costs'!$F$5*'Prod & Costs'!$K$5) -> 68730 | F6: =('Prod & Costs'!$F$6*'Prod & Costs'!$K$6) -> 109052 | H6: =('Prod & Costs'!$F$7*'Prod & Costs'!$K$7) -> 129924 | J6: =('Prod & Costs'!$F$8*'Prod & Costs'!$K$8) -> 139137.02 | L6: =('Prod & Costs'!$F$9*'Prod & Costs'!$K$9) -> 149868 | N6: =('Prod & Costs'!$F$10*'Prod & Costs'!$K$10) -> 161406 | P6: =('Prod & Costs'!$F$11*'Prod & Costs'!$K$11) -> 171527
B7: Operating Income | D7: =D5-D6 -> 140070 | F7: =F5-F6 -> 438948 | H7: =H5-H6 -> 777276 | J7: =J5-J6 -> 1228303 | L7: =L5-L6 -> 1225732 | N7: =N5-N6 -> 1183644 | P7: =P5-P6 -> 1224623
B8: Interest Expense | D8: =0.07*'Inputs'!E18 -> -16730 | F8: =IF((D16<0.0),(0.07*D16),0.0) -> -9193.8 | H8: =IF((F16<0.0),(0.07*F16),0.0) -> 0 | J8: =IF((H16<0.0),(0.07*H16),0.0) -> 0 | L8: =IF((J16<0.0),(0.07*J16),0.0) -> 0 | N8: =IF((L16<0.0),(0.07*L16),0.0) -> 0 | P8: =IF((N16<0.0),(0.07*N16),0.0) -> 0
B9: Taxes | D9: =(D7-D8)*'Inputs'!$E$19 -> 15680 | F9: =IF((D8<0.0),('Inputs'!$E$19*(F7+F8)),('Inputs'!$E$19*F7)) -> 42975.42 | H9: =IF((F8<0.0),('Inputs'!$E$19*(H7+H8)),('Inputs'!$E$19*H7)) -> 77727.6 | J9: =IF((H8<0.0),('Inputs'!$E$19*(J7+J8)),('Inputs'!$E$19*J7)) -> 122830.3 | L9: =IF((J8<0.0),('Inputs'!$E$19*(L7+L8)),('Inputs'!$E$19*L7)) -> 122573.2 | N9: =IF((L8<0.0),('Inputs'!$E$19*(N7+N8)),('Inputs'!$E$19*N7)) -> 118364.4 | P9: =IF((N8<0.0),('Inputs'!$E$19*(P7+P8)),('Inputs'!$E$19*P7)) -> 122462.3
B10: NOPAT | D10: =(D7+D8)-D9 -> 107660 | F10: =(F7+F8)-F9 -> 386778.78 | H10: =(H7+H8)-H9 -> 699548.4 | J10: =(J7+J8)-J9 -> 1105472.7 | L10: =(L7+L8)-L9 -> 1103158.8 | N10: =(N7+N8)-N9 -> 1065279.6 | P10: =(P7+P8)-P9 -> 1102160.7
B11: Debt Repayment | D11: =D10 -> 107660 | F11: =IF((F10<D16),F10,(F10-(F10+D16))) -> 131340 | H11: =IF((H10<F16),H10,(H10-(H10+F16))) -> 0 | J11: =IF((J10<H16),J10,(J10-(J10+H16))) -> 0 | L11: =IF((L10<J16),L10,(L10-(L10+J16))) -> 0 | N11: =IF((N10<L16),N10,(N10-(N10+L16))) -> 0 | P11: =IF((P10<N16),P10,(P10-(P10+N16))) -> 0
B12: Capital Reinvestment | D12: 0 | F12: 0 | H12: 0 | J12: 0 | L12: 0 | N12: 0 | P12: 0
B13: FCF | D13: 0 | F13: =F10-F11 -> 255438.78 | H13: =H10-H11 -> 699548.4 | J13: =J10-J11 -> 1105472.7 | L13: =L10-L11 -> 1103158.8 | N13: =N10-N11 -> 1065279.6 | P13: =P10-P11 -> 1102160.7
B14: Ke | D14: =(1.0+'Inputs'!$E$11) -> 1.06 | F14: =(1.0+'Inputs'!$E$11)^2.0 -> 1.1236 | H14: =(1.0+'Inputs'!$E$11)^3.0 -> 1.191016 | J14: =(1.0+'Inputs'!$E$11)^4.0 -> 1.262477 | L14: =(1.0+'Inputs'!$E$11)^5.0 -> 1.3382256 | N14: =(1.0+'Inputs'!$E$11)^6.0 -> 1.4185191 | P14: =(1.0+'Inputs'!$E$11)^8.0 -> 1.5938481
B15: Net Present Value | D15: =SUM(D13)/SUM(D14) -> 0 | F15: =SUM(F13)/SUM(F14) -> 227339.6 | H15: =SUM(H13)/SUM(H14) -> 587354.33 | J15: =SUM(J13)/SUM(J14) -> 875637.91 | L15: =SUM(L13)/SUM(L14) -> 824344.43 | N15: =SUM(N13)/SUM(N14) -> 750980.08 | P15: =SUM(P13)/SUM(P14) -> 691509.26
B16: Debt Remaining | D16: ='Inputs'!E18+'DCF'!D11 -> -131340 | F16: =D16+F11 -> 0 | H16: =F16+H11 -> 0 | J16: =H16+J11 -> 0 | L16: =J16+L11 -> 0 | N16: =L16+N11 -> 0 | P16: =N16+P11 -> 0

Sheet Valuation range
B5: Valuation 1(BASIC DCF: Best for Retailers) | G5: Valuation 2 (Mining Companies)
B6: VPS (2009-2015) | D6: =SUM('DCF'!D15:Q15)/'Inputs'!E17 -> 12.027859 | G6: VPS | I6: =D6+D7 -> 32.083124
B7: VPS Terminal Stage | D7: =((((('Inputs'!E10*'Prod & Costs'!F12)-('Prod & Costs'!F12*'Prod & Costs'!K12))*(1.0-'Inputs'!E19))/'DCF'!P14)/0.06)/'Inputs'!E17 -> 20.055265 | G7: Reserve Value | I7: =(('Prod & Costs'!F14*'Inputs'!E15)*'Inputs'!E10)/'Inputs'!E17 -> 11.437793
B8: Intrinsic Value | D8: =D7+D6 -> 32.083124 | G8: Resource Value | I8: =(('Inputs'!E10*'Inputs'!E14)*'Inputs'!E16)/'Inputs'!E17 -> 3.6844985
G9: Intrinsic Value | I9: =SUM(I6:J8) -> 47.205416
