Workbook
Name liabilitytotals: 'Projected Debts and Liabilities'!$C$16:$G$16
Name Monthly_Totals: 'Projected Debts and Liabilities'!$C$16:$G$16

Sheet Projected Income
B3: INCOME | C3: September | D3: October | E3: November | F3: December | G3: Semester Total
B4: Vending Machine | C4: 400 | D4: 400 | E4: 400 | F4: 400 | G4: =SUM(C4:F4) -> 1600
B5: Recycling | C5: 70 | D5: 70 | E5: 70 | F5: 70 | G5: =SUM(C5:F5) -> 280
B6: Pop Machine | C6: 50 | D6: 50 | E6: 50 | F6: 50 | G6: =SUM(C6:F6) -> 200
B7: Brother Fees | C7: 1000 | D7: 400 | G7: =SUM(C7:F7) -> 1400
B8: Parking | C8: 220 | D8: 315 | E8: 315 | F8: 315 | G8: =SUM(C8:F8) -> 1165
B9: T-Shirt Sales | C9: 80 | D9: 80 | E9: 80 | F9: 80 | G9: =SUM(C9:F9) -> 320
B10: Coin Laundry | C10: 120 | D10: 120 | E10: 120 | F10: 120 | G10: =SUM(C10:F10) -> 480
B11: House Company | D11: 450 | G11: =SUM(D11:F11) -> 450
B13: Monthly Totals | C13: =SUM(C4:C11) -> 1940 | D13: =SUM(D4:D11) -> 1885 | E13: =SUM(E4:E11) -> 1035 | F13: =SUM(F4:F11) -> 1035 | G13: =SUM(G4:G11) -> 5895

Sheet Projected Debts and Liabilities
B3: LIABILITIES | C3: September | D3: October | E3: November | F3: December | G3: Semester Total
B4: Exchanges | C4: 150 | D4: 150 | E4: 150 | F4: 150 | G4: =SUM(C4:F4) -> 600
B5: Brother Nights | C5: 100 | D5: 100 | E5: 100 | F5: 100 | G5: =SUM(C5:F5) -> 400
B6: Rush | C6: 350 | D6: 250 | E6: 100 | G6: =SUM(C6:F6) -> 700
B7: Initiation | E7: 1000 | G7: =SUM(C7:F7) -> 1000
B8: Road Trips | D8: 750 | G8: =SUM(C8:F8) -> 750
B9: Philanthropy | C9: 50 | D9: 50 | E9: 50 | F9: 50 | G9: =SUM(C9:F9) -> 200
B10: Scholarship | C10: 50 | D10: 50 | E10: 50 | F10: 50 | G10: =SUM(C10:F10) -> 200
B11: Chapter Fee | C11: paid | G11: =SUM(C11:F11) -> 0
B12: Membership Fees | C12: paid | G12: =SUM(C12:F12) -> 0
B13: Loss Prevention | C13: paid | G13: =SUM(C13:F13) -> 0
B14: Payment Plan | C14: 300 | D14: 300 | E14: 300 | F14: 300 | G14: =SUM(C14:F14) -> 1200
B15: Directors Insurance | C15: paid
B16: Monthly Totals | C16: =SUM(C4:C15) -> 1000 | D16: =SUM(D4:D14) -> 1650 | E16: =SUM(E4:E14) -> 1750 | F16: =SUM(F4:F14) -> 650 | G16: =SUM(G4:G15) -> 5050
B20: DEBT | C20: September | D20: October | E20: November | F20: December
B21: International | C21: 3235.43 | D21: =SUM(3235.43-300) -> 2935.43 | E21: 2635.43 | F21: 2335.43
B24: Debt free from international as of June 2012

Sheet Projected Totals
C6: PROJECTED TOTALS | D6: September | E6: October | F6: November | G6: December | H6: Semester Total
C7: Income | D7: ='Projected Income'!$C$13 -> 1940 | E7: ='Projected Income'!D13 -> 1885 | F7: ='Projected Income'!$E$13 -> 1035 | G7: ='Projected Income'!$F$13 -> 1035 | H7: ='Projected Income'!$G$13 -> 5895
C8: Liabilities | D8: =-'Projected Debts and Liabilities'!$C$16 -> -1000 | E8: =-'Projected Debts and Liabilities'!$D$16 -> -1650 | F8: =-'Projected Debts and Liabilities'!$E$16 -> -1750 | G8: =-'Projected Debts and Liabilities'!$F$16 -> -650 | H8: =-'Projected Debts and Liabilities'!$G$16 -> -5050
C10: TOTALS | D10: =SUM(D7:D8) -> 940 | E10: =SUM('Projected Income'!$D$13 - 'Projected Debts and Liabilities'!$D$16) -> 235 | F10: =SUM(F7:F9) -> -715 | G10: =SUM(G7:G9) -> 385 | H10: =SUM(H7:H9) -> 845
C13: CASH FLOW ANALYSIS | D13: September | E13: October | F13: November | G13: December | H13: Semester Total
C14: Chapter Account Totals | D14: 188.57 | E14: =D17 -> 1128.57 | F14: =E17 -> 1363.57 | G14: =F17 -> 648.57 | H14: =SUM(D14:G14) -> 3329.28
C15: Income | D15: ='Projected Income'!$C$13 -> 1940 | E15: ='Projected Income'!D13 -> 1885 | F15: ='Projected Income'!$E$13 -> 1035 | G15: ='Projected Income'!$F$13 -> 1035 | H15: ='Projected Income'!$G$13 -> 5895
C16: Liabilities | D16: =-'Projected Debts and Liabilities'!$C$16 -> -1000 | E16: =-'Projected Debts and Liabilities'!$D$16 -> -1650 | F16: =-'Projected Debts and Liabilities'!$E$16 -> -1750 | G16: =-'Projected Debts and Liabilities'!$F$16 -> -650 | H16: =-'Projected Debts and Liabilities'!$G$16 -> -5050
C17: TOTALS | D17: =SUM(D14:D16) -> 1128.57 | E17: =SUM(E14:E16) -> 1363.57 | F17: =SUM(F14:F16) -> 648.57 | G17: =SUM(G14:G16) -> 1033.57 | H17: =SUM(H14:H16) -> 4174.28
C23: End Fall Budget | D23: =H10 -> 845
C24: Current Chapter Account Balance | D24: 188.57
C25: Chapter Cash Balance | D25: 980 | F25: $200 of this is deposited in rental equipment waiting to be returned
C27: Account Balance for Winter | D27: =SUM(D23:D26) -> 2013.57
C29: Debt to International Winter | D29: 2335.43

Sheet Parkers
A1: NAME | B1: CONTACT | C1: Car Details | D1: Notes
A2: Alex | B2: 647-830-7015 | C2: Black Toyota Corolla | D2: Paid till July 30th, Not Renewing
A3: Simon | B3: 416-867-7097 lizichao@gmail.com 5195909603 | C3: Tan Toyota Corolla | D3: monthly parker, pays at beginning of the month
A4: Susan | B4: 416-803-9112 susanhopper1@googlemail.com | C4: Khaki Jeep Liberty (year 2003) Black Range Rover (year 2006) Licence plate no. BKBT 223 Licence plate no: BLLB 107 | D4: Pays on the 15th of each month $75)
A5: Spencer | B5: 613-261-4126 | C5: Black Alero | D5: Prepaid checks for Summer
A6: Rachel | B6: rachel.tulloch@utoronto.ca | C6: wants spot starting August 1st | D6: pays on the 1st of each month $75
B14: June | C14: July | D14: August | E14: September | F14: October | G14: November | H14: December
A15: Alex | B15: 75 | C15: 75 | D15: 0 | E15: 0 | F15: 0 | G15: 0 | H15: 0
A16: Simon | B16: 0 | C16: 70 | D16: 75 | E16: 0 | F16: 0 | G16: 0 | H16: 0
A17: Susan | B17: 0 | C17: 75 | D17: 75 | E17: 75 | F17: 75 | G17: 75 | H17: 75
A18: Spencer | B18: 75 | C18: 75 | D18: 75 | E18: 0 | F18: 0 | G18: 0 | H18: 0
A19: Uncashed checks | B19: 0 | C19: 0 | D19: 0 | E19: 150

Sheet Brother Fees
A3: Michael Capicotto | B3: Paid | C3: 400
A4: Ryan Breen | C4: 200
A5: Michael Shaw
A6: Dave Shaw | B6: Paid | C6: 400
A7: Tyler Dixon | B7: Paid | C7: 400
A8: Ben Triolo | B8: Paid | C8: 400
A9: Andrew Triolo | B9: Paid | C9: 400
A10: Balveer Singh
A11: Dovi Henry
A12: Aatish Jamal | B12: Paid | C12: 400
