Workbook
Name AllowFundHlook: 'Linked Program Codes'!$B$6:$W$7
Name AllowProg: 'Linked Program Codes'!$A$8:$W$53
Name CertBen: 'Staff Details'!$AA$11:$AA$201
Name CertFund: 'Staff Details'!$A$11:$A$201
Name CertGrant: 'Staff Details'!$I$11:$I$201
Name CertObj: 'Staff Details'!$G$11:$G$201
Name CertProg: 'Staff Details'!$E$11:$E$201
Name CertSalary: 'Staff Details'!$R$11:$R$201
Name ERRORRPT: #REF!
Name Fund22Grants: 'Fund 20 Grants'!$D$3:$W$3
Name Fund22Grants: 'Fund 22 Grants'!$D$3:$W$3
Name MINRESERVE: #REF!
Name PAGE01: #REF!
Name PAGE02: #REF!
Name PAGE03: #REF!
Name PAGE04: #REF!
Name PAGE05: #REF!
Name PAGE06: #REF!
Name PAGE07: #REF!
Name PAGE08: #REF!
Name PAGE09: #REF!
Name PAGE10: #REF!
Name PAGE11: #REF!
Name PAGE12: #REF!
Name PAGE13: #REF!
Name PAGE14: #REF!
Name PAGE15: #REF!
Name PAGE16: #REF!
Name page17: #REF!
Name PAGE18: #REF!
Name PAGE19: #REF!
Name PAGE20: #REF!
Name PAGE21: #REF!
Name PAGE22: #REF!
Name PAGE23: #REF!
Name printjob1: #REF!,#REF!,#REF!,#REF!,#REF!,#REF!,#REF!,#REF!,#REF!,#REF!,#REF!
Name printjob2: #REF!,#REF!,#REF!,#REF!,#REF!,#REF!,#REF!,#REF!,#REF!,#REF!,#REF!
Name printjob3: #REF!,#REF!
Name printsumm: #REF!,#REF!,#REF!,#REF!,#REF!
Name printtabor: #REF!,#REF!,#REF!
Name SPENDLIM: #REF!
Name SUMM01: #REF!
Name SUMM02: #REF!
Name SUMM03: #REF!
Name SUMM04: #REF!
Name SUMM05: #REF!
Name TAXLIM: #REF!

Sheet General Instructions
A1: GENERAL INSTRUCTIONS
A4: 1. | B4: Please enter information in the cells with Blue Text. Do not use decimals when entering data in the CDE-18 report.
B6: Cells that are gray are protected cells and can not be modified.
A9: 2. | B9: In cell B5, F5, C7and F7 on page 1, enter the header information exactly as it is to appears below.
B10: DISTRICT NAME: ALAMOSA RE-11J
B11: COUNTY: ALAMOSA
B12: ESTIMATED FUNDED PUPIL COUNT: 3000
B13: FOUR DIGIT DISTRICT/BOCES CODE: 0100
A16: 3. | B16: The "Salary Schedule" tab has been added for you to provide your master salary schedule for this workbook.
B17: The information on the "Salary Schedule" tab will be available to use on the "Staff Details" tab
A20: 4. | B20: The "Linked Program Codes" lets you know which fund - program combination will be linked to be various fund tab
B21: through the "Staff Details" tab.
A24: 5. | B24: Complete the "Staff Details" tab with staff that meet the valid fund - program combination for linkage to the various
B25: fund tabs in this workbook.
B26: If a cell is "Pink" is input is not valid and must be fixed.
B27: The "Salary" column of the "Staff Details" tab may be modified if needed, by overwriting the cell input.
B28: Columns highlighted in "Rose" are linked to the various fund tabs in this workbook.
A31: 6. | B31: After the data is provided on the "Staff Details" tab, the Fund 22 Grants must be
B32: identified and added to row 3 of the "Fund 22 Grants" tab.
B33: Also , add the grant description to row 4 of the "Fund 22 Grants" tab.
A36: 7. | B36: Complete the CDE-18 pages for funds that only pertain to your district
B38: You may "Hide" sheets that you are not using - under "Format", "Sheet", "Hide"
B39: You may "Hide" rows or columns that you are not using - under "Format", "Row" or "Column", "Hide"
B40: Be careful that no data is reflected on the hidden sheets.
A43: 8. | B43: After completing the CDE-18 -review the error report. Make appropriate corrections to fund pages to correct errors.
A46: 9. | B46: Additional worksheets to assist you in the budget process
B47: TABOR Worksheets (2 pages)
B48: Consolidated Budget Summary (6 pages)
A51: 10. | B51: Budget Adoption and Appropriations Resolution
A54: 11 | B54: Summary Budget Form page is generated based on the data provided within this workbook.

Sheet Page 1 - FY2013-14
A1: FISCAL YEAR 2013-2014
A2: COLORADO SCHOOL DISTRICT/BOCES
A3: OPTIONAL REPORT OF ADOPTED BUDGET - FORM CDE-18
A5: FOR SCHOOL DISTRICT (NAME) | E5: HEADQUARTERED IN (COUNTY)
A6: OR BOCES
A7: ESTIMATED FUNDED PUPIL COUNT FOR USE IN BUDGET YEAR 2013-2014 | E7: FOUR DIGIT DISTRICT/BOCES CODE
A11: CONTENTS
A12: Fund Type & | E12: Fund Type &
A13: Fund Number | E13: Fund Number
A14: 10 General Fund Revenue . . . . . . . . . . . . . . . . . . . . . . . . . . . . . . . . . . . . . . . . . . . . . . . . . . . . . . . . . . . . . . . . . . . . . . . . | E14: Internal Service Funds:
A15: 10 General Fund Expenditures . . . . . . . . . . . . . . . . . . . . . . . . . . . . . . . . . . . . . . . . . . . . . . . . . . . . . . . . . . . . . . . . . . | E15: 64 Risk-Related Activity Fund . . . . . . . . . . . . . . . . . . . . . . . . . . . . . . . . . . . . . . . . . . . . . . . . . . . . . . . . . . . . . . . . . . . . . . . .
A16: 11 Charter Fund Revenue . . . . . . . . . . . . . . . . . . . . . . . . . . . . . . . . . . . . . . . . . . . . . . . . . . . . . . . . . . . . . . | E16: Note: Fund 63 may be used as another risk-related activity fund. It will roll to Fund 64
A17: 11 Charter Fund Expenditures . . . . . . . . . . . . . . . . . . . . . . . . . . . . . . . . . . . . . . . . . . . . . . . . . . . . . . . . | E17: 61-62 & 65-69 Other Internal Service Funds . . . . . . . . . . . . . . . . . . . . . . . . . . . . . . . . . . . . . . . . . . . . . . . . . . . . . . . . . . . . . . . . . . . . . .
A18: 18 Insurance Reserve Special Revenue Fund. . . . . . . . . . . . . . . . . . . . . . . . . . . . . . . . . . . . . . . . . . . . . . . . . . . . . . . | E18: Trust/Agency Funds:
A19: 19 Colorado Preschool Fund. . . . . . . . . . . . . . . . . . . . . . . . . . . . . . . . . . . . . . . . . . . . . . . . . . . . . . . . . . . . . . . . . | E19: 74 Pupil Activity Agency Fund . . . . . . . . . . . . . . . . . . . . . . . . . . . . . . . . . . . . . . . . . . . . . . . . . . . . .
A20: Special Revenue Funds: | E20: 71-73 & 75-79 Trust and Other Agency Funds . . . . . . . . . . . . . . . . . . . . . . . . . . . . . . . . . . . . . . . . . . . . . . . . . . . . . . . . . . . . .
A21: 20 ARRA (Federal Stimulus Funding) Grants Fund . . . . . . . . . . . . . . . . . . . . . . . . . . . . . . . . . . . . . . . . . . . .
A22: 21 Capital Reserve Special Revenue Fund . . . . . . . . . . . . . . . . . . . . . . . . . . . . . . . . . . . . . . . . . . . . . . . . | E22: 85 Foundation Fund . . . . . . . . . . . . . . . . . . . . . . . . . . . . . . . . . . . . . . . . . . . . . . . . . . . . . . . . . . . . . . . . . .
A23: 22 Governmental Designated-Purpose Grants Fund. . . . . . . . . . . . . . . . . . . . . . . . . . . . . . . . . . . . . . . . . | E23: GASB 34 . . . . . . . . . . . . . . . . . . . . . . . . . . . . . . . . . . . . . . . . . . . . . . . . . . . . . . . . . . . . . . . . . . . . . . . . . . .
A24: 23 Pupil Activity Special Revenue Fund . . . . . . . . . . . . . . . . . . . . . . . . . . . . . . . . . . . . . . . . . . . . . . . . . . . . . . . . . . . . | E24: District Debt . . . . . . . . . . . . . . . . . . . . . . . . . . . . . . . . . . . . . . . . . . . . . . . . . . . . . . . . . . . . . . . . . . . . . .
A25: 24 Full-Day Kindergarten Mill Levy Override Fund. . . . . . . . . . . . . . . . . . . . . . . . . . . . . . . . . . . . . . .
A26: 25 Transportation Fund . . . . . . . . . . . . . . . . . . . . . . . . . . . . . . . . . . . . . . . . . . . . . . . . . . . . . . . . . . . . . . . . .
A27: 26-29 Other Special Revenue Funds . . . . . . . . . . . . . . . . . . . . . . . . . . . . . . . . . . . . . . . . . . . . . . . . . . . . . . . . .
A28: Debt Service Fund: | E28: Miscellaneous Worksheets: (USE WHEN RELEVANT)
A29: 31 Bond Redemption Fund . . . . . . . . . . . . . . . . . . . . . . . . . . . . . . . . . . . . . . . . . . . . . . . . . . . . . . . . . . . . . . . . . . . . . | E29: Arbitrage Rebate Amount . . . . . . . . . . . . . . . . . . . . . . . . . . . . . . . . . . . . . . . . . . . . . . . . . . . . . . . . . . . . . . . . . . . . . .
A30: 39 Non-Voter Approved Debt Service Fund . . . . . . . . . . . . . . . . . . . . . . . . . . . . . . . . . . . . . . . . . . . . . . . . . . . . . . . . . . . . . . . . . . . . . | E30: Arbitrage Rebate Amount . . . . . . . . . . . . . . . . . . . . . . . . . . . . . . . . . . . . . . . . . . . . . . . . . . . . . . . . . . . . . . . . . . . . . .
A31: Capital Projects Funds: | E31: Component Unit Revenues and Expenditures/Expenses . . . . . . . . . . . . . . . . . . . . . . . . . . . . . . . . . . .
A32: 41 Building Fund . . . . . . . . . . . . . . . . . . . . . . . . . . . . . . . . . . . . . . . . . . . . . . . . . . . . . . . . . . . . . . . . . . . . . . . . . . . . | E32: TABOR Emergency Reserves . . . . . . . . . . . . . . . . . . . . . . . . . . . . . . . . . . . . . . . . . . . . . . . . . . . . . . . . . . . . . . .
A33: 42 Special Building and Technology Fund . . . . . . . . . . . . . . . .. . . . . . . . . . . . . . . . . . . . . . . . . . . . . . . . . . . . . . . . . | E33: Appropriation Resolution. . . . . . . . . . . . . . . . . . . . . . . . . . . . . . . . . . . . . . . . . . . . . . . . . . . . . . . . . . . . . . . . . . . .
A34: 43 Capital Reserve Capital Projects Fund . . . . . . . . . . . . . . . . . . . . . . . . . . . . . . . . . . . . . . . . . . . . . . . . . . . . . . . . . . . . . . . . . . . | E34: Error Report . . . . . . . . . . . . . . . . . . . . . . . . . . . . . . . . . . . . . . . . . . . . . . . . . . . . .
A35: Enterprise Funds: | E35: Tabor Compliance Worksheet. . . . . . . . . . . . . . . . . . . . . . . . . . . . . . . . . . . . . . . . . . . . . . . . . . . . . . . . . . . . . . .
A36: 51 Food Service Fund . . . . . . . . . . . . . . . . . . . . . . . . . . . . . . . . . . . . . . . . . . . . . . . . . . . . . . . . . . . . . . . . . . . . . . . . . | E36: Summary Information:
A37: 52-59 Other Enterprise Funds . . . . . . . . . . . . . . . . . . . . . . . . . . . . . . . . . . . . . . . . . . . . . . . . . . . . . . . . . . . . . . . . . . . . . . . | E37: Budget Summary Worksheet (District Use Only) . . . . . . . . . . . . . . . . . . . . . . . . . . . . . . . . . . . . . . . . . . . . . . . . .
A39: NAME AND TITLE OF PERSON(S) TO CONTACT IN THE EVENT THERE ARE QUESTIONS REGARDING THIS REPORT:
A41: NAME | E41: TITLE
A43: PHONE | E43: FAX
A45: E-MAIL

Sheet Salary Schedule
B1: School District | D1: =+'Page 1 - FY2013-14'!B5 -> 0 | J1: District Code | K1: =+'Page 1 - FY2013-14'!F7 -> 0
B2: School District
B3: Salary Schedule for Certified Staff
B4: FY 2013-2014
B5: Directions:
B6: Insert the BASE amount in cell C11
B7: Insert the Step Increase amount (DOWN) in cell C12
B8: Insert the Education Level increase amount (ACROSS) in cell C13
B9: Insert the Step increase amount for Education Level at MA or higher (MA-DOWN) in cell C14
B11: S D | C11: BASE | D11: 0
B12: T O | C12: DOWN | D12: 0 | F12: Note: Do not change the size or location of this schedule, will impact linkage.
B13: E W | C13: ACROSS | D13: 0
B14: P N | C14: MA-DOWN | D14: 0
C15: 1 | D15: 2 | E15: 3 | F15: 4 | G15: 5 | H15: 6 | I15: 7 | J15: 8 | K15: 9 | L15: 10 | M15: 11 | N15: 12
C16: BA | D16: BA+12 | E16: BA+24 | F16: BA+36 | G16: BA+45 | H16: MA | I16: MA+12 | J16: MA+24 | K16: MA+36 | L16: MA+45 | M16: SPECED | N16: ED
B17: 0 | C17: =+$D$11 -> 0 | D17: =+C17+$D$13 -> 0 | E17: =+D17+$D$13 -> 0 | F17: =+E17+$D$13 -> 0 | G17: =+F17+$D$13 -> 0 | H17: =+G17+$D$13 -> 0 | I17: =+H17+$D$13 -> 0 | J17: =+I17+$D$13 -> 0 | K17: =+J17+$D$13 -> 0 | ... N17: =+M17+$D$13 -> 0
B18: 1 | C18: =+C17+$D$12 -> 0 | D18: =+D17+$D$12 -> 0 | E18: =+E17+$D$12 -> 0 | F18: =+F17+$D$12 -> 0 | G18: =+G17+$D$12 -> 0 | H18: =+H17+$D$14 -> 0 | I18: =+I17+$D$14 -> 0 | J18: =+J17+$D$14 -> 0 | K18: =+K17+$D$14 -> 0 | L18: =+L17+$D$14 -> 0 | M18: =+M17+$D$14 -> 0 | N18: =+N17+$D$14 -> 0
B19: 2 | C19: =+C18+$D$12 -> 0 | D19: =+D18+$D$12 -> 0 | E19: =+E18+$D$12 -> 0 | F19: =+F18+$D$12 -> 0 | G19: =+G18+$D$12 -> 0 | H19: =+H18+$D$14 -> 0 | I19: =+I18+$D$14 -> 0 | J19: =+J18+$D$14 -> 0 | K19: =+K18+$D$14 -> 0 | L19: =+L18+$D$14 -> 0 | M19: =+M18+$D$14 -> 0 | N19: =+N18+$D$14 -> 0
B20: 3 | C20: =+C19+$D$12 -> 0 | D20: =+D19+$D$12 -> 0 | E20: =+E19+$D$12 -> 0 | F20: =+F19+$D$12 -> 0 | G20: =+G19+$D$12 -> 0 | H20: =+H19+$D$14 -> 0 | I20: =+I19+$D$14 -> 0 | J20: =+J19+$D$14 -> 0 | K20: =+K19+$D$14 -> 0 | L20: =+L19+$D$14 -> 0 | M20: =+M19+$D$14 -> 0 | N20: =+N19+$D$14 -> 0
B21: 4 | C21: =+C20+$D$12 -> 0 | D21: =+D20+$D$12 -> 0 | E21: =+E20+$D$12 -> 0 | F21: =+F20+$D$12 -> 0 | G21: =+G20+$D$12 -> 0 | H21: =+H20+$D$14 -> 0 | I21: =+I20+$D$14 -> 0 | J21: =+J20+$D$14 -> 0 | K21: =+K20+$D$14 -> 0 | L21: =+L20+$D$14 -> 0 | M21: =+M20+$D$14 -> 0 | N21: =+N20+$D$14 -> 0
B22: 5 | C22: =+C21+$D$12 -> 0 | D22: =+D21+$D$12 -> 0 | E22: =+E21+$D$12 -> 0 | F22: =+F21+$D$12 -> 0 | G22: =+G21+$D$12 -> 0 | H22: =+H21+$D$14 -> 0 | I22: =+I21+$D$14 -> 0 | J22: =+J21+$D$14 -> 0 | K22: =+K21+$D$14 -> 0 | L22: =+L21+$D$14 -> 0 | M22: =+M21+$D$14 -> 0 | N22: =+N21+$D$14 -> 0
B23: 6 | C23: =+C22+$D$12 -> 0 | D23: =+D22+$D$12 -> 0 | E23: =+E22+$D$12 -> 0 | F23: =+F22+$D$12 -> 0 | G23: =+G22+$D$12 -> 0 | H23: =+H22+$D$14 -> 0 | I23: =+I22+$D$14 -> 0 | J23: =+J22+$D$14 -> 0 | K23: =+K22+$D$14 -> 0 | L23: =+L22+$D$14 -> 0 | M23: =+M22+$D$14 -> 0 | N23: =+N22+$D$14 -> 0
B24: 7 | C24: =+C23+$D$12 -> 0 | D24: =+D23+$D$12 -> 0 | E24: =+E23+$D$12 -> 0 | F24: =+F23+$D$12 -> 0 | G24: =+G23+$D$12 -> 0 | H24: =+H23+$D$14 -> 0 | I24: =+I23+$D$14 -> 0 | J24: =+J23+$D$14 -> 0 | K24: =+K23+$D$14 -> 0 | L24: =+L23+$D$14 -> 0 | M24: =+M23+$D$14 -> 0 | N24: =+N23+$D$14 -> 0
B25: 8 | C25: =+C24+$D$12 -> 0 | D25: =+D24+$D$12 -> 0 | E25: =+E24+$D$12 -> 0 | F25: =+F24+$D$12 -> 0 | G25: =+G24+$D$12 -> 0 | H25: =+H24+$D$14 -> 0 | I25: =+I24+$D$14 -> 0 | J25: =+J24+$D$14 -> 0 | K25: =+K24+$D$14 -> 0 | L25: =+L24+$D$14 -> 0 | M25: =+M24+$D$14 -> 0 | N25: =+N24+$D$14 -> 0
B26: 9 | C26: =+C25+$D$12 -> 0 | D26: =+D25+$D$12 -> 0 | E26: =+E25+$D$12 -> 0 | F26: =+F25+$D$12 -> 0 | G26: =+G25+$D$12 -> 0 | H26: =+H25+$D$14 -> 0 | I26: =+I25+$D$14 -> 0 | J26: =+J25+$D$14 -> 0 | K26: =+K25+$D$14 -> 0 | L26: =+L25+$D$14 -> 0 | M26: =+M25+$D$14 -> 0 | N26: =+N25+$D$14 -> 0
B27: 10 | C27: =+C26+$D$12 -> 0 | D27: =+D26+$D$12 -> 0 | E27: =+E26+$D$12 -> 0 | F27: =+F26+$D$12 -> 0 | G27: =+G26+$D$12 -> 0 | H27: =+H26+$D$14 -> 0 | I27: =+I26+$D$14 -> 0 | J27: =+J26+$D$14 -> 0 | K27: =+K26+$D$14 -> 0 | L27: =+L26+$D$14 -> 0 | M27: =+M26+$D$14 -> 0 | N27: =+N26+$D$14 -> 0
B28: 11 | C28: =+C27+$D$12 -> 0 | D28: =+D27+$D$12 -> 0 | E28: =+E27+$D$12 -> 0 | F28: =+F27+$D$12 -> 0 | G28: =+G27+$D$12 -> 0 | H28: =+H27+$D$14 -> 0 | I28: =+I27+$D$14 -> 0 | J28: =+J27+$D$14 -> 0 | K28: =+K27+$D$14 -> 0 | L28: =+L27+$D$14 -> 0 | M28: =+M27+$D$14 -> 0 | N28: =+N27+$D$14 -> 0
B29: 12 | C29: =+C28+$D$12 -> 0 | D29: =+D28+$D$12 -> 0 | E29: =+E28+$D$12 -> 0 | F29: =+F28+$D$12 -> 0 | G29: =+G28+$D$12 -> 0 | H29: =+H28+$D$14 -> 0 | I29: =+I28+$D$14 -> 0 | J29: =+J28+$D$14 -> 0 | K29: =+K28+$D$14 -> 0 | L29: =+L28+$D$14 -> 0 | M29: =+M28+$D$14 -> 0 | N29: =+N28+$D$14 -> 0
... B47: 30 | C47: =+C46+$D$12 -> 0 | D47: =+D46+$D$12 -> 0 | E47: =+E46+$D$12 -> 0 | F47: =+F46+$D$12 -> 0 | G47: =+G46+$D$12 -> 0 | H47: =+H46+$D$14 -> 0 | I47: =+I46+$D$14 -> 0 | J47: =+J46+$D$14 -> 0 | K47: =+K46+$D$14 -> 0 | L47: =+L46+$D$14 -> 0 | M47: =+M46+$D$14 -> 0 | N47: =+N46+$D$14 -> 0

Sheet Linked Program Codes
A1: School District | C1: =+'Page 1 - FY2013-14'!B5 -> 0 | I1: District Code | K1: =+'Page 1 - FY2013-14'!F7 -> 0
A2: School District
A3: Program Codes that are Linked to the Fund Tabs through Staff Details Page
A4: FY 2013-2014
B5: Fund:
B6: 10 | C6: 11 | D6: 18 | E6: 19 | F6: 20 | G6: 21 | H6: 22 | I6: 23 | J6: 24 | K6: 25 | L6: 26-29 | M6: 31 | N6: 41 | O6: 42 | P6: 43 | Q6: 51 | R6: 52-59 | S6: 64 | T6: 61-62/65-69 | U6: 74 | V6: 72-73/75-78 | W6: 85
A7: Program: | B7: 2 | C7: 3 | D7: 4 | E7: 5 | F7: 6 | G7: 7 | H7: 8 | I7: 9 | J7: 10 | K7: 11 | L7: 12 | M7: 13 | N7: 14 | O7: 15 | P7: 16 | Q7: 17 | R7: 18 | S7: 19 | T7: 20 | U7: 21 | V7: 22 | W7: 23
A8: 0010 | B8: 0010 | C8: 0010 | D8: N/A | E8: N/A | F8: 0010 | G8: N/A | H8: 0010 | I8: N/A | J8: 0010 | K8: N/A | L8: N/A | M8: N/A | N8: N/A | O8: N/A | P8: N/A | Q8: N/A | R8: N/A | S8: N/A | T8: N/A | U8: N/A | V8: N/A | W8: N/A
A9: 0020 | B9: 0020 | C9: 0020 | D9: N/A | E9: N/A | F9: 0020 | G9: N/A | H9: 0020 | I9: N/A | J9: N/A | K9: N/A | L9: N/A | M9: N/A | N9: N/A | O9: N/A | P9: N/A | Q9: N/A | R9: N/A | S9: N/A | T9: N/A | U9: N/A | V9: N/A | W9: N/A
A10: 0030 | B10: 0030 | C10: 0030 | D10: N/A | E10: N/A | F10: N/A | G10: N/A | H10: N/A | I10: N/A | J10: N/A | K10: N/A | L10: N/A | M10: N/A | N10: N/A | O10: N/A | P10: N/A | Q10: N/A | R10: N/A | S10: N/A | T10: N/A | U10: N/A | V10: N/A | W10: N/A
A11: 0040 | B11: 0040 | C11: 0040 | D11: N/A | E11: 0040 | F11: N/A | G11: N/A | H11: N/A | I11: N/A | J11: N/A | K11: N/A | L11: N/A | M11: N/A | N11: N/A | O11: N/A | P11: N/A | Q11: N/A | R11: N/A | S11: N/A | T11: N/A | U11: N/A | V11: N/A | W11: N/A
A12: 0050 | B12: 0050 | C12: 0050 | D12: N/A | E12: N/A | F12: N/A | G12: N/A | H12: N/A | I12: N/A | J12: N/A | K12: N/A | L12: N/A | M12: N/A | N12: N/A | O12: N/A | P12: N/A | Q12: N/A | R12: N/A | S12: N/A | T12: N/A | U12: N/A | V12: N/A | W12: N/A
A13: 0051 | B13: 0051 | C13: 0051 | D13: N/A | E13: N/A | F13: N/A | G13: N/A | H13: N/A | I13: N/A | J13: N/A | K13: N/A | L13: N/A | M13: N/A | N13: N/A | O13: N/A | P13: N/A | Q13: N/A | R13: N/A | S13: N/A | T13: N/A | U13: N/A | V13: N/A | W13: N/A
A14: 0060 | B14: 0060 | C14: 0060 | D14: N/A | E14: N/A | F14: 0060 | G14: N/A | H14: 0060 | I14: N/A | J14: N/A | K14: N/A | L14: N/A | M14: N/A | N14: N/A | O14: N/A | P14: N/A | Q14: N/A | R14: N/A | S14: N/A | T14: N/A | U14: N/A | V14: N/A | W14: N/A
A15: 0070 | B15: 0070 | C15: 0070 | D15: N/A | E15: N/A | F15: N/A | G15: N/A | H15: N/A | I15: N/A | J15: N/A | K15: N/A | L15: N/A | M15: N/A | N15: N/A | O15: N/A | P15: N/A | Q15: N/A | R15: N/A | S15: N/A | T15: N/A | U15: N/A | V15: N/A | W15: N/A
A16: 0080 | B16: 0080 | C16: 0080 | D16: N/A | E16: N/A | F16: N/A | G16: N/A | H16: N/A | I16: N/A | J16: N/A | K16: N/A | L16: N/A | M16: N/A | N16: N/A | O16: N/A | P16: N/A | Q16: N/A | R16: N/A | S16: N/A | T16: N/A | U16: N/A | V16: N/A | W16: N/A
A17: 0090 | B17: 0090 | C17: 0090 | D17: N/A | E17: N/A | F17: N/A | G17: N/A | H17: N/A | I17: N/A | J17: N/A | K17: N/A | L17: N/A | M17: N/A | N17: N/A | O17: N/A | P17: N/A | Q17: N/A | R17: N/A | S17: N/A | T17: N/A | U17: N/A | V17: N/A | W17: N/A
A18: 0100 | B18: 0100 | C18: 0100 | D18: N/A | E18: N/A | F18: N/A | G18: N/A | H18: N/A | I18: N/A | J18: N/A | K18: N/A | L18: N/A | M18: N/A | N18: N/A | O18: N/A | P18: N/A | Q18: N/A | R18: N/A | S18: N/A | T18: N/A | U18: N/A | V18: N/A | W18: N/A
A19: 0200 | B19: 0200 | C19: 0200 | D19: N/A | E19: N/A | F19: N/A | G19: N/A | H19: N/A | I19: N/A | J19: N/A | K19: N/A | L19: N/A | M19: N/A | N19: N/A | O19: N/A | P19: N/A | Q19: N/A | R19: N/A | S19: N/A | T19: N/A | U19: N/A | V19: N/A | W19: N/A
... A53: 4000 | B53: 4000 | C53: 4000 | D53: N/A | E53: N/A | F53: N/A | G53: N/A | H53: N/A | I53: N/A | J53: N/A | K53: N/A | L53: N/A | M53: N/A | N53: N/A | O53: N/A | P53: N/A | Q53: N/A | R53: N/A | S53: N/A | T53: N/A | U53: N/A | V53: N/A | W53: N/A

Sheet Staff Details
A1: School District | C1: =+'Page 1 - FY2013-14'!B5 -> 0 | J1: District Code | K1: =+'Page 1 - FY2013-14'!F7 -> 0
S3: 0.1015 | T3: 0.07 | U3: 0.0145 | V3: 300 | W3: Amount per month towards insurances
L4: FY2013-2014 | S4: 0.1015 | T4: 0.07 | U4: 0.0145
A5: State Account Number | L5: Salary Schedule | R5: PROPOSED SALARY AND BENEFITS FY2011-2012 | AA5: Total | AB5: Total
E6: Bolded | F6: Salary | G6: Bolded | H6: Job | I6: Grant | L6: Education | M6: Step - | N6: Salary Schedule | O6: Contract | P6: FTE % | Q6: PY | T6: Add'l | AA6: Benefit | AB6: Position
A7: Fund | B7: Location | C7: SRE | D7: Program | E7: Program | F7: Object | G7: Object | H7: Class | I7: Code | J7: Employee Name | K7: Position | L7: Level | M7: Years in District | N7: Amount | O7: Start Date | P7: 1.00 = 100% | Q7: Salary | R7: Salary | S7: PERA | T7: PERA | U7: Medicare | V7: Health | W7: Dental | X7: Life | Y7: St. Disab. | Z7: Others | AA7: Costs | AB7: Costs
R9: =SUM(R11:R65536) -> 0 | S9: =SUM(S11:S65536) -> 0 | T9: =SUM(T11:T65536) -> 0 | U9: =SUM(U11:U65536) -> 0 | V9: =SUM(V11:V65536) -> 0 | W9: =SUM(W11:W65536) -> 0 | X9: =SUM(X11:X65536) -> 0 | Y9: =SUM(Y11:Y65536) -> 0 | ... AB9: =SUM(AB11:AB65536) -> 0 | AC9: Totals
A10: f1 | B10: f2 | C10: f3 | D10: f4 | E10: f5 | F10: f6 | G10: f7 | H10: f8 | I10: f9 | J10: f10 | K10: f11 | L10: f13 | M10: f14 | N10: f15 | O10: f16 | P10: f18 | Q10: f19 | R10: f20 | S10: f21 | T10: f22 | U10: f23 | V10: f24 | W10: f25 | X10: f26 | Y10: f27 | Z10: f28 | AA10: f29 | AB10: f30
G11: 0100 | N11: =VLOOKUP(M11,'Salary Schedule'!$B$16:$N$47,L11+1,FALSE) -> 0 | P11: 0 | R11: =ROUND((+N11*P11),0) -> 0 | S11: =+R11*$S$4 -> 0 | T11: =+R11*$T$4 -> 0 | U11: =+R11*$U$4 -> 0 | V11: =($V$3*12)*P11 -> 0 | W11: 0 | X11: 0 | Y11: 0 | Z11: 0 | AA11: =ROUND((SUM(S11:Z11)),0) -> 0 | AB11: =ROUND((+R11+AA11),0) -> 0
G12: 0100 | N12: =VLOOKUP(M12,'Salary Schedule'!$B$16:$N$47,L12+1,FALSE) -> 0 | P12: 0 | R12: =ROUND((+N12*P12),0) -> 0 | S12: =+R12*$S$4 -> 0 | T12: =+R12*$T$4 -> 0 | U12: =+R12*$U$4 -> 0 | V12: =($V$3*12)*P12 -> 0 | W12: 0 | X12: 0 | Y12: 0 | Z12: 0 | AA12: =ROUND((SUM(S12:Z12)),0) -> 0 | AB12: =ROUND((+R12+AA12),0) -> 0
G13: 0100 | N13: =VLOOKUP(M13,'Salary Schedule'!$B$16:$N$47,L13+1,FALSE) -> 0 | P13: 0 | R13: =ROUND((+N13*P13),0) -> 0 | S13: =+R13*$S$4 -> 0 | T13: =+R13*$T$4 -> 0 | U13: =+R13*$U$4 -> 0 | V13: =($V$3*12)*P13 -> 0 | W13: 0 | X13: 0 | Y13: 0 | Z13: 0 | AA13: =ROUND((SUM(S13:Z13)),0) -> 0 | AB13: =ROUND((+R13+AA13),0) -> 0
G14: 0100 | N14: =VLOOKUP(M14,'Salary Schedule'!$B$16:$N$47,L14+1,FALSE) -> 0 | P14: 0 | R14: =ROUND((+N14*P14),0) -> 0 | S14: =+R14*$S$4 -> 0 | T14: =+R14*$T$4 -> 0 | U14: =+R14*$U$4 -> 0 | V14: =($V$3*12)*P14 -> 0 | W14: 0 | X14: 0 | Y14: 0 | Z14: 0 | AA14: =ROUND((SUM(S14:Z14)),0) -> 0 | AB14: =ROUND((+R14+AA14),0) -> 0
G15: 0100 | N15: =VLOOKUP(M15,'Salary Schedule'!$B$16:$N$47,L15+1,FALSE) -> 0 | P15: 0 | R15: =ROUND((+N15*P15),0) -> 0 | S15: =+R15*$S$4 -> 0 | T15: =+R15*$T$4 -> 0 | U15: =+R15*$U$4 -> 0 | V15: =($V$3*12)*P15 -> 0 | W15: 0 | X15: 0 | Y15: 0 | Z15: 0 | AA15: =ROUND((SUM(S15:Z15)),0) -> 0 | AB15: =ROUND((+R15+AA15),0) -> 0
G16: 0100 | N16: =VLOOKUP(M16,'Salary Schedule'!$B$16:$N$47,L16+1,FALSE) -> 0 | P16: 0 | R16: =ROUND((+N16*P16),0) -> 0 | S16: =+R16*$S$4 -> 0 | T16: =+R16*$T$4 -> 0 | U16: =+R16*$U$4 -> 0 | V16: =($V$3*12)*P16 -> 0 | W16: 0 | X16: 0 | Y16: 0 | Z16: 0 | AA16: =ROUND((SUM(S16:Z16)),0) -> 0 | AB16: =ROUND((+R16+AA16),0) -> 0
G17: 0100 | N17: =VLOOKUP(M17,'Salary Schedule'!$B$16:$N$47,L17+1,FALSE) -> 0 | P17: 0 | R17: =ROUND((+N17*P17),0) -> 0 | S17: =+R17*$S$4 -> 0 | T17: =+R17*$T$4 -> 0 | U17: =+R17*$U$4 -> 0 | V17: =($V$3*12)*P17 -> 0 | W17: 0 | X17: 0 | Y17: 0 | Z17: 0 | AA17: =ROUND((SUM(S17:Z17)),0) -> 0 | AB17: =ROUND((+R17+AA17),0) -> 0
G18: 0100 | N18: =VLOOKUP(M18,'Salary Schedule'!$B$16:$N$47,L18+1,FALSE) -> 0 | P18: 0 | R18: =ROUND((+N18*P18),0) -> 0 | S18: =+R18*$S$4 -> 0 | T18: =+R18*$T$4 -> 0 | U18: =+R18*$U$4 -> 0 | V18: =($V$3*12)*P18 -> 0 | W18: 0 | X18: 0 | Y18: 0 | Z18: 0 | AA18: =ROUND((SUM(S18:Z18)),0) -> 0 | AB18: =ROUND((+R18+AA18),0) -> 0
G19: 0100 | N19: =VLOOKUP(M19,'Salary Schedule'!$B$16:$N$47,L19+1,FALSE) -> 0 | P19: 0 | R19: =ROUND((+N19*P19),0) -> 0 | S19: =+R19*$S$4 -> 0 | T19: =+R19*$T$4 -> 0 | U19: =+R19*$U$4 -> 0 | V19: =($V$3*12)*P19 -> 0 | W19: 0 | X19: 0 | Y19: 0 | Z19: 0 | AA19: =ROUND((SUM(S19:Z19)),0) -> 0 | AB19: =ROUND((+R19+AA19),0) -> 0
G20: 0100 | N20: =VLOOKUP(M20,'Salary Schedule'!$B$16:$N$47,L20+1,FALSE) -> 0 | P20: 0 | R20: =ROUND((+N20*P20),0) -> 0 | S20: =+R20*$S$4 -> 0 | T20: =+R20*$T$4 -> 0 | U20: =+R20*$U$4 -> 0 | V20: =($V$3*12)*P20 -> 0 | W20: 0 | X20: 0 | Y20: 0 | Z20: 0 | AA20: =ROUND((SUM(S20:Z20)),0) -> 0 | AB20: =ROUND((+R20+AA20),0) -> 0
G21: 0100 | N21: =VLOOKUP(M21,'Salary Schedule'!$B$16:$N$47,L21+1,FALSE) -> 0 | P21: 0 | R21: =ROUND((+N21*P21),0) -> 0 | S21: =+R21*$S$4 -> 0 | T21: =+R21*$T$4 -> 0 | U21: =+R21*$U$4 -> 0 | V21: =($V$3*12)*P21 -> 0 | W21: 0 | X21: 0 | Y21: 0 | Z21: 0 | AA21: =ROUND((SUM(S21:Z21)),0) -> 0 | AB21: =ROUND((+R21+AA21),0) -> 0
G22: 0100 | N22: =VLOOKUP(M22,'Salary Schedule'!$B$16:$N$47,L22+1,FALSE) -> 0 | P22: 0 | R22: =ROUND((+N22*P22),0) -> 0 | S22: =+R22*$S$4 -> 0 | T22: =+R22*$T$4 -> 0 | U22: =+R22*$U$4 -> 0 | V22: =($V$3*12)*P22 -> 0 | W22: 0 | X22: 0 | Y22: 0 | Z22: 0 | AA22: =ROUND((SUM(S22:Z22)),0) -> 0 | AB22: =ROUND((+R22+AA22),0) -> 0
... G201: 0100 | N201: =VLOOKUP(M201,'Salary Schedule'!$B$16:$N$47,L201+1,FALSE) -> 0 | P201: 0 | R201: =ROUND((+N201*P201),0) -> 0 | S201: =+R201*$S$4 -> 0 | T201: =+R201*$T$4 -> 0 | U201: =+R201*$U$4 -> 0 | V201: =($V$3*12)*P201 -> 0 | W201: 0 | X201: 0 | Y201: 0 | Z201: 0 | AA201: =ROUND((SUM(S201:Z201)),0) -> 0 | AB201: =ROUND((+R201+AA201),0) -> 0

Sheet GenFundREV
A1: School District | C1: =+'Page 1 - FY2013-14'!B5 -> 0 | D1: District Code | E1: =+'Page 1 - FY2013-14'!F7 -> 0 | G1: * Round to Nearest Dollar *
A2: Fund 10: GENERAL FUND REVENUE
D3: Prior Year Actual - Audited FY11-12 | E3: Current Fiscal Year - Budgeted FY12-13 | F3: Current Fiscal Year - Projected FY12-13 | G3: Original Ensuing Fiscal Year - Budget FY13-14 | H3: Adjustments Ensuing Fiscal Year - Budget FY13-14 | I3: Revised Ensuing Fiscal Year - Budget FY13-14
H4: Record Inceases to revenue are positive amounts and Decreases as negatives | I4: Figures (Totals) which will appear on Budget Form to Submit to CDE
A5: Codes | B5: BEGINNING FUND BALANCE | D5: 0 | E5: 0 | F5: 0 | G5: 0 | H5: 0 | I5: =SUM(G5+H5) -> 0
A6: Source | B6: REVENUE FROM LOCAL SOURCES
A7: 1110 | B7: 1. | C7: Current Property Taxes | D7: 0 | E7: 0 | F7: 0 | G7: 0 | H7: 0 | I7: =SUM(G7+H7) -> 0
A8: 1120 | B8: 2. | C8: Specific Ownership Taxes | D8: 0 | E8: 0 | F8: 0 | G8: 0 | H8: 0 | I8: =SUM(G8+H8) -> 0
A9: 1130 | B9: 3. | C9: Sales and Use Taxes | D9: 0 | E9: 0 | F9: 0 | G9: 0 | H9: 0 | I9: =SUM(G9+H9) -> 0
A10: 1140 | B10: 4. | C10: Delinquent Taxes and Penalties and Interest on Taxes | D10: 0 | E10: 0 | F10: 0 | G10: 0 | H10: 0 | I10: =SUM(G10+H10) -> 0
A11: 1190 | B11: 5. | C11: Other Taxes from Local Sources | D11: 0 | E11: 0 | F11: 0 | G11: 0 | H11: 0 | I11: =SUM(G11+H11) -> 0
A12: 1310 | B12: 6. | C12: Tuition from Individuals | D12: 0 | E12: 0 | F12: 0 | G12: 0 | H12: 0 | I12: =SUM(G12+H12) -> 0
A13: 1311 | B13: 7. | C13: Summer School/Interterm/Intercession Fees | D13: 0 | E13: 0 | F13: 0 | G13: 0 | H13: 0 | I13: =SUM(G13+H13) -> 0
A14: 1321 | B14: 8. | C14: Tuition from WITHIN the BOCES (or Administrative Unit(AU)) | D14: 0 | E14: 0 | F14: 0 | G14: 0 | H14: 0 | I14: =SUM(G14+H14) -> 0
A15: 1322 | B15: 9. | C15: Tuition from Other Colorado Districts or BOCES (or AU) | D15: 0 | E15: 0 | F15: 0 | G15: 0 | H15: 0 | I15: =SUM(G15+H15) -> 0
A16: 1323 | B16: 10. | C16: Tuition from Excess Costs | D16: 0 | E16: 0 | F16: 0 | G16: 0 | H16: 0 | I16: =SUM(G16+H16) -> 0
A17: 1324 | B17: 11. | C17: Tuition from CDE for Out-of District Placed Pupils | D17: 0 | E17: 0 | F17: 0 | G17: 0 | H17: 0 | I17: =SUM(G17+H17) -> 0
A18: 1330 | B18: 12. | C18: Tuition from School Districts Outside the State | D18: 0 | E18: 0 | F18: 0 | G18: 0 | H18: 0 | I18: =SUM(G18+H18) -> 0
... A30: 1740 | B30: 24. | C30: Fees | D30: 0 | E30: 0 | F30: 0 | G30: 0 | H30: 0 | I30: =SUM(G30+H30) -> 0
A31: 1800 | B31: 25. | C31: Community Service Activities | D31: 0 | E31: 0 | F31: 0 | G31: 0 | H31: 0 | I31: =SUM(G31+H31) -> 0
A32: 1850 | B32: 26. | C32: Charter School Revenue | D32: 0 | E32: 0 | F32: 0 | G32: 0 | H32: 0 | I32: =SUM(G32+H32) -> 0
A33: 1900 | B33: 28. | C33: Other Revenue from Local Sources | D33: 0 | E33: 0 | F33: 0 | G33: 0 | H33: 0 | I33: =SUM(G33+H33) -> 0
A34: 1910 | B34: 29. | C34: Rentals/Leases | D34: 0 | E34: 0 | F34: 0 | G34: 0 | H34: 0 | I34: =SUM(G34+H34) -> 0
A35: 1920 | B35: 30. | C35: Contributions and Donations for Private Sources | D35: 0 | E35: 0 | F35: 0 | G35: 0 | H35: 0 | I35: =SUM(G35+H35) -> 0
A36: 1930 | B36: 31. | C36: Sale of Fixed Assets | D36: 0 | E36: 0 | F36: 0 | G36: 0 | H36: 0 | I36: =SUM(G36+H36) -> 0
A37: 1940 | B37: 32. | C37: Instructional Materials Fees | D37: 0 | E37: 0 | F37: 0 | G37: 0 | H37: 0 | I37: =SUM(G37+H37) -> 0
A38: 1951 | B38: 33. | C38: Services Provided within BOCES: local | D38: 0 | E38: 0 | F38: 0 | G38: 0 | H38: 0 | I38: =SUM(G38+H38) -> 0
A39: 1952 | B39: 34. | C39: Serivces Provided other Colorado BOCES of Districts: local | D39: 0 | E39: 0 | F39: 0 | G39: 0 | H39: 0 | I39: =SUM(G39+H39) -> 0
A40: 1954 | B40: 35. | C40: Services Provided Charter Schools: local | D40: 0 | E40: 0 | F40: 0 | G40: 0 | H40: 0 | I40: =SUM(G40+H40) -> 0
A41: 1959 | B41: 36. | C41: Services Provided other Units: local | D41: 0 | E41: 0 | F41: 0 | G41: 0 | H41: 0 | I41: =SUM(G41+H41) -> 0
A42: 1960 | B42: 37. | C42: Parking Fees | D42: 0 | E42: 0 | F42: 0 | G42: 0 | H42: 0 | I42: =SUM(G42+H42) -> 0
B43: 38. | C43: All Other Local Revenue Codes | D43: 0 | E43: 0 | F43: 0 | G43: 0 | H43: 0 | I43: =SUM(G43+H43) -> 0
B45: 39. | C45: TOTAL REVENUE FROM LOCAL SOURCES (Sum of lines 1-38) | D45: =SUM(D7:D43) -> 0 | E45: =SUM(E7:E43) -> 0 | F45: =SUM(F7:F43) -> 0 | G45: =SUM(G7:G43) -> 0 | H45: =SUM(H7:H43) -> 0 | I45: =SUM(I7:I43) -> 0
B47: REVENUE FROM INTERMEDIATE (COUNTY) SOURCES
A48: 2000 | B48: 40. | C48: TOTAL REVENUE FROM INTERMEDIATE (COUNTY) SOURCES | D48: 0 | E48: 0 | F48: 0 | G48: 0 | H48: 0 | I48: =SUM(G48+H48) -> 0
B50: REVENUE FROM STATE SOURCES
A51: 3110 | B51: 41. | C51: State Equalization | D51: 0 | E51: 0 | F51: 0 | G51: 0 | H51: 0 | I51: =SUM(G51+H51) -> 0
A52: 3111 | B52: 41a | C52: Full Day Kindergarten, Hold Harmless (Grant Code: 0000) | D52: 0 | E52: 0 | F52: 0 | G52: 0 | H52: 0 | I52: =SUM(G52+H52) -> 0
A53: 3112 | B53: 42. | C53: Capital Construction | D53: 0 | E53: 0 | F53: 0 | G53: 0 | H53: 0 | I53: =SUM(G53+H53) -> 0
A54: 3113 | B54: 43. | C54: Charter School Capital Constrcution | D54: 0 | E54: 0 | F54: 0 | G54: 0 | H54: 0 | I54: =SUM(G54+H54) -> 0
A55: 3114 | B55: 44. | C55: Increasing Enrollment Aid | D55: 0 | E55: 0 | F55: 0 | G55: 0 | H55: 0 | I55: =SUM(G55+H55) -> 0
A56: 3115 | B56: 45. | C56: Tracking On-Line Programs | D56: 0 | E56: 0 | F56: 0 | G56: 0 | H56: 0 | I56: =SUM(G56+H56) -> 0
A57: 3116 | B57: 46. | C57: School Construction and Renovation Project | D57: 0 | E57: 0 | F57: 0 | G57: 0 | H57: 0 | I57: =SUM(G57+H57) -> 0
A58: 3120 | B58: 47. | C58: Vocational Education | D58: 0 | E58: 0 | F58: 0 | G58: 0 | H58: 0 | I58: =SUM(G58+H58) -> 0
A59: 3130 | B59: 48. | C59: Exceptional Children's Education Act (ECEA) | D59: 0 | E59: 0 | F59: 0 | G59: 0 | H59: 0 | I59: =SUM(G59+H59) -> 0
A60: 3140 | B60: 49. | C60: English Language Proficiency Act (ELPA) | D60: 0 | E60: 0 | F60: 0 | G60: 0 | H60: 0 | I60: =SUM(G60+H60) -> 0
A61: 3150 | B61: 50. | C61: Gifted and Talented (ECEA) | D61: 0 | E61: 0 | F61: 0 | G61: 0 | H61: 0 | I61: =SUM(G61+H61) -> 0
A62: 3160 | B62: 51. | C62: Transportation | D62: 0 | E62: 0 | F62: 0 | G62: 0 | H62: 0 | I62: =SUM(G62+H62) -> 0
... A73: 3959 | B73: 62. | C73: Services Provided Other Units: State Level | D73: 0 | E73: 0 | F73: 0 | G73: 0 | H73: 0 | I73: =SUM(G73+H73) -> 0
B75: 63. | C75: TOTAL NET REVENUE FROM STATE SOURCES (Sum of lines 41-62) | D75: =SUM(D51:D73) -> 0 | E75: =SUM(E51:E73) -> 0 | F75: =SUM(F51:F73) -> 0 | G75: =SUM(G51:G73) -> 0 | H75: =SUM(H51:H73) -> 0 | I75: =SUM(I51:I73) -> 0
C77: REVENUE FROM FEDERAL SOURCES
A78: 4000 | B78: 64. | C78: Federal Revenue from CDE | D78: 0 | E78: 0 | F78: 0 | G78: 0 | H78: 0 | I78: =SUM(G78+H78) -> 0
A79: 4010 | B79: 65a. | C79: Federal Revenue - ARRA - Education Stabilization Funding (Grant Code: 4394) | D79: 0 | E79: 0 | F79: 0 | G79: 0 | H79: 0 | I79: =SUM(G79+H79) -> 0
A80: 4010 | B80: 65b. | C80: Federal Revenue from other State Source | D80: 0 | E80: 0 | F80: 0 | G80: 0 | H80: 0 | I80: =SUM(G80+H80) -> 0
A81: 4020 | B81: 66. | C81: Federal Revenue directly from Federal Government | D81: 0 | E81: 0 | F81: 0 | G81: 0 | H81: 0 | I81: =SUM(G81+H81) -> 0
A82: 4951 | B82: 67. | C82: Services Provided within BOCES: Federal Level | D82: 0 | E82: 0 | F82: 0 | G82: 0 | H82: 0 | I82: =SUM(G82+H82) -> 0
A83: 4952 | B83: 68. | C83: Services Provided other Colorado Districts or BOCES: Federal Level | D83: 0 | E83: 0 | F83: 0 | G83: 0 | H83: 0 | I83: =SUM(G83+H83) -> 0
A84: 4954 | B84: 69. | C84: Services Provided Charter Schools: Federal Level | D84: 0 | E84: 0 | F84: 0 | G84: 0 | H84: 0 | I84: =SUM(G84+H84) -> 0
A85: 4959 | B85: 70. | C85: Services Provided Other Units: Federal Level | D85: 0 | E85: 0 | F85: 0 | G85: 0 | H85: 0 | I85: =SUM(G85+H85) -> 0
B86: 71. | C86: Impact Aid | D86: 0 | E86: 0 | F86: 0 | G86: 0 | H86: 0 | I86: =SUM(G86+H86) -> 0
B87: 72. | C87: Vocational Education | D87: 0 | E87: 0 | F87: 0 | G87: 0 | H87: 0 | I87: =SUM(G87+H87) -> 0
B88: 73. | C88: Handicapped Education | D88: 0 | E88: 0 | F88: 0 | G88: 0 | H88: 0 | I88: =SUM(G88+H88) -> 0
B89: 74. | C89: All Other Federal Revenue Codes | D89: 0 | E89: 0 | F89: 0 | G89: 0 | H89: 0 | I89: =SUM(G89+H89) -> 0
B91: 75. | C91: TOTAL REVENUE FROM FEDERAL SOURCES (Sum of lines 64-74) | D91: =SUM(D78:D89) -> 0 | E91: =SUM(E78:E89) -> 0 | F91: =SUM(F78:F89) -> 0 | G91: =SUM(G78:G89) -> 0 | H91: =SUM(H78:H89) -> 0 | I91: =SUM(I78:I89) -> 0
C93: REVENUE FROM OTHER SOURCES (See NOTE-1 below)
A94: 52XX | B94: 76. | C94: Transfer From(+)/To(-)________________Fund(s) (Net to zero across all funds)* | D94: 0 | E94: 0 | F94: 0 | G94: 0 | H94: 0 | I94: =SUM(G94+H94) -> 0
A95: 5400 | B95: 77. | C95: Capital Leases | D95: 0 | E95: 0 | F95: 0 | G95: 0 | H95: 0 | I95: =SUM(G95+H95) -> 0
A96: 5500 | B96: 78. | C96: Certificates of Participation | D96: 0 | E96: 0 | F96: 0 | G96: 0 | H96: 0 | I96: =SUM(G96+H96) -> 0
A97: 5900 | B97: 79. | C97: Other Sources | D97: 0 | E97: 0 | F97: 0 | G97: 0 | H97: 0 | I97: =SUM(G97+H97) -> 0
B98: 80. | C98: TOTAL REVENUE FROM OTHER SOURCES (Sum of lines 76-80) | D98: =SUM(D94:D97) -> 0 | E98: =SUM(E94:E97) -> 0 | F98: =SUM(F94:F97) -> 0 | G98: =SUM(G94:G97) -> 0 | H98: =SUM(H94:H97) -> 0 | I98: =SUM(I94:I97) -> 0
B100: 81. | C100: TOTAL GENERAL FUND REVENUE FOR ALL SOURCES (Sum of lines 39,40,63,75,80) | D100: =SUM(D45+D48+D75+D91+D98) -> 0 | E100: =SUM(E45+E48+E75+E91+E98) -> 0 | F100: =SUM(F45+F48+F75+F91+F98) -> 0 | G100: =SUM(G45+G48+G75+G91+G98) -> 0 | H100: =SUM(H45+H48+H75+H91+H98) -> 0 | I100: =SUM(I45+I48+I75+I91+I98) -> 0
B102: 82 | C102: TOTAL GENERAL FUND REVENUE INCLUDING BEGINNING FUND BALANCE (Sum of line 81 plus BFB) | D102: =D100+D5 -> 0 | E102: =E100+E5 -> 0 | F102: =F100+F5 -> 0 | G102: =G100+G5 -> 0 | H102: =H100+H5 -> 0 | I102: =I100+I5 -> 0
C103: Input the next three lines as a positive number (See NOTE-2 below)
A104: 56XX | B104: 83 | C104: Allocation to Capital Reserve or Insurance Reserve (Funds 21, 18, 43) | D104: 0 | E104: 0 | F104: 0 | G104: 0 | H104: 0 | I104: =SUM(G104+H104) -> 0
A105: 5711 | B105: 84 | C105: Allocation to Charter School (fund 11) | D105: 0 | E105: 0 | F105: 0 | G105: 0 | H105: 0 | I105: =SUM(G105+H105) -> 0
A106: 5819 | B106: 85 | C106: Allocation to CPP Fund (fund 19) | D106: 0 | E106: 0 | F106: 0 | G106: 0 | H106: 0 | I106: =SUM(G106+H106) -> 0
B108: 86 | C108: TOTAL ALLOCATIONS (Sum of lines 83-85) | D108: =SUM(D104:D106) -> 0 | E108: =SUM(E104:E106) -> 0 | F108: =SUM(F104:F106) -> 0 | G108: =SUM(G104:G106) -> 0 | H108: =SUM(H104:H106) -> 0 | I108: =SUM(I104:I106) -> 0
B110: 87 | C110: NET REVENUE (Line 82 minus line 86) | D110: =D102-D108 -> 0 | E110: =E102-E108 -> 0 | F110: =F102-F108 -> 0 | G110: =G102-G108 -> 0 | H110: =H102-H108 -> 0 | I110: =I102-I108 -> 0
A112: NOTE-1: | C112: If you treat Transfers Out as an expenditure - report such amounts here:
A113: 52XX | B113: 76a. | C113: Transfer To________________Fund(s) (input as a positive number on this line) | D113: 0 | E113: 0 | F113: 0 | G113: 0 | H113: 0 | I113: =SUM(G113+H113) -> 0
A115: NOTE-2: | C115: If you treat Allocations Out as an expenditure - report such amounts here:
C116: Also input these amounts as a positive number here
A117: 56XX | B117: 83a. | C117: Allocation to Capital Reserve or Insurance Reserve (Funds 21, 18, 43) | D117: 0 | E117: 0 | F117: 0 | G117: 0 | H117: 0 | I117: =SUM(G117+H117) -> 0
A118: 5711 | B118: 84a. | C118: Allocation to Charter School (fund 11) | D118: 0 | E118: 0 | F118: 0 | G118: 0 | H118: 0 | I118: =SUM(G118+H118) -> 0
A119: 5819 | B119: 85a. | C119: Allocation to CPP Fund (fund 19) | D119: 0 | E119: 0 | F119: 0 | G119: 0 | H119: 0 | I119: =SUM(G119+H119) -> 0
B121: The above four lines will be linked for inclusion in the "TOTAL OTHER USES" line on the GenFund Exp2 page.
A123: * | B123: Unless Transfers Out are recognized as an expenditure per above treatment.

Sheet GenFundExp
A1: School District | C1: =+'Page 1 - FY2013-14'!B5 -> 0 | D1: District Code | E1: =+'Page 1 - FY2013-14'!F7 -> 0 | G1: * Round to Nearest Dollar *
A2: Fund 10: GENERAL FUND EXPENDITURES
D4: Prior Year Actual - Audited FY11-12 | E4: Current Fiscal Year - Budgeted FY12-13 | F4: Current Fiscal Year - Projected FY12-13 | G4: Original Ensuing Fiscal Year - Budget FY13-14 | H4: Adjustments Ensuing Fiscal Year - Budget FY13-14 | I4: Revised Ensuing Fiscal Year - Budget FY13-14
H5: Record Inceases to revenue are positive amounts and Decreases as negatives | I5: Figures (Totals) which will appear on Budget Form to Submit to CDE
A8: INSTRUCTION PROGRAM CODES
B9: Object Codes
A10: 0010 - General Elementary Education
B11: 0100 | C11: Salaries - from staff details tab | D11: 0 | E11: 0 | F11: 0 | G11: {=SUM(IF(CertFund&CertProg&CertObj=RIGHT(LEFT($A$2,7),2)&LEFT(A10,4)&B11,CertSalary))} -> 0 | H11: 0 | I11: =SUM(G11+H11) -> 0
B12: 0100 | C12: Salaries - additional items | D12: 0 | E12: 0 | F12: 0 | G12: 0 | H12: 0 | I12: =SUM(G12+H12) -> 0
B13: 0200 | C13: Employee Benefits - staff details tab | D13: 0 | E13: 0 | F13: 0 | G13: {=SUM(IF(CertFund&CertProg&CertObj=RIGHT(LEFT($A$2,7),2)&LEFT(A10,4)&B11,CertBen))} -> 0 | H13: 0 | I13: =SUM(G13+H13) -> 0
B14: 0200 | C14: Employee Benefits - addl items | D14: 0 | E14: 0 | F14: 0 | G14: 0 | H14: 0 | I14: =SUM(G14+H14) -> 0
B15: 0300 | C15: Purchased Professional & Technical Services | D15: 0 | E15: 0 | F15: 0 | G15: 0 | H15: 0 | I15: =SUM(G15+H15) -> 0
B16: 0400 | C16: Purchased Property Services | D16: 0 | E16: 0 | F16: 0 | G16: 0 | H16: 0 | I16: =SUM(G16+H16) -> 0
B17: 0430 | C17: Repairs & Maintenance Services | D17: 0 | E17: 0 | F17: 0 | G17: 0 | H17: 0 | I17: =SUM(G17+H17) -> 0
B18: 0442 | C18: Rental of Equipment | D18: 0 | E18: 0 | F18: 0 | G18: 0 | H18: 0 | I18: =SUM(G18+H18) -> 0
B19: 0500 | C19: Other Purchased Services | D19: 0 | E19: 0 | F19: 0 | G19: 0 | H19: 0 | I19: =SUM(G19+H19) -> 0
B20: 0513 | C20: Contracted Field Trips | D20: 0 | E20: 0 | F20: 0 | G20: 0 | H20: 0 | I20: =SUM(G20+H20) -> 0
B21: 0519 | C21: Other Purchased Student Transportation | D21: 0 | E21: 0 | F21: 0 | G21: 0 | H21: 0 | I21: =SUM(G21+H21) -> 0
B22: 0561 | C22: Tuition Paid Within the BOCES or AU | D22: 0 | E22: 0 | F22: 0 | G22: 0 | H22: 0 | I22: =SUM(G22+H22) -> 0
B23: 0562 | C23: Tuition Paid to Other Colorado Districts, BOCES or AU | D23: 0 | E23: 0 | F23: 0 | G23: 0 | H23: 0 | I23: =SUM(G23+H23) -> 0
B24: 0563 | C24: Tuition to School Districts Outside The State | D24: 0 | E24: 0 | F24: 0 | G24: 0 | H24: 0 | I24: =SUM(G24+H24) -> 0
B25: 0564 | C25: Tuition To Private Sources | D25: 0 | E25: 0 | F25: 0 | G25: 0 | H25: 0 | I25: =SUM(G25+H25) -> 0
... B43: 0851 | C43: Transportation/Field Trips | D43: 0 | E43: 0 | F43: 0 | G43: 0 | H43: 0 | I43: =SUM(G43+H43) -> 0
C44: TOTAL GENERAL ELEMENTARY EDUCATION | D44: =SUM(D11:D43) -> 0 | E44: =SUM(E11:E43) -> 0 | F44: =SUM(F11:F43) -> 0 | G44: =SUM(G11:G43) -> 0 | H44: =SUM(H11:H43) -> 0 | I44: =SUM(G44+H44) -> 0
A46: 0020 - General Middle/Jr. High School Education
B47: 0100 | C47: Salaries - from staff details tab | D47: 0 | E47: 0 | F47: 0 | G47: {=SUM(IF(CertFund&CertProg&CertObj=RIGHT(LEFT($A$2,7),2)&LEFT(A46,4)&B47,CertSalary))} -> 0 | H47: 0 | I47: =SUM(G47+H47) -> 0
B48: 0100 | C48: Salaries - additional items | D48: 0 | E48: 0 | F48: 0 | G48: 0 | H48: 0 | I48: =SUM(G48+H48) -> 0
B49: 0200 | C49: Employee Benefits - staff details tab | D49: 0 | E49: 0 | F49: 0 | G49: {=SUM(IF(CertFund&CertProg&CertObj=RIGHT(LEFT($A$2,7),2)&LEFT(A46,4)&B47,CertBen))} -> 0 | H49: 0 | I49: =SUM(G49+H49) -> 0
B50: 0200 | C50: Employee Benefits - addl items | D50: 0 | E50: 0 | F50: 0 | G50: 0 | H50: 0 | I50: =SUM(G50+H50) -> 0
B51: 0300 | C51: Purchased Professional & Technical Services | D51: 0 | E51: 0 | F51: 0 | G51: 0 | H51: 0 | I51: =SUM(G51+H51) -> 0
B52: 0400 | C52: Purchased Property Services | D52: 0 | E52: 0 | F52: 0 | G52: 0 | H52: 0 | I52: =SUM(G52+H52) -> 0
B53: 0430 | C53: Repairs & Maintenance Services | D53: 0 | E53: 0 | F53: 0 | G53: 0 | H53: 0 | I53: =SUM(G53+H53) -> 0
B54: 0442 | C54: Rental of Equipment | D54: 0 | E54: 0 | F54: 0 | G54: 0 | H54: 0 | I54: =SUM(G54+H54) -> 0
B55: 0500 | C55: Other Purchased Services | D55: 0 | E55: 0 | F55: 0 | G55: 0 | H55: 0 | I55: =SUM(G55+H55) -> 0
B56: 0513 | C56: Contracted Field Trips | D56: 0 | E56: 0 | F56: 0 | G56: 0 | H56: 0 | I56: =SUM(G56+H56) -> 0
B57: 0519 | C57: Other Purchased Student Transportation | D57: 0 | E57: 0 | F57: 0 | G57: 0 | H57: 0 | I57: =SUM(G57+H57) -> 0
B58: 0561 | C58: Tuition Paid Within the BOCES or AU | D58: 0 | E58: 0 | F58: 0 | G58: 0 | H58: 0 | I58: =SUM(G58+H58) -> 0
B59: 0562 | C59: Tuition Paid to Other Colorado Districts, BOCES or AU | D59: 0 | E59: 0 | F59: 0 | G59: 0 | H59: 0 | I59: =SUM(G59+H59) -> 0
B60: 0563 | C60: Tuition to School Districts Outside The State | D60: 0 | E60: 0 | F60: 0 | G60: 0 | H60: 0 | I60: =SUM(G60+H60) -> 0
B61: 0564 | C61: Tuition To Private Sources | D61: 0 | E61: 0 | F61: 0 | G61: 0 | H61: 0 | I61: =SUM(G61+H61) -> 0
... B79: 0851 | C79: Transportation/Field Trips | D79: 0 | E79: 0 | F79: 0 | G79: 0 | H79: 0 | I79: =SUM(G79+H79) -> 0
C80: TOTAL GENERAL MIDDLE/JR.HIGH SCHOOL EDUCATION | D80: =SUM(D47:D79) -> 0 | E80: =SUM(E47:E79) -> 0 | F80: =SUM(F47:F79) -> 0 | G80: =SUM(G47:G79) -> 0 | H80: =SUM(H47:H79) -> 0 | I80: =SUM(G80+H80) -> 0
A82: 0030 - General High School Education
B83: 0100 | C83: Salaries - from staff details tab | D83: 0 | E83: 0 | F83: 0 | G83: {=SUM(IF(CertFund&CertProg&CertObj=RIGHT(LEFT($A$2,7),2)&LEFT(A82,4)&B83,CertSalary))} -> 0 | H83: 0 | I83: =SUM(G83+H83) -> 0
B84: 0100 | C84: Salaries - additional items | D84: 0 | E84: 0 | F84: 0 | G84: 0 | H84: 0 | I84: =SUM(G84+H84) -> 0
B85: 0200 | C85: Employee Benefits - staff details tab | D85: 0 | E85: 0 | F85: 0 | G85: {=SUM(IF(CertFund&CertProg&CertObj=RIGHT(LEFT($A$2,7),2)&LEFT(A82,4)&B83,CertBen))} -> 0 | H85: 0 | I85: =SUM(G85+H85) -> 0
B86: 0200 | C86: Employee Benefits - addl items | D86: 0 | E86: 0 | F86: 0 | G86: 0 | H86: 0 | I86: =SUM(G86+H86) -> 0
B87: 0300 | C87: Purchased Professional & Technical Services | D87: 0 | E87: 0 | F87: 0 | G87: 0 | H87: 0 | I87: =SUM(G87+H87) -> 0
B88: 0400 | C88: Purchased Property Services | D88: 0 | E88: 0 | F88: 0 | G88: 0 | H88: 0 | I88: =SUM(G88+H88) -> 0
B89: 0430 | C89: Repairs & Maintenance Services | D89: 0 | E89: 0 | F89: 0 | G89: 0 | H89: 0 | I89: =SUM(G89+H89) -> 0
B90: 0442 | C90: Rental of Equipment | D90: 0 | E90: 0 | F90: 0 | G90: 0 | H90: 0 | I90: =SUM(G90+H90) -> 0
B91: 0500 | C91: Other Purchased Services | D91: 0 | E91: 0 | F91: 0 | G91: 0 | H91: 0 | I91: =SUM(G91+H91) -> 0
B92: 0513 | C92: Contracted Field Trips | D92: 0 | E92: 0 | F92: 0 | G92: 0 | H92: 0 | I92: =SUM(G92+H92) -> 0
B93: 0519 | C93: Other Purchased Student Transportation | D93: 0 | E93: 0 | F93: 0 | G93: 0 | H93: 0 | I93: =SUM(G93+H93) -> 0
B94: 0561 | C94: Tuition Paid Within the BOCES or AU | D94: 0 | E94: 0 | F94: 0 | G94: 0 | H94: 0 | I94: =SUM(G94+H94) -> 0
B95: 0562 | C95: Tuition Paid to Other Colorado Districts, BOCES or AU | D95: 0 | E95: 0 | F95: 0 | G95: 0 | H95: 0 | I95: =SUM(G95+H95) -> 0
B96: 0563 | C96: Tuition to School Districts Outside The State | D96: 0 | E96: 0 | F96: 0 | G96: 0 | H96: 0 | I96: =SUM(G96+H96) -> 0
B97: 0564 | C97: Tuition To Private Sources | D97: 0 | E97: 0 | F97: 0 | G97: 0 | H97: 0 | I97: =SUM(G97+H97) -> 0
... B115: 0851 | C115: Transportation/Field Trips | D115: 0 | E115: 0 | F115: 0 | G115: 0 | H115: 0 | I115: =SUM(G115+H115) -> 0
C116: TOTAL GENERAL HIGH SCHOOL EDUCATION | D116: =SUM(D83:D115) -> 0 | E116: =SUM(E83:E115) -> 0 | F116: =SUM(F83:F115) -> 0 | G116: =SUM(G83:G115) -> 0 | H116: =SUM(H83:H115) -> 0 | I116: =SUM(G116+H116) -> 0
A118: 0040 - General Pre-School Education
B119: 0100 | C119: Salaries - from staff details tab | D119: 0 | E119: 0 | F119: 0 | G119: {=SUM(IF(CertFund&CertProg&CertObj=RIGHT(LEFT($A$2,7),2)&LEFT(A118,4)&B119,CertSalary))} -> 0 | H119: 0 | I119: =SUM(G119+H119) -> 0
B120: 0100 | C120: Salaries - additional items | D120: 0 | E120: 0 | F120: 0 | G120: 0 | H120: 0 | I120: =SUM(G120+H120) -> 0
B121: 0200 | C121: Employee Benefits - staff details tab | D121: 0 | E121: 0 | F121: 0 | G121: {=SUM(IF(CertFund&CertProg&CertObj=RIGHT(LEFT($A$2,7),2)&LEFT(A118,4)&B119,CertBen))} -> 0 | H121: 0 | I121: =SUM(G121+H121) -> 0
B122: 0200 | C122: Employee Benefits - addl items | D122: 0 | E122: 0 | F122: 0 | G122: 0 | H122: 0 | I122: =SUM(G122+H122) -> 0
B123: 0300 | C123: Purchased Professional & Technical Services | D123: 0 | E123: 0 | F123: 0 | G123: 0 | H123: 0 | I123: =SUM(G123+H123) -> 0
B124: 0400 | C124: Purchased Property Services | D124: 0 | E124: 0 | F124: 0 | G124: 0 | H124: 0 | I124: =SUM(G124+H124) -> 0
B125: 0430 | C125: Repairs & Maintenance Services | D125: 0 | E125: 0 | F125: 0 | G125: 0 | H125: 0 | I125: =SUM(G125+H125) -> 0
B126: 0442 | C126: Rental of Equipment | D126: 0 | E126: 0 | F126: 0 | G126: 0 | H126: 0 | I126: =SUM(G126+H126) -> 0
B127: 0500 | C127: Other Purchased Services | D127: 0 | E127: 0 | F127: 0 | G127: 0 | H127: 0 | I127: =SUM(G127+H127) -> 0
B128: 0513 | C128: Contracted Field Trips | D128: 0 | E128: 0 | F128: 0 | G128: 0 | H128: 0 | I128: =SUM(G128+H128) -> 0
B129: 0519 | C129: Other Purchased Student Transportation | D129: 0 | E129: 0 | F129: 0 | G129: 0 | H129: 0 | I129: =SUM(G129+H129) -> 0
B130: 0561 | C130: Tuition Paid Within the BOCES or AU | D130: 0 | E130: 0 | F130: 0 | G130: 0 | H130: 0 | I130: =SUM(G130+H130) -> 0
B131: 0562 | C131: Tuition Paid to Other Colorado Districts, BOCES or AU | D131: 0 | E131: 0 | F131: 0 | G131: 0 | H131: 0 | I131: =SUM(G131+H131) -> 0
B132: 0563 | C132: Tuition to School Districts Outside The State | D132: 0 | E132: 0 | F132: 0 | G132: 0 | H132: 0 | I132: =SUM(G132+H132) -> 0
B133: 0564 | C133: Tuition To Private Sources | D133: 0 | E133: 0 | F133: 0 | G133: 0 | H133: 0 | I133: =SUM(G133+H133) -> 0
... B151: 0851 | C151: Transportation/Field Trips | D151: 0 | E151: 0 | F151: 0 | G151: 0 | H151: 0 | I151: =SUM(G151+H151) -> 0
C152: TOTAL GENERAL PRE-SCHOOL EDUCATION | D152: =SUM(D119:D151) -> 0 | E152: =SUM(E119:E151) -> 0 | F152: =SUM(F119:F151) -> 0 | G152: =SUM(G119:G151) -> 0 | H152: =SUM(H119:H151) -> 0 | I152: =SUM(G152+H152) -> 0
A154: 0050 - General Post-Secondary Education
B155: 0100 | C155: Salaries - from staff details tab | D155: 0 | E155: 0 | F155: 0 | G155: {=SUM(IF(CertFund&CertProg&CertObj=RIGHT(LEFT($A$2,7),2)&LEFT(A154,4)&B155,CertSalary))} -> 0 | H155: 0 | I155: =SUM(G155+H155) -> 0
B156: 0100 | C156: Salaries - additional items | D156: 0 | E156: 0 | F156: 0 | G156: 0 | H156: 0 | I156: =SUM(G156+H156) -> 0
B157: 0200 | C157: Employee Benefits - staff details tab | D157: 0 | E157: 0 | F157: 0 | G157: {=SUM(IF(CertFund&CertProg&CertObj=RIGHT(LEFT($A$2,7),2)&LEFT(A154,4)&B155,CertBen))} -> 0 | H157: 0 | I157: =SUM(G157+H157) -> 0
B158: 0200 | C158: Employee Benefits - addl items | D158: 0 | E158: 0 | F158: 0 | G158: 0 | H158: 0 | I158: =SUM(G158+H158) -> 0
B159: 0300 | C159: Purchased Professional & Technical Services | D159: 0 | E159: 0 | F159: 0 | G159: 0 | H159: 0 | I159: =SUM(G159+H159) -> 0
B160: 0400 | C160: Purchased Property Services | D160: 0 | E160: 0 | F160: 0 | G160: 0 | H160: 0 | I160: =SUM(G160+H160) -> 0
B161: 0430 | C161: Repairs & Maintenance Services | D161: 0 | E161: 0 | F161: 0 | G161: 0 | H161: 0 | I161: =SUM(G161+H161) -> 0
B162: 0442 | C162: Rental of Equipment | D162: 0 | E162: 0 | F162: 0 | G162: 0 | H162: 0 | I162: =SUM(G162+H162) -> 0
B163: 0500 | C163: Other Purchased Services | D163: 0 | E163: 0 | F163: 0 | G163: 0 | H163: 0 | I163: =SUM(G163+H163) -> 0
B164: 0513 | C164: Contracted Field Trips | D164: 0 | E164: 0 | F164: 0 | G164: 0 | H164: 0 | I164: =SUM(G164+H164) -> 0
B165: 0519 | C165: Other Purchased Student Transportation | D165: 0 | E165: 0 | F165: 0 | G165: 0 | H165: 0 | I165: =SUM(G165+H165) -> 0
B166: 0561 | C166: Tuition Paid Within the BOCES or AU | D166: 0 | E166: 0 | F166: 0 | G166: 0 | H166: 0 | I166: =SUM(G166+H166) -> 0
B167: 0562 | C167: Tuition Paid to Other Colorado Districts, BOCES or AU | D167: 0 | E167: 0 | F167: 0 | G167: 0 | H167: 0 | I167: =SUM(G167+H167) -> 0
B168: 0563 | C168: Tuition to School Districts Outside The State | D168: 0 | E168: 0 | F168: 0 | G168: 0 | H168: 0 | I168: =SUM(G168+H168) -> 0
B169: 0564 | C169: Tuition To Private Sources | D169: 0 | E169: 0 | F169: 0 | G169: 0 | H169: 0 | I169: =SUM(G169+H169) -> 0
... B187: 0851 | C187: Transportation/Field Trips | D187: 0 | E187: 0 | F187: 0 | G187: 0 | H187: 0 | I187: =SUM(G187+H187) -> 0
C188: TOTAL GENERAL POST-SECONDARY EDUCATION | D188: =SUM(D155:D187) -> 0 | E188: =SUM(E155:E187) -> 0 | F188: =SUM(F155:F187) -> 0 | G188: =SUM(G155:G187) -> 0 | H188: =SUM(H155:H187) -> 0 | I188: =SUM(G188+H188) -> 0
A190: 0051 - Programs for Adult/Continuing
B191: 0100 | C191: Salaries - from staff details tab | D191: 0 | E191: 0 | F191: 0 | G191: {=SUM(IF(CertFund&CertProg&CertObj=RIGHT(LEFT($A$2,7),2)&LEFT(A190,4)&B191,CertSalary))} -> 0 | H191: 0 | I191: =SUM(G191+H191) -> 0
B192: 0100 | C192: Salaries - additional items | D192: 0 | E192: 0 | F192: 0 | G192: 0 | H192: 0 | I192: =SUM(G192+H192) -> 0
B193: 0200 | C193: Employee Benefits - staff details tab | D193: 0 | E193: 0 | F193: 0 | G193: {=SUM(IF(CertFund&CertProg&CertObj=RIGHT(LEFT($A$2,7),2)&LEFT(A190,4)&B191,CertBen))} -> 0 | H193: 0 | I193: =SUM(G193+H193) -> 0
...

Sheet GenFundExp2
A1: School District | C1: =+'Page 1 - FY2013-14'!B5 -> 0 | D1: District Code | E1: =+'Page 1 - FY2013-14'!F7 -> 0 | G1: * Round to Nearest Dollar *
A2: Fund 10: GENERAL FUND EXPENDITURES
D4: Prior Year Actual - Audited FY11-12 | E4: Current Fiscal Year - Budgeted FY12-13 | F4: Current Fiscal Year - Projected FY12-13 | G4: Original Ensuing Fiscal Year - Budget FY13-14 | H4: Adjustments Ensuing Fiscal Year - Budget FY13-14 | I4: Revised Ensuing Fiscal Year - Budget FY13-14
H5: Record Inceases to revenue are positive amounts and Decreases as negatives | I5: Figures (Totals) which will appear on Budget Form to Submit to CDE
A7: SUPPORT SERVICES PROGRAM CODES
B8: Object Codes
A9: 2100 - Students
B10: 0100 | C10: Salaries - from staff details tab | D10: 0 | E10: 0 | F10: 0 | G10: {=SUM(IF(CertFund&CertProg&CertObj=RIGHT(LEFT($A$2,7),2)&LEFT(A9,4)&B10,CertSalary))} -> 0 | H10: 0 | I10: =SUM(G10+H10) -> 0
B11: 0100 | C11: Salaries - additional items | D11: 0 | E11: 0 | F11: 0 | G11: 0 | H11: 0 | I11: =SUM(G11+H11) -> 0
B12: 0200 | C12: Employee Benefits - staff details tab | D12: 0 | E12: 0 | F12: 0 | G12: {=SUM(IF(CertFund&CertProg&CertObj=RIGHT(LEFT($A$2,7),2)&LEFT(A9,4)&B10,CertBen))} -> 0 | H12: 0 | I12: =SUM(G12+H12) -> 0
B13: 0200 | C13: Employee Benefits - addl items | D13: 0 | E13: 0 | F13: 0 | G13: 0 | H13: 0 | I13: =SUM(G13+H13) -> 0
B14: 0300 | C14: Purchased Professional & Technical Services | D14: 0 | E14: 0 | F14: 0 | G14: 0 | H14: 0 | I14: =SUM(G14+H14) -> 0
B15: 0400 | C15: Purchased Property Services | D15: 0 | E15: 0 | F15: 0 | G15: 0 | H15: 0 | I15: =SUM(G15+H15) -> 0
B16: 0430 | C16: Repairs & Maintenance Services | D16: 0 | E16: 0 | F16: 0 | G16: 0 | H16: 0 | I16: =SUM(G16+H16) -> 0
B17: 0442 | C17: Rental of Equipment | D17: 0 | E17: 0 | F17: 0 | G17: 0 | H17: 0 | I17: =SUM(G17+H17) -> 0
B18: 0500 | C18: Other Purchased Services | D18: 0 | E18: 0 | F18: 0 | G18: 0 | H18: 0 | I18: =SUM(G18+H18) -> 0
B19: 0511 | C19: Student Transportation Purchased Within the BOCES or AU | D19: 0 | E19: 0 | F19: 0 | G19: 0 | H19: 0 | I19: =SUM(G19+H19) -> 0
B20: 0512 | C20: Student Transportation Purchased from Other Colorado Districts, BOCES or AU | D20: 0 | E20: 0 | F20: 0 | G20: 0 | H20: 0 | I20: =SUM(G20+H20) -> 0
B21: 0513 | C21: Contracted Field Trips | D21: 0 | E21: 0 | F21: 0 | G21: 0 | H21: 0 | I21: =SUM(G21+H21) -> 0
B22: 0514 | C22: Student Transportation Purchased from Parents | D22: 0 | E22: 0 | F22: 0 | G22: 0 | H22: 0 | I22: =SUM(G22+H22) -> 0
B23: 0515 | C23: Student Transportation Purchased from Contractors | D23: 0 | E23: 0 | F23: 0 | G23: 0 | H23: 0 | I23: =SUM(G23+H23) -> 0
B24: 0517 | C24: Student Transportation Purchased from School District Outside the State | D24: 0 | E24: 0 | F24: 0 | G24: 0 | H24: 0 | I24: =SUM(G24+H24) -> 0
... B43: 0869 | C43: Indirect Costs | D43: 0 | E43: 0 | F43: 0 | G43: 0 | H43: 0 | I43: =SUM(G43+H43) -> 0
C44: TOTAL STUDENT SUPPORT | D44: =SUM(D10:D43) -> 0 | E44: =SUM(E10:E43) -> 0 | F44: =SUM(F10:F43) -> 0 | G44: =SUM(G10:G43) -> 0 | H44: =SUM(H10:H43) -> 0 | I44: =SUM(G44+H44) -> 0
A46: 2200 - Instructional Staff
B47: 0100 | C47: Salaries - from staff details tab | D47: 0 | E47: 0 | F47: 0 | G47: {=SUM(IF(CertFund&CertProg&CertObj=RIGHT(LEFT($A$2,7),2)&LEFT(A46,4)&B47,CertSalary))} -> 0 | H47: 0 | I47: =SUM(G47+H47) -> 0
B48: 0100 | C48: Salaries - additional items | D48: 0 | E48: 0 | F48: 0 | G48: 0 | H48: 0 | I48: =SUM(G48+H48) -> 0
B49: 0200 | C49: Employee Benefits - staff details tab | D49: 0 | E49: 0 | F49: 0 | G49: {=SUM(IF(CertFund&CertProg&CertObj=RIGHT(LEFT($A$2,7),2)&LEFT(A46,4)&B47,CertBen))} -> 0 | H49: 0 | I49: =SUM(G49+H49) -> 0
B50: 0200 | C50: Employee Benefits - addl items | D50: 0 | E50: 0 | F50: 0 | G50: 0 | H50: 0 | I50: =SUM(G50+H50) -> 0
B51: 0300 | C51: Purchased Professional & Technical Services | D51: 0 | E51: 0 | F51: 0 | G51: 0 | H51: 0 | I51: =SUM(G51+H51) -> 0
B52: 0400 | C52: Purchased Property Services | D52: 0 | E52: 0 | F52: 0 | G52: 0 | H52: 0 | I52: =SUM(G52+H52) -> 0
B53: 0430 | C53: Repairs & Maintenance Services | D53: 0 | E53: 0 | F53: 0 | G53: 0 | H53: 0 | I53: =SUM(G53+H53) -> 0
B54: 0442 | C54: Rental of Equipment | D54: 0 | E54: 0 | F54: 0 | G54: 0 | H54: 0 | I54: =SUM(G54+H54) -> 0
B55: 0500 | C55: Other Purchased Services | D55: 0 | E55: 0 | F55: 0 | G55: 0 | H55: 0 | I55: =SUM(G55+H55) -> 0
B56: 0511 | C56: Student Transportation Purchased Within the BOCES or AU | D56: 0 | E56: 0 | F56: 0 | G56: 0 | H56: 0 | I56: =SUM(G56+H56) -> 0
B57: 0512 | C57: Student Transportation Purchased from Other Colorado Districts, BOCES or AU | D57: 0 | E57: 0 | F57: 0 | G57: 0 | H57: 0 | I57: =SUM(G57+H57) -> 0
B58: 0513 | C58: Contracted Field Trips | D58: 0 | E58: 0 | F58: 0 | G58: 0 | H58: 0 | I58: =SUM(G58+H58) -> 0
B59: 0514 | C59: Student Transportation Purchased from Parents | D59: 0 | E59: 0 | F59: 0 | G59: 0 | H59: 0 | I59: =SUM(G59+H59) -> 0
B60: 0515 | C60: Student Transportation Purchased from Contractors | D60: 0 | E60: 0 | F60: 0 | G60: 0 | H60: 0 | I60: =SUM(G60+H60) -> 0
B61: 0517 | C61: Student Transportation Purchased from School District Outside the State | D61: 0 | E61: 0 | F61: 0 | G61: 0 | H61: 0 | I61: =SUM(G61+H61) -> 0
... B80: 0869 | C80: Indirect Costs | D80: 0 | E80: 0 | F80: 0 | G80: 0 | H80: 0 | I80: =SUM(G80+H80) -> 0
C81: TOTAL INSTRUCTIONAL STAFF SUPPORT | D81: =SUM(D47:D80) -> 0 | E81: =SUM(E47:E80) -> 0 | F81: =SUM(F47:F80) -> 0 | G81: =SUM(G47:G80) -> 0 | H81: =SUM(H47:H80) -> 0 | I81: =SUM(G81+H81) -> 0
A83: 2220 - Educational Library Services
B84: 0100 | C84: Salaries - from staff details tab | D84: 0 | E84: 0 | F84: 0 | G84: {=SUM(IF(CertFund&CertProg&CertObj=RIGHT(LEFT($A$2,7),2)&LEFT(A83,4)&B84,CertSalary))} -> 0 | H84: 0 | I84: =SUM(G84+H84) -> 0
B85: 0100 | C85: Salaries - additional items | D85: 0 | E85: 0 | F85: 0 | G85: 0 | H85: 0 | I85: =SUM(G85+H85) -> 0
B86: 0200 | C86: Employee Benefits - staff details tab | D86: 0 | E86: 0 | F86: 0 | G86: {=SUM(IF(CertFund&CertProg&CertObj=RIGHT(LEFT($A$2,7),2)&LEFT(A83,4)&B84,CertBen))} -> 0 | H86: 0 | I86: =SUM(G86+H86) -> 0
B87: 0200 | C87: Employee Benefits - addl items | D87: 0 | E87: 0 | F87: 0 | G87: 0 | H87: 0 | I87: =SUM(G87+H87) -> 0
B88: 0300 | C88: Purchased Professional & Technical Services | D88: 0 | E88: 0 | F88: 0 | G88: 0 | H88: 0 | I88: =SUM(G88+H88) -> 0
B89: 0400 | C89: Purchased Property Services | D89: 0 | E89: 0 | F89: 0 | G89: 0 | H89: 0 | I89: =SUM(G89+H89) -> 0
B90: 0430 | C90: Repairs & Maintenance Services | D90: 0 | E90: 0 | F90: 0 | G90: 0 | H90: 0 | I90: =SUM(G90+H90) -> 0
B91: 0442 | C91: Rental of Equipment | D91: 0 | E91: 0 | F91: 0 | G91: 0 | H91: 0 | I91: =SUM(G91+H91) -> 0
B92: 0500 | C92: Other Purchased Services | D92: 0 | E92: 0 | F92: 0 | G92: 0 | H92: 0 | I92: =SUM(G92+H92) -> 0
B93: 0511 | C93: Student Transportation Purchased Within the BOCES or AU | D93: 0 | E93: 0 | F93: 0 | G93: 0 | H93: 0 | I93: =SUM(G93+H93) -> 0
B94: 0512 | C94: Student Transportation Purchased from Other Colorado Districts, BOCES or AU | D94: 0 | E94: 0 | F94: 0 | G94: 0 | H94: 0 | I94: =SUM(G94+H94) -> 0
B95: 0513 | C95: Contracted Field Trips | D95: 0 | E95: 0 | F95: 0 | G95: 0 | H95: 0 | I95: =SUM(G95+H95) -> 0
B96: 0514 | C96: Student Transportation Purchased from Parents | D96: 0 | E96: 0 | F96: 0 | G96: 0 | H96: 0 | I96: =SUM(G96+H96) -> 0
B97: 0515 | C97: Student Transportation Purchased from Contractors | D97: 0 | E97: 0 | F97: 0 | G97: 0 | H97: 0 | I97: =SUM(G97+H97) -> 0
B98: 0517 | C98: Student Transportation Purchased from School District Outside the State | D98: 0 | E98: 0 | F98: 0 | G98: 0 | H98: 0 | I98: =SUM(G98+H98) -> 0
... B117: 0869 | C117: Indirect Costs | D117: 0 | E117: 0 | F117: 0 | G117: 0 | H117: 0 | I117: =SUM(G117+H117) -> 0
C118: TOTAL EDUCATIONAL LIBRARY SERVICES | D118: =SUM(D84:D117) -> 0 | E118: =SUM(E84:E117) -> 0 | F118: =SUM(F84:F117) -> 0 | G118: =SUM(G84:G117) -> 0 | H118: =SUM(H84:H117) -> 0 | I118: =SUM(G118+H118) -> 0
A120: 2300 - General Administration
B121: 0100 | C121: Salaries - from staff details tab | D121: 0 | E121: 0 | F121: 0 | G121: {=SUM(IF(CertFund&CertProg&CertObj=RIGHT(LEFT($A$2,7),2)&LEFT(A120,4)&B121,CertSalary))} -> 0 | H121: 0 | I121: =SUM(G121+H121) -> 0
B122: 0100 | C122: Salaries - additional items | D122: 0 | E122: 0 | F122: 0 | G122: 0 | H122: 0 | I122: =SUM(G122+H122) -> 0
B123: 0200 | C123: Employee Benefits - staff details tab | D123: 0 | E123: 0 | F123: 0 | G123: {=SUM(IF(CertFund&CertProg&CertObj=RIGHT(LEFT($A$2,7),2)&LEFT(A120,4)&B121,CertBen))} -> 0 | H123: 0 | I123: =SUM(G123+H123) -> 0
B124: 0200 | C124: Employee Benefits - addl items | D124: 0 | E124: 0 | F124: 0 | G124: 0 | H124: 0 | I124: =SUM(G124+H124) -> 0
B125: 0300 | C125: Purchased Professional & Technical Services | D125: 0 | E125: 0 | F125: 0 | G125: 0 | H125: 0 | I125: =SUM(G125+H125) -> 0
B126: 0400 | C126: Purchased Property Services | D126: 0 | E126: 0 | F126: 0 | G126: 0 | H126: 0 | I126: =SUM(G126+H126) -> 0
B127: 0430 | C127: Repairs & Maintenance Services | D127: 0 | E127: 0 | F127: 0 | G127: 0 | H127: 0 | I127: =SUM(G127+H127) -> 0
B128: 0442 | C128: Rental of Equipment | D128: 0 | E128: 0 | F128: 0 | G128: 0 | H128: 0 | I128: =SUM(G128+H128) -> 0
B129: 0500 | C129: Other Purchased Services | D129: 0 | E129: 0 | F129: 0 | G129: 0 | H129: 0 | I129: =SUM(G129+H129) -> 0
B130: 0569 | C130: Tuition - Other | D130: 0 | E130: 0 | F130: 0 | G130: 0 | H130: 0 | I130: =SUM(G130+H130) -> 0
B131: 0580 | C131: Travel, Registration, and Entrance | D131: 0 | E131: 0 | F131: 0 | G131: 0 | H131: 0 | I131: =SUM(G131+H131) -> 0
B132: 0591 | C132: Services Purchased Within the BOCES or AU | D132: 0 | E132: 0 | F132: 0 | G132: 0 | H132: 0 | I132: =SUM(G132+H132) -> 0
B133: 0592 | C133: Services Purchased from Other Colorado Districts, BOCES or AU | D133: 0 | E133: 0 | F133: 0 | G133: 0 | H133: 0 | I133: =SUM(G133+H133) -> 0
B134: 0593 | C134: Services Purchased from School Districts Outside the State | D134: 0 | E134: 0 | F134: 0 | G134: 0 | H134: 0 | I134: =SUM(G134+H134) -> 0
B135: 0594 | C135: Purchased Services from Districts by Charter Schools | D135: 0 | E135: 0 | F135: 0 | G135: 0 | H135: 0 | I135: =SUM(G135+H135) -> 0
... B148: 0869 | C148: Indirect Costs | D148: 0 | E148: 0 | F148: 0 | G148: 0 | H148: 0 | I148: =SUM(G148+H148) -> 0
C149: TOTAL GENERAL ADMINISTRATION SUPPORT | D149: =SUM(D121:D148) -> 0 | E149: =SUM(E121:E148) -> 0 | F149: =SUM(F121:F148) -> 0 | G149: =SUM(G121:G148) -> 0 | H149: =SUM(H121:H148) -> 0 | I149: =SUM(G149+H149) -> 0
A151: 2400 - School Administration
B152: 0100 | C152: Salaries - from staff details tab | D152: 0 | E152: 0 | F152: 0 | G152: {=SUM(IF(CertFund&CertProg&CertObj=RIGHT(LEFT($A$2,7),2)&LEFT(A151,4)&B152,CertSalary))} -> 0 | H152: 0 | I152: =SUM(G152+H152) -> 0
B153: 0100 | C153: Salaries - additional items | D153: 0 | E153: 0 | F153: 0 | G153: 0 | H153: 0 | I153: =SUM(G153+H153) -> 0
B154: 0200 | C154: Employee Benefits - staff details tab | D154: 0 | E154: 0 | F154: 0 | G154: {=SUM(IF(CertFund&CertProg&CertObj=RIGHT(LEFT($A$2,7),2)&LEFT(A151,4)&B152,CertBen))} -> 0 | H154: 0 | I154: =SUM(G154+H154) -> 0
B155: 0200 | C155: Employee Benefits - addl items | D155: 0 | E155: 0 | F155: 0 | G155: 0 | H155: 0 | I155: =SUM(G155+H155) -> 0
B156: 0300 | C156: Purchased Professional & Technical Services | D156: 0 | E156: 0 | F156: 0 | G156: 0 | H156: 0 | I156: =SUM(G156+H156) -> 0
B157: 0400 | C157: Purchased Property Services | D157: 0 | E157: 0 | F157: 0 | G157: 0 | H157: 0 | I157: =SUM(G157+H157) -> 0
B158: 0430 | C158: Repairs & Maintenance Services | D158: 0 | E158: 0 | F158: 0 | G158: 0 | H158: 0 | I158: =SUM(G158+H158) -> 0
B159: 0442 | C159: Rental of Equipment | D159: 0 | E159: 0 | F159: 0 | G159: 0 | H159: 0 | I159: =SUM(G159+H159) -> 0
B160: 0500 | C160: Other Purchased Services | D160: 0 | E160: 0 | F160: 0 | G160: 0 | H160: 0 | I160: =SUM(G160+H160) -> 0
B161: 0511 | C161: Student Transportation Purchased Within the BOCES or AU | D161: 0 | E161: 0 | F161: 0 | G161: 0 | H161: 0 | I161: =SUM(G161+H161) -> 0
B162: 0512 | C162: Student Transportation Purchased from Other Colorado Districts, BOCES or AU | D162: 0 | E162: 0 | F162: 0 | G162: 0 | H162: 0 | I162: =SUM(G162+H162) -> 0
B163: 0513 | C163: Contracted Field Trips | D163: 0 | E163: 0 | F163: 0 | G163: 0 | H163: 0 | I163: =SUM(G163+H163) -> 0
B164: 0514 | C164: Student Transportation Purchased from Parents | D164: 0 | E164: 0 | F164: 0 | G164: 0 | H164: 0 | I164: =SUM(G164+H164) -> 0
B165: 0515 | C165: Student Transportation Purchased from Contractors | D165: 0 | E165: 0 | F165: 0 | G165: 0 | H165: 0 | I165: =SUM(G165+H165) -> 0
B166: 0516 | C166: Student Transportation In-service | D166: 0 | E166: 0 | F166: 0 | G166: 0 | H166: 0 | I166: =SUM(G166+H166) -> 0
... B186: 0869 | C186: Indirect Costs | D186: 0 | E186: 0 | F186: 0 | G186: 0 | H186: 0 | I186: =SUM(G186+H186) -> 0
C187: TOTAL SCHOOL ADMINISTRATION SUPPORT | D187: =SUM(D152:D186) -> 0 | E187: =SUM(E152:E186) -> 0 | F187: =SUM(F152:F186) -> 0 | G187: =SUM(G152:G186) -> 0 | H187: =SUM(H152:H186) -> 0 | I187: =SUM(G187+H187) -> 0
A189: 2500 - Business Services
B190: 0100 | C190: Salaries - from staff details tab | D190: 0 | E190: 0 | F190: 0 | G190: {=SUM(IF(CertFund&CertProg&CertObj=RIGHT(LEFT($A$2,7),2)&LEFT(A189,4)&B190,CertSalary))} -> 0 | H190: 0 | I190: =SUM(G190+H190) -> 0
B191: 0100 | C191: Salaries - additional items | D191: 0 | E191: 0 | F191: 0 | G191: 0 | H191: 0 | I191: =SUM(G191+H191) -> 0
B192: 0200 | C192: Employee Benefits - staff details tab | D192: 0 | E192: 0 | F192: 0 | G192: {=SUM(IF(CertFund&CertProg&CertObj=RIGHT(LEFT($A$2,7),2)&LEFT(A189,4)&B190,CertBen))} -> 0 | H192: 0 | I192: =SUM(G192+H192) -> 0
...

Sheet CharterFundRev
A1: School District | C1: =+'Page 1 - FY2013-14'!B5 -> 0 | D1: District Code | E1: =+'Page 1 - FY2013-14'!F7 -> 0 | G1: * Round to Nearest Dollar *
A2: Fund 11: CHARTER FUND REVENUE
D3: Prior Year Actual - Audited FY11-12 | E3: Current Fiscal Year - Budgeted FY12-13 | F3: Current Fiscal Year - Projected FY12-13 | G3: Original Ensuing Fiscal Year - Budget FY13-14 | H3: Adjustments Ensuing Fiscal Year - Budget FY13-14 | I3: Revised Ensuing Fiscal Year - Budget FY13-14
H4: Record Inceases to revenue are positive amounts and Decreases as negatives | I4: Figures (Totals) which will appear on Budget Form to Submit to CDE
A5: Codes | B5: BEGINNING FUND BALANCE | D5: 0 | E5: 0 | F5: 0 | G5: 0 | H5: 0 | I5: =SUM(G5+H5) -> 0
A6: Source | B6: REVENUE FROM LOCAL SOURCES
A7: 1110 | B7: 1. | C7: Current Property Taxes | D7: 0 | E7: 0 | F7: 0 | G7: 0 | H7: 0 | I7: =SUM(G7+H7) -> 0
A8: 1120 | B8: 2. | C8: Specific Ownership Taxes | D8: 0 | E8: 0 | F8: 0 | G8: 0 | H8: 0 | I8: =SUM(G8+H8) -> 0
A9: 1130 | B9: 3. | C9: Sales and Use Taxes | D9: 0 | E9: 0 | F9: 0 | G9: 0 | H9: 0 | I9: =SUM(G9+H9) -> 0
A10: 1140 | B10: 4. | C10: Delinquent Taxes and Penalties and Interest on Taxes | D10: 0 | E10: 0 | F10: 0 | G10: 0 | H10: 0 | I10: =SUM(G10+H10) -> 0
A11: 1190 | B11: 5. | C11: Other Taxes from Local Sources | D11: 0 | E11: 0 | F11: 0 | G11: 0 | H11: 0 | I11: =SUM(G11+H11) -> 0
A12: 1310 | B12: 6. | C12: Tuition from Individuals | D12: 0 | E12: 0 | F12: 0 | G12: 0 | H12: 0 | I12: =SUM(G12+H12) -> 0
A13: 1311 | B13: 7. | C13: Summer School/Interterm/Intercession Fees | D13: 0 | E13: 0 | F13: 0 | G13: 0 | H13: 0 | I13: =SUM(G13+H13) -> 0
A14: 1321 | B14: 8. | C14: Tuition from WITHIN the BOCES (or Administrative Unit(AU)) | D14: 0 | E14: 0 | F14: 0 | G14: 0 | H14: 0 | I14: =SUM(G14+H14) -> 0
A15: 1322 | B15: 9. | C15: Tuition from Other Colorado Districts or BOCES (or AU) | D15: 0 | E15: 0 | F15: 0 | G15: 0 | H15: 0 | I15: =SUM(G15+H15) -> 0
A16: 1323 | B16: 10. | C16: Tuition from Excess Costs | D16: 0 | E16: 0 | F16: 0 | G16: 0 | H16: 0 | I16: =SUM(G16+H16) -> 0
A17: 1324 | B17: 11. | C17: Tuition from CDE for Out-of District Placed Pupils | D17: 0 | E17: 0 | F17: 0 | G17: 0 | H17: 0 | I17: =SUM(G17+H17) -> 0
A18: 1330 | B18: 12. | C18: Tuition from School Districts Outside the State | D18: 0 | E18: 0 | F18: 0 | G18: 0 | H18: 0 | I18: =SUM(G18+H18) -> 0
... A30: 1740 | B30: 24. | C30: Fees | D30: 0 | E30: 0 | F30: 0 | G30: 0 | H30: 0 | I30: =SUM(G30+H30) -> 0
A31: 1800 | B31: 25. | C31: Community Service Activities | D31: 0 | E31: 0 | F31: 0 | G31: 0 | H31: 0 | I31: =SUM(G31+H31) -> 0
A32: 1850 | B32: 26. | C32: Charter School Revenue | D32: 0 | E32: 0 | F32: 0 | G32: 0 | H32: 0 | I32: =SUM(G32+H32) -> 0
A33: 1900 | B33: 28. | C33: Other Revenue from Local Sources | D33: 0 | E33: 0 | F33: 0 | G33: 0 | H33: 0 | I33: =SUM(G33+H33) -> 0
A34: 1910 | B34: 29. | C34: Rentals/Leases | D34: 0 | E34: 0 | F34: 0 | G34: 0 | H34: 0 | I34: =SUM(G34+H34) -> 0
A35: 1920 | B35: 30. | C35: Contributions and Donations for Private Sources | D35: 0 | E35: 0 | F35: 0 | G35: 0 | H35: 0 | I35: =SUM(G35+H35) -> 0
A36: 1930 | B36: 31. | C36: Sale of Fixed Assets | D36: 0 | E36: 0 | F36: 0 | G36: 0 | H36: 0 | I36: =SUM(G36+H36) -> 0
A37: 1940 | B37: 32. | C37: Instructional Materials Fees | D37: 0 | E37: 0 | F37: 0 | G37: 0 | H37: 0 | I37: =SUM(G37+H37) -> 0
A38: 1951 | B38: 33. | C38: Services Provided within BOCES: local | D38: 0 | E38: 0 | F38: 0 | G38: 0 | H38: 0 | I38: =SUM(G38+H38) -> 0
A39: 1952 | B39: 34. | C39: Serivces Provided other Colorado BOCES of Districts: local | D39: 0 | E39: 0 | F39: 0 | G39: 0 | H39: 0 | I39: =SUM(G39+H39) -> 0
A40: 1954 | B40: 35. | C40: Services Provided Charter Schools: local | D40: 0 | E40: 0 | F40: 0 | G40: 0 | H40: 0 | I40: =SUM(G40+H40) -> 0
A41: 1959 | B41: 36. | C41: Services Provided other Units: local | D41: 0 | E41: 0 | F41: 0 | G41: 0 | H41: 0 | I41: =SUM(G41+H41) -> 0
A42: 1960 | B42: 37. | C42: Parking Fees | D42: 0 | E42: 0 | F42: 0 | G42: 0 | H42: 0 | I42: =SUM(G42+H42) -> 0
B43: 38. | C43: All Other Local Revenue Codes | D43: 0 | E43: 0 | F43: 0 | G43: 0 | H43: 0 | I43: =SUM(G43+H43) -> 0
B45: 39. | C45: TOTAL REVENUE FROM LOCAL SOURCES (Sum of lines 1-38) | D45: =SUM(D7:D43) -> 0 | E45: =SUM(E7:E43) -> 0 | F45: =SUM(F7:F43) -> 0 | G45: =SUM(G7:G43) -> 0 | H45: =SUM(H7:H43) -> 0 | I45: =SUM(I7:I43) -> 0
B47: REVENUE FROM INTERMEDIATE (COUNTY) SOURCES
A48: 2000 | B48: 40. | C48: TOTAL REVENUE FROM INTERMEDIATE (COUNTY) SOURCES | D48: 0 | E48: 0 | F48: 0 | G48: 0 | H48: 0 | I48: =SUM(G48+H48) -> 0
B50: REVENUE FROM STATE SOURCES
A51: 3110 | B51: 41. | C51: State Equalization | D51: 0 | E51: 0 | F51: 0 | G51: 0 | H51: 0 | I51: =SUM(G51+H51) -> 0
A52: 3112 | B52: 42. | C52: Capital Construction | D52: 0 | E52: 0 | F52: 0 | G52: 0 | H52: 0 | I52: =SUM(G52+H52) -> 0
A53: 3113 | B53: 43. | C53: Charter School Capital Constrcution | D53: 0 | E53: 0 | F53: 0 | G53: 0 | H53: 0 | I53: =SUM(G53+H53) -> 0
A54: 3114 | B54: 44. | C54: Increasing Enrollment Aid | D54: 0 | E54: 0 | F54: 0 | G54: 0 | H54: 0 | I54: =SUM(G54+H54) -> 0
A55: 3115 | B55: 45. | C55: Tracking On-Line Programs | D55: 0 | E55: 0 | F55: 0 | G55: 0 | H55: 0 | I55: =SUM(G55+H55) -> 0
A56: 3116 | B56: 46. | C56: School Construction and Renovation Project | D56: 0 | E56: 0 | F56: 0 | G56: 0 | H56: 0 | I56: =SUM(G56+H56) -> 0
A57: 3120 | B57: 47. | C57: Vocational Education | D57: 0 | E57: 0 | F57: 0 | G57: 0 | H57: 0 | I57: =SUM(G57+H57) -> 0
A58: 3130 | B58: 48. | C58: Exceptional Children's Education Act (ECEA) | D58: 0 | E58: 0 | F58: 0 | G58: 0 | H58: 0 | I58: =SUM(G58+H58) -> 0
A59: 3140 | B59: 49. | C59: English Language Proficiency Act (ELPA) | D59: 0 | E59: 0 | F59: 0 | G59: 0 | H59: 0 | I59: =SUM(G59+H59) -> 0
A60: 3150 | B60: 50. | C60: Gifted and Talented (ECEA) | D60: 0 | E60: 0 | F60: 0 | G60: 0 | H60: 0 | I60: =SUM(G60+H60) -> 0
A61: 3160 | B61: 51. | C61: Transportation | D61: 0 | E61: 0 | F61: 0 | G61: 0 | H61: 0 | I61: =SUM(G61+H61) -> 0
A62: 3170 | B62: 52. | C62: Small Attendance Center Aid | D62: 0 | E62: 0 | F62: 0 | G62: 0 | H62: 0 | I62: =SUM(G62+H62) -> 0
... A72: 3959 | B72: 62. | C72: Services Provided Other Units: State Level | D72: 0 | E72: 0 | F72: 0 | G72: 0 | H72: 0 | I72: =SUM(G72+H72) -> 0
B74: 63. | C74: TOTAL NET REVENUE FROM STATE SOURCES (Sum of lines 41-62) | D74: =SUM(D51:D72) -> 0 | E74: =SUM(E51:E72) -> 0 | F74: =SUM(F51:F72) -> 0 | G74: =SUM(G51:G72) -> 0 | H74: =SUM(H51:H72) -> 0 | I74: =SUM(I51:I72) -> 0
C76: REVENUE FROM FEDERAL SOURCES
A77: 4000 | B77: 64. | C77: Federal Revenue from CDE | D77: 0 | E77: 0 | F77: 0 | G77: 0 | H77: 0 | I77: =SUM(G77+H77) -> 0
A78: 4010 | B78: 65. | C78: Federal Revenue from other State Source | D78: 0 | E78: 0 | F78: 0 | G78: 0 | H78: 0 | I78: =SUM(G78+H78) -> 0
A79: 4020 | B79: 66. | C79: Federal Revenue directly from Federal Government | D79: 0 | E79: 0 | F79: 0 | G79: 0 | H79: 0 | I79: =SUM(G79+H79) -> 0
A80: 4951 | B80: 67. | C80: Services Provided within BOCES: Federal Level | D80: 0 | E80: 0 | F80: 0 | G80: 0 | H80: 0 | I80: =SUM(G80+H80) -> 0
A81: 4952 | B81: 68. | C81: Services Provided other Colorado Districts or BOCES: Federal Level | D81: 0 | E81: 0 | F81: 0 | G81: 0 | H81: 0 | I81: =SUM(G81+H81) -> 0
A82: 4954 | B82: 69. | C82: Services Provided Charter Schools: Federal Level | D82: 0 | E82: 0 | F82: 0 | G82: 0 | H82: 0 | I82: =SUM(G82+H82) -> 0
A83: 4959 | B83: 70. | C83: Services Provided Other Units: Federal Level | D83: 0 | E83: 0 | F83: 0 | G83: 0 | H83: 0 | I83: =SUM(G83+H83) -> 0
B84: 71. | C84: Impact Aid | D84: 0 | E84: 0 | F84: 0 | G84: 0 | H84: 0 | I84: =SUM(G84+H84) -> 0
B85: 72. | C85: Vocational Education | D85: 0 | E85: 0 | F85: 0 | G85: 0 | H85: 0 | I85: =SUM(G85+H85) -> 0
B86: 73. | C86: Handicapped Education | D86: 0 | E86: 0 | F86: 0 | G86: 0 | H86: 0 | I86: =SUM(G86+H86) -> 0
B87: 74. | C87: All Other Federal Revenue Codes | D87: 0 | E87: 0 | F87: 0 | G87: 0 | H87: 0 | I87: =SUM(G87+H87) -> 0
B89: 75. | C89: TOTAL REVENUE FROM FEDERAL SOURCES (Sum of lines 64-74) | D89: =SUM(D77:D87) -> 0 | E89: =SUM(E77:E87) -> 0 | F89: =SUM(F77:F87) -> 0 | G89: =SUM(G77:G87) -> 0 | H89: =SUM(H77:H87) -> 0 | I89: =SUM(I77:I87) -> 0
C91: REVENUE FROM OTHER SOURCES (See NOTE-1 below)
A92: 52XX | B92: 76. | C92: Transfer From(+)/To(-)________________Fund(s) (Net to zero across all funds)* | D92: 0 | E92: 0 | F92: 0 | G92: 0 | H92: 0 | I92: =SUM(G92+H92) -> 0
A93: 5400 | B93: 77. | C93: Capital Leases | D93: 0 | E93: 0 | F93: 0 | G93: 0 | H93: 0 | I93: =SUM(G93+H93) -> 0
A94: 5500 | B94: 78. | C94: Certificates of Participation | D94: 0 | E94: 0 | F94: 0 | G94: 0 | H94: 0 | I94: =SUM(G94+H94) -> 0
A95: 5900 | B95: 79. | C95: Other Sources | D95: 0 | E95: 0 | F95: 0 | G95: 0 | H95: 0 | I95: =SUM(G95+H95) -> 0
B96: 80. | C96: TOTAL REVENUE FROM OTHER SOURCES (Sum of lines 76-80) | D96: =SUM(D92:D95) -> 0 | E96: =SUM(E92:E95) -> 0 | F96: =SUM(F92:F95) -> 0 | G96: =SUM(G92:G95) -> 0 | H96: =SUM(H92:H95) -> 0 | I96: =SUM(I92:I95) -> 0
B98: 81. | C98: TOTAL GENERAL FUND REVENUE FOR ALL SOURCES (Sum of lines 39,40,63,75,80) | D98: =SUM(D45+D48+D74+D89+D96) -> 0 | E98: =SUM(E45+E48+E74+E89+E96) -> 0 | F98: =SUM(F45+F48+F74+F89+F96) -> 0 | G98: =SUM(G45+G48+G74+G89+G96) -> 0 | H98: =SUM(H45+H48+H74+H89+H96) -> 0 | I98: =SUM(I45+I48+I74+I89+I96) -> 0
B100: 82 | C100: TOTAL GENERAL FUND REVENUE INCLUDING BEGINNING FUND BALANCE (Sum of line 81 plus BFB) | D100: =D98+D5 -> 0 | E100: =E98+E5 -> 0 | F100: =F98+F5 -> 0 | G100: =G98+G5 -> 0 | H100: =H98+H5 -> 0 | I100: =I98+I5 -> 0
C101: Input lines 83 and 85 as a positive number (See NOTE-2 below)
A102: 56XX | B102: 83 | C102: Allocation to Capital Reserve or Insurance Reserve (Funds 21, 18, 43) | D102: 0 | E102: 0 | F102: 0 | G102: 0 | H102: 0 | I102: =SUM(G102+H102) -> 0
A103: 5711 | B103: 84 | C103: Allocation to Charter School (fund 11) from General Fund (fund 10) (as a negative amount) | D103: 0 | E103: 0 | F103: 0 | G103: 0 | H103: 0 | I103: =SUM(G103+H103) -> 0
A104: 5819 | B104: 85 | C104: Allocation to CPKP Fund (fund 19) | D104: 0 | E104: 0 | F104: 0 | G104: 0 | H104: 0 | I104: =SUM(G104+H104) -> 0
B106: 86 | C106: TOTAL ALLOCATIONS (Sum of lines83-85) | D106: =SUM(D102:D104) -> 0 | E106: =SUM(E102:E104) -> 0 | F106: =SUM(F102:F104) -> 0 | G106: =SUM(G102:G104) -> 0 | H106: =SUM(H102:H104) -> 0 | I106: =SUM(I102:I104) -> 0
B108: 87 | C108: NET REVENUE (Line 82 minus line 86) | D108: =D100-D106 -> 0 | E108: =E100-E106 -> 0 | F108: =F100-F106 -> 0 | G108: =G100-G106 -> 0 | H108: =H100-H106 -> 0 | I108: =I100-I106 -> 0
A110: NOTE-1: | C110: If you treat Transfers Out as an expenditure - report such amounts here:
A111: 52XX | B111: 76a. | C111: Transfer To________________Fund(s) (input as a positive number on this line) | D111: 0 | E111: 0 | F111: 0 | G111: 0 | H111: 0 | I111: =SUM(G111+H111) -> 0
A113: NOTE-2: | C113: If you treat Allocations Out as an expenditure - report such amounts here:
C114: Also input these amounts as a positive number here
A115: 56XX | B115: 83a. | C115: Allocation to Capital Reserve or Insurance Reserve (Funds 21, 18, 43) | D115: 0 | E115: 0 | F115: 0 | G115: 0 | H115: 0 | I115: =SUM(G115+H115) -> 0
A116: 5711 | B116: 84a. | C116: Allocation to Charter School (fund 11) | D116: 0 | E116: 0 | F116: 0 | G116: 0 | H116: 0 | I116: =SUM(G116+H116) -> 0
A117: 5819 | B117: 85a. | C117: Allocation to CPP Fund (fund 19) | D117: 0 | E117: 0 | F117: 0 | G117: 0 | H117: 0 | I117: =SUM(G117+H117) -> 0
B119: The above four lines will be linked for inclusion in the "TOTAL OTHER USES" line on the CharterFund Exp2 page.
A121: * | B121: Unless Transfers Out are recognized as an expenditure per above treatment.

Sheet CharterFundExp
A1: School District | C1: =+'Page 1 - FY2013-14'!B5 -> 0 | D1: District Code | E1: =+'Page 1 - FY2013-14'!F7 -> 0 | G1: * Round to Nearest Dollar *
A2: Fund 11: CHARTER FUND EXPENDITURES
D4: Prior Year Actual - Audited FY11-12 | E4: Current Fiscal Year - Budgeted FY12-13 | F4: Current Fiscal Year - Projected FY12-13 | G4: Original Ensuing Fiscal Year - Budget FY13-14 | H4: Adjustments Ensuing Fiscal Year - Budget FY13-14 | I4: Revised Ensuing Fiscal Year - Budget FY13-14
H5: Record Inceases to revenue are positive amounts and Decreases as negatives | I5: Figures (Totals) which will appear on Budget Form to Submit to CDE
A8: INSTRUCTION PROGRAM CODES
B9: Object Codes
A10: 0010 - General Elementary Education
B11: 0100 | C11: Salaries - from staff details tab | D11: 0 | E11: 0 | F11: 0 | G11: {=SUM(IF(CertFund&CertProg&CertObj=RIGHT(LEFT($A$2,7),2)&LEFT(A10,4)&B11,CertSalary))} -> 0 | H11: 0 | I11: =SUM(G11+H11) -> 0
B12: 0100 | C12: Salaries - additional items | D12: 0 | E12: 0 | F12: 0 | G12: 0 | H12: 0 | I12: =SUM(G12+H12) -> 0
B13: 0200 | C13: Employee Benefits - staff details tab | D13: 0 | E13: 0 | F13: 0 | G13: {=SUM(IF(CertFund&CertProg&CertObj=RIGHT(LEFT($A$2,7),2)&LEFT(A10,4)&B11,CertBen))} -> 0 | H13: 0 | I13: =SUM(G13+H13) -> 0
B14: 0200 | C14: Employee Benefits - addl items | D14: 0 | E14: 0 | F14: 0 | G14: 0 | H14: 0 | I14: =SUM(G14+H14) -> 0
B15: 0300 | C15: Purchased Professional & Technical Services | D15: 0 | E15: 0 | F15: 0 | G15: 0 | H15: 0 | I15: =SUM(G15+H15) -> 0
B16: 0400 | C16: Purchased Property Services | D16: 0 | E16: 0 | F16: 0 | G16: 0 | H16: 0 | I16: =SUM(G16+H16) -> 0
B17: 0430 | C17: Repairs & Maintenance Services | D17: 0 | E17: 0 | F17: 0 | G17: 0 | H17: 0 | I17: =SUM(G17+H17) -> 0
B18: 0442 | C18: Rental of Equipment | D18: 0 | E18: 0 | F18: 0 | G18: 0 | H18: 0 | I18: =SUM(G18+H18) -> 0
B19: 0500 | C19: Other Purchased Services | D19: 0 | E19: 0 | F19: 0 | G19: 0 | H19: 0 | I19: =SUM(G19+H19) -> 0
B20: 0513 | C20: Contracted Field Trips | D20: 0 | E20: 0 | F20: 0 | G20: 0 | H20: 0 | I20: =SUM(G20+H20) -> 0
B21: 0519 | C21: Other Purchased Student Transportation | D21: 0 | E21: 0 | F21: 0 | G21: 0 | H21: 0 | I21: =SUM(G21+H21) -> 0
B22: 0561 | C22: Tuition Paid Within the BOCES or AU | D22: 0 | E22: 0 | F22: 0 | G22: 0 | H22: 0 | I22: =SUM(G22+H22) -> 0
B23: 0562 | C23: Tuition Paid to Other Colorado Districts, BOCES or AU | D23: 0 | E23: 0 | F23: 0 | G23: 0 | H23: 0 | I23: =SUM(G23+H23) -> 0
B24: 0563 | C24: Tuition to School Districts Outside The State | D24: 0 | E24: 0 | F24: 0 | G24: 0 | H24: 0 | I24: =SUM(G24+H24) -> 0
B25: 0564 | C25: Tuition To Private Sources | D25: 0 | E25: 0 | F25: 0 | G25: 0 | H25: 0 | I25: =SUM(G25+H25) -> 0
... B43: 0851 | C43: Transportation/Field Trips | D43: 0 | E43: 0 | F43: 0 | G43: 0 | H43: 0 | I43: =SUM(G43+H43) -> 0
C44: TOTAL GENERAL ELEMENTARY EDUCATION | D44: =SUM(D11:D43) -> 0 | E44: =SUM(E11:E43) -> 0 | F44: =SUM(F11:F43) -> 0 | G44: =SUM(G11:G43) -> 0 | H44: =SUM(H11:H43) -> 0 | I44: =SUM(G44+H44) -> 0
A46: 0020 - General Middle/Jr. High School Education
B47: 0100 | C47: Salaries - from staff details tab | D47: 0 | E47: 0 | F47: 0 | G47: {=SUM(IF(CertFund&CertProg&CertObj=RIGHT(LEFT($A$2,7),2)&LEFT(A46,4)&B47,CertSalary))} -> 0 | H47: 0 | I47: =SUM(G47+H47) -> 0
B48: 0100 | C48: Salaries - additional items | D48: 0 | E48: 0 | F48: 0 | G48: 0 | H48: 0 | I48: =SUM(G48+H48) -> 0
B49: 0200 | C49: Employee Benefits - staff details tab | D49: 0 | E49: 0 | F49: 0 | G49: {=SUM(IF(CertFund&CertProg&CertObj=RIGHT(LEFT($A$2,7),2)&LEFT(A46,4)&B47,CertBen))} -> 0 | H49: 0 | I49: =SUM(G49+H49) -> 0
B50: 0200 | C50: Employee Benefits - addl items | D50: 0 | E50: 0 | F50: 0 | G50: 0 | H50: 0 | I50: =SUM(G50+H50) -> 0
B51: 0300 | C51: Purchased Professional & Technical Services | D51: 0 | E51: 0 | F51: 0 | G51: 0 | H51: 0 | I51: =SUM(G51+H51) -> 0
B52: 0400 | C52: Purchased Property Services | D52: 0 | E52: 0 | F52: 0 | G52: 0 | H52: 0 | I52: =SUM(G52+H52) -> 0
B53: 0430 | C53: Repairs & Maintenance Services | D53: 0 | E53: 0 | F53: 0 | G53: 0 | H53: 0 | I53: =SUM(G53+H53) -> 0
B54: 0442 | C54: Rental of Equipment | D54: 0 | E54: 0 | F54: 0 | G54: 0 | H54: 0 | I54: =SUM(G54+H54) -> 0
B55: 0500 | C55: Other Purchased Services | D55: 0 | E55: 0 | F55: 0 | G55: 0 | H55: 0 | I55: =SUM(G55+H55) -> 0
B56: 0513 | C56: Contracted Field Trips | D56: 0 | E56: 0 | F56: 0 | G56: 0 | H56: 0 | I56: =SUM(G56+H56) -> 0
B57: 0519 | C57: Other Purchased Student Transportation | D57: 0 | E57: 0 | F57: 0 | G57: 0 | H57: 0 | I57: =SUM(G57+H57) -> 0
B58: 0561 | C58: Tuition Paid Within the BOCES or AU | D58: 0 | E58: 0 | F58: 0 | G58: 0 | H58: 0 | I58: =SUM(G58+H58) -> 0
B59: 0562 | C59: Tuition Paid to Other Colorado Districts, BOCES or AU | D59: 0 | E59: 0 | F59: 0 | G59: 0 | H59: 0 | I59: =SUM(G59+H59) -> 0
B60: 0563 | C60: Tuition to School Districts Outside The State | D60: 0 | E60: 0 | F60: 0 | G60: 0 | H60: 0 | I60: =SUM(G60+H60) -> 0
B61: 0564 | C61: Tuition To Private Sources | D61: 0 | E61: 0 | F61: 0 | G61: 0 | H61: 0 | I61: =SUM(G61+H61) -> 0
... B79: 0851 | C79: Transportation/Field Trips | D79: 0 | E79: 0 | F79: 0 | G79: 0 | H79: 0 | I79: =SUM(G79+H79) -> 0
C80: TOTAL GENERAL MIDDLE/JR.HIGH SCHOOL EDUCATION | D80: =SUM(D47:D79) -> 0 | E80: =SUM(E47:E79) -> 0 | F80: =SUM(F47:F79) -> 0 | G80: =SUM(G47:G79) -> 0 | H80: =SUM(H47:H79) -> 0 | I80: =SUM(G80+H80) -> 0
A82: 0030 - General High School Education
B83: 0100 | C83: Salaries - from staff details tab | D83: 0 | E83: 0 | F83: 0 | G83: {=SUM(IF(CertFund&CertProg&CertObj=RIGHT(LEFT($A$2,7),2)&LEFT(A82,4)&B83,CertSalary))} -> 0 | H83: 0 | I83: =SUM(G83+H83) -> 0
B84: 0100 | C84: Salaries - additional items | D84: 0 | E84: 0 | F84: 0 | G84: 0 | H84: 0 | I84: =SUM(G84+H84) -> 0
B85: 0200 | C85: Employee Benefits - staff details tab | D85: 0 | E85: 0 | F85: 0 | G85: {=SUM(IF(CertFund&CertProg&CertObj=RIGHT(LEFT($A$2,7),2)&LEFT(A82,4)&B83,CertBen))} -> 0 | H85: 0 | I85: =SUM(G85+H85) -> 0
B86: 0200 | C86: Employee Benefits - addl items | D86: 0 | E86: 0 | F86: 0 | G86: 0 | H86: 0 | I86: =SUM(G86+H86) -> 0
B87: 0300 | C87: Purchased Professional & Technical Services | D87: 0 | E87: 0 | F87: 0 | G87: 0 | H87: 0 | I87: =SUM(G87+H87) -> 0
B88: 0400 | C88: Purchased Property Services | D88: 0 | E88: 0 | F88: 0 | G88: 0 | H88: 0 | I88: =SUM(G88+H88) -> 0
B89: 0430 | C89: Repairs & Maintenance Services | D89: 0 | E89: 0 | F89: 0 | G89: 0 | H89: 0 | I89: =SUM(G89+H89) -> 0
B90: 0442 | C90: Rental of Equipment | D90: 0 | E90: 0 | F90: 0 | G90: 0 | H90: 0 | I90: =SUM(G90+H90) -> 0
B91: 0500 | C91: Other Purchased Services | D91: 0 | E91: 0 | F91: 0 | G91: 0 | H91: 0 | I91: =SUM(G91+H91) -> 0
B92: 0513 | C92: Contracted Field Trips | D92: 0 | E92: 0 | F92: 0 | G92: 0 | H92: 0 | I92: =SUM(G92+H92) -> 0
B93: 0519 | C93: Other Purchased Student Transportation | D93: 0 | E93: 0 | F93: 0 | G93: 0 | H93: 0 | I93: =SUM(G93+H93) -> 0
B94: 0561 | C94: Tuition Paid Within the BOCES or AU | D94: 0 | E94: 0 | F94: 0 | G94: 0 | H94: 0 | I94: =SUM(G94+H94) -> 0
B95: 0562 | C95: Tuition Paid to Other Colorado Districts, BOCES or AU | D95: 0 | E95: 0 | F95: 0 | G95: 0 | H95: 0 | I95: =SUM(G95+H95) -> 0
B96: 0563 | C96: Tuition to School Districts Outside The State | D96: 0 | E96: 0 | F96: 0 | G96: 0 | H96: 0 | I96: =SUM(G96+H96) -> 0
B97: 0564 | C97: Tuition To Private Sources | D97: 0 | E97: 0 | F97: 0 | G97: 0 | H97: 0 | I97: =SUM(G97+H97) -> 0
... B115: 0851 | C115: Transportation/Field Trips | D115: 0 | E115: 0 | F115: 0 | G115: 0 | H115: 0 | I115: =SUM(G115+H115) -> 0
C116: TOTAL GENERAL HIGH SCHOOL EDUCATION | D116: =SUM(D83:D115) -> 0 | E116: =SUM(E83:E115) -> 0 | F116: =SUM(F83:F115) -> 0 | G116: =SUM(G83:G115) -> 0 | H116: =SUM(H83:H115) -> 0 | I116: =SUM(G116+H116) -> 0
A118: 0040 - General Pre-School Education
B119: 0100 | C119: Salaries - from staff details tab | D119: 0 | E119: 0 | F119: 0 | G119: {=SUM(IF(CertFund&CertProg&CertObj=RIGHT(LEFT($A$2,7),2)&LEFT(A118,4)&B119,CertSalary))} -> 0 | H119: 0 | I119: =SUM(G119+H119) -> 0
B120: 0100 | C120: Salaries - additional items | D120: 0 | E120: 0 | F120: 0 | G120: 0 | H120: 0 | I120: =SUM(G120+H120) -> 0
B121: 0200 | C121: Employee Benefits - staff details tab | D121: 0 | E121: 0 | F121: 0 | G121: {=SUM(IF(CertFund&CertProg&CertObj=RIGHT(LEFT($A$2,7),2)&LEFT(A118,4)&B119,CertBen))} -> 0 | H121: 0 | I121: =SUM(G121+H121) -> 0
B122: 0200 | C122: Employee Benefits - addl items | D122: 0 | E122: 0 | F122: 0 | G122: 0 | H122: 0 | I122: =SUM(G122+H122) -> 0
B123: 0300 | C123: Purchased Professional & Technical Services | D123: 0 | E123: 0 | F123: 0 | G123: 0 | H123: 0 | I123: =SUM(G123+H123) -> 0
B124: 0400 | C124: Purchased Property Services | D124: 0 | E124: 0 | F124: 0 | G124: 0 | H124: 0 | I124: =SUM(G124+H124) -> 0
B125: 0430 | C125: Repairs & Maintenance Services | D125: 0 | E125: 0 | F125: 0 | G125: 0 | H125: 0 | I125: =SUM(G125+H125) -> 0
B126: 0442 | C126: Rental of Equipment | D126: 0 | E126: 0 | F126: 0 | G126: 0 | H126: 0 | I126: =SUM(G126+H126) -> 0
B127: 0500 | C127: Other Purchased Services | D127: 0 | E127: 0 | F127: 0 | G127: 0 | H127: 0 | I127: =SUM(G127+H127) -> 0
B128: 0513 | C128: Contracted Field Trips | D128: 0 | E128: 0 | F128: 0 | G128: 0 | H128: 0 | I128: =SUM(G128+H128) -> 0
B129: 0519 | C129: Other Purchased Student Transportation | D129: 0 | E129: 0 | F129: 0 | G129: 0 | H129: 0 | I129: =SUM(G129+H129) -> 0
B130: 0561 | C130: Tuition Paid Within the BOCES or AU | D130: 0 | E130: 0 | F130: 0 | G130: 0 | H130: 0 | I130: =SUM(G130+H130) -> 0
B131: 0562 | C131: Tuition Paid to Other Colorado Districts, BOCES or AU | D131: 0 | E131: 0 | F131: 0 | G131: 0 | H131: 0 | I131: =SUM(G131+H131) -> 0
B132: 0563 | C132: Tuition to School Districts Outside The State | D132: 0 | E132: 0 | F132: 0 | G132: 0 | H132: 0 | I132: =SUM(G132+H132) -> 0
B133: 0564 | C133: Tuition To Private Sources | D133: 0 | E133: 0 | F133: 0 | G133: 0 | H133: 0 | I133: =SUM(G133+H133) -> 0
... B151: 0851 | C151: Transportation/Field Trips | D151: 0 | E151: 0 | F151: 0 | G151: 0 | H151: 0 | I151: =SUM(G151+H151) -> 0
C152: TOTAL GENERAL PRE-SCHOOL EDUCATION | D152: =SUM(D119:D151) -> 0 | E152: =SUM(E119:E151) -> 0 | F152: =SUM(F119:F151) -> 0 | G152: =SUM(G119:G151) -> 0 | H152: =SUM(H119:H151) -> 0 | I152: =SUM(G152+H152) -> 0
A154: 0050 - General Post-Secondary Education
B155: 0100 | C155: Salaries - from staff details tab | D155: 0 | E155: 0 | F155: 0 | G155: {=SUM(IF(CertFund&CertProg&CertObj=RIGHT(LEFT($A$2,7),2)&LEFT(A154,4)&B155,CertSalary))} -> 0 | H155: 0 | I155: =SUM(G155+H155) -> 0
B156: 0100 | C156: Salaries - additional items | D156: 0 | E156: 0 | F156: 0 | G156: 0 | H156: 0 | I156: =SUM(G156+H156) -> 0
B157: 0200 | C157: Employee Benefits - staff details tab | D157: 0 | E157: 0 | F157: 0 | G157: {=SUM(IF(CertFund&CertProg&CertObj=RIGHT(LEFT($A$2,7),2)&LEFT(A154,4)&B155,CertBen))} -> 0 | H157: 0 | I157: =SUM(G157+H157) -> 0
B158: 0200 | C158: Employee Benefits - addl items | D158: 0 | E158: 0 | F158: 0 | G158: 0 | H158: 0 | I158: =SUM(G158+H158) -> 0
B159: 0300 | C159: Purchased Professional & Technical Services | D159: 0 | E159: 0 | F159: 0 | G159: 0 | H159: 0 | I159: =SUM(G159+H159) -> 0
B160: 0400 | C160: Purchased Property Services | D160: 0 | E160: 0 | F160: 0 | G160: 0 | H160: 0 | I160: =SUM(G160+H160) -> 0
B161: 0430 | C161: Repairs & Maintenance Services | D161: 0 | E161: 0 | F161: 0 | G161: 0 | H161: 0 | I161: =SUM(G161+H161) -> 0
B162: 0442 | C162: Rental of Equipment | D162: 0 | E162: 0 | F162: 0 | G162: 0 | H162: 0 | I162: =SUM(G162+H162) -> 0
B163: 0500 | C163: Other Purchased Services | D163: 0 | E163: 0 | F163: 0 | G163: 0 | H163: 0 | I163: =SUM(G163+H163) -> 0
B164: 0513 | C164: Contracted Field Trips | D164: 0 | E164: 0 | F164: 0 | G164: 0 | H164: 0 | I164: =SUM(G164+H164) -> 0
B165: 0519 | C165: Other Purchased Student Transportation | D165: 0 | E165: 0 | F165: 0 | G165: 0 | H165: 0 | I165: =SUM(G165+H165) -> 0
B166: 0561 | C166: Tuition Paid Within the BOCES or AU | D166: 0 | E166: 0 | F166: 0 | G166: 0 | H166: 0 | I166: =SUM(G166+H166) -> 0
B167: 0562 | C167: Tuition Paid to Other Colorado Districts, BOCES or AU | D167: 0 | E167: 0 | F167: 0 | G167: 0 | H167: 0 | I167: =SUM(G167+H167) -> 0
B168: 0563 | C168: Tuition to School Districts Outside The State | D168: 0 | E168: 0 | F168: 0 | G168: 0 | H168: 0 | I168: =SUM(G168+H168) -> 0
B169: 0564 | C169: Tuition To Private Sources | D169: 0 | E169: 0 | F169: 0 | G169: 0 | H169: 0 | I169: =SUM(G169+H169) -> 0
... B187: 0851 | C187: Transportation/Field Trips | D187: 0 | E187: 0 | F187: 0 | G187: 0 | H187: 0 | I187: =SUM(G187+H187) -> 0
C188: TOTAL GENERAL POST-SECONDARY EDUCATION | D188: =SUM(D155:D187) -> 0 | E188: =SUM(E155:E187) -> 0 | F188: =SUM(F155:F187) -> 0 | G188: =SUM(G155:G187) -> 0 | H188: =SUM(H155:H187) -> 0 | I188: =SUM(G188+H188) -> 0
A190: 0051 - Programs for Adult/Continuing
B191: 0100 | C191: Salaries - from staff details tab | D191: 0 | E191: 0 | F191: 0 | G191: {=SUM(IF(CertFund&CertProg&CertObj=RIGHT(LEFT($A$2,7),2)&LEFT(A190,4)&B191,CertSalary))} -> 0 | H191: 0 | I191: =SUM(G191+H191) -> 0
B192: 0100 | C192: Salaries - additional items | D192: 0 | E192: 0 | F192: 0 | G192: 0 | H192: 0 | I192: =SUM(G192+H192) -> 0
B193: 0200 | C193: Employee Benefits - staff details tab | D193: 0 | E193: 0 | F193: 0 | G193: {=SUM(IF(CertFund&CertProg&CertObj=RIGHT(LEFT($A$2,7),2)&LEFT(A190,4)&B191,CertBen))} -> 0 | H193: 0 | I193: =SUM(G193+H193) -> 0
...

Sheet CharterFundExp2
A1: School District | C1: =+'Page 1 - FY2013-14'!B5 -> 0 | D1: District Code | E1: =+'Page 1 - FY2013-14'!F7 -> 0 | G1: * Round to Nearest Dollar *
A2: Fund 11: CHARTER FUND EXPENDITURES
D4: Prior Year Actual - Audited FY11-12 | E4: Current Fiscal Year - Budgeted FY12-13 | F4: Current Fiscal Year - Projected FY12-13 | G4: Original Ensuing Fiscal Year - Budget FY13-14 | H4: Adjustments Ensuing Fiscal Year - Budget FY13-14 | I4: Revised Ensuing Fiscal Year - Budget FY13-14
H5: Record Inceases to revenue are positive amounts and Decreases as negatives | I5: Figures (Totals) which will appear on Budget Form to Submit to CDE
A7: SUPPORT SERVICES PROGRAM CODES
B8: Object Codes
A9: 2100 - Students
B10: 0100 | C10: Salaries - from staff details tab | D10: 0 | E10: 0 | F10: 0 | G10: {=SUM(IF(CertFund&CertProg&CertObj=RIGHT(LEFT($A$2,7),2)&LEFT(A9,4)&B10,CertSalary))} -> 0 | H10: 0 | I10: =SUM(G10+H10) -> 0
B11: 0100 | C11: Salaries - additional items | D11: 0 | E11: 0 | F11: 0 | G11: 0 | H11: 0 | I11: =SUM(G11+H11) -> 0
B12: 0200 | C12: Employee Benefits - staff details tab | D12: 0 | E12: 0 | F12: 0 | G12: {=SUM(IF(CertFund&CertProg&CertObj=RIGHT(LEFT($A$2,7),2)&LEFT(A9,4)&B10,CertBen))} -> 0 | H12: 0 | I12: =SUM(G12+H12) -> 0
B13: 0200 | C13: Employee Benefits - addl items | D13: 0 | E13: 0 | F13: 0 | G13: 0 | H13: 0 | I13: =SUM(G13+H13) -> 0
B14: 0300 | C14: Purchased Professional & Technical Services | D14: 0 | E14: 0 | F14: 0 | G14: 0 | H14: 0 | I14: =SUM(G14+H14) -> 0
B15: 0400 | C15: Purchased Property Services | D15: 0 | E15: 0 | F15: 0 | G15: 0 | H15: 0 | I15: =SUM(G15+H15) -> 0
B16: 0430 | C16: Repairs & Maintenance Services | D16: 0 | E16: 0 | F16: 0 | G16: 0 | H16: 0 | I16: =SUM(G16+H16) -> 0
B17: 0442 | C17: Rental of Equipment | D17: 0 | E17: 0 | F17: 0 | G17: 0 | H17: 0 | I17: =SUM(G17+H17) -> 0
B18: 0500 | C18: Other Purchased Services | D18: 0 | E18: 0 | F18: 0 | G18: 0 | H18: 0 | I18: =SUM(G18+H18) -> 0
B19: 0511 | C19: Student Transportation Purchased Within the BOCES or AU | D19: 0 | E19: 0 | F19: 0 | G19: 0 | H19: 0 | I19: =SUM(G19+H19) -> 0
B20: 0512 | C20: Student Transportation Purchased from Other Colorado Districts, BOCES or AU | D20: 0 | E20: 0 | F20: 0 | G20: 0 | H20: 0 | I20: =SUM(G20+H20) -> 0
B21: 0513 | C21: Contracted Field Trips | D21: 0 | E21: 0 | F21: 0 | G21: 0 | H21: 0 | I21: =SUM(G21+H21) -> 0
B22: 0514 | C22: Student Transportation Purchased from Parents | D22: 0 | E22: 0 | F22: 0 | G22: 0 | H22: 0 | I22: =SUM(G22+H22) -> 0
B23: 0515 | C23: Student Transportation Purchased from Contractors | D23: 0 | E23: 0 | F23: 0 | G23: 0 | H23: 0 | I23: =SUM(G23+H23) -> 0
B24: 0517 | C24: Student Transportation Purchased from School District Outside the State | D24: 0 | E24: 0 | F24: 0 | G24: 0 | H24: 0 | I24: =SUM(G24+H24) -> 0
... B43: 0869 | C43: Indirect Costs | D43: 0 | E43: 0 | F43: 0 | G43: 0 | H43: 0 | I43: =SUM(G43+H43) -> 0
C44: TOTAL STUDENT SUPPORT | D44: =SUM(D10:D43) -> 0 | E44: =SUM(E10:E43) -> 0 | F44: =SUM(F10:F43) -> 0 | G44: =SUM(G10:G43) -> 0 | H44: =SUM(H10:H43) -> 0 | I44: =SUM(G44+H44) -> 0
A46: 2200 - Instructional Staff
B47: 0100 | C47: Salaries - from staff details tab | D47: 0 | E47: 0 | F47: 0 | G47: {=SUM(IF(CertFund&CertProg&CertObj=RIGHT(LEFT($A$2,7),2)&LEFT(A46,4)&B47,CertSalary))} -> 0 | H47: 0 | I47: =SUM(G47+H47) -> 0
B48: 0100 | C48: Salaries - additional items | D48: 0 | E48: 0 | F48: 0 | G48: 0 | H48: 0 | I48: =SUM(G48+H48) -> 0
B49: 0200 | C49: Employee Benefits - staff details tab | D49: 0 | E49: 0 | F49: 0 | G49: {=SUM(IF(CertFund&CertProg&CertObj=RIGHT(LEFT($A$2,7),2)&LEFT(A46,4)&B47,CertBen))} -> 0 | H49: 0 | I49: =SUM(G49+H49) -> 0
B50: 0200 | C50: Employee Benefits - addl items | D50: 0 | E50: 0 | F50: 0 | G50: 0 | H50: 0 | I50: =SUM(G50+H50) -> 0
B51: 0300 | C51: Purchased Professional & Technical Services | D51: 0 | E51: 0 | F51: 0 | G51: 0 | H51: 0 | I51: =SUM(G51+H51) -> 0
B52: 0400 | C52: Purchased Property Services | D52: 0 | E52: 0 | F52: 0 | G52: 0 | H52: 0 | I52: =SUM(G52+H52) -> 0
B53: 0430 | C53: Repairs & Maintenance Services | D53: 0 | E53: 0 | F53: 0 | G53: 0 | H53: 0 | I53: =SUM(G53+H53) -> 0
B54: 0442 | C54: Rental of Equipment | D54: 0 | E54: 0 | F54: 0 | G54: 0 | H54: 0 | I54: =SUM(G54+H54) -> 0
B55: 0500 | C55: Other Purchased Services | D55: 0 | E55: 0 | F55: 0 | G55: 0 | H55: 0 | I55: =SUM(G55+H55) -> 0
B56: 0511 | C56: Student Transportation Purchased Within the BOCES or AU | D56: 0 | E56: 0 | F56: 0 | G56: 0 | H56: 0 | I56: =SUM(G56+H56) -> 0
B57: 0512 | C57: Student Transportation Purchased from Other Colorado Districts, BOCES or AU | D57: 0 | E57: 0 | F57: 0 | G57: 0 | H57: 0 | I57: =SUM(G57+H57) -> 0
B58: 0513 | C58: Contracted Field Trips | D58: 0 | E58: 0 | F58: 0 | G58: 0 | H58: 0 | I58: =SUM(G58+H58) -> 0
B59: 0514 | C59: Student Transportation Purchased from Parents | D59: 0 | E59: 0 | F59: 0 | G59: 0 | H59: 0 | I59: =SUM(G59+H59) -> 0
B60: 0515 | C60: Student Transportation Purchased from Contractors | D60: 0 | E60: 0 | F60: 0 | G60: 0 | H60: 0 | I60: =SUM(G60+H60) -> 0
B61: 0517 | C61: Student Transportation Purchased from School District Outside the State | D61: 0 | E61: 0 | F61: 0 | G61: 0 | H61: 0 | I61: =SUM(G61+H61) -> 0
... B80: 0869 | C80: Indirect Costs | D80: 0 | E80: 0 | F80: 0 | G80: 0 | H80: 0 | I80: =SUM(G80+H80) -> 0
C81: TOTAL INSTRUCTIONAL STAFF SUPPORT | D81: =SUM(D47:D80) -> 0 | E81: =SUM(E47:E80) -> 0 | F81: =SUM(F47:F80) -> 0 | G81: =SUM(G47:G80) -> 0 | H81: =SUM(H47:H80) -> 0 | I81: =SUM(G81+H81) -> 0
A83: 2220 - Educational Library Services
B84: 0100 | C84: Salaries - from staff details tab | D84: 0 | E84: 0 | F84: 0 | G84: {=SUM(IF(CertFund&CertProg&CertObj=RIGHT(LEFT($A$2,7),2)&LEFT(A83,4)&B84,CertSalary))} -> 0 | H84: 0 | I84: =SUM(G84+H84) -> 0
B85: 0100 | C85: Salaries - additional items | D85: 0 | E85: 0 | F85: 0 | G85: 0 | H85: 0 | I85: =SUM(G85+H85) -> 0
B86: 0200 | C86: Employee Benefits - staff details tab | D86: 0 | E86: 0 | F86: 0 | G86: {=SUM(IF(CertFund&CertProg&CertObj=RIGHT(LEFT($A$2,7),2)&LEFT(A83,4)&B84,CertBen))} -> 0 | H86: 0 | I86: =SUM(G86+H86) -> 0
B87: 0200 | C87: Employee Benefits - addl items | D87: 0 | E87: 0 | F87: 0 | G87: 0 | H87: 0 | I87: =SUM(G87+H87) -> 0
B88: 0300 | C88: Purchased Professional & Technical Services | D88: 0 | E88: 0 | F88: 0 | G88: 0 | H88: 0 | I88: =SUM(G88+H88) -> 0
B89: 0400 | C89: Purchased Property Services | D89: 0 | E89: 0 | F89: 0 | G89: 0 | H89: 0 | I89: =SUM(G89+H89) -> 0
B90: 0430 | C90: Repairs & Maintenance Services | D90: 0 | E90: 0 | F90: 0 | G90: 0 | H90: 0 | I90: =SUM(G90+H90) -> 0
B91: 0442 | C91: Rental of Equipment | D91: 0 | E91: 0 | F91: 0 | G91: 0 | H91: 0 | I91: =SUM(G91+H91) -> 0
B92: 0500 | C92: Other Purchased Services | D92: 0 | E92: 0 | F92: 0 | G92: 0 | H92: 0 | I92: =SUM(G92+H92) -> 0
B93: 0511 | C93: Student Transportation Purchased Within the BOCES or AU | D93: 0 | E93: 0 | F93: 0 | G93: 0 | H93: 0 | I93: =SUM(G93+H93) -> 0
B94: 0512 | C94: Student Transportation Purchased from Other Colorado Districts, BOCES or AU | D94: 0 | E94: 0 | F94: 0 | G94: 0 | H94: 0 | I94: =SUM(G94+H94) -> 0
B95: 0513 | C95: Contracted Field Trips | D95: 0 | E95: 0 | F95: 0 | G95: 0 | H95: 0 | I95: =SUM(G95+H95) -> 0
B96: 0514 | C96: Student Transportation Purchased from Parents | D96: 0 | E96: 0 | F96: 0 | G96: 0 | H96: 0 | I96: =SUM(G96+H96) -> 0
B97: 0515 | C97: Student Transportation Purchased from Contractors | D97: 0 | E97: 0 | F97: 0 | G97: 0 | H97: 0 | I97: =SUM(G97+H97) -> 0
B98: 0517 | C98: Student Transportation Purchased from School District Outside the State | D98: 0 | E98: 0 | F98: 0 | G98: 0 | H98: 0 | I98: =SUM(G98+H98) -> 0
... B117: 0869 | C117: Indirect Costs | D117: 0 | E117: 0 | F117: 0 | G117: 0 | H117: 0 | I117: =SUM(G117+H117) -> 0
C118: TOTAL EDUCATIONAL LIBRARY SERVICES | D118: =SUM(D84:D117) -> 0 | E118: =SUM(E84:E117) -> 0 | F118: =SUM(F84:F117) -> 0 | G118: =SUM(G84:G117) -> 0 | H118: =SUM(H84:H117) -> 0 | I118: =SUM(G118+H118) -> 0
A120: 2300 - General Administration
B121: 0100 | C121: Salaries - from staff details tab | D121: 0 | E121: 0 | F121: 0 | G121: {=SUM(IF(CertFund&CertProg&CertObj=RIGHT(LEFT($A$2,7),2)&LEFT(A120,4)&B121,CertSalary))} -> 0 | H121: 0 | I121: =SUM(G121+H121) -> 0
B122: 0100 | C122: Salaries - additional items | D122: 0 | E122: 0 | F122: 0 | G122: 0 | H122: 0 | I122: =SUM(G122+H122) -> 0
B123: 0200 | C123: Employee Benefits - staff details tab | D123: 0 | E123: 0 | F123: 0 | G123: {=SUM(IF(CertFund&CertProg&CertObj=RIGHT(LEFT($A$2,7),2)&LEFT(A120,4)&B121,CertBen))} -> 0 | H123: 0 | I123: =SUM(G123+H123) -> 0
B124: 0200 | C124: Employee Benefits - addl items | D124: 0 | E124: 0 | F124: 0 | G124: 0 | H124: 0 | I124: =SUM(G124+H124) -> 0
B125: 0300 | C125: Purchased Professional & Technical Services | D125: 0 | E125: 0 | F125: 0 | G125: 0 | H125: 0 | I125: =SUM(G125+H125) -> 0
B126: 0400 | C126: Purchased Property Services | D126: 0 | E126: 0 | F126: 0 | G126: 0 | H126: 0 | I126: =SUM(G126+H126) -> 0
B127: 0430 | C127: Repairs & Maintenance Services | D127: 0 | E127: 0 | F127: 0 | G127: 0 | H127: 0 | I127: =SUM(G127+H127) -> 0
B128: 0442 | C128: Rental of Equipment | D128: 0 | E128: 0 | F128: 0 | G128: 0 | H128: 0 | I128: =SUM(G128+H128) -> 0
B129: 0500 | C129: Other Purchased Services | D129: 0 | E129: 0 | F129: 0 | G129: 0 | H129: 0 | I129: =SUM(G129+H129) -> 0
B130: 0569 | C130: Tuition - Other | D130: 0 | E130: 0 | F130: 0 | G130: 0 | H130: 0 | I130: =SUM(G130+H130) -> 0
B131: 0580 | C131: Travel, Registration, and Entrance | D131: 0 | E131: 0 | F131: 0 | G131: 0 | H131: 0 | I131: =SUM(G131+H131) -> 0
B132: 0591 | C132: Services Purchased Within the BOCES or AU | D132: 0 | E132: 0 | F132: 0 | G132: 0 | H132: 0 | I132: =SUM(G132+H132) -> 0
B133: 0592 | C133: Services Purchased from Other Colorado Districts, BOCES or AU | D133: 0 | E133: 0 | F133: 0 | G133: 0 | H133: 0 | I133: =SUM(G133+H133) -> 0
B134: 0593 | C134: Services Purchased from School Districts Outside the State | D134: 0 | E134: 0 | F134: 0 | G134: 0 | H134: 0 | I134: =SUM(G134+H134) -> 0
B135: 0594 | C135: Purchased Services from Districts by Charter Schools | D135: 0 | E135: 0 | F135: 0 | G135: 0 | H135: 0 | I135: =SUM(G135+H135) -> 0
... B148: 0869 | C148: Indirect Costs | D148: 0 | E148: 0 | F148: 0 | G148: 0 | H148: 0 | I148: =SUM(G148+H148) -> 0
C149: TOTAL GENERAL ADMINISTRATION SUPPORT | D149: =SUM(D121:D148) -> 0 | E149: =SUM(E121:E148) -> 0 | F149: =SUM(F121:F148) -> 0 | G149: =SUM(G121:G148) -> 0 | H149: =SUM(H121:H148) -> 0 | I149: =SUM(G149+H149) -> 0
A151: 2400 - School Administration
B152: 0100 | C152: Salaries - from staff details tab | D152: 0 | E152: 0 | F152: 0 | G152: {=SUM(IF(CertFund&CertProg&CertObj=RIGHT(LEFT($A$2,7),2)&LEFT(A151,4)&B152,CertSalary))} -> 0 | H152: 0 | I152: =SUM(G152+H152) -> 0
B153: 0100 | C153: Salaries - additional items | D153: 0 | E153: 0 | F153: 0 | G153: 0 | H153: 0 | I153: =SUM(G153+H153) -> 0
B154: 0200 | C154: Employee Benefits - staff details tab | D154: 0 | E154: 0 | F154: 0 | G154: {=SUM(IF(CertFund&CertProg&CertObj=RIGHT(LEFT($A$2,7),2)&LEFT(A151,4)&B152,CertBen))} -> 0 | H154: 0 | I154: =SUM(G154+H154) -> 0
B155: 0200 | C155: Employee Benefits - addl items | D155: 0 | E155: 0 | F155: 0 | G155: 0 | H155: 0 | I155: =SUM(G155+H155) -> 0
B156: 0300 | C156: Purchased Professional & Technical Services | D156: 0 | E156: 0 | F156: 0 | G156: 0 | H156: 0 | I156: =SUM(G156+H156) -> 0
B157: 0400 | C157: Purchased Property Services | D157: 0 | E157: 0 | F157: 0 | G157: 0 | H157: 0 | I157: =SUM(G157+H157) -> 0
B158: 0430 | C158: Repairs & Maintenance Services | D158: 0 | E158: 0 | F158: 0 | G158: 0 | H158: 0 | I158: =SUM(G158+H158) -> 0
B159: 0442 | C159: Rental of Equipment | D159: 0 | E159: 0 | F159: 0 | G159: 0 | H159: 0 | I159: =SUM(G159+H159) -> 0
B160: 0500 | C160: Other Purchased Services | D160: 0 | E160: 0 | F160: 0 | G160: 0 | H160: 0 | I160: =SUM(G160+H160) -> 0
B161: 0511 | C161: Student Transportation Purchased Within the BOCES or AU | D161: 0 | E161: 0 | F161: 0 | G161: 0 | H161: 0 | I161: =SUM(G161+H161) -> 0
B162: 0512 | C162: Student Transportation Purchased from Other Colorado Districts, BOCES or AU | D162: 0 | E162: 0 | F162: 0 | G162: 0 | H162: 0 | I162: =SUM(G162+H162) -> 0
B163: 0513 | C163: Contracted Field Trips | D163: 0 | E163: 0 | F163: 0 | G163: 0 | H163: 0 | I163: =SUM(G163+H163) -> 0
B164: 0514 | C164: Student Transportation Purchased from Parents | D164: 0 | E164: 0 | F164: 0 | G164: 0 | H164: 0 | I164: =SUM(G164+H164) -> 0
B165: 0515 | C165: Student Transportation Purchased from Contractors | D165: 0 | E165: 0 | F165: 0 | G165: 0 | H165: 0 | I165: =SUM(G165+H165) -> 0
B166: 0516 | C166: Student Transportation In-service | D166: 0 | E166: 0 | F166: 0 | G166: 0 | H166: 0 | I166: =SUM(G166+H166) -> 0
... B186: 0869 | C186: Indirect Costs | D186: 0 | E186: 0 | F186: 0 | G186: 0 | H186: 0 | I186: =SUM(G186+H186) -> 0
C187: TOTAL SCHOOL ADMINISTRATION SUPPORT | D187: =SUM(D152:D186) -> 0 | E187: =SUM(E152:E186) -> 0 | F187: =SUM(F152:F186) -> 0 | G187: =SUM(G152:G186) -> 0 | H187: =SUM(H152:H186) -> 0 | I187: =SUM(G187+H187) -> 0
A189: 2500 - Business Services
B190: 0100 | C190: Salaries - from staff details tab | D190: 0 | E190: 0 | F190: 0 | G190: {=SUM(IF(CertFund&CertProg&CertObj=RIGHT(LEFT($A$2,7),2)&LEFT(A189,4)&B190,CertSalary))} -> 0 | H190: 0 | I190: =SUM(G190+H190) -> 0
B191: 0100 | C191: Salaries - additional items | D191: 0 | E191: 0 | F191: 0 | G191: 0 | H191: 0 | I191: =SUM(G191+H191) -> 0
B192: 0200 | C192: Employee Benefits - staff details tab | D192: 0 | E192: 0 | F192: 0 | G192: {=SUM(IF(CertFund&CertProg&CertObj=RIGHT(LEFT($A$2,7),2)&LEFT(A189,4)&B190,CertBen))} -> 0 | H192: 0 | I192: =SUM(G192+H192) -> 0
...

Sheet InsResv
A1: School District | C1: =+'Page 1 - FY2013-14'!B5 -> 0 | D1: District Code | E1: =+'Page 1 - FY2013-14'!F7 -> 0 | G1: * Round to Nearest Dollar *
A2: Fund 18: INSURANCE RESERVE FUND
D3: Prior Year Actual - Audited FY11-12 | E3: Current Fiscal Year - Budgeted FY12-13 | F3: Current Fiscal Year - Projected FY12-13 | G3: Original Ensuing Fiscal Year - Budget FY13-14 | H3: Adjustments Ensuing Fiscal Year - Budget FY13-14 | I3: Revised Ensuing Fiscal Year - Budget FY13-14
H4: Record Inceases to revenue are positive amounts and Decreases as negatives | I4: Figures (Totals) which will appear on Budget Form to Submit to CDE
A6: Codes: | B6: BEGINNING FUND BALANCE | D6: 0 | E6: 0 | F6: 0 | G6: 0 | H6: 0 | I6: =G6+H6 -> 0
A7: Source | C7: REVENUE AND OTHER SOURCES
A8: 1110 | B8: 1. | C8: Property Taxes | D8: 0 | E8: 0 | F8: 0 | G8: 0 | H8: 0 | I8: =SUM(G8+H8) -> 0
A9: 1120 | B9: 2. | C9: Specific Ownership Taxes | D9: 0 | E9: 0 | F9: 0 | G9: 0 | H9: 0 | I9: =SUM(G9+H9) -> 0
A10: 1500 | B10: 3. | C10: Earnings on Investments | D10: 0 | E10: 0 | F10: 0 | G10: 0 | H10: 0 | I10: =SUM(G10+H10) -> 0
A11: 3110 | B11: 4. | C11: State Equalization | D11: 0 | E11: 0 | F11: 0 | G11: 0 | H11: 0 | I11: =SUM(G11+H11) -> 0
A12: 52XX | B12: 5. | C12: Transfer From(+)/To(-)________________Fund(s) (Net to zero across all funds)* NOTE-1 | D12: 0 | E12: 0 | F12: 0 | G12: 0 | H12: 0 | I12: =SUM(G12+H12) -> 0
A13: 5600 | B13: 6. | C13: Allocation From General Fund** (Optional starting in FY09-10) | D13: 0 | E13: 0 | F13: 0 | G13: 0 | H13: 0 | I13: =SUM(G13+H13) -> 0
B14: 7. | C14: Other Revenue | D14: 0 | E14: 0 | F14: 0 | G14: 0 | H14: 0 | I14: =SUM(G14+H14) -> 0
B16: 8. | C16: TOTAL REVENUE (Sum of lines 1-7) | D16: =SUM(D8:D14) -> 0 | E16: =SUM(E8:E14) -> 0 | F16: =SUM(F8:F14) -> 0 | G16: =SUM(G8:G14) -> 0 | H16: =SUM(H8:H14) -> 0 | I16: =SUM(I8:I14) -> 0
A18: TOTAL REVENUE INCLUDING BEGINNING FUND BALANCE (Sum of line 8 and BFB) | D18: =D6+D16 -> 0 | E18: =E6+E16 -> 0 | F18: =F6+F16 -> 0 | G18: =G6+G16 -> 0 | H18: =H6+H16 -> 0 | I18: =I6+I16 -> 0
A20: NOTE-1: | C20: If you treat Transfers Out as an expenditure - report such amounts here:
A21: 52XX | B21: 5a | C21: Transfer To________________Fund(s) (input as a positive number on this line) | D21: 0 | E21: 0 | F21: 0 | G21: 0 | H21: 0 | I21: =SUM(G21+H21) -> 0
A24: Object | C24: EXPENDITURES AND OTHER USES
A25: 0520 | B25: 9. | C25: Insurance Premiums (typically Program 2600) | D25: 0 | E25: 0 | F25: 0 | G25: 0 | H25: 0 | I25: =SUM(G25+H25) -> 0
A26: 0521 | B26: 10. | C26: Liability Insurance (typically Program 2600) | D26: 0 | E26: 0 | F26: 0 | G26: 0 | H26: 0 | I26: =SUM(G26+H26) -> 0
A27: 0522 | B27: 11. | C27: Property Insurance - Program Code 2620 (or 2600) | D27: 0 | E27: 0 | F27: 0 | G27: 0 | H27: 0 | I27: =SUM(G27+H27) -> 0
A28: 0523 | B28: 12a | C28: Vehicle Insurance - Program Code 2650 (or 2600) | D28: 0 | E28: 0 | F28: 0 | G28: 0 | H28: 0 | I28: =SUM(G28+H28) -> 0
A29: 0523 | B29: 12b | C29: Vehicle Insurance - Program Code 2720 (or 2700) | D29: 0 | E29: 0 | F29: 0 | G29: 0 | H29: 0 | I29: =SUM(G29+H29) -> 0
A30: 0523 | B30: 12c | C30: Vehicle Insurance - Program Code 3130 (or 3100) | D30: 0 | E30: 0 | F30: 0 | G30: 0 | H30: 0 | I30: =SUM(G30+H30) -> 0
A31: 0524 | B31: 13. | C31: Fidelity Insurance - Program Code 2850 (or 2800) | D31: 0 | E31: 0 | F31: 0 | G31: 0 | H31: 0 | I31: =SUM(G31+H31) -> 0
A32: 0525 | B32: 14. | C32: Unemployment Compensation Insurance - Program Code 2850 (or 2800) | D32: 0 | E32: 0 | F32: 0 | G32: 0 | H32: 0 | I32: =SUM(G32+H32) -> 0
A33: 0526 | B33: 15. | C33: Workers' Compensation Insurance - Program Code 2850 (or 2800) | D33: 0 | E33: 0 | F33: 0 | G33: 0 | H33: 0 | I33: =SUM(G33+H33) -> 0
A34: 0527 | B34: 16. | C34: District Multiple-Coverage &/or Other Insurance - Program Code 2850 (or 2800) | D34: 0 | E34: 0 | F34: 0 | G34: 0 | H34: 0 | I34: =SUM(G34+H34) -> 0
A35: 0528 | B35: 17. | C35: District Student Insurance - Program Code 2850 (or 2800) | D35: 0 | E35: 0 | F35: 0 | G35: 0 | H35: 0 | I35: =SUM(G35+H35) -> 0
C36: Transfers Out if reported as an expenditure - Linked from line 5a above | D36: =+D21 -> 0 | E36: =+E21 -> 0 | F36: =+F21 -> 0 | G36: =+G21 -> 0 | H36: =+H21 -> 0 | I36: =+I21 -> 0
B37: 20. | C37: Other Expenditures (Program 2600) | D37: 0 | E37: 0 | F37: 0 | G37: 0 | H37: 0 | I37: =SUM(G37+H37) -> 0
B39: 21. | C39: TOTAL EXPENDITURES & OTHER USES (Sum of lines 9-20) | D39: =SUM(D25:D37) -> 0 | E39: =SUM(E25:E37) -> 0 | F39: =SUM(F25:F37) -> 0 | G39: =SUM(G25:G37) -> 0 | H39: =SUM(H25:H37) -> 0 | I39: =SUM(I25:I37) -> 0
A41: Program | C41: APPROPRIATED RESERVES
A42: 9100 | B42: 22. | C42: Operating Reserve | D42: 0 | E42: 0 | F42: 0 | G42: 0 | H42: 0 | I42: =SUM(G42+H42) -> 0
A43: 9310 | B43: 23. | C43: TABOR Emergency Reserve | D43: 0 | E43: 0 | F43: 0 | G43: 0 | H43: 0 | I43: =SUM(G43+H43) -> 0
A44: 9320 | B44: 24. | C44: Reserve for Multi-Year Obligations | D44: 0 | E44: 0 | F44: 0 | G44: 0 | H44: 0 | I44: =SUM(G44+H44) -> 0
A45: 932X | B45: 25. | C45: Other Restricted Reserves | D45: 0 | E45: 0 | F45: 0 | G45: 0 | H45: 0 | I45: =SUM(G45+H45) -> 0
A46: 9900 | B46: 26. | C46: Other Reserves | D46: 0 | E46: 0 | F46: 0 | G46: 0 | H46: 0 | I46: =SUM(G46+H46) -> 0
B47: 27. | C47: TOTAL APPROPRIATED RESERVES (Sum of 22 - 26) | D47: =SUM(D42:D46) -> 0 | E47: =SUM(E42:E46) -> 0 | F47: =SUM(F42:F46) -> 0 | G47: =SUM(G42:G46) -> 0 | H47: =SUM(H42:H46) -> 0 | I47: =SUM(I42:I46) -> 0
A49: TOTAL INSURANCE RESERVE SPECIAL REVENUE FUND EXPENDITURES AND APPROPRIATED RESERVES Sum of lines 21 & 27) | D49: =D39+D47 -> 0 | E49: =E39+E47 -> 0 | F49: =F39+F47 -> 0 | G49: =G39+G47 -> 0 | H49: =H39+H47 -> 0 | I49: =G49+H49 -> 0
C50: ---MUST EQUAL AMOUNT ON APPROPRIATION RESOLUTION PAGE---
C52: TOTAL NET REVENUE | D52: =D18 -> 0 | E52: =E18 -> 0 | F52: =F18 -> 0 | G52: =G18 -> 0 | H52: =H18 -> 0 | I52: =G52+H52 -> 0
C54: DIFFERENCE MUST EQUAL 0 | D54: =D49-D52 -> 0 | E54: =E49-E52 -> 0 | F54: =F49-F52 -> 0 | G54: =G49-G52 -> 0 | H54: =H49-H52 -> 0 | I54: =I49-I52 -> 0
A59: *Transfers should only be made to/from funds 21 - Capital Reserve Fund or 43 - Capital Reserve Capital Projects Fund
A61: **The ALLOCATION FROM GENERAL FUND ON LINE 7 MUST BE INCLUDED IN THE AMOUNT ON LINE 83 or LINE 83a OF GENERAL FUND REVENUE.
A63: Please Note: Object codes 0520 through 0529 are non-bolded codes that roll to the bolded "0500 - Other Purchased Services" in the Automated Data Exchange.

Sheet CPP Fund
A1: School District | C1: =+'Page 1 - FY2013-14'!B5 -> 0 | D1: District Code | E1: =+'Page 1 - FY2013-14'!F7 -> 0 | G1: * Round to Nearest Dollar *
A2: Fund 19: Colorado Pre-School Fund
D3: Prior Year Actual - Audited FY11-12 | E3: Current Fiscal Year - Budgeted FY12-13 | F3: Current Fiscal Year - Projected FY12-13 | G3: Original Ensuing Fiscal Year - Budget FY13-14 | H3: Adjustments Ensuing Fiscal Year - Budget FY13-14 | I3: Revised Ensuing Fiscal Year - Budget FY13-14
H4: Record Inceases to revenue are positive amounts and Decreases as negatives | I4: Figures (Totals) which will appear on Budget Form to Submit to CDE
A7: Codes: | B7: BEGINNING FUND BALANCE | D7: 0 | E7: 0 | F7: 0 | G7: 0 | H7: 0 | I7: =G7+H7 -> 0
A8: Source | C8: REVENUE AND OTHER SOURCES
A9: 1000-1999 | B9: 1. | C9: Local Sources | D9: 0 | E9: 0 | F9: 0 | G9: 0 | H9: 0 | I9: =G9+H9 -> 0
A10: 2000-2999 | B10: 2. | C10: Intermediate Sources | D10: 0 | E10: 0 | F10: 0 | G10: 0 | H10: 0 | I10: =G10+H10 -> 0
A11: 3000-3999 | B11: 3. | C11: State Sources | D11: 0 | E11: 0 | F11: 0 | G11: 0 | H11: 0 | I11: =G11+H11 -> 0
A12: 4000-4999 | B12: 4. | C12: Federal Sources | D12: 0 | E12: 0 | F12: 0 | G12: 0 | H12: 0 | I12: =G12+H12 -> 0
A13: 52XX | B13: 5. | C13: Transfer From(+)/To(-)________________Fund(s) (Net to zero across all funds)* NOTE-1 | D13: 0 | E13: 0 | F13: 0 | G13: 0 | H13: 0 | I13: =G13+H13 -> 0
A14: 5810 | B14: 6. | C14: Allocation from the General Fund** | D14: 0 | E14: 0 | F14: 0 | G14: 0 | H14: 0 | I14: =G14+H14 -> 0
B15: 7. | C15: Other Revenue | D15: 0 | E15: 0 | F15: 0 | G15: 0 | H15: 0 | I15: =G15+H15 -> 0
B17: 8. | C17: TOTAL REVENUE (sum of lines 1 - 7) | D17: =SUM(D8:D15) -> 0 | E17: =SUM(E8:E15) -> 0 | F17: =SUM(F8:F15) -> 0 | G17: =SUM(G8:G15) -> 0 | H17: =SUM(H8:H15) -> 0 | I17: =SUM(I8:I15) -> 0
A19: TOTAL REVENUE INCLUDING BEGINNING FUND BALANCE (sum of line 8 & BFB) | D19: =D7+D17 -> 0 | E19: =E7+E17 -> 0 | F19: =F7+F17 -> 0 | G19: =G7+G17 -> 0 | H19: =H7+H17 -> 0 | I19: =I7+I17 -> 0
A21: NOTE-1: | C21: If you treat Transfers Out as an expenditure - report such amounts here:
A22: 52XX | B22: 5a | C22: Transfer To________________Fund(s) (input as a positive number on this line) * | D22: 0 | E22: 0 | F22: 0 | G22: 0 | H22: 0 | I22: =SUM(G22+H22) -> 0
C25: EXPENDITURES AND OTHER USES
A26: Object | C26: INSTRUCTIONAL PROGRAM - (PROGRAM CODE 0040 IS RECOMMENDED FOR USE IN FUND 19)
A27: 0040 - General Pre-School Education
A28: 0100 | B28: 9. | C28: Salaries - from staff details tab | D28: 0 | E28: 0 | F28: 0 | G28: {=SUM(IF(CertFund&CertProg&CertObj=RIGHT(LEFT($A$2,7),2)&LEFT(A27,4)&A28,CertSalary))} -> 0 | H28: 0 | I28: =SUM(G28+H28) -> 0
A29: 0100 | B29: 9. | C29: Salaries - additional items | D29: 0 | E29: 0 | F29: 0 | G29: 0 | H29: 0 | I29: =SUM(G29+H29) -> 0
A30: 0200 | B30: 10. | C30: Employee Benefits - staff details tab | D30: 0 | E30: 0 | F30: 0 | G30: {=SUM(IF(CertFund&CertProg&CertObj=RIGHT(LEFT($A$2,7),2)&LEFT(A27,4)&A28,CertBen))} -> 0 | H30: 0 | I30: =SUM(G30+H30) -> 0
A31: 0200 | B31: 10. | C31: Employee Benefits - addl items | D31: 0 | E31: 0 | F31: 0 | G31: 0 | H31: 0 | I31: =SUM(G31+H31) -> 0
A32: 0300 | B32: 11. | C32: Purchased Professional & Technical Services | D32: 0 | E32: 0 | F32: 0 | G32: 0 | H32: 0 | I32: =G32+H32 -> 0
A33: 0400 | B33: 12. | C33: Purchased Property Services | D33: 0 | E33: 0 | F33: 0 | G33: 0 | H33: 0 | I33: =G33+H33 -> 0
A34: 0430 | B34: 13. | C34: Repairs & Maintenance Services | D34: 0 | E34: 0 | F34: 0 | G34: 0 | H34: 0 | I34: =G34+H34 -> 0
A35: 0442 | B35: 14. | C35: Rental of Equipment | D35: 0 | E35: 0 | F35: 0 | G35: 0 | H35: 0 | I35: =G35+H35 -> 0
A36: 0500 | B36: 15. | C36: Other Purchased Services | D36: 0 | E36: 0 | F36: 0 | G36: 0 | H36: 0 | I36: =G36+H36 -> 0
A37: 0513 | B37: 16. | C37: Contracted Field Trips | D37: 0 | E37: 0 | F37: 0 | G37: 0 | H37: 0 | I37: =G37+H37 -> 0
A38: 0519 | B38: 17. | C38: Other Purchased Student Transportation | D38: 0 | E38: 0 | F38: 0 | G38: 0 | H38: 0 | I38: =G38+H38 -> 0
A39: 0561 | B39: 18. | C39: Tuition Paid Within the BOCES or AU | D39: 0 | E39: 0 | F39: 0 | G39: 0 | H39: 0 | I39: =G39+H39 -> 0
A40: 0562 | B40: 19. | C40: Tuition Paid to Other Colorado Districts, BOCES or AU | D40: 0 | E40: 0 | F40: 0 | G40: 0 | H40: 0 | I40: =G40+H40 -> 0
A41: 0563 | B41: 20. | C41: Tuition to School Districts Outside The State | D41: 0 | E41: 0 | F41: 0 | G41: 0 | H41: 0 | I41: =G41+H41 -> 0
A42: 0564 | B42: 21. | C42: Tuition To Private Sources | D42: 0 | E42: 0 | F42: 0 | G42: 0 | H42: 0 | I42: =G42+H42 -> 0
A43: 0565 | B43: 22. | C43: Tuition to Agencies with Colorado Dept. of Ed. - Approved Rates | D43: 0 | E43: 0 | F43: 0 | G43: 0 | H43: 0 | I43: =G43+H43 -> 0
... A59: 0851 | B59: 38. | C59: Transportation/Field Trips | D59: 0 | E59: 0 | F59: 0 | G59: 0 | H59: 0 | I59: =G59+H59 -> 0
B61: 39. | C61: Total Instructional Program Expenditures (Sum of lines 9-38) | D61: =SUM(D28:D59) -> 0 | E61: =SUM(E28:E59) -> 0 | F61: =SUM(F28:F59) -> 0 | G61: =SUM(G28:G59) -> 0 | H61: =SUM(H28:H59) -> 0 | I61: =SUM(I28:I59) -> 0
C63: SUPPORT PROGRAMS - 2100 THROUGH 3300
A64: 2100 - Students
A65: 2200 - Instructional Staff
A66: 2220 - Educational Library Services
A67: 2300 - General Administration
A68: 2400 - School Administration
A69: 2500 - Business Services
A70: 2600 - Operations and Maintenance
A71: 2700 - Student Transportation
A72: 2800 - Central Support
A73: 2900 - Other Support
A74: 3300 - Community Services
A75: 0100 | B75: 9. | C75: Salaries - from staff details tab | D75: 0 | E75: 0 | F75: 0 | G75: {=SUM(IF(CertFund&CertProg&CertObj=RIGHT(LEFT($A$2,7),2)&LEFT(A64,4)&A75,CertSalary))+SUM(IF(CertFund&CertProg&CertObj=RIGHT(LEFT($A$2,7),2)&LEFT(A65,4)&A75,CertSalary))+SUM(IF(CertFund&CertProg&CertObj=RIGHT(LEFT($A$2,7),2)&LEFT(A66,4)&A75,CertSalary))+SUM(IF(CertFund&CertProg&CertObj=RIGHT(LEFT($A$2,7),2)&LEFT(A67,4)&A75,CertSalary))+SUM(IF(CertFund&CertProg&CertObj=RIGHT(LEFT($A$2,7),2)&LEFT(A68,4)&A75,CertSalary))+SUM(IF(CertFund&CertProg&CertObj=RIGHT(LEFT($A$2,7),2)&LEFT(A69,4)&A75,CertSalary))+SUM(IF(CertFund&CertProg&CertObj=RIGHT(LEFT($A$2,7),2)&LEFT(A70,4)&A75,CertSalary))+SUM(IF(CertFund&CertProg&CertObj=RIGHT(LEFT($A$2,7),2)&LEFT(A71,4)&A75,CertSalary))+SUM(IF(CertFund&CertProg&CertObj=RIGHT(LEFT($A$2,7),2)&LEFT(A72,4)&A75,CertSalary))+SUM(IF(CertFund&CertProg&CertObj=RIGHT(LEFT($A$2,7),2)&LEFT(A73,4)&A75,CertSalary))+SUM(IF(CertFund&CertProg&CertObj=RIGHT(LEFT($A$2,7),2)&LEFT(A74,4)&A75,CertSalary))} -> 0 | H75: 0 | I75: =SUM(G75+H75) -> 0
A76: 0100 | B76: 9. | C76: Salaries - additional items | D76: 0 | E76: 0 | F76: 0 | G76: 0 | H76: 0 | I76: =SUM(G76+H76) -> 0
A77: 0200 | B77: 10. | C77: Employee Benefits - staff details tab | D77: 0 | E77: 0 | F77: 0 | G77: {=SUM(IF(CertFund&CertProg&CertObj=RIGHT(LEFT($A$2,7),2)&LEFT(A64,4)&A75,CertBen))+SUM(IF(CertFund&CertProg&CertObj=RIGHT(LEFT($A$2,7),2)&LEFT(A65,4)&A75,CertBen))+SUM(IF(CertFund&CertProg&CertObj=RIGHT(LEFT($A$2,7),2)&LEFT(A66,4)&A75,CertBen))+SUM(IF(CertFund&CertProg&CertObj=RIGHT(LEFT($A$2,7),2)&LEFT(A67,4)&A75,CertBen))+SUM(IF(CertFund&CertProg&CertObj=RIGHT(LEFT($A$2,7),2)&LEFT(A68,4)&A75,CertBen))+SUM(IF(CertFund&CertProg&CertObj=RIGHT(LEFT($A$2,7),2)&LEFT(A69,4)&A75,CertBen))+SUM(IF(CertFund&CertProg&CertObj=RIGHT(LEFT($A$2,7),2)&LEFT(A70,4)&A75,CertBen))+SUM(IF(CertFund&CertProg&CertObj=RIGHT(LEFT($A$2,7),2)&LEFT(A71,4)&A75,CertBen))+SUM(IF(CertFund&CertProg&CertObj=RIGHT(LEFT($A$2,7),2)&LEFT(A72,4)&A75,CertBen))+SUM(IF(CertFund&CertProg&CertObj=RIGHT(LEFT($A$2,7),2)&LEFT(A73,4)&A75,CertBen))+SUM(IF(CertFund&CertProg&CertObj=RIGHT(LEFT($A$2,7),2)&LEFT(A75,4)&A75,CertBen))} -> 0 | H77: 0 | I77: =SUM(G77+H77) -> 0
A78: 0200 | B78: 10. | C78: Employee Benefits - addl items | D78: 0 | E78: 0 | F78: 0 | G78: 0 | H78: 0 | I78: =SUM(G78+H78) -> 0
A79: 0300 | B79: 42. | C79: Purchased Professional & Technical Services | D79: 0 | E79: 0 | F79: 0 | G79: 0 | H79: 0 | I79: =G79+H79 -> 0
A80: 0400 | B80: 43. | C80: Purchased Property Services | D80: 0 | E80: 0 | F80: 0 | G80: 0 | H80: 0 | I80: =G80+H80 -> 0
A81: 0430 | B81: 44. | C81: Repairs & Maintenance Services | D81: 0 | E81: 0 | F81: 0 | G81: 0 | H81: 0 | I81: =G81+H81 -> 0
A82: 0442 | B82: 45. | C82: Rental of Equipment | D82: 0 | E82: 0 | F82: 0 | G82: 0 | H82: 0 | I82: =G82+H82 -> 0
A83: 0500 | B83: 46. | C83: Other Purchased Services | D83: 0 | E83: 0 | F83: 0 | G83: 0 | H83: 0 | I83: =G83+H83 -> 0
A84: 0511 | B84: 47. | C84: Student Transportation Purchased Within the BOCES or AU | D84: 0 | E84: 0 | F84: 0 | G84: 0 | H84: 0 | I84: =G84+H84 -> 0
A85: 0512 | B85: 48. | C85: Student Transportation Purchased from Other Colorado Districts, BOCES or AU | D85: 0 | E85: 0 | F85: 0 | G85: 0 | H85: 0 | I85: =G85+H85 -> 0
A86: 0513 | B86: 49. | C86: Contracted Field Trips | D86: 0 | E86: 0 | F86: 0 | G86: 0 | H86: 0 | I86: =G86+H86 -> 0
A87: 0514 | B87: 50. | C87: Student Transportation Purchased from Parents | D87: 0 | E87: 0 | F87: 0 | G87: 0 | H87: 0 | I87: =G87+H87 -> 0
A88: 0515 | B88: 51. | C88: Student Transportation Purchased from Contractors | D88: 0 | E88: 0 | F88: 0 | G88: 0 | H88: 0 | I88: =G88+H88 -> 0
A89: 0517 | B89: 52. | C89: Student Transportation Purchased from School District Outside the State | D89: 0 | E89: 0 | F89: 0 | G89: 0 | H89: 0 | I89: =G89+H89 -> 0
A90: 0519 | B90: 53. | C90: Other Purchased Student Transportation | D90: 0 | E90: 0 | F90: 0 | G90: 0 | H90: 0 | I90: =G90+H90 -> 0
... A109: 0869 | B109: 72. | C109: Indirect Costs | D109: 0 | E109: 0 | F109: 0 | G109: 0 | H109: 0 | I109: =G109+H109 -> 0
B111: 73. | C111: Total Support Program Expenditures (Sum of lines 40-72) | D111: =SUM(D75:D109) -> 0 | E111: =SUM(E75:E109) -> 0 | F111: =SUM(F75:F109) -> 0 | G111: =SUM(G75:G109) -> 0 | H111: =SUM(H75:H109) -> 0 | I111: =SUM(I75:I109) -> 0
A113: 0100-0899 | B113: 74. | C113: OTHER USES - PROGRAM 5000 | D113: 0 | E113: 0 | F113: 0 | G113: 0 | H113: 0 | I113: =G113+H113 -> 0
B114: 74a | C114: Transfers Out if reported as an expenditure - Linked from line 5a above | D114: =+D22 -> 0 | E114: =+E22 -> 0 | F114: =+F22 -> 0 | G114: =+G22 -> 0 | H114: =+H22 -> 0 | I114: =+I22 -> 0
B116: 75. | C116: TOTAL EXPENDITURES AND OTHER USES (Sum of lines 39, 73, 74 & 74a) | D116: =D61+D111+D113+D114 -> 0 | E116: =E61+E111+E113+E114 -> 0 | F116: =F61+F111+F113+F114 -> 0 | G116: =G61+G111+G113+G114 -> 0 | H116: =H61+H111+H113+H114 -> 0 | I116: =I61+I111+I113+I114 -> 0
A119: Program | C119: APPROPRIATED RESERVES
A120: 9100 | B120: 76. | C120: Operating Reserve | D120: 0 | E120: 0 | F120: 0 | G120: 0 | H120: 0 | I120: =G120+H120 -> 0
A121: 9310 | B121: 77. | C121: TABOR Emergency Reserve | D121: 0 | E121: 0 | F121: 0 | G121: 0 | H121: 0 | I121: =G121+H121 -> 0
A122: 9320 | B122: 78. | C122: Reserve for Multi-Year Obligations | D122: 0 | E122: 0 | F122: 0 | G122: 0 | H122: 0 | I122: =G122+H122 -> 0
A123: 932X | B123: 79. | C123: Other Restricted Reserves | D123: 0 | E123: 0 | F123: 0 | G123: 0 | H123: 0 | I123: =G123+H123 -> 0
A124: 9900 | B124: 80. | C124: Other Reserves | D124: 0 | E124: 0 | F124: 0 | G124: 0 | H124: 0 | I124: =G124+H124 -> 0
B125: 81. | C125: TOTAL APPROPRIATED RESERVES (Sum of lines 76-80) | D125: =SUM(D120:D124) -> 0 | E125: =SUM(E120:E124) -> 0 | F125: =SUM(F120:F124) -> 0 | G125: =SUM(G120:G124) -> 0 | H125: =SUM(H120:H124) -> 0 | I125: =SUM(I120:I124) -> 0
A127: TOTAL CPP FUND EXPENDITURES AND APPROPRIATED RESERVES(Sum of lines 75 & 81) | D127: =D116+D125 -> 0 | E127: =E116+E125 -> 0 | F127: =F116+F125 -> 0 | G127: =G116+G125 -> 0 | H127: =H116+H125 -> 0 | I127: =I116+I125 -> 0
C128: ---MUST EQUAL AMOUNT ON APPROPRIATION RESOLUTION PAGE---
C130: TOTAL NET REVENUE | D130: =D19 -> 0 | E130: =E19 -> 0 | F130: =F19 -> 0 | G130: =G19 -> 0 | H130: =H19 -> 0 | I130: =I19 -> 0
C132: DIFFERENCE MUST EQUAL 0 | D132: =D127-D130 -> 0 | E132: =E127-E130 -> 0 | F132: =F127-F130 -> 0 | G132: =G127-G130 -> 0 | H132: =H127-H130 -> 0 | I132: =I127-I130 -> 0
A135: * Additional funds may be transferred from General fund to cover program expenditures in excess of Pre-School Allocation.
A136: * Transfers Out are limited to the closing of this fund only.
A137: **The Allocation from the General Fund on line 6 must equal the amount on line 85 or line 85a of General Fund Revenues

Sheet Fund 20 Grants
D1: =IF(D3>4000,300,IF(D3>3000,200,100)) -> 100 | E1: =IF(E3>4000,300,IF(E3>3000,200,100)) -> 100 | F1: =IF(F3>4000,300,IF(F3>3000,200,100)) -> 100 | G1: =IF(G3>4000,300,IF(G3>3000,200,100)) -> 100 | H1: =IF(H3>4000,300,IF(H3>3000,200,100)) -> 100 | I1: =IF(I3>4000,300,IF(I3>3000,200,100)) -> 100 | J1: =IF(J3>4000,300,IF(J3>3000,200,100)) -> 100 | K1: =IF(K3>4000,300,IF(K3>3000,200,100)) -> 100 | ... W1: =IF(W3>4000,300,IF(W3>3000,200,100)) -> 100
A2: Fund 20: ARRA (Federal Stimulus Funding) Grants Fund FY 2009-2010 | D2: =D1+COUNTIF($D$1:D$1,D1) -> 101 | E2: =E1+COUNTIF($D$1:E$1,E1) -> 102 | F2: =F1+COUNTIF($D$1:F$1,F1) -> 103 | G2: =G1+COUNTIF($D$1:G$1,G1) -> 104 | H2: =H1+COUNTIF($D$1:H$1,H1) -> 105 | I2: =I1+COUNTIF($D$1:I$1,I1) -> 106 | J2: =J1+COUNTIF($D$1:J$1,J1) -> 107 | K2: =K1+COUNTIF($D$1:K$1,K1) -> 108 | ... W2: =W1+COUNTIF($D$1:W$1,W1) -> 120
C3: Input the Grant Code on row 3 and the description on row 4
A4: Line | B4: Object | C4: Description | X4: Total
A7: 1 | C7: Current Year Allocation | D7: 0 | E7: 0 | F7: 0 | G7: 0 | H7: 0 | I7: 0 | J7: 0 | K7: 0 | L7: 0 | M7: 0 | N7: 0 | O7: 0 | P7: 0 | Q7: 0 | R7: 0 | S7: 0 | T7: 0 | U7: 0 | V7: 0 | W7: 0 | X7: =SUM(D7:W7) -> 0
A8: 2a | C8: Grant Transfer Activity IN (source code 53xx) - subject to limitations | D8: 0 | E8: 0 | F8: 0 | G8: 0 | H8: 0 | I8: 0 | J8: 0 | K8: 0 | L8: 0 | M8: 0 | N8: 0 | O8: 0 | P8: 0 | Q8: 0 | R8: 0 | S8: 0 | T8: 0 | U8: 0 | V8: 0 | W8: 0 | X8: =SUM(D8:W8) -> 0
A9: 2b | C9: Grant Transfer Activity OUT (source code 53xx) - subject to limitations | D9: 0 | E9: 0 | F9: 0 | G9: 0 | H9: 0 | I9: 0 | J9: 0 | K9: 0 | L9: 0 | M9: 0 | N9: 0 | O9: 0 | P9: 0 | Q9: 0 | R9: 0 | S9: 0 | T9: 0 | U9: 0 | V9: 0 | W9: 0 | X9: =SUM(D9:W9) -> 0
A10: 3 | C10: Prior Year Carryover | D10: 0 | E10: 0 | F10: 0 | G10: 0 | H10: 0 | I10: 0 | J10: 0 | K10: 0 | L10: 0 | M10: 0 | N10: 0 | O10: 0 | P10: 0 | Q10: 0 | R10: 0 | S10: 0 | T10: 0 | U10: 0 | V10: 0 | W10: 0 | X10: =SUM(D10:W10) -> 0
A11: 3a
A12: 4 | C12: Total Funds Available (lines 1, 2 ,3) | D12: =SUM(D7:D10) -> 0 | E12: =SUM(E7:E10) -> 0 | F12: =SUM(F7:F10) -> 0 | G12: =SUM(G7:G10) -> 0 | H12: =SUM(H7:H10) -> 0 | I12: =SUM(I7:I10) -> 0 | J12: =SUM(J7:J10) -> 0 | K12: =SUM(K7:K10) -> 0 | ... W12: =SUM(W7:W10) -> 0 | X12: =SUM(D12:W12) -> 0
A13: 0010 - Elementary Instructional Program
A14: 5 | B14: 0100 | C14: Salaries - from staff details tab | D14: {=SUM(IF(CertFund&CertProg&CertObj&CertGrant=RIGHT(LEFT($A$2,7),2)&LEFT($A$13,4)&$B$14&D$3,CertSalary))} -> 0 | E14: {=SUM(IF(CertFund&CertProg&CertObj&CertGrant=RIGHT(LEFT($A$2,7),2)&LEFT($A$13,4)&$B$14&E$3,CertSalary))} -> 0 | F14: {=SUM(IF(CertFund&CertProg&CertObj&CertGrant=RIGHT(LEFT($A$2,7),2)&LEFT($A$13,4)&$B$14&F$3,CertSalary))} -> 0 | G14: {=SUM(IF(CertFund&CertProg&CertObj&CertGrant=RIGHT(LEFT($A$2,7),2)&LEFT($A$13,4)&$B$14&G$3,CertSalary))} -> 0 | H14: {=SUM(IF(CertFund&CertProg&CertObj&CertGrant=RIGHT(LEFT($A$2,7),2)&LEFT($A$13,4)&$B$14&H$3,CertSalary))} -> 0 | I14: {=SUM(IF(CertFund&CertProg&CertObj&CertGrant=RIGHT(LEFT($A$2,7),2)&LEFT($A$13,4)&$B$14&I$3,CertSalary))} -> 0 | J14: {=SUM(IF(CertFund&CertProg&CertObj&CertGrant=RIGHT(LEFT($A$2,7),2)&LEFT($A$13,4)&$B$14&J$3,CertSalary))} -> 0 | K14: {=SUM(IF(CertFund&CertProg&CertObj&CertGrant=RIGHT(LEFT($A$2,7),2)&LEFT($A$13,4)&$B$14&K$3,CertSalary))} -> 0 | ... W14: {=SUM(IF(CertFund&CertProg&CertObj&CertGrant=RIGHT(LEFT($A$2,7),2)&LEFT($A$13,4)&$B$14&W$3,CertSalary))} -> 0 | X14: =SUM(D14:W14) -> 0
A15: 5a | B15: 0100 | C15: Salaries - additional items | D15: 0 | E15: 0 | F15: 0 | G15: 0 | H15: 0 | I15: 0 | J15: 0 | K15: 0 | L15: 0 | M15: 0 | N15: 0 | O15: 0 | P15: 0 | Q15: 0 | R15: 0 | S15: 0 | T15: 0 | U15: 0 | V15: 0 | W15: 0 | X15: =SUM(D15:W15) -> 0
A16: 6 | B16: 0200 | C16: Employee Benefits - staff benefits tab | D16: {=SUM(IF(CertFund&CertProg&CertObj&CertGrant=RIGHT(LEFT($A$2,7),2)&LEFT($A$13,4)&$B$14&D$3,CertBen))} -> 0 | E16: {=SUM(IF(CertFund&CertProg&CertObj&CertGrant=RIGHT(LEFT($A$2,7),2)&LEFT($A$13,4)&$B$14&E$3,CertBen))} -> 0 | F16: {=SUM(IF(CertFund&CertProg&CertObj&CertGrant=RIGHT(LEFT($A$2,7),2)&LEFT($A$13,4)&$B$14&F$3,CertBen))} -> 0 | G16: {=SUM(IF(CertFund&CertProg&CertObj&CertGrant=RIGHT(LEFT($A$2,7),2)&LEFT($A$13,4)&$B$14&G$3,CertBen))} -> 0 | H16: {=SUM(IF(CertFund&CertProg&CertObj&CertGrant=RIGHT(LEFT($A$2,7),2)&LEFT($A$13,4)&$B$14&H$3,CertBen))} -> 0 | I16: {=SUM(IF(CertFund&CertProg&CertObj&CertGrant=RIGHT(LEFT($A$2,7),2)&LEFT($A$13,4)&$B$14&I$3,CertBen))} -> 0 | J16: {=SUM(IF(CertFund&CertProg&CertObj&CertGrant=RIGHT(LEFT($A$2,7),2)&LEFT($A$13,4)&$B$14&J$3,CertBen))} -> 0 | K16: {=SUM(IF(CertFund&CertProg&CertObj&CertGrant=RIGHT(LEFT($A$2,7),2)&LEFT($A$13,4)&$B$14&K$3,CertBen))} -> 0 | ... W16: {=SUM(IF(CertFund&CertProg&CertObj&CertGrant=RIGHT(LEFT($A$2,7),2)&LEFT($A$13,4)&$B$14&W$3,CertBen))} -> 0 | X16: =SUM(D16:W16) -> 0
A17: 6a | B17: 0200 | C17: Employee Benefits - addl items | D17: 0 | E17: 0 | F17: 0 | G17: 0 | H17: 0 | I17: 0 | J17: 0 | K17: 0 | L17: 0 | M17: 0 | N17: 0 | O17: 0 | P17: 0 | Q17: 0 | R17: 0 | S17: 0 | T17: 0 | U17: 0 | V17: 0 | W17: 0 | X17: =SUM(D17:W17) -> 0
A18: 7 | B18: 0300 | C18: Purchased Professional & Technical Services (0300) | D18: 0 | E18: 0 | F18: 0 | G18: 0 | H18: 0 | I18: 0 | J18: 0 | K18: 0 | L18: 0 | M18: 0 | N18: 0 | O18: 0 | P18: 0 | Q18: 0 | R18: 0 | S18: 0 | T18: 0 | U18: 0 | V18: 0 | W18: 0 | X18: =SUM(D18:W18) -> 0
A19: 8 | B19: 0500 | C19: Other Purchased Services (0500) | D19: 0 | E19: 0 | F19: 0 | G19: 0 | H19: 0 | I19: 0 | J19: 0 | K19: 0 | L19: 0 | M19: 0 | N19: 0 | O19: 0 | P19: 0 | Q19: 0 | R19: 0 | S19: 0 | T19: 0 | U19: 0 | V19: 0 | W19: 0 | X19: =SUM(D19:W19) -> 0
A20: 9 | B20: 0600 | C20: Supplies (0600) | D20: 0 | E20: 0 | F20: 0 | G20: 0 | H20: 0 | I20: 0 | J20: 0 | K20: 0 | L20: 0 | M20: 0 | N20: 0 | O20: 0 | P20: 0 | Q20: 0 | R20: 0 | S20: 0 | T20: 0 | U20: 0 | V20: 0 | W20: 0 | X20: =SUM(D20:W20) -> 0
A21: 10 | B21: 0800 | C21: Other (0800) | D21: 0 | E21: 0 | F21: 0 | G21: 0 | H21: 0 | I21: 0 | J21: 0 | K21: 0 | L21: 0 | M21: 0 | N21: 0 | O21: 0 | P21: 0 | Q21: 0 | R21: 0 | S21: 0 | T21: 0 | U21: 0 | V21: 0 | W21: 0 | X21: =SUM(D21:W21) -> 0
A22: 11 | C22: Subtotal 0010 - Elementary Instructional | D22: =SUM(D14:D21) -> 0 | E22: =SUM(E14:E21) -> 0 | F22: =SUM(F14:F21) -> 0 | G22: =SUM(G14:G21) -> 0 | H22: =SUM(H14:H21) -> 0 | I22: =SUM(I14:I21) -> 0 | J22: =SUM(J14:J21) -> 0 | K22: =SUM(K14:K21) -> 0 | ... W22: =SUM(W14:W21) -> 0 | X22: =SUM(D22:W22) -> 0
A23: 0020 - Middle School Instructional Program
A24: 5 | B24: 0100 | C24: Salaries - from staff details tab | D24: {=SUM(IF(CertFund&CertProg&CertObj&CertGrant=RIGHT(LEFT($A$2,7),2)&LEFT($A$23,4)&$B$24&D$3,CertSalary))} -> 0 | E24: {=SUM(IF(CertFund&CertProg&CertObj&CertGrant=RIGHT(LEFT($A$2,7),2)&LEFT($A$23,4)&$B$24&E$3,CertSalary))} -> 0 | F24: {=SUM(IF(CertFund&CertProg&CertObj&CertGrant=RIGHT(LEFT($A$2,7),2)&LEFT($A$23,4)&$B$24&F$3,CertSalary))} -> 0 | G24: {=SUM(IF(CertFund&CertProg&CertObj&CertGrant=RIGHT(LEFT($A$2,7),2)&LEFT($A$23,4)&$B$24&G$3,CertSalary))} -> 0 | H24: {=SUM(IF(CertFund&CertProg&CertObj&CertGrant=RIGHT(LEFT($A$2,7),2)&LEFT($A$23,4)&$B$24&H$3,CertSalary))} -> 0 | I24: {=SUM(IF(CertFund&CertProg&CertObj&CertGrant=RIGHT(LEFT($A$2,7),2)&LEFT($A$23,4)&$B$24&I$3,CertSalary))} -> 0 | J24: {=SUM(IF(CertFund&CertProg&CertObj&CertGrant=RIGHT(LEFT($A$2,7),2)&LEFT($A$23,4)&$B$24&J$3,CertSalary))} -> 0 | K24: {=SUM(IF(CertFund&CertProg&CertObj&CertGrant=RIGHT(LEFT($A$2,7),2)&LEFT($A$23,4)&$B$24&K$3,CertSalary))} -> 0 | ... W24: {=SUM(IF(CertFund&CertProg&CertObj&CertGrant=RIGHT(LEFT($A$2,7),2)&LEFT($A$23,4)&$B$24&W$3,CertSalary))} -> 0 | X24: =SUM(D24:W24) -> 0
A25: 5a | B25: 0100 | C25: Salaries - additional items | D25: 0 | E25: 0 | F25: 0 | G25: 0 | H25: 0 | I25: 0 | J25: 0 | K25: 0 | L25: 0 | M25: 0 | N25: 0 | O25: 0 | P25: 0 | Q25: 0 | R25: 0 | S25: 0 | T25: 0 | U25: 0 | V25: 0 | W25: 0 | X25: =SUM(D25:W25) -> 0
A26: 6 | B26: 0200 | C26: Employee Benefits - staff benefits tab | D26: {=SUM(IF(CertFund&CertProg&CertObj&CertGrant=RIGHT(LEFT($A$2,7),2)&LEFT($A$23,4)&$B$24&D$3,CertBen))} -> 0 | E26: {=SUM(IF(CertFund&CertProg&CertObj&CertGrant=RIGHT(LEFT($A$2,7),2)&LEFT($A$23,4)&$B$24&E$3,CertBen))} -> 0 | F26: {=SUM(IF(CertFund&CertProg&CertObj&CertGrant=RIGHT(LEFT($A$2,7),2)&LEFT($A$23,4)&$B$24&F$3,CertBen))} -> 0 | G26: {=SUM(IF(CertFund&CertProg&CertObj&CertGrant=RIGHT(LEFT($A$2,7),2)&LEFT($A$23,4)&$B$24&G$3,CertBen))} -> 0 | H26: {=SUM(IF(CertFund&CertProg&CertObj&CertGrant=RIGHT(LEFT($A$2,7),2)&LEFT($A$23,4)&$B$24&H$3,CertBen))} -> 0 | I26: {=SUM(IF(CertFund&CertProg&CertObj&CertGrant=RIGHT(LEFT($A$2,7),2)&LEFT($A$23,4)&$B$24&I$3,CertBen))} -> 0 | J26: {=SUM(IF(CertFund&CertProg&CertObj&CertGrant=RIGHT(LEFT($A$2,7),2)&LEFT($A$23,4)&$B$24&J$3,CertBen))} -> 0 | K26: {=SUM(IF(CertFund&CertProg&CertObj&CertGrant=RIGHT(LEFT($A$2,7),2)&LEFT($A$23,4)&$B$24&K$3,CertBen))} -> 0 | ... W26: {=SUM(IF(CertFund&CertProg&CertObj&CertGrant=RIGHT(LEFT($A$2,7),2)&LEFT($A$23,4)&$B$24&W$3,CertBen))} -> 0 | X26: =SUM(D26:W26) -> 0
A27: 6a | B27: 0200 | C27: Employee Benefits - addl items | D27: 0 | E27: 0 | F27: 0 | G27: 0 | H27: 0 | I27: 0 | J27: 0 | K27: 0 | L27: 0 | M27: 0 | N27: 0 | O27: 0 | P27: 0 | Q27: 0 | R27: 0 | S27: 0 | T27: 0 | U27: 0 | V27: 0 | W27: 0 | X27: =SUM(D27:W27) -> 0
A28: 7 | B28: 0300 | C28: Purchased Professional & Technical Services (0300) | D28: 0 | E28: 0 | F28: 0 | G28: 0 | H28: 0 | I28: 0 | J28: 0 | K28: 0 | L28: 0 | M28: 0 | N28: 0 | O28: 0 | P28: 0 | Q28: 0 | R28: 0 | S28: 0 | T28: 0 | U28: 0 | V28: 0 | W28: 0 | X28: =SUM(D28:W28) -> 0
A29: 8 | B29: 0500 | C29: Other Purchased Services (0500) | D29: 0 | E29: 0 | F29: 0 | G29: 0 | H29: 0 | I29: 0 | J29: 0 | K29: 0 | L29: 0 | M29: 0 | N29: 0 | O29: 0 | P29: 0 | Q29: 0 | R29: 0 | S29: 0 | T29: 0 | U29: 0 | V29: 0 | W29: 0 | X29: =SUM(D29:W29) -> 0
A30: 9 | B30: 0600 | C30: Supplies (0600) | D30: 0 | E30: 0 | F30: 0 | G30: 0 | H30: 0 | I30: 0 | J30: 0 | K30: 0 | L30: 0 | M30: 0 | N30: 0 | O30: 0 | P30: 0 | Q30: 0 | R30: 0 | S30: 0 | T30: 0 | U30: 0 | V30: 0 | W30: 0 | X30: =SUM(D30:W30) -> 0
A31: 10 | B31: 0800 | C31: Other (0800) | D31: 0 | E31: 0 | F31: 0 | G31: 0 | H31: 0 | I31: 0 | J31: 0 | K31: 0 | L31: 0 | M31: 0 | N31: 0 | O31: 0 | P31: 0 | Q31: 0 | R31: 0 | S31: 0 | T31: 0 | U31: 0 | V31: 0 | W31: 0 | X31: =SUM(D31:W31) -> 0
A32: 11 | C32: Subtotal 0020 - Middle School Instructional | D32: =SUM(D24:D31) -> 0 | E32: =SUM(E24:E31) -> 0 | F32: =SUM(F24:F31) -> 0 | G32: =SUM(G24:G31) -> 0 | H32: =SUM(H24:H31) -> 0 | I32: =SUM(I24:I31) -> 0 | J32: =SUM(J24:J31) -> 0 | K32: =SUM(K24:K31) -> 0 | ... W32: =SUM(W24:W31) -> 0 | X32: =SUM(D32:W32) -> 0
A33: 0060 - General Integrated Education Program
A34: 5 | B34: 0100 | C34: Salaries - from staff details tab | D34: {=SUM(IF(CertFund&CertProg&CertObj&CertGrant=RIGHT(LEFT($A$2,7),2)&LEFT($A$33,4)&$B$34&D$3,CertSalary))} -> 0 | E34: {=SUM(IF(CertFund&CertProg&CertObj&CertGrant=RIGHT(LEFT($A$2,7),2)&LEFT($A$33,4)&$B$34&E$3,CertSalary))} -> 0 | F34: {=SUM(IF(CertFund&CertProg&CertObj&CertGrant=RIGHT(LEFT($A$2,7),2)&LEFT($A$33,4)&$B$34&F$3,CertSalary))} -> 0 | G34: {=SUM(IF(CertFund&CertProg&CertObj&CertGrant=RIGHT(LEFT($A$2,7),2)&LEFT($A$33,4)&$B$34&G$3,CertSalary))} -> 0 | H34: {=SUM(IF(CertFund&CertProg&CertObj&CertGrant=RIGHT(LEFT($A$2,7),2)&LEFT($A$33,4)&$B$34&H$3,CertSalary))} -> 0 | I34: {=SUM(IF(CertFund&CertProg&CertObj&CertGrant=RIGHT(LEFT($A$2,7),2)&LEFT($A$33,4)&$B$34&I$3,CertSalary))} -> 0 | J34: {=SUM(IF(CertFund&CertProg&CertObj&CertGrant=RIGHT(LEFT($A$2,7),2)&LEFT($A$33,4)&$B$34&J$3,CertSalary))} -> 0 | K34: {=SUM(IF(CertFund&CertProg&CertObj&CertGrant=RIGHT(LEFT($A$2,7),2)&LEFT($A$33,4)&$B$34&K$3,CertSalary))} -> 0 | ... W34: {=SUM(IF(CertFund&CertProg&CertObj&CertGrant=RIGHT(LEFT($A$2,7),2)&LEFT($A$33,4)&$B$34&W$3,CertSalary))} -> 0 | X34: =SUM(D34:W34) -> 0
A35: 5a | B35: 0100 | C35: Salaries - additional items | D35: 0 | E35: 0 | F35: 0 | G35: 0 | H35: 0 | I35: 0 | J35: 0 | K35: 0 | L35: 0 | M35: 0 | N35: 0 | O35: 0 | P35: 0 | Q35: 0 | R35: 0 | S35: 0 | T35: 0 | U35: 0 | V35: 0 | W35: 0 | X35: =SUM(D35:W35) -> 0
A36: 6 | B36: 0200 | C36: Employee Benefits - staff benefits tab | D36: {=SUM(IF(CertFund&CertProg&CertObj&CertGrant=RIGHT(LEFT($A$2,7),2)&LEFT($A$33,4)&$B$34&D$3,CertBen))} -> 0 | E36: {=SUM(IF(CertFund&CertProg&CertObj&CertGrant=RIGHT(LEFT($A$2,7),2)&LEFT($A$33,4)&$B$34&E$3,CertBen))} -> 0 | F36: {=SUM(IF(CertFund&CertProg&CertObj&CertGrant=RIGHT(LEFT($A$2,7),2)&LEFT($A$33,4)&$B$34&F$3,CertBen))} -> 0 | G36: {=SUM(IF(CertFund&CertProg&CertObj&CertGrant=RIGHT(LEFT($A$2,7),2)&LEFT($A$33,4)&$B$34&G$3,CertBen))} -> 0 | H36: {=SUM(IF(CertFund&CertProg&CertObj&CertGrant=RIGHT(LEFT($A$2,7),2)&LEFT($A$33,4)&$B$34&H$3,CertBen))} -> 0 | I36: {=SUM(IF(CertFund&CertProg&CertObj&CertGrant=RIGHT(LEFT($A$2,7),2)&LEFT($A$33,4)&$B$34&I$3,CertBen))} -> 0 | J36: {=SUM(IF(CertFund&CertProg&CertObj&CertGrant=RIGHT(LEFT($A$2,7),2)&LEFT($A$33,4)&$B$34&J$3,CertBen))} -> 0 | K36: {=SUM(IF(CertFund&CertProg&CertObj&CertGrant=RIGHT(LEFT($A$2,7),2)&LEFT($A$33,4)&$B$34&K$3,CertBen))} -> 0 | ... W36: {=SUM(IF(CertFund&CertProg&CertObj&CertGrant=RIGHT(LEFT($A$2,7),2)&LEFT($A$33,4)&$B$34&W$3,CertBen))} -> 0 | X36: =SUM(D36:W36) -> 0
A37: 6a | B37: 0200 | C37: Employee Benefits - addl items | D37: 0 | E37: 0 | F37: 0 | G37: 0 | H37: 0 | I37: 0 | J37: 0 | K37: 0 | L37: 0 | M37: 0 | N37: 0 | O37: 0 | P37: 0 | Q37: 0 | R37: 0 | S37: 0 | T37: 0 | U37: 0 | V37: 0 | W37: 0 | X37: =SUM(D37:W37) -> 0
A38: 7 | B38: 0300 | C38: Purchased Professional & Technical Services (0300) | D38: 0 | E38: 0 | F38: 0 | G38: 0 | H38: 0 | I38: 0 | J38: 0 | K38: 0 | L38: 0 | M38: 0 | N38: 0 | O38: 0 | P38: 0 | Q38: 0 | R38: 0 | S38: 0 | T38: 0 | U38: 0 | V38: 0 | W38: 0 | X38: =SUM(D38:W38) -> 0
A39: 8 | B39: 0500 | C39: Other Purchased Services (0500) | D39: 0 | E39: 0 | F39: 0 | G39: 0 | H39: 0 | I39: 0 | J39: 0 | K39: 0 | L39: 0 | M39: 0 | N39: 0 | O39: 0 | P39: 0 | Q39: 0 | R39: 0 | S39: 0 | T39: 0 | U39: 0 | V39: 0 | W39: 0 | X39: =SUM(D39:W39) -> 0
A40: 9 | B40: 0600 | C40: Supplies (0600) | D40: 0 | E40: 0 | F40: 0 | G40: 0 | H40: 0 | I40: 0 | J40: 0 | K40: 0 | L40: 0 | M40: 0 | N40: 0 | O40: 0 | P40: 0 | Q40: 0 | R40: 0 | S40: 0 | T40: 0 | U40: 0 | V40: 0 | W40: 0 | X40: =SUM(D40:W40) -> 0
A41: 10 | B41: 0800 | C41: Other (0800) | D41: 0 | E41: 0 | F41: 0 | G41: 0 | H41: 0 | I41: 0 | J41: 0 | K41: 0 | L41: 0 | M41: 0 | N41: 0 | O41: 0 | P41: 0 | Q41: 0 | R41: 0 | S41: 0 | T41: 0 | U41: 0 | V41: 0 | W41: 0 | X41: =SUM(D41:W41) -> 0
A42: 11 | C42: Subtotal 0060 - General Integrated Education | D42: =SUM(D34:D41) -> 0 | E42: =SUM(E34:E41) -> 0 | F42: =SUM(F34:F41) -> 0 | G42: =SUM(G34:G41) -> 0 | H42: =SUM(H34:H41) -> 0 | I42: =SUM(I34:I41) -> 0 | J42: =SUM(J34:J41) -> 0 | K42: =SUM(K34:K41) -> 0 | ... W42: =SUM(W34:W41) -> 0 | X42: =SUM(D42:W42) -> 0
A43: 1600 - Technical Education/Computer Technology Program
A44: 5 | B44: 0100 | C44: Salaries - from staff details tab | D44: {=SUM(IF(CertFund&CertProg&CertObj&CertGrant=RIGHT(LEFT($A$2,7),2)&LEFT($A$43,4)&$B$44&D$3,CertSalary))} -> 0 | E44: {=SUM(IF(CertFund&CertProg&CertObj&CertGrant=RIGHT(LEFT($A$2,7),2)&LEFT($A$43,4)&$B$44&E$3,CertSalary))} -> 0 | F44: {=SUM(IF(CertFund&CertProg&CertObj&CertGrant=RIGHT(LEFT($A$2,7),2)&LEFT($A$43,4)&$B$44&F$3,CertSalary))} -> 0 | G44: {=SUM(IF(CertFund&CertProg&CertObj&CertGrant=RIGHT(LEFT($A$2,7),2)&LEFT($A$43,4)&$B$44&G$3,CertSalary))} -> 0 | H44: {=SUM(IF(CertFund&CertProg&CertObj&CertGrant=RIGHT(LEFT($A$2,7),2)&LEFT($A$43,4)&$B$44&H$3,CertSalary))} -> 0 | I44: {=SUM(IF(CertFund&CertProg&CertObj&CertGrant=RIGHT(LEFT($A$2,7),2)&LEFT($A$43,4)&$B$44&I$3,CertSalary))} -> 0 | J44: {=SUM(IF(CertFund&CertProg&CertObj&CertGrant=RIGHT(LEFT($A$2,7),2)&LEFT($A$43,4)&$B$44&J$3,CertSalary))} -> 0 | K44: {=SUM(IF(CertFund&CertProg&CertObj&CertGrant=RIGHT(LEFT($A$2,7),2)&LEFT($A$43,4)&$B$44&K$3,CertSalary))} -> 0 | ... W44: {=SUM(IF(CertFund&CertProg&CertObj&CertGrant=RIGHT(LEFT($A$2,7),2)&LEFT($A$43,4)&$B$44&W$3,CertSalary))} -> 0 | X44: =SUM(D44:W44) -> 0
A45: 5a | B45: 0100 | C45: Salaries - additional items | D45: 0 | E45: 0 | F45: 0 | G45: 0 | H45: 0 | I45: 0 | J45: 0 | K45: 0 | L45: 0 | M45: 0 | N45: 0 | O45: 0 | P45: 0 | Q45: 0 | R45: 0 | S45: 0 | T45: 0 | U45: 0 | V45: 0 | W45: 0 | X45: =SUM(D45:W45) -> 0
A46: 6 | B46: 0200 | C46: Employee Benefits - staff benefits tab | D46: {=SUM(IF(CertFund&CertProg&CertObj&CertGrant=RIGHT(LEFT($A$2,7),2)&LEFT($A$43,4)&$B$44&D$3,CertBen))} -> 0 | E46: {=SUM(IF(CertFund&CertProg&CertObj&CertGrant=RIGHT(LEFT($A$2,7),2)&LEFT($A$43,4)&$B$44&E$3,CertBen))} -> 0 | F46: {=SUM(IF(CertFund&CertProg&CertObj&CertGrant=RIGHT(LEFT($A$2,7),2)&LEFT($A$43,4)&$B$44&F$3,CertBen))} -> 0 | G46: {=SUM(IF(CertFund&CertProg&CertObj&CertGrant=RIGHT(LEFT($A$2,7),2)&LEFT($A$43,4)&$B$44&G$3,CertBen))} -> 0 | H46: {=SUM(IF(CertFund&CertProg&CertObj&CertGrant=RIGHT(LEFT($A$2,7),2)&LEFT($A$43,4)&$B$44&H$3,CertBen))} -> 0 | I46: {=SUM(IF(CertFund&CertProg&CertObj&CertGrant=RIGHT(LEFT($A$2,7),2)&LEFT($A$43,4)&$B$44&I$3,CertBen))} -> 0 | J46: {=SUM(IF(CertFund&CertProg&CertObj&CertGrant=RIGHT(LEFT($A$2,7),2)&LEFT($A$43,4)&$B$44&J$3,CertBen))} -> 0 | K46: {=SUM(IF(CertFund&CertProg&CertObj&CertGrant=RIGHT(LEFT($A$2,7),2)&LEFT($A$43,4)&$B$44&K$3,CertBen))} -> 0 | ... W46: {=SUM(IF(CertFund&CertProg&CertObj&CertGrant=RIGHT(LEFT($A$2,7),2)&LEFT($A$43,4)&$B$44&W$3,CertBen))} -> 0 | X46: =SUM(D46:W46) -> 0
A47: 6a | B47: 0200 | C47: Employee Benefits - addl items | D47: 0 | E47: 0 | F47: 0 | G47: 0 | H47: 0 | I47: 0 | J47: 0 | K47: 0 | L47: 0 | M47: 0 | N47: 0 | O47: 0 | P47: 0 | Q47: 0 | R47: 0 | S47: 0 | T47: 0 | U47: 0 | V47: 0 | W47: 0 | X47: =SUM(D47:W47) -> 0
A48: 7 | B48: 0300 | C48: Purchased Professional & Technical Services (0300) | D48: 0 | E48: 0 | F48: 0 | G48: 0 | H48: 0 | I48: 0 | J48: 0 | K48: 0 | L48: 0 | M48: 0 | N48: 0 | O48: 0 | P48: 0 | Q48: 0 | R48: 0 | S48: 0 | T48: 0 | U48: 0 | V48: 0 | W48: 0 | X48: =SUM(D48:W48) -> 0
A49: 8 | B49: 0500 | C49: Other Purchased Services (0500) | D49: 0 | E49: 0 | F49: 0 | G49: 0 | H49: 0 | I49: 0 | J49: 0 | K49: 0 | L49: 0 | M49: 0 | N49: 0 | O49: 0 | P49: 0 | Q49: 0 | R49: 0 | S49: 0 | T49: 0 | U49: 0 | V49: 0 | W49: 0 | X49: =SUM(D49:W49) -> 0
A50: 9 | B50: 0600 | C50: Supplies (0600) | D50: 0 | E50: 0 | F50: 0 | G50: 0 | H50: 0 | I50: 0 | J50: 0 | K50: 0 | L50: 0 | M50: 0 | N50: 0 | O50: 0 | P50: 0 | Q50: 0 | R50: 0 | S50: 0 | T50: 0 | U50: 0 | V50: 0 | W50: 0 | X50: =SUM(D50:W50) -> 0
A51: 10 | B51: 0800 | C51: Other (0800) | D51: 0 | E51: 0 | F51: 0 | G51: 0 | H51: 0 | I51: 0 | J51: 0 | K51: 0 | L51: 0 | M51: 0 | N51: 0 | O51: 0 | P51: 0 | Q51: 0 | R51: 0 | S51: 0 | T51: 0 | U51: 0 | V51: 0 | W51: 0 | X51: =SUM(D51:W51) -> 0
A52: 11 | C52: Subtotal 1600 - Technical Education | D52: =SUM(D44:D51) -> 0 | E52: =SUM(E44:E51) -> 0 | F52: =SUM(F44:F51) -> 0 | G52: =SUM(G44:G51) -> 0 | H52: =SUM(H44:H51) -> 0 | I52: =SUM(I44:I51) -> 0 | J52: =SUM(J44:J51) -> 0 | K52: =SUM(K44:K51) -> 0 | ... W52: =SUM(W44:W51) -> 0 | X52: =SUM(D52:W52) -> 0
A53: 1700 - Special Education Program
A54: 5 | B54: 0100 | C54: Salaries - from staff details tab | D54: {=SUM(IF(CertFund&CertProg&CertObj&CertGrant=RIGHT(LEFT($A$2,7),2)&LEFT($A$53,4)&$B$54&D$3,CertSalary))} -> 0 | E54: {=SUM(IF(CertFund&CertProg&CertObj&CertGrant=RIGHT(LEFT($A$2,7),2)&LEFT($A$53,4)&$B$54&E$3,CertSalary))} -> 0 | F54: {=SUM(IF(CertFund&CertProg&CertObj&CertGrant=RIGHT(LEFT($A$2,7),2)&LEFT($A$53,4)&$B$54&F$3,CertSalary))} -> 0 | G54: {=SUM(IF(CertFund&CertProg&CertObj&CertGrant=RIGHT(LEFT($A$2,7),2)&LEFT($A$53,4)&$B$54&G$3,CertSalary))} -> 0 | H54: {=SUM(IF(CertFund&CertProg&CertObj&CertGrant=RIGHT(LEFT($A$2,7),2)&LEFT($A$53,4)&$B$54&H$3,CertSalary))} -> 0 | I54: {=SUM(IF(CertFund&CertProg&CertObj&CertGrant=RIGHT(LEFT($A$2,7),2)&LEFT($A$53,4)&$B$54&I$3,CertSalary))} -> 0 | J54: {=SUM(IF(CertFund&CertProg&CertObj&CertGrant=RIGHT(LEFT($A$2,7),2)&LEFT($A$53,4)&$B$54&J$3,CertSalary))} -> 0 | K54: {=SUM(IF(CertFund&CertProg&CertObj&CertGrant=RIGHT(LEFT($A$2,7),2)&LEFT($A$53,4)&$B$54&K$3,CertSalary))} -> 0 | ... W54: {=SUM(IF(CertFund&CertProg&CertObj&CertGrant=RIGHT(LEFT($A$2,7),2)&LEFT($A$53,4)&$B$54&W$3,CertSalary))} -> 0 | X54: =SUM(D54:W54) -> 0
A55: 5a | B55: 0100 | C55: Salaries - additional items | D55: 0 | E55: 0 | F55: 0 | G55: 0 | H55: 0 | I55: 0 | J55: 0 | K55: 0 | L55: 0 | M55: 0 | N55: 0 | O55: 0 | P55: 0 | Q55: 0 | R55: 0 | S55: 0 | T55: 0 | U55: 0 | V55: 0 | W55: 0 | X55: =SUM(D55:W55) -> 0
A56: 6 | B56: 0200 | C56: Employee Benefits - staff benefits tab | D56: {=SUM(IF(CertFund&CertProg&CertObj&CertGrant=RIGHT(LEFT($A$2,7),2)&LEFT($A$53,4)&$B$54&D$3,CertBen))} -> 0 | E56: {=SUM(IF(CertFund&CertProg&CertObj&CertGrant=RIGHT(LEFT($A$2,7),2)&LEFT($A$53,4)&$B$54&E$3,CertBen))} -> 0 | F56: {=SUM(IF(CertFund&CertProg&CertObj&CertGrant=RIGHT(LEFT($A$2,7),2)&LEFT($A$53,4)&$B$54&F$3,CertBen))} -> 0 | G56: {=SUM(IF(CertFund&CertProg&CertObj&CertGrant=RIGHT(LEFT($A$2,7),2)&LEFT($A$53,4)&$B$54&G$3,CertBen))} -> 0 | H56: {=SUM(IF(CertFund&CertProg&CertObj&CertGrant=RIGHT(LEFT($A$2,7),2)&LEFT($A$53,4)&$B$54&H$3,CertBen))} -> 0 | I56: {=SUM(IF(CertFund&CertProg&CertObj&CertGrant=RIGHT(LEFT($A$2,7),2)&LEFT($A$53,4)&$B$54&I$3,CertBen))} -> 0 | J56: {=SUM(IF(CertFund&CertProg&CertObj&CertGrant=RIGHT(LEFT($A$2,7),2)&LEFT($A$53,4)&$B$54&J$3,CertBen))} -> 0 | K56: {=SUM(IF(CertFund&CertProg&CertObj&CertGrant=RIGHT(LEFT($A$2,7),2)&LEFT($A$53,4)&$B$54&K$3,CertBen))} -> 0 | ... W56: {=SUM(IF(CertFund&CertProg&CertObj&CertGrant=RIGHT(LEFT($A$2,7),2)&LEFT($A$53,4)&$B$54&W$3,CertBen))} -> 0 | X56: =SUM(D56:W56) -> 0
A57: 6a | B57: 0200 | C57: Employee Benefits - addl items | D57: 0 | E57: 0 | F57: 0 | G57: 0 | H57: 0 | I57: 0 | J57: 0 | K57: 0 | L57: 0 | M57: 0 | N57: 0 | O57: 0 | P57: 0 | Q57: 0 | R57: 0 | S57: 0 | T57: 0 | U57: 0 | V57: 0 | W57: 0 | X57: =SUM(D57:W57) -> 0
A58: 7 | B58: 0300 | C58: Purchased Professional & Technical Services (0300) | D58: 0 | E58: 0 | F58: 0 | G58: 0 | H58: 0 | I58: 0 | J58: 0 | K58: 0 | L58: 0 | M58: 0 | N58: 0 | O58: 0 | P58: 0 | Q58: 0 | R58: 0 | S58: 0 | T58: 0 | U58: 0 | V58: 0 | W58: 0 | X58: =SUM(D58:W58) -> 0
A59: 8 | B59: 0500 | C59: Other Purchased Services (0500) | D59: 0 | E59: 0 | F59: 0 | G59: 0 | H59: 0 | I59: 0 | J59: 0 | K59: 0 | L59: 0 | M59: 0 | N59: 0 | O59: 0 | P59: 0 | Q59: 0 | R59: 0 | S59: 0 | T59: 0 | U59: 0 | V59: 0 | W59: 0 | X59: =SUM(D59:W59) -> 0
A60: 9 | B60: 0600 | C60: Supplies (0600) | D60: 0 | E60: 0 | F60: 0 | G60: 0 | H60: 0 | I60: 0 | J60: 0 | K60: 0 | L60: 0 | M60: 0 | N60: 0 | O60: 0 | P60: 0 | Q60: 0 | R60: 0 | S60: 0 | T60: 0 | U60: 0 | V60: 0 | W60: 0 | X60: =SUM(D60:W60) -> 0
A61: 10 | B61: 0800 | C61: Other (0800) | D61: 0 | E61: 0 | F61: 0 | G61: 0 | H61: 0 | I61: 0 | J61: 0 | K61: 0 | L61: 0 | M61: 0 | N61: 0 | O61: 0 | P61: 0 | Q61: 0 | R61: 0 | S61: 0 | T61: 0 | U61: 0 | V61: 0 | W61: 0 | X61: =SUM(D61:W61) -> 0
A62: 11 | C62: Subtotal 1700 - Special Education | D62: =SUM(D54:D61) -> 0 | E62: =SUM(E54:E61) -> 0 | F62: =SUM(F54:F61) -> 0 | G62: =SUM(G54:G61) -> 0 | H62: =SUM(H54:H61) -> 0 | I62: =SUM(I54:I61) -> 0 | J62: =SUM(J54:J61) -> 0 | K62: =SUM(K54:K61) -> 0 | ... W62: =SUM(W54:W61) -> 0 | X62: =SUM(D62:W62) -> 0
A63: 2100 - Students
A64: 2200 - Instructional Staff
A65: 2600 - Operations and Maintenance
A66: 2700 - Student Transportation
A67: 2800 - Central Support
A68: 2900 - Other Support
A69: 3300 - Community Services
A70: 12 | B70: 0100 | C70: Salaries - from staff details tab | D70: {=SUM(IF(CertFund&CertProg&CertObj&CertGrant=RIGHT(LEFT($A$2,7),2)&LEFT($A$63,4)&$B$70&D$3,CertSalary))+SUM(IF(CertFund&CertProg&CertObj&CertGrant=RIGHT(LEFT($A$2,7),2)&LEFT($A$64,4)&$B$70&D$3,CertSalary))+SUM(IF(CertFund&CertProg&CertObj&CertGrant=RIGHT(LEFT($A$2,7),2)&LEFT($A$65,4)&$B$70&D$3,CertSalary))+SUM(IF(CertFund&CertProg&CertObj&CertGrant=RIGHT(LEFT($A$2,7),2)&LEFT($A$66,4)&$B$70&D$3,CertSalary))+SUM(IF(CertFund&CertProg&CertObj&CertGrant=RIGHT(LEFT($A$2,7),2)&LEFT($A$67,4)&$B$70&D$3,CertSalary))+SUM(IF(CertFund&CertProg&CertObj&CertGrant=RIGHT(LEFT($A$2,7),2)&LEFT($A$68,4)&$B$70&D$3,CertSalary))+SUM(IF(CertFund&CertProg&CertObj&CertGrant=RIGHT(LEFT($A$2,7),2)&LEFT($A$69,4)&$B$70&D$3,CertSalary))} -> 0 | E70: {=SUM(IF(CertFund&CertProg&CertObj&CertGrant=RIGHT(LEFT($A$2,7),2)&LEFT($A$63,4)&$B$70&E$3,CertSalary))+SUM(IF(CertFund&CertProg&CertObj&CertGrant=RIGHT(LEFT($A$2,7),2)&LEFT($A$64,4)&$B$70&E$3,CertSalary))+SUM(IF(CertFund&CertProg&CertObj&CertGrant=RIGHT(LEFT($A$2,7),2)&LEFT($A$65,4)&$B$70&E$3,CertSalary))+SUM(IF(CertFund&CertProg&CertObj&CertGrant=RIGHT(LEFT($A$2,7),2)&LEFT($A$66,4)&$B$70&E$3,CertSalary))+SUM(IF(CertFund&CertProg&CertObj&CertGrant=RIGHT(LEFT($A$2,7),2)&LEFT($A$67,4)&$B$70&E$3,CertSalary))+SUM(IF(CertFund&CertProg&CertObj&CertGrant=RIGHT(LEFT($A$2,7),2)&LEFT($A$68,4)&$B$70&E$3,CertSalary))+SUM(IF(CertFund&CertProg&CertObj&CertGrant=RIGHT(LEFT($A$2,7),2)&LEFT($A$69,4)&$B$70&E$3,CertSalary))} -> 0 | F70: {=SUM(IF(CertFund&CertProg&CertObj&CertGrant=RIGHT(LEFT($A$2,7),2)&LEFT($A$63,4)&$B$70&F$3,CertSalary))+SUM(IF(CertFund&CertProg&CertObj&CertGrant=RIGHT(LEFT($A$2,7),2)&LEFT($A$64,4)&$B$70&F$3,CertSalary))+SUM(IF(CertFund&CertProg&CertObj&CertGrant=RIGHT(LEFT($A$2,7),2)&LEFT($A$65,4)&$B$70&F$3,CertSalary))+SUM(IF(CertFund&CertProg&CertObj&CertGrant=RIGHT(LEFT($A$2,7),2)&LEFT($A$66,4)&$B$70&F$3,CertSalary))+SUM(IF(CertFund&CertProg&CertObj&CertGrant=RIGHT(LEFT($A$2,7),2)&LEFT($A$67,4)&$B$70&F$3,CertSalary))+SUM(IF(CertFund&CertProg&CertObj&CertGrant=RIGHT(LEFT($A$2,7),2)&LEFT($A$68,4)&$B$70&F$3,CertSalary))+SUM(IF(CertFund&CertProg&CertObj&CertGrant=RIGHT(LEFT($A$2,7),2)&LEFT($A$69,4)&$B$70&F$3,CertSalary))} -> 0 | G70: {=SUM(IF(CertFund&CertProg&CertObj&CertGrant=RIGHT(LEFT($A$2,7),2)&LEFT($A$63,4)&$B$70&G$3,CertSalary))+SUM(IF(CertFund&CertProg&CertObj&CertGrant=RIGHT(LEFT($A$2,7),2)&LEFT($A$64,4)&$B$70&G$3,CertSalary))+SUM(IF(CertFund&CertProg&CertObj&CertGrant=RIGHT(LEFT($A$2,7),2)&LEFT($A$65,4)&$B$70&G$3,CertSalary))+SUM(IF(CertFund&CertProg&CertObj&CertGrant=RIGHT(LEFT($A$2,7),2)&LEFT($A$66,4)&$B$70&G$3,CertSalary))+SUM(IF(CertFund&CertProg&CertObj&CertGrant=RIGHT(LEFT($A$2,7),2)&LEFT($A$67,4)&$B$70&G$3,CertSalary))+SUM(IF(CertFund&CertProg&CertObj&CertGrant=RIGHT(LEFT($A$2,7),2)&LEFT($A$68,4)&$B$70&G$3,CertSalary))+SUM(IF(CertFund&CertProg&CertObj&CertGrant=RIGHT(LEFT($A$2,7),2)&LEFT($A$69,4)&$B$70&G$3,CertSalary))} -> 0 | H70: {=SUM(IF(CertFund&CertProg&CertObj&CertGrant=RIGHT(LEFT($A$2,7),2)&LEFT($A$63,4)&$B$70&H$3,CertSalary))+SUM(IF(CertFund&CertProg&CertObj&CertGrant=RIGHT(LEFT($A$2,7),2)&LEFT($A$64,4)&$B$70&H$3,CertSalary))+SUM(IF(CertFund&CertProg&CertObj&CertGrant=RIGHT(LEFT($A$2,7),2)&LEFT($A$65,4)&$B$70&H$3,CertSalary))+SUM(IF(CertFund&CertProg&CertObj&CertGrant=RIGHT(LEFT($A$2,7),2)&LEFT($A$66,4)&$B$70&H$3,CertSalary))+SUM(IF(CertFund&CertProg&CertObj&CertGrant=RIGHT(LEFT($A$2,7),2)&LEFT($A$67,4)&$B$70&H$3,CertSalary))+SUM(IF(CertFund&CertProg&CertObj&CertGrant=RIGHT(LEFT($A$2,7),2)&LEFT($A$68,4)&$B$70&H$3,CertSalary))+SUM(IF(CertFund&CertProg&CertObj&CertGrant=RIGHT(LEFT($A$2,7),2)&LEFT($A$69,4)&$B$70&H$3,CertSalary))} -> 0 | I70: {=SUM(IF(CertFund&CertProg&CertObj&CertGrant=RIGHT(LEFT($A$2,7),2)&LEFT($A$63,4)&$B$70&I$3,CertSalary))+SUM(IF(CertFund&CertProg&CertObj&CertGrant=RIGHT(LEFT($A$2,7),2)&LEFT($A$64,4)&$B$70&I$3,CertSalary))+SUM(IF(CertFund&CertProg&CertObj&CertGrant=RIGHT(LEFT($A$2,7),2)&LEFT($A$65,4)&$B$70&I$3,CertSalary))+SUM(IF(CertFund&CertProg&CertObj&CertGrant=RIGHT(LEFT($A$2,7),2)&LEFT($A$66,4)&$B$70&I$3,CertSalary))+SUM(IF(CertFund&CertProg&CertObj&CertGrant=RIGHT(LEFT($A$2,7),2)&LEFT($A$67,4)&$B$70&I$3,CertSalary))+SUM(IF(CertFund&CertProg&CertObj&CertGrant=RIGHT(LEFT($A$2,7),2)&LEFT($A$68,4)&$B$70&I$3,CertSalary))+SUM(IF(CertFund&CertProg&CertObj&CertGrant=RIGHT(LEFT($A$2,7),2)&LEFT($A$69,4)&$B$70&I$3,CertSalary))} -> 0 | J70: {=SUM(IF(CertFund&CertProg&CertObj&CertGrant=RIGHT(LEFT($A$2,7),2)&LEFT($A$63,4)&$B$70&J$3,CertSalary))+SUM(IF(CertFund&CertProg&CertObj&CertGrant=RIGHT(LEFT($A$2,7),2)&LEFT($A$64,4)&$B$70&J$3,CertSalary))+SUM(IF(CertFund&CertProg&CertObj&CertGrant=RIGHT(LEFT($A$2,7),2)&LEFT($A$65,4)&$B$70&J$3,CertSalary))+SUM(IF(CertFund&CertProg&CertObj&CertGrant=RIGHT(LEFT($A$2,7),2)&LEFT($A$66,4)&$B$70&J$3,CertSalary))+SUM(IF(CertFund&CertProg&CertObj&CertGrant=RIGHT(LEFT($A$2,7),2)&LEFT($A$67,4)&$B$70&J$3,CertSalary))+SUM(IF(CertFund&CertProg&CertObj&CertGrant=RIGHT(LEFT($A$2,7),2)&LEFT($A$68,4)&$B$70&J$3,CertSalary))+SUM(IF(CertFund&CertProg&CertObj&CertGrant=RIGHT(LEFT($A$2,7),2)&LEFT($A$69,4)&$B$70&J$3,CertSalary))} -> 0 | K70: {=SUM(IF(CertFund&CertProg&CertObj&CertGrant=RIGHT(LEFT($A$2,7),2)&LEFT($A$63,4)&$B$70&K$3,CertSalary))+SUM(IF(CertFund&CertProg&CertObj&CertGrant=RIGHT(LEFT($A$2,7),2)&LEFT($A$64,4)&$B$70&K$3,CertSalary))+SUM(IF(CertFund&CertProg&CertObj&CertGrant=RIGHT(LEFT($A$2,7),2)&LEFT($A$65,4)&$B$70&K$3,CertSalary))+SUM(IF(CertFund&CertProg&CertObj&CertGrant=RIGHT(LEFT($A$2,7),2)&LEFT($A$66,4)&$B$70&K$3,CertSalary))+SUM(IF(CertFund&CertProg&CertObj&CertGrant=RIGHT(LEFT($A$2,7),2)&LEFT($A$67,4)&$B$70&K$3,CertSalary))+SUM(IF(CertFund&CertProg&CertObj&CertGrant=RIGHT(LEFT($A$2,7),2)&LEFT($A$68,4)&$B$70&K$3,CertSalary))+SUM(IF(CertFund&CertProg&CertObj&CertGrant=RIGHT(LEFT($A$2,7),2)&LEFT($A$69,4)&$B$70&K$3,CertSalary))} -> 0 | ... W70: {=SUM(IF(CertFund&CertProg&CertObj&CertGrant=RIGHT(LEFT($A$2,7),2)&LEFT($A$63,4)&$B$70&W$3,CertSalary))+SUM(IF(CertFund&CertProg&CertObj&CertGrant=RIGHT(LEFT($A$2,7),2)&LEFT($A$64,4)&$B$70&W$3,CertSalary))+SUM(IF(CertFund&CertProg&CertObj&CertGrant=RIGHT(LEFT($A$2,7),2)&LEFT($A$65,4)&$B$70&W$3,CertSalary))+SUM(IF(CertFund&CertProg&CertObj&CertGrant=RIGHT(LEFT($A$2,7),2)&LEFT($A$66,4)&$B$70&W$3,CertSalary))+SUM(IF(CertFund&CertProg&CertObj&CertGrant=RIGHT(LEFT($A$2,7),2)&LEFT($A$67,4)&$B$70&W$3,CertSalary))+SUM(IF(CertFund&CertProg&CertObj&CertGrant=RIGHT(LEFT($A$2,7),2)&LEFT($A$68,4)&$B$70&W$3,CertSalary))+SUM(IF(CertFund&CertProg&CertObj&CertGrant=RIGHT(LEFT($A$2,7),2)&LEFT($A$69,4)&$B$70&W$3,CertSalary))} -> 0 | X70: =SUM(D70:W70) -> 0
A71: 12a | B71: 0100 | C71: Salaries - additional items | D71: 0 | E71: 0 | F71: 0 | G71: 0 | H71: 0 | I71: 0 | J71: 0 | K71: 0 | L71: 0 | M71: 0 | N71: 0 | O71: 0 | P71: 0 | Q71: 0 | R71: 0 | S71: 0 | T71: 0 | U71: 0 | V71: 0 | W71: 0 | X71: =SUM(D71:W71) -> 0
A72: 13 | B72: 0200 | C72: Employee Benefits - staff benefits tab | D72: {=SUM(IF(CertFund&CertProg&CertObj&CertGrant=RIGHT(LEFT($A$2,7),2)&LEFT($A$63,4)&$B$70&D$3,CertBen))+SUM(IF(CertFund&CertProg&CertObj&CertGrant=RIGHT(LEFT($A$2,7),2)&LEFT($A$64,4)&$B$70&D$3,CertBen))+SUM(IF(CertFund&CertProg&CertObj&CertGrant=RIGHT(LEFT($A$2,7),2)&LEFT($A$65,4)&$B$70&D$3,CertBen))+SUM(IF(CertFund&CertProg&CertObj&CertGrant=RIGHT(LEFT($A$2,7),2)&LEFT($A$66,4)&$B$70&D$3,CertBen))+SUM(IF(CertFund&CertProg&CertObj&CertGrant=RIGHT(LEFT($A$2,7),2)&LEFT($A$67,4)&$B$70&D$3,CertBen))+SUM(IF(CertFund&CertProg&CertObj&CertGrant=RIGHT(LEFT($A$2,7),2)&LEFT($A$68,4)&$B$70&D$3,CertBen))+SUM(IF(CertFund&CertProg&CertObj&CertGrant=RIGHT(LEFT($A$2,7),2)&LEFT($A$69,4)&$B$70&D$3,CertBen))} -> 0 | E72: {=SUM(IF(CertFund&CertProg&CertObj&CertGrant=RIGHT(LEFT($A$2,7),2)&LEFT($A$63,4)&$B$70&E$3,CertBen))+SUM(IF(CertFund&CertProg&CertObj&CertGrant=RIGHT(LEFT($A$2,7),2)&LEFT($A$64,4)&$B$70&E$3,CertBen))+SUM(IF(CertFund&CertProg&CertObj&CertGrant=RIGHT(LEFT($A$2,7),2)&LEFT($A$65,4)&$B$70&E$3,CertBen))+SUM(IF(CertFund&CertProg&CertObj&CertGrant=RIGHT(LEFT($A$2,7),2)&LEFT($A$66,4)&$B$70&E$3,CertBen))+SUM(IF(CertFund&CertProg&CertObj&CertGrant=RIGHT(LEFT($A$2,7),2)&LEFT($A$67,4)&$B$70&E$3,CertBen))+SUM(IF(CertFund&CertProg&CertObj&CertGrant=RIGHT(LEFT($A$2,7),2)&LEFT($A$68,4)&$B$70&E$3,CertBen))+SUM(IF(CertFund&CertProg&CertObj&CertGrant=RIGHT(LEFT($A$2,7),2)&LEFT($A$69,4)&$B$70&E$3,CertBen))} -> 0 | F72: {=SUM(IF(CertFund&CertProg&CertObj&CertGrant=RIGHT(LEFT($A$2,7),2)&LEFT($A$63,4)&$B$70&F$3,CertBen))+SUM(IF(CertFund&CertProg&CertObj&CertGrant=RIGHT(LEFT($A$2,7),2)&LEFT($A$64,4)&$B$70&F$3,CertBen))+SUM(IF(CertFund&CertProg&CertObj&CertGrant=RIGHT(LEFT($A$2,7),2)&LEFT($A$65,4)&$B$70&F$3,CertBen))+SUM(IF(CertFund&CertProg&CertObj&CertGrant=RIGHT(LEFT($A$2,7),2)&LEFT($A$66,4)&$B$70&F$3,CertBen))+SUM(IF(CertFund&CertProg&CertObj&CertGrant=RIGHT(LEFT($A$2,7),2)&LEFT($A$67,4)&$B$70&F$3,CertBen))+SUM(IF(CertFund&CertProg&CertObj&CertGrant=RIGHT(LEFT($A$2,7),2)&LEFT($A$68,4)&$B$70&F$3,CertBen))+SUM(IF(CertFund&CertProg&CertObj&CertGrant=RIGHT(LEFT($A$2,7),2)&LEFT($A$69,4)&$B$70&F$3,CertBen))} -> 0 | G72: {=SUM(IF(CertFund&CertProg&CertObj&CertGrant=RIGHT(LEFT($A$2,7),2)&LEFT($A$63,4)&$B$70&G$3,CertBen))+SUM(IF(CertFund&CertProg&CertObj&CertGrant=RIGHT(LEFT($A$2,7),2)&LEFT($A$64,4)&$B$70&G$3,CertBen))+SUM(IF(CertFund&CertProg&CertObj&CertGrant=RIGHT(LEFT($A$2,7),2)&LEFT($A$65,4)&$B$70&G$3,CertBen))+SUM(IF(CertFund&CertProg&CertObj&CertGrant=RIGHT(LEFT($A$2,7),2)&LEFT($A$66,4)&$B$70&G$3,CertBen))+SUM(IF(CertFund&CertProg&CertObj&CertGrant=RIGHT(LEFT($A$2,7),2)&LEFT($A$67,4)&$B$70&G$3,CertBen))+SUM(IF(CertFund&CertProg&CertObj&CertGrant=RIGHT(LEFT($A$2,7),2)&LEFT($A$68,4)&$B$70&G$3,CertBen))+SUM(IF(CertFund&CertProg&CertObj&CertGrant=RIGHT(LEFT($A$2,7),2)&LEFT($A$69,4)&$B$70&G$3,CertBen))} -> 0 | H72: {=SUM(IF(CertFund&CertProg&CertObj&CertGrant=RIGHT(LEFT($A$2,7),2)&LEFT($A$63,4)&$B$70&H$3,CertBen))+SUM(IF(CertFund&CertProg&CertObj&CertGrant=RIGHT(LEFT($A$2,7),2)&LEFT($A$64,4)&$B$70&H$3,CertBen))+SUM(IF(CertFund&CertProg&CertObj&CertGrant=RIGHT(LEFT($A$2,7),2)&LEFT($A$65,4)&$B$70&H$3,CertBen))+SUM(IF(CertFund&CertProg&CertObj&CertGrant=RIGHT(LEFT($A$2,7),2)&LEFT($A$66,4)&$B$70&H$3,CertBen))+SUM(IF(CertFund&CertProg&CertObj&CertGrant=RIGHT(LEFT($A$2,7),2)&LEFT($A$67,4)&$B$70&H$3,CertBen))+SUM(IF(CertFund&CertProg&CertObj&CertGrant=RIGHT(LEFT($A$2,7),2)&LEFT($A$68,4)&$B$70&H$3,CertBen))+SUM(IF(CertFund&CertProg&CertObj&CertGrant=RIGHT(LEFT($A$2,7),2)&LEFT($A$69,4)&$B$70&H$3,CertBen))} -> 0 | I72: {=SUM(IF(CertFund&CertProg&CertObj&CertGrant=RIGHT(LEFT($A$2,7),2)&LEFT($A$63,4)&$B$70&I$3,CertBen))+SUM(IF(CertFund&CertProg&CertObj&CertGrant=RIGHT(LEFT($A$2,7),2)&LEFT($A$64,4)&$B$70&I$3,CertBen))+SUM(IF(CertFund&CertProg&CertObj&CertGrant=RIGHT(LEFT($A$2,7),2)&LEFT($A$65,4)&$B$70&I$3,CertBen))+SUM(IF(CertFund&CertProg&CertObj&CertGrant=RIGHT(LEFT($A$2,7),2)&LEFT($A$66,4)&$B$70&I$3,CertBen))+SUM(IF(CertFund&CertProg&CertObj&CertGrant=RIGHT(LEFT($A$2,7),2)&LEFT($A$67,4)&$B$70&I$3,CertBen))+SUM(IF(CertFund&CertProg&CertObj&CertGrant=RIGHT(LEFT($A$2,7),2)&LEFT($A$68,4)&$B$70&I$3,CertBen))+SUM(IF(CertFund&CertProg&CertObj&CertGrant=RIGHT(LEFT($A$2,7),2)&LEFT($A$69,4)&$B$70&I$3,CertBen))} -> 0 | J72: {=SUM(IF(CertFund&CertProg&CertObj&CertGrant=RIGHT(LEFT($A$2,7),2)&LEFT($A$63,4)&$B$70&J$3,CertBen))+SUM(IF(CertFund&CertProg&CertObj&CertGrant=RIGHT(LEFT($A$2,7),2)&LEFT($A$64,4)&$B$70&J$3,CertBen))+SUM(IF(CertFund&CertProg&CertObj&CertGrant=RIGHT(LEFT($A$2,7),2)&LEFT($A$65,4)&$B$70&J$3,CertBen))+SUM(IF(CertFund&CertProg&CertObj&CertGrant=RIGHT(LEFT($A$2,7),2)&LEFT($A$66,4)&$B$70&J$3,CertBen))+SUM(IF(CertFund&CertProg&CertObj&CertGrant=RIGHT(LEFT($A$2,7),2)&LEFT($A$67,4)&$B$70&J$3,CertBen))+SUM(IF(CertFund&CertProg&CertObj&CertGrant=RIGHT(LEFT($A$2,7),2)&LEFT($A$68,4)&$B$70&J$3,CertBen))+SUM(IF(CertFund&CertProg&CertObj&CertGrant=RIGHT(LEFT($A$2,7),2)&LEFT($A$69,4)&$B$70&J$3,CertBen))} -> 0 | K72: {=SUM(IF(CertFund&CertProg&CertObj&CertGrant=RIGHT(LEFT($A$2,7),2)&LEFT($A$63,4)&$B$70&K$3,CertBen))+SUM(IF(CertFund&CertProg&CertObj&CertGrant=RIGHT(LEFT($A$2,7),2)&LEFT($A$64,4)&$B$70&K$3,CertBen))+SUM(IF(CertFund&CertProg&CertObj&CertGrant=RIGHT(LEFT($A$2,7),2)&LEFT($A$65,4)&$B$70&K$3,CertBen))+SUM(IF(CertFund&CertProg&CertObj&CertGrant=RIGHT(LEFT($A$2,7),2)&LEFT($A$66,4)&$B$70&K$3,CertBen))+SUM(IF(CertFund&CertProg&CertObj&CertGrant=RIGHT(LEFT($A$2,7),2)&LEFT($A$67,4)&$B$70&K$3,CertBen))+SUM(IF(CertFund&CertProg&CertObj&CertGrant=RIGHT(LEFT($A$2,7),2)&LEFT($A$68,4)&$B$70&K$3,CertBen))+SUM(IF(CertFund&CertProg&CertObj&CertGrant=RIGHT(LEFT($A$2,7),2)&LEFT($A$69,4)&$B$70&K$3,CertBen))} -> 0 | ... W72: {=SUM(IF(CertFund&CertProg&CertObj&CertGrant=RIGHT(LEFT($A$2,7),2)&LEFT($A$63,4)&$B$70&W$3,CertBen))+SUM(IF(CertFund&CertProg&CertObj&CertGrant=RIGHT(LEFT($A$2,7),2)&LEFT($A$64,4)&$B$70&W$3,CertBen))+SUM(IF(CertFund&CertProg&CertObj&CertGrant=RIGHT(LEFT($A$2,7),2)&LEFT($A$65,4)&$B$70&W$3,CertBen))+SUM(IF(CertFund&CertProg&CertObj&CertGrant=RIGHT(LEFT($A$2,7),2)&LEFT($A$66,4)&$B$70&W$3,CertBen))+SUM(IF(CertFund&CertProg&CertObj&CertGrant=RIGHT(LEFT($A$2,7),2)&LEFT($A$67,4)&$B$70&W$3,CertBen))+SUM(IF(CertFund&CertProg&CertObj&CertGrant=RIGHT(LEFT($A$2,7),2)&LEFT($A$68,4)&$B$70&W$3,CertBen))+SUM(IF(CertFund&CertProg&CertObj&CertGrant=RIGHT(LEFT($A$2,7),2)&LEFT($A$69,4)&$B$70&W$3,CertBen))} -> 0 | X72: =SUM(D72:W72) -> 0
A73: 13a | B73: 0200 | C73: Employee Benefits - addl items | D73: 0 | E73: 0 | F73: 0 | G73: 0 | H73: 0 | I73: 0 | J73: 0 | K73: 0 | L73: 0 | M73: 0 | N73: 0 | O73: 0 | P73: 0 | Q73: 0 | R73: 0 | S73: 0 | T73: 0 | U73: 0 | V73: 0 | W73: 0 | X73: =SUM(D73:W73) -> 0
A74: 14 | B74: 0300 | C74: Purchased Professional & Technical Services (0300) | D74: 0 | E74: 0 | F74: 0 | G74: 0 | H74: 0 | I74: 0 | J74: 0 | K74: 0 | L74: 0 | M74: 0 | N74: 0 | O74: 0 | P74: 0 | Q74: 0 | R74: 0 | S74: 0 | T74: 0 | U74: 0 | V74: 0 | W74: 0 | X74: =SUM(D74:W74) -> 0
A75: 15 | B75: 0400 | C75: Purchased Property Services (0400) | D75: 0 | E75: 0 | F75: 0 | G75: 0 | H75: 0 | I75: 0 | J75: 0 | K75: 0 | L75: 0 | M75: 0 | N75: 0 | O75: 0 | P75: 0 | Q75: 0 | R75: 0 | S75: 0 | T75: 0 | U75: 0 | V75: 0 | W75: 0 | X75: =SUM(D75:W75) -> 0
A76: 16 | B76: 0500 | C76: Other Purchased Services (0500) | D76: 0 | E76: 0 | F76: 0 | G76: 0 | H76: 0 | I76: 0 | J76: 0 | K76: 0 | L76: 0 | M76: 0 | N76: 0 | O76: 0 | P76: 0 | Q76: 0 | R76: 0 | S76: 0 | T76: 0 | U76: 0 | V76: 0 | W76: 0 | X76: =SUM(D76:W76) -> 0
A77: 17 | B77: 0600 | C77: Supplies (0600) | D77: 0 | E77: 0 | F77: 0 | G77: 0 | H77: 0 | I77: 0 | J77: 0 | K77: 0 | L77: 0 | M77: 0 | N77: 0 | O77: 0 | P77: 0 | Q77: 0 | R77: 0 | S77: 0 | T77: 0 | U77: 0 | V77: 0 | W77: 0 | X77: =SUM(D77:W77) -> 0
A78: 18 | B78: 0800 | C78: Other (0800) | D78: 0 | E78: 0 | F78: 0 | G78: 0 | H78: 0 | I78: 0 | J78: 0 | K78: 0 | L78: 0 | M78: 0 | N78: 0 | O78: 0 | P78: 0 | Q78: 0 | R78: 0 | S78: 0 | T78: 0 | U78: 0 | V78: 0 | W78: 0 | X78: =SUM(D78:W78) -> 0
A79: 19 | C79: Subtotal Support Program (lines 12 through 18) | D79: =SUM(D70:D78) -> 0 | E79: =SUM(E70:E78) -> 0 | F79: =SUM(F70:F78) -> 0 | G79: =SUM(G70:G78) -> 0 | H79: =SUM(H70:H78) -> 0 | I79: =SUM(I70:I78) -> 0 | J79: =SUM(J70:J78) -> 0 | K79: =SUM(K70:K78) -> 0 | ... W79: =SUM(W70:W78) -> 0 | X79: =SUM(D79:W79) -> 0
A80: 2210 - Improvement of Instructional Services
A81: 20 | B81: 0100 | C81: Salaries - from staff details tab | D81: {=SUM(IF(CertFund&CertProg&CertObj&CertGrant=RIGHT(LEFT($A$2,7),2)&LEFT($A$80,4)&$B$81&D$3,CertSalary))} -> 0 | E81: {=SUM(IF(CertFund&CertProg&CertObj&CertGrant=RIGHT(LEFT($A$2,7),2)&LEFT($A$80,4)&$B$81&E$3,CertSalary))} -> 0 | F81: {=SUM(IF(CertFund&CertProg&CertObj&CertGrant=RIGHT(LEFT($A$2,7),2)&LEFT($A$80,4)&$B$81&F$3,CertSalary))} -> 0 | G81: {=SUM(IF(CertFund&CertProg&CertObj&CertGrant=RIGHT(LEFT($A$2,7),2)&LEFT($A$80,4)&$B$81&G$3,CertSalary))} -> 0 | H81: {=SUM(IF(CertFund&CertProg&CertObj&CertGrant=RIGHT(LEFT($A$2,7),2)&LEFT($A$80,4)&$B$81&H$3,CertSalary))} -> 0 | I81: {=SUM(IF(CertFund&CertProg&CertObj&CertGrant=RIGHT(LEFT($A$2,7),2)&LEFT($A$80,4)&$B$81&I$3,CertSalary))} -> 0 | J81: {=SUM(IF(CertFund&CertProg&CertObj&CertGrant=RIGHT(LEFT($A$2,7),2)&LEFT($A$80,4)&$B$81&J$3,CertSalary))} -> 0 | K81: {=SUM(IF(CertFund&CertProg&CertObj&CertGrant=RIGHT(LEFT($A$2,7),2)&LEFT($A$80,4)&$B$81&K$3,CertSalary))} -> 0 | ... W81: {=SUM(IF(CertFund&CertProg&CertObj&CertGrant=RIGHT(LEFT($A$2,7),2)&LEFT($A$80,4)&$B$81&W$3,CertSalary))} -> 0 | X81: =SUM(D81:W81) -> 0
A82: 20a | B82: 0100 | C82: Salaries - additional items | D82: 0 | E82: 0 | F82: 0 | G82: 0 | H82: 0 | I82: 0 | J82: 0 | K82: 0 | L82: 0 | M82: 0 | N82: 0 | O82: 0 | P82: 0 | Q82: 0 | R82: 0 | S82: 0 | T82: 0 | U82: 0 | V82: 0 | W82: 0 | X82: =SUM(D82:W82) -> 0
A83: 21 | B83: 0200 | C83: Employee Benefits - staff benefits tab | D83: {=SUM(IF(CertFund&CertProg&CertObj&CertGrant=RIGHT(LEFT($A$2,7),2)&LEFT($A$80,4)&$B$81&D$3,CertBen))} -> 0 | E83: {=SUM(IF(CertFund&CertProg&CertObj&CertGrant=RIGHT(LEFT($A$2,7),2)&LEFT($A$80,4)&$B$81&E$3,CertBen))} -> 0 | F83: {=SUM(IF(CertFund&CertProg&CertObj&CertGrant=RIGHT(LEFT($A$2,7),2)&LEFT($A$80,4)&$B$81&F$3,CertBen))} -> 0 | G83: {=SUM(IF(CertFund&CertProg&CertObj&CertGrant=RIGHT(LEFT($A$2,7),2)&LEFT($A$80,4)&$B$81&G$3,CertBen))} -> 0 | H83: {=SUM(IF(CertFund&CertProg&CertObj&CertGrant=RIGHT(LEFT($A$2,7),2)&LEFT($A$80,4)&$B$81&H$3,CertBen))} -> 0 | I83: {=SUM(IF(CertFund&CertProg&CertObj&CertGrant=RIGHT(LEFT($A$2,7),2)&LEFT($A$80,4)&$B$81&I$3,CertBen))} -> 0 | J83: {=SUM(IF(CertFund&CertProg&CertObj&CertGrant=RIGHT(LEFT($A$2,7),2)&LEFT($A$80,4)&$B$81&J$3,CertBen))} -> 0 | K83: {=SUM(IF(CertFund&CertProg&CertObj&CertGrant=RIGHT(LEFT($A$2,7),2)&LEFT($A$80,4)&$B$81&K$3,CertBen))} -> 0 | ... W83: {=SUM(IF(CertFund&CertProg&CertObj&CertGrant=RIGHT(LEFT($A$2,7),2)&LEFT($A$80,4)&$B$81&W$3,CertBen))} -> 0 | X83: =SUM(D83:W83) -> 0
A84: 21a | B84: 0200 | C84: Employee Benefits - addl items | D84: 0 | E84: 0 | F84: 0 | G84: 0 | H84: 0 | I84: 0 | J84: 0 | K84: 0 | L84: 0 | M84: 0 | N84: 0 | O84: 0 | P84: 0 | Q84: 0 | R84: 0 | S84: 0 | T84: 0 | U84: 0 | V84: 0 | W84: 0 | X84: =SUM(D84:W84) -> 0
A85: 22 | B85: 0300 | C85: Purchased Professional & Technical Services (0300) | D85: 0 | E85: 0 | F85: 0 | G85: 0 | H85: 0 | I85: 0 | J85: 0 | K85: 0 | L85: 0 | M85: 0 | N85: 0 | O85: 0 | P85: 0 | Q85: 0 | R85: 0 | S85: 0 | T85: 0 | U85: 0 | V85: 0 | W85: 0 | X85: =SUM(D85:W85) -> 0
A86: 23 | B86: 0500 | C86: Other Purchased Services (0500) | D86: 0 | E86: 0 | F86: 0 | G86: 0 | H86: 0 | I86: 0 | J86: 0 | K86: 0 | L86: 0 | M86: 0 | N86: 0 | O86: 0 | P86: 0 | Q86: 0 | R86: 0 | S86: 0 | T86: 0 | U86: 0 | V86: 0 | W86: 0 | X86: =SUM(D86:W86) -> 0
A87: 24 | B87: 0600 | C87: Supplies (0600) | D87: 0 | E87: 0 | F87: 0 | G87: 0 | H87: 0 | I87: 0 | J87: 0 | K87: 0 | L87: 0 | M87: 0 | N87: 0 | O87: 0 | P87: 0 | Q87: 0 | R87: 0 | S87: 0 | T87: 0 | U87: 0 | V87: 0 | W87: 0 | X87: =SUM(D87:W87) -> 0
A88: 25 | B88: 0800 | C88: Other (0800) | D88: 0 | E88: 0 | F88: 0 | G88: 0 | H88: 0 | I88: 0 | J88: 0 | K88: 0 | L88: 0 | M88: 0 | N88: 0 | O88: 0 | P88: 0 | Q88: 0 | R88: 0 | S88: 0 | T88: 0 | U88: 0 | V88: 0 | W88: 0 | X88: =SUM(D88:W88) -> 0
A89: 26 | C89: Subtotal Improvement of Instructional Services (lines 20 through 25) | D89: =SUM(D81:D88) -> 0 | E89: =SUM(E81:E88) -> 0 | F89: =SUM(F81:F88) -> 0 | G89: =SUM(G81:G88) -> 0 | H89: =SUM(H81:H88) -> 0 | I89: =SUM(I81:I88) -> 0 | J89: =SUM(J81:J88) -> 0 | K89: =SUM(K81:K88) -> 0 | ... W89: =SUM(W81:W88) -> 0 | X89: =SUM(D89:W89) -> 0
A90: 2300 - General Administration
A91: 2400 - School Administration
A92: 2500 - Business Services
A93: 27 | B93: 0100 | C93: Salaries - from staff details tab | D93: {=SUM(IF(CertFund&CertProg&CertObj&CertGrant=RIGHT(LEFT($A$2,7),2)&LEFT($A$90,4)&$B$93&D$3,CertSalary))+SUM(IF(CertFund&CertProg&CertObj&CertGrant=RIGHT(LEFT($A$2,7),2)&LEFT($A$91,4)&$B$93&D$3,CertSalary))+SUM(IF(CertFund&CertProg&CertObj&CertGrant=RIGHT(LEFT($A$2,7),2)&LEFT($A$92,4)&$B$93&D$3,CertSalary))} -> 0 | E93: {=SUM(IF(CertFund&CertProg&CertObj&CertGrant=RIGHT(LEFT($A$2,7),2)&LEFT($A$90,4)&$B$93&E$3,CertSalary))+SUM(IF(CertFund&CertProg&CertObj&CertGrant=RIGHT(LEFT($A$2,7),2)&LEFT($A$91,4)&$B$93&E$3,CertSalary))+SUM(IF(CertFund&CertProg&CertObj&CertGrant=RIGHT(LEFT($A$2,7),2)&LEFT($A$92,4)&$B$93&E$3,CertSalary))} -> 0 | F93: {=SUM(IF(CertFund&CertProg&CertObj&CertGrant=RIGHT(LEFT($A$2,7),2)&LEFT($A$90,4)&$B$93&F$3,CertSalary))+SUM(IF(CertFund&CertProg&CertObj&CertGrant=RIGHT(LEFT($A$2,7),2)&LEFT($A$91,4)&$B$93&F$3,CertSalary))+SUM(IF(CertFund&CertProg&CertObj&CertGrant=RIGHT(LEFT($A$2,7),2)&LEFT($A$92,4)&$B$93&F$3,CertSalary))} -> 0 | G93: {=SUM(IF(CertFund&CertProg&CertObj&CertGrant=RIGHT(LEFT($A$2,7),2)&LEFT($A$90,4)&$B$93&G$3,CertSalary))+SUM(IF(CertFund&CertProg&CertObj&CertGrant=RIGHT(LEFT($A$2,7),2)&LEFT($A$91,4)&$B$93&G$3,CertSalary))+SUM(IF(CertFund&CertProg&CertObj&CertGrant=RIGHT(LEFT($A$2,7),2)&LEFT($A$92,4)&$B$93&G$3,CertSalary))} -> 0 | H93: {=SUM(IF(CertFund&CertProg&CertObj&CertGrant=RIGHT(LEFT($A$2,7),2)&LEFT($A$90,4)&$B$93&H$3,CertSalary))+SUM(IF(CertFund&CertProg&CertObj&CertGrant=RIGHT(LEFT($A$2,7),2)&LEFT($A$91,4)&$B$93&H$3,CertSalary))+SUM(IF(CertFund&CertProg&CertObj&CertGrant=RIGHT(LEFT($A$2,7),2)&LEFT($A$92,4)&$B$93&H$3,CertSalary))} -> 0 | I93: {=SUM(IF(CertFund&CertProg&CertObj&CertGrant=RIGHT(LEFT($A$2,7),2)&LEFT($A$90,4)&$B$93&I$3,CertSalary))+SUM(IF(CertFund&CertProg&CertObj&CertGrant=RIGHT(LEFT($A$2,7),2)&LEFT($A$91,4)&$B$93&I$3,CertSalary))+SUM(IF(CertFund&CertProg&CertObj&CertGrant=RIGHT(LEFT($A$2,7),2)&LEFT($A$92,4)&$B$93&I$3,CertSalary))} -> 0 | J93: {=SUM(IF(CertFund&CertProg&CertObj&CertGrant=RIGHT(LEFT($A$2,7),2)&LEFT($A$90,4)&$B$93&J$3,CertSalary))+SUM(IF(CertFund&CertProg&CertObj&CertGrant=RIGHT(LEFT($A$2,7),2)&LEFT($A$91,4)&$B$93&J$3,CertSalary))+SUM(IF(CertFund&CertProg&CertObj&CertGrant=RIGHT(LEFT($A$2,7),2)&LEFT($A$92,4)&$B$93&J$3,CertSalary))} -> 0 | K93: {=SUM(IF(CertFund&CertProg&CertObj&CertGrant=RIGHT(LEFT($A$2,7),2)&LEFT($A$90,4)&$B$93&K$3,CertSalary))+SUM(IF(CertFund&CertProg&CertObj&CertGrant=RIGHT(LEFT($A$2,7),2)&LEFT($A$91,4)&$B$93&K$3,CertSalary))+SUM(IF(CertFund&CertProg&CertObj&CertGrant=RIGHT(LEFT($A$2,7),2)&LEFT($A$92,4)&$B$93&K$3,CertSalary))} -> 0 | ... W93: {=SUM(IF(CertFund&CertProg&CertObj&CertGrant=RIGHT(LEFT($A$2,7),2)&LEFT($A$90,4)&$B$93&W$3,CertSalary))+SUM(IF(CertFund&CertProg&CertObj&CertGrant=RIGHT(LEFT($A$2,7),2)&LEFT($A$91,4)&$B$93&W$3,CertSalary))+SUM(IF(CertFund&CertProg&CertObj&CertGrant=RIGHT(LEFT($A$2,7),2)&LEFT($A$92,4)&$B$93&W$3,CertSalary))} -> 0 | X93: =SUM(D93:W93) -> 0
A94: 27a | B94: 0100 | C94: Salaries - additional items | D94: 0 | E94: 0 | F94: 0 | G94: 0 | H94: 0 | I94: 0 | J94: 0 | K94: 0 | L94: 0 | M94: 0 | N94: 0 | O94: 0 | P94: 0 | Q94: 0 | R94: 0 | S94: 0 | T94: 0 | U94: 0 | V94: 0 | W94: 0 | X94: =SUM(D94:W94) -> 0
A95: 28 | B95: 0200 | C95: Employee Benefits - staff benefits tab | D95: {=SUM(IF(CertFund&CertProg&CertObj&CertGrant=RIGHT(LEFT($A$2,7),2)&LEFT($A$90,4)&$B$93&D$3,CertBen))+SUM(IF(CertFund&CertProg&CertObj&CertGrant=RIGHT(LEFT($A$2,7),2)&LEFT($A$91,4)&$B$93&D$3,CertBen))+SUM(IF(CertFund&CertProg&CertObj&CertGrant=RIGHT(LEFT($A$2,7),2)&LEFT($A$92,4)&$B$93&D$3,CertBen))} -> 0 | E95: {=SUM(IF(CertFund&CertProg&CertObj&CertGrant=RIGHT(LEFT($A$2,7),2)&LEFT($A$90,4)&$B$93&E$3,CertBen))+SUM(IF(CertFund&CertProg&CertObj&CertGrant=RIGHT(LEFT($A$2,7),2)&LEFT($A$91,4)&$B$93&E$3,CertBen))+SUM(IF(CertFund&CertProg&CertObj&CertGrant=RIGHT(LEFT($A$2,7),2)&LEFT($A$92,4)&$B$93&E$3,CertBen))} -> 0 | F95: {=SUM(IF(CertFund&CertProg&CertObj&CertGrant=RIGHT(LEFT($A$2,7),2)&LEFT($A$90,4)&$B$93&F$3,CertBen))+SUM(IF(CertFund&CertProg&CertObj&CertGrant=RIGHT(LEFT($A$2,7),2)&LEFT($A$91,4)&$B$93&F$3,CertBen))+SUM(IF(CertFund&CertProg&CertObj&CertGrant=RIGHT(LEFT($A$2,7),2)&LEFT($A$92,4)&$B$93&F$3,CertBen))} -> 0 | G95: {=SUM(IF(CertFund&CertProg&CertObj&CertGrant=RIGHT(LEFT($A$2,7),2)&LEFT($A$90,4)&$B$93&G$3,CertBen))+SUM(IF(CertFund&CertProg&CertObj&CertGrant=RIGHT(LEFT($A$2,7),2)&LEFT($A$91,4)&$B$93&G$3,CertBen))+SUM(IF(CertFund&CertProg&CertObj&CertGrant=RIGHT(LEFT($A$2,7),2)&LEFT($A$92,4)&$B$93&G$3,CertBen))} -> 0 | H95: {=SUM(IF(CertFund&CertProg&CertObj&CertGrant=RIGHT(LEFT($A$2,7),2)&LEFT($A$90,4)&$B$93&H$3,CertBen))+SUM(IF(CertFund&CertProg&CertObj&CertGrant=RIGHT(LEFT($A$2,7),2)&LEFT($A$91,4)&$B$93&H$3,CertBen))+SUM(IF(CertFund&CertProg&CertObj&CertGrant=RIGHT(LEFT($A$2,7),2)&LEFT($A$92,4)&$B$93&H$3,CertBen))} -> 0 | I95: {=SUM(IF(CertFund&CertProg&CertObj&CertGrant=RIGHT(LEFT($A$2,7),2)&LEFT($A$90,4)&$B$93&I$3,CertBen))+SUM(IF(CertFund&CertProg&CertObj&CertGrant=RIGHT(LEFT($A$2,7),2)&LEFT($A$91,4)&$B$93&I$3,CertBen))+SUM(IF(CertFund&CertProg&CertObj&CertGrant=RIGHT(LEFT($A$2,7),2)&LEFT($A$92,4)&$B$93&I$3,CertBen))} -> 0 | J95: {=SUM(IF(CertFund&CertProg&CertObj&CertGrant=RIGHT(LEFT($A$2,7),2)&LEFT($A$90,4)&$B$93&J$3,CertBen))+SUM(IF(CertFund&CertProg&CertObj&CertGrant=RIGHT(LEFT($A$2,7),2)&LEFT($A$91,4)&$B$93&J$3,CertBen))+SUM(IF(CertFund&CertProg&CertObj&CertGrant=RIGHT(LEFT($A$2,7),2)&LEFT($A$92,4)&$B$93&J$3,CertBen))} -> 0 | K95: {=SUM(IF(CertFund&CertProg&CertObj&CertGrant=RIGHT(LEFT($A$2,7),2)&LEFT($A$90,4)&$B$93&K$3,CertBen))+SUM(IF(CertFund&CertProg&CertObj&CertGrant=RIGHT(LEFT($A$2,7),2)&LEFT($A$91,4)&$B$93&K$3,CertBen))+SUM(IF(CertFund&CertProg&CertObj&CertGrant=RIGHT(LEFT($A$2,7),2)&LEFT($A$92,4)&$B$93&K$3,CertBen))} -> 0 | ... W95: {=SUM(IF(CertFund&CertProg&CertObj&CertGrant=RIGHT(LEFT($A$2,7),2)&LEFT($A$90,4)&$B$93&W$3,CertBen))+SUM(IF(CertFund&CertProg&CertObj&CertGrant=RIGHT(LEFT($A$2,7),2)&LEFT($A$91,4)&$B$93&W$3,CertBen))+SUM(IF(CertFund&CertProg&CertObj&CertGrant=RIGHT(LEFT($A$2,7),2)&LEFT($A$92,4)&$B$93&W$3,CertBen))} -> 0 | X95: =SUM(D95:W95) -> 0
A96: 28a | B96: 0200 | C96: Employee Benefits - addl items | D96: 0 | E96: 0 | F96: 0 | G96: 0 | H96: 0 | I96: 0 | J96: 0 | K96: 0 | L96: 0 | M96: 0 | N96: 0 | O96: 0 | P96: 0 | Q96: 0 | R96: 0 | S96: 0 | T96: 0 | U96: 0 | V96: 0 | W96: 0 | X96: =SUM(D96:W96) -> 0
A97: 29 | B97: 0300 | C97: Purchased Professional & Technical Services (0300) | D97: 0 | E97: 0 | F97: 0 | G97: 0 | H97: 0 | I97: 0 | J97: 0 | K97: 0 | L97: 0 | M97: 0 | N97: 0 | O97: 0 | P97: 0 | Q97: 0 | R97: 0 | S97: 0 | T97: 0 | U97: 0 | V97: 0 | W97: 0 | X97: =SUM(D97:W97) -> 0
A98: 30 | B98: 0500 | C98: Other Purchased Services (0500) | D98: 0 | E98: 0 | F98: 0 | G98: 0 | H98: 0 | I98: 0 | J98: 0 | K98: 0 | L98: 0 | M98: 0 | N98: 0 | O98: 0 | P98: 0 | Q98: 0 | R98: 0 | S98: 0 | T98: 0 | U98: 0 | V98: 0 | W98: 0 | X98: =SUM(D98:W98) -> 0
A99: 31 | B99: 0600 | C99: Supplies (0600) | D99: 0 | E99: 0 | F99: 0 | G99: 0 | H99: 0 | I99: 0 | J99: 0 | K99: 0 | L99: 0 | M99: 0 | N99: 0 | O99: 0 | P99: 0 | Q99: 0 | R99: 0 | S99: 0 | T99: 0 | U99: 0 | V99: 0 | W99: 0 | X99: =SUM(D99:W99) -> 0
A100: 32a | B100: 0730 | C100: Property (0730) (Capitalized) | D100: 0 | E100: 0 | F100: 0 | G100: 0 | H100: 0 | I100: 0 | J100: 0 | K100: 0 | L100: 0 | M100: 0 | N100: 0 | O100: 0 | P100: 0 | Q100: 0 | R100: 0 | S100: 0 | T100: 0 | U100: 0 | V100: 0 | W100: 0 | X100: =SUM(D100:W100) -> 0
A101: 32b | B101: 0735 | C101: Property (0735) (Non-capitalized) | D101: 0 | E101: 0 | F101: 0 | G101: 0 | H101: 0 | I101: 0 | J101: 0 | K101: 0 | L101: 0 | M101: 0 | N101: 0 | O101: 0 | P101: 0 | Q101: 0 | R101: 0 | S101: 0 | T101: 0 | U101: 0 | V101: 0 | W101: 0 | X101: =SUM(D101:W101) -> 0
A102: 33 | C102: Subtotal Administration (lines 27 through 32) | D102: =SUM(D93:D101) -> 0 | E102: =SUM(E93:E101) -> 0 | F102: =SUM(F93:F101) -> 0 | G102: =SUM(G93:G101) -> 0 | H102: =SUM(H93:H101) -> 0 | I102: =SUM(I93:I101) -> 0 | J102: =SUM(J93:J101) -> 0 | K102: =SUM(K93:K101) -> 0 | ... W102: =SUM(W93:W101) -> 0 | X102: =SUM(D102:W102) -> 0
...

Sheet ARRAGrants
A1: School District | C1: 0 | E1: District Code | F1: 0 | H1: * Round to Nearest Dollar *
A2: Fund 20: GOVERNMENTAL DESIGNATED-PURPOSE GRANTS FUND
E3: Prior Year Actual - Audited FY07-08 | F3: Current Fiscal Year - Budgeted FY08-09 | G3: Current Fiscal Year - Projected FY08-09 | H3: Original Ensuing Fiscal Year - Budget FY09-10 | I3: Adjustments Ensuing Fiscal Year - Budget FY09-10 | J3: Revised Ensuing Fiscal Year - Budget FY09-10
I4: Record Inceases to revenue are positive amounts and Decreases as negatives | J4: Figures (Totals) which will appear on Budget Form to Submit to CDE
A6: BEGINNING FUND BALANCE | E6: 0 | F6: 0 | G6: 0 | H6: 0 | I6: 0 | J6: =H6+I6 -> 0
C7: REVENUE AND OTHER SOURCES
A8: Grant/Project Code | C8: STATE GRANT/PROJECT TITLE
C9: STATE FUNDS NOT IN OTHER FUNDS
A10: =HLOOKUP(201,'Fund 20 Grants'!$D$2:$W$3,2,FALSE) -> #N/A | C10: =HLOOKUP(201,'Fund 20 Grants'!$D$2:$W$4,3,FALSE) -> #N/A | E10: 0 | F10: 0 | G10: 0 | H10: =IF(ISERROR(HLOOKUP(201,'Fund 20 Grants'!$D$2:$W$12,11,FALSE)),0,(HLOOKUP(201,'Fund 20 Grants'!$D$2:$W$12,11,FALSE))) -> 0 | I10: 0 | J10: =H10+I10 -> 0
A11: =HLOOKUP(202,'Fund 20 Grants'!$D$2:$W$3,2,FALSE) -> #N/A | C11: =HLOOKUP(202,'Fund 20 Grants'!$D$2:$W$4,3,FALSE) -> #N/A | E11: 0 | F11: 0 | G11: 0 | H11: =IF(ISERROR(HLOOKUP(202,'Fund 20 Grants'!$D$2:$W$12,11,FALSE)),0,(HLOOKUP(202,'Fund 20 Grants'!$D$2:$W$12,11,FALSE))) -> 0 | I11: 0 | J11: =H11+I11 -> 0
A12: =HLOOKUP(203,'Fund 20 Grants'!$D$2:$W$3,2,FALSE) -> #N/A | C12: =HLOOKUP(203,'Fund 20 Grants'!$D$2:$W$4,3,FALSE) -> #N/A | E12: 0 | F12: 0 | G12: 0 | H12: =IF(ISERROR(HLOOKUP(203,'Fund 20 Grants'!$D$2:$W$12,11,FALSE)),0,(HLOOKUP(203,'Fund 20 Grants'!$D$2:$W$12,11,FALSE))) -> 0 | I12: 0 | J12: =H12+I12 -> 0
A13: =HLOOKUP(204,'Fund 20 Grants'!$D$2:$W$3,2,FALSE) -> #N/A | C13: =HLOOKUP(204,'Fund 20 Grants'!$D$2:$W$4,3,FALSE) -> #N/A | E13: 0 | F13: 0 | G13: 0 | H13: =IF(ISERROR(HLOOKUP(204,'Fund 20 Grants'!$D$2:$W$12,11,FALSE)),0,(HLOOKUP(204,'Fund 20 Grants'!$D$2:$W$12,11,FALSE))) -> 0 | I13: 0 | J13: =H13+I13 -> 0
A14: =HLOOKUP(205,'Fund 20 Grants'!$D$2:$W$3,2,FALSE) -> #N/A | C14: =HLOOKUP(205,'Fund 20 Grants'!$D$2:$W$4,3,FALSE) -> #N/A | E14: 0 | F14: 0 | G14: 0 | H14: =IF(ISERROR(HLOOKUP(205,'Fund 20 Grants'!$D$2:$W$12,11,FALSE)),0,(HLOOKUP(205,'Fund 20 Grants'!$D$2:$W$12,11,FALSE))) -> 0 | I14: 0 | J14: =H14+I14 -> 0
A15: =HLOOKUP(206,'Fund 20 Grants'!$D$2:$W$3,2,FALSE) -> #N/A | C15: =HLOOKUP(206,'Fund 20 Grants'!$D$2:$W$4,3,FALSE) -> #N/A | E15: 0 | F15: 0 | G15: 0 | H15: =IF(ISERROR(HLOOKUP(206,'Fund 20 Grants'!$D$2:$W$12,11,FALSE)),0,(HLOOKUP(206,'Fund 20 Grants'!$D$2:$W$12,11,FALSE))) -> 0 | I15: 0 | J15: =H15+I15 -> 0
A16: =HLOOKUP(207,'Fund 20 Grants'!$D$2:$W$3,2,FALSE) -> #N/A | C16: =HLOOKUP(207,'Fund 20 Grants'!$D$2:$W$4,3,FALSE) -> #N/A | E16: 0 | F16: 0 | G16: 0 | H16: =IF(ISERROR(HLOOKUP(207,'Fund 20 Grants'!$D$2:$W$12,11,FALSE)),0,(HLOOKUP(207,'Fund 20 Grants'!$D$2:$W$12,11,FALSE))) -> 0 | I16: 0 | J16: =H16+I16 -> 0
A17: =HLOOKUP(208,'Fund 20 Grants'!$D$2:$W$3,2,FALSE) -> #N/A | C17: =HLOOKUP(208,'Fund 20 Grants'!$D$2:$W$4,3,FALSE) -> #N/A | E17: 0 | F17: 0 | G17: 0 | H17: =IF(ISERROR(HLOOKUP(208,'Fund 20 Grants'!$D$2:$W$12,11,FALSE)),0,(HLOOKUP(208,'Fund 20 Grants'!$D$2:$W$12,11,FALSE))) -> 0 | I17: 0 | J17: =H17+I17 -> 0
A18: =HLOOKUP(209,'Fund 20 Grants'!$D$2:$W$3,2,FALSE) -> #N/A | C18: =HLOOKUP(209,'Fund 20 Grants'!$D$2:$W$4,3,FALSE) -> #N/A | E18: 0 | F18: 0 | G18: 0 | H18: =IF(ISERROR(HLOOKUP(209,'Fund 20 Grants'!$D$2:$W$12,11,FALSE)),0,(HLOOKUP(209,'Fund 20 Grants'!$D$2:$W$12,11,FALSE))) -> 0 | I18: 0 | J18: =H18+I18 -> 0
A19: =HLOOKUP(210,'Fund 20 Grants'!$D$2:$W$3,2,FALSE) -> #N/A | C19: =HLOOKUP(210,'Fund 20 Grants'!$D$2:$W$4,3,FALSE) -> #N/A | E19: 0 | F19: 0 | G19: 0 | H19: =IF(ISERROR(HLOOKUP(210,'Fund 20 Grants'!$D$2:$W$12,11,FALSE)),0,(HLOOKUP(210,'Fund 20 Grants'!$D$2:$W$12,11,FALSE))) -> 0 | I19: 0 | J19: =H19+I19 -> 0
A20: =HLOOKUP(211,'Fund 20 Grants'!$D$2:$W$3,2,FALSE) -> #N/A | C20: =HLOOKUP(211,'Fund 20 Grants'!$D$2:$W$4,3,FALSE) -> #N/A | E20: 0 | F20: 0 | G20: 0 | H20: =IF(ISERROR(HLOOKUP(211,'Fund 20 Grants'!$D$2:$W$12,11,FALSE)),0,(HLOOKUP(211,'Fund 20 Grants'!$D$2:$W$12,11,FALSE))) -> 0 | I20: 0 | J20: =H20+I20 -> 0
A21: =HLOOKUP(212,'Fund 20 Grants'!$D$2:$W$3,2,FALSE) -> #N/A | C21: =HLOOKUP(212,'Fund 20 Grants'!$D$2:$W$4,3,FALSE) -> #N/A | E21: 0 | F21: 0 | G21: 0 | H21: =IF(ISERROR(HLOOKUP(212,'Fund 20 Grants'!$D$2:$W$12,11,FALSE)),0,(HLOOKUP(212,'Fund 20 Grants'!$D$2:$W$12,11,FALSE))) -> 0 | I21: 0 | J21: =H21+I21 -> 0
C23: TOTAL STATE GRANT REVENUE NOT INCLUDED IN OTHER FUNDS (Sum of lines 1-6) | E23: =SUM(E10:E21) -> 0 | F23: =SUM(F10:F21) -> 0 | G23: =SUM(G10:G21) -> 0 | H23: =SUM(H10:H21) -> 0 | I23: =SUM(I10:I21) -> 0 | J23: =SUM(J10:J21) -> 0
B25: FEDERAL FUNDS NOT IN OTHER FUNDS - LIST ALL FEDERAL GRANTS BY GRANT/PROJECT CODE AND TITLE
A26: See Note Below Regarding Source Codes for Federal Funds
A27: Grant/Project Code | C27: FEDERAL GRANT/PROJECT TITLE
C28: FEDERAL FUNDS NOT IN OTHER FUNDS
A29: =HLOOKUP(301,'Fund 20 Grants'!$D$2:$W$3,2,FALSE) -> #N/A | C29: =HLOOKUP(301,'Fund 20 Grants'!$D$2:$W$4,3,FALSE) -> #N/A | E29: 0 | F29: 0 | G29: 0 | H29: =IF(ISERROR(HLOOKUP(301,'Fund 20 Grants'!$D$2:$W$12,11,FALSE)),0,(HLOOKUP(301,'Fund 20 Grants'!$D$2:$W$12,11,FALSE))) -> 0 | I29: 0 | J29: =H29+I29 -> 0
A30: =HLOOKUP(302,'Fund 20 Grants'!$D$2:$W$3,2,FALSE) -> #N/A | C30: =HLOOKUP(302,'Fund 20 Grants'!$D$2:$W$4,3,FALSE) -> #N/A | E30: 0 | F30: 0 | G30: 0 | H30: =IF(ISERROR(HLOOKUP(302,'Fund 20 Grants'!$D$2:$W$12,11,FALSE)),0,(HLOOKUP(302,'Fund 20 Grants'!$D$2:$W$12,11,FALSE))) -> 0 | I30: 0 | J30: =H30+I30 -> 0
A31: =HLOOKUP(303,'Fund 20 Grants'!$D$2:$W$3,2,FALSE) -> #N/A | C31: =HLOOKUP(303,'Fund 20 Grants'!$D$2:$W$4,3,FALSE) -> #N/A | E31: 0 | F31: 0 | G31: 0 | H31: =IF(ISERROR(HLOOKUP(303,'Fund 20 Grants'!$D$2:$W$12,11,FALSE)),0,(HLOOKUP(303,'Fund 20 Grants'!$D$2:$W$12,11,FALSE))) -> 0 | I31: 0 | J31: =H31+I31 -> 0
A32: =HLOOKUP(304,'Fund 20 Grants'!$D$2:$W$3,2,FALSE) -> #N/A | C32: =HLOOKUP(304,'Fund 20 Grants'!$D$2:$W$4,3,FALSE) -> #N/A | E32: 0 | F32: 0 | G32: 0 | H32: =IF(ISERROR(HLOOKUP(304,'Fund 20 Grants'!$D$2:$W$12,11,FALSE)),0,(HLOOKUP(304,'Fund 20 Grants'!$D$2:$W$12,11,FALSE))) -> 0 | I32: 0 | J32: =H32+I32 -> 0
A33: =HLOOKUP(305,'Fund 20 Grants'!$D$2:$W$3,2,FALSE) -> #N/A | C33: =HLOOKUP(305,'Fund 20 Grants'!$D$2:$W$4,3,FALSE) -> #N/A | E33: 0 | F33: 0 | G33: 0 | H33: =IF(ISERROR(HLOOKUP(305,'Fund 20 Grants'!$D$2:$W$12,11,FALSE)),0,(HLOOKUP(305,'Fund 20 Grants'!$D$2:$W$12,11,FALSE))) -> 0 | I33: 0 | J33: =H33+I33 -> 0
A34: =HLOOKUP(306,'Fund 20 Grants'!$D$2:$W$3,2,FALSE) -> #N/A | C34: =HLOOKUP(306,'Fund 20 Grants'!$D$2:$W$4,3,FALSE) -> #N/A | E34: 0 | F34: 0 | G34: 0 | H34: =IF(ISERROR(HLOOKUP(306,'Fund 20 Grants'!$D$2:$W$12,11,FALSE)),0,(HLOOKUP(306,'Fund 20 Grants'!$D$2:$W$12,11,FALSE))) -> 0 | I34: 0 | J34: =H34+I34 -> 0
A35: =HLOOKUP(307,'Fund 20 Grants'!$D$2:$W$3,2,FALSE) -> #N/A | C35: =HLOOKUP(307,'Fund 20 Grants'!$D$2:$W$4,3,FALSE) -> #N/A | E35: 0 | F35: 0 | G35: 0 | H35: =IF(ISERROR(HLOOKUP(307,'Fund 20 Grants'!$D$2:$W$12,11,FALSE)),0,(HLOOKUP(307,'Fund 20 Grants'!$D$2:$W$12,11,FALSE))) -> 0 | I35: 0 | J35: =H35+I35 -> 0
A36: =HLOOKUP(308,'Fund 20 Grants'!$D$2:$W$3,2,FALSE) -> #N/A | C36: =HLOOKUP(308,'Fund 20 Grants'!$D$2:$W$4,3,FALSE) -> #N/A | E36: 0 | F36: 0 | G36: 0 | H36: =IF(ISERROR(HLOOKUP(308,'Fund 20 Grants'!$D$2:$W$12,11,FALSE)),0,(HLOOKUP(308,'Fund 20 Grants'!$D$2:$W$12,11,FALSE))) -> 0 | I36: 0 | J36: =H36+I36 -> 0
A37: =HLOOKUP(309,'Fund 20 Grants'!$D$2:$W$3,2,FALSE) -> #N/A | C37: =HLOOKUP(309,'Fund 20 Grants'!$D$2:$W$4,3,FALSE) -> #N/A | E37: 0 | F37: 0 | G37: 0 | H37: =IF(ISERROR(HLOOKUP(309,'Fund 20 Grants'!$D$2:$W$12,11,FALSE)),0,(HLOOKUP(309,'Fund 20 Grants'!$D$2:$W$12,11,FALSE))) -> 0 | I37: 0 | J37: =H37+I37 -> 0
A38: =HLOOKUP(310,'Fund 20 Grants'!$D$2:$W$3,2,FALSE) -> #N/A | C38: =HLOOKUP(310,'Fund 20 Grants'!$D$2:$W$4,3,FALSE) -> #N/A | E38: 0 | F38: 0 | G38: 0 | H38: =IF(ISERROR(HLOOKUP(310,'Fund 20 Grants'!$D$2:$W$12,11,FALSE)),0,(HLOOKUP(310,'Fund 20 Grants'!$D$2:$W$12,11,FALSE))) -> 0 | I38: 0 | J38: =H38+I38 -> 0
A39: =HLOOKUP(311,'Fund 20 Grants'!$D$2:$W$3,2,FALSE) -> #N/A | C39: =HLOOKUP(311,'Fund 20 Grants'!$D$2:$W$4,3,FALSE) -> #N/A | E39: 0 | F39: 0 | G39: 0 | H39: =IF(ISERROR(HLOOKUP(311,'Fund 20 Grants'!$D$2:$W$12,11,FALSE)),0,(HLOOKUP(311,'Fund 20 Grants'!$D$2:$W$12,11,FALSE))) -> 0 | I39: 0 | J39: =H39+I39 -> 0
A40: =HLOOKUP(312,'Fund 20 Grants'!$D$2:$W$3,2,FALSE) -> #N/A | C40: =HLOOKUP(312,'Fund 20 Grants'!$D$2:$W$4,3,FALSE) -> #N/A | E40: 0 | F40: 0 | G40: 0 | H40: =IF(ISERROR(HLOOKUP(312,'Fund 20 Grants'!$D$2:$W$12,11,FALSE)),0,(HLOOKUP(312,'Fund 20 Grants'!$D$2:$W$12,11,FALSE))) -> 0 | I40: 0 | J40: =H40+I40 -> 0
A41: =HLOOKUP(313,'Fund 20 Grants'!$D$2:$W$3,2,FALSE) -> #N/A | C41: =HLOOKUP(313,'Fund 20 Grants'!$D$2:$W$4,3,FALSE) -> #N/A | E41: 0 | F41: 0 | G41: 0 | H41: =IF(ISERROR(HLOOKUP(313,'Fund 20 Grants'!$D$2:$W$12,11,FALSE)),0,(HLOOKUP(313,'Fund 20 Grants'!$D$2:$W$12,11,FALSE))) -> 0 | I41: 0 | J41: =H41+I41 -> 0
A42: =HLOOKUP(314,'Fund 20 Grants'!$D$2:$W$3,2,FALSE) -> #N/A | C42: =HLOOKUP(314,'Fund 20 Grants'!$D$2:$W$4,3,FALSE) -> #N/A | E42: 0 | F42: 0 | G42: 0 | H42: =IF(ISERROR(HLOOKUP(314,'Fund 20 Grants'!$D$2:$W$12,11,FALSE)),0,(HLOOKUP(314,'Fund 20 Grants'!$D$2:$W$12,11,FALSE))) -> 0 | I42: 0 | J42: =H42+I42 -> 0
A43: =HLOOKUP(315,'Fund 20 Grants'!$D$2:$W$3,2,FALSE) -> #N/A | C43: =HLOOKUP(315,'Fund 20 Grants'!$D$2:$W$4,3,FALSE) -> #N/A | E43: 0 | F43: 0 | G43: 0 | H43: =IF(ISERROR(HLOOKUP(315,'Fund 20 Grants'!$D$2:$W$12,11,FALSE)),0,(HLOOKUP(315,'Fund 20 Grants'!$D$2:$W$12,11,FALSE))) -> 0 | I43: 0 | J43: =H43+I43 -> 0
A44: =HLOOKUP(316,'Fund 20 Grants'!$D$2:$W$3,2,FALSE) -> #N/A | C44: =HLOOKUP(316,'Fund 20 Grants'!$D$2:$W$4,3,FALSE) -> #N/A | E44: 0 | F44: 0 | G44: 0 | H44: =IF(ISERROR(HLOOKUP(316,'Fund 20 Grants'!$D$2:$W$12,11,FALSE)),0,(HLOOKUP(316,'Fund 20 Grants'!$D$2:$W$12,11,FALSE))) -> 0 | I44: 0 | J44: =H44+I44 -> 0
A45: =HLOOKUP(317,'Fund 20 Grants'!$D$2:$W$3,2,FALSE) -> #N/A | C45: =HLOOKUP(317,'Fund 20 Grants'!$D$2:$W$4,3,FALSE) -> #N/A | E45: 0 | F45: 0 | G45: 0 | H45: =IF(ISERROR(HLOOKUP(317,'Fund 20 Grants'!$D$2:$W$12,11,FALSE)),0,(HLOOKUP(317,'Fund 20 Grants'!$D$2:$W$12,11,FALSE))) -> 0 | I45: 0 | J45: =H45+I45 -> 0
A46: =HLOOKUP(318,'Fund 20 Grants'!$D$2:$W$3,2,FALSE) -> #N/A | C46: =HLOOKUP(318,'Fund 20 Grants'!$D$2:$W$4,3,FALSE) -> #N/A | E46: 0 | F46: 0 | G46: 0 | H46: =IF(ISERROR(HLOOKUP(318,'Fund 20 Grants'!$D$2:$W$12,11,FALSE)),0,(HLOOKUP(318,'Fund 20 Grants'!$D$2:$W$12,11,FALSE))) -> 0 | I46: 0 | J46: =H46+I46 -> 0
A47: =HLOOKUP(319,'Fund 20 Grants'!$D$2:$W$3,2,FALSE) -> #N/A | C47: =HLOOKUP(319,'Fund 20 Grants'!$D$2:$W$4,3,FALSE) -> #N/A | E47: 0 | F47: 0 | G47: 0 | H47: =IF(ISERROR(HLOOKUP(319,'Fund 20 Grants'!$D$2:$W$12,11,FALSE)),0,(HLOOKUP(319,'Fund 20 Grants'!$D$2:$W$12,11,FALSE))) -> 0 | I47: 0 | J47: =H47+I47 -> 0
A48: =HLOOKUP(320,'Fund 20 Grants'!$D$2:$W$3,2,FALSE) -> #N/A | C48: =HLOOKUP(320,'Fund 20 Grants'!$D$2:$W$4,3,FALSE) -> #N/A | E48: 0 | F48: 0 | G48: 0 | H48: =IF(ISERROR(HLOOKUP(320,'Fund 20 Grants'!$D$2:$W$12,11,FALSE)),0,(HLOOKUP(320,'Fund 20 Grants'!$D$2:$W$12,11,FALSE))) -> 0 | I48: 0 | J48: =H48+I48 -> 0
C50: TOTAL FEDERAL GRANT REVENUE NOT INCLUDED IN OTHER FUNDS (Sum of lines 8-17) | E50: =SUM(E29:E49) -> 0 | F50: =SUM(F29:F49) -> 0 | G50: =SUM(G29:G49) -> 0 | H50: =SUM(H29:H49) -> 0 | I50: =SUM(I29:I49) -> 0 | J50: =SUM(J29:J49) -> 0
B52: LOCAL AND INTERMEDIATE GRANTS NOT IN OTHER FUNDS - LIST ALL LOCAL AND INTERMEDIATE GRANTS BY GRANT/PROJECT CODE AND TITLE
A53: Grant/Project Code | C53: LOCAL AND INTERMEDIATE GRANT/PROJECT TITLE
A54: =HLOOKUP(101,'Fund 20 Grants'!$D$2:$W$3,2,FALSE) -> 0 | C54: =HLOOKUP(101,'Fund 20 Grants'!$D$2:$W$4,3,FALSE) -> 0 | E54: 0 | F54: 0 | G54: 0 | H54: =IF(ISERROR(HLOOKUP(101,'Fund 20 Grants'!$D$2:$W$12,11,FALSE)),0,(HLOOKUP(101,'Fund 20 Grants'!$D$2:$W$12,11,FALSE))) -> 0 | I54: 0 | J54: =H54+I54 -> 0
A55: =HLOOKUP(102,'Fund 20 Grants'!$D$2:$W$3,2,FALSE) -> 0 | C55: =HLOOKUP(102,'Fund 20 Grants'!$D$2:$W$4,3,FALSE) -> 0 | E55: 0 | F55: 0 | G55: 0 | H55: =IF(ISERROR(HLOOKUP(102,'Fund 20 Grants'!$D$2:$W$12,11,FALSE)),0,(HLOOKUP(102,'Fund 20 Grants'!$D$2:$W$12,11,FALSE))) -> 0 | I55: 0 | J55: =H55+I55 -> 0
A56: =HLOOKUP(103,'Fund 20 Grants'!$D$2:$W$3,2,FALSE) -> 0 | C56: =HLOOKUP(103,'Fund 20 Grants'!$D$2:$W$4,3,FALSE) -> 0 | E56: 0 | F56: 0 | G56: 0 | H56: =IF(ISERROR(HLOOKUP(103,'Fund 20 Grants'!$D$2:$W$12,11,FALSE)),0,(HLOOKUP(103,'Fund 20 Grants'!$D$2:$W$12,11,FALSE))) -> 0 | I56: 0 | J56: =H56+I56 -> 0
A57: =HLOOKUP(104,'Fund 20 Grants'!$D$2:$W$3,2,FALSE) -> 0 | C57: =HLOOKUP(104,'Fund 20 Grants'!$D$2:$W$4,3,FALSE) -> 0 | E57: 0 | F57: 0 | G57: 0 | H57: =IF(ISERROR(HLOOKUP(104,'Fund 20 Grants'!$D$2:$W$12,11,FALSE)),0,(HLOOKUP(104,'Fund 20 Grants'!$D$2:$W$12,11,FALSE))) -> 0 | I57: 0 | J57: =H57+I57 -> 0
A58: =HLOOKUP(105,'Fund 20 Grants'!$D$2:$W$3,2,FALSE) -> 0 | C58: =HLOOKUP(105,'Fund 20 Grants'!$D$2:$W$4,3,FALSE) -> 0 | E58: 0 | F58: 0 | G58: 0 | H58: =IF(ISERROR(HLOOKUP(105,'Fund 20 Grants'!$D$2:$W$12,11,FALSE)),0,(HLOOKUP(105,'Fund 20 Grants'!$D$2:$W$12,11,FALSE))) -> 0 | I58: 0 | J58: =H58+I58 -> 0
A59: =HLOOKUP(106,'Fund 20 Grants'!$D$2:$W$3,2,FALSE) -> 0 | C59: =HLOOKUP(106,'Fund 20 Grants'!$D$2:$W$4,3,FALSE) -> 0 | E59: 0 | F59: 0 | G59: 0 | H59: =IF(ISERROR(HLOOKUP(106,'Fund 20 Grants'!$D$2:$W$12,11,FALSE)),0,(HLOOKUP(106,'Fund 20 Grants'!$D$2:$W$12,11,FALSE))) -> 0 | I59: 0 | J59: =H59+I59 -> 0
A60: =HLOOKUP(107,'Fund 20 Grants'!$D$2:$W$3,2,FALSE) -> 0 | C60: =HLOOKUP(107,'Fund 20 Grants'!$D$2:$W$4,3,FALSE) -> 0 | E60: 0 | F60: 0 | G60: 0 | H60: =IF(ISERROR(HLOOKUP(107,'Fund 20 Grants'!$D$2:$W$12,11,FALSE)),0,(HLOOKUP(107,'Fund 20 Grants'!$D$2:$W$12,11,FALSE))) -> 0 | I60: 0 | J60: =H60+I60 -> 0
A61: =HLOOKUP(108,'Fund 20 Grants'!$D$2:$W$3,2,FALSE) -> 0 | C61: =HLOOKUP(108,'Fund 20 Grants'!$D$2:$W$4,3,FALSE) -> 0 | E61: 0 | F61: 0 | G61: 0 | H61: =IF(ISERROR(HLOOKUP(108,'Fund 20 Grants'!$D$2:$W$12,11,FALSE)),0,(HLOOKUP(108,'Fund 20 Grants'!$D$2:$W$12,11,FALSE))) -> 0 | I61: 0 | J61: =H61+I61 -> 0
A62: =HLOOKUP(109,'Fund 20 Grants'!$D$2:$W$3,2,FALSE) -> 0 | C62: =HLOOKUP(109,'Fund 20 Grants'!$D$2:$W$4,3,FALSE) -> 0 | E62: 0 | F62: 0 | G62: 0 | H62: =IF(ISERROR(HLOOKUP(109,'Fund 20 Grants'!$D$2:$W$12,11,FALSE)),0,(HLOOKUP(109,'Fund 20 Grants'!$D$2:$W$12,11,FALSE))) -> 0 | I62: 0 | J62: =H62+I62 -> 0
A63: =HLOOKUP(110,'Fund 20 Grants'!$D$2:$W$3,2,FALSE) -> 0 | C63: =HLOOKUP(110,'Fund 20 Grants'!$D$2:$W$4,3,FALSE) -> 0 | E63: 0 | F63: 0 | G63: 0 | H63: =IF(ISERROR(HLOOKUP(110,'Fund 20 Grants'!$D$2:$W$12,11,FALSE)),0,(HLOOKUP(110,'Fund 20 Grants'!$D$2:$W$12,11,FALSE))) -> 0 | I63: 0 | J63: =H63+I63 -> 0
A65: 1000-2999 | C65: TOTAL LOCAL AND INTERMEDIATE GRANT REVENUE NOT INCLUDED IN OTHER FUNDS | E65: =SUM(E54:E64) -> 0 | F65: =SUM(F54:F64) -> 0 | G65: =SUM(G54:G64) -> 0 | H65: =SUM(H54:H64) -> 0 | I65: =SUM(I54:I64) -> 0 | J65: =SUM(J54:J64) -> 0
C67: TOTAL GRANTS NOT IN OTHER FUNDS | E67: =E23+E50+E65 -> 0 | F67: =F23+F50+F65 -> 0 | G67: =G23+G50+G65 -> 0 | H67: =H23+H50+H65 -> 0 | I67: =I23+I50+I65 -> 0 | J67: =J23+J50+J65 -> 0
B69: TRANSFERS FROM(POSITIVE)/TO(NEGATIVE) OTHER FUNDS - LIST ALL GRANTS BY GRANT/PROJECT CODE, TITLE AND FUND
A70: Grant/Project Code | C70: GRANT/PROJECT TITLE AND FUND TRANSFERRED FROM/TO
A71: 52XX | B71: 5. | C71: Transfer From(+)/To(-)________________Fund(s) (Net to zero across all funds)* NOTE-1 | E71: 0 | F71: 0 | G71: 0 | H71: 0 | I71: 0 | J71: =+H71+I71 -> 0
B73: OTHER SOURCES - LIST ALL GRANTS BY GRANT/PROJECT CODE, TITLE AND FUND
A74: Grant/Project Code | C74: GRANT/PROJECT TITLE
E75: 0 | F75: 0 | G75: 0 | H75: 0 | I75: 0 | J75: =H75+I75 -> 0
E76: 0 | F76: 0 | G76: 0 | H76: 0 | I76: 0 | J76: =H76+I76 -> 0
E77: 0 | F77: 0 | G77: 0 | H77: 0 | I77: 0 | J77: =H77+I77 -> 0
E78: 0 | F78: 0 | G78: 0 | H78: 0 | I78: 0 | J78: =H78+I78 -> 0
E79: 0 | F79: 0 | G79: 0 | H79: 0 | I79: 0 | J79: =H79+I79 -> 0
E80: 0 | F80: 0 | G80: 0 | H80: 0 | I80: 0 | J80: =H80+I80 -> 0
E81: 0 | F81: 0 | G81: 0 | H81: 0 | I81: 0 | J81: =H81+I81 -> 0
E82: 0 | F82: 0 | G82: 0 | H82: 0 | I82: 0 | J82: =H82+I82 -> 0
E83: 0 | F83: 0 | G83: 0 | H83: 0 | I83: 0 | J83: =H83+I83 -> 0
E84: 0 | F84: 0 | G84: 0 | H84: 0 | I84: 0 | J84: =H84+I84 -> 0
C86: OTHER SOURCES | E86: =SUM(E75:E85) -> 0 | F86: =SUM(F75:F85) -> 0 | G86: =SUM(G75:G85) -> 0 | H86: =SUM(H75:H85) -> 0 | I86: =SUM(I75:I85) -> 0 | J86: =SUM(J75:J85) -> 0
A88: TOTAL STATE, FEDERAL AND LOCAL DESIGNATED PURPOSE GRANT REVENUE AND OTHER SOURCES INCLUDING BFB | E88: =E6+E67+E71+E86 -> 0 | F88: =F6+F67+F71+F86 -> 0 | G88: =G6+G67+G71+G86 -> 0 | H88: =H6+H67+H71+H86 -> 0 | I88: =I6+I67+I71+I86 -> 0 | J88: =J6+J67+J71+J86 -> 0
A90: NOTE-1: | C90: If you treat Transfers Out as an expenditure - report such amounts here:
A91: 52XX | B91: 5a | C91: Transfer To________________Fund(s) (input as a positive number on this line) * | E91: 0 | F91: 0 | G91: 0 | H91: 0 | I91: 0 | J91: =SUM(H91+I91) -> 0
C94: EXPENDITURES AND OTHER USES
A95: Grant/Project Code | C95: STATE GRANT/PROJECT TITLE
C96: STATE FUNDS NOT IN OTHER FUNDS
A97: =HLOOKUP(201,'Fund 20 Grants'!$D$2:$W$3,2,FALSE) -> #N/A | C97: =HLOOKUP(201,'Fund 20 Grants'!$D$2:$W$4,3,FALSE) -> #N/A | E97: 0 | F97: 0 | G97: 0 | H97: =IF(ISERROR(HLOOKUP(201,'Fund 20 Grants'!$D$2:$W$113,112,FALSE)),0,(HLOOKUP(201,'Fund 20 Grants'!$D$2:$W$113,112,FALSE))) -> 0 | I97: 0 | J97: =H97+I97 -> 0
A98: =HLOOKUP(202,'Fund 20 Grants'!$D$2:$W$3,2,FALSE) -> #N/A | C98: =HLOOKUP(202,'Fund 20 Grants'!$D$2:$W$4,3,FALSE) -> #N/A | E98: 0 | F98: 0 | G98: 0 | H98: =IF(ISERROR(HLOOKUP(202,'Fund 20 Grants'!$D$2:$W$13,112,FALSE)),0,(HLOOKUP(202,'Fund 20 Grants'!$D$2:$W$113,112,FALSE))) -> 0 | I98: 0 | J98: =H98+I98 -> 0
A99: =HLOOKUP(203,'Fund 20 Grants'!$D$2:$W$3,2,FALSE) -> #N/A | C99: =HLOOKUP(203,'Fund 20 Grants'!$D$2:$W$4,3,FALSE) -> #N/A | E99: 0 | F99: 0 | G99: 0 | H99: =IF(ISERROR(HLOOKUP(203,'Fund 20 Grants'!$D$2:$W$113,12,FALSE)),0,(HLOOKUP(203,'Fund 20 Grants'!$D$2:$W$113,112,FALSE))) -> 0 | I99: 0 | J99: =H99+I99 -> 0
A100: =HLOOKUP(204,'Fund 20 Grants'!$D$2:$W$3,2,FALSE) -> #N/A | C100: =HLOOKUP(204,'Fund 20 Grants'!$D$2:$W$4,3,FALSE) -> #N/A | E100: 0 | F100: 0 | G100: 0 | H100: =IF(ISERROR(HLOOKUP(204,'Fund 20 Grants'!$D$2:$W$113,112,FALSE)),0,(HLOOKUP(204,'Fund 20 Grants'!$D$2:$W$113,112,FALSE))) -> 0 | I100: 0 | J100: =H100+I100 -> 0
A101: =HLOOKUP(205,'Fund 20 Grants'!$D$2:$W$3,2,FALSE) -> #N/A | C101: =HLOOKUP(205,'Fund 20 Grants'!$D$2:$W$4,3,FALSE) -> #N/A | E101: 0 | F101: 0 | G101: 0 | H101: =IF(ISERROR(HLOOKUP(205,'Fund 20 Grants'!$D$2:$W$113,112,FALSE)),0,(HLOOKUP(205,'Fund 20 Grants'!$D$2:$W$113,112,FALSE))) -> 0 | I101: 0 | J101: =H101+I101 -> 0
A102: =HLOOKUP(206,'Fund 20 Grants'!$D$2:$W$3,2,FALSE) -> #N/A | C102: =HLOOKUP(206,'Fund 20 Grants'!$D$2:$W$4,3,FALSE) -> #N/A | E102: 0 | F102: 0 | G102: 0 | H102: =IF(ISERROR(HLOOKUP(206,'Fund 20 Grants'!$D$2:$W$113,112,FALSE)),0,(HLOOKUP(206,'Fund 20 Grants'!$D$2:$W$113,112,FALSE))) -> 0 | I102: 0 | J102: =H102+I102 -> 0
A103: =HLOOKUP(207,'Fund 20 Grants'!$D$2:$W$3,2,FALSE) -> #N/A | C103: =HLOOKUP(207,'Fund 20 Grants'!$D$2:$W$4,3,FALSE) -> #N/A | E103: 0 | F103: 0 | G103: 0 | H103: =IF(ISERROR(HLOOKUP(207,'Fund 20 Grants'!$D$2:$W$113,112,FALSE)),0,(HLOOKUP(207,'Fund 20 Grants'!$D$2:$W$113,112,FALSE))) -> 0 | I103: 0 | J103: =H103+I103 -> 0
A104: =HLOOKUP(208,'Fund 20 Grants'!$D$2:$W$3,2,FALSE) -> #N/A | C104: =HLOOKUP(208,'Fund 20 Grants'!$D$2:$W$4,3,FALSE) -> #N/A | E104: 0 | F104: 0 | G104: 0 | H104: =IF(ISERROR(HLOOKUP(208,'Fund 20 Grants'!$D$2:$W$113,112,FALSE)),0,(HLOOKUP(208,'Fund 20 Grants'!$D$2:$W$113,112,FALSE))) -> 0 | I104: 0 | J104: =H104+I104 -> 0
A105: =HLOOKUP(209,'Fund 20 Grants'!$D$2:$W$3,2,FALSE) -> #N/A | C105: =HLOOKUP(209,'Fund 20 Grants'!$D$2:$W$4,3,FALSE) -> #N/A | E105: 0 | F105: 0 | G105: 0 | H105: =IF(ISERROR(HLOOKUP(209,'Fund 20 Grants'!$D$2:$W$113,112,FALSE)),0,(HLOOKUP(209,'Fund 20 Grants'!$D$2:$W$113,112,FALSE))) -> 0 | I105: 0 | J105: =H105+I105 -> 0
A106: =HLOOKUP(210,'Fund 20 Grants'!$D$2:$W$3,2,FALSE) -> #N/A | C106: =HLOOKUP(210,'Fund 20 Grants'!$D$2:$W$4,3,FALSE) -> #N/A | E106: 0 | F106: 0 | G106: 0 | H106: =IF(ISERROR(HLOOKUP(210,'Fund 20 Grants'!$D$2:$W$113,112,FALSE)),0,(HLOOKUP(210,'Fund 20 Grants'!$D$2:$W$113,112,FALSE))) -> 0 | I106: 0 | J106: =H106+I106 -> 0
A107: =HLOOKUP(211,'Fund 20 Grants'!$D$2:$W$3,2,FALSE) -> #N/A | C107: =HLOOKUP(211,'Fund 20 Grants'!$D$2:$W$4,3,FALSE) -> #N/A | E107: 0 | F107: 0 | G107: 0 | H107: =IF(ISERROR(HLOOKUP(211,'Fund 20 Grants'!$D$2:$W$113,112,FALSE)),0,(HLOOKUP(211,'Fund 20 Grants'!$D$2:$W$113,112,FALSE))) -> 0 | I107: 0 | J107: =H107+I107 -> 0
A108: =HLOOKUP(212,'Fund 20 Grants'!$D$2:$W$3,2,FALSE) -> #N/A | C108: =HLOOKUP(212,'Fund 20 Grants'!$D$2:$W$4,3,FALSE) -> #N/A | E108: 0 | F108: 0 | G108: 0 | H108: =IF(ISERROR(HLOOKUP(212,'Fund 20 Grants'!$D$2:$W$113,112,FALSE)),0,(HLOOKUP(212,'Fund 20 Grants'!$D$2:$W$113,112,FALSE))) -> 0 | I108: 0 | J108: =H108+I108 -> 0
C110: TOTAL STATE GRANT EXPENDITURES NOT INCLUDED IN OTHER FUNDS (Sum of lines 1-6) | E110: =SUM(E97:E108) -> 0 | F110: =SUM(F97:F108) -> 0 | G110: =SUM(G97:G108) -> 0 | H110: =SUM(H97:H108) -> 0 | I110: =SUM(I97:I108) -> 0 | J110: =SUM(J97:J108) -> 0
B112: FEDERAL FUNDS NOT IN OTHER FUNDS - LIST ALL FEDERAL GRANTS BY GRANT/PROJECT CODE AND TITLE
A113: Grant/Project Code | C113: FEDERAL GRANT/PROJECT TITLE
C114: FEDERAL FUNDS NOT IN OTHER FUNDS
A115: =HLOOKUP(301,'Fund 20 Grants'!$D$2:$W$3,2,FALSE) -> #N/A | C115: =HLOOKUP(301,'Fund 20 Grants'!$D$2:$W$4,3,FALSE) -> #N/A | E115: 0 | F115: 0 | G115: 0 | H115: =IF(ISERROR(HLOOKUP(301,'Fund 20 Grants'!$D$2:$W$113,112,FALSE)),0,(HLOOKUP(301,'Fund 20 Grants'!$D$2:$W$113,112,FALSE))) -> 0 | I115: 0 | J115: =H115+I115 -> 0
A116: =HLOOKUP(302,'Fund 20 Grants'!$D$2:$W$3,2,FALSE) -> #N/A | C116: =HLOOKUP(302,'Fund 20 Grants'!$D$2:$W$4,3,FALSE) -> #N/A | E116: 0 | F116: 0 | G116: 0 | H116: =IF(ISERROR(HLOOKUP(302,'Fund 20 Grants'!$D$2:$W$113,112,FALSE)),0,(HLOOKUP(302,'Fund 20 Grants'!$D$2:$W$113,112,FALSE))) -> 0 | I116: 0 | J116: =H116+I116 -> 0
...

Sheet CapRes
A1: School District | C1: =+'Page 1 - FY2013-14'!B5 -> 0 | D1: District Code | E1: =+'Page 1 - FY2013-14'!F7 -> 0 | G1: * Round to Nearest Dollar *
A2: Fund 21: CAPITAL RESERVE SPECIAL REVENUE FUND
D3: Prior Year Actual - Audited FY11-12 | E3: Current Fiscal Year - Budgeted FY12-13 | F3: Current Fiscal Year - Projected FY12-13 | G3: Original Ensuing Fiscal Year - Budget FY13-14 | H3: Adjustments Ensuing Fiscal Year - Budget FY13-14 | I3: Revised Ensuing Fiscal Year - Budget FY13-14
H4: Record Inceases to revenue are positive amounts and Decreases as negatives | I4: Figures (Totals) which will appear on Budget Form to Submit to CDE
A6: Codes: | B6: BEGINNING FUND BALANCE | D6: 0 | E6: 0 | F6: 0 | G6: 0 | H6: 0 | I6: =G6+H6 -> 0
A7: Source | C7: REVENUE AND OTHER SOURCES
A8: 1110 | B8: 1. | C8: Property Taxes | D8: 0 | E8: 0 | F8: 0 | G8: 0 | H8: 0 | I8: =G8+H8 -> 0
A9: 1120 | B9: 2. | C9: Specific Ownership Taxes | D9: 0 | E9: 0 | F9: 0 | G9: 0 | H9: 0 | I9: =G9+H9 -> 0
A10: 1140-1190 | B10: 3. | C10: Other Taxes | D10: 0 | E10: 0 | F10: 0 | G10: 0 | H10: 0 | I10: =G10+H10 -> 0
A11: 1500 | B11: 4. | C11: Earnings on Investments | D11: 0 | E11: 0 | F11: 0 | G11: 0 | H11: 0 | I11: =G11+H11 -> 0
A12: 19XX | B12: 5. | C12: Other Local Sources | D12: 0 | E12: 0 | F12: 0 | G12: 0 | H12: 0 | I12: =G12+H12 -> 0
A13: 2000 | B13: 6. | C13: Intermediate Sources | D13: 0 | E13: 0 | F13: 0 | G13: 0 | H13: 0 | I13: =G13+H13 -> 0
A14: 3110 | B14: 7. | C14: State Equalization | D14: 0 | E14: 0 | F14: 0 | G14: 0 | H14: 0 | I14: =G14+H14 -> 0
A15: 3112 | B15: 8. | C15: Capital Construction | D15: 0 | E15: 0 | F15: 0 | G15: 0 | H15: 0 | I15: =G15+H15 -> 0
A16: 3113 | B16: 9. | C16: Charter School Capital Construction | D16: 0 | E16: 0 | F16: 0 | G16: 0 | H16: 0 | I16: =G16+H16 -> 0
A17: 3XXX | B17: 10. | C17: Other State Sources | D17: 0 | E17: 0 | F17: 0 | G17: 0 | H17: 0 | I17: =G17+H17 -> 0
A18: 4000-4999 | B18: 11. | C18: Federal Sources | D18: 0 | E18: 0 | F18: 0 | G18: 0 | H18: 0 | I18: =G18+H18 -> 0
A19: 52XX | B19: 12. | C19: Transfer From(+)/To(-)________________Fund(s) (Net to zero across all funds)* NOTE-1 | D19: 0 | E19: 0 | F19: 0 | G19: 0 | H19: 0 | I19: =G19+H19 -> 0
... A22: 5600 | B22: 15. | C22: Allocation From General Fund** (Optional starting in FY09-10) | D22: 0 | E22: 0 | F22: 0 | G22: 0 | H22: 0 | I22: =G22+H22 -> 0
B23: 16. | C23: Other Revenue | D23: 0 | E23: 0 | F23: 0 | G23: 0 | H23: 0 | I23: =G23+H23 -> 0
B25: 17. | C25: TOTAL REVENUE (Sum of lines 1-16) | D25: =SUM(D8:D23) -> 0 | E25: =SUM(E8:E23) -> 0 | F25: =SUM(F8:F23) -> 0 | G25: =SUM(G8:G23) -> 0 | H25: =SUM(H8:H23) -> 0 | I25: =SUM(I8:I23) -> 0
A27: TOTAL REVENUE INCLUDING BEGINNING FUND BALANCE (Sum of line 17 and BFB) | D27: =D6+D25 -> 0 | E27: =E6+E25 -> 0 | F27: =F6+F25 -> 0 | G27: =G6+G25 -> 0 | H27: =H6+H25 -> 0 | I27: =I6+I25 -> 0
A29: NOTE-1: | C29: If you treat Transfers Out as an expenditure - report such amounts here:
A30: 52XX | B30: 12a | C30: Transfer To________________Fund(s) (input as a positive number on this line) | D30: 0 | E30: 0 | F30: 0 | G30: 0 | H30: 0 | I30: =SUM(G30+H30) -> 0
A33: Object | C33: EXPENDITURES AND OTHER USES
C34: INSTRUCTIONAL PROGRAMS - 0010 THROUGH 2099
A35: 0700 | B35: 18. | C35: Property | D35: 0 | E35: 0 | F35: 0 | G35: 0 | H35: 0 | I35: =G35+H35 -> 0
A36: 0710 | B36: 19. | C36: Land and Improvements | D36: 0 | E36: 0 | F36: 0 | G36: 0 | H36: 0 | I36: =G36+H36 -> 0
A37: 0720 | B37: 20. | C37: Buildings | D37: 0 | E37: 0 | F37: 0 | G37: 0 | H37: 0 | I37: =G37+H37 -> 0
A38: 0721 | B38: 21. | C38: Lease Holding Improvements | D38: 0 | E38: 0 | F38: 0 | G38: 0 | H38: 0 | I38: =G38+H38 -> 0
A39: 0722 | B39: 22. | C39: New Construction | D39: 0 | E39: 0 | F39: 0 | G39: 0 | H39: 0 | I39: =G39+H39 -> 0
A40: 0723 | B40: 23 | C40: Major Renovations | D40: 0 | E40: 0 | F40: 0 | G40: 0 | H40: 0 | I40: =G40+H40 -> 0
A41: 0730 | B41: 24 | C41: Equipment (including unlicensed vehicles) | D41: 0 | E41: 0 | F41: 0 | G41: 0 | H41: 0 | I41: =G41+H41 -> 0
A42: 0732 | B42: 25 | C42: Licensed Vehicles (e.g., buses and vans) | D42: 0 | E42: 0 | F42: 0 | G42: 0 | H42: 0 | I42: =G42+H42 -> 0
A43: 0740 | B43: 26 | C43: Depreciation | D43: 0 | E43: 0 | F43: 0 | G43: 0 | H43: 0 | I43: =G43+H43 -> 0
B44: 27 | C44: Other Expenditures | D44: 0 | E44: 0 | F44: 0 | G44: 0 | H44: 0 | I44: =G44+H44 -> 0
