Workbook

Sheet Compute
A1: Compute Costs
A2: DISCLAIMER: This is a sample worksheet making assumptions for a specific scenario, and without considering partner discounts. You can use this worksheet as a sample to get you started. | K2: Legend:
L3: Azure costs that could require update
A4: VM Size | B4: Instances | C4: Hourly $ | D4: Monthly $/Instance | E4: Monthly $/Total | F4: Yearly $ Total/Instance | G4: Yearly $ Total | L4: Input values that are source for calculations on the page
A5: xs | B5: 0 | C5: 0.04 | D5: =24*365*C5/12 -> 29.2 | E5: =D5*B5 -> 0 | F5: =24*365*C5 -> 350.4 | G5: =F5*B5 -> 0
A6: s | B6: =MAX($G$39/1.75,2) -> 2 | C6: 0.12 | D6: =24*365*C6/12 -> 87.6 | E6: =D6*B6 -> 175.2 | F6: =24*365*C6 -> 1051.2 | G6: =F6*B6 -> 2102.4
A7: m | B7: =IF(B6>2,MAX($G$39/3.5,2),0) -> 0 | C7: 0.24 | D7: =24*365*C7/12 -> 175.2 | E7: =D7*B7 -> 0 | F7: =24*365*C7 -> 2102.4 | G7: =F7*B7 -> 0
A8: l | B8: =IF(B7>2,MAX($G$39/7,2),0) -> 0 | C8: 0.48 | D8: =24*365*C8/12 -> 350.4 | E8: =D8*B8 -> 0 | F8: =24*365*C8 -> 4204.8 | G8: =F8*B8 -> 0
A9: xl | B9: =IF(B8>2,MAX($G$39/14,2),0) -> 0 | C9: 0.96 | D9: =24*365*C9/12 -> 700.8 | E9: =D9*B9 -> 0 | F9: =24*365*C9 -> 8409.6 | G9: =F9*B9 -> 0
E10: =MAX(E6:E9) -> 175.2 | G10: =MAX(G6:G9) -> 2102.4
A15: Estimation Worksheet
A16: Assumptions:
A17: fewer producers online consuming media than consumers
A18: % of concurrent users is estimated
A19: 100 KB/S transfer for media, less for small pages
A20: memory usage per second uses multiplier from page/media size buffer
A23: How many users?
B24: Current | C24: Q1 | D24: Q2 | E24: Q3 | F24: Q4
A25: # producers | B25: 50 | C25: 50 | D25: =(C25*$H25)+C25 -> 75 | E25: =(D25*$H25)+D25 -> 112.5 | F25: =(E25*$H25)+E25 -> 168.75 | H25: 0.5 | I25: growth per quarter
A26: # consumers | B26: 100 | C26: 100 | D26: =(C26*$H26)+C26 -> 300 | E26: =(D26*$H26)+D26 -> 900 | F26: =(E26*$H26)+E26 -> 2700 | H26: 2 | I26: growth per quarter
A27: How many users online? | B27: Percent | C27: # Users
A28: % producers online | B28: 0.03 | C28: =B28*B25 -> 1.5
A29: % consumers online | B29: 0.03 | C29: =B29*B26 -> 3
A32: What bandwidth and memory requirements?
B33: Usage | C33: KB/s | D33: total bandwidth (KB/s) | E33: total bandwidth (MB/s) | F33: Memory Usage (KB/s) | G33: Memory Usage (GB/s)
A34: Usage by user
A35: # concurrent media producers | B35: =C28 -> 1.5 | C35: 100 | D35: =C35*B35 -> 150 | E35: =D35/1000000 -> 0.00015 | F35: =B35*C35*$G$40 -> 450 | G35: =F35/1000000 -> 0.00045
A36: # concurrent media consumers | B36: =C29 -> 3 | C36: 100 | D36: =C36*B36 -> 300 | E36: =D36/1000000 -> 0.0003 | F36: =B36*C36*$G$40 -> 900 | G36: =F36/1000000 -> 0.0009
A37: # pages / sec | B37: 300 | C37: 10 | D37: =C37*B37 -> 3000 | E37: =D37/1000000 -> 0.003 | F37: =B37*C37*$G$40 -> 9000 | G37: =F37/1000000 -> 0.009
A38: # reports /sec | B38: 100 | C38: 100 | D38: =C38*B38 -> 10000 | E38: =D38/1000000 -> 0.01 | F38: =B38*C38*$G$40 -> 30000 | G38: =F38/1000000 -> 0.03
E39: =SUM(E35:E38) -> 0.01345 | G39: =SUM(G35:G38) -> 0.04035
F40: Memory Multiplier | G40: 3
A42: Bandwidth concerns are primarily related to concurrent media uploads/downloads, concurrent page requests and related upload/download transfers.
A43: Memory concerns vary by application, should try to reduce concurrent memory requirements by chunking or streaming media.
A44: CPU usage and diskspace also matter but are harder to predict, monitor trends and increase accordingly.

Sheet Storage
A1: Storage and CDN Costs
A2: DISCLAIMER: This is a sample worksheet making assumptions for a specific scenario, and without considering partner discounts. You can use this worksheet as a sample to get you started. | N2: Legend:
O3: Azure costs that could require update
A4: Storage Costs | C4: Q1 | D4: Q2 | E4: Q3 | F4: Q4 | O4: Input values that are source for calculations on the page
A5: $/GB | B5: 0.14 | H5: Assumptions:
A6: Daily Average (GB) | C6: =C42 -> 12.51018 | D6: =D42 -> 18.76545 | E6: =E42 -> 28.148715 | F6: =F42 -> 42.224693 | H6: Quarterly totals are same as daily average for quarter
A7: Monthly cost | C7: =C6*$B$5 -> 1.7514252 | D7: =D6*$B$5 -> 2.627163 | E7: =E6*$B$5 -> 3.9408201 | F7: =F6*$B$5 -> 5.911457 | H7: Using producer users as cost point, consumers pay for media downloads, cost is covered by sale
A8: Monthly cost per producer | C8: =C7/C18 -> 0.035028504 | D8: =D7/D18 -> 0.03502884 | E8: =E7/E18 -> 0.035029512 | F8: =F7/F18 -> 0.035030856
A9: $/10K storage transactions | B9: 0.01
A10: Monthly costs | C10: =C65*$B$9 -> 0.07745 | D10: =D65*$B$9 -> 0.120875 | E10: =E65*$B$9 -> 0.2109125 | F10: =F65*$B$9 -> 0.42066875
A11: Monthly cost per producer | C11: =C10/C18 -> 0.001549 | D11: =D10/D18 -> 0.0016116667 | E11: =E10/E18 -> 0.0018747778 | F11: =F10/F18 -> 0.0024928519
A14: How many bytes per record and # record estimates? | K14: Assumptions:
B15: bytes/rec | C15: Q1 | D15: Q2 | E15: Q3 | F15: Q4 | K15: average 50 media records uploaded by each publisher account
A16: media information | B16: 2000 | C16: =C18*50 -> 2500 | D16: =D18*50 -> 3750 | E16: =E18*50 -> 5625 | F16: =F18*50 -> 8437.5 | K16: average 1 profile per user
A17: profile | B17: 1000 | C17: =C18+C19 -> 150 | D17: =D18+D19 -> 375 | E17: =E18+E19 -> 1012.5 | F17: =F18+F19 -> 2868.75 | K17: fewer publishers than consumer users
A18: producer users | B18: 200 | C18: 50 | D18: =(C18*$G$18)+C18 -> 75 | E18: =(D18*$G$18)+D18 -> 112.5 | F18: =(E18*$G$18)+E18 -> 168.75 | G18: 0.5 | H18: growth per quarter | K18: consumer users will grow faster
A19: consumer users | B19: 200 | C19: 100 | D19: =(C19*$G$19)+C19 -> 300 | E19: =(D19*$G$19)+D19 -> 900 | F19: =(E19*$G$19)+E19 -> 2700 | G19: 2 | H19: growth per quarter
A20: total table storage records | C20: =SUM(C16:C19) -> 2800 | D20: =SUM(D16:D19) -> 4500 | E20: =SUM(E16:E19) -> 7650 | F20: =SUM(F16:F19) -> 14175
A22: How many bytes table storage by quarter?
C23: Q1 | D23: Q2 | E23: Q3 | F23: Q4
A24: media information | C24: =C16*B16 -> 5000000 | D24: =D16*B16 -> 7500000 | E24: =E16*B16 -> 11250000 | F24: =F16*B16 -> 16875000
A25: profile | C25: =C17*B17 -> 150000 | D25: =D17*B17 -> 375000 | E25: =E17*B17 -> 1012500 | F25: =F17*B17 -> 2868750
A26: producer users | C26: =C18*B18 -> 10000 | D26: =D18*B18 -> 15000 | E26: =E18*B18 -> 22500 | F26: =F18*B18 -> 33750
A27: consumer users | C27: =C19*B19 -> 20000 | D27: =D19*B19 -> 60000 | E27: =E19*B19 -> 180000 | F27: =F19*B19 -> 540000
A28: total table storage bytes | C28: =SUM(C24:C27) -> 5180000 | D28: =SUM(D24:D27) -> 7950000 | E28: =SUM(E24:E27) -> 12465000 | F28: =SUM(F24:F27) -> 20317500
A29: in GB | C29: =C28/1000000000 -> 0.00518 | D29: =D28/1000000000 -> 0.00795 | E29: =E28/1000000000 -> 0.012465 | F29: =F28/1000000000 -> 0.0203175 | H29: SQL Storage values, assuming blob and queue remain in azure storage
A30: How many bytes blob data?
C31: Q1 | D31: Q2 | E31: Q3 | F31: Q4 | H31: Assumptions:
A32: media blob | B32: 5000000 | C32: =C16*$B$32 -> 12500000000 | D32: =D16*$B$32 -> 18750000000 | E32: =E16*$B$32 -> 28125000000 | F32: =F16*$B$32 -> 42187500000 | H32: All blobs go to CDN.
A33: CDN storage | C33: =C$16*$B$32 -> 12500000000 | D33: =D$16*$B$32 -> 18750000000 | E33: =E$16*$B$32 -> 28125000000 | F33: =F$16*$B$32 -> 42187500000
A34: CDN storage GB | C34: =C33/1000000000 -> 12.5 | D34: =D33/1000000000 -> 18.75 | E34: =E33/1000000000 -> 28.125 | F34: =F33/1000000000 -> 42.1875
A36: How many bytes queue data?
C37: Q1 | D37: Q2 | E37: Q3 | F37: Q4 | H37: Assumption:
A38: upload confirmation bytes | B38: 2000 | C38: =C16*$B$38 -> 5000000 | D38: =D16*$B$38 -> 7500000 | E38: =E16*$B$38 -> 11250000 | F38: =F16*$B$38 -> 16875000 | H38: All media uploads generate a queue message
A40: Total storage in bytes | C40: =C28+C32+C38 -> 12510180000 | D40: =D28+D32+D38 -> 18765450000 | E40: =E28+E32+E38 -> 28148715000 | F40: =F28+F32+F38 -> 42224692500
A41: in MB | C41: =C40/1000000 -> 12510.18 | D41: =D40/1000000 -> 18765.45 | E41: =E40/1000000 -> 28148.715 | F41: =F40/1000000 -> 42224.692
A42: in GB | C42: =C40/1000000000 -> 12.51018 | D42: =D40/1000000000 -> 18.76545 | E42: =E40/1000000000 -> 28.148715 | F42: =F40/1000000000 -> 42.224693 | H42: represents total GB uploaded that quarter, could average this over 3 months
A45: Average storage per producer | C45: =(C32/C18)/1000000 -> 250 | D45: =(D32/D18)/1000000 -> 250 | E45: =(E32/E18)/1000000 -> 250 | F45: =(F32/F18)/1000000 -> 250
A47: Media downloads transactions
B48: avg per user | C48: Q1 | D48: Q2 | E48: Q3 | F48: Q4
A49: per day | B49: 2 | C49: =$B49*C$19 -> 200 | D49: =$B49*D$19 -> 600 | E49: =$B49*E$19 -> 1800 | F49: =$B49*F$19 -> 5400
A50: per week | B50: =$B$49*7 -> 14 | C50: =$B50*C$19 -> 1400 | D50: =$B50*D$19 -> 4200 | E50: =$B50*E$19 -> 12600 | F50: =$B50*F$19 -> 37800
A51: per month | B51: =$B$49*30 -> 60 | C51: =$B51*C$19 -> 6000 | D51: =$B51*D$19 -> 18000 | E51: =$B51*E$19 -> 54000 | F51: =$B51*F$19 -> 162000 | H51: Assumptions
A52: per year | B52: =$B$49*365 -> 730 | C52: =$B52*C$19 -> 73000 | D52: =$B52*D$19 -> 219000 | E52: =$B52*E$19 -> 657000 | F52: =$B52*F$19 -> 1971000 | H52: cdn and blob storage downloads based on per month numbers with average consumption per user
A53: per month 10K tx | C53: =C51/10000 -> 0.6 | D53: =D51/10000 -> 1.8 | E53: =E51/10000 -> 5.4 | F53: =F51/10000 -> 16.2 | H53: total GB downloads per month also maps to downloads of media used
A55: Table storage transactions per month
B56: avg per user | C56: Q1 | D56: Q2 | E56: Q3 | F56: Q4
A57: media blob | B57: 10 | C57: =C16*$B57 -> 25000 | D57: =D16*$B57 -> 37500 | E57: =E16*$B57 -> 56250 | F57: =F16*$B57 -> 84375 | H57: how many add, update, delete (reads are downloads above)
A58: media record | B58: 20 | C58: =C16*$B58 -> 50000 | D58: =D16*$B58 -> 75000 | E58: =E16*$B58 -> 112500 | F58: =F16*$B58 -> 168750 | H58: how many add, update, read, delete
A59: profile | B59: 20 | C59: =C17*$B59 -> 3000 | D59: =D17*$B59 -> 7500 | E59: =E17*$B59 -> 20250 | F59: =F17*$B59 -> 57375 | H59: each table has patterns
A60: source users | B60: 3 | C60: =C18*$B60 -> 150 | D60: =D18*$B60 -> 225 | E60: =E18*$B60 -> 337.5 | F60: =F18*$B60 -> 506.25 | H60: how many times would a source upload, read, write, delete media records per month?
A61: consumer users | B61: 3 | C61: =C19*$B61 -> 300 | D61: =D19*$B61 -> 900 | E61: =E19*$B61 -> 2700 | F61: =F19*$B61 -> 8100
A62: total tx per month | C62: =SUM(C58:C61) -> 53450 | D62: =SUM(D58:D61) -> 83625 | E62: =SUM(E58:E61) -> 135787.5 | F62: =SUM(F58:F61) -> 234731.25 | H62: each queue message has a create, read, delete action
A63: total 10K tx per month | C63: =C62/10000 -> 5.345 | D63: =D62/10000 -> 8.3625 | E63: =E62/10000 -> 13.57875 | F63: =F62/10000 -> 23.473125 | H63: queue polls per second is in addition to actual reads where a message is not present
A64: total 10K tx incl blob downloads | C64: =C63+C53 -> 5.945 | D64: =D63+D53 -> 10.1625 | E64: =E63+E53 -> 18.97875 | F64: =F63+F53 -> 39.673125
A65: total 10K tx incl queue tx | C65: =C64+C73 -> 7.745 | D65: =D64+D73 -> 12.0875 | E65: =E64+E73 -> 21.09125 | F65: =F64+F73 -> 42.066875
A69: Queue transactions | B69: avg / day | C69: Q1 | D69: Q2 | E69: Q3 | F69: Q4
A70: queue messages | C70: =(C16/3)*3 -> 2500 | D70: =(D16/3)*3 -> 3750 | E70: =(E16/3)*3 -> 5625 | F70: =(F16/3)*3 -> 8437.5
A71: empty queue polls / month | B71: 500 | C71: =$B$71*31 -> 15500 | D71: =$B$71*31 -> 15500 | E71: =$B$71*31 -> 15500 | F71: =$B$71*31 -> 15500
A72: total tx per month | C72: =SUM(C70:C71) -> 18000 | D72: =SUM(D70:D71) -> 19250 | E72: =SUM(E70:E71) -> 21125 | F72: =SUM(F70:F71) -> 23937.5
A73: total 10K tx per month | C73: =C72/10000 -> 1.8 | D73: =D72/10000 -> 1.925 | E73: =E72/10000 -> 2.1125 | F73: =F72/10000 -> 2.39375
A77: Bandwidth usage per month
C78: Q1 | D78: Q2 | E78: Q3 | F78: Q4
H79: bandwidth inbound not charged, but we'll track it in case future changes require estimation
A80: media uploads in bytes | C80: =C32/3 -> 4.1666667e+09 | D80: =D32/3 -> 6250000000 | E80: =E32/3 -> 9375000000 | F80: =F32/3 -> 14062500000 | H80: upload is producer based, create records, interact with service, upload media, does not yet account for mistakes, reupload, replacing media
A81: record uploads in bytes | C81: =C28/3 -> 1726666.7 | D81: =D28/3 -> 2650000 | E81: =E28/3 -> 4155000 | F81: =F28/3 -> 6772500 | H81: download is consumer based and application consumption
A82: total transfer inbound in bytes | C82: =SUM(C80:C81) -> 4.1683933e+09 | D82: =SUM(D80:D81) -> 6252650000 | E82: =SUM(E80:E81) -> 9379155000 | F82: =SUM(F80:F81) -> 14069272500 | H82: avoid download media if not streaming it, use previews, etc.
A83: total transfer inbound in GB /mo | C83: =C82/1000000000 -> 4.1683933 | D83: =D82/1000000000 -> 6.25265 | E83: =E82/1000000000 -> 9.379155 | F83: =F82/1000000000 -> 14.069273 | H83: based on page loads and average record size
A84: GB/hour | C84: =C83/(24*31) -> 0.0056026792 | D84: =D83/(24*31) -> 0.0084040995 | E84: =E83/(24*31) -> 0.012606391 | F84: =F83/(24*31) -> 0.018910313
A85: media downloads in bytes | C85: =$B$32*C51 -> 30000000000 | D85: =$B$32*D51 -> 90000000000 | E85: =$B$32*E51 -> 270000000000 | F85: =$B$32*F51 -> 810000000000
A86: record downloads | C86: =$B$88*C87 -> 90000 | D86: =$B$88*D87 -> 180000 | E86: =$B$88*E87 -> 300000 | F86: =$B$88*F87 -> 1500000
A87: average pages / s | C87: 30 | D87: 60 | E87: 100 | F87: 500
A88: average record size / pg | B88: 3000
C89: =C85+C86 -> 30000090000 | D89: =D85+D86 -> 90000180000 | E89: =E85+E86 -> 270000300000 | F89: =F85+F86 -> 810001500000
A90: transfer outbound in GB /mo | C90: =C89/1000000000 -> 30.00009 | D90: =D89/1000000000 -> 90.00018 | E90: =E89/1000000000 -> 270.0003 | F90: =F89/1000000000 -> 810.0015
A91: % users US/EU | B91: 0.8 | C91: =C90*$B91 -> 24.000072 | D91: =D90*$B91 -> 72.000144 | E91: =E90*$B91 -> 216.00024 | F91: =F90*$B91 -> 648.0012
A92: % user APAC | B92: 0.2 | C92: =C91*$B92 -> 4.8000144 | D92: =D91*$B92 -> 14.400029 | E92: =E91*$B92 -> 43.200048 | F92: =F91*$B92 -> 129.60024
A93: GB/hour | C93: =C90/(31*24) -> 0.040322702 | D93: =D90/(31*24) -> 0.12096798 | E93: =E90/(31*24) -> 0.36290363 | F93: =F90/(31*24) -> 1.0887117
A95: $ users US/EU | B95: 0.15 | C95: =C91*$B95 -> 3.6000108 | D95: =D91*$B95 -> 10.800022 | E95: =E91*$B95 -> 32.400036 | F95: =F91*$B95 -> 97.20018
A96: $ users APAC | B96: 0.2 | C96: =C92*$B96 -> 0.96000288 | D96: =D92*$B96 -> 2.8800058 | E96: =E92*$B96 -> 8.6400096 | F96: =F92*$B96 -> 25.920048
C97: =SUM(C95:C96) -> 4.5600137 | D97: =SUM(D95:D96) -> 13.680027 | E97: =SUM(E95:E96) -> 41.040046 | F97: =SUM(F95:F96) -> 123.12023
A98: price per download | B98: 1 | C98: =C51*$B98 -> 6000 | D98: =D51*$B98 -> 18000 | E98: =E51*$B98 -> 54000 | F98: =F51*$B98 -> 162000 | H98: This is a shot in the dark at revenues per month based on charging for media downloads. Just to indicate the potential for revenue to offset bandwidth costs.

Sheet Cache
A1: Cache Costs
A2: DISCLAIMER: This is a sample worksheet making assumptions for a specific scenario, and without considering partner discounts. You can use this worksheet as a sample to get you started.
A4: Cache Size | C4: Cost/mo | D4: Q1 | E4: Q2 | F4: Q3 | G4: Q4
A5: 128MB | C5: 45 | D5: =IF(C$25>128000000,0,C$5) -> 45 | E5: =IF(D$25>128000000,0,D$5) -> 45 | F5: =IF(E$25>128000000,0,E$5) -> 45 | G5: =IF(F$25>128000000,0,F$5) -> 45 | J5: Legend:
A6: 256MB | C6: 55 | D6: =IF(C$25>128000000,IF(C$25>256000000,0,$C6),0) -> 0 | E6: =IF(D$25>128000000,IF(D$25>256000000,0,$C6),0) -> 0 | F6: =IF(E$25>128000000,IF(E$25>256000000,0,$C6),0) -> 0 | G6: =IF(F$25>128000000,IF(F$25>256000000,0,$C6),0) -> 0 | K6: Azure costs that could require update
A7: 512MB | C7: 75 | D7: =IF(C$25>256000000,IF(C$25>512000000,0,$C7),0) -> 0 | E7: =IF(D$25>256000000,IF(D$25>512000000,0,$C7),0) -> 0 | F7: =IF(E$25>256000000,IF(E$25>512000000,0,$C7),0) -> 0 | G7: =IF(F$25>256000000,IF(F$25>512000000,0,$C7),0) -> 0 | K7: Input values that are source for calculations on the page
A8: 1GB | C8: 110 | D8: =IF(C$25>512000000,IF(C$25>1000000000,0,$C8),0) -> 0 | E8: =IF(D$25>512000000,IF(D$25>1000000000,0,$C8),0) -> 0 | F8: =IF(E$25>512000000,IF(E$25>1000000000,0,$C8),0) -> 0 | G8: =IF(F$25>512000000,IF(F$25>1000000000,0,$C8),0) -> 0
A9: 2GB | C9: 180 | D9: =IF(C$25>1000000000,IF(C$25>2000000000,0,$C9),0) -> 0 | E9: =IF(D$25>1000000000,IF(D$25>2000000000,0,$C9),0) -> 0 | F9: =IF(E$25>1000000000,IF(E$25>2000000000,0,$C9),0) -> 0 | G9: =IF(F$25>1000000000,IF(F$25>2000000000,0,$C9),0) -> 0
A10: 4GB | C10: 325 | D10: =IF(C$25>2000000000,IF(C$25>4000000000,NA,$C10),0) -> 0 | E10: =IF(D$25>2000000000,IF(D$25>4000000000,NA,$C10),0) -> 0 | F10: =IF(E$25>2000000000,IF(E$25>4000000000,NA,$C10),0) -> 0 | G10: =IF(F$25>2000000000,IF(F$25>4000000000,NA,$C10),0) -> 0
D11: =SUM(D5:D10) -> 45 | E11: =SUM(E5:E10) -> 45 | F11: =SUM(F5:F10) -> 45 | G11: =SUM(G5:G10) -> 45
A15: Estimation Worksheet
A16: Assumptions:
A17: Using cache for session data only
A19: How many bytes per session?
B20: bytes/rec | C20: Q1 | D20: Q2 | E20: Q3 | F20: Q4
A21: shopping cart | B21: 2000
A22: misc session | B22: 1000
A23: data storage | B23: 0
A24: #users | C24: 150 | D24: =(C24*$H$24)+C24 -> 225 | E24: =(D24*$H$24)+D24 -> 337.5 | F24: =(E24*$H$24)+E24 -> 506.25 | H24: 0.5 | I24: growth per quarter
B25: =SUM(B21:B24) -> 3000 | C25: =$B$25*C24 -> 450000 | D25: =$B$25*D24 -> 675000 | E25: =$B$25*E24 -> 1012500 | F25: =$B$25*F24 -> 1518750
A26: in GB | C26: =C25/1000000000 -> 0.00045 | D26: =D25/1000000000 -> 0.000675 | E26: =E25/1000000000 -> 0.0010125 | F26: =F25/1000000000 -> 0.00151875

Sheet ServiceBus
A1: Service Bus Costs
A2: DISCLAIMER: This is a sample worksheet making assumptions for a specific scenario, and without considering partner discounts. You can use this worksheet as a sample to get you started.
A4: Packages | B4: Unit cost | C4: Q1 | D4: Q2 | E4: Q3 | F4: Q4 | J4: Legend:
K5: Azure costs that could require update
A6: 5 Pack | B6: 9.95 | C6: =IF(C$30<5,B6,0) -> 0 | D6: =IF(D$30<5,C6,0) -> 0 | E6: =IF(E$30<5,D6,0) -> 0 | F6: =IF(F$30<5,E6,0) -> 0 | K6: Input values that are source for calculations on the page
A7: 25 Pack | B7: 49.75 | C7: =IF(AND(C$30>5, C$30<25),$B7,0) -> 49.75 | D7: =IF(AND(D$30>5, D$30<25),$B7,0) -> 0 | E7: =IF(AND(E$30>5, E$30<25),$B7,0) -> 0 | F7: =IF(AND(F$30>5, F$30<25),$B7,0) -> 0
A8: 100 Pack | B8: 199 | C8: =IF(AND(C$30>25,C$30<100),$B8,0) -> 0 | D8: =IF(AND(D$30>25,D$30<100),$B8,0) -> 199 | E8: =IF(AND(E$30>25,E$30<100),$B8,0) -> 199 | F8: =IF(AND(F$30>25,F$30<100),$B8,0) -> 199
A9: 500 Pack | B9: 995 | C9: =IF(C$30>100,$B9,0) -> 0 | D9: =IF(D$30>100,$B9,0) -> 0 | E9: =IF(E$30>100,$B9,0) -> 0 | F9: =IF(F$30>100,$B9,0) -> 0
A10: Per use | B10: 3.99
C11: =SUM(C6:C10) -> 49.75 | D11: =SUM(D6:D10) -> 199 | E11: =SUM(E6:E10) -> 199 | F11: =SUM(F6:F10) -> 199
A15: Estimation Worksheet
A19: Number of concurrent connections?
C20: Q1 | D20: Q2 | E20: Q3 | F20: Q4
A21: #users | C21: 150 | D21: =(C21*$H$21)+C21 -> 225 | E21: =(D21*$H$21)+D21 -> 337.5 | F21: =(E21*$H$21)+E21 -> 506.25 | H21: 0.5 | I21: growth per quarter
A22: # services | B22: 3
A23: svc connect / day | B23: 2 | C23: =$B$22*$B$23 -> 6 | D23: =$B$22*$B$23 -> 6 | E23: =$B$22*$B$23 -> 6 | F23: =$B$22*$B$23 -> 6
A24: concurrent user conn /d | B24: 0.03 | C24: =C21*$B$24*$B$22 -> 13.5 | D24: =D21*$B$24*$B$22 -> 20.25 | E24: =E21*$B$24*$B$22 -> 30.375 | F24: =F21*$B$24*$B$22 -> 45.5625
A25: management calls | C25: 1 | D25: 1 | E25: 1 | F25: 1
A27: messages / user / day
A28: message buffer writes
A29: message buffer reads
A30: total concurrent conn/day | C30: =SUM(C23:C29) -> 20.5 | D30: =SUM(D23:D29) -> 27.25 | E30: =SUM(E23:E29) -> 37.375 | F30: =SUM(F23:F29) -> 52.5625

Sheet AccessControl
A1: Access Control Costs
A2: DISCLAIMER: This is a sample worksheet making assumptions for a specific scenario, and without considering partner discounts. You can use this worksheet as a sample to get you started.
A4: Packages | B4: Unit cost | C4: Q1 | D4: Q2 | E4: Q3 | F4: Q4
A5: 100K tx | B5: 1.99 | C5: =C24*$B$5 -> 0.18507 | D5: =D24*$B$5 -> 0.277605 | E5: =E24*$B$5 -> 0.4164075 | F5: =F24*$B$5 -> 0.62461125 | I5: Legend:
J6: Azure costs that could require update
C7: =SUM(C5:C6) -> 0.18507 | D7: =SUM(D5:D6) -> 0.277605 | E7: =SUM(E5:E6) -> 0.4164075 | F7: =SUM(F5:F6) -> 0.62461125 | J7: Input values that are source for calculations on the page
A15: Estimation Worksheet
A18: Number of concurrent connections?
C19: Q1 | D19: Q2 | E19: Q3 | F19: Q4
A20: #users | C20: 150 | D20: =(C20*$H$20)+C20 -> 225 | E20: =(D20*$H$20)+D20 -> 337.5 | F20: =(E20*$H$20)+E20 -> 506.25 | H20: 0.5 | I20: growth per quarter
A21: # login / day | B21: 2 | C21: =C20*$B$21 -> 300 | D21: =D20*$B$21 -> 450 | E21: =E20*$B$21 -> 675 | F21: =F20*$B$21 -> 1012.5
A23: tx per month | C23: =C21*31 -> 9300 | D23: =D21*31 -> 13950 | E23: =E21*31 -> 20925 | F23: =F21*31 -> 31387.5
A24: tx per 100K tx | C24: =C23/100000 -> 0.093 | D24: =D23/100000 -> 0.1395 | E24: =E23/100000 -> 0.20925 | F24: =F23/100000 -> 0.313875

Sheet Totals
A1: Total Cost Estimate
A2: DISCLAIMER: This is a sample worksheet making assumptions for a specific scenario, and without considering partner discounts. You can use this worksheet as a sample to get you started.
A3: These costs derive information from each of the other spreadsheets. Try adjusting the number of users on each page and see the results here. Also make note of the potential "revenues" on Storage sheet to offset these costs.
A5: VM Cost / month | B5: =Compute!E10 -> 175.2
A6: Storage | B6: =Storage!C7 -> 1.7514252
A7: Storage tx | B7: =Storage!C10 -> 0.07745
A8: Bandwidth | B8: =Storage!C97 -> 4.5600137
A9: Cache | B9: =Cache!D11 -> 45
A10: Service Bus | B10: =ServiceBus!C11 -> 49.75
A11: Access Control | B11: =AccessControl!C7 -> 0.18507
A12: Total cost per month | B12: =SUM(B5:B11) -> 276.52396 | D12: Estimated costs if you use every aspect of Azure for a fictional business that hosts media
A14: Revenue projection per month | B14: =Storage!C98 -> 6000 | D14: Shot in the dark at revenue per media upload
