Workbook

Sheet Introduction
B2: FabulesslyFrugal.com - Budget Model 2012 | H2: Budget Model Directions
B4: Personal Budget Prepared for: | G4: =MATCH(C8,$G$11:$G$22,0) -> 1 | H4: 1. Enter your Name - it will appear on throughout the model .
B5: Budget for Year | C5: 2012 | H5: 2. Enter your Income Categories (Net Payroll, Gift from Parents, etc. in green cells in Box Titled Income Categories in Left Column.
B6: Applied to Worksheets Start | C6: =CONCATENATE("01/01/",C5) -> 01/01/2012 | H6: 3. Enter your Expense Categories (Rent, Auto, Cell Phone, Water, Gas, Electric, Cable, etc. in yellow in Box Titled Expense Categories
B7: Applied to Worksheets End | C7: =CONCATENATE("12/31/",C5) -> 12/31/2012 | H7: in Center Column (Orange). (Note: your income and expense categories will be captured in your bank ledger entries and reporting.
B8: Budget Comparison Month for Reports | C8: Jan | H8: 4. Enter your Current IRA Balance. The model is designed with an IRA Budget category for your convenience.
B10: Income Categories | D10: 0 | E10: Expense Categories | H10: (Note: your income and expense categories will be made available to you in your bank ledger and reporting results.
A11: 1 | B11: Income 1 | C11: Income 1 | D11: 1 | E11: Expense 1 | F11: Expense 1 | G11: Jan
A12: 2 | B12: Income 2 | C12: Income 2 | D12: 2 | E12: Expense 2 | F12: Expense 2 | G12: Feb | H12: Once you have set up your income and expense categories, enter your Beginning Cash balance in Center Box, bottom. If you have, a IRA
A13: 3 | B13: Income 3 | C13: Income 3 | D13: 3 | E13: Expense 3 | F13: Expense 3 | G13: Mar | H13: balance, enter it in Center Box above the Beginning Cash Balance. You are now ready to begin budgeting. Simply open the BUDGET tab
A14: 4 | B14: Income 4 | C14: Income 4 | D14: 4 | E14: Expense 4 | F14: Expense 4 | G14: Apr | H14: =CONCATENATE("and begin entering your monthly budget numbers. That's it -- the model does all the math for you. Beginning Cash Balance is -> $",F32,".") -> and begin entering your monthly budget numbers. That's it -- the model does all the math for you. Beginning Cash Balance is -> $0.
A15: 5 | B15: Income 5 | C15: Income 5 | D15: 5 | E15: Expense 5 | F15: Expense 5 | G15: May
A16: 6 | B16: Income 6 | C16: Income 6 | D16: 6 | E16: Expense 6 | F16: Expense 6 | G16: Jun | H16: Now it is time to capture your actual results. This is simple too -- go to the LEDGER tab and update your banking ledger for all checks, debit
A17: 7 | B17: Income 7 | C17: Income 7 | D17: 7 | E17: Expense 7 | F17: Expense 7 | G17: Jul | H17: charges, withdrawals, etc. Also, enter check deposits, cash deposits, or other sources of funding entering the account. The model will
A18: 8 | B18: Income 8 | C18: Income 8 | D18: 8 | E18: Expense 8 | F18: Expense 8 | G18: Aug | H18: do all the math for you and provide you a statement against your budget by month, quarter to date, and year-to-date.
D19: 9 | E19: Expense 9 | F19: Expense 9 | G19: Sep
B20: Fabulessly Frugal Budget Model | D20: 10 | E20: Expense 10 | F20: Expense 10 | G20: Oct | H20: As you receive a new bank statement, go to the ledger tab and put number "1" in the bank reconciliation field to balance your bank account.
B21: This simple budget model has been prepared as an expression of my love for my children, in hopes that in some small way I can teach them to organize their financial affairs in a fun and meaningful way. While simple, this model is quite powerful, and it can be used by beginners and experts alike. I give special acknowledgment to my daughter Monica, who has worked diligently with her partner Cathy and the rest of the Fabulessly Frugal team to provide you this wonderful web site that gives you practical advice on cost effectively providing for your family in a -- Fabulessly Frugal way. I hope you find this budget tool to be helpful, Dave January 2012. | D21: 11 | E21: Expense 11 | F21: Expense 11 | G21: Nov | H21: Note the example below, employee Payroll receipt cleared the bank, as did the rent, electric, and gas payments so "1" is entered. The Auto
D22: 12 | E22: Expense 12 | F22: Expense 12 | G22: Dec | H22: payment has not cleared the bank. You can track your actual cash balance, anticipating all payments clearing the bank. No more overdrafts.
D23: 13 | E23: Expense 13 | F23: Expense 13
D24: 14 | E24: Expense 14 | F24: Expense 14
D25: 15 | E25: Expense 15 | F25: Expense 15
D26: 16 | E26: Expense 16 | F26: Expense 16
D27: 17 | E27: Expense 17 | F27: Expense 17
D28: 18 | E28: Expense 18 | F28: Expense 18
D29: 19 | E29: Expense 19 | F29: Expense 19
D30: 20 | E30: Expense 20 | F30: IRA Contribution
E31: IRA Beginning Balance | F31: 0
E32: Beginning Cash Balance | F32: 0
F33: Income
F34: Expense
E35: Click to go to website
H75: category. That's it -- the model does all the math. Beginning Cash Balance is ….

Sheet Ledger
B2: Reconcile your banking account on this sheet. This ledger feeds directly to the expense report. Note the bank clearing column (K), enter 1 as you reconcile to your bank statement. Enter Check number (if applicable), Date, Income or Expense then Category Number, Description, Amount (positive numbers income, negative as expense), and bank clearing as you reconcile to your bank statement. | O2: 1
B3: Check Number | C3: Date | D3: Income or Expense | E3: Cateogry Number | F3: Budget Category From Input Sheets (This captures the Category for Reporting based on Category Number) | G3: Pay to or Received From Enter Name or Description | H3: Amount | I3: Your Actual Account Balance | J3: Bank Clearing - Enter 1 if Cleared Bank | K3: Bank Balance as Shown on your Bank Statement | P3: Lookup Field
I5: =+Introduction!F32 -> 0 | K5: =+Introduction!F32 -> 0 | M5: Income
A6: Start Here => | F6: =IF(D6="Income",LOOKUP(E6,Introduction!$A$11:$A$18,Introduction!$C$11:$C$18),IF(D6="Expense",LOOKUP(E6,Introduction!$D$11:$D$30,Introduction!$F$11:$F$30),"_")) -> _ | I6: =+I5+H6 -> 0 | K6: =IF(J6=1,K5+H6,++K5) -> 0 | M6: Expense | P6: =CONCATENATE(D6," ",E6," ",MONTH(C6)," ",YEAR(C6)," ") -> 1 1900
F7: =IF(D7="Income",LOOKUP(E7,Introduction!$A$11:$A$18,Introduction!$C$11:$C$18),IF(D7="Expense",LOOKUP(E7,Introduction!$D$11:$D$30,Introduction!$F$11:$F$30),"_")) -> _ | I7: =+I6+H7 -> 0 | K7: =IF(J7=1,K6+H7,++K6) -> 0 | P7: =CONCATENATE(D7," ",E7," ",MONTH(C7)," ",YEAR(C7)," ") -> 1 1900
F8: =IF(D8="Income",LOOKUP(E8,Introduction!$A$11:$A$18,Introduction!$C$11:$C$18),IF(D8="Expense",LOOKUP(E8,Introduction!$D$11:$D$30,Introduction!$F$11:$F$30),"_")) -> _ | I8: =+I7+H8 -> 0 | K8: =IF(J8=1,K7+H8,++K7) -> 0 | P8: =CONCATENATE(D8," ",E8," ",MONTH(C8)," ",YEAR(C8)," ") -> 1 1900
F9: =IF(D9="Income",LOOKUP(E9,Introduction!$A$11:$A$18,Introduction!$C$11:$C$18),IF(D9="Expense",LOOKUP(E9,Introduction!$D$11:$D$30,Introduction!$F$11:$F$30),"_")) -> _ | I9: =+I8+H9 -> 0 | K9: =IF(J9=1,K8+H9,++K8) -> 0 | P9: =CONCATENATE(D9," ",E9," ",MONTH(C9)," ",YEAR(C9)," ") -> 1 1900
F10: =IF(D10="Income",LOOKUP(E10,Introduction!$A$11:$A$18,Introduction!$C$11:$C$18),IF(D10="Expense",LOOKUP(E10,Introduction!$D$11:$D$30,Introduction!$F$11:$F$30),"_")) -> _ | I10: =+I9+H10 -> 0 | K10: =IF(J10=1,K9+H10,++K9) -> 0 | P10: =CONCATENATE(D10," ",E10," ",MONTH(C10)," ",YEAR(C10)," ") -> 1 1900
F11: =IF(D11="Income",LOOKUP(E11,Introduction!$A$11:$A$18,Introduction!$C$11:$C$18),IF(D11="Expense",LOOKUP(E11,Introduction!$D$11:$D$30,Introduction!$F$11:$F$30),"_")) -> _ | I11: =+I10+H11 -> 0 | K11: =IF(J11=1,K10+H11,++K10) -> 0 | P11: =CONCATENATE(D11," ",E11," ",MONTH(C11)," ",YEAR(C11)," ") -> 1 1900
F12: =IF(D12="Income",LOOKUP(E12,Introduction!$A$11:$A$18,Introduction!$C$11:$C$18),IF(D12="Expense",LOOKUP(E12,Introduction!$D$11:$D$30,Introduction!$F$11:$F$30),"_")) -> _ | I12: =+I11+H12 -> 0 | K12: =IF(J12=1,K11+H12,++K11) -> 0 | P12: =CONCATENATE(D12," ",E12," ",MONTH(C12)," ",YEAR(C12)," ") -> 1 1900
F13: =IF(D13="Income",LOOKUP(E13,Introduction!$A$11:$A$18,Introduction!$C$11:$C$18),IF(D13="Expense",LOOKUP(E13,Introduction!$D$11:$D$30,Introduction!$F$11:$F$30),"_")) -> _ | I13: =+I12+H13 -> 0 | K13: =IF(J13=1,K12+H13,++K12) -> 0 | P13: =CONCATENATE(D13," ",E13," ",MONTH(C13)," ",YEAR(C13)," ") -> 1 1900
F14: =IF(D14="Income",LOOKUP(E14,Introduction!$A$11:$A$18,Introduction!$C$11:$C$18),IF(D14="Expense",LOOKUP(E14,Introduction!$D$11:$D$30,Introduction!$F$11:$F$30),"_")) -> _ | I14: =+I13+H14 -> 0 | K14: =IF(J14=1,K13+H14,++K13) -> 0 | P14: =CONCATENATE(D14," ",E14," ",MONTH(C14)," ",YEAR(C14)," ") -> 1 1900
F15: =IF(D15="Income",LOOKUP(E15,Introduction!$A$11:$A$18,Introduction!$C$11:$C$18),IF(D15="Expense",LOOKUP(E15,Introduction!$D$11:$D$30,Introduction!$F$11:$F$30),"_")) -> _ | I15: =+I14+H15 -> 0 | K15: =IF(J15=1,K14+H15,++K14) -> 0 | P15: =CONCATENATE(D15," ",E15," ",MONTH(C15)," ",YEAR(C15)," ") -> 1 1900
F16: =IF(D16="Income",LOOKUP(E16,Introduction!$A$11:$A$18,Introduction!$C$11:$C$18),IF(D16="Expense",LOOKUP(E16,Introduction!$D$11:$D$30,Introduction!$F$11:$F$30),"_")) -> _ | I16: =+I15+H16 -> 0 | K16: =IF(J16=1,K15+H16,++K15) -> 0 | P16: =CONCATENATE(D16," ",E16," ",MONTH(C16)," ",YEAR(C16)," ") -> 1 1900
F17: =IF(D17="Income",LOOKUP(E17,Introduction!$A$11:$A$18,Introduction!$C$11:$C$18),IF(D17="Expense",LOOKUP(E17,Introduction!$D$11:$D$30,Introduction!$F$11:$F$30),"_")) -> _ | I17: =+I16+H17 -> 0 | K17: =IF(J17=1,K16+H17,++K16) -> 0 | P17: =CONCATENATE(D17," ",E17," ",MONTH(C17)," ",YEAR(C17)," ") -> 1 1900
F18: =IF(D18="Income",LOOKUP(E18,Introduction!$A$11:$A$18,Introduction!$C$11:$C$18),IF(D18="Expense",LOOKUP(E18,Introduction!$D$11:$D$30,Introduction!$F$11:$F$30),"_")) -> _ | I18: =+I17+H18 -> 0 | K18: =IF(J18=1,K17+H18,++K17) -> 0 | P18: =CONCATENATE(D18," ",E18," ",MONTH(C18)," ",YEAR(C18)," ") -> 1 1900
... F111: =IF(D111="Income",LOOKUP(E111,Introduction!$A$11:$A$18,Introduction!$C$11:$C$18),IF(D111="Expense",LOOKUP(E111,Introduction!$D$11:$D$30,Introduction!$F$11:$F$30),"_")) -> _ | I111: =+I110+H111 -> 0 | K111: =IF(J111=1,K110+H111,++K110) -> 0 | P111: =CONCATENATE(D111," ",E111," ",MONTH(C111)," ",YEAR(C111)," ") -> 1 1900
F112: =IF(D112="Income",LOOKUP(E112,Introduction!$A$11:$A$18,Introduction!$C$11:$C$18),IF(D112="Expense",LOOKUP(E112,Introduction!$D$11:$D$30,Introduction!$F$11:$F$30),"_")) -> _ | H112: =-ROUND(H6*$O$2,2) -> 0 | I112: =+I111+H112 -> 0 | K112: =IF(J112=1,K111+H112,++K111) -> 0 | P112: =CONCATENATE(D112," ",E112," ",MONTH(C112)," ",YEAR(C112)," ") -> 1 1900
F113: =IF(D113="Income",LOOKUP(E113,Introduction!$A$11:$A$18,Introduction!$C$11:$C$18),IF(D113="Expense",LOOKUP(E113,Introduction!$D$11:$D$30,Introduction!$F$11:$F$30),"_")) -> _ | H113: =-ROUND(H7*$O$2,2) -> 0 | I113: =+I112+H113 -> 0 | K113: =IF(J113=1,K112+H113,++K112) -> 0 | P113: =CONCATENATE(D113," ",E113," ",MONTH(C113)," ",YEAR(C113)," ") -> 1 1900
F114: =IF(D114="Income",LOOKUP(E114,Introduction!$A$11:$A$18,Introduction!$C$11:$C$18),IF(D114="Expense",LOOKUP(E114,Introduction!$D$11:$D$30,Introduction!$F$11:$F$30),"_")) -> _ | H114: =-ROUND(H8*$O$2,2) -> 0 | I114: =+I113+H114 -> 0 | K114: =IF(J114=1,K113+H114,++K113) -> 0 | P114: =CONCATENATE(D114," ",E114," ",MONTH(C114)," ",YEAR(C114)," ") -> 1 1900
F115: =IF(D115="Income",LOOKUP(E115,Introduction!$A$11:$A$18,Introduction!$C$11:$C$18),IF(D115="Expense",LOOKUP(E115,Introduction!$D$11:$D$30,Introduction!$F$11:$F$30),"_")) -> _ | H115: =-ROUND(H9*$O$2,2) -> 0 | I115: =+I114+H115 -> 0 | K115: =IF(J115=1,K114+H115,++K114) -> 0 | P115: =CONCATENATE(D115," ",E115," ",MONTH(C115)," ",YEAR(C115)," ") -> 1 1900
F116: =IF(D116="Income",LOOKUP(E116,Introduction!$A$11:$A$18,Introduction!$C$11:$C$18),IF(D116="Expense",LOOKUP(E116,Introduction!$D$11:$D$30,Introduction!$F$11:$F$30),"_")) -> _ | H116: =-ROUND(H10*$O$2,2) -> 0 | I116: =+I115+H116 -> 0 | K116: =IF(J116=1,K115+H116,++K115) -> 0 | P116: =CONCATENATE(D116," ",E116," ",MONTH(C116)," ",YEAR(C116)," ") -> 1 1900
F117: =IF(D117="Income",LOOKUP(E117,Introduction!$A$11:$A$18,Introduction!$C$11:$C$18),IF(D117="Expense",LOOKUP(E117,Introduction!$D$11:$D$30,Introduction!$F$11:$F$30),"_")) -> _ | H117: =-ROUND(H11*$O$2,2) -> 0 | I117: =+I116+H117 -> 0 | K117: =IF(J117=1,K116+H117,++K116) -> 0 | P117: =CONCATENATE(D117," ",E117," ",MONTH(C117)," ",YEAR(C117)," ") -> 1 1900
F118: =IF(D118="Income",LOOKUP(E118,Introduction!$A$11:$A$18,Introduction!$C$11:$C$18),IF(D118="Expense",LOOKUP(E118,Introduction!$D$11:$D$30,Introduction!$F$11:$F$30),"_")) -> _ | H118: =-ROUND(H12*$O$2,2) -> 0 | I118: =+I117+H118 -> 0 | K118: =IF(J118=1,K117+H118,++K117) -> 0 | P118: =CONCATENATE(D118," ",E118," ",MONTH(C118)," ",YEAR(C118)," ") -> 1 1900
F119: =IF(D119="Income",LOOKUP(E119,Introduction!$A$11:$A$18,Introduction!$C$11:$C$18),IF(D119="Expense",LOOKUP(E119,Introduction!$D$11:$D$30,Introduction!$F$11:$F$30),"_")) -> _ | H119: =-ROUND(H13*$O$2,2) -> 0 | I119: =+I118+H119 -> 0 | K119: =IF(J119=1,K118+H119,++K118) -> 0 | P119: =CONCATENATE(D119," ",E119," ",MONTH(C119)," ",YEAR(C119)," ") -> 1 1900
F120: =IF(D120="Income",LOOKUP(E120,Introduction!$A$11:$A$18,Introduction!$C$11:$C$18),IF(D120="Expense",LOOKUP(E120,Introduction!$D$11:$D$30,Introduction!$F$11:$F$30),"_")) -> _ | H120: =-ROUND(H14*$O$2,2) -> 0 | I120: =+I119+H120 -> 0 | K120: =IF(J120=1,K119+H120,++K119) -> 0 | P120: =CONCATENATE(D120," ",E120," ",MONTH(C120)," ",YEAR(C120)," ") -> 1 1900
F121: =IF(D121="Income",LOOKUP(E121,Introduction!$A$11:$A$18,Introduction!$C$11:$C$18),IF(D121="Expense",LOOKUP(E121,Introduction!$D$11:$D$30,Introduction!$F$11:$F$30),"_")) -> _ | H121: =-ROUND(H15*$O$2,2) -> 0 | I121: =+I120+H121 -> 0 | K121: =IF(J121=1,K120+H121,++K120) -> 0 | P121: =CONCATENATE(D121," ",E121," ",MONTH(C121)," ",YEAR(C121)," ") -> 1 1900
F122: =IF(D122="Income",LOOKUP(E122,Introduction!$A$11:$A$18,Introduction!$C$11:$C$18),IF(D122="Expense",LOOKUP(E122,Introduction!$D$11:$D$30,Introduction!$F$11:$F$30),"_")) -> _ | H122: =-ROUND(H16*$O$2,2) -> 0 | I122: =+I121+H122 -> 0 | K122: =IF(J122=1,K121+H122,++K121) -> 0 | P122: =CONCATENATE(D122," ",E122," ",MONTH(C122)," ",YEAR(C122)," ") -> 1 1900
F123: =IF(D123="Income",LOOKUP(E123,Introduction!$A$11:$A$18,Introduction!$C$11:$C$18),IF(D123="Expense",LOOKUP(E123,Introduction!$D$11:$D$30,Introduction!$F$11:$F$30),"_")) -> _ | H123: =-ROUND(H17*$O$2,2) -> 0 | I123: =+I122+H123 -> 0 | K123: =IF(J123=1,K122+H123,++K122) -> 0 | P123: =CONCATENATE(D123," ",E123," ",MONTH(C123)," ",YEAR(C123)," ") -> 1 1900
F124: =IF(D124="Income",LOOKUP(E124,Introduction!$A$11:$A$18,Introduction!$C$11:$C$18),IF(D124="Expense",LOOKUP(E124,Introduction!$D$11:$D$30,Introduction!$F$11:$F$30),"_")) -> _ | I124: =+I123+H124 -> 0 | K124: =IF(J124=1,K123+H124,++K123) -> 0 | P124: =CONCATENATE(D124," ",E124," ",MONTH(C124)," ",YEAR(C124)," ") -> 1 1900
F125: =IF(D125="Income",LOOKUP(E125,Introduction!$A$11:$A$18,Introduction!$C$11:$C$18),IF(D125="Expense",LOOKUP(E125,Introduction!$D$11:$D$30,Introduction!$F$11:$F$30),"_")) -> _ | H125: =-ROUND(H19*$O$2,2) -> 0 | I125: =+I124+H125 -> 0 | K125: =IF(J125=1,K124+H125,++K124) -> 0 | P125: =CONCATENATE(D125," ",E125," ",MONTH(C125)," ",YEAR(C125)," ") -> 1 1900
F126: =IF(D126="Income",LOOKUP(E126,Introduction!$A$11:$A$18,Introduction!$C$11:$C$18),IF(D126="Expense",LOOKUP(E126,Introduction!$D$11:$D$30,Introduction!$F$11:$F$30),"_")) -> _ | H126: =-ROUND(H20*$O$2,2) -> 0 | I126: =+I125+H126 -> 0 | K126: =IF(J126=1,K125+H126,++K125) -> 0 | P126: =CONCATENATE(D126," ",E126," ",MONTH(C126)," ",YEAR(C126)," ") -> 1 1900
F127: =IF(D127="Income",LOOKUP(E127,Introduction!$A$11:$A$18,Introduction!$C$11:$C$18),IF(D127="Expense",LOOKUP(E127,Introduction!$D$11:$D$30,Introduction!$F$11:$F$30),"_")) -> _ | H127: =-ROUND(H21*$O$2,2) -> 0 | I127: =+I126+H127 -> 0 | K127: =IF(J127=1,K126+H127,++K126) -> 0 | P127: =CONCATENATE(D127," ",E127," ",MONTH(C127)," ",YEAR(C127)," ") -> 1 1900
F128: =IF(D128="Income",LOOKUP(E128,Introduction!$A$11:$A$18,Introduction!$C$11:$C$18),IF(D128="Expense",LOOKUP(E128,Introduction!$D$11:$D$30,Introduction!$F$11:$F$30),"_")) -> _ | H128: =-ROUND(H22*$O$2,2) -> 0 | I128: =+I127+H128 -> 0 | K128: =IF(J128=1,K127+H128,++K127) -> 0 | P128: =CONCATENATE(D128," ",E128," ",MONTH(C128)," ",YEAR(C128)," ") -> 1 1900
F129: =IF(D129="Income",LOOKUP(E129,Introduction!$A$11:$A$18,Introduction!$C$11:$C$18),IF(D129="Expense",LOOKUP(E129,Introduction!$D$11:$D$30,Introduction!$F$11:$F$30),"_")) -> _ | H129: =-ROUND(H23*$O$2,2) -> 0 | I129: =+I128+H129 -> 0 | K129: =IF(J129=1,K128+H129,++K128) -> 0 | P129: =CONCATENATE(D129," ",E129," ",MONTH(C129)," ",YEAR(C129)," ") -> 1 1900
F130: =IF(D130="Income",LOOKUP(E130,Introduction!$A$11:$A$18,Introduction!$C$11:$C$18),IF(D130="Expense",LOOKUP(E130,Introduction!$D$11:$D$30,Introduction!$F$11:$F$30),"_")) -> _ | H130: =-ROUND(H24*$O$2,2) -> 0 | I130: =+I129+H130 -> 0 | K130: =IF(J130=1,K129+H130,++K129) -> 0 | P130: =CONCATENATE(D130," ",E130," ",MONTH(C130)," ",YEAR(C130)," ") -> 1 1900
F131: =IF(D131="Income",LOOKUP(E131,Introduction!$A$11:$A$18,Introduction!$C$11:$C$18),IF(D131="Expense",LOOKUP(E131,Introduction!$D$11:$D$30,Introduction!$F$11:$F$30),"_")) -> _ | H131: =-ROUND(H25*$O$2,2) -> 0 | I131: =+I130+H131 -> 0 | K131: =IF(J131=1,K130+H131,++K130) -> 0 | P131: =CONCATENATE(D131," ",E131," ",MONTH(C131)," ",YEAR(C131)," ") -> 1 1900
F132: =IF(D132="Income",LOOKUP(E132,Introduction!$A$11:$A$18,Introduction!$C$11:$C$18),IF(D132="Expense",LOOKUP(E132,Introduction!$D$11:$D$30,Introduction!$F$11:$F$30),"_")) -> _ | H132: =-ROUND(H26*$O$2,2) -> 0 | I132: =+I131+H132 -> 0 | K132: =IF(J132=1,K131+H132,++K131) -> 0 | P132: =CONCATENATE(D132," ",E132," ",MONTH(C132)," ",YEAR(C132)," ") -> 1 1900
F133: =IF(D133="Income",LOOKUP(E133,Introduction!$A$11:$A$18,Introduction!$C$11:$C$18),IF(D133="Expense",LOOKUP(E133,Introduction!$D$11:$D$30,Introduction!$F$11:$F$30),"_")) -> _ | H133: =-ROUND(H27*$O$2,2) -> 0 | I133: =+I132+H133 -> 0 | K133: =IF(J133=1,K132+H133,++K132) -> 0 | P133: =CONCATENATE(D133," ",E133," ",MONTH(C133)," ",YEAR(C133)," ") -> 1 1900
F134: =IF(D134="Income",LOOKUP(E134,Introduction!$A$11:$A$18,Introduction!$C$11:$C$18),IF(D134="Expense",LOOKUP(E134,Introduction!$D$11:$D$30,Introduction!$F$11:$F$30),"_")) -> _ | H134: =-ROUND(H28*$O$2,2) -> 0 | I134: =+I133+H134 -> 0 | K134: =IF(J134=1,K133+H134,++K133) -> 0 | P134: =CONCATENATE(D134," ",E134," ",MONTH(C134)," ",YEAR(C134)," ") -> 1 1900
F135: =IF(D135="Income",LOOKUP(E135,Introduction!$A$11:$A$18,Introduction!$C$11:$C$18),IF(D135="Expense",LOOKUP(E135,Introduction!$D$11:$D$30,Introduction!$F$11:$F$30),"_")) -> _ | H135: =-ROUND(H29*$O$2,2) -> 0 | I135: =+I134+H135 -> 0 | K135: =IF(J135=1,K134+H135,++K134) -> 0 | P135: =CONCATENATE(D135," ",E135," ",MONTH(C135)," ",YEAR(C135)," ") -> 1 1900
F136: =IF(D136="Income",LOOKUP(E136,Introduction!$A$11:$A$18,Introduction!$C$11:$C$18),IF(D136="Expense",LOOKUP(E136,Introduction!$D$11:$D$30,Introduction!$F$11:$F$30),"_")) -> _ | H136: =-ROUND(H30*$O$2,2) -> 0 | I136: =+I135+H136 -> 0 | K136: =IF(J136=1,K135+H136,++K135) -> 0 | P136: =CONCATENATE(D136," ",E136," ",MONTH(C136)," ",YEAR(C136)," ") -> 1 1900
F137: =IF(D137="Income",LOOKUP(E137,Introduction!$A$11:$A$18,Introduction!$C$11:$C$18),IF(D137="Expense",LOOKUP(E137,Introduction!$D$11:$D$30,Introduction!$F$11:$F$30),"_")) -> _ | I137: =+I136+H137 -> 0 | K137: =IF(J137=1,K136+H137,++K136) -> 0 | P137: =CONCATENATE(D137," ",E137," ",MONTH(C137)," ",YEAR(C137)," ") -> 1 1900
F138: =IF(D138="Income",LOOKUP(E138,Introduction!$A$11:$A$18,Introduction!$C$11:$C$18),IF(D138="Expense",LOOKUP(E138,Introduction!$D$11:$D$30,Introduction!$F$11:$F$30),"_")) -> _ | H138: =-ROUND(H32*$O$2,2) -> 0 | I138: =+I137+H138 -> 0 | K138: =IF(J138=1,K137+H138,++K137) -> 0 | P138: =CONCATENATE(D138," ",E138," ",MONTH(C138)," ",YEAR(C138)," ") -> 1 1900
F139: =IF(D139="Income",LOOKUP(E139,Introduction!$A$11:$A$18,Introduction!$C$11:$C$18),IF(D139="Expense",LOOKUP(E139,Introduction!$D$11:$D$30,Introduction!$F$11:$F$30),"_")) -> _ | H139: =-ROUND(H33*$O$2,2) -> 0 | I139: =+I138+H139 -> 0 | K139: =IF(J139=1,K138+H139,++K138) -> 0 | P139: =CONCATENATE(D139," ",E139," ",MONTH(C139)," ",YEAR(C139)," ") -> 1 1900
F140: =IF(D140="Income",LOOKUP(E140,Introduction!$A$11:$A$18,Introduction!$C$11:$C$18),IF(D140="Expense",LOOKUP(E140,Introduction!$D$11:$D$30,Introduction!$F$11:$F$30),"_")) -> _ | H140: =-ROUND(H34*$O$2,2) -> 0 | I140: =+I139+H140 -> 0 | K140: =IF(J140=1,K139+H140,++K139) -> 0 | P140: =CONCATENATE(D140," ",E140," ",MONTH(C140)," ",YEAR(C140)," ") -> 1 1900
F141: =IF(D141="Income",LOOKUP(E141,Introduction!$A$11:$A$18,Introduction!$C$11:$C$18),IF(D141="Expense",LOOKUP(E141,Introduction!$D$11:$D$30,Introduction!$F$11:$F$30),"_")) -> _ | H141: =-ROUND(H35*$O$2,2) -> 0 | I141: =+I140+H141 -> 0 | K141: =IF(J141=1,K140+H141,++K140) -> 0 | P141: =CONCATENATE(D141," ",E141," ",MONTH(C141)," ",YEAR(C141)," ") -> 1 1900
F142: =IF(D142="Income",LOOKUP(E142,Introduction!$A$11:$A$18,Introduction!$C$11:$C$18),IF(D142="Expense",LOOKUP(E142,Introduction!$D$11:$D$30,Introduction!$F$11:$F$30),"_")) -> _ | H142: =-ROUND(H36*$O$2,2) -> 0 | I142: =+I141+H142 -> 0 | K142: =IF(J142=1,K141+H142,++K141) -> 0 | P142: =CONCATENATE(D142," ",E142," ",MONTH(C142)," ",YEAR(C142)," ") -> 1 1900
F143: =IF(D143="Income",LOOKUP(E143,Introduction!$A$11:$A$18,Introduction!$C$11:$C$18),IF(D143="Expense",LOOKUP(E143,Introduction!$D$11:$D$30,Introduction!$F$11:$F$30),"_")) -> _ | H143: =-ROUND(H37*$O$2,2) -> 0 | I143: =+I142+H143 -> 0 | K143: =IF(J143=1,K142+H143,++K142) -> 0 | P143: =CONCATENATE(D143," ",E143," ",MONTH(C143)," ",YEAR(C143)," ") -> 1 1900
F144: =IF(D144="Income",LOOKUP(E144,Introduction!$A$11:$A$18,Introduction!$C$11:$C$18),IF(D144="Expense",LOOKUP(E144,Introduction!$D$11:$D$30,Introduction!$F$11:$F$30),"_")) -> _ | H144: =-ROUND(H38*$O$2,2) -> 0 | I144: =+I143+H144 -> 0 | K144: =IF(J144=1,K143+H144,++K143) -> 0 | P144: =CONCATENATE(D144," ",E144," ",MONTH(C144)," ",YEAR(C144)," ") -> 1 1900
F145: =IF(D145="Income",LOOKUP(E145,Introduction!$A$11:$A$18,Introduction!$C$11:$C$18),IF(D145="Expense",LOOKUP(E145,Introduction!$D$11:$D$30,Introduction!$F$11:$F$30),"_")) -> _ | H145: =-ROUND(H39*$O$2,2) -> 0 | I145: =+I144+H145 -> 0 | K145: =IF(J145=1,K144+H145,++K144) -> 0 | P145: =CONCATENATE(D145," ",E145," ",MONTH(C145)," ",YEAR(C145)," ") -> 1 1900
F146: =IF(D146="Income",LOOKUP(E146,Introduction!$A$11:$A$18,Introduction!$C$11:$C$18),IF(D146="Expense",LOOKUP(E146,Introduction!$D$11:$D$30,Introduction!$F$11:$F$30),"_")) -> _ | H146: =-ROUND(H40*$O$2,2) -> 0 | I146: =+I145+H146 -> 0 | K146: =IF(J146=1,K145+H146,++K145) -> 0 | P146: =CONCATENATE(D146," ",E146," ",MONTH(C146)," ",YEAR(C146)," ") -> 1 1900
F147: =IF(D147="Income",LOOKUP(E147,Introduction!$A$11:$A$18,Introduction!$C$11:$C$18),IF(D147="Expense",LOOKUP(E147,Introduction!$D$11:$D$30,Introduction!$F$11:$F$30),"_")) -> _ | H147: =-ROUND(H41*$O$2,2) -> 0 | I147: =+I146+H147 -> 0 | K147: =IF(J147=1,K146+H147,++K146) -> 0 | P147: =CONCATENATE(D147," ",E147," ",MONTH(C147)," ",YEAR(C147)," ") -> 1 1900
F148: =IF(D148="Income",LOOKUP(E148,Introduction!$A$11:$A$18,Introduction!$C$11:$C$18),IF(D148="Expense",LOOKUP(E148,Introduction!$D$11:$D$30,Introduction!$F$11:$F$30),"_")) -> _ | H148: =-ROUND(H42*$O$2,2) -> 0 | I148: =+I147+H148 -> 0 | K148: =IF(J148=1,K147+H148,++K147) -> 0 | P148: =CONCATENATE(D148," ",E148," ",MONTH(C148)," ",YEAR(C148)," ") -> 1 1900
F149: =IF(D149="Income",LOOKUP(E149,Introduction!$A$11:$A$18,Introduction!$C$11:$C$18),IF(D149="Expense",LOOKUP(E149,Introduction!$D$11:$D$30,Introduction!$F$11:$F$30),"_")) -> _ | H149: =-ROUND(H43*$O$2,2) -> 0 | I149: =+I148+H149 -> 0 | K149: =IF(J149=1,K148+H149,++K148) -> 0 | P149: =CONCATENATE(D149," ",E149," ",MONTH(C149)," ",YEAR(C149)," ") -> 1 1900
F150: =IF(D150="Income",LOOKUP(E150,Introduction!$A$11:$A$18,Introduction!$C$11:$C$18),IF(D150="Expense",LOOKUP(E150,Introduction!$D$11:$D$30,Introduction!$F$11:$F$30),"_")) -> _ | I150: =+I149+H150 -> 0 | K150: =IF(J150=1,K149+H150,++K149) -> 0 | P150: =CONCATENATE(D150," ",E150," ",MONTH(C150)," ",YEAR(C150)," ") -> 1 1900
F151: =IF(D151="Income",LOOKUP(E151,Introduction!$A$11:$A$18,Introduction!$C$11:$C$18),IF(D151="Expense",LOOKUP(E151,Introduction!$D$11:$D$30,Introduction!$F$11:$F$30),"_")) -> _ | H151: =-ROUND(H45*$O$2,2) -> 0 | I151: =+I150+H151 -> 0 | K151: =IF(J151=1,K150+H151,++K150) -> 0 | P151: =CONCATENATE(D151," ",E151," ",MONTH(C151)," ",YEAR(C151)," ") -> 1 1900
F152: =IF(D152="Income",LOOKUP(E152,Introduction!$A$11:$A$18,Introduction!$C$11:$C$18),IF(D152="Expense",LOOKUP(E152,Introduction!$D$11:$D$30,Introduction!$F$11:$F$30),"_")) -> _ | H152: =-ROUND(H46*$O$2,2) -> 0 | I152: =+I151+H152 -> 0 | K152: =IF(J152=1,K151+H152,++K151) -> 0 | P152: =CONCATENATE(D152," ",E152," ",MONTH(C152)," ",YEAR(C152)," ") -> 1 1900
F153: =IF(D153="Income",LOOKUP(E153,Introduction!$A$11:$A$18,Introduction!$C$11:$C$18),IF(D153="Expense",LOOKUP(E153,Introduction!$D$11:$D$30,Introduction!$F$11:$F$30),"_")) -> _ | H153: =-ROUND(H47*$O$2,2) -> 0 | I153: =+I152+H153 -> 0 | K153: =IF(J153=1,K152+H153,++K152) -> 0 | P153: =CONCATENATE(D153," ",E153," ",MONTH(C153)," ",YEAR(C153)," ") -> 1 1900
F154: =IF(D154="Income",LOOKUP(E154,Introduction!$A$11:$A$18,Introduction!$C$11:$C$18),IF(D154="Expense",LOOKUP(E154,Introduction!$D$11:$D$30,Introduction!$F$11:$F$30),"_")) -> _ | H154: =-ROUND(H48*$O$2,2) -> 0 | I154: =+I153+H154 -> 0 | K154: =IF(J154=1,K153+H154,++K153) -> 0 | P154: =CONCATENATE(D154," ",E154," ",MONTH(C154)," ",YEAR(C154)," ") -> 1 1900
F155: =IF(D155="Income",LOOKUP(E155,Introduction!$A$11:$A$18,Introduction!$C$11:$C$18),IF(D155="Expense",LOOKUP(E155,Introduction!$D$11:$D$30,Introduction!$F$11:$F$30),"_")) -> _ | H155: =-ROUND(H49*$O$2,2) -> 0 | I155: =+I154+H155 -> 0 | K155: =IF(J155=1,K154+H155,++K154) -> 0 | P155: =CONCATENATE(D155," ",E155," ",MONTH(C155)," ",YEAR(C155)," ") -> 1 1900
F156: =IF(D156="Income",LOOKUP(E156,Introduction!$A$11:$A$18,Introduction!$C$11:$C$18),IF(D156="Expense",LOOKUP(E156,Introduction!$D$11:$D$30,Introduction!$F$11:$F$30),"_")) -> _ | H156: =-ROUND(H50*$O$2,2) -> 0 | I156: =+I155+H156 -> 0 | K156: =IF(J156=1,K155+H156,++K155) -> 0 | P156: =CONCATENATE(D156," ",E156," ",MONTH(C156)," ",YEAR(C156)," ") -> 1 1900
F157: =IF(D157="Income",LOOKUP(E157,Introduction!$A$11:$A$18,Introduction!$C$11:$C$18),IF(D157="Expense",LOOKUP(E157,Introduction!$D$11:$D$30,Introduction!$F$11:$F$30),"_")) -> _ | H157: =-ROUND(H51*$O$2,2) -> 0 | I157: =+I156+H157 -> 0 | K157: =IF(J157=1,K156+H157,++K156) -> 0 | P157: =CONCATENATE(D157," ",E157," ",MONTH(C157)," ",YEAR(C157)," ") -> 1 1900
F158: =IF(D158="Income",LOOKUP(E158,Introduction!$A$11:$A$18,Introduction!$C$11:$C$18),IF(D158="Expense",LOOKUP(E158,Introduction!$D$11:$D$30,Introduction!$F$11:$F$30),"_")) -> _ | H158: =-ROUND(H52*$O$2,2) -> 0 | I158: =+I157+H158 -> 0 | K158: =IF(J158=1,K157+H158,++K157) -> 0 | P158: =CONCATENATE(D158," ",E158," ",MONTH(C158)," ",YEAR(C158)," ") -> 1 1900
F159: =IF(D159="Income",LOOKUP(E159,Introduction!$A$11:$A$18,Introduction!$C$11:$C$18),IF(D159="Expense",LOOKUP(E159,Introduction!$D$11:$D$30,Introduction!$F$11:$F$30),"_")) -> _ | H159: =-ROUND(H53*$O$2,2) -> 0 | I159: =+I158+H159 -> 0 | K159: =IF(J159=1,K158+H159,++K158) -> 0 | P159: =CONCATENATE(D159," ",E159," ",MONTH(C159)," ",YEAR(C159)," ") -> 1 1900
F160: =IF(D160="Income",LOOKUP(E160,Introduction!$A$11:$A$18,Introduction!$C$11:$C$18),IF(D160="Expense",LOOKUP(E160,Introduction!$D$11:$D$30,Introduction!$F$11:$F$30),"_")) -> _ | H160: =-ROUND(H54*$O$2,2) -> 0 | I160: =+I159+H160 -> 0 | K160: =IF(J160=1,K159+H160,++K159) -> 0 | P160: =CONCATENATE(D160," ",E160," ",MONTH(C160)," ",YEAR(C160)," ") -> 1 1900
F161: =IF(D161="Income",LOOKUP(E161,Introduction!$A$11:$A$18,Introduction!$C$11:$C$18),IF(D161="Expense",LOOKUP(E161,Introduction!$D$11:$D$30,Introduction!$F$11:$F$30),"_")) -> _ | H161: =-ROUND(H55*$O$2,2) -> 0 | I161: =+I160+H161 -> 0 | K161: =IF(J161=1,K160+H161,++K160) -> 0 | P161: =CONCATENATE(D161," ",E161," ",MONTH(C161)," ",YEAR(C161)," ") -> 1 1900
F162: =IF(D162="Income",LOOKUP(E162,Introduction!$A$11:$A$18,Introduction!$C$11:$C$18),IF(D162="Expense",LOOKUP(E162,Introduction!$D$11:$D$30,Introduction!$F$11:$F$30),"_")) -> _ | H162: =-ROUND(H56*$O$2,2) -> 0 | I162: =+I161+H162 -> 0 | K162: =IF(J162=1,K161+H162,++K161) -> 0 | P162: =CONCATENATE(D162," ",E162," ",MONTH(C162)," ",YEAR(C162)," ") -> 1 1900
F163: =IF(D163="Income",LOOKUP(E163,Introduction!$A$11:$A$18,Introduction!$C$11:$C$18),IF(D163="Expense",LOOKUP(E163,Introduction!$D$11:$D$30,Introduction!$F$11:$F$30),"_")) -> _ | I163: =+I162+H163 -> 0 | K163: =IF(J163=1,K162+H163,++K162) -> 0 | P163: =CONCATENATE(D163," ",E163," ",MONTH(C163)," ",YEAR(C163)," ") -> 1 1900
F164: =IF(D164="Income",LOOKUP(E164,Introduction!$A$11:$A$18,Introduction!$C$11:$C$18),IF(D164="Expense",LOOKUP(E164,Introduction!$D$11:$D$30,Introduction!$F$11:$F$30),"_")) -> _ | H164: =-ROUND(H58*$O$2,2) -> 0 | I164: =+I163+H164 -> 0 | K164: =IF(J164=1,K163+H164,++K163) -> 0 | P164: =CONCATENATE(D164," ",E164," ",MONTH(C164)," ",YEAR(C164)," ") -> 1 1900
F165: =IF(D165="Income",LOOKUP(E165,Introduction!$A$11:$A$18,Introduction!$C$11:$C$18),IF(D165="Expense",LOOKUP(E165,Introduction!$D$11:$D$30,Introduction!$F$11:$F$30),"_")) -> _ | H165: =-ROUND(H59*$O$2,2) -> 0 | I165: =+I164+H165 -> 0 | K165: =IF(J165=1,K164+H165,++K164) -> 0 | P165: =CONCATENATE(D165," ",E165," ",MONTH(C165)," ",YEAR(C165)," ") -> 1 1900
F166: =IF(D166="Income",LOOKUP(E166,Introduction!$A$11:$A$18,Introduction!$C$11:$C$18),IF(D166="Expense",LOOKUP(E166,Introduction!$D$11:$D$30,Introduction!$F$11:$F$30),"_")) -> _ | H166: =-ROUND(H60*$O$2,2) -> 0 | I166: =+I165+H166 -> 0 | K166: =IF(J166=1,K165+H166,++K165) -> 0 | P166: =CONCATENATE(D166," ",E166," ",MONTH(C166)," ",YEAR(C166)," ") -> 1 1900
F167: =IF(D167="Income",LOOKUP(E167,Introduction!$A$11:$A$18,Introduction!$C$11:$C$18),IF(D167="Expense",LOOKUP(E167,Introduction!$D$11:$D$30,Introduction!$F$11:$F$30),"_")) -> _ | H167: =-ROUND(H61*$O$2,2) -> 0 | I167: =+I166+H167 -> 0 | K167: =IF(J167=1,K166+H167,++K166) -> 0 | P167: =CONCATENATE(D167," ",E167," ",MONTH(C167)," ",YEAR(C167)," ") -> 1 1900
F168: =IF(D168="Income",LOOKUP(E168,Introduction!$A$11:$A$18,Introduction!$C$11:$C$18),IF(D168="Expense",LOOKUP(E168,Introduction!$D$11:$D$30,Introduction!$F$11:$F$30),"_")) -> _ | H168: =-ROUND(H62*$O$2,2) -> 0 | I168: =+I167+H168 -> 0 | K168: =IF(J168=1,K167+H168,++K167) -> 0 | P168: =CONCATENATE(D168," ",E168," ",MONTH(C168)," ",YEAR(C168)," ") -> 1 1900
F169: =IF(D169="Income",LOOKUP(E169,Introduction!$A$11:$A$18,Introduction!$C$11:$C$18),IF(D169="Expense",LOOKUP(E169,Introduction!$D$11:$D$30,Introduction!$F$11:$F$30),"_")) -> _ | H169: =-ROUND(H63*$O$2,2) -> 0 | I169: =+I168+H169 -> 0 | K169: =IF(J169=1,K168+H169,++K168) -> 0 | P169: =CONCATENATE(D169," ",E169," ",MONTH(C169)," ",YEAR(C169)," ") -> 1 1900
F170: =IF(D170="Income",LOOKUP(E170,Introduction!$A$11:$A$18,Introduction!$C$11:$C$18),IF(D170="Expense",LOOKUP(E170,Introduction!$D$11:$D$30,Introduction!$F$11:$F$30),"_")) -> _ | H170: =-ROUND(H64*$O$2,2) -> 0 | I170: =+I169+H170 -> 0 | K170: =IF(J170=1,K169+H170,++K169) -> 0 | P170: =CONCATENATE(D170," ",E170," ",MONTH(C170)," ",YEAR(C170)," ") -> 1 1900
F171: =IF(D171="Income",LOOKUP(E171,Introduction!$A$11:$A$18,Introduction!$C$11:$C$18),IF(D171="Expense",LOOKUP(E171,Introduction!$D$11:$D$30,Introduction!$F$11:$F$30),"_")) -> _ | H171: =-ROUND(H65*$O$2,2) -> 0 | I171: =+I170+H171 -> 0 | K171: =IF(J171=1,K170+H171,++K170) -> 0 | P171: =CONCATENATE(D171," ",E171," ",MONTH(C171)," ",YEAR(C171)," ") -> 1 1900
F172: =IF(D172="Income",LOOKUP(E172,Introduction!$A$11:$A$18,Introduction!$C$11:$C$18),IF(D172="Expense",LOOKUP(E172,Introduction!$D$11:$D$30,Introduction!$F$11:$F$30),"_")) -> _ | H172: =-ROUND(H66*$O$2,2) -> 0 | I172: =+I171+H172 -> 0 | K172: =IF(J172=1,K171+H172,++K171) -> 0 | P172: =CONCATENATE(D172," ",E172," ",MONTH(C172)," ",YEAR(C172)," ") -> 1 1900
F173: =IF(D173="Income",LOOKUP(E173,Introduction!$A$11:$A$18,Introduction!$C$11:$C$18),IF(D173="Expense",LOOKUP(E173,Introduction!$D$11:$D$30,Introduction!$F$11:$F$30),"_")) -> _ | H173: =-ROUND(H67*$O$2,2) -> 0 | I173: =+I172+H173 -> 0 | K173: =IF(J173=1,K172+H173,++K172) -> 0 | P173: =CONCATENATE(D173," ",E173," ",MONTH(C173)," ",YEAR(C173)," ") -> 1 1900
F174: =IF(D174="Income",LOOKUP(E174,Introduction!$A$11:$A$18,Introduction!$C$11:$C$18),IF(D174="Expense",LOOKUP(E174,Introduction!$D$11:$D$30,Introduction!$F$11:$F$30),"_")) -> _ | H174: =-ROUND(H68*$O$2,2) -> 0 | I174: =+I173+H174 -> 0 | K174: =IF(J174=1,K173+H174,++K173) -> 0 | P174: =CONCATENATE(D174," ",E174," ",MONTH(C174)," ",YEAR(C174)," ") -> 1 1900
F175: =IF(D175="Income",LOOKUP(E175,Introduction!$A$11:$A$18,Introduction!$C$11:$C$18),IF(D175="Expense",LOOKUP(E175,Introduction!$D$11:$D$30,Introduction!$F$11:$F$30),"_")) -> _ | H175: =-ROUND(H69*$O$2,2) -> 0 | I175: =+I174+H175 -> 0 | K175: =IF(J175=1,K174+H175,++K174) -> 0 | P175: =CONCATENATE(D175," ",E175," ",MONTH(C175)," ",YEAR(C175)," ") -> 1 1900
F176: =IF(D176="Income",LOOKUP(E176,Introduction!$A$11:$A$18,Introduction!$C$11:$C$18),IF(D176="Expense",LOOKUP(E176,Introduction!$D$11:$D$30,Introduction!$F$11:$F$30),"_")) -> _ | I176: =+I175+H176 -> 0 | K176: =IF(J176=1,K175+H176,++K175) -> 0 | P176: =CONCATENATE(D176," ",E176," ",MONTH(C176)," ",YEAR(C176)," ") -> 1 1900
F177: =IF(D177="Income",LOOKUP(E177,Introduction!$A$11:$A$18,Introduction!$C$11:$C$18),IF(D177="Expense",LOOKUP(E177,Introduction!$D$11:$D$30,Introduction!$F$11:$F$30),"_")) -> _ | H177: =-ROUND(H71*$O$2,2) -> 0 | I177: =+I176+H177 -> 0 | K177: =IF(J177=1,K176+H177,++K176) -> 0 | P177: =CONCATENATE(D177," ",E177," ",MONTH(C177)," ",YEAR(C177)," ") -> 1 1900
F178: =IF(D178="Income",LOOKUP(E178,Introduction!$A$11:$A$18,Introduction!$C$11:$C$18),IF(D178="Expense",LOOKUP(E178,Introduction!$D$11:$D$30,Introduction!$F$11:$F$30),"_")) -> _ | H178: =-ROUND(H72*$O$2,2) -> 0 | I178: =+I177+H178 -> 0 | K178: =IF(J178=1,K177+H178,++K177) -> 0 | P178: =CONCATENATE(D178," ",E178," ",MONTH(C178)," ",YEAR(C178)," ") -> 1 1900
F179: =IF(D179="Income",LOOKUP(E179,Introduction!$A$11:$A$18,Introduction!$C$11:$C$18),IF(D179="Expense",LOOKUP(E179,Introduction!$D$11:$D$30,Introduction!$F$11:$F$30),"_")) -> _ | H179: =-ROUND(H73*$O$2,2) -> 0 | I179: =+I178+H179 -> 0 | K179: =IF(J179=1,K178+H179,++K178) -> 0 | P179: =CONCATENATE(D179," ",E179," ",MONTH(C179)," ",YEAR(C179)," ") -> 1 1900
F180: =IF(D180="Income",LOOKUP(E180,Introduction!$A$11:$A$18,Introduction!$C$11:$C$18),IF(D180="Expense",LOOKUP(E180,Introduction!$D$11:$D$30,Introduction!$F$11:$F$30),"_")) -> _ | H180: =-ROUND(H74*$O$2,2) -> 0 | I180: =+I179+H180 -> 0 | K180: =IF(J180=1,K179+H180,++K179) -> 0 | P180: =CONCATENATE(D180," ",E180," ",MONTH(C180)," ",YEAR(C180)," ") -> 1 1900
F181: =IF(D181="Income",LOOKUP(E181,Introduction!$A$11:$A$18,Introduction!$C$11:$C$18),IF(D181="Expense",LOOKUP(E181,Introduction!$D$11:$D$30,Introduction!$F$11:$F$30),"_")) -> _ | H181: =-ROUND(H75*$O$2,2) -> 0 | I181: =+I180+H181 -> 0 | K181: =IF(J181=1,K180+H181,++K180) -> 0 | P181: =CONCATENATE(D181," ",E181," ",MONTH(C181)," ",YEAR(C181)," ") -> 1 1900
F182: =IF(D182="Income",LOOKUP(E182,Introduction!$A$11:$A$18,Introduction!$C$11:$C$18),IF(D182="Expense",LOOKUP(E182,Introduction!$D$11:$D$30,Introduction!$F$11:$F$30),"_")) -> _ | H182: =-ROUND(H76*$O$2,2) -> 0 | I182: =+I181+H182 -> 0 | K182: =IF(J182=1,K181+H182,++K181) -> 0 | P182: =CONCATENATE(D182," ",E182," ",MONTH(C182)," ",YEAR(C182)," ") -> 1 1900
F183: =IF(D183="Income",LOOKUP(E183,Introduction!$A$11:$A$18,Introduction!$C$11:$C$18),IF(D183="Expense",LOOKUP(E183,Introduction!$D$11:$D$30,Introduction!$F$11:$F$30),"_")) -> _ | H183: =-ROUND(H77*$O$2,2) -> 0 | I183: =+I182+H183 -> 0 | K183: =IF(J183=1,K182+H183,++K182) -> 0 | P183: =CONCATENATE(D183," ",E183," ",MONTH(C183)," ",YEAR(C183)," ") -> 1 1900
F184: =IF(D184="Income",LOOKUP(E184,Introduction!$A$11:$A$18,Introduction!$C$11:$C$18),IF(D184="Expense",LOOKUP(E184,Introduction!$D$11:$D$30,Introduction!$F$11:$F$30),"_")) -> _ | H184: =-ROUND(H78*$O$2,2) -> 0 | I184: =+I183+H184 -> 0 | K184: =IF(J184=1,K183+H184,++K183) -> 0 | P184: =CONCATENATE(D184," ",E184," ",MONTH(C184)," ",YEAR(C184)," ") -> 1 1900
F185: =IF(D185="Income",LOOKUP(E185,Introduction!$A$11:$A$18,Introduction!$C$11:$C$18),IF(D185="Expense",LOOKUP(E185,Introduction!$D$11:$D$30,Introduction!$F$11:$F$30),"_")) -> _ | H185: =-ROUND(H79*$O$2,2) -> 0 | I185: =+I184+H185 -> 0 | K185: =IF(J185=1,K184+H185,++K184) -> 0 | P185: =CONCATENATE(D185," ",E185," ",MONTH(C185)," ",YEAR(C185)," ") -> 1 1900
F186: =IF(D186="Income",LOOKUP(E186,Introduction!$A$11:$A$18,Introduction!$C$11:$C$18),IF(D186="Expense",LOOKUP(E186,Introduction!$D$11:$D$30,Introduction!$F$11:$F$30),"_")) -> _ | H186: =-ROUND(H80*$O$2,2) -> 0 | I186: =+I185+H186 -> 0 | K186: =IF(J186=1,K185+H186,++K185) -> 0 | P186: =CONCATENATE(D186," ",E186," ",MONTH(C186)," ",YEAR(C186)," ") -> 1 1900
F187: =IF(D187="Income",LOOKUP(E187,Introduction!$A$11:$A$18,Introduction!$C$11:$C$18),IF(D187="Expense",LOOKUP(E187,Introduction!$D$11:$D$30,Introduction!$F$11:$F$30),"_")) -> _ | H187: =-ROUND(H81*$O$2,2) -> 0 | I187: =+I186+H187 -> 0 | K187: =IF(J187=1,K186+H187,++K186) -> 0 | P187: =CONCATENATE(D187," ",E187," ",MONTH(C187)," ",YEAR(C187)," ") -> 1 1900
F188: =IF(D188="Income",LOOKUP(E188,Introduction!$A$11:$A$18,Introduction!$C$11:$C$18),IF(D188="Expense",LOOKUP(E188,Introduction!$D$11:$D$30,Introduction!$F$11:$F$30),"_")) -> _ | H188: =-ROUND(H82*$O$2,2) -> 0 | I188: =+I187+H188 -> 0 | K188: =IF(J188=1,K187+H188,++K187) -> 0 | P188: =CONCATENATE(D188," ",E188," ",MONTH(C188)," ",YEAR(C188)," ") -> 1 1900
F189: =IF(D189="Income",LOOKUP(E189,Introduction!$A$11:$A$18,Introduction!$C$11:$C$18),IF(D189="Expense",LOOKUP(E189,Introduction!$D$11:$D$30,Introduction!$F$11:$F$30),"_")) -> _ | I189: =+I188+H189 -> 0 | K189: =IF(J189=1,K188+H189,++K188) -> 0 | P189: =CONCATENATE(D189," ",E189," ",MONTH(C189)," ",YEAR(C189)," ") -> 1 1900
F190: =IF(D190="Income",LOOKUP(E190,Introduction!$A$11:$A$18,Introduction!$C$11:$C$18),IF(D190="Expense",LOOKUP(E190,Introduction!$D$11:$D$30,Introduction!$F$11:$F$30),"_")) -> _ | H190: =-ROUND(H84*$O$2,2) -> 0 | I190: =+I189+H190 -> 0 | K190: =IF(J190=1,K189+H190,++K189) -> 0 | P190: =CONCATENATE(D190," ",E190," ",MONTH(C190)," ",YEAR(C190)," ") -> 1 1900
F191: =IF(D191="Income",LOOKUP(E191,Introduction!$A$11:$A$18,Introduction!$C$11:$C$18),IF(D191="Expense",LOOKUP(E191,Introduction!$D$11:$D$30,Introduction!$F$11:$F$30),"_")) -> _ | H191: =-ROUND(H85*$O$2,2) -> 0 | I191: =+I190+H191 -> 0 | K191: =IF(J191=1,K190+H191,++K190) -> 0 | P191: =CONCATENATE(D191," ",E191," ",MONTH(C191)," ",YEAR(C191)," ") -> 1 1900
F192: =IF(D192="Income",LOOKUP(E192,Introduction!$A$11:$A$18,Introduction!$C$11:$C$18),IF(D192="Expense",LOOKUP(E192,Introduction!$D$11:$D$30,Introduction!$F$11:$F$30),"_")) -> _ | H192: =-ROUND(H86*$O$2,2) -> 0 | I192: =+I191+H192 -> 0 | K192: =IF(J192=1,K191+H192,++K191) -> 0 | P192: =CONCATENATE(D192," ",E192," ",MONTH(C192)," ",YEAR(C192)," ") -> 1 1900
F193: =IF(D193="Income",LOOKUP(E193,Introduction!$A$11:$A$18,Introduction!$C$11:$C$18),IF(D193="Expense",LOOKUP(E193,Introduction!$D$11:$D$30,Introduction!$F$11:$F$30),"_")) -> _ | H193: =-ROUND(H87*$O$2,2) -> 0 | I193: =+I192+H193 -> 0 | K193: =IF(J193=1,K192+H193,++K192) -> 0 | P193: =CONCATENATE(D193," ",E193," ",MONTH(C193)," ",YEAR(C193)," ") -> 1 1900
F194: =IF(D194="Income",LOOKUP(E194,Introduction!$A$11:$A$18,Introduction!$C$11:$C$18),IF(D194="Expense",LOOKUP(E194,Introduction!$D$11:$D$30,Introduction!$F$11:$F$30),"_")) -> _ | H194: =-ROUND(H88*$O$2,2) -> 0 | I194: =+I193+H194 -> 0 | K194: =IF(J194=1,K193+H194,++K193) -> 0 | P194: =CONCATENATE(D194," ",E194," ",MONTH(C194)," ",YEAR(C194)," ") -> 1 1900
...

Sheet Budget
B2: =CONCATENATE(Introduction!C4:C4,"'s"," Personal Budget ",Introduction!C5) -> 's Personal Budget 2012
B3: Days on Month Calc | E3: 31 | F3: =IF(MOD(Introduction!C5,4)=0,29,28) -> 29 | G3: 31 | H3: 30 | I3: 31 | J3: 30 | K3: 31 | L3: 31 | M3: 30 | N3: 31 | O3: 30 | P3: 31
B4: Month and Year Calc | E4: =CONCATENATE(MONTH(E5)," ",YEAR(E5)) -> 1 2012 | F4: =CONCATENATE(MONTH(F5)," ",YEAR(F5)) -> 2 2012 | G4: =CONCATENATE(MONTH(G5)," ",YEAR(G5)) -> 3 2012 | H4: =CONCATENATE(MONTH(H5)," ",YEAR(H5)) -> 4 2012 | I4: =CONCATENATE(MONTH(I5)," ",YEAR(I5)) -> 5 2012 | J4: =CONCATENATE(MONTH(J5)," ",YEAR(J5)) -> 6 2012 | K4: =CONCATENATE(MONTH(K5)," ",YEAR(K5)) -> 7 2012 | L4: =CONCATENATE(MONTH(L5)," ",YEAR(L5)) -> 8 2012 | ... P4: =CONCATENATE(MONTH(P5)," ",YEAR(P5)) -> 12 2012
B5: Items Revenue/Expense | E5: =+Introduction!C6+0 -> 40909 | F5: =+E5+E3 -> 40940 | G5: =+F5+F3 -> 40969 | H5: =+G5+G3 -> 41000 | I5: =+H5+H3 -> 41030 | J5: =+I5+I3 -> 41061 | K5: =+J5+J3 -> 41091 | L5: =+K5+K3 -> 41122 | M5: =+L5+L3 -> 41153 | ... Q5: =+P5+P3 -> 41275 | R5: Total
B6: 1 | C6: =+Introduction!C11 -> Income 1 | Q6: . | R6: =SUM(E6:P6) -> 0
B7: 2 | C7: =+Introduction!C12 -> Income 2 | R7: =SUM(E7:P7) -> 0
B8: 3 | C8: =+Introduction!C13 -> Income 3 | R8: =SUM(E8:P8) -> 0
B9: 4 | C9: =+Introduction!C14 -> Income 4 | R9: =SUM(E9:P9) -> 0
B10: 5 | C10: =+Introduction!C15 -> Income 5 | R10: =SUM(E10:P10) -> 0
B11: 6 | C11: =+Introduction!C16 -> Income 6 | R11: =SUM(E11:P11) -> 0
B12: 7 | C12: =+Introduction!C17 -> Income 7 | R12: =SUM(E12:P12) -> 0
B13: 8 | C13: =+Introduction!C18 -> Income 8 | R13: =SUM(E13:P13) -> 0
C14: Total Income | E14: =SUM(E6:E13) -> 0 | F14: =SUM(F6:F13) -> 0 | G14: =SUM(G6:G13) -> 0 | H14: =SUM(H6:H13) -> 0 | I14: =SUM(I6:I13) -> 0 | J14: =SUM(J6:J13) -> 0 | K14: =SUM(K6:K13) -> 0 | L14: =SUM(L6:L13) -> 0 | ... R14: =SUM(R6:R13) -> 0
R15: =IF(SUM(E15:P15)<>0,SUM(E15:P15),"")
C16: Month and Year Calc Income/Expense | E16: =CONCATENATE(MONTH(E17)," ",YEAR(E17), " Expense") -> 1 2012 Expense | F16: =CONCATENATE(MONTH(F17)," ",YEAR(F17), " Expense") -> 2 2012 Expense | G16: =CONCATENATE(MONTH(G17)," ",YEAR(G17), " Expense") -> 3 2012 Expense | H16: =CONCATENATE(MONTH(H17)," ",YEAR(H17), " Expense") -> 4 2012 Expense | I16: =CONCATENATE(MONTH(I17)," ",YEAR(I17), " Expense") -> 5 2012 Expense | J16: =CONCATENATE(MONTH(J17)," ",YEAR(J17), " Expense") -> 6 2012 Expense | K16: =CONCATENATE(MONTH(K17)," ",YEAR(K17), " Expense") -> 7 2012 Expense | L16: =CONCATENATE(MONTH(L17)," ",YEAR(L17), " Expense") -> 8 2012 Expense | ... P16: =CONCATENATE(MONTH(P17)," ",YEAR(P17), " Expense") -> 12 2012 Expense
C17: Expenses | E17: =+E5 -> 40909 | F17: =+F5 -> 40940 | G17: =+G5 -> 40969 | H17: =+H5 -> 41000 | I17: =+I5 -> 41030 | J17: =+J5 -> 41061 | K17: =+K5 -> 41091 | L17: =+L5 -> 41122 | ... P17: =+P5 -> 41244 | R17: Total
B18: 1 | C18: =+Introduction!F11 -> Expense 1 | R18: =SUM(E18:P18) -> 0
B19: 2 | C19: =+Introduction!F12 -> Expense 2 | R19: =SUM(E19:P19) -> 0
B20: 3 | C20: =+Introduction!F13 -> Expense 3 | R20: =SUM(E20:P20) -> 0
B21: 4 | C21: =+Introduction!F14 -> Expense 4 | R21: =SUM(E21:P21) -> 0
B22: 5 | C22: =+Introduction!F15 -> Expense 5 | R22: =SUM(E22:P22) -> 0
B23: 6 | C23: =+Introduction!F16 -> Expense 6 | R23: =SUM(E23:P23) -> 0
B24: 7 | C24: =+Introduction!F17 -> Expense 7 | R24: =SUM(E24:P24) -> 0
B25: 8 | C25: =+Introduction!F18 -> Expense 8 | R25: =SUM(E25:P25) -> 0
B26: 9 | C26: =+Introduction!F19 -> Expense 9 | R26: =SUM(E26:P26) -> 0
B27: 10 | C27: =+Introduction!F20 -> Expense 10 | R27: =SUM(E27:P27) -> 0
B28: 11 | C28: =+Introduction!F21 -> Expense 11 | R28: =SUM(E28:P28) -> 0
B29: 12 | C29: =+Introduction!F22 -> Expense 12 | R29: =SUM(E29:P29) -> 0
... B37: 20 | C37: =+Introduction!F30 -> IRA Contribution | R37: =SUM(E37:P37) -> 0
B38: Total Expenses | E38: =SUM(E18:E37) -> 0 | F38: =SUM(F18:F37) -> 0 | G38: =SUM(G18:G37) -> 0 | H38: =SUM(H18:H37) -> 0 | I38: =SUM(I18:I37) -> 0 | J38: =SUM(J18:J37) -> 0 | K38: =SUM(K18:K37) -> 0 | L38: =SUM(L18:L37) -> 0 | ... P38: =SUM(P18:P37) -> 0 | R38: =SUM(E38:P38) -> 0
R39: =IF(SUM(E39:P39)<>0,SUM(E39:P39),"")
B40: Income Less Expenses | E40: =+E14-E38 -> 0 | F40: =+F14-F38 -> 0 | G40: =+G14-G38 -> 0 | H40: =+H14-H38 -> 0 | I40: =+I14-I38 -> 0 | J40: =+J14-J38 -> 0 | K40: =+K14-K38 -> 0 | L40: =+L14-L38 -> 0 | ... R40: =+R14-R38 -> 0
R41: =IF(SUM(E41:P41)<>0,SUM(E41:P41),"")
B42: 1 | C42: Beginning Cash Balance | E42: =+Introduction!F32 -> 0 | F42: =+E44 -> 0 | G42: =+F44 -> 0 | H42: =+G44 -> 0 | I42: =+H44 -> 0 | J42: =+I44 -> 0 | K42: =+J44 -> 0 | L42: =+K44 -> 0 | M42: =+L44 -> 0 | ... P42: =+O44 -> 0 | R42: =+E42 -> 0
B43: 2 | C43: Income Less Expense | E43: =+E40 -> 0 | F43: =+F40 -> 0 | G43: =+G40 -> 0 | H43: =+H40 -> 0 | I43: =+I40 -> 0 | J43: =+J40 -> 0 | K43: =+K40 -> 0 | L43: =+L40 -> 0 | ... P43: =+P40 -> 0 | R43: =SUM(E43:P43) -> 0
B44: 3 | C44: Ending Cash Balance | E44: =+E43+E42 -> 0 | F44: =+F43+F42 -> 0 | G44: =+G43+G42 -> 0 | H44: =+H43+H42 -> 0 | I44: =+I43+I42 -> 0 | J44: =+J43+J42 -> 0 | K44: =+K43+K42 -> 0 | L44: =+L43+L42 -> 0 | ... P44: =+P43+P42 -> 0 | Q44: =IFERROR(IF(OR(Q42<>0,Q43<>0),Q42+Q43,""),"") | R44: =R42+R43 -> 0
B46: 1 | C46: Roth IRA Cumulative Contribution | E46: =+Introduction!F31+Budget!E37 -> 0 | F46: =+E46+F37 -> 0 | G46: =+F46+G37 -> 0 | H46: =+G46+H37 -> 0 | I46: =+H46+I37 -> 0 | J46: =+I46+J37 -> 0 | K46: =+J46+K37 -> 0 | L46: =+K46+L37 -> 0 | M46: =+L46+M37 -> 0 | ... P46: =+O46+P37 -> 0 | R46: =+P46 -> 0
R48: =IF(SUM(E48:P48)<>0,SUM(E48:P48),"")
R49: =IF(SUM(E49:P49)<>0,SUM(E49:P49),"")
R50: =IF(SUM(E50:P50)<>0,SUM(E50:P50),"")
R51: =IF(SUM(E51:P51)<>0,SUM(E51:P51),"")
R52: =IF(SUM(E52:P52)<>0,SUM(E52:P52),"")
R53: =IF(SUM(E53:P53)<>0,SUM(E53:P53),"")
R54: =IF(SUM(E54:P54)<>0,SUM(E54:P54),"")
R55: =IF(SUM(E55:P55)<>0,SUM(E55:P55),"")
R56: =IF(SUM(E56:P56)<>0,SUM(E56:P56),"")
R57: =IF(SUM(E57:P57)<>0,SUM(E57:P57),"")
R58: =IF(SUM(E58:P58)<>0,SUM(E58:P58),"")
R59: =IF(SUM(E59:P59)<>0,SUM(E59:P59),"")
... R117: =IF(SUM(E117:P117)<>0,SUM(E117:P117),"")

Sheet Actual
B2: =CONCATENATE(Introduction!C4:C4,"'s"," ACTUAL SPENDING ",Introduction!C5) -> 's ACTUAL SPENDING 2012
C3: Days on Month Calc | E3: 31 | F3: =IF(MOD(Introduction!C5,4)=0,29,28) -> 29 | G3: 31 | H3: 30 | I3: 31 | J3: 30 | K3: 31 | L3: 31 | M3: 30 | N3: 31 | O3: 30 | P3: 31
C4: Month and Year Calc Income/Expense | E4: =CONCATENATE(MONTH(E5)," ",YEAR(E5), " Income") -> 1 2012 Income | F4: =CONCATENATE(MONTH(F5)," ",YEAR(F5), " Income") -> 2 2012 Income | G4: =CONCATENATE(MONTH(G5)," ",YEAR(G5), " Income") -> 3 2012 Income | H4: =CONCATENATE(MONTH(H5)," ",YEAR(H5), " Income") -> 4 2012 Income | I4: =CONCATENATE(MONTH(I5)," ",YEAR(I5), " Income") -> 5 2012 Income | J4: =CONCATENATE(MONTH(J5)," ",YEAR(J5), " Income") -> 6 2012 Income | K4: =CONCATENATE(MONTH(K5)," ",YEAR(K5), " Income") -> 7 2012 Income | L4: =CONCATENATE(MONTH(L5)," ",YEAR(L5), " Income") -> 8 2012 Income | ... P4: =CONCATENATE(MONTH(P5)," ",YEAR(P5), " Income") -> 12 2012 Income
B5: ={"Items Revenue/Expense",0} -> Items Revenue/Expense | C5: Items Revenue/Expense | E5: =+Introduction!C6+0 -> 40909 | F5: =+E5+E3 -> 40940 | G5: =+F5+F3 -> 40969 | H5: =+G5+G3 -> 41000 | I5: =+H5+H3 -> 41030 | J5: =+I5+I3 -> 41061 | K5: =+J5+J3 -> 41091 | L5: =+K5+K3 -> 41122 | M5: =+L5+L3 -> 41153 | ... Q5: =+P5+P3 -> 41275 | R5: Total
B6: 1 | C6: =+Introduction!C11 -> Income 1 | E6: =SUMIF(Ledger!$P$6:$P$2011,CONCATENATE("Income ",Actual!$B6," ",MONTH(Actual!E$5)," ",YEAR(Actual!E$5)," "),Ledger!$H$6:$H$2011) -> 0 | F6: =SUMIF(Ledger!$P$6:$P$2011,CONCATENATE("Income ",Actual!$B6," ",MONTH(Actual!F$5)," ",YEAR(Actual!F$5)," "),Ledger!$H$6:$H$2011) -> 0 | G6: =SUMIF(Ledger!$P$6:$P$2011,CONCATENATE("Income ",Actual!$B6," ",MONTH(Actual!G$5)," ",YEAR(Actual!G$5)," "),Ledger!$H$6:$H$2011) -> 0 | H6: =SUMIF(Ledger!$P$6:$P$2011,CONCATENATE("Income ",Actual!$B6," ",MONTH(Actual!H$5)," ",YEAR(Actual!H$5)," "),Ledger!$H$6:$H$2011) -> 0 | I6: =SUMIF(Ledger!$P$6:$P$2011,CONCATENATE("Income ",Actual!$B6," ",MONTH(Actual!I$5)," ",YEAR(Actual!I$5)," "),Ledger!$H$6:$H$2011) -> 0 | J6: =SUMIF(Ledger!$P$6:$P$2011,CONCATENATE("Income ",Actual!$B6," ",MONTH(Actual!J$5)," ",YEAR(Actual!J$5)," "),Ledger!$H$6:$H$2011) -> 0 | K6: =SUMIF(Ledger!$P$6:$P$2011,CONCATENATE("Income ",Actual!$B6," ",MONTH(Actual!K$5)," ",YEAR(Actual!K$5)," "),Ledger!$H$6:$H$2011) -> 0 | L6: =SUMIF(Ledger!$P$6:$P$2011,CONCATENATE("Income ",Actual!$B6," ",MONTH(Actual!L$5)," ",YEAR(Actual!L$5)," "),Ledger!$H$6:$H$2011) -> 0 | ... P6: =SUMIF(Ledger!$P$6:$P$2011,CONCATENATE("Income ",Actual!$B6," ",MONTH(Actual!P$5)," ",YEAR(Actual!P$5)," "),Ledger!$H$6:$H$2011) -> 0 | R6: =SUM(E6:P6) -> 0
B7: 2 | C7: =+Introduction!C12 -> Income 2 | E7: =SUMIF(Ledger!$P$6:$P$2011,CONCATENATE("Income ",Actual!$B7," ",MONTH(Actual!E$5)," ",YEAR(Actual!E$5)," "),Ledger!$H$6:$H$2011) -> 0 | F7: =SUMIF(Ledger!$P$6:$P$2011,CONCATENATE("Income ",Actual!$B7," ",MONTH(Actual!F$5)," ",YEAR(Actual!F$5)," "),Ledger!$H$6:$H$2011) -> 0 | G7: =SUMIF(Ledger!$P$6:$P$2011,CONCATENATE("Income ",Actual!$B7," ",MONTH(Actual!G$5)," ",YEAR(Actual!G$5)," "),Ledger!$H$6:$H$2011) -> 0 | H7: =SUMIF(Ledger!$P$6:$P$2011,CONCATENATE("Income ",Actual!$B7," ",MONTH(Actual!H$5)," ",YEAR(Actual!H$5)," "),Ledger!$H$6:$H$2011) -> 0 | I7: =SUMIF(Ledger!$P$6:$P$2011,CONCATENATE("Income ",Actual!$B7," ",MONTH(Actual!I$5)," ",YEAR(Actual!I$5)," "),Ledger!$H$6:$H$2011) -> 0 | J7: =SUMIF(Ledger!$P$6:$P$2011,CONCATENATE("Income ",Actual!$B7," ",MONTH(Actual!J$5)," ",YEAR(Actual!J$5)," "),Ledger!$H$6:$H$2011) -> 0 | K7: =SUMIF(Ledger!$P$6:$P$2011,CONCATENATE("Income ",Actual!$B7," ",MONTH(Actual!K$5)," ",YEAR(Actual!K$5)," "),Ledger!$H$6:$H$2011) -> 0 | L7: =SUMIF(Ledger!$P$6:$P$2011,CONCATENATE("Income ",Actual!$B7," ",MONTH(Actual!L$5)," ",YEAR(Actual!L$5)," "),Ledger!$H$6:$H$2011) -> 0 | ... P7: =SUMIF(Ledger!$P$6:$P$2011,CONCATENATE("Income ",Actual!$B7," ",MONTH(Actual!P$5)," ",YEAR(Actual!P$5)," "),Ledger!$H$6:$H$2011) -> 0 | R7: =SUM(E7:P7) -> 0
B8: 3 | C8: =+Introduction!C13 -> Income 3 | E8: =SUMIF(Ledger!$P$6:$P$2011,CONCATENATE("Income ",Actual!$B8," ",MONTH(Actual!E$5)," ",YEAR(Actual!E$5)," "),Ledger!$H$6:$H$2011) -> 0 | F8: =SUMIF(Ledger!$P$6:$P$2011,CONCATENATE("Income ",Actual!$B8," ",MONTH(Actual!F$5)," ",YEAR(Actual!F$5)," "),Ledger!$H$6:$H$2011) -> 0 | G8: =SUMIF(Ledger!$P$6:$P$2011,CONCATENATE("Income ",Actual!$B8," ",MONTH(Actual!G$5)," ",YEAR(Actual!G$5)," "),Ledger!$H$6:$H$2011) -> 0 | H8: =SUMIF(Ledger!$P$6:$P$2011,CONCATENATE("Income ",Actual!$B8," ",MONTH(Actual!H$5)," ",YEAR(Actual!H$5)," "),Ledger!$H$6:$H$2011) -> 0 | I8: =SUMIF(Ledger!$P$6:$P$2011,CONCATENATE("Income ",Actual!$B8," ",MONTH(Actual!I$5)," ",YEAR(Actual!I$5)," "),Ledger!$H$6:$H$2011) -> 0 | J8: =SUMIF(Ledger!$P$6:$P$2011,CONCATENATE("Income ",Actual!$B8," ",MONTH(Actual!J$5)," ",YEAR(Actual!J$5)," "),Ledger!$H$6:$H$2011) -> 0 | K8: =SUMIF(Ledger!$P$6:$P$2011,CONCATENATE("Income ",Actual!$B8," ",MONTH(Actual!K$5)," ",YEAR(Actual!K$5)," "),Ledger!$H$6:$H$2011) -> 0 | L8: =SUMIF(Ledger!$P$6:$P$2011,CONCATENATE("Income ",Actual!$B8," ",MONTH(Actual!L$5)," ",YEAR(Actual!L$5)," "),Ledger!$H$6:$H$2011) -> 0 | ... P8: =SUMIF(Ledger!$P$6:$P$2011,CONCATENATE("Income ",Actual!$B8," ",MONTH(Actual!P$5)," ",YEAR(Actual!P$5)," "),Ledger!$H$6:$H$2011) -> 0 | R8: =SUM(E8:P8) -> 0
B9: 4 | C9: =+Introduction!C14 -> Income 4 | E9: =SUMIF(Ledger!$P$6:$P$2011,CONCATENATE("Income ",Actual!$B9," ",MONTH(Actual!E$5)," ",YEAR(Actual!E$5)," "),Ledger!$H$6:$H$2011) -> 0 | F9: =SUMIF(Ledger!$P$6:$P$2011,CONCATENATE("Income ",Actual!$B9," ",MONTH(Actual!F$5)," ",YEAR(Actual!F$5)," "),Ledger!$H$6:$H$2011) -> 0 | G9: =SUMIF(Ledger!$P$6:$P$2011,CONCATENATE("Income ",Actual!$B9," ",MONTH(Actual!G$5)," ",YEAR(Actual!G$5)," "),Ledger!$H$6:$H$2011) -> 0 | H9: =SUMIF(Ledger!$P$6:$P$2011,CONCATENATE("Income ",Actual!$B9," ",MONTH(Actual!H$5)," ",YEAR(Actual!H$5)," "),Ledger!$H$6:$H$2011) -> 0 | I9: =SUMIF(Ledger!$P$6:$P$2011,CONCATENATE("Income ",Actual!$B9," ",MONTH(Actual!I$5)," ",YEAR(Actual!I$5)," "),Ledger!$H$6:$H$2011) -> 0 | J9: =SUMIF(Ledger!$P$6:$P$2011,CONCATENATE("Income ",Actual!$B9," ",MONTH(Actual!J$5)," ",YEAR(Actual!J$5)," "),Ledger!$H$6:$H$2011) -> 0 | K9: =SUMIF(Ledger!$P$6:$P$2011,CONCATENATE("Income ",Actual!$B9," ",MONTH(Actual!K$5)," ",YEAR(Actual!K$5)," "),Ledger!$H$6:$H$2011) -> 0 | L9: =SUMIF(Ledger!$P$6:$P$2011,CONCATENATE("Income ",Actual!$B9," ",MONTH(Actual!L$5)," ",YEAR(Actual!L$5)," "),Ledger!$H$6:$H$2011) -> 0 | ... P9: =SUMIF(Ledger!$P$6:$P$2011,CONCATENATE("Income ",Actual!$B9," ",MONTH(Actual!P$5)," ",YEAR(Actual!P$5)," "),Ledger!$H$6:$H$2011) -> 0 | R9: =SUM(E9:P9) -> 0
B10: 5 | C10: =+Introduction!C15 -> Income 5 | E10: =SUMIF(Ledger!$P$6:$P$2011,CONCATENATE("Income ",Actual!$B10," ",MONTH(Actual!E$5)," ",YEAR(Actual!E$5)," "),Ledger!$H$6:$H$2011) -> 0 | F10: =SUMIF(Ledger!$P$6:$P$2011,CONCATENATE("Income ",Actual!$B10," ",MONTH(Actual!F$5)," ",YEAR(Actual!F$5)," "),Ledger!$H$6:$H$2011) -> 0 | G10: =SUMIF(Ledger!$P$6:$P$2011,CONCATENATE("Income ",Actual!$B10," ",MONTH(Actual!G$5)," ",YEAR(Actual!G$5)," "),Ledger!$H$6:$H$2011) -> 0 | H10: =SUMIF(Ledger!$P$6:$P$2011,CONCATENATE("Income ",Actual!$B10," ",MONTH(Actual!H$5)," ",YEAR(Actual!H$5)," "),Ledger!$H$6:$H$2011) -> 0 | I10: =SUMIF(Ledger!$P$6:$P$2011,CONCATENATE("Income ",Actual!$B10," ",MONTH(Actual!I$5)," ",YEAR(Actual!I$5)," "),Ledger!$H$6:$H$2011) -> 0 | J10: =SUMIF(Ledger!$P$6:$P$2011,CONCATENATE("Income ",Actual!$B10," ",MONTH(Actual!J$5)," ",YEAR(Actual!J$5)," "),Ledger!$H$6:$H$2011) -> 0 | K10: =SUMIF(Ledger!$P$6:$P$2011,CONCATENATE("Income ",Actual!$B10," ",MONTH(Actual!K$5)," ",YEAR(Actual!K$5)," "),Ledger!$H$6:$H$2011) -> 0 | L10: =SUMIF(Ledger!$P$6:$P$2011,CONCATENATE("Income ",Actual!$B10," ",MONTH(Actual!L$5)," ",YEAR(Actual!L$5)," "),Ledger!$H$6:$H$2011) -> 0 | ... P10: =SUMIF(Ledger!$P$6:$P$2011,CONCATENATE("Income ",Actual!$B10," ",MONTH(Actual!P$5)," ",YEAR(Actual!P$5)," "),Ledger!$H$6:$H$2011) -> 0 | R10: =SUM(E10:P10) -> 0
B11: 6 | C11: =+Introduction!C16 -> Income 6 | E11: =SUMIF(Ledger!$P$6:$P$2011,CONCATENATE("Income ",Actual!$B11," ",MONTH(Actual!E$5)," ",YEAR(Actual!E$5)," "),Ledger!$H$6:$H$2011) -> 0 | F11: =SUMIF(Ledger!$P$6:$P$2011,CONCATENATE("Income ",Actual!$B11," ",MONTH(Actual!F$5)," ",YEAR(Actual!F$5)," "),Ledger!$H$6:$H$2011) -> 0 | G11: =SUMIF(Ledger!$P$6:$P$2011,CONCATENATE("Income ",Actual!$B11," ",MONTH(Actual!G$5)," ",YEAR(Actual!G$5)," "),Ledger!$H$6:$H$2011) -> 0 | H11: =SUMIF(Ledger!$P$6:$P$2011,CONCATENATE("Income ",Actual!$B11," ",MONTH(Actual!H$5)," ",YEAR(Actual!H$5)," "),Ledger!$H$6:$H$2011) -> 0 | I11: =SUMIF(Ledger!$P$6:$P$2011,CONCATENATE("Income ",Actual!$B11," ",MONTH(Actual!I$5)," ",YEAR(Actual!I$5)," "),Ledger!$H$6:$H$2011) -> 0 | J11: =SUMIF(Ledger!$P$6:$P$2011,CONCATENATE("Income ",Actual!$B11," ",MONTH(Actual!J$5)," ",YEAR(Actual!J$5)," "),Ledger!$H$6:$H$2011) -> 0 | K11: =SUMIF(Ledger!$P$6:$P$2011,CONCATENATE("Income ",Actual!$B11," ",MONTH(Actual!K$5)," ",YEAR(Actual!K$5)," "),Ledger!$H$6:$H$2011) -> 0 | L11: =SUMIF(Ledger!$P$6:$P$2011,CONCATENATE("Income ",Actual!$B11," ",MONTH(Actual!L$5)," ",YEAR(Actual!L$5)," "),Ledger!$H$6:$H$2011) -> 0 | ... P11: =SUMIF(Ledger!$P$6:$P$2011,CONCATENATE("Income ",Actual!$B11," ",MONTH(Actual!P$5)," ",YEAR(Actual!P$5)," "),Ledger!$H$6:$H$2011) -> 0 | R11: =SUM(E11:P11) -> 0
B12: 7 | C12: =+Introduction!C17 -> Income 7 | E12: =SUMIF(Ledger!$P$6:$P$2011,CONCATENATE("Income ",Actual!$B12," ",MONTH(Actual!E$5)," ",YEAR(Actual!E$5)," "),Ledger!$H$6:$H$2011) -> 0 | F12: =SUMIF(Ledger!$P$6:$P$2011,CONCATENATE("Income ",Actual!$B12," ",MONTH(Actual!F$5)," ",YEAR(Actual!F$5)," "),Ledger!$H$6:$H$2011) -> 0 | G12: =SUMIF(Ledger!$P$6:$P$2011,CONCATENATE("Income ",Actual!$B12," ",MONTH(Actual!G$5)," ",YEAR(Actual!G$5)," "),Ledger!$H$6:$H$2011) -> 0 | H12: =SUMIF(Ledger!$P$6:$P$2011,CONCATENATE("Income ",Actual!$B12," ",MONTH(Actual!H$5)," ",YEAR(Actual!H$5)," "),Ledger!$H$6:$H$2011) -> 0 | I12: =SUMIF(Ledger!$P$6:$P$2011,CONCATENATE("Income ",Actual!$B12," ",MONTH(Actual!I$5)," ",YEAR(Actual!I$5)," "),Ledger!$H$6:$H$2011) -> 0 | J12: =SUMIF(Ledger!$P$6:$P$2011,CONCATENATE("Income ",Actual!$B12," ",MONTH(Actual!J$5)," ",YEAR(Actual!J$5)," "),Ledger!$H$6:$H$2011) -> 0 | K12: =SUMIF(Ledger!$P$6:$P$2011,CONCATENATE("Income ",Actual!$B12," ",MONTH(Actual!K$5)," ",YEAR(Actual!K$5)," "),Ledger!$H$6:$H$2011) -> 0 | L12: =SUMIF(Ledger!$P$6:$P$2011,CONCATENATE("Income ",Actual!$B12," ",MONTH(Actual!L$5)," ",YEAR(Actual!L$5)," "),Ledger!$H$6:$H$2011) -> 0 | ... P12: =SUMIF(Ledger!$P$6:$P$2011,CONCATENATE("Income ",Actual!$B12," ",MONTH(Actual!P$5)," ",YEAR(Actual!P$5)," "),Ledger!$H$6:$H$2011) -> 0 | R12: =SUM(E12:P12) -> 0
B13: 8 | C13: =+Introduction!C18 -> Income 8 | E13: =SUMIF(Ledger!$P$6:$P$2011,CONCATENATE("Income ",Actual!$B13," ",MONTH(Actual!E$5)," ",YEAR(Actual!E$5)," "),Ledger!$H$6:$H$2011) -> 0 | F13: =SUMIF(Ledger!$P$6:$P$2011,CONCATENATE("Income ",Actual!$B13," ",MONTH(Actual!F$5)," ",YEAR(Actual!F$5)," "),Ledger!$H$6:$H$2011) -> 0 | G13: =SUMIF(Ledger!$P$6:$P$2011,CONCATENATE("Income ",Actual!$B13," ",MONTH(Actual!G$5)," ",YEAR(Actual!G$5)," "),Ledger!$H$6:$H$2011) -> 0 | H13: =SUMIF(Ledger!$P$6:$P$2011,CONCATENATE("Income ",Actual!$B13," ",MONTH(Actual!H$5)," ",YEAR(Actual!H$5)," "),Ledger!$H$6:$H$2011) -> 0 | I13: =SUMIF(Ledger!$P$6:$P$2011,CONCATENATE("Income ",Actual!$B13," ",MONTH(Actual!I$5)," ",YEAR(Actual!I$5)," "),Ledger!$H$6:$H$2011) -> 0 | J13: =SUMIF(Ledger!$P$6:$P$2011,CONCATENATE("Income ",Actual!$B13," ",MONTH(Actual!J$5)," ",YEAR(Actual!J$5)," "),Ledger!$H$6:$H$2011) -> 0 | K13: =SUMIF(Ledger!$P$6:$P$2011,CONCATENATE("Income ",Actual!$B13," ",MONTH(Actual!K$5)," ",YEAR(Actual!K$5)," "),Ledger!$H$6:$H$2011) -> 0 | L13: =SUMIF(Ledger!$P$6:$P$2011,CONCATENATE("Income ",Actual!$B13," ",MONTH(Actual!L$5)," ",YEAR(Actual!L$5)," "),Ledger!$H$6:$H$2011) -> 0 | ... P13: =SUMIF(Ledger!$P$6:$P$2011,CONCATENATE("Income ",Actual!$B13," ",MONTH(Actual!P$5)," ",YEAR(Actual!P$5)," "),Ledger!$H$6:$H$2011) -> 0 | R13: =SUM(E13:P13) -> 0
C14: Total Income | E14: =SUM(E6:E13) -> 0 | F14: =SUM(F6:F13) -> 0 | G14: =SUM(G6:G13) -> 0 | H14: =SUM(H6:H13) -> 0 | I14: =SUM(I6:I13) -> 0 | J14: =SUM(J6:J13) -> 0 | K14: =SUM(K6:K13) -> 0 | L14: =SUM(L6:L13) -> 0 | ... R14: =SUM(R6:R13) -> 0
R15: =IF(SUM(E15:P15)<>0,SUM(E15:P15),"")
C16: Month and Year Calc Income/Expense | E16: =CONCATENATE(MONTH(E17)," ",YEAR(E17), " Expense") -> 1 2012 Expense | F16: =CONCATENATE(MONTH(F17)," ",YEAR(F17), " Expense") -> 2 2012 Expense | G16: =CONCATENATE(MONTH(G17)," ",YEAR(G17), " Expense") -> 3 2012 Expense | H16: =CONCATENATE(MONTH(H17)," ",YEAR(H17), " Expense") -> 4 2012 Expense | I16: =CONCATENATE(MONTH(I17)," ",YEAR(I17), " Expense") -> 5 2012 Expense | J16: =CONCATENATE(MONTH(J17)," ",YEAR(J17), " Expense") -> 6 2012 Expense | K16: =CONCATENATE(MONTH(K17)," ",YEAR(K17), " Expense") -> 7 2012 Expense | L16: =CONCATENATE(MONTH(L17)," ",YEAR(L17), " Expense") -> 8 2012 Expense | ... P16: =CONCATENATE(MONTH(P17)," ",YEAR(P17), " Expense") -> 12 2012 Expense
C17: Expenses | E17: =+E5 -> 40909 | F17: =+F5 -> 40940 | G17: =+G5 -> 40969 | H17: =+H5 -> 41000 | I17: =+I5 -> 41030 | J17: =+J5 -> 41061 | K17: =+K5 -> 41091 | L17: =+L5 -> 41122 | ... P17: =+P5 -> 41244 | R17: Total
B18: 1 | C18: =+Introduction!F11 -> Expense 1 | E18: =-SUMIF(Ledger!$P$6:$P$2011,CONCATENATE("Expense ",Actual!$B18," ",MONTH(Actual!E$5)," ",YEAR(Actual!E$5)," "),Ledger!$H$6:$H$2011) -> 0 | F18: =-SUMIF(Ledger!$P$6:$P$2011,CONCATENATE("Expense ",Actual!$B18," ",MONTH(Actual!F$5)," ",YEAR(Actual!F$5)," "),Ledger!$H$6:$H$2011) -> 0 | G18: =-SUMIF(Ledger!$P$6:$P$2011,CONCATENATE("Expense ",Actual!$B18," ",MONTH(Actual!G$5)," ",YEAR(Actual!G$5)," "),Ledger!$H$6:$H$2011) -> 0 | H18: =-SUMIF(Ledger!$P$6:$P$2011,CONCATENATE("Expense ",Actual!$B18," ",MONTH(Actual!H$5)," ",YEAR(Actual!H$5)," "),Ledger!$H$6:$H$2011) -> 0 | I18: =-SUMIF(Ledger!$P$6:$P$2011,CONCATENATE("Expense ",Actual!$B18," ",MONTH(Actual!I$5)," ",YEAR(Actual!I$5)," "),Ledger!$H$6:$H$2011) -> 0 | J18: =-SUMIF(Ledger!$P$6:$P$2011,CONCATENATE("Expense ",Actual!$B18," ",MONTH(Actual!J$5)," ",YEAR(Actual!J$5)," "),Ledger!$H$6:$H$2011) -> 0 | K18: =-SUMIF(Ledger!$P$6:$P$2011,CONCATENATE("Expense ",Actual!$B18," ",MONTH(Actual!K$5)," ",YEAR(Actual!K$5)," "),Ledger!$H$6:$H$2011) -> 0 | L18: =-SUMIF(Ledger!$P$6:$P$2011,CONCATENATE("Expense ",Actual!$B18," ",MONTH(Actual!L$5)," ",YEAR(Actual!L$5)," "),Ledger!$H$6:$H$2011) -> 0 | ... P18: =-SUMIF(Ledger!$P$6:$P$2011,CONCATENATE("Expense ",Actual!$B18," ",MONTH(Actual!P$5)," ",YEAR(Actual!P$5)," "),Ledger!$H$6:$H$2011) -> 0 | R18: =SUM(E18:P18) -> 0
B19: 2 | C19: =+Introduction!F12 -> Expense 2 | E19: =-SUMIF(Ledger!$P$6:$P$2011,CONCATENATE("Expense ",Actual!$B19," ",MONTH(Actual!E$5)," ",YEAR(Actual!E$5)," "),Ledger!$H$6:$H$2011) -> 0 | F19: =-SUMIF(Ledger!$P$6:$P$2011,CONCATENATE("Expense ",Actual!$B19," ",MONTH(Actual!F$5)," ",YEAR(Actual!F$5)," "),Ledger!$H$6:$H$2011) -> 0 | G19: =-SUMIF(Ledger!$P$6:$P$2011,CONCATENATE("Expense ",Actual!$B19," ",MONTH(Actual!G$5)," ",YEAR(Actual!G$5)," "),Ledger!$H$6:$H$2011) -> 0 | H19: =-SUMIF(Ledger!$P$6:$P$2011,CONCATENATE("Expense ",Actual!$B19," ",MONTH(Actual!H$5)," ",YEAR(Actual!H$5)," "),Ledger!$H$6:$H$2011) -> 0 | I19: =-SUMIF(Ledger!$P$6:$P$2011,CONCATENATE("Expense ",Actual!$B19," ",MONTH(Actual!I$5)," ",YEAR(Actual!I$5)," "),Ledger!$H$6:$H$2011) -> 0 | J19: =-SUMIF(Ledger!$P$6:$P$2011,CONCATENATE("Expense ",Actual!$B19," ",MONTH(Actual!J$5)," ",YEAR(Actual!J$5)," "),Ledger!$H$6:$H$2011) -> 0 | K19: =-SUMIF(Ledger!$P$6:$P$2011,CONCATENATE("Expense ",Actual!$B19," ",MONTH(Actual!K$5)," ",YEAR(Actual!K$5)," "),Ledger!$H$6:$H$2011) -> 0 | L19: =-SUMIF(Ledger!$P$6:$P$2011,CONCATENATE("Expense ",Actual!$B19," ",MONTH(Actual!L$5)," ",YEAR(Actual!L$5)," "),Ledger!$H$6:$H$2011) -> 0 | ... P19: =-SUMIF(Ledger!$P$6:$P$2011,CONCATENATE("Expense ",Actual!$B19," ",MONTH(Actual!P$5)," ",YEAR(Actual!P$5)," "),Ledger!$H$6:$H$2011) -> 0 | R19: =SUM(E19:P19) -> 0
B20: 3 | C20: =+Introduction!F13 -> Expense 3 | E20: =-SUMIF(Ledger!$P$6:$P$2011,CONCATENATE("Expense ",Actual!$B20," ",MONTH(Actual!E$5)," ",YEAR(Actual!E$5)," "),Ledger!$H$6:$H$2011) -> 0 | F20: =-SUMIF(Ledger!$P$6:$P$2011,CONCATENATE("Expense ",Actual!$B20," ",MONTH(Actual!F$5)," ",YEAR(Actual!F$5)," "),Ledger!$H$6:$H$2011) -> 0 | G20: =-SUMIF(Ledger!$P$6:$P$2011,CONCATENATE("Expense ",Actual!$B20," ",MONTH(Actual!G$5)," ",YEAR(Actual!G$5)," "),Ledger!$H$6:$H$2011) -> 0 | H20: =-SUMIF(Ledger!$P$6:$P$2011,CONCATENATE("Expense ",Actual!$B20," ",MONTH(Actual!H$5)," ",YEAR(Actual!H$5)," "),Ledger!$H$6:$H$2011) -> 0 | I20: =-SUMIF(Ledger!$P$6:$P$2011,CONCATENATE("Expense ",Actual!$B20," ",MONTH(Actual!I$5)," ",YEAR(Actual!I$5)," "),Ledger!$H$6:$H$2011) -> 0 | J20: =-SUMIF(Ledger!$P$6:$P$2011,CONCATENATE("Expense ",Actual!$B20," ",MONTH(Actual!J$5)," ",YEAR(Actual!J$5)," "),Ledger!$H$6:$H$2011) -> 0 | K20: =-SUMIF(Ledger!$P$6:$P$2011,CONCATENATE("Expense ",Actual!$B20," ",MONTH(Actual!K$5)," ",YEAR(Actual!K$5)," "),Ledger!$H$6:$H$2011) -> 0 | L20: =-SUMIF(Ledger!$P$6:$P$2011,CONCATENATE("Expense ",Actual!$B20," ",MONTH(Actual!L$5)," ",YEAR(Actual!L$5)," "),Ledger!$H$6:$H$2011) -> 0 | ... P20: =-SUMIF(Ledger!$P$6:$P$2011,CONCATENATE("Expense ",Actual!$B20," ",MONTH(Actual!P$5)," ",YEAR(Actual!P$5)," "),Ledger!$H$6:$H$2011) -> 0 | R20: =SUM(E20:P20) -> 0
B21: 4 | C21: =+Introduction!F14 -> Expense 4 | E21: =-SUMIF(Ledger!$P$6:$P$2011,CONCATENATE("Expense ",Actual!$B21," ",MONTH(Actual!E$5)," ",YEAR(Actual!E$5)," "),Ledger!$H$6:$H$2011) -> 0 | F21: =-SUMIF(Ledger!$P$6:$P$2011,CONCATENATE("Expense ",Actual!$B21," ",MONTH(Actual!F$5)," ",YEAR(Actual!F$5)," "),Ledger!$H$6:$H$2011) -> 0 | G21: =-SUMIF(Ledger!$P$6:$P$2011,CONCATENATE("Expense ",Actual!$B21," ",MONTH(Actual!G$5)," ",YEAR(Actual!G$5)," "),Ledger!$H$6:$H$2011) -> 0 | H21: =-SUMIF(Ledger!$P$6:$P$2011,CONCATENATE("Expense ",Actual!$B21," ",MONTH(Actual!H$5)," ",YEAR(Actual!H$5)," "),Ledger!$H$6:$H$2011) -> 0 | I21: =-SUMIF(Ledger!$P$6:$P$2011,CONCATENATE("Expense ",Actual!$B21," ",MONTH(Actual!I$5)," ",YEAR(Actual!I$5)," "),Ledger!$H$6:$H$2011) -> 0 | J21: =-SUMIF(Ledger!$P$6:$P$2011,CONCATENATE("Expense ",Actual!$B21," ",MONTH(Actual!J$5)," ",YEAR(Actual!J$5)," "),Ledger!$H$6:$H$2011) -> 0 | K21: =-SUMIF(Ledger!$P$6:$P$2011,CONCATENATE("Expense ",Actual!$B21," ",MONTH(Actual!K$5)," ",YEAR(Actual!K$5)," "),Ledger!$H$6:$H$2011) -> 0 | L21: =-SUMIF(Ledger!$P$6:$P$2011,CONCATENATE("Expense ",Actual!$B21," ",MONTH(Actual!L$5)," ",YEAR(Actual!L$5)," "),Ledger!$H$6:$H$2011) -> 0 | ... P21: =-SUMIF(Ledger!$P$6:$P$2011,CONCATENATE("Expense ",Actual!$B21," ",MONTH(Actual!P$5)," ",YEAR(Actual!P$5)," "),Ledger!$H$6:$H$2011) -> 0 | R21: =SUM(E21:P21) -> 0
B22: 5 | C22: =+Introduction!F15 -> Expense 5 | E22: =-SUMIF(Ledger!$P$6:$P$2011,CONCATENATE("Expense ",Actual!$B22," ",MONTH(Actual!E$5)," ",YEAR(Actual!E$5)," "),Ledger!$H$6:$H$2011) -> 0 | F22: =-SUMIF(Ledger!$P$6:$P$2011,CONCATENATE("Expense ",Actual!$B22," ",MONTH(Actual!F$5)," ",YEAR(Actual!F$5)," "),Ledger!$H$6:$H$2011) -> 0 | G22: =-SUMIF(Ledger!$P$6:$P$2011,CONCATENATE("Expense ",Actual!$B22," ",MONTH(Actual!G$5)," ",YEAR(Actual!G$5)," "),Ledger!$H$6:$H$2011) -> 0 | H22: =-SUMIF(Ledger!$P$6:$P$2011,CONCATENATE("Expense ",Actual!$B22," ",MONTH(Actual!H$5)," ",YEAR(Actual!H$5)," "),Ledger!$H$6:$H$2011) -> 0 | I22: =-SUMIF(Ledger!$P$6:$P$2011,CONCATENATE("Expense ",Actual!$B22," ",MONTH(Actual!I$5)," ",YEAR(Actual!I$5)," "),Ledger!$H$6:$H$2011) -> 0 | J22: =-SUMIF(Ledger!$P$6:$P$2011,CONCATENATE("Expense ",Actual!$B22," ",MONTH(Actual!J$5)," ",YEAR(Actual!J$5)," "),Ledger!$H$6:$H$2011) -> 0 | K22: =-SUMIF(Ledger!$P$6:$P$2011,CONCATENATE("Expense ",Actual!$B22," ",MONTH(Actual!K$5)," ",YEAR(Actual!K$5)," "),Ledger!$H$6:$H$2011) -> 0 | L22: =-SUMIF(Ledger!$P$6:$P$2011,CONCATENATE("Expense ",Actual!$B22," ",MONTH(Actual!L$5)," ",YEAR(Actual!L$5)," "),Ledger!$H$6:$H$2011) -> 0 | ... P22: =-SUMIF(Ledger!$P$6:$P$2011,CONCATENATE("Expense ",Actual!$B22," ",MONTH(Actual!P$5)," ",YEAR(Actual!P$5)," "),Ledger!$H$6:$H$2011) -> 0 | R22: =SUM(E22:P22) -> 0
B23: 6 | C23: =+Introduction!F16 -> Expense 6 | E23: =-SUMIF(Ledger!$P$6:$P$2011,CONCATENATE("Expense ",Actual!$B23," ",MONTH(Actual!E$5)," ",YEAR(Actual!E$5)," "),Ledger!$H$6:$H$2011) -> 0 | F23: =-SUMIF(Ledger!$P$6:$P$2011,CONCATENATE("Expense ",Actual!$B23," ",MONTH(Actual!F$5)," ",YEAR(Actual!F$5)," "),Ledger!$H$6:$H$2011) -> 0 | G23: =-SUMIF(Ledger!$P$6:$P$2011,CONCATENATE("Expense ",Actual!$B23," ",MONTH(Actual!G$5)," ",YEAR(Actual!G$5)," "),Ledger!$H$6:$H$2011) -> 0 | H23: =-SUMIF(Ledger!$P$6:$P$2011,CONCATENATE("Expense ",Actual!$B23," ",MONTH(Actual!H$5)," ",YEAR(Actual!H$5)," "),Ledger!$H$6:$H$2011) -> 0 | I23: =-SUMIF(Ledger!$P$6:$P$2011,CONCATENATE("Expense ",Actual!$B23," ",MONTH(Actual!I$5)," ",YEAR(Actual!I$5)," "),Ledger!$H$6:$H$2011) -> 0 | J23: =-SUMIF(Ledger!$P$6:$P$2011,CONCATENATE("Expense ",Actual!$B23," ",MONTH(Actual!J$5)," ",YEAR(Actual!J$5)," "),Ledger!$H$6:$H$2011) -> 0 | K23: =-SUMIF(Ledger!$P$6:$P$2011,CONCATENATE("Expense ",Actual!$B23," ",MONTH(Actual!K$5)," ",YEAR(Actual!K$5)," "),Ledger!$H$6:$H$2011) -> 0 | L23: =-SUMIF(Ledger!$P$6:$P$2011,CONCATENATE("Expense ",Actual!$B23," ",MONTH(Actual!L$5)," ",YEAR(Actual!L$5)," "),Ledger!$H$6:$H$2011) -> 0 | ... P23: =-SUMIF(Ledger!$P$6:$P$2011,CONCATENATE("Expense ",Actual!$B23," ",MONTH(Actual!P$5)," ",YEAR(Actual!P$5)," "),Ledger!$H$6:$H$2011) -> 0 | R23: =SUM(E23:P23) -> 0
B24: 7 | C24: =+Introduction!F17 -> Expense 7 | E24: =-SUMIF(Ledger!$P$6:$P$2011,CONCATENATE("Expense ",Actual!$B24," ",MONTH(Actual!E$5)," ",YEAR(Actual!E$5)," "),Ledger!$H$6:$H$2011) -> 0 | F24: =-SUMIF(Ledger!$P$6:$P$2011,CONCATENATE("Expense ",Actual!$B24," ",MONTH(Actual!F$5)," ",YEAR(Actual!F$5)," "),Ledger!$H$6:$H$2011) -> 0 | G24: =-SUMIF(Ledger!$P$6:$P$2011,CONCATENATE("Expense ",Actual!$B24," ",MONTH(Actual!G$5)," ",YEAR(Actual!G$5)," "),Ledger!$H$6:$H$2011) -> 0 | H24: =-SUMIF(Ledger!$P$6:$P$2011,CONCATENATE("Expense ",Actual!$B24," ",MONTH(Actual!H$5)," ",YEAR(Actual!H$5)," "),Ledger!$H$6:$H$2011) -> 0 | I24: =-SUMIF(Ledger!$P$6:$P$2011,CONCATENATE("Expense ",Actual!$B24," ",MONTH(Actual!I$5)," ",YEAR(Actual!I$5)," "),Ledger!$H$6:$H$2011) -> 0 | J24: =-SUMIF(Ledger!$P$6:$P$2011,CONCATENATE("Expense ",Actual!$B24," ",MONTH(Actual!J$5)," ",YEAR(Actual!J$5)," "),Ledger!$H$6:$H$2011) -> 0 | K24: =-SUMIF(Ledger!$P$6:$P$2011,CONCATENATE("Expense ",Actual!$B24," ",MONTH(Actual!K$5)," ",YEAR(Actual!K$5)," "),Ledger!$H$6:$H$2011) -> 0 | L24: =-SUMIF(Ledger!$P$6:$P$2011,CONCATENATE("Expense ",Actual!$B24," ",MONTH(Actual!L$5)," ",YEAR(Actual!L$5)," "),Ledger!$H$6:$H$2011) -> 0 | ... P24: =-SUMIF(Ledger!$P$6:$P$2011,CONCATENATE("Expense ",Actual!$B24," ",MONTH(Actual!P$5)," ",YEAR(Actual!P$5)," "),Ledger!$H$6:$H$2011) -> 0 | R24: =SUM(E24:P24) -> 0
B25: 8 | C25: =+Introduction!F18 -> Expense 8 | E25: =-SUMIF(Ledger!$P$6:$P$2011,CONCATENATE("Expense ",Actual!$B25," ",MONTH(Actual!E$5)," ",YEAR(Actual!E$5)," "),Ledger!$H$6:$H$2011) -> 0 | F25: =-SUMIF(Ledger!$P$6:$P$2011,CONCATENATE("Expense ",Actual!$B25," ",MONTH(Actual!F$5)," ",YEAR(Actual!F$5)," "),Ledger!$H$6:$H$2011) -> 0 | G25: =-SUMIF(Ledger!$P$6:$P$2011,CONCATENATE("Expense ",Actual!$B25," ",MONTH(Actual!G$5)," ",YEAR(Actual!G$5)," "),Ledger!$H$6:$H$2011) -> 0 | H25: =-SUMIF(Ledger!$P$6:$P$2011,CONCATENATE("Expense ",Actual!$B25," ",MONTH(Actual!H$5)," ",YEAR(Actual!H$5)," "),Ledger!$H$6:$H$2011) -> 0 | I25: =-SUMIF(Ledger!$P$6:$P$2011,CONCATENATE("Expense ",Actual!$B25," ",MONTH(Actual!I$5)," ",YEAR(Actual!I$5)," "),Ledger!$H$6:$H$2011) -> 0 | J25: =-SUMIF(Ledger!$P$6:$P$2011,CONCATENATE("Expense ",Actual!$B25," ",MONTH(Actual!J$5)," ",YEAR(Actual!J$5)," "),Ledger!$H$6:$H$2011) -> 0 | K25: =-SUMIF(Ledger!$P$6:$P$2011,CONCATENATE("Expense ",Actual!$B25," ",MONTH(Actual!K$5)," ",YEAR(Actual!K$5)," "),Ledger!$H$6:$H$2011) -> 0 | L25: =-SUMIF(Ledger!$P$6:$P$2011,CONCATENATE("Expense ",Actual!$B25," ",MONTH(Actual!L$5)," ",YEAR(Actual!L$5)," "),Ledger!$H$6:$H$2011) -> 0 | ... P25: =-SUMIF(Ledger!$P$6:$P$2011,CONCATENATE("Expense ",Actual!$B25," ",MONTH(Actual!P$5)," ",YEAR(Actual!P$5)," "),Ledger!$H$6:$H$2011) -> 0 | R25: =SUM(E25:P25) -> 0
B26: 9 | C26: =+Introduction!F19 -> Expense 9 | E26: =-SUMIF(Ledger!$P$6:$P$2011,CONCATENATE("Expense ",Actual!$B26," ",MONTH(Actual!E$5)," ",YEAR(Actual!E$5)," "),Ledger!$H$6:$H$2011) -> 0 | F26: =-SUMIF(Ledger!$P$6:$P$2011,CONCATENATE("Expense ",Actual!$B26," ",MONTH(Actual!F$5)," ",YEAR(Actual!F$5)," "),Ledger!$H$6:$H$2011) -> 0 | G26: =-SUMIF(Ledger!$P$6:$P$2011,CONCATENATE("Expense ",Actual!$B26," ",MONTH(Actual!G$5)," ",YEAR(Actual!G$5)," "),Ledger!$H$6:$H$2011) -> 0 | H26: =-SUMIF(Ledger!$P$6:$P$2011,CONCATENATE("Expense ",Actual!$B26," ",MONTH(Actual!H$5)," ",YEAR(Actual!H$5)," "),Ledger!$H$6:$H$2011) -> 0 | I26: =-SUMIF(Ledger!$P$6:$P$2011,CONCATENATE("Expense ",Actual!$B26," ",MONTH(Actual!I$5)," ",YEAR(Actual!I$5)," "),Ledger!$H$6:$H$2011) -> 0 | J26: =-SUMIF(Ledger!$P$6:$P$2011,CONCATENATE("Expense ",Actual!$B26," ",MONTH(Actual!J$5)," ",YEAR(Actual!J$5)," "),Ledger!$H$6:$H$2011) -> 0 | K26: =-SUMIF(Ledger!$P$6:$P$2011,CONCATENATE("Expense ",Actual!$B26," ",MONTH(Actual!K$5)," ",YEAR(Actual!K$5)," "),Ledger!$H$6:$H$2011) -> 0 | L26: =-SUMIF(Ledger!$P$6:$P$2011,CONCATENATE("Expense ",Actual!$B26," ",MONTH(Actual!L$5)," ",YEAR(Actual!L$5)," "),Ledger!$H$6:$H$2011) -> 0 | ... P26: =-SUMIF(Ledger!$P$6:$P$2011,CONCATENATE("Expense ",Actual!$B26," ",MONTH(Actual!P$5)," ",YEAR(Actual!P$5)," "),Ledger!$H$6:$H$2011) -> 0 | R26: =SUM(E26:P26) -> 0
B27: 10 | C27: =+Introduction!F20 -> Expense 10 | E27: =-SUMIF(Ledger!$P$6:$P$2011,CONCATENATE("Expense ",Actual!$B27," ",MONTH(Actual!E$5)," ",YEAR(Actual!E$5)," "),Ledger!$H$6:$H$2011) -> 0 | F27: =-SUMIF(Ledger!$P$6:$P$2011,CONCATENATE("Expense ",Actual!$B27," ",MONTH(Actual!F$5)," ",YEAR(Actual!F$5)," "),Ledger!$H$6:$H$2011) -> 0 | G27: =-SUMIF(Ledger!$P$6:$P$2011,CONCATENATE("Expense ",Actual!$B27," ",MONTH(Actual!G$5)," ",YEAR(Actual!G$5)," "),Ledger!$H$6:$H$2011) -> 0 | H27: =-SUMIF(Ledger!$P$6:$P$2011,CONCATENATE("Expense ",Actual!$B27," ",MONTH(Actual!H$5)," ",YEAR(Actual!H$5)," "),Ledger!$H$6:$H$2011) -> 0 | I27: =-SUMIF(Ledger!$P$6:$P$2011,CONCATENATE("Expense ",Actual!$B27," ",MONTH(Actual!I$5)," ",YEAR(Actual!I$5)," "),Ledger!$H$6:$H$2011) -> 0 | J27: =-SUMIF(Ledger!$P$6:$P$2011,CONCATENATE("Expense ",Actual!$B27," ",MONTH(Actual!J$5)," ",YEAR(Actual!J$5)," "),Ledger!$H$6:$H$2011) -> 0 | K27: =-SUMIF(Ledger!$P$6:$P$2011,CONCATENATE("Expense ",Actual!$B27," ",MONTH(Actual!K$5)," ",YEAR(Actual!K$5)," "),Ledger!$H$6:$H$2011) -> 0 | L27: =-SUMIF(Ledger!$P$6:$P$2011,CONCATENATE("Expense ",Actual!$B27," ",MONTH(Actual!L$5)," ",YEAR(Actual!L$5)," "),Ledger!$H$6:$H$2011) -> 0 | ... P27: =-SUMIF(Ledger!$P$6:$P$2011,CONCATENATE("Expense ",Actual!$B27," ",MONTH(Actual!P$5)," ",YEAR(Actual!P$5)," "),Ledger!$H$6:$H$2011) -> 0 | R27: =SUM(E27:P27) -> 0
B28: 11 | C28: =+Introduction!F21 -> Expense 11 | E28: =-SUMIF(Ledger!$P$6:$P$2011,CONCATENATE("Expense ",Actual!$B28," ",MONTH(Actual!E$5)," ",YEAR(Actual!E$5)," "),Ledger!$H$6:$H$2011) -> 0 | F28: =-SUMIF(Ledger!$P$6:$P$2011,CONCATENATE("Expense ",Actual!$B28," ",MONTH(Actual!F$5)," ",YEAR(Actual!F$5)," "),Ledger!$H$6:$H$2011) -> 0 | G28: =-SUMIF(Ledger!$P$6:$P$2011,CONCATENATE("Expense ",Actual!$B28," ",MONTH(Actual!G$5)," ",YEAR(Actual!G$5)," "),Ledger!$H$6:$H$2011) -> 0 | H28: =-SUMIF(Ledger!$P$6:$P$2011,CONCATENATE("Expense ",Actual!$B28," ",MONTH(Actual!H$5)," ",YEAR(Actual!H$5)," "),Ledger!$H$6:$H$2011) -> 0 | I28: =-SUMIF(Ledger!$P$6:$P$2011,CONCATENATE("Expense ",Actual!$B28," ",MONTH(Actual!I$5)," ",YEAR(Actual!I$5)," "),Ledger!$H$6:$H$2011) -> 0 | J28: =-SUMIF(Ledger!$P$6:$P$2011,CONCATENATE("Expense ",Actual!$B28," ",MONTH(Actual!J$5)," ",YEAR(Actual!J$5)," "),Ledger!$H$6:$H$2011) -> 0 | K28: =-SUMIF(Ledger!$P$6:$P$2011,CONCATENATE("Expense ",Actual!$B28," ",MONTH(Actual!K$5)," ",YEAR(Actual!K$5)," "),Ledger!$H$6:$H$2011) -> 0 | L28: =-SUMIF(Ledger!$P$6:$P$2011,CONCATENATE("Expense ",Actual!$B28," ",MONTH(Actual!L$5)," ",YEAR(Actual!L$5)," "),Ledger!$H$6:$H$2011) -> 0 | ... P28: =-SUMIF(Ledger!$P$6:$P$2011,CONCATENATE("Expense ",Actual!$B28," ",MONTH(Actual!P$5)," ",YEAR(Actual!P$5)," "),Ledger!$H$6:$H$2011) -> 0 | R28: =SUM(E28:P28) -> 0
B29: 12 | C29: =+Introduction!F22 -> Expense 12 | E29: =-SUMIF(Ledger!$P$6:$P$2011,CONCATENATE("Expense ",Actual!$B29," ",MONTH(Actual!E$5)," ",YEAR(Actual!E$5)," "),Ledger!$H$6:$H$2011) -> 0 | F29: =-SUMIF(Ledger!$P$6:$P$2011,CONCATENATE("Expense ",Actual!$B29," ",MONTH(Actual!F$5)," ",YEAR(Actual!F$5)," "),Ledger!$H$6:$H$2011) -> 0 | G29: =-SUMIF(Ledger!$P$6:$P$2011,CONCATENATE("Expense ",Actual!$B29," ",MONTH(Actual!G$5)," ",YEAR(Actual!G$5)," "),Ledger!$H$6:$H$2011) -> 0 | H29: =-SUMIF(Ledger!$P$6:$P$2011,CONCATENATE("Expense ",Actual!$B29," ",MONTH(Actual!H$5)," ",YEAR(Actual!H$5)," "),Ledger!$H$6:$H$2011) -> 0 | I29: =-SUMIF(Ledger!$P$6:$P$2011,CONCATENATE("Expense ",Actual!$B29," ",MONTH(Actual!I$5)," ",YEAR(Actual!I$5)," "),Ledger!$H$6:$H$2011) -> 0 | J29: =-SUMIF(Ledger!$P$6:$P$2011,CONCATENATE("Expense ",Actual!$B29," ",MONTH(Actual!J$5)," ",YEAR(Actual!J$5)," "),Ledger!$H$6:$H$2011) -> 0 | K29: =-SUMIF(Ledger!$P$6:$P$2011,CONCATENATE("Expense ",Actual!$B29," ",MONTH(Actual!K$5)," ",YEAR(Actual!K$5)," "),Ledger!$H$6:$H$2011) -> 0 | L29: =-SUMIF(Ledger!$P$6:$P$2011,CONCATENATE("Expense ",Actual!$B29," ",MONTH(Actual!L$5)," ",YEAR(Actual!L$5)," "),Ledger!$H$6:$H$2011) -> 0 | ... P29: =-SUMIF(Ledger!$P$6:$P$2011,CONCATENATE("Expense ",Actual!$B29," ",MONTH(Actual!P$5)," ",YEAR(Actual!P$5)," "),Ledger!$H$6:$H$2011) -> 0 | R29: =SUM(E29:P29) -> 0
... B37: 20 | C37: =+Introduction!F30 -> IRA Contribution | E37: =-SUMIF(Ledger!$P$6:$P$2011,CONCATENATE("Expense ",Actual!$B37," ",MONTH(Actual!E$5)," ",YEAR(Actual!E$5)," "),Ledger!$H$6:$H$2011) -> 0 | F37: =-SUMIF(Ledger!$P$6:$P$2011,CONCATENATE("Expense ",Actual!$B37," ",MONTH(Actual!F$5)," ",YEAR(Actual!F$5)," "),Ledger!$H$6:$H$2011) -> 0 | G37: =-SUMIF(Ledger!$P$6:$P$2011,CONCATENATE("Expense ",Actual!$B37," ",MONTH(Actual!G$5)," ",YEAR(Actual!G$5)," "),Ledger!$H$6:$H$2011) -> 0 | H37: =-SUMIF(Ledger!$P$6:$P$2011,CONCATENATE("Expense ",Actual!$B37," ",MONTH(Actual!H$5)," ",YEAR(Actual!H$5)," "),Ledger!$H$6:$H$2011) -> 0 | I37: =-SUMIF(Ledger!$P$6:$P$2011,CONCATENATE("Expense ",Actual!$B37," ",MONTH(Actual!I$5)," ",YEAR(Actual!I$5)," "),Ledger!$H$6:$H$2011) -> 0 | J37: =-SUMIF(Ledger!$P$6:$P$2011,CONCATENATE("Expense ",Actual!$B37," ",MONTH(Actual!J$5)," ",YEAR(Actual!J$5)," "),Ledger!$H$6:$H$2011) -> 0 | K37: =-SUMIF(Ledger!$P$6:$P$2011,CONCATENATE("Expense ",Actual!$B37," ",MONTH(Actual!K$5)," ",YEAR(Actual!K$5)," "),Ledger!$H$6:$H$2011) -> 0 | L37: =-SUMIF(Ledger!$P$6:$P$2011,CONCATENATE("Expense ",Actual!$B37," ",MONTH(Actual!L$5)," ",YEAR(Actual!L$5)," "),Ledger!$H$6:$H$2011) -> 0 | ... P37: =-SUMIF(Ledger!$P$6:$P$2011,CONCATENATE("Expense ",Actual!$B37," ",MONTH(Actual!P$5)," ",YEAR(Actual!P$5)," "),Ledger!$H$6:$H$2011) -> 0 | R37: =SUM(E37:P37) -> 0
C38: Total Expenses | E38: =SUM(E18:E37) -> 0 | F38: =SUM(F18:F37) -> 0 | G38: =SUM(G18:G37) -> 0 | H38: =SUM(H18:H37) -> 0 | I38: =SUM(I18:I37) -> 0 | J38: =SUM(J18:J37) -> 0 | K38: =SUM(K18:K37) -> 0 | L38: =SUM(L18:L37) -> 0 | ... Q38: =SUM(Q18:Q37) -> 0 | R38: =SUM(E38:P38) -> 0
R39: =IF(SUM(E39:P39)<>0,SUM(E39:P39),"")
C40: Income Less Expenses | E40: =+E14-E38 -> 0 | F40: =+F14-F38 -> 0 | G40: =+G14-G38 -> 0 | H40: =+H14-H38 -> 0 | I40: =+I14-I38 -> 0 | J40: =+J14-J38 -> 0 | K40: =+K14-K38 -> 0 | L40: =+L14-L38 -> 0 | ... P40: =+P14-P38 -> 0 | R40: =+R14-R38 -> 0
R41: =IF(SUM(E41:P41)<>0,SUM(E41:P41),"")
B42: 1 | C42: Beginning Cash Balance | E42: =+Ledger!K5 -> 0 | F42: =+E44 -> 0 | G42: =+F44 -> 0 | H42: =+G44 -> 0 | I42: =+H44 -> 0 | J42: =+I44 -> 0 | K42: =+J44 -> 0 | L42: =+K44 -> 0 | M42: =+L44 -> 0 | ... P42: =+O44 -> 0 | R42: =+E42 -> 0
B43: 2 | C43: Income Less Expense | E43: =+E40 -> 0 | F43: =+F40 -> 0 | G43: =+G40 -> 0 | H43: =+H40 -> 0 | I43: =+I40 -> 0 | J43: =+J40 -> 0 | K43: =+K40 -> 0 | L43: =+L40 -> 0 | ... P43: =+P40 -> 0 | R43: =SUM(E43:P43) -> 0
B44: 3 | C44: Ending Cash Balance | E44: =+E42+E43 -> 0 | F44: =+F42+F43 -> 0 | G44: =+G42+G43 -> 0 | H44: =+H42+H43 -> 0 | I44: =+I42+I43 -> 0 | J44: =+J42+J43 -> 0 | K44: =+K42+K43 -> 0 | L44: =+L42+L43 -> 0 | ... P44: =+P42+P43 -> 0 | R44: =+R42+R43 -> 0
B46: 1 | C46: Roth IRA Cumulative Contribution | E46: =+Introduction!F31+Actual!E37 -> 0 | F46: =+E46+F37 -> 0 | G46: =+F46+G37 -> 0 | H46: =+G46+H37 -> 0 | I46: =+H46+I37 -> 0 | J46: =+I46+J37 -> 0 | K46: =+J46+K37 -> 0 | L46: =+K46+L37 -> 0 | M46: =+L46+M37 -> 0 | ... P46: =+O46+P37 -> 0 | R46: =+P46 -> 0
R48: =IF(SUM(E48:P48)<>0,SUM(E48:P48),"")
R49: =IF(SUM(E49:P49)<>0,SUM(E49:P49),"")
R50: =IF(SUM(E50:P50)<>0,SUM(E50:P50),"")
R51: =IF(SUM(E51:P51)<>0,SUM(E51:P51),"")
R52: =IF(SUM(E52:P52)<>0,SUM(E52:P52),"")
R53: =IF(SUM(E53:P53)<>0,SUM(E53:P53),"")
R54: =IF(SUM(E54:P54)<>0,SUM(E54:P54),"")
R55: =IF(SUM(E55:P55)<>0,SUM(E55:P55),"")
R56: =IF(SUM(E56:P56)<>0,SUM(E56:P56),"")
R57: =IF(SUM(E57:P57)<>0,SUM(E57:P57),"")
R58: =IF(SUM(E58:P58)<>0,SUM(E58:P58),"")
R59: =IF(SUM(E59:P59)<>0,SUM(E59:P59),"")
... R82: =IF(SUM(E82:P82)<>0,SUM(E82:P82),"")

Sheet Budget Actual Comparision
B2: =CONCATENATE(Introduction!C4:C4,"'s"," Budget To Actual Performance for ", Introduction!C8," ",Introduction!C5) -> 's Budget To Actual Performance for Jan 2012
C3: Days on Month Calc | D3: 31 | E3: =IF(MOD(Introduction!C7,4)=0,29,28) -> 28 | F3: 31 | G3: 30 | H3: 31 | I3: 30 | J3: 31 | K3: 30 | L3: 30 | M3: 31 | N3: 30
C4: Month and Year Calc Income/Expense | D4: =CONCATENATE(MONTH(D5)," ",YEAR(D5), " Income") -> #VALUE! | E4: =CONCATENATE(MONTH(E5)," ",YEAR(E5), " Income") -> #VALUE! | F4: =CONCATENATE(MONTH(F5)," ",YEAR(F5), " Income") -> #VALUE! | G4: =CONCATENATE(MONTH(G5)," ",YEAR(G5), " Income") -> 1 1900 Income | H4: =CONCATENATE(MONTH(H5)," ",YEAR(H5), " Income") -> #VALUE! | I4: =CONCATENATE(MONTH(I5)," ",YEAR(I5), " Income") -> #VALUE! | J4: =CONCATENATE(MONTH(J5)," ",YEAR(J5), " Income") -> #VALUE! | K4: =CONCATENATE(MONTH(K5)," ",YEAR(K5), " Income") -> 1 1900 Income | ... N4: =CONCATENATE(MONTH(N5)," ",YEAR(N5), " Income") -> #VALUE!
B5: ={"Items Revenue/Expense",0} -> Items Revenue/Expense | C5: Items Revenue/Expense | D5: Month Act | E5: Month Bud | F5: Month Var | H5: QRT Act | I5: QRT Bud | J5: QRT Var | L5: YTD Act | M5: YTD Budget | N5: YTD Var
B6: 1 | C6: =+Introduction!C11 -> Income 1 | D6: =INDEX(Actual!$E6:$P6,Introduction!$G$4) -> 0 | E6: =INDEX(Budget!$E6:$P6,Introduction!$G$4) -> 0 | F6: =+D6-E6 -> 0 | H6: =INDEX('Actual QTD'!$E6:$P6,Introduction!$G$4) -> 0 | I6: =INDEX('Budget QTD'!$E6:$P6,Introduction!$G$4) -> 0 | J6: =+H6-I6 -> 0 | L6: =INDEX('Actual YTD'!$E6:$P6,Introduction!$G$4) -> 0 | M6: =INDEX('Budget YTD'!$E6:$P6,Introduction!$G$4) -> 0 | N6: =+L6-M6 -> 0
B7: 2 | C7: =+Introduction!C12 -> Income 2 | D7: =INDEX(Actual!$E7:$P7,Introduction!$G$4) -> 0 | E7: =INDEX(Budget!$E7:$P7,Introduction!$G$4) -> 0 | F7: =+D7-E7 -> 0 | H7: =INDEX('Actual QTD'!$E7:$P7,Introduction!$G$4) -> 0 | I7: =INDEX('Budget QTD'!$E7:$P7,Introduction!$G$4) -> 0 | J7: =+H7-I7 -> 0 | L7: =INDEX('Actual YTD'!$E7:$P7,Introduction!$G$4) -> 0 | M7: =INDEX('Budget YTD'!$E7:$P7,Introduction!$G$4) -> 0 | N7: =+L7-M7 -> 0
B8: 3 | C8: =+Introduction!C13 -> Income 3 | D8: =INDEX(Actual!$E8:$P8,Introduction!$G$4) -> 0 | E8: =INDEX(Budget!$E8:$P8,Introduction!$G$4) -> 0 | F8: =+D8-E8 -> 0 | H8: =INDEX('Actual QTD'!$E8:$P8,Introduction!$G$4) -> 0 | I8: =INDEX('Budget QTD'!$E8:$P8,Introduction!$G$4) -> 0 | J8: =+H8-I8 -> 0 | L8: =INDEX('Actual YTD'!$E8:$P8,Introduction!$G$4) -> 0 | M8: =INDEX('Budget YTD'!$E8:$P8,Introduction!$G$4) -> 0 | N8: =+L8-M8 -> 0
B9: 4 | C9: =+Introduction!C14 -> Income 4 | D9: =INDEX(Actual!$E9:$P9,Introduction!$G$4) -> 0 | E9: =INDEX(Budget!$E9:$P9,Introduction!$G$4) -> 0 | F9: =+D9-E9 -> 0 | H9: =INDEX('Actual QTD'!$E9:$P9,Introduction!$G$4) -> 0 | I9: =INDEX('Budget QTD'!$E9:$P9,Introduction!$G$4) -> 0 | J9: =+H9-I9 -> 0 | L9: =INDEX('Actual YTD'!$E9:$P9,Introduction!$G$4) -> 0 | M9: =INDEX('Budget YTD'!$E9:$P9,Introduction!$G$4) -> 0 | N9: =+L9-M9 -> 0
B10: 5 | C10: =+Introduction!C15 -> Income 5 | D10: =INDEX(Actual!$E10:$P10,Introduction!$G$4) -> 0 | E10: =INDEX(Budget!$E10:$P10,Introduction!$G$4) -> 0 | F10: =+D10-E10 -> 0 | H10: =INDEX('Actual QTD'!$E10:$P10,Introduction!$G$4) -> 0 | I10: =INDEX('Budget QTD'!$E10:$P10,Introduction!$G$4) -> 0 | J10: =+H10-I10 -> 0 | L10: =INDEX('Actual YTD'!$E10:$P10,Introduction!$G$4) -> 0 | M10: =INDEX('Budget YTD'!$E10:$P10,Introduction!$G$4) -> 0 | N10: =+L10-M10 -> 0
B11: 6 | C11: =+Introduction!C16 -> Income 6 | D11: =INDEX(Actual!$E11:$P11,Introduction!$G$4) -> 0 | E11: =INDEX(Budget!$E11:$P11,Introduction!$G$4) -> 0 | F11: =+D11-E11 -> 0 | H11: =INDEX('Actual QTD'!$E11:$P11,Introduction!$G$4) -> 0 | I11: =INDEX('Budget QTD'!$E11:$P11,Introduction!$G$4) -> 0 | J11: =+H11-I11 -> 0 | L11: =INDEX('Actual YTD'!$E11:$P11,Introduction!$G$4) -> 0 | M11: =INDEX('Budget YTD'!$E11:$P11,Introduction!$G$4) -> 0 | N11: =+L11-M11 -> 0
B12: 7 | C12: =+Introduction!C17 -> Income 7 | D12: =INDEX(Actual!$E12:$P12,Introduction!$G$4) -> 0 | E12: =INDEX(Budget!$E12:$P12,Introduction!$G$4) -> 0 | F12: =+D12-E12 -> 0 | H12: =INDEX('Actual QTD'!$E12:$P12,Introduction!$G$4) -> 0 | I12: =INDEX('Budget QTD'!$E12:$P12,Introduction!$G$4) -> 0 | J12: =+H12-I12 -> 0 | L12: =INDEX('Actual YTD'!$E12:$P12,Introduction!$G$4) -> 0 | M12: =INDEX('Budget YTD'!$E12:$P12,Introduction!$G$4) -> 0 | N12: C
B13: 8 | C13: =+Introduction!C18 -> Income 8 | D13: =INDEX(Actual!$E13:$P13,Introduction!$G$4) -> 0 | E13: =INDEX(Budget!$E13:$P13,Introduction!$G$4) -> 0 | F13: =+D13-E13 -> 0 | H13: =INDEX('Actual QTD'!$E13:$P13,Introduction!$G$4) -> 0 | I13: =INDEX('Budget QTD'!$E13:$P13,Introduction!$G$4) -> 0 | J13: =+H13-I13 -> 0 | L13: =INDEX('Actual YTD'!$E13:$P13,Introduction!$G$4) -> 0 | M13: =INDEX('Budget YTD'!$E13:$P13,Introduction!$G$4) -> 0 | N13: =+L13-M13 -> 0
C14: Total Income | D14: =SUM(D6:D13) -> 0 | E14: =SUM(E6:E13) -> 0 | F14: =SUM(F6:F13) -> 0 | H14: =SUM(H6:H13) -> 0 | I14: =INDEX('Budget QTD'!$E14:$P14,Introduction!$G$4) -> 0 | J14: =SUM(J6:J13) -> 0 | L14: =SUM(L6:L13) -> 0 | M14: =SUM(M6:M13) -> 0 | N14: =SUM(N6:N13) -> 0
C16: Month and Year Calc Income/Expense | D16: =CONCATENATE(MONTH(D17)," ",YEAR(D17), " Expense") -> #VALUE! | E16: =CONCATENATE(MONTH(E17)," ",YEAR(E17), " Expense") -> #VALUE! | F16: =CONCATENATE(MONTH(F17)," ",YEAR(F17), " Expense") -> #VALUE! | H16: =CONCATENATE(MONTH(H17)," ",YEAR(H17), " Expense") -> #VALUE! | I16: =CONCATENATE(MONTH(I17)," ",YEAR(I17), " Expense") -> #VALUE! | J16: =CONCATENATE(MONTH(J17)," ",YEAR(J17), " Expense") -> #VALUE! | L16: =CONCATENATE(MONTH(L17)," ",YEAR(L17), " Expense") -> #VALUE! | M16: =CONCATENATE(MONTH(M17)," ",YEAR(M17), " Expense") -> #VALUE! | N16: =CONCATENATE(MONTH(N17)," ",YEAR(N17), " Expense") -> #VALUE!
C17: Expenses | D17: =+D5 -> Month Act | E17: =+E5 -> Month Bud | F17: =+F5 -> Month Var | H17: =+H5 -> QRT Act | I17: =+I5 -> QRT Bud | J17: =+J5 -> QRT Var | L17: =+L5 -> YTD Act | M17: =+M5 -> YTD Budget | N17: =+N5 -> YTD Var
B18: 1 | C18: =+Introduction!F11 -> Expense 1 | D18: =INDEX(Actual!$E$18:$P$37,Actual!B18,Introduction!$G$4) -> 0 | E18: =INDEX(Budget!$E$18:$P$37,Actual!B18,Introduction!$G$4) -> 0 | F18: =+E18-D18 -> 0 | H18: =INDEX('Actual QTD'!$E$18:$P$37,Actual!B18,Introduction!$G$4) -> 0 | I18: =INDEX('Budget QTD'!$E$18:$P$37,Actual!B18,Introduction!$G$4) -> 0 | J18: =+I18-H18 -> 0 | L18: =INDEX('Actual YTD'!$E$18:$P$37,Actual!B18,Introduction!$G$4) -> 0 | M18: =INDEX('Budget YTD'!$E$18:$P$37,Actual!B18,Introduction!$G$4) -> 0 | N18: =+M18-L18 -> 0
B19: 2 | C19: =+Introduction!F12 -> Expense 2 | D19: =INDEX(Actual!$E$18:$P$37,Actual!B19,Introduction!$G$4) -> 0 | E19: =INDEX(Budget!$E$18:$P$37,Actual!B19,Introduction!$G$4) -> 0 | F19: =+E19-D19 -> 0 | H19: =INDEX('Actual QTD'!$E$18:$P$37,Actual!B19,Introduction!$G$4) -> 0 | I19: =INDEX('Budget QTD'!$E$18:$P$37,Actual!B19,Introduction!$G$4) -> 0 | J19: =+I19-H19 -> 0 | L19: =INDEX('Actual YTD'!$E$18:$P$37,Actual!B19,Introduction!$G$4) -> 0 | M19: =INDEX('Budget YTD'!$E$18:$P$37,Actual!B19,Introduction!$G$4) -> 0 | N19: =+M19-L19 -> 0
B20: 3 | C20: =+Introduction!F13 -> Expense 3 | D20: =INDEX(Actual!$E$18:$P$37,Actual!B20,Introduction!$G$4) -> 0 | E20: =INDEX(Budget!$E$18:$P$37,Actual!B20,Introduction!$G$4) -> 0 | F20: =+E20-D20 -> 0 | H20: =INDEX('Actual QTD'!$E$18:$P$37,Actual!B20,Introduction!$G$4) -> 0 | I20: =INDEX('Budget QTD'!$E$18:$P$37,Actual!B20,Introduction!$G$4) -> 0 | J20: =+I20-H20 -> 0 | L20: =INDEX('Actual YTD'!$E$18:$P$37,Actual!B20,Introduction!$G$4) -> 0 | M20: =INDEX('Budget YTD'!$E$18:$P$37,Actual!B20,Introduction!$G$4) -> 0 | N20: =+M20-L20 -> 0
B21: 4 | C21: =+Introduction!F14 -> Expense 4 | D21: =INDEX(Actual!$E$18:$P$37,Actual!B21,Introduction!$G$4) -> 0 | E21: =INDEX(Budget!$E$18:$P$37,Actual!B21,Introduction!$G$4) -> 0 | F21: =+E21-D21 -> 0 | H21: =INDEX('Actual QTD'!$E$18:$P$37,Actual!B21,Introduction!$G$4) -> 0 | I21: =INDEX('Budget QTD'!$E$18:$P$37,Actual!B21,Introduction!$G$4) -> 0 | J21: =+I21-H21 -> 0 | L21: =INDEX('Actual YTD'!$E$18:$P$37,Actual!B21,Introduction!$G$4) -> 0 | M21: =INDEX('Budget YTD'!$E$18:$P$37,Actual!B21,Introduction!$G$4) -> 0 | N21: =+M21-L21 -> 0
B22: 5 | C22: =+Introduction!F15 -> Expense 5 | D22: =INDEX(Actual!$E$18:$P$37,Actual!B22,Introduction!$G$4) -> 0 | E22: =INDEX(Budget!$E$18:$P$37,Actual!B22,Introduction!$G$4) -> 0 | F22: =+E22-D22 -> 0 | H22: =INDEX('Actual QTD'!$E$18:$P$37,Actual!B22,Introduction!$G$4) -> 0 | I22: =INDEX('Budget QTD'!$E$18:$P$37,Actual!B22,Introduction!$G$4) -> 0 | J22: =+I22-H22 -> 0 | L22: =INDEX('Actual YTD'!$E$18:$P$37,Actual!B22,Introduction!$G$4) -> 0 | M22: =INDEX('Budget YTD'!$E$18:$P$37,Actual!B22,Introduction!$G$4) -> 0 | N22: =+M22-L22 -> 0
B23: 6 | C23: =+Introduction!F16 -> Expense 6 | D23: =INDEX(Actual!$E$18:$P$37,Actual!B23,Introduction!$G$4) -> 0 | E23: =INDEX(Budget!$E$18:$P$37,Actual!B23,Introduction!$G$4) -> 0 | F23: =+E23-D23 -> 0 | H23: =INDEX('Actual QTD'!$E$18:$P$37,Actual!B23,Introduction!$G$4) -> 0 | I23: =INDEX('Budget QTD'!$E$18:$P$37,Actual!B23,Introduction!$G$4) -> 0 | J23: =+I23-H23 -> 0 | L23: =INDEX('Actual YTD'!$E$18:$P$37,Actual!B23,Introduction!$G$4) -> 0 | M23: =INDEX('Budget YTD'!$E$18:$P$37,Actual!B23,Introduction!$G$4) -> 0 | N23: =+M23-L23 -> 0
B24: 7 | C24: =+Introduction!F17 -> Expense 7 | D24: =INDEX(Actual!$E$18:$P$37,Actual!B24,Introduction!$G$4) -> 0 | E24: =INDEX(Budget!$E$18:$P$37,Actual!B24,Introduction!$G$4) -> 0 | F24: =+E24-D24 -> 0 | H24: =INDEX('Actual QTD'!$E$18:$P$37,Actual!B24,Introduction!$G$4) -> 0 | I24: =INDEX('Budget QTD'!$E$18:$P$37,Actual!B24,Introduction!$G$4) -> 0 | J24: =+I24-H24 -> 0 | L24: =INDEX('Actual YTD'!$E$18:$P$37,Actual!B24,Introduction!$G$4) -> 0 | M24: =INDEX('Budget YTD'!$E$18:$P$37,Actual!B24,Introduction!$G$4) -> 0 | N24: =+M24-L24 -> 0
B25: 8 | C25: =+Introduction!F18 -> Expense 8 | D25: =INDEX(Actual!$E$18:$P$37,Actual!B25,Introduction!$G$4) -> 0 | E25: =INDEX(Budget!$E$18:$P$37,Actual!B25,Introduction!$G$4) -> 0 | F25: =+E25-D25 -> 0 | H25: =INDEX('Actual QTD'!$E$18:$P$37,Actual!B25,Introduction!$G$4) -> 0 | I25: =INDEX('Budget QTD'!$E$18:$P$37,Actual!B25,Introduction!$G$4) -> 0 | J25: =+I25-H25 -> 0 | L25: =INDEX('Actual YTD'!$E$18:$P$37,Actual!B25,Introduction!$G$4) -> 0 | M25: =INDEX('Budget YTD'!$E$18:$P$37,Actual!B25,Introduction!$G$4) -> 0 | N25: =+M25-L25 -> 0
B26: 9 | C26: =+Introduction!F19 -> Expense 9 | D26: =INDEX(Actual!$E$18:$P$37,Actual!B26,Introduction!$G$4) -> 0 | E26: =INDEX(Budget!$E$18:$P$37,Actual!B26,Introduction!$G$4) -> 0 | F26: =+E26-D26 -> 0 | H26: =INDEX('Actual QTD'!$E$18:$P$37,Actual!B26,Introduction!$G$4) -> 0 | I26: =INDEX('Budget QTD'!$E$18:$P$37,Actual!B26,Introduction!$G$4) -> 0 | J26: =+I26-H26 -> 0 | L26: =INDEX('Actual YTD'!$E$18:$P$37,Actual!B26,Introduction!$G$4) -> 0 | M26: =INDEX('Budget YTD'!$E$18:$P$37,Actual!B26,Introduction!$G$4) -> 0 | N26: =+M26-L26 -> 0
B27: 10 | C27: =+Introduction!F20 -> Expense 10 | D27: =INDEX(Actual!$E$18:$P$37,Actual!B27,Introduction!$G$4) -> 0 | E27: =INDEX(Budget!$E$18:$P$37,Actual!B27,Introduction!$G$4) -> 0 | F27: =+E27-D27 -> 0 | H27: =INDEX('Actual QTD'!$E$18:$P$37,Actual!B27,Introduction!$G$4) -> 0 | I27: =INDEX('Budget QTD'!$E$18:$P$37,Actual!B27,Introduction!$G$4) -> 0 | J27: =+I27-H27 -> 0 | L27: =INDEX('Actual YTD'!$E$18:$P$37,Actual!B27,Introduction!$G$4) -> 0 | M27: =INDEX('Budget YTD'!$E$18:$P$37,Actual!B27,Introduction!$G$4) -> 0 | N27: =+M27-L27 -> 0
B28: 11 | C28: =+Introduction!F21 -> Expense 11 | D28: =INDEX(Actual!$E$18:$P$37,Actual!B28,Introduction!$G$4) -> 0 | E28: =INDEX(Budget!$E$18:$P$37,Actual!B28,Introduction!$G$4) -> 0 | F28: =+E28-D28 -> 0 | H28: =INDEX('Actual QTD'!$E$18:$P$37,Actual!B28,Introduction!$G$4) -> 0 | I28: =INDEX('Budget QTD'!$E$18:$P$37,Actual!B28,Introduction!$G$4) -> 0 | J28: =+I28-H28 -> 0 | L28: =INDEX('Actual YTD'!$E$18:$P$37,Actual!B28,Introduction!$G$4) -> 0 | M28: =INDEX('Budget YTD'!$E$18:$P$37,Actual!B28,Introduction!$G$4) -> 0 | N28: =+M28-L28 -> 0
B29: 12 | C29: =+Introduction!F22 -> Expense 12 | D29: =INDEX(Actual!$E$18:$P$37,Actual!B29,Introduction!$G$4) -> 0 | E29: =INDEX(Budget!$E$18:$P$37,Actual!B29,Introduction!$G$4) -> 0 | F29: =+E29-D29 -> 0 | H29: =INDEX('Actual QTD'!$E$18:$P$37,Actual!B29,Introduction!$G$4) -> 0 | I29: =INDEX('Budget QTD'!$E$18:$P$37,Actual!B29,Introduction!$G$4) -> 0 | J29: =+I29-H29 -> 0 | L29: =INDEX('Actual YTD'!$E$18:$P$37,Actual!B29,Introduction!$G$4) -> 0 | M29: =INDEX('Budget YTD'!$E$18:$P$37,Actual!B29,Introduction!$G$4) -> 0 | N29: =+M29-L29 -> 0
... B37: 20 | C37: =+Introduction!F30 -> IRA Contribution | D37: =INDEX(Actual!$E$18:$P$37,Actual!B37,Introduction!$G$4) -> 0 | E37: =INDEX(Budget!$E$18:$P$37,Actual!B37,Introduction!$G$4) -> 0 | F37: =+E37-D37 -> 0 | H37: =INDEX('Actual QTD'!$E$18:$P$37,Actual!B37,Introduction!$G$4) -> 0 | I37: =INDEX('Budget QTD'!$E$18:$P$37,Actual!B37,Introduction!$G$4) -> 0 | J37: =+I37-H37 -> 0 | L37: =INDEX('Actual YTD'!$E$18:$P$37,Actual!B37,Introduction!$G$4) -> 0 | M37: =INDEX('Budget YTD'!$E$18:$P$37,Actual!B37,Introduction!$G$4) -> 0 | N37: =+M37-L37 -> 0
C38: Total Expenses | D38: =SUM(D18:D37) -> 0 | E38: =SUM(E18:E37) -> 0 | F38: =SUM(F18:F37) -> 0 | H38: =SUM(H18:H37) -> 0 | I38: =SUM(I18:I37) -> 0 | J38: =SUM(J18:J37) -> 0 | L38: =SUM(L18:L37) -> 0 | M38: =SUM(M18:M37) -> 0 | N38: =SUM(N18:N37) -> 0
C40: Income Less Expenses | D40: =+D14-D38 -> 0 | E40: =+E14-E38 -> 0 | F40: =+D40-E40 -> 0 | H40: =+H14-H38 -> 0 | I40: =+I14-I38 -> 0 | J40: =+H40-I40 -> 0 | L40: =+L14-L38 -> 0 | M40: =+M14-M38 -> 0 | N40: =+L40-M40 -> 0
B42: 1 | C42: Beginning Cash Balance | D42: =INDEX(Actual!$E$42:$P$42,Actual!$B42,Introduction!$G$4) -> 0 | E42: =INDEX(Budget!$E$42:$P$42,Actual!$B42,Introduction!$G$4) -> 0 | F42: =+D42-E42 -> 0 | H42: =INDEX('Actual QTD'!$E$42:$P$42,'Actual QTD'!$B42,Introduction!$G$4) -> 0 | I42: =INDEX('Budget QTD'!$E$42:$P$42,'Actual QTD'!$B42,Introduction!$G$4) -> 0 | J42: =+H42-I42 -> 0 | L42: =INDEX('Actual YTD'!$E$42:$P$42,Actual!$B42,Introduction!$G$4) -> 0 | M42: =INDEX('Budget YTD'!$E$42:$P$42,'Actual QTD'!$B42,Introduction!$G$4) -> 0 | N42: =+L42-M42 -> 0
B43: 2 | C43: Income Less Expense | D43: =+D40 -> 0 | E43: =+E40 -> 0 | F43: =+F40 -> 0 | H43: =+H40 -> 0 | I43: =+I40 -> 0 | J43: =+J40 -> 0 | L43: =+L40 -> 0 | M43: =+M40 -> 0 | N43: =+N40 -> 0
B44: 3 | C44: Ending Cash Balance | D44: =+D42+D43 -> 0 | E44: =+E42+E43 -> 0 | F44: =+F42+F43 -> 0 | H44: =+H42+H43 -> 0 | I44: =+I42+I43 -> 0 | J44: =+J42+J43 -> 0 | L44: =+L42+L43 -> 0 | M44: =+M42+M43 -> 0 | N44: =+N42+N43 -> 0
B46: 1 | C46: Roth IRA Cumulative Contribution | D46: =INDEX(Actual!$E$46:$P$46,'Budget Actual Comparision'!$B46,Introduction!$G$4) -> 0 | E46: =INDEX(Budget!$E$46:$P$46,'Budget Actual Comparision'!$B46,Introduction!$G$4) -> 0 | F46: =+E46-D46 -> 0 | H46: =INDEX('Actual QTD'!$E$46:$P$46,'Budget Actual Comparision'!$B46,Introduction!$G$4) -> 0 | I46: =INDEX('Budget QTD'!$E$46:$P$46,'Budget Actual Comparision'!$B46,Introduction!$G$4) -> 0 | J46: =+I46-H46 -> 0 | L46: =INDEX('Actual YTD'!$E$46:$P$46,'Budget Actual Comparision'!$B46,Introduction!$G$4) -> 0 | M46: =INDEX('Budget YTD'!$E$46:$P$46,'Budget Actual Comparision'!$B46,Introduction!$G$4) -> 0 | N46: =+M46-L46 -> 0

Sheet Budget QTD
B2: =CONCATENATE(Introduction!C4:C4,"'s"," Personal Budget ",Introduction!C5," Quarter to Date by Month") -> 's Personal Budget 2012 Quarter to Date by Month
B3: Days on Month Calc | E3: 31 | F3: =IF(MOD(Introduction!C5,4)=0,29,28) -> 29 | G3: 31 | H3: 30 | I3: 31 | J3: 30 | K3: 31 | L3: 31 | M3: 30 | N3: 31 | O3: 30 | P3: 31
B4: Month and Year Calc | E4: =CONCATENATE(MONTH(E5)," ",YEAR(E5)) -> 1 2012 | F4: =CONCATENATE(MONTH(F5)," ",YEAR(F5)) -> 2 2012 | G4: =CONCATENATE(MONTH(G5)," ",YEAR(G5)) -> 3 2012 | H4: =CONCATENATE(MONTH(H5)," ",YEAR(H5)) -> 4 2012 | I4: =CONCATENATE(MONTH(I5)," ",YEAR(I5)) -> 5 2012 | J4: =CONCATENATE(MONTH(J5)," ",YEAR(J5)) -> 6 2012 | K4: =CONCATENATE(MONTH(K5)," ",YEAR(K5)) -> 7 2012 | L4: =CONCATENATE(MONTH(L5)," ",YEAR(L5)) -> 8 2012 | ... P4: =CONCATENATE(MONTH(P5)," ",YEAR(P5)) -> 12 2012
B5: Items Revenue/Expense | E5: =+Introduction!C6+0 -> 40909 | F5: =+E5+E3 -> 40940 | G5: =+F5+F3 -> 40969 | H5: =+G5+G3 -> 41000 | I5: =+H5+H3 -> 41030 | J5: =+I5+I3 -> 41061 | K5: =+J5+J3 -> 41091 | L5: =+K5+K3 -> 41122 | M5: =+L5+L3 -> 41153 | ... Q5: =+P5+P3 -> 41275 | R5: Total
B6: 1 | C6: =+Introduction!C11 -> Income 1 | E6: =Budget!E6 -> 0 | F6: =+E6+Budget!F6 -> 0 | G6: =+F6+Budget!G6 -> 0 | H6: =Budget!H6 -> 0 | I6: =+H6+Budget!I6 -> 0 | J6: =+I6+Budget!J6 -> 0 | K6: =Budget!K6 -> 0 | L6: =+K6+Budget!L6 -> 0 | M6: =+L6+Budget!M6 -> 0 | N6: =Budget!N6 -> 0 | O6: =+N6+Budget!O6 -> 0 | P6: =+O6+Budget!P6 -> 0
B7: 2 | C7: =+Introduction!C12 -> Income 2 | E7: =Budget!E7 -> 0 | F7: =+E7+Budget!F7 -> 0 | G7: =+F7+Budget!G7 -> 0 | H7: =Budget!H7 -> 0 | I7: =+H7+Budget!I7 -> 0 | J7: =+I7+Budget!J7 -> 0 | K7: =Budget!K7 -> 0 | L7: =+K7+Budget!L7 -> 0 | M7: =+L7+Budget!M7 -> 0 | N7: =Budget!N7 -> 0 | O7: =+N7+Budget!O7 -> 0 | P7: =+O7+Budget!P7 -> 0
B8: 3 | C8: =+Introduction!C13 -> Income 3 | E8: =Budget!E8 -> 0 | F8: =+E8+Budget!F8 -> 0 | G8: =+F8+Budget!G8 -> 0 | H8: =Budget!H8 -> 0 | I8: =+H8+Budget!I8 -> 0 | J8: =+I8+Budget!J8 -> 0 | K8: =Budget!K8 -> 0 | L8: =+K8+Budget!L8 -> 0 | M8: =+L8+Budget!M8 -> 0 | N8: =Budget!N8 -> 0 | O8: =+N8+Budget!O8 -> 0 | P8: =+O8+Budget!P8 -> 0
B9: 4 | C9: =+Introduction!C14 -> Income 4 | E9: =Budget!E9 -> 0 | F9: =+E9+Budget!F9 -> 0 | G9: =+F9+Budget!G9 -> 0 | H9: =Budget!H9 -> 0 | I9: =+H9+Budget!I9 -> 0 | J9: =+I9+Budget!J9 -> 0 | K9: =Budget!K9 -> 0 | L9: =+K9+Budget!L9 -> 0 | M9: =+L9+Budget!M9 -> 0 | N9: =Budget!N9 -> 0 | O9: =+N9+Budget!O9 -> 0 | P9: =+O9+Budget!P9 -> 0
B10: 5 | C10: =+Introduction!C15 -> Income 5 | E10: =Budget!E10 -> 0 | F10: =+E10+Budget!F10 -> 0 | G10: =+F10+Budget!G10 -> 0 | H10: =Budget!H10 -> 0 | I10: =+H10+Budget!I10 -> 0 | J10: =+I10+Budget!J10 -> 0 | K10: =Budget!K10 -> 0 | L10: =+K10+Budget!L10 -> 0 | M10: =+L10+Budget!M10 -> 0 | N10: =Budget!N10 -> 0 | O10: =+N10+Budget!O10 -> 0 | P10: =+O10+Budget!P10 -> 0
B11: 6 | C11: =+Introduction!C16 -> Income 6 | E11: =Budget!E11 -> 0 | F11: =+E11+Budget!F11 -> 0 | G11: =+F11+Budget!G11 -> 0 | H11: =Budget!H11 -> 0 | I11: =+H11+Budget!I11 -> 0 | J11: =+I11+Budget!J11 -> 0 | K11: =Budget!K11 -> 0 | L11: =+K11+Budget!L11 -> 0 | M11: =+L11+Budget!M11 -> 0 | N11: =Budget!N11 -> 0 | O11: =+N11+Budget!O11 -> 0 | P11: =+O11+Budget!P11 -> 0
B12: 7 | C12: =+Introduction!C17 -> Income 7 | E12: =Budget!E12 -> 0 | F12: =+E12+Budget!F12 -> 0 | G12: =+F12+Budget!G12 -> 0 | H12: =Budget!H12 -> 0 | I12: =+H12+Budget!I12 -> 0 | J12: =+I12+Budget!J12 -> 0 | K12: =Budget!K12 -> 0 | L12: =+K12+Budget!L12 -> 0 | M12: =+L12+Budget!M12 -> 0 | N12: =Budget!N12 -> 0 | O12: =+N12+Budget!O12 -> 0 | P12: =+O12+Budget!P12 -> 0
B13: 8 | C13: =+Introduction!C18 -> Income 8 | E13: =Budget!E13 -> 0 | F13: =+E13+Budget!F13 -> 0 | G13: =+F13+Budget!G13 -> 0 | H13: =Budget!H13 -> 0 | I13: =+H13+Budget!I13 -> 0 | J13: =+I13+Budget!J13 -> 0 | K13: =Budget!K13 -> 0 | L13: =+K13+Budget!L13 -> 0 | M13: =+L13+Budget!M13 -> 0 | N13: =Budget!N13 -> 0 | O13: =+N13+Budget!O13 -> 0 | P13: =+O13+Budget!P13 -> 0
C14: Total Income | E14: =SUM(E6:E13) -> 0 | F14: =SUM(F6:F13) -> 0 | G14: =SUM(G6:G13) -> 0 | H14: =SUM(H6:H13) -> 0 | I14: =SUM(I6:I13) -> 0 | J14: =SUM(J6:J13) -> 0 | K14: =SUM(K6:K13) -> 0 | L14: =SUM(L6:L13) -> 0 | ... P14: =SUM(P6:P13) -> 0
C16: Month and Year Calc Income/Expense | E16: =CONCATENATE(MONTH(E17)," ",YEAR(E17), " Expense") -> 1 2012 Expense | F16: =CONCATENATE(MONTH(F17)," ",YEAR(F17), " Expense") -> 2 2012 Expense | G16: =CONCATENATE(MONTH(G17)," ",YEAR(G17), " Expense") -> 3 2012 Expense | H16: =CONCATENATE(MONTH(H17)," ",YEAR(H17), " Expense") -> 4 2012 Expense | I16: =CONCATENATE(MONTH(I17)," ",YEAR(I17), " Expense") -> 5 2012 Expense | J16: =CONCATENATE(MONTH(J17)," ",YEAR(J17), " Expense") -> 6 2012 Expense | K16: =CONCATENATE(MONTH(K17)," ",YEAR(K17), " Expense") -> 7 2012 Expense | L16: =CONCATENATE(MONTH(L17)," ",YEAR(L17), " Expense") -> 8 2012 Expense | ... P16: =CONCATENATE(MONTH(P17)," ",YEAR(P17), " Expense") -> 12 2012 Expense
C17: Expenses | E17: =+E5 -> 40909 | F17: =+F5 -> 40940 | G17: =+G5 -> 40969 | H17: =+H5 -> 41000 | I17: =+I5 -> 41030 | J17: =+J5 -> 41061 | K17: =+K5 -> 41091 | L17: =+L5 -> 41122 | ... P17: =+P5 -> 41244 | R17: Total
B18: 1 | C18: =+Introduction!F11 -> Expense 1 | E18: =Budget!E18 -> 0 | F18: =+E18+Budget!F18 -> 0 | G18: =+F18+Budget!G18 -> 0 | H18: =Budget!H18 -> 0 | I18: =+H18+Budget!I18 -> 0 | J18: =+I18+Budget!J18 -> 0 | K18: =Budget!K18 -> 0 | L18: =+K18+Budget!L18 -> 0 | M18: =+L18+Budget!M18 -> 0 | N18: =Budget!N18 -> 0 | O18: =+N18+Budget!O18 -> 0 | P18: =+O18+Budget!P18 -> 0
B19: 2 | C19: =+Introduction!F12 -> Expense 2 | E19: =Budget!E19 -> 0 | F19: =+E19+Budget!F19 -> 0 | G19: =+F19+Budget!G19 -> 0 | H19: =Budget!H19 -> 0 | I19: =+H19+Budget!I19 -> 0 | J19: =+I19+Budget!J19 -> 0 | K19: =Budget!K19 -> 0 | L19: =+K19+Budget!L19 -> 0 | M19: =+L19+Budget!M19 -> 0 | N19: =Budget!N19 -> 0 | O19: =+N19+Budget!O19 -> 0 | P19: =+O19+Budget!P19 -> 0
B20: 3 | C20: =+Introduction!F13 -> Expense 3 | E20: =Budget!E20 -> 0 | F20: =+E20+Budget!F20 -> 0 | G20: =+F20+Budget!G20 -> 0 | H20: =Budget!H20 -> 0 | I20: =+H20+Budget!I20 -> 0 | J20: =+I20+Budget!J20 -> 0 | K20: =Budget!K20 -> 0 | L20: =+K20+Budget!L20 -> 0 | M20: =+L20+Budget!M20 -> 0 | N20: =Budget!N20 -> 0 | O20: =+N20+Budget!O20 -> 0 | P20: =+O20+Budget!P20 -> 0
B21: 4 | C21: =+Introduction!F14 -> Expense 4 | E21: =Budget!E21 -> 0 | F21: =+E21+Budget!F21 -> 0 | G21: =+F21+Budget!G21 -> 0 | H21: =Budget!H21 -> 0 | I21: =+H21+Budget!I21 -> 0 | J21: =+I21+Budget!J21 -> 0 | K21: =Budget!K21 -> 0 | L21: =+K21+Budget!L21 -> 0 | M21: =+L21+Budget!M21 -> 0 | N21: =Budget!N21 -> 0 | O21: =+N21+Budget!O21 -> 0 | P21: =+O21+Budget!P21 -> 0
B22: 5 | C22: =+Introduction!F15 -> Expense 5 | E22: =Budget!E22 -> 0 | F22: =+E22+Budget!F22 -> 0 | G22: =+F22+Budget!G22 -> 0 | H22: =Budget!H22 -> 0 | I22: =+H22+Budget!I22 -> 0 | J22: =+I22+Budget!J22 -> 0 | K22: =Budget!K22 -> 0 | L22: =+K22+Budget!L22 -> 0 | M22: =+L22+Budget!M22 -> 0 | N22: =Budget!N22 -> 0 | O22: =+N22+Budget!O22 -> 0 | P22: =+O22+Budget!P22 -> 0
B23: 6 | C23: =+Introduction!F16 -> Expense 6 | E23: =Budget!E23 -> 0 | F23: =+E23+Budget!F23 -> 0 | G23: =+F23+Budget!G23 -> 0 | H23: =Budget!H23 -> 0 | I23: =+H23+Budget!I23 -> 0 | J23: =+I23+Budget!J23 -> 0 | K23: =Budget!K23 -> 0 | L23: =+K23+Budget!L23 -> 0 | M23: =+L23+Budget!M23 -> 0 | N23: =Budget!N23 -> 0 | O23: =+N23+Budget!O23 -> 0 | P23: =+O23+Budget!P23 -> 0
B24: 7 | C24: =+Introduction!F17 -> Expense 7 | E24: =Budget!E24 -> 0 | F24: =+E24+Budget!F24 -> 0 | G24: =+F24+Budget!G24 -> 0 | H24: =Budget!H24 -> 0 | I24: =+H24+Budget!I24 -> 0 | J24: =+I24+Budget!J24 -> 0 | K24: =Budget!K24 -> 0 | L24: =+K24+Budget!L24 -> 0 | M24: =+L24+Budget!M24 -> 0 | N24: =Budget!N24 -> 0 | O24: =+N24+Budget!O24 -> 0 | P24: =+O24+Budget!P24 -> 0
B25: 8 | C25: =+Introduction!F18 -> Expense 8 | E25: =Budget!E25 -> 0 | F25: =+E25+Budget!F25 -> 0 | G25: =+F25+Budget!G25 -> 0 | H25: =Budget!H25 -> 0 | I25: =+H25+Budget!I25 -> 0 | J25: =+I25+Budget!J25 -> 0 | K25: =Budget!K25 -> 0 | L25: =+K25+Budget!L25 -> 0 | M25: =+L25+Budget!M25 -> 0 | N25: =Budget!N25 -> 0 | O25: =+N25+Budget!O25 -> 0 | P25: =+O25+Budget!P25 -> 0
B26: 9 | C26: =+Introduction!F19 -> Expense 9 | E26: =Budget!E26 -> 0 | F26: =+E26+Budget!F26 -> 0 | G26: =+F26+Budget!G26 -> 0 | H26: =Budget!H26 -> 0 | I26: =+H26+Budget!I26 -> 0 | J26: =+I26+Budget!J26 -> 0 | K26: =Budget!K26 -> 0 | L26: =+K26+Budget!L26 -> 0 | M26: =+L26+Budget!M26 -> 0 | N26: =Budget!N26 -> 0 | O26: =+N26+Budget!O26 -> 0 | P26: =+O26+Budget!P26 -> 0
B27: 10 | C27: =+Introduction!F20 -> Expense 10 | E27: =Budget!E27 -> 0 | F27: =+E27+Budget!F27 -> 0 | G27: =+F27+Budget!G27 -> 0 | H27: =Budget!H27 -> 0 | I27: =+H27+Budget!I27 -> 0 | J27: =+I27+Budget!J27 -> 0 | K27: =Budget!K27 -> 0 | L27: =+K27+Budget!L27 -> 0 | M27: =+L27+Budget!M27 -> 0 | N27: =Budget!N27 -> 0 | O27: =+N27+Budget!O27 -> 0 | P27: =+O27+Budget!P27 -> 0
B28: 11 | C28: =+Introduction!F21 -> Expense 11 | E28: =Budget!E28 -> 0 | F28: =+E28+Budget!F28 -> 0 | G28: =+F28+Budget!G28 -> 0 | H28: =Budget!H28 -> 0 | I28: =+H28+Budget!I28 -> 0 | J28: =+I28+Budget!J28 -> 0 | K28: =Budget!K28 -> 0 | L28: =+K28+Budget!L28 -> 0 | M28: =+L28+Budget!M28 -> 0 | N28: =Budget!N28 -> 0 | O28: =+N28+Budget!O28 -> 0 | P28: =+O28+Budget!P28 -> 0
B29: 12 | C29: =+Introduction!F22 -> Expense 12 | E29: =Budget!E29 -> 0 | F29: =+E29+Budget!F29 -> 0 | G29: =+F29+Budget!G29 -> 0 | H29: =Budget!H29 -> 0 | I29: =+H29+Budget!I29 -> 0 | J29: =+I29+Budget!J29 -> 0 | K29: =Budget!K29 -> 0 | L29: =+K29+Budget!L29 -> 0 | M29: =+L29+Budget!M29 -> 0 | N29: =Budget!N29 -> 0 | O29: =+N29+Budget!O29 -> 0 | P29: =+O29+Budget!P29 -> 0
... B37: 20 | C37: =+Introduction!F30 -> IRA Contribution | E37: =Budget!E37 -> 0 | F37: =+E37+Budget!F37 -> 0 | G37: =+F37+Budget!G37 -> 0 | H37: =Budget!H37 -> 0 | I37: =+H37+Budget!I37 -> 0 | J37: =+I37+Budget!J37 -> 0 | K37: =Budget!K37 -> 0 | L37: =+K37+Budget!L37 -> 0 | M37: =+L37+Budget!M37 -> 0 | N37: =Budget!N37 -> 0 | O37: =+N37+Budget!O37 -> 0 | P37: =+O37+Budget!P37 -> 0
B38: Total Expenses | E38: =SUM(E18:E37) -> 0 | F38: =SUM(F18:F37) -> 0 | G38: =SUM(G18:G37) -> 0 | H38: =SUM(H18:H37) -> 0 | I38: =SUM(I18:I37) -> 0 | J38: =SUM(J18:J37) -> 0 | K38: =SUM(K18:K37) -> 0 | L38: =SUM(L18:L37) -> 0 | ... P38: =SUM(P18:P37) -> 0
B40: Income Less Expenses | E40: =+E14-E38 -> 0 | F40: =+F14-F38 -> 0 | G40: =+G14-G38 -> 0 | H40: =+H14-H38 -> 0 | I40: =+I14-I38 -> 0 | J40: =+J14-J38 -> 0 | K40: =+K14-K38 -> 0 | L40: =+L14-L38 -> 0 | ... P40: =+P14-P38 -> 0
B42: 1 | C42: Beginning Cash Balance | E42: =+Budget!E42 -> 0 | F42: =+E42 -> 0 | G42: =+F42 -> 0 | H42: =+Budget!H42 -> 0 | I42: =+H42 -> 0 | J42: =+I42 -> 0 | K42: =+Budget!K42 -> 0 | L42: =+K42 -> 0 | M42: =+L42 -> 0 | N42: =+Budget!N42 -> 0 | O42: =+N42 -> 0 | P42: =+O42 -> 0
B43: 2 | C43: Income Less Expense | E43: =+E40 -> 0 | F43: =+F40 -> 0 | G43: =+G40 -> 0 | H43: =+H40 -> 0 | I43: =+I40 -> 0 | J43: =+J40 -> 0 | K43: =+K40 -> 0 | L43: =+L40 -> 0 | ... P43: =+P40 -> 0
B44: 3 | C44: Ending Cash Balance | E44: =+E42+E43 -> 0 | F44: =+F42+F43 -> 0 | G44: =+G42+G43 -> 0 | H44: =+H42+H43 -> 0 | I44: =+I42+I43 -> 0 | J44: =+J42+J43 -> 0 | K44: =+K42+K43 -> 0 | L44: =+L42+L43 -> 0 | ... P44: =+P42+P43 -> 0
B46: 1 | C46: Roth IRA Cumulative Contribution | E46: =+Budget!E46 -> 0 | F46: =+Budget!F46 -> 0 | G46: =+Budget!G46 -> 0 | H46: =+Budget!H46 -> 0 | I46: =+Budget!I46 -> 0 | J46: =+Budget!J46 -> 0 | K46: =+Budget!K46 -> 0 | L46: =+Budget!L46 -> 0 | ... P46: =+Budget!P46 -> 0

Sheet Actual QTD
B2: =CONCATENATE(Introduction!C4:C4,"'s"," Personal Actual ",Introduction!C5," Quarter To Date by Month") -> 's Personal Actual 2012 Quarter To Date by Month
E3: 31 | F3: =IF(MOD(Introduction!C5,4)=0,29,28) -> 29 | G3: 31 | H3: 30 | I3: 31 | J3: 30 | K3: 31 | L3: 31 | M3: 30 | N3: 31 | O3: 30 | P3: 31
B4: Month and Year Calc | E4: =CONCATENATE(MONTH(E5)," ",YEAR(E5)) -> 1 2012 | F4: =CONCATENATE(MONTH(F5)," ",YEAR(F5)) -> 2 2012 | G4: =CONCATENATE(MONTH(G5)," ",YEAR(G5)) -> 3 2012 | H4: =CONCATENATE(MONTH(H5)," ",YEAR(H5)) -> 4 2012 | I4: =CONCATENATE(MONTH(I5)," ",YEAR(I5)) -> 5 2012 | J4: =CONCATENATE(MONTH(J5)," ",YEAR(J5)) -> 6 2012 | K4: =CONCATENATE(MONTH(K5)," ",YEAR(K5)) -> 7 2012 | L4: =CONCATENATE(MONTH(L5)," ",YEAR(L5)) -> 8 2012 | ... P4: =CONCATENATE(MONTH(P5)," ",YEAR(P5)) -> 12 2012
B5: Items Revenue/Expense | E5: =+Introduction!$C$6+0 -> 40909 | F5: =+E5+E3 -> 40940 | G5: =+F5+F3 -> 40969 | H5: =+G5+G3 -> 41000 | I5: =+H5+H3 -> 41030 | J5: =+I5+I3 -> 41061 | K5: =+J5+J3 -> 41091 | L5: =+K5+K3 -> 41122 | M5: =+L5+L3 -> 41153 | ... Q5: =+P5+P3 -> 41275 | R5: Total
B6: 1 | C6: =+Introduction!C11 -> Income 1 | E6: =Actual!E6 -> 0 | F6: =+E6+Actual!F6 -> 0 | G6: =+F6+Actual!G6 -> 0 | H6: =Actual!H6 -> 0 | I6: =+H6+Actual!I6 -> 0 | J6: =+I6+Actual!J6 -> 0 | K6: =Actual!K6 -> 0 | L6: =+K6+Actual!L6 -> 0 | M6: =+L6+Actual!M6 -> 0 | N6: =Actual!N6 -> 0 | O6: =+N6+Actual!O6 -> 0 | P6: =+O6+Actual!P6 -> 0
B7: 2 | C7: =+Introduction!C12 -> Income 2 | E7: =Actual!E7 -> 0 | F7: =+E7+Actual!F7 -> 0 | G7: =+F7+Actual!G7 -> 0 | H7: =Actual!H7 -> 0 | I7: =+H7+Actual!I7 -> 0 | J7: =+I7+Actual!J7 -> 0 | K7: =Actual!K7 -> 0 | L7: =+K7+Actual!L7 -> 0 | M7: =+L7+Actual!M7 -> 0 | N7: =Actual!N7 -> 0 | O7: =+N7+Actual!O7 -> 0 | P7: =+O7+Actual!P7 -> 0
B8: 3 | C8: =+Introduction!C13 -> Income 3 | E8: =Actual!E8 -> 0 | F8: =+E8+Actual!F8 -> 0 | G8: =+F8+Actual!G8 -> 0 | H8: =Actual!H8 -> 0 | I8: =+H8+Actual!I8 -> 0 | J8: =+I8+Actual!J8 -> 0 | K8: =Actual!K8 -> 0 | L8: =+K8+Actual!L8 -> 0 | M8: =+L8+Actual!M8 -> 0 | N8: =Actual!N8 -> 0 | O8: =+N8+Actual!O8 -> 0 | P8: =+O8+Actual!P8 -> 0
B9: 4 | C9: =+Introduction!C14 -> Income 4 | E9: =Actual!E9 -> 0 | F9: =+E9+Actual!F9 -> 0 | G9: =+F9+Actual!G9 -> 0 | H9: =Actual!H9 -> 0 | I9: =+H9+Actual!I9 -> 0 | J9: =+I9+Actual!J9 -> 0 | K9: =Actual!K9 -> 0 | L9: =+K9+Actual!L9 -> 0 | M9: =+L9+Actual!M9 -> 0 | N9: =Actual!N9 -> 0 | O9: =+N9+Actual!O9 -> 0 | P9: =+O9+Actual!P9 -> 0
B10: 5 | C10: =+Introduction!C15 -> Income 5 | E10: =Actual!E10 -> 0 | F10: =+E10+Actual!F10 -> 0 | G10: =+F10+Actual!G10 -> 0 | H10: =Actual!H10 -> 0 | I10: =+H10+Actual!I10 -> 0 | J10: =+I10+Actual!J10 -> 0 | K10: =Actual!K10 -> 0 | L10: =+K10+Actual!L10 -> 0 | M10: =+L10+Actual!M10 -> 0 | N10: =Actual!N10 -> 0 | O10: =+N10+Actual!O10 -> 0 | P10: =+O10+Actual!P10 -> 0
B11: 6 | C11: =+Introduction!C16 -> Income 6 | E11: =Actual!E11 -> 0 | F11: =+E11+Actual!F11 -> 0 | G11: =+F11+Actual!G11 -> 0 | H11: =Actual!H11 -> 0 | I11: =+H11+Actual!I11 -> 0 | J11: =+I11+Actual!J11 -> 0 | K11: =Actual!K11 -> 0 | L11: =+K11+Actual!L11 -> 0 | M11: =+L11+Actual!M11 -> 0 | N11: =Actual!N11 -> 0 | O11: =+N11+Actual!O11 -> 0 | P11: =+O11+Actual!P11 -> 0
B12: 7 | C12: =+Introduction!C17 -> Income 7 | E12: =Actual!E12 -> 0 | F12: =+E12+Actual!F12 -> 0 | G12: =+F12+Actual!G12 -> 0 | H12: =Actual!H12 -> 0 | I12: =+H12+Actual!I12 -> 0 | J12: =+I12+Actual!J12 -> 0 | K12: =Actual!K12 -> 0 | L12: =+K12+Actual!L12 -> 0 | M12: =+L12+Actual!M12 -> 0 | N12: =Actual!N12 -> 0 | O12: =+N12+Actual!O12 -> 0 | P12: =+O12+Actual!P12 -> 0
B13: 8 | C13: =+Introduction!C18 -> Income 8 | E13: =Actual!E13 -> 0 | F13: =+E13+Actual!F13 -> 0 | G13: =+F13+Actual!G13 -> 0 | H13: =Actual!H13 -> 0 | I13: =+H13+Actual!I13 -> 0 | J13: =+I13+Actual!J13 -> 0 | K13: =Actual!K13 -> 0 | L13: =+K13+Actual!L13 -> 0 | M13: =+L13+Actual!M13 -> 0 | N13: =Actual!N13 -> 0 | O13: =+N13+Actual!O13 -> 0 | P13: =+O13+Actual!P13 -> 0
C14: Total Income | E14: =SUM(E6:E13) -> 0 | F14: =SUM(F6:F13) -> 0 | G14: =SUM(G6:G13) -> 0 | H14: =SUM(H6:H13) -> 0 | I14: =SUM(I6:I13) -> 0 | J14: =SUM(J6:J13) -> 0 | K14: =SUM(K6:K13) -> 0 | L14: =SUM(L6:L13) -> 0 | ... P14: =SUM(P6:P13) -> 0
C16: Month and Year Calc Income/Expense | E16: =CONCATENATE(MONTH(E17)," ",YEAR(E17), " Expense") -> 1 2012 Expense | F16: =CONCATENATE(MONTH(F17)," ",YEAR(F17), " Expense") -> 2 2012 Expense | G16: =CONCATENATE(MONTH(G17)," ",YEAR(G17), " Expense") -> 3 2012 Expense | H16: =CONCATENATE(MONTH(H17)," ",YEAR(H17), " Expense") -> 4 2012 Expense | I16: =CONCATENATE(MONTH(I17)," ",YEAR(I17), " Expense") -> 5 2012 Expense | J16: =CONCATENATE(MONTH(J17)," ",YEAR(J17), " Expense") -> 6 2012 Expense | K16: =CONCATENATE(MONTH(K17)," ",YEAR(K17), " Expense") -> 7 2012 Expense | L16: =CONCATENATE(MONTH(L17)," ",YEAR(L17), " Expense") -> 8 2012 Expense | ... P16: =CONCATENATE(MONTH(P17)," ",YEAR(P17), " Expense") -> 12 2012 Expense
C17: Expenses | E17: =+E5 -> 40909 | F17: =+F5 -> 40940 | G17: =+G5 -> 40969 | H17: =+H5 -> 41000 | I17: =+I5 -> 41030 | J17: =+J5 -> 41061 | K17: =+K5 -> 41091 | L17: =+L5 -> 41122 | ... P17: =+P5 -> 41244
B18: 1 | C18: =+Introduction!F11 -> Expense 1 | E18: =Actual!E18 -> 0 | F18: =+E18+Actual!F18 -> 0 | G18: =+F18+Actual!G18 -> 0 | H18: =Actual!H18 -> 0 | I18: =+H18+Actual!I18 -> 0 | J18: =+I18+Actual!J18 -> 0 | K18: =Actual!K18 -> 0 | L18: =+K18+Actual!L18 -> 0 | M18: =+L18+Actual!M18 -> 0 | N18: =Actual!N18 -> 0 | O18: =+N18+Actual!O18 -> 0 | P18: =+O18+Actual!P18 -> 0
B19: 2 | C19: =+Introduction!F12 -> Expense 2 | E19: =Actual!E19 -> 0 | F19: =+E19+Actual!F19 -> 0 | G19: =+F19+Actual!G19 -> 0 | H19: =Actual!H19 -> 0 | I19: =+H19+Actual!I19 -> 0 | J19: =+I19+Actual!J19 -> 0 | K19: =Actual!K19 -> 0 | L19: =+K19+Actual!L19 -> 0 | M19: =+L19+Actual!M19 -> 0 | N19: =Actual!N19 -> 0 | O19: =+N19+Actual!O19 -> 0 | P19: =+O19+Actual!P19 -> 0
B20: 3 | C20: =+Introduction!F13 -> Expense 3 | E20: =Actual!E20 -> 0 | F20: =+E20+Actual!F20 -> 0 | G20: =+F20+Actual!G20 -> 0 | H20: =Actual!H20 -> 0 | I20: =+H20+Actual!I20 -> 0 | J20: =+I20+Actual!J20 -> 0 | K20: =Actual!K20 -> 0 | L20: =+K20+Actual!L20 -> 0 | M20: =+L20+Actual!M20 -> 0 | N20: =Actual!N20 -> 0 | O20: =+N20+Actual!O20 -> 0 | P20: =+O20+Actual!P20 -> 0
B21: 4 | C21: =+Introduction!F14 -> Expense 4 | E21: =Actual!E21 -> 0 | F21: =+E21+Actual!F21 -> 0 | G21: =+F21+Actual!G21 -> 0 | H21: =Actual!H21 -> 0 | I21: =+H21+Actual!I21 -> 0 | J21: =+I21+Actual!J21 -> 0 | K21: =Actual!K21 -> 0 | L21: =+K21+Actual!L21 -> 0 | M21: =+L21+Actual!M21 -> 0 | N21: =Actual!N21 -> 0 | O21: =+N21+Actual!O21 -> 0 | P21: =+O21+Actual!P21 -> 0
B22: 5 | C22: =+Introduction!F15 -> Expense 5 | E22: =Actual!E22 -> 0 | F22: =+E22+Actual!F22 -> 0 | G22: =+F22+Actual!G22 -> 0 | H22: =Actual!H22 -> 0 | I22: =+H22+Actual!I22 -> 0 | J22: =+I22+Actual!J22 -> 0 | K22: =Actual!K22 -> 0 | L22: =+K22+Actual!L22 -> 0 | M22: =+L22+Actual!M22 -> 0 | N22: =Actual!N22 -> 0 | O22: =+N22+Actual!O22 -> 0 | P22: =+O22+Actual!P22 -> 0
B23: 6 | C23: =+Introduction!F16 -> Expense 6 | E23: =Actual!E23 -> 0 | F23: =+E23+Actual!F23 -> 0 | G23: =+F23+Actual!G23 -> 0 | H23: =Actual!H23 -> 0 | I23: =+H23+Actual!I23 -> 0 | J23: =+I23+Actual!J23 -> 0 | K23: =Actual!K23 -> 0 | L23: =+K23+Actual!L23 -> 0 | M23: =+L23+Actual!M23 -> 0 | N23: =Actual!N23 -> 0 | O23: =+N23+Actual!O23 -> 0 | P23: =+O23+Actual!P23 -> 0
B24: 7 | C24: =+Introduction!F17 -> Expense 7 | E24: =Actual!E24 -> 0 | F24: =+E24+Actual!F24 -> 0 | G24: =+F24+Actual!G24 -> 0 | H24: =Actual!H24 -> 0 | I24: =+H24+Actual!I24 -> 0 | J24: =+I24+Actual!J24 -> 0 | K24: =Actual!K24 -> 0 | L24: =+K24+Actual!L24 -> 0 | M24: =+L24+Actual!M24 -> 0 | N24: =Actual!N24 -> 0 | O24: =+N24+Actual!O24 -> 0 | P24: =+O24+Actual!P24 -> 0
B25: 8 | C25: =+Introduction!F18 -> Expense 8 | E25: =Actual!E25 -> 0 | F25: =+E25+Actual!F25 -> 0 | G25: =+F25+Actual!G25 -> 0 | H25: =Actual!H25 -> 0 | I25: =+H25+Actual!I25 -> 0 | J25: =+I25+Actual!J25 -> 0 | K25: =Actual!K25 -> 0 | L25: =+K25+Actual!L25 -> 0 | M25: =+L25+Actual!M25 -> 0 | N25: =Actual!N25 -> 0 | O25: =+N25+Actual!O25 -> 0 | P25: =+O25+Actual!P25 -> 0
B26: 9 | C26: =+Introduction!F19 -> Expense 9 | E26: =Actual!E26 -> 0 | F26: =+E26+Actual!F26 -> 0 | G26: =+F26+Actual!G26 -> 0 | H26: =Actual!H26 -> 0 | I26: =+H26+Actual!I26 -> 0 | J26: =+I26+Actual!J26 -> 0 | K26: =Actual!K26 -> 0 | L26: =+K26+Actual!L26 -> 0 | M26: =+L26+Actual!M26 -> 0 | N26: =Actual!N26 -> 0 | O26: =+N26+Actual!O26 -> 0 | P26: =+O26+Actual!P26 -> 0
B27: 10 | C27: =+Introduction!F20 -> Expense 10 | E27: =Actual!E27 -> 0 | F27: =+E27+Actual!F27 -> 0 | G27: =+F27+Actual!G27 -> 0 | H27: =Actual!H27 -> 0 | I27: =+H27+Actual!I27 -> 0 | J27: =+I27+Actual!J27 -> 0 | K27: =Actual!K27 -> 0 | L27: =+K27+Actual!L27 -> 0 | M27: =+L27+Actual!M27 -> 0 | N27: =Actual!N27 -> 0 | O27: =+N27+Actual!O27 -> 0 | P27: =+O27+Actual!P27 -> 0
B28: 11 | C28: =+Introduction!F21 -> Expense 11 | E28: =Actual!E28 -> 0 | F28: =+E28+Actual!F28 -> 0 | G28: =+F28+Actual!G28 -> 0 | H28: =Actual!H28 -> 0 | I28: =+H28+Actual!I28 -> 0 | J28: =+I28+Actual!J28 -> 0 | K28: =Actual!K28 -> 0 | L28: =+K28+Actual!L28 -> 0 | M28: =+L28+Actual!M28 -> 0 | N28: =Actual!N28 -> 0 | O28: =+N28+Actual!O28 -> 0 | P28: =+O28+Actual!P28 -> 0
B29: 12 | C29: =+Introduction!F22 -> Expense 12 | E29: =Actual!E29 -> 0 | F29: =+E29+Actual!F29 -> 0 | G29: =+F29+Actual!G29 -> 0 | H29: =Actual!H29 -> 0 | I29: =+H29+Actual!I29 -> 0 | J29: =+I29+Actual!J29 -> 0 | K29: =Actual!K29 -> 0 | L29: =+K29+Actual!L29 -> 0 | M29: =+L29+Actual!M29 -> 0 | N29: =Actual!N29 -> 0 | O29: =+N29+Actual!O29 -> 0 | P29: =+O29+Actual!P29 -> 0
... B37: 20 | C37: =+Introduction!F30 -> IRA Contribution | E37: =Actual!E37 -> 0 | F37: =+E37+Actual!F37 -> 0 | G37: =+F37+Actual!G37 -> 0 | H37: =Actual!H37 -> 0 | I37: =+H37+Actual!I37 -> 0 | J37: =+I37+Actual!J37 -> 0 | K37: =Actual!K37 -> 0 | L37: =+K37+Actual!L37 -> 0 | M37: =+L37+Actual!M37 -> 0 | N37: =Actual!N37 -> 0 | O37: =+N37+Actual!O37 -> 0 | P37: =+O37+Actual!P37 -> 0
B38: Total Expenses | E38: =SUM(E18:E37) -> 0 | F38: =SUM(F18:F37) -> 0 | G38: =SUM(G18:G37) -> 0 | H38: =SUM(H18:H37) -> 0 | I38: =SUM(I18:I37) -> 0 | J38: =SUM(J18:J37) -> 0 | K38: =SUM(K18:K37) -> 0 | L38: =SUM(L18:L37) -> 0 | ... P38: =SUM(P18:P37) -> 0
B40: Income Less Expenses | E40: =+E14-E38 -> 0 | F40: =+F14-F38 -> 0 | G40: =+G14-G38 -> 0 | H40: =+H14-H38 -> 0 | I40: =+I14-I38 -> 0 | J40: =+J14-J38 -> 0 | K40: =+K14-K38 -> 0 | L40: =+L14-L38 -> 0 | ... P40: =+P14-P38 -> 0
B42: 1 | C42: Beginning Cash Balance | E42: =+Actual!E42 -> 0 | F42: =+E42 -> 0 | G42: =+F42 -> 0 | H42: =+Actual!H42 -> 0 | I42: =+H42 -> 0 | J42: =+I42 -> 0 | K42: =+Actual!K42 -> 0 | L42: =+K42 -> 0 | M42: =+L42 -> 0 | N42: =+Actual!N42 -> 0 | O42: =+N42 -> 0 | P42: =+O42 -> 0
B43: 2 | C43: Income Less Expense | E43: =+E40 -> 0 | F43: =+F40 -> 0 | G43: =+G40 -> 0 | H43: =+H40 -> 0 | I43: =+I40 -> 0 | J43: =+J40 -> 0 | K43: =+K40 -> 0 | L43: =+L40 -> 0 | ... P43: =+P40 -> 0
B44: 3 | C44: Ending Cash Balance | E44: =+E43+E42 -> 0 | F44: =+F43+F42 -> 0 | G44: =+G43+G42 -> 0 | H44: =+H43+H42 -> 0 | I44: =+I43+I42 -> 0 | J44: =+J43+J42 -> 0 | K44: =+K43+K42 -> 0 | L44: =+L43+L42 -> 0 | ... P44: =+P43+P42 -> 0
B46: 1 | C46: Roth IRA Cumulative Contribution | E46: =+Actual!E46 -> 0 | F46: =+Actual!F46 -> 0 | G46: =+Actual!G46 -> 0 | H46: =+Actual!H46 -> 0 | I46: =+Actual!I46 -> 0 | J46: =+Actual!J46 -> 0 | K46: =+Actual!K46 -> 0 | L46: =+Actual!L46 -> 0 | ... P46: =+Actual!P46 -> 0

Sheet Budget YTD
B2: =CONCATENATE(Introduction!C4:C4,"'s"," Personal Budget ",Introduction!C5," Year-To-Date by Month") -> 's Personal Budget 2012 Year-To-Date by Month
B3: Days on Month Calc | E3: 31 | F3: =IF(MOD(Introduction!C5,4)=0,29,28) -> 29 | G3: 31 | H3: 30 | I3: 31 | J3: 30 | K3: 31 | L3: 31 | M3: 30 | N3: 31 | O3: 30 | P3: 31
B4: Month and Year Calc | E4: =CONCATENATE(MONTH(E5)," ",YEAR(E5)) -> 1 2012 | F4: =CONCATENATE(MONTH(F5)," ",YEAR(F5)) -> 2 2012 | G4: =CONCATENATE(MONTH(G5)," ",YEAR(G5)) -> 3 2012 | H4: =CONCATENATE(MONTH(H5)," ",YEAR(H5)) -> 4 2012 | I4: =CONCATENATE(MONTH(I5)," ",YEAR(I5)) -> 5 2012 | J4: =CONCATENATE(MONTH(J5)," ",YEAR(J5)) -> 6 2012 | K4: =CONCATENATE(MONTH(K5)," ",YEAR(K5)) -> 7 2012 | L4: =CONCATENATE(MONTH(L5)," ",YEAR(L5)) -> 8 2012 | ... P4: =CONCATENATE(MONTH(P5)," ",YEAR(P5)) -> 12 2012
B5: Items Revenue/Expense | E5: =+Introduction!C6+0 -> 40909 | F5: =+E5+E3 -> 40940 | G5: =+F5+F3 -> 40969 | H5: =+G5+G3 -> 41000 | I5: =+H5+H3 -> 41030 | J5: =+I5+I3 -> 41061 | K5: =+J5+J3 -> 41091 | L5: =+K5+K3 -> 41122 | M5: =+L5+L3 -> 41153 | ... Q5: =+P5+P3 -> 41275 | R5: Total
B6: 1 | C6: =+Introduction!C11 -> Income 1 | E6: =+D6+Budget!E6 -> 0 | F6: =+E6+Budget!F6 -> 0 | G6: =+F6+Budget!G6 -> 0 | H6: =+G6+Budget!H6 -> 0 | I6: =+H6+Budget!I6 -> 0 | J6: =+I6+Budget!J6 -> 0 | K6: =+J6+Budget!K6 -> 0 | L6: =+K6+Budget!L6 -> 0 | ... P6: =+O6+Budget!P6 -> 0
B7: 2 | C7: =+Introduction!C12 -> Income 2 | E7: =+D7+Budget!E7 -> 0 | F7: =+E7+Budget!F7 -> 0 | G7: =+F7+Budget!G7 -> 0 | H7: =+G7+Budget!H7 -> 0 | I7: =+H7+Budget!I7 -> 0 | J7: =+I7+Budget!J7 -> 0 | K7: =+J7+Budget!K7 -> 0 | L7: =+K7+Budget!L7 -> 0 | ... P7: =+O7+Budget!P7 -> 0
B8: 3 | C8: =+Introduction!C13 -> Income 3 | E8: =+D8+Budget!E8 -> 0 | F8: =+E8+Budget!F8 -> 0 | G8: =+F8+Budget!G8 -> 0 | H8: =+G8+Budget!H8 -> 0 | I8: =+H8+Budget!I8 -> 0 | J8: =+I8+Budget!J8 -> 0 | K8: =+J8+Budget!K8 -> 0 | L8: =+K8+Budget!L8 -> 0 | ... P8: =+O8+Budget!P8 -> 0
B9: 4 | C9: =+Introduction!C14 -> Income 4 | E9: =+D9+Budget!E9 -> 0 | F9: =+E9+Budget!F9 -> 0 | G9: =+F9+Budget!G9 -> 0 | H9: =+G9+Budget!H9 -> 0 | I9: =+H9+Budget!I9 -> 0 | J9: =+I9+Budget!J9 -> 0 | K9: =+J9+Budget!K9 -> 0 | L9: =+K9+Budget!L9 -> 0 | ... P9: =+O9+Budget!P9 -> 0
B10: 5 | C10: =+Introduction!C15 -> Income 5 | E10: =+D10+Budget!E10 -> 0 | F10: =+E10+Budget!F10 -> 0 | G10: =+F10+Budget!G10 -> 0 | H10: =+G10+Budget!H10 -> 0 | I10: =+H10+Budget!I10 -> 0 | J10: =+I10+Budget!J10 -> 0 | K10: =+J10+Budget!K10 -> 0 | L10: =+K10+Budget!L10 -> 0 | ... P10: =+O10+Budget!P10 -> 0
B11: 6 | C11: =+Introduction!C16 -> Income 6 | E11: =+D11+Budget!E11 -> 0 | F11: =+E11+Budget!F11 -> 0 | G11: =+F11+Budget!G11 -> 0 | H11: =+G11+Budget!H11 -> 0 | I11: =+H11+Budget!I11 -> 0 | J11: =+I11+Budget!J11 -> 0 | K11: =+J11+Budget!K11 -> 0 | L11: =+K11+Budget!L11 -> 0 | ... P11: =+O11+Budget!P11 -> 0
B12: 7 | C12: =+Introduction!C17 -> Income 7 | E12: =+D12+Budget!E12 -> 0 | F12: =+E12+Budget!F12 -> 0 | G12: =+F12+Budget!G12 -> 0 | H12: =+G12+Budget!H12 -> 0 | I12: =+H12+Budget!I12 -> 0 | J12: =+I12+Budget!J12 -> 0 | K12: =+J12+Budget!K12 -> 0 | L12: =+K12+Budget!L12 -> 0 | ... P12: =+O12+Budget!P12 -> 0
B13: 8 | C13: =+Introduction!C18 -> Income 8 | E13: =+D13+Budget!E13 -> 0 | F13: =+E13+Budget!F13 -> 0 | G13: =+F13+Budget!G13 -> 0 | H13: =+G13+Budget!H13 -> 0 | I13: =+H13+Budget!I13 -> 0 | J13: =+I13+Budget!J13 -> 0 | K13: =+J13+Budget!K13 -> 0 | L13: =+K13+Budget!L13 -> 0 | ... P13: =+O13+Budget!P13 -> 0
C14: Total Income | E14: =SUM(E6:E13) -> 0 | F14: =SUM(F6:F13) -> 0 | G14: =SUM(G6:G13) -> 0 | H14: =SUM(H6:H13) -> 0 | I14: =SUM(I6:I13) -> 0 | J14: =SUM(J6:J13) -> 0 | K14: =SUM(K6:K13) -> 0 | L14: =SUM(L6:L13) -> 0 | ... P14: =SUM(P6:P13) -> 0
C16: Month and Year Calc Income/Expense | E16: =CONCATENATE(MONTH(E17)," ",YEAR(E17), " Expense") -> 1 2012 Expense | F16: =CONCATENATE(MONTH(F17)," ",YEAR(F17), " Expense") -> 2 2012 Expense | G16: =CONCATENATE(MONTH(G17)," ",YEAR(G17), " Expense") -> 3 2012 Expense | H16: =CONCATENATE(MONTH(H17)," ",YEAR(H17), " Expense") -> 4 2012 Expense | I16: =CONCATENATE(MONTH(I17)," ",YEAR(I17), " Expense") -> 5 2012 Expense | J16: =CONCATENATE(MONTH(J17)," ",YEAR(J17), " Expense") -> 6 2012 Expense | K16: =CONCATENATE(MONTH(K17)," ",YEAR(K17), " Expense") -> 7 2012 Expense | L16: =CONCATENATE(MONTH(L17)," ",YEAR(L17), " Expense") -> 8 2012 Expense | ... P16: =CONCATENATE(MONTH(P17)," ",YEAR(P17), " Expense") -> 12 2012 Expense
C17: Expenses | E17: =+E5 -> 40909 | F17: =+F5 -> 40940 | G17: =+G5 -> 40969 | H17: =+H5 -> 41000 | I17: =+I5 -> 41030 | J17: =+J5 -> 41061 | K17: =+K5 -> 41091 | L17: =+L5 -> 41122 | ... P17: =+P5 -> 41244 | R17: Total
B18: 1 | C18: =+Introduction!F11 -> Expense 1 | E18: =+D18+Budget!E18 -> 0 | F18: =+E18+Budget!F18 -> 0 | G18: =+F18+Budget!G18 -> 0 | H18: =+G18+Budget!H18 -> 0 | I18: =+H18+Budget!I18 -> 0 | J18: =+I18+Budget!J18 -> 0 | K18: =+J18+Budget!K18 -> 0 | L18: =+K18+Budget!L18 -> 0 | ... P18: =+O18+Budget!P18 -> 0
B19: 2 | C19: =+Introduction!F12 -> Expense 2 | E19: =+D19+Budget!E19 -> 0 | F19: =+E19+Budget!F19 -> 0 | G19: =+F19+Budget!G19 -> 0 | H19: =+G19+Budget!H19 -> 0 | I19: =+H19+Budget!I19 -> 0 | J19: =+I19+Budget!J19 -> 0 | K19: =+J19+Budget!K19 -> 0 | L19: =+K19+Budget!L19 -> 0 | ... P19: =+O19+Budget!P19 -> 0
B20: 3 | C20: =+Introduction!F13 -> Expense 3 | E20: =+D20+Budget!E20 -> 0 | F20: =+E20+Budget!F20 -> 0 | G20: =+F20+Budget!G20 -> 0 | H20: =+G20+Budget!H20 -> 0 | I20: =+H20+Budget!I20 -> 0 | J20: =+I20+Budget!J20 -> 0 | K20: =+J20+Budget!K20 -> 0 | L20: =+K20+Budget!L20 -> 0 | ... P20: =+O20+Budget!P20 -> 0
B21: 4 | C21: =+Introduction!F14 -> Expense 4 | E21: =+D21+Budget!E21 -> 0 | F21: =+E21+Budget!F21 -> 0 | G21: =+F21+Budget!G21 -> 0 | H21: =+G21+Budget!H21 -> 0 | I21: =+H21+Budget!I21 -> 0 | J21: =+I21+Budget!J21 -> 0 | K21: =+J21+Budget!K21 -> 0 | L21: =+K21+Budget!L21 -> 0 | ... P21: =+O21+Budget!P21 -> 0
B22: 5 | C22: =+Introduction!F15 -> Expense 5 | E22: =+D22+Budget!E22 -> 0 | F22: =+E22+Budget!F22 -> 0 | G22: =+F22+Budget!G22 -> 0 | H22: =+G22+Budget!H22 -> 0 | I22: =+H22+Budget!I22 -> 0 | J22: =+I22+Budget!J22 -> 0 | K22: =+J22+Budget!K22 -> 0 | L22: =+K22+Budget!L22 -> 0 | ... P22: =+O22+Budget!P22 -> 0
B23: 6 | C23: =+Introduction!F16 -> Expense 6 | E23: =+D23+Budget!E23 -> 0 | F23: =+E23+Budget!F23 -> 0 | G23: =+F23+Budget!G23 -> 0 | H23: =+G23+Budget!H23 -> 0 | I23: =+H23+Budget!I23 -> 0 | J23: =+I23+Budget!J23 -> 0 | K23: =+J23+Budget!K23 -> 0 | L23: =+K23+Budget!L23 -> 0 | ... P23: =+O23+Budget!P23 -> 0
B24: 7 | C24: =+Introduction!F17 -> Expense 7 | E24: =+D24+Budget!E24 -> 0 | F24: =+E24+Budget!F24 -> 0 | G24: =+F24+Budget!G24 -> 0 | H24: =+G24+Budget!H24 -> 0 | I24: =+H24+Budget!I24 -> 0 | J24: =+I24+Budget!J24 -> 0 | K24: =+J24+Budget!K24 -> 0 | L24: =+K24+Budget!L24 -> 0 | ... P24: =+O24+Budget!P24 -> 0
B25: 8 | C25: =+Introduction!F18 -> Expense 8 | E25: =+D25+Budget!E25 -> 0 | F25: =+E25+Budget!F25 -> 0 | G25: =+F25+Budget!G25 -> 0 | H25: =+G25+Budget!H25 -> 0 | I25: =+H25+Budget!I25 -> 0 | J25: =+I25+Budget!J25 -> 0 | K25: =+J25+Budget!K25 -> 0 | L25: =+K25+Budget!L25 -> 0 | ... P25: =+O25+Budget!P25 -> 0
B26: 9 | C26: =+Introduction!F19 -> Expense 9 | E26: =+D26+Budget!E26 -> 0 | F26: =+E26+Budget!F26 -> 0 | G26: =+F26+Budget!G26 -> 0 | H26: =+G26+Budget!H26 -> 0 | I26: =+H26+Budget!I26 -> 0 | J26: =+I26+Budget!J26 -> 0 | K26: =+J26+Budget!K26 -> 0 | L26: =+K26+Budget!L26 -> 0 | ... P26: =+O26+Budget!P26 -> 0
B27: 10 | C27: =+Introduction!F20 -> Expense 10 | E27: =+D27+Budget!E27 -> 0 | F27: =+E27+Budget!F27 -> 0 | G27: =+F27+Budget!G27 -> 0 | H27: =+G27+Budget!H27 -> 0 | I27: =+H27+Budget!I27 -> 0 | J27: =+I27+Budget!J27 -> 0 | K27: =+J27+Budget!K27 -> 0 | L27: =+K27+Budget!L27 -> 0 | ... P27: =+O27+Budget!P27 -> 0
B28: 11 | C28: =+Introduction!F21 -> Expense 11 | E28: =+D28+Budget!E28 -> 0 | F28: =+E28+Budget!F28 -> 0 | G28: =+F28+Budget!G28 -> 0 | H28: =+G28+Budget!H28 -> 0 | I28: =+H28+Budget!I28 -> 0 | J28: =+I28+Budget!J28 -> 0 | K28: =+J28+Budget!K28 -> 0 | L28: =+K28+Budget!L28 -> 0 | ... P28: =+O28+Budget!P28 -> 0
B29: 12 | C29: =+Introduction!F22 -> Expense 12 | E29: =+D29+Budget!E29 -> 0 | F29: =+E29+Budget!F29 -> 0 | G29: =+F29+Budget!G29 -> 0 | H29: =+G29+Budget!H29 -> 0 | I29: =+H29+Budget!I29 -> 0 | J29: =+I29+Budget!J29 -> 0 | K29: =+J29+Budget!K29 -> 0 | L29: =+K29+Budget!L29 -> 0 | ... P29: =+O29+Budget!P29 -> 0
... B37: 20 | C37: =+Introduction!F30 -> IRA Contribution | E37: =+D37+Budget!E37 -> 0 | F37: =+E37+Budget!F37 -> 0 | G37: =+F37+Budget!G37 -> 0 | H37: =+G37+Budget!H37 -> 0 | I37: =+H37+Budget!I37 -> 0 | J37: =+I37+Budget!J37 -> 0 | K37: =+J37+Budget!K37 -> 0 | L37: =+K37+Budget!L37 -> 0 | ... P37: =+O37+Budget!P37 -> 0
B38: Total Expenses | E38: =SUM(E18:E37) -> 0 | F38: =SUM(F18:F37) -> 0 | G38: =SUM(G18:G37) -> 0 | H38: =SUM(H18:H37) -> 0 | I38: =SUM(I18:I37) -> 0 | J38: =SUM(J18:J37) -> 0 | K38: =SUM(K18:K37) -> 0 | L38: =SUM(L18:L37) -> 0 | ... P38: =SUM(P18:P37) -> 0
B40: Income Less Expenses | E40: =+E14-E38 -> 0 | F40: =+F14-F38 -> 0 | G40: =+G14-G38 -> 0 | H40: =+H14-H38 -> 0 | I40: =+I14-I38 -> 0 | J40: =+J14-J38 -> 0 | K40: =+K14-K38 -> 0 | L40: =+L14-L38 -> 0 | ... P40: =+P14-P38 -> 0
B42: 1 | C42: Beginning Cash Balance | E42: =+Budget!E42 -> 0 | F42: =+E42 -> 0 | G42: =+F42 -> 0 | H42: =+G42 -> 0 | I42: =+H42 -> 0 | J42: =+I42 -> 0 | K42: =+J42 -> 0 | L42: =+K42 -> 0 | M42: =+L42 -> 0 | ... P42: =+O42 -> 0
B43: 2 | C43: Income Less Expense | E43: =+E40 -> 0 | F43: =+F40 -> 0 | G43: =+G40 -> 0 | H43: =+H40 -> 0 | I43: =+I40 -> 0 | J43: =+J40 -> 0 | K43: =+K40 -> 0 | L43: =+L40 -> 0 | ... P43: =+P40 -> 0
B44: 3 | C44: Ending Cash Balance | E44: =+E42+E43 -> 0 | F44: =+F42+F43 -> 0 | G44: =+G42+G43 -> 0 | H44: =+H42+H43 -> 0 | I44: =+I42+I43 -> 0 | J44: =+J42+J43 -> 0 | K44: =+K42+K43 -> 0 | L44: =+L42+L43 -> 0 | ... P44: =+P42+P43 -> 0
B46: 1 | C46: Roth IRA Cumulative Contribution | E46: =+Budget!E46 -> 0 | F46: =+Budget!F46 -> 0 | G46: =+Budget!G46 -> 0 | H46: =+Budget!H46 -> 0 | I46: =+Budget!I46 -> 0 | J46: =+Budget!J46 -> 0 | K46: =+Budget!K46 -> 0 | L46: =+Budget!L46 -> 0 | ... P46: =+Budget!P46 -> 0

Sheet Actual YTD
B2: =CONCATENATE(Introduction!C4:C4,"'s"," Personal Actual ",Introduction!C5," Year-To-Date by Month") -> 's Personal Actual 2012 Year-To-Date by Month
B3: Days on Month Calc | E3: 31 | F3: =IF(MOD(Introduction!C5,4)=0,29,28) -> 29 | G3: 31 | H3: 30 | I3: 31 | J3: 30 | K3: 31 | L3: 31 | M3: 30 | N3: 31 | O3: 30 | P3: 31
B4: Month and Year Calc | E4: =CONCATENATE(MONTH(E5)," ",YEAR(E5)) -> 1 2012 | F4: =CONCATENATE(MONTH(F5)," ",YEAR(F5)) -> 2 2012 | G4: =CONCATENATE(MONTH(G5)," ",YEAR(G5)) -> 3 2012 | H4: =CONCATENATE(MONTH(H5)," ",YEAR(H5)) -> 4 2012 | I4: =CONCATENATE(MONTH(I5)," ",YEAR(I5)) -> 5 2012 | J4: =CONCATENATE(MONTH(J5)," ",YEAR(J5)) -> 6 2012 | K4: =CONCATENATE(MONTH(K5)," ",YEAR(K5)) -> 7 2012 | L4: =CONCATENATE(MONTH(L5)," ",YEAR(L5)) -> 8 2012 | ... P4: =CONCATENATE(MONTH(P5)," ",YEAR(P5)) -> 12 2012
B5: Items Revenue/Expense | E5: =+Introduction!C6+0 -> 40909 | F5: =+E5+E3 -> 40940 | G5: =+F5+F3 -> 40969 | H5: =+G5+G3 -> 41000 | I5: =+H5+H3 -> 41030 | J5: =+I5+I3 -> 41061 | K5: =+J5+J3 -> 41091 | L5: =+K5+K3 -> 41122 | M5: =+L5+L3 -> 41153 | ... Q5: =+P5+P3 -> 41275 | R5: Total
B6: 1 | C6: =+Introduction!C11 -> Income 1 | E6: =+D6+Actual!E6 -> 0 | F6: =+E6+Actual!F6 -> 0 | G6: =+F6+Actual!G6 -> 0 | H6: =+G6+Actual!H6 -> 0 | I6: =+H6+Actual!I6 -> 0 | J6: =+I6+Actual!J6 -> 0 | K6: =+J6+Actual!K6 -> 0 | L6: =+K6+Actual!L6 -> 0 | ... P6: =+O6+Actual!P6 -> 0
B7: 2 | C7: =+Introduction!C12 -> Income 2 | E7: =+D7+Actual!E7 -> 0 | F7: =+E7+Actual!F7 -> 0 | G7: =+F7+Actual!G7 -> 0 | H7: =+G7+Actual!H7 -> 0 | I7: =+H7+Actual!I7 -> 0 | J7: =+I7+Actual!J7 -> 0 | K7: =+J7+Actual!K7 -> 0 | L7: =+K7+Actual!L7 -> 0 | ... P7: =+O7+Actual!P7 -> 0
B8: 3 | C8: =+Introduction!C13 -> Income 3 | E8: =+D8+Actual!E8 -> 0 | F8: =+E8+Actual!F8 -> 0 | G8: =+F8+Actual!G8 -> 0 | H8: =+G8+Actual!H8 -> 0 | I8: =+H8+Actual!I8 -> 0 | J8: =+I8+Actual!J8 -> 0 | K8: =+J8+Actual!K8 -> 0 | L8: =+K8+Actual!L8 -> 0 | ... P8: =+O8+Actual!P8 -> 0
B9: 4 | C9: =+Introduction!C14 -> Income 4 | E9: =+D9+Actual!E9 -> 0 | F9: =+E9+Actual!F9 -> 0 | G9: =+F9+Actual!G9 -> 0 | H9: =+G9+Actual!H9 -> 0 | I9: =+H9+Actual!I9 -> 0 | J9: =+I9+Actual!J9 -> 0 | K9: =+J9+Actual!K9 -> 0 | L9: =+K9+Actual!L9 -> 0 | ... P9: =+O9+Actual!P9 -> 0
B10: 5 | C10: =+Introduction!C15 -> Income 5 | E10: =+D10+Actual!E10 -> 0 | F10: =+E10+Actual!F10 -> 0 | G10: =+F10+Actual!G10 -> 0 | H10: =+G10+Actual!H10 -> 0 | I10: =+H10+Actual!I10 -> 0 | J10: =+I10+Actual!J10 -> 0 | K10: =+J10+Actual!K10 -> 0 | L10: =+K10+Actual!L10 -> 0 | ... P10: =+O10+Actual!P10 -> 0
B11: 6 | C11: =+Introduction!C16 -> Income 6 | E11: =+D11+Actual!E11 -> 0 | F11: =+E11+Actual!F11 -> 0 | G11: =+F11+Actual!G11 -> 0 | H11: =+G11+Actual!H11 -> 0 | I11: =+H11+Actual!I11 -> 0 | J11: =+I11+Actual!J11 -> 0 | K11: =+J11+Actual!K11 -> 0 | L11: =+K11+Actual!L11 -> 0 | ... P11: =+O11+Actual!P11 -> 0
B12: 7 | C12: =+Introduction!C17 -> Income 7 | E12: =+D12+Actual!E12 -> 0 | F12: =+E12+Actual!F12 -> 0 | G12: =+F12+Actual!G12 -> 0 | H12: =+G12+Actual!H12 -> 0 | I12: =+H12+Actual!I12 -> 0 | J12: =+I12+Actual!J12 -> 0 | K12: =+J12+Actual!K12 -> 0 | L12: =+K12+Actual!L12 -> 0 | ... P12: =+O12+Actual!P12 -> 0
B13: 8 | C13: =+Introduction!C18 -> Income 8 | E13: =+D13+Actual!E13 -> 0 | F13: =+E13+Actual!F13 -> 0 | G13: =+F13+Actual!G13 -> 0 | H13: =+G13+Actual!H13 -> 0 | I13: =+H13+Actual!I13 -> 0 | J13: =+I13+Actual!J13 -> 0 | K13: =+J13+Actual!K13 -> 0 | L13: =+K13+Actual!L13 -> 0 | ... P13: =+O13+Actual!P13 -> 0
C14: Total Income | E14: =SUM(E6:E13) -> 0 | F14: =SUM(F6:F13) -> 0 | G14: =SUM(G6:G13) -> 0 | H14: =SUM(H6:H13) -> 0 | I14: =SUM(I6:I13) -> 0 | J14: =SUM(J6:J13) -> 0 | K14: =SUM(K6:K13) -> 0 | L14: =SUM(L6:L13) -> 0 | ... P14: =SUM(P6:P13) -> 0
C16: Month and Year Calc Income/Expense | E16: =CONCATENATE(MONTH(E17)," ",YEAR(E17), " Expense") -> 1 2012 Expense | F16: =CONCATENATE(MONTH(F17)," ",YEAR(F17), " Expense") -> 2 2012 Expense | G16: =CONCATENATE(MONTH(G17)," ",YEAR(G17), " Expense") -> 3 2012 Expense | H16: =CONCATENATE(MONTH(H17)," ",YEAR(H17), " Expense") -> 4 2012 Expense | I16: =CONCATENATE(MONTH(I17)," ",YEAR(I17), " Expense") -> 5 2012 Expense | J16: =CONCATENATE(MONTH(J17)," ",YEAR(J17), " Expense") -> 6 2012 Expense | K16: =CONCATENATE(MONTH(K17)," ",YEAR(K17), " Expense") -> 7 2012 Expense | L16: =CONCATENATE(MONTH(L17)," ",YEAR(L17), " Expense") -> 8 2012 Expense | ... P16: =CONCATENATE(MONTH(P17)," ",YEAR(P17), " Expense") -> 12 2012 Expense
C17: Expenses | E17: =+E5 -> 40909 | F17: =+F5 -> 40940 | G17: =+G5 -> 40969 | H17: =+H5 -> 41000 | I17: =+I5 -> 41030 | J17: =+J5 -> 41061 | K17: =+K5 -> 41091 | L17: =+L5 -> 41122 | ... P17: =+P5 -> 41244 | R17: Total
B18: 1 | C18: =+Introduction!F11 -> Expense 1 | E18: =+D18+Actual!E18 -> 0 | F18: =+E18+Actual!F18 -> 0 | G18: =+F18+Actual!G18 -> 0 | H18: =+G18+Actual!H18 -> 0 | I18: =+H18+Actual!I18 -> 0 | J18: =+I18+Actual!J18 -> 0 | K18: =+J18+Actual!K18 -> 0 | L18: =+K18+Actual!L18 -> 0 | ... P18: =+O18+Actual!P18 -> 0
B19: 2 | C19: =+Introduction!F12 -> Expense 2 | E19: =+D19+Actual!E19 -> 0 | F19: =+E19+Actual!F19 -> 0 | G19: =+F19+Actual!G19 -> 0 | H19: =+G19+Actual!H19 -> 0 | I19: =+H19+Actual!I19 -> 0 | J19: =+I19+Actual!J19 -> 0 | K19: =+J19+Actual!K19 -> 0 | L19: =+K19+Actual!L19 -> 0 | ... P19: =+O19+Actual!P19 -> 0
B20: 3 | C20: =+Introduction!F13 -> Expense 3 | E20: =+D20+Actual!E20 -> 0 | F20: =+E20+Actual!F20 -> 0 | G20: =+F20+Actual!G20 -> 0 | H20: =+G20+Actual!H20 -> 0 | I20: =+H20+Actual!I20 -> 0 | J20: =+I20+Actual!J20 -> 0 | K20: =+J20+Actual!K20 -> 0 | L20: =+K20+Actual!L20 -> 0 | ... P20: =+O20+Actual!P20 -> 0
B21: 4 | C21: =+Introduction!F14 -> Expense 4 | E21: =+D21+Actual!E21 -> 0 | F21: =+E21+Actual!F21 -> 0 | G21: =+F21+Actual!G21 -> 0 | H21: =+G21+Actual!H21 -> 0 | I21: =+H21+Actual!I21 -> 0 | J21: =+I21+Actual!J21 -> 0 | K21: =+J21+Actual!K21 -> 0 | L21: =+K21+Actual!L21 -> 0 | ... P21: =+O21+Actual!P21 -> 0
B22: 5 | C22: =+Introduction!F15 -> Expense 5 | E22: =+D22+Actual!E22 -> 0 | F22: =+E22+Actual!F22 -> 0 | G22: =+F22+Actual!G22 -> 0 | H22: =+G22+Actual!H22 -> 0 | I22: =+H22+Actual!I22 -> 0 | J22: =+I22+Actual!J22 -> 0 | K22: =+J22+Actual!K22 -> 0 | L22: =+K22+Actual!L22 -> 0 | ... P22: =+O22+Actual!P22 -> 0
B23: 6 | C23: =+Introduction!F16 -> Expense 6 | E23: =+D23+Actual!E23 -> 0 | F23: =+E23+Actual!F23 -> 0 | G23: =+F23+Actual!G23 -> 0 | H23: =+G23+Actual!H23 -> 0 | I23: =+H23+Actual!I23 -> 0 | J23: =+I23+Actual!J23 -> 0 | K23: =+J23+Actual!K23 -> 0 | L23: =+K23+Actual!L23 -> 0 | ... P23: =+O23+Actual!P23 -> 0
B24: 7 | C24: =+Introduction!F17 -> Expense 7 | E24: =+D24+Actual!E24 -> 0 | F24: =+E24+Actual!F24 -> 0 | G24: =+F24+Actual!G24 -> 0 | H24: =+G24+Actual!H24 -> 0 | I24: =+H24+Actual!I24 -> 0 | J24: =+I24+Actual!J24 -> 0 | K24: =+J24+Actual!K24 -> 0 | L24: =+K24+Actual!L24 -> 0 | ... P24: =+O24+Actual!P24 -> 0
B25: 8 | C25: =+Introduction!F18 -> Expense 8 | E25: =+D25+Actual!E25 -> 0 | F25: =+E25+Actual!F25 -> 0 | G25: =+F25+Actual!G25 -> 0 | H25: =+G25+Actual!H25 -> 0 | I25: =+H25+Actual!I25 -> 0 | J25: =+I25+Actual!J25 -> 0 | K25: =+J25+Actual!K25 -> 0 | L25: =+K25+Actual!L25 -> 0 | ... P25: =+O25+Actual!P25 -> 0
B26: 9 | C26: =+Introduction!F19 -> Expense 9 | E26: =+D26+Actual!E26 -> 0 | F26: =+E26+Actual!F26 -> 0 | G26: =+F26+Actual!G26 -> 0 | H26: =+G26+Actual!H26 -> 0 | I26: =+H26+Actual!I26 -> 0 | J26: =+I26+Actual!J26 -> 0 | K26: =+J26+Actual!K26 -> 0 | L26: =+K26+Actual!L26 -> 0 | ... P26: =+O26+Actual!P26 -> 0
B27: 10 | C27: =+Introduction!F20 -> Expense 10 | E27: =+D27+Actual!E27 -> 0 | F27: =+E27+Actual!F27 -> 0 | G27: =+F27+Actual!G27 -> 0 | H27: =+G27+Actual!H27 -> 0 | I27: =+H27+Actual!I27 -> 0 | J27: =+I27+Actual!J27 -> 0 | K27: =+J27+Actual!K27 -> 0 | L27: =+K27+Actual!L27 -> 0 | ... P27: =+O27+Actual!P27 -> 0
B28: 11 | C28: =+Introduction!F21 -> Expense 11 | E28: =+D28+Actual!E28 -> 0 | F28: =+E28+Actual!F28 -> 0 | G28: =+F28+Actual!G28 -> 0 | H28: =+G28+Actual!H28 -> 0 | I28: =+H28+Actual!I28 -> 0 | J28: =+I28+Actual!J28 -> 0 | K28: =+J28+Actual!K28 -> 0 | L28: =+K28+Actual!L28 -> 0 | ... P28: =+O28+Actual!P28 -> 0
B29: 12 | C29: =+Introduction!F22 -> Expense 12 | E29: =+D29+Actual!E29 -> 0 | F29: =+E29+Actual!F29 -> 0 | G29: =+F29+Actual!G29 -> 0 | H29: =+G29+Actual!H29 -> 0 | I29: =+H29+Actual!I29 -> 0 | J29: =+I29+Actual!J29 -> 0 | K29: =+J29+Actual!K29 -> 0 | L29: =+K29+Actual!L29 -> 0 | ... P29: =+O29+Actual!P29 -> 0
... B37: 20 | C37: =+Introduction!F30 -> IRA Contribution | E37: =+D37+Actual!E37 -> 0 | F37: =+E37+Actual!F37 -> 0 | G37: =+F37+Actual!G37 -> 0 | H37: =+G37+Actual!H37 -> 0 | I37: =+H37+Actual!I37 -> 0 | J37: =+I37+Actual!J37 -> 0 | K37: =+J37+Actual!K37 -> 0 | L37: =+K37+Actual!L37 -> 0 | ... P37: =+O37+Actual!P37 -> 0
B38: Total Expenses | E38: =SUM(E18:E37) -> 0 | F38: =SUM(F18:F37) -> 0 | G38: =SUM(G18:G37) -> 0 | H38: =SUM(H18:H37) -> 0 | I38: =SUM(I18:I37) -> 0 | J38: =SUM(J18:J37) -> 0 | K38: =SUM(K18:K37) -> 0 | L38: =SUM(L18:L37) -> 0 | ... P38: =SUM(P18:P37) -> 0
B40: Income Less Expenses | E40: =+E14-E38 -> 0 | F40: =+F14-F38 -> 0 | G40: =+G14-G38 -> 0 | H40: =+H14-H38 -> 0 | I40: =+I14-I38 -> 0 | J40: =+J14-J38 -> 0 | K40: =+K14-K38 -> 0 | L40: =+L14-L38 -> 0 | ... P40: =+P14-P38 -> 0
B42: 1 | C42: Beginning Cash Balance | E42: =+Actual!E42 -> 0 | F42: =+E42 -> 0 | G42: =+F42 -> 0 | H42: =+G42 -> 0 | I42: =+H42 -> 0 | J42: =+I42 -> 0 | K42: =+J42 -> 0 | L42: =+K42 -> 0 | M42: =+L42 -> 0 | ... P42: =+O42 -> 0
B43: 2 | C43: Income Less Expense | E43: =+E40 -> 0 | F43: =+F40 -> 0 | G43: =+G40 -> 0 | H43: =+H40 -> 0 | I43: =+I40 -> 0 | J43: =+J40 -> 0 | K43: =+K40 -> 0 | L43: =+L40 -> 0 | ... P43: =+P40 -> 0
B44: 3 | C44: Ending Cash Balance | E44: =+E42+E43 -> 0 | F44: =+F42+F43 -> 0 | G44: =+G42+G43 -> 0 | H44: =+H42+H43 -> 0 | I44: =+I42+I43 -> 0 | J44: =+J42+J43 -> 0 | K44: =+K42+K43 -> 0 | L44: =+L42+L43 -> 0 | ... P44: =+P42+P43 -> 0
B46: 1 | C46: Roth IRA Cumulative Contribution | E46: =+Actual!E46 -> 0 | F46: =+Actual!F46 -> 0 | G46: =+Actual!G46 -> 0 | H46: =+Actual!H46 -> 0 | I46: =+Actual!I46 -> 0 | J46: =+Actual!J46 -> 0 | K46: =+Actual!K46 -> 0 | L46: =+Actual!L46 -> 0 | ... P46: =+Actual!P46 -> 0

Sheet Charts

Sheet Audit Sheet
C1: =+Introduction!G4 -> 1
B2: Try this Value | C2: Dec
D4: =+Budget!E5 -> 40909 | E4: =+Budget!F5 -> 40940 | F4: =+Budget!G5 -> 40969 | G4: =+Budget!H5 -> 41000 | H4: =+Budget!I5 -> 41030 | I4: =+Budget!J5 -> 41061 | J4: =+Budget!K5 -> 41091 | K4: =+Budget!L5 -> 41122 | ... O4: =+Budget!P5 -> 41244 | Q4: Total
B5: Sum of All Income in the Budget | D5: =SUM(Budget!E6:E13) -> 0 | E5: =SUM(Budget!F6:F13) -> 0 | F5: =SUM(Budget!G6:G13) -> 0 | G5: =SUM(Budget!H6:H13) -> 0 | H5: =SUM(Budget!I6:I13) -> 0 | I5: =SUM(Budget!J6:J13) -> 0 | J5: =SUM(Budget!K6:K13) -> 0 | K5: =SUM(Budget!L6:L13) -> 0 | ... O5: =SUM(Budget!P6:P13) -> 0 | Q5: =SUM(D5:O5) -> 0
B6: Sum of All Expense in Budget | D6: =SUM(Budget!E18:E37) -> 0 | E6: =SUM(Budget!F18:F37) -> 0 | F6: =SUM(Budget!G18:G37) -> 0 | G6: =SUM(Budget!H18:H37) -> 0 | H6: =SUM(Budget!I18:I37) -> 0 | I6: =SUM(Budget!J18:J37) -> 0 | J6: =SUM(Budget!K18:K37) -> 0 | K6: =SUM(Budget!L18:L37) -> 0 | ... O6: =SUM(Budget!P18:P37) -> 0 | Q6: =SUM(D6:O6) -> 0
B7: Net of All | D7: =+D5-D6 -> 0 | E7: =+E5-E6 -> 0 | F7: =+F5-F6 -> 0 | G7: =+G5-G6 -> 0 | H7: =+H5-H6 -> 0 | I7: =+I5-I6 -> 0 | J7: =+J5-J6 -> 0 | K7: =+K5-K6 -> 0 | ... O7: =+O5-O6 -> 0 | Q7: =+Q5-Q6 -> 0
B9: Month Net | D9: =+D7 -> 0 | E9: =+E7 -> 0 | F9: =+F7 -> 0 | G9: =+G7 -> 0 | H9: =+H7 -> 0 | I9: =+I7 -> 0 | J9: =+J7 -> 0 | K9: =+K7 -> 0 | ... O9: =+O7 -> 0
B10: YTD Net | D10: =+C10+D7 -> 0 | E10: =+D10+E7 -> 0 | F10: =+E10+F7 -> 0 | G10: =+F10+G7 -> 0 | H10: =+G10+H7 -> 0 | I10: =+H10+I7 -> 0 | J10: =+I10+J7 -> 0 | K10: =+J10+K7 -> 0 | ... Q10: =+P10+Q7 -> 0
B11: QTD Net | D11: =+C11+D7 -> 0 | E11: =+D11+E7 -> 0 | F11: =+E11+F7 -> 0 | G11: =+G7 -> 0 | H11: =+G11+H7 -> 0 | I11: =+H11+I7 -> 0 | J11: =+J7 -> 0 | K11: =+J11+K7 -> 0 | L11: =+K11+L7 -> 0 | M11: =+M7 -> 0 | N11: =+M11+N7 -> 0 | O11: =+N11+O7 -> 0
B12: Cash Balance | D12: =+Budget!E44 -> 0 | E12: =+Budget!F44 -> 0 | F12: =+Budget!G44 -> 0 | G12: =+Budget!H44 -> 0 | H12: =+Budget!I44 -> 0 | I12: =+Budget!J44 -> 0 | J12: =+Budget!K44 -> 0 | K12: =+Budget!L44 -> 0 | ... O12: =+Budget!P44 -> 0
B13: IRA Balance | D13: =+Budget!E46 -> 0 | E13: =+Budget!F46 -> 0 | F13: =+Budget!G46 -> 0 | G13: =+Budget!H46 -> 0 | H13: =+Budget!I46 -> 0 | I13: =+Budget!J46 -> 0 | J13: =+Budget!K46 -> 0 | K13: =+Budget!L46 -> 0 | ... O13: =+Budget!P46 -> 0
B15: Month From Comparison Sheet | D15: =+'Budget Actual Comparision'!$E$40 -> 0 | E15: =+'Budget Actual Comparision'!$E$40 -> 0 | F15: =+'Budget Actual Comparision'!$E$40 -> 0 | G15: =+'Budget Actual Comparision'!$E$40 -> 0 | H15: =+'Budget Actual Comparision'!$E$40 -> 0 | I15: =+'Budget Actual Comparision'!$E$40 -> 0 | J15: =+'Budget Actual Comparision'!$E$40 -> 0 | K15: =+'Budget Actual Comparision'!$E$40 -> 0 | ... O15: =+'Budget Actual Comparision'!$E$40 -> 0
B16: YTD From Comparison Sheet | D16: =+'Budget Actual Comparision'!$M$40 -> 0 | E16: =+'Budget Actual Comparision'!$M$40 -> 0 | F16: =+'Budget Actual Comparision'!$M$40 -> 0 | G16: =+'Budget Actual Comparision'!$M$40 -> 0 | H16: =+'Budget Actual Comparision'!$M$40 -> 0 | I16: =+'Budget Actual Comparision'!$M$40 -> 0 | J16: =+'Budget Actual Comparision'!$M$40 -> 0 | K16: =+'Budget Actual Comparision'!$M$40 -> 0 | ... O16: =+'Budget Actual Comparision'!$M$40 -> 0
B17: QTD From Comparison Sheet | D17: ='Budget Actual Comparision'!$I$40 -> 0 | E17: ='Budget Actual Comparision'!$I$40 -> 0 | F17: ='Budget Actual Comparision'!$I$40 -> 0 | G17: ='Budget Actual Comparision'!$I$40 -> 0 | H17: ='Budget Actual Comparision'!$I$40 -> 0 | I17: ='Budget Actual Comparision'!$I$40 -> 0 | J17: ='Budget Actual Comparision'!$I$40 -> 0 | K17: ='Budget Actual Comparision'!$I$40 -> 0 | ... O17: ='Budget Actual Comparision'!$I$40 -> 0
B18: Cash Balance From Comparison Sheet | D18: =+'Budget Actual Comparision'!$E$44 -> 0 | E18: =+'Budget Actual Comparision'!$E$44 -> 0 | F18: =+'Budget Actual Comparision'!$E$44 -> 0 | G18: =+'Budget Actual Comparision'!$E$44 -> 0 | H18: =+'Budget Actual Comparision'!$E$44 -> 0 | I18: =+'Budget Actual Comparision'!$E$44 -> 0 | J18: =+'Budget Actual Comparision'!$E$44 -> 0 | K18: =+'Budget Actual Comparision'!$E$44 -> 0 | ... O18: =+'Budget Actual Comparision'!$E$44 -> 0
B19: IRA Balance From Comparison Sheet | D19: =+'Budget Actual Comparision'!$E$46 -> 0 | E19: =+'Budget Actual Comparision'!$E$46 -> 0 | F19: =+'Budget Actual Comparision'!$E$46 -> 0 | G19: =+'Budget Actual Comparision'!$E$46 -> 0 | H19: =+'Budget Actual Comparision'!$E$46 -> 0 | I19: =+'Budget Actual Comparision'!$E$46 -> 0 | J19: =+'Budget Actual Comparision'!$E$46 -> 0 | K19: =+'Budget Actual Comparision'!$E$46 -> 0 | ... O19: =+'Budget Actual Comparision'!$E$46 -> 0
B22: Month Test | D22: =IF(MONTH(D$4=$C$1),D15-D9,"") -> 0 | E22: =IF(MONTH(E$4=$C$1),E15-E9,"") -> 0 | F22: =IF(MONTH(F$4=$C$1),F15-F9,"") -> 0 | G22: =IF(MONTH(G$4=$C$1),G15-G9,"") -> 0 | H22: =IF(MONTH(H$4=$C$1),H15-H9,"") -> 0 | I22: =IF(MONTH(I$4=$C$1),I15-I9,"") -> 0 | J22: =IF(MONTH(J$4=$C$1),J15-J9,"") -> 0 | K22: =IF(MONTH(K$4=$C$1),K15-K9,"") -> 0 | ... O22: =IF(MONTH(O$4=$C$1),O15-O9,"") -> 0
B23: YTD Test | D23: =IF(MONTH(D$4=$C$1),D16-D10,"") -> 0 | E23: =IF(MONTH(E$4=$C$1),E16-E10,"") -> 0 | F23: =IF(MONTH(F$4=$C$1),F16-F10,"") -> 0 | G23: =IF(MONTH(G$4=$C$1),G16-G10,"") -> 0 | H23: =IF(MONTH(H$4=$C$1),H16-H10,"") -> 0 | I23: =IF(MONTH(I$4=$C$1),I16-I10,"") -> 0 | J23: =IF(MONTH(J$4=$C$1),J16-J10,"") -> 0 | K23: =IF(MONTH(K$4=$C$1),K16-K10,"") -> 0 | ... O23: =IF(MONTH(O$4=$C$1),O16-O10,"") -> 0
B24: QTD Test | D24: =IF(MONTH(D$4=$C$1),D17-D11,"") -> 0 | E24: =IF(MONTH(E$4=$C$1),E17-E11,"") -> 0 | F24: =IF(MONTH(F$4=$C$1),F17-F11,"") -> 0 | G24: =IF(MONTH(G$4=$C$1),G17-G11,"") -> 0 | H24: =IF(MONTH(H$4=$C$1),H17-H11,"") -> 0 | I24: =IF(MONTH(I$4=$C$1),I17-I11,"") -> 0 | J24: =IF(MONTH(J$4=$C$1),J17-J11,"") -> 0 | K24: =IF(MONTH(K$4=$C$1),K17-K11,"") -> 0 | ... O24: =IF(MONTH(O$4=$C$1),O17-O11,"") -> 0
B25: Cash Test | D25: =IF(MONTH(D$4=$C$1),D18-D12,"") -> 0 | E25: =IF(MONTH(E$4=$C$1),E18-E12,"") -> 0 | F25: =IF(MONTH(F$4=$C$1),F18-F12,"") -> 0 | G25: =IF(MONTH(G$4=$C$1),G18-G12,"") -> 0 | H25: =IF(MONTH(H$4=$C$1),H18-H12,"") -> 0 | I25: =IF(MONTH(I$4=$C$1),I18-I12,"") -> 0 | J25: =IF(MONTH(J$4=$C$1),J18-J12,"") -> 0 | K25: =IF(MONTH(K$4=$C$1),K18-K12,"") -> 0 | ... O25: =IF(MONTH(O$4=$C$1),O18-O12,"") -> 0
B26: IRA Test | D26: =IF(MONTH(D$4=$C$1),D19-D13,"") -> 0 | E26: =IF(MONTH(E$4=$C$1),E19-E13,"") -> 0 | F26: =IF(MONTH(F$4=$C$1),F19-F13,"") -> 0 | G26: =IF(MONTH(G$4=$C$1),G19-G13,"") -> 0 | H26: =IF(MONTH(H$4=$C$1),H19-H13,"") -> 0 | I26: =IF(MONTH(I$4=$C$1),I19-I13,"") -> 0 | J26: =IF(MONTH(J$4=$C$1),J19-J13,"") -> 0 | K26: =IF(MONTH(K$4=$C$1),K19-K13,"") -> 0 | ... O26: =IF(MONTH(O$4=$C$1),O19-O13,"") -> 0
B28: Test of All Income in Budget | D28: =IF(D5=Budget!E14,"OK","Error") -> OK | E28: =IF(E5=Budget!F14,"OK","Error") -> OK | F28: =IF(F5=Budget!G14,"OK","Error") -> OK | G28: =IF(G5=Budget!H14,"OK","Error") -> OK | H28: =IF(H5=Budget!I14,"OK","Error") -> OK | I28: =IF(I5=Budget!J14,"OK","Error") -> OK | J28: =IF(J5=Budget!K14,"OK","Error") -> OK | K28: =IF(K5=Budget!L14,"OK","Error") -> OK | ... Q28: =IF(Q5=Budget!R14,"OK","Error") -> OK
B29: Test of All Expense in Budget | D29: =IF(D6=Budget!E38,"OK","Error") -> OK | E29: =IF(E6=Budget!F38,"OK","Error") -> OK | F29: =IF(F6=Budget!G38,"OK","Error") -> OK | G29: =IF(G6=Budget!H38,"OK","Error") -> OK | H29: =IF(H6=Budget!I38,"OK","Error") -> OK | I29: =IF(I6=Budget!J38,"OK","Error") -> OK | J29: =IF(J6=Budget!K38,"OK","Error") -> OK | K29: =IF(K6=Budget!L38,"OK","Error") -> OK | ... Q29: =IF(Q6=Budget!R38,"OK","Error") -> OK
B30: Test of Net All In Budget | D30: =IF(Budget!E40='Audit Sheet'!D7,"OK","Error") -> OK | E30: =IF(Budget!F40='Audit Sheet'!E7,"OK","Error") -> OK | F30: =IF(Budget!G40='Audit Sheet'!F7,"OK","Error") -> OK | G30: =IF(Budget!H40='Audit Sheet'!G7,"OK","Error") -> OK | H30: =IF(Budget!I40='Audit Sheet'!H7,"OK","Error") -> OK | I30: =IF(Budget!J40='Audit Sheet'!I7,"OK","Error") -> OK | J30: =IF(Budget!K40='Audit Sheet'!J7,"OK","Error") -> OK | K30: =IF(Budget!L40='Audit Sheet'!K7,"OK","Error") -> OK | ... Q30: =IF(Budget!R40='Audit Sheet'!Q7,"OK","Error") -> OK
B33: Sum of All Income in the Budget | D33: =SUM(Actual!E6:E13) -> 0 | E33: =SUM(Actual!F6:F13) -> 0 | F33: =SUM(Actual!G6:G13) -> 0 | G33: =SUM(Actual!H6:H13) -> 0 | H33: =SUM(Actual!I6:I13) -> 0 | I33: =SUM(Actual!J6:J13) -> 0 | J33: =SUM(Actual!K6:K13) -> 0 | K33: =SUM(Actual!L6:L13) -> 0 | ... O33: =SUM(Actual!P6:P13) -> 0 | Q33: =SUM(D33:O33) -> 0
B34: Sum of All Expense in Budget | D34: =SUM(Actual!E18:E37) -> 0 | E34: =SUM(Actual!F18:F37) -> 0 | F34: =SUM(Actual!G18:G37) -> 0 | G34: =SUM(Actual!H18:H37) -> 0 | H34: =SUM(Actual!I18:I37) -> 0 | I34: =SUM(Actual!J18:J37) -> 0 | J34: =SUM(Actual!K18:K37) -> 0 | K34: =SUM(Actual!L18:L37) -> 0 | ... O34: =SUM(Actual!P18:P37) -> 0 | Q34: =SUM(D34:O34) -> 0
B35: Net of All | D35: =+D33-D34 -> 0 | E35: =+E33-E34 -> 0 | F35: =+F33-F34 -> 0 | G35: =+G33-G34 -> 0 | H35: =+H33-H34 -> 0 | I35: =+I33-I34 -> 0 | J35: =+J33-J34 -> 0 | K35: =+K33-K34 -> 0 | ... O35: =+O33-O34 -> 0 | Q35: =SUM(D35:O35) -> 0
B37: Cash Balance | D37: =+Actual!E44 -> 0 | E37: =+Actual!F44 -> 0 | F37: =+Actual!G44 -> 0 | G37: =+Actual!H44 -> 0 | H37: =+Actual!I44 -> 0 | I37: =+Actual!J44 -> 0 | J37: =+Actual!K44 -> 0 | K37: =+Actual!L44 -> 0 | ... O37: =+Actual!P44 -> 0
B38: IRA Balance | D38: =+Actual!E46 -> 0 | E38: =+Actual!F46 -> 0 | F38: =+Actual!G46 -> 0 | G38: =+Actual!H46 -> 0 | H38: =+Actual!I46 -> 0 | I38: =+Actual!J46 -> 0 | J38: =+Actual!K46 -> 0 | K38: =+Actual!L46 -> 0 | ... O38: =+Actual!P46 -> 0
B39: Month Net | D39: =+D35 -> 0 | E39: =+E35 -> 0 | F39: =+F35 -> 0 | G39: =+G35 -> 0 | H39: =+H35 -> 0 | I39: =+I35 -> 0 | J39: =+J35 -> 0 | K39: =+K35 -> 0 | ... O39: =+O35 -> 0
B40: YTD Net | D40: =+C40+D35 -> 0 | E40: =+D40+E35 -> 0 | F40: =+E40+F35 -> 0 | G40: =+F40+G35 -> 0 | H40: =+G40+H35 -> 0 | I40: =+H40+I35 -> 0 | J40: =+I40+J35 -> 0 | K40: =+J40+K35 -> 0 | ... Q40: =+P40+Q35 -> 0
B41: QTD Net | D41: =+C41+D35 -> 0 | E41: =+D41+E35 -> 0 | F41: =+E41+F35 -> 0 | G41: =+G35 -> 0 | H41: =+G41+H35 -> 0 | I41: =+H41+I35 -> 0 | J41: =+J35 -> 0 | K41: =+J41+K35 -> 0 | L41: =+K41+L35 -> 0 | M41: =+M35 -> 0 | N41: =+M41+N35 -> 0 | O41: =+N41+O35 -> 0
B43: Month From Comparison Sheet | D43: =+'Budget Actual Comparision'!$D$40 -> 0 | E43: =+'Budget Actual Comparision'!$D$40 -> 0 | F43: =+'Budget Actual Comparision'!$D$40 -> 0 | G43: =+'Budget Actual Comparision'!$D$40 -> 0 | H43: =+'Budget Actual Comparision'!$D$40 -> 0 | I43: =+'Budget Actual Comparision'!$D$40 -> 0 | J43: =+'Budget Actual Comparision'!$D$40 -> 0 | K43: =+'Budget Actual Comparision'!$D$40 -> 0 | ... O43: =+'Budget Actual Comparision'!$D$40 -> 0
B44: YTD From Comparison Sheet | D44: =+'Budget Actual Comparision'!$L$40 -> 0 | E44: =+'Budget Actual Comparision'!$L$40 -> 0 | F44: =+'Budget Actual Comparision'!$L$40 -> 0 | G44: =+'Budget Actual Comparision'!$L$40 -> 0 | H44: =+'Budget Actual Comparision'!$L$40 -> 0 | I44: =+'Budget Actual Comparision'!$L$40 -> 0 | J44: =+'Budget Actual Comparision'!$L$40 -> 0 | K44: =+'Budget Actual Comparision'!$L$40 -> 0 | ... O44: =+'Budget Actual Comparision'!$L$40 -> 0
B45: QTD From Comparison Sheet | D45: ='Budget Actual Comparision'!$H$40 -> 0 | E45: ='Budget Actual Comparision'!$H$40 -> 0 | F45: ='Budget Actual Comparision'!$H$40 -> 0 | G45: ='Budget Actual Comparision'!$H$40 -> 0 | H45: ='Budget Actual Comparision'!$H$40 -> 0 | I45: ='Budget Actual Comparision'!$H$40 -> 0 | J45: ='Budget Actual Comparision'!$H$40 -> 0 | K45: ='Budget Actual Comparision'!$H$40 -> 0 | ... O45: ='Budget Actual Comparision'!$H$40 -> 0
B46: Cash Balance From Comparison Sheet | D46: =+'Budget Actual Comparision'!$D$44 -> 0 | E46: =+'Budget Actual Comparision'!$D$44 -> 0 | F46: =+'Budget Actual Comparision'!$D$44 -> 0 | G46: =+'Budget Actual Comparision'!$D$44 -> 0 | H46: =+'Budget Actual Comparision'!$D$44 -> 0 | I46: =+'Budget Actual Comparision'!$D$44 -> 0 | J46: =+'Budget Actual Comparision'!$D$44 -> 0 | K46: =+'Budget Actual Comparision'!$D$44 -> 0 | ... O46: =+'Budget Actual Comparision'!$D$44 -> 0
B47: IRA Balance From Comparison Sheet | D47: =+'Budget Actual Comparision'!$D$46 -> 0 | E47: =+'Budget Actual Comparision'!$D$46 -> 0 | F47: =+'Budget Actual Comparision'!$D$46 -> 0 | G47: =+'Budget Actual Comparision'!$D$46 -> 0 | H47: =+'Budget Actual Comparision'!$D$46 -> 0 | I47: =+'Budget Actual Comparision'!$D$46 -> 0 | J47: =+'Budget Actual Comparision'!$D$46 -> 0 | K47: =+'Budget Actual Comparision'!$D$46 -> 0 | ... O47: =+'Budget Actual Comparision'!$D$46 -> 0
B49: Month From Comparison Sheet | D49: =IF(MONTH(D$4=$C$1),D43-D39,"") -> 0 | E49: =IF(MONTH(E$4=$C$1),E43-E39,"") -> 0 | F49: =IF(MONTH(F$4=$C$1),F43-F39,"") -> 0 | G49: =IF(MONTH(G$4=$C$1),G43-G39,"") -> 0 | H49: =IF(MONTH(H$4=$C$1),H43-H39,"") -> 0 | I49: =IF(MONTH(I$4=$C$1),I43-I39,"") -> 0 | J49: =IF(MONTH(J$4=$C$1),J43-J39,"") -> 0 | K49: =IF(MONTH(K$4=$C$1),K43-K39,"") -> 0 | ... O49: =IF(MONTH(O$4=$C$1),O43-O39,"") -> 0
B50: YTD Test | D50: =IF(MONTH(D$4=$C$1),D44-D40,"") -> 0 | E50: =IF(MONTH(E$4=$C$1),E44-E40,"") -> 0 | F50: =IF(MONTH(F$4=$C$1),F44-F40,"") -> 0 | G50: =IF(MONTH(G$4=$C$1),G44-G40,"") -> 0 | H50: =IF(MONTH(H$4=$C$1),H44-H40,"") -> 0 | I50: =IF(MONTH(I$4=$C$1),I44-I40,"") -> 0 | J50: =IF(MONTH(J$4=$C$1),J44-J40,"") -> 0 | K50: =IF(MONTH(K$4=$C$1),K44-K40,"") -> 0 | ... O50: =IF(MONTH(O$4=$C$1),O44-O40,"") -> 0
B51: QTD Test | D51: =IF(MONTH(D$4=$C$1),D45-D41,"") -> 0 | E51: =IF(MONTH(E$4=$C$1),E45-E41,"") -> 0 | F51: =IF(MONTH(F$4=$C$1),F45-F41,"") -> 0 | G51: =IF(MONTH(G$4=$C$1),G45-G41,"") -> 0 | H51: =IF(MONTH(H$4=$C$1),H45-H41,"") -> 0 | I51: =IF(MONTH(I$4=$C$1),I45-I41,"") -> 0 | J51: =IF(MONTH(J$4=$C$1),J45-J41,"") -> 0 | K51: =IF(MONTH(K$4=$C$1),K45-K41,"") -> 0 | ... O51: =IF(MONTH(O$4=$C$1),O45-O41,"") -> 0
B52: Cash Test | D52: =IF(MONTH(D$4=$C$1),D46-D37,"") -> 0 | E52: =IF(MONTH(E$4=$C$1),E46-E37,"") -> 0 | F52: =IF(MONTH(F$4=$C$1),F46-F37,"") -> 0 | G52: =IF(MONTH(G$4=$C$1),G46-G37,"") -> 0 | H52: =IF(MONTH(H$4=$C$1),H46-H37,"") -> 0 | I52: =IF(MONTH(I$4=$C$1),I46-I37,"") -> 0 | J52: =IF(MONTH(J$4=$C$1),J46-J37,"") -> 0 | K52: =IF(MONTH(K$4=$C$1),K46-K37,"") -> 0 | ... O52: =IF(MONTH(O$4=$C$1),O46-O37,"") -> 0
B53: IRA Test | D53: =IF(MONTH(D$4=$C$1),D47-D38,"") -> 0 | E53: =IF(MONTH(E$4=$C$1),E47-E38,"") -> 0 | F53: =IF(MONTH(F$4=$C$1),F47-F38,"") -> 0 | G53: =IF(MONTH(G$4=$C$1),G47-G38,"") -> 0 | H53: =IF(MONTH(H$4=$C$1),H47-H38,"") -> 0 | I53: =IF(MONTH(I$4=$C$1),I47-I38,"") -> 0 | J53: =IF(MONTH(J$4=$C$1),J47-J38,"") -> 0 | K53: =IF(MONTH(K$4=$C$1),K47-K38,"") -> 0 | ... O53: =IF(MONTH(O$4=$C$1),O47-O38,"") -> 0
B55: Test of All Income in Budget | D55: =IF(D33=Actual!E14,"OK","Error") -> OK | E55: =IF(E33=Actual!F14,"OK","Error") -> OK | F55: =IF(F33=Actual!G14,"OK","Error") -> OK | G55: =IF(G33=Actual!H14,"OK","Error") -> OK | H55: =IF(H33=Actual!I14,"OK","Error") -> OK | I55: =IF(I33=Actual!J14,"OK","Error") -> OK | J55: =IF(J33=Actual!K14,"OK","Error") -> OK | K55: =IF(K33=Actual!L14,"OK","Error") -> OK | ... Q55: =IF(Q33=Actual!R14,"OK","Error") -> OK
B56: Test of All Expense in Budget | D56: =IF(D34=Actual!E38,"OK","Error") -> OK | E56: =IF(E34=Actual!F38,"OK","Error") -> OK | F56: =IF(F34=Actual!G38,"OK","Error") -> OK | G56: =IF(G34=Actual!H38,"OK","Error") -> OK | H56: =IF(H34=Actual!I38,"OK","Error") -> OK | I56: =IF(I34=Actual!J38,"OK","Error") -> OK | J56: =IF(J34=Actual!K38,"OK","Error") -> OK | K56: =IF(K34=Actual!L38,"OK","Error") -> OK | ... Q56: =IF(Q34=Actual!R38,"OK","Error") -> OK
B57: Test of Net All In Budget | D57: =IF(D35=Actual!E40,"OK","Error") -> OK | E57: =IF(E35=Actual!F40,"OK","Error") -> OK | F57: =IF(F35=Actual!G40,"OK","Error") -> OK | G57: =IF(G35=Actual!H40,"OK","Error") -> OK | H57: =IF(H35=Actual!I40,"OK","Error") -> OK | I57: =IF(I35=Actual!J40,"OK","Error") -> OK | J57: =IF(J35=Actual!K40,"OK","Error") -> OK | K57: =IF(K35=Actual!L40,"OK","Error") -> OK | ... Q57: =IF(Q35=Actual!R40,"OK","Error") -> OK
