Workbook
Name CmpIdSelected: INDIRECT(ADDRESS(CmpSelectedOnRow,1,1,TRUE,"Cmp"))
Name CmpSelectedOnRow: IFERROR(MATCH('Concept Note'!$C$4,Cmp!$D:$D,0),IFERROR(MATCH('Concept Note'!$C$4,Cmp!$E:$E,0),IFERROR(MATCH('Concept Note'!$C$4,Cmp!$F:$F,0),IFERROR(MATCH('Concept Note'!$C$4,Cmp!$G:$G,0),""))))
Name ComponentSelected: 'Concept Note'!$C$4
Name Country_Applicant: Definitions!$N$3:$N$204
Name DataSrcInCmp: OFFSET('Data src'!$D$1,MATCH(CmpIdSelected,'Data src'!$A:$A,0)-1,0,COUNTIF('Data src'!$A:$A,CmpIdSelected),1)
Name ImpactIndInCmp: OFFSET('Impact ind'!$E$1,MATCH(CmpIdSelected,'Impact ind'!$A:$A,0)-1,0,COUNTIF('Impact ind'!$A:$A,CmpIdSelected),1)
Name LangOffset: Translations!$C$1
Name Language: 'Concept Note'!$P$1
Name ModulesInCmp: OFFSET(Modules!$D$1,MATCH(CmpIdSelected,Modules!$A:$A,0)-1,0,COUNTIF(Modules!$A:$A,CmpIdSelected),1)
Name MonthIndex: Definitions!$M$3
Name Months: Definitions!$G$3:$G$15
Name MonthSelected: 'Concept Note'!$C$6
Name OutcomeIndInCmp: OFFSET('Outcome ind'!$E$1,MATCH(CmpIdSelected,'Outcome ind'!$A:$A,0)-1,0,COUNTIF('Outcome ind'!$A:$A,CmpIdSelected),1)
Name PRs: 'Concept Note'!$H$5
Name PRsInApplicant: OFFSET(Definitions!$R$3,MATCH(VLOOKUP('Concept Note'!$C$3,Definitions!D:E,2,FALSE),Definitions!G:G,0)-3,0,COUNTIF(Definitions!G:G,VLOOKUP('Concept Note'!$C$3,Definitions!D:E,2,FALSE)),1)
Name StartYearSelected: 'Concept Note'!$C$5
Name TiedTo: Definitions!$U$3:$U$7
Name Years: Definitions!$A$3:$A$6
Name YearSelected: 'Concept Note'!$C$5

Sheet Instructions en
A1: =Translations!B81 -> Modular Approach - Concept Note | O1: =Translations!$B$80 -> Language: | P1: English
A2: =Translations!$B$7 -> A. Program details
A3: =Translations!$B$8 -> Country / Applicant: | D3: =Translations!B72 -> Please select… | H3: =Translations!$B$13 -> Principal Recipients | S3: =IFERROR(VLOOKUP(K3,Definitions!R:S,2,FALSE),"") | U3: =Translations!$B$77 -> Total requested amount
A4: =Translations!$B$9 -> Component: | D4: =Translations!B72 -> Please select… | S4: =IFERROR(VLOOKUP(K4,Definitions!R:S,2,FALSE),"")
A5: =Translations!$B$10 -> Start Year: | D5: =Translations!B72 -> Please select… | H5: =Translations!$B$14 -> (Please select from list or add a new one) | S5: =IFERROR(VLOOKUP(K5,Definitions!R:S,2,FALSE),"") | U5: =Translations!$B$78 -> Indicative | Y5: =SUMIF(A:A,Translations!$A$84,F:F) -> 0
A6: =Translations!$B$11 -> Start Month: | D6: =Translations!B72 -> Please select… | S6: =IFERROR(VLOOKUP(K6,Definitions!R:S,2,FALSE),"") | U6: =Translations!$B$79 -> Above indicative | Y6: =SUMIF(J:J,Translations!$A$85,Q:Q) -> 0
A8: =Translations!$B$25 -> B. Program goals and impact indicators
A9: =Translations!$B$26 -> Goals:
A10: 1
A11: 2
A12: 3
A14: =Translations!$B$27 -> Linked to goal(s) # | B14: =Translations!$B$28 -> Impact indicator | I14: =Translations!$B$29 -> Baseline | O14: =Translations!$B$30 -> Targets | U14: =Translations!$B$73 -> Comments and Assumptions
I15: =Translations!$B$31 -> Value | K15: =Translations!$B$32 -> Year | L15: =Translations!$B$33 -> Source | O15: =Translations!$B$34 -> Year 1 | Q15: =Translations!$B$35 -> Year 2 | S15: =Translations!$B$36 -> Year 3
O16: =IFERROR(IF(MonthIndex<7,StartYearSelected,StartYearSelected+1),"") -> Please select… | Q16: =IFERROR(O16+1,"") | S16: =IFERROR(Q16+1,"")
B17: =Translations!B72 -> Please select… | L17: =Translations!$B$72 -> Please select…
B18: =Translations!B72 -> Please select… | L18: =Translations!$B$72 -> Please select…
B19: =Translations!B72 -> Please select… | L19: =Translations!$B$72 -> Please select…
B20: =Translations!B72 -> Please select… | L20: =Translations!$B$72 -> Please select…
B21: =Translations!B72 -> Please select… | L21: =Translations!$B$72 -> Please select…
A23: =Translations!$B$41 -> C. Program objectives and outcome indicators
A24: =Translations!$B$42 -> Objectives:
A25: 1
A26: 2
A27: 3
A28: 4
A29: 5
A30: 6
A32: =Translations!$B$43 -> Linked to objective(s) # | B32: =Translations!B44 -> Outcome indicator | I32: =Translations!$B$29 -> Baseline | O32: =Translations!$B$30 -> Targets | U32: =Translations!$B$73 -> Comments and Assumptions
I33: =Translations!$B$31 -> Value | K33: =Translations!$B$32 -> Year | L33: =Translations!$B$33 -> Source | O33: =Translations!$B$34 -> Year 1 | Q33: =Translations!$B$35 -> Year 2 | S33: =Translations!$B$36 -> Year 3
O34: =O16 -> Please select… | Q34: =Q16 | S34: =S16
B35: =Translations!$B$72 -> Please select… | L35: =Translations!$B$72 -> Please select…
B36: =Translations!$B$72 -> Please select… | L36: =Translations!$B$72 -> Please select…
B37: =Translations!$B$72 -> Please select… | L37: =Translations!$B$72 -> Please select…
B38: =Translations!$B$72 -> Please select… | L38: =Translations!$B$72 -> Please select…
B39: =Translations!$B$72 -> Please select… | L39: =Translations!$B$72 -> Please select…
A41: =Translations!B74 -> D. Modules
A43: =Translations!$B$75 -> Module | C43: 1 | D43: =Translations!$B$72 -> Please select…
A44: =Translations!$B$76 -> Measurement framework for module
A45: =Translations!$B$49 -> Coverage/Output indicator | D45: =Translations!$B$67 -> Responsible Principal Recipient(s) | E45: =Translations!$B$66 -> Tied to | G45: =Translations!$B$29 -> Baseline | M45: =Translations!$B$30 -> Targets | S45: =Translations!$B$82 -> Target assumptions
M46: =Translations!$B$34 -> Year 1 | O46: =Translations!$B$35 -> Year 2 | Q46: =Translations!$B$36 -> Year 3 | S46: =Translations!$B$83 -> Please describe: 1) overall assumptions used in calculating targets, 2) anticipated rate of scale-up, 3) population size estimates, 4) description of indicator/package of services, 5) data source, 6) other relevant information
G47: N # | H47: % | I47: =Translations!$B$32 -> Year | J47: =Translations!$B$33 -> Source | M47: N # | N47: % | O47: N # | P47: % | Q47: N # | R47: %
G48: D # | M48: D # | O48: D # | Q48: D #
D49: =Translations!$B$72 -> Please select… | E49: =Translations!$B$72 -> Please select… | H49: =IF($G51<>"",$G49/$G51,"") | J49: =Translations!$B$72 -> Please select… | K49: =Translations!$B$78 -> Indicative | N49: =IF(M50<>"",M49/M50,"") | P49: =IF(O50<>"",O49/O50,"") | R49: =IF(Q50<>"",Q49/Q50,"")
K51: =Translations!$B$79 -> Above indicative | N51: =IF(M52<>"",M51/M52,"") | P51: =IF(O52<>"",O51/O52,"") | R51: =IF(Q52<>"",Q51/Q52,"")
D53: =Translations!$B$72 -> Please select… | E53: =Translations!$B$72 -> Please select… | H53: =IF($G55<>"",$G53/$G55,"") | J53: =Translations!$B$72 -> Please select… | K53: =Translations!$B$78 -> Indicative | N53: =IF(M54<>"",M53/M54,"") | P53: =IF(O54<>"",O53/O54,"") | R53: =IF(Q54<>"",Q53/Q54,"")
K55: =Translations!$B$79 -> Above indicative | N55: =IF(M56<>"",M55/M56,"") | P55: =IF(O56<>"",O55/O56,"") | R55: =IF(Q56<>"",Q55/Q56,"")
D57: =Translations!$B$72 -> Please select… | E57: =Translations!$B$72 -> Please select… | H57: =IF($G59<>"",$G57/$G59,"") | J57: =Translations!$B$72 -> Please select… | K57: =Translations!$B$78 -> Indicative | N57: =IF(M58<>"",M57/M58,"") | P57: =IF(O58<>"",O57/O58,"") | R57: =IF(Q58<>"",Q57/Q58,"")
K59: =Translations!$B$79 -> Above indicative | N59: =IF(M60<>"",M59/M60,"") | P59: =IF(O60<>"",O59/O60,"") | R59: =IF(Q60<>"",Q59/Q60,"")
A61: =Translations!$B$87 -> Module budget
A62: =Translations!$B$84 -> Indicative request for entire module | F62: =SUMIF($K65:$K84,Translations!$A$78,$M65:$M84)+SUMIF($K65:$K84,Translations!$A$78,$O65:$O84)+SUMIF($K65:$K84,Translations!$A$78,$Q65:$Q84) -> 0 | J62: =Translations!$B$85 -> Above indicative request for entire module | Q62: =SUMIF($K65:$K84,Translations!$A$79,$M65:$M84)+SUMIF($K65:$K84,Translations!$A$79,$O65:$O84)+SUMIF($K65:$K84,Translations!$A$79,$Q65:$Q84) -> 0
A63: =Translations!$B$86 -> Intervention | D63: =Translations!$B$88 -> Description of Intervention | J63: =Translations!$B$67 -> Responsible Principal Recipient(s) | K63: =Translations!$B$90 -> Intervention budget (request to the Global Fund only) | S63: =Translations!$B$91 -> Cost Assumptions for the request to the Global Fund | Z63: =Translations!$B$93 -> Other funding received for this intervention (including scope of activities funded)
D64: =Translations!$B$89 -> Please describe 1) rationale for Global Fund support, 2) linkages to national strategic plan, 3) target population & geographic scope, 4) implementation approach, and 5) other relevant information. Please differentiate between scope of indicative and above indicative request | M64: =Translations!$B$34 -> Year 1 | O64: =Translations!$B$35 -> Year 2 | Q64: =Translations!$B$36 -> Year 3 | S64: =Translations!$B$92 -> Please describe: 1) cost assumptions and data sources, 2) key activities, 3) other relevant information. Please differentiate between indicative and above indicative
A65: =Translations!$A$72 -> Please select… | K65: =Translations!$B$78 -> Indicative
K66: =Translations!$B$79 -> Above indicative
K67: =Translations!$B$78 -> Indicative
K68: =Translations!$B$79 -> Above indicative
A69: =Translations!$A$72 -> Please select… | K69: =Translations!$B$78 -> Indicative
K70: =Translations!$B$79 -> Above indicative
K71: =Translations!$B$78 -> Indicative
K72: =Translations!$B$79 -> Above indicative
A73: =Translations!$A$72 -> Please select… | K73: =Translations!$B$78 -> Indicative
K74: =Translations!$B$79 -> Above indicative
K75: =Translations!$B$78 -> Indicative
K76: =Translations!$B$79 -> Above indicative
A77: =Translations!$A$72 -> Please select… | K77: =Translations!$B$78 -> Indicative
K78: =Translations!$B$79 -> Above indicative
K79: =Translations!$B$78 -> Indicative
K80: =Translations!$B$79 -> Above indicative
A81: =Translations!$A$72 -> Please select… | K81: =Translations!$B$78 -> Indicative
K82: =Translations!$B$79 -> Above indicative
K83: =Translations!$B$78 -> Indicative
K84: =Translations!$B$79 -> Above indicative

Sheet Instructions fr
A1: =Translations!C81 -> Démarche modulaire : note conceptuelle | O1: =Translations!$C$80 -> Langue : | P1: Français
A2: =Translations!$C$7 -> A. Détails du programme
A3: =Translations!$C$8 -> Pays / Candidat : | D3: =Translations!C72 -> Veuillez sélectionner… | H3: =Translations!$C$13 -> Récipiendaires principaux | U3: =Translations!$C$77 demandé -> #NAME?
A4: =Translations!$C$9 -> Composante : | D4: =Translations!C72 -> Veuillez sélectionner…
A5: =Translations!$C$10 -> Année de début : | D5: =Translations!C72 -> Veuillez sélectionner… | H5: =Translations!$C$14 -> (Veuillez choisir un récipiendaire principal dans la liste ou en ajouter un nouveau) | U5: =Translations!$C$78 -> Indicatif | Y5: 0
A6: =Translations!$C$11 -> Mois de début : | D6: =Translations!C72 -> Veuillez sélectionner… | U6: =Translations!$C$79 -> Au-delà du montant indicatif | Y6: 0
A8: =Translations!$C$25 -> B. Buts du programme et indicateurs d'impact
A9: =Translations!$C$26 -> Buts :
A10: 1
A11: 2
A12: 3
A14: =Translations!$C$27 -> Lié au(x) but(s) n° | B14: =Translations!$C$28 -> Indicateur d'impact | I14: =Translations!$C$29 -> Données de référence | O14: =Translations!$C$30 -> Cibles | U14: =Translations!$C$73 -> Remarques et hypothèses
I15: =Translations!$C$31 -> Valeur | K15: =Translations!$C$32 -> Année | L15: =Translations!$C$33 -> Source | O15: =Translations!$C$34 -> Année 1 | Q15: =Translations!$C$35 -> Année 2 | S15: =Translations!$C$36 -> Année 3
O16: =IFERROR(IF(MonthIndex<7,StartYearSelected,StartYearSelected+1),"") -> Please select… | Q16: =IFERROR(O16+1,"") | S16: =IFERROR(Q16+1,"")
B17: =Translations!$C$72 -> Veuillez sélectionner… | L17: =Translations!$C$72 -> Veuillez sélectionner…
B18: =Translations!$C$72 -> Veuillez sélectionner… | L18: =Translations!$C$72 -> Veuillez sélectionner…
B19: Please select… | L19: =Translations!$C$72 -> Veuillez sélectionner…
B20: Please select… | L20: =Translations!$C$72 -> Veuillez sélectionner…
B21: Please select… | L21: =Translations!$C$72 -> Veuillez sélectionner…
A23: =Translations!$C$41 -> C. Objectifs du programme et indicateurs d'effets
A24: =Translations!$C$42 -> Objectifs :
A25: 1
A26: 2
A27: 3
A28: 4
A29: 5
A30: 6
A32: =Translations!$C$43 -> Lié à ou aux objectifs n° | B32: =Translations!C44 -> Indicateur d'effet | I32: =Translations!$C$29 -> Données de référence | O32: =Translations!$C$30 -> Cibles | U32: =Translations!$C$73 -> Remarques et hypothèses
I33: =Translations!$C$31 -> Valeur | K33: =Translations!$C$32 -> Année | L33: =Translations!$C$33 -> Source | O33: =Translations!$C$34 -> Année 1 | Q33: =Translations!$C$35 -> Année 2 | S33: =Translations!$C$36 -> Année 3
O34: =O16 -> Please select… | Q34: =Q16 | S34: =S16
B35: =Translations!$C$72 -> Veuillez sélectionner… | L35: =Translations!$C$72 -> Veuillez sélectionner…
B36: =Translations!$C$72 -> Veuillez sélectionner… | L36: =Translations!$C$72 -> Veuillez sélectionner…
B37: =Translations!$C$72 -> Veuillez sélectionner… | L37: =Translations!$C$72 -> Veuillez sélectionner…
B38: =Translations!$C$72 -> Veuillez sélectionner… | L38: =Translations!$C$72 -> Veuillez sélectionner…
B39: =Translations!$C$72 -> Veuillez sélectionner… | L39: =Translations!$C$72 -> Veuillez sélectionner…
A41: =Translations!$C$74 -> D. Modules
A43: =Translations!$C$75 -> Module | C43: 1 | D43: =Translations!$C$72 -> Veuillez sélectionner…
A44: =Translations!$C$76 -> Cadre de mesure du module
A45: =Translations!$C$49 -> Indicateur de couverture/produit | D45: =Translations!$C$67 -> Récipiendaires principaux responsables | E45: =Translations!$C$66 -> Lié à | G45: =Translations!$C$29 -> Données de référence | M45: =Translations!$C$30 -> Cibles | S45: =Translations!$C$82 -> Hypothèses pour les cibles
M46: =Translations!$C$34 -> Année 1 | O46: =Translations!$C$35 -> Année 2 | Q46: =Translations!$C$36 -> Année 3 | S46: =Translations!$C$83 -> Veuillez décrire : 1) les hypothèses générales utilisées pour le calcul des cibles, 2) le taux d'intensification prévisionnel, 3) les estimations démographiques, 4) l'indicateur ou paquet de services, 5) les sources de données, 6) toute autre information pertinente
G47: N | H47: % | I47: =Translations!$C$32 -> Année | J47: =Translations!$C$33 -> Source | M47: N | N47: % | O47: N | P47: % | Q47: N | R47: %
G48: D | M48: D | O48: D | Q48: D
D49: =Translations!$C$72 -> Veuillez sélectionner… | E49: =Translations!$C$72 -> Veuillez sélectionner… | H49: =IF($G51<>"",$G49/$G51,"") | J49: =Translations!$C$72 -> Veuillez sélectionner… | K49: =Translations!$C$78 -> Indicatif | N49: =IF(M50<>"",M49/M50,"") | P49: =IF(O50<>"",O49/O50,"") | R49: =IF(Q50<>"",Q49/Q50,"")
K51: =Translations!$C$79 -> Au-delà du montant indicatif | N51: =IF(M52<>"",M51/M52,"") | P51: =IF(O52<>"",O51/O52,"") | R51: =IF(Q52<>"",Q51/Q52,"")
D53: =Translations!$C$72 -> Veuillez sélectionner… | E53: =Translations!$C$72 -> Veuillez sélectionner… | H53: =IF($G55<>"",$G53/$G55,"") | J53: =Translations!$C$72 -> Veuillez sélectionner… | K53: =Translations!$C$78 -> Indicatif | N53: =IF(M54<>"",M53/M54,"") | P53: =IF(O54<>"",O53/O54,"") | R53: =IF(Q54<>"",Q53/Q54,"")
K55: =Translations!$C$79 -> Au-delà du montant indicatif | N55: =IF(M56<>"",M55/M56,"") | P55: =IF(O56<>"",O55/O56,"") | R55: =IF(Q56<>"",Q55/Q56,"")
D57: =Translations!$C$72 -> Veuillez sélectionner… | E57: =Translations!$C$72 -> Veuillez sélectionner… | H57: =IF($G59<>"",$G57/$G59,"") | J57: =Translations!$C$72 -> Veuillez sélectionner… | K57: =Translations!$C$78 -> Indicatif | N57: =IF(M58<>"",M57/M58,"") | P57: =IF(O58<>"",O57/O58,"") | R57: =IF(Q58<>"",Q57/Q58,"")
K59: =Translations!$C$79 -> Au-delà du montant indicatif | N59: =IF(M60<>"",M59/M60,"") | P59: =IF(O60<>"",O59/O60,"") | R59: =IF(Q60<>"",Q59/Q60,"")
A61: =Translations!$C$87 -> Budget consacré au module
A62: =Translations!$C$84 -> Demande de financement indicatif pour le module complet | F62: 0 | J62: =Translations!$C$85 -> Demande de financement au-delà du montant indicatif pour le module complet | Q62: 0
A63: =Translations!$C$86 -> Intervention | D63: =Translations!$C$88 -> Description de l'intervention | J63: =Translations!$C$67 -> Récipiendaires principaux responsables | K63: =Translations!$C$90 -> Budget consacré à l'intervention (demande adressée au Fonds mondial uniquement) | S63: =Translations!$C$91 -> Hypothèses des coûts pour la demande adressée au Fonds mondial | Z63: =Translations!$C$93 -> Autres financements obtenus pour cette intervention (précisez la portée des activités financées)
D64: =Translations!$C$89 -> Veuillez décrire 1) le fondement du soutien du Fonds mondial, 2) les liens avec le plan stratégique national, 3) la population ciblée et le champ d'application géographique, 4) la démarche de mise en œuvre, 5) toute autre information pertinente. Veuillez différencier le champ d'application de la demande de financement indicatif de celui de la demande de financement au-delà du montant indicatif | M64: =Translations!$C$34 -> Année 1 | O64: =Translations!$C$35 -> Année 2 | Q64: =Translations!$C$36 -> Année 3 | S64: =Translations!$C$92 -> Veuillez décrire : 1) les hypothèses de coûts et les sources de données, 2) les activités clés, 3) toute autre information pertinente. Veuillez différencier le financement indicatif du financement au-delà du montant indicatif
A65: =Translations!$C$72 -> Veuillez sélectionner… | K65: =Translations!$C$78 -> Indicatif
K66: =Translations!$C$79 -> Au-delà du montant indicatif
K67: =Translations!$C$78 -> Indicatif
K68: =Translations!$C$79 -> Au-delà du montant indicatif
A69: =Translations!$C$72 -> Veuillez sélectionner… | K69: =Translations!$C$78 -> Indicatif
K70: =Translations!$C$79 -> Au-delà du montant indicatif
K71: =Translations!$C$78 -> Indicatif
K72: =Translations!$C$79 -> Au-delà du montant indicatif
A73: =Translations!$C$72 -> Veuillez sélectionner… | K73: =Translations!$C$78 -> Indicatif
K74: =Translations!$C$79 -> Au-delà du montant indicatif
K75: =Translations!$C$78 -> Indicatif
K76: =Translations!$C$79 -> Au-delà du montant indicatif
A77: Please select… | K77: =Translations!$C$78 -> Indicatif
K78: =Translations!$C$79 -> Au-delà du montant indicatif
K79: =Translations!$C$78 -> Indicatif
K80: =Translations!$C$79 -> Au-delà du montant indicatif
A81: Please select… | K81: =Translations!$C$78 -> Indicatif
K82: =Translations!$C$79 -> Au-delà du montant indicatif
K83: =Translations!$C$78 -> Indicatif
K84: =Translations!$C$79 -> Au-delà du montant indicatif

Sheet Instructions es
A1: =Translations!D81 -> Enfoque modular - nota conceptual | O1: =Translations!D80 -> Idioma: | P1: Inglés
A2: =Translations!$D$7 -> A. Datos del programa
A3: =Translations!$D$8 -> País / Solicitante: | D3: =Translations!$D$72 -> Seleccione… | H3: =Translations!$D$13 -> Receptores principales | U3: =Translations!$D$77 solicitado -> #NAME?
A4: =Translations!$D$9 -> Componente: | D4: =Translations!$D$72 -> Seleccione…
A5: =Translations!$D$10 -> Año de inicio: | D5: =Translations!$D$72 -> Seleccione… | H5: =Translations!$D$14 -> (seleccione uno de la lista o añada uno nuevo) | U5: =Translations!$D$78 -> Indicativo | Y5: 0
A6: =Translations!$D$11 -> Mes de inicio: | D6: =Translations!$D$72 -> Seleccione… | U6: =Translations!$D$79 -> Por encima del indicativo | Y6: 0
A8: =Translations!$D$25 -> B. Metas del programa e indicadores de impacto
A9: =Translations!$D$26 -> Metas:
A10: 1
A11: 2
A12: 3
A14: =Translations!$D$27 -> Vinculado a lo(s) objetivos(s) nº | B14: =Translations!$D$28 -> Indicador de impacto | I14: =Translations!$D$29 -> Línea de base | O14: =Translations!$D$30 -> Metas | U14: =Translations!$D$73 -> Comentarios y supuestos
I15: =Translations!$D$31 -> Valor | K15: =Translations!$D$32 -> Año | L15: =Translations!$D$33 -> Fuente | O15: =Translations!$D$34 -> Año 1 | Q15: =Translations!$D$35 -> Año 2 | S15: =Translations!$D$36 -> Año 3
O16: =IFERROR(IF(MonthIndex<7,StartYearSelected,StartYearSelected+1),"") -> Please select… | Q16: =IFERROR(O16+1,"") | S16: =IFERROR(Q16+1,"")
B17: =Translations!$D$72 -> Seleccione… | L17: =Translations!$D$72 -> Seleccione…
B18: =Translations!$D$72 -> Seleccione… | L18: =Translations!$D$72 -> Seleccione…
B19: =Translations!$D$72 -> Seleccione… | L19: =Translations!$D$72 -> Seleccione…
B20: =Translations!$D$72 -> Seleccione… | L20: =Translations!$D$72 -> Seleccione…
B21: =Translations!$D$72 -> Seleccione… | L21: =Translations!$D$72 -> Seleccione…
A23: =Translations!$D$41 -> C. Objetivos del programa e indicadores de resultados
A24: =Translations!$D$42 -> Objetivos:
A25: 1
A26: 2
A27: 3
A28: 4
A29: 5
A30: 6
A32: =Translations!$D$43 -> Vinculado al (los) objetivo(s) nº | B32: =Translations!D44 -> Indicador de resultados | I32: =Translations!$D$29 -> Línea de base | O32: =Translations!$D$30 -> Metas | U32: =Translations!$D$73 -> Comentarios y supuestos
I33: =Translations!$D$31 -> Valor | K33: =Translations!$D$32 -> Año | L33: =Translations!$D$33 -> Fuente | O33: =Translations!$D$34 -> Año 1 | Q33: =Translations!$D$35 -> Año 2 | S33: =Translations!$D$36 -> Año 3
O34: =O16 -> Please select… | Q34: =Q16 | S34: =S16
B35: =Translations!$D$72 -> Seleccione… | L35: =Translations!$D$72 -> Seleccione…
B36: =Translations!$D$72 -> Seleccione… | L36: =Translations!$D$72 -> Seleccione…
B37: =Translations!$D$72 -> Seleccione… | L37: =Translations!$D$72 -> Seleccione…
B38: =Translations!$D$72 -> Seleccione… | L38: =Translations!$D$72 -> Seleccione…
B39: =Translations!$D$72 -> Seleccione… | L39: =Translations!$D$72 -> Seleccione…
A41: =Translations!$D$74 -> D. Módulos
A43: =Translations!$D$75 -> Módulo | C43: 1 | D43: =Translations!$D$72 -> Seleccione…
A44: =Translations!$D$76 -> Marco de medición por módulo
A45: =Translations!$D$49 -> Indicador de cobertura/producto | D45: =Translations!$D$67 -> Receptores principales | E45: =Translations!$D$66 -> Vinculado al | G45: =Translations!$D$29 -> Línea de base | M45: =Translations!$D$30 -> Metas | S45: =Translations!$D$82 -> Supuestos de metas
M46: =Translations!$D$34 -> Año 1 | O46: =Translations!$D$35 -> Año 2 | Q46: =Translations!$D$36 -> Año 3 | S46: =Translations!$D$83 -> Describa lo siguiente: 1) supuestos generales usados al calcular las metas;: 2) tasa de ampliación prevista; 3) estimaciones del tamaño de la población; 4) descripción del indicador/paquete de servicios; 5) fuente de datos; 6) otra información pertinente.
G47: Numerador | H47: % | I47: =Translations!$D$32 -> Año | J47: =Translations!$D$33 -> Fuente | M47: Numerador | N47: % | O47: Numerador | P47: % | Q47: Numerador | R47: %
G48: Denominador | M48: Denominador | O48: Denominador | Q48: Denominador
D49: =Translations!$D$72 -> Seleccione… | E49: =Translations!$D$72 -> Seleccione… | H49: =IF($G51<>"",$G49/$G51,"") | J49: =Translations!$D$72 -> Seleccione… | K49: =Translations!$D$78 -> Indicativo | N49: =IF(M50<>"",M49/M50,"") | P49: =IF(O50<>"",O49/O50,"") | R49: =IF(Q50<>"",Q49/Q50,"")
K51: =Translations!$D$79 -> Por encima del indicativo | N51: =IF(M52<>"",M51/M52,"") | P51: =IF(O52<>"",O51/O52,"") | R51: =IF(Q52<>"",Q51/Q52,"")
D53: =Translations!$D$72 -> Seleccione… | E53: =Translations!$D$72 -> Seleccione… | H53: =IF($G55<>"",$G53/$G55,"") | J53: =Translations!$D$72 -> Seleccione… | K53: =Translations!$D$78 -> Indicativo | N53: =IF(M54<>"",M53/M54,"") | P53: =IF(O54<>"",O53/O54,"") | R53: =IF(Q54<>"",Q53/Q54,"")
K55: =Translations!$D$79 -> Por encima del indicativo | N55: =IF(M56<>"",M55/M56,"") | P55: =IF(O56<>"",O55/O56,"") | R55: =IF(Q56<>"",Q55/Q56,"")
D57: =Translations!$D$72 -> Seleccione… | E57: =Translations!$D$72 -> Seleccione… | H57: =IF($G59<>"",$G57/$G59,"") | J57: =Translations!$D$72 -> Seleccione… | K57: =Translations!$D$78 -> Indicativo | N57: =IF(M58<>"",M57/M58,"") | P57: =IF(O58<>"",O57/O58,"") | R57: =IF(Q58<>"",Q57/Q58,"")
K59: =Translations!$D$79 -> Por encima del indicativo | N59: =IF(M60<>"",M59/M60,"") | P59: =IF(O60<>"",O59/O60,"") | R59: =IF(Q60<>"",Q59/Q60,"")
A61: =Translations!$D$87 -> Presupuesto del módulo
A62: =Translations!$D$84 -> Solicitud de importe indicativo para todo el módulo | F62: 0 | J62: =Translations!$D$85 -> Solicitud de importe por encima del indicativo para todo el módulo | Q62: 0
A63: =Translations!$D$86 -> Intervención | D63: =Translations!$D$88 -> Descripción de la intervención | J63: =Translations!$D$67 -> Receptores principales | K63: =Translations!$D$90 -> Presupuesto de la intervención (solicitud al Fondo Mundial exclusivamente) | S63: =Translations!$D$91 -> Supuestos de costo para la solicitud al Fondo Mundial | Z63: =Translations!$D$93 -> Otros fondos recibidos para esta intervención (incluido el alcance de las actividades financiadas)
D64: =Translations!$D$89 -> Describa lo siguiente: 1) justificación para el apoyo del Fondo Mundial; 2) vínculos con el plan estratégico nacional; 3) población objetivo y alcance geográfico; 4) enfoque de ejecución; y 5) otra información pertinente. Diferencie entre el alcance de la solicitud de financiamiento indicativo y la correspondiente al importe por encima del indicativo. | M64: =Translations!$D$34 -> Año 1 | O64: =Translations!$D$35 -> Año 2 | Q64: =Translations!$D$36 -> Año 3 | S64: =Translations!$D$92 -> Describa lo siguiente: 1) supuestos de costo y fuentes de datos; 2) actividades clave; 3) otra información pertinente. Diferencie entre el alcance de la solicitud de financiamiento indicativo y la correspondiente al importe por encima del indicativo..
A65: =Translations!$D$72 -> Seleccione… | K65: =Translations!$D$78 -> Indicativo
K66: =Translations!$D$79 -> Por encima del indicativo
K67: =Translations!$D$78 -> Indicativo
K68: =Translations!$D$79 -> Por encima del indicativo
A69: =Translations!$D$72 -> Seleccione… | K69: =Translations!$D$78 -> Indicativo
K70: =Translations!$D$79 -> Por encima del indicativo
K71: =Translations!$D$78 -> Indicativo
K72: =Translations!$D$79 -> Por encima del indicativo
A73: =Translations!$D$72 -> Seleccione… | K73: =Translations!$D$78 -> Indicativo
K74: =Translations!$D$79 -> Por encima del indicativo
K75: =Translations!$D$78 -> Indicativo
K76: =Translations!$D$79 -> Por encima del indicativo
A77: =Translations!$D$72 -> Seleccione… | K77: =Translations!$D$78 -> Indicativo
K78: =Translations!$D$79 -> Por encima del indicativo
K79: =Translations!$D$78 -> Indicativo
K80: =Translations!$D$79 -> Por encima del indicativo
A81: =Translations!$D$72 -> Seleccione… | K81: =Translations!$D$78 -> Indicativo
K82: =Translations!$D$79 -> Por encima del indicativo
K83: =Translations!$D$78 -> Indicativo
K84: =Translations!$D$79 -> Por encima del indicativo

Sheet Instructions ru
A1: =Translations!E81 -> Модульный подход — концептуальная записка | O1: =Translations!$E$80 -> Язык: | P1: Английский
A2: =Translations!$E$7 -> A. Сведения о программе
A3: =Translations!$E$8 -> Страна/ Кандидат: | D3: =Translations!$E$72 -> Выберите значение… | H3: =Translations!$E$13 -> Основные реципиенты | U3: =Translations!$E$77 запрашиваемого финансирования -> #NAME?
A4: =Translations!$E$9 -> Компонент: | D4: =Translations!$E$72 -> Выберите значение…
A5: =Translations!$E$10 -> Год начала: | D5: =Translations!$E$72 -> Выберите значение… | H5: =Translations!$E$14 -> (Выберите из списка или добавьте нового) | U5: =Translations!$E$78 -> Ориентировочное | Y5: 0
A6: =Translations!$E$11 -> Месяц начала: | D6: =Translations!$E$72 -> Выберите значение… | U6: =Translations!$E$79 -> Свыше ориентировочного | Y6: 0
A8: =Translations!$E$25 -> B. Цели программы и показатели воздействия
A9: =Translations!$E$26 -> Цели:
A10: 1
A11: 2
A12: 3
A14: =Translations!$E$27 -> Привязка к цели(ям) # | B14: =Translations!$E$28 -> Показатель воздействия | I14: =Translations!$E$29 -> Исходный уровень | O14: =Translations!$E$30 -> Целевые показатели | U14: =Translations!$E$73 -> Комментарии и ориентировочные расчеты
I15: =Translations!$E$31 -> Величина | K15: =Translations!$E$32 -> Год | L15: =Translations!$E$33 -> Источник | O15: =Translations!$E$34 -> Год 1 | Q15: =Translations!$E$35 -> Год 2 | S15: =Translations!$E$36 -> Год 3
O16: =IFERROR(IF(MonthIndex<7,StartYearSelected,StartYearSelected+1),"") -> Please select… | Q16: =IFERROR(O16+1,"") | S16: =IFERROR(Q16+1,"")
B17: =Translations!$E$72 -> Выберите значение… | L17: =Translations!$E$72 -> Выберите значение…
B18: =Translations!$E$72 -> Выберите значение… | L18: =Translations!$E$72 -> Выберите значение…
B19: =Translations!$E$72 -> Выберите значение… | L19: =Translations!$E$72 -> Выберите значение…
B20: =Translations!$E$72 -> Выберите значение… | L20: =Translations!$E$72 -> Выберите значение…
B21: =Translations!$E$72 -> Выберите значение… | L21: =Translations!$E$72 -> Выберите значение…
A23: =Translations!$E$41 -> C. Задачи программы и показатели долгосрочных результатов
A24: =Translations!$E$42 -> Задачи:
A25: 1
A26: 2
A27: 3
A28: 4
A29: 5
A30: 6
A32: =Translations!$E$43 -> Привязка к задаче(задачам) # | B32: =Translations!E44 -> Показатель долгосрочного результата | I32: =Translations!$E$29 -> Исходный уровень | O32: =Translations!$E$30 -> Целевые показатели | U32: =Translations!$E$73 -> Комментарии и ориентировочные расчеты
I33: =Translations!$E$31 -> Величина | K33: =Translations!$E$32 -> Год | L33: =Translations!$E$33 -> Источник | O33: =Translations!$E$34 -> Год 1 | Q33: =Translations!$E$35 -> Год 2 | S33: =Translations!$E$36 -> Год 3
O34: =O16 -> Please select… | Q34: =Q16 | S34: =S16
B35: =Translations!$E$72 -> Выберите значение… | L35: =Translations!$E$72 -> Выберите значение…
B36: =Translations!$E$72 -> Выберите значение… | L36: =Translations!$E$72 -> Выберите значение…
B37: =Translations!$E$72 -> Выберите значение… | L37: =Translations!$E$72 -> Выберите значение…
B38: =Translations!$E$72 -> Выберите значение… | L38: =Translations!$E$72 -> Выберите значение…
B39: =Translations!$E$72 -> Выберите значение… | L39: =Translations!$E$72 -> Выберите значение…
A41: =Translations!$E$74 -> D. Модули
A43: =Translations!$E$75 -> Модуль | C43: 1 | D43: =Translations!$E$72 -> Выберите значение…
A44: =Translations!$E$76 -> Система показателей для модуля
A45: =Translations!$E$49 -> Показатель долгосрочного охвата/ результата | D45: =Translations!$E$67 -> Ответственный основной реципиент (реципиенты) | E45: =Translations!$E$66 -> Привязывается к | G45: =Translations!$E$29 -> Исходный уровень | M45: =Translations!$E$30 -> Целевые показатели | S45: =Translations!$E$82 -> Целевые предпосылки
M46: =Translations!$E$34 -> Год 1 | O46: =Translations!$E$35 -> Год 2 | Q46: =Translations!$E$36 -> Год 3 | S46: =Translations!$E$83 -> Укажите: 1) общие предположения, использованные при расчете целевых показателей; 2) предположительный уровень расширения охвата; 3) показатели численности населения, 4) описание показателей/ пакета услуг; 5) источники данных; 6) другую необходимую информацию.
G47: Ч | H47: % | I47: =Translations!$E$32 -> Год | J47: =Translations!$E$33 -> Источник | M47: Ч | N47: % | O47: Ч | P47: % | Q47: Ч | R47: %
G48: З | M48: З | O48: З | Q48: З
D49: =Translations!$E$72 -> Выберите значение… | E49: =Translations!$E$72 -> Выберите значение… | H49: =IF($G51<>"",$G49/$G51,"") | J49: =Translations!$E$72 -> Выберите значение… | K49: =Translations!$E$78 -> Ориентировочное | N49: =IF(M50<>"",M49/M50,"") | P49: =IF(O50<>"",O49/O50,"") | R49: =IF(Q50<>"",Q49/Q50,"")
K51: =Translations!$E$79 -> Свыше ориентировочного | N51: =IF(M52<>"",M51/M52,"") | P51: =IF(O52<>"",O51/O52,"") | R51: =IF(Q52<>"",Q51/Q52,"")
D53: =Translations!$E$72 -> Выберите значение… | E53: =Translations!$E$72 -> Выберите значение… | H53: =IF($G55<>"",$G53/$G55,"") | J53: =Translations!$E$72 -> Выберите значение… | K53: =Translations!$E$78 -> Ориентировочное | N53: =IF(M54<>"",M53/M54,"") | P53: =IF(O54<>"",O53/O54,"") | R53: =IF(Q54<>"",Q53/Q54,"")
K55: =Translations!$E$79 -> Свыше ориентировочного | N55: =IF(M56<>"",M55/M56,"") | P55: =IF(O56<>"",O55/O56,"") | R55: =IF(Q56<>"",Q55/Q56,"")
D57: =Translations!$E$72 -> Выберите значение… | E57: =Translations!$E$72 -> Выберите значение… | H57: =IF($G59<>"",$G57/$G59,"") | J57: =Translations!$E$72 -> Выберите значение… | K57: =Translations!$E$78 -> Ориентировочное | N57: =IF(M58<>"",M57/M58,"") | P57: =IF(O58<>"",O57/O58,"") | R57: =IF(Q58<>"",Q57/Q58,"")
K59: =Translations!$E$79 -> Свыше ориентировочного | N59: =IF(M60<>"",M59/M60,"") | P59: =IF(O60<>"",O59/O60,"") | R59: =IF(Q60<>"",Q59/Q60,"")
A61: =Translations!$E$87 -> Бюджет модуля
A62: =Translations!$E$84 -> Ориентировочное финансирование для всего модуля | F62: 0 | J62: =Translations!$E$85 -> Объем финансирования сверх ориентировочного уровня для всего модуля | Q62: 0
A63: =Translations!$E$86 -> Мероприятие | D63: =Translations!$E$88 -> Описание мероприятия | J63: =Translations!$E$67 -> Ответственный основной реципиент (реципиенты) | K63: =Translations!$E$90 -> Бюджет мероприятия (только для запросов в Глобальный фонд) | S63: =Translations!$E$91 -> Предполагаемые затраты, для финансирования которых подается запрос в Глобальный фонд | Z63: =Translations!$E$93 -> Другое финансирование, полученное для реализации данного мероприятия (включая охват финансируемыми видами деятельности)
D64: =Translations!$E$89 -> Укажите: 1) обоснование запроса на предоставление поддержки Глобальным фондом; 2) связь с национальным стратегическим планом; 3) целевую группу населения и географический охват; 4) подход к реализации; 5) другую необходимую информацию. Разграничьте охват запроса на ориентировочное финансирование и запроса на финансирование сверх ориентировочного уровня. | M64: =Translations!$E$34 -> Год 1 | O64: =Translations!$E$35 -> Год 2 | Q64: =Translations!$E$36 -> Год 3 | S64: =Translations!$E$92 -> Укажите: 1) примерное число услуг, которые предполагается профинансировать; 2) предполагаемые затраты и источники данных; 3) основные виды деятельности; 4) другую необходимую информацию. Разграничьте ориентировочное финансирование и финансирование сверх ориентировочного уровня.
A65: Please select… | K65: =Translations!$E$78 -> Ориентировочное
K66: =Translations!$E$79 -> Свыше ориентировочного
K67: =Translations!$E$78 -> Ориентировочное
K68: =Translations!$E$79 -> Свыше ориентировочного
A69: Please select… | K69: =Translations!$E$78 -> Ориентировочное
K70: =Translations!$E$79 -> Свыше ориентировочного
K71: =Translations!$E$78 -> Ориентировочное
K72: =Translations!$E$79 -> Свыше ориентировочного
A73: Please select… | K73: =Translations!$E$78 -> Ориентировочное
K74: =Translations!$E$79 -> Свыше ориентировочного
K75: =Translations!$E$78 -> Ориентировочное
K76: =Translations!$E$79 -> Свыше ориентировочного
A77: Please select… | K77: =Translations!$E$78 -> Ориентировочное
K78: =Translations!$E$79 -> Свыше ориентировочного
K79: =Translations!$E$78 -> Ориентировочное
K80: =Translations!$E$79 -> Свыше ориентировочного
A81: Please select… | K81: =Translations!$E$78 -> Ориентировочное
K82: =Translations!$E$79 -> Свыше ориентировочного
K83: =Translations!$E$78 -> Ориентировочное
K84: =Translations!$E$79 -> Свыше ориентировочного

Sheet Concept Note
A1: =Translations!A81 -> Modular Approach - Concept Note | O1: =Translations!$A$80 -> Language: | P1: English
A2: =Translations!$A$7 -> A. Program details
A3: =Translations!$A$8 -> Country / Applicant: | C3: Please select… | H3: =Translations!$A$13 -> Principal Recipients | S3: =IFERROR(VLOOKUP(K3,Definitions!R:S,2,FALSE),"") | U3: =Translations!$A$77 -> Total requested amount
A4: =Translations!$A$9 -> Component: | C4: =Translations!$A$72 -> Please select… | S4: =IFERROR(VLOOKUP(K4,Definitions!R:S,2,FALSE),"")
A5: =Translations!$A$10 -> Start Year: | C5: =Translations!$A$72 -> Please select… | H5: =Translations!$A$14 -> (Please select from list or add a new one) | S5: =IFERROR(VLOOKUP(K5,Definitions!R:S,2,FALSE),"") | U5: =Translations!$A$78 -> Indicative | Y5: =SUMIF(A:A,Translations!$A$84,F:F) -> 0
A6: =Translations!$A$11 -> Start Month: | C6: =Translations!$A$72 -> Please select… | S6: =IFERROR(VLOOKUP(K6,Definitions!R:S,2,FALSE),"") | U6: =Translations!$A$79 -> Above indicative | Y6: =SUMIF(J:J,Translations!$A$85,Q:Q) -> 0
A8: =Translations!$A$25 -> B. Program goals and impact indicators
A9: =Translations!$A$26 -> Goals:
A10: 1
A11: 2
A12: 3
A14: =Translations!$A$27 -> Linked to goal(s) # | B14: =Translations!$A$28 -> Impact indicator | I14: =Translations!$A$29 -> Baseline | O14: =Translations!$A$30 -> Targets | U14: =Translations!$A$73 -> Comments and Assumptions
I15: =Translations!$A$31 -> Value | K15: =Translations!$A$32 -> Year | L15: =Translations!$A$33 -> Source | O15: =Translations!$A$34 -> Year 1 | Q15: =Translations!$A$35 -> Year 2 | S15: =Translations!$A$36 -> Year 3
O16: =IFERROR(IF(MonthIndex<7,StartYearSelected,StartYearSelected+1),"") -> Please select… | Q16: =IFERROR(O16+1,"") | S16: =IFERROR(Q16+1,"")
B17: =Translations!$A$72 -> Please select… | L17: =Translations!$A$72 -> Please select…
B18: =Translations!$A$72 -> Please select… | L18: =Translations!$A$72 -> Please select…
B19: =Translations!$A$72 -> Please select… | L19: =Translations!$A$72 -> Please select…
B20: =Translations!$A$72 -> Please select… | L20: =Translations!$A$72 -> Please select…
B21: =Translations!$A$72 -> Please select… | L21: =Translations!$A$72 -> Please select…
A23: =Translations!$A$41 -> C. Program objectives and outcome indicators
A24: =Translations!$A$42 -> Objectives:
A25: 1
A26: 2
A27: 3
A28: 4
A29: 5
A30: 6
A32: =Translations!$A$43 -> Linked to objective(s) # | B32: =Translations!A44 -> Outcome indicator | I32: =Translations!$A$29 -> Baseline | O32: =Translations!$A$30 -> Targets | U32: =Translations!$A$73 -> Comments and Assumptions
I33: =Translations!$A$31 -> Value | K33: =Translations!$A$32 -> Year | L33: =Translations!$A$33 -> Source | O33: =Translations!$A$34 -> Year 1 | Q33: =Translations!$A$35 -> Year 2 | S33: =Translations!$A$36 -> Year 3
O34: =O16 -> Please select… | Q34: =Q16 | S34: =S16
B35: =Translations!$A$72 -> Please select… | L35: =Translations!$A$72 -> Please select…
B36: =Translations!$A$72 -> Please select… | L36: =Translations!$A$72 -> Please select…
B37: =Translations!$A$72 -> Please select… | L37: =Translations!$A$72 -> Please select…
B38: =Translations!$A$72 -> Please select… | L38: =Translations!$A$72 -> Please select…
B39: =Translations!$A$72 -> Please select… | L39: =Translations!$A$72 -> Please select…
A41: =Translations!A74 -> D. Modules | AJ41: Start row | AK41: Nbr of ind | AL41: Cov ind row | AM41: ModuleId | AN41: Indicative | AO41: Above
A43: =Translations!$A$75 -> Module | AM43: =INDIRECT(ADDRESS(MATCH(D43,ModulesInCmp,0)+MATCH(CmpIdSelected,Modules!$A:$A,0)-1,3,1,TRUE,"Modules")) -> #VALUE!
A44: =Translations!$A$76 -> Measurement framework for module | AM44: =INDIRECT(ADDRESS(ROW()-1,COLUMN())) -> #VALUE!
A45: =Translations!$A$49 -> Coverage/Output indicator | D45: =Translations!$A$67 -> Responsible Principal Recipient(s) | E45: =Translations!$A$66 -> Tied to | G45: =Translations!$A$29 -> Baseline | M45: =Translations!$A$30 -> Targets | S45: =Translations!$A$82 -> Target assumptions | AJ45: =MATCH(AM44,'Coverage ind'!$A:$A,0)-1 -> #VALUE! | AK45: =COUNTIF('Coverage ind'!A:A,'Concept Note'!AM44) -> 0 | AL45: =MATCH(AM44,'Coverage ind'!$A:$A,0)-1 -> #VALUE! | AM45: =INDIRECT(ADDRESS(ROW()-1,COLUMN())) -> #VALUE!
M46: =Translations!$A$34 -> Year 1 | O46: =Translations!$A$35 -> Year 2 | Q46: =Translations!$A$36 -> Year 3 | S46: =Translations!$A$83 -> Please describe: 1) overall assumptions used in calculating targets, 2) anticipated rate of scale-up, 3) population size estimates, 4) description of indicator/package of services, 5) data source, 6) other relevant information | AJ46: =INDIRECT(ADDRESS(ROW()-1,COLUMN())) -> #VALUE! | AK46: =INDIRECT(ADDRESS(ROW()-1,COLUMN())) -> 0 | AM46: =INDIRECT(ADDRESS(ROW()-1,COLUMN())) -> #VALUE!
G47: N # | H47: % | I47: =Translations!$A$32 -> Year | J47: =Translations!$A$33 -> Source | M47: N # | N47: % | O47: N # | P47: % | Q47: N # | R47: % | AJ47: =INDIRECT(ADDRESS(ROW()-1,COLUMN())) -> #VALUE! | AK47: =INDIRECT(ADDRESS(ROW()-1,COLUMN())) -> 0 | AM47: =INDIRECT(ADDRESS(ROW()-1,COLUMN())) -> #VALUE!
G48: D # | M48: D # | O48: D # | Q48: D # | AJ48: =INDIRECT(ADDRESS(ROW()-1,COLUMN())) -> #VALUE! | AK48: =INDIRECT(ADDRESS(ROW()-1,COLUMN())) -> 0 | AM48: =INDIRECT(ADDRESS(ROW()-1,COLUMN())) -> #VALUE!
A49: =IFERROR(INDIRECT(ADDRESS(AL49,5,1,TRUE,"Coverage ind")),"") | D49: =Translations!$A$72 -> Please select… | E49: =Translations!$A$72 -> Please select… | H49: =IF($G51<>"",$G49/$G51,"") | J49: =Translations!$A$72 -> Please select… | K49: =Translations!$A$78 -> Indicative | N49: =IF(M50<>"",M49/M50,"") | P49: =IF(O50<>"",O49/O50,"") | R49: =IF(Q50<>"",Q49/Q50,"") | AJ49: =INDIRECT(ADDRESS(ROW()-1,COLUMN())) -> #VALUE! | AK49: =INDIRECT(ADDRESS(ROW()-1,COLUMN())) -> 0 | AL49: =IFERROR(IF(INDIRECT(ADDRESS(ROW()-4,COLUMN()))+1<=AJ49+AK49,INDIRECT(ADDRESS(ROW()-4,COLUMN()))+1,""),"") | AM49: =INDIRECT(ADDRESS(ROW()-1,COLUMN())) -> #VALUE!
AJ50: =INDIRECT(ADDRESS(ROW()-1,COLUMN())) -> #VALUE! | AK50: =INDIRECT(ADDRESS(ROW()-1,COLUMN())) -> 0 | AM50: =INDIRECT(ADDRESS(ROW()-1,COLUMN())) -> #VALUE!
K51: =Translations!$A$79 -> Above indicative | N51: =IF(M52<>"",M51/M52,"") | P51: =IF(O52<>"",O51/O52,"") | R51: =IF(Q52<>"",Q51/Q52,"") | AJ51: =INDIRECT(ADDRESS(ROW()-1,COLUMN())) -> #VALUE! | AK51: =INDIRECT(ADDRESS(ROW()-1,COLUMN())) -> 0 | AM51: =INDIRECT(ADDRESS(ROW()-1,COLUMN())) -> #VALUE!
AJ52: =INDIRECT(ADDRESS(ROW()-1,COLUMN())) -> #VALUE! | AK52: =INDIRECT(ADDRESS(ROW()-1,COLUMN())) -> 0 | AM52: =INDIRECT(ADDRESS(ROW()-1,COLUMN())) -> #VALUE!
A53: =IFERROR(INDIRECT(ADDRESS(AL53,5,1,TRUE,"Coverage ind")),"") | D53: =Translations!$A$72 -> Please select… | E53: =Translations!$A$72 -> Please select… | H53: =IF($G55<>"",$G53/$G55,"") | J53: =Translations!$A$72 -> Please select… | K53: =Translations!$A$78 -> Indicative | N53: =IF(M54<>"",M53/M54,"") | P53: =IF(O54<>"",O53/O54,"") | R53: =IF(Q54<>"",Q53/Q54,"") | AJ53: =INDIRECT(ADDRESS(ROW()-1,COLUMN())) -> #VALUE! | AK53: =INDIRECT(ADDRESS(ROW()-1,COLUMN())) -> 0 | AL53: =IFERROR(IF(INDIRECT(ADDRESS(ROW()-4,COLUMN()))+1<=AJ53+AK53,INDIRECT(ADDRESS(ROW()-4,COLUMN()))+1,""),"") | AM53: =INDIRECT(ADDRESS(ROW()-1,COLUMN())) -> #VALUE!
AJ54: =INDIRECT(ADDRESS(ROW()-1,COLUMN())) -> #VALUE! | AK54: =INDIRECT(ADDRESS(ROW()-1,COLUMN())) -> 0 | AM54: =INDIRECT(ADDRESS(ROW()-1,COLUMN())) -> #VALUE!
K55: =Translations!$A$79 -> Above indicative | N55: =IF(M56<>"",M55/M56,"") | P55: =IF(O56<>"",O55/O56,"") | R55: =IF(Q56<>"",Q55/Q56,"") | AJ55: =INDIRECT(ADDRESS(ROW()-1,COLUMN())) -> #VALUE! | AK55: =INDIRECT(ADDRESS(ROW()-1,COLUMN())) -> 0 | AM55: =INDIRECT(ADDRESS(ROW()-1,COLUMN())) -> #VALUE!
AJ56: =INDIRECT(ADDRESS(ROW()-1,COLUMN())) -> #VALUE! | AK56: =INDIRECT(ADDRESS(ROW()-1,COLUMN())) -> 0 | AM56: =INDIRECT(ADDRESS(ROW()-1,COLUMN())) -> #VALUE!
A57: =IFERROR(INDIRECT(ADDRESS(AL57,5,1,TRUE,"Coverage ind")),"") | D57: =Translations!$A$72 -> Please select… | E57: =Translations!$A$72 -> Please select… | H57: =IF($G59<>"",$G57/$G59,"") | J57: =Translations!$A$72 -> Please select… | K57: =Translations!$A$78 -> Indicative | N57: =IF(M58<>"",M57/M58,"") | P57: =IF(O58<>"",O57/O58,"") | R57: =IF(Q58<>"",Q57/Q58,"") | AJ57: =INDIRECT(ADDRESS(ROW()-1,COLUMN())) -> #VALUE! | AK57: =INDIRECT(ADDRESS(ROW()-1,COLUMN())) -> 0 | AL57: =IFERROR(IF(INDIRECT(ADDRESS(ROW()-4,COLUMN()))+1<=AJ57+AK57,INDIRECT(ADDRESS(ROW()-4,COLUMN()))+1,""),"") | AM57: =INDIRECT(ADDRESS(ROW()-1,COLUMN())) -> #VALUE!
AJ58: =INDIRECT(ADDRESS(ROW()-1,COLUMN())) -> #VALUE! | AK58: =INDIRECT(ADDRESS(ROW()-1,COLUMN())) -> 0 | AM58: =INDIRECT(ADDRESS(ROW()-1,COLUMN())) -> #VALUE!
K59: =Translations!$A$79 -> Above indicative | N59: =IF(M60<>"",M59/M60,"") | P59: =IF(O60<>"",O59/O60,"") | R59: =IF(Q60<>"",Q59/Q60,"") | AJ59: =INDIRECT(ADDRESS(ROW()-1,COLUMN())) -> #VALUE! | AK59: =INDIRECT(ADDRESS(ROW()-1,COLUMN())) -> 0 | AM59: =INDIRECT(ADDRESS(ROW()-1,COLUMN())) -> #VALUE!
AJ60: =INDIRECT(ADDRESS(ROW()-1,COLUMN())) -> #VALUE! | AK60: =INDIRECT(ADDRESS(ROW()-1,COLUMN())) -> 0 | AM60: =INDIRECT(ADDRESS(ROW()-1,COLUMN())) -> #VALUE!
A61: =IFERROR(INDIRECT(ADDRESS(AL61,5,1,TRUE,"Coverage ind")),"") | D61: =Translations!$A$72 -> Please select… | E61: =Translations!$A$72 -> Please select… | H61: =IF($G63<>"",$G61/$G63,"") | J61: =Translations!$A$72 -> Please select… | K61: =Translations!$A$78 -> Indicative | N61: =IF(M62<>"",M61/M62,"") | P61: =IF(O62<>"",O61/O62,"") | R61: =IF(Q62<>"",Q61/Q62,"") | AJ61: =INDIRECT(ADDRESS(ROW()-1,COLUMN())) -> #VALUE! | AK61: =INDIRECT(ADDRESS(ROW()-1,COLUMN())) -> 0 | AL61: =IFERROR(IF(INDIRECT(ADDRESS(ROW()-4,COLUMN()))+1<=AJ61+AK61,INDIRECT(ADDRESS(ROW()-4,COLUMN()))+1,""),"") | AM61: =INDIRECT(ADDRESS(ROW()-1,COLUMN())) -> #VALUE!
AJ62: =INDIRECT(ADDRESS(ROW()-1,COLUMN())) -> #VALUE! | AK62: =INDIRECT(ADDRESS(ROW()-1,COLUMN())) -> 0 | AM62: =INDIRECT(ADDRESS(ROW()-1,COLUMN())) -> #VALUE!
K63: =Translations!$A$79 -> Above indicative | N63: =IF(M64<>"",M63/M64,"") | P63: =IF(O64<>"",O63/O64,"") | R63: =IF(Q64<>"",Q63/Q64,"") | AJ63: =INDIRECT(ADDRESS(ROW()-1,COLUMN())) -> #VALUE! | AK63: =INDIRECT(ADDRESS(ROW()-1,COLUMN())) -> 0 | AM63: =INDIRECT(ADDRESS(ROW()-1,COLUMN())) -> #VALUE!
AJ64: =INDIRECT(ADDRESS(ROW()-1,COLUMN())) -> #VALUE! | AK64: =INDIRECT(ADDRESS(ROW()-1,COLUMN())) -> 0 | AM64: =INDIRECT(ADDRESS(ROW()-1,COLUMN())) -> #VALUE!
A65: =IFERROR(INDIRECT(ADDRESS(AL65,5,1,TRUE,"Coverage ind")),"") | D65: =Translations!$A$72 -> Please select… | E65: =Translations!$A$72 -> Please select… | H65: =IF($G67<>"",$G65/$G67,"") | J65: =Translations!$A$72 -> Please select… | K65: =Translations!$A$78 -> Indicative | N65: =IF(M66<>"",M65/M66,"") | P65: =IF(O66<>"",O65/O66,"") | R65: =IF(Q66<>"",Q65/Q66,"") | AJ65: =INDIRECT(ADDRESS(ROW()-1,COLUMN())) -> #VALUE! | AK65: =INDIRECT(ADDRESS(ROW()-1,COLUMN())) -> 0 | AL65: =IFERROR(IF(INDIRECT(ADDRESS(ROW()-4,COLUMN()))+1<=AJ65+AK65,INDIRECT(ADDRESS(ROW()-4,COLUMN()))+1,""),"") | AM65: =INDIRECT(ADDRESS(ROW()-1,COLUMN())) -> #VALUE!
AJ66: =INDIRECT(ADDRESS(ROW()-1,COLUMN())) -> #VALUE! | AK66: =INDIRECT(ADDRESS(ROW()-1,COLUMN())) -> 0 | AM66: =INDIRECT(ADDRESS(ROW()-1,COLUMN())) -> #VALUE!
K67: =Translations!$A$79 -> Above indicative | N67: =IF(M68<>"",M67/M68,"") | P67: =IF(O68<>"",O67/O68,"") | R67: =IF(Q68<>"",Q67/Q68,"") | AJ67: =INDIRECT(ADDRESS(ROW()-1,COLUMN())) -> #VALUE! | AK67: =INDIRECT(ADDRESS(ROW()-1,COLUMN())) -> 0 | AM67: =INDIRECT(ADDRESS(ROW()-1,COLUMN())) -> #VALUE!
AJ68: =INDIRECT(ADDRESS(ROW()-1,COLUMN())) -> #VALUE! | AK68: =INDIRECT(ADDRESS(ROW()-1,COLUMN())) -> 0 | AM68: =INDIRECT(ADDRESS(ROW()-1,COLUMN())) -> #VALUE!
A69: =IFERROR(INDIRECT(ADDRESS(AL69,5,1,TRUE,"Coverage ind")),"") | D69: =Translations!$A$72 -> Please select… | E69: =Translations!$A$72 -> Please select… | H69: =IF($G71<>"",$G69/$G71,"") | J69: =Translations!$A$72 -> Please select… | K69: =Translations!$A$78 -> Indicative | N69: =IF(M70<>"",M69/M70,"") | P69: =IF(O70<>"",O69/O70,"") | R69: =IF(Q70<>"",Q69/Q70,"") | AJ69: =INDIRECT(ADDRESS(ROW()-1,COLUMN())) -> #VALUE! | AK69: =INDIRECT(ADDRESS(ROW()-1,COLUMN())) -> 0 | AL69: =IFERROR(IF(INDIRECT(ADDRESS(ROW()-4,COLUMN()))+1<=AJ69+AK69,INDIRECT(ADDRESS(ROW()-4,COLUMN()))+1,""),"") | AM69: =INDIRECT(ADDRESS(ROW()-1,COLUMN())) -> #VALUE!
AJ70: =INDIRECT(ADDRESS(ROW()-1,COLUMN())) -> #VALUE! | AK70: =INDIRECT(ADDRESS(ROW()-1,COLUMN())) -> 0 | AM70: =INDIRECT(ADDRESS(ROW()-1,COLUMN())) -> #VALUE!
K71: =Translations!$A$79 -> Above indicative | N71: =IF(M72<>"",M71/M72,"") | P71: =IF(O72<>"",O71/O72,"") | R71: =IF(Q72<>"",Q71/Q72,"") | AJ71: =INDIRECT(ADDRESS(ROW()-1,COLUMN())) -> #VALUE! | AK71: =INDIRECT(ADDRESS(ROW()-1,COLUMN())) -> 0 | AM71: =INDIRECT(ADDRESS(ROW()-1,COLUMN())) -> #VALUE!
AJ72: =INDIRECT(ADDRESS(ROW()-1,COLUMN())) -> #VALUE! | AK72: =INDIRECT(ADDRESS(ROW()-1,COLUMN())) -> 0 | AM72: =INDIRECT(ADDRESS(ROW()-1,COLUMN())) -> #VALUE!
A73: =IFERROR(INDIRECT(ADDRESS(AL73,5,1,TRUE,"Coverage ind")),"") | D73: =Translations!$A$72 -> Please select… | E73: =Translations!$A$72 -> Please select… | H73: =IF($G75<>"",$G73/$G75,"") | J73: =Translations!$A$72 -> Please select… | K73: =Translations!$A$78 -> Indicative | N73: =IF(M74<>"",M73/M74,"") | P73: =IF(O74<>"",O73/O74,"") | R73: =IF(Q74<>"",Q73/Q74,"") | AJ73: =INDIRECT(ADDRESS(ROW()-1,COLUMN())) -> #VALUE! | AK73: =INDIRECT(ADDRESS(ROW()-1,COLUMN())) -> 0 | AL73: =IFERROR(IF(INDIRECT(ADDRESS(ROW()-4,COLUMN()))+1<=AJ73+AK73,INDIRECT(ADDRESS(ROW()-4,COLUMN()))+1,""),"") | AM73: =INDIRECT(ADDRESS(ROW()-1,COLUMN())) -> #VALUE!
AJ74: =INDIRECT(ADDRESS(ROW()-1,COLUMN())) -> #VALUE! | AK74: =INDIRECT(ADDRESS(ROW()-1,COLUMN())) -> 0 | AM74: =INDIRECT(ADDRESS(ROW()-1,COLUMN())) -> #VALUE!
K75: =Translations!$A$79 -> Above indicative | N75: =IF(M76<>"",M75/M76,"") | P75: =IF(O76<>"",O75/O76,"") | R75: =IF(Q76<>"",Q75/Q76,"") | AJ75: =INDIRECT(ADDRESS(ROW()-1,COLUMN())) -> #VALUE! | AK75: =INDIRECT(ADDRESS(ROW()-1,COLUMN())) -> 0 | AM75: =INDIRECT(ADDRESS(ROW()-1,COLUMN())) -> #VALUE!
AJ76: =INDIRECT(ADDRESS(ROW()-1,COLUMN())) -> #VALUE! | AK76: =INDIRECT(ADDRESS(ROW()-1,COLUMN())) -> 0 | AM76: =INDIRECT(ADDRESS(ROW()-1,COLUMN())) -> #VALUE!
A77: =IFERROR(INDIRECT(ADDRESS(AL77,5,1,TRUE,"Coverage ind")),"") | D77: =Translations!$A$72 -> Please select… | E77: =Translations!$A$72 -> Please select… | H77: =IF($G79<>"",$G77/$G79,"") | J77: =Translations!$A$72 -> Please select… | K77: =Translations!$A$78 -> Indicative | N77: =IF(M78<>"",M77/M78,"") | P77: =IF(O78<>"",O77/O78,"") | R77: =IF(Q78<>"",Q77/Q78,"") | AJ77: =INDIRECT(ADDRESS(ROW()-1,COLUMN())) -> #VALUE! | AK77: =INDIRECT(ADDRESS(ROW()-1,COLUMN())) -> 0 | AL77: =IFERROR(IF(INDIRECT(ADDRESS(ROW()-4,COLUMN()))+1<=AJ77+AK77,INDIRECT(ADDRESS(ROW()-4,COLUMN()))+1,""),"") | AM77: =INDIRECT(ADDRESS(ROW()-1,COLUMN())) -> #VALUE!
AJ78: =INDIRECT(ADDRESS(ROW()-1,COLUMN())) -> #VALUE! | AK78: =INDIRECT(ADDRESS(ROW()-1,COLUMN())) -> 0 | AM78: =INDIRECT(ADDRESS(ROW()-1,COLUMN())) -> #VALUE!
K79: =Translations!$A$79 -> Above indicative | N79: =IF(M80<>"",M79/M80,"") | P79: =IF(O80<>"",O79/O80,"") | R79: =IF(Q80<>"",Q79/Q80,"") | AJ79: =INDIRECT(ADDRESS(ROW()-1,COLUMN())) -> #VALUE! | AK79: =INDIRECT(ADDRESS(ROW()-1,COLUMN())) -> 0 | AM79: =INDIRECT(ADDRESS(ROW()-1,COLUMN())) -> #VALUE!
AJ80: =INDIRECT(ADDRESS(ROW()-1,COLUMN())) -> #VALUE! | AK80: =INDIRECT(ADDRESS(ROW()-1,COLUMN())) -> 0 | AM80: =INDIRECT(ADDRESS(ROW()-1,COLUMN())) -> #VALUE!
A81: =IFERROR(INDIRECT(ADDRESS(AL81,5,1,TRUE,"Coverage ind")),"") | D81: =Translations!$A$72 -> Please select… | E81: =Translations!$A$72 -> Please select… | H81: =IF($G83<>"",$G81/$G83,"") | J81: =Translations!$A$72 -> Please select… | K81: =Translations!$A$78 -> Indicative | N81: =IF(M82<>"",M81/M82,"") | P81: =IF(O82<>"",O81/O82,"") | R81: =IF(Q82<>"",Q81/Q82,"") | AJ81: =INDIRECT(ADDRESS(ROW()-1,COLUMN())) -> #VALUE! | AK81: =INDIRECT(ADDRESS(ROW()-1,COLUMN())) -> 0 | AL81: =IFERROR(IF(INDIRECT(ADDRESS(ROW()-4,COLUMN()))+1<=AJ81+AK81,INDIRECT(ADDRESS(ROW()-4,COLUMN()))+1,""),"") | AM81: =INDIRECT(ADDRESS(ROW()-1,COLUMN())) -> #VALUE!
AJ82: =INDIRECT(ADDRESS(ROW()-1,COLUMN())) -> #VALUE! | AK82: =INDIRECT(ADDRESS(ROW()-1,COLUMN())) -> 0 | AM82: =INDIRECT(ADDRESS(ROW()-1,COLUMN())) -> #VALUE!
K83: =Translations!$A$79 -> Above indicative | N83: =IF(M84<>"",M83/M84,"") | P83: =IF(O84<>"",O83/O84,"") | R83: =IF(Q84<>"",Q83/Q84,"") | AJ83: =INDIRECT(ADDRESS(ROW()-1,COLUMN())) -> #VALUE! | AK83: =INDIRECT(ADDRESS(ROW()-1,COLUMN())) -> 0 | AM83: =INDIRECT(ADDRESS(ROW()-1,COLUMN())) -> #VALUE!
AJ84: =INDIRECT(ADDRESS(ROW()-1,COLUMN())) -> #VALUE! | AK84: =INDIRECT(ADDRESS(ROW()-1,COLUMN())) -> 0 | AM84: =INDIRECT(ADDRESS(ROW()-1,COLUMN())) -> #VALUE!
A85: =Translations!$A$87 -> Module budget | AM85: =INDIRECT(ADDRESS(ROW()-1,COLUMN())) -> #VALUE!
A86: =Translations!$A$84 -> Indicative request for entire module | F86: =SUMIF($K89:$K108,Translations!$A$78,$M89:$M108)+SUMIF($K89:$K108,Translations!$A$78,$O89:$O108)+SUMIF($K89:$K108,Translations!$A$78,$Q89:$Q108) -> 0 | J86: =Translations!$A$85 -> Above indicative request for entire module | Q86: =SUMIF($K89:$K108,Translations!$A$79,$M89:$M108)+SUMIF($K89:$K108,Translations!$A$79,$O89:$O108)+SUMIF($K89:$K108,Translations!$A$79,$Q89:$Q108) -> 0 | AM86: =INDIRECT(ADDRESS(ROW()-1,COLUMN())) -> #VALUE! | AN86: =F86 -> 0 | AO86: =Q86 -> 0
A87: =Translations!$A$86 -> Intervention | D87: =Translations!$A$88 -> Description of Intervention | J87: =Translations!$A$67 -> Responsible Principal Recipient(s) | K87: =Translations!$A$90 -> Intervention budget (request to the Global Fund only) | S87: =Translations!$A$91 -> Cost Assumptions for the request to the Global Fund | Z87: =Translations!$A$93 -> Other funding received for this intervention (including scope of activities funded) | AM87: =INDIRECT(ADDRESS(ROW()-1,COLUMN())) -> #VALUE!
D88: =Translations!$A$89 -> Please describe 1) rationale for Global Fund support, 2) linkages to national strategic plan, 3) target population & geographic scope, 4) implementation approach, and 5) other relevant information. Please differentiate between scope of indicative and above indicative request | M88: =Translations!$A$34 -> Year 1 | O88: =Translations!$A$35 -> Year 2 | Q88: =Translations!$A$36 -> Year 3 | S88: =Translations!$A$92 -> Please describe: 1) cost assumptions and data sources, 2) key activities, 3) other relevant information. Please differentiate between indicative and above indicative | AM88: =INDIRECT(ADDRESS(ROW()-1,COLUMN())) -> #VALUE!
A89: =Translations!$A$72 -> Please select… | K89: =Translations!$A$78 -> Indicative
K90: =Translations!$A$79 -> Above indicative
K91: =Translations!$A$78 -> Indicative
K92: =Translations!$A$79 -> Above indicative
A93: =Translations!$A$72 -> Please select… | K93: =Translations!$A$78 -> Indicative
K94: =Translations!$A$79 -> Above indicative
K95: =Translations!$A$78 -> Indicative
K96: =Translations!$A$79 -> Above indicative
A97: =Translations!$A$72 -> Please select… | K97: =Translations!$A$78 -> Indicative
K98: =Translations!$A$79 -> Above indicative
K99: =Translations!$A$78 -> Indicative
K100: =Translations!$A$79 -> Above indicative
A101: =Translations!$A$72 -> Please select… | K101: =Translations!$A$78 -> Indicative
K102: =Translations!$A$79 -> Above indicative
K103: =Translations!$A$78 -> Indicative
K104: =Translations!$A$79 -> Above indicative
A105: =Translations!$A$72 -> Please select… | K105: =Translations!$A$78 -> Indicative
K106: =Translations!$A$79 -> Above indicative
...

Sheet Summary budget
J1: =Translations!$A$96 -> Summary of requested 3 years of funding by module
A3: ModId | B3: =Modules!D1 -> Label | C3: Indicative | D3: P1 | E3: Above | F3: P2 | G3: Total / Full | H3: P3 | J3: =Translations!$A$97 -> To refresh the pivot table with latest amounts entered in the Module budgets on the Concept Note sheet, click anywhere on the pivot table and then press Alt + F5.
A4: =Modules!C2 -> 1 | B4: =Modules!D2 -> Prevention - General population | C4: =SUMIF('Concept Note'!AM:AM,A4,'Concept Note'!AN:AN) -> 0 | D4: =C4/SUM(C:C) -> #DIV/0! | E4: =SUMIF('Concept Note'!$AM:$AM,A4,'Concept Note'!$AO:$AO) -> 0 | F4: =E4/SUM(E:E) -> #DIV/0! | G4: =SUM(C4,E4) -> 0 | H4: =G4/SUM(G:G) -> #DIV/0!
A5: =Modules!C8 -> 2 | B5: =Modules!D8 -> PMTCT | C5: =SUMIF('Concept Note'!AM:AM,A5,'Concept Note'!AN:AN) -> 0 | D5: =C5/SUM(C:C) -> #DIV/0! | E5: =SUMIF('Concept Note'!$AM:$AM,A5,'Concept Note'!$AO:$AO) -> 0 | F5: =E5/SUM(E:E) -> #DIV/0! | G5: =SUM(C5,E5) -> 0 | H5: =G5/SUM(G:G) -> #DIV/0!
A6: =Modules!C9 -> 3 | B6: =Modules!D9 -> Treatment, care and support | C6: =SUMIF('Concept Note'!AM:AM,A6,'Concept Note'!AN:AN) -> 0 | D6: =C6/SUM(C:C) -> #DIV/0! | E6: =SUMIF('Concept Note'!$AM:$AM,A6,'Concept Note'!$AO:$AO) -> 0 | F6: =E6/SUM(E:E) -> #DIV/0! | G6: =SUM(C6,E6) -> 0 | H6: =G6/SUM(G:G) -> #DIV/0! | J6: Row Labels | K6: Indicative budget | L6: Indicative % | M6: Above indicative | N6: Above % | O6: Full request | P6: Full %
A7: =Modules!C10 -> 4 | B7: =Modules!D10 -> Monitoring and Evaluation | C7: =SUMIF('Concept Note'!AM:AM,A7,'Concept Note'!AN:AN) -> 0 | D7: =C7/SUM(C:C) -> #DIV/0! | E7: =SUMIF('Concept Note'!$AM:$AM,A7,'Concept Note'!$AO:$AO) -> 0 | F7: =E7/SUM(E:E) -> #DIV/0! | G7: =SUM(C7,E7) -> 0 | H7: =G7/SUM(G:G) -> #DIV/0! | J7: Grand Total
A8: =Modules!C11 -> 5 | B8: =Modules!D11 -> Program management | C8: =SUMIF('Concept Note'!AM:AM,A8,'Concept Note'!AN:AN) -> 0 | D8: =C8/SUM(C:C) -> #DIV/0! | E8: =SUMIF('Concept Note'!$AM:$AM,A8,'Concept Note'!$AO:$AO) -> 0 | F8: =E8/SUM(E:E) -> #DIV/0! | G8: =SUM(C8,E8) -> 0 | H8: =G8/SUM(G:G) -> #DIV/0!
A9: =Modules!C12 -> 6 | B9: =Modules!D12 -> DOTS-based package | C9: =SUMIF('Concept Note'!AM:AM,A9,'Concept Note'!AN:AN) -> 0 | D9: =C9/SUM(C:C) -> #DIV/0! | E9: =SUMIF('Concept Note'!$AM:$AM,A9,'Concept Note'!$AO:$AO) -> 0 | F9: =E9/SUM(E:E) -> #DIV/0! | G9: =SUM(C9,E9) -> 0 | H9: =G9/SUM(G:G) -> #DIV/0!
A10: =Modules!C13 -> 7 | B10: =Modules!D13 -> TB/HIV package (in high TB/HIV burden countries or for high risk groups in all countries) | C10: =SUMIF('Concept Note'!AM:AM,A10,'Concept Note'!AN:AN) -> 0 | D10: =C10/SUM(C:C) -> #DIV/0! | E10: =SUMIF('Concept Note'!$AM:$AM,A10,'Concept Note'!$AO:$AO) -> 0 | F10: =E10/SUM(E:E) -> #DIV/0! | G10: =SUM(C10,E10) -> 0 | H10: =G10/SUM(G:G) -> #DIV/0!
A11: =Modules!C14 -> 8 | B11: =Modules!D14 -> MDR-TB package (in high MDR-TB burden countries or for high risk groups in all countries) | C11: =SUMIF('Concept Note'!AM:AM,A11,'Concept Note'!AN:AN) -> 0 | D11: =C11/SUM(C:C) -> #DIV/0! | E11: =SUMIF('Concept Note'!$AM:$AM,A11,'Concept Note'!$AO:$AO) -> 0 | F11: =E11/SUM(E:E) -> #DIV/0! | G11: =SUM(C11,E11) -> 0 | H11: =G11/SUM(G:G) -> #DIV/0!
A12: =Modules!C15 -> 9 | B12: =Modules!D15 -> Human Rights | C12: =SUMIF('Concept Note'!AM:AM,A12,'Concept Note'!AN:AN) -> 0 | D12: =C12/SUM(C:C) -> #DIV/0! | E12: =SUMIF('Concept Note'!$AM:$AM,A12,'Concept Note'!$AO:$AO) -> 0 | F12: =E12/SUM(E:E) -> #DIV/0! | G12: =SUM(C12,E12) -> 0 | H12: =G12/SUM(G:G) -> #DIV/0!
A13: =Modules!C16 -> 10 | B13: =Modules!D16 -> Monitoring and Evaluation | C13: =SUMIF('Concept Note'!AM:AM,A13,'Concept Note'!AN:AN) -> 0 | D13: =C13/SUM(C:C) -> #DIV/0! | E13: =SUMIF('Concept Note'!$AM:$AM,A13,'Concept Note'!$AO:$AO) -> 0 | F13: =E13/SUM(E:E) -> #DIV/0! | G13: =SUM(C13,E13) -> 0 | H13: =G13/SUM(G:G) -> #DIV/0!
A14: =Modules!C17 -> 11 | B14: =Modules!D17 -> Program Management | C14: =SUMIF('Concept Note'!AM:AM,A14,'Concept Note'!AN:AN) -> 0 | D14: =C14/SUM(C:C) -> #DIV/0! | E14: =SUMIF('Concept Note'!$AM:$AM,A14,'Concept Note'!$AO:$AO) -> 0 | F14: =E14/SUM(E:E) -> #DIV/0! | G14: =SUM(C14,E14) -> 0 | H14: =G14/SUM(G:G) -> #DIV/0!
A15: =Modules!C18 -> 12 | B15: =Modules!D18 -> Vector Control (VC) | C15: =SUMIF('Concept Note'!AM:AM,A15,'Concept Note'!AN:AN) -> 0 | D15: =C15/SUM(C:C) -> #DIV/0! | E15: =SUMIF('Concept Note'!$AM:$AM,A15,'Concept Note'!$AO:$AO) -> 0 | F15: =E15/SUM(E:E) -> #DIV/0! | G15: =SUM(C15,E15) -> 0 | H15: =G15/SUM(G:G) -> #DIV/0!
A16: =Modules!C19 -> 13 | B16: =Modules!D19 -> Case Management (CM) | C16: =SUMIF('Concept Note'!AM:AM,A16,'Concept Note'!AN:AN) -> 0 | D16: =C16/SUM(C:C) -> #DIV/0! | E16: =SUMIF('Concept Note'!$AM:$AM,A16,'Concept Note'!$AO:$AO) -> 0 | F16: =E16/SUM(E:E) -> #DIV/0! | G16: =SUM(C16,E16) -> 0 | H16: =G16/SUM(G:G) -> #DIV/0!
A17: =Modules!C20 -> 14 | B17: =Modules!D20 -> Specific Prevention Interventions (SPI) | C17: =SUMIF('Concept Note'!AM:AM,A17,'Concept Note'!AN:AN) -> 0 | D17: =C17/SUM(C:C) -> #DIV/0! | E17: =SUMIF('Concept Note'!$AM:$AM,A17,'Concept Note'!$AO:$AO) -> 0 | F17: =E17/SUM(E:E) -> #DIV/0! | G17: =SUM(C17,E17) -> 0 | H17: =G17/SUM(G:G) -> #DIV/0!
A18: =Modules!C21 -> 15 | B18: =Modules!D21 -> Monitoring and Evaluation (ME) | C18: =SUMIF('Concept Note'!AM:AM,A18,'Concept Note'!AN:AN) -> 0 | D18: =C18/SUM(C:C) -> #DIV/0! | E18: =SUMIF('Concept Note'!$AM:$AM,A18,'Concept Note'!$AO:$AO) -> 0 | F18: =E18/SUM(E:E) -> #DIV/0! | G18: =SUM(C18,E18) -> 0 | H18: =G18/SUM(G:G) -> #DIV/0!
A19: =Modules!C22 -> 16 | B19: =Modules!D22 -> Program Management (PM) | C19: =SUMIF('Concept Note'!AM:AM,A19,'Concept Note'!AN:AN) -> 0 | D19: =C19/SUM(C:C) -> #DIV/0! | E19: =SUMIF('Concept Note'!$AM:$AM,A19,'Concept Note'!$AO:$AO) -> 0 | F19: =E19/SUM(E:E) -> #DIV/0! | G19: =SUM(C19,E19) -> 0 | H19: =G19/SUM(G:G) -> #DIV/0!
... A27: =Modules!C30 -> 24 | B27: =Modules!D30 -> Program management (applicable for standalone HSS grants) | C27: =SUMIF('Concept Note'!AM:AM,A27,'Concept Note'!AN:AN) -> 0 | D27: =C27/SUM(C:C) -> #DIV/0! | E27: =SUMIF('Concept Note'!$AM:$AM,A27,'Concept Note'!$AO:$AO) -> 0 | F27: =E27/SUM(E:E) -> #DIV/0! | G27: =SUM(C27,E27) -> 0 | H27: =G27/SUM(G:G) -> #DIV/0!
A28: =Modules!C3 -> 25 | B28: =Modules!D3 -> Prevention - MSM and TGs | C28: =SUMIF('Concept Note'!AM:AM,A28,'Concept Note'!AN:AN) -> 0 | D28: =C28/SUM(C:C) -> #DIV/0! | E28: =SUMIF('Concept Note'!$AM:$AM,A28,'Concept Note'!$AO:$AO) -> 0 | F28: =E28/SUM(E:E) -> #DIV/0! | G28: =SUM(C28,E28) -> 0 | H28: =G28/SUM(G:G) -> #DIV/0!
A29: =Modules!C4 -> 26 | B29: =Modules!D4 -> Prevention - Sex Workers and their clients | C29: =SUMIF('Concept Note'!AM:AM,A29,'Concept Note'!AN:AN) -> 0 | D29: =C29/SUM(C:C) -> #DIV/0! | E29: =SUMIF('Concept Note'!$AM:$AM,A29,'Concept Note'!$AO:$AO) -> 0 | F29: =E29/SUM(E:E) -> #DIV/0! | G29: =SUM(C29,E29) -> 0 | H29: =G29/SUM(G:G) -> #DIV/0!
A30: =Modules!C5 -> 27 | B30: =Modules!D5 -> Prevention - Harm-reduction programmes for injecting drug users (IDUs) and their partners | C30: =SUMIF('Concept Note'!AM:AM,A30,'Concept Note'!AN:AN) -> 0 | D30: =C30/SUM(C:C) -> #DIV/0! | E30: =SUMIF('Concept Note'!$AM:$AM,A30,'Concept Note'!$AO:$AO) -> 0 | F30: =E30/SUM(E:E) -> #DIV/0! | G30: =SUM(C30,E30) -> 0 | H30: =G30/SUM(G:G) -> #DIV/0!
A31: =Modules!C7 -> 28 | B31: =Modules!D7 -> Prevention - Other vulnerable populations (please specify) | C31: =SUMIF('Concept Note'!AM:AM,A31,'Concept Note'!AN:AN) -> 0 | D31: =C31/SUM(C:C) -> #DIV/0! | E31: =SUMIF('Concept Note'!$AM:$AM,A31,'Concept Note'!$AO:$AO) -> 0 | F31: =E31/SUM(E:E) -> #DIV/0! | G31: =SUM(C31,E31) -> 0 | H31: =G31/SUM(G:G) -> #DIV/0!
A32: =Modules!C6 -> 29 | B32: =Modules!D6 -> Prevention - Adolescents and youth, in and out of school | C32: =SUMIF('Concept Note'!AM:AM,A32,'Concept Note'!AN:AN) -> 0 | D32: =C32/SUM(C:C) -> #DIV/0! | E32: =SUMIF('Concept Note'!$AM:$AM,A32,'Concept Note'!$AO:$AO) -> 0 | F32: =E32/SUM(E:E) -> #DIV/0! | G32: =SUM(C32,E32) -> 0 | H32: =G32/SUM(G:G) -> #DIV/0!
A33: =Modules!C31 -> 0 | B33: =Modules!D31 -> 0 | C33: =SUMIF('Concept Note'!AM:AM,A33,'Concept Note'!AN:AN) -> 0 | D33: =C33/SUM(C:C) -> #DIV/0! | E33: =SUMIF('Concept Note'!$AM:$AM,A33,'Concept Note'!$AO:$AO) -> 0 | F33: =E33/SUM(E:E) -> #DIV/0! | G33: =SUM(C33,E33) -> 0 | H33: =G33/SUM(G:G) -> #DIV/0!
A34: =Modules!C32 -> 0 | B34: =Modules!D32 -> 0 | C34: =SUMIF('Concept Note'!AM:AM,A34,'Concept Note'!AN:AN) -> 0 | D34: =C34/SUM(C:C) -> #DIV/0! | E34: =SUMIF('Concept Note'!$AM:$AM,A34,'Concept Note'!$AO:$AO) -> 0 | F34: =E34/SUM(E:E) -> #DIV/0! | G34: =SUM(C34,E34) -> 0 | H34: =G34/SUM(G:G) -> #DIV/0!
A35: =Modules!C33 -> 0 | B35: =Modules!D33 -> 0 | C35: =SUMIF('Concept Note'!AM:AM,A35,'Concept Note'!AN:AN) -> 0 | D35: =C35/SUM(C:C) -> #DIV/0! | E35: =SUMIF('Concept Note'!$AM:$AM,A35,'Concept Note'!$AO:$AO) -> 0 | F35: =E35/SUM(E:E) -> #DIV/0! | G35: =SUM(C35,E35) -> 0 | H35: =G35/SUM(G:G) -> #DIV/0!
A36: =Modules!C34 -> 0 | B36: =Modules!D34 -> 0 | C36: =SUMIF('Concept Note'!AM:AM,A36,'Concept Note'!AN:AN) -> 0 | D36: =C36/SUM(C:C) -> #DIV/0! | E36: =SUMIF('Concept Note'!$AM:$AM,A36,'Concept Note'!$AO:$AO) -> 0 | F36: =E36/SUM(E:E) -> #DIV/0! | G36: =SUM(C36,E36) -> 0 | H36: =G36/SUM(G:G) -> #DIV/0!
A37: =Modules!C35 -> 0 | B37: =Modules!D35 -> 0 | C37: =SUMIF('Concept Note'!AM:AM,A37,'Concept Note'!AN:AN) -> 0 | D37: =C37/SUM(C:C) -> #DIV/0! | E37: =SUMIF('Concept Note'!$AM:$AM,A37,'Concept Note'!$AO:$AO) -> 0 | F37: =E37/SUM(E:E) -> #DIV/0! | G37: =SUM(C37,E37) -> 0 | H37: =G37/SUM(G:G) -> #DIV/0!
A38: =Modules!C36 -> 0 | B38: =Modules!D36 -> 0 | C38: =SUMIF('Concept Note'!AM:AM,A38,'Concept Note'!AN:AN) -> 0 | D38: =C38/SUM(C:C) -> #DIV/0! | E38: =SUMIF('Concept Note'!$AM:$AM,A38,'Concept Note'!$AO:$AO) -> 0 | F38: =E38/SUM(E:E) -> #DIV/0! | G38: =SUM(C38,E38) -> 0 | H38: =G38/SUM(G:G) -> #DIV/0!
A39: =Modules!C37 -> 0 | B39: =Modules!D37 -> 0 | C39: =SUMIF('Concept Note'!AM:AM,A39,'Concept Note'!AN:AN) -> 0 | D39: =C39/SUM(C:C) -> #DIV/0! | E39: =SUMIF('Concept Note'!$AM:$AM,A39,'Concept Note'!$AO:$AO) -> 0 | F39: =E39/SUM(E:E) -> #DIV/0! | G39: =SUM(C39,E39) -> 0 | H39: =G39/SUM(G:G) -> #DIV/0!
A40: =Modules!C38 -> 0 | B40: =Modules!D38 -> 0 | C40: =SUMIF('Concept Note'!AM:AM,A40,'Concept Note'!AN:AN) -> 0 | D40: =C40/SUM(C:C) -> #DIV/0! | E40: =SUMIF('Concept Note'!$AM:$AM,A40,'Concept Note'!$AO:$AO) -> 0 | F40: =E40/SUM(E:E) -> #DIV/0! | G40: =SUM(C40,E40) -> 0 | H40: =G40/SUM(G:G) -> #DIV/0!
A41: =Modules!C39 -> 0 | B41: =Modules!D39 -> 0 | C41: =SUMIF('Concept Note'!AM:AM,A41,'Concept Note'!AN:AN) -> 0 | D41: =C41/SUM(C:C) -> #DIV/0! | E41: =SUMIF('Concept Note'!$AM:$AM,A41,'Concept Note'!$AO:$AO) -> 0 | F41: =E41/SUM(E:E) -> #DIV/0! | G41: =SUM(C41,E41) -> 0 | H41: =G41/SUM(G:G) -> #DIV/0!
A42: =Modules!C40 -> 0 | B42: =Modules!D40 -> 0 | C42: =SUMIF('Concept Note'!AM:AM,A42,'Concept Note'!AN:AN) -> 0 | D42: =C42/SUM(C:C) -> #DIV/0! | E42: =SUMIF('Concept Note'!$AM:$AM,A42,'Concept Note'!$AO:$AO) -> 0 | F42: =E42/SUM(E:E) -> #DIV/0! | G42: =SUM(C42,E42) -> 0 | H42: =G42/SUM(G:G) -> #DIV/0!
A43: =Modules!C41 -> 0 | B43: =Modules!D41 -> 0 | C43: =SUMIF('Concept Note'!AM:AM,A43,'Concept Note'!AN:AN) -> 0 | D43: =C43/SUM(C:C) -> #DIV/0! | E43: =SUMIF('Concept Note'!$AM:$AM,A43,'Concept Note'!$AO:$AO) -> 0 | F43: =E43/SUM(E:E) -> #DIV/0! | G43: =SUM(C43,E43) -> 0 | H43: =G43/SUM(G:G) -> #DIV/0!
A44: =Modules!C42 -> 0 | B44: =Modules!D42 -> 0 | C44: =SUMIF('Concept Note'!AM:AM,A44,'Concept Note'!AN:AN) -> 0 | D44: =C44/SUM(C:C) -> #DIV/0! | E44: =SUMIF('Concept Note'!$AM:$AM,A44,'Concept Note'!$AO:$AO) -> 0 | F44: =E44/SUM(E:E) -> #DIV/0! | G44: =SUM(C44,E44) -> 0 | H44: =G44/SUM(G:G) -> #DIV/0!
... A52: =Modules!C50 -> 0 | B52: =Modules!D50 -> 0 | C52: =SUMIF('Concept Note'!AM:AM,A52,'Concept Note'!AN:AN) -> 0 | D52: =C52/SUM(C:C) -> #DIV/0! | E52: =SUMIF('Concept Note'!$AM:$AM,A52,'Concept Note'!$AO:$AO) -> 0 | F52: =E52/SUM(E:E) -> #DIV/0! | G52: =SUM(C52,E52) -> 0 | H52: =G52/SUM(G:G) -> #DIV/0!
A57: =MATCH(TRUE,INDEX((Modules!I:I<>0),0),0) -> 2
A58: =MATCH(TRUE,INDEX((INDIRECT(ADDRESS(A57+1,9,1,TRUE,"Modules")):'Modules'!$I$50<>0),0),0) -> 6 | B58: =ADDRESS(A57+1,9,1,TRUE,"Modules") -> Modules!$I$3
B59: =VLOOKUP(86,Modules!$I$8:'Modules'!$I$50,1,FALSE) -> #N/A
B60: =VLOOKUP(86,INDIRECT(ADDRESS(A57+1,9,1,TRUE,"Modules")):'Modules'!$I$50,1,FALSE) -> #N/A
B62: {=INDEX(Modules!I:I,0)} -> 0
B63: =VLOOKUP(86,B62,1,FALSE) -> #N/A
A67: =Modules!C1 -> ModId
A68: =Modules!C2 -> 1
A69: =Modules!C8 -> 2

Sheet Target assumptions - optional
A1: =Translations!$A$69 -> PLEASE PROVIDE TARGET ASSUMPTIONS FOR OUTPUT AND COVERAGE INDICATORS HERE
A2: =Translations!$A$70 -> It is not compulsory to provide target assumptions for the indicators included in the performance framework, however providing additional information on how targets were set may help to reach a common understanding and agreement between the Principal Recipient and the Global Fund Secretariat and speed up the negotiation process.

Sheet Cost assumptions - optional
A1: =Translations!A94 -> PLEASE PROVIDE COST ASSUMPTIONS FOR BUDGET HERE
A2: =Translations!A95 -> It is not compulsory to provide detailed cost assumptions for the budget, however providing additional information may help to reach a common understanding and agreement between the Principal Recipient and the Global Fund Secretariat and speed up the negotiation process.

Sheet Cmp
A1: CmpId | B1: CmpAcro | C1: Label | D1: Component en | E1: Component fr | F1: Component es | G1: Component ru
A2: 1 | B2: H | C2: =OFFSET(D2,0,LangOffset,1,1) -> HIV/AIDS | D2: HIV/AIDS | E2: VIH/SIDA | F2: VIH/SIDA | G2: ВИЧ/СПИД
A3: 2 | B3: T | C3: =OFFSET(D3,0,LangOffset,1,1) -> Tuberculosis | D3: Tuberculosis | E3: Tuberculose | F3: Tuberculosis | G3: Туберкулез
A4: 3 | B4: M | C4: =OFFSET(D4,0,LangOffset,1,1) -> Malaria | D4: Malaria | E4: Paludisme | F4: Malaria | G4: Малярия
A5: 6 | B5: S | C5: =OFFSET(D5,0,LangOffset,1,1) -> HSS | D5: HSS | E5: RSS | F5: FSS | G5: УСЗ

Sheet Modules
A1: CmpId | B1: CmpAcro | C1: ModId | D1: Label | E1: Module en | F1: Module fr | G1: Module es | H1: Module ru
A2: 1 | B2: H | C2: 1 | D2: =OFFSET(E2,0,LangOffset,1,1) -> Prevention - General population | E2: Prevention - General population | F2: Prévention - Population générale | G2: Prevención - Población general | H2: Профилактика для всего населения | I2: =IFERROR(MATCH(C2,'Concept Note'!AM:AM,0),"")
A3: 1 | B3: H | C3: 25 | D3: =OFFSET(E3,0,LangOffset,1,1) -> Prevention - MSM and TGs | E3: Prevention - MSM and TGs | F3: Prévention - HSM et transgenres | G3: Prevención - Hombres que tienen relaciones sexuales con hombres y personas transgénero | H3: Профилактика для МСМ и целевых групп населения
A4: 1 | B4: H | C4: 26 | D4: =OFFSET(E4,0,LangOffset,1,1) -> Prevention - Sex Workers and their clients | E4: Prevention - Sex Workers and their clients | F4: Prévention - Professionnels du sexe et leurs clients | G4: Prevención - Profesionales del sexo y sus clientes | H4: Профилактика для работников секс-бизнеса и их клиентов
A5: 1 | B5: H | C5: 27 | D5: =OFFSET(E5,0,LangOffset,1,1) -> Prevention - Harm-reduction programmes for injecting drug users (IDUs) and their partners | E5: Prevention - Harm-reduction programmes for injecting drug users (IDUs) and their partners | F5: Prévention - Programmes de réduction des méfaits pour les consommateurs de drogues par injection et leurs partenaires | G5: Prevención - Programas de reducción de daños para consumidores de drogas inyectables y sus parejas | H5: Профилактика для ПИН и их партнеров
A6: 1 | B6: H | C6: 29 | D6: =OFFSET(E6,0,LangOffset,1,1) -> Prevention - Adolescents and youth, in and out of school | E6: Prevention - Adolescents and youth, in and out of school | F6: Prévention - Adolescents et jeunes, scolarisés ou non | G6: Prevención - Adolescentes y jóvenes | H6: Профилактика для подростков и молодежи
A7: 1 | B7: H | C7: 28 | D7: =OFFSET(E7,0,LangOffset,1,1) -> Prevention - Other vulnerable populations (please specify) | E7: Prevention - Other vulnerable populations (please specify) | F7: Prévention - Autres populations vulnérables (préciser) | G7: Prevención - Otras poblaciones vulnerables | H7: Профилактика для других язвимых групп населения
A8: 1 | B8: H | C8: 2 | D8: =OFFSET(E8,0,LangOffset,1,1) -> PMTCT | E8: PMTCT | F8: Prévention de la transmission de la mère à l'enfant | G8: PTMI | H8: ППМР | I8: =IFERROR(MATCH(C8,'Concept Note'!AM:AM,0),"")
A9: 1 | B9: H | C9: 3 | D9: =OFFSET(E9,0,LangOffset,1,1) -> Treatment, care and support | E9: Treatment, care and support | F9: Traitement, prise en charge et soutien | G9: Tratamiento, atención y apoyo | H9: Лечение | I9: =IFERROR(MATCH(C9,'Concept Note'!AM:AM,0),"")
A10: 1 | B10: H | C10: 4 | D10: =OFFSET(E10,0,LangOffset,1,1) -> Monitoring and Evaluation | E10: Monitoring and Evaluation | F10: Suivi et évaluation | G10: Seguimiento y evaluación | H10: Мониторинг и оценка | I10: =IFERROR(MATCH(C10,'Concept Note'!AM:AM,0),"")
A11: 1 | B11: H | C11: 5 | D11: =OFFSET(E11,0,LangOffset,1,1) -> Program management | E11: Program management | F11: Gestion de programme | G11: Gestión de programas | H11: Управление программой | I11: =IFERROR(MATCH(C11,'Concept Note'!AM:AM,0),"")
A12: 2 | B12: T | C12: 6 | D12: =OFFSET(E12,0,LangOffset,1,1) -> DOTS-based package | E12: DOTS-based package | F12: Pack DOTS | G12: Paquete basado en DOTS | H12: Пакет мер на основе ДОТС | I12: =IFERROR(MATCH(C12,'Concept Note'!AM:AM,0),"")
A13: 2 | B13: T | C13: 7 | D13: =OFFSET(E13,0,LangOffset,1,1) -> TB/HIV package (in high TB/HIV burden countries or for high risk groups in all countries) | E13: TB/HIV package (in high TB/HIV burden countries or for high risk groups in all countries) | F13: Tuberculose/VIH (dans les pays lourdement touchés par la tuberculose et le VIH ou pour les groupes à haut risque dans tous les pays) | G13: Paquete para tuberculosis/VIH (en países con una carga elevada de tuberculosis/VIH o para grupos de alto riesgo de todos los países) | H13: Пакет мер по борьбе с ТБ/ВИЧ (для стран с высоким бременем ТБ/ВИЧ или для групп населения, подверженных высокому риску, во всех странах) | I13: =IFERROR(MATCH(C13,'Concept Note'!AM:AM,0),"")
A14: 2 | B14: T | C14: 8 | D14: =OFFSET(E14,0,LangOffset,1,1) -> MDR-TB package (in high MDR-TB burden countries or for high risk groups in all countries) | E14: MDR-TB package (in high MDR-TB burden countries or for high risk groups in all countries) | F14: Tuberculose multirésistante (dans les pays lourdement touchés par la tuberculose multirésistante ou pour les groupes à haut risque dans tous les pays) | G14: Paquete para TB-MR (en países con una carga elevada de tuberculosis multirresistente o para grupos de alto riesgo de todos los países) | H14: Пакет мер по борьбе с МЛУ-ТБ (для стран с высоким бременем МЛУ-ТБ или для групп населения, подверженных высокому риску, во всех странах) | I14: =IFERROR(MATCH(C14,'Concept Note'!AM:AM,0),"")
A15: 2 | B15: T | C15: 9 | D15: =OFFSET(E15,0,LangOffset,1,1) -> Human Rights | E15: Human Rights | F15: Droits de l'homme | G15: Derechos humanos | H15: Права человека | I15: =IFERROR(MATCH(C15,'Concept Note'!AM:AM,0),"")
A16: 2 | B16: T | C16: 10 | D16: =OFFSET(E16,0,LangOffset,1,1) -> Monitoring and Evaluation | E16: Monitoring and Evaluation | F16: Suivi et évaluation | G16: Seguimiento y evaluación | H16: Мониторинг и оценка | I16: =IFERROR(MATCH(C16,'Concept Note'!AM:AM,0),"")
A17: 2 | B17: T | C17: 11 | D17: =OFFSET(E17,0,LangOffset,1,1) -> Program Management | E17: Program Management | F17: Gestion de programme | G17: Gestión de programas | H17: Управление программой | I17: =IFERROR(MATCH(C17,'Concept Note'!AM:AM,0),"")
A18: 3 | B18: M | C18: 12 | D18: =OFFSET(E18,0,LangOffset,1,1) -> Vector Control (VC) | E18: Vector Control (VC) | F18: Lutte antivectorielle | G18: Control de vectores | H18: Борьба с переносчиками (БсП) | I18: =IFERROR(MATCH(C18,'Concept Note'!AM:AM,0),"")
A19: 3 | B19: M | C19: 13 | D19: =OFFSET(E19,0,LangOffset,1,1) -> Case Management (CM) | E19: Case Management (CM) | F19: Prise en charge | G19: Gestión de casos | H19: Ведение пациентов (ВП) | I19: =IFERROR(MATCH(C19,'Concept Note'!AM:AM,0),"")
... A30: 6 | B30: S | C30: 24 | D30: =OFFSET(E30,0,LangOffset,1,1) -> Program management (applicable for standalone HSS grants) | E30: Program management (applicable for standalone HSS grants) | F30: Gestion de programme (applicable dans le cadre des subventions indépendantes allouées au renforcement des systèmes de santé) | G30: Gestión de programas (aplicable para subvenciones de FSS independientes) | H30: Управление программой (относится к отдельным грантам по УЗС) | I30: =IFERROR(MATCH(C30,'Concept Note'!AM:AM,0),"")

Sheet Interven
A1: ModId | B1: CmpAcro | C1: Module | D1: IntId | E1: Label | F1: Intervention en | G1: Intervention fr | H1: Intervention es | I1: Intervention ru | J1: En: Scope and description of intervention package (includes human resources required under each intervention) | K1: Fr: Scope… | L1: Es: Scope…
A2: 1 | B2: H | D2: 1 | E2: =OFFSET(F2,0,LangOffset,1,1) -> Behavioural Change as part of programs for General population | F2: Behavioural Change as part of programs for General population | G2: Changement de comportement dans le cadre des programmes destinés à la population générale | H2: Cambio del comportamiento como parte de programas para la población general | I2: Распространение информации о поведенческих изменениях в рамках программ для всего населения
A3: 1 | B3: H | D3: 2 | E3: =OFFSET(F3,0,LangOffset,1,1) -> Condoms as part of programs for General population | F3: Condoms as part of programs for General population | G3: Préservatifs dans le cadre des programmes destinés à la population générale | H3: Preservativos como parte de programas para la población general | I3: Распространение презервативов в рамках программ для всего населения
A4: 1 | B4: H | D4: 3 | E4: =OFFSET(F4,0,LangOffset,1,1) -> Male Circumcision | F4: Male Circumcision | G4: Circoncision masculine | H4: Circuncisión masculina | I4: Мужское обрезание
A5: 1 | B5: H | D5: 4 | E5: =OFFSET(F5,0,LangOffset,1,1) -> HIV testing and Counselling as part of programs for General population | F5: HIV testing and Counselling as part of programs for General population | G5: Dépistage du VIH et conseil dans le cadre des programmes destinés à la population générale | H5: Pruebas de VIH y asesoramiento como parte de programas para la población general | I5: Тестирование на ВИЧ и консультирование по вопросам ВИЧ в рамках программ для всего населения
A6: 1 | B6: H | D6: 5 | E6: =OFFSET(F6,0,LangOffset,1,1) -> Diagnosis and treatment of STIs as part of programs for General population | F6: Diagnosis and treatment of STIs as part of programs for General population | G6: Diagnostic et traitement des infections sexuellement transmissibles dans le cadre des programmes destinés à la population générale | H6: Diagnóstico y tratamiento de ITS como parte de programas para la población general | I6: Диагностика и лечение ИППП в рамках программ для всего населения
A7: 1 | B7: H | D7: 6 | E7: =OFFSET(F7,0,LangOffset,1,1) -> Blood Safety | F7: Blood Safety | G7: Sécurité transfusionnelle | H7: Seguridad hematológica | I7: Безопасность крови
A8: 1 | B8: H | D8: 7 | E8: =OFFSET(F8,0,LangOffset,1,1) -> Orphan and Vulnerable Children (OVC) Package | F8: Orphan and Vulnerable Children (OVC) Package | G8: Orphelins et enfants vulnérables | H8: Paquete para huérfanos y niños vulnerables | I8: Мероприятия по поддержке сирот и уязвимых детей (СУД)
A9: 1 | B9: H | D9: 8 | E9: =OFFSET(F9,0,LangOffset,1,1) -> Community Systems Strengthening -Prevention General Population | F9: Community Systems Strengthening -Prevention General Population | G9: Renforcement des systèmes communautaires : prévention auprès de la population générale | H9: Fortalecimiento de los sistemas comunitarios - Prevención para la población general | I9: Укрепление систем сообществ — профилактика для всего населения
A10: 1 | B10: H | D10: 9 | E10: =OFFSET(F10,0,LangOffset,1,1) -> Removing human rights barriers to accessing services - Prevention General Population | F10: Removing human rights barriers to accessing services - Prevention General Population | G10: Suppression des obstacles aux droits de l'homme afin d'accéder aux services : prévention auprès de la population générale | H10: Supresión de obstáculos relacionados con los derechos humanos para el acceso a servicios - Prevención para la población general | I10: Устранение факторов, имеющих отношение к правам человека и препятствующих доступу к услугам — профилактика всего населения
A11: 1 | B11: H | D11: 10 | E11: =OFFSET(F11,0,LangOffset,1,1) -> RMNCH linkages and Gender Based Violence (GBV) | F11: RMNCH linkages and Gender Based Violence (GBV) | G11: Liens avec la santé génésique, maternelle, néonatale et infantile et violence sexiste | H11: Vínculos entre la salud reproductiva, materna, neonatal e infantil y la violencia de género | I11: Репродуктивное здоровье, здоровье матерей, новорожденных и детей и гендерное насилие
A12: 1 | B12: H | D12: 11 | E12: =OFFSET(F12,0,LangOffset,1,1) -> Other interventions for General Populations - please specify | F12: Other interventions for General Populations - please specify | G12: Autres interventions réalisées auprès de la population générale : veuillez préciser | H12: Otras intervenciones para la población general (especificar) | I12: Другие мероприятия для всего населения (укажите)
A13: 25 | B13: H | D13: 12 | E13: =OFFSET(F13,0,LangOffset,1,1) -> Behavioural Change as part of Programs for MSM and TGs | F13: Behavioural Change as part of Programs for MSM and TGs | G13: Changement de comportement dans le cadre des programmes destinés aux hommes ayant des rapports sexuels avec des hommes et aux transgenres | H13: Cambio de comportamiento como parte de programas para hombres que tienen relaciones sexuales con hombres y personas transgénero | I13: Распространение информации о поведенческих изменениях в рамках программ для МСМ и целевых групп населения
... A51: 29 | B51: H | D51: 50 | E51: =OFFSET(F51,0,LangOffset,1,1) -> Removing human rights barriers to accessing services - Prevention adolescents and youth | F51: Removing human rights barriers to accessing services - Prevention adolescents and youth | G51: Suppression des obstacles aux droits de l'homme afin d'accéder aux services : prévention auprès des jeunes et des adolescents | H51: Supresión de obstáculos relacionados con los derechos humanos para el acceso a servicios - Prevención para adolescentes y jóvenes | I51: Устранение факторов, имеющих отношение к правам человека и препятствующих доступу к услугам — профилактика для подростков и молодежи
A52: 2 | B52: H | C52: PMTCT | D52: 51 | E52: =OFFSET(F52,0,LangOffset,1,1) -> Prong 1: Primary prevention of HIV infection among women of childbearing age | F52: Prong 1: Primary prevention of HIV infection among women of childbearing age | G52: Volet 1 : prévention primaire de l'infection à VIH chez les femmes en âge de procréer | H52: Flanco 1: Prevención primaria de la infección por el VIH en mujeres en edad fértil | I52: Направление 1: первичная профилактика ВИЧ-инфицирования среди женщин детородного возраста
A53: 2 | B53: H | C53: PMTCT | D53: 52 | E53: =OFFSET(F53,0,LangOffset,1,1) -> Prong 2: Preventing unintended pregnancies among women living with HIV | F53: Prong 2: Preventing unintended pregnancies among women living with HIV | G53: Volet 2 : prévention des grossesses non désirées chez les femmes vivant avec le VIH | H53: Flanco 2: Prevención de embarazos no deseados entre mujeres que viven con el VIH | I53: Направление 2: предупреждение нежелательной беременности среди женщин, живущих с ВИЧ
A54: 2 | B54: H | C54: PMTCT | D54: 53 | E54: =OFFSET(F54,0,LangOffset,1,1) -> Prong 3: Preventing vertical HIV transmission | F54: Prong 3: Preventing vertical HIV transmission | G54: Volet 3 : prévention de la transmission verticale du VIH | H54: Flanco 3: Prevención de la transmisión vertical del VIH | I54: Направление 3: профилактика вертикальной передачи ВИЧ-инфекции
A55: 2 | B55: H | C55: PMTCT | D55: 54 | E55: =OFFSET(F55,0,LangOffset,1,1) -> Prong 4: Treatment, care and support to mothers living with HIV and their children and families | F55: Prong 4: Treatment, care and support to mothers living with HIV and their children and families | G55: Volet 4 : traitement, soins et prise en charge pour les mères vivant avec le VIH, ainsi que leurs enfants et familles | H55: Flanco 4: Tratamiento, atención y apoyo para madres que viven con el VIH, así como para sus hijos y familias | I55: Направление 4: надлежащее лечение, уход и поддержка для ВИЧ-инфицированных матерей, их детей и близких
A56: 2 | B56: H | C56: PMTCT | D56: 55 | E56: =OFFSET(F56,0,LangOffset,1,1) -> Community Systems Strengthening - PMTCT | F56: Community Systems Strengthening - PMTCT | G56: Renforcement des systèmes communautaires : prévention de la transmission de la mère à l'enfant | H56: Fortalecimiento de los sistemas comunitarios - PTMI | I56: Укрепление систем сообществ — ППМР
A57: 2 | B57: H | C57: PMTCT | D57: 56 | E57: =OFFSET(F57,0,LangOffset,1,1) -> Removing human rights barriers to accessing services - PMTCT | F57: Removing human rights barriers to accessing services - PMTCT | G57: Suppression des obstacles aux droits de l'homme afin d'accéder aux services : prévention de la transmission de la mère à l'enfant | H57: Supresión de obstáculos relacionados con los derechos humanos para el acceso a servicios - PTMI | I57: Устранение факторов, имеющих отношение к правам человека и препятствующих доступу к услугам — ППМР
A58: 2 | B58: H | C58: PMTCT | D58: 57 | E58: =OFFSET(F58,0,LangOffset,1,1) -> Other interventions for PMTCT- Please specify | F58: Other interventions for PMTCT- Please specify | G58: Autres interventions réalisées pour prévenir la transmission de la mère à l'enfant : veuillez préciser | H58: Otras intervenciones para PTMI (especificar) | I58: Другие мероприятия в целях ППМР (укажите)
A59: 3 | B59: H | C59: Treatment | D59: 58 | E59: =OFFSET(F59,0,LangOffset,1,1) -> Pre-ART Care | F59: Pre-ART Care | G59: Soins préalables au traitement antirétroviral | H59: Pretratamiento antirretroviral | I59: Лечение до начала АРТ
A60: 3 | B60: H | C60: Treatment | D60: 59 | E60: =OFFSET(F60,0,LangOffset,1,1) -> First-line ART – adults | F60: First-line ART – adults | G60: Traitement antirétroviral de première intention : adultes | H60: Tratamiento antirretroviral de primera línea – adultos | I60: АРТ первой линии для взрослых
A61: 3 | B61: H | C61: Treatment | D61: 60 | E61: =OFFSET(F61,0,LangOffset,1,1) -> Second-line ART – adults | F61: Second-line ART – adults | G61: Traitement antirétroviral de deuxième intention : adultes | H61: Tratamiento antirretroviral de segunda línea – adultos | I61: АРТ второй линии для взрослых
A62: 3 | B62: H | C62: Treatment | D62: 61 | E62: =OFFSET(F62,0,LangOffset,1,1) -> Adult multidrug ART after second-line treatment failure | F62: Adult multidrug ART after second-line treatment failure | G62: Multithérapie antirétrovirale chez les adultes après échec du traitement de deuxième intention | H62: Tratamiento antirretroviral multimedicamentoso para adultos tras fracaso en el tratamiento de segunda línea | I62: Многокомпонентная АРТ для взрослых в случае неблагоприятного исхода терапии препаратами первой линии
A63: 3 | B63: H | C63: Treatment | D63: 62 | E63: =OFFSET(F63,0,LangOffset,1,1) -> First-line ART – paediatric | F63: First-line ART – paediatric | G63: Traitement antirétroviral de première intention : enfants | H63: Tratamiento antirretroviral de primera línea – pediátrico | I63: АРТ первой линии для детей
... A122: 11 | B122: T | C122: Program Management | D122: 176 | E122: =OFFSET(F122,0,LangOffset,1,1) -> Other | F122: Other | G122: Autre | H122: Otro | I122: другой
A123: 12 | B123: M | C123: Vector Control (VC) | D123: 114 | E123: =OFFSET(F123,0,LangOffset,1,1) -> Long-lasting Insecticide-treated Nets (LLIN) - Mass Campaign | F123: Long-lasting Insecticide-treated Nets (LLIN) - Mass Campaign | G123: Moustiquaires imprégnées d'insecticide de longue durée : campagne à grande échelle | H123: Mosquiteros tratados con insecticida de larga duración (MILD) – Campaña a gran escala | I123: Сетки, обработанные инсектицидом длительного действия (СОИДД) – массовая кампания | J123: Includes activities related to planning and implementation of mass LLIN distributions, whether targeted to specific population groups or for universal coverage. It includes coordination, planning and budgeting, procurement, logistics, communication, implementation, training, etc. | K123: Comprend les activités liées à la planification et à la mise en œuvre de campagnes de distribution de masse de moustiquaires imprégnées d'insecticide de longue durée, qu'elles ciblent des groupes de population spécifiques ou qu'elles visent une couverture universelle. Comprend la coordination, la planification et la budgétisation, les achats, la logistique, la communication, la mise en œuvre, les formations, etc. | L123: Incluye actividades relacionadas con la planificación y ejecución de campañas de distribución de MILD masivas, ya sean dirigidas a grupos de población específicos o de cobertura universal. Aquí se incluyen la coordinación, planificación y creación de presupuestos, adquisición, logística, comunicación, ejecución, formación, etc.
A124: 12 | B124: M | C124: Vector Control (VC) | D124: 115 | E124: =OFFSET(F124,0,LangOffset,1,1) -> Long-lasting Insecticide-treated Nets (LLIN) - Routine Distribution | F124: Long-lasting Insecticide-treated Nets (LLIN) - Routine Distribution | G124: Moustiquaires imprégnées d'insecticide de longue durée : distribution régulière | H124: Mosquiteros tratados con insecticida de larga duración (MILD) – Distribución rutinaria | I124: Сетки, обработанные инсектицидом длительного действия (СОИДД) – регулярное распространение | J124: This intervention encompasses efforts to start, strengthen or scale up continuous delivery of LLINs through antenatal care (ANC) clinics, the Expanded Programme on Immunization (EPI), or other routine services at public and private health facilities, to sustain high LLIN coverage. It includes activities related to- Coordination and Planning; Training; Logistics; Communication; Supervision, etc. | K124: Cette intervention comprend les mesures visant à commencer, renforcer ou intensifier la distribution continue de moustiquaires imprégnées d’insecticide longue durée à travers les centres de consultations prénatales, le Programme élargi de vaccination (PEV) ou tout autre service courant fourni dans des établissements de santé publics et privés, afin de maintenir une forte couverture en moustiquaires imprégnées d'insecticide de longue durée. Comprend les activités liées à la coordination et à la planification, aux formations, à la logistique, à la communication, à la supervision, etc. | L124: Esta intervención entraña esfuerzos destinados a iniciar, fomentar o ampliar la entrega continua de MILD a través de clínicas de atención prenatal, el Programa Ampliado de Inmunización u otros servicios rutinarios en centros de salud públicos y privados con el fin de mantener una cobertura de MILD alta. Incluye actividades relacionadas con la coordinación y planificación, formación, logística, comunicación, supervisión, etc.
A125: 12 | B125: M | C125: Vector Control (VC) | D125: 116 | E125: =OFFSET(F125,0,LangOffset,1,1) -> Indoor Residual Spraying (IRS) | F125: Indoor Residual Spraying (IRS) | G125: Pulvérisation intradomiciliaire d’insecticide à effet rémanent | H125: Fumigación de interiores con insecticidas de acción residual (IRS) | I125: Обработка помещений инсектицидами длительного действия | J125: It includes planning and implementation of Indoor Residual Spraying campaigns as well as enumeration of households to be sprayed. Activities include procurement of insecticides, equipment, other commodities, IEC material for IRS campaigns, trainings, etc. | K125: Comprend la planification et la mise en œuvre de campagnes de pulvérisation intradomiciliaire d'insecticide à effet rémanent ainsi que le recensement des foyers à traiter. Comprend les activités liées à l'approvisionnement en insecticides, en équipements et autres produits de base, les supports IEC pour les campagnes de pulvérisation intradomiciliaire d'insecticide à effet rémanent, les formations, etc. | L125: Incluye la planificación y puesta en práctica de campañas de fumigación de interiores con insecticidas de acción residual, así como la enumeración de hogares por fumigar. Entre las actividades, se incluyen la adquisición de insecticidas, equipamiento, otros productos, material de IEC para campañas de IRS, formación, etc.
A126: 12 | B126: M | C126: Vector Control (VC) | D126: 117 | E126: =OFFSET(F126,0,LangOffset,1,1) -> Other Vector Control Measures | F126: Other Vector Control Measures | G126: Autres mesures de lutte antivectorielle | H126: Otras medidas de control de vectores | I126: Другие меры борьбы с переносчиками | J126: This includes environmental management strategies that can reduce or eliminate vector breeding grounds, through improved design or operation of water resources development projects; and the use of biological controls (e.g. bacterial larvicides and larvivorous fish) that target and kill vector larvae. In addtion it includes chemical larvicides and adulticides that reduce disease transmission by shortening or interrupting the lifespan of vectors. | K126: Comprend les stratégies de gestion de l'environnement susceptibles de réduire ou de supprimer les gîtes larvaires de vecteurs par une amélioration de la conception ou de la mise en œuvre des projets de développement des ressources en eau, ainsi que l'utilisation de contrôles biologiques (par exemple, larvicides bactériens ou poissons larvivores) pour cibler et tuer les larves de vecteurs. Comprend également les larvicides et adulticides chimiques permettant de réduire les cas de transmission en raccourcissant la durée de vie des vecteurs ou en les tuant. | L126: Aquí se incluyen estrategias de gestión medioambiental que permitan reducir o eliminar criaderos de vectores a través de una mejora en el diseño o funcionamiento de los proyectos de desarrollo de recursos hídricos, así como el uso de controles biológicos (como larvicidas bacterianos y peces larvívoros) dirigidos a la eliminación de larvas de vectores. Incluye, además, adulticidas y larvicidas químicos que reducen la transmisión de enfermedades al acortar u obstaculizar la vida de los vectores.
A127: 12 | B127: M | C127: Vector Control (VC) | D127: 118 | E127: =OFFSET(F127,0,LangOffset,1,1) -> Entomological Monitoring | F127: Entomological Monitoring | G127: Surveillance entomologique | H127: Seguimiento entomológico | I127: Энтомологический мониторинг | J127: Includes activities to determine and characterize the dominant mosquito species in the area, vector density, biting behaviour as well as test mosquitoes' susceptibility to insecticides. The activities range from planning for entomological monitoring and implementation, mosquito collection and testing, procurement of entomological equipment, training, maintenance of insectary, etc. | K127: Comprend les activités visant à déterminer et à caractériser l'espèce de moustique dominante dans la région, la densité des vecteurs et le comportement de piqûre, mais également à tester la sensibilité des moustiques aux insecticides. Comprend les activités liées à la planification d'un système de surveillance entomologique et à sa mise en œuvre, la collecte de moustiques, les tests réalisés sur les moustiques, l'approvisionnement en matériel entomologique, les formations, l'entretien des insectariums, etc. | L127: Incluye actividades encaminadas a determinar y caracterizar las especies de mosquitos dominantes en el área, la densidad del vector, el comportamiento de picadura, así como pruebas de susceptibilidad de los mosquitos a los insecticidas. Las actividades abarcan la planificación del seguimiento entomológico y su ejecución, recogida de mosquitos y prueba, adquisición de equipo entomológico, formación, mantenimiento de insectario, etc.
A128: 12 | B128: M | C128: Vector Control (VC) | D128: 119 | E128: =OFFSET(F128,0,LangOffset,1,1) -> ACSM | F128: ACSM | G128: Sensibilisation, communication et mobilisation sociale | H128: Actividades de Promoción, Comunicación y Movilización Social | I128: Адвокация, коммуникация и социальная мобилизация (АКСМ) | J128: It includes advocacy, communication and social mobilization activities related to vector control- Preparation of advocacy kits (including kits for CBOs and NGOs); sensitization and mobilisation events targeting the policy makers and key players; periodic multi-media campaigns, radio and TV instructional series, jingles, billboards and community radio, etc.; development and distributtion of IEC materials; training of community health workers and community volunteers on effective BCC and Community Mobilisation on malaria; periodic sensitization meetings for opinion leaders at community and village level. | K128: Comprend les activités de sensibilisation, de communication et de mobilisation sociale liées à la lutte antivectorielle : préparation de kits de sensibilisation (comprenant les kits pour les organisations communautaires et les organisations non gouvernementales) ; manifestations de sensibilisation et de mobilisation ciblant les décideurs et les acteurs clés ; campagnes multimédias périodiques, émissions TV et radio éducatives, chansons publicitaires, panneaux d'affichage, radio communautaire, etc. ; élaboration et diffusion de supports IEC ; formation des agents de santé communautaires et des volontaires de la communauté sur l'efficacité d'une communication pour le changement de comportement et d'une mobilisation communautaire pour lutter contre le paludisme ; réunions de sensibilisation périodiques des leaders d'opinion au niveau des villages et des communautés. | L128: Incluye actividades de promoción, comunicación y movilización social relacionadas con el control de vectores: preparación de kits de promoción (incluidos kits para OBC y ONG); eventos de sensibilización y movilización dirigidos a los responsables de formular las políticas y a otros actores clave; campañas multimediales periódicas, series instructivas de radio y TV, sintonías y vallas publicitarias, radio comunitaria, etc.; desarrollo y distribución de material de IEC; formación de trabajadores de salud y voluntarios comunitarios en comunicación para el cambio de comportamiento y movilización comunitaria sobre la malaria; reuniones de sensibilización periódicas para líderes de opinión de la comunidad y locales.
A129: 13 | B129: M | C129: Case Management (CM) | D129: 120 | E129: =OFFSET(F129,0,LangOffset,1,1) -> Facility-based Treatment | F129: Facility-based Treatment | G129: Traitement en milieu hospitalier | H129: Tratamiento en centro sanitario | I129: Стационарное лечение | J129: Includes activities related to testing and treating malaria cases ranging from procuremnt of diagnositic equipment, rapid diagnostic tests, reagents and anti-malaria drugs, quality assurance of laboratories, training of health care providers and technical assistance. | K129: Comprend les activités liées au dépistage et au traitement des cas de paludisme : approvisionnement en matériel de diagnostic, tests de dépistage rapide, réactifs et médicaments antipaludiques, assurance qualité des laboratoires, formation des prestataires de soins et assistance technique. | L129: Incluye actividades relacionadas con la prueba y el tratamiento de casos de malaria, que abarcan la adquisición de equipo de diagnóstico, pruebas de diagnóstico rápidas, reactivos y medicamentos antipalúdicos, aseguramiento de la calidad de los laboratorios, formación de proveedores de atención sanitaria y asistencia técnica.
A130: 13 | B130: M | C130: Case Management (CM) | D130: 121 | E130: =OFFSET(F130,0,LangOffset,1,1) -> Epidemic preparedness and response | F130: Epidemic preparedness and response | G130: Préparation et riposte aux épidémies | H130: Preparación y respuesta frente a epidemias | I130: Эпидемиологическая готовность и ответные меры
A131: 13 | B131: M | C131: Case Management (CM) | D131: 122 | E131: =OFFSET(F131,0,LangOffset,1,1) -> Integrated Community Case Management (ICCM) | F131: Integrated Community Case Management (ICCM) | G131: Prise en charge des cas intégrée au niveau communautaire | H131: Gestión de casos integrada en la comunidad | I131: Комплексное ведение больных на уровне сообществ
A132: 13 | B132: M | C132: Case Management (CM) | D132: 123 | E132: =OFFSET(F132,0,LangOffset,1,1) -> Active Case Detection and Investigation (malaria elimination phase) | F132: Active Case Detection and Investigation (malaria elimination phase) | G132: Dépistage et enquête actifs de cas (phase d'élimination du paludisme) | H132: Detección activa de casos e investigación (fase de eliminación de la malaria) | I132: Активное выявление и расследование случаев заболевания (этап ликвидации малярии)
A133: 13 | B133: M | C133: Case Management (CM) | D133: 124 | E133: =OFFSET(F133,0,LangOffset,1,1) -> Therapeutic Efficacy Surveillance | F133: Therapeutic Efficacy Surveillance | G133: Surveillance de l'efficacité thérapeutique | H133: Vigilancia de la eficacia terapéutica | I133: Контроль эффективности лечения
A134: 13 | B134: M | C134: Case Management (CM) | D134: 125 | E134: =OFFSET(F134,0,LangOffset,1,1) -> Severe Malaria | F134: Severe Malaria | G134: Paludisme grave | H134: Malaria grave | I134: Тяжелые случаи малярии
A135: 13 | B135: M | C135: Case Management (CM) | D135: 126 | E135: =OFFSET(F135,0,LangOffset,1,1) -> Private Sector Co-Payment Mechanism | F135: Private Sector Co-Payment Mechanism | G135: Programme de participation du secteur privé | H135: Mecanismo de copago con el sector privado | I135: Механизм совместного финансирования с участием частного сектора
A136: 13 | B136: M | C136: Case Management (CM) | D136: 127 | E136: =OFFSET(F136,0,LangOffset,1,1) -> Private sector case management (other) | F136: Private sector case management (other) | G136: Prise en charge dans le secteur privé (autres) | H136: Gestión de casos del sector privado (otros) | I136: Ведение пациентов частного сектора (другое)
A137: 13 | B137: M | C137: Case Management (CM) | D137: 128 | E137: =OFFSET(F137,0,LangOffset,1,1) -> Ensuring Drug Quality | F137: Ensuring Drug Quality | G137: Autorité nationale de réglementation des médicaments | H137: Organismo nacional de reglamentación farmacéutica | I137: Национальный регуляторный орган по медпрепаратам
A138: 13 | B138: M | C138: Case Management (CM) | D138: 129 | E138: =OFFSET(F138,0,LangOffset,1,1) -> ACSM | F138: ACSM | G138: Sensibilisation, communication et mobilisation sociale | H138: Actividades de Promoción, Comunicación y Movilización Social | I138: Адвокация, коммуникация и социальная мобилизация (АКСМ) | J138: It includes advocacy, communication and social mobilization activities related to malaria case mangement- Preparation of advocacy kits (including kits for CBOs and NGOs); sensitization and mobilisation events targeting the policy makers and key players; periodic multi-media campaigns, radio and TV instructional series, jingles, billboards and community radio, etc.; development and distributtion of IEC materials; training of community health workers and community volunteers on effective BCC and Community Mobilisation on malaria; periodic sensitization meetings for opinion leaders at community and village level. | K138: Comprend les activités de sensibilisation, de communication et de mobilisation sociale liées à la prise en charge des cas de paludisme : préparation de kits de sensibilisation (comprenant les kits pour les organisations communautaires et les organisations non gouvernementales) ; manifestations de sensibilisation et de mobilisation ciblant les décideurs et les acteurs clés ; campagnes multimédias périodiques, émissions TV et radio éducatives, chansons publicitaires, panneaux d'affichage, radio communautaire, etc. ; élaboration et diffusion de supports IEC ; formation des agents de santé communautaires et des volontaires de la communauté sur l'efficacité d'une communication pour le changement de comportement et d'une mobilisation communautaire pour lutter contre le paludisme ; réunions de sensibilisation périodiques des leaders d'opinion au niveau des villages et des communautés. | L138: Incluye actividades de promoción, comunicación y movilización social relacionadas con la gestión de casos de malaria: preparación de kits de promoción (incluidos kits para OBC y ONG); eventos de sensibilización y movilización dirigidos a los responsables de formular las políticas y a otros actores clave; campañas multimediales periódicas, series instructivas de radio y TV, sintonías y vallas publicitarias, radio comunitaria, etc.; desarrollo y distribución de material de IEC; formación de trabajadores de salud y voluntarios comunitarios en comunicación para el cambio de comportamiento y movilización comunitaria sobre la malaria; reuniones de sensibilización periódicas para líderes de opinión de la comunidad y locales.
A139: 13 | B139: M | C139: Case Management (CM) | D139: 174 | E139: =OFFSET(F139,0,LangOffset,1,1) -> Other | F139: Other | G139: Autre | H139: Otro | I139: другой
A140: 14 | B140: M | C140: Specific Prevention Interventions (SPI) | D140: 130 | E140: =OFFSET(F140,0,LangOffset,1,1) -> Intermittent Preventive Treatment (IPT) - in Pregnancy | F140: Intermittent Preventive Treatment (IPT) - in Pregnancy | G140: Traitement préventif intermittent : femmes enceintes | H140: Tratamiento preventivo intermitente (TPI) – en el embarazo | I140: Периодическое профилактическое лечение (ППЛ) – во время беременности | J140: Includes procurement and provision of of intermittent preventive treatment with sulfadoxine-pyrimethamine during pregnancy. | K140: Comprend l'approvisionnement en traitements préventifs intermittents à base de sulfadoxine-pyriméthamine pendant la grossesse et leur mise à disposition. | L140: Incluye la adquisición y suministro de tratamiento preventivo intermitente con sulfadoxina/pirimetamina durante el embarazo.
A141: 14 | B141: M | C141: Specific Prevention Interventions (SPI) | D141: 131 | E141: =OFFSET(F141,0,LangOffset,1,1) -> Intermittent Preventive Treatment (IPT) - in Infancy | F141: Intermittent Preventive Treatment (IPT) - in Infancy | G141: Traitement préventif intermittent : nourrissons | H141: Tratamiento preventivo intermitente – en la lactancia | I141: Периодическое профилактическое лечение (ППЛ) – в младенческом возрасте | J141: It refers to activities related to administration of a full therapeutic course of sulfadoxine-pyrimethamine delivered through the Expanded Program on immunization (EPI) at defined intervals corresponding to routine vaccination schedules | K141: Comprend les activités liées à l'administration de cycles de traitement complets par sulfadoxine-pyriméthamine par l'intermédiaire du Programme élargi de vaccination (PEV) à des intervalles précis correspondant aux calendriers de vaccination systématique | L141: Hace referencia a actividades asociadas a la administración de un curso terapéutico completo con sulfadoxina/pirimetamina a través del Programa Ampliado de Inmunización a intervalos definidos correspondientes a los programas de vacunación rutinarios.
A142: 14 | B142: M | C142: Specific Prevention Interventions (SPI) | D142: 132 | E142: =OFFSET(F142,0,LangOffset,1,1) -> Seasonal Malaria Chemoprevention | F142: Seasonal Malaria Chemoprevention | G142: Chimioprévention du paludisme saisonnier | H142: Quimioprevención estacional de la malaria | I142: Химиопрофилактика сезонной малярии | J142: It includes activities (in areas with highly seasonal malaria transmission) related to intermittent administration of full treatment courses of an antimalarial medicine during the malaria season to prevent malarial illness by maintaining therapeutic antimalarial drug concentrations in the blood throughout the period of greatest malarial risk. The activities include procurement of anti-malarials (AQ-SP), pharmacovigilance, drug resistance monitoring, etc. | K142: Comprend les activités (dans les zones où la transmission du paludisme se caractérise par une forte saisonnalité) liées à l'administration par intermittence de cycles de traitement antipaludique complets pendant la saison de transmission du paludisme afin de prévenir les épisodes de paludisme, l'objectif étant de maintenir des concentrations thérapeutiques en médicament antipaludique dans le sang pendant toute la période où le risque palustre est le plus élevé. Comprend les activités liées à l'approvisionnement en antipaludéens (AQ-SP), à la pharmacovigilance, au suivi de la pharmacorésistance, etc. | L142: Incluye actividades (en áreas con una alta transmisión de malaria estacional) relacionadas con la administración intermitente de cursos de tratamiento completos con un medicamento antipalúdico durante la estación de transmisión de la malaria con el fin de prevenir la enfermedad gracias al mantenimiento de concentraciones terapéuticas de dicho medicamento en la sangre durante el período de mayor riesgo. Entre estas actividades, se incluye la adquisición de medicamentos antipalúdicos (amodiaquina y sulfadoxina/pirimetamina), farmacovigilancia, seguimiento de la resistencia a los medicamentos, etc.
A143: 14 | B143: M | C143: Specific Prevention Interventions (SPI) | D143: 173 | E143: =OFFSET(F143,0,LangOffset,1,1) -> Other | F143: Other | G143: Autre | H143: Otro | I143: другой
A144: 15 | B144: M | C144: Monitoring and Evaluation (ME) | D144: 133 | E144: =OFFSET(F144,0,LangOffset,1,1) -> Routine Reporting | F144: Routine Reporting | G144: Communication régulière de l'information | H144: Presentación de informes rutinarios | I144: Регулярная отчетность | J144: Routine data collection, recording and reporting of out-patients, in-patients and deaths (HMIS, sentinel sites or other systems); microscopy and RDT tests and treatment; reporting on stock-outs; data collection and reporting from other care providers (private, communities and civil society); reporting on ITN/LLIN distribution, IRS; printing of reporting forms; training on data entry and reporting; data verification; health facility assessment including quality of services | K144: Collecte régulière des données, enregistrement des patients ambulatoires, des patients hospitalisés et des décès (système d’information sur la gestion de la santé, sites sentinelles ou autres systèmes), et communication de l'information y afférente ; microscopie et tests de dépistage rapide, et traitement ; communication de l'information liée aux ruptures de stock ; collecte des données et communication de l'information par d'autres prestataires de soins (secteur privé, communautés et société civile) ; communication de l'information liée à la distribution de moustiquaires imprégnées d'insecticide ou de moustiquaires imprégnées d'insecticide de longue durée, pulvérisation intradomiciliaire d'insecticide à effet rémanent ; impression des formulaires de notification ; formations sur la saisie et la communication des données ; vérification des données ; évaluation de l'établissement de santé comprenant la qualité des services | L144: Recopilación de datos rutinaria, registro y presentación de informes sobre pacientes extrahospitalarios, hospitalarios y muertes (sistema de información sobre gestión sanitaria, centros centinela u otros sistemas); pruebas microscópicas y PDR y tratamiento; notificación de desabastecimientos; recopilación de datos e informes de otros proveedores de servicios de atención sanitaria (privados, comunidades y sociedad civil); informes sobre MTI/MILD, IRS; impresión de formularios para presentación de informes; formación en entrada de datos y presentación de informes; verificación de datos; evaluación de centros de salud, incluida la calidad de los servicios.
A145: 15 | B145: M | C145: Monitoring and Evaluation (ME) | D145: 134 | E145: =OFFSET(F145,0,LangOffset,1,1) -> Analysis, Review and Transparency | F145: Analysis, Review and Transparency | G145: Analyse, examen et transparence | H145: Análisis, revisión y transparencia | I145: Анализ, оценка и прозрачность | J145: Ananalysis, interpretation and use of data and evidence generated through Malaria program reviews, evaluation of whole or a specific component of the program; development and sharing of quarterly, semi annual or annual reports through websites/ publications; Operations Research- specific to any of the components of Maria control program | K145: Analyse, interprétation et utilisation des données et des preuves obtenues par le biais des examens du programme de lutte contre le paludisme, évaluation du programme dans son intégralité ou d'une de ses composantes spécifiques ; élaboration et partage des rapports trimestriels, semestriels ou annuels grâce à des sites web et des publications ; recherche opérationnelle (spécifique aux composantes du programme de lutte contre le paludisme) | L145: Análisis, interpretación y uso de datos y pruebas generados por medio de las revisiones de los programas de malaria, evaluación de componentes globales o específicos del programa; desarrollo y uso compartido de informes trimestrales, semestrales o anuales a través de sitios web/publicaciones; Investigación operativa: específica de cualquiera de los componentes del programa de control de malaria.
A146: 15 | B146: M | C146: Monitoring and Evaluation (ME) | D146: 135 | E146: =OFFSET(F146,0,LangOffset,1,1) -> Surveys | F146: Surveys | G146: Enquête | H146: Encuestas | I146: Надзор | J146: Household surveys (e.g. DHS, MICS and MIS) to monitor anemia/ parasitemia prevalence, under-5 mortality and ITN/IRS/IPT/treatment coverage implemented | K146: Enquêtes réalisées auprès des ménages (par exemple, enquêtes démographiques et de santé, enquêtes en grappes à indicateurs multiples et enquêtes sur les indicateurs du paludisme) pour suivre l'évolution de la prévalence de l'anémie et de la parasitémie, du taux de mortalité chez les enfants de moins de 5 ans et de la couverture en moustiquaires imprégnées d'insecticide/pulvérisation intradomiciliaire d'insecticide à effet rémanent/traitement préventif intermittent/traitement mise en œuvre | L146: Encuestas a hogares (por ejemplo, EDS, EGIM y MIS) para supervisar la prevalencia de anemia/parasitemia, mortalidad en menores de 5 años y cobertura de MTI/IRS/TPI/tratamiento aplicada.
A147: 15 | B147: M | C147: Monitoring and Evaluation (ME) | D147: 136 | E147: =OFFSET(F147,0,LangOffset,1,1) -> Administrative and Finance Data Sources | F147: Administrative and Finance Data Sources | G147: Sources de données administratives et financières | H147: Fuentes de datos económicos y administrativos | I147: Источники административных и финансовых данных | J147: Includes establishing systems for periodic (annual) reporting on key health administrative and service availability statistics, such as- Health workforce, inventory of health care providers and institutions National Health Accounts and Malaria sub-accounts; annual review of national malaria program budget and expenditures by funding source; expenditure studies according to WHO-GMP reporting guideline; Establishing and maintaining Logistics Management Information system (LMIS) | K147: Comprend la mise en place de systèmes de communication de l'information périodique (annuelle) sur les statistiques clés en matière d'administration de la santé et de disponibilité des services, tels que le personnel de santé, l'inventaire des prestataires des soins et les institutions Comptes nationaux de la santé et sous-comptes paludisme ; examen annuel du budget et des dépenses consacrés au programme national de lutte contre le paludisme par source de financement ; étude des dépenses selon les directives établies par l'Organisation mondiale de la Santé et les bonnes pratiques de fabrication en matière de communication de l'information ; mise en place et maintien du système informatique de gestion de la logistique | L147: Incluye el establecimiento de sistemas para la presentación de informes periódicos (anuales) de estadísticas clave referentes a administración sanitaria y disponibilidad de servicios, como personal de salud, inventario de proveedores de atención sanitaria e instituciones. Cuentas Nacionales de Salud y cuentas secundarias de la malaria; revisión anual del presupuesto y gastos del programa nacional para la malaria por fuente de financiamiento; estudios del gasto conformes a las directrices de presentación de informes de la OMS/Programa Mundial sobre Malaria; establecimiento y mantenimiento del sistema de información de gestión logística.
A148: 15 | B148: M | C148: Monitoring and Evaluation (ME) | D148: 137 | E148: =OFFSET(F148,0,LangOffset,1,1) -> Vital Registration System | F148: Vital Registration System | G148: Système de registre d’état civil | H148: Sistema de registro civil | I148: Системы регистрации актов гражданского состояния | J148: Establishing/ strengthening and scale up of Vital registration information system including Sample Vital Registration systems, strengthening reporting of hospital morbidity and mortality statistics, cause of death, establishment of SMS system of reporting; training of community health workers on reporting vital events, drug stock-outs etc. | K148: Mise en place/renforcement et intensification des systèmes de registre d'état civil, y compris des systèmes de registre d'échantillons, renforcement de la communication de l'information relative aux statistiques de morbidité et de mortalité à l'hôpital, cause de décès, mise en place d'un système de communication de l'information par SMS ; formation des agents de santé communautaires sur la communication de l'information relative aux données de l'état civil, ruptures de stock de médicaments, etc. | L148: Establecimiento, fortalecimiento y ampliación del sistema de información de registro civil, incluidos sistemas de registro vital de muestra, fortalecimiento del sistema de presentación de informes para estadísticas de mortalidad y morbilidad hospitalaria, causa de muerte y establecimiento de un sistema SMS para generación de informes; formación del personal de salud de la comunidad en presentación de informes sobre eventos esenciales, desabastecimiento de medicamentos, etc.
A149: 15 | B149: M | C149: Monitoring and Evaluation (ME) | D149: 172 | E149: =OFFSET(F149,0,LangOffset,1,1) -> Other | F149: Other | G149: Autre | H149: Otro | I149: другой
A150: 16 | B150: M | C150: Program Management (PM) | D150: 138 | E150: =OFFSET(F150,0,LangOffset,1,1) -> Planning, coordination and management | F150: Planning, coordination and management | G150: Planification, coordination et gestion | H150: Planificación, coordinación y gestión | I150: Планирование, координация и управление | J150: Includes- Activities at the administrative level outside the point of health care delivery, such as development of national strategic plans and annual operational plans and budgets; oversight, technical assistance and supervision from national to subnational levels; human resource- planning/ staffing and overheads, operational costs; coordination with district and local authorities; quarterly meetings, training, and office/IT equipment; partnering process including Malaria advocacy and communication carried out by partners and Malaria program; mobilizing leaders to support implementation and sustainability of the program | K150: Comprend les activités administratives menées en dehors du point de prestation de services de soins, par exemple : élaboration des plans stratégiques nationaux ainsi que des plans opérationnels et des budgets annuels ; suivi, assistance technique et supervision du niveau national au niveau infranational ; ressources humaines : planification/dotation en effectifs et frais généraux, frais de fonctionnement ; coordination avec les autorités locales et instances de districts ; réunions trimestrielles, formations et matériel informatique et bureautique ; procédure d'établissement de partenariats incluant la sensibilisation à la lutte contre le paludisme et les activités de communication menées par les partenaires et les acteurs du programme de lutte contre le paludisme ; mobilisation des responsables pour appuyer la mise en œuvre et la viabilité du programme | L150: Incluye actividades de nivel administrativo, ajenas a la prestación de servicios de atención sanitaria, como desarrollo de planes estratégicos nacionales y planes y presupuestos operativos anuales; supervisión, asistencia técnica y control en los niveles nacional y subnacional; planificación de recursos humanos, personal, gastos generales y operativos; coordinación con las autoridades locales y del distrito; reuniones trimestrales, formación y equipo informático/de oficina; procesos de asociación y colaboración, incluidas actividades de promoción y comunicación desempeñadas por socios y programas para la malaria; movilización de líderes para apoyar la ejecución del programa y su sostenibilidad.
A151: 16 | B151: M | C151: Program Management (PM) | D151: 139 | E151: =OFFSET(F151,0,LangOffset,1,1) -> Grant Management | F151: Grant Management | G151: Gestion de subvention | H151: Gestión de subvenciones | I151: Управление грантами | J151: Includes specific Global Fund grant management related activities at the PMU/PR/SR level. These could include- development and submission of grant documents; oversight and technical assistance related to Global Fund grant implementation and management and specific Global Fund requirements; supervision from PR to SR level (applicable when national malaria program is not the PR); human resource planning/ staffing and overheads, operational costs; coordination with national program, district and local authorities; quarterly meetings, training, and office/IT equipment at PR/SR level; mobilizing leaders to support implementation and sustainability of the program | K151: Comprend les activités spécifiques liées à la gestion des subventions du Fonds mondial au niveau de l'unité de gestion de projet, du récipiendaire principal ou des sous-récipiendaires. Exemples : élaboration et transmission de documents de subvention ; supervision et assistance technique liées à la mise en œuvre et à la gestion des subventions du Fonds mondial et aux exigences spécifiques du Fonds mondial ; supervision du niveau du récipiendaire principal au niveau des sous-récipiendaires (applicable lorsque le programme national de lutte contre le paludisme n'est pas le récipiendaire principal) ; planification des ressources humaines/dotation en effectifs et frais généraux, frais de fonctionnement ; coordination avec le programme national, les autorités locales et les instances de districts ; réunions trimestrielles, formations et matériel informatique et bureautique au niveau du récipiendaire principal ou des sous-récipiendaires ; mobilisation des responsables pour appuyer la mise en œuvre et la viabilité du programme | L151: Incluye actividades relacionadas con la gestión de las subvenciones específicas del Fondo Mundial en el nivel de unidad de gestión de programas/receptor principal/subreceptor. Aquí podrían incluirse el desarrollo y presentación de documentos de las subvenciones; supervisión y asistencia técnica asociadas a la ejecución y gestión de las subvenciones del Fondo Mundial, y requisitos específicos del Fondo Mundial; supervisión desde el nivel de receptor principal a subreceptor, aplicable cuando el programa nacional para la malaria no es el receptor principal; planificación de recursos humanos, personal, gastos generales y operativos; coordinación con las autoridades del programa nacional, locales y del distrito; reuniones trimestrales, formación y equipo informático/de oficina en el nivel de receptor principal/subreceptor; movilización de líderes para apoyar la ejecución de programa y su sostenibilidad.
A152: 16 | B152: M | C152: Program Management (PM) | D152: 171 | E152: =OFFSET(F152,0,LangOffset,1,1) -> Other | F152: Other | G152: Autre | H152: Otro | I152: другой
A153: 17 | B153: S | C153: Service Delivery | D153: 140 | E153: =OFFSET(F153,0,LangOffset,1,1) -> Infrastructure | F153: Infrastructure | G153: Infrastructure | H153: Infraestructura | I153: Инфраструктура | J153: This intervention aims to support the scale-up, accessibility, availability and quality of health services including facility and community-level service delivery, such as- upgrading or scaling-up service delivery infrastructure including facilities, equipment, furniture, vehicles etc. It also includes necessary operational inputs that are necessary for uninterrupted seervice delivey. These activities benefit more than one of the three disease outcomes (HIV, TB, malaria), and may also have broader reach to other health outcomes (e.g. MNCH, SRHR) at the hospital, primary care and community levels. Similar activities benefitting only one disease may be included in a disease grant. These activities do not include large-scale construction projects (e.g. building a multi-functional hospital) | K153: Cette intervention vise à appuyer l'intensification, l'accessibilité, la disponibilité et la qualité des services de santé, y compris les prestations de services fournies au niveau des formations sanitaires et au niveau communautaire, par exemple : modernisation ou renforcement des infrastructures de services, notamment les établissements, les équipements, le mobilier, les véhicules, etc. Elle comprend également les résultats opérationnels nécessaires pour des prestations de services continues. Ces activités bénéficient à plus d'une des trois maladies (VIH, tuberculose, paludisme) et leur portée peut également être élargie à d'autres résultats sanitaires (par exemple, santé maternelle, néonatale et infantile, droit à la santé sexuelle et reproductive) au niveau de l'hôpital, du secteur des soins de santé primaires et de la communauté. Les activités similaires bénéficiant à seulement une maladie peuvent être incluses dans une subvention de lutte contre la maladie. Ces activités ne comprennent pas les projets de construction à grande échelle (par exemple, construction d'un hôpital multifonctionnel) | L153: El objetivo de esta intervención es fomentar la ampliación, accesibilidad, disponibilidad y calidad de los servicios de salud, incluida la prestación de servicios en los niveles de comunidad y centro, como actualización o ampliación de la infraestructura de prestación de servicios, incluidas instalaciones, equipo, mobiliario, vehículos, etc. También incluye los recursos operativos necesarios para promover una prestación de servicios ininterrumpida. Estas actividades mejoran los resultados indirectos en más de una de las tres enfermedades (VIH, tuberculosis, malaria) y podrían tener un mayor alcance, extendiéndose a otros resultados indirectos en materia de salud (como salud maternoinfantil y derecho a la salud sexual y reproductiva) en los niveles hospitalario, de atención primaria y comunitario. Actividades análogas que beneficien sólo a una enfermedad podrían incluirse en una subvención para la enfermedad específica. Dichas actividades no incluyen proyectos de construcción a gran escala (como la construcción de un hospital policlínico).
A154: 17 | B154: S | C154: Service Delivery | D154: 141 | E154: =OFFSET(F154,0,LangOffset,1,1) -> Service organization and facility management | F154: Service organization and facility management | G154: Organisation des services et gestion des établissements | H154: Organización de servicios y gestión de instalaciones | I154: Сервисные организации и управление медучреждениями | J154: Includes activities that are aimed to improve effectiveness and efficiency of organizational management systems for service delivery such as training healthcare managers at all levels, developing and implementing policies and regulations related to service delivery, organization and management (e.g. referral system, waste management etc.), developing supervision mechanisms for wuality assuance etc. It also includes necessary operational inputs, which primarily benefit more than one of the three disease outcomes (HIV, TB, malaria) but may also have broader reach to other health outcomes (e.g. MNCH, SRHR…) at the hospital, primary care and community levels; Similar activities benefitting only one disease may be included in a disease grant. | K154: Comprend les activités visant à améliorer l'efficacité et l'efficience des systèmes de gestion organisationnelle pour fournir divers services : formation des responsables de soins de santé à tous les niveaux, élaboration et mise en œuvre de politiques et réglementations liées à la prestation de services, à l'organisation et à la gestion (par exemple, système d'orientation, gestion des déchets, etc.), élaboration de mécanismes de supervision dans le cadre de l'assurance qualité, etc. Cette intervention comprend également les résultats opérationnels nécessaires, qui bénéficient essentiellement à plus d'une des trois maladies (VIH, tuberculose, paludisme) mais dont la portée peut également être élargie à d'autres résultats sanitaires (par exemple, santé maternelle, néonatale et infantile, droit à la santé sexuelle et reproductive, etc.) au niveau de l'hôpital, des établissements des soins de santé primaires et de la communauté ; les activités similaires bénéficiant à seulement une maladie peuvent être incluses dans une subvention de lutte contre la maladie. | L154: Incluye actividades encaminadas a mejorar la eficacia y eficiencia de los sistemas de gestión organizativos para la prestación de servicios, como formación de gestores de servicios sanitarios de todos los niveles, desarrollo y ejecución de políticas y reglamentos asociados a la prestación de servicios, organización y gestión (por ejemplo, sistema de derivación, gestión de residuos, etc.), desarrollo de mecanismos de supervisión para aseguramiento de la calidad, etc. También incluye los insumos operativos necesarios, que mejoran principalmente los resultados indirectos de más de una de las tres enfermedades (VIH, tuberculosis, malaria), pero que pueden tener un mayor alcance y extenderse a otros resultados indirectos en materia de salud (como salud maternoinfantil, derecho a la salud sexual y reproductiva, etc.) en los niveles hospitalario, de atención primaria y comunitario; actividades análogas que beneficien sólo a una enfermedad podrían incluirse en una subvención para la enfermedad específica.
A155: 17 | B155: S | C155: Service Delivery | D155: 142 | E155: =OFFSET(F155,0,LangOffset,1,1) -> Increasing demand for health services | F155: Increasing demand for health services | G155: Demande croissante de services de santé | H155: Aumento de la demanda de servicios de salud | I155: Повышение спроса на услуги здравоохранения | J155: Includes capacity building for leadership & advocacy for service delivery at the community level; Increasing community awareness of service availability; Community mobilization for equitable access to services; | K155: Comprend le renforcement des capacités visant à encadrer et favoriser les prestations de services au niveau communautaire ; sensibilisation accrue de la communauté à la disponibilité des services ; mobilisation communautaire en faveur d'un accès équitable aux services | L155: Incluye capacitación en liderazgo y promoción para prestación de servicios en el nivel comunitario; aumento de la concienciación en la comunidad sobre la disponibilidad de servicios; movilización de la comunidad para un acceso equitativo a los servicios.
A156: 17 | B156: S | C156: Service Delivery | D156: 170 | E156: =OFFSET(F156,0,LangOffset,1,1) -> Other | F156: Other | G156: Autre | H156: Otro | I156: другой
A157: 18 | B157: S | C157: Health Workforce | D157: 143 | E157: =OFFSET(F157,0,LangOffset,1,1) -> Capacity building | F157: Capacity building | G157: Renforcement des capacités | H157: Creación de capacidad | I157: Укрепление потенциала | J157: Activities that are aimed to train health workforce in service delivery and provision of care and support, which primarily benefit more than one of the three disease outcomes (HIV, TB, malaria) but may also have broader reach to other health outcomes (e.g. MNCH, SRHR, etc.); It includes training in integrated packages (e.g. IMCI, RMNCH etc.) which cover one or more of HIV, TB, malaria, but may also go beyond the three diseases. Single disease-specific trainings (e.g. training in new PMTCT guidelines) can be funded by relevant disease grants. | K157: Comprend les activités visant à former le personnel de santé pour fournir des services, assurer des soins et une prise en charge, qui bénéficient essentiellement à plus d'une des maladies (VIH, tuberculose, paludisme) mais dont la portée peut également être élargie à d'autres résultats sanitaires (par exemple, santé maternelle, néonatale et infantile, droit à la santé sexuelle et reproductive, etc.) Comprend des formations intégrées (par exemple, gestion intégrée des maladies infantiles, santé génésique, maternelle, néonatale et infantile, etc.) qui prennent en compte au moins l'une des trois maladies, à savoir le VIH, la tuberculose et le paludisme, mais qui peuvent également dépasser le cadre de ces trois maladies. Les formations uniques propres à chaque maladie (par exemple, formation sur les nouvelles directives relatives à la prévention de la transmission de la mère à l'enfant) peuvent être financées par les subventions de lutte contre la maladie correspondante. | L157: Actividades encaminadas a la formación del personal de salud en la prestación de servicios y provisión de atención y asistencia, que mejoran principalmente los resultados indirectos de más de una de las tres enfermedades (VIH, tuberculosis, malaria), pero que pueden tener un mayor alcance y extenderse a otros resultados indirectos en materia de salud (como salud maternoinfantil, derecho a la salud sexual y reproductiva, etc.). Incluye formación en paquetes integrados (como gestión integrada de enfermedades infantiles, salud reproductiva, materna, neonatal e infantil, etc.), que cubren una o varias de las tres enfermedades (VIH, tuberculosis, malaria), pero que pueden sobrepasar el ámbito de estas. La formación específica para una enfermedad (por ejemplo, formación en nuevas directrices de PTMI) se puede financiar a través de subvenciones para la enfermedad específica.
A158: 18 | B158: S | C158: Health Workforce | D158: 144 | E158: =OFFSET(F158,0,LangOffset,1,1) -> Scaling up and distribution of workforce | F158: Scaling up and distribution of workforce | G158: Renforcement et répartition du personnel | H158: Ampliación y distribución del personal | I158: Расширение охвата и распределение трудовых ресурсов | J158: Activities that are aimed at expansion and scaling up of skilled and competent health workforce, which primarily benefit more than one of the three disease outcomes (HIV, TB, malaria) but may also have broader reach to other health outcomes (e.g. MNCH, SRHR…). Scale-up of multi-disciplinary health workforce (e.g. primary care doctors and nurses, community health workers etc.) is included here. Those who are engaged in single disease-specific practice (e.g. ART clinics), can be supported by relevant disease grant. | K158: Comprend les activités visant à élargir et renforcer le personnel de santé formé et compétent, qui bénéficient essentiellement à plus d'une des trois maladies (VIH, tuberculose, paludisme) mais dont la portée peut également être élargie à d'autres résultats sanitaires (par exemple, santé maternelle, néonatale et infantile, droit à la santé sexuelle et reproductive, etc.) Comprend notamment le renforcement du personnel de santé pluridisciplinaire (par exemple, docteurs et infirmiers en soins de santé primaires, agents de santé communautaires, etc.). Les personnes engagées en faveur d'une maladie spécifique (par exemple, centres de traitement antirétroviral) peuvent bénéficier d'une subvention de lutte contre la maladie correspondante. | L158: Actividades dirigidas a la expansión y ampliación de personal sanitario capacitado y competente, que mejoran principalmente los resultados indirectos de más de una de las tres enfermedades (VIH, tuberculosis, malaria), pero que pueden tener un mayor alcance y extenderse a otros resultados indirectos en materia de salud (como salud maternoinfantil, derecho a la salud sexual y reproductiva, etc.). Aquí se incluye el aumento del personal de salud multidisciplinar (por ejemplo, médicos y enfermeras de atención primaria, trabajadores de salud de la comunidad, etc.). Los implicados en el tratamiento de una enfermedad específica (por ejemplo, clínicas de tratamiento antirretroviral) se pueden financiar por medio de subvenciones para la enfermedad correspondiente.
A159: 18 | B159: S | C159: Health Workforce | D159: 145 | E159: =OFFSET(F159,0,LangOffset,1,1) -> Retention of workforce | F159: Retention of workforce | G159: Fidélisation du personnel | H159: Retención del personal | I159: Удержание работников | J159: Activities that are aimed at improving equitable distribution and retention of skilled and competent health workforce espcially in hard-to-reach areas and serving marginalized populations, which primarily benefit more than one of the three disease outcomes (HIV, TB, malaria) but may also have broader reach to other health outcomes (e.g. MNCH, SRHR, etc.); It includes development and implementation of policies for workforce distribution and retention and financial and non-financial incentives for health workers for service delivery and to increase task shifting between them. Those who are engaged in single disease-specific practice, can be supported by relevant disease grant. | K159: Comprend les activités visant à améliorer la répartition équitable et la fidélisation du personnel de santé qualifié et compétent, notamment dans les zones difficiles d'accès et parmi les populations marginalisées, qui bénéficient essentiellement à plus d'une des trois maladies (VIH, tuberculose, paludisme) mais dont la portée peut également être élargie à d'autres résultats sanitaires (par exemple, santé maternelle, néonatale et infantile, droit à la santé sexuelle et reproductive, etc.). Comprend l'élaboration et la mise en œuvre de politiques visant à répartir et fidéliser le personnel, à proposer des incitations financières et non financières aux agents de santé pour fournir les services et à développer la délégation de tâches entre eux. Les personnes engagées en faveur d'une maladie spécifique peuvent bénéficier d'une subvention de lutte contre la maladie correspondante. | L159: Actividades dirigidas a lograr la distribución más equitativa y la retención del personal de salud capacitado y competente, especialmente en áreas de difícil acceso o con poblaciones marginadas, que mejoran principalmente los resultados indirectos de más de una de las tres enfermedades (VIH, tuberculosis, malaria), pero que pueden tener un mayor alcance y extenderse a otros resultados indirectos en materia de salud (como salud maternoinfantil, derecho a la salud sexual y reproductiva, etc.). Incluye el desarrollo y aplicación de políticas de distribución y retención de trabajadores, así como incentivos, tanto económicos como no económicos, para promover la prestación de servicios y la delegación de funciones entre los trabajadores de salud. Los implicados en el tratamiento de una enfermedad específica se pueden financiar por medio de subvenciones para la enfermedad correspondiente.
A160: 18 | B160: S | C160: Health Workforce | D160: 169 | E160: =OFFSET(F160,0,LangOffset,1,1) -> Other | F160: Other | G160: Autre | H160: Otro | I160: другой
A161: 19 | B161: S | C161: Procurement and Supply Chain Management | D161: 146 | E161: =OFFSET(F161,0,LangOffset,1,1) -> PSM infrastructure | F161: PSM infrastructure | G161: Infrastructure de gestion des achats et des stocks | H161: Infraestructura de la Gestión de Adquisiciones y Suministros (GAS) | I161: Инфраструктура УЗС | J161: Activities which ensure appropriate storage and distribution of medicines, consumables and other products that are necessary for effective delivery of more than one of the three disease services, (HIV, TB and malaria) but may also have broader reach to other health outcomes (e.g. IMCI, TB/HIV, SRHR, comprehensive PMTCT, MNCH). It includes refurbishing or building of storage facilities, purchase of vehicles and hardware and software for the procurement and supply management system. | K161: Comprend les activités qui assurent un stockage et une distribution appropriés de médicaments, consommables et autres produits nécessaires à la prise en charge efficace de plus d'une des trois maladies (VIH, tuberculose et paludisme) mais dont la portée peut également être élargie à d'autres résultats sanitaires (par exemple, gestion intégrée des maladies infantiles, tuberculose/VIH, droit à la santé sexuelle et reproductive, prévention systématique de la transmission de la mère à l'enfant, santé maternelle, néonatale et infantile). Comprend la réhabilitation ou la construction de structures de stockage ainsi que l'achat de véhicules, de matériel et de logiciels pour le système de gestion des achats et de l'approvisionnement. | L161: Actividades que garantizan el almacenamiento y distribución correctos de medicamentos, consumibles y otros productos necesarios para el tratamiento eficaz de más de una de las tres enfermedades (VIH, tuberculosis y malaria), pero que pueden tener un mayor alcance y extenderse a otros resultados indirectos en materia de salud (como gestión integrada de enfermedades infantiles, tuberculosis/VIH, derecho a la salud sexual y reproductiva, PMTI integral y salud maternoinfantil). Incluye el reacondicionamiento o construcción de centros de almacenamiento, compra de vehículos y hardware y software para el sistema de gestión de adquisiciones y suministro.
A162: 19 | B162: S | C162: Procurement and Supply Chain Management | D162: 147 | E162: =OFFSET(F162,0,LangOffset,1,1) -> Operationalization of PSM system | F162: Operationalization of PSM system | G162: Mise en pratique du système de gestion des achats et des stocks | H162: Instrumentación del sistema de Gestión de Adquisiciones y Suministros (GAS) | I162: Практическое применение систем управления закупками и снабжением (УЗС) | J162: Activities which ensure uninterrupted, efficient and transparent purchase and distribution of medicines, consumables and other products that are necessary for effective delivery of more than one of the three disease services, (HIV, TB and malaria) but may also have broader reach to other health outcomes (e.g. IMCI, TB/HIV, SRHR, comprehensive PMTCT, MNCH). It includes training of PSM personnel, development and implementation of policies and regulations and monitoring mechanisms such as early warning system for stock-outs. | K162: Comprend les activités qui assurent un approvisionnement et une distribution continus, efficaces et transparents de médicaments, consommables et autres produits nécessaires à la prise en charge efficace de plus d'une des trois maladies (VIH, tuberculose et paludisme) mais dont la portée peut également être élargie à d'autres résultats sanitaires (par exemple, gestion intégrée des maladies infantiles, tuberculose/VIH, droit à la santé sexuelle et reproductive, prévention systématique de la transmission de la mère à l'enfant, santé maternelle, néonatale et infantile). Comprend la formation du personnel chargé de la gestion des achats et des stocks, ainsi que l'élaboration et la mise en œuvre de politiques et réglementations et de mécanismes de suivi, notamment les systèmes d'alerte rapide en cas de ruptures de stock. | L162: Actividades que garantizan la compra y distribución ininterrumpida, eficiente y transparente de medicamentos, consumibles y otros productos necesarios para el tratamiento eficaz de más de una de las tres enfermedades (VIH, tuberculosis y malaria), pero que pueden tener un mayor alcance y extenderse a otros resultados indirectos en materia de salud (como gestión integrada de enfermedades infantiles, tuberculosis/VIH, derecho a la salud sexual y reproductiva, PMTI integral y salud maternoinfantil). Incluye la formación de personal para gestión de adquisiciones y suministros (GAS), desarrollo y ejecución de políticas y reglamentos, así como mecanismos de seguimiento, como sistemas de alerta precoz para desabastecimientos.
A163: 19 | B163: S | C163: Procurement and Supply Chain Management | D163: 168 | E163: =OFFSET(F163,0,LangOffset,1,1) -> Other | F163: Other | G163: Autre | H163: Otro | I163: другой
A164: 20 | B164: S | C164: Information systems and M&E | D164: 148 | E164: =OFFSET(F164,0,LangOffset,1,1) -> Routine reporting | F164: Routine reporting | G164: Communication régulière de l’information | H164: Presentación de informes periódicos | I164: Регулярная отчетность | J164: Establishment/maintenance/strengthening of national HMIS system including DHIS 2 and any related web-based/electronic system to support data reporting from all levels of health system – including public, private, private-not-for-profit and community reporting; training; reporting forms and tools with appropriate disaggregation of indicators; sentinel surveillance; Data Quality Assessments | K164: Mise en place/maintenance/renforcement du système national d’information sur la gestion de la santé, notamment le DHIS 2, et de tout système web/électronique lié, afin de favoriser la communication des données à tous les niveaux du système de santé, y compris dans les secteurs public, privé et privé à but non lucratif et dans la communication de l'information au niveau communautaire ; formations ; fiches et outils de communication de l'information avec une ventilation correcte des indicateurs ; surveillance sentinelle ; évaluations de la qualité des données | L164: Establecimiento/mantenimiento/fortalecimiento de un sistema de información sobre la gestión sanitaria nacional, incluido un sistema de información sanitaria distrital (SISD 2) y cualquier sistema basado en web/electrónico asociado para respaldar la notificación de datos desde todos los niveles del sistema sanitario, ya sea público, privado, privado sin ánimo de lucro y comunitario; formación; formularios y herramientas para generación de informes con desglose de indicadores; sistemas de vigilancia centinela; evaluaciones de la calidad de los datos.
A165: 20 | B165: S | C165: Information systems and M&E | D165: 149 | E165: =OFFSET(F165,0,LangOffset,1,1) -> Analysis, review and transparency | F165: Analysis, review and transparency | G165: Analyse, examen et transparence | H165: Análisis, revisión y transparencia | I165: Анализ, оценка и прозрачность | J165: Analysis, interpretation and use of data and evidence generated through TB program review/ evaluation; development and sharing of periodic reports through websites/publications; reviews and evaluations of national health or disease strategies (these exclude the monthly/ quarterly review meetings held at different levels to strengthen programmatic supervision/monitoring); Operations Research | K165: Analyse, interprétation et utilisation des données et des preuves obtenues grâce à l'évaluation ou à l'examen du programme de lutte contre la tuberculose ; élaboration et partage de rapports périodiques grâce à des sites web et des publications ; examens et évaluations des stratégies nationales de santé et de lutte contre la maladie (sont exclues les réunions mensuelles et trimestrielles d'examen tenues à différents niveaux pour renforcer la supervision et le suivi programmatiques) ; recherche opérationnelle | L165: Análisis, interpretación y uso de datos y pruebas generados por medio de la revisión/evaluación de los programas de tuberculosis; desarrollo y uso compartido de informes periódicos a través de sitios web/publicaciones; revisiones y evaluaciones de estrategias de salud nacionales o sobre enfermedades (aquí se excluyen las reuniones de revisión mensuales/trimestrales mantenidas a distintos niveles para reforzar la supervisión y seguimiento de los programas); investigación operativa.
A166: 20 | B166: S | C166: Information systems and M&E | D166: 150 | E166: =OFFSET(F166,0,LangOffset,1,1) -> Surveys | F166: Surveys | G166: Enquêtes | H166: Encuestas | I166: Надзор | J166: Surveys/studies for assessment of morbidity, mortality, service coverage and behavioral surveys/studies in general population or identified risk groups – ex. DHS; MICS, health and morbidity surveys to assess out-of-pocket expenditures or burden etc. | K166: Enquêtes et études destinées à évaluer la morbidité, la mortalité, la couverture des services, et enquêtes ou études comportementales dans la population générale ou les groupes à risques identifiés, par exemple : enquêtes démographiques et de santé, enquêtes en grappes à indicateurs multiples, enquêtes de santé et de morbidité visant à évaluer les dépenses engagées ou la charge, etc. | L166: Encuestas/estudios para evaluación de la morbilidad, mortalidad, cobertura de servicios y encuestas/estudios conductuales en la población general o grupos de riesgo identificados, por ejemplo, EDS, EGIM, encuestas sobre salud y morbilidad para evaluación de desembolsos o cargas, etc.
A167: 20 | B167: S | C167: Information systems and M&E | D167: 151 | E167: =OFFSET(F167,0,LangOffset,1,1) -> Administrative and financial data sources | F167: Administrative and financial data sources | G167: Sources de données administratives et financières | H167: Fuentes de datos económicos y administrativos | I167: Источники административных и финансовых данных | J167: Includes establishing systems for periodic (annual) reporting on key health administrative and service availability statistics, such as- Health workforce, inventory of health care providers and institutions; National Health Accounts and sub-accounts; setting up of financial reporting/ accounting systems; annual review of health sector budget and expenditures by funding source; Expenditure studies; Establishing and maintaining Logistics Management Information system (LMIS) | K167: Comprend la mise en place de systèmes de communication de l'information périodique (annuelle) sur les statistiques clés en matière d'administration de la santé et de disponibilité des services, tels que le personnel de santé, l'inventaire des prestataires des soins et les institutions ; comptes et sous-comptes nationaux de la santé ; mise en place de systèmes de communication de l'information financière ou de systèmes comptables ; examen annuel du budget et des dépenses consacrés à la santé par source de financement ; étude des dépenses ; mise en place et maintien du système informatique de gestion de la logistique | L167: Incluye el establecimiento de sistemas para la presentación de informes periódicos (anuales) de estadísticas clave referentes a administración sanitaria y disponibilidad de servicios, como personal de salud, inventario de proveedores de atención sanitaria e instituciones; Cuentas Nacionales de Salud y cuentas secundarias; revisión anual del presupuesto del sector sanitario y gastos por fuente de financiamiento; estudios del gasto; establecimiento y mantenimiento del sistema de información de gestión logística.
A168: 20 | B168: S | C168: Information systems and M&E | D168: 152 | E168: =OFFSET(F168,0,LangOffset,1,1) -> Vital Registration Systems | F168: Vital Registration Systems | G168: Systèmes de registre d'état civil | H168: Sistemas de registro civil | I168: Системы регистрации актов гражданского состояния | J168: Establishing/ strengthening and scale up of Vital registration information system including Sample Vital Registration systems, strengthening reporting of hospital morbidity and mortality statistics, cause of death, establishment of SMS system of reporting; training of community health workers on reporting vital events, drug stock-outs etc. | K168: Mise en place/renforcement et intensification des systèmes de registre d'état civil, y compris des systèmes de registre d'échantillons, renforcement de la communication de l'information relative aux statistiques de morbidité et de mortalité à l'hôpital, cause de décès, mise en place d'un système de communication de l'information par SMS ; formation des agents de santé communautaires sur la communication de l'information relative aux données de l'état civil, ruptures de stock de médicaments, etc. | L168: Establecimiento, fortalecimiento y ampliación del sistema de información de registro civil, incluidos sistemas de registro vital de muestra, fortalecimiento del sistema de presentación de informes para estadísticas de mortalidad y morbilidad hospitalaria, causa de muerte y establecimiento de un sistema SMS para generación de informes; formación del personal de salud de la comunidad en presentación de informes sobre eventos esenciales, desabastecimiento de medicamentos, etc.
A169: 20 | B169: S | C169: Information systems and M&E | D169: 167 | E169: =OFFSET(F169,0,LangOffset,1,1) -> Other | F169: Other | G169: Autre | H169: Otro | I169: другой
A170: 21 | B170: S | C170: Legal, policy, strategy and regulatory environment | D170: 153 | E170: =OFFSET(F170,0,LangOffset,1,1) -> Development and Implementation of legal and policy reform | F170: Development and Implementation of legal and policy reform | G170: Élaboration et mise en œuvre de réformes juridiques et politiques | H170: Desarrollo y ejecución de la reforma legal y política | I170: Разработка и реализация правовых и политических реформ | J170: This includes activities which contribute to developing and executing health systems-related laws, strategies, policies, regulations, and, protocols, and monitoring their implementation such as- developing, ratifying and executing evidence-based, non-discriminatory laws, policies, regulations, coordination and supervision mechanisms; Capacity building and training of MoH, local government, non-government and other relevant personnel to improve policy-making, policy-execution and monitoring functions; Inter-sectoral consultations, coordinating meetings, community meetings and similar activities aimed at policy-making, policy-execution and monitoring; Supporting analytical needs assessment, surveys, research and relevant activities to generate information for policy-making | K170: Comprend les activités qui contribuent à l'élaboration et à l'exécution des lois, stratégies, politiques, réglementations et protocoles liés aux systèmes de santé, et au suivi de leur mise en œuvre. Exemples : élaboration, ratification et exécution de lois, politiques, réglementations, mécanismes de coordination et de supervision fondés sur des preuves et non discriminatoires ; renforcement des capacités et formation des agents du ministère de la Santé, des agents gouvernementaux locaux, des agents non gouvernementaux et de tout autre membre du personnel approprié visant à améliorer l'élaboration et l'exécution des politiques et le suivi des fonctions ; consultations intersectorielles, réunions de coordination, réunions communautaires et activités similaires visant à élaborer, exécuter et assurer le suivi des politiques ; appui à l'évaluation des besoins analytiques, enquêtes, recherches et autres activités pertinentes destinées à générer des informations dans le cadre de l'élaboration de politiques | L170: Aquí se incluyen actividades que contribuyen al desarrollo y aplicación de leyes, estrategias, políticas, reglamentos y protocolos relacionados con los sistemas de salud, así como la supervisión de su aplicación, como desarrollo, ratificación y ejecución basados en pruebas, leyes no discriminatorias, políticas, reglamentos y mecanismos de coordinación y supervisión; capacitación y formación del personal del Ministerio de Salud, gobierno local, no gubernamental y otro personal relevante a fin de mejorar la elaboración y ejecución de políticas, así como las funciones de supervisión; consultas intersectoriales, reuniones de coordinación, reuniones con la comunidad y actividades análogas dirigidas a la elaboración y ejecución de políticas y a la supervisión; apoyo a la evaluación de necesidades analítica, encuestas, investigación y actividades relevantes a fin de generar información para la elaboración de políticas.
A171: 21 | B171: S | C171: Legal, policy, strategy and regulatory environment | D171: 154 | E171: =OFFSET(F171,0,LangOffset,1,1) -> Advocacy for legal and policy reforms | F171: Advocacy for legal and policy reforms | G171: Plaidoyer pour des réformes juridiques et politiques | H171: Promoción de reformas jurídicas y políticas | I171: Адвокация в целях проведения правовых и политических реформ | J171: This includes advocacy activities aimed at promoting appropriate legal and policy reform related to health and community systems such as- capacity building and mobilization of community activists, civil society organizations and other stakeholders to improve their engagement with government officials; Information campaigns (community level, local and national mass media etc.) aimed at promoting legislation, policy/regulation development and implementation; Building community linkages, collaboration and coordination; Advocacy on legal and policy frameworks e.g. decriminalization of behaviors or marginalized groups; development and enforcement of child protection policies; | K171: Comprend les activités de sensibilisation visant à promouvoir les réformes juridiques et politiques appropriées liées aux systèmes communautaires et de santé. Exemples : renforcement des capacités et mobilisation des acteurs communautaires, des organisations de la société civile et de tout autre intervenant pour renforcer leur engagement auprès des représentants des fonctionnaires publics ; campagnes d'information (niveau communautaire, médias de masse locaux et nationaux, etc.) visant à promouvoir l'élaboration et la mise en œuvre de lois, politiques et réglementations ; établissement de liens, d'une collaboration et d'une coordination communautaires ; sensibilisation aux cadres juridiques et politiques, par exemple : dépénalisation de certains comportements ou protection des groupes marginalisés ; élaboration et mise en application de politiques de protection des enfants | L171: Aquí se incluyen actividades dirigidas a la promoción de reformas legales y políticas relacionadas con los sistemas y servicios de salud y comunitarios, como capacitación y movilización de activistas de la comunidad, organizaciones de la sociedad civil y otras partes interesadas para mejorar su colaboración con funcionarios de la administración; campañas de información (comunitarias y en medios de comunicación locales y nacionales, etc.) dirigidas a promover el desarrollo y aplicación de leyes y políticas/reglamentos; creación de vínculos, colaboración y coordinación de la comunidad; promoción de los marcos legales y políticos, por ejemplo, despenalización de comportamientos o grupos marginados; desarrollo y cumplimiento de las políticas de protección de la infancia.
A172: 21 | B172: S | C172: Legal, policy, strategy and regulatory environment | D172: 155 | E172: =OFFSET(F172,0,LangOffset,1,1) -> Monitoring and reporting implementation of laws and policies | F172: Monitoring and reporting implementation of laws and policies | G172: Suivi de la mise en œuvre des législations et des politiques et communication de l'information y afférente | H172: Seguimiento y comunicación de la ejecución de leyes y políticas | I172: Мониторинг и отчетность в области осуществления права и мер политики | J172: This includes developing and supporting independent mechanisms to supervise, monitor and report on development and implementation of laws and policies such as- Capacity building and support for effective litigation; Ensuring meaningful participation of community actors in national consultative forums, including policy, planning and other decision making bodies; Improving strategic and operational planning, management, accountability and leadership, including for community systems; | K172: Comprend l'élaboration et la promotion de mécanismes indépendants pour la supervision, le suivi et la communication d'informations sur l'élaboration et la mise en œuvre de lois et politiques. Exemples : renforcement des capacités et appui à une procédure efficace ; garantie d'une participation active des acteurs communautaires aux forums consultatifs nationaux, notamment dans les politiques, la planification et les organismes décisionnaires ; amélioration de la planification, de la gestion, de l'obligation redditionnelle et de l'encadrement stratégiques et opérationnels, notamment pour les systèmes communautaires | L172: Incluye el desarrollo y fomento de mecanismos independientes para la supervisión, seguimiento y notificación con respecto a la elaboración y aplicación de leyes y políticas, como capacitación y apoyo a un sistema de litigio eficaz; participación de los agentes comunitarios en los foros de consulta nacionales, incluidos los organismos legisladores, planificadores y de toma de decisiones; mejora de la planificación, gestión, responsabilidad y liderazgo estratégicos y operativos, incluso en el caso de los sistemas comunitarios.
A173: 21 | B173: S | C173: Legal, policy, strategy and regulatory environment | D173: 166 | E173: =OFFSET(F173,0,LangOffset,1,1) -> Other | F173: Other | G173: Autre | H173: Otro | I173: другой
A174: 22 | B174: S | C174: Healthcare financing | D174: 156 | E174: =OFFSET(F174,0,LangOffset,1,1) -> Financial sustainability | F174: Financial sustainability | G174: Viabilité financière | H174: Sostenibilidad financiera | I174: Финансовая устойчивость | J174: It includes activities which contribute to improving adequate provision of financial resources to public, private and non-government/community institutions for effective delivery of services and disease control programs such as- Improving revenue collection, pooling and purchasing for ensuring financial sustainability of service delivery. For example, supporting the development, operationalization and management of funding schemes for purchasing healthcare services (insurance fund, community-based insurance schemes, revolving drug funds etc.); Providing training in financial planning and budgeting; Capacity building for improving public financial management; | K174: Comprend les activités qui contribuent à améliorer la mise à disposition adéquate de ressources financières auprès des institutions publiques, privées et non gouvernementales/communautaires pour l'exécution efficace des services et programmes de lutte contre la maladie. Exemple : amélioration de la collecte des recettes, de la mise en commun et des achats pour assurer la viabilité financière des services fournis. Par exemple, appui à l'élaboration, à la mise en pratique et à la gestion des mécanismes de financement pour l'achat de services de santé (fonds d'assurance, régimes d'assurance communautaires, fonds renouvelables pour les médicaments, etc.) ; formation sur la planification financière et l'établissement du budget ; renforcement des capacités pour une meilleure gestion des finances publiques | L174: Incluye actividades que contribuyen a mejorar la provisión de recursos financieros a instituciones públicas, privadas y no gubernamentales/comunitarias con el fin de lograr una prestación de servicios y unos programas de control de enfermedades eficaces, como mejora en la recaudación de ingresos, centralización y adquisiciones para garantizar la sostenibilidad financiera en la prestación de servicios. Por ejemplo, apoyo al desarrollo, instrumentación y gestión de programas de financiamiento para la contratación de servicios sanitarios (fondo de seguros, programas de seguros comunitarios, fondos rotatorios para medicamentos, etc.); formación en planificación financiera y creación de presupuestos; capacitación para mejorar la gestión financiera pública.
A175: 22 | B175: S | C175: Healthcare financing | D175: 157 | E175: =OFFSET(F175,0,LangOffset,1,1) -> Equity of healthcare financing | F175: Equity of healthcare financing | G175: Financement équitable des soins de santé | H175: Igualdad en el financiamiento de la atención sanitaria | I175: Справедливое финансирование здравоохранения | J175: Activities which contribute to improving equitable provision of financial resources to public, private and non-government institutions for effective delivery of services and disease control programs; | K175: Comprend les activités qui contribuent à améliorer la mise à disposition équitable des ressources financières auprès des institutions publiques, privées et non gouvernementales pour l'exécution efficace des services et programmes de lutte contre la maladie | L175: Actividades que contribuyen a mejorar la provisión igualitaria de recursos financieros a instituciones públicas, privadas y no gubernamentales para lograr una prestación de servicios y unos programas de control de enfermedades eficaces.
A176: 22 | B176: S | C176: Healthcare financing | D176: 165 | E176: =OFFSET(F176,0,LangOffset,1,1) -> Other | F176: Other | G176: Autre | H176: Otro | I176: другой
A177: 23 | B177: S | C177: Human Rights | D177: 158 | E177: =OFFSET(F177,0,LangOffset,1,1) -> Law and policy reform | F177: Law and policy reform | G177: Réforme juridique et politique | H177: Reforma legislativa y política | I177: Правовая и политическая реформа | J177: Activities which contribute to developing laws, policies and regulations that strengthen ability to deliver equal access to health services, and enable community systems to register and advocate for rights of people living with and affected by the 3 diseases. It includes creation of enabling environment for Global Fund supported interventions through drafting and ratifying laws and policies Cross-cutting human rights interventions that affect the three diseases (e.g., prison reform, reform of laws and policies on refugees/migrants, IDPs, and others) also included here. | K177: Comprend les activités qui contribuent à élaborer des lois, politiques et réglementations permettant de renforcer la capacité à proposer un accès équitable aux services de santé et permettant aux systèmes communautaires de s'inscrire et de défendre les droits des personnes vivant avec les trois maladies et touchées par elles. Comprend la création d'un environnement favorable aux interventions soutenues par le Fonds mondial à travers l'élaboration et la ratification de lois et de politiques. Comprend également les interventions transversales basées sur les droits de l'homme qui concernent les trois maladies (par exemple, réforme pénitentiaire, réforme des lois et politiques en matière de réfugiés/migrants, de personnes déplacées à l'intérieur du pays et autres). | L177: Actividades que contribuyen al desarrollo de leyes, políticas y reglamentos encaminados a promover un acceso igualitario a los servicios de salud y que posibilitan que los sistemas comunitarios registren y defiendan los derechos de las personas afectadas por las tres enfermedades. Incluye la creación de un entorno propicio para las intervenciones auspiciadas por el Fondo Mundial a través de la redacción y ratificación de leyes y políticas. Aquí también se incluyen intervenciones transversales en materia de derechos humanos que afectan a las tres enfermedades (por ejemplo, reforma de las prisiones, reforma de las leyes y políticas sobre refugiados e inmigrantes, desplazados y otras).
A178: 23 | B178: S | C178: Human Rights | D178: 159 | E178: =OFFSET(F178,0,LangOffset,1,1) -> Implementation | F178: Implementation | G178: Mise en œuvre | H178: Ejecución | I178: Осуществление | J178: Activities which contribute to implementing and enforcing laws, policies and regulations that strengthen ability to deliver equal access to health services, and enable community systems to register and advocate for rights of people living with and affected by the 3 diseases. Cross-cutting human rights interventions that affect the three diseases (e.g., prison reform, reform of laws and policies on refugees/migrants, IDPs, and others) also included here. It includes capacity building activities to ensure health/human rights related laws and policies are fully implemented | K178: Comprend les activités qui contribuent à exécuter et à mettre en application des lois, politiques et réglementations permettant de renforcer la capacité à proposer un accès équitable aux services de santé et permettant aux systèmes communautaires de s'inscrire et de défendre les droits des personnes vivant avec les trois maladies et touchées par elles. Comprend également les interventions transversales basées sur les droits de l'homme qui concernent les trois maladies (par exemple, réforme pénitentiaire, réforme des lois et politiques en matière de réfugiés/migrants, de personnes déplacées à l'intérieur du pays et autres). Comprend les activités de renforcement des capacités visant à garantir l'application totale des lois et des politiques liées à la santé et aux droits de l'homme. | L178: Actividades que contribuyen a la promulgación y aplicación de leyes, políticas y reglamentos encaminados a promover un acceso igualitario a los servicios de salud y que posibilitan que los sistemas comunitarios registren y defiendan los derechos de las personas afectadas por las tres enfermedades. Aquí también se incluyen intervenciones transversales en materia de derechos humanos que afectan a las tres enfermedades (por ejemplo, reforma de las prisiones, reforma de las leyes y políticas sobre refugiados e inmigrantes, desplazados y otras). Incluye actividades de capacitación para garantizar la plena implantación de leyes y políticas relacionadas con los derechos humanos y el derecho a la salud.
A179: 23 | B179: S | C179: Human Rights | D179: 160 | E179: =OFFSET(F179,0,LangOffset,1,1) -> Enforcement | F179: Enforcement | G179: Application | H179: Cumplimiento | I179: Правоприменительные меры | J179: Activities which contribute to enforcing laws, policies and regulations that strengthen ability to deliver equal access to health services, and enable community systems to register and advocate for rights of people living with and affected by the 3 diseases. It includes activities to ensure routes to redress are available to people living with the three diseases, key affected populations, women, etc. Cross-cutting human rights interventions that affect the three diseases (e.g., prison reform, reform of laws and policies on refugees/migrants, IDPs, and others) also included here. | K179: Comprend les activités qui contribuent à mettre en application des lois, politiques et réglementations permettant de renforcer la capacité à proposer un accès équitable aux services de santé et permettant aux systèmes communautaires de s'inscrire et de défendre les droits des personnes vivant avec les trois maladies et touchées par elles. Comprend les activités visant à garantir la mise à disposition des moyens de recours pour les personnes vivant avec les trois maladies, les populations-clés affectées, les femmes, etc. Comprend également les interventions transversales basées sur les droits de l'homme qui concernent les trois maladies (par exemple, réforme pénitentiaire, réforme des lois et politiques en matière de réfugiés/migrants, de personnes déplacées à l'intérieur du pays et autres). | L179: Actividades que contribuyen a la aplicación de leyes, políticas y reglamentos encaminados a promover un acceso igualitario a los servicios de salud y que posibilitan que los sistemas comunitarios registren y defiendan los derechos de las personas afectadas por las tres enfermedades. Incluye actividades que garantizan la disponibilidad de vías de compensación para las personas que viven con las tres enfermedades, población clave afectada, mujeres, etc. Aquí también se incluyen intervenciones transversales en materia de derechos humanos que afectan a las tres enfermedades (por ejemplo, reforma de las prisiones, reforma de las leyes y políticas sobre refugiados e inmigrantes, desplazados y otras).
A180: 23 | B180: S | C180: Human Rights | D180: 161 | E180: =OFFSET(F180,0,LangOffset,1,1) -> Monitoring and reporting implementation of human rights | F180: Monitoring and reporting implementation of human rights | G180: Suivi de la mise en œuvre des droits de l'homme et communication de l'information y afférente | H180: Seguimiento y comunicación de la aplicación de los derechos humanos | I180: Мониторинг и отчетность в области осуществления прав человека | J180: It inlcudes activities to monitor implementation and document violations (health services, human rights commissions, civil society) | K180: Comprend les activités visant à contrôler la mise en œuvre et à documenter les violations (services de santé, commissions des droits de l'homme, société civile) | L180: Incluye actividades dirigidas a supervisar la puesta en práctica y documentar las violaciones (servicios sanitarios, comisiones sobre derechos humanos, sociedad civil).
A181: 23 | B181: S | C181: Human Rights | D181: 164 | E181: =OFFSET(F181,0,LangOffset,1,1) -> Other | F181: Other | G181: Autre | H181: Otro | I181: другой
A182: 24 | B182: S | C182: Program management (applicable for standalone HSS grants) | D182: 162 | E182: =OFFSET(F182,0,LangOffset,1,1) -> Grant Management | F182: Grant Management | G182: Gestion de subvention | H182: Gestión de subvenciones | I182: Управление грантами | J182: Includes specific Global Fund grant management related activities at the PMU/PR/SR level. These could include- development and submission of grant documents; oversight and technical assistance related to Global Fund grant implementation and management and specific Global Fund requirements; supervision from PR to SR level (applicable when national malaria program is not the PR); human resource planning/ staffing and overheads, operational costs; coordination with national program, district and local authorities; quarterly meetings, training, and office/IT equipment at PR/SR level; mobilizing leaders to support implementation and sustainability of the program | K182: Comprend les activités spécifiques liées à la gestion des subventions du Fonds mondial au niveau de l'unité de gestion de projet, du récipiendaire principal ou des sous-récipiendaires. Exemples : élaboration et transmission de documents de subvention ; supervision et assistance technique liées à la mise en œuvre et à la gestion des subventions du Fonds mondial et aux exigences spécifiques du Fonds mondial ; supervision des sous-récipiendaires au niveau du récipiendaire principal (applicable lorsque le programme national de lutte contre le paludisme n'est pas le récipiendaire principal) ; planification des ressources humaines/dotation en effectifs et frais généraux, frais de fonctionnement ; coordination avec le programme national, les autorités locales et les instances de districts ; réunions trimestrielles, formations et matériel informatique et bureautique au niveau du récipiendaire principal ou des sous-récipiendaires ; mobilisation des responsables pour appuyer la mise en œuvre et la viabilité du programme | L182: Incluye actividades relacionadas con la gestión de las subvenciones específicas del Fondo Mundial en el nivel de unidad de gestión de programas/receptor principal/subreceptor. Aquí podrían incluirse el desarrollo y presentación de documentos de las subvenciones; supervisión y asistencia técnica asociadas a la ejecución y gestión de las subvenciones del Fondo Mundial, y requisitos específicos del Fondo Mundial; supervisión desde el nivel de receptor principal a subreceptor, aplicable cuando el programa nacional para la malaria no es el receptor principal; planificación de recursos humanos, personal, gastos generales y operativos; coordinación con las autoridades del programa nacional, locales y del distrito; reuniones trimestrales, formación y equipo informático/de oficina en el nivel de receptor principal/subreceptor; movilización de líderes para apoyar la ejecución de programa y su sostenibilidad.
A183: 24 | B183: S | C183: Program management (applicable for standalone HSS grants) | D183: 163 | E183: =OFFSET(F183,0,LangOffset,1,1) -> Other | F183: Other | G183: Autre | H183: Otro | I183: другой

Sheet Coverage ind
A1: ModId | B1: CmpAcro | C1: Module | D1: CovIndId | E1: Label | F1: Coverage Indicator en | G1: Coverage Indicator fr | H1: Coverage Indicator es | I1: Coverage Indicator ru
A2: 1 | B2: H | D2: 1 | E2: =OFFSET(F2,0,LangOffset,1,1) -> # of women and men 15-49 who received an HIV test and know their results | F2: # of women and men 15-49 who received an HIV test and know their results | G2: Nombre de femmes et d'hommes âgés de 15 à 49 ans qui ont fait un test VIH et connaissent les résultats | H2: Número de mujeres y hombres entre 15 y 49 años que se han sometido a una prueba del VIH y conocen los resultados | I2: Число женщин и мужчин в возрасте от 15 до 49 лет, прошедших анализ на ВИЧ и получивших результаты
A3: 1 | B3: H | D3: 2 | E3: =OFFSET(F3,0,LangOffset,1,1) -> # & % of individuals from the targeted population reached through community outreach with a standardized HIV prevention intervention | F3: # & % of individuals from the targeted population reached through community outreach with a standardized HIV prevention intervention | G3: Nombre et pourcentage d'individus issus de la population cible qui ont bénéficié d'une approche communautaire au travers d'interventions harmonisées de prévention du VIH | H3: Número y porcentaje de individuos de la población objetivo cubiertos por programas de divulgación comunitarios con una intervención de prevención del VIH estandarizada | I3: Число и % представителей целевой группы населения, охваченных стандартными мероприятиями по профилактике ВИЧ посредством аутрич-работы на уровне сообществ
A4: 1 | B4: H | D4: 3 | E4: =OFFSET(F4,0,LangOffset,1,1) -> % of men 15-49 that are circumcised | F4: % of men 15-49 that are circumcised | G4: Pourcentage d'hommes circoncis âgés de 15 à 49 ans | H4: Porcentaje de hombres de entre 15 y 49 años circuncidados | I4: % мужчин в возрасте 15-49 лет, сделавших обрезание
A5: 1 | B5: H | D5: 19 | E5: =OFFSET(F5,0,LangOffset,1,1) -> # & % of orphaned and vulnerable children aged 0-17 years whose households received free basic external support in caring for the child according to national guidelines | F5: # & % of orphaned and vulnerable children aged 0-17 years whose households received free basic external support in caring for the child according to national guidelines | G5: Nombre et pourcentage d'orphelins et d'enfants vulnérables âgés de 0 à 17 ans qui vivent dans des foyers ayant bénéficié d'une aide extérieure gratuite pour leur prise en charge, conformément aux directives nationales | H5: Número y porcentaje de hombres que tienen relaciones sexuales con hombres cubiertos por programas de prevención del VIH (paquetes definidos de servicios); notificar personas transgénero por separado, si procede | I5: Число и % МСМ, охваченных программами профилактики ВИЧ (определенный пакет услуг) с разбивкой по целевым группам населения (если возможно)
A6: 25 | B6: H | D6: 4 | E6: =OFFSET(F6,0,LangOffset,1,1) -> # & % of MSM reached with HIV prevention programs (defined package of services), report separately for TGs, if applicable | F6: # & % of MSM reached with HIV prevention programs (defined package of services), report separately for TGs, if applicable | G6: Nombre et pourcentage d'hommes ayant des rapports sexuels avec des hommes qui ont bénéficié de programmes de prévention du VIH (paquet de services définis) ; établissez un rapport distinct pour les transgenres, le cas échéant | H6: Número y porcentaje de hombres que tienen relaciones sexuales con hombres a los que han llegado intervenciones de prevención del VIH a nivel individual o de grupo reducido basadas en pruebas o que cumplen los niveles mínimos exigidos; notificar personas transgénero por separado, si procede | I6: Число и % МСМ, охваченных индивидуальными и/или проводимыми на уровне небольших групп мероприятиями по профилактике ВИЧ, основанными на научных данных и/или соответствующими минимальным обязательным стандартам (если возможно, с разбивкой по целевым группам населения)
A7: 25 | B7: H | D7: 5 | E7: =OFFSET(F7,0,LangOffset,1,1) -> # & % of MSM reached with individual and/or smaller group-level HIV preventive interventions that are based on evidence and/or meet the minimum standards required, report separately for TGs, if applicable | F7: # & % of MSM reached with individual and/or smaller group-level HIV preventive interventions that are based on evidence and/or meet the minimum standards required, report separately for TGs, if applicable | G7: Nombre et pourcentage d'hommes ayant des rapports sexuels avec des hommes, calculés à partir de données probantes et/ou répondant aux normes minimales requises, qui ont bénéficié d'interventions de prévention du VIH menées individuellement et/ou en petits groupes ; établissez un rapport distinct pour les transgenres, le cas échéant | H7: Número y porcentaje de hombres que tienen relaciones sexuales con hombres que se han sometido a una prueba del VIH y conocen los resultados; notificar personas transgénero por separado, si procede | I7: Число и % МСМ, прошедших анализ на ВИЧ и получивших результаты (если возможно, с разбивкой по целевым группам населения)
A8: 25 | B8: H | D8: 6 | E8: =OFFSET(F8,0,LangOffset,1,1) -> # & % of MSM who received an HIV test and who know the results, report separately for TGs, if applicable | F8: # & % of MSM who received an HIV test and who know the results, report separately for TGs, if applicable | G8: Nombre et pourcentage d'hommes ayant des rapports sexuels avec des hommes qui ont fait un test VIH et connaissent les résultats ; établissez un rapport distinct pour les transgenres, le cas échéant | H8: Número y porcentaje de profesionales del sexo cubiertos por programas de prevención del VIH - paquete de servicios definido | I8: Число и % работников секс-бизнеса, охваченных программами профилактики ВИЧ (определенный пакет услуг)
A9: 26 | B9: H | D9: 7 | E9: =OFFSET(F9,0,LangOffset,1,1) -> # & % of SWs reached with HIV prevention programs- defined package of services | F9: # & % of SWs reached with HIV prevention programs- defined package of services | G9: Nombre et pourcentage de professionnels du sexe ayant bénéficié de programmes de prévention du VIH (paquet de services définis) | H9: Número y porcentaje de profesionales del sexo a los que han llegado intervenciones de prevención del VIH a nivel individual o de grupo reducido basadas en pruebas o que cumplen los niveles mínimos exigidos | I9: Число и % работников секс-бизнеса, охваченных индивидуальными и/или проводимыми на уровне небольших групп мероприятиями по профилактике ВИЧ, основанными на научных данных и/или соответствующими минимальным обязательным стандартам
A10: 26 | B10: H | D10: 8 | E10: =OFFSET(F10,0,LangOffset,1,1) -> # & % of SWs reached with individual and/or smaller group-level HIV preventive interventions that are based on evidence and/or meet the minimum standards required | F10: # & % of SWs reached with individual and/or smaller group-level HIV preventive interventions that are based on evidence and/or meet the minimum standards required | G10: Nombre et pourcentage de professionnels du sexe, calculés à partir de données probantes et/ou répondant aux normes minimales requises, qui ont bénéficié d'interventions de prévention du VIH menées individuellement et/ou en petits groupes | H10: Número y porcentaje de profesionales del sexo que se han sometido a una prueba del VIH y conocen los resultados | I10: Число и % работников секс-бизнеса, прошедших анализ на ВИЧ и получивших результаты
A11: 26 | B11: H | D11: 9 | E11: =OFFSET(F11,0,LangOffset,1,1) -> # & % of SWs that received an HIV test and who know the results | F11: # & % of SWs that received an HIV test and who know the results | G11: Nombre et pourcentage de professionnels du sexe qui ont fait un test VIH et connaissent les résultats | H11: Número y porcentaje de usuarios de drogas inyectables cubiertos por programas de prevención del VIH - paquete de servicios definido | I11: Число и % ПИН, охваченных программами профилактики ВИЧ (определенный пакет услуг)
A12: 27 | B12: H | D12: 10 | E12: =OFFSET(F12,0,LangOffset,1,1) -> # & % of PWID reached with HIV prevention programs- defined package of services | F12: # & % of PWID reached with HIV prevention programs- defined package of services | G12: Nombre et pourcentage de consommateurs de drogues injectables ayant bénéficié de programmes de prévention du VIH (paquet de services définis) | H12: Número y porcentaje de usuarios de drogas inyectables a los que han llegado intervenciones de prevención del VIH a nivel individual o de grupo reducido basadas en pruebas o que cumplen los niveles mínimos exigidos | I12: Число и % ПИН, охваченных индивидуальными и/или проводимыми на уровне небольших групп мероприятиями по профилактике ВИЧ, основанными на научных данных и/или соответствующими минимальным обязательным стандартам
A13: 27 | B13: H | D13: 11 | E13: =OFFSET(F13,0,LangOffset,1,1) -> # & % of PWID reached with individual and/or smaller group-level HIV preventive interventions that are based on evidence and/or meet the minimum standards required | F13: # & % of PWID reached with individual and/or smaller group-level HIV preventive interventions that are based on evidence and/or meet the minimum standards required | G13: Nombre et pourcentage de consommateurs de drogues injectables, calculés à partir de données probantes et/ou répondant aux normes minimales requises, qui ont bénéficié d'interventions de prévention du VIH menées individuellement et/ou en petits groupes | H13: Número y porcentaje de usuarios de drogas inyectables que se han sometido a una prueba del VIH y conocen los resultados | I13: Число и % ПИН, прошедших анализ на ВИЧ и получивших результаты
... A21: 29 | B21: H | D21: 20 | E21: =OFFSET(F21,0,LangOffset,1,1) -> # & % of young people aged 10-24 years reached by life-skills based HIV education in schools | F21: # & % of young people aged 10-24 years reached by life-skills based HIV education in schools | G21: Nombre et pourcentage de jeunes âgés de 10 à 24 ans ayant reçu une formation sur le VIH fondée sur les compétences pratiques en milieu scolaire | H21: Número y porcentaje de jóvenes entre 10 y 24 años beneficiarios de formación de aptitudes para la vida relativas al VIH en escuelas | I21: Число и % молодых людей в возрасте от 10 до 24 лет, охваченных школьным обучением навыкам, необходимым для жизни с ВИЧ
A22: 2 | B22: H | C22: PMTCT | D22: 21 | E22: =OFFSET(F22,0,LangOffset,1,1) -> # & % of HIV-positive pregnant women who received anti-retrovirals to reduce the risk of mother-to-child transmission | F22: # & % of HIV-positive pregnant women who received anti-retrovirals to reduce the risk of mother-to-child transmission | G22: Nombre et pourcentage de femmes enceintes séropositives au VIH ayant reçu des antirétroviraux dans le but de réduire le risque de transmission de la mère à l'enfant | H22: Número y porcentaje de mujeres embarazadas seropositivas que han recibido antirretrovirales para reducir el riesgo de transmisión maternoinfantil | I22: Число и % ВИЧ-инфицированных беременных женщин, прошедших антиретровирусную терапию для снижения риска передачи вируса от матери ребенку
A23: 2 | B23: H | C23: PMTCT | D23: 22 | E23: =OFFSET(F23,0,LangOffset,1,1) -> # & % of pregnant women who know their HIV status | F23: # & % of pregnant women who know their HIV status | G23: Nombre et pourcentage de femmes enceintes qui connaissent leur statut sérologique à l'égard du VIH | H23: Número y porcentaje de mujeres embarazadas que conocen su estado serológico respecto al VIH | I23: Число и % беременных женщин, знающих свой ВИЧ-статус
A24: 2 | B24: H | C24: PMTCT | D24: 23 | E24: =OFFSET(F24,0,LangOffset,1,1) -> # & % of infants born to HIV-infected women who receive a virological test for HIV within 2 months of birth | F24: # & % of infants born to HIV-infected women who receive a virological test for HIV within 2 months of birth | G24: Nombre et pourcentage de nourrissons, nés de femmes infectées par le VIH, ayant bénéficié d'un dépistage du VIH dans les 2 mois qui ont suivi leur naissance | H24: Número y porcentaje de bebés nacidos de mujeres seropositivas que reciben pruebas virológicas para el VIH en sus dos primeros meses de vida | I24: Число и % детей, рожденных ВИЧ-инфицированными женщинами и прошедших вирусологический тест на ВИЧ в течение 2 месяцев после рождения
A25: 3 | B25: H | C25: Treatment | D25: 24 | E25: =OFFSET(F25,0,LangOffset,1,1) -> # & % of eligible adults and children currently receiving antiretroviral therapy (disaggregated by age and sex) | F25: # & % of eligible adults and children currently receiving antiretroviral therapy (disaggregated by age and sex) | G25: Nombre et pourcentage d'adultes et d'enfants répondant aux conditions et bénéficiant actuellement d'un traitement antirétroviral (ventilés par âge et par sexe) | H25: Número y porcentaje de adultos y niños elegibles que reciben terapia antirretroviral (desglosado por edad y sexo) | I25: Число и % имеющих показания взрослых и детей в настоящее время получающих антиретровирусную терапию (с разбивкой по возрастным категориям и полу)
A26: 3 | B26: H | C26: Treatment | D26: 25 | E26: =OFFSET(F26,0,LangOffset,1,1) -> # & % of health facilities dispensing antiretroviral therapy that have experienced a stock-out of at least one required antiretroviral drug in the last 12 month | F26: # & % of health facilities dispensing antiretroviral therapy that have experienced a stock-out of at least one required antiretroviral drug in the last 12 month | G26: Nombre et pourcentage d'établissements de santé dispensant des traitements antirétroviraux qui ont connu une rupture de stock pour au moins l'un des médicaments antirétroviraux requis au cours des 12 derniers mois | H26: Número y porcentaje de centros de salud que administran terapia antirretroviral y han experimentado desabastecimiento de al menos un medicamento antirretroviral necesario en los últimos 12 meses | I26: Число и % медицинских учреждений, предоставляющих антиретровирусную терапию, которые испытывали дефицит как минимум одного антиретровирусного препарата за последние 12 месяцев
A27: 3 | B27: H | C27: Treatment | D27: 26 | E27: =OFFSET(F27,0,LangOffset,1,1) -> # & % of adults and children enrolled in HIV care who had TB status assessed and recorded during their last visit during the reporting period among all adults and children enrolled in HIV care and seen for care during the reporting period | F27: # & % of adults and children enrolled in HIV care who had TB status assessed and recorded during their last visit during the reporting period among all adults and children enrolled in HIV care and seen for care during the reporting period | G27: Nombre et pourcentage d'adultes et d'enfants admis dans des services de prise en charge du VIH dont le statut à l'égard de la tuberculose a été examiné et enregistré au cours de leur dernière visite, pendant la période de communication de l’information, parmi tous les adultes et enfants admis dans des services de prise en charge du VIH et ayant consulté pour des soins pendant la période de communication de l’information | H27: Número y porcentaje de adultos y niños del total que reciben servicios de atención del VIH a quienes se ha evaluado y registrado su estado con respecto a la tuberculosis en su última visita durante el período de informe | I27: Число и % взрослых и детей, включенных в списки для получения ухода в связи с ВИЧ, ТБ-статус которых был оценен и зарегистрирован во время последнего посещения врача за отчетный период, по отношению к общему числу взрослых и детей, включенных в списки для получения ухода в связи с ВИЧ и получивших соответствующий уход за отчетный период
A28: 3 | B28: H | C28: Treatment | D28: 27 | E28: =OFFSET(F28,0,LangOffset,1,1) -> # & % of adults and children newly enrolled in HIV care who start treatment of latent TB infection (IPT) | F28: # & % of adults and children newly enrolled in HIV care who start treatment of latent TB infection (IPT) | G28: Nombre et pourcentage d'adultes et d'enfants nouvellement admis dans des services de prise en charge du VIH qui ont commencé un traitement pour infection tuberculeuse latente | H28: Número y porcentaje de adultos y niños que han comenzado a recibir servicios de atención del VIH recientemente que empiezan un tratamiento por infección latente de tuberculosis (TPI) | I28: Число и % взрослых и детей, впервые включенных в списки для получения ухода в связи с ВИЧ и начавших лечение от латентного ТБ (профилактическая терапия изониазидом)
A29: 3 | B29: H | C29: Treatment | D29: 28 | E29: =OFFSET(F29,0,LangOffset,1,1) -> # & % of TB patients with known HIV status: TB patients registered during the reporting period who had an HIV test result recorded in the TB register among the total number of TB patients registered during the reporting period | F29: # & % of TB patients with known HIV status: TB patients registered during the reporting period who had an HIV test result recorded in the TB register among the total number of TB patients registered during the reporting period | G29: Nombre et pourcentage de patients tuberculeux avec statut sérologique à l'égard du VIH connu : patients tuberculeux enregistrés pendant la période de communication de l’information dont le résultat du test VIH a été enregistré dans le registre de la tuberculose, par rapport au nombre total de patients tuberculeux enregistrés pendant la période de communication de l’information | H29: Número y porcentaje de pacientes de tuberculosis con estado serológico respecto al VIH conocido: pacientes con tuberculosis registrados durante el período de informe para los que se registró el resultado de la prueba del VIH en el registro de tuberculosis entre el total de pacientes de tuberculosis registrados durante el período de informe | I29: Число и % пациентов с ТБ, которые знают свой ВИЧ-статус: доля пациентов с ТБ, зарегистрированных за отчетный период, чьи результаты тестирования на ВИЧ были занесены в реестр больных туберкулезом, по отношению к общему числу пациентов с ТБ, зарегистрированных за отчетный период
A30: 3 | B30: H | C30: Treatment | D30: 29 | E30: =OFFSET(F30,0,LangOffset,1,1) -> # & % of HIV-positive TB patients given anti-retroviral therapy during TB treatment | F30: # & % of HIV-positive TB patients given anti-retroviral therapy during TB treatment | G30: Nombre et pourcentage de patients séropositifs atteints de tuberculose ayant suivi une thérapie antirétrovirale pendant leur traitement contre la tuberculose | H30: Número y porcentaje de pacientes de tuberculosis seropositivos que reciben terapia antirretroviral durante el tratamiento de la tuberculosis | I30: Число и % ВИЧ-положительных пациентов с ТБ, получавших антиретровирусную терапию в ходе противотуберкулезного лечения
A31: 4 | B31: H | C31: Monitoring and Evaluation | D31: 30 | E31: =OFFSET(F31,0,LangOffset,1,1) -> # & % of reporting units submitting timely reports according to national guidelines | F31: # & % of reporting units submitting timely reports according to national guidelines | G31: Nombre et pourcentage d’entités déclarantes présentant leurs rapports dans les délais selon les directives nationales | H31: Número y porcentaje de equipos informadores que presentan los informes puntualmente conforme a las directrices nacionales | I31: Число и % отчетных учреждений, своевременно представляющих отчетность в соответствии с национальными руководящими принципами
A32: 6 | B32: T | C32: DOTS-based package | D32: 31 | E32: =OFFSET(F32,0,LangOffset,1,1) -> # of notified cases of bacteriologically confirmed TB | F32: # of notified cases of bacteriologically confirmed TB | G32: Nombre de cas déclarés de tuberculose bactériologiquement confirmés | H32: Número de casos notificados de tuberculosis confirmada bacteriológicamente | I32: Число зарегистрированных и бактериологически подтвержденных случаев ТБ
A33: 6 | B33: T | C33: DOTS-based package | D33: 32 | E33: =OFFSET(F33,0,LangOffset,1,1) -> # of notified cases of all forms of TB (bacteriologically confirmed plus clinically diagnosed) | F33: # of notified cases of all forms of TB (bacteriologically confirmed plus clinically diagnosed) | G33: Nombre de cas déclarés de tuberculose, toutes formes confondues (bactériologiquement confirmés et cliniquement diagnostiqués) | H33: Número de casos notificados de tuberculosis en todas sus formas (confirmada bacteriológicamente y con diagnóstico clínico) | I33: Число зарегистрированных случаев любых форм ТБ (бактериологически подтвержденных + клинически диагностированных)
... A74: 22 | B74: S | C74: Healthcare financing | D74: 73 | E74: =OFFSET(F74,0,LangOffset,1,1) -> Government expenditure on health as percentage of general government expenditure | F74: Government expenditure on health as percentage of general government expenditure | G74: Dépenses publiques allouées à la santé, en pourcentage des dépenses publiques globales | H74: Gasto gubernamental en materia de salud expresado como porcentaje del gasto general del gobierno | I74: Процентная доля государственных расходов на здравоохранение по отношению к общему объему государственных расходов

Sheet Outcome ind
A1: CmpId | B1: CmpAcro | C1: Module | D1: OutcIndId | E1: Label | F1: Outcome Indicator en | G1: Outcome Indicator fr | H1: Outcome Indicator es | I1: Outcome Indicator ru
A2: 1 | B2: H | C2: Prevention | D2: 1 | E2: =OFFSET(F2,0,LangOffset,1,1) -> % of women and men aged 15–49 years who have had more than one sexual partner in the past 12 months (disaggregated by 15-19 and 20-24 age groups) | F2: % of women and men aged 15–49 years who have had more than one sexual partner in the past 12 months (disaggregated by 15-19 and 20-24 age groups) | G2: Pourcentage de femmes et d'hommes âgés de 15 à 49 ans ayant eu plus d'un partenaire sexuel au cours des 12 derniers mois (ventilé par tranche d'âge allant de 15 à 19 ans et de 20 à 24 ans) | H2: Porcentaje de mujeres y hombres de entre 15 y 49 años que han tenido más de una pareja sexual en los últimos 12 meses (desglosado por grupos de edad de 15 a 19 y de 20 a 24) | I2: % женщин и мужчин в возрасте от 15 до 49 лет, которые за последние 12 месяцев имели половые контакты более чем с одним партнером (с разбивкой по возрастным группам 15-19 лет и 20-24 года)
A3: 1 | B3: H | C3: Prevention | D3: 2 | E3: =OFFSET(F3,0,LangOffset,1,1) -> % of women and men aged 15–49 years who have had more than one sexual partner in the past 12 months reporting the use of a condom during their last sexual intercourse (disaggregated by 15-19 and 20-24 age groups) | F3: % of women and men aged 15–49 years who have had more than one sexual partner in the past 12 months reporting the use of a condom during their last sexual intercourse (disaggregated by 15-19 and 20-24 age groups) | G3: Pourcentage de femmes et d'hommes âgés de 15 à 49 ans ayant eu plus d'un partenaire sexuel au cours des 12 derniers mois et ayant déclaré avoir utilisé un préservatif lors de leur dernier rapport sexuel (ventilé par tranche d'âge allant de 15 à 19 ans et de 20 à 24 ans) | H3: Porcentaje de mujeres y hombres de entre 15 y 49 años que han tenido más de una pareja sexual en los últimos 12 meses y dicen haber utilizado preservativo en su última relación sexual (desglosado por grupos de edad de 15 a 19 y de 20 a 24) | I3: % женщин и мужчин в возрасте от 15 до 49 лет, которые за последние 12 месяцев имели половые контакты более чем с одним партнером и использовали презерватив при последнем половом контакте (с разбивкой по возрастным группам 15-19 лет и 20-24 года)
A4: 1 | B4: H | C4: Prevention | D4: 3 | E4: =OFFSET(F4,0,LangOffset,1,1) -> % of men reporting the use of a condom the last time they had anal sex with a male partner | F4: % of men reporting the use of a condom the last time they had anal sex with a male partner | G4: Pourcentage d'hommes ayant déclaré avoir utilisé un préservatif lors de leur dernier rapport anal avec un partenaire de sexe masculin | H4: Porcentaje de hombres que afirman haber utilizado preservativo en su última relación de sexo anal con otro hombre | I4: % мужчин, сообщивших об использовании презерватива во время последнего анального полового акта с партнером мужского пола
A5: 1 | B5: H | C5: Prevention | D5: 4 | E5: =OFFSET(F5,0,LangOffset,1,1) -> % of sex workers reporting use of a condom with their most recent client | F5: % of sex workers reporting use of a condom with their most recent client | G5: Pourcentage de travailleurs du sexe ayant déclaré avoir utilisé un préservatif avec leur dernier client | H5: Porcentaje de profesionales del sexo que dicen haber utilizado preservativo con su último cliente | I5: % работников секс-бизнеса, сообщивших об использовании презерватива с последним клиентом
