Workbook

Sheet Summary
A1: FY 2012
A2: Telecommunications Equity Aid
A4: PAYMENTS TO TELECOM ACCESS CLUSTERS | F4: DIRECT PAYMENTS TO SCHOOLS
A6: Cluster | B6: NUMBER | C6: Aid Eligible | D6: Prorated Aid | F6: None
A7: CMETS | B7: 01-206 | C7: ='Schools by Cluster Group'!O11 -> 118050.74 | D7: ='Schools by Cluster Group'!Q11 -> 54618.46
A8: ECMECC | B8: 50-6003 | C8: ='Schools by Cluster Group'!O27 -> 548617.9 | D8: ='Schools by Cluster Group'!Q27 -> 253828.76
A9: FRESHWATER ED. DIST. | B9: 61-6004 | C9: ='Schools by Cluster Group'!O40 -> 45305.74 | D9: ='Schools by Cluster Group'!Q40 -> 20961.58
A10: REGION 10 - SOUTHEAST SERVICE COOP | B10: 83-0921 | C10: ='Schools by Cluster Group'!O60 -> 569516.78 | D10: ='Schools by Cluster Group'!Q60 -> 263498.02
A11: IASC | B11: 50-6070 | C11: ='Schools by Cluster Group'!O70 -> 75790.01 | D11: ='Schools by Cluster Group'!Q70 -> 35065.72
A12: LITTLE CROW TELE-MEDIA NETWORK | B12: 50-6040 | C12: ='Schools by Cluster Group'!O84 -> 322598 | D12: ='Schools by Cluster Group'!Q84 -> 149256.23
A13: MSET | B13: 61-6979 | C13: ='Schools by Cluster Group'!O96 -> 115285.23 | D13: ='Schools by Cluster Group'!Q96 -> 53338.95
A14: MNRVED | B14: 61-6018 | C14: ='Schools by Cluster Group'!O106 -> 119557.91 | D14: ='Schools by Cluster Group'!Q106 -> 55315.82
A15: NW LINKS (REGION I) | B15: 82-0869 | C15: ='Schools by Cluster Group'!O172 -> 879326.4 | D15: ='Schools by Cluster Group'!Q172 -> 406837.47
A16: REDWOOD AREA TELECOM COOPERATIVE | B16: 01-2890 | C16: ='Schools by Cluster Group'!O178 -> 23519.72 | D16: ='Schools by Cluster Group'!Q178 -> 10881.85
A17: REGION 2 - ARCC | B17: 82-0868 | C17: ='Schools by Cluster Group'!O190 -> 82066.97 | D17: ='Schools by Cluster Group'!Q190 -> 37969.88
A18: CENTRAL | B18: 82-0867 | C18: ='Schools by Cluster Group'!O214 -> 350028 | D18: ='Schools by Cluster Group'!Q214 -> 161947.27
A19: NESC | B19: 83-0927 | C19: ='Schools by Cluster Group'!O234 -> 536144.05 | D19: ='Schools by Cluster Group'!Q234 -> 248057.5
A20: Ties (Region 7) | B20: 82-0925 | C20: ='Schools by Cluster Group'!O275 -> 2492939 | D20: ='Schools by Cluster Group'!Q275 -> 1153406.7
A21: SOUTHWEST (Region 6 & 8) | B21: 83-0991 | C21: ='Schools by Cluster Group'!O311 -> 683147.3 | D21: ='Schools by Cluster Group'!Q311 -> 316071.4
A22: SOCRATES | B22: 50-6036 | C22: ='Schools by Cluster Group'!O342 -> 986300.58 | D22: ='Schools by Cluster Group'!Q342 -> 456331.15
A23: WETC | B23: 50-6048 | C23: ='Schools by Cluster Group'!O348 -> 131424.98 | D23: ='Schools by Cluster Group'!Q348 -> 60806.32
A24: SCSN | B24: 01-720 | C24: ='Schools by Cluster Group'!O353 -> 25519 | D24: ='Schools by Cluster Group'!Q353 -> 11806.86
A25: TOTAL | C25: =SUM(C7:C24) -> 8105138.3 | D25: =SUM(D7:D24) -> 3750000
A29: Proration Rate > | B29: 0.46266947

Sheet Schools by Cluster Group
A1: Dist Num | B1: District Or School Name | C1: Cluster Name | D1: Cluster Num | E1: Cluster Type | F1: Line Lease Before Erate | G1: Line Lease After Erate | H1: Install Before E Rate | I1: E Rate Discount Install | J1: Install After E Rate | K1: COOP Costs | L1: Maint Costs | M1: E Rate Discount | N1: Total Before E Rate | O1: Total After E Rate | P1: Prorated Aid Amount | Q1: Rounded
A2: 206 | B2: ALEXANDRIA PUBLIC SCHOOL DISTRICT | C2: CENTRAL MN ED TELECOM SYSTEM | D2: 6054 | E2: 50 | F2: 63276.98 | G2: 23354.5 | H2: 0 | I2: 0 | J2: 0 | K2: 0 | L2: 4680 | M2: 39922.48 | N2: 67956.98 | O2: 28034.5 | P2: =O2*Summary!$B$29 -> 12970.707 | Q2: =ROUND(P2,2) -> 12970.71
A3: 207 | B3: BRANDON PUBLIC SCHOOL DISTRICT | C3: CENTRAL MN ED TELECOM SYSTEM | D3: 6054 | E3: 50 | F3: 24859.46 | G3: 9610.56 | H3: 0 | I3: 0 | J3: 0 | K3: 0 | L3: 0 | M3: 15248.9 | N3: 24859.46 | O3: 9610.56 | P3: =O3*Summary!$B$29 -> 4446.5127 | Q3: =ROUND(P3,2) -> 4446.51
A4: 208 | B4: EVANSVILLE PUBLIC SCHOOL DISTRICT | C4: CENTRAL MN ED TELECOM SYSTEM | D4: 6054 | E4: 50 | F4: 24859.46 | G4: 9610.56 | H4: 0 | I4: 0 | J4: 0 | K4: 0 | L4: 0 | M4: 15248.9 | N4: 24859.46 | O4: 9610.56 | P4: =O4*Summary!$B$29 -> 4446.5127 | Q4: =ROUND(P4,2) -> 4446.51
A5: 213 | B5: OSAKIS PUBLIC SCHOOL DISTRICT | C5: CENTRAL MN ED TELECOM SYSTEM | D5: 6054 | E5: 50 | F5: 24859.46 | G5: 9610.56 | H5: 0 | I5: 0 | J5: 0 | K5: 0 | L5: 0 | M5: 15248.9 | N5: 24859.46 | O5: 9610.56 | P5: =O5*Summary!$B$29 -> 4446.5127 | Q5: =ROUND(P5,2) -> 4446.51
A6: 547 | B6: PARKERS PRAIRIE PUBLIC SCHOOL DIST. | C6: CENTRAL MN ED TELECOM SYSTEM | D6: 6054 | E6: 50 | F6: 24859.46 | G6: 9610.56 | H6: 0 | I6: 0 | J6: 0 | K6: 0 | L6: 0 | M6: 15248.9 | N6: 24859.46 | O6: 9610.56 | P6: =O6*Summary!$B$29 -> 4446.5127 | Q6: =ROUND(P6,2) -> 4446.51
A7: 740 | B7: MELROSE PUBLIC SCHOOL DISTRICT | C7: CENTRAL MN ED TELECOM SYSTEM | D7: 6054 | E7: 50 | F7: 24859.46 | G7: 9610.56 | H7: 0 | I7: 0 | J7: 0 | K7: 0 | L7: 0 | M7: 15248.9 | N7: 24859.46 | O7: 9610.56 | P7: =O7*Summary!$B$29 -> 4446.5127 | Q7: =ROUND(P7,2) -> 4446.51
A8: 743 | B8: SAUK CENTRE PUBLIC SCHOOL DISTRICT | C8: CENTRAL MN ED TELECOM SYSTEM | D8: 6054 | E8: 50 | F8: 24859.46 | G8: 9610.56 | H8: 0 | I8: 0 | J8: 0 | K8: 0 | L8: 0 | M8: 15248.9 | N8: 24859.46 | O8: 9610.56 | P8: =O8*Summary!$B$29 -> 4446.5127 | Q8: =ROUND(P8,2) -> 4446.51
A9: 745 | B9: ALBANY PUBLIC SCHOOL DISTRICT | C9: CENTRAL MN ED TELECOM SYSTEM | D9: 6054 | E9: 50 | F9: 24859.46 | G9: 9610.56 | H9: 0 | I9: 0 | J9: 0 | K9: 0 | L9: 0 | M9: 15248.9 | N9: 24859.46 | O9: 9610.56 | P9: =O9*Summary!$B$29 -> 4446.5127 | Q9: =ROUND(P9,2) -> 4446.51
A10: 2149 | B10: MINNEWASKA SCHOOL DISTRICT | C10: CENTRAL MN ED TELECOM SYSTEM | D10: 6054 | E10: 50 | F10: 63311.46 | G10: 22742.32 | H10: 0 | I10: 0 | J10: 0 | K10: 0 | L10: 0 | M10: 40569.14 | N10: 63311.46 | O10: 22742.32 | P10: =O10*Summary!$B$29 -> 10522.177 | Q10: =ROUND(P10,2) -> 10522.18
M11: =SUM(M2:M10) -> 187233.92 | N11: =SUM(N2:N10) -> 305284.66 | O11: =SUM(O2:O10) -> 118050.74 | P11: =SUM(P2:P10) -> 54618.473 | Q11: =SUM(Q2:Q10) -> 54618.46
A14: 15 | B14: ST. FRANCIS PUBLIC SCHOOL DISTRICT | C14: EAST CENTRAL MN ED. CABLE COOP. | D14: 6003 | E14: 50 | F14: 73845 | G14: 35088.3 | H14: 0 | I14: 0 | J14: 0 | K14: 27771.71 | L14: 0 | M14: 38756.7 | N14: 101616.71 | O14: 62860.01 | P14: =O14*Summary!$B$29 -> 29083.407 | Q14: =ROUND(P14,2) -> 29083.41
A15: 138 | B15: NORTH BRANCH PUBLIC SCHOOLS | C15: EAST CENTRAL MN ED. CABLE COOP. | D15: 6003 | E15: 50 | F15: 55740 | G15: 25105.2 | H15: 0 | I15: 0 | J15: 0 | K15: 20483.21 | L15: 323.6 | M15: 30634.8 | N15: 76546.81 | O15: 45912.01 | P15: =O15*Summary!$B$29 -> 21242.085 | Q15: =ROUND(P15,2) -> 21242.09
A16: 139 | B16: RUSH CITY PUBLIC SCHOOL DISTRICT | C16: EAST CENTRAL MN ED. CABLE COOP. | D16: 6003 | E16: 50 | F16: 47235 | G16: 19963.5 | H16: 0 | I16: 0 | J16: 0 | K16: 10062.26 | L16: 0 | M16: 27271.5 | N16: 57297.26 | O16: 30025.76 | P16: =O16*Summary!$B$29 -> 13892.002 | Q16: =ROUND(P16,2) -> 13892
A17: 314 | B17: BRAHAM PUBLIC SCHOOL DISTRICT | C17: EAST CENTRAL MN ED. CABLE COOP. | D17: 6003 | E17: 50 | F17: 50700 | G17: 19422 | H17: 0 | I17: 0 | J17: 0 | K17: 15406.23 | L17: 0 | M17: 31278 | N17: 66106.23 | O17: 34828.23 | P17: =O17*Summary!$B$29 -> 16113.959 | Q17: =ROUND(P17,2) -> 16113.96
A18: 332 | B18: MORA PUBLIC SCHOOL DISTRICT | C18: EAST CENTRAL MN ED. CABLE COOP. | D18: 6003 | E18: 50 | F18: 47310 | G18: 16819.5 | H18: 0 | I18: 0 | J18: 0 | K18: 13186.52 | L18: 0 | M18: 30490.5 | N18: 60496.52 | O18: 30006.02 | P18: =O18*Summary!$B$29 -> 13882.869 | Q18: =ROUND(P18,2) -> 13882.87
A19: 333 | B19: OGILVIE PUBLIC SCHOOL DISTRICT | C19: EAST CENTRAL MN ED. CABLE COOP. | D19: 6003 | E19: 50 | F19: 37875 | G19: 12928.5 | H19: 0 | I19: 0 | J19: 0 | K19: 8124.92 | L19: 0 | M19: 24946.5 | N19: 45999.92 | O19: 21053.42 | P19: =O19*Summary!$B$29 -> 9740.7746 | Q19: =ROUND(P19,2) -> 9740.77
A20: 477 | B20: PRINCETON PUBLIC SCHOOL DISTRICT | C20: EAST CENTRAL MN ED. CABLE COOP. | D20: 6003 | E20: 50 | F20: 48015 | G20: 18819.45 | H20: 0 | I20: 0 | J20: 0 | K20: 19823.67 | L20: 2034.4 | M20: 29195.55 | N20: 69873.07 | O20: 40677.52 | P20: =O20*Summary!$B$29 -> 18820.246 | Q20: =ROUND(P20,2) -> 18820.25
A21: 578 | B21: PINE CITY PUBLIC SCHOOL DISTRICT | C21: EAST CENTRAL MN ED. CABLE COOP. | D21: 6003 | E21: 50 | F21: 56855 | G21: 20276.25 | H21: 0 | I21: 0 | J21: 0 | K21: 18873.64 | L21: 0 | M21: 36578.75 | N21: 75728.64 | O21: 39149.89 | P21: =O21*Summary!$B$29 -> 18113.459 | Q21: =ROUND(P21,2) -> 18113.46
A22: 911 | B22: CAMBRIDGE-ISANTI PUBLIC SCHOOL DIST | C22: EAST CENTRAL MN ED. CABLE COOP. | D22: 6003 | E22: 50 | F22: 93840 | G22: 41616 | H22: 0 | I22: 0 | J22: 0 | K22: 26903.3 | L22: 0 | M22: 52224 | N22: 120743.3 | O22: 68519.3 | P22: =O22*Summary!$B$29 -> 31701.788 | Q22: =ROUND(P22,2) -> 31701.79
A23: 912 | B23: MILACA PUBLIC SCHOOL DISTRICT | C23: EAST CENTRAL MN ED. CABLE COOP. | D23: 6003 | E23: 50 | F23: 44895 | G23: 16914 | H23: 0 | I23: 0 | J23: 0 | K23: 13496.67 | L23: 0 | M23: 27981 | N23: 58391.67 | O23: 30410.67 | P23: =O23*Summary!$B$29 -> 14070.088 | Q23: =ROUND(P23,2) -> 14070.09
A24: 2144 | B24: CHISAGO LAKES SCHOOL DISTRICT | C24: EAST CENTRAL MN ED. CABLE COOP. | D24: 6003 | E24: 50 | F24: 96270 | G24: 55407.3 | H24: 0 | I24: 0 | J24: 0 | K24: 20512.16 | L24: 1028 | M24: 40862.7 | N24: 117810.16 | O24: 76947.46 | P24: =O24*Summary!$B$29 -> 35601.24 | Q24: =ROUND(P24,2) -> 35601.24
A25: 2165 | B25: HINCKLEY-FINLAYSON SCHOOL DISTRICT | C25: EAST CENTRAL MN ED. CABLE COOP. | D25: 6003 | E25: 50 | F25: 73640 | G25: 23636.4 | H25: 0 | I25: 0 | J25: 0 | K25: 16268.4 | L25: 0 | M25: 50003.6 | N25: 89908.4 | O25: 39904.8 | P25: =O25*Summary!$B$29 -> 18462.732 | Q25: =ROUND(P25,2) -> 18462.73
A26: 2580 | B26: EAST CENTRAL SCHOOL DISTRICT | C26: EAST CENTRAL MN ED. CABLE COOP. | D26: 6003 | E26: 50 | F26: 44718 | G26: 13026.2 | H26: 0 | I26: 0 | J26: 0 | K26: 15296.61 | L26: 0 | M26: 31691.8 | N26: 60014.61 | O26: 28322.81 | P26: =O26*Summary!$B$29 -> 13104.099 | Q26: =ROUND(P26,2) -> 13104.1
M27: =SUM(M14:M26) -> 451915.4 | N27: =SUM(N14:N26) -> 1000533.3 | O27: =SUM(O14:O26) -> 548617.9 | P27: =SUM(P14:P26) -> 253828.75 | Q27: =SUM(Q14:Q26) -> 253828.76
A30: 116 | B30: PILLAGER PUBLIC SCHOOL DISTRICT | C30: FRESHWATER ED. DIST. | D30: 6004 | E30: 61 | F30: 9018 | G30: 1803.6 | H30: 0 | I30: 0 | J30: 0 | K30: 863.08 | L30: 1797.5 | M30: 7214.4 | N30: 11678.58 | O30: 4464.18 | P30: =O30*Summary!$B$29 -> 2065.4398 | Q30: =ROUND(P30,2) -> 2065.44
A31: 545 | B31: HENNING PUBLIC SCHOOL DISTRICT | C31: FRESHWATER ED. DIST. | D31: 6004 | E31: 61 | F31: 12480 | G31: 3744 | H31: 0 | I31: 0 | J31: 0 | K31: 1797.5 | L31: 863.08 | M31: 8736 | N31: 15140.58 | O31: 6404.58 | P31: =O31*Summary!$B$29 -> 2963.2036 | Q31: =ROUND(P31,2) -> 2963.2
A32: 786 | B32: BERTHA-HEWITT PUBLIC SCHOOL DIST. | C32: FRESHWATER ED. DIST. | D32: 6004 | E32: 61 | F32: 11856 | G32: 2371.2 | H32: 0 | I32: 0 | J32: 0 | K32: 0 | L32: 0 | M32: 9484.8 | N32: 11856 | O32: 2371.2 | P32: =O32*Summary!$B$29 -> 1097.0818 | Q32: =ROUND(P32,2) -> 1097.08
A33: 787 | B33: BROWERVILLE PUBLIC SCHOOL DISTRICT | C33: FRESHWATER ED. DIST. | D33: 6004 | E33: 61 | F33: 12096 | G33: 2419.2 | H33: 0 | I33: 0 | J33: 0 | K33: 0 | L33: 0 | M33: 9676.8 | N33: 12096 | O33: 2419.2 | P33: =O33*Summary!$B$29 -> 1119.29 | Q33: =ROUND(P33,2) -> 1119.29
A34: 818 | B34: VERNDALE PUBLIC SCHOOL DISTRICT | C34: FRESHWATER ED. DIST. | D34: 6004 | E34: 61 | F34: 8502.84 | G34: 1700.57 | H34: 0 | I34: 0 | J34: 0 | K34: 863.08 | L34: 1797.5 | M34: 6802.27 | N34: 11163.42 | O34: 4361.15 | P34: =O34*Summary!$B$29 -> 2017.7709 | Q34: =ROUND(P34,2) -> 2017.77
A35: 820 | B35: SEBEKA PUBLIC SCHOOL DISTRICT | C35: FRESHWATER ED. DIST. | D35: 6004 | E35: 61 | F35: 8502.96 | G35: 1700.59 | H35: 0 | I35: 0 | J35: 0 | K35: 863.08 | L35: 1797.5 | M35: 6802.37 | N35: 11163.54 | O35: 4361.17 | P35: =O35*Summary!$B$29 -> 2017.7802 | Q35: =ROUND(P35,2) -> 2017.78
A36: 821 | B36: MENAHGA PUBLIC SCHOOL DISTRICT | C36: FRESHWATER ED. DIST. | D36: 6004 | E36: 61 | F36: 8502.96 | G36: 2040.71 | H36: 0 | I36: 0 | J36: 0 | K36: 1797.5 | L36: 863.08 | M36: 6462.25 | N36: 11163.54 | O36: 4701.29 | P36: =O36*Summary!$B$29 -> 2175.1433 | Q36: =ROUND(P36,2) -> 2175.14
A37: 2155 | B37: WADENA-DEER CREEK SCHOOL DISTRICT | C37: FRESHWATER ED. DIST. | D37: 6004 | E37: 61 | F37: 10575 | G37: 2115 | H37: 0 | I37: 0 | J37: 0 | K37: 863.08 | L37: 1797.5 | M37: 8460 | N37: 13235.58 | O37: 4775.58 | P37: =O37*Summary!$B$29 -> 2209.515 | Q37: =ROUND(P37,2) -> 2209.52
A38: 2170 | B38: STAPLES-MOTLEY SCHOOL DISTRICT | C38: FRESHWATER ED. DIST. | D38: 6004 | E38: 61 | F38: 12698.57 | G38: 2683.56 | H38: 0 | I38: 0 | J38: 0 | K38: 1797.5 | L38: 0 | M38: 10015.01 | N38: 14496.07 | O38: 4481.06 | P38: =O38*Summary!$B$29 -> 2073.2496 | Q38: =ROUND(P38,2) -> 2073.25
A39: 2759 | B39: EAGLE VALLEY PUBLIC SCHOOL DISTRICT | C39: FRESHWATER ED. DIST. | D39: 6004 | E39: 61 | F39: 17223 | G39: 4305.75 | H39: 0 | I39: 0 | J39: 0 | K39: 863.08 | L39: 1797.5 | M39: 12917.25 | N39: 19883.58 | O39: 6966.33 | P39: =O39*Summary!$B$29 -> 3223.1082 | Q39: =ROUND(P39,2) -> 3223.11
M40: =SUM(M30:M39) -> 86571.15 | N40: =SUM(N30:N39) -> 131876.89 | O40: =SUM(O30:O39) -> 45305.74 | P40: =SUM(P30:P39) -> 20961.582 | Q40: =SUM(Q30:Q39) -> 20961.58
A43: 227 | B43: CHATFIELD PUBLIC SCHOOLS | C43: REGION 10 - SOUTHEAST SERVICE COOP | D43: 921 | E43: 83 | F43: 50973.56 | G43: 28035.46 | H43: 1900 | I43: 855 | J43: 1045 | K43: 1599.95 | L43: 0 | M43: 23793.1 | N43: 54473.51 | O43: 30680.41 | P43: =O43*Summary!$B$29 -> 14194.889 | Q43: =ROUND(P43,2) -> 14194.89
A44: 241 | B44: ALBERT LEA PUBLIC SCHOOL DISTRICT | C44: REGION 10 - SOUTHEAST SERVICE COOP | D44: 921 | E44: 83 | F44: 113340 | G44: 35135.4 | H44: 1250 | J44: 1250 | K44: 1000 | L44: 0 | M44: 78204.6 | N44: 115590 | O44: 37385.4 | P44: =O44*Summary!$B$29 -> 17297.083 | Q44: =ROUND(P44,2) -> 17297.08
A45: 252 | B45: CANNON FALLS PUBLIC SCHOOL DISTRICT | C45: REGION 10 - SOUTHEAST SERVICE COOP | D45: 921 | E45: 83 | F45: 65446.01 | G45: 32722.86 | H45: 0 | I45: 0 | J45: 0 | K45: 1446.54 | L45: 0 | M45: 32723.15 | N45: 66892.55 | O45: 34169.4 | P45: =O45*Summary!$B$29 -> 15809.138 | Q45: =ROUND(P45,2) -> 15809.14
A46: 255 | B46: PINE ISLAND PUBLIC SCHOOL DIST. | C46: REGION 10 - SOUTHEAST SERVICE COOP | D46: 921 | E46: 83 | F46: 67583.25 | G46: 31507.67 | H46: 0 | I46: 0 | J46: 0 | K46: 1232.64 | L46: 0 | M46: 36075.58 | N46: 68815.89 | O46: 32740.31 | P46: =O46*Summary!$B$29 -> 15147.942 | Q46: =ROUND(P46,2) -> 15147.94
A47: 294 | B47: HOUSTON PUBLIC SCHOOL DISTRICT | C47: REGION 10 - SOUTHEAST SERVICE COOP | D47: 921 | E47: 83 | F47: 55135.51 | G47: 26526.49 | H47: 250 | I47: 0 | J47: 250 | K47: 1000 | L47: 0 | M47: 28609.02 | N47: 56385.51 | O47: 27776.49 | P47: =O47*Summary!$B$29 -> 12851.334 | Q47: =ROUND(P47,2) -> 12851.33
A48: 497 | B48: LYLE PUBLIC SCHOOL DISTRICT | C48: REGION 10 - SOUTHEAST SERVICE COOP | D48: 921 | E48: 83 | F48: 19883.58 | G48: 5225.1 | H48: 250 | I48: 0 | J48: 250 | K48: 1000 | L48: 0 | M48: 14658.48 | N48: 21133.58 | O48: 6475.1 | P48: =O48*Summary!$B$29 -> 2995.8311 | Q48: =ROUND(P48,2) -> 2995.83
A49: 499 | B49: LEROY-OSTRANDER PUBLIC SCHOOLS | C49: REGION 10 - SOUTHEAST SERVICE COOP | D49: 921 | E49: 83 | F49: 24860.58 | G49: 7459.64 | H49: 0 | I49: 0 | J49: 0 | K49: 1537.64 | L49: 0 | M49: 17400.94 | N49: 26398.22 | O49: 8997.28 | P49: =O49*Summary!$B$29 -> 4162.7667 | Q49: =ROUND(P49,2) -> 4162.77
A50: 500 | B50: SOUTHLAND PUBLIC SCHOOL DISTRICT | C50: REGION 10 - SOUTHEAST SERVICE COOP | D50: 921 | E50: 83 | F50: 21429.84 | G50: 8571.94 | H50: 0 | I50: 0 | J50: 0 | K50: 1581.67 | L50: 0 | M50: 12857.9 | N50: 23011.51 | O50: 10153.61 | P50: =O50*Summary!$B$29 -> 4697.7653 | Q50: =ROUND(P50,2) -> 4697.77
A51: 531 | B51: BYRON PUBLIC SCHOOL DISTRICT | C51: REGION 10 - SOUTHEAST SERVICE COOP | D51: 921 | E51: 83 | F51: 41211.84 | G51: 24932.67 | H51: 0 | I51: 0 | J51: 0 | K51: 1272.12 | L51: 6040.22 | M51: 16279.17 | N51: 48524.18 | O51: 32245.01 | P51: =O51*Summary!$B$29 -> 14918.782 | Q51: =ROUND(P51,2) -> 14918.78
A52: 533 | B52: DOVER-EYOTA PUBLIC SCHOOL DISTRICT | C52: REGION 10 - SOUTHEAST SERVICE COOP | D52: 921 | E52: 83 | F52: 22642.2 | G52: 12453.21 | H52: 0 | I52: 0 | J52: 0 | K52: 1000 | L52: 0 | M52: 10188.99 | N52: 23642.2 | O52: 13453.21 | P52: =O52*Summary!$B$29 -> 6224.3895 | Q52: =ROUND(P52,2) -> 6224.39
A53: 534 | B53: STEWARTVILLE PUBLIC SCHOOL DISTRICT | C53: REGION 10 - SOUTHEAST SERVICE COOP | D53: 921 | E53: 83 | F53: 38127.6 | G53: 19063.8 | H53: 0 | I53: 0 | J53: 0 | K53: 1000 | L53: 0 | M53: 19063.8 | N53: 39127.6 | O53: 20063.8 | P53: =O53*Summary!$B$29 -> 9282.9076 | Q53: =ROUND(P53,2) -> 9282.91
A54: 535 | B54: ROCHESTER PUBLIC SCHOOL DISTRICT | C54: REGION 10 - SOUTHEAST SERVICE COOP | D54: 921 | E54: 83 | F54: 439275.12 | G54: 204518.31 | H54: 0 | I54: 0 | J54: 0 | K54: 1000 | L54: 10698.92 | M54: 234756.81 | N54: 450974.04 | O54: 216217.23 | P54: =O54*Summary!$B$29 -> 100037.11 | Q54: =ROUND(P54,2) -> 100037.11
A55: 2137 | B55: KINGSLAND PUBLIC SCHOOL DISTRICT | C55: REGION 10 - SOUTHEAST SERVICE COOP | D55: 921 | E55: 83 | F55: 68720.58 | G55: 24052.23 | H55: 0 | I55: 0 | J55: 0 | K55: 1000 | L55: 0 | M55: 44668.35 | N55: 70118.66 | O55: 25450.31 | P55: =O55*Summary!$B$29 -> 11775.081 | Q55: =ROUND(P55,2) -> 11775.08
A56: 2899 | B56: PLAINVIEW-ELGIN-MILLVILLE | C56: REGION 10 - SOUTHEAST SERVICE COOP | D56: 921 | E56: 83 | F56: 31452 | G56: 13524.36 | H56: 0 | I56: 0 | J56: 0 | K56: 1398.08 | L56: 0 | M56: 17927.64 | N56: 32917.38 | O56: 14989.74 | P56: =O56*Summary!$B$29 -> 6935.295 | Q56: =ROUND(P56,2) -> 6935.29
... A58: 256 | B58: RED WING PUBLIC SCHOOL DISTRICT | C58: REGION 10 - SOUTHEAST SERVICE COOP | D58: 921 | E58: 83 | F58: 16800 | G58: 6384 | H58: 0 | I58: 0 | J58: 0 | K58: 1000 | L58: 0 | M58: 10416 | N58: 17800 | O58: 7384 | P58: =O58*Summary!$B$29 -> 3416.3513 | Q58: =ROUND(P58,2) -> 3416.35
A59: 495 | B59: GRAND MEADOW PUBLIC SCHOOLS | C59: REGION 10 - SOUTHEAST SERVICE COOP | D59: 921 | E59: 83 | F59: 46863 | G59: 31509.38 | K59: 1000 | M59: 15353.62 | N59: 47863 | O59: 32509.38 | P59: =O59*Summary!$B$29 -> 15041.097 | Q59: =ROUND(P59,2) -> 15041.1
M60: =SUM(M43:M59) -> 627108.05 | N60: =SUM(N43:N59) -> 1196624.8 | O60: =SUM(O43:O59) -> 569516.78 | P60: =SUM(P43:P59) -> 263498.02 | Q60: =SUM(Q43:Q59) -> 263498.02
A63: 2 | B63: HILL CITY PUBLIC SCHOOL DISTRICT | C63: ITASCA AREA SCHOOLS COLLABORATIVE E | D63: 6070 | E63: 50 | F63: 11802.84 | G63: 2714.65 | H63: 0 | I63: 0 | J63: 0 | K63: 616.84 | L63: 0 | M63: 9088.19 | N63: 12419.68 | O63: 3331.49 | P63: =O63*Summary!$B$29 -> 1541.3787 | Q63: =ROUND(P63,2) -> 1541.38
A64: 118 | B64: NORTHLAND COMMUNITY SCHOOLS | C64: ITASCA AREA SCHOOLS COLLABORATIVE E | D64: 6070 | E64: 50 | F64: 540 | G64: 108 | H64: 0 | I64: 0 | J64: 0 | K64: 2714.65 | L64: 0 | M64: 432 | N64: 3254.65 | O64: 2822.65 | P64: =O64*Summary!$B$29 -> 1305.954 | Q64: =ROUND(P64,2) -> 1305.95
A65: 316 | B65: GREENWAY PUBLIC SCHOOL DISTRICT | C65: ITASCA AREA SCHOOLS COLLABORATIVE E | D65: 6070 | E65: 50 | F65: 14400 | G65: 3312 | H65: 0 | I65: 0 | J65: 0 | K65: 5127.16 | L65: 0 | M65: 11088 | N65: 19527.16 | O65: 8439.16 | P65: =O65*Summary!$B$29 -> 3904.5416 | Q65: =ROUND(P65,2) -> 3904.54
A66: 317 | B66: DEER RIVER PUBLIC SCHOOL DISTRICT | C66: ITASCA AREA SCHOOLS COLLABORATIVE E | D66: 6070 | E66: 50 | F66: 19817.16 | G66: 7490.42 | H66: 0 | I66: 0 | J66: 0 | K66: 1824.61 | L66: 7500 | M66: 12326.74 | N66: 29141.77 | O66: 16815.03 | P66: =O66*Summary!$B$29 -> 7779.8009 | Q66: =ROUND(P66,2) -> 7779.8
A67: 318 | B67: GRAND RAPIDS PUBLIC SCHOOL DISTRICT | C67: ITASCA AREA SCHOOLS COLLABORATIVE E | D67: 6070 | E67: 50 | F67: 47039.76 | G67: 15933.52 | H67: 0 | I67: 0 | J67: 0 | K67: 27526.99 | L67: 0 | M67: 46315.53 | N67: 74566.75 | O67: 28251.22 | P67: =O67*Summary!$B$29 -> 13070.977 | Q67: =ROUND(P67,2) -> 13070.98
A68: 319 | B68: NASHWAUK-KEEWATIN SCHOOL DISTRICT | C68: ITASCA AREA SCHOOLS COLLABORATIVE E | D68: 6070 | E68: 50 | F68: 28542.99 | G68: 5723.5 | H68: 0 | I68: 0 | J68: 0 | K68: 5025.88 | L68: 0 | M68: 22819.49 | N68: 33568.87 | O68: 10749.38 | P68: =O68*Summary!$B$29 -> 4973.4099 | Q68: =ROUND(P68,2) -> 4973.41
A69: 698 | B69: FLOODWOOD PUBLIC SCHOOL DISTRICT | C69: ITASCA AREA SCHOOLS COLLABORATIVE E | D69: 6070 | E69: 50 | F69: 20382.84 | G69: 4688.04 | H69: 0 | I69: 0 | J69: 0 | K69: 693.04 | L69: 0 | M69: 15694.8 | N69: 21075.88 | O69: 5381.08 | P69: =O69*Summary!$B$29 -> 2489.6614 | Q69: =ROUND(P69,2) -> 2489.66
M70: =SUM(M63:M69) -> 117764.75 | N70: =SUM(N63:N69) -> 193554.76 | O70: =SUM(O63:O69) -> 75790.01 | P70: =SUM(P63:P69) -> 35065.723 | Q70: =SUM(Q63:Q69) -> 35065.72
A73: 345 | B73: NEW LONDON-SPICER SCHOOL DISTRICT | C73: LITTLE CROW TELE-MEDIA NETWORK | D73: 6040 | E73: 50 | F73: 31023 | G73: 10991 | H73: 0 | I73: 0 | J73: 0 | K73: 16414 | L73: 350 | M73: 20032 | N73: 47787 | O73: 27755 | P73: =O73*Summary!$B$29 -> 12841.391 | Q73: =ROUND(P73,2) -> 12841.39
A74: 347 | B74: WILLMAR PUBLIC SCHOOL DISTRICT | C74: LITTLE CROW TELE-MEDIA NETWORK | D74: 6040 | E74: 50 | F74: 90813 | G74: 24144 | H74: 0 | I74: 0 | J74: 0 | K74: 16414 | L74: 350 | M74: 66669 | N74: 107577 | O74: 40908 | P74: =O74*Summary!$B$29 -> 18926.882 | Q74: =ROUND(P74,2) -> 18926.88
A75: 423 | B75: HUTCHINSON PUBLIC SCHOOL DISTRICT | C75: LITTLE CROW TELE-MEDIA NETWORK | D75: 6040 | E75: 50 | F75: 33874 | G75: 14625 | H75: 0 | I75: 0 | J75: 0 | K75: 16414 | L75: 350 | M75: 19249 | N75: 50638 | O75: 31389 | P75: =O75*Summary!$B$29 -> 14522.732 | Q75: =ROUND(P75,2) -> 14522.73
A76: 424 | B76: LESTER PRAIRIE PUBLIC SCHOOL DIST. | C76: LITTLE CROW TELE-MEDIA NETWORK | D76: 6040 | E76: 50 | F76: 29613 | G76: 10364 | H76: 0 | I76: 0 | J76: 0 | K76: 16414 | L76: 350 | M76: 19249 | N76: 46377 | O76: 27128 | P76: =O76*Summary!$B$29 -> 12551.297 | Q76: =ROUND(P76,2) -> 12551.3
A77: 775 | B77: KERKHOVEN-MURDOCK-SUNBURG | C77: LITTLE CROW TELE-MEDIA NETWORK | D77: 6040 | E77: 50 | F77: 29613 | G77: 10364 | H77: 857 | I77: 0 | J77: 857 | K77: 16414 | L77: 350 | M77: 19249 | N77: 47234 | O77: 27985 | P77: =O77*Summary!$B$29 -> 12947.805 | Q77: =ROUND(P77,2) -> 12947.8
A78: 2159 | B78: BUFFALO LK-HECTOR-STEWART PUBLIC SC | C78: LITTLE CROW TELE-MEDIA NETWORK | D78: 6040 | E78: 50 | F78: 29613 | G78: 10364 | H78: 1247 | I78: 0 | J78: 1247 | K78: 16414 | L78: 350 | M78: 19249 | N78: 47624 | O78: 28375 | P78: =O78*Summary!$B$29 -> 13128.246 | Q78: =ROUND(P78,2) -> 13128.25
A79: 2180 | B79: M.A.C.C.R.A.Y. SCHOOL DISTRICT | C79: LITTLE CROW TELE-MEDIA NETWORK | D79: 6040 | E79: 50 | F79: 29613 | G79: 10364 | H79: 857 | I79: 0 | J79: 857 | K79: 16414 | L79: 350 | M79: 19249 | N79: 47234 | O79: 27985 | P79: =O79*Summary!$B$29 -> 12947.805 | Q79: =ROUND(P79,2) -> 12947.8
A80: 2364 | B80: BELGRADE-BROOTEN-ELROSA SCHOOL DIST | C80: LITTLE CROW TELE-MEDIA NETWORK | D80: 6040 | E80: 50 | F80: 45213 | G80: 10364 | H80: 0 | I80: 0 | J80: 0 | K80: 16414 | L80: 350 | M80: 34849 | N80: 61977 | O80: 27128 | P80: =O80*Summary!$B$29 -> 12551.297 | Q80: =ROUND(P80,2) -> 12551.3
A81: 2396 | B81: A.C.G.C. | C81: LITTLE CROW TELE-MEDIA NETWORK | D81: 6040 | E81: 50 | F81: 29613 | G81: 10364 | H81: 857 | I81: 0 | J81: 857 | K81: 16414 | L81: 350 | M81: 19249 | N81: 47234 | O81: 27985 | P81: =O81*Summary!$B$29 -> 12947.805 | Q81: =ROUND(P81,2) -> 12947.8
A82: 2534 | B82: BIRD ISLAND-OLIVIA-LAKE LILLIAN | C82: LITTLE CROW TELE-MEDIA NETWORK | D82: 6040 | E82: 50 | F82: 29613 | G82: 10068 | H82: 750 | I82: 0 | J82: 750 | K82: 16414 | L82: 350 | M82: 19545 | N82: 47127 | O82: 27582 | P82: =O82*Summary!$B$29 -> 12761.349 | Q82: =ROUND(P82,2) -> 12761.35
A83: 2859 | B83: GLENCOE-SILVER LAKE SCHOOL DISTRICT | C83: LITTLE CROW TELE-MEDIA NETWORK | D83: 6040 | E83: 50 | F83: 29613 | G83: 10364 | H83: 1250 | I83: 0 | J83: 1250 | K83: 16414 | L83: 350 | M83: 19249 | N83: 47627 | O83: 28378 | P83: =O83*Summary!$B$29 -> 13129.634 | Q83: =ROUND(P83,2) -> 13129.63
M84: =SUM(M73:M83) -> 275838 | N84: =SUM(N73:N83) -> 598436 | O84: =SUM(O73:O83) -> 322598 | P84: =SUM(P73:P83) -> 149256.24 | Q84: =SUM(Q73:Q83) -> 149256.23
A87: 473 | B87: ISLE PUBLIC SCHOOL DISTRICT | C87: MID STATE EDUCATION DISTRICT | D87: 6979 | E87: 61 | F87: 3954 | G87: 1265.28 | H87: 0 | I87: 0 | J87: 0 | K87: 7189.75 | L87: 4354.44 | M87: 2688.72 | N87: 15498.19 | O87: 12809.47 | P87: =O87*Summary!$B$29 -> 5926.5506 | Q87: =ROUND(P87,2) -> 5926.55
A88: 480 | B88: ONAMIA PUBLIC SCHOOL DISTRICT | C88: MID STATE EDUCATION DISTRICT | D88: 6979 | E88: 61 | F88: 3954 | G88: 1265.28 | H88: 0 | I88: 0 | J88: 0 | K88: 7189.75 | L88: 4354.44 | M88: 2688.72 | N88: 15498.19 | O88: 12809.47 | P88: =O88*Summary!$B$29 -> 5926.5506 | Q88: =ROUND(P88,2) -> 5926.55
A89: 482 | B89: LITTLE FALLS PUBLIC SCHOOL DISTRICT | C89: MID STATE EDUCATION DISTRICT | D89: 6979 | E89: 61 | F89: 3954 | G89: 1265.28 | H89: 0 | I89: 0 | J89: 0 | K89: 7189.75 | L89: 4354.44 | M89: 2688.72 | N89: 15498.19 | O89: 12809.47 | P89: =O89*Summary!$B$29 -> 5926.5506 | Q89: =ROUND(P89,2) -> 5926.55
A90: 484 | B90: PIERZ PUBLIC SCHOOL DISTRICT | C90: MID STATE EDUCATION DISTRICT | D90: 6979 | E90: 61 | F90: 3954 | G90: 1265.28 | H90: 0 | I90: 0 | J90: 0 | K90: 7189.75 | L90: 4354.44 | M90: 2688.72 | N90: 15498.19 | O90: 12809.47 | P90: =O90*Summary!$B$29 -> 5926.5506 | Q90: =ROUND(P90,2) -> 5926.55
A91: 485 | B91: ROYALTON PUBLIC SCHOOL DISTRICT | C91: MID STATE EDUCATION DISTRICT | D91: 6979 | E91: 61 | F91: 3954 | G91: 1265.28 | H91: 0 | I91: 0 | J91: 0 | K91: 7189.75 | L91: 4354.44 | M91: 2688.72 | N91: 15498.19 | O91: 12809.47 | P91: =O91*Summary!$B$29 -> 5926.5506 | Q91: =ROUND(P91,2) -> 5926.55
A92: 486 | B92: SWANVILLE PUBLIC SCHOOL DISTRICT | C92: MID STATE EDUCATION DISTRICT | D92: 6979 | E92: 61 | F92: 3954 | G92: 1265.28 | H92: 0 | I92: 0 | J92: 0 | K92: 7189.75 | L92: 4354.44 | M92: 2688.72 | N92: 15498.19 | O92: 12809.47 | P92: =O92*Summary!$B$29 -> 5926.5506 | Q92: =ROUND(P92,2) -> 5926.55
A93: 487 | B93: UPSALA PUBLIC SCHOOL DISTRICT | C93: MID STATE EDUCATION DISTRICT | D93: 6979 | E93: 61 | F93: 3954 | G93: 1265.28 | H93: 0 | I93: 0 | J93: 0 | K93: 7189.75 | L93: 4354.44 | M93: 2688.72 | N93: 15498.19 | O93: 12809.47 | P93: =O93*Summary!$B$29 -> 5926.5506 | Q93: =ROUND(P93,2) -> 5926.55
A94: 738 | B94: HOLDINGFORD PUBLIC SCHOOL DISTRICT | C94: MID STATE EDUCATION DISTRICT | D94: 6979 | E94: 61 | F94: 3954 | G94: 1265.28 | H94: 0 | I94: 0 | J94: 0 | K94: 7189.75 | L94: 4354.44 | M94: 2688.72 | N94: 15498.19 | O94: 12809.47 | P94: =O94*Summary!$B$29 -> 5926.5506 | Q94: =ROUND(P94,2) -> 5926.55
A95: 2753 | B95: LONG PRAIRIE-GREY EAGLE SCHOOL DIST | C95: MID STATE EDUCATION DISTRICT | D95: 6979 | E95: 61 | F95: 3954 | G95: 1265.28 | H95: 0 | I95: 0 | J95: 0 | K95: 7189.75 | L95: 4354.44 | M95: 2688.72 | N95: 15498.19 | O95: 12809.47 | P95: =O95*Summary!$B$29 -> 5926.5506 | Q95: =ROUND(P95,2) -> 5926.55
M96: =SUM(M87:M95) -> 24198.48 | N96: =SUM(N87:N95) -> 139483.71 | O96: =SUM(O87:O95) -> 115285.23 | P96: =SUM(P87:P95) -> 53338.956 | Q96: =SUM(Q87:Q95) -> 53338.95
A99: 129 | B99: MONTEVIDEO PUBLIC SCHOOL DISTRICT | C99: MN RIVER VALLEY EDUCATION DISTRICT | D99: 6018 | E99: 61 | F99: 31671.58 | G99: 9218.24 | H99: 0 | I99: 0 | J99: 0 | K99: 8620.89 | L99: 0 | M99: 22453.34 | N99: 40292.47 | O99: 17839.13 | P99: =O99*Summary!$B$29 -> 8253.6207 | Q99: =ROUND(P99,2) -> 8253.62
A100: 378 | B100: DAWSON-BOYD PUBLIC SCHOOL DISTRICT | C100: MN RIVER VALLEY EDUCATION DISTRICT | D100: 6018 | E100: 61 | F100: 28323.58 | G100: 8213.84 | H100: 0 | I100: 0 | J100: 0 | K100: 8620.89 | L100: 0 | M100: 20109.74 | N100: 36944.47 | O100: 16834.73 | P100: =O100*Summary!$B$29 -> 7788.9155 | Q100: =ROUND(P100,2) -> 7788.92
A101: 777 | B101: BENSON PUBLIC SCHOOL DISTRICT | C101: MN RIVER VALLEY EDUCATION DISTRICT | D101: 6018 | E101: 61 | F101: 28323.58 | G101: 8213.84 | H101: 0 | I101: 0 | J101: 0 | K101: 8620.89 | L101: 0 | M101: 20109.74 | N101: 36944.47 | O101: 16834.73 | P101: =O101*Summary!$B$29 -> 7788.9155 | Q101: =ROUND(P101,2) -> 7788.92
A102: 2167 | B102: LAKEVIEW SCHOOL DISTRICT | C102: MN RIVER VALLEY EDUCATION DISTRICT | D102: 6018 | E102: 61 | F102: 28323.58 | G102: 8213.84 | H102: 0 | I102: 0 | J102: 0 | K102: 8620.89 | L102: 0 | M102: 20109.74 | N102: 36944.47 | O102: 16834.73 | P102: =O102*Summary!$B$29 -> 7788.9155 | Q102: =ROUND(P102,2) -> 7788.92
A103: 2190 | B103: YELLOW MEDICINE EAST | C103: MN RIVER VALLEY EDUCATION DISTRICT | D103: 6018 | E103: 61 | F103: 28323.58 | G103: 8213.84 | H103: 0 | I103: 0 | J103: 0 | K103: 8620.89 | L103: 0 | M103: 20109.74 | N103: 36944.47 | O103: 16834.73 | P103: =O103*Summary!$B$29 -> 7788.9155 | Q103: =ROUND(P103,2) -> 7788.92
A104: 2853 | B104: LAC QUI PARLE VALLEY SCHOOL DIST. | C104: MN RIVER VALLEY EDUCATION DISTRICT | D104: 6018 | E104: 61 | F104: 30075.58 | G104: 8924.24 | H104: 0 | I104: 0 | J104: 0 | K104: 8620.89 | L104: 0 | M104: 21151.34 | N104: 38696.47 | O104: 17545.13 | P104: =O104*Summary!$B$29 -> 8117.5959 | Q104: =ROUND(P104,2) -> 8117.6
A105: 2903 | B105: ORTONVILLE PUBLIC SCHOOLS | C105: MN RIVER VALLEY EDUCATION DISTRICT | D105: 6018 | E105: 61 | F105: 28323.58 | G105: 8213.84 | H105: 0 | I105: 0 | J105: 0 | K105: 8620.89 | L105: 0 | M105: 20109.74 | N105: 36944.47 | O105: 16834.73 | P105: =O105*Summary!$B$29 -> 7788.9155 | Q105: =ROUND(P105,2) -> 7788.92
M106: =SUM(M99:M105) -> 144153.38 | N106: =SUM(N99:N105) -> 263711.29 | O106: =SUM(O99:O105) -> 119557.91 | P106: =SUM(P99:P105) -> 55315.794 | Q106: =SUM(Q99:Q105) -> 55315.82
A109: 23 | B109: Frazee-Vergas | C109: NW-Links | D109: 869 | E109: 82 | F109: 48956.837 | G109: 12239.209 | K109: 600 | M109: 36717.628 | N109: 49556.837 | O109: 12839.209 | P109: =O109*Summary!$B$29 -> 5940.3101 | Q109: =ROUND(P109,2) -> 5940.31
A110: 25 | B110: Pine Point | C110: NW-Links | D110: 869 | E110: 82 | F110: 14654.839 | G110: 1465.4839 | K110: 600 | M110: 13189.355 | N110: 15254.839 | O110: 2065.4839 | P110: =O110*Summary!$B$29 -> 955.63634 | Q110: =ROUND(P110,2) -> 955.64
A111: 32 | B111: Blackduck | C111: NW-Links | D111: 869 | E111: 82 | F111: 38814.303 | G111: 9703.5757 | K111: 1200 | M111: 29110.727 | N111: 40014.303 | O111: 10903.576 | P111: =O111*Summary!$B$29 -> 5044.7515 | Q111: =ROUND(P111,2) -> 5044.75
A112: 36 | B112: Kelliher | C112: NW-Links | D112: 869 | E112: 82 | F112: 27443.744 | G112: 3823.8344 | K112: 1200 | M112: 23619.91 | N112: 28643.744 | O112: 5023.8344 | P112: =O112*Summary!$B$29 -> 2324.3748 | Q112: =ROUND(P112,2) -> 2324.37
A113: 38 | B113: Red Lake | C113: NW-Links | D113: 869 | E113: 82 | F113: 77998.312 | G113: 8273.5112 | K113: 600 | M113: 69724.801 | N113: 78598.312 | O113: 8873.5112 | P113: =O113*Summary!$B$29 -> 4105.5027 | Q113: =ROUND(P113,2) -> 4105.5
A114: 113 | B114: Walker-Hackensack-Akeley | C114: NW-Links | D114: 869 | E114: 82 | F114: 37980.876 | G114: 11394.263 | K114: 1200 | M114: 26586.613 | N114: 39180.876 | O114: 12594.263 | P114: =O114*Summary!$B$29 -> 5826.9808 | Q114: =ROUND(P114,2) -> 5826.98
A115: 146 | B115: Barnesville | C115: NW-Links | D115: 869 | E115: 82 | F115: 25955.239 | G115: 14015.829 | K115: 600 | M115: 11939.41 | N115: 26555.239 | O115: 14615.829 | P115: =O115*Summary!$B$29 -> 6762.2978 | Q115: =ROUND(P115,2) -> 6762.3
A116: 150 | B116: Hawley | C116: NW-Links | D116: 869 | E116: 82 | F116: 34889.465 | G116: 21282.574 | K116: 600 | M116: 13606.891 | N116: 35489.465 | O116: 21882.574 | P116: =O116*Summary!$B$29 -> 10124.399 | Q116: =ROUND(P116,2) -> 10124.4
A117: 152 | B117: Moorhead | C117: NW-Links | D117: 869 | E117: 82 | F117: 32738.942 | G117: 15533.713 | K117: 1200 | M117: 17205.229 | N117: 33938.942 | O117: 16733.713 | P117: =O117*Summary!$B$29 -> 7742.1782 | Q117: =ROUND(P117,2) -> 7742.18
...
