Workbook

Sheet Structure
A2: Uniform
A3: Other

Sheet Main
A2: CWSRF
A3: CWSRF-GPR
A4: CWSRF-PF
A5: STAG
A6: SRL
A7: SEL

Sheet Type
A2: Loan
A3: Principal Forgiveness
A4: Grant
A5: Cash

Sheet Funding
A2: CWSRF
A3: STAG
A4: SRL
A5: SEL
A6: Bonds
A7: Bank Loans
A8: CWMTF Grant
A9: NCRC Grant
A10: USDA Grant
A11: USDA Loan
A12: Local Funds
A13: Other

Sheet Input
A2: Enter information into the gray areas.
A4: Project Name:
A5: LGU Name:
A6: Preferred Alternative Name:

Sheet LGU Condition
A1: Table 7.1. Local Government Unit Financial Condition
A2: =Input!B4 -> 0
A3: =Input!B6 -> 0
A4: Provide revenues generated from the most recent complete fiscal year (e.g., FY 2010-2011). Water and sewer expenses should not include depreciation. Existing debt should be debt paid in the previous fiscal year only.
A5: Operating Ratio
A6: Water and Sewer Revenue:
A7: Water and Sewer Expenses:
A8: Existing Debt:
A9: Operating Ratio: | C9: =$C$6/($C$7+$C$8) -> #DIV/0!
A10: Utility Bill as Percent of Median Household Income
A11: Use the pulldown menu to select the type of rate structure used for water and sewer. If using a rate structure other than uniform, then there is no need to complete the base charge (charge and volume) or volumetric charge.
B12: Sewer Rate Structure | C12: Water Rate Structure
A13: Rate Structure:
A14: Base Charge:
A15: Thousands of Gallons in Base Charge:
A16: Volumetric Charge per 1,000 gallons:
A17: Monthly Bill for 5,000 gallons: | B17: =IF($B$13="Uniform", ($B$14+($B$16*(5-$B$15))), ($B$16*5)) -> 0 | C17: =IF($C$13="Uniform", ($C$14+($C$16*(5-$C$15))), ($C$16*5)) -> 0
A18: Combined Monthly Water and Sewer Bill for 5,000 gallons: | B18: =B17+C17 -> 0
A19: Median Houshold Income:
A20: Monthly Median Household Income for LGU: | B20: =B19/12 -> 0
A21: Bill as % of Median Household Income: | B21: =IF($B$13="Uniform", $B$17/$B$20, $B$17/$B$20) -> #DIV/0! | C21: =IF($C$13="Uniform", $C$17/$B$20, $C$17/$B$20) -> #DIV/0!
A22: Overall Bill as % of Median Household Income: | B22: =$B18/$B20 -> #DIV/0!
A23: Additional Information if needed (see Section 2.2.7.1, Step 1 of the guidance).

Sheet Loan Repayment Input
A1: Table 7.2. Funding Distribution
A2: =Input!B4 -> 0
A3: =Input!B5 -> 0
A4: =Input!B6 -> 0
A5: Enter data into the gray areas. Where applicable, use the pulldown menus as shown by the arrows.
B6: Funding Sourcea | C6: Amount | D6: Funding Type | E6: Interest Rate (if applicable) | F6: Repayment Period (if applicable)
A7: Main IFS Fundingb:
A8: Funding 1:
A9: Funding 2:
A10: Funding 3:
A11: Funding 4:
A12: Funding 5:
B13: Closing Fee: | C13: =IF($B$7="CWSRF", (0.02*$C$7), (IF($B$7="CWSRF-PF", (0.02*$C$7), (IF($B$7="CWSRF-GPR", (0.02*$C$7), (IF($B$7="SRL", (0.025*$C$7), (IF($B$7="SEL", (0.025*$C$7), 0)))))))))+(IF($B$8="CWSRF", (0.02*$C$8), (IF($B$8="SRL", (0.025*$C$8), (IF($B$8="SEL", (0.025*$C$8), 0))))))+(IF($B$9="CWSRF", (0.02*$C$9), (IF($B$9="SRL", (0.025*$C$9), (IF($B$9="SEL", (0.025*$C$9), 0))))))+(IF($B$10="CWSRF", (0.02*$C$10), (IF($B$10="SRL", (0.025*$C$10), (IF($B$10="SEL", (0.025*$C$10), 0))))))+(IF($B$11="CWSRF", (0.02*$C$11), (IF($B$11="SRL", (0.025*$C$11), (IF($B$11="SEL", (0.025*$C$11),0))))))+(IF($B$12="CWSRF", (0.02*$C$12), (IF($B$12="SRL", (0.025*$C$12), (IF($B$12="SEL", (0.025*$C$12), 0)))))) -> 0 | D13: If Other, list:
A14: Total Funded Amount (minus applicable closing fee): | C14: =SUM(C7:C12) -> 0
B15: Total Project Cost (with closing fee): | C15: =SUM(C7:C13) -> 0
A16: aFor STAG grants, EPA charges a 3% administrative fee. Enter the net STAG grant (total grant - 3% administrative fee).
A17: bIf principal forgiveness is used, place the principal forgiveness portion of the loan in Funding 1.

Sheet Loan Repayment Output
A1: Table 7.3. Year 1 Interest and Repayment
A2: =Input!B4 -> 0
A3: =Input!B5 -> 0
A4: =Input!B6 -> 0
B5: Funding Source | C5: Total Funding Amount | D5: Year 1 Principal Payment | E5: Year 1 Interest Payment - Current Interest Rate | F5: Year 1 Interest Payment - Worst-Case Interest Rate | G5: Year 1 Total Payment - Current Interest Rate | H5: Year 1 Total Payment - Worst Case Interest Rate
A6: Main IFS Funding : | B6: =IF('Loan Repayment Input'!B7<>"", 'Loan Repayment Input'!$B7, "") | C6: =IF($B6<>"", 'Loan Repayment Input'!C7, "") | D6: =IF('Loan Repayment Input'!$D$7="Loan", ('Loan Repayment Input'!C7/'Loan Repayment Input'!F7), "") | E6: =IF('Loan Repayment Input'!$D$7="Loan", ('Loan Repayment Input'!$C$7*'Loan Repayment Input'!$E$7), "") | F6: =IF($B6<>"", (IF('Loan Repayment Input'!$D7="Loan", ($C6*0.04), "")), "") | G6: =IF($B6<>"", (IF('Loan Repayment Input'!D7="Loan", SUM(D6:E6), "")), "") | H6: =IF($B6<>"", (IF('Loan Repayment Input'!D7="Loan", (D6+F6), "")), "")
A7: Funding 1: | B7: =IF('Loan Repayment Input'!B8<>"", 'Loan Repayment Input'!$B8, "") | C7: =IF($B7<>"", 'Loan Repayment Input'!C8, "") | D7: =IF('Loan Repayment Input'!F8<>"", (IF('Loan Repayment Input'!$D8="Loan", ('Loan Repayment Input'!C8/'Loan Repayment Input'!F8), "")), "") | E7: =IF('Loan Repayment Input'!D8="Loan", ('Loan Repayment Input'!C8*'Loan Repayment Input'!E8), "") | F7: =IF($B7<>"", (IF('Loan Repayment Input'!$D8="Loan", (IF('Loan Repayment Input'!$B8="CWSRF", ($C7*0.04), (IF('Loan Repayment Input'!$B8="SRL", ($C7*0.04), (IF('Loan Repayment Input'!$B8="SEL", (0.04*$C7), "")))))), "")), "") | G7: =IF($B7<>"", (IF('Loan Repayment Input'!D8="Loan", SUM(D7:E7), "")), "") | H7: =IF($B7<>"", (IF('Loan Repayment Input'!$D8="Loan", (IF($B7="CWSRF", ($D7+$F7), (IF($B7="SRL", ($D7+$F7), (IF($B7="SEL", ($D7+$F7), ($D7+$E7))))))), "")), "")
A8: Funding 2: | B8: =IF('Loan Repayment Input'!B9<>"", 'Loan Repayment Input'!$B9, "") | C8: =IF($B8<>"", 'Loan Repayment Input'!C9, "") | D8: =IF('Loan Repayment Input'!F9<>"", (IF('Loan Repayment Input'!$D9="Loan", ('Loan Repayment Input'!C9/'Loan Repayment Input'!F9), "")), "") | E8: =IF('Loan Repayment Input'!D9="Loan", ('Loan Repayment Input'!C9*'Loan Repayment Input'!E9), "") | F8: =IF($B8<>"", (IF('Loan Repayment Input'!$D9="Loan", (IF('Loan Repayment Input'!$B9="CWSRF", ($C8*0.04), (IF('Loan Repayment Input'!$B9="SRL", ($C8*0.04), (IF('Loan Repayment Input'!$B9="SEL", (0.04*$C8), "")))))), "")), "") | G8: =IF($B8<>"", (IF('Loan Repayment Input'!D9="Loan", SUM(D8:E8), "")), "") | H8: =IF($B8<>"", (IF('Loan Repayment Input'!$D9="Loan", (IF($B8="CWSRF", ($D8+$F8), (IF($B8="SRL", ($D8+$F8), (IF($B8="SEL", ($D8+$F8), ($D8+$E8))))))), "")), "")
A9: Funding 3: | B9: =IF('Loan Repayment Input'!B10<>"", 'Loan Repayment Input'!$B10, "") | C9: =IF($B9<>"", 'Loan Repayment Input'!C10, "") | D9: =IF('Loan Repayment Input'!F10<>"", (IF('Loan Repayment Input'!$D10="Loan", ('Loan Repayment Input'!C10/'Loan Repayment Input'!F10), "")), "") | E9: =IF('Loan Repayment Input'!D10="Loan", ('Loan Repayment Input'!C10*'Loan Repayment Input'!E10), "") | F9: =IF($B9<>"", (IF('Loan Repayment Input'!$D10="Loan", (IF('Loan Repayment Input'!$B10="CWSRF", ($C9*0.04), (IF('Loan Repayment Input'!$B10="SRL", ($C9*0.04), (IF('Loan Repayment Input'!$B10="SEL", (0.04*$C9), "")))))), "")), "") | G9: =IF($B9<>"", (IF('Loan Repayment Input'!D10="Loan", SUM(D9:E9), "")), "") | H9: =IF($B9<>"", (IF('Loan Repayment Input'!$D10="Loan", (IF($B9="CWSRF", ($D9+$F9), (IF($B9="SRL", ($D9+$F9), (IF($B9="SEL", ($D9+$F9), ($D9+$E9))))))), "")), "")
A10: Funding 4: | B10: =IF('Loan Repayment Input'!B11<>"", 'Loan Repayment Input'!$B11, "") | C10: =IF($B10<>"", 'Loan Repayment Input'!C11, "") | D10: =IF('Loan Repayment Input'!F11<>"", (IF('Loan Repayment Input'!$D11="Loan", ('Loan Repayment Input'!C11/'Loan Repayment Input'!F11), "")), "") | E10: =IF('Loan Repayment Input'!D11="Loan", ('Loan Repayment Input'!C11*'Loan Repayment Input'!E11), "") | F10: =IF($B10<>"", (IF('Loan Repayment Input'!$D11="Loan", (IF('Loan Repayment Input'!$B11="CWSRF", ($C10*0.04), (IF('Loan Repayment Input'!$B11="SRL", ($C10*0.04), (IF('Loan Repayment Input'!$B11="SEL", (0.04*$C10), "")))))), "")), "") | G10: =IF($B10<>"", (IF('Loan Repayment Input'!D11="Loan", SUM(D10:E10), "")), "") | H10: =IF($B10<>"", (IF('Loan Repayment Input'!$D11="Loan", (IF($B10="CWSRF", ($D10+$F10), (IF($B10="SRL", ($D10+$F10), (IF($B10="SEL", ($D10+$F10), ($D10+$E10))))))), "")), "")
A11: Funding 5: | B11: =IF('Loan Repayment Input'!B12<>"", 'Loan Repayment Input'!$B12, "") | C11: =IF($B11<>"", 'Loan Repayment Input'!C12, "") | D11: =IF('Loan Repayment Input'!F12<>"", (IF('Loan Repayment Input'!$D12="Loan", ('Loan Repayment Input'!C12/'Loan Repayment Input'!F12), "")), "") | E11: =IF('Loan Repayment Input'!D12="Loan", ('Loan Repayment Input'!C12*'Loan Repayment Input'!E12), "") | F11: =IF($B11<>"", (IF('Loan Repayment Input'!$D12="Loan", (IF('Loan Repayment Input'!$B12="CWSRF", ($C11*0.04), (IF('Loan Repayment Input'!$B12="SRL", ($C11*0.04), (IF('Loan Repayment Input'!$B12="SEL", (0.04*$C11), "")))))), "")), "") | G11: =IF($B11<>"", (IF('Loan Repayment Input'!D12="Loan", SUM(D11:E11), "")), "") | H11: =IF($B11<>"", (IF('Loan Repayment Input'!$D12="Loan", (IF($B11="CWSRF", ($D11+$F11), (IF($B11="SRL", ($D11+$F11), (IF($B11="SEL", ($D11+$F11), ($D11+$E11))))))), "")), "")
A12: aWorst case is an interest rate of 4%. Applies to CWSRF, SRL, and SEL only. | F12: Total Payment @ Current Interest Rate: | G12: =(IF(G6<>"", $G$6, 0))+(IF($G$7<>"", $G$7, 0))+(IF($G$8<>"", $G$8, 0))+(IF($G$9<>"", $G$9, 0))+(IF($G$10<>"", $G$10, 0))+(IF($G$11<>"", $G$11, 0)) -> 0
F13: Total Payment @ Worst-Case Interest Rate: | H13: =IF($H$6<>"", $H$6, 0)+(IF($H7<>"", $H$7, 0))+(IF($H$8<>"", $H$8, ))+(IF($H$9<>"", $H$9, 0))+(IF($H$10<>"", $H$10, 0))+(IF($H$11<>"", $H$11, 0)) -> 0

Sheet User Rate Analysis
A1: Table 7.4. Cost per 5,000 Gallons to Finance Project
A2: =Input!B4 -> 0
A3: =Input!B5 -> 0
A4: =Input!B6 -> 0
A5: Select Customer Type for Financing Projectc | D5: Average Water Usage Per Month (gallons) | E5: Number of Connections | F5: Total Monthly Water Usage by Customer Type (gallons) | I5: Total Monthly Water Usage for Customer Base (gallons): | M5: =SUM(F6:F8) -> 0
A6: Residential | F6: =IF(W6 = TRUE, D6 * E6,"") | J6: # of 5000 Gallon Units to Finance Project: | M6: =M5/5000 -> 0 | V6: Residential Checkbox = | W6: FALSE
A7: Commercial | F7: =IF(Y7 = TRUE, D7 * E7,"") | J7: Year 1 O&M Expenses Due to Project: | X7: Commercial Checkbox = | Y7: FALSE
A8: Industrial | F8: =IF(Y8 = TRUE, D8 * E8,"") | X8: Industrial Checkbox = | Y8: FALSE
C9: Funding Source | D9: Year 1 Annual Repayment | E9: Year 1 Annual O&M Costs | F9: Total Year 1 Annual Costs @ Current Interest Rate | G9: Year 1 Annual Cost @ Worst-Case Interest Rate | H9: Year 1 Monthly Costs @ Current Interest Rate | I9: Year 1 Monthly Costs @ Worst-Case Interest Rate | J9: Monthly Cost/ 5,000 Gallons Due to Project @ Current Interest Rate (All Users ) | K9: Monthly Cost/5,000 Gallons Due to Project @ Worst-Case Interest Rate (All Users) | L9: Monthly Cost/5,000 Gallons Due to Project @ Current Interest Rate (Residential Users Only) | M9: Monthly Cost/5,000 Gallons Due to Project @ Worst-Case Interest Rate (Residential Users Only)
A10: IFS Main Funding Source: | C10: ='Loan Repayment Input'!B7 -> 0 | D10: ='Loan Repayment Output'!G6 | E10: =$M$7 -> 0 | F10: =IF($D$10<>"", ($D$10+$E$10), $E$10) -> 0 | G10: =IF($D$10<>"", ($E10+'Loan Repayment Output'!H6), $E$10) -> 0 | H10: =$F10/12 -> 0 | I10: =$G10/12 -> 0 | J10: =(H10 /$M$6) -> #DIV/0! | K10: =($I10/$M$6) -> #DIV/0! | L10: =($H10/($F$6/5000)) -> #VALUE! | M10: =($I10/($F$6/5000)) -> #VALUE!
B11: Funding Source 1: | C11: =IF('Loan Repayment Input'!B8<>"", 'Loan Repayment Input'!B8, "") | D11: =IF('Loan Repayment Output'!G7<>"", 'Loan Repayment Output'!G7, "") | F11: =IF(D11<>"", D11, "") | G11: =(IF($C11<>"", (IF('Loan Repayment Input'!$D8="Loan", (IF($C11="CWSRF", 'Loan Repayment Output'!$H7, (IF($C11="SRL", 'Loan Repayment Output'!$H7, (IF($C11="SEL", 'Loan Repayment Output'!$H7, $F11)))))), "")), "")) | H11: =IF($F11<>"", (F11/12), "") | I11: =IF($G11<>"", (G11/12), "") | J11: =IF(D11<>"", (H11/$M$6), "") | K11: =IF($I11<>"", ($I11/$M$6), "") | L11: =IF($H11<>"", ($H11/($F$6/5000)), "") | M11: =IF($I11<>"", ($I11/($F$6/5000)), "")
A12: Funding Source 2: | C12: =IF('Loan Repayment Input'!B9<>"", 'Loan Repayment Input'!B9, "") | D12: =IF('Loan Repayment Output'!G8<>"", 'Loan Repayment Output'!G8, "") | F12: =IF(D12<>"", D12, "") | G12: =(IF($C12<>"", (IF('Loan Repayment Input'!$D9="Loan", (IF($C12="CWSRF", 'Loan Repayment Output'!$H8, (IF($C12="SRL", 'Loan Repayment Output'!$H8, (IF($C12="SEL", 'Loan Repayment Output'!$H8, $F12)))))), "")), "")) | H12: =IF($F12<>"", (F12/12), "") | I12: =IF($G12<>"", (G12/12), "") | J12: =IF(D12<>"", (H12/$M$6), "") | K12: =IF($I12<>"", ($I12/$M$6), "") | L12: =IF($H12<>"", ($H12/($F$6/5000)), "") | M12: =IF($I12<>"", ($I12/($F$6/5000)), "")
A13: Funding Source 3: | C13: =IF('Loan Repayment Input'!B10<>"", 'Loan Repayment Input'!B10, "") | D13: =IF('Loan Repayment Output'!G9<>"", 'Loan Repayment Output'!G9, "") | F13: =IF(D13<>"", D13, "") | G13: =(IF($C13<>"", (IF('Loan Repayment Input'!$D10="Loan", (IF($C13="CWSRF", 'Loan Repayment Output'!$H9, (IF($C13="SRL", 'Loan Repayment Output'!$H9, (IF($C13="SEL", 'Loan Repayment Output'!$H9, $F13)))))), "")), "")) | H13: =IF($F13<>"", (F13/12), "") | I13: =IF($G13<>"", (G13/12), "") | J13: =IF(D13<>"", (H13/$M$6), "") | K13: =IF($I13<>"", ($I13/$M$6), "") | L13: =IF($H13<>"", ($H13/($F$6/5000)), "") | M13: =IF($I13<>"", ($I13/($F$6/5000)), "")
A14: Funding Source 4: | C14: =IF('Loan Repayment Input'!B11<>"", 'Loan Repayment Input'!B11, "") | D14: =IF('Loan Repayment Output'!G10<>"", 'Loan Repayment Output'!G10, "") | F14: =IF(D14<>"", D14, "") | G14: =(IF($C14<>"", (IF('Loan Repayment Input'!$D11="Loan", (IF($C14="CWSRF", 'Loan Repayment Output'!$H10, (IF($C14="SRL", 'Loan Repayment Output'!$H10, (IF($C14="SEL", 'Loan Repayment Output'!$H10, $F14)))))), "")), "")) | H14: =IF($F14<>"", (F14/12), "") | I14: =IF($G14<>"", (G14/12), "") | J14: =IF(D14<>"", (H14/$M$6), "") | K14: =IF($I14<>"", ($I14/$M$6), "") | L14: =IF($H14<>"", ($H14/($F$6/5000)), "") | M14: =IF($I14<>"", ($I14/($F$6/5000)), "")
A15: Funding Source 5: | C15: =IF('Loan Repayment Input'!B12<>"", 'Loan Repayment Input'!B12, "") | D15: =IF('Loan Repayment Output'!G11<>"", 'Loan Repayment Output'!G11, "") | F15: =IF(D15<>"", D15, "") | G15: =(IF($C15<>"", (IF('Loan Repayment Input'!$D12="Loan", (IF($C15="CWSRF", 'Loan Repayment Output'!$H11, (IF($C15="SRL", 'Loan Repayment Output'!$H11, (IF($C15="SEL", 'Loan Repayment Output'!$H11, $F15)))))), "")), "")) | H15: =IF($F15<>"", (F15/12), "") | I15: =IF($G15<>"", (G15/12), "") | J15: =IF(D15<>"", (H15/$M$6), "") | K15: =IF($I15<>"", ($I15/$M$6), "") | L15: =IF($H15<>"", ($H15/($F$6/5000)), "") | M15: =IF($I15<>"", ($I15/($F$6/5000)), "")
A16: Total Year 1 Annual Cost @ Current Interest Rate: | F16: =SUM(F10:F15) -> 0
A17: Total Year 1 Annual Cost @ Worst-Case Interest Rate | G17: =SUM(G10:G15) -> 0
A18: Total Year 1 Monthly Cost @ Current Interest Rate: | H18: =SUM(H10:H15) -> 0
A19: Total Year 1 Monthly Cost @ Worst-Case Interest Rate: | I19: =SUM(I10:I15) -> 0
A20: Total Monthly Cost to Treat 5,000 Gallons @ Current Interest Rate: | J20: =SUM(J10:J15) -> #DIV/0!
A21: Total Monthly Cost to Treat 5,000 Gallons @ Worst-Case Interest Rate (All Users): | K21: =SUM(K10:K15) -> #DIV/0!
A22: Total Monthly Cost to Treat 5,000 Gallons @ Current Interest Rate (Residential Users Only): | L22: =SUM(L10:L15) -> #VALUE!
A23: Total Monthly Cost to Treat 5,000 Gallons @ Worst-Case Interest Rate (Residential Users Only): | M23: =SUM(M10:M15) -> #VALUE!

Sheet User Rate Change Summary
A1: Table 7.5. User Rates Needed to Finance Project
A2: =Input!B4 -> 0
A3: =Input!B5 -> 0
A4: =Input!B6 -> 0
A5: Current Sewer Bill ($/5,000 gallons): | B5: ='LGU Condition'!$B$17 -> 0 | C5: Current Water Bill ($/5,000 gallons): | F5: ='LGU Condition'!$C$17 -> 0
B6: Funding Source | C6: User Rate Increase Due to Project @ Current Interest Rate (All Users) | D6: User Rate Increase Due to Project @ Worst-Case Interest Rate (All Users) | E6: User Rate Increase Due to Project @ Current Rate (Residential Users Only) | F6: User Rate Increase Due to Project @ Worst-Case Interest Rate (Residential Users Only)
A7: Main IFS Funding Source: | B7: =IF('Loan Repayment Input'!$B7<>"", 'Loan Repayment Input'!B7, "") | C7: ='User Rate Analysis'!J10 -> #DIV/0! | D7: ='User Rate Analysis'!K10 -> #DIV/0! | E7: ='User Rate Analysis'!L10 -> #VALUE! | F7: ='User Rate Analysis'!M10 -> #VALUE!
A8: Funding Source 1: | B8: =IF('Loan Repayment Input'!$B8<>"", 'Loan Repayment Input'!B8, "") | C8: ='User Rate Analysis'!J11 | D8: ='User Rate Analysis'!K11 | E8: ='User Rate Analysis'!L11 | F8: ='User Rate Analysis'!M11
A9: Funding Source 2: | B9: =IF('Loan Repayment Input'!$B9<>"", 'Loan Repayment Input'!B9, "") | C9: ='User Rate Analysis'!J12 | D9: ='User Rate Analysis'!K12 | E9: ='User Rate Analysis'!L12 | F9: ='User Rate Analysis'!M12
A10: Funding Source 3: | B10: =IF('Loan Repayment Input'!$B10<>"", 'Loan Repayment Input'!B10, "") | C10: ='User Rate Analysis'!J13 | D10: ='User Rate Analysis'!K13 | E10: ='User Rate Analysis'!L13 | F10: ='User Rate Analysis'!M13
A11: Funding Source 4: | B11: =IF('Loan Repayment Input'!$B11<>"", 'Loan Repayment Input'!B11, "") | C11: ='User Rate Analysis'!J14 | D11: ='User Rate Analysis'!K14 | E11: ='User Rate Analysis'!L14 | F11: ='User Rate Analysis'!M14
A12: Funding Source 5: | B12: =IF('Loan Repayment Input'!$B12<>"", 'Loan Repayment Input'!B12, "") | C12: ='User Rate Analysis'!J15 | D12: ='User Rate Analysis'!K15 | E12: ='User Rate Analysis'!L15 | F12: ='User Rate Analysis'!M15
B13: Total User Rate Increase Due to IFS Loan(s) ($/5,000 gal.): | C13: =IF('User Rate Analysis'!$J$20<0, 0, ($C7+(IF($B8="CWSRF", C$8, (IF($B8="SRL", C$8, (IF($B8="SEL", C$8, 0))))))+(IF($B9="CWSRF", C$9, (IF($B9="SRL", C$9, (IF($B9="SEL", C$9, 0))))))+(IF($B10="CWSRF", C$10, (IF($B10="SRL", C$10, (IF($B10="SEL", C$10, 0))))))+(IF($B11="CWSRF", C$11, (IF($B11="SRL", C$11, (IF($B11="SEL", C$11, ))))))+(IF($B12="CWSRF", C$12, (IF($B12="SRL", C$12, (IF($B12="SEL", C$12, 0)))))))) -> #DIV/0! | D13: =IF('User Rate Analysis'!$J$20<0, 0, ($D7+(IF($B8="CWSRF", D$8, (IF($B8="SRL", D$8, (IF($B8="SEL", D$8, 0))))))+(IF($B9="CWSRF", D$9, (IF($B9="SRL", D$9, (IF($B9="SEL", D$9, 0))))))+(IF($B10="CWSRF", D$10, (IF($B10="SRL", D$10, (IF($B10="SEL", D$10, 0))))))+(IF($B11="CWSRF", D$11, (IF($B11="SRL", D$11, (IF($B11="SEL", D$11, ))))))+(IF($B12="CWSRF", D$12, (IF($B12="SRL", D$12, (IF($B12="SEL", D$12, 0)))))))) -> #DIV/0! | E13: =IF('User Rate Analysis'!$J$20<0, 0, ($E7+(IF($B8="CWSRF", E$8, (IF($B8="SRL", E$8, (IF($B8="SEL", E$8, 0))))))+(IF($B9="CWSRF", E$9, (IF($B9="SRL", E$9, (IF($B9="SEL", E$9, 0))))))+(IF($B10="CWSRF", E$10, (IF($B10="SRL", E$10, (IF($B10="SEL", E$10, 0))))))+(IF($B11="CWSRF", E$11, (IF($B11="SRL", E$11, (IF($B11="SEL", E$11, ))))))+(IF($B12="CWSRF", E$12, (IF($B12="SRL", E$12, (IF($B12="SEL", E$12, 0)))))))) -> #DIV/0! | F13: =IF('User Rate Analysis'!$J$20<0, 0, ($F7+(IF($B8="CWSRF", F$8, (IF($B8="SRL", F$8, (IF($B8="SEL", F$8, 0))))))+(IF($B9="CWSRF", F$9, (IF($B9="SRL", F$9, (IF($B9="SEL", F$9, 0))))))+(IF($B10="CWSRF", F$10, (IF($B10="SRL", F$10, (IF($B10="SEL", F$10, 0))))))+(IF($B11="CWSRF", F$11, (IF($B11="SRL", F$11, (IF($B11="SEL", F$11, ))))))+(IF($B12="CWSRF", F$12, (IF($B12="SRL", F$12, (IF($B12="SEL", F$12, 0)))))))) -> #DIV/0!
B14: Total Increase Due to All Loans(s) ($/5,000 gal.): | C14: =IF('User Rate Analysis'!$J$20<0, 0, (((IF($C7<>"", C$7, 0))+ (IF($C8<>"", C$8, 0))+(IF($C9<>"", C$9, 0))+(IF($C10<>"", C$10, 0))+(IF($C11<>"", C$11, 0))+(IF($C12<>"", C$12, ))))) -> #DIV/0! | D14: =IF('User Rate Analysis'!$J$20<0, 0, (((IF($C7<>"", D$7, 0))+ (IF($C8<>"", D$8, 0))+(IF($C9<>"", D$9, 0))+(IF($C10<>"", D$10, 0))+(IF($C11<>"", D$11, 0))+(IF($C12<>"", D$12, ))))) -> #DIV/0! | E14: =IF('User Rate Analysis'!$J$20<0, 0, (((IF($C7<>"", E$7, 0))+ (IF($C8<>"", E$8, 0))+(IF($C9<>"", E$9, 0))+(IF($C10<>"", E$10, 0))+(IF($C11<>"", E$11, 0))+(IF($C12<>"", E$12, ))))) -> #DIV/0! | F14: =IF('User Rate Analysis'!$J$20<0, 0, (((IF($C7<>"", F$7, 0))+ (IF($C8<>"", F$8, 0))+(IF($C9<>"", F$9, 0))+(IF($C10<>"", F$10, 0))+(IF($C11<>"", F$11, 0))+(IF($C12<>"", F$12, ))))) -> #DIV/0!
B15: New Sewer Bill Due to IFS Loan(s) ($/5,000 gal.): | C15: =$B$5+C$13 -> #DIV/0! | D15: =$B$5+D$13 -> #DIV/0! | E15: =$B$5+E$13 -> #DIV/0! | F15: =$B$5+F$13 -> #DIV/0!
A16: New Sewer Bill Due to All Loan(s) ($/5,000 gal.): | C16: =$B$5+C$14 -> #DIV/0! | D16: =$B$5+D$14 -> #DIV/0! | E16: =$B$5+E$14 -> #DIV/0! | F16: =$B$5+F$14 -> #DIV/0!
B17: Percent Change in Sewer Bill Due to IFS Loan(s): | C17: =(C$15-$B$5)/$B$5 -> #DIV/0! | D17: =(D$15-$B$5)/$B$5 -> #DIV/0! | E17: =(E$15-$B$5)/$B$5 -> #DIV/0! | F17: =(F$15-$B$5)/$B$5 -> #DIV/0!
A18: Percent Change in Sewer Bill Due to All Loan(s): | C18: =(C$16-$B$5)/($B$5) -> #DIV/0! | D18: =(D$16-$B$5)/($B$5) -> #DIV/0! | E18: =(E$16-$B$5)/($B$5) -> #DIV/0! | F18: =(F$16-$B$5)/($B$5) -> #DIV/0!
B19: New Sewer & Water Bills Due to IFS Loan(s) ($/5,000 gal.): | C19: =$B$5+$F$5+C$13 -> #DIV/0! | D19: =$B$5+$F$5+D$13 -> #DIV/0! | E19: =$B$5+$F$5+E$13 -> #DIV/0! | F19: =$B$5+$F$5+F$13 -> #DIV/0!
B20: New Water & Sewer Bills Due to All Loan(s) ($/5,000 gal.): | C20: =C$14+$B$5+$F$5 -> #DIV/0! | D20: =D$14+$B$5+$F$5 -> #DIV/0! | E20: =E$14+$B$5+$F$5 -> #DIV/0! | F20: =F$14+$B$5+$F$5 -> #DIV/0!
B21: Percent Change in Sewer & Water Bills Due to IFS Loan(s): | C21: =($C19-($B$5+$F$5))/($B$5+$F$5) -> #DIV/0! | D21: =($C19-($B$5+$F$5))/($B$5+$F$5) -> #DIV/0! | E21: =($C19-($B$5+$F$5))/($B$5+$F$5) -> #DIV/0! | F21: =($C19-($B$5+$F$5))/($B$5+$F$5) -> #DIV/0!
B22: Percent Change in Sewer & Water Bills Due to All Loan(s): | C22: =(C$20-($B$5+$F$5))/($B$5+$F$5) -> #DIV/0! | D22: =(D$20-($B$5+$F$5))/($B$5+$F$5) -> #DIV/0! | E22: =(E$20-($B$5+$F$5))/($B$5+$F$5) -> #DIV/0! | F22: =(F$20-($B$5+$F$5))/($B$5+$F$5) -> #DIV/0!
A23: aChange in User Fee to finance IFS Loan.
A24: bChange in User Fee to finance ALL funding sources.

Sheet Impact to Bills
A1: Table 7.6. Impact to Bills Due to Project
A2: =Input!B4 -> 0
A3: =Input!B5 -> 0
A4: =Input!B6 -> 0
B5: Sewer Bill as % Monthly MHI: | C5: ='LGU Condition'!$B$21 -> #DIV/0! | E5: Water Bill as % Monthly MHI: | F5: ='LGU Condition'!$C$21 -> #DIV/0!
B6: Current Sewer Bill ($/5,000 gal.): | C6: ='LGU Condition'!B17 -> 0 | E6: Current Water Bill ($/5,000 gal.): | F6: ='LGU Condition'!C17 -> 0
B7: Current Sewer & Water Bill ($/5,000 gal.): | C7: ='LGU Condition'!B18 -> 0 | E7: Sewer & Water Bill as % Monthly MHI: | F7: ='LGU Condition'!$B$22 -> #DIV/0!
B8: Monthly MHI for LGU: | C8: ='LGU Condition'!B20 -> 0
C9: Sewer Bill Due to IFS Loans | D9: Sewer Bill Due to All Loans | E9: Water & Sewer Bills Due to IFS Loans | F9: Water & Sewer Bills Due to All Loans
A10: Current Interest Rate (All Users) | B10: New | C10: ='User Rate Change Summary'!C15 -> #DIV/0! | D10: ='User Rate Change Summary'!C16 -> #DIV/0! | E10: ='User Rate Change Summary'!C19 -> #DIV/0! | F10: ='User Rate Change Summary'!C20 -> #DIV/0!
B11: New %MHI Due to Project | C11: =C$10/$C$8 -> #DIV/0! | D11: =D$10/$C$8 -> #DIV/0! | E11: =E$10/$C$8 -> #DIV/0! | F11: =F$10/$C$8 -> #DIV/0!
B12: Potentially Significant Impact? | C12: =IF(C$11>=0.02, "Yes", "No") -> #DIV/0! | D12: =IF(D$11>=0.02, "Yes", "No") -> #DIV/0! | E12: =IF(E$11>=0.04, "Yes", "No") -> #DIV/0! | F12: =IF(F$11>=0.04, "Yes", "No") -> #DIV/0!
A13: Current Interest Rate (Residential Users Only) | B13: New | C13: ='User Rate Change Summary'!D15 -> #DIV/0! | D13: ='User Rate Change Summary'!D16 -> #DIV/0! | E13: ='User Rate Change Summary'!D19 -> #DIV/0! | F13: ='User Rate Change Summary'!D20 -> #DIV/0!
B14: New %MHI Due to Project | C14: =C$13/$C$8 -> #DIV/0! | D14: =D$13/$C$8 -> #DIV/0! | E14: =E$13/$C$8 -> #DIV/0! | F14: =F$13/$C$8 -> #DIV/0!
B15: Potentially Significant Impact? | C15: =IF(C$14>=0.02, "Yes", "No") -> #DIV/0! | D15: =IF(D$14>=0.02, "Yes", "No") -> #DIV/0! | E15: =IF(E$14>=0.04, "Yes", "No") -> #DIV/0! | F15: =IF(F$14>=0.04, "Yes", "No") -> #DIV/0!
A16: Worst-Case Interest Rate (All Users) | B16: New | C16: ='User Rate Change Summary'!E15 -> #DIV/0! | D16: ='User Rate Change Summary'!E16 -> #DIV/0! | E16: ='User Rate Change Summary'!E19 -> #DIV/0! | F16: ='User Rate Change Summary'!E20 -> #DIV/0!
B17: New %MHI Due to Project | C17: =C$16/$C$8 -> #DIV/0! | D17: =D$16/$C$8 -> #DIV/0! | E17: =E$16/$C$8 -> #DIV/0! | F17: =F$16/$C$8 -> #DIV/0!
B18: Potentially Significant Impact? | C18: =IF(C$17>=0.02, "Yes", "No") -> #DIV/0! | D18: =IF(D$17>=0.02, "Yes", "No") -> #DIV/0! | E18: =IF(E$17>=0.04, "Yes", "No") -> #DIV/0! | F18: =IF(F$17>=0.04, "Yes", "No") -> #DIV/0!
A19: Worst-Case Interest Rate (Residential Users Only) | B19: New | C19: ='User Rate Change Summary'!F15 -> #DIV/0! | D19: ='User Rate Change Summary'!F16 -> #DIV/0! | E19: ='User Rate Change Summary'!F19 -> #DIV/0! | F19: ='User Rate Change Summary'!F20 -> #DIV/0!
B20: New %MHI Due to Project | C20: =C$19/$C$8 -> #DIV/0! | D20: =D$19/$C$8 -> #DIV/0! | E20: =E$19/$C$8 -> #DIV/0! | F20: =F$19/$C$8 -> #DIV/0!
B21: Potentially Significant Impact? | C21: =IF(C$20>=0.02, "Yes", "No") -> #DIV/0! | D21: =IF(D$20>=0.02, "Yes", "No") -> #DIV/0! | E21: =IF(E$20>=0.04, "Yes", "No") -> #DIV/0! | F21: =IF(F$20>=0.04, "Yes", "No") -> #DIV/0!
A22: If the user fee increases will be significantly increased, discuss why the LGU has determined to proceed with the project.
