Workbook

Sheet Inputs
B4: Iowa and Nebraska Dairy Budgets
D7: August 2010
D8: Milk Components & Prices
D9: BF% | E9: 3.55
D10: Protein% | E10: 3.05
D11: Other solids% | E11: 5.73
D12: scc | E12: 265
D14: BF price | E14: 2.4044
D15: Protein price | E15: 2.3057
D16: Other solids price | E16: 0.1673
D17: PPD | E17: 0.75
D18: SCC adjustment | E18: 0.00085
D20: MILC | E20: 0
D23: Feed prices
D25: Corn | E25: 4.35
D26: Soybean meal | E26: 333
D27: Cottonseed | E27: 290
D28: Animal fat | E28: 0.3
D29: Hay | E29: 132.5
D31: Cull Cow Price | E31: 57
B34: Notes on budget assumptions and prices
B35: (a) Cull cow income represents sales of dairy stock, a capital asset. This income is included to calculate production in terms of milk equivalents. Price fron most recent Iowa weekly slaughter report http://www.ams.usda.gov/mnreports/nw_ls785.txt
B36: (b) A detailed explanation of the feed rations utilized is available upon request from the authors.
B37: (c) Facilities budgeted here represent those needed for a 250 cow herd housed in a freestall and milked in a parlor.
B38: (d) Milk equivalents are calculated by computing the adjusted gross receipts (gross receipts - death loss) then dividing by the total price per cwt. of milk.
B39: (e) The break even milk price is the gross Grade A price per cwt. required in the receipts section, so the budget will cover total costs and labor.
B40: (f) Corn price obtained from Monthly Grain report Omaha/Council Bluffs http://www.ams.usda.gov/mnreports/wh_gr110.txt. Fat & Soybean Meal prices are obtained fron the most recent Minneapolis Weekly Feedstuffs report, http://www.ams.usda.gov/mnreports/ms_gr852.txt
B41: Cottonseed price from most recent Feedstuffs magazine. Hay price obrained from NE/IA Weekly hay report, http://www.ams.usda.gov/mnreports/sc_gr310.txt, Premium quality alfalfa large squares.
B42: (g) Other costs revised August 2009
B43: Prepared by: Paul W. Brown, Extension Farm Management Specialist, Dale Thoreson, Extension Dairy Specialist,
B44: and Lee Kilmer, Extension Dairy Specialist, Iowa State University.
B45: Revised by: Robert Tigner, Extension Educator, UN-L, June 2010

Sheet Freestall
E1: Midwest Dairy Cow Annual Budget- Freestall | H1: =Inputs!D7 -> August 2010
E2: Large Breed Dairy Cow Including Replacements Producing
E3: 20,000 lbs. & 24,000 lbs. of Grade A Milk
A4: I. RECEIPTS | F4: $$ Value | K4: $$ Value
A5: 1. Components: | B5: 200 | C5: cwts. | G5: 240 | H5: cwts.
A6: a. Butterfat | B6: =Inputs!E9*B5 -> 710 | C6: lbs. | D6: =Inputs!E14 -> 2.4044 | E6: $/lb. | F6: =B6*D6 -> 1707.124 | G6: =Inputs!E9*G5 -> 852 | H6: lbs. | I6: =D6 -> 2.4044 | J6: $/lb. | K6: =G6*I6 -> 2048.5488
A7: b. Protein | B7: =Inputs!E10*B5 -> 610 | C7: lbs. | D7: =Inputs!E15 -> 2.3057 | E7: $/lb. | F7: =B7*D7 -> 1406.477 | G7: =Inputs!E10*G5 -> 732 | H7: lbs. | I7: =D7 -> 2.3057 | J7: $/lb. | K7: =G7*I7 -> 1687.7724
A8: c. Other Solids | B8: =Inputs!E11*B5 -> 1146 | C8: lbs. | D8: =Inputs!E16 -> 0.1673 | E8: $/lb. | F8: =B8*D8 -> 191.7258 | G8: =Inputs!E11*G5 -> 1375.2 | H8: lbs. | I8: =D8 -> 0.1673 | J8: $/lb. | K8: =G8*I8 -> 230.07096
A9: d. Producer Price Differential | D9: =Inputs!E17 -> 0.75 | E9: $/cwt. | F9: =B5*D9 -> 150 | I9: =D9 -> 0.75 | J9: $/cwt. | K9: =G5*I9 -> 180
A10: e. Quality | B10: =Inputs!E12*1000 -> 265000 | C10: SCC | D10: =Inputs!E18 -> 0.00085 | E10: $/thousand | F10: =(B10/1000)*D10 -> 0.22525 | G10: =Inputs!E12*1000 -> 265000 | H10: SCC | I10: =D10 -> 0.00085 | J10: $/thousand | K10: =(G10/1000)*I10 -> 0.22525
A11: f. Protein Premium | D11: 0 | E11: $/lb. | F11: =B7*D11 -> 0 | I11: =D11 -> 0 | J11: $/lb. | K11: =G7*I11 -> 0
A12: g. Volume | D12: 0.185 | E12: $/cwt. | F12: =B5*D12 -> 37 | I12: =D12 -> 0.185 | J12: $/cwt. | K12: =G5*I12 -> 44.4
A13: 2. Capital Payout | D13: 0 | E13: $/cwt. | F13: =B5*D13 -> 0 | I13: =D13 -> 0 | J13: $/cwt. | K13: =G5*I13 -> 0
A14: 3. Cull/cow (a) | B14: 0.36 | C14: head | D14: =B14*Inputs!E31*14 -> 287.28 | E14: per hd. | F14: =B14*D14 -> 103.4208 | G14: 0.39 | H14: head | I14: =D14 -> 287.28 | J14: per hd. | K14: =G14*I14 -> 112.0392
A15: 4. Dairy calf | B15: 0.51 | C15: head | D15: 150 | E15: per hd. | F15: =B15*D15 -> 76.5 | G15: 0.52 | H15: head | I15: =D15 -> 150 | J15: per hd. | K15: =G15*I15 -> 78
A16: 5. Replacement heifer calf | B16: 0.18 | C16: head | D16: 450 | E16: per hd. | F16: =B16*D16 -> 81 | G16: 0.21 | H16: head | I16: =D16 -> 450 | J16: per hd. | K16: =G16*I16 -> 94.5
A17: 6. MILC payment | D17: =Inputs!E20 -> 0 | E17: $/cwt. | F17: =B5*D17 -> 0 | I17: =D17 -> 0 | K17: =G5*I17 -> 0
A18: GROSS RECEIPTS | F18: =SUM(F6:F17) -> 3753.4728 | K18: =SUM(K6:K17) -> 4475.5566
A20: II. VARIABLE COSTS
A21: A. FEED COSTS (b) | B21: Price/Unit | D21: Amount | F21: $$ Value | H21: Amount | K21: $$ Value
A22: 1. Corn equivalents | B22: =Inputs!E25 -> 4.35 | C22: per bu. | D22: 104.38 | E22: bu. | F22: =B22*D22 -> 454.053 | H22: 112.91 | I22: bu. | K22: =B22*H22 -> 491.1585
A23: 2. Corn Silage | B23: =Inputs!E25*10 -> 43.5 | C23: per ton | D23: 8.04 | E23: tons | F23: =B23*D23 -> 349.74 | H23: 7.99 | I23: tons | K23: =B23*H23 -> 347.565
A24: 3. Hay equivalents | B24: =Inputs!E29 -> 132.5 | C24: per ton | D24: 6.09 | E24: tons | F24: =B24*D24 -> 806.925 | H24: 6.03 | I24: tons | K24: =H24*B24 -> 798.975
A25: 4. Salts and minerals | B25: 0.14 | C25: per lb. | D25: 241.97 | E25: lbs. | F25: =B25*D25 -> 33.8758 | H25: 323.23 | I25: lbs. | K25: =H25*B25 -> 45.2522
A26: 5. Protein supplement | B26: =Inputs!E26/2000 -> 0.1665 | C26: per lb. | D26: 1284.83 | E26: lbs. | F26: =B26*D26 -> 213.92419 | H26: 1855.08 | I26: lbs. | K26: =B26*H26 -> 308.87082
A27: 6. Whole (linted) cottonseed | B27: =Inputs!E27/2000 -> 0.145 | C27: per lb. | D27: 724.5 | E27: lbs. | F27: =B27*D27 -> 105.0525 | H27: 1361.25 | I27: lbs. | K27: =B27*H27 -> 197.38125
A28: 7. Fat | B28: =Inputs!E28 -> 0.3 | C28: per lb. | D28: 26 | E28: lbs. | F28: =B28*D28 -> 7.8 | H28: 111 | I28: lbs. | K28: =B28*H28 -> 33.3
A29: 8. Milk replacer, calf starter | F29: 65 | K29: 44
A30: 9. Total Feed Costs | F30: =SUM(F22:F29) -> 2036.3705 | K30: =SUM(K22:K29) -> 2266.5028
A32: B. LIVESTOCK COSTS | F32: $$Value | K32: $$Value
A33: 1. Milk marketing per cwt. | B33: 0.3 | D33: 200 | E33: cwts. | F33: =B33*D33 -> 60 | G33: 0.275 | H33: 240 | I33: cwts. | K33: =G33*H33 -> 66
A34: 2. Veterinary and Health | F34: 130 | K34: 140
A35: 3. Fuel, utilities and repairs | F35: 152 | K35: 155
A36: 4. DHIA & accounting | F36: 28 | K36: 30
A37: 5. Breeding fees | F37: 42 | K37: 52
A38: 6. Bedding, supplies and misc. | F38: 160 | K38: 170
A39: 7. Total Livestock Cost | F39: =SUM(F33:F38) -> 572 | K39: =SUM(K33:K38) -> 613
A40: 8. Operating Capital Interest | B40: 0.09 | D40: 3 | E40: months | F40: =(F30+F39)*B40*0.25 -> 58.688336 | H40: 3 | I40: months | K40: =(K30+K39)*B40*0.25 -> 64.788812
A41: 9. Total Variable Costs | F41: =F30+F39+F40 -> 2667.0588 | K41: =K30+K39+K40 -> 2944.2916
A43: III. FIXED COSTS (c)
A44: 1. Machinery, equipment, facilities | F44: 310 | K44: 340
A45: 2. Interest & Ins. on Herd | B45: 0.075 | C45: annually | F45: =B45*C46 -> 105 | K45: =B45*I46 -> 115.5
A46: 3. Death Loss | B46: 0.05 | C46: 1400 | F46: =C46*B46 -> 70 | H46: 0.05 | I46: 1540 | K46: =H46*I46 -> 77
A47: 4. Total Fixed Cost | F47: =SUM(F44:F46) -> 485 | K47: =SUM(K44:K46) -> 532.5
A49: IV. TOTAL COST | C49: per cwt. (d) | F49: per cow | H49: per cwt. (d) | K49: per cow
A50: (except for labor and management) | C50: =F50/((F18-F46)/((F6+F7+F8+F9+F10+F11+F12+F13)/200)) -> 14.943411 | F50: =F41+F47 -> 3152.0588 | H50: =K50/((K18-K46)/((K6+K7+K8+K9+K10+K11+K12+K13)/240)) -> 13.803102 | K50: =K41+K47 -> 3476.7916
A52: V. RETURNS | C52: per cwt. (d) | F52: per cow | H52: per cwt. (d) | K52: per cow
A53: 1. Gross receipts | C53: =F53/((F18-F46)/((F6+F7+F8+F9+F10+F11+F12+F13+F17)/200)) -> 17.794619 | F53: =F18 -> 3753.4728 | H53: =K53/((K18-K46)/((K6+K7+K8+K9+K10+K11+K12+K13+K17)/240)) -> 17.768268 | K53: =K18 -> 4475.5566
A54: 2. Less variable costs | C54: =F54/((F18-F46)/((F6+F7+F8+F9+F10+F11+F12+F13)/200)) -> 12.644103 | F54: =F41 -> 2667.0588 | H54: =K54/((K18-K46)/((K6+K7+K8+K9+K10+K11+K12+K13)/240)) -> 11.68904 | K54: =K41 -> 2944.2916
A55: 3. Returns above variable costs | C55: =F55/((F18-F46)/((F6+F7+F8+F9+F10+F11+F12+F13)/200)) -> 5.1505165 | F55: =F18-F41 -> 1086.414 | H55: =K55/((K18-K46)/((K6+K7+K8+K9+K10+K11+K12+K13)/240)) -> 6.0792276 | K55: =K18-K41 -> 1531.265
A56: 4. Less fixed costs | C56: =F56/((F18-F46)/((F6+F7+F8+F9+F10+F11+F12+F13)/200)) -> 2.299308 | F56: =F47 -> 485 | H56: =K56/((K18-K46)/((K6+K7+K8+K9+K10+K11+K12+K13)/240)) -> 2.1140617 | K56: =K47 -> 532.5
A57: 5. Returns to labor & management | C57: =F57/((F18-F46)/((F6+F7+F8+F9+F10+F11+F12+F13)/200)) -> 2.8512084 | F57: =F55-F56 -> 601.41402 | H57: =K57/((K18-K46)/((K6+K7+K8+K9+K10+K11+K12+K13)/240)) -> 3.9651659 | K57: =K55-K56 -> 998.76503
A58: 6. Less labor cost 45 hrs. @ $13/hr. | C58: =F58/((F18-F46)/((F6+F7+F8+F9+F10+F11+F12+F13)/200)) -> 2.7733922 | F58: =45*13 -> 585 | H58: =K58/((K18-K46)/((K6+K7+K8+K9+K10+K11+K12+K13)/240)) -> 2.3224903 | K58: =45*13 -> 585
A59: 7. Returns to management | C59: =F59/((F18-F46)/((F6+F7+F8+F9+F10+F11+F12+F13)/200)) -> 0.077816259 | F59: =F57-F58 -> 16.414019 | H59: =K59/((K18-K46)/((K6+K7+K8+K9+K10+K11+K12+K13)/240)) -> 1.6426756 | K59: =K57-K58 -> 413.76503
A61: VI. BREAK EVEN MILK PRICE (e)
A62: 1. Budget break even per cwt. | F62: =((F50+F58)-(F14+F15+F16))/B5 -> 17.38069 | K62: =((K50+K58)-(K14+K15+K16))/G5 -> 15.738552
A63: 2. Actual milk price received this month | F63: =(SUM(F6:F12))/B5 -> 17.46276 | K63: =(SUM(K6:K12))/G5 -> 17.462573
A64: 3. Actual price received this month+MILC payment | F64: =(SUM(F6:F13)+F17)/200 -> 17.46276 | K64: =(SUM(K6:K13)+K17)/240 -> 17.462573

Sheet Tiestall
E1: =Freestall!E1 -> Midwest Dairy Cow Annual Budget- Freestall | H1: =Inputs!D7 -> August 2010
E2: Large Breed Dairy Cow Including Replacements Producing
E3: 20,000 lbs. & 24,000 lbs. of Grade A Milk
A4: I. RECEIPTS | F4: $$ Value | K4: $$ Value
A5: 1. Components: | B5: 200 | C5: cwts. | G5: 240 | H5: cwts.
A6: a. Butterfat | B6: =Inputs!E9*B5 -> 710 | C6: lbs. | D6: =Inputs!E14 -> 2.4044 | E6: $/lb. | F6: =B6*D6 -> 1707.124 | G6: =G5*Inputs!E9 -> 852 | H6: lbs. | I6: =D6 -> 2.4044 | J6: $/lb. | K6: =G6*I6 -> 2048.5488
A7: b. Protein | B7: =Inputs!E10*B5 -> 610 | C7: lbs. | D7: =Inputs!E15 -> 2.3057 | E7: $/lb. | F7: =B7*D7 -> 1406.477 | G7: =G5*Inputs!E10 -> 732 | H7: lbs. | I7: =D7 -> 2.3057 | J7: $/lb. | K7: =G7*I7 -> 1687.7724
A8: c. Other Solids | B8: =Inputs!E11*B5 -> 1146 | C8: lbs. | D8: =Inputs!E16 -> 0.1673 | E8: $/lb. | F8: =B8*D8 -> 191.7258 | G8: =G5*Inputs!E11 -> 1375.2 | H8: lbs. | I8: =D8 -> 0.1673 | J8: $/lb. | K8: =G8*I8 -> 230.07096
A9: d. Producer Price Differential | D9: =Inputs!E17 -> 0.75 | E9: $/cwt. | F9: =B5*D9 -> 150 | I9: =D9 -> 0.75 | J9: $/cwt. | K9: =G5*I9 -> 180
A10: e. Quality | B10: =Inputs!E12*1000 -> 265000 | C10: SCC | D10: =Inputs!E18 -> 0.00085 | E10: $/thousand | F10: =(B10/1000)*D10 -> 0.22525 | G10: =Inputs!E12*1000 -> 265000 | H10: SCC | I10: =D10 -> 0.00085 | J10: $/thousand | K10: =(G10/1000)*I10 -> 0.22525
A11: f. Protein Premium | D11: 0 | E11: $/lb. | F11: =B7*D11 -> 0 | I11: =D11 -> 0 | J11: $/lb. | K11: =G7*I11 -> 0
A12: g. Volume | D12: 0.185 | E12: $/cwt. | F12: =B5*D12 -> 37 | I12: =D12 -> 0.185 | J12: $/cwt. | K12: =G5*I12 -> 44.4
A13: 2. Capital Payout | D13: 0 | E13: $/cwt. | F13: =B5*D13 -> 0 | I13: =D13 -> 0 | J13: $/cwt. | K13: =G5*I13 -> 0
A14: 3. Cull/cow (a) | B14: 0.36 | C14: head | D14: =B14*Inputs!E31*14 -> 287.28 | E14: per hd. | F14: =B14*D14 -> 103.4208 | G14: 0.39 | H14: head | I14: =D14 -> 287.28 | J14: per hd. | K14: =G14*I14 -> 112.0392
A15: 4. Dairy calf | B15: 0.51 | C15: head | D15: 150 | E15: per hd. | F15: =B15*D15 -> 76.5 | G15: 0.52 | H15: head | I15: =D15 -> 150 | J15: per hd. | K15: =G15*I15 -> 78
A16: 5. Replacement heifer calf | B16: 0.18 | C16: head | D16: 450 | E16: per hd. | F16: =B16*D16 -> 81 | G16: 0.21 | H16: head | I16: =D16 -> 450 | J16: per hd. | K16: =G16*I16 -> 94.5
A17: 6. MILC payment | D17: =Inputs!E20 -> 0 | E17: $/cwt. | F17: =B5*D17 -> 0 | I17: =D17 -> 0 | K17: =G5*I17 -> 0
A18: GROSS RECEIPTS | F18: =SUM(F6:F17) -> 3753.4728 | K18: =SUM(K6:K17) -> 4475.5566
A20: II. VARIABLE COSTS
A21: A. FEED COSTS (b) | B21: Price/Unit | D21: Amount | F21: $$ Value | H21: Amount | K21: $$ Value
A22: 1. Corn equivalents | B22: =Inputs!E25 -> 4.35 | C22: per bu. | D22: 104.38 | E22: bu. | F22: =B22*D22 -> 454.053 | H22: 112.91 | I22: bu. | K22: =B22*H22 -> 491.1585
A23: 2. Corn Silage | B23: =Inputs!E25*10 -> 43.5 | C23: per ton | D23: 8.04 | E23: tons | F23: =B23*D23 -> 349.74 | H23: 7.99 | I23: tons | K23: =B23*H23 -> 347.565
A24: 3. Hay equivalents | B24: =Inputs!E29 -> 132.5 | C24: per ton | D24: 6.09 | E24: tons | F24: =B24*D24 -> 806.925 | H24: 6.03 | I24: tons | K24: =H24*B24 -> 798.975
A25: 4. Salts and minerals | B25: 0.14 | C25: per lb. | D25: 241.97 | E25: lbs. | F25: =B25*D25 -> 33.8758 | H25: 323.23 | I25: lbs. | K25: =H25*B25 -> 45.2522
A26: 5. Protein supplement | B26: =Inputs!E26/2000 -> 0.1665 | C26: per lb. | D26: 1284.83 | E26: lbs. | F26: =B26*D26 -> 213.92419 | H26: 1855.08 | I26: lbs. | K26: =B26*H26 -> 308.87082
A27: 6. Whole (linted) cottonseed | B27: =Inputs!E27/2000 -> 0.145 | C27: per lb. | D27: 724.5 | E27: lbs. | F27: =B27*D27 -> 105.0525 | H27: 1361.25 | I27: lbs. | K27: =B27*H27 -> 197.38125
A28: 7. Fat | B28: =Inputs!E28 -> 0.3 | C28: per lb. | D28: 26 | E28: lbs. | F28: =B28*D28 -> 7.8 | H28: 111 | I28: lbs. | K28: =B28*H28 -> 33.3
A29: 8. Milk replacer, calf starter | F29: 65 | K29: 44
A30: 9. Total Feed Costs | F30: =SUM(F22:F29) -> 2036.3705 | K30: =SUM(K22:K29) -> 2266.5028
A32: B. LIVESTOCK COSTS | F32: $$Value | K32: $$Value
A33: 1. Milk marketing per cwt. | B33: 0.3 | D33: 200 | E33: cwts. | F33: =B33*D33 -> 60 | G33: 0.275 | H33: 240 | I33: cwts. | K33: =G33*H33 -> 66
A34: 2. Veterinary and Health | F34: 130 | K34: 140
A35: 3. Fuel, utilities and repairs | F35: 152 | K35: 155
A36: 4. DHIA & accounting | F36: 28 | K36: 30
A37: 5. Breeding fees | F37: 42 | K37: 52
A38: 6. Bedding, supplies and misc. | F38: 160 | K38: 170
A39: 7. Total Livestock Cost | F39: =SUM(F33:F38) -> 572 | K39: =SUM(K33:K38) -> 613
A40: 8. Operating Capital Interest | B40: 0.09 | D40: 3 | E40: months | F40: =(F30+F39)*B40*0.25 -> 58.688336 | H40: 3 | I40: months | K40: =(K30+K39)*B40*0.25 -> 64.788812
A41: 9. Total Variable Costs | F41: =F30+F39+F40 -> 2667.0588 | K41: =K30+K39+K40 -> 2944.2916
A43: III. FIXED COSTS (c)
A44: 1. Machinery, equipment, facilities | F44: 310 | K44: 340
A45: 2. Interest & Ins. on Herd | B45: 0.075 | C45: annually | F45: 126.82 | K45: 152.25
A46: 3. Death Loss | B46: 0.05 | C46: x $1400.00 | F46: 45.5 | H46: 0.05 | I46: x $1540.00 | K46: 53.44
A47: 4. Total Fixed Cost | F47: =SUM(F44:F46) -> 482.32 | K47: =SUM(K44:K46) -> 545.69
A49: IV. TOTAL COST | C49: per cwt. (d) | F49: per cow | H49: per cwt. (d) | K49: per cow
A50: (except for labor and management) | C50: =F50/((F18-F46)/((F6+F7+F8+F9+F10+F11+F12+F13)/200)) -> 14.832052 | F50: =F41+F47 -> 3149.3788 | H50: =K50/((K18-K46)/((K6+K7+K8+K9+K10+K11+K12+K13)/240)) -> 13.781648 | K50: =K41+K47 -> 3489.9816
A52: V. RETURNS | C52: per cwt. (d) | F52: per cow | H52: per cwt. (d) | K52: per cow
A53: 1. Gross receipts | C53: =F53/((F18-F46)/((F6+F7+F8+F9+F10+F11+F12+F13+F17)/200)) -> 17.677043 | F53: =F18 -> 3753.4728 | H53: =K53/((K18-K46)/((K6+K7+K8+K9+K10+K11+K12+K13+K17)/240)) -> 17.673603 | K53: =K18 -> 4475.5566
A54: 2. Less variable costs | C54: =F54/((F18-F46)/((F6+F7+F8+F9+F10+F11+F12+F13)/200)) -> 12.560558 | F54: =F41 -> 2667.0588 | H54: =K54/((K18-K46)/((K6+K7+K8+K9+K10+K11+K12+K13)/240)) -> 11.626764 | K54: =K41 -> 2944.2916
A55: 3. Returns above variable costs | C55: =F55/((F18-F46)/((F6+F7+F8+F9+F10+F11+F12+F13)/200)) -> 5.116485 | F55: =F18-F41 -> 1086.414 | H55: =K55/((K18-K46)/((K6+K7+K8+K9+K10+K11+K12+K13)/240)) -> 6.0468389 | K55: =K18-K41 -> 1531.265
A56: 4. Less fixed costs | C56: =F56/((F18-F46)/((F6+F7+F8+F9+F10+F11+F12+F13)/200)) -> 2.2714941 | F56: =F47 -> 482.32 | H56: =K56/((K18-K46)/((K6+K7+K8+K9+K10+K11+K12+K13)/240)) -> 2.1548847 | K56: =K47 -> 545.69
A57: 5. Returns to labor & management | C57: =F57/((F18-F46)/((F6+F7+F8+F9+F10+F11+F12+F13)/200)) -> 2.8449909 | F57: =F55-F56 -> 604.09402 | H57: =K57/((K18-K46)/((K6+K7+K8+K9+K10+K11+K12+K13)/240)) -> 3.8919542 | K57: =K55-K56 -> 985.57503
A58: 6. Less labor cost 70 hrs. @ $13/hr. | C58: =F58/((F18-F46)/((F6+F7+F8+F9+F10+F11+F12+F13)/200)) -> 4.2856602 | F58: =70*13 -> 910 | H58: =K58/((K18-K46)/((K6+K7+K8+K9+K10+K11+K12+K13)/240)) -> 3.5935147 | K58: =70*13 -> 910
A59: 7. Returns to management | C59: =F59/((F18-F46)/((F6+F7+F8+F9+F10+F11+F12+F13)/200)) -> -1.4406693 | F59: =F57-F58 -> -305.90598 | H59: =K59/((K18-K46)/((K6+K7+K8+K9+K10+K11+K12+K13)/240)) -> 0.29843953 | K59: =K57-K58 -> 75.575028
A61: VI. BREAK EVEN MILK PRICE (e)
A62: 1. Budget break even per cwt. | F62: =((F50+F58)-(F14+F15+F16))/B5 -> 18.99229 | K62: =((K50+K58)-(K14+K15+K16))/G5 -> 17.147677
A63: 2. Actual milk price received this month | F63: =(SUM(F6:F12))/B5 -> 17.46276 | K63: =(SUM(K6:K12))/G5 -> 17.462573
A64: 3. Actual price received this month+MILC payment | F64: =(SUM(F6:F13)+F17)/200 -> 17.46276 | K64: =(SUM(K6:K13)+K17)/240 -> 17.462573
