Workbook
Name Aid: 'Aid Adjust'!$A$10:$H$341
Name Ideas: Credits!$A$8:$C$339
Name Ideas: Levy!$A$9:$C$342
Name Ideas: Ideas!$A$9:$H$341
Name Query_from_Databridge: Query1!$A$3:$F$125
Name Query_from_Databridge: Query4!$A$3:$F$48
Name Shift05: Receipts!$A$7:$K$338
Name ShiftCY: 'Shift 14'!$A$6:$O$337
Name ShiftPY: 'Shift 13'!$A$11:$O$342
Name TitleRegion1.a1.ba339.8: Data!$BA$339
Name TitleRegion1.a1.bd340.10: Levy!$BD$340
Name TitleRegion1.a1.g345.15: Names!$G$345
Name TitleRegion1.a1.n108.4: Accounts!$N$108
Name TitleRegion1.a1.o342.9: 'Shift 13'!$O$342
Name TitleRegion1.a2.ah339.11: Credits!$AH$339
Name TitleRegion1.a2.f130.14: Query1!$F$130
Name TitleRegion1.a2.f55.15: Query4!$A$1
Name TitleRegion1.a2.h341.6: 'Aid Adjust'!$H$341
Name TitleRegion1.a2.p340.13: Ideas!$A$2
Name TitleRegion1.a2.q338.12: Receipts!$Q$338
Name TitleRegion1.a2.q342.7: 'Shift 14'!$Q$342
Name TitleRegion1.a3.d72.5: Entries!$D$72
Name TitleRegion1.a3.i124.2: Report!$I$124
Name TitleRegion1.a4.s131.3: Funds!$S$131
Name TitleRegiona1.t70.1: Instructions!$T$70

Sheet Instructions
A1: PROPERTY TAX SHIFT | F1: n/a | G1: n/a | H1: n/a | I1: n/a | J1: n/a | K1: n/a | L1: n/a | M1: =Report!I1 -> 41828 | N1: coulumn left blank intentionally | O1: 2014 | P1: Pay 2014 | Q1: 13 Pay 14 | R1: FY 2015
A2: n/a | B2: n/a | C2: n/a | D2: n/a | E2: n/a | F2: n/a | G2: n/a | H2: n/a | I2: n/a | J2: n/a | K2: n/a | L2: n/a | M2: n/a | O2: rest of coulumn left blank intentionally | P2: Pay 2013 | Q2: 12 Pay 13 | R2: FY 2014 | S2: 06/30/14 | T2: 07/01/2013 to 06/30/2014
A3: n/a | B3: n/a | C3: n/a | D3: n/a | E3: n/a | F3: n/a | G3: n/a | H3: n/a | I3: n/a | J3: n/a | K3: n/a | L3: n/a | M3: n/a | P3: Pay 2012 | Q3: rest of column left blank intentionally | R3: FY 2013 | S3: 06/30/13 | T3: 07/01/2013 to 04/30/2014
A4: n/a | B4: n/a | C4: n/a | D4: n/a | E4: n/a | F4: n/a | G4: n/a | H4: n/a | I4: n/a | J4: n/a | K4: n/a | L4: n/a | M4: n/a | P4: Pay 2011 | R4: rest of column left blank intentionally | S4: rest of column left blank intentionally | T4: 05/01/2014 to 06/30/2014
A5: ="The property tax shift is an accounting entry that takes a portion of the school district's property tax revenue and moves it forward one fiscal year, i.e., taxes that would otherwise be revenue for fiscal year "&RIGHT(R1,4)&" are shifted into fiscal year "&RIGHT(R2,4)&". The property tax shift requirement is in Minnesota Statutes, section 123B.75, subdivision 5." -> The property tax shift is an accounting entry that takes a portion of the school district's property tax revenue and moves it forward one fiscal year, i.e., taxes that would otherwise be revenue for fiscal year 2015 are shifted into fiscal year 2014. The property tax shift requirement is in Minnesota Statutes, section 123B.75, subdivision 5. | P5: Pay 2010 | T5: rest of column left blank intentionally
A6: n/a | B6: n/a | C6: n/a | D6: n/a | E6: n/a | F6: n/a | G6: n/a | H6: n/a | I6: n/a | J6: n/a | K6: n/a | L6: n/a | M6: n/a | O6: n/a | P6: Pay 2009
A7: n/a | B7: n/a | C7: n/a | D7: n/a | E7: n/a | F7: n/a | G7: n/a | H7: n/a | I7: n/a | J7: n/a | K7: n/a | L7: n/a | M7: n/a | O7: n/a | P7: Pay 2008
A8: Notes: | C8: n/a | D8: n/a | E8: n/a | F8: n/a | G8: n/a | H8: n/a | I8: n/a | J8: n/a | K8: n/a | L8: n/a | M8: n/a | O8: n/a | P8: Pay 2007
A9: line left blank intentionally
A10: ="For the June 30, "&RIGHT(R2,4)&", tax shift this spreadsheet is using the payable "&RIGHT(P1,4)&" final certified levies plus/minus county auditor adjustments." -> For the June 30, 2014, tax shift this spreadsheet is using the payable 2014 final certified levies plus/minus county auditor adjustments.
A11: line left blank intentionally
A12: ="Preliminary payable "&RIGHT(P1,4)&" credits are used in this spreadsheet. The spreadsheet will be updated to use final payable "&RIGHT(P1,4)&" credits when that data is available." -> Preliminary payable 2014 credits are used in this spreadsheet. The spreadsheet will be updated to use final payable 2014 credits when that data is available.
A13: line left blank intentionally
A14: ="Tax receipts for May-July "&RIGHT(R2,4)&" for the general fund and community service fund have been estimated on the Receipts tab. Preliminary payable "&RIGHT(P1,4)&" credits from the Department of Revenue are used in computing estimated tax receipts. These estimates are carried over to cells E91 and F91 of the Report tab. Districts should override these estimates when actual tax receipts are determined." -> Tax receipts for May-July 2014 for the general fund and community service fund have been estimated on the Receipts tab. Preliminary payable 2014 credits from the Department of Revenue are used in computing estimated tax receipts. These estimates are carried over to cells E91 and F91 of the Report tab. Districts should override these estimates when actual tax receipts are determined.
A17: line left blank intentionally
A18: Early Recognition Levies | E18: n/a | F18: n/a | G18: n/a | H18: n/a | I18: n/a | J18: n/a | K18: n/a | L18: n/a | M18: n/a
A19: Certain levies have been--and will continue to be--shifted 100% with no aid reduction. Recognizing these levies early gets the revenue into the same fiscal year as the related expenditures. There is no state aid adjustment for this portion of the shift.
A20: line left blank intentionally
A21: Other Levies | D21: n/a | E21: n/a | F21: n/a | G21: n/a | H21: n/a | I21: n/a | J21: n/a | K21: n/a | L21: n/a | M21: n/a
A22: Starting in fiscal year 2004, the shift was expanded to include all other general and community service fund levies, net of tax credits. There is a corresponding state aid adjustment for this portion of the property tax shift, making this portion of the shift revenue neutral to school districts each year. If the shift at the end of the current year is larger than the shift at the end of the previous year, state aid for the current year is reduced for the net increase in the shift. If the shift at the end of the current year is less than the shift at the end of the previous year, state aid for the current year is increased for the net decrease in the shift.
A26: line left blank intentionally
A27: Starting in fiscal year 2006, the shift percentage for other levies was set to zero percent.
A28: Starting in fiscal year 2011, the shift percentage for other levies was set to 48.6 percent, and based on gross levies (before subtraction of credits).
A29: Starting in fiscal year 2014, the shift percentage for other levies was again set to zero percent.
A30: line left blank intentionally
A31: The "Reports" tab shows the property tax shift report for a selected school district. | I31: n/a | J31: n/a | K31: n/a | L31: n/a | M31: n/a
B32: To select a specific district, type the district number in cell A3 (use 1.2 for Minneapolis) and press enter. Information for the selected district will then appear in the report. Running a macro is not required.
A34: line left blank intentionally
A35: n/a | B35: The first section shows the property tax shift report for the school district, with a definition for each tax shift category. | K35: n/a | L35: n/a | M35: n/a
A36: n/a | B36: n/a | C36: ="Column 1 is the amount of payable "&RIGHT(P1,4)&" levy to be recognized in fiscal year "&RIGHT(R2,4)&"." -> Column 1 is the amount of payable 2014 levy to be recognized in fiscal year 2014. | I36: n/a | J36: n/a | K36: n/a | L36: n/a | M36: n/a
A37: n/a | B37: n/a | C37: ="Column 2 is the amount of payable "&RIGHT(P2,4)&" levy that was recognized in fiscal year "&RIGHT(R3,4)&"." -> Column 2 is the amount of payable 2013 levy that was recognized in fiscal year 2013. | I37: n/a | J37: n/a | K37: n/a | L37: n/a | M37: n/a
A38: n/a | B38: n/a | C38: Column 3 is the revenue change to be recognized as a result of the levies shifted with with no aid reduction (net of column 1 and column 2 for these categories).
A39: n/a | B39: n/a | C39: Column 4 is the net shift amount to be recognized as a result of levies shifted with an aid reduction. A negative amount in this column represents a debit balance in source 020 and related crebit balance in source 299.
A40: line left blank intentionally
A41: n/a | B41: n/a | C41: Column 5 is the state aid payment (reduction) that is being made in the current year for the property tax shift.
A42: n/a | B42: n/a | C42: Column 6 represents the state aid payment (reduction) that will be made next year, for this year's tax shift. Column 4 plus column 5 plus column 6 should equal zero.
A43: line left blank intentionally
A44: n/a | B44: The second section discusses the assumptions that have been made in generating the entries to record the tax shift. Also review the Accounts tab and Entries tab.
A45: line left blank intentionally
A46: n/a | B46: ="In the third section, estimated tax receipts for May, June and July "&RIGHT(R2,4)&" have been computed. See blue highlighted area. Override these estimates with actual tax settlement receipts for May, June and July "&RIGHT(R2,4)&" when this data is available. If the gross shift amount is greater than May, June and July tax receipts, the district will recognize fiscal year "&RIGHT(R1,4)&" general education aid early in an amount equal to the difference between tax receipts and the gross shift." -> In the third section, estimated tax receipts for May, June and July 2014 have been computed. See blue highlighted area. Override these estimates with actual tax settlement receipts for May, June and July 2014 when this data is available. If the gross shift amount is greater than May, June and July tax receipts, the district will recognize fiscal year 2015 general education aid early in an amount equal to the difference between tax receipts and the gross shift.
A49: line left blank intentionally
A50: n/a | B50: ="The fourth section provides information to make the year-end accounting entries for the fiscal year "&RIGHT(R2,4)&" property tax shift. The entry will include any general education aid to be recognized early if tax settlement receipts entered in section three are less than the gross shift amount." -> The fourth section provides information to make the year-end accounting entries for the fiscal year 2014 property tax shift. The entry will include any general education aid to be recognized early if tax settlement receipts entered in section three are less than the gross shift amount.
A51: line left blank intentionally
A52: Enter data on the Funds tab if you want to use the reconciliation feature in the Accounts tab. | I52: n/a | J52: n/a | K52: n/a | L52: n/a | M52: n/a
A53: n/a | B53: ="Enter certified levy by fund for payable "&RIGHT(P8,4)&" through "&RIGHT(P1,4)&" in the yellow highlighted section. Verify total certified levy. This data is used in the Accounts tab to automatically enter the certifed levy and to allocate abatements and adjustments." -> Enter certified levy by fund for payable 2007 through 2014 in the yellow highlighted section. Verify total certified levy. This data is used in the Accounts tab to automatically enter the certifed levy and to allocate abatements and adjustments.
A54: line left blank intentionally
A55: n/a | B55: ="Enter tax settlements received during fiscal year "&RIGHT(R2,4)&" in the green highlighted section. The green outlined section below will then show each settlement allocated by fund. This data carries over as settlements received in the Accounts tab." -> Enter tax settlements received during fiscal year 2014 in the green highlighted section. The green outlined section below will then show each settlement allocated by fund. This data carries over as settlements received in the Accounts tab.
A56: line left blank intentionally
A57: The Accounts tab provides a year-end reconciliation for each tax-related account. | H57: n/a | I57: n/a | J57: n/a | K57: n/a | L57: n/a | M57: n/a
A58: n/a | B58: This section shows how to determine the balance to be reflected in each account at year-end after all tax entries (including the property tax shift entries) have been made. Balance sheet accounts are listed first and then revenue source codes. Also shown is the source document where the data for each step of the reconcilation can be obtained.
A61: line left blank intentionally
B62: This tab can serve as a year-end reconcilation tool. Enter data in the highlighted fields on this tab and in the Funds tab. All other fields in this tab will automatically be computed.
A64: line left blank intentionally
A65: The Entries tab shows standard accounting entries for recording property taxes.
A66: n/a | B66: The entries start with the levy being certified by the school board and work through a full year of accounting entries.
A67: line left blank intentionally
A68: The other tabs in this spreadsheet provide the data that is used to create the tax shift report shown in the Reports tab. | K68: n/a | L68: n/a | M68: n/a
A69: line left blank intentionally
A70: If you have questions about the property tax shift or about using this spreadsheet, contact Terri Yetter by phone at 651-582-8868 or by e-mail at terri.yetter@state.mn.us.
A71: End of worksheet

Sheet Report
D1: PROPERTY TAX SHIFT YEAR-END RECONCILIATION | I1: 41828
D2: =Instructions!S2 -> 06/30/14
A3: 1 | B3: Enter District Number
B5: =VLOOKUP(A3,ShiftCY,3) -> AITKIN
C6: 1 | D6: 2 | E6: 3 | F6: 4 | H6: 5 | I6: 6
C7: ="Gross Shift Amount "&Instructions!Q1 -> Gross Shift Amount 13 Pay 14 | D7: ="Replacement for "&Instructions!Q2&" Shift" -> Replacement for 12 Pay 13 Shift | E7: =Instructions!R2&" Revenue Adjust Src Code 001" -> FY 2014 Revenue Adjust Src Code 001 | F7: =Instructions!R2&" Net Shift Amount Src Code 020" -> FY 2014 Net Shift Amount Src Code 020 | H7: State Aid Adjustment Src Code 299 | I7: Revenue Adjustment Src Code 299
A9: A | B9: General - Shift & Adjust Aid | C9: =VLOOKUP($A$3,ShiftCY,4,FALSE) -> 0 | D9: =VLOOKUP($A$3,ShiftPY,4,FALSE) -> 348692.74 | F9: =C9-D9 -> -348692.74
A10: B | B10: General - Operating Referendum (with aid adjust) | C10: =VLOOKUP($A$3,ShiftCY,5,FALSE) -> 0 | D10: =VLOOKUP($A$3,ShiftPY,5,FALSE) -> 0 | F10: =C10-D10 -> 0
A11: C | B11: General - Operating Referendum (no aid adjust) | C11: =VLOOKUP($A$3,ShiftCY,6,FALSE) -> 141143.88 | D11: =VLOOKUP($A$3,ShiftPY,6,FALSE) -> 141143.88 | E11: =C11-D11 -> 0
A12: D | B12: General - Addl Referendum Shift | C12: =VLOOKUP($A$3,ShiftCY,7,FALSE) -> 0 | D12: =VLOOKUP($A$3,ShiftPY,7,FALSE) -> 0 | E12: =C12-D12 -> 0
A13: E | B13: General - Career Technical | C13: =VLOOKUP($A$3,ShiftCY,8,FALSE) -> 30163.77 | D13: =VLOOKUP($A$3,ShiftPY,8,FALSE) -> 25644.59 | E13: =C13-D13 -> 4519.18
A14: F | B14: General - 100% Shift, No Adjust | C14: =VLOOKUP($A$3,ShiftCY,9,FALSE) -> 0 | D14: =VLOOKUP($A$3,ShiftPY,9,FALSE) -> 0 | E14: =C14-D14 -> 0
A15: G | B15: General - Reemploy Ins (Reserved) | C15: =VLOOKUP($A$3,ShiftCY,10,FALSE) -> 0 | D15: =VLOOKUP($A$3,ShiftPY,10,FALSE) -> 0 | E15: =C15-D15 -> 0
A16: H | B16: General - Reemploy Ins (Unreserved) | C16: =VLOOKUP($A$3,ShiftCY,11,FALSE) -> 6695.76 | D16: =VLOOKUP($A$3,ShiftPY,11,FALSE) -> 8234.63 | E16: =C16-D16 -> -1538.87
A17: I | B17: General - Legislative Changes | C17: =VLOOKUP($A$3,ShiftCY,12,FALSE) -> 0 | D17: =VLOOKUP($A$3,ShiftPY,12,FALSE) -> 0 | E17: =C17-D17 -> 0
A18: J | B18: General Fund Total | C18: =SUM(C9:C17) -> 178003.41 | D18: =SUM(D9:D17) -> 523715.84 | E18: =SUM(E9:E17) -> 2980.31 | F18: =SUM(F9:F17) -> -348692.74 | H18: =VLOOKUP($A$3,Ideas,4) -> 354088.31 | I18: =-F18-H18 -> -5395.57
A20: K | B20: Comm Serv - Shift & Adjust Aid | C20: =VLOOKUP($A$3,ShiftCY,13,FALSE) -> 0 | D20: =VLOOKUP($A$3,ShiftPY,13,FALSE) -> 5395.57 | F20: =C20-D20 -> -5395.57
A21: L | B21: Comm Serv - 100% Shift, No Adjust | C21: 0 | D21: 0 | E21: =C21-D21 -> 0
A22: M | B22: Comm Serv - Legislative Change | C22: =VLOOKUP($A$3,ShiftCY,14,FALSE) -> 0 | D22: =VLOOKUP($A$3,ShiftPY,14,FALSE) -> 0 | E22: =C22-D22 -> 0
A23: N | B23: Comm Serv Fund Total | C23: =SUM(C20:C22) -> 0 | D23: =SUM(D20:D22) -> 5395.57 | E23: =SUM(E20:E22) -> 0 | F23: =SUM(F20:F22) -> -5395.57 | H23: =VLOOKUP($A$3,Ideas,5) -> 0 | I23: =-F23-H23 -> 5395.57
A26: O | B26: Total | C26: =C18+C23 -> 178003.41 | D26: =D18+D23 -> 529111.41 | E26: =E18+E23 -> 2980.31 | F26: =F18+F23 -> -354088.31 | H26: =H18+H23 -> 354088.31 | I26: =I18+I23 -> -7.2759576e-12
A28: Definitions of levy categories within funds
A29: The following categories are mutually exclusive, that is, each levy appears in one category only.
B30: Shift & Adjust Aid | C30: ="For "&Instructions!P1&" this category includes all levies not identified below, shifted at 0.0%." -> For Pay 2014 this category includes all levies not identified below, shifted at 0.0%.
C31: ="For "&Instructions!P2&" this category includes all levies not identified below, shifted at 48.6%." -> For Pay 2013 this category includes all levies not identified below, shifted at 48.6%.
B32: Operating referendum (with aid adjust) | C32: ="For "&Instructions!P1&" this category is the greater of zero, or the "&Instructions!P1&" referendum levy shifted at 0.0% minus" -> For Pay 2014 this category is the greater of zero, or the Pay 2014 referendum levy shifted at 0.0% minus
C33: ="the Pay 2001 referendum shifted at 31%." -> the Pay 2001 referendum shifted at 31%.
B34: Operating referendum (no aid adjust) | C34: This category is the Pay 2001 referendum levy shifted at 31%. This amount will be constant from year to year.
B35: Addl referendum shift | C35: This is an additional revenue shift for districts that had a decrease in Pay 1994 referendum levy
C36: due to the net of changes in the allocation of HACA and the increase in referendum equalization aid.
C37: This amount will be constant from year to year.
B38: Career Technical | C38: Career technical levy and adjustment shifted at 100% with no aid adjustment.
B39: 100% shift, no adjust | C39: Includes levies that are shifted at 100% and for which there is no reduction to state aid. This category
C40: includes integration for first class districts, additional retirement, health benefits, and related adjustments.
B41: Reemploy Ins (reserved) | C41: Includes reemployment insurance levy adjustments for FY 2003 shifted at 100% with no aid adjustment.
B42: Reemploy Ins (unreserved) | C42: Includes reemployment insurance levy and adjustments for FY 2004 and later shifted at 100% with no aid adjustment.
B43: Legislative changes | C43: Includes selected levies that have been adjusted based on legislation that changes a levy authority after the levy has
C44: been certified (See Minnesota Statutes, section 126C.48, subdivision 6). The revenue shift is at 100% and there is
C45: ="no adjustment to state aids. For "&Instructions!P2&" and "&Instructions!P1&" this category is zero." -> no adjustment to state aids. For Pay 2013 and Pay 2014 this category is zero.
A46: =$A$3 -> 1 | B46: =VLOOKUP($A$3,ShiftCY,3) -> AITKIN | I46: =Instructions!$M$1 -> 41828
A47: ASSUMPTIONS:
A49: 1) | B49: Property Taxes for Subsequent Years (GNL 235) entries have already taken place. Prior to the tax shift entries the balance
B50: ="in account 235 should equal the Certified "&Instructions!P1&" levy from the School Tax Report." -> in account 235 should equal the Certified Pay 2014 levy from the School Tax Report.
A54: 2) | B54: ="If the Advance of Unearned General Education Revenue (GNL 214) was used in "&Instructions!R3&", enough general ed payments should" -> If the Advance of Unearned General Education Revenue (GNL 214) was used in FY 2013, enough general ed payments should
B55: have been coded to 214 to zero out the account. If not, the following entry should be made:
E56: Debit | F56: Credit
A57: REV | B57: 01-005-000-000-211-000 | C57: Gen Ed Revenue | E57: =F59 -> 113799.41
A58: REV | B58: 04-005-000-000-211-000 | C58: Gen Ed Revenue | E58: =F60 -> 0
A59: GNL | B59: 01-214 | C59: Adv of Unearned Gen Ed | F59: =-VLOOKUP($A$3,Ideas,7) -> 113799.41
A60: GNL | B60: 04-214 | C60: Adv of Unearned Gen Ed | F60: =-VLOOKUP($A$3,Ideas,8) -> 0
A64: 3) | B64: ="The "&Instructions!R2&" tax shift payment adjustments reflected on the IDEAS reports should have been recorded to source 299." -> The FY 2014 tax shift payment adjustments reflected on the IDEAS reports should have been recorded to source 299.
B65: If not, the following entries should be made:
E66: Debit | F66: Credit
A67: REV | B67: 01-005-000-000-299-000 | C67: Prop Tax Shift Adjustment | E67: =IF(H18<=0,-H18," ") | F67: =IF(H18<=0," ",H18) -> 354088.31
A68: REV | B68: 04-005-000-000-299-000 | C68: Prop Tax Shift Adjustment | E68: =IF(H23<=0,-H23," ") -> 0 | F68: =IF(H23<=0," ",H23)
A69: REV | B69: 01-005-000-XXX-XXX-000 | C69: State Aid Receivable or State Aid Revenue | E69: =F67 -> 354088.31 | F69: =E67
A70: REV | B70: 04-005-000-XXX-XXX-000 | C70: State Aid Receivable or State Aid Revenue | E70: =F68 | F70: =E68 -> 0
A72: ="ENTER: May/June/July "&RIGHT(Instructions!R2,4)&" Receipts for:" -> ENTER: May/June/July 2014 Receipts for: | E72: General Fund | F72: Comm Service Fund
B74: =Instructions!P1&" Real Estate and Personal Property Taxes" -> Pay 2014 Real Estate and Personal Property Taxes | E74: =VLOOKUP($A3,Receipts!$A$7:$L$338,5,FALSE) -> 424563.77 | F74: =VLOOKUP($A3,Receipts!$A$7:$L$338,10,FALSE) -> 0 | H74: Note: District should override when actual data is available
B75: =Instructions!P2&" and earlier Real Estate and Personal Property Taxes" -> Pay 2013 and earlier Real Estate and Personal Property Taxes | E75: 0 | F75: 0
B76: =Instructions!P1&" Fiscal Disparities" -> Pay 2014 Fiscal Disparities | E76: 0 | F76: 0
B77: =Instructions!P1&" Taconite Homestead Credit" -> Pay 2014 Taconite Homestead Credit | E77: 0 | F77: 0
B78: Mobile Home Taxes | E78: 0 | F78: 0
B80: Total May/June/July Tax Settlement Receipts | E80: =SUM(E74:E78) -> 424563.77 | F80: =SUM(F74:F78) -> 0
A82: =$A$3 -> 1 | B82: =VLOOKUP($A$3,ShiftCY,3) -> AITKIN | I82: =Instructions!$M$1 -> 41828
A83: ="Entry to record June "&RIGHT(Instructions!R2,4)&" property tax shift" -> Entry to record June 2014 property tax shift | E83: Debit (Credit) | F83: Credit (Debit)
A85: GNL | B85: 01-235 | C85: Prop Tax Sub Years | E85: =IF(C18<E80,C18,E80) -> 178003.41 | H85: ="Column "&C6&" - line "&A18 -> Column 1 - line J
B86: 01-214 | C86: Adv of Unearned Gen Ed | E86: =IF(C18-E85<0,0,C18-E85) -> 0
A87: GNL | B87: 04-235 | C87: Prop Tax Sub Years | E87: =IF(C23<F80,C23,F80) -> 0 | H87: ="Column "&C6&" - line "&A23 -> Column 1 - line N
B88: 04-214 | C88: Adv of Unearned Gen Ed | E88: =C23-E87 -> 0
B89: ="(recognition of gross shift for "&Instructions!R2&")" -> (recognition of gross shift for FY 2014)
A90: line left blank intentionally
A91: REV | B91: 01-005-000-000-001-000 | C91: Local Property Taxes--Reemployment | F91: =C15 -> 0 | H91: ="Column "&C6&" - line "&A15 -> Column 1 - line G
A92: REV | B92: 01-005-000-830-001-000 | C92: Local Property Taxes--Career Technical | F92: =C13-F93 -> 30163.77 | H92: ="Column "&C6&" - line "&A13 -> Column 1 - line E
A93: REV | B93: 01-005-000-830-211-000 (if not enough tax receipts) | C93: Gen Ed Revenue--Career Technical | F93: =MIN(E86-F95,C13) -> 0
A94: REV | B94: 01-005-000-000-001-000 | C94: Local Property Taxes | F94: =C11+C12+C14+C16+C17-F95 -> 147839.64 | H94: ="Column "&C6&" - line "&A11&"+"&A12&"+"&A14&"+"&A16&"+"&A17 -> Column 1 - line C+D+F+H+I
A95: REV | B95: 01-005-000-000-211-000 (if not enough tax receipts) | C95: Gen Ed Revenue | F95: =MIN(E86,MAX(0,C11+C12+C14+C16+C17)) -> 0
A96: REV | B96: 04-005-000-XXX-001-000 | C96: Local Property Taxes | F96: =C21+C22-F97 -> 0 | H96: ="Column "&C6&" - line "&A21&"+"&A22 -> Column 1 - line L+M
A97: REV | B97: 04-005-000-XXX-211-000 | C97: Gen Ed Revenue | F97: =E88 -> 0
B98: ="(spread of early recognition items for "&Instructions!R2&")" -> (spread of early recognition items for FY 2014)
A99: line left blank intentionally
A100: REV | B100: 01-005-000-000-211-000 | C100: Gen Ed Revenue | F100: =E86-F93-F95 -> 0 | H100: Entry to GNL 214 minus entries to SRC 211
A101: REV | B101: 01-005-000-000-296-000 | C101: Property Tax Shift Offset Adjustment | E101: =F100 -> 0
A102: REV | B102: 04-005-000-000-211-000 | C102: Gen Ed Revenue | F102: =E88-F97 -> 0 | H102: Entry toGNL 214 minus entries to SRC 211
A103: REV | B103: 04-005-000-000-296-000 | C103: Property Tax Shift Offset Adjustment | E103: =F102 -> 0
B104: (adjustment to balance GNL 214 account with SRC 211)
A105: line left blank intentionally
A106: REV | B106: 01-005-000-000-001-000 | C106: Local Property Taxes | F106: =D9+D10 -> 348692.74 | H106: ="Column "&D6&" - line "&A9&"+"&A10 -> Column 2 - line A+B
A107: REV | B107: 04-005-000-XXX-001-000 | C107: Local Property Taxes | F107: =D20 -> 5395.57 | H107: ="Column "&D6&" - line "&A20 -> Column 2 - line K
B108: (reverse prior year shift)
A109: line left blank intentionally
A110: REV | B110: 01-005-000-000-020-000 | C110: Prop Tax Shift Revenue | E110: =IF($F18<0,-$F18," ") -> 348692.74 | F110: =IF($F18<0," ",$F18) | H110: ="Column "&F6&" - line "&A18 -> Column 4 - line J
A111: REV | B111: 04-005-000-000-020-000 | C111: Prop Tax Shift Revenue | E111: =IF($F23<0,-$F23," ") -> 5395.57 | F111: =IF($F23<0," ",$F23) | H111: ="Column "&F6&" - line "&A23 -> Column 4 - line N
B112: ="(spread of tax shift amount for "&Instructions!R2&")" -> (spread of tax shift amount for FY 2014)
A113: line left blank intentionally
B114: Total | E114: =SUM(E85:E113) -> 532091.72 | F114: =SUM(F85:F113) -> 532091.72
A115: line left blank intentionally
A116: REV | B116: 01-005-000-000-299-000 | C116: State Aid Adjustment for Shift | E116: =IF(I18<0,-I18," ") -> 5395.57 | F116: =IF(I18<0," ",I18) | H116: ="Column "&I6&" - line "&A18 -> Column 6 - line J
A117: GNL | B117: 01-101 | C117: Cash | E117: =F116 | F117: =E116 -> 5395.57
A118: REV | B118: 04-005-000-000-299-000 | C118: State Aid Adjustment for Shift | E118: =IF(I23<0,-I23," ") | F118: =IF(I23<0," ",I23) -> 5395.57 | H118: ="Column "&I6&" - line "&A23 -> Column 6 - line N
...

Sheet Funds
A1: Enter certified levies for each year below | K1: =Report!I1 -> 41828 | L1: rest of line left blank
A2: This data is used to report certified levies on Accounts tab | L2: rest of line left blank
A3: Also used to allocate adjustments and abatements on Accounts tab | L3: rest of line left blank
A4: n/a | B4: n/a | C4: n/a | D4: Certified Levy | L4: rest of line left blank
A5: n/a | B5: n/a | C5: n/a | D5: =Instructions!P1 -> Pay 2014 | E5: =Instructions!P2 -> Pay 2013 | F5: =Instructions!P3 -> Pay 2012 | G5: =Instructions!P4 -> Pay 2011 | H5: =Instructions!P5 -> Pay 2010 | I5: =Instructions!P6 -> Pay 2009 | J5: =Instructions!P7 -> Pay 2008 | K5: =Instructions!P8 -> Pay 2007 | L5: rest of line left blank
A6: n/a | B6: General | C6: n/a | D6: 0 | E6: 0 | F6: 0 | G6: 0 | H6: 0 | I6: 0 | J6: 0 | K6: 0 | L6: rest of line left blank
A7: n/a | B7: Community Serv | D7: 0 | E7: 0 | F7: 0 | G7: 0 | H7: 0 | I7: 0 | J7: 0 | K7: 0 | L7: rest of line left blank
A8: n/a | B8: Debt Service | C8: n/a | D8: 0 | E8: 0 | F8: 0 | G8: 0 | H8: 0 | I8: 0 | J8: 0 | K8: 0 | L8: rest of line left blank
A9: n/a | B9: OPEB | C9: n/a | D9: 0 | E9: 0 | F9: 0 | G9: 0 | H9: 0 | I9: 0 | J9: 0 | K9: 0 | L9: rest of line left blank
A10: line left blank intentionally | L10: rest of line left blank
A11: n/a | B11: Total Certified Levy | D11: =SUM(D6:D10) -> 0 | E11: =SUM(E6:E10) -> 0 | F11: =SUM(F6:F10) -> 0 | G11: =SUM(G6:G10) -> 0 | H11: =SUM(H6:H10) -> 0 | I11: =SUM(I6:I10) -> 0 | J11: =SUM(J6:J10) -> 0 | K11: =SUM(K6:K10) -> 0 | L11: rest of line left blank
A12: ="Enter each tax settlement received July 1, "&RIGHT(Instructions!P2,4)&" through June 30, "&RIGHT(Instructions!P1,4) -> Enter each tax settlement received July 1, 2013 through June 30, 2014 | G12: rest of line left blank
A13: Enter data in green highlighted cells | F13: rest of line left blank
A14: If more columns are needed, insert between column M and S | F14: rest of line left blank
A15: Amounts will be allocated to funds based upon certified levies above | F15: rest of line left blank
A16: Settlements will be totaled by year and fund for carryover to Accounts tab | F16: rest of line left blank
A17: line left blank intentionally | F17: rest of line left blank
A18: If settlement sheet from the county already shows settlements by fund: | G18: rest of line left blank
A19: Unprotect this tab and enter settlement data directly into cells E56 through S145, orange outlined section below | H19: rest of line left blank
A20: Caution: You will be overriding the formulas in these cells | E20: rest of line left blank
A21: n/a | B21: n/a | C21: n/a | D21: n/a | E21: County | F21: County | G21: County | H21: County | I21: County | J21: County | K21: County | L21: County | M21: County | N21: County | O21: County | P21: County | Q21: County | R21: County | S21: County
A22: n/a | B22: n/a | C22: n/a | D22: Total | E22: Date | F22: Date | G22: Date | H22: Date | I22: Date | J22: Date | K22: Date | L22: Date | M22: Date | N22: Date | O22: Date | P22: Date | Q22: Date | R22: Date | S22: Date
A24: Taxes receivable | C24: =Instructions!P1 -> Pay 2014 | D24: =SUM(E24:S24) -> 0 | E24: 0 | F24: 0 | G24: 0 | H24: 0 | I24: 0 | J24: 0 | K24: 0 | L24: 0 | M24: 0 | N24: 0 | O24: 0 | P24: 0 | Q24: 0 | R24: 0 | S24: 0
A25: n/a | B25: n/a | C25: =Instructions!P2 -> Pay 2013 | D25: =SUM(E25:S25) -> 0 | E25: 0 | F25: 0 | G25: 0 | H25: 0 | I25: 0 | J25: 0 | K25: 0 | L25: 0 | M25: 0 | N25: 0 | O25: 0 | P25: 0 | Q25: 0 | R25: 0 | S25: 0
A26: n/a | B26: n/a | C26: =Instructions!P3 -> Pay 2012 | D26: =SUM(E26:S26) -> 0 | E26: 0 | F26: 0 | G26: 0 | H26: 0 | I26: 0 | J26: 0 | K26: 0 | L26: 0 | M26: 0 | N26: 0 | O26: 0 | P26: 0 | Q26: 0 | R26: 0 | S26: 0
A27: n/a | B27: n/a | C27: =Instructions!P4 -> Pay 2011 | D27: =SUM(E27:S27) -> 0 | E27: 0 | F27: 0 | G27: 0 | H27: 0 | I27: 0 | J27: 0 | K27: 0 | L27: 0 | M27: 0 | N27: 0 | O27: 0 | P27: 0 | Q27: 0 | R27: 0 | S27: 0
A28: n/a | B28: n/a | C28: =Instructions!P5 -> Pay 2010 | D28: =SUM(E28:S28) -> 0 | E28: 0 | F28: 0 | G28: 0 | H28: 0 | I28: 0 | J28: 0 | K28: 0 | L28: 0 | M28: 0 | N28: 0 | O28: 0 | P28: 0 | Q28: 0 | R28: 0 | S28: 0
A29: n/a | B29: n/a | C29: =Instructions!P6 -> Pay 2009 | D29: =SUM(E29:S29) -> 0 | E29: 0 | F29: 0 | G29: 0 | H29: 0 | I29: 0 | J29: 0 | K29: 0 | L29: 0 | M29: 0 | N29: 0 | O29: 0 | P29: 0 | Q29: 0 | R29: 0 | S29: 0
A30: n/a | B30: n/a | C30: =Instructions!P7 -> Pay 2008 | D30: =SUM(E30:S30) -> 0 | E30: 0 | F30: 0 | G30: 0 | H30: 0 | I30: 0 | J30: 0 | K30: 0 | L30: 0 | M30: 0 | N30: 0 | O30: 0 | P30: 0 | Q30: 0 | R30: 0 | S30: 0
A31: n/a | B31: n/a | C31: =Instructions!P8 -> Pay 2007 | D31: =SUM(E31:S31) -> 0 | E31: 0 | F31: 0 | G31: 0 | H31: 0 | I31: 0 | J31: 0 | K31: 0 | L31: 0 | M31: 0 | N31: 0 | O31: 0 | P31: 0 | Q31: 0 | R31: 0 | S31: 0
A32: Fiscal disparities | C32: =Instructions!P1 -> Pay 2014 | D32: =SUM(E32:S32) -> 0 | E32: 0 | F32: 0 | G32: 0 | H32: 0 | I32: 0 | J32: 0 | K32: 0 | L32: 0 | M32: 0 | N32: 0 | O32: 0 | P32: 0 | Q32: 0 | R32: 0 | S32: 0
A33: n/a | B33: n/a | C33: =Instructions!P2 -> Pay 2013 | D33: =SUM(E33:S33) -> 0 | E33: 0 | F33: 0 | G33: 0 | H33: 0 | I33: 0 | J33: 0 | K33: 0 | L33: 0 | M33: 0 | N33: 0 | O33: 0 | P33: 0 | Q33: 0 | R33: 0 | S33: 0
A34: Taconite homestead | C34: =Instructions!P1 -> Pay 2014 | D34: =SUM(E34:S34) -> 0 | E34: 0 | F34: 0 | G34: 0 | H34: 0 | I34: 0 | J34: 0 | K34: 0 | L34: 0 | M34: 0 | N34: 0 | O34: 0 | P34: 0 | Q34: 0 | R34: 0 | S34: 0
A35: n/a | B35: n/a | C35: =Instructions!P2 -> Pay 2013 | D35: =SUM(E35:S35) -> 0 | E35: 0 | F35: 0 | G35: 0 | H35: 0 | I35: 0 | J35: 0 | K35: 0 | L35: 0 | M35: 0 | N35: 0 | O35: 0 | P35: 0 | Q35: 0 | R35: 0 | S35: 0
A36: Miscellaneous taxes | E36: 0 | F36: 0 | G36: 0 | H36: 0 | I36: 0 | J36: 0 | K36: 0 | L36: 0 | M36: 0 | N36: 0 | O36: 0 | P36: 0 | Q36: 0 | R36: 0 | S36: 0
A37: line left blank intentionally
A38: n/a | B38: Total settlement | D38: =SUM(D24:D37) -> 0 | E38: =SUM(E24:E37) -> 0 | F38: =SUM(F24:F37) -> 0 | G38: =SUM(G24:G37) -> 0 | H38: =SUM(H24:H37) -> 0 | I38: =SUM(I24:I37) -> 0 | J38: =SUM(J24:J37) -> 0 | K38: =SUM(K24:K37) -> 0 | ... S38: =SUM(S24:S37) -> 0
A39: Current Taxes receivable
A40: n/a | B40: =Instructions!P1 -> Pay 2014 | C40: General | D40: =SUM(E40:S40) -> 0 | E40: =ROUND(IF($D$11=0,0,E$24/$D$11*$D6),2) -> 0 | F40: =ROUND(IF($D$11=0,0,F$24/$D$11*$D6),2) -> 0 | G40: =ROUND(IF($D$11=0,0,G$24/$D$11*$D6),2) -> 0 | H40: =ROUND(IF($D$11=0,0,H$24/$D$11*$D6),2) -> 0 | I40: =ROUND(IF($D$11=0,0,I$24/$D$11*$D6),2) -> 0 | J40: =ROUND(IF($D$11=0,0,J$24/$D$11*$D6),2) -> 0 | K40: =ROUND(IF($D$11=0,0,K$24/$D$11*$D6),2) -> 0 | L40: =ROUND(IF($D$11=0,0,L$24/$D$11*$D6),2) -> 0 | ... S40: =ROUND(IF($D$11=0,0,S$24/$D$11*$D6),2) -> 0
A41: n/a | B41: =Instructions!P1 -> Pay 2014 | C41: Comm Serv | D41: =SUM(E41:S41) -> 0 | E41: =ROUND(IF($D$11=0,0,E$24/$D$11*$D7),2) -> 0 | F41: =ROUND(IF($D$11=0,0,F$24/$D$11*$D7),2) -> 0 | G41: =ROUND(IF($D$11=0,0,G$24/$D$11*$D7),2) -> 0 | H41: =ROUND(IF($D$11=0,0,H$24/$D$11*$D7),2) -> 0 | I41: =ROUND(IF($D$11=0,0,I$24/$D$11*$D7),2) -> 0 | J41: =ROUND(IF($D$11=0,0,J$24/$D$11*$D7),2) -> 0 | K41: =ROUND(IF($D$11=0,0,K$24/$D$11*$D7),2) -> 0 | L41: =ROUND(IF($D$11=0,0,L$24/$D$11*$D7),2) -> 0 | ... S41: =ROUND(IF($D$11=0,0,S$24/$D$11*$D7),2) -> 0
A42: n/a | B42: =Instructions!P1 -> Pay 2014 | C42: Debt Serv | D42: =SUM(E42:S42) -> 0 | E42: =ROUND(IF($D$11=0,0,E$24/$D$11*$D8),2) -> 0 | F42: =ROUND(IF($D$11=0,0,F$24/$D$11*$D8),2) -> 0 | G42: =ROUND(IF($D$11=0,0,G$24/$D$11*$D8),2) -> 0 | H42: =ROUND(IF($D$11=0,0,H$24/$D$11*$D8),2) -> 0 | I42: =ROUND(IF($D$11=0,0,I$24/$D$11*$D8),2) -> 0 | J42: =ROUND(IF($D$11=0,0,J$24/$D$11*$D8),2) -> 0 | K42: =ROUND(IF($D$11=0,0,K$24/$D$11*$D8),2) -> 0 | L42: =ROUND(IF($D$11=0,0,L$24/$D$11*$D8),2) -> 0 | ... S42: =ROUND(IF($D$11=0,0,S$24/$D$11*$D8),2) -> 0
A43: n/a | B43: =Instructions!P1 -> Pay 2014 | C43: OPEB | D43: =SUM(E43:S43) -> 0 | E43: =ROUND(IF($D$11=0,0,E$24/$D$11*$D9),2) -> 0 | F43: =ROUND(IF($D$11=0,0,F$24/$D$11*$D9),2) -> 0 | G43: =ROUND(IF($D$11=0,0,G$24/$D$11*$D9),2) -> 0 | H43: =ROUND(IF($D$11=0,0,H$24/$D$11*$D9),2) -> 0 | I43: =ROUND(IF($D$11=0,0,I$24/$D$11*$D9),2) -> 0 | J43: =ROUND(IF($D$11=0,0,J$24/$D$11*$D9),2) -> 0 | K43: =ROUND(IF($D$11=0,0,K$24/$D$11*$D9),2) -> 0 | L43: =ROUND(IF($D$11=0,0,L$24/$D$11*$D9),2) -> 0 | ... S43: =ROUND(IF($D$11=0,0,S$24/$D$11*$D9),2) -> 0
A44: line left blank intentionally
A45: n/a | B45: n/a | C45: Subtotal | D45: =SUM(D40:D44) -> 0 | E45: =SUM(E40:E44) -> 0 | F45: =SUM(F40:F44) -> 0 | G45: =SUM(G40:G44) -> 0 | H45: =SUM(H40:H44) -> 0 | I45: =SUM(I40:I44) -> 0 | J45: =SUM(J40:J44) -> 0 | K45: =SUM(K40:K44) -> 0 | ... S45: =SUM(S40:S44) -> 0
A46: line left blank intentionally
A47: line left blank intentionally
A48: Delinquent Taxes receivable
A49: n/a | B49: =Instructions!P2 -> Pay 2013 | C49: General | D49: =SUM(E49:S49) -> 0 | E49: =ROUND(IF($E$11=0,0,E$25/$E$11*$E6),2) -> 0 | F49: =ROUND(IF($E$11=0,0,F$25/$E$11*$E6),2) -> 0 | G49: =ROUND(IF($E$11=0,0,G$25/$E$11*$E6),2) -> 0 | H49: =ROUND(IF($E$11=0,0,H$25/$E$11*$E6),2) -> 0 | I49: =ROUND(IF($E$11=0,0,I$25/$E$11*$E6),2) -> 0 | J49: =ROUND(IF($E$11=0,0,J$25/$E$11*$E6),2) -> 0 | K49: =ROUND(IF($E$11=0,0,K$25/$E$11*$E6),2) -> 0 | L49: =ROUND(IF($E$11=0,0,L$25/$E$11*$E6),2) -> 0 | ... S49: =ROUND(IF($E$11=0,0,S$25/$E$11*$E6),2) -> 0
A50: n/a | B50: =Instructions!P3 -> Pay 2012 | C50: General | D50: =SUM(E50:S50) -> 0 | E50: =ROUND(IF($F$11=0,0,E$26/$F$11*$F6),2) -> 0 | F50: =ROUND(IF($F$11=0,0,F$26/$F$11*$F6),2) -> 0 | G50: =ROUND(IF($F$11=0,0,G$26/$F$11*$F6),2) -> 0 | H50: =ROUND(IF($F$11=0,0,H$26/$F$11*$F6),2) -> 0 | I50: =ROUND(IF($F$11=0,0,I$26/$F$11*$F6),2) -> 0 | J50: =ROUND(IF($F$11=0,0,J$26/$F$11*$F6),2) -> 0 | K50: =ROUND(IF($F$11=0,0,K$26/$F$11*$F6),2) -> 0 | L50: =ROUND(IF($F$11=0,0,L$26/$F$11*$F6),2) -> 0 | ... S50: =ROUND(IF($F$11=0,0,S$26/$F$11*$F6),2) -> 0
A51: n/a | B51: =Instructions!P4 -> Pay 2011 | C51: General | D51: =SUM(E51:S51) -> 0 | E51: =ROUND(IF($G$11=0,0,E$27/$G$11*$G6),2) -> 0 | F51: =ROUND(IF($G$11=0,0,F$27/$G$11*$G6),2) -> 0 | G51: =ROUND(IF($G$11=0,0,G$27/$G$11*$G6),2) -> 0 | H51: =ROUND(IF($G$11=0,0,H$27/$G$11*$G6),2) -> 0 | I51: =ROUND(IF($G$11=0,0,I$27/$G$11*$G6),2) -> 0 | J51: =ROUND(IF($G$11=0,0,J$27/$G$11*$G6),2) -> 0 | K51: =ROUND(IF($G$11=0,0,K$27/$G$11*$G6),2) -> 0 | L51: =ROUND(IF($G$11=0,0,L$27/$G$11*$G6),2) -> 0 | ... S51: =ROUND(IF($G$11=0,0,S$27/$G$11*$G6),2) -> 0
A52: n/a | B52: =Instructions!P5 -> Pay 2010 | C52: General | D52: =SUM(E52:S52) -> 0 | E52: =ROUND(IF($H$11=0,0,E$28/$H$11*$H6),2) -> 0 | F52: =ROUND(IF($H$11=0,0,F$28/$H$11*$H6),2) -> 0 | G52: =ROUND(IF($H$11=0,0,G$28/$H$11*$H6),2) -> 0 | H52: =ROUND(IF($H$11=0,0,H$28/$H$11*$H6),2) -> 0 | I52: =ROUND(IF($H$11=0,0,I$28/$H$11*$H6),2) -> 0 | J52: =ROUND(IF($H$11=0,0,J$28/$H$11*$H6),2) -> 0 | K52: =ROUND(IF($H$11=0,0,K$28/$H$11*$H6),2) -> 0 | L52: =ROUND(IF($H$11=0,0,L$28/$H$11*$H6),2) -> 0 | ... S52: =ROUND(IF($H$11=0,0,S$28/$H$11*$H6),2) -> 0
A53: n/a | B53: =Instructions!P6 -> Pay 2009 | C53: General | D53: =SUM(E53:S53) -> 0 | E53: =ROUND(IF($I$11=0,0,E$29/$I$11*$I6),2) -> 0 | F53: =ROUND(IF($I$11=0,0,F$29/$I$11*$I6),2) -> 0 | G53: =ROUND(IF($I$11=0,0,G$29/$I$11*$I6),2) -> 0 | H53: =ROUND(IF($I$11=0,0,H$29/$I$11*$I6),2) -> 0 | I53: =ROUND(IF($I$11=0,0,I$29/$I$11*$I6),2) -> 0 | J53: =ROUND(IF($I$11=0,0,J$29/$I$11*$I6),2) -> 0 | K53: =ROUND(IF($I$11=0,0,K$29/$I$11*$I6),2) -> 0 | L53: =ROUND(IF($I$11=0,0,L$29/$I$11*$I6),2) -> 0 | ... S53: =ROUND(IF($I$11=0,0,S$29/$I$11*$I6),2) -> 0
A54: n/a | B54: =Instructions!P7 -> Pay 2008 | C54: General | D54: =SUM(E54:S54) -> 0 | E54: =ROUND(IF($J$11=0,0,E$30/$J$11*$J6),2) -> 0 | F54: =ROUND(IF($J$11=0,0,F$30/$J$11*$J6),2) -> 0 | G54: =ROUND(IF($J$11=0,0,G$30/$J$11*$J6),2) -> 0 | H54: =ROUND(IF($J$11=0,0,H$30/$J$11*$J6),2) -> 0 | I54: =ROUND(IF($J$11=0,0,I$30/$J$11*$J6),2) -> 0 | J54: =ROUND(IF($J$11=0,0,J$30/$J$11*$J6),2) -> 0 | K54: =ROUND(IF($J$11=0,0,K$30/$J$11*$J6),2) -> 0 | L54: =ROUND(IF($J$11=0,0,L$30/$J$11*$J6),2) -> 0 | ... S54: =ROUND(IF($J$11=0,0,S$30/$J$11*$J6),2) -> 0
A55: n/a | B55: =Instructions!P8 -> Pay 2007 | C55: General | D55: =SUM(E55:S55) -> 0 | E55: =ROUND(IF($K$11=0,0,E$31/$K$11*$K6),2) -> 0 | F55: =ROUND(IF($K$11=0,0,F$31/$K$11*$K6),2) -> 0 | G55: =ROUND(IF($K$11=0,0,G$31/$K$11*$K6),2) -> 0 | H55: =ROUND(IF($K$11=0,0,H$31/$K$11*$K6),2) -> 0 | I55: =ROUND(IF($K$11=0,0,I$31/$K$11*$K6),2) -> 0 | J55: =ROUND(IF($K$11=0,0,J$31/$K$11*$K6),2) -> 0 | K55: =ROUND(IF($K$11=0,0,K$31/$K$11*$K6),2) -> 0 | L55: =ROUND(IF($K$11=0,0,L$31/$K$11*$K6),2) -> 0 | ... S55: =ROUND(IF($K$11=0,0,S$31/$K$11*$K6),2) -> 0
A56: line left blank intentionally
A57: n/a | B57: n/a | C57: Subtotal | D57: =SUM(D49:D56) -> 0 | E57: =SUM(E49:E56) -> 0 | F57: =SUM(F49:F56) -> 0 | G57: =SUM(G49:G56) -> 0 | H57: =SUM(H49:H56) -> 0 | I57: =SUM(I49:I56) -> 0 | J57: =SUM(J49:J56) -> 0 | K57: =SUM(K49:K56) -> 0 | ... S57: =SUM(S49:S56) -> 0
A58: line left blank intentionally
A59: line left blank intentionally
A60: n/a | B60: =Instructions!P2 -> Pay 2013 | C60: Comm Serv | D60: =SUM(E60:S60) -> 0 | E60: =ROUND(IF($E$11=0,0,E$25/$E$11*$E7),2) -> 0 | F60: =ROUND(IF($E$11=0,0,F$25/$E$11*$E7),2) -> 0 | G60: =ROUND(IF($E$11=0,0,G$25/$E$11*$E7),2) -> 0 | H60: =ROUND(IF($E$11=0,0,H$25/$E$11*$E7),2) -> 0 | I60: =ROUND(IF($E$11=0,0,I$25/$E$11*$E7),2) -> 0 | J60: =ROUND(IF($E$11=0,0,J$25/$E$11*$E7),2) -> 0 | K60: =ROUND(IF($E$11=0,0,K$25/$E$11*$E7),2) -> 0 | L60: =ROUND(IF($E$11=0,0,L$25/$E$11*$E7),2) -> 0 | ... S60: =ROUND(IF($E$11=0,0,S$25/$E$11*$E7),2) -> 0
A61: n/a | B61: =Instructions!P3 -> Pay 2012 | C61: Comm Serv | D61: =SUM(E61:S61) -> 0 | E61: =ROUND(IF($F$11=0,0,E$26/$F$11*$F7),2) -> 0 | F61: =ROUND(IF($F$11=0,0,F$26/$F$11*$F7),2) -> 0 | G61: =ROUND(IF($F$11=0,0,G$26/$F$11*$F7),2) -> 0 | H61: =ROUND(IF($F$11=0,0,H$26/$F$11*$F7),2) -> 0 | I61: =ROUND(IF($F$11=0,0,I$26/$F$11*$F7),2) -> 0 | J61: =ROUND(IF($F$11=0,0,J$26/$F$11*$F7),2) -> 0 | K61: =ROUND(IF($F$11=0,0,K$26/$F$11*$F7),2) -> 0 | L61: =ROUND(IF($F$11=0,0,L$26/$F$11*$F7),2) -> 0 | ... S61: =ROUND(IF($F$11=0,0,S$26/$F$11*$F7),2) -> 0
A62: n/a | B62: =Instructions!P4 -> Pay 2011 | C62: Comm Serv | D62: =SUM(E62:S62) -> 0 | E62: =ROUND(IF($G$11=0,0,E$27/$G$11*$G7),2) -> 0 | F62: =ROUND(IF($G$11=0,0,F$27/$G$11*$G7),2) -> 0 | G62: =ROUND(IF($G$11=0,0,G$27/$G$11*$G7),2) -> 0 | H62: =ROUND(IF($G$11=0,0,H$27/$G$11*$G7),2) -> 0 | I62: =ROUND(IF($G$11=0,0,I$27/$G$11*$G7),2) -> 0 | J62: =ROUND(IF($G$11=0,0,J$27/$G$11*$G7),2) -> 0 | K62: =ROUND(IF($G$11=0,0,K$27/$G$11*$G7),2) -> 0 | L62: =ROUND(IF($G$11=0,0,L$27/$G$11*$G7),2) -> 0 | ... S62: =ROUND(IF($G$11=0,0,S$27/$G$11*$G7),2) -> 0
A63: n/a | B63: =Instructions!P5 -> Pay 2010 | C63: Comm Serv | D63: =SUM(E63:S63) -> 0 | E63: =ROUND(IF($H$11=0,0,E$28/$H$11*$H7),2) -> 0 | F63: =ROUND(IF($H$11=0,0,F$28/$H$11*$H7),2) -> 0 | G63: =ROUND(IF($H$11=0,0,G$28/$H$11*$H7),2) -> 0 | H63: =ROUND(IF($H$11=0,0,H$28/$H$11*$H7),2) -> 0 | I63: =ROUND(IF($H$11=0,0,I$28/$H$11*$H7),2) -> 0 | J63: =ROUND(IF($H$11=0,0,J$28/$H$11*$H7),2) -> 0 | K63: =ROUND(IF($H$11=0,0,K$28/$H$11*$H7),2) -> 0 | L63: =ROUND(IF($H$11=0,0,L$28/$H$11*$H7),2) -> 0 | ... S63: =ROUND(IF($H$11=0,0,S$28/$H$11*$H7),2) -> 0
A64: n/a | B64: =Instructions!P6 -> Pay 2009 | C64: Comm Serv | D64: =SUM(E64:S64) -> 0 | E64: =ROUND(IF($I$11=0,0,E$29/$I$11*$I7),2) -> 0 | F64: =ROUND(IF($I$11=0,0,F$29/$I$11*$I7),2) -> 0 | G64: =ROUND(IF($I$11=0,0,G$29/$I$11*$I7),2) -> 0 | H64: =ROUND(IF($I$11=0,0,H$29/$I$11*$I7),2) -> 0 | I64: =ROUND(IF($I$11=0,0,I$29/$I$11*$I7),2) -> 0 | J64: =ROUND(IF($I$11=0,0,J$29/$I$11*$I7),2) -> 0 | K64: =ROUND(IF($I$11=0,0,K$29/$I$11*$I7),2) -> 0 | L64: =ROUND(IF($I$11=0,0,L$29/$I$11*$I7),2) -> 0 | ... S64: =ROUND(IF($I$11=0,0,S$29/$I$11*$I7),2) -> 0
A65: n/a | B65: =Instructions!P7 -> Pay 2008 | C65: Comm Serv | D65: =SUM(E65:S65) -> 0 | E65: =ROUND(IF($J$11=0,0,E$30/$J$11*$J7),2) -> 0 | F65: =ROUND(IF($J$11=0,0,F$30/$J$11*$J7),2) -> 0 | G65: =ROUND(IF($J$11=0,0,G$30/$J$11*$J7),2) -> 0 | H65: =ROUND(IF($J$11=0,0,H$30/$J$11*$J7),2) -> 0 | I65: =ROUND(IF($J$11=0,0,I$30/$J$11*$J7),2) -> 0 | J65: =ROUND(IF($J$11=0,0,J$30/$J$11*$J7),2) -> 0 | K65: =ROUND(IF($J$11=0,0,K$30/$J$11*$J7),2) -> 0 | L65: =ROUND(IF($J$11=0,0,L$30/$J$11*$J7),2) -> 0 | ... S65: =ROUND(IF($J$11=0,0,S$30/$J$11*$J7),2) -> 0
A66: n/a | B66: =Instructions!P8 -> Pay 2007 | C66: Comm Serv | D66: =SUM(E66:S66) -> 0 | E66: =ROUND(IF($K$11=0,0,E$31/$K$11*$K7),2) -> 0 | F66: =ROUND(IF($K$11=0,0,F$31/$K$11*$K7),2) -> 0 | G66: =ROUND(IF($K$11=0,0,G$31/$K$11*$K7),2) -> 0 | H66: =ROUND(IF($K$11=0,0,H$31/$K$11*$K7),2) -> 0 | I66: =ROUND(IF($K$11=0,0,I$31/$K$11*$K7),2) -> 0 | J66: =ROUND(IF($K$11=0,0,J$31/$K$11*$K7),2) -> 0 | K66: =ROUND(IF($K$11=0,0,K$31/$K$11*$K7),2) -> 0 | L66: =ROUND(IF($K$11=0,0,L$31/$K$11*$K7),2) -> 0 | ... S66: =ROUND(IF($K$11=0,0,S$31/$K$11*$K7),2) -> 0
A67: line left blank intentionally
A68: n/a | B68: n/a | C68: Subtotal | D68: =SUM(D60:D67) -> 0 | E68: =SUM(E60:E67) -> 0 | F68: =SUM(F60:F67) -> 0 | G68: =SUM(G60:G67) -> 0 | H68: =SUM(H60:H67) -> 0 | I68: =SUM(I60:I67) -> 0 | J68: =SUM(J60:J67) -> 0 | K68: =SUM(K60:K67) -> 0 | ... S68: =SUM(S60:S67) -> 0
A69: line left blank intentionally
A70: line left blank intentionally
A71: n/a | B71: =Instructions!P2 -> Pay 2013 | C71: Debt Serv | D71: =SUM(E71:S71) -> 0 | E71: =ROUND(IF($E$11=0,0,E$25/$E$11*$E8),2) -> 0 | F71: =ROUND(IF($E$11=0,0,F$25/$E$11*$E8),2) -> 0 | G71: =ROUND(IF($E$11=0,0,G$25/$E$11*$E8),2) -> 0 | H71: =ROUND(IF($E$11=0,0,H$25/$E$11*$E8),2) -> 0 | I71: =ROUND(IF($E$11=0,0,I$25/$E$11*$E8),2) -> 0 | J71: =ROUND(IF($E$11=0,0,J$25/$E$11*$E8),2) -> 0 | K71: =ROUND(IF($E$11=0,0,K$25/$E$11*$E8),2) -> 0 | L71: =ROUND(IF($E$11=0,0,L$25/$E$11*$E8),2) -> 0 | ... S71: =ROUND(IF($E$11=0,0,S$25/$E$11*$E8),2) -> 0
A72: n/a | B72: =Instructions!P3 -> Pay 2012 | C72: Debt Serv | D72: =SUM(E72:S72) -> 0 | E72: =ROUND(IF($F$11=0,0,E$26/$F$11*$F8),2) -> 0 | F72: =ROUND(IF($F$11=0,0,F$26/$F$11*$F8),2) -> 0 | G72: =ROUND(IF($F$11=0,0,G$26/$F$11*$F8),2) -> 0 | H72: =ROUND(IF($F$11=0,0,H$26/$F$11*$F8),2) -> 0 | I72: =ROUND(IF($F$11=0,0,I$26/$F$11*$F8),2) -> 0 | J72: =ROUND(IF($F$11=0,0,J$26/$F$11*$F8),2) -> 0 | K72: =ROUND(IF($F$11=0,0,K$26/$F$11*$F8),2) -> 0 | L72: =ROUND(IF($F$11=0,0,L$26/$F$11*$F8),2) -> 0 | ... S72: =ROUND(IF($F$11=0,0,S$26/$F$11*$F8),2) -> 0
A73: n/a | B73: =Instructions!P4 -> Pay 2011 | C73: Debt Serv | D73: =SUM(E73:S73) -> 0 | E73: =ROUND(IF($G$11=0,0,E$27/$G$11*$G8),2) -> 0 | F73: =ROUND(IF($G$11=0,0,F$27/$G$11*$G8),2) -> 0 | G73: =ROUND(IF($G$11=0,0,G$27/$G$11*$G8),2) -> 0 | H73: =ROUND(IF($G$11=0,0,H$27/$G$11*$G8),2) -> 0 | I73: =ROUND(IF($G$11=0,0,I$27/$G$11*$G8),2) -> 0 | J73: =ROUND(IF($G$11=0,0,J$27/$G$11*$G8),2) -> 0 | K73: =ROUND(IF($G$11=0,0,K$27/$G$11*$G8),2) -> 0 | L73: =ROUND(IF($G$11=0,0,L$27/$G$11*$G8),2) -> 0 | ... S73: =ROUND(IF($G$11=0,0,S$27/$G$11*$G8),2) -> 0
A74: n/a | B74: =Instructions!P5 -> Pay 2010 | C74: Debt Serv | D74: =SUM(E74:S74) -> 0 | E74: =ROUND(IF($H$11=0,0,E$28/$H$11*$H8),2) -> 0 | F74: =ROUND(IF($H$11=0,0,F$28/$H$11*$H8),2) -> 0 | G74: =ROUND(IF($H$11=0,0,G$28/$H$11*$H8),2) -> 0 | H74: =ROUND(IF($H$11=0,0,H$28/$H$11*$H8),2) -> 0 | I74: =ROUND(IF($H$11=0,0,I$28/$H$11*$H8),2) -> 0 | J74: =ROUND(IF($H$11=0,0,J$28/$H$11*$H8),2) -> 0 | K74: =ROUND(IF($H$11=0,0,K$28/$H$11*$H8),2) -> 0 | L74: =ROUND(IF($H$11=0,0,L$28/$H$11*$H8),2) -> 0 | ... S74: =ROUND(IF($H$11=0,0,S$28/$H$11*$H8),2) -> 0
A75: n/a | B75: =Instructions!P6 -> Pay 2009 | C75: Debt Serv | D75: =SUM(E75:S75) -> 0 | E75: =ROUND(IF($I$11=0,0,E$29/$I$11*$I8),2) -> 0 | F75: =ROUND(IF($I$11=0,0,F$29/$I$11*$I8),2) -> 0 | G75: =ROUND(IF($I$11=0,0,G$29/$I$11*$I8),2) -> 0 | H75: =ROUND(IF($I$11=0,0,H$29/$I$11*$I8),2) -> 0 | I75: =ROUND(IF($I$11=0,0,I$29/$I$11*$I8),2) -> 0 | J75: =ROUND(IF($I$11=0,0,J$29/$I$11*$I8),2) -> 0 | K75: =ROUND(IF($I$11=0,0,K$29/$I$11*$I8),2) -> 0 | L75: =ROUND(IF($I$11=0,0,L$29/$I$11*$I8),2) -> 0 | ... S75: =ROUND(IF($I$11=0,0,S$29/$I$11*$I8),2) -> 0
A76: n/a | B76: =Instructions!P7 -> Pay 2008 | C76: Debt Serv | D76: =SUM(E76:S76) -> 0 | E76: =ROUND(IF($J$11=0,0,E$30/$J$11*$J8),2) -> 0 | F76: =ROUND(IF($J$11=0,0,F$30/$J$11*$J8),2) -> 0 | G76: =ROUND(IF($J$11=0,0,G$30/$J$11*$J8),2) -> 0 | H76: =ROUND(IF($J$11=0,0,H$30/$J$11*$J8),2) -> 0 | I76: =ROUND(IF($J$11=0,0,I$30/$J$11*$J8),2) -> 0 | J76: =ROUND(IF($J$11=0,0,J$30/$J$11*$J8),2) -> 0 | K76: =ROUND(IF($J$11=0,0,K$30/$J$11*$J8),2) -> 0 | L76: =ROUND(IF($J$11=0,0,L$30/$J$11*$J8),2) -> 0 | ... S76: =ROUND(IF($J$11=0,0,S$30/$J$11*$J8),2) -> 0
A77: n/a | B77: =Instructions!P8 -> Pay 2007 | C77: Debt Serv | D77: =SUM(E77:S77) -> 0 | E77: =ROUND(IF($K$11=0,0,E$31/$K$11*$K8),2) -> 0 | F77: =ROUND(IF($K$11=0,0,F$31/$K$11*$K8),2) -> 0 | G77: =ROUND(IF($K$11=0,0,G$31/$K$11*$K8),2) -> 0 | H77: =ROUND(IF($K$11=0,0,H$31/$K$11*$K8),2) -> 0 | I77: =ROUND(IF($K$11=0,0,I$31/$K$11*$K8),2) -> 0 | J77: =ROUND(IF($K$11=0,0,J$31/$K$11*$K8),2) -> 0 | K77: =ROUND(IF($K$11=0,0,K$31/$K$11*$K8),2) -> 0 | L77: =ROUND(IF($K$11=0,0,L$31/$K$11*$K8),2) -> 0 | ... S77: =ROUND(IF($K$11=0,0,S$31/$K$11*$K8),2) -> 0
A78: line left blank intentionally
A79: n/a | B79: n/a | C79: Subtotal | D79: =SUM(D71:D78) -> 0 | E79: =SUM(E71:E78) -> 0 | F79: =SUM(F71:F78) -> 0 | G79: =SUM(G71:G78) -> 0 | H79: =SUM(H71:H78) -> 0 | I79: =SUM(I71:I78) -> 0 | J79: =SUM(J71:J78) -> 0 | K79: =SUM(K71:K78) -> 0 | ... S79: =SUM(S71:S78) -> 0
A80: line left blank intentionally
A81: line left blank intentionally
A82: n/a | B82: =Instructions!P2 -> Pay 2013 | C82: OPEB | D82: =SUM(E82:S82) -> 0 | E82: =ROUND(IF($E$11=0,0,E$25/$E$11*$E9),2) -> 0 | F82: =ROUND(IF($E$11=0,0,F$25/$E$11*$E9),2) -> 0 | G82: =ROUND(IF($E$11=0,0,G$25/$E$11*$E9),2) -> 0 | H82: =ROUND(IF($E$11=0,0,H$25/$E$11*$E9),2) -> 0 | I82: =ROUND(IF($E$11=0,0,I$25/$E$11*$E9),2) -> 0 | J82: =ROUND(IF($E$11=0,0,J$25/$E$11*$E9),2) -> 0 | K82: =ROUND(IF($E$11=0,0,K$25/$E$11*$E9),2) -> 0 | L82: =ROUND(IF($E$11=0,0,L$25/$E$11*$E9),2) -> 0 | ... S82: =ROUND(IF($E$11=0,0,S$25/$E$11*$E9),2) -> 0
A83: n/a | B83: =Instructions!P3 -> Pay 2012 | C83: OPEB | D83: =SUM(E83:S83) -> 0 | E83: =ROUND(IF($F$11=0,0,E$26/$F$11*$F9),2) -> 0 | F83: =ROUND(IF($F$11=0,0,F$26/$F$11*$F9),2) -> 0 | G83: =ROUND(IF($F$11=0,0,G$26/$F$11*$F9),2) -> 0 | H83: =ROUND(IF($F$11=0,0,H$26/$F$11*$F9),2) -> 0 | I83: =ROUND(IF($F$11=0,0,I$26/$F$11*$F9),2) -> 0 | J83: =ROUND(IF($F$11=0,0,J$26/$F$11*$F9),2) -> 0 | K83: =ROUND(IF($F$11=0,0,K$26/$F$11*$F9),2) -> 0 | L83: =ROUND(IF($F$11=0,0,L$26/$F$11*$F9),2) -> 0 | ... S83: =ROUND(IF($F$11=0,0,S$26/$F$11*$F9),2) -> 0
A84: n/a | B84: =Instructions!P4 -> Pay 2011 | C84: OPEB | D84: =SUM(E84:S84) -> 0 | E84: =ROUND(IF($G$11=0,0,E$27/$G$11*$G9),2) -> 0 | F84: =ROUND(IF($G$11=0,0,F$27/$G$11*$G9),2) -> 0 | G84: =ROUND(IF($G$11=0,0,G$27/$G$11*$G9),2) -> 0 | H84: =ROUND(IF($G$11=0,0,H$27/$G$11*$G9),2) -> 0 | I84: =ROUND(IF($G$11=0,0,I$27/$G$11*$G9),2) -> 0 | J84: =ROUND(IF($G$11=0,0,J$27/$G$11*$G9),2) -> 0 | K84: =ROUND(IF($G$11=0,0,K$27/$G$11*$G9),2) -> 0 | L84: =ROUND(IF($G$11=0,0,L$27/$G$11*$G9),2) -> 0 | ... S84: =ROUND(IF($G$11=0,0,S$27/$G$11*$G9),2) -> 0
A85: n/a | B85: =Instructions!P5 -> Pay 2010 | C85: OPEB | D85: =SUM(E85:S85) -> 0 | E85: =ROUND(IF($H$11=0,0,E$28/$H$11*$H9),2) -> 0 | F85: =ROUND(IF($H$11=0,0,F$28/$H$11*$H9),2) -> 0 | G85: =ROUND(IF($H$11=0,0,G$28/$H$11*$H9),2) -> 0 | H85: =ROUND(IF($H$11=0,0,H$28/$H$11*$H9),2) -> 0 | I85: =ROUND(IF($H$11=0,0,I$28/$H$11*$H9),2) -> 0 | J85: =ROUND(IF($H$11=0,0,J$28/$H$11*$H9),2) -> 0 | K85: =ROUND(IF($H$11=0,0,K$28/$H$11*$H9),2) -> 0 | L85: =ROUND(IF($H$11=0,0,L$28/$H$11*$H9),2) -> 0 | ... S85: =ROUND(IF($H$11=0,0,S$28/$H$11*$H9),2) -> 0
A86: n/a | B86: =Instructions!P6 -> Pay 2009 | C86: OPEB | D86: =SUM(E86:S86) -> 0 | E86: =ROUND(IF($I$11=0,0,E$29/$I$11*$I9),2) -> 0 | F86: =ROUND(IF($I$11=0,0,F$29/$I$11*$I9),2) -> 0 | G86: =ROUND(IF($I$11=0,0,G$29/$I$11*$I9),2) -> 0 | H86: =ROUND(IF($I$11=0,0,H$29/$I$11*$I9),2) -> 0 | I86: =ROUND(IF($I$11=0,0,I$29/$I$11*$I9),2) -> 0 | J86: =ROUND(IF($I$11=0,0,J$29/$I$11*$I9),2) -> 0 | K86: =ROUND(IF($I$11=0,0,K$29/$I$11*$I9),2) -> 0 | L86: =ROUND(IF($I$11=0,0,L$29/$I$11*$I9),2) -> 0 | ... S86: =ROUND(IF($I$11=0,0,S$29/$I$11*$I9),2) -> 0
A87: n/a | B87: =Instructions!P7 -> Pay 2008 | C87: OPEB | D87: =SUM(E87:S87) -> 0 | E87: =ROUND(IF($J$11=0,0,E$30/$J$11*$J9),2) -> 0 | F87: =ROUND(IF($J$11=0,0,F$30/$J$11*$J9),2) -> 0 | G87: =ROUND(IF($J$11=0,0,G$30/$J$11*$J9),2) -> 0 | H87: =ROUND(IF($J$11=0,0,H$30/$J$11*$J9),2) -> 0 | I87: =ROUND(IF($J$11=0,0,I$30/$J$11*$J9),2) -> 0 | J87: =ROUND(IF($J$11=0,0,J$30/$J$11*$J9),2) -> 0 | K87: =ROUND(IF($J$11=0,0,K$30/$J$11*$J9),2) -> 0 | L87: =ROUND(IF($J$11=0,0,L$30/$J$11*$J9),2) -> 0 | ... S87: =ROUND(IF($J$11=0,0,S$30/$J$11*$J9),2) -> 0
A88: n/a | B88: =Instructions!P8 -> Pay 2007 | C88: OPEB | D88: =SUM(E88:S88) -> 0 | E88: =ROUND(IF($K$11=0,0,E$31/$K$11*$K9),2) -> 0 | F88: =ROUND(IF($K$11=0,0,F$31/$K$11*$K9),2) -> 0 | G88: =ROUND(IF($K$11=0,0,G$31/$K$11*$K9),2) -> 0 | H88: =ROUND(IF($K$11=0,0,H$31/$K$11*$K9),2) -> 0 | I88: =ROUND(IF($K$11=0,0,I$31/$K$11*$K9),2) -> 0 | J88: =ROUND(IF($K$11=0,0,J$31/$K$11*$K9),2) -> 0 | K88: =ROUND(IF($K$11=0,0,K$31/$K$11*$K9),2) -> 0 | L88: =ROUND(IF($K$11=0,0,L$31/$K$11*$K9),2) -> 0 | ... S88: =ROUND(IF($K$11=0,0,S$31/$K$11*$K9),2) -> 0
A89: line left blank intentionally
A90: n/a | B90: n/a | C90: Subtotal | D90: =SUM(D82:D89) -> 0 | E90: =SUM(E82:E89) -> 0 | F90: =SUM(F82:F89) -> 0 | G90: =SUM(G82:G89) -> 0 | H90: =SUM(H82:H89) -> 0 | I90: =SUM(I82:I89) -> 0 | J90: =SUM(J82:J89) -> 0 | K90: =SUM(K82:K89) -> 0 | ... S90: =SUM(S82:S89) -> 0
A91: line left blank intentionally
A92: line left blank intentionally
A93: Fiscal disparities
A94: n/a | B94: =Instructions!P1 -> Pay 2014 | C94: General | D94: =SUM(E94:S94) -> 0 | E94: =ROUND(IF($D$11=0,0,E$32/$D$11*$D6),2) -> 0 | F94: =ROUND(IF($D$11=0,0,F$32/$D$11*$D6),2) -> 0 | G94: =ROUND(IF($D$11=0,0,G$32/$D$11*$D6),2) -> 0 | H94: =ROUND(IF($D$11=0,0,H$32/$D$11*$D6),2) -> 0 | I94: =ROUND(IF($D$11=0,0,I$32/$D$11*$D6),2) -> 0 | J94: =ROUND(IF($D$11=0,0,J$32/$D$11*$D6),2) -> 0 | K94: =ROUND(IF($D$11=0,0,K$32/$D$11*$D6),2) -> 0 | L94: =ROUND(IF($D$11=0,0,L$32/$D$11*$D6),2) -> 0 | ... S94: =ROUND(IF($D$11=0,0,S$32/$D$11*$D6),2) -> 0
A95: n/a | B95: =Instructions!P1 -> Pay 2014 | C95: Comm Serv | D95: =SUM(E95:S95) -> 0 | E95: =ROUND(IF($D$11=0,0,E$32/$D$11*$D7),2) -> 0 | F95: =ROUND(IF($D$11=0,0,F$32/$D$11*$D7),2) -> 0 | G95: =ROUND(IF($D$11=0,0,G$32/$D$11*$D7),2) -> 0 | H95: =ROUND(IF($D$11=0,0,H$32/$D$11*$D7),2) -> 0 | I95: =ROUND(IF($D$11=0,0,I$32/$D$11*$D7),2) -> 0 | J95: =ROUND(IF($D$11=0,0,J$32/$D$11*$D7),2) -> 0 | K95: =ROUND(IF($D$11=0,0,K$32/$D$11*$D7),2) -> 0 | L95: =ROUND(IF($D$11=0,0,L$32/$D$11*$D7),2) -> 0 | ... S95: =ROUND(IF($D$11=0,0,S$32/$D$11*$D7),2) -> 0
A96: n/a | B96: =Instructions!P1 -> Pay 2014 | C96: Debt Serv | D96: =SUM(E96:S96) -> 0 | E96: =ROUND(IF($D$11=0,0,E$32/$D$11*$D8),2) -> 0 | F96: =ROUND(IF($D$11=0,0,F$32/$D$11*$D8),2) -> 0 | G96: =ROUND(IF($D$11=0,0,G$32/$D$11*$D8),2) -> 0 | H96: =ROUND(IF($D$11=0,0,H$32/$D$11*$D8),2) -> 0 | I96: =ROUND(IF($D$11=0,0,I$32/$D$11*$D8),2) -> 0 | J96: =ROUND(IF($D$11=0,0,J$32/$D$11*$D8),2) -> 0 | K96: =ROUND(IF($D$11=0,0,K$32/$D$11*$D8),2) -> 0 | L96: =ROUND(IF($D$11=0,0,L$32/$D$11*$D8),2) -> 0 | ... S96: =ROUND(IF($D$11=0,0,S$32/$D$11*$D8),2) -> 0
A97: n/a | B97: =Instructions!P1 -> Pay 2014 | C97: OPEB | D97: =SUM(E97:S97) -> 0 | E97: =ROUND(IF($D$11=0,0,E$32/$D$11*$D9),2) -> 0 | F97: =ROUND(IF($D$11=0,0,F$32/$D$11*$D9),2) -> 0 | G97: =ROUND(IF($D$11=0,0,G$32/$D$11*$D9),2) -> 0 | H97: =ROUND(IF($D$11=0,0,H$32/$D$11*$D9),2) -> 0 | I97: =ROUND(IF($D$11=0,0,I$32/$D$11*$D9),2) -> 0 | J97: =ROUND(IF($D$11=0,0,J$32/$D$11*$D9),2) -> 0 | K97: =ROUND(IF($D$11=0,0,K$32/$D$11*$D9),2) -> 0 | L97: =ROUND(IF($D$11=0,0,L$32/$D$11*$D9),2) -> 0 | ... S97: =ROUND(IF($D$11=0,0,S$32/$D$11*$D9),2) -> 0
A98: line left blank intentionally
A99: n/a | B99: n/a | C99: Subtotal | D99: =SUM(D94:D98) -> 0 | E99: =SUM(E94:E98) -> 0 | F99: =SUM(F94:F98) -> 0 | G99: =SUM(G94:G98) -> 0 | H99: =SUM(H94:H98) -> 0 | I99: =SUM(I94:I98) -> 0 | J99: =SUM(J94:J98) -> 0 | K99: =SUM(K94:K98) -> 0 | ... S99: =SUM(S94:S98) -> 0
A100: line left blank intentionally
A101: line left blank intentionally
...

Sheet Accounts
A1: Reconciation of Property Tax Accounts | I1: =Report!A3 -> 1 | J1: =Report!B5 -> AITKIN | L1: =Report!I1 -> 41828 | N1: Note:
N2: Account balances are indicated as debit or (credit) balance
A3: On Reports tab enter your district # in cell A3 so correct tax shift amounts carryover | N3: Asset and expenditure accounts would normally have a debit balance
A4: Data entered on Funds tab will carryover and be used to allocate adjustments and abatements | N4: Liability and revenue accounts would normally have a credit balance
A5: On this tab enter data in highlighted fields only--from source indicated | N5: See comments by accounts GNL 214 and SRC 020 and 299
A6: All other fields will compute, including those that come from the Tax Shift spreadsheet
A7: Enter debits as positive and credits as negative, as indicated in column H | I7: General | J7: Comm Serv | K7: GDS Debt | L7: OPEB Debt | M7: Total
I8: Debit (Credit) | J8: Debit (Credit) | K8: Debit (Credit) | L8: Debit (Credit) | M8: Debit (Credit)
A10: Balance Sheet Acccounts:
A12: =Instructions!P1&" Certified Levy" -> Pay 2014 Certified Levy | H12: Debit | I12: =Funds!D6 -> 0 | J12: =Funds!D7 -> 0 | K12: =Funds!D8 -> 0 | L12: =Funds!D9 -> 0 | M12: =SUM(I12:L12) -> 0 | N12: Levy Limitation & Certification Report
A13: ="Tax settlements "&Instructions!T4&" for "&Instructions!P1&" levy" -> Tax settlements 05/01/2014 to 06/30/2014 for Pay 2014 levy | H13: (Credit) | I13: =-Funds!D40 -> 0 | J13: =-Funds!D41 -> 0 | K13: =-Funds!D42 -> 0 | L13: =-Funds!D43 -> 0 | M13: =SUM(I13:L13) -> 0 | N13: ="Tax Settlement Reports (Form 52) "&Instructions!T2 -> Tax Settlement Reports (Form 52) 07/01/2013 to 06/30/2014
A14: ="Tax settlements Fiscal disparities "&Instructions!T4&" for "&Instructions!P1&" levy" -> Tax settlements Fiscal disparities 05/01/2014 to 06/30/2014 for Pay 2014 levy | H14: (Credit) | I14: =-Funds!D94 -> 0 | J14: =-Funds!D95 -> 0 | K14: =-Funds!D96 -> 0 | L14: =-Funds!D97 -> 0 | M14: =SUM(I14:L14) -> 0 | N14: ="Tax Settlement Reports (Form 52) "&Instructions!T2 -> Tax Settlement Reports (Form 52) 07/01/2013 to 06/30/2014
A15: ="Tax settlements Taconite homestead credit "&Instructions!T4&" for "&Instructions!P1&" levy" -> Tax settlements Taconite homestead credit 05/01/2014 to 06/30/2014 for Pay 2014 levy | H15: (Credit) | I15: =-Funds!D112 -> 0 | J15: =-Funds!D113 -> 0 | K15: =-Funds!D114 -> 0 | L15: =-Funds!D115 -> 0 | M15: =SUM(I15:L15) -> 0 | N15: ="Tax Settlement Reports (Form 52) "&Instructions!T2 -> Tax Settlement Reports (Form 52) 07/01/2013 to 06/30/2014
A16: (Do not include any July payments)
B18: ="110 Taxes Receivable--Current "&Instructions!S2 -> 110 Taxes Receivable--Current 06/30/14 | I18: =SUM(I12:I16) -> 0 | J18: =SUM(J12:J16) -> 0 | K18: =SUM(K12:K16) -> 0 | L18: =SUM(L12:L16) -> 0
A22: ="Delinquent Taxes Receivable "&Instructions!S3 -> Delinquent Taxes Receivable 06/30/13 | H22: Debit | I22: 0 | J22: 0 | K22: 0 | L22: 0 | M22: =SUM(I22:L22) -> 0 | N22: ="General Ledger "&Instructions!S3 -> General Ledger 06/30/13
A23: ="Current Taxes Receivable "&Instructions!S3 -> Current Taxes Receivable 06/30/13 | H23: Debit | I23: 0 | J23: 0 | K23: 0 | L23: 0 | M23: =SUM(I23:L23) -> 0 | N23: ="General Ledger "&Instructions!S3 -> General Ledger 06/30/13
A24: ="Increase (decrease) to "&Instructions!P2&" levy by county" -> Increase (decrease) to Pay 2013 levy by county | H24: Debit (Credit) | I24: =ROUND(IF(M24=0,0,Funds!E6/Funds!E11*M24),2) -> 0 | J24: =ROUND(IF(M24=0,0,Funds!E7/Funds!E11*M24),2) -> 0 | K24: =ROUND(IF(M24=0,0,Funds!E8/Funds!E11*M24),2) -> 0 | L24: =ROUND(IF(M24=0,0,Funds!E9/Funds!E11*M24),2) -> 0 | M24: 0 | N24: Taxes Receivable Report (Form 51)
A25: ="Increase (decrease) to "&Instructions!P3&" levy by county" -> Increase (decrease) to Pay 2012 levy by county | H25: Debit (Credit) | I25: =ROUND(IF($M$25=0,0,Funds!F6/Funds!$F$11*$M$25),2) -> 0 | J25: =ROUND(IF($M$25=0,0,Funds!F7/Funds!$F$11*$M$25),2) -> 0 | K25: =ROUND(IF($M$25=0,0,Funds!F8/Funds!$F$11*$M$25),2) -> 0 | L25: =ROUND(IF($M$25=0,0,Funds!F9/Funds!$F$11*$M$25),2) -> 0 | M25: 0 | N25: Taxes Receivable Report (Form 51)
A26: ="Agricultural Educ Homestead Market Value Credit for "&Instructions!R2 -> Agricultural Educ Homestead Market Value Credit for FY 2014 | H26: (Credit) | I26: 0 | J26: 0 | K26: 0 | L26: 0 | M26: =SUM(I26:L26) -> 0 | N26: Report of Credits from Dept of Revenue
A27: ="Other credits for "&Instructions!R2 -> Other credits for FY 2014 | H27: (Credit) | I27: 0 | J27: 0 | K27: 0 | L27: 0 | M27: =SUM(I27:L27) -> 0 | N27: Report of Credits from Dept of Revenue
A28: ="Disparity Aid adjustments for "&Instructions!R2 -> Disparity Aid adjustments for FY 2014 | H28: (Credit) | I28: 0 | J28: 0 | K28: 0 | L28: 0 | M28: =SUM(I28:L28) -> 0 | N28: Report of Credits from Dept of Revenue
A29: ="Decrease (increase) to credits by county" -> Decrease (increase) to credits by county | H29: Debit (Credit) | I29: =ROUND(IF(Funds!$E$11=0,0,Funds!E6/Funds!$E$11*$M$29),2) -> 0 | J29: =ROUND(IF(Funds!$E$11=0,0,Funds!E7/Funds!$E$11*$M$29),2) -> 0 | K29: =ROUND(IF(Funds!$E$11=0,0,Funds!E8/Funds!$E$11*$M$29),2) -> 0 | L29: =ROUND(IF(Funds!$E$11=0,0,Funds!E9/Funds!$E$11*$M$29),2) -> 0 | M29: 0 | N29: Credits on Taxes receivable minus credits from Revenue
A30: ="Abatements "&Instructions!T2&" for "&Instructions!P2&" levy" -> Abatements 07/01/2013 to 06/30/2014 for Pay 2013 levy | H30: (Credit) | I30: =ROUND(IF(Funds!$E$11=0,0,Funds!E6/Funds!$E$11*$M$30),2) -> 0 | J30: =ROUND(IF(Funds!$E$11=0,0,Funds!E7/Funds!$E$11*$M$30),2) -> 0 | K30: =ROUND(IF(Funds!$E$11=0,0,Funds!E8/Funds!$E$11*$M$30),2) -> 0 | L30: =ROUND(IF(Funds!$E$11=0,0,Funds!E9/Funds!$E$11*$M$30),2) -> 0 | M30: 0 | N30: Taxes Receivable Report (Form 51)
A31: ="Abatements "&Instructions!T2&" for "&Instructions!P3&" levy" -> Abatements 07/01/2013 to 06/30/2014 for Pay 2012 levy | H31: (Credit) | I31: =ROUND(IF(Funds!$F$11=0,0,Funds!F6/Funds!$F$11*$M$31),2) -> 0 | J31: =ROUND(IF(Funds!$F$11=0,0,Funds!F7/Funds!$F$11*$M$31),2) -> 0 | K31: =ROUND(IF(Funds!$F$11=0,0,Funds!F8/Funds!$F$11*$M$31),2) -> 0 | L31: =ROUND(IF(Funds!$F$11=0,0,Funds!F9/Funds!$F$11*$M$31),2) -> 0 | M31: 0 | N31: Taxes Receivable Report (Form 51)
A32: ="Abatements "&Instructions!T2&" for "&Instructions!P4&" levy" -> Abatements 07/01/2013 to 06/30/2014 for Pay 2011 levy | H32: (Credit) | I32: =ROUND(IF(Funds!$G$11=0,0,Funds!G6/Funds!$G$11*$M$32),2) -> 0 | J32: =ROUND(IF(Funds!$G$11=0,0,Funds!G7/Funds!$G$11*$M$32),2) -> 0 | K32: =ROUND(IF(Funds!$G$11=0,0,Funds!G8/Funds!$G$11*$M$32),2) -> 0 | L32: =ROUND(IF(Funds!$G$11=0,0,Funds!G9/Funds!$G$11*$M$32),2) -> 0 | M32: 0 | N32: Taxes Receivable Report (Form 51)
A33: ="Abatements "&Instructions!T2&" for "&Instructions!P5&" levy" -> Abatements 07/01/2013 to 06/30/2014 for Pay 2010 levy | H33: (Credit) | I33: =ROUND(IF(Funds!$H$11=0,0,Funds!H6/Funds!$H$11*$M$33),2) -> 0 | J33: =ROUND(IF(Funds!$H$11=0,0,Funds!H7/Funds!$H$11*$M$33),2) -> 0 | K33: =ROUND(IF(Funds!$H$11=0,0,Funds!H8/Funds!$H$11*$M$33),2) -> 0 | L33: =ROUND(IF(Funds!$H$11=0,0,Funds!H9/Funds!$H$11*$M$33),2) -> 0 | M33: 0 | N33: Taxes Receivable Report (Form 51)
A34: ="Abatements "&Instructions!T2&" for "&Instructions!P6&" levy" -> Abatements 07/01/2013 to 06/30/2014 for Pay 2009 levy | H34: (Credit) | I34: =ROUND(IF(Funds!$I$11=0,0,Funds!I6/Funds!$I$11*$M$34),2) -> 0 | J34: =ROUND(IF(Funds!$I$11=0,0,Funds!I7/Funds!$I$11*$M$34),2) -> 0 | K34: =ROUND(IF(Funds!$I$11=0,0,Funds!I8/Funds!$I$11*$M$34),2) -> 0 | L34: =ROUND(IF(Funds!$I$11=0,0,Funds!I9/Funds!$I$11*$M$34),2) -> 0 | M34: 0 | N34: Taxes Receivable Report (Form 51)
A35: ="Abatements "&Instructions!T2&" for "&Instructions!P7&" levy" -> Abatements 07/01/2013 to 06/30/2014 for Pay 2008 levy | H35: (Credit) | I35: =ROUND(IF(Funds!$J$11=0,0,Funds!J6/Funds!$J$11*$M$35),2) -> 0 | J35: =ROUND(IF(Funds!$J$11=0,0,Funds!J7/Funds!$J$11*$M$35),2) -> 0 | K35: =ROUND(IF(Funds!$J$11=0,0,Funds!J8/Funds!$J$11*$M$35),2) -> 0 | L35: =ROUND(IF(Funds!$J$11=0,0,Funds!J9/Funds!$J$11*$M$35),2) -> 0 | M35: 0 | N35: Taxes Receivable Report (Form 51)
A36: ="Abatements "&Instructions!T2&" for "&Instructions!P8&" levy" -> Abatements 07/01/2013 to 06/30/2014 for Pay 2007 levy | H36: (Credit) | I36: =ROUND(IF(Funds!$K$11=0,0,Funds!K6/Funds!$K$11*$M$36),2) -> 0 | J36: =ROUND(IF(Funds!$K$11=0,0,Funds!K7/Funds!$K$11*$M$36),2) -> 0 | K36: =ROUND(IF(Funds!$K$11=0,0,Funds!K8/Funds!$K$11*$M$36),2) -> 0 | L36: =ROUND(IF(Funds!$K$11=0,0,Funds!K9/Funds!$K$11*$M$36),2) -> 0 | M36: 0 | N36: Taxes Receivable Report (Form 51)
A37: ="Write off "&Instructions!P8&" delinquent taxes negative (positive) balance due" -> Write off Pay 2007 delinquent taxes negative (positive) balance due | H37: Debit (Credit) | I37: =ROUND(IF(Funds!$K$11=0,0,Funds!K6/Funds!$K$11*$M$37),2) -> 0 | J37: =ROUND(IF(Funds!$K$11=0,0,Funds!K7/Funds!$K$11*$M$37),2) -> 0 | K37: =ROUND(IF(Funds!$K$11=0,0,Funds!K8/Funds!$K$11*$M$37),2) -> 0 | L37: =ROUND(IF(Funds!$K$11=0,0,Funds!K9/Funds!$K$11*$M$37),2) -> 0 | M37: 0 | N37: Taxes Receivable Report (Form 51)
A38: ="Tax settlements "&Instructions!T2&" for "&Instructions!P2&" and prior levies" -> Tax settlements 07/01/2013 to 06/30/2014 for Pay 2013 and prior levies | H38: (Credit) | I38: =-Funds!D57 -> 0 | J38: =-Funds!D68 -> 0 | K38: =-Funds!D79 -> 0 | L38: =-Funds!D90 -> 0 | M38: =SUM(I38:L38) -> 0 | N38: ="Tax Settlement Reports (Form 52) "&Instructions!T2 -> Tax Settlement Reports (Form 52) 07/01/2013 to 06/30/2014
A39: ="Tax settlements Fiscal Disparities "&Instructions!T3&" for "&Instructions!P2 -> Tax settlements Fiscal Disparities 07/01/2013 to 04/30/2014 for Pay 2013 | H39: (Credit) | I39: =-Funds!D103 -> 0 | J39: =-Funds!D104 -> 0 | K39: =-Funds!D105 -> 0 | L39: =-Funds!D106 -> 0 | M39: =SUM(I39:L39) -> 0 | N39: ="Tax Settlement Reports (Form 52) "&Instructions!T2 -> Tax Settlement Reports (Form 52) 07/01/2013 to 06/30/2014
A40: ="Tax settlements Taconite homestead credit "&Instructions!T3&" for "&Instructions!P2 -> Tax settlements Taconite homestead credit 07/01/2013 to 04/30/2014 for Pay 2013 | H40: (Credit) | I40: =-Funds!D121 -> 0 | J40: =-Funds!D122 -> 0 | K40: =-Funds!D123 -> 0 | L40: =-Funds!D124 -> 0 | M40: =SUM(I40:L40) -> 0 | N40: ="Tax Settlement Reports (Form 52) "&Instructions!T2 -> Tax Settlement Reports (Form 52) 07/01/2013 to 06/30/2014
B42: ="111 Delinquent Taxes Receivable "&Instructions!S2 -> 111 Delinquent Taxes Receivable 06/30/14 | I42: =SUM(I22:I40) -> 0 | J42: =SUM(J22:J40) -> 0 | K42: =SUM(K22:K40) -> 0 | L42: =SUM(L22:L40) -> 0
A44: Year end receivable (payable) adjustment for property tax shift | H44: (Credit) | I44: =Report!I18 -> -5395.57 | J44: =Report!I23 -> 5395.57 | M44: =SUM(I44:L44) -> -7.2759576e-12 | N44: Tax Shift Report (column 6)
B46: ="213 Property Tax Shift Adjustment "&Instructions!S2 -> 213 Property Tax Shift Adjustment 06/30/14 | I46: =I44 -> -5395.57 | J46: =J44 -> 5395.57
A48: Amount by which tax shift exceeds property tax receipts | H48: Debit | I48: =Report!E86 -> 0 | J48: =Report!E88 -> 0 | M48: =SUM(I48:L48) -> 0 | N48: Tax Shift Entry
B50: ="214 Advance of Unearned General Education Aid "&Instructions!S2 -> 214 Advance of Unearned General Education Aid 06/30/14 | I50: =SUM(I48:I49) -> 0 | J50: =SUM(J48:J49) -> 0
A52: ="Deferred Revenue for Delinquent Taxes "&Instructions!S3 -> Deferred Revenue for Delinquent Taxes 06/30/13 | H52: (Credit) | I52: 0 | J52: 0 | K52: 0 | L52: 0 | M52: =SUM(I52:L52) -> 0 | N52: ="General Ledger "&Instructions!S3 -> General Ledger 06/30/13
A53: ="Decrease (increase) in Delinquent Taxes from "&Instructions!S3&" to "&Instructions!S2 -> Decrease (increase) in Delinquent Taxes from 06/30/13 to 06/30/14 | H53: Debit (Credit) | I53: =I22-I42 -> 0 | J53: =J22-J42 -> 0 | K53: =K22-K42 -> 0 | L53: =L22-L42 -> 0 | M53: =SUM(I53:L53) -> 0 | N53: General Ledger
A54: ="Increase (decrease) in amount to be collected within 60 days from "&Instructions!S3&" to "&Instructions!S2 -> Increase (decrease) in amount to be collected within 60 days from 06/30/13 to 06/30/14 | H54: Debit (Credit) | I54: 0 | J54: 0 | K54: 0 | L54: 0 | M54: =SUM(I54:L54) -> 0 | N54: Tax Settlement Reports (Form 52) for each July
B56: ="231 Deferred Revenue--Delinquent Taxes "&Instructions!S2 -> 231 Deferred Revenue--Delinquent Taxes 06/30/14 | I56: =SUM(I52:I54) -> 0 | J56: =SUM(J52:J54) -> 0 | K56: =SUM(K52:K54) -> 0 | L56: =SUM(L52:L54) -> 0
A58: =Instructions!P1&" Certified Levy" -> Pay 2014 Certified Levy | H58: (Credit) | I58: =-I12 -> 0 | J58: =-J12 -> 0 | K58: =-K12 -> 0 | L58: =-L12 -> 0 | M58: =SUM(I58:L58) -> 0 | N58: Levy Limitation & Certification Report
A59: ="Property Tax Shift into "&Instructions!R2 -> Property Tax Shift into FY 2014 | H59: Debit | I59: =Report!C18 -> 178003.41 | J59: =Report!C23 -> 0 | M59: =SUM(I59:L59) -> 178003.41 | N59: Tax Shift Report (column 1 - line J or N)
A60: Amount by which tax shift exceeds property tax receipts | H60: (Credit) | I60: =-I50 -> 0 | J60: =-J50 -> 0 | M60: =SUM(I60:L60) -> 0 | N60: ="Account 214 balance at "&Instructions!S2 -> Account 214 balance at 06/30/14
B62: ="235 Property Taxes for Subsequent Years "&Instructions!S2 -> 235 Property Taxes for Subsequent Years 06/30/14 | I62: =SUM(I58:I60) -> 178003.41 | J62: =SUM(J58:J60) -> 0 | K62: =SUM(K58:K60) -> 0 | L62: =SUM(L58:L60) -> 0
A64: Revenue Accounts:
A66: =Instructions!P2&" Certified Levy" -> Pay 2013 Certified Levy | H66: (Credit) | I66: =-Funds!E6 -> 0 | J66: =-Funds!E7 -> 0 | K66: =-Funds!E8 -> 0 | L66: =-Funds!E9 -> 0 | M66: =SUM(I66:L66) -> 0 | N66: Levy Limitation & Certification Report
A67: ="Decrease (increase) to "&Instructions!P2&" levy by county" -> Decrease (increase) to Pay 2013 levy by county | H67: Debit (Credit) | I67: =-I24 -> 0 | J67: =-J24 -> 0 | K67: =-K24 -> 0 | L67: =-L24 -> 0 | M67: =SUM(I67:L67) -> 0 | N67: Taxes Receivable Report (Form 51)
A68: ="Decrease (increase) to "&Instructions!P3&" levy by county" -> Decrease (increase) to Pay 2012 levy by county | H68: Debit (Credit) | I68: =-I25 -> 0 | J68: =-J25 -> 0 | K68: =-K25 -> 0 | L68: =-L25 -> 0 | M68: =SUM(I68:L68) -> 0 | N68: Taxes Receivable Report (Form 51)
A69: ="Agricultural Educ Homestead Market Value Credit for "&Instructions!R2 -> Agricultural Educ Homestead Market Value Credit for FY 2014 | H69: Debit | I69: =-I26 -> 0 | J69: =-J26 -> 0 | K69: =-K26 -> 0 | L69: =-L26 -> 0 | M69: =SUM(I69:L69) -> 0 | N69: Taxes Receivable Report (Form 51)
A70: ="Other Credits for "&Instructions!R2 -> Other Credits for FY 2014 | H70: Debit | I70: =-I27 -> 0 | J70: =-J27 -> 0 | K70: =-K27 -> 0 | L70: =-L27 -> 0 | M70: =SUM(I70:L70) -> 0 | N70: Taxes Receivable Report (Form 51)
A71: ="Disparity Aid adjustments for "&Instructions!R2 -> Disparity Aid adjustments for FY 2014 | H71: Debit | I71: =-I28 -> 0 | J71: =-J28 -> 0 | K71: =-K28 -> 0 | L71: =-L28 -> 0 | M71: =SUM(I71:L71) -> 0 | N71: Taxes Receivable Report (Form 51)
A72: Increase (decrease) to credits by county | H72: Debit (Credit) | I72: =-I29 -> 0 | J72: =-J29 -> 0 | K72: =-K29 -> 0 | L72: =-L29 -> 0 | M72: =SUM(I72:L72) -> 0 | N72: Credits on Taxes receivable minus credits from Revenue
A73: ="Abatements "&Instructions!T2&" for "&Instructions!P2&" levy" -> Abatements 07/01/2013 to 06/30/2014 for Pay 2013 levy | H73: Debit | I73: =-I30 -> 0 | J73: =-J30 -> 0 | K73: =-K30 -> 0 | L73: =-L30 -> 0 | M73: =SUM(I73:L73) -> 0 | N73: Taxes Receivable Report (Form 51)
A74: ="Abatements "&Instructions!T2&" for "&Instructions!P3&" levy" -> Abatements 07/01/2013 to 06/30/2014 for Pay 2012 levy | H74: Debit | I74: =-I31 -> 0 | J74: =-J31 -> 0 | K74: =-K31 -> 0 | L74: =-L31 -> 0 | M74: =SUM(I74:L74) -> 0 | N74: Taxes Receivable Report (Form 51)
A75: ="Abatements "&Instructions!T2&" for "&Instructions!P4&" levy" -> Abatements 07/01/2013 to 06/30/2014 for Pay 2011 levy | H75: Debit | I75: =-I32 -> 0 | J75: =-J32 -> 0 | K75: =-K32 -> 0 | L75: =-L32 -> 0 | M75: =SUM(I75:L75) -> 0 | N75: Taxes Receivable Report (Form 51)
A76: ="Abatements "&Instructions!T2&" for "&Instructions!P5&" levy" -> Abatements 07/01/2013 to 06/30/2014 for Pay 2010 levy | H76: Debit | I76: =-I33 -> 0 | J76: =-J33 -> 0 | K76: =-K33 -> 0 | L76: =-L33 -> 0 | M76: =SUM(I76:L76) -> 0 | N76: Taxes Receivable Report (Form 51)
A77: ="Abatements "&Instructions!T2&" for "&Instructions!P6&" levy" -> Abatements 07/01/2013 to 06/30/2014 for Pay 2009 levy | H77: Debit | I77: =-I34 -> 0 | J77: =-J34 -> 0 | K77: =-K34 -> 0 | L77: =-L34 -> 0 | M77: =SUM(I77:L77) -> 0 | N77: Taxes Receivable Report (Form 51)
A78: ="Abatements "&Instructions!T2&" for "&Instructions!P7&" levy" -> Abatements 07/01/2013 to 06/30/2014 for Pay 2008 levy | H78: Debit | I78: =-I35 -> 0 | J78: =-J35 -> 0 | K78: =-K35 -> 0 | L78: =-L35 -> 0 | M78: =SUM(I78:L78) -> 0 | N78: Taxes Receivable Report (Form 51)
A79: ="Abatements "&Instructions!T2&" for "&Instructions!P8&" levy" -> Abatements 07/01/2013 to 06/30/2014 for Pay 2007 levy | H79: Debit | I79: =-I36 -> 0 | J79: =-J36 -> 0 | K79: =-K36 -> 0 | L79: =-L36 -> 0 | M79: =SUM(I79:L79) -> 0 | N79: Taxes Receivable Report (Form 51)
A80: ="Write off "&Instructions!P8&" delinquent taxes positive (negative) balance due" -> Write off Pay 2007 delinquent taxes positive (negative) balance due | H80: Debit (Credit) | I80: =-I37 -> 0 | J80: =-J37 -> 0 | K80: =-K37 -> 0 | L80: =-L37 -> 0 | M80: =SUM(I80:L80) -> 0 | N80: Taxes Receivable Report (Form 51)
A81: ="Fiscal Disparities adjustment for "&Instructions!R2 -> Fiscal Disparities adjustment for FY 2014 | H81: Debit | I81: =-I88 -> 0 | J81: =-J88 -> 0 | K81: =-K88 -> 0 | L81: =-L88 -> 0 | M81: =SUM(I81:L81) -> 0 | N81: Tax Settlement Reports (Form 52)
A82: ="Taconite Homestead credit for "&Instructions!R2 -> Taconite Homestead credit for FY 2014 | H82: Debit | I82: =-I92 -> 0 | J82: =-J92 -> 0 | K82: =-K92 -> 0 | L82: =-L92 -> 0 | M82: =SUM(I82:L82) -> 0 | N82: Tax Settlement Reports (Form 52)
A83: ="Property Tax Shift into "&Instructions!R3 -> Property Tax Shift into FY 2013 | H83: Debit | I83: =Report!D11+Report!D12+Report!D13+Report!D14+Report!D15+Report!D16+Report!D17 -> 175023.1 | J83: =Report!D21+Report!D22 -> 0 | M83: =SUM(I83:L83) -> 175023.1 | N83: Tax Shift Report (column 2 - lines C+D+E+F+G+H+I or L+M)
A84: ="Property Tax Shift into "&Instructions!R2 -> Property Tax Shift into FY 2014 | H84: (Credit) | I84: =-(Report!C11+Report!C12+Report!C13+Report!C14+Report!C15+Report!C16+Report!C17) -> -178003.41 | J84: =-(Report!C21+Report!C22) -> 0 | M84: =SUM(I84:L84) -> -178003.41 | N84: Tax Shift Report (column 1 - lines C+D+E+F+G+H+I or L+M)
B86: ="001 Tax Revenue for "&Instructions!R2 -> 001 Tax Revenue for FY 2014 | I86: =SUM(I66:I84) -> -2980.31 | J86: =SUM(J66:J84) -> 0 | K86: =SUM(K66:K84) -> 0 | L86: =SUM(L66:L84) -> 0
A88: ="Tax settlements Fiscal Disparities for "&Instructions!P2&" levy" -> Tax settlements Fiscal Disparities for Pay 2013 levy | H88: (Credit) | I88: =I14+I39 -> 0 | J88: =J14+J39 -> 0 | K88: =K14+K39 -> 0 | L88: =L14+L39 -> 0 | M88: =SUM(I88:L88) -> 0 | N88: Tax Settlement Reports (Form 52)
B90: ="009 Fisclal Disparities for "&Instructions!R2 -> 009 Fisclal Disparities for FY 2014 | I90: =SUM(I88) -> 0 | J90: =SUM(J88) -> 0 | K90: =SUM(K88) -> 0 | L90: =SUM(L88) -> 0
A92: ="Tax settlements Taconite homestead credit for "&Instructions!P2&" levy" -> Tax settlements Taconite homestead credit for Pay 2013 levy | H92: (Credit) | I92: =I15+I40 -> 0 | J92: =J15+J40 -> 0 | K92: =K15+K40 -> 0 | L92: =L15+L40 -> 0 | M92: =SUM(I92:L92) -> 0 | N92: Tax Settlement Reports (Form 52)
B94: ="014 Taconite Homestead Credits for "&Instructions!R2 -> 014 Taconite Homestead Credits for FY 2014 | I94: =I92 -> 0 | J94: =J92 -> 0 | K94: =K92 -> 0 | L94: =L92 -> 0
A96: ="Property Tax Shift into "&Instructions!R3 -> Property Tax Shift into FY 2013 | H96: Debit | I96: =Report!D9+Report!D10 -> 348692.74 | J96: =Report!D20 -> 5395.57 | M96: =SUM(I96:L96) -> 354088.31 | N96: Tax Shift Report (column 2 - lines A+B or K )
A97: ="Property Tax Shift into "&Instructions!R2 -> Property Tax Shift into FY 2014 | H97: (Credit) | I97: =-(Report!C9+Report!C10) -> 0 | J97: =-Report!C20 -> 0 | M97: =SUM(I97:L97) -> 0 | N97: Tax Shift Report (column 1 - lines A+B or K)
B99: ="020 Property Tax Shift Revenue for "&Instructions!R2 -> 020 Property Tax Shift Revenue for FY 2014 | I99: =SUM(I96:I97) -> 348692.74 | J99: =SUM(J96:J97) -> 5395.57
A101: Amount of General Ed Aid recognized early for shift with aid reduction | H101: (Credit) | I101: =Report!E101 -> 0 | J101: =Report!E103 -> 0 | M101: =SUM(I101:L101) -> 0 | N101: Tax Shift Entry
B103: ="296 State Aid Adjustment for Shift for "&Instructions!R2 -> 296 State Aid Adjustment for Shift for FY 2014 | I103: =SUM(I101) -> 0 | J103: =SUM(J101) -> 0
A105: ="Reductions to aid payments for "&Instructions!R2&" for property tax shift" -> Reductions to aid payments for FY 2014 for property tax shift | H105: Debit | I105: =-Report!H18 -> -354088.31 | J105: =-Report!H23 -> 0 | M105: =SUM(I105:L105) -> -354088.31 | N105: Tax Shift Report (column 5 - line J or N)
A106: Year end payable (receivable) for property tax shift | H106: Debit (Credit) | I106: =-Report!I18 -> 5395.57 | J106: =-Report!I23 -> -5395.57 | M106: =SUM(I106:L106) -> 7.2759576e-12 | N106: Tax Shift Report (column 6 - line J or N)
B108: ="299 State Aid Adjustment for Shift for "&Instructions!R2 -> 299 State Aid Adjustment for Shift for FY 2014 | I108: =SUM(I105:I106) -> -348692.74 | J108: =SUM(J105:J106) -> -5395.57
A109: End of worksheet

Sheet Entries
A1: Entries to record property taxes | C1: n/a | D1: n/a | E1: =Report!I1 -> 41828 | F1: n/a | G1: n/a
A2: line left blank intentionally
A3: Jan 1 | B3: Debit | C3: GL 110 | D3: Current Taxes Receivable
A4: n/a | B4: Credit | C4: GL 235 | D4: Deferred Revenue
A5: n/a | B5: n/a | C5: To record current year levy as taxes receivable
A6: line left blank intentionally
A7: Jan 1 | B7: Debit | C7: GL 111 | D7: Delinquent Taxes Receivable
A8: n/a | B8: Credit | C8: GL 110 | D8: Current Taxes Receivable
A9: n/a | B9: n/a | C9: To transfer current taxes receivable to delinquent taxes
A10: line left blank intentionally
A11: Jan - July | B11: Debit | C11: GL 101 | D11: Cash
A12: n/a | B12: Credit | C12: GL 110 | D12: Current Taxes Receivable
A13: n/a | B13: Credit | C13: GL 111 | D13: Delinquent Taxes Receivable
A14: n/a | B14: Credit | C14: SRC 009 | D14: Fiscal Disparities
A15: n/a | B15: Credit | C15: SRC 014 | D15: Taconite Homestead Credit
A16: n/a | B16: Credit | C16: SRC 019 | D16: Miscellaneous tax revenue
A17: n/a | B17: n/a | C17: To record first half tax settlements received from counties
A18: line left blank intentionally
A19: June 30 | B19: Debit | C19: GL 235 | D19: Deferred Revenue
A20: n/a | B20: Debit | C20: GL 214 | D20: Advance of Unearned Gened
A21: n/a | B21: Credit | C21: SRC 001 | D21: Tax Revenue
A22: n/a | B22: Credit | C22: SRC 211 | D22: Tax Revenue (Portions with Finance Codes)
A23: n/a | B23: n/a | C23: To record current year tax shift
A24: line left blank intentionally
A25: n/a | B25: Note: Property tax shift entry shown on "Report" tab combines the June 30th entry to record the current year tax shift (entry just above this note) with the prior July 1st entry to reverse the prior year tax shift (entry similar to entry below, but for the previous July 1st). | C25: n/a | D25: n/a | E25: n/a | F25: n/a | G25: n/a
A26: line left blank intentionally
A27: July 1 | B27: Debit | C27: SRC 001 | D27: Tax Revenue
A28: n/a | B28: Debit | C28: SRC 211 | D28: Tax Revenue (Portions with Finance Codes)
A29: n/a | B29: Credit | C29: GL 235 | D29: Deferred Revenue
A30: n/a | B30: Debit | C30: GL 214 | D30: Advance of Unearned Gened
A31: n/a | B31: n/a | C31: To reverse prior year tax shift
A32: line left blank intentionally
A33: July 1 | B33: Debit | C33: GL 235 | D33: Deferred Revenue
A34: n/a | B34: Credit | C34: SRC 001 | D34: Tax Revenue
A35: n/a | B35: Credit | C35: SRC 001 | D35: Tax Revenue (Portions with Finance Codes)
A36: n/a | B36: n/a | C36: To record levy revenue for current year
A37: line left blank intentionally
A38: July 1 | B38: Debit | C38: SRC 001 | D38: Tax Revenue
A39: n/a | B39: Credit | C39: GL 110 | D39: Current Taxes Receivable
A40: n/a | B40: n/a | C40: To reduce taxes receivable for amount to be paid by state credits
A41: line left blank intentionally
A42: July 1 | B42: Debit | C42: SRC 001 | D42: Tax Revenue
A43: n/a | B43: Credit | C43: GL 110 | D43: Current Taxes Receivable
A44: n/a | B44: n/a | C44: To reduce taxes receivable for amount to be paid by fiscal disparities
A45: line left blank intentionally
A46: July 1 | B46: Debit | C46: SRC 001 | D46: Tax Revenue
A47: n/a | B47: Credit | C47: GL 110 | D47: Current Taxes Receivable
A48: n/a | B48: n/a | C48: To reduce taxes receivable for amount to be paid by taconite homestead credit
A49: line left blank intentionally
A50: July 1 | B50: Debit/Credit | C50: SRC 001 | D50: Tax Revenue
A51: n/a | B51: Credit/Debit | C51: GL 110 | D51: Current Taxes Receivable
A52: n/a | B52: n/a | C52: To adjust taxes receivable for county auditor adjustments
A53: line left blank intentionally
A54: Oct - Jan | B54: Debit | C54: GL 101 | D54: Cash
A55: n/a | B55: Credit | C55: GL 110 | D55: Current Taxes Receivable
A56: n/a | B56: Credit | C56: GL 111 | D56: Delinquent Taxes Receivable
A57: n/a | B57: Credit | C57: GL 009 | D57: Fiscal Disparities
A58: n/a | B58: Credit | C58: GL 014 | D58: Taconite Homestead Credit
A59: n/a | B59: Credit | C59: SRC 019 | D59: Miscellaneous tax revenue
A60: n/a | B60: n/a | C60: To record second half tax settlements received from counties
A61: line left blank intentionally
A62: June 30 | B62: Debit | C62: SRC 001 | D62: Tax Revenue
A63: n/a | B63: Credit | C63: GL 111 | D63: Delinquent Taxes Receivable
A64: n/a | B64: n/a | C64: To reduce taxes receivable for abatements
A65: line left blank intentionally
A66: June 30 | B66: Debit | C66: SRC 001 | D66: Tax Revenue
A67: n/a | B67: Credit | C67: GL 111 | D67: Delinquent Taxes Receivable
A68: n/a | B68: n/a | C68: To reduce taxes receivable for seventh-year write offs
A69: line left blank intentionally
A70: June 30 | B70: Debit/Credit | C70: SRC 001 | D70: Tax Revenue
A71: n/a | B71: Credit/Debit | C71: GL 231 | D71: Deferred Revenue--Delinquent Taxes
A72: n/a | B72: n/a | C72: To adjust deferred revenue for delinquent taxes
A73: End of worksheet

Sheet Aid Adjust
A1: =Instructions!R2&" Aid Payment (Reduction)" -> FY 2014 Aid Payment (Reduction) | H1: =Report!I1 -> 41828
A2: Positve amount indicates state aid payment | E2: n/a | F2: n/a | G2: n/a | H2: n/a
A3: Negative amount indicates reduction to state aid payments | E3: n/a | F3: n/a | G3: n/a | H3: n/a
A4: File created from LEVY run under S:\common\TAXSHIFT | E4: n/a | F4: n/a | G4: n/a | H4: n/a
A5: line left blank intentionally | E5: n/a | F5: n/a | G5: n/a | H5: n/a
A6: n/a | B6: n/a | C6: n/a | D6: General Shift Aid Adjust | E6: Refer Aid Adjust | F6: Total General Aid Adjust | G6: Comm Serv Aid Adjust | H6: Total Aid Adjust
A7: n/a | B7: n/a | C7: n/a | D7: -2.4734801e+08 | E7: -2.455034e+08 | F7: -4.9285142e+08 | G7: -35601749 | H7: -5.2845317e+08
A8: n/a | B8: n/a | C8: n/a | D8: =SUM(D10:D341) -> 2.4944436e+08 | E8: =SUM(E10:E341) -> 2.6547387e+08 | F8: =SUM(F10:F341) -> 5.1491822e+08 | G8: =SUM(G10:G341) -> 36141518 | H8: =SUM(H10:H341) -> 5.5105974e+08
A9: line left blank intentionally
A10: 1 | B10: 1 | C10: AITKIN | D10: ='Shift 13'!D11-'Shift 14'!D6 -> 348692.74 | E10: ='Shift 13'!E11-'Shift 14'!E6 -> 0 | F10: =D10+E10 -> 348692.74 | G10: ='Shift 13'!M11-'Shift 14'!M6 -> 5395.57 | H10: =SUM(F10:G10) -> 354088.31
A11: 1.2 | B11: 3 | C11: MINNEAPOLIS | D11: ='Shift 13'!D12-'Shift 14'!D7 -> 10520675 | E11: ='Shift 13'!E12-'Shift 14'!E7 -> 21877596 | F11: =D11+E11 -> 32398271 | G11: ='Shift 13'!M12-'Shift 14'!M7 -> 2310760.1 | H11: =SUM(F11:G11) -> 34709031
A12: 2 | B12: 1 | C12: HILL CITY | D12: ='Shift 13'!D13-'Shift 14'!D8 -> 52908.37 | E12: ='Shift 13'!E13-'Shift 14'!E8 -> 0 | F12: =D12+E12 -> 52908.37 | G12: ='Shift 13'!M13-'Shift 14'!M8 -> 9691.81 | H12: =SUM(F12:G12) -> 62600.18
A13: 4 | B13: 1 | C13: MCGREGOR | D13: ='Shift 13'!D14-'Shift 14'!D9 -> 171965.38 | E13: ='Shift 13'!E14-'Shift 14'!E9 -> 0 | F13: =D13+E13 -> 171965.38 | G13: ='Shift 13'!M14-'Shift 14'!M9 -> 25493.62 | H13: =SUM(F13:G13) -> 197459
A14: 6 | B14: 3 | C14: SOUTH ST. PAUL | D14: ='Shift 13'!D15-'Shift 14'!D10 -> 1373574.9 | E14: ='Shift 13'!E15-'Shift 14'!E10 -> 1070015.6 | F14: =D14+E14 -> 2443590.5 | G14: ='Shift 13'!M15-'Shift 14'!M10 -> 174530.38 | H14: =SUM(F14:G14) -> 2618120.8
A15: 11 | B15: 1 | C15: ANOKA-HENNEPIN | D15: ='Shift 13'!D16-'Shift 14'!D11 -> 10965625 | E15: ='Shift 13'!E16-'Shift 14'!E11 -> 20072770 | F15: =D15+E15 -> 31038395 | G15: ='Shift 13'!M16-'Shift 14'!M11 -> 1511185 | H15: =SUM(F15:G15) -> 32549580
A16: 12 | B16: 1 | C16: CENTENNIAL | D16: ='Shift 13'!D17-'Shift 14'!D12 -> 1678920.9 | E16: ='Shift 13'!E17-'Shift 14'!E12 -> 2331680 | F16: =D16+E16 -> 4010601 | G16: ='Shift 13'!M17-'Shift 14'!M12 -> 203136.35 | H16: =SUM(F16:G16) -> 4213737.3
A17: 13 | B17: 1 | C17: COLUMBIA HEIGHTS | D17: ='Shift 13'!D18-'Shift 14'!D13 -> 1067552.7 | E17: ='Shift 13'!E18-'Shift 14'!E13 -> 780519.38 | F17: =D17+E17 -> 1848072.1 | G17: ='Shift 13'!M18-'Shift 14'!M13 -> 171191.46 | H17: =SUM(F17:G17) -> 2019263.6
A18: 14 | B18: 1 | C18: FRIDLEY | D18: ='Shift 13'!D19-'Shift 14'!D14 -> 1197487.9 | E18: ='Shift 13'!E19-'Shift 14'!E14 -> 702683.97 | F18: =D18+E18 -> 1900171.8 | G18: ='Shift 13'!M19-'Shift 14'!M14 -> 198881.39 | H18: =SUM(F18:G18) -> 2099053.2
A19: 15 | B19: 1 | C19: ST. FRANCIS | D19: ='Shift 13'!D20-'Shift 14'!D15 -> 1128147.4 | E19: ='Shift 13'!E20-'Shift 14'!E15 -> 558074.99 | F19: =D19+E19 -> 1686222.4 | G19: ='Shift 13'!M20-'Shift 14'!M15 -> 177575.69 | H19: =SUM(F19:G19) -> 1863798.1
A20: 16 | B20: 1 | C20: SPRING LAKE PARK | D20: ='Shift 13'!D21-'Shift 14'!D16 -> 2285453.8 | E20: ='Shift 13'!E21-'Shift 14'!E16 -> 1718912.6 | F20: =D20+E20 -> 4004366.4 | G20: ='Shift 13'!M21-'Shift 14'!M16 -> 224515.36 | H20: =SUM(F20:G20) -> 4228881.8
A21: 22 | B21: 1 | C21: DETROIT LAKES | D21: ='Shift 13'!D22-'Shift 14'!D17 -> 704875.8 | E21: ='Shift 13'!E22-'Shift 14'!E17 -> 499115.63 | F21: =D21+E21 -> 1203991.4 | G21: ='Shift 13'!M22-'Shift 14'!M17 -> 102673.53 | H21: =SUM(F21:G21) -> 1306665
... A341: 2908 | B341: 1 | C341: BRANDON-EVANSVILLE | D341: ='Shift 13'!D342-'Shift 14'!D337 -> 161904.79 | E341: ='Shift 13'!E342-'Shift 14'!E337 -> 235233.04 | F341: =D341+E341 -> 397137.83 | G341: ='Shift 13'!M342-'Shift 14'!M337 -> 18280.88 | H341: =SUM(F341:G341) -> 415418.71
A342: End of worksheet

Sheet Shift 14
A1: =Instructions!P1&" Gross Shift" -> Pay 2014 Gross Shift | D1: n/a | E1: n/a | F1: n/a | G1: n/a | H1: n/a | I1: n/a | J1: n/a | K1: n/a | L1: n/a | M1: n/a | N1: n/a | O1: n/a | P1: n/a | Q1: =Report!I1 -> 41828
A2: Shift at | B2: 0 | C2: n/a | D2: n/a | E2: n/a | F2: n/a | G2: n/a | H2: n/a | I2: n/a | J2: n/a | K2: n/a | L2: n/a | M2: n/a | N2: n/a | O2: n/a | P2: n/a | Q2: n/a
A3: n/a | B3: n/a | C3: n/a | D3: Genl with Aid Adjust | E3: Refer with Aid Adjust | F3: Refer No Aid Adjust | G3: Addl Refer Shift | H3: Career Technical | I3: 100% Shift | J3: Reemploy Resv | K3: Reemploy Unrsv | L3: Leg Changes Genl Fund | M3: Comm Serv at Shift % | N3: Leg Changes Comm Serv | O3: Total Gross Shift | P3: Total General Fund Shift | Q3: Total Comm Serv Fund Shift
A4: n/a | B4: n/a | C4: State Total | D4: =SUM(D6:D337) -> 0 | E4: =SUM(E6:E337) -> 0 | F4: =SUM(F6:F337) -> 1.1422854e+08 | G4: =SUM(G6:G337) -> 4282529.2 | H4: =SUM(H6:H337) -> 13410958 | I4: =SUM(I6:I337) -> 33527326 | J4: =SUM(J6:J337) -> -42970.9 | K4: =SUM(K6:K337) -> 5715999.1 | ... Q4: =SUM(Q6:Q337) -> 0
A5: line left blank intentionally
A6: 1 | B6: 1 | C6: AITKIN | D6: =ROUND(Data!AA8*$B$2,2) -> 0 | E6: =MAX(0,Data!AD8-Data!Y8) -> 0 | F6: =Data!Y8 -> 141143.88 | G6: =Data!X8 -> 0 | H6: =Data!K8+Data!R8 -> 30163.77 | I6: =Data!I8+Data!L8+Data!M8+Data!N8+Data!O8+Data!S8 -> 0 | J6: =Data!Q8 -> 0 | K6: =Data!J8+Data!P8 -> 6695.76 | L6: =Data!T8 -> 0 | M6: =ROUND(Data!AB8*$B$2,2) -> 0 | N6: =Data!U8 -> 0 | O6: =SUM(D6:N6) -> 178003.41 | P6: =SUM(D6:L6) -> 178003.41 | Q6: =SUM(M6:N6) -> 0
A7: 1.2 | B7: 3 | C7: MINNEAPOLIS | D7: =ROUND(Data!AA9*$B$2,2) -> 0 | E7: =MAX(0,Data!AD9-Data!Y9) -> 0 | F7: =Data!Y9 -> 10049626 | G7: =Data!X9 -> 1205612.7 | H7: =Data!K9+Data!R9 -> 677261.48 | I7: =Data!I9+Data!L9+Data!M9+Data!N9+Data!O9+Data!S9 -> 12969267 | J7: =Data!Q9 -> 0 | K7: =Data!J9+Data!P9 -> 652807.7 | L7: =Data!T9 -> 0 | M7: =ROUND(Data!AB9*$B$2,2) -> 0 | N7: =Data!U9 -> 0 | O7: =SUM(D7:N7) -> 25554575 | P7: =SUM(D7:L7) -> 25554575 | Q7: =SUM(M7:N7) -> 0
A8: 2 | B8: 1 | C8: HILL CITY | D8: =ROUND(Data!AA10*$B$2,2) -> 0 | E8: =MAX(0,Data!AD10-Data!Y10) -> 0 | F8: =Data!Y10 -> 0 | G8: =Data!X10 -> 0 | H8: =Data!K10+Data!R10 -> -10000 | I8: =Data!I10+Data!L10+Data!M10+Data!N10+Data!O10+Data!S10 -> 0 | J8: =Data!Q10 -> 0 | K8: =Data!J10+Data!P10 -> -9946.37 | L8: =Data!T10 -> 0 | M8: =ROUND(Data!AB10*$B$2,2) -> 0 | N8: =Data!U10 -> 0 | O8: =SUM(D8:N8) -> -19946.37 | P8: =SUM(D8:L8) -> -19946.37 | Q8: =SUM(M8:N8) -> 0
A9: 4 | B9: 1 | C9: MCGREGOR | D9: =ROUND(Data!AA11*$B$2,2) -> 0 | E9: =MAX(0,Data!AD11-Data!Y11) -> 0 | F9: =Data!Y11 -> 51784.65 | G9: =Data!X11 -> 0 | H9: =Data!K11+Data!R11 -> 10982.92 | I9: =Data!I11+Data!L11+Data!M11+Data!N11+Data!O11+Data!S11 -> 0 | J9: =Data!Q11 -> 0 | K9: =Data!J11+Data!P11 -> 15077.41 | L9: =Data!T11 -> 0 | M9: =ROUND(Data!AB11*$B$2,2) -> 0 | N9: =Data!U11 -> 0 | O9: =SUM(D9:N9) -> 77844.98 | P9: =SUM(D9:L9) -> 77844.98 | Q9: =SUM(M9:N9) -> 0
A10: 6 | B10: 3 | C10: SOUTH ST. PAUL | D10: =ROUND(Data!AA12*$B$2,2) -> 0 | E10: =MAX(0,Data!AD12-Data!Y12) -> 0 | F10: =Data!Y12 -> 360711.07 | G10: =Data!X12 -> 0 | H10: =Data!K12+Data!R12 -> 33145.64 | I10: =Data!I12+Data!L12+Data!M12+Data!N12+Data!O12+Data!S12 -> 0 | J10: =Data!Q12 -> 0 | K10: =Data!J12+Data!P12 -> 18214.15 | L10: =Data!T12 -> 0 | M10: =ROUND(Data!AB12*$B$2,2) -> 0 | N10: =Data!U12 -> 0 | O10: =SUM(D10:N10) -> 412070.86 | P10: =SUM(D10:L10) -> 412070.86 | Q10: =SUM(M10:N10) -> 0
A11: 11 | B11: 1 | C11: ANOKA-HENNEPIN | D11: =ROUND(Data!AA13*$B$2,2) -> 0 | E11: =MAX(0,Data!AD13-Data!Y13) -> 0 | F11: =Data!Y13 -> 3515884.7 | G11: =Data!X13 -> 197692.1 | H11: =Data!K13+Data!R13 -> 502489.57 | I11: =Data!I13+Data!L13+Data!M13+Data!N13+Data!O13+Data!S13 -> 0 | J11: =Data!Q13 -> 0 | K11: =Data!J13+Data!P13 -> -42469.48 | L11: =Data!T13 -> 0 | M11: =ROUND(Data!AB13*$B$2,2) -> 0 | N11: =Data!U13 -> 0 | O11: =SUM(D11:N11) -> 4173596.9 | P11: =SUM(D11:L11) -> 4173596.9 | Q11: =SUM(M11:N11) -> 0
A12: 12 | B12: 1 | C12: CENTENNIAL | D12: =ROUND(Data!AA14*$B$2,2) -> 0 | E12: =MAX(0,Data!AD14-Data!Y14) -> 0 | F12: =Data!Y14 -> 320094.52 | G12: =Data!X14 -> 16533.75 | H12: =Data!K14+Data!R14 -> 51446.72 | I12: =Data!I14+Data!L14+Data!M14+Data!N14+Data!O14+Data!S14 -> 0 | J12: =Data!Q14 -> 0 | K12: =Data!J14+Data!P14 -> 50424.71 | L12: =Data!T14 -> 0 | M12: =ROUND(Data!AB14*$B$2,2) -> 0 | N12: =Data!U14 -> 0 | O12: =SUM(D12:N12) -> 438499.7 | P12: =SUM(D12:L12) -> 438499.7 | Q12: =SUM(M12:N12) -> 0
A13: 13 | B13: 1 | C13: COLUMBIA HEIGHTS | D13: =ROUND(Data!AA15*$B$2,2) -> 0 | E13: =MAX(0,Data!AD15-Data!Y15) -> 0 | F13: =Data!Y15 -> 848958.71 | G13: =Data!X15 -> 0 | H13: =Data!K15+Data!R15 -> 50538.88 | I13: =Data!I15+Data!L15+Data!M15+Data!N15+Data!O15+Data!S15 -> 0 | J13: =Data!Q15 -> 0 | K13: =Data!J15+Data!P15 -> 36973.76 | L13: =Data!T15 -> 0 | M13: =ROUND(Data!AB15*$B$2,2) -> 0 | N13: =Data!U15 -> 0 | O13: =SUM(D13:N13) -> 936471.35 | P13: =SUM(D13:L13) -> 936471.35 | Q13: =SUM(M13:N13) -> 0
A14: 14 | B14: 1 | C14: FRIDLEY | D14: =ROUND(Data!AA16*$B$2,2) -> 0 | E14: =MAX(0,Data!AD16-Data!Y16) -> 0 | F14: =Data!Y16 -> 468605.33 | G14: =Data!X16 -> 0 | H14: =Data!K16+Data!R16 -> 34601.96 | I14: =Data!I16+Data!L16+Data!M16+Data!N16+Data!O16+Data!S16 -> 0 | J14: =Data!Q16 -> 0 | K14: =Data!J16+Data!P16 -> -28231.13 | L14: =Data!T16 -> 0 | M14: =ROUND(Data!AB16*$B$2,2) -> 0 | N14: =Data!U16 -> 0 | O14: =SUM(D14:N14) -> 474976.16 | P14: =SUM(D14:L14) -> 474976.16 | Q14: =SUM(M14:N14) -> 0
A15: 15 | B15: 1 | C15: ST. FRANCIS | D15: =ROUND(Data!AA17*$B$2,2) -> 0 | E15: =MAX(0,Data!AD17-Data!Y17) -> 0 | F15: =Data!Y17 -> 288492.79 | G15: =Data!X17 -> 0 | H15: =Data!K17+Data!R17 -> 75072.48 | I15: =Data!I17+Data!L17+Data!M17+Data!N17+Data!O17+Data!S17 -> 0 | J15: =Data!Q17 -> 0 | K15: =Data!J17+Data!P17 -> 26458.58 | L15: =Data!T17 -> 0 | M15: =ROUND(Data!AB17*$B$2,2) -> 0 | N15: =Data!U17 -> 0 | O15: =SUM(D15:N15) -> 390023.85 | P15: =SUM(D15:L15) -> 390023.85 | Q15: =SUM(M15:N15) -> 0
A16: 16 | B16: 1 | C16: SPRING LAKE PARK | D16: =ROUND(Data!AA18*$B$2,2) -> 0 | E16: =MAX(0,Data!AD18-Data!Y18) -> 0 | F16: =Data!Y18 -> 804793.86 | G16: =Data!X18 -> 73286.44 | H16: =Data!K18+Data!R18 -> 57958.55 | I16: =Data!I18+Data!L18+Data!M18+Data!N18+Data!O18+Data!S18 -> 0 | J16: =Data!Q18 -> 0 | K16: =Data!J18+Data!P18 -> 135923.82 | L16: =Data!T18 -> 0 | M16: =ROUND(Data!AB18*$B$2,2) -> 0 | N16: =Data!U18 -> 0 | O16: =SUM(D16:N16) -> 1071962.7 | P16: =SUM(D16:L16) -> 1071962.7 | Q16: =SUM(M16:N16) -> 0
A17: 22 | B17: 1 | C17: DETROIT LAKES | D17: =ROUND(Data!AA19*$B$2,2) -> 0 | E17: =MAX(0,Data!AD19-Data!Y19) -> 0 | F17: =Data!Y19 -> 133298.49 | G17: =Data!X19 -> 0 | H17: =Data!K19+Data!R19 -> 53846.78 | I17: =Data!I19+Data!L19+Data!M19+Data!N19+Data!O19+Data!S19 -> 0 | J17: =Data!Q19 -> 0 | K17: =Data!J19+Data!P19 -> 29758.83 | L17: =Data!T19 -> 0 | M17: =ROUND(Data!AB19*$B$2,2) -> 0 | N17: =Data!U19 -> 0 | O17: =SUM(D17:N17) -> 216904.1 | P17: =SUM(D17:L17) -> 216904.1 | Q17: =SUM(M17:N17) -> 0
... A337: 2908 | B337: 1 | C337: BRANDON-EVANSVILLE | D337: =ROUND(Data!AA339*$B$2,2) -> 0 | E337: =MAX(0,Data!AD339-Data!Y339) -> 0 | F337: =Data!Y339 -> 0 | G337: =Data!X339 -> 0 | H337: =Data!K339+Data!R339 -> 26815.88 | I337: =Data!I339+Data!L339+Data!M339+Data!N339+Data!O339+Data!S339 -> 0 | J337: =Data!Q339 -> -4306.76 | K337: =Data!J339+Data!P339 -> -493.12 | L337: =Data!T339 -> 0 | M337: =ROUND(Data!AB339*$B$2,2) -> 0 | N337: =Data!U339 -> 0 | O337: =SUM(D337:N337) -> 22016 | P337: =SUM(D337:L337) -> 22016 | Q337: =SUM(M337:N337) -> 0
A338: line left blank intentionally
A339: line left blank intentionally
A340: line left blank intentionally | D340: =+D4 -> 0
A341: n/a | B341: n/a | C341: n/a | D341: 2.4944824e+08
A342: n/a | B342: n/a | C342: n/a | D342: =+D340-D341 -> -2.4944824e+08
A343: End of worksheet

Sheet Data
A1: =Levy!A3 -> Pay 2014 Levy | I1: Pay 2014 Levy Summary data (G:\Finance\LEVY\levy summaries\…\......xls) | AD1: =Report!I1 -> 41828
I2: From Certified Levy Summaries
I3: dsg_lvy | J3: mnt_lvy_ini_une | K3: car_tec_lvy_crt | L3: hea_ben_lvy | M3: add_ret_lvy | N3: dsg_adj_lvy | O3: dsg_adj_lvy_2 | P3: une_adj_lvy | Q3: mnt_lvy_une_fb1 | R3: car_tec_adj_lvy | S3: hea_ben_adj_lvy | V3: ref_mkt_err_crt | W3: ref_tcp_err_crt | X3: fixed | Y3: fixed
D4: Genl RMV Voter | E4: Genl RMV Other | F4: Genl NTC Voter | G4: Genl NTC Other | H4: Comm Service | I4: Integ--1st Class | J4: Reemploy | K4: Career Technical | L4: Hea Ben | M4: Addl Retire | N4: Int Adj PY--1st Class | O4: Int Adj 2YP--1st Class | P4: Reemploy Adjust Unreserved | Q4: Reemploy Adjust Reserved | R4: Career Tech Adjust | S4: Hea Ben Adjust | T4: Legislative Changes Genl Fund | U4: Legislative Changes Comm Serv | V4: Prinsburg Exclusion RMV Voter | W4: Prinsburg Exclusion NTC Voter | X4: Add'l Referendum | Y4: Pay 2001 Refer Shift | Z4: 100% Shift Total | AA4: Shiftable Oth Gen (E+F+G-U-X-Y-AA) | AB4: Shiftable Comm Serv (H-T-V) | AC4: =Instructions!P1&" Refer at Shift Percent" -> Pay 2014 Refer at Shift Percent | AD4: ="Refer (GTR of "&Instructions!P1&" or Pay 2001)" -> Refer (GTR of Pay 2014 or Pay 2001) | AZ4: Add'l Referendum | BA4: Pay 2001 Refer Shift
AA5: 5.0894653e+08 | AB5: 73254628 | AZ5: 4282529.2 | BA5: 1.1422854e+08
C6: State Total | D6: =SUM(D8:D339) -> 5.3052543e+08 | E6: =SUM(E8:E339) -> 3.3639926e+08 | F6: =SUM(F8:F339) -> 60897104 | G6: =SUM(G8:G339) -> 4.8154312e+08 | H6: =SUM(H8:H339) -> 74876386 | I6: =SUM(I8:I339) -> 10042493 | J6: =SUM(J8:J339) -> 8090511.2 | K6: =SUM(K8:K339) -> 16370041 | ... AD6: =SUM(AD8:AD339) -> 1.1422854e+08 | AY6: State Total | AZ6: =SUM(AZ8:AZ339) -> 4282529.2 | BA6: =SUM(BA8:BA339) -> 1.1422854e+08
AF7: dst_num | AG7: dst_tye | AH7: ref_mkt_err_crt | AI7: ref_tcp_err_crt | AJ7: dsg_lvy | AK7: mnt_lvy_ini_une | AL7: car_tec_lvy_crt | AM7: hea_ben_lvy | AN7: add_ret_lvy | AO7: dsg_adj_lvy | AP7: dsg_adj_lvy_2 | AQ7: une_adj_lvy | AR7: mnt_lvy_une_fb1 | AS7: car_tec_adj_lvy | AT7: hea_ben_adj_lvy | AV7: cos-num | AW7: dist | AX7: type
A8: 1 | B8: 1 | C8: AITKIN | D8: =Levy!F9 -> 3 | E8: =Levy!G9 -> 512160 | F8: =Levy!H9 -> 0 | G8: =Levy!I9 -> 376935 | H8: =Levy!J9 -> 0 | I8: 0 | J8: 7000 | K8: 34841.34 | L8: 0 | M8: 0 | N8: 0 | O8: 0 | P8: -304.24 | Q8: 0 | R8: -4677.57 | S8: 0 | T8: 0 | U8: 0 | V8: 0 | W8: 0 | X8: 0 | Y8: 141143.88 | Z8: =SUM(I8:T8) -> 36859.53 | AA8: =ROUND(MAX(E8+F8+G8-W8-X8-Z8,0),2) -> 852235.47 | AB8: =ROUND(MAX(H8-U8,0),2) -> 0 | AC8: =ROUND(MAX(0,(D8-V8)*'Shift 14'!$B$2),2) -> 0 | AD8: =MAX(AC8,Y8) -> 141143.88 | AE8: =AF8-A8 -> 0 | AF8: 1 | AG8: 1 | AH8: 0 | AI8: 0 | AJ8: 0 | AK8: 7000 | AL8: 34841.34 | AM8: 0 | AN8: 0 | AO8: 0 | AP8: 0 | AQ8: -304.24 | AR8: 0 | AS8: -4677.57 | AT8: 0 | AU8: =AV8-A8 -> 0 | AV8: 1 | AW8: 1 | AX8: 1 | AY8: AITKIN | AZ8: 0 | BA8: 141143.88
A9: 1.2 | B9: 3 | C9: MINNEAPOLIS | D9: =Levy!F10 -> 42963957 | E9: =Levy!G10 -> 32244453 | F9: =Levy!H10 -> 0 | G9: =Levy!I10 -> 40377225 | H9: =Levy!J10 -> 4958085 | I9: 4400061 | J9: 1000000 | K9: 705788.41 | L9: 0 | M9: 8470800 | N9: 0 | O9: 98405.69 | P9: -347192.3 | Q9: 0 | R9: -28526.93 | S9: 0 | T9: 0 | U9: 0 | V9: 0 | W9: 0 | X9: 1205612.7 | Y9: 10049626 | Z9: =SUM(I9:T9) -> 14299336 | AA9: =ROUND(MAX(E9+F9+G9-W9-X9-Z9,0),2) -> 57116729 | AB9: =ROUND(MAX(H9-U9,0),2) -> 4958085 | AC9: =ROUND(MAX(0,(D9-V9)*'Shift 14'!$B$2),2) -> 0 | AD9: =MAX(AC9,Y9) -> 10049626 | AE9: =AF9-A9 -> 0 | AF9: 1.2 | AG9: 3 | AH9: 0 | AI9: 0 | AJ9: 4400061 | AK9: 1000000 | AL9: 705788.41 | AM9: 0 | AN9: 8470800 | AO9: 0 | AP9: 98405.69 | AQ9: -347192.3 | AR9: 0 | AS9: -28526.93 | AT9: 0 | AU9: =AV9-A9 -> 0 | AV9: 1.2 | AW9: 1.2 | AX9: 3 | AY9: MINNEAPOLIS | AZ9: 1205612.7 | BA9: 10049626
A10: 2 | B10: 1 | C10: HILL CITY | D10: =Levy!F11 -> 0 | E10: =Levy!G11 -> 55347 | F10: =Levy!H11 -> 0 | G10: =Levy!I11 -> 61170 | H10: =Levy!J11 -> 18559 | I10: 0 | J10: 0 | K10: 0 | L10: 0 | M10: 0 | N10: 0 | O10: 0 | P10: -9946.37 | Q10: 0 | R10: -10000 | S10: 0 | T10: 0 | U10: 0 | V10: 0 | W10: 0 | X10: 0 | Y10: 0 | Z10: =SUM(I10:T10) -> -19946.37 | AA10: =ROUND(MAX(E10+F10+G10-W10-X10-Z10,0),2) -> 136463.37 | AB10: =ROUND(MAX(H10-U10,0),2) -> 18559 | AC10: =ROUND(MAX(0,(D10-V10)*'Shift 14'!$B$2),2) -> 0 | AD10: =MAX(AC10,Y10) -> 0 | AE10: =AF10-A10 -> 0 | AF10: 2 | AG10: 1 | AH10: 0 | AI10: 0 | AJ10: 0 | AK10: 0 | AL10: 0 | AM10: 0 | AN10: 0 | AO10: 0 | AP10: 0 | AQ10: -9946.37 | AR10: 0 | AS10: -10000 | AT10: 0 | AU10: =AV10-A10 -> 0 | AV10: 2 | AW10: 2 | AX10: 1 | AY10: HILL CITY | AZ10: 0 | BA10: 0
A11: 4 | B11: 1 | C11: MCGREGOR | D11: =Levy!F12 -> 375 | E11: =Levy!G12 -> 100950 | F11: =Levy!H12 -> 0 | G11: =Levy!I12 -> 319645 | H11: =Levy!J12 -> 53030 | I11: 0 | J11: 7300 | K11: 12648 | L11: 0 | M11: 0 | N11: 0 | O11: 0 | P11: 7777.41 | Q11: 0 | R11: -1665.08 | S11: 0 | T11: 0 | U11: 0 | V11: 0 | W11: 0 | X11: 0 | Y11: 51784.65 | Z11: =SUM(I11:T11) -> 26060.33 | AA11: =ROUND(MAX(E11+F11+G11-W11-X11-Z11,0),2) -> 394534.67 | AB11: =ROUND(MAX(H11-U11,0),2) -> 53030 | AC11: =ROUND(MAX(0,(D11-V11)*'Shift 14'!$B$2),2) -> 0 | AD11: =MAX(AC11,Y11) -> 51784.65 | AE11: =AF11-A11 -> 0 | AF11: 4 | AG11: 1 | AH11: 0 | AI11: 0 | AJ11: 0 | AK11: 7300 | AL11: 12648 | AM11: 0 | AN11: 0 | AO11: 0 | AP11: 0 | AQ11: 7777.41 | AR11: 0 | AS11: -1665.08 | AT11: 0 | AU11: =AV11-A11 -> 0 | AV11: 4 | AW11: 4 | AX11: 1 | AY11: MCGREGOR | AZ11: 0 | BA11: 51784.65
A12: 6 | B12: 3 | C12: SOUTH ST. PAUL | D12: =Levy!F13 -> 1109814 | E12: =Levy!G13 -> 1607848 | F12: =Levy!H13 -> 522346 | G12: =Levy!I13 -> 2118168 | H12: =Levy!J13 -> 313589 | I12: 0 | J12: 26700 | K12: 45409.2 | L12: 0 | M12: 0 | N12: 0 | O12: 0 | P12: -8485.85 | Q12: 0 | R12: -12263.56 | S12: 0 | T12: 0 | U12: 0 | V12: 0 | W12: 0 | X12: 0 | Y12: 360711.07 | Z12: =SUM(I12:T12) -> 51359.79 | AA12: =ROUND(MAX(E12+F12+G12-W12-X12-Z12,0),2) -> 4197002.2 | AB12: =ROUND(MAX(H12-U12,0),2) -> 313589 | AC12: =ROUND(MAX(0,(D12-V12)*'Shift 14'!$B$2),2) -> 0 | AD12: =MAX(AC12,Y12) -> 360711.07 | AE12: =AF12-A12 -> 0 | AF12: 6 | AG12: 3 | AH12: 0 | AI12: 0 | AJ12: 154304.54 | AK12: 26700 | AL12: 45409.2 | AM12: 0 | AN12: 0 | AO12: 0 | AP12: -1881.17 | AQ12: -8485.85 | AR12: 0 | AS12: -12263.56 | AT12: 0 | AU12: =AV12-A12 -> 0 | AV12: 6 | AW12: 6 | AX12: 3 | AY12: SOUTH ST. PAUL | AZ12: 0 | BA12: 360711.07
A13: 11 | B13: 1 | C13: ANOKA-HENNEPIN | D13: =Levy!F14 -> 26446869 | E13: =Levy!G14 -> 15845308 | F13: =Levy!H14 -> 2728226 | G13: =Levy!I14 -> 23560897 | H13: =Levy!J14 -> 3085048.6 | I13: 0 | J13: 100000 | K13: 652459.11 | L13: 0 | M13: 0 | N13: 0 | O13: 0 | P13: -142469.48 | Q13: 0 | R13: -149969.54 | S13: 0 | T13: 0 | U13: 0 | V13: 0 | W13: 0 | X13: 197692.1 | Y13: 3515884.7 | Z13: =SUM(I13:T13) -> 460020.09 | AA13: =ROUND(MAX(E13+F13+G13-W13-X13-Z13,0),2) -> 41476719 | AB13: =ROUND(MAX(H13-U13,0),2) -> 3085048.6 | AC13: =ROUND(MAX(0,(D13-V13)*'Shift 14'!$B$2),2) -> 0 | AD13: =MAX(AC13,Y13) -> 3515884.7 | AE13: =AF13-A13 -> 0 | AF13: 11 | AG13: 1 | AH13: 0 | AI13: 0 | AJ13: 1502416.4 | AK13: 100000 | AL13: 652459.11 | AM13: 0 | AN13: 0 | AO13: 0 | AP13: 288.18 | AQ13: -142469.48 | AR13: 0 | AS13: -149969.54 | AT13: 0 | AU13: =AV13-A13 -> 0 | AV13: 11 | AW13: 11 | AX13: 1 | AY13: ANOKA-HENNEPIN | AZ13: 197692.1 | BA13: 3515884.7
A14: 12 | B14: 1 | C14: CENTENNIAL | D14: =Levy!F15 -> 1845321.4 | E14: =Levy!G15 -> 3019153.1 | F14: =Levy!H15 -> 0 | G14: =Levy!I15 -> 4960893.5 | H14: =Levy!J15 -> 413840.61 | I14: 0 | J14: 25000 | K14: 67877.92 | L14: 0 | M14: 0 | N14: 0 | O14: 0 | P14: 25424.71 | Q14: 0 | R14: -16431.2 | S14: 0 | T14: 0 | U14: 0 | V14: 0 | W14: 0 | X14: 16533.75 | Y14: 320094.52 | Z14: =SUM(I14:T14) -> 101871.43 | AA14: =ROUND(MAX(E14+F14+G14-W14-X14-Z14,0),2) -> 7861641.5 | AB14: =ROUND(MAX(H14-U14,0),2) -> 413840.61 | AC14: =ROUND(MAX(0,(D14-V14)*'Shift 14'!$B$2),2) -> 0 | AD14: =MAX(AC14,Y14) -> 320094.52 | AE14: =AF14-A14 -> 0 | AF14: 12 | AG14: 1 | AH14: 0 | AI14: 0 | AJ14: 0 | AK14: 25000 | AL14: 67877.92 | AM14: 0 | AN14: 0 | AO14: 0 | AP14: 0 | AQ14: 25424.71 | AR14: 0 | AS14: -16431.2 | AT14: 0 | AU14: =AV14-A14 -> 0 | AV14: 12 | AW14: 12 | AX14: 1 | AY14: CENTENNIAL | AZ14: 16533.75 | BA14: 320094.52
A15: 13 | B15: 1 | C15: COLUMBIA HEIGHTS | D15: =Levy!F16 -> 999598.58 | E15: =Levy!G16 -> 1846818.2 | F15: =Levy!H16 -> 0 | G15: =Levy!I16 -> 1950276.2 | H15: =Levy!J16 -> 404050.21 | I15: 0 | J15: 22414.64 | K15: 57533.58 | L15: 0 | M15: 0 | N15: 0 | O15: 0 | P15: 14559.12 | Q15: 0 | R15: -6994.7 | S15: 0 | T15: 0 | U15: 0 | V15: 0 | W15: 0 | X15: 0 | Y15: 848958.71 | Z15: =SUM(I15:T15) -> 87512.64 | AA15: =ROUND(MAX(E15+F15+G15-W15-X15-Z15,0),2) -> 3709581.8 | AB15: =ROUND(MAX(H15-U15,0),2) -> 404050.21 | AC15: =ROUND(MAX(0,(D15-V15)*'Shift 14'!$B$2),2) -> 0 | AD15: =MAX(AC15,Y15) -> 848958.71 | AE15: =AF15-A15 -> 0 | AF15: 13 | AG15: 1 | AH15: 0 | AI15: 0 | AJ15: 19944.57 | AK15: 22414.64 | AL15: 57533.58 | AM15: 0 | AN15: 0 | AO15: 0 | AP15: 0 | AQ15: 14559.12 | AR15: 0 | AS15: -6994.7 | AT15: 0 | AU15: =AV15-A15 -> 0 | AV15: 13 | AW15: 13 | AX15: 1 | AY15: COLUMBIA HEIGHTS | AZ15: 0 | BA15: 848958.71
A16: 14 | B16: 1 | C16: FRIDLEY | D16: =Levy!F17 -> 799891.31 | E16: =Levy!G17 -> 1293258.1 | F16: =Levy!H17 -> 651253 | G16: =Levy!I17 -> 1382396.7 | H16: =Levy!J17 -> 321785.77 | I16: 0 | J16: 40000 | K16: 44391.45 | L16: 0 | M16: 0 | N16: 0 | O16: 0 | P16: -68231.13 | Q16: 0 | R16: -9789.49 | S16: 0 | T16: 0 | U16: 0 | V16: 0 | W16: 0 | X16: 0 | Y16: 468605.33 | Z16: =SUM(I16:T16) -> 6370.83 | AA16: =ROUND(MAX(E16+F16+G16-W16-X16-Z16,0),2) -> 3320537 | AB16: =ROUND(MAX(H16-U16,0),2) -> 321785.77 | AC16: =ROUND(MAX(0,(D16-V16)*'Shift 14'!$B$2),2) -> 0 | AD16: =MAX(AC16,Y16) -> 468605.33 | AE16: =AF16-A16 -> 0 | AF16: 14 | AG16: 1 | AH16: 0 | AI16: 0 | AJ16: 155039.36 | AK16: 40000 | AL16: 44391.45 | AM16: 0 | AN16: 0 | AO16: 0 | AP16: 0 | AQ16: -68231.13 | AR16: 0 | AS16: -9789.49 | AT16: 0 | AU16: =AV16-A16 -> 0 | AV16: 14 | AW16: 14 | AX16: 1 | AY16: FRIDLEY | AZ16: 0 | BA16: 468605.33
A17: 15 | B17: 1 | C17: ST. FRANCIS | D17: =Levy!F18 -> 0 | E17: =Levy!G18 -> 2815887.7 | F17: =Levy!H18 -> 0 | G17: =Levy!I18 -> 1739098.9 | H17: =Levy!J18 -> 353468.71 | I17: 0 | J17: 60000 | K17: 104874.58 | L17: 0 | M17: 0 | N17: 0 | O17: 0 | P17: -33541.42 | Q17: 0 | R17: -29802.1 | S17: 0 | T17: 0 | U17: 0 | V17: 0 | W17: 0 | X17: 0 | Y17: 288492.79 | Z17: =SUM(I17:T17) -> 101531.06 | AA17: =ROUND(MAX(E17+F17+G17-W17-X17-Z17,0),2) -> 4453455.5 | AB17: =ROUND(MAX(H17-U17,0),2) -> 353468.71 | AC17: =ROUND(MAX(0,(D17-V17)*'Shift 14'!$B$2),2) -> 0 | AD17: =MAX(AC17,Y17) -> 288492.79 | AE17: =AF17-A17 -> 0 | AF17: 15 | AG17: 1 | AH17: 0 | AI17: 0 | AJ17: 0 | AK17: 60000 | AL17: 104874.58 | AM17: 0 | AN17: 0 | AO17: 0 | AP17: 0 | AQ17: -33541.42 | AR17: 0 | AS17: -29802.1 | AT17: 0 | AU17: =AV17-A17 -> 0 | AV17: 15 | AW17: 15 | AX17: 1 | AY17: ST. FRANCIS | AZ17: 0 | BA17: 288492.79
A18: 16 | B18: 1 | C18: SPRING LAKE PARK | D18: =Levy!F19 -> 2046138.2 | E18: =Levy!G19 -> 3636327.6 | F18: =Levy!H19 -> 940446 | G18: =Levy!I19 -> 3060271.5 | H18: =Levy!J19 -> 461412.97 | I18: 0 | J18: 100000 | K18: 80264.11 | L18: 0 | M18: 0 | N18: 0 | O18: 0 | P18: 35923.82 | Q18: 0 | R18: -22305.56 | S18: 0 | T18: 0 | U18: 0 | V18: 0 | W18: 0 | X18: 73286.44 | Y18: 804793.86 | Z18: =SUM(I18:T18) -> 193882.37 | AA18: =ROUND(MAX(E18+F18+G18-W18-X18-Z18,0),2) -> 7369876.3 | AB18: =ROUND(MAX(H18-U18,0),2) -> 461412.97 | AC18: =ROUND(MAX(0,(D18-V18)*'Shift 14'!$B$2),2) -> 0 | AD18: =MAX(AC18,Y18) -> 804793.86 | AE18: =AF18-A18 -> 0 | AF18: 16 | AG18: 1 | AH18: 0 | AI18: 0 | AJ18: 220864.07 | AK18: 100000 | AL18: 80264.11 | AM18: 0 | AN18: 0 | AO18: 0 | AP18: 0 | AQ18: 35923.82 | AR18: 0 | AS18: -22305.56 | AT18: 0 | AU18: =AV18-A18 -> 0 | AV18: 16 | AW18: 16 | AX18: 1 | AY18: SPRING LAKE PARK | AZ18: 73286.44 | BA18: 804793.86
A19: 22 | B19: 1 | C19: DETROIT LAKES | D19: =Levy!F20 -> 408798.15 | E19: =Levy!G20 -> 1057760.7 | F19: =Levy!H20 -> 0 | G19: =Levy!I20 -> 1282085.8 | H19: =Levy!J20 -> 214519.78 | I19: 0 | J19: 7231.58 | K19: 59281.47 | L19: 0 | M19: 0 | N19: 0 | O19: 0 | P19: 22527.25 | Q19: 0 | R19: -5434.69 | S19: 0 | T19: 0 | U19: 0 | V19: 0 | W19: 0 | X19: 0 | Y19: 133298.49 | Z19: =SUM(I19:T19) -> 83605.61 | AA19: =ROUND(MAX(E19+F19+G19-W19-X19-Z19,0),2) -> 2256240.9 | AB19: =ROUND(MAX(H19-U19,0),2) -> 214519.78 | AC19: =ROUND(MAX(0,(D19-V19)*'Shift 14'!$B$2),2) -> 0 | AD19: =MAX(AC19,Y19) -> 133298.49 | AE19: =AF19-A19 -> 0 | AF19: 22 | AG19: 1 | AH19: 0 | AI19: 0 | AJ19: 82342.7 | AK19: 7231.58 | AL19: 59281.47 | AM19: 0 | AN19: 0 | AO19: 0 | AP19: -282.92 | AQ19: 22527.25 | AR19: 0 | AS19: -5434.69 | AT19: 0 | AU19: =AV19-A19 -> 0 | AV19: 22 | AW19: 22 | AX19: 1 | AY19: DETROIT LAKES | AZ19: 0 | BA19: 133298.49
... A315: 2759 | B315: 1 | C315: EAGLE VALLEY PUBLIC SCH | D315: =Levy!F316 -> 150574 | E315: =Levy!G316 -> 14547 | F315: =Levy!H316 -> 0 | G315: =Levy!I316 -> 124797 | H315: =Levy!J316 -> 21800 | I315: 0 | J315: 4000 | K315: 19040.69 | L315: 0 | M315: 0 | N315: 0 | O315: 0 | P315: 5924.22 | Q315: 0 | R315: -15573.1 | S315: 0 | T315: 0 | U315: 0 | V315: 0 | W315: 0 | X315: 0 | Y315: 12843.72 | Z315: =SUM(I315:T315) -> 13391.81 | AA315: =ROUND(MAX(E315+F315+G315-W315-X315-Z315,0),2) -> 125952.19 | AB315: =ROUND(MAX(H315-U315,0),2) -> 21800 | AC315: =ROUND(MAX(0,(D315-V315)*'Shift 14'!$B$2),2) -> 0 | AD315: =MAX(AC315,Y315) -> 12843.72 | AE315: =AF315-A315 -> 0 | AF315: 2759 | AG315: 1 | AH315: 0 | AI315: 0 | AJ315: 5824.85 | AK315: 4000 | AL315: 19040.69 | AM315: 0 | AN315: 0 | AO315: 0 | AP315: -2854.68 | AQ315: 5924.22 | AR315: 0 | AS315: -15573.1 | AT315: 0 | AU315: =AV315-A315 -> 0 | AV315: 2759 | AW315: 2759 | AX315: 1 | AY315: EAGLE VALLEY PUB | AZ315: 0 | BA315: 12843.72
A316: 2769 | B316: 1 | C316: MORRIS AREA | D316: =Levy!F317 -> 703989.99 | E316: =Levy!G317 -> 82347.59 | F316: =Levy!H317 -> 0 | G316: =Levy!I317 -> 494106 | H316: =Levy!J317 -> 109108 | I316: 0 | J316: 2500 | K316: 22251.37 | L316: 0 | M316: 0 | N316: 0 | O316: 0 | P316: -22078.85 | Q316: 0 | R316: 0 | S316: 0 | T316: 0 | U316: 0 | V316: 0 | W316: 0 | X316: 0 | Y316: 185416.57 | Z316: =SUM(I316:T316) -> 2672.52 | AA316: =ROUND(MAX(E316+F316+G316-W316-X316-Z316,0),2) -> 573781.07 | AB316: =ROUND(MAX(H316-U316,0),2) -> 109108 | AC316: =ROUND(MAX(0,(D316-V316)*'Shift 14'!$B$2),2) -> 0 | AD316: =MAX(AC316,Y316) -> 185416.57 | AE316: =AF316-A316 -> 0 | AF316: 2769 | AG316: 1 | AH316: 0 | AI316: 0 | AJ316: 0 | AK316: 2500 | AL316: 22251.37 | AM316: 0 | AN316: 0 | AO316: 0 | AP316: 0 | AQ316: -22078.85 | AR316: 0 | AS316: 0 | AT316: 0 | AU316: =AV316-A316 -> 0 | AV316: 2769 | AZ316: 0 | BA316: 185416.57
A317: 2805 | B317: 1 | C317: ZUMBROTA-MAZEPPA | D317: =Levy!F318 -> 1363042 | E317: =Levy!G318 -> 77942 | F317: =Levy!H318 -> 0 | G317: =Levy!I318 -> 435534 | H317: =Levy!J318 -> 162012 | I317: 0 | J317: 1260 | K317: 23125.19 | L317: 0 | M317: 0 | N317: 0 | O317: 0 | P317: -229.4 | Q317: 0 | R317: -3915.03 | S317: 0 | T317: 0 | U317: 0 | V317: 0 | W317: 0 | X317: 0 | Y317: 152693.4 | Z317: =SUM(I317:T317) -> 20240.76 | AA317: =ROUND(MAX(E317+F317+G317-W317-X317-Z317,0),2) -> 493235.24 | AB317: =ROUND(MAX(H317-U317,0),2) -> 162012 | AC317: =ROUND(MAX(0,(D317-V317)*'Shift 14'!$B$2),2) -> 0 | AD317: =MAX(AC317,Y317) -> 152693.4 | AE317: =AF317-A317 -> 0 | AF317: 2805 | AG317: 1 | AH317: 0 | AI317: 0 | AJ317: 5115.3 | AK317: 1260 | AL317: 23125.19 | AM317: 0 | AN317: 0 | AO317: 0 | AP317: -8873.14 | AQ317: -229.4 | AR317: 0 | AS317: -3915.03 | AT317: 0 | AU317: =AV317-A317 -> 0 | AV317: 2805 | AW317: 2805 | AX317: 1 | AY317: ZUMBROTA-MAZEPPA | AZ317: 0 | BA317: 152693.4
A318: 2835 | B318: 1 | C318: JANESVILLE-WALDORF-P | D318: =Levy!F319 -> 1137922 | E318: =Levy!G319 -> 26113 | F318: =Levy!H319 -> 0 | G318: =Levy!I319 -> 283378 | H318: =Levy!J319 -> 39108 | I318: 0 | J318: 0 | K318: 25035.79 | L318: 0 | M318: 0 | N318: 0 | O318: 0 | P318: 4426.32 | Q318: 0 | R318: -3109.09 | S318: 0 | T318: 0 | U318: 0 | V318: 0 | W318: 0 | X318: 0 | Y318: 161255.4 | Z318: =SUM(I318:T318) -> 26353.02 | AA318: =ROUND(MAX(E318+F318+G318-W318-X318-Z318,0),2) -> 283137.98 | AB318: =ROUND(MAX(H318-U318,0),2) -> 39108 | AC318: =ROUND(MAX(0,(D318-V318)*'Shift 14'!$B$2),2) -> 0 | AD318: =MAX(AC318,Y318) -> 161255.4 | AE318: =AF318-A318 -> 0 | AF318: 2835 | AG318: 1 | AH318: 0 | AI318: 0 | AJ318: 0 | AK318: 0 | AL318: 25035.79 | AM318: 0 | AN318: 0 | AO318: 0 | AP318: 0 | AQ318: 4426.32 | AR318: 0 | AS318: -3109.09 | AT318: 0 | AU318: =AV318-A318 -> 0 | AV318: 2835 | AW318: 2835 | AX318: 1 | AY318: JANESVILLE-WALDO | AZ318: 0 | BA318: 161255.4
A319: 2853 | B319: 1 | C319: LAC QUI PARLE VALLEY | D319: =Levy!F320 -> 631998.12 | E319: =Levy!G320 -> 42206.59 | F319: =Levy!H320 -> 0 | G319: =Levy!I320 -> 555056.43 | H319: =Levy!J320 -> 110947.01 | I319: 0 | J319: 0 | K319: 40286.95 | L319: 0 | M319: 0 | N319: 0 | O319: 0 | P319: 5382.45 | Q319: 0 | R319: -5003.07 | S319: 0 | T319: 0 | U319: 0 | V319: 0 | W319: 0 | X319: 642.47 | Y319: 88378.21 | Z319: =SUM(I319:T319) -> 40666.33 | AA319: =ROUND(MAX(E319+F319+G319-W319-X319-Z319,0),2) -> 555954.22 | AB319: =ROUND(MAX(H319-U319,0),2) -> 110947.01 | AC319: =ROUND(MAX(0,(D319-V319)*'Shift 14'!$B$2),2) -> 0 | AD319: =MAX(AC319,Y319) -> 88378.21 | AE319: =AF319-A319 -> 0 | AF319: 2853 | AG319: 1 | AH319: 0 | AI319: 0 | AJ319: 0 | AK319: 0 | AL319: 40286.95 | AM319: 0 | AN319: 0 | AO319: 0 | AP319: 0 | AQ319: 5382.45 | AR319: 0 | AS319: -5003.07 | AT319: 0 | AU319: =AV319-A319 -> 0 | AV319: 2853 | AW319: 2853 | AX319: 1 | AY319: LAC QUI PARLE VA | AZ319: 642.47 | BA319: 88378.21
A320: 2854 | B320: 1 | C320: ADA-BORUP | D320: =Levy!F321 -> 160837.45 | E320: =Levy!G321 -> 24169.25 | F320: =Levy!H321 -> 0 | G320: =Levy!I321 -> 271627.65 | H320: =Levy!J321 -> 41483.87 | I320: 0 | J320: 0 | K320: 32245.36 | L320: 0 | M320: 0 | N320: 0 | O320: 0 | P320: -1416.41 | Q320: 0 | R320: 0 | S320: 0 | T320: 0 | U320: 0 | V320: 0 | W320: 0 | X320: 0 | Y320: 40913.34 | Z320: =SUM(I320:T320) -> 30828.95 | AA320: =ROUND(MAX(E320+F320+G320-W320-X320-Z320,0),2) -> 264967.95 | AB320: =ROUND(MAX(H320-U320,0),2) -> 41483.87 | AC320: =ROUND(MAX(0,(D320-V320)*'Shift 14'!$B$2),2) -> 0 | AD320: =MAX(AC320,Y320) -> 40913.34 | AE320: =AF320-A320 -> 0 | AF320: 2854 | AG320: 1 | AH320: 0 | AI320: 0 | AJ320: 0 | AK320: 0 | AL320: 32245.36 | AM320: 0 | AN320: 0 | AO320: 0 | AP320: 0 | AQ320: -1416.41 | AR320: 0 | AS320: 0 | AT320: 0 | AU320: =AV320-A320 -> 0 | AV320: 2854 | AW320: 2854 | AX320: 1 | AY320: ADA-BORUP | AZ320: 0 | BA320: 40913.34
A321: 2856 | B321: 1 | C321: STEPHEN-ARGYLE CENTRAL | D321: =Levy!F322 -> 424472.78 | E321: =Levy!G322 -> 18886.57 | F321: =Levy!H322 -> 0 | G321: =Levy!I322 -> 111396 | H321: =Levy!J322 -> 54255.98 | I321: 0 | J321: 10000 | K321: 13407.94 | L321: 0 | M321: 0 | N321: 0 | O321: 0 | P321: 3888.54 | Q321: 0 | R321: -1665.08 | S321: 0 | T321: 0 | U321: 0 | V321: 0 | W321: 0 | X321: 2021.24 | Y321: 122060.62 | Z321: =SUM(I321:T321) -> 25631.4 | AA321: =ROUND(MAX(E321+F321+G321-W321-X321-Z321,0),2) -> 102629.93 | AB321: =ROUND(MAX(H321-U321,0),2) -> 54255.98 | AC321: =ROUND(MAX(0,(D321-V321)*'Shift 14'!$B$2),2) -> 0 | AD321: =MAX(AC321,Y321) -> 122060.62 | AE321: =AF321-A321 -> 0 | AF321: 2856 | AG321: 1 | AH321: 0 | AI321: 0 | AJ321: 0 | AK321: 10000 | AL321: 13407.94 | AM321: 0 | AN321: 0 | AO321: 0 | AP321: 0 | AQ321: 3888.54 | AR321: 0 | AS321: -1665.08 | AT321: 0 | AU321: =AV321-A321 -> 0 | AV321: 2856 | AW321: 2856 | AX321: 1 | AY321: STEPHEN-ARGYLE C | AZ321: 2021.24 | BA321: 122060.62
A322: 2859 | B322: 1 | C322: GLENCOE-SILVER LAKE | D322: =Levy!F323 -> 373599 | E322: =Levy!G323 -> 712914 | F322: =Levy!H323 -> 0 | G322: =Levy!I323 -> 695676 | H322: =Levy!J323 -> 164774 | I322: 0 | J322: 20000 | K322: 40300.89 | L322: 0 | M322: 0 | N322: 0 | O322: 0 | P322: 0 | Q322: 0 | R322: -10841.44 | S322: 0 | T322: 0 | U322: 0 | V322: 0 | W322: 0 | X322: 3949.77 | Y322: 168353.22 | Z322: =SUM(I322:T322) -> 49459.45 | AA322: =ROUND(MAX(E322+F322+G322-W322-X322-Z322,0),2) -> 1355180.8 | AB322: =ROUND(MAX(H322-U322,0),2) -> 164774 | AC322: =ROUND(MAX(0,(D322-V322)*'Shift 14'!$B$2),2) -> 0 | AD322: =MAX(AC322,Y322) -> 168353.22 | AE322: =AF322-A322 -> 0 | AF322: 2859 | AG322: 1 | AH322: 0 | AI322: 0 | AJ322: 0 | AK322: 20000 | AL322: 40300.89 | AM322: 0 | AN322: 0 | AO322: 0 | AP322: 0 | AQ322: 0 | AR322: 0 | AS322: -10841.44 | AT322: 0 | AU322: =AV322-A322 -> 0 | AV322: 2859 | AW322: 2859 | AX322: 1 | AY322: GLENCOE-SILVER L | AZ322: 3949.77 | BA322: 168353.22
A323: 2860 | B323: 1 | C323: BLUE EARTH AREA | D323: =Levy!F324 -> 406622.81 | E323: =Levy!G324 -> 79740.65 | F323: =Levy!H324 -> 0 | G323: =Levy!I324 -> 521253.24 | H323: =Levy!J324 -> 137522.94 | I323: 0 | J323: 0 | K323: 0 | L323: 0 | M323: 0 | N323: 0 | O323: 0 | P323: 9583.94 | Q323: -9583.94 | R323: 0 | S323: 0 | T323: 0 | U323: 0 | V323: 0 | W323: 0 | X323: 0 | Y323: 161661.34 | Z323: =SUM(I323:T323) -> 0 | AA323: =ROUND(MAX(E323+F323+G323-W323-X323-Z323,0),2) -> 600993.89 | AB323: =ROUND(MAX(H323-U323,0),2) -> 137522.94 | AC323: =ROUND(MAX(0,(D323-V323)*'Shift 14'!$B$2),2) -> 0 | AD323: =MAX(AC323,Y323) -> 161661.34 | AE323: =AF323-A323 -> 0 | AF323: 2860 | AG323: 1 | AH323: 0 | AI323: 0 | AJ323: 0 | AK323: 0 | AL323: 0 | AM323: 0 | AN323: 0 | AO323: 0 | AP323: 0 | AQ323: 9583.94 | AR323: -9583.94 | AS323: 0 | AT323: 0 | AU323: =AV323-A323 -> 0 | AV323: 2860 | AW323: 2860 | AX323: 1 | AY323: BLUE EARTH AREA | AZ323: 0 | BA323: 161661.34
A324: 2884 | B324: 1 | C324: RED ROCK CENTRAL | D324: =Levy!F325 -> 527508 | E324: =Levy!G325 -> 15526 | F324: =Levy!H325 -> 0 | G324: =Levy!I325 -> 380816 | H324: =Levy!J325 -> 26007 | I324: 0 | J324: 0 | K324: 10795 | L324: 0 | M324: 0 | N324: 0 | O324: 0 | P324: 0 | Q324: 0 | R324: 0 | S324: 0 | T324: 0 | U324: 0 | V324: 0 | W324: 0 | X324: 16313.15 | Y324: 56094.94 | Z324: =SUM(I324:T324) -> 10795 | AA324: =ROUND(MAX(E324+F324+G324-W324-X324-Z324,0),2) -> 369233.85 | AB324: =ROUND(MAX(H324-U324,0),2) -> 26007 | AC324: =ROUND(MAX(0,(D324-V324)*'Shift 14'!$B$2),2) -> 0 | AD324: =MAX(AC324,Y324) -> 56094.94 | AE324: =AF324-A324 -> 0 | AF324: 2884 | AG324: 1 | AH324: 0 | AI324: 0 | AJ324: 1194.3 | AK324: 0 | AL324: 10795 | AM324: 0 | AN324: 0 | AO324: 0 | AP324: 0 | AQ324: 0 | AR324: 0 | AS324: 0 | AT324: 0 | AU324: =AV324-A324 -> 0 | AV324: 2884 | AW324: 2884 | AX324: 1 | AY324: RED ROCK CENTRAL | AZ324: 16313.15 | BA324: 56094.94
A325: 2886 | B325: 1 | C325: GLENVILLE-EMMONS | D325: =Levy!F326 -> 260034 | E325: =Levy!G326 -> 25303 | F325: =Levy!H326 -> 0 | G325: =Levy!I326 -> 183932 | H325: =Levy!J326 -> 25668 | I325: 0 | J325: 0 | K325: 9955.13 | L325: 0 | M325: 0 | N325: 0 | O325: 0 | P325: -7898.46 | Q325: 0 | R325: 10000 | S325: 0 | T325: 0 | U325: 0 | V325: 0 | W325: 0 | X325: 519.49 | Y325: 122081.61 | Z325: =SUM(I325:T325) -> 12056.67 | AA325: =ROUND(MAX(E325+F325+G325-W325-X325-Z325,0),2) -> 196658.84 | AB325: =ROUND(MAX(H325-U325,0),2) -> 25668 | AC325: =ROUND(MAX(0,(D325-V325)*'Shift 14'!$B$2),2) -> 0 | AD325: =MAX(AC325,Y325) -> 122081.61 | AE325: =AF325-A325 -> 0 | AF325: 2886 | AG325: 1 | AH325: 0 | AI325: 0 | AJ325: 0 | AK325: 0 | AL325: 9955.13 | AM325: 0 | AN325: 0 | AO325: 0 | AP325: 0 | AQ325: -7898.46 | AR325: 0 | AS325: 10000 | AT325: 0 | AU325: =AV325-A325 -> 0 | AV325: 2886 | AW325: 2886 | AX325: 1 | AY325: GLENVILLE-EMMONS | AZ325: 519.49 | BA325: 122081.61
A326: 2888 | B326: 1 | C326: CLINTON-GRACEVILLE-B | D326: =Levy!F327 -> 194141.15 | E326: =Levy!G327 -> 17615.95 | F326: =Levy!H327 -> 0 | G326: =Levy!I327 -> 133876.13 | H326: =Levy!J327 -> 14027.49 | I326: 0 | J326: 4332 | K326: 13700.89 | L326: 0 | M326: 0 | N326: 0 | O326: 0 | P326: -5216.72 | Q326: 0 | R326: -1701.46 | S326: 0 | T326: 0 | U326: 0 | V326: 0 | W326: 0 | X326: 5805.07 | Y326: 38564.47 | Z326: =SUM(I326:T326) -> 11114.71 | AA326: =ROUND(MAX(E326+F326+G326-W326-X326-Z326,0),2) -> 134572.3 | AB326: =ROUND(MAX(H326-U326,0),2) -> 14027.49 | AC326: =ROUND(MAX(0,(D326-V326)*'Shift 14'!$B$2),2) -> 0 | AD326: =MAX(AC326,Y326) -> 38564.47 | AE326: =AF326-A326 -> 0 | AF326: 2888 | AG326: 1 | AH326: 0 | AI326: 0 | AJ326: 0 | AK326: 4332 | AL326: 13700.89 | AM326: 0 | AN326: 0 | AO326: 0 | AP326: 0 | AQ326: -5216.72 | AR326: 0 | AS326: -1701.46 | AT326: 0 | AU326: =AV326-A326 -> 0 | AV326: 2888 | AW326: 2888 | AX326: 1 | AY326: CLINTON-GRACEVIL | AZ326: 5805.07 | BA326: 38564.47
A327: 2889 | B327: 1 | C327: LAKE PARK AUDUBON | D327: =Levy!F328 -> 470324.23 | E327: =Levy!G328 -> 217534.32 | F327: =Levy!H328 -> 0 | G327: =Levy!I328 -> 358716.45 | H327: =Levy!J328 -> 73621.1 | I327: 0 | J327: 5894.96 | K327: 18092.84 | L327: 0 | M327: 0 | N327: 0 | O327: 0 | P327: -3284.49 | Q327: 0 | R327: -2246.87 | S327: 0 | T327: 0 | U327: 0 | V327: 0 | W327: 0 | X327: 11121.56 | Y327: 70465.44 | Z327: =SUM(I327:T327) -> 18456.44 | AA327: =ROUND(MAX(E327+F327+G327-W327-X327-Z327,0),2) -> 546672.77 | AB327: =ROUND(MAX(H327-U327,0),2) -> 73621.1 | AC327: =ROUND(MAX(0,(D327-V327)*'Shift 14'!$B$2),2) -> 0 | AD327: =MAX(AC327,Y327) -> 70465.44 | AE327: =AF327-A327 -> 0 | AF327: 2889 | AG327: 1 | AH327: 0 | AI327: 0 | AJ327: 0 | AK327: 5894.96 | AL327: 18092.84 | AM327: 0 | AN327: 0 | AO327: 0 | AP327: -6218.29 | AQ327: -3284.49 | AR327: 0 | AS327: -2246.87 | AT327: 0 | AU327: =AV327-A327 -> 0 | AV327: 2889 | AW327: 2889 | AX327: 1 | AY327: LAKE PARK AUDUBO | AZ327: 11121.56 | BA327: 70465.44
A328: 2890 | B328: 1 | C328: RENVILLE COUNTY WEST | D328: =Levy!F329 -> 932288.32 | E328: =Levy!G329 -> 16658.65 | F328: =Levy!H329 -> 0 | G328: =Levy!I329 -> 359599.38 | H328: =Levy!J329 -> 67636.64 | I328: 0 | J328: 0 | K328: 17480.44 | L328: 0 | M328: 0 | N328: 0 | O328: 0 | P328: 5100.48 | Q328: 0 | R328: -2170.82 | S328: 0 | T328: 0 | U328: 0 | V328: 0 | W328: 0 | X328: 0 | Y328: 202355.05 | Z328: =SUM(I328:T328) -> 20410.1 | AA328: =ROUND(MAX(E328+F328+G328-W328-X328-Z328,0),2) -> 355847.93 | AB328: =ROUND(MAX(H328-U328,0),2) -> 67636.64 | AC328: =ROUND(MAX(0,(D328-V328)*'Shift 14'!$B$2),2) -> 0 | AD328: =MAX(AC328,Y328) -> 202355.05 | AE328: =AF328-A328 -> 0 | AF328: 2890 | AG328: 1 | AH328: 0 | AI328: 0 | AJ328: 0 | AK328: 0 | AL328: 17480.44 | AM328: 0 | AN328: 0 | AO328: 0 | AP328: 0 | AQ328: 5100.48 | AR328: 0 | AS328: -2170.82 | AT328: 0 | AU328: =AV328-A328 -> 0 | AV328: 2890 | AW328: 2890 | AX328: 1 | AY328: RENVILLE COUNTY | AZ328: 0 | BA328: 202355.05
... A336: 2905 | B336: 1 | C336: TRI-CITY UNITED | D336: =Levy!F337 -> 518422.38 | E336: =Levy!G337 -> 155153.61 | F336: =Levy!H337 -> 0 | G336: =Levy!I337 -> 1217581.4 | H336: =Levy!J337 -> 146536.23 | I336: 0 | J336: 24689 | K336: 34984.62 | L336: 0 | M336: 0 | N336: 0 | O336: 0 | P336: -10811.15 | Q336: 0 | R336: 0 | S336: 0 | T336: 0 | U336: 0 | V336: 0 | W336: 0 | X336: 0 | Y336: 24770.37 | Z336: =SUM(I336:T336) -> 48862.47 | AA336: =ROUND(MAX(E336+F336+G336-W336-X336-Z336,0),2) -> 1323872.5 | AB336: =ROUND(MAX(H336-U336,0),2) -> 146536.23 | AC336: =ROUND(MAX(0,(D336-V336)*'Shift 14'!$B$2),2) -> 0 | AD336: =MAX(AC336,Y336) -> 24770.37 | AE336: =AF336-A336 -> 0 | AF336: 2905 | AG336: 1 | AH336: 0 | AI336: 0 | AJ336: 0 | AK336: 24689 | AL336: 34984.62 | AM336: 0 | AN336: 0 | AO336: 0 | AP336: -4725.42 | AQ336: -10811.15 | AR336: 0 | AS336: 0 | AT336: 0 | AU336: =AV336-A336 -> 0 | AV336: 2905 | AW336: 2905 | AX336: 1 | AY336: Tri City | AZ336: 0 | BA336: 24770.37
A337: 2906 | B337: 1 | C337: RED LAKE COUNTY CENTRAL | D337: =Levy!F338 -> 328224 | E337: =Levy!G338 -> 33804 | F337: =Levy!H338 -> 0 | G337: =Levy!I338 -> 548175 | H337: =Levy!J338 -> 49057 | I337: 0 | J337: 0 | K337: 16390.79 | L337: 0 | M337: 0 | N337: 0 | O337: 0 | P337: -8253.66 | Q337: 0 | R337: 0 | S337: 0 | T337: 0 | U337: 0 | V337: 0 | W337: 0 | X337: 5099.47 | Y337: 99235.77 | Z337: =SUM(I337:T337) -> 8137.13 | AA337: =ROUND(MAX(E337+F337+G337-W337-X337-Z337,0),2) -> 568742.4 | AB337: =ROUND(MAX(H337-U337,0),2) -> 49057 | AC337: =ROUND(MAX(0,(D337-V337)*'Shift 14'!$B$2),2) -> 0 | AD337: =MAX(AC337,Y337) -> 99235.77 | AE337: =AF337-A337 -> 0 | AF337: 2906 | AG337: 1 | AH337: 0 | AI337: 0 | AJ337: 0 | AK337: 0 | AL337: 16390.79 | AM337: 0 | AN337: 0 | AO337: 0 | AP337: 0 | AQ337: -8253.66 | AR337: 0 | AS337: 0 | AT337: 0 | AU337: =AV337-A337 -> 0 | AV337: 2906 | AZ337: 5099.47 | BA337: 99235.77
A338: 2907 | B338: 1 | C338: ROUND LAKE-BREWSTER | D338: =Levy!F339 -> 337890.42 | E338: =Levy!G339 -> 7075.46 | F338: =Levy!H339 -> 0 | G338: =Levy!I339 -> 351702.55 | H338: =Levy!J339 -> 28193.42 | I338: 0 | J338: 9990 | K338: 0 | L338: 0 | M338: 0 | N338: 0 | O338: 0 | P338: -3339.13 | Q338: 0 | R338: 0 | S338: 0 | T338: 0 | U338: 0 | V338: 0 | W338: 0 | X338: 7070.94 | Y338: 77208.32 | Z338: =SUM(I338:T338) -> 6650.87 | AA338: =ROUND(MAX(E338+F338+G338-W338-X338-Z338,0),2) -> 345056.2 | AB338: =ROUND(MAX(H338-U338,0),2) -> 28193.42 | AC338: =ROUND(MAX(0,(D338-V338)*'Shift 14'!$B$2),2) -> 0 | AD338: =MAX(AC338,Y338) -> 77208.32 | AE338: =AF338-A338 -> 0 | AF338: 2907 | AG338: 1 | AH338: 0 | AI338: 0 | AJ338: 10211.91 | AK338: 9990 | AL338: 0 | AM338: 0 | AN338: 0 | AO338: 0 | AP338: 33.39 | AQ338: -3339.13 | AR338: 0 | AS338: 0 | AT338: 0 | AU338: =AV338-A338 -> 0 | AV338: 2907 | AZ338: 7070.94 | BA338: 77208.32
A339: 2908 | B339: 1 | C339: BRANDON-EVANSVILLE | D339: =Levy!F340 -> 332679.06 | E339: =Levy!G340 -> 47368.78 | F339: =Levy!H340 -> 0 | G339: =Levy!I340 -> 313765.78 | H339: =Levy!J340 -> 41778.39 | I339: 0 | J339: 15000 | K339: 26815.88 | L339: 0 | M339: 0 | N339: 0 | O339: 0 | P339: -15493.12 | Q339: -4306.76 | R339: 0 | S339: 0 | T339: 0 | U339: 0 | V339: 0 | W339: 0 | X339: 0 | Y339: 0 | Z339: =SUM(I339:T339) -> 22016 | AA339: =ROUND(MAX(E339+F339+G339-W339-X339-Z339,0),2) -> 339118.56 | AB339: =ROUND(MAX(H339-U339,0),2) -> 41778.39 | AC339: =ROUND(MAX(0,(D339-V339)*'Shift 14'!$B$2),2) -> 0 | AD339: =MAX(AC339,Y339) -> 0 | AE339: =AF339-A339 -> 0 | AF339: 2908 | AG339: 1 | AH339: 0 | AI339: 0 | AJ339: 0 | AK339: 15000 | AL339: 26815.88 | AM339: 0 | AN339: 0 | AO339: 0 | AP339: 0 | AQ339: -15493.12 | AR339: -4306.76 | AS339: 0 | AT339: 0 | AU339: =AV339-A339 -> 0 | AV339: 2908 | AZ339: 0 | BA339: 0
A340: End of worksheet | AE340: =SUM(AE8:AE339) -> 0
AV345: 2769 | AW345: 611 | AX345: 1 | AY345: CYRUS | AZ345: 0 | BA345: 23770.64
AV346: 2769 | AW346: 769 | AX346: 1 | AY346: MORRIS | AZ346: 0 | BA346: 161645.93
AV347: 2769 | AZ347: =SUM(AZ345:AZ346) -> 0 | BA347: =SUM(BA345:BA346) -> 185416.57
AV349: 2906 | AW349: 627 | AX349: 1 | AY349: OKLEE | AZ349: 0 | BA349: 75830.54
AV350: 2906 | AW350: 628 | AX350: 1 | AY350: PLUMMER | AZ350: 5099.47 | BA350: 23405.23
AV351: 2906 | AZ351: =SUM(AZ349:AZ350) -> 5099.47 | BA351: =SUM(BA349:BA350) -> 99235.77
AV353: 2907 | AW353: 513 | AX353: 1 | AY353: BREWSTER | AZ353: 3066.79 | BA353: 33457.41
AV354: 2907 | AW354: 516 | AX354: 1 | AY354: ROUND LAKE | AZ354: 4004.15 | BA354: 43750.91
AV355: 2907 | AZ355: =SUM(AZ353:AZ354) -> 7070.94 | BA355: =SUM(BA353:BA354) -> 77208.32
AV357: 2908 | AW357: 207 | AX357: 1 | AY357: BRANDON | AZ357: 0 | BA357: 0
AV358: 2908 | AW358: 208 | AX358: 1 | AY358: EVANSVILLE | AZ358: 0 | BA358: 0
AV359: 2908 | AZ359: =SUM(AZ357:AZ358) -> 0 | BA359: =SUM(BA357:BA358) -> 0

Sheet Shift 13
A1: ="Actual "&Instructions!P2&" Gross Shift" -> Actual Pay 2013 Gross Shift | D1: G:\Finance|Colleen's Files\Taxshift\Shift 12-13\Final Taxshift\TAXSHIFT-final history 12-13.xlsx | O1: =Report!I1 -> 41828
D2: (1A) | E2: (1B) | F2: (1C) | G2: (1D) | H2: (1E) | I2: (1F) | J2: (1G) | K2: (1H) | L2: (1I) | M2: (1K) | N2: (1M)
A3: Shift at 48.6% | D3: MNT-LVY-ADJ-SHF | E3: MNT-REF-LVY-SHF-2 | F3: MNT-REF-LVY-SHF | G3: REF-HAC-LVY-SHF | H3: MNT-CAR-TEC-SHF | I3: MNT-NON-AID-SHF | J3: MNT-UNE-RES-SHF | K3: MNT-UNE-UNR-SHF | L3: MNT-LEG-CHG-SHF | M3: CSE-LVY-ADJ-SHF | N3: CSE-LEG-CHG-SHF
D4: Genl with Aid Adjust | E4: Refer with Aid Adjust | F4: Refer No Aid Adjust | G4: Addl Refer Shift | H4: Career Technical | I4: 100% Shift | J4: Reemploy Resv | K4: Reemploy Unrsv | L4: Leg Changes Genl Fund | M4: Comm Serv at Shift % | N4: Leg Changes Comm Serv | O4: Total Gross Shift
C6: State Total | D6: =SUM(D11:D342) -> 2.4944436e+08 | E6: =SUM(E11:E342) -> 2.6547387e+08 | F6: =SUM(F11:F342) -> 1.1422854e+08 | G6: =SUM(G11:G342) -> 4282529.2 | H6: =SUM(H11:H342) -> 14728250 | I6: =SUM(I11:I342) -> 35781240 | J6: =SUM(J11:J342) -> -110878.95 | K6: =SUM(K11:K342) -> 11639227 | ... O6: =SUM(O11:O342) -> 7.3160865e+08
D8: (1A) | E8: (1B) | F8: (1C) | G8: (1D) | H8: (1E) | I8: (1F) | J8: (1G) | K8: (1H) | L8: (1I) | M8: (1K) | N8: (1M)
A9: 0 | B9: DST-TYE | D9: MNT-LVY-ADJ-SHF | E9: MNT-REF-LVY-SHF-2 | F9: MNT-REF-LVY-SHF | G9: REF-HAC-LVY-SHF | H9: MNT-CAR-TEC-SHF | I9: MNT-NON-AID-SHF | J9: MNT-UNE-RES-SHF | K9: MNT-UNE-UNR-SHF | L9: MNT-LEG-CHG-SHF | M9: CSE-LVY-ADJ-SHF | N9: CSE-LEG-CHG-SHF
A11: 1 | B11: 1 | C11: AITKIN | D11: 348692.74 | E11: 0 | F11: 141143.88 | G11: 0 | H11: 25644.59 | I11: 0 | J11: 0 | K11: 8234.63 | L11: 0 | M11: 5395.57 | N11: 0 | O11: =SUM(D11:N11) -> 529111.41
A12: 1.2 | B12: 3 | C12: MINNEAPOLIS | D12: 10520675 | E12: 21877596 | F12: 10049626 | G12: 1205612.7 | H12: 524739.16 | I12: 14946995 | J12: 0 | K12: 1083282.2 | L12: 0 | M12: 2310760.1 | N12: 0 | O12: =SUM(D12:N12) -> 62519286
A13: 2 | B13: 1 | C13: HILL CITY | D13: 52908.37 | E13: 0 | F13: 0 | G13: 0 | H13: 0 | I13: 0 | J13: 0 | K13: 17587.04 | L13: 0 | M13: 9691.81 | N13: 0 | O13: =SUM(D13:N13) -> 80187.22
A14: 4 | B14: 1 | C14: MCGREGOR | D14: 171965.38 | E14: 0 | F14: 51784.65 | G14: 0 | H14: 10003.75 | I14: 0 | J14: 0 | K14: 247.02 | L14: 0 | M14: 25493.62 | N14: 0 | O14: =SUM(D14:N14) -> 259494.42
A15: 6 | B15: 3 | C15: SOUTH ST. PAUL | D15: 1373574.9 | E15: 1070015.6 | F15: 360711.07 | G15: 0 | H15: 60403.38 | I15: 0 | J15: 0 | K15: 26690.88 | L15: 0 | M15: 174530.38 | N15: 0 | O15: =SUM(D15:N15) -> 3065926.2
A16: 11 | B16: 1 | C16: ANOKA-HENNEPIN | D16: 10965625 | E16: 20072770 | F16: 3515884.7 | G16: 197692.1 | H16: 804097.39 | I16: 0 | J16: 0 | K16: 466030.14 | L16: 0 | M16: 1511185 | N16: 0 | O16: =SUM(D16:N16) -> 37533284
A17: 12 | B17: 1 | C17: CENTENNIAL | D17: 1678920.9 | E17: 2331680 | F17: 320094.52 | G17: 16533.75 | H17: 98718.45 | I17: 0 | J17: 0 | K17: 112774.85 | L17: 0 | M17: 203136.35 | N17: 0 | O17: =SUM(D17:N17) -> 4761858.9
A18: 13 | B18: 1 | C18: COLUMBIA HEIGHTS | D18: 1067552.7 | E18: 780519.38 | F18: 848958.71 | G18: 0 | H18: 55361.66 | I18: 0 | J18: 0 | K18: 67771.04 | L18: 0 | M18: 171191.46 | N18: 0 | O18: =SUM(D18:N18) -> 2991355
A19: 14 | B19: 1 | C19: FRIDLEY | D19: 1197487.9 | E19: 702683.97 | F19: 468605.33 | G19: 0 | H19: 58815.15 | I19: 0 | J19: 0 | K19: 68636.97 | L19: 0 | M19: 198881.39 | N19: 0 | O19: =SUM(D19:N19) -> 2695110.7
A20: 15 | B20: 1 | C20: ST. FRANCIS | D20: 1128147.4 | E20: 558074.99 | F20: 288492.79 | G20: 0 | H20: 106419.83 | I20: 0 | J20: 0 | K20: 165109.94 | L20: 0 | M20: 177575.69 | N20: 0 | O20: =SUM(D20:N20) -> 2423820.7
A21: 16 | B21: 1 | C21: SPRING LAKE PARK | D21: 2285453.8 | E21: 1718912.6 | F21: 804793.86 | G21: 73286.44 | H21: 68504.68 | I21: 0 | J21: 0 | K21: 131229.05 | L21: 0 | M21: 224515.36 | N21: 0 | O21: =SUM(D21:N21) -> 5306695.8
A22: 22 | B22: 1 | C22: DETROIT LAKES | D22: 704875.8 | E22: 499115.63 | F22: 133298.49 | G22: 0 | H22: 51500.13 | I22: 0 | J22: 0 | K22: 41059.27 | L22: 0 | M22: 102673.53 | N22: 0 | O22: =SUM(D22:N22) -> 1532522.9
... A342: 2908 | B342: 1 | C342: BRANDON-EVANSVILLE | D342: 161904.79 | E342: 235233.04 | F342: 0 | G342: 0 | H342: 20007.5 | I342: 0 | J342: -5590 | K342: -4885.69 | L342: 0 | M342: 18280.88 | N342: 0 | O342: =SUM(D342:N342) -> 424950.52
A343: End of worksheet

Sheet Levy
A1: Computed Credits for Tax Shift | F1: Pay 2014 STR Pay 2014 STR (G:\Finance\Colleen's Files\Levies\Levy Pay 2014\School Tax Reports &Edits\Query Pay 2014 School Tax Report Data.xls | V1: =Report!I1 -> 41828
A2: ="Preliminary "&Instructions!P2&" credits" -> Preliminary Pay 2013 credits | AF2: STR column-row | AJ2: 21-1 | AK2: 22-1 | AL2: 21-2 | AM2: 22-2 | AN2: 21-3 | AO2: 22-3 | AP2: 21-4 | AQ2: 22-4 | AR2: 21-5 | AS2: 22-5 | AT2: 21-6 | AU2: 22-6 | AV2: 21-7 | AW2: 22-7 | AX2: 21-8 | AY2: 22-8 | AZ2: 21-9 | BA2: 22-9
A3: =Instructions!P1&" Levy" -> Pay 2014 Levy | F3: STR 21,22-1 | G3: STR 21,22-2 | H3: STR 21,22-3 | I3: STR 21,22-4 | J3: STR 21,22-5 | K3: STR 21,22-6 | L3: STR 21,22-7 | M3: STR 21,22-8 | N3: STR 21,22-9 | O3: 2.2409359e+09 | U3: Credit Tab | AF3: dat_yer | AG3: dst_num | AH3: dst_tye | AI3: dst_act_sts | AJ3: mnt_crt_tax_lvy_6 | AK3: mnt_cua_tax_adj_6 | AL3: mnt_crt_tax_lvy_5 | AM3: mnt_cua_tax_adj_5 | AN3: mnt_crt_tax_lvy_3 | AO3: mnt_cua_tax_adj_3 | AP3: mnt_crt_tax_lvy | AQ3: mnt_cua_tax_adj | AR3: cse_crt_tax_lvy | AS3: cse_cua_tax_adj | AT3: gds_crt_tax_lvy | AU3: gds_cua_tax_adj | AV3: gds_crt_tax_lvy_2 | AW3: gds_cua_tax_adj_2 | AX3: peb_crt_tax_lvy | AY3: peb_cua_tax_adj | AZ3: peb_crt_tax_lvy_2 | BA3: peb_cua_tax_adj_2 | BB3: calc | BC3: tot_lvy_crt
A4: Estimated Credits Allocation? 1=Yes, 0=No | D4: Prel Pay 2010 Credits | E4: Est Pay 2010 Credits | F4: Genl RMV Voter Levy | G4: Genl RMV Other Levy | H4: Genl NTC Voter Levy | I4: Genl NTC Other Levy | J4: Comm Service Levy | K4: Debt Voter Levy | L4: Debt Other Levy | M4: OPEB Voter Levy | N4: OPEB Other Levy | O4: Total Levy | P4: Total Levy for Credit Allocation | Q4: Genl Levy for Credit Allocation | R4: CSE Levy for Credit Allocation | S4: GDS Levy for Credit Allocation | T4: OPEB Levy for Credit Allocation | U4: Est/Act Fund 1 Credits | V4: Est/Act Fund 4 Credits | W4: Est/Act Fund 7 Credits | X4: Est/Act Fund 47 Credits | Y4: Estimated Total Credits | AJ4: STR 21,22-1 | AK4: 22-1 | AL4: STR 21,22-2 | AM4: 22-2 | AN4: STR 21,22-3 | AO4: 22-3 | AP4: STR 21,22-4 | AQ4: 22-4 | AR4: STR 21,22-5 | AS4: 22-5 | AT4: STR 21,22-6 | AU4: 22-6 | AV4: STR 21,22-7 | AW4: 22-7 | AX4: STR 21,22-8 | AY4: 22-8 | AZ4: STR 21,22-9 | BA4: 22-9 | BB4: STR Total | BC4: Cert Levy Total
A5: 0
C6: State Total | D6: =SUM(D9:D340) -> 0 | E6: =SUM(E9:E340) -> 0 | F6: =SUM(F9:F340) -> 5.3052543e+08 | G6: =SUM(G9:G340) -> 3.3639926e+08 | H6: =SUM(H9:H340) -> 60897104 | I6: =SUM(I9:I340) -> 4.8154312e+08 | J6: =SUM(J9:J340) -> 74876386 | K6: =SUM(K9:K340) -> 5.7802268e+08 | ... Y6: =SUM(Y9:Y340) -> 17140934 | AE6: =SUM(AE9:AE340) -> 0 | AJ6: =SUM(AJ9:AJ340) -> 5.3052782e+08 | AK6: =SUM(AK9:AK340) -> -2393.07 | AL6: =SUM(AL9:AL340) -> 3.3645545e+08 | AM6: =SUM(AM9:AM340) -> -56185.29 | AN6: =SUM(AN9:AN340) -> 60897104 | AO6: =SUM(AO9:AO340) -> 0 | AP6: =SUM(AP9:AP340) -> 4.8148454e+08 | AQ6: =SUM(AQ9:AQ340) -> 58579.01 | ... BC6: =SUM(BC9:BC340) -> 2.3561265e+09 | BD6: 0
AF7: dat_yer | AG7: dst_num | AH7: dst_tye | AJ7: ref_mkt_tot_lvy | AL7: gen_rmv_tot_crt | AN7: ref_tcp_tot_lvy | AP7: tax_cpc_lvy_crt | AR7: cse_lvy_crt | AT7: gds_vtr_tot_lvy | AV7: gds_oth_tot_lvy | AX7: pvt_lvy_crt | AZ7: pno_lvy_crt | BB7: calc | BC7: tot_lvy_crt | BD7: Difference
A9: 1 | B9: 1 | C9: AITKIN | D9: 0 | E9: 0 | F9: =+AJ9+AK9 -> 3 | G9: =+AL9+AM9 -> 512160 | H9: =+AN9+AO9 -> 0 | I9: =+AP9+AQ9 -> 376935 | J9: =+AR9+AS9 -> 0 | K9: =+AT9+AU9 -> 0 | L9: =+AV9+AW9 -> 122144 | M9: =+AX9+AY9 -> 0 | N9: =+AZ9+BA9 -> 0 | O9: =SUM(F9:N9) -> 1011242 | P9: =SUM(H9:N9) -> 499079 | Q9: =SUM(H9:I9) -> 376935 | R9: =J9 -> 0 | S9: =K9+L9 -> 122144 | T9: =N9+M9 -> 0 | U9: =IF($A$5=1,IF($P9=0,0,ROUND(Q9/$P9*$E9,2)),Credits!D8)+Credits!J8 -> 39970.46 | V9: =IF($A$5=1,IF($P9=0,0,ROUND(R9/$P9*$E9,2)),Credits!E8)+Credits!K8 -> 2155.14 | W9: =IF($A$5=1,IF($P9=0,0,ROUND(S9/$P9*$E9,2)),Credits!F8)+Credits!L8 -> 14079.85 | X9: =IF($A$5=1,IF($P9=0,0,ROUND(T9/$P9*$E9,2)),Credits!G8)+Credits!M8 -> 2155.14 | Y9: =SUM(U9:X9) -> 58360.59 | AE9: =+A9-AG9 -> 0 | AF9: 13-14 | AG9: 1 | AH9: 1 | AI9: 1 | AJ9: 3 | AK9: 0 | AL9: 512160 | AM9: 0 | AN9: 0 | AO9: 0 | AP9: 376935 | AQ9: 0 | AR9: 0 | AS9: 0 | AT9: 0 | AU9: 0 | AV9: 122144 | AW9: 0 | AX9: 0 | AY9: 0 | AZ9: 0 | BA9: 0 | BB9: =SUM(AJ9:BA9) -> 1011242 | BC9: 1011242 | BD9: =BB9-BC9 -> -0.04
A10: 1.2 | B10: 3 | C10: MINNEAPOLIS | D10: 0 | E10: 0 | F10: =+AJ10+AK10 -> 42963957 | G10: =+AL10+AM10 -> 32244453 | H10: =+AN10+AO10 -> 0 | I10: =+AP10+AQ10 -> 40377225 | J10: =+AR10+AS10 -> 4958085 | K10: =+AT10+AU10 -> 0 | L10: =+AV10+AW10 -> 51348833 | M10: =+AX10+AY10 -> 0 | N10: =+AZ10+BA10 -> 0 | O10: =SUM(F10:N10) -> 1.7189255e+08 | P10: =SUM(H10:N10) -> 96684143 | Q10: =SUM(H10:I10) -> 40377225 | R10: =J10 -> 4958085 | S10: =K10+L10 -> 51348833 | T10: =N10+M10 -> 0 | U10: =IF($A$5=1,IF($P10=0,0,ROUND(Q10/$P10*$E10,2)),Credits!D9)+Credits!J9 -> 179608.01 | V10: =IF($A$5=1,IF($P10=0,0,ROUND(R10/$P10*$E10,2)),Credits!E9)+Credits!K9 -> 22053.33 | W10: =IF($A$5=1,IF($P10=0,0,ROUND(S10/$P10*$E10,2)),Credits!F9)+Credits!L9 -> 228395.17 | X10: =IF($A$5=1,IF($P10=0,0,ROUND(T10/$P10*$E10,2)),Credits!G9)+Credits!M9 -> 0 | Y10: =SUM(U10:X10) -> 430056.51 | AE10: =+A10-AG10 -> 0 | AF10: 13-14 | AG10: 1.2 | AH10: 3 | AI10: 1 | AJ10: 42963957 | AK10: 0 | AL10: 32244453 | AM10: 0 | AN10: 0 | AO10: 0 | AP10: 40377225 | AQ10: 0 | AR10: 4958085 | AS10: 0 | AT10: 0 | AU10: 0 | AV10: 51348833 | AW10: 0 | AX10: 0 | AY10: 0 | AZ10: 0 | BA10: 0 | BB10: =SUM(AJ10:BA10) -> 1.7189255e+08 | BC10: 1.7189255e+08 | BD10: =BB10-BC10 -> 0
A11: 2 | B11: 1 | C11: HILL CITY | D11: 0 | E11: 0 | F11: =+AJ11+AK11 -> 0 | G11: =+AL11+AM11 -> 55347 | H11: =+AN11+AO11 -> 0 | I11: =+AP11+AQ11 -> 61170 | J11: =+AR11+AS11 -> 18559 | K11: =+AT11+AU11 -> 205724 | L11: =+AV11+AW11 -> 0 | M11: =+AX11+AY11 -> 0 | N11: =+AZ11+BA11 -> 0 | O11: =SUM(F11:N11) -> 340800 | P11: =SUM(H11:N11) -> 285453 | Q11: =SUM(H11:I11) -> 61170 | R11: =J11 -> 18559 | S11: =K11+L11 -> 205724 | T11: =N11+M11 -> 0 | U11: =IF($A$5=1,IF($P11=0,0,ROUND(Q11/$P11*$E11,2)),Credits!D10)+Credits!J10 -> 2269.22 | V11: =IF($A$5=1,IF($P11=0,0,ROUND(R11/$P11*$E11,2)),Credits!E10)+Credits!K10 -> 688.53 | W11: =IF($A$5=1,IF($P11=0,0,ROUND(S11/$P11*$E11,2)),Credits!F10)+Credits!L10 -> 7632.7 | X11: =IF($A$5=1,IF($P11=0,0,ROUND(T11/$P11*$E11,2)),Credits!G10)+Credits!M10 -> 0 | Y11: =SUM(U11:X11) -> 10590.45 | AE11: =+A11-AG11 -> 0 | AF11: 13-14 | AG11: 2 | AH11: 1 | AI11: 1 | AJ11: 0 | AK11: 0 | AL11: 55347 | AM11: 0 | AN11: 0 | AO11: 0 | AP11: 61170 | AQ11: 0 | AR11: 18559 | AS11: 0 | AT11: 205724 | AU11: 0 | AV11: 0 | AW11: 0 | AX11: 0 | AY11: 0 | AZ11: 0 | BA11: 0 | BB11: =SUM(AJ11:BA11) -> 340800 | BC11: 340799.59 | BD11: =BB11-BC11 -> 0.41
A12: 4 | B12: 1 | C12: MCGREGOR | D12: 0 | E12: 0 | F12: =+AJ12+AK12 -> 375 | G12: =+AL12+AM12 -> 100950 | H12: =+AN12+AO12 -> 0 | I12: =+AP12+AQ12 -> 319645 | J12: =+AR12+AS12 -> 53030 | K12: =+AT12+AU12 -> 737425 | L12: =+AV12+AW12 -> 50049 | M12: =+AX12+AY12 -> 0 | N12: =+AZ12+BA12 -> 159544 | O12: =SUM(F12:N12) -> 1421018 | P12: =SUM(H12:N12) -> 1319693 | Q12: =SUM(H12:I12) -> 319645 | R12: =J12 -> 53030 | S12: =K12+L12 -> 787474 | T12: =N12+M12 -> 159544 | U12: =IF($A$5=1,IF($P12=0,0,ROUND(Q12/$P12*$E12,2)),Credits!D11)+Credits!J11 -> 4370.4 | V12: =IF($A$5=1,IF($P12=0,0,ROUND(R12/$P12*$E12,2)),Credits!E11)+Credits!K11 -> 725.33 | W12: =IF($A$5=1,IF($P12=0,0,ROUND(S12/$P12*$E12,2)),Credits!F11)+Credits!L11 -> 10763.91 | X12: =IF($A$5=1,IF($P12=0,0,ROUND(T12/$P12*$E12,2)),Credits!G11)+Credits!M11 -> 2180.6 | Y12: =SUM(U12:X12) -> 18040.24 | AE12: =+A12-AG12 -> 0 | AF12: 13-14 | AG12: 4 | AH12: 1 | AI12: 1 | AJ12: 375 | AK12: 0 | AL12: 100950 | AM12: 0 | AN12: 0 | AO12: 0 | AP12: 319645 | AQ12: 0 | AR12: 53030 | AS12: 0 | AT12: 737425 | AU12: 0 | AV12: 50049 | AW12: 0 | AX12: 0 | AY12: 0 | AZ12: 159544 | BA12: 0 | BB12: =SUM(AJ12:BA12) -> 1421018 | BC12: 1421018.3 | BD12: =BB12-BC12 -> -0.29
A13: 6 | B13: 3 | C13: SOUTH ST. PAUL | D13: 0 | E13: 0 | F13: =+AJ13+AK13 -> 1109814 | G13: =+AL13+AM13 -> 1607848 | H13: =+AN13+AO13 -> 522346 | I13: =+AP13+AQ13 -> 2118168 | J13: =+AR13+AS13 -> 313589 | K13: =+AT13+AU13 -> 2162689 | L13: =+AV13+AW13 -> 0 | M13: =+AX13+AY13 -> 0 | N13: =+AZ13+BA13 -> 753580 | O13: =SUM(F13:N13) -> 8588034 | P13: =SUM(H13:N13) -> 5870372 | Q13: =SUM(H13:I13) -> 2640514 | R13: =J13 -> 313589 | S13: =K13+L13 -> 2162689 | T13: =N13+M13 -> 753580 | U13: =IF($A$5=1,IF($P13=0,0,ROUND(Q13/$P13*$E13,2)),Credits!D12)+Credits!J12 -> 0 | V13: =IF($A$5=1,IF($P13=0,0,ROUND(R13/$P13*$E13,2)),Credits!E12)+Credits!K12 -> 0 | W13: =IF($A$5=1,IF($P13=0,0,ROUND(S13/$P13*$E13,2)),Credits!F12)+Credits!L12 -> 0 | X13: =IF($A$5=1,IF($P13=0,0,ROUND(T13/$P13*$E13,2)),Credits!G12)+Credits!M12 -> 0 | Y13: =SUM(U13:X13) -> 0 | AE13: =+A13-AG13 -> 0 | AF13: 13-14 | AG13: 6 | AH13: 3 | AI13: 1 | AJ13: 1109814 | AK13: 0 | AL13: 1607848 | AM13: 0 | AN13: 522346 | AO13: 0 | AP13: 2118168 | AQ13: 0 | AR13: 313589 | AS13: 0 | AT13: 2162689 | AU13: 0 | AV13: 0 | AW13: 0 | AX13: 0 | AY13: 0 | AZ13: 753580 | BA13: 0 | BB13: =SUM(AJ13:BA13) -> 8588034 | BC13: 8588034 | BD13: =BB13-BC13 -> 0.0099999998
A14: 11 | B14: 1 | C14: ANOKA-HENNEPIN | D14: 0 | E14: 0 | F14: =+AJ14+AK14 -> 26446869 | G14: =+AL14+AM14 -> 15845308 | H14: =+AN14+AO14 -> 2728226 | I14: =+AP14+AQ14 -> 23560897 | J14: =+AR14+AS14 -> 3085048.6 | K14: =+AT14+AU14 -> 16665867 | L14: =+AV14+AW14 -> 1603590.1 | M14: =+AX14+AY14 -> 0 | N14: =+AZ14+BA14 -> 2146664.2 | O14: =SUM(F14:N14) -> 92082469 | P14: =SUM(H14:N14) -> 49790293 | Q14: =SUM(H14:I14) -> 26289123 | R14: =J14 -> 3085048.6 | S14: =K14+L14 -> 18269457 | T14: =N14+M14 -> 2146664.2 | U14: =IF($A$5=1,IF($P14=0,0,ROUND(Q14/$P14*$E14,2)),Credits!D13)+Credits!J13 -> 5248.43 | V14: =IF($A$5=1,IF($P14=0,0,ROUND(R14/$P14*$E14,2)),Credits!E13)+Credits!K13 -> 582.57 | W14: =IF($A$5=1,IF($P14=0,0,ROUND(S14/$P14*$E14,2)),Credits!F13)+Credits!L13 -> 3337.86 | X14: =IF($A$5=1,IF($P14=0,0,ROUND(T14/$P14*$E14,2)),Credits!G13)+Credits!M13 -> 404.4 | Y14: =SUM(U14:X14) -> 9573.26 | AE14: =+A14-AG14 -> 0 | AF14: 13-14 | AG14: 11 | AH14: 1 | AI14: 1 | AJ14: 26446869 | AK14: 0 | AL14: 15845308 | AM14: 0 | AN14: 2728226 | AO14: 0 | AP14: 23560897 | AQ14: 0 | AR14: 3085048.6 | AS14: 0 | AT14: 16665867 | AU14: 0 | AV14: 1603590.1 | AW14: 0 | AX14: 0 | AY14: 0 | AZ14: 2146664.2 | BA14: 0 | BB14: =SUM(AJ14:BA14) -> 92082469 | BC14: 92082469 | BD14: =BB14-BC14 -> 0
A15: 12 | B15: 1 | C15: CENTENNIAL | D15: 0 | E15: 0 | F15: =+AJ15+AK15 -> 1845321.4 | G15: =+AL15+AM15 -> 3019153.1 | H15: =+AN15+AO15 -> 0 | I15: =+AP15+AQ15 -> 4960893.5 | J15: =+AR15+AS15 -> 413840.61 | K15: =+AT15+AU15 -> 5656801.7 | L15: =+AV15+AW15 -> 345543.78 | M15: =+AX15+AY15 -> 0 | N15: =+AZ15+BA15 -> 602900.55 | O15: =SUM(F15:N15) -> 16844455 | P15: =SUM(H15:N15) -> 11979980 | Q15: =SUM(H15:I15) -> 4960893.5 | R15: =J15 -> 413840.61 | S15: =K15+L15 -> 6002345.5 | T15: =N15+M15 -> 602900.55 | U15: =IF($A$5=1,IF($P15=0,0,ROUND(Q15/$P15*$E15,2)),Credits!D14)+Credits!J14 -> 752.26 | V15: =IF($A$5=1,IF($P15=0,0,ROUND(R15/$P15*$E15,2)),Credits!E14)+Credits!K14 -> 57.56 | W15: =IF($A$5=1,IF($P15=0,0,ROUND(S15/$P15*$E15,2)),Credits!F14)+Credits!L14 -> 802.77 | X15: =IF($A$5=1,IF($P15=0,0,ROUND(T15/$P15*$E15,2)),Credits!G14)+Credits!M14 -> 82.66 | Y15: =SUM(U15:X15) -> 1695.25 | AE15: =+A15-AG15 -> 0 | AF15: 13-14 | AG15: 12 | AH15: 1 | AI15: 1 | AJ15: 1845321.4 | AK15: 0 | AL15: 3019153.1 | AM15: 0 | AN15: 0 | AO15: 0 | AP15: 4960893.5 | AQ15: 0 | AR15: 413840.61 | AS15: 0 | AT15: 5656801.7 | AU15: 0 | AV15: 345543.78 | AW15: 0 | AX15: 0 | AY15: 0 | AZ15: 602900.55 | BA15: 0 | BB15: =SUM(AJ15:BA15) -> 16844455 | BC15: 16844455 | BD15: =BB15-BC15 -> 0
A16: 13 | B16: 1 | C16: COLUMBIA HEIGHTS | D16: 0 | E16: 0 | F16: =+AJ16+AK16 -> 999598.58 | G16: =+AL16+AM16 -> 1846818.2 | H16: =+AN16+AO16 -> 0 | I16: =+AP16+AQ16 -> 1950276.2 | J16: =+AR16+AS16 -> 404050.21 | K16: =+AT16+AU16 -> 2090169.5 | L16: =+AV16+AW16 -> 79645.78 | M16: =+AX16+AY16 -> 0 | N16: =+AZ16+BA16 -> 0 | O16: =SUM(F16:N16) -> 7370558.5 | P16: =SUM(H16:N16) -> 4524141.7 | Q16: =SUM(H16:I16) -> 1950276.2 | R16: =J16 -> 404050.21 | S16: =K16+L16 -> 2169815.3 | T16: =N16+M16 -> 0 | U16: =IF($A$5=1,IF($P16=0,0,ROUND(Q16/$P16*$E16,2)),Credits!D15)+Credits!J15 -> 72.65 | V16: =IF($A$5=1,IF($P16=0,0,ROUND(R16/$P16*$E16,2)),Credits!E15)+Credits!K15 -> 15.46 | W16: =IF($A$5=1,IF($P16=0,0,ROUND(S16/$P16*$E16,2)),Credits!F15)+Credits!L15 -> 72.89 | X16: =IF($A$5=1,IF($P16=0,0,ROUND(T16/$P16*$E16,2)),Credits!G15)+Credits!M15 -> 0 | Y16: =SUM(U16:X16) -> 161 | AE16: =+A16-AG16 -> 0 | AF16: 13-14 | AG16: 13 | AH16: 1 | AI16: 1 | AJ16: 999598.58 | AK16: 0 | AL16: 1846818.2 | AM16: 0 | AN16: 0 | AO16: 0 | AP16: 1950276.2 | AQ16: 0 | AR16: 404050.21 | AS16: 0 | AT16: 2090169.5 | AU16: 0 | AV16: 79645.78 | AW16: 0 | AX16: 0 | AY16: 0 | AZ16: 0 | BA16: 0 | BB16: =SUM(AJ16:BA16) -> 7370558.5 | BC16: 7370558.5 | BD16: =BB16-BC16 -> 0
A17: 14 | B17: 1 | C17: FRIDLEY | D17: 0 | E17: 0 | F17: =+AJ17+AK17 -> 799891.31 | G17: =+AL17+AM17 -> 1293258.1 | H17: =+AN17+AO17 -> 651253 | I17: =+AP17+AQ17 -> 1382396.7 | J17: =+AR17+AS17 -> 321785.77 | K17: =+AT17+AU17 -> 1117835.3 | L17: =+AV17+AW17 -> 1686647.7 | M17: =+AX17+AY17 -> 0 | N17: =+AZ17+BA17 -> 601908.08 | O17: =SUM(F17:N17) -> 7854975.9 | P17: =SUM(H17:N17) -> 5761826.5 | Q17: =SUM(H17:I17) -> 2033649.7 | R17: =J17 -> 321785.77 | S17: =K17+L17 -> 2804483 | T17: =N17+M17 -> 601908.08 | U17: =IF($A$5=1,IF($P17=0,0,ROUND(Q17/$P17*$E17,2)),Credits!D16)+Credits!J16 -> 0 | V17: =IF($A$5=1,IF($P17=0,0,ROUND(R17/$P17*$E17,2)),Credits!E16)+Credits!K16 -> 0 | W17: =IF($A$5=1,IF($P17=0,0,ROUND(S17/$P17*$E17,2)),Credits!F16)+Credits!L16 -> 0 | X17: =IF($A$5=1,IF($P17=0,0,ROUND(T17/$P17*$E17,2)),Credits!G16)+Credits!M16 -> 0 | Y17: =SUM(U17:X17) -> 0 | AE17: =+A17-AG17 -> 0 | AF17: 13-14 | AG17: 14 | AH17: 1 | AI17: 1 | AJ17: 799891.31 | AK17: 0 | AL17: 1293258.1 | AM17: 0 | AN17: 651253 | AO17: 0 | AP17: 1382396.7 | AQ17: 0 | AR17: 321785.77 | AS17: 0 | AT17: 1117835.3 | AU17: 0 | AV17: 1686647.7 | AW17: 0 | AX17: 0 | AY17: 0 | AZ17: 601908.08 | BA17: 0 | BB17: =SUM(AJ17:BA17) -> 7854975.9 | BC17: 7854975.9 | BD17: =BB17-BC17 -> 0
A18: 15 | B18: 1 | C18: ST. FRANCIS | D18: 0 | E18: 0 | F18: =+AJ18+AK18 -> 0 | G18: =+AL18+AM18 -> 2815887.7 | H18: =+AN18+AO18 -> 0 | I18: =+AP18+AQ18 -> 1739098.9 | J18: =+AR18+AS18 -> 353468.71 | K18: =+AT18+AU18 -> 4582277.5 | L18: =+AV18+AW18 -> 929607.3 | M18: =+AX18+AY18 -> 0 | N18: =+AZ18+BA18 -> 682236.41 | O18: =SUM(F18:N18) -> 11102576 | P18: =SUM(H18:N18) -> 8286688.8 | Q18: =SUM(H18:I18) -> 1739098.9 | R18: =J18 -> 353468.71 | S18: =K18+L18 -> 5511884.8 | T18: =N18+M18 -> 682236.41 | U18: =IF($A$5=1,IF($P18=0,0,ROUND(Q18/$P18*$E18,2)),Credits!D17)+Credits!J17 -> 5109.01 | V18: =IF($A$5=1,IF($P18=0,0,ROUND(R18/$P18*$E18,2)),Credits!E17)+Credits!K17 -> 1039.95 | W18: =IF($A$5=1,IF($P18=0,0,ROUND(S18/$P18*$E18,2)),Credits!F17)+Credits!L17 -> 16304.75 | X18: =IF($A$5=1,IF($P18=0,0,ROUND(T18/$P18*$E18,2)),Credits!G17)+Credits!M17 -> 2161.85 | Y18: =SUM(U18:X18) -> 24615.56 | AE18: =+A18-AG18 -> 0 | AF18: 13-14 | AG18: 15 | AH18: 1 | AI18: 1 | AJ18: 0 | AK18: 0 | AL18: 2815887.7 | AM18: 0 | AN18: 0 | AO18: 0 | AP18: 1739098.9 | AQ18: 0 | AR18: 353468.71 | AS18: 0 | AT18: 4582277.5 | AU18: 0 | AV18: 929607.3 | AW18: 0 | AX18: 0 | AY18: 0 | AZ18: 682236.41 | BA18: 0 | BB18: =SUM(AJ18:BA18) -> 11102576 | BC18: 11102576 | BD18: =BB18-BC18 -> 0
A19: 16 | B19: 1 | C19: SPRING LAKE PARK | D19: 0 | E19: 0 | F19: =+AJ19+AK19 -> 2046138.2 | G19: =+AL19+AM19 -> 3636327.6 | H19: =+AN19+AO19 -> 940446 | I19: =+AP19+AQ19 -> 3060271.5 | J19: =+AR19+AS19 -> 461412.97 | K19: =+AT19+AU19 -> 8721493.1 | L19: =+AV19+AW19 -> 679130.22 | M19: =+AX19+AY19 -> 0 | N19: =+AZ19+BA19 -> 421011.74 | O19: =SUM(F19:N19) -> 19966231 | P19: =SUM(H19:N19) -> 14283766 | Q19: =SUM(H19:I19) -> 4000717.5 | R19: =J19 -> 461412.97 | S19: =K19+L19 -> 9400623.3 | T19: =N19+M19 -> 421011.74 | U19: =IF($A$5=1,IF($P19=0,0,ROUND(Q19/$P19*$E19,2)),Credits!D18)+Credits!J18 -> 0 | V19: =IF($A$5=1,IF($P19=0,0,ROUND(R19/$P19*$E19,2)),Credits!E18)+Credits!K18 -> 0 | W19: =IF($A$5=1,IF($P19=0,0,ROUND(S19/$P19*$E19,2)),Credits!F18)+Credits!L18 -> 0 | X19: =IF($A$5=1,IF($P19=0,0,ROUND(T19/$P19*$E19,2)),Credits!G18)+Credits!M18 -> 0 | Y19: =SUM(U19:X19) -> 0 | AE19: =+A19-AG19 -> 0 | AF19: 13-14 | AG19: 16 | AH19: 1 | AI19: 1 | AJ19: 2046138.2 | AK19: 0 | AL19: 3636327.6 | AM19: 0 | AN19: 940446 | AO19: 0 | AP19: 3060271.5 | AQ19: 0 | AR19: 461412.97 | AS19: 0 | AT19: 8721493.1 | AU19: 0 | AV19: 679130.22 | AW19: 0 | AX19: 0 | AY19: 0 | AZ19: 421011.74 | BA19: 0 | BB19: =SUM(AJ19:BA19) -> 19966231 | BC19: 19966231 | BD19: =BB19-BC19 -> 0
A20: 22 | B20: 1 | C20: DETROIT LAKES | D20: 0 | E20: 0 | F20: =+AJ20+AK20 -> 408798.15 | G20: =+AL20+AM20 -> 1057760.7 | H20: =+AN20+AO20 -> 0 | I20: =+AP20+AQ20 -> 1282085.8 | J20: =+AR20+AS20 -> 214519.78 | K20: =+AT20+AU20 -> 763317.49 | L20: =+AV20+AW20 -> 0 | M20: =+AX20+AY20 -> 0 | N20: =+AZ20+BA20 -> 0 | O20: =SUM(F20:N20) -> 3726481.9 | P20: =SUM(H20:N20) -> 2259923.1 | Q20: =SUM(H20:I20) -> 1282085.8 | R20: =J20 -> 214519.78 | S20: =K20+L20 -> 763317.49 | T20: =N20+M20 -> 0 | U20: =IF($A$5=1,IF($P20=0,0,ROUND(Q20/$P20*$E20,2)),Credits!D19)+Credits!J19 -> 7458.27 | V20: =IF($A$5=1,IF($P20=0,0,ROUND(R20/$P20*$E20,2)),Credits!E19)+Credits!K19 -> 1247.42 | W20: =IF($A$5=1,IF($P20=0,0,ROUND(S20/$P20*$E20,2)),Credits!F19)+Credits!L19 -> 4437.68 | X20: =IF($A$5=1,IF($P20=0,0,ROUND(T20/$P20*$E20,2)),Credits!G19)+Credits!M19 -> 0 | Y20: =SUM(U20:X20) -> 13143.37 | AE20: =+A20-AG20 -> 0 | AF20: 13-14 | AG20: 22 | AH20: 1 | AI20: 1 | AJ20: 408798.15 | AK20: 0 | AL20: 1057760.7 | AM20: 0 | AN20: 0 | AO20: 0 | AP20: 1282085.8 | AQ20: 0 | AR20: 214519.78 | AS20: 0 | AT20: 763317.49 | AU20: 0 | AV20: 0 | AW20: 0 | AX20: 0 | AY20: 0 | AZ20: 0 | BA20: 0 | BB20: =SUM(AJ20:BA20) -> 3726481.9 | BC20: 3726481.9 | BD20: =BB20-BC20 -> 0
... A340: 2908 | B340: 1 | C340: BRANDON-EVANSVILLE | D340: 0 | E340: 0 | F340: =+AJ340+AK340 -> 332679.06 | G340: =+AL340+AM340 -> 47368.78 | H340: =+AN340+AO340 -> 0 | I340: =+AP340+AQ340 -> 313765.78 | J340: =+AR340+AS340 -> 41778.39 | K340: =+AT340+AU340 -> 0 | L340: =+AV340+AW340 -> 0 | M340: =+AX340+AY340 -> 0 | N340: =+AZ340+BA340 -> 0 | O340: =SUM(F340:N340) -> 735592.01 | P340: =SUM(H340:N340) -> 355544.17 | Q340: =SUM(H340:I340) -> 313765.78 | R340: =J340 -> 41778.39 | S340: =K340+L340 -> 0 | T340: =N340+M340 -> 0 | U340: =IF($A$5=1,IF($P340=0,0,ROUND(Q340/$P340*$E340,2)),Credits!D339)+Credits!J339 -> 6296.96 | V340: =IF($A$5=1,IF($P340=0,0,ROUND(R340/$P340*$E340,2)),Credits!E339)+Credits!K339 -> 838.99 | W340: =IF($A$5=1,IF($P340=0,0,ROUND(S340/$P340*$E340,2)),Credits!F339)+Credits!L339 -> 0 | X340: =IF($A$5=1,IF($P340=0,0,ROUND(T340/$P340*$E340,2)),Credits!G339)+Credits!M339 -> 0 | Y340: =SUM(U340:X340) -> 7135.95 | AE340: =+A340-AG340 -> 0 | AF340: 13-14 | AG340: 2908 | AH340: 1 | AI340: 1 | AJ340: 332679.06 | AK340: 0 | AL340: 47368.78 | AM340: 0 | AN340: 0 | AO340: 0 | AP340: 313765.78 | AQ340: 0 | AR340: 41778.39 | AS340: 0 | AT340: 0 | AU340: 0 | AV340: 0 | AW340: 0 | AX340: 0 | AY340: 0 | AZ340: 0 | BA340: 0 | BB340: =SUM(AJ340:BA340) -> 735592.01 | BC340: 735592.01 | BD340: =BB340-BC340 -> 0
A341: End of worksheet
AJ342: 5.3052782e+08 | AK342: -2393.07 | AL342: 3.3645545e+08 | AM342: -56185.29 | AN342: 60897104 | AO342: 0 | AP342: 4.8148454e+08 | AQ342: 58579.01 | AR342: 74876386 | AS342: 0 | AT342: 5.7802268e+08 | AU342: 0 | AV342: 2.2358783e+08 | AW342: 0 | AX342: 0 | AY342: 0 | AZ342: 70274641 | BA342: 0 | BB342: 2.3561265e+09 | BC342: 2.3561265e+09
AJ343: 302 | AL343: 334 | AN343: 29 | AP343: 332 | AR343: 319 | AT343: 260 | AV343: 142 | AX343: 0 | AZ343: 93 | BB343: 331 | BC343: 331

Sheet Credits
A1: Credits by Fund from Revenue | H1: =Report!I1 -> 41828
A2: ="Preliminary "&Instructions!P1&" credits" -> Preliminary Pay 2014 credits
A3: =Instructions!P1&" Levy" -> Pay 2014 Levy | D3: Credits by Fund from Revenue | J3: Taconite Homestead Credit
D4: Fund 1 | E4: Fund 4 | F4: Fund 7 | G4: Fund 47 | H4: Total | J4: Fund 1 | K4: Fund 4 | L4: Fund 7 | M4: Fund 47 | N4: Total
C6: State Total | D6: =SUM(D8:D339) -> 4475710.4 | E6: =SUM(E8:E339) -> 797219.63 | F6: =SUM(F8:F339) -> 8650900.8 | G6: =SUM(G8:G339) -> 1041097.7 | H6: =SUM(H8:H340) -> 14964929 | J6: =SUM(J8:J339) -> 486649.62 | K6: =SUM(K8:K339) -> 2898.11 | L6: =SUM(L8:L339) -> 1064166.4 | M6: =SUM(M8:M339) -> 622291.03 | N6: =SUM(N8:N339) -> 2176005.1 | O6: =N6+H6 -> 17140934 | S6: MNT-TAC-SLP-HMC | T6: CSE-TAC-SLP-HMC | U6: GDS-TAC-SLP-HMC | V6: PEB-TAC-SLP-HMC | W6: ACU-TAC-SLP-CRD | Z6: DIST | AA6: TYPE | AB6: NAME | AD6: TOTAL | AE6: GENERAL | AF6: COMMED | AG6: DEBT | AH6: OPEB
A8: 1 | B8: 1 | C8: AITKIN | D8: 4590.58 | E8: 0 | F8: 1486.72 | G8: 0 | H8: =SUM(D8:G8) -> 6077.3 | J8: 35379.88 | K8: 2155.14 | L8: 12593.13 | M8: 2155.14 | N8: =SUM(J8:M8) -> 52283.29 | Q8: 1 | R8: 1 | S8: 35379.88 | T8: 2155.14 | U8: 12593.13 | V8: 2155.14 | W8: 52283.29 | X8: =SUM(S8:V8)-W8 -> 0 | Y8: =Z8-A8 -> 0 | Z8: 1 | AA8: 1 | AB8: AITKIN | AC8: 0 | AD8: 6077.3 | AE8: 4590.58 | AF8: 0 | AG8: 1486.72 | AH8: 0
A9: 1.2 | B9: 3 | C9: MINNEAPOLIS | D9: 179608.01 | E9: 22053.33 | F9: 228395.17 | G9: 0 | H9: =SUM(D9:G9) -> 430056.51 | J9: 0 | K9: 0 | L9: 0 | M9: 0 | N9: =SUM(J9:M9) -> 0 | Q9: 166 | R9: 1 | S9: 3236.92 | T9: 0 | U9: 27332.43 | V9: 4475.82 | W9: 35045.17 | X9: =SUM(S9:V9)-W9 -> 0 | Y9: =Z9-A9 -> 0 | Z9: 1.2 | AA9: 3 | AB9: MINNEAPOLIS | AC9: 0 | AD9: 430056.51 | AE9: 179608.01 | AF9: 22053.33 | AG9: 228395.17 | AH9: 0
A10: 2 | B10: 1 | C10: HILL CITY | D10: 2269.22 | E10: 688.53 | F10: 7632.7 | G10: 0 | H10: =SUM(D10:G10) -> 10590.45 | J10: 0 | K10: 0 | L10: 0 | M10: 0 | N10: =SUM(J10:M10) -> 0 | Q10: 182 | R10: 1 | S10: 34530.73 | T10: 0 | U10: 114118.4 | V10: 46814.91 | W10: 195464.04 | X10: =SUM(S10:V10)-W10 -> 0 | Y10: =Z10-A10 -> 0 | Z10: 2 | AA10: 1 | AB10: HILL CITY | AC10: 0 | AD10: 10590.45 | AE10: 2269.22 | AF10: 688.53 | AG10: 7632.7 | AH10: 0
A11: 4 | B11: 1 | C11: MCGREGOR | D11: 4370.4 | E11: 725.33 | F11: 10763.91 | G11: 2180.6 | H11: =SUM(D11:G11) -> 18040.24 | J11: 0 | K11: 0 | L11: 0 | M11: 0 | N11: =SUM(J11:M11) -> 0 | Q11: 316 | R11: 1 | S11: 9137.74 | T11: 0 | U11: 66171.74 | V11: 152489.88 | W11: 227799.36 | X11: =SUM(S11:V11)-W11 -> 0 | Y11: =Z11-A11 -> 0 | Z11: 4 | AA11: 1 | AB11: MCGREGOR | AC11: 0 | AD11: 18040.24 | AE11: 4370.4 | AF11: 725.33 | AG11: 10763.91 | AH11: 2180.6
A12: 6 | B12: 3 | C12: SOUTH ST. PAUL | D12: 0 | E12: 0 | F12: 0 | G12: 0 | H12: =SUM(D12:G12) -> 0 | J12: 0 | K12: 0 | L12: 0 | M12: 0 | N12: =SUM(J12:M12) -> 0 | Q12: 317 | R12: 1 | S12: 28.37 | T12: 0 | U12: 51761.85 | V12: 10236.96 | W12: 62027.18 | X12: =SUM(S12:V12)-W12 -> 0 | Y12: =Z12-A12 -> 0 | Z12: 6 | AA12: 3 | AB12: SOUTH ST. PAUL | AC12: 0 | AD12: 0 | AE12: 0 | AF12: 0 | AG12: 0 | AH12: 0
A13: 11 | B13: 1 | C13: ANOKA-HENNEPIN | D13: 5248.43 | E13: 582.57 | F13: 3337.86 | G13: 404.4 | H13: =SUM(D13:G13) -> 9573.26 | J13: 0 | K13: 0 | L13: 0 | M13: 0 | N13: =SUM(J13:M13) -> 0 | Q13: 318 | R13: 1 | S13: 150372.81 | T13: 0 | U13: 166120.73 | V13: 146759.23 | W13: 463252.77 | X13: =SUM(S13:V13)-W13 -> 0 | Y13: =Z13-A13 -> 0 | Z13: 11 | AA13: 1 | AB13: ANOKA-HENNEPIN | AC13: 0 | AD13: 9573.26 | AE13: 5248.43 | AF13: 582.57 | AG13: 3337.86 | AH13: 404.4
A14: 12 | B14: 1 | C14: CENTENNIAL | D14: 752.26 | E14: 57.56 | F14: 802.77 | G14: 82.66 | H14: =SUM(D14:G14) -> 1695.25 | J14: 0 | K14: 0 | L14: 0 | M14: 0 | N14: =SUM(J14:M14) -> 0 | Q14: 319 | R14: 1 | S14: 9575.15 | T14: 0 | U14: 0 | V14: 26977.01 | W14: 36552.16 | X14: =SUM(S14:V14)-W14 -> 0 | Y14: =Z14-A14 -> 0 | Z14: 12 | AA14: 1 | AB14: CENTENNIAL | AC14: 0 | AD14: 1695.25 | AE14: 752.26 | AF14: 57.56 | AG14: 802.77 | AH14: 82.66
A15: 13 | B15: 1 | C15: COLUMBIA HEIGHTS | D15: 72.65 | E15: 15.46 | F15: 72.89 | G15: 0 | H15: =SUM(D15:G15) -> 161 | J15: 0 | K15: 0 | L15: 0 | M15: 0 | N15: =SUM(J15:M15) -> 0 | Q15: 381 | R15: 1 | S15: 14503.16 | T15: 0 | U15: 173932.41 | V15: 51252.64 | W15: 239688.21 | X15: =SUM(S15:V15)-W15 -> 0 | Y15: =Z15-A15 -> 0 | Z15: 13 | AA15: 1 | AB15: COLUMBIA HEIGHTS | AC15: 0 | AD15: 161 | AE15: 72.65 | AF15: 15.46 | AG15: 72.89 | AH15: 0
A16: 14 | B16: 1 | C16: FRIDLEY | D16: 0 | E16: 0 | F16: 0 | G16: 0 | H16: =SUM(D16:G16) -> 0 | J16: 0 | K16: 0 | L16: 0 | M16: 0 | N16: =SUM(J16:M16) -> 0 | Q16: 695 | R16: 1 | S16: 22276.95 | T16: 0 | U16: 28529.51 | V16: 60091.56 | W16: 110898.02 | X16: =SUM(S16:V16)-W16 -> 0 | Y16: =Z16-A16 -> 0 | Z16: 14 | AA16: 1 | AB16: FRIDLEY | AC16: 0 | AD16: 0 | AE16: 0 | AF16: 0 | AG16: 0 | AH16: 0
A17: 15 | B17: 1 | C17: ST. FRANCIS | D17: 5109.01 | E17: 1039.95 | F17: 16304.75 | G17: 2161.85 | H17: =SUM(D17:G17) -> 24615.56 | J17: 0 | K17: 0 | L17: 0 | M17: 0 | N17: =SUM(J17:M17) -> 0 | Q17: 696 | R17: 1 | S17: 39457.87 | T17: 0 | U17: 14382.24 | V17: 0 | W17: 53840.11 | X17: =SUM(S17:V17)-W17 -> 0 | Y17: =Z17-A17 -> 0 | Z17: 15 | AA17: 1 | AB17: ST. FRANCIS | AC17: 0 | AD17: 24615.56 | AE17: 5109.01 | AF17: 1039.95 | AG17: 16304.75 | AH17: 2161.85
A18: 16 | B18: 1 | C18: SPRING LAKE PARK | D18: 0 | E18: 0 | F18: 0 | G18: 0 | H18: =SUM(D18:G18) -> 0 | J18: 0 | K18: 0 | L18: 0 | M18: 0 | N18: =SUM(J18:M18) -> 0 | Q18: 698 | R18: 1 | S18: 5275.86 | T18: 742.97 | U18: 31599.85 | V18: 0 | W18: 37618.68 | X18: =SUM(S18:V18)-W18 -> 0 | Y18: =Z18-A18 -> 0 | Z18: 16 | AA18: 1 | AB18: SPRING LAKE PARK | AC18: 0 | AD18: 0 | AE18: 0 | AF18: 0 | AG18: 0 | AH18: 0
A19: 22 | B19: 1 | C19: DETROIT LAKES | D19: 7458.27 | E19: 1247.42 | F19: 4437.68 | G19: 0 | H19: =SUM(D19:G19) -> 13143.37 | J19: 0 | K19: 0 | L19: 0 | M19: 0 | N19: =SUM(J19:M19) -> 0 | Q19: 701 | R19: 1 | S19: 52679.49 | T19: 0 | U19: 38687.8 | V19: 0 | W19: 91367.29 | X19: =SUM(S19:V19)-W19 -> 0 | Y19: =Z19-A19 -> 0 | Z19: 22 | AA19: 1 | AB19: DETROIT LAKES | AC19: 0 | AD19: 13143.37 | AE19: 7458.27 | AF19: 1247.42 | AG19: 4437.68 | AH19: 0
A20: 23 | B20: 1 | C20: FRAZEE-VERGAS | D20: 6165.16 | E20: 1570.58 | F20: 16577.83 | G20: 0 | H20: =SUM(D20:G20) -> 24313.57 | J20: 0 | K20: 0 | L20: 0 | M20: 0 | N20: =SUM(J20:M20) -> 0 | Q20: 706 | R20: 1 | S20: 25055.74 | T20: 0 | U20: 1974.29 | V20: 28187.05 | W20: 55217.08 | X20: =SUM(S20:V20)-W20 -> 0 | Y20: =Z20-A20 -> 0 | Z20: 23 | AA20: 1 | AB20: FRAZEE-VERGAS | AC20: 0 | AD20: 24313.57 | AE20: 6165.16 | AF20: 1570.58 | AG20: 16577.83 | AH20: 0
A21: 25 | B21: 1 | C21: PINE POINT | D21: 0 | E21: 0 | F21: 0 | G21: 0 | J21: 0 | K21: 0 | L21: 0 | M21: 0 | N21: =SUM(J21:M21) -> 0 | Q21: 712 | R21: 1 | S21: 0 | T21: 0 | U21: 2743.19 | V21: 0 | W21: 2743.19 | X21: =SUM(S21:V21)-W21 -> 0 | Y21: =Z21-A21 -> 0 | Z21: 25 | AA21: 1 | AB21: PINE POINT | AC21: 0 | AD21: 0 | AE21: 0 | AF21: 0 | AG21: 0 | AH21: 0
A22: 31 | B22: 1 | C22: BEMIDJI | D22: 13900.17 | E22: 2802.55 | F22: 24084.93 | G22: 4055.21 | H22: =SUM(D22:G22) -> 44842.86 | J22: 0 | K22: 0 | L22: 0 | M22: 0 | N22: =SUM(J22:M22) -> 0 | Q22: 2142 | R22: 1 | S22: 85028.21 | T22: 0 | U22: 284222.99 | V22: 0 | W22: 369251.2 | X22: =SUM(S22:V22)-W22 -> 0 | Y22: =Z22-A22 -> 0 | Z22: 31 | AA22: 1 | AB22: BEMIDJI | AC22: 0 | AD22: 44842.86 | AE22: 13900.17 | AF22: 2802.55 | AG22: 24084.93 | AH22: 4055.21
A23: 32 | B23: 1 | C23: BLACKDUCK | D23: 8125.04 | E23: 1212.73 | F23: 13694.79 | G23: 0 | H23: =SUM(D23:G23) -> 23032.56 | J23: 0 | K23: 0 | L23: 0 | M23: 0 | N23: =SUM(J23:M23) -> 0 | Q23: 2154 | R23: 1 | S23: 59.79 | T23: 0 | U23: 3825.98 | V23: 0 | W23: 3885.77 | X23: =SUM(S23:V23)-W23 -> 0 | Y23: =Z23-A23 -> 0 | Z23: 32 | AA23: 1 | AB23: BLACKDUCK | AC23: 0 | AD23: 23032.56 | AE23: 8125.04 | AF23: 1212.73 | AG23: 13694.79 | AH23: 0
A24: 36 | B24: 1 | C24: KELLIHER | D24: 603.37 | E24: 359.9 | F24: 9694.47 | G24: 0 | H24: =SUM(D24:G24) -> 10657.74 | J24: 0 | K24: 0 | L24: 0 | M24: 0 | N24: =SUM(J24:M24) -> 0 | Q24: 2711 | R24: 1 | S24: 50.95 | T24: 0 | U24: 46169.85 | V24: 92850.83 | W24: 139071.63 | X24: =SUM(S24:V24)-W24 -> 0 | Y24: =Z24-A24 -> 0 | Z24: 36 | AA24: 1 | AB24: KELLIHER | AC24: 0 | AD24: 10657.74 | AE24: 603.37 | AF24: 359.9 | AG24: 9694.47 | AH24: 0
A25: 38 | B25: 1 | C25: RED LAKE | D25: 0 | E25: 0 | F25: 0 | G25: 0 | H25: =SUM(D25:G25) -> 0 | J25: 0 | K25: 0 | L25: 0 | M25: 0 | N25: =SUM(J25:M25) -> 0 | W25: =SUM(W8:W24) -> 2176005.1 | Y25: =Z25-A25 -> 0 | Z25: 38 | AA25: 1 | AB25: RED LAKE | AC25: 0 | AD25: 0 | AE25: 0 | AF25: 0 | AG25: 0 | AH25: 0
A26: 47 | B26: 1 | C26: SAUK RAPIDS | D26: 5836.68 | E26: 1054.08 | F26: 23891 | G26: 0 | H26: =SUM(D26:G26) -> 30781.76 | J26: 0 | K26: 0 | L26: 0 | M26: 0 | N26: =SUM(J26:M26) -> 0 | Y26: =Z26-A26 -> 0 | Z26: 47 | AA26: 1 | AB26: SAUK RAPIDS | AC26: 0 | AD26: 30781.76 | AE26: 5836.68 | AF26: 1054.08 | AG26: 23891 | AH26: 0
A27: 51 | B27: 1 | C27: FOLEY | D27: 11538.69 | E27: 2622.95 | F27: 98756.54 | G27: 0 | H27: =SUM(D27:G27) -> 112918.18 | J27: 0 | K27: 0 | L27: 0 | M27: 0 | N27: =SUM(J27:M27) -> 0 | Y27: =Z27-A27 -> 0 | Z27: 51 | AA27: 1 | AB27: FOLEY | AC27: 0 | AD27: 112918.18 | AE27: 11538.69 | AF27: 2622.95 | AG27: 98756.54 | AH27: 0
A28: 75 | B28: 1 | C28: ST. CLAIR | D28: 2367.55 | E28: 508.36 | F28: 10590.26 | G28: 0 | H28: =SUM(D28:G28) -> 13466.17 | J28: 0 | K28: 0 | L28: 0 | M28: 0 | N28: =SUM(J28:M28) -> 0 | Y28: =Z28-A28 -> 0 | Z28: 75 | AA28: 1 | AB28: ST. CLAIR | AC28: 0 | AD28: 13466.17 | AE28: 2367.55 | AF28: 508.36 | AG28: 10590.26 | AH28: 0
A29: 77 | B29: 1 | C29: MANKATO | D29: 19817.7 | E29: 4526.84 | F29: 36447.13 | G29: 9387.63 | H29: =SUM(D29:G29) -> 70179.3 | J29: 0 | K29: 0 | L29: 0 | M29: 0 | N29: =SUM(J29:M29) -> 0 | Y29: =Z29-A29 -> 0 | Z29: 77 | AA29: 1 | AB29: MANKATO | AC29: 0 | AD29: 70179.3 | AE29: 19817.7 | AF29: 4526.84 | AG29: 36447.13 | AH29: 9387.63
A30: 81 | B30: 1 | C30: COMFREY | D30: 8111.52 | E30: 1401.71 | F30: 0 | G30: 0 | H30: =SUM(D30:G30) -> 9513.23 | J30: 0 | K30: 0 | L30: 0 | M30: 0 | N30: =SUM(J30:M30) -> 0 | Y30: =Z30-A30 -> 0 | Z30: 81 | AA30: 1 | AB30: COMFREY | AC30: 0 | AD30: 9513.23 | AE30: 8111.52 | AF30: 1401.71 | AG30: 0 | AH30: 0
A31: 84 | B31: 1 | C31: SLEEPY EYE | D31: 9737.19 | E31: 2260.11 | F31: 10989 | G31: 0 | H31: =SUM(D31:G31) -> 22986.3 | J31: 0 | K31: 0 | L31: 0 | M31: 0 | N31: =SUM(J31:M31) -> 0 | Y31: =Z31-A31 -> 0 | Z31: 84 | AA31: 1 | AB31: SLEEPY EYE | AC31: 0 | AD31: 22986.3 | AE31: 9737.19 | AF31: 2260.11 | AG31: 10989 | AH31: 0
A32: 85 | B32: 1 | C32: SPRINGFIELD | D32: 9885.03 | E32: 2177.8 | F32: 0 | G32: 0 | H32: =SUM(D32:G32) -> 12062.83 | J32: 0 | K32: 0 | L32: 0 | M32: 0 | N32: =SUM(J32:M32) -> 0 | Y32: =Z32-A32 -> 0 | Z32: 85 | AA32: 1 | AB32: SPRINGFIELD | AC32: 0 | AD32: 12062.83 | AE32: 9885.03 | AF32: 2177.8 | AG32: 0 | AH32: 0
A33: 88 | B33: 1 | C33: NEW ULM | D33: 27958.78 | E33: 4832.75 | F33: 31260.69 | G33: 0 | H33: =SUM(D33:G33) -> 64052.22 | J33: 0 | K33: 0 | L33: 0 | M33: 0 | N33: =SUM(J33:M33) -> 0 | Y33: =Z33-A33 -> 0 | Z33: 88 | AA33: 1 | AB33: NEW ULM | AC33: 0 | AD33: 64052.22 | AE33: 27958.78 | AF33: 4832.75 | AG33: 31260.69 | AH33: 0
A34: 91 | B34: 1 | C34: BARNUM | D34: 8412.47 | E34: 1599.73 | F34: 8767.27 | G34: 0 | H34: =SUM(D34:G34) -> 18779.47 | J34: 0 | K34: 0 | L34: 0 | M34: 0 | N34: =SUM(J34:M34) -> 0 | Y34: =Z34-A34 -> 0 | Z34: 91 | AA34: 1 | AB34: BARNUM | AC34: 0 | AD34: 18779.47 | AE34: 8412.47 | AF34: 1599.73 | AG34: 8767.27 | AH34: 0
A35: 93 | B35: 1 | C35: CARLTON | D35: 7797.92 | E35: 3587.52 | F35: 4370.91 | G35: 15091.97 | H35: =SUM(D35:G35) -> 30848.32 | J35: 0 | K35: 0 | L35: 0 | M35: 0 | N35: =SUM(J35:M35) -> 0 | Y35: =Z35-A35 -> 0 | Z35: 93 | AA35: 1 | AB35: CARLTON | AC35: 0 | AD35: 30848.32 | AE35: 7797.92 | AF35: 3587.52 | AG35: 4370.91 | AH35: 15091.97
A36: 94 | B36: 1 | C36: CLOQUET | D36: 23797.24 | E36: 15675.95 | F36: 117203.58 | G36: 30620.06 | H36: =SUM(D36:G36) -> 187296.83 | J36: 0 | K36: 0 | L36: 0 | M36: 0 | N36: =SUM(J36:M36) -> 0 | Y36: =Z36-A36 -> 0 | Z36: 94 | AA36: 1 | AB36: CLOQUET | AC36: 0 | AD36: 187296.83 | AE36: 23797.24 | AF36: 15675.95 | AG36: 117203.58 | AH36: 30620.06
A37: 95 | B37: 1 | C37: CROMWELL-WRIGHT | D37: 1506.2 | E37: 443.61 | F37: 10741.86 | G37: 0 | H37: =SUM(D37:G37) -> 12691.67 | J37: 0 | K37: 0 | L37: 0 | M37: 0 | N37: =SUM(J37:M37) -> 0 | Y37: =Z37-A37 -> 0 | Z37: 95 | AA37: 1 | AB37: CROMWELL-WRIGHT | AC37: 0 | AD37: 12691.67 | AE37: 1506.2 | AF37: 443.61 | AG37: 10741.86 | AH37: 0
... A339: 2908 | B339: 1 | C339: BRANDON-EVANSVILLE | D339: 6296.96 | E339: 838.99 | F339: 0 | G339: 0 | H339: =SUM(D339:G339) -> 7135.95 | J339: 0 | K339: 0 | L339: 0 | M339: 0 | N339: =SUM(J339:M339) -> 0 | Y339: =Z339-A339 -> 0 | Z339: 2908 | AA339: 1 | AB339: BRANDON-EVANSVILLE | AC339: 0 | AD339: 7135.95 | AE339: 6296.96 | AF339: 838.99 | AG339: 0 | AH339: 0
A340: End of worksheet

Sheet Receipts
A1: ="Compare "&Instructions!P1&" Gross Shift to Tax Receipts" -> Compare Pay 2014 Gross Shift to Tax Receipts | L1: =Report!I1 -> 41828
A2: Shift at | B2: ='Shift 14'!B2 -> 0 | D2: General Fund | I2: Community Service Fund | N2: Total May-June 2014 Tax Receipts for Ideas | O2: =Instructions!P1&" General + Comm Service Levies" -> Pay 2014 General + Comm Service Levies
D3: Total Gross Shift | E3: ="Est Tax Receipts May-July "&Instructions!O1 -> Est Tax Receipts May-July 2014 | F3: Estimated Gened Recognition | G3: Lesser of Gross Shift or Tax Receipts (but not less than zero) | I3: Total Gross Shift | J3: ="Est Tax Receipts May-July "&Instructions!O1 -> Est Tax Receipts May-July 2014 | K3: Estimated Gened Recognition | L3: Lesser of Gross Shift or Tax Receipts (but not less than zero) | O3: Levy | P3: Credits | Q3: Net Levy
C5: State Total | D5: =SUM(D7:D338) -> 1.7112238e+08 | E5: =SUM(E7:E338) -> 7.0220128e+08 | F5: =SUM(F7:F338) -> 652437.24 | G5: =SUM(G7:G338) -> 1.7050931e+08 | I5: =SUM(I7:I338) -> 0 | J5: =SUM(J7:J338) -> 37039212 | K5: =SUM(K7:K338) -> 0 | L5: =SUM(L7:L338) -> 0 | N5: =SUM(N7:N338) -> 1.7050931e+08 | O5: =SUM(O7:O338) -> 1.4842413e+09 | P5: =SUM(P7:P338) -> 5762477.8 | Q5: =SUM(Q7:Q338) -> 1.4784788e+09
A7: 1 | B7: 1 | C7: AITKIN | D7: =SUM('Shift 14'!D6:L6) -> 178003.41 | E7: =ROUND(MAX(0,(Levy!Q9+Data!D8+Data!E8-Levy!U9)*0.5),2) -> 424563.77 | F7: =IF(D7>E7,D7-E7,0) -> 0 | G7: =MAX(0,MIN(D7,E7)) -> 178003.41 | I7: =SUM('Shift 14'!M6:N6) -> 0 | J7: =ROUND(MAX(0,(Levy!R9-Levy!V9)*0.5),2) -> 0 | K7: =IF(I7>J7,I7-J7,0) -> 0 | L7: =MAX(0,MIN(I7,J7)) -> 0 | N7: =G7+L7 -> 178003.41 | O7: =SUM(Levy!F9:J9) -> 889098 | P7: =SUM(Levy!U9:V9) -> 42125.6 | Q7: =O7-P7 -> 846972.4
A8: 1.2 | B8: 3 | C8: MINNEAPOLIS | D8: =SUM('Shift 14'!D7:L7) -> 25554575 | E8: =ROUND(MAX(0,(Levy!Q10+Data!D9+Data!E9-Levy!U10)*0.5),2) -> 57703013 | F8: =IF(D8>E8,D8-E8,0) -> 0 | G8: =MAX(0,MIN(D8,E8)) -> 25554575 | I8: =SUM('Shift 14'!M7:N7) -> 0 | J8: =ROUND(MAX(0,(Levy!R10-Levy!V10)*0.5),2) -> 2468015.8 | K8: =IF(I8>J8,I8-J8,0) -> 0 | L8: =MAX(0,MIN(I8,J8)) -> 0 | N8: =G8+L8 -> 25554575 | O8: =SUM(Levy!F10:J10) -> 1.2054372e+08 | P8: =SUM(Levy!U10:V10) -> 201661.34 | Q8: =O8-P8 -> 1.2034206e+08
A9: 2 | B9: 1 | C9: HILL CITY | D9: =SUM('Shift 14'!D8:L8) -> -19946.37 | E9: =ROUND(MAX(0,(Levy!Q11+Data!D10+Data!E10-Levy!U11)*0.5),2) -> 57123.89 | F9: =IF(D9>E9,D9-E9,0) -> 0 | G9: =MAX(0,MIN(D9,E9)) -> 0 | I9: =SUM('Shift 14'!M8:N8) -> 0 | J9: =ROUND(MAX(0,(Levy!R11-Levy!V11)*0.5),2) -> 8935.24 | K9: =IF(I9>J9,I9-J9,0) -> 0 | L9: =MAX(0,MIN(I9,J9)) -> 0 | N9: =G9+L9 -> 0 | O9: =SUM(Levy!F11:J11) -> 135076 | P9: =SUM(Levy!U11:V11) -> 2957.75 | Q9: =O9-P9 -> 132118.25
A10: 4 | B10: 1 | C10: MCGREGOR | D10: =SUM('Shift 14'!D9:L9) -> 77844.98 | E10: =ROUND(MAX(0,(Levy!Q12+Data!D11+Data!E11-Levy!U12)*0.5),2) -> 208299.8 | F10: =IF(D10>E10,D10-E10,0) -> 0 | G10: =MAX(0,MIN(D10,E10)) -> 77844.98 | I10: =SUM('Shift 14'!M9:N9) -> 0 | J10: =ROUND(MAX(0,(Levy!R12-Levy!V12)*0.5),2) -> 26152.34 | K10: =IF(I10>J10,I10-J10,0) -> 0 | L10: =MAX(0,MIN(I10,J10)) -> 0 | N10: =G10+L10 -> 77844.98 | O10: =SUM(Levy!F12:J12) -> 474000 | P10: =SUM(Levy!U12:V12) -> 5095.73 | Q10: =O10-P10 -> 468904.27
A11: 6 | B11: 3 | C11: SOUTH ST. PAUL | D11: =SUM('Shift 14'!D10:L10) -> 412070.86 | E11: =ROUND(MAX(0,(Levy!Q13+Data!D12+Data!E12-Levy!U13)*0.5),2) -> 2679088 | F11: =IF(D11>E11,D11-E11,0) -> 0 | G11: =MAX(0,MIN(D11,E11)) -> 412070.86 | I11: =SUM('Shift 14'!M10:N10) -> 0 | J11: =ROUND(MAX(0,(Levy!R13-Levy!V13)*0.5),2) -> 156794.5 | K11: =IF(I11>J11,I11-J11,0) -> 0 | L11: =MAX(0,MIN(I11,J11)) -> 0 | N11: =G11+L11 -> 412070.86 | O11: =SUM(Levy!F13:J13) -> 5671765 | P11: =SUM(Levy!U13:V13) -> 0 | Q11: =O11-P11 -> 5671765
A12: 11 | B12: 1 | C12: ANOKA-HENNEPIN | D12: =SUM('Shift 14'!D11:L11) -> 4173596.9 | E12: =ROUND(MAX(0,(Levy!Q14+Data!D13+Data!E13-Levy!U14)*0.5),2) -> 34288026 | F12: =IF(D12>E12,D12-E12,0) -> 0 | G12: =MAX(0,MIN(D12,E12)) -> 4173596.9 | I12: =SUM('Shift 14'!M11:N11) -> 0 | J12: =ROUND(MAX(0,(Levy!R14-Levy!V14)*0.5),2) -> 1542233 | K12: =IF(I12>J12,I12-J12,0) -> 0 | L12: =MAX(0,MIN(I12,J12)) -> 0 | N12: =G12+L12 -> 4173596.9 | O12: =SUM(Levy!F14:J14) -> 71666349 | P12: =SUM(Levy!U14:V14) -> 5831 | Q12: =O12-P12 -> 71660518
A13: 12 | B13: 1 | C13: CENTENNIAL | D13: =SUM('Shift 14'!D12:L12) -> 438499.7 | E13: =ROUND(MAX(0,(Levy!Q15+Data!D14+Data!E14-Levy!U15)*0.5),2) -> 4912307.9 | F13: =IF(D13>E13,D13-E13,0) -> 0 | G13: =MAX(0,MIN(D13,E13)) -> 438499.7 | I13: =SUM('Shift 14'!M12:N12) -> 0 | J13: =ROUND(MAX(0,(Levy!R15-Levy!V15)*0.5),2) -> 206891.53 | K13: =IF(I13>J13,I13-J13,0) -> 0 | L13: =MAX(0,MIN(I13,J13)) -> 0 | N13: =G13+L13 -> 438499.7 | O13: =SUM(Levy!F15:J15) -> 10239209 | P13: =SUM(Levy!U15:V15) -> 809.82 | Q13: =O13-P13 -> 10238399
A14: 13 | B14: 1 | C14: COLUMBIA HEIGHTS | D14: =SUM('Shift 14'!D13:L13) -> 936471.35 | E14: =ROUND(MAX(0,(Levy!Q16+Data!D15+Data!E15-Levy!U16)*0.5),2) -> 2398310.2 | F14: =IF(D14>E14,D14-E14,0) -> 0 | G14: =MAX(0,MIN(D14,E14)) -> 936471.35 | I14: =SUM('Shift 14'!M13:N13) -> 0 | J14: =ROUND(MAX(0,(Levy!R16-Levy!V16)*0.5),2) -> 202017.38 | K14: =IF(I14>J14,I14-J14,0) -> 0 | L14: =MAX(0,MIN(I14,J14)) -> 0 | N14: =G14+L14 -> 936471.35 | O14: =SUM(Levy!F16:J16) -> 5200743.2 | P14: =SUM(Levy!U16:V16) -> 88.11 | Q14: =O14-P14 -> 5200655.1
A15: 14 | B15: 1 | C15: FRIDLEY | D15: =SUM('Shift 14'!D14:L14) -> 474976.16 | E15: =ROUND(MAX(0,(Levy!Q17+Data!D16+Data!E16-Levy!U17)*0.5),2) -> 2063399.6 | F15: =IF(D15>E15,D15-E15,0) -> 0 | G15: =MAX(0,MIN(D15,E15)) -> 474976.16 | I15: =SUM('Shift 14'!M14:N14) -> 0 | J15: =ROUND(MAX(0,(Levy!R17-Levy!V17)*0.5),2) -> 160892.89 | K15: =IF(I15>J15,I15-J15,0) -> 0 | L15: =MAX(0,MIN(I15,J15)) -> 0 | N15: =G15+L15 -> 474976.16 | O15: =SUM(Levy!F17:J17) -> 4448584.9 | P15: =SUM(Levy!U17:V17) -> 0 | Q15: =O15-P15 -> 4448584.9
A16: 15 | B16: 1 | C16: ST. FRANCIS | D16: =SUM('Shift 14'!D15:L15) -> 390023.85 | E16: =ROUND(MAX(0,(Levy!Q18+Data!D17+Data!E17-Levy!U18)*0.5),2) -> 2274938.8 | F16: =IF(D16>E16,D16-E16,0) -> 0 | G16: =MAX(0,MIN(D16,E16)) -> 390023.85 | I16: =SUM('Shift 14'!M15:N15) -> 0 | J16: =ROUND(MAX(0,(Levy!R18-Levy!V18)*0.5),2) -> 176214.38 | K16: =IF(I16>J16,I16-J16,0) -> 0 | L16: =MAX(0,MIN(I16,J16)) -> 0 | N16: =G16+L16 -> 390023.85 | O16: =SUM(Levy!F18:J18) -> 4908455.2 | P16: =SUM(Levy!U18:V18) -> 6148.96 | Q16: =O16-P16 -> 4902306.3
A17: 16 | B17: 1 | C17: SPRING LAKE PARK | D17: =SUM('Shift 14'!D16:L16) -> 1071962.7 | E17: =ROUND(MAX(0,(Levy!Q19+Data!D18+Data!E18-Levy!U19)*0.5),2) -> 4841591.6 | F17: =IF(D17>E17,D17-E17,0) -> 0 | G17: =MAX(0,MIN(D17,E17)) -> 1071962.7 | I17: =SUM('Shift 14'!M16:N16) -> 0 | J17: =ROUND(MAX(0,(Levy!R19-Levy!V19)*0.5),2) -> 230706.49 | K17: =IF(I17>J17,I17-J17,0) -> 0 | L17: =MAX(0,MIN(I17,J17)) -> 0 | N17: =G17+L17 -> 1071962.7 | O17: =SUM(Levy!F19:J19) -> 10144596 | P17: =SUM(Levy!U19:V19) -> 0 | Q17: =O17-P17 -> 10144596
A18: 22 | B18: 1 | C18: DETROIT LAKES | D18: =SUM('Shift 14'!D17:L17) -> 216904.1 | E18: =ROUND(MAX(0,(Levy!Q20+Data!D19+Data!E19-Levy!U20)*0.5),2) -> 1370593.2 | F18: =IF(D18>E18,D18-E18,0) -> 0 | G18: =MAX(0,MIN(D18,E18)) -> 216904.1 | I18: =SUM('Shift 14'!M17:N17) -> 0 | J18: =ROUND(MAX(0,(Levy!R20-Levy!V20)*0.5),2) -> 106636.18 | K18: =IF(I18>J18,I18-J18,0) -> 0 | L18: =MAX(0,MIN(I18,J18)) -> 0 | N18: =G18+L18 -> 216904.1 | O18: =SUM(Levy!F20:J20) -> 2963164.4 | P18: =SUM(Levy!U20:V20) -> 8705.69 | Q18: =O18-P18 -> 2954458.8
... A338: 2908 | B338: 1 | C338: BRANDON-EVANSVILLE | D338: =SUM('Shift 14'!D337:L337) -> 22016 | E338: =ROUND(MAX(0,(Levy!Q340+Data!D339+Data!E339-Levy!U340)*0.5),2) -> 343758.33 | F338: =IF(D338>E338,D338-E338,0) -> 0 | G338: =MAX(0,MIN(D338,E338)) -> 22016 | I338: =SUM('Shift 14'!M337:N337) -> 0 | J338: =ROUND(MAX(0,(Levy!R340-Levy!V340)*0.5),2) -> 20469.7 | K338: =IF(I338>J338,I338-J338,0) -> 0 | L338: =MAX(0,MIN(I338,J338)) -> 0 | N338: =G338+L338 -> 22016 | O338: =SUM(Levy!F340:J340) -> 735592.01 | P338: =SUM(Levy!U340:V340) -> 7135.95 | Q338: =O338-P338 -> 728456.06
A339: End of worksheet

Sheet Ideas
A1: IDEAS from State Aid Adjustment (Column 5).xlsx | E1: -1
A2: File created from IDEAS run under S:\common\TAXSFTR
H3: =Report!I1 -> 41828
D4: ="Est Aid Reductions (Payments) in "&Instructions!R2&" for Shift" -> Est Aid Reductions (Payments) in FY 2014 for Shift | G4: ="GNL 214 Account "&Instructions!S3 -> GNL 214 Account 06/30/13
D5: General Fund | E5: Comm Serv Fund | G5: General Fund | H5: Comm Serv Fund
C7: State Total | D7: =SUM(D9:D340) -> 5.5105974e+08 | E7: =SUM(E9:E340) -> 0 | F7: =E7+D7 -> 5.5105974e+08 | G7: =SUM(G9:G340) -> -10807543 | H7: =SUM(H9:H340) -> -92759.3
A9: 1 | B9: 1 | C9: AITKIN | D9: 354088.31 | E9: 0 | G9: =SUMIF(Query1!$B$4:$B$125,A9,Query1!$F$4:$F$125) -> -113799.41 | H9: =SUMIF(Query4!$B$4:$B$48,A9,Query4!$F$4:$F$48) -> 0 | J9: =L9-A9 -> 0 | K9: 13-14 | L9: 1 | M9: 1 | N9: AITKIN PUBLIC SCHOOL DIST | O9: 354088.31 | P9: 0
A10: 1.2 | B10: 3 | C10: MINNEAPOLIS | D10: 34709031 | E10: 0 | G10: =SUMIF(Query1!$B$4:$B$125,A10,Query1!$F$4:$F$125) -> -6868314 | H10: =SUMIF(Query4!$B$4:$B$48,A10,Query4!$F$4:$F$48) -> 0 | J10: =L10-A10 -> 0 | K10: 13-14 | L10: 1.2 | M10: 3 | N10: MINNEAPOLIS PUBLIC SCHOOL | O10: 34709031 | P10: 0
A11: 2 | B11: 1 | C11: HILL CITY | D11: 62600.18 | E11: 0 | G11: =SUMIF(Query1!$B$4:$B$125,A11,Query1!$F$4:$F$125) -> 0 | H11: =SUMIF(Query4!$B$4:$B$48,A11,Query4!$F$4:$F$48) -> 0 | J11: =L11-A11 -> 0 | K11: 13-14 | L11: 2 | M11: 1 | N11: HILL CITY PUBLIC SCHOOL D | O11: 62600.18 | P11: 0
A12: 4 | B12: 1 | C12: MCGREGOR | D12: 197459 | E12: 0 | G12: =SUMIF(Query1!$B$4:$B$125,A12,Query1!$F$4:$F$125) -> -34513.74 | H12: =SUMIF(Query4!$B$4:$B$48,A12,Query4!$F$4:$F$48) -> 0 | J12: =L12-A12 -> 0 | K12: 13-14 | L12: 4 | M12: 1 | N12: MCGREGOR PUBLIC SCHOOL DI | O12: 197459 | P12: 0
A13: 6 | B13: 3 | C13: SOUTH ST. PAUL | D13: 2618120.8 | E13: 0 | G13: =SUMIF(Query1!$B$4:$B$125,A13,Query1!$F$4:$F$125) -> 0 | H13: =SUMIF(Query4!$B$4:$B$48,A13,Query4!$F$4:$F$48) -> 0 | J13: =L13-A13 -> 0 | K13: 13-14 | L13: 6 | M13: 3 | N13: SOUTH ST. PAUL PUBLIC SCH | O13: 2618120.8 | P13: 0
A14: 11 | B14: 1 | C14: ANOKA-HENNEPIN | D14: 32549580 | E14: 0 | G14: =SUMIF(Query1!$B$4:$B$125,A14,Query1!$F$4:$F$125) -> 0 | H14: =SUMIF(Query4!$B$4:$B$48,A14,Query4!$F$4:$F$48) -> 0 | J14: =L14-A14 -> 0 | K14: 13-14 | L14: 11 | M14: 1 | N14: ANOKA-HENNEPIN PUBLIC SCH | O14: 32549580 | P14: 0
A15: 12 | B15: 1 | C15: CENTENNIAL | D15: 4213737.3 | E15: 0 | G15: =SUMIF(Query1!$B$4:$B$125,A15,Query1!$F$4:$F$125) -> 0 | H15: =SUMIF(Query4!$B$4:$B$48,A15,Query4!$F$4:$F$48) -> 0 | J15: =L15-A15 -> 0 | K15: 13-14 | L15: 12 | M15: 1 | N15: CENTENNIAL PUBLIC SCHOOL | O15: 4213737.3 | P15: 0
A16: 13 | B16: 1 | C16: COLUMBIA HEIGHTS | D16: 2019263.6 | E16: 0 | G16: =SUMIF(Query1!$B$4:$B$125,A16,Query1!$F$4:$F$125) -> 0 | H16: =SUMIF(Query4!$B$4:$B$48,A16,Query4!$F$4:$F$48) -> 0 | J16: =L16-A16 -> 0 | K16: 13-14 | L16: 13 | M16: 1 | N16: COLUMBIA HEIGHTS PUBLIC S | O16: 2019263.6 | P16: 0
A17: 14 | B17: 1 | C17: FRIDLEY | D17: 2099053.2 | E17: 0 | G17: =SUMIF(Query1!$B$4:$B$125,A17,Query1!$F$4:$F$125) -> 0 | H17: =SUMIF(Query4!$B$4:$B$48,A17,Query4!$F$4:$F$48) -> 0 | J17: =L17-A17 -> 0 | K17: 13-14 | L17: 14 | M17: 1 | N17: FRIDLEY PUBLIC SCHOOL DIS | O17: 2099053.2 | P17: 0
A18: 15 | B18: 1 | C18: ST. FRANCIS | D18: 1863798.1 | E18: 0 | G18: =SUMIF(Query1!$B$4:$B$125,A18,Query1!$F$4:$F$125) -> 0 | H18: =SUMIF(Query4!$B$4:$B$48,A18,Query4!$F$4:$F$48) -> 0 | J18: =L18-A18 -> 0 | K18: 13-14 | L18: 15 | M18: 1 | N18: ST. FRANCIS PUBLIC SCHOOL | O18: 1863798.1 | P18: 0
A19: 16 | B19: 1 | C19: SPRING LAKE PARK | D19: 4228881.8 | E19: 0 | G19: =SUMIF(Query1!$B$4:$B$125,A19,Query1!$F$4:$F$125) -> 0 | H19: =SUMIF(Query4!$B$4:$B$48,A19,Query4!$F$4:$F$48) -> 0 | J19: =L19-A19 -> 0 | K19: 13-14 | L19: 16 | M19: 1 | N19: SPRING LAKE PARK PUBLIC S | O19: 4228881.8 | P19: 0
A20: 22 | B20: 1 | C20: DETROIT LAKES | D20: 1306665 | E20: 0 | G20: =SUMIF(Query1!$B$4:$B$125,A20,Query1!$F$4:$F$125) -> 0 | H20: =SUMIF(Query4!$B$4:$B$48,A20,Query4!$F$4:$F$48) -> 0 | J20: =L20-A20 -> 0 | K20: 13-14 | L20: 22 | M20: 1 | N20: DETROIT LAKES PUBLIC SCHO | O20: 1306665 | P20: 0
... A340: 2908 | B340: 1 | C340: BRANDON-EVANSVILLE | D340: 415418.71 | E340: 0 | G340: =SUMIF(Query1!$B$4:$B$125,A340,Query1!$F$4:$F$125) -> 0 | H340: =SUMIF(Query4!$B$4:$B$48,A340,Query4!$F$4:$F$48) -> 0 | J340: =L340-A340 -> 0 | K340: 13-14 | L340: 2908 | M340: 1 | N340: BRANDON-EVANSVILLE PUBLIC | O340: 415418.71 | P340: 0
A341: End of worksheet

Sheet Query1
A1: Query Date 07-06-14
A2: Watch for consolidated districts
A3: dat_yer | B3: dst_num | C3: dst_tye | D3: gen_lgr_num | E3: fun_num | F3: end_bal_amt
A4: 12-13 | B4: 1 | C4: 1 | D4: 2.14 | E4: 1 | F4: -113799.41
A5: 12-13 | B5: 1.2 | C5: 3 | D5: 2.14 | E5: 1 | F5: -6868314
A6: 12-13 | B6: 2 | C6: 1 | D6: 2.14 | E6: 1 | F6: 0
A7: 12-13 | B7: 4 | C7: 1 | D7: 2.14 | E7: 1 | F7: -34513.74
A8: 12-13 | B8: 23 | C8: 1 | D8: 2.14 | E8: 1 | F8: 0
A9: 12-13 | B9: 47 | C9: 1 | D9: 2.14 | E9: 1 | F9: -0.2
A10: 12-13 | B10: 81 | C10: 1 | D10: 2.14 | E10: 1 | F10: -2763.2
A11: 12-13 | B11: 84 | C11: 1 | D11: 2.14 | E11: 1 | F11: -60338.91
A12: 12-13 | B12: 85 | C12: 1 | D12: 2.14 | E12: 1 | F12: 0
A13: 12-13 | B13: 91 | C13: 1 | D13: 2.14 | E13: 1 | F13: -14949.61
A14: 12-13 | B14: 94 | C14: 1 | D14: 2.14 | E14: 1 | F14: -11100.62
A15: 12-13 | B15: 95 | C15: 1 | D15: 2.14 | E15: 1 | F15: 0
... A125: 12-13 | B125: 2905 | C125: 1 | D125: 2.14 | E125: 1 | F125: 0
F126: =SUM(F4:F125) -> -10837630
A129: 11-12 | B129: 392 | C129: 1 | D129: 2.14 | E129: 1 | F129: 0
A130: 11-12 | B130: 394 | C130: 1 | D130: 2.14 | E130: 1 | F130: -8.49
A131: End of worksheet

Sheet Query4
A1: Query Date 07-06-14
A2: Watch for consolidated districts
A3: dat_yer | B3: dst_num | C3: dst_tye | D3: gen_lgr_num | E3: fun_num | F3: end_bal_amt
A4: 12-13 | B4: 1 | C4: 1 | D4: 2.14 | E4: 4 | F4: 0
A5: 12-13 | B5: 108 | C5: 1 | D5: 2.14 | E5: 4 | F5: -7554
A6: 12-13 | B6: 150 | C6: 1 | D6: 2.14 | E6: 4 | F6: 0.12
A7: 12-13 | B7: 152 | C7: 1 | D7: 2.14 | E7: 4 | F7: -28387
A8: 12-13 | B8: 173 | C8: 1 | D8: 2.14 | E8: 4 | F8: 0
A9: 12-13 | B9: 192 | C9: 1 | D9: 2.14 | E9: 4 | F9: -28386.78
A10: 12-13 | B10: 195 | C10: 1 | D10: 2.14 | E10: 4 | F10: 0
A11: 12-13 | B11: 229 | C11: 1 | D11: 2.14 | E11: 4 | F11: -165.25
A12: 12-13 | B12: 252 | C12: 1 | D12: 2.14 | E12: 4 | F12: 0
A13: 12-13 | B13: 264 | C13: 1 | D13: 2.14 | E13: 4 | F13: 0
A14: 12-13 | B14: 297 | C14: 1 | D14: 2.14 | E14: 4 | F14: -1911
A15: 12-13 | B15: 432 | C15: 1 | D15: 2.14 | E15: 4 | F15: -236
... A49: 11-12 | B49: 2905 | C49: 1 | D49: 2.14 | E49: 4 | F49: 0
F50: =SUM(F4:F49) -> -92759.77
A54: 11-12 | B54: 392 | C54: 1 | D54: 2.14 | E54: 4 | F54: 0
A55: 11-12 | B55: 394 | C55: 1 | D55: 2.14 | E55: 4 | F55: 0
A56: End of worksheet

Sheet Names
A1: Dist | B1: Type | C1: Name
A2: 1 | B2: 1 | C2: AITKIN | D2: =E2-A2 -> 0 | E2: 1 | F2: 1 | G2: AITKIN PUBLIC SCHOOL DIST
A3: 1.2 | B3: 3 | C3: MINNEAPOLIS | D3: =E3-A3 -> -0.2 | E3: 1 | F3: 3 | G3: MINNEAPOLIS PUBLIC SCHOOL
A4: 2 | B4: 1 | C4: HILL CITY | D4: =E4-A4 -> 0 | E4: 2 | F4: 1 | G4: HILL CITY PUBLIC SCHOOL D
A5: 4 | B5: 1 | C5: MCGREGOR | D5: =E5-A5 -> 0 | E5: 4 | F5: 1 | G5: MCGREGOR PUBLIC SCHOOL DI
A6: 6 | B6: 3 | C6: SOUTH ST. PAUL | D6: =E6-A6 -> 0 | E6: 6 | F6: 3 | G6: SOUTH ST. PAUL PUBLIC SCH
A7: 11 | B7: 1 | C7: ANOKA-HENNEPIN | D7: =E7-A7 -> 0 | E7: 11 | F7: 1 | G7: ANOKA-HENNEPIN PUBLIC SCH
A8: 12 | B8: 1 | C8: CENTENNIAL | D8: =E8-A8 -> 0 | E8: 12 | F8: 1 | G8: CENTENNIAL PUBLIC SCHOOL
A9: 13 | B9: 1 | C9: COLUMBIA HEIGHTS | D9: =E9-A9 -> 0 | E9: 13 | F9: 1 | G9: COLUMBIA HEIGHTS PUBLIC S
A10: 14 | B10: 1 | C10: FRIDLEY | D10: =E10-A10 -> 0 | E10: 14 | F10: 1 | G10: FRIDLEY PUBLIC SCHOOL DIS
A11: 15 | B11: 1 | C11: ST. FRANCIS | D11: =E11-A11 -> 0 | E11: 15 | F11: 1 | G11: ST. FRANCIS PUBLIC SCHOOL
A12: 16 | B12: 1 | C12: SPRING LAKE PARK | D12: =E12-A12 -> 0 | E12: 16 | F12: 1 | G12: SPRING LAKE PARK PUBLIC S
A13: 22 | B13: 1 | C13: DETROIT LAKES | D13: =E13-A13 -> 0 | E13: 22 | F13: 1 | G13: DETROIT LAKES PUBLIC SCHO
... A333: 2908 | B333: 1 | C333: BRANDON-EVANSVILLE | D333: =E333-A333 -> 0 | E333: 2908 | F333: 1 | G333: BRANDON-EVANSVILLE PUBLIC S
A334: line left blank intentionally
A335: 207 | B335: 1 | C335: BRANDON
A336: 208 | B336: 1 | C336: EVANSVILLE
A337: line left blank intentionally
A338: 513 | B338: 1 | C338: BREWSTER
A339: 516 | B339: 1 | C339: ROUND LAKE
A340: line left blank intentionally
A341: 627 | B341: 1 | C341: OKLEE
A342: 628 | B342: 1 | C342: PLUMMER
A343: line left blank intentionally
A344: 611 | B344: 1 | C344: CYRUS
A345: 769 | B345: 1 | C345: MORRIS
A346: End of worksheet
