Workbook

Sheet GRA-FINANC.
A2: CRONOGRAMA FINANCIERO REFORMULADO - ORDEN DE CAMBIO No 1
A4: 2.0439169e+08
B6: Cert Nº1 | C6: Cert Nº2 | D6: Cert Nº3 | E6: Cert Nº4 | F6: Cert Nº5 | G6: Cert Nº6 | H6: Cert Nº7 | I6: Cert Nº9 | J6: Cert Nº10 | K6: Cert Nº11 | L6: Cert Nº12 | M6: Cert Nº13 | N6: Cert Nº14 | O6: Cert Nº15 | P6: Cert Nº16 | Q6: Cert Nº17 | R6: Cert Nº18 | S6: Cert Nº19 | T6: Cert Nº20 | U6: Cert Nº21 | V6: Cert Nº22 | W6: Cert Nº23 | X6: Cert Nº24 | Y6: Cert Nº25 | Z6: Cert Nº26 | AA6: Cert Nº27 | AB6: Cert Nº28 | AC6: Cert Nº29 | AD6: Cert Nº30 | AE6: Cert Nº31 | AF6: Cert Nº32 | AG6: Cert Nº33 | AH6: Cert-Año1 | AI6: Cert-Año2 | AJ6: Cert-Año3 | AK6: TOTAL (BS.)
B7: 40544 | C7: 40575 | D7: 40603 | E7: 40634 | F7: 40664 | G7: 40695 | H7: 40725 | I7: 40756 | J7: 40787 | K7: 40817 | L7: 40848 | M7: 40878 | N7: 40909 | O7: 40940 | P7: 40969 | Q7: 41000 | R7: 41030 | S7: 41061 | T7: 41091 | U7: 41122 | V7: 41153 | W7: 41183 | X7: 41214 | Y7: 41244 | Z7: 41275 | AA7: 41306 | AB7: 41334 | AC7: 41365 | AD7: 41395 | AE7: 41426 | AF7: 41456 | AG7: 41487
A8: PROGRAMADO
A9: PROGRAMADO MENSUAL (BS.): | C9: =+C14 -> 77666.36 | D9: =+D14 -> 67986.93 | E9: =+E14 -> 81681.27 | F9: =+F14 -> 85754.32 | G9: =+G14 -> 782177.68 | H9: =+H14 -> 2839990.9 | I9: =+I14 -> 3867198.6 | J9: =+J14 -> 3154343.5 | ... Q9: =+Q14 -> 1867946.4 | R9: =CRONO!U489-'GRA-FINANC.'!Q10 -> 5612044 | S9: =+CRONO!W489 -> 3801368.9 | T9: =+CRONO!X489 -> 6224643.6 | U9: =+CRONO!Y489 -> 8526568.3 | V9: =+CRONO!Z489 -> 10676787 | W9: =+CRONO!AA489 -> 12837837 | X9: =+CRONO!AB489 -> 12721622 | Y9: =+CRONO!AC489 -> 11582344 | Z9: =+CRONO!AD489 -> 11865789 | ... AG9: =+CRONO!AK489 -> 4291994.5 | AH9: =+CRONO!AM489 -> 2739007.9 | AI9: =+CRONO!AN489 -> 2739007.9 | AJ9: =+CRONO!AO489 -> 2739007.9 | AK9: =SUM(C9:AJ9) -> 2.2419464e+08
A10: DESEMBOLSO ACUMULADO (BS.): | B10: =B9 -> 0 | C10: =B10+C9 -> 77666.36 | D10: =C10+D9 -> 145653.29 | E10: =D10+E9 -> 227334.56 | F10: =E10+F9 -> 313088.88 | G10: =F10+G9 -> 1095266.6 | H10: =G10+H9 -> 3935257.5 | I10: =H10+I9 -> 7802456 | J10: =I10+J9 -> 10956800 | ... AJ10: =AI10+AJ9 -> 2.2419464e+08
A13: EJECUTADO | B13: Cert Nº1 | C13: Cert Nº2 | D13: Cert Nº3 | E13: Cert Nº4 | F13: Cert Nº5 | G13: Cert Nº6 | H13: Cert Nº7 | I13: Cert Nº9 | J13: Cert Nº10 | K13: Cert Nº11 | L13: Cert Nº12 | M13: Cert Nº13 | N13: Cert Nº14 | O13: Cert Nº15 | P13: Cert Nº16 | Q13: Cert Nº17 | R13: Cert Nº18 | S13: Cert Nº19 | T13: Cert Nº20 | U13: Cert Nº21 | V13: Cert Nº22 | W13: Cert Nº23 | X13: Cert Nº24 | Y13: Cert Nº25 | Z13: Cert Nº26 | AA13: Cert Nº27 | AB13: Cert Nº28 | AC13: Cert Nº29 | AD13: Cert Nº30 | AE13: Cert Nº31 | AF13: Cert Nº32 | AG13: Cert Nº33 | AH13: Cert-Año1 | AI13: Cert-Año2 | AJ13: Cert-Año3
A14: EJECUTADO MENSUAL (BS.): | B14: =+B9 -> 0 | C14: 77666.36 | D14: 67986.93 | E14: 81681.27 | F14: 85754.32 | G14: 782177.68 | H14: 2839990.9 | I14: 3867198.6 | J14: 3154343.5 | K14: 1251047.5 | L14: 1217725.5 | M14: 129468.78 | N14: 935930.37 | O14: 720487.39 | P14: 1257187.2 | Q14: 1867946.4 | R14: 2072454.3 | AK14: =SUM(C14:AJ14) -> 20409047
A15: EJECUTADO ACUMULADO (BS.): | B15: =B14 -> 0 | C15: =B15+C14 -> 77666.36 | D15: =C15+D14 -> 145653.29 | E15: =D15+E14 -> 227334.56 | F15: =E15+F14 -> 313088.88 | G15: =F15+G14 -> 1095266.6 | H15: =G15+H14 -> 3935257.5 | I15: =H15+I14 -> 7802456 | J15: =I15+J14 -> 10956800 | ... R15: =Q15+R14 -> 20409047
C96: NOTA: | D96: Certificado Nº 8 Corresponde al Anticipo Adicional del Cemento Asfaltico
B106: 40878338 | L106: 2.2419464e+08
L107: =L15 -> 13425573
L108: =L107/L106 -> 0.0599
L109: =L14/L106 -> 0.0054

Sheet CRONO
D1: CRONOGRAMA FISICO - FINANCIERO
C2: CRONOGRAMA REFORMULADO DE OBRA - ORDEN DE CAMBIO No 1
C3: PROYECTO PAVIMENTACION ZUDAÑEZ - PADILLA: PROGRESIVAS: (INICIO:99+000; FIN:167+668)
C6: N° | D6: Descripcion de Rubros/Items | E6: Unidad | F6: Precio Unitario ( Bs ) | G6: CANTIDADES Y MONTOS | N6: Notas | O6: Mes 10 | P6: Mes 12 | Q6: Mes 12 | R6: Mes 13 | S6: Mes 14 | T6: Mes 15 | U6: Mes 17 | W6: Mes 18 | X6: Mes 19 | Y6: Mes 20 | Z6: Mes 21 | AA6: Mes 22 | AB6: Mes 23 | AC6: Mes 24 | AD6: Mes 25 | AE6: Mes 26 | AF6: Mes 27 | AG6: Mes 28 | AH6: Mes 29 | AI6: Mes 30 | AJ6: Mes 31 | AK6: Mes 32 | AM6: Año 1 | AN6: Año 2 | AO6: Año 3
G7: Contrato Original | H7: Contrato Modific.#3 | I7: Ejecutada | J7: Adicional | K7: TOTAL | L7: A Ejecutar | O7: 40817 | P7: 40848 | Q7: 40878 | R7: 40909 | S7: 40940 | T7: 40969 | U7: 41030 | W7: =U7+31 -> 41061 | X7: =W7+31 -> 41092 | Y7: =X7+31 -> 41123 | Z7: =Y7+31 -> 41154 | AA7: =Z7+31 -> 41185 | AB7: =AA7+31 -> 41216 | AC7: =AB7+31 -> 41247 | AD7: =AC7+31 -> 41278 | AE7: =AD7+31 -> 41309 | ... AK7: =AJ7+31 -> 41495
AV8: Por Ejecutar
C9: 1 | D9: MOVIMIENTO DE TIERRAS. | E9: =+E12+E16+E20+E24+E28+E32+E36+E40+E44+E48+E52 -> 0
A10: P | C10: 1 | D10: 1.1 Desbroce, Desbosque, Destronque y Limpieza | E10: [ ha ] | F10: 3467.88 | G10: 378 | H10: 391 | I10: 0.75 | K10: =H10+J10 -> 391 | L10: =+H10-I10+J10 -> 390.25 | N10: Cantidad | U10: =+I10 -> 0.75 | W10: =+W11*$G$10 -> 0 | X10: =+X11*$G$10 -> 0 | Y10: =+Y11*$K$10 -> 39.1 | Z10: =+Z11*$K$10 -> 39.1 | AA10: =+AA11*$K$10 -> 39.1 | AB10: =+AB11*$K$10 -> 39.1 | AC10: =+AC11*$G$10 -> 0 | AD10: =+AD11*$G$10 -> 0 | AE10: =+AE11*$G$10 -> 0 | AF10: =+AF11*$K$10 -> 58.65 | AG10: =+AG11*$K$10 -> 58.65 | AH10: =+AH11*$K$10 -> 58.65 | AI10: =+AI11*$K$10+0.03 -> 57.9 | AJ10: =+AJ11*$K$10 -> 0 | AQ10: =SUM(O10:AO10) -> 391 | AR10: =+K10-AQ10 -> 0 | AT10: =+F10*K10 -> 1355941.1 | AV10: =SUM(W10:AO10) -> 390.25 | AW10: =+L10-AV10 -> 0 | BA10: =SUM(O10:U10) -> 0.75
A11: P | N11: Porcentaje | U11: =+U10/G10 -> 0.002 | Y11: 0.1 | Z11: 0.1 | AA11: 0.1 | AB11: 0.1 | AF11: 0.15 | AG11: 0.15 | AH11: 0.15 | AI11: 0.148 | AQ11: =SUM(O11:AO11) -> 1 | BA11: =SUM(O11:U11) -> 0
A12: C | BA12: =SUM(O12:U12) -> 0
A13: 1 | G13: =ROUND(G10*$F10,2) -> 1310858.6 | H13: =ROUND(H10*$F10,2) -> 1355941.1 | I13: =ROUND(I10*$F10,2) -> 2600.91 | J13: =J10*$F10 -> 0 | K13: =ROUND(K10*$F10,2) -> 1355941.1 | L13: =ROUND(L10*$F10,2) -> 1353340.2 | N13: Monto | U13: =U10*$F10 -> 2600.91 | W13: =W10*$F10 -> 0 | X13: =X10*$F10 -> 0 | Y13: =Y10*$F10 -> 135594.11 | Z13: =Z10*$F10 -> 135594.11 | AA13: =AA10*$F10 -> 135594.11 | AB13: =AB10*$F10 -> 135594.11 | AC13: =AC10*$F10 -> 0 | AD13: =AD10*$F10 -> 0 | ... AJ13: =AJ10*$F10 -> 0 | AQ13: =SUM(O13:AO13) -> 1355941.1 | AR13: =+K13-AQ13 -> 0
C14: 2 | D14: 1.2 Excavación No Clasificada Distancia < 300 m | E14: [ m³ ] | F14: 17.35 | G14: 757437 | H14: 840374.49 | I14: 325132.65 | K14: =H14+J14 -> 840374.49 | L14: =+H14-I14+J14 -> 515241.84 | N14: Cantidad | U14: =+I14 -> 325132.65 | W14: 25000 | X14: 25000 | Y14: 25000 | Z14: 25000 | AA14: 25000 | AB14: 25000 | AC14: 25000 | AD14: 50000 | AE14: 50000 | AF14: 60000 | AG14: 75000 | AH14: 60000 | AI14: 45241.84 | AQ14: =SUM(O14:AO14) -> 840374.49 | AR14: =+K14-AQ14 -> 0 | AT14: =+F14*K14 -> 14580497 | AV14: =SUM(W14:AO14) -> 515241.84 | AW14: =+L14-AV14 -> 0 | BA14: =SUM(O14:U14) -> 325132.65
A15: P | N15: Porcentaje | U15: =+U14/K14 -> 0.3869 | W15: =+W14/$K14 -> 0.0297 | X15: =+X14/$K14 -> 0.0297 | Y15: =+Y14/$K14 -> 0.0297 | Z15: =+Z14/$K14 -> 0.0297 | AA15: =+AA14/$K14 -> 0.0297 | AB15: =+AB14/$K14 -> 0.0297 | AC15: =+AC14/$K14 -> 0.0297 | AD15: =+AD14/$K14 -> 0.0595 | ... AK15: =+AK14/$K14 -> 0 | AQ15: =SUM(O15:AO15) -> 0.9996
A16: C | BA16: =SUM(O16:U16) -> 0
A17: 1 | G17: =ROUND(G14*$F14,2) -> 13141532 | H17: =ROUND(H14*$F14,2) -> 14580497 | I17: =ROUND(I14*$F14,2) -> 5641051.5 | J17: =J14*$F14 -> 0 | K17: =ROUND(K14*$F14,2) -> 14580497 | L17: =ROUND(L14*$F14,2) -> 8939445.9 | N17: Monto | U17: =U14*$F14+0.01 -> 5641051.5 | W17: =W14*$F14 -> 433750 | X17: =X14*$F14 -> 433750 | Y17: =Y14*$F14 -> 433750 | Z17: =Z14*$F14 -> 433750 | AA17: =AA14*$F14 -> 433750 | AB17: =AB14*$F14 -> 433750 | AC17: =AC14*$F14 -> 433750 | AD17: =AD14*$F14 -> 867500 | ... AH17: =AH14*$F14 -> 1041000 | AI17: =AI14*$F14-0.01 -> 784945.91 | AJ17: =AJ14*$F14 -> 0 | AK17: =AK14*$F14 -> 0 | AQ17: =SUM(O17:AO17) -> 14580497 | AR17: =+K17-AQ17 -> 0
C18: 3 | D18: 1.3 Excavación en Fango Distancia < 300 m | E18: [ m³ ] | F18: 26.97 | G18: 22724 | H18: 22724 | I18: 0 | J18: -13395.106 | K18: =H18+J18 -> 9328.8936 | L18: =+H18-I18+J18 -> 9328.89 | N18: Cantidad | U18: =+I18 -> 0 | AE18: =+AE19*$K18 -> 1865.78 | AF18: =+AF19*$K18 -> 1865.78 | AG18: =+AG19*$K18 -> 1865.78 | AH18: =+AH19*$K18 -> 1865.78 | AI18: 1865.77 | AJ18: =+AJ19*$K18 -> 0 | AQ18: =SUM(O18:AO18) -> 9328.89 | AR18: =+K18-AQ18 -> 0 | AT18: =+F18*K18 -> 251600.26 | AV18: =SUM(W18:AO18) -> 9328.89 | AW18: =+L18-AV18 -> 0 | BA18: =SUM(O18:U18) -> 0
A19: P | N19: Porcentaje | U19: =+U18/K18 -> 0 | AE19: 0.2 | AF19: 0.2 | AG19: 0.2 | AH19: 0.2 | AI19: 0.2 | AQ19: =SUM(O19:AO19) -> 1 | BA19: =SUM(O19:U19) -> 0
A20: C | BA20: =SUM(O20:U20) -> 0
A21: 1 | G21: =ROUND(G18*$F18,2) -> 612866.28 | H21: =ROUND(H18*$F18,2) -> 612866.28 | I21: =ROUND(I18*$F18,2) -> 0 | J21: =J18*$F18 -> -361266.02 | K21: =ROUND(K18*$F18,4) -> 251600.26 | L21: =ROUND(L18*$F18,2) -> 251600.16 | N21: Monto | U21: =U18*$F18 -> 0 | AE21: =AE18*$F18 -> 50320.087 | AF21: =AF18*$F18 -> 50320.087 | AG21: =AG18*$F18 -> 50320.087 | AH21: =AH18*$F18 -> 50320.087 | AI21: =AI18*$F18+0.09 -> 50319.907 | AJ21: =AJ18*$F18 -> 0 | AQ21: =SUM(O21:AO21) -> 251600.26 | AR21: =+K21-AQ21 -> 0 | BA21: =SUM(O21:U21) -> 0
C22: 4 | D22: 1.4 Terraplén con Material de Préstamo | E22: [ m³ ] | F22: 21.91 | G22: 201199 | H22: 203324.05 | I22: 106111.67 | K22: =H22+J22 -> 203324.05 | L22: =+H22-I22+J22 -> 97212.38 | N22: Cantidad | U22: =+I22 -> 106111.67 | W22: 1500 | X22: 1500 | Y22: 1500 | Z22: 1500 | AA22: 5000 | AB22: 5000 | AC22: 5000 | AD22: 10000 | AE22: 10000 | AF22: 10000 | AG22: 15000 | AH22: 15000 | AI22: 16212.38 | AQ22: =SUM(O22:AO22) -> 203324.05 | AR22: =+K22-AQ22 -> 0 | AT22: =+F22*K22 -> 4454829.9 | AV22: =SUM(W22:AO22) -> 97212.38 | AW22: =+L22-AV22 -> 0 | BA22: =SUM(O22:U22) -> 106111.67
A23: P | N23: Porcentaje | U23: =+U22/K22 -> 0.5219 | W23: =+W22/$K22 -> 0.0074 | X23: =+X22/$K22 -> 0.0074 | Y23: =+Y22/$K22 -> 0.0074 | Z23: =+Z22/$K22 -> 0.0074 | AA23: =+AA22/$K22 -> 0.0246 | AB23: =+AB22/$K22 -> 0.0246 | AC23: =+AC22/$K22 -> 0.0246 | AD23: =+AD22/$K22 -> 0.0492 | ... AK23: =+AK22/$K22 -> 0 | AQ23: =SUM(O23:AO23) -> 1.0002
A24: C | BA24: =SUM(O24:U24) -> 0
A25: 1 | G25: =ROUND(G22*$F22,2) -> 4408270.1 | H25: =ROUND(H22*$F22,2) -> 4454829.9 | I25: =ROUND(I22*$F22,2) -> 2324906.7 | J25: =J22*$F22 -> 0 | K25: =ROUND(K22*$F22,2) -> 4454829.9 | L25: =ROUND(L22*$F22,2) -> 2129923.2 | N25: Monto | U25: =U22*$F22 -> 2324906.7 | W25: =W22*$F22 -> 32865 | X25: =X22*$F22 -> 32865 | Y25: =Y22*$F22 -> 32865 | Z25: =Z22*$F22 -> 32865 | AA25: =AA22*$F22 -> 109550 | AB25: =AB22*$F22 -> 109550 | AC25: =AC22*$F22 -> 109550 | AD25: =AD22*$F22 -> 219100 | ... AK25: =AK22*$F22 -> 0 | AQ25: =SUM(O25:AO25) -> 4454829.9 | AR25: =+K25-AQ25 -> 0
C26: 5 | D26: 1.5 Terraplén con Material de Corte | E26: [ m³ ] | F26: 11.19 | G26: 299800 | H26: 323252 | I26: 47007.92 | K26: =H26+J26 -> 323252 | L26: =+H26-I26+J26 -> 276244.08 | N26: Cantidad | U26: =+I26 -> 47007.92 | W26: 15000 | X26: 20000 | Y26: 20000 | Z26: 25000 | AA26: 15000 | AB26: 25000 | AC26: 25000 | AD26: 25000 | AE26: 35000 | AF26: 35000 | AG26: 36244.08 | AQ26: =SUM(O26:AO26) -> 323252 | AR26: =+K26-AQ26 -> 0 | AT26: =+F26*K26 -> 3617189.9 | AV26: =SUM(W26:AO26) -> 276244.08 | AW26: =+L26-AV26 -> 0 | BA26: =SUM(O26:U26) -> 47007.92
A27: P | N27: Porcentaje | U27: =+U26/K26 -> 0.1454 | W27: =+W26/$K26 -> 0.0464 | X27: =+X26/$K26 -> 0.0619 | Y27: =+Y26/$K26 -> 0.0619 | Z27: =+Z26/$K26 -> 0.0773 | AA27: =+AA26/$K26 -> 0.0464 | AB27: =+AB26/$K26 -> 0.0773 | AC27: =+AC26/$K26 -> 0.0773 | AD27: =+AD26/$K26 -> 0.0773 | ... AI27: =+AI26/$K26 -> 0 | AQ27: =SUM(O27:AO27) -> 0.9999
A28: C | BA28: =SUM(O28:U28) -> 0
A29: 1 | G29: =ROUND(G26*$F26,2) -> 3354762 | H29: =ROUND(H26*$F26,2) -> 3617189.9 | I29: =ROUND(I26*$F26,2) -> 526018.62 | J29: =J26*$F26 -> 0 | K29: =ROUND(K26*$F26,2) -> 3617189.9 | L29: =ROUND(L26*$F26,2) -> 3091171.3 | N29: Monto | U29: =U26*$F26+0.02 -> 526018.64 | W29: =W26*$F26 -> 167850 | X29: =X26*$F26 -> 223800 | Y29: =Y26*$F26 -> 223800 | Z29: =Z26*$F26 -> 279750 | AA29: =AA26*$F26 -> 167850 | AB29: =AB26*$F26 -> 279750 | AC29: =AC26*$F26 -> 279750 | AD29: =AD26*$F26 -> 279750 | ... AF29: =AF26*$F26 -> 391650 | AG29: =AG26*$F26-0.02 -> 405571.24 | AH29: =AH26*$F26 -> 0 | AI29: =AI26*$F26 -> 0 | AQ29: =SUM(O29:AO29) -> 3617189.9 | AR29: =+K29-AQ29 -> 0
C30: 6 | D30: 1.6 Relleno Compactado en Áreas de Depósito | E30: [ m³ ] | F30: 4.05 | G30: 409401 | H30: 471920.81 | I30: 165193.72 | K30: =H30+J30 -> 471920.81 | L30: =+H30-I30+J30 -> 306727.09 | N30: Cantidad | U30: =+I30 -> 165193.72 | W30: 10000 | X30: 15000 | Y30: 15000 | Z30: 15000 | AA30: 15000 | AB30: 15000 | AC30: 15000 | AD30: 35000 | AE30: 35000 | AF30: 35000 | AG30: 35000 | AH30: 35000 | AI30: 31727.09 | AQ30: =SUM(O30:AO30) -> 471920.81 | AR30: =+K30-AQ30 -> 0 | AT30: =+F30*K30 -> 1911279.3 | AV30: =SUM(W30:AO30) -> 306727.09 | AW30: =+L30-AV30 -> 0 | BA30: =SUM(O30:U30) -> 165193.72
A31: P | N31: Porcentaje | U31: =+U30/K30 -> 0.35 | W31: =+W30/$K30 -> 0.0212 | X31: =+X30/$K30 -> 0.0318 | Y31: =+Y30/$K30 -> 0.0318 | Z31: =+Z30/$K30 -> 0.0318 | AA31: =+AA30/$K30 -> 0.0318 | AB31: =+AB30/$K30 -> 0.0318 | AC31: =+AC30/$K30 -> 0.0318 | AD31: =+AD30/$K30 -> 0.0742 | ... AK31: =+AK30/$K30 -> 0 | AQ31: =SUM(O31:AO31) -> 1.0002
A32: C | BA32: =SUM(O32:U32) -> 0
A33: 1 | G33: =ROUND(G30*$F30,2) -> 1658074.1 | H33: =ROUND(H30*$F30,2) -> 1911279.3 | I33: =ROUND(I30*$F30,2) -> 669034.57 | J33: =J30*$F30 -> 0 | K33: =ROUND(K30*$F30,2) -> 1911279.3 | L33: =ROUND(L30*$F30,2) -> 1242244.7 | N33: Monto | U33: =U30*$F30 -> 669034.57 | W33: =W30*$F30 -> 40500 | X33: =X30*$F30 -> 60750 | Y33: =Y30*$F30 -> 60750 | Z33: =Z30*$F30 -> 60750 | AA33: =AA30*$F30 -> 60750 | AB33: =AB30*$F30 -> 60750 | AC33: =AC30*$F30 -> 60750 | AD33: =AD30*$F30 -> 141750 | ... AK33: =AK30*$F30 -> 0 | AQ33: =SUM(O33:AO33) -> 1911279.3 | AR33: =+K33-AQ33 -> 0
C34: 7 | D34: 1.7 Remoción de Derrumbes | E34: [ m³ ] | F34: 19.71 | G34: 75744 | H34: 75744 | I34: 9913.26 | K34: =H34+J34 -> 75744 | L34: =+H34-I34+J34 -> 65830.74 | N34: Cantidad | U34: =+I34 -> 9913.26 | AB34: 5000 | AC34: 10000 | AD34: 10000 | AE34: 15000 | AF34: 15000 | AG34: 6000 | AH34: 4830.74 | AQ34: =SUM(O34:AO34) -> 75744 | AR34: =+K34-AQ34 -> 0 | AT34: =+F34*K34 -> 1492914.2 | AV34: =SUM(W34:AO34) -> 65830.74 | AW34: =+L34-AV34 -> 0 | BA34: =SUM(O34:U34) -> 9913.26
A35: P | N35: Porcentaje | U35: =+U34/K34 -> 0.1309 | AB35: =+AB34/$K34 -> 0.066 | AC35: =+AC34/$K34 -> 0.132 | AD35: =+AD34/$K34 -> 0.132 | AE35: =+AE34/$K34 -> 0.198 | AF35: =+AF34/$K34 -> 0.198 | AG35: =+AG34/$K34 -> 0.0792 | AH35: =+AH34/$K34 -> 0.0638 | AK35: =+AK34/$K34 -> 0 | AQ35: =SUM(O35:AO35) -> 0.9999
A36: C | BA36: =SUM(O36:U36) -> 0
A37: 1 | G37: =ROUND(G34*$F34,2) -> 1492914.2 | H37: =ROUND(H34*$F34,2) -> 1492914.2 | I37: =ROUND(I34*$F34,2) -> 195390.35 | J37: =J34*$F34 -> 0 | K37: =ROUND(K34*$F34,2) -> 1492914.2 | L37: =ROUND(L34*$F34,2) -> 1297523.9 | N37: Monto | U37: =U34*$F34 -> 195390.35 | AB37: =AB34*$F34 -> 98550 | AC37: =AC34*$F34 -> 197100 | AD37: =AD34*$F34 -> 197100 | AE37: =AE34*$F34 -> 295650 | AF37: =AF34*$F34 -> 295650 | AG37: =AG34*$F34 -> 118260 | AH37: =AH34*$F34 -> 95213.89 | AK37: =AK34*$F34 -> 0 | AQ37: =SUM(O37:AO37) -> 1492914.2 | AR37: =+K37-AQ37 -> 0
C38: 8 | D38: 1.8 Sobreacarreo para Distancias > 300 m | E38: [ m³-km ] | F38: 2.48 | G38: 152240 | H38: 157482.36 | I38: 9504.28 | K38: =H38+J38 -> 157482.36 | L38: =+H38-I38+J38 -> 147978.08 | N38: Cantidad | U38: =+I38 -> 9504.28 | W38: 1500 | X38: 1500 | Y38: 1500 | Z38: 1500 | AA38: 1500 | AB38: 1500 | AC38: 1500 | AD38: 23500 | AE38: 23500 | AF38: 23500 | AG38: 23500 | AH38: 23500 | AI38: 19978.08 | AQ38: =SUM(O38:AO38) -> 157482.36 | AR38: =+K38-AQ38 -> 0 | AT38: =+F38*K38 -> 390556.25 | AV38: =SUM(W38:AO38) -> 147978.08 | AW38: =+L38-AV38 -> 0 | BA38: =SUM(O38:U38) -> 9504.28
A39: P | N39: Porcentaje | U39: =+U38/K38 -> 0.0604 | W39: =+W38/$K38 -> 0.0095 | X39: =+X38/$K38 -> 0.0095 | Y39: =+Y38/$K38 -> 0.0095 | Z39: =+Z38/$K38 -> 0.0095 | AA39: =+AA38/$K38 -> 0.0095 | AB39: =+AB38/$K38 -> 0.0095 | AC39: =+AC38/$K38 -> 0.0095 | AD39: =+AD38/$K38 -> 0.1492 | ... AI39: =+AI38/$K38 -> 0.1269 | AQ39: =SUM(O39:AO39) -> 0.9998
A40: C | BA40: =SUM(O40:U40) -> 0
A41: 1 | G41: =ROUND(G38*$F38,2) -> 377555.2 | H41: =ROUND(H38*$F38,2) -> 390556.25 | I41: =ROUND(I38*$F38,2) -> 23570.61 | J41: =J38*$F38 -> 0 | K41: =ROUND(K38*$F38,2) -> 390556.25 | L41: =ROUND(L38*$F38,2) -> 366985.64 | N41: Monto | U41: =U38*$F38 -> 23570.61 | W41: =W38*$F38 -> 3720 | X41: =X38*$F38 -> 3720 | Y41: =Y38*$F38 -> 3720 | Z41: =Z38*$F38 -> 3720 | AA41: =AA38*$F38 -> 3720 | AB41: =AB38*$F38 -> 3720 | AC41: =AC38*$F38 -> 3720 | AD41: =AD38*$F38 -> 58280 | ... AI41: =AI38*$F38 -> 49545.64 | AQ41: =SUM(O41:AO41) -> 390556.25 | AR41: =+K41-AQ41 -> 0
C42: 9 | D42: 1.9 Transporte de Material de Acopios | E42: [ m³-km ] | F42: 2.22 | G42: 1647249 | H42: 1650035.6 | I42: 172514.55 | K42: =H42+J42 -> 1650035.6 | L42: =+H42-I42+J42 -> 1477521 | N42: Cantidad | U42: =+I42 -> 172514.55 | W42: 3500 | X42: 4500 | Y42: 4500 | Z42: 5000 | AA42: =+AA22*5 -> 25000 | AB42: =+AB22*5 -> 25000 | AC42: =+AC22*5 -> 25000 | AD42: 250000 | AE42: 250000 | AF42: 250000 | AG42: 266000 | AH42: 369021.03 | AJ42: =+AJ22*10 -> 0 | AK42: =+AK22*10 -> 0 | AQ42: =SUM(O42:AO42) -> 1650035.6 | AR42: =+K42-AQ42 -> 0 | AT42: =+F42*K42 -> 3663079 | AV42: =SUM(W42:AO42) -> 1477521 | AW42: =+L42-AV42 -> 0 | BA42: =SUM(O42:U42) -> 172514.55
A43: P | N43: Porcentaje | U43: =+U42/K42 -> 0.1046 | W43: =+W42/$K42 -> 0.0021 | X43: =+X42/$K42 -> 0.0027 | Y43: =+Y42/$K42 -> 0.0027 | Z43: =+Z42/$K42 -> 0.003 | AA43: =+AA42/$K42 -> 0.0152 | AB43: =+AB42/$K42 -> 0.0152 | AC43: =+AC42/$K42 -> 0.0152 | AD43: =+AD42/$K42 -> 0.1515 | ... AK43: =+AK42/$K42 -> 0 | AQ43: =SUM(O43:AO43) -> 1
A44: C | BA44: =SUM(O44:U44) -> 0
A45: 1 | G45: =ROUND(G42*$F42,2) -> 3656892.8 | H45: =ROUND(H42*$F42,2) -> 3663079 | I45: =ROUND(I42*$F42,2) -> 382982.3 | J45: =J42*$F42 -> 0 | K45: =ROUND(K42*$F42,2) -> 3663079 | L45: =ROUND(L42*$F42,2) -> 3280096.7 | N45: Monto | U45: =U42*$F42 -> 382982.3 | W45: =W42*$F42 -> 7770 | X45: =X42*$F42 -> 9990 | Y45: =Y42*$F42 -> 9990 | Z45: =Z42*$F42 -> 11100 | AA45: =AA42*$F42 -> 55500 | AB45: =AB42*$F42 -> 55500 | AC45: =AC42*$F42 -> 55500 | AD45: =AD42*$F42 -> 555000 | ... AK45: =AK42*$F42 -> 0 | AQ45: =SUM(O45:AO45) -> 3663079 | AR45: =+K45-AQ45 -> 0
C46: 10 | D46: 1.10 Transporte de Material de Buzones | E46: [ m³-km ] | F46: 1.97 | G46: 1072633 | H46: 1147878.4 | I46: 157798.82 | K46: =H46+J46 -> 1147878.4 | L46: =+H46-I46+J46 -> 990079.53 | N46: Cantidad | U46: =+I46 -> 157798.82 | W46: 2500 | X46: 2500 | Y46: 7500 | Z46: 7500 | AA46: 7500 | AB46: 10000 | AC46: 10000 | AD46: 200000 | AE46: 200000 | AF46: 200000 | AG46: 200000 | AH46: 142579.53 | AJ46: =+AJ30*5*50% -> 0 | AK46: =+AK30*5*50% -> 0 | AQ46: =SUM(O46:AO46) -> 1147878.4 | AR46: =+K46-AQ46 -> 0 | AT46: =+F46*K46 -> 2261320.4 | AV46: =SUM(W46:AO46) -> 990079.53 | AW46: =+L46-AV46 -> 0 | BA46: =SUM(O46:U46) -> 157798.82
A47: P | N47: Porcentaje | U47: =+U46/K46 -> 0.1375 | W47: =+W46/$K46 -> 0.0022 | X47: =+X46/$K46 -> 0.0022 | Y47: =+Y46/$K46 -> 0.0065 | Z47: =+Z46/$K46 -> 0.0065 | AA47: =+AA46/$K46 -> 0.0065 | AB47: =+AB46/$K46 -> 0.0087 | AC47: =+AC46/$K46 -> 0.0087 | AD47: =+AD46/$K46 -> 0.1742 | ... AK47: =+AK46/$K46 -> 0 | AQ47: =SUM(O47:AO47) -> 0.9998
A48: C | BA48: =SUM(O48:U48) -> 0
A49: 1 | G49: =ROUND(G46*$F46,2) -> 2113087 | H49: =ROUND(H46*$F46,2) -> 2261320.4 | I49: =ROUND(I46*$F46,2) -> 310863.68 | J49: =J46*$F46 -> 0 | K49: =ROUND(K46*$F46,2)+0.12 -> 2261320.5 | L49: =ROUND(L46*$F46,2) -> 1950456.7 | N49: Monto | U49: =U46*$F46-0.01 -> 310863.67 | W49: =W46*$F46 -> 4925 | X49: =X46*$F46 -> 4925 | Y49: =Y46*$F46 -> 14775 | Z49: =Z46*$F46 -> 14775 | AA49: =AA46*$F46 -> 14775 | AB49: =AB46*$F46 -> 19700 | AC49: =AC46*$F46 -> 19700 | AD49: =AD46*$F46 -> 394000 | ... AG49: =AG46*$F46 -> 394000 | AH49: =AH46*$F46+0.13 -> 280881.8 | AI49: =AI46*$F46 -> 0 | AJ49: =AJ46*$F46 -> 0 | AK49: =AK46*$F46 -> 0 | AQ49: =SUM(O49:AO49) -> 2261320.5 | AR49: =+K49-AQ49 -> 0
C50: 11 | D50: 1.11 Pedraplén para Estabilización de Plataforma | E50: [ m³ ] | F50: 40.81 | G50: 22724 | H50: 22724 | I50: 554.52 | K50: =H50+J50 -> 22724 | L50: =+H50-I50+J50 -> 22169.48 | N50: Cantidad | U50: =+I50 -> 554.52 | Z50: =+Z34*5*50% -> 0 | AA50: 3500 | AB50: 3500 | AC50: 3500 | AE50: 4000 | AF50: 4000 | AG50: 3669.48 | AQ50: =SUM(O50:AO50) -> 22724 | AR50: =+K50-AQ50 -> 0 | AT50: =+F50*K50 -> 927366.44 | AV50: =SUM(W50:AO50) -> 22169.48 | AW50: =+L50-AV50 -> 0 | BA50: =SUM(O50:U50) -> 554.52
A51: P | N51: Porcentaje | U51: =+U50/K50 -> 0.0244 | Z51: =+Z50/$K50 -> 0 | AA51: =+AA50/$K50 -> 0.154 | AB51: =+AB50/$K50 -> 0.154 | AC51: =+AC50/$K50 -> 0.154 | AE51: =+AE50/$K50 -> 0.176 | AF51: =+AF50/$K50 -> 0.176 | AG51: =+AG50/$K50 -> 0.1615 | AQ51: =SUM(O51:AO51) -> 0.9999
A52: C | BA52: =SUM(O52:U52) -> 0
A53: 1 | G53: =ROUND(G50*$F50,2) -> 927366.44 | H53: =ROUND(H50*$F50,2) -> 927366.44 | I53: =ROUND(I50*$F50,2) -> 22629.96 | J53: =J50*$F50 -> 0 | K53: =ROUND(K50*$F50,2) -> 927366.44 | L53: =ROUND(L50*$F50,2) -> 904736.48 | N53: Monto | U53: =U50*$F50 -> 22629.96 | Z53: =Z50*$F50 -> 0 | AA53: =AA50*$F50 -> 142835 | AB53: =AB50*$F50 -> 142835 | AC53: =AC50*$F50 -> 142835 | AE53: =AE50*$F50 -> 163240 | AF53: =AF50*$F50 -> 163240 | AG53: =AG50*$F50 -> 149751.48 | AQ53: =SUM(O53:AO53) -> 927366.44 | AR53: =+K53-AQ53 -> 0
C55: TOTAL MOVIMIENTO DE SUELOS | J55: % | K55: =SUM(U55:AO55) -> 1.0002 | N55: % | U55: =+U56/$K$56 -> 0.2893 | W55: =+W56/$K$56 -> 0.0198 | X55: =+X56/$K$56 -> 0.0221 | Y55: =+Y56/$K$56 -> 0.0262 | Z55: =+Z56/$K$56 -> 0.0279 | AA55: =+AA56/$K$56 -> 0.0322 | AB55: =+AB56/$K$56 -> 0.0384 | AC55: =+AC56/$K$56 -> 0.0373 | AD55: =+AD56/$K$56 -> 0.0777 | ... AO55: =+AO56/$K$56 -> 0
J56: Bs. | K56: =+K13+K17+K21+K25+K29+K33+K37+K41+K45+K49+K53 -> 34906574 | N56: Bs. | U56: =+U13+U17+U21+U25+U29+U33+U37+U41+U45+U49+U53 -> 10099049 | W56: =+W13+W17+W21+W25+W29+W33+W37+W41+W45+W49+W53 -> 691380 | X56: =+X13+X17+X21+X25+X29+X33+X37+X41+X45+X49+X53 -> 769800 | Y56: =+Y13+Y17+Y21+Y25+Y29+Y33+Y37+Y41+Y45+Y49+Y53 -> 915244.11 | Z56: =+Z13+Z17+Z21+Z25+Z29+Z33+Z37+Z41+Z45+Z49+Z53 -> 972304.11 | AA56: =+AA13+AA17+AA21+AA25+AA29+AA33+AA37+AA41+AA45+AA49+AA53 -> 1124324.1 | AB56: =+AB13+AB17+AB21+AB25+AB29+AB33+AB37+AB41+AB45+AB49+AB53 -> 1339699.1 | AC56: =+AC13+AC17+AC21+AC25+AC29+AC33+AC37+AC41+AC45+AC49+AC53 -> 1302655 | AD56: =+AD13+AD17+AD21+AD25+AD29+AD33+AD37+AD41+AD45+AD49+AD53 -> 2712480 | ... AO56: =+AO13+AO17+AO21+AO25+AO29+AO33+AO37+AO41+AO45+AO49+AO53 -> 0
BA57: =SUM(O57:U57) -> 0
C58: 2 | D58: PAVIMENTACION. | AT58: =SUM(AT10:AT53) -> 34906574 | AU58: 35267840 | AV58: =+AU58-AT58 -> 361266.02 | BA58: =SUM(O58:U58) -> 0
A59: P | C59: 12 | D59: 2.1 Sub Base Material Granular | E59: [ m³ ] | F59: 50.89 | G59: 312513 | H59: 327829.31 | I59: 89350.93 | J59: -10000.39 | K59: =H59+J59 -> 317828.92 | L59: =+H59-I59+J59 -> 228477.99 | N59: Cantidad | U59: =+I59 -> 89350.93 | W59: 15000 | X59: 20000 | Y59: 20000 | Z59: 20000 | AA59: 20000 | AB59: 15000 | AC59: 10000 | AD59: 10000 | AE59: 10000 | AF59: 25000 | AG59: 25000 | AH59: 25000 | AI59: 13477.99 | AQ59: =SUM(O59:AO59) -> 317828.92 | AR59: =+K59-AQ59 -> 0 | AT59: =+F59*K59 -> 16174314 | AV59: =SUM(W59:AO59) -> 228477.99 | AW59: =+L59-AV59 -> 0 | BA59: =SUM(O59:U59) -> 89350.93
A60: P | N60: Porcentaje | U60: =+U59/K59 -> 0.2811 | W60: =+W59/$K59 -> 0.0472 | X60: =+X59/$K59 -> 0.0629 | Y60: =+Y59/$K59 -> 0.0629 | Z60: =+Z59/$K59 -> 0.0629 | AA60: =+AA59/$K59 -> 0.0629 | AB60: =+AB59/$K59 -> 0.0472 | AC60: =+AC59/$K59 -> 0.0315 | AD60: =+AD59/$K59 -> 0.0315 | ... AK60: =+AK59/$K59 -> 0 | AQ60: =SUM(O60:AO60) -> 1.0001
A61: C
A62: 1 | G62: =ROUND(G59*$F59,2) -> 15903787 | H62: =ROUND(H59*$F59,2) -> 16683234 | I62: =ROUND(I59*$F59,2) -> 4547068.8 | J62: =J59*$F59 -> -508919.85 | K62: =ROUND(K59*$F59,2) -> 16174314 | L62: =ROUND(L59*$F59,2) -> 11627245 | N62: Monto | U62: =U59*$F59+0.01 -> 4547068.8 | W62: =W59*$F59 -> 763350 | X62: =X59*$F59 -> 1017800 | Y62: =Y59*$F59 -> 1017800 | Z62: =Z59*$F59 -> 1017800 | AA62: =AA59*$F59 -> 1017800 | AB62: =AB59*$F59 -> 763350 | AC62: =AC59*$F59 -> 508900 | AD62: =AD59*$F59 -> 508900 | ... AH62: =AH59*$F59 -> 1272250 | AI62: =AI59*$F59-0.01 -> 685894.9 | AJ62: =AJ59*$F59 -> 0 | AK62: =AK59*$F59 -> 0 | AQ62: =SUM(O62:AO62) -> 16174314 | AR62: =+K62-AQ62 -> 0
C63: 13 | D63: 2.2 Base Material Granular | E63: [ m³ ] | F63: 102.45 | G63: 176706 | H63: 184750.72 | J63: -19450.81 | K63: =H63+J63 -> 165299.91 | L63: =+H63-I63+J63 -> 165299.91 | N63: Cantidad | U63: =+I63 -> 0 | W63: 2500 | X63: 10000 | Y63: 15000 | Z63: 15000 | AA63: 15000 | AB63: 15000 | AC63: 10000 | AD63: 10000 | AE63: 10000 | AF63: 15000 | AG63: 15000 | AH63: 15000 | AI63: 17799.91 | AQ63: =SUM(O63:AO63) -> 165299.91 | AR63: =+K63-AQ63 -> 0 | AT63: =+F63*K63 -> 16934976 | AV63: =SUM(W63:AO63) -> 165299.91 | AW63: =+L63-AV63 -> 0 | BA63: =SUM(O63:U63) -> 0
A64: P | N64: Porcentaje | U64: =+U63/K63 -> 0 | W64: =+W63/$K63 -> 0.0151 | X64: =+X63/$K63 -> 0.0605 | Y64: =+Y63/$K63 -> 0.0907 | Z64: =+Z63/$K63 -> 0.0907 | AA64: =+AA63/$K63 -> 0.0907 | AB64: =+AB63/$K63 -> 0.0907 | AC64: =+AC63/$K63 -> 0.0605 | AD64: =+AD63/$K63 -> 0.0605 | ... AK64: =+AK63/$K63 -> 0 | AQ64: =SUM(O64:AO64) -> 0.9997 | BA64: =SUM(O64:U64) -> 0
A65: C | BA65: =SUM(O65:U65) -> 0
A66: 1 | G66: =ROUND(G63*$F63,2) -> 18103530 | H66: =ROUND(H63*$F63,2) -> 18927711 | I66: =ROUND(I63*$F63,2) -> 0 | J66: =J63*$F63 -> -1992735.5 | K66: =ROUND(K63*$F63,2) -> 16934976 | L66: =ROUND(L63*$F63,2) -> 16934976 | N66: Monto | U66: =U63*$F63 -> 0 | W66: =W63*$F63 -> 256125 | X66: =X63*$F63 -> 1024500 | Y66: =Y63*$F63 -> 1536750 | Z66: =Z63*$F63 -> 1536750 | AA66: =AA63*$F63 -> 1536750 | AB66: =AB63*$F63 -> 1536750 | AC66: =AC63*$F63 -> 1024500 | AD66: =AD63*$F63 -> 1024500 | ... AK66: =AK63*$F63 -> 0 | AQ66: =SUM(O66:AO66) -> 16934976 | AR66: =+K66-AQ66 -> 0 | BA66: =SUM(O66:U66) -> 0
C67: 14 | D67: 2.3 Imprimación - Ejecución | E67: [ m² ] | F67: 0.83 | G67: 785875 | H67: 827538.15 | K67: =H67+J67 -> 827538.15 | L67: =+H67-I67+J67 -> 827538.15 | N67: Cantidad | U67: =+I67 -> 0 | Y67: 11700 | Z67: 28000 | AA67: 70000 | AB67: 50000 | AC67: 40000 | AD67: 40000 | AE67: 40000 | AF67: 125000 | AG67: 125000 | AH67: 125000 | AI67: 125000 | AJ67: 47838.15 | AQ67: =SUM(O67:AO67) -> 827538.15 | AR67: =+K67-AQ67 -> 0 | AT67: =+F67*K67 -> 686856.66 | AV67: =SUM(W67:AO67) -> 827538.15 | AW67: =+L67-AV67 -> 0 | BA67: =SUM(O67:U67) -> 0
A68: P | N68: Porcentaje | U68: =+U67/K67 -> 0 | X68: =+X67/$K67 -> 0 | Y68: =+Y67/$K67 -> 0.0141 | Z68: =+Z67/$K67 -> 0.0338 | AA68: =+AA67/$K67 -> 0.0846 | AB68: =+AB67/$K67 -> 0.0604 | AC68: =+AC67/$K67 -> 0.0483 | AD68: =+AD67/$K67 -> 0.0483 | AE68: =+AE67/$K67 -> 0.0483 | ... AK68: =+AK67/$K67 -> 0 | AQ68: =SUM(O68:AO68) -> 1 | BA68: =SUM(O68:U68) -> 0
A69: C | E69: [m²] | BA69: =SUM(O69:U69) -> 0
A70: 1 | G70: =ROUND(G67*$F67,2) -> 652276.25 | H70: =ROUND(H67*$F67,2) -> 686856.66 | I70: =ROUND(I67*$F67,2) -> 0 | J70: =J67*$F67 -> 0 | K70: =ROUND(K67*$F67,2) -> 686856.66 | L70: =ROUND(L67*$F67,2) -> 686856.66 | N70: Monto | U70: =U67*$F67 -> 0 | X70: =X67*$F67 -> 0 | Y70: =Y67*$F67 -> 9711 | Z70: =Z67*$F67 -> 23240 | AA70: =AA67*$F67 -> 58100 | AB70: =AB67*$F67 -> 41500 | AC70: =AC67*$F67 -> 33200 | AD70: =AD67*$F67 -> 33200 | AE70: =AE67*$F67 -> 33200 | ... AK70: =AK67*$F67 -> 0 | AQ70: =SUM(O70:AO70) -> 686856.66 | AR70: =+K70-AQ70 -> 0 | BA70: =SUM(O70:U70) -> 0
C71: 15 | D71: 2.4 Riego de Liga - Ejecución | E71: [ m² ] | F71: 0.99 | G71: 157175 | H71: 165508.39 | K71: =H71+J71 -> 165508.39 | L71: =+H71-I71+J71 -> 165508.39 | N71: Cantidad | U71: =+I71 -> 0 | Z71: 2700 | AA71: 6000 | AB71: 15000 | AC71: 10000 | AD71: 10000 | AE71: 10000 | AF71: 21000 | AG71: 25000 | AH71: 25000 | AI71: 25000 | AJ71: 15808.39 | AQ71: =SUM(O71:AO71) -> 165508.39 | AR71: =+K71-AQ71 -> 0 | AT71: =+F71*K71 -> 163853.31 | AV71: =SUM(W71:AO71) -> 165508.39 | AW71: =+L71-AV71 -> 0 | BA71: =SUM(O71:U71) -> 0
A72: P | N72: Porcentaje | U72: =+U71/K71 -> 0 | X72: =+X71/$K71 -> 0 | Y72: =+Y71/$K71 -> 0 | Z72: =+Z71/$K71 -> 0.0163 | AA72: =+AA71/$K71 -> 0.0363 | AB72: =+AB71/$K71 -> 0.0906 | AC72: =+AC71/$K71 -> 0.0604 | AD72: =+AD71/$K71 -> 0.0604 | AE72: =+AE71/$K71 -> 0.0604 | ... AK72: =+AK71/$K71 -> 0 | AQ72: =SUM(O72:AO72) -> 0.9998 | BA72: =SUM(O72:U72) -> 0
A73: C | E73: [m²] | BA73: =SUM(O73:U73) -> 0
A74: 1 | G74: =ROUND(G71*$F71,2) -> 155603.25 | H74: =ROUND(H71*$F71,2) -> 163853.31 | I74: =ROUND(I71*$F71,2) -> 0 | J74: =J71*$F71 -> 0 | K74: =ROUND(K71*$F71,2) -> 163853.31 | L74: =ROUND(L71*$F71,2) -> 163853.31 | N74: Monto | U74: =U71*$F71 -> 0 | X74: =X71*$F71 -> 0 | Y74: =Y71*$F71 -> 0 | Z74: =Z71*$F71 -> 2673 | AA74: =AA71*$F71 -> 5940 | AB74: =AB71*$F71 -> 14850 | AC74: =AC71*$F71 -> 9900 | AD74: =AD71*$F71 -> 9900 | AE74: =AE71*$F71 -> 9900 | ... AK74: =AK71*$F71 -> 0 | AQ74: =SUM(O74:AO74) -> 163853.31 | AR74: =+K74-AQ74 -> 0 | BA74: =SUM(O74:U74) -> 0
C75: 16 | D75: 2.5 Tratamiento Superficial Doble - Ejecución | E75: [ m² ] | F75: 7.89 | G75: 785875 | H75: 827267.38 | K75: =H75+J75 -> 827267.38 | L75: =+H75-I75+J75 -> 827267.38 | N75: Cantidad | U75: =+I75 -> 0 | Z75: 2700 | AA75: 30000 | AB75: 40000 | AC75: 30000 | AD75: 30000 | AE75: 100000 | AF75: 120000 | AG75: 120000 | AH75: 120000 | AI75: 120000 | AJ75: 114567.38 | AQ75: =SUM(O75:AO75) -> 827267.38 | AR75: =+K75-AQ75 -> 0 | AT75: =+F75*K75 -> 6527139.6 | AV75: =SUM(W75:AO75) -> 827267.38 | AW75: =+L75-AV75 -> 0 | BA75: =SUM(O75:U75) -> 0
A76: P | N76: Porcentaje | U76: =+U75/K75 -> 0 | Y76: =+Y75/$K75 -> 0 | Z76: =+Z75/$K75 -> 0.0033 | AA76: =+AA75/$K75 -> 0.0363 | AB76: =+AB75/$K75 -> 0.0484 | AC76: =+AC75/$K75 -> 0.0363 | AD76: =+AD75/$K75 -> 0.0363 | AE76: =+AE75/$K75 -> 0.1209 | AF76: =+AF75/$K75 -> 0.1451 | ... AK76: =+AK75/$K75 -> 0 | AQ76: =SUM(O76:AO76) -> 1.0004 | BA76: =SUM(O76:U76) -> 0
A77: C | E77: [m²] | BA77: =SUM(O77:U77) -> 0
A78: 1 | G78: =ROUND(G75*$F75,2) -> 6200553.8 | H78: =ROUND(H75*$F75,2) -> 6527139.6 | I78: =ROUND(I75*$F75,2) -> 0 | J78: =J75*$F75 -> 0 | K78: =ROUND(K75*$F75,2) -> 6527139.6 | L78: =ROUND(L75*$F75,2) -> 6527139.6 | N78: Monto | U78: =U75*$F75 -> 0 | Y78: =Y75*$F75 -> 0 | Z78: =Z75*$F75 -> 21303 | AA78: =AA75*$F75 -> 236700 | AB78: =AB75*$F75 -> 315600 | AC78: =AC75*$F75 -> 236700 | AD78: =AD75*$F75 -> 236700 | AE78: =AE75*$F75 -> 789000 | AF78: =AF75*$F75 -> 946800 | ... AK78: =AK75*$F75 -> 0 | AQ78: =SUM(O78:AO78) -> 6527139.6 | AR78: =+K78-AQ78 -> 0 | BA78: =SUM(O78:U78) -> 0
C79: 17 | D79: 2.6 Suministro de Asfalto Diluido para la Imprimación | E79: [ lt ] | F79: 7.51 | G79: 943050 | H79: 991642.34 | K79: =H79+J79 -> 991642.34 | L79: =+H79-I79+J79 -> 991642.34 | N79: Cantidad | U79: =+I79 -> 0 | Y79: =ROUND(Y67*1.2,2) -> 14040 | Z79: =ROUND(Z67*1.2,2) -> 33600 | AA79: =ROUND(AA67*1.2,2) -> 84000 | AB79: =ROUND(AB67*1.2,2) -> 60000 | AC79: =ROUND(AC67*1.2,2) -> 48000 | AD79: =ROUND(AD67*1.2,2) -> 48000 | AE79: =ROUND(AE67*1.2,2) -> 48000 | AF79: =ROUND(AF67*1.2,2) -> 150000 | ... AI79: =ROUND(AI67*1.2,2) -> 150000 | AJ79: 56002.34 | AK79: =+AK67*1.2 -> 0 | AQ79: =SUM(O79:AO79) -> 991642.34 | AR79: =+K79-AQ79 -> 0 | AT79: =+F79*K79 -> 7447234 | AV79: =SUM(W79:AO79) -> 991642.34 | AW79: =+L79-AV79 -> 0 | BA79: =SUM(O79:U79) -> 0
A80: P | N80: Porcentaje | U80: =+U79/K79 -> 0 | X80: =+X79/$K79 -> 0 | Y80: =+Y79/$K79 -> 0.0142 | Z80: =+Z79/$K79 -> 0.0339 | AA80: =+AA79/$K79 -> 0.0847 | AB80: =+AB79/$K79 -> 0.0605 | AC80: =+AC79/$K79 -> 0.0484 | AD80: =+AD79/$K79 -> 0.0484 | AE80: =+AE79/$K79 -> 0.0484 | ... AK80: =+AK79/$K79 -> 0 | AQ80: =SUM(O80:AO80) -> 1.0002 | BA80: =SUM(O80:U80) -> 0
A81: C | BA81: =SUM(O81:U81) -> 0
A82: 1 | G82: =ROUND(G79*$F79,2) -> 7082305.5 | H82: =ROUND(H79*$F79,2) -> 7447234 | I82: =ROUND(I79*$F79,2) -> 0 | J82: =J79*$F79 -> 0 | K82: =ROUND(K79*$F79,2) -> 7447234 | L82: =ROUND(L79*$F79,2) -> 7447234 | N82: Monto | U82: =U79*$F79 -> 0 | X82: =X79*$F79 -> 0 | Y82: =Y79*$F79 -> 105440.4 | Z82: =Z79*$F79 -> 252336 | AA82: =AA79*$F79 -> 630840 | AB82: =AB79*$F79 -> 450600 | AC82: =AC79*$F79 -> 360480 | AD82: =AD79*$F79 -> 360480 | AE82: =AE79*$F79 -> 360480 | ... AK82: =AK79*$F79 -> 0 | AQ82: =SUM(O82:AO82) -> 7447234 | AR82: =+K82-AQ82 -> 0 | BA82: =SUM(O82:U82) -> 0
C83: 18 | D83: 2.7 Suministro de Asfalto Diluido/Emulsión para el Riego de Liga | E83: [ lt ] | F83: 8.4 | G83: 94305 | H83: 99164.18 | K83: =H83+J83 -> 99164.18 | L83: =+H83-I83+J83 -> 99164.18 | N83: Cantidad | U83: =+I83 -> 0 | X83: =ROUND(0.6*X71,2) -> 0 | Y83: =ROUND(0.6*Y71,2) -> 0 | Z83: =ROUND(0.6*Z71,2) -> 1620 | AA83: =ROUND(0.6*AA71,2) -> 3600 | AB83: =ROUND(0.6*AB71,2) -> 9000 | AC83: =ROUND(0.6*AC71,2) -> 6000 | AD83: =ROUND(0.6*AD71,2) -> 6000 | AE83: =ROUND(0.6*AE71,2) -> 6000 | ... AI83: =ROUND(0.6*AI71,2) -> 15000 | AJ83: =ROUND(0.6*AJ71,2)-140.85 -> 9344.18 | AK83: =ROUND(0.6*AK71,2) -> 0 | AQ83: =SUM(O83:AO83) -> 99164.18 | AR83: =+K83-AQ83 -> 0 | AT83: =+F83*K83 -> 832979.11 | AV83: =SUM(W83:AO83) -> 99164.18 | AW83: =+L83-AV83 -> 0 | BA83: =SUM(O83:U83) -> 0
A84: P | N84: Porcentaje | U84: =+U83/K83 -> 0 | X84: =+X83/$K83 -> 0 | Y84: =+Y83/$K83 -> 0 | Z84: =+Z83/$K83 -> 0.0163 | AA84: =+AA83/$K83 -> 0.0363 | AB84: =+AB83/$K83 -> 0.0908 | AC84: =+AC83/$K83 -> 0.0605 | AD84: =+AD83/$K83 -> 0.0605 | AE84: =+AE83/$K83 -> 0.0605 | ... AK84: =+AK83/$K83 -> 0 | AQ84: =SUM(O84:AO84) -> 1.0001 | BA84: =SUM(O84:U84) -> 0
A85: C | BA85: =SUM(O85:U85) -> 0
A86: 1 | G86: =ROUND(G83*$F83,2) -> 792162 | H86: =ROUND(H83*$F83,2) -> 832979.11 | I86: =ROUND(I83*$F83,2) -> 0 | J86: =J83*$F83 -> 0 | K86: =ROUND(K83*$F83,2) -> 832979.11 | L86: =ROUND(L83*$F83,2) -> 832979.11 | N86: Monto | U86: =U83*$F83 -> 0 | X86: =X83*$F83 -> 0 | Y86: =Y83*$F83 -> 0 | Z86: =Z83*$F83 -> 13608 | AA86: =AA83*$F83 -> 30240 | AB86: =AB83*$F83 -> 75600 | AC86: =AC83*$F83 -> 50400 | AD86: =AD83*$F83 -> 50400 | AE86: =AE83*$F83 -> 50400 | ... AK86: =AK83*$F83 -> 0 | AQ86: =SUM(O86:AO86) -> 832979.11 | AR86: =+K86-AQ86 -> 0 | BA86: =SUM(O86:U86) -> 0
C87: 19 | D87: 2.9 Suministro de Asfalto Diluido/Emulsión para Tratamiento Superficial | E87: [ lt ] | F87: 8.4 | G87: 2750563 | H87: 2891388.1 | K87: =H87+J87 -> 2891388.1 | L87: =+H87-I87+J87 -> 2891388.1 | N87: Cantidad | U87: =+I87 -> 0 | X87: =ROUND(X75*3.5,2) -> 0 | Y87: =ROUND(Y75*3.5,2) -> 0 | Z87: =ROUND(Z75*3.5,2) -> 9450 | AA87: =ROUND(AA75*3.5,2) -> 105000 | AB87: =ROUND(AB75*3.5,2) -> 140000 | AC87: =ROUND(AC75*3.5,2) -> 105000 | AD87: =ROUND(AD75*3.5,2) -> 105000 | AE87: =ROUND(AE75*3.5,2) -> 350000 | ... AI87: =ROUND(AI75*3.5,2) -> 420000 | AJ87: =ROUND(AJ75*3.5,2)-4047.77 -> 396938.06 | AK87: =ROUND(AK75*3.5,2) -> 0 | AQ87: =SUM(O87:AO87) -> 2891388.1 | AR87: =+K87-AQ87 -> 0 | AT87: =+F87*K87 -> 24287660 | AV87: =SUM(W87:AO87) -> 2891388.1 | AW87: =+L87-AV87 -> 0 | BA87: =SUM(O87:U87) -> 0
A88: P | N88: Porcentaje | U88: =+U87/K87 -> 0 | X88: =+X87/$K87 -> 0 | Y88: =+Y87/$K87 -> 0 | Z88: =+Z87/$K87 -> 0.0033 | AA88: =+AA87/$K87 -> 0.0363 | AB88: =+AB87/$K87 -> 0.0484 | AC88: =+AC87/$K87 -> 0.0363 | AD88: =+AD87/$K87 -> 0.0363 | AE88: =+AE87/$K87 -> 0.121 | ... AK88: =+AK87/$K87 -> 0 | AQ88: =SUM(O88:AO88) -> 1.0001 | BA88: =SUM(O88:U88) -> 0
A89: C | BA89: =SUM(O89:U89) -> 0
A90: 1 | G90: =ROUND(G87*$F87,2) -> 23104729 | H90: =ROUND(H87*$F87,2) -> 24287660 | I90: =ROUND(I87*$F87,2) -> 0 | J90: =J87*$F87 -> 0 | K90: =ROUND(K87*$F87,2) -> 24287660 | L90: =ROUND(L87*$F87,2) -> 24287660 | N90: Monto | U90: =U87*$F87 -> 0 | X90: =X87*$F87 -> 0 | Y90: =Y87*$F87 -> 0 | Z90: =Z87*$F87 -> 79380 | AA90: =AA87*$F87 -> 882000 | AB90: =AB87*$F87 -> 1176000 | AC90: =AC87*$F87 -> 882000 | AD90: =AD87*$F87 -> 882000 | AE90: =AE87*$F87 -> 2940000 | ... AK90: =AK87*$F87 -> 0 | AQ90: =SUM(O90:AO90) -> 24287660 | AR90: =+K90-AQ90 -> 0 | BA90: =SUM(O90:U90) -> 0
C91: 20 | D91: 2.10 Transporte de Material Granular | E91: [ m³-km ] | F91: 2.22 | G91: 5374508 | H91: 5797215.1 | I91: 714755.13 | K91: =H91+J91 -> 5797215.1 | L91: =+H91-I91+J91 -> 5082459.9 | N91: Cantidad | U91: =+I91 -> 714755.13 | W91: =ROUND(+W59*8.5*100%+W63*17.5*100%+W75*0.02*17.5*100%,2) -> 171250 | X91: =ROUND(+X59*8.5*100%+X63*17.5*100%+X75*0.02*17.5*100%,2) -> 345000 | Y91: =ROUND(+Y59*8.5*100%+Y63*17.5*100%+Y75*0.02*17.5*100%,2) -> 432500 | Z91: =ROUND(+Z59*8.5*100%+Z63*17.5*100%+Z75*0.02*17.5*100%,2) -> 433445 | AA91: =ROUND(+AA59*8.5*100%+AA63*17.5*100%+AA75*0.02*17.5*100%,2) -> 443000 | AB91: =ROUND(+AB59*8.5*100%+AB63*17.5*100%+AB75*0.02*17.5*100%,2) -> 404000 | AC91: =ROUND(+AC59*8.5*100%+AC63*17.5*100%+AC75*0.02*17.5*100%,2) -> 270500 | AD91: =ROUND(+AD59*8.5*100%+AD63*17.5*100%+AD75*0.02*17.5*100%,2) -> 270500 | ... AH91: =ROUND(+AH59*8.5*100%+AH63*17.5*100%+AH75*0.02*17.5*100%,2) -> 517000 | AI91: =ROUND(+AI59*8.5*100%+AI63*17.5*100%+AI75*0.02*17.5*100%,2)-41894.99 -> 426166.35 | AJ91: =ROUND(+AJ59*8.5*100%+AJ63*17.5*100%+AJ75*0.02*17.5*100%,2) -> 40098.58 | AK91: =ROUND(+AK59*8.5*100%+AK63*17.5*100%+AK75*0.02*17.5*100%,2) -> 0 | AQ91: =SUM(O91:AO91) -> 5797215.1 | AR91: =+K91-AQ91 -> 0 | AT91: =+F91*K91 -> 12869817 | AV91: =SUM(W91:AO91) -> 5082459.9 | AW91: =+L91-AV91 -> 0 | BA91: =SUM(O91:U91) -> 714755.13
A92: P | N92: Porcentaje | U92: =+U91/K91 -> 0.1233 | W92: =+W91/$K$91 -> 0.0295 | X92: =+X91/$K$91 -> 0.0595 | Y92: =+Y91/$K$91 -> 0.0746 | Z92: =+Z91/$K$91 -> 0.0748 | AA92: =+AA91/$K$91 -> 0.0764 | AB92: =+AB91/$K$91 -> 0.0697 | AC92: =+AC91/$K$91 -> 0.0467 | AD92: =+AD91/$K$91 -> 0.0467 | ... AK92: =+AK91/$K$91 -> 0 | AQ92: =SUM(O92:AO92) -> 1.0001
A93: C
A94: 1 | G94: =ROUND(G91*$F91,2) -> 11931408 | H94: =ROUND(H91*$F91,2) -> 12869817 | I94: =ROUND(I91*$F91,2) -> 1586756.4 | J94: =J91*$F91 -> 0 | K94: =ROUND(K91*$F91,2) -> 12869817 | L94: =ROUND(L91*$F91,2) -> 11283061 | N94: Monto | U94: =U91*$F91 -> 1586756.4 | W94: =W91*$F91 -> 380175 | X94: =X91*$F91 -> 765900 | Y94: =Y91*$F91 -> 960150 | Z94: =Z91*$F91 -> 962247.9 | AA94: =AA91*$F91 -> 983460 | AB94: =AB91*$F91 -> 896880 | AC94: =AC91*$F91 -> 600510 | AD94: =AD91*$F91 -> 600510 | ... AI94: =AI91*$F91 -> 946089.3 | AJ94: =AJ91*$F91-0.01 -> 89018.84 | AK94: =AK91*$F91 -> 0 | AQ94: =SUM(O94:AO94) -> 12869817 | AR94: =+K94-AQ94 -> 0
C96: TOTAL PAVIMENTACION | J96: % | K96: =SUM(U96:AO96) -> 0.9998 | N96: % | U96: =+U97/$K$97 -> 0.0714 | W96: =+W97/$K$97 -> 0.0163 | X96: =+X97/$K$97 -> 0.0327 | Y96: =+Y97/$K$97 -> 0.0422 | Z96: =+Z97/$K$97 -> 0.0455 | AA96: =+AA97/$K$97 -> 0.0626 | AB96: =+AB97/$K$97 -> 0.0613 | AC96: =+AC97/$K$97 -> 0.0431 | AD96: =+AD97/$K$97 -> 0.0431 | ... AK96: =+AK97/$K$97 -> 0
J97: Bs. | K97: =+K62+K66+K70+K74+K78+K82+K86+K90+K94 -> 85924829 | N97: Bs. | U97: =+U62+U66+U70+U74+U78+U82+U86+U90+U94 -> 6133825.2 | W97: =+W62+W66+W70+W74+W78+W82+W86+W90+W94 -> 1399650 | X97: =+X62+X66+X70+X74+X78+X82+X86+X90+X94 -> 2808200 | Y97: =+Y62+Y66+Y70+Y74+Y78+Y82+Y86+Y90+Y94 -> 3629851.4 | Z97: =+Z62+Z66+Z70+Z74+Z78+Z82+Z86+Z90+Z94 -> 3909337.9 | AA97: =+AA62+AA66+AA70+AA74+AA78+AA82+AA86+AA90+AA94 -> 5381830 | AB97: =+AB62+AB66+AB70+AB74+AB78+AB82+AB86+AB90+AB94 -> 5271130 | AC97: =+AC62+AC66+AC70+AC74+AC78+AC82+AC86+AC90+AC94 -> 3706590 | AD97: =+AD62+AD66+AD70+AD74+AD78+AD82+AD86+AD90+AD94 -> 3706590 | ... AK97: =+AK62+AK66+AK70+AK74+AK78+AK82+AK86+AK90+AK94 -> 0
BA98: =SUM(O98:U98) -> 0
C99: 3 | D99: OBRAS DE DRENAJE | AT99: =SUM(AT59:AT94) -> 85924829 | AU99: 88426485 | AV99: =+AU99-AT99 -> 2501655.3 | AW99: ok | BA99: =SUM(O99:U99) -> 0
C100: 21 | D100: 3.1 Zanjas de Coronamiento Revestidas, Incluye Excavación | E100: [ m ] | F100: 124.34 | G100: 11394.6 | H100: 12699.09 | K100: =H100+J100 -> 12699.09 | L100: =+H100-I100+J100 -> 12699.09 | N100: Cantidad | U100: =+I100 -> 0 | X100: 300 | Y100: 700 | Z100: 1000 | AA100: 1000 | AB100: 1500 | AC100: 1000 | AD100: 1000 | AE100: 1000 | AF100: 1000 | AG100: 1000 | AH100: 1000 | AI100: 1000 | AJ100: 1199.09 | AQ100: =SUM(O100:AO100) -> 12699.09 | AR100: =+K100-AQ100 -> 0 | AT100: =+F100*K100 -> 1579004.9 | AV100: =SUM(W100:AO100) -> 12699.09 | AW100: =+L100-AV100 -> 0 | BA100: =SUM(O100:U100) -> 0
A101: P | N101: Porcentaje | U101: =+U100/$K100 -> 0 | X101: =+X100/$K100 -> 0.0236 | Y101: =+Y100/$K100 -> 0.0551 | Z101: =+Z100/$K100 -> 0.0787 | AA101: =+AA100/$K100 -> 0.0787 | AB101: =+AB100/$K100 -> 0.1181 | AC101: =+AC100/$K100 -> 0.0787 | AD101: =+AD100/$K100 -> 0.0787 | AE101: =+AE100/$K100 -> 0.0787 | ... AK101: =+AK100/$K100 -> 0 | AQ101: =SUM(O101:AO101)-0.0003 -> 0.9992 | BA101: =SUM(O101:U101) -> 0
A102: C | BA102: =SUM(O102:U102) -> 0
A103: 1 | G103: =ROUND(G100*$F100,2) -> 1416804.6 | H103: =ROUND(H100*$F100,2) -> 1579004.9 | I103: =ROUND(I100*$F100,2) -> 0 | J103: =J100*$F100 -> 0 | K103: =ROUND(K100*$F100,2) -> 1579004.9 | L103: =ROUND(L100*$F100,2) -> 1579004.9 | N103: Monto | U103: =U100*$F100 -> 0 | X103: =X100*$F100 -> 37302 | Y103: =Y100*$F100 -> 87038 | Z103: =Z100*$F100 -> 124340 | AA103: =AA100*$F100 -> 124340 | AB103: =AB100*$F100 -> 186510 | AC103: =AC100*$F100 -> 124340 | AD103: =AD100*$F100 -> 124340 | AE103: =AE100*$F100 -> 124340 | ... AK103: =AK100*$F100 -> 0 | AQ103: =SUM(O103:AO103) -> 1579004.9 | AR103: =+K103-AQ103 -> 0 | BA103: =SUM(O103:U103) -> 0
C104: 22 | D104: 3.1A Zanjas de Coronamiento Sin Revestir | E104: [ m ] | F104: 26.33 | G104: 2426.55 | H104: 2426.55 | K104: =H104+J104 -> 2426.55 | L104: =+H104-I104+J104 -> 2426.55 | N104: Cantidad | U104: =+I104 -> 0 | Y104: 180 | Z104: 180 | AA104: 190 | AB104: 190 | AC104: 190 | AD104: 190 | AE104: 190 | AF104: 190 | AG104: 190 | AH104: 190 | AI104: 190 | AJ104: 190 | AK104: 166.55 | AQ104: =SUM(O104:AO104) -> 2426.55 | AR104: =+K104-AQ104 -> 0 | AT104: =+F104*K104 -> 63891.06 | AV104: =SUM(W104:AO104) -> 2426.55 | AW104: =+L104-AV104 -> 0 | BA104: =SUM(O104:U104) -> 0
...
