Workbook

Sheet Cover Sheet
D1: Integration Revenue Budget Worksheet
F2: FY14
A5: Use this worksheet to provide budget data needed to calculate FY14 integration revenue.
A6: Address general questions on Integration Revenue budget submission to the Office of Equity and Innovation,
A7: 651-582-8462. Return the completed worksheet by March 15, 2013 to mde.integration@state.mn.us.
A8: Electronic submission is required. Delete additional pages or those that do not pertain to your budget.
A10: District Name:
A11: District Number:
A12: Superintendent:
A13: Collaborative:
A14: District Contact:
A15: Phone:
A16: E-mail:
A18: Partner Districts:
... A27: Integration Revenue
A28: TOTAL REVENUE | G28: =SUM(G27:G27) -> 0
A30: Integration Revenue Contributed to Collaborative
A32: Notes or Comments:
E35: CERTIFICATION STATEMENT
A36: We certify that the budget information submitted for our school district to the Minnesota Department of Education (MDE)
A37: is an accurate and complete representation of the fiscal year 2014 Integration Revenue budget that was approved by the
A38: school board.
C39: Board Approval Date ____________________
A41: School Board Chair | G41: Date
A43: Superintendent | G43: Date
A46: MDE Approval:____________________ Amount:_______________Date:______________

Sheet Inter-District Goal 1
D1: Integration Revenue Budget Worksheet
F2: FY14
E3: Inter-District Budget: Goal 1
A5: District Number: | C5: ='Cover Sheet'!C11 | E5: District Name: | G5: ='Cover Sheet'!C10
A8: Please insert Inter-district integration goal #1 from your district's desegregation plan:
A17: Line Item Description | C17: UFARS | D17: Code | E17: (Required) | G17: Budgeted Amount | I17: Actual Expenditures
I18: Resubmit this form with
A19: Provide a short description | G19: Provide the total amount | I19: the actual FY14
A20: of the expenditure. | C20: ORG | D20: PROG | E20: FIN | F20: OBJ | G20: budgeted for this line item | I20: expenditures by 12/1/14.
A36: TOTAL | G36: =SUM(G21:G35) -> 0 | I36: =SUM(I21:I35) -> 0
A38: PARTICIPATION INFORMATION | G38: Projected (7/1/13) | I38: Actual
G39: Students | H39: Staff | I39: Students | J39: Staff
A40: Participation from Racially Isolated District (RI):
A41: Participation from Your District (if not the RI):
A42: Participation from Other Member Districts:
A44: Total Program Participation:
A46: Notes or Comments:

Sheet Inter-District Goal 2
D1: Integration Revenue Budget Worksheet
F2: FY14
E3: Inter-District Budget: Goal 2
A5: District Number: | C5: ='Cover Sheet'!C11 | E5: District Name: | G5: ='Cover Sheet'!C10
A8: Please insert Inter-district integration goal #2 from your district's desegregation plan:
A17: Line Item Description | C17: UFARS | D17: Code | E17: (Required) | G17: Budgeted Amount | I17: Actual Expenditures
I18: Resubmit this form with
A19: Provide a short description | G19: Provide the total amount | I19: the actual FY14
A20: of the expenditure | C20: ORG | D20: PROG | E20: FIN | F20: OBJ | G20: budgeted for this line item | I20: expenditures by 12/1/14.
A36: TOTAL | G36: =SUM(G21:G35) -> 0 | I36: =SUM(I21:I35) -> 0
A38: PARTICIPATION INFORMATION | G38: Projected (7/1/13) | I38: Actual
G39: Students | H39: Staff | I39: Students | J39: Staff
A40: Participation from Racially Isolated District (RI):
A41: Participation from Your District (if not the RI):
A42: Participation from Other Member Districts:
A44: Total Program Participation:
A46: Notes or Comments:

Sheet Inter-District Goal 3
D1: Integration Revenue Budget Worksheet
F2: FY14
E3: Inter-District Budget: Goal 3
A5: District Number: | C5: ='Cover Sheet'!C11 | E5: District Name: | G5: ='Cover Sheet'!C10
A8: Please insert Inter-District integration goal #3 from your district's desegregation plan:
A17: Line Item Description | C17: UFARS | D17: Code | E17: (Required) | G17: Budgeted Amount | I17: Actual Expenditures
I18: Resubmit this form with
A19: Provide a short description | G19: Provide the total amount | I19: the actual FY14
A20: of the expenditure. | C20: ORG | D20: PROG | E20: FIN | F20: OBJ | G20: budgeted for this line item | I20: expenditures by 12/1/14.
A36: TOTAL | G36: =SUM(G21:G35) -> 0 | I36: =SUM(I21:I35) -> 0
A38: PARTICIPATION INFORMATION | G38: Projected (7/1/13) | I38: Actual
G39: Students | H39: Staff | I39: Students | J39: Staff
A40: Participation from Racially Isolated District (RI):
A41: Participation from Your District (if not the RI):
A42: Participation from Other Member Districts:
A44: Total Program Participation:
A46: Notes or Comments:

Sheet Inter-District Goal 4
D1: Integration Revenue Budget Worksheet
F2: FY14
E3: Inter-District Budget: Goal 4
A5: District Number: | C5: ='Cover Sheet'!C11 | E5: District Name: | G5: ='Cover Sheet'!C10
A8: Please insert Inter-District integration goal #4 from your district's desegregation plan:
A17: Line Item Description | C17: UFARS | D17: Code | E17: (Required) | G17: Budgeted Amount | I17: Actual Expenditures
I18: Resubmit this form with
A19: Provide a short description | G19: Provide the total amount | I19: the actual FY14
A20: of the expenditure. | C20: ORG | D20: PROG | E20: FIN | F20: OBJ | G20: budgeted for this line item | I20: expenditures by 12/1/14.
A36: TOTAL | G36: =SUM(G21:G35) -> 0 | I36: =SUM(I21:I35) -> 0
A38: PARTICIPATION INFORMATION | G38: Projected (7/1/13) | I38: Actual
G39: Students | H39: Staff | I39: Students | J39: Staff
A40: Participation from Racially Isolated District (RI):
A41: Participation from Your District (if not the RI):
A42: Participation from Other Member Districts:
A44: Total Program Participation:
A46: Notes or Comments:

Sheet AdministrativeIndirect
B1: Integration Revenue Budget Worksheet
B2: FY14
B3: Administrative/Indirect
A5: District Name: | G5: District Number:
A8: Please include on this worksheet all Admin./Indirect proposed expenditures from your FY14 budget. No more than 10 percent of the total budget may be spent on Admin./Indirect costs. See FY14 Budget Guide for details.
A10: Line Item Description | B10: UFARS Code (Required) | F10: Budgeted Amount | G10: Actual Expenditures
A11: Provide a short description of the expenditure | B11: ORG | C11: PROG | D11: FIN | E11: OBJ | F11: Provide the total amount budgeted for this line item | G11: Resubmit this form with the actual FY14 expenditures by 12/01/2014
A12: (example - Administrator salary) | C12: 030 | E12: 110
A13: (example - Administrator benefits) | C13: 030 | E13: 210
A33: TOTAL | F33: =SUM(F12:F32) -> 0 | G33: =SUM(G12:G32) -> 0
A35: Notes or Comments:

Sheet Identifiable School Goal 1
D1: Integration Revenue Budget Worksheet
F2: FY14
D3: Racially Identifiable School(s) Budget: Goal 1
A5: District Number: | C5: ='Cover Sheet'!C11 | E5: District Name: | G5: ='Cover Sheet'!C10
A8: Please insert Identifiable School integration goal from your district's desegregation plan. Include the
A9: Racially Identifiable School(s) addressed by this goal:
A17: Line Item Description | C17: UFARS | D17: Code | E17: (Required) | G17: Budgeted Amount | I17: Actual Expenditures
I18: Resubmit this form with
A19: Provide a short description | G19: Provide the total amount | I19: the actual FY14
A20: of the expenditure. | C20: ORG | D20: PROG | E20: FIN | F20: OBJ | G20: budgeted for this line item | I20: expenditures by 12/1/14.
A36: TOTAL | G36: =SUM(G21:G35) -> 0 | I36: =SUM(I21:I35) -> 0
A38: PARTICIPATION INFORMATION | G38: Projected (7/1/13) | I38: Actual
G39: Students | H39: Staff | I39: Students | J39: Staff
A40: Participation from the Identifiable School(s):
A42: Participation from Other Schools in the District:
A44: Total Program Participation:
A46: Notes or Comments:

Sheet Identifiable School Goal 2
D1: Integration Revenue Budget Worksheet
F2: FY14
D3: Racially Identifiable School(s) Budget: Goal 2
A5: District Number: | C5: ='Cover Sheet'!C11 | E5: District Name: | G5: ='Cover Sheet'!C10
A8: Please insert Identifiable School integration goal from your district's desegregation plan. Include the
A9: Racially Identifiable School(s) addressed by this goal:
A17: Line Item Description | C17: UFARS | D17: Code | E17: (Required) | G17: Budgeted Amount | I17: Actual Expenditures
I18: Resubmit this form with
A19: Provide a short description | G19: Provide the total amount | I19: the actual FY14
A20: of the expenditure. | C20: ORG | D20: PROG | E20: FIN | F20: OBJ | G20: budgeted for this line item | I20: expenditures by 12/1/14.
A36: TOTAL | G36: =SUM(G21:G35) -> 0 | I36: =SUM(I21:I35) -> 0
A38: PARTICIPATION INFORMATION | G38: Projected (7/1/13) | I38: Actual
G39: Students | H39: Staff | I39: Students | J39: Staff
A40: Participation from the Identifiable School(s):
A42: Participation from Other Schools in the District:
A44: Total Program Participation:
A46: Notes or Comments:

Sheet Identifiable School Goal 3
D1: Integration Revenue Budget Worksheet
F2: FY14
D3: Racially Identifiable School(s) Budget: Goal 3
A5: District Number: | C5: ='Cover Sheet'!C11 | E5: District Name: | G5: ='Cover Sheet'!C10
A8: Please insert Identifiable School integration goal from your district's desegregation plan. Include the
A9: Racially Identifiable School(s) addressed by this goal:
A17: Line Item Description | C17: UFARS | D17: Code | E17: (Required) | G17: Budgeted Amount | I17: Actual Expenditures
I18: Resubmit this form with
A19: Provide a short description | G19: Provide the total amount | I19: the actual FY14
A20: of the expenditure. | C20: ORG | D20: PROG | E20: FIN | F20: OBJ | G20: budgeted for this line item | I20: expenditures by 12/1/14.
A36: TOTAL | G36: =SUM(G21:H35,) -> 0 | I36: =SUM(I21:J35,) -> 0
A38: PARTICIPATION INFORMATION | G38: Projected (7/1/13) | I38: Actual
G39: Students | H39: Staff | I39: Students | J39: Staff
A40: Participation from the Identifiable School(s):
A42: Participation from Other Schools in the District:
A44: Total Program Participation:
A46: Notes or Comments:
