Workbook

Sheet Instructions
A1: Service Center Billing Rate Proposal Worksheet
A2: University of Idaho
A3: FY2013
A5: General Instructions
A6: 1) Fill in only the yellow highlighted areas. Do not enter data in non-highlighted areas
A7: 2) Use this worksheet for one budget number only
A9: The following worksheets (see worksheet tabs below) are designed to assist in the calculation of the Service Center Billing Rates. Detailed explanations are included as comments in the worksheets. Please do them in order.
A11: The proposal contains the following worksheets with named tabs:
A13: 1. General - provides an overall description of the services and methodology used in the proposal.
A14: 2. Salaries - provides a calculation of the salaries & benefits included in the proposal.
A15: 3. Operating Costs - lists the non-salary and non-depreciation costs included in the proposal.
A16: 4. Add'l Costs - lists the cost center costs paid for by non-cost center budgets and whether they are included in the proposal.
... A18: 6. Summary - rate calculation page where all costs are summarized for each service and the rates are calculated.

Sheet General
A1: General Information | F1: =Instructions!A3 -> FY2013
A3: Instructions
B4: Fill in the yellow highlighted areas
B5: Service Name (short) - A short name of the service. For example: copier chgs, field tests, etc.
A7: Contact Information
B8: Name
B9: Email
B10: Phone #
B11: Department
A13: Service Center Name
A14: Budget #
A17: Most Recent Complete Fiscal Year Information (Statement of Changes - FWRDSTR)
B18: Most recent fiscal year used | C18: FY2011
B19: Previous fiscal year carryover | C19: 0
B20: Revenue | C20: 0
B21: Expenditures | C21: 0
B22: Transfers | C22: 0
B23: Ending balance | C23: 0
D26: Current Rate | G26: Proposed New Rate
B27: Service Name (short) | C27: Brief description of the service | D27: FY2012 | E27: Unit* | F27: Estmated # of annual units | G27: =Instructions!A3 -> FY2013
A28: 1) | D28: 0 | E28: 0 | F28: 0 | G28: 0
A29: 2) | D29: 0 | E29: 0 | F29: 0 | G29: 0
A31: *Unit is how the rate is charged such as per hour, each, etc.

Sheet Salaries
A1: Service Center Calculations | D1: =General!C14 | K1: =Instructions!A3 -> FY2013
A3: Salaries & Benefits Expenditures
A4: Purpose: To list personnel paid on the service center and allocate personnel costs to each service.
A6: Sheet Instructions
A7: 1) Only fill in the areas shaded in yellow
A8: 2) Fill in the name of the person(s) that is providing the service (board apptd only)
A9: 3) For TH employee costs you may put in a lump sum total for the estimated expenditures.
A10: 4) Fill in that person's PCN
A11: 5) Enter in the employee type | C11: *<<Type is EX for exempt, CL for classified, TH for temporary help, or GA for graduate assistant>>
A12: 6) Enter in the employee's annual salary
A13: 7) Enter in the employee's annual FTE (0.5, 1, 0.75, etc.)
A14: 8) Enter in the FTE % of this employee's time associated with the service and this budget
H16: SERVICE 1 | J16: SERVICE 2
H17: =General!B28 | J17: =General!B29 -> 0
A18: NAME | B18: PCN | C18: TYPE* | D18: ANNUAL SALARY | E18: FTE | F18: FRINGES | G18: TOTAL COST | H18: FTE % | I18: Amount | J18: FTE % | K18: Amount
D19: 0 | E19: 0 | F19: =IF(D19=0,0,IF(C19="ex",E19*Salaries!$B$35+Salaries!$B$34*Salaries!D19,IF(C19="cl",E19*Salaries!$B$35+Salaries!$B$34*D19,IF(C19="GA",Salaries!$B$37*D19,IF(C19="TH",Salaries!$B$36*D19,"Need TYPE"))))) -> 0 | G19: =F19+D19 -> 0 | H19: 0 | I19: =H19*G19 -> 0 | J19: 0 | K19: =J19*G19 -> 0
D20: 0 | E20: 0 | F20: =IF(D20=0,0,IF(C20="ex",E20*Salaries!$B$35+Salaries!$B$34*Salaries!D20,IF(C20="cl",E20*Salaries!$B$35+Salaries!$B$34*D20,IF(C20="GA",Salaries!$B$37*D20,IF(C20="TH",Salaries!$B$36*D20,"Need TYPE"))))) -> 0 | G20: =F20+D20 -> 0 | H20: 0 | I20: =H20*G20 -> 0 | J20: 0 | K20: =J20*G20 -> 0
D21: 0 | E21: 0 | F21: =IF(D21=0,0,IF(C21="ex",E21*Salaries!$B$35+Salaries!$B$34*Salaries!D21,IF(C21="cl",E21*Salaries!$B$35+Salaries!$B$34*D21,IF(C21="GA",Salaries!$B$37*D21,IF(C21="TH",Salaries!$B$36*D21,"Need TYPE"))))) -> 0 | G21: =F21+D21 -> 0 | H21: 0 | I21: =H21*G21 -> 0 | J21: 0 | K21: =J21*G21 -> 0
D22: 0 | E22: 0 | F22: =IF(D22=0,0,IF(C22="ex",E22*Salaries!$B$35+Salaries!$B$34*Salaries!D22,IF(C22="cl",E22*Salaries!$B$35+Salaries!$B$34*D22,IF(C22="GA",Salaries!$B$37*D22,IF(C22="TH",Salaries!$B$36*D22,"Need TYPE"))))) -> 0 | G22: =F22+D22 -> 0 | H22: 0 | I22: =H22*G22 -> 0 | J22: 0 | K22: =J22*G22 -> 0
D23: 0 | E23: 0 | F23: =IF(D23=0,0,IF(C23="ex",E23*Salaries!$B$35+Salaries!$B$34*Salaries!D23,IF(C23="cl",E23*Salaries!$B$35+Salaries!$B$34*D23,IF(C23="GA",Salaries!$B$37*D23,IF(C23="TH",Salaries!$B$36*D23,"Need TYPE"))))) -> 0 | G23: =F23+D23 -> 0 | H23: 0 | I23: =H23*G23 -> 0 | J23: 0 | K23: =J23*G23 -> 0
D24: 0 | E24: 0 | F24: =IF(D24=0,0,IF(C24="ex",E24*Salaries!$B$35+Salaries!$B$34*Salaries!D24,IF(C24="cl",E24*Salaries!$B$35+Salaries!$B$34*D24,IF(C24="GA",Salaries!$B$37*D24,IF(C24="TH",Salaries!$B$36*D24,"Need TYPE"))))) -> 0 | G24: =F24+D24 -> 0 | H24: 0 | I24: =H24*G24 -> 0 | J24: 0 | K24: =J24*G24 -> 0
D25: 0 | E25: 0 | F25: =IF(D25=0,0,IF(C25="ex",E25*Salaries!$B$35+Salaries!$B$34*Salaries!D25,IF(C25="cl",E25*Salaries!$B$35+Salaries!$B$34*D25,IF(C25="GA",Salaries!$B$37*D25,IF(C25="TH",Salaries!$B$36*D25,"Need TYPE"))))) -> 0 | G25: =F25+D25 -> 0 | H25: 0 | I25: =H25*G25 -> 0 | J25: 0 | K25: =J25*G25 -> 0
D26: 0 | E26: 0 | F26: =IF(D26=0,0,IF(C26="ex",E26*Salaries!$B$35+Salaries!$B$34*Salaries!D26,IF(C26="cl",E26*Salaries!$B$35+Salaries!$B$34*D26,IF(C26="GA",Salaries!$B$37*D26,IF(C26="TH",Salaries!$B$36*D26,"Need TYPE"))))) -> 0 | G26: =F26+D26 -> 0 | H26: 0 | I26: =H26*G26 -> 0 | J26: 0 | K26: =J26*G26 -> 0
D27: 0 | E27: 0 | F27: =IF(D27=0,0,IF(C27="ex",E27*Salaries!$B$35+Salaries!$B$34*Salaries!D27,IF(C27="cl",E27*Salaries!$B$35+Salaries!$B$34*D27,IF(C27="GA",Salaries!$B$37*D27,IF(C27="TH",Salaries!$B$36*D27,"Need TYPE"))))) -> 0 | G27: =F27+D27 -> 0 | H27: 0 | I27: =H27*G27 -> 0 | J27: 0 | K27: =J27*G27 -> 0
D28: 0 | E28: 0 | F28: =IF(D28=0,0,IF(C28="ex",E28*Salaries!$B$35+Salaries!$B$34*Salaries!D28,IF(C28="cl",E28*Salaries!$B$35+Salaries!$B$34*D28,IF(C28="GA",Salaries!$B$37*D28,IF(C28="TH",Salaries!$B$36*D28,"Need TYPE"))))) -> 0 | G28: =F28+D28 -> 0 | H28: 0 | I28: =H28*G28 -> 0 | J28: 0 | K28: =J28*G28 -> 0
A30: TOTAL SALARIES | D30: =SUM(D19:D28) -> 0 | G30: =SUM(G19:G28) -> 0 | I30: =SUM(I19:I28) -> 0 | K30: =SUM(K19:K28) -> 0
A33: Fringe Benefits* | B33: Rate
A34: Variable | B34: 0.24
A35: Fixed (Health) | B35: 8600
A36: TH | B36: 0.0872
A37: GA | B37: 0.0051
A39: *The FB rates can be modified if needed in this rate box

Sheet Operating Costs
A1: Service Center Calculations | B1: =General!C14 | F1: =Instructions!A3 -> FY2013
A3: Budgeted operating costs
A4: Purpose: To detail non-salary and non-equipment costs associated with the service center services
A6: Sheet Instructions
A7: Fill in only the yellow highlighted areas
A8: You may insert additional lines as necessary.
C9: SERVICE 1 | E9: SERVICE 2
A10: Travel | C10: =General!B28 | E10: =General!B29 -> 0
A11: Description | B11: Annual Amt | C11: % | D11: Amount | E11: % | F11: Amount
B12: 0 | D12: =$B12*C12 -> 0 | E12: 0 | F12: =$B12*E12 -> 0
B13: 0 | C13: 0 | D13: =$B13*C13 -> 0 | E13: 0 | F13: =$B13*E13 -> 0
B14: 0 | C14: 0 | D14: =$B14*C14 -> 0 | E14: 0 | F14: =$B14*E14 -> 0
B15: 0 | C15: 0 | D15: =$B15*C15 -> 0 | E15: 0 | F15: =$B15*E15 -> 0
B17: Totals | D17: =SUM(D12:D15) -> 0 | F17: =SUM(F12:F15) -> 0
C19: SERVICE 1 | E19: SERVICE 2
A20: Operating Expenses | C20: =General!B28 | E20: =General!B29 -> 0
A21: Description | B21: Annual Amt | C21: % | D21: Amount | E21: % | F21: Amount
C22: 0 | D22: =$B22*C22 -> 0 | E22: 0 | F22: =$B22*E22 -> 0
C23: 0 | D23: =$B23*C23 -> 0 | E23: 0 | F23: =$B23*E23 -> 0
C24: 0 | D24: =$B24*C24 -> 0 | E24: 0 | F24: =$B24*E24 -> 0
C25: 0 | D25: =$B25*C25 -> 0 | E25: 0 | F25: =$B25*E25 -> 0
C26: 0 | D26: =$B26*C26 -> 0 | E26: 0 | F26: =$B26*E26 -> 0
B28: Totals | D28: =SUM(D22:D26) -> 0 | F28: =SUM(F22:F26) -> 0
C30: SERVICE 1 | E30: SERVICE 2
A31: Equipment < $5,000*
A32: Description | B32: Annual Amt | C32: % | D32: Amount | E32: % | F32: Amount
B33: 0 | C33: 0 | D33: =$B33*C33 -> 0 | E33: 0 | F33: =$B33*E33 -> 0
B34: 0 | C34: 0 | D34: =$B34*C34 -> 0 | E34: 0 | F34: =$B34*E34 -> 0
B35: 0 | C35: 0 | D35: =$B35*C35 -> 0 | E35: 0 | F35: =$B35*E35 -> 0
B36: 0 | C36: 0 | D36: =$B36*C36 -> 0 | E36: 0 | F36: =$B36*E36 -> 0
B37: 0 | C37: 0 | D37: =$B37*C37 -> 0 | E37: 0 | F37: =$B37*E37 -> 0
B38: 0 | C38: 0 | D38: =$B38*C38 -> 0 | E38: 0 | F38: =$B38*E38 -> 0
B39: 0 | C39: 0 | D39: =$B39*C39 -> 0 | E39: 0 | F39: =$B39*E39 -> 0
B41: Totals | D41: =SUM(D33:D39) -> 0 | F41: =SUM(F33:F39) -> 0
A43: Equipment >$5,000 - See next worksheet

Sheet Capital Equip
A1: Service Center Calculations | D1: =General!C14 | M1: =Instructions!A3 -> FY2013
A3: Equipment > $5,000
A4: The purpose of this sheet is to track depreciation costs of capitalized equipment used to provide the service(s)
A5: *If you have any questions about the accounting for equipment >$5,000 for this service center, please contact BAAS
A7: Sheet instructions
A8: Fill in only yellow highlighted areas
A9: Column J - Identify the % of use of the equipment for each service
A10: Add additional lines as needed
J12: SERVICE 1 | L12: SERVICE 2
A13: Depreciation Schedule - Please Fill in Only Yellow Highlighted Areas | J13: =General!B28 | L13: =General!B29 -> 0
A14: Desc/Type of Equipment | B14: UI Property Tag# | C14: Acquisition Budget No. | D14: Acquistion Date | E14: Depr Start Date | F14: Depr End Date | G14: Acquisition Cost | H14: Useful Life (years) | I14: Annual depreciation | J14: % | K14: Amount | L14: % | M14: Amount
G15: 0 | H15: 0 | I15: =IF(G15=0,0,G15/H15) -> 0 | J15: 0 | K15: =I15*J15 -> 0 | L15: 0 | M15: =L15*I15 -> 0
G16: 0 | H16: 0 | I16: =IF(G16=0,0,G16/H16) -> 0 | J16: 0 | K16: =I16*J16 -> 0 | L16: 0 | M16: =L16*I16 -> 0
G17: 0 | H17: 0 | I17: =IF(G17=0,0,G17/H17) -> 0 | J17: 0 | K17: =I17*J17 -> 0 | L17: 0 | M17: =L17*I17 -> 0
G18: 0 | H18: 0 | I18: =IF(G18=0,0,G18/H18) -> 0 | J18: 0 | K18: =I18*J18 -> 0 | L18: 0 | M18: =L18*I18 -> 0
G19: 0 | H19: 0 | I19: =IF(G19=0,0,G19/H19) -> 0 | J19: 0 | K19: =I19*J19 -> 0 | L19: 0 | M19: =L19*I19 -> 0
G20: 0 | H20: 0 | I20: =IF(G20=0,0,G20/H20) -> 0 | J20: 0 | K20: =I20*J20 -> 0 | L20: 0 | M20: =L20*I20 -> 0
G21: 0 | H21: 0 | I21: =IF(G21=0,0,G21/H21) -> 0 | J21: 0 | K21: =I21*J21 -> 0 | L21: 0 | M21: =L21*I21 -> 0
I22: =IF(G22=0,0,G22/H22) -> 0 | J22: 0 | K22: =I22*J22 -> 0 | L22: 0 | M22: =L22*I22 -> 0
A24: Totals | G24: =SUM(G15:G23) -> 0 | I24: =SUM(I15:I23) -> 0 | K24: =SUM(K15:K23) -> 0 | M24: =SUM(M15:M23) -> 0
F27: Percentage of Use
F28: SERVICE 1 | G28: SERVICE 2
A29: Other Equipment Used to Provide Service But Not Included in the Costs | F29: =General!B28 | G29: =General!B29 -> 0
A30: Desc/Type of Equipment | B30: U of I Tag Number | C30: Acquisition Budget No. | D30: Acquistion Date | E30: Acquisition Cost | F30: % | G30: %
E31: 0 | F31: 0 | G31: 0
E32: 0 | F32: 0 | G32: 0
E33: 0 | F33: 0 | G33: 0
E34: 0 | F34: 0 | G34: 0
E35: 0 | F35: 0 | G35: 0
E36: 0 | F36: 0 | G36: 0
E37: 0 | F37: 0 | G37: 0
E38: 0 | F38: 0 | G38: 0

Sheet Add'l Costs
A1: Additional Cost Worksheet | C1: =Instructions!A3 -> FY2013
A2: Purpose: Used to identify other costs that support the service but are paid by other budgets
A4: Sheet Instructions
A5: 1) Fill in only yellow highlighted areas
A6: 2) Additional lines may be inserted as necessary
A8: Description of Cost | B8: Budget Number | C8: Amount
C33: =SUM(C9:C32) -> 0

Sheet Notes
A1: Notes and Comments | C1: =Instructions!A3 -> FY2013
A2: Purpose: To include comments that clarify how this rate sheet was developed or notes about the service center
A4: Sheet Instructions
A5: 1) Fill in only yellow highlighted areas
A6: 2) Additional lines may be inserted as necessary
C33: =SUM(C9:C32) -> 0

Sheet Summary
A1: =General!C13
A2: =General!C14
A3: =Instructions!A3 -> FY2013
A4: Service Center Summary Sheet
B7: =General!G27 -> FY2013
B8: Service 1 | C8: Service 2
B9: =General!B28 | C9: =General!B29 -> 0
A10: ANNUAL COSTS
A11: Salaries and Fringe Benefits | B11: =Salaries!I30 -> 0 | C11: =Salaries!K30 -> 0
A12: Travel | B12: ='Operating Costs'!D17 -> 0 | C12: ='Operating Costs'!F17 -> 0
A13: Operating Costs | B13: ='Operating Costs'!D28 -> 0 | C13: ='Operating Costs'!F28 -> 0
A14: Equipment < $5,000 | B14: ='Operating Costs'!D41 -> 0 | C14: ='Operating Costs'!F41 -> 0
A15: Capital equipment depreciation | B15: ='Capital Equip'!K24 -> 0 | C15: ='Capital Equip'!M24 -> 0
A17: TOTAL ANNUAL COSTS | B17: =SUM(B11:B16) -> 0 | C17: =SUM(C11:C16) -> 0
A19: % of Total Costs | B19: =IF(B17=0,0,B17/SUM(B17:C17)) -> 0 | C19: =IF(C17=0,0,C17/SUM(B17:C17)) -> 0
A21: Prior Year Balance (Add Deficit, Subtract Surplus) | B21: =-1*General!$C$23 -> 0 | C21: =-1*General!$C$23 -> 0
A22: Estimated 2 months working capital | B22: =B17/12*2 -> 0 | C22: =C17/12*2 -> 0
A24: TOTAL REVISED COSTS | B24: =B17+SUM(B21:B22) -> 0 | C24: =C17+SUM(C21:C22) -> 0
A26: # of Annual Units | B26: =General!F28 -> 0 | C26: =General!F29 -> 0 | E26: Rates
A27: Unit Base | B27: =General!E28 -> 0 | C27: =General!E29 -> 0 | E27: =General!D27 -> FY2012
E28: Service 1 | F28: Service 2
A29: CALCULATED RATE PER SERVICE PER UNIT | B29: =IF(B26<>0,B24/B26,0) -> 0 | C29: =IF(C26<>0,C24/C26,0) -> 0 | E29: =General!B24 -> 0 | F29: =General!B25 -> 0
E30: =General!D28 -> 0 | F30: =General!D29 -> 0
A31: SUBSIDY
A32: Subsidized Rate | B32: =IF(B26=0,0,(B24-B31)/B26) -> 0 | C32: =IF(C26=0,0,(C24-C31)/C26) -> 0
A34: UNIT RATE THAT WILL BE CHARGED TO CUSTOMERS | B34: 0 | C34: 0
