Workbook
Name Beef: Allocations!$J$60
Name Brown_Rice: Allocations!$J$86
Name Cheese: Allocations!$J$28
Name Chicken: Allocations!$J$41
Name Corn: Allocations!$J$84
Name Eggs: Allocations!$J$32
Name Flour: Allocations!$J$82
Name Fruit_Juice: Allocations!$J$72
Name Peanut_Butter: Allocations!$J$76
Name Pollock: Allocations!$J$89
Name Pork: Allocations!$J$65
Name Potatoes: Allocations!$J$98
Name sepdsflour: [1]Sheet8!$A$310:$J$600,[1]Sheet8!$A$309:$J$310
Name Tomato_Paste: Allocations!$J$74
Name Turkey: Allocations!$J$49

Sheet Allocations
A1: NOI Request Form
A2: Choose Name of SFA From Drop Down: | S2: Adair-Casey Comm School District
A3: Agreement Number: | F3: Due: March 8th, 2013 | S3: Adel DeSoto Minburn Comm School District
A4: Contact Name: | F4: Estimated Entitlement Budget | S4: AEA 267
A5: Contact e-mail: | F5: =LOOKUP(B2,Data!C2:C496,Data!E2:E496) -> #N/A | S5: AGWSR Comm School District
A6: Processor Name | B6: Material # | C6: Pounds | D6: $ Value | E6: Total $ Value | F6: Broker | S6: A-H-S-T Comm School District
S7: Akron Westfield Comm School District
A8: Cheese | S8: Albert City-Truesdale Comm School District
A9: 1. Bongard's Cheese | B9: 110242 | D9: 1.8003 | E9: =C9*D9 -> 0 | F9: Wolff Group | S9: Albia Comm School District
A10: 2. ES Foods | B10: 110242 | D10: 1.8003 | E10: =C10*D10 -> 0 | F10: Wolff Group | S10: Alburnett Comm School District
A11: 3. JTM Food Group | B11: 110242 | D11: 1.8003 | E11: =C11*D11 -> 0 | F11: Wolff Group | S11: Alden Comm School District
A12: 4. Land O Lakes | B12: 110242 | D12: 1.8003 | E12: =C12*D12 -> 0 | F12: Advantage Waypoint | S12: Algona Comm School District
A13: 5. Windsor Foods | B13: 110242 | D13: 1.8003 | E13: =C13*D13 -> 0 | F13: Advantage Waypoint | S13: All Saints Catholic School
A14: 6. Tasty Brands | B14: 110242 | D14: 1.8003 | E14: =C14*D14 -> 0 | F14: Advantage Waypoint | S14: All Saints School
A15: 7. Alpha Foods Co. | B15: 110244 | D15: 1.7117 | E15: =C15*D15 -> 0 | F15: GVM Food Marketing | S15: Allamakee Comm School District
A16: 8. Nardone Brothers | B16: 110244 | D16: 1.8003 | E16: =C16*D16 -> 0 | F16: Food Marketing Service | S16: Alta Comm School District
A17: 9. Rich's Products Corp. | B17: 110244 | D17: 1.7117 | E17: =C17*D17 -> 0 | F17: Elite Foodservice | S17: Ames Comm School District
A18: 10. Schwans Foodservice | B18: 110244 | D18: 1.7117 | E18: =C18*D18 -> 0 | F18: Elite Foodservice | S18: Anamosa Comm School District
A19: 11. Bosco Pizza | B19: 110244 | D19: 1.7117 | E19: =C19*D19 -> 0 | F19: Advantage Waypoint | S19: Andrew Comm School District
A20: 12. Café Favorites | B20: 110244 | D20: 1.7117 | E20: =C20*D20 -> 0 | F20: Café Favorites | S20: Ankeny Comm School District
... A27: 19. McCain Foods USA | B27: 100034 | D27: 1.7117 | E27: =C27*D27 -> 0 | F27: Elite Foodservice | S27: Assumption School
A28: Eggs | J28: =SUM(E9:E27) -> 0 | S28: Atlantic Comm School District
A29: 20. Café Favorites | B29: 100047 | D29: 0.696 | E29: =C29*D29 -> 0 | F29: Café Favorites | S29: Audubon Comm School District
A30: 21. Cargill Kitchen Solutions | B30: 100047 | D30: 0.696 | E30: =C30*D30 -> 0 | F30: Hockenberg Newburgh | S30: Aurelia Comm School District
A31: 22. Michael Foods | B31: 100047 | D31: 0.696 | E31: =C31*D31 -> 0 | F31: Advantage Waypoint | S31: Ballard Comm School District
A32: Chicken | J32: =SUM(E29:E31) -> 0 | S32: Battle Creek-Ida Grove Comm School District
A33: 23. Asian Food Solutions | B33: 100113 | D33: 0.7063 | E33: =C33*D33 -> 0 | F33: Hockenberg Newburgh | S33: Baxter Comm School District
A34: 24. Ling's 5th Taste | B34: 100113 | D34: 0.7063 | E34: =C34*D34 -> 0 | F34: GVM Food Marketing | S34: BCLUW Comm School District
A35: 25. Schwans Foodservice | B35: 100113 | D35: 0.7063 | E35: =C35*D35 -> 0 | F35: Elite Foodservice | S35: Beckman High School
A36: 26. Pilgrim's Pride | B36: 100103 | D36: 0.7503 | E36: =C36*D36 -> 0 | F36: Food Marketing Service | S36: Bedford Comm School District
A37: 27. Tyson | B37: 100103 | D37: 0.7503 | E37: =C37*D37 -> 0 | F37: Advantage Waypoint | S37: Belle Plaine Comm School District
A38: 28. Quantum Foods | B38: 100103 | D38: 0.7503 | E38: =C38*D38 -> 0 | F38: Hockenberg Newburgh | S38: Bellevue Comm School District
A39: 29. Pilgrim's Pride | B39: 100100 | D39: 0.863 | E39: =C39*D39 -> 0 | F39: Food Marketing Service | S39: Belmond-Klemme Comm School District
A40: 30. Tyson | B40: 100100 | D40: 0.863 | E40: =C40*D40 -> 0 | F40: Advantage Waypoint | S40: Bennett Comm School District
A41: Turkey | J41: =SUM(E33:E40) -> 0 | S41: Benton Comm School District
A42: 31. Café Favorites | B42: 100124 | D42: 1.1167 | E42: =C42*D42 -> 0 | F42: Café Favorites | S42: Bettendorf Comm School District
A43: 32. Cargill Value Added Meats | B43: 100124 | D43: 1.1167 | E43: =C43*D43 -> 0 | F43: Hockenberg Newburgh | S43: Bishop Garrigan High School
A44: 33. Jennie-O-Turkey | B44: 100124 | D44: 1.1167 | E44: =C44*D44 -> 0 | F44: Food Marketing Service | S44: Bishop Heelan Catholic Schools
A45: 34. Tasty Brands | B45: 100124 | D45: 1.1167 | E45: =C45*D45 -> 0 | F45: Advantage Waypoint | S45: Bishop Heelan Catholic High School
A46: 35. Jennie-O-Turkey | B46: 100883 | D46: 1.3259 | E46: =C46*D46 -> 0 | F46: Food Marketing Service | S46: Blackhawk Co Youth Shelt Youth Shelter
A47: 36. JTM Food Group | B47: 100883 | D47: 1.3259 | E47: =C47*D47 -> 0 | F47: Wolff Group | S47: Bondurant-Farrar Comm School District
A48: 37. AdvancePierre Foods, Inc. | B48: 100883 | D48: 1.3259 | E48: =C48*D48 -> 0 | F48: Elite Foodservice | S48: Boone Comm School District
A49: Beef | J49: =SUM(E42:E48) -> 0 | S49: Boyden-Hull Comm School District
A50: 38. American Foods Group | B50: 100154 | D50: 2.2874 | E50: =C50*D50 -> 0 | F50: Hockenberg Newburgh | S50: Boyer Valley Comm School District
A51: 39. AdvancePierre Foods, Inc. | B51: 100154 | D51: 2.2874 | E51: =C51*D51 -> 0 | F51: Elite Foodservice | S51: Boys & Girls Home
A52: 40. Integrated Food Service | B52: 100154 | D52: 2.2874 | E52: =C52*D52 -> 0 | F52: Hockenberg Newburgh | S52: Bremwood-Lchs System
A53: 41. JTM Food Group | B53: 100154 | D53: 2.2874 | E53: =C53*D53 -> 0 | F53: Wolff Group | S53: Brooklyn-Guernsey-Malcom Comm School District
A54: 42. Rich Products | B54: 100154 | D54: 2.2874 | E54: =C54*D54 -> 0 | F54: Elite Foodservice | S54: Burlington Comm School District
A55: 43. Quantum Foods | B55: 100154 | D55: 2.2874 | E55: =C55*D55 -> 0 | F55: Hockenberg Newburgh | S55: Burlington Notre Dame Schools
A56: 44. JTM Food Group | B56: 100156 | D56: 3.0892 | E56: =C56*D56 -> 0 | F56: Wolff Group | S56: CAL Comm School District
A57: 45. Quantum Foods | B57: 100156 | D57: 3.0892 | E57: =C57*D57 -> 0 | F57: Hockenberg Newburgh | S57: Calamus-Wheatland Comm School District
A58: 46. Tyson | B58: 100156 | D58: 3.0892 | E58: =C58*D58 -> 0 | F58: Advantage Waypoint | S58: CAM Comm School District
A59: 47. Tyson | B59: 100155 | D59: 2.3941 | E59: =C59*D59 -> 0 | F59: Advantage Waypoint | S59: Camanche Comm School District
A60: Pork | J60: =SUM(E50:E59) -> 0 | S60: Cardinal Comm School District
A61: 48. AdvancePierre Foods, Inc. | B61: 100193 | D61: 1.1954 | E61: =C61*D61 -> 0 | F61: Elite Foodservice | S61: Carlisle Comm School District
A62: 49. JTM Food Group | B62: 100193 | D62: 1.1954 | E62: =C62*D62 -> 0 | F62: Wolff Group | S62: Carroll Comm School District
A63: 50. JTM Food Group | B63: 110138 | D63: 1.3789 | E63: =C63*D63 -> 0 | F63: Wolff Group | S63: Cedar Falls Comm School District
A64: 51. Quantum Foods | B64: 110138 | D64: 1.3789 | E64: =C64*D64 -> 0 | F64: Hockenberg Newburgh | S64: Cedar Rapids Comm School District
A65: Fruit/Juice | J65: =SUM(E61:E64) -> 0 | S65: Cedar Valley Catholic School System
A66: 52. AdvancePierre Foods, Inc. (applesauce) | B66: 100208 | D66: 0.686 | E66: =C66*D66 -> 0 | F66: Elite Foodservice | S66: Center Point-Urbana Comm School District
A67: 53. AdvancePierre Foods, Inc. (peaches) | B67: 100219 | D67: 0.5994 | E67: =C67*D67 -> 0 | F67: Elite Foodservice | S67: Centerville Comm School District
A68: 54. AdvancePierre Foods, Inc. (pears) | B68: 100224 | D68: 0.6667 | E68: =C68*D68 -> 0 | F68: Elite Foodservice | S68: Central City Comm School District
A69: 55. Citrus Systems (orange juice) | B69: 100204 | D69: 2.2474 | E69: =C69*D69 -> 0 | F69: GVM Food Marketing | S69: Central Clinton Comm School District
A70: 56. Horizon Foods (apples slices frozen) | B70: 100258 | D70: 0.7219 | E70: =C70*D70 -> 0 | F70: Advantage Waypoint | S70: Central Comm School District
A71: 57. Horizon Foods (cherries IQF frozen) | B71: 100237 | D71: 0.8626 | E71: =C71*D71 -> 0 | F71: Advantage Waypoint | S71: Central Decatur Comm School District
A72: Tomato Paste | J72: =SUM(E66:E71) -> 0 | S72: Central Ia Juv Det Cntr
A73: 58. Schwans Foodservice | B73: 100332 | D73: 0.3612 | E73: =C73*D73 -> 0 | F73: Elite Foodservice | S73: Central Lee Comm School District
A74: 59. Red Gold | B74: 100332 | D74: 0.3612 | E74: =C74*D74 -> 0 | F74: Red Gold | J74: =SUM(E73:E74) -> 0 | S74: Central Lutheran School
A75: Peanut Butter | S75: Central Lyon Comm School District
A76: 60. AdvancePierre, Inc. | B76: 100397 | D76: 1.2197 | E76: =C76*D76 -> 0 | F76: Elite Foodservice | J76: =E76 -> 0 | S76: Central Springs Comm School District
A77: Flour | S77: Cfs Catholic School
A78: 61. Asian Food Solutions | B78: 100495 | D78: 0.214 | E78: =C78*D78 -> 0 | F78: Hockenberg Newburgh | S78: Chariton Comm School District
A79: 62. Country Home Bakers | B79: 100421 | D79: 0.21 | E79: =C79*D79 -> 0 | F79: Hockenberg Newburgh | S79: Charles City Comm School District
A80: 63. J&J Snack Foods | B80: 100420 | D80: 0.2865 | E80: =C80*D80 -> 0 | F80: Hockenberg Newburgh | S80: Charter Oak-Ute Comm School District
A81: 64. Rich's Products Corp. | B81: 100912 | D81: 0.2433 | E81: =C81*D81 -> 0 | F81: Elite Foodservice | S81: Cherokee Comm School District
A82: 65. Schwans Foodservice | B82: 100418 | D82: 0.211 | E82: =C82*D82 -> 0 | F82: Elite Foodservice | J82: =SUM(E78:E82) -> 0 | S82: Children and Fams of IA
A83: Corn | S83: Children'S Square Usa
A84: 66. Barrel of Fun | B84: 100444 | D84: 0.1798 | E84: =C84*D84 -> 0 | F84: Wolff Group | J84: =E84 -> 0 | S84: Christ The King School
A85: Brown Rice | S85: Clarinda Academy
A86: 67. Asian Food Solutions | B86: 101031 | D86: 0.5175 | E86: =C86*D86 -> 0 | F86: Hockenberg Newburgh | J86: =E86 -> 0 | S86: Clarinda Comm School District
A87: Pollock | S87: Clarion-Goldfield Comm School District
A88: 68. Highliner | B88: 100892 | D88: 1.6302 | E88: =C88*D88 -> 0 | F88: Advantage Waypoint | S88: Clarke Comm School District
A89: 69. Trident Seafoods Corp | B89: 100892 | D89: 1.6302 | E89: =C89*D89 -> 0 | F89: Elite Foodservice | J89: =SUM(E88:E89) -> 0 | S89: Clarksville Comm School District
A90: Potatoes | S90: Clay Central-Everly Comm School District
A91: 68. Basic American Foods (for dehy) | B91: 110227 | D91: 0.0536 | E91: =C91*D91 -> 0 | F91: Elite Foodservice | S91: Clayton Ridge Comm School District
A92: 69. Idahoan Foods (for dehy) | B92: 110227 | D92: 0.0536 | E92: =C92*D92 -> 0 | F92: Hockenberg Newburgh | S92: Clear Creek Amana Comm School District
A93: 70. J.R. Simplot (for dehy) | B93: 110227 | D93: 0.0536 | E93: =C93*D93 -> 0 | F93: Advantage Waypoint | S93: Clear Lake Comm School District
A94: 71. J.R. Simplot (for frozen) | B94: 100506 | D94: 0.0945 | E94: =C94*D94 -> 0 | F94: Advantage Waypoint | S94: Clearfield Comm School District
A95: 72. Lamb Weston (for frozen) | B95: 100506 | D95: 0.0945 | E95: =C95*D95 -> 0 | F95: Hockenberg Newburgh | S95: Clemons Lutheran School
A96: 73. Mc Cain Foods, USA (for frozen) | B96: 100506 | D96: 0.0945 | E96: =C96*D96 -> 0 | F96: Elite Foodservice | S96: Clinton Comm School District
A97: 74. J. R. Simplot (sweet potatoes) | B97: 100980 | D97: 0.1997 | E97: =C97*D97 -> 0 | F97: Advantage Waypoint | S97: Co Bluffs Area Cath Sch
A98: 75. Lamb Weston (sweet potatoes) | B98: 100980 | D98: 0.1997 | E98: =C98*D98 -> 0 | F98: Hockenberg Newburgh | J98: =SUM(E91:E99) -> 0 | S98: Colfax-Mingo Comm School District
A99: 76. Mc Cain Foods, USA (sweet potatoes) | B99: 100980 | D99: 0.1997 | E99: =C99*D99 -> 0 | F99: Elite Foodservice | S99: College Comm School District
S100: Collins-Maxwell Comm School District
C101: Total Request: | E101: ='Entitlement Details'!C23 -> 0 | F101: =IF('Entitlement Details'!C5<0,"Request exceeds entitlement balance","") -> #N/A | S101: Colo-NESCO School Comm School District
A102: Please complete this form and send back to the State Agency: | S102: Columbus Comm School District
A103: Jill.Stuecker@iowa.gov | S103: Comm Lutheran School
A104: Phone: 515-725-2887
A105: Fax: 515-242-5988 | S105: Coon Rapids-Bayard Comm School District
S106: Corning Comm School District
...

Sheet Entitlement Details
B1: Estimated Entitlement Budget Overview, SY 14
B2: Estimated Total Entitlement Budget (taken from SY 13) | C2: =LOOKUP(Allocations!B2,Data!C2:C496,Data!E2:E496) -> #N/A
B3: DoD Budget, SY 14 | C3: =LOOKUP(Allocations!B2,Data!C2:C496,Data!F2:F496) -> #N/A
B4: NOI Request, SY 14 | C4: =C23 -> 0
B5: Entitlement Balance Remaining for 6 state orders | C5: =C2-C23-C3 -> #N/A
B8: NOI Request Overview | C8: Dollars
B9: Cheese | C9: =Cheese -> 0
B10: Eggs | C10: =Eggs -> 0
B11: Chicken | C11: =Chicken -> 0
B12: Turkey | C12: =Turkey -> 0 | D12: =IF(C5<0,"Request exceeds entitlement balance !","") -> #N/A
B13: Beef | C13: =Beef -> 0
B14: Pork | C14: =Pork -> 0
B15: Fruit Juice | C15: =Fruit_Juice -> 0
B16: Tomato Paste | C16: =Tomato_Paste -> 0
B17: Peanut Butter | C17: =Peanut_Butter -> 0
B18: Flour | C18: =Flour -> 0
B19: Corn | C19: =Corn -> 0
B20: Brown Rice | C20: =Brown_Rice -> 0
B21: Pollock | C21: =Pollock -> 0
B22: Potatoes | C22: =Potatoes -> 0
B23: Total NOI Request | C23: =SUM(C9:C22) -> 0

Sheet Data
A1: District | B1: School | C1: Name | D1: ADP | E1: CalcEntitle | F1: DoD Amount
E2: 0 | F2: 0
A3: 0018 | B3: 0000 | C3: Adair-Casey Comm School District | D3: 266 | E3: 11491.2
A4: 0027 | B4: 0000 | C4: Adel DeSoto Minburn Comm School District | D4: 1110 | E4: 47952 | F4: 10000
A5: 9207 | B5: 0000 | C5: AEA 267 | D5: 143 | E5: 6177.6
A6: 0009 | B6: 0000 | C6: AGWSR Comm School District | D6: 460 | E6: 19872
A7: 0441 | B7: 0000 | C7: A-H-S-T Comm School District | D7: 486 | E7: 20995.2
A8: 0063 | B8: 0000 | C8: Akron Westfield Comm School District | D8: 442 | E8: 19094.4
A9: 0072 | B9: 0000 | C9: Albert City-Truesdale Comm School District | D9: 88 | E9: 3801.6
A10: 0081 | B10: 0000 | C10: Albia Comm School District | D10: 877 | E10: 37886.4
A11: 0099 | B11: 0000 | C11: Alburnett Comm School District | D11: 514 | E11: 22204.8 | F11: 7500
A12: 0108 | B12: 0000 | C12: Alden Comm School District | D12: 238 | E12: 10281.6
A13: 0126 | B13: 0000 | C13: Algona Comm School District | D13: 1016 | E13: 43891.2
A14: 1611 | B14: 8103 | C14: All Saints Catholic School | D14: 298 | E14: 12873.6 | F14: 5000
A15: 1053 | B15: 8101 | C15: All Saints School | D15: 151 | E15: 6523.2
A16: 0135 | B16: 0000 | C16: Allamakee Comm School District | D16: 1041 | E16: 44971.2
A17: 0171 | B17: 0000 | C17: Alta Comm School District | D17: 417 | E17: 18014.4
A18: 0225 | B18: 0000 | C18: Ames Comm School District | D18: 2031 | E18: 87739.2 | F18: 15000
A19: 0234 | B19: 0000 | C19: Anamosa Comm School District | D19: 947 | E19: 40910.4
A20: 0243 | B20: 0000 | C20: Andrew Comm School District | D20: 145 | E20: 6264
A21: 0261 | B21: 0000 | C21: Ankeny Comm School District | D21: 4581 | E21: 197899.2 | F21: 50000
A22: 0279 | B22: 0000 | C22: Aplington-Parkersburg Comm School District | D22: 732 | E22: 31622.4
A23: 6961 | B23: 8150 | C23: Aquin Elementary School | D23: 220 | E23: 9504
A24: 1053 | B24: 8006 | C24: Area Substnce Abuse Coun System | D24: 19 | E24: 820.8
A25: 0333 | B25: 0000 | C25: Armstrong-Ringsted Comm School District | D25: 275 | E25: 11880
A26: 0355 | B26: 0000 | C26: Ar-We-Va Comm School District | D26: 192 | E26: 8294.4
A27: 1611 | B27: 8101 | C27: Assumption High School | D27: 266 | E27: 11491.2
A28: 7110 | B28: 8101 | C28: Assumption School | D28: 59 | E28: 2548.8
A29: 0387 | B29: 0000 | C29: Atlantic Comm School District | D29: 1193 | E29: 51537.6
A30: 0414 | B30: 0000 | C30: Audubon Comm School District | D30: 466 | E30: 20131.2
A31: 0423 | B31: 0000 | C31: Aurelia Comm School District | D31: 238 | E31: 10281.6
A32: 0472 | B32: 0000 | C32: Ballard Comm School District | D32: 1174 | E32: 50716.8
A33: 0504 | B33: 0000 | C33: Battle Creek-Ida Grove Comm School District | D33: 505 | E33: 21816
A34: 0513 | B34: 0000 | C34: Baxter Comm School District | D34: 344 | E34: 14860.8 | F34: 2000
A35: 0540 | B35: 0000 | C35: BCLUW Comm School District | D35: 528 | E35: 22809.6
A36: 6961 | B36: 8146 | C36: Beckman High School | D36: 414 | E36: 17884.8 | F36: 5000
A37: 0549 | B37: 0000 | C37: Bedford Comm School District | D37: 438 | E37: 18921.6
A38: 0576 | B38: 0000 | C38: Belle Plaine Comm School District | D38: 441 | E38: 19051.2 | F38: 5000
A39: 0585 | B39: 0000 | C39: Bellevue Comm School District | D39: 479 | E39: 20692.8
A40: 0594 | B40: 0000 | C40: Belmond-Klemme Comm School District | D40: 527 | E40: 22766.4
A41: 0603 | B41: 0000 | C41: Bennett Comm School District | D41: 63 | E41: 2721.6
A42: 0609 | B42: 0000 | C42: Benton Comm School District | D42: 1125 | E42: 48600
A43: 0621 | B43: 0000 | C43: Bettendorf Comm School District | D43: 2630 | E43: 113616 | F43: 35000
A44: 0126 | B44: 8108 | C44: Bishop Garrigan High School | D44: 194 | E44: 8380.8
A45: 6039 | B45: 8000 | C45: Bishop Heelan Catholic Schools | D45: 295 | E45: 12744 | F45: 3000
A46: 6039 | B46: 8106 | C46: Bishop Heelan Catholic High School | D46: 252 | E46: 10886.4
A47: 6795 | B47: 8601 | C47: Blackhawk Co Youth Shelt Youth Shelter | D47: 7 | E47: 302.4
A48: 0720 | B48: 0000 | C48: Bondurant-Farrar Comm School District | D48: 1105 | E48: 47736 | F48: 18000
A49: 0729 | B49: 0000 | C49: Boone Comm School District | D49: 1542 | E49: 66614.4
A50: 0747 | B50: 0000 | C50: Boyden-Hull Comm School District | D50: 500 | E50: 21600
A51: 1917 | B51: 0000 | C51: Boyer Valley Comm School District | D51: 379 | E51: 16372.8
A52: 6039 | B52: 8003 | C52: Boys & Girls Home | D52: 40 | E52: 1728
A53: 6840 | B53: 8000 | C53: Bremwood-Lchs System | D53: 69 | E53: 2980.8
A54: 0846 | B54: 0000 | C54: Brooklyn-Guernsey-Malcom Comm School District | D54: 462 | E54: 19958.4
A55: 0882 | B55: 0000 | C55: Burlington Comm School District | D55: 2959 | E55: 127828.8 | F55: 61000
A56: 0882 | B56: 8000 | C56: Burlington Notre Dame Schools | D56: 167 | E56: 7214.4
A57: 0916 | B57: 0000 | C57: CAL Comm School District | D57: 248 | E57: 10713.6
A58: 0918 | B58: 0000 | C58: Calamus-Wheatland Comm School District | D58: 439 | E58: 18964.8
A59: 0914 | B59: 0000 | C59: CAM Comm School District | D59: 356 | E59: 15379.2
A60: 0936 | B60: 0000 | C60: Camanche Comm School District | D60: 847 | E60: 36590.4
A61: 0977 | B61: 0000 | C61: Cardinal Comm School District | D61: 507 | E61: 21902.4
A62: 0981 | B62: 0000 | C62: Carlisle Comm School District | D62: 1315 | E62: 56808
A63: 0999 | B63: 0000 | C63: Carroll Comm School District | D63: 1447 | E63: 62510.4 | F63: 16000
A64: 1044 | B64: 0000 | C64: Cedar Falls Comm School District | D64: 3099 | E64: 133876.8 | F64: 48000
A65: 1053 | B65: 0000 | C65: Cedar Rapids Comm School District | D65: 11681 | E65: 504619.2 | F65: 80000
A66: 6795 | B66: 8007 | C66: Cedar Valley Catholic School System | D66: 847 | E66: 36590.4
A67: 1062 | B67: 0000 | C67: Center Point-Urbana Comm School District | D67: 1158 | E67: 50025.6 | F67: 10000
A68: 1071 | B68: 0000 | C68: Centerville Comm School District | D68: 974 | E68: 42076.8
A69: 1089 | B69: 0000 | C69: Central City Comm School District | D69: 350 | E69: 15120
A70: 1082 | B70: 0000 | C70: Central Clinton Comm School District | D70: 1329 | E70: 57412.8 | F70: 15000
A71: 1080 | B71: 0000 | C71: Central Comm School District | D71: 371 | E71: 16027.2
A72: 1093 | B72: 0000 | C72: Central Decatur Comm School District | D72: 558 | E72: 24105.6 | F72: 4500
A73: 2007 | B73: 8607 | C73: Central Ia Juv Det Cntr | D73: 17 | E73: 734.4
A74: 1079 | B74: 0000 | C74: Central Lee Comm School District | D74: 766 | E74: 33091.2
A75: 0609 | B75: 8000 | C75: Central Lutheran School | D75: 115 | E75: 4968
A76: 1095 | B76: 0000 | C76: Central Lyon Comm School District | D76: 548 | E76: 23673.6
A77: 4772 | B77: 0000 | C77: Central Springs Comm School District | D77: 592 | E77: 25574.4
A78: 6100 | B78: 8000 | C78: Cfs Catholic School | D78: 98 | E78: 4233.6
A79: 1107 | B79: 0000 | C79: Chariton Comm School District | D79: 961 | E79: 41515.2 | F79: 20000
A80: 1116 | B80: 0000 | C80: Charles City Comm School District | D80: 1388 | E80: 59961.6
A81: 1134 | B81: 0000 | C81: Charter Oak-Ute Comm School District | D81: 285 | E81: 12312
A82: 1152 | B82: 0000 | C82: Cherokee Comm School District | D82: 753 | E82: 32529.6
A83: 1737 | B83: 8011 | C83: Children and Fams of IA | D83: 6 | E83: 259.2
A84: 1476 | B84: 8000 | C84: Children'S Square Usa | D84: 43 | E84: 1857.6
A85: 1737 | B85: 8117 | C85: Christ The King School | D85: 174 | E85: 7516.8 | F85: 2000
A86: 1197 | B86: 8601 | C86: Clarinda Academy | D86: 204 | E86: 8812.8
A87: 1197 | B87: 0000 | C87: Clarinda Comm School District | D87: 859 | E87: 37108.8
A88: 1206 | B88: 0000 | C88: Clarion-Goldfield Comm School District | D88: 702 | E88: 30326.4 | F88: 8000
A89: 1211 | B89: 0000 | C89: Clarke Comm School District | D89: 1063 | E89: 45921.6 | F89: 15000
A90: 1215 | B90: 0000 | C90: Clarksville Comm School District | D90: 284 | E90: 12268.8
A91: 1218 | B91: 0000 | C91: Clay Central-Everly Comm School District | D91: 283 | E91: 12225.6
A92: 2763 | B92: 0000 | C92: Clayton Ridge Comm School District | D92: 521 | E92: 22507.2
A93: 1221 | B93: 0000 | C93: Clear Creek Amana Comm School District | D93: 1363 | E93: 58881.6
A94: 1233 | B94: 0000 | C94: Clear Lake Comm School District | D94: 1009 | E94: 43588.8 | F94: 20000
A95: 1224 | B95: 0000 | C95: Clearfield Comm School District | D95: 36 | E95: 1555.2
A96: 6985 | B96: 8201 | C96: Clemons Lutheran School | D96: 11 | E96: 475.2
A97: 1278 | B97: 0000 | C97: Clinton Comm School District | D97: 2770 | E97: 119664
A98: 1476 | B98: 8002 | C98: Co Bluffs Area Cath Sch | D98: 554 | E98: 23932.8 | F98: 5000
A99: 1332 | B99: 0000 | C99: Colfax-Mingo Comm School District | D99: 513 | E99: 22161.6
A100: 1337 | B100: 0000 | C100: College Comm School District | D100: 3683 | E100: 159105.6 | F100: 55000
...
