Workbook

Sheet Petition
A1: Scouting's Journey to Excellence
A2: 2012 OA Lodge Performance Recognition Program
B4: Council name | C4: Southrn New Jersey | D4: Council number | E4: 3.34 | F4: HQ City/State | G4: Millville | I4: NJ
B6: Lodge name | C6: Te'Kening | D6: Region | E6: NE | F6: Section | G6: NE | I6: Yes
I7: No
A8: Form completed by | C8: Allen Thorpe | D8: Phone number | E8: 302-275-0949 | F8: E-mail address | G8: althorpe1@verizon.net
A9: To qualify for recognition lodges must renew their 2013 charter on time with appropriate fees and be in compliance with the current editions of the OA Handbook, Guide for Officers and Advisers, Field Operations Guide, Guide to Inductions, and ceremony books.
A10: Item # | B10: Objective | D10: Bronze level | E10: Silver level | F10: Gold level | G10: Bronze points | H10: Silver points | I10: Gold points
B11: Finance
A12: 1 | B12: Fiscal management: Develop and successfully execute a lodge annual budget. | D12: Complete and follow an annual budget approved by the lodge executive committee | E12: Close the year with a positive operating balance (i.e., operate in the black) | F12: Close with an operating balance at least as great as your budget projection | G12: =IF(H12+I12=0,IF(I13>1,0,(IF(H13>1,0,(IF(D13="Yes",25,0))))),0) -> 0 | H12: =IF(I12=0,IF(D13="Yes",IF(I12=100,0,(IF(D13=E13,50,0))),0),0) -> 0 | I12: =IF(D13="Yes",IF(D13=E13,(IF(F13="Yes",100,0)),0),0) -> 100
D13: yes | E13: yes | F13: Yes
A14: 2 | B14: Contribution to council: Contribute cash, materials or both to the council. | D14: Contribute an average of $2.00 per lodge member | E14: Contribute the equivalent of $3.50 per lodge member | F14: Contribute the equivalent of $5.00 per lodge member | G14: =IF(Worksheet!I8=0,0,(IF((H14+I14)=0,(IF((Worksheet!I8/Worksheet!I16)>=2,75,0)),0))) -> 0 | H14: =IF(Worksheet!I8=0,0,(IF(I14=0,(IF((Worksheet!I8/Worksheet!I16)>=3.5,100,0)),0))) -> 0 | I14: =IF(Worksheet!I8=0,0,(IF((Worksheet!I8/Worksheet!I16)>=5,200,0))) -> 200
B15: Membership
A16: 3 | B16: Membership impact: Experience positive growth in membership over the previous year. [REQUIRED] | D16: Grow membership by at least 1 | E16: Grow membership by at least 1% | F16: Grow membership by at least 3% | G16: =IF(H16+I16=0,(IF(Worksheet!I16>=(Worksheet!H16+1),75,0)),0) -> 0 | H16: =IF(Worksheet!I16=0,0,(IF(I16=0,IF(Worksheet!I16>=(Worksheet!H16*1.01),100,0),0))) -> 0 | I16: =IF(Worksheet!I16=0,0,(IF(Worksheet!I16>=(Worksheet!H16*1.03),200,0))) -> 200
A17: 4 | B17: Ordeal completion: Complete induction of elected Ordeal candidates. | D17: Complete induction of at least 60% of Ordeal candidates or 5% increase | E17: Complete induction of at least 75% of Ordeal candidates or 5% increase over 60% | F17: Complete induction of at least 90% of Ordeal candidates or 5% increase over 75% | G17: =IF(Worksheet!I16=0,0,(IF(H17+I17=0,IF(OR(Worksheet!I19>=(Worksheet!I27*0.6),Worksheet!I19>=(Worksheet!H19*1.05)),25,0),0))) -> 0 | H17: =IF(Worksheet!I19=0,0,(IF(Worksheet!I19>=(Worksheet!I27*0.6),IF(I17=0,IF(OR(Worksheet!I19>=(Worksheet!I27*0.75),Worksheet!I19>=(Worksheet!H19*1.05)),50,0),0),0))) -> 50 | I17: =IF(Worksheet!I19=0,0,(IF(Worksheet!I19>=(Worksheet!I27*0.75),IF(OR(Worksheet!I19>=(Worksheet!I27*0.9),Worksheet!I19>=(Worksheet!H19*1.05)),100,0),0))) -> 0
A18: 5 | B18: Brotherhood completion: Convert eligible Ordeal members to Brotherhood. [REQUIRED] | D18: Convert at least 30% or 5% increase over prior year | E18: Convert at least 40% or 3% increase over 30% | F18: Convert at least 50% or 3% increase over 40% | G18: =IF(Worksheet!I20=0,0,(IF(H18+I18=0,IF(OR(Worksheet!I20/(Worksheet!I11-Worksheet!I19+Worksheet!I20)>=0.3,Worksheet!I20>=(Worksheet!H20*1.05)),25,0),0))) -> 25 | H18: =IF(Worksheet!I20=0,0,IF((Worksheet!I20/(Worksheet!I11-Worksheet!I19+Worksheet!I20)>=0.3),(IF(Worksheet!I20/(Worksheet!I11-Worksheet!I2+Worksheet!I230)>=0.3,IF(I18=0,IF(OR(Worksheet!I20/(Worksheet!I11-Worksheet!I19+Worksheet!I20)>=0.4,Worksheet!I20>=(Worksheet!H20*1.03)),50,0),0),0)),0)) -> 0 | I18: =IF(Worksheet!I20=0,0,IF((Worksheet!I20/(Worksheet!I11-Worksheet!I19+Worksheet!I20)>=0.3),(IF(Worksheet!I20/(Worksheet!I11-Worksheet!I19+Worksheet!I20)>=0.4,IF(OR(Worksheet!I20/(Worksheet!I11-Worksheet!I19+Worksheet!I20)>=0.5,Worksheet!I20>=(Worksheet!H20*1.05)),100,0),0)),0)) -> 0
A19: 6 | B19: Membership retention: Improve retention rate of lodge members. | D19: Achieve 50% or a 4% increase over prior year | E19: Achieve 60% or a 4% increase over 50% | F19: Achieve 70% or a 5% increase over 60% | G19: =IF(Worksheet!I16=0,0,(IF(H19+I19=0,IF(OR(((Worksheet!I16-Worksheet!I19)/Worksheet!I16>=0.5),(((Worksheet!I16-Worksheet!I19)/Worksheet!I16)-(((Worksheet!H16-Worksheet!H19)/Worksheet!H16))>=0.04)),75,0),0))) -> 0 | H19: =IF(Worksheet!I16=0,0,(IF(((Worksheet!I16-Worksheet!I19)/Worksheet!I16>=0.5),IF(I19=0,IF(OR(((Worksheet!I16-Worksheet!I19)/Worksheet!I16>=0.6),(((Worksheet!I16-Worksheet!I19)/Worksheet!I16)-(((Worksheet!H16-Worksheet!H19)/Worksheet!H16))>=0.04)),100,0),0),0))) -> 0 | I19: =IF(Worksheet!I16=0,0,(IF(((Worksheet!I16-Worksheet!I19)/Worksheet!I16>=0.6),IF(OR(((Worksheet!I16-Worksheet!I19)/Worksheet!I16>=0.7),(((Worksheet!I16-Worksheet!I19)/Worksheet!I16)-(((Worksheet!H16-Worksheet!H19)/Worksheet!H16))>=0.05)),200,0),0))) -> 200
B20: Program
A21: 7 | B21: Unit elections: Conduct unit elections in council troops and teams desiring them. | D21: Complete elections for at least 90% of requesting units | E21: Complete elections for at least 95% of requesting units | F21: Complete elections for 100% of requesting units | G21: =IF(Worksheet!I25=0,0,(IF(I21+H21=0,(IF((Worksheet!I26/Worksheet!I25)>=0.9,75,0)),0))) -> 0 | H21: =IF(Worksheet!I25=0,0,(IF(I21=0,(IF((Worksheet!I26/Worksheet!I25)>=0.95,100,0)),0))) -> 0 | I21: =IF(Worksheet!I25=0,0,(IF((Worksheet!I26/Worksheet!I25)=1,200,0))) -> 200
A22: 8 | B22: Section and national event attendance: Attend section and national events. | D22: Set and achieve a lodge attendance goal at scheduled section & national events | E22: Exceed the lodge attendance goal by 10% | F22: Exceed the lodge attendance goal by 20% | G22: =IF(Worksheet!H33=0,0,(IF(H22+I22=0,(IF(Worksheet!H33<=Worksheet!I33,25,0)),0))) -> 0 | H22: =IF(Worksheet!H33=0,0,(IF(I22=0,(IF(Worksheet!H33*1.1<=Worksheet!I33,50,0)),0))) -> 0 | I22: =IF(Worksheet!H33=0,0,(IF(Worksheet!H33*1.2<=Worksheet!I33,100,0))) -> 100
A23: 9 | B23: Lodge communications: Maintain active communications within the lodge. | D23: Have and follow a written lodge communication plan | E23: Publish a lodge newsletter or update your lodge web site at least quarterly | F23: Contribute to the council newsletter or web site | G23: =IF(H23+I23=0,IF(I23>1,0,(IF(H23>1,0,(IF(D24="Yes",25,0))))),0) -> 0 | H23: =IF(I23=0,IF(D24="Yes",IF(I23=100,0,(IF(D24=E24,50,0))),0),0) -> 0 | I23: =IF(D24=E24,(IF(F24="Yes",100,0)),0) -> 100
D24: yes | E24: yes | F24: Yes
A25: 10 | B25: Lodge event participation: Improve lodge membership participation at full lodge events. | D25: Average at least 10% of lodge membership at all lodge events | E25: Average at least 20% of lodge membership at all lodge events | F25: Average at least 30% of lodge membership at all lodge events | G25: =IF(Worksheet!I16=0,0,(IF(I25+H25=0,(IF(Worksheet!I46>=(Worksheet!I16*0.1),25,0)),0))) -> 0 | H25: =IF(Worksheet!I16=0,0,(IF(I25=0,(IF(Worksheet!I46>=(Worksheet!I16*0.2),50,0)),0))) -> 50 | I25: =IF(Worksheet!I16=0,0,(IF(Worksheet!I46>=(Worksheet!I16*0.3),100,0))) -> 0
A26: 11 | B26: Lodge planning: Maintain an active planning process that guides the lodge program and supports the council strategic plan. | D26: Have a written annual plan approved by the Scout Executive | E26: Conduct an annual review and update of your plan in conjunction with a review of the Council Strategic Plan | F26: Have an annual meeting with the Scout Executive to review your updated plan | G26: =IF(H26+I26=0,IF(I26>1,0,(IF(H26>1,0,(IF(D27="Yes",25,0))))),0) -> 0 | H26: =IF(I26=0,IF(D27="Yes",IF(I26=100,0,(IF(D27=E27,50,0))),0),0) -> 0 | I26: =IF(D27="YES",IF(D27=E27,(IF(F27="Yes",100,0)),0),0) -> 100
D27: yes | E27: yes | F27: yes
B28: Council service
A29: 12 | B29: Council service projects: Complete Scout Executive approved service project(s) on council property and in the community. | D29: Complete project(s) equal to at least 2 hours of service per lodge member | E29: Complete project(s) equal to at least 2.5 hours of service per lodge member | F29: Complete project(s) equal to at least 3 hours of service per lodge member | G29: =IF(Worksheet!H7=0,0,(IF((H29+I29)=0,(IF((Worksheet!H7/Worksheet!I16)>=2,75,0)),0))) -> 0 | H29: =IF(Worksheet!H7=0,0,(IF(I29=0,(IF((Worksheet!H7/Worksheet!I16)>=2.5,100,0)),0))) -> 0 | I29: =IF(Worksheet!H7=0,0,(IF((Worksheet!H7/Worksheet!I16)>=3,200,0))) -> 200
A30: 13 | B30: Council camping support: Conduct camp promotion contacts to council troops and teams. | D30: Complete contacts to at least 75% of units or 3% increase | E30: Complete contacts to at least 80% of units or 3% increase over 75% | F30: Complete contacts to at least 85% of units or 3% increase over 80% | G30: =IF(Worksheet!I49=0,0,(IF(H30+I30=0,IF(OR(Worksheet!I49>=(Worksheet!I24*0.75),Worksheet!I49>=(Worksheet!H49*1.03)),75,0),0))) -> 0 | H30: =IF(Worksheet!I49=0,0,(IF(Worksheet!I49>=(Worksheet!I24*0.75),IF(I30=0,IF(OR(Worksheet!I49>=(Worksheet!I24*0.8),Worksheet!I49>=(Worksheet!H49*1.03)),100,0),0),0))) -> 0 | I30: =IF(Worksheet!I49=0,0,(IF(Worksheet!I49>=(Worksheet!I24*0.8),IF(OR(Worksheet!I49>=(Worksheet!I24*0.85),Worksheet!I49>=(Worksheet!H49*1.03)),200,0),0))) -> 200
A31: 14 | B31: Council program support: Provide OA member staff support for council and district program events. | D31: Support 2 council or district events | E31: Support 3 council or district events | F31: Support 5 council or district events | G31: =IF(H31+I31=0,IF((5-(COUNTBLANK(Worksheet!G52:G56)))=2,75,0),0) -> 0 | H31: =IF(I31=0,IF((5-(COUNTBLANK(Worksheet!G52:G56)))>2,100,0),0) -> 0 | I31: =IF((5-(COUNTBLANK(Worksheet!G52:G56)))=5,200,0) -> 200
A32: 15 | B32: Council designated support: Complete Scout Executive designated program support projects. | D32: Complete one project | E32: Complete two projects | F32: Complete three projects | G32: =IF(H32+I32=0,IF((3-(COUNTBLANK(Worksheet!E59:E61)))=1,75,0),0) -> 0 | H32: =IF(I32=0,IF((3-(COUNTBLANK(Worksheet!E59:E61)))=2,100,0),0) -> 0 | I32: =IF((3-(COUNTBLANK(Worksheet!E59:E61)))=3,200,0) -> 200
B33: Leadership and governance
A34: 16 | B34: Lodge and chapter leadership: Conduct at least one LLD during the year with qualified instructors using current material. | D34: Achieve at least 75% of eligible members trained or 3% increase | E34: Achieve at least 80% of eligible members trained or 3% over 75% | F34: Achieve at least 85% of eligible members trained or 3% over 80% | G34: =IF(Worksheet!I64=0,0,(IF(H34+I34=0,IF(OR(Worksheet!I65>=(Worksheet!I64*0.75),Worksheet!I65>=(Worksheet!H65*1.03)),25,0),0))) -> 25 | H34: =IF(Worksheet!I64=0,0,(IF(Worksheet!I65>=(Worksheet!I64*0.75),IF(I34=0,IF(OR(Worksheet!I65>=(Worksheet!I64*0.8),Worksheet!I65>=(Worksheet!H65*1.03)),50,0),0),0))) -> 0 | I34: =IF(Worksheet!I64=0,0,(IF(Worksheet!I65>=(Worksheet!I64*0.8),IF(OR(Worksheet!I65>=(Worksheet!I64*0.85),Worksheet!I65>=(Worksheet!H65*1.03)),100,0),0))) -> 0
A35: 17 | B35: Annual report: Submit a written annual report of accomplishments to the council executive board. | D35: Written report submitted | E35: Written report submitted and verbal report given to the executive board | F35: Verbal report given by the lodge chief | G35: =IF(H35+I35=0,IF(I35>1,0,(IF(H35>1,0,(IF(D36="Yes",25,0))))),0) -> 25 | H35: =IF(I35=0,IF(D36="Yes",IF(I35=100,0,(IF(D36=E36,50,0))),0),0) -> 0 | I35: =IF(D36="YES",IF(D36=E36,(IF(F36="Yes",100,0)),0),0) -> 0
D36: yes
F37: Total achieved | G37: =SUM(G12:G35) -> 75 | H37: =SUM(H12:H35) -> 100 | I37: =SUM(I12:I35) -> 2000
B38: Award level: | D38: =IF(AND(I38>=1400,SUM(G16:I16)>0,SUM(G18:I18)>0,COUNTIF(G12:I36,0)<=36),"Gold",(IF(AND(I38>=1100,SUM(G16:I16)>0,SUM(G18:I18)>0,COUNTIF(G12:I36,0)<=39),"Silver",(IF(AND(I38>=800,SUM(G16:I16)>0,SUM(G18:I18)>0,COUNTIF(G12:I36,0)<=41),"Bronze","None"))))) -> Gold | H38: Grand total | I38: =SUM(G37:I37) -> 2175
A40: Journey to Excellence, the new performance recognition program adopted by the BSA in 2011, changes the basic way we measure and recognize success by moving away from measuring process and toward measuring performance. To be aligned with the BSA and to capitalize on this best practice used in the corporate performance measurement field today, the Order of the Arrow is adopting the Journey to Excellence format to evaluate lodge performance and evaluate opportunities for continuous improvement. Below is specific information to help you understand the criteria and exactly what data will be used to determine the three levels of performance. In planning your strategy, use actual numbers from the previous year to guide your performance improvement goal-planning.
A42: Scoring the Lodge's performance
C43: To qualify for silver or gold points within an individual criterion, a lodge must have completed the lower level criterion (e.g., to qualify for silver level in item number 1, a lodge must have completed the bronze level in that item)
C44: To determine the lodge’s overall performance level, the council will use the above matrix to determine the points earned in each of the 17 individual criteria, circle the criteria completed, add the scores in each column to determine the points earned at each award level, then add the three column scores to obtain the Grand Total points earned.
C45: Overall award levels are determined as follows using the grand total points earned:
C46: - Bronze = at least 800 grand total points plus have completed at least bronze performance in 10 criteria, two of which must be objectives #3 and #5
C47: - Silver - at least 1100 grand total points plus have completed bronze performance, including items #3 and #5, in at least 12 criteria
C48: - Gold = at least 1400 grand total points plus have completed bronze performance, including items #3 and #5, in at least 15 criteria
A49: Note: In cases where an individual criterion states for example “Achieve 60% retention or a 4% increase over 50” the award level can only be achieved in reference to the previous year’s performance in that area. In this example, if the lodge achieved 50% retention in the previous year, achieving 54% would be required to qualify them in this area in the current year. If they then achieved 54% in the current year, they would have to achieve at least 58% in the next year to qualify.
A50: Amplifying instructions keyed to item numbers above:
A52: 2. Contributions are to be in either cash (e.g. an FOS contribution to the council) or materials. In the case of materials, the value should be determined on the basis of current market value or the value determined by the Scout Executive.
A53: 6. To determine retention, take current year total membership less current year Ordeal inductions times 100 and then divide by prior year total membership. For example, ((2012 total membership less 2012 Ordeal inductions) x 100) ÷ (2011 total membership). All numbers are to be taken from the respective lodge charter renewal applications.
A54: 7. All troops and teams must have been contacted and given the opportunity to request an election. Election teams must be trained, all team members in proper uniform during each unit election, and team members must be from units other than the one for which the election is being held.
A55: 8. Lodge representation at all national events is not required. The intent of this criterion is to encourage lodges to set and meet a goal for participation in as many national events as they can support. Attendance at an OA High Adventure program qualifies under this item. Recognizing that quotas to section and national events can vary from year to year, each year’s goal should be set such that the lodge leadership considers it more challenging than the previous year’s goal.
A56: 10. To determine lodge event participation, add the attendance of all events where all lodge members were invited to attend (e.g., fellowships and lodge banquets), then divide by the number of events to get an average attendance number. Divide that number by the total lodge membership to determine the overall average percent of the lodge in attendance.
A57: 12. At least one council project and one community service project must be conducted and a written report of each project included in the lodge annual report.
A58: 13. What constitutes an acceptable contact under this category is determined by the Scout Executive or the council’s camping committee if delegated by the Scout Executive.
A59: 15. Scout Executive designated projects are to be developed during a meeting with the lodge Key 3 with consideration for both the current local council and national Order of the Arrow strategic plans. Example projects are listed below.
A60: 16. LLD courses must be conducted with qualified instructors and using current LLD materials (see www.oa-bsa.org) to train lodge and chapter committee chairmen and their advisers. Eligible participants include elected and appointed youth mebers of the LEC and their advisers.
A62: Examples of item 15 - Council Scout Executive designated Council support projects:
C63: In addition to the contributions in item 2, the lodge is to make a minimum contribution of $1,000 to the council endowment fund through the award of a James E. West Fellowship to a deserving member of the lodge.
C64: The lodge is to publish [update] a Where to Go Camping pamphlet, CD, or information published on the council or lodge website.
C65: The lodge Key 3 is to meet with the Scout Executive at least quarterly to discuss progress in the lodge.
C66: The lodge is to provide manpower, resources, and/or program assistance in support of the council Cub Scout outdoor program.
C67: The lodge is to provide support to a minimum of ten Cub Scout crossover ceremonies.
C68: At least one adult and two youth are to attend a National Lodge Adviser Training Seminar (NLATS) and a National Leadership Seminar (NLS) respectively.
C69: The lodge is to create and activate an OA Mentoring Program within the council.
C70: At least one lodge member is to attend an OA national high adventure program.
C71: The lodge is to recruit XX lodge members to serve as summer camp staff.
A73: Note: the above project list is provided only as an example of possible projects to consider. Actual projects assigned are entirely at the discretion of the Scout Executive.

Sheet Worksheet
A1: 2012 OA Lodge Performance Worksheet
A3: Complete all shaded fields. Values will automatically be calculated and solved to Journey to Excellence petition
A4: Item # | B4: Finance
A5: 2,12 | B5: How much did the lodge contribute in cash, materials and manpower to the council? | D5: Dollar value of FOS contributions | H5: 1000
D6: Capital contributions* | H6: 1250
D7: Hours of service | H7: 2354
D8: *(cash and estimated value of material) | H8: Total | I8: =(H7*7.25)+H6+H5 -> 19316.5
B9: Membership
A10: 3,5,10 | B10: How many dues-paying members did the lodge have the last two years? What level was the membership? | H10: 2011 | I10: 2012
D11: Ordeal members | H11: 146 | I11: 200
D12: Brotherhood members | H12: 159 | I12: 164
D13: Vigil members | H13: 86 | I13: 82
D14: Youth members (under 21) | H14: 205 | I14: 246
D15: Adult members | H15: 159 | I15: 200
D16: Total lodge membership | H16: =SUM(H11:H13) -> 391 | I16: =SUM(I11:I13) -> 446
D17: Lodge annual dues | H17: 8 | I17: 8
A19: 4,5 | B19: How many candidates completed their Ordeal? Sealed their Brotherhood? Kept the Vigil? | D19: Ordeal inductions (this year) | H19: 64 | I19: 123
D20: Brotherhood inductions (this year) | H20: 23 | I20: 37
D21: Vigil inductions (this year) | H21: 8 | I21: 6
B22: Program
A23: 7,13 | B23: Of the troops/teams in the council, how many requested elections? How many conducted elections and what number of candidates were elected? | H23: 2011 | I23: 2012
G24: Total troops/teams in the council | H24: 115 | I24: 115
G25: Number requesting elections | H25: 38 | I25: 37
G26: Elections conducted | H26: 38 | I26: 37
G27: Candidates elected | H27: 112 | I27: 197
A29: 8 | B29: How many members attended the last two years section Conclaves, OA High Adventure programs, and other national events (NOAC, Indian Summer, etc.)? | F29: 2011 | H29: 2012 goal | I29: 2012 actual
E30: Section Conclave | F30: 62 | H30: 35 | I30: 67
E31: OA High Adventure | F31: 2 | H31: 2 | I31: 2
E32: National events | F32: 3 | H32: 15 | I32: 29
E33: Total | F33: =SUM(F30:G32) -> 67 | H33: =SUM(H30:H32) -> 52 | I33: =SUM(I30:I32) -> 98
A35: 10 | B35: Which lodge events did the lodge host the past year? What was lodge member attendance over the past two years? | E35: Event name | H35: 2011 | I35: 2012
D36: 1 | E36: May Induction | H36: 94 | I36: 68
D37: 2 | E37: June Induction | H37: 64 | I37: 82
D38: 3 | E38: September Induction | H38: 102 | I38: 114
D39: 4 | E39: October LLD | H39: 71 | I39: 90
D40: 5 | E40: December Annual Dinner | H40: 103 | I40: 157
D41: 6 | E41: Summer camp Social | H41: 91 | I41: 115
D42: 7
D43: 8
D44: 9
D45: 10
E46: Average attendance | H46: =IF(SUM(H36:H45)=0,0,SUM(H36:H45)/(10-COUNTBLANK(E36:E45))) -> 87.5 | I46: =IF(SUM(I36:I45)=0,0,SUM(I36:I45)/(10-COUNTBLANK(E36:E45))) -> 104.33333
B47: Council service
A48: 13 | B48: How many troops/teams were contacted for camp promotion? | H48: 2011 | I48: 2012
E49: Unit contacts completed | H49: 115 | I49: 115
A51: 14 | B51: Which council or district events were supported by the lodge with Order of the Arrow staff? | G51: Event supported
F52: 1 | G52: NYLT
F53: 2 | G53: FireQuest
F54: 3 | G54: Old Colony
F55: 4 | G55: Cub Day Camp
F56: 5 | G56: Summer Camp Promotions
A58: 15 | B58: Which programs, designated by the Scout Executive, were completed this year? | E58: Project
D59: 1 | E59: Bridge Project at PHSR
D60: 2 | E60: Roosevelt Trail connector Bridge installation
D61: 3 | E61: Summer camp onsite promotion support
B62: Leadership and governance
A63: 16 | B63: How many members are there on the lodge executive committee? How many participated in this years LLD? | H63: 2011 | I63: 2012
D64: LEC members (youth and adult) | H64: 39 | I64: 42
D65: Number participating in LLD | H65: 29 | I65: 30
