Workbook

Sheet Cover
A2: Within this Excel workbook is a worksheet for data entry. Click on the FinReview tab, and enter the CDN for your charter school. Then enter the student and staff estimates, the financial categories/object code amounts, and the total revenues and total net working capital balance amounts. The worksheet will automatically calculate the status.

Sheet FinReview
B2: CDN: | F2: Charter Name: | H2: =LOOKUP(FinReview!D2,TEAData!A2:A250,TEAData!B2:B250) -> #N/A
B5: Category 1. Student-to-Staff Ratio Outside Norm or Declining | D5: 2011-2012 Estimate | E5: 2010-2011 Actual | J5: Comments
B6: Enrollment | E6: =LOOKUP(FinReview!D2,TEAData!A2:A250,TEAData!C2:C250) -> #N/A
B7: WADA | E7: =LOOKUP(FinReview!D2,TEAData!A2:A250,TEAData!D2:D250) -> #N/A
B8: All Staff FTE | E8: =LOOKUP(FinReview!D2,TEAData!A2:A250,TEAData!E2:E250) -> #N/A
D9: 2011-2012 Estimate | E9: 2010-2011 Actual | F9: Average per Group | H9: Indicator Description | I9: Indicator
B10: a. WADA-to-All-Staff-FTE Ratio | D10: =D7/D8 -> #DIV/0! | E10: =E7/E8 -> #N/A | F10: =IF(FinReview!E6>=Average!B10,Average!C10,IF(FinReview!E6>=Average!B9,Average!C9,IF(FinReview!E6>=Average!B8,Average!C8,IF(FinReview!E6>=Average!B7,Average!C7, IF(FinReview!E6>=Average!B6,Average!C6,IF(FinReview!E6>=Average!B5,Average!C5,IF(FinReview!E6>=Average!B4,Average!C4,IF(FinReview!E6>=Average!B3,Average!C3,IF(FinReview!E6>=Average!B2,Average!C2,0))))))))) -> #N/A | H10: < 70% of group avg | I10: =IF(D10<F10*0.7,"Yes","No") -> #DIV/0!
B11: b. WADA-to-All-Staff-FTE Ratio | D11: =D7/D8 -> #DIV/0! | E11: =E7/E8 -> #N/A | F11: =IF(FinReview!E6>=Average!B10,Average!C10,IF(FinReview!E6>=Average!B9,Average!C9,IF(FinReview!E6>=Average!B8,Average!C8,IF(FinReview!E6>=Average!B7,Average!C7,IF(FinReview!E6>=Average!B6,Average!C6,IF(FinReview!E6>=Average!B5,Average!C5,IF(FinReview!E6>=Average!B4,Average!C4,IF(FinReview!E6>=Average!B3,Average!C3,IF(FinReview!E6>=Average!B2,Average!C2,0))))))))) -> #N/A | H11: < group avg and decline of more than 10% from prior year | I11: =IF(AND(D11<F11*0.7,D11<E11-(E11*0.1)),"Yes","No") -> #DIV/0!
B14: Category 2. General Fund Expenditures Exceeding Revenues | D14: 2011-2012 Amount | E14: 2010-2011 Actual Amount | F14: 2010-2011 Budget Amount | G14: Suggested Difference | H14: 2009-2010 Actual Amount | I14: 2009-2010 Budget Amount | J14: Comments
B16: Payroll
B17: Object codes 6110-6149
B19: Contract Costs
B20: Object code series 6200
B22: Supplies and Materials
B23: Object code series 6300 | G23: =#REF!*#REF! -> #REF!
B25: Other Operating
B26: Object code series 6400
B28: Debt Service
B29: Object code series 6500 | G29: =#REF!*#REF! -> #REF!
B31: Capital Outlay
B32: Object code series 1500
B34: Total Expenditures
D35: =SUM(D17+D20+D23+D26+D29+D32) -> 0 | E35: =SUM(E17+E20+E23+E26+E29+E32) -> 0 | F35: =LOOKUP(FinReview!D2,TEAData!A2:A250,TEAData!H2:H250) -> #N/A | G35: =#REF!*#REF! -> #REF! | H35: =LOOKUP(FinReview!D2,TEAData!A2:A250,TEAData!I2:I250) -> #N/A | I35: =LOOKUP(FinReview!D2,TEAData!A2:A250,TEAData!G2:G250) -> #N/A
B37: a. Expenditures** exceed revenues by more than 8%. | I37: =IF(E35>E42*1.08,"Yes","No") -> No
B38: b. Expenditures exceed revenues by more than 6% and exceeded revenues by more than 4% in the prior year. | I38: =IF(AND(E35>E42*1.06,H35>H42*1.04),"Yes","No") -> #N/A
B39: c. Expenditures exceed revenues by more than 5%, and the charter school has a prior year end-of-year net working capital balance* that has declined from the year before by more than 20% and that is less than 4% of general fund expenditures for the school. | I39: =IF(AND(E35>E42,E45<H45,E45<E35*0.04),"Yes","No") -> #N/A
B40: Category 3. Declining or Low Net Working Capital Balance*
B41: Total Revenues
F42: =LOOKUP(FinReview!D2,TEAData!A2:A250,TEAData!K2:K250) -> #N/A | G42: =#REF!*#REF! -> #REF! | H42: =LOOKUP(FinReview!D2,TEAData!A2:A250,TEAData!L2:L250) -> #N/A | I42: =LOOKUP(FinReview!D2,TEAData!A2:A250,TEAData!J2:J250) -> #N/A
B44: Net Working Capital Balance
H45: =LOOKUP(FinReview!D2,TEAData!A2:A250,TEAData!M2:M250) -> #N/A
J47: Additional Questions
B48: a. Prior year end-of-year net working capital balance declined from the year before by more than 50%, and the net working capital balance is less than 6% of the general fund expenditures for the charter school. | I48: =IF(AND(E45<H45-(H45*0.5),E45<E35-(E35*0.06)),"Yes","No") -> #N/A | J48: Did your charter school borrow funds to pay for operating expenses and not repay the funds within 12 months from the time they were borrowed within the last two years?
B49: b. Prior year end-of-year net working capital balance is less than 1% of the general fund expenditures for the charter school. | I49: =IF(E45<E35*0.01,"Yes","No") -> No | J49: Has your charter school declared bankruptcy within the past two years?
J50: How many executive directors/superintendents has your charter school had in the last three years?
B51: At least one "Declining or Low Net Working Capital Balance" "Yes" indicator and one other "Yes" indicator: | I51: =IF(AND(COUNTIF(I48:I49,"Yes")>0,COUNTIF(I10:I42,"Yes")>0),"Yes","No") -> No | J51: How many business managers has your charter school had in the last three years?
B52: Net working capital balance less than 1% of general fund expenditures: | I52: =IF(E45<E35*0.01,"Yes","No") -> No | J52: Eligible to be considered for additional review?
J53: =IF(COUNTIF(I51:I52,"Yes")>0,"Yes","No") -> No
B54: * The net working capital balance (equivalent to a school district's general fund assigned and unassigned fund balance) is defined as current assets minus current liabilities.
B55: ** For charter schools, general fund expenditures do not include depreciation expenses.

Sheet TEAData
A1: CDN | B1: District Name | C1: 2010-2011 Enrollment | D1: 2010-2011 WADA | E1: 2010-2011 Staff FTE | F1: 2010-2011 WADA-to-All-Staff Avg | G1: 2009-2010 Budgeted Expenditures | H1: 2010-2011 Budgeted Expenditures | I1: 2009-2010 Actual Expenditures | J1: 2009-2010 Budget Revenues | K1: 2010-2011 Budget Revenues | L1: 2009-2010 Actual Revenues | M1: 2009-2010 Net Working Capital Balance
A2: 003801 | B2: PINEYWOODS COMMUNITY ACADEMY | C2: 465 | D2: 633.248 | E2: 62.8061 | F2: 10.082588 | G2: 2544274 | H2: 3019657 | I2: 2736638 | J2: 2544274 | K2: 2903766 | L2: 2915445 | M2: 264053
A3: 013801 | B3: ST MARY'S ACADEMY CHARTER SCHOOL | C3: 361 | D3: 533.793 | E3: 66.2103 | F3: 8.062084 | G3: 2674559 | H3: 2940780 | I3: 2717372 | J3: 2764943 | K3: 3011595 | L3: 2938489 | M3: 873022
A4: 014801 | B4: RICHARD MILBURN ALTER HIGH SCHOOL | C4: 152 | D4: 252.002 | E4: 24.9788 | F4: 10.088635 | G4: 1322049 | H4: 1402443 | I4: 1331297 | J4: 1808368 | K4: 1401808 | L4: 1421534 | M4: 368438
A5: 014802 | B5: TRANSFORMATIVE CHARTER ACADEMY | C5: 75 | D5: 104.937 | E5: 11.3884 | F5: 9.214376 | G5: 574509 | H5: 646848 | I5: 648910 | J5: 545711 | K5: 647136 | L5: 653391 | M5: -86555
A6: 014803 | B6: TEMPLE EDUCATION CENTER | C6: 165 | D6: 240.656 | E6: 19.9992 | F6: 12.033281 | G6: 1072116 | H6: 1369008 | I6: 970597 | J6: 1035786 | K6: 1237495 | L6: 1305884 | M6: 592199.89
A7: 014804 | B7: ORENDA CHARTER SCHOOL | C7: 395 | D7: 751.38 | E7: 52.055 | F7: 14.434348 | G7: 3089792 | H7: 4816326 | I7: 3063133 | J7: 3262757 | K7: 4858504 | L7: 3432569 | M7: 1123901
A8: 015801 | B8: POR VIDA ACADEMY | C8: 339 | D8: 470.333 | E8: 59.9997 | F8: 7.8389225 | G8: 2718249 | H8: 3035203 | I8: 3041289 | J8: 2895246 | K8: 3063552 | L8: 2870277 | M8: 206857
A9: 015802 | B9: GEORGE GERVIN ACADEMY | C9: 1327 | D9: 1247.34 | E9: 53.2198 | F9: 23.437518 | G9: 4018854 | H9: 7181980 | I9: 4663396 | J9: 4018855 | K9: 7181980 | L9: 4663396 | M9: 139814
A10: 015803 | B10: HIGGS CARTER KING GIFTED & TALENTE | C10: 695 | D10: 700.884 | E10: 35.2695 | F10: 19.872241 | G10: 3103202 | H10: 3596034 | I10: 3358807 | J10: 3103203 | K10: 3596034 | L10: 3785107 | M10: 979113
A11: 015805 | B11: NEW FRONTIERS CHARTER SCHOOL | C11: 616 | D11: 941.404 | E11: 69.6463 | F11: 13.516928 | G11: 4799470 | H11: 4894083 | I11: 4698958 | J11: 4533061 | K11: 4894081 | L11: 5207597 | M11: 1562136
A12: 015806 | B12: SCHOOL OF EXCELLENCE IN EDUCATION | C12: 1624 | D12: 2430.669 | E12: 302.0031 | F12: 8.0484902 | G12: 15517760 | H12: 17008475 | I12: 15056223 | J12: 17059200 | K12: 17402781 | L12: 16775510 | M12: 2860386
A13: 015807 | B13: SOUTHWEST PREPARATORY SCHOOL | C13: 772 | D13: 989.993 | E13: 113.7893 | F13: 8.7002293 | G13: 7364355 | H13: 6830958 | I13: 6760520 | J13: 7019246 | K13: 6393000 | L13: 6848412 | M13: 830351
... A196: 243801 | B196: BRIGHT IDEAS CHARTER | C196: 187 | D196: 242.007 | E196: 24.2789 | F196: 9.967791 | G196: 1382809 | H196: 1249199 | I196: 1486070 | J196: 1445550 | K196: 1940337 | L196: 1410509 | M196: 1

Sheet Average
A1: Group | B1: Enrollment | C1: Statewide Average WADA-to-All-Staff Ratio
A2: 1 | B2: 1 | C2: 9.74
A3: 2 | B3: 100 | C3: 10.18
A4: 3 | B4: 250 | C4: 11.73
A5: 4 | B5: 500 | C5: 11.99
A6: 5 | B6: 1000 | C6: 11.97
A7: 6 | B7: 1600 | C7: 12.48
A8: 7 | B8: 3000 | C8: 14.61
A9: 8 | B9: 5000 | C9: 13.26
A10: 9 | B10: 10000 | C10: 12.07
