Workbook

Sheet OA Budget Planning-Report Sheet
A1: Order of the Arrow Event Budget Planning and Report Sheet
A3: Name of Event: | B3: Chapter Events (typical) | E3: Event Dates (start-end): | H3: The event name is entered into cell "B3" by selecting the event type from the drop-down menu
E4: Start | F4: End | H4: The event start date is entered into cell "E4" and the event end date is entered into cell "F4"
A5: Chapter: | B5: Chapter Name (Number) | H5: The chapter name is entered in the cell "B5 " by selecting the chapter name from the drop-down menu
A7: Account #: | B7: Custodial Account | E7: Date to be Closed: | H7: The chapter cost center number is entered in cell B7" by selecting the Account # from the drop-down menu
A9: Expected Attendance: | E9: Actual Attendance:
A11: Expenses | B11: Last Year | C11: Budget | D11: Actual | H11: Expenses
A12: Food | B12: 0 | C12: ='Estimated Budget'!$P$113 -> 0 | D12: ='Final Closeout'!N29 -> 0 | E12: Pre-Approval | H12: The figures in Column B are from the prior actual OA Event Budget Planning and Report Sheet | P12: Chapter Name (Number) | Q12: Custodial Account | S12: Chapter Events (typical)
A13: Postage | B13: 0 | C13: ='Estimated Budget'!$P$115 -> 0 | D13: ='Final Closeout'!N35 -> 0 | P13: O/A Appalachian Tail (40) | Q13: 1-2371-238-00 (AT) | S13: Ordeal (Fall)
A14: Printing | B14: 0 | C14: ='Estimated Budget'!$P$117 -> 0 | D14: ='Final Closeout'!$N$41 -> 0 | H14: The figures in Column C are from Estimated Budget Worksheet totals | P14: O/A Aquia (17) | Q14: 1-2371-127-00 (Aquia) | S14: Ordeal (Spring)
A15: Awards (Recognitions) | B15: 0 | C15: ='Estimated Budget'!$P$119 -> 0 | D15: ='Final Closeout'!$N$49 -> 0 | E15: (Prepared by - Chapter Adviser) | H15: The figures in Column D are the totals by category from the Chapter Event Budget Closeout Worksheet | P15: O/A Bull Run (29) | Q15: 1-2371-726-00 (BR) | S15: Banquet
A16: Ceremonies | B16: 0 | C16: ='Estimated Budget'!$P$121 -> 0 | D16: ='Final Closeout'!$N$57 -> 0 | P16: O/A Catoctin Mountain (41) | Q16: 1-2371-259-00 (CM) | S16: Brotherhood
A17: Health & Safety | B17: 0 | C17: ='Estimated Budget'!$P$123 -> 0 | D17: ='Final Closeout'!$N$63 -> 0 | P17: O/A Chain Bridge (21) | Q17: 1-2371-175-00 (CB) | S17: Fellowship
A18: Facility/Site Infrastructure | B18: 0 | C18: ='Estimated Budget'!$N$51 -> 0 | D18: =IF('Final Closeout'!$K$77>0,'Final Closeout'!$K$75-$K$70,'Final Closeout'!$K$70) -> 0 | E18: (Reviewed by - Lodge Financial Adviser) | H18: Reimbursements/Disbursements | P18: O/A Colonial (22) | Q18: 1-2371-324-00 (Col)
H19: The figure in column B is from the prior year actual OA Event Budget Planning and Report sheet | P19: O/A George Mason (23) | Q19: 1-2371-337-00 (GM)
A20: Less: Reimbursements | D20: ='Reimbursements-Refunds'!$M$51 -> 0 | P20: O/A Goose Creek (28) | Q20: 1-2371-649-00 (GC)
A21: Sub-Total Event Expenses | B21: =SUM($B$12:$B$19) -> 0 | C21: =SUM($C$12:$C$19) -> 0 | D21: =SUM($D$12:$D$19)-$D$20 -> 0 | E21: (Approved by - Lodge Staff Adviser) | H21: The figure in Column D is the Total of Reimbursements from the Reimbursement/Disbursement Statement | P21: O/A Mattaponi (32) | Q21: 1-2371-840-00 (Matt)
A22: Program Materials | P22: O/A Occoquan (30) | Q22: 1-2371-805-00 (Occ)
A23: Ordeal Sashes, OA Handbooks, & Lodge Flaps | B23: 0 | C23: ='Estimated Budget'!$P$127 -> 0 | D23: ='Final Closeout'!$N$85 -> 0 | E23: Close out approval | P23: O/A Old Dominion (24) | Q23: 1-2371-365-00 (OD)
H24: Program Materials | P24: O/A Patriot (25) | Q24: 1-2371-965-00 (Patr)
A25: Brotherhood Sashes | B25: 0 | C25: ='Estimated Budget'!$P$132 -> 0 | D25: ='Final Closeout'!$N$89 -> 0 | H25: The figures in Column B are from the prior actual OA Event Budget Planning and Report Sheet | P25: O/A Piedmont (33) | Q25: 1-2371-885-00 (Pied)
A26: Elangomat Patches | B26: 0 | C26: ='Estimated Budget'!$P$134 -> 0 | D26: ='Final Closeout'!$N$91 -> 0 | E26: (Prepared by - Chapter Adviser) | P26: O/A Potomac (36) | Q26: 1-2371-687-00 (Pot)
B27: 0 | C27: 0 | D27: 0 | H27: The figures in Column C are from Estimated Budget Worksheet totals | P27: O/A Powhatan (26) | Q27: 1-2371-480-00 (Pow)
B28: 0 | C28: 0 | D28: 0 | H28: The figures in Column D are the totals by category from the Chapter Event Budget Closeout Worksheet | P28: O/A Prince George's (31) | Q28: 1-2371-290-00 (PG)
B29: 0 | C29: 0 | D29: 0 | E29: (Reviewed by - Lodge Financial Adviser) | P29: O/A Seneca (38) | Q29: 1-2371-938-00 (Sen)
B30: 0 | C30: 0 | D30: 0 | P30: O/A Sully (27) | Q30: 1-2371-534-00 (Sully)
B31: 0 | C31: 0 | D31: 0 | P31: O/A Washington DC (11) | Q31: 1-2371-199-00 (W DC)
B32: 0 | C32: 0 | D32: 0 | E32: (Approved by - Lodge Staff Adviser) | P32: O/A Western Shore (43) | Q32: 1-2371-792-00 (WS)
B33: 0 | C33: 0 | D33: 0 | E33: Disposition of Funds | P33: O/A White Oak (37) | Q33: 1-2371-277-00 (WO)
A34: Sub-Total Program Exp | B34: =SUM($B$23:$B$33) -> 0 | C34: =SUM($C$23:$C$33) -> 0 | D34: =SUM($D$23:$D$33) -> 0 | E34: Total Revenue | F34: =$D$46 -> 0 | P34: O/A Zekiah (42) | Q34: 1-2371-448-00 (Zek)
E36: Sub-Total Event Exp | F36: =$D$21 -> 0
A37: Liability Recovery | B37: 0 | C37: ='Estimated Budget'!$P$143 -> 0 | D37: ='Final Closeout'!$N$97 -> 0 | E37: Sub-Total Prog Exp | F37: =$D$34 -> 0
E38: (1-2371-419-00)
A39: Dues (Ordeal Candidates Only) | B39: 0 | C39: ='Estimated Budget'!$P$130 -> 0 | D39: ='Final Closeout'!$N$99 -> 0 | E39: Disbursements | F39: =$D$20 -> 0 | H39: Disbursements represent the combined Reimbursements and Refunds
A40: Contingency | C40: ='Estimated Budget'!$N$54+'Estimated Budget'!$P$151 -> 0 | E40: Liability Recovery | F40: =$D$37 -> 0
A41: Total Expenses | B41: =$B$21+$B$34+$B$37+$B$39 -> 0 | C41: =$C$21+$C$34+$C$37+$C$39+$C$40 -> 0 | D41: =D20+$D$21+$D$34+$D$37+$D$39 -> 0 | E41: (1-9315- - ) | H41: Revenues
A42: Revenue | E42: Dues (Ordeal Only) | F42: =$D$39 -> 0 | H42: The figures in Column B are from the prior actual OA Event Budget Planning and Report Sheet
A43: Registration Fees | B43: 0 | C43: ='Estimated Budget'!$K$100 -> 0 | D43: ='Final Closeout'!$N$15 -> 0 | E43: (1-2371-425-00)
A44: Miscellaneous | B44: 0 | C44: ='Estimated Budget'!$K$106 -> 0 | D44: 0 | E44: Subtotal | F44: =SUM($F$36:$F$43) -> 0 | H44: The figures in Column C are from Estimated Budget Worksheet totals
A45: Less: Approved Refunds | B45: 0 | D45: ='Final Closeout'!$N$78 -> 0 | H45: The figures in Column D are the totals by category from the Chapter Event Budget Closeout Worksheet and Reimbursement/Disbursement Statement (Refunds)
A46: Total Revenue | B46: =SUM($B$43:$B$44)-$B$45 -> 0 | C46: =SUM($C$43:$C$45) -> 0 | D46: =SUM($D$43:$D$44)-$D$45 -> 0 | E46: Balance | F46: =$F$34-$F$44 -> 0
A47: Excess Revenue/Deficit | B47: =SUM($B$46-$B$41) -> 0 | D47: =D46-D41 -> 0

Sheet Estimated Budget
A1: CHAPTER: | D1: ='OA Budget Planning-Report Sheet'!$B$5 -> Chapter Name (Number) | K1: Account #: | N1: ='OA Budget Planning-Report Sheet'!$B$7 -> Custodial Account | R1: The chapter name is mapped from the OA Budget Planning-Report worksheet cell "OA Budget Planning-Report Sheet'!B5"
R2: The chapter account # is mapped from the OA Budget Planning-Report worksheet cell "OA Budget Planning-Report Sheet'!B7"
A4: CALCULATING EXPENSES:
A6: Food | H6: Quantity | K6: Cost | N6: Total
B7: Ordeal Candidates | I7: x | J7: $ | L7: = | M7: $ | N7: =$H$7*$K$7 -> 0
B8: Elangomats | I8: x | J8: $ | L8: = | M8: $ | N8: =$H$8*$K$8 -> 0 | R8: The estimated number of attendees by category is entered
B9: Members | I9: x | J9: $ | L9: = | M9: $ | N9: =$H$9*$K$9 -> 0 | R9: in column "H" in the gray shaded cells "H7" to "H13"
B10: Members (Day Only) | I10: x | J10: $ | L10: = | M10: $ | N10: =$H$10*$K$10 -> 0 | R10: The estimated food cost per person by category is entered
B11: Feast Only | I11: x | J11: $ | L11: = | M11: $ | N11: =$H$11*$K$11 -> 0 | R11: in column "K" in the gray shaded cells "K7" to "K13"
I12: x | J12: $ | L12: = | M12: $ | N12: =$H$12*$K$12 -> 0 | R12: The Estimated Food Cost per attendee category is automatically calculated
I13: x | J13: $ | L13: = | M13: $ | N13: =$H$13*$K$13 -> 0
B14: TOTAL ESTIMATED FOOD COSTS | M14: $ | N14: =SUM($N$7:$N$13) -> 0 | R14: The Total Estimated Food Cost is automatically calculated
A16: Operating
B17: Postage | H17: Quantity | K17: Cost | N17: Total | R17: The current first class postage rate is entered into cell "K18" and is mapped to cell "K19"
C18: Ordeal Candidates | I18: x | J18: $ | L18: = | M18: $ | N18: =$H$18*$K$18 -> 0 | R18: The number of elected ordeal candidates elected during the current elections season is entered into cell "H18"
C19: Members | I19: x | J19: $ | K19: =$K$18 -> 0 | L19: = | M19: $ | N19: =$H$19*$K$19 -> 0 | R19: The number of members in the chapter is entered into cell "H19"
R20: Additional printing cost description is entered in cell "C20and the cost in cell 'N20"
C21: TOTAL ESTIMATED POSTAGE COSTS | M21: $ | N21: =SUM($N$18:$N$20) -> 0 | R21: The Total Postage Cost is automatically calculated
B22: Printing & Printing Supplies | H22: Quantity | K22: Cost | N22: Total
C23: Ordeal Candidates | H23: =$H$18 -> 0 | I23: x | J23: $ | L23: = | M23: $ | N23: =$H$23*$K$23 -> 0
C24: Members | H24: =$H$19 -> 0 | I24: x | J24: $ | K24: =$K$23 -> 0 | L24: = | M24: $ | N24: =$H$24*$K$24 -> 0 | R24: The per person printing cost is entered into cell "K23 and is mapped to cell "K24"
R25: The quantities are mapped from cells "H18 and "H19"
R26: Additional printing cost description is entered in cell "C25" to "C27" and the cost in cell "N25" to "N27"
R27: The Total Printing Cost is automatically calculated
C28: TOTAL ESTIMATED PRINTING COSTS | M28: $ | N28: =SUM($N$23:$N$27) -> 0
B29: Awards | N29: Cost
R31: Awards cost descriptions are entered in cells "C30" to "C33"
R32: and the costs are entered in cells "N30 to "N33"
R33: The Total Awards Cost is automatically calculated
C34: TOTAL ESTIMATED AWARDS COSTS | M34: $ | N34: =SUM($N$30:$N$33) -> 0
B35: Ceremonies | N35: Cost
R37: Ceremonies cost descriptions are entered in cells "C36" to "C39"
R38: and the costs are entered in cells "N36" to "N39"
R39: The Total Ceremonies Cost is automatically calculated
C40: TOTAL ESTIMATED CEREMONIES COSTS | M40: $ | N40: =SUM($N$36:$N$39) -> 0
B41: Health & Safety | N41: Cost
R42: Health & Saftey cost descriptions are entered in cells "C42" to "C45"
R43: and the costs are entered in cells "N42" to "N45"
R44: The Total Ceremonies Cost is automatically calculated
C46: TOTAL ESTIMATED HEATLH & SAFTEY COSTS | M46: $ | N46: =SUM($N$41:$N$45) -> 0
B47: Facility/Site Infrastructure | H47: Quantity | K47: Cost | N47: Total
C48: Facility usage Fee (per attendee) | H48: =SUM($H$7:$H$13) -> 0 | I48: x | J48: $ | L48: = | M48: $ | N48: =$H$48*$K$48 -> 0 | R48: Facilities usage per person is entered in cell "K48" and the quantity is mapped as the sum of cells "H7 to H13"
C49: Port-a-John(s) | I49: x | J49: $ | L49: = | M49: $ | N49: =$H$49*$K$49 -> 0 | R49: The number of Port-a-John(s) is entered in cell "H49" and the cost for each in cell "K49"
R50: Additional Facility/Site Infrastructure cost description is entered in cell "C50" and the cost in cell "N50"
C51: TOTAL ESTIMATED FACILITY/SITE INFRASTRUCTURE COSTS | N51: =SUM($N$48:$N$50) -> 0 | R51: The Total Facility/Site Infrastructure cost is automatically calculated
B52: Contingency Fee
C54: Estimated Foods Costs | G54: $ | H54: =$N$14 -> 0 | I54: x | K54: 0.1 | M54: $ | N54: =$H$54*$K$54 -> 0 | R54: The Estimated Contingency Fee is automatically calculated as 10% of the Estimated Food Cost in cell "N54"
B55: TOTAL OPERATING ESTIMATED COSTS | M55: $ | N55: =$N$21+$N$28+$N$34+$N$40+$N$46+$N$51+$N$54 -> 0 | R55: The Total of the Estimated Operating Costs is automatically total in cell "N55
H56: Operating Unit Costs | M56: $ | N56: =$N$55/SUM($H$7:$H$13) -> #DIV/0! | R56: The per person Operating Cost is automatically calculated by dividing cell "N55" by the total of cells "H7 to H13"
A59: CALCULATING FEES:
A61: Ordeal Candidate | H61: Cost | K61: Total | N61: Fee to be Charged | R61: The cost for the Ordeal Induction materials is set by LEC policy
B62: Ordeal Sash, O/A Handbook, Amangamek-Wipit Flap Patch | G62: $ | H62: 25 | R62: These include ordeal Sash, O/A Handbook and Standard Lodge Flap
R63: The current amount of the O/A dues is entered in cell "H64"
B64: O/A Dues | G64: $ | H64: 12 | R64: The Liability Insurance Recovery for the event is entered in cell "H65"
B65: Liability Insurance Recovery | G65: $ | H65: 2 | K65: =SUM($H$62:$H$65) -> 39 | R65: The food cost is mapped from cell "K7"
B66: Food | G66: $ | H66: =$K$7 -> 0 | R66: The per person operating cost is mapped from cell "N56"
B67: Operating Cost | G67: $ | H67: =$N$56 -> #DIV/0! | R67: Additional Ordeal fee cost description is entered in cell "B68" and the cost in cell 'H68"
G68: $ | R68: The Estimated fee for Ordeal Candidate is automatically calculated
B69: Ordeal Candidate Fee | J69: $ | K69: =SUM($H$62:$H$68) -> #DIV/0! | M69: $ | R69: Use Cell "N69 to establish actual fee to be charged
A70: Elangomat | H70: Cost | K70: Total | R70: The cost for the Elangomat Patch is mapped from the Consignment worksheet "Consignment!D18"
B71: Elangomat Patch | G71: $ | H71: =Consignment!$D$18 -> 3 | R71: The Liability Insurance Recovery is mapped from cell "H65"
B72: Liability Insurance Recovery | G72: $ | H72: =$H$65 -> 2 | R72: The food cost is mapped from cell "K8"
B73: Food | G73: $ | H73: =$K$8 -> 0 | R73: The per person operating cost is mapped from cell "N56"
B74: Operating Cost | G74: $ | H74: =$N$56 -> #DIV/0! | R74: Additional Elangomat fee cost description is entered in cell "B75" and the cost in cell 'H75"
G75: $ | R75: The Estimated fee for Elangomat is automatically calculated
B76: Elangomat Fee | J76: $ | K76: =SUM($H$71:$H$75) -> #DIV/0! | M76: $ | R76: Use Cell "N77" to establish actual fee to be charged
A77: Member Fee | H77: Cost | K77: Total | P77: Day Only | R77: The Liability Insurance Recovery is mapped from cell "H65" (Day Participant only is automatically reduced to one day in cell "P78")
B78: Liability Insurance recovery | G78: $ | H78: =$H$65 -> 2 | P78: =$H$65/2 -> 1 | R78: The food cost is mapped from cell "K9" ("K10" for Day Participant Only)
B79: Food | G79: $ | H79: =$K$9 -> 0 | M79: $ | N79: =SUM($P$78:$P$79) -> 1 | P79: =$K$10 -> 0 | R79: The per person operating cost is mapped from cell "N56"
B80: Operating Cost | G80: $ | H80: =$N$56 -> #DIV/0! | R80: Additional Member fee cost description is entered in cell "B81" and the cost in cell 'H81"
G81: $ | P81: Day Only | R81: The Estimated fee for Member is automatically calculated
B82: Member Fee | J82: $ | K82: =SUM($H$78:$H$81) -> #DIV/0! | M82: $ | R82: Use Cell "N82"and "P82" to establish actual fee to be charged for Member and Day Participant
A83: Member Fee (Feast Only) | H83: Cost | K83: Total | R83: The Liability Insurance Recovery is mapped from cell "H65" and is automatically reduced to one day
B84: Liability Insurance recovery | G84: $ | H84: =$H$65/2 -> 1 | R84: The food cost is mapped from cell "K11"
B85: Food | G85: $ | H85: =$K$11 -> 0 | R85: Additional Member (Feast Only) fee cost description is entered in cell "B86" and the cost in cell 'H86"
G86: $ | R86: The Estimated fee for Member (Feast Only) is automatically calculated
B87: Member Fee | J87: $ | K87: =SUM($H$84:$H$86) -> 1 | M87: $ | R87: Use Cell "N87" to establish actual fee to be charged
A90: CALCULATING ESTIMATED BUDGET REVENUE:
A92: Registration Fees | F92: Quantity | H92: Fee | K92: Total | R92: The estimated attendees and registration fees are mapped from
B93: Ordeal Candidates | F93: =$H$7 -> 0 | G93: x | H93: =$N$69 -> 0 | I93: = | J93: $ | K93: =$F$93*$H$93 -> 0 | R93: cells "H7 and "N69"
B94: Elangomats | F94: =$H$8 -> 0 | G94: x | H94: =$N$76 -> 0 | I94: = | J94: $ | K94: =$F$94*$H$94 -> 0 | R94: cells "H8" and "N76"
B95: Members | F95: =$H$9 -> 0 | G95: x | H95: =$N$82 -> 0 | I95: = | J95: $ | K95: =$F$95*$H$95 -> 0 | R95: cells "H9" and "N82"
B96: Members (Day Only) | F96: =$H$10 -> 0 | G96: x | H96: =$P$82 -> 0 | I96: = | J96: $ | K96: =$F$96*$H$96 -> 0 | R96: cells "H10" and "P82"
B97: Feast Only | F97: =$H$11 -> 0 | G97: x | H97: =$N$87 -> 0 | I97: = | J97: $ | K97: =$F$97*$H$97 -> 0 | R97: cell's "H11" and "N87"
B98: =$B$12 -> 0 | F98: =$H$12 -> 0 | G98: x | I98: = | J98: $ | K98: =$F$98*$H$98 -> 0 | R98: cell's "H12" and the appropriate fee is entered in cell "H98"
B99: =$B$13 -> 0 | F99: =$H$13 -> 0 | G99: x | I99: = | J99: $ | K99: =$F$99*$H$99 -> 0 | R99: cells "H13" and the appropriate fee is entered in cell "H99"
C100: TOTAL Fee Based Revenue | J100: $ | K100: =SUM($K$93:$K$99) -> 0 | R100: The total fees by attendee is automatically calculated
R101: The total fee based revenue is automatically calculated
A102: Other Revenue Sources | K102: Total
B103: Chapter Contribution (Current Account Balance Reduction) | J103: $ | R103: If existing chapter funds are to be treated as "revenue" the amount is entered in cell "K112"
J104: $ | R104: Additional revenue description is entered in cell "B104 to B105" and the dollar amount in cell 'K104 to K105"
J105: $
C106: Total Other Revenue Sources | J106: $ | K106: =SUM($K$103:$K$105) -> 0 | R106: The Total Other Revenue is automatically calculated
B108: TOTAL ESTIMATED REVENUE | J108: $ | K108: =$K$100+$K$106 -> 0 | R108: The Total Estimated Revenue is automatically calculated
A111: BALANCING THE ESTIMATED BUDGET: | P111: Total
B113: Estimated Food Cost | O113: $ | P113: =$N$14 -> 0 | R113: The Estimated Food Cost is mapped from cell "N14"
B115: Estimated Postage Cost | O115: $ | P115: =$N$21 -> 0 | R115: The Estimated Postage Cost is mapped from cell "N21"
B117: Estimate Printing cost | O117: $ | P117: =$N$28 -> 0 | R117: The Estimated Printing Cost is mapped from cell "N28"
B119: Estimated Awards Cost | O119: $ | P119: =$N$34 -> 0 | R119: The Estimated Awards Cost is mapped from cell "N34"
B121: Estimated Ceremonies Cost | O121: $ | P121: =$N$40 -> 0 | R121: The Estimated Ceremonies Cost is mapped from cell "N40"
...

Sheet Consignment
A1: CHAPTER: | C1: ='OA Budget Planning-Report Sheet'!$B$5 -> Chapter Name (Number) | G1: REQUEST DATE: | L1: The request date for the consignment is entered into cell "I1"
L2: The chapter name is mapped from the OA Budget Planning-Report worksheet cell "OA Budget Planning-Report Sheet'!B5"
A3: EVENT NAME: | C3: ='OA Budget Planning-Report Sheet'!$B$3 -> Chapter Events (typical) | G3: EVENT DATES (start-end): | I3: ='OA Budget Planning-Report Sheet'!E4 -> Start | J3: ='OA Budget Planning-Report Sheet'!F4 -> End | L3: The event name is mapped from the OA Budget Planning-Report worksheet cell "OA Budget Planning-Report Sheet'!B3"
L4: The event date is mapped from the OA Budget Planning-Report worksheet cell "OA Budget Planning-Report Sheet'!F35"
A5: RECEIVED BY: | G5: RECEIVED:
A7: RETURNED BY: | G7: RETURNED:
L8: The prices listed are the Retail cost for each item (NOTE: the charge for the chapters is preset for Ordeal Inductions and Brotherhood Conversions by the LEC)
E9: Quantities | L9: The quantity of the items being request for consignment is entered into cells "E12" to "E43"
A10: Item Description | D10: Price | E10: Requested | F10: Received | G10: Ordeal | H10: Returned | I10: Used | J10: Sales | L10: The actual quantities received are entered in to cells "F12" to "F43"
D11: "Retail" | L11: The actual quantities used for the event are entered into the following
A12: Ordeal Sash (Regular) | D12: 16 | I12: =$F12-$G12-$H12 -> 0 | J12: =$D12*$I12 -> 0 | L12: Ordeal Sash (Regular) cell "G12"
A13: Ordeal Sash (Long) | D13: 16 | I13: =$F13-$G13-$H13 -> 0 | J13: =$D13*$I13 -> 0 | L13: Ordeal Sash (Long) cell "G13"
A14: OA Handbook | D14: 3.5 | I14: =$F14-$G14-$H14 -> 0 | J14: =$D14*$I14 -> 0 | L14: OA Handbook cell "G14"
A15: OA Lodge Flap | D15: 3 | I15: =$F15-$G15-$H15 -> 0 | J15: =$D15*$I15 -> 0 | L15: OA Lodge Flap cell "G15"
A16: Brotherhood Sash (Regular) | D16: 16 | I16: =$F16-$G16-$H16 -> 0 | J16: =$D16*$I16 -> 0 | L16: Brotherhood Sash (Regular) cell "G16"
A17: Brotherhood Sash (Long) | D17: 16 | I17: =$F17-$G17-$H17 -> 0 | J17: =$D17*$I17 -> 0 | L17: Brotherhood Sash (Long) cell "G17"
A18: Elangomat Patch | D18: 3 | I18: =$F18-$G18-$H18 -> 0 | J18: =$D18*$I18 -> 0 | L18: Elangomat Patch cell "G18"
A19: OA Pocket Device | D19: 3.8 | I19: =$F19-$G19-$H19 -> 0 | J19: =$D19*$I19 -> 0 | L19: The quantities returned are entered into cells "H12 to H42"
A20: OA Baseball Cap | D20: 18 | I20: =$F20-$G20-$H20 -> 0 | J20: =$D20*$I20 -> 0
A21: OA Hat Pin Silver Arrow | D21: 4.5 | I21: =$F21-$G21-$H21 -> 0 | J21: =$D21*$I21 -> 0
A22: OA Pewter Pin | D22: 4 | I22: =$F22-$G22-$H22 -> 0 | J22: =$D22*$I22 -> 0
A23: OA Jacket Emblem | D23: 6 | I23: =$F23-$G23-$H23 -> 0 | J23: =$D23*$I23 -> 0
A24: OA 3" Sticker | D24: 2 | I24: =$F24-$G24-$H24 -> 0 | J24: =$D24*$I24 -> 0
A25: OA Hat Pin | D25: 1.5 | I25: =$F25-$G25-$H25 -> 0 | J25: =$D25*$I25 -> 0
A26: Vigil Pin | D26: 4.5 | I26: =$F26-$G26-$H26 -> 0 | J26: =$D26*$I26 -> 0 | L26: The inventory of returned items is entered into cells "H12" to "H42"
A27: Ordeal Ceremony Book | D27: 5 | I27: =$F27-$G27-$H27 -> 0 | J27: =$D27*$I27 -> 0 | L27: The quaintly of the consignment items actually sold as part of a Trading Post is automatically calculated in cells "I12" to "I42"
A28: Brotherhood Ceremony Book | D28: 5 | I28: =$F28-$G28-$H28 -> 0 | J28: =$D28*$I28 -> 0 | L28: The total sales for each item is automatically calculated in cells "J12" to "J41"
D29: 0 | I29: =$F29-$G29-$H29 -> 0 | J29: =$D29*$I29 -> 0
D30: 0 | I30: =$F30-$G30-$H30 -> 0 | J30: =$D30*$I30 -> 0
D31: 0 | I31: =$F31-$G31-$H31 -> 0 | J31: =$D31*$I31 -> 0
D32: 0 | I32: =$F32-$G32-$H32 -> 0 | J32: =$D32*$I32 -> 0
D33: 0 | I33: =$F33-$G33-$H33 -> 0 | J33: =$D33*$I33 -> 0
D34: 0 | I34: =$F34-$G34-$H34 -> 0 | J34: =$D34*$I34 -> 0
D35: 0 | I35: =$F35-$G35-$H35 -> 0 | J35: =$D35*$I35 -> 0
D36: 0 | I36: =$F36-$G36-$H36 -> 0 | J36: =$D36*$I36 -> 0 | L36: The description of any additional consignment items is entered in the cells "A31" to "A41"
D37: 0 | I37: =$F37-$G37-$H37 -> 0 | J37: =$D37*$I37 -> 0 | L37: The price for the additional items is entered in the cells "D31" to" D41"
D38: 0 | I38: =$F38-$G38-$H38 -> 0 | J38: =$D38*$I38 -> 0
D39: 0 | I39: =$F39-$G39-$H39 -> 0 | J39: =$D39*$I39 -> 0
D40: 0 | I40: =$F40-$G40-$H40 -> 0 | J40: =$D40*$I40 -> 0
D41: 0 | I41: =$F41-$G41-$H41 -> 0 | J41: =$D41*$I41 -> 0
A42: Field Receipt Book | D42: n/c | L42: At least one (1) receipt book should be requested to use for on-site registrations
A43: Spirit of the Arrow Booklets (1-8) | D43: n/c
B45: Total Sales to charged to Account # 1-2371-419-00 OA Trading Post Sales | J45: =SUM($J$12:$J$42) -> 0 | L45: The total Trading Post sales of consignment items is automatically calculated
A48: The Trading Post consignment must be closed and returned within 30 days of the Activity

Sheet Registrations
A1: CHAPTER: | E1: ='OA Budget Planning-Report Sheet'!$B$5 -> Chapter Name (Number) | O1: The chapter name is mapped from the OA Budget Planning-Report worksheet cell "OA Budget Planning-Report Sheet'!B5"
A3: RECEIPTS
G4: Registrations
I5: Council | K5: On-Site
A6: Name | C6: Role | G6: Receipt # | I6: Amount | K6: Check | M6: Cash | AE6: Select Role
H7: $ | J7: $ | L7: $ | O7: There are six columns for recording event receipts | AE7: Adviser
H8: $ | J8: $ | L8: $ | O8: The first column is for Name of the Registrants, each registrant is listed separately and NOT combined under the name of the Payee if the payment is by check | AE8: Ceremony Team
H9: $ | J9: $ | L9: $ | O9: The name of the registrant is entered in the cells "A7" to "A104" | AE9: Cook Crew
H10: $ | J10: $ | L10: $ | O10: The role of the registrant is selected from the drop down menu in cells "E7" to "E104" | AE10: Day Participant
H11: $ | J11: $ | L11: $ | O11: The "Receipt" column is where the receipt number from the council receipt is entered or the receipt number from the Filed Receipt Book is entered | AE11: Elangomat
H12: $ | J12: $ | L12: $ | AE12: Feast Only
H13: $ | J13: $ | L13: $ | AE13: Health & Safety
H14: $ | J14: $ | L14: $ | AE14: Ordeal Candidate
H15: $ | J15: $ | L15: $ | O15: The next columns are for recording the fee paid (i.e. pre-paid at Council or paid On-Site | AE15: Ordeal Master
H16: $ | J16: $ | L16: $ | O16: These can be either checks or cash | AE16: Participant
H17: $ | J17: $ | L17: $ | O17: The name of the registrant is entered in cells "G6" to "G104" | AE17: Staff Adviser
H18: $ | J18: $ | L18: $ | O18: The registration fee paid is entered as follows | AE18: Non-Member
H19: $ | J19: $ | L19: $ | O19: The registration fee paid is entered as follows
H20: $ | J20: $ | L20: $ | O20: pre-paid in cells "I7" to "I104"
H21: $ | J21: $ | L21: $ | O21: checks in cells "K7" to "K104"
H22: $ | J22: $ | L22: $ | O22: cash in cells "M7" too "M104"
H23: $ | J23: $ | L23: $
H24: $ | J24: $ | L24: $
H25: $ | J25: $ | L25: $ | O25: ='Final Closeout'!$K$5 -> 0 | P25: =COUNTIF($I$7:$M$98,$O$25) -> 0 | Q25: =$O$25*$P$25 -> 0 | R25: =$P$25+$P$26 -> 0 | S25: =$O$25*$R$25 -> 0
H26: $ | J26: $ | L26: $ | Q26: =$O$26*$P$26 -> 0 | T26: Ordeal Candidates w/ Late Fee
H27: $ | J27: $ | L27: $ | O27: ='Final Closeout'!$K$6 -> 0 | P27: =COUNTIF($I$7:$M$98,$O$27) -> 0 | Q27: =$O$27*$P$27 -> 0 | R27: =$P$27+$P$28 -> 0 | S27: =$O$27*$R$27 -> 0
H28: $ | J28: $ | L28: $ | Q28: =$O$28*$P$28 -> 0 | T28: Elangomats w/ Late Fees
H29: $ | J29: $ | L29: $ | O29: ='Final Closeout'!$K$7 -> 0 | P29: =COUNTIF($I$7:$M$98,$O$29) -> 0 | Q29: =$O$29*$P$29 -> 0 | R29: =$P$29+$P$30 -> 0 | S29: =$O$29*$R$29 -> 0
H30: $ | J30: $ | L30: $ | Q30: =$O$30*$P$30 -> 0 | T30: Members w/ Late Fees
H31: $ | J31: $ | L31: $ | O31: ='Final Closeout'!$K$8 -> 0 | P31: =COUNTIF($I$7:$M$98,$O$31) -> 0 | Q31: =$O$31*$P$31 -> 0 | R31: =$P$31+$P$32 -> 0 | S31: =$O$31*$R$31 -> 0
H32: $ | J32: $ | L32: $ | Q32: =$O$32*$P$32 -> 0 | T32: Day Participants w/ Late Fees
H33: $ | J33: $ | L33: $ | O33: ='Final Closeout'!$K$9 -> 0 | P33: =COUNTIF($I$7:$M$98,$O$33) -> 0 | Q33: =$O$33*$P$33 -> 0 | R33: =$P$33+$P$34 -> 0 | S33: =$O$33*$R$33 -> 0
H34: $ | J34: $ | L34: $ | Q34: =$O$34*$P$34 -> 0 | T34: Feast Only w/ Late Fees
H35: $ | J35: $ | L35: $ | O35: ='Final Closeout'!$K$10 -> 0 | P35: =COUNTIF($I$7:$M$98,$O$35) -> 0 | Q35: =$O$35*$P$35 -> 0 | R35: =$P$35+$P$36 -> 0 | S35: =$O$35*$R$35 -> 0
H36: $ | J36: $ | L36: $ | Q36: =$O$36*$P$36 -> 0
H37: $ | J37: $ | L37: $ | O37: ='Final Closeout'!$K$11 -> 0 | P37: =COUNTIF($I$7:$M$98,$O$37) -> 0 | Q37: =$O$37*$P$37 -> 0 | R37: =$P$37+$P$38 -> 0 | S37: =$O$37*$R$37 -> 0
H38: $ | J38: $ | L38: $ | Q38: =$O$38*$P$38 -> 0
H39: $ | J39: $ | L39: $
H40: $ | J40: $ | L40: $ | O40: ='Final Closeout'!$K$14 -> 0 | R40: =$P$26+$P$28+$P$30+$P$32+P34+P36+P38 -> 0 | S40: =$O$40*$R$40 -> 0 | T40: Late Fees
H41: $ | J41: $ | L41: $ | O41: Totals | P41: =SUM($P$25:$P$40) -> 0 | Q41: =SUM($Q$25:$Q$40) -> 0 | S41: =SUM($S$25:$S$40) -> 0
H42: $ | J42: $ | L42: $
H43: $ | J43: $ | L43: $
H44: $ | J44: $ | L44: $
H45: $ | J45: $ | L45: $
H46: $ | J46: $ | L46: $ | O46: Ordeal Candidate | Q46: =COUNTIF($C$7:$E$98,$O$46) -> 0
H47: $ | J47: $ | L47: $ | O47: Elangomat | Q47: =COUNTIF($C$7:$E$98,$O$47) -> 0
H48: $ | J48: $ | L48: $ | O48: Member | Q48: =Q55+Q56+Q57+Q61+Q63+Q64+Q65 -> 0
H49: $ | J49: $ | L49: $ | O49: Day Participant | Q49: =COUNTIF($C$7:$E$98,$O$49) -> 0
H50: $ | J50: $ | L50: $ | O50: Feast Only | Q50: =COUNTIF($C$7:$E$98,$O$50) -> 0
H51: $ | J51: $ | L51: $ | O51: Non-member | Q51: =COUNTIF($C$7:$E$98,$O$46) -> 0
H52: $ | J52: $ | L52: $ | O52: Total Registrations | Q52: =COUNTA($A$7:$B$98) -> 0
H53: $ | J53: $ | L53: $
H54: $ | J54: $ | L54: $ | O54: Roles | R54: Description
H55: $ | J55: $ | L55: $ | O55: Adviser | Q55: =COUNTIF($C$7:$E$98,$O$55) -> 0 | R55: There is only One Adviser for the Event
H56: $ | J56: $ | L56: $ | O56: Ceremony Team | Q56: =COUNTIF($C$7:$E$98,$O$56) -> 0 | R56: Members Youth & Adult who participate or advise
H57: $ | J57: $ | L57: $ | O57: Cook Crew | Q57: =COUNTIF($C$7:$E$98,$O$57) -> 0 | R57: Members Youth & Adult who participate or advise
H58: $ | J58: $ | L58: $ | O58: Day Participant | Q58: =COUNTIF($C$7:$E$98,$O$58) -> 0 | R58: Member who attends the event for the Day Only
H59: $ | J59: $ | L59: $ | O59: Elangomat | Q59: =COUNTIF($C$7:$E$98,$O$59) -> 0 | R59: Members Youth & Adult who participate in this Role
H60: $ | J60: $ | L60: $ | O60: Feast Only | Q60: =COUNTIF($C$7:$E$98,$O$60) -> 0 | R60: Members who attends the event for the Fellowship Feast Only
H61: $ | J61: $ | L61: $ | O61: Health & Safety | Q61: =COUNTIF($C$7:$E$98,$O$61) -> 0 | R61: Members Youth & Adult who participate or advise
H62: $ | J62: $ | L62: $ | O62: Ordeal Candidate | Q62: =COUNTIF($C$7:$E$98,$O$62) -> 0
H63: $ | J63: $ | L63: $ | O63: Ordeal Master | Q63: =COUNTIF($C$7:$E$98,$O$63) -> 0 | R63: This is a Youth Only Role; there may be one or more
H64: $ | J64: $ | L64: $ | O64: Participant | Q64: =COUNTIF($C$7:$E$98,$O$64) -> 0 | R64: Member attending the event
H65: $ | J65: $ | L65: $ | O65: Staff Adviser | Q65: =COUNTIF($C$7:$E$98,$O$65) -> 0 | R65: This is the District Executive(s) or Chapter Staff Adviser(s)
H66: $ | J66: $ | L66: $ | O66: Non-Member | Q66: =COUNTIF($C$7:$E$98,$O$66) -> 0 | R66: Participants who are NOT members or in the Lodge membership database
H67: $ | J67: $ | L67: $ | Q67: =SUM($Q$55:$Q$66) -> 0
H68: $ | J68: $ | L68: $
H69: $ | J69: $ | L69: $
H70: $ | J70: $ | L70: $
H71: $ | J71: $ | L71: $
H72: $ | J72: $ | L72: $
H73: $ | J73: $ | L73: $
H74: $ | J74: $ | L74: $
H75: $ | J75: $ | L75: $
H76: $ | J76: $ | L76: $
H77: $ | J77: $ | L77: $
H78: $ | J78: $ | L78: $
H79: $ | J79: $ | L79: $
... H97: $ | J97: $ | L97: $
H98: $ | J98: $ | L98: $ | O98: The total receipts from the Council Office is automatically calculated in cell "E135"
A99: Totals | H99: $ | I99: =SUM($I$7:$I$98) -> 0 | J99: $ | K99: =SUM($K$7:$K$98) -> 0 | L99: $ | M99: =SUM($M$7:$M$98) -> 0 | O99: The checks received On Site are totaled in cell "K135"
O100: The total cash received On Site is totaled in cell "M135"
E101: Total Registrations through Council | J101: $ | K101: =$I$99 -> 0 | O101: The receipts from Council Office is mapped from cell "E137"
E102: Total Registrations On-Site (Checks) | J102: $ | K102: =$K$99 -> 0 | O102: The total checks received On Site is mapped from cell "K138"
E103: Total Registrations On-Site (Cash) | J103: $ | K103: =$M$99 -> 0 | O103: The total cash received On Site is mapped from cell "M139"
E104: Total Receipts | L104: $ | M104: =SUM($K$101:$K$103) -> 0 | O104: The total receipts are automatically calculated in cell "M140"

Sheet Reimbursements-Refunds
A1: CHAPTER: | E1: ='OA Budget Planning-Report Sheet'!$B$5 -> Chapter Name (Number) | O1: The chapter name is mapped from the OA Budget Planning-Report worksheet cell "OA Budget Planning-Report Sheet'!B5"
A3: REIMBURSEMENTS
A4: Name | E4: Address | M4: Amount | O4: If there are any Disbursements (Reimbursements) due for event expenses
L5: $ | O5: The name of the person is entered into cell "A5, A7, A9" etc
O6: The mailing address is entered in cells "E5-E6", "E7-E9", "E10-E11" etc
L7: $ | O7: The amount of the Disbursement (Reimbursement) is entered into cell "M5", "M7". "M9", etc
O8: This is repeated as necessary by filling in the required information in the gray shaded cells as follows
L9: $
L11: $
L13: $
L15: $
O16: Additional rows are available in intervals of 10 rows by selecting the "+" symbol on the left side of the page
L17: $
L19: $
L21: $
L23: $
L25: $
L27: $
L29: $
L31: $
L33: $
L35: $
L37: $
L39: $
... L49: $
F51: Total Reimbursements | L51: $ | M51: =SUM($M$5:$M$50) -> 0 | O51: The Total Disbursements (Reimbursements) are automatically calculated
A53: REFUNDS
A54: Name | E54: Address | M54: Amount | O54: If there are any Disbursements (Refunds) due for event expenses
L55: $ | O55: The name of the person is entered into cell "A55, A57, A59" etc
O56: The mailing address is entered in cells "E55-E56", "E57-E59", "E60-E61" etc
L57: $ | O57: The amount of the Disbursement (Reimbursement) is entered into cell "M55", "M57". "M59", etc
O58: This is repeated as necessary by filling in the required information in the gray shaded cells as follows
L59: $
L61: $
L63: $
L65: $ | O65: Additional rows are available in intervals of 10 rows by selecting the "+" symbol on the left side of the page
L67: $
L69: $
L71: $
L73: $
L75: $
L77: $
L79: $
L81: $
L83: $
L85: $
L87: $
L89: $
... L99: $
F101: Total Refunds | L101: $ | M101: =SUM($M$55:$M$100) -> 0 | O101: The Total Disbursements (Refunds) are automatically calculated and mapped to Final Closeout K82

Sheet Final Closeout
A1: CHAPTER: | D1: ='OA Budget Planning-Report Sheet'!B5 -> Chapter Name (Number) | K1: Account #: | N1: ='OA Budget Planning-Report Sheet'!B7 -> Custodial Account | R1: The chapter name is mapped from the OA Budget Planning-Report worksheet cell "OA Budget Planning-Report Sheet'!B5"
R2: The chapter account # is mapped from the OA Budget Planning-Report worksheet cell "OA Budget Planning-Report Sheet'!B7"
A3: CALCULATING ACTUAL REVENUE
H4: Quantity | K4: Cost | N4: Total
B5: Ordeal Candidates | I5: x | J5: $ | K5: ='Estimated Budget'!$N$69 -> 0 | L5: = | M5: $ | N5: =$H$5*$K$5 -> 0 | R5: The number of registrants by attendee category is entered into cells "H5" to "H11"
B6: Elangomats | I6: x | J6: $ | K6: ='Estimated Budget'!$N$76 -> 0 | L6: = | M6: $ | N6: =$H$6*$K$6 -> 0 | R6: The fee/cost is mapped from the Estimated Budget worksheet
B7: Members | I7: x | J7: $ | K7: ='Estimated Budget'!$N$82 -> 0 | L7: = | M7: $ | N7: =$H$7*$K$7 -> 0 | R7: cells "H5" through "H11"
B8: Members (Day Only) | I8: x | J8: $ | K8: ='Estimated Budget'!$P$82 -> 0 | L8: = | M8: $ | N8: =$H$8*$K$8 -> 0
B9: Feast Only | I9: x | J9: $ | K9: ='Estimated Budget'!$N$87 -> 0 | L9: = | M9: $ | N9: =$H$9*$K$9 -> 0
B10: ='Estimated Budget'!B98:E98 -> 0 | I10: x | J10: $ | K10: ='Estimated Budget'!$K$98 -> 0 | L10: = | M10: $ | N10: =$H$10*$K$10 -> 0
B11: ='Estimated Budget'!B99:E99 -> 0 | I11: x | J11: $ | K11: ='Estimated Budget'!$K$99 -> 0 | L11: = | M11: $ | N11: =$H$11*$K$11 -> 0 | R11: Any Miscellaneous Income is entered as follows
I12: x | J12: $ | L12: = | M12: $ | N12: =$H$12*$K$12 -> 0 | R12: The description of the Miscellaneous Income in cells "B12" to "B13"
I13: x | J13: $ | L13: = | M13: $ | N13: =$H$13*$K$13 -> 0 | R13: As a quantity of "1" in cells "H12" to "H13"
B14: Late Fee | I14: x | J14: $ | L14: = | M14: $ | N14: =$H$14*$K$14 -> 0 | R14: The amount received in cells "K12" to "K13"
B15: REVENUE | M15: $ | N15: =SUM($N$5:$N$14) -> 0 | R15: The categories of revenue are automatically totaled and the Total Revenue is calculated in cell "N15"
A16: CALCULATING ACTUAL EXPENSES
B17: Food | E17: [attach all original receipts] | K17: Cost
J18: $
J19: $
J20: $
J21: $
J22: $
J23: $ | R23: Each receipt for Food is listed in cells "C18" to "C28"
J24: $ | R24: and the corresponding receipt total is listed in cells "K18" to "K28"
J25: $
J26: $
J27: $
J28: $
C29: TOTAL ACTUAL FOOD COSTS | M29: $ | N29: =SUM($K$18:$K$28) -> 0 | R29: The Total Actual Foods Cost is totaled in cell "N29"
B30: Postage | E30: [attach all original receipts] | K30: Cost
J31: $
J32: $ | R32: Each receipt for Postage is listed in cells "C31" to "C34"
J33: $ | R33: and the corresponding receipt total is listed in cells "K31" to "K34"
J34: $ | R34: The Total Actual Postage Cost is totaled in cell "N35"
C35: TOTAL ACTUAL POSTAGE COSTS | M35: $ | N35: =SUM($K$31:$K$34) -> 0
B36: Printing | E36: [attach all original receipts] | K36: Cost
J37: $ | R37: Each receipt for Printing is listed in cells "C37" to "C40"
J38: $ | R38: and the corresponding receipt total is listed in cells "K37" to "K40"
J39: $ | R39: The Total Actual Printing Cost is totaled in cell "N41"
J40: $
C41: TOTAL ACTUAL PRINTING COSTS | M41: $ | N41: =SUM($K$37:$K$40) -> 0
B42: Awards | E42: [attach all original receipts] | K42: Cost
J43: $
J44: $
J45: $ | R45: Each receipt for Awards is listed in cells "C43" to "C48"
J46: $ | R46: and the corresponding receipt total is listed in cells "K43" to "K48"
J47: $ | R47: The Total Actual Awards Cost is totaled in cell "N49"
J48: $
C49: TOTAL ACTUAL AWARDS COSTS | M49: $ | N49: =SUM($K$43:$K$48) -> 0
B50: Ceremonies | E50: [attach all original receipts] | K50: Cost
J51: $
J52: $
J53: $ | R53: Each receipt for Ceremonies is listed in cells "C51" to "C56"
J54: $ | R54: and the corresponding receipt total is listed in cells "K51" to "K56"
J55: $ | R55: The Total Actual Ceremonies Cost is totaled in cell "N57"
J56: $
C57: TOTAL ACTUAL CEREMONIES COSTS | M57: $ | N57: =SUM($K$51:$K$56) -> 0
B58: Health & Safety | F58: [attach all original receipts] | K58: Cost
J59: $ | R59: Each receipt for Health & Safety is listed in cells "C59" to "C62"
J60: $ | R60: and the corresponding receipt total is listed in cells "K59" to "K62"
J61: $ | R61: The Total Actual Facility/Site Infrastructure Cost is totaled in cell "N63"
J62: $
C63: TOTAL ACTUAL HEALTH & SAFETEY COSTS | M63: $ | N63: =SUM($K$59:$K$62) -> 0
B64: Facility/Site Infrastructure | F64: [attach all original receipts] | K64: Cost
F65: Facility Usage Fee | J65: $ | R65: 679"
F66: Port-a-John(s) | J66: $ | R66: and the corresponding receipt total is listed in cells "K65" to "K69"
J67: $ | R67: NOTE: if the facility Usage Fee and/or the Port-a-John(s) cost are not a "reimbursement"
J68: $ | R68: then the dollar amount is listed under "Checks issued by Council Finance Office
J69: $
C70: TOTAL ACTUAL FACILITY/SITE INFRASTRUCTURE COSTS | M70: $ | N70: =SUM($K$65:$K$69) -> 0 | R70: The Total Actual Facility/Site Infrastructure Cost is totaled in cell "N70"
B71: Total Disbursement (Reimbursements)
C72: TOTAL ACTUAL DISBURSEMENTS (REIMBURSEMENTS) | M72: $ | N72: =SUM($N$29:$N$70) -> 0 | R72: The Actual Total of Disbursements (Reimbursements) equal balance in cell "Reimbursements-Refunds'!M101"
B73: Checks issued by Council Finance Office
F74: Facility Usage Fee | J74: $
F75: Port-a-John(s) | J75: $ | R75: The Actual Total of Invoices to be paid by Council Finance Office
J76: $
J77: $ | N77: =SUM(K74:K77) -> 0
C78: Total Refund Checks paid by Council Finance Office | M78: $ | N78: ='Reimbursements-Refunds'!$M$101 -> 0 | R78: The Actual Total of Refunds to be paid by Council Finance Office
C79: TOTAL ACTUAL CHECKS FROM COUNCIL FINANCE OFFICE | M79: $ | N79: =SUM($K$74:$K$78) -> 0
B80: Ordeal Candidates | F80: Quantity | H80: Cost | K80: Total | R80: The event specific supplies are mapped as follows
C81: Ordeal Sash (Regular) | F81: =Consignment!$G$12 -> 0 | R81: Ordeal Sash (Regular) quantity calculated as indicated in the comment attached to cell"F81" and Cost is mapped from "Consignment!D12"
C82: Ordeal Sash (Long) | F82: =Consignment!$G$13 -> 0 | R82: Ordeal Sash (Long) quantity calculated as indicated in the comment attached to cell "F82" and Cost is mapped from "Consignment!D13" and totaled automatically
C83: O/A Handbook | F83: =Consignment!$G$14 -> 0 | R83: O/A Handbook quantity calculated as indicated in the comment attached to cell"F83" and Cost is mapped from "Consignment!D14" and totaled automatically
C84: Amangamek-Wipit Flap | F84: =Consignment!$G$15 -> 0 | R84: Amangamek-Wipit Flap quantity calculated as indicated in the comment attached to cell"F84" and Cost is mapped from "Consignment!D15" and totaled automatically
F85: =SUM($F$81:$F$84)/3 -> 0 | G85: x | H85: ='Estimated Budget'!$K$127 -> 18 | I85: = | J85: $ | K85: =$F$85*$H$85 -> 0 | M85: $ | N85: =$K$85 -> 0 | R85: The Total Ordeal Candidates Cost is totaled in cell "N85"
B86: Brotherhood Candidates | F86: Quantity | H86: Cost | K86: Total
C87: Brotherhood Sash (Regular) | F87: =Consignment!$G$16 -> 0 | R87: Brotherhood Sash (Regular) quantity calculated as indicated in the comment attached to cell "F87" and Cost is mapped from "Consignment!D16" and totaled automatically
C88: Brotherhood Sash (Long) | F88: =Consignment!$G$17 -> 0 | R88: Brotherhood Sash (Long) quantity calculated as indicated in the comment attached to cell "F88" and Cost is mapped from "Consignment!D17" and totaled automatically
F89: =SUM(F87:F88) -> 0 | G89: x | H89: ='Estimated Budget'!$K$132 -> 14 | I89: = | J89: $ | K89: =$F$89*$H$89 -> 0 | M89: $ | N89: =$K$89 -> 0 | R89: The Total Brotherhood Candidates Cost is totaled in cell "N89"
B90: Elangomats | F90: Quantity | H90: Cost | K90: Total
C91: Elangomat Patch | F91: =Consignment!$G$18 -> 0 | G91: x | H91: =Consignment!$D$18 -> 3 | I91: = | J91: $ | K91: =$F$91*$H$91 -> 0 | M91: $ | N91: =$K$91 -> 0 | R91: Elangomat Patch quantity is calculated as indicated in the comment attached to cell"F91" and Cost is mapped from "Consignment!D18" and totaled automatically
B92: Insurance Recovery | F92: Quantity | H92: Cost | K92: Total | R92: The event Liability Insurance Recovery is mapped as follows
C93: Ordeal Candidates / Elangomats / Members | F93: =$H$5+$H$6+$H$7+$H$10+$H$105 -> 0 | G93: x | H93: ='Estimated Budget'!H65 -> 2 | I93: = | J93: $ | K93: =($F$93-$F$94+$F$95)*$H$93 -> 0 | R93: The quantity is mapped from the sum of cells "H5", "H6", and "H7" and the Cost is mapped from cell "Estimated Budget'!H65" and totaled automatically
C94: No Shows Ordeal Candidates / Elangomats / Members | R94: The number of "no shows" are entered in cell "F94" (i.e. pre-registrations that do not attend the event)
C95: Non-members
C96: Members (Day Only) | F96: =$H$8 -> 0 | G96: x | H96: ='Estimated Budget'!H78/2 -> 1 | I96: = | J96: $ | K96: =$F$96*$H$96 -> 0 | R96: The quantity is mapped from cell "H8"and the Cost is mapped from cell "Estimated Budget'!P87" and totaled automatically
C97: Feast Only | F97: =$H$9 -> 0 | G97: x | H97: ='Estimated Budget'!H84 -> 1 | I97: = | J97: $ | K97: =$F$97*$H$97 -> 0 | M97: $ | N97: =SUM($K$93:$K$97) -> 0 | R97: The quantity is mapped from cell "H9"and the Cost is mapped from cell "Estimated Budget'!H8" and totaled automatically
B98: Dues | F98: Quantity | H98: Cost | K98: Total | R98: The event OA Dues is mapped as follows
C99: Candidates O/A Dues | F99: =$H$5 -> 0 | G99: x | H99: ='Estimated Budget'!H64 -> 12 | I99: = | J99: $ | K99: =($F$99-$F$100)*$H$99 -> 0 | M99: $ | N99: =$K$99 -> 0 | R99: The quantity is mapped from cell "H5"and the Cost is mapped from cell "Estimated Budget'!H64" and totaled automatically
C100: No Shows Candidates | R100: The number of ordeal candidate "no shows" are entered in cell "F100" (i.e. pre-registrations that do not attend the event)
...
