Workbook

Sheet Hardware
A1: Exhibit B continued
A3: Item | B3: Description | C3: Unit Price (List) | D3: Extended Price | E3: % discount
A4: 5060B002 | B4: CR-135i, 135cpm Canon Check Scanner | C4: 2795 | D4: 2347.8 | E4: =1-SUM(D4/C4) -> 0.16
A5: 4605B002 | B5: CR-190i, 190cpm Canon Check Scanner | C5: 3495 | D5: 2621.25 | E5: =1-SUM(D5/C5) -> 0.25
A6: 5367B002 | B6: CR-50, 50cpm Canon Check Scanner | C6: 795 | D6: =C6*0.75 -> 596.25 | E6: =1-SUM(D6/C6) -> 0.25
A7: 5368B002 | B7: CR-80, 80cpm Canon Check Scanner | C7: 995 | D7: =C7*0.75 -> 746.25 | E7: =1-SUM(D7/C7) -> 0.25
A8: 5005B002 | B8: DR-C125, 25ppm/50ipm Canon Color Scanner | C8: 495 | D8: =C8*0.84 -> 415.8 | E8: =1-SUM(D8/C8) -> 0.16
A9: 6583B002 | B9: DR-C130, 30ppm/60ipm Canon Color Scanner | C9: 595 | D9: =C9*0.84 -> 499.8 | E9: =1-SUM(D9/C9) -> 0.16
A10: 3923B002 | B10: DR-2020U, 20ppm/40ipm Canon Color Scanner | C10: 695 | D10: 583.8 | E10: =1-SUM(D10/C10) -> 0.16
A11: 3093B002 | B11: DR-3010C, 30ppm Canon Color Scanner | C11: 1095 | D11: 766.5 | E11: =1-SUM(D11/C11) -> 0.3
A12: 5482B002 | B12: DR-M140, 40ppm/80ipm Canon Color Scanner | C12: 1195 | D12: =C12*0.7 -> 836.5 | E12: =1-SUM(D12/C12) -> 0.3
A13: 5483B002 | B13: DR-M160, 60ppm/120ipm Canon Color Scanner | C13: 1295 | D13: =C13*0.7 -> 906.5 | E13: =1-SUM(D13/C13) -> 0.3
A14: 3801B002 | B14: DR-6010C, 60ppm/ 120ipm Canon Color Scanner | C14: 3495 | D14: 2446.5 | E14: =1-SUM(D14/C14) -> 0.3
A15: 4624B002 | B15: DR-6030C, 80ppm/160ipm Canon Color Scanner | C15: 4495 | D15: 3011.65 | E15: =1-SUM(D15/C15) -> 0.33
A16: 8074B002 | B16: DR-G1100, 100 ppm / 200ipm Canon Color Scanner | C16: 6775 | D16: 4742.5 | E16: =1-SUM(D16/C16) -> 0.3
A17: 8073B002 | B17: DR-G1130, 130ppm/260ipm Canon Color Scanner | C17: 9975 | D17: 6982.5 | E17: =1-SUM(D17/C17) -> 0.3
A18: 2417B002 | B18: DR-X10C, 128ppm/256ipm Canon Color Scanner | C18: 17995 | D18: 17200 | E18: =1-SUM(D18/C18) -> 0.044178939
A19: 0088T050 | B19: P-150 Canon Color Scanner | C19: 295 | D19: 265.5 | E19: =1-SUM(D19/C19) -> 0.1
A20: 4575B002 | B20: ScanFront 300P 30ppm/60ipm Scanner | C20: 2295 | D20: =C20*0.8 -> 1836 | E20: 0.2
A21: 4574B002 | B21: ScanFront 300 30ppm/60ipm Scanner | C21: 1995 | D21: =C21*0.8 -> 1596 | E21: 0.2
A22: 4575B007 | B22: ScanFront 300P CAC/PIV 30ppm/60ipm Scanner | C22: 2695 | D22: =C22*0.8 -> 2156 | E22: 0.2
A23: 4574B007 | B23: ScanFront 300 CAC/PIV 30ppm/60ipm Scanner | C23: 2395 | D23: =C23*0.8 -> 1916 | E23: 0.2
A24: 3324B001 | B24: ScanFront 220eP 24ppm/26ipm Scanner | C24: 3195 | D24: =C24*0.8 -> 2556 | E24: 0.2
A25: 3323B001 | B25: ScanFront 220e 24ppm/26ipm Scanner | C25: 2995 | D25: =C25*0.8 -> 2396 | E25: 0.2
A26: 4009B001 | B26: 6050/7550/9050/G1100/G1130 Exch Roller Kit | C26: 74 | D26: 55.5 | E26: 0.25
A27: 8927A004 | B27: 6080/7580/9080 Exch Roller Kit | C27: 74 | D27: 55.5 | E27: 0.25
A28: 4623B001 | B28: CR-190i,135i Exch. Roller Kit | C28: 59 | D28: 44.25 | E28: 0.25
A29: 1541B001 | B29: DR-1210C Feed Roller Unit | C29: 45 | D29: 33.75 | E29: 0.25
A30: 4048B001 | B30: DR-2020U Feed Roller Unit | C30: 53 | D30: 39.75 | E30: =1-SUM(D30/C30) -> 0.25
A31: 4048B001 | B31: DR-2020U, 20ppm/40ipm Feed Roller Unit, DR--2020U | C31: 53 | D31: 39.75 | E31: 0.25
A32: 7982A001 | B32: DR-2050C/2080C Exch Roller Kit | C32: 49 | D32: 36.75 | E32: 0.25
A33: 0106B002 | B33: DR-2580C Exch Roller Kit | C33: 63 | D33: 50.4 | E33: 0.2
A34: 0106B002 | B34: DR-2580C, 25ppm/50ipm Exch Roller Kit, DR-2580C | C34: 63 | D34: 50.4 | E34: 0.2
A35: 3335B001 | B35: DR-3010C Exchange Roller Kit | C35: 49 | D35: 34.3 | E35: 0.3
A36: 3335B001 | B36: DR-3010C, 30ppm Exchange Roller Kit, 3010C | C36: 49 | D36: 34.3 | E36: 0.3
A37: 4082B004 | B37: DR-4010/6010C Exch Roller Kit | C37: 74 | D37: 55.5 | E37: 0.25
A38: 4082B004 | B38: DR-4010C, 40ppm/80ipm Exch Roller Kit 4010/6010C | C38: 74 | D38: 59.2 | E38: 0.2
A39: 3651A003 | B39: DR-4080U Exchange Roller Kit | C39: 399 | D39: 299.25 | E39: 0.25
A40: 0434B002 | B40: DR-5010/6030 Exchange Roller Kit | C40: 74 | D40: 59.2 | E40: 0.2
A41: 0042T396 | B41: DR-5020/5080 Exchange Roller Kit | C41: 78 | D41: 62.4 | E41: 0.2
A42: 4082B004 | B42: DR-6010C, 60ppm/ 120ipm Exch Roller Kit 4010/6010C | C42: 74 | D42: 59.2 | E42: 0.2
... A127: 100-000-110 | B127: BIS Cloud Kiosk Scanning Appliance - Platinum Lease + Support | C127: 333 | D127: 300 | E127: 0.099099099
A128: 101104 | B128: ProStor InfiniVault Model 3 -- System Controller, 700GB Online Area, 3 RDX slots | C128: 9995 | D128: 8995.5 | E128: 0.1
A129: 101796 | B129: ProStor InfiniVault Model 5 -- System Controller, 1.8TB Online Area, 5 RDX slots | C129: 14995 | D129: 13495.5 | E129: 0.1
A130: 101099 | B130: ProStor InfiniVault Model 30 - - System Controller with 3.7TB Online Area- Removable Disk Unit (RDU), 10 RDX slots | C130: 29995 | D130: 26995.5 | E130: 0.1
A131: 111467 | B131: ProStor InfiniVault Model 35 - - System Controller with 5.6TB Online Area- Removable Disk Unit (RDU), 10 RDX slots | C131: 34995 | D131: 31495.5 | E131: 0.1
A132: 101080 | B132: ProStor InfiniVault Model 100 - - System Controller- 13TB Online Area- Two Removable Disk Units (RDU), 20 RDX slots | C132: 69995 | D132: 62995.5 | E132: 0.1
A133: 101083 | B133: ProStor InfiniVault Expansion Removable Disk Unit, 3U component with10 RDX slots | C133: 6995 | D133: 6295.5 | E133: 0.1
A134: 101615 | B134: 5 pack of 500 GB cartridges | C134: 1245 | D134: 1120.5 | E134: 0.1
A135: 101909 | B135: 5 pack of 640 GB cartridges | C135: 1495 | D135: 1345.5 | E135: 0.1
A136: 101966 | B136: 5 pack of 1 TB cartridges | C136: 1995 | D136: 1795.5 | E136: 0.1
A137: 101792 | B137: FileStore Data Migrator for InfiniVault. | C137: 3000 | D137: 2700 | E137: 0.1
A138: 101642 | B138: ProStor InfiniVault DICOM Model 3 - System Controller, 700GB Online Area, 3 RDX slots- Integrated DICOM software | C138: 14995 | D138: 13495.5 | E138: 0.1
A139: 101847 | B139: ProStor InfiniVault DICOM Model 5 - - System Controller, 1.8TB Online Area, 5 RDX slots- Integrated DICOM software | C139: 19995 | D139: 17995.5 | E139: 0.1
... A142: 101643 | B142: ProStor InfiniVault DICOM Model 100-System Controller-13TB Online Area-Two Removable Disk Units, 20 RDX slots | C142: 89995 | D142: 80995.5 | E142: 0.1
A143: TC-07311 | B143: Hardware Line Server Model 305, 4 channel ISDN (2*BRI) | C143: 3300 | D143: 2805 | E143: 0.15
A144: TC-07321 | B144: Hardware Line Interface Upgrade 4 to 8 channel ISDN BRI | C144: 3300 | D144: 2805 | E144: 0.15
A145: TC-07313 | B145: Hardware Line Server Model 305, 4 analog channels | C145: 3300 | D145: 2805 | E145: 0.15
A146: TC-07323 | B146: Hardware Line interface (Mod. 305) upgrade 4 to 8 channel analog | C146: 3300 | D146: 2805 | E146: 0.15
A147: TC-07324 | B147: Hardware Line interface (Mod. 305) upgrade 2 to 4 channel Bell DID | C147: 3300 | D147: 2805 | E147: 0.15
A148: TC-07402 | B148: Hardware Wireless messaging GSM Box Model 350 for SMS | C148: 2600 | D148: 2210 | E148: 0.15
A149: TS15 | B149: Hardware TS15 | C149: 500 | D149: 425 | E149: 0.15
A150: TC-07101 | B150: Hardware Telex interfaces Dual Telex Interface S.19 (XD-Interface) | C150: 2500 | D150: 2125 | E150: 0.15
A151: TC-07103 | B151: Hardware Telex interfaces as S07101 for V.21 standard | C151: 2500 | D151: 2125 | E151: 0.15
A152: TC-07104 | B152: Hardware Telex interfaces as S07101 for V.21 France | C152: 2500 | D152: 2125 | E152: 0.15
A153: 2001469 | B153: Everest™ 600/400 Printer Ribbons Retransfer Roll (up to 500 prints) | C153: 42.5 | D153: 38.25 | E153: 0.1
A154: 2001480 | B154: Everest™ 600/400 Printer Ribbons Three Panel Color - CMY Ribbon (up to 500 prints) | C154: 132.5 | D154: 119.25 | E154: 0.1
A155: 2001481 | B155: Everest™ 600/400 Printer Ribbons Black Ribbon (up to 1,000 prints) | C155: 75 | D155: 67.5 | E155: 0.1
A156: 2001624 | B156: Everest™ 600/400 Printer Ribbons Extra Ribbon Carriage for Everest 400 Printer ITS | C156: 125 | D156: 112.5 | E156: 0.1
A157: 2001625 | B157: Everest™ 600/400 Printer Ribbons Extra Ribbon Carriage for Everest 400 Printer CMY/BLK | C157: 150 | D157: 135 | E157: 0.1
A158: 2001631 | B158: Everest™ CD, DVD and Blu-ray Disc™ Blank Media CD-R White Everest (Qty = 100) | C158: 43.12 | D158: 38.81 | E158: 0.099953618
A159: 2001632 | B159: Everest™ CD, DVD and Blu-ray Disc™ Blank Media CD-R Silver Everest (Qty = 100) | C159: 43.12 | D159: 38.81 | E159: 0.099953618
A160: 2001633 | B160: Everest™ CD, DVD and Blu-ray Disc™ Blank Media DVD-R White Everest (Qty = 100) | C160: 47 | D160: 42.3 | E160: 0.1
A161: 2001634 | B161: Everest™ CD, DVD and Blu-ray Disc™ Blank Media DVD-R CSS White Everest (Qty = 50) | C161: 53 | D161: 47.7 | E161: 0.1
A162: 2001635 | B162: Everest™ CD, DVD and Blu-ray Disc™ Blank Media BD-R Single Layer (25 GB) 6x White Everest (Qty = 25) | C162: 168 | D162: 151.2 | E162: 0.1
A163: 2001636 | B163: Everest™ CD, DVD and Blu-ray Disc™ Blank Media BD-R Dual Layer (50 GB) 6x White Everest (Qty = 25) | C163: 406 | D163: 365.4 | E163: 0.1
A164: 2001637 | B164: InkJet CD & DVD Blank Media Media InkJet CD & DVD Blank Media CD-R White InkJet (Qty = 100) | C164: 37.93 | D164: 34.14 | E164: 0.099920907
... A241: 4000700 | B241: Rimage Copy Station Rimage 5400N Copy Station-2 BD | C241: 15950 | D241: 14355 | E241: 0.1
A242: 130027-001 | B242: Stand-Alone Everest III, PrismPlus! AutoPrinters (AutoEverest, AutoPrismPlus!) Stand-Alone and AutoPrinter Replacement Software | C242: 419 | D242: 377.1 | E242: 0.1
A243: 130028-001 | B243: Stand-Alone Everest III, PrismPlus! AutoPrinters (AutoEverest, AutoPrismPlus!) 360i Replacement Software | C243: 329 | D243: 296.1 | E243: 0.1
A244: 201737-006 | B244: PrismPlus!™ Printer RibbonsBlack Ribbon | C244: 50.25 | D244: 45.23 | E244: 0.099900498
A245: 202082-002 | B245: PrismPlus!™ Printer RibbonsRed Ribbon | C245: 63.75 | D245: 57.38 | E245: 0.099921569
A246: 202506-001 | B246: PrismPlus!™ Printer RibbonsThree Panel Color Ribbon - CMY (OQI = 10) | C246: 93.75 | D246: 84.38 | E246: 0.099946667
A247: 203015-001 | B247: Everest™ I, Everest II, Everest III Printer Ribbons Extra Ribbon Carriage for Everest I, II, III Printers | C247: 179 | D247: 161.1 | E247: 0.1
A248: 203217-001 | B248: PrismPlus!™ Printer RibbonsRoyal Blue Ribbon | C248: 63.75 | D248: 57.38 | E248: 0.099921569
A249: 203339-001 | B249: Rimage Ink Jet Cartridges (Rimage 2000i, Rimage 360i, and Rimage 480i) Color Ink Cartridge | C249: 65.95 | D249: 59.36 | E249: 0.099924185
A250: 203340-001 | B250: Rimage Ink Jet Cartridges (Rimage 2000i, Rimage 360i, and Rimage 480i) Black Ink Cartridge | C250: 54.95 | D250: 49.46 | E250: 0.099909008
A251: 203474-001 | B251: Everest™ I, Everest II, Everest III Printer Ribbons Retransfer Roll (up to 500 prints) | C251: 42.5 | D251: 38.25 | E251: 0.1
A252: 203638-001 | B252: Everest™ I, Everest II, Everest III Printer Ribbons Three Panel Color - CMY Ribbon (up to 500 prints) | C252: 132.5 | D252: 119.25 | E252: 0.1
A253: 203639-001 | B253: Everest™ I, Everest II, Everest III Printer Ribbons Three Panel Color + White - CMYW Ribbon (up to 375 prints) | C253: 148.5 | D253: 133.65 | E253: 0.1
... A336: S-CPRF2670021 | B336: Brooktrout SR-140-60F - 60 Channel FoIP Boardless Fax Solution - Redundant | C336: 16480 | D336: 14832 | E336: 0.1

Sheet Configuration and Training
A1: Exhibit B continued
A3: Consultant Implementation/Configuration/Training Cost Proposal, Tab 3
A4: Item / Category | B4: Description | C4: Unit Price (List) | D4: Extended Price | E4: % discount
A5: BIS-PS-01 | B5: Content Management System Integrator | C5: 225 | D5: 105 | E5: 0.53
A6: BIS-PS-02 | B6: Content Management Consultant | C6: 225 | D6: 113 | E6: 0.5
A7: BIS-PS-03 | B7: Content Management Project Manager | C7: 225 | D7: 120 | E7: 0.47
A8: BIS-PS-04 | B8: Content Management Developer | C8: 225 | D8: 185 | E8: 0.18
A9: BIS-PS-05 | B9: Support Technician | C9: 225 | D9: 185 | E9: 0.18

Sheet Technical Support
A1: Exhibit B continued
A3: Technical Support - Phone Support, Online Support, On-site Support, Tab 4
A4: Item | B4: Description | C4: Unit Price (List) | D4: Extended Price | E4: % discount
A5: 457-100-087 - Standard Support | B5: V6.5_APPLICATIONXTENDER APPLICATIONXTENDER PRODUCTS APPLICATIONXTENDER 10 USER, PROINDEX, AND QSP-Standard Support | C5: 4301.1 | D5: 3225.825 | E5: 0.25
A6: 457-100-087 - Platinum Support | B6: V6.5_APPLICATIONXTENDER APPLICATIONXTENDER PRODUCTS APPLICATIONXTENDER 10 USER, PROINDEX, AND QSP-Platinum Support | C6: 6690.6 | D6: 5017.95 | E6: 0.25
A7: 457-100-088 - Standard Support | B7: V6.5_APPLICATIONXTENDER APPLICATIONXTENDER PRODUCTS APPLICATIONXTENDER 10 USER, VERITY AND QSP-Standard Support | C7: 4499.1 | D7: 3374.325 | E7: 0.25
A8: 457-100-088 - Platinum Support | B8: V6.5_APPLICATIONXTENDER APPLICATIONXTENDER PRODUCTS APPLICATIONXTENDER 10 USER, VERITY AND QSP-Platinum Support | C8: 6998.6 | D8: 5248.95 | E8: 0.25
A9: 456-102-320 - Standard Support | B9: V6.5_APPLICATIONXTENDER APPLICATIONXTENDER PRODUCTS APPXTENDER IMAGE ENHANCER-Standard Support | C9: 18 | D9: 13.5 | E9: 0.25
A10: 456-102-320 - Platinum Support | B10: V6.5_APPLICATIONXTENDER APPLICATIONXTENDER PRODUCTS APPXTENDER IMAGE ENHANCER-Platinum Support | C10: 28 | D10: 21 | E10: 0.25
A11: 457-100-039 - Standard Support | B11: V6.5_APPLICATIONXTENDER APPLICATIONXTENDER PRODUCTS EMC APPLICATIONXTENDER 3 USER BUNDLE W/QSP-Standard Support | C11: 1079.1 | D11: 809.325 | E11: 0.25
A12: 457-100-039 - Platinum Support | B12: V6.5_APPLICATIONXTENDER APPLICATIONXTENDER PRODUCTS EMC APPLICATIONXTENDER 3 USER BUNDLE W/QSP-Platinum Support | C12: 1678.6 | D12: 1258.95 | E12: 0.25
A13: 456-100-376 - Standard Support | B13: V6.5_APPLICATIONXTENDER APPLICATIONXTENDER PRODUCTS EMC CAPTIVA QSP FOR APPLICATIONXTENDER-Standard Support | C13: 126 | D13: 94.5 | E13: 0.25
A14: 456-100-376 - Platinum Support | B14: V6.5_APPLICATIONXTENDER APPLICATIONXTENDER PRODUCTS EMC CAPTIVA QSP FOR APPLICATIONXTENDER-Platinum Support | C14: 196 | D14: 147 | E14: 0.25
A15: 457-100-248 - Standard Support | B15: V6.5_APPLICATIONXTENDER AX CAPTURE PACKAGE APPXTENDER CAPTURE PACKAGE-Standard Support | C15: 126 | D15: 94.5 | E15: 0.25
A16: 457-100-248 - Platinum Support | B16: V6.5_APPLICATIONXTENDER AX CAPTURE PACKAGE APPXTENDER CAPTURE PACKAGE-Platinum Support | C16: 196 | D16: 147 | E16: 0.25
... A2797: KACE-017- PLTMAINT | B2797: KACE - Additional Nodes for K1100 and VK100 - 1-Yr Platinum Support and Maintenance | C2797: 3.64 | D2797: 3.3852 | E2797: 0.07
A2798: 100-000-002 | B2798: MasterScan Check Processing for ApplicationXtender-Standard Support | C2798: 300 | D2798: 248.4 | E2798: =1-SUM(D2798/C2798) -> 0.172
A2799: 100-000-003 | B2799: MasterScan Check Processing for ApplicationXtender-Platinum Support | C2799: 466.2 | D2799: 386.4 | E2799: =1-SUM(D2799/C2799) -> 0.17117117
A2800: 100-000-005 | B2800: MasterScan AppXtender Services for SharePoint -Standard Support | C2800: 3199.8 | D2800: 2649.4344 | E2800: =1-SUM(D2800/C2800) -> 0.172
A2801: 100-000-006 | B2801: MasterScan AppXtender Services for SharePoint -Platinum Support | C2801: 4972.4892 | D2801: 4121.3424 | E2801: =1-SUM(D2801/C2801) -> 0.17117117
A2802: 100-000-008 | B2802: MasterScan Fax Image Gateway -Standard Support | C2802: 599.8 | D2802: 496.6344 | E2802: =1-SUM(D2802/C2802) -> 0.172
A2803: 100-000-009 | B2803: MasterScan Fax Image Gateway -Platinum Support | C2803: 932.0892 | D2803: 772.5424 | E2803: =1-SUM(D2803/C2803) -> 0.17117117
A2804: 100-000-011 | B2804: MasterScan Desktop -Standard Support | C2804: 319.8 | D2804: 264.7944 | E2804: =1-SUM(D2804/C2804) -> 0.172
A2805: 100-000-012 | B2805: MasterScan Desktop -Platinum Support | C2805: 496.9692 | D2805: 411.9024 | E2805: =1-SUM(D2805/C2805) -> 0.17117117
A2806: 100-000-014 | B2806: MasterScan Media Distribution -Standard Support | C2806: 799.8 | D2806: 662.2344 | E2806: =1-SUM(D2806/C2806) -> 0.172
A2807: 100-000-015 | B2807: MasterScan Media Distribution -Platinum Support | C2807: 1242.8892 | D2807: 1030.1424 | E2807: =1-SUM(D2807/C2807) -> 0.17117117
A2808: 100-000-017 | B2808: MasterScan Data Assimilation -Standard Support | C2808: 599.8 | D2808: 496.6344 | E2808: =1-SUM(D2808/C2808) -> 0.172
A2809: 100-000-018 | B2809: MasterScan Data Assimilation -Platinum Support | C2809: 932.0892 | D2809: 772.5424 | E2809: =1-SUM(D2809/C2809) -> 0.17117117
... A2837: 100-000-064 | B2837: Masterscan Legacy Integrator (Per User)-Platinum Support | C2837: 155.4 | D2837: 140 | E2837: =1-SUM(D2837/C2837) -> 0.099099099
A2838: 100-000-066 | B2838: BIS Cloud_0 - 50 GB (Per GB Per Month)-Standard Support | C2838: 8.991 | D2838: 8.1 | E2838: 0.099099099
A2839: 100-000-067 | B2839: BIS Cloud_0 - 50 GB (Per GB Per Month)-Platinum Support | C2839: 13.986 | D2839: 12.6 | E2839: 0.099099099
A2840: 100-000-069 | B2840: BIS Cloud_51-100GB (Per GB Per Month)-Standard Support | C2840: 7.4925 | D2840: 6.75 | E2840: 0.099099099
A2841: 100-000-070 | B2841: BIS Cloud_51-100GB (Per GB Per Month)-Platinum Support | C2841: 11.655 | D2841: 10.5 | E2841: 0.099099099
A2842: 100-000-072 | B2842: BIS Cloud_101 -200GB (Per GB Per Month)-Standard Support | C2842: 5.994 | D2842: 5.4 | E2842: 0.099099099
A2843: 100-000-073 | B2843: BIS Cloud_101 -200GB (Per GB Per Month)-Platinum Support | C2843: 9.324 | D2843: 8.4 | E2843: 0.099099099
A2844: 100-000-075 | B2844: BIS Cloud_201 - 400GB (Per GB Per Month)-Standard Support | C2844: 4.4955 | D2844: 4.05 | E2844: 0.099099099
A2845: 100-000-076 | B2845: BIS Cloud_201 - 400GB (Per GB Per Month)-Platinum Support | C2845: 6.993 | D2845: 6.3 | E2845: 0.099099099
A2846: 100-000-078 | B2846: BIS Cloud_401 - 600GB (Per GB Per Month)-Standard Support | C2846: 4.1514 | D2846: 3.74 | E2846: 0.099099099
A2847: 100-000-079 | B2847: BIS Cloud_401 - 600GB (Per GB Per Month)-Platinum Support | C2847: 6.4491 | D2847: 5.81 | E2847: 0.099099099
A2848: 100-000-081 | B2848: BIS Cloud_601 - 800GB (Per GB Per Month)-Standard Support | C2848: 3.6519 | D2848: 3.29 | E2848: 0.099099099
A2849: 100-000-082 | B2849: BIS Cloud_601 - 800GB (Per GB Per Month)-Platinum Support | C2849: 5.6721 | D2849: 5.11 | E2849: 0.099099099
... A3542: 456-100-092- Platinum Maintenance | B3542: QUICKSCAN PRO PRODUCTION LEVEL ST- Platinum Maintenance | C3542: 866.6 | D3542: 649.95 | E3542: 0.25
A3543: 001-CAN-001 | B3543: =CONCATENATE(Hardware!B4," - Platinum Maintenance") -> CR-135i, 135cpm Canon Check Scanner - Platinum Maintenance | C3543: =Hardware!C4*0.23 -> 642.85 | D3543: =C3543*(1-E3543) -> 578.565 | E3543: 0.1 | F3543: 23
A3544: 001-CAN-002 | B3544: =CONCATENATE(Hardware!B5," - Platinum Maintenance") -> CR-190i, 190cpm Canon Check Scanner - Platinum Maintenance | C3544: =Hardware!C5*0.23 -> 803.85 | D3544: =C3544*(1-E3544) -> 723.465 | E3544: 0.1
A3545: 001-CAN-003 | B3545: =CONCATENATE(Hardware!B6," - Platinum Maintenance") -> CR-50, 50cpm Canon Check Scanner - Platinum Maintenance | C3545: =Hardware!C6*0.23 -> 182.85 | D3545: =C3545*(1-E3545) -> 164.565 | E3545: 0.1
A3546: 001-CAN-004 | B3546: =CONCATENATE(Hardware!B7," - Platinum Maintenance") -> CR-80, 80cpm Canon Check Scanner - Platinum Maintenance | C3546: =Hardware!C7*0.23 -> 228.85 | D3546: =C3546*(1-E3546) -> 205.965 | E3546: 0.1
A3547: 001-CAN-005 | B3547: =CONCATENATE(Hardware!B8," - Platinum Maintenance") -> DR-C125, 25ppm/50ipm Canon Color Scanner - Platinum Maintenance | C3547: =Hardware!C8*0.23 -> 113.85 | D3547: =C3547*(1-E3547) -> 102.465 | E3547: 0.1
A3548: 001-CAN-006 | B3548: =CONCATENATE(Hardware!B9," - Platinum Maintenance") -> DR-C130, 30ppm/60ipm Canon Color Scanner - Platinum Maintenance | C3548: =Hardware!C9*0.23 -> 136.85 | D3548: =C3548*(1-E3548) -> 123.165 | E3548: 0.1
A3549: 001-CAN-007 | B3549: =CONCATENATE(Hardware!B10," - Platinum Maintenance") -> DR-2020U, 20ppm/40ipm Canon Color Scanner - Platinum Maintenance | C3549: =Hardware!C10*0.23 -> 159.85 | D3549: =C3549*(1-E3549) -> 143.865 | E3549: 0.1
A3550: 001-CAN-008 | B3550: =CONCATENATE(Hardware!B11," - Platinum Maintenance") -> DR-3010C, 30ppm Canon Color Scanner - Platinum Maintenance | C3550: =Hardware!C11*0.23 -> 251.85 | D3550: =C3550*(1-E3550) -> 226.665 | E3550: 0.1
A3551: 001-CAN-009 | B3551: =CONCATENATE(Hardware!B12," - Platinum Maintenance") -> DR-M140, 40ppm/80ipm Canon Color Scanner - Platinum Maintenance | C3551: =Hardware!C12*0.23 -> 274.85 | D3551: =C3551*(1-E3551) -> 247.365 | E3551: 0.1
A3552: 001-CAN-010 | B3552: =CONCATENATE(Hardware!B13," - Platinum Maintenance") -> DR-M160, 60ppm/120ipm Canon Color Scanner - Platinum Maintenance | C3552: =Hardware!C13*0.23 -> 297.85 | D3552: =C3552*(1-E3552) -> 268.065 | E3552: 0.1
A3553: 001-CAN-011 | B3553: =CONCATENATE(Hardware!B14," - Platinum Maintenance") -> DR-6010C, 60ppm/ 120ipm Canon Color Scanner - Platinum Maintenance | C3553: =Hardware!C14*0.23 -> 803.85 | D3553: =C3553*(1-E3553) -> 723.465 | E3553: 0.1
A3554: 001-CAN-012 | B3554: =CONCATENATE(Hardware!B15," - Platinum Maintenance") -> DR-6030C, 80ppm/160ipm Canon Color Scanner - Platinum Maintenance | C3554: =Hardware!C15*0.23 -> 1033.85 | D3554: =C3554*(1-E3554) -> 930.465 | E3554: 0.1
A3555: 001-CAN-013 | B3555: =CONCATENATE(Hardware!B16," - Platinum Maintenance") -> DR-G1100, 100 ppm / 200ipm Canon Color Scanner - Platinum Maintenance | C3555: =Hardware!C16*0.23 -> 1558.25 | D3555: =C3555*(1-E3555) -> 1402.425 | E3555: 0.1
... A3564: 001-CAN-022 | B3564: =CONCATENATE(Hardware!B25," - Platinum Maintenance") -> ScanFront 220e 24ppm/26ipm Scanner - Platinum Maintenance | C3564: =Hardware!C25*0.23 -> 688.85 | D3564: =C3564*(1-E3564) -> 619.965 | E3564: 0.1
A3565: 001-CAN-023 | B3565: =CONCATENATE(Hardware!B4," - Standard Maintenance") -> CR-135i, 135cpm Canon Check Scanner - Standard Maintenance | C3565: =Hardware!C4*0.13 -> 363.35 | D3565: =C3565*(1-E3565) -> 327.015 | E3565: 0.1 | F3565: 13
A3566: 001-CAN-024 | B3566: =CONCATENATE(Hardware!B5," - Standard Maintenance") -> CR-190i, 190cpm Canon Check Scanner - Standard Maintenance | C3566: =Hardware!C5*0.13 -> 454.35 | D3566: =C3566*(1-E3566) -> 408.915 | E3566: 0.1
A3567: 001-CAN-025 | B3567: =CONCATENATE(Hardware!B6," - Standard Maintenance") -> CR-50, 50cpm Canon Check Scanner - Standard Maintenance | C3567: =Hardware!C6*0.13 -> 103.35 | D3567: =C3567*(1-E3567) -> 93.015 | E3567: 0.1
A3568: 001-CAN-026 | B3568: =CONCATENATE(Hardware!B7," - Standard Maintenance") -> CR-80, 80cpm Canon Check Scanner - Standard Maintenance | C3568: =Hardware!C7*0.13 -> 129.35 | D3568: =C3568*(1-E3568) -> 116.415 | E3568: 0.1
A3569: 001-CAN-027 | B3569: =CONCATENATE(Hardware!B8," - Standard Maintenance") -> DR-C125, 25ppm/50ipm Canon Color Scanner - Standard Maintenance | C3569: =Hardware!C8*0.13 -> 64.35 | D3569: =C3569*(1-E3569) -> 57.915 | E3569: 0.1
A3570: 001-CAN-028 | B3570: =CONCATENATE(Hardware!B9," - Standard Maintenance") -> DR-C130, 30ppm/60ipm Canon Color Scanner - Standard Maintenance | C3570: =Hardware!C9*0.13 -> 77.35 | D3570: =C3570*(1-E3570) -> 69.615 | E3570: 0.1
A3571: 001-CAN-029 | B3571: =CONCATENATE(Hardware!B10," - Standard Maintenance") -> DR-2020U, 20ppm/40ipm Canon Color Scanner - Standard Maintenance | C3571: =Hardware!C10*0.13 -> 90.35 | D3571: =C3571*(1-E3571) -> 81.315 | E3571: 0.1
A3572: 001-CAN-030 | B3572: =CONCATENATE(Hardware!B11," - Standard Maintenance") -> DR-3010C, 30ppm Canon Color Scanner - Standard Maintenance | C3572: =Hardware!C11*0.13 -> 142.35 | D3572: =C3572*(1-E3572) -> 128.115 | E3572: 0.1
A3573: 001-CAN-031 | B3573: =CONCATENATE(Hardware!B12," - Standard Maintenance") -> DR-M140, 40ppm/80ipm Canon Color Scanner - Standard Maintenance | C3573: =Hardware!C12*0.13 -> 155.35 | D3573: =C3573*(1-E3573) -> 139.815 | E3573: 0.1
A3574: 001-CAN-032 | B3574: =CONCATENATE(Hardware!B13," - Standard Maintenance") -> DR-M160, 60ppm/120ipm Canon Color Scanner - Standard Maintenance | C3574: =Hardware!C13*0.13 -> 168.35 | D3574: =C3574*(1-E3574) -> 151.515 | E3574: 0.1
A3575: 001-CAN-033 | B3575: =CONCATENATE(Hardware!B14," - Standard Maintenance") -> DR-6010C, 60ppm/ 120ipm Canon Color Scanner - Standard Maintenance | C3575: =Hardware!C14*0.13 -> 454.35 | D3575: =C3575*(1-E3575) -> 408.915 | E3575: 0.1
A3576: 001-CAN-034 | B3576: =CONCATENATE(Hardware!B15," - Standard Maintenance") -> DR-6030C, 80ppm/160ipm Canon Color Scanner - Standard Maintenance | C3576: =Hardware!C15*0.13 -> 584.35 | D3576: =C3576*(1-E3576) -> 525.915 | E3576: 0.1
A3577: 001-CAN-035 | B3577: =CONCATENATE(Hardware!B16," - Standard Maintenance") -> DR-G1100, 100 ppm / 200ipm Canon Color Scanner - Standard Maintenance | C3577: =Hardware!C16*0.13 -> 880.75 | D3577: =C3577*(1-E3577) -> 792.675 | E3577: 0.1
... A3586: 001-CAN-045 | B3586: =CONCATENATE(Hardware!B25," - Standard Maintenance") -> ScanFront 220e 24ppm/26ipm Scanner - Standard Maintenance | C3586: =Hardware!C25*0.13 -> 389.35 | D3586: =C3586*(1-E3586) -> 350.415 | E3586: 0.1
A3587: FUJ-005 | B3587: fi-5950, 135ppm/270ipm Fujitsu Color Scanner-Platinum Support | C3587: 6381.39 | D3587: 5749 | E3587: 0.099099099
A3588: FUJ-017 | B3588: fi-6800, 130ppm/260ipm Fujitsu Color Scanner-Platinum Support | C3588: 5104.89 | D3588: 4599 | E3588: 0.099099099
A3589: FUJ-029 | B3589: fi-5950, 135ppm/270ipm Fujitsu Color Scanner-Standard Support | C3589: 3606.39 | D3589: 3249 | E3589: 0.099099099
A3590: FUJ-041 | B3590: fi-6800, 130ppm/260ipm Fujitsu Color Scanner-Standard Support | C3590: 2884.89 | D3590: 2599 | E3590: 0.099099099
A3591: FUJ-016 | B3591: fi-6770A (VRS), 70ppm/140ipm Fujitsu Color Scanner-Platinum Support | C3591: 2296.59 | D3591: 2069 | E3591: 0.099099099
A3592: FUJ-015 | B3592: fi-6770, 70ppm/140ipm Fujitsu Color Scanner-Platinum Support | C3592: 2041.29 | D3592: 1839 | E3592: 0.099099099
A3593: FUJ-014 | B3593: fi-6670A (VRS), 70ppm/140ipm Fujitsu Color Scanner-Platinum Support | C3593: 1785.99 | D3593: 1609 | E3593: 0.099099099
A3594: FUJ-013 | B3594: fi-6670, 70ppm/140ipm Fujitsu Color Scanner-Platinum Support | C3594: 1530.69 | D3594: 1379 | E3594: 0.099099099
A3595: FUJ-040 | B3595: fi-6770A (VRS), 70ppm/140ipm Fujitsu Color Scanner-Standard Support | C3595: 1297.59 | D3595: 1169 | E3595: 0.099099099
A3596: FUJ-001 | B3596: fi-4340C, 40ppm/80ipm, Flatbed Fujitsu Color Scanner-Platinum Support | C3596: 1275.39 | D3596: 1149 | E3596: 0.099099099
A3597: FUJ-002 | B3597: fi-4340C, 40ppm/80ipm, Flatbed Fujitsu Color Scanner-Platinum Support | C3597: 1275.39 | D3597: 1149 | E3597: 0.099099099
A3598: FUJ-039 | B3598: fi-6770, 70ppm/140ipm Fujitsu Color Scanner-Standard Support | C3598: 1153.29 | D3598: 1039 | E3598: 0.099099099
... A3683: 105-5755 - Platinum Support | B3683: Truper 3610, 90ppm/180ipm Kodak Color Scanner | C3683: 1748.75 | D3683: 1521.4125 | E3683: 0.13

Sheet Scanning Services Detail
A1: Exhibit B continued
A4: Offsite / Onsite Scanning Services Cost Proposal, Tab 5
C5: Onsite | E5: Offsite
B6: SERVICE REQUESTED | C6: Flat Fee | D6: COST/Copy | E6: Flat Fee | F6: COST/Copy
A7: A | B7: Paper up to 11 x 17 converted into TIFF Group-4 (black and white) images at 200dpi including document scanning and digital enhancement (despekle, deskew).
B8: Price Per Image | D8: 0.025 | F8: 0.025
A9: B | B9: Paper up to 11" x 17" converted into TIFF or JPEG (color or grayscale) images at resolution of up to 400dpi.
B10: Color/grayscale images within black/white documents (Price per Image) | D10: 0.032 | F10: 0.025
B11: Documents consist of all color/grayscale images (Price per Image) | D11: 0.032 | F11: 0.025
A12: C | B12: Paper of stated size converted into TIFF Group-4 (black and white) images at 200dpi including document scanning and digital enhancement (despekle, deskew).
B13: 12" x 18" (Price per Image) | D13: 0.45 | F13: 0.45
B14: 18" x 24" (price per Image) | D14: 0.52 | F14: 0.52
B15: 24" x 36" (Price per Image) | D15: 0.6 | F15: 0.6
B16: 36" x 48" (Price per Image) | D16: 0.7 | F16: 0.7
B17: Roll 36" x (Price per linear ft) | D17: 0.2 | F17: 0.2
A18: D | B18: Paper size larger than 11" x 17" converted into TIFF or JPEG (color or grayscale) images at resolution of up to 400dpi, including document preparation and scanning.
B19: 12" x 18" (Price per Image) | D19: 0.52 | F19: 0.52
B20: 18" x 24" (price per Image) | D20: 0.59 | F20: 0.59
B21: 24" x 36" (Price per Image) | D21: 0.67 | F21: 0.67
B22: 36" x 48" (Price per Image) | D22: 0.77 | F22: 0.77
B23: Roll 36" x (Price per linear ft) | D23: 0.27 | F23: 0.27
A24: E | B24: Bound volume or book scanning (up to 11" x 17" converted into TIFF or PDF images at resolution of up to 400dpi.
B25: Bound Book Scanning (black/white up to 400dpi TIFF) | D25: 0.14 | F25: 0.14
B26: Bound book scanning (color or grayscale up to 400dpi TIFF, PDF, or JPEG) | D26: 0.2 | F26: 0.14
A27: F | B27: Scanning of COM Microfiche or Jacketed Microfiche to TIFF Group-4 (black and white) images at 200dpi including digital enhancements (despekle, deskew).
B28: Microfiche COM (Price per Image) | D28: 0.0187 | F28: 0.0187
B29: Microfiche - Jacketed (Price per Image) | D29: 0.0374 | F29: 0.0374
A30: G | B30: Scanning of 16mm or 35mm Microfilm rolls to TIFF Group-4 (black and white) images at 200dpi including digital enhancements (despekle, deskew).
B31: Microfilm Scanning - 16mm film (Price per Image) | D31: 0.0187 | F31: 0.0187
B32: Microfilm Scanning - 35mm film (Price per Image) | D32: 0.0374 | F32: 0.0374
A33: H | B33: Additional Imaging Conversion Services
B34: Indexing Services (Per Character) | D34: 0.00351 | F34: 0.00351
B35: Conversion of TIFF to Adobe PDF file Format (Per Image) | D35: 0.00015 | F35: 0.00015
B36: Optical Character Recognition - OCR - (Per Image) | D36: 0.00015 | F36: 0.00015
B37: Document Preparation | D37: 0.038 | F37: 0.038
B38: Document Reassembly | D38: 0.027 | F38: 0.027
B39: Boxing documents for transport | C39: $4.00/box | E39: $4.00/box
B40: Transport of documents | C40: No Charge | D40: No Charge | E40: No Charge | F40: No Charge
B41: CD Master (Each) | C41: No Charge | D41: No Charge | E41: No Charge | F41: No Charge
B42: CD Duplicate (Each) | C42: No Charge | D42: No Charge | E42: No Charge | F42: No Charge
B43: DVD Master (Each) | C43: No Charge | D43: No Charge | E43: No Charge | F43: No Charge
B44: DVD Duplicate (Each) | C44: No Charge | D44: No Charge | E44: No Charge | F44: No Charge
B45: Book Rebinding | E45: $35/Book

Sheet Software
A1: Software Pricing
A3: BIS | B3: 0.1
A4: EMC | B4: Lowest Price GSA Match or better
A5: Kofax | B5: Lowest Price GSA Match or better
A6: Rightfax | B6: 0.11
A7: Kace | B7: 0.07
A8: Formatta/Formsoft | B8: 0.1
A9: IBML | B9: 0.05
A10: Rimage | B10: 0.1
A11: Equallogic | B11: 0.25
A15: See example of GSA Pricing on some EMC products PDF attachment. Other product discounts on EMC products may be less.

Sheet Sheet2
