Workbook
Name E: 'Memo HIV'!$F$3
Name ES: 'Memo HIV'!$F$4
Name HIVII: 'Memo HIV'!$B$2:$B$8
Name HIVOI: 'Memo HIV'!$D$2:$D$15
Name HIVSDA: 'Memo HIV'!$A$2:$A$30
Name HIVSource: 'Memo HIV'!$E$2:$E$22
Name IndicatorTypesList: [1]SDAs_impact_datasources!$D$2:$D$3
Name LFA_SDA: #REF!
Name LFA_SDA: '[2]LFA_Programmatic Progress_1B'!#REF!
Name LFA_SDA: #REF!
Name LFA_SDA: 'LFA_Programmatic Progress_1B'!#REF!
Name LFASig: #REF!
Name LFASig: '[2]LFA_Signature (image)'!$B$2
Name LFASig: #REF!
Name LFASig: #REF!
Name list: #REF!
Name List_IE: 'Definitions-lists-EFR'!$A$58:$A$65
Name list1: #REF!
Name list2: #REF!
Name listH: #REF!
Name listH: #REF!
Name ListHIV: 'Definitions-lists-EFR'!$A$1:$A$7
Name ListHIV_SDA: 'Definitions-lists-EFR'!$A$11:$A$18
Name listie: #REF!
Name listmac: #REF!
Name ListMal: 'Definitions-lists-EFR'!$A$21:$A$25
Name ListMal_SDA: 'Definitions-lists-EFR'!$A$28:$A$35
Name listnew: #REF!
Name listS: #REF!
Name listsda: #REF!
Name listsdah: #REF!
Name listsdahiv: #REF!
Name listsdahiv1: #REF!
Name listsdam: [3]Definitions!$C$28:$C$50
Name listsdat: #REF!
Name listsdat1: [4]Definitions!$C$39:$C$54
Name listserv: #REF!
Name ListTB: 'Definitions-lists-EFR'!$A$39:$A$44
Name ListTB_SDA: 'Definitions-lists-EFR'!$A$48:$A$55
Name MalariaII: 'Memo Malaria'!$B$2:$B$10
Name MalariaOI: 'Memo Malaria'!$D$2:$D$10
Name MalariaSDA: 'Memo Malaria'!$A$2:$A$23
Name MalariaSource: 'Memo Malaria'!$E$2:$E$25
Name Please_Select: 'Memo Malaria'!$A$3:$A$14
Name PR_SDA: #REF!
Name PR_SDA: '[2]LFA_Programmatic Progress_1A'!#REF!
Name PR_SDA: 'PR_Programmatic Progress_1B'!$C$12:$C$31
Name PR_SDA: #REF!
Name PR_SDA: 'LFA_Programmatic Progress_1A'!#REF!
Name PS: 'Memo HIV'!$F$5
Name SD: #REF!
Name SD: #REF!
Name SDA: #REF!
Name SDA: #REF!
Name SDAList: 'Memo Malaria'!$A$3:$A$20
Name Select: 'Memo HIV'!$J$2:$J$3
Name Sources: #REF!
Name Sources: #REF!
Name TBII: 'Memo TB'!$B$2:$B$5
Name TBOI: 'Memo TB'!$D$2:$D$5

Sheet Cover Sheet
A1: On-going Progress Update and Disbursement Request and LFA On-going Progress Review and Disbursement Recommendation
A3: In completing this report, please refer to the detailed "Guidelines for completing the PR “ongoing progress update and disbursement request”, and LFA “ongoing progress review and disbursement recommendation”
A4: During the lifetime of a grant, the Global Fund periodically disburses funds to the Principal Recipient (PR) based on demonstrated program performance and financial needs for the following period of implementation. The PR’s ongoing progress update and disbursement request (PU/DR) is both a progress report on the latest completed period of program implementation and a request for funds for the following period of implementation. Its purpose is to provide an update of the programmatic and financial progress of a Global Fund-financed grant, as well as an update on fulfillment of conditions precedent, management actions and other requirements. The PU/DR, alongside the Local Fund Agent (LFA) ongoing progress review and disbursement recommendation (short-form: LFA-verified PU/DR), forms the basis for the Global Fund’s disbursement decision by linking historical and expected program performance with the level of financing to be provided to the PR. One Excel file contains both the PR’s PU/DR and the LFA-verified PU/DR. The PR should only complete the worksheets of the file pertaining to the PU/DR (the worksheet tabs color-coded in green), whereas the LFA should complete the worksheets of the file pertaining to the LFA-verified PU/DR (the worksheet tabs color-coded in blue). The Excel file also includes a reference checklist of supporting documents for the PU/DR review (the worksheet tab color-coded in yellow). This checklist is included for information and not for completion. The PU/DR should be completed by the PR of a Global Fund grant for every period in which a progress update is required, usually either on a quarterly, semiannual or annual basis, regardless of whether or not a disbursement is being requested. Once a year, the PR is expected to submit the Enhanced Financial Report (EFR) as part of the PU/DR (there is a dedicated tab for EFR in the Excel file). The PR is required to submit the PU/DR to the LFA within 45 calendar days from the closing date of the relevant progress update period when the report does not contain the EFR (as indicated in the performance framework of Annex A of the grant agreement) and within 60 calendar days when the report contains the EFR (once a year). The LFA should complete and submit a signed copy of the LFA-verified PU/DR to the Global Fund within ten working days after receiving the final signed version of the PU/DR from the PR and within 13 working days when the PU/DR report contains the EFR (once a year), unless agreed otherwise with the FPM (The LFA does not need to submit original/hard copies of each PU/DR reports. However, these documents should be available at the LFA’s offices for any audit/reviews. Also, the LFA should be ready at all times to submit these originals to the Secretariat upon request). In this report the LFA should provide an analysis and comments based on verification of the PR-reported information, document grant risks and recommendations for improving program implementation, and finally, provide a performance rating to the grant and disbursement recommendation for the Global Fund’s consideration. In defining the performance rating and recommending a disbursement amount, the LFA should use the Grant Rating Methodology of the Global Fund (as described in Annex 2 and communicated at various regional meetings and LFA training events) along with the Excel version of the Grant Rating Tool (to be provided to LFAs) to support the calculation of Indicator Rating.
A17: Upon completion, this form should be submitted (with supporting documentation) to the Local Fund Agent and copied to the Global Fund.

Sheet PR_Programmatic Progress_1A
A1: On-going Progress Update and Disbursement Request | U1: Select
U2: AIS (AIDS Indicator Survey)
U3: BSS (Behavioral and Surveillance Survey)
A4: GENERAL GRANT INFORMATION | U4: Census
A5: Country: | C5: Monrovia | U5: Clinical cohort follow-up studies
A6: Disease: | C6: HIV/AIDS | U6: DHS/DHS+ (Demographic and Health Survey)
A7: Grant Number: | C7: MNR-809-G04-H | U7: MICS (Multiple Indicator Cluster Survey)
A8: Principal Recipient: | C8: Ministry of Health | U8: MIS (Malaria Indicator Survey)
A9: Program Start Date: | C9: 40087 | U9: WHO Global report/estimates
A10: Currency: | C10: EUR | U10: Other (type as appropriate)
A11: PROGRESS UPDATE
A12: Progress Update - Reporting Period: | C12: Cycle: | D12: Quarter | E12: Number: | F12: 7
A13: Progress Update - Period Covered: | C13: Beginning Date: | D13: 40452 | E13: End Date: | F13: 40543
A14: Progress Update - Number: | C14: 5
A15: DISBURSEMENT REQUEST
A16: Disbursement Request - Disbursement Period: | C16: Cycle: | D16: Quarter | E16: Number: | F16: 8
A17: Disbursement Request - Period Covered: | C17: Beginning Date: | D17: 40544 | E17: End Date: | F17: 40633
A18: Disbursement Request - Number: | C18: 6
A22: Section 1: Programmatic Progress
A23: Note: The table below should contain those Impact/Outcome indicators that are (1) due for reporting during the current year of a grant and (2) those reporting on which is overdue from the previous periods.
A24: A. Impact / Outcome Indicators
A25: Impact / Outcome | B25: Indicator Description | G25: Baseline (if applicable) | I25: Year of Target | J25: Intended Target | K25: Report Due Date | L25: Actual Result | M25: Data Source of Results | N25: Comments on results on Impact/Outcome indicators and data sources, and any other comments
G26: Value | H26: Year
A27: Outcome | B27: % of young women and men aged 15 - 24 who have had sexual intercourse before the age of 15 | G27: 2.7 (males) 17.1% (females) | H27: 2005 | I27: 2010 | J27: 2.1% (males) 13% (females) | K27: 40543 | L27: 1.5% (males) 7.4% (females) | M27: BSS (Behavioral and Surveillance Survey) | N27: Draft report of the BSS has been validated. Final report expecetd on 21/02/11
A28: Impact | B28: % of young women and men aged 15 - 24 who are HIV infected | G28: 2.4% NSS | H28: 2006 | I28: 2010 | J28: 0.0224 | K28: 40543 | L28: - | M28: Other (NSS) | N28: Preparatory work for 2010 NSS has been completed and sample collection is expected to commence soon
A29: Outcome | B29: % of most-at-risk populatoion(s) (sex workers, clients of sex workers, men who have sex with men, injecting drug users) who are HIV infected | G29: TBA | H29: 2008 | I29: 2011 | J29: TBD | K29: - | L29: - | M29: Other (2 yearly mapping) | N29: Two-yearly mapping updates and surveys
A30: Outcome | B30: % of people aged 15 - 49 years with more than one sexual partners in the past 12 months reporting the use of condoms during their last sexual intercourse | G30: 18.8% (males) 11.1% (females) | H30: 2010 | I30: 2010 | J30: 18.8% (males) 11.1% (females) | K30: 40543 | L30: 18.8% (males) 11.1% (females) | M30: BSS (Behavioral and Surveillance Survey) | N30: Draft report of the BSS has been validated. Final report expecetd on 21/02/11
A31: Outcome | B31: % of young people aged 10 -24 years reached by life skill-based HIV/AIDS education in and out of school | G31: 0.56 | H31: 2010 | I31: 2010 | J31: 0.56 | K31: 40543 | L31: 0.56 | M31: Other (Life skills based HIV/AIDS education survey) | N31: Baseline information information on out-of school youths reached through life skills training updated in the report and new baseline established.
A32: Select | G32: - | H32: - | I32: - | J32: - | K32: - | L32: - | M32: Select
A33: Select | G33: - | H33: - | I33: - | J33: - | K33: - | L33: - | M33: Select
A34: Select | G34: - | H34: - | I34: - | J34: - | K34: - | L34: - | M34: Select
A35: Select | G35: - | H35: - | I35: - | J35: - | K35: - | L35: - | M35: Select
A36: Select | G36: - | H36: - | I36: - | J36: - | K36: - | L36: - | M36: Select

Sheet PR_Programmatic Progress_1B
A1: On-going Progress Update and Disbursement Request
A2: PROGRESS UPDATE PERIOD
A3: Grant number: | D3: =IF('PR_Programmatic Progress_1A'!C7="","",'PR_Programmatic Progress_1A'!C7) -> MNR-809-G04-H
A4: Progress Update - Reporting Period: | D4: Cycle: | E4: =IF('PR_Programmatic Progress_1A'!D12="Select","",'PR_Programmatic Progress_1A'!D12) -> Quarter | F4: Number: | G4: 7
A5: Progress Update - Period Covered: | D5: Beginning Date: | E5: =IF('PR_Programmatic Progress_1A'!D13="","",'PR_Programmatic Progress_1A'!D13) -> 40452 | F5: End Date: | G5: =IF('PR_Programmatic Progress_1A'!F13="","",'PR_Programmatic Progress_1A'!F13) -> 40543
A6: Progress Update - Number: | D6: 5
A8: Note: All programmatic indicators contained in the current Performance Framework should be listed, regardless of whether there are targets/results for the period covered by the Progress Update or whether the targets have been met in previous periods.
A9: B. Programmatic Indicators
A10: Objective No. | B10: * Indicator No. | C10: Indicator Description | G10: Tied To | H10: Targets cumulative? | I10: Top 10 indicator? | J10: Baseline (if applicable) | L10: Intended Target to date | M10: Actual Result to date | N10: % achievement (Please calculate as appropriate) | O10: Reasons for programmatic deviation from intended target and deviations from the related workplan activities
J11: Value | K11: Year
A12: 1 | B12: 1.2 | C12: Number of commercial sex workers reached with prevention interventions | G12: GF | H12: Y-cumulative annually | I12: Yes - Top 10 | J12: 95 | K12: 2008 | L12: 225 | M12: 100 | N12: =M12/L12 -> 0.44444444 | O12: The delays are due to the following reasons: The PR has canceled a contract with one SR due to performance and accountability issues. There is ongoing prevention work with CSWs in the capital city but given the underperformance with regards to the set targets for prevention activities for commercial sex workers, the PR has decided to support service delivery sites in additional cities and towns where the need for the work with this target group has been identified (initial findings of ongoing BSS activities). The PR has signed contracts with new SRs after the end of the reporting period and plans to accelerate the work to achieve the targets. The PR has developed with the new SRs an accelerated implementation plan, to be supported with the unused budgeted resources as of the end of Q5 (EUR 400,000) (see attached docs).
A13: 1 | B13: 1.3 | C13: Number of medical (doctors and nurses) and non-medical staff (psychologists, social assistants, peer consultants) trained in HIV/AIDS | G13: GF | H13: Y-over program term | I13: Yes - Top 10 | J13: n/a | K13: n/a | L13: 400 | M13: 594 | N13: =M13/L13 -> 1.485 | O13: The PR, in coordination with the sub-recipients, managed to deliver trainings to more people than initially planned. The target was exceeded by 194 people. This was possible due to the involvement of a newly opened training center with the Medical Academy in the capital city and the engagement of the Regional Centers of the social services. The PR coordinated with the regional centers to add a module on HIV/AIDS to a training program, which was already organized by the social services. . All sub-recipients and contractors are required to maintain detailed training records. The PR is also conducting spot checks of training activities. The PR is also conducting spot checks of training activities. Finally, the PR is reviewing all SR reports and training log sheets, cross-checking the data and maintaining a central database of participants in trainings. As a result of the PR’s quality checks, 53 people from the SR reports were excluded from the cumulative results reported by the PR (e.g. due to incomplete records, double-counting by SRs).
A14: 1 | B14: 1.4 | C14: Number of IDUs on opioid substitution therapy | G14: GF | H14: Y-over program term | I14: Yes - Top 10 | J14: 30 | K14: 2008 | L14: 100 | M14: 0 | N14: =M14/L14 -> 0 | O14: While no people started methadone therapy during the reporting period, a number of important preparatory activities were completed. The first site in the capital city was fully renovated and it passed successfully the mandatory review procedures by the local authorities, who granted the necessary authorizations for its full-fledge operation. In the meantime, the contractors for the renovation of the service delivery facilities in one additional spot in the capital city and two other regional centers were selected and they started the renovation works in these spots. Importantly, the necessary authorizations for the methadone import were obtained and the partial pre-payment (15% of the invoice amount) was made during the reporting period. The methadone was actually delivered to the country after the end of the reporting period, and at the time of this PU/DR submission the first patients are already receiving therapy in the capital city. The already functioning center has the capacity to service 60 people per day and we expect to accelerate performance in this area. With the ongoing work on the opening of similar centers in other locations, we will be able to achieve the set targets.
A15: 2 | B15: 2.1 | C15: Number of people provided with ARV treatment | G15: Current grant | H15: N-not cumulative | I15: Yes - Top 10 | J15: 200 | K15: 2008 | L15: 300 | M15: 300 | N15: =M15/L15 -> 1 | O15: We are fully on track with the set targets for this indicator thanks to close coordination with the Central and Regional Infectious Disease Hospitals and the close cooperation with the NGOs providing care and support to the patients. It is important to note that the PR has supported the development of a comprehensive treatment monitoring electronic system, including treatment regimens and ARV drugs consumption. The system has been rolled out at the central hospital for now and following the field testing, the necessary revisions will be made and the e-system will be rolled out to the regional centers.
G18: Select | H18: Select | I18: Select | L18: - | M18: -
G19: Select | H19: Select | I19: Select | L19: - | M19: -
G20: Select | H20: Select | I20: Select | L20: - | M20: -
G21: Select | H21: Select | I21: Select | L21: - | M21: -
G22: Select | H22: Select | I22: Select | L22: - | M22: -
G23: Select | H23: Select | I23: Select | L23: - | M23: -
G24: Select | H24: Select | I24: Select | L24: - | M24: -
G26: Select | H26: Select | I26: Select | L26: - | M26: -
G27: Select | H27: Select | I27: Select | L27: - | M27: -
G28: Select | H28: Select | I28: Select | L28: - | M28: -
G29: Select | H29: Select | I29: Select | L29: - | M29: -
G30: Select | H30: Select | I30: Select | L30: - | M30: -
A32: * Indicator No. should correspond to the indicator number listed in the approved Performance Framework of the grant (1.1, 1.2, etc.)
A33: C. Analysis of data quality and reporting issues (!) This section should contain (1) a summary of issues related to data quality and reporting on programmatic indicators, and any relevant issues which are not covered in 'Reasons for programmatic deviation', and (2) remedial actions that are underway or planned to address these issues.
A35: Please see above for details.

Sheet PR_Grant Management_2
A1: On-going Progress Update and Disbursement Request
A2: PROGRESS UPDATE PERIOD
A3: Grant number: | D3: =IF('PR_Programmatic Progress_1A'!C7="","",'PR_Programmatic Progress_1A'!C7) -> MNR-809-G04-H
A4: Progress Update - Reporting Period: | D4: Cycle: | E4: =IF('PR_Programmatic Progress_1A'!D12="Select","",'PR_Programmatic Progress_1A'!D12) -> Quarter | F4: Number: | G4: =IF('PR_Programmatic Progress_1A'!F12="Select","",'PR_Programmatic Progress_1A'!F12) -> 7
A5: Progress Update - Period Covered: | D5: Beginning Date: | E5: =IF('PR_Programmatic Progress_1A'!D13="","",'PR_Programmatic Progress_1A'!D13) -> 40452 | F5: End Date: | G5: =IF('PR_Programmatic Progress_1A'!F13="","",'PR_Programmatic Progress_1A'!F13) -> 40543
A6: Progress Update - Number: | D6: 5
A8: Section 2: Grant Management
A10: A. PR COMMENTS ON THE FULFILLMENT OF CONDITIONS PRECEDENT AND/OR SPECIAL CONDITIONS UNDER THE GRANT AGREEMENT
A12: ! Please include in this table the CP number as per Grant Agreement and full text of CPs and/or other special conditions due for fulfilment during this period or outstanding from previous periods. ! Some Special Conditions may apply to more than one period of grant implementation. Their fulfilment during one period does not automatically imply fulfilment in subsequent periods. The LFA should verify that the status of such conditions is reported by the PR during each period concerned.
A13: Conditions Precedent and/or other special conditions | F13: Status | G13: PR Comments on Progress of Implementation
A14: The first disbursement of Grant funds by the Global Fund to the Principal Recipient is subject to the satisfaction of each of the following conditions: a. the delivery by the Principal Recipient to the Global Fund of a statement confirming the bank account into which the Grant funds will be disbursed as indicated in block 10 of the face sheet of this Agreement; | F14: Met | G14: This condition was initially met at the time of grant signing. During the last reporting period, the GF communicated a management action to the PR requiring the opening of a separate bank account. The PR opened the required separate bank account. Please find attached the PR Bank Details form duly completed and the respective supporting documents for the new bank account.
A15: The second disbursement of Grant funds by the Global Fund to the Principal Recipient is subject to the delivery by the Principal Recipient to the Global Fund of evidence, in form and substance satisfactory to the Global Fund, that the Principal Recipient has upgraded its Accounting System as well as its Accounting Manual, particularly cash basis of accounting, to facilitate compliance with Global Fund reporting requirements. | F15: Met | G15: The condition was fulfilled. The PR has upgraded its accounting system to generate expense reports on cash basis. The Accounting Manual was also updated to reflect the requirement for cash basis reporting to the GF and the necessary changes in the internal accounting procedures.
A17: B. PR REVIEW OF PROGRESS ON IMPLEMENTATION OF OUTSTANDING MANAGEMENT ACTIONS FROM PREVIOUS DISBURSEMENTS
A18: ! Please list all issues raised in the last Management Letter from the Global Fund or outstanding from previous Management Letters, and comment on the progress. Please include the date of the management letter and the item number.
A20: Global Fund Management Actions | E20: PR Comments on Progress of Implementation
A21: Reduce Stigma and Discrimination - Meaningful involvement of PLHIVs (Mission meeting in Nov. 2010) | E21: The two PRS (AAITG/NAS) had a joint meeting with all SRs on the R8 grant including social workers from ART sites which agreed that PLHIVs should be involved in all grant activities where possible in order to help reduce stigma and discrimination
A26: 1. The sub-recipients audit plan is still outstanding. It was due by 30 October 2010. | E26: The PR was indeed late with the submission of the plan for the audit of SRs for Year 1 (1 October 2009 - 30 September 2010) of the program. The SR audit plan, however, was submitted in December following the newly issued GF Guidelines on Annual Audits. The GF has already commented on the plan and required further amendments. They were made and the revised SR Audit Plan was submitted in January. Hence, the management action was completed.
A27: 2. The PR needs to open a separate bank account for this grant and transfer the correct cash balance from the current joint bank account. | E27: The bank account is opened and new bank instructions are provided for this disbursement. The Finance team has calculate the necessary balance on GF funds to be transferred to the account and submitted the necessary calculations and supporting information and documentation to the LFA for their review.
A28: 3. Although the PR has upgraded its accounting system to allow generating expenses reports on cash basis, the expenditures in the PU are still presented using the accrual basis of accounting. This prevents the verification of the cash balance, which is being calculated as a balance based on the cumulative expenditures of the program. Cumulative expenditures need to be updated based on actual cash disbursements from the PR grant account. | E28: The PR has worked on this point and the expenses for the reporting period covered by this PU/DR (both current reporting period expenditures and cumulative expenditures) are presented on a cash basis.
A35: C. PR COMMENTS ON ANNUAL GRANT REPORTING REQUIREMENTS
A36: ! Please indicate a date for the report due for submission. If a report is overdue, indicate the original due date and explain the reason for delay.
A37: Required Documentation | E37: Due date (dd-mmm-yy) | F37: Status | G37: Comments
A38: PR Audit Report | E38: 40724 | F38: Preparation on track
A39: PR Audit Report | E39: 40633 | F39: Preparation on track | G39: The audit company was selected and contracted, the field audit work was completed, the final report is due for submission by the end of March.
A40: Enhanced Financial Reporting (EFR) | E40: 40589 | F40: Submitted to GF | G40: The EFR was submitted in accordance with the set timelines.

Sheet PR_Total PR Cash Outflow_3A
A1: On-going Progress Update and Disbursement Request
A2: PROGRESS UPDATE PERIOD
A3: Grant number: | D3: =IF('PR_Programmatic Progress_1A'!C7="","",'PR_Programmatic Progress_1A'!C7) -> MNR-809-G04-H
A4: Progress Update - Reporting Period: | D4: Cycle: | E4: =IF('PR_Programmatic Progress_1A'!D12="Select","",'PR_Programmatic Progress_1A'!D12) -> Quarter | F4: Number: | G4: =IF('PR_Programmatic Progress_1A'!F12="Select","",'PR_Programmatic Progress_1A'!F12) -> 7
A5: Progress Update - Period Covered: | D5: Beginning Date: | E5: =IF('PR_Programmatic Progress_1A'!D13="","",'PR_Programmatic Progress_1A'!D13) -> 40452 | F5: End Date: | G5: =IF('PR_Programmatic Progress_1A'!F13="","",'PR_Programmatic Progress_1A'!F13) -> 40543
A6: Progress Update - Number: | D6: =IF('PR_Programmatic Progress_1A'!C14="Select","",'PR_Programmatic Progress_1A'!C14) -> 5
A7: Currency: | D7: =IF('PR_Programmatic Progress_1A'!C10="Select","",'PR_Programmatic Progress_1A'!C10) -> EUR
A9: Section 3A: Total PR Cash Outflow
A10: ! For RCC grants the cumulative section of the table below should contain cumulative amount from the start of the RCC and not from the start of Phase 1 of the program.
C11: Budget for Reporting Period | D11: Actual Cash Outflow for Reporting Period | E11: Variance | F11: Reason for Variance | H11: Cumulative Budget through period of Progress Update | I11: Cumulative Actual Cash Outflow through period of Progress Update | J11: Variance | K11: Reason for Variance
A12: 1. Total PR cash outflow vs. budget | C12: =C13+C14 -> 2500000 | D12: =D13+D14 -> 2235000 | E12: =IF(C12="",IF(D12="","",C12-D12),C12-D12) -> 265000 | H12: =H13+H14 -> 5600000 | I12: =I13+I14 -> 4500000 | J12: =IF(H12="",IF(I12="","",H12-I12),H12-I12) -> 1100000
A13: 1a. PR's total expenditures | C13: 1500000 | D13: 1435000 | E13: =IF(C13="",IF(D13="",0,C13-D13),C13-D13) -> 65000 | F13: Not implemented: 50,000 Technical Assistance for lab assessment Staff travel not realized in the amount of 15,000. | H13: 2600000 | I13: 2000000 | J13: =IF(H13="",IF(I13="",0,H13-I13),H13-I13) -> 600000 | K13: Contracts signed for procuring CD4 count equipment but not yet paid - 300,000. Final installment per signed contract to be paid for transportation and storage of drugs in regional warehouses - 35,000. Savings: 100,000 from late recruitment of staff Delayed activities (in progress now): 265,000 (media campaign - 50,000, refurbishment of facilities for delivery of opioid substitution therapy - 150,000, trainings related to substitution therapy - $15,000) Advance payment: (100,000) for procurement of test systems brought forward from Q7 due to bulk order
A14: 1b. Disbursements to sub-recipients | C14: 1000000 | D14: 800000 | E14: =IF(C14="",IF(D14="",0,C14-D14),C14-D14) -> 200000 | F14: The PR has canceled a contract with one SR due to performance and accountability issues. Given the underperformance with regards to the set targets for prevention activities for commercial sex workers, the PR has decided to support service delivery sites in additional cities and towns where the need for the work with this target group has been identified (initial findings of ongoing BSS activities). The PR has signed contracts with new SRs after the end of the reporting period and plans to accelerate the work to achieve the targets. The PR has developed with the new SRs an accelerated implementation plan, to be supported with the unused budgeted resources as of the end of Q5 (200,000) (see attached docs). | H14: 3000000 | I14: 2500000 | J14: =IF(H14="",IF(I14="",0,H14-I14),H14-I14) -> 500000 | K14: The PR has canceled a contract with one SR due to performance and accountability issues. Given the underperformance with regards to the set targets for prevention activities for commercial sex workers, the PR has decided to support service delivery sites in additional cities and towns where the need for the work with this target group has been identified (initial findings of ongoing BSS activities). The PR has signed contracts with new SRs after the end of the reporting period and plans to accelerate the work to achieve the targets. The PR has developed with the new SRs an accelerated implementation plan, to be supported with the unused budgeted resources as of the end of Q5 (200,000) (see attached docs). Payments in the amount of 300,000 were not made to SRs by the end of the reporting period due to delays in submission of the SR reports or inconsistent reports. Payment in the amount of 280,000 was made to SR right after the end of the reporting period (for all SRs where the outstanding issues were successfully resolved).
C16: Budget for Reporting Period* | D16: Actual Cash Outflow for Reporting Period | E16: Variance | F16: Reason for Variance | H16: Cumulative Budget through period of Progress Update | I16: Cumulative Actual Cash Outflow through period of Progress Update | J16: Variance | K16: Reason for Variance
A17: 2. Total pharmaceutical & health product expenditures vs. budget | C17: =C18+C19 -> 1300000 | D17: =D18+D19 -> 1350000 | E17: =IF(C17="",IF(D17="","",C17-D17),C17-D17) -> -50000 | H17: =H18+H19 -> 2500000 | I17: =I18+I19 -> 1950000 | J17: =IF(H17="",IF(I17="","",H17-I17),H17-I17) -> 550000
A18: 2a. Medicines and pharmaceutical products | C18: 600000 | D18: =C18-50000 -> 550000 | E18: =IF(C18="",IF(D18="",0,C18-D18),C18-D18) -> 50000 | F18: OI drugs cost less than initially budgeted (savings in the amount of 50,000). | H18: 1000000 | I18: 850000 | J18: =IF(H18="",IF(I18="",0,H18-I18),H18-I18) -> 150000 | K18: OI drugs cost less than initially budgeted (savings in the amount of 50,000). These savings are used to fund higher prices for some second-line ARVs. There is a last installement for the annual order of ARV drugs in the amount 100,000 to be paid in the next quarter.
A19: 2b. Health products and health equipment | C19: 700000 | D19: =C19+100000 -> 800000 | E19: =IF(C19="",IF(D19="",0,C19-D19),C19-D19) -> -100000 | F19: Advance payment: (100,000) for procurement of test systems brought forward from Q7 due to bulk order | H19: 1500000 | I19: =H19-E19-500000 -> 1100000 | J19: =IF(H19="",IF(I19="",0,H19-I19),H19-I19) -> 400000 | K19: Advance payment: (100,000) for procurement of test systems brought forward from Q7 due to bulk order. The order for lab equipment was placed (total amount: 500,000) - payment will be made in installements in the next two quarters.

Sheet EFR HIV AIDS Financial Data_3B
A1: SECTION 3B: HIV/AIDS FINANCIAL REPORTING FORM
A3: Country | C3: ='PR_Programmatic Progress_1A'!C5:F5 -> Monrovia | F3: PLEASE REFER TO THE "GUIDANCE FOR COMPLETION OF THE ENHANCED FINANCIAL REPORTING TEMPLATE" DOCUMENT TO ASSIST YOU IN COMPLETING THE TEMPLATE
A4: Grant No. | C4: ='PR_Programmatic Progress_1A'!C7:F7 -> MNR-809-G04-H
A5: PR | C5: ='PR_Programmatic Progress_1A'!C8:F8 -> Ministry of Health | F5: TO BE COMPLETED ONLY ONCE A YEAR EXCEPT AT MONTH 18 FOR PURPOSES OF PHASE 2 REVIEW
A6: Currency | C6: Please Select …
G7: dd-mm-yyyy | K7: dd-mm-yyyy
E8: Current Reporting Period | F8: Start Date: | I8: Cumulative Reporting Period | J8: Start Date:
F9: End Date: | J9: End Date:
H10: The end date for the current reporting period and cumulative reporting period must be the same
E12: The "TOTAL" rows in Table A, B and C will have a RED background if the amounts in each table do not agree. If the Totals for each Table agrees, these rows will have a YELLOW background.
A15: A- BREAKDOWN* BY EXPENDITURE CATEGORY | E15: Current Reporting Period | I15: Cumulative Reporting Period | P15: =IF('PR_Programmatic Progress_1A'!R15="Select","Please select currency on Page 'PR_Programmatic Achievement (1)'", "All amounts are in: "&'PR_Programmatic Progress_1A'!R15) -> All amounts are in: | R15: Budget for Reporting Period | S15: Actual Cash Outflow for Reporting Period | T15: Variance | U15: Reason for Variance | W15: Cumulative Budget through period of Progress Update | X15: Cumulative Actual Cash Outflow through period of Progress Update | Y15: Variance | Z15: Reason for Variance
A16: # | B16: Category | E16: Budget | F16: Expenditures | G16: Variance | H16: Reason for Variance | I16: Cumulative Budget | J16: Cumulative Expenditure | K16: Variance | L16: Reason for Variance | P16: 1. Total PR cash outflow vs. budget | R16: =R17+R18 -> 2500000 | S16: =S17+S18 -> 2235000 | T16: =IF(R16="",IF(S16="","",R16-S16),R16-S16) -> 265000 | W16: =W17+W18 -> 5600000 | X16: =X17+X18 -> 4500000 | Y16: =IF(W16="",IF(X16="","",W16-X16),W16-X16) -> 1100000
A17: 1 | B17: Human Resources | G17: =IF((E17=0)*AND(F17=0)," ",E17-F17) | K17: =IF((I17=0)*AND(J17=0)," ",I17-J17) | P17: 1a. PR's total expenditures | R17: ='PR_Total PR Cash Outflow_3A'!C13 -> 1500000 | S17: ='PR_Total PR Cash Outflow_3A'!D13 -> 1435000 | T17: =IF(R17="",IF(S17="",0,R17-S17),R17-S17) -> 65000 | W17: ='PR_Total PR Cash Outflow_3A'!H13 -> 2600000 | X17: ='PR_Total PR Cash Outflow_3A'!I13 -> 2000000 | Y17: =IF(W17="",IF(X17="",0,W17-X17),W17-X17) -> 600000
A18: 2 | B18: Technical Assistance | G18: =IF((E18=0)*AND(F18=0)," ",E18-F18) | K18: =IF((I18=0)*AND(J18=0)," ",I18-J18) | P18: 1b. Disbursements to sub-recipients | R18: ='PR_Total PR Cash Outflow_3A'!C14 -> 1000000 | S18: ='PR_Total PR Cash Outflow_3A'!D14 -> 800000 | T18: =IF(R18="",IF(S18="",0,R18-S18),R18-S18) -> 200000 | W18: ='PR_Total PR Cash Outflow_3A'!H14 -> 3000000 | X18: ='PR_Total PR Cash Outflow_3A'!I14 -> 2500000 | Y18: =IF(W18="",IF(X18="",0,W18-X18),W18-X18) -> 500000
A19: 3 | B19: Training | G19: =IF((E19=0)*AND(F19=0)," ",E19-F19) | K19: =IF((I19=0)*AND(J19=0)," ",I19-J19)
A20: 4 | B20: Health Products and Health Equipment | G20: =IF((E20=0)*AND(F20=0)," ",E20-F20) | K20: =IF((I20=0)*AND(J20=0)," ",I20-J20) | R20: Budget for Reporting Period* | S20: Actual Cash Outflow for Reporting Period | T20: Variance | U20: Reason for Variance | W20: Cumulative Budget through period of Progress Update | X20: Cumulative Actual Cash Outflow through period of Progress Update | Y20: Variance | Z20: Reason for Variance
A21: 5 | B21: Medicines and Pharmaceutical Products | G21: =IF((E21=0)*AND(F21=0)," ",E21-F21) | K21: =IF((I21=0)*AND(J21=0)," ",I21-J21) | P21: 2. Total pharmaceutical & health product expenditures vs. budget | R21: =R22+R23 -> 1300000 | S21: =S22+S23 -> 1350000 | T21: =IF(R21="",IF(S21="","",R21-S21),R21-S21) -> -50000 | W21: =W22+W23 -> 2500000 | X21: =X22+X23 -> 1950000 | Y21: =IF(W21="",IF(X21="","",W21-X21),W21-X21) -> 550000
A22: 6 | B22: Procurement and Supply Management Costs | G22: =IF((E22=0)*AND(F22=0)," ",E22-F22) | K22: =IF((I22=0)*AND(J22=0)," ",I22-J22) | P22: 2a. Medicines and pharmaceutical products | R22: ='PR_Total PR Cash Outflow_3A'!C18 -> 600000 | S22: ='PR_Total PR Cash Outflow_3A'!D18 -> 550000 | T22: =IF(R22="",IF(S22="",0,R22-S22),R22-S22) -> 50000 | W22: ='PR_Total PR Cash Outflow_3A'!H18 -> 1000000 | X22: ='PR_Total PR Cash Outflow_3A'!I18 -> 850000 | Y22: =IF(W22="",IF(X22="",0,W22-X22),W22-X22) -> 150000
A23: 7 | B23: Infrastructure and Other Equipment | G23: =IF((E23=0)*AND(F23=0)," ",E23-F23) | K23: =IF((I23=0)*AND(J23=0)," ",I23-J23) | P23: 2b. Health products and health equipment | R23: ='PR_Total PR Cash Outflow_3A'!C19 -> 700000 | S23: ='PR_Total PR Cash Outflow_3A'!D19 -> 800000 | T23: =IF(R23="",IF(S23="",0,R23-S23),R23-S23) -> -100000 | W23: ='PR_Total PR Cash Outflow_3A'!H19 -> 1500000 | X23: ='PR_Total PR Cash Outflow_3A'!I19 -> 1100000 | Y23: =IF(W23="",IF(X23="",0,W23-X23),W23-X23) -> 400000
A24: 8 | B24: Communication Materials | G24: =IF((E24=0)*AND(F24=0)," ",E24-F24) | K24: =IF((I24=0)*AND(J24=0)," ",I24-J24)
A25: 9 | B25: Monitoring & Evaluation | G25: =IF((E25=0)*AND(F25=0)," ",E25-F25) | K25: =IF((I25=0)*AND(J25=0)," ",I25-J25)
A26: 10 | B26: Living Support to Clients/Target Populations | G26: =IF((E26=0)*AND(F26=0)," ",E26-F26) | K26: =IF((I26=0)*AND(J26=0)," ",I26-J26)
A27: 11 | B27: Planning and Administration | G27: =IF((E27=0)*AND(F27=0)," ",E27-F27) | K27: =IF((I27=0)*AND(J27=0)," ",I27-J27)
A28: 12 | B28: Overheads | G28: =IF((E28=0)*AND(F28=0)," ",E28-F28) | K28: =IF((I28=0)*AND(J28=0)," ",I28-J28)
A29: 13 | B29: Other | G29: =IF((E29=0)*AND(F29=0)," ",E29-F29) | K29: =IF((I29=0)*AND(J29=0)," ",I29-J29)
D30: TOTAL | E30: =SUM(E17:E29) -> 0 | F30: =SUM(F17:F29) -> 0 | G30: =SUM(G17:G29) -> 0 | I30: =SUM(I17:I29) -> 0 | J30: =SUM(J17:J29) -> 0 | K30: =SUM(K17:K29) -> 0
A33: B- BREAKDOWN* BY PROGRAM ACTIVITY | E33: Current Reporting Period | I33: Cumulative Reporting Period
A34: # | B34: Macro-category | C34: Objectives | D34: Service Delivery Area | E34: Budget | F34: Expenditures | G34: Variance | H34: Reason for Variance | I34: Cumulative Budget | J34: Cumulative Expenditure | K34: Variance | L34: Reason for Variance
B35: Please Select… | D35: Please Select… | G35: =IF((E35=0)*AND(F35=0)," ",E35-F35) | K35: =IF((I35=0)*AND(J35=0)," ",I35-J35)
B36: Please Select… | D36: Please Select… | G36: =IF((E36=0)*AND(F36=0)," ",E36-F36) | K36: =IF((I36=0)*AND(J36=0)," ",I36-J36)
B37: Please Select… | D37: Please Select… | G37: =IF((E37=0)*AND(F37=0)," ",E37-F37) | K37: =IF((I37=0)*AND(J37=0)," ",I37-J37)
B38: Please Select… | D38: Please Select… | G38: =IF((E38=0)*AND(F38=0)," ",E38-F38) | K38: =IF((I38=0)*AND(J38=0)," ",I38-J38)
B39: Please Select… | D39: Please Select… | G39: =IF((E39=0)*AND(F39=0)," ",E39-F39) | K39: =IF((I39=0)*AND(J39=0)," ",I39-J39)
A40: TOTAL | E40: =SUM(E35:E39) -> 0 | F40: =SUM(F35:F39) -> 0 | G40: =SUM(G35:G39) -> 0 | I40: =SUM(I35:I39) -> 0 | J40: =SUM(J35:J39) -> 0 | K40: =SUM(K35:K39) -> 0
A41: To add additional rows, right click the row number (Row 39 in a blank template) to the left of the row above the row for TOTAL and select copy, then over the same number, right click again and select Insert Copied Cells. WARNING: Inserting Rows without copying a row as described above will cause the formula in the variance column to become invalid and will mean the overall information will be inaccurate.
A45: C- BREAKDOWN* BY IMPLEMENTING ENTITY | E45: Current Reporting Period | I45: Cumulative Reporting Period
A46: # | B46: PR/SR | C46: Name | D46: Type of Implementing Entity | E46: Budget | F46: Expenditures | G46: Variance | H46: Reason for Variance | I46: Cumulative Budget | J46: Cumulative Expenditure | K46: Variance | L46: Reason for Variance
B47: Please Select … | D47: Please Select… | G47: =IF((E47=0)*AND(F47=0)," ",E47-F47) | K47: =IF((I47=0)*AND(J47=0)," ",I47-J47)
B48: Please Select … | D48: Please Select… | G48: =IF((E48=0)*AND(F48=0)," ",E48-F48) | K48: =IF((I48=0)*AND(J48=0)," ",I48-J48)
B49: Please Select … | D49: Please Select… | G49: =IF((E49=0)*AND(F49=0)," ",E49-F49) | K49: =IF((I49=0)*AND(J49=0)," ",I49-J49)
B50: Please Select … | D50: Please Select… | G50: =IF((E50=0)*AND(F50=0)," ",E50-F50) | K50: =IF((I50=0)*AND(J50=0)," ",I50-J50)
B51: Please Select … | D51: Please Select… | G51: =IF((E51=0)*AND(F51=0)," ",E51-F51) | K51: =IF((I51=0)*AND(J51=0)," ",I51-J51)
D52: TOTAL | E52: =SUM(E47:E51) -> 0 | F52: =SUM(F47:F51) -> 0 | G52: =SUM(G47:G51) -> 0 | I52: =SUM(I47:I51) -> 0 | J52: =SUM(J47:J51) -> 0 | K52: =SUM(K47:K51) -> 0
A53: To add additional rows, right click the row number (Row 51 in a blank template) to the left of the row above the row for TOTAL and select copy, then over the same number, right click again and select Insert Copied Cells. WARNING: Inserting Rows without copying a row as described above will cause the formula in the variance column to become invalid and will mean the overall information will be inaccurate.
A57: * The sum of all three breakdowns should be equal (A- Budget Line-item, B- Program Activity, C- Implementing Entity).
A58: ** For the purposes of this report, the SDA Program management and administration should be included in the Supportive Environment Macro Category.
A60: D- ADDITIONAL INFORMATION
A61: Please disclose any relevant information concerning the information in the above tables. Refer to the Guidelines for Completing the Template if required.
A68: E- DISBURSEMENTS BREAKDOWN BY IMPLEMENTING ENTITY | E68: Cumulative Reporting Period
A69: # | B69: Name | C69: Type of Implementing Entity | D69: Cumulative Disbursements | E69: Comments
C70: Please Select…
C71: Please Select…
C72: Please Select…
C73: Please Select…
C74: Please Select…
C75: TOTAL | D75: =SUM(D70:D74) -> 0

Sheet PR_Procurement Info_4
A1: On-going Progress Update and Disbursement Request
A2: PROGRESS UPDATE PERIOD
A3: Grant number: | D3: =IF('PR_Programmatic Progress_1A'!C7="","",'PR_Programmatic Progress_1A'!C7) -> MNR-809-G04-H
A4: Progress Update - Reporting Period: | D4: Cycle: | E4: =IF('PR_Programmatic Progress_1A'!D12="Select","",'PR_Programmatic Progress_1A'!D12) -> Quarter | F4: Number: | G4: =IF('PR_Programmatic Progress_1A'!F12="Select","",'PR_Programmatic Progress_1A'!F12) -> 7
A5: Progress Update - Period Covered: | D5: Beginning Date: | E5: =IF('PR_Programmatic Progress_1A'!D13="","",'PR_Programmatic Progress_1A'!D13) -> 40452 | F5: End Date: | G5: =IF('PR_Programmatic Progress_1A'!F13="","",'PR_Programmatic Progress_1A'!F13) -> 40543
A6: Progress Update - Number: | D6: =IF('PR_Programmatic Progress_1A'!C14="Select","",'PR_Programmatic Progress_1A'!C14) -> 5
A8: Section 4: Procurement and Supply Management
G9: Comments
A10: 1a. Have you updated the Price Quality Reporting (PQR) with the required information on the pharmaceuticals and health products received during the period covered by this PU/DR’ (if applicable)? If health products procurement information has not been entered into the PQR, please explain why. ! For further guidance on PQR data entry, please refer to the guidelines. | F10: Yes | G10: The required information was updated for ARVs, rapid tests and condoms in the PQR (for cases when we did not have the final invoices, we updated the PQR based on pro-forma invoices).
A11: 2. Based on the most up-to-date stock situation, are there any risks of stockouts of key pharmaceuticals & health products at the central level in the next period of implementation? If yes, please comment. | F11: No | G11: Based on available information, there are sufficient stocks of drugs at central level. There were issues with drugs stocks in two regional centers but the PR worked closely with the central warehouse, the chief medical facility and the distribution company and ensured that the stocks at the regional level were replenished as soon as possible.
A13: 3. Comment on additional issues related to the procurement and supply management of pharmaceuticals and health products

Sheet PR Cash Rec Answer
A1: On-going Progress Update and Disbursement Request
A2: DISBURSEMENT REQUEST PERIOD
A3: Grant number: | D3: =IF('[5]PR_Programmatic Progress_1A'!C7="","",'[5]PR_Programmatic Progress_1A'!C7) -> MNR-809-G04-H | H3: ! A Statement of Sources and Uses of Funds (SSUF) is to be provided by PR along with the PUDR form
A4: Progress Update - Reporting Period: | D4: Cycle: | E4: =IF('[5]PR_Programmatic Progress_1A'!D12="Select","",'[5]PR_Programmatic Progress_1A'!D12) -> Quarter | F4: Number: | G4: =IF('[5]PR_Programmatic Progress_1A'!F12="Select","",'[5]PR_Programmatic Progress_1A'!F12) -> 7
A5: Progress Update - Period Covered: | D5: Beginning Date: | E5: =IF('[5]PR_Programmatic Progress_1A'!D13="","",'[5]PR_Programmatic Progress_1A'!D13) -> 40452 | F5: End Date: | G5: =IF('[5]PR_Programmatic Progress_1A'!F13="","",'[5]PR_Programmatic Progress_1A'!F13) -> 40543
A6: Progress Update - Number: | D6: =IF('[5]PR_Programmatic Progress_1A'!C14="Select","",'[5]PR_Programmatic Progress_1A'!C14) -> 5
A7: Currency: | D7: =IF('[5]PR_Programmatic Progress_1A'!C10="Select","",'[5]PR_Programmatic Progress_1A'!C10) -> EUR
A9: Section 5: Cash Reconciliation and Disbursement Request
A10: A: CASH RECONCILIATION FOR PERIOD COVERED BY PROGRESS UPDATE
A12: 1. Cash Balance: Beginning of period covered by Progress Update (line 10 from Cash Reconciliation section of the period covered by the previous Progress Update):
M13: 1700000 | O13: End balance from previous report
A15: Add: | B15: 2. Cash received by the PR from the Global Fund during the period covered by this progress update: | K15: 1000000
B16: 3. Cash disbursed to third parties by the Global Fund on behalf of the PR during the period covered by this progress update: | K16: 250000 | O16: GF pmt to third party on behalf of PR
B17: 4. Interest received on bank account | K17: 20000 | O17: Interest income in correct line
B18: 5. Revenue from income-generating activities (if applicable) | K18: 0
B19: 6. Other income, if applicable (e.g. income from disposal of fixed assets, tax refunds) | M19: =+K15+K16+K17+K18+K19 -> 1270000
A22: Less: | B22: 7. Total cash outflow during period covered by Progress Update (value entered in Section 3A "Total cash outflow"): | K22: =IF('[5]PR_Total PR Cash Outflow_3A'!D12="","",'[5]PR_Total PR Cash Outflow_3A'!D12) -> 2860000
B23: 8. Net exchange rate gains/losses (gains should be shown with a minus sign; losses should be shown with a plus sign)
B24: 9. Reconciliation adjustments (gains should be shown with a minus sign; losses should be shown with a plus sign) | K24: -100000 | M24: =+K22+K23+K24 -> 2760000 | O24: One-off reconciliation for under-reporting in previous reporting period
A26: 10. Cash Balance: End of period covered by Progress Update: | M26: =M13+M19-M24 -> 210000
A28: Explanation of reconciliation adjustments (line 9)
A29: ! An explanation must be provided if there have been any adjustments.
A30: Note re: Adjustment in Line 6: In Year 1 the PR opened a bank account dedicated to VAT re-funds per the requirement of the Ministry of Finance. At the very end of Year 1 i.e. prior to the reporting period of Q5, the first tranche of tax re-funds in the amount of $100,000 was made by the Ministry of Finance to the dedicated tax refund account. This amount is reflected in line 9 above. This is a one-time reconciliation adjustment and in the future tax refunds will be reflected on a periodic basis as part of reporting on other income under Line 6.

Sheet PR_Cash Reconciliation_Answer
A1: On-going Progress Update and Disbursement Request
A2: DISBURSEMENT REQUEST PERIOD
A3: Grant number: | D3: =IF('[5]PR_Programmatic Progress_1A'!C7="","",'[5]PR_Programmatic Progress_1A'!C7) -> MNR-809-G04-H | H3: ! A Statement of Sources and Uses of Funds (SSUF) is to be provided by PR along with the PUDR form
A4: Progress Update - Reporting Period: | D4: Cycle: | E4: =IF('[5]PR_Programmatic Progress_1A'!D12="Select","",'[5]PR_Programmatic Progress_1A'!D12) -> Quarter | F4: Number: | G4: =IF('[5]PR_Programmatic Progress_1A'!F12="Select","",'[5]PR_Programmatic Progress_1A'!F12) -> 7
A5: Progress Update - Period Covered: | D5: Beginning Date: | E5: =IF('[5]PR_Programmatic Progress_1A'!D13="","",'[5]PR_Programmatic Progress_1A'!D13) -> 40452 | F5: End Date: | G5: =IF('[5]PR_Programmatic Progress_1A'!F13="","",'[5]PR_Programmatic Progress_1A'!F13) -> 40543
A6: Progress Update - Number: | D6: =IF('[5]PR_Programmatic Progress_1A'!C14="Select","",'[5]PR_Programmatic Progress_1A'!C14) -> 5
A7: Currency: | D7: =IF('[5]PR_Programmatic Progress_1A'!C10="Select","",'[5]PR_Programmatic Progress_1A'!C10) -> EUR
A9: Section 5: Cash Reconciliation and Disbursement Request
A10: A: CASH RECONCILIATION FOR PERIOD COVERED BY PROGRESS UPDATE
A12: 1. Cash Balance: Beginning of period covered by Progress Update (line 10 from Cash Reconciliation section of the period covered by the previous Progress Update):
M13: 1700000 | O13: End balance from previous report
A15: Add: | B15: 2. Cash received by the PR from the Global Fund during the period covered by this progress update: | K15: 1000000
B16: 3. Cash disbursed to third parties by the Global Fund on behalf of the PR during the period covered by this progress update: | K16: 250000 | O16: GF pmt to third party on behalf of PR
B17: 4. Interest received on bank account | K17: 20000 | O17: Interest income in correct line
B18: 5. Revenue from income-generating activities (if applicable) | K18: 0
B19: 6. Other income, if applicable (e.g. income from disposal of fixed assets, tax refunds) | M19: =+K15+K16+K17+K18+K19 -> 1270000
A22: Less: | B22: 7. Total cash outflow during period covered by Progress Update (value entered in Section 3A "Total cash outflow"): | K22: ='PR_Total PR Cash Outflow_3A'!D12 -> 2235000
B23: 8. Net exchange rate gains/losses (gains should be shown with a minus sign; losses should be shown with a plus sign)
B24: 9. Reconciliation adjustments (gains should be shown with a minus sign; losses should be shown with a plus sign) | K24: -100000 | M24: =+K22+K23+K24 -> 2135000 | O24: One-off reconciliation for under-reporting in previous reporting period
A26: 10. Cash Balance: End of period covered by Progress Update: | M26: =M13+M19-M24 -> 835000
A28: Explanation of reconciliation adjustments (line 9)
A29: ! An explanation must be provided if there have been any adjustments.
A30: Note re: Adjustment in Line 6: In Year 1 the PR opened a bank account dedicated to VAT re-funds per the requirement of the Ministry of Finance. At the very end of Year 1 i.e. prior to the reporting period of Q5, the first tranche of tax re-funds in the amount of $100,000 was made by the Ministry of Finance to the dedicated tax refund account. This amount is reflected in line 9 above. This is a one-time reconciliation adjustment and in the future tax refunds will be reflected on a periodic basis as part of reporting on other income under Line 6.

Sheet PR_Cash Reconciliation_5A
A1: On-going Progress Update and Disbursement Request
A2: DISBURSEMENT REQUEST PERIOD
A3: Grant number: | D3: =IF('PR_Programmatic Progress_1A'!C7="","",'PR_Programmatic Progress_1A'!C7) -> MNR-809-G04-H | H3: ! A Statement of Sources and Uses of Funds (SSUF) is to be provided by PR along with the PUDR form
A4: Progress Update - Reporting Period: | D4: Cycle: | E4: =IF('PR_Programmatic Progress_1A'!D12="Select","",'PR_Programmatic Progress_1A'!D12) -> Quarter | F4: Number: | G4: =IF('PR_Programmatic Progress_1A'!F12="Select","",'PR_Programmatic Progress_1A'!F12) -> 7
A5: Progress Update - Period Covered: | D5: Beginning Date: | E5: =IF('PR_Programmatic Progress_1A'!D13="","",'PR_Programmatic Progress_1A'!D13) -> 40452 | F5: End Date: | G5: =IF('PR_Programmatic Progress_1A'!F13="","",'PR_Programmatic Progress_1A'!F13) -> 40543
A6: Progress Update - Number: | D6: =IF('PR_Programmatic Progress_1A'!C14="Select","",'PR_Programmatic Progress_1A'!C14) -> 5
A7: Currency: | D7: =IF('PR_Programmatic Progress_1A'!C10="Select","",'PR_Programmatic Progress_1A'!C10) -> EUR
A9: Section 5: Cash Reconciliation and Disbursement Request
A10: A: CASH RECONCILIATION FOR PERIOD COVERED BY PROGRESS UPDATE
A12: 1. Cash Balance: Beginning of period covered by Progress Update (line 10 from Cash Reconciliation section of the period covered by the previous Progress Update):
M13: 1700000
A15: Add: | B15: 2. Cash received by the PR from the Global Fund during the period covered by this progress update: | K15: 1000000
B16: 3. Cash disbursed to third parties by the Global Fund on behalf of the PR during the period covered by this progress update: | K16: 250000
B17: 4. Interest received on bank account | K17: 20000
B18: 5. Revenue from income-generating activities (if applicable)
B19: 6. Other income, if applicable (e.g. income from disposal of fixed assets, tax refunds) | M19: =+K15+K16+K17+K18+K19 -> 1270000
A22: Less: | B22: 7. Total cash outflow during period covered by Progress Update (value entered in Section 3A "Total cash outflow"): | K22: =IF('PR_Total PR Cash Outflow_3A'!D12="","",'PR_Total PR Cash Outflow_3A'!D12) -> 2235000
B23: 8. Net exchange rate gains/losses (gains should be shown with a minus sign; losses should be shown with a plus sign) | K23: -100000
B24: 9. Reconciliation adjustments (gains should be shown with a minus sign; losses should be shown with a plus sign) | M24: =+K22+K23+K24 -> 2135000
A26: 10. Cash Balance: End of period covered by Progress Update: | M26: =M13+M19-M24 -> 835000
A28: Explanation of reconciliation adjustments (line 9)
A29: ! An explanation must be provided if there have been any adjustments.
A30: An adjustment of EUR 100,000 in the beginning cash balance was made - VAT refund account was not considered in the financial reporting to date.

Sheet Cash Forecast Detail Top Down
G1: Disbursement Forecast
A2: Amount as originally budgeted: | B2: 500000 | C2: forecasted amount: | E2: 1600000 | F2: Q6
A4: Amount as originally budgeted: | B4: 600000 | C4: forecasted amount: | E4: 600000 | F4: Q7 | G4: =SUM(E2:E4) -> 2200000 | I4: Forecasted expenditures/cash needs in the PU/DR
A6: FORECAST REVIEW
A8: LESS
A9: as of last reporting period | B9: Savings from late staff recruitment | G9: -100000 | I9: See Section 3A
A10: as of last reporting period | B10: Technical assistance for labs - to be funded by another donor | G10: -50000 | I10: See Section 3A
A11: Q5 | B11: Unused SR cash balance not offset by commitments/due payments | E11: Less | G11: -80000 | I11: See Section 4C from Background information
A12: Q7 | B12: Advance pmt for test systems | E12: Less | G12: -100000 | I12: See Section 4C from Background information
E14: TOTAL | F14: (a) | G14: =SUM(G9:G12) -> -330000 | I14: Subtotal of cash declared as "needed" but unjustified
B16: Adjusted Forecasted Cash Needs | F16: (b) | G16: =G4+G14 -> 1870000 | I16: Adjusted Forecast
B18: Cash Balance: End of period covered by Progress Update: | F18: (c ) | G18: ='PR_Cash Reconciliation_Answer'!M26 -> 835000 | I18: Available Funds
F20: (b-c) | G20: =G16-G18 -> 1035000 | I20: Disbursement Amount

Sheet PR_Disbursement Request_5B
A1: On-going Progress Update and Disbursement Request
A2: DISBURSEMENT REQUEST PERIOD
A3: Grant number: | F3: =IF('PR_Programmatic Progress_1A'!C7="","",'PR_Programmatic Progress_1A'!C7) -> MNR-809-G04-H
A4: Progress Update - Reporting Period: | F4: Cycle: | G4: =IF('PR_Programmatic Progress_1A'!D12="Select","",'PR_Programmatic Progress_1A'!D12) -> Quarter | H4: Number: | I4: =IF('PR_Programmatic Progress_1A'!F12="Select","",'PR_Programmatic Progress_1A'!F12) -> 7
A5: Progress Update - Period Covered: | F5: Beginning Date: | G5: =IF('PR_Programmatic Progress_1A'!D13="","",'PR_Programmatic Progress_1A'!D13) -> 40452 | H5: End Date: | I5: =IF('PR_Programmatic Progress_1A'!F13="","",'PR_Programmatic Progress_1A'!F13) -> 40543
A6: Progress Update - Number: | F6: =IF('PR_Programmatic Progress_1A'!C14="Select","",'PR_Programmatic Progress_1A'!C14) -> 5
A7: Currency: | D7: =IF('PR_Programmatic Progress_1A'!C10="Select","",'PR_Programmatic Progress_1A'!C10) -> EUR
A9: Section 5: Cash Reconciliation and Disbursement Request
A11: B: DISBURSEMENT REQUEST
A14: Total forecasted net cash expenditures by the Principal Recipient for the period immediately following the period covered
A15: by the Progress Update:
A16: 1. Period beginning date: | E16: =IF('PR_Programmatic Progress_1A'!D17="","",'PR_Programmatic Progress_1A'!D17) -> 40544 | G16: end date: | H16: =IF('PR_Programmatic Progress_1A'!F17="","",'PR_Programmatic Progress_1A'!F17) -> 40633 | J16: approved budget amount: | K16: 500000 | L16: forecasted amount: | N16: =K16+'PR_Total PR Cash Outflow_3A'!J12-100000-50000-80000 -> 1370000
A17: 2a. Cash buffer period (by default)
A18: (cash "buffer") beginning date: | E18: =IF(H16="","",H16+1) -> 40634 | G18: end date: | H18: =IF(E18="","",DATE(YEAR(E18),MONTH(E18)+3,DAY(E18)-1)) -> 40724 | J18: approved budget amount: | K18: 600000 | L18: forecasted amount: | N18: =K18-100000 -> 500000
S19: PR Total Forecast
A20: 2b. Additional "buffer" (discretionary, select only if there is a prior agreement with the FPM) (1) | S20: =N16+N18+N22 -> 1870000
A21: cash "buffer" agreed with FPM (2) | C21: Select
A22: (cash "buffer") beginning date | E22: =IF(H18="","",H18+1) -> 40725 | G22: end date: | H22: =IF(C21="","",IF(C21="1M",DATE(YEAR(E22),MONTH(E22)+1,DAY(E22)-1),IF(C21="2M",DATE(YEAR(E22),MONTH(E22)+2,DAY(E22)-1),IF(C21="3M",DATE(YEAR(E22),MONTH(E22)+3,DAY(E22)-1),"")))) | J22: approved budget amount: | L22: forecasted amount: | N22: 0
A24: (1) Additional Cash buffer can be requested if the next PU/DR report will contain a completed EFR report or a completed Annex on SR financials, requested by the Secretariat, or if there are any additional GF-specific requirements that cannot be delivered within 45 days. An agreement in principal from the FPM should be obtained prior to requesting an additional cash buffer.
A25: (2) When the additional (cash "buffer" ) period is 1 or 2 months, the approved budget and forecasted amounts should be calculated as prorated values for the period following the regular buffer period.
A27: Please explain any significant variance (based on your judgment) between the forecasted amounts and the amounts as per approved budgets. Please specify the main factors and related amounts that are the major drivers of the variance. NB. Consider the following items when providing the analysis. - Expected timing of payments for any significant budgetary items, - Impact of existing cash balance at SR levels - Current confirmed commitments to be paid during disbursement request period - Current/expected unit prices compared to those in the budget - Change in quantities compared to budget - Exchange rates and inflation - Linkage between budget absorption and programmatic performance to-date. ! The forecast should include any existing commitments (eligible under this grant) as of the end of the reporting period and which are likely to be paid during the disbursement period | I27: Please see the attached spreadsheet named "Cash Forecast Detail Top Down" . The forecast for the next reporting period is based on the Q6 budget adjusted down for the following: Less $100,000 for savings from late staff recruitment (see Section 3A) Less $50,000 – TA for labs to be funded by another donor (see Section 3A) Less $80,000 – Unused SR cash balance not offset by commitments The budget for the buffer quarter is adjusted down for the following: Less $100,00 – advance payment for test systems
A31: Less: | B31: 3. Cash Balance: End of period covered by Progress Update (number 10 from PR Cash Reconciliation sheet): | N31: =+'PR_Cash Reconciliation_5A'!M26 -> 835000
B33: 4. Cash "in transit" disbursed to the PR: | N33: 0
B34: 5. Cash "in transit" disbursed to third parties by the Global Fund on behalf of the PR | N34: 0 | S34: =+N31+N33+N34 -> 835000
A36: 6. PR's Disbursement Request to the Global Fund for the period immediately following the period covered by the Progress Update, plus additional period (cash buffer): | S36: =IF(S20=0,0,IF(S20-S34<0,0,S20-S34)) -> 1035000
A38: 7. Does the PR's Disbursement Request include funds for health product procurement? | I38: Yes
A40: 8. Exchange Rate (used to translate local currency into grant currency) | I40: Name of local currency, date and source of the exchange rate, and other comments (if appropriate)
B41: - used to convert Opening Cash Balance | G41: 46 | I41: Amizian Kilasi
B43: - used to convert Closing Cash Balance | G43: 46 | I43: Amizian Kilasi
B45: - used to convert Total Cash Outflow for the Progress Update Period

Sheet PR_Overall Performance_6
A1: On-going Progress Update and Disbursement Request
A2: PROGRESS UPDATE PERIOD
A3: Grant number: | C3: =IF('LFA_Programmatic Progress_1A'!C7="","",'LFA_Programmatic Progress_1A'!C7) -> MNR-809-G04-H
A4: Progress Update - Reporting Period: | C4: Cycle: | D4: =IF('LFA_Programmatic Progress_1A'!D12="Select","",'LFA_Programmatic Progress_1A'!D12) -> Quarter | E4: Number: | F4: =IF('LFA_Programmatic Progress_1A'!F12="Select","",'LFA_Programmatic Progress_1A'!F12) -> 7
A5: Progress Update - Period Covered: | C5: Beginning Date: | D5: =IF('LFA_Programmatic Progress_1A'!D13="","",'LFA_Programmatic Progress_1A'!D13) -> 40452 | E5: End Date: | F5: =IF('LFA_Programmatic Progress_1A'!F13="","",'LFA_Programmatic Progress_1A'!F13) -> 40543
A6: Progress Update - Number: | C6: =IF('LFA_Programmatic Progress_1A'!C14="Select","",'LFA_Programmatic Progress_1A'!C14) -> 5
A8: Section 6: Overall Performance
A10: A. PR's Overall Self-Evaluation of Grant Performance (including a summary of how financial performance is linked to programmatic achievements)
A11: ! The self-evaluation should be undertaken by taking into account programmatic achievements, financial performance and program issues in various functional areas (M&E, Finance, Procurement, and Program Management, including management of sub-recipients). See Guidelines for more detailed guidance.
A18: B. Planned Changes in the Program, if any
A25: C. External factors beyond the control of the Principal Recipient that have impacted or may impact the Program

Sheet PR_Cash Request_7A&B
A1: On-going Progress Update and Disbursement Request
A2: GENERAL GRANT INFORMATION
A3: Country: | C3: =IF('PR_Programmatic Progress_1A'!C5:F5="","",'PR_Programmatic Progress_1A'!C5:F5) -> Monrovia
A4: Disease: | C4: =IF('PR_Programmatic Progress_1A'!C6:F6="Select","",'PR_Programmatic Progress_1A'!C6:F6) -> HIV/AIDS
A5: Grant number: | C5: =IF('PR_Programmatic Progress_1A'!C7:F7="","",'PR_Programmatic Progress_1A'!C7:F7) -> MNR-809-G04-H
A6: Principal Recipient: | C6: =IF('PR_Programmatic Progress_1A'!C8:F8="","",'PR_Programmatic Progress_1A'!C8:F8) -> Ministry of Health
A7: Program Start Date: | C7: =IF('PR_Programmatic Progress_1A'!C9:F9="","",'PR_Programmatic Progress_1A'!C9:F9) -> 40087
A8: Currency: | C8: =IF('PR_Programmatic Progress_1A'!C10="Select","",'PR_Programmatic Progress_1A'!C10) -> EUR
A9: PROGRESS UPDATE PERIOD
A10: Progress Update - Reporting Period: | C10: Cycle: | D10: =IF('PR_Programmatic Progress_1A'!D12="Select","",'PR_Programmatic Progress_1A'!D12) -> Quarter | E10: Number: | F10: =IF('PR_Programmatic Progress_1A'!F12="Select","",'PR_Programmatic Progress_1A'!F12) -> 7
A11: Progress Update - Period Covered: | C11: Beginning Date: | D11: =IF('PR_Programmatic Progress_1A'!D13="","",'PR_Programmatic Progress_1A'!D13) -> 40452 | E11: End Date: | F11: =IF('PR_Programmatic Progress_1A'!F13="","",'PR_Programmatic Progress_1A'!F13) -> 40543
A12: Progress Update - Number: | C12: =IF('PR_Programmatic Progress_1A'!C14:F14="Select","",'PR_Programmatic Progress_1A'!C14:F14) -> 5
A13: DISBURSEMENT REQUEST PERIOD
A14: Disbursement Request - Disbursement Period: | C14: Cycle: | D14: =IF('PR_Programmatic Progress_1A'!D16="Select","",'PR_Programmatic Progress_1A'!D16) -> Quarter | E14: Number: | F14: =IF('PR_Programmatic Progress_1A'!F16="Select","",'PR_Programmatic Progress_1A'!F16) -> 8
A15: Disbursement Request - Period Covered: | C15: Beginning Date: | D15: =IF('PR_Programmatic Progress_1A'!D17="","",'PR_Programmatic Progress_1A'!D17) -> 40544 | E15: End Date: | F15: =IF('PR_Programmatic Progress_1A'!F17="","",'PR_Programmatic Progress_1A'!F17) -> 40633
A16: Disbursement Request - Number: | C16: =IF('PR_Programmatic Progress_1A'!C18:F18="Select","",'PR_Programmatic Progress_1A'!C18:F18) -> 6
A18: Section 7: Cash Request and Authorization
A19: A: CASH REQUEST
A21: On behalf of the PR, the undersigned hereby requests the Global Fund to disburse funds under the above-referenced Grant Agreement as follows:
A23: 1. Cash amount requested from the Global Fund (from line 14 – “PR's Disbursement Request” in the tab “PR_Disbursement Request_4B”), in grant currency | D23: =+'PR_Disbursement Request_5B'!S36 -> 1035000
A25: ="2. Amount requested in words (in: "&IF('PR_Programmatic Progress_1A'!$C$10="Select","please select currency in 'PR_Section 1A')",'PR_Programmatic Progress_1A'!$C$10&"):") -> 2. Amount requested in words (in: EUR): | D25: One million thirty-five thousand US dollars
A27: B: AUTHORIZATION
A28: The undersigned acknowledges that: (i) all the information (programmatic, financial, or otherwise) provided in this Progress Update and Disbursement Request is complete and accurate; (ii) funds disbursed in accordance with this request shall be deposited in the bank account specified in block 9 of the face sheet of the Grant Agreement unless otherwise specified herein; and (iii) funds disbursed under the Grant Agreement shall be used in accordance with the Grant Agreement.
A30: Signed on behalf of the Principal Recipient: (signature of Authorized Designated Representative)
A32: Name: | C32: Mr. James
A33: Title: | C33: Executive Director PIU
A34: Date and Place: | C34: 13/06/2011 , Monrovia
A37: NB: Please ensure that section 7C Bank Details on the following page is completed, if (1) this is a split disbursement (i.e. disbursement going to more than one recipient) or (2) if there have been changes to the bank details since the previous disbursement.

Sheet PR_Bank Details_7C
A1: On-going Progress Update and Disbursement Request
A3: NB: This page should be completed if (1) this is a split disbursement (i.e. disbursement going to more than one recipient) or (2) if there have been changes to the bank details since the previous disbursement.
B5: 7C: Bank Account Details
B7: Disbursement Request Period
B9: Summary
C11: Beneficiary Name | D11: Amount in grant currency
B12: Payee 1 - Principal Recipient: | C12: =C20 -> 0 | D12: =IF(C30="",C24,C30) -> 0
B13: Payee 2: | C13: =C36 -> 0 | D13: =IF(C46="",C40,C46) -> 0
B14: Payee 3: | C14: =C53 -> 0 | D14: =IF(C63="",C57,C63) -> 0
B15: Payee 4: | C15: =C69 -> 0 | D15: =IF(C79="",C73,C79) -> 0
B16: Total | D16: =SUM(D12:D15) -> 0 | E16: =IF(D16<>'PR_Cash Request_7A&B'!D23,"The total does not match requested amount on PR signature page","") -> The total does not match requested amount on PR signature page
B18: Payee 1:
B20: Beneficiary Name: | E20: Owner of Bank Account:
B22: Currency in which beneficiary should receive the funds | E22: Owner of Bank Account:
B24: Amount in currency in which beneficiary should receive the funds: | E24: Bank Account Number:
B26: Amount in Words: | E26: Bank Address
B28: Exchange rate, date and source (Complete only if currency in which beneficiary should receive the funds is different from the grant currency) | E28: Bank SWIFT Code:
B30: Equivalent in grant currency (Calculated based on the indicated exchange rate) | E30: Bank Code (Other):
E32: Routing Instructions:
B34: Payee 2:
B36: Beneficiary Name: | E36: Owner of Bank Account:
B38: Currency in which beneficiary should receive the funds | E38: Owner of Bank Account:
B40: Amount in currency in which beneficiary should receive the funds: | E40: Bank Account Number:
B42: Amount in Words: | E42: Bank Address
B44: Exchange rate, date and source (Complete only if currency in which beneficiary should receive the funds is different from the grant currency) | E44: Bank SWIFT Code:
B46: Equivalent in grant currency (Calculated based on the indicated exchange rate) | E46: Bank Code (Other):
E48: Routing Instructions:
B51: Payee 3:
B53: Beneficiary Name: | E53: Owner of Bank Account:
B55: Currency in which beneficiary should receive the funds | E55: Owner of Bank Account:
B57: Amount in currency in which beneficiary should receive the funds: | E57: Bank Account Number:
B59: Amount in Words: | E59: Bank Address
B61: Exchange rate, date and source (Complete only if currency in which beneficiary should receive the funds is different from the grant currency) | E61: Bank SWIFT Code:
B63: Equivalent in grant currency (Calculated based on the indicated exchange rate) | E63: Bank Code (Other):
E65: Routing Instructions:
B67: Payee 4:
B69: Beneficiary Name: | E69: Owner of Bank Account:
B71: Currency in which beneficiary should receive the funds | E71: Owner of Bank Account:
B73: Amount in currency in which beneficiary should receive the funds: | E73: Bank Account Number:
B75: Amount in Words: | E75: Bank Address
B77: Exchange rate, date and source (Complete only if currency in which beneficiary should receive the funds is different from the grant currency) | E77: Bank SWIFT Code:
B79: Equivalent in grant currency (Calculated based on the indicated exchange rate) | E79: Bank Code (Other):
E81: Routing Instructions:

Sheet PR_Annex_SR-Financials
B1: On-going Progress Update and Disbursement Request
B3: Annex to PU/DR - Sub-recipient financial information - FOR DISCRETIONARY COMPLETION, UPON THE SECRETARIAT'S REQUEST
B5: Has the Secretariat requested the PR to complete this Annex for this reporting period?
B7: Grant number: | G7: ='PR_Programmatic Progress_1A'!C7 -> MNR-809-G04-H
B8: Progress Update - Reporting Period: | G8: Cycle: | H8: ='PR_Programmatic Progress_1A'!D12 -> Quarter | J8: Number: | L8: ='PR_Programmatic Progress_1A'!F12 -> 7
B9: Progress Update - Period Covered: | G9: Beginning Date: | H9: ='PR_Programmatic Progress_1A'!D13 -> 40452 | J9: End Date: | L9: ='PR_Programmatic Progress_1A'!F13 -> 40543
B10: Progress Update - Number: | G10: ='PR_Programmatic Progress_1A'!C14 -> 5
B11: Currency: | E11: =IF('PR_Programmatic Progress_1A'!C10="Select","",'PR_Programmatic Progress_1A'!C10) -> EUR
B14: Name of Entity | C14: Type of Implementing Entity | D14: Date of Most Recent Disbursement to SR | F14: Budget for Reporting Period* | G14: Disbursed during Reporting Period* | I14: Cumulative Budget through period of this Progress Update* | J14: Cumulative Disbursed through period of this Progress Update* | L14: Cumulative Actual Expenditure through period covered by this Progress Update | M14: Cash balance at the end of the period covered by this Progress Update | N14: Variance between Latest Cumulative Expenditure Reported and Cumulative Budget | O14: Expenditure Verified by PR (YES/NO) | P14: PR's explanation of variance (1) between cumulative budget and cumulative expenditure and (2) between cumulative disbursement and cumulative expenditure (mandatory for amounts above $50,000 or equivalent and with more than 10% variance)
C15: 0 | F15: 0 | G15: 0 | I15: 0 | J15: 0 | L15: 0 | N15: =SUM(I15-L15) -> 0 | O15: Yes
C16: 0 | F16: 0 | G16: 0 | I16: 0 | J16: 0 | L16: 0 | N16: =SUM(I16-L16) -> 0 | O16: 0
C17: 0 | F17: 0 | G17: 0 | I17: 0 | J17: 0 | L17: 0 | N17: =SUM(I17-L17) -> 0 | O17: 0
C18: 0 | F18: 0 | G18: 0 | I18: 0 | J18: 0 | L18: 0 | N18: =SUM(I18-L18) -> 0 | O18: 0
C19: 0 | F19: 0 | G19: 0 | I19: 0 | J19: 0 | L19: 0 | N19: =SUM(I19-L19) -> 0 | O19: 0
C20: 0 | F20: 0 | G20: 0 | I20: 0 | J20: 0 | L20: 0 | N20: =SUM(I20-L20) -> 0 | O20: 0
C21: 0 | F21: 0 | G21: 0 | I21: 0 | J21: 0 | L21: 0 | N21: =SUM(I21-L21) -> 0 | O21: 0
C22: 0 | F22: 0 | G22: 0 | I22: 0 | J22: 0 | L22: 0 | N22: =SUM(I22-L22) -> 0 | O22: 0
C23: 0 | F23: 0 | G23: 0 | I23: 0 | J23: 0 | L23: 0 | N23: =SUM(I23-L23) -> 0 | O23: 0
C24: 0 | F24: 0 | G24: 0 | I24: 0 | J24: 0 | L24: 0 | N24: =SUM(I24-L24) -> 0 | O24: 0
C25: 0 | F25: 0 | G25: 0 | I25: 0 | J25: 0 | L25: 0 | N25: =SUM(I25-L25) -> 0 | O25: 0
C26: 0 | F26: 0 | G26: 0 | I26: 0 | J26: 0 | L26: 0 | N26: =SUM(I26-L26) -> 0 | O26: 0
C27: 0 | F27: 0 | G27: 0 | I27: 0 | J27: 0 | L27: 0 | N27: =SUM(I27-L27) -> 0 | O27: 0
... C34: 0 | F34: 0 | G34: 0 | I34: 0 | J34: 0 | L34: 0 | N34: =SUM(I34-L34) -> 0 | O34: 0
B36: TOTAL | F36: =SUM(F15:F34) -> 0 | G36: =SUM(G15:G34) -> 0 | I36: =SUM(I15:I34) -> 0 | J36: =SUM(J15:J34) -> 0 | L36: =SUM(L15:L34) -> 0 | N36: =SUM(N15:N34) -> 0
B38: *TOTAL amount for these columns should reconcile with relevant amounts under "1b Disbursed to Sub Recipients" in Section 3A"
B39: ** Where the number of SRs is significant (over 10), SRs with small budgets (less than $50,000 cumulative each) do not need to be reported separately and the figures can be aggregated in a group called "Other Minor SRs"

Sheet Checklist
A1: List of supporting documents for PU/DR review
A3: This checklist is included for information and not for completion.
A5: List of Latest Approved Documents by functional area | B5: To be made available to the LFA by the PR | C5: To be submitted by the LFA to the Secretariat | D5: Comments
A6: M&E
A7: Performance Framework | B7: x
A8: M&E Plan | B8: x
A9: Survey results | B9: x | D9: For Impact/Outcome indicators
A10: M&E Systems Strengthening Assessment | B10: x | D10: If newly available during the reporting period.
A11: Other M&E assessments done by partners to assess data quality and M&E system issues. | B11: x | D11: If newly available during the reporting period.
A13: Procurement
A14: Consumption reports for pharmaceuticals and health products | B14: x
A15: Supplier invoices | B15: x
A16: PSM Plan | B16: x
A17: Stock level reports | B17: x
A19: Finance
A20: Approved budgets | B20: x | D20: For the periods covered by Progress Update and Disbursement Request, including the buffer period.
A21: Statement of sources and uses of funds (Cash flow statement) | B21: x | C21: x | D21: See guidance on SSUF content and format in the guidelines.
A22: Cash books | B22: x
A23: General Ledger | B23: x
A24: Cash forecasts | B24: x
A25: Bank statements | B25: x
A26: Bank Reconciliations | B26: x
A27: Annual PR Audit Report, Financial Statements, Management Letters and Responses (if Due) | B27: x | C27: x
A28: Annual SR Audit Report, Financial Statements, Management Letters and Responses (if Due) | B28: x
A29: General Management
A30: Grant Agreement (including Annex A and subsequent implementation letters) | B30: x
A31: Workplan | B31: x

Sheet LFA_Programmatic Progress_1A
A1: LFA On-going Progress Review and Disbursement Recommendation
A3: LFA Organization / Responsible office: | C3: PricewaterhouseCoopers (Ghana) Limited
A4: GENERAL GRANT INFORMATION
A5: Country: | C5: =IF('PR_Programmatic Progress_1A'!C5:F5="","",'PR_Programmatic Progress_1A'!C5:F5) -> Monrovia
A6: Disease: | C6: =IF('PR_Programmatic Progress_1A'!C6:F6="Select","",'PR_Programmatic Progress_1A'!C6:F6) -> HIV/AIDS
A7: Grant Number: | C7: =IF('PR_Programmatic Progress_1A'!C7:F7="","",'PR_Programmatic Progress_1A'!C7:F7) -> MNR-809-G04-H
A8: Principal Recipient: | C8: =IF('PR_Programmatic Progress_1A'!C8:F8="","",'PR_Programmatic Progress_1A'!C8:F8) -> Ministry of Health
A9: Program Start Date: | C9: =IF('PR_Programmatic Progress_1A'!C9:F9="","",'PR_Programmatic Progress_1A'!C9:F9) -> 40087
A10: Currency: | C10: =IF('PR_Programmatic Progress_1A'!C10:F10="Select","",'PR_Programmatic Progress_1A'!C10:F10) -> EUR
A11: PROGRESS UPDATE PERIOD
A12: Progress Update - Reporting Period: | C12: Cycle: | D12: =IF('PR_Programmatic Progress_1A'!D12="Select","",'PR_Programmatic Progress_1A'!D12) -> Quarter | E12: Number: | F12: =IF('PR_Programmatic Progress_1A'!F12="Select","",'PR_Programmatic Progress_1A'!F12) -> 7
A13: Progress Update - Period Covered: | C13: Beginning Date: | D13: =IF('PR_Programmatic Progress_1A'!D13="","",'PR_Programmatic Progress_1A'!D13) -> 40452 | E13: End Date: | F13: =IF('PR_Programmatic Progress_1A'!F13="","",'PR_Programmatic Progress_1A'!F13) -> 40543
A14: Progress Update - Number: | C14: =IF('PR_Programmatic Progress_1A'!C14="Select","",'PR_Programmatic Progress_1A'!C14) -> 5
A15: DISBURSEMENT REQUEST PERIOD
A16: Disbursement Request - Disbursement Period: | C16: Cycle: | D16: =IF('PR_Programmatic Progress_1A'!D16="Select","",'PR_Programmatic Progress_1A'!D16) -> Quarter | E16: Number: | F16: =IF('PR_Programmatic Progress_1A'!F16="Select","",'PR_Programmatic Progress_1A'!F16) -> 8
A17: Disbursement Request - Period Covered: | C17: Beginning Date: | D17: =IF('PR_Programmatic Progress_1A'!D17="","",'PR_Programmatic Progress_1A'!D17) -> 40544 | E17: End Date: | F17: =IF('PR_Programmatic Progress_1A'!F17="","",'PR_Programmatic Progress_1A'!F17) -> 40633
A18: Disbursement Request - Number: | C18: =IF('PR_Programmatic Progress_1A'!C18:F18="Select","",'PR_Programmatic Progress_1A'!C18:F18) -> 6
A20: TERMS AND ACRONYMS USED IN THIS PROGRESS REVIEW AND DISBURSEMENT RECOMMENDATION HAVE THE MEANING GIVEN TO THEM IN THE GRANT AGREEMENT RELATING TO THE ABOVE GRANT
A22: Section 1: LFA Review and Verification of the Principal Recipient's Programmatic Progress
A23: Note: The table below should contain those Impact/Outcome indicators that are (1) due for reporting during the current year of a grant and (2) those reporting on which is overdue from the previous periods.
A24: A. Impact / Outcome Indicators | U24: A. Impact / Outcome Indicators
A25: Impact / Outcome | B25: Indicator Description | F25: Year of Target | G25: Intended Target (from Attachment) | H25: Report Due Date | I25: Actual Result (as reported by PR) | J25: Data Source of Results | L25: Verification Method | M25: Verified Result | N25: LFA comments on (a) verified result, (b) source of information used by the PR to report results, including the status of completion of surveys and other methods to measure Impact/Outcome, as applicable, | U25: Impact / Outcome | V25: Indicator Description | Z25: Year of Target | AA25: Intended Target (from Attachment) | AB25: Report Due Date | AC25: Actual Result (as reported by PR) | AD25: Data Source of Results
A27: =U27 -> Outcome | B27: =V27 -> % of young women and men aged 15 - 24 who have had sexual intercourse before the age of 15 | F27: =Z27 -> 2010 | G27: =AA27 -> 2.1% (males) 13% (females) | H27: =AB27 -> 40543 | I27: =AC27 -> 1.5% (males) 7.4% (females) | J27: =AD27 -> BSS (Behavioral and Surveillance Survey) | L27: Desk Review | M27: 1.5% males, 7.4% females | N27: The draft 2010 BSS report was shared with the LFA during the verification exercise. The draft 2010 BSS report was validated on 14 February 2011 and it was expected to be finalised by the end of February 2011, however at the time of the completion of this report in March 2011, the final report had not been submitted by the PR. | U27: =IF('PR_Programmatic Progress_1A'!A27="Select","",'PR_Programmatic Progress_1A'!A27) -> Outcome | V27: =IF('PR_Programmatic Progress_1A'!B27="","",'PR_Programmatic Progress_1A'!B27) -> % of young women and men aged 15 - 24 who have had sexual intercourse before the age of 15 | Z27: =IF('PR_Programmatic Progress_1A'!I27="","",'PR_Programmatic Progress_1A'!I27) -> 2010 | AA27: =IF('PR_Programmatic Progress_1A'!J27="","",'PR_Programmatic Progress_1A'!J27) -> 2.1% (males) 13% (females) | AB27: =IF('PR_Programmatic Progress_1A'!K27="","",'PR_Programmatic Progress_1A'!K27) -> 40543 | AC27: =IF('PR_Programmatic Progress_1A'!L27="","",'PR_Programmatic Progress_1A'!L27) -> 1.5% (males) 7.4% (females) | AD27: ='PR_Programmatic Progress_1A'!M27 -> BSS (Behavioral and Surveillance Survey)
A28: =U28 -> Impact | B28: =V28 -> % of young women and men aged 15 - 24 who are HIV infected | F28: =Z28 -> 2010 | G28: =AA28 -> 0.0224 | H28: =AB28 -> 40543 | I28: =AC28 -> - | J28: =AD28 -> Other (NSS) | L28: Desk Review | M28: 0.0194 | N28: The 2010 NSS was ongoing at the time of the VoI and the report was expected by end of March 2011. The results of the 2008 NSS were shared with LFA and this showed that HIV prevalence among people aged 15-24 is estimated at 1.94%. | U28: =IF('PR_Programmatic Progress_1A'!A28="Select","",'PR_Programmatic Progress_1A'!A28) -> Impact | V28: =IF('PR_Programmatic Progress_1A'!B28="","",'PR_Programmatic Progress_1A'!B28) -> % of young women and men aged 15 - 24 who are HIV infected | Z28: =IF('PR_Programmatic Progress_1A'!I28="","",'PR_Programmatic Progress_1A'!I28) -> 2010 | AA28: =IF('PR_Programmatic Progress_1A'!J28="","",'PR_Programmatic Progress_1A'!J28) -> 0.0224 | AB28: =IF('PR_Programmatic Progress_1A'!K28="","",'PR_Programmatic Progress_1A'!K28) -> 40543 | AC28: =IF('PR_Programmatic Progress_1A'!L28="","",'PR_Programmatic Progress_1A'!L28) -> - | AD28: ='PR_Programmatic Progress_1A'!M28 -> Other (NSS)
A29: =U29 -> Outcome | B29: =V29 -> % of most-at-risk populatoion(s) (sex workers, clients of sex workers, men who have sex with men, injecting drug users) who are HIV infected | F29: =Z29 -> 2011 | G29: =AA29 -> TBD | H29: =AB29 -> - | I29: =AC29 -> - | J29: =AD29 -> Other (2 yearly mapping) | N29: The first results for this indicator are expected at the end of year 2. | U29: =IF('PR_Programmatic Progress_1A'!A29="Select","",'PR_Programmatic Progress_1A'!A29) -> Outcome | V29: =IF('PR_Programmatic Progress_1A'!B29="","",'PR_Programmatic Progress_1A'!B29) -> % of most-at-risk populatoion(s) (sex workers, clients of sex workers, men who have sex with men, injecting drug users) who are HIV infected | Z29: =IF('PR_Programmatic Progress_1A'!I29="","",'PR_Programmatic Progress_1A'!I29) -> 2011 | AA29: =IF('PR_Programmatic Progress_1A'!J29="","",'PR_Programmatic Progress_1A'!J29) -> TBD | AB29: =IF('PR_Programmatic Progress_1A'!K29="","",'PR_Programmatic Progress_1A'!K29) -> - | AC29: =IF('PR_Programmatic Progress_1A'!L29="","",'PR_Programmatic Progress_1A'!L29) -> - | AD29: ='PR_Programmatic Progress_1A'!M29 -> Other (2 yearly mapping)
A30: =U30 -> Outcome | B30: =V30 -> % of people aged 15 - 49 years with more than one sexual partners in the past 12 months reporting the use of condoms during their last sexual intercourse | F30: =Z30 -> 2010 | G30: =AA30 -> 18.8% (males) 11.1% (females) | H30: =AB30 -> 40543 | I30: =AC30 -> 18.8% (males) 11.1% (females) | J30: =AD30 -> BSS (Behavioral and Surveillance Survey) | L30: Desk Review | M30: 18.8% males, 11.1% females | N30: The draft 2010 BSS report was shared with the LFA during the verification exercise. The draft 2010 BSS report was validated on 14 February 2011 and it was expected to be finalised by the end of February 2011, however at the time of the completion of this report in March 2011, the final report had not been submitted by the PR. | U30: =IF('PR_Programmatic Progress_1A'!A30="Select","",'PR_Programmatic Progress_1A'!A30) -> Outcome | V30: =IF('PR_Programmatic Progress_1A'!B30="","",'PR_Programmatic Progress_1A'!B30) -> % of people aged 15 - 49 years with more than one sexual partners in the past 12 months reporting the use of condoms during their last sexual intercourse | Z30: =IF('PR_Programmatic Progress_1A'!I30="","",'PR_Programmatic Progress_1A'!I30) -> 2010 | AA30: =IF('PR_Programmatic Progress_1A'!J30="","",'PR_Programmatic Progress_1A'!J30) -> 18.8% (males) 11.1% (females) | AB30: =IF('PR_Programmatic Progress_1A'!K30="","",'PR_Programmatic Progress_1A'!K30) -> 40543 | AC30: =IF('PR_Programmatic Progress_1A'!L30="","",'PR_Programmatic Progress_1A'!L30) -> 18.8% (males) 11.1% (females) | AD30: ='PR_Programmatic Progress_1A'!M30 -> BSS (Behavioral and Surveillance Survey)
A31: =U31 -> Outcome | B31: =V31 -> % of young people aged 10 -24 years reached by life skill-based HIV/AIDS education in and out of school | F31: =Z31 -> 2010 | G31: =AA31 -> 0.56 | H31: =AB31 -> 40543 | I31: =AC31 -> 0.56 | J31: =AD31 -> Other (Life skills based HIV/AIDS education survey) | L31: Desk Review | M31: 0.57 | N31: As per recommendations from VOI for period 3, the baseline data was updated to reflect both in and out of school youth reached with life-skills based health education. The revised baseline figure is 57%. | U31: =IF('PR_Programmatic Progress_1A'!A31="Select","",'PR_Programmatic Progress_1A'!A31) -> Outcome | V31: =IF('PR_Programmatic Progress_1A'!B31="","",'PR_Programmatic Progress_1A'!B31) -> % of young people aged 10 -24 years reached by life skill-based HIV/AIDS education in and out of school | Z31: =IF('PR_Programmatic Progress_1A'!I31="","",'PR_Programmatic Progress_1A'!I31) -> 2010 | AA31: =IF('PR_Programmatic Progress_1A'!J31="","",'PR_Programmatic Progress_1A'!J31) -> 0.56 | AB31: =IF('PR_Programmatic Progress_1A'!K31="","",'PR_Programmatic Progress_1A'!K31) -> 40543 | AC31: =IF('PR_Programmatic Progress_1A'!L31="","",'PR_Programmatic Progress_1A'!L31) -> 0.56 | AD31: ='PR_Programmatic Progress_1A'!M31 -> Other (Life skills based HIV/AIDS education survey)
A32: =U32 | B32: =V32 | F32: =Z32 -> - | G32: =AA32 -> - | H32: =AB32 -> - | I32: =AC32 -> - | J32: =AD32 -> Select | U32: =IF('PR_Programmatic Progress_1A'!A32="Select","",'PR_Programmatic Progress_1A'!A32) | V32: =IF('PR_Programmatic Progress_1A'!B32="","",'PR_Programmatic Progress_1A'!B32) | Z32: =IF('PR_Programmatic Progress_1A'!I32="","",'PR_Programmatic Progress_1A'!I32) -> - | AA32: =IF('PR_Programmatic Progress_1A'!J32="","",'PR_Programmatic Progress_1A'!J32) -> - | AB32: =IF('PR_Programmatic Progress_1A'!K32="","",'PR_Programmatic Progress_1A'!K32) -> - | AC32: =IF('PR_Programmatic Progress_1A'!L32="","",'PR_Programmatic Progress_1A'!L32) -> - | AD32: ='PR_Programmatic Progress_1A'!M32 -> Select
A33: =U33 | B33: =V33 | F33: =Z33 -> - | G33: =AA33 -> - | H33: =AB33 -> - | I33: =AC33 -> - | J33: =AD33 -> Select | U33: =IF('PR_Programmatic Progress_1A'!A33="Select","",'PR_Programmatic Progress_1A'!A33) | V33: =IF('PR_Programmatic Progress_1A'!B33="","",'PR_Programmatic Progress_1A'!B33) | Z33: =IF('PR_Programmatic Progress_1A'!I33="","",'PR_Programmatic Progress_1A'!I33) -> - | AA33: =IF('PR_Programmatic Progress_1A'!J33="","",'PR_Programmatic Progress_1A'!J33) -> - | AB33: =IF('PR_Programmatic Progress_1A'!K33="","",'PR_Programmatic Progress_1A'!K33) -> - | AC33: =IF('PR_Programmatic Progress_1A'!L33="","",'PR_Programmatic Progress_1A'!L33) -> - | AD33: ='PR_Programmatic Progress_1A'!M33 -> Select
A34: =U34 | B34: =V34 | F34: =Z34 -> - | G34: =AA34 -> - | H34: =AB34 -> - | I34: =AC34 -> - | J34: =AD34 -> Select | U34: =IF('PR_Programmatic Progress_1A'!A34="Select","",'PR_Programmatic Progress_1A'!A34) | V34: =IF('PR_Programmatic Progress_1A'!B34="","",'PR_Programmatic Progress_1A'!B34) | Z34: =IF('PR_Programmatic Progress_1A'!I34="","",'PR_Programmatic Progress_1A'!I34) -> - | AA34: =IF('PR_Programmatic Progress_1A'!J34="","",'PR_Programmatic Progress_1A'!J34) -> - | AB34: =IF('PR_Programmatic Progress_1A'!K34="","",'PR_Programmatic Progress_1A'!K34) -> - | AC34: =IF('PR_Programmatic Progress_1A'!L34="","",'PR_Programmatic Progress_1A'!L34) -> - | AD34: ='PR_Programmatic Progress_1A'!M34 -> Select
A35: =U35 | B35: =V35 | F35: =Z35 -> - | G35: =AA35 -> - | H35: =AB35 -> - | I35: =AC35 -> - | J35: =AD35 -> Select | U35: =IF('PR_Programmatic Progress_1A'!A35="Select","",'PR_Programmatic Progress_1A'!A35) | V35: =IF('PR_Programmatic Progress_1A'!B35="","",'PR_Programmatic Progress_1A'!B35) | Z35: =IF('PR_Programmatic Progress_1A'!I35="","",'PR_Programmatic Progress_1A'!I35) -> - | AA35: =IF('PR_Programmatic Progress_1A'!J35="","",'PR_Programmatic Progress_1A'!J35) -> - | AB35: =IF('PR_Programmatic Progress_1A'!K35="","",'PR_Programmatic Progress_1A'!K35) -> - | AC35: =IF('PR_Programmatic Progress_1A'!L35="","",'PR_Programmatic Progress_1A'!L35) -> - | AD35: ='PR_Programmatic Progress_1A'!M35 -> Select
A36: =U36 | B36: =V36 | F36: =Z36 -> - | G36: =AA36 -> - | H36: =AB36 -> - | I36: =AC36 -> - | J36: =AD36 -> Select | U36: =IF('PR_Programmatic Progress_1A'!A36="Select","",'PR_Programmatic Progress_1A'!A36) | V36: =IF('PR_Programmatic Progress_1A'!B36="","",'PR_Programmatic Progress_1A'!B36) | Z36: =IF('PR_Programmatic Progress_1A'!I36="","",'PR_Programmatic Progress_1A'!I36) -> - | AA36: =IF('PR_Programmatic Progress_1A'!J36="","",'PR_Programmatic Progress_1A'!J36) -> - | AB36: =IF('PR_Programmatic Progress_1A'!K36="","",'PR_Programmatic Progress_1A'!K36) -> - | AC36: =IF('PR_Programmatic Progress_1A'!L36="","",'PR_Programmatic Progress_1A'!L36) -> - | AD36: ='PR_Programmatic Progress_1A'!M36 -> Select

Sheet LFA_Programmatic Progress_1B
A1: LFA On-going Progress Review and Disbursement Recommendation
A2: PROGRESS UPDATE PERIOD
A3: Grant number: | D3: =IF('LFA_Programmatic Progress_1A'!C7="","",'LFA_Programmatic Progress_1A'!C7) -> MNR-809-G04-H
A4: Progress Update - Reporting Period: | D4: Cycle: | E4: =IF('LFA_Programmatic Progress_1A'!D12="Select","",'LFA_Programmatic Progress_1A'!D12) -> Quarter | F4: Number: | G4: =IF('LFA_Programmatic Progress_1A'!F12="Select","",'LFA_Programmatic Progress_1A'!F12) -> 7
A5: Progress Update - Period Covered: | D5: Beginning Date: | E5: =IF('LFA_Programmatic Progress_1A'!D13="","",'LFA_Programmatic Progress_1A'!D13) -> 40452 | F5: End Date: | G5: =IF('LFA_Programmatic Progress_1A'!F13="","",'LFA_Programmatic Progress_1A'!F13) -> 40543
A6: Progress Update - Number: | D6: =IF('LFA_Programmatic Progress_1A'!C14="Select","",'LFA_Programmatic Progress_1A'!C14) -> 5
A8: Note: All programmatic indicators contained in the current Performance Framework should be listed, regardless of whether there are targets/results for the period covered by the Progress Update or whether the targets have been met in previous periods.
A9: B. Programmatic Indicators | W9: B. Programmatic Indicators
A10: Objective No. | B10: Indicator No. | C10: Indicator Description | H10: Tied to | I10: Targets cumulative? | J10: Top 10 indicator? | K10: Intended Target to date (from PF) | L10: Actual Result to date (as reported by PR) | M10: Verification Method | O10: Verified Result | P10: % achievement (Please calculate as appropriate) | Q10: LFA analysis on progress to date and any variance between targets and results, and any other comments (this should not be a “Copy and Paste” of the reasons provided by the PR) | W10: Objective No. | X10: Indicator No. | Y10: Indicator Description | AD10: Tied to | AE10: Targets cumulative? | AF10: Top 10 indicator? | AG10: Intended Target to date (from PF) | AH10: Actual Result to date (as reported by PR)
A12: =W12 -> #REF! | B12: =X12 -> #REF! | C12: =Y12 -> #REF! | H12: =AD12 -> #REF! | I12: =AE12 -> #REF! | J12: =AF12 -> #REF! | K12: =AG12 -> #REF! | L12: =AH12 -> #REF! | M12: PR On-site Visit | O12: 62104 | P12: 1.06 | Q12: A review of the SR and PR reports showed a marked improvement in data collection and reporting. 16,292 males and females were reached during the period under review.Various participatory methods such as Stepping Stones, Kabilo and STAR were used to reach people within the communities. These are proven and effective participatory methods. PR should continue to collaborate with SRs/SGs to implement and monitor these activities within the communities. | W12: =IF('PR_Programmatic Progress_1B'!#REF!="","",'PR_Programmatic Progress_1B'!#REF!) -> #REF! | X12: =IF('PR_Programmatic Progress_1B'!#REF!="","",'PR_Programmatic Progress_1B'!#REF!) -> #REF! | Y12: =IF('PR_Programmatic Progress_1B'!#REF!="","",'PR_Programmatic Progress_1B'!#REF!) -> #REF! | AD12: =IF('PR_Programmatic Progress_1B'!#REF!="","",'PR_Programmatic Progress_1B'!#REF!) -> #REF! | AE12: =IF('PR_Programmatic Progress_1B'!#REF!="","",'PR_Programmatic Progress_1B'!#REF!) -> #REF! | AF12: =IF('PR_Programmatic Progress_1B'!#REF!="","",'PR_Programmatic Progress_1B'!#REF!) -> #REF! | AG12: =IF('PR_Programmatic Progress_1B'!#REF!="","",'PR_Programmatic Progress_1B'!#REF!) -> #REF! | AH12: =IF('PR_Programmatic Progress_1B'!#REF!="","",'PR_Programmatic Progress_1B'!#REF!) -> #REF!
A13: =W13 -> 1 | B13: =X13 -> 1.2 | C13: =Y13 -> Number of commercial sex workers reached with prevention interventions | H13: =AD13 -> GF | I13: =AE13 -> Y-cumulative annually | J13: =AF13 -> Yes - Top 10 | K13: =AG13 -> 225 | L13: =AH13 -> 100 | M13: PR On-site Visit | O13: 15234 | P13: 164% (120%) | Q13: 5,870 young people aged 10-24 were reached in and out of school for the period of review. Nova Scotia Gambia Association (NSGA) commenced implementation as a SG under CRS (SR) during this period. NSGA is one of the pioneer implementers of LSBHE in the Gambia. There has been a marked improvement in the quality of data collected and reported for the period, although some arithmetic errors were noted in the result for this indicator. Finally, the overachievement of the target is due to the "roll-over" effect from previous quarters. | W13: =IF('PR_Programmatic Progress_1B'!A12="","",'PR_Programmatic Progress_1B'!A12) -> 1 | X13: =IF('PR_Programmatic Progress_1B'!B12="","",'PR_Programmatic Progress_1B'!B12) -> 1.2 | Y13: =IF('PR_Programmatic Progress_1B'!C12="","",'PR_Programmatic Progress_1B'!C12) -> Number of commercial sex workers reached with prevention interventions | AD13: =IF('PR_Programmatic Progress_1B'!G12="","",'PR_Programmatic Progress_1B'!G12) -> GF | AE13: =IF('PR_Programmatic Progress_1B'!H12="","",'PR_Programmatic Progress_1B'!H12) -> Y-cumulative annually | AF13: =IF('PR_Programmatic Progress_1B'!I12="","",'PR_Programmatic Progress_1B'!I12) -> Yes - Top 10 | AG13: =IF('PR_Programmatic Progress_1B'!L12="","",'PR_Programmatic Progress_1B'!L12) -> 225 | AH13: =IF('PR_Programmatic Progress_1B'!M12="","",'PR_Programmatic Progress_1B'!M12) -> 100
A14: =W14 -> 1 | B14: =X14 -> 1.3 | C14: =Y14 -> Number of medical (doctors and nurses) and non-medical staff (psychologists, social assistants, peer consultants) trained in HIV/AIDS | H14: =AD14 -> GF | I14: =AE14 -> Y-over program term | J14: =AF14 -> Yes - Top 10 | K14: =AG14 -> 400 | L14: =AH14 -> 594 | M14: PR On-site Visit | O14: 125 | P14: 1 | Q14: During the period of reporting 38 additional CSWs were trained as Peer Health Educators. It must be noted that there has been a marked improvement in the quality of training reports. In spite of this, the SR/SG should be strengthened to continue to improve the quality of the training reports. PR/SR should also ensure that Peer Health Education (PHE) tools are regularly reviewed to assess the need for revision of the tools. In addition, follow-up monitoring and supportive supervision should be undertaken on a regular basis. | W14: =IF('PR_Programmatic Progress_1B'!A13="","",'PR_Programmatic Progress_1B'!A13) -> 1 | X14: =IF('PR_Programmatic Progress_1B'!B13="","",'PR_Programmatic Progress_1B'!B13) -> 1.3 | Y14: =IF('PR_Programmatic Progress_1B'!C13="","",'PR_Programmatic Progress_1B'!C13) -> Number of medical (doctors and nurses) and non-medical staff (psychologists, social assistants, peer consultants) trained in HIV/AIDS | AD14: =IF('PR_Programmatic Progress_1B'!G13="","",'PR_Programmatic Progress_1B'!G13) -> GF | AE14: =IF('PR_Programmatic Progress_1B'!H13="","",'PR_Programmatic Progress_1B'!H13) -> Y-over program term | AF14: =IF('PR_Programmatic Progress_1B'!I13="","",'PR_Programmatic Progress_1B'!I13) -> Yes - Top 10 | AG14: =IF('PR_Programmatic Progress_1B'!L13="","",'PR_Programmatic Progress_1B'!L13) -> 400 | AH14: =IF('PR_Programmatic Progress_1B'!M13="","",'PR_Programmatic Progress_1B'!M13) -> 594
A15: =W15 -> 1 | B15: =X15 -> 1.4 | C15: =Y15 -> Number of IDUs on opioid substitution therapy | H15: =AD15 -> GF | I15: =AE15 -> Y-over program term | J15: =AF15 -> Yes - Top 10 | K15: =AG15 -> 100 | L15: =AH15 -> 0 | M15: PR On-site Visit | O15: 1255 | P15: 130% (120%) | Q15: 450 students and teachers were trained in LSE during the period of review. NSGA commenced implementation as a SG under CRS (SR) during this period. NSGA is one of the pioneer implementers of LSBHE in the Gambia. There has been an improvement in the quality of data collected and reported. | W15: =IF('PR_Programmatic Progress_1B'!A14="","",'PR_Programmatic Progress_1B'!A14) -> 1 | X15: =IF('PR_Programmatic Progress_1B'!B14="","",'PR_Programmatic Progress_1B'!B14) -> 1.4 | Y15: =IF('PR_Programmatic Progress_1B'!C14="","",'PR_Programmatic Progress_1B'!C14) -> Number of IDUs on opioid substitution therapy | AD15: =IF('PR_Programmatic Progress_1B'!G14="","",'PR_Programmatic Progress_1B'!G14) -> GF | AE15: =IF('PR_Programmatic Progress_1B'!H14="","",'PR_Programmatic Progress_1B'!H14) -> Y-over program term | AF15: =IF('PR_Programmatic Progress_1B'!I14="","",'PR_Programmatic Progress_1B'!I14) -> Yes - Top 10 | AG15: =IF('PR_Programmatic Progress_1B'!L14="","",'PR_Programmatic Progress_1B'!L14) -> 100 | AH15: =IF('PR_Programmatic Progress_1B'!M14="","",'PR_Programmatic Progress_1B'!M14) -> 0
A16: =W16 -> #REF! | B16: =X16 -> #REF! | C16: =Y16 -> #REF! | H16: =AD16 -> #REF! | I16: =AE16 -> #REF! | J16: =AF16 -> #REF! | K16: =AG16 -> #REF! | L16: =AH16 -> #REF! | M16: PR On-site Visit | O16: 398807 | P16: 0.8 | Q16: During the period under review, no female condoms were available for distribution; however 169,617 male condoms were distributed. Socio-cultural and religious factors also affected the uptake and use of condoms during the period under review. In spite of these challenges, there is need for PR to restrategise to ensure that the Most At Risk Population (MARPs) are regularly reached with condoms in order to ensure that new cases of HIV are minimised. Interactions with some incountry partners (including NAS) revealed that there have been complaints by some of the MARPs that they do not get regular supply of condoms. Finally, it was observed that PR experienced delays in the procurement of condoms. | W16: =IF('PR_Programmatic Progress_1B'!#REF!="","",'PR_Programmatic Progress_1B'!#REF!) -> #REF! | X16: =IF('PR_Programmatic Progress_1B'!#REF!="","",'PR_Programmatic Progress_1B'!#REF!) -> #REF! | Y16: =IF('PR_Programmatic Progress_1B'!#REF!="","",'PR_Programmatic Progress_1B'!#REF!) -> #REF! | AD16: =IF('PR_Programmatic Progress_1B'!#REF!="","",'PR_Programmatic Progress_1B'!#REF!) -> #REF! | AE16: =IF('PR_Programmatic Progress_1B'!#REF!="","",'PR_Programmatic Progress_1B'!#REF!) -> #REF! | AF16: =IF('PR_Programmatic Progress_1B'!#REF!="","",'PR_Programmatic Progress_1B'!#REF!) -> #REF! | AG16: =IF('PR_Programmatic Progress_1B'!#REF!="","",'PR_Programmatic Progress_1B'!#REF!) -> #REF! | AH16: =IF('PR_Programmatic Progress_1B'!#REF!="","",'PR_Programmatic Progress_1B'!#REF!) -> #REF!
A17: =W17 | B17: =X17 | C17: =Y17 | H17: =AD17 | I17: =AE17 | J17: =AF17 | K17: =AG17 | L17: =AH17 | M17: Desk Review | O17: 396 | P17: 0.18 | Q17: The under-achievement of this target was discussed during the November 2010 VoI, which coincided with the visit of the FPM. A recommendation was made to the PR to conduct a desk review to detemine a realistic baseline for "PLHIV provided with HBC at the home and community level" and revise the relevant information. PR subsequently developed a proposal and shared with LFA/GF in February 2011. The findings of the desk review are expected at the end of March 2011. | W17: =IF('PR_Programmatic Progress_1B'!A16="","",'PR_Programmatic Progress_1B'!A16) | X17: =IF('PR_Programmatic Progress_1B'!B16="","",'PR_Programmatic Progress_1B'!B16) | Y17: =IF('PR_Programmatic Progress_1B'!C16="","",'PR_Programmatic Progress_1B'!C16) | AD17: =IF('PR_Programmatic Progress_1B'!G16="","",'PR_Programmatic Progress_1B'!G16) | AE17: =IF('PR_Programmatic Progress_1B'!H16="","",'PR_Programmatic Progress_1B'!H16) | AF17: =IF('PR_Programmatic Progress_1B'!I16="","",'PR_Programmatic Progress_1B'!I16) | AG17: =IF('PR_Programmatic Progress_1B'!L16="","",'PR_Programmatic Progress_1B'!L16) | AH17: =IF('PR_Programmatic Progress_1B'!M16="","",'PR_Programmatic Progress_1B'!M16)
A18: =W18 | B18: =X18 | C18: =Y18 | H18: =AD18 | I18: =AE18 | J18: =AF18 | K18: =AG18 | L18: =AH18 | M18: Desk Review | O18: 3221 | P18: 0.99 | Q18: During this period of review, 790 OVCs received educational support and 2,431 received nutritional support. Improved collaboration between the PR and SRs on one hand and also between the ART centres and Ministry of Education facilitated increased identification of OVCs within the communities and in the schools. A review of some of the receipts provided by some schools revealed that some of the schools are still using unorthodox documents as receipts. In view of this, PR should encourage appropriate supporting documentation to be provided by private schools for the funds they receive from the program for OVCs . | W18: =IF('PR_Programmatic Progress_1B'!A17="","",'PR_Programmatic Progress_1B'!A17) | X18: =IF('PR_Programmatic Progress_1B'!B17="","",'PR_Programmatic Progress_1B'!B17) | Y18: =IF('PR_Programmatic Progress_1B'!C17="","",'PR_Programmatic Progress_1B'!C17) | AD18: =IF('PR_Programmatic Progress_1B'!G17="","",'PR_Programmatic Progress_1B'!G17) | AE18: =IF('PR_Programmatic Progress_1B'!H17="","",'PR_Programmatic Progress_1B'!H17) | AF18: =IF('PR_Programmatic Progress_1B'!I17="","",'PR_Programmatic Progress_1B'!I17) | AG18: =IF('PR_Programmatic Progress_1B'!L17="","",'PR_Programmatic Progress_1B'!L17) | AH18: =IF('PR_Programmatic Progress_1B'!M17="","",'PR_Programmatic Progress_1B'!M17)
A19: =W19 | B19: =X19 | C19: =Y19 | H19: =AD19 -> Select | I19: =AE19 -> Select | J19: =AF19 -> Select | K19: =AG19 -> - | L19: =AH19 -> - | W19: =IF('PR_Programmatic Progress_1B'!A18="","",'PR_Programmatic Progress_1B'!A18) | X19: =IF('PR_Programmatic Progress_1B'!B18="","",'PR_Programmatic Progress_1B'!B18) | Y19: =IF('PR_Programmatic Progress_1B'!C18="","",'PR_Programmatic Progress_1B'!C18) | AD19: =IF('PR_Programmatic Progress_1B'!G18="","",'PR_Programmatic Progress_1B'!G18) -> Select | AE19: =IF('PR_Programmatic Progress_1B'!H18="","",'PR_Programmatic Progress_1B'!H18) -> Select | AF19: =IF('PR_Programmatic Progress_1B'!I18="","",'PR_Programmatic Progress_1B'!I18) -> Select | AG19: =IF('PR_Programmatic Progress_1B'!L18="","",'PR_Programmatic Progress_1B'!L18) -> - | AH19: =IF('PR_Programmatic Progress_1B'!M18="","",'PR_Programmatic Progress_1B'!M18) -> -
A20: =W20 | B20: =X20 | C20: =Y20 | H20: =AD20 -> Select | I20: =AE20 -> Select | J20: =AF20 -> Select | K20: =AG20 -> - | L20: =AH20 -> - | W20: =IF('PR_Programmatic Progress_1B'!A19="","",'PR_Programmatic Progress_1B'!A19) | X20: =IF('PR_Programmatic Progress_1B'!B19="","",'PR_Programmatic Progress_1B'!B19) | Y20: =IF('PR_Programmatic Progress_1B'!C19="","",'PR_Programmatic Progress_1B'!C19) | AD20: =IF('PR_Programmatic Progress_1B'!G19="","",'PR_Programmatic Progress_1B'!G19) -> Select | AE20: =IF('PR_Programmatic Progress_1B'!H19="","",'PR_Programmatic Progress_1B'!H19) -> Select | AF20: =IF('PR_Programmatic Progress_1B'!I19="","",'PR_Programmatic Progress_1B'!I19) -> Select | AG20: =IF('PR_Programmatic Progress_1B'!L19="","",'PR_Programmatic Progress_1B'!L19) -> - | AH20: =IF('PR_Programmatic Progress_1B'!M19="","",'PR_Programmatic Progress_1B'!M19) -> -
A21: =W21 -> #REF! | B21: =X21 -> #REF! | C21: =Y21 -> #REF! | H21: =AD21 -> #REF! | I21: =AE21 -> #REF! | J21: =AF21 -> #REF! | K21: =AG21 -> #REF! | L21: =AH21 -> #REF! | W21: =IF('PR_Programmatic Progress_1B'!#REF!="","",'PR_Programmatic Progress_1B'!#REF!) -> #REF! | X21: =IF('PR_Programmatic Progress_1B'!#REF!="","",'PR_Programmatic Progress_1B'!#REF!) -> #REF! | Y21: =IF('PR_Programmatic Progress_1B'!#REF!="","",'PR_Programmatic Progress_1B'!#REF!) -> #REF! | AD21: =IF('PR_Programmatic Progress_1B'!#REF!="","",'PR_Programmatic Progress_1B'!#REF!) -> #REF! | AE21: =IF('PR_Programmatic Progress_1B'!#REF!="","",'PR_Programmatic Progress_1B'!#REF!) -> #REF! | AF21: =IF('PR_Programmatic Progress_1B'!#REF!="","",'PR_Programmatic Progress_1B'!#REF!) -> #REF! | AG21: =IF('PR_Programmatic Progress_1B'!#REF!="","",'PR_Programmatic Progress_1B'!#REF!) -> #REF! | AH21: =IF('PR_Programmatic Progress_1B'!#REF!="","",'PR_Programmatic Progress_1B'!#REF!) -> #REF!
A22: =W22 -> #REF! | B22: =X22 -> #REF! | C22: =Y22 -> #REF! | H22: =AD22 -> #REF! | I22: =AE22 -> #REF! | J22: =AF22 -> #REF! | K22: =AG22 -> #REF! | L22: =AH22 -> #REF! | W22: =IF('PR_Programmatic Progress_1B'!#REF!="","",'PR_Programmatic Progress_1B'!#REF!) -> #REF! | X22: =IF('PR_Programmatic Progress_1B'!#REF!="","",'PR_Programmatic Progress_1B'!#REF!) -> #REF! | Y22: =IF('PR_Programmatic Progress_1B'!#REF!="","",'PR_Programmatic Progress_1B'!#REF!) -> #REF! | AD22: =IF('PR_Programmatic Progress_1B'!#REF!="","",'PR_Programmatic Progress_1B'!#REF!) -> #REF! | AE22: =IF('PR_Programmatic Progress_1B'!#REF!="","",'PR_Programmatic Progress_1B'!#REF!) -> #REF! | AF22: =IF('PR_Programmatic Progress_1B'!#REF!="","",'PR_Programmatic Progress_1B'!#REF!) -> #REF! | AG22: =IF('PR_Programmatic Progress_1B'!#REF!="","",'PR_Programmatic Progress_1B'!#REF!) -> #REF! | AH22: =IF('PR_Programmatic Progress_1B'!#REF!="","",'PR_Programmatic Progress_1B'!#REF!) -> #REF!
A23: =W23 -> #REF! | B23: =X23 -> #REF! | C23: =Y23 -> #REF! | H23: =AD23 -> #REF! | I23: =AE23 -> #REF! | J23: =AF23 -> #REF! | K23: =AG23 -> #REF! | L23: =AH23 -> #REF! | W23: =IF('PR_Programmatic Progress_1B'!#REF!="","",'PR_Programmatic Progress_1B'!#REF!) -> #REF! | X23: =IF('PR_Programmatic Progress_1B'!#REF!="","",'PR_Programmatic Progress_1B'!#REF!) -> #REF! | Y23: =IF('PR_Programmatic Progress_1B'!#REF!="","",'PR_Programmatic Progress_1B'!#REF!) -> #REF! | AD23: =IF('PR_Programmatic Progress_1B'!#REF!="","",'PR_Programmatic Progress_1B'!#REF!) -> #REF! | AE23: =IF('PR_Programmatic Progress_1B'!#REF!="","",'PR_Programmatic Progress_1B'!#REF!) -> #REF! | AF23: =IF('PR_Programmatic Progress_1B'!#REF!="","",'PR_Programmatic Progress_1B'!#REF!) -> #REF! | AG23: =IF('PR_Programmatic Progress_1B'!#REF!="","",'PR_Programmatic Progress_1B'!#REF!) -> #REF! | AH23: =IF('PR_Programmatic Progress_1B'!#REF!="","",'PR_Programmatic Progress_1B'!#REF!) -> #REF!
A24: =W24 -> #REF! | B24: =X24 -> #REF! | C24: =Y24 -> #REF! | H24: =AD24 -> #REF! | I24: =AE24 -> #REF! | J24: =AF24 -> #REF! | K24: =AG24 -> #REF! | L24: =AH24 -> #REF! | W24: =IF('PR_Programmatic Progress_1B'!#REF!="","",'PR_Programmatic Progress_1B'!#REF!) -> #REF! | X24: =IF('PR_Programmatic Progress_1B'!#REF!="","",'PR_Programmatic Progress_1B'!#REF!) -> #REF! | Y24: =IF('PR_Programmatic Progress_1B'!#REF!="","",'PR_Programmatic Progress_1B'!#REF!) -> #REF! | AD24: =IF('PR_Programmatic Progress_1B'!#REF!="","",'PR_Programmatic Progress_1B'!#REF!) -> #REF! | AE24: =IF('PR_Programmatic Progress_1B'!#REF!="","",'PR_Programmatic Progress_1B'!#REF!) -> #REF! | AF24: =IF('PR_Programmatic Progress_1B'!#REF!="","",'PR_Programmatic Progress_1B'!#REF!) -> #REF! | AG24: =IF('PR_Programmatic Progress_1B'!#REF!="","",'PR_Programmatic Progress_1B'!#REF!) -> #REF! | AH24: =IF('PR_Programmatic Progress_1B'!#REF!="","",'PR_Programmatic Progress_1B'!#REF!) -> #REF!
A25: =W25 -> #REF! | B25: =X25 -> #REF! | C25: =Y25 -> #REF! | H25: =AD25 -> #REF! | I25: =AE25 -> #REF! | J25: =AF25 -> #REF! | K25: =AG25 -> #REF! | L25: =AH25 -> #REF! | W25: =IF('PR_Programmatic Progress_1B'!#REF!="","",'PR_Programmatic Progress_1B'!#REF!) -> #REF! | X25: =IF('PR_Programmatic Progress_1B'!#REF!="","",'PR_Programmatic Progress_1B'!#REF!) -> #REF! | Y25: =IF('PR_Programmatic Progress_1B'!#REF!="","",'PR_Programmatic Progress_1B'!#REF!) -> #REF! | AD25: =IF('PR_Programmatic Progress_1B'!#REF!="","",'PR_Programmatic Progress_1B'!#REF!) -> #REF! | AE25: =IF('PR_Programmatic Progress_1B'!#REF!="","",'PR_Programmatic Progress_1B'!#REF!) -> #REF! | AF25: =IF('PR_Programmatic Progress_1B'!#REF!="","",'PR_Programmatic Progress_1B'!#REF!) -> #REF! | AG25: =IF('PR_Programmatic Progress_1B'!#REF!="","",'PR_Programmatic Progress_1B'!#REF!) -> #REF! | AH25: =IF('PR_Programmatic Progress_1B'!#REF!="","",'PR_Programmatic Progress_1B'!#REF!) -> #REF!
A26: =W26 -> #REF! | B26: =X26 -> #REF! | C26: =Y26 -> #REF! | H26: =AD26 -> #REF! | I26: =AE26 -> #REF! | J26: =AF26 -> #REF! | K26: =AG26 -> #REF! | L26: =AH26 -> #REF! | W26: =IF('PR_Programmatic Progress_1B'!#REF!="","",'PR_Programmatic Progress_1B'!#REF!) -> #REF! | X26: =IF('PR_Programmatic Progress_1B'!#REF!="","",'PR_Programmatic Progress_1B'!#REF!) -> #REF! | Y26: =IF('PR_Programmatic Progress_1B'!#REF!="","",'PR_Programmatic Progress_1B'!#REF!) -> #REF! | AD26: =IF('PR_Programmatic Progress_1B'!#REF!="","",'PR_Programmatic Progress_1B'!#REF!) -> #REF! | AE26: =IF('PR_Programmatic Progress_1B'!#REF!="","",'PR_Programmatic Progress_1B'!#REF!) -> #REF! | AF26: =IF('PR_Programmatic Progress_1B'!#REF!="","",'PR_Programmatic Progress_1B'!#REF!) -> #REF! | AG26: =IF('PR_Programmatic Progress_1B'!#REF!="","",'PR_Programmatic Progress_1B'!#REF!) -> #REF! | AH26: =IF('PR_Programmatic Progress_1B'!#REF!="","",'PR_Programmatic Progress_1B'!#REF!) -> #REF!
A27: =W27 | B27: =X27 | C27: =Y27 | H27: =AD27 -> Select | I27: =AE27 -> Select | J27: =AF27 -> Select | K27: =AG27 -> - | L27: =AH27 -> - | W27: =IF('PR_Programmatic Progress_1B'!A20="","",'PR_Programmatic Progress_1B'!A20) | X27: =IF('PR_Programmatic Progress_1B'!B20="","",'PR_Programmatic Progress_1B'!B20) | Y27: =IF('PR_Programmatic Progress_1B'!C20="","",'PR_Programmatic Progress_1B'!C20) | AD27: =IF('PR_Programmatic Progress_1B'!G20="","",'PR_Programmatic Progress_1B'!G20) -> Select | AE27: =IF('PR_Programmatic Progress_1B'!H20="","",'PR_Programmatic Progress_1B'!H20) -> Select | AF27: =IF('PR_Programmatic Progress_1B'!I20="","",'PR_Programmatic Progress_1B'!I20) -> Select | AG27: =IF('PR_Programmatic Progress_1B'!L20="","",'PR_Programmatic Progress_1B'!L20) -> - | AH27: =IF('PR_Programmatic Progress_1B'!M20="","",'PR_Programmatic Progress_1B'!M20) -> -
A28: =W28 | B28: =X28 | C28: =Y28 | H28: =AD28 -> Select | I28: =AE28 -> Select | J28: =AF28 -> Select | K28: =AG28 -> - | L28: =AH28 -> - | W28: =IF('PR_Programmatic Progress_1B'!A21="","",'PR_Programmatic Progress_1B'!A21) | X28: =IF('PR_Programmatic Progress_1B'!B21="","",'PR_Programmatic Progress_1B'!B21) | Y28: =IF('PR_Programmatic Progress_1B'!C21="","",'PR_Programmatic Progress_1B'!C21) | AD28: =IF('PR_Programmatic Progress_1B'!G21="","",'PR_Programmatic Progress_1B'!G21) -> Select | AE28: =IF('PR_Programmatic Progress_1B'!H21="","",'PR_Programmatic Progress_1B'!H21) -> Select | AF28: =IF('PR_Programmatic Progress_1B'!I21="","",'PR_Programmatic Progress_1B'!I21) -> Select | AG28: =IF('PR_Programmatic Progress_1B'!L21="","",'PR_Programmatic Progress_1B'!L21) -> - | AH28: =IF('PR_Programmatic Progress_1B'!M21="","",'PR_Programmatic Progress_1B'!M21) -> -
A29: =W29 | B29: =X29 | C29: =Y29 | H29: =AD29 -> Select | I29: =AE29 -> Select | J29: =AF29 -> Select | K29: =AG29 -> - | L29: =AH29 -> - | W29: =IF('PR_Programmatic Progress_1B'!A22="","",'PR_Programmatic Progress_1B'!A22) | X29: =IF('PR_Programmatic Progress_1B'!B22="","",'PR_Programmatic Progress_1B'!B22) | Y29: =IF('PR_Programmatic Progress_1B'!C22="","",'PR_Programmatic Progress_1B'!C22) | AD29: =IF('PR_Programmatic Progress_1B'!G22="","",'PR_Programmatic Progress_1B'!G22) -> Select | AE29: =IF('PR_Programmatic Progress_1B'!H22="","",'PR_Programmatic Progress_1B'!H22) -> Select | AF29: =IF('PR_Programmatic Progress_1B'!I22="","",'PR_Programmatic Progress_1B'!I22) -> Select | AG29: =IF('PR_Programmatic Progress_1B'!L22="","",'PR_Programmatic Progress_1B'!L22) -> - | AH29: =IF('PR_Programmatic Progress_1B'!M22="","",'PR_Programmatic Progress_1B'!M22) -> -
A30: =W30 | B30: =X30 | C30: =Y30 | H30: =AD30 -> Select | I30: =AE30 -> Select | J30: =AF30 -> Select | K30: =AG30 -> - | L30: =AH30 -> - | W30: =IF('PR_Programmatic Progress_1B'!A23="","",'PR_Programmatic Progress_1B'!A23) | X30: =IF('PR_Programmatic Progress_1B'!B23="","",'PR_Programmatic Progress_1B'!B23) | Y30: =IF('PR_Programmatic Progress_1B'!C23="","",'PR_Programmatic Progress_1B'!C23) | AD30: =IF('PR_Programmatic Progress_1B'!G23="","",'PR_Programmatic Progress_1B'!G23) -> Select | AE30: =IF('PR_Programmatic Progress_1B'!H23="","",'PR_Programmatic Progress_1B'!H23) -> Select | AF30: =IF('PR_Programmatic Progress_1B'!I23="","",'PR_Programmatic Progress_1B'!I23) -> Select | AG30: =IF('PR_Programmatic Progress_1B'!L23="","",'PR_Programmatic Progress_1B'!L23) -> - | AH30: =IF('PR_Programmatic Progress_1B'!M23="","",'PR_Programmatic Progress_1B'!M23) -> -
A31: =W31 | B31: =X31 | C31: =Y31 | H31: =AD31 -> Select | I31: =AE31 -> Select | J31: =AF31 -> Select | K31: =AG31 -> - | L31: =AH31 -> - | W31: =IF('PR_Programmatic Progress_1B'!A24="","",'PR_Programmatic Progress_1B'!A24) | X31: =IF('PR_Programmatic Progress_1B'!B24="","",'PR_Programmatic Progress_1B'!B24) | Y31: =IF('PR_Programmatic Progress_1B'!C24="","",'PR_Programmatic Progress_1B'!C24) | AD31: =IF('PR_Programmatic Progress_1B'!G24="","",'PR_Programmatic Progress_1B'!G24) -> Select | AE31: =IF('PR_Programmatic Progress_1B'!H24="","",'PR_Programmatic Progress_1B'!H24) -> Select | AF31: =IF('PR_Programmatic Progress_1B'!I24="","",'PR_Programmatic Progress_1B'!I24) -> Select | AG31: =IF('PR_Programmatic Progress_1B'!L24="","",'PR_Programmatic Progress_1B'!L24) -> - | AH31: =IF('PR_Programmatic Progress_1B'!M24="","",'PR_Programmatic Progress_1B'!M24) -> -
A33: =W33 | B33: =X33 | C33: =Y33 | H33: =AD33 -> Select | I33: =AE33 -> Select | J33: =AF33 -> Select | K33: =AG33 -> - | L33: =AH33 -> - | W33: =IF('PR_Programmatic Progress_1B'!A26="","",'PR_Programmatic Progress_1B'!A26) | X33: =IF('PR_Programmatic Progress_1B'!B26="","",'PR_Programmatic Progress_1B'!B26) | Y33: =IF('PR_Programmatic Progress_1B'!C26="","",'PR_Programmatic Progress_1B'!C26) | AD33: =IF('PR_Programmatic Progress_1B'!G26="","",'PR_Programmatic Progress_1B'!G26) -> Select | AE33: =IF('PR_Programmatic Progress_1B'!H26="","",'PR_Programmatic Progress_1B'!H26) -> Select | AF33: =IF('PR_Programmatic Progress_1B'!I26="","",'PR_Programmatic Progress_1B'!I26) -> Select | AG33: =IF('PR_Programmatic Progress_1B'!L26="","",'PR_Programmatic Progress_1B'!L26) -> - | AH33: =IF('PR_Programmatic Progress_1B'!M26="","",'PR_Programmatic Progress_1B'!M26) -> -
A34: =W34 | B34: =X34 | C34: =Y34 | H34: =AD34 -> Select | I34: =AE34 -> Select | J34: =AF34 -> Select | K34: =AG34 -> - | L34: =AH34 -> - | W34: =IF('PR_Programmatic Progress_1B'!A27="","",'PR_Programmatic Progress_1B'!A27) | X34: =IF('PR_Programmatic Progress_1B'!B27="","",'PR_Programmatic Progress_1B'!B27) | Y34: =IF('PR_Programmatic Progress_1B'!C27="","",'PR_Programmatic Progress_1B'!C27) | AD34: =IF('PR_Programmatic Progress_1B'!G27="","",'PR_Programmatic Progress_1B'!G27) -> Select | AE34: =IF('PR_Programmatic Progress_1B'!H27="","",'PR_Programmatic Progress_1B'!H27) -> Select | AF34: =IF('PR_Programmatic Progress_1B'!I27="","",'PR_Programmatic Progress_1B'!I27) -> Select | AG34: =IF('PR_Programmatic Progress_1B'!L27="","",'PR_Programmatic Progress_1B'!L27) -> - | AH34: =IF('PR_Programmatic Progress_1B'!M27="","",'PR_Programmatic Progress_1B'!M27) -> -
A35: =W35 | B35: =X35 | C35: =Y35 | H35: =AD35 -> Select | I35: =AE35 -> Select | J35: =AF35 -> Select | K35: =AG35 -> - | L35: =AH35 -> - | W35: =IF('PR_Programmatic Progress_1B'!A28="","",'PR_Programmatic Progress_1B'!A28) | X35: =IF('PR_Programmatic Progress_1B'!B28="","",'PR_Programmatic Progress_1B'!B28) | Y35: =IF('PR_Programmatic Progress_1B'!C28="","",'PR_Programmatic Progress_1B'!C28) | AD35: =IF('PR_Programmatic Progress_1B'!G28="","",'PR_Programmatic Progress_1B'!G28) -> Select | AE35: =IF('PR_Programmatic Progress_1B'!H28="","",'PR_Programmatic Progress_1B'!H28) -> Select | AF35: =IF('PR_Programmatic Progress_1B'!I28="","",'PR_Programmatic Progress_1B'!I28) -> Select | AG35: =IF('PR_Programmatic Progress_1B'!L28="","",'PR_Programmatic Progress_1B'!L28) -> - | AH35: =IF('PR_Programmatic Progress_1B'!M28="","",'PR_Programmatic Progress_1B'!M28) -> -
A36: =W36 | B36: =X36 | C36: =Y36 | H36: =AD36 -> Select | I36: =AE36 -> Select | J36: =AF36 -> Select | K36: =AG36 -> - | L36: =AH36 -> - | W36: =IF('PR_Programmatic Progress_1B'!A29="","",'PR_Programmatic Progress_1B'!A29) | X36: =IF('PR_Programmatic Progress_1B'!B29="","",'PR_Programmatic Progress_1B'!B29) | Y36: =IF('PR_Programmatic Progress_1B'!C29="","",'PR_Programmatic Progress_1B'!C29) | AD36: =IF('PR_Programmatic Progress_1B'!G29="","",'PR_Programmatic Progress_1B'!G29) -> Select | AE36: =IF('PR_Programmatic Progress_1B'!H29="","",'PR_Programmatic Progress_1B'!H29) -> Select | AF36: =IF('PR_Programmatic Progress_1B'!I29="","",'PR_Programmatic Progress_1B'!I29) -> Select | AG36: =IF('PR_Programmatic Progress_1B'!L29="","",'PR_Programmatic Progress_1B'!L29) -> - | AH36: =IF('PR_Programmatic Progress_1B'!M29="","",'PR_Programmatic Progress_1B'!M29) -> -
A37: =W37 | B37: =X37 | C37: =Y37 | H37: =AD37 -> Select | I37: =AE37 -> Select | J37: =AF37 -> Select | K37: =AG37 -> - | L37: =AH37 -> - | W37: =IF('PR_Programmatic Progress_1B'!A30="","",'PR_Programmatic Progress_1B'!A30) | X37: =IF('PR_Programmatic Progress_1B'!B30="","",'PR_Programmatic Progress_1B'!B30) | Y37: =IF('PR_Programmatic Progress_1B'!C30="","",'PR_Programmatic Progress_1B'!C30) | AD37: =IF('PR_Programmatic Progress_1B'!G30="","",'PR_Programmatic Progress_1B'!G30) -> Select | AE37: =IF('PR_Programmatic Progress_1B'!H30="","",'PR_Programmatic Progress_1B'!H30) -> Select | AF37: =IF('PR_Programmatic Progress_1B'!I30="","",'PR_Programmatic Progress_1B'!I30) -> Select | AG37: =IF('PR_Programmatic Progress_1B'!L30="","",'PR_Programmatic Progress_1B'!L30) -> - | AH37: =IF('PR_Programmatic Progress_1B'!M30="","",'PR_Programmatic Progress_1B'!M30) -> -
A39: C LFA comments on data quality and reporting issues (!) This section should contain any common issues and/or additional information related to data quality and reporting on the programmatic indicators which are not covered in 'LFA analysis on progress to date and any variance between targets and results'
A40: There has been a marked improvement in data quality and reporting in this period compared to the previous periods.

Sheet LFA_Grant Management_2
A1: LFA On-going Progress Review and Disbursement Recommendation
A2: PROGRESS UPDATE PERIOD
A3: Grant number: | C3: =IF('LFA_Programmatic Progress_1A'!C7="","",'LFA_Programmatic Progress_1A'!C7) -> MNR-809-G04-H
A4: Progress Update - Reporting Period: | C4: Cycle: | D4: =IF('LFA_Programmatic Progress_1A'!D12="Select","",'LFA_Programmatic Progress_1A'!D12) -> Quarter | E4: Number: | F4: =IF('LFA_Programmatic Progress_1A'!F12="Select","",'LFA_Programmatic Progress_1A'!F12) -> 7
A5: Progress Update - Period Covered: | C5: Beginning Date: | D5: =IF('LFA_Programmatic Progress_1A'!D13="","",'LFA_Programmatic Progress_1A'!D13) -> 40452 | E5: End Date: | F5: =IF('LFA_Programmatic Progress_1A'!F13="","",'LFA_Programmatic Progress_1A'!F13) -> 40543
A6: Progress Update - Number: | C6: =IF('LFA_Programmatic Progress_1A'!C14="Select","",'LFA_Programmatic Progress_1A'!C14) -> 5
A8: Section 2: Grant Management
A10: A. PR & LFA COMMENTS ON THE FULFILLMENT OF OUTSTANDING CONDITIONS PRECEDENT AND/OR SPECIAL CONDITIONS UNDER THE GRANT AGREEMENT
A11: ! This table should contain a full text of the CP and/or other special conditions due for fulfilment during this period or outstanding from previous periods.
A12: ! Some Special Conditions may apply to more than one period of grant implementation. Their fulfilment during one period does not automatically imply fulfilment in subsequent periods. The LFA should verify that the status of such conditions is reported by the PR during each period concerned.
A13: ! If a Condition Precedent that was previously fulfilled is re-opened due to new circumstances, and the issue addressed by this condition is considered critical, the issue should be disclosed by the LFA in the Section 4 LFA Findings and Recommendations. At the discretion of the Fund Portfolio Manager, the issue may be followed up through the management actions assigned by the Global Fund to the PR.
D14: PR SECTION | E14: LFA SECTION
A15: Conditions Precedent and/or other special conditions | D15: Status | E15: Status | F15: Analysis (this should not be a "Copy and Paste" of the comments provided by the PR)
A16: =IF('PR_Grant Management_2'!A14="","",'PR_Grant Management_2'!A14) -> The first disbursement of Grant funds by the Global Fund to the Principal Recipient is subject to the satisfaction of each of the following conditions: a. the delivery by the Principal Recipient to the Global Fund of a statement confirming the bank account into which the Grant funds will be disbursed as indicated in block 10 of the face sheet of this Agreement; | D16: =IF('PR_Grant Management_2'!F14="","",'PR_Grant Management_2'!F14) -> Met | E16: Met | F16: All positions have been filled and approved by the GF FPM. These are: i. Program Coordinator - Dawda Joof - 15 March 2010 , ii. M&E - Kebba M Sima - December 2009, iii. Procurement Officer - Suleman Kinteh - October 2010, iv. Finance Officer's Coordinator - Allassan K Jitteh - February 2010.
A17: =IF('PR_Grant Management_2'!A15="","",'PR_Grant Management_2'!A15) -> The second disbursement of Grant funds by the Global Fund to the Principal Recipient is subject to the delivery by the Principal Recipient to the Global Fund of evidence, in form and substance satisfactory to the Global Fund, that the Principal Recipient has upgraded its Accounting System as well as its Accounting Manual, particularly cash basis of accounting, to facilitate compliance with Global Fund reporting requirements. | D17: =IF('PR_Grant Management_2'!F15="","",'PR_Grant Management_2'!F15) -> Met | E17: Met | F17: The MESST report was submitted to GF and approved by the FPM on 18th August 2010.
A18: =IF('PR_Grant Management_2'!#REF!="","",'PR_Grant Management_2'!#REF!) -> #REF! | D18: =IF('PR_Grant Management_2'!#REF!="","",'PR_Grant Management_2'!#REF!) -> #REF! | E18: Met | F18: The updated M&E plan was submitted as part of the MESST report which was subsequently approved by the FPM on 18th August 2010.
A19: =IF('PR_Grant Management_2'!#REF!="","",'PR_Grant Management_2'!#REF!) -> #REF! | D19: =IF('PR_Grant Management_2'!#REF!="","",'PR_Grant Management_2'!#REF!) -> #REF! | E19: Unmet - In Progress | F19: The revised budget following the MESST was submitted to the FPM on 12th July 2010. However the revised budget has not been approved by the Global Fund.
A20: =IF('PR_Grant Management_2'!#REF!="","",'PR_Grant Management_2'!#REF!) -> #REF! | D20: =IF('PR_Grant Management_2'!#REF!="","",'PR_Grant Management_2'!#REF!) -> #REF!
A21: =IF('PR_Grant Management_2'!#REF!="","",'PR_Grant Management_2'!#REF!) -> #REF! | D21: =IF('PR_Grant Management_2'!#REF!="","",'PR_Grant Management_2'!#REF!) -> #REF! | E21: Met | F21: We reviewed an email dated 10th November 2009 from the Fund Portfolio Manager indicating the approval of the PSM plan by The Global Fund.
A22: =IF('PR_Grant Management_2'!#REF!="","",'PR_Grant Management_2'!#REF!) -> #REF! | D22: =IF('PR_Grant Management_2'!#REF!="","",'PR_Grant Management_2'!#REF!) -> #REF! | E22: Unmet - In Progress | F22: On January 14th, 2010, an email was sent from the FPM approving the assessment of the SRs and indicating that disbursement could commence. The FPM however noted that a "joint action plan" should be developed to address the weaknesses of the SRs. The plan was to be submitted to GF by the end of January 2010. At the time of the verification, the PR had not developed the "joint action plan". The Principal Recipient has not established a computerized accounting system for Sub-recipients. Two of the Sub-recipients (GFPA and HOC) of AATG have however computerised accounting systems because NAS has provided them, while CRS has its own computerized accounting system.
A23: =IF('PR_Grant Management_2'!#REF!="","",'PR_Grant Management_2'!#REF!) -> #REF! | D23: =IF('PR_Grant Management_2'!#REF!="","",'PR_Grant Management_2'!#REF!) -> #REF! | E23: Unmet - In Progress | F23: During the November 2010 VOI for Q3 , the LFA noted and reported that two out of the three baseline studies had been conducted: 1) Commercial Sex Workers, and 2) Life Skills Based HIV Education in and out of Schools. Hard copies of these studies were shared with LFA and GF. During this VOI (February 2011), the 2010 BSS report was shared with the LFA. The revised data on the number of out-of-school baseline was also shared with LFA during the February 2011 VOI.
A24: =IF('PR_Grant Management_2'!#REF!="","",'PR_Grant Management_2'!#REF!) -> #REF! | D24: =IF('PR_Grant Management_2'!#REF!="","",'PR_Grant Management_2'!#REF!) -> #REF!
A25: =IF('PR_Grant Management_2'!#REF!="","",'PR_Grant Management_2'!#REF!) -> #REF! | D25: =IF('PR_Grant Management_2'!#REF!="","",'PR_Grant Management_2'!#REF!) -> #REF!
A26: =IF('PR_Grant Management_2'!#REF!="","",'PR_Grant Management_2'!#REF!) -> #REF! | D26: =IF('PR_Grant Management_2'!#REF!="","",'PR_Grant Management_2'!#REF!) -> #REF!
A27: =IF('PR_Grant Management_2'!A16="","",'PR_Grant Management_2'!A16)
A28: =IF('PR_Grant Management_2'!#REF!="","",'PR_Grant Management_2'!#REF!) -> #REF! | D28: =IF('PR_Grant Management_2'!#REF!="","",'PR_Grant Management_2'!#REF!) -> #REF!
A29: =IF('PR_Grant Management_2'!#REF!="","",'PR_Grant Management_2'!#REF!) -> #REF! | D29: =IF('PR_Grant Management_2'!#REF!="","",'PR_Grant Management_2'!#REF!) -> #REF!
A30: =IF('PR_Grant Management_2'!#REF!="","",'PR_Grant Management_2'!#REF!) -> #REF! | D30: =IF('PR_Grant Management_2'!#REF!="","",'PR_Grant Management_2'!#REF!) -> #REF!
A32: B. PR & LFA REVIEW OF PROGRESS ON IMPLEMENTATION OF OUTSTANDING MANAGEMENT ACTIONS FROM PREVIOUS DISBURSEMENTS
A34: ! This table should contain all issues raised in the last Management Letter from the Global Fund or outstanding from previous Management Letters, and comment on the progress.
A35: Global Fund Management Actions | D35: LFA Review of PR Progress on Global Fund Management Actions
A36: =IF('PR_Grant Management_2'!A21="","",'PR_Grant Management_2'!A21) -> Reduce Stigma and Discrimination - Meaningful involvement of PLHIVs (Mission meeting in Nov. 2010) | D36: Interaction with PR and NAS showed that a meeting was held and this was supported by the minutes of the meeting with the support groups on 20 July 2010.
A37: =IF('PR_Grant Management_2'!A22="","",'PR_Grant Management_2'!A22) | D37: As noted in the Programmatic Progress_1B, there has been an improvement in the quality of training reports submitted by the PR compared to those we reviewed during the previous VoI.
A38: =IF('PR_Grant Management_2'!A23="","",'PR_Grant Management_2'!A23) | D38: As at the time of the VoI, PR had not undertaken any financial monitoring of the SRs, but they informed us that they will undertake this immediately after the VoI and share the report with us during the next VoI.
A39: =IF('PR_Grant Management_2'!A24="","",'PR_Grant Management_2'!A24) | D39: During the VoI, we visited the SR in question, that is CRS, and interactions with them revealed that there has been a significant improvement in their relationship with the PR.
A40: =IF('PR_Grant Management_2'!A25="","",'PR_Grant Management_2'!A25) | D40: PR shared a joint action plan to address SR weaknesses with us. A review of the document showed that there were follow-up actions which PR and NAS were supposed to have done on 2010. Although some of these have subsequently been done, no update was provided on the current status of the follow-up actions in the document submitted by PR.
A41: =IF('PR_Grant Management_2'!A26="","",'PR_Grant Management_2'!A26) -> 1. The sub-recipients audit plan is still outstanding. It was due by 30 October 2010. | D41: PR shared the reports for the various studies with us during the VoI. The BSS report was, however, a draft one and the PR promised to send the final one at the end of February 2011, but this was not done.
A42: =IF('PR_Grant Management_2'!A27="","",'PR_Grant Management_2'!A27) -> 2. The PR needs to open a separate bank account for this grant and transfer the correct cash balance from the current joint bank account.
A43: =IF('PR_Grant Management_2'!A28="","",'PR_Grant Management_2'!A28) -> 3. Although the PR has upgraded its accounting system to allow generating expenses reports on cash basis, the expenditures in the PU are still presented using the accrual basis of accounting. This prevents the verification of the cash balance, which is being calculated as a balance based on the cumulative expenditures of the program. Cumulative expenditures need to be updated based on actual cash disbursements from the PR grant account.
A44: =IF('PR_Grant Management_2'!A29="","",'PR_Grant Management_2'!A29)
A45: =IF('PR_Grant Management_2'!A30="","",'PR_Grant Management_2'!A30)
A46: =IF('PR_Grant Management_2'!#REF!="","",'PR_Grant Management_2'!#REF!) -> #REF!
A48: =IF('PR_Grant Management_2'!A31="","",'PR_Grant Management_2'!A31)
A49: =IF('PR_Grant Management_2'!A32="","",'PR_Grant Management_2'!A32)
A50: =IF('PR_Grant Management_2'!#REF!="","",'PR_Grant Management_2'!#REF!) -> #REF!
A53: C. PR & LFA COMMENTS ON ANNUAL GRANT REPORTING REQUIREMENTS
A54: This table should contain the due date for the report due for submission. If a report is overdue, indicate the original due date and explain the reason for delay.
C55: PR SECTION | E55: LFA SECTION
A56: Required Documentation | C56: Due date | D56: Status | E56: Due date | F56: Status | J56: Comments
A57: PR Audit Report | C57: =IF('PR_Grant Management_2'!E38="","",'PR_Grant Management_2'!E38) -> 40724 | D57: =IF('PR_Grant Management_2'!F38="","",'PR_Grant Management_2'!F38) -> Preparation on track | E57: 40724 | F57: Preparation on track | J57: The Audit TOR was approved on 10 March 2011.
A58: Enhanced Financial Reporting (EFR) | C58: =IF('PR_Grant Management_2'!E39="","",'PR_Grant Management_2'!E39) -> 40633 | D58: =IF('PR_Grant Management_2'!F39="","",'PR_Grant Management_2'!F39) -> Preparation on track | E58: 40589 | F58: Preparation on track | J58: The EFR was submitted as part of the PUDR and this has been reviewed by the LFA. The LFA reviewed report will be submitted as part of this PUDR report.

Sheet LFA_Total PR Cash Outflow_3A
A1: LFA On-going Progress Review and Disbursement Recommendation
A2: PROGRESS UPDATE PERIOD
A3: Grant number: | C3: =IF('LFA_Programmatic Progress_1A'!C7="","",'LFA_Programmatic Progress_1A'!C7) -> MNR-809-G04-H
A4: Progress Update - Reporting Period: | C4: Cycle: | D4: =IF('LFA_Programmatic Progress_1A'!D12="Select","",'LFA_Programmatic Progress_1A'!D12) -> Quarter | F4: Number: | G4: =IF('LFA_Programmatic Progress_1A'!F12="Select","",'LFA_Programmatic Progress_1A'!F12) -> 7
A5: Progress Update - Period Covered: | C5: Beginning Date: | D5: =IF('LFA_Programmatic Progress_1A'!D13="","",'LFA_Programmatic Progress_1A'!D13) -> 40452 | F5: End Date: | G5: =IF('LFA_Programmatic Progress_1A'!F13="","",'LFA_Programmatic Progress_1A'!F13) -> 40543
A6: Progress Update - Number: | C6: =IF('LFA_Programmatic Progress_1A'!C14="Select","",'LFA_Programmatic Progress_1A'!C14) -> 5
A7: Currency: | C7: =IF('PR_Programmatic Progress_1A'!C10="Select","",'PR_Programmatic Progress_1A'!C10) -> EUR
A9: Section 3A: Total PR Cash Outflow
A10: LFA-VERIFIED TABLES ON TOTAL PR CASH OUTFLOW
A11: ! For RCC grants the cumulative section of the table below should contain cumulative amount from the start of the RCC and not from the start of Phase 1 of the program.
C12: LFA-Verified Budget for Reporting Period | D12: LFA-Verified Actual for Reporting Period | E12: Variance | F12: LFA Analysis of Variance | H12: LFA-Verified Cumulative Budget through period of Progress Update | I12: LFA-Verified Actual through period of Progress Update | J12: Variance | K12: LFA Analysis of Variance | N12: =IF('PR_Programmatic Progress_1A'!P10="Select","Please select currency on Page 'PR_Programmatic Achievement (1)'", "All amounts are in: "&'PR_Programmatic Progress_1A'!P10) -> All amounts are in: | P12: LFA-Verified Budget for Reporting Period | Q12: LFA-Verified Actual for Reporting Period | R12: Variance | S12: LFA Analysis of Variance | U12: LFA-Verified Cumulative Budget through period of Progress Update | V12: LFA-Verified Actual through period of Progress Update | W12: Variance | X12: LFA Analysis of Variance
A13: 1. Total cash outflow vs. budget | C13: =C14+C15 -> 2500000 | D13: =D14+D15 -> 2235000 | E13: =IF(C13="",IF(D13="","",C13-D13),C13-D13) -> 265000 | H13: =H14+H15 -> 5600000 | I13: =I14+I15 -> 4500000 | J13: =IF(H13="",IF(I13="","",H13-I13),H13-I13) -> 1100000 | N13: 1. Total cash outflow vs. budget | P13: =P14+P15 -> 2500000 | Q13: =Q14+Q15 -> 2235000 | R13: =IF(P13="",IF(Q13="","",P13-Q13),P13-Q13) -> 265000 | U13: =U14+U15 -> 5600000 | V13: =V14+V15 -> 4500000 | W13: =IF(U13="",IF(V13="","",U13-V13),U13-V13) -> 1100000
A14: 1a. PR's total expenditures | C14: =P14 -> 1500000 | D14: =Q14 -> 1435000 | E14: =IF(C14="",IF(D14="",0,C14-D14),C14-D14) -> 65000 | F14: The negative variance for the period was mainly due to: - Higher than planned expenditure on health products by Eur 13,069 due to increases in prices at the global level. - Higher than planned costs incurred on OVC educational support of Eur 53,808. The 2010-2011 academic year began in the fourth quarter hence most OVC fees for the 2010-2011 academic year were paid in period 4. There was no budget for this activitiy in period 4. The payments made were mainly drawn on the Eur 10,000 surplus from the budget for period 1 in year 1 and the year 2 period 1 budget of Eur 70,000. - Higher than planned cost incurred on OVC nutritional support by Eur 8,145. This was mainly due to general increases in prices of goods and increase in the number of OVCs supported. The number of OVCs increased from the initial target of 1,700 to 2,000 after the MESST workshop in June 2010. - Some expenditure from the previous quarter was rolled over to the current quarter. The roll over was due to the PR's decision to prioritise and spend on activities in period 3 in line with funds available at the time. These include activities under BCC Mass media and community outreach - Eur 60,279, procurement of bicycles under home based care and support for PLHIV- Eur 13,713, administrative costs, monthly meetings for PL support groups - Eur 25,706. The negative variance was partly offset by unutilised funds/savings from the following budget lines; - Technical assistance from Action Aid International - Eur 4,465 - Life skills training sessions under BCC community outreach - Eur 10,575 - M & E survey on the youth - Eur 6,624 - PR Human resource and general administrative cost - Eur 4,956 - Training on Income generating activities and phsycosocial care and support - Eur 10,148 | H14: =U14 -> 2600000 | I14: =V14 -> 2000000 | J14: =IF(H14="",IF(I14="",0,H14-I14),H14-I14) -> 600000 | K14: The total variance is made up both positive and negative variances. The negative variance was mainly due to over expenditure on - Educational and nutrional support for OVCs of Eur 58,515 - Administration cost for PL support groups of Eur 10,352 and printing of guideline materials under life skills training. - Procurement of HBC kits - Eur 13,482 - Administration cost for PLHIV support groups - 10,318 - Update of CSWs register under BCC community outreach - Eur 14,265 The PR also incurred some expenditure on behalf of the SRs. The positive variance is due mainly to the following outstanding activities in: - BCC mass media and community outreach, STAR sessions and training - Translation of life skills manual for special needs - Eur 14,140 - HIV advocacy sensitization - Eur 12,375 - Policy development on multi indicator survey - Eur 16,369 | N14: 1a. PR's total expenditures | P14: ='PR_Total PR Cash Outflow_3A'!C13 -> 1500000 | Q14: ='PR_Total PR Cash Outflow_3A'!D13 -> 1435000 | R14: =IF(P14="",IF(Q14="",0,P14-Q14),P14-Q14) -> 65000 | U14: ='PR_Total PR Cash Outflow_3A'!H13 -> 2600000 | V14: ='PR_Total PR Cash Outflow_3A'!I13 -> 2000000 | W14: =IF(U14="",IF(V14="",0,U14-V14),U14-V14) -> 600000
A15: 1b. Disbursements to sub-recipients | C15: =P15 -> 1000000 | D15: =Q15 -> 800000 | E15: =IF(C15="",IF(D15="",0,C15-D15),C15-D15) -> 200000 | F15: The positive variance was due to some expenditure originally designated to SRs and support groups but incurred by the PR to accelerate program implementation. | H15: =U15 -> 3000000 | I15: =V15 -> 2500000 | J15: =IF(H15="",IF(I15="",0,H15-I15),H15-I15) -> 500000 | K15: The positive variance is accounted for by procurements made directly by the PR on behalf of the SRs to accelerate program implementation. These include procurement of condoms by VPP, vehicles, office equipment and payment of other administrative costs for support groups orginally designated to CRS. | N15: 1b. Disbursements to sub-recipients | P15: ='PR_Total PR Cash Outflow_3A'!C14 -> 1000000 | Q15: ='PR_Total PR Cash Outflow_3A'!D14 -> 800000 | R15: =IF(P15="",IF(Q15="",0,P15-Q15),P15-Q15) -> 200000 | U15: ='PR_Total PR Cash Outflow_3A'!H14 -> 3000000 | V15: ='PR_Total PR Cash Outflow_3A'!I14 -> 2500000 | W15: =IF(U15="",IF(V15="",0,U15-V15),U15-V15) -> 500000
C17: LFA-Verified Budget for Reporting Period | D17: LFA-Verified Actual for Reporting Period | E17: Variance | F17: LFA Analysis of Variance | H17: LFA-Verified Cumulative Budget through period of Progress Update | I17: LFA-Verified Actual through period of Progress Update | J17: Variance | K17: LFA Analysis of Variance | P17: LFA-Verified Budget for Reporting Period | Q17: LFA-Verified Actual for Reporting Period | R17: Variance | S17: LFA Analysis of Variance | U17: LFA-Verified Cumulative Budget through period of Progress Update | V17: LFA-Verified Actual through period of Progress Update | W17: Variance | X17: LFA Analysis of Variance
A18: 2. Pharmaceuticals & health product expenditures vs. budget | C18: =C19+C20 -> 1300000 | D18: =D19+D20 -> 1350000 | E18: =IF(C18="",IF(D18="","",C18-D18),C18-D18) -> -50000 | H18: =H19+H20 -> 2500000 | I18: =I19+I20 -> 1950000 | J18: =IF(H18="",IF(I18="","",H18-I18),H18-I18) -> 550000 | N18: 2. Pharmaceuticals & health product expenditures vs. budget | P18: =P19+P20 -> 1300000 | Q18: =Q19+Q20 -> 1350000 | R18: =IF(P18="",IF(Q18="","",P18-Q18),P18-Q18) -> -50000 | U18: =U19+U20 -> 2500000 | V18: =V19+V20 -> 1950000 | W18: =IF(U18="",IF(V18="","",U18-V18),U18-V18) -> 550000
A19: 2a. Medicines and pharmaceutical products | C19: =P19 -> 600000 | D19: =Q19 -> 550000 | E19: =IF(C19="",IF(D19="",0,C19-D19),C19-D19) -> 50000 | H19: =U19 -> 1000000 | I19: =V19 -> 850000 | J19: =IF(H19="",IF(I19="",0,H19-I19),H19-I19) -> 150000 | N19: 2a. Medicines and pharmaceutical products | P19: ='PR_Total PR Cash Outflow_3A'!C18 -> 600000 | Q19: ='PR_Total PR Cash Outflow_3A'!D18 -> 550000 | R19: =IF(P19="",IF(Q19="",0,P19-Q19),P19-Q19) -> 50000 | U19: ='PR_Total PR Cash Outflow_3A'!H18 -> 1000000 | V19: ='PR_Total PR Cash Outflow_3A'!I18 -> 850000 | W19: =IF(U19="",IF(V19="",0,U19-V19),U19-V19) -> 150000
A20: 2b. Health products and health equipment | C20: =P20 -> 700000 | D20: =Q20 -> 800000 | E20: =IF(C20="",IF(D20="",0,C20-D20),C20-D20) -> -100000 | F20: The expenditure relates to the procurement of HBC kits which was carried out through the VPP during the period. The budget for procurement was Eur 72,092 and scheduled for period 2. The only products procured then were male and female condoms. The remaining health products were procured in the current period after completing all procurement procedures. | H20: =U20 -> 1500000 | I20: =V20 -> 1100000 | J20: =IF(H20="",IF(I20="",0,H20-I20),H20-I20) -> 400000 | K20: The cumulative expenditure relates to male and female condoms procured in Q2 and other health products (mainly HBC kits) procured in quarter 4. The excess expenditure was due to increases in prices of health products procured mainly in period 4. | N20: 2b. Health products and health equipment | P20: ='PR_Total PR Cash Outflow_3A'!C19 -> 700000 | Q20: ='PR_Total PR Cash Outflow_3A'!D19 -> 800000 | R20: =IF(P20="",IF(Q20="",0,P20-Q20),P20-Q20) -> -100000 | U20: ='PR_Total PR Cash Outflow_3A'!H19 -> 1500000 | V20: ='PR_Total PR Cash Outflow_3A'!I19 -> 1100000 | W20: =IF(U20="",IF(V20="",0,U20-V20),U20-V20) -> 400000
A22: * If LFA-entered data differs from PR's figures, the respective cells will change colour automatically
A24: 3. Indicate any expenditures (incurred or forecasted) that should not be financed by the Global Fund
A25: None

Sheet LFA_EFR Review_3B
A1: LFA review of Enhanced Financial Reporting template
A3: LFA Organization / Responsible office: | D3: =IF('LFA_Programmatic Progress_1A'!C3=0,"",'LFA_Programmatic Progress_1A'!C3) -> PricewaterhouseCoopers (Ghana) Limited
A4: GENERAL GRANT INFORMATION
A5: Country: | D5: =IF('PR_Programmatic Progress_1A'!C5="","",'PR_Programmatic Progress_1A'!C5) -> Monrovia
A6: Disease: | D6: =IF('PR_Programmatic Progress_1A'!C6="","",'PR_Programmatic Progress_1A'!C6) -> HIV/AIDS
A7: Grant Number: | D7: =IF('PR_Programmatic Progress_1A'!C7="","",'PR_Programmatic Progress_1A'!C7) -> MNR-809-G04-H
A8: Principal Recipient: | D8: =IF('PR_Programmatic Progress_1A'!C8="","",'PR_Programmatic Progress_1A'!C8) -> Ministry of Health
A9: Program Start Date: | D9: =IF('PR_Programmatic Progress_1A'!C9="","",'PR_Programmatic Progress_1A'!C9) -> 40087
A10: Currency: | D10: =IF('PR_Programmatic Progress_1A'!C10="","",'PR_Programmatic Progress_1A'!C10) -> EUR
A12: Section 3B: ENHANCED FINANCIAL REPORTING PERIOD
A13: Current Period | D13: Beginning Date: | E13: 40148 | F13: End Date: | G13: 40543
A14: Cumulative Period | D14: Beginning Date: | E14: 40148 | F14: End Date: | G14: 40543
A16: 1. CHECKLIST
A17: The following information provided by the Principal Recipient in its EFR has been checked. | J17: Comments if any:
B19: Yes | C19: The template has been fully completed. | J19: None
A20: 1
B21: Yes | C21: The total figures in Tables A, B and C are equal. | J21: None
A22: 2
B23: Yes | C23: The reporting dates are correct for both current period and cumulative period. | J23: None
A24: 3
B25: No | C25: The total budget figure is accurate based on existing approved budgets. | J25: The cumulative budget in the grant agreement for the period under review is Eur 1,838,031. The PR has however used Eur 1,902,135 which is based on a revised budget that has not been approved by the GF yet.
A26: 4
B27: No | C27: The PR expenditure in Table C is consistent with PR expenditure for the same period as provided in the Progress Updates/Disbursements Request (PU/DR). | J27: There is a variance of Eur 157,976 between the cumulative expenditure reported in the PUDR of Eur 1,526,224 and the cumulative expenditure reported in the EFR of Eur 1,368,698
A28: 5
B29: Yes | C29: The total expenditure is supported by appropriate documentation ( PR expenditure reports, bank reconciliations, SR expenditure reports to PR etc.) or reasonable assumptions. | J29: None
A30: 6
A33: 2. COMPLETION OF THE TEMPLATE
A35: Comments on the process, assumptions and supporting documentation used by the PR to complete the template. (If space is insufficient, please provide comments in an addendum)
A37: Process of capturing expenditure in the EFR The PR uses the Sun system to process financial transactions. It then extracts financial information into Microsoft (MS) excel which is used to prepare financial reports in the form requested by The Global Fund. To ensure that the financial information is complete and accurate, reconciliation is performed between Sun and MS excel. The reporting currency in the PR's accounting system is Gambia Dalasi (GMD).
A42: 3. VARIANCE ANALYSIS
A44: Comments on the explanations for variances provided by the PR (LFA can also provide comment directly on the EFR template completed by the PR)
A45: We reviewed the expenditure reported in the EFR and compared it to the cumulative expenditure in the PUDR. We noted a variance of Eur 157,976. We further traced the budget amounts reported in the EFR to the approved budget and noted a variance of Eur 64,104 (PR budget Eur 1,902,135 less approved budget of Eur 1,838,031). The PR's budget is based on the revised budget which has not been approved by the GF. We recommend that the PR review the EFR and resolve these variances for our final review.
A46: Signed on behalf of the LFA:
A47: Name: | D47: Mark Appleby
A48: Title: | D48: Director
A49: Date and Place: | D49: 21st March 2011/Accra

Sheet LFA_Procurement Info_4
A1: LFA On-going Progress Review and Disbursement Recommendation
A2: PROGRESS UPDATE PERIOD
A3: Grant number: | C3: =IF('LFA_Programmatic Progress_1A'!C7="","",'LFA_Programmatic Progress_1A'!C7) -> MNR-809-G04-H
A4: Progress Update - Reporting Period: | C4: Cycle: | D4: =IF('LFA_Programmatic Progress_1A'!D12="Select","",'LFA_Programmatic Progress_1A'!D12) -> Quarter | F4: Number: | I4: =IF('LFA_Programmatic Progress_1A'!F12="Select","",'LFA_Programmatic Progress_1A'!F12) -> 7
A5: Progress Update - Period Covered: | C5: Beginning Date: | D5: =IF('LFA_Programmatic Progress_1A'!D13="","",'LFA_Programmatic Progress_1A'!D13) -> 40452 | F5: End Date: | I5: =IF('LFA_Programmatic Progress_1A'!F13="","",'LFA_Programmatic Progress_1A'!F13) -> 40543
A6: Progress Update - Number: | C6: =IF('LFA_Programmatic Progress_1A'!C14="Select","",'LFA_Programmatic Progress_1A'!C14) -> 5
A8: Section 4: LFA-verified Procurement and Supply Management Information
C11: PR's response | D11: LFA's response | E11: LFA Comments/Analysis
A12: 1a. Has the PR updated the Price Quality Reporting (PQR) with the required information on the pharmaceuticals and health products received during the period covered by this PU/DR’ (if applicable)? (If health products procurement information has not been entered into the PQR, please explain why in comments box) | C12: ='PR_Procurement Info_4'!F10 -> Yes | D12: N/A | E12: Health products totaling Eur 64,081 were procured through VPP during the period. The health products procured were mainly HBC kits and do not relate to the 6 PQR categories in the table below.
A14: 1b. Value of Pharmaceuticals and Health Products in the PQR (6 categories only)
A15: (!) This table is included in the PU/DR form with the aim to improve completeness of information in the PQR system and not for comparing PQR amounts vis-à-vis expenditure per se. NB: PQR and expenditure amounts on health products may not be equal due to a timelag between payments and delivery of pharmaceuticals/health products. (!) For further guidance on PQR data entry, please refer to the guidelines.
A16: Reporting Currency
A17: PQR Product Categories | C17: Value of products received during reporting period | D17: Value of products entered by the PR and verified as correct by the LFA in the PQR during reporting period | E17: Variance | F17: Reason for Variance | H17: Cumulative value of products received since Jan 2011 | I17: Cumulative value of products verified as correct by the LFA in the PQR since Jan 2011 | J17: Variance | K17: Reason for Variance
A18: 1. Anti-malaria medicines | E18: =IF(C18="",IF(D18="","",C18-D18),C18-D18) | J18: =IF(H18="",IF(I18="","",H18-I18),H18-I18)
A19: 2. Bed nets | E19: =IF(C19="",IF(D19="","",C19-D19),C19-D19) | J19: =IF(H19="",IF(I19="","",H19-I19),H19-I19)
A20: 3. Rapid Diagnostic Tests | E20: =IF(C20="",IF(D20="","",C20-D20),C20-D20) | J20: =IF(H20="",IF(I20="","",H20-I20),H20-I20)
A21: 4. Condoms | E21: =IF(C21="",IF(D21="","",C21-D21),C21-D21) | J21: =IF(H21="",IF(I21="","",H21-I21),H21-I21)
A22: 5. Anti-retrovirals | E22: =IF(C22="",IF(D22="","",C22-D22),C22-D22) | J22: =IF(H22="",IF(I22="","",H22-I22),H22-I22)
A23: 6. Anti-TB Medicines | E23: =IF(C23="",IF(D23="","",C23-D23),C23-D23) | J23: =IF(H23="",IF(I23="","",H23-I23),H23-I23)
A24: Total | C24: =SUM(C18:C23) -> 0 | D24: =SUM(D18:D23) -> 0 | E24: =SUM(E18:E23) -> 0 | H24: =SUM(H18:H23) -> 0 | I24: =SUM(I18:I23) -> 0 | J24: =SUM(J18:J23) -> 0
A27: 2. Based on best information available to the LFA, are there any risks of drug stockout at the central level in the next period of implementation? (If yes, please explain in comments box) ! This section should be completed by the LFA based on best information on stock levels at the central level available to the LFA and should not require dedicated visits for on-site checks of stocks. | C27: ='PR_Procurement Info_4'!F11 -> No | D27: Yes | E27: • The stock of male condoms as at 28 February 2011 were 488,160 pieces. • Monthly consumption in 2010 was approximately 70,898 pieces. • Taking the monthly consumption rate into consideration, there is a risk of stock out as the quantities on hand will only be adequate to cater for the next 6-7 months in 2011. The additional requirement for the remaining months in 2011 is approximately 212,694 pieces. However there is no budget in year for the procurement of condoms. In view of this, PR in collaboration with NAS should ensure that they explore other avenues to raise funds for the procurement of the additional condom requirements for Year 2 of program implementation.
A29: 3. PR comments on issues related to the procurement and supply management of pharmaceuticals and health products | F29: LFA analysis on issues related to the procurement and supply management of pharmaceuticals and health products
A30: =IF('PR_Procurement Info_4'!A14:J14="","",'PR_Procurement Info_4'!A14:J14) | F30: The stock of male condoms as at 28 February 2011 is not considered adequate to cater for the whole of 2011. Delays in the delivery of HBC kits affects program implementation. Religious and cultural opposition to the use of condoms in some sects of the community poses challenges to the distribution and use of condoms in these communities.

Sheet LFA_Findings&Recommendations
A1: LFA On-going Progress Review and Disbursement Recommendation
A2: DISBURSEMENT REQUEST PERIOD
A3: Grant number: | C3: =IF('LFA_Programmatic Progress_1A'!C7="","",'LFA_Programmatic Progress_1A'!C7) -> MNR-809-G04-H
A4: Progress Update - Reporting Period: | C4: Cycle: | D4: =IF('LFA_Programmatic Progress_1A'!D12="Select","",'LFA_Programmatic Progress_1A'!D12) -> Quarter | E4: Number: | F4: =IF('LFA_Programmatic Progress_1A'!F12="Select","",'LFA_Programmatic Progress_1A'!F12) -> 7
A5: Progress Update - Period Covered: | C5: Beginning Date: | D5: =IF('LFA_Programmatic Progress_1A'!D13="","",'LFA_Programmatic Progress_1A'!D13) -> 40452 | E5: End Date: | F5: =IF('LFA_Programmatic Progress_1A'!F13="","",'LFA_Programmatic Progress_1A'!F13) -> 40543
A6: Progress Update - Number: | C6: =IF('LFA_Programmatic Progress_1A'!C14="Select","",'LFA_Programmatic Progress_1A'!C14) -> 5
A9: LFA-specific section: LFA Findings & Recommendations
A11: ! Based on the information provided in the previous sections and your understanding of the grant, please summarise any important management issues, proposing a recommendation for each. NB: an issue is considered as 'important' if it impacts or is likely to impact program implementation and results. ! Instead of repeating detailed descriptions of issues covered in other sections, it is acceptable to state the issue and reference the section containing the details.
A13: Functional Areas | C13: Description of Identified Issues (in order of importance) | F13: LFA Recommendations (in order of importance) | J13: FPM Comments (to be completed upon receipt of the LFA-verified form)
A14: Financial management and systems | C14: Budgeted exchange rate used to translate cumulative expenditure According to International Accounting Standards (IAS 21), an exchange rate that approximates the actual rate at the date of the transaction is often used for translation of transactions. An average rate for a week or a month might also be used for all transactions in each foreign currency occurring during that period. For the current quarter, transactions were appropriately translated at average rates on a monthly basis. The cumulative expenditure for the year, on the other hand, was translated at the budget rate of D38.25 - € 1. | F14: Recommendation The PR should ensure that transactions are translated to the reporting/presentation currency using the rate that approximates the actual rate at the date of the transaction, and cash balances at the end of the period should be translated using the closing rate at the date of the end of the reporting period.
A15: Financial management and systems | C15: Long outstanding reconciling items noted in bank reconciliation statements We identified long outstanding reconciling items amounting to €251 from review of the bank reconciliation statement for Round 8 Dalasi account as at 31 December 2010. Reconciling items are usually considered long outstanding and stale after a 6 month period. The items identified were mainly unpresented cheques which had been outstanding since March 2010. | F15: Recommendation We recommend that these unpresented cheques are reversed in the cash book as they may be stale and not accepted by the bank if presented.
A16: Financial management and systems | C16: Variances noted in budget and actual expenditure reported in EFR We noted a variance of Eur 157,976 between the expenditure reported in the EFR of Eur 1,368,698 and the cumulative expenditure reported in the PUDR of Eur 1,526,224 for the period from 1 December 2009 to 31 December 2010. We also noted a variance of Eur 64,104 between the budget amounts reported in the EFR of Eur 1,902,135 and approved budget in the grant agreement of Eur 1,838,031. Subsequent enquiry revealed that the budget that the PR used was based on a revised budget which has not been approved by the GF. | F16: Recommendation We recommend that the PR review the EFR and resolve these variances for our final review.
A17: Pharmaceutical & health product management | C17: Potential shortage of during last quarter of Year 2 We noted during the assessment of the stock levels of condoms that the available stock as at 28 February 2011 will not be adequate to cater for the expected consumption for the whole of year. This is based on the analysis below: The stock of male condoms as at February 2011 was 488,160 and the monthly consumption in 2010 was 70,898. On the assumption that the 2010 monthly consumption pattern will continue in 2011, the existing stock of male condoms will only last for a maximum of 7 months, implying that by the end of September, the stock would have been exhausted. A review of the PR's Year 2 budget shows that there is no budget for the procurement of condoms in Year 2. | F17: We recommend that PR in collaboration with the National AIDS Secretariat should explore other avenues for funding to procure the additional condom requirements for the year.
A18: Select
A19: Select
A20: Select
A21: Select
A22: Select
A23: Select
A24: Select
A25: Select
A26: Select
A27: Select
E29: LFA_Findings & Recommendations
A30: Select
A31: Yes
A32: No
A34: Select
A35: Program management (including SR management)
A36: Financial management and systems
A37: Monitoring and evaluation
A38: Pharmaceutical & health product management
A39: Other management issues, including: PR capacity to develop quality programmatic and financial reports

Sheet LFA_Cash Reconciliation_5A
A1: LFA On-going Progress Review and Disbursement Recommendation
A2: DISBURSEMENT REQUEST PERIOD
A3: Grant number: | D3: =IF('LFA_Programmatic Progress_1A'!C7="","",'LFA_Programmatic Progress_1A'!C7) -> MNR-809-G04-H
A4: Disbursement Request - Disbursement Period: | D4: Cycle: | E4: =IF('LFA_Programmatic Progress_1A'!D16="Select","",'LFA_Programmatic Progress_1A'!D16) -> Quarter | F4: Number: | G4: =IF('LFA_Programmatic Progress_1A'!F16="Select","",'LFA_Programmatic Progress_1A'!F16) -> 8
A5: Disbursement Request - Period Covered: | D5: Beginning Date: | E5: =IF('LFA_Programmatic Progress_1A'!D17="Select","",'LFA_Programmatic Progress_1A'!D17) -> 40544 | F5: End Date: | G5: =IF('LFA_Programmatic Progress_1A'!F17="Select","",'LFA_Programmatic Progress_1A'!F17) -> 40633
A6: Disbursement Request - Number: | D6: =IF('LFA_Programmatic Progress_1A'!C18="Select","",'LFA_Programmatic Progress_1A'!C18) -> 6
A8: Section 5: LFA-verified Cash Reconciliation & Disbursement Recommendation
A11: A. LFA-VERIFIED CASH RECONCILIATION FOR PERIOD COVERED BY PROGRESS UPDATE
F13: PR-reported amounts | G13: LFA-verified amounts | H13: LFA Comments on verified amounts (if they are different from those reported by the PR) and PR's explanation of reconciliation adjustments (line 9)
A14: 1. Cash Balance: Beginning of period covered by Progress Update (line 10 from Cash Reconciliation section of the period covered by the previous Progress Update): | F14: =+'PR_Cash Reconciliation_5A'!M13 -> 1700000 | G14: 7588
A15: Add: | F15: =+'PR_Cash Reconciliation_5A'!K15 -> 1000000 | G15: 984665
B16: 2. Cash received by the PR from the Global Fund during the period covered by this progress update: (1)
B17: 3. Cash disbursed to third parties by the Global Fund on behalf of the PR during the period covered by this progress update: (1) | F17: =+'PR_Cash Reconciliation_5A'!K16 -> 250000 | G17: 64081
B18: 4. Interest received on bank account | F18: =+'PR_Cash Reconciliation_5A'!K17 -> 20000 | G18: 0
B19: 5. Revenue from income-generating activities (if applicable) | F19: =+'PR_Cash Reconciliation_5A'!K18 -> 0 | G19: 0
B20: 6. Other income, if applicable (e.g. income from disposal of fixed assets, tax refunds) | F20: =+'PR_Cash Reconciliation_5A'!K19 -> 0 | G20: 0
A21: Less: | B21: 7. Total PR cash outflow during period covered by Progress Update (value entered in Section 3A "Total cash outflow"): | F21: =+'PR_Cash Reconciliation_5A'!K22 -> 2235000 | G21: 535804 | H21: Our initial review of the PUDR resulted in a net adjustment of Eur64,235 which has been taken up by the PR and adjusted in the current PUDR: The total reconciliation is made up of: The total expenditure reported by the PR in the initial PUDR - Eur 471,569 Add : Exchange losses computed by LFA using Central Bank of Gambia average monthly rates to translate total Q4 expenditure in Gambian Dalasi - Eur 280 Add : Direct payments by the GF to VPP, but not included in PUDR expenditure - Eur 64,081 Add: Bank charges not included in PUDR expenditure - Eur 125 Less : Long outstanding reconciling items in Dalasi account bank reconciliation - Eur 251
B22: 8. Net exchange rate gains/losses (gains should be shown with a minus sign; losses should be shown with a plus sign) | F22: =+'PR_Cash Reconciliation_5A'!K23 -> -100000 | G22: 217 | H22: This represents exchange loss on translation of cash balance denominated in the Gambian Dalasi as at 31 December 2010. Cash balances Euro account - Eur 493,628 Dalasi account - Eur 39, 194
B23: 9. Reconciliation adjustments (gains should be shown with a minus sign; losses should be shown with a plus sign) | F23: =+'PR_Cash Reconciliation_5A'!K24 -> 0 | G23: -12509 | H23: The cash balance was Eur 7,588.11 as at the end of September 2010. This should have been adjusted by Eur 12,509 to arrive at Eur 20,097.08. The adjustment was due to an exchange gain of Eur 5,196, which the PR omitted and an amount of Eur 7,313 which was an error in the expenditure for period 2.
A24: 10. Cash Balance: End of period covered by Progress Update: | F24: =+F14+F15+F17+F18+F19+F20-F21-F22-F23 -> 835000 | G24: =+G14+G15+G17+G18+G19+G20-G21-G22-G23 -> 532822 | H24: The balance per the LFA represents the cash balance as at 31 December 2010 as follows; Cash balance on Euro account - 493,628 Cash balance on Dalasi account - 39,194 (Dalasi 1,468,200 translated at D 37.46 : Eur 1)

Sheet LFA_Disbursement Recommend_5B
A1: LFA On-going Progress Review and Disbursement Recommendation
A2: DISBURSEMENT REQUEST PERIOD
A3: Grant number: | F3: ='LFA_Programmatic Progress_1A'!C7 -> MNR-809-G04-H
A4: Disbursement Request - Disbursement Period: | F4: Cycle: | H4: =IF('LFA_Programmatic Progress_1A'!D16="Select","",'LFA_Programmatic Progress_1A'!D16) -> Quarter | I4: Number: | J4: =IF('LFA_Programmatic Progress_1A'!F16="Select","",'LFA_Programmatic Progress_1A'!F16) -> 8
A5: Disbursement Request - Period Covered: | F5: Beginning Date: | H5: =IF('LFA_Programmatic Progress_1A'!D17="Select","",'LFA_Programmatic Progress_1A'!D17) -> 40544 | I5: End Date: | J5: =IF('LFA_Programmatic Progress_1A'!F17="Select","",'LFA_Programmatic Progress_1A'!F17) -> 40633
A6: Disbursement Request - Number: | F6: =IF('LFA_Programmatic Progress_1A'!C18="Select","",'LFA_Programmatic Progress_1A'!C18) -> 6
A7: Currency: | F7: =IF('PR_Programmatic Progress_1A'!C10="","",'PR_Programmatic Progress_1A'!C10) -> EUR
A9: Section 5: LFA-verified Cash Reconciliation & Disbursement Recommendation
A12: B. LFA-RECOMMENDED DISBURSEMENT AMOUNT AND EXPLANATIONS
A14: Total forecasted net cash expenditures by the Principal Recipient for the period immediately following the period covered
A15: by the Progress Update:
A16: 1. Period beginning date: | F16: =IF('PR_Programmatic Progress_1A'!D17="","",'PR_Programmatic Progress_1A'!D17) -> 40544 | H16: end date: | I16: =IF('PR_Programmatic Progress_1A'!F17="","",'PR_Programmatic Progress_1A'!F17) -> 40633 | K16: Approved budget amount (reported by PR): | M16: =+'PR_Disbursement Request_5B'!K16 -> 500000 | O16: Forecasted amount (reported by PR): | P16: =+'PR_Disbursement Request_5B'!N16 -> 1370000
K18: LFA-verified approved budget amount: | M18: 499774 | O18: LFA-adjusted forecasted amount: | P18: 856891.72
A19: 2a. Cash buffer period (by default)
A20: (cash "buffer") beginning date: | F20: =IF(I16="","",I16+1) -> 40634 | H20: end date: | I20: =IF(F20="","",DATE(YEAR(F20),MONTH(F20)+3,DAY(F20)-1)) -> 40724 | K20: Approved budget amount (reported by PR): | M20: =+'PR_Disbursement Request_5B'!K18 -> 600000 | O20: Forecasted amount (reported by PR): | P20: =+'PR_Disbursement Request_5B'!N18 -> 500000
R21: PR Total Forecast
K22: LFA-verified approved budget amount: | M22: 578147 | O22: LFA-adjusted forecasted amount: | P22: 542393.68 | R22: =P16+P20+P26 -> 1870000
A23: 2b. Additional "buffer" (discretionary, select only if there is a prior agreement with the FPM) (1) | R23: LFA Total Forecast
R24: =P18+P22+P28 -> 1399285.4
A26: (cash "buffer") beginning date | F26: =IF(I20="","",I20+1) -> 40725 | H26: end date: | I26: ='PR_Disbursement Request_5B'!H22 | K26: approved budget amount: | M26: ='PR_Disbursement Request_5B'!K22 -> 0 | O26: forecasted amount: | P26: ='PR_Disbursement Request_5B'!N22 -> 0
K28: LFA-verified approved budget amount: | O28: LFA-adjusted forecasted amount:
A30: (1) Upon agreement with the FPM, additional Cash buffer can be requested if the PU/DR report contains a completed EFR report or a completed Annex on SR financials, requested by the Secretariat, or if there are any additional GF-specific requirements that cannot be delivered within 45 days. However such requests may or may not be satisfied based on the review of the current PUDR
A31: (2) When the additional (cash "buffer" ) period is 1 or 2months, the approved budget and forecasted amounts should be calculated as prorated values for the period following the regular buffer period.
A33: PR's explanation of any significant variance between forecasted amounts and amounts as originally budgeted. | H33: =IF('PR_Disbursement Request_5B'!I27="","",'PR_Disbursement Request_5B'!I27) -> Please see the attached spreadsheet named "Cash Forecast Detail Top Down" . The forecast for the next reporting period is based on the Q6 budget adjusted down for the following: Less $100,000 for savings from late staff recruitment (see Section 3A) Less $50,000 – TA for labs to be funded by another donor (see Section 3A) Less $80,000 – Unused SR cash balance not offset by commitments The budget for the buffer quarter is adjusted down for the following: Less $100,00 – advance payment for test systems
A35: LFA's explanation of any significant variance between forecasted amounts and amounts as originally budgeted. Please explain any significant variance (based on your judgment) between the forecasted amounts and the amounts as per approved budgets. Please specify the main factors and related amounts that are the major drivers of the variance. NB. Consider the following items when providing the analysis. - Expected timing of payments for any significant budgetary items, - Impact of existing cash balance at SR levels - Current confirmed commitments to be paid during disbursement request period - Current/expected unit prices compared to those in the budget - Change in quantities compared to budget - Exchange rates and inflation - Linkage between budget absorption and programmatic performance to-date. ! The forecast should include any existing commitments (eligible under this grant) as of the end of the reporting period and which are likely to be paid during the disbursement period | H35: We noted that the PR used a revised year 2 budget which has not been approved by the GF. This accounts for the difference between the budget reported by the PR and LFA. The variance between the forecasted amount and the original budgeted amount is due to the inclusion of outstanding activities from the previous period into the forecast. The outstanding activities mainly relate to the following: BCC community outreach and schools - Eur 43,949 , Policy development on HIV advocacy - Eur 6,825, Educational and nutritional support for OVCs - Eur 43,772, and PR and SR administrative costs - Eur 40,099. Savings of Eur 169,304 were identified during the review of the forecast. The PR did not provide a plan for utilisation of the savings. These savings have therefore been excluded from the total forecast amount by the LFA.
A39: Less: | B39: 3. Cash Balance: End of period covered by Progress Update (number 10 from LFA or PR Cash Reconciliation sheet): | J39: PR-reported amounts | K39: LFA-verified amounts | L39: LFA Comments
J40: =+'LFA_Cash Reconciliation_5A'!F24 -> 835000 | K40: =+'LFA_Cash Reconciliation_5A'!G24 -> 532822 | L40: The cash balance in the LFA section represents adjusted cash balance as at 31 December 2010. See details of adjustments in LFA cash reconciliaiton 5A.
B41: 4. Cash "in transit" disbursed to the PR: | J41: =+'PR_Disbursement Request_5B'!N33 -> 0
B42: 5. Cash "in transit" disbursed to third parties by the Global Fund on behalf of the PR : | J42: =+'PR_Disbursement Request_5B'!N34 -> 0
J43: PR-requested amount | K43: LFA-recommended amount
A44: 6. Disbursement Request to the Global Fund for the period immediately following the period covered by the Progress Update, plus additional period (cash buffer): | J44: =IF(R22=0,0,IF(R22-J40-J41-J42<0,0,R22-J40-J41-J42)) -> 1035000 | K44: =IF(R24=0,0,IF(R24-K40-K41-K42<0,0,R24-K40-K41-K42)) -> 866463.4
A46: 7. Does the PR's Disbursement Request include funds for health product procurement? | J46: Yes
A47: 8. Exchange Rate (used to translate local currency into grant currency)
F48: Rates used by the PR | H48: LFA-verified rates | J48: Name of local currency and LFA comments on the exchange rates used by the PR
B50: - used to convert Opening Cash Balance | F50: =+'PR_Disbursement Request_5B'!G41 -> 46 | H50: 37 | J50: The PR used Euro 1:37 Dalasi to translate bank and cash balances at the beginning of the period (quarter 4) and a monthly rate generated from the accounting system in translating expenditure incurred in the local currency. At the end of the period, Euro 1:37 Dalasi was used in translating the closing cash and bank balances. The rates used compare to the Central Bank of The Gambia indicative exchange rate which was Eur 1 : 37.46 Dalasi at the end of the period. The outflow for the period were translated at average rates on a monthly basis. October - Eur 1 : 39.41 Dalasi, November Eur 1 : 37.84 Dalasi and December Eur 1 : 37.58 Dalasi
B52: - used to convert Closing Cash Balance | F52: =+'PR_Disbursement Request_5B'!G43 -> 46 | H52: 37.46
B54: - used to convert Total PR Cash Outflow for the Progress Update Period | F54: =+'PR_Disbursement Request_5B'!G45 -> 0 | H54: Average monthly rate

Sheet Sheet1

Sheet LFA_Overall Performance_6
A1: LFA On-going Progress Review and Disbursement Recommendation
A2: PROGRESS UPDATE PERIOD
A3: Grant number: | C3: =IF('LFA_Programmatic Progress_1A'!C7="","",'LFA_Programmatic Progress_1A'!C7) -> MNR-809-G04-H
A4: Progress Update - Reporting Period: | C4: Cycle: | D4: =IF('LFA_Programmatic Progress_1A'!D12="Select","",'LFA_Programmatic Progress_1A'!D12) -> Quarter | E4: Number: | F4: =IF('LFA_Programmatic Progress_1A'!F12="Select","",'LFA_Programmatic Progress_1A'!F12) -> 7
A5: Progress Update - Period Covered: | C5: Beginning Date: | D5: =IF('LFA_Programmatic Progress_1A'!D13="","",'LFA_Programmatic Progress_1A'!D13) -> 40452 | E5: End Date: | F5: =IF('LFA_Programmatic Progress_1A'!F13="","",'LFA_Programmatic Progress_1A'!F13) -> 40543
A6: Progress Update - Number: | C6: =IF('LFA_Programmatic Progress_1A'!C14="Select","",'LFA_Programmatic Progress_1A'!C14) -> 5
A8: Section 6: LFA EVALUATION AND COMMENTS ON OVERALL PERFORMANCE
A10: A. Overall Evaluation and Rating of Grant Performance (including a summary of how financial performance is linked to programmatic achievements)
A11: ! The evaluation should be undertaken by taking into account programmatic achievements, financial performance and program issues in various functional areas (M&E, Finance, Procurement, and Program Management, including management of sub-recipients). See Guidelines for more detailed guidance on the completion of this section. ! For RCC grants, this section should cover the period from the RCC start date through the end date of the current Progress Update period. ! For guidance on the methodology for rating overall performance, refer to Annex 2 of Guidelines.
A13: Indicator rating | B13: B1 | D13: Any major management issues resulting in downgrade? | E13: No | G13: Overall Grant Rating | H13: B1
A15: Overall, the PR has demonstrated improved performance (4 out of 7 indicators achieved >100% to maximum limit of 120% and 2 out 7 indicators achieved >80% with the remaining indicator achieving 18% in the implementation of the grant during the period of review. A quantitative average for all the 7 indicators resulted in an average of 71.51%, which falls under the "B1" rating. In terms of financial absorption, PR had absorbed 83% of the budgeted funds as at the end of December 2010. The high rate of financial absorption as compared to the programmatic rate was mainly due to: - Payments during the period for HBC kits which were not received from the VPP for distribution.This had a negative impact on program implementation and the related performance indicator. - Secondly, the PR achieved 18% under number of PLHIV provided with HBC and psychosocial support during the period. The under achievement was due to the fact that the setting of the target was based on a higher baseline as a result of wrong definition of the indicator at the time of the proposal development. In spite of the good performance, going forward, the PR must intensify efforts to: Improve the quality of services, training/sensitization programmes being provided Continously Improve the content and quality of training and sensitization reports Improve M&E training to facilitate standardization of data collection and reporting tools Continue to strengthen partnerships with SRs/SGs (feedback has been positive during this period of review)
A18: B. LFA comments on PR planned changes in the program, if any
A19: Not applicable. No planned changes in the program
A22: C. LFA Comments on External Factors Beyond Control of the Principal Recipients that have impacted or may impact program
A23: Delays in procurement of HBC kits had an impact on program implementation, but this was beyond the control of the PR, as the procurement was done through VPP.

Sheet LFA_DisbursementRecommendation7
A1: LFA On-going Progress Review and Disbursement Recommendation
A3: LFA Organization / Responsible office: | D3: =IF('LFA_Programmatic Progress_1A'!C3="","",'LFA_Programmatic Progress_1A'!C3) -> PricewaterhouseCoopers (Ghana) Limited
A4: GENERAL GRANT INFORMATION
A5: Country: | D5: =IF('LFA_Programmatic Progress_1A'!C5="","",'LFA_Programmatic Progress_1A'!C5) -> Monrovia
A6: Disease: | D6: =IF('LFA_Programmatic Progress_1A'!C6="","",'LFA_Programmatic Progress_1A'!C6) -> HIV/AIDS
A7: Grant Number: | D7: =IF('LFA_Programmatic Progress_1A'!C7="","",'LFA_Programmatic Progress_1A'!C7) -> MNR-809-G04-H
A8: Principal Recipient: | D8: =IF('LFA_Programmatic Progress_1A'!C8="","",'LFA_Programmatic Progress_1A'!C8) -> Ministry of Health
A9: Program Start Date: | D9: =IF('LFA_Programmatic Progress_1A'!C9="","",'LFA_Programmatic Progress_1A'!C9) -> 40087
A10: Currency: | D10: =IF('LFA_Programmatic Progress_1A'!C10="","",'LFA_Programmatic Progress_1A'!C10) -> EUR
A11: PROGRESS UPDATE PERIOD | I11: DISBURSEMENT REQUEST PERIOD
A12: Progress Update - Reporting Period: | D12: Cycle: | E12: =IF('LFA_Programmatic Progress_1A'!D12="Select","",'LFA_Programmatic Progress_1A'!D12) -> Quarter | F12: Number: | G12: =IF('LFA_Programmatic Progress_1A'!F12="Select","",'LFA_Programmatic Progress_1A'!F12) -> 7 | I12: Disbursement Request - Disbursement Period: | L12: Cycle: | M12: =IF('LFA_Programmatic Progress_1A'!D16="Select","",'LFA_Programmatic Progress_1A'!D16) -> Quarter | N12: Number: | O12: =IF('LFA_Programmatic Progress_1A'!F16="Select","",'LFA_Programmatic Progress_1A'!F16) -> 8
A13: Progress Update - Period Covered: | D13: Beginning Date: | E13: =IF('LFA_Programmatic Progress_1A'!D13="Select","",'LFA_Programmatic Progress_1A'!D13) -> 40452 | F13: End Date: | G13: =IF('LFA_Programmatic Progress_1A'!F13="Select","",'LFA_Programmatic Progress_1A'!F13) -> 40543 | I13: Disbursement Request - Period Covered: | L13: Beginning Date: | M13: =IF('LFA_Programmatic Progress_1A'!D17="Select","",'LFA_Programmatic Progress_1A'!D17) -> 40544 | N13: End Date: | O13: =IF('LFA_Programmatic Progress_1A'!F17="Select","",'LFA_Programmatic Progress_1A'!F17) -> 40633
A14: Progress Update - Number: | D14: =IF('LFA_Programmatic Progress_1A'!C14="Select","",'LFA_Programmatic Progress_1A'!C14) -> 5 | I14: Disbursement Request - Number: | L14: =IF('LFA_Programmatic Progress_1A'!C18="Select","",'LFA_Programmatic Progress_1A'!C18) -> 6
A16: Section 7: Disbursement Recommendation
A17: A. DISBURSEMENT RECOMMENDATION
B19: Overall Rating | C19: ='LFA_Overall Performance_6'!H13 -> B1
A21: Indicative disbursement ranges by performance rating (included as a reference)
A22: Performance rating | D22: Range for cumulative disbursement amount (after the currently recommended disbursement)
A23: A1 | B23: Exceeding expectations | D23: Above 95% of cumulative budget through the next reporting period
A24: A2 | B24: Meeting expectations | D24: Between 85-105% of cumulative budget through the next reporting period
A25: B1 | B25: Adequate | D25: Between 55-95% of cumulative budget through the next reporting period
A26: B2 | B26: Inadequate but potential demonstrated | D26: Between 25-65% of cumulative budget through the next reporting period
A27: C | B27: Unacceptable | D27: Below 35% of cumulative budget through the next reporting period
A29: ="1. Cash amount requested by the Principal Recipient from the Global Fund for next disbursement period plus one additional quarter (amount in: "&IF(D10="","please select currency in 'PR_Section 1A')",D10&"):") -> 1. Cash amount requested by the Principal Recipient from the Global Fund for next disbursement period plus one additional quarter (amount in: EUR): | H29: =+'PR_Cash Request_7A&B'!D23 -> 1035000 | J29: =+IF('PR_Cash Request_7A&B'!D25="","",'PR_Cash Request_7A&B'!D25) -> One million thirty-five thousand US dollars
A31: ="2. LFA disbursement recommendation (amount in: "&IF(D10="","please select currency in 'PR_Section1A')",D10&"):") -> 2. LFA disbursement recommendation (amount in: EUR): | H31: ='LFA_Disbursement Recommend_5B'!K44 -> 866463.4 | J31: Eight hundred and Sixty Six thousand, Four hundred and Sixty three Euros.
J32: State the amount in words
A33: Cumulative budget through the next period of implementation (including the buffer) | D33: Cumulative disbursed amount to date (*) | F33: Cumulative disbursed after recommended disbursement (including the buffer) | H33: % range | J33: Is the recommended disbursement within the range?
B34: ='LFA_Total PR Cash Outflow_3A'!H13+'LFA_Disbursement Recommend_5B'!M18+'LFA_Disbursement Recommend_5B'!M22+'LFA_Disbursement Recommend_5B'!M28 -> 6677921 | D34: =958963+984665.49+64081.06+32734.99 -> 2040444.5 | F34: =H31+D34 -> 2906907.9 | H34: =IF(B34=0, "", F34/B34) -> 0.43530134 | J34: No
A35: (*)This data can be obtained from the "Disbursements in detail report (PDF)" (http://www.theglobalfund.org/documents/disbursementdetails.pdf)
A37: 3. Rationale for the LFA's disbursement recommendation (if resulting in cumulative disbursement outside the indicative ranges):
A38: PR had an LFA adjusted cash balance of EUR 532,822 as at 31 December 2010 and had an LFA adjusted forecast expenditure of Eur 1,399,285. Considering the PR's forecasted expenditure of EUR 1,399,285, the cash balance will not be adequate to finance the forecasted activities. In terms of financial performance, the PR had an absorption rate of 83% of the budgeted funds as at the end of December 2010. The PR's programmatic performance during the period under review was good, achieving an overall rating of 71.51% and being rated "B1" on an overall basis. Conclusion: Considering PR's improved programmatic performance and the financial absorption, we recommend that EUR 866,463 be disbursed. This will be split as follows: EUR 826,062 for program activities paid into the Global Fund Round 8 A/C # 0011084900890301 and EUR 40,401 to the VPP for procurement of health products.
A41: B. VERIFICATIONS
A42: The following information provided by the Principal Recipient in its On-going Progress Review and Disbursement Request has been verified: | J42: Comments regarding verifications, if any:
B43: Yes | C43: Signature on behalf of Principal Recipient is authentic and the person to whom it belongs is authorized to sign the disbursement request | J43: The signature on the PR signed page is that of Dr. Kujejatou Manneh, the Country Director of ActionAid The Gambia.
B44: Partially | C44: Conditions Precedent for disbursement and/or Special Conditions, if any, have been met (see Section 2, if applicable). | J44: With the exception of the Biological Surveillance Study (BSS) which is on-going, the PR has fulfilled all the other CPs as at the end of December 2010
B45: Yes | C45: Program Expenditures and cash reconciliation have been verified and correspond with the PR's Statement of Sources and Uses of Funds (Cash Flow Statement). | J45: We reviewed 95% of the PR's program expenditure. Program expenditure and cash reconciliations have been verified and reconciled by the LFA. Refer to LFA cash reconciliation 5A for details
B46: Yes | C46: Programmatic information provided by Principal Recipient in its On-going Progress Review and Disbursement Recommendation has been verified and corresponds with actual program progress. | J46: The programmatic results were verified
B47: Yes | C47: Exchange rate stated by Principal Recipient has been verified and is correct. | J47: Exchange rate provided has been verified with the Central Bank of Gambia rates for the same period and found to be reasonable.
B48: Yes | C48: PR Bank details verified/corrected by LFA | J48: The bank account information of the PR remains the same.
B49: Yes | C49: Current budget forecasts of the Principal Recipient for the next disbursement period plus buffer period have been reviewed for reasonableness | J49: The forecast submitted by PR has been reviewed and corrected. The PR in computing the forecast used the revised budget which has not yet been approved by GF.
B50: Yes | C50: LFA has debriefed the Principal Recipient on the key findings (comment on the format of this debriefing) | J50: An exit meeting was held with the PR, key members of the CCM and the LFA on 2 March 2011.
A51: NB: Please ensure that section 7C Bank Details on the following page is completed if (1) this is a split disbursement (i.e. disbursement going to more than one recipient) or (2) if there have been changes to the bank details since the previous disbursement.
A53: D. Summary of the LFA's approach used for verification of financial, programmatic and procurement data and Quality Assurance undertaken by the LFA
A54: In this section the LFA should indicate, as applicable, what percentage of expenditures was verified at PR level, if any expenditures were verified at SR level, how many site visits were made, what tender documentation was verified, and any other material parts of verification procedures in line with the verification approach agreed upfront between the LFA and GF Secretariat based on country/grant risks. As a good practice, the verification approach needs to be reviewed jointly by the LFA and the Secretariat annually.
A55: Programmatic review: Various approaches were used for the verification of the programmatic components during the current period's VOI. These included: - PR on site visits, interactions with PR staff, desk review of supporting documents (monthly/quarterly/survey reports, email, other correspondence) Financial, procurement and quality assurance: - Reviewed PR expenditure by validating supporting documents such as PVs, receipts, invoices, delivery notes etc - Reviewed cashbooks, bank reconciliation statements and bank statements. - Verified fixed assets procured and delivered to the PR. - Obtained explanations for variance between the budget and actual expenditure.
A57: NB: The LFA should sign a printed version of the verified PU/DR and send it to the Secretariat as a pdf file by email, or include an electronic signature in the Excel file to be submitted to the Global Fund.
A58: Signed on behalf of the LFA:
A59: Name: | D59: Mark Appleby
A60: Title: | D60: Director
A61: Date and Place: | D61: 21st March 2011/Accra

Sheet LFA_Bank Details_7C
A1: LFA On-going Progress Review and Disbursement Recommendation
B3: Note for LFAs: This page should be completed by the PR if (1) this is a split disbursement (i.e. disbursement going to more than one recipient) or (2) if there have been changes to the bank details since the previous disbursement. The amounts and bank details below are displayed as entered by the PR. If any of this information is incorrect, please correct them by overwriting with correct information.
B5: 7C: LFA-verified Bank Account Details
B7: Disbursement Request Period | C7: ='PR_Bank Details_7C'!C7 -> 0
B9: Summary | K9: Summary
C11: Beneficiary Name | D11: Amount in grant currency | L11: Beneficiary Name | M11: Amount in grant currency
B12: Payee 1 - Principal Recipient: | C12: =IF(C20="","",C20) -> ACTION AID , THE GAMBIA | D12: =IF(C30="",C24,C30) -> 826062 | K12: Payee 1 - Principal Recipient: | L12: =IF(L20="","",L20) | M12: =IF(L30="",L24,L30)
B13: Payee 2: | C13: =IF(C36="","",C36) -> VPP | D13: =IF(C46="",C40,C46) -> 40401 | K13: Payee 2: | L13: =IF(L36="","",L36) | M13: =IF(L46="",L40,L46)
B14: Payee 3: | C14: =IF(C53="","",C53) | D14: =IF(C63="",C57,C63) | K14: Payee 3: | L14: =IF(L53="","",L53) | M14: =IF(L63="",L57,L63)
B15: Payee 4: | C15: =IF(C69="","",C69) | D15: =IF(C79="",C73,C79) | K15: Payee 4: | L15: =IF(L69="","",L69) | M15: =IF(L79="",L73,L79)
B16: Total | D16: =SUM(D12:D15) -> 866463 | E16: =IF(D16<>'PR_Cash Request_7A&B'!D23,"The total does not match requested amount on PR signature page","") -> The total does not match requested amount on PR signature page | K16: Total | M16: =SUM(M12:M15) -> 0 | N16: =IF(M16<>'PR_Cash Request_7A&B'!M23,"The total does not match requested amount on PR signature page","")
B18: Payee 1: | K18: Payee 1:
B20: Beneficiary Name: | C20: ACTION AID , THE GAMBIA | E20: Owner of Bank Account: | F20: ActionAid The Gambia | K20: Beneficiary Name: | L20: =IF('PR_Bank Details_7C'!C20="","",'PR_Bank Details_7C'!C20) | N20: Owner of Bank Account: | O20: =IF('PR_Bank Details_7C'!F20="","",'PR_Bank Details_7C'!F20)
B22: Currency in which beneficiary should receive the funds | C22: EURO | E22: Owner of Bank Account: | F22: ActionAid The Gambia | K22: Currency in which beneficiary should receive the funds | L22: =IF('PR_Bank Details_7C'!C22="","",'PR_Bank Details_7C'!C22) | N22: Owner of Bank Account: | O22: =IF('PR_Bank Details_7C'!F22="","",'PR_Bank Details_7C'!F22)
B24: Amount in currency in which beneficiary should receive the funds: | C24: 826062 | E24: Bank Account Number: | F24: 11084900890301 | K24: Amount in currency in which beneficiary should receive the funds: | L24: =IF('PR_Bank Details_7C'!C24="","",'PR_Bank Details_7C'!C24) | N24: Bank Account Number: | O24: =IF('PR_Bank Details_7C'!F24="","",'PR_Bank Details_7C'!F24)
B26: Amount in Words: | C26: Eight hundred and twenty six thousand, sixty two Euros. | E26: Bank Address | F26: Ecobank 42 Kairaba Avenue P.O. Box 3466 The Gambia | K26: Amount in Words: | L26: =IF('PR_Bank Details_7C'!C26="","",'PR_Bank Details_7C'!C26) | N26: Bank Address | O26: =IF('PR_Bank Details_7C'!F26="","",'PR_Bank Details_7C'!F26)
B28: Exchange rate, date and source (Complete only if currency in which beneficiary should receive the funds is different from the grant currency) | C28: =L28 | E28: Bank SWIFT Code: | F28: =O28 | K28: Exchange rate, date and source (Complete only if currency in which beneficiary should receive the funds is different from the grant currency) | L28: =IF('PR_Bank Details_7C'!C28="","",'PR_Bank Details_7C'!C28) | N28: Bank SWIFT Code: | O28: =IF('PR_Bank Details_7C'!F28="","",'PR_Bank Details_7C'!F28)
B30: Equivalent in grant currency (Calculated based on the indicated exchange rate) | C30: =L30 | E30: Bank Code (Other): | F30: =O30 | K30: Equivalent in grant currency (Calculated based on the indicated exchange rate) | L30: =IF('PR_Bank Details_7C'!C30="","",'PR_Bank Details_7C'!C30) | N30: Bank Code (Other): | O30: =IF('PR_Bank Details_7C'!F30="","",'PR_Bank Details_7C'!F30)
E32: Routing Instructions: | F32: =O32 | N32: Routing Instructions: | O32: =IF('PR_Bank Details_7C'!F32="","",'PR_Bank Details_7C'!F32)
B34: Payee 2: | K34: Payee 2:
B36: Beneficiary Name: | C36: VPP | E36: Owner of Bank Account: | F36: =O36 | K36: Beneficiary Name: | L36: =IF('PR_Bank Details_7C'!C36="","",'PR_Bank Details_7C'!C36) | N36: Owner of Bank Account: | O36: =IF('PR_Bank Details_7C'!F36="","",'PR_Bank Details_7C'!F36)
B38: Currency in which beneficiary should receive the funds | C38: EUROS | E38: Owner of Bank Account: | F38: =O38 | K38: Currency in which beneficiary should receive the funds | L38: =IF('PR_Bank Details_7C'!C38="","",'PR_Bank Details_7C'!C38) | N38: Owner of Bank Account: | O38: =IF('PR_Bank Details_7C'!F38="","",'PR_Bank Details_7C'!F38)
B40: Amount in currency in which beneficiary should receive the funds: | C40: 40401 | E40: Bank Account Number: | F40: =O40 | K40: Amount in currency in which beneficiary should receive the funds: | L40: =IF('PR_Bank Details_7C'!C40="","",'PR_Bank Details_7C'!C40) | N40: Bank Account Number: | O40: =IF('PR_Bank Details_7C'!F40="","",'PR_Bank Details_7C'!F40)
B42: Amount in Words: | C42: Fourty thousand four hundred and one Euros. | E42: Bank Address | F42: =O42 | K42: Amount in Words: | L42: =IF('PR_Bank Details_7C'!C42="","",'PR_Bank Details_7C'!C42) | N42: Bank Address | O42: =IF('PR_Bank Details_7C'!F42="","",'PR_Bank Details_7C'!F42)
B44: Exchange rate, date and source (Complete only if currency in which beneficiary should receive the funds is different from the grant currency) | C44: =L44 | E44: Bank SWIFT Code: | F44: =O44 | K44: Exchange rate, date and source (Complete only if currency in which beneficiary should receive the funds is different from the grant currency) | L44: =IF('PR_Bank Details_7C'!C44="","",'PR_Bank Details_7C'!C44) | N44: Bank SWIFT Code: | O44: =IF('PR_Bank Details_7C'!F44="","",'PR_Bank Details_7C'!F44)
B46: Equivalent in grant currency (Calculated based on the indicated exchange rate) | C46: =L46 | E46: Bank Code (Other): | F46: =O46 | K46: Equivalent in grant currency (Calculated based on the indicated exchange rate) | L46: =IF('PR_Bank Details_7C'!C46="","",'PR_Bank Details_7C'!C46) | N46: Bank Code (Other): | O46: =IF('PR_Bank Details_7C'!F46="","",'PR_Bank Details_7C'!F46)
E48: Routing Instructions: | F48: =O48 | N48: Routing Instructions: | O48: =IF('PR_Bank Details_7C'!F48="","",'PR_Bank Details_7C'!F48)
B51: Payee 3: | K51: Payee 3:
B53: Beneficiary Name: | C53: =L53 | E53: Owner of Bank Account: | F53: =O53 | K53: Beneficiary Name: | L53: =IF('PR_Bank Details_7C'!C53="","",'PR_Bank Details_7C'!C53) | N53: Owner of Bank Account: | O53: =IF('PR_Bank Details_7C'!F53="","",'PR_Bank Details_7C'!F53)
B55: Currency in which beneficiary should receive the funds | C55: =L55 | E55: Owner of Bank Account: | F55: =O55 | K55: Currency in which beneficiary should receive the funds | L55: =IF('PR_Bank Details_7C'!C55="","",'PR_Bank Details_7C'!C55) | N55: Owner of Bank Account: | O55: =IF('PR_Bank Details_7C'!F55="","",'PR_Bank Details_7C'!F55)
B57: Amount in currency in which beneficiary should receive the funds: | C57: =L57 | E57: Bank Account Number: | F57: =O57 | K57: Amount in currency in which beneficiary should receive the funds: | L57: =IF('PR_Bank Details_7C'!C57="","",'PR_Bank Details_7C'!C57) | N57: Bank Account Number: | O57: =IF('PR_Bank Details_7C'!F57="","",'PR_Bank Details_7C'!F57)
B59: Amount in Words: | C59: =L59 | E59: Bank Address | F59: =O59 | K59: Amount in Words: | L59: =IF('PR_Bank Details_7C'!C59="","",'PR_Bank Details_7C'!C59) | N59: Bank Address | O59: =IF('PR_Bank Details_7C'!F59="","",'PR_Bank Details_7C'!F59)
B61: Exchange rate, date and source (Complete only if currency in which beneficiary should receive the funds is different from the grant currency) | C61: =L61 | E61: Bank SWIFT Code: | F61: =O61 | K61: Exchange rate, date and source (Complete only if currency in which beneficiary should receive the funds is different from the grant currency) | L61: =IF('PR_Bank Details_7C'!C61="","",'PR_Bank Details_7C'!C61) | N61: Bank SWIFT Code: | O61: =IF('PR_Bank Details_7C'!F61="","",'PR_Bank Details_7C'!F61)
B63: Equivalent in grant currency (Calculated based on the indicated exchange rate) | C63: =L63 | E63: Bank Code (Other): | F63: =O63 | K63: Equivalent in grant currency (Calculated based on the indicated exchange rate) | L63: =IF('PR_Bank Details_7C'!C63="","",'PR_Bank Details_7C'!C63) | N63: Bank Code (Other): | O63: =IF('PR_Bank Details_7C'!F63="","",'PR_Bank Details_7C'!F63)
E65: Routing Instructions: | F65: =O65 | N65: Routing Instructions: | O65: =IF('PR_Bank Details_7C'!F65="","",'PR_Bank Details_7C'!F65)
B67: Payee 4: | K67: Payee 4:
B69: Beneficiary Name: | C69: =L69 | E69: Owner of Bank Account: | F69: =O69 | K69: Beneficiary Name: | L69: =IF('PR_Bank Details_7C'!C69="","",'PR_Bank Details_7C'!C69) | N69: Owner of Bank Account: | O69: =IF('PR_Bank Details_7C'!F69="","",'PR_Bank Details_7C'!F69)
B71: Currency in which beneficiary should receive the funds | C71: =L71 | E71: Owner of Bank Account: | F71: =O71 | K71: Currency in which beneficiary should receive the funds | L71: =IF('PR_Bank Details_7C'!C71="","",'PR_Bank Details_7C'!C71) | N71: Owner of Bank Account: | O71: =IF('PR_Bank Details_7C'!F71="","",'PR_Bank Details_7C'!F71)
B73: Amount in currency in which beneficiary should receive the funds: | C73: =L73 | E73: Bank Account Number: | F73: =O73 | K73: Amount in currency in which beneficiary should receive the funds: | L73: =IF('PR_Bank Details_7C'!C73="","",'PR_Bank Details_7C'!C73) | N73: Bank Account Number: | O73: =IF('PR_Bank Details_7C'!F73="","",'PR_Bank Details_7C'!F73)
B75: Amount in Words: | C75: =L75 | E75: Bank Address | F75: =O75 | K75: Amount in Words: | L75: =IF('PR_Bank Details_7C'!C75="","",'PR_Bank Details_7C'!C75) | N75: Bank Address | O75: =IF('PR_Bank Details_7C'!F75="","",'PR_Bank Details_7C'!F75)
B77: Exchange rate, date and source (Complete only if currency in which beneficiary should receive the funds is different from the grant currency) | C77: =L77 | E77: Bank SWIFT Code: | F77: =O77 | K77: Exchange rate, date and source (Complete only if currency in which beneficiary should receive the funds is different from the grant currency) | L77: =IF('PR_Bank Details_7C'!C77="","",'PR_Bank Details_7C'!C77) | N77: Bank SWIFT Code: | O77: =IF('PR_Bank Details_7C'!F77="","",'PR_Bank Details_7C'!F77)
B79: Equivalent in grant currency (Calculated based on the indicated exchange rate) | C79: =L79 | E79: Bank Code (Other): | F79: =O79 | K79: Equivalent in grant currency (Calculated based on the indicated exchange rate) | L79: =IF('PR_Bank Details_7C'!C79="","",'PR_Bank Details_7C'!C79) | N79: Bank Code (Other): | O79: =IF('PR_Bank Details_7C'!F79="","",'PR_Bank Details_7C'!F79)
E81: Routing Instructions: | F81: =O81 | N81: Routing Instructions: | O81: =IF('PR_Bank Details_7C'!F81="","",'PR_Bank Details_7C'!F81)

Sheet LFA_Annex-SR Financials
B1: LFA On-going Progress Review and Disbursement Recommendation
B3: Annex to PU/DR - LFA-reviewed Sub-recipient financial information ! Completion of this table by the PR and verification by the LFA are discretionary, and should be done upon the Secretariat's request.
B5: Grant number: | G5: ='LFA_Programmatic Progress_1A'!C7 -> MNR-809-G04-H
B6: Progress Update - Reporting Period: | G6: Cycle: | H6: ='PR_Programmatic Progress_1A'!D12 -> Quarter | J6: Number: | L6: ='PR_Programmatic Progress_1A'!F12 -> 7
B7: Progress Update - Period Covered: | G7: Beginning Date: | H7: ='PR_Programmatic Progress_1A'!D13 -> 40452 | J7: End Date: | L7: ='PR_Programmatic Progress_1A'!F13 -> 40543
B8: Progress Update - Number: | G8: ='LFA_Programmatic Progress_1A'!C14 -> 5
B9: Currency: | G9: =IF('LFA_Programmatic Progress_1A'!C10="","",'LFA_Programmatic Progress_1A'!C10) -> EUR
B11: Note for LFAs: The information below is displayed as entered by the PR. If any of this information is incorrect, please correct them by overwriting with correct information.
B14: Name of Entity | C14: Type of Implementing Entity | D14: Date of Most Recent Disbursement to SR | F14: Budget for Reporting Period* | G14: Disbursed during Reporting Period* | I14: Cumulative Budget through period of Progress Update* | J14: Cumulative Disbursed through period of Progress Update* | L14: Cumulative Actual Expenditure through period covered by this Progress Update | M14: Cash balance at the end of the period covered by this Progress Update | N14: Variance between Latest Cumulative Expenditure Reported and Cumulative Budget | O14: Expenditure Verified by PR (YES/NO) | P14: PR's explanation of variance (1) between cumulative budget and cumulative expenditure and (2) between cumulative disbursement and cumulative expenditure (mandatory for amounts above $50,000 or equivalent and with more than 10% variance) | Q14: LFA Comments on the PR's overall verification efforts of SR expenditure and the explanations of variance provided | U14: Name of Entity | V14: Type of Implementing Entity | W14: Date of Most Recent Disbursement to SR | Y14: Budget for Reporting Period* | Z14: Disbursed during Reporting Period* | AB14: Cumulative Budget through period of Progress Update* | AC14: Cumulative Disbursed through period of Progress Update* | AE14: Latest Cumulative Actual Expenditure (as per most recent SR reports available at PR level) | AF14: End date of period covered in most recent SR report | AG14: Variance between Latest Cumulative Expenditure Reported and Cumulative Budget | AH14: Expenditure Verified by PR (YES/NO) | AI14: PR's explanation of variance (mandatory for amounts above $50,000 and with more than 10% variance)
B15: =U15 | C15: =V15 -> 0 | D15: =W15 | F15: =Y15 -> 0 | G15: =Z15 -> 0 | I15: =AB15 -> 0 | J15: =AC15 -> 0 | L15: =AE15 -> 0 | N15: =IF(I15="",IF(L15="",0,SUM(I15-L15)),SUM(I15-L15)) -> 0 | O15: 0 | P15: =AI15 | U15: =IF('PR_Annex_SR-Financials'!B15="","",'PR_Annex_SR-Financials'!B15) | V15: =IF('PR_Annex_SR-Financials'!C15="","",'PR_Annex_SR-Financials'!C15) -> 0 | W15: =IF('PR_Annex_SR-Financials'!D15="","",'PR_Annex_SR-Financials'!D15) | Y15: =IF('PR_Annex_SR-Financials'!F15="","",'PR_Annex_SR-Financials'!F15) -> 0 | Z15: =IF('PR_Annex_SR-Financials'!G15="","",'PR_Annex_SR-Financials'!G15) -> 0 | AB15: =IF('PR_Annex_SR-Financials'!I15="","",'PR_Annex_SR-Financials'!I15) -> 0 | AC15: =IF('PR_Annex_SR-Financials'!J15="","",'PR_Annex_SR-Financials'!J15) -> 0 | AE15: =IF('PR_Annex_SR-Financials'!L15="","",'PR_Annex_SR-Financials'!L15) -> 0 | AF15: =IF('PR_Annex_SR-Financials'!M15="","",'PR_Annex_SR-Financials'!M15) | AG15: =IF(AB15="",IF(AE15="",0,SUM(AB15-AE15)),SUM(AB15-AE15)) -> 0 | AI15: =IF('PR_Annex_SR-Financials'!P15="","",'PR_Annex_SR-Financials'!P15)
B16: =U16 | C16: =IF('PR_Annex_SR-Financials'!C16="","",'PR_Annex_SR-Financials'!C16) -> 0 | D16: =W16 | F16: =Y16 -> 0 | G16: =Z16 -> 0 | I16: =AB16 -> 0 | J16: =AC16 -> 0 | L16: =AE16 -> 0 | N16: =IF(I16="",IF(L16="",0,SUM(I16-L16)),SUM(I16-L16)) -> 0 | O16: 0 | P16: =AI16 | U16: =IF('PR_Annex_SR-Financials'!B16="","",'PR_Annex_SR-Financials'!B16) | V16: =IF('PR_Annex_SR-Financials'!C16="","",'PR_Annex_SR-Financials'!C16) -> 0 | W16: =IF('PR_Annex_SR-Financials'!D16="","",'PR_Annex_SR-Financials'!D16) | Y16: =IF('PR_Annex_SR-Financials'!F16="","",'PR_Annex_SR-Financials'!F16) -> 0 | Z16: =IF('PR_Annex_SR-Financials'!G16="","",'PR_Annex_SR-Financials'!G16) -> 0 | AB16: =IF('PR_Annex_SR-Financials'!I16="","",'PR_Annex_SR-Financials'!I16) -> 0 | AC16: =IF('PR_Annex_SR-Financials'!J16="","",'PR_Annex_SR-Financials'!J16) -> 0 | AE16: =IF('PR_Annex_SR-Financials'!L16="","",'PR_Annex_SR-Financials'!L16) -> 0 | AF16: =IF('PR_Annex_SR-Financials'!M16="","",'PR_Annex_SR-Financials'!M16) | AG16: =IF(AB16="",IF(AE16="",0,SUM(AB16-AE16)),SUM(AB16-AE16)) -> 0 | AI16: =IF('PR_Annex_SR-Financials'!P16="","",'PR_Annex_SR-Financials'!P16)
B17: =U17 | C17: =IF('PR_Annex_SR-Financials'!C17="","",'PR_Annex_SR-Financials'!C17) -> 0 | D17: =W17 | F17: =Y17 -> 0 | G17: =Z17 -> 0 | I17: =AB17 -> 0 | J17: =AC17 -> 0 | L17: =AE17 -> 0 | M17: =AF17 | N17: =IF(I17="",IF(L17="",0,SUM(I17-L17)),SUM(I17-L17)) -> 0 | O17: 0 | P17: =AI17 | U17: =IF('PR_Annex_SR-Financials'!B17="","",'PR_Annex_SR-Financials'!B17) | V17: =IF('PR_Annex_SR-Financials'!C17="","",'PR_Annex_SR-Financials'!C17) -> 0 | W17: =IF('PR_Annex_SR-Financials'!D17="","",'PR_Annex_SR-Financials'!D17) | Y17: =IF('PR_Annex_SR-Financials'!F17="","",'PR_Annex_SR-Financials'!F17) -> 0 | Z17: =IF('PR_Annex_SR-Financials'!G17="","",'PR_Annex_SR-Financials'!G17) -> 0 | AB17: =IF('PR_Annex_SR-Financials'!I17="","",'PR_Annex_SR-Financials'!I17) -> 0 | AC17: =IF('PR_Annex_SR-Financials'!J17="","",'PR_Annex_SR-Financials'!J17) -> 0 | AE17: =IF('PR_Annex_SR-Financials'!L17="","",'PR_Annex_SR-Financials'!L17) -> 0 | AF17: =IF('PR_Annex_SR-Financials'!M17="","",'PR_Annex_SR-Financials'!M17) | AG17: =IF(AB17="",IF(AE17="",0,SUM(AB17-AE17)),SUM(AB17-AE17)) -> 0 | AI17: =IF('PR_Annex_SR-Financials'!P17="","",'PR_Annex_SR-Financials'!P17)
B18: =U18 | C18: =IF('PR_Annex_SR-Financials'!C18="","",'PR_Annex_SR-Financials'!C18) -> 0 | D18: =W18 | F18: =Y18 -> 0 | G18: =Z18 -> 0 | I18: =AB18 -> 0 | J18: =AC18 -> 0 | L18: =AE18 -> 0 | M18: =AF18 | N18: =IF(I18="",IF(L18="",0,SUM(I18-L18)),SUM(I18-L18)) -> 0 | O18: 0 | P18: =AI18 | U18: =IF('PR_Annex_SR-Financials'!B18="","",'PR_Annex_SR-Financials'!B18) | V18: =IF('PR_Annex_SR-Financials'!C18="","",'PR_Annex_SR-Financials'!C18) -> 0 | W18: =IF('PR_Annex_SR-Financials'!D18="","",'PR_Annex_SR-Financials'!D18) | Y18: =IF('PR_Annex_SR-Financials'!F18="","",'PR_Annex_SR-Financials'!F18) -> 0 | Z18: =IF('PR_Annex_SR-Financials'!G18="","",'PR_Annex_SR-Financials'!G18) -> 0 | AB18: =IF('PR_Annex_SR-Financials'!I18="","",'PR_Annex_SR-Financials'!I18) -> 0 | AC18: =IF('PR_Annex_SR-Financials'!J18="","",'PR_Annex_SR-Financials'!J18) -> 0 | AE18: =IF('PR_Annex_SR-Financials'!L18="","",'PR_Annex_SR-Financials'!L18) -> 0 | AF18: =IF('PR_Annex_SR-Financials'!M18="","",'PR_Annex_SR-Financials'!M18) | AG18: =IF(AB18="",IF(AE18="",0,SUM(AB18-AE18)),SUM(AB18-AE18)) -> 0 | AI18: =IF('PR_Annex_SR-Financials'!P18="","",'PR_Annex_SR-Financials'!P18)
B19: =U19 | C19: =IF('PR_Annex_SR-Financials'!C19="","",'PR_Annex_SR-Financials'!C19) -> 0 | D19: =W19 | F19: =Y19 -> 0 | G19: =Z19 -> 0 | I19: =AB19 -> 0 | J19: =AC19 -> 0 | L19: =AE19 -> 0 | M19: =AF19 | N19: =IF(I19="",IF(L19="",0,SUM(I19-L19)),SUM(I19-L19)) -> 0 | O19: 0 | P19: =AI19 | U19: =IF('PR_Annex_SR-Financials'!B19="","",'PR_Annex_SR-Financials'!B19) | V19: =IF('PR_Annex_SR-Financials'!C19="","",'PR_Annex_SR-Financials'!C19) -> 0 | W19: =IF('PR_Annex_SR-Financials'!D19="","",'PR_Annex_SR-Financials'!D19) | Y19: =IF('PR_Annex_SR-Financials'!F19="","",'PR_Annex_SR-Financials'!F19) -> 0 | Z19: =IF('PR_Annex_SR-Financials'!G19="","",'PR_Annex_SR-Financials'!G19) -> 0 | AB19: =IF('PR_Annex_SR-Financials'!I19="","",'PR_Annex_SR-Financials'!I19) -> 0 | AC19: =IF('PR_Annex_SR-Financials'!J19="","",'PR_Annex_SR-Financials'!J19) -> 0 | AE19: =IF('PR_Annex_SR-Financials'!L19="","",'PR_Annex_SR-Financials'!L19) -> 0 | AF19: =IF('PR_Annex_SR-Financials'!M19="","",'PR_Annex_SR-Financials'!M19) | AG19: =IF(AB19="",IF(AE19="",0,SUM(AB19-AE19)),SUM(AB19-AE19)) -> 0 | AI19: =IF('PR_Annex_SR-Financials'!P19="","",'PR_Annex_SR-Financials'!P19)
