Workbook

Sheet Summary
A1: Community and Technical Colleges, Report of Fundable Operating Expenses, Fiscal Year (FY) 2008
A2: Summary of Expense divided Contact Hours
A3: Contact Hours for fall 2007 and spring and summer 2008
A4: Fund | B4: Total Expense by Discipline | D4: Contact Hours | E4: Expense | F4: Expense per Contact Hour
A5: 1 | B5: Agriculture | D5: =D36 -> 1534719 | E5: =E36+E67+IFERROR($E$105/$D$105*D5,0) -> 13513304 | F5: =F36+F67+$F$105 -> 7.7
A6: 2 | B6: Architecture and Precision Production Trades | D6: =D37 -> 3407979 | E6: =E37+E68+IFERROR($E$105/$D$105*D6,0) -> 34957122 | F6: =F37+F68+$F$105 -> 8.88
A7: 3 | B7: Biology, Physical Sciences, and Science Technology | D7: =D38 -> 29317564 | E7: =E38+E69+IFERROR($E$105/$D$105*D7,0) -> 2.2249238e+08 | F7: =F38+F69+$F$105 -> 6.85
A8: 4 | B8: Business Management, Marketing, and Administrative Services | D8: =D39 -> 17818481 | E8: =E39+E70+IFERROR($E$105/$D$105*D8,0) -> 1.4084724e+08 | F8: =F39+F70+$F$105 -> 7.11
A9: 5 | B9: Career Pilot | D9: =D40 -> 180656 | E9: =E40+E71+IFERROR($E$105/$D$105*D9,0) -> 5463573.8 | F9: =F40+F71+$F$105 -> 33.87
A10: 6 | B10: Communications | D10: =D41 -> 4119103 | E10: =E41+E72+IFERROR($E$105/$D$105*D10,0) -> 33422475 | F10: =F41+F72+$F$105 -> 7.65
A11: 7 | B11: Computer and Information Sciences | D11: =D42 -> 11156743 | E11: =E42+E73+IFERROR($E$105/$D$105*D11,0) -> 1.0896882e+08 | F11: =F42+F73+$F$105 -> 8.52
A12: 8 | B12: Construction Trades | D12: =D43 -> 1641826 | E12: =E43+E74+IFERROR($E$105/$D$105*D12,0) -> 15050396 | F12: =F43+F74+$F$105 -> 8.03
A13: 9 | B13: Consumer and Homemaking Education | D13: =D44 -> 8752792 | E13: =E44+E75+IFERROR($E$105/$D$105*D13,0) -> 66186357 | F13: =F44+F75+$F$105 -> 6.75
A14: 10 | B14: Engineering | D14: =D45 -> 253339 | E14: =E45+E76+IFERROR($E$105/$D$105*D14,0) -> 2621275.6 | F14: =F45+F76+$F$105 -> 7.86
A15: 11 | B15: Engineering Related | D15: =D46 -> 6787477 | E15: =E46+E77+IFERROR($E$105/$D$105*D15,0) -> 60923755 | F15: =F46+F77+$F$105 -> 7.41
A16: 12 | B16: English Language, Lit, Philosophy, Humanities, & Interdisciplinary | D16: =D47 -> 38977120 | E16: =E47+E78+IFERROR($E$105/$D$105*D16,0) -> 3.2234136e+08 | F16: =F47+F78+$F$105 -> 7.31
... A30: 26 | B30: Visual and Performing Arts | D30: =D61 -> 12932275 | E30: =E61+E92+IFERROR($E$105/$D$105*D30,0) -> 1.2311475e+08 | F30: =F61+F92+$F$105 -> 8.36
A31: 28 | B31: Developmental Education - Math | D31: =D62 -> 0 | E31: =E62+E93+IFERROR($E$105/$D$105*D31,0) -> 0
A32: 29 | B32: Developmental Education - Reading/Writing | D32: =D63 -> 0 | E32: =E63+E94+IFERROR($E$105/$D$105*D32,0) -> 0
B33: Total | D33: =SUM(D5:D32) -> 254560011 | E33: =SUM(E5:E32) -> 2.1110026e+09 | F33: =F64+F95+$F$105 -> 7.6
A35: Fund | B35: Departmental Operating Expense by Discipline | D35: Contact Hours | E35: Expense | F35: Expense per Contact Hour
A36: 1 | B36: Agriculture | D36: =SUM('1:57'!D36) -> 1534719 | E36: =SUM('1:57'!E36) -> 2984519 | F36: =ROUND(MEDIAN('1:57'!F36),2) -> 1.16
A37: 2 | B37: Architecture and Precision Production Trades | D37: =SUM('1:57'!D37) -> 3407979 | E37: =SUM('1:57'!E37) -> 8046820 | F37: =ROUND(MEDIAN('1:57'!F37),2) -> 2.22
A38: 3 | B38: Biology, Physical Sciences, and Science Technology | D38: =SUM('1:57'!D38) -> 29317564 | E38: =SUM('1:57'!E38) -> 29374637 | F38: =ROUND(MEDIAN('1:57'!F38),2) -> 0.81
A39: 4 | B39: Business Management, Marketing, and Administrative Services | D39: =SUM('1:57'!D39) -> 17818481 | E39: =SUM('1:57'!E39) -> 19582467 | F39: =ROUND(MEDIAN('1:57'!F39),2) -> 0.81
A40: 5 | B40: Career Pilot | D40: =SUM('1:57'!D40) -> 180656 | E40: =SUM('1:57'!E40) -> 3465653 | F40: =ROUND(MEDIAN('1:57'!F40),2) -> 20.99
A41: 6 | B41: Communications | D41: =SUM('1:57'!D41) -> 4119103 | E41: =SUM('1:57'!E41) -> 9113634 | F41: =ROUND(MEDIAN('1:57'!F41),2) -> 1.5
A42: 7 | B42: Computer and Information Sciences | D42: =SUM('1:57'!D42) -> 11156743 | E42: =SUM('1:57'!E42) -> 22748020 | F42: =ROUND(MEDIAN('1:57'!F42),2) -> 1.39
A43: 8 | B43: Construction Trades | D43: =SUM('1:57'!D43) -> 1641826 | E43: =SUM('1:57'!E43) -> 3590333 | F43: =ROUND(MEDIAN('1:57'!F43),2) -> 1.92
A44: 9 | B44: Consumer and Homemaking Education | D44: =SUM('1:57'!D44) -> 8752792 | E44: =SUM('1:57'!E44) -> 11488314 | F44: =ROUND(MEDIAN('1:57'!F44),2) -> 0.87
A45: 10 | B45: Engineering | D45: =SUM('1:57'!D45) -> 253339 | E45: =SUM('1:57'!E45) -> 456097 | F45: =ROUND(MEDIAN('1:57'!F45),2) -> 1.29
A46: 11 | B46: Engineering Related | D46: =SUM('1:57'!D46) -> 6787477 | E46: =SUM('1:57'!E46) -> 13809588 | F46: =ROUND(MEDIAN('1:57'!F46),2) -> 1.28
A47: 12 | B47: English Language, Lit, Philosophy, Humanities, & Interdisciplinary | D47: =SUM('1:57'!D47) -> 38977120 | E47: =SUM('1:57'!E47) -> 35213340 | F47: =ROUND(MEDIAN('1:57'!F47),2) -> 0.71
... A61: 26 | B61: Visual and Performing Arts | D61: =SUM('1:57'!D61) -> 12932275 | E61: =SUM('1:57'!E61) -> 19609036 | F61: =ROUND(MEDIAN('1:57'!F61),2) -> 1.23
A62: 28 | B62: Developmental Education - Math | D62: =SUM('1:57'!D62) -> 0 | E62: =SUM('1:57'!E62) -> 0
A63: 29 | B63: Developmental Education - Reading/Writing | D63: =SUM('1:57'!D63) -> 0 | E63: =SUM('1:57'!E63) -> 0
C64: Total | D64: =SUM(D36:D63) -> 254560011 | E64: =SUM(E36:E63) -> 298174071 | F64: =ROUND(MEDIAN('1:57'!F64),2) -> 1.05
A66: Fund | B66: Faculty Salaries by Discipline | D66: Contact Hours | E66: Expense | F66: Expense per Contact Hour
A67: 1 | B67: Agriculture | D67: =D36 -> 1534719 | E67: =SUM('1:57'!E67) -> 4815786 | F67: =ROUND(MEDIAN('1:57'!F67),2) -> 3.26
A68: 2 | B68: Architecture and Precision Production Trades | D68: =D37 -> 3407979 | E68: =SUM('1:57'!E68) -> 14224084 | F68: =ROUND(MEDIAN('1:57'!F68),2) -> 3.38
A69: 3 | B69: Biology, Physical Sciences, and Science Technology | D69: =D38 -> 29317564 | E69: =SUM('1:57'!E69) -> 83982977 | F69: =ROUND(MEDIAN('1:57'!F69),2) -> 2.76
A70: 4 | B70: Business Management, Marketing, and Administrative Services | D70: =D39 -> 17818481 | E70: =SUM('1:57'!E70) -> 54935391 | F70: =ROUND(MEDIAN('1:57'!F70),2) -> 3.02
A71: 5 | B71: Career Pilot | D71: =D40 -> 180656 | E71: =SUM('1:57'!E71) -> 1325428 | F71: =ROUND(MEDIAN('1:57'!F71),2) -> 9.6
A72: 6 | B72: Communications | D72: =D41 -> 4119103 | E72: =SUM('1:57'!E72) -> 8975461 | F72: =ROUND(MEDIAN('1:57'!F72),2) -> 2.87
A73: 7 | B73: Computer and Information Sciences | D73: =D42 -> 11156743 | E73: =SUM('1:57'!E73) -> 44689771 | F73: =ROUND(MEDIAN('1:57'!F73),2) -> 3.85
A74: 8 | B74: Construction Trades | D74: =D43 -> 1641826 | E74: =SUM('1:57'!E74) -> 5348358 | F74: =ROUND(MEDIAN('1:57'!F74),2) -> 2.83
A75: 9 | B75: Consumer and Homemaking Education | D75: =D44 -> 8752792 | E75: =SUM('1:57'!E75) -> 22115734 | F75: =ROUND(MEDIAN('1:57'!F75),2) -> 2.6
A76: 10 | B76: Engineering | D76: =D45 -> 253339 | E76: =SUM('1:57'!E76) -> 1222123 | F76: =ROUND(MEDIAN('1:57'!F76),2) -> 3.29
A77: 11 | B77: Engineering Related | D77: =D46 -> 6787477 | E77: =SUM('1:57'!E77) -> 21847753 | F77: =ROUND(MEDIAN('1:57'!F77),2) -> 2.85
A78: 12 | B78: English Language, Lit, Philosophy, Humanities, & Interdisciplinary | D78: =D47 -> 38977120 | E78: =SUM('1:57'!E78) -> 142035506 | F78: =ROUND(MEDIAN('1:57'!F78),2) -> 3.32
... A92: 26 | B92: Visual and Performing Arts | D92: =D61 -> 12932275 | E92: =SUM('1:57'!E92) -> 55365256 | F92: =ROUND(MEDIAN('1:57'!F92),2) -> 3.85
A93: 28 | B93: Developmental Education - Math | D93: =D62 -> 0 | E93: =SUM('1:57'!E93) -> 0
A94: 29 | B94: Developmental Education - Reading/Writing | D94: =D63 -> 0 | E94: =SUM('1:57'!E94) -> 0
C95: Total | D95: =SUM(D67:D94) -> 254560011 | E95: =SUM(E67:E94) -> 865227750 | F95: =ROUND(MEDIAN('1:57'!F95),2) -> 3.27
B97: Allocated Administrative Expense | D97: Contact Hours | E97: Expense | F97: Expense per Contact Hour
B98: Institutional Support | E98: =SUM('1:57'!E98) -> 405557297 | F98: =ROUND(MEDIAN('1:57'!F98),2) -> 1.54
B99: Student Services | E99: =SUM('1:57'!E99) -> 208797311 | F99: =ROUND(MEDIAN('1:57'!F99),2) -> 0.71
B100: Academic Support | E100: =SUM('1:57'!E100) -> 218103285 | F100: =ROUND(MEDIAN('1:57'!F100),2) -> 0.7
B101: Research | E101: =SUM('1:57'!E101) -> 716702 | F101: =ROUND(MEDIAN('1:57'!F101),2) -> 0
B102: Scholarships and Fellowships | E102: =SUM('1:57'!E102) -> 19975984 | F102: =ROUND(MEDIAN('1:57'!F102),2) -> 0.01
B103: Equipment Depreciation | E103: =SUM('1:57'!E103) -> 37941862 | F103: =ROUND(MEDIAN('1:57'!F103),2) -> 0.15
B104: Local Benefits | E104: =SUM('1:57'!E104) -> 56508376 | F104: =ROUND(MEDIAN('1:57'!F104),2) -> 0.17
C105: Total | D105: =D95 -> 254560011 | E105: =SUM(E98:E104) -> 947600817 | F105: =SUM(F98:F104) -> 3.28
B107: Annual Financial Report - Schedule B
B108: Unrestricted - Educational Activities | C108: Salaries and Wages | D108: Local Benefits | E108: Other Expenses | F108: Total
B109: Instruction | C109: =SUM('1:57'!C109) -> 983013791 | D109: =SUM('1:57'!D109) -> 72954960 | E109: =SUM('1:57'!E109) -> 116272376 | F109: =SUM('1:57'!F109) -> 1172241127
B110: Research | C110: =SUM('1:57'!C110) -> 603575 | D110: =SUM('1:57'!D110) -> 0 | E110: =SUM('1:57'!E110) -> 603575 | F110: =SUM('1:57'!F110) -> 1207150
B111: Public Service | C111: =SUM('1:57'!C111) -> 59589438 | D111: =SUM('1:57'!D111) -> 0 | E111: =SUM('1:57'!E111) -> 39256244 | F111: =SUM('1:57'!F111) -> 98845682
B112: Academic Support | C112: =SUM('1:57'!C112) -> 163580304 | D112: =SUM('1:57'!D112) -> 0 | E112: =SUM('1:57'!E112) -> 54522981 | F112: =SUM('1:57'!F112) -> 218103285
B113: Student Services | C113: =SUM('1:57'!C113) -> 173410735 | D113: =SUM('1:57'!D113) -> 0 | E113: =SUM('1:57'!E113) -> 35386576 | F113: =SUM('1:57'!F113) -> 208797311
B114: Instructional Support | C114: =SUM('1:57'!C114) -> 244719614 | D114: =SUM('1:57'!D114) -> 0 | E114: =SUM('1:57'!E114) -> 160837683 | F114: =SUM('1:57'!F114) -> 405557297
B115: Operation and Maintenance of Plant | C115: =SUM('1:57'!C115) -> 87302395 | D115: =SUM('1:57'!D115) -> 20876555 | E115: =SUM('1:57'!E115) -> 249888001 | F115: =SUM('1:57'!F115) -> 358066951
B116: Scholarships and Fellowships | C116: =SUM('1:57'!C116) -> 51442 | D116: =SUM('1:57'!D116) -> 0 | E116: =SUM('1:57'!E116) -> 19975984 | F116: =SUM('1:57'!F116) -> 20027426
B117: Other | C117: =SUM('1:57'!C117) -> 0 | D117: =SUM('1:57'!D117) -> 56508376 | E117: =SUM('1:57'!E117) -> 0 | F117: =SUM('1:57'!F117) -> 56508376
B118: Total | C118: =SUM(C109:C116) -> 1712271294 | D118: =SUM(D109:D116) -> 93831515 | E118: =SUM(E109:E116) -> 676743420 | F118: =SUM(F109:F116) -> 2482846229
B120: Depreciation Expense - Equipment | C120: =SUM('1:57'!C120) -> 0 | D120: =SUM('1:57'!D120) -> 0 | E120: =SUM('1:57'!E120) -> 37941862 | F120: =SUM('1:57'!F120) -> 37941862
A122: Each year, the Texas Higher Education Coordinating Board revises the Texas Public Community and Technical Colleges Expense per Contact Hour Rates used in its Instruction and Operations Formula Funding Recommendation to the Legislative Budget Board (LBB). The Report of Fundable Operating Expenses (RFOE), completed by the institutions, collects departmental operating expense, faculty salaries, institutional support, student services, academic support, research, scholarships and fellowships, equipment depreciation, and local benefits for input into this summary using Annual Financial Report (AFR) Schedule B, which ties to the AFR Statement of Revenues, Expenses and Changes in Net Assets (SRECNA). The RFOE subcategorizes the expenditures collected in Schedule B funded with unrestricted funds, totals them for all institutions, and divides them by the statewide contact hours to determine rates by discipline.

Sheet Rate History
A1: =Summary!A1 -> Community and Technical Colleges, Report of Fundable Operating Expenses, Fiscal Year (FY) 2008
A2: Rate History | N2: Year over Year Change
A3: Fund | B3: Expense per Contact Hour by Discipline | C3: 2008 | D3: 2007 | E3: 2006 | F3: 2005 | G3: 2004 | H3: 2003 | I3: 2002 | J3: 2001 | K3: 2000 | L3: 1999 | N3: 2008 | O3: 2007 | P3: 2006 | Q3: 2005 | R3: 2004 | S3: 2003 | T3: 2002 | U3: 2001 | V3: 2000
A4: 1 | B4: Agriculture | C4: =Summary!F5 -> 7.7 | D4: 7.37 | F4: 7.25 | G4: 9.82 | H4: 7.18 | I4: 7.58 | J4: 7 | K4: 6.67 | L4: 6.81 | N4: =IFERROR(C4/D4-1,"") -> 0.044776119 | O4: =IFERROR(D4/E4-1,"") | P4: =IFERROR(E4/F4-1,"") -> -1 | Q4: =IFERROR(F4/G4-1,"") -> -0.26171079 | R4: =IFERROR(G4/H4-1,"") -> 0.36768802 | S4: =IFERROR(H4/I4-1,"") -> -0.052770449 | T4: =IFERROR(I4/J4-1,"") -> 0.082857143 | U4: =IFERROR(J4/K4-1,"") -> 0.049475262 | V4: =IFERROR(K4/L4-1,"") -> -0.020558003
A5: 2 | B5: Architecture and Precision Production Trades | C5: =Summary!F6 -> 8.88 | D5: 10.29 | F5: 8.82 | G5: 11.31 | H5: 7.31 | I5: 7.27 | J5: 7.56 | K5: 6.83 | L5: 6.64 | N5: =IFERROR(C5/D5-1,"") -> -0.13702624 | O5: =IFERROR(D5/E5-1,"") | P5: =IFERROR(E5/F5-1,"") -> -1 | Q5: =IFERROR(F5/G5-1,"") -> -0.22015915 | R5: =IFERROR(G5/H5-1,"") -> 0.54719562 | S5: =IFERROR(H5/I5-1,"") -> 0.0055020633 | T5: =IFERROR(I5/J5-1,"") -> -0.038359788 | U5: =IFERROR(J5/K5-1,"") -> 0.10688141 | V5: =IFERROR(K5/L5-1,"") -> 0.028614458
A6: 3 | B6: Biology, Physical Sciences, and Science Technology | C6: =Summary!F7 -> 6.85 | D6: 6.65 | F6: 6.19 | G6: 7.98 | H6: 5.86 | I6: 6.04 | J6: 5.9 | K6: 5.69 | L6: 5.51 | N6: =IFERROR(C6/D6-1,"") -> 0.030075188 | O6: =IFERROR(D6/E6-1,"") | P6: =IFERROR(E6/F6-1,"") -> -1 | Q6: =IFERROR(F6/G6-1,"") -> -0.22431078 | R6: =IFERROR(G6/H6-1,"") -> 0.36177474 | S6: =IFERROR(H6/I6-1,"") -> -0.029801325 | T6: =IFERROR(I6/J6-1,"") -> 0.023728814 | U6: =IFERROR(J6/K6-1,"") -> 0.036906854 | V6: =IFERROR(K6/L6-1,"") -> 0.032667877
A7: 4 | B7: Business Management, Marketing, and Administrative Services | C7: =Summary!F8 -> 7.11 | D7: 6.97 | F7: 6.58 | G7: 8.86 | H7: 6.69 | I7: 6.46 | J7: 6.07 | K7: 6.13 | L7: 6.22 | N7: =IFERROR(C7/D7-1,"") -> 0.020086083 | O7: =IFERROR(D7/E7-1,"") | P7: =IFERROR(E7/F7-1,"") -> -1 | Q7: =IFERROR(F7/G7-1,"") -> -0.25733634 | R7: =IFERROR(G7/H7-1,"") -> 0.32436472 | S7: =IFERROR(H7/I7-1,"") -> 0.035603715 | T7: =IFERROR(I7/J7-1,"") -> 0.064250412 | U7: =IFERROR(J7/K7-1,"") -> -0.0097879282 | V7: =IFERROR(K7/L7-1,"") -> -0.014469453
A8: 5 | B8: Career Pilot | C8: =Summary!F9 -> 33.87 | D8: 30.76 | F8: 23.45 | G8: 25.28 | H8: 13.77 | I8: 11.03 | J8: 16.04 | K8: 19.42 | L8: 18.69 | N8: =IFERROR(C8/D8-1,"") -> 0.10110533 | O8: =IFERROR(D8/E8-1,"") | P8: =IFERROR(E8/F8-1,"") -> -1 | Q8: =IFERROR(F8/G8-1,"") -> -0.072389241 | R8: =IFERROR(G8/H8-1,"") -> 0.83587509 | S8: =IFERROR(H8/I8-1,"") -> 0.24841342 | T8: =IFERROR(I8/J8-1,"") -> -0.31234414 | U8: =IFERROR(J8/K8-1,"") -> -0.17404737 | V8: =IFERROR(K8/L8-1,"") -> 0.03905832
A9: 6 | B9: Communications | C9: =Summary!F10 -> 7.65 | D9: 7.3 | F9: 7.3 | G9: 10.01 | H9: 7.21 | I9: 7.26 | J9: 6.99 | K9: 9.21 | L9: 8.21 | N9: =IFERROR(C9/D9-1,"") -> 0.047945205 | O9: =IFERROR(D9/E9-1,"") | P9: =IFERROR(E9/F9-1,"") -> -1 | Q9: =IFERROR(F9/G9-1,"") -> -0.27072927 | R9: =IFERROR(G9/H9-1,"") -> 0.38834951 | S9: =IFERROR(H9/I9-1,"") -> -0.0068870523 | T9: =IFERROR(I9/J9-1,"") -> 0.038626609 | U9: =IFERROR(J9/K9-1,"") -> -0.24104235 | V9: =IFERROR(K9/L9-1,"") -> 0.12180268
A10: 7 | B10: Computer and Information Sciences | C10: =Summary!F11 -> 8.52 | D10: 8.44 | F10: 7.57 | G10: 9.93 | H10: 6.94 | I10: 6.92 | J10: 6.69 | K10: 6.32 | L10: 5.44 | N10: =IFERROR(C10/D10-1,"") -> 0.009478673 | O10: =IFERROR(D10/E10-1,"") | P10: =IFERROR(E10/F10-1,"") -> -1 | Q10: =IFERROR(F10/G10-1,"") -> -0.23766365 | R10: =IFERROR(G10/H10-1,"") -> 0.43083573 | S10: =IFERROR(H10/I10-1,"") -> 0.0028901734 | T10: =IFERROR(I10/J10-1,"") -> 0.034379671 | U10: =IFERROR(J10/K10-1,"") -> 0.058544304 | V10: =IFERROR(K10/L10-1,"") -> 0.16176471
A11: 8 | B11: Construction Trades | C11: =Summary!F12 -> 8.03 | D11: 7.77 | F11: 8.2 | G11: 10.92 | H11: 7.36 | I11: 6.75 | J11: 6.12 | K11: 6.42 | L11: 5.99 | N11: =IFERROR(C11/D11-1,"") -> 0.033462033 | O11: =IFERROR(D11/E11-1,"") | P11: =IFERROR(E11/F11-1,"") -> -1 | Q11: =IFERROR(F11/G11-1,"") -> -0.24908425 | R11: =IFERROR(G11/H11-1,"") -> 0.48369565 | S11: =IFERROR(H11/I11-1,"") -> 0.09037037 | T11: =IFERROR(I11/J11-1,"") -> 0.10294118 | U11: =IFERROR(J11/K11-1,"") -> -0.046728972 | V11: =IFERROR(K11/L11-1,"") -> 0.071786311
A12: 9 | B12: Consumer and Homemaking Education | C12: =Summary!F13 -> 6.75 | D12: 6.49 | F12: 6.14 | G12: 8.08 | H12: 5.49 | I12: 5.51 | J12: 5.52 | K12: 5.14 | L12: 5.35 | N12: =IFERROR(C12/D12-1,"") -> 0.040061633 | O12: =IFERROR(D12/E12-1,"") | P12: =IFERROR(E12/F12-1,"") -> -1 | Q12: =IFERROR(F12/G12-1,"") -> -0.24009901 | R12: =IFERROR(G12/H12-1,"") -> 0.47176685 | S12: =IFERROR(H12/I12-1,"") -> -0.0036297641 | T12: =IFERROR(I12/J12-1,"") -> -0.0018115942 | U12: =IFERROR(J12/K12-1,"") -> 0.073929961 | V12: =IFERROR(K12/L12-1,"") -> -0.039252336
A13: 10 | B13: Engineering | C13: =Summary!F14 -> 7.86 | D13: 7.53 | F13: 10.3 | G13: 11.38 | H13: 8.92 | I13: 8.54 | J13: 11.49 | K13: 9.83 | L13: 7.64 | N13: =IFERROR(C13/D13-1,"") -> 0.043824701 | O13: =IFERROR(D13/E13-1,"") | P13: =IFERROR(E13/F13-1,"") -> -1 | Q13: =IFERROR(F13/G13-1,"") -> -0.094903339 | R13: =IFERROR(G13/H13-1,"") -> 0.27578475 | S13: =IFERROR(H13/I13-1,"") -> 0.044496487 | T13: =IFERROR(I13/J13-1,"") -> -0.256745 | U13: =IFERROR(J13/K13-1,"") -> 0.1688708 | V13: =IFERROR(K13/L13-1,"") -> 0.28664921
A14: 11 | B14: Engineering Related | C14: =Summary!F15 -> 7.41 | D14: 7.09 | F14: 6.82 | G14: 9.52 | H14: 7.23 | I14: 6.89 | J14: 6.58 | K14: 6.71 | L14: 6.42 | N14: =IFERROR(C14/D14-1,"") -> 0.045133992 | O14: =IFERROR(D14/E14-1,"") | P14: =IFERROR(E14/F14-1,"") -> -1 | Q14: =IFERROR(F14/G14-1,"") -> -0.28361345 | R14: =IFERROR(G14/H14-1,"") -> 0.31673582 | S14: =IFERROR(H14/I14-1,"") -> 0.04934688 | T14: =IFERROR(I14/J14-1,"") -> 0.047112462 | U14: =IFERROR(J14/K14-1,"") -> -0.019374069 | V14: =IFERROR(K14/L14-1,"") -> 0.04517134
A15: 12 | B15: English Language, Lit, Philosophy, Humanities, & Interdisciplinary | C15: =Summary!F16 -> 7.31 | D15: 7.08 | F15: 6.48 | G15: 8.33 | H15: 5.83 | I15: 5.94 | J15: 5.75 | K15: 5.68 | L15: 5.26 | N15: =IFERROR(C15/D15-1,"") -> 0.032485876 | O15: =IFERROR(D15/E15-1,"") | P15: =IFERROR(E15/F15-1,"") -> -1 | Q15: =IFERROR(F15/G15-1,"") -> -0.22208884 | R15: =IFERROR(G15/H15-1,"") -> 0.42881647 | S15: =IFERROR(H15/I15-1,"") -> -0.018518519 | T15: =IFERROR(I15/J15-1,"") -> 0.033043478 | U15: =IFERROR(J15/K15-1,"") -> 0.012323944 | V15: =IFERROR(K15/L15-1,"") -> 0.079847909
... A31: 29 | B31: Developmental Education - Reading/Writing | C31: =Summary!F32 -> 0 | D31: 0 | F31: 0 | G31: 0 | H31: 0 | I31: 0 | J31: 0 | K31: 0 | L31: 0 | N31: =IFERROR(C31/D31-1,"") | O31: =IFERROR(D31/E31-1,"") | P31: =IFERROR(E31/F31-1,"") | Q31: =IFERROR(F31/G31-1,"") | R31: =IFERROR(G31/H31-1,"") | S31: =IFERROR(H31/I31-1,"") | T31: =IFERROR(I31/J31-1,"") | U31: =IFERROR(J31/K31-1,"") | V31: =IFERROR(K31/L31-1,"")
B32: Average | C32: =AVERAGE(C4:C31) -> 8.67 | D32: =AVERAGE(D4:D31) -> 8.4635714 | F32: =AVERAGE(F4:F31) -> 7.7992857 | G32: =AVERAGE(G4:G31) -> 9.7525 | H32: =AVERAGE(H4:H31) -> 6.9428571 | I32: =AVERAGE(I4:I31) -> 7.0071429 | J32: =AVERAGE(J4:J31) -> 7.0107143 | K32: =AVERAGE(K4:K31) -> 7.0171429 | L32: =AVERAGE(L4:L31) -> 6.5617857 | N32: =IFERROR(C32/D32-1,"") -> 0.024390244 | O32: =IFERROR(D32/E32-1,"") | P32: =IFERROR(E32/F32-1,"") -> -1 | Q32: =IFERROR(F32/G32-1,"") -> -0.20027832 | R32: =IFERROR(G32/H32-1,"") -> 0.40468107 | S32: =IFERROR(H32/I32-1,"") -> -0.0091743119 | T32: =IFERROR(I32/J32-1,"") -> -0.00050942435 | U32: =IFERROR(J32/K32-1,"") -> -0.00091612378 | V32: =IFERROR(K32/L32-1,"") -> 0.069395308
B33: Median | C33: =MEDIAN(C4:C31) -> 7.78 | D33: =MEDIAN(D4:D31) -> 7.525 | F33: =MEDIAN(F4:F31) -> 7.345 | G33: =MEDIAN(G4:G31) -> 9.615 | H33: =MEDIAN(H4:H31) -> 6.995 | I33: =MEDIAN(I4:I31) -> 6.905 | J33: =MEDIAN(J4:J31) -> 6.69 | K33: =MEDIAN(K4:K31) -> 6.69 | L33: =MEDIAN(L4:L31) -> 6.32 | N33: =IFERROR(C33/D33-1,"") -> 0.033887043 | O33: =IFERROR(D33/E33-1,"") | P33: =IFERROR(E33/F33-1,"") -> -1 | Q33: =IFERROR(F33/G33-1,"") -> -0.23608944 | R33: =IFERROR(G33/H33-1,"") -> 0.37455325 | S33: =IFERROR(H33/I33-1,"") -> 0.013034033 | T33: =IFERROR(I33/J33-1,"") -> 0.032137519 | U33: =IFERROR(J33/K33-1,"") -> 0 | V33: =IFERROR(K33/L33-1,"") -> 0.058544304
B34: Standard Deviation | C34: =STDEV(C4:C31) -> 5.7536855 | D34: =STDEV(D4:D31) -> 5.2587227 | F34: =STDEV(F4:F31) -> 4.1137528 | G34: =STDEV(G4:G31) -> 4.4105653 | H34: =STDEV(H4:H31) -> 2.7509808 | I34: =STDEV(I4:I31) -> 2.6772026 | J34: =STDEV(J4:J31) -> 3.0868058 | K34: =STDEV(K4:K31) -> 3.4645516 | L34: =STDEV(L4:L31) -> 3.2525364 | N34: =IFERROR(C34/D34-1,"") -> 0.094122236 | O34: =IFERROR(D34/E34-1,"") | P34: =IFERROR(E34/F34-1,"") -> -1 | Q34: =IFERROR(F34/G34-1,"") -> -0.067295782 | R34: =IFERROR(G34/H34-1,"") -> 0.60327012 | S34: =IFERROR(H34/I34-1,"") -> 0.027557936 | T34: =IFERROR(I34/J34-1,"") -> -0.13269483 | U34: =IFERROR(J34/K34-1,"") -> -0.10903165 | V34: =IFERROR(K34/L34-1,"") -> 0.065184562

Sheet FTSE Summary
A1: =Summary!A1 -> Community and Technical Colleges, Report of Fundable Operating Expenses, Fiscal Year (FY) 2008
A2: Average Total Expenditure per Full-Time Student Equivalent (FTSE)
A3: Institution | B3: Annual State Funded Semester Credit Hours | C3: Total FTSE | D3: Total Expenditure | E3: Average Expenditure per FTSE
A4: Alamo | B4: 998865 | C4: =B4/30 -> 33295.5 | D4: ='1'!$E$33 -> 1.9123947e+08 | E4: =IFERROR(D4/C4,"") -> 5743.7032
A5: Alvin | B5: 92788 | C5: =B5/30 -> 3092.9333 | D5: ='2'!$E$33 -> 20109762 | E5: =IFERROR(D5/C5,"") -> 6501.8414
A6: Amarillo | B6: 178668 | C6: =B6/30 -> 5955.6 | D6: ='3'!$E$33 -> 34512276 | E6: =IFERROR(D6/C6,"") -> 5794.9285
A7: Angelina | B7: 94431 | C7: =B7/30 -> 3147.7 | D7: ='4'!$E$33 -> 13509317 | E7: =IFERROR(D7/C7,"") -> 4291.8058
A8: Austin | B8: 637122 | C8: =B8/30 -> 21237.4 | D8: ='5'!$E$33 -> 136750474 | E8: =IFERROR(D8/C8,"") -> 6439.1345
A9: Blinn | B9: 328749 | C9: =B9/30 -> 10958.3 | D9: ='6'!$E$33 -> 39123738 | E9: =IFERROR(D9/C9,"") -> 3570.2379
A10: Brazosport | B10: 66827 | C10: =B10/30 -> 2227.5667 | D10: ='7'!$E$33 -> 14287859 | E10: =IFERROR(D10/C10,"") -> 6414.1106
A11: Central Texas | B11: 261238 | C11: =B11/30 -> 8707.9333 | D11: ='8'!$E$33 -> 44599543 | E11: =IFERROR(D11/C11,"") -> 5121.7139
A12: Cisco | B12: 71870 | C12: =B12/30 -> 2395.6667 | D12: ='9'!$E$33 -> 9248686 | E12: =IFERROR(D12/C12,"") -> 3860.5897
A13: Clarendon | B13: 25155 | C13: =B13/30 -> 838.5 | D13: ='10'!$E$33 -> 3668635 | E13: =IFERROR(D13/C13,"") -> 4375.2355
A14: Coastal Bend | B14: 63382 | C14: =B14/30 -> 2112.7333 | D14: ='11'!$E$33 -> 0 | E14: =IFERROR(D14/C14,"") -> 0
A15: College Of The Mainland | B15: 71997 | C15: =B15/30 -> 2399.9 | D15: ='12'!$E$33 -> 24391320 | E15: =IFERROR(D15/C15,"") -> 10163.473
A16: Collin | B16: 412203 | C16: =B16/30 -> 13740.1 | D16: ='13'!$E$33 -> 70034922 | E16: =IFERROR(D16/C16,"") -> 5097.1188
A17: Dallas | B17: 1151165 | C17: =B17/30 -> 38372.167 | D17: ='14'!$E$33 -> 214562812 | E17: =IFERROR(D17/C17,"") -> 5591.6262
A18: Del Mar | B18: 204427 | C18: =B18/30 -> 6814.2333 | D18: ='15'!$E$33 -> 57594377 | E18: =IFERROR(D18/C18,"") -> 8452.07
A19: El Paso | B19: 471363 | C19: =B19/30 -> 15712.1 | D19: ='16'!$E$33 -> 81085589 | E19: =IFERROR(D19/C19,"") -> 5160.7098
A20: Frank Phillips | B20: 26276 | C20: =B20/30 -> 875.86667 | D20: ='17'!$E$33 -> 5764019 | E20: =IFERROR(D20/C20,"") -> 6580.932
A21: Galveston | B21: 40208 | C21: =B21/30 -> 1340.2667 | D21: ='18'!$E$33 -> 0 | E21: =IFERROR(D21/C21,"") -> 0
A22: Grayson | B22: 82457 | C22: =B22/30 -> 2748.5667 | D22: ='19'!$E$33 -> 13664320 | E22: =IFERROR(D22/C22,"") -> 4971.4348
A23: Hill | B23: 70448 | C23: =B23/30 -> 2348.2667 | D23: ='20'!$E$33 -> 10335070 | E23: =IFERROR(D23/C23,"") -> 4401.1484
A24: Houston | B24: 846337 | C24: =B24/30 -> 28211.233 | D24: ='21'!$E$33 -> 166950232 | E24: =IFERROR(D24/C24,"") -> 5917.8636
A25: Howard | B25: 61090 | C25: =B25/30 -> 2036.3333 | D25: ='22'!$E$33 -> 15565901 | E25: =IFERROR(D25/C25,"") -> 7644.083
A26: Kilgore | B26: 115663 | C26: =B26/30 -> 3855.4333 | D26: ='23'!$E$33 -> 18384957 | E26: =IFERROR(D26/C26,"") -> 4768.5838
A27: Laredo | B27: 154193 | C27: =B27/30 -> 5139.7667 | D27: ='24'!$E$33 -> 33753934 | E27: =IFERROR(D27/C27,"") -> 6567.2114
A28: Lee | B28: 125718 | C28: =B28/30 -> 4190.6 | D28: ='25'!$E$33 -> 29033951 | E28: =IFERROR(D28/C28,"") -> 6928.3518
A29: Lonestar | B29: 832324 | C29: =B29/30 -> 27744.133 | D29: ='26'!$E$33 -> 1.5254139e+08 | E29: =IFERROR(D29/C29,"") -> 5498.1494
A30: Mclennan | B30: 174178 | C30: =B30/30 -> 5805.9333 | D30: ='27'!$E$33 -> 29680633 | E30: =IFERROR(D30/C30,"") -> 5112.1209
A31: Midland | B31: 111509 | C31: =B31/30 -> 3716.9667 | D31: ='28'!$E$33 -> 26095442 | E31: =IFERROR(D31/C31,"") -> 7020.6285
A32: Navarro | B32: 165450 | C32: =B32/30 -> 5515 | D32: ='29'!$E$33 -> 19666734 | E32: =IFERROR(D32/C32,"") -> 3566.0442
A33: North Central Texas | B33: 145014 | C33: =B33/30 -> 4833.8 | D33: ='30'!$E$33 -> 16235310 | E33: =IFERROR(D33/C33,"") -> 3358.7054
A34: Northeast Texas | B34: 52949 | C34: =B34/30 -> 1764.9667 | D34: ='31'!$E$33 -> 8929016 | E34: =IFERROR(D34/C34,"") -> 5059.0281
A35: Odessa | B35: 85524 | C35: =B35/30 -> 2850.8 | D35: ='32'!$E$33 -> 19384637 | E35: =IFERROR(D35/C35,"") -> 6799.7183
A36: Panola | B36: 40729 | C36: =B36/30 -> 1357.6333 | D36: ='33'!$E$33 -> 8985085 | E36: =IFERROR(D36/C36,"") -> 6618.1971
A37: Paris | B37: 90017 | C37: =B37/30 -> 3000.5667 | D37: ='34'!$E$33 -> 12682934 | E37: =IFERROR(D37/C37,"") -> 4226.8463
A38: Ranger | B38: 18238 | C38: =B38/30 -> 607.93333 | D38: ='35'!$E$33 -> 2678849 | E38: =IFERROR(D38/C38,"") -> 4406.4848
A39: San Jacinto | B39: 476825 | C39: =B39/30 -> 15894.167 | D39: ='36'!$E$33 -> 91234511 | E39: =IFERROR(D39/C39,"") -> 5740.1255
A40: South Plains | B40: 192922 | C40: =B40/30 -> 6430.7333 | D40: ='37'!$E$33 -> 27138670 | E40: =IFERROR(D40/C40,"") -> 4220.1517
A41: South Texas | B41: 375255 | C41: =B41/30 -> 12508.5 | D41: ='38'!$E$33 -> 65267325 | E41: =IFERROR(D41/C41,"") -> 5217.8379
A42: Southwest Texas | B42: 93303 | C42: =B42/30 -> 3110.1 | D42: ='39'!$E$33 -> 15762315 | E42: =IFERROR(D42/C42,"") -> 5068.1055
A43: Tarrant | B43: 728201 | C43: =B43/30 -> 24273.367 | D43: ='40'!$E$33 -> 1.1340096e+08 | E43: =IFERROR(D43/C43,"") -> 4671.8265
A44: Temple | B44: 95894 | C44: =B44/30 -> 3196.4667 | D44: ='41'!$E$33 -> 16346843 | E44: =IFERROR(D44/C44,"") -> 5114.0352
A45: Texarkana | B45: 87473 | C45: =B45/30 -> 2915.7667 | D45: ='42'!$E$33 -> 14839812 | E45: =IFERROR(D45/C45,"") -> 5089.506
A46: Texas Southmost | B46: 189835 | C46: =B46/30 -> 6327.8333 | D46: ='43'!$E$33 -> 0 | E46: =IFERROR(D46/C46,"") -> 0
A47: Trinity Valley | B47: 131916 | C47: =B47/30 -> 4397.2 | D47: ='44'!$E$33 -> 17586898 | E47: =IFERROR(D47/C47,"") -> 3999.5675
A48: Tyler | B48: 205968 | C48: =B48/30 -> 6865.6 | D48: ='45'!$E$33 -> 35569462 | E48: =IFERROR(D48/C48,"") -> 5180.8235
A49: Vernon | B49: 57233 | C49: =B49/30 -> 1907.7667 | D49: ='46'!$E$33 -> 0 | E49: =IFERROR(D49/C49,"") -> 0
A50: Victoria | B50: 74015 | C50: =B50/30 -> 2467.1667 | D50: ='47'!$E$33 -> 15386480 | E50: =IFERROR(D50/C50,"") -> 6236.498
A51: Weatherford | B51: 91593 | C51: =B51/30 -> 3053.1 | D51: ='48'!$E$33 -> 18011246 | E51: =IFERROR(D51/C51,"") -> 5899.3305
A52: Western Texas | B52: 41029 | C52: =B52/30 -> 1367.6333 | D52: ='49'!$E$33 -> 6397575 | E52: =IFERROR(D52/C52,"") -> 4677.8437
A53: Wharton | B53: 120743 | C53: =B53/30 -> 4024.7667 | D53: ='50'!$E$33 -> 20748577 | E53: =IFERROR(D53/C53,"") -> 5155.2248
A54: TSTC-Harlingen | B54: 110187 | C54: =B54/30 -> 3672.9 | D54: ='51'!$E$33 -> 21311585 | E54: =IFERROR(D54/C54,"") -> 5802.3864
A55: TSTC-West Texas | B55: 39449 | C55: =B55/30 -> 1314.9667 | D55: ='52'!$E$33 -> 13720657 | E55: =IFERROR(D55/C55,"") -> 10434.224
A56: TSTC-Marshall | B56: 16611 | C56: =B56/30 -> 553.7 | D56: ='53'!$E$33 -> 4865946 | E56: =IFERROR(D56/C56,"") -> 8788.0549
A57: TSTC-Waco | B57: 122169 | C57: =B57/30 -> 4072.3 | D57: ='54'!$E$33 -> 32537666 | E57: =IFERROR(D57/C57,"") -> 7989.9973
A58: Lamar-IOT | B58: 57077 | C58: =B58/30 -> 1902.5667 | D58: ='55'!$E$33 -> 19200729 | E58: =IFERROR(D58/C58,"") -> 10092.014
A59: Lamar-Orange | B59: 42154 | C59: =B59/30 -> 1405.1333 | D59: ='56'!$E$33 -> 0 | E59: =IFERROR(D59/C59,"") -> 0
A60: Lamar-Port Arthur | B60: 44993 | C60: =B60/30 -> 1499.7667 | D60: ='57'!$E$33 -> 16624188 | E60: =IFERROR(D60/C60,"") -> 11084.516
A61: Total for Instutions Reporting Expense | B61: =SUMIF(D4:D60,">0",B4:B60) -> 11370605 | C61: =B61/30 -> 379020.17 | D61: =SUM(D4:D60) -> 2111002638 | E61: =IFERROR(D61/C61,"") -> 5569.6314

Sheet Discipline Summary
A1: =Summary!A1 -> Community and Technical Colleges, Report of Fundable Operating Expenses, Fiscal Year (FY) 2008
A2: Discipline Summary of Expense per Contact Hour by Institution
A3: Institution | B3: AG | C3: ARCH | D3: SCI | E3: BA | F3: CP | G3: COMM | H3: CS | I3: CNSTR | J3: HE | K3: ENG | L3: ENGR | M3: LA | N3: FL | O3: HODA | P3: HODH | Q3: HOO | R3: HORT | S3: NUR | T3: MATH | U3: AUTO | V3: MECH | W3: ELECT | X3: PE | Y3: PA | Z3: SS | AA3: FA | AB3: DEM | AC3: DER | AD3: Total
A4: Alamo | B4: ='1'!$F$5 -> 6.93 | C4: ='1'!$F$6 -> 12.48 | D4: ='1'!$F$7 -> 9.03 | E4: ='1'!$F$8 -> 9.83 | F4: ='1'!$F$9 -> 36.07 | G4: ='1'!$F$10 -> 10.5 | H4: ='1'!$F$11 -> 10.79 | I4: ='1'!$F$12 -> 11.76 | J4: ='1'!$F$13 -> 8.76 | K4: ='1'!$F$14 -> 15.24 | L4: ='1'!$F$15 -> 13.35 | M4: ='1'!$F$16 -> 9.3 | N4: ='1'!$F$17 -> 7.7 | O4: ='1'!$F$18 -> 15.39 | P4: ='1'!$F$19 | Q4: ='1'!$F$20 -> 9.88 | R4: ='1'!$F$21 -> 15.1 | S4: ='1'!$F$22 -> 10.47 | T4: ='1'!$F$23 -> 8.65 | U4: ='1'!$F$24 -> 10.37 | V4: ='1'!$F$25 -> 12.62 | W4: ='1'!$F$26 -> 4.95 | X4: ='1'!$F$27 -> 9.82 | Y4: ='1'!$F$28 -> 9 | Z4: ='1'!$F$29 -> 8.28 | AA4: ='1'!$F$30 -> 10.18 | AB4: ='1'!$F$31 | AC4: ='1'!$F$32 | AD4: ='1'!$F$33 -> 9.43
A5: Alvin | B5: ='2'!$F$5 -> 5.33 | C5: ='2'!$F$6 -> 9.53 | D5: ='2'!$F$7 -> 6.06 | E5: ='2'!$F$8 -> 9.56 | F5: ='2'!$F$9 | G5: ='2'!$F$10 -> 8.89 | H5: ='2'!$F$11 -> 10.72 | I5: ='2'!$F$12 -> 14.76 | J5: ='2'!$F$13 -> 7.83 | K5: ='2'!$F$14 | L5: ='2'!$F$15 -> 7.58 | M5: ='2'!$F$16 -> 7.7 | N5: ='2'!$F$17 -> 8.7 | O5: ='2'!$F$18 -> 10.72 | P5: ='2'!$F$19 | Q5: ='2'!$F$20 -> 10.54 | R5: ='2'!$F$21 -> 12.37 | S5: ='2'!$F$22 -> 10.06 | T5: ='2'!$F$23 -> 7.24 | U5: ='2'!$F$24 -> 7.61 | V5: ='2'!$F$25 -> 17.98 | W5: ='2'!$F$26 -> 12.56 | X5: ='2'!$F$27 -> 10.16 | Y5: ='2'!$F$28 -> 7.6 | Z5: ='2'!$F$29 -> 7.48 | AA5: ='2'!$F$30 -> 12.81 | AB5: ='2'!$F$31 | AC5: ='2'!$F$32 | AD5: ='2'!$F$33 -> 8.68
A6: Amarillo | B6: ='3'!$F$5 -> 7.44 | C6: ='3'!$F$6 -> 7.96 | D6: ='3'!$F$7 -> 7.13 | E6: ='3'!$F$8 -> 7.78 | F6: ='3'!$F$9 | G6: ='3'!$F$10 -> 7.74 | H6: ='3'!$F$11 -> 7.74 | I6: ='3'!$F$12 -> 8.27 | J6: ='3'!$F$13 -> 6.74 | K6: ='3'!$F$14 -> 7.12 | L6: ='3'!$F$15 -> 7.74 | M6: ='3'!$F$16 -> 8.34 | N6: ='3'!$F$17 -> 7.5 | O6: ='3'!$F$18 -> 8.32 | P6: ='3'!$F$19 -> 8.06 | Q6: ='3'!$F$20 -> 7.93 | R6: ='3'!$F$21 -> 8.16 | S6: ='3'!$F$22 -> 8.47 | T6: ='3'!$F$23 -> 7.29 | U6: ='3'!$F$24 -> 7.96 | V6: ='3'!$F$25 -> 7.96 | W6: ='3'!$F$26 -> 7.58 | X6: ='3'!$F$27 -> 5.6 | Y6: ='3'!$F$28 -> 7.42 | Z6: ='3'!$F$29 -> 5.79 | AA6: ='3'!$F$30 -> 7.48 | AB6: ='3'!$F$31 | AC6: ='3'!$F$32 | AD6: ='3'!$F$33 -> 7.45
A7: Angelina | B7: ='4'!$F$5 | C7: ='4'!$F$6 -> 8.46 | D7: ='4'!$F$7 -> 5.39 | E7: ='4'!$F$8 -> 5.65 | F7: ='4'!$F$9 | G7: ='4'!$F$10 -> 12.59 | H7: ='4'!$F$11 -> 10.21 | I7: ='4'!$F$12 -> 5.61 | J7: ='4'!$F$13 -> 6.66 | K7: ='4'!$F$14 -> 12.31 | L7: ='4'!$F$15 -> 5.61 | M7: ='4'!$F$16 -> 5.37 | N7: ='4'!$F$17 -> 5.46 | O7: ='4'!$F$18 -> 9.58 | P7: ='4'!$F$19 | Q7: ='4'!$F$20 -> 5.85 | R7: ='4'!$F$21 -> 7.98 | S7: ='4'!$F$22 -> 6.24 | T7: ='4'!$F$23 -> 6.83 | U7: ='4'!$F$24 -> 9.2 | V7: ='4'!$F$25 -> 7.98 | W7: ='4'!$F$26 -> 5.66 | X7: ='4'!$F$27 -> 6.39 | Y7: ='4'!$F$28 -> 5.93 | Z7: ='4'!$F$29 -> 5.28 | AA7: ='4'!$F$30 -> 7.49 | AB7: ='4'!$F$31 | AC7: ='4'!$F$32 | AD7: ='4'!$F$33 -> 6.3
A8: Austin | B8: ='5'!$F$5 -> 6.53 | C8: ='5'!$F$6 -> 15.75 | D8: ='5'!$F$7 -> 10.89 | E8: ='5'!$F$8 -> 9.69 | F8: ='5'!$F$9 | G8: ='5'!$F$10 -> 9.36 | H8: ='5'!$F$11 -> 16.63 | I8: ='5'!$F$12 -> 5.84 | J8: ='5'!$F$13 -> 14.69 | K8: ='5'!$F$14 -> 16.99 | L8: ='5'!$F$15 -> 12.33 | M8: ='5'!$F$16 -> 9.87 | N8: ='5'!$F$17 -> 9.5 | O8: ='5'!$F$18 -> 15.12 | P8: ='5'!$F$19 -> 32.54 | Q8: ='5'!$F$20 -> 15.01 | R8: ='5'!$F$21 | S8: ='5'!$F$22 -> 16.87 | T8: ='5'!$F$23 -> 8.99 | U8: ='5'!$F$24 -> 14.52 | V8: ='5'!$F$25 -> 12.64 | W8: ='5'!$F$26 -> 4.93 | X8: ='5'!$F$27 -> 9.84 | Y8: ='5'!$F$28 -> 9.1 | Z8: ='5'!$F$29 -> 8.47 | AA8: ='5'!$F$30 -> 14.03 | AB8: ='5'!$F$31 | AC8: ='5'!$F$32 | AD8: ='5'!$F$33 -> 10.6
A9: Blinn | B9: ='6'!$F$5 -> 6.53 | C9: ='6'!$F$6 -> 12.83 | D9: ='6'!$F$7 -> 4.78 | E9: ='6'!$F$8 -> 7.02 | F9: ='6'!$F$9 | G9: ='6'!$F$10 -> 4.45 | H9: ='6'!$F$11 -> 16.77 | I9: ='6'!$F$12 -> 12.83 | J9: ='6'!$F$13 -> 3.87 | K9: ='6'!$F$14 | L9: ='6'!$F$15 -> 9.04 | M9: ='6'!$F$16 -> 6.49 | N9: ='6'!$F$17 -> 6.12 | O9: ='6'!$F$18 -> 13.47 | P9: ='6'!$F$19 -> 21.61 | Q9: ='6'!$F$20 -> 6.87 | R9: ='6'!$F$21 | S9: ='6'!$F$22 -> 7.27 | T9: ='6'!$F$23 -> 5.71 | U9: ='6'!$F$24 -> 12.83 | V9: ='6'!$F$25 -> 12.83 | W9: ='6'!$F$26 -> 12.83 | X9: ='6'!$F$27 -> 6.76 | Y9: ='6'!$F$28 -> 5.07 | Z9: ='6'!$F$29 -> 4.8 | AA9: ='6'!$F$30 -> 6.51 | AB9: ='6'!$F$31 | AC9: ='6'!$F$32 | AD9: ='6'!$F$33 -> 6.04
A10: Brazosport | B10: ='7'!$F$5 | C10: ='7'!$F$6 -> 9.46 | D10: ='7'!$F$7 -> 9.57 | E10: ='7'!$F$8 -> 10.16 | F10: ='7'!$F$9 | G10: ='7'!$F$10 -> 5.14 | H10: ='7'!$F$11 -> 15.6 | I10: ='7'!$F$12 -> 8.81 | J10: ='7'!$F$13 -> 8.41 | K10: ='7'!$F$14 | L10: ='7'!$F$15 -> 6.72 | M10: ='7'!$F$16 -> 9.24 | N10: ='7'!$F$17 -> 9.21 | O10: ='7'!$F$18 -> 37.39 | P10: ='7'!$F$19 | Q10: ='7'!$F$20 -> 15.62 | R10: ='7'!$F$21 | S10: ='7'!$F$22 -> 13.83 | T10: ='7'!$F$23 -> 8.66 | U10: ='7'!$F$24 -> 9.22 | V10: ='7'!$F$25 | W10: ='7'!$F$26 -> 13.48 | X10: ='7'!$F$27 -> 10.68 | Y10: ='7'!$F$28 -> 8.3 | Z10: ='7'!$F$29 -> 8.33 | AA10: ='7'!$F$30 -> 14.11 | AB10: ='7'!$F$31 | AC10: ='7'!$F$32 | AD10: ='7'!$F$33 -> 9.54
A11: Central Texas | B11: ='8'!$F$5 -> 5.2 | C11: ='8'!$F$6 -> 12.49 | D11: ='8'!$F$7 -> 7.2 | E11: ='8'!$F$8 -> 6.79 | F11: ='8'!$F$9 -> 56.23 | G11: ='8'!$F$10 -> 7.41 | H11: ='8'!$F$11 -> 14.68 | I11: ='8'!$F$12 -> 8.98 | J11: ='8'!$F$13 -> 5.46 | K11: ='8'!$F$14 -> 2.98 | L11: ='8'!$F$15 -> 3.46 | M11: ='8'!$F$16 -> 6.71 | N11: ='8'!$F$17 -> 7.37 | O11: ='8'!$F$18 -> 11.72 | P11: ='8'!$F$19 | Q11: ='8'!$F$20 -> 9.54 | R11: ='8'!$F$21 | S11: ='8'!$F$22 -> 9.11 | T11: ='8'!$F$23 -> 5.88 | U11: ='8'!$F$24 -> 9.71 | V11: ='8'!$F$25 -> 6.87 | W11: ='8'!$F$26 -> 17.9 | X11: ='8'!$F$27 -> 7.67 | Y11: ='8'!$F$28 -> 8.2 | Z11: ='8'!$F$29 -> 5.79 | AA11: ='8'!$F$30 -> 6.62 | AB11: ='8'!$F$31 | AC11: ='8'!$F$32 | AD11: ='8'!$F$33 -> 7.74
A12: Cisco | B12: ='9'!$F$5 -> 9.89 | C12: ='9'!$F$6 -> 6.05 | D12: ='9'!$F$7 -> 4.79 | E12: ='9'!$F$8 -> 4.83 | F12: ='9'!$F$9 | G12: ='9'!$F$10 | H12: ='9'!$F$11 -> 17.6 | I12: ='9'!$F$12 -> 5.98 | J12: ='9'!$F$13 -> 5.3 | K12: ='9'!$F$14 | L12: ='9'!$F$15 -> 6.21 | M12: ='9'!$F$16 -> 5.81 | N12: ='9'!$F$17 -> 5.2 | O12: ='9'!$F$18 -> 6.53 | P12: ='9'!$F$19 | Q12: ='9'!$F$20 -> 4.41 | R12: ='9'!$F$21 -> 18.94 | S12: ='9'!$F$22 -> 7.26 | T12: ='9'!$F$23 -> 5.95 | U12: ='9'!$F$24 -> 7.77 | V12: ='9'!$F$25 | W12: ='9'!$F$26 | X12: ='9'!$F$27 -> 10.28 | Y12: ='9'!$F$28 -> 8.72 | Z12: ='9'!$F$29 -> 5.56 | AA12: ='9'!$F$30 -> 7.44 | AB12: ='9'!$F$31 | AC12: ='9'!$F$32 | AD12: ='9'!$F$33 -> 6.14
A13: Clarendon | B13: ='10'!$F$5 -> 10.25 | C13: ='10'!$F$6 | D13: ='10'!$F$7 -> 6.04 | E13: ='10'!$F$8 -> 5.84 | F13: ='10'!$F$9 | G13: ='10'!$F$10 | H13: ='10'!$F$11 -> 10.19 | I13: ='10'!$F$12 | J13: ='10'!$F$13 -> 3.96 | K13: ='10'!$F$14 | L13: ='10'!$F$15 -> 5.05 | M13: ='10'!$F$16 -> 6.08 | N13: ='10'!$F$17 -> 7.15 | O13: ='10'!$F$18 | P13: ='10'!$F$19 | Q13: ='10'!$F$20 -> 3.48 | R13: ='10'!$F$21 | S13: ='10'!$F$22 -> 6.96 | T13: ='10'!$F$23 -> 5.79 | U13: ='10'!$F$24 | V13: ='10'!$F$25 | W13: ='10'!$F$26 -> 4.09 | X13: ='10'!$F$27 -> 9.35 | Y13: ='10'!$F$28 -> 3.15 | Z13: ='10'!$F$29 -> 5.73 | AA13: ='10'!$F$30 -> 6.03 | AB13: ='10'!$F$31 | AC13: ='10'!$F$32 | AD13: ='10'!$F$33 -> 6.62
A14: Coastal Bend | B14: ='11'!$F$5 | C14: ='11'!$F$6 | D14: ='11'!$F$7 | E14: ='11'!$F$8 | F14: ='11'!$F$9 | G14: ='11'!$F$10 | H14: ='11'!$F$11 | I14: ='11'!$F$12 | J14: ='11'!$F$13 | K14: ='11'!$F$14 | L14: ='11'!$F$15 | M14: ='11'!$F$16 | N14: ='11'!$F$17 | O14: ='11'!$F$18 | P14: ='11'!$F$19 | Q14: ='11'!$F$20 | R14: ='11'!$F$21 | S14: ='11'!$F$22 | T14: ='11'!$F$23 | U14: ='11'!$F$24 | V14: ='11'!$F$25 | W14: ='11'!$F$26 | X14: ='11'!$F$27 | Y14: ='11'!$F$28 | Z14: ='11'!$F$29 | AA14: ='11'!$F$30 | AB14: ='11'!$F$31 | AC14: ='11'!$F$32 | AD14: ='11'!$F$33
A15: College Of The Mainland | B15: ='12'!$F$5 -> 7.62 | C15: ='12'!$F$6 -> 27.1 | D15: ='12'!$F$7 -> 10.85 | E15: ='12'!$F$8 -> 12.8 | F15: ='12'!$F$9 | G15: ='12'!$F$10 -> 7.62 | H15: ='12'!$F$11 -> 21.16 | I15: ='12'!$F$12 -> 9.61 | J15: ='12'!$F$13 -> 20.2 | K15: ='12'!$F$14 | L15: ='12'!$F$15 -> 8.25 | M15: ='12'!$F$16 -> 11.92 | N15: ='12'!$F$17 -> 11.97 | O15: ='12'!$F$18 -> 20.29 | P15: ='12'!$F$19 | Q15: ='12'!$F$20 -> 12.61 | R15: ='12'!$F$21 | S15: ='12'!$F$22 -> 17.8 | T15: ='12'!$F$23 -> 11.29 | U15: ='12'!$F$24 | V15: ='12'!$F$25 | W15: ='12'!$F$26 -> 9.64 | X15: ='12'!$F$27 -> 12.89 | Y15: ='12'!$F$28 -> 15.59 | Z15: ='12'!$F$29 -> 13.2 | AA15: ='12'!$F$30 -> 17.18 | AB15: ='12'!$F$31 | AC15: ='12'!$F$32 | AD15: ='12'!$F$33 -> 13.81
A16: Collin | B16: ='13'!$F$5 -> 6.59 | C16: ='13'!$F$6 -> 9.96 | D16: ='13'!$F$7 -> 7.46 | E16: ='13'!$F$8 -> 7.92 | F16: ='13'!$F$9 -> 3.54 | G16: ='13'!$F$10 -> 9.47 | H16: ='13'!$F$11 -> 7.26 | I16: ='13'!$F$12 -> 10.01 | J16: ='13'!$F$13 -> 7.41 | K16: ='13'!$F$14 -> 14.08 | L16: ='13'!$F$15 -> 16.19 | M16: ='13'!$F$16 -> 7.45 | N16: ='13'!$F$17 -> 6.66 | O16: ='13'!$F$18 -> 16.05 | P16: ='13'!$F$19 -> 29.51 | Q16: ='13'!$F$20 -> 10.55 | R16: ='13'!$F$21 -> 12.88 | S16: ='13'!$F$22 | T16: ='13'!$F$23 -> 6.92 | U16: ='13'!$F$24 | V16: ='13'!$F$25 | W16: ='13'!$F$26 -> 4.88 | X16: ='13'!$F$27 -> 8.5 | Y16: ='13'!$F$28 -> 11.22 | Z16: ='13'!$F$29 -> 6.57 | AA16: ='13'!$F$30 -> 10.28 | AB16: ='13'!$F$31 | AC16: ='13'!$F$32 | AD16: ='13'!$F$33 -> 7.91
A17: Dallas | B17: ='14'!$F$5 -> 15.27 | C17: ='14'!$F$6 -> 11.16 | D17: ='14'!$F$7 -> 7.91 | E17: ='14'!$F$8 -> 8.28 | F17: ='14'!$F$9 -> 13.04 | G17: ='14'!$F$10 -> 7.96 | H17: ='14'!$F$11 -> 8.24 | I17: ='14'!$F$12 -> 11.99 | J17: ='14'!$F$13 -> 7.29 | K17: ='14'!$F$14 -> 10.11 | L17: ='14'!$F$15 -> 6.03 | M17: ='14'!$F$16 -> 8.34 | N17: ='14'!$F$17 -> 7.18 | O17: ='14'!$F$18 -> 12.27 | P17: ='14'!$F$19 | Q17: ='14'!$F$20 -> 7.89 | R17: ='14'!$F$21 -> 17.52 | S17: ='14'!$F$22 -> 12.73 | T17: ='14'!$F$23 -> 7.33 | U17: ='14'!$F$24 -> 9.5 | V17: ='14'!$F$25 -> 6.08 | W17: ='14'!$F$26 -> 12.78 | X17: ='14'!$F$27 -> 9.12 | Y17: ='14'!$F$28 -> 6.66 | Z17: ='14'!$F$29 -> 6.94 | AA17: ='14'!$F$30 -> 9.09 | AB17: ='14'!$F$31 | AC17: ='14'!$F$32 | AD17: ='14'!$F$33 -> 8
A18: Del Mar | B18: ='15'!$F$5 -> 9.51 | C18: ='15'!$F$6 -> 11.75 | D18: ='15'!$F$7 -> 9.64 | E18: ='15'!$F$8 -> 11.73 | F18: ='15'!$F$9 | G18: ='15'!$F$10 -> 12.93 | H18: ='15'!$F$11 -> 10.65 | I18: ='15'!$F$12 -> 8.82 | J18: ='15'!$F$13 -> 11.11 | K18: ='15'!$F$14 -> 12.43 | L18: ='15'!$F$15 -> 11.48 | M18: ='15'!$F$16 -> 12.02 | N18: ='15'!$F$17 -> 10.84 | O18: ='15'!$F$18 -> 15 | P18: ='15'!$F$19 -> 21.76 | Q18: ='15'!$F$20 -> 11.06 | R18: ='15'!$F$21 -> 24.55 | S18: ='15'!$F$22 -> 13.81 | T18: ='15'!$F$23 -> 11.74 | U18: ='15'!$F$24 -> 11.75 | V18: ='15'!$F$25 -> 11.52 | W18: ='15'!$F$26 -> 14.26 | X18: ='15'!$F$27 -> 10.21 | Y18: ='15'!$F$28 -> 12.18 | Z18: ='15'!$F$29 -> 9.73 | AA18: ='15'!$F$30 -> 14.28 | AB18: ='15'!$F$31 | AC18: ='15'!$F$32 | AD18: ='15'!$F$33 -> 11.64
A19: El Paso | B19: ='16'!$F$5 -> 8.63 | C19: ='16'!$F$6 -> 18.43 | D19: ='16'!$F$7 -> 7.34 | E19: ='16'!$F$8 -> 8.7 | F19: ='16'!$F$9 | G19: ='16'!$F$10 -> 8.01 | H19: ='16'!$F$11 -> 10.75 | I19: ='16'!$F$12 -> 5.55 | J19: ='16'!$F$13 -> 5.92 | K19: ='16'!$F$14 -> 7.67 | L19: ='16'!$F$15 -> 5.48 | M19: ='16'!$F$16 -> 9.77 | N19: ='16'!$F$17 -> 6.63 | O19: ='16'!$F$18 -> 14.41 | P19: ='16'!$F$19 -> 15.19 | Q19: ='16'!$F$20 -> 12.84 | R19: ='16'!$F$21 -> 16.07 | S19: ='16'!$F$22 -> 7 | T19: ='16'!$F$23 -> 7.08 | U19: ='16'!$F$24 -> 9.7 | V19: ='16'!$F$25 -> 15.44 | W19: ='16'!$F$26 -> 4.46 | X19: ='16'!$F$27 -> 23.39 | Y19: ='16'!$F$28 -> 9.06 | Z19: ='16'!$F$29 -> 6.69 | AA19: ='16'!$F$30 -> 7.76 | AB19: ='16'!$F$31 | AC19: ='16'!$F$32 | AD19: ='16'!$F$33 -> 8.42
A20: Frank Phillips | B20: ='17'!$F$5 -> 9.77 | C20: ='17'!$F$6 -> 9.3 | D20: ='17'!$F$7 -> 7.12 | E20: ='17'!$F$8 -> 7.09 | F20: ='17'!$F$9 | G20: ='17'!$F$10 -> 3.6 | H20: ='17'!$F$11 -> 15.08 | I20: ='17'!$F$12 -> 13.47 | J20: ='17'!$F$13 -> 7.63 | K20: ='17'!$F$14 -> 67.81 | L20: ='17'!$F$15 -> 9.76 | M20: ='17'!$F$16 -> 7.12 | N20: ='17'!$F$17 -> 5.3 | O20: ='17'!$F$18 -> 6.96 | P20: ='17'!$F$19 | Q20: ='17'!$F$20 -> 6.96 | R20: ='17'!$F$21 | S20: ='17'!$F$22 -> 7.31 | T20: ='17'!$F$23 -> 7.19 | U20: ='17'!$F$24 | V20: ='17'!$F$25 -> 5.39 | W20: ='17'!$F$26 -> 5.85 | X20: ='17'!$F$27 -> 7.24 | Y20: ='17'!$F$28 -> 5.52 | Z20: ='17'!$F$29 -> 6.92 | AA20: ='17'!$F$30 -> 8.83 | AB20: ='17'!$F$31 | AC20: ='17'!$F$32 | AD20: ='17'!$F$33 -> 8.28
A21: Galveston | B21: ='18'!$F$5 | C21: ='18'!$F$6 | D21: ='18'!$F$7 | E21: ='18'!$F$8 | F21: ='18'!$F$9 | G21: ='18'!$F$10 | H21: ='18'!$F$11 | I21: ='18'!$F$12 | J21: ='18'!$F$13 | K21: ='18'!$F$14 | L21: ='18'!$F$15 | M21: ='18'!$F$16 | N21: ='18'!$F$17 | O21: ='18'!$F$18 | P21: ='18'!$F$19 | Q21: ='18'!$F$20 | R21: ='18'!$F$21 | S21: ='18'!$F$22 | T21: ='18'!$F$23 | U21: ='18'!$F$24 | V21: ='18'!$F$25 | W21: ='18'!$F$26 | X21: ='18'!$F$27 | Y21: ='18'!$F$28 | Z21: ='18'!$F$29 | AA21: ='18'!$F$30 | AB21: ='18'!$F$31 | AC21: ='18'!$F$32 | AD21: ='18'!$F$33
A22: Grayson | B22: ='19'!$F$5 -> 8.93 | C22: ='19'!$F$6 -> 11.85 | D22: ='19'!$F$7 -> 6.31 | E22: ='19'!$F$8 -> 7.54 | F22: ='19'!$F$9 | G22: ='19'!$F$10 -> 3.06 | H22: ='19'!$F$11 -> 8.28 | I22: ='19'!$F$12 -> 3.06 | J22: ='19'!$F$13 -> 5.26 | K22: ='19'!$F$14 -> 3.06 | L22: ='19'!$F$15 -> 6.01 | M22: ='19'!$F$16 -> 6.08 | N22: ='19'!$F$17 -> 6.22 | O22: ='19'!$F$18 -> 9.89 | P22: ='19'!$F$19 | Q22: ='19'!$F$20 -> 6.76 | R22: ='19'!$F$21 | S22: ='19'!$F$22 -> 8.39 | T22: ='19'!$F$23 -> 5.82 | U22: ='19'!$F$24 -> 7.37 | V22: ='19'!$F$25 -> 3.06 | W22: ='19'!$F$26 -> 18.29 | X22: ='19'!$F$27 -> 18.88 | Y22: ='19'!$F$28 -> 6.93 | Z22: ='19'!$F$29 -> 5.8 | AA22: ='19'!$F$30 -> 7.86 | AB22: ='19'!$F$31 | AC22: ='19'!$F$32 | AD22: ='19'!$F$33 -> 7.02
A23: Hill | B23: ='20'!$F$5 -> 12.33 | C23: ='20'!$F$6 -> 6.45 | D23: ='20'!$F$7 -> 5.34 | E23: ='20'!$F$8 -> 4.13 | F23: ='20'!$F$9 | G23: ='20'!$F$10 -> 8.12 | H23: ='20'!$F$11 -> 6.52 | I23: ='20'!$F$12 -> 8.16 | J23: ='20'!$F$13 -> 5.21 | K23: ='20'!$F$14 | L23: ='20'!$F$15 -> 4.63 | M23: ='20'!$F$16 -> 4.87 | N23: ='20'!$F$17 -> 4.65 | O23: ='20'!$F$18 -> 6.49 | P23: ='20'!$F$19 | Q23: ='20'!$F$20 -> 4.23 | R23: ='20'!$F$21 | S23: ='20'!$F$22 -> 9.69 | T23: ='20'!$F$23 -> 5.19 | U23: ='20'!$F$24 -> 4.72 | V23: ='20'!$F$25 -> 8.12 | W23: ='20'!$F$26 -> 8.12 | X23: ='20'!$F$27 -> 9.5 | Y23: ='20'!$F$28 -> 6.84 | Z23: ='20'!$F$29 -> 5.22 | AA23: ='20'!$F$30 -> 6.32 | AB23: ='20'!$F$31 | AC23: ='20'!$F$32 | AD23: ='20'!$F$33 -> 5.78
A24: Houston | B24: ='21'!$F$5 -> 8.36 | C24: ='21'!$F$6 -> 8.58 | D24: ='21'!$F$7 -> 7.74 | E24: ='21'!$F$8 -> 8.08 | F24: ='21'!$F$9 | G24: ='21'!$F$10 -> 7.31 | H24: ='21'!$F$11 -> 19.81 | I24: ='21'!$F$12 -> 9.44 | J24: ='21'!$F$13 -> 7.87 | K24: ='21'!$F$14 -> 9.2 | L24: ='21'!$F$15 -> 9.11 | M24: ='21'!$F$16 -> 8.74 | N24: ='21'!$F$17 -> 8.26 | O24: ='21'!$F$18 -> 10.69 | P24: ='21'!$F$19 | Q24: ='21'!$F$20 -> 11.58 | R24: ='21'!$F$21 -> 14.44 | S24: ='21'!$F$22 -> 13.33 | T24: ='21'!$F$23 -> 7.72 | U24: ='21'!$F$24 -> 10.25 | V24: ='21'!$F$25 -> 15.16 | W24: ='21'!$F$26 -> 8.8 | X24: ='21'!$F$27 -> 11.47 | Y24: ='21'!$F$28 -> 9.81 | Z24: ='21'!$F$29 -> 7.48 | AA24: ='21'!$F$30 -> 9.47 | AB24: ='21'!$F$31 | AC24: ='21'!$F$32 | AD24: ='21'!$F$33 -> 8.64
A25: Howard | B25: ='22'!$F$5 -> 5.98 | C25: ='22'!$F$6 -> 6.79 | D25: ='22'!$F$7 -> 6.26 | E25: ='22'!$F$8 -> 4.45 | F25: ='22'!$F$9 | G25: ='22'!$F$10 -> 4.49 | H25: ='22'!$F$11 -> 6.47 | I25: ='22'!$F$12 -> 7.99 | J25: ='22'!$F$13 -> 4.41 | K25: ='22'!$F$14 | L25: ='22'!$F$15 -> 7.52 | M25: ='22'!$F$16 -> 10.16 | N25: ='22'!$F$17 -> 7.34 | O25: ='22'!$F$18 -> 14.13 | P25: ='22'!$F$19 -> 16.56 | Q25: ='22'!$F$20 -> 7.58 | R25: ='22'!$F$21 -> 12.82 | S25: ='22'!$F$22 -> 8.12 | T25: ='22'!$F$23 -> 5.34 | U25: ='22'!$F$24 -> 48.31 | V25: ='22'!$F$25 -> 7.69 | W25: ='22'!$F$26 -> 7.26 | X25: ='22'!$F$27 -> 19.12 | Y25: ='22'!$F$28 -> 6.29 | Z25: ='22'!$F$29 -> 5.66 | AA25: ='22'!$F$30 -> 7.27 | AB25: ='22'!$F$31 | AC25: ='22'!$F$32 | AD25: ='22'!$F$33 -> 6.8
A26: Kilgore | B26: ='23'!$F$5 -> 10.64 | C26: ='23'!$F$6 -> 7.96 | D26: ='23'!$F$7 -> 6.05 | E26: ='23'!$F$8 -> 5.06 | F26: ='23'!$F$9 | G26: ='23'!$F$10 -> 9.81 | H26: ='23'!$F$11 -> 3.66 | I26: ='23'!$F$12 -> 2.22 | J26: ='23'!$F$13 -> 5.2 | K26: ='23'!$F$14 -> 24.95 | L26: ='23'!$F$15 -> 7.15 | M26: ='23'!$F$16 -> 5.06 | N26: ='23'!$F$17 -> 9.5 | O26: ='23'!$F$18 -> 6.36 | P26: ='23'!$F$19 | Q26: ='23'!$F$20 -> 6.19 | R26: ='23'!$F$21 | S26: ='23'!$F$22 -> 5.94 | T26: ='23'!$F$23 -> 5.11 | U26: ='23'!$F$24 -> 7.09 | V26: ='23'!$F$25 -> 5.84 | W26: ='23'!$F$26 -> 2.3 | X26: ='23'!$F$27 -> 6.95 | Y26: ='23'!$F$28 -> 4.39 | Z26: ='23'!$F$29 -> 4.31 | AA26: ='23'!$F$30 -> 6.51 | AB26: ='23'!$F$31 | AC26: ='23'!$F$32 | AD26: ='23'!$F$33 -> 5.33
A27: Laredo | B27: ='24'!$F$5 | C27: ='24'!$F$6 | D27: ='24'!$F$7 -> 9.27 | E27: ='24'!$F$8 -> 10.74 | F27: ='24'!$F$9 | G27: ='24'!$F$10 -> 8.4 | H27: ='24'!$F$11 -> 11.07 | I27: ='24'!$F$12 -> 10.1 | J27: ='24'!$F$13 | K27: ='24'!$F$14 | L27: ='24'!$F$15 | M27: ='24'!$F$16 -> 12.29 | N27: ='24'!$F$17 -> 10.95 | O27: ='24'!$F$18 -> 15.58 | P27: ='24'!$F$19 | Q27: ='24'!$F$20 -> 11 | R27: ='24'!$F$21 | S27: ='24'!$F$22 -> 17.03 | T27: ='24'!$F$23 -> 8.74 | U27: ='24'!$F$24 -> 22.85 | V27: ='24'!$F$25 | W27: ='24'!$F$26 -> 11.07 | X27: ='24'!$F$27 -> 9.92 | Y27: ='24'!$F$28 -> 11.3 | Z27: ='24'!$F$29 -> 8.01 | AA27: ='24'!$F$30 -> 12.6 | AB27: ='24'!$F$31 | AC27: ='24'!$F$32 | AD27: ='24'!$F$33 -> 10.58
A28: Lee | B28: ='25'!$F$5 -> 7.12 | C28: ='25'!$F$6 -> 13.32 | D28: ='25'!$F$7 -> 8.97 | E28: ='25'!$F$8 -> 8.08 | F28: ='25'!$F$9 -> 4.5 | G28: ='25'!$F$10 -> 10.91 | H28: ='25'!$F$11 -> 10.67 | I28: ='25'!$F$12 -> 13.63 | J28: ='25'!$F$13 -> 7.33 | K28: ='25'!$F$14 | L28: ='25'!$F$15 -> 7.56 | M28: ='25'!$F$16 -> 11.46 | N28: ='25'!$F$17 -> 9.03 | O28: ='25'!$F$18 -> 11.69 | P28: ='25'!$F$19 | Q28: ='25'!$F$20 -> 27.66 | R28: ='25'!$F$21 | S28: ='25'!$F$22 -> 13.22 | T28: ='25'!$F$23 -> 10.6 | U28: ='25'!$F$24 -> 7.65 | V28: ='25'!$F$25 -> 8.02 | W28: ='25'!$F$26 -> 4.5 | X28: ='25'!$F$27 -> 20.06 | Y28: ='25'!$F$28 -> 6.99 | Z28: ='25'!$F$29 -> 9 | AA28: ='25'!$F$30 -> 11.05 | AB28: ='25'!$F$31 | AC28: ='25'!$F$32 | AD28: ='25'!$F$33 -> 10
A29: Lonestar | B29: ='26'!$F$5 -> 9.74 | C29: ='26'!$F$6 -> 8.95 | D29: ='26'!$F$7 -> 8.25 | E29: ='26'!$F$8 -> 8.68 | F29: ='26'!$F$9 -> 4.43 | G29: ='26'!$F$10 -> 6.32 | H29: ='26'!$F$11 -> 8.93 | I29: ='26'!$F$12 -> 9.2 | J29: ='26'!$F$13 -> 7.52 | K29: ='26'!$F$14 -> 17.99 | L29: ='26'!$F$15 -> 10.95 | M29: ='26'!$F$16 -> 8.9 | N29: ='26'!$F$17 -> 7.7 | O29: ='26'!$F$18 -> 12.49 | P29: ='26'!$F$19 -> 22.52 | Q29: ='26'!$F$20 -> 10.62 | R29: ='26'!$F$21 -> 14.16 | S29: ='26'!$F$22 -> 9.78 | T29: ='26'!$F$23 -> 7.84 | U29: ='26'!$F$24 -> 8.77 | V29: ='26'!$F$25 -> 15.47 | W29: ='26'!$F$26 -> 8.87 | X29: ='26'!$F$27 -> 9.49 | Y29: ='26'!$F$28 -> 8.4 | Z29: ='26'!$F$29 -> 7.66 | AA29: ='26'!$F$30 -> 10.64 | AB29: ='26'!$F$31 | AC29: ='26'!$F$32 | AD29: ='26'!$F$33 -> 8.7
A30: Mclennan | B30: ='27'!$F$5 -> 16.59 | C30: ='27'!$F$6 | D30: ='27'!$F$7 -> 5.91 | E30: ='27'!$F$8 -> 7.31 | F30: ='27'!$F$9 | G30: ='27'!$F$10 -> 3.37 | H30: ='27'!$F$11 -> 13.57 | I30: ='27'!$F$12 | J30: ='27'!$F$13 -> 9.95 | K30: ='27'!$F$14 -> 3.01 | L30: ='27'!$F$15 -> 6.41 | M30: ='27'!$F$16 -> 7.72 | N30: ='27'!$F$17 -> 5.83 | O30: ='27'!$F$18 -> 13.28 | P30: ='27'!$F$19 | Q30: ='27'!$F$20 -> 8.45 | R30: ='27'!$F$21 -> 9.43 | S30: ='27'!$F$22 -> 7.56 | T30: ='27'!$F$23 -> 6.56 | U30: ='27'!$F$24 | V30: ='27'!$F$25 -> 3.27 | W30: ='27'!$F$26 -> 3.01 | X30: ='27'!$F$27 -> 10.1 | Y30: ='27'!$F$28 -> 7.35 | Z30: ='27'!$F$29 -> 5.69 | AA30: ='27'!$F$30 -> 10.33 | AB30: ='27'!$F$31 | AC30: ='27'!$F$32 | AD30: ='27'!$F$33 -> 7.83
A31: Midland | B31: ='28'!$F$5 -> 4.72 | C31: ='28'!$F$6 -> 9.34 | D31: ='28'!$F$7 -> 7.95 | E31: ='28'!$F$8 -> 9.76 | F31: ='28'!$F$9 -> 41.03 | G31: ='28'!$F$10 -> 14.47 | H31: ='28'!$F$11 -> 18.73 | I31: ='28'!$F$12 -> 9.67 | J31: ='28'!$F$13 -> 8.03 | K31: ='28'!$F$14 -> 10.58 | L31: ='28'!$F$15 -> 19.08 | M31: ='28'!$F$16 -> 9.32 | N31: ='28'!$F$17 -> 6.01 | O31: ='28'!$F$18 -> 10.11 | P31: ='28'!$F$19 | Q31: ='28'!$F$20 -> 10.9 | R31: ='28'!$F$21 -> 10.45 | S31: ='28'!$F$22 -> 9.67 | T31: ='28'!$F$23 -> 8.57 | U31: ='28'!$F$24 -> 13.29 | V31: ='28'!$F$25 -> 20.9 | W31: ='28'!$F$26 -> 13.75 | X31: ='28'!$F$27 -> 9.76 | Y31: ='28'!$F$28 -> 10.43 | Z31: ='28'!$F$29 -> 7.7 | AA31: ='28'!$F$30 -> 9.54 | AB31: ='28'!$F$31 | AC31: ='28'!$F$32 | AD31: ='28'!$F$33 -> 9.79
A32: Navarro | B32: ='29'!$F$5 -> 6.72 | C32: ='29'!$F$6 -> 2.46 | D32: ='29'!$F$7 -> 5.01 | E32: ='29'!$F$8 -> 5.54 | F32: ='29'!$F$9 | G32: ='29'!$F$10 -> 10.08 | H32: ='29'!$F$11 -> 4 | I32: ='29'!$F$12 -> 4.43 | J32: ='29'!$F$13 -> 3.06 | K32: ='29'!$F$14 -> 19.34 | L32: ='29'!$F$15 -> 6.34 | M32: ='29'!$F$16 -> 5.09 | N32: ='29'!$F$17 -> 3.91 | O32: ='29'!$F$18 -> 8.65 | P32: ='29'!$F$19 | Q32: ='29'!$F$20 -> 4.41 | R32: ='29'!$F$21 | S32: ='29'!$F$22 -> 8.12 | T32: ='29'!$F$23 -> 5.04 | U32: ='29'!$F$24 -> 6.34 | V32: ='29'!$F$25 -> 6.34 | W32: ='29'!$F$26 -> 2.84 | X32: ='29'!$F$27 -> 5.37 | Y32: ='29'!$F$28 -> 3.79 | Z32: ='29'!$F$29 -> 4.78 | AA32: ='29'!$F$30 -> 5.92 | AB32: ='29'!$F$31 | AC32: ='29'!$F$32 | AD32: ='29'!$F$33 -> 4.91
A33: North Central Texas | B33: ='30'!$F$5 -> 9.18 | C33: ='30'!$F$6 -> 25.75 | D33: ='30'!$F$7 -> 5.28 | E33: ='30'!$F$8 -> 5.46 | F33: ='30'!$F$9 | G33: ='30'!$F$10 -> 4.5 | H33: ='30'!$F$11 -> 12.1 | I33: ='30'!$F$12 | J33: ='30'!$F$13 -> 4.75 | K33: ='30'!$F$14 | L33: ='30'!$F$15 -> 3.2 | M33: ='30'!$F$16 -> 5.63 | N33: ='30'!$F$17 -> 4.19 | O33: ='30'!$F$18 -> 7.64 | P33: ='30'!$F$19 | Q33: ='30'!$F$20 -> 7.41 | R33: ='30'!$F$21 | S33: ='30'!$F$22 -> 5.12 | T33: ='30'!$F$23 -> 5.05 | U33: ='30'!$F$24 | V33: ='30'!$F$25 | W33: ='30'!$F$26 -> 15.35 | X33: ='30'!$F$27 -> 8.41 | Y33: ='30'!$F$28 -> 6.59 | Z33: ='30'!$F$29 -> 4.56 | AA33: ='30'!$F$30 -> 6.05 | AB33: ='30'!$F$31 | AC33: ='30'!$F$32 | AD33: ='30'!$F$33 -> 5.73
A34: Northeast Texas | B34: ='31'!$F$5 -> 16.17 | C34: ='31'!$F$6 -> 7.6 | D34: ='31'!$F$7 -> 7.3 | E34: ='31'!$F$8 -> 7.16 | F34: ='31'!$F$9 | G34: ='31'!$F$10 -> 13.67 | H34: ='31'!$F$11 -> 14.83 | I34: ='31'!$F$12 -> 7.01 | J34: ='31'!$F$13 -> 5.46 | K34: ='31'!$F$14 | L34: ='31'!$F$15 -> 3.28 | M34: ='31'!$F$16 -> 6.56 | N34: ='31'!$F$17 -> 12.39 | O34: ='31'!$F$18 -> 10.61 | P34: ='31'!$F$19 -> 16.06 | Q34: ='31'!$F$20 -> 8.43 | R34: ='31'!$F$21 | S34: ='31'!$F$22 -> 9.78 | T34: ='31'!$F$23 -> 6.81 | U34: ='31'!$F$24 -> 7.85 | V34: ='31'!$F$25 -> 18.63 | W34: ='31'!$F$26 -> 3.28 | X34: ='31'!$F$27 -> 6.66 | Y34: ='31'!$F$28 -> 10.95 | Z34: ='31'!$F$29 -> 6.15 | AA34: ='31'!$F$30 -> 10.52 | AB34: ='31'!$F$31 | AC34: ='31'!$F$32 | AD34: ='31'!$F$33 -> 7.84
A35: Odessa | B35: ='32'!$F$5 -> 12.25 | C35: ='32'!$F$6 -> 7.16 | D35: ='32'!$F$7 -> 8.13 | E35: ='32'!$F$8 -> 8.51 | F35: ='32'!$F$9 | G35: ='32'!$F$10 -> 5.04 | H35: ='32'!$F$11 -> 8.78 | I35: ='32'!$F$12 -> 5.61 | J35: ='32'!$F$13 -> 9.62 | K35: ='32'!$F$14 | L35: ='32'!$F$15 -> 8.16 | M35: ='32'!$F$16 -> 9.05 | N35: ='32'!$F$17 -> 8.97 | O35: ='32'!$F$18 -> 12.16 | P35: ='32'!$F$19 | Q35: ='32'!$F$20 -> 11.36 | R35: ='32'!$F$21 -> 24.08 | S35: ='32'!$F$22 -> 10.67 | T35: ='32'!$F$23 -> 8.52 | U35: ='32'!$F$24 -> 10.06 | V35: ='32'!$F$25 -> 13.58 | W35: ='32'!$F$26 -> 7.3 | X35: ='32'!$F$27 -> 9.76 | Y35: ='32'!$F$28 -> 10.57 | Z35: ='32'!$F$29 -> 8.01 | AA35: ='32'!$F$30 -> 10.97 | AB35: ='32'!$F$31 | AC35: ='32'!$F$32 | AD35: ='32'!$F$33 -> 9.18
A36: Panola | B36: ='33'!$F$5 -> 6.47 | C36: ='33'!$F$6 -> 13.66 | D36: ='33'!$F$7 -> 8.56 | E36: ='33'!$F$8 -> 8.49 | F36: ='33'!$F$9 | G36: ='33'!$F$10 -> 17.51 | H36: ='33'!$F$11 -> 15.87 | I36: ='33'!$F$12 -> 8.16 | J36: ='33'!$F$13 -> 7.07 | K36: ='33'!$F$14 | L36: ='33'!$F$15 -> 15.01 | M36: ='33'!$F$16 -> 8.21 | N36: ='33'!$F$17 -> 11.65 | O36: ='33'!$F$18 -> 10.92 | P36: ='33'!$F$19 | Q36: ='33'!$F$20 -> 8.78 | R36: ='33'!$F$21 | S36: ='33'!$F$22 -> 7.94 | T36: ='33'!$F$23 -> 10.58 | U36: ='33'!$F$24 | V36: ='33'!$F$25 | W36: ='33'!$F$26 -> 30.38 | X36: ='33'!$F$27 -> 8.75 | Y36: ='33'!$F$28 -> 6.41 | Z36: ='33'!$F$29 -> 7.35 | AA36: ='33'!$F$30 -> 9.58 | AB36: ='33'!$F$31 | AC36: ='33'!$F$32 | AD36: ='33'!$F$33 -> 9.17
A37: Paris | B37: ='34'!$F$5 -> 14.53 | C37: ='34'!$F$6 -> 6.41 | D37: ='34'!$F$7 -> 4.35 | E37: ='34'!$F$8 -> 5.55 | F37: ='34'!$F$9 | G37: ='34'!$F$10 -> 11.04 | H37: ='34'!$F$11 -> 5.47 | I37: ='34'!$F$12 -> 6.83 | J37: ='34'!$F$13 -> 4.26 | K37: ='34'!$F$14 | L37: ='34'!$F$15 -> 4.72 | M37: ='34'!$F$16 -> 5.19 | N37: ='34'!$F$17 -> 4.98 | O37: ='34'!$F$18 -> 11.63 | P37: ='34'!$F$19 | Q37: ='34'!$F$20 -> 6.16 | R37: ='34'!$F$21 | S37: ='34'!$F$22 -> 7.23 | T37: ='34'!$F$23 -> 4.16 | U37: ='34'!$F$24 | V37: ='34'!$F$25 -> 14.85 | W37: ='34'!$F$26 -> 2.31 | X37: ='34'!$F$27 -> 6.05 | Y37: ='34'!$F$28 -> 4.98 | Z37: ='34'!$F$29 -> 5 | AA37: ='34'!$F$30 -> 6.65 | AB37: ='34'!$F$31 | AC37: ='34'!$F$32 | AD37: ='34'!$F$33 -> 5.44
A38: Ranger | B38: ='35'!$F$5 -> 7.29 | C38: ='35'!$F$6 -> 5.22 | D38: ='35'!$F$7 -> 4.89 | E38: ='35'!$F$8 -> 7.82 | F38: ='35'!$F$9 | G38: ='35'!$F$10 | H38: ='35'!$F$11 -> 5.64 | I38: ='35'!$F$12 | J38: ='35'!$F$13 -> 5.29 | K38: ='35'!$F$14 | L38: ='35'!$F$15 | M38: ='35'!$F$16 -> 5.73 | N38: ='35'!$F$17 -> 4.52 | O38: ='35'!$F$18 | P38: ='35'!$F$19 | Q38: ='35'!$F$20 -> 7.92 | R38: ='35'!$F$21 | S38: ='35'!$F$22 -> 5.41 | T38: ='35'!$F$23 -> 6.1 | U38: ='35'!$F$24 | V38: ='35'!$F$25 | W38: ='35'!$F$26 -> 6.16 | X38: ='35'!$F$27 -> 11.25 | Y38: ='35'!$F$28 | Z38: ='35'!$F$29 -> 4.75 | AA38: ='35'!$F$30 -> 8.72 | AB38: ='35'!$F$31 | AC38: ='35'!$F$32 | AD38: ='35'!$F$33 -> 6.3
A39: San Jacinto | B39: ='36'!$F$5 -> 7.86 | C39: ='36'!$F$6 -> 6.94 | D39: ='36'!$F$7 -> 7.07 | E39: ='36'!$F$8 -> 7.17 | F39: ='36'!$F$9 -> 32.32 | G39: ='36'!$F$10 -> 5.81 | H39: ='36'!$F$11 -> 10.11 | I39: ='36'!$F$12 -> 7.4 | J39: ='36'!$F$13 -> 8.42 | K39: ='36'!$F$14 -> 10 | L39: ='36'!$F$15 -> 18.38 | M39: ='36'!$F$16 -> 7.52 | N39: ='36'!$F$17 -> 9.36 | O39: ='36'!$F$18 -> 10.76 | P39: ='36'!$F$19 | Q39: ='36'!$F$20 -> 10.92 | R39: ='36'!$F$21 -> 10.15 | S39: ='36'!$F$22 -> 10.99 | T39: ='36'!$F$23 -> 7.64 | U39: ='36'!$F$24 -> 10.07 | V39: ='36'!$F$25 -> 18.31 | W39: ='36'!$F$26 -> 7.95 | X39: ='36'!$F$27 -> 8.62 | Y39: ='36'!$F$28 -> 12.33 | Z39: ='36'!$F$29 -> 7.43 | AA39: ='36'!$F$30 -> 9.68 | AB39: ='36'!$F$31 | AC39: ='36'!$F$32 | AD39: ='36'!$F$33 -> 8.52
A40: South Plains | B40: ='37'!$F$5 -> 11.14 | C40: ='37'!$F$6 -> 6.41 | D40: ='37'!$F$7 -> 5.81 | E40: ='37'!$F$8 -> 5.85 | F40: ='37'!$F$9 -> 2.49 | G40: ='37'!$F$10 -> 5.32 | H40: ='37'!$F$11 -> 6.83 | I40: ='37'!$F$12 -> 2.49 | J40: ='37'!$F$13 -> 5.99 | K40: ='37'!$F$14 -> 2.49 | L40: ='37'!$F$15 -> 4.06 | M40: ='37'!$F$16 -> 6.54 | N40: ='37'!$F$17 -> 5.29 | O40: ='37'!$F$18 -> 6.33 | P40: ='37'!$F$19 | Q40: ='37'!$F$20 -> 8.75 | R40: ='37'!$F$21 -> 8.45 | S40: ='37'!$F$22 -> 6.14 | T40: ='37'!$F$23 -> 5.31 | U40: ='37'!$F$24 -> 6.11 | V40: ='37'!$F$25 -> 5.6 | W40: ='37'!$F$26 -> 18.9 | X40: ='37'!$F$27 -> 11.04 | Y40: ='37'!$F$28 -> 4.6 | Z40: ='37'!$F$29 -> 5.42 | AA40: ='37'!$F$30 -> 9.78 | AB40: ='37'!$F$31 | AC40: ='37'!$F$32 | AD40: ='37'!$F$33 -> 6.33
A41: South Texas | B41: ='38'!$F$5 -> 7.08 | C41: ='38'!$F$6 -> 18.58 | D41: ='38'!$F$7 -> 7.08 | E41: ='38'!$F$8 -> 5.96 | F41: ='38'!$F$9 | G41: ='38'!$F$10 -> 10.4 | H41: ='38'!$F$11 -> 7.88 | I41: ='38'!$F$12 -> 12.83 | J41: ='38'!$F$13 -> 9.87 | K41: ='38'!$F$14 -> 6.65 | L41: ='38'!$F$15 -> 5.95 | M41: ='38'!$F$16 -> 9.07 | N41: ='38'!$F$17 -> 6.93 | O41: ='38'!$F$18 -> 10.29 | P41: ='38'!$F$19 | Q41: ='38'!$F$20 -> 13.37 | R41: ='38'!$F$21 -> 16.83 | S41: ='38'!$F$22 -> 10.97 | T41: ='38'!$F$23 -> 6.83 | U41: ='38'!$F$24 -> 7.73 | V41: ='38'!$F$25 -> 9.03 | W41: ='38'!$F$26 -> 11.2 | X41: ='38'!$F$27 -> 10.98 | Y41: ='38'!$F$28 -> 8.81 | Z41: ='38'!$F$29 -> 7.33 | AA41: ='38'!$F$30 -> 7.5 | AB41: ='38'!$F$31 | AC41: ='38'!$F$32 | AD41: ='38'!$F$33 -> 8.18
A42: Southwest Texas | B42: ='39'!$F$5 -> 9.87 | C42: ='39'!$F$6 -> 13.71 | D42: ='39'!$F$7 -> 7.33 | E42: ='39'!$F$8 -> 9.54 | F42: ='39'!$F$9 | G42: ='39'!$F$10 -> 5.38 | H42: ='39'!$F$11 -> 5.67 | I42: ='39'!$F$12 -> 9.06 | J42: ='39'!$F$13 -> 7.08 | K42: ='39'!$F$14 -> 4.93 | L42: ='39'!$F$15 -> 14.84 | M42: ='39'!$F$16 -> 7.41 | N42: ='39'!$F$17 -> 5.49 | O42: ='39'!$F$18 -> 3.33 | P42: ='39'!$F$19 | Q42: ='39'!$F$20 -> 5.17 | R42: ='39'!$F$21 | S42: ='39'!$F$22 -> 9.1 | T42: ='39'!$F$23 -> 7.93 | U42: ='39'!$F$24 -> 8.19 | V42: ='39'!$F$25 -> 15.47 | W42: ='39'!$F$26 -> 3.81 | X42: ='39'!$F$27 -> 8.22 | Y42: ='39'!$F$28 -> 9.24 | Z42: ='39'!$F$29 -> 6.51 | AA42: ='39'!$F$30 -> 7.3 | AB42: ='39'!$F$31 | AC42: ='39'!$F$32 | AD42: ='39'!$F$33 -> 7.59
A43: Tarrant | B43: ='40'!$F$5 -> 9.51 | C43: ='40'!$F$6 -> 18.52 | D43: ='40'!$F$7 -> 6.98 | E43: ='40'!$F$8 -> 7.2 | F43: ='40'!$F$9 -> 3.15 | G43: ='40'!$F$10 -> 9.31 | H43: ='40'!$F$11 -> 9 | I43: ='40'!$F$12 -> 6.06 | J43: ='40'!$F$13 -> 7.54 | K43: ='40'!$F$14 -> 11.31 | L43: ='40'!$F$15 -> 10.66 | M43: ='40'!$F$16 -> 7.28 | N43: ='40'!$F$17 -> 6.77 | O43: ='40'!$F$18 -> 13.95 | P43: ='40'!$F$19 -> 17.67 | Q43: ='40'!$F$20 -> 11.48 | R43: ='40'!$F$21 -> 14.47 | S43: ='40'!$F$22 | T43: ='40'!$F$23 -> 7.25 | U43: ='40'!$F$24 -> 9.81 | V43: ='40'!$F$25 -> 10.32 | W43: ='40'!$F$26 -> 5.04 | X43: ='40'!$F$27 -> 8.21 | Y43: ='40'!$F$28 -> 14.33 | Z43: ='40'!$F$29 -> 6.28 | AA43: ='40'!$F$30 -> 8.52 | AB43: ='40'!$F$31 | AC43: ='40'!$F$32 | AD43: ='40'!$F$33 -> 7.77
A44: Temple | B44: ='41'!$F$5 -> 7.25 | C44: ='41'!$F$6 -> 15.62 | D44: ='41'!$F$7 -> 7.48 | E44: ='41'!$F$8 -> 6 | F44: ='41'!$F$9 | G44: ='41'!$F$10 -> 8.72 | H44: ='41'!$F$11 -> 7.6 | I44: ='41'!$F$12 | J44: ='41'!$F$13 -> 7.08 | K44: ='41'!$F$14 | L44: ='41'!$F$15 -> 6.82 | M44: ='41'!$F$16 -> 6.67 | N44: ='41'!$F$17 -> 7.11 | O44: ='41'!$F$18 -> 9.88 | P44: ='41'!$F$19 -> 23.29 | Q44: ='41'!$F$20 -> 9.17 | R44: ='41'!$F$21 -> 9.5 | S44: ='41'!$F$22 -> 8.99 | T44: ='41'!$F$23 -> 7.41 | U44: ='41'!$F$24 | V44: ='41'!$F$25 | W44: ='41'!$F$26 -> 7.77 | X44: ='41'!$F$27 -> 6.53 | Y44: ='41'!$F$28 -> 7.05 | Z44: ='41'!$F$29 -> 6.1 | AA44: ='41'!$F$30 -> 10.37 | AB44: ='41'!$F$31 | AC44: ='41'!$F$32 | AD44: ='41'!$F$33 -> 7.61
A45: Texarkana | B45: ='42'!$F$5 -> 8.78 | C45: ='42'!$F$6 -> 6.17 | D45: ='42'!$F$7 -> 5.95 | E45: ='42'!$F$8 -> 6.42 | F45: ='42'!$F$9 | G45: ='42'!$F$10 -> 6.98 | H45: ='42'!$F$11 -> 8.64 | I45: ='42'!$F$12 -> 4.97 | J45: ='42'!$F$13 -> 5.53 | K45: ='42'!$F$14 | L45: ='42'!$F$15 -> 4.16 | M45: ='42'!$F$16 -> 5.26 | N45: ='42'!$F$17 -> 5.93 | O45: ='42'!$F$18 -> 10.27 | P45: ='42'!$F$19 -> 3.83 | Q45: ='42'!$F$20 -> 4.67 | R45: ='42'!$F$21 | S45: ='42'!$F$22 -> 6.06 | T45: ='42'!$F$23 -> 5.23 | U45: ='42'!$F$24 -> 5.75 | V45: ='42'!$F$25 -> 4.37 | W45: ='42'!$F$26 -> 4.64 | X45: ='42'!$F$27 -> 3.08 | Y45: ='42'!$F$28 -> 5.85 | Z45: ='42'!$F$29 -> 5.2 | AA45: ='42'!$F$30 -> 5.46 | AB45: ='42'!$F$31 | AC45: ='42'!$F$32 | AD45: ='42'!$F$33 -> 5.83
A46: Texas Southmost | B46: ='43'!$F$5 | C46: ='43'!$F$6 | D46: ='43'!$F$7 | E46: ='43'!$F$8 | F46: ='43'!$F$9 | G46: ='43'!$F$10 | H46: ='43'!$F$11 | I46: ='43'!$F$12 | J46: ='43'!$F$13 | K46: ='43'!$F$14 | L46: ='43'!$F$15 | M46: ='43'!$F$16 | N46: ='43'!$F$17 | O46: ='43'!$F$18 | P46: ='43'!$F$19 | Q46: ='43'!$F$20 | R46: ='43'!$F$21 | S46: ='43'!$F$22 | T46: ='43'!$F$23 | U46: ='43'!$F$24 | V46: ='43'!$F$25 | W46: ='43'!$F$26 | X46: ='43'!$F$27 | Y46: ='43'!$F$28 | Z46: ='43'!$F$29 | AA46: ='43'!$F$30 | AB46: ='43'!$F$31 | AC46: ='43'!$F$32 | AD46: ='43'!$F$33
A47: Trinity Valley | B47: ='44'!$F$5 -> 5.98 | C47: ='44'!$F$6 -> 4.24 | D47: ='44'!$F$7 -> 5.39 | E47: ='44'!$F$8 -> 6.88 | F47: ='44'!$F$9 | G47: ='44'!$F$10 -> 3.59 | H47: ='44'!$F$11 -> 3.8 | I47: ='44'!$F$12 -> 5.58 | J47: ='44'!$F$13 -> 4.86 | K47: ='44'!$F$14 | L47: ='44'!$F$15 -> 4.74 | M47: ='44'!$F$16 -> 5.15 | N47: ='44'!$F$17 -> 3.67 | O47: ='44'!$F$18 -> 7.32 | P47: ='44'!$F$19 | Q47: ='44'!$F$20 -> 6.16 | R47: ='44'!$F$21 | S47: ='44'!$F$22 -> 5.53 | T47: ='44'!$F$23 -> 5.68 | U47: ='44'!$F$24 -> 5.28 | V47: ='44'!$F$25 | W47: ='44'!$F$26 -> 3.69 | X47: ='44'!$F$27 -> 7.56 | Y47: ='44'!$F$28 -> 4.83 | Z47: ='44'!$F$29 -> 5 | AA47: ='44'!$F$30 -> 7.86 | AB47: ='44'!$F$31 | AC47: ='44'!$F$32 | AD47: ='44'!$F$33 -> 5.4
A48: Tyler | B48: ='45'!$F$5 -> 5.16 | C48: ='45'!$F$6 -> 11.35 | D48: ='45'!$F$7 -> 6.68 | E48: ='45'!$F$8 -> 5.21 | F48: ='45'!$F$9 -> 3.29 | G48: ='45'!$F$10 -> 6.1 | H48: ='45'!$F$11 -> 21.18 | I48: ='45'!$F$12 -> 8.08 | J48: ='45'!$F$13 -> 8.16 | K48: ='45'!$F$14 -> 3.75 | L48: ='45'!$F$15 -> 7.94 | M48: ='45'!$F$16 -> 8.56 | N48: ='45'!$F$17 -> 5.02 | O48: ='45'!$F$18 -> 10.22 | P48: ='45'!$F$19 -> 14.77 | Q48: ='45'!$F$20 -> 9.28 | R48: ='45'!$F$21 -> 9.93 | S48: ='45'!$F$22 -> 7.12 | T48: ='45'!$F$23 -> 6.89 | U48: ='45'!$F$24 -> 15.37 | V48: ='45'!$F$25 -> 8.08 | W48: ='45'!$F$26 -> 5.68 | X48: ='45'!$F$27 -> 12.44 | Y48: ='45'!$F$28 -> 8.91 | Z48: ='45'!$F$29 -> 6.03 | AA48: ='45'!$F$30 -> 7.56 | AB48: ='45'!$F$31 | AC48: ='45'!$F$32 | AD48: ='45'!$F$33 -> 7.56
A49: Vernon | B49: ='46'!$F$5 | C49: ='46'!$F$6 | D49: ='46'!$F$7 | E49: ='46'!$F$8 | F49: ='46'!$F$9 | G49: ='46'!$F$10 | H49: ='46'!$F$11 | I49: ='46'!$F$12 | J49: ='46'!$F$13 | K49: ='46'!$F$14 | L49: ='46'!$F$15 | M49: ='46'!$F$16 | N49: ='46'!$F$17 | O49: ='46'!$F$18 | P49: ='46'!$F$19 | Q49: ='46'!$F$20 | R49: ='46'!$F$21 | S49: ='46'!$F$22 | T49: ='46'!$F$23 | U49: ='46'!$F$24 | V49: ='46'!$F$25 | W49: ='46'!$F$26 | X49: ='46'!$F$27 | Y49: ='46'!$F$28 | Z49: ='46'!$F$29 | AA49: ='46'!$F$30 | AB49: ='46'!$F$31 | AC49: ='46'!$F$32 | AD49: ='46'!$F$33
A50: Victoria | B50: ='47'!$F$5 -> 7.54 | C50: ='47'!$F$6 -> 7.34 | D50: ='47'!$F$7 -> 8.31 | E50: ='47'!$F$8 -> 6.94 | F50: ='47'!$F$9 | G50: ='47'!$F$10 -> 9.4 | H50: ='47'!$F$11 -> 9.19 | I50: ='47'!$F$12 -> 17.77 | J50: ='47'!$F$13 -> 5.21 | K50: ='47'!$F$14 | L50: ='47'!$F$15 -> 10.09 | M50: ='47'!$F$16 -> 8 | N50: ='47'!$F$17 -> 10.29 | O50: ='47'!$F$18 -> 12.58 | P50: ='47'!$F$19 | Q50: ='47'!$F$20 -> 7.42 | R50: ='47'!$F$21 -> 11.28 | S50: ='47'!$F$22 -> 8.7 | T50: ='47'!$F$23 -> 9.36 | U50: ='47'!$F$24 | V50: ='47'!$F$25 -> 18.57 | W50: ='47'!$F$26 -> 3.61 | X50: ='47'!$F$27 -> 8.02 | Y50: ='47'!$F$28 -> 12.58 | Z50: ='47'!$F$29 -> 6.9 | AA50: ='47'!$F$30 -> 11 | AB50: ='47'!$F$31 | AC50: ='47'!$F$32 | AD50: ='47'!$F$33 -> 8.68
A51: Weatherford | B51: ='48'!$F$5 -> 12.7 | C51: ='48'!$F$6 -> 8.56 | D51: ='48'!$F$7 -> 7.37 | E51: ='48'!$F$8 -> 9.05 | F51: ='48'!$F$9 | G51: ='48'!$F$10 -> 10.48 | H51: ='48'!$F$11 -> 7.91 | I51: ='48'!$F$12 -> 8.56 | J51: ='48'!$F$13 -> 7.7 | K51: ='48'!$F$14 | L51: ='48'!$F$15 -> 8.22 | M51: ='48'!$F$16 -> 8.14 | N51: ='48'!$F$17 -> 7.9 | O51: ='48'!$F$18 -> 11.15 | P51: ='48'!$F$19 | Q51: ='48'!$F$20 -> 9.22 | R51: ='48'!$F$21 -> 11.02 | S51: ='48'!$F$22 -> 8.17 | T51: ='48'!$F$23 -> 8.59 | U51: ='48'!$F$24 | V51: ='48'!$F$25 -> 24.94 | W51: ='48'!$F$26 -> 8.28 | X51: ='48'!$F$27 -> 8.08 | Y51: ='48'!$F$28 -> 9.76 | Z51: ='48'!$F$29 -> 7.21 | AA51: ='48'!$F$30 -> 10.22 | AB51: ='48'!$F$31 | AC51: ='48'!$F$32 | AD51: ='48'!$F$33 -> 8.57
A52: Western Texas | B52: ='49'!$F$5 -> 7.74 | C52: ='49'!$F$6 -> 7.55 | D52: ='49'!$F$7 -> 5.71 | E52: ='49'!$F$8 -> 7.9 | F52: ='49'!$F$9 | G52: ='49'!$F$10 -> 155.39 | H52: ='49'!$F$11 -> 5.32 | I52: ='49'!$F$12 | J52: ='49'!$F$13 -> 7.67 | K52: ='49'!$F$14 | L52: ='49'!$F$15 -> 7.63 | M52: ='49'!$F$16 -> 6.43 | N52: ='49'!$F$17 -> 5.34 | O52: ='49'!$F$18 | P52: ='49'!$F$19 | Q52: ='49'!$F$20 -> 7.41 | R52: ='49'!$F$21 | S52: ='49'!$F$22 -> 7.24 | T52: ='49'!$F$23 -> 5.18 | U52: ='49'!$F$24 | V52: ='49'!$F$25 | W52: ='49'!$F$26 -> 7.57 | X52: ='49'!$F$27 -> 8.49 | Y52: ='49'!$F$28 -> 5.49 | Z52: ='49'!$F$29 -> 6.57 | AA52: ='49'!$F$30 -> 8.09 | AB52: ='49'!$F$31 | AC52: ='49'!$F$32 | AD52: ='49'!$F$33 -> 6.48
A53: Wharton | B53: ='50'!$F$5 -> 13.61 | C53: ='50'!$F$6 -> 16.74 | D53: ='50'!$F$7 -> 7.96 | E53: ='50'!$F$8 -> 6.71 | F53: ='50'!$F$9 | G53: ='50'!$F$10 | H53: ='50'!$F$11 -> 11.12 | I53: ='50'!$F$12 -> 4.31 | J53: ='50'!$F$13 -> 9.37 | K53: ='50'!$F$14 -> 4.31 | L53: ='50'!$F$15 -> 7.81 | M53: ='50'!$F$16 -> 7.94 | N53: ='50'!$F$17 -> 9.05 | O53: ='50'!$F$18 -> 15.8 | P53: ='50'!$F$19 -> 20.19 | Q53: ='50'!$F$20 -> 9.87 | R53: ='50'!$F$21 | S53: ='50'!$F$22 -> 10.21 | T53: ='50'!$F$23 -> 7.74 | U53: ='50'!$F$24 -> 13.4 | V53: ='50'!$F$25 | W53: ='50'!$F$26 -> 7.48 | X53: ='50'!$F$27 -> 8.78 | Y53: ='50'!$F$28 -> 13.14 | Z53: ='50'!$F$29 -> 7.12 | AA53: ='50'!$F$30 -> 9.15 | AB53: ='50'!$F$31 | AC53: ='50'!$F$32 | AD53: ='50'!$F$33 -> 8.65
A54: TSTC-Harlingen | B54: ='51'!$F$5 -> 10.92 | C54: ='51'!$F$6 -> 11.71 | D54: ='51'!$F$7 -> 6.48 | E54: ='51'!$F$8 -> 5.48 | F54: ='51'!$F$9 | G54: ='51'!$F$10 -> 11.7 | H54: ='51'!$F$11 -> 12.12 | I54: ='51'!$F$12 -> 15.52 | J54: ='51'!$F$13 -> 8.13 | K54: ='51'!$F$14 -> 3.91 | L54: ='51'!$F$15 -> 8.21 | M54: ='51'!$F$16 -> 6.74 | N54: ='51'!$F$17 -> 6.15 | O54: ='51'!$F$18 -> 7.31 | P54: ='51'!$F$19 -> 12.47 | Q54: ='51'!$F$20 -> 11.03 | R54: ='51'!$F$21 | S54: ='51'!$F$22 | T54: ='51'!$F$23 -> 8 | U54: ='51'!$F$24 -> 8.03 | V54: ='51'!$F$25 -> 6.58 | W54: ='51'!$F$26 -> 4.21 | X54: ='51'!$F$27 -> 3.91 | Y54: ='51'!$F$28 -> 6.08 | Z54: ='51'!$F$29 -> 5.64 | AA54: ='51'!$F$30 -> 5.21 | AB54: ='51'!$F$31 | AC54: ='51'!$F$32 | AD54: ='51'!$F$33 -> 7.56
A55: TSTC-West Texas | B55: ='52'!$F$5 | C55: ='52'!$F$6 -> 11.31 | D55: ='52'!$F$7 -> 9.43 | E55: ='52'!$F$8 -> 8.35 | F55: ='52'!$F$9 -> 4.64 | G55: ='52'!$F$10 -> 11.31 | H55: ='52'!$F$11 -> 8.35 | I55: ='52'!$F$12 -> 11.31 | J55: ='52'!$F$13 -> 11.31 | K55: ='52'!$F$14 | L55: ='52'!$F$15 -> 13.92 | M55: ='52'!$F$16 -> 9.43 | N55: ='52'!$F$17 -> 9.43 | O55: ='52'!$F$18 -> 9.22 | P55: ='52'!$F$19 | Q55: ='52'!$F$20 -> 9.22 | R55: ='52'!$F$21 | S55: ='52'!$F$22 -> 9.22 | T55: ='52'!$F$23 -> 9.43 | U55: ='52'!$F$24 -> 9.77 | V55: ='52'!$F$25 -> 9.77 | W55: ='52'!$F$26 -> 11.31 | X55: ='52'!$F$27 | Y55: ='52'!$F$28 -> 8.35 | Z55: ='52'!$F$29 -> 9.43 | AA55: ='52'!$F$30 -> 8.35 | AB55: ='52'!$F$31 | AC55: ='52'!$F$32 | AD55: ='52'!$F$33 -> 9.39
A56: TSTC-Marshall | B56: ='53'!$F$5 -> 11.07 | C56: ='53'!$F$6 -> 14.19 | D56: ='53'!$F$7 -> 8.71 | E56: ='53'!$F$8 -> 8.48 | F56: ='53'!$F$9 -> 5.76 | G56: ='53'!$F$10 -> 11.07 | H56: ='53'!$F$11 -> 8.48 | I56: ='53'!$F$12 -> 11.07 | J56: ='53'!$F$13 -> 11.07 | K56: ='53'!$F$14 | L56: ='53'!$F$15 -> 11.49 | M56: ='53'!$F$16 -> 9.71 | N56: ='53'!$F$17 -> 8.3 | O56: ='53'!$F$18 | P56: ='53'!$F$19 | Q56: ='53'!$F$20 -> 11.05 | R56: ='53'!$F$21 | S56: ='53'!$F$22 | T56: ='53'!$F$23 -> 10.29 | U56: ='53'!$F$24 -> 12.29 | V56: ='53'!$F$25 -> 12.29 | W56: ='53'!$F$26 -> 11.07 | X56: ='53'!$F$27 | Y56: ='53'!$F$28 -> 8.47 | Z56: ='53'!$F$29 -> 7.14 | AA56: ='53'!$F$30 -> 8.48 | AB56: ='53'!$F$31 | AC56: ='53'!$F$32 | AD56: ='53'!$F$33 -> 10.53
A57: TSTC-Waco | B57: ='54'!$F$5 -> 9.62 | C57: ='54'!$F$6 -> 8.09 | D57: ='54'!$F$7 -> 9.84 | E57: ='54'!$F$8 -> 6.77 | F57: ='54'!$F$9 -> 27.82 | G57: ='54'!$F$10 -> 8.5 | H57: ='54'!$F$11 -> 8.83 | I57: ='54'!$F$12 -> 7.87 | J57: ='54'!$F$13 -> 8.53 | K57: ='54'!$F$14 -> 13.28 | L57: ='54'!$F$15 -> 8.88 | M57: ='54'!$F$16 -> 7.07 | N57: ='54'!$F$17 -> 8.28 | O57: ='54'!$F$18 -> 6.19 | P57: ='54'!$F$19 | Q57: ='54'!$F$20 -> 3.72 | R57: ='54'!$F$21 | S57: ='54'!$F$22 | T57: ='54'!$F$23 -> 8.41 | U57: ='54'!$F$24 -> 7.5 | V57: ='54'!$F$25 -> 7.97 | W57: ='54'!$F$26 -> 10.27 | X57: ='54'!$F$27 | Y57: ='54'!$F$28 -> 9.23 | Z57: ='54'!$F$29 -> 7.85 | AA57: ='54'!$F$30 -> 6.32 | AB57: ='54'!$F$31 | AC57: ='54'!$F$32 | AD57: ='54'!$F$33 -> 8.34
A58: Lamar-IOT | B58: ='55'!$F$5 | C58: ='55'!$F$6 -> 12.45 | D58: ='55'!$F$7 -> 12.45 | E58: ='55'!$F$8 -> 12.45 | F58: ='55'!$F$9 | G58: ='55'!$F$10 | H58: ='55'!$F$11 -> 12.45 | I58: ='55'!$F$12 -> 12.45 | J58: ='55'!$F$13 -> 12.45 | K58: ='55'!$F$14 | L58: ='55'!$F$15 -> 12.45 | M58: ='55'!$F$16 -> 12.45 | N58: ='55'!$F$17 | O58: ='55'!$F$18 | P58: ='55'!$F$19 -> 12.45 | Q58: ='55'!$F$20 -> 12.45 | R58: ='55'!$F$21 -> 12.45 | S58: ='55'!$F$22 | T58: ='55'!$F$23 -> 12.45 | U58: ='55'!$F$24 -> 12.44 | V58: ='55'!$F$25 -> 12.45 | W58: ='55'!$F$26 -> 12.45 | X58: ='55'!$F$27 | Y58: ='55'!$F$28 -> 12.45 | Z58: ='55'!$F$29 -> 12.45 | AA58: ='55'!$F$30 -> 12.45 | AB58: ='55'!$F$31 | AC58: ='55'!$F$32 | AD58: ='55'!$F$33 -> 12.45
A59: Lamar-Orange | B59: ='56'!$F$5 | C59: ='56'!$F$6 | D59: ='56'!$F$7 | E59: ='56'!$F$8 | F59: ='56'!$F$9 | G59: ='56'!$F$10 | H59: ='56'!$F$11 | I59: ='56'!$F$12 | J59: ='56'!$F$13 | K59: ='56'!$F$14 | L59: ='56'!$F$15 | M59: ='56'!$F$16 | N59: ='56'!$F$17 | O59: ='56'!$F$18 | P59: ='56'!$F$19 | Q59: ='56'!$F$20 | R59: ='56'!$F$21 | S59: ='56'!$F$22 | T59: ='56'!$F$23 | U59: ='56'!$F$24 | V59: ='56'!$F$25 | W59: ='56'!$F$26 | X59: ='56'!$F$27 | Y59: ='56'!$F$28 | Z59: ='56'!$F$29 | AA59: ='56'!$F$30 | AB59: ='56'!$F$31 | AC59: ='56'!$F$32 | AD59: ='56'!$F$33
A60: Lamar-Port Arthur | B60: ='57'!$F$5 | C60: ='57'!$F$6 -> 12.66 | D60: ='57'!$F$7 -> 12.66 | E60: ='57'!$F$8 -> 12.66 | F60: ='57'!$F$9 | G60: ='57'!$F$10 -> 12.66 | H60: ='57'!$F$11 -> 12.66 | I60: ='57'!$F$12 -> 12.66 | J60: ='57'!$F$13 -> 12.66 | K60: ='57'!$F$14 | L60: ='57'!$F$15 -> 12.66 | M60: ='57'!$F$16 -> 12.66 | N60: ='57'!$F$17 -> 12.66 | O60: ='57'!$F$18 -> 12.66 | P60: ='57'!$F$19 | Q60: ='57'!$F$20 -> 12.66 | R60: ='57'!$F$21 | S60: ='57'!$F$22 -> 12.66 | T60: ='57'!$F$23 -> 12.66 | U60: ='57'!$F$24 -> 12.66 | V60: ='57'!$F$25 -> 12.66 | W60: ='57'!$F$26 -> 12.66 | X60: ='57'!$F$27 -> 12.66 | Y60: ='57'!$F$28 -> 12.66 | Z60: ='57'!$F$29 -> 12.66 | AA60: ='57'!$F$30 -> 12.66 | AB60: ='57'!$F$31 | AC60: ='57'!$F$32 | AD60: ='57'!$F$33 -> 12.66
A61: Total | B61: =Summary!$F$5 -> 7.7 | C61: =Summary!$F$6 -> 8.88 | D61: =Summary!$F$7 -> 6.85 | E61: =Summary!$F$8 -> 7.11 | F61: =Summary!$F$9 -> 33.87 | G61: =Summary!$F$10 -> 7.65 | H61: =Summary!$F$11 -> 8.52 | I61: =Summary!$F$12 -> 8.03 | J61: =Summary!$F$13 -> 6.75 | K61: =Summary!$F$14 -> 7.86 | L61: =Summary!$F$15 -> 7.41 | M61: =Summary!$F$16 -> 7.31 | N61: =Summary!$F$17 -> 6.87 | O61: =Summary!$F$18 -> 10.55 | P61: =Summary!$F$19 -> 16.87 | Q61: =Summary!$F$20 -> 8.34 | R61: =Summary!$F$21 -> 11.1 | S61: =Summary!$F$22 -> 8.42 | T61: =Summary!$F$23 -> 6.98 | U61: =Summary!$F$24 -> 8.57 | V61: =Summary!$F$25 -> 9.33 | W61: =Summary!$F$26 -> 7.22 | X61: =Summary!$F$27 -> 8.32 | Y61: =Summary!$F$28 -> 7.58 | Z61: =Summary!$F$29 -> 6.31 | AA61: =Summary!$F$30 -> 8.36 | AD61: =Summary!$F$33 -> 7.6
A62: Average (Excluding zero values) | B62: =AVERAGE(B$4:B$60) -> 9.0943478 | C62: =AVERAGE(C$4:C$60) -> 10.945918 | D62: =AVERAGE(D$4:D$60) -> 7.4126923 | E62: =AVERAGE(E$4:E$60) -> 7.7125 | F62: =AVERAGE(F$4:F$60) -> 17.022143 | G62: =AVERAGE(G$4:G$60) -> 11.614681 | H62: =AVERAGE(H$4:H$60) -> 10.684808 | I62: =AVERAGE(I$4:I$60) -> 8.8215217 | ... AA62: =AVERAGE(AA$4:AA$60) -> 9.1553846 | AD62: =AVERAGE(AD$4:AD$60) -> 8.1488462
A63: High | B63: =MAX(B$4:B$60) -> 16.59 | C63: =MAX(C$4:C$60) -> 27.1 | D63: =MAX(D$4:D$60) -> 12.66 | E63: =MAX(E$4:E$60) -> 12.8 | F63: =MAX(F$4:F$60) -> 56.23 | G63: =MAX(G$4:G$60) -> 155.39 | H63: =MAX(H$4:H$60) -> 21.18 | I63: =MAX(I$4:I$60) -> 17.77 | ... AA63: =MAX(AA$4:AA$60) -> 17.18 | AD63: =MAX(AD$4:AD$60) -> 13.81
A64: Low (Excluding zero values) | B64: =MIN(B$4:B$60) -> 4.72 | C64: =MIN(C$4:C$60) -> 2.46 | D64: =MIN(D$4:D$60) -> 4.35 | E64: =MIN(E$4:E$60) -> 4.13 | F64: =MIN(F$4:F$60) -> 2.49 | G64: =MIN(G$4:G$60) -> 3.06 | H64: =MIN(H$4:H$60) -> 3.66 | I64: =MIN(I$4:I$60) -> 2.22 | ... AA64: =MIN(AA$4:AA$60) -> 5.21 | AD64: =MIN(AD$4:AD$60) -> 4.91
A65: Median (Excluding zero values) | B65: =MEDIAN(B$4:B$60) -> 8.705 | C65: =MEDIAN(C$4:C$60) -> 9.53 | D65: =MEDIAN(D$4:D$60) -> 7.25 | E65: =MEDIAN(E$4:E$60) -> 7.425 | F65: =MEDIAN(F$4:F$60) -> 5.2 | G65: =MEDIAN(G$4:G$60) -> 8.5 | H65: =MEDIAN(H$4:H$60) -> 10.15 | I65: =MEDIAN(I$4:I$60) -> 8.685 | ... AA65: =MEDIAN(AA$4:AA$60) -> 8.775 | AD65: =MEDIAN(AD$4:AD$60) -> 7.955
B67: Discipline | L67: Discipline | V67: Discipline
B68: AG - Agriculture | L68: ENGR - Engineering Related | V68: MECH - Mechanics and Repairers - Diesel, Aviation Mechanics, and Transportation Workers
B69: ARCH - Architecture and Precision Production Trades | L69: LA - English Language, Lit, Philosophy, Humanities, & Interdisciplinary | V69: ELECT - Mechanics and Repairers - Electronics
B70: SCI - Biology, Physical Sciences, and Science Technology | L70: FL - Foreign Languages | V70: PE - Physical Education and Fitness
B71: BA - Business Management, Marketing, and Administrative Services | L71: HODA - Health Occupations - Dental Assistants, Medical Lab, and Assoc. Degree Nursing | V71: PA - Protective Services and Public Administration
B72: CP - Career Pilot | L72: HODH - Health Occupations - Dental Hygiene | V72: SS - Psychology, Social Sciences, and History
B73: COMM - Communications | L73: HOO - Health Occupations - Other | V73: FA - Visual and Performing Arts
B74: CS - Computer and Information Sciences | L74: HORT - Health Occupations - Respiratory Therapy
B75: CNSTR - Construction Trades | L75: NUR - Health Occupations - Vocational Nursing | V75: DEM - Developmental Education - Math
B76: HE - Consumer and Homemaking Education | L76: MATH - Mathematics | V76: DER - Developmental Education - Reading/Writing
B77: ENG - Engineering | L77: AUTO - Mechanics and Repairers - Automotive | V77: Total - All Disciplines

Sheet Discipline Analysis
A1: =Summary!A1 -> Community and Technical Colleges, Report of Fundable Operating Expenses, Fiscal Year (FY) 2008
A2: Discipline Analysis by Institution | X2: Discipline
A3: 1 | X3: Agriculture
X4: Architecture and Precision Production Trades
A5: Institution | B5: Contact Hours | C5: Total | E5: Faculty Salaries | G5: Academic Support | I5: Institutional Support | K5: Student Services | M5: Departmental Operating Expense | O5: Research | Q5: Scholarships and Fellowships | S5: Equipment Depreciation | U5: Local Benefits | X5: Biology, Physical Sciences, and Science Technology
C6: Expense | D6: per Hour | E6: Expense | F6: per Hour | G6: Expense | H6: per Hour | I6: Expense | J6: per Hour | K6: Expense | L6: per Hour | M6: Expense | N6: per Hour | O6: Expense | P6: per Hour | Q6: Expense | R6: per Hour | S6: Expense | T6: per Hour | U6: Expense | V6: per Hour | X6: Business Management, Marketing, and Administrative Services
A7: Alamo | B7: =OFFSET('1'!$D$4,$A$3,0) -> 71760 | C7: =OFFSET('1'!$E$4,$A$3,0) -> 496985.98 | D7: =OFFSET('1'!$F$4,$A$3,0) -> 6.93 | E7: =OFFSET('1'!$E$66,$A$3,0) -> 109155 | F7: =OFFSET('1'!$F$66,$A$3,0) -> 1.52 | G7: =IFERROR('1'!$F$100*'Discipline Analysis'!$B7,"") -> 66019.2 | H7: ='1'!$F$100 -> 0.92 | I7: =IFERROR('1'!$F$98*'Discipline Analysis'!$B7,"") -> 133473.6 | J7: ='1'!$F$98 -> 1.86 | K7: =IFERROR('1'!$F$99*'Discipline Analysis'!$B7,"") -> 71760 | L7: ='1'!$F$99 -> 1 | M7: =OFFSET('1'!$E$35,$A$3,0) -> 76984 | N7: =OFFSET('1'!$F$35,$A$3,0) -> 1.07 | O7: =IFERROR('1'!$F$101*'Discipline Analysis'!$B7,"") -> 0 | P7: ='1'!$F$101 -> 0 | Q7: =IFERROR('1'!$F$102*'Discipline Analysis'!$B7,"") -> 2152.8 | R7: ='1'!$F$102 -> 0.03 | S7: =IFERROR('1'!$F$103*'Discipline Analysis'!$B7,"") -> 11481.6 | T7: ='1'!$F$103 -> 0.16 | U7: =IFERROR('1'!$F$104*'Discipline Analysis'!$B7,"") -> 25833.6 | V7: ='1'!$F$104 -> 0.36 | X7: Career Pilot
A8: Alvin | B8: =OFFSET('2'!$D$4,$A$3,0) -> 39312 | C8: =OFFSET('2'!$E$4,$A$3,0) -> 209379.57 | D8: =OFFSET('2'!$F$4,$A$3,0) -> 5.33 | E8: =OFFSET('2'!$E$66,$A$3,0) -> 67356 | F8: =OFFSET('2'!$F$66,$A$3,0) -> 1.71 | G8: =IFERROR('2'!$F$100*'Discipline Analysis'!$B8,"") -> 41670.72 | H8: ='2'!$F$100 -> 1.06 | I8: =IFERROR('2'!$F$98*'Discipline Analysis'!$B8,"") -> 54250.56 | J8: ='2'!$F$98 -> 1.38 | K8: =IFERROR('2'!$F$99*'Discipline Analysis'!$B8,"") -> 28304.64 | L8: ='2'!$F$99 -> 0.72 | M8: =OFFSET('2'!$E$35,$A$3,0) -> 7191 | N8: =OFFSET('2'!$F$35,$A$3,0) -> 0.18 | O8: =IFERROR('2'!$F$101*'Discipline Analysis'!$B8,"") -> 0 | P8: ='2'!$F$101 -> 0 | Q8: =IFERROR('2'!$F$102*'Discipline Analysis'!$B8,"") -> 0 | R8: ='2'!$F$102 -> 0 | S8: =IFERROR('2'!$F$103*'Discipline Analysis'!$B8,"") -> 5110.56 | T8: ='2'!$F$103 -> 0.13 | U8: =IFERROR('2'!$F$104*'Discipline Analysis'!$B8,"") -> 5110.56 | V8: ='2'!$F$104 -> 0.13 | X8: Communications
A9: Amarillo | B9: =OFFSET('3'!$D$4,$A$3,0) -> 10184 | C9: =OFFSET('3'!$E$4,$A$3,0) -> 75770.544 | D9: =OFFSET('3'!$F$4,$A$3,0) -> 7.44 | E9: =OFFSET('3'!$E$66,$A$3,0) -> 29498 | F9: =OFFSET('3'!$F$66,$A$3,0) -> 2.9 | G9: =IFERROR('3'!$F$100*'Discipline Analysis'!$B9,"") -> 5397.52 | H9: ='3'!$F$100 -> 0.53 | I9: =IFERROR('3'!$F$98*'Discipline Analysis'!$B9,"") -> 18942.24 | J9: ='3'!$F$98 -> 1.86 | K9: =IFERROR('3'!$F$99*'Discipline Analysis'!$B9,"") -> 5397.52 | L9: ='3'!$F$99 -> 0.53 | M9: =OFFSET('3'!$E$35,$A$3,0) -> 11524 | N9: =OFFSET('3'!$F$35,$A$3,0) -> 1.13 | O9: =IFERROR('3'!$F$101*'Discipline Analysis'!$B9,"") -> 0 | P9: ='3'!$F$101 -> 0 | Q9: =IFERROR('3'!$F$102*'Discipline Analysis'!$B9,"") -> 0 | R9: ='3'!$F$102 -> 0 | S9: =IFERROR('3'!$F$103*'Discipline Analysis'!$B9,"") -> 1527.6 | T9: ='3'!$F$103 -> 0.15 | U9: =IFERROR('3'!$F$104*'Discipline Analysis'!$B9,"") -> 3564.4 | V9: ='3'!$F$104 -> 0.35 | X9: Computer and Information Sciences
A10: Angelina | B10: =OFFSET('4'!$D$4,$A$3,0) -> 0 | C10: =OFFSET('4'!$E$4,$A$3,0) -> 0 | D10: =OFFSET('4'!$F$4,$A$3,0) | E10: =OFFSET('4'!$E$66,$A$3,0) -> 0 | F10: =OFFSET('4'!$F$66,$A$3,0) | G10: =IFERROR('4'!$F$100*'Discipline Analysis'!$B10,"") -> 0 | H10: ='4'!$F$100 -> 0.86 | I10: =IFERROR('4'!$F$98*'Discipline Analysis'!$B10,"") -> 0 | J10: ='4'!$F$98 -> 0.93 | K10: =IFERROR('4'!$F$99*'Discipline Analysis'!$B10,"") -> 0 | L10: ='4'!$F$99 -> 0.41 | M10: =OFFSET('4'!$E$35,$A$3,0) -> 0 | N10: =OFFSET('4'!$F$35,$A$3,0) | O10: =IFERROR('4'!$F$101*'Discipline Analysis'!$B10,"") -> 0 | P10: ='4'!$F$101 -> 0 | Q10: =IFERROR('4'!$F$102*'Discipline Analysis'!$B10,"") -> 0 | R10: ='4'!$F$102 -> 0 | S10: =IFERROR('4'!$F$103*'Discipline Analysis'!$B10,"") -> 0 | T10: ='4'!$F$103 -> 0.13 | U10: =IFERROR('4'!$F$104*'Discipline Analysis'!$B10,"") -> 0 | V10: ='4'!$F$104 -> 0.08 | X10: Construction Trades
A11: Austin | B11: =OFFSET('5'!$D$4,$A$3,0) -> 85570 | C11: =OFFSET('5'!$E$4,$A$3,0) -> 559145.37 | D11: =OFFSET('5'!$F$4,$A$3,0) -> 6.53 | E11: =OFFSET('5'!$E$66,$A$3,0) -> 113776 | F11: =OFFSET('5'!$F$66,$A$3,0) -> 1.33 | G11: =IFERROR('5'!$F$100*'Discipline Analysis'!$B11,"") -> 116375.2 | H11: ='5'!$F$100 -> 1.36 | I11: =IFERROR('5'!$F$98*'Discipline Analysis'!$B11,"") -> 167717.2 | J11: ='5'!$F$98 -> 1.96 | K11: =IFERROR('5'!$F$99*'Discipline Analysis'!$B11,"") -> 98405.5 | L11: ='5'!$F$99 -> 1.15 | M11: =OFFSET('5'!$E$35,$A$3,0) -> 23208 | N11: =OFFSET('5'!$F$35,$A$3,0) -> 0.27 | O11: =IFERROR('5'!$F$101*'Discipline Analysis'!$B11,"") -> 0 | P11: ='5'!$F$101 -> 0 | Q11: =IFERROR('5'!$F$102*'Discipline Analysis'!$B11,"") -> 0 | R11: ='5'!$F$102 -> 0 | S11: =IFERROR('5'!$F$103*'Discipline Analysis'!$B11,"") -> 11979.8 | T11: ='5'!$F$103 -> 0.14 | U11: =IFERROR('5'!$F$104*'Discipline Analysis'!$B11,"") -> 28238.1 | V11: ='5'!$F$104 -> 0.33 | X11: Consumer and Homemaking Education
A12: Blinn | B12: =OFFSET('6'!$D$4,$A$3,0) -> 59744 | C12: =OFFSET('6'!$E$4,$A$3,0) -> 389838.05 | D12: =OFFSET('6'!$F$4,$A$3,0) -> 6.53 | E12: =OFFSET('6'!$E$66,$A$3,0) -> 221421 | F12: =OFFSET('6'!$F$66,$A$3,0) -> 3.71 | G12: =IFERROR('6'!$F$100*'Discipline Analysis'!$B12,"") -> 26287.36 | H12: ='6'!$F$100 -> 0.44 | I12: =IFERROR('6'!$F$98*'Discipline Analysis'!$B12,"") -> 58549.12 | J12: ='6'!$F$98 -> 0.98 | K12: =IFERROR('6'!$F$99*'Discipline Analysis'!$B12,"") -> 31664.32 | L12: ='6'!$F$99 -> 0.53 | M12: =OFFSET('6'!$E$35,$A$3,0) -> 39519 | N12: =OFFSET('6'!$F$35,$A$3,0) -> 0.66 | O12: =IFERROR('6'!$F$101*'Discipline Analysis'!$B12,"") -> 0 | P12: ='6'!$F$101 -> 0 | Q12: =IFERROR('6'!$F$102*'Discipline Analysis'!$B12,"") -> 3584.64 | R12: ='6'!$F$102 -> 0.06 | S12: =IFERROR('6'!$F$103*'Discipline Analysis'!$B12,"") -> 2987.2 | T12: ='6'!$F$103 -> 0.05 | U12: =IFERROR('6'!$F$104*'Discipline Analysis'!$B12,"") -> 5376.96 | V12: ='6'!$F$104 -> 0.09 | X12: Engineering
A13: Brazosport | B13: =OFFSET('7'!$D$4,$A$3,0) -> 0 | C13: =OFFSET('7'!$E$4,$A$3,0) -> 0 | D13: =OFFSET('7'!$F$4,$A$3,0) | E13: =OFFSET('7'!$E$66,$A$3,0) -> 0 | F13: =OFFSET('7'!$F$66,$A$3,0) | G13: =IFERROR('7'!$F$100*'Discipline Analysis'!$B13,"") -> 0 | H13: ='7'!$F$100 -> 0.92 | I13: =IFERROR('7'!$F$98*'Discipline Analysis'!$B13,"") -> 0 | J13: ='7'!$F$98 -> 2.59 | K13: =IFERROR('7'!$F$99*'Discipline Analysis'!$B13,"") -> 0 | L13: ='7'!$F$99 -> 1.1 | M13: =OFFSET('7'!$E$35,$A$3,0) -> 0 | N13: =OFFSET('7'!$F$35,$A$3,0) | O13: =IFERROR('7'!$F$101*'Discipline Analysis'!$B13,"") -> 0 | P13: ='7'!$F$101 -> 0 | Q13: =IFERROR('7'!$F$102*'Discipline Analysis'!$B13,"") -> 0 | R13: ='7'!$F$102 -> 0.18 | S13: =IFERROR('7'!$F$103*'Discipline Analysis'!$B13,"") -> 0 | T13: ='7'!$F$103 -> 0.23 | U13: =IFERROR('7'!$F$104*'Discipline Analysis'!$B13,"") -> 0 | V13: ='7'!$F$104 -> 0.13 | X13: Engineering Related
A14: Central Texas | B14: =OFFSET('8'!$D$4,$A$3,0) -> 72622 | C14: =OFFSET('8'!$E$4,$A$3,0) -> 377500.37 | D14: =OFFSET('8'!$F$4,$A$3,0) -> 5.2 | E14: =OFFSET('8'!$E$66,$A$3,0) -> 87639 | F14: =OFFSET('8'!$F$66,$A$3,0) -> 1.21 | G14: =IFERROR('8'!$F$100*'Discipline Analysis'!$B14,"") -> 26143.92 | H14: ='8'!$F$100 -> 0.36 | I14: =IFERROR('8'!$F$98*'Discipline Analysis'!$B14,"") -> 111837.88 | J14: ='8'!$F$98 -> 1.54 | K14: =IFERROR('8'!$F$99*'Discipline Analysis'!$B14,"") -> 47204.3 | L14: ='8'!$F$99 -> 0.65 | M14: =OFFSET('8'!$E$35,$A$3,0) -> 73228 | N14: =OFFSET('8'!$F$35,$A$3,0) -> 1.01 | O14: =IFERROR('8'!$F$101*'Discipline Analysis'!$B14,"") -> 0 | P14: ='8'!$F$101 -> 0 | Q14: =IFERROR('8'!$F$102*'Discipline Analysis'!$B14,"") -> 0 | R14: ='8'!$F$102 -> 0 | S14: =IFERROR('8'!$F$103*'Discipline Analysis'!$B14,"") -> 10893.3 | T14: ='8'!$F$103 -> 0.15 | U14: =IFERROR('8'!$F$104*'Discipline Analysis'!$B14,"") -> 19607.94 | V14: ='8'!$F$104 -> 0.27 | X14: English Language, Lit, Philosophy, Humanities, & Interdisciplinary
A15: Cisco | B15: =OFFSET('9'!$D$4,$A$3,0) -> 7360 | C15: =OFFSET('9'!$E$4,$A$3,0) -> 72773.299 | D15: =OFFSET('9'!$F$4,$A$3,0) -> 9.89 | E15: =OFFSET('9'!$E$66,$A$3,0) -> 46166 | F15: =OFFSET('9'!$F$66,$A$3,0) -> 6.27 | G15: =IFERROR('9'!$F$100*'Discipline Analysis'!$B15,"") -> 3900.8 | H15: ='9'!$F$100 -> 0.53 | I15: =IFERROR('9'!$F$98*'Discipline Analysis'!$B15,"") -> 8979.2 | J15: ='9'!$F$98 -> 1.22 | K15: =IFERROR('9'!$F$99*'Discipline Analysis'!$B15,"") -> 4195.2 | L15: ='9'!$F$99 -> 0.57 | M15: =OFFSET('9'!$E$35,$A$3,0) -> 7552 | N15: =OFFSET('9'!$F$35,$A$3,0) -> 1.03 | O15: =IFERROR('9'!$F$101*'Discipline Analysis'!$B15,"") -> 0 | P15: ='9'!$F$101 -> 0 | Q15: =IFERROR('9'!$F$102*'Discipline Analysis'!$B15,"") -> 0 | R15: ='9'!$F$102 -> 0 | S15: =IFERROR('9'!$F$103*'Discipline Analysis'!$B15,"") -> 1472 | T15: ='9'!$F$103 -> 0.2 | U15: =IFERROR('9'!$F$104*'Discipline Analysis'!$B15,"") -> 588.8 | V15: ='9'!$F$104 -> 0.08 | X15: Foreign Languages
A16: Clarendon | B16: =OFFSET('10'!$D$4,$A$3,0) -> 34368 | C16: =OFFSET('10'!$E$4,$A$3,0) -> 352163.33 | D16: =OFFSET('10'!$F$4,$A$3,0) -> 10.25 | E16: =OFFSET('10'!$E$66,$A$3,0) -> 173229 | F16: =OFFSET('10'!$F$66,$A$3,0) -> 5.04 | G16: =IFERROR('10'!$F$100*'Discipline Analysis'!$B16,"") -> 22339.2 | H16: ='10'!$F$100 -> 0.65 | I16: =IFERROR('10'!$F$98*'Discipline Analysis'!$B16,"") -> 45709.44 | J16: ='10'!$F$98 -> 1.33 | K16: =IFERROR('10'!$F$99*'Discipline Analysis'!$B16,"") -> 20620.8 | L16: ='10'!$F$99 -> 0.6 | M16: =OFFSET('10'!$E$35,$A$3,0) -> 70511 | N16: =OFFSET('10'!$F$35,$A$3,0) -> 2.05 | O16: =IFERROR('10'!$F$101*'Discipline Analysis'!$B16,"") -> 0 | P16: ='10'!$F$101 -> 0 | Q16: =IFERROR('10'!$F$102*'Discipline Analysis'!$B16,"") -> 0 | R16: ='10'!$F$102 -> 0 | S16: =IFERROR('10'!$F$103*'Discipline Analysis'!$B16,"") -> 17184 | T16: ='10'!$F$103 -> 0.5 | U16: =IFERROR('10'!$F$104*'Discipline Analysis'!$B16,"") -> 2749.44 | V16: ='10'!$F$104 -> 0.08 | X16: Health Occupations - Dental Assistants, Medical Lab, and Assoc. Degree Nursing
A17: Coastal Bend | B17: =OFFSET('11'!$D$4,$A$3,0) -> 0 | C17: =OFFSET('11'!$E$4,$A$3,0) -> 0 | D17: =OFFSET('11'!$F$4,$A$3,0) | E17: =OFFSET('11'!$E$66,$A$3,0) -> 0 | F17: =OFFSET('11'!$F$66,$A$3,0) | G17: =IFERROR('11'!$F$100*'Discipline Analysis'!$B17,"") | H17: ='11'!$F$100 | I17: =IFERROR('11'!$F$98*'Discipline Analysis'!$B17,"") | J17: ='11'!$F$98 | K17: =IFERROR('11'!$F$99*'Discipline Analysis'!$B17,"") | L17: ='11'!$F$99 | M17: =OFFSET('11'!$E$35,$A$3,0) -> 0 | N17: =OFFSET('11'!$F$35,$A$3,0) | O17: =IFERROR('11'!$F$101*'Discipline Analysis'!$B17,"") | P17: ='11'!$F$101 | Q17: =IFERROR('11'!$F$102*'Discipline Analysis'!$B17,"") | R17: ='11'!$F$102 | S17: =IFERROR('11'!$F$103*'Discipline Analysis'!$B17,"") | T17: ='11'!$F$103 | U17: =IFERROR('11'!$F$104*'Discipline Analysis'!$B17,"") | V17: ='11'!$F$104 | X17: Health Occupations - Dental Hygiene
A18: College Of The Mainland | B18: =OFFSET('12'!$D$4,$A$3,0) -> 3261 | C18: =OFFSET('12'!$E$4,$A$3,0) -> 24859.812 | D18: =OFFSET('12'!$F$4,$A$3,0) -> 7.62 | E18: =OFFSET('12'!$E$66,$A$3,0) -> 0 | F18: =OFFSET('12'!$F$66,$A$3,0) | G18: =IFERROR('12'!$F$100*'Discipline Analysis'!$B18,"") -> 4500.18 | H18: ='12'!$F$100 -> 1.38 | I18: =IFERROR('12'!$F$98*'Discipline Analysis'!$B18,"") -> 11772.21 | J18: ='12'!$F$98 -> 3.61 | K18: =IFERROR('12'!$F$99*'Discipline Analysis'!$B18,"") -> 5511.09 | L18: ='12'!$F$99 -> 1.69 | M18: =OFFSET('12'!$E$35,$A$3,0) -> 0 | N18: =OFFSET('12'!$F$35,$A$3,0) | O18: =IFERROR('12'!$F$101*'Discipline Analysis'!$B18,"") -> 0 | P18: ='12'!$F$101 -> 0 | Q18: =IFERROR('12'!$F$102*'Discipline Analysis'!$B18,"") -> 0 | R18: ='12'!$F$102 -> 0 | S18: =IFERROR('12'!$F$103*'Discipline Analysis'!$B18,"") -> 978.3 | T18: ='12'!$F$103 -> 0.3 | U18: =IFERROR('12'!$F$104*'Discipline Analysis'!$B18,"") -> 2119.65 | V18: ='12'!$F$104 -> 0.65 | X18: Health Occupations - Other
A19: Collin | B19: =OFFSET('13'!$D$4,$A$3,0) -> 95914 | C19: =OFFSET('13'!$E$4,$A$3,0) -> 632193.28 | D19: =OFFSET('13'!$F$4,$A$3,0) -> 6.59 | E19: =OFFSET('13'!$E$66,$A$3,0) -> 192392 | F19: =OFFSET('13'!$F$66,$A$3,0) -> 2.01 | G19: =IFERROR('13'!$F$100*'Discipline Analysis'!$B19,"") -> 80567.76 | H19: ='13'!$F$100 -> 0.84 | I19: =IFERROR('13'!$F$98*'Discipline Analysis'!$B19,"") -> 109341.96 | J19: ='13'!$F$98 -> 1.14 | K19: =IFERROR('13'!$F$99*'Discipline Analysis'!$B19,"") -> 73853.78 | L19: ='13'!$F$99 -> 0.77 | M19: =OFFSET('13'!$E$35,$A$3,0) -> 100001 | N19: =OFFSET('13'!$F$35,$A$3,0) -> 1.04 | O19: =IFERROR('13'!$F$101*'Discipline Analysis'!$B19,"") -> 0 | P19: ='13'!$F$101 -> 0 | Q19: =IFERROR('13'!$F$102*'Discipline Analysis'!$B19,"") -> 46038.72 | R19: ='13'!$F$102 -> 0.48 | S19: =IFERROR('13'!$F$103*'Discipline Analysis'!$B19,"") -> 21101.08 | T19: ='13'!$F$103 -> 0.22 | U19: =IFERROR('13'!$F$104*'Discipline Analysis'!$B19,"") -> 8632.26 | V19: ='13'!$F$104 -> 0.09 | X19: Health Occupations - Respiratory Therapy
A20: Dallas | B20: =OFFSET('14'!$D$4,$A$3,0) -> 104261 | C20: =OFFSET('14'!$E$4,$A$3,0) -> 1591788.7 | D20: =OFFSET('14'!$F$4,$A$3,0) -> 15.27 | E20: =OFFSET('14'!$E$66,$A$3,0) -> 597793 | F20: =OFFSET('14'!$F$66,$A$3,0) -> 5.73 | G20: =IFERROR('14'!$F$100*'Discipline Analysis'!$B20,"") -> 62556.6 | H20: ='14'!$F$100 -> 0.6 | I20: =IFERROR('14'!$F$98*'Discipline Analysis'!$B20,"") -> 179328.92 | J20: ='14'!$F$98 -> 1.72 | K20: =IFERROR('14'!$F$99*'Discipline Analysis'!$B20,"") -> 93834.9 | L20: ='14'!$F$99 -> 0.9 | M20: =OFFSET('14'!$E$35,$A$3,0) -> 631244 | N20: =OFFSET('14'!$F$35,$A$3,0) -> 6.05 | O20: =IFERROR('14'!$F$101*'Discipline Analysis'!$B20,"") -> 0 | P20: ='14'!$F$101 -> 0 | Q20: =IFERROR('14'!$F$102*'Discipline Analysis'!$B20,"") -> 0 | R20: ='14'!$F$102 -> 0 | S20: =IFERROR('14'!$F$103*'Discipline Analysis'!$B20,"") -> 12511.32 | T20: ='14'!$F$103 -> 0.12 | U20: =IFERROR('14'!$F$104*'Discipline Analysis'!$B20,"") -> 15639.15 | V20: ='14'!$F$104 -> 0.15 | X20: Health Occupations - Vocational Nursing
A21: Del Mar | B21: =OFFSET('15'!$D$4,$A$3,0) -> 704 | C21: =OFFSET('15'!$E$4,$A$3,0) -> 6691.7976 | D21: =OFFSET('15'!$F$4,$A$3,0) -> 9.51 | E21: =OFFSET('15'!$E$66,$A$3,0) -> 1000 | F21: =OFFSET('15'!$F$66,$A$3,0) -> 1.42 | G21: =IFERROR('15'!$F$100*'Discipline Analysis'!$B21,"") -> 711.04 | H21: ='15'!$F$100 -> 1.01 | I21: =IFERROR('15'!$F$98*'Discipline Analysis'!$B21,"") -> 1781.12 | J21: ='15'!$F$98 -> 2.53 | K21: =IFERROR('15'!$F$99*'Discipline Analysis'!$B21,"") -> 844.8 | L21: ='15'!$F$99 -> 1.2 | M21: =OFFSET('15'!$E$35,$A$3,0) -> 2058 | N21: =OFFSET('15'!$F$35,$A$3,0) -> 2.92 | O21: =IFERROR('15'!$F$101*'Discipline Analysis'!$B21,"") -> 0 | P21: ='15'!$F$101 -> 0 | Q21: =IFERROR('15'!$F$102*'Discipline Analysis'!$B21,"") -> 0 | R21: ='15'!$F$102 -> 0 | S21: =IFERROR('15'!$F$103*'Discipline Analysis'!$B21,"") -> 0 | T21: ='15'!$F$103 -> 0 | U21: =IFERROR('15'!$F$104*'Discipline Analysis'!$B21,"") -> 302.72 | V21: ='15'!$F$104 -> 0.43 | X21: Mathematics
A22: El Paso | B22: =OFFSET('16'!$D$4,$A$3,0) -> 3168 | C22: =OFFSET('16'!$E$4,$A$3,0) -> 27328.793 | D22: =OFFSET('16'!$F$4,$A$3,0) -> 8.63 | E22: =OFFSET('16'!$E$66,$A$3,0) -> 6704 | F22: =OFFSET('16'!$F$66,$A$3,0) -> 2.12 | G22: =IFERROR('16'!$F$100*'Discipline Analysis'!$B22,"") -> 4245.12 | H22: ='16'!$F$100 -> 1.34 | I22: =IFERROR('16'!$F$98*'Discipline Analysis'!$B22,"") -> 5797.44 | J22: ='16'!$F$98 -> 1.83 | K22: =IFERROR('16'!$F$99*'Discipline Analysis'!$B22,"") -> 2566.08 | L22: ='16'!$F$99 -> 0.81 | M22: =OFFSET('16'!$E$35,$A$3,0) -> 6496 | N22: =OFFSET('16'!$F$35,$A$3,0) -> 2.05 | O22: =IFERROR('16'!$F$101*'Discipline Analysis'!$B22,"") -> 0 | P22: ='16'!$F$101 -> 0 | Q22: =IFERROR('16'!$F$102*'Discipline Analysis'!$B22,"") -> 506.88 | R22: ='16'!$F$102 -> 0.16 | S22: =IFERROR('16'!$F$103*'Discipline Analysis'!$B22,"") -> 506.88 | T22: ='16'!$F$103 -> 0.16 | U22: =IFERROR('16'!$F$104*'Discipline Analysis'!$B22,"") -> 506.88 | V22: ='16'!$F$104 -> 0.16 | X22: Mechanics and Repairers - Automotive
A23: Frank Phillips | B23: =OFFSET('17'!$D$4,$A$3,0) -> 11064 | C23: =OFFSET('17'!$E$4,$A$3,0) -> 108051.72 | D23: =OFFSET('17'!$F$4,$A$3,0) -> 9.77 | E23: =OFFSET('17'!$E$66,$A$3,0) -> 45645 | F23: =OFFSET('17'!$F$66,$A$3,0) -> 4.13 | G23: =IFERROR('17'!$F$100*'Discipline Analysis'!$B23,"") -> 2212.8 | H23: ='17'!$F$100 -> 0.2 | I23: =IFERROR('17'!$F$98*'Discipline Analysis'!$B23,"") -> 26000.4 | J23: ='17'!$F$98 -> 2.35 | K23: =IFERROR('17'!$F$99*'Discipline Analysis'!$B23,"") -> 8076.72 | L23: ='17'!$F$99 -> 0.73 | M23: =OFFSET('17'!$E$35,$A$3,0) -> 22598 | N23: =OFFSET('17'!$F$35,$A$3,0) -> 2.04 | O23: =IFERROR('17'!$F$101*'Discipline Analysis'!$B23,"") -> 0 | P23: ='17'!$F$101 -> 0 | Q23: =IFERROR('17'!$F$102*'Discipline Analysis'!$B23,"") -> 1548.96 | R23: ='17'!$F$102 -> 0.14 | S23: =IFERROR('17'!$F$103*'Discipline Analysis'!$B23,"") -> 0 | T23: ='17'!$F$103 -> 0 | U23: =IFERROR('17'!$F$104*'Discipline Analysis'!$B23,"") -> 1880.88 | V23: ='17'!$F$104 -> 0.17 | X23: Mechanics and Repairers - Diesel, Aviation Mechanics, and Transportation Workers
A24: Galveston | B24: =OFFSET('18'!$D$4,$A$3,0) -> 0 | C24: =OFFSET('18'!$E$4,$A$3,0) -> 0 | D24: =OFFSET('18'!$F$4,$A$3,0) | E24: =OFFSET('18'!$E$66,$A$3,0) -> 0 | F24: =OFFSET('18'!$F$66,$A$3,0) | G24: =IFERROR('18'!$F$100*'Discipline Analysis'!$B24,"") | H24: ='18'!$F$100 | I24: =IFERROR('18'!$F$98*'Discipline Analysis'!$B24,"") | J24: ='18'!$F$98 | K24: =IFERROR('18'!$F$99*'Discipline Analysis'!$B24,"") | L24: ='18'!$F$99 | M24: =OFFSET('18'!$E$35,$A$3,0) -> 0 | N24: =OFFSET('18'!$F$35,$A$3,0) | O24: =IFERROR('18'!$F$101*'Discipline Analysis'!$B24,"") | P24: ='18'!$F$101 | Q24: =IFERROR('18'!$F$102*'Discipline Analysis'!$B24,"") | R24: ='18'!$F$102 | S24: =IFERROR('18'!$F$103*'Discipline Analysis'!$B24,"") | T24: ='18'!$F$103 | U24: =IFERROR('18'!$F$104*'Discipline Analysis'!$B24,"") | V24: ='18'!$F$104 | X24: Mechanics and Repairers - Electronics
A25: Grayson | B25: =OFFSET('19'!$D$4,$A$3,0) -> 14424 | C25: =OFFSET('19'!$E$4,$A$3,0) -> 128826.99 | D25: =OFFSET('19'!$F$4,$A$3,0) -> 8.93 | E25: =OFFSET('19'!$E$66,$A$3,0) -> 0 | F25: =OFFSET('19'!$F$66,$A$3,0) -> 0 | G25: =IFERROR('19'!$F$100*'Discipline Analysis'!$B25,"") -> 8077.44 | H25: ='19'!$F$100 -> 0.56 | I25: =IFERROR('19'!$F$98*'Discipline Analysis'!$B25,"") -> 21203.28 | J25: ='19'!$F$98 -> 1.47 | K25: =IFERROR('19'!$F$99*'Discipline Analysis'!$B25,"") -> 10529.52 | L25: ='19'!$F$99 -> 0.73 | M25: =OFFSET('19'!$E$35,$A$3,0) -> 84636 | N25: =OFFSET('19'!$F$35,$A$3,0) -> 5.87 | O25: =IFERROR('19'!$F$101*'Discipline Analysis'!$B25,"") -> 0 | P25: ='19'!$F$101 -> 0 | Q25: =IFERROR('19'!$F$102*'Discipline Analysis'!$B25,"") -> 0 | R25: ='19'!$F$102 -> 0 | S25: =IFERROR('19'!$F$103*'Discipline Analysis'!$B25,"") -> 1875.12 | T25: ='19'!$F$103 -> 0.13 | U25: =IFERROR('19'!$F$104*'Discipline Analysis'!$B25,"") -> 2596.32 | V25: ='19'!$F$104 -> 0.18 | X25: Physical Education and Fitness
A26: Hill | B26: =OFFSET('20'!$D$4,$A$3,0) -> 7008 | C26: =OFFSET('20'!$E$4,$A$3,0) -> 86424.601 | D26: =OFFSET('20'!$F$4,$A$3,0) -> 12.33 | E26: =OFFSET('20'!$E$66,$A$3,0) -> 56968 | F26: =OFFSET('20'!$F$66,$A$3,0) -> 8.13 | G26: =IFERROR('20'!$F$100*'Discipline Analysis'!$B26,"") -> 3433.92 | H26: ='20'!$F$100 -> 0.49 | I26: =IFERROR('20'!$F$98*'Discipline Analysis'!$B26,"") -> 11142.72 | J26: ='20'!$F$98 -> 1.59 | K26: =IFERROR('20'!$F$99*'Discipline Analysis'!$B26,"") -> 4695.36 | L26: ='20'!$F$99 -> 0.67 | M26: =OFFSET('20'!$E$35,$A$3,0) -> 10209 | N26: =OFFSET('20'!$F$35,$A$3,0) -> 1.46 | O26: =IFERROR('20'!$F$101*'Discipline Analysis'!$B26,"") -> 0 | P26: ='20'!$F$101 -> 0 | Q26: =IFERROR('20'!$F$102*'Discipline Analysis'!$B26,"") -> 0 | R26: ='20'!$F$102 -> 0 | S26: =IFERROR('20'!$F$103*'Discipline Analysis'!$B26,"") -> 0 | T26: ='20'!$F$103 -> 0 | U26: =IFERROR('20'!$F$104*'Discipline Analysis'!$B26,"") -> 0 | V26: ='20'!$F$104 -> 0 | X26: Protective Services and Public Administration
A27: Houston | B27: =OFFSET('21'!$D$4,$A$3,0) -> 81920 | C27: =OFFSET('21'!$E$4,$A$3,0) -> 685212.51 | D27: =OFFSET('21'!$F$4,$A$3,0) -> 8.36 | E27: =OFFSET('21'!$E$66,$A$3,0) -> 244844 | F27: =OFFSET('21'!$F$66,$A$3,0) -> 2.99 | G27: =IFERROR('21'!$F$100*'Discipline Analysis'!$B27,"") -> 71270.4 | H27: ='21'!$F$100 -> 0.87 | I27: =IFERROR('21'!$F$98*'Discipline Analysis'!$B27,"") -> 171212.8 | J27: ='21'!$F$98 -> 2.09 | K27: =IFERROR('21'!$F$99*'Discipline Analysis'!$B27,"") -> 82739.2 | L27: ='21'!$F$99 -> 1.01 | M27: =OFFSET('21'!$E$35,$A$3,0) -> 89839 | N27: =OFFSET('21'!$F$35,$A$3,0) -> 1.1 | O27: =IFERROR('21'!$F$101*'Discipline Analysis'!$B27,"") -> 0 | P27: ='21'!$F$101 -> 0 | Q27: =IFERROR('21'!$F$102*'Discipline Analysis'!$B27,"") -> 0 | R27: ='21'!$F$102 -> 0 | S27: =IFERROR('21'!$F$103*'Discipline Analysis'!$B27,"") -> 16384 | T27: ='21'!$F$103 -> 0.2 | U27: =IFERROR('21'!$F$104*'Discipline Analysis'!$B27,"") -> 9011.2 | V27: ='21'!$F$104 -> 0.11 | X27: Psychology, Social Sciences, and History
A28: Howard | B28: =OFFSET('22'!$D$4,$A$3,0) -> 95694 | C28: =OFFSET('22'!$E$4,$A$3,0) -> 571902.3 | D28: =OFFSET('22'!$F$4,$A$3,0) -> 5.98 | E28: =OFFSET('22'!$E$66,$A$3,0) -> 220532 | F28: =OFFSET('22'!$F$66,$A$3,0) -> 2.3 | G28: =IFERROR('22'!$F$100*'Discipline Analysis'!$B28,"") -> 48803.94 | H28: ='22'!$F$100 -> 0.51 | I28: =IFERROR('22'!$F$98*'Discipline Analysis'!$B28,"") -> 143541 | J28: ='22'!$F$98 -> 1.5 | K28: =IFERROR('22'!$F$99*'Discipline Analysis'!$B28,"") -> 65071.92 | L28: ='22'!$F$99 -> 0.68 | M28: =OFFSET('22'!$E$35,$A$3,0) -> 63441 | N28: =OFFSET('22'!$F$35,$A$3,0) -> 0.66 | O28: =IFERROR('22'!$F$101*'Discipline Analysis'!$B28,"") -> 0 | P28: ='22'!$F$101 -> 0 | Q28: =IFERROR('22'!$F$102*'Discipline Analysis'!$B28,"") -> 0 | R28: ='22'!$F$102 -> 0 | S28: =IFERROR('22'!$F$103*'Discipline Analysis'!$B28,"") -> 16267.98 | T28: ='22'!$F$103 -> 0.17 | U28: =IFERROR('22'!$F$104*'Discipline Analysis'!$B28,"") -> 13397.16 | V28: ='22'!$F$104 -> 0.14 | X28: Visual and Performing Arts
A29: Kilgore | B29: =OFFSET('23'!$D$4,$A$3,0) -> 8276 | C29: =OFFSET('23'!$E$4,$A$3,0) -> 88062.474 | D29: =OFFSET('23'!$F$4,$A$3,0) -> 10.64 | E29: =OFFSET('23'!$E$66,$A$3,0) -> 60825 | F29: =OFFSET('23'!$F$66,$A$3,0) -> 7.35 | G29: =IFERROR('23'!$F$100*'Discipline Analysis'!$B29,"") -> 5213.88 | H29: ='23'!$F$100 -> 0.63 | I29: =IFERROR('23'!$F$98*'Discipline Analysis'!$B29,"") -> 8110.48 | J29: ='23'!$F$98 -> 0.98 | K29: =IFERROR('23'!$F$99*'Discipline Analysis'!$B29,"") -> 3144.88 | L29: ='23'!$F$99 -> 0.38 | M29: =OFFSET('23'!$E$35,$A$3,0) -> 8852 | N29: =OFFSET('23'!$F$35,$A$3,0) -> 1.07 | O29: =IFERROR('23'!$F$101*'Discipline Analysis'!$B29,"") -> 0 | P29: ='23'!$F$101 -> 0 | Q29: =IFERROR('23'!$F$102*'Discipline Analysis'!$B29,"") -> 82.76 | R29: ='23'!$F$102 -> 0.01 | S29: =IFERROR('23'!$F$103*'Discipline Analysis'!$B29,"") -> 579.32 | T29: ='23'!$F$103 -> 0.07 | U29: =IFERROR('23'!$F$104*'Discipline Analysis'!$B29,"") -> 1158.64 | V29: ='23'!$F$104 -> 0.14 | X29: Developmental Education - Math
A30: Laredo | B30: =OFFSET('24'!$D$4,$A$3,0) -> 0 | C30: =OFFSET('24'!$E$4,$A$3,0) -> 0 | D30: =OFFSET('24'!$F$4,$A$3,0) | E30: =OFFSET('24'!$E$66,$A$3,0) -> 0 | F30: =OFFSET('24'!$F$66,$A$3,0) | G30: =IFERROR('24'!$F$100*'Discipline Analysis'!$B30,"") -> 0 | H30: ='24'!$F$100 -> 1.39 | I30: =IFERROR('24'!$F$98*'Discipline Analysis'!$B30,"") -> 0 | J30: ='24'!$F$98 -> 1.66 | K30: =IFERROR('24'!$F$99*'Discipline Analysis'!$B30,"") -> 0 | L30: ='24'!$F$99 -> 1.25 | M30: =OFFSET('24'!$E$35,$A$3,0) -> 0 | N30: =OFFSET('24'!$F$35,$A$3,0) | O30: =IFERROR('24'!$F$101*'Discipline Analysis'!$B30,"") -> 0 | P30: ='24'!$F$101 -> 0 | Q30: =IFERROR('24'!$F$102*'Discipline Analysis'!$B30,"") -> 0 | R30: ='24'!$F$102 -> 0.09 | S30: =IFERROR('24'!$F$103*'Discipline Analysis'!$B30,"") -> 0 | T30: ='24'!$F$103 -> 0.31 | U30: =IFERROR('24'!$F$104*'Discipline Analysis'!$B30,"") -> 0 | V30: ='24'!$F$104 -> 0.45 | X30: Developmental Education - Reading/Writing
A31: Lee | B31: =OFFSET('25'!$D$4,$A$3,0) -> 70176 | C31: =OFFSET('25'!$E$4,$A$3,0) -> 499710.74 | D31: =OFFSET('25'!$F$4,$A$3,0) -> 7.12 | E31: =OFFSET('25'!$E$66,$A$3,0) -> 142296 | F31: =OFFSET('25'!$F$66,$A$3,0) -> 2.03 | G31: =IFERROR('25'!$F$100*'Discipline Analysis'!$B31,"") -> 55439.04 | H31: ='25'!$F$100 -> 0.79 | I31: =IFERROR('25'!$F$98*'Discipline Analysis'!$B31,"") -> 172632.96 | J31: ='25'!$F$98 -> 2.46 | K31: =IFERROR('25'!$F$99*'Discipline Analysis'!$B31,"") -> 40000.32 | L31: ='25'!$F$99 -> 0.57 | M31: =OFFSET('25'!$E$35,$A$3,0) -> 41850 | N31: =OFFSET('25'!$F$35,$A$3,0) -> 0.6 | O31: =IFERROR('25'!$F$101*'Discipline Analysis'!$B31,"") -> 0 | P31: ='25'!$F$101 -> 0 | Q31: =IFERROR('25'!$F$102*'Discipline Analysis'!$B31,"") -> 0 | R31: ='25'!$F$102 -> 0 | S31: =IFERROR('25'!$F$103*'Discipline Analysis'!$B31,"") -> 14035.2 | T31: ='25'!$F$103 -> 0.2 | U31: =IFERROR('25'!$F$104*'Discipline Analysis'!$B31,"") -> 34386.24 | V31: ='25'!$F$104 -> 0.49 | X31: All Disciplines
A32: Lonestar | B32: =OFFSET('26'!$D$4,$A$3,0) -> 30852 | C32: =OFFSET('26'!$E$4,$A$3,0) -> 300475.79 | D32: =OFFSET('26'!$F$4,$A$3,0) -> 9.74 | E32: =OFFSET('26'!$E$66,$A$3,0) -> 134287 | F32: =OFFSET('26'!$F$66,$A$3,0) -> 4.35 | G32: =IFERROR('26'!$F$100*'Discipline Analysis'!$B32,"") -> 53682.48 | H32: ='26'!$F$100 -> 1.74 | I32: =IFERROR('26'!$F$98*'Discipline Analysis'!$B32,"") -> 47203.56 | J32: ='26'!$F$98 -> 1.53 | K32: =IFERROR('26'!$F$99*'Discipline Analysis'!$B32,"") -> 25298.64 | L32: ='26'!$F$99 -> 0.82 | M32: =OFFSET('26'!$E$35,$A$3,0) -> 29662 | N32: =OFFSET('26'!$F$35,$A$3,0) -> 0.96 | O32: =IFERROR('26'!$F$101*'Discipline Analysis'!$B32,"") -> 0 | P32: ='26'!$F$101 -> 0 | Q32: =IFERROR('26'!$F$102*'Discipline Analysis'!$B32,"") -> 0 | R32: ='26'!$F$102 -> 0 | S32: =IFERROR('26'!$F$103*'Discipline Analysis'!$B32,"") -> 3393.72 | T32: ='26'!$F$103 -> 0.11 | U32: =IFERROR('26'!$F$104*'Discipline Analysis'!$B32,"") -> 6787.44 | V32: ='26'!$F$104 -> 0.22
A33: Mclennan | B33: =OFFSET('27'!$D$4,$A$3,0) -> 33794 | C33: =OFFSET('27'!$E$4,$A$3,0) -> 560680.4 | D33: =OFFSET('27'!$F$4,$A$3,0) -> 16.59 | E33: =OFFSET('27'!$E$66,$A$3,0) -> 102560 | F33: =OFFSET('27'!$F$66,$A$3,0) -> 3.03 | G33: =IFERROR('27'!$F$100*'Discipline Analysis'!$B33,"") -> 13855.54 | H33: ='27'!$F$100 -> 0.41 | I33: =IFERROR('27'!$F$98*'Discipline Analysis'!$B33,"") -> 59815.38 | J33: ='27'!$F$98 -> 1.77 | K33: =IFERROR('27'!$F$99*'Discipline Analysis'!$B33,"") -> 18248.76 | L33: ='27'!$F$99 -> 0.54 | M33: =OFFSET('27'!$E$35,$A$3,0) -> 356288 | N33: =OFFSET('27'!$F$35,$A$3,0) -> 10.54 | O33: =IFERROR('27'!$F$101*'Discipline Analysis'!$B33,"") -> 0 | P33: ='27'!$F$101 -> 0 | Q33: =IFERROR('27'!$F$102*'Discipline Analysis'!$B33,"") -> 7434.68 | R33: ='27'!$F$102 -> 0.22 | S33: =IFERROR('27'!$F$103*'Discipline Analysis'!$B33,"") -> 0 | T33: ='27'!$F$103 -> 0 | U33: =IFERROR('27'!$F$104*'Discipline Analysis'!$B33,"") -> 2703.52 | V33: ='27'!$F$104 -> 0.08
A34: Midland | B34: =OFFSET('28'!$D$4,$A$3,0) -> 3984 | C34: =OFFSET('28'!$E$4,$A$3,0) -> 18818.726 | D34: =OFFSET('28'!$F$4,$A$3,0) -> 4.72 | E34: =OFFSET('28'!$E$66,$A$3,0) -> 2112 | F34: =OFFSET('28'!$F$66,$A$3,0) -> 0.53 | G34: =IFERROR('28'!$F$100*'Discipline Analysis'!$B34,"") -> 5856.48 | H34: ='28'!$F$100 -> 1.47 | I34: =IFERROR('28'!$F$98*'Discipline Analysis'!$B34,"") -> 5816.64 | J34: ='28'!$F$98 -> 1.46 | K34: =IFERROR('28'!$F$99*'Discipline Analysis'!$B34,"") -> 2709.12 | L34: ='28'!$F$99 -> 0.68 | M34: =OFFSET('28'!$E$35,$A$3,0) -> 236 | N34: =OFFSET('28'!$F$35,$A$3,0) -> 0.06 | O34: =IFERROR('28'!$F$101*'Discipline Analysis'!$B34,"") -> 0 | P34: ='28'!$F$101 -> 0 | Q34: =IFERROR('28'!$F$102*'Discipline Analysis'!$B34,"") -> 79.68 | R34: ='28'!$F$102 -> 0.02 | S34: =IFERROR('28'!$F$103*'Discipline Analysis'!$B34,"") -> 836.64 | T34: ='28'!$F$103 -> 0.21 | U34: =IFERROR('28'!$F$104*'Discipline Analysis'!$B34,"") -> 1155.36 | V34: ='28'!$F$104 -> 0.29
A35: Navarro | B35: =OFFSET('29'!$D$4,$A$3,0) -> 19696 | C35: =OFFSET('29'!$E$4,$A$3,0) -> 132332.93 | D35: =OFFSET('29'!$F$4,$A$3,0) -> 6.72 | E35: =OFFSET('29'!$E$66,$A$3,0) -> 65284 | F35: =OFFSET('29'!$F$66,$A$3,0) -> 3.31 | G35: =IFERROR('29'!$F$100*'Discipline Analysis'!$B35,"") -> 11423.68 | H35: ='29'!$F$100 -> 0.58 | I35: =IFERROR('29'!$F$98*'Discipline Analysis'!$B35,"") -> 17923.36 | J35: ='29'!$F$98 -> 0.91 | K35: =IFERROR('29'!$F$99*'Discipline Analysis'!$B35,"") -> 9651.04 | L35: ='29'!$F$99 -> 0.49 | M35: =OFFSET('29'!$E$35,$A$3,0) -> 24085 | N35: =OFFSET('29'!$F$35,$A$3,0) -> 1.22 | O35: =IFERROR('29'!$F$101*'Discipline Analysis'!$B35,"") -> 0 | P35: ='29'!$F$101 -> 0 | Q35: =IFERROR('29'!$F$102*'Discipline Analysis'!$B35,"") -> 0 | R35: ='29'!$F$102 -> 0 | S35: =IFERROR('29'!$F$103*'Discipline Analysis'!$B35,"") -> 787.84 | T35: ='29'!$F$103 -> 0.04 | U35: =IFERROR('29'!$F$104*'Discipline Analysis'!$B35,"") -> 3348.32 | V35: ='29'!$F$104 -> 0.17
A36: North Central Texas | B36: =OFFSET('30'!$D$4,$A$3,0) -> 64304 | C36: =OFFSET('30'!$E$4,$A$3,0) -> 590323.66 | D36: =OFFSET('30'!$F$4,$A$3,0) -> 9.18 | E36: =OFFSET('30'!$E$66,$A$3,0) -> 248234 | F36: =OFFSET('30'!$F$66,$A$3,0) -> 3.86 | G36: =IFERROR('30'!$F$100*'Discipline Analysis'!$B36,"") -> 45012.8 | H36: ='30'!$F$100 -> 0.7 | I36: =IFERROR('30'!$F$98*'Discipline Analysis'!$B36,"") -> 58516.64 | J36: ='30'!$F$98 -> 0.91 | K36: =IFERROR('30'!$F$99*'Discipline Analysis'!$B36,"") -> 25078.56 | L36: ='30'!$F$99 -> 0.39 | M36: =OFFSET('30'!$E$35,$A$3,0) -> 197485 | N36: =OFFSET('30'!$F$35,$A$3,0) -> 3.07 | O36: =IFERROR('30'!$F$101*'Discipline Analysis'!$B36,"") -> 1929.12 | P36: ='30'!$F$101 -> 0.03 | Q36: =IFERROR('30'!$F$102*'Discipline Analysis'!$B36,"") -> 0 | R36: ='30'!$F$102 -> 0 | S36: =IFERROR('30'!$F$103*'Discipline Analysis'!$B36,"") -> 9645.6 | T36: ='30'!$F$103 -> 0.15 | U36: =IFERROR('30'!$F$104*'Discipline Analysis'!$B36,"") -> 4501.28 | V36: ='30'!$F$104 -> 0.07
A37: Northeast Texas | B37: =OFFSET('31'!$D$4,$A$3,0) -> 13040 | C37: =OFFSET('31'!$E$4,$A$3,0) -> 210854.58 | D37: =OFFSET('31'!$F$4,$A$3,0) -> 16.17 | E37: =OFFSET('31'!$E$66,$A$3,0) -> 94667 | F37: =OFFSET('31'!$F$66,$A$3,0) -> 7.26 | G37: =IFERROR('31'!$F$100*'Discipline Analysis'!$B37,"") -> 8606.4 | H37: ='31'!$F$100 -> 0.66 | I37: =IFERROR('31'!$F$98*'Discipline Analysis'!$B37,"") -> 25297.6 | J37: ='31'!$F$98 -> 1.94 | K37: =IFERROR('31'!$F$99*'Discipline Analysis'!$B37,"") -> 6780.8 | L37: ='31'!$F$99 -> 0.52 | M37: =OFFSET('31'!$E$35,$A$3,0) -> 73406 | N37: =OFFSET('31'!$F$35,$A$3,0) -> 5.63 | O37: =IFERROR('31'!$F$101*'Discipline Analysis'!$B37,"") -> 0 | P37: ='31'!$F$101 -> 0 | Q37: =IFERROR('31'!$F$102*'Discipline Analysis'!$B37,"") -> 0 | R37: ='31'!$F$102 -> 0 | S37: =IFERROR('31'!$F$103*'Discipline Analysis'!$B37,"") -> 0 | T37: ='31'!$F$103 -> 0 | U37: =IFERROR('31'!$F$104*'Discipline Analysis'!$B37,"") -> 2086.4 | V37: ='31'!$F$104 -> 0.16
A38: Odessa | B38: =OFFSET('32'!$D$4,$A$3,0) -> 7768 | C38: =OFFSET('32'!$E$4,$A$3,0) -> 95161.075 | D38: =OFFSET('32'!$F$4,$A$3,0) -> 12.25 | E38: =OFFSET('32'!$E$66,$A$3,0) -> 51777 | F38: =OFFSET('32'!$F$66,$A$3,0) -> 6.67 | G38: =IFERROR('32'!$F$100*'Discipline Analysis'!$B38,"") -> 8389.44 | H38: ='32'!$F$100 -> 1.08 | I38: =IFERROR('32'!$F$98*'Discipline Analysis'!$B38,"") -> 12894.88 | J38: ='32'!$F$98 -> 1.66 | K38: =IFERROR('32'!$F$99*'Discipline Analysis'!$B38,"") -> 7301.92 | L38: ='32'!$F$99 -> 0.94 | M38: =OFFSET('32'!$E$35,$A$3,0) -> 8165 | N38: =OFFSET('32'!$F$35,$A$3,0) -> 1.05 | O38: =IFERROR('32'!$F$101*'Discipline Analysis'!$B38,"") -> 0 | P38: ='32'!$F$101 -> 0 | Q38: =IFERROR('32'!$F$102*'Discipline Analysis'!$B38,"") -> 2097.36 | R38: ='32'!$F$102 -> 0.27 | S38: =IFERROR('32'!$F$103*'Discipline Analysis'!$B38,"") -> 1631.28 | T38: ='32'!$F$103 -> 0.21 | U38: =IFERROR('32'!$F$104*'Discipline Analysis'!$B38,"") -> 2874.16 | V38: ='32'!$F$104 -> 0.37
A39: Panola | B39: =OFFSET('33'!$D$4,$A$3,0) -> 8821 | C39: =OFFSET('33'!$E$4,$A$3,0) -> 57031.884 | D39: =OFFSET('33'!$F$4,$A$3,0) -> 6.47 | E39: =OFFSET('33'!$E$66,$A$3,0) -> 9302 | F39: =OFFSET('33'!$F$66,$A$3,0) -> 1.05 | G39: =IFERROR('33'!$F$100*'Discipline Analysis'!$B39,"") -> 13231.5 | H39: ='33'!$F$100 -> 1.5 | I39: =IFERROR('33'!$F$98*'Discipline Analysis'!$B39,"") -> 13319.71 | J39: ='33'!$F$98 -> 1.51 | K39: =IFERROR('33'!$F$99*'Discipline Analysis'!$B39,"") -> 7056.8 | L39: ='33'!$F$99 -> 0.8 | M39: =OFFSET('33'!$E$35,$A$3,0) -> 9845 | N39: =OFFSET('33'!$F$35,$A$3,0) -> 1.12 | O39: =IFERROR('33'!$F$101*'Discipline Analysis'!$B39,"") -> 0 | P39: ='33'!$F$101 -> 0 | Q39: =IFERROR('33'!$F$102*'Discipline Analysis'!$B39,"") -> 0 | R39: ='33'!$F$102 -> 0 | S39: =IFERROR('33'!$F$103*'Discipline Analysis'!$B39,"") -> 1852.41 | T39: ='33'!$F$103 -> 0.21 | U39: =IFERROR('33'!$F$104*'Discipline Analysis'!$B39,"") -> 2469.88 | V39: ='33'!$F$104 -> 0.28
A40: Paris | B40: =OFFSET('34'!$D$4,$A$3,0) -> 4304 | C40: =OFFSET('34'!$E$4,$A$3,0) -> 62533.139 | D40: =OFFSET('34'!$F$4,$A$3,0) -> 14.53 | E40: =OFFSET('34'!$E$66,$A$3,0) -> 41804 | F40: =OFFSET('34'!$F$66,$A$3,0) -> 9.71 | G40: =IFERROR('34'!$F$100*'Discipline Analysis'!$B40,"") -> 1807.68 | H40: ='34'!$F$100 -> 0.42 | I40: =IFERROR('34'!$F$98*'Discipline Analysis'!$B40,"") -> 4088.8 | J40: ='34'!$F$98 -> 0.95 | K40: =IFERROR('34'!$F$99*'Discipline Analysis'!$B40,"") -> 2152 | L40: ='34'!$F$99 -> 0.5 | M40: =OFFSET('34'!$E$35,$A$3,0) -> 12046 | N40: =OFFSET('34'!$F$35,$A$3,0) -> 2.8 | O40: =IFERROR('34'!$F$101*'Discipline Analysis'!$B40,"") -> 0 | P40: ='34'!$F$101 -> 0 | Q40: =IFERROR('34'!$F$102*'Discipline Analysis'!$B40,"") -> 0 | R40: ='34'!$F$102 -> 0 | S40: =IFERROR('34'!$F$103*'Discipline Analysis'!$B40,"") -> 0 | T40: ='34'!$F$103 -> 0 | U40: =IFERROR('34'!$F$104*'Discipline Analysis'!$B40,"") -> 602.56 | V40: ='34'!$F$104 -> 0.14
A41: Ranger | B41: =OFFSET('35'!$D$4,$A$3,0) -> 2112 | C41: =OFFSET('35'!$E$4,$A$3,0) -> 15390.999 | D41: =OFFSET('35'!$F$4,$A$3,0) -> 7.29 | E41: =OFFSET('35'!$E$66,$A$3,0) -> 6210 | F41: =OFFSET('35'!$F$66,$A$3,0) -> 2.94 | G41: =IFERROR('35'!$F$100*'Discipline Analysis'!$B41,"") -> 612.48 | H41: ='35'!$F$100 -> 0.29 | I41: =IFERROR('35'!$F$98*'Discipline Analysis'!$B41,"") -> 3442.56 | J41: ='35'!$F$98 -> 1.63 | K41: =IFERROR('35'!$F$99*'Discipline Analysis'!$B41,"") -> 1056 | L41: ='35'!$F$99 -> 0.5 | M41: =OFFSET('35'!$E$35,$A$3,0) -> 2777 | N41: =OFFSET('35'!$F$35,$A$3,0) -> 1.31 | O41: =IFERROR('35'!$F$101*'Discipline Analysis'!$B41,"") -> 0 | P41: ='35'!$F$101 -> 0 | Q41: =IFERROR('35'!$F$102*'Discipline Analysis'!$B41,"") -> 612.48 | R41: ='35'!$F$102 -> 0.29 | S41: =IFERROR('35'!$F$103*'Discipline Analysis'!$B41,"") -> 464.64 | T41: ='35'!$F$103 -> 0.22 | U41: =IFERROR('35'!$F$104*'Discipline Analysis'!$B41,"") -> 190.08 | V41: ='35'!$F$104 -> 0.09
A42: San Jacinto | B42: =OFFSET('36'!$D$4,$A$3,0) -> 12768 | C42: =OFFSET('36'!$E$4,$A$3,0) -> 100379.71 | D42: =OFFSET('36'!$F$4,$A$3,0) -> 7.86 | E42: =OFFSET('36'!$E$66,$A$3,0) -> 34040 | F42: =OFFSET('36'!$F$66,$A$3,0) -> 2.67 | G42: =IFERROR('36'!$F$100*'Discipline Analysis'!$B42,"") -> 11874.24 | H42: ='36'!$F$100 -> 0.93 | I42: =IFERROR('36'!$F$98*'Discipline Analysis'!$B42,"") -> 18002.88 | J42: ='36'!$F$98 -> 1.41 | K42: =IFERROR('36'!$F$99*'Discipline Analysis'!$B42,"") -> 11108.16 | L42: ='36'!$F$99 -> 0.87 | M42: =OFFSET('36'!$E$35,$A$3,0) -> 21872 | N42: =OFFSET('36'!$F$35,$A$3,0) -> 1.71 | O42: =IFERROR('36'!$F$101*'Discipline Analysis'!$B42,"") -> 0 | P42: ='36'!$F$101 -> 0 | Q42: =IFERROR('36'!$F$102*'Discipline Analysis'!$B42,"") -> 0 | R42: ='36'!$F$102 -> 0 | S42: =IFERROR('36'!$F$103*'Discipline Analysis'!$B42,"") -> 0 | T42: ='36'!$F$103 -> 0 | U42: =IFERROR('36'!$F$104*'Discipline Analysis'!$B42,"") -> 3575.04 | V42: ='36'!$F$104 -> 0.28
A43: South Plains | B43: =OFFSET('37'!$D$4,$A$3,0) -> 29868 | C43: =OFFSET('37'!$E$4,$A$3,0) -> 332866.43 | D43: =OFFSET('37'!$F$4,$A$3,0) -> 11.14 | E43: =OFFSET('37'!$E$66,$A$3,0) -> 223816 | F43: =OFFSET('37'!$F$66,$A$3,0) -> 7.49 | G43: =IFERROR('37'!$F$100*'Discipline Analysis'!$B43,"") -> 11051.16 | H43: ='37'!$F$100 -> 0.37 | I43: =IFERROR('37'!$F$98*'Discipline Analysis'!$B43,"") -> 24193.08 | J43: ='37'!$F$98 -> 0.81 | K43: =IFERROR('37'!$F$99*'Discipline Analysis'!$B43,"") -> 24193.08 | L43: ='37'!$F$99 -> 0.81 | M43: =OFFSET('37'!$E$35,$A$3,0) -> 34716 | N43: =OFFSET('37'!$F$35,$A$3,0) -> 1.16 | O43: =IFERROR('37'!$F$101*'Discipline Analysis'!$B43,"") -> 0 | P43: ='37'!$F$101 -> 0 | Q43: =IFERROR('37'!$F$102*'Discipline Analysis'!$B43,"") -> 896.04 | R43: ='37'!$F$102 -> 0.03 | S43: =IFERROR('37'!$F$103*'Discipline Analysis'!$B43,"") -> 5077.56 | T43: ='37'!$F$103 -> 0.17 | U43: =IFERROR('37'!$F$104*'Discipline Analysis'!$B43,"") -> 9259.08 | V43: ='37'!$F$104 -> 0.31
A44: South Texas | B44: =OFFSET('38'!$D$4,$A$3,0) -> 21648 | C44: =OFFSET('38'!$E$4,$A$3,0) -> 153312.61 | D44: =OFFSET('38'!$F$4,$A$3,0) -> 7.08 | E44: =OFFSET('38'!$E$66,$A$3,0) -> 58294 | F44: =OFFSET('38'!$F$66,$A$3,0) -> 2.69 | G44: =IFERROR('38'!$F$100*'Discipline Analysis'!$B44,"") -> 14504.16 | H44: ='38'!$F$100 -> 0.67 | I44: =IFERROR('38'!$F$98*'Discipline Analysis'!$B44,"") -> 35502.72 | J44: ='38'!$F$98 -> 1.64 | K44: =IFERROR('38'!$F$99*'Discipline Analysis'!$B44,"") -> 15803.04 | L44: ='38'!$F$99 -> 0.73 | M44: =OFFSET('38'!$E$35,$A$3,0) -> 19094 | N44: =OFFSET('38'!$F$35,$A$3,0) -> 0.88 | O44: =IFERROR('38'!$F$101*'Discipline Analysis'!$B44,"") -> 0 | P44: ='38'!$F$101 -> 0 | Q44: =IFERROR('38'!$F$102*'Discipline Analysis'!$B44,"") -> 0 | R44: ='38'!$F$102 -> 0 | S44: =IFERROR('38'!$F$103*'Discipline Analysis'!$B44,"") -> 4979.04 | T44: ='38'!$F$103 -> 0.23 | U44: =IFERROR('38'!$F$104*'Discipline Analysis'!$B44,"") -> 4979.04 | V44: ='38'!$F$104 -> 0.23
A45: Southwest Texas | B45: =OFFSET('39'!$D$4,$A$3,0) -> 20672 | C45: =OFFSET('39'!$E$4,$A$3,0) -> 204077.6 | D45: =OFFSET('39'!$F$4,$A$3,0) -> 9.87 | E45: =OFFSET('39'!$E$66,$A$3,0) -> 108329 | F45: =OFFSET('39'!$F$66,$A$3,0) -> 5.24 | G45: =IFERROR('39'!$F$100*'Discipline Analysis'!$B45,"") -> 18398.08 | H45: ='39'!$F$100 -> 0.89 | I45: =IFERROR('39'!$F$98*'Discipline Analysis'!$B45,"") -> 31834.88 | J45: ='39'!$F$98 -> 1.54 | K45: =IFERROR('39'!$F$99*'Discipline Analysis'!$B45,"") -> 12196.48 | L45: ='39'!$F$99 -> 0.59 | M45: =OFFSET('39'!$E$35,$A$3,0) -> 26923 | N45: =OFFSET('39'!$F$35,$A$3,0) -> 1.3 | O45: =IFERROR('39'!$F$101*'Discipline Analysis'!$B45,"") -> 0 | P45: ='39'!$F$101 -> 0 | Q45: =IFERROR('39'!$F$102*'Discipline Analysis'!$B45,"") -> 0 | R45: ='39'!$F$102 -> 0 | S45: =IFERROR('39'!$F$103*'Discipline Analysis'!$B45,"") -> 3100.8 | T45: ='39'!$F$103 -> 0.15 | U45: =IFERROR('39'!$F$104*'Discipline Analysis'!$B45,"") -> 3100.8 | V45: ='39'!$F$104 -> 0.15
A46: Tarrant | B46: =OFFSET('40'!$D$4,$A$3,0) -> 27236 | C46: =OFFSET('40'!$E$4,$A$3,0) -> 259133.15 | D46: =OFFSET('40'!$F$4,$A$3,0) -> 9.51 | E46: =OFFSET('40'!$E$66,$A$3,0) -> 99287 | F46: =OFFSET('40'!$F$66,$A$3,0) -> 3.65 | G46: =IFERROR('40'!$F$100*'Discipline Analysis'!$B46,"") -> 19065.2 | H46: ='40'!$F$100 -> 0.7 | I46: =IFERROR('40'!$F$98*'Discipline Analysis'!$B46,"") -> 30776.68 | J46: ='40'!$F$98 -> 1.13 | K46: =IFERROR('40'!$F$99*'Discipline Analysis'!$B46,"") -> 21788.8 | L46: ='40'!$F$99 -> 0.8 | M46: =OFFSET('40'!$E$35,$A$3,0) -> 74142 | N46: =OFFSET('40'!$F$35,$A$3,0) -> 2.72 | O46: =IFERROR('40'!$F$101*'Discipline Analysis'!$B46,"") -> 0 | P46: ='40'!$F$101 -> 0 | Q46: =IFERROR('40'!$F$102*'Discipline Analysis'!$B46,"") -> 817.08 | R46: ='40'!$F$102 -> 0.03 | S46: =IFERROR('40'!$F$103*'Discipline Analysis'!$B46,"") -> 4357.76 | T46: ='40'!$F$103 -> 0.16 | U46: =IFERROR('40'!$F$104*'Discipline Analysis'!$B46,"") -> 8715.52 | V46: ='40'!$F$104 -> 0.32
A47: Temple | B47: =OFFSET('41'!$D$4,$A$3,0) -> 19984 | C47: =OFFSET('41'!$E$4,$A$3,0) -> 144921.83 | D47: =OFFSET('41'!$F$4,$A$3,0) -> 7.25 | E47: =OFFSET('41'!$E$66,$A$3,0) -> 66122 | F47: =OFFSET('41'!$F$66,$A$3,0) -> 3.31 | G47: =IFERROR('41'!$F$100*'Discipline Analysis'!$B47,"") -> 12989.6 | H47: ='41'!$F$100 -> 0.65 | I47: =IFERROR('41'!$F$98*'Discipline Analysis'!$B47,"") -> 35771.36 | J47: ='41'!$F$98 -> 1.79 | K47: =IFERROR('41'!$F$99*'Discipline Analysis'!$B47,"") -> 10791.36 | L47: ='41'!$F$99 -> 0.54 | M47: =OFFSET('41'!$E$35,$A$3,0) -> 12321 | N47: =OFFSET('41'!$F$35,$A$3,0) -> 0.62 | O47: =IFERROR('41'!$F$101*'Discipline Analysis'!$B47,"") -> 0 | P47: ='41'!$F$101 -> 0 | Q47: =IFERROR('41'!$F$102*'Discipline Analysis'!$B47,"") -> 1998.4 | R47: ='41'!$F$102 -> 0.1 | S47: =IFERROR('41'!$F$103*'Discipline Analysis'!$B47,"") -> 0 | T47: ='41'!$F$103 -> 0 | U47: =IFERROR('41'!$F$104*'Discipline Analysis'!$B47,"") -> 4996 | V47: ='41'!$F$104 -> 0.25
A48: Texarkana | B48: =OFFSET('42'!$D$4,$A$3,0) -> 22171 | C48: =OFFSET('42'!$E$4,$A$3,0) -> 194644.53 | D48: =OFFSET('42'!$F$4,$A$3,0) -> 8.78 | E48: =OFFSET('42'!$E$66,$A$3,0) -> 98888 | F48: =OFFSET('42'!$F$66,$A$3,0) -> 4.46 | G48: =IFERROR('42'!$F$100*'Discipline Analysis'!$B48,"") -> 12859.18 | H48: ='42'!$F$100 -> 0.58 | I48: =IFERROR('42'!$F$98*'Discipline Analysis'!$B48,"") -> 16406.54 | J48: ='42'!$F$98 -> 0.74 | K48: =IFERROR('42'!$F$99*'Discipline Analysis'!$B48,"") -> 7316.43 | L48: ='42'!$F$99 -> 0.33 | M48: =OFFSET('42'!$E$35,$A$3,0) -> 48204 | N48: =OFFSET('42'!$F$35,$A$3,0) -> 2.17 | O48: =IFERROR('42'!$F$101*'Discipline Analysis'!$B48,"") -> 0 | P48: ='42'!$F$101 -> 0 | Q48: =IFERROR('42'!$F$102*'Discipline Analysis'!$B48,"") -> 443.42 | R48: ='42'!$F$102 -> 0.02 | S48: =IFERROR('42'!$F$103*'Discipline Analysis'!$B48,"") -> 7759.85 | T48: ='42'!$F$103 -> 0.35 | U48: =IFERROR('42'!$F$104*'Discipline Analysis'!$B48,"") -> 2882.23 | V48: ='42'!$F$104 -> 0.13
A49: Texas Southmost | B49: =OFFSET('43'!$D$4,$A$3,0) -> 0 | C49: =OFFSET('43'!$E$4,$A$3,0) -> 0 | D49: =OFFSET('43'!$F$4,$A$3,0) | E49: =OFFSET('43'!$E$66,$A$3,0) -> 0 | F49: =OFFSET('43'!$F$66,$A$3,0) | G49: =IFERROR('43'!$F$100*'Discipline Analysis'!$B49,"") | H49: ='43'!$F$100 | I49: =IFERROR('43'!$F$98*'Discipline Analysis'!$B49,"") | J49: ='43'!$F$98 | K49: =IFERROR('43'!$F$99*'Discipline Analysis'!$B49,"") | L49: ='43'!$F$99 | M49: =OFFSET('43'!$E$35,$A$3,0) -> 0 | N49: =OFFSET('43'!$F$35,$A$3,0) | O49: =IFERROR('43'!$F$101*'Discipline Analysis'!$B49,"") | P49: ='43'!$F$101 | Q49: =IFERROR('43'!$F$102*'Discipline Analysis'!$B49,"") | R49: ='43'!$F$102 | S49: =IFERROR('43'!$F$103*'Discipline Analysis'!$B49,"") | T49: ='43'!$F$103 | U49: =IFERROR('43'!$F$104*'Discipline Analysis'!$B49,"") | V49: ='43'!$F$104
A50: Trinity Valley | B50: =OFFSET('44'!$D$4,$A$3,0) -> 74336 | C50: =OFFSET('44'!$E$4,$A$3,0) -> 444453.83 | D50: =OFFSET('44'!$F$4,$A$3,0) -> 5.98 | E50: =OFFSET('44'!$E$66,$A$3,0) -> 219453 | F50: =OFFSET('44'!$F$66,$A$3,0) -> 2.95 | G50: =IFERROR('44'!$F$100*'Discipline Analysis'!$B50,"") -> 55008.64 | H50: ='44'!$F$100 -> 0.74 | I50: =IFERROR('44'!$F$98*'Discipline Analysis'!$B50,"") -> 46831.68 | J50: ='44'!$F$98 -> 0.63 | K50: =IFERROR('44'!$F$99*'Discipline Analysis'!$B50,"") -> 37911.36 | L50: ='44'!$F$99 -> 0.51 | M50: =OFFSET('44'!$E$35,$A$3,0) -> 62522 | N50: =OFFSET('44'!$F$35,$A$3,0) -> 0.84 | O50: =IFERROR('44'!$F$101*'Discipline Analysis'!$B50,"") -> 0 | P50: ='44'!$F$101 -> 0 | Q50: =IFERROR('44'!$F$102*'Discipline Analysis'!$B50,"") -> 0 | R50: ='44'!$F$102 -> 0 | S50: =IFERROR('44'!$F$103*'Discipline Analysis'!$B50,"") -> 8176.96 | T50: ='44'!$F$103 -> 0.11 | U50: =IFERROR('44'!$F$104*'Discipline Analysis'!$B50,"") -> 14867.2 | V50: ='44'!$F$104 -> 0.2
A51: Tyler | B51: =OFFSET('45'!$D$4,$A$3,0) -> 37562 | C51: =OFFSET('45'!$E$4,$A$3,0) -> 193963.08 | D51: =OFFSET('45'!$F$4,$A$3,0) -> 5.16 | E51: =OFFSET('45'!$E$66,$A$3,0) -> 43859 | F51: =OFFSET('45'!$F$66,$A$3,0) -> 1.17 | G51: =IFERROR('45'!$F$100*'Discipline Analysis'!$B51,"") -> 18781 | H51: ='45'!$F$100 -> 0.5 | I51: =IFERROR('45'!$F$98*'Discipline Analysis'!$B51,"") -> 45825.64 | J51: ='45'!$F$98 -> 1.22 | K51: =IFERROR('45'!$F$99*'Discipline Analysis'!$B51,"") -> 36435.14 | L51: ='45'!$F$99 -> 0.97 | M51: =OFFSET('45'!$E$35,$A$3,0) -> 26365 | N51: =OFFSET('45'!$F$35,$A$3,0) -> 0.7 | O51: =IFERROR('45'!$F$101*'Discipline Analysis'!$B51,"") -> 0 | P51: ='45'!$F$101 -> 0 | Q51: =IFERROR('45'!$F$102*'Discipline Analysis'!$B51,"") -> 7136.78 | R51: ='45'!$F$102 -> 0.19 | S51: =IFERROR('45'!$F$103*'Discipline Analysis'!$B51,"") -> 5634.3 | T51: ='45'!$F$103 -> 0.15 | U51: =IFERROR('45'!$F$104*'Discipline Analysis'!$B51,"") -> 10141.74 | V51: ='45'!$F$104 -> 0.27
A52: Vernon | B52: =OFFSET('46'!$D$4,$A$3,0) -> 0 | C52: =OFFSET('46'!$E$4,$A$3,0) -> 0 | D52: =OFFSET('46'!$F$4,$A$3,0) | E52: =OFFSET('46'!$E$66,$A$3,0) -> 0 | F52: =OFFSET('46'!$F$66,$A$3,0) | G52: =IFERROR('46'!$F$100*'Discipline Analysis'!$B52,"") | H52: ='46'!$F$100 | I52: =IFERROR('46'!$F$98*'Discipline Analysis'!$B52,"") | J52: ='46'!$F$98 | K52: =IFERROR('46'!$F$99*'Discipline Analysis'!$B52,"") | L52: ='46'!$F$99 | M52: =OFFSET('46'!$E$35,$A$3,0) -> 0 | N52: =OFFSET('46'!$F$35,$A$3,0) | O52: =IFERROR('46'!$F$101*'Discipline Analysis'!$B52,"") | P52: ='46'!$F$101 | Q52: =IFERROR('46'!$F$102*'Discipline Analysis'!$B52,"") | R52: ='46'!$F$102 | S52: =IFERROR('46'!$F$103*'Discipline Analysis'!$B52,"") | T52: ='46'!$F$103 | U52: =IFERROR('46'!$F$104*'Discipline Analysis'!$B52,"") | V52: ='46'!$F$104
A53: Victoria | B53: =OFFSET('47'!$D$4,$A$3,0) -> 10752 | C53: =OFFSET('47'!$E$4,$A$3,0) -> 81038.498 | D53: =OFFSET('47'!$F$4,$A$3,0) -> 7.54 | E53: =OFFSET('47'!$E$66,$A$3,0) -> 2100 | F53: =OFFSET('47'!$F$66,$A$3,0) -> 0.2 | G53: =IFERROR('47'!$F$100*'Discipline Analysis'!$B53,"") -> 8494.08 | H53: ='47'!$F$100 -> 0.79 | I53: =IFERROR('47'!$F$98*'Discipline Analysis'!$B53,"") -> 15052.8 | J53: ='47'!$F$98 -> 1.4 | K53: =IFERROR('47'!$F$99*'Discipline Analysis'!$B53,"") -> 8494.08 | L53: ='47'!$F$99 -> 0.79 | M53: =OFFSET('47'!$E$35,$A$3,0) -> 42483 | N53: =OFFSET('47'!$F$35,$A$3,0) -> 3.95 | O53: =IFERROR('47'!$F$101*'Discipline Analysis'!$B53,"") -> 0 | P53: ='47'!$F$101 -> 0 | Q53: =IFERROR('47'!$F$102*'Discipline Analysis'!$B53,"") -> 430.08 | R53: ='47'!$F$102 -> 0.04 | S53: =IFERROR('47'!$F$103*'Discipline Analysis'!$B53,"") -> 1290.24 | T53: ='47'!$F$103 -> 0.12 | U53: =IFERROR('47'!$F$104*'Discipline Analysis'!$B53,"") -> 2688 | V53: ='47'!$F$104 -> 0.25
A54: Weatherford | B54: =OFFSET('48'!$D$4,$A$3,0) -> 19216 | C54: =OFFSET('48'!$E$4,$A$3,0) -> 244034.91 | D54: =OFFSET('48'!$F$4,$A$3,0) -> 12.7 | E54: =OFFSET('48'!$E$66,$A$3,0) -> 71696 | F54: =OFFSET('48'!$F$66,$A$3,0) -> 3.73 | G54: =IFERROR('48'!$F$100*'Discipline Analysis'!$B54,"") -> 10568.8 | H54: ='48'!$F$100 -> 0.55 | I54: =IFERROR('48'!$F$98*'Discipline Analysis'!$B54,"") -> 49000.8 | J54: ='48'!$F$98 -> 2.55 | K54: =IFERROR('48'!$F$99*'Discipline Analysis'!$B54,"") -> 13259.04 | L54: ='48'!$F$99 -> 0.69 | M54: =OFFSET('48'!$E$35,$A$3,0) -> 95429 | N54: =OFFSET('48'!$F$35,$A$3,0) -> 4.97 | O54: =IFERROR('48'!$F$101*'Discipline Analysis'!$B54,"") -> 0 | P54: ='48'!$F$101 -> 0 | Q54: =IFERROR('48'!$F$102*'Discipline Analysis'!$B54,"") -> 0 | R54: ='48'!$F$102 -> 0 | S54: =IFERROR('48'!$F$103*'Discipline Analysis'!$B54,"") -> 2498.08 | T54: ='48'!$F$103 -> 0.13 | U54: =IFERROR('48'!$F$104*'Discipline Analysis'!$B54,"") -> 1729.44 | V54: ='48'!$F$104 -> 0.09
A55: Western Texas | B55: =OFFSET('49'!$D$4,$A$3,0) -> 75073 | C55: =OFFSET('49'!$E$4,$A$3,0) -> 580967.31 | D55: =OFFSET('49'!$F$4,$A$3,0) -> 7.74 | E55: =OFFSET('49'!$E$66,$A$3,0) -> 244979 | F55: =OFFSET('49'!$F$66,$A$3,0) -> 3.26 | G55: =IFERROR('49'!$F$100*'Discipline Analysis'!$B55,"") -> 57055.48 | H55: ='49'!$F$100 -> 0.76 | I55: =IFERROR('49'!$F$98*'Discipline Analysis'!$B55,"") -> 150146 | J55: ='49'!$F$98 -> 2 | K55: =IFERROR('49'!$F$99*'Discipline Analysis'!$B55,"") -> 28527.74 | L55: ='49'!$F$99 -> 0.38 | M55: =OFFSET('49'!$E$35,$A$3,0) -> 73932 | N55: =OFFSET('49'!$F$35,$A$3,0) -> 0.98 | O55: =IFERROR('49'!$F$101*'Discipline Analysis'!$B55,"") -> 0 | P55: ='49'!$F$101 -> 0 | Q55: =IFERROR('49'!$F$102*'Discipline Analysis'!$B55,"") -> 5255.11 | R55: ='49'!$F$102 -> 0.07 | S55: =IFERROR('49'!$F$103*'Discipline Analysis'!$B55,"") -> 15014.6 | T55: ='49'!$F$103 -> 0.2 | U55: =IFERROR('49'!$F$104*'Discipline Analysis'!$B55,"") -> 6005.84 | V55: ='49'!$F$104 -> 0.08
A56: Wharton | B56: =OFFSET('50'!$D$4,$A$3,0) -> 9760 | C56: =OFFSET('50'!$E$4,$A$3,0) -> 132856.18 | D56: =OFFSET('50'!$F$4,$A$3,0) -> 13.61 | E56: =OFFSET('50'!$E$66,$A$3,0) -> 77669 | F56: =OFFSET('50'!$F$66,$A$3,0) -> 7.96 | G56: =IFERROR('50'!$F$100*'Discipline Analysis'!$B56,"") -> 8881.6 | H56: ='50'!$F$100 -> 0.91 | I56: =IFERROR('50'!$F$98*'Discipline Analysis'!$B56,"") -> 19520 | J56: ='50'!$F$98 -> 2 | K56: =IFERROR('50'!$F$99*'Discipline Analysis'!$B56,"") -> 6344 | L56: ='50'!$F$99 -> 0.65 | M56: =OFFSET('50'!$E$35,$A$3,0) -> 13163 | N56: =OFFSET('50'!$F$35,$A$3,0) -> 1.35 | O56: =IFERROR('50'!$F$101*'Discipline Analysis'!$B56,"") -> 0 | P56: ='50'!$F$101 -> 0 | Q56: =IFERROR('50'!$F$102*'Discipline Analysis'!$B56,"") -> 2342.4 | R56: ='50'!$F$102 -> 0.24 | S56: =IFERROR('50'!$F$103*'Discipline Analysis'!$B56,"") -> 2440 | T56: ='50'!$F$103 -> 0.25 | U56: =IFERROR('50'!$F$104*'Discipline Analysis'!$B56,"") -> 2537.6 | V56: ='50'!$F$104 -> 0.26
A57: TSTC-Harlingen | B57: =OFFSET('51'!$D$4,$A$3,0) -> 33280 | C57: =OFFSET('51'!$E$4,$A$3,0) -> 363543.52 | D57: =OFFSET('51'!$F$4,$A$3,0) -> 10.92 | E57: =OFFSET('51'!$E$66,$A$3,0) -> 85467 | F57: =OFFSET('51'!$F$66,$A$3,0) -> 2.57 | G57: =IFERROR('51'!$F$100*'Discipline Analysis'!$B57,"") -> 12979.2 | H57: ='51'!$F$100 -> 0.39 | I57: =IFERROR('51'!$F$98*'Discipline Analysis'!$B57,"") -> 32947.2 | J57: ='51'!$F$98 -> 0.99 | K57: =IFERROR('51'!$F$99*'Discipline Analysis'!$B57,"") -> 27622.4 | L57: ='51'!$F$99 -> 0.83 | M57: =OFFSET('51'!$E$35,$A$3,0) -> 183980 | N57: =OFFSET('51'!$F$35,$A$3,0) -> 5.53 | O57: =IFERROR('51'!$F$101*'Discipline Analysis'!$B57,"") -> 1664 | P57: ='51'!$F$101 -> 0.05 | Q57: =IFERROR('51'!$F$102*'Discipline Analysis'!$B57,"") -> 11980.8 | R57: ='51'!$F$102 -> 0.36 | S57: =IFERROR('51'!$F$103*'Discipline Analysis'!$B57,"") -> 4326.4 | T57: ='51'!$F$103 -> 0.13 | U57: =IFERROR('51'!$F$104*'Discipline Analysis'!$B57,"") -> 2329.6 | V57: ='51'!$F$104 -> 0.07
A58: TSTC-West Texas | B58: =OFFSET('52'!$D$4,$A$3,0) -> 0 | C58: =OFFSET('52'!$E$4,$A$3,0) -> 0 | D58: =OFFSET('52'!$F$4,$A$3,0) | E58: =OFFSET('52'!$E$66,$A$3,0) -> 0 | F58: =OFFSET('52'!$F$66,$A$3,0) | G58: =IFERROR('52'!$F$100*'Discipline Analysis'!$B58,"") -> 0 | H58: ='52'!$F$100 -> 1.28 | I58: =IFERROR('52'!$F$98*'Discipline Analysis'!$B58,"") -> 0 | J58: ='52'!$F$98 -> 1.15 | K58: =IFERROR('52'!$F$99*'Discipline Analysis'!$B58,"") -> 0 | L58: ='52'!$F$99 -> 1.42 | M58: =OFFSET('52'!$E$35,$A$3,0) -> 0 | N58: =OFFSET('52'!$F$35,$A$3,0) | O58: =IFERROR('52'!$F$101*'Discipline Analysis'!$B58,"") -> 0 | P58: ='52'!$F$101 -> 0.04 | Q58: =IFERROR('52'!$F$102*'Discipline Analysis'!$B58,"") -> 0 | R58: ='52'!$F$102 -> 0.55 | S58: =IFERROR('52'!$F$103*'Discipline Analysis'!$B58,"") -> 0 | T58: ='52'!$F$103 -> 0.12 | U58: =IFERROR('52'!$F$104*'Discipline Analysis'!$B58,"") -> 0 | V58: ='52'!$F$104 -> 0.07
A59: TSTC-Marshall | B59: =OFFSET('53'!$D$4,$A$3,0) -> 672 | C59: =OFFSET('53'!$E$4,$A$3,0) -> 7435.724 | D59: =OFFSET('53'!$F$4,$A$3,0) -> 11.07 | E59: =OFFSET('53'!$E$66,$A$3,0) -> 3091 | F59: =OFFSET('53'!$F$66,$A$3,0) -> 4.6 | G59: =IFERROR('53'!$F$100*'Discipline Analysis'!$B59,"") -> 840 | H59: ='53'!$F$100 -> 1.25 | I59: =IFERROR('53'!$F$98*'Discipline Analysis'!$B59,"") -> 1014.72 | J59: ='53'!$F$98 -> 1.51 | K59: =IFERROR('53'!$F$99*'Discipline Analysis'!$B59,"") -> 1068.48 | L59: ='53'!$F$99 -> 1.59 | M59: =OFFSET('53'!$E$35,$A$3,0) -> 474 | N59: =OFFSET('53'!$F$35,$A$3,0) -> 0.71 | O59: =IFERROR('53'!$F$101*'Discipline Analysis'!$B59,"") -> 235.2 | P59: ='53'!$F$101 -> 0.35 | Q59: =IFERROR('53'!$F$102*'Discipline Analysis'!$B59,"") -> 423.36 | R59: ='53'!$F$102 -> 0.63 | S59: =IFERROR('53'!$F$103*'Discipline Analysis'!$B59,"") -> 201.6 | T59: ='53'!$F$103 -> 0.3 | U59: =IFERROR('53'!$F$104*'Discipline Analysis'!$B59,"") -> 87.36 | V59: ='53'!$F$104 -> 0.13
A60: TSTC-Waco | B60: =OFFSET('54'!$D$4,$A$3,0) -> 54256 | C60: =OFFSET('54'!$E$4,$A$3,0) -> 522023.75 | D60: =OFFSET('54'!$F$4,$A$3,0) -> 9.62 | E60: =OFFSET('54'!$E$66,$A$3,0) -> 205220 | F60: =OFFSET('54'!$F$66,$A$3,0) -> 3.78 | G60: =IFERROR('54'!$F$100*'Discipline Analysis'!$B60,"") -> 20074.72 | H60: ='54'!$F$100 -> 0.37 | I60: =IFERROR('54'!$F$98*'Discipline Analysis'!$B60,"") -> 51000.64 | J60: ='54'!$F$98 -> 0.94 | K60: =IFERROR('54'!$F$99*'Discipline Analysis'!$B60,"") -> 29840.8 | L60: ='54'!$F$99 -> 0.55 | M60: =OFFSET('54'!$E$35,$A$3,0) -> 163963 | N60: =OFFSET('54'!$F$35,$A$3,0) -> 3.02 | O60: =IFERROR('54'!$F$101*'Discipline Analysis'!$B60,"") -> 3797.92 | P60: ='54'!$F$101 -> 0.07 | Q60: =IFERROR('54'!$F$102*'Discipline Analysis'!$B60,"") -> 34723.84 | R60: ='54'!$F$102 -> 0.64 | S60: =IFERROR('54'!$F$103*'Discipline Analysis'!$B60,"") -> 10851.2 | T60: ='54'!$F$103 -> 0.2 | U60: =IFERROR('54'!$F$104*'Discipline Analysis'!$B60,"") -> 2712.8 | V60: ='54'!$F$104 -> 0.05
A61: Lamar-IOT | B61: =OFFSET('55'!$D$4,$A$3,0) -> 0 | C61: =OFFSET('55'!$E$4,$A$3,0) -> 0 | D61: =OFFSET('55'!$F$4,$A$3,0) | E61: =OFFSET('55'!$E$66,$A$3,0) -> 0 | F61: =OFFSET('55'!$F$66,$A$3,0) | G61: =IFERROR('55'!$F$100*'Discipline Analysis'!$B61,"") -> 0 | H61: ='55'!$F$100 -> 0.18 | I61: =IFERROR('55'!$F$98*'Discipline Analysis'!$B61,"") -> 0 | J61: ='55'!$F$98 -> 1.83 | K61: =IFERROR('55'!$F$99*'Discipline Analysis'!$B61,"") -> 0 | L61: ='55'!$F$99 -> 0.75 | M61: =OFFSET('55'!$E$35,$A$3,0) -> 0 | N61: =OFFSET('55'!$F$35,$A$3,0) | O61: =IFERROR('55'!$F$101*'Discipline Analysis'!$B61,"") -> 0 | P61: ='55'!$F$101 -> 0 | Q61: =IFERROR('55'!$F$102*'Discipline Analysis'!$B61,"") -> 0 | R61: ='55'!$F$102 -> 1.43 | S61: =IFERROR('55'!$F$103*'Discipline Analysis'!$B61,"") -> 0 | T61: ='55'!$F$103 -> 0.61 | U61: =IFERROR('55'!$F$104*'Discipline Analysis'!$B61,"") -> 0 | V61: ='55'!$F$104 -> 0.31
A62: Lamar-Orange | B62: =OFFSET('56'!$D$4,$A$3,0) -> 0 | C62: =OFFSET('56'!$E$4,$A$3,0) -> 0 | D62: =OFFSET('56'!$F$4,$A$3,0) | E62: =OFFSET('56'!$E$66,$A$3,0) -> 0 | F62: =OFFSET('56'!$F$66,$A$3,0) | G62: =IFERROR('56'!$F$100*'Discipline Analysis'!$B62,"") | H62: ='56'!$F$100 | I62: =IFERROR('56'!$F$98*'Discipline Analysis'!$B62,"") | J62: ='56'!$F$98 | K62: =IFERROR('56'!$F$99*'Discipline Analysis'!$B62,"") | L62: ='56'!$F$99 | M62: =OFFSET('56'!$E$35,$A$3,0) -> 0 | N62: =OFFSET('56'!$F$35,$A$3,0) | O62: =IFERROR('56'!$F$101*'Discipline Analysis'!$B62,"") | P62: ='56'!$F$101 | Q62: =IFERROR('56'!$F$102*'Discipline Analysis'!$B62,"") | R62: ='56'!$F$102 | S62: =IFERROR('56'!$F$103*'Discipline Analysis'!$B62,"") | T62: ='56'!$F$103 | U62: =IFERROR('56'!$F$104*'Discipline Analysis'!$B62,"") | V62: ='56'!$F$104
A63: Lamar-Port Arthur | B63: =OFFSET('57'!$D$4,$A$3,0) -> 0 | C63: =OFFSET('57'!$E$4,$A$3,0) -> 0 | D63: =OFFSET('57'!$F$4,$A$3,0) | E63: =OFFSET('57'!$E$66,$A$3,0) -> 0 | F63: =OFFSET('57'!$F$66,$A$3,0) | G63: =IFERROR('57'!$F$100*'Discipline Analysis'!$B63,"") -> 0 | H63: ='57'!$F$100 -> 1.27 | I63: =IFERROR('57'!$F$98*'Discipline Analysis'!$B63,"") -> 0 | J63: ='57'!$F$98 -> 1.75 | K63: =IFERROR('57'!$F$99*'Discipline Analysis'!$B63,"") -> 0 | L63: ='57'!$F$99 -> 0.58 | M63: =OFFSET('57'!$E$35,$A$3,0) -> 0 | N63: =OFFSET('57'!$F$35,$A$3,0) | O63: =IFERROR('57'!$F$101*'Discipline Analysis'!$B63,"") -> 0 | P63: ='57'!$F$101 -> 0 | Q63: =IFERROR('57'!$F$102*'Discipline Analysis'!$B63,"") -> 0 | R63: ='57'!$F$102 -> 1.35 | S63: =IFERROR('57'!$F$103*'Discipline Analysis'!$B63,"") -> 0 | T63: ='57'!$F$103 -> 0.97 | U63: =IFERROR('57'!$F$104*'Discipline Analysis'!$B63,"") -> 0 | V63: ='57'!$F$104 -> 0.77
A64: Total | B64: =OFFSET(Summary!$D$4,$A$3,0) -> 1534719 | C64: =OFFSET(Summary!$E$4,$A$3,0) -> 13513304 | D64: =MEDIAN(D7:D63) -> 8.705 | E64: =OFFSET(Summary!$E$66,$A$3,0) -> 4815786 | F64: =MEDIAN(F7:F63) -> 3.26 | G64: =Summary!$F$100*B64 -> 1074303.3 | H64: =MEDIAN(H7:H63) -> 0.7 | I64: =Summary!$F$98*'Discipline Analysis'!B64 -> 2363467.3 | J64: =MEDIAN(J7:J63) -> 1.535 | K64: =Summary!$F$99*'Discipline Analysis'!B64 -> 1089650.5 | L64: =MEDIAN(L7:L63) -> 0.705 | M64: =OFFSET(Summary!$E$35,$A$3,0) -> 2984519 | N64: =MEDIAN(N7:N63) -> 1.16 | O64: =IFERROR(Summary!$F$101*'Discipline Analysis'!B64,"") -> 0 | P64: =MEDIAN(P7:P63) -> 0 | Q64: =Summary!$F$102*'Discipline Analysis'!B64 -> 15347.19 | R64: =MEDIAN(R7:R63) -> 0.005 | S64: =Summary!$F$103*'Discipline Analysis'!B64 -> 230207.85 | T64: =MEDIAN(T7:T63) -> 0.15 | U64: =Summary!$F$104*'Discipline Analysis'!B64 -> 260902.23 | V64: =MEDIAN(V7:V63) -> 0.165

Sheet Neutral
A1: =Summary!A1 -> Community and Technical Colleges, Report of Fundable Operating Expenses, Fiscal Year (FY) 2008
A2: Percent of Rates to Maintain Funding Total
A3: This calculation is completed to indicate the relative change in financing assuming the legislature were to fund the institutions at the same total as the previous biennium. The percent funded used against the current rates is adjusted so that the total funded for all institutions is equal to the previous biennium's percent funded.
A4: Institution | B4: ="FY 2008 - 2009 Rates @ "&TEXT(B5,"0.00%")&" (Using FY 2008 CH)" -> FY 2008 - 2009 Rates @ 47.99% (Using FY 2008 CH) | C4: ="Annual Budget Neutral Percent Funded "&TEXT(C5,"0.00%")&" (Using FY 2008 CH)" -> Annual Budget Neutral Percent Funded 47.11% (Using FY 2008 CH) | D4: Difference | E4: Percent Change
A5: Percent of Rates Funded | B5: 0.47991153 | C5: 0.47113766 | D5: =C5-B5 -> -0.0087738737
A6: Alamo Community College District | B6: =$B$5*('Rate History'!$D$4*SUMIF(Data!$G:$G,Neutral!$A6,Data!$CU:$CU)+'Rate History'!$D$5*SUMIF(Data!$G:$G,Neutral!$A6,Data!$CV:$CV)+'Rate History'!$D$6*SUMIF(Data!$G:$G,Neutral!$A6,Data!$CW:$CW)+'Rate History'!$D$7*SUMIF(Data!$G:$G,Neutral!$A6,Data!$CX:$CX)+'Rate History'!$D$8*SUMIF(Data!$G:$G,Neutral!$A6,Data!$CY:$CY)+'Rate History'!$D$9*SUMIF(Data!$G:$G,Neutral!$A6,Data!$CZ:$CZ)+'Rate History'!$D$10*SUMIF(Data!$G:$G,Neutral!$A6,Data!$DA:$DA)+'Rate History'!$D$11*SUMIF(Data!$G:$G,Neutral!$A6,Data!$DB:$DB)+'Rate History'!$D$12*SUMIF(Data!$G:$G,Neutral!$A6,Data!$DC:$DC)+'Rate History'!$D$13*SUMIF(Data!$G:$G,Neutral!$A6,Data!$DD:$DD)+'Rate History'!$D$14*SUMIF(Data!$G:$G,Neutral!$A6,Data!$DE:$DE)+'Rate History'!$D$15*SUMIF(Data!$G:$G,Neutral!$A6,Data!$DF:$DF)+'Rate History'!$D$16*SUMIF(Data!$G:$G,Neutral!$A6,Data!$DG:$DG)+'Rate History'!$D$17*SUMIF(Data!$G:$G,Neutral!$A6,Data!$DH:$DH)+'Rate History'!$D$18*SUMIF(Data!$G:$G,Neutral!$A6,Data!$DI:$DI)+'Rate History'!$D$19*SUMIF(Data!$G:$G,Neutral!$A6,Data!$DJ:$DJ)+'Rate History'!$D$20*SUMIF(Data!$G:$G,Neutral!$A6,Data!$DK:$DK)+'Rate History'!$D$21*SUMIF(Data!$G:$G,Neutral!$A6,Data!$DL:$DL)+'Rate History'!$D$22*SUMIF(Data!$G:$G,Neutral!$A6,Data!$DM:$DM)+'Rate History'!$D$23*SUMIF(Data!$G:$G,Neutral!$A6,Data!$DN:$DN)+'Rate History'!$D$24*SUMIF(Data!$G:$G,Neutral!$A6,Data!$DO:$DO)+'Rate History'!$D$25*SUMIF(Data!$G:$G,Neutral!$A6,Data!$DP:$DP)+'Rate History'!$D$26*SUMIF(Data!$G:$G,Neutral!$A6,Data!$DQ:$DQ)+'Rate History'!$D$27*SUMIF(Data!$G:$G,Neutral!$A6,Data!$DR:$DR)+'Rate History'!$D$28*SUMIF(Data!$G:$G,Neutral!$A6,Data!$DS:$DS)+'Rate History'!$D$29*SUMIF(Data!$G:$G,Neutral!$A6,Data!$DT:$DT)+'Rate History'!$D$30*SUMIF(Data!$G:$G,Neutral!$A6,Data!$DV:$DV)+'Rate History'!$D$31*SUMIF(Data!$G:$G,Neutral!$A6,Data!$DW:$DW)) -> 69921277 | C6: =$C$5*('Rate History'!$C$4*SUMIF(Data!$G:$G,Neutral!$A6,Data!$CU:$CU)+'Rate History'!$C$5*SUMIF(Data!$G:$G,Neutral!$A6,Data!$CV:$CV)+'Rate History'!$C$6*SUMIF(Data!$G:$G,Neutral!$A6,Data!$CW:$CW)+'Rate History'!$C$7*SUMIF(Data!$G:$G,Neutral!$A6,Data!$CX:$CX)+'Rate History'!$C$8*SUMIF(Data!$G:$G,Neutral!$A6,Data!$CY:$CY)+'Rate History'!$C$9*SUMIF(Data!$G:$G,Neutral!$A6,Data!$CZ:$CZ)+'Rate History'!$C$10*SUMIF(Data!$G:$G,Neutral!$A6,Data!$DA:$DA)+'Rate History'!$C$11*SUMIF(Data!$G:$G,Neutral!$A6,Data!$DB:$DB)+'Rate History'!$C$12*SUMIF(Data!$G:$G,Neutral!$A6,Data!$DC:$DC)+'Rate History'!$C$13*SUMIF(Data!$G:$G,Neutral!$A6,Data!$DD:$DD)+'Rate History'!$C$14*SUMIF(Data!$G:$G,Neutral!$A6,Data!$DE:$DE)+'Rate History'!$C$15*SUMIF(Data!$G:$G,Neutral!$A6,Data!$DF:$DF)+'Rate History'!$C$16*SUMIF(Data!$G:$G,Neutral!$A6,Data!$DG:$DG)+'Rate History'!$C$17*SUMIF(Data!$G:$G,Neutral!$A6,Data!$DH:$DH)+'Rate History'!$C$18*SUMIF(Data!$G:$G,Neutral!$A6,Data!$DI:$DI)+'Rate History'!$C$19*SUMIF(Data!$G:$G,Neutral!$A6,Data!$DJ:$DJ)+'Rate History'!$C$20*SUMIF(Data!$G:$G,Neutral!$A6,Data!$DK:$DK)+'Rate History'!$C$21*SUMIF(Data!$G:$G,Neutral!$A6,Data!$DL:$DL)+'Rate History'!$C$22*SUMIF(Data!$G:$G,Neutral!$A6,Data!$DM:$DM)+'Rate History'!$C$23*SUMIF(Data!$G:$G,Neutral!$A6,Data!$DN:$DN)+'Rate History'!$C$24*SUMIF(Data!$G:$G,Neutral!$A6,Data!$DO:$DO)+'Rate History'!$C$25*SUMIF(Data!$G:$G,Neutral!$A6,Data!$DP:$DP)+'Rate History'!$C$26*SUMIF(Data!$G:$G,Neutral!$A6,Data!$DQ:$DQ)+'Rate History'!$C$27*SUMIF(Data!$G:$G,Neutral!$A6,Data!$DR:$DR)+'Rate History'!$C$28*SUMIF(Data!$G:$G,Neutral!$A6,Data!$DS:$DS)+'Rate History'!$C$29*SUMIF(Data!$G:$G,Neutral!$A6,Data!$DT:$DT)+'Rate History'!$C$30*SUMIF(Data!$G:$G,Neutral!$A6,Data!$DV:$DV)+'Rate History'!$C$31*SUMIF(Data!$G:$G,Neutral!$A6,Data!$DW:$DW)) -> 70044341 | D6: =C6-B6 -> 123064.19 | E6: =IFERROR(D6/B6,"") -> 0.0017600392
A7: Alvin Community College | B7: =$B$5*('Rate History'!$D$4*SUMIF(Data!$G:$G,Neutral!$A7,Data!$CU:$CU)+'Rate History'!$D$5*SUMIF(Data!$G:$G,Neutral!$A7,Data!$CV:$CV)+'Rate History'!$D$6*SUMIF(Data!$G:$G,Neutral!$A7,Data!$CW:$CW)+'Rate History'!$D$7*SUMIF(Data!$G:$G,Neutral!$A7,Data!$CX:$CX)+'Rate History'!$D$8*SUMIF(Data!$G:$G,Neutral!$A7,Data!$CY:$CY)+'Rate History'!$D$9*SUMIF(Data!$G:$G,Neutral!$A7,Data!$CZ:$CZ)+'Rate History'!$D$10*SUMIF(Data!$G:$G,Neutral!$A7,Data!$DA:$DA)+'Rate History'!$D$11*SUMIF(Data!$G:$G,Neutral!$A7,Data!$DB:$DB)+'Rate History'!$D$12*SUMIF(Data!$G:$G,Neutral!$A7,Data!$DC:$DC)+'Rate History'!$D$13*SUMIF(Data!$G:$G,Neutral!$A7,Data!$DD:$DD)+'Rate History'!$D$14*SUMIF(Data!$G:$G,Neutral!$A7,Data!$DE:$DE)+'Rate History'!$D$15*SUMIF(Data!$G:$G,Neutral!$A7,Data!$DF:$DF)+'Rate History'!$D$16*SUMIF(Data!$G:$G,Neutral!$A7,Data!$DG:$DG)+'Rate History'!$D$17*SUMIF(Data!$G:$G,Neutral!$A7,Data!$DH:$DH)+'Rate History'!$D$18*SUMIF(Data!$G:$G,Neutral!$A7,Data!$DI:$DI)+'Rate History'!$D$19*SUMIF(Data!$G:$G,Neutral!$A7,Data!$DJ:$DJ)+'Rate History'!$D$20*SUMIF(Data!$G:$G,Neutral!$A7,Data!$DK:$DK)+'Rate History'!$D$21*SUMIF(Data!$G:$G,Neutral!$A7,Data!$DL:$DL)+'Rate History'!$D$22*SUMIF(Data!$G:$G,Neutral!$A7,Data!$DM:$DM)+'Rate History'!$D$23*SUMIF(Data!$G:$G,Neutral!$A7,Data!$DN:$DN)+'Rate History'!$D$24*SUMIF(Data!$G:$G,Neutral!$A7,Data!$DO:$DO)+'Rate History'!$D$25*SUMIF(Data!$G:$G,Neutral!$A7,Data!$DP:$DP)+'Rate History'!$D$26*SUMIF(Data!$G:$G,Neutral!$A7,Data!$DQ:$DQ)+'Rate History'!$D$27*SUMIF(Data!$G:$G,Neutral!$A7,Data!$DR:$DR)+'Rate History'!$D$28*SUMIF(Data!$G:$G,Neutral!$A7,Data!$DS:$DS)+'Rate History'!$D$29*SUMIF(Data!$G:$G,Neutral!$A7,Data!$DT:$DT)+'Rate History'!$D$30*SUMIF(Data!$G:$G,Neutral!$A7,Data!$DV:$DV)+'Rate History'!$D$31*SUMIF(Data!$G:$G,Neutral!$A7,Data!$DW:$DW)) -> 8297339.3 | C7: =$C$5*('Rate History'!$C$4*SUMIF(Data!$G:$G,Neutral!$A7,Data!$CU:$CU)+'Rate History'!$C$5*SUMIF(Data!$G:$G,Neutral!$A7,Data!$CV:$CV)+'Rate History'!$C$6*SUMIF(Data!$G:$G,Neutral!$A7,Data!$CW:$CW)+'Rate History'!$C$7*SUMIF(Data!$G:$G,Neutral!$A7,Data!$CX:$CX)+'Rate History'!$C$8*SUMIF(Data!$G:$G,Neutral!$A7,Data!$CY:$CY)+'Rate History'!$C$9*SUMIF(Data!$G:$G,Neutral!$A7,Data!$CZ:$CZ)+'Rate History'!$C$10*SUMIF(Data!$G:$G,Neutral!$A7,Data!$DA:$DA)+'Rate History'!$C$11*SUMIF(Data!$G:$G,Neutral!$A7,Data!$DB:$DB)+'Rate History'!$C$12*SUMIF(Data!$G:$G,Neutral!$A7,Data!$DC:$DC)+'Rate History'!$C$13*SUMIF(Data!$G:$G,Neutral!$A7,Data!$DD:$DD)+'Rate History'!$C$14*SUMIF(Data!$G:$G,Neutral!$A7,Data!$DE:$DE)+'Rate History'!$C$15*SUMIF(Data!$G:$G,Neutral!$A7,Data!$DF:$DF)+'Rate History'!$C$16*SUMIF(Data!$G:$G,Neutral!$A7,Data!$DG:$DG)+'Rate History'!$C$17*SUMIF(Data!$G:$G,Neutral!$A7,Data!$DH:$DH)+'Rate History'!$C$18*SUMIF(Data!$G:$G,Neutral!$A7,Data!$DI:$DI)+'Rate History'!$C$19*SUMIF(Data!$G:$G,Neutral!$A7,Data!$DJ:$DJ)+'Rate History'!$C$20*SUMIF(Data!$G:$G,Neutral!$A7,Data!$DK:$DK)+'Rate History'!$C$21*SUMIF(Data!$G:$G,Neutral!$A7,Data!$DL:$DL)+'Rate History'!$C$22*SUMIF(Data!$G:$G,Neutral!$A7,Data!$DM:$DM)+'Rate History'!$C$23*SUMIF(Data!$G:$G,Neutral!$A7,Data!$DN:$DN)+'Rate History'!$C$24*SUMIF(Data!$G:$G,Neutral!$A7,Data!$DO:$DO)+'Rate History'!$C$25*SUMIF(Data!$G:$G,Neutral!$A7,Data!$DP:$DP)+'Rate History'!$C$26*SUMIF(Data!$G:$G,Neutral!$A7,Data!$DQ:$DQ)+'Rate History'!$C$27*SUMIF(Data!$G:$G,Neutral!$A7,Data!$DR:$DR)+'Rate History'!$C$28*SUMIF(Data!$G:$G,Neutral!$A7,Data!$DS:$DS)+'Rate History'!$C$29*SUMIF(Data!$G:$G,Neutral!$A7,Data!$DT:$DT)+'Rate History'!$C$30*SUMIF(Data!$G:$G,Neutral!$A7,Data!$DV:$DV)+'Rate History'!$C$31*SUMIF(Data!$G:$G,Neutral!$A7,Data!$DW:$DW)) -> 8281428.9 | D7: =C7-B7 -> -15910.348 | E7: =IFERROR(D7/B7,"") -> -0.0019175241
A8: Amarillo College | B8: =$B$5*('Rate History'!$D$4*SUMIF(Data!$G:$G,Neutral!$A8,Data!$CU:$CU)+'Rate History'!$D$5*SUMIF(Data!$G:$G,Neutral!$A8,Data!$CV:$CV)+'Rate History'!$D$6*SUMIF(Data!$G:$G,Neutral!$A8,Data!$CW:$CW)+'Rate History'!$D$7*SUMIF(Data!$G:$G,Neutral!$A8,Data!$CX:$CX)+'Rate History'!$D$8*SUMIF(Data!$G:$G,Neutral!$A8,Data!$CY:$CY)+'Rate History'!$D$9*SUMIF(Data!$G:$G,Neutral!$A8,Data!$CZ:$CZ)+'Rate History'!$D$10*SUMIF(Data!$G:$G,Neutral!$A8,Data!$DA:$DA)+'Rate History'!$D$11*SUMIF(Data!$G:$G,Neutral!$A8,Data!$DB:$DB)+'Rate History'!$D$12*SUMIF(Data!$G:$G,Neutral!$A8,Data!$DC:$DC)+'Rate History'!$D$13*SUMIF(Data!$G:$G,Neutral!$A8,Data!$DD:$DD)+'Rate History'!$D$14*SUMIF(Data!$G:$G,Neutral!$A8,Data!$DE:$DE)+'Rate History'!$D$15*SUMIF(Data!$G:$G,Neutral!$A8,Data!$DF:$DF)+'Rate History'!$D$16*SUMIF(Data!$G:$G,Neutral!$A8,Data!$DG:$DG)+'Rate History'!$D$17*SUMIF(Data!$G:$G,Neutral!$A8,Data!$DH:$DH)+'Rate History'!$D$18*SUMIF(Data!$G:$G,Neutral!$A8,Data!$DI:$DI)+'Rate History'!$D$19*SUMIF(Data!$G:$G,Neutral!$A8,Data!$DJ:$DJ)+'Rate History'!$D$20*SUMIF(Data!$G:$G,Neutral!$A8,Data!$DK:$DK)+'Rate History'!$D$21*SUMIF(Data!$G:$G,Neutral!$A8,Data!$DL:$DL)+'Rate History'!$D$22*SUMIF(Data!$G:$G,Neutral!$A8,Data!$DM:$DM)+'Rate History'!$D$23*SUMIF(Data!$G:$G,Neutral!$A8,Data!$DN:$DN)+'Rate History'!$D$24*SUMIF(Data!$G:$G,Neutral!$A8,Data!$DO:$DO)+'Rate History'!$D$25*SUMIF(Data!$G:$G,Neutral!$A8,Data!$DP:$DP)+'Rate History'!$D$26*SUMIF(Data!$G:$G,Neutral!$A8,Data!$DQ:$DQ)+'Rate History'!$D$27*SUMIF(Data!$G:$G,Neutral!$A8,Data!$DR:$DR)+'Rate History'!$D$28*SUMIF(Data!$G:$G,Neutral!$A8,Data!$DS:$DS)+'Rate History'!$D$29*SUMIF(Data!$G:$G,Neutral!$A8,Data!$DT:$DT)+'Rate History'!$D$30*SUMIF(Data!$G:$G,Neutral!$A8,Data!$DV:$DV)+'Rate History'!$D$31*SUMIF(Data!$G:$G,Neutral!$A8,Data!$DW:$DW)) -> 16787844 | C8: =$C$5*('Rate History'!$C$4*SUMIF(Data!$G:$G,Neutral!$A8,Data!$CU:$CU)+'Rate History'!$C$5*SUMIF(Data!$G:$G,Neutral!$A8,Data!$CV:$CV)+'Rate History'!$C$6*SUMIF(Data!$G:$G,Neutral!$A8,Data!$CW:$CW)+'Rate History'!$C$7*SUMIF(Data!$G:$G,Neutral!$A8,Data!$CX:$CX)+'Rate History'!$C$8*SUMIF(Data!$G:$G,Neutral!$A8,Data!$CY:$CY)+'Rate History'!$C$9*SUMIF(Data!$G:$G,Neutral!$A8,Data!$CZ:$CZ)+'Rate History'!$C$10*SUMIF(Data!$G:$G,Neutral!$A8,Data!$DA:$DA)+'Rate History'!$C$11*SUMIF(Data!$G:$G,Neutral!$A8,Data!$DB:$DB)+'Rate History'!$C$12*SUMIF(Data!$G:$G,Neutral!$A8,Data!$DC:$DC)+'Rate History'!$C$13*SUMIF(Data!$G:$G,Neutral!$A8,Data!$DD:$DD)+'Rate History'!$C$14*SUMIF(Data!$G:$G,Neutral!$A8,Data!$DE:$DE)+'Rate History'!$C$15*SUMIF(Data!$G:$G,Neutral!$A8,Data!$DF:$DF)+'Rate History'!$C$16*SUMIF(Data!$G:$G,Neutral!$A8,Data!$DG:$DG)+'Rate History'!$C$17*SUMIF(Data!$G:$G,Neutral!$A8,Data!$DH:$DH)+'Rate History'!$C$18*SUMIF(Data!$G:$G,Neutral!$A8,Data!$DI:$DI)+'Rate History'!$C$19*SUMIF(Data!$G:$G,Neutral!$A8,Data!$DJ:$DJ)+'Rate History'!$C$20*SUMIF(Data!$G:$G,Neutral!$A8,Data!$DK:$DK)+'Rate History'!$C$21*SUMIF(Data!$G:$G,Neutral!$A8,Data!$DL:$DL)+'Rate History'!$C$22*SUMIF(Data!$G:$G,Neutral!$A8,Data!$DM:$DM)+'Rate History'!$C$23*SUMIF(Data!$G:$G,Neutral!$A8,Data!$DN:$DN)+'Rate History'!$C$24*SUMIF(Data!$G:$G,Neutral!$A8,Data!$DO:$DO)+'Rate History'!$C$25*SUMIF(Data!$G:$G,Neutral!$A8,Data!$DP:$DP)+'Rate History'!$C$26*SUMIF(Data!$G:$G,Neutral!$A8,Data!$DQ:$DQ)+'Rate History'!$C$27*SUMIF(Data!$G:$G,Neutral!$A8,Data!$DR:$DR)+'Rate History'!$C$28*SUMIF(Data!$G:$G,Neutral!$A8,Data!$DS:$DS)+'Rate History'!$C$29*SUMIF(Data!$G:$G,Neutral!$A8,Data!$DT:$DT)+'Rate History'!$C$30*SUMIF(Data!$G:$G,Neutral!$A8,Data!$DV:$DV)+'Rate History'!$C$31*SUMIF(Data!$G:$G,Neutral!$A8,Data!$DW:$DW)) -> 16800626 | D8: =C8-B8 -> 12781.624 | E8: =IFERROR(D8/B8,"") -> 0.00076136188
A9: Angelina College | B9: =$B$5*('Rate History'!$D$4*SUMIF(Data!$G:$G,Neutral!$A9,Data!$CU:$CU)+'Rate History'!$D$5*SUMIF(Data!$G:$G,Neutral!$A9,Data!$CV:$CV)+'Rate History'!$D$6*SUMIF(Data!$G:$G,Neutral!$A9,Data!$CW:$CW)+'Rate History'!$D$7*SUMIF(Data!$G:$G,Neutral!$A9,Data!$CX:$CX)+'Rate History'!$D$8*SUMIF(Data!$G:$G,Neutral!$A9,Data!$CY:$CY)+'Rate History'!$D$9*SUMIF(Data!$G:$G,Neutral!$A9,Data!$CZ:$CZ)+'Rate History'!$D$10*SUMIF(Data!$G:$G,Neutral!$A9,Data!$DA:$DA)+'Rate History'!$D$11*SUMIF(Data!$G:$G,Neutral!$A9,Data!$DB:$DB)+'Rate History'!$D$12*SUMIF(Data!$G:$G,Neutral!$A9,Data!$DC:$DC)+'Rate History'!$D$13*SUMIF(Data!$G:$G,Neutral!$A9,Data!$DD:$DD)+'Rate History'!$D$14*SUMIF(Data!$G:$G,Neutral!$A9,Data!$DE:$DE)+'Rate History'!$D$15*SUMIF(Data!$G:$G,Neutral!$A9,Data!$DF:$DF)+'Rate History'!$D$16*SUMIF(Data!$G:$G,Neutral!$A9,Data!$DG:$DG)+'Rate History'!$D$17*SUMIF(Data!$G:$G,Neutral!$A9,Data!$DH:$DH)+'Rate History'!$D$18*SUMIF(Data!$G:$G,Neutral!$A9,Data!$DI:$DI)+'Rate History'!$D$19*SUMIF(Data!$G:$G,Neutral!$A9,Data!$DJ:$DJ)+'Rate History'!$D$20*SUMIF(Data!$G:$G,Neutral!$A9,Data!$DK:$DK)+'Rate History'!$D$21*SUMIF(Data!$G:$G,Neutral!$A9,Data!$DL:$DL)+'Rate History'!$D$22*SUMIF(Data!$G:$G,Neutral!$A9,Data!$DM:$DM)+'Rate History'!$D$23*SUMIF(Data!$G:$G,Neutral!$A9,Data!$DN:$DN)+'Rate History'!$D$24*SUMIF(Data!$G:$G,Neutral!$A9,Data!$DO:$DO)+'Rate History'!$D$25*SUMIF(Data!$G:$G,Neutral!$A9,Data!$DP:$DP)+'Rate History'!$D$26*SUMIF(Data!$G:$G,Neutral!$A9,Data!$DQ:$DQ)+'Rate History'!$D$27*SUMIF(Data!$G:$G,Neutral!$A9,Data!$DR:$DR)+'Rate History'!$D$28*SUMIF(Data!$G:$G,Neutral!$A9,Data!$DS:$DS)+'Rate History'!$D$29*SUMIF(Data!$G:$G,Neutral!$A9,Data!$DT:$DT)+'Rate History'!$D$30*SUMIF(Data!$G:$G,Neutral!$A9,Data!$DV:$DV)+'Rate History'!$D$31*SUMIF(Data!$G:$G,Neutral!$A9,Data!$DW:$DW)) -> 7737302.5 | C9: =$C$5*('Rate History'!$C$4*SUMIF(Data!$G:$G,Neutral!$A9,Data!$CU:$CU)+'Rate History'!$C$5*SUMIF(Data!$G:$G,Neutral!$A9,Data!$CV:$CV)+'Rate History'!$C$6*SUMIF(Data!$G:$G,Neutral!$A9,Data!$CW:$CW)+'Rate History'!$C$7*SUMIF(Data!$G:$G,Neutral!$A9,Data!$CX:$CX)+'Rate History'!$C$8*SUMIF(Data!$G:$G,Neutral!$A9,Data!$CY:$CY)+'Rate History'!$C$9*SUMIF(Data!$G:$G,Neutral!$A9,Data!$CZ:$CZ)+'Rate History'!$C$10*SUMIF(Data!$G:$G,Neutral!$A9,Data!$DA:$DA)+'Rate History'!$C$11*SUMIF(Data!$G:$G,Neutral!$A9,Data!$DB:$DB)+'Rate History'!$C$12*SUMIF(Data!$G:$G,Neutral!$A9,Data!$DC:$DC)+'Rate History'!$C$13*SUMIF(Data!$G:$G,Neutral!$A9,Data!$DD:$DD)+'Rate History'!$C$14*SUMIF(Data!$G:$G,Neutral!$A9,Data!$DE:$DE)+'Rate History'!$C$15*SUMIF(Data!$G:$G,Neutral!$A9,Data!$DF:$DF)+'Rate History'!$C$16*SUMIF(Data!$G:$G,Neutral!$A9,Data!$DG:$DG)+'Rate History'!$C$17*SUMIF(Data!$G:$G,Neutral!$A9,Data!$DH:$DH)+'Rate History'!$C$18*SUMIF(Data!$G:$G,Neutral!$A9,Data!$DI:$DI)+'Rate History'!$C$19*SUMIF(Data!$G:$G,Neutral!$A9,Data!$DJ:$DJ)+'Rate History'!$C$20*SUMIF(Data!$G:$G,Neutral!$A9,Data!$DK:$DK)+'Rate History'!$C$21*SUMIF(Data!$G:$G,Neutral!$A9,Data!$DL:$DL)+'Rate History'!$C$22*SUMIF(Data!$G:$G,Neutral!$A9,Data!$DM:$DM)+'Rate History'!$C$23*SUMIF(Data!$G:$G,Neutral!$A9,Data!$DN:$DN)+'Rate History'!$C$24*SUMIF(Data!$G:$G,Neutral!$A9,Data!$DO:$DO)+'Rate History'!$C$25*SUMIF(Data!$G:$G,Neutral!$A9,Data!$DP:$DP)+'Rate History'!$C$26*SUMIF(Data!$G:$G,Neutral!$A9,Data!$DQ:$DQ)+'Rate History'!$C$27*SUMIF(Data!$G:$G,Neutral!$A9,Data!$DR:$DR)+'Rate History'!$C$28*SUMIF(Data!$G:$G,Neutral!$A9,Data!$DS:$DS)+'Rate History'!$C$29*SUMIF(Data!$G:$G,Neutral!$A9,Data!$DT:$DT)+'Rate History'!$C$30*SUMIF(Data!$G:$G,Neutral!$A9,Data!$DV:$DV)+'Rate History'!$C$31*SUMIF(Data!$G:$G,Neutral!$A9,Data!$DW:$DW)) -> 7709531.5 | D9: =C9-B9 -> -27771.035 | E9: =IFERROR(D9/B9,"") -> -0.0035892399
A10: Austin Community College | B10: =$B$5*('Rate History'!$D$4*SUMIF(Data!$G:$G,Neutral!$A10,Data!$CU:$CU)+'Rate History'!$D$5*SUMIF(Data!$G:$G,Neutral!$A10,Data!$CV:$CV)+'Rate History'!$D$6*SUMIF(Data!$G:$G,Neutral!$A10,Data!$CW:$CW)+'Rate History'!$D$7*SUMIF(Data!$G:$G,Neutral!$A10,Data!$CX:$CX)+'Rate History'!$D$8*SUMIF(Data!$G:$G,Neutral!$A10,Data!$CY:$CY)+'Rate History'!$D$9*SUMIF(Data!$G:$G,Neutral!$A10,Data!$CZ:$CZ)+'Rate History'!$D$10*SUMIF(Data!$G:$G,Neutral!$A10,Data!$DA:$DA)+'Rate History'!$D$11*SUMIF(Data!$G:$G,Neutral!$A10,Data!$DB:$DB)+'Rate History'!$D$12*SUMIF(Data!$G:$G,Neutral!$A10,Data!$DC:$DC)+'Rate History'!$D$13*SUMIF(Data!$G:$G,Neutral!$A10,Data!$DD:$DD)+'Rate History'!$D$14*SUMIF(Data!$G:$G,Neutral!$A10,Data!$DE:$DE)+'Rate History'!$D$15*SUMIF(Data!$G:$G,Neutral!$A10,Data!$DF:$DF)+'Rate History'!$D$16*SUMIF(Data!$G:$G,Neutral!$A10,Data!$DG:$DG)+'Rate History'!$D$17*SUMIF(Data!$G:$G,Neutral!$A10,Data!$DH:$DH)+'Rate History'!$D$18*SUMIF(Data!$G:$G,Neutral!$A10,Data!$DI:$DI)+'Rate History'!$D$19*SUMIF(Data!$G:$G,Neutral!$A10,Data!$DJ:$DJ)+'Rate History'!$D$20*SUMIF(Data!$G:$G,Neutral!$A10,Data!$DK:$DK)+'Rate History'!$D$21*SUMIF(Data!$G:$G,Neutral!$A10,Data!$DL:$DL)+'Rate History'!$D$22*SUMIF(Data!$G:$G,Neutral!$A10,Data!$DM:$DM)+'Rate History'!$D$23*SUMIF(Data!$G:$G,Neutral!$A10,Data!$DN:$DN)+'Rate History'!$D$24*SUMIF(Data!$G:$G,Neutral!$A10,Data!$DO:$DO)+'Rate History'!$D$25*SUMIF(Data!$G:$G,Neutral!$A10,Data!$DP:$DP)+'Rate History'!$D$26*SUMIF(Data!$G:$G,Neutral!$A10,Data!$DQ:$DQ)+'Rate History'!$D$27*SUMIF(Data!$G:$G,Neutral!$A10,Data!$DR:$DR)+'Rate History'!$D$28*SUMIF(Data!$G:$G,Neutral!$A10,Data!$DS:$DS)+'Rate History'!$D$29*SUMIF(Data!$G:$G,Neutral!$A10,Data!$DT:$DT)+'Rate History'!$D$30*SUMIF(Data!$G:$G,Neutral!$A10,Data!$DV:$DV)+'Rate History'!$D$31*SUMIF(Data!$G:$G,Neutral!$A10,Data!$DW:$DW)) -> 44300833 | C10: =$C$5*('Rate History'!$C$4*SUMIF(Data!$G:$G,Neutral!$A10,Data!$CU:$CU)+'Rate History'!$C$5*SUMIF(Data!$G:$G,Neutral!$A10,Data!$CV:$CV)+'Rate History'!$C$6*SUMIF(Data!$G:$G,Neutral!$A10,Data!$CW:$CW)+'Rate History'!$C$7*SUMIF(Data!$G:$G,Neutral!$A10,Data!$CX:$CX)+'Rate History'!$C$8*SUMIF(Data!$G:$G,Neutral!$A10,Data!$CY:$CY)+'Rate History'!$C$9*SUMIF(Data!$G:$G,Neutral!$A10,Data!$CZ:$CZ)+'Rate History'!$C$10*SUMIF(Data!$G:$G,Neutral!$A10,Data!$DA:$DA)+'Rate History'!$C$11*SUMIF(Data!$G:$G,Neutral!$A10,Data!$DB:$DB)+'Rate History'!$C$12*SUMIF(Data!$G:$G,Neutral!$A10,Data!$DC:$DC)+'Rate History'!$C$13*SUMIF(Data!$G:$G,Neutral!$A10,Data!$DD:$DD)+'Rate History'!$C$14*SUMIF(Data!$G:$G,Neutral!$A10,Data!$DE:$DE)+'Rate History'!$C$15*SUMIF(Data!$G:$G,Neutral!$A10,Data!$DF:$DF)+'Rate History'!$C$16*SUMIF(Data!$G:$G,Neutral!$A10,Data!$DG:$DG)+'Rate History'!$C$17*SUMIF(Data!$G:$G,Neutral!$A10,Data!$DH:$DH)+'Rate History'!$C$18*SUMIF(Data!$G:$G,Neutral!$A10,Data!$DI:$DI)+'Rate History'!$C$19*SUMIF(Data!$G:$G,Neutral!$A10,Data!$DJ:$DJ)+'Rate History'!$C$20*SUMIF(Data!$G:$G,Neutral!$A10,Data!$DK:$DK)+'Rate History'!$C$21*SUMIF(Data!$G:$G,Neutral!$A10,Data!$DL:$DL)+'Rate History'!$C$22*SUMIF(Data!$G:$G,Neutral!$A10,Data!$DM:$DM)+'Rate History'!$C$23*SUMIF(Data!$G:$G,Neutral!$A10,Data!$DN:$DN)+'Rate History'!$C$24*SUMIF(Data!$G:$G,Neutral!$A10,Data!$DO:$DO)+'Rate History'!$C$25*SUMIF(Data!$G:$G,Neutral!$A10,Data!$DP:$DP)+'Rate History'!$C$26*SUMIF(Data!$G:$G,Neutral!$A10,Data!$DQ:$DQ)+'Rate History'!$C$27*SUMIF(Data!$G:$G,Neutral!$A10,Data!$DR:$DR)+'Rate History'!$C$28*SUMIF(Data!$G:$G,Neutral!$A10,Data!$DS:$DS)+'Rate History'!$C$29*SUMIF(Data!$G:$G,Neutral!$A10,Data!$DT:$DT)+'Rate History'!$C$30*SUMIF(Data!$G:$G,Neutral!$A10,Data!$DV:$DV)+'Rate History'!$C$31*SUMIF(Data!$G:$G,Neutral!$A10,Data!$DW:$DW)) -> 44307018 | D10: =C10-B10 -> 6185.3336 | E10: =IFERROR(D10/B10,"") -> 0.00013962116
A11: Blinn College | B11: =$B$5*('Rate History'!$D$4*SUMIF(Data!$G:$G,Neutral!$A11,Data!$CU:$CU)+'Rate History'!$D$5*SUMIF(Data!$G:$G,Neutral!$A11,Data!$CV:$CV)+'Rate History'!$D$6*SUMIF(Data!$G:$G,Neutral!$A11,Data!$CW:$CW)+'Rate History'!$D$7*SUMIF(Data!$G:$G,Neutral!$A11,Data!$CX:$CX)+'Rate History'!$D$8*SUMIF(Data!$G:$G,Neutral!$A11,Data!$CY:$CY)+'Rate History'!$D$9*SUMIF(Data!$G:$G,Neutral!$A11,Data!$CZ:$CZ)+'Rate History'!$D$10*SUMIF(Data!$G:$G,Neutral!$A11,Data!$DA:$DA)+'Rate History'!$D$11*SUMIF(Data!$G:$G,Neutral!$A11,Data!$DB:$DB)+'Rate History'!$D$12*SUMIF(Data!$G:$G,Neutral!$A11,Data!$DC:$DC)+'Rate History'!$D$13*SUMIF(Data!$G:$G,Neutral!$A11,Data!$DD:$DD)+'Rate History'!$D$14*SUMIF(Data!$G:$G,Neutral!$A11,Data!$DE:$DE)+'Rate History'!$D$15*SUMIF(Data!$G:$G,Neutral!$A11,Data!$DF:$DF)+'Rate History'!$D$16*SUMIF(Data!$G:$G,Neutral!$A11,Data!$DG:$DG)+'Rate History'!$D$17*SUMIF(Data!$G:$G,Neutral!$A11,Data!$DH:$DH)+'Rate History'!$D$18*SUMIF(Data!$G:$G,Neutral!$A11,Data!$DI:$DI)+'Rate History'!$D$19*SUMIF(Data!$G:$G,Neutral!$A11,Data!$DJ:$DJ)+'Rate History'!$D$20*SUMIF(Data!$G:$G,Neutral!$A11,Data!$DK:$DK)+'Rate History'!$D$21*SUMIF(Data!$G:$G,Neutral!$A11,Data!$DL:$DL)+'Rate History'!$D$22*SUMIF(Data!$G:$G,Neutral!$A11,Data!$DM:$DM)+'Rate History'!$D$23*SUMIF(Data!$G:$G,Neutral!$A11,Data!$DN:$DN)+'Rate History'!$D$24*SUMIF(Data!$G:$G,Neutral!$A11,Data!$DO:$DO)+'Rate History'!$D$25*SUMIF(Data!$G:$G,Neutral!$A11,Data!$DP:$DP)+'Rate History'!$D$26*SUMIF(Data!$G:$G,Neutral!$A11,Data!$DQ:$DQ)+'Rate History'!$D$27*SUMIF(Data!$G:$G,Neutral!$A11,Data!$DR:$DR)+'Rate History'!$D$28*SUMIF(Data!$G:$G,Neutral!$A11,Data!$DS:$DS)+'Rate History'!$D$29*SUMIF(Data!$G:$G,Neutral!$A11,Data!$DT:$DT)+'Rate History'!$D$30*SUMIF(Data!$G:$G,Neutral!$A11,Data!$DV:$DV)+'Rate History'!$D$31*SUMIF(Data!$G:$G,Neutral!$A11,Data!$DW:$DW)) -> 21792602 | C11: =$C$5*('Rate History'!$C$4*SUMIF(Data!$G:$G,Neutral!$A11,Data!$CU:$CU)+'Rate History'!$C$5*SUMIF(Data!$G:$G,Neutral!$A11,Data!$CV:$CV)+'Rate History'!$C$6*SUMIF(Data!$G:$G,Neutral!$A11,Data!$CW:$CW)+'Rate History'!$C$7*SUMIF(Data!$G:$G,Neutral!$A11,Data!$CX:$CX)+'Rate History'!$C$8*SUMIF(Data!$G:$G,Neutral!$A11,Data!$CY:$CY)+'Rate History'!$C$9*SUMIF(Data!$G:$G,Neutral!$A11,Data!$CZ:$CZ)+'Rate History'!$C$10*SUMIF(Data!$G:$G,Neutral!$A11,Data!$DA:$DA)+'Rate History'!$C$11*SUMIF(Data!$G:$G,Neutral!$A11,Data!$DB:$DB)+'Rate History'!$C$12*SUMIF(Data!$G:$G,Neutral!$A11,Data!$DC:$DC)+'Rate History'!$C$13*SUMIF(Data!$G:$G,Neutral!$A11,Data!$DD:$DD)+'Rate History'!$C$14*SUMIF(Data!$G:$G,Neutral!$A11,Data!$DE:$DE)+'Rate History'!$C$15*SUMIF(Data!$G:$G,Neutral!$A11,Data!$DF:$DF)+'Rate History'!$C$16*SUMIF(Data!$G:$G,Neutral!$A11,Data!$DG:$DG)+'Rate History'!$C$17*SUMIF(Data!$G:$G,Neutral!$A11,Data!$DH:$DH)+'Rate History'!$C$18*SUMIF(Data!$G:$G,Neutral!$A11,Data!$DI:$DI)+'Rate History'!$C$19*SUMIF(Data!$G:$G,Neutral!$A11,Data!$DJ:$DJ)+'Rate History'!$C$20*SUMIF(Data!$G:$G,Neutral!$A11,Data!$DK:$DK)+'Rate History'!$C$21*SUMIF(Data!$G:$G,Neutral!$A11,Data!$DL:$DL)+'Rate History'!$C$22*SUMIF(Data!$G:$G,Neutral!$A11,Data!$DM:$DM)+'Rate History'!$C$23*SUMIF(Data!$G:$G,Neutral!$A11,Data!$DN:$DN)+'Rate History'!$C$24*SUMIF(Data!$G:$G,Neutral!$A11,Data!$DO:$DO)+'Rate History'!$C$25*SUMIF(Data!$G:$G,Neutral!$A11,Data!$DP:$DP)+'Rate History'!$C$26*SUMIF(Data!$G:$G,Neutral!$A11,Data!$DQ:$DQ)+'Rate History'!$C$27*SUMIF(Data!$G:$G,Neutral!$A11,Data!$DR:$DR)+'Rate History'!$C$28*SUMIF(Data!$G:$G,Neutral!$A11,Data!$DS:$DS)+'Rate History'!$C$29*SUMIF(Data!$G:$G,Neutral!$A11,Data!$DT:$DT)+'Rate History'!$C$30*SUMIF(Data!$G:$G,Neutral!$A11,Data!$DV:$DV)+'Rate History'!$C$31*SUMIF(Data!$G:$G,Neutral!$A11,Data!$DW:$DW)) -> 21864675 | D11: =C11-B11 -> 72073.084 | E11: =IFERROR(D11/B11,"") -> 0.0033072271
A12: Brazosport College | B12: =$B$5*('Rate History'!$D$4*SUMIF(Data!$G:$G,Neutral!$A12,Data!$CU:$CU)+'Rate History'!$D$5*SUMIF(Data!$G:$G,Neutral!$A12,Data!$CV:$CV)+'Rate History'!$D$6*SUMIF(Data!$G:$G,Neutral!$A12,Data!$CW:$CW)+'Rate History'!$D$7*SUMIF(Data!$G:$G,Neutral!$A12,Data!$CX:$CX)+'Rate History'!$D$8*SUMIF(Data!$G:$G,Neutral!$A12,Data!$CY:$CY)+'Rate History'!$D$9*SUMIF(Data!$G:$G,Neutral!$A12,Data!$CZ:$CZ)+'Rate History'!$D$10*SUMIF(Data!$G:$G,Neutral!$A12,Data!$DA:$DA)+'Rate History'!$D$11*SUMIF(Data!$G:$G,Neutral!$A12,Data!$DB:$DB)+'Rate History'!$D$12*SUMIF(Data!$G:$G,Neutral!$A12,Data!$DC:$DC)+'Rate History'!$D$13*SUMIF(Data!$G:$G,Neutral!$A12,Data!$DD:$DD)+'Rate History'!$D$14*SUMIF(Data!$G:$G,Neutral!$A12,Data!$DE:$DE)+'Rate History'!$D$15*SUMIF(Data!$G:$G,Neutral!$A12,Data!$DF:$DF)+'Rate History'!$D$16*SUMIF(Data!$G:$G,Neutral!$A12,Data!$DG:$DG)+'Rate History'!$D$17*SUMIF(Data!$G:$G,Neutral!$A12,Data!$DH:$DH)+'Rate History'!$D$18*SUMIF(Data!$G:$G,Neutral!$A12,Data!$DI:$DI)+'Rate History'!$D$19*SUMIF(Data!$G:$G,Neutral!$A12,Data!$DJ:$DJ)+'Rate History'!$D$20*SUMIF(Data!$G:$G,Neutral!$A12,Data!$DK:$DK)+'Rate History'!$D$21*SUMIF(Data!$G:$G,Neutral!$A12,Data!$DL:$DL)+'Rate History'!$D$22*SUMIF(Data!$G:$G,Neutral!$A12,Data!$DM:$DM)+'Rate History'!$D$23*SUMIF(Data!$G:$G,Neutral!$A12,Data!$DN:$DN)+'Rate History'!$D$24*SUMIF(Data!$G:$G,Neutral!$A12,Data!$DO:$DO)+'Rate History'!$D$25*SUMIF(Data!$G:$G,Neutral!$A12,Data!$DP:$DP)+'Rate History'!$D$26*SUMIF(Data!$G:$G,Neutral!$A12,Data!$DQ:$DQ)+'Rate History'!$D$27*SUMIF(Data!$G:$G,Neutral!$A12,Data!$DR:$DR)+'Rate History'!$D$28*SUMIF(Data!$G:$G,Neutral!$A12,Data!$DS:$DS)+'Rate History'!$D$29*SUMIF(Data!$G:$G,Neutral!$A12,Data!$DT:$DT)+'Rate History'!$D$30*SUMIF(Data!$G:$G,Neutral!$A12,Data!$DV:$DV)+'Rate History'!$D$31*SUMIF(Data!$G:$G,Neutral!$A12,Data!$DW:$DW)) -> 5196085.9 | C12: =$C$5*('Rate History'!$C$4*SUMIF(Data!$G:$G,Neutral!$A12,Data!$CU:$CU)+'Rate History'!$C$5*SUMIF(Data!$G:$G,Neutral!$A12,Data!$CV:$CV)+'Rate History'!$C$6*SUMIF(Data!$G:$G,Neutral!$A12,Data!$CW:$CW)+'Rate History'!$C$7*SUMIF(Data!$G:$G,Neutral!$A12,Data!$CX:$CX)+'Rate History'!$C$8*SUMIF(Data!$G:$G,Neutral!$A12,Data!$CY:$CY)+'Rate History'!$C$9*SUMIF(Data!$G:$G,Neutral!$A12,Data!$CZ:$CZ)+'Rate History'!$C$10*SUMIF(Data!$G:$G,Neutral!$A12,Data!$DA:$DA)+'Rate History'!$C$11*SUMIF(Data!$G:$G,Neutral!$A12,Data!$DB:$DB)+'Rate History'!$C$12*SUMIF(Data!$G:$G,Neutral!$A12,Data!$DC:$DC)+'Rate History'!$C$13*SUMIF(Data!$G:$G,Neutral!$A12,Data!$DD:$DD)+'Rate History'!$C$14*SUMIF(Data!$G:$G,Neutral!$A12,Data!$DE:$DE)+'Rate History'!$C$15*SUMIF(Data!$G:$G,Neutral!$A12,Data!$DF:$DF)+'Rate History'!$C$16*SUMIF(Data!$G:$G,Neutral!$A12,Data!$DG:$DG)+'Rate History'!$C$17*SUMIF(Data!$G:$G,Neutral!$A12,Data!$DH:$DH)+'Rate History'!$C$18*SUMIF(Data!$G:$G,Neutral!$A12,Data!$DI:$DI)+'Rate History'!$C$19*SUMIF(Data!$G:$G,Neutral!$A12,Data!$DJ:$DJ)+'Rate History'!$C$20*SUMIF(Data!$G:$G,Neutral!$A12,Data!$DK:$DK)+'Rate History'!$C$21*SUMIF(Data!$G:$G,Neutral!$A12,Data!$DL:$DL)+'Rate History'!$C$22*SUMIF(Data!$G:$G,Neutral!$A12,Data!$DM:$DM)+'Rate History'!$C$23*SUMIF(Data!$G:$G,Neutral!$A12,Data!$DN:$DN)+'Rate History'!$C$24*SUMIF(Data!$G:$G,Neutral!$A12,Data!$DO:$DO)+'Rate History'!$C$25*SUMIF(Data!$G:$G,Neutral!$A12,Data!$DP:$DP)+'Rate History'!$C$26*SUMIF(Data!$G:$G,Neutral!$A12,Data!$DQ:$DQ)+'Rate History'!$C$27*SUMIF(Data!$G:$G,Neutral!$A12,Data!$DR:$DR)+'Rate History'!$C$28*SUMIF(Data!$G:$G,Neutral!$A12,Data!$DS:$DS)+'Rate History'!$C$29*SUMIF(Data!$G:$G,Neutral!$A12,Data!$DT:$DT)+'Rate History'!$C$30*SUMIF(Data!$G:$G,Neutral!$A12,Data!$DV:$DV)+'Rate History'!$C$31*SUMIF(Data!$G:$G,Neutral!$A12,Data!$DW:$DW)) -> 5159650.4 | D12: =C12-B12 -> -36435.585 | E12: =IFERROR(D12/B12,"") -> -0.0070121214
A13: Central Texas College | B13: =$B$5*('Rate History'!$D$4*SUMIF(Data!$G:$G,Neutral!$A13,Data!$CU:$CU)+'Rate History'!$D$5*SUMIF(Data!$G:$G,Neutral!$A13,Data!$CV:$CV)+'Rate History'!$D$6*SUMIF(Data!$G:$G,Neutral!$A13,Data!$CW:$CW)+'Rate History'!$D$7*SUMIF(Data!$G:$G,Neutral!$A13,Data!$CX:$CX)+'Rate History'!$D$8*SUMIF(Data!$G:$G,Neutral!$A13,Data!$CY:$CY)+'Rate History'!$D$9*SUMIF(Data!$G:$G,Neutral!$A13,Data!$CZ:$CZ)+'Rate History'!$D$10*SUMIF(Data!$G:$G,Neutral!$A13,Data!$DA:$DA)+'Rate History'!$D$11*SUMIF(Data!$G:$G,Neutral!$A13,Data!$DB:$DB)+'Rate History'!$D$12*SUMIF(Data!$G:$G,Neutral!$A13,Data!$DC:$DC)+'Rate History'!$D$13*SUMIF(Data!$G:$G,Neutral!$A13,Data!$DD:$DD)+'Rate History'!$D$14*SUMIF(Data!$G:$G,Neutral!$A13,Data!$DE:$DE)+'Rate History'!$D$15*SUMIF(Data!$G:$G,Neutral!$A13,Data!$DF:$DF)+'Rate History'!$D$16*SUMIF(Data!$G:$G,Neutral!$A13,Data!$DG:$DG)+'Rate History'!$D$17*SUMIF(Data!$G:$G,Neutral!$A13,Data!$DH:$DH)+'Rate History'!$D$18*SUMIF(Data!$G:$G,Neutral!$A13,Data!$DI:$DI)+'Rate History'!$D$19*SUMIF(Data!$G:$G,Neutral!$A13,Data!$DJ:$DJ)+'Rate History'!$D$20*SUMIF(Data!$G:$G,Neutral!$A13,Data!$DK:$DK)+'Rate History'!$D$21*SUMIF(Data!$G:$G,Neutral!$A13,Data!$DL:$DL)+'Rate History'!$D$22*SUMIF(Data!$G:$G,Neutral!$A13,Data!$DM:$DM)+'Rate History'!$D$23*SUMIF(Data!$G:$G,Neutral!$A13,Data!$DN:$DN)+'Rate History'!$D$24*SUMIF(Data!$G:$G,Neutral!$A13,Data!$DO:$DO)+'Rate History'!$D$25*SUMIF(Data!$G:$G,Neutral!$A13,Data!$DP:$DP)+'Rate History'!$D$26*SUMIF(Data!$G:$G,Neutral!$A13,Data!$DQ:$DQ)+'Rate History'!$D$27*SUMIF(Data!$G:$G,Neutral!$A13,Data!$DR:$DR)+'Rate History'!$D$28*SUMIF(Data!$G:$G,Neutral!$A13,Data!$DS:$DS)+'Rate History'!$D$29*SUMIF(Data!$G:$G,Neutral!$A13,Data!$DT:$DT)+'Rate History'!$D$30*SUMIF(Data!$G:$G,Neutral!$A13,Data!$DV:$DV)+'Rate History'!$D$31*SUMIF(Data!$G:$G,Neutral!$A13,Data!$DW:$DW)) -> 20369867 | C13: =$C$5*('Rate History'!$C$4*SUMIF(Data!$G:$G,Neutral!$A13,Data!$CU:$CU)+'Rate History'!$C$5*SUMIF(Data!$G:$G,Neutral!$A13,Data!$CV:$CV)+'Rate History'!$C$6*SUMIF(Data!$G:$G,Neutral!$A13,Data!$CW:$CW)+'Rate History'!$C$7*SUMIF(Data!$G:$G,Neutral!$A13,Data!$CX:$CX)+'Rate History'!$C$8*SUMIF(Data!$G:$G,Neutral!$A13,Data!$CY:$CY)+'Rate History'!$C$9*SUMIF(Data!$G:$G,Neutral!$A13,Data!$CZ:$CZ)+'Rate History'!$C$10*SUMIF(Data!$G:$G,Neutral!$A13,Data!$DA:$DA)+'Rate History'!$C$11*SUMIF(Data!$G:$G,Neutral!$A13,Data!$DB:$DB)+'Rate History'!$C$12*SUMIF(Data!$G:$G,Neutral!$A13,Data!$DC:$DC)+'Rate History'!$C$13*SUMIF(Data!$G:$G,Neutral!$A13,Data!$DD:$DD)+'Rate History'!$C$14*SUMIF(Data!$G:$G,Neutral!$A13,Data!$DE:$DE)+'Rate History'!$C$15*SUMIF(Data!$G:$G,Neutral!$A13,Data!$DF:$DF)+'Rate History'!$C$16*SUMIF(Data!$G:$G,Neutral!$A13,Data!$DG:$DG)+'Rate History'!$C$17*SUMIF(Data!$G:$G,Neutral!$A13,Data!$DH:$DH)+'Rate History'!$C$18*SUMIF(Data!$G:$G,Neutral!$A13,Data!$DI:$DI)+'Rate History'!$C$19*SUMIF(Data!$G:$G,Neutral!$A13,Data!$DJ:$DJ)+'Rate History'!$C$20*SUMIF(Data!$G:$G,Neutral!$A13,Data!$DK:$DK)+'Rate History'!$C$21*SUMIF(Data!$G:$G,Neutral!$A13,Data!$DL:$DL)+'Rate History'!$C$22*SUMIF(Data!$G:$G,Neutral!$A13,Data!$DM:$DM)+'Rate History'!$C$23*SUMIF(Data!$G:$G,Neutral!$A13,Data!$DN:$DN)+'Rate History'!$C$24*SUMIF(Data!$G:$G,Neutral!$A13,Data!$DO:$DO)+'Rate History'!$C$25*SUMIF(Data!$G:$G,Neutral!$A13,Data!$DP:$DP)+'Rate History'!$C$26*SUMIF(Data!$G:$G,Neutral!$A13,Data!$DQ:$DQ)+'Rate History'!$C$27*SUMIF(Data!$G:$G,Neutral!$A13,Data!$DR:$DR)+'Rate History'!$C$28*SUMIF(Data!$G:$G,Neutral!$A13,Data!$DS:$DS)+'Rate History'!$C$29*SUMIF(Data!$G:$G,Neutral!$A13,Data!$DT:$DT)+'Rate History'!$C$30*SUMIF(Data!$G:$G,Neutral!$A13,Data!$DV:$DV)+'Rate History'!$C$31*SUMIF(Data!$G:$G,Neutral!$A13,Data!$DW:$DW)) -> 20347586 | D13: =C13-B13 -> -22280.5 | E13: =IFERROR(D13/B13,"") -> -0.001093797
A14: Cisco Junior College | B14: =$B$5*('Rate History'!$D$4*SUMIF(Data!$G:$G,Neutral!$A14,Data!$CU:$CU)+'Rate History'!$D$5*SUMIF(Data!$G:$G,Neutral!$A14,Data!$CV:$CV)+'Rate History'!$D$6*SUMIF(Data!$G:$G,Neutral!$A14,Data!$CW:$CW)+'Rate History'!$D$7*SUMIF(Data!$G:$G,Neutral!$A14,Data!$CX:$CX)+'Rate History'!$D$8*SUMIF(Data!$G:$G,Neutral!$A14,Data!$CY:$CY)+'Rate History'!$D$9*SUMIF(Data!$G:$G,Neutral!$A14,Data!$CZ:$CZ)+'Rate History'!$D$10*SUMIF(Data!$G:$G,Neutral!$A14,Data!$DA:$DA)+'Rate History'!$D$11*SUMIF(Data!$G:$G,Neutral!$A14,Data!$DB:$DB)+'Rate History'!$D$12*SUMIF(Data!$G:$G,Neutral!$A14,Data!$DC:$DC)+'Rate History'!$D$13*SUMIF(Data!$G:$G,Neutral!$A14,Data!$DD:$DD)+'Rate History'!$D$14*SUMIF(Data!$G:$G,Neutral!$A14,Data!$DE:$DE)+'Rate History'!$D$15*SUMIF(Data!$G:$G,Neutral!$A14,Data!$DF:$DF)+'Rate History'!$D$16*SUMIF(Data!$G:$G,Neutral!$A14,Data!$DG:$DG)+'Rate History'!$D$17*SUMIF(Data!$G:$G,Neutral!$A14,Data!$DH:$DH)+'Rate History'!$D$18*SUMIF(Data!$G:$G,Neutral!$A14,Data!$DI:$DI)+'Rate History'!$D$19*SUMIF(Data!$G:$G,Neutral!$A14,Data!$DJ:$DJ)+'Rate History'!$D$20*SUMIF(Data!$G:$G,Neutral!$A14,Data!$DK:$DK)+'Rate History'!$D$21*SUMIF(Data!$G:$G,Neutral!$A14,Data!$DL:$DL)+'Rate History'!$D$22*SUMIF(Data!$G:$G,Neutral!$A14,Data!$DM:$DM)+'Rate History'!$D$23*SUMIF(Data!$G:$G,Neutral!$A14,Data!$DN:$DN)+'Rate History'!$D$24*SUMIF(Data!$G:$G,Neutral!$A14,Data!$DO:$DO)+'Rate History'!$D$25*SUMIF(Data!$G:$G,Neutral!$A14,Data!$DP:$DP)+'Rate History'!$D$26*SUMIF(Data!$G:$G,Neutral!$A14,Data!$DQ:$DQ)+'Rate History'!$D$27*SUMIF(Data!$G:$G,Neutral!$A14,Data!$DR:$DR)+'Rate History'!$D$28*SUMIF(Data!$G:$G,Neutral!$A14,Data!$DS:$DS)+'Rate History'!$D$29*SUMIF(Data!$G:$G,Neutral!$A14,Data!$DT:$DT)+'Rate History'!$D$30*SUMIF(Data!$G:$G,Neutral!$A14,Data!$DV:$DV)+'Rate History'!$D$31*SUMIF(Data!$G:$G,Neutral!$A14,Data!$DW:$DW)) -> 5268484.7 | C14: =$C$5*('Rate History'!$C$4*SUMIF(Data!$G:$G,Neutral!$A14,Data!$CU:$CU)+'Rate History'!$C$5*SUMIF(Data!$G:$G,Neutral!$A14,Data!$CV:$CV)+'Rate History'!$C$6*SUMIF(Data!$G:$G,Neutral!$A14,Data!$CW:$CW)+'Rate History'!$C$7*SUMIF(Data!$G:$G,Neutral!$A14,Data!$CX:$CX)+'Rate History'!$C$8*SUMIF(Data!$G:$G,Neutral!$A14,Data!$CY:$CY)+'Rate History'!$C$9*SUMIF(Data!$G:$G,Neutral!$A14,Data!$CZ:$CZ)+'Rate History'!$C$10*SUMIF(Data!$G:$G,Neutral!$A14,Data!$DA:$DA)+'Rate History'!$C$11*SUMIF(Data!$G:$G,Neutral!$A14,Data!$DB:$DB)+'Rate History'!$C$12*SUMIF(Data!$G:$G,Neutral!$A14,Data!$DC:$DC)+'Rate History'!$C$13*SUMIF(Data!$G:$G,Neutral!$A14,Data!$DD:$DD)+'Rate History'!$C$14*SUMIF(Data!$G:$G,Neutral!$A14,Data!$DE:$DE)+'Rate History'!$C$15*SUMIF(Data!$G:$G,Neutral!$A14,Data!$DF:$DF)+'Rate History'!$C$16*SUMIF(Data!$G:$G,Neutral!$A14,Data!$DG:$DG)+'Rate History'!$C$17*SUMIF(Data!$G:$G,Neutral!$A14,Data!$DH:$DH)+'Rate History'!$C$18*SUMIF(Data!$G:$G,Neutral!$A14,Data!$DI:$DI)+'Rate History'!$C$19*SUMIF(Data!$G:$G,Neutral!$A14,Data!$DJ:$DJ)+'Rate History'!$C$20*SUMIF(Data!$G:$G,Neutral!$A14,Data!$DK:$DK)+'Rate History'!$C$21*SUMIF(Data!$G:$G,Neutral!$A14,Data!$DL:$DL)+'Rate History'!$C$22*SUMIF(Data!$G:$G,Neutral!$A14,Data!$DM:$DM)+'Rate History'!$C$23*SUMIF(Data!$G:$G,Neutral!$A14,Data!$DN:$DN)+'Rate History'!$C$24*SUMIF(Data!$G:$G,Neutral!$A14,Data!$DO:$DO)+'Rate History'!$C$25*SUMIF(Data!$G:$G,Neutral!$A14,Data!$DP:$DP)+'Rate History'!$C$26*SUMIF(Data!$G:$G,Neutral!$A14,Data!$DQ:$DQ)+'Rate History'!$C$27*SUMIF(Data!$G:$G,Neutral!$A14,Data!$DR:$DR)+'Rate History'!$C$28*SUMIF(Data!$G:$G,Neutral!$A14,Data!$DS:$DS)+'Rate History'!$C$29*SUMIF(Data!$G:$G,Neutral!$A14,Data!$DT:$DT)+'Rate History'!$C$30*SUMIF(Data!$G:$G,Neutral!$A14,Data!$DV:$DV)+'Rate History'!$C$31*SUMIF(Data!$G:$G,Neutral!$A14,Data!$DW:$DW)) -> 5265243.4 | D14: =C14-B14 -> -3241.2702 | E14: =IFERROR(D14/B14,"") -> -0.00061521869
A15: Clarendon College | B15: =$B$5*('Rate History'!$D$4*SUMIF(Data!$G:$G,Neutral!$A15,Data!$CU:$CU)+'Rate History'!$D$5*SUMIF(Data!$G:$G,Neutral!$A15,Data!$CV:$CV)+'Rate History'!$D$6*SUMIF(Data!$G:$G,Neutral!$A15,Data!$CW:$CW)+'Rate History'!$D$7*SUMIF(Data!$G:$G,Neutral!$A15,Data!$CX:$CX)+'Rate History'!$D$8*SUMIF(Data!$G:$G,Neutral!$A15,Data!$CY:$CY)+'Rate History'!$D$9*SUMIF(Data!$G:$G,Neutral!$A15,Data!$CZ:$CZ)+'Rate History'!$D$10*SUMIF(Data!$G:$G,Neutral!$A15,Data!$DA:$DA)+'Rate History'!$D$11*SUMIF(Data!$G:$G,Neutral!$A15,Data!$DB:$DB)+'Rate History'!$D$12*SUMIF(Data!$G:$G,Neutral!$A15,Data!$DC:$DC)+'Rate History'!$D$13*SUMIF(Data!$G:$G,Neutral!$A15,Data!$DD:$DD)+'Rate History'!$D$14*SUMIF(Data!$G:$G,Neutral!$A15,Data!$DE:$DE)+'Rate History'!$D$15*SUMIF(Data!$G:$G,Neutral!$A15,Data!$DF:$DF)+'Rate History'!$D$16*SUMIF(Data!$G:$G,Neutral!$A15,Data!$DG:$DG)+'Rate History'!$D$17*SUMIF(Data!$G:$G,Neutral!$A15,Data!$DH:$DH)+'Rate History'!$D$18*SUMIF(Data!$G:$G,Neutral!$A15,Data!$DI:$DI)+'Rate History'!$D$19*SUMIF(Data!$G:$G,Neutral!$A15,Data!$DJ:$DJ)+'Rate History'!$D$20*SUMIF(Data!$G:$G,Neutral!$A15,Data!$DK:$DK)+'Rate History'!$D$21*SUMIF(Data!$G:$G,Neutral!$A15,Data!$DL:$DL)+'Rate History'!$D$22*SUMIF(Data!$G:$G,Neutral!$A15,Data!$DM:$DM)+'Rate History'!$D$23*SUMIF(Data!$G:$G,Neutral!$A15,Data!$DN:$DN)+'Rate History'!$D$24*SUMIF(Data!$G:$G,Neutral!$A15,Data!$DO:$DO)+'Rate History'!$D$25*SUMIF(Data!$G:$G,Neutral!$A15,Data!$DP:$DP)+'Rate History'!$D$26*SUMIF(Data!$G:$G,Neutral!$A15,Data!$DQ:$DQ)+'Rate History'!$D$27*SUMIF(Data!$G:$G,Neutral!$A15,Data!$DR:$DR)+'Rate History'!$D$28*SUMIF(Data!$G:$G,Neutral!$A15,Data!$DS:$DS)+'Rate History'!$D$29*SUMIF(Data!$G:$G,Neutral!$A15,Data!$DT:$DT)+'Rate History'!$D$30*SUMIF(Data!$G:$G,Neutral!$A15,Data!$DV:$DV)+'Rate History'!$D$31*SUMIF(Data!$G:$G,Neutral!$A15,Data!$DW:$DW)) -> 1915276.6 | C15: =$C$5*('Rate History'!$C$4*SUMIF(Data!$G:$G,Neutral!$A15,Data!$CU:$CU)+'Rate History'!$C$5*SUMIF(Data!$G:$G,Neutral!$A15,Data!$CV:$CV)+'Rate History'!$C$6*SUMIF(Data!$G:$G,Neutral!$A15,Data!$CW:$CW)+'Rate History'!$C$7*SUMIF(Data!$G:$G,Neutral!$A15,Data!$CX:$CX)+'Rate History'!$C$8*SUMIF(Data!$G:$G,Neutral!$A15,Data!$CY:$CY)+'Rate History'!$C$9*SUMIF(Data!$G:$G,Neutral!$A15,Data!$CZ:$CZ)+'Rate History'!$C$10*SUMIF(Data!$G:$G,Neutral!$A15,Data!$DA:$DA)+'Rate History'!$C$11*SUMIF(Data!$G:$G,Neutral!$A15,Data!$DB:$DB)+'Rate History'!$C$12*SUMIF(Data!$G:$G,Neutral!$A15,Data!$DC:$DC)+'Rate History'!$C$13*SUMIF(Data!$G:$G,Neutral!$A15,Data!$DD:$DD)+'Rate History'!$C$14*SUMIF(Data!$G:$G,Neutral!$A15,Data!$DE:$DE)+'Rate History'!$C$15*SUMIF(Data!$G:$G,Neutral!$A15,Data!$DF:$DF)+'Rate History'!$C$16*SUMIF(Data!$G:$G,Neutral!$A15,Data!$DG:$DG)+'Rate History'!$C$17*SUMIF(Data!$G:$G,Neutral!$A15,Data!$DH:$DH)+'Rate History'!$C$18*SUMIF(Data!$G:$G,Neutral!$A15,Data!$DI:$DI)+'Rate History'!$C$19*SUMIF(Data!$G:$G,Neutral!$A15,Data!$DJ:$DJ)+'Rate History'!$C$20*SUMIF(Data!$G:$G,Neutral!$A15,Data!$DK:$DK)+'Rate History'!$C$21*SUMIF(Data!$G:$G,Neutral!$A15,Data!$DL:$DL)+'Rate History'!$C$22*SUMIF(Data!$G:$G,Neutral!$A15,Data!$DM:$DM)+'Rate History'!$C$23*SUMIF(Data!$G:$G,Neutral!$A15,Data!$DN:$DN)+'Rate History'!$C$24*SUMIF(Data!$G:$G,Neutral!$A15,Data!$DO:$DO)+'Rate History'!$C$25*SUMIF(Data!$G:$G,Neutral!$A15,Data!$DP:$DP)+'Rate History'!$C$26*SUMIF(Data!$G:$G,Neutral!$A15,Data!$DQ:$DQ)+'Rate History'!$C$27*SUMIF(Data!$G:$G,Neutral!$A15,Data!$DR:$DR)+'Rate History'!$C$28*SUMIF(Data!$G:$G,Neutral!$A15,Data!$DS:$DS)+'Rate History'!$C$29*SUMIF(Data!$G:$G,Neutral!$A15,Data!$DT:$DT)+'Rate History'!$C$30*SUMIF(Data!$G:$G,Neutral!$A15,Data!$DV:$DV)+'Rate History'!$C$31*SUMIF(Data!$G:$G,Neutral!$A15,Data!$DW:$DW)) -> 1926334.8 | D15: =C15-B15 -> 11058.262 | E15: =IFERROR(D15/B15,"") -> 0.0057737153
A16: Coastal Bend College | B16: =$B$5*('Rate History'!$D$4*SUMIF(Data!$G:$G,Neutral!$A16,Data!$CU:$CU)+'Rate History'!$D$5*SUMIF(Data!$G:$G,Neutral!$A16,Data!$CV:$CV)+'Rate History'!$D$6*SUMIF(Data!$G:$G,Neutral!$A16,Data!$CW:$CW)+'Rate History'!$D$7*SUMIF(Data!$G:$G,Neutral!$A16,Data!$CX:$CX)+'Rate History'!$D$8*SUMIF(Data!$G:$G,Neutral!$A16,Data!$CY:$CY)+'Rate History'!$D$9*SUMIF(Data!$G:$G,Neutral!$A16,Data!$CZ:$CZ)+'Rate History'!$D$10*SUMIF(Data!$G:$G,Neutral!$A16,Data!$DA:$DA)+'Rate History'!$D$11*SUMIF(Data!$G:$G,Neutral!$A16,Data!$DB:$DB)+'Rate History'!$D$12*SUMIF(Data!$G:$G,Neutral!$A16,Data!$DC:$DC)+'Rate History'!$D$13*SUMIF(Data!$G:$G,Neutral!$A16,Data!$DD:$DD)+'Rate History'!$D$14*SUMIF(Data!$G:$G,Neutral!$A16,Data!$DE:$DE)+'Rate History'!$D$15*SUMIF(Data!$G:$G,Neutral!$A16,Data!$DF:$DF)+'Rate History'!$D$16*SUMIF(Data!$G:$G,Neutral!$A16,Data!$DG:$DG)+'Rate History'!$D$17*SUMIF(Data!$G:$G,Neutral!$A16,Data!$DH:$DH)+'Rate History'!$D$18*SUMIF(Data!$G:$G,Neutral!$A16,Data!$DI:$DI)+'Rate History'!$D$19*SUMIF(Data!$G:$G,Neutral!$A16,Data!$DJ:$DJ)+'Rate History'!$D$20*SUMIF(Data!$G:$G,Neutral!$A16,Data!$DK:$DK)+'Rate History'!$D$21*SUMIF(Data!$G:$G,Neutral!$A16,Data!$DL:$DL)+'Rate History'!$D$22*SUMIF(Data!$G:$G,Neutral!$A16,Data!$DM:$DM)+'Rate History'!$D$23*SUMIF(Data!$G:$G,Neutral!$A16,Data!$DN:$DN)+'Rate History'!$D$24*SUMIF(Data!$G:$G,Neutral!$A16,Data!$DO:$DO)+'Rate History'!$D$25*SUMIF(Data!$G:$G,Neutral!$A16,Data!$DP:$DP)+'Rate History'!$D$26*SUMIF(Data!$G:$G,Neutral!$A16,Data!$DQ:$DQ)+'Rate History'!$D$27*SUMIF(Data!$G:$G,Neutral!$A16,Data!$DR:$DR)+'Rate History'!$D$28*SUMIF(Data!$G:$G,Neutral!$A16,Data!$DS:$DS)+'Rate History'!$D$29*SUMIF(Data!$G:$G,Neutral!$A16,Data!$DT:$DT)+'Rate History'!$D$30*SUMIF(Data!$G:$G,Neutral!$A16,Data!$DV:$DV)+'Rate History'!$D$31*SUMIF(Data!$G:$G,Neutral!$A16,Data!$DW:$DW)) -> 5864400.1 | C16: =$C$5*('Rate History'!$C$4*SUMIF(Data!$G:$G,Neutral!$A16,Data!$CU:$CU)+'Rate History'!$C$5*SUMIF(Data!$G:$G,Neutral!$A16,Data!$CV:$CV)+'Rate History'!$C$6*SUMIF(Data!$G:$G,Neutral!$A16,Data!$CW:$CW)+'Rate History'!$C$7*SUMIF(Data!$G:$G,Neutral!$A16,Data!$CX:$CX)+'Rate History'!$C$8*SUMIF(Data!$G:$G,Neutral!$A16,Data!$CY:$CY)+'Rate History'!$C$9*SUMIF(Data!$G:$G,Neutral!$A16,Data!$CZ:$CZ)+'Rate History'!$C$10*SUMIF(Data!$G:$G,Neutral!$A16,Data!$DA:$DA)+'Rate History'!$C$11*SUMIF(Data!$G:$G,Neutral!$A16,Data!$DB:$DB)+'Rate History'!$C$12*SUMIF(Data!$G:$G,Neutral!$A16,Data!$DC:$DC)+'Rate History'!$C$13*SUMIF(Data!$G:$G,Neutral!$A16,Data!$DD:$DD)+'Rate History'!$C$14*SUMIF(Data!$G:$G,Neutral!$A16,Data!$DE:$DE)+'Rate History'!$C$15*SUMIF(Data!$G:$G,Neutral!$A16,Data!$DF:$DF)+'Rate History'!$C$16*SUMIF(Data!$G:$G,Neutral!$A16,Data!$DG:$DG)+'Rate History'!$C$17*SUMIF(Data!$G:$G,Neutral!$A16,Data!$DH:$DH)+'Rate History'!$C$18*SUMIF(Data!$G:$G,Neutral!$A16,Data!$DI:$DI)+'Rate History'!$C$19*SUMIF(Data!$G:$G,Neutral!$A16,Data!$DJ:$DJ)+'Rate History'!$C$20*SUMIF(Data!$G:$G,Neutral!$A16,Data!$DK:$DK)+'Rate History'!$C$21*SUMIF(Data!$G:$G,Neutral!$A16,Data!$DL:$DL)+'Rate History'!$C$22*SUMIF(Data!$G:$G,Neutral!$A16,Data!$DM:$DM)+'Rate History'!$C$23*SUMIF(Data!$G:$G,Neutral!$A16,Data!$DN:$DN)+'Rate History'!$C$24*SUMIF(Data!$G:$G,Neutral!$A16,Data!$DO:$DO)+'Rate History'!$C$25*SUMIF(Data!$G:$G,Neutral!$A16,Data!$DP:$DP)+'Rate History'!$C$26*SUMIF(Data!$G:$G,Neutral!$A16,Data!$DQ:$DQ)+'Rate History'!$C$27*SUMIF(Data!$G:$G,Neutral!$A16,Data!$DR:$DR)+'Rate History'!$C$28*SUMIF(Data!$G:$G,Neutral!$A16,Data!$DS:$DS)+'Rate History'!$C$29*SUMIF(Data!$G:$G,Neutral!$A16,Data!$DT:$DT)+'Rate History'!$C$30*SUMIF(Data!$G:$G,Neutral!$A16,Data!$DV:$DV)+'Rate History'!$C$31*SUMIF(Data!$G:$G,Neutral!$A16,Data!$DW:$DW)) -> 5872751 | D16: =C16-B16 -> 8350.8386 | E16: =IFERROR(D16/B16,"") -> 0.0014239886
A17: College of the Mainland Community College District | B17: =$B$5*('Rate History'!$D$4*SUMIF(Data!$G:$G,Neutral!$A17,Data!$CU:$CU)+'Rate History'!$D$5*SUMIF(Data!$G:$G,Neutral!$A17,Data!$CV:$CV)+'Rate History'!$D$6*SUMIF(Data!$G:$G,Neutral!$A17,Data!$CW:$CW)+'Rate History'!$D$7*SUMIF(Data!$G:$G,Neutral!$A17,Data!$CX:$CX)+'Rate History'!$D$8*SUMIF(Data!$G:$G,Neutral!$A17,Data!$CY:$CY)+'Rate History'!$D$9*SUMIF(Data!$G:$G,Neutral!$A17,Data!$CZ:$CZ)+'Rate History'!$D$10*SUMIF(Data!$G:$G,Neutral!$A17,Data!$DA:$DA)+'Rate History'!$D$11*SUMIF(Data!$G:$G,Neutral!$A17,Data!$DB:$DB)+'Rate History'!$D$12*SUMIF(Data!$G:$G,Neutral!$A17,Data!$DC:$DC)+'Rate History'!$D$13*SUMIF(Data!$G:$G,Neutral!$A17,Data!$DD:$DD)+'Rate History'!$D$14*SUMIF(Data!$G:$G,Neutral!$A17,Data!$DE:$DE)+'Rate History'!$D$15*SUMIF(Data!$G:$G,Neutral!$A17,Data!$DF:$DF)+'Rate History'!$D$16*SUMIF(Data!$G:$G,Neutral!$A17,Data!$DG:$DG)+'Rate History'!$D$17*SUMIF(Data!$G:$G,Neutral!$A17,Data!$DH:$DH)+'Rate History'!$D$18*SUMIF(Data!$G:$G,Neutral!$A17,Data!$DI:$DI)+'Rate History'!$D$19*SUMIF(Data!$G:$G,Neutral!$A17,Data!$DJ:$DJ)+'Rate History'!$D$20*SUMIF(Data!$G:$G,Neutral!$A17,Data!$DK:$DK)+'Rate History'!$D$21*SUMIF(Data!$G:$G,Neutral!$A17,Data!$DL:$DL)+'Rate History'!$D$22*SUMIF(Data!$G:$G,Neutral!$A17,Data!$DM:$DM)+'Rate History'!$D$23*SUMIF(Data!$G:$G,Neutral!$A17,Data!$DN:$DN)+'Rate History'!$D$24*SUMIF(Data!$G:$G,Neutral!$A17,Data!$DO:$DO)+'Rate History'!$D$25*SUMIF(Data!$G:$G,Neutral!$A17,Data!$DP:$DP)+'Rate History'!$D$26*SUMIF(Data!$G:$G,Neutral!$A17,Data!$DQ:$DQ)+'Rate History'!$D$27*SUMIF(Data!$G:$G,Neutral!$A17,Data!$DR:$DR)+'Rate History'!$D$28*SUMIF(Data!$G:$G,Neutral!$A17,Data!$DS:$DS)+'Rate History'!$D$29*SUMIF(Data!$G:$G,Neutral!$A17,Data!$DT:$DT)+'Rate History'!$D$30*SUMIF(Data!$G:$G,Neutral!$A17,Data!$DV:$DV)+'Rate History'!$D$31*SUMIF(Data!$G:$G,Neutral!$A17,Data!$DW:$DW)) -> 6199680.4 | C17: =$C$5*('Rate History'!$C$4*SUMIF(Data!$G:$G,Neutral!$A17,Data!$CU:$CU)+'Rate History'!$C$5*SUMIF(Data!$G:$G,Neutral!$A17,Data!$CV:$CV)+'Rate History'!$C$6*SUMIF(Data!$G:$G,Neutral!$A17,Data!$CW:$CW)+'Rate History'!$C$7*SUMIF(Data!$G:$G,Neutral!$A17,Data!$CX:$CX)+'Rate History'!$C$8*SUMIF(Data!$G:$G,Neutral!$A17,Data!$CY:$CY)+'Rate History'!$C$9*SUMIF(Data!$G:$G,Neutral!$A17,Data!$CZ:$CZ)+'Rate History'!$C$10*SUMIF(Data!$G:$G,Neutral!$A17,Data!$DA:$DA)+'Rate History'!$C$11*SUMIF(Data!$G:$G,Neutral!$A17,Data!$DB:$DB)+'Rate History'!$C$12*SUMIF(Data!$G:$G,Neutral!$A17,Data!$DC:$DC)+'Rate History'!$C$13*SUMIF(Data!$G:$G,Neutral!$A17,Data!$DD:$DD)+'Rate History'!$C$14*SUMIF(Data!$G:$G,Neutral!$A17,Data!$DE:$DE)+'Rate History'!$C$15*SUMIF(Data!$G:$G,Neutral!$A17,Data!$DF:$DF)+'Rate History'!$C$16*SUMIF(Data!$G:$G,Neutral!$A17,Data!$DG:$DG)+'Rate History'!$C$17*SUMIF(Data!$G:$G,Neutral!$A17,Data!$DH:$DH)+'Rate History'!$C$18*SUMIF(Data!$G:$G,Neutral!$A17,Data!$DI:$DI)+'Rate History'!$C$19*SUMIF(Data!$G:$G,Neutral!$A17,Data!$DJ:$DJ)+'Rate History'!$C$20*SUMIF(Data!$G:$G,Neutral!$A17,Data!$DK:$DK)+'Rate History'!$C$21*SUMIF(Data!$G:$G,Neutral!$A17,Data!$DL:$DL)+'Rate History'!$C$22*SUMIF(Data!$G:$G,Neutral!$A17,Data!$DM:$DM)+'Rate History'!$C$23*SUMIF(Data!$G:$G,Neutral!$A17,Data!$DN:$DN)+'Rate History'!$C$24*SUMIF(Data!$G:$G,Neutral!$A17,Data!$DO:$DO)+'Rate History'!$C$25*SUMIF(Data!$G:$G,Neutral!$A17,Data!$DP:$DP)+'Rate History'!$C$26*SUMIF(Data!$G:$G,Neutral!$A17,Data!$DQ:$DQ)+'Rate History'!$C$27*SUMIF(Data!$G:$G,Neutral!$A17,Data!$DR:$DR)+'Rate History'!$C$28*SUMIF(Data!$G:$G,Neutral!$A17,Data!$DS:$DS)+'Rate History'!$C$29*SUMIF(Data!$G:$G,Neutral!$A17,Data!$DT:$DT)+'Rate History'!$C$30*SUMIF(Data!$G:$G,Neutral!$A17,Data!$DV:$DV)+'Rate History'!$C$31*SUMIF(Data!$G:$G,Neutral!$A17,Data!$DW:$DW)) -> 6171954.7 | D17: =C17-B17 -> -27725.785 | E17: =IFERROR(D17/B17,"") -> -0.0044721313
... A62: Lamar State College-Port Arthur | B62: =$B$5*('Rate History'!$D$4*SUMIF(Data!$G:$G,Neutral!$A62,Data!$CU:$CU)+'Rate History'!$D$5*SUMIF(Data!$G:$G,Neutral!$A62,Data!$CV:$CV)+'Rate History'!$D$6*SUMIF(Data!$G:$G,Neutral!$A62,Data!$CW:$CW)+'Rate History'!$D$7*SUMIF(Data!$G:$G,Neutral!$A62,Data!$CX:$CX)+'Rate History'!$D$8*SUMIF(Data!$G:$G,Neutral!$A62,Data!$CY:$CY)+'Rate History'!$D$9*SUMIF(Data!$G:$G,Neutral!$A62,Data!$CZ:$CZ)+'Rate History'!$D$10*SUMIF(Data!$G:$G,Neutral!$A62,Data!$DA:$DA)+'Rate History'!$D$11*SUMIF(Data!$G:$G,Neutral!$A62,Data!$DB:$DB)+'Rate History'!$D$12*SUMIF(Data!$G:$G,Neutral!$A62,Data!$DC:$DC)+'Rate History'!$D$13*SUMIF(Data!$G:$G,Neutral!$A62,Data!$DD:$DD)+'Rate History'!$D$14*SUMIF(Data!$G:$G,Neutral!$A62,Data!$DE:$DE)+'Rate History'!$D$15*SUMIF(Data!$G:$G,Neutral!$A62,Data!$DF:$DF)+'Rate History'!$D$16*SUMIF(Data!$G:$G,Neutral!$A62,Data!$DG:$DG)+'Rate History'!$D$17*SUMIF(Data!$G:$G,Neutral!$A62,Data!$DH:$DH)+'Rate History'!$D$18*SUMIF(Data!$G:$G,Neutral!$A62,Data!$DI:$DI)+'Rate History'!$D$19*SUMIF(Data!$G:$G,Neutral!$A62,Data!$DJ:$DJ)+'Rate History'!$D$20*SUMIF(Data!$G:$G,Neutral!$A62,Data!$DK:$DK)+'Rate History'!$D$21*SUMIF(Data!$G:$G,Neutral!$A62,Data!$DL:$DL)+'Rate History'!$D$22*SUMIF(Data!$G:$G,Neutral!$A62,Data!$DM:$DM)+'Rate History'!$D$23*SUMIF(Data!$G:$G,Neutral!$A62,Data!$DN:$DN)+'Rate History'!$D$24*SUMIF(Data!$G:$G,Neutral!$A62,Data!$DO:$DO)+'Rate History'!$D$25*SUMIF(Data!$G:$G,Neutral!$A62,Data!$DP:$DP)+'Rate History'!$D$26*SUMIF(Data!$G:$G,Neutral!$A62,Data!$DQ:$DQ)+'Rate History'!$D$27*SUMIF(Data!$G:$G,Neutral!$A62,Data!$DR:$DR)+'Rate History'!$D$28*SUMIF(Data!$G:$G,Neutral!$A62,Data!$DS:$DS)+'Rate History'!$D$29*SUMIF(Data!$G:$G,Neutral!$A62,Data!$DT:$DT)+'Rate History'!$D$30*SUMIF(Data!$G:$G,Neutral!$A62,Data!$DV:$DV)+'Rate History'!$D$31*SUMIF(Data!$G:$G,Neutral!$A62,Data!$DW:$DW)) -> 4745439.1 | C62: =$C$5*('Rate History'!$C$4*SUMIF(Data!$G:$G,Neutral!$A62,Data!$CU:$CU)+'Rate History'!$C$5*SUMIF(Data!$G:$G,Neutral!$A62,Data!$CV:$CV)+'Rate History'!$C$6*SUMIF(Data!$G:$G,Neutral!$A62,Data!$CW:$CW)+'Rate History'!$C$7*SUMIF(Data!$G:$G,Neutral!$A62,Data!$CX:$CX)+'Rate History'!$C$8*SUMIF(Data!$G:$G,Neutral!$A62,Data!$CY:$CY)+'Rate History'!$C$9*SUMIF(Data!$G:$G,Neutral!$A62,Data!$CZ:$CZ)+'Rate History'!$C$10*SUMIF(Data!$G:$G,Neutral!$A62,Data!$DA:$DA)+'Rate History'!$C$11*SUMIF(Data!$G:$G,Neutral!$A62,Data!$DB:$DB)+'Rate History'!$C$12*SUMIF(Data!$G:$G,Neutral!$A62,Data!$DC:$DC)+'Rate History'!$C$13*SUMIF(Data!$G:$G,Neutral!$A62,Data!$DD:$DD)+'Rate History'!$C$14*SUMIF(Data!$G:$G,Neutral!$A62,Data!$DE:$DE)+'Rate History'!$C$15*SUMIF(Data!$G:$G,Neutral!$A62,Data!$DF:$DF)+'Rate History'!$C$16*SUMIF(Data!$G:$G,Neutral!$A62,Data!$DG:$DG)+'Rate History'!$C$17*SUMIF(Data!$G:$G,Neutral!$A62,Data!$DH:$DH)+'Rate History'!$C$18*SUMIF(Data!$G:$G,Neutral!$A62,Data!$DI:$DI)+'Rate History'!$C$19*SUMIF(Data!$G:$G,Neutral!$A62,Data!$DJ:$DJ)+'Rate History'!$C$20*SUMIF(Data!$G:$G,Neutral!$A62,Data!$DK:$DK)+'Rate History'!$C$21*SUMIF(Data!$G:$G,Neutral!$A62,Data!$DL:$DL)+'Rate History'!$C$22*SUMIF(Data!$G:$G,Neutral!$A62,Data!$DM:$DM)+'Rate History'!$C$23*SUMIF(Data!$G:$G,Neutral!$A62,Data!$DN:$DN)+'Rate History'!$C$24*SUMIF(Data!$G:$G,Neutral!$A62,Data!$DO:$DO)+'Rate History'!$C$25*SUMIF(Data!$G:$G,Neutral!$A62,Data!$DP:$DP)+'Rate History'!$C$26*SUMIF(Data!$G:$G,Neutral!$A62,Data!$DQ:$DQ)+'Rate History'!$C$27*SUMIF(Data!$G:$G,Neutral!$A62,Data!$DR:$DR)+'Rate History'!$C$28*SUMIF(Data!$G:$G,Neutral!$A62,Data!$DS:$DS)+'Rate History'!$C$29*SUMIF(Data!$G:$G,Neutral!$A62,Data!$DT:$DT)+'Rate History'!$C$30*SUMIF(Data!$G:$G,Neutral!$A62,Data!$DV:$DV)+'Rate History'!$C$31*SUMIF(Data!$G:$G,Neutral!$A62,Data!$DW:$DW)) -> 4754392.6 | D62: =C62-B62 -> 8953.4991 | E62: =IFERROR(D62/B62,"") -> 0.0018867588
A63: Total | B63: =SUM(B5:B62) -> 9.2268194e+08 | C63: =SUM(C6:C62) -> 9.2268194e+08 | D63: =C63-B63 -> 0 | E63: =IFERROR(D63/B63,"") -> 0

Sheet 1
A1: =Summary!A1 -> Community and Technical Colleges, Report of Fundable Operating Expenses, Fiscal Year (FY) 2008
A2: 003607 | B2: =VLOOKUP(A2,Data!A:G,7,0) -> Alamo Community College District
F3: =IFERROR(VLOOKUP(A2,Data!A:C,3,0),"0") -> 1
A4: Fund | B4: Total Expense by Discipline | D4: Contact Hours | E4: Expense | F4: Expense per Contact Hour
A5: 1 | B5: Agriculture | D5: =D36 -> 71760 | E5: =E36+E67+IFERROR($E$105/$D$105*D5,0) -> 496985.98 | F5: =IF(OR(D5=0,E5=0),"",ROUND(E5/D5,2)) -> 6.93
A6: 2 | B6: Architecture and Precision Production Trades | D6: =D37 -> 170428 | E6: =E37+E68+IFERROR($E$105/$D$105*D6,0) -> 2127659.9 | F6: =IF(OR(D6=0,E6=0),"",ROUND(E6/D6,2)) -> 12.48
A7: 3 | B7: Biology, Physical Sciences, and Science Technology | D7: =D38 -> 2158384 | E7: =E38+E69+IFERROR($E$105/$D$105*D7,0) -> 19490411 | F7: =IF(OR(D7=0,E7=0),"",ROUND(E7/D7,2)) -> 9.03
A8: 4 | B8: Business Management, Marketing, and Administrative Services | D8: =D39 -> 1108981 | E8: =E39+E70+IFERROR($E$105/$D$105*D8,0) -> 10901108 | F8: =IF(OR(D8=0,E8=0),"",ROUND(E8/D8,2)) -> 9.83
A9: 5 | B9: Career Pilot | D9: =D40 -> 3568 | E9: =E40+E71+IFERROR($E$105/$D$105*D9,0) -> 128688.71 | F9: =IF(OR(D9=0,E9=0),"",ROUND(E9/D9,2)) -> 36.07
A10: 6 | B10: Communications | D10: =D41 -> 314561 | E10: =E41+E72+IFERROR($E$105/$D$105*D10,0) -> 3304397.2 | F10: =IF(OR(D10=0,E10=0),"",ROUND(E10/D10,2)) -> 10.5
A11: 7 | B11: Computer and Information Sciences | D11: =D42 -> 766228 | E11: =E42+E73+IFERROR($E$105/$D$105*D11,0) -> 8266734.5 | F11: =IF(OR(D11=0,E11=0),"",ROUND(E11/D11,2)) -> 10.79
A12: 8 | B12: Construction Trades | D12: =D43 -> 75468 | E12: =E43+E74+IFERROR($E$105/$D$105*D12,0) -> 887858.14 | F12: =IF(OR(D12=0,E12=0),"",ROUND(E12/D12,2)) -> 11.76
A13: 9 | B13: Consumer and Homemaking Education | D13: =D44 -> 748495 | E13: =E44+E75+IFERROR($E$105/$D$105*D13,0) -> 6555903.5 | F13: =IF(OR(D13=0,E13=0),"",ROUND(E13/D13,2)) -> 8.76
A14: 10 | B14: Engineering | D14: =D45 -> 23472 | E14: =E45+E76+IFERROR($E$105/$D$105*D14,0) -> 357611.03 | F14: =IF(OR(D14=0,E14=0),"",ROUND(E14/D14,2)) -> 15.24
A15: 11 | B15: Engineering Related | D15: =D46 -> 358676 | E15: =E46+E77+IFERROR($E$105/$D$105*D15,0) -> 4789118.8 | F15: =IF(OR(D15=0,E15=0),"",ROUND(E15/D15,2)) -> 13.35
A16: 12 | B16: English Language, Lit, Philosophy, Humanities, & Interdisciplinary | D16: =D47 -> 3806778 | E16: =E47+E78+IFERROR($E$105/$D$105*D16,0) -> 35386658 | F16: =IF(OR(D16=0,E16=0),"",ROUND(E16/D16,2)) -> 9.3
... A32: 29 | B32: Developmental Education - Reading/Writing | D32: =D63 -> 0 | E32: =E63+E94+IFERROR($E$105/$D$105*D32,0) -> 0 | F32: =IF(OR(D32=0,E32=0),"",ROUND(E32/D32,2))
C33: Total | D33: =SUM(D5:D32) -> 20282455 | E33: =SUM(E5:E32) -> 1.9123947e+08 | F33: =IF(OR(D33=0,E33=0),"",ROUND(E33/D33,2)) -> 9.43
A35: Fund | B35: Departmental Operating Expense by Discipline | D35: Contact Hours | E35: Expense | F35: Expense per Contact Hour
A36: 1 | B36: Agriculture | D36: =IF(F3="1",SUMIF(Data!A:A,$A$2,Data!CU:CU),0) -> 71760 | E36: =IF(F3="1",SUMIF(Data!$A:$A,$A$2,Data!IO:IO),0) -> 76984 | F36: =IF(D36=0,"",ROUND(E36/D36,2)) -> 1.07
A37: 2 | B37: Architecture and Precision Production Trades | D37: =IF(F3="1",SUMIF(Data!A:A,$A$2,Data!CV:CV),0) -> 170428 | E37: =IF(F3="1",SUMIF(Data!$A:$A,$A$2,Data!IP:IP),0) -> 486043 | F37: =IF(D37=0,"",ROUND(E37/D37,2)) -> 2.85
A38: 3 | B38: Biology, Physical Sciences, and Science Technology | D38: =IF(F3="1",SUMIF(Data!A:A,$A$2,Data!CW:CW),0) -> 2158384 | E38: =IF(F3="1",SUMIF(Data!$A:$A,$A$2,Data!IQ:IQ),0) -> 2509068 | F38: =IF(D38=0,"",ROUND(E38/D38,2)) -> 1.16
A39: 4 | B39: Business Management, Marketing, and Administrative Services | D39: =IF(F3="1",SUMIF(Data!A:A,$A$2,Data!CX:CX),0) -> 1108981 | E39: =IF(F3="1",SUMIF(Data!$A:$A,$A$2,Data!IR:IR),0) -> 1901651 | F39: =IF(D39=0,"",ROUND(E39/D39,2)) -> 1.71
A40: 5 | B40: Career Pilot | D40: =IF(F3="1",SUMIF(Data!A:A,$A$2,Data!CY:CY),0) -> 3568 | E40: =IF(F3="1",SUMIF(Data!$A:$A,$A$2,Data!IS:IS),0) -> 54999 | F40: =IF(D40=0,"",ROUND(E40/D40,2)) -> 15.41
A41: 6 | B41: Communications | D41: =IF(F3="1",SUMIF(Data!A:A,$A$2,Data!CZ:CZ),0) -> 314561 | E41: =IF(F3="1",SUMIF(Data!$A:$A,$A$2,Data!IT:IT),0) -> 1033293 | F41: =IF(D41=0,"",ROUND(E41/D41,2)) -> 3.28
A42: 7 | B42: Computer and Information Sciences | D42: =IF(F3="1",SUMIF(Data!A:A,$A$2,Data!DA:DA),0) -> 766228 | E42: =IF(F3="1",SUMIF(Data!$A:$A,$A$2,Data!IU:IU),0) -> 1468398 | F42: =IF(D42=0,"",ROUND(E42/D42,2)) -> 1.92
A43: 8 | B43: Construction Trades | D43: =IF(F3="1",SUMIF(Data!A:A,$A$2,Data!DB:DB),0) -> 75468 | E43: =IF(F3="1",SUMIF(Data!$A:$A,$A$2,Data!IV:IV),0) -> 224097 | F43: =IF(D43=0,"",ROUND(E43/D43,2)) -> 2.97
A44: 9 | B44: Consumer and Homemaking Education | D44: =IF(F3="1",SUMIF(Data!A:A,$A$2,Data!DC:DC),0) -> 748495 | E44: =IF(F3="1",SUMIF(Data!$A:$A,$A$2,Data!IW:IW),0) -> 1541605 | F44: =IF(D44=0,"",ROUND(E44/D44,2)) -> 2.06
A45: 10 | B45: Engineering | D45: =IF(F3="1",SUMIF(Data!A:A,$A$2,Data!DD:DD),0) -> 23472 | E45: =IF(F3="1",SUMIF(Data!$A:$A,$A$2,Data!IX:IX),0) -> 82545 | F45: =IF(D45=0,"",ROUND(E45/D45,2)) -> 3.52
A46: 11 | B46: Engineering Related | D46: =IF(F3="1",SUMIF(Data!A:A,$A$2,Data!DE:DE),0) -> 358676 | E46: =IF(F3="1",SUMIF(Data!$A:$A,$A$2,Data!IY:IY),0) -> 1443788 | F46: =IF(D46=0,"",ROUND(E46/D46,2)) -> 4.03
A47: 12 | B47: English Language, Lit, Philosophy, Humanities, & Interdisciplinary | D47: =IF(F3="1",SUMIF(Data!A:A,$A$2,Data!DF:DF),0) -> 3806778 | E47: =IF(F3="1",SUMIF(Data!$A:$A,$A$2,Data!IZ:IZ),0) -> 4565943 | F47: =IF(D47=0,"",ROUND(E47/D47,2)) -> 1.2
A48: 13 | B48: Foreign Languages | D48: =IF(F3="1",SUMIF(Data!A:A,$A$2,Data!DG:DG),0) -> 696204 | E48: =IF(F3="1",SUMIF(Data!$A:$A,$A$2,Data!JA:JA),0) -> 675397 | F48: =IF(D48=0,"",ROUND(E48/D48,2)) -> 0.97
A49: 14 | B49: Health Occupations - Dental Assistants, Medical Lab, and Assoc. Degree Nursing | D49: =IF(F3="1",SUMIF(Data!A:A,$A$2,Data!DH:DH),0) -> 452026 | E49: =IF(F3="1",SUMIF(Data!$A:$A,$A$2,Data!JB:JB),0) -> 1700758 | F49: =IF(D49=0,"",ROUND(E49/D49,2)) -> 3.76
A50: 15 | B50: Health Occupations - Dental Hygiene | D50: =IF(F3="1",SUMIF(Data!A:A,$A$2,Data!DI:DI),0) -> 0 | E50: =IF(F3="1",SUMIF(Data!$A:$A,$A$2,Data!JC:JC),0) -> 0 | F50: =IF(D50=0,"",ROUND(E50/D50,2))
A51: 16 | B51: Health Occupations - Other | D51: =IF(F3="1",SUMIF(Data!A:A,$A$2,Data!DJ:DJ),0) -> 656649 | E51: =IF(F3="1",SUMIF(Data!$A:$A,$A$2,Data!JD:JD),0) -> 1290763 | F51: =IF(D51=0,"",ROUND(E51/D51,2)) -> 1.97
A52: 17 | B52: Health Occupations - Respiratory Therapy | D52: =IF(F3="1",SUMIF(Data!A:A,$A$2,Data!DK:DK),0) -> 47936 | E52: =IF(F3="1",SUMIF(Data!$A:$A,$A$2,Data!JE:JE),0) -> 102053 | F52: =IF(D52=0,"",ROUND(E52/D52,2)) -> 2.13
A53: 18 | B53: Health Occupations - Vocational Nursing | D53: =IF(F3="1",SUMIF(Data!A:A,$A$2,Data!DL:DL),0) -> 267616 | E53: =IF(F3="1",SUMIF(Data!$A:$A,$A$2,Data!JF:JF),0) -> 475082 | F53: =IF(D53=0,"",ROUND(E53/D53,2)) -> 1.78
A54: 19 | B54: Mathematics | D54: =IF(F3="1",SUMIF(Data!A:A,$A$2,Data!DM:DM),0) -> 2606552 | E54: =IF(F3="1",SUMIF(Data!$A:$A,$A$2,Data!JG:JG),0) -> 2207563 | F54: =IF(D54=0,"",ROUND(E54/D54,2)) -> 0.85
A55: 20 | B55: Mechanics and Repairers - Automotive | D55: =IF(F3="1",SUMIF(Data!A:A,$A$2,Data!DN:DN),0) -> 283561 | E55: =IF(F3="1",SUMIF(Data!$A:$A,$A$2,Data!JH:JH),0) -> 698053 | F55: =IF(D55=0,"",ROUND(E55/D55,2)) -> 2.46
A56: 21 | B56: Mechanics and Repairers - Diesel, Aviation Mechanics, and Transportation Workers | D56: =IF(F3="1",SUMIF(Data!A:A,$A$2,Data!DO:DO),0) -> 181310 | E56: =IF(F3="1",SUMIF(Data!$A:$A,$A$2,Data!JI:JI),0) -> 627466 | F56: =IF(D56=0,"",ROUND(E56/D56,2)) -> 3.46
A57: 22 | B57: Mechanics and Repairers - Electronics | D57: =IF(F3="1",SUMIF(Data!A:A,$A$2,Data!DP:DP),0) -> 26326 | E57: =IF(F3="1",SUMIF(Data!$A:$A,$A$2,Data!JJ:JJ),0) -> 8532 | F57: =IF(D57=0,"",ROUND(E57/D57,2)) -> 0.32
A58: 23 | B58: Physical Education and Fitness | D58: =IF(F3="1",SUMIF(Data!A:A,$A$2,Data!DQ:DQ),0) -> 553824 | E58: =IF(F3="1",SUMIF(Data!$A:$A,$A$2,Data!JK:JK),0) -> 750508 | F58: =IF(D58=0,"",ROUND(E58/D58,2)) -> 1.36
A59: 24 | B59: Protective Services and Public Administration | D59: =IF(F3="1",SUMIF(Data!A:A,$A$2,Data!DR:DR),0) -> 475864 | E59: =IF(F3="1",SUMIF(Data!$A:$A,$A$2,Data!JL:JL),0) -> 757251 | F59: =IF(D59=0,"",ROUND(E59/D59,2)) -> 1.59
A60: 25 | B60: Psychology, Social Sciences, and History | D60: =IF(F3="1",SUMIF(Data!A:A,$A$2,Data!DS:DS),0) -> 3414220 | E60: =IF(F3="1",SUMIF(Data!$A:$A,$A$2,Data!JM:JM),0) -> 2294329 | F60: =IF(D60=0,"",ROUND(E60/D60,2)) -> 0.67
A61: 26 | B61: Visual and Performing Arts | D61: =IF(F3="1",SUMIF(Data!A:A,$A$2,Data!DT:DT),0) -> 1013568 | E61: =IF(F3="1",SUMIF(Data!$A:$A,$A$2,Data!JN:JN),0) -> 1603623 | F61: =IF(D61=0,"",ROUND(E61/D61,2)) -> 1.58
A62: 28 | B62: Developmental Education - Math | D62: =IF(F3="1",SUMIF(Data!A:A,$A$2,Data!DV:DV),0) -> 0 | E62: =IF(F3="1",SUMIF(Data!$A:$A,$A$2,Data!JP:JP),0) -> 0 | F62: =IF(D62=0,"",ROUND(E62/D62,2))
A63: 29 | B63: Developmental Education - Reading/Writing | D63: =IF(F3="1",SUMIF(Data!A:A,$A$2,Data!DW:DW),0) -> 0 | E63: =IF(F3="1",SUMIF(Data!$A:$A,$A$2,Data!JQ:JQ),0) -> 0 | F63: =IF(D63=0,"",ROUND(E63/D63,2))
C64: Total | D64: =SUM(D36:D63) -> 20282455 | E64: =SUM(E36:E63) -> 28579792 | F64: =IF(D64=0,"",ROUND(E64/D64,2)) -> 1.41
A66: Fund | B66: Faculty Salaries by Discipline | D66: Contact Hours | E66: Expense | F66: Expense per Contact Hour
A67: 1 | B67: Agriculture | D67: =D36 -> 71760 | E67: =IF(F3="1",SUMIF(Data!A:A,$A$2,Data!DY:DY),0) -> 109155 | F67: =IF(D67=0,"",ROUND(E67/D67,2)) -> 1.52
A68: 2 | B68: Architecture and Precision Production Trades | D68: =D37 -> 170428 | E68: =IF(F3="1",SUMIF(Data!A:A,$A$2,Data!DZ:DZ),0) -> 903364 | F68: =IF(D68=0,"",ROUND(E68/D68,2)) -> 5.3
A69: 3 | B69: Biology, Physical Sciences, and Science Technology | D69: =D38 -> 2158384 | E69: =IF(F3="1",SUMIF(Data!A:A,$A$2,Data!EA:EA),0) -> 7631745 | F69: =IF(D69=0,"",ROUND(E69/D69,2)) -> 3.54
A70: 4 | B70: Business Management, Marketing, and Administrative Services | D70: =D39 -> 1108981 | E70: =IF(F3="1",SUMIF(Data!A:A,$A$2,Data!EB:EB),0) -> 4195619 | F70: =IF(D70=0,"",ROUND(E70/D70,2)) -> 3.78
A71: 5 | B71: Career Pilot | D71: =D40 -> 3568 | E71: =IF(F3="1",SUMIF(Data!A:A,$A$2,Data!EC:EC),0) -> 58234 | F71: =IF(D71=0,"",ROUND(E71/D71,2)) -> 16.32
A72: 6 | B72: Communications | D72: =D41 -> 314561 | E72: =IF(F3="1",SUMIF(Data!A:A,$A$2,Data!ED:ED),0) -> 908502 | F72: =IF(D72=0,"",ROUND(E72/D72,2)) -> 2.89
A73: 7 | B73: Computer and Information Sciences | D73: =D42 -> 766228 | E73: =IF(F3="1",SUMIF(Data!A:A,$A$2,Data!EE:EE),0) -> 3479222 | F73: =IF(D73=0,"",ROUND(E73/D73,2)) -> 4.54
A74: 8 | B74: Construction Trades | D74: =D43 -> 75468 | E74: =IF(F3="1",SUMIF(Data!A:A,$A$2,Data!EF:EF),0) -> 336852 | F74: =IF(D74=0,"",ROUND(E74/D74,2)) -> 4.46
A75: 9 | B75: Consumer and Homemaking Education | D75: =D44 -> 748495 | E75: =IF(F3="1",SUMIF(Data!A:A,$A$2,Data!EG:EG),0) -> 1771999 | F75: =IF(D75=0,"",ROUND(E75/D75,2)) -> 2.37
A76: 10 | B76: Engineering | D76: =D45 -> 23472 | E76: =IF(F3="1",SUMIF(Data!A:A,$A$2,Data!EH:EH),0) -> 173391 | F76: =IF(D76=0,"",ROUND(E76/D76,2)) -> 7.39
A77: 11 | B77: Engineering Related | D77: =D46 -> 358676 | E77: =IF(F3="1",SUMIF(Data!A:A,$A$2,Data!EI:EI),0) -> 1791633 | F77: =IF(D77=0,"",ROUND(E77/D77,2)) -> 5
A78: 12 | B78: English Language, Lit, Philosophy, Humanities, & Interdisciplinary | D78: =D47 -> 3806778 | E78: =IF(F3="1",SUMIF(Data!A:A,$A$2,Data!EJ:EJ),0) -> 14330673 | F78: =IF(D78=0,"",ROUND(E78/D78,2)) -> 3.76
A79: 13 | B79: Foreign Languages | D79: =D48 -> 696204 | E79: =IF(F3="1",SUMIF(Data!A:A,$A$2,Data!EK:EK),0) -> 1666817 | F79: =IF(D79=0,"",ROUND(E79/D79,2)) -> 2.39
A80: 14 | B80: Health Occupations - Dental Assistants, Medical Lab, and Assoc. Degree Nursing | D80: =D49 -> 452026 | E80: =IF(F3="1",SUMIF(Data!A:A,$A$2,Data!EL:EL),0) -> 3295854 | F80: =IF(D80=0,"",ROUND(E80/D80,2)) -> 7.29
A81: 15 | B81: Health Occupations - Dental Hygiene | D81: =D50 -> 0 | E81: =IF(F3="1",SUMIF(Data!A:A,$A$2,Data!EM:EM),0) -> 0 | F81: =IF(D81=0,"",ROUND(E81/D81,2))
A82: 16 | B82: Health Occupations - Other | D82: =D51 -> 656649 | E82: =IF(F3="1",SUMIF(Data!A:A,$A$2,Data!EN:EN),0) -> 2352776 | F82: =IF(D82=0,"",ROUND(E82/D82,2)) -> 3.58
A83: 17 | B83: Health Occupations - Respiratory Therapy | D83: =D52 -> 47936 | E83: =IF(F3="1",SUMIF(Data!A:A,$A$2,Data!EO:EO),0) -> 414215 | F83: =IF(D83=0,"",ROUND(E83/D83,2)) -> 8.64
A84: 18 | B84: Health Occupations - Vocational Nursing | D84: =D53 -> 267616 | E84: =IF(F3="1",SUMIF(Data!A:A,$A$2,Data!EP:EP),0) -> 1167033 | F84: =IF(D84=0,"",ROUND(E84/D84,2)) -> 4.36
A85: 19 | B85: Mathematics | D85: =D54 -> 2606552 | E85: =IF(F3="1",SUMIF(Data!A:A,$A$2,Data!EQ:EQ),0) -> 9045562 | F85: =IF(D85=0,"",ROUND(E85/D85,2)) -> 3.47
A86: 20 | B86: Mechanics and Repairers - Automotive | D86: =D55 -> 283561 | E86: =IF(F3="1",SUMIF(Data!A:A,$A$2,Data!ER:ER),0) -> 1014047 | F86: =IF(D86=0,"",ROUND(E86/D86,2)) -> 3.58
A87: 21 | B87: Mechanics and Repairers - Diesel, Aviation Mechanics, and Transportation Workers | D87: =D56 -> 181310 | E87: =IF(F3="1",SUMIF(Data!A:A,$A$2,Data!ES:ES),0) -> 875214 | F87: =IF(D87=0,"",ROUND(E87/D87,2)) -> 4.83
A88: 22 | B88: Mechanics and Repairers - Electronics | D88: =D57 -> 26326 | E88: =IF(F3="1",SUMIF(Data!A:A,$A$2,Data!ET:ET),0) -> 7859 | F88: =IF(D88=0,"",ROUND(E88/D88,2)) -> 0.3
A89: 23 | B89: Physical Education and Fitness | D89: =D58 -> 553824 | E89: =IF(F3="1",SUMIF(Data!A:A,$A$2,Data!EU:EU),0) -> 2286452 | F89: =IF(D89=0,"",ROUND(E89/D89,2)) -> 4.13
A90: 24 | B90: Protective Services and Public Administration | D90: =D59 -> 475864 | E90: =IF(F3="1",SUMIF(Data!A:A,$A$2,Data!EV:EV),0) -> 1465868 | F90: =IF(D90=0,"",ROUND(E90/D90,2)) -> 3.08
A91: 25 | B91: Psychology, Social Sciences, and History | D91: =D60 -> 3414220 | E91: =IF(F3="1",SUMIF(Data!A:A,$A$2,Data!EW:EW),0) -> 11198342 | F91: =IF(D91=0,"",ROUND(E91/D91,2)) -> 3.28
A92: 26 | B92: Visual and Performing Arts | D92: =D61 -> 1013568 | E92: =IF(F3="1",SUMIF(Data!A:A,$A$2,Data!EX:EX),0) -> 4320557 | F92: =IF(D92=0,"",ROUND(E92/D92,2)) -> 4.26
A93: 28 | B93: Developmental Education - Math | D93: =D62 -> 0 | E93: =IF(F3="1",SUMIF(Data!A:A,$A$2,Data!EZ:EZ),0) -> 0 | F93: =IF(D93=0,"",ROUND(E93/D93,2))
A94: 29 | B94: Developmental Education - Reading/Writing | D94: =D63 -> 0 | E94: =IF(F3="1",SUMIF(Data!A:A,$A$2,Data!FA:FA),0) -> 0 | F94: =IF(D94=0,"",ROUND(E94/D94,2))
C95: Total | D95: =SUM(D67:D94) -> 20282455 | E95: =SUM(E67:E94) -> 74800985 | F95: =IF(D95=0,"",ROUND(E95/D95,2)) -> 3.69
B97: Allocated Administrative Expense | D97: Contact Hours | E97: Expense | F97: Expense per Contact Hour
B98: Institutional Support | E98: =IF(F3="1",SUMIF(Data!A:A,$A$2,Data!AH:AH),0) -> 37767074 | F98: =IF($D$105=0,"",ROUND(E98/$D$105,2)) -> 1.86
B99: Student Services | E99: =IF(F3="1",SUMIF(Data!A:A,$A$2,Data!AI:AI),0) -> 20351315 | F99: =IF($D$105=0,"",ROUND(E99/$D$105,2)) -> 1
B100: Academic Support | E100: =IF(F3="1",SUMIF(Data!A:A,$A$2,Data!AJ:AJ),0) -> 18587690 | F100: =IF($D$105=0,"",ROUND(E100/$D$105,2)) -> 0.92
B101: Research | E101: =IF(F3="1",SUMIF(Data!A:A,$A$2,Data!AK:AK),0) -> 0 | F101: =IF($D$105=0,"",ROUND(E101/$D$105,2)) -> 0
B102: Scholarships and Fellowships | E102: =IF(F3="1",SUMIF(Data!A:A,$A$2,Data!AL:AL),0) -> 546574 | F102: =IF($D$105=0,"",ROUND(E102/$D$105,2)) -> 0.03
B103: Equipment Depreciation | E103: =IF(F3="1",SUMIF(Data!A:A,$A$2,Data!AM:AM),0) -> 3293903 | F103: =IF($D$105=0,"",ROUND(E103/$D$105,2)) -> 0.16
B104: Local Benefits | E104: =IF(F3="1",SUMIF(Data!A:A,$A$2,Data!Q:Q),0) -> 7312138 | F104: =IF($D$105=0,"",ROUND(E104/$D$105,2)) -> 0.36
C105: Total | D105: =D95 -> 20282455 | E105: =SUM(E98:E104) -> 87858694 | F105: =IF($D$105=0,"",ROUND(E105/$D$105,2)) -> 4.33
B107: Annual Financial Report - Schedule B
B108: Unrestricted - Educational Activities | C108: Salaries and Wages | D108: Local Benefits | E108: Other Expenses | F108: Total
B109: Instruction | C109: =E95+IF(F3="1",SUMIF(Data!$A:$A,$A$2,Data!GF:GF),0) -> 88839213 | D109: =IF(F3="1",SUMIF(Data!$A:$A,$A$2,Data!HJ:HJ),0) -> 8378007 | E109: =IF(F3="1",SUMIF(Data!$A:$A,$A$2,Data!IN:IN),0) -> 6163557 | F109: =SUM(C109:E109) -> 103380777
B110: Research | C110: =IF(F3="1",SUMIF(Data!A:A,$A$2,Data!W:W),0) -> 0 | E110: =IF(F3="1",SUMIF(Data!A:A,$A$2,Data!W:W),0) -> 0 | F110: =SUM(C110:E110) -> 0
B111: Public Service | C111: =IF(F3="1",SUMIF(Data!A:A,$A$2,Data!AS:AS),0) -> 223310 | E111: =IF(F3="1",SUMIF(Data!A:A,$A$2,Data!AX:AX),0) -> 206173 | F111: =SUM(C111:E111) -> 429483
B112: Academic Support | C112: =IF(F3="1",SUMIF(Data!A:A,$A$2,Data!V:V),0) -> 13259962 | E112: =IF(F3="1",SUMIF(Data!A:A,$A$2,Data!AC:AC),0) -> 5327728 | F112: =SUM(C112:E112) -> 18587690
B113: Student Services | C113: =IF(F3="1",SUMIF(Data!A:A,$A$2,Data!U:U),0) -> 16129130 | E113: =IF(F3="1",SUMIF(Data!A:A,$A$2,Data!AB:AB),0) -> 4222185 | F113: =SUM(C113:E113) -> 20351315
B114: Instructional Support | C114: =IF(F3="1",SUMIF(Data!A:A,$A$2,Data!T:T),0) -> 21810752 | E114: =IF(F3="1",SUMIF(Data!A:A,$A$2,Data!AA:AA),0) -> 15956322 | F114: =SUM(C114:E114) -> 37767074
B115: Operation and Maintenance of Plant | C115: =IF(F3="1",SUMIF(Data!A:A,$A$2,Data!BI:BI),0) -> 7958726 | D115: =IF(F3="1",SUMIF(Data!A:A,$A$2,Data!BL:BL),0) -> 2727171 | E115: =IF(F3="1",SUMIF(Data!A:A,$A$2,Data!BU:BU),0) -> 9694670 | F115: =SUM(C115:E115) -> 20380567
B116: Scholarships and Fellowships | C116: =IF(F3="1",SUMIF(Data!A:A,$A$2,Data!X:X),0) -> 0 | E116: =E102 -> 546574 | F116: =SUM(C116:E116) -> 546574
B117: Other | D117: =IF(F3="1",SUMIF(Data!A:A,$A$2,Data!Q:Q),0) -> 7312138 | F117: =SUM(C117:E117) -> 7312138
B118: Total | C118: =SUM(C109:C116) -> 148221093 | D118: =SUM(D109:D116) -> 11105178 | E118: =SUM(E109:E116) -> 42117209 | F118: =SUM(F109:F116) -> 201443480
B120: Depreciation Expense - Equipment | E120: =IF(F3="1",SUMIF(Data!A:A,$A$2,Data!AM:AM),0) -> 3293903 | F120: =SUM(C120:E120) -> 3293903
...

Sheet 2
A1: =Summary!A1 -> Community and Technical Colleges, Report of Fundable Operating Expenses, Fiscal Year (FY) 2008
