Workbook

Sheet April 2013 - Data
A1: Department / Read date 3/31/2013 | B1: General Ledger | C1: GL Description | D1: Building | E1: Room | F1: Model | G1: Device Type | H1: Ricoh Tag | I1: Total BW Click Count | J1: Total Color Click Count | K1: BW Click Charge | L1: Color Click Charge | M1: Device Total Click Charge | N1: Serial Number | O1: IP Address | P1: CPC BW | Q1: CPC Color | R1: Prev BW Click Count | S1: Current BW Click Count | T1: Prev Color Click Count | U1: Current Color Click Count
A2: Academic Advising | B2: 10_07_205_90300_5521 | C2: =VLOOKUP(B2,Tables!$G$2:$H$90,2,FALSE) -> Academic Advising | D2: Shell Hall | E2: 301 | F2: AF SPC242DN | G2: =VLOOKUP(F2,Tables!$D$2:$E$20,2,FALSE) -> PTR | H2: 17099684 | I2: =SUM(S2-R2) -> 234 | J2: =SUM(U2-T2) -> 165 | K2: =SUM(I2*$P2) -> 6.1308 | L2: =SUM(J2*$Q2) -> 19.47 | M2: =K2+L2 -> 25.6008 | N2: T202P700442 | O2: 144.75.180.103 | P2: =IF(G2="MFP",Tables!$B$2,Tables!$B$5) -> 0.0262 | Q2: =IF(G2="MFP",Tables!$B$3,Tables!$B$6) -> 0.118 | R2: =VLOOKUP($N2,'Meter Comparison'!$C$2:$G$314,2,FALSE) -> 2529 | S2: =VLOOKUP($N2,'Meter Comparison'!$C$2:$G$314,3,FALSE) -> 2763 | T2: =VLOOKUP($N2,'Meter Comparison'!$C$2:$G$314,4,FALSE) -> 834 | U2: =VLOOKUP($N2,'Meter Comparison'!$C$2:$G$314,5,FALSE) -> 999
B3: 10_07_205_90300_5521 Total | M3: =SUBTOTAL(9,M2:M2) -> 25.6008
A4: Addmissions | B4: 10_03_054_01100_5521 | C4: =VLOOKUP(B4,Tables!$G$2:$H$90,2,FALSE) -> Admissions Office | D4: Moody Hall | E4: 104 | F4: AF SP4310N | G4: =VLOOKUP(F4,Tables!$D$2:$E$20,2,FALSE) -> PTR | H4: 17099824 | I4: =SUM(S4-R4) -> 43 | J4: =SUM(U4-T4) -> 0 | K4: =SUM(I4*$P4) -> 1.1266 | L4: =SUM(J4*$Q4) -> 0 | M4: =K4+L4 -> 1.1266 | N4: T1129010634 | O4: 144.75.184.23 | P4: =IF(G4="MFP",Tables!$B$2,Tables!$B$5) -> 0.0262 | Q4: =IF(G4="MFP",Tables!$B$3,Tables!$B$6) -> 0.118 | R4: =VLOOKUP($N4,'Meter Comparison'!$C$2:$G$314,2,FALSE) -> 505 | S4: =VLOOKUP($N4,'Meter Comparison'!$C$2:$G$314,3,FALSE) -> 548 | T4: =VLOOKUP($N4,'Meter Comparison'!$C$2:$G$314,4,FALSE) -> 0 | U4: =VLOOKUP($N4,'Meter Comparison'!$C$2:$G$314,5,FALSE) -> 0
A5: Admissions | B5: 10_03_054_01100_5521 | C5: =VLOOKUP(B5,Tables!$G$2:$H$90,2,FALSE) -> Admissions Office | D5: 307 Letcher | E5: 204 | F5: AF MPC3502 | G5: =VLOOKUP(F5,Tables!$D$2:$E$20,2,FALSE) -> MFP | H5: 17099493 | I5: =SUM(S5-R5) -> 2045 | J5: =SUM(U5-T5) -> 2677 | K5: =SUM(I5*$P5) -> 42.3315 | L5: =SUM(J5*$Q5) -> 232.899 | M5: =K5+L5 -> 275.2305 | N5: W502L600872 | O5: 144.75.215.48 | P5: =IF(G5="MFP",Tables!$B$2,Tables!$B$5) -> 0.0207 | Q5: =IF(G5="MFP",Tables!$B$3,Tables!$B$6) -> 0.087 | R5: =VLOOKUP($N5,'Meter Comparison'!$C$2:$G$314,2,FALSE) -> 41492 | S5: =VLOOKUP($N5,'Meter Comparison'!$C$2:$G$314,3,FALSE) -> 43537 | T5: =VLOOKUP($N5,'Meter Comparison'!$C$2:$G$314,4,FALSE) -> 22039 | U5: =VLOOKUP($N5,'Meter Comparison'!$C$2:$G$314,5,FALSE) -> 24716
A6: Admissions | B6: 10_03_054_01100_5521 | C6: =VLOOKUP(B6,Tables!$G$2:$H$90,2,FALSE) -> Admissions Office | D6: 309 Letcher | E6: 200 | F6: AF SPC430DN | G6: =VLOOKUP(F6,Tables!$D$2:$E$20,2,FALSE) -> PTR | H6: 17099785 | I6: =SUM(S6-R6) -> 262 | J6: =SUM(U6-T6) -> 682 | K6: =SUM(I6*$P6) -> 6.8644 | L6: =SUM(J6*$Q6) -> 80.476 | M6: =K6+L6 -> 87.3404 | N6: S9329101091 | O6: 144.75.186.31 | P6: =IF(G6="MFP",Tables!$B$2,Tables!$B$5) -> 0.0262 | Q6: =IF(G6="MFP",Tables!$B$3,Tables!$B$6) -> 0.118 | R6: =VLOOKUP($N6,'Meter Comparison'!$C$2:$G$314,2,FALSE) -> 1512 | S6: =VLOOKUP($N6,'Meter Comparison'!$C$2:$G$314,3,FALSE) -> 1774 | T6: =VLOOKUP($N6,'Meter Comparison'!$C$2:$G$314,4,FALSE) -> 3151 | U6: =VLOOKUP($N6,'Meter Comparison'!$C$2:$G$314,5,FALSE) -> 3833
A7: Admissions | B7: 10_03_054_01100_5521 | C7: =VLOOKUP(B7,Tables!$G$2:$H$90,2,FALSE) -> Admissions Office | D7: 309 Letcher | E7: 201 | F7: AF SP4310N | G7: =VLOOKUP(F7,Tables!$D$2:$E$20,2,FALSE) -> PTR | H7: 17099780 | I7: =SUM(S7-R7) -> 468 | J7: =SUM(U7-T7) -> 0 | K7: =SUM(I7*$P7) -> 12.2616 | L7: =SUM(J7*$Q7) -> 0 | M7: =K7+L7 -> 12.2616 | N7: T1128911219 | O7: 144.75.215.43 | P7: =IF(G7="MFP",Tables!$B$2,Tables!$B$5) -> 0.0262 | Q7: =IF(G7="MFP",Tables!$B$3,Tables!$B$6) -> 0.118 | R7: =VLOOKUP($N7,'Meter Comparison'!$C$2:$G$314,2,FALSE) -> 948 | S7: =VLOOKUP($N7,'Meter Comparison'!$C$2:$G$314,3,FALSE) -> 1416 | T7: =VLOOKUP($N7,'Meter Comparison'!$C$2:$G$314,4,FALSE) -> 0 | U7: =VLOOKUP($N7,'Meter Comparison'!$C$2:$G$314,5,FALSE) -> 0
A8: Admissions | B8: 10_03_054_01100_5521 | C8: =VLOOKUP(B8,Tables!$G$2:$H$90,2,FALSE) -> Admissions Office | D8: 309 Letcher | E8: 201 | F8: AF SP4310N | G8: =VLOOKUP(F8,Tables!$D$2:$E$20,2,FALSE) -> PTR | H8: 17099512 | I8: =SUM(S8-R8) -> 2 | J8: =SUM(U8-T8) -> 0 | K8: =SUM(I8*$P8) -> 0.0524 | L8: =SUM(J8*$Q8) -> 0 | M8: =K8+L8 -> 0.0524 | N8: T1129010877 | O8: 144.75.186.30 | P8: =IF(G8="MFP",Tables!$B$2,Tables!$B$5) -> 0.0262 | Q8: =IF(G8="MFP",Tables!$B$3,Tables!$B$6) -> 0.118 | R8: =VLOOKUP($N8,'Meter Comparison'!$C$2:$G$314,2,FALSE) -> 50 | S8: =VLOOKUP($N8,'Meter Comparison'!$C$2:$G$314,3,FALSE) -> 52 | T8: =VLOOKUP($N8,'Meter Comparison'!$C$2:$G$314,4,FALSE) -> 0 | U8: =VLOOKUP($N8,'Meter Comparison'!$C$2:$G$314,5,FALSE) -> 0
A9: Admissions | B9: 10_03_054_01100_5521 | C9: =VLOOKUP(B9,Tables!$G$2:$H$90,2,FALSE) -> Admissions Office | D9: 309 Letcher | E9: 302 | F9: AF SPC242DN | G9: =VLOOKUP(F9,Tables!$D$2:$E$20,2,FALSE) -> PTR | H9: 17099423 | I9: =SUM(S9-R9) -> 53 | J9: =SUM(U9-T9) -> 130 | K9: =SUM(I9*$P9) -> 1.3886 | L9: =SUM(J9*$Q9) -> 15.34 | M9: =K9+L9 -> 16.7286 | N9: T202P700463 | O9: 144.75.186.29 | P9: =IF(G9="MFP",Tables!$B$2,Tables!$B$5) -> 0.0262 | Q9: =IF(G9="MFP",Tables!$B$3,Tables!$B$6) -> 0.118 | R9: =VLOOKUP($N9,'Meter Comparison'!$C$2:$G$314,2,FALSE) -> 255 | S9: =VLOOKUP($N9,'Meter Comparison'!$C$2:$G$314,3,FALSE) -> 308 | T9: =VLOOKUP($N9,'Meter Comparison'!$C$2:$G$314,4,FALSE) -> 766 | U9: =VLOOKUP($N9,'Meter Comparison'!$C$2:$G$314,5,FALSE) -> 896
A10: Admissions | B10: 10_03_054_01100_5521 | C10: =VLOOKUP(B10,Tables!$G$2:$H$90,2,FALSE) -> Admissions Office | D10: 309 Letcher | E10: 306 | F10: AF SPC242DN | G10: =VLOOKUP(F10,Tables!$D$2:$E$20,2,FALSE) -> PTR | H10: 17099731 | I10: =SUM(S10-R10) -> 279 | J10: =SUM(U10-T10) -> 111 | K10: =SUM(I10*$P10) -> 7.3098 | L10: =SUM(J10*$Q10) -> 13.098 | M10: =K10+L10 -> 20.4078 | N10: T202P600637 | O10: 144.75.186.28 | P10: =IF(G10="MFP",Tables!$B$2,Tables!$B$5) -> 0.0262 | Q10: =IF(G10="MFP",Tables!$B$3,Tables!$B$6) -> 0.118 | R10: =VLOOKUP($N10,'Meter Comparison'!$C$2:$G$314,2,FALSE) -> 1730 | S10: =VLOOKUP($N10,'Meter Comparison'!$C$2:$G$314,3,FALSE) -> 2009 | T10: =VLOOKUP($N10,'Meter Comparison'!$C$2:$G$314,4,FALSE) -> 672 | U10: =VLOOKUP($N10,'Meter Comparison'!$C$2:$G$314,5,FALSE) -> 783
A11: Admissions | B11: 10_03_054_01100_5521 | C11: =VLOOKUP(B11,Tables!$G$2:$H$90,2,FALSE) -> Admissions Office | D11: 309 Letcher | E11: 306 | F11: AF SPC242DN | G11: =VLOOKUP(F11,Tables!$D$2:$E$20,2,FALSE) -> PTR | H11: 17099511 | I11: =SUM(S11-R11) -> 31 | J11: =SUM(U11-T11) -> 58 | K11: =SUM(I11*$P11) -> 0.8122 | L11: =SUM(J11*$Q11) -> 6.844 | M11: =K11+L11 -> 7.6562 | N11: T202P700465 | O11: 144.75.186.25 | P11: =IF(G11="MFP",Tables!$B$2,Tables!$B$5) -> 0.0262 | Q11: =IF(G11="MFP",Tables!$B$3,Tables!$B$6) -> 0.118 | R11: =VLOOKUP($N11,'Meter Comparison'!$C$2:$G$314,2,FALSE) -> 445 | S11: =VLOOKUP($N11,'Meter Comparison'!$C$2:$G$314,3,FALSE) -> 476 | T11: =VLOOKUP($N11,'Meter Comparison'!$C$2:$G$314,4,FALSE) -> 557 | U11: =VLOOKUP($N11,'Meter Comparison'!$C$2:$G$314,5,FALSE) -> 615
B12: 10_03_054_01100_5521 Total | M12: =SUBTOTAL(9,M4:M11) -> 420.8041
A13: ADV | B13: 10_03_064_50550_5521 | C13: =VLOOKUP(B13,Tables!$G$2:$H$90,2,FALSE) -> Printer Services | D13: Carroll Hall | E13: 210C | F13: AF SP4310N | G13: =VLOOKUP(F13,Tables!$D$2:$E$20,2,FALSE) -> PTR | H13: 17099562 | I13: =SUM(S13-R13) -> 148 | J13: =SUM(U13-T13) -> 0 | K13: =SUM(I13*$P13) -> 3.8776 | L13: =SUM(J13*$Q13) -> 0 | M13: =K13+L13 -> 3.8776 | N13: T1128911292 | O13: 144.75.195.20 | P13: =IF(G13="MFP",Tables!$B$2,Tables!$B$5) -> 0.0262 | Q13: =IF(G13="MFP",Tables!$B$3,Tables!$B$6) -> 0.118 | R13: =VLOOKUP($N13,'Meter Comparison'!$C$2:$G$314,2,FALSE) -> 3771 | S13: =VLOOKUP($N13,'Meter Comparison'!$C$2:$G$314,3,FALSE) -> 3919 | T13: =VLOOKUP($N13,'Meter Comparison'!$C$2:$G$314,4,FALSE) -> 0 | U13: =VLOOKUP($N13,'Meter Comparison'!$C$2:$G$314,5,FALSE) -> 0
A14: ADV | B14: 10_03_064_50550_5521 | C14: =VLOOKUP(B14,Tables!$G$2:$H$90,2,FALSE) -> Printer Services | D14: Carroll Hall | E14: 210C | F14: AF SPC242DN | G14: =VLOOKUP(F14,Tables!$D$2:$E$20,2,FALSE) -> PTR | H14: 17099741 | I14: =SUM(S14-R14) -> 89 | J14: =SUM(U14-T14) -> 119 | K14: =SUM(I14*$P14) -> 2.3318 | L14: =SUM(J14*$Q14) -> 14.042 | M14: =K14+L14 -> 16.3738 | N14: T202P801019 | O14: 144.75.195.97 | P14: =IF(G14="MFP",Tables!$B$2,Tables!$B$5) -> 0.0262 | Q14: =IF(G14="MFP",Tables!$B$3,Tables!$B$6) -> 0.118 | R14: =VLOOKUP($N14,'Meter Comparison'!$C$2:$G$314,2,FALSE) -> 47 | S14: =VLOOKUP($N14,'Meter Comparison'!$C$2:$G$314,3,FALSE) -> 136 | T14: =VLOOKUP($N14,'Meter Comparison'!$C$2:$G$314,4,FALSE) -> 71 | U14: =VLOOKUP($N14,'Meter Comparison'!$C$2:$G$314,5,FALSE) -> 190
B15: 10_03_064_50550_5521 Total | M15: =SUBTOTAL(9,M13:M14) -> 20.2514
A16: Air Force Rotc | B16: 10_03_011_02100_5521 | C16: =VLOOKUP(B16,Tables!$G$2:$H$90,2,FALSE) -> ROTC-Air Force | D16: Kilbourne Hall | E16: 2012 | F16: AF SP4310N | G16: =VLOOKUP(F16,Tables!$D$2:$E$20,2,FALSE) -> PTR | H16: 17099443 | I16: =SUM(S16-R16) -> 0 | J16: =SUM(U16-T16) -> 0 | K16: =SUM(I16*$P16) -> 0 | L16: =SUM(J16*$Q16) -> 0 | M16: =K16+L16 -> 0 | N16: T1129010871 | O16: 144.75.187.135 | P16: =IF(G16="MFP",Tables!$B$2,Tables!$B$5) -> 0.0262 | Q16: =IF(G16="MFP",Tables!$B$3,Tables!$B$6) -> 0.118 | R16: =VLOOKUP($N16,'Meter Comparison'!$C$2:$G$314,2,FALSE) -> 321 | S16: =VLOOKUP($N16,'Meter Comparison'!$C$2:$G$314,3,FALSE) -> 321 | T16: =VLOOKUP($N16,'Meter Comparison'!$C$2:$G$314,4,FALSE) -> 0 | U16: =VLOOKUP($N16,'Meter Comparison'!$C$2:$G$314,5,FALSE) -> 0
A17: Air Force Rotc | B17: 10_03_011_02100_5521 | C17: =VLOOKUP(B17,Tables!$G$2:$H$90,2,FALSE) -> ROTC-Air Force | D17: Kilbourne Hall | E17: 2018 | F17: AF SP4310N | G17: =VLOOKUP(F17,Tables!$D$2:$E$20,2,FALSE) -> PTR | H17: 17099438 | I17: =SUM(S17-R17) -> 6 | J17: =SUM(U17-T17) -> 0 | K17: =SUM(I17*$P17) -> 0.1572 | L17: =SUM(J17*$Q17) -> 0 | M17: =K17+L17 -> 0.1572 | N17: T1129010832 | O17: 144.75.187.138 | P17: =IF(G17="MFP",Tables!$B$2,Tables!$B$5) -> 0.0262 | Q17: =IF(G17="MFP",Tables!$B$3,Tables!$B$6) -> 0.118 | R17: =VLOOKUP($N17,'Meter Comparison'!$C$2:$G$314,2,FALSE) -> 844 | S17: =VLOOKUP($N17,'Meter Comparison'!$C$2:$G$314,3,FALSE) -> 850 | T17: =VLOOKUP($N17,'Meter Comparison'!$C$2:$G$314,4,FALSE) -> 0 | U17: =VLOOKUP($N17,'Meter Comparison'!$C$2:$G$314,5,FALSE) -> 0
B18: 10_03_011_02100_5521 Total | M18: =SUBTOTAL(9,M16:M17) -> 0.1572
A19: Army Rotc | B19: 10_03_011_04100_5521 | C19: =VLOOKUP(B19,Tables!$G$2:$H$90,2,FALSE) -> ROTC-Army | D19: Kilbourne Hall | E19: 1024 | F19: AF SP4310N | G19: =VLOOKUP(F19,Tables!$D$2:$E$20,2,FALSE) -> PTR | H19: 17099705 | I19: =SUM(S19-R19) -> 0 | J19: =SUM(U19-T19) -> 0 | K19: =SUM(I19*$P19) -> 0 | L19: =SUM(J19*$Q19) -> 0 | M19: =K19+L19 -> 0 | N19: T1128911220 | O19: 144.75.187.127 | P19: =IF(G19="MFP",Tables!$B$2,Tables!$B$5) -> 0.0262 | Q19: =IF(G19="MFP",Tables!$B$3,Tables!$B$6) -> 0.118 | R19: =VLOOKUP($N19,'Meter Comparison'!$C$2:$G$314,2,FALSE) -> 119 | S19: =VLOOKUP($N19,'Meter Comparison'!$C$2:$G$314,3,FALSE) -> 119 | T19: =VLOOKUP($N19,'Meter Comparison'!$C$2:$G$314,4,FALSE) -> 0 | U19: =VLOOKUP($N19,'Meter Comparison'!$C$2:$G$314,5,FALSE) -> 0
A20: Army Rotc | B20: 10_03_011_04100_5521 | C20: =VLOOKUP(B20,Tables!$G$2:$H$90,2,FALSE) -> ROTC-Army | D20: Kilbourne Hall | E20: 1027 | F20: AF SP4310N | G20: =VLOOKUP(F20,Tables!$D$2:$E$20,2,FALSE) -> PTR | H20: 17099737 | I20: =SUM(S20-R20) -> 165 | J20: =SUM(U20-T20) -> 0 | K20: =SUM(I20*$P20) -> 4.323 | L20: =SUM(J20*$Q20) -> 0 | M20: =K20+L20 -> 4.323 | N20: T1129011362 | O20: 144.75.187.151 | P20: =IF(G20="MFP",Tables!$B$2,Tables!$B$5) -> 0.0262 | Q20: =IF(G20="MFP",Tables!$B$3,Tables!$B$6) -> 0.118 | R20: =VLOOKUP($N20,'Meter Comparison'!$C$2:$G$314,2,FALSE) -> 132 | S20: =VLOOKUP($N20,'Meter Comparison'!$C$2:$G$314,3,FALSE) -> 297 | T20: =VLOOKUP($N20,'Meter Comparison'!$C$2:$G$314,4,FALSE) -> 0 | U20: =VLOOKUP($N20,'Meter Comparison'!$C$2:$G$314,5,FALSE) -> 0
A21: Army Rotc | B21: 10_03_011_04100_5521 | C21: =VLOOKUP(B21,Tables!$G$2:$H$90,2,FALSE) -> ROTC-Army | D21: Kilbourne Hall | E21: 1027 | F21: AF SP4310N | G21: =VLOOKUP(F21,Tables!$D$2:$E$20,2,FALSE) -> PTR | H21: 17099738 | I21: =SUM(S21-R21) -> 49 | J21: =SUM(U21-T21) -> 0 | K21: =SUM(I21*$P21) -> 1.2838 | L21: =SUM(J21*$Q21) -> 0 | M21: =K21+L21 -> 1.2838 | N21: T1129012368 | O21: 144.75.187.148 | P21: =IF(G21="MFP",Tables!$B$2,Tables!$B$5) -> 0.0262 | Q21: =IF(G21="MFP",Tables!$B$3,Tables!$B$6) -> 0.118 | R21: =VLOOKUP($N21,'Meter Comparison'!$C$2:$G$314,2,FALSE) -> 297 | S21: =VLOOKUP($N21,'Meter Comparison'!$C$2:$G$314,3,FALSE) -> 346 | T21: =VLOOKUP($N21,'Meter Comparison'!$C$2:$G$314,4,FALSE) -> 0 | U21: =VLOOKUP($N21,'Meter Comparison'!$C$2:$G$314,5,FALSE) -> 0
A22: Army Rotc | B22: 10_03_011_04100_5521 | C22: =VLOOKUP(B22,Tables!$G$2:$H$90,2,FALSE) -> ROTC-Army | D22: Kilbourne Hall | E22: 1030 | F22: Af SP4310N | G22: =VLOOKUP(F22,Tables!$D$2:$E$20,2,FALSE) -> PTR | H22: 17099719 | I22: =SUM(S22-R22) -> 189 | J22: =SUM(U22-T22) -> 0 | K22: =SUM(I22*$P22) -> 4.9518 | L22: =SUM(J22*$Q22) -> 0 | M22: =K22+L22 -> 4.9518 | N22: T1129010918 | O22: 144.75.187.124 | P22: =IF(G22="MFP",Tables!$B$2,Tables!$B$5) -> 0.0262 | Q22: =IF(G22="MFP",Tables!$B$3,Tables!$B$6) -> 0.118 | R22: =VLOOKUP($N22,'Meter Comparison'!$C$2:$G$314,2,FALSE) -> 2399 | S22: =VLOOKUP($N22,'Meter Comparison'!$C$2:$G$314,3,FALSE) -> 2588 | T22: =VLOOKUP($N22,'Meter Comparison'!$C$2:$G$314,4,FALSE) -> 0 | U22: =VLOOKUP($N22,'Meter Comparison'!$C$2:$G$314,5,FALSE) -> 0
A23: Army Rotc | B23: 10_03_011_04100_5521 | C23: =VLOOKUP(B23,Tables!$G$2:$H$90,2,FALSE) -> ROTC-Army | D23: Kilbourne Hall | E23: 2020 | F23: AF SP4310N | G23: =VLOOKUP(F23,Tables!$D$2:$E$20,2,FALSE) -> PTR | H23: 17099714 | I23: =SUM(S23-R23) -> 113 | J23: =SUM(U23-T23) -> 0 | K23: =SUM(I23*$P23) -> 2.9606 | L23: =SUM(J23*$Q23) -> 0 | M23: =K23+L23 -> 2.9606 | N23: T1129010890 | O23: 144.75.187.101 | P23: =IF(G23="MFP",Tables!$B$2,Tables!$B$5) -> 0.0262 | Q23: =IF(G23="MFP",Tables!$B$3,Tables!$B$6) -> 0.118 | R23: =VLOOKUP($N23,'Meter Comparison'!$C$2:$G$314,2,FALSE) -> 794 | S23: =VLOOKUP($N23,'Meter Comparison'!$C$2:$G$314,3,FALSE) -> 907 | T23: =VLOOKUP($N23,'Meter Comparison'!$C$2:$G$314,4,FALSE) -> 0 | U23: =VLOOKUP($N23,'Meter Comparison'!$C$2:$G$314,5,FALSE) -> 0
A24: Army Rotc | B24: 10_03_011_04100_5521 | C24: =VLOOKUP(B24,Tables!$G$2:$H$90,2,FALSE) -> ROTC-Army | D24: Kilbourne Hall | E24: 2022 | F24: AF MPC3502 | G24: =VLOOKUP(F24,Tables!$D$2:$E$20,2,FALSE) -> MFP | H24: 17099434 | I24: =SUM(S24-R24) -> 10563 | J24: =SUM(U24-T24) -> 1101 | K24: =SUM(I24*$P24) -> 218.6541 | L24: =SUM(J24*$Q24) -> 95.787 | M24: =K24+L24 -> 314.4411 | N24: W502L600854 | O24: 144.75.187.122 | P24: =IF(G24="MFP",Tables!$B$2,Tables!$B$5) -> 0.0207 | Q24: =IF(G24="MFP",Tables!$B$3,Tables!$B$6) -> 0.087 | R24: =VLOOKUP($N24,'Meter Comparison'!$C$2:$G$314,2,FALSE) -> 85021 | S24: =VLOOKUP($N24,'Meter Comparison'!$C$2:$G$314,3,FALSE) -> 95584 | T24: =VLOOKUP($N24,'Meter Comparison'!$C$2:$G$314,4,FALSE) -> 8124 | U24: =VLOOKUP($N24,'Meter Comparison'!$C$2:$G$314,5,FALSE) -> 9225
A25: Army Rotc | B25: 10_03_011_04100_5521 | C25: =VLOOKUP(B25,Tables!$G$2:$H$90,2,FALSE) -> ROTC-Army | D25: Kilbourne Hall | E25: 2023 | F25: AF SP4310N | G25: =VLOOKUP(F25,Tables!$D$2:$E$20,2,FALSE) -> PTR | H25: 17099435 | I25: =SUM(S25-R25) -> 86 | J25: =SUM(U25-T25) -> 0 | K25: =SUM(I25*$P25) -> 2.2532 | L25: =SUM(J25*$Q25) -> 0 | M25: =K25+L25 -> 2.2532 | N25: T1129010902 | O25: 144.75.187.16 | P25: =IF(G25="MFP",Tables!$B$2,Tables!$B$5) -> 0.0262 | Q25: =IF(G25="MFP",Tables!$B$3,Tables!$B$6) -> 0.118 | R25: =VLOOKUP($N25,'Meter Comparison'!$C$2:$G$314,2,FALSE) -> 616 | S25: =VLOOKUP($N25,'Meter Comparison'!$C$2:$G$314,3,FALSE) -> 702 | T25: =VLOOKUP($N25,'Meter Comparison'!$C$2:$G$314,4,FALSE) -> 0 | U25: =VLOOKUP($N25,'Meter Comparison'!$C$2:$G$314,5,FALSE) -> 0
A26: Army Rotc | B26: 10_03_011_04100_5521 | C26: =VLOOKUP(B26,Tables!$G$2:$H$90,2,FALSE) -> ROTC-Army | D26: Kilbourne Hall | E26: 2029 | F26: AF SP4310N | G26: =VLOOKUP(F26,Tables!$D$2:$E$20,2,FALSE) -> PTR | H26: 17099446 | I26: =SUM(S26-R26) -> 29 | J26: =SUM(U26-T26) -> 0 | K26: =SUM(I26*$P26) -> 0.7598 | L26: =SUM(J26*$Q26) -> 0 | M26: =K26+L26 -> 0.7598 | N26: T1129010869 | O26: 144.75.187.137 | P26: =IF(G26="MFP",Tables!$B$2,Tables!$B$5) -> 0.0262 | Q26: =IF(G26="MFP",Tables!$B$3,Tables!$B$6) -> 0.118 | R26: =VLOOKUP($N26,'Meter Comparison'!$C$2:$G$314,2,FALSE) -> 308 | S26: =VLOOKUP($N26,'Meter Comparison'!$C$2:$G$314,3,FALSE) -> 337 | T26: =VLOOKUP($N26,'Meter Comparison'!$C$2:$G$314,4,FALSE) -> 0 | U26: =VLOOKUP($N26,'Meter Comparison'!$C$2:$G$314,5,FALSE) -> 0
A27: Army Rotc | B27: 10_03_011_04100_5521 | C27: =VLOOKUP(B27,Tables!$G$2:$H$90,2,FALSE) -> ROTC-Army | D27: Kilbourne Hall | E27: 2051 | F27: AF SP4310N | G27: =VLOOKUP(F27,Tables!$D$2:$E$20,2,FALSE) -> PTR | H27: 17099715 | I27: =SUM(S27-R27) -> 7 | J27: =SUM(U27-T27) -> 0 | K27: =SUM(I27*$P27) -> 0.1834 | L27: =SUM(J27*$Q27) -> 0 | M27: =K27+L27 -> 0.1834 | N27: T1129010910 | O27: 144.75.187.111 | P27: =IF(G27="MFP",Tables!$B$2,Tables!$B$5) -> 0.0262 | Q27: =IF(G27="MFP",Tables!$B$3,Tables!$B$6) -> 0.118 | R27: =VLOOKUP($N27,'Meter Comparison'!$C$2:$G$314,2,FALSE) -> 504 | S27: =VLOOKUP($N27,'Meter Comparison'!$C$2:$G$314,3,FALSE) -> 511 | T27: =VLOOKUP($N27,'Meter Comparison'!$C$2:$G$314,4,FALSE) -> 0 | U27: =VLOOKUP($N27,'Meter Comparison'!$C$2:$G$314,5,FALSE) -> 0
A28: Army Rotc | B28: 10_03_011_04100_5521 | C28: =VLOOKUP(B28,Tables!$G$2:$H$90,2,FALSE) -> ROTC-Army | D28: Kilbourne Hall | E28: 2052 | F28: AF SP4310N | G28: =VLOOKUP(F28,Tables!$D$2:$E$20,2,FALSE) -> PTR | H28: 17099852 | I28: =SUM(S28-R28) -> 2 | J28: =SUM(U28-T28) -> 0 | K28: =SUM(I28*$P28) -> 0.0524 | L28: =SUM(J28*$Q28) -> 0 | M28: =K28+L28 -> 0.0524 | N28: T1129010839 | O28: 144.75.187.102 | P28: =IF(G28="MFP",Tables!$B$2,Tables!$B$5) -> 0.0262 | Q28: =IF(G28="MFP",Tables!$B$3,Tables!$B$6) -> 0.118 | R28: =VLOOKUP($N28,'Meter Comparison'!$C$2:$G$314,2,FALSE) -> 5 | S28: =VLOOKUP($N28,'Meter Comparison'!$C$2:$G$314,3,FALSE) -> 7 | T28: =VLOOKUP($N28,'Meter Comparison'!$C$2:$G$314,4,FALSE) -> 0 | U28: =VLOOKUP($N28,'Meter Comparison'!$C$2:$G$314,5,FALSE) -> 0
A29: Army Rotc | B29: 10_03_011_04100_5521 | C29: =VLOOKUP(B29,Tables!$G$2:$H$90,2,FALSE) -> ROTC-Army | D29: Kilbourne Hall | E29: 2053 | F29: AF SP4310N | G29: =VLOOKUP(F29,Tables!$D$2:$E$20,2,FALSE) -> PTR | H29: 17099437 | I29: =SUM(S29-R29) -> 154 | J29: =SUM(U29-T29) -> 0 | K29: =SUM(I29*$P29) -> 4.0348 | L29: =SUM(J29*$Q29) -> 0 | M29: =K29+L29 -> 4.0348 | N29: T1129010748 | O29: 144.75.187.112 | P29: =IF(G29="MFP",Tables!$B$2,Tables!$B$5) -> 0.0262 | Q29: =IF(G29="MFP",Tables!$B$3,Tables!$B$6) -> 0.118 | R29: =VLOOKUP($N29,'Meter Comparison'!$C$2:$G$314,2,FALSE) -> 1512 | S29: =VLOOKUP($N29,'Meter Comparison'!$C$2:$G$314,3,FALSE) -> 1666 | T29: =VLOOKUP($N29,'Meter Comparison'!$C$2:$G$314,4,FALSE) -> 0 | U29: =VLOOKUP($N29,'Meter Comparison'!$C$2:$G$314,5,FALSE) -> 0
A30: Army Rotc | B30: 10_03_011_04100_5521 | C30: =VLOOKUP(B30,Tables!$G$2:$H$90,2,FALSE) -> ROTC-Army | D30: Kilbourne Hall | E30: 2056 | F30: AF SP4310N | G30: =VLOOKUP(F30,Tables!$D$2:$E$20,2,FALSE) -> PTR | H30: 17099436 | I30: =SUM(S30-R30) -> 385 | J30: =SUM(U30-T30) -> 0 | K30: =SUM(I30*$P30) -> 10.087 | L30: =SUM(J30*$Q30) -> 0 | M30: =K30+L30 -> 10.087 | N30: T1129010837 | O30: 144.75.187.131 | P30: =IF(G30="MFP",Tables!$B$2,Tables!$B$5) -> 0.0262 | Q30: =IF(G30="MFP",Tables!$B$3,Tables!$B$6) -> 0.118 | R30: =VLOOKUP($N30,'Meter Comparison'!$C$2:$G$314,2,FALSE) -> 2029 | S30: =VLOOKUP($N30,'Meter Comparison'!$C$2:$G$314,3,FALSE) -> 2414 | T30: =VLOOKUP($N30,'Meter Comparison'!$C$2:$G$314,4,FALSE) -> 0 | U30: =VLOOKUP($N30,'Meter Comparison'!$C$2:$G$314,5,FALSE) -> 0
... A40: Army Rotc | B40: 10_03_011_04100_5521 | C40: =VLOOKUP(B40,Tables!$G$2:$H$90,2,FALSE) -> ROTC-Army | D40: Kilbourne Hall | E40: 2070 | F40: AF SP4310N | G40: =VLOOKUP(F40,Tables!$D$2:$E$20,2,FALSE) -> PTR | H40: 17099428 | I40: =SUM(S40-R40) -> 94 | J40: =SUM(U40-T40) -> 0 | K40: =SUM(I40*$P40) -> 2.4628 | L40: =SUM(J40*$Q40) -> 0 | M40: =K40+L40 -> 2.4628 | N40: T1129010900 | O40: 144.75.187.132 | P40: =IF(G40="MFP",Tables!$B$2,Tables!$B$5) -> 0.0262 | Q40: =IF(G40="MFP",Tables!$B$3,Tables!$B$6) -> 0.118 | R40: =VLOOKUP($N40,'Meter Comparison'!$C$2:$G$314,2,FALSE) -> 1306 | S40: =VLOOKUP($N40,'Meter Comparison'!$C$2:$G$314,3,FALSE) -> 1400 | T40: =VLOOKUP($N40,'Meter Comparison'!$C$2:$G$314,4,FALSE) -> 0 | U40: =VLOOKUP($N40,'Meter Comparison'!$C$2:$G$314,5,FALSE) -> 0
B41: 10_03_011_04100_5521 Total | M41: =SUBTOTAL(9,M19:M40) -> 404.0189
A42: Athletic Advising | B42: 40_00_052_06550_5521 | C42: =VLOOKUP(B42,Tables!$G$2:$H$90,2,FALSE) -> AOF - Academic Advising | D42: Carroll Hall | E42: 210 | F42: AF MPC2051 | G42: =VLOOKUP(F42,Tables!$D$2:$E$20,2,FALSE) -> MFP | H42: 17099459 | I42: =SUM(S42-R42) -> 8227 | J42: =SUM(U42-T42) -> 433 | K42: =SUM(I42*$P42) -> 170.2989 | L42: =SUM(J42*$Q42) -> 37.671 | M42: =K42+L42 -> 207.9699 | N42: V9725401429 | O42: 144.75.195.41 | P42: =IF(G42="MFP",Tables!$B$2,Tables!$B$5) -> 0.0207 | Q42: =IF(G42="MFP",Tables!$B$3,Tables!$B$6) -> 0.087 | R42: =VLOOKUP($N42,'Meter Comparison'!$C$2:$G$314,2,FALSE) -> 41732 | S42: =VLOOKUP($N42,'Meter Comparison'!$C$2:$G$314,3,FALSE) -> 49959 | T42: =VLOOKUP($N42,'Meter Comparison'!$C$2:$G$314,4,FALSE) -> 3496 | U42: =VLOOKUP($N42,'Meter Comparison'!$C$2:$G$314,5,FALSE) -> 3929
B43: 40_00_052_06550_5521 Total | M43: =SUBTOTAL(9,M42:M42) -> 207.9699
A44: Athletic Communications | B44: 30_00_310_06104_5521 | C44: =VLOOKUP(B44,Tables!$G$2:$H$90,2,FALSE) -> Sports Information | D44: Smith Hall | E44: 116 | F44: AF MP301SP | G44: =VLOOKUP(F44,Tables!$D$2:$E$20,2,FALSE) -> MFP | H44: 17099531 | I44: =SUM(S44-R44) -> 1251 | J44: =SUM(U44-T44) -> 0 | K44: =SUM(I44*$P44) -> 25.8957 | L44: =SUM(J44*$Q44) -> 0 | M44: =K44+L44 -> 25.8957 | N44: W912P602286 | O44: 144.75.179.49 | P44: =IF(G44="MFP",Tables!$B$2,Tables!$B$5) -> 0.0207 | Q44: =IF(G44="MFP",Tables!$B$3,Tables!$B$6) -> 0.087 | R44: =VLOOKUP($N44,'Meter Comparison'!$C$2:$G$314,2,FALSE) -> 6785 | S44: =VLOOKUP($N44,'Meter Comparison'!$C$2:$G$314,3,FALSE) -> 8036 | T44: =VLOOKUP($N44,'Meter Comparison'!$C$2:$G$314,4,FALSE) -> 0 | U44: =VLOOKUP($N44,'Meter Comparison'!$C$2:$G$314,5,FALSE) -> 0
B45: 30_00_310_06104_5521 Total | M45: =SUBTOTAL(9,M44:M44) -> 25.8957
A46: Athletics | B46: 30_00_310_06020_5521 | C46: =VLOOKUP(B46,Tables!$G$2:$H$90,2,FALSE) -> Track & Cross Country | D46: Cameron Hall | E46: 231 | F46: AF SP4310N | G46: =VLOOKUP(F46,Tables!$D$2:$E$20,2,FALSE) -> PTR | H46: 17099560 | I46: =SUM(S46-R46) -> 520 | J46: =SUM(U46-T46) -> 0 | K46: =SUM(I46*$P46) -> 13.624 | L46: =SUM(J46*$Q46) -> 0 | M46: =K46+L46 -> 13.624 | N46: T1129010426 | O46: 144.75.183.68 | P46: =IF(G46="MFP",Tables!$B$2,Tables!$B$5) -> 0.0262 | Q46: =IF(G46="MFP",Tables!$B$3,Tables!$B$6) -> 0.118 | R46: =VLOOKUP($N46,'Meter Comparison'!$C$2:$G$314,2,FALSE) -> 3600 | S46: =VLOOKUP($N46,'Meter Comparison'!$C$2:$G$314,3,FALSE) -> 4120 | T46: =VLOOKUP($N46,'Meter Comparison'!$C$2:$G$314,4,FALSE) -> 0 | U46: =VLOOKUP($N46,'Meter Comparison'!$C$2:$G$314,5,FALSE) -> 0
B47: 30_00_310_06020_5521 Total | M47: =SUBTOTAL(9,M46:M46) -> 13.624
A48: Athletics | B48: 30_00_310_06090_5521 | C48: =VLOOKUP(B48,Tables!$G$2:$H$90,2,FALSE) -> Soccer | D48: Cameron Hall | E48: 245 | F48: AF SP4310N | G48: =VLOOKUP(F48,Tables!$D$2:$E$20,2,FALSE) -> PTR | H48: 17099557 | I48: =SUM(S48-R48) -> 93 | J48: =SUM(U48-T48) -> 0 | K48: =SUM(I48*$P48) -> 2.4366 | L48: =SUM(J48*$Q48) -> 0 | M48: =K48+L48 -> 2.4366 | N48: T1129010429 | O48: 144.75.183.65 | P48: =IF(G48="MFP",Tables!$B$2,Tables!$B$5) -> 0.0262 | Q48: =IF(G48="MFP",Tables!$B$3,Tables!$B$6) -> 0.118 | R48: =VLOOKUP($N48,'Meter Comparison'!$C$2:$G$314,2,FALSE) -> 948 | S48: =VLOOKUP($N48,'Meter Comparison'!$C$2:$G$314,3,FALSE) -> 1041 | T48: =VLOOKUP($N48,'Meter Comparison'!$C$2:$G$314,4,FALSE) -> 0 | U48: =VLOOKUP($N48,'Meter Comparison'!$C$2:$G$314,5,FALSE) -> 0
B49: 30_00_310_06090_5521 Total | M49: =SUBTOTAL(9,M48:M48) -> 2.4366
A50: Athletics | B50: 30_00_310_06095_5521 | C50: =VLOOKUP(B50,Tables!$G$2:$H$90,2,FALSE) -> Soccer - Women | D50: Cameron Hall | E50: 239 | F50: AF SP4310N | G50: =VLOOKUP(F50,Tables!$D$2:$E$20,2,FALSE) -> PTR | H50: 17099565 | I50: =SUM(S50-R50) -> 341 | J50: =SUM(U50-T50) -> 0 | K50: =SUM(I50*$P50) -> 8.9342 | L50: =SUM(J50*$Q50) -> 0 | M50: =K50+L50 -> 8.9342 | N50: T1129010419 | O50: 144.75.183.69 | P50: =IF(G50="MFP",Tables!$B$2,Tables!$B$5) -> 0.0262 | Q50: =IF(G50="MFP",Tables!$B$3,Tables!$B$6) -> 0.118 | R50: =VLOOKUP($N50,'Meter Comparison'!$C$2:$G$314,2,FALSE) -> 777 | S50: =VLOOKUP($N50,'Meter Comparison'!$C$2:$G$314,3,FALSE) -> 1118 | T50: =VLOOKUP($N50,'Meter Comparison'!$C$2:$G$314,4,FALSE) -> 0 | U50: =VLOOKUP($N50,'Meter Comparison'!$C$2:$G$314,5,FALSE) -> 0
B51: 30_00_310_06095_5521 Total | M51: =SUBTOTAL(9,M50:M50) -> 8.9342
A52: Athletics | B52: 30_00_310_06110_5521 | C52: =VLOOKUP(B52,Tables!$G$2:$H$90,2,FALSE) -> Administrative | D52: Cameron Hall | E52: 204 | F52: AF MP301SP | G52: =VLOOKUP(F52,Tables!$D$2:$E$20,2,FALSE) -> MFP | H52: 17099507 | I52: =SUM(S52-R52) -> 1453 | J52: =SUM(U52-T52) -> 0 | K52: =SUM(I52*$P52) -> 30.0771 | L52: =SUM(J52*$Q52) -> 0 | M52: =K52+L52 -> 30.0771 | N52: W912P602280 | O52: 144.75.183.73 | P52: =IF(G52="MFP",Tables!$B$2,Tables!$B$5) -> 0.0207 | Q52: =IF(G52="MFP",Tables!$B$3,Tables!$B$6) -> 0.087 | R52: =VLOOKUP($N52,'Meter Comparison'!$C$2:$G$314,2,FALSE) -> 13733 | S52: =VLOOKUP($N52,'Meter Comparison'!$C$2:$G$314,3,FALSE) -> 15186 | T52: =VLOOKUP($N52,'Meter Comparison'!$C$2:$G$314,4,FALSE) -> 0 | U52: =VLOOKUP($N52,'Meter Comparison'!$C$2:$G$314,5,FALSE) -> 0
A53: Athletics | B53: 30_00_310_06110_5521 | C53: =VLOOKUP(B53,Tables!$G$2:$H$90,2,FALSE) -> Administrative | D53: Cameron Hall | E53: 235 | F53: AF MPC6501 | G53: =VLOOKUP(F53,Tables!$D$2:$E$20,2,FALSE) -> MFP | H53: 17099490 | I53: =SUM(S53-R53) -> 8890 | J53: =SUM(U53-T53) -> 2334 | K53: =SUM(I53*$P53) -> 184.023 | L53: =SUM(J53*$Q53) -> 203.058 | M53: =K53+L53 -> 387.081 | N53: V7620400078 | O53: 144.75.183.56 | P53: =IF(G53="MFP",Tables!$B$2,Tables!$B$5) -> 0.0207 | Q53: =IF(G53="MFP",Tables!$B$3,Tables!$B$6) -> 0.087 | R53: =VLOOKUP($N53,'Meter Comparison'!$C$2:$G$314,2,FALSE) -> 44575 | S53: =VLOOKUP($N53,'Meter Comparison'!$C$2:$G$314,3,FALSE) -> 53465 | T53: =VLOOKUP($N53,'Meter Comparison'!$C$2:$G$314,4,FALSE) -> 16173 | U53: =VLOOKUP($N53,'Meter Comparison'!$C$2:$G$314,5,FALSE) -> 18507
A54: Athletics | B54: 30_00_310_06110_5521 | C54: =VLOOKUP(B54,Tables!$G$2:$H$90,2,FALSE) -> Administrative | D54: Cameron Hall | E54: 241 | F54: AF SP4310N | G54: =VLOOKUP(F54,Tables!$D$2:$E$20,2,FALSE) -> PTR | H54: 17099552 | I54: =SUM(S54-R54) -> 783 | J54: =SUM(U54-T54) -> 0 | K54: =SUM(I54*$P54) -> 20.5146 | L54: =SUM(J54*$Q54) -> 0 | M54: =K54+L54 -> 20.5146 | N54: T1129010427 | O54: 144.75.183.9 | P54: =IF(G54="MFP",Tables!$B$2,Tables!$B$5) -> 0.0262 | Q54: =IF(G54="MFP",Tables!$B$3,Tables!$B$6) -> 0.118 | R54: =VLOOKUP($N54,'Meter Comparison'!$C$2:$G$314,2,FALSE) -> 4560 | S54: =VLOOKUP($N54,'Meter Comparison'!$C$2:$G$314,3,FALSE) -> 5343 | T54: =VLOOKUP($N54,'Meter Comparison'!$C$2:$G$314,4,FALSE) -> 0 | U54: =VLOOKUP($N54,'Meter Comparison'!$C$2:$G$314,5,FALSE) -> 0
A55: Athletics | B55: 30_00_310_06110_5521 | C55: =VLOOKUP(B55,Tables!$G$2:$H$90,2,FALSE) -> Administrative | D55: Cameron Hall | E55: 242 | F55: AF SP4310N | G55: =VLOOKUP(F55,Tables!$D$2:$E$20,2,FALSE) -> PTR | H55: 17099553 | I55: =SUM(S55-R55) -> 244 | J55: =SUM(U55-T55) -> 0 | K55: =SUM(I55*$P55) -> 6.3928 | L55: =SUM(J55*$Q55) -> 0 | M55: =K55+L55 -> 6.3928 | N55: T1129010420 | O55: 144.75.183.64 | P55: =IF(G55="MFP",Tables!$B$2,Tables!$B$5) -> 0.0262 | Q55: =IF(G55="MFP",Tables!$B$3,Tables!$B$6) -> 0.118 | R55: =VLOOKUP($N55,'Meter Comparison'!$C$2:$G$314,2,FALSE) -> 1332 | S55: =VLOOKUP($N55,'Meter Comparison'!$C$2:$G$314,3,FALSE) -> 1576 | T55: =VLOOKUP($N55,'Meter Comparison'!$C$2:$G$314,4,FALSE) -> 0 | U55: =VLOOKUP($N55,'Meter Comparison'!$C$2:$G$314,5,FALSE) -> 0
A56: Athletics | B56: 30_00_310_06110_5521 | C56: =VLOOKUP(B56,Tables!$G$2:$H$90,2,FALSE) -> Administrative | D56: Cameron Hall | E56: 302 | F56: AF MPC2051 | G56: =VLOOKUP(F56,Tables!$D$2:$E$20,2,FALSE) -> MFP | H56: 17099722 | I56: =SUM(S56-R56) -> 1020 | J56: =SUM(U56-T56) -> 1717 | K56: =SUM(I56*$P56) -> 21.114 | L56: =SUM(J56*$Q56) -> 149.379 | M56: =K56+L56 -> 170.493 | N56: V9725401418 | O56: 144.75.183.52 | P56: =IF(G56="MFP",Tables!$B$2,Tables!$B$5) -> 0.0207 | Q56: =IF(G56="MFP",Tables!$B$3,Tables!$B$6) -> 0.087 | R56: =VLOOKUP($N56,'Meter Comparison'!$C$2:$G$314,2,FALSE) -> 6989 | S56: =VLOOKUP($N56,'Meter Comparison'!$C$2:$G$314,3,FALSE) -> 8009 | T56: =VLOOKUP($N56,'Meter Comparison'!$C$2:$G$314,4,FALSE) -> 15368 | U56: =VLOOKUP($N56,'Meter Comparison'!$C$2:$G$314,5,FALSE) -> 17085
A57: Athletics | B57: 30_00_310_06110_5521 | C57: =VLOOKUP(B57,Tables!$G$2:$H$90,2,FALSE) -> Administrative | D57: Cameron Hall | E57: 312 | F57: AF SP4310N | G57: =VLOOKUP(F57,Tables!$D$2:$E$20,2,FALSE) -> PTR | H57: 17099555 | I57: =SUM(S57-R57) -> 244 | J57: =SUM(U57-T57) -> 0 | K57: =SUM(I57*$P57) -> 6.3928 | L57: =SUM(J57*$Q57) -> 0 | M57: =K57+L57 -> 6.3928 | N57: T1129010428 | O57: 144.75.183.67 | P57: =IF(G57="MFP",Tables!$B$2,Tables!$B$5) -> 0.0262 | Q57: =IF(G57="MFP",Tables!$B$3,Tables!$B$6) -> 0.118 | R57: =VLOOKUP($N57,'Meter Comparison'!$C$2:$G$314,2,FALSE) -> 1861 | S57: =VLOOKUP($N57,'Meter Comparison'!$C$2:$G$314,3,FALSE) -> 2105 | T57: =VLOOKUP($N57,'Meter Comparison'!$C$2:$G$314,4,FALSE) -> 0 | U57: =VLOOKUP($N57,'Meter Comparison'!$C$2:$G$314,5,FALSE) -> 0
A58: Athletics | B58: 30_00_310_06110_5521 | C58: =VLOOKUP(B58,Tables!$G$2:$H$90,2,FALSE) -> Administrative | D58: Cameron Hall | E58: 314 | F58: AF SP4310N | G58: =VLOOKUP(F58,Tables!$D$2:$E$20,2,FALSE) -> PTR | H58: 17099558 | I58: =SUM(S58-R58) -> 229 | J58: =SUM(U58-T58) -> 0 | K58: =SUM(I58*$P58) -> 5.9998 | L58: =SUM(J58*$Q58) -> 0 | M58: =K58+L58 -> 5.9998 | N58: T1129010421 | O58: 144.75.183.62 | P58: =IF(G58="MFP",Tables!$B$2,Tables!$B$5) -> 0.0262 | Q58: =IF(G58="MFP",Tables!$B$3,Tables!$B$6) -> 0.118 | R58: =VLOOKUP($N58,'Meter Comparison'!$C$2:$G$314,2,FALSE) -> 2100 | S58: =VLOOKUP($N58,'Meter Comparison'!$C$2:$G$314,3,FALSE) -> 2329 | T58: =VLOOKUP($N58,'Meter Comparison'!$C$2:$G$314,4,FALSE) -> 0 | U58: =VLOOKUP($N58,'Meter Comparison'!$C$2:$G$314,5,FALSE) -> 0
A59: Athletics | B59: 30_00_310_06110_5521 | C59: =VLOOKUP(B59,Tables!$G$2:$H$90,2,FALSE) -> Administrative | D59: Cameron Hall | E59: 317 | F59: AF SP4310N | G59: =VLOOKUP(F59,Tables!$D$2:$E$20,2,FALSE) -> PTR | H59: 17099554 | I59: =SUM(S59-R59) -> 209 | J59: =SUM(U59-T59) -> 0 | K59: =SUM(I59*$P59) -> 5.4758 | L59: =SUM(J59*$Q59) -> 0 | M59: =K59+L59 -> 5.4758 | N59: T1129010385 | O59: 144.75.183.63 | P59: =IF(G59="MFP",Tables!$B$2,Tables!$B$5) -> 0.0262 | Q59: =IF(G59="MFP",Tables!$B$3,Tables!$B$6) -> 0.118 | R59: =VLOOKUP($N59,'Meter Comparison'!$C$2:$G$314,2,FALSE) -> 694 | S59: =VLOOKUP($N59,'Meter Comparison'!$C$2:$G$314,3,FALSE) -> 903 | T59: =VLOOKUP($N59,'Meter Comparison'!$C$2:$G$314,4,FALSE) -> 0 | U59: =VLOOKUP($N59,'Meter Comparison'!$C$2:$G$314,5,FALSE) -> 0
B60: 30_00_310_06110_5521 Total | M60: =SUBTOTAL(9,M52:M59) -> 632.4269
A61: Auxiliary Services | B61: 10_08_309_82115_5521 | C61: =VLOOKUP(B61,Tables!$G$2:$H$90,2,FALSE) -> Auxiliary Administration | D61: Cocke Hall | E61: 502 | F61: AF MPC2051 | G61: =VLOOKUP(F61,Tables!$D$2:$E$20,2,FALSE) -> MFP | H61: 17099424 | I61: =SUM(S61-R61) -> 1017 | J61: =SUM(U61-T61) -> 36 | K61: =SUM(I61*$P61) -> 21.0519 | L61: =SUM(J61*$Q61) -> 3.132 | M61: =K61+L61 -> 24.1839 | N61: V9725500651 | O61: 144.75.177.32 | P61: =IF(G61="MFP",Tables!$B$2,Tables!$B$5) -> 0.0207 | Q61: =IF(G61="MFP",Tables!$B$3,Tables!$B$6) -> 0.087 | R61: =VLOOKUP($N61,'Meter Comparison'!$C$2:$G$314,2,FALSE) -> 6728 | S61: =VLOOKUP($N61,'Meter Comparison'!$C$2:$G$314,3,FALSE) -> 7745 | T61: =VLOOKUP($N61,'Meter Comparison'!$C$2:$G$314,4,FALSE) -> 821 | U61: =VLOOKUP($N61,'Meter Comparison'!$C$2:$G$314,5,FALSE) -> 857
B62: 10_08_309_82115_5521 Total | M62: =SUBTOTAL(9,M61:M61) -> 24.1839
A63: Band | B63: 10_07_205_30200_5521 | C63: =VLOOKUP(B63,Tables!$G$2:$H$90,2,FALSE) -> UMA-Band | D63: Shell Hall | E63: 207 | F63: AF MP301SP | G63: =VLOOKUP(F63,Tables!$D$2:$E$20,2,FALSE) -> MFP | H63: 17099460 | I63: =SUM(S63-R63) -> 774 | J63: =SUM(U63-T63) -> 0 | K63: =SUM(I63*$P63) -> 16.0218 | L63: =SUM(J63*$Q63) -> 0 | M63: =K63+L63 -> 16.0218 | N63: W912P602276 | O63: 144.75.180.76 | P63: =IF(G63="MFP",Tables!$B$2,Tables!$B$5) -> 0.0207 | Q63: =IF(G63="MFP",Tables!$B$3,Tables!$B$6) -> 0.087 | R63: =VLOOKUP($N63,'Meter Comparison'!$C$2:$G$314,2,FALSE) -> 6616 | S63: =VLOOKUP($N63,'Meter Comparison'!$C$2:$G$314,3,FALSE) -> 7390 | T63: =VLOOKUP($N63,'Meter Comparison'!$C$2:$G$314,4,FALSE) -> 0 | U63: =VLOOKUP($N63,'Meter Comparison'!$C$2:$G$314,5,FALSE) -> 0
B64: 10_07_205_30200_5521 Total | M64: =SUBTOTAL(9,M63:M63) -> 16.0218
A65: Biology | B65: 10_03_011_10100_5521 | C65: =VLOOKUP(B65,Tables!$G$2:$H$90,2,FALSE) -> Biology | D65: Maury Brooke | E65: 219 | F65: AF SP4310N | G65: =VLOOKUP(F65,Tables!$D$2:$E$20,2,FALSE) -> PTR | H65: 17099760 | I65: =SUM(S65-R65) -> 306 | J65: =SUM(U65-T65) -> 0 | K65: =SUM(I65*$P65) -> 8.0172 | L65: =SUM(J65*$Q65) -> 0 | M65: =K65+L65 -> 8.0172 | N65: T1129011348 | O65: 144.75.202.70 | P65: =IF(G65="MFP",Tables!$B$2,Tables!$B$5) -> 0.0262 | Q65: =IF(G65="MFP",Tables!$B$3,Tables!$B$6) -> 0.118 | R65: =VLOOKUP($N65,'Meter Comparison'!$C$2:$G$314,2,FALSE) -> 906 | S65: =VLOOKUP($N65,'Meter Comparison'!$C$2:$G$314,3,FALSE) -> 1212 | T65: =VLOOKUP($N65,'Meter Comparison'!$C$2:$G$314,4,FALSE) -> 0 | U65: =VLOOKUP($N65,'Meter Comparison'!$C$2:$G$314,5,FALSE) -> 0
A66: Biology | B66: 10_03_011_10100_5521 | C66: =VLOOKUP(B66,Tables!$G$2:$H$90,2,FALSE) -> Biology | D66: Maury Brooke | E66: 216A | F66: AF SP4310N | G66: =VLOOKUP(F66,Tables!$D$2:$E$20,2,FALSE) -> PTR | H66: 17099814 | I66: =SUM(S66-R66) -> 68 | J66: =SUM(U66-T66) -> 0 | K66: =SUM(I66*$P66) -> 1.7816 | L66: =SUM(J66*$Q66) -> 0 | M66: =K66+L66 -> 1.7816 | N66: T1128911357 | O66: 144.75.202.38 | P66: =IF(G66="MFP",Tables!$B$2,Tables!$B$5) -> 0.0262 | Q66: =IF(G66="MFP",Tables!$B$3,Tables!$B$6) -> 0.118 | R66: =VLOOKUP($N66,'Meter Comparison'!$C$2:$G$314,2,FALSE) -> 169 | S66: =VLOOKUP($N66,'Meter Comparison'!$C$2:$G$314,3,FALSE) -> 237 | T66: =VLOOKUP($N66,'Meter Comparison'!$C$2:$G$314,4,FALSE) -> 0 | U66: =VLOOKUP($N66,'Meter Comparison'!$C$2:$G$314,5,FALSE) -> 0
B67: 10_03_011_10100_5521 Total | M67: =SUBTOTAL(9,M65:M66) -> 9.7988
A68: Biology | B68: 10_03_064_50550_5521 | C68: =VLOOKUP(B68,Tables!$G$2:$H$90,2,FALSE) -> Printer Services | D68: Maury Brooke | E68: 204A | F68: AF SP4310N | G68: =VLOOKUP(F68,Tables!$D$2:$E$20,2,FALSE) -> PTR | H68: 17099708 | I68: =SUM(S68-R68) -> 150 | J68: =SUM(U68-T68) -> 0 | K68: =SUM(I68*$P68) -> 3.93 | L68: =SUM(J68*$Q68) -> 0 | M68: =K68+L68 -> 3.93 | N68: T1129011358 | O68: 144.75.202.47 | P68: =IF(G68="MFP",Tables!$B$2,Tables!$B$5) -> 0.0262 | Q68: =IF(G68="MFP",Tables!$B$3,Tables!$B$6) -> 0.118 | R68: =VLOOKUP($N68,'Meter Comparison'!$C$2:$G$314,2,FALSE) -> 472 | S68: =VLOOKUP($N68,'Meter Comparison'!$C$2:$G$314,3,FALSE) -> 622 | T68: =VLOOKUP($N68,'Meter Comparison'!$C$2:$G$314,4,FALSE) -> 0 | U68: =VLOOKUP($N68,'Meter Comparison'!$C$2:$G$314,5,FALSE) -> 0
B69: 10_03_064_50550_5521 Total | M69: =SUBTOTAL(9,M68:M68) -> 3.93
A70: Biology | B70: 40_00_011_10250_5521 | C70: =VLOOKUP(B70,Tables!$G$2:$H$90,2,FALSE) -> Carroll Biology Fund | D70: Mallory Hall | E70: 207 | F70: AF SP4310N | G70: =VLOOKUP(F70,Tables!$D$2:$E$20,2,FALSE) -> PTR | H70: 17099734 | I70: =SUM(S70-R70) -> 174 | J70: =SUM(U70-T70) -> 0 | K70: =SUM(I70*$P70) -> 4.5588 | L70: =SUM(J70*$Q70) -> 0 | M70: =K70+L70 -> 4.5588 | N70: T1129012363 | O70: 144.75.182.92 | P70: =IF(G70="MFP",Tables!$B$2,Tables!$B$5) -> 0.0262 | Q70: =IF(G70="MFP",Tables!$B$3,Tables!$B$6) -> 0.118 | R70: =VLOOKUP($N70,'Meter Comparison'!$C$2:$G$314,2,FALSE) -> 320 | S70: =VLOOKUP($N70,'Meter Comparison'!$C$2:$G$314,3,FALSE) -> 494 | T70: =VLOOKUP($N70,'Meter Comparison'!$C$2:$G$314,4,FALSE) -> 0 | U70: =VLOOKUP($N70,'Meter Comparison'!$C$2:$G$314,5,FALSE) -> 0
A71: Biology | B71: 40_00_011_10250_5521 | C71: =VLOOKUP(B71,Tables!$G$2:$H$90,2,FALSE) -> Carroll Biology Fund | D71: Maury Brooke | E71: 203 | F71: AF SP4310N | G71: =VLOOKUP(F71,Tables!$D$2:$E$20,2,FALSE) -> PTR | H71: 17099613 | I71: =SUM(S71-R71) -> 1807 | J71: =SUM(U71-T71) -> 0 | K71: =SUM(I71*$P71) -> 47.3434 | L71: =SUM(J71*$Q71) -> 0 | M71: =K71+L71 -> 47.3434 | N71: T1129011365 | O71: 144.75.202.56 | P71: =IF(G71="MFP",Tables!$B$2,Tables!$B$5) -> 0.0262 | Q71: =IF(G71="MFP",Tables!$B$3,Tables!$B$6) -> 0.118 | R71: =VLOOKUP($N71,'Meter Comparison'!$C$2:$G$314,2,FALSE) -> 7117 | S71: =VLOOKUP($N71,'Meter Comparison'!$C$2:$G$314,3,FALSE) -> 8924 | T71: =VLOOKUP($N71,'Meter Comparison'!$C$2:$G$314,4,FALSE) -> 0 | U71: =VLOOKUP($N71,'Meter Comparison'!$C$2:$G$314,5,FALSE) -> 0
A72: Biology | B72: 40_00_011_10250_5521 | C72: =VLOOKUP(B72,Tables!$G$2:$H$90,2,FALSE) -> Carroll Biology Fund | D72: Maury Brooke | E72: 203 | F72: AF MPC2051 | G72: =VLOOKUP(F72,Tables!$D$2:$E$20,2,FALSE) -> MFP | H72: 17099484 | I72: =SUM(S72-R72) -> 3096 | J72: =SUM(U72-T72) -> 1516 | K72: =SUM(I72*$P72) -> 64.0872 | L72: =SUM(J72*$Q72) -> 131.892 | M72: =K72+L72 -> 195.9792 | N72: V9725401445 | O72: 144.75.191.21 | P72: =IF(G72="MFP",Tables!$B$2,Tables!$B$5) -> 0.0207 | Q72: =IF(G72="MFP",Tables!$B$3,Tables!$B$6) -> 0.087 | R72: =VLOOKUP($N72,'Meter Comparison'!$C$2:$G$314,2,FALSE) -> 16505 | S72: =VLOOKUP($N72,'Meter Comparison'!$C$2:$G$314,3,FALSE) -> 19601 | T72: =VLOOKUP($N72,'Meter Comparison'!$C$2:$G$314,4,FALSE) -> 2396 | U72: =VLOOKUP($N72,'Meter Comparison'!$C$2:$G$314,5,FALSE) -> 3912
A73: Biology | B73: 40_00_011_10250_5521 | C73: =VLOOKUP(B73,Tables!$G$2:$H$90,2,FALSE) -> Carroll Biology Fund | D73: Maury Brooke | E73: 203A | F73: AF SP4310N | G73: =VLOOKUP(F73,Tables!$D$2:$E$20,2,FALSE) -> PTR | H73: 17099611 | I73: =SUM(S73-R73) -> 1325 | J73: =SUM(U73-T73) -> 0 | K73: =SUM(I73*$P73) -> 34.715 | L73: =SUM(J73*$Q73) -> 0 | M73: =K73+L73 -> 34.715 | N73: T1128911356 | O73: 144.75.202.51 | P73: =IF(G73="MFP",Tables!$B$2,Tables!$B$5) -> 0.0262 | Q73: =IF(G73="MFP",Tables!$B$3,Tables!$B$6) -> 0.118 | R73: =VLOOKUP($N73,'Meter Comparison'!$C$2:$G$314,2,FALSE) -> 3967 | S73: =VLOOKUP($N73,'Meter Comparison'!$C$2:$G$314,3,FALSE) -> 5292 | T73: =VLOOKUP($N73,'Meter Comparison'!$C$2:$G$314,4,FALSE) -> 0 | U73: =VLOOKUP($N73,'Meter Comparison'!$C$2:$G$314,5,FALSE) -> 0
A74: Biology | B74: 40_00_011_10250_5521 | C74: =VLOOKUP(B74,Tables!$G$2:$H$90,2,FALSE) -> Carroll Biology Fund | D74: Maury Brooke | E74: 203B | F74: AF SP4310N | G74: =VLOOKUP(F74,Tables!$D$2:$E$20,2,FALSE) -> PTR | H74: 17099569 | I74: =SUM(S74-R74) -> 194 | J74: =SUM(U74-T74) -> 0 | K74: =SUM(I74*$P74) -> 5.0828 | L74: =SUM(J74*$Q74) -> 0 | M74: =K74+L74 -> 5.0828 | N74: T1129011364 | O74: 144.75.202.58 | P74: =IF(G74="MFP",Tables!$B$2,Tables!$B$5) -> 0.0262 | Q74: =IF(G74="MFP",Tables!$B$3,Tables!$B$6) -> 0.118 | R74: =VLOOKUP($N74,'Meter Comparison'!$C$2:$G$314,2,FALSE) -> 548 | S74: =VLOOKUP($N74,'Meter Comparison'!$C$2:$G$314,3,FALSE) -> 742 | T74: =VLOOKUP($N74,'Meter Comparison'!$C$2:$G$314,4,FALSE) -> 0 | U74: =VLOOKUP($N74,'Meter Comparison'!$C$2:$G$314,5,FALSE) -> 0
A75: Biology | B75: 40_00_011_10250_5521 | C75: =VLOOKUP(B75,Tables!$G$2:$H$90,2,FALSE) -> Carroll Biology Fund | D75: Maury Brooke | E75: 203C | F75: AF SP4310N | G75: =VLOOKUP(F75,Tables!$D$2:$E$20,2,FALSE) -> PTR | H75: 17099612 | I75: =SUM(S75-R75) -> 63 | J75: =SUM(U75-T75) -> 0 | K75: =SUM(I75*$P75) -> 1.6506 | L75: =SUM(J75*$Q75) -> 0 | M75: =K75+L75 -> 1.6506 | N75: T1128911365 | O75: 144.75.202.44 | P75: =IF(G75="MFP",Tables!$B$2,Tables!$B$5) -> 0.0262 | Q75: =IF(G75="MFP",Tables!$B$3,Tables!$B$6) -> 0.118 | R75: =VLOOKUP($N75,'Meter Comparison'!$C$2:$G$314,2,FALSE) -> 588 | S75: =VLOOKUP($N75,'Meter Comparison'!$C$2:$G$314,3,FALSE) -> 651 | T75: =VLOOKUP($N75,'Meter Comparison'!$C$2:$G$314,4,FALSE) -> 0 | U75: =VLOOKUP($N75,'Meter Comparison'!$C$2:$G$314,5,FALSE) -> 0
A76: Biology | B76: 40_00_011_10250_5521 | C76: =VLOOKUP(B76,Tables!$G$2:$H$90,2,FALSE) -> Carroll Biology Fund | D76: Maury Brooke | E76: 203D | F76: AF SP4310N | G76: =VLOOKUP(F76,Tables!$D$2:$E$20,2,FALSE) -> PTR | H76: 17099568 | I76: =SUM(S76-R76) -> 351 | J76: =SUM(U76-T76) -> 0 | K76: =SUM(I76*$P76) -> 9.1962 | L76: =SUM(J76*$Q76) -> 0 | M76: =K76+L76 -> 9.1962 | N76: T1129012361 | O76: 144.75.202.57 | P76: =IF(G76="MFP",Tables!$B$2,Tables!$B$5) -> 0.0262 | Q76: =IF(G76="MFP",Tables!$B$3,Tables!$B$6) -> 0.118 | R76: =VLOOKUP($N76,'Meter Comparison'!$C$2:$G$314,2,FALSE) -> 839 | S76: =VLOOKUP($N76,'Meter Comparison'!$C$2:$G$314,3,FALSE) -> 1190 | T76: =VLOOKUP($N76,'Meter Comparison'!$C$2:$G$314,4,FALSE) -> 0 | U76: =VLOOKUP($N76,'Meter Comparison'!$C$2:$G$314,5,FALSE) -> 0
B77: 40_00_011_10250_5521 Total | M77: =SUBTOTAL(9,M70:M76) -> 298.526
A78: Business Office | B78: 10_03_062_16100_5521 | C78: =VLOOKUP(B78,Tables!$G$2:$H$90,2,FALSE) -> Business Executive | D78: Smith Hall | E78: 301 | F78: AF SP4310N | G78: =VLOOKUP(F78,Tables!$D$2:$E$20,2,FALSE) -> PTR | H78: 17099696 | I78: =SUM(S78-R78) -> 585 | J78: =SUM(U78-T78) -> 0 | K78: =SUM(I78*$P78) -> 15.327 | L78: =SUM(J78*$Q78) -> 0 | M78: =K78+L78 -> 15.327 | N78: T1129012215 | O78: 144.75.179.113 | P78: =IF(G78="MFP",Tables!$B$2,Tables!$B$5) -> 0.0262 | Q78: =IF(G78="MFP",Tables!$B$3,Tables!$B$6) -> 0.118 | R78: =VLOOKUP($N78,'Meter Comparison'!$C$2:$G$314,2,FALSE) -> 2689 | S78: =VLOOKUP($N78,'Meter Comparison'!$C$2:$G$314,3,FALSE) -> 3274 | T78: =VLOOKUP($N78,'Meter Comparison'!$C$2:$G$314,4,FALSE) -> 0 | U78: =VLOOKUP($N78,'Meter Comparison'!$C$2:$G$314,5,FALSE) -> 0
A79: Business Office | B79: 10_03_062_16100_5521 | C79: =VLOOKUP(B79,Tables!$G$2:$H$90,2,FALSE) -> Business Executive | D79: Smith Hall | E79: 302 | F79: AF SPC242DN | G79: =VLOOKUP(F79,Tables!$D$2:$E$20,2,FALSE) -> PTR | H79: 17099750 | I79: =SUM(S79-R79) -> 1050 | J79: =SUM(U79-T79) -> 1365 | K79: =SUM(I79*$P79) -> 27.51 | L79: =SUM(J79*$Q79) -> 161.07 | M79: =K79+L79 -> 188.58 | N79: T202P801022 | O79: 144.75.179.112 | P79: =IF(G79="MFP",Tables!$B$2,Tables!$B$5) -> 0.0262 | Q79: =IF(G79="MFP",Tables!$B$3,Tables!$B$6) -> 0.118 | R79: =VLOOKUP($N79,'Meter Comparison'!$C$2:$G$314,2,FALSE) -> 281 | S79: =VLOOKUP($N79,'Meter Comparison'!$C$2:$G$314,3,FALSE) -> 1331 | T79: =VLOOKUP($N79,'Meter Comparison'!$C$2:$G$314,4,FALSE) -> 549 | U79: =VLOOKUP($N79,'Meter Comparison'!$C$2:$G$314,5,FALSE) -> 1914
A80: Business Office | B80: 10_03_062_16100_5521 | C80: =VLOOKUP(B80,Tables!$G$2:$H$90,2,FALSE) -> Business Executive | D80: Smith Hall | E80: 303 | F80: AF SPC242DN | G80: =VLOOKUP(F80,Tables!$D$2:$E$20,2,FALSE) -> PTR | H80: 17099739 | I80: =SUM(S80-R80) -> 44 | J80: =SUM(U80-T80) -> 218 | K80: =SUM(I80*$P80) -> 1.1528 | L80: =SUM(J80*$Q80) -> 25.724 | M80: =K80+L80 -> 26.8768 | N80: T202P901338 | O80: 144.75.179.122 | P80: =IF(G80="MFP",Tables!$B$2,Tables!$B$5) -> 0.0262 | Q80: =IF(G80="MFP",Tables!$B$3,Tables!$B$6) -> 0.118 | R80: =VLOOKUP($N80,'Meter Comparison'!$C$2:$G$314,2,FALSE) -> 95 | S80: =VLOOKUP($N80,'Meter Comparison'!$C$2:$G$314,3,FALSE) -> 139 | T80: =VLOOKUP($N80,'Meter Comparison'!$C$2:$G$314,4,FALSE) -> 237 | U80: =VLOOKUP($N80,'Meter Comparison'!$C$2:$G$314,5,FALSE) -> 455
B81: 10_03_062_16100_5521 Total | M81: =SUBTOTAL(9,M78:M80) -> 230.7838
A82: Business Office | B82: 10_03_062_16150_5521 | C82: =VLOOKUP(B82,Tables!$G$2:$H$90,2,FALSE) -> Institute Planning | D82: Smith Hall | E82: 303 | F82: AF SP4310N | G82: =VLOOKUP(F82,Tables!$D$2:$E$20,2,FALSE) -> PTR | H82: 17099709 | I82: =SUM(S82-R82) -> 777 | J82: =SUM(U82-T82) -> 0 | K82: =SUM(I82*$P82) -> 20.3574 | L82: =SUM(J82*$Q82) -> 0 | M82: =K82+L82 -> 20.3574 | N82: T1128911215 | O82: 144.75.179.115 | P82: =IF(G82="MFP",Tables!$B$2,Tables!$B$5) -> 0.0262 | Q82: =IF(G82="MFP",Tables!$B$3,Tables!$B$6) -> 0.118 | R82: =VLOOKUP($N82,'Meter Comparison'!$C$2:$G$314,2,FALSE) -> 1591 | S82: =VLOOKUP($N82,'Meter Comparison'!$C$2:$G$314,3,FALSE) -> 2368 | T82: =VLOOKUP($N82,'Meter Comparison'!$C$2:$G$314,4,FALSE) -> 0 | U82: =VLOOKUP($N82,'Meter Comparison'!$C$2:$G$314,5,FALSE) -> 0
A83: Business Office | B83: 10_03_062_16150_5521 | C83: =VLOOKUP(B83,Tables!$G$2:$H$90,2,FALSE) -> Institute Planning | D83: Smith Hall | E83: 303 | F83: AF SPC242DN | G83: =VLOOKUP(F83,Tables!$D$2:$E$20,2,FALSE) -> PTR | H83: 17099513 | I83: =SUM(S83-R83) -> 0 | J83: =SUM(U83-T83) -> 0 | K83: =SUM(I83*$P83) -> 0 | L83: =SUM(J83*$Q83) -> 0 | M83: =K83+L83 -> 0 | N83: T202P700462 | O83: 144.75.179.112 | P83: =IF(G83="MFP",Tables!$B$2,Tables!$B$5) -> 0.0262 | Q83: =IF(G83="MFP",Tables!$B$3,Tables!$B$6) -> 0.118 | R83: =VLOOKUP($N83,'Meter Comparison'!$C$2:$G$314,2,FALSE) -> 0 | S83: =VLOOKUP($N83,'Meter Comparison'!$C$2:$G$314,3,FALSE) -> 0 | T83: =VLOOKUP($N83,'Meter Comparison'!$C$2:$G$314,4,FALSE) -> 0 | U83: =VLOOKUP($N83,'Meter Comparison'!$C$2:$G$314,5,FALSE) -> 0
A84: Business Office | B84: 10_03_062_16150_5521 | C84: =VLOOKUP(B84,Tables!$G$2:$H$90,2,FALSE) -> Institute Planning | D84: Smith Hall | E84: 304 | F84: AF MPC3502 | G84: =VLOOKUP(F84,Tables!$D$2:$E$20,2,FALSE) -> MFP | H84: 17099529 | I84: =SUM(S84-R84) -> 11100 | J84: =SUM(U84-T84) -> 7742 | K84: =SUM(I84*$P84) -> 229.77 | L84: =SUM(J84*$Q84) -> 673.554 | M84: =K84+L84 -> 903.324 | N84: W502L600725 | O84: 144.75.179.35 | P84: =IF(G84="MFP",Tables!$B$2,Tables!$B$5) -> 0.0207 | Q84: =IF(G84="MFP",Tables!$B$3,Tables!$B$6) -> 0.087 | R84: =VLOOKUP($N84,'Meter Comparison'!$C$2:$G$314,2,FALSE) -> 26054 | S84: =VLOOKUP($N84,'Meter Comparison'!$C$2:$G$314,3,FALSE) -> 37154 | T84: =VLOOKUP($N84,'Meter Comparison'!$C$2:$G$314,4,FALSE) -> 21767 | U84: =VLOOKUP($N84,'Meter Comparison'!$C$2:$G$314,5,FALSE) -> 29509
B85: 10_03_062_16150_5521 Total | M85: =SUBTOTAL(9,M82:M84) -> 923.6814
A86: Business Office | B86: 10_03_062_98100_5521 | C86: =VLOOKUP(B86,Tables!$G$2:$H$90,2,FALSE) -> Treasurers Office | D86: Smith Hall | E86: 303 | F86: AF SP4310N | G86: =VLOOKUP(F86,Tables!$D$2:$E$20,2,FALSE) -> PTR | H86: 17099711 | I86: =SUM(S86-R86) -> 2499 | J86: =SUM(U86-T86) -> 0 | K86: =SUM(I86*$P86) -> 65.4738 | L86: =SUM(J86*$Q86) -> 0 | M86: =K86+L86 -> 65.4738 | N86: T1128911216 | O86: 144.75.179.65 | P86: =IF(G86="MFP",Tables!$B$2,Tables!$B$5) -> 0.0262 | Q86: =IF(G86="MFP",Tables!$B$3,Tables!$B$6) -> 0.118 | R86: =VLOOKUP($N86,'Meter Comparison'!$C$2:$G$314,2,FALSE) -> 11038 | S86: =VLOOKUP($N86,'Meter Comparison'!$C$2:$G$314,3,FALSE) -> 13537 | T86: =VLOOKUP($N86,'Meter Comparison'!$C$2:$G$314,4,FALSE) -> 0 | U86: =VLOOKUP($N86,'Meter Comparison'!$C$2:$G$314,5,FALSE) -> 0
A87: Business Office | B87: 10_03_062_98100_5521 | C87: =VLOOKUP(B87,Tables!$G$2:$H$90,2,FALSE) -> Treasurers Office | D87: Smith Hall | E87: 305 | F87: AF SP4310N | G87: =VLOOKUP(F87,Tables!$D$2:$E$20,2,FALSE) -> PTR | H87: 17099710 | I87: =SUM(S87-R87) -> 1766 | J87: =SUM(U87-T87) -> 0 | K87: =SUM(I87*$P87) -> 46.2692 | L87: =SUM(J87*$Q87) -> 0 | M87: =K87+L87 -> 46.2692 | N87: T1129012239 | O87: 144.75.179.114 | P87: =IF(G87="MFP",Tables!$B$2,Tables!$B$5) -> 0.0262 | Q87: =IF(G87="MFP",Tables!$B$3,Tables!$B$6) -> 0.118 | R87: =VLOOKUP($N87,'Meter Comparison'!$C$2:$G$314,2,FALSE) -> 4542 | S87: =VLOOKUP($N87,'Meter Comparison'!$C$2:$G$314,3,FALSE) -> 6308 | T87: =VLOOKUP($N87,'Meter Comparison'!$C$2:$G$314,4,FALSE) -> 0 | U87: =VLOOKUP($N87,'Meter Comparison'!$C$2:$G$314,5,FALSE) -> 0
B88: 10_03_062_98100_5521 Total | M88: =SUBTOTAL(9,M86:M87) -> 111.743
A89: Cadet Life | B89: 10_08_307_18380_5521 | C89: =VLOOKUP(B89,Tables!$G$2:$H$90,2,FALSE) -> Student Union | D89: Lejeune Hall | E89: 3115 | F89: AF MPC2051 | G89: =VLOOKUP(F89,Tables!$D$2:$E$20,2,FALSE) -> MFP | H89: 17099486 | I89: =SUM(S89-R89) -> 1084 | J89: =SUM(U89-T89) -> 35 | K89: =SUM(I89*$P89) -> 22.4388 | L89: =SUM(J89*$Q89) -> 3.045 | M89: =K89+L89 -> 25.4838 | N89: V9725401441 | O89: 144.75.149.13 | P89: =IF(G89="MFP",Tables!$B$2,Tables!$B$5) -> 0.0207 | Q89: =IF(G89="MFP",Tables!$B$3,Tables!$B$6) -> 0.087 | R89: =VLOOKUP($N89,'Meter Comparison'!$C$2:$G$314,2,FALSE) -> 20927 | S89: =VLOOKUP($N89,'Meter Comparison'!$C$2:$G$314,3,FALSE) -> 22011 | T89: =VLOOKUP($N89,'Meter Comparison'!$C$2:$G$314,4,FALSE) -> 809 | U89: =VLOOKUP($N89,'Meter Comparison'!$C$2:$G$314,5,FALSE) -> 844
A90: Cadet Life | B90: 10_08_307_18380_5521 | C90: =VLOOKUP(B90,Tables!$G$2:$H$90,2,FALSE) -> Student Union | D90: Lejeune Hall | E90: 3116 | F90: AF SP4310N | G90: =VLOOKUP(F90,Tables!$D$2:$E$20,2,FALSE) -> PTR | H90: 17099717 | I90: =SUM(S90-R90) -> 312 | J90: =SUM(U90-T90) -> 0 | K90: =SUM(I90*$P90) -> 8.1744 | L90: =SUM(J90*$Q90) -> 0 | M90: =K90+L90 -> 8.1744 | N90: T1129010915 | O90: 144.75.149.11 | P90: =IF(G90="MFP",Tables!$B$2,Tables!$B$5) -> 0.0262 | Q90: =IF(G90="MFP",Tables!$B$3,Tables!$B$6) -> 0.118 | R90: =VLOOKUP($N90,'Meter Comparison'!$C$2:$G$314,2,FALSE) -> 778 | S90: =VLOOKUP($N90,'Meter Comparison'!$C$2:$G$314,3,FALSE) -> 1090 | T90: =VLOOKUP($N90,'Meter Comparison'!$C$2:$G$314,4,FALSE) -> 0 | U90: =VLOOKUP($N90,'Meter Comparison'!$C$2:$G$314,5,FALSE) -> 0
B91: 10_08_307_18380_5521 Total | M91: =SUBTOTAL(9,M89:M90) -> 33.6582
A92: Career Services / Financial Aid | B92: 10_03_053_20300_5521 | C92: =VLOOKUP(B92,Tables!$G$2:$H$90,2,FALSE) -> Career Services and Placement | D92: Carroll Hall | E92: 311 | F92: AF SP4310N | G92: =VLOOKUP(F92,Tables!$D$2:$E$20,2,FALSE) -> PTR | H92: 17099570 | I92: =SUM(S92-R92) -> 441 | J92: =SUM(U92-T92) -> 0 | K92: =SUM(I92*$P92) -> 11.5542 | L92: =SUM(J92*$Q92) -> 0 | M92: =K92+L92 -> 11.5542 | N92: T1128910754 | O92: 144.75.195.25 | P92: =IF(G92="MFP",Tables!$B$2,Tables!$B$5) -> 0.0262 | Q92: =IF(G92="MFP",Tables!$B$3,Tables!$B$6) -> 0.118 | R92: =VLOOKUP($N92,'Meter Comparison'!$C$2:$G$314,2,FALSE) -> 2373 | S92: =VLOOKUP($N92,'Meter Comparison'!$C$2:$G$314,3,FALSE) -> 2814 | T92: =VLOOKUP($N92,'Meter Comparison'!$C$2:$G$314,4,FALSE) -> 0 | U92: =VLOOKUP($N92,'Meter Comparison'!$C$2:$G$314,5,FALSE) -> 0
A93: Career Services / Financial Aid | B93: 10_03_053_20300_5521 | C93: =VLOOKUP(B93,Tables!$G$2:$H$90,2,FALSE) -> Career Services and Placement | D93: Carroll Hall | E93: 312 | F93: AF SP4310N | G93: =VLOOKUP(F93,Tables!$D$2:$E$20,2,FALSE) -> PTR | H93: 17099618 | I93: =SUM(S93-R93) -> 1563 | J93: =SUM(U93-T93) -> 0 | K93: =SUM(I93*$P93) -> 40.9506 | L93: =SUM(J93*$Q93) -> 0 | M93: =K93+L93 -> 40.9506 | N93: T1128911369 | O93: 144.75.195.109 | P93: =IF(G93="MFP",Tables!$B$2,Tables!$B$5) -> 0.0262 | Q93: =IF(G93="MFP",Tables!$B$3,Tables!$B$6) -> 0.118 | R93: =VLOOKUP($N93,'Meter Comparison'!$C$2:$G$314,2,FALSE) -> 7918 | S93: =VLOOKUP($N93,'Meter Comparison'!$C$2:$G$314,3,FALSE) -> 9481 | T93: =VLOOKUP($N93,'Meter Comparison'!$C$2:$G$314,4,FALSE) -> 0 | U93: =VLOOKUP($N93,'Meter Comparison'!$C$2:$G$314,5,FALSE) -> 0
A94: Career Services / Financial Aid | B94: 10_03_053_20300_5521 | C94: =VLOOKUP(B94,Tables!$G$2:$H$90,2,FALSE) -> Career Services and Placement | D94: Carroll Hall | E94: 313 | F94: AF SP4310N | G94: =VLOOKUP(F94,Tables!$D$2:$E$20,2,FALSE) -> PTR | H94: 17099617 | I94: =SUM(S94-R94) -> 420 | J94: =SUM(U94-T94) -> 0 | K94: =SUM(I94*$P94) -> 11.004 | L94: =SUM(J94*$Q94) -> 0 | M94: =K94+L94 -> 11.004 | N94: T1128911361 | O94: 144.75.195.81 | P94: =IF(G94="MFP",Tables!$B$2,Tables!$B$5) -> 0.0262 | Q94: =IF(G94="MFP",Tables!$B$3,Tables!$B$6) -> 0.118 | R94: =VLOOKUP($N94,'Meter Comparison'!$C$2:$G$314,2,FALSE) -> 806 | S94: =VLOOKUP($N94,'Meter Comparison'!$C$2:$G$314,3,FALSE) -> 1226 | T94: =VLOOKUP($N94,'Meter Comparison'!$C$2:$G$314,4,FALSE) -> 0 | U94: =VLOOKUP($N94,'Meter Comparison'!$C$2:$G$314,5,FALSE) -> 0
B95: 10_03_053_20300_5521 Total | M95: =SUBTOTAL(9,M92:M94) -> 63.5088
A96: Career Services / Financial Aid | B96: 10_03_064_32145_5521 | C96: =VLOOKUP(B96,Tables!$G$2:$H$90,2,FALSE) -> Duplicating | D96: Carroll Hall | E96: 307 | F96: AF MPC6501 | G96: =VLOOKUP(F96,Tables!$D$2:$E$20,2,FALSE) -> MFP | H96: 17099420 | I96: =SUM(S96-R96) -> 20678 | J96: =SUM(U96-T96) -> 877 | K96: =SUM(I96*$P96) -> 428.0346 | L96: =SUM(J96*$Q96) -> 76.299 | M96: =K96+L96 -> 504.3336 | N96: V7620400172 | O96: 144.75.195.225 | P96: =IF(G96="MFP",Tables!$B$2,Tables!$B$5) -> 0.0207 | Q96: =IF(G96="MFP",Tables!$B$3,Tables!$B$6) -> 0.087 | R96: =VLOOKUP($N96,'Meter Comparison'!$C$2:$G$314,2,FALSE) -> 191062 | S96: =VLOOKUP($N96,'Meter Comparison'!$C$2:$G$314,3,FALSE) -> 211740 | T96: =VLOOKUP($N96,'Meter Comparison'!$C$2:$G$314,4,FALSE) -> 14613 | U96: =VLOOKUP($N96,'Meter Comparison'!$C$2:$G$314,5,FALSE) -> 15490
B97: 10_03_064_32145_5521 Total | M97: =SUBTOTAL(9,M96:M96) -> 504.3336
A98: Center for Leadership & Ethics | B98: 30_00_045_61150_5521 | C98: =VLOOKUP(B98,Tables!$G$2:$H$90,2,FALSE) -> Center for Leadership & Ethics | D98: Center for Leadership & Ethics | E98: 102 | F98: AF SPC242DN | G98: =VLOOKUP(F98,Tables!$D$2:$E$20,2,FALSE) -> PTR | H98: 17099779 | I98: =SUM(S98-R98) -> 0 | J98: =SUM(U98-T98) -> 0 | K98: =SUM(I98*$P98) -> 0 | L98: =SUM(J98*$Q98) -> 0 | M98: =K98+L98 -> 0 | N98: T202P600366 | O98: 144.75.215.67 | P98: =IF(G98="MFP",Tables!$B$2,Tables!$B$5) -> 0.0262 | Q98: =IF(G98="MFP",Tables!$B$3,Tables!$B$6) -> 0.118 | R98: =VLOOKUP($N98,'Meter Comparison'!$C$2:$G$314,2,FALSE) -> 30 | S98: =VLOOKUP($N98,'Meter Comparison'!$C$2:$G$314,3,FALSE) -> 30 | T98: =VLOOKUP($N98,'Meter Comparison'!$C$2:$G$314,4,FALSE) -> 8 | U98: =VLOOKUP($N98,'Meter Comparison'!$C$2:$G$314,5,FALSE) -> 8
A99: Center for Leadership & Ethics | B99: 30_00_045_61150_5521 | C99: =VLOOKUP(B99,Tables!$G$2:$H$90,2,FALSE) -> Center for Leadership & Ethics | D99: Center for Leadership & Ethics | E99: 201 | F99: AF SP4310N | G99: =VLOOKUP(F99,Tables!$D$2:$E$20,2,FALSE) -> PTR | H99: 17099694 | I99: =SUM(S99-R99) -> 110 | J99: =SUM(U99-T99) -> 0 | K99: =SUM(I99*$P99) -> 2.882 | L99: =SUM(J99*$Q99) -> 0 | M99: =K99+L99 -> 2.882 | N99: T1129011351 | O99: 144.75.215.30 | P99: =IF(G99="MFP",Tables!$B$2,Tables!$B$5) -> 0.0262 | Q99: =IF(G99="MFP",Tables!$B$3,Tables!$B$6) -> 0.118 | R99: =VLOOKUP($N99,'Meter Comparison'!$C$2:$G$314,2,FALSE) -> 252 | S99: =VLOOKUP($N99,'Meter Comparison'!$C$2:$G$314,3,FALSE) -> 362 | T99: =VLOOKUP($N99,'Meter Comparison'!$C$2:$G$314,4,FALSE) -> 0 | U99: =VLOOKUP($N99,'Meter Comparison'!$C$2:$G$314,5,FALSE) -> 0
A100: Center for Leadership & Ethics | B100: 30_00_045_61150_5521 | C100: =VLOOKUP(B100,Tables!$G$2:$H$90,2,FALSE) -> Center for Leadership & Ethics | D100: Center for Leadership & Ethics | E100: 201 | F100: AF SP4310N | G100: =VLOOKUP(F100,Tables!$D$2:$E$20,2,FALSE) -> PTR | H100: 17099602 | I100: =SUM(S100-R100) -> 908 | J100: =SUM(U100-T100) -> 0 | K100: =SUM(I100*$P100) -> 23.7896 | L100: =SUM(J100*$Q100) -> 0 | M100: =K100+L100 -> 23.7896 | N100: T1129012327 | O100: 144.75.215.10 | P100: =IF(G100="MFP",Tables!$B$2,Tables!$B$5) -> 0.0262 | Q100: =IF(G100="MFP",Tables!$B$3,Tables!$B$6) -> 0.118 | R100: =VLOOKUP($N100,'Meter Comparison'!$C$2:$G$314,2,FALSE) -> 5142 | S100: =VLOOKUP($N100,'Meter Comparison'!$C$2:$G$314,3,FALSE) -> 6050 | T100: =VLOOKUP($N100,'Meter Comparison'!$C$2:$G$314,4,FALSE) -> 0 | U100: =VLOOKUP($N100,'Meter Comparison'!$C$2:$G$314,5,FALSE) -> 0
A101: Center for Leadership & Ethics | B101: 30_00_045_61150_5521 | C101: =VLOOKUP(B101,Tables!$G$2:$H$90,2,FALSE) -> Center for Leadership & Ethics | D101: Center for Leadership & Ethics | E101: 201 | F101: AF MPC2051 | G101: =VLOOKUP(F101,Tables!$D$2:$E$20,2,FALSE) -> MFP | H101: 17099534 | I101: =SUM(S101-R101) -> 5902 | J101: =SUM(U101-T101) -> 2572 | K101: =SUM(I101*$P101) -> 122.1714 | L101: =SUM(J101*$Q101) -> 223.764 | M101: =K101+L101 -> 345.9354 | N101: V9725400756 | O101: 144.75.215.6 | P101: =IF(G101="MFP",Tables!$B$2,Tables!$B$5) -> 0.0207 | Q101: =IF(G101="MFP",Tables!$B$3,Tables!$B$6) -> 0.087 | R101: =VLOOKUP($N101,'Meter Comparison'!$C$2:$G$314,2,FALSE) -> 16774 | S101: =VLOOKUP($N101,'Meter Comparison'!$C$2:$G$314,3,FALSE) -> 22676 | T101: =VLOOKUP($N101,'Meter Comparison'!$C$2:$G$314,4,FALSE) -> 9576 | U101: =VLOOKUP($N101,'Meter Comparison'!$C$2:$G$314,5,FALSE) -> 12148
B102: 30_00_045_61150_5521 Total | M102: =SUBTOTAL(9,M98:M101) -> 372.607
A103: Chaplains Office | B103: 10_07_205_24100_5521 | C103: =VLOOKUP(B103,Tables!$G$2:$H$90,2,FALSE) -> UMA-Counselors Office | D103: Old Hospital | E103: 202 | F103: AF MP301SP | G103: =VLOOKUP(F103,Tables!$D$2:$E$20,2,FALSE) -> MFP | H103: 17099532 | I103: =SUM(S103-R103) -> 1002 | J103: =SUM(U103-T103) -> 0 | K103: =SUM(I103*$P103) -> 20.7414 | L103: =SUM(J103*$Q103) -> 0 | M103: =K103+L103 -> 20.7414 | N103: W912P601485 | O103: 144.75.180.73 | P103: =IF(G103="MFP",Tables!$B$2,Tables!$B$5) -> 0.0207 | Q103: =IF(G103="MFP",Tables!$B$3,Tables!$B$6) -> 0.087 | R103: =VLOOKUP($N103,'Meter Comparison'!$C$2:$G$314,2,FALSE) -> 6561 | S103: =VLOOKUP($N103,'Meter Comparison'!$C$2:$G$314,3,FALSE) -> 7563 | T103: =VLOOKUP($N103,'Meter Comparison'!$C$2:$G$314,4,FALSE) -> 0 | U103: =VLOOKUP($N103,'Meter Comparison'!$C$2:$G$314,5,FALSE) -> 0
B104: 10_07_205_24100_5521 Total | M104: =SUBTOTAL(9,M103:M103) -> 20.7414
A105: Chemistry | B105: 10_03_011_26100_5521 | C105: =VLOOKUP(B105,Tables!$G$2:$H$90,2,FALSE) -> Chemistry | D105: Maury Brooke | E105: 105 | F105: AF SP4310N | G105: =VLOOKUP(F105,Tables!$D$2:$E$20,2,FALSE) -> PTR | H105: 17099816 | I105: =SUM(S105-R105) -> 84 | J105: =SUM(U105-T105) -> 0 | K105: =SUM(I105*$P105) -> 2.2008 | L105: =SUM(J105*$Q105) -> 0 | M105: =K105+L105 -> 2.2008 | N105: T1129010633 | O105: Not Networked | P105: =IF(G105="MFP",Tables!$B$2,Tables!$B$5) -> 0.0262 | Q105: =IF(G105="MFP",Tables!$B$3,Tables!$B$6) -> 0.118 | R105: =VLOOKUP($N105,'Meter Comparison'!$C$2:$G$314,2,FALSE) -> 8 | S105: =VLOOKUP($N105,'Meter Comparison'!$C$2:$G$314,3,FALSE) -> 92 | T105: =VLOOKUP($N105,'Meter Comparison'!$C$2:$G$314,4,FALSE) -> 0 | U105: =VLOOKUP($N105,'Meter Comparison'!$C$2:$G$314,5,FALSE) -> 0
A106: Chemistry | B106: 10_03_011_26100_5521 | C106: =VLOOKUP(B106,Tables!$G$2:$H$90,2,FALSE) -> Chemistry | D106: Maury Brooke | E106: 303 | F106: AF SP4310N | G106: =VLOOKUP(F106,Tables!$D$2:$E$20,2,FALSE) -> PTR | H106: 17099615 | I106: =SUM(S106-R106) -> 441 | J106: =SUM(U106-T106) -> 0 | K106: =SUM(I106*$P106) -> 11.5542 | L106: =SUM(J106*$Q106) -> 0 | M106: =K106+L106 -> 11.5542 | N106: T1129011366 | O106: 144.75.202.14 | P106: =IF(G106="MFP",Tables!$B$2,Tables!$B$5) -> 0.0262 | Q106: =IF(G106="MFP",Tables!$B$3,Tables!$B$6) -> 0.118 | R106: =VLOOKUP($N106,'Meter Comparison'!$C$2:$G$314,2,FALSE) -> 9288 | S106: =VLOOKUP($N106,'Meter Comparison'!$C$2:$G$314,3,FALSE) -> 9729 | T106: =VLOOKUP($N106,'Meter Comparison'!$C$2:$G$314,4,FALSE) -> 0 | U106: =VLOOKUP($N106,'Meter Comparison'!$C$2:$G$314,5,FALSE) -> 0
A107: Chemistry | B107: 10_03_011_26100_5521 | C107: =VLOOKUP(B107,Tables!$G$2:$H$90,2,FALSE) -> Chemistry | D107: Maury Brooke | E107: 402 | F107: AF SP4310N | G107: =VLOOKUP(F107,Tables!$D$2:$E$20,2,FALSE) -> PTR | H107: 17099823 | I107: =SUM(S107-R107) -> 0 | J107: =SUM(U107-T107) -> 0 | K107: =SUM(I107*$P107) -> 0 | L107: =SUM(J107*$Q107) -> 0 | M107: =K107+L107 -> 0 | N107: T1128911469 | O107: 144.75.202.89 | P107: =IF(G107="MFP",Tables!$B$2,Tables!$B$5) -> 0.0262 | Q107: =IF(G107="MFP",Tables!$B$3,Tables!$B$6) -> 0.118 | R107: =VLOOKUP($N107,'Meter Comparison'!$C$2:$G$314,2,FALSE) -> 8 | S107: =VLOOKUP($N107,'Meter Comparison'!$C$2:$G$314,3,FALSE) -> 8 | T107: =VLOOKUP($N107,'Meter Comparison'!$C$2:$G$314,4,FALSE) -> 0 | U107: =VLOOKUP($N107,'Meter Comparison'!$C$2:$G$314,5,FALSE) -> 0
A108: Chemistry | B108: 10_03_011_26100_5521 | C108: =VLOOKUP(B108,Tables!$G$2:$H$90,2,FALSE) -> Chemistry | D108: Maury Brooke | E108: 411 | F108: AF SP4310N | G108: =VLOOKUP(F108,Tables!$D$2:$E$20,2,FALSE) -> PTR | H108: 17099822 | I108: =SUM(S108-R108) -> 229 | J108: =SUM(U108-T108) -> 0 | K108: =SUM(I108*$P108) -> 5.9998 | L108: =SUM(J108*$Q108) -> 0 | M108: =K108+L108 -> 5.9998 | N108: T1129010904 | O108: 144.75.202.76 | P108: =IF(G108="MFP",Tables!$B$2,Tables!$B$5) -> 0.0262 | Q108: =IF(G108="MFP",Tables!$B$3,Tables!$B$6) -> 0.118 | R108: =VLOOKUP($N108,'Meter Comparison'!$C$2:$G$314,2,FALSE) -> 182 | S108: =VLOOKUP($N108,'Meter Comparison'!$C$2:$G$314,3,FALSE) -> 411 | T108: =VLOOKUP($N108,'Meter Comparison'!$C$2:$G$314,4,FALSE) -> 0 | U108: =VLOOKUP($N108,'Meter Comparison'!$C$2:$G$314,5,FALSE) -> 0
A109: Chemistry | B109: 10_03_011_26100_5521 | C109: =VLOOKUP(B109,Tables!$G$2:$H$90,2,FALSE) -> Chemistry | D109: Maury Brooke | E109: 415 | F109: AF SP4310N | G109: =VLOOKUP(F109,Tables!$D$2:$E$20,2,FALSE) -> PTR | H109: 17099812 | I109: =SUM(S109-R109) -> 108 | J109: =SUM(U109-T109) -> 0 | K109: =SUM(I109*$P109) -> 2.8296 | L109: =SUM(J109*$Q109) -> 0 | M109: =K109+L109 -> 2.8296 | N109: T1129010621 | O109: Not Networked | P109: =IF(G109="MFP",Tables!$B$2,Tables!$B$5) -> 0.0262 | Q109: =IF(G109="MFP",Tables!$B$3,Tables!$B$6) -> 0.118 | R109: =VLOOKUP($N109,'Meter Comparison'!$C$2:$G$314,2,FALSE) -> 548 | S109: =VLOOKUP($N109,'Meter Comparison'!$C$2:$G$314,3,FALSE) -> 656 | T109: =VLOOKUP($N109,'Meter Comparison'!$C$2:$G$314,4,FALSE) -> 0 | U109: =VLOOKUP($N109,'Meter Comparison'!$C$2:$G$314,5,FALSE) -> 0
...

Sheet Sheet2
A1: Department / Read date 3/31/2013 | B1: General Ledger | C1: GL Description | D1: Building | E1: Room | F1: Model | G1: Device Type | H1: Ricoh Tag | I1: Total BW Click Count | J1: Total Color Click Count | K1: BW Click Charge | L1: Color Click Charge | M1: Device Total Click Charge | N1: Serial Number | O1: IP Address | P1: CPC BW | Q1: CPC Color | R1: Prev BW Click Count | S1: Current BW Click Count | T1: Prev Color Click Count | U1: Current Color Click Count
A2: Academic Advising | B2: 10_07_205_90300_5521 | C2: Academic Advising | D2: Shell Hall | E2: 301 | F2: AF SPC242DN | G2: PTR | H2: 17099684 | I2: 341 | J2: 165 | K2: 8.9342 | L2: 19.47 | M2: 28.4042 | N2: T202P700442 | O2: 144.75.180.103 | P2: 0.0262 | Q2: 0.118 | R2: 2188 | S2: 2529 | T2: 669 | U2: 834
A3: Athletics | B3: 30_00_310_06110_5521 | C3: Administrative | D3: Cameron Hall | E3: 204 | F3: AF MP301SP | G3: MFP | H3: 17099507 | I3: 1486 | J3: 0 | K3: 30.7602 | L3: 0 | M3: 30.7602 | N3: W912P602280 | O3: 144.75.183.73 | P3: 0.0207 | Q3: 0.087 | R3: 12247 | S3: 13733 | T3: 0 | U3: 0
A4: Athletics | B4: 30_00_310_06110_5521 | C4: Administrative | D4: Cameron Hall | E4: 235 | F4: AF MPC6501 | G4: MFP | H4: 17099490 | I4: 9308 | J4: 3008 | K4: 192.6756 | L4: 261.696 | M4: 454.3716 | N4: V7620400078 | O4: 144.75.183.56 | P4: 0.0207 | Q4: 0.087 | R4: 35267 | S4: 44575 | T4: 13165 | U4: 16173
A5: Athletics | B5: 30_00_310_06110_5521 | C5: Administrative | D5: Cameron Hall | E5: 241 | F5: AF SP4310N | G5: PTR | H5: 17099552 | I5: 644 | J5: 0 | K5: 16.8728 | L5: 0 | M5: 16.8728 | N5: T1129010427 | O5: 144.75.183.9 | P5: 0.0262 | Q5: 0.118 | R5: 3916 | S5: 4560 | T5: 0 | U5: 0
A6: Athletics | B6: 30_00_310_06110_5521 | C6: Administrative | D6: Cameron Hall | E6: 242 | F6: AF SP4310N | G6: PTR | H6: 17099553 | I6: 222 | J6: 0 | K6: 5.8164 | L6: 0 | M6: 5.8164 | N6: T1129010420 | O6: 144.75.183.64 | P6: 0.0262 | Q6: 0.118 | R6: 1110 | S6: 1332 | T6: 0 | U6: 0
A7: Athletics | B7: 30_00_310_06110_5521 | C7: Administrative | D7: Cameron Hall | E7: 302 | F7: AF MPC2051 | G7: MFP | H7: 17099722 | I7: 810 | J7: 1418 | K7: 16.767 | L7: 123.366 | M7: 140.133 | N7: V9725401418 | O7: 144.75.183.52 | P7: 0.0207 | Q7: 0.087 | R7: 6179 | S7: 6989 | T7: 13950 | U7: 15368
A8: Athletics | B8: 30_00_310_06110_5521 | C8: Administrative | D8: Cameron Hall | E8: 312 | F8: AF SP4310N | G8: PTR | H8: 17099555 | I8: 287 | J8: 0 | K8: 7.5194 | L8: 0 | M8: 7.5194 | N8: T1129010428 | O8: 144.75.183.67 | P8: 0.0262 | Q8: 0.118 | R8: 1574 | S8: 1861 | T8: 0 | U8: 0
A9: Athletics | B9: 30_00_310_06110_5521 | C9: Administrative | D9: Cameron Hall | E9: 314 | F9: AF SP4310N | G9: PTR | H9: 17099558 | I9: 175 | J9: 0 | K9: 4.585 | L9: 0 | M9: 4.585 | N9: T1129010421 | O9: 144.75.183.62 | P9: 0.0262 | Q9: 0.118 | R9: 1925 | S9: 2100 | T9: 0 | U9: 0
A10: Athletics | B10: 30_00_310_06110_5521 | C10: Administrative | D10: Cameron Hall | E10: 317 | F10: AF SP4310N | G10: PTR | H10: 17099554 | I10: 62 | J10: 0 | K10: 1.6244 | L10: 0 | M10: 1.6244 | N10: T1129010385 | O10: 144.75.183.63 | P10: 0.0262 | Q10: 0.118 | R10: 632 | S10: 694 | T10: 0 | U10: 0
A11: Commandant's Office | B11: 30_00_310_06110_5521 | C11: Administrative | D11: Kilbourne Hall | E11: Rifle Range | F11: AF SP4310N | G11: PTR | H11: 17099797 | I11: 0 | J11: 0 | K11: 0 | L11: 0 | M11: 0 | N11: T1129010627 | O11: 144.75.187.120 | P11: 0.0262 | Q11: 0.118 | R11: 204 | S11: 204 | T11: 0 | U11: 0
A12: Commandant's Office | B12: 30_00_310_06110_5521 | C12: Administrative | D12: Old Barracks | E12: 3C-14 | F12: AF SP4310N | G12: PTR | H12: 17099762 | I12: 189 | J12: 0 | K12: 4.9518 | L12: 0 | M12: 4.9518 | N12: T1129010629 | O12: 144.75.155.56 | P12: 0.0262 | Q12: 0.118 | R12: 545 | S12: 734 | T12: 0 | U12: 0
A13: Sport Medicine | B13: 30_00_310_06110_5521 | C13: Administrative | D13: Cameron Hall | E13: 215 | F13: AF SP4310N | G13: PTR | H13: 17099566 | I13: 180 | J13: 0 | K13: 4.716 | L13: 0 | M13: 4.716 | N13: T1129010423 | O13: 144.75.183.71 | P13: 0.0262 | Q13: 0.118 | R13: 1047 | S13: 1227 | T13: 0 | U13: 0
A14: Addmissions | B14: 10_03_054_01100_5521 | C14: Admissions Office | D14: Moody Hall | E14: 104 | F14: AF SP4310N | G14: PTR | H14: 17099824 | I14: 101 | J14: 0 | K14: 2.6462 | L14: 0 | M14: 2.6462 | N14: T1129010634 | O14: 144.75.184.23 | P14: 0.0262 | Q14: 0.118 | R14: 404 | S14: 505 | T14: 0 | U14: 0
A15: Admissions | B15: 10_03_054_01100_5521 | C15: Admissions Office | D15: 307 Letcher | E15: 204 | F15: AF MPC3502 | G15: MFP | H15: 17099493 | I15: 6744 | J15: 5255 | K15: 139.6008 | L15: 457.185 | M15: 596.7858 | N15: W502L600872 | O15: 144.75.215.48 | P15: 0.0207 | Q15: 0.087 | R15: 34748 | S15: 41492 | T15: 16784 | U15: 22039
A16: Admissions | B16: 10_03_054_01100_5521 | C16: Admissions Office | D16: 309 Letcher | E16: 200 | F16: AF SPC430DN | G16: PTR | H16: 17099785 | I16: 519 | J16: 1151 | K16: 13.5978 | L16: 135.818 | M16: 149.4158 | N16: S9329101091 | O16: 144.75.186.31 | P16: 0.0262 | Q16: 0.118 | R16: 993 | S16: 1512 | T16: 2000 | U16: 3151
A17: Admissions | B17: 10_03_054_01100_5521 | C17: Admissions Office | D17: 309 Letcher | E17: 201 | F17: AF SP4310N | G17: PTR | H17: 17099780 | I17: 269 | J17: 0 | K17: 7.0478 | L17: 0 | M17: 7.0478 | N17: T1128911219 | O17: 144.75.215.43 | P17: 0.0262 | Q17: 0.118 | R17: 679 | S17: 948 | T17: 0 | U17: 0
A18: Admissions | B18: 10_03_054_01100_5521 | C18: Admissions Office | D18: 309 Letcher | E18: 201 | F18: AF SP4310N | G18: PTR | H18: 17099512 | I18: 0 | J18: 0 | K18: 0 | L18: 0 | M18: 0 | N18: T1129010877 | O18: 144.75.186.30 | P18: 0.0262 | Q18: 0.118 | R18: 50 | S18: 50 | T18: 0 | U18: 0
A19: Admissions | B19: 10_03_054_01100_5521 | C19: Admissions Office | D19: 309 Letcher | E19: 302 | F19: AF SPC242DN | G19: PTR | H19: 17099423 | I19: 59 | J19: 216 | K19: 1.5458 | L19: 25.488 | M19: 27.0338 | N19: T202P700463 | O19: 144.75.186.29 | P19: 0.0262 | Q19: 0.118 | R19: 196 | S19: 255 | T19: 550 | U19: 766
A20: Admissions | B20: 10_03_054_01100_5521 | C20: Admissions Office | D20: 309 Letcher | E20: 306 | F20: AF SPC242DN | G20: PTR | H20: 17099731 | I20: 230 | J20: 54 | K20: 6.026 | L20: 6.372 | M20: 12.398 | N20: T202P600637 | O20: 144.75.186.28 | P20: 0.0262 | Q20: 0.118 | R20: 1500 | S20: 1730 | T20: 618 | U20: 672
A21: Admissions | B21: 10_03_054_01100_5521 | C21: Admissions Office | D21: 309 Letcher | E21: 306 | F21: AF SPC242DN | G21: PTR | H21: 17099511 | I21: 36 | J21: 85 | K21: 0.9432 | L21: 10.03 | M21: 10.9732 | N21: T202P700465 | O21: 144.75.186.25 | P21: 0.0262 | Q21: 0.118 | R21: 409 | S21: 445 | T21: 472 | U21: 557
A22: Athletic Advising | B22: 40_00_052_06550_5521 | C22: AOF - Academic Advising | D22: Carroll Hall | E22: 210 | F22: AF MPC2051 | G22: MFP | H22: 17099459 | I22: 8103 | J22: 326 | K22: 167.7321 | L22: 28.362 | M22: 196.0941 | N22: V9725401429 | O22: 144.75.195.41 | P22: 0.0207 | Q22: 0.087 | R22: 33629 | S22: 41732 | T22: 3170 | U22: 3496
A23: Auxiliary Services | B23: 10_08_309_82115_5521 | C23: Auxiliary Administration | D23: Cocke Hall | E23: 502 | F23: AF MPC2051 | G23: MFP | H23: 17099424 | I23: 968 | J23: 196 | K23: 20.0376 | L23: 17.052 | M23: 37.0896 | N23: V9725500651 | O23: 144.75.177.32 | P23: 0.0207 | Q23: 0.087 | R23: 5760 | S23: 6728 | T23: 625 | U23: 821
A24: Laundry | B24: 10_08_303_82240_5521 | C24: AUX-Laundry & Pressing | D24: Richardson Hall | E24: 201 | F24: AF SPC242DN | G24: PTR | H24: 17099622 | I24: 39 | J24: 37 | K24: 1.0218 | L24: 4.366 | M24: 5.3878 | N24: T202P700340 | O24: 144.75.195.95 | P24: 0.0262 | Q24: 0.118 | R24: 51 | S24: 90 | T24: 38 | U24: 75
A25: Laundry | B25: 10_08_303_82240_5521 | C25: AUX-Laundry & Pressing | D25: Richardson Hall | E25: 201 | F25: AF MP301SP | G25: MFP | H25: 17099401 | I25: 1046 | J25: 0 | K25: 21.6522 | L25: 0 | M25: 21.6522 | N25: W912P602288 | O25: 144.75.195.6 | P25: 0.0207 | Q25: 0.087 | R25: 6131 | S25: 7177 | T25: 0 | U25: 0
A26: Military Store | B26: 10_08_302_82190_5521 | C26: AUX-Military Store | D26: Kilbourne Hall | E26: QMD | F26: AF MPC2051 | G26: MFP | H26: 17099416 | I26: 1277 | J26: 6 | K26: 26.4339 | L26: 0.522 | M26: 26.9559 | N26: V9734900029 | O26: 144.75.187.37 | P26: 0.0207 | Q26: 0.087 | R26: 463 | S26: 1740 | T26: 27 | U26: 33
A27: Military Store | B27: 10_08_302_82190_5521 | C27: AUX-Military Store | D27: Richardson Hall | E27: 401 | F27: AF SP4310N | G27: PTR | H27: 17099589 | I27: 149 | J27: 0 | K27: 3.9038 | L27: 0 | M27: 3.9038 | N27: T1129012233 | O27: 144.75.180.101 | P27: 0.0262 | Q27: 0.118 | R27: 314 | S27: 463 | T27: 0 | U27: 0
A28: Military Store | B28: 10_08_302_82190_5521 | C28: AUX-Military Store | D28: Richardson Hall | E28: 401 | F28: AF SPC242DN | G28: PTR | H28: 17099724 | I28: 284 | J28: 87 | K28: 7.4408 | L28: 10.266 | M28: 17.7068 | N28: T202P801021 | O28: 144.75.180.11 | P28: 0.0262 | Q28: 0.118 | R28: 905 | S28: 1189 | T28: 229 | U28: 316
A29: Military Store | B29: 10_08_302_82190_5521 | C29: AUX-Military Store | D29: Richardson Hall | E29: 401 | F29: AF MPC2051 | G29: MFP | H29: 17099491 | I29: 1198 | J29: 1172 | K29: 24.7986 | L29: 101.964 | M29: 126.7626 | N29: V9725700303 | O29: 144.75.180.200 | P29: 0.0207 | Q29: 0.087 | R29: 5718 | S29: 6916 | T29: 2571 | U29: 3743
A30: Infirmary | B30: 10_08_305_80150_5521 | C30: AUX-Student Health | D30: Infirmary | E30: 113 | F30: AF SP4310N | G30: PTR | H30: 17099605 | I30: 2113 | J30: 0 | K30: 55.3606 | L30: 0 | M30: 55.3606 | N30: T1129010432 | O30: 144.75.176.29 | P30: 0.0262 | Q30: 0.118 | R30: 9160 | S30: 11273 | T30: 0 | U30: 0
A31: Infirmary | B31: 10_08_305_80150_5521 | C31: AUX-Student Health | D31: Infirmary | E31: 121 | F31: AF MPC2051 | G31: MFP | H31: 17099496 | I31: 1988 | J31: 715 | K31: 41.1516 | L31: 62.205 | M31: 103.3566 | N31: V9725401162 | O31: 144.75.176.21 | P31: 0.0207 | Q31: 0.087 | R31: 13826 | S31: 15814 | T31: 1144 | U31: 1859
A32: Infirmary | B32: 10_08_305_80150_5521 | C32: AUX-Student Health | D32: Infirmary | E32: 219 | F32: AF SP4310N | G32: PTR | H32: 17099635 | I32: 1130 | J32: 0 | K32: 29.606 | L32: 0 | M32: 29.606 | N32: T1128710823 | O32: 144.75.176.20 | P32: 0.0262 | Q32: 0.118 | R32: 4720 | S32: 5850 | T32: 0 | U32: 0
A33: Infirmary | B33: 10_08_305_80150_5521 | C33: AUX-Student Health | D33: Infirmary | E33: 219 | F33: AF MPC2051 | G33: MFP | H33: 17099495 | I33: 644 | J33: 138 | K33: 13.3308 | L33: 12.006 | M33: 25.3368 | N33: V9725401375 | O33: 144.75.176.46 | P33: 0.0207 | Q33: 0.087 | R33: 3815 | S33: 4459 | T33: 130 | U33: 268
A34: Tailor Shop | B34: 10_08_302_82230_5521 | C34: AUX-Tailor Shop | D34: Kilbourne Hall | E34: Tailor Shop | F34: AF SP4310N | G34: PTR | H34: 17099415 | I34: 0 | J34: 0 | K34: 0 | L34: 0 | M34: 0 | N34: T1129010838 | O34: 144.75.187.152 | P34: 0.0262 | Q34: 0.118 | R34: 7 | S34: 7 | T34: 0 | U34: 0
A35: Tailor Shop | B35: 10_08_302_82230_5521 | C35: AUX-Tailor Shop | D35: Richardson Hall | E35: Tailor Shop | F35: AF SP4310N | G35: PTR | H35: 17099610 | I35: 857 | J35: 0 | K35: 22.4534 | L35: 0 | M35: 22.4534 | N35: T1129012234 | O35: 144.75.180.89 | P35: 0.0262 | Q35: 0.118 | R35: 2746 | S35: 3603 | T35: 0 | U35: 0
A36: Business Office | B36: 10_03_062_16100_5521 | C36: Business Executive | D36: Smith Hall | E36: 301 | F36: AF SP4310N | G36: PTR | H36: 17099696 | I36: 581 | J36: 0 | K36: 15.2222 | L36: 0 | M36: 15.2222 | N36: T1129012215 | O36: 144.75.179.113 | P36: 0.0262 | Q36: 0.118 | R36: 2108 | S36: 2689 | T36: 0 | U36: 0
A37: Business Office | B37: 10_03_062_16100_5521 | C37: Business Executive | D37: Smith Hall | E37: 303 | F37: AF SPC242DN | G37: PTR | H37: 17099739 | I37: 78 | J37: 130 | K37: 2.0436 | L37: 15.34 | M37: 17.3836 | N37: T202P901338 | O37: 144.75.179.122 | P37: 0.0262 | Q37: 0.118 | R37: 17 | S37: 95 | T37: 107 | U37: 237
A38: Physics & Astronomy | B38: 40_00_011_78500_5521 | C38: Cameron Physics & Astronomy | D38: Mallory Hall | E38: 123 | F38: AF SP4310N | G38: PTR | H38: 17099689 | I38: 25 | J38: 0 | K38: 0.655 | L38: 0 | M38: 0.655 | N38: T1129011274 | O38: 144.75.182.85 | P38: 0.0262 | Q38: 0.118 | R38: 443 | S38: 468 | T38: 0 | U38: 0
A39: Physics & Astronomy | B39: 40_00_011_78500_5521 | C39: Cameron Physics & Astronomy | D39: Mallory Hall | E39: 324 | F39: AF MPC3502 | G39: MFP | H39: 17099463 | I39: 5358 | J39: 1725 | K39: 110.9106 | L39: 150.075 | M39: 260.9856 | N39: W502L601236 | O39: 144.75.182.208 | P39: 0.0207 | Q39: 0.087 | R39: 38106 | S39: 43464 | T39: 4714 | U39: 6439
A40: Physics & Astronomy | B40: 40_00_011_78500_5521 | C40: Cameron Physics & Astronomy | D40: Mallory Hall | E40: 328 | F40: AF SP4310N | G40: PTR | H40: 17099588 | I40: 156 | J40: 0 | K40: 4.0872 | L40: 0 | M40: 4.0872 | N40: T1129011359 | O40: 144.75.182.15 | P40: 0.0262 | Q40: 0.118 | R40: 762 | S40: 918 | T40: 0 | U40: 0
A41: Career Services / Financial Aid | B41: 10_03_053_20300_5521 | C41: Career Services and Placement | D41: Carroll Hall | E41: 311 | F41: AF SP4310N | G41: PTR | H41: 17099570 | I41: 466 | J41: 0 | K41: 12.2092 | L41: 0 | M41: 12.2092 | N41: T1128910754 | O41: 144.75.195.25 | P41: 0.0262 | Q41: 0.118 | R41: 1907 | S41: 2373 | T41: 0 | U41: 0
A42: Career Services / Financial Aid | B42: 10_03_053_20300_5521 | C42: Career Services and Placement | D42: Carroll Hall | E42: 312 | F42: AF SP4310N | G42: PTR | H42: 17099618 | I42: 1142 | J42: 0 | K42: 29.9204 | L42: 0 | M42: 29.9204 | N42: T1128911369 | O42: 144.75.195.109 | P42: 0.0262 | Q42: 0.118 | R42: 6776 | S42: 7918 | T42: 0 | U42: 0
A43: Career Services / Financial Aid | B43: 10_03_053_20300_5521 | C43: Career Services and Placement | D43: Carroll Hall | E43: 313 | F43: AF SP4310N | G43: PTR | H43: 17099617 | I43: 103 | J43: 0 | K43: 2.6986 | L43: 0 | M43: 2.6986 | N43: T1128911361 | O43: 144.75.195.81 | P43: 0.0262 | Q43: 0.118 | R43: 703 | S43: 806 | T43: 0 | U43: 0
A44: Biology | B44: 40_00_011_10250_5521 | C44: Carroll Biology Fund | D44: Mallory Hall | E44: 207 | F44: AF SP4310N | G44: PTR | H44: 17099734 | I44: 68 | J44: 0 | K44: 1.7816 | L44: 0 | M44: 1.7816 | N44: T1129012363 | O44: 144.75.182.92 | P44: 0.0262 | Q44: 0.118 | R44: 252 | S44: 320 | T44: 0 | U44: 0
A45: Biology | B45: 40_00_011_10250_5521 | C45: Carroll Biology Fund | D45: Maury Brooke | E45: 203 | F45: AF SP4310N | G45: PTR | H45: 17099613 | I45: 1134 | J45: 0 | K45: 29.7108 | L45: 0 | M45: 29.7108 | N45: T1129011365 | O45: 144.75.202.56 | P45: 0.0262 | Q45: 0.118 | R45: 5983 | S45: 7117 | T45: 0 | U45: 0
A46: Biology | B46: 40_00_011_10250_5521 | C46: Carroll Biology Fund | D46: Maury Brooke | E46: 203 | F46: AF MPC2051 | G46: MFP | H46: 17099484 | I46: 2433 | J46: 606 | K46: 50.3631 | L46: 52.722 | M46: 103.0851 | N46: V9725401445 | O46: 144.75.191.21 | P46: 0.0207 | Q46: 0.087 | R46: 14072 | S46: 16505 | T46: 1790 | U46: 2396
A47: Biology | B47: 40_00_011_10250_5521 | C47: Carroll Biology Fund | D47: Maury Brooke | E47: 203A | F47: AF SP4310N | G47: PTR | H47: 17099611 | I47: 610 | J47: 0 | K47: 15.982 | L47: 0 | M47: 15.982 | N47: T1128911356 | O47: 144.75.202.51 | P47: 0.0262 | Q47: 0.118 | R47: 3357 | S47: 3967 | T47: 0 | U47: 0
A48: Biology | B48: 40_00_011_10250_5521 | C48: Carroll Biology Fund | D48: Maury Brooke | E48: 203B | F48: AF SP4310N | G48: PTR | H48: 17099569 | I48: 72 | J48: 0 | K48: 1.8864 | L48: 0 | M48: 1.8864 | N48: T1129011364 | O48: 144.75.202.58 | P48: 0.0262 | Q48: 0.118 | R48: 476 | S48: 548 | T48: 0 | U48: 0
A49: Biology | B49: 40_00_011_10250_5521 | C49: Carroll Biology Fund | D49: Maury Brooke | E49: 203C | F49: AF SP4310N | G49: PTR | H49: 17099612 | I49: 41 | J49: 0 | K49: 1.0742 | L49: 0 | M49: 1.0742 | N49: T1128911365 | O49: 144.75.202.44 | P49: 0.0262 | Q49: 0.118 | R49: 547 | S49: 588 | T49: 0 | U49: 0
A50: Biology | B50: 40_00_011_10250_5521 | C50: Carroll Biology Fund | D50: Maury Brooke | E50: 203D | F50: AF SP4310N | G50: PTR | H50: 17099568 | I50: 364 | J50: 0 | K50: 9.5368 | L50: 0 | M50: 9.5368 | N50: T1129012361 | O50: 144.75.202.57 | P50: 0.0262 | Q50: 0.118 | R50: 475 | S50: 839 | T50: 0 | U50: 0
A51: Center for Leadership & Ethics | B51: 30_00_045_61150_5521 | C51: Center for Leadership & Ethics | D51: Center for Leadership & Ethics | E51: 102 | F51: AF SPC242DN | G51: PTR | H51: 17099779 | I51: 0 | J51: 2 | K51: 0 | L51: 0.236 | M51: 0.236 | N51: T202P600366 | O51: 144.75.215.67 | P51: 0.0262 | Q51: 0.118 | R51: 30 | S51: 30 | T51: 6 | U51: 8
A52: Center for Leadership & Ethics | B52: 30_00_045_61150_5521 | C52: Center for Leadership & Ethics | D52: Center for Leadership & Ethics | E52: 201 | F52: AF SP4310N | G52: PTR | H52: 17099694 | I52: 75 | J52: 0 | K52: 1.965 | L52: 0 | M52: 1.965 | N52: T1129011351 | O52: 144.75.215.30 | P52: 0.0262 | Q52: 0.118 | R52: 177 | S52: 252 | T52: 0 | U52: 0
A53: Center for Leadership & Ethics | B53: 30_00_045_61150_5521 | C53: Center for Leadership & Ethics | D53: Center for Leadership & Ethics | E53: 201 | F53: AF SP4310N | G53: PTR | H53: 17099602 | I53: 670 | J53: 0 | K53: 17.554 | L53: 0 | M53: 17.554 | N53: T1129012327 | O53: 144.75.215.10 | P53: 0.0262 | Q53: 0.118 | R53: 4472 | S53: 5142 | T53: 0 | U53: 0
A54: Center for Leadership & Ethics | B54: 30_00_045_61150_5521 | C54: Center for Leadership & Ethics | D54: Center for Leadership & Ethics | E54: 201 | F54: AF MPC2051 | G54: MFP | H54: 17099534 | I54: 5193 | J54: 1224 | K54: 107.4951 | L54: 106.488 | M54: 213.9831 | N54: V9725400756 | O54: 144.75.215.6 | P54: 0.0207 | Q54: 0.087 | R54: 11581 | S54: 16774 | T54: 8352 | U54: 9576
A55: Chemistry | B55: 10_03_011_26100_5521 | C55: Chemistry | D55: Maury Brooke | E55: 105 | F55: AF SP4310N | G55: PTR | H55: 17099816 | I55: 8 | J55: 0 | K55: 0.2096 | L55: 0 | M55: 0.2096 | N55: T1129010633 | O55: Not Networked | P55: 0.0262 | Q55: 0.118 | R55: 0 | S55: 8 | T55: 0 | U55: 0
A56: Chemistry | B56: 10_03_011_26100_5521 | C56: Chemistry | D56: Maury Brooke | E56: 303 | F56: AF SP4310N | G56: PTR | H56: 17099615 | I56: 705 | J56: 0 | K56: 18.471 | L56: 0 | M56: 18.471 | N56: T1129011366 | O56: 144.75.202.14 | P56: 0.0262 | Q56: 0.118 | R56: 8583 | S56: 9288 | T56: 0 | U56: 0
A57: Chemistry | B57: 10_03_011_26100_5521 | C57: Chemistry | D57: Maury Brooke | E57: 402 | F57: AF SP4310N | G57: PTR | H57: 17099823 | I57: 5 | J57: 0 | K57: 0.131 | L57: 0 | M57: 0.131 | N57: T1128911469 | O57: 144.75.202.28 | P57: 0.0262 | Q57: 0.118 | R57: 0 | S57: 5 | T57: 0 | U57: 0
A58: Chemistry | B58: 10_03_011_26100_5521 | C58: Chemistry | D58: Maury Brooke | E58: 411 | F58: AF SP4310N | G58: PTR | H58: 17099822 | I58: 131 | J58: 0 | K58: 3.4322 | L58: 0 | M58: 3.4322 | N58: T1129010904 | O58: 144.75.202.76 | P58: 0.0262 | Q58: 0.118 | R58: 51 | S58: 182 | T58: 0 | U58: 0
A59: Chemistry | B59: 10_03_011_26100_5521 | C59: Chemistry | D59: Maury Brooke | E59: 415 | F59: AF SP4310N | G59: PTR | H59: 17099812 | I59: 548 | J59: 0 | K59: 14.3576 | L59: 0 | M59: 14.3576 | N59: T1129010621 | O59: Not Networked | P59: 0.0262 | Q59: 0.118 | R59: 0 | S59: 548 | T59: 0 | U59: 0
A60: Chemistry | B60: 10_03_011_26100_5521 | C60: Chemistry | D60: Maury Brooke | E60: 415 | F60: AF SP4310N | G60: PTR | H60: 17099794 | I60: 115 | J60: 0 | K60: 3.013 | L60: 0 | M60: 3.013 | N60: T1129010906 | O60: Not Networked | P60: 0.0262 | Q60: 0.118 | R60: 0 | S60: 115 | T60: 0 | U60: 0
A61: Chemistry | B61: 10_03_011_26100_5521 | C61: Chemistry | D61: Maury Brooke | E61: 415 | F61: AF SP4310N | G61: PTR | H61: 17099795 | I61: 5 | J61: 0 | K61: 0.131 | L61: 0 | M61: 0.131 | N61: T1129010908 | O61: Not Networked | P61: 0.0262 | Q61: 0.118 | R61: 0 | S61: 5 | T61: 0 | U61: 0
A62: Chemistry | B62: 10_03_011_26100_5521 | C62: Chemistry | D62: Maury Brooke | E62: 415 | F62: AF SP4310N | G62: PTR | H62: 17099811 | I62: 209 | J62: 0 | K62: 5.4758 | L62: 0 | M62: 5.4758 | N62: T1129010922 | O62: 144.75.202.75 | P62: 0.0262 | Q62: 0.118 | R62: 124 | S62: 333 | T62: 0 | U62: 0
... A64: Chemistry | B64: 10_03_011_26100_5521 | C64: Chemistry | D64: Maury Brooke | E64: 415 | F64: AF SP4310N | G64: PTR | H64: 17099793 | I64: 138 | J64: 0 | K64: 3.6156 | L64: 0 | M64: 3.6156 | N64: T1129012364 | O64: Not Networked | P64: 0.0262 | Q64: 0.118 | R64: 0 | S64: 138 | T64: 0 | U64: 0
A65: Chemistry | B65: 10_03_011_26100_5521 | C65: Chemistry | D65: Maury Brooke | E65: 303E | F65: AF MPC3502 | G65: MFP | H65: 17099462 | I65: 9065 | J65: 611 | K65: 187.6455 | L65: 53.157 | M65: 240.8025 | N65: W502L601221 | O65: 144.75.202.45 | P65: 0.0207 | Q65: 0.087 | R65: 47349 | S65: 56414 | T65: 1468 | U65: 2079
A66: Chemistry | B66: 10_03_011_26100_5521 | C66: Chemistry | D66: Maury Brooke | E66: 403H | F66: AF SP4310N | G66: PTR | H66: 17099616 | I66: 1514 | J66: 0 | K66: 39.6668 | L66: 0 | M66: 39.6668 | N66: T1129011350 | O66: 144.75.202.13 | P66: 0.0262 | Q66: 0.118 | R66: 7343 | S66: 8857 | T66: 0 | U66: 0
A67: Civil & Environmental Eng. | B67: 10_03_011_28100_5521 | C67: Civil Engineering | D67: Nichols Hall | E67: 410 | F67: AF SP4310N | G67: PTR | H67: 17099752 | I67: 53 | J67: 0 | K67: 1.3886 | L67: 0 | M67: 1.3886 | N67: T1128812156 | O67: 144.75.189.88 | P67: 0.0262 | Q67: 0.118 | R67: 675 | S67: 728 | T67: 0 | U67: 0
A68: Civil & Environmental Eng. | B68: 10_03_011_28100_5521 | C68: Civil Engineering | D68: Nichols Hall | E68: 609 | F68: AF SP4310N | G68: PTR | H68: 17099621 | I68: 324 | J68: 0 | K68: 8.4888 | L68: 0 | M68: 8.4888 | N68: T1129011096 | O68: 144.75.193.196 | P68: 0.0262 | Q68: 0.118 | R68: 1319 | S68: 1643 | T68: 0 | U68: 0
A69: Civil & Environmental Eng. | B69: 10_03_011_28100_5521 | C69: Civil Engineering | D69: Nichols Hall | E69: 609 | F69: AF MPC4502 | G69: MFP | H69: 17099782 | I69: 12466 | J69: 285 | K69: 258.0462 | L69: 24.795 | M69: 282.8412 | N69: W512L700506 | O69: 144.75.193.90 | P69: 0.0207 | Q69: 0.087 | R69: 108345 | S69: 120811 | T69: 24259 | U69: 24544
A70: Communications and Marketing | B70: 10_03_065_88100_5521 | C70: Communications & Marketing | D70: Smith Hall | E70: 111 | F70: AF MP301SP | G70: MFP | H70: 17099530 | I70: 645 | J70: 0 | K70: 13.3515 | L70: 0 | M70: 13.3515 | N70: W912P602281 | O70: 144.75.179.81 | P70: 0.0207 | Q70: 0.087 | R70: 5305 | S70: 5950 | T70: 0 | U70: 0
A71: Communications and Marketing | B71: 10_03_065_88100_5521 | C71: Communications & Marketing | D71: Smith Hall | E71: 114A | F71: AF SP4310N | G71: PTR | H71: 17099697 | I71: 177 | J71: 0 | K71: 4.6374 | L71: 0 | M71: 4.6374 | N71: T1128911218 | O71: 144.75.179.110 | P71: 0.0262 | Q71: 0.118 | R71: 828 | S71: 1005 | T71: 0 | U71: 0
A72: Comptrollers | B72: 10_03_062_32100_5521 | C72: Comptroller's Office | D72: Smith Hall | E72: 320 | F72: AF SP4310N | G72: PTR | H72: 17099695 | I72: 2480 | J72: 0 | K72: 64.976 | L72: 0 | M72: 64.976 | N72: T1129012230 | O72: 144.75.179.43 | P72: 0.0262 | Q72: 0.118 | R72: 8903 | S72: 11383 | T72: 0 | U72: 0
A73: Comptrollers | B73: 10_03_062_32100_5521 | C73: Comptroller's Office | D73: Smith Hall | E73: 320 | F73: AF MP4002 | G73: MFP | H73: 17099414 | I73: 6382 | J73: 0 | K73: 132.1074 | L73: 0 | M73: 132.1074 | N73: W523L101576 | O73: 144.75.179.234 | P73: 0.0207 | Q73: 0.087 | R73: 2945 | S73: 9327 | T73: 0 | U73: 0
A74: Dean's Office | B74: 10_03_045_34100_5521 | C74: Dean of the Faculty | D74: Smith Hall | E74: 201 | F74: AF SP4310N | G74: PTR | H74: 17099687 | I74: 445 | J74: 0 | K74: 11.659 | L74: 0 | M74: 11.659 | N74: T1128911197 | O74: 144.75.179.4 | P74: 0.0262 | Q74: 0.118 | R74: 2545 | S74: 2990 | T74: 0 | U74: 0
A75: Dean's Office | B75: 10_03_045_34100_5521 | C75: Dean of the Faculty | D75: Smith Hall | E75: 212 | F75: AF SP4310N | G75: PTR | H75: 17099699 | I75: 213 | J75: 0 | K75: 5.5806 | L75: 0 | M75: 5.5806 | N75: T1128911227 | O75: 144.75.179.56 | P75: 0.0262 | Q75: 0.118 | R75: 546 | S75: 759 | T75: 0 | U75: 0
A76: Dean's Office | B76: 10_03_045_34100_5521 | C76: Dean of the Faculty | D76: Smith Hall | E76: 213 | F76: AF SP4310N | G76: PTR | H76: 17099686 | I76: 243 | J76: 0 | K76: 6.3666 | L76: 0 | M76: 6.3666 | N76: T1128911226 | O76: 144.75.179.101 | P76: 0.0262 | Q76: 0.118 | R76: 1686 | S76: 1929 | T76: 0 | U76: 0
A77: Dean's Office | B77: 10_03_045_34100_5521 | C77: Dean of the Faculty | D77: Smith Hall | E77: 216 | F77: AF SP4310N | G77: PTR | H77: 17099730 | I77: 662 | J77: 0 | K77: 17.3444 | L77: 0 | M77: 17.3444 | N77: T1128710864 | O77: 144.75.179.11 | P77: 0.0262 | Q77: 0.118 | R77: 2096 | S77: 2758 | T77: 0 | U77: 0
A78: Dean's Office | B78: 10_03_045_34100_5521 | C78: Dean of the Faculty | D78: Smith Hall | E78: 216 | F78: AF MPC2051 | G78: MFP | H78: 17099499 | I78: 1432 | J78: 79 | K78: 29.6424 | L78: 6.873 | M78: 36.5154 | N78: V9725401451 | O78: 144.75.179.99 | P78: 0.0207 | Q78: 0.087 | R78: 8187 | S78: 9619 | T78: 711 | U78: 790
A79: Career Services / Financial Aid | B79: 10_03_064_32145_5521 | C79: Duplicating | D79: Carroll Hall | E79: 307 | F79: AF MPC6501 | G79: MFP | H79: 17099420 | I79: 14168 | J79: 2796 | K79: 293.2776 | L79: 243.252 | M79: 536.5296 | N79: V7620400172 | O79: 144.75.195.225 | P79: 0.0207 | Q79: 0.087 | R79: 176894 | S79: 191062 | T79: 11817 | U79: 14613
A80: Old Barracks | B80: 10_03_064_32145_5521 | C80: Duplicating | D80: Old Barracks | E80: B8 | F80: AF SPC242DN | G80: PTR | H80: 17099702 | I80: 23 | J80: 47 | K80: 0.6026 | L80: 5.546 | M80: 6.1486 | N80: T202P700470 | O80: 144.75.190.50 | P80: 0.0262 | Q80: 0.118 | R80: 225 | S80: 248 | T80: 456 | U80: 503
A81: Scott Shipp Fair Use | B81: 10_03_064_32145_5521 | C81: Duplicating | D81: Scott Shipp Hall | E81: 512 | F81: AF MP6001 | G81: MFP | H81: 17099480 | I81: 9047 | J81: 0 | K81: 187.2729 | L81: 0 | M81: 187.2729 | N81: V6925300966 | O81: 144.75.212.17 | P81: 0.0207 | Q81: 0.087 | R81: 28059 | S81: 37106 | T81: 0 | U81: 0
A82: Smith Hall | B82: 10_03_064_32145_5521 | C82: Duplicating | D82: Smith Hall | E82: 208 | F82: AF MP6001 | G82: MFP | H82: 17099419 | I82: 24587 | J82: 0 | K82: 508.9509 | L82: 0 | M82: 508.9509 | N82: V6925301072 | O82: 144.75.179.230 | P82: 0.0207 | Q82: 0.087 | R82: 14127 | S82: 38714 | T82: 0 | U82: 0
A83: Smith Hall | B83: 10_03_064_32145_5521 | C83: Duplicating | D83: Smith Hall | E83: 208 | F83: AF MPC6501 | G83: MFP | H83: 17099421 | I83: 3510 | J83: 8826 | K83: 72.657 | L83: 767.862 | M83: 840.519 | N83: V7620500472 | O83: 144.75.179.103 | P83: 0.0207 | Q83: 0.087 | R83: 46338 | S83: 49848 | T83: 68697 | U83: 77523
A84: Economics & Business | B84: 10_03_011_36100_5521 | C84: Economics | D84: Scott Shipp Hall | E84: 307 | F84: AF SP4310N | G84: PTR | H84: 17099831 | I84: 812 | J84: 0 | K84: 21.2744 | L84: 0 | M84: 21.2744 | N84: T1128710860 | O84: 144.75.213.35 | P84: 0.0262 | Q84: 0.118 | R84: 2787 | S84: 3599 | T84: 0 | U84: 0
A85: Economics & Business | B85: 10_03_011_36100_5521 | C85: Economics | D85: Scott Shipp Hall | E85: 318 | F85: AF SP4310N | G85: PTR | H85: 17099440 | I85: 0 | J85: 0 | K85: 0 | L85: 0 | M85: 0 | N85: T1129010899 | O85: 144.75.214.41 | P85: 0.0262 | Q85: 0.118 | R85: 477 | S85: 477 | T85: 0 | U85: 0
A86: Economics & Business | B86: 10_03_011_36100_5521 | C86: Economics | D86: Scott Shipp Hall | E86: 320 | F86: AF SP4310N | G86: PTR | H86: 17099771 | I86: 5882 | J86: 0 | K86: 154.1084 | L86: 0 | M86: 154.1084 | N86: T1128712307 | O86: 144.75.214.34 | P86: 0.0262 | Q86: 0.118 | R86: 50078 | S86: 55960 | T86: 0 | U86: 0
A87: Economics & Business | B87: 10_03_011_36100_5521 | C87: Economics | D87: Scott Shipp Hall | E87: 331 | F87: AF SP4310N | G87: PTR | H87: 17099723 | I87: 784 | J87: 0 | K87: 20.5408 | L87: 0 | M87: 20.5408 | N87: T1128911184 | O87: 144.75.208.26 | P87: 0.0262 | Q87: 0.118 | R87: 791 | S87: 1575 | T87: 0 | U87: 0
A88: Economics & Business | B88: 10_03_011_36100_5521 | C88: Economics | D88: Scott Shipp Hall | E88: 337 | F88: AF MPC4502 | G88: MFP | H88: 17099456 | I88: 20678 | J88: 924 | K88: 428.0346 | L88: 80.388 | M88: 508.4226 | N88: W512L601991 | O88: 144.75.208.32 | P88: 0.0207 | Q88: 0.087 | R88: 119688 | S88: 140366 | T88: 8442 | U88: 9366
A89: Economics & Business | B89: 10_03_011_36100_5521 | C89: Economics | D89: Scott Shipp Hall | E89: 345 | F89: AF SP4310N | G89: PTR | H89: 17099813 | I89: 419 | J89: 0 | K89: 10.9778 | L89: 0 | M89: 10.9778 | N89: T1128811965 | O89: 144.75.208.37 | P89: 0.0262 | Q89: 0.118 | R89: 8797 | S89: 9216 | T89: 0 | U89: 0
A90: Economics & Business | B90: 10_03_011_36100_5521 | C90: Economics | D90: Scott Shipp Hall | E90: 346 | F90: AF SPC242DN | G90: PTR | H90: 17099643 | I90: 64 | J90: 95 | K90: 1.6768 | L90: 11.21 | M90: 12.8868 | N90: T202P700467 | O90: 144.75.208.40 | P90: 0.0262 | Q90: 0.118 | R90: 154 | S90: 218 | T90: 176 | U90: 271
A91: Electrical & Computer Eng. | B91: 10_03_011_38100_5521 | C91: Electrical Engineering | D91: Nichols Hall | E91: 502 | F91: AF SP4310N | G91: PTR | H91: 17099626 | I91: 49 | J91: 0 | K91: 1.2838 | L91: 0 | M91: 1.2838 | N91: T1129011159 | O91: 144.75.193.195 | P91: 0.0262 | Q91: 0.118 | R91: 215 | S91: 264 | T91: 0 | U91: 0
A92: Electrical & Computer Eng. | B92: 10_03_011_38100_5521 | C92: Electrical Engineering | D92: Nichols Hall | E92: 507 | F92: AF SP4310N | G92: PTR | H92: 17099587 | I92: 107 | J92: 0 | K92: 2.8034 | L92: 0 | M92: 2.8034 | N92: T1129011158 | O92: 144.75.193.192 | P92: 0.0262 | Q92: 0.118 | R92: 413 | S92: 520 | T92: 0 | U92: 0
... A136: Learning Center | B136: 10_03_054_60100_5521 | C136: Learning Programs | D136: Carroll Hall | E136: 209 | F136: AF SP4310N | G136: PTR | H136: 17099577 | I136: 23 | J136: 0 | K136: 0.6026 | L136: 0 | M136: 0.6026 | N136: T1128911363 | O136: 144.75.195.229 | P136: 0.0262 | Q136: 0.118 | R136: 8 | S136: 31 | T136: 0 | U136: 0
A137: Learning Center | B137: 10_03_054_60100_5521 | C137: Learning Programs | D137: Carroll Hall | E137: 207A | F137: AF SP4310N | G137: PTR | H137: 17099754 | I137: 700 | J137: 0 | K137: 18.34 | L137: 0 | M137: 18.34 | N137: T1128811582 | O137: 144.75.195.46 | P137: 0.0262 | Q137: 0.118 | R137: 4081 | S137: 4781 | T137: 0 | U137: 0
A138: Miller Head Clinic | B138: 10_03_054_60100_5521 | C138: Learning Programs | D138: Carroll Hall | E138: 202 | F138: AF SP4310N | G138: PTR | H138: 17099755 | I138: 2555 | J138: 0 | K138: 66.941 | L138: 0 | M138: 66.941 | N138: T1128911512 | O138: 144.75.195.65 | P138: 0.0262 | Q138: 0.118 | R138: 9749 | S138: 12304 | T138: 0 | U138: 0
A139: Miller Head Clinic | B139: 10_03_054_60100_5521 | C139: Learning Programs | D139: Carroll Hall | E139: 203 | F139: AF SP4310N | G139: PTR | H139: 17099584 | I139: 248 | J139: 0 | K139: 6.4976 | L139: 0 | M139: 6.4976 | N139: T1128911370 | O139: 144.75.195.92 | P139: 0.0262 | Q139: 0.118 | R139: 1221 | S139: 1469 | T139: 0 | U139: 0
A140: Miller Head Clinic | B140: 10_03_054_60100_5521 | C140: Learning Programs | D140: Carroll Hall | E140: 206 | F140: AF SP4310N | G140: PTR | H140: 17099825 | I140: 638 | J140: 0 | K140: 16.7156 | L140: 0 | M140: 16.7156 | N140: T1129010623 | O140: 144.75.195.90 | P140: 0.0262 | Q140: 0.118 | R140: 557 | S140: 1195 | T140: 0 | U140: 0
A141: Preston Library | B141: 10_03_041_62100_5521 | C141: Libraries | D141: Preston Library | E141: 302 | F141: AF SP4310N | G141: PTR | H141: 17099502 | I141: 1388 | J141: 0 | K141: 36.3656 | L141: 0 | M141: 36.3656 | N141: T1128911524 | O141: 144.75.197.12 | P141: 0.0262 | Q141: 0.118 | R141: 5940 | S141: 7328 | T141: 0 | U141: 0
A142: Preston Library | B142: 10_03_041_62100_5521 | C142: Libraries | D142: Preston Library | E142: 303 | F142: AF SP4310N | G142: PTR | H142: 17099504 | I142: 634 | J142: 0 | K142: 16.6108 | L142: 0 | M142: 16.6108 | N142: T1128811633 | O142: 144.75.197.11 | P142: 0.0262 | Q142: 0.118 | R142: 6064 | S142: 6698 | T142: 0 | U142: 0
A143: Preston Library | B143: 10_03_041_62100_5521 | C143: Libraries | D143: Preston Library | E143: 401 | F143: AF SP4310N | G143: PTR | H143: 17099526 | I143: 1292 | J143: 0 | K143: 33.8504 | L143: 0 | M143: 33.8504 | N143: T1128811625 | O143: 144.75.196.12 | P143: 0.0262 | Q143: 0.118 | R143: 4765 | S143: 6057 | T143: 0 | U143: 0
A144: Preston Library | B144: 10_03_041_62100_5521 | C144: Libraries | D144: Preston Library | E144: 401 | F144: AF SP4310N | G144: PTR | H144: 17099641 | I144: 98 | J144: 0 | K144: 2.5676 | L144: 0 | M144: 2.5676 | N144: T1129011155 | O144: 144.75.196.9 | P144: 0.0262 | Q144: 0.118 | R144: 596 | S144: 694 | T144: 0 | U144: 0
...

Sheet GL Summary
A3: Row Labels | B3: Sum of Device Total Click Charge
A4: Academic Advising | B4: 25.6008
A5: Administrative | B5: 657.5527
A6: Admissions Office | B6: 420.8041
A7: AOF - Academic Advising | B7: 207.9699
A8: Auxiliary Administration | B8: 24.1839
A9: AUX-Laundry & Pressing | B9: 28.5029
A10: AUX-Military Store | B10: 150.7084
A11: AUX-Student Health | B11: 208.4622
A12: AUX-Tailor Shop | B12: 18.1042
A13: Business Executive | B13: 230.7838
A14: Cameron Physics & Astronomy | B14: 417.5798
A15: Career Services and Placement | B15: 63.5088
... A65: Undergraduate Research | B65: 30.1076
A66: (blank)
A67: Biology | B67: 9.7988
A68: Drug & Alcohol Abuse | B68: 66.4495
A69: Financial Aid Administration | B69: 146.5366
A70: Post Security | B70: 195.9836
A71: Stone Wall Jackson House | B71: 26.3756
A72: Math Education Resource Center | B72: 28.9077
A73: Grand Total | B73: 22154.258

Sheet April 2013 - HP Toner
A1: Department | B1: General Ledger | C1: GL Description | D1: Building | E1: Room | F1: Model | G1: Device Type | H1: Ricoh Tag | I1: Toner Type | J1: Quantity | K1: Toner Cost Ea. | L1: Total Toner Cost | M1: Serial Number | N1: IP Address
A2: Superintendents House | B2: 10_03_061_94100_5521 | C2: =VLOOKUP(B2,Tables!G$2:H$79,2,FALSE) -> Superintendents Office | D2: Superintendents House | E2: Basement | F2: M2727 | G2: HP-MFP | H2: 17099735 | I2: Black | K2: 47.92 | L2: =SUM(J2*K2) -> 0 | M2: CNG8961SWT | N2: 144.75.156.35
A3: Protocol | B3: 10_03_065_84100_5521 | C3: =VLOOKUP(B3,Tables!G$2:H$79,2,FALSE) -> Protocol Office | D3: 303 Letcher | E3: 300 | F3: 4650 | G3: HP-PTR | H3: 17099-732 | I3: Black | K3: 58.48 | L3: =SUM(J3*K3) -> 0 | M3: JPKAC48117 | N3: 144.75.178.14
A4: Protocol | B4: 10_03_065_84100_5521 | C4: =VLOOKUP(B4,Tables!G$2:H$79,2,FALSE) -> Protocol Office | D4: 303 Letcher | E4: 300 | F4: 4650 | G4: HP-PTR | H4: 17099-732 | I4: Cyan | K4: 58.48 | L4: =SUM(J4*K4) -> 0 | M4: JPKAC48117 | N4: 144.75.178.14
A5: Protocol | B5: 10_03_065_84100_5521 | C5: =VLOOKUP(B5,Tables!G$2:H$90,2,FALSE) -> Protocol Office | D5: 303 Letcher | E5: 300 | F5: 4650 | G5: HP-PTR | H5: 17099-732 | I5: Magenta | K5: 58.48 | L5: =SUM(J5*K5) -> 0 | M5: JPKAC48117 | N5: 144.75.178.14
A6: Protocol | B6: 10_03_065_84100_5521 | C6: =VLOOKUP(B6,Tables!G$2:H$90,2,FALSE) -> Protocol Office | D6: 303 Letcher | E6: 300 | F6: 4650 | G6: HP-PTR | H6: 17099-732 | I6: Yellow | K6: 58.48 | L6: =SUM(J6*K6) -> 0 | M6: JPKAC48117 | N6: 144.75.178.14
A7: Admissions | B7: 10_03_054_01100_5521 | C7: =VLOOKUP(B7,Tables!G$2:H$90,2,FALSE) -> Admissions Office | D7: 307 Letcher | E7: 204 | F7: CP4025 | G7: HP-PTR | H7: 17099781 | I7: Black | K7: 89.75 | L7: =SUM(J7*K7) -> 0 | M7: JPBCBBMOSG | N7: 144.75.215.29
A8: Admissions | B8: 10_03_054_01100_5521 | C8: =VLOOKUP(B8,Tables!G$2:H$90,2,FALSE) -> Admissions Office | D8: 307 Letcher | E8: 204 | F8: CP4025 | G8: HP-PTR | H8: 17099781 | I8: Cyan | K8: 91.49 | L8: =SUM(J8*K8) -> 0 | M8: JPBCBBMOSG | N8: 144.75.215.29
A9: Admissions | B9: 10_03_054_01100_5521 | C9: =VLOOKUP(B9,Tables!G$2:H$90,2,FALSE) -> Admissions Office | D9: 307 Letcher | E9: 204 | F9: CP4025 | G9: HP-PTR | H9: 17099781 | I9: Magenta | K9: 91.49 | L9: =SUM(J9*K9) -> 0 | M9: JPBCBBMOSG | N9: 144.75.215.29
A10: Admissions | B10: 10_03_054_01100_5521 | C10: =VLOOKUP(B10,Tables!G$2:H$90,2,FALSE) -> Admissions Office | D10: 307 Letcher | E10: 204 | F10: CP4025 | G10: HP-PTR | H10: 17099781 | I10: Yellow | K10: 91.49 | L10: =SUM(J10*K10) -> 0 | M10: JPBCBBMOSG | N10: 144.75.215.29
A11: Media Services | B11: 10_03_041_62100_5521 | C11: =VLOOKUP(B11,Tables!G$2:H$90,2,FALSE) -> Libraries | D11: Preston Library | E11: 406 | F11: LJ3600 | G11: HP-PTR | H11: 17099815 | I11: Black | K11: 53.82 | L11: =SUM(J11*K11) -> 0 | M11: CNWDF12176 | N11: 144.75.196.251
A12: Media Services | B12: 10_03_041_62100_5521 | C12: =VLOOKUP(B12,Tables!G$2:H$90,2,FALSE) -> Libraries | D12: Preston Library | E12: 406 | F12: LJ3600 | G12: HP-PTR | H12: 17099815 | I12: Cyan | K12: 61.89 | L12: =SUM(J12*K12) -> 0 | M12: CNWDF12177 | N12: 144.75.196.251
A13: Media Services | B13: 10_03_041_62100_5521 | C13: =VLOOKUP(B13,Tables!G$2:H$90,2,FALSE) -> Libraries | D13: Preston Library | E13: 406 | F13: LJ3600 | G13: HP-PTR | H13: 17099815 | I13: Magenta | K13: 61.89 | L13: =SUM(J13*K13) -> 0 | M13: CNWDF12178 | N13: 144.75.196.251
A14: Media Services | B14: 10_03_041_62100_5521 | C14: =VLOOKUP(B14,Tables!G$2:H$90,2,FALSE) -> Libraries | D14: Preston Library | E14: 406 | F14: LJ3600 | G14: HP-PTR | H14: 17099815 | I14: Yellow | K14: 61.89 | L14: =SUM(J14*K14) -> 0 | M14: CNWDF12179 | N14: 144.75.196.251
A15: Psychology & Philosophy | B15: 10_03_011_86100_5521 | C15: =VLOOKUP(B15,Tables!G$2:H$90,2,FALSE) -> Philosophy & Psychology | D15: Carroll Hall | E15: 403 | F15: LJ4005 | G15: HP-PTR | H15: 17099728 | I15: Black | K15: 74.18 | L15: =SUM(J15*K15) -> 0 | M15: JPRLB46624 | N15: 144.75.195.232
A16: Psychology & Philosophy | B16: 10_03_011_86100_5521 | C16: =VLOOKUP(B16,Tables!G$2:H$90,2,FALSE) -> Philosophy & Psychology | D16: Carroll Hall | E16: 403 | F16: LJ4005 | G16: HP-PTR | H16: 17099728 | I16: Cyan | K16: 76.19 | L16: =SUM(J16*K16) -> 0 | M16: JPRLB46625 | N16: 144.75.195.232
A17: Psychology & Philosophy | B17: 10_03_011_86100_5521 | C17: =VLOOKUP(B17,Tables!G$2:H$90,2,FALSE) -> Philosophy & Psychology | D17: Carroll Hall | E17: 403 | F17: LJ4005 | G17: HP-PTR | H17: 17099728 | I17: Magenta | K17: 76.19 | L17: =SUM(J17*K17) -> 0 | M17: JPRLB46626 | N17: 144.75.195.232
A18: Psychology & Philosophy | B18: 10_03_011_86100_5521 | C18: =VLOOKUP(B18,Tables!G$2:H$90,2,FALSE) -> Philosophy & Psychology | D18: Carroll Hall | E18: 403 | F18: LJ4005 | G18: HP-PTR | H18: 17099728 | I18: Yellow | K18: 76.19 | L18: =SUM(J18*K18) -> 0 | M18: JPRLB46627 | N18: 144.75.195.232
A19: Athletics | B19: 30_00_310_06110_5521 | C19: =VLOOKUP(B19,Tables!G$2:H$90,2,FALSE) -> Administrative | D19: Cameron Hall | E19: 345 | F19: LJ4005 | G19: HP-PTR | H19: 17099-828 | I19: Black | K19: 74.18 | L19: =SUM(J19*K19) -> 0 | M19: JP4LC17284 | N19: Not on network
A20: Athletics | B20: 30_00_310_06110_5521 | C20: =VLOOKUP(B20,Tables!G$2:H$90,2,FALSE) -> Administrative | D20: Cameron Hall | E20: 345 | F20: LJ4005 | G20: HP-PTR | H20: 17099-828 | I20: Cyan | K20: 76.19 | L20: =SUM(J20*K20) -> 0 | M20: JP4LC17284 | N20: Not on network
A21: Athletics | B21: 30_00_310_06110_5521 | C21: =VLOOKUP(B21,Tables!G$2:H$90,2,FALSE) -> Administrative | D21: Cameron Hall | E21: 345 | F21: LJ4005 | G21: HP-PTR | H21: 17099-828 | I21: Magenta | K21: 76.19 | L21: =SUM(J21*K21) -> 0 | M21: JP4LC17284 | N21: Not on network
A22: Athletics | B22: 30_00_310_06110_5521 | C22: =VLOOKUP(B22,Tables!G$2:H$90,2,FALSE) -> Administrative | D22: Cameron Hall | E22: 345 | F22: LJ4005 | G22: HP-PTR | H22: 17099-828 | I22: Yellow | K22: 76.19 | L22: =SUM(J22*K22) -> 0 | M22: JP4LC17284 | N22: Not on network
A23: Comptrollers | B23: 10_03_062_32100_5521 | C23: =VLOOKUP(B23,Tables!G$2:H$90,2,FALSE) -> Comptroller's Office | D23: Smith Hall | E23: 311 | F23: P3010 | G23: HP-PTR | H23: 17099745 | I23: Black | K23: 32.03 | L23: =SUM(J23*K23) -> 0 | M23: VNBCC4L0MD | N23: 144.75.179.5
A24: Comptrollers | B24: 10_03_062_32100_5521 | C24: =VLOOKUP(B24,Tables!G$2:H$90,2,FALSE) -> Comptroller's Office | D24: Smith Hall | E24: 320 | F24: P3010 | G24: HP-PTR | H24: 17099744 | I24: Black | K24: 32.03 | L24: =SUM(J24*K24) -> 0 | M24: VNBCC4L0M6 | N24: 144.75.179.31
A25: Laundry | B25: 10_08_303_82240_5521 | C25: =VLOOKUP(B25,Tables!G$2:H$90,2,FALSE) -> AUX-Laundry & Pressing | D25: Ricohardson Hall | E25: Kiosk | F25: 2430 | G25: HP-PTR | H25: 17099843 | I25: Black | K25: 117.39 | L25: =SUM(J25*K25) -> 0
A26: Financial Aid | B26: 10_03_055_42100_5521 | C26: =VLOOKUP(B26,Tables!G$2:H$90,2,FALSE) -> Financial Aid Administration | D26: Carroll Hall | E26: 302 | F26: m1536dnf | G26: HP-MFP | H26: 17099742 | I26: Black | K26: 25.24 | L26: =SUM(J26*K26) -> 0 | M26: CNC9CC2DKZ | N26: 144.75.195.116
A27: Physical Education | B27: 10_03_011_76100_5521 | C27: =VLOOKUP(B27,Tables!G$2:H$90,2,FALSE) -> Physical Education | D27: Cocke Hall | E27: 322A | F27: CP4025 | G27: HP-PTR | H27: 17099746 | I27: Black | L27: =SUM(J27*K27) -> 0 | M27: CNDX147930 | N27: 144.75.177.50
A28: Math & Computer Science | B28: 10_03_011_64100_5521 | C28: =VLOOKUP(B28,Tables!G$2:H$90,2,FALSE) -> Mathematics | D28: Mallory Hall | E28: 310 | F28: P3005DN | G28: HP-PTR | H28: 17099747 | I28: Black | J28: 1 | K28: 49.38 | L28: =SUM(J28*K28) -> 49.38 | M28: CDN1S33307 | N28: 144.75.182.73
A29: Math & Computer Science | B29: 10_03_011_64100_5521 | C29: =VLOOKUP(B29,Tables!G$2:H$90,2,FALSE) -> Mathematics | D29: Mallory Hall | E29: 314 | F29: P3005DN | G29: HP-PTR | H29: 17099748 | I29: Black | K29: 49.38 | L29: =SUM(J29*K29) -> 0 | M29: CND1S29060 | N29: 144.75.182.65
A30: Math & Computer Science | B30: 10_03_011_64100_5521 | C30: =VLOOKUP(B30,Tables!G$2:H$90,2,FALSE) -> Mathematics | D30: Mallory Hall | E30: 316 | F30: P3005DN | G30: HP-PTR | H30: 17099748 | I30: Black | K30: 49.38 | L30: =SUM(J30*K30) -> 0 | M30: CND1R25001 | N30: 144.75.182.88
A31: Chemistry | B31: 10_03_011_26100_5521 | C31: =VLOOKUP(B31,Tables!G$2:H$90,2,FALSE) -> Chemistry | D31: Maury Brooke | E31: 303 | F31: LJ4005 | G31: HP-PTR | H31: 17099751 | I31: Black | K31: 102.01 | L31: =SUM(J31*K31) -> 0 | M31: JP4LC04882 | N31: 144.75.202.79
A32: Chemistry | B32: 10_03_011_26100_5521 | C32: =VLOOKUP(B32,Tables!G$2:H$90,2,FALSE) -> Chemistry | D32: Maury Brooke | E32: 303 | F32: LJ4005 | G32: HP-PTR | H32: 17099751 | I32: Cyan | K32: 102.01 | L32: =SUM(J32*K32) -> 0 | M32: JP4LC04883 | N32: 144.75.202.80
A33: Chemistry | B33: 10_03_011_26100_5521 | C33: =VLOOKUP(B33,Tables!G$2:H$90,2,FALSE) -> Chemistry | D33: Maury Brooke | E33: 303 | F33: LJ4005 | G33: HP-PTR | H33: 17099751 | I33: Magenta | K33: 102.01 | L33: =SUM(J33*K33) -> 0 | M33: JP4LC04884 | N33: 144.75.202.81
A34: Chemistry | B34: 10_03_011_26100_5521 | C34: =VLOOKUP(B34,Tables!G$2:H$90,2,FALSE) -> Chemistry | D34: Maury Brooke | E34: 303 | F34: LJ4005 | G34: HP-PTR | H34: 17099751 | I34: Yellow | K34: 102.01 | L34: =SUM(J34*K34) -> 0 | M34: JP4LC04885 | N34: 144.75.202.82
A35: Custodial Services | B35: 10_03_071_14100_5521 | C35: =VLOOKUP(B35,Tables!G$2:H$90,2,FALSE) -> Physical Plant Administration | D35: 320 Institute Hill | E35: Basement | F35: LJ2420 | G35: HP-PTR | H35: 17099855 | I35: Black | J35: 1 | K35: 49.37 | L35: =SUM(J35*K35) -> 49.37 | M35: CNGKK65998 | N35: 144.75.201.27
A36: Business Office | B36: 10_03_062_16100_5521 | C36: =VLOOKUP(B36,Tables!G$2:H$90,2,FALSE) -> Business Executive | D36: Smith Hall | E36: 303 | F36: LJ4005 | G36: HP-PTR | H36: 17099854 | I36: Black | K36: 102.01 | L36: =SUM(J36*K36) -> 0 | M36: JP4LC04906 | N36: 144.75.179.112
A37: Business Office | B37: 10_03_062_16100_5521 | C37: =VLOOKUP(B37,Tables!G$2:H$90,2,FALSE) -> Business Executive | D37: Smith Hall | E37: 303 | F37: LJ4005 | G37: HP-PTR | H37: 17099854 | I37: Cyan | K37: 102.01 | L37: =SUM(J37*K37) -> 0 | M37: JP4LC04906 | N37: 144.75.179.112
A38: Business Office | B38: 10_03_062_16100_5521 | C38: =VLOOKUP(B38,Tables!G$2:H$90,2,FALSE) -> Business Executive | D38: Smith Hall | E38: 303 | F38: LJ4005 | G38: HP-PTR | H38: 17099854 | I38: Magenta | K38: 102.01 | L38: =SUM(J38*K38) -> 0 | M38: JP4LC04906 | N38: 144.75.179.112
A39: Business Office | B39: 10_03_062_16100_5521 | C39: =VLOOKUP(B39,Tables!G$2:H$90,2,FALSE) -> Business Executive | D39: Smith Hall | E39: 303 | F39: LJ4005 | G39: HP-PTR | H39: 17099854 | I39: Yellow | K39: 102.01 | L39: =SUM(J39*K39) -> 0 | M39: JP4LC04906 | N39: 144.75.179.112
A40: Institutional Research | B40: 10_03_045_54100_5521 | C40: =VLOOKUP(B40,Tables!G$2:H$90,2,FALSE) -> Institutional Analysis | D40: Smith Hall | E40: 101 | F40: LJ5550HDN | G40: HP-PTR | H40: 17099854 | I40: Black | K40: 127.24 | L40: =SUM(J40*K40) -> 0 | M40: JPDC4CK00H | N40: 144.75.179.229
A41: Institutional Research | B41: 10_03_045_54100_5521 | C41: =VLOOKUP(B41,Tables!G$2:H$90,2,FALSE) -> Institutional Analysis | D41: Smith Hall | E41: 101 | F41: LJ5550HDN | G41: HP-PTR | H41: 17099854 | I41: Cyan | K41: 127.24 | L41: =SUM(J41*K41) -> 0 | M41: JPDC4CK00H | N41: 144.75.179.229
A42: Institutional Research | B42: 10_03_045_54100_5521 | C42: =VLOOKUP(B42,Tables!G$2:H$90,2,FALSE) -> Institutional Analysis | D42: Smith Hall | E42: 101 | F42: LJ5550HDN | G42: HP-PTR | H42: 17099854 | I42: Magenta | K42: 127.24 | L42: =SUM(J42*K42) -> 0 | M42: JPDC4CK00H | N42: 144.75.179.229
A43: Institutional Research | B43: 10_03_045_54100_5521 | C43: =VLOOKUP(B43,Tables!G$2:H$90,2,FALSE) -> Institutional Analysis | D43: Smith Hall | E43: 101 | F43: LJ5550HDN | G43: HP-PTR | H43: 17099854 | I43: Yellow | K43: 127.24 | L43: =SUM(J43*K43) -> 0 | M43: JPDC4CK00H | N43: 144.75.179.229
A44: New Market | B44: 30_00_031_70150_5521 | C44: =VLOOKUP(B44,Tables!G$2:H$90,2,FALSE) -> New Market Battle Field | D44: New Market | E44: Office | F44: LJP3015DN | G44: HP-PTR | I44: Black | K44: 70.91 | L44: =SUM(J44*K44) -> 0 | M44: VNBCB3L2BW | N44: Not on network
A45: New Market | B45: 30_00_031_70150_5521 | C45: =VLOOKUP(B45,Tables!G$2:H$90,2,FALSE) -> New Market Battle Field | D45: New Market | E45: Office | F45: LJp4015DN | G45: HP-PTR | I45: Black | K45: 72.96 | L45: =SUM(J45*K45) -> 0 | M45: JPDF028849 | N45: Not on network
A46: Physical Plant | B46: 10_03_071_14100_5521 | C46: =VLOOKUP(B46,Tables!G$2:H$90,2,FALSE) -> Physical Plant Administration | D46: Hinty Hall | E46: Supply | F46: LJCP2025 | G46: HP-PTR | I46: Black | J46: 1 | K46: 58.53 | L46: =SUM(J46*K46) -> 58.53
A47: Physical Plant | B47: 10_03_071_14100_5521 | C47: =VLOOKUP(B47,Tables!G$2:H$90,2,FALSE) -> Physical Plant Administration | D47: Hinty Hall | E47: Supply | F47: LJCP2025 | G47: HP-PTR | I47: Cyan | K47: 58.53 | L47: =SUM(J47*K47) -> 0
A48: Physical Plant | B48: 10_03_071_14100_5521 | C48: =VLOOKUP(B48,Tables!G$2:H$90,2,FALSE) -> Physical Plant Administration | D48: Hinty Hall | E48: Supply | F48: LJCP2025 | G48: HP-PTR | I48: Magenta | K48: 58.53 | L48: =SUM(J48*K48) -> 0
A49: Physical Plant | B49: 10_03_071_14100_5521 | C49: =VLOOKUP(B49,Tables!G$2:H$90,2,FALSE) -> Physical Plant Administration | D49: Hinty Hall | E49: Supply | F49: LJCP2025 | G49: HP-PTR | I49: Yellow | K49: 58.53 | L49: =SUM(J49*K49) -> 0
L50: =SUM(J50*K50) -> 0
J51: =SUM(J2:J50) -> 3 | K51: TOTAL | L51: =SUM(L2:L50) -> 157.28

Sheet Totals
D2: B&W MFP | E2: Color MFP | F2: B/W MFD | G2: Color MFD | J2: B&W MFP | K2: Color MFP
C3: MFP: | D3: =SUMIF('April 2013 - Data'!G$2:$G$384,"MFP",'April 2013 - Data'!I$2:I$384) -> 443547 | E3: =SUMIF('April 2013 - Data'!G$2:$G$384,"MFP",'April 2013 - Data'!J$2:J$384) -> 75530 | F3: =SUM(D3)*D14 -> 9181.4229 | G3: =SUM(E3)*E14 -> 6571.11 | J3: =SUMIF('April 2013 - Data'!$G$2:G$384,"MFP",'April 2013 - Data'!K$2:K$384) -> 9181.4229 | K3: =SUMIF('April 2013 - Data'!$G$2:$G$384,"MFP",'April 2013 - Data'!L$2:L$384) -> 6571.11
D5: B&W Printer | E5: Color Printer | F5: B/W Printer | G5: Color Printer | J5: B&W Printer | K5: Color Printer
C6: Printer: | D6: =SUMIF('April 2013 - Data'!$G$2:$G$384,"PTR",'April 2013 - Data'!I2:I384) -> 223033 | E6: =SUMIF('April 2013 - Data'!$G2:$G$384,"PTR",'April 2013 - Data'!J$2:J$384) -> 4731 | F6: =SUM(D6)*D15 -> 5843.4646 | G6: =SUM(E6)*E15 -> 558.258 | J6: =SUMIF('April 2013 - Data'!$G$2:$G$384,"PTR",'April 2013 - Data'!K$2:K$384) -> 5843.4646 | K6: =SUMIF('April 2013 - Data'!$G$2:$G$384,"PTR",'April 2013 - Data'!L$2:L$384) -> 558.258
D8: Total B&W | E8: Total Color | F8: Total B&W | G8: Total Color | J8: Total B&W | K8: Total Color
C9: Total: | D9: =SUM(D3,D6) -> 666580 | E9: =SUM(E3,E6) -> 80261 | F9: =ROUNDUP(F3+F6,2) -> 15024.89 | G9: =ROUNDUP(G3+G6,2) -> 7129.37 | J9: =ROUNDUP(J3+J6,2) -> 15024.89 | K9: =ROUNDUP(K3+K6,2) -> 7129.37
F11: Total This Invoice: | G11: =(F9+G9) -> 22154.26 | J11: Total This Invoice: | K11: =SUM(J9+K9) -> 22154.26
F12: HP Toner: | G12: ='April 2013 - HP Toner'!L51 -> 157.28 | J12: Total Invoice w/ HP Toner: | K12: =G13 -> 22311.54
F13: Invoice Total | G13: =SUM(G11:G12) -> 22311.54
C14: MFP | D14: =Tables!B2 -> 0.0207 | E14: =Tables!B3 -> 0.087
C15: Printer | D15: =Tables!B5 -> 0.0262 | E15: =Tables!B6 -> 0.118
F18: MFP Total: | G18: =COUNTIF('April 2013 - Data'!G2:G384,"PTR") -> 231
F19: Printer Total: | G19: =COUNTIF('April 2013 - Data'!G2:G384,"MFP") -> 68
F20: Device Total: | G20: =SUM(G18:G19) -> 299

Sheet Tables
A1: Rates | D1: Devices | E1: Type | G1: GL # | H1: Description
A2: MFP B&W | B2: 0.0207 | D2: AF MP301SP | E2: MFP | G2: 10_03_054_60100_5521 | H2: Learning Programs
A3: MFP Color | B3: 0.087 | D3: AF MP4002 | E3: MFP | G3: 10_03_054_01100_5521 | H3: Admissions Office
D4: AF MP6001 | E4: MFP | G4: 10_03_011_02100_5521 | H4: ROTC-Air Force
A5: Printer B&W | B5: 0.0262 | D5: AF MPC2051 | E5: MFP | G5: 10_03_011_04100_5521 | H5: ROTC-Army
A6: Printer Color | B6: 0.118 | D6: AF MPC3502 | E6: MFP | G6: 30_00_310_06104_5521 | H6: Sports Information
D7: AF MPC4502 | E7: MFP | G7: 30_00_310_06095_5521 | H7: Soccer - Women
D8: AF MPC6501 | E8: MFP | G8: 30_00_310_06000_5521 | H8: Football
D9: AF SP4310N | E9: PTR | G9: 30_00_310_06090_5521 | H9: Soccer
D10: AF SPC242DN | E10: PTR | G10: 30_00_310_06010_5521 | H10: Basketball
D11: AF SPC430DN | E11: PTR | G11: 30_00_310_06020_5521 | H11: Track & Cross Country
D12: AF MPC5502 | E12: MFP | G12: 30_00_310_06110_5521 | H12: Administrative
G13: 40_00_052_06550_5521 | H13: AOF - Academic Advising
G14: 10_08_309_82115_5521 | H14: Auxiliary Administration
G15: 10_08_303_82240_5521 | H15: AUX-Laundry & Pressing
G16: 10_08_302_82230_5521 | H16: AUX-Tailor Shop
G17: 10_03_064_82140_5521 | H17: Post Mail
G18: 10_08_302_82190_5521 | H18: AUX-Military Store
G19: 40_00_011_10250_5521 | H19: Carroll Biology Fund
G20: 10_03_011_10100_5521 | H20: Biology
G21: 10_03_062_16100_5521 | H21: Business Executive
G22: 10_03_062_16150_5521 | H22: Institute Planning
G23: 10_08_307_18380_5521 | H23: Student Union
G24: 10_03_053_20300_5521 | H24: Career Services and Placement
... G82: 30_00_031_70150_5521 | H82: New Market Battle Field

Sheet Meter Comparison
A1: Manufacturer | B1: Model | C1: Serial Number | D1: Mono Pages First Meter | E1: Mono Pages Last Meter | F1: Color Pages First Meter | G1: Color Pages Last Meter | H1: First Meter Date | I1: Last Meter Date | J1: Serial Number
A2: RICOH | B2: Aficio SP C430DN | C2: S9329101012 | D2: 871 | E2: 873 | F2: 87 | G2: 87 | J2: S9329101012
A3: RICOH | B3: Aficio SP C430DN | C3: S9329101091 | D3: 1512 | E3: 1774 | F3: 3151 | G3: 3833 | J3: S9329101091
A4: RICOH | B4: Aficio SP 4310N | C4: T1128710718 | D4: 14950 | E4: 17598 | F4: 0 | G4: 0 | J4: T1128710718
A5: RICOH | B5: Aficio SP 4310N | C5: T1128710823 | D5: 5850 | E5: 6833 | F5: 0 | G5: 0 | J5: T1128710823
A6: RICOH | B6: Aficio SP 4310N | C6: T1128710825 | D6: 2296 | E6: 2859 | F6: 0 | G6: 0 | J6: T1128710825
A7: RICOH | B7: Aficio SP 4310N | C7: T1128710860 | D7: 3599 | E7: 4324 | F7: 0 | G7: 0 | J7: T1128710860
A8: RICOH | B8: Aficio SP 4310N | C8: T1128710864 | D8: 2758 | E8: 4419 | F8: 0 | G8: 0 | J8: T1128710864
A9: RICOH | B9: Aficio SP 4310N | C9: T1128712304 | D9: 55883 | E9: 64629 | F9: 0 | G9: 0 | J9: T1128712304
A10: RICOH | B10: Aficio SP 4310N | C10: T1128712307 | D10: 55960 | E10: 66853 | F10: 0 | G10: 0 | J10: T1128712307
A11: RICOH | B11: Aficio SP 4310N | C11: T1128810903 | D11: 2373 | E11: 2608 | F11: 0 | G11: 0 | J11: T1128810903
A12: RICOH | B12: Aficio SP 4310N | C12: T1128811582 | D12: 4781 | E12: 5958 | F12: 0 | G12: 0 | J12: T1128811582
A13: RICOH | B13: Aficio SP 4310N | C13: T1128811618 | D13: 1527 | E13: 1918 | F13: 0 | G13: 0 | J13: T1128811618
... A101: RICOH | B101: Aficio SP 4310N | C101: T1129010432 | D101: 11273 | E101: 14673 | F101: 0 | G101: 0 | J101: T1129010432
A102: RICOH | B102: Aficio SP 4310N | C102: T1129010621 | D102: 548 | E102: 656 | J102: T1129010621
A103: RICOH | B103: Aficio SP 4310N | C103: T1129010623 | D103: 1195 | E103: 1852 | F103: 0 | G103: 0 | J103: T1129010623
A104: RICOH | B104: Aficio SP 4310N | C104: T1129010625 | D104: 148 | E104: 297 | F104: 0 | G104: 0 | J104: T1129010625
A105: RICOH | B105: Aficio SP 4310N | C105: T1129010627 | D105: 204 | E105: 204 | F105: 0 | G105: 0 | J105: T1129010627
A106: RICOH | B106: Aficio SP 4310N | C106: T1129010629 | D106: 734 | E106: 1293 | F106: 0 | G106: 0 | J106: T1129010629
A107: RICOH | B107: Aficio SP 4310N | C107: T1129010631 | D107: 122 | E107: 240 | F107: 0 | G107: 0 | J107: T1129010631
A108: RICOH | B108: Aficio SP 4310N | C108: T1129010633 | D108: 8 | E108: 92 | J108: T1129010633
A109: RICOH | B109: Aficio SP 4310N | C109: T1129010634 | D109: 505 | E109: 548 | F109: 0 | G109: 0 | J109: T1129010634
A110: RICOH | B110: Aficio SP 4310N | C110: T1129010677 | D110: 3865 | E110: 4735 | F110: 0 | G110: 0 | J110: T1129010677
A111: RICOH | B111: Aficio SP 4310N | C111: T1129010681 | D111: 1133 | E111: 1332 | F111: 0 | G111: 0 | J111: T1129010681
A112: RICOH | B112: Aficio SP 4310N | C112: T1129010744 | D112: 1394 | E112: 1678 | F112: 0 | G112: 0 | J112: T1129010744
A113: RICOH | B113: Aficio SP 4310N | C113: T1129010748 | D113: 1512 | E113: 1666 | F113: 0 | G113: 0 | J113: T1129010748
A114: RICOH | B114: Aficio SP 4310N | C114: T1129010760 | D114: 561 | E114: 719 | F114: 0 | G114: 0 | J114: T1129010760
A115: RICOH | B115: Aficio SP 4310N | C115: T1129010803 | D115: 3808 | E115: 4686 | F115: 0 | G115: 0 | J115: T1129010803
A116: RICOH | B116: Aficio SP 4310N | C116: T1129010820 | D116: 458 | E116: 589 | F116: 0 | G116: 0 | J116: T1129010820
A117: RICOH | B117: Aficio SP 4310N | C117: T1129010823 | D117: 979 | E117: 1176 | F117: 0 | G117: 0 | J117: T1129010823
A118: RICOH | B118: Aficio SP 4310N | C118: T1129010832 | D118: 844 | E118: 850 | F118: 0 | G118: 0 | J118: T1129010832
A119: RICOH | B119: Aficio SP 4310N | C119: T1129010833 | D119: 2654 | E119: 3155 | F119: 0 | G119: 0 | J119: T1129010833
A120: RICOH | B120: Aficio SP 4310N | C120: T1129010836 | D120: 1912 | E120: 1932 | F120: 0 | G120: 0 | J120: T1129010836
... A141: RICOH | B141: Aficio SP 4310N | C141: T1129010904 | D141: 182 | E141: 411 | F141: 0 | G141: 0 | J141: T1129010904
A142: RICOH | B142: Aficio SP 4310N | C142: T1129010906 | D142: 115 | E142: 119 | J142: T1129010906
A143: RICOH | B143: Aficio SP 4310N | C143: T1129010908 | D143: 5 | E143: 7 | J143: T1129010908
A144: RICOH | B144: Aficio SP 4310N | C144: T1129010910 | D144: 504 | E144: 511 | F144: 0 | G144: 0 | J144: T1129010910
A145: RICOH | B145: Aficio SP 4310N | C145: T1129010912 | D145: 148 | E145: 176 | F145: 0 | G145: 0 | J145: T1129010912
A146: RICOH | B146: Aficio SP 4310N | C146: T1129010915 | D146: 778 | E146: 1090 | F146: 0 | G146: 0 | J146: T1129010915
A147: RICOH | B147: Aficio SP 4310N | C147: T1129010918 | D147: 2399 | E147: 2588 | F147: 0 | G147: 0 | J147: T1129010918
A148: RICOH | B148: Aficio SP 4310N | C148: T1129010922 | D148: 333 | E148: 449 | F148: 0 | G148: 0 | J148: T1129010922
A149: RICOH | B149: Aficio SP 4310N | C149: T1129011038 | D149: 2469 | E149: 3057 | F149: 0 | G149: 0 | J149: T1129011038
A150: RICOH | B150: Aficio SP 4310N | C150: T1129011096 | D150: 1643 | E150: 2703 | F150: 0 | G150: 0 | J150: T1129011096
A151: RICOH | B151: Aficio SP 4310N | C151: T1129011106 | D151: 446 | E151: 509 | F151: 0 | G151: 0 | J151: T1129011106
A152: RICOH | B152: Aficio SP 4310N | C152: T1129011126 | D152: 1512 | E152: 1749 | F152: 0 | G152: 0 | J152: T1129011126
A153: RICOH | B153: Aficio SP 4310N | C153: T1129011154 | D153: 117 | E153: 144 | F153: 0 | G153: 0 | J153: T1129011154
A154: RICOH | B154: Aficio SP 4310N | C154: T1129011155 | D154: 694 | E154: 956 | F154: 0 | G154: 0 | J154: T1129011155
A155: RICOH | B155: Aficio SP 4310N | C155: T1129011158 | D155: 520 | E155: 537 | F155: 0 | G155: 0 | J155: T1129011158
... A198: RICOH | B198: Aficio SP 4310N | C198: T1129012328 | D198: 17 | E198: 235 | F198: 0 | G198: 0 | J198: T1129012328
A199: RICOH | B199: Aficio SP 4310N | C199: T1129012350 | D199: 288 | E199: 333 | J199: T1129012350
A200: RICOH | B200: Aficio SP 4310N | C200: T1129012361 | D200: 839 | E200: 1190 | F200: 0 | G200: 0 | J200: T1129012361
A201: RICOH | B201: Aficio SP 4310N | C201: T1129012363 | D201: 320 | E201: 494 | F201: 0 | G201: 0 | J201: T1129012363
A202: RICOH | B202: Aficio SP 4310N | C202: T1129012364 | D202: 138 | E202: 149 | J202: T1129012364
A203: RICOH | B203: Aficio SP 4310N | C203: T1129012368 | D203: 297 | E203: 346 | F203: 0 | G203: 0 | J203: T1129012368
A204: RICOH | B204: Aficio SP 4310N | C204: T1129012371 | D204: 211 | E204: 354 | F204: 0 | G204: 0 | J204: T1129012371
A205: RICOH | B205: Aficio SP 4310N | C205: T202P600356 | D205: 570 | E205: 621 | F205: 241 | G205: 254 | J205: T202P600356
A206: RICOH | B206: Aficio SP C242DN | C206: T202P600366 | D206: 30 | E206: 30 | F206: 8 | G206: 8 | J206: T202P600366
A207: RICOH | B207: Aficio SP C242DN | C207: T202P600371 | D207: 0 | E207: 0 | F207: 0 | G207: 0 | J207: T202P600371
A208: RICOH | B208: Aficio SP C242DN | C208: T202P600637 | D208: 1730 | E208: 2009 | F208: 672 | G208: 783 | J208: T202P600637
A209: RICOH | B209: Aficio SP C242DN | C209: T202P600824 | D209: 587 | E209: 612 | F209: 1524 | G209: 1608 | J209: T202P600824
A210: RICOH | B210: Aficio SP C242DN | C210: T202P600942 | D210: 2674 | E210: 3412 | F210: 538 | G210: 663 | J210: T202P600942
A211: RICOH | B211: Aficio SP C242DN | C211: T202P700273 | D211: 753 | E211: 794 | F211: 381 | G211: 417 | J211: T202P700273
A212: RICOH | B212: Aficio SP C242DN | C212: T202P700340 | D212: 90 | E212: 92 | F212: 75 | G212: 117 | J212: T202P700340
A213: RICOH | B213: Aficio SP C242DN | C213: T202P700442 | D213: 2529 | E213: 2763 | F213: 834 | G213: 999 | J213: T202P700442
A214: RICOH | B214: Aficio SP C242DN | C214: T202P700447 | D214: 0 | E214: 0 | F214: 0 | G214: 0 | J214: T202P700447
... A300: RICOH | B300: Aficio MP 301 | C300: W912P903531 | D300: 3159 | E300: 3894 | F300: 0 | G300: 0 | J300: W912P903531
A301: RICOH
A302: RICOH
A303: RICOH
A304: RICOH
A305: RICOH
A306: RICOH
A307: RICOH
A308: RICOH
A309: RICOH
A310: RICOH
A311: RICOH
A312: RICOH
... A315: Date:
A316: Client Name: | B316: Virginia Military Institute
A317: Client Contact Information: | B317: Craig Peltion
A318: Meter Analysis Period:
