Workbook

Sheet sources minimal
A1: url | B1: score
A2: http://www.washingtonmonthly.com/ | B2: ='sources full'!H2 -> -1
A3: http://thinkprogress.org/ | B3: ='sources full'!H3 -> -0.82170898
A4: http://www.americablog.com/ | B4: ='sources full'!H4 -> -0.78782425
A5: http://www.dailykos.com/ | B5: ='sources full'!H5 -> -0.59595404
A6: http://downwithtyranny.blogspot.com/ | B6: ='sources full'!H6 -> -0.53686419
A7: http://firedoglake.com/ | B7: ='sources full'!H7 -> -0.53325778
A8: http://www.newshoggers.com/blog/ | B8: ='sources full'!H8 -> -0.49626626
A9: http://digbysblog.blogspot.com/ | B9: ='sources full'!H9 -> -0.46671809
A10: http://www.mydd.com/ | B10: ='sources full'!H10 -> -0.44136057
A11: http://tpmelectioncentral.talkingpointsmemo.com/ | B11: ='sources full'!H11 -> -0.44111687
A12: http://www.huffingtonpost.com/theblog/ | B12: ='sources full'!H12 -> -0.41960414
A13: http://talkingpointsmemo.com/ | B13: ='sources full'!H13 -> -0.41566858
... A1387: http://hotair.com/ | B1387: ='sources full'!H1387 -> 1

Sheet sources full
A1: name | B1: url | C1: v1 | D1: v2 | E1: v3 | F1: v4 | G1: v5 | H1: score
A2: Washington Monthly | B2: http://www.washingtonmonthly.com/ | C2: -0.14833796 | D2: -0.22412926 | E2: -0.11436973 | F2: 0.10532516 | G2: 0.0060320104 | H2: =IF((D2>0.0),(D2/LARGE($D$2:$D$1387,1.0)),IF((D2<0.0),(-D2/SMALL($D$2:$D$1387,1.0)),0.0)) -> -1
A3: Think Progress | B3: http://thinkprogress.org/ | C3: -0.1297935 | D3: -0.18416903 | E3: -0.016569148 | F3: 0.12686418 | G3: 0.14543742 | H3: =IF((D3>0.0),(D3/LARGE($D$2:$D$1387,1.0)),IF((D3<0.0),(-D3/SMALL($D$2:$D$1387,1.0)),0.0)) -> -0.82170898
A4: AMERICAblog News | B4: http://www.americablog.com/ | C4: -0.11629498 | D4: -0.17657447 | E4: -0.0012386676 | F4: 0.088265006 | G4: -0.013769946 | H4: =IF((D4>0.0),(D4/LARGE($D$2:$D$1387,1.0)),IF((D4<0.0),(-D4/SMALL($D$2:$D$1387,1.0)),0.0)) -> -0.78782425
A5: Daily Kos | B5: http://www.dailykos.com/ | C5: -0.10830741 | D5: -0.13357074 | E5: -0.0085139548 | F5: 0.071187508 | G5: -0.063661935 | H5: =IF((D5>0.0),(D5/LARGE($D$2:$D$1387,1.0)),IF((D5<0.0),(-D5/SMALL($D$2:$D$1387,1.0)),0.0)) -> -0.59595404
A6: DownWithTyranny! | B6: http://downwithtyranny.blogspot.com/ | C6: -0.086613747 | D6: -0.12032697 | E6: 0.0039589827 | F6: 0.061534966 | G6: -0.022037578 | H6: =IF((D6>0.0),(D6/LARGE($D$2:$D$1387,1.0)),IF((D6<0.0),(-D6/SMALL($D$2:$D$1387,1.0)),0.0)) -> -0.53686419
A7: Firedoglake | B7: http://firedoglake.com/ | C7: -0.10623617 | D7: -0.11951867 | E7: -0.077794296 | F7: 0.069177732 | G7: 0.055123155 | H7: =IF((D7>0.0),(D7/LARGE($D$2:$D$1387,1.0)),IF((D7<0.0),(-D7/SMALL($D$2:$D$1387,1.0)),0.0)) -> -0.53325778
A8: Newshoggers.com | B8: http://www.newshoggers.com/blog/ | C8: -0.10483014 | D8: -0.11122779 | E8: -0.088173121 | F8: -0.081440949 | G8: 0.069679837 | H8: =IF((D8>0.0),(D8/LARGE($D$2:$D$1387,1.0)),IF((D8<0.0),(-D8/SMALL($D$2:$D$1387,1.0)),0.0)) -> -0.49626626
A9: Hullabaloo | B9: http://digbysblog.blogspot.com/ | C9: -0.091783798 | D9: -0.10460518 | E9: -0.037088859 | F9: 0.039365029 | G9: 0.044307287 | H9: =IF((D9>0.0),(D9/LARGE($D$2:$D$1387,1.0)),IF((D9<0.0),(-D9/SMALL($D$2:$D$1387,1.0)),0.0)) -> -0.46671809
A10: MyDD | B10: http://www.mydd.com/ | C10: -0.10414597 | D10: -0.098921818 | E10: 0.00058502628 | F10: 0.0015274313 | G10: -0.043086209 | H10: =IF((D10>0.0),(D10/LARGE($D$2:$D$1387,1.0)),IF((D10<0.0),(-D10/SMALL($D$2:$D$1387,1.0)),0.0)) -> -0.44136057
A11: TPM Election Central | B11: http://tpmelectioncentral.talkingpointsmemo.com/ | C11: -0.14194534 | D11: -0.098867198 | E11: 0.12483721 | F11: 0.053004401 | G11: 0.16647074 | H11: =IF((D11>0.0),(D11/LARGE($D$2:$D$1387,1.0)),IF((D11<0.0),(-D11/SMALL($D$2:$D$1387,1.0)),0.0)) -> -0.44111687
A12: The Huffington Post | B12: http://www.huffingtonpost.com/theblog/ | C12: -0.15906465 | D12: -0.094045564 | E12: -0.14146736 | F12: -0.086098179 | G12: 0.05803119 | H12: =IF((D12>0.0),(D12/LARGE($D$2:$D$1387,1.0)),IF((D12<0.0),(-D12/SMALL($D$2:$D$1387,1.0)),0.0)) -> -0.41960414
A13: Talking Points Memo | B13: http://talkingpointsmemo.com/ | C13: -0.085151588 | D13: -0.093163491 | E13: -0.012993565 | F13: 0.060464352 | G13: 0.040464721 | H13: =IF((D13>0.0),(D13/LARGE($D$2:$D$1387,1.0)),IF((D13<0.0),(-D13/SMALL($D$2:$D$1387,1.0)),0.0)) -> -0.41566858
... A1387: Hot Air | B1387: http://hotair.com/ | C1387: -0.26101714 | D1387: 0.54313314 | E1387: 0.078752924 | F1387: 0.29868589 | G1387: -0.10397674 | H1387: =IF((D1387>0.0),(D1387/LARGE($D$2:$D$1387,1.0)),IF((D1387<0.0),(-D1387/SMALL($D$2:$D$1387,1.0)),0.0)) -> 1
