Workbook

Sheet February 2013 - Data
A1: Department / Read date 2/28/2013 | B1: General Ledger | C1: GL Description | D1: Building | E1: Room | F1: Model | G1: Device Type | H1: Ricoh Tag | I1: Total BW Click Count | J1: Total Color Click Count | K1: BW Click Charge | L1: Color Click Charge | M1: Device Total Click Charge | N1: Serial Number | O1: IP Address | P1: CPC BW | Q1: CPC Color | R1: Prev BW Click Count | S1: Current BW Click Count | T1: Prev Color Click Count | U1: Current Color Click Count
A2: Academic Advising | B2: 10_07_205_90300_5521 | C2: =VLOOKUP(B2,Tables!G$2:H$79,2,FALSE) -> Academic Advising | D2: Shell Hall | E2: 301 | F2: AF SPC242DN | G2: =VLOOKUP(F2,Tables!D$2:E$12,2,FALSE) -> PTR | H2: 17099684 | I2: =SUM(S2-R2) -> 249 | J2: =SUM(U2-T2) -> 214 | K2: =SUM(I2*$P2) -> 6.5238 | L2: =SUM(J2*$Q2) -> 25.252 | M2: =K2+L2 -> 31.7758 | N2: T202P700442 | O2: 144.75.180.103 | P2: =IF(G2="MFP",Tables!B$2,Tables!B$5) -> 0.0262 | Q2: =IF(G2="MFP",Tables!B$3,Tables!B$6) -> 0.118 | R2: =VLOOKUP($N2,'Meter Read info'!$C$2:$G$249,2,"FALSE") -> 1922 | S2: =VLOOKUP($N2,'Meter Read info'!$C$2:$G$249,3,"FALSE") -> 2171 | T2: =VLOOKUP($N2,'Meter Read info'!$C$2:$G$249,4,"FALSE") -> 326 | U2: =VLOOKUP($N2,'Meter Read info'!$C$2:$G$249,5,"FALSE") -> 540
B3: 10_07_205_90300_5521 Total | M3: =SUBTOTAL(9,M2:M2) -> 31.7758
A4: Admissions | B4: 10_03_054_01100_5521 | C4: =VLOOKUP(B4,Tables!G$2:H$79,2,FALSE) -> Admissions Office | D4: 307 Letcher | E4: 204 | F4: AF MPC3502 | G4: =VLOOKUP(F4,Tables!D$2:E$12,2,FALSE) -> MFP | H4: 17099493 | I4: =SUM(S4-R4) -> 5882 | J4: =SUM(U4-T4) -> 5382 | K4: =SUM(I4*$P4) -> 121.7574 | L4: =SUM(J4*$Q4) -> 468.234 | M4: =K4+L4 -> 589.9914 | N4: W502L600872 | O4: 144.75.215.48 | P4: =IF(G4="MFP",Tables!B$2,Tables!B$5) -> 0.0207 | Q4: =IF(G4="MFP",Tables!B$3,Tables!B$6) -> 0.087 | R4: =VLOOKUP($N4,'Meter Read info'!$C$2:$G$249,2,"FALSE") -> 27457 | S4: =VLOOKUP($N4,'Meter Read info'!$C$2:$G$249,3,"FALSE") -> 33339 | T4: =VLOOKUP($N4,'Meter Read info'!$C$2:$G$249,4,"FALSE") -> 11004 | U4: =VLOOKUP($N4,'Meter Read info'!$C$2:$G$249,5,"FALSE") -> 16386
A5: Admissions | B5: 10_03_054_01100_5521 | C5: =VLOOKUP(B5,Tables!G$2:H$79,2,FALSE) -> Admissions Office | D5: 309 Letcher | E5: 200 | F5: AF SPC430DN | G5: =VLOOKUP(F5,Tables!D$2:E$12,2,FALSE) -> PTR | H5: 17099785 | I5: =SUM(S5-R5) -> 43 | J5: =SUM(U5-T5) -> 624 | K5: =SUM(I5*$P5) -> 1.1266 | L5: =SUM(J5*$Q5) -> 73.632 | M5: =K5+L5 -> 74.7586 | N5: S9329101091 | O5: 144.75.186.31 | P5: =IF(G5="MFP",Tables!B$2,Tables!B$5) -> 0.0262 | Q5: =IF(G5="MFP",Tables!B$3,Tables!B$6) -> 0.118 | R5: =VLOOKUP($N5,'Meter Read info'!$C$2:$G$249,2,"FALSE") -> 845 | S5: =VLOOKUP($N5,'Meter Read info'!$C$2:$G$249,3,"FALSE") -> 888 | T5: =VLOOKUP($N5,'Meter Read info'!$C$2:$G$249,4,"FALSE") -> 1305 | U5: =VLOOKUP($N5,'Meter Read info'!$C$2:$G$249,5,"FALSE") -> 1929
A6: Admissions | B6: 10_03_054_01100_5521 | C6: =VLOOKUP(B6,Tables!G$2:H$79,2,FALSE) -> Admissions Office | D6: 309 Letcher | E6: 201 | F6: AF SP4310N | G6: =VLOOKUP(F6,Tables!D$2:E$12,2,FALSE) -> PTR | H6: 17099512 | I6: =SUM(S6-R6) -> 2 | J6: =SUM(U6-T6) -> 0 | K6: =SUM(I6*$P6) -> 0.0524 | L6: =SUM(J6*$Q6) -> 0 | M6: =K6+L6 -> 0.0524 | N6: T1129010877 | O6: 144.75.186.30 | P6: =IF(G6="MFP",Tables!B$2,Tables!B$5) -> 0.0262 | Q6: =IF(G6="MFP",Tables!B$3,Tables!B$6) -> 0.118 | R6: =VLOOKUP($N6,'Meter Read info'!$C$2:$G$249,2,"FALSE") -> 48 | S6: =VLOOKUP($N6,'Meter Read info'!$C$2:$G$249,3,"FALSE") -> 50 | T6: =VLOOKUP($N6,'Meter Read info'!$C$2:$G$249,4,"FALSE") -> 0 | U6: =VLOOKUP($N6,'Meter Read info'!$C$2:$G$249,5,"FALSE") -> 0
A7: Admissions | B7: 10_03_054_01100_5521 | C7: =VLOOKUP(B7,Tables!G$2:H$79,2,FALSE) -> Admissions Office | D7: 309 Letcher | E7: 201 | F7: AF SP4310N | G7: =VLOOKUP(F7,Tables!D$2:E$12,2,FALSE) -> PTR | H7: 17099780 | I7: =SUM(S7-R7) -> 280 | J7: =SUM(U7-T7) -> 0 | K7: =SUM(I7*$P7) -> 7.336 | L7: =SUM(J7*$Q7) -> 0 | M7: =K7+L7 -> 7.336 | N7: T1128911219 | O7: 144.75.215.43 | P7: =IF(G7="MFP",Tables!B$2,Tables!B$5) -> 0.0262 | Q7: =IF(G7="MFP",Tables!B$3,Tables!B$6) -> 0.118 | R7: =VLOOKUP($N7,'Meter Read info'!$C$2:$G$249,2,"FALSE") -> 399 | S7: =VLOOKUP($N7,'Meter Read info'!$C$2:$G$249,3,"FALSE") -> 679 | T7: =VLOOKUP($N7,'Meter Read info'!$C$2:$G$249,4,"FALSE") -> 0 | U7: =VLOOKUP($N7,'Meter Read info'!$C$2:$G$249,5,"FALSE") -> 0
A8: Admissions | B8: 10_03_054_01100_5521 | C8: =VLOOKUP(B8,Tables!G$2:H$79,2,FALSE) -> Admissions Office | D8: 309 Letcher | E8: 302 | F8: AF SPC242DN | G8: =VLOOKUP(F8,Tables!D$2:E$12,2,FALSE) -> PTR | H8: 17099423 | I8: =SUM(S8-R8) -> 106 | J8: =SUM(U8-T8) -> 336 | K8: =SUM(I8*$P8) -> 2.7772 | L8: =SUM(J8*$Q8) -> 39.648 | M8: =K8+L8 -> 42.4252 | N8: T202P700463 | O8: 144.75.186.29 | P8: =IF(G8="MFP",Tables!B$2,Tables!B$5) -> 0.0262 | Q8: =IF(G8="MFP",Tables!B$3,Tables!B$6) -> 0.118 | R8: =VLOOKUP($N8,'Meter Read info'!$C$2:$G$249,2,"FALSE") -> 90 | S8: =VLOOKUP($N8,'Meter Read info'!$C$2:$G$249,3,"FALSE") -> 196 | T8: =VLOOKUP($N8,'Meter Read info'!$C$2:$G$249,4,"FALSE") -> 214 | U8: =VLOOKUP($N8,'Meter Read info'!$C$2:$G$249,5,"FALSE") -> 550
A9: Admissions | B9: 10_03_054_01100_5521 | C9: =VLOOKUP(B9,Tables!G$2:H$79,2,FALSE) -> Admissions Office | D9: 309 Letcher | E9: 306 | F9: AF SPC242DN | G9: =VLOOKUP(F9,Tables!D$2:E$12,2,FALSE) -> PTR | H9: 17099511 | I9: =SUM(S9-R9) -> 127 | J9: =SUM(U9-T9) -> 197 | K9: =SUM(I9*$P9) -> 3.3274 | L9: =SUM(J9*$Q9) -> 23.246 | M9: =K9+L9 -> 26.5734 | N9: T202P700465 | O9: 144.75.186.25 | P9: =IF(G9="MFP",Tables!B$2,Tables!B$5) -> 0.0262 | Q9: =IF(G9="MFP",Tables!B$3,Tables!B$6) -> 0.118 | R9: =VLOOKUP($N9,'Meter Read info'!$C$2:$G$249,2,"FALSE") -> 280 | S9: =VLOOKUP($N9,'Meter Read info'!$C$2:$G$249,3,"FALSE") -> 407 | T9: =VLOOKUP($N9,'Meter Read info'!$C$2:$G$249,4,"FALSE") -> 274 | U9: =VLOOKUP($N9,'Meter Read info'!$C$2:$G$249,5,"FALSE") -> 471
A10: Admissions | B10: 10_03_054_01100_5521 | C10: =VLOOKUP(B10,Tables!G$2:H$79,2,FALSE) -> Admissions Office | D10: 309 Letcher | E10: 306 | F10: AF SPC242DN | G10: =VLOOKUP(F10,Tables!D$2:E$12,2,FALSE) -> PTR | H10: 17099731 | I10: =SUM(S10-R10) -> 512 | J10: =SUM(U10-T10) -> 317 | K10: =SUM(I10*$P10) -> 13.4144 | L10: =SUM(J10*$Q10) -> 37.406 | M10: =K10+L10 -> 50.8204 | N10: T202P600637 | O10: 144.75.186.28 | P10: =IF(G10="MFP",Tables!B$2,Tables!B$5) -> 0.0262 | Q10: =IF(G10="MFP",Tables!B$3,Tables!B$6) -> 0.118 | R10: =VLOOKUP($N10,'Meter Read info'!$C$2:$G$249,2,"FALSE") -> 974 | S10: =VLOOKUP($N10,'Meter Read info'!$C$2:$G$249,3,"FALSE") -> 1486 | T10: =VLOOKUP($N10,'Meter Read info'!$C$2:$G$249,4,"FALSE") -> 225 | U10: =VLOOKUP($N10,'Meter Read info'!$C$2:$G$249,5,"FALSE") -> 542
B11: 10_03_054_01100_5521 Total | M11: =SUBTOTAL(9,M4:M10) -> 791.9574
A12: ADV | B12: 10_03_064_50550_5521 | C12: =VLOOKUP(B12,Tables!G$2:H$79,2,FALSE) -> Printer Services | D12: Carroll Hall | E12: 210C | F12: AF SP4310N | G12: =VLOOKUP(F12,Tables!D$2:E$12,2,FALSE) -> PTR | H12: 17099562 | I12: =SUM(S12-R12) -> 266 | J12: =SUM(U12-T12) -> 0 | K12: =SUM(I12*$P12) -> 6.9692 | L12: =SUM(J12*$Q12) -> 0 | M12: =K12+L12 -> 6.9692 | N12: T1128911292 | O12: 144.75.195.20 | P12: =IF(G12="MFP",Tables!B$2,Tables!B$5) -> 0.0262 | Q12: =IF(G12="MFP",Tables!B$3,Tables!B$6) -> 0.118 | R12: =VLOOKUP($N12,'Meter Read info'!$C$2:$G$249,2,"FALSE") -> 3297 | S12: =VLOOKUP($N12,'Meter Read info'!$C$2:$G$249,3,"FALSE") -> 3563 | T12: =VLOOKUP($N12,'Meter Read info'!$C$2:$G$249,4,"FALSE") -> 0 | U12: =VLOOKUP($N12,'Meter Read info'!$C$2:$G$249,5,"FALSE") -> 0
B13: 10_03_064_50550_5521 Total | M13: =SUBTOTAL(9,M12:M12) -> 6.9692
A14: Air Force Rotc | B14: 10_03_011_02100_5521 | C14: =VLOOKUP(B14,Tables!G$2:H$79,2,FALSE) -> ROTC-Air Force | D14: Kilbourne Hall | E14: 2012 | F14: AF SP4310N | G14: =VLOOKUP(F14,Tables!D$2:E$12,2,FALSE) -> PTR | H14: 17099443 | I14: =SUM(S14-R14) -> 0 | J14: =SUM(U14-T14) -> 0 | K14: =SUM(I14*$P14) -> 0 | L14: =SUM(J14*$Q14) -> 0 | M14: =K14+L14 -> 0 | N14: T1129010871 | O14: 144.75.187.135 | P14: =IF(G14="MFP",Tables!B$2,Tables!B$5) -> 0.0262 | Q14: =IF(G14="MFP",Tables!B$3,Tables!B$6) -> 0.118 | R14: =VLOOKUP($N14,'Meter Read info'!$C$2:$G$249,2,"FALSE") -> 319 | S14: =VLOOKUP($N14,'Meter Read info'!$C$2:$G$249,3,"FALSE") -> 319 | T14: =VLOOKUP($N14,'Meter Read info'!$C$2:$G$249,4,"FALSE") -> 0 | U14: =VLOOKUP($N14,'Meter Read info'!$C$2:$G$249,5,"FALSE") -> 0
A15: Air Force Rotc | B15: 10_03_011_02100_5521 | C15: =VLOOKUP(B15,Tables!G$2:H$79,2,FALSE) -> ROTC-Air Force | D15: Kilbourne Hall | E15: 2018 | F15: AF SP4310N | G15: =VLOOKUP(F15,Tables!D$2:E$12,2,FALSE) -> PTR | H15: 17099438 | I15: =SUM(S15-R15) -> 0 | J15: =SUM(U15-T15) -> 0 | K15: =SUM(I15*$P15) -> 0 | L15: =SUM(J15*$Q15) -> 0 | M15: =K15+L15 -> 0 | N15: T1129010832 | O15: 144.75.187.138 | P15: =IF(G15="MFP",Tables!B$2,Tables!B$5) -> 0.0262 | Q15: =IF(G15="MFP",Tables!B$3,Tables!B$6) -> 0.118 | R15: =VLOOKUP($N15,'Meter Read info'!$C$2:$G$249,2,"FALSE") -> 0 | S15: =VLOOKUP($N15,'Meter Read info'!$C$2:$G$249,3,"FALSE") -> 0 | T15: =VLOOKUP($N15,'Meter Read info'!$C$2:$G$249,4,"FALSE") -> 0 | U15: =VLOOKUP($N15,'Meter Read info'!$C$2:$G$249,5,"FALSE") -> 0
B16: 10_03_011_02100_5521 Total | M16: =SUBTOTAL(9,M14:M15) -> 0
A17: Army Rotc | B17: 10_03_011_04100_5521 | C17: =VLOOKUP(B17,Tables!G$2:H$79,2,FALSE) -> ROTC-Army | D17: Kilbourne Hall | E17: 2022 | F17: AF MPC3502 | G17: =VLOOKUP(F17,Tables!D$2:E$12,2,FALSE) -> MFP | H17: 17099434 | I17: =SUM(S17-R17) -> 10585 | J17: =SUM(U17-T17) -> 1754 | K17: =SUM(I17*$P17) -> 219.1095 | L17: =SUM(J17*$Q17) -> 152.598 | M17: =K17+L17 -> 371.7075 | N17: W502L600854 | O17: 144.75.187.122 | P17: =IF(G17="MFP",Tables!B$2,Tables!B$5) -> 0.0207 | Q17: =IF(G17="MFP",Tables!B$3,Tables!B$6) -> 0.087 | R17: =VLOOKUP($N17,'Meter Read info'!$C$2:$G$249,2,"FALSE") -> 64703 | S17: =VLOOKUP($N17,'Meter Read info'!$C$2:$G$249,3,"FALSE") -> 75288 | T17: =VLOOKUP($N17,'Meter Read info'!$C$2:$G$249,4,"FALSE") -> 5655 | U17: =VLOOKUP($N17,'Meter Read info'!$C$2:$G$249,5,"FALSE") -> 7409
A18: Army Rotc | B18: 10_03_011_04100_5521 | C18: =VLOOKUP(B18,Tables!G$2:H$79,2,FALSE) -> ROTC-Army | D18: Kilbourne Hall | E18: 2023 | F18: AF SP4310N | G18: =VLOOKUP(F18,Tables!D$2:E$12,2,FALSE) -> PTR | H18: 17099435 | I18: =SUM(S18-R18) -> 116 | J18: =SUM(U18-T18) -> 0 | K18: =SUM(I18*$P18) -> 3.0392 | L18: =SUM(J18*$Q18) -> 0 | M18: =K18+L18 -> 3.0392 | N18: T1129010902 | O18: 144.75.187.16 | P18: =IF(G18="MFP",Tables!B$2,Tables!B$5) -> 0.0262 | Q18: =IF(G18="MFP",Tables!B$3,Tables!B$6) -> 0.118 | R18: =VLOOKUP($N18,'Meter Read info'!$C$2:$G$249,2,"FALSE") -> 368 | S18: =VLOOKUP($N18,'Meter Read info'!$C$2:$G$249,3,"FALSE") -> 484 | T18: =VLOOKUP($N18,'Meter Read info'!$C$2:$G$249,4,"FALSE") -> 0 | U18: =VLOOKUP($N18,'Meter Read info'!$C$2:$G$249,5,"FALSE") -> 0
A19: Army Rotc | B19: 10_03_011_04100_5521 | C19: =VLOOKUP(B19,Tables!G$2:H$79,2,FALSE) -> ROTC-Army | D19: Kilbourne Hall | E19: 2029 | F19: AF SP4310N | G19: =VLOOKUP(F19,Tables!D$2:E$12,2,FALSE) -> PTR | H19: 17099446 | I19: =SUM(S19-R19) -> 29 | J19: =SUM(U19-T19) -> 0 | K19: =SUM(I19*$P19) -> 0.7598 | L19: =SUM(J19*$Q19) -> 0 | M19: =K19+L19 -> 0.7598 | N19: T1129010869 | O19: 144.75.187.137 | P19: =IF(G19="MFP",Tables!B$2,Tables!B$5) -> 0.0262 | Q19: =IF(G19="MFP",Tables!B$3,Tables!B$6) -> 0.118 | R19: =VLOOKUP($N19,'Meter Read info'!$C$2:$G$249,2,"FALSE") -> 276 | S19: =VLOOKUP($N19,'Meter Read info'!$C$2:$G$249,3,"FALSE") -> 305 | T19: =VLOOKUP($N19,'Meter Read info'!$C$2:$G$249,4,"FALSE") -> 0 | U19: =VLOOKUP($N19,'Meter Read info'!$C$2:$G$249,5,"FALSE") -> 0
A20: Army Rotc | B20: 10_03_011_04100_5521 | C20: =VLOOKUP(B20,Tables!G$2:H$79,2,FALSE) -> ROTC-Army | D20: Kilbourne Hall | E20: 2053 | F20: AF SP4310N | G20: =VLOOKUP(F20,Tables!D$2:E$12,2,FALSE) -> PTR | H20: 17099437 | I20: =SUM(S20-R20) -> 254 | J20: =SUM(U20-T20) -> 0 | K20: =SUM(I20*$P20) -> 6.6548 | L20: =SUM(J20*$Q20) -> 0 | M20: =K20+L20 -> 6.6548 | N20: T1129010748 | O20: 144.75.187.112 | P20: =IF(G20="MFP",Tables!B$2,Tables!B$5) -> 0.0262 | Q20: =IF(G20="MFP",Tables!B$3,Tables!B$6) -> 0.118 | R20: =VLOOKUP($N20,'Meter Read info'!$C$2:$G$249,2,"FALSE") -> 1086 | S20: =VLOOKUP($N20,'Meter Read info'!$C$2:$G$249,3,"FALSE") -> 1340 | T20: =VLOOKUP($N20,'Meter Read info'!$C$2:$G$249,4,"FALSE") -> 0 | U20: =VLOOKUP($N20,'Meter Read info'!$C$2:$G$249,5,"FALSE") -> 0
A21: Army Rotc | B21: 10_03_011_04100_5521 | C21: =VLOOKUP(B21,Tables!G$2:H$79,2,FALSE) -> ROTC-Army | D21: Kilbourne Hall | E21: 2056 | F21: AF SP4310N | G21: =VLOOKUP(F21,Tables!D$2:E$12,2,FALSE) -> PTR | H21: 17099436 | I21: =SUM(S21-R21) -> 280 | J21: =SUM(U21-T21) -> 0 | K21: =SUM(I21*$P21) -> 7.336 | L21: =SUM(J21*$Q21) -> 0 | M21: =K21+L21 -> 7.336 | N21: T1129010837 | O21: 144.75.187.131 | P21: =IF(G21="MFP",Tables!B$2,Tables!B$5) -> 0.0262 | Q21: =IF(G21="MFP",Tables!B$3,Tables!B$6) -> 0.118 | R21: =VLOOKUP($N21,'Meter Read info'!$C$2:$G$249,2,"FALSE") -> 1616 | S21: =VLOOKUP($N21,'Meter Read info'!$C$2:$G$249,3,"FALSE") -> 1896 | T21: =VLOOKUP($N21,'Meter Read info'!$C$2:$G$249,4,"FALSE") -> 0 | U21: =VLOOKUP($N21,'Meter Read info'!$C$2:$G$249,5,"FALSE") -> 0
A22: Army Rotc | B22: 10_03_011_04100_5521 | C22: =VLOOKUP(B22,Tables!G$2:H$79,2,FALSE) -> ROTC-Army | D22: Kilbourne Hall | E22: 2057 | F22: AF SP4310N | G22: =VLOOKUP(F22,Tables!D$2:E$12,2,FALSE) -> PTR | H22: 17099444 | I22: =SUM(S22-R22) -> 749 | J22: =SUM(U22-T22) -> 0 | K22: =SUM(I22*$P22) -> 19.6238 | L22: =SUM(J22*$Q22) -> 0 | M22: =K22+L22 -> 19.6238 | N22: T1129010677 | O22: 144.75.187.133 | P22: =IF(G22="MFP",Tables!B$2,Tables!B$5) -> 0.0262 | Q22: =IF(G22="MFP",Tables!B$3,Tables!B$6) -> 0.118 | R22: =VLOOKUP($N22,'Meter Read info'!$C$2:$G$249,2,"FALSE") -> 2561 | S22: =VLOOKUP($N22,'Meter Read info'!$C$2:$G$249,3,"FALSE") -> 3310 | T22: =VLOOKUP($N22,'Meter Read info'!$C$2:$G$249,4,"FALSE") -> 0 | U22: =VLOOKUP($N22,'Meter Read info'!$C$2:$G$249,5,"FALSE") -> 0
A23: Army Rotc | B23: 10_03_011_04100_5521 | C23: =VLOOKUP(B23,Tables!G$2:H$79,2,FALSE) -> ROTC-Army | D23: Kilbourne Hall | E23: 2060 | F23: AF SP4310N | G23: =VLOOKUP(F23,Tables!D$2:E$12,2,FALSE) -> PTR | H23: 17099430 | I23: =SUM(S23-R23) -> 154 | J23: =SUM(U23-T23) -> 0 | K23: =SUM(I23*$P23) -> 4.0348 | L23: =SUM(J23*$Q23) -> 0 | M23: =K23+L23 -> 4.0348 | N23: T1129010760 | O23: 144.75.187.119 | P23: =IF(G23="MFP",Tables!B$2,Tables!B$5) -> 0.0262 | Q23: =IF(G23="MFP",Tables!B$3,Tables!B$6) -> 0.118 | R23: =VLOOKUP($N23,'Meter Read info'!$C$2:$G$249,2,"FALSE") -> 287 | S23: =VLOOKUP($N23,'Meter Read info'!$C$2:$G$249,3,"FALSE") -> 441 | T23: =VLOOKUP($N23,'Meter Read info'!$C$2:$G$249,4,"FALSE") -> 0 | U23: =VLOOKUP($N23,'Meter Read info'!$C$2:$G$249,5,"FALSE") -> 0
A24: Army Rotc | B24: 10_03_011_04100_5521 | C24: =VLOOKUP(B24,Tables!G$2:H$79,2,FALSE) -> ROTC-Army | D24: Kilbourne Hall | E24: 2061 | F24: AF SP4310N | G24: =VLOOKUP(F24,Tables!D$2:E$12,2,FALSE) -> PTR | H24: 17099442 | I24: =SUM(S24-R24) -> 395 | J24: =SUM(U24-T24) -> 0 | K24: =SUM(I24*$P24) -> 10.349 | L24: =SUM(J24*$Q24) -> 0 | M24: =K24+L24 -> 10.349 | N24: T1129010681 | O24: 144.75.187.136 | P24: =IF(G24="MFP",Tables!B$2,Tables!B$5) -> 0.0262 | Q24: =IF(G24="MFP",Tables!B$3,Tables!B$6) -> 0.118 | R24: =VLOOKUP($N24,'Meter Read info'!$C$2:$G$249,2,"FALSE") -> 503 | S24: =VLOOKUP($N24,'Meter Read info'!$C$2:$G$249,3,"FALSE") -> 898 | T24: =VLOOKUP($N24,'Meter Read info'!$C$2:$G$249,4,"FALSE") -> 0 | U24: =VLOOKUP($N24,'Meter Read info'!$C$2:$G$249,5,"FALSE") -> 0
A25: Army Rotc | B25: 10_03_011_04100_5521 | C25: =VLOOKUP(B25,Tables!G$2:H$79,2,FALSE) -> ROTC-Army | D25: Kilbourne Hall | E25: 2063 | F25: AF SP4310N | G25: =VLOOKUP(F25,Tables!D$2:E$12,2,FALSE) -> PTR | H25: 17099427 | I25: =SUM(S25-R25) -> 416 | J25: =SUM(U25-T25) -> 0 | K25: =SUM(I25*$P25) -> 10.8992 | L25: =SUM(J25*$Q25) -> 0 | M25: =K25+L25 -> 10.8992 | N25: T1129010874 | O25: 144.75.187.118 | P25: =IF(G25="MFP",Tables!B$2,Tables!B$5) -> 0.0262 | Q25: =IF(G25="MFP",Tables!B$3,Tables!B$6) -> 0.118 | R25: =VLOOKUP($N25,'Meter Read info'!$C$2:$G$249,2,"FALSE") -> 1059 | S25: =VLOOKUP($N25,'Meter Read info'!$C$2:$G$249,3,"FALSE") -> 1475 | T25: =VLOOKUP($N25,'Meter Read info'!$C$2:$G$249,4,"FALSE") -> 0 | U25: =VLOOKUP($N25,'Meter Read info'!$C$2:$G$249,5,"FALSE") -> 0
A26: Army Rotc | B26: 10_03_011_04100_5521 | C26: =VLOOKUP(B26,Tables!G$2:H$79,2,FALSE) -> ROTC-Army | D26: Kilbourne Hall | E26: 2064 | F26: AF SP4310N | G26: =VLOOKUP(F26,Tables!D$2:E$12,2,FALSE) -> PTR | H26: 17099439 | I26: =SUM(S26-R26) -> 164 | J26: =SUM(U26-T26) -> 0 | K26: =SUM(I26*$P26) -> 4.2968 | L26: =SUM(J26*$Q26) -> 0 | M26: =K26+L26 -> 4.2968 | N26: T1129010823 | O26: 144.75.187.140 | P26: =IF(G26="MFP",Tables!B$2,Tables!B$5) -> 0.0262 | Q26: =IF(G26="MFP",Tables!B$3,Tables!B$6) -> 0.118 | R26: =VLOOKUP($N26,'Meter Read info'!$C$2:$G$249,2,"FALSE") -> 747 | S26: =VLOOKUP($N26,'Meter Read info'!$C$2:$G$249,3,"FALSE") -> 911 | T26: =VLOOKUP($N26,'Meter Read info'!$C$2:$G$249,4,"FALSE") -> 0 | U26: =VLOOKUP($N26,'Meter Read info'!$C$2:$G$249,5,"FALSE") -> 0
A27: Army Rotc | B27: 10_03_011_04100_5521 | C27: =VLOOKUP(B27,Tables!G$2:H$79,2,FALSE) -> ROTC-Army | D27: Kilbourne Hall | E27: 2066 | F27: AF SP4310N | G27: =VLOOKUP(F27,Tables!D$2:E$12,2,FALSE) -> PTR | H27: 17099426 | I27: =SUM(S27-R27) -> 55 | J27: =SUM(U27-T27) -> 0 | K27: =SUM(I27*$P27) -> 1.441 | L27: =SUM(J27*$Q27) -> 0 | M27: =K27+L27 -> 1.441 | N27: T1129010820 | O27: 144.75.187.121 | P27: =IF(G27="MFP",Tables!B$2,Tables!B$5) -> 0.0262 | Q27: =IF(G27="MFP",Tables!B$3,Tables!B$6) -> 0.118 | R27: =VLOOKUP($N27,'Meter Read info'!$C$2:$G$249,2,"FALSE") -> 329 | S27: =VLOOKUP($N27,'Meter Read info'!$C$2:$G$249,3,"FALSE") -> 384 | T27: =VLOOKUP($N27,'Meter Read info'!$C$2:$G$249,4,"FALSE") -> 0 | U27: =VLOOKUP($N27,'Meter Read info'!$C$2:$G$249,5,"FALSE") -> 0
A28: Army Rotc | B28: 10_03_011_04100_5521 | C28: =VLOOKUP(B28,Tables!G$2:H$79,2,FALSE) -> ROTC-Army | D28: Kilbourne Hall | E28: 2067 | F28: AF SP4310N | G28: =VLOOKUP(F28,Tables!D$2:E$12,2,FALSE) -> PTR | H28: 17099425 | I28: =SUM(S28-R28) -> 249 | J28: =SUM(U28-T28) -> 0 | K28: =SUM(I28*$P28) -> 6.5238 | L28: =SUM(J28*$Q28) -> 0 | M28: =K28+L28 -> 6.5238 | N28: T1129010889 | O28: 144.75.187.123 | P28: =IF(G28="MFP",Tables!B$2,Tables!B$5) -> 0.0262 | Q28: =IF(G28="MFP",Tables!B$3,Tables!B$6) -> 0.118 | R28: =VLOOKUP($N28,'Meter Read info'!$C$2:$G$249,2,"FALSE") -> 761 | S28: =VLOOKUP($N28,'Meter Read info'!$C$2:$G$249,3,"FALSE") -> 1010 | T28: =VLOOKUP($N28,'Meter Read info'!$C$2:$G$249,4,"FALSE") -> 0 | U28: =VLOOKUP($N28,'Meter Read info'!$C$2:$G$249,5,"FALSE") -> 0
A29: Army Rotc | B29: 10_03_011_04100_5521 | C29: =VLOOKUP(B29,Tables!G$2:H$79,2,FALSE) -> ROTC-Army | D29: Kilbourne Hall | E29: 2070 | F29: AF SP4310N | G29: =VLOOKUP(F29,Tables!D$2:E$12,2,FALSE) -> PTR | H29: 17099428 | I29: =SUM(S29-R29) -> 105 | J29: =SUM(U29-T29) -> 0 | K29: =SUM(I29*$P29) -> 2.751 | L29: =SUM(J29*$Q29) -> 0 | M29: =K29+L29 -> 2.751 | N29: T1129010900 | O29: 144.75.187.132 | P29: =IF(G29="MFP",Tables!B$2,Tables!B$5) -> 0.0262 | Q29: =IF(G29="MFP",Tables!B$3,Tables!B$6) -> 0.118 | R29: =VLOOKUP($N29,'Meter Read info'!$C$2:$G$249,2,"FALSE") -> 1042 | S29: =VLOOKUP($N29,'Meter Read info'!$C$2:$G$249,3,"FALSE") -> 1147 | T29: =VLOOKUP($N29,'Meter Read info'!$C$2:$G$249,4,"FALSE") -> 0 | U29: =VLOOKUP($N29,'Meter Read info'!$C$2:$G$249,5,"FALSE") -> 0
B30: 10_03_011_04100_5521 Total | M30: =SUBTOTAL(9,M17:M29) -> 449.4167
A31: Athletic Advising | B31: 40_00_052_06550_5521 | C31: =VLOOKUP(B31,Tables!G$2:H$79,2,FALSE) -> AOF - Academic Advising | D31: Carroll Hall | E31: 210 | F31: AF MPC2051 | G31: =VLOOKUP(F31,Tables!D$2:E$12,2,FALSE) -> MFP | H31: 17099459 | I31: =SUM(S31-R31) -> 8899 | J31: =SUM(U31-T31) -> 79 | K31: =SUM(I31*$P31) -> 184.2093 | L31: =SUM(J31*$Q31) -> 6.873 | M31: =K31+L31 -> 191.0823 | N31: V9725401429 | O31: 144.75.195.41 | P31: =IF(G31="MFP",Tables!B$2,Tables!B$5) -> 0.0207 | Q31: =IF(G31="MFP",Tables!B$3,Tables!B$6) -> 0.087 | R31: =VLOOKUP($N31,'Meter Read info'!$C$2:$G$249,2,"FALSE") -> 24087 | S31: =VLOOKUP($N31,'Meter Read info'!$C$2:$G$249,3,"FALSE") -> 32986 | T31: =VLOOKUP($N31,'Meter Read info'!$C$2:$G$249,4,"FALSE") -> 3089 | U31: =VLOOKUP($N31,'Meter Read info'!$C$2:$G$249,5,"FALSE") -> 3168
B32: 40_00_052_06550_5521 Total | M32: =SUBTOTAL(9,M31:M31) -> 191.0823
A33: Athletic Communications | B33: 30_00_310_06104_5521 | C33: =VLOOKUP(B33,Tables!G$2:H$79,2,FALSE) -> Sports Information | D33: Smith Hall | E33: 116 | F33: AF MP301SP | G33: =VLOOKUP(F33,Tables!D$2:E$12,2,FALSE) -> MFP | H33: 17099531 | I33: =SUM(S33-R33) -> 1944 | J33: =SUM(U33-T33) -> 0 | K33: =SUM(I33*$P33) -> 40.2408 | L33: =SUM(J33*$Q33) -> 0 | M33: =K33+L33 -> 40.2408 | N33: W912P602286 | O33: 144.75.179.49 | P33: =IF(G33="MFP",Tables!B$2,Tables!B$5) -> 0.0207 | Q33: =IF(G33="MFP",Tables!B$3,Tables!B$6) -> 0.087 | R33: =VLOOKUP($N33,'Meter Read info'!$C$2:$G$249,2,"FALSE") -> 3693 | S33: =VLOOKUP($N33,'Meter Read info'!$C$2:$G$249,3,"FALSE") -> 5637 | T33: =VLOOKUP($N33,'Meter Read info'!$C$2:$G$249,4,"FALSE") -> 0 | U33: =VLOOKUP($N33,'Meter Read info'!$C$2:$G$249,5,"FALSE") -> 0
B34: 30_00_310_06104_5521 Total | M34: =SUBTOTAL(9,M33:M33) -> 40.2408
A35: Athletics | B35: 30_00_310_06020_5521 | C35: =VLOOKUP(B35,Tables!G$2:H$79,2,FALSE) -> Track & Cross Country | D35: Cameron Hall | E35: 231 | F35: AF SP4310N | G35: =VLOOKUP(F35,Tables!D$2:E$12,2,FALSE) -> PTR | H35: 17099560 | I35: =SUM(S35-R35) -> 1013 | J35: =SUM(U35-T35) -> 0 | K35: =SUM(I35*$P35) -> 26.5406 | L35: =SUM(J35*$Q35) -> 0 | M35: =K35+L35 -> 26.5406 | N35: T1129010426 | O35: 144.75.183.68 | P35: =IF(G35="MFP",Tables!B$2,Tables!B$5) -> 0.0262 | Q35: =IF(G35="MFP",Tables!B$3,Tables!B$6) -> 0.118 | R35: =VLOOKUP($N35,'Meter Read info'!$C$2:$G$249,2,"FALSE") -> 2252 | S35: =VLOOKUP($N35,'Meter Read info'!$C$2:$G$249,3,"FALSE") -> 3265 | T35: =VLOOKUP($N35,'Meter Read info'!$C$2:$G$249,4,"FALSE") -> 0 | U35: =VLOOKUP($N35,'Meter Read info'!$C$2:$G$249,5,"FALSE") -> 0
B36: 30_00_310_06020_5521 Total | M36: =SUBTOTAL(9,M35:M35) -> 26.5406
A37: Athletics | B37: 30_00_310_06090_5521 | C37: =VLOOKUP(B37,Tables!G$2:H$79,2,FALSE) -> Soccer | D37: Cameron Hall | E37: 245 | F37: AF SP4310N | G37: =VLOOKUP(F37,Tables!D$2:E$12,2,FALSE) -> PTR | H37: 17099557 | I37: =SUM(S37-R37) -> 191 | J37: =SUM(U37-T37) -> 0 | K37: =SUM(I37*$P37) -> 5.0042 | L37: =SUM(J37*$Q37) -> 0 | M37: =K37+L37 -> 5.0042 | N37: T1129010429 | O37: 144.75.183.65 | P37: =IF(G37="MFP",Tables!B$2,Tables!B$5) -> 0.0262 | Q37: =IF(G37="MFP",Tables!B$3,Tables!B$6) -> 0.118 | R37: =VLOOKUP($N37,'Meter Read info'!$C$2:$G$249,2,"FALSE") -> 692 | S37: =VLOOKUP($N37,'Meter Read info'!$C$2:$G$249,3,"FALSE") -> 883 | T37: =VLOOKUP($N37,'Meter Read info'!$C$2:$G$249,4,"FALSE") -> 0 | U37: =VLOOKUP($N37,'Meter Read info'!$C$2:$G$249,5,"FALSE") -> 0
B38: 30_00_310_06090_5521 Total | M38: =SUBTOTAL(9,M37:M37) -> 5.0042
A39: Athletics | B39: 30_00_310_06095_5521 | C39: =VLOOKUP(B39,Tables!G$2:H$79,2,FALSE) -> Soccer - Women | D39: Cameron Hall | E39: 239 | F39: AF SP4310N | G39: =VLOOKUP(F39,Tables!D$2:E$12,2,FALSE) -> PTR | H39: 17099565 | I39: =SUM(S39-R39) -> 173 | J39: =SUM(U39-T39) -> 0 | K39: =SUM(I39*$P39) -> 4.5326 | L39: =SUM(J39*$Q39) -> 0 | M39: =K39+L39 -> 4.5326 | N39: T1129010419 | O39: 144.75.183.69 | P39: =IF(G39="MFP",Tables!B$2,Tables!B$5) -> 0.0262 | Q39: =IF(G39="MFP",Tables!B$3,Tables!B$6) -> 0.118 | R39: =VLOOKUP($N39,'Meter Read info'!$C$2:$G$249,2,"FALSE") -> 462 | S39: =VLOOKUP($N39,'Meter Read info'!$C$2:$G$249,3,"FALSE") -> 635 | T39: =VLOOKUP($N39,'Meter Read info'!$C$2:$G$249,4,"FALSE") -> 0 | U39: =VLOOKUP($N39,'Meter Read info'!$C$2:$G$249,5,"FALSE") -> 0
B40: 30_00_310_06095_5521 Total | M40: =SUBTOTAL(9,M39:M39) -> 4.5326
A41: Athletics | B41: 30_00_310_06110_5521 | C41: =VLOOKUP(B41,Tables!G$2:H$79,2,FALSE) -> Administrative | D41: Cameron Hall | E41: 204 | F41: AF MP301SP | G41: =VLOOKUP(F41,Tables!D$2:E$12,2,FALSE) -> MFP | H41: 17099507 | I41: =SUM(S41-R41) -> 2470 | J41: =SUM(U41-T41) -> 0 | K41: =SUM(I41*$P41) -> 51.129 | L41: =SUM(J41*$Q41) -> 0 | M41: =K41+L41 -> 51.129 | N41: W912P602280 | O41: 144.75.183.73 | P41: =IF(G41="MFP",Tables!B$2,Tables!B$5) -> 0.0207 | Q41: =IF(G41="MFP",Tables!B$3,Tables!B$6) -> 0.087 | R41: =VLOOKUP($N41,'Meter Read info'!$C$2:$G$249,2,"FALSE") -> 9675 | S41: =VLOOKUP($N41,'Meter Read info'!$C$2:$G$249,3,"FALSE") -> 12145 | T41: =VLOOKUP($N41,'Meter Read info'!$C$2:$G$249,4,"FALSE") -> 0 | U41: =VLOOKUP($N41,'Meter Read info'!$C$2:$G$249,5,"FALSE") -> 0
A42: Athletics | B42: 30_00_310_06110_5521 | C42: =VLOOKUP(B42,Tables!G$2:H$79,2,FALSE) -> Administrative | D42: Cameron Hall | E42: 235 | F42: AF MPC6501 | G42: =VLOOKUP(F42,Tables!D$2:E$12,2,FALSE) -> MFP | H42: 17099490 | I42: =SUM(S42-R42) -> 8125 | J42: =SUM(U42-T42) -> 4871 | K42: =SUM(I42*$P42) -> 168.1875 | L42: =SUM(J42*$Q42) -> 423.777 | M42: =K42+L42 -> 591.9645 | N42: V7620400078 | O42: 144.75.183.56 | P42: =IF(G42="MFP",Tables!B$2,Tables!B$5) -> 0.0207 | Q42: =IF(G42="MFP",Tables!B$3,Tables!B$6) -> 0.087 | R42: =VLOOKUP($N42,'Meter Read info'!$C$2:$G$249,2,"FALSE") -> 26987 | S42: =VLOOKUP($N42,'Meter Read info'!$C$2:$G$249,3,"FALSE") -> 35112 | T42: =VLOOKUP($N42,'Meter Read info'!$C$2:$G$249,4,"FALSE") -> 8187 | U42: =VLOOKUP($N42,'Meter Read info'!$C$2:$G$249,5,"FALSE") -> 13058
A43: Athletics | B43: 30_00_310_06110_5521 | C43: =VLOOKUP(B43,Tables!G$2:H$79,2,FALSE) -> Administrative | D43: Cameron Hall | E43: 241 | F43: AF SP4310N | G43: =VLOOKUP(F43,Tables!D$2:E$12,2,FALSE) -> PTR | H43: 17099552 | I43: =SUM(S43-R43) -> 787 | J43: =SUM(U43-T43) -> 0 | K43: =SUM(I43*$P43) -> 20.6194 | L43: =SUM(J43*$Q43) -> 0 | M43: =K43+L43 -> 20.6194 | N43: T1129010427 | O43: 144.75.183.9 | P43: =IF(G43="MFP",Tables!B$2,Tables!B$5) -> 0.0262 | Q43: =IF(G43="MFP",Tables!B$3,Tables!B$6) -> 0.118 | R43: =VLOOKUP($N43,'Meter Read info'!$C$2:$G$249,2,"FALSE") -> 3109 | S43: =VLOOKUP($N43,'Meter Read info'!$C$2:$G$249,3,"FALSE") -> 3896 | T43: =VLOOKUP($N43,'Meter Read info'!$C$2:$G$249,4,"FALSE") -> 0 | U43: =VLOOKUP($N43,'Meter Read info'!$C$2:$G$249,5,"FALSE") -> 0
A44: Athletics | B44: 30_00_310_06110_5521 | C44: =VLOOKUP(B44,Tables!G$2:H$79,2,FALSE) -> Administrative | D44: Cameron Hall | E44: 242 | F44: AF SP4310N | G44: =VLOOKUP(F44,Tables!D$2:E$12,2,FALSE) -> PTR | H44: 17099553 | I44: =SUM(S44-R44) -> 263 | J44: =SUM(U44-T44) -> 0 | K44: =SUM(I44*$P44) -> 6.8906 | L44: =SUM(J44*$Q44) -> 0 | M44: =K44+L44 -> 6.8906 | N44: T1129010420 | O44: 144.75.183.64 | P44: =IF(G44="MFP",Tables!B$2,Tables!B$5) -> 0.0262 | Q44: =IF(G44="MFP",Tables!B$3,Tables!B$6) -> 0.118 | R44: =VLOOKUP($N44,'Meter Read info'!$C$2:$G$249,2,"FALSE") -> 847 | S44: =VLOOKUP($N44,'Meter Read info'!$C$2:$G$249,3,"FALSE") -> 1110 | T44: =VLOOKUP($N44,'Meter Read info'!$C$2:$G$249,4,"FALSE") -> 0 | U44: =VLOOKUP($N44,'Meter Read info'!$C$2:$G$249,5,"FALSE") -> 0
A45: Athletics | B45: 30_00_310_06110_5521 | C45: =VLOOKUP(B45,Tables!G$2:H$79,2,FALSE) -> Administrative | D45: Cameron Hall | E45: 302 | F45: AF MPC2051 | G45: =VLOOKUP(F45,Tables!D$2:E$12,2,FALSE) -> MFP | H45: 17099722 | I45: =SUM(S45-R45) -> 637 | J45: =SUM(U45-T45) -> 1486 | K45: =SUM(I45*$P45) -> 13.1859 | L45: =SUM(J45*$Q45) -> 129.282 | M45: =K45+L45 -> 142.4679 | N45: V9725401418 | O45: 144.75.183.52 | P45: =IF(G45="MFP",Tables!B$2,Tables!B$5) -> 0.0207 | Q45: =IF(G45="MFP",Tables!B$3,Tables!B$6) -> 0.087 | R45: =VLOOKUP($N45,'Meter Read info'!$C$2:$G$249,2,"FALSE") -> 5516 | S45: =VLOOKUP($N45,'Meter Read info'!$C$2:$G$249,3,"FALSE") -> 6153 | T45: =VLOOKUP($N45,'Meter Read info'!$C$2:$G$249,4,"FALSE") -> 12424 | U45: =VLOOKUP($N45,'Meter Read info'!$C$2:$G$249,5,"FALSE") -> 13910
A46: Athletics | B46: 30_00_310_06110_5521 | C46: =VLOOKUP(B46,Tables!G$2:H$79,2,FALSE) -> Administrative | D46: Cameron Hall | E46: 312 | F46: AF SP4310N | G46: =VLOOKUP(F46,Tables!D$2:E$12,2,FALSE) -> PTR | H46: 17099555 | I46: =SUM(S46-R46) -> 317 | J46: =SUM(U46-T46) -> 0 | K46: =SUM(I46*$P46) -> 8.3054 | L46: =SUM(J46*$Q46) -> 0 | M46: =K46+L46 -> 8.3054 | N46: T1129010428 | O46: 144.75.183.67 | P46: =IF(G46="MFP",Tables!B$2,Tables!B$5) -> 0.0262 | Q46: =IF(G46="MFP",Tables!B$3,Tables!B$6) -> 0.118 | R46: =VLOOKUP($N46,'Meter Read info'!$C$2:$G$249,2,"FALSE") -> 1256 | S46: =VLOOKUP($N46,'Meter Read info'!$C$2:$G$249,3,"FALSE") -> 1573 | T46: =VLOOKUP($N46,'Meter Read info'!$C$2:$G$249,4,"FALSE") -> 0 | U46: =VLOOKUP($N46,'Meter Read info'!$C$2:$G$249,5,"FALSE") -> 0
A47: Athletics | B47: 30_00_310_06110_5521 | C47: =VLOOKUP(B47,Tables!G$2:H$79,2,FALSE) -> Administrative | D47: Cameron Hall | E47: 314 | F47: AF SP4310N | G47: =VLOOKUP(F47,Tables!D$2:E$12,2,FALSE) -> PTR | H47: 17099558 | I47: =SUM(S47-R47) -> 586 | J47: =SUM(U47-T47) -> 0 | K47: =SUM(I47*$P47) -> 15.3532 | L47: =SUM(J47*$Q47) -> 0 | M47: =K47+L47 -> 15.3532 | N47: T1129010421 | O47: 144.75.183.62 | P47: =IF(G47="MFP",Tables!B$2,Tables!B$5) -> 0.0262 | Q47: =IF(G47="MFP",Tables!B$3,Tables!B$6) -> 0.118 | R47: =VLOOKUP($N47,'Meter Read info'!$C$2:$G$249,2,"FALSE") -> 1317 | S47: =VLOOKUP($N47,'Meter Read info'!$C$2:$G$249,3,"FALSE") -> 1903 | T47: =VLOOKUP($N47,'Meter Read info'!$C$2:$G$249,4,"FALSE") -> 0 | U47: =VLOOKUP($N47,'Meter Read info'!$C$2:$G$249,5,"FALSE") -> 0
A48: Athletics | B48: 30_00_310_06110_5521 | C48: =VLOOKUP(B48,Tables!G$2:H$79,2,FALSE) -> Administrative | D48: Cameron Hall | E48: 317 | F48: AF SP4310N | G48: =VLOOKUP(F48,Tables!D$2:E$12,2,FALSE) -> PTR | H48: 17099554 | I48: =SUM(S48-R48) -> 157 | J48: =SUM(U48-T48) -> 0 | K48: =SUM(I48*$P48) -> 4.1134 | L48: =SUM(J48*$Q48) -> 0 | M48: =K48+L48 -> 4.1134 | N48: T1129010385 | O48: 144.75.183.63 | P48: =IF(G48="MFP",Tables!B$2,Tables!B$5) -> 0.0262 | Q48: =IF(G48="MFP",Tables!B$3,Tables!B$6) -> 0.118 | R48: =VLOOKUP($N48,'Meter Read info'!$C$2:$G$249,2,"FALSE") -> 469 | S48: =VLOOKUP($N48,'Meter Read info'!$C$2:$G$249,3,"FALSE") -> 626 | T48: =VLOOKUP($N48,'Meter Read info'!$C$2:$G$249,4,"FALSE") -> 0 | U48: =VLOOKUP($N48,'Meter Read info'!$C$2:$G$249,5,"FALSE") -> 0
B49: 30_00_310_06110_5521 Total | M49: =SUBTOTAL(9,M41:M48) -> 840.8434
A50: Auxiliary Services | B50: 10_08_309_82115_5521 | C50: =VLOOKUP(B50,Tables!G$2:H$79,2,FALSE) -> Auxiliary Administration | D50: Cocke Hall | E50: 502 | F50: AF MPC2051 | G50: =VLOOKUP(F50,Tables!D$2:E$12,2,FALSE) -> MFP | H50: 17099424 | I50: =SUM(S50-R50) -> 1526 | J50: =SUM(U50-T50) -> 116 | K50: =SUM(I50*$P50) -> 31.5882 | L50: =SUM(J50*$Q50) -> 10.092 | M50: =K50+L50 -> 41.6802 | N50: V9725500651 | O50: 144.75.177.32 | P50: =IF(G50="MFP",Tables!B$2,Tables!B$5) -> 0.0207 | Q50: =IF(G50="MFP",Tables!B$3,Tables!B$6) -> 0.087 | R50: =VLOOKUP($N50,'Meter Read info'!$C$2:$G$249,2,"FALSE") -> 4051 | S50: =VLOOKUP($N50,'Meter Read info'!$C$2:$G$249,3,"FALSE") -> 5577 | T50: =VLOOKUP($N50,'Meter Read info'!$C$2:$G$249,4,"FALSE") -> 504 | U50: =VLOOKUP($N50,'Meter Read info'!$C$2:$G$249,5,"FALSE") -> 620
B51: 10_08_309_82115_5521 Total | M51: =SUBTOTAL(9,M50:M50) -> 41.6802
A52: Band | B52: 10_07_205_30200_5521 | C52: =VLOOKUP(B52,Tables!G$2:H$79,2,FALSE) -> UMA-Band | D52: Shell Hall | E52: 207 | F52: AF MP301SP | G52: =VLOOKUP(F52,Tables!D$2:E$12,2,FALSE) -> MFP | H52: 17099460 | I52: =SUM(S52-R52) -> 1280 | J52: =SUM(U52-T52) -> 0 | K52: =SUM(I52*$P52) -> 26.496 | L52: =SUM(J52*$Q52) -> 0 | M52: =K52+L52 -> 26.496 | N52: W912P602276 | O52: 144.75.180.76 | P52: =IF(G52="MFP",Tables!B$2,Tables!B$5) -> 0.0207 | Q52: =IF(G52="MFP",Tables!B$3,Tables!B$6) -> 0.087 | R52: =VLOOKUP($N52,'Meter Read info'!$C$2:$G$249,2,"FALSE") -> 4729 | S52: =VLOOKUP($N52,'Meter Read info'!$C$2:$G$249,3,"FALSE") -> 6009 | T52: =VLOOKUP($N52,'Meter Read info'!$C$2:$G$249,4,"FALSE") -> 0 | U52: =VLOOKUP($N52,'Meter Read info'!$C$2:$G$249,5,"FALSE") -> 0
B53: 10_07_205_30200_5521 Total | M53: =SUBTOTAL(9,M52:M52) -> 26.496
A54: Biology | B54: 10_03_064_50550_5521 | C54: =VLOOKUP(B54,Tables!G$2:H$79,2,FALSE) -> Printer Services | D54: Mallory Hall | E54: 214 | F54: AF SP4310N | G54: =VLOOKUP(F54,Tables!D$2:E$12,2,FALSE) -> PTR | H54: 17099580 | I54: =SUM(S54-R54) -> 173 | J54: =SUM(U54-T54) -> 0 | K54: =SUM(I54*$P54) -> 4.5326 | L54: =SUM(J54*$Q54) -> 0 | M54: =K54+L54 -> 4.5326 | N54: T1129011291 | O54: 144.75.182.5 | P54: =IF(G54="MFP",Tables!B$2,Tables!B$5) -> 0.0262 | Q54: =IF(G54="MFP",Tables!B$3,Tables!B$6) -> 0.118 | R54: =VLOOKUP($N54,'Meter Read info'!$C$2:$G$249,2,"FALSE") -> 2810 | S54: =VLOOKUP($N54,'Meter Read info'!$C$2:$G$249,3,"FALSE") -> 2983 | T54: =VLOOKUP($N54,'Meter Read info'!$C$2:$G$249,4,"FALSE") -> 0 | U54: =VLOOKUP($N54,'Meter Read info'!$C$2:$G$249,5,"FALSE") -> 0
A55: Biology | B55: 10_03_064_50550_5521 | C55: =VLOOKUP(B55,Tables!G$2:H$79,2,FALSE) -> Printer Services | D55: Maury Brooke | E55: 204A | F55: AF SP4310N | G55: =VLOOKUP(F55,Tables!D$2:E$12,2,FALSE) -> PTR | H55: 17099708 | I55: =SUM(S55-R55) -> 123 | J55: =SUM(U55-T55) -> 0 | K55: =SUM(I55*$P55) -> 3.2226 | L55: =SUM(J55*$Q55) -> 0 | M55: =K55+L55 -> 3.2226 | N55: T1129011358 | O55: 144.75.202.47 | P55: =IF(G55="MFP",Tables!B$2,Tables!B$5) -> 0.0262 | Q55: =IF(G55="MFP",Tables!B$3,Tables!B$6) -> 0.118 | R55: =VLOOKUP($N55,'Meter Read info'!$C$2:$G$249,2,"FALSE") -> 232 | S55: =VLOOKUP($N55,'Meter Read info'!$C$2:$G$249,3,"FALSE") -> 355 | T55: =VLOOKUP($N55,'Meter Read info'!$C$2:$G$249,4,"FALSE") -> 0 | U55: =VLOOKUP($N55,'Meter Read info'!$C$2:$G$249,5,"FALSE") -> 0
B56: 10_03_064_50550_5521 Total | M56: =SUBTOTAL(9,M54:M55) -> 7.7552
A57: Biology | B57: 40_00_011_10250_5521 | C57: =VLOOKUP(B57,Tables!G$2:H$79,2,FALSE) -> Carroll Biology Fund | D57: Maury Brooke | E57: 203 | F57: AF MPC2051 | G57: =VLOOKUP(F57,Tables!D$2:E$12,2,FALSE) -> MFP | H57: 17099484 | I57: =SUM(S57-R57) -> 3942 | J57: =SUM(U57-T57) -> 506 | K57: =SUM(I57*$P57) -> 81.5994 | L57: =SUM(J57*$Q57) -> 44.022 | M57: =K57+L57 -> 125.6214 | N57: V9725401445 | O57: 144.75.191.21 | P57: =IF(G57="MFP",Tables!B$2,Tables!B$5) -> 0.0207 | Q57: =IF(G57="MFP",Tables!B$3,Tables!B$6) -> 0.087 | R57: =VLOOKUP($N57,'Meter Read info'!$C$2:$G$249,2,"FALSE") -> 9957 | S57: =VLOOKUP($N57,'Meter Read info'!$C$2:$G$249,3,"FALSE") -> 13899 | T57: =VLOOKUP($N57,'Meter Read info'!$C$2:$G$249,4,"FALSE") -> 1174 | U57: =VLOOKUP($N57,'Meter Read info'!$C$2:$G$249,5,"FALSE") -> 1680
A58: Biology | B58: 40_00_011_10250_5521 | C58: =VLOOKUP(B58,Tables!G$2:H$79,2,FALSE) -> Carroll Biology Fund | D58: Maury Brooke | E58: 203 | F58: AF SP4310N | G58: =VLOOKUP(F58,Tables!D$2:E$12,2,FALSE) -> PTR | H58: 17099613 | I58: =SUM(S58-R58) -> 1013 | J58: =SUM(U58-T58) -> 0 | K58: =SUM(I58*$P58) -> 26.5406 | L58: =SUM(J58*$Q58) -> 0 | M58: =K58+L58 -> 26.5406 | N58: T1129011365 | O58: 144.75.202.56 | P58: =IF(G58="MFP",Tables!B$2,Tables!B$5) -> 0.0262 | Q58: =IF(G58="MFP",Tables!B$3,Tables!B$6) -> 0.118 | R58: =VLOOKUP($N58,'Meter Read info'!$C$2:$G$249,2,"FALSE") -> 4954 | S58: =VLOOKUP($N58,'Meter Read info'!$C$2:$G$249,3,"FALSE") -> 5967 | T58: =VLOOKUP($N58,'Meter Read info'!$C$2:$G$249,4,"FALSE") -> 0 | U58: =VLOOKUP($N58,'Meter Read info'!$C$2:$G$249,5,"FALSE") -> 0
A59: Biology | B59: 40_00_011_10250_5521 | C59: =VLOOKUP(B59,Tables!G$2:H$79,2,FALSE) -> Carroll Biology Fund | D59: Maury Brooke | E59: 203A | F59: AF SP4310N | G59: =VLOOKUP(F59,Tables!D$2:E$12,2,FALSE) -> PTR | H59: 17099611 | I59: =SUM(S59-R59) -> 803 | J59: =SUM(U59-T59) -> 0 | K59: =SUM(I59*$P59) -> 21.0386 | L59: =SUM(J59*$Q59) -> 0 | M59: =K59+L59 -> 21.0386 | N59: T1128911356 | O59: 144.75.202.51 | P59: =IF(G59="MFP",Tables!B$2,Tables!B$5) -> 0.0262 | Q59: =IF(G59="MFP",Tables!B$3,Tables!B$6) -> 0.118 | R59: =VLOOKUP($N59,'Meter Read info'!$C$2:$G$249,2,"FALSE") -> 2531 | S59: =VLOOKUP($N59,'Meter Read info'!$C$2:$G$249,3,"FALSE") -> 3334 | T59: =VLOOKUP($N59,'Meter Read info'!$C$2:$G$249,4,"FALSE") -> 0 | U59: =VLOOKUP($N59,'Meter Read info'!$C$2:$G$249,5,"FALSE") -> 0
A60: Biology | B60: 40_00_011_10250_5521 | C60: =VLOOKUP(B60,Tables!G$2:H$79,2,FALSE) -> Carroll Biology Fund | D60: Maury Brooke | E60: 203B | F60: AF SP4310N | G60: =VLOOKUP(F60,Tables!D$2:E$12,2,FALSE) -> PTR | H60: 17099569 | I60: =SUM(S60-R60) -> 100 | J60: =SUM(U60-T60) -> 0 | K60: =SUM(I60*$P60) -> 2.62 | L60: =SUM(J60*$Q60) -> 0 | M60: =K60+L60 -> 2.62 | N60: T1129011364 | O60: 144.75.202.58 | P60: =IF(G60="MFP",Tables!B$2,Tables!B$5) -> 0.0262 | Q60: =IF(G60="MFP",Tables!B$3,Tables!B$6) -> 0.118 | R60: =VLOOKUP($N60,'Meter Read info'!$C$2:$G$249,2,"FALSE") -> 361 | S60: =VLOOKUP($N60,'Meter Read info'!$C$2:$G$249,3,"FALSE") -> 461 | T60: =VLOOKUP($N60,'Meter Read info'!$C$2:$G$249,4,"FALSE") -> 0 | U60: =VLOOKUP($N60,'Meter Read info'!$C$2:$G$249,5,"FALSE") -> 0
A61: Biology | B61: 40_00_011_10250_5521 | C61: =VLOOKUP(B61,Tables!G$2:H$79,2,FALSE) -> Carroll Biology Fund | D61: Maury Brooke | E61: 203C | F61: AF SP4310N | G61: =VLOOKUP(F61,Tables!D$2:E$12,2,FALSE) -> PTR | H61: 17099612 | I61: =SUM(S61-R61) -> 17 | J61: =SUM(U61-T61) -> 0 | K61: =SUM(I61*$P61) -> 0.4454 | L61: =SUM(J61*$Q61) -> 0 | M61: =K61+L61 -> 0.4454 | N61: T1128911365 | O61: 144.75.202.44 | P61: =IF(G61="MFP",Tables!B$2,Tables!B$5) -> 0.0262 | Q61: =IF(G61="MFP",Tables!B$3,Tables!B$6) -> 0.118 | R61: =VLOOKUP($N61,'Meter Read info'!$C$2:$G$249,2,"FALSE") -> 530 | S61: =VLOOKUP($N61,'Meter Read info'!$C$2:$G$249,3,"FALSE") -> 547 | T61: =VLOOKUP($N61,'Meter Read info'!$C$2:$G$249,4,"FALSE") -> 0 | U61: =VLOOKUP($N61,'Meter Read info'!$C$2:$G$249,5,"FALSE") -> 0
A62: Biology | B62: 40_00_011_10250_5521 | C62: =VLOOKUP(B62,Tables!G$2:H$79,2,FALSE) -> Carroll Biology Fund | D62: Maury Brooke | E62: 203D | F62: AF SP4310N | G62: =VLOOKUP(F62,Tables!D$2:E$12,2,FALSE) -> PTR | H62: 17099568 | I62: =SUM(S62-R62) -> 484 | J62: =SUM(U62-T62) -> 0 | K62: =SUM(I62*$P62) -> 12.6808 | L62: =SUM(J62*$Q62) -> 0 | M62: =K62+L62 -> 12.6808 | N62: T1129011299 | O62: 144.75.202.57 | P62: =IF(G62="MFP",Tables!B$2,Tables!B$5) -> 0.0262 | Q62: =IF(G62="MFP",Tables!B$3,Tables!B$6) -> 0.118 | R62: =VLOOKUP($N62,'Meter Read info'!$C$2:$G$249,2,"FALSE") -> 0 | S62: =VLOOKUP($N62,'Meter Read info'!$C$2:$G$249,3,"FALSE") -> 484 | T62: =VLOOKUP($N62,'Meter Read info'!$C$2:$G$249,4,"FALSE") -> 0 | U62: =VLOOKUP($N62,'Meter Read info'!$C$2:$G$249,5,"FALSE") -> 0
B63: 40_00_011_10250_5521 Total | M63: =SUBTOTAL(9,M57:M62) -> 188.9468
A64: Business Office | B64: 10_03_062_16100_5521 | C64: =VLOOKUP(B64,Tables!G$2:H$79,2,FALSE) -> Business Executive | D64: Smith Hall | E64: 303 | F64: AF SPC242DN | G64: =VLOOKUP(F64,Tables!D$2:E$12,2,FALSE) -> PTR | H64: 17099513 | I64: =SUM(S64-R64) -> 408 | J64: =SUM(U64-T64) -> 951 | K64: =SUM(I64*$P64) -> 10.6896 | L64: =SUM(J64*$Q64) -> 112.218 | M64: =K64+L64 -> 122.9076 | N64: T202P700462 | O64: 144.75.179.112 | P64: =IF(G64="MFP",Tables!B$2,Tables!B$5) -> 0.0262 | Q64: =IF(G64="MFP",Tables!B$3,Tables!B$6) -> 0.118 | R64: =VLOOKUP($N64,'Meter Read info'!$C$2:$G$249,2,"FALSE") -> 933 | S64: =VLOOKUP($N64,'Meter Read info'!$C$2:$G$249,3,"FALSE") -> 1341 | T64: =VLOOKUP($N64,'Meter Read info'!$C$2:$G$249,4,"FALSE") -> 482 | U64: =VLOOKUP($N64,'Meter Read info'!$C$2:$G$249,5,"FALSE") -> 1433
A65: Business Office | B65: 10_03_062_16100_5521 | C65: =VLOOKUP(B65,Tables!G$2:H$79,2,FALSE) -> Business Executive | D65: Smith Hall | E65: 304 | F65: AF MPC3502 | G65: =VLOOKUP(F65,Tables!D$2:E$12,2,FALSE) -> MFP | H65: 17099529 | I65: =SUM(S65-R65) -> 5400 | J65: =SUM(U65-T65) -> 5406 | K65: =SUM(I65*$P65) -> 111.78 | L65: =SUM(J65*$Q65) -> 470.322 | M65: =K65+L65 -> 582.102 | N65: W502L600725 | O65: 144.75.179.35 | P65: =IF(G65="MFP",Tables!B$2,Tables!B$5) -> 0.0207 | Q65: =IF(G65="MFP",Tables!B$3,Tables!B$6) -> 0.087 | R65: =VLOOKUP($N65,'Meter Read info'!$C$2:$G$249,2,"FALSE") -> 15751 | S65: =VLOOKUP($N65,'Meter Read info'!$C$2:$G$249,3,"FALSE") -> 21151 | T65: =VLOOKUP($N65,'Meter Read info'!$C$2:$G$249,4,"FALSE") -> 11763 | U65: =VLOOKUP($N65,'Meter Read info'!$C$2:$G$249,5,"FALSE") -> 17169
B66: 10_03_062_16100_5521 Total | M66: =SUBTOTAL(9,M64:M65) -> 705.0096
A67: Business Office | B67: 10_03_062_16150_5521 | C67: =VLOOKUP(B67,Tables!G$2:H$79,2,FALSE) -> Institute Planning | D67: Smith Hall | E67: 303 | F67: AF SP4310N | G67: =VLOOKUP(F67,Tables!D$2:E$12,2,FALSE) -> PTR | H67: 17099709 | I67: =SUM(S67-R67) -> 310 | J67: =SUM(U67-T67) -> 0 | K67: =SUM(I67*$P67) -> 8.122 | L67: =SUM(J67*$Q67) -> 0 | M67: =K67+L67 -> 8.122 | N67: T1128911215 | O67: 144.75.179.115 | P67: =IF(G67="MFP",Tables!B$2,Tables!B$5) -> 0.0262 | Q67: =IF(G67="MFP",Tables!B$3,Tables!B$6) -> 0.118 | R67: =VLOOKUP($N67,'Meter Read info'!$C$2:$G$249,2,"FALSE") -> 1164 | S67: =VLOOKUP($N67,'Meter Read info'!$C$2:$G$249,3,"FALSE") -> 1474 | T67: =VLOOKUP($N67,'Meter Read info'!$C$2:$G$249,4,"FALSE") -> 0 | U67: =VLOOKUP($N67,'Meter Read info'!$C$2:$G$249,5,"FALSE") -> 0
B68: 10_03_062_16150_5521 Total | M68: =SUBTOTAL(9,M67:M67) -> 8.122
A69: Business Office | B69: 10_03_062_98100_5521 | C69: =VLOOKUP(B69,Tables!G$2:H$79,2,FALSE) -> Treasurers Office | D69: Smith Hall | E69: 303 | F69: AF SP4310N | G69: =VLOOKUP(F69,Tables!D$2:E$12,2,FALSE) -> PTR | H69: 17099711 | I69: =SUM(S69-R69) -> 2392 | J69: =SUM(U69-T69) -> 0 | K69: =SUM(I69*$P69) -> 62.6704 | L69: =SUM(J69*$Q69) -> 0 | M69: =K69+L69 -> 62.6704 | N69: T1128911216 | O69: 144.75.179.65 | P69: =IF(G69="MFP",Tables!B$2,Tables!B$5) -> 0.0262 | Q69: =IF(G69="MFP",Tables!B$3,Tables!B$6) -> 0.118 | R69: =VLOOKUP($N69,'Meter Read info'!$C$2:$G$249,2,"FALSE") -> 6929 | S69: =VLOOKUP($N69,'Meter Read info'!$C$2:$G$249,3,"FALSE") -> 9321 | T69: =VLOOKUP($N69,'Meter Read info'!$C$2:$G$249,4,"FALSE") -> 0 | U69: =VLOOKUP($N69,'Meter Read info'!$C$2:$G$249,5,"FALSE") -> 0
B70: 10_03_062_98100_5521 Total | M70: =SUBTOTAL(9,M69:M69) -> 62.6704
A71: Cadet Life | B71: 10_08_307_18380_5521 | C71: =VLOOKUP(B71,Tables!G$2:H$79,2,FALSE) -> Student Union | D71: Lejeune Hall | E71: 3115 | F71: AF MPC2051 | G71: =VLOOKUP(F71,Tables!D$2:E$12,2,FALSE) -> MFP | H71: 17099486 | I71: =SUM(S71-R71) -> 1517 | J71: =SUM(U71-T71) -> 230 | K71: =SUM(I71*$P71) -> 31.4019 | L71: =SUM(J71*$Q71) -> 20.01 | M71: =K71+L71 -> 51.4119 | N71: V9725401441 | O71: 144.75.209.65 | P71: =IF(G71="MFP",Tables!B$2,Tables!B$5) -> 0.0207 | Q71: =IF(G71="MFP",Tables!B$3,Tables!B$6) -> 0.087 | R71: =VLOOKUP($N71,'Meter Read info'!$C$2:$G$249,2,"FALSE") -> 18920 | S71: =VLOOKUP($N71,'Meter Read info'!$C$2:$G$249,3,"FALSE") -> 20437 | T71: =VLOOKUP($N71,'Meter Read info'!$C$2:$G$249,4,"FALSE") -> 526 | U71: =VLOOKUP($N71,'Meter Read info'!$C$2:$G$249,5,"FALSE") -> 756
A72: Cadet Life | B72: 10_08_307_18380_5521 | C72: =VLOOKUP(B72,Tables!G$2:H$79,2,FALSE) -> Student Union | D72: Lejeune Hall | E72: 3116 | F72: AF SP4310N | G72: =VLOOKUP(F72,Tables!D$2:E$12,2,FALSE) -> PTR | H72: 17099717 | I72: =SUM(S72-R72) -> 1517 | J72: =SUM(U72-T72) -> 230 | K72: =SUM(I72*$P72) -> 39.7454 | L72: =SUM(J72*$Q72) -> 27.14 | M72: =K72+L72 -> 66.8854 | N72: V9725401441 | O72: 144.75.149.13 | P72: =IF(G72="MFP",Tables!B$2,Tables!B$5) -> 0.0262 | Q72: =IF(G72="MFP",Tables!B$3,Tables!B$6) -> 0.118 | R72: =VLOOKUP($N72,'Meter Read info'!$C$2:$G$249,2,"FALSE") -> 18920 | S72: =VLOOKUP($N72,'Meter Read info'!$C$2:$G$249,3,"FALSE") -> 20437 | T72: =VLOOKUP($N72,'Meter Read info'!$C$2:$G$249,4,"FALSE") -> 526 | U72: =VLOOKUP($N72,'Meter Read info'!$C$2:$G$249,5,"FALSE") -> 756
B73: 10_08_307_18380_5521 Total | M73: =SUBTOTAL(9,M71:M72) -> 118.2973
A74: Career Services / Financial Aid | B74: 10_03_053_20300_5521 | C74: =VLOOKUP(B74,Tables!G$2:H$79,2,FALSE) -> Career Services and Placement | D74: Carroll Hall | E74: 311 | F74: AF SP4310N | G74: =VLOOKUP(F74,Tables!D$2:E$12,2,FALSE) -> PTR | H74: 17099570 | I74: =SUM(S74-R74) -> 338 | J74: =SUM(U74-T74) -> 0 | K74: =SUM(I74*$P74) -> 8.8556 | L74: =SUM(J74*$Q74) -> 0 | M74: =K74+L74 -> 8.8556 | N74: T1128910754 | O74: 144.75.195.25 | P74: =IF(G74="MFP",Tables!B$2,Tables!B$5) -> 0.0262 | Q74: =IF(G74="MFP",Tables!B$3,Tables!B$6) -> 0.118 | R74: =VLOOKUP($N74,'Meter Read info'!$C$2:$G$249,2,"FALSE") -> 1566 | S74: =VLOOKUP($N74,'Meter Read info'!$C$2:$G$249,3,"FALSE") -> 1904 | T74: =VLOOKUP($N74,'Meter Read info'!$C$2:$G$249,4,"FALSE") -> 0 | U74: =VLOOKUP($N74,'Meter Read info'!$C$2:$G$249,5,"FALSE") -> 0
A75: Career Services / Financial Aid | B75: 10_03_053_20300_5521 | C75: =VLOOKUP(B75,Tables!G$2:H$79,2,FALSE) -> Career Services and Placement | D75: Carroll Hall | E75: 312 | F75: AF SP4310N | G75: =VLOOKUP(F75,Tables!D$2:E$12,2,FALSE) -> PTR | H75: 17099618 | I75: =SUM(S75-R75) -> 2261 | J75: =SUM(U75-T75) -> 0 | K75: =SUM(I75*$P75) -> 59.2382 | L75: =SUM(J75*$Q75) -> 0 | M75: =K75+L75 -> 59.2382 | N75: T1128911369 | O75: 144.75.195.109 | P75: =IF(G75="MFP",Tables!B$2,Tables!B$5) -> 0.0262 | Q75: =IF(G75="MFP",Tables!B$3,Tables!B$6) -> 0.118 | R75: =VLOOKUP($N75,'Meter Read info'!$C$2:$G$249,2,"FALSE") -> 4515 | S75: =VLOOKUP($N75,'Meter Read info'!$C$2:$G$249,3,"FALSE") -> 6776 | T75: =VLOOKUP($N75,'Meter Read info'!$C$2:$G$249,4,"FALSE") -> 0 | U75: =VLOOKUP($N75,'Meter Read info'!$C$2:$G$249,5,"FALSE") -> 0
A76: Career Services / Financial Aid | B76: 10_03_053_20300_5521 | C76: =VLOOKUP(B76,Tables!G$2:H$79,2,FALSE) -> Career Services and Placement | D76: Carroll Hall | E76: 313 | F76: AF SP4310N | G76: =VLOOKUP(F76,Tables!D$2:E$12,2,FALSE) -> PTR | H76: 17099617 | I76: =SUM(S76-R76) -> 200 | J76: =SUM(U76-T76) -> 0 | K76: =SUM(I76*$P76) -> 5.24 | L76: =SUM(J76*$Q76) -> 0 | M76: =K76+L76 -> 5.24 | N76: T1128911361 | O76: 144.75.195.81 | P76: =IF(G76="MFP",Tables!B$2,Tables!B$5) -> 0.0262 | Q76: =IF(G76="MFP",Tables!B$3,Tables!B$6) -> 0.118 | R76: =VLOOKUP($N76,'Meter Read info'!$C$2:$G$249,2,"FALSE") -> 483 | S76: =VLOOKUP($N76,'Meter Read info'!$C$2:$G$249,3,"FALSE") -> 683 | T76: =VLOOKUP($N76,'Meter Read info'!$C$2:$G$249,4,"FALSE") -> 0 | U76: =VLOOKUP($N76,'Meter Read info'!$C$2:$G$249,5,"FALSE") -> 0
B77: 10_03_053_20300_5521 Total | M77: =SUBTOTAL(9,M74:M76) -> 73.3338
A78: Career Services / Financial Aid | B78: 10_03_064_32145_5521 | C78: =VLOOKUP(B78,Tables!G$2:H$79,2,FALSE) -> Duplicating | D78: Carroll Hall | E78: 307 | F78: AF MPC6501 | G78: =VLOOKUP(F78,Tables!D$2:E$12,2,FALSE) -> MFP | H78: 17099454 | I78: =SUM(S78-R78) -> 15737 | J78: =SUM(U78-T78) -> 1894 | K78: =SUM(I78*$P78) -> 325.7559 | L78: =SUM(J78*$Q78) -> 164.778 | M78: =K78+L78 -> 490.5339 | N78: V7620400172 | O78: 144.75.195.225 | P78: =IF(G78="MFP",Tables!B$2,Tables!B$5) -> 0.0207 | Q78: =IF(G78="MFP",Tables!B$3,Tables!B$6) -> 0.087 | R78: =VLOOKUP($N78,'Meter Read info'!$C$2:$G$249,2,"FALSE") -> 154317 | S78: =VLOOKUP($N78,'Meter Read info'!$C$2:$G$249,3,"FALSE") -> 170054 | T78: =VLOOKUP($N78,'Meter Read info'!$C$2:$G$249,4,"FALSE") -> 9923 | U78: =VLOOKUP($N78,'Meter Read info'!$C$2:$G$249,5,"FALSE") -> 11817
B79: 10_03_064_32145_5521 Total | M79: =SUBTOTAL(9,M78:M78) -> 490.5339
A80: Center for Leadership & Ethics | B80: 30_00_045_61150_5521 | C80: =VLOOKUP(B80,Tables!G$2:H$79,2,FALSE) -> Center for Leadership & Ethics | D80: Center for Leadership & Ethics | E80: 201 | F80: AF MPC2051 | G80: =VLOOKUP(F80,Tables!D$2:E$12,2,FALSE) -> MFP | H80: 17099534 | I80: =SUM(S80-R80) -> 2018 | J80: =SUM(U80-T80) -> 1079 | K80: =SUM(I80*$P80) -> 41.7726 | L80: =SUM(J80*$Q80) -> 93.873 | M80: =K80+L80 -> 135.6456 | N80: V9725400756 | O80: 144.75.215.6 | P80: =IF(G80="MFP",Tables!B$2,Tables!B$5) -> 0.0207 | Q80: =IF(G80="MFP",Tables!B$3,Tables!B$6) -> 0.087 | R80: =VLOOKUP($N80,'Meter Read info'!$C$2:$G$249,2,"FALSE") -> 9433 | S80: =VLOOKUP($N80,'Meter Read info'!$C$2:$G$249,3,"FALSE") -> 11451 | T80: =VLOOKUP($N80,'Meter Read info'!$C$2:$G$249,4,"FALSE") -> 6246 | U80: =VLOOKUP($N80,'Meter Read info'!$C$2:$G$249,5,"FALSE") -> 7325
A81: Center for Leadership & Ethics | B81: 30_00_045_61150_5521 | C81: =VLOOKUP(B81,Tables!G$2:H$79,2,FALSE) -> Center for Leadership & Ethics | D81: Center for Leadership & Ethics | E81: 201 | F81: AF SP4310N | G81: =VLOOKUP(F81,Tables!D$2:E$12,2,FALSE) -> PTR | H81: 17099602 | I81: =SUM(S81-R81) -> 823 | J81: =SUM(U81-T81) -> 0 | K81: =SUM(I81*$P81) -> 21.5626 | L81: =SUM(J81*$Q81) -> 0 | M81: =K81+L81 -> 21.5626 | N81: T1129012327 | O81: 144.75.215.10 | P81: =IF(G81="MFP",Tables!B$2,Tables!B$5) -> 0.0262 | Q81: =IF(G81="MFP",Tables!B$3,Tables!B$6) -> 0.118 | R81: =VLOOKUP($N81,'Meter Read info'!$C$2:$G$249,2,"FALSE") -> 3623 | S81: =VLOOKUP($N81,'Meter Read info'!$C$2:$G$249,3,"FALSE") -> 4446 | T81: =VLOOKUP($N81,'Meter Read info'!$C$2:$G$249,4,"FALSE") -> 0 | U81: =VLOOKUP($N81,'Meter Read info'!$C$2:$G$249,5,"FALSE") -> 0
A82: Center for Leadership & Ethics | B82: 30_00_045_61150_5521 | C82: =VLOOKUP(B82,Tables!G$2:H$79,2,FALSE) -> Center for Leadership & Ethics | D82: Center for Leadership & Ethics | E82: 201 | F82: AF SP4310N | G82: =VLOOKUP(F82,Tables!D$2:E$12,2,FALSE) -> PTR | H82: 17099694 | I82: =SUM(S82-R82) -> 72 | J82: =SUM(U82-T82) -> 0 | K82: =SUM(I82*$P82) -> 1.8864 | L82: =SUM(J82*$Q82) -> 0 | M82: =K82+L82 -> 1.8864 | N82: T1129011351 | O82: 144.75.215.30 | P82: =IF(G82="MFP",Tables!B$2,Tables!B$5) -> 0.0262 | Q82: =IF(G82="MFP",Tables!B$3,Tables!B$6) -> 0.118 | R82: =VLOOKUP($N82,'Meter Read info'!$C$2:$G$249,2,"FALSE") -> 96 | S82: =VLOOKUP($N82,'Meter Read info'!$C$2:$G$249,3,"FALSE") -> 168 | T82: =VLOOKUP($N82,'Meter Read info'!$C$2:$G$249,4,"FALSE") -> 0 | U82: =VLOOKUP($N82,'Meter Read info'!$C$2:$G$249,5,"FALSE") -> 0
B83: 30_00_045_61150_5521 Total | M83: =SUBTOTAL(9,M80:M82) -> 159.0946
A84: Chaplains Office | B84: 10_07_205_24100_5521 | C84: =VLOOKUP(B84,Tables!G$2:H$79,2,FALSE) -> UMA-Counselors Office | D84: Old Hospital | E84: 202 | F84: AF MP301SP | G84: =VLOOKUP(F84,Tables!D$2:E$12,2,FALSE) -> MFP | H84: 17099532 | I84: =SUM(S84-R84) -> 1891 | J84: =SUM(U84-T84) -> 0 | K84: =SUM(I84*$P84) -> 39.1437 | L84: =SUM(J84*$Q84) -> 0 | M84: =K84+L84 -> 39.1437 | N84: W912P601485 | O84: 144.75.180.73 | P84: =IF(G84="MFP",Tables!B$2,Tables!B$5) -> 0.0207 | Q84: =IF(G84="MFP",Tables!B$3,Tables!B$6) -> 0.087 | R84: =VLOOKUP($N84,'Meter Read info'!$C$2:$G$249,2,"FALSE") -> 3880 | S84: =VLOOKUP($N84,'Meter Read info'!$C$2:$G$249,3,"FALSE") -> 5771 | T84: =VLOOKUP($N84,'Meter Read info'!$C$2:$G$249,4,"FALSE") -> 0 | U84: =VLOOKUP($N84,'Meter Read info'!$C$2:$G$249,5,"FALSE") -> 0
B85: 10_07_205_24100_5521 Total | M85: =SUBTOTAL(9,M84:M84) -> 39.1437
A86: Chemistry | B86: 10_03_011_26100_5521 | C86: =VLOOKUP(B86,Tables!G$2:H$79,2,FALSE) -> Chemistry | D86: Maury Brooke | E86: 303 | F86: AF SP4310N | G86: =VLOOKUP(F86,Tables!D$2:E$12,2,FALSE) -> PTR | H86: 17099615 | I86: =SUM(S86-R86) -> 1567 | J86: =SUM(U86-T86) -> 0 | K86: =SUM(I86*$P86) -> 41.0554 | L86: =SUM(J86*$Q86) -> 0 | M86: =K86+L86 -> 41.0554 | N86: T1129011366 | O86: 144.75.202.14 | P86: =IF(G86="MFP",Tables!B$2,Tables!B$5) -> 0.0262 | Q86: =IF(G86="MFP",Tables!B$3,Tables!B$6) -> 0.118 | R86: =VLOOKUP($N86,'Meter Read info'!$C$2:$G$249,2,"FALSE") -> 6979 | S86: =VLOOKUP($N86,'Meter Read info'!$C$2:$G$249,3,"FALSE") -> 8546 | T86: =VLOOKUP($N86,'Meter Read info'!$C$2:$G$249,4,"FALSE") -> 0 | U86: =VLOOKUP($N86,'Meter Read info'!$C$2:$G$249,5,"FALSE") -> 0
A87: Chemistry | B87: 10_03_011_26100_5521 | C87: =VLOOKUP(B87,Tables!G$2:H$79,2,FALSE) -> Chemistry | D87: Maury Brooke | E87: 303E | F87: AF MPC3502 | G87: =VLOOKUP(F87,Tables!D$2:E$12,2,FALSE) -> MFP | H87: 17099462 | I87: =SUM(S87-R87) -> 12063 | J87: =SUM(U87-T87) -> 352 | K87: =SUM(I87*$P87) -> 249.7041 | L87: =SUM(J87*$Q87) -> 30.624 | M87: =K87+L87 -> 280.3281 | N87: W502L601221 | O87: 144.75.202.45 | P87: =IF(G87="MFP",Tables!B$2,Tables!B$5) -> 0.0207 | Q87: =IF(G87="MFP",Tables!B$3,Tables!B$6) -> 0.087 | R87: =VLOOKUP($N87,'Meter Read info'!$C$2:$G$249,2,"FALSE") -> 34366 | S87: =VLOOKUP($N87,'Meter Read info'!$C$2:$G$249,3,"FALSE") -> 46429 | T87: =VLOOKUP($N87,'Meter Read info'!$C$2:$G$249,4,"FALSE") -> 1033 | U87: =VLOOKUP($N87,'Meter Read info'!$C$2:$G$249,5,"FALSE") -> 1385
A88: Chemistry | B88: 10_03_011_26100_5521 | C88: =VLOOKUP(B88,Tables!G$2:H$79,2,FALSE) -> Chemistry | D88: Maury Brooke | E88: 403H | F88: AF SP4310N | G88: =VLOOKUP(F88,Tables!D$2:E$12,2,FALSE) -> PTR | H88: 17099616 | I88: =SUM(S88-R88) -> 2155 | J88: =SUM(U88-T88) -> 0 | K88: =SUM(I88*$P88) -> 56.461 | L88: =SUM(J88*$Q88) -> 0 | M88: =K88+L88 -> 56.461 | N88: T1129011350 | O88: 144.75.202.13 | P88: =IF(G88="MFP",Tables!B$2,Tables!B$5) -> 0.0262 | Q88: =IF(G88="MFP",Tables!B$3,Tables!B$6) -> 0.118 | R88: =VLOOKUP($N88,'Meter Read info'!$C$2:$G$249,2,"FALSE") -> 5102 | S88: =VLOOKUP($N88,'Meter Read info'!$C$2:$G$249,3,"FALSE") -> 7257 | T88: =VLOOKUP($N88,'Meter Read info'!$C$2:$G$249,4,"FALSE") -> 0 | U88: =VLOOKUP($N88,'Meter Read info'!$C$2:$G$249,5,"FALSE") -> 0
B89: 10_03_011_26100_5521 Total | M89: =SUBTOTAL(9,M86:M88) -> 377.8445
A90: Civil & Environmental Eng. | B90: 10_03_011_28100_5521 | C90: =VLOOKUP(B90,Tables!G$2:H$79,2,FALSE) -> Civil Engineering | D90: Nichols Hall | E90: 410 | F90: AF SP4310N | G90: =VLOOKUP(F90,Tables!D$2:E$12,2,FALSE) -> PTR | H90: 17099752 | I90: =SUM(S90-R90) -> 196 | J90: =SUM(U90-T90) -> 0 | K90: =SUM(I90*$P90) -> 5.1352 | L90: =SUM(J90*$Q90) -> 0 | M90: =K90+L90 -> 5.1352 | N90: T1128812156 | O90: 144.75.189.88 | P90: =IF(G90="MFP",Tables!B$2,Tables!B$5) -> 0.0262 | Q90: =IF(G90="MFP",Tables!B$3,Tables!B$6) -> 0.118 | R90: =VLOOKUP($N90,'Meter Read info'!$C$2:$G$249,2,"FALSE") -> 470 | S90: =VLOOKUP($N90,'Meter Read info'!$C$2:$G$249,3,"FALSE") -> 666 | T90: =VLOOKUP($N90,'Meter Read info'!$C$2:$G$249,4,"FALSE") -> 0 | U90: =VLOOKUP($N90,'Meter Read info'!$C$2:$G$249,5,"FALSE") -> 0
A91: Civil & Environmental Eng. | B91: 10_03_011_28100_5521 | C91: =VLOOKUP(B91,Tables!G$2:H$79,2,FALSE) -> Civil Engineering | D91: Nichols Hall | E91: 609 | F91: AF SP4310N | G91: =VLOOKUP(F91,Tables!D$2:E$12,2,FALSE) -> PTR | H91: 17099621 | I91: =SUM(S91-R91) -> 533 | J91: =SUM(U91-T91) -> 0 | K91: =SUM(I91*$P91) -> 13.9646 | L91: =SUM(J91*$Q91) -> 0 | M91: =K91+L91 -> 13.9646 | N91: T1129011096 | O91: 144.75.193.196 | P91: =IF(G91="MFP",Tables!B$2,Tables!B$5) -> 0.0262 | Q91: =IF(G91="MFP",Tables!B$3,Tables!B$6) -> 0.118 | R91: =VLOOKUP($N91,'Meter Read info'!$C$2:$G$249,2,"FALSE") -> 779 | S91: =VLOOKUP($N91,'Meter Read info'!$C$2:$G$249,3,"FALSE") -> 1312 | T91: =VLOOKUP($N91,'Meter Read info'!$C$2:$G$249,4,"FALSE") -> 0 | U91: =VLOOKUP($N91,'Meter Read info'!$C$2:$G$249,5,"FALSE") -> 0
A92: Civil & Environmental Eng. | B92: 10_03_011_28100_5521 | C92: =VLOOKUP(B92,Tables!G$2:H$79,2,FALSE) -> Civil Engineering | D92: Nichols Hall | E92: 609 | F92: AF MPC4502 | G92: =VLOOKUP(F92,Tables!D$2:E$12,2,FALSE) -> MFP | H92: 17099782 | I92: =SUM(S92-R92) -> 20795 | J92: =SUM(U92-T92) -> 276 | K92: =SUM(I92*$P92) -> 430.4565 | L92: =SUM(J92*$Q92) -> 24.012 | M92: =K92+L92 -> 454.4685 | N92: W512L700506 | O92: 144.75.193.90 | P92: =IF(G92="MFP",Tables!B$2,Tables!B$5) -> 0.0207 | Q92: =IF(G92="MFP",Tables!B$3,Tables!B$6) -> 0.087 | R92: =VLOOKUP($N92,'Meter Read info'!$C$2:$G$249,2,"FALSE") -> 86015 | S92: =VLOOKUP($N92,'Meter Read info'!$C$2:$G$249,3,"FALSE") -> 106810 | T92: =VLOOKUP($N92,'Meter Read info'!$C$2:$G$249,4,"FALSE") -> 23969 | U92: =VLOOKUP($N92,'Meter Read info'!$C$2:$G$249,5,"FALSE") -> 24245
A93: Civil & Environmental Eng. | B93: 10_03_011_28100_5521 | C93: =VLOOKUP(B93,Tables!G$2:H$79,2,FALSE) -> Civil Engineering | D93: Nichols Hall | E93: 410-445 | F93: AF SPC242DN | G93: =VLOOKUP(F93,Tables!D$2:E$12,2,FALSE) -> PTR | H93: 17099740 | I93: =SUM(S93-R93) -> 482 | J93: =SUM(U93-T93) -> 18 | K93: =SUM(I93*$P93) -> 12.6284 | L93: =SUM(J93*$Q93) -> 2.124 | M93: =K93+L93 -> 14.7524 | N93: T202P600371 | O93: 144.75.193.75 | P93: =IF(G93="MFP",Tables!B$2,Tables!B$5) -> 0.0262 | Q93: =IF(G93="MFP",Tables!B$3,Tables!B$6) -> 0.118 | R93: =VLOOKUP($N93,'Meter Read info'!$C$2:$G$249,2,"FALSE") -> 1031 | S93: =VLOOKUP($N93,'Meter Read info'!$C$2:$G$249,3,"FALSE") -> 1513 | T93: =VLOOKUP($N93,'Meter Read info'!$C$2:$G$249,4,"FALSE") -> 59 | U93: =VLOOKUP($N93,'Meter Read info'!$C$2:$G$249,5,"FALSE") -> 77
B94: 10_03_011_28100_5521 Total | M94: =SUBTOTAL(9,M90:M93) -> 488.3207
A95: Civil & Environmental Eng. | B95: 10_03_064_50550_5521 | C95: =VLOOKUP(B95,Tables!G$2:H$79,2,FALSE) -> Printer Services | D95: Nichols Hall | E95: 601 | F95: AF SP4310N | G95: =VLOOKUP(F95,Tables!D$2:E$12,2,FALSE) -> PTR | H95: 17099768 | I95: =SUM(S95-R95) -> 11138 | J95: =SUM(U95-T95) -> 0 | K95: =SUM(I95*$P95) -> 291.8156 | L95: =SUM(J95*$Q95) -> 0 | M95: =K95+L95 -> 291.8156 | N95: T1128811663 | O95: 144.75.193.42 | P95: =IF(G95="MFP",Tables!B$2,Tables!B$5) -> 0.0262 | Q95: =IF(G95="MFP",Tables!B$3,Tables!B$6) -> 0.118 | R95: =VLOOKUP($N95,'Meter Read info'!$C$2:$G$249,2,"FALSE") -> 50026 | S95: =VLOOKUP($N95,'Meter Read info'!$C$2:$G$249,3,"FALSE") -> 61164 | T95: =VLOOKUP($N95,'Meter Read info'!$C$2:$G$249,4,"FALSE") -> 0 | U95: =VLOOKUP($N95,'Meter Read info'!$C$2:$G$249,5,"FALSE") -> 0
B96: 10_03_064_50550_5521 Total | M96: =SUBTOTAL(9,M95:M95) -> 291.8156
A97: Commandant's Office | B97: 10_07_205_30150_5521 | C97: =VLOOKUP(B97,Tables!G$2:H$79,2,FALSE) -> UMA-Commandant's Office | D97: Old Barracks | E97: 1 | F97: AF MPC4502 | G97: =VLOOKUP(F97,Tables!D$2:E$12,2,FALSE) -> MFP | H97: 17099497 | I97: =SUM(S97-R97) -> 6635 | J97: =SUM(U97-T97) -> 962 | K97: =SUM(I97*$P97) -> 137.3445 | L97: =SUM(J97*$Q97) -> 83.694 | M97: =K97+L97 -> 221.0385 | N97: W512L601992 | O97: 144.75.190.18 | P97: =IF(G97="MFP",Tables!B$2,Tables!B$5) -> 0.0207 | Q97: =IF(G97="MFP",Tables!B$3,Tables!B$6) -> 0.087 | R97: =VLOOKUP($N97,'Meter Read info'!$C$2:$G$249,2,"FALSE") -> 23085 | S97: =VLOOKUP($N97,'Meter Read info'!$C$2:$G$249,3,"FALSE") -> 29720 | T97: =VLOOKUP($N97,'Meter Read info'!$C$2:$G$249,4,"FALSE") -> 4417 | U97: =VLOOKUP($N97,'Meter Read info'!$C$2:$G$249,5,"FALSE") -> 5379
A98: Commandant's Office | B98: 10_07_205_30150_5521 | C98: =VLOOKUP(B98,Tables!G$2:H$79,2,FALSE) -> UMA-Commandant's Office | D98: Old Barracks | E98: 131 | F98: AF SP4310N | G98: =VLOOKUP(F98,Tables!D$2:E$12,2,FALSE) -> PTR | H98: 17099704 | I98: =SUM(S98-R98) -> 732 | J98: =SUM(U98-T98) -> 0 | K98: =SUM(I98*$P98) -> 19.1784 | L98: =SUM(J98*$Q98) -> 0 | M98: =K98+L98 -> 19.1784 | N98: T1129012235 | O98: 144.75.190.21 | P98: =IF(G98="MFP",Tables!B$2,Tables!B$5) -> 0.0262 | Q98: =IF(G98="MFP",Tables!B$3,Tables!B$6) -> 0.118 | R98: =VLOOKUP($N98,'Meter Read info'!$C$2:$G$249,2,"FALSE") -> 2387 | S98: =VLOOKUP($N98,'Meter Read info'!$C$2:$G$249,3,"FALSE") -> 3119 | T98: =VLOOKUP($N98,'Meter Read info'!$C$2:$G$249,4,"FALSE") -> 0 | U98: =VLOOKUP($N98,'Meter Read info'!$C$2:$G$249,5,"FALSE") -> 0
A99: Commandant's Office | B99: 10_07_205_30150_5521 | C99: =VLOOKUP(B99,Tables!G$2:H$79,2,FALSE) -> UMA-Commandant's Office | D99: Old Barracks | E99: 135C | F99: AF SP4310N | G99: =VLOOKUP(F99,Tables!D$2:E$12,2,FALSE) -> PTR | H99: 17099703 | I99: =SUM(S99-R99) -> 3951 | J99: =SUM(U99-T99) -> 0 | K99: =SUM(I99*$P99) -> 103.5162 | L99: =SUM(J99*$Q99) -> 0 | M99: =K99+L99 -> 103.5162 | N99: T1129012232 | O99: 144.75.190.22 | P99: =IF(G99="MFP",Tables!B$2,Tables!B$5) -> 0.0262 | Q99: =IF(G99="MFP",Tables!B$3,Tables!B$6) -> 0.118 | R99: =VLOOKUP($N99,'Meter Read info'!$C$2:$G$249,2,"FALSE") -> 7041 | S99: =VLOOKUP($N99,'Meter Read info'!$C$2:$G$249,3,"FALSE") -> 10992 | T99: =VLOOKUP($N99,'Meter Read info'!$C$2:$G$249,4,"FALSE") -> 0 | U99: =VLOOKUP($N99,'Meter Read info'!$C$2:$G$249,5,"FALSE") -> 0
B100: 10_07_205_30150_5521 Total | M100: =SUBTOTAL(9,M97:M99) -> 343.7331
...

Sheet GL Summary
A3: Row Labels | B3: Sum of Device Total Click Charge
A4: Academic Advising | B4: 31.7758
A5: Administrative | B5: 848.1794
A6: Admissions Office | B6: 791.9574
A7: AOF - Academic Advising | B7: 191.0823
A8: Auxiliary Administration | B8: 41.6802
A9: AUX-Laundry & Pressing | B9: 32.6534
A10: AUX-Military Store | B10: 113.9497
A11: AUX-Student Health | B11: 217.8009
A12: AUX-Tailor Shop | B12: 26.4882
A13: Business Executive | B13: 720.1008
A14: Cameron Physics & Astronomy | B14: 394.4457
A15: Career Services and Placement | B15: 73.3338
... A68: #N/A | B68: 0
A69: (blank)
A70: Grand Total | B70: 19580.925

Sheet February 2013 - HP Toner
A1: Department | B1: General Ledger | C1: GL Description | D1: Building | E1: Room | F1: Model | G1: Device Type | H1: Ricoh Tag | I1: Toner Type | J1: Quantity | K1: Toner Cost Ea. | L1: Total Toner Cost | M1: Serial Number | N1: IP Address
A2: Superintendents House | B2: 10_03_061_94100_5521 | C2: =VLOOKUP(B2,Tables!G$2:H$79,2,FALSE) -> Superintendents Office | D2: Superintendents House | E2: Basement | F2: M2727 | G2: HP-MFP | H2: 17099735 | I2: Black | J2: 1 | K2: 25.32 | L2: =SUM(J2*K2) -> 25.32 | M2: CNG8961SWT | N2: 144.75.156.35
A3: Protocol | B3: 10_03_065_84100_5521 | C3: =VLOOKUP(B3,Tables!G$2:H$79,2,FALSE) -> Protocol Office | D3: 303 Letcher | E3: 300 | F3: 4650 | G3: HP-PTR | H3: 17099-732 | I3: Black | K3: 58.48 | L3: =SUM(J3*K3) -> 0 | M3: JPKAC48117 | N3: 144.75.178.14
A4: Protocol | B4: 10_03_065_84100_5521 | C4: =VLOOKUP(B4,Tables!G$2:H$79,2,FALSE) -> Protocol Office | D4: 303 Letcher | E4: 300 | F4: 4650 | G4: HP-PTR | H4: 17099-732 | I4: Cyan | K4: 58.48 | L4: =SUM(J4*K4) -> 0 | M4: JPKAC48117 | N4: 144.75.178.14
A5: Protocol | B5: 10_03_065_84100_5521 | C5: =VLOOKUP(B5,Tables!G$2:H$79,2,FALSE) -> Protocol Office | D5: 303 Letcher | E5: 300 | F5: 4650 | G5: HP-PTR | H5: 17099-732 | I5: Magenta | K5: 58.48 | L5: =SUM(J5*K5) -> 0 | M5: JPKAC48117 | N5: 144.75.178.14
A6: Protocol | B6: 10_03_065_84100_5521 | C6: =VLOOKUP(B6,Tables!G$2:H$79,2,FALSE) -> Protocol Office | D6: 303 Letcher | E6: 300 | F6: 4650 | G6: HP-PTR | H6: 17099-732 | I6: Yellow | K6: 58.48 | L6: =SUM(J6*K6) -> 0 | M6: JPKAC48117 | N6: 144.75.178.14
A7: Admissions | B7: 10_03_054_01100_5521 | C7: =VLOOKUP(B7,Tables!G$2:H$79,2,FALSE) -> Admissions Office | D7: 307 Letcher | E7: 204 | F7: CP4025 | G7: HP-PTR | H7: 17099781 | I7: Black | K7: 89.75 | L7: =SUM(J7*K7) -> 0 | M7: JPBCBBMOSG | N7: 144.75.215.29
A8: Admissions | B8: 10_03_054_01100_5521 | C8: =VLOOKUP(B8,Tables!G$2:H$79,2,FALSE) -> Admissions Office | D8: 307 Letcher | E8: 204 | F8: CP4025 | G8: HP-PTR | H8: 17099781 | I8: Cyan | K8: 91.49 | L8: =SUM(J8*K8) -> 0 | M8: JPBCBBMOSG | N8: 144.75.215.29
A9: Admissions | B9: 10_03_054_01100_5521 | C9: =VLOOKUP(B9,Tables!G$2:H$79,2,FALSE) -> Admissions Office | D9: 307 Letcher | E9: 204 | F9: CP4025 | G9: HP-PTR | H9: 17099781 | I9: Magenta | K9: 91.49 | L9: =SUM(J9*K9) -> 0 | M9: JPBCBBMOSG | N9: 144.75.215.29
A10: Admissions | B10: 10_03_054_01100_5521 | C10: =VLOOKUP(B10,Tables!G$2:H$79,2,FALSE) -> Admissions Office | D10: 307 Letcher | E10: 204 | F10: CP4025 | G10: HP-PTR | H10: 17099781 | I10: Yellow | K10: 91.49 | L10: =SUM(J10*K10) -> 0 | M10: JPBCBBMOSG | N10: 144.75.215.29
A11: Media Services | B11: 10_03_041_62100_5521 | C11: =VLOOKUP(B11,Tables!G$2:H$79,2,FALSE) -> Libraries | D11: Preston Library | E11: 406 | F11: LJ3600 | G11: HP-PTR | H11: 17099815 | I11: Black | K11: 53.82 | L11: =SUM(J11*K11) -> 0 | M11: CNWDF12176 | N11: 144.75.196.251
A12: Media Services | B12: 10_03_041_62100_5521 | C12: =VLOOKUP(B12,Tables!G$2:H$79,2,FALSE) -> Libraries | D12: Preston Library | E12: 406 | F12: LJ3600 | G12: HP-PTR | H12: 17099815 | I12: Cyan | K12: 61.89 | L12: =SUM(J12*K12) -> 0 | M12: CNWDF12177 | N12: 144.75.196.251
A13: Media Services | B13: 10_03_041_62100_5521 | C13: =VLOOKUP(B13,Tables!G$2:H$79,2,FALSE) -> Libraries | D13: Preston Library | E13: 406 | F13: LJ3600 | G13: HP-PTR | H13: 17099815 | I13: Magenta | K13: 61.89 | L13: =SUM(J13*K13) -> 0 | M13: CNWDF12178 | N13: 144.75.196.251
A14: Media Services | B14: 10_03_041_62100_5521 | C14: =VLOOKUP(B14,Tables!G$2:H$79,2,FALSE) -> Libraries | D14: Preston Library | E14: 406 | F14: LJ3600 | G14: HP-PTR | H14: 17099815 | I14: Yellow | K14: 61.89 | L14: =SUM(J14*K14) -> 0 | M14: CNWDF12179 | N14: 144.75.196.251
A15: Psychology & Philosophy | B15: 10_03_011_86100_5521 | C15: =VLOOKUP(B15,Tables!G$2:H$79,2,FALSE) -> Philosophy & Psychology | D15: Carroll Hall | E15: 403 | F15: LJ4005 | G15: HP-PTR | H15: 17099728 | I15: Black | K15: 74.18 | L15: =SUM(J15*K15) -> 0 | M15: JPRLB46624 | N15: 144.75.195.232
A16: Psychology & Philosophy | B16: 10_03_011_86100_5521 | C16: =VLOOKUP(B16,Tables!G$2:H$79,2,FALSE) -> Philosophy & Psychology | D16: Carroll Hall | E16: 403 | F16: LJ4005 | G16: HP-PTR | H16: 17099728 | I16: Cyan | K16: 76.19 | L16: =SUM(J16*K16) -> 0 | M16: JPRLB46625 | N16: 144.75.195.232
A17: Psychology & Philosophy | B17: 10_03_011_86100_5521 | C17: =VLOOKUP(B17,Tables!G$2:H$79,2,FALSE) -> Philosophy & Psychology | D17: Carroll Hall | E17: 403 | F17: LJ4005 | G17: HP-PTR | H17: 17099728 | I17: Magenta | K17: 76.19 | L17: =SUM(J17*K17) -> 0 | M17: JPRLB46626 | N17: 144.75.195.232
A18: Psychology & Philosophy | B18: 10_03_011_86100_5521 | C18: =VLOOKUP(B18,Tables!G$2:H$79,2,FALSE) -> Philosophy & Psychology | D18: Carroll Hall | E18: 403 | F18: LJ4005 | G18: HP-PTR | H18: 17099728 | I18: Yellow | K18: 76.19 | L18: =SUM(J18*K18) -> 0 | M18: JPRLB46627 | N18: 144.75.195.232
A19: Athletics | B19: 30_00_310_06090_5521 | C19: =VLOOKUP(B19,Tables!G$2:H$79,2,FALSE) -> Soccer | D19: Cameron Hall | E19: 345 | F19: LJ4005 | G19: HP-PTR | H19: 17099-828 | I19: Black | J19: 1 | K19: 74.18 | L19: =SUM(J19*K19) -> 74.18 | M19: JP4LC17284 | N19: Not on network
A20: Athletics | B20: 30_00_310_06090_5521 | C20: =VLOOKUP(B20,Tables!G$2:H$79,2,FALSE) -> Soccer | D20: Cameron Hall | E20: 345 | F20: LJ4005 | G20: HP-PTR | H20: 17099-828 | I20: Cyan | J20: 1 | K20: 76.19 | L20: =SUM(J20*K20) -> 76.19 | M20: JP4LC17284 | N20: Not on network
A21: Athletics | B21: 30_00_310_06090_5521 | C21: =VLOOKUP(B21,Tables!G$2:H$79,2,FALSE) -> Soccer | D21: Cameron Hall | E21: 345 | F21: LJ4005 | G21: HP-PTR | H21: 17099-828 | I21: Magenta | J21: 1 | K21: 76.19 | L21: =SUM(J21*K21) -> 76.19 | M21: JP4LC17284 | N21: Not on network
A22: Athletics | B22: 30_00_310_06090_5521 | C22: =VLOOKUP(B22,Tables!G$2:H$79,2,FALSE) -> Soccer | D22: Cameron Hall | E22: 345 | F22: LJ4005 | G22: HP-PTR | H22: 17099-828 | I22: Yellow | J22: 1 | K22: 76.19 | L22: =SUM(J22*K22) -> 76.19 | M22: JP4LC17284 | N22: Not on network
A23: Comptrollers | B23: 10_03_062_32100_5521 | C23: =VLOOKUP(B23,Tables!G$2:H$79,2,FALSE) -> Comptroller's Office | D23: Smith Hall | E23: 311 | F23: P3010 | G23: HP-PTR | H23: 17099745 | I23: Black | K23: 32.03 | L23: =SUM(J23*K23) -> 0 | M23: VNBCC4L0MD | N23: 144.75.179.5
A24: Comptrollers | B24: 10_03_062_32100_5521 | C24: =VLOOKUP(B24,Tables!G$2:H$79,2,FALSE) -> Comptroller's Office | D24: Smith Hall | E24: 320 | F24: P3010 | G24: HP-PTR | H24: 17099744 | I24: Black | K24: 32.03 | L24: =SUM(J24*K24) -> 0 | M24: VNBCC4L0M6 | N24: 144.75.179.31
K40: Total | L40: =SUM(L2:L25) -> 328.07

Sheet Totals
D2: B&W MFP | E2: Color MFP | F2: B/W MFD | G2: Color MFD | J2: B&W MFP | K2: Color MFP
C3: MFP: | D3: =SUMIF('February 2013 - Data'!G$2:$G$335,"MFP",'February 2013 - Data'!I$2:I$335) -> 422652 | E3: =SUMIF('February 2013 - Data'!G$2:$G$335,"MFP",'February 2013 - Data'!J$2:J$335) -> 58404 | F3: =SUM(D3)*D14 -> 8748.8964 | G3: =SUM(E3)*E14 -> 5081.148 | J3: =SUMIF('February 2013 - Data'!$G$2:G$335,"MFP",'February 2013 - Data'!K$2:K$335) -> 8748.8964 | K3: =SUMIF('February 2013 - Data'!$G$2:$G$335,"MFP",'February 2013 - Data'!L$2:L$335) -> 5081.148
D5: B&W Printer | E5: Color Printer | F5: B/W Printer | G5: Color Printer | J5: B&W Printer | K5: Color Printer
C6: Printer: | D6: =SUMIF('February 2013 - Data'!$G$2:$G$335,"PTR",'February 2013 - Data'!I2:I335) -> 199741 | E6: =SUMIF('February 2013 - Data'!$G2:$G$335,"PTR",'February 2013 - Data'!J$2:J$335) -> 4387 | F6: =SUM(D6)*D15 -> 5233.2142 | G6: =SUM(E6)*E15 -> 517.666 | J6: =SUMIF('February 2013 - Data'!$G$2:$G$335,"PTR",'February 2013 - Data'!K$2:K$335) -> 5233.2142 | K6: =SUMIF('February 2013 - Data'!$G$2:$G$335,"PTR",'February 2013 - Data'!L$2:L$335) -> 517.666
D8: Total B&W | E8: Total Color | F8: Total B&W | G8: Total Color | J8: Total B&W | K8: Total Color
C9: Total: | D9: =SUM(D3,D6) -> 622393 | E9: =SUM(E3,E6) -> 62791 | F9: =SUM(F3,F6) -> 13982.111 | G9: =ROUNDUP(G3+G6,2) -> 5598.82 | J9: =SUM(J3,J6) -> 13982.111 | K9: =ROUNDUP(K3+K6,2) -> 5598.82
F11: Total This Invoice: | G11: =(F9+G9) -> 19580.931 | J11: Total This Invoice: | K11: =SUM(J9+K9) -> 19580.931
F12: HP Toner: | G12: ='February 2013 - HP Toner'!L40 -> 328.07 | J12: Total Invoice w/ HP Toner: | K12: =G13 -> 19909.001
F13: Invoice Total | G13: =SUM(G11:G12) -> 19909.001
C14: MFP | D14: =Tables!B2 -> 0.0207 | E14: =Tables!B3 -> 0.087
C15: Printer | D15: =Tables!B5 -> 0.0262 | E15: =Tables!B6 -> 0.118
F18: MFP Total: | G18: =COUNTIF('February 2013 - Data'!G2:G335,"MFP") -> 63
F19: Printer Total: | G19: =COUNTIF('February 2013 - Data'!G2:G335,"PTR") -> 186
F20: Device Total: | G20: =SUM(G18:G19) -> 249

Sheet Tables
A1: Rates | D1: Devices | E1: Type | G1: GL # | H1: Description
A2: MFP B&W | B2: 0.0207 | D2: AF MP301SP | E2: MFP | G2: 10_03_054_60100_5521 | H2: Learning Programs
A3: MFP Color | B3: 0.087 | D3: AF MP4002 | E3: MFP | G3: 10_03_054_01100_5521 | H3: Admissions Office
D4: AF MP6001 | E4: MFP | G4: 10_03_011_02100_5521 | H4: ROTC-Air Force
A5: Printer B&W | B5: 0.0262 | D5: AF MPC2051 | E5: MFP | G5: 10_03_011_04100_5521 | H5: ROTC-Army
A6: Printer Color | B6: 0.118 | D6: AF MPC3502 | E6: MFP | G6: 30_00_310_06104_5521 | H6: Sports Information
D7: AF MPC4502 | E7: MFP | G7: 30_00_310_06095_5521 | H7: Soccer - Women
D8: AF MPC6501 | E8: MFP | G8: 30_00_310_06000_5521 | H8: Football
D9: AF SP4310N | E9: PTR | G9: 30_00_310_06090_5521 | H9: Soccer
D10: AF SPC242DN | E10: PTR | G10: 30_00_310_06010_5521 | H10: Basketball
D11: AF SPC430DN | E11: PTR | G11: 30_00_310_06020_5521 | H11: Track & Cross Country
D12: AF MPC5502 | E12: MFP | G12: 30_00_310_06110_5521 | H12: Administrative
G13: 40_00_052_06550_5521 | H13: AOF - Academic Advising
G14: 10_08_309_82115_5521 | H14: Auxiliary Administration
G15: 10_08_303_82240_5521 | H15: AUX-Laundry & Pressing
G16: 10_08_302_82230_5521 | H16: AUX-Tailor Shop
G17: 10_03_064_82140_5521 | H17: Post Mail
G18: 10_08_302_82190_5521 | H18: AUX-Military Store
G19: 40_00_011_10250_5521 | H19: Carroll Biology Fund
G20: 10_03_011_10100_5521 | H20: Biology
G21: 10_03_062_16100_5521 | H21: Business Executive
G22: 10_03_062_16150_5521 | H22: Institute Planning
G23: 10_08_307_18380_5521 | H23: Student Union
G24: 10_03_053_20300_5521 | H24: Career Services and Placement
... G79: 10_03_045_99200_5521 | H79: Institute Writing Program

Sheet Meter Read info
A1: Dept | B1: Equip ID | C1: Serial Number | D1: Total BW Begin Meter Read | E1: Total BW End Meter Read | F1: Total Color Begin Meter Read | G1: Total Color End Meter Read
A2: Information Technology | B2: 17099400 | C2: W512L601973 | D2: 23181 | E2: 26942 | F2: 2384 | G2: 2883
A3: Laundry | B3: 17099401 | C3: W912P602288 | D3: 4566 | E3: 6070 | F3: 0 | G3: 0
A4: Physical Plant | B4: 17099402 | C4: W912P602228 | D4: 4650 | E4: 6470 | F4: 0 | G4: 0
A5: International Studies | B5: 17099404 | C5: W542LB00047 | D5: 24677 | E5: 39625 | F5: 1530 | G5: 1530
A6: Modern Languages | B6: 17099405 | C6: W502LA00634 | D6: 13939 | E6: 26862 | F6: 879 | G6: 1314
A7: Post Police | B7: 17099406 | C7: W912P903531 | D7: 1558 | E7: 2432 | F7: 0 | G7: 0
A8: Career Services / Financial Aid | B8: 17099420 | C8: V7620400172 | D8: 154317 | E8: 170054 | F8: 9923 | G8: 11817
A9: Smith Hall | B9: 17099421 | C9: V7620500472 | D9: 34001 | E9: 45970 | F9: 51382 | G9: 65242
A10: Human Resources | B10: 17099422 | C10: T1129010803 | D10: 2309 | E10: 2916 | F10: 0 | G10: 0
A11: Admissions | B11: 17099423 | C11: T202P700463 | D11: 90 | E11: 196 | F11: 214 | G11: 550
A12: Auxiliary Services | B12: 17099424 | C12: V9725500651 | D12: 4051 | E12: 5577 | F12: 504 | G12: 620
A13: Army Rotc | B13: 17099425 | C13: T1129010889 | D13: 761 | E13: 1010 | F13: 0 | G13: 0
... A250: Modern Languages | B250: 17099405 | C250: W502LA00634 | D250: 13939 | E250: 26862 | F250: 879 | G250: 1314
