Workbook

Sheet Summary
A1: Community and Technical Colleges, Report of Fundable Operating Expenses, Fiscal Year (FY) 1999
A2: Summary of Expense divided Contact Hours
A3: Contact Hours for fall 1998 and spring and summer 1999
A4: Fund | B4: Total Expense by Discipline | D4: Contact Hours | E4: Expense | F4: Expense per Contact Hour
A5: 1 | B5: Agriculture | D5: =D36 -> 1156306 | E5: =E36+E67+IFERROR($E$105/$D$105*D5,0) -> 8858021.5 | F5: =F36+F67+$F$105 -> 6.81
A6: 2 | B6: Architecture and Precision Production Trades | D6: =D37 -> 5213661 | E6: =E37+E68+IFERROR($E$105/$D$105*D6,0) -> 34812484 | F6: =F37+F68+$F$105 -> 6.64
A7: 3 | B7: Biology, Physical Sciences, and Science Technology | D7: =D38 -> 18409138 | E7: =E38+E69+IFERROR($E$105/$D$105*D7,0) -> 1.0786112e+08 | F7: =F38+F69+$F$105 -> 5.51
A8: 4 | B8: Business Management, Marketing, and Administrative Services | D8: =D39 -> 15167456 | E8: =E39+E70+IFERROR($E$105/$D$105*D8,0) -> 1.0390477e+08 | F8: =F39+F70+$F$105 -> 6.22
A9: 5 | B9: Career Pilot | D9: =D40 -> 204871 | E9: =E40+E71+IFERROR($E$105/$D$105*D9,0) -> 3446564.2 | F9: =F40+F71+$F$105 -> 18.69
A10: 6 | B10: Communications | D10: =D41 -> 914335 | E10: =E41+E72+IFERROR($E$105/$D$105*D10,0) -> 8275048.8 | F10: =F41+F72+$F$105 -> 8.21
A11: 7 | B11: Computer and Information Sciences | D11: =D42 -> 13874819 | E11: =E42+E73+IFERROR($E$105/$D$105*D11,0) -> 84977754 | F11: =F42+F73+$F$105 -> 5.44
A12: 8 | B12: Construction Trades | D12: =D43 -> 1587260 | E12: =E43+E74+IFERROR($E$105/$D$105*D12,0) -> 9343167 | F12: =F43+F74+$F$105 -> 5.99
A13: 9 | B13: Consumer and Homemaking Education | D13: =D44 -> 4970395 | E13: =E44+E75+IFERROR($E$105/$D$105*D13,0) -> 30743351 | F13: =F44+F75+$F$105 -> 5.35
A14: 10 | B14: Engineering | D14: =D45 -> 109700 | E14: =E45+E76+IFERROR($E$105/$D$105*D14,0) -> 2076928.4 | F14: =F45+F76+$F$105 -> 7.64
A15: 11 | B15: Engineering Related | D15: =D46 -> 4655432 | E15: =E46+E77+IFERROR($E$105/$D$105*D15,0) -> 31866786 | F15: =F46+F77+$F$105 -> 6.42
A16: 12 | B16: English Language, Lit, Philosophy, Humanities, & Interdisciplinary | D16: =D47 -> 31461433 | E16: =E47+E78+IFERROR($E$105/$D$105*D16,0) -> 1.7977561e+08 | F16: =F47+F78+$F$105 -> 5.26
... A30: 26 | B30: Visual and Performing Arts | D30: =D61 -> 7572223 | E30: =E61+E92+IFERROR($E$105/$D$105*D30,0) -> 59044663 | F30: =F61+F92+$F$105 -> 7.33
A31: 28 | B31: Developmental Education - Math | D31: =D62 -> 0 | E31: =E62+E93+IFERROR($E$105/$D$105*D31,0) -> 0
A32: 29 | B32: Developmental Education - Reading/Writing | D32: =D63 -> 0 | E32: =E63+E94+IFERROR($E$105/$D$105*D32,0) -> 0
B33: Total | D33: =SUM(D5:D32) -> 192706184 | E33: =SUM(E5:E32) -> 1.2071055e+09 | F33: =F64+F95+$F$105 -> 5.77
A35: Fund | B35: Departmental Operating Expense by Discipline | D35: Contact Hours | E35: Expense | F35: Expense per Contact Hour
A36: 1 | B36: Agriculture | D36: =SUM('1:57'!D36) -> 1156306 | E36: =SUM('1:57'!E36) -> 1784347 | F36: =ROUND(MEDIAN('1:57'!F36),2) -> 0.92
A37: 2 | B37: Architecture and Precision Production Trades | D37: =SUM('1:57'!D37) -> 5213661 | E37: =SUM('1:57'!E37) -> 6224692 | F37: =ROUND(MEDIAN('1:57'!F37),2) -> 1.29
A38: 3 | B38: Biology, Physical Sciences, and Science Technology | D38: =SUM('1:57'!D38) -> 18409138 | E38: =SUM('1:57'!E38) -> 12557365 | F38: =ROUND(MEDIAN('1:57'!F38),2) -> 0.5
A39: 4 | B39: Business Management, Marketing, and Administrative Services | D39: =SUM('1:57'!D39) -> 15167456 | E39: =SUM('1:57'!E39) -> 14533847 | F39: =ROUND(MEDIAN('1:57'!F39),2) -> 0.56
A40: 5 | B40: Career Pilot | D40: =SUM('1:57'!D40) -> 204871 | E40: =SUM('1:57'!E40) -> 1699963 | F40: =ROUND(MEDIAN('1:57'!F40),2) -> 8.73
A41: 6 | B41: Communications | D41: =SUM('1:57'!D41) -> 914335 | E41: =SUM('1:57'!E41) -> 2355814 | F41: =ROUND(MEDIAN('1:57'!F41),2) -> 1.48
A42: 7 | B42: Computer and Information Sciences | D42: =SUM('1:57'!D42) -> 13874819 | E42: =SUM('1:57'!E42) -> 16343241 | F42: =ROUND(MEDIAN('1:57'!F42),2) -> 0.69
A43: 8 | B43: Construction Trades | D43: =SUM('1:57'!D43) -> 1587260 | E43: =SUM('1:57'!E43) -> 1163947 | F43: =ROUND(MEDIAN('1:57'!F43),2) -> 0.86
A44: 9 | B44: Consumer and Homemaking Education | D44: =SUM('1:57'!D44) -> 4970395 | E44: =SUM('1:57'!E44) -> 4180066 | F44: =ROUND(MEDIAN('1:57'!F44),2) -> 0.48
A45: 10 | B45: Engineering | D45: =SUM('1:57'!D45) -> 109700 | E45: =SUM('1:57'!E45) -> 744438 | F45: =ROUND(MEDIAN('1:57'!F45),2) -> 0.46
A46: 11 | B46: Engineering Related | D46: =SUM('1:57'!D46) -> 4655432 | E46: =SUM('1:57'!E46) -> 5378490 | F46: =ROUND(MEDIAN('1:57'!F46),2) -> 0.92
A47: 12 | B47: English Language, Lit, Philosophy, Humanities, & Interdisciplinary | D47: =SUM('1:57'!D47) -> 31461433 | E47: =SUM('1:57'!E47) -> 13161115 | F47: =ROUND(MEDIAN('1:57'!F47),2) -> 0.26
... A61: 26 | B61: Visual and Performing Arts | D61: =SUM('1:57'!D61) -> 7572223 | E61: =SUM('1:57'!E61) -> 8194517 | F61: =ROUND(MEDIAN('1:57'!F61),2) -> 0.94
A62: 28 | B62: Developmental Education - Math | D62: =SUM('1:57'!D62) -> 0 | E62: =SUM('1:57'!E62) -> 0
A63: 29 | B63: Developmental Education - Reading/Writing | D63: =SUM('1:57'!D63) -> 0 | E63: =SUM('1:57'!E63) -> 0
C64: Total | D64: =SUM(D36:D63) -> 192706184 | E64: =SUM(E36:E63) -> 136043544 | F64: =ROUND(MEDIAN('1:57'!F64),2) -> 0.62
A66: Fund | B66: Faculty Salaries by Discipline | D66: Contact Hours | E66: Expense | F66: Expense per Contact Hour
A67: 1 | B67: Agriculture | D67: =D36 -> 1156306 | E67: =SUM('1:57'!E67) -> 3793956 | F67: =ROUND(MEDIAN('1:57'!F67),2) -> 3.32
A68: 2 | B68: Architecture and Precision Production Trades | D68: =D37 -> 5213661 | E68: =SUM('1:57'!E68) -> 13799890 | F68: =ROUND(MEDIAN('1:57'!F68),2) -> 2.78
A69: 3 | B69: Biology, Physical Sciences, and Science Technology | D69: =D38 -> 18409138 | E69: =SUM('1:57'!E69) -> 43088517 | F69: =ROUND(MEDIAN('1:57'!F69),2) -> 2.44
A70: 4 | B70: Business Management, Marketing, and Administrative Services | D70: =D39 -> 15167456 | E70: =SUM('1:57'!E70) -> 46350319 | F70: =ROUND(MEDIAN('1:57'!F70),2) -> 3.09
A71: 5 | B71: Career Pilot | D71: =D40 -> 204871 | E71: =SUM('1:57'!E71) -> 1165510 | F71: =ROUND(MEDIAN('1:57'!F71),2) -> 7.39
A72: 6 | B72: Communications | D72: =D41 -> 914335 | E72: =SUM('1:57'!E72) -> 3325837 | F72: =ROUND(MEDIAN('1:57'!F72),2) -> 4.16
A73: 7 | B73: Computer and Information Sciences | D73: =D42 -> 13874819 | E73: =SUM('1:57'!E73) -> 29280311 | F73: =ROUND(MEDIAN('1:57'!F73),2) -> 2.18
A74: 8 | B74: Construction Trades | D74: =D43 -> 1587260 | E74: =SUM('1:57'!E74) -> 3677154 | F74: =ROUND(MEDIAN('1:57'!F74),2) -> 2.56
A75: 9 | B75: Consumer and Homemaking Education | D75: =D44 -> 4970395 | E75: =SUM('1:57'!E75) -> 12465376 | F75: =ROUND(MEDIAN('1:57'!F75),2) -> 2.3
A76: 10 | B76: Engineering | D76: =D45 -> 109700 | E76: =SUM('1:57'!E76) -> 1021340 | F76: =ROUND(MEDIAN('1:57'!F76),2) -> 4.61
A77: 11 | B77: Engineering Related | D77: =D46 -> 4655432 | E77: =SUM('1:57'!E77) -> 13283741 | F77: =ROUND(MEDIAN('1:57'!F77),2) -> 2.93
A78: 12 | B78: English Language, Lit, Philosophy, Humanities, & Interdisciplinary | D78: =D47 -> 31461433 | E78: =SUM('1:57'!E78) -> 77378045 | F78: =ROUND(MEDIAN('1:57'!F78),2) -> 2.43
... A92: 26 | B92: Visual and Performing Arts | D92: =D61 -> 7572223 | E92: =SUM('1:57'!E92) -> 29372475 | F92: =ROUND(MEDIAN('1:57'!F92),2) -> 3.82
A93: 28 | B93: Developmental Education - Math | D93: =D62 -> 0 | E93: =SUM('1:57'!E93) -> 0
A94: 29 | B94: Developmental Education - Reading/Writing | D94: =D63 -> 0 | E94: =SUM('1:57'!E94) -> 0
C95: Total | D95: =SUM(D67:D94) -> 192706184 | E95: =SUM(E67:E94) -> 524474824 | F95: =ROUND(MEDIAN('1:57'!F95),2) -> 2.58
B97: Allocated Administrative Expense | D97: Contact Hours | E97: Expense | F97: Expense per Contact Hour
B98: Institutional Support | E98: =SUM('1:57'!E98) -> 232104083 | F98: =ROUND(MEDIAN('1:57'!F98),2) -> 1.13
B99: Student Services | E99: =SUM('1:57'!E99) -> 111456875 | F99: =ROUND(MEDIAN('1:57'!F99),2) -> 0.51
B100: Library | E100: =SUM('1:57'!E100) -> 52661803 | F100: =ROUND(MEDIAN('1:57'!F100),2) -> 0.23
B101: Instructional Administration | E101: =SUM('1:57'!E101) -> 73798533 | F101: =ROUND(MEDIAN('1:57'!F101),2) -> 0.31
B102: Organized Activities | E102: =SUM('1:57'!E102) -> 3457685 | F102: =ROUND(MEDIAN('1:57'!F102),2) -> 0.06
B103: Equipment Depreciation | E103: =SUM('1:57'!E103) -> 1e-06 | F103: =ROUND(MEDIAN('1:57'!F103),2) -> 0
B104: Local Benefits | E104: =SUM('1:57'!E104) -> 73108196 | F104: =ROUND(MEDIAN('1:57'!F104),2) -> 0.33
C105: Total | D105: =D95 -> 192706184 | E105: =SUM(E98:E104) -> 5.4658718e+08 | F105: =SUM(F98:F104) -> 2.57
B107: Annual Financial Report - Schedule B
B108: Unrestricted - Educational Activities | C108: Salaries and Wages | D108: Local Benefits | E108: Other Expenses | F108: Total
B109: Instruction | C109: =SUM('1:57'!C109) -> 524474824 | D109: =SUM('1:57'!D109) -> 0 | E109: =SUM('1:57'!E109) -> 0 | F109: =SUM('1:57'!F109) -> 524474824
B110: Research | C110: =SUM('1:57'!C110) -> 0 | D110: =SUM('1:57'!D110) -> 0 | E110: =SUM('1:57'!E110) -> 0 | F110: =SUM('1:57'!F110) -> 0
B111: Public Service | C111: =SUM('1:57'!C111) -> 0 | D111: =SUM('1:57'!D111) -> 0 | E111: =SUM('1:57'!E111) -> 0 | F111: =SUM('1:57'!F111) -> 0
B112: Academic Support | C112: =SUM('1:57'!C112) -> 0 | D112: =SUM('1:57'!D112) -> 0 | E112: =SUM('1:57'!E112) -> 0 | F112: =SUM('1:57'!F112) -> 0
B113: Student Services | C113: =SUM('1:57'!C113) -> 0 | D113: =SUM('1:57'!D113) -> 0 | E113: =SUM('1:57'!E113) -> 0 | F113: =SUM('1:57'!F113) -> 0
B114: Instructional Support | C114: =SUM('1:57'!C114) -> 0 | D114: =SUM('1:57'!D114) -> 0 | E114: =SUM('1:57'!E114) -> 0 | F114: =SUM('1:57'!F114) -> 0
B115: Operation and Maintenance of Plant | C115: =SUM('1:57'!C115) -> 0 | D115: =SUM('1:57'!D115) -> 0 | E115: =SUM('1:57'!E115) -> 0 | F115: =SUM('1:57'!F115) -> 0
B116: Scholarships and Fellowships | C116: =SUM('1:57'!C116) -> 0 | D116: =SUM('1:57'!D116) -> 0 | E116: =SUM('1:57'!E116) -> 3457685 | F116: =SUM('1:57'!F116) -> 3457685
B117: Other | C117: =SUM('1:57'!C117) -> 0 | D117: =SUM('1:57'!D117) -> 73108196 | E117: =SUM('1:57'!E117) -> 0 | F117: =SUM('1:57'!F117) -> 73108196
B118: Total | C118: =SUM(C109:C116) -> 524474824 | D118: =SUM(D109:D116) -> 0 | E118: =SUM(E109:E116) -> 3457685 | F118: =SUM(F109:F116) -> 527932509
B120: Depreciation Expense - Equipment | C120: =SUM('1:57'!C120) -> 0 | D120: =SUM('1:57'!D120) -> 0 | E120: =SUM('1:57'!E120) -> 1e-06 | F120: =SUM('1:57'!F120) -> 1e-06
A122: Each year, the Texas Higher Education Coordinating Board revises the Texas Public Community and Technical Colleges Expense per Contact Hour Rates used in its Instruction and Operations Formula Funding Recommendation to the Legislative Budget Board (LBB). The Report of Fundable Operating Expenses (RFOE), completed by the institutions, collects departmental operating expense, faculty salaries, institutional support, student services, academic support, research, scholarships and fellowships, equipment depreciation, and local benefits for input into this summary using Annual Financial Report (AFR) Schedule B, which ties to the AFR Statement of Revenues, Expenses and Changes in Net Assets (SRECNA). The RFOE subcategorizes the expenditures collected in Schedule B funded with unrestricted funds, totals them for all institutions, and divides them by the statewide contact hours to determine rates by discipline.

Sheet Rate History
A1: =Summary!A1 -> Community and Technical Colleges, Report of Fundable Operating Expenses, Fiscal Year (FY) 1999
A2: Rate History
A3: Fund | B3: Expense per Contact Hour by Discipline | C3: 1999
A4: 1 | B4: Agriculture | C4: =Summary!F5 -> 6.81
A5: 2 | B5: Architecture and Precision Production Trades | C5: =Summary!F6 -> 6.64
A6: 3 | B6: Biology, Physical Sciences, and Science Technology | C6: =Summary!F7 -> 5.51
A7: 4 | B7: Business Management, Marketing, and Administrative Services | C7: =Summary!F8 -> 6.22
A8: 5 | B8: Career Pilot | C8: =Summary!F9 -> 18.69
A9: 6 | B9: Communications | C9: =Summary!F10 -> 8.21
A10: 7 | B10: Computer and Information Sciences | C10: =Summary!F11 -> 5.44
A11: 8 | B11: Construction Trades | C11: =Summary!F12 -> 5.99
A12: 9 | B12: Consumer and Homemaking Education | C12: =Summary!F13 -> 5.35
A13: 10 | B13: Engineering | C13: =Summary!F14 -> 7.64
A14: 11 | B14: Engineering Related | C14: =Summary!F15 -> 6.42
A15: 12 | B15: English Language, Lit, Philosophy, Humanities, & Interdisciplinary | C15: =Summary!F16 -> 5.26
... A31: 29 | B31: Developmental Education - Reading/Writing | C31: =Summary!F32 -> 0
B32: Average | C32: =AVERAGE(C4:C31) -> 6.5617857
B33: Median | C33: =MEDIAN(C4:C31) -> 6.32
B34: Standard Deviation | C34: =STDEV(C4:C31) -> 3.2525364

Sheet FTSE Summary
A1: =Summary!A1 -> Community and Technical Colleges, Report of Fundable Operating Expenses, Fiscal Year (FY) 1999
A2: Average Total Expenditure per Full-Time Student Equivalent (FTSE)
A3: Institution | B3: Annual State Funded Semester Credit Hours | C3: Total FTSE | D3: Total Expenditure | E3: Average Expenditure per FTSE
A4: Alamo | B4: =(161+3898+11775+4803)*30 -> 619110 | C4: =B4/30 -> 20637 | D4: ='1'!$E$33 -> 1.1017196e+08 | E4: =IFERROR(D4/C4,"") -> 5338.5647
A5: Alvin | B5: =2047*30 -> 61410 | C5: =B5/30 -> 2047 | D5: ='2'!$E$33 -> 12071182 | E5: =IFERROR(D5/C5,"") -> 5897.0112
A6: Amarillo | B6: =4129*30 -> 123870 | C6: =B6/30 -> 4129 | D6: ='3'!$E$33 -> 25602472 | E6: =IFERROR(D6/C6,"") -> 6200.6471
A7: Angelina | B7: =2579*30 -> 77370 | C7: =B7/30 -> 2579 | D7: ='4'!$E$33 -> 9238820 | E7: =IFERROR(D7/C7,"") -> 3582.3265
A8: Austin | B8: =13182*30 -> 395460 | C8: =B8/30 -> 13182 | D8: ='5'!$E$33 -> 67025182 | E8: =IFERROR(D8/C8,"") -> 5084.5988
A9: Blinn | B9: =7374*30 -> 221220 | C9: =B9/30 -> 7374 | D9: ='6'!$E$33 -> 21396825 | E9: =IFERROR(D9/C9,"") -> 2901.6579
A10: Brazosport | B10: =1772*30 -> 53160 | C10: =B10/30 -> 1772 | D10: ='7'!$E$33 -> 9361650 | E10: =IFERROR(D10/C10,"") -> 5283.0982
A11: Central Texas | B11: =4163*30 -> 124890 | C11: =B11/30 -> 4163 | D11: ='8'!$E$33 -> 20575441 | E11: =IFERROR(D11/C11,"") -> 4942.4552
A12: Cisco | B12: =1780*30 -> 53400 | C12: =B12/30 -> 1780 | D12: ='9'!$E$33 -> 5009954 | E12: =IFERROR(D12/C12,"") -> 2814.5809
A13: Clarendon | B13: =527*30 -> 15810 | C13: =B13/30 -> 527 | D13: ='10'!$E$33 -> 2796292 | E13: =IFERROR(D13/C13,"") -> 5306.0569
A14: Coastal Bend | B14: =1874*30 -> 56220 | C14: =B14/30 -> 1874 | D14: ='11'!$E$33 -> 9107206 | E14: =IFERROR(D14/C14,"") -> 4859.7684
A15: College Of The Mainland | B15: =1962*30 -> 58860 | C15: =B15/30 -> 1962 | D15: ='12'!$E$33 -> 13101401 | E15: =IFERROR(D15/C15,"") -> 6677.5744
A16: Collin | B16: =6003*30 -> 180090 | C16: =B16/30 -> 6003 | D16: ='13'!$E$33 -> 33833767 | E16: =IFERROR(D16/C16,"") -> 5636.1431
A17: Dallas | B17: =+(4194+1465+4658+2342+2713+3055+6601)*30 -> 750840 | C17: =B17/30 -> 25028 | D17: ='14'!$E$33 -> 134413752 | E17: =IFERROR(D17/C17,"") -> 5370.5351
A18: Del Mar | B18: =5744*30 -> 172320 | C18: =B18/30 -> 5744 | D18: ='15'!$E$33 -> 0 | E18: =IFERROR(D18/C18,"") -> 0
A19: El Paso | B19: =12805*30 -> 384150 | C19: =B19/30 -> 12805 | D19: ='16'!$E$33 -> 55011518 | E19: =IFERROR(D19/C19,"") -> 4296.0967
A20: Frank Phillips | B20: =701*30 -> 21030 | C20: =B20/30 -> 701 | D20: ='17'!$E$33 -> 3485837 | E20: =IFERROR(D20/C20,"") -> 4972.6633
A21: Galveston | B21: =1124*30 -> 33720 | C21: =B21/30 -> 1124 | D21: ='18'!$E$33 -> 8461037 | E21: =IFERROR(D21/C21,"") -> 7527.613
A22: Grayson | B22: =2087*30 -> 62610 | C22: =B22/30 -> 2087 | D22: ='19'!$E$33 -> 9022087 | E22: =IFERROR(D22/C22,"") -> 4322.9933
A23: Hill | B23: =1470*30 -> 44100 | C23: =B23/30 -> 1470 | D23: ='20'!$E$33 -> 6266760 | E23: =IFERROR(D23/C23,"") -> 4263.102
A24: Houston | B24: =17117*30 -> 513510 | C24: =B24/30 -> 17117 | D24: ='21'!$E$33 -> 109213361 | E24: =IFERROR(D24/C24,"") -> 6380.4032
A25: Howard | B25: =(1274+79)*30 -> 40590 | C25: =B25/30 -> 1353 | D25: ='22'!$E$33 -> 8125967 | E25: =IFERROR(D25/C25,"") -> 6005.8884
A26: Kilgore | B26: =2826*30 -> 84780 | C26: =B26/30 -> 2826 | D26: ='23'!$E$33 -> 0 | E26: =IFERROR(D26/C26,"") -> 0
A27: Laredo | B27: =4700*30 -> 141000 | C27: =B27/30 -> 4700 | D27: ='24'!$E$33 -> 21519871 | E27: =IFERROR(D27/C27,"") -> 4578.696
A28: Lee | B28: =3063*30 -> 91890 | C28: =B28/30 -> 3063 | D28: ='25'!$E$33 -> 22425942 | E28: =IFERROR(D28/C28,"") -> 7321.5612
A29: Lonestar | B29: =(2033+2554+4755+2525)*30 -> 356010 | C29: =B29/30 -> 11867 | D29: ='26'!$E$33 -> 62042788 | E29: =IFERROR(D29/C29,"") -> 5228.178
A30: Mclennan | B30: =3623*30 -> 108690 | C30: =B30/30 -> 3623 | D30: ='27'!$E$33 -> 17848119 | E30: =IFERROR(D30/C30,"") -> 4926.337
A31: Midland | B31: =2601*30 -> 78030 | C31: =B31/30 -> 2601 | D31: ='28'!$E$33 -> 14172389 | E31: =IFERROR(D31/C31,"") -> 5448.8231
A32: Navarro | B32: =2512*30 -> 75360 | C32: =B32/30 -> 2512 | D32: ='29'!$E$33 -> 10082860 | E32: =IFERROR(D32/C32,"") -> 4013.8774
A33: North Central Texas | B33: =2404*30 -> 72120 | C33: =B33/30 -> 2404 | D33: ='30'!$E$33 -> 8053602 | E33: =IFERROR(D33/C33,"") -> 3350.084
A34: Northeast Texas | B34: =1346*30 -> 40380 | C34: =B34/30 -> 1346 | D34: ='31'!$E$33 -> 6397564 | E34: =IFERROR(D34/C34,"") -> 4753.0193
A35: Odessa | B35: =2738*30 -> 82140 | C35: =B35/30 -> 2738 | D35: ='32'!$E$33 -> 15350416 | E35: =IFERROR(D35/C35,"") -> 5606.4339
A36: Panola | B36: =1129*30 -> 33870 | C36: =B36/30 -> 1129 | D36: ='33'!$E$33 -> 6580557 | E36: =IFERROR(D36/C36,"") -> 5828.6599
A37: Paris | B37: =1923*30 -> 57690 | C37: =B37/30 -> 1923 | D37: ='34'!$E$33 -> 8390679 | E37: =IFERROR(D37/C37,"") -> 4363.3276
A38: Ranger | B38: =628*30 -> 18840 | C38: =B38/30 -> 628 | D38: ='35'!$E$33 -> 2269241 | E38: =IFERROR(D38/C38,"") -> 3613.4411
A39: San Jacinto | B39: =(5723+2339+2873)*30 -> 328050 | C39: =B39/30 -> 10935 | D39: ='36'!$E$33 -> 55578066 | E39: =IFERROR(D39/C39,"") -> 5082.5849
A40: South Plains | B40: =4483*30 -> 134490 | C40: =B40/30 -> 4483 | D40: ='37'!$E$33 -> 17958309 | E40: =IFERROR(D40/C40,"") -> 4005.8686
A41: South Texas | B41: =5442*30 -> 163260 | C41: =B41/30 -> 5442 | D41: ='38'!$E$33 -> 22887502 | E41: =IFERROR(D41/C41,"") -> 4205.7152
A42: Southwest Texas | B42: =2349*30 -> 70470 | C42: =B42/30 -> 2349 | D42: ='39'!$E$33 -> 8827225 | E42: =IFERROR(D42/C42,"") -> 3757.865
A43: Tarrant | B43: =(5044+2166+3922+3659)*30 -> 443730 | C43: =B43/30 -> 14791 | D43: ='40'!$E$33 -> 66018614 | E43: =IFERROR(D43/C43,"") -> 4463.4314
A44: Temple | B44: =1834*30 -> 55020 | C44: =B44/30 -> 1834 | D44: ='41'!$E$33 -> 8807432 | E44: =IFERROR(D44/C44,"") -> 4802.3075
A45: Texarkana | B45: =2342*30 -> 70260 | C45: =B45/30 -> 2342 | D45: ='42'!$E$33 -> 9716448 | E45: =IFERROR(D45/C45,"") -> 4148.7822
A46: Texas Southmost | B46: =4003*30 -> 120090 | C46: =B46/30 -> 4003 | D46: ='43'!$E$33 -> 19695405 | E46: =IFERROR(D46/C46,"") -> 4920.1611
A47: Trinity Valley | B47: =2846*30 -> 85380 | C47: =B47/30 -> 2846 | D47: ='44'!$E$33 -> 12338593 | E47: =IFERROR(D47/C47,"") -> 4335.4157
A48: Tyler | B48: =5564*30 -> 166920 | C48: =B48/30 -> 5564 | D48: ='45'!$E$33 -> 21563646 | E48: =IFERROR(D48/C48,"") -> 3875.5654
A49: Vernon | B49: =1085*30 -> 32550 | C49: =B49/30 -> 1085 | D49: ='46'!$E$33 -> 6484661 | E49: =IFERROR(D49/C49,"") -> 5976.6461
A50: Victoria | B50: =2435*30 -> 73050 | C50: =B50/30 -> 2435 | D50: ='47'!$E$33 -> 11602282 | E50: =IFERROR(D50/C50,"") -> 4764.7975
A51: Weatherford | B51: =1854*30 -> 55620 | C51: =B51/30 -> 1854 | D51: ='48'!$E$33 -> 7536289 | E51: =IFERROR(D51/C51,"") -> 4064.8808
A52: Western Texas | B52: =727*30 -> 21810 | C52: =B52/30 -> 727 | D52: ='49'!$E$33 -> 4311614 | E52: =IFERROR(D52/C52,"") -> 5930.6933
A53: Wharton | B53: =2886*30 -> 86580 | C53: =B53/30 -> 2886 | D53: ='50'!$E$33 -> 11686941 | E53: =IFERROR(D53/C53,"") -> 4049.5291
A54: TSTC-Harlingen | B54: =2018*30 -> 60540 | C54: =B54/30 -> 2018 | D54: ='51'!$E$33 -> 13101592 | E54: =IFERROR(D54/C54,"") -> 6492.3647
A55: TSTC-West Texas | B55: =779*30 -> 23370 | C55: =B55/30 -> 779 | D55: ='52'!$E$33 -> 7170831 | E55: =IFERROR(D55/C55,"") -> 9205.1746
A56: TSTC-Marshall | B56: 0 | C56: =B56/30 -> 0 | D56: ='53'!$E$33 -> 0 | E56: =IFERROR(D56/C56,"")
A57: TSTC-Waco | B57: =2920*30 -> 87600 | C57: =B57/30 -> 2920 | D57: ='54'!$E$33 -> 21781069 | E57: =IFERROR(D57/C57,"") -> 7459.2702
A58: Lamar-IOT | B58: =1398*30 -> 41940 | C58: =B58/30 -> 1398 | D58: ='55'!$E$33 -> 0 | E58: =IFERROR(D58/C58,"") -> 0
A59: Lamar-Orange | B59: =904*30 -> 27120 | C59: =B59/30 -> 904 | D59: ='56'!$E$33 -> 4356777 | E59: =IFERROR(D59/C59,"") -> 4819.4436
A60: Lamar-Port Arthur | B60: =1490*30 -> 44700 | C60: =B60/30 -> 1490 | D60: ='57'!$E$33 -> 7255748 | E60: =IFERROR(D60/C60,"") -> 4869.6295
A61: Total for Instutions Reporting Expense | B61: =SUMIF(D4:D60,">0",B4:B60) -> 7198050 | C61: =B61/30 -> 239935 | D61: =SUM(D4:D60) -> 1.2071055e+09 | E61: =IFERROR(D61/C61,"") -> 5030.969
C63: 249903
C64: =C61-C63 -> -9968

Sheet Discipline Summary
A1: =Summary!A1 -> Community and Technical Colleges, Report of Fundable Operating Expenses, Fiscal Year (FY) 1999
A2: Discipline Summary of Expense per Contact Hour by Institution
A3: Institution | B3: AG | C3: ARCH | D3: SCI | E3: BA | F3: CP | G3: COMM | H3: CS | I3: CNSTR | J3: HE | K3: ENG | L3: ENGR | M3: LA | N3: FL | O3: HODA | P3: HODH | Q3: HOO | R3: HORT | S3: NUR | T3: MATH | U3: AUTO | V3: MECH | W3: ELECT | X3: PE | Y3: PA | Z3: SS | AA3: FA | AB3: DEM | AC3: DER | AD3: Total
A4: Alamo | B4: ='1'!$F$5 -> 6.35 | C4: ='1'!$F$6 -> 8.93 | D4: ='1'!$F$7 -> 7.15 | E4: ='1'!$F$8 -> 8.81 | F4: ='1'!$F$9 -> 24.55 | G4: ='1'!$F$10 -> 13.15 | H4: ='1'!$F$11 -> 6.27 | I4: ='1'!$F$12 | J4: ='1'!$F$13 -> 9.45 | K4: ='1'!$F$14 -> 18.17 | L4: ='1'!$F$15 -> 8.79 | M4: ='1'!$F$16 -> 6.38 | N4: ='1'!$F$17 -> 6.82 | O4: ='1'!$F$18 -> 11.63 | P4: ='1'!$F$19 | Q4: ='1'!$F$20 -> 6.79 | R4: ='1'!$F$21 -> 10.18 | S4: ='1'!$F$22 -> 7.91 | T4: ='1'!$F$23 -> 6.48 | U4: ='1'!$F$24 -> 9.01 | V4: ='1'!$F$25 -> 8.85 | W4: ='1'!$F$26 -> 7.23 | X4: ='1'!$F$27 -> 7.64 | Y4: ='1'!$F$28 -> 6.04 | Z4: ='1'!$F$29 -> 7.44 | AA4: ='1'!$F$30 -> 9.24 | AB4: ='1'!$F$31 | AC4: ='1'!$F$32 | AD4: ='1'!$F$33 -> 7.45
A5: Alvin | B5: ='2'!$F$5 -> 4.92 | C5: ='2'!$F$6 -> 5.34 | D5: ='2'!$F$7 -> 6.02 | E5: ='2'!$F$8 -> 6.13 | F5: ='2'!$F$9 | G5: ='2'!$F$10 -> 5.14 | H5: ='2'!$F$11 -> 5.46 | I5: ='2'!$F$12 | J5: ='2'!$F$13 -> 7.05 | K5: ='2'!$F$14 | L5: ='2'!$F$15 -> 4.36 | M5: ='2'!$F$16 -> 4.9 | N5: ='2'!$F$17 -> 5.66 | O5: ='2'!$F$18 -> 7.9 | P5: ='2'!$F$19 | Q5: ='2'!$F$20 -> 7.59 | R5: ='2'!$F$21 -> 12.68 | S5: ='2'!$F$22 -> 12.34 | T5: ='2'!$F$23 -> 9.25 | U5: ='2'!$F$24 -> 5.11 | V5: ='2'!$F$25 | W5: ='2'!$F$26 | X5: ='2'!$F$27 -> 7.48 | Y5: ='2'!$F$28 -> 5.18 | Z5: ='2'!$F$29 -> 4.84 | AA5: ='2'!$F$30 -> 7.77 | AB5: ='2'!$F$31 | AC5: ='2'!$F$32 | AD5: ='2'!$F$33 -> 5.92
A6: Amarillo | B6: ='3'!$F$5 -> 11.1 | C6: ='3'!$F$6 -> 7.69 | D6: ='3'!$F$7 -> 5.49 | E6: ='3'!$F$8 -> 6.46 | F6: ='3'!$F$9 | G6: ='3'!$F$10 -> 9.4 | H6: ='3'!$F$11 -> 5.51 | I6: ='3'!$F$12 -> 4.31 | J6: ='3'!$F$13 -> 5.48 | K6: ='3'!$F$14 -> 7.28 | L6: ='3'!$F$15 -> 7.97 | M6: ='3'!$F$16 -> 5.82 | N6: ='3'!$F$17 -> 7.58 | O6: ='3'!$F$18 -> 7.91 | P6: ='3'!$F$19 -> 9.84 | Q6: ='3'!$F$20 -> 5.96 | R6: ='3'!$F$21 -> 8.46 | S6: ='3'!$F$22 -> 6.03 | T6: ='3'!$F$23 -> 5.18 | U6: ='3'!$F$24 -> 8.22 | V6: ='3'!$F$25 -> 6.78 | W6: ='3'!$F$26 -> 7.89 | X6: ='3'!$F$27 -> 5.63 | Y6: ='3'!$F$28 -> 5.57 | Z6: ='3'!$F$29 -> 5.47 | AA6: ='3'!$F$30 -> 9.25 | AB6: ='3'!$F$31 | AC6: ='3'!$F$32 | AD6: ='3'!$F$33 -> 6.26
A7: Angelina | B7: ='4'!$F$5 -> 5.94 | C7: ='4'!$F$6 -> 4.18 | D7: ='4'!$F$7 -> 3.99 | E7: ='4'!$F$8 -> 5.84 | F7: ='4'!$F$9 | G7: ='4'!$F$10 -> 6.22 | H7: ='4'!$F$11 -> 6.21 | I7: ='4'!$F$12 -> 5.89 | J7: ='4'!$F$13 -> 4.78 | K7: ='4'!$F$14 -> 10.82 | L7: ='4'!$F$15 -> 3.53 | M7: ='4'!$F$16 -> 3.89 | N7: ='4'!$F$17 -> 5.11 | O7: ='4'!$F$18 -> 6.73 | P7: ='4'!$F$19 | Q7: ='4'!$F$20 -> 6.54 | R7: ='4'!$F$21 -> 6.39 | S7: ='4'!$F$22 -> 6.17 | T7: ='4'!$F$23 -> 3.89 | U7: ='4'!$F$24 -> 5.59 | V7: ='4'!$F$25 -> 6.15 | W7: ='4'!$F$26 -> 5.53 | X7: ='4'!$F$27 -> 4.6 | Y7: ='4'!$F$28 -> 4.66 | Z7: ='4'!$F$29 -> 3.68 | AA7: ='4'!$F$30 -> 5.87 | AB7: ='4'!$F$31 | AC7: ='4'!$F$32 | AD7: ='4'!$F$33 -> 4.75
A8: Austin | B8: ='5'!$F$5 | C8: ='5'!$F$6 -> 9.55 | D8: ='5'!$F$7 -> 7 | E8: ='5'!$F$8 -> 7.78 | F8: ='5'!$F$9 | G8: ='5'!$F$10 -> 7.3 | H8: ='5'!$F$11 -> 6.99 | I8: ='5'!$F$12 -> 10.73 | J8: ='5'!$F$13 -> 7.59 | K8: ='5'!$F$14 -> 12.19 | L8: ='5'!$F$15 -> 9.8 | M8: ='5'!$F$16 -> 6.61 | N8: ='5'!$F$17 -> 5.99 | O8: ='5'!$F$18 -> 13.68 | P8: ='5'!$F$19 | Q8: ='5'!$F$20 -> 9.03 | R8: ='5'!$F$21 | S8: ='5'!$F$22 -> 11.43 | T8: ='5'!$F$23 -> 6.08 | U8: ='5'!$F$24 -> 13.12 | V8: ='5'!$F$25 | W8: ='5'!$F$26 -> 9.47 | X8: ='5'!$F$27 -> 8.58 | Y8: ='5'!$F$28 -> 7.8 | Z8: ='5'!$F$29 -> 5.51 | AA8: ='5'!$F$30 -> 7.76 | AB8: ='5'!$F$31 | AC8: ='5'!$F$32 | AD8: ='5'!$F$33 -> 6.97
A9: Blinn | B9: ='6'!$F$5 -> 7.82 | C9: ='6'!$F$6 -> 5.12 | D9: ='6'!$F$7 -> 3.38 | E9: ='6'!$F$8 -> 4.41 | F9: ='6'!$F$9 | G9: ='6'!$F$10 -> 4.96 | H9: ='6'!$F$11 -> 7.84 | I9: ='6'!$F$12 | J9: ='6'!$F$13 -> 4.65 | K9: ='6'!$F$14 | L9: ='6'!$F$15 -> 2.35 | M9: ='6'!$F$16 -> 4.4 | N9: ='6'!$F$17 -> 3.96 | O9: ='6'!$F$18 -> 9.28 | P9: ='6'!$F$19 -> 10.14 | Q9: ='6'!$F$20 -> 5.62 | R9: ='6'!$F$21 | S9: ='6'!$F$22 -> 5 | T9: ='6'!$F$23 -> 3.83 | U9: ='6'!$F$24 | V9: ='6'!$F$25 | W9: ='6'!$F$26 | X9: ='6'!$F$27 -> 3.8 | Y9: ='6'!$F$28 -> 3.83 | Z9: ='6'!$F$29 -> 3.63 | AA9: ='6'!$F$30 -> 6.62 | AB9: ='6'!$F$31 | AC9: ='6'!$F$32 | AD9: ='6'!$F$33 -> 4.21
A10: Brazosport | B10: ='7'!$F$5 | C10: ='7'!$F$6 -> 5.98 | D10: ='7'!$F$7 -> 7.14 | E10: ='7'!$F$8 -> 6.35 | F10: ='7'!$F$9 | G10: ='7'!$F$10 -> 6.92 | H10: ='7'!$F$11 -> 6.41 | I10: ='7'!$F$12 -> 5.27 | J10: ='7'!$F$13 -> 5.05 | K10: ='7'!$F$14 | L10: ='7'!$F$15 -> 5.81 | M10: ='7'!$F$16 -> 6.51 | N10: ='7'!$F$17 -> 7.86 | O10: ='7'!$F$18 -> 14.95 | P10: ='7'!$F$19 | Q10: ='7'!$F$20 -> 4.8 | R10: ='7'!$F$21 | S10: ='7'!$F$22 | T10: ='7'!$F$23 -> 5.69 | U10: ='7'!$F$24 -> 16.37 | V10: ='7'!$F$25 -> 4.47 | W10: ='7'!$F$26 -> 6.16 | X10: ='7'!$F$27 -> 7.59 | Y10: ='7'!$F$28 -> 4.82 | Z10: ='7'!$F$29 -> 5.82 | AA10: ='7'!$F$30 -> 9.19 | AB10: ='7'!$F$31 | AC10: ='7'!$F$32 | AD10: ='7'!$F$33 -> 6.21
A11: Central Texas | B11: ='8'!$F$5 -> 9.43 | C11: ='8'!$F$6 -> 5.09 | D11: ='8'!$F$7 -> 6.1 | E11: ='8'!$F$8 -> 4.59 | F11: ='8'!$F$9 -> 28.12 | G11: ='8'!$F$10 | H11: ='8'!$F$11 -> 3.85 | I11: ='8'!$F$12 -> 5.29 | J11: ='8'!$F$13 -> 4.23 | K11: ='8'!$F$14 -> 5.68 | L11: ='8'!$F$15 -> 3.28 | M11: ='8'!$F$16 -> 4.31 | N11: ='8'!$F$17 -> 4.41 | O11: ='8'!$F$18 -> 8.69 | P11: ='8'!$F$19 | Q11: ='8'!$F$20 -> 5.93 | R11: ='8'!$F$21 | S11: ='8'!$F$22 -> 4.79 | T11: ='8'!$F$23 -> 3.63 | U11: ='8'!$F$24 -> 5.47 | V11: ='8'!$F$25 -> 11.21 | W11: ='8'!$F$26 -> 4.99 | X11: ='8'!$F$27 -> 4.84 | Y11: ='8'!$F$28 -> 3.8 | Z11: ='8'!$F$29 -> 3.73 | AA11: ='8'!$F$30 -> 6.02 | AB11: ='8'!$F$31 | AC11: ='8'!$F$32 | AD11: ='8'!$F$33 -> 4.66
A12: Cisco | B12: ='9'!$F$5 -> 6.71 | C12: ='9'!$F$6 -> 3.36 | D12: ='9'!$F$7 -> 3.46 | E12: ='9'!$F$8 -> 4.7 | F12: ='9'!$F$9 | G12: ='9'!$F$10 | H12: ='9'!$F$11 -> 4.36 | I12: ='9'!$F$12 | J12: ='9'!$F$13 -> 3.48 | K12: ='9'!$F$14 | L12: ='9'!$F$15 -> 3.35 | M12: ='9'!$F$16 -> 3.68 | N12: ='9'!$F$17 -> 6.03 | O12: ='9'!$F$18 -> 5.4 | P12: ='9'!$F$19 | Q12: ='9'!$F$20 -> 4.43 | R12: ='9'!$F$21 | S12: ='9'!$F$22 -> 4.06 | T12: ='9'!$F$23 -> 3.7 | U12: ='9'!$F$24 -> 5.23 | V12: ='9'!$F$25 | W12: ='9'!$F$26 -> 6.09 | X12: ='9'!$F$27 -> 7 | Y12: ='9'!$F$28 -> 4.81 | Z12: ='9'!$F$29 -> 3.32 | AA12: ='9'!$F$30 -> 6.12 | AB12: ='9'!$F$31 | AC12: ='9'!$F$32 | AD12: ='9'!$F$33 -> 4.14
A13: Clarendon | B13: ='10'!$F$5 -> 9.45 | C13: ='10'!$F$6 | D13: ='10'!$F$7 -> 6.43 | E13: ='10'!$F$8 -> 8.9 | F13: ='10'!$F$9 | G13: ='10'!$F$10 | H13: ='10'!$F$11 -> 7.1 | I13: ='10'!$F$12 | J13: ='10'!$F$13 -> 4.2 | K13: ='10'!$F$14 | L13: ='10'!$F$15 -> 8.49 | M13: ='10'!$F$16 -> 6.2 | N13: ='10'!$F$17 -> 4.78 | O13: ='10'!$F$18 | P13: ='10'!$F$19 | Q13: ='10'!$F$20 -> 4.07 | R13: ='10'!$F$21 | S13: ='10'!$F$22 -> 8.15 | T13: ='10'!$F$23 -> 4.67 | U13: ='10'!$F$24 | V13: ='10'!$F$25 | W13: ='10'!$F$26 | X13: ='10'!$F$27 -> 9.7 | Y13: ='10'!$F$28 | Z13: ='10'!$F$29 -> 6.13 | AA13: ='10'!$F$30 -> 14.93 | AB13: ='10'!$F$31 | AC13: ='10'!$F$32 | AD13: ='10'!$F$33 -> 7.01
A14: Coastal Bend | B14: ='11'!$F$5 -> 3.59 | C14: ='11'!$F$6 -> 7.69 | D14: ='11'!$F$7 -> 3.94 | E14: ='11'!$F$8 -> 5.2 | F14: ='11'!$F$9 | G14: ='11'!$F$10 | H14: ='11'!$F$11 -> 3.82 | I14: ='11'!$F$12 -> 3.77 | J14: ='11'!$F$13 -> 5.12 | K14: ='11'!$F$14 -> 4.27 | L14: ='11'!$F$15 | M14: ='11'!$F$16 -> 4.4 | N14: ='11'!$F$17 -> 11.59 | O14: ='11'!$F$18 | P14: ='11'!$F$19 -> 7.32 | Q14: ='11'!$F$20 -> 4.71 | R14: ='11'!$F$21 | S14: ='11'!$F$22 -> 3.78 | T14: ='11'!$F$23 -> 4.44 | U14: ='11'!$F$24 -> 5.77 | V14: ='11'!$F$25 | W14: ='11'!$F$26 -> 10.1 | X14: ='11'!$F$27 -> 5.56 | Y14: ='11'!$F$28 -> 4.86 | Z14: ='11'!$F$29 -> 4.39 | AA14: ='11'!$F$30 -> 8.76 | AB14: ='11'!$F$31 | AC14: ='11'!$F$32 | AD14: ='11'!$F$33 -> 4.88
A15: College Of The Mainland | B15: ='12'!$F$5 | C15: ='12'!$F$6 | D15: ='12'!$F$7 -> 7.7 | E15: ='12'!$F$8 -> 10.4 | F15: ='12'!$F$9 | G15: ='12'!$F$10 -> 30.94 | H15: ='12'!$F$11 | I15: ='12'!$F$12 | J15: ='12'!$F$13 -> 10.39 | K15: ='12'!$F$14 | L15: ='12'!$F$15 | M15: ='12'!$F$16 -> 9.53 | N15: ='12'!$F$17 | O15: ='12'!$F$18 -> 10.03 | P15: ='12'!$F$19 | Q15: ='12'!$F$20 | R15: ='12'!$F$21 | S15: ='12'!$F$22 | T15: ='12'!$F$23 -> 7.09 | U15: ='12'!$F$24 | V15: ='12'!$F$25 -> 12.87 | W15: ='12'!$F$26 -> 8.77 | X15: ='12'!$F$27 -> 9.11 | Y15: ='12'!$F$28 -> 7.48 | Z15: ='12'!$F$29 -> 7.17 | AA15: ='12'!$F$30 -> 11.05 | AB15: ='12'!$F$31 | AC15: ='12'!$F$32 | AD15: ='12'!$F$33 -> 8.8
A16: Collin | B16: ='13'!$F$5 -> 11.07 | C16: ='13'!$F$6 -> 7.91 | D16: ='13'!$F$7 -> 6.41 | E16: ='13'!$F$8 -> 8.19 | F16: ='13'!$F$9 -> 7.37 | G16: ='13'!$F$10 -> 4.35 | H16: ='13'!$F$11 -> 6.31 | I16: ='13'!$F$12 | J16: ='13'!$F$13 -> 8.71 | K16: ='13'!$F$14 -> 5.36 | L16: ='13'!$F$15 -> 7.42 | M16: ='13'!$F$16 -> 6.38 | N16: ='13'!$F$17 -> 7.24 | O16: ='13'!$F$18 -> 13.82 | P16: ='13'!$F$19 -> 16.09 | Q16: ='13'!$F$20 -> 7.36 | R16: ='13'!$F$21 -> 8.88 | S16: ='13'!$F$22 -> 9.39 | T16: ='13'!$F$23 -> 5.5 | U16: ='13'!$F$24 | V16: ='13'!$F$25 | W16: ='13'!$F$26 -> 10.43 | X16: ='13'!$F$27 -> 10.05 | Y16: ='13'!$F$28 -> 8.03 | Z16: ='13'!$F$29 -> 6.21 | AA16: ='13'!$F$30 -> 9.41 | AB16: ='13'!$F$31 | AC16: ='13'!$F$32 | AD16: ='13'!$F$33 -> 6.97
A17: Dallas | B17: ='14'!$F$5 -> 12.63 | C17: ='14'!$F$6 -> 4.82 | D17: ='14'!$F$7 -> 6.52 | E17: ='14'!$F$8 -> 6.66 | F17: ='14'!$F$9 -> 22.92 | G17: ='14'!$F$10 -> 9.6 | H17: ='14'!$F$11 -> 6.86 | I17: ='14'!$F$12 -> 12.21 | J17: ='14'!$F$13 -> 4.31 | K17: ='14'!$F$14 -> 6.91 | L17: ='14'!$F$15 -> 3.83 | M17: ='14'!$F$16 -> 6.08 | N17: ='14'!$F$17 -> 6.06 | O17: ='14'!$F$18 -> 11.34 | P17: ='14'!$F$19 | Q17: ='14'!$F$20 -> 6.43 | R17: ='14'!$F$21 -> 12.99 | S17: ='14'!$F$22 -> 8.13 | T17: ='14'!$F$23 -> 5.68 | U17: ='14'!$F$24 -> 7.01 | V17: ='14'!$F$25 -> 3.47 | W17: ='14'!$F$26 -> 16.38 | X17: ='14'!$F$27 -> 7.99 | Y17: ='14'!$F$28 -> 4.53 | Z17: ='14'!$F$29 -> 5.89 | AA17: ='14'!$F$30 -> 8.85 | AB17: ='14'!$F$31 | AC17: ='14'!$F$32 | AD17: ='14'!$F$33 -> 6.42
A18: Del Mar | B18: ='15'!$F$5 | C18: ='15'!$F$6 | D18: ='15'!$F$7 | E18: ='15'!$F$8 | F18: ='15'!$F$9 | G18: ='15'!$F$10 | H18: ='15'!$F$11 | I18: ='15'!$F$12 | J18: ='15'!$F$13 | K18: ='15'!$F$14 | L18: ='15'!$F$15 | M18: ='15'!$F$16 | N18: ='15'!$F$17 | O18: ='15'!$F$18 | P18: ='15'!$F$19 | Q18: ='15'!$F$20 | R18: ='15'!$F$21 | S18: ='15'!$F$22 | T18: ='15'!$F$23 | U18: ='15'!$F$24 | V18: ='15'!$F$25 | W18: ='15'!$F$26 | X18: ='15'!$F$27 | Y18: ='15'!$F$28 | Z18: ='15'!$F$29 | AA18: ='15'!$F$30 | AB18: ='15'!$F$31 | AC18: ='15'!$F$32 | AD18: ='15'!$F$33
A19: El Paso | B19: ='16'!$F$5 | C19: ='16'!$F$6 -> 8.85 | D19: ='16'!$F$7 -> 5.74 | E19: ='16'!$F$8 -> 17.52 | F19: ='16'!$F$9 | G19: ='16'!$F$10 -> 12.78 | H19: ='16'!$F$11 -> 6.47 | I19: ='16'!$F$12 | J19: ='16'!$F$13 -> 7.13 | K19: ='16'!$F$14 -> 9.36 | L19: ='16'!$F$15 -> 6.03 | M19: ='16'!$F$16 -> 6.31 | N19: ='16'!$F$17 -> 6.72 | O19: ='16'!$F$18 -> 10.16 | P19: ='16'!$F$19 -> 17.76 | Q19: ='16'!$F$20 -> 10.56 | R19: ='16'!$F$21 -> 11.9 | S19: ='16'!$F$22 | T19: ='16'!$F$23 -> 5.83 | U19: ='16'!$F$24 -> 6.92 | V19: ='16'!$F$25 | W19: ='16'!$F$26 -> 9.57 | X19: ='16'!$F$27 -> 7.29 | Y19: ='16'!$F$28 -> 6.85 | Z19: ='16'!$F$29 -> 6.03 | AA19: ='16'!$F$30 -> 7.03 | AB19: ='16'!$F$31 | AC19: ='16'!$F$32 | AD19: ='16'!$F$33 -> 7.09
A20: Frank Phillips | B20: ='17'!$F$5 -> 8.22 | C20: ='17'!$F$6 -> 4.85 | D20: ='17'!$F$7 -> 6.34 | E20: ='17'!$F$8 -> 6.87 | F20: ='17'!$F$9 | G20: ='17'!$F$10 -> 10.35 | H20: ='17'!$F$11 -> 4.22 | I20: ='17'!$F$12 -> 5.66 | J20: ='17'!$F$13 -> 4.64 | K20: ='17'!$F$14 | L20: ='17'!$F$15 -> 4.45 | M20: ='17'!$F$16 -> 4.52 | N20: ='17'!$F$17 -> 5.01 | O20: ='17'!$F$18 -> 6.55 | P20: ='17'!$F$19 | Q20: ='17'!$F$20 -> 5.53 | R20: ='17'!$F$21 | S20: ='17'!$F$22 -> 5.19 | T20: ='17'!$F$23 -> 4.75 | U20: ='17'!$F$24 | V20: ='17'!$F$25 | W20: ='17'!$F$26 -> 4.04 | X20: ='17'!$F$27 -> 7.68 | Y20: ='17'!$F$28 -> 5.64 | Z20: ='17'!$F$29 -> 5.25 | AA20: ='17'!$F$30 -> 8.35 | AB20: ='17'!$F$31 | AC20: ='17'!$F$32 | AD20: ='17'!$F$33 -> 5.44
A21: Galveston | B21: ='18'!$F$5 | C21: ='18'!$F$6 -> 5.46 | D21: ='18'!$F$7 -> 7.89 | E21: ='18'!$F$8 -> 6.64 | F21: ='18'!$F$9 | G21: ='18'!$F$10 | H21: ='18'!$F$11 -> 7.35 | I21: ='18'!$F$12 -> 7.16 | J21: ='18'!$F$13 -> 6.43 | K21: ='18'!$F$14 | L21: ='18'!$F$15 -> 6.36 | M21: ='18'!$F$16 -> 6.63 | N21: ='18'!$F$17 -> 5.57 | O21: ='18'!$F$18 -> 10.47 | P21: ='18'!$F$19 | Q21: ='18'!$F$20 -> 8.23 | R21: ='18'!$F$21 | S21: ='18'!$F$22 -> 6.93 | T21: ='18'!$F$23 -> 6.16 | U21: ='18'!$F$24 | V21: ='18'!$F$25 | W21: ='18'!$F$26 | X21: ='18'!$F$27 -> 8.24 | Y21: ='18'!$F$28 -> 6.17 | Z21: ='18'!$F$29 -> 7.54 | AA21: ='18'!$F$30 -> 8.99 | AB21: ='18'!$F$31 | AC21: ='18'!$F$32 | AD21: ='18'!$F$33 -> 7.33
A22: Grayson | B22: ='19'!$F$5 -> 6.31 | C22: ='19'!$F$6 -> 8.04 | D22: ='19'!$F$7 -> 5.23 | E22: ='19'!$F$8 -> 5.69 | F22: ='19'!$F$9 | G22: ='19'!$F$10 | H22: ='19'!$F$11 -> 6.53 | I22: ='19'!$F$12 -> 2.91 | J22: ='19'!$F$13 -> 5.32 | K22: ='19'!$F$14 -> 6.88 | L22: ='19'!$F$15 -> 5.32 | M22: ='19'!$F$16 -> 5.15 | N22: ='19'!$F$17 -> 5.16 | O22: ='19'!$F$18 -> 8.23 | P22: ='19'!$F$19 | Q22: ='19'!$F$20 -> 6.72 | R22: ='19'!$F$21 | S22: ='19'!$F$22 -> 4.52 | T22: ='19'!$F$23 -> 4.37 | U22: ='19'!$F$24 -> 7.43 | V22: ='19'!$F$25 -> 2.43 | W22: ='19'!$F$26 -> 7.63 | X22: ='19'!$F$27 -> 6.39 | Y22: ='19'!$F$28 -> 5.66 | Z22: ='19'!$F$29 -> 4.65 | AA22: ='19'!$F$30 -> 6.75 | AB22: ='19'!$F$31 | AC22: ='19'!$F$32 | AD22: ='19'!$F$33 -> 5.7
A23: Hill | B23: ='20'!$F$5 -> 7.28 | C23: ='20'!$F$6 -> 7.53 | D23: ='20'!$F$7 -> 5.37 | E23: ='20'!$F$8 -> 2.98 | F23: ='20'!$F$9 | G23: ='20'!$F$10 | H23: ='20'!$F$11 -> 5.66 | I23: ='20'!$F$12 | J23: ='20'!$F$13 -> 4.26 | K23: ='20'!$F$14 | L23: ='20'!$F$15 -> 6.96 | M23: ='20'!$F$16 -> 4.28 | N23: ='20'!$F$17 -> 4.84 | O23: ='20'!$F$18 | P23: ='20'!$F$19 | Q23: ='20'!$F$20 -> 4.28 | R23: ='20'!$F$21 | S23: ='20'!$F$22 -> 6.11 | T23: ='20'!$F$23 -> 4.03 | U23: ='20'!$F$24 -> 6.09 | V23: ='20'!$F$25 | W23: ='20'!$F$26 -> 7.4 | X23: ='20'!$F$27 -> 5.95 | Y23: ='20'!$F$28 -> 5.47 | Z23: ='20'!$F$29 -> 5.48 | AA23: ='20'!$F$30 -> 5.38 | AB23: ='20'!$F$31 | AC23: ='20'!$F$32 | AD23: ='20'!$F$33 -> 5.12
A24: Houston | B24: ='21'!$F$5 -> 5.78 | C24: ='21'!$F$6 -> 5.4 | D24: ='21'!$F$7 -> 5.95 | E24: ='21'!$F$8 -> 7.04 | F24: ='21'!$F$9 | G24: ='21'!$F$10 -> 8.27 | H24: ='21'!$F$11 -> 7.55 | I24: ='21'!$F$12 -> 6.67 | J24: ='21'!$F$13 -> 6.62 | K24: ='21'!$F$14 -> 7.4 | L24: ='21'!$F$15 -> 7.46 | M24: ='21'!$F$16 -> 6.14 | N24: ='21'!$F$17 -> 6.84 | O24: ='21'!$F$18 -> 11.6 | P24: ='21'!$F$19 | Q24: ='21'!$F$20 -> 8.77 | R24: ='21'!$F$21 -> 11.42 | S24: ='21'!$F$22 -> 8.28 | T24: ='21'!$F$23 -> 5.82 | U24: ='21'!$F$24 -> 11.11 | V24: ='21'!$F$25 -> 10.23 | W24: ='21'!$F$26 -> 4.54 | X24: ='21'!$F$27 -> 5.76 | Y24: ='21'!$F$28 -> 6.59 | Z24: ='21'!$F$29 -> 5.9 | AA24: ='21'!$F$30 -> 7.95 | AB24: ='21'!$F$31 | AC24: ='21'!$F$32 | AD24: ='21'!$F$33 -> 6.71
A25: Howard | B25: ='22'!$F$5 -> 4.76 | C25: ='22'!$F$6 -> 4.96 | D25: ='22'!$F$7 -> 4.98 | E25: ='22'!$F$8 -> 4.01 | F25: ='22'!$F$9 -> 3.26 | G25: ='22'!$F$10 -> 3.88 | H25: ='22'!$F$11 -> 7.44 | I25: ='22'!$F$12 -> 3.28 | J25: ='22'!$F$13 -> 3.52 | K25: ='22'!$F$14 | L25: ='22'!$F$15 -> 6.67 | M25: ='22'!$F$16 -> 3.85 | N25: ='22'!$F$17 -> 2.43 | O25: ='22'!$F$18 -> 5.39 | P25: ='22'!$F$19 -> 12.05 | Q25: ='22'!$F$20 -> 4.79 | R25: ='22'!$F$21 -> 6.88 | S25: ='22'!$F$22 -> 11.84 | T25: ='22'!$F$23 -> 4.31 | U25: ='22'!$F$24 -> 2.25 | V25: ='22'!$F$25 -> 2.77 | W25: ='22'!$F$26 -> 3.95 | X25: ='22'!$F$27 -> 9.74 | Y25: ='22'!$F$28 -> 2.79 | Z25: ='22'!$F$29 -> 4.83 | AA25: ='22'!$F$30 -> 7.9 | AB25: ='22'!$F$31 | AC25: ='22'!$F$32 | AD25: ='22'!$F$33 -> 4.65
A26: Kilgore | B26: ='23'!$F$5 | C26: ='23'!$F$6 | D26: ='23'!$F$7 | E26: ='23'!$F$8 | F26: ='23'!$F$9 | G26: ='23'!$F$10 | H26: ='23'!$F$11 | I26: ='23'!$F$12 | J26: ='23'!$F$13 | K26: ='23'!$F$14 | L26: ='23'!$F$15 | M26: ='23'!$F$16 | N26: ='23'!$F$17 | O26: ='23'!$F$18 | P26: ='23'!$F$19 | Q26: ='23'!$F$20 | R26: ='23'!$F$21 | S26: ='23'!$F$22 | T26: ='23'!$F$23 | U26: ='23'!$F$24 | V26: ='23'!$F$25 | W26: ='23'!$F$26 | X26: ='23'!$F$27 | Y26: ='23'!$F$28 | Z26: ='23'!$F$29 | AA26: ='23'!$F$30 | AB26: ='23'!$F$31 | AC26: ='23'!$F$32 | AD26: ='23'!$F$33
A27: Laredo | B27: ='24'!$F$5 | C27: ='24'!$F$6 -> 6.76 | D27: ='24'!$F$7 -> 7.01 | E27: ='24'!$F$8 -> 6.79 | F27: ='24'!$F$9 | G27: ='24'!$F$10 | H27: ='24'!$F$11 -> 6.05 | I27: ='24'!$F$12 -> 11.22 | J27: ='24'!$F$13 -> 6.3 | K27: ='24'!$F$14 | L27: ='24'!$F$15 -> 5.27 | M27: ='24'!$F$16 -> 6.08 | N27: ='24'!$F$17 -> 21.97 | O27: ='24'!$F$18 -> 12.94 | P27: ='24'!$F$19 | Q27: ='24'!$F$20 -> 6.16 | R27: ='24'!$F$21 | S27: ='24'!$F$22 -> 10.07 | T27: ='24'!$F$23 -> 5.5 | U27: ='24'!$F$24 -> 11.94 | V27: ='24'!$F$25 | W27: ='24'!$F$26 -> 7.85 | X27: ='24'!$F$27 -> 5.69 | Y27: ='24'!$F$28 -> 4.8 | Z27: ='24'!$F$29 -> 5.34 | AA27: ='24'!$F$30 -> 8.58 | AB27: ='24'!$F$31 | AC27: ='24'!$F$32 | AD27: ='24'!$F$33 -> 6.46
A28: Lee | B28: ='25'!$F$5 -> 6.03 | C28: ='25'!$F$6 -> 6.23 | D28: ='25'!$F$7 -> 9.47 | E28: ='25'!$F$8 -> 8.18 | F28: ='25'!$F$9 -> 11.08 | G28: ='25'!$F$10 -> 19.8 | H28: ='25'!$F$11 -> 7.07 | I28: ='25'!$F$12 -> 6.53 | J28: ='25'!$F$13 -> 6.98 | K28: ='25'!$F$14 | L28: ='25'!$F$15 -> 6.76 | M28: ='25'!$F$16 -> 8.91 | N28: ='25'!$F$17 -> 8.43 | O28: ='25'!$F$18 -> 12.68 | P28: ='25'!$F$19 | Q28: ='25'!$F$20 -> 7.28 | R28: ='25'!$F$21 | S28: ='25'!$F$22 -> 8.02 | T28: ='25'!$F$23 -> 7.33 | U28: ='25'!$F$24 -> 6.06 | V28: ='25'!$F$25 -> 11 | W28: ='25'!$F$26 -> 8.68 | X28: ='25'!$F$27 -> 8.28 | Y28: ='25'!$F$28 -> 7.48 | Z28: ='25'!$F$29 -> 8.28 | AA28: ='25'!$F$30 -> 19.85 | AB28: ='25'!$F$31 | AC28: ='25'!$F$32 | AD28: ='25'!$F$33 -> 8.02
A29: Lonestar | B29: ='26'!$F$5 -> 11.2 | C29: ='26'!$F$6 -> 7.34 | D29: ='26'!$F$7 -> 6.75 | E29: ='26'!$F$8 -> 6.92 | F29: ='26'!$F$9 -> 17.3 | G29: ='26'!$F$10 -> 10.1 | H29: ='26'!$F$11 -> 7.06 | I29: ='26'!$F$12 -> 7.89 | J29: ='26'!$F$13 -> 6.88 | K29: ='26'!$F$14 -> 8.8 | L29: ='26'!$F$15 -> 7.83 | M29: ='26'!$F$16 -> 6.63 | N29: ='26'!$F$17 -> 6.3 | O29: ='26'!$F$18 -> 9.64 | P29: ='26'!$F$19 | Q29: ='26'!$F$20 -> 7.38 | R29: ='26'!$F$21 -> 8.81 | S29: ='26'!$F$22 -> 6.97 | T29: ='26'!$F$23 -> 6.07 | U29: ='26'!$F$24 -> 8.27 | V29: ='26'!$F$25 | W29: ='26'!$F$26 -> 8.73 | X29: ='26'!$F$27 -> 7.22 | Y29: ='26'!$F$28 -> 5.7 | Z29: ='26'!$F$29 -> 6.36 | AA29: ='26'!$F$30 -> 8.47 | AB29: ='26'!$F$31 | AC29: ='26'!$F$32 | AD29: ='26'!$F$33 -> 6.82
A30: Mclennan | B30: ='27'!$F$5 | C30: ='27'!$F$6 -> 10.61 | D30: ='27'!$F$7 -> 4.92 | E30: ='27'!$F$8 -> 5.34 | F30: ='27'!$F$9 | G30: ='27'!$F$10 -> 7.36 | H30: ='27'!$F$11 -> 7.29 | I30: ='27'!$F$12 -> 10.33 | J30: ='27'!$F$13 -> 9.33 | K30: ='27'!$F$14 -> 11.69 | L30: ='27'!$F$15 -> 3.82 | M30: ='27'!$F$16 -> 5.53 | N30: ='27'!$F$17 -> 4.58 | O30: ='27'!$F$18 -> 9.54 | P30: ='27'!$F$19 | Q30: ='27'!$F$20 -> 7.42 | R30: ='27'!$F$21 -> 8.68 | S30: ='27'!$F$22 -> 4.36 | T30: ='27'!$F$23 -> 5.17 | U30: ='27'!$F$24 | V30: ='27'!$F$25 | W30: ='27'!$F$26 | X30: ='27'!$F$27 -> 7.11 | Y30: ='27'!$F$28 -> 5.5 | Z30: ='27'!$F$29 -> 3.83 | AA30: ='27'!$F$30 -> 8.66 | AB30: ='27'!$F$31 | AC30: ='27'!$F$32 | AD30: ='27'!$F$33 -> 6.12
A31: Midland | B31: ='28'!$F$5 -> 15.88 | C31: ='28'!$F$6 -> 6.81 | D31: ='28'!$F$7 -> 5.61 | E31: ='28'!$F$8 -> 5.42 | F31: ='28'!$F$9 | G31: ='28'!$F$10 -> 9.67 | H31: ='28'!$F$11 -> 5.23 | I31: ='28'!$F$12 -> 6.38 | J31: ='28'!$F$13 -> 6.22 | K31: ='28'!$F$14 | L31: ='28'!$F$15 -> 10.94 | M31: ='28'!$F$16 -> 6.98 | N31: ='28'!$F$17 -> 5.28 | O31: ='28'!$F$18 -> 9.55 | P31: ='28'!$F$19 | Q31: ='28'!$F$20 -> 7.76 | R31: ='28'!$F$21 -> 10.16 | S31: ='28'!$F$22 -> 13.67 | T31: ='28'!$F$23 -> 5.42 | U31: ='28'!$F$24 -> 7.57 | V31: ='28'!$F$25 -> 10.56 | W31: ='28'!$F$26 | X31: ='28'!$F$27 -> 8.64 | Y31: ='28'!$F$28 -> 7.04 | Z31: ='28'!$F$29 -> 5.84 | AA31: ='28'!$F$30 -> 8.46 | AB31: ='28'!$F$31 | AC31: ='28'!$F$32 | AD31: ='28'!$F$33 -> 6.77
A32: Navarro | B32: ='29'!$F$5 -> 3.26 | C32: ='29'!$F$6 | D32: ='29'!$F$7 -> 4.63 | E32: ='29'!$F$8 -> 6.39 | F32: ='29'!$F$9 -> 30.55 | G32: ='29'!$F$10 -> 31.35 | H32: ='29'!$F$11 -> 4.38 | I32: ='29'!$F$12 | J32: ='29'!$F$13 -> 3.81 | K32: ='29'!$F$14 -> 4.25 | L32: ='29'!$F$15 -> 6.15 | M32: ='29'!$F$16 -> 4.5 | N32: ='29'!$F$17 -> 3.71 | O32: ='29'!$F$18 -> 13.21 | P32: ='29'!$F$19 | Q32: ='29'!$F$20 -> 5.02 | R32: ='29'!$F$21 | S32: ='29'!$F$22 -> 4.71 | T32: ='29'!$F$23 -> 4.54 | U32: ='29'!$F$24 | V32: ='29'!$F$25 -> 16.58 | W32: ='29'!$F$26 -> 2.84 | X32: ='29'!$F$27 -> 5.64 | Y32: ='29'!$F$28 -> 4.11 | Z32: ='29'!$F$29 -> 3.94 | AA32: ='29'!$F$30 -> 6.09 | AB32: ='29'!$F$31 | AC32: ='29'!$F$32 | AD32: ='29'!$F$33 -> 5.17
A33: North Central Texas | B33: ='30'!$F$5 -> 8.06 | C33: ='30'!$F$6 -> 6.6 | D33: ='30'!$F$7 -> 4.44 | E33: ='30'!$F$8 -> 5.12 | F33: ='30'!$F$9 | G33: ='30'!$F$10 -> 5.38 | H33: ='30'!$F$11 -> 6.4 | I33: ='30'!$F$12 | J33: ='30'!$F$13 -> 3.72 | K33: ='30'!$F$14 | L33: ='30'!$F$15 -> 20.73 | M33: ='30'!$F$16 -> 4.41 | N33: ='30'!$F$17 -> 4.73 | O33: ='30'!$F$18 -> 6.65 | P33: ='30'!$F$19 | Q33: ='30'!$F$20 -> 8.63 | R33: ='30'!$F$21 | S33: ='30'!$F$22 -> 5.66 | T33: ='30'!$F$23 -> 3.52 | U33: ='30'!$F$24 | V33: ='30'!$F$25 | W33: ='30'!$F$26 -> 6.34 | X33: ='30'!$F$27 -> 5.4 | Y33: ='30'!$F$28 -> 4.71 | Z33: ='30'!$F$29 -> 3.76 | AA33: ='30'!$F$30 -> 5.84 | AB33: ='30'!$F$31 | AC33: ='30'!$F$32 | AD33: ='30'!$F$33 -> 5.05
A34: Northeast Texas | B34: ='31'!$F$5 -> 6.62 | C34: ='31'!$F$6 -> 6.07 | D34: ='31'!$F$7 -> 6.45 | E34: ='31'!$F$8 -> 7.07 | F34: ='31'!$F$9 | G34: ='31'!$F$10 -> 9.85 | H34: ='31'!$F$11 -> 6.18 | I34: ='31'!$F$12 | J34: ='31'!$F$13 -> 4.97 | K34: ='31'!$F$14 | L34: ='31'!$F$15 | M34: ='31'!$F$16 -> 5.08 | N34: ='31'!$F$17 -> 8.23 | O34: ='31'!$F$18 -> 10.71 | P34: ='31'!$F$19 -> 12.1 | Q34: ='31'!$F$20 -> 10.44 | R34: ='31'!$F$21 | S34: ='31'!$F$22 -> 5.11 | T34: ='31'!$F$23 -> 6.24 | U34: ='31'!$F$24 -> 10.98 | V34: ='31'!$F$25 -> 6.21 | W34: ='31'!$F$26 | X34: ='31'!$F$27 -> 5.85 | Y34: ='31'!$F$28 -> 6.31 | Z34: ='31'!$F$29 -> 5.43 | AA34: ='31'!$F$30 -> 9.27 | AB34: ='31'!$F$31 | AC34: ='31'!$F$32 | AD34: ='31'!$F$33 -> 6.26
A35: Odessa | B35: ='32'!$F$5 -> 5.32 | C35: ='32'!$F$6 -> 8.27 | D35: ='32'!$F$7 -> 6.13 | E35: ='32'!$F$8 -> 7.36 | F35: ='32'!$F$9 | G35: ='32'!$F$10 -> 8.8 | H35: ='32'!$F$11 -> 7.32 | I35: ='32'!$F$12 -> 5.35 | J35: ='32'!$F$13 -> 6.38 | K35: ='32'!$F$14 | L35: ='32'!$F$15 -> 9.11 | M35: ='32'!$F$16 -> 6.05 | N35: ='32'!$F$17 -> 6.26 | O35: ='32'!$F$18 -> 11.12 | P35: ='32'!$F$19 | Q35: ='32'!$F$20 -> 7.25 | R35: ='32'!$F$21 -> 8.03 | S35: ='32'!$F$22 -> 6.06 | T35: ='32'!$F$23 -> 5.54 | U35: ='32'!$F$24 -> 5.75 | V35: ='32'!$F$25 -> 13.95 | W35: ='32'!$F$26 -> 6.42 | X35: ='32'!$F$27 -> 6.19 | Y35: ='32'!$F$28 -> 6.88 | Z35: ='32'!$F$29 -> 5.88 | AA35: ='32'!$F$30 -> 10.02 | AB35: ='32'!$F$31 | AC35: ='32'!$F$32 | AD35: ='32'!$F$33 -> 6.88
A36: Panola | B36: ='33'!$F$5 -> 8.46 | C36: ='33'!$F$6 -> 7.12 | D36: ='33'!$F$7 -> 6.76 | E36: ='33'!$F$8 -> 8.9 | F36: ='33'!$F$9 | G36: ='33'!$F$10 -> 19.85 | H36: ='33'!$F$11 -> 6.65 | I36: ='33'!$F$12 | J36: ='33'!$F$13 -> 5.36 | K36: ='33'!$F$14 -> 7.56 | L36: ='33'!$F$15 -> 6 | M36: ='33'!$F$16 -> 5.88 | N36: ='33'!$F$17 -> 12.84 | O36: ='33'!$F$18 -> 14.64 | P36: ='33'!$F$19 | Q36: ='33'!$F$20 -> 7.98 | R36: ='33'!$F$21 | S36: ='33'!$F$22 -> 6.06 | T36: ='33'!$F$23 -> 5.86 | U36: ='33'!$F$24 | V36: ='33'!$F$25 | W36: ='33'!$F$26 | X36: ='33'!$F$27 -> 6.22 | Y36: ='33'!$F$28 | Z36: ='33'!$F$29 -> 5.89 | AA36: ='33'!$F$30 -> 9.48 | AB36: ='33'!$F$31 | AC36: ='33'!$F$32 | AD36: ='33'!$F$33 -> 7.05
A37: Paris | B37: ='34'!$F$5 -> 9.35 | C37: ='34'!$F$6 -> 7.43 | D37: ='34'!$F$7 -> 4.4 | E37: ='34'!$F$8 -> 5.52 | F37: ='34'!$F$9 | G37: ='34'!$F$10 -> 12.67 | H37: ='34'!$F$11 -> 4.54 | I37: ='34'!$F$12 | J37: ='34'!$F$13 -> 3.33 | K37: ='34'!$F$14 -> 29.94 | L37: ='34'!$F$15 -> 5.59 | M37: ='34'!$F$16 -> 4.34 | N37: ='34'!$F$17 -> 5.2 | O37: ='34'!$F$18 -> 14.51 | P37: ='34'!$F$19 | Q37: ='34'!$F$20 -> 2.16 | R37: ='34'!$F$21 | S37: ='34'!$F$22 -> 7.13 | T37: ='34'!$F$23 -> 3.44 | U37: ='34'!$F$24 | V37: ='34'!$F$25 | W37: ='34'!$F$26 -> 4.85 | X37: ='34'!$F$27 -> 4.9 | Y37: ='34'!$F$28 -> 2.16 | Z37: ='34'!$F$29 -> 4.02 | AA37: ='34'!$F$30 -> 9.56 | AB37: ='34'!$F$31 | AC37: ='34'!$F$32 | AD37: ='34'!$F$33 -> 4.99
A38: Ranger | B38: ='35'!$F$5 -> 3.54 | C38: ='35'!$F$6 -> 6.57 | D38: ='35'!$F$7 -> 4.37 | E38: ='35'!$F$8 -> 4.65 | F38: ='35'!$F$9 | G38: ='35'!$F$10 -> 3.78 | H38: ='35'!$F$11 -> 4.82 | I38: ='35'!$F$12 | J38: ='35'!$F$13 -> 4.57 | K38: ='35'!$F$14 | L38: ='35'!$F$15 | M38: ='35'!$F$16 -> 4.42 | N38: ='35'!$F$17 -> 3.26 | O38: ='35'!$F$18 | P38: ='35'!$F$19 | Q38: ='35'!$F$20 | R38: ='35'!$F$21 | S38: ='35'!$F$22 -> 4.14 | T38: ='35'!$F$23 -> 4.35 | U38: ='35'!$F$24 -> 7.86 | V38: ='35'!$F$25 | W38: ='35'!$F$26 | X38: ='35'!$F$27 -> 10.18 | Y38: ='35'!$F$28 -> 2.4 | Z38: ='35'!$F$29 -> 4.02 | AA38: ='35'!$F$30 -> 5.45 | AB38: ='35'!$F$31 | AC38: ='35'!$F$32 | AD38: ='35'!$F$33 -> 4.97
A39: San Jacinto | B39: ='36'!$F$5 -> 3.87 | C39: ='36'!$F$6 -> 5.89 | D39: ='36'!$F$7 -> 4.66 | E39: ='36'!$F$8 -> 6.83 | F39: ='36'!$F$9 -> 10.77 | G39: ='36'!$F$10 -> 10.01 | H39: ='36'!$F$11 -> 6.43 | I39: ='36'!$F$12 -> 4.57 | J39: ='36'!$F$13 -> 7.15 | K39: ='36'!$F$14 -> 381.63 | L39: ='36'!$F$15 -> 8.27 | M39: ='36'!$F$16 -> 4.63 | N39: ='36'!$F$17 -> 6.56 | O39: ='36'!$F$18 -> 6.85 | P39: ='36'!$F$19 | Q39: ='36'!$F$20 -> 8.69 | R39: ='36'!$F$21 -> 9.28 | S39: ='36'!$F$22 -> 8.78 | T39: ='36'!$F$23 -> 6.54 | U39: ='36'!$F$24 -> 9.41 | V39: ='36'!$F$25 -> 12.41 | W39: ='36'!$F$26 -> 8.91 | X39: ='36'!$F$27 -> 80.07 | Y39: ='36'!$F$28 -> 6.01 | Z39: ='36'!$F$29 -> 5.33 | AA39: ='36'!$F$30 -> 7.39 | AB39: ='36'!$F$31 | AC39: ='36'!$F$32 | AD39: ='36'!$F$33 -> 6.64
A40: South Plains | B40: ='37'!$F$5 -> 8.12 | C40: ='37'!$F$6 -> 8.7 | D40: ='37'!$F$7 -> 5.03 | E40: ='37'!$F$8 -> 6.97 | F40: ='37'!$F$9 | G40: ='37'!$F$10 -> 8.15 | H40: ='37'!$F$11 -> 5.57 | I40: ='37'!$F$12 -> 15.4 | J40: ='37'!$F$13 -> 4.71 | K40: ='37'!$F$14 -> 18.95 | L40: ='37'!$F$15 -> 7.04 | M40: ='37'!$F$16 -> 5.39 | N40: ='37'!$F$17 -> 5.44 | O40: ='37'!$F$18 -> 6.77 | P40: ='37'!$F$19 | Q40: ='37'!$F$20 -> 4.2 | R40: ='37'!$F$21 -> 7.77 | S40: ='37'!$F$22 -> 3.55 | T40: ='37'!$F$23 -> 4.57 | U40: ='37'!$F$24 -> 6.07 | V40: ='37'!$F$25 -> 7.03 | W40: ='37'!$F$26 -> 5.75 | X40: ='37'!$F$27 -> 10.04 | Y40: ='37'!$F$28 -> 6.59 | Z40: ='37'!$F$29 -> 5.15 | AA40: ='37'!$F$30 -> 9.37 | AB40: ='37'!$F$31 | AC40: ='37'!$F$32 | AD40: ='37'!$F$33 -> 5.67
A41: South Texas | B41: ='38'!$F$5 | C41: ='38'!$F$6 -> 10.73 | D41: ='38'!$F$7 -> 4.74 | E41: ='38'!$F$8 -> 12.41 | F41: ='38'!$F$9 | G41: ='38'!$F$10 | H41: ='38'!$F$11 -> 5.05 | I41: ='38'!$F$12 | J41: ='38'!$F$13 -> 6.8 | K41: ='38'!$F$14 -> 6.81 | L41: ='38'!$F$15 -> 22.8 | M41: ='38'!$F$16 -> 4.83 | N41: ='38'!$F$17 -> 4.71 | O41: ='38'!$F$18 -> 16.6 | P41: ='38'!$F$19 | Q41: ='38'!$F$20 -> 15.47 | R41: ='38'!$F$21 | S41: ='38'!$F$22 -> 5.44 | T41: ='38'!$F$23 -> 4.39 | U41: ='38'!$F$24 -> 6.83 | V41: ='38'!$F$25 -> 3.75 | W41: ='38'!$F$26 -> 5.6 | X41: ='38'!$F$27 -> 6.05 | Y41: ='38'!$F$28 -> 2.77 | Z41: ='38'!$F$29 -> 4.46 | AA41: ='38'!$F$30 -> 4.35 | AB41: ='38'!$F$31 | AC41: ='38'!$F$32 | AD41: ='38'!$F$33 -> 5.13
A42: Southwest Texas | B42: ='39'!$F$5 -> 9.63 | C42: ='39'!$F$6 | D42: ='39'!$F$7 -> 4.7 | E42: ='39'!$F$8 -> 4.79 | F42: ='39'!$F$9 -> 25.04 | G42: ='39'!$F$10 -> 8.75 | H42: ='39'!$F$11 -> 6.6 | I42: ='39'!$F$12 -> 6.36 | J42: ='39'!$F$13 -> 4.39 | K42: ='39'!$F$14 | L42: ='39'!$F$15 | M42: ='39'!$F$16 -> 5.53 | N42: ='39'!$F$17 -> 5.03 | O42: ='39'!$F$18 | P42: ='39'!$F$19 | Q42: ='39'!$F$20 | R42: ='39'!$F$21 | S42: ='39'!$F$22 -> 5.56 | T42: ='39'!$F$23 -> 5.34 | U42: ='39'!$F$24 -> 6.06 | V42: ='39'!$F$25 -> 6.48 | W42: ='39'!$F$26 -> 2.52 | X42: ='39'!$F$27 -> 5.44 | Y42: ='39'!$F$28 -> 4.23 | Z42: ='39'!$F$29 -> 4.92 | AA42: ='39'!$F$30 -> 4.97 | AB42: ='39'!$F$31 | AC42: ='39'!$F$32 | AD42: ='39'!$F$33 -> 5.25
A43: Tarrant | B43: ='40'!$F$5 -> 7.91 | C43: ='40'!$F$6 -> 9.88 | D43: ='40'!$F$7 -> 6.54 | E43: ='40'!$F$8 -> 7.19 | F43: ='40'!$F$9 | G43: ='40'!$F$10 -> 11.09 | H43: ='40'!$F$11 -> 5.05 | I43: ='40'!$F$12 -> 21.93 | J43: ='40'!$F$13 -> 8.74 | K43: ='40'!$F$14 -> 8.82 | L43: ='40'!$F$15 -> 10.61 | M43: ='40'!$F$16 -> 5.79 | N43: ='40'!$F$17 -> 5.6 | O43: ='40'!$F$18 -> 10.48 | P43: ='40'!$F$19 -> 10.5 | Q43: ='40'!$F$20 -> 6.87 | R43: ='40'!$F$21 -> 10.34 | S43: ='40'!$F$22 -> 4.47 | T43: ='40'!$F$23 -> 5.44 | U43: ='40'!$F$24 -> 8.56 | V43: ='40'!$F$25 -> 9.56 | W43: ='40'!$F$26 -> 6.1 | X43: ='40'!$F$27 -> 7.11 | Y43: ='40'!$F$28 -> 7.92 | Z43: ='40'!$F$29 -> 5.49 | AA43: ='40'!$F$30 -> 7.52 | AB43: ='40'!$F$31 | AC43: ='40'!$F$32 | AD43: ='40'!$F$33 -> 6.37
A44: Temple | B44: ='41'!$F$5 | C44: ='41'!$F$6 | D44: ='41'!$F$7 -> 5.92 | E44: ='41'!$F$8 -> 4.89 | F44: ='41'!$F$9 | G44: ='41'!$F$10 | H44: ='41'!$F$11 -> 5.64 | I44: ='41'!$F$12 -> 33.38 | J44: ='41'!$F$13 -> 29.82 | K44: ='41'!$F$14 -> 6.49 | L44: ='41'!$F$15 -> 8.54 | M44: ='41'!$F$16 -> 5.23 | N44: ='41'!$F$17 -> 6.69 | O44: ='41'!$F$18 -> 8.49 | P44: ='41'!$F$19 -> 17.31 | Q44: ='41'!$F$20 -> 6.91 | R44: ='41'!$F$21 -> 6.77 | S44: ='41'!$F$22 -> 6.09 | T44: ='41'!$F$23 -> 5.69 | U44: ='41'!$F$24 -> 9.33 | V44: ='41'!$F$25 | W44: ='41'!$F$26 -> 2.85 | X44: ='41'!$F$27 -> 5.47 | Y44: ='41'!$F$28 -> 4.03 | Z44: ='41'!$F$29 -> 4.99 | AA44: ='41'!$F$30 -> 9.21 | AB44: ='41'!$F$31 | AC44: ='41'!$F$32 | AD44: ='41'!$F$33 -> 6.18
A45: Texarkana | B45: ='42'!$F$5 -> 5.47 | C45: ='42'!$F$6 -> 3.76 | D45: ='42'!$F$7 -> 4.81 | E45: ='42'!$F$8 -> 4.96 | F45: ='42'!$F$9 | G45: ='42'!$F$10 -> 5.38 | H45: ='42'!$F$11 -> 3.2 | I45: ='42'!$F$12 -> 3.4 | J45: ='42'!$F$13 -> 3.1 | K45: ='42'!$F$14 -> 7.18 | L45: ='42'!$F$15 | M45: ='42'!$F$16 -> 4.14 | N45: ='42'!$F$17 -> 5.1 | O45: ='42'!$F$18 -> 8.15 | P45: ='42'!$F$19 -> 8.1 | Q45: ='42'!$F$20 -> 5.19 | R45: ='42'!$F$21 | S45: ='42'!$F$22 -> 4.07 | T45: ='42'!$F$23 -> 3.77 | U45: ='42'!$F$24 -> 4.71 | V45: ='42'!$F$25 -> 3.79 | W45: ='42'!$F$26 -> 3.91 | X45: ='42'!$F$27 -> 4.71 | Y45: ='42'!$F$28 -> 3.91 | Z45: ='42'!$F$29 -> 3.81 | AA45: ='42'!$F$30 -> 4.45 | AB45: ='42'!$F$31 | AC45: ='42'!$F$32 | AD45: ='42'!$F$33 -> 4.47
A46: Texas Southmost | B46: ='43'!$F$5 | C46: ='43'!$F$6 -> 10.75 | D46: ='43'!$F$7 -> 5.79 | E46: ='43'!$F$8 -> 8.31 | F46: ='43'!$F$9 | G46: ='43'!$F$10 -> 15.02 | H46: ='43'!$F$11 -> 6.38 | I46: ='43'!$F$12 -> 5.5 | J46: ='43'!$F$13 -> 22.08 | K46: ='43'!$F$14 | L46: ='43'!$F$15 -> 4.63 | M46: ='43'!$F$16 -> 5.19 | N46: ='43'!$F$17 -> 7.06 | O46: ='43'!$F$18 -> 7.81 | P46: ='43'!$F$19 | Q46: ='43'!$F$20 -> 7.34 | R46: ='43'!$F$21 -> 9.2 | S46: ='43'!$F$22 -> 8.07 | T46: ='43'!$F$23 -> 5.85 | U46: ='43'!$F$24 -> 4.08 | V46: ='43'!$F$25 -> 12.08 | W46: ='43'!$F$26 -> 12.92 | X46: ='43'!$F$27 -> 5.47 | Y46: ='43'!$F$28 -> 4.56 | Z46: ='43'!$F$29 -> 6.23 | AA46: ='43'!$F$30 -> 7.1 | AB46: ='43'!$F$31 | AC46: ='43'!$F$32 | AD46: ='43'!$F$33 -> 6.43
A47: Trinity Valley | B47: ='44'!$F$5 -> 6.69 | C47: ='44'!$F$6 -> 4.37 | D47: ='44'!$F$7 -> 5.27 | E47: ='44'!$F$8 -> 6.04 | F47: ='44'!$F$9 | G47: ='44'!$F$10 -> 19.5 | H47: ='44'!$F$11 -> 4.05 | I47: ='44'!$F$12 -> 5.67 | J47: ='44'!$F$13 -> 4.16 | K47: ='44'!$F$14 | L47: ='44'!$F$15 -> 3.85 | M47: ='44'!$F$16 -> 5.25 | N47: ='44'!$F$17 -> 5.17 | O47: ='44'!$F$18 -> 6.44 | P47: ='44'!$F$19 | Q47: ='44'!$F$20 -> 6.65 | R47: ='44'!$F$21 | S47: ='44'!$F$22 -> 4.3 | T47: ='44'!$F$23 -> 4.91 | U47: ='44'!$F$24 -> 4.7 | V47: ='44'!$F$25 | W47: ='44'!$F$26 | X47: ='44'!$F$27 -> 5.26 | Y47: ='44'!$F$28 -> 4.31 | Z47: ='44'!$F$29 -> 4.84 | AA47: ='44'!$F$30 -> 5.46 | AB47: ='44'!$F$31 | AC47: ='44'!$F$32 | AD47: ='44'!$F$33 -> 5
A48: Tyler | B48: ='45'!$F$5 -> 8.14 | C48: ='45'!$F$6 -> 9.95 | D48: ='45'!$F$7 -> 5.42 | E48: ='45'!$F$8 -> 4.82 | F48: ='45'!$F$9 | G48: ='45'!$F$10 -> 8.08 | H48: ='45'!$F$11 -> 4.68 | I48: ='45'!$F$12 -> 7.65 | J48: ='45'!$F$13 -> 3.18 | K48: ='45'!$F$14 | L48: ='45'!$F$15 -> 4.7 | M48: ='45'!$F$16 -> 4.98 | N48: ='45'!$F$17 -> 6.03 | O48: ='45'!$F$18 -> 10.04 | P48: ='45'!$F$19 -> 10.99 | Q48: ='45'!$F$20 -> 6.65 | R48: ='45'!$F$21 -> 8.08 | S48: ='45'!$F$22 -> 5.69 | T48: ='45'!$F$23 -> 4.9 | U48: ='45'!$F$24 | V48: ='45'!$F$25 | W48: ='45'!$F$26 | X48: ='45'!$F$27 -> 33.68 | Y48: ='45'!$F$28 -> 4.56 | Z48: ='45'!$F$29 -> 4.83 | AA48: ='45'!$F$30 -> 7.09 | AB48: ='45'!$F$31 | AC48: ='45'!$F$32 | AD48: ='45'!$F$33 -> 5.58
A49: Vernon | B49: ='46'!$F$5 -> 6.67 | C49: ='46'!$F$6 -> 6.63 | D49: ='46'!$F$7 -> 5.38 | E49: ='46'!$F$8 -> 5.95 | F49: ='46'!$F$9 | G49: ='46'!$F$10 | H49: ='46'!$F$11 -> 5.3 | I49: ='46'!$F$12 | J49: ='46'!$F$13 -> 4.66 | K49: ='46'!$F$14 | L49: ='46'!$F$15 -> 3.39 | M49: ='46'!$F$16 -> 5.69 | N49: ='46'!$F$17 -> 6.09 | O49: ='46'!$F$18 -> 6.63 | P49: ='46'!$F$19 | Q49: ='46'!$F$20 -> 5.35 | R49: ='46'!$F$21 | S49: ='46'!$F$22 -> 4.94 | T49: ='46'!$F$23 -> 5.49 | U49: ='46'!$F$24 -> 5.55 | V49: ='46'!$F$25 | W49: ='46'!$F$26 -> 6.13 | X49: ='46'!$F$27 -> 4.43 | Y49: ='46'!$F$28 -> 6.23 | Z49: ='46'!$F$29 -> 4.46 | AA49: ='46'!$F$30 -> 5.59 | AB49: ='46'!$F$31 | AC49: ='46'!$F$32 | AD49: ='46'!$F$33 -> 5.42
A50: Victoria | B50: ='47'!$F$5 -> 5.38 | C50: ='47'!$F$6 -> 10.17 | D50: ='47'!$F$7 -> 7 | E50: ='47'!$F$8 -> 5.4 | F50: ='47'!$F$9 | G50: ='47'!$F$10 | H50: ='47'!$F$11 -> 7.46 | I50: ='47'!$F$12 | J50: ='47'!$F$13 -> 5.42 | K50: ='47'!$F$14 | L50: ='47'!$F$15 -> 7.81 | M50: ='47'!$F$16 -> 6.09 | N50: ='47'!$F$17 -> 6.69 | O50: ='47'!$F$18 -> 12.53 | P50: ='47'!$F$19 | Q50: ='47'!$F$20 -> 8.59 | R50: ='47'!$F$21 -> 8.58 | S50: ='47'!$F$22 -> 5.83 | T50: ='47'!$F$23 -> 5.56 | U50: ='47'!$F$24 | V50: ='47'!$F$25 | W50: ='47'!$F$26 | X50: ='47'!$F$27 -> 6.81 | Y50: ='47'!$F$28 -> 10.92 | Z50: ='47'!$F$29 -> 5.43 | AA50: ='47'!$F$30 -> 7.13 | AB50: ='47'!$F$31 | AC50: ='47'!$F$32 | AD50: ='47'!$F$33 -> 6.77
A51: Weatherford | B51: ='48'!$F$5 -> 7.62 | C51: ='48'!$F$6 -> 3.27 | D51: ='48'!$F$7 -> 4.36 | E51: ='48'!$F$8 -> 5.69 | F51: ='48'!$F$9 | G51: ='48'!$F$10 -> 5.45 | H51: ='48'!$F$11 -> 5.8 | I51: ='48'!$F$12 | J51: ='48'!$F$13 -> 5.24 | K51: ='48'!$F$14 -> 10.02 | L51: ='48'!$F$15 -> 11.78 | M51: ='48'!$F$16 -> 4.62 | N51: ='48'!$F$17 -> 4.65 | O51: ='48'!$F$18 -> 7.61 | P51: ='48'!$F$19 | Q51: ='48'!$F$20 -> 5.33 | R51: ='48'!$F$21 -> 10.34 | S51: ='48'!$F$22 -> 6.87 | T51: ='48'!$F$23 -> 4.56 | U51: ='48'!$F$24 -> 5.06 | V51: ='48'!$F$25 -> 9.05 | W51: ='48'!$F$26 | X51: ='48'!$F$27 -> 6.01 | Y51: ='48'!$F$28 -> 8.51 | Z51: ='48'!$F$29 -> 3.93 | AA51: ='48'!$F$30 -> 9.48 | AB51: ='48'!$F$31 | AC51: ='48'!$F$32 | AD51: ='48'!$F$33 -> 5.66
A52: Western Texas | B52: ='49'!$F$5 -> 6.38 | C52: ='49'!$F$6 -> 8.9 | D52: ='49'!$F$7 -> 5.81 | E52: ='49'!$F$8 -> 8.9 | F52: ='49'!$F$9 | G52: ='49'!$F$10 -> 11.84 | H52: ='49'!$F$11 -> 4.75 | I52: ='49'!$F$12 -> 6.09 | J52: ='49'!$F$13 -> 8.13 | K52: ='49'!$F$14 | L52: ='49'!$F$15 -> 5.19 | M52: ='49'!$F$16 -> 6.17 | N52: ='49'!$F$17 -> 7.88 | O52: ='49'!$F$18 -> 6.49 | P52: ='49'!$F$19 | Q52: ='49'!$F$20 -> 6.98 | R52: ='49'!$F$21 | S52: ='49'!$F$22 -> 5.45 | T52: ='49'!$F$23 -> 4.76 | U52: ='49'!$F$24 -> 7.17 | V52: ='49'!$F$25 -> 13.24 | W52: ='49'!$F$26 -> 11.85 | X52: ='49'!$F$27 -> 10.01 | Y52: ='49'!$F$28 -> 6.15 | Z52: ='49'!$F$29 -> 5.62 | AA52: ='49'!$F$30 -> 8.01 | AB52: ='49'!$F$31 | AC52: ='49'!$F$32 | AD52: ='49'!$F$33 -> 6.28
A53: Wharton | B53: ='50'!$F$5 -> 5.73 | C53: ='50'!$F$6 -> 5.75 | D53: ='50'!$F$7 -> 5.74 | E53: ='50'!$F$8 -> 5.55 | F53: ='50'!$F$9 | G53: ='50'!$F$10 | H53: ='50'!$F$11 -> 5.39 | I53: ='50'!$F$12 -> 3.85 | J53: ='50'!$F$13 -> 5.67 | K53: ='50'!$F$14 -> 5.74 | L53: ='50'!$F$15 -> 5.56 | M53: ='50'!$F$16 -> 5.75 | N53: ='50'!$F$17 -> 5.45 | O53: ='50'!$F$18 -> 5.35 | P53: ='50'!$F$19 -> 5.75 | Q53: ='50'!$F$20 -> 5.08 | R53: ='50'!$F$21 | S53: ='50'!$F$22 -> 5.68 | T53: ='50'!$F$23 -> 5.75 | U53: ='50'!$F$24 -> 5.75 | V53: ='50'!$F$25 | W53: ='50'!$F$26 -> 5.75 | X53: ='50'!$F$27 -> 5.75 | Y53: ='50'!$F$28 -> 5.13 | Z53: ='50'!$F$29 -> 5.75 | AA53: ='50'!$F$30 -> 5.75 | AB53: ='50'!$F$31 | AC53: ='50'!$F$32 | AD53: ='50'!$F$33 -> 5.62
A54: TSTC-Harlingen | B54: ='51'!$F$5 -> 9.06 | C54: ='51'!$F$6 -> 8.18 | D54: ='51'!$F$7 -> 4.33 | E54: ='51'!$F$8 -> 4.41 | F54: ='51'!$F$9 | G54: ='51'!$F$10 | H54: ='51'!$F$11 -> 5.04 | I54: ='51'!$F$12 -> 11.97 | J54: ='51'!$F$13 -> 5.57 | K54: ='51'!$F$14 | L54: ='51'!$F$15 -> 5.48 | M54: ='51'!$F$16 -> 4.2 | N54: ='51'!$F$17 -> 3.51 | O54: ='51'!$F$18 -> 9.46 | P54: ='51'!$F$19 -> 19.57 | Q54: ='51'!$F$20 -> 7.18 | R54: ='51'!$F$21 | S54: ='51'!$F$22 | T54: ='51'!$F$23 -> 3.49 | U54: ='51'!$F$24 -> 7.23 | V54: ='51'!$F$25 -> 9.89 | W54: ='51'!$F$26 -> 4.02 | X54: ='51'!$F$27 | Y54: ='51'!$F$28 -> 4.38 | Z54: ='51'!$F$29 -> 3.48 | AA54: ='51'!$F$30 -> 2.92 | AB54: ='51'!$F$31 | AC54: ='51'!$F$32 | AD54: ='51'!$F$33 -> 4.86
A55: TSTC-West Texas | B55: ='52'!$F$5 -> 6.19 | C55: ='52'!$F$6 -> 5.43 | D55: ='52'!$F$7 -> 5.49 | E55: ='52'!$F$8 -> 6.36 | F55: ='52'!$F$9 | G55: ='52'!$F$10 | H55: ='52'!$F$11 -> 4.93 | I55: ='52'!$F$12 -> 8.6 | J55: ='52'!$F$13 | K55: ='52'!$F$14 | L55: ='52'!$F$15 -> 7.55 | M55: ='52'!$F$16 -> 7.04 | N55: ='52'!$F$17 | O55: ='52'!$F$18 | P55: ='52'!$F$19 | Q55: ='52'!$F$20 -> 7 | R55: ='52'!$F$21 | S55: ='52'!$F$22 -> 4.71 | T55: ='52'!$F$23 -> 5.56 | U55: ='52'!$F$24 -> 4.91 | V55: ='52'!$F$25 -> 6.34 | W55: ='52'!$F$26 -> 6.89 | X55: ='52'!$F$27 | Y55: ='52'!$F$28 -> 3.56 | Z55: ='52'!$F$29 -> 5.18 | AA55: ='52'!$F$30 -> 8.6 | AB55: ='52'!$F$31 | AC55: ='52'!$F$32 | AD55: ='52'!$F$33 -> 5.67
A56: TSTC-Marshall | B56: ='53'!$F$5 | C56: ='53'!$F$6 | D56: ='53'!$F$7 | E56: ='53'!$F$8 | F56: ='53'!$F$9 | G56: ='53'!$F$10 | H56: ='53'!$F$11 | I56: ='53'!$F$12 | J56: ='53'!$F$13 | K56: ='53'!$F$14 | L56: ='53'!$F$15 | M56: ='53'!$F$16 | N56: ='53'!$F$17 | O56: ='53'!$F$18 | P56: ='53'!$F$19 | Q56: ='53'!$F$20 | R56: ='53'!$F$21 | S56: ='53'!$F$22 | T56: ='53'!$F$23 | U56: ='53'!$F$24 | V56: ='53'!$F$25 | W56: ='53'!$F$26 | X56: ='53'!$F$27 | Y56: ='53'!$F$28 | Z56: ='53'!$F$29 | AA56: ='53'!$F$30 | AB56: ='53'!$F$31 | AC56: ='53'!$F$32 | AD56: ='53'!$F$33
A57: TSTC-Waco | B57: ='54'!$F$5 -> 8.27 | C57: ='54'!$F$6 -> 5.54 | D57: ='54'!$F$7 -> 5.11 | E57: ='54'!$F$8 -> 2.68 | F57: ='54'!$F$9 -> 14.35 | G57: ='54'!$F$10 -> 5.61 | H57: ='54'!$F$11 -> 4.02 | I57: ='54'!$F$12 -> 2.28 | J57: ='54'!$F$13 -> 5.68 | K57: ='54'!$F$14 | L57: ='54'!$F$15 -> 6.14 | M57: ='54'!$F$16 -> 4.24 | N57: ='54'!$F$17 | O57: ='54'!$F$18 -> 3.36 | P57: ='54'!$F$19 | Q57: ='54'!$F$20 -> 6.24 | R57: ='54'!$F$21 | S57: ='54'!$F$22 | T57: ='54'!$F$23 -> 4.41 | U57: ='54'!$F$24 -> 6.3 | V57: ='54'!$F$25 -> 4.82 | W57: ='54'!$F$26 -> 7.64 | X57: ='54'!$F$27 | Y57: ='54'!$F$28 | Z57: ='54'!$F$29 -> 3.18 | AA57: ='54'!$F$30 -> 4.65 | AB57: ='54'!$F$31 | AC57: ='54'!$F$32 | AD57: ='54'!$F$33 -> 5.14
A58: Lamar-IOT | B58: ='55'!$F$5 | C58: ='55'!$F$6 | D58: ='55'!$F$7 | E58: ='55'!$F$8 | F58: ='55'!$F$9 | G58: ='55'!$F$10 | H58: ='55'!$F$11 | I58: ='55'!$F$12 | J58: ='55'!$F$13 | K58: ='55'!$F$14 | L58: ='55'!$F$15 | M58: ='55'!$F$16 | N58: ='55'!$F$17 | O58: ='55'!$F$18 | P58: ='55'!$F$19 | Q58: ='55'!$F$20 | R58: ='55'!$F$21 | S58: ='55'!$F$22 | T58: ='55'!$F$23 | U58: ='55'!$F$24 | V58: ='55'!$F$25 | W58: ='55'!$F$26 | X58: ='55'!$F$27 | Y58: ='55'!$F$28 | Z58: ='55'!$F$29 | AA58: ='55'!$F$30 | AB58: ='55'!$F$31 | AC58: ='55'!$F$32 | AD58: ='55'!$F$33
A59: Lamar-Orange | B59: ='56'!$F$5 -> 6.74 | C59: ='56'!$F$6 | D59: ='56'!$F$7 -> 6.74 | E59: ='56'!$F$8 -> 6.74 | F59: ='56'!$F$9 | G59: ='56'!$F$10 -> 6.74 | H59: ='56'!$F$11 -> 6.74 | I59: ='56'!$F$12 | J59: ='56'!$F$13 -> 6.74 | K59: ='56'!$F$14 | L59: ='56'!$F$15 -> 6.74 | M59: ='56'!$F$16 -> 6.74 | N59: ='56'!$F$17 -> 6.74 | O59: ='56'!$F$18 -> 6.74 | P59: ='56'!$F$19 | Q59: ='56'!$F$20 -> 6.74 | R59: ='56'!$F$21 | S59: ='56'!$F$22 -> 6.74 | T59: ='56'!$F$23 -> 6.74 | U59: ='56'!$F$24 | V59: ='56'!$F$25 | W59: ='56'!$F$26 -> 6.74 | X59: ='56'!$F$27 -> 6.74 | Y59: ='56'!$F$28 -> 6.74 | Z59: ='56'!$F$29 -> 6.74 | AA59: ='56'!$F$30 -> 6.74 | AB59: ='56'!$F$31 | AC59: ='56'!$F$32 | AD59: ='56'!$F$33 -> 6.74
A60: Lamar-Port Arthur | B60: ='57'!$F$5 | C60: ='57'!$F$6 | D60: ='57'!$F$7 -> 6.44 | E60: ='57'!$F$8 -> 6.45 | F60: ='57'!$F$9 | G60: ='57'!$F$10 | H60: ='57'!$F$11 -> 6.44 | I60: ='57'!$F$12 -> 6.46 | J60: ='57'!$F$13 -> 6.45 | K60: ='57'!$F$14 | L60: ='57'!$F$15 | M60: ='57'!$F$16 -> 6.44 | N60: ='57'!$F$17 -> 6.44 | O60: ='57'!$F$18 -> 6.46 | P60: ='57'!$F$19 | Q60: ='57'!$F$20 -> 6.46 | R60: ='57'!$F$21 | S60: ='57'!$F$22 -> 6.46 | T60: ='57'!$F$23 -> 6.44 | U60: ='57'!$F$24 -> 6.46 | V60: ='57'!$F$25 | W60: ='57'!$F$26 -> 6.46 | X60: ='57'!$F$27 | Y60: ='57'!$F$28 | Z60: ='57'!$F$29 -> 6.44 | AA60: ='57'!$F$30 | AB60: ='57'!$F$31 | AC60: ='57'!$F$32 | AD60: ='57'!$F$33 -> 6.45
A61: Total | B61: =Summary!$F$5 -> 6.81 | C61: =Summary!$F$6 -> 6.64 | D61: =Summary!$F$7 -> 5.51 | E61: =Summary!$F$8 -> 6.22 | F61: =Summary!$F$9 -> 18.69 | G61: =Summary!$F$10 -> 8.21 | H61: =Summary!$F$11 -> 5.44 | I61: =Summary!$F$12 -> 5.99 | J61: =Summary!$F$13 -> 5.35 | K61: =Summary!$F$14 -> 7.64 | L61: =Summary!$F$15 -> 6.42 | M61: =Summary!$F$16 -> 5.26 | N61: =Summary!$F$17 -> 5.7 | O61: =Summary!$F$18 -> 9.04 | P61: =Summary!$F$19 -> 11.21 | Q61: =Summary!$F$20 -> 6.51 | R61: =Summary!$F$21 -> 8.64 | S61: =Summary!$F$22 -> 5.76 | T61: =Summary!$F$23 -> 4.96 | U61: =Summary!$F$24 -> 6.49 | V61: =Summary!$F$25 -> 7.32 | W61: =Summary!$F$26 -> 6.47 | X61: =Summary!$F$27 -> 6.21 | Y61: =Summary!$F$28 -> 4.94 | Z61: =Summary!$F$29 -> 4.97 | AA61: =Summary!$F$30 -> 7.33 | AD61: =Summary!$F$33 -> 5.77
A62: Average (Excluding zero values) | B62: =AVERAGE(B$4:B$60) -> 7.4035714 | C62: =AVERAGE(C$4:C$60) -> 6.9230435 | D62: =AVERAGE(D$4:D$60) -> 5.7066038 | E62: =AVERAGE(E$4:E$60) -> 6.5692453 | F62: =AVERAGE(F$4:F$60) -> 17.755455 | G62: =AVERAGE(G$4:G$60) -> 10.472703 | H62: =AVERAGE(H$4:H$60) -> 5.8407692 | I62: =AVERAGE(I$4:I$60) -> 7.9987879 | ... AA62: =AVERAGE(AA$4:AA$60) -> 7.8596154 | AD62: =AVERAGE(AD$4:AD$60) -> 5.9732075
A63: High | B63: =MAX(B$4:B$60) -> 15.88 | C63: =MAX(C$4:C$60) -> 10.75 | D63: =MAX(D$4:D$60) -> 9.47 | E63: =MAX(E$4:E$60) -> 17.52 | F63: =MAX(F$4:F$60) -> 30.55 | G63: =MAX(G$4:G$60) -> 31.35 | H63: =MAX(H$4:H$60) -> 7.84 | I63: =MAX(I$4:I$60) -> 33.38 | ... AA63: =MAX(AA$4:AA$60) -> 19.85 | AD63: =MAX(AD$4:AD$60) -> 8.8
A64: Low (Excluding zero values) | B64: =MIN(B$4:B$60) -> 3.26 | C64: =MIN(C$4:C$60) -> 3.27 | D64: =MIN(D$4:D$60) -> 3.38 | E64: =MIN(E$4:E$60) -> 2.68 | F64: =MIN(F$4:F$60) -> 3.26 | G64: =MIN(G$4:G$60) -> 3.78 | H64: =MIN(H$4:H$60) -> 3.2 | I64: =MIN(I$4:I$60) -> 2.28 | ... AA64: =MIN(AA$4:AA$60) -> 2.92 | AD64: =MIN(AD$4:AD$60) -> 4.14
A65: Median (Excluding zero values) | B65: =MEDIAN(B$4:B$60) -> 6.725 | C65: =MEDIAN(C$4:C$60) -> 6.695 | D65: =MEDIAN(D$4:D$60) -> 5.74 | E65: =MEDIAN(E$4:E$60) -> 6.36 | F65: =MEDIAN(F$4:F$60) -> 17.3 | G65: =MEDIAN(G$4:G$60) -> 8.8 | H65: =MEDIAN(H$4:H$60) -> 6.115 | I65: =MEDIAN(I$4:I$60) -> 6.36 | ... AA65: =MEDIAN(AA$4:AA$60) -> 7.835 | AD65: =MEDIAN(AD$4:AD$60) -> 6.12
B67: Discipline | L67: Discipline | V67: Discipline
B68: AG - Agriculture | L68: ENGR - Engineering Related | V68: MECH - Mechanics and Repairers - Diesel, Aviation Mechanics, and Transportation Workers
B69: ARCH - Architecture and Precision Production Trades | L69: LA - English Language, Lit, Philosophy, Humanities, & Interdisciplinary | V69: ELECT - Mechanics and Repairers - Electronics
B70: SCI - Biology, Physical Sciences, and Science Technology | L70: FL - Foreign Languages | V70: PE - Physical Education and Fitness
B71: BA - Business Management, Marketing, and Administrative Services | L71: HODA - Health Occupations - Dental Assistants, Medical Lab, and Assoc. Degree Nursing | V71: PA - Protective Services and Public Administration
B72: CP - Career Pilot | L72: HODH - Health Occupations - Dental Hygiene | V72: SS - Psychology, Social Sciences, and History
B73: COMM - Communications | L73: HOO - Health Occupations - Other | V73: FA - Visual and Performing Arts
B74: CS - Computer and Information Sciences | L74: HORT - Health Occupations - Respiratory Therapy
B75: CNSTR - Construction Trades | L75: NUR - Health Occupations - Vocational Nursing | V75: DEM - Developmental Education - Math
B76: HE - Consumer and Homemaking Education | L76: MATH - Mathematics | V76: DER - Developmental Education - Reading/Writing
B77: ENG - Engineering | L77: AUTO - Mechanics and Repairers - Automotive | V77: Total - All Disciplines

Sheet Discipline Analysis
A1: =Summary!A1 -> Community and Technical Colleges, Report of Fundable Operating Expenses, Fiscal Year (FY) 1999
A2: Discipline Analysis by Institution | X2: Discipline
A3: 1 | X3: Agriculture
X4: Architecture and Precision Production Trades
A5: Institution | B5: Contact Hours | C5: Total | E5: Faculty Salaries | G5: Library | I5: Institutional Support | K5: Student Services | M5: Departmental Operating Expense | O5: Instructional Administration | Q5: Organized Activities | S5: Equipment Depreciation | U5: Local Benefits | X5: Biology, Physical Sciences, and Science Technology
C6: Expense | D6: per Hour | E6: Expense | F6: per Hour | G6: Expense | H6: per Hour | I6: Expense | J6: per Hour | K6: Expense | L6: per Hour | M6: Expense | N6: per Hour | O6: Expense | P6: per Hour | Q6: Expense | R6: per Hour | S6: Expense | T6: per Hour | U6: Expense | V6: per Hour | X6: Business Management, Marketing, and Administrative Services
A7: Alamo | B7: =OFFSET('1'!$D$4,$A$3,0) -> 22080 | C7: =OFFSET('1'!$E$4,$A$3,0) -> 140133.37 | D7: =OFFSET('1'!$F$4,$A$3,0) -> 6.35 | E7: =OFFSET('1'!$E$66,$A$3,0) -> 57648 | F7: =OFFSET('1'!$F$66,$A$3,0) -> 2.61 | G7: =IFERROR('1'!$F$100*'Discipline Analysis'!$B7,"") -> 6844.8 | H7: ='1'!$F$100 -> 0.31 | I7: =IFERROR('1'!$F$98*'Discipline Analysis'!$B7,"") -> 28262.4 | J7: ='1'!$F$98 -> 1.28 | K7: =IFERROR('1'!$F$99*'Discipline Analysis'!$B7,"") -> 16780.8 | L7: ='1'!$F$99 -> 0.76 | M7: =OFFSET('1'!$E$35,$A$3,0) -> 2068 | N7: =OFFSET('1'!$F$35,$A$3,0) -> 0.09 | O7: =IFERROR('1'!$F$101*'Discipline Analysis'!$B7,"") -> 11481.6 | P7: ='1'!$F$101 -> 0.52 | Q7: =IFERROR('1'!$F$102*'Discipline Analysis'!$B7,"") -> 220.8 | R7: ='1'!$F$102 -> 0.01 | S7: =IFERROR('1'!$F$103*'Discipline Analysis'!$B7,"") -> 0 | T7: ='1'!$F$103 -> 0 | U7: =IFERROR('1'!$F$104*'Discipline Analysis'!$B7,"") -> 16780.8 | V7: ='1'!$F$104 -> 0.76 | X7: Career Pilot
A8: Alvin | B8: =OFFSET('2'!$D$4,$A$3,0) -> 28654 | C8: =OFFSET('2'!$E$4,$A$3,0) -> 141037.41 | D8: =OFFSET('2'!$F$4,$A$3,0) -> 4.92 | E8: =OFFSET('2'!$E$66,$A$3,0) -> 58178 | F8: =OFFSET('2'!$F$66,$A$3,0) -> 2.03 | G8: =IFERROR('2'!$F$100*'Discipline Analysis'!$B8,"") -> 7450.04 | H8: ='2'!$F$100 -> 0.26 | I8: =IFERROR('2'!$F$98*'Discipline Analysis'!$B8,"") -> 27507.84 | J8: ='2'!$F$98 -> 0.96 | K8: =IFERROR('2'!$F$99*'Discipline Analysis'!$B8,"") -> 17192.4 | L8: ='2'!$F$99 -> 0.6 | M8: =OFFSET('2'!$E$35,$A$3,0) -> 13379 | N8: =OFFSET('2'!$F$35,$A$3,0) -> 0.47 | O8: =IFERROR('2'!$F$101*'Discipline Analysis'!$B8,"") -> 10028.9 | P8: ='2'!$F$101 -> 0.35 | Q8: =IFERROR('2'!$F$102*'Discipline Analysis'!$B8,"") | R8: ='2'!$F$102 | S8: =IFERROR('2'!$F$103*'Discipline Analysis'!$B8,"") | T8: ='2'!$F$103 | U8: =IFERROR('2'!$F$104*'Discipline Analysis'!$B8,"") -> 7450.04 | V8: ='2'!$F$104 -> 0.26 | X8: Communications
A9: Amarillo | B9: =OFFSET('3'!$D$4,$A$3,0) -> 2552 | C9: =OFFSET('3'!$E$4,$A$3,0) -> 28324.803 | D9: =OFFSET('3'!$F$4,$A$3,0) -> 11.1 | E9: =OFFSET('3'!$E$66,$A$3,0) -> 16833 | F9: =OFFSET('3'!$F$66,$A$3,0) -> 6.6 | G9: =IFERROR('3'!$F$100*'Discipline Analysis'!$B9,"") -> 535.92 | H9: ='3'!$F$100 -> 0.21 | I9: =IFERROR('3'!$F$98*'Discipline Analysis'!$B9,"") -> 3496.24 | J9: ='3'!$F$98 -> 1.37 | K9: =IFERROR('3'!$F$99*'Discipline Analysis'!$B9,"") -> 1352.56 | L9: ='3'!$F$99 -> 0.53 | M9: =OFFSET('3'!$E$35,$A$3,0) -> 3905 | N9: =OFFSET('3'!$F$35,$A$3,0) -> 1.53 | O9: =IFERROR('3'!$F$101*'Discipline Analysis'!$B9,"") -> 791.12 | P9: ='3'!$F$101 -> 0.31 | Q9: =IFERROR('3'!$F$102*'Discipline Analysis'!$B9,"") -> 178.64 | R9: ='3'!$F$102 -> 0.07 | S9: =IFERROR('3'!$F$103*'Discipline Analysis'!$B9,"") | T9: ='3'!$F$103 | U9: =IFERROR('3'!$F$104*'Discipline Analysis'!$B9,"") -> 1250.48 | V9: ='3'!$F$104 -> 0.49 | X9: Computer and Information Sciences
A10: Angelina | B10: =OFFSET('4'!$D$4,$A$3,0) -> 120 | C10: =OFFSET('4'!$E$4,$A$3,0) -> 713.38161 | D10: =OFFSET('4'!$F$4,$A$3,0) -> 5.94 | E10: =OFFSET('4'!$E$66,$A$3,0) -> 105 | F10: =OFFSET('4'!$F$66,$A$3,0) -> 0.88 | G10: =IFERROR('4'!$F$100*'Discipline Analysis'!$B10,"") -> 16.8 | H10: ='4'!$F$100 -> 0.14 | I10: =IFERROR('4'!$F$98*'Discipline Analysis'!$B10,"") -> 63.6 | J10: ='4'!$F$98 -> 0.53 | K10: =IFERROR('4'!$F$99*'Discipline Analysis'!$B10,"") -> 42 | L10: ='4'!$F$99 -> 0.35 | M10: =OFFSET('4'!$E$35,$A$3,0) -> 431 | N10: =OFFSET('4'!$F$35,$A$3,0) -> 3.59 | O10: =IFERROR('4'!$F$101*'Discipline Analysis'!$B10,"") -> 38.4 | P10: ='4'!$F$101 -> 0.32 | Q10: =IFERROR('4'!$F$102*'Discipline Analysis'!$B10,"") | R10: ='4'!$F$102 | S10: =IFERROR('4'!$F$103*'Discipline Analysis'!$B10,"") | T10: ='4'!$F$103 | U10: =IFERROR('4'!$F$104*'Discipline Analysis'!$B10,"") -> 15.6 | V10: ='4'!$F$104 -> 0.13 | X10: Construction Trades
A11: Austin | B11: =OFFSET('5'!$D$4,$A$3,0) -> 0 | C11: =OFFSET('5'!$E$4,$A$3,0) -> 0 | D11: =OFFSET('5'!$F$4,$A$3,0) | E11: =OFFSET('5'!$E$66,$A$3,0) -> 0 | F11: =OFFSET('5'!$F$66,$A$3,0) | G11: =IFERROR('5'!$F$100*'Discipline Analysis'!$B11,"") -> 0 | H11: ='5'!$F$100 -> 0.35 | I11: =IFERROR('5'!$F$98*'Discipline Analysis'!$B11,"") -> 0 | J11: ='5'!$F$98 -> 1.38 | K11: =IFERROR('5'!$F$99*'Discipline Analysis'!$B11,"") -> 0 | L11: ='5'!$F$99 -> 0.64 | M11: =OFFSET('5'!$E$35,$A$3,0) -> 0 | N11: =OFFSET('5'!$F$35,$A$3,0) | O11: =IFERROR('5'!$F$101*'Discipline Analysis'!$B11,"") -> 0 | P11: ='5'!$F$101 -> 0.74 | Q11: =IFERROR('5'!$F$102*'Discipline Analysis'!$B11,"") | R11: ='5'!$F$102 | S11: =IFERROR('5'!$F$103*'Discipline Analysis'!$B11,"") | T11: ='5'!$F$103 | U11: =IFERROR('5'!$F$104*'Discipline Analysis'!$B11,"") -> 0 | V11: ='5'!$F$104 -> 0.24 | X11: Consumer and Homemaking Education
A12: Blinn | B12: =OFFSET('6'!$D$4,$A$3,0) -> 17856 | C12: =OFFSET('6'!$E$4,$A$3,0) -> 139615.11 | D12: =OFFSET('6'!$F$4,$A$3,0) -> 7.82 | E12: =OFFSET('6'!$E$66,$A$3,0) -> 95600 | F12: =OFFSET('6'!$F$66,$A$3,0) -> 5.35 | G12: =IFERROR('6'!$F$100*'Discipline Analysis'!$B12,"") -> 3035.52 | H12: ='6'!$F$100 -> 0.17 | I12: =IFERROR('6'!$F$98*'Discipline Analysis'!$B12,"") -> 8392.32 | J12: ='6'!$F$98 -> 0.47 | K12: =IFERROR('6'!$F$99*'Discipline Analysis'!$B12,"") -> 6963.84 | L12: ='6'!$F$99 -> 0.39 | M12: =OFFSET('6'!$E$35,$A$3,0) -> 16173 | N12: =OFFSET('6'!$F$35,$A$3,0) -> 0.91 | O12: =IFERROR('6'!$F$101*'Discipline Analysis'!$B12,"") -> 3392.64 | P12: ='6'!$F$101 -> 0.19 | Q12: =IFERROR('6'!$F$102*'Discipline Analysis'!$B12,"") | R12: ='6'!$F$102 | S12: =IFERROR('6'!$F$103*'Discipline Analysis'!$B12,"") | T12: ='6'!$F$103 | U12: =IFERROR('6'!$F$104*'Discipline Analysis'!$B12,"") -> 6249.6 | V12: ='6'!$F$104 -> 0.35 | X12: Engineering
A13: Brazosport | B13: =OFFSET('7'!$D$4,$A$3,0) -> 0 | C13: =OFFSET('7'!$E$4,$A$3,0) -> 0 | D13: =OFFSET('7'!$F$4,$A$3,0) | E13: =OFFSET('7'!$E$66,$A$3,0) -> 0 | F13: =OFFSET('7'!$F$66,$A$3,0) | G13: =IFERROR('7'!$F$100*'Discipline Analysis'!$B13,"") -> 0 | H13: ='7'!$F$100 -> 0.23 | I13: =IFERROR('7'!$F$98*'Discipline Analysis'!$B13,"") -> 0 | J13: ='7'!$F$98 -> 1.51 | K13: =IFERROR('7'!$F$99*'Discipline Analysis'!$B13,"") -> 0 | L13: ='7'!$F$99 -> 0.51 | M13: =OFFSET('7'!$E$35,$A$3,0) -> 0 | N13: =OFFSET('7'!$F$35,$A$3,0) | O13: =IFERROR('7'!$F$101*'Discipline Analysis'!$B13,"") -> 0 | P13: ='7'!$F$101 -> 0.23 | Q13: =IFERROR('7'!$F$102*'Discipline Analysis'!$B13,"") -> 0 | R13: ='7'!$F$102 -> 0.2 | S13: =IFERROR('7'!$F$103*'Discipline Analysis'!$B13,"") | T13: ='7'!$F$103 | U13: =IFERROR('7'!$F$104*'Discipline Analysis'!$B13,"") -> 0 | V13: ='7'!$F$104 -> 0.79 | X13: Engineering Related
A14: Central Texas | B14: =OFFSET('8'!$D$4,$A$3,0) -> 11440 | C14: =OFFSET('8'!$E$4,$A$3,0) -> 107910.12 | D14: =OFFSET('8'!$F$4,$A$3,0) -> 9.43 | E14: =OFFSET('8'!$E$66,$A$3,0) -> 50760 | F14: =OFFSET('8'!$F$66,$A$3,0) -> 4.44 | G14: =IFERROR('8'!$F$100*'Discipline Analysis'!$B14,"") -> 2059.2 | H14: ='8'!$F$100 -> 0.18 | I14: =IFERROR('8'!$F$98*'Discipline Analysis'!$B14,"") -> 9609.6 | J14: ='8'!$F$98 -> 0.84 | K14: =IFERROR('8'!$F$99*'Discipline Analysis'!$B14,"") -> 5605.6 | L14: ='8'!$F$99 -> 0.49 | M14: =OFFSET('8'!$E$35,$A$3,0) -> 37342 | N14: =OFFSET('8'!$F$35,$A$3,0) -> 3.26 | O14: =IFERROR('8'!$F$101*'Discipline Analysis'!$B14,"") -> 1944.8 | P14: ='8'!$F$101 -> 0.17 | Q14: =IFERROR('8'!$F$102*'Discipline Analysis'!$B14,"") -> 457.6 | R14: ='8'!$F$102 -> 0.04 | S14: =IFERROR('8'!$F$103*'Discipline Analysis'!$B14,"") | T14: ='8'!$F$103 | U14: =IFERROR('8'!$F$104*'Discipline Analysis'!$B14,"") | V14: ='8'!$F$104 | X14: English Language, Lit, Philosophy, Humanities, & Interdisciplinary
A15: Cisco | B15: =OFFSET('9'!$D$4,$A$3,0) -> 10032 | C15: =OFFSET('9'!$E$4,$A$3,0) -> 67298.013 | D15: =OFFSET('9'!$F$4,$A$3,0) -> 6.71 | E15: =OFFSET('9'!$E$66,$A$3,0) -> 44101 | F15: =OFFSET('9'!$F$66,$A$3,0) -> 4.4 | G15: =IFERROR('9'!$F$100*'Discipline Analysis'!$B15,"") -> 1003.2 | H15: ='9'!$F$100 -> 0.1 | I15: =IFERROR('9'!$F$98*'Discipline Analysis'!$B15,"") -> 6821.76 | J15: ='9'!$F$98 -> 0.68 | K15: =IFERROR('9'!$F$99*'Discipline Analysis'!$B15,"") -> 6621.12 | L15: ='9'!$F$99 -> 0.66 | M15: =OFFSET('9'!$E$35,$A$3,0) -> 5707 | N15: =OFFSET('9'!$F$35,$A$3,0) -> 0.57 | O15: =IFERROR('9'!$F$101*'Discipline Analysis'!$B15,"") -> 1605.12 | P15: ='9'!$F$101 -> 0.16 | Q15: =IFERROR('9'!$F$102*'Discipline Analysis'!$B15,"") | R15: ='9'!$F$102 | S15: =IFERROR('9'!$F$103*'Discipline Analysis'!$B15,"") | T15: ='9'!$F$103 | U15: =IFERROR('9'!$F$104*'Discipline Analysis'!$B15,"") -> 1404.48 | V15: ='9'!$F$104 -> 0.14 | X15: Foreign Languages
A16: Clarendon | B16: =OFFSET('10'!$D$4,$A$3,0) -> 35120 | C16: =OFFSET('10'!$E$4,$A$3,0) -> 331938.42 | D16: =OFFSET('10'!$F$4,$A$3,0) -> 9.45 | E16: =OFFSET('10'!$E$66,$A$3,0) -> 151895 | F16: =OFFSET('10'!$F$66,$A$3,0) -> 4.33 | G16: =IFERROR('10'!$F$100*'Discipline Analysis'!$B16,"") -> 5619.2 | H16: ='10'!$F$100 -> 0.16 | I16: =IFERROR('10'!$F$98*'Discipline Analysis'!$B16,"") -> 57596.8 | J16: ='10'!$F$98 -> 1.64 | K16: =IFERROR('10'!$F$99*'Discipline Analysis'!$B16,"") -> 24935.2 | L16: ='10'!$F$99 -> 0.71 | M16: =OFFSET('10'!$E$35,$A$3,0) -> 71504 | N16: =OFFSET('10'!$F$35,$A$3,0) -> 2.04 | O16: =IFERROR('10'!$F$101*'Discipline Analysis'!$B16,"") -> 14048 | P16: ='10'!$F$101 -> 0.4 | Q16: =IFERROR('10'!$F$102*'Discipline Analysis'!$B16,"") | R16: ='10'!$F$102 | S16: =IFERROR('10'!$F$103*'Discipline Analysis'!$B16,"") | T16: ='10'!$F$103 | U16: =IFERROR('10'!$F$104*'Discipline Analysis'!$B16,"") -> 6321.6 | V16: ='10'!$F$104 -> 0.18 | X16: Health Occupations - Dental Assistants, Medical Lab, and Assoc. Degree Nursing
A17: Coastal Bend | B17: =OFFSET('11'!$D$4,$A$3,0) -> 32264 | C17: =OFFSET('11'!$E$4,$A$3,0) -> 115846.44 | D17: =OFFSET('11'!$F$4,$A$3,0) -> 3.59 | E17: =OFFSET('11'!$E$66,$A$3,0) -> 42518 | F17: =OFFSET('11'!$F$66,$A$3,0) -> 1.32 | G17: =IFERROR('11'!$F$100*'Discipline Analysis'!$B17,"") -> 8711.28 | H17: ='11'!$F$100 -> 0.27 | I17: =IFERROR('11'!$F$98*'Discipline Analysis'!$B17,"") -> 31941.36 | J17: ='11'!$F$98 -> 0.99 | K17: =IFERROR('11'!$F$99*'Discipline Analysis'!$B17,"") -> 10001.84 | L17: ='11'!$F$99 -> 0.31 | M17: =OFFSET('11'!$E$35,$A$3,0) -> 2545 | N17: =OFFSET('11'!$F$35,$A$3,0) -> 0.08 | O17: =IFERROR('11'!$F$101*'Discipline Analysis'!$B17,"") -> 14518.8 | P17: ='11'!$F$101 -> 0.45 | Q17: =IFERROR('11'!$F$102*'Discipline Analysis'!$B17,"") | R17: ='11'!$F$102 | S17: =IFERROR('11'!$F$103*'Discipline Analysis'!$B17,"") | T17: ='11'!$F$103 | U17: =IFERROR('11'!$F$104*'Discipline Analysis'!$B17,"") -> 5807.52 | V17: ='11'!$F$104 -> 0.18 | X17: Health Occupations - Dental Hygiene
A18: College Of The Mainland | B18: =OFFSET('12'!$D$4,$A$3,0) -> 0 | C18: =OFFSET('12'!$E$4,$A$3,0) -> 0 | D18: =OFFSET('12'!$F$4,$A$3,0) | E18: =OFFSET('12'!$E$66,$A$3,0) -> 0 | F18: =OFFSET('12'!$F$66,$A$3,0) | G18: =IFERROR('12'!$F$100*'Discipline Analysis'!$B18,"") -> 0 | H18: ='12'!$F$100 -> 0.47 | I18: =IFERROR('12'!$F$98*'Discipline Analysis'!$B18,"") -> 0 | J18: ='12'!$F$98 -> 1.89 | K18: =IFERROR('12'!$F$99*'Discipline Analysis'!$B18,"") -> 0 | L18: ='12'!$F$99 -> 0.69 | M18: =OFFSET('12'!$E$35,$A$3,0) -> 0 | N18: =OFFSET('12'!$F$35,$A$3,0) | O18: =IFERROR('12'!$F$101*'Discipline Analysis'!$B18,"") | P18: ='12'!$F$101 | Q18: =IFERROR('12'!$F$102*'Discipline Analysis'!$B18,"") | R18: ='12'!$F$102 | S18: =IFERROR('12'!$F$103*'Discipline Analysis'!$B18,"") | T18: ='12'!$F$103 | U18: =IFERROR('12'!$F$104*'Discipline Analysis'!$B18,"") -> 0 | V18: ='12'!$F$104 -> 1.16 | X18: Health Occupations - Other
A19: Collin | B19: =OFFSET('13'!$D$4,$A$3,0) -> 9036 | C19: =OFFSET('13'!$E$4,$A$3,0) -> 100017.98 | D19: =OFFSET('13'!$F$4,$A$3,0) -> 11.07 | E19: =OFFSET('13'!$E$66,$A$3,0) -> 57491 | F19: =OFFSET('13'!$F$66,$A$3,0) -> 6.36 | G19: =IFERROR('13'!$F$100*'Discipline Analysis'!$B19,"") -> 4156.56 | H19: ='13'!$F$100 -> 0.46 | I19: =IFERROR('13'!$F$98*'Discipline Analysis'!$B19,"") -> 10752.84 | J19: ='13'!$F$98 -> 1.19 | K19: =IFERROR('13'!$F$99*'Discipline Analysis'!$B19,"") -> 7499.88 | L19: ='13'!$F$99 -> 0.83 | M19: =OFFSET('13'!$E$35,$A$3,0) -> 12724 | N19: =OFFSET('13'!$F$35,$A$3,0) -> 1.41 | O19: =IFERROR('13'!$F$101*'Discipline Analysis'!$B19,"") -> 4337.28 | P19: ='13'!$F$101 -> 0.48 | Q19: =IFERROR('13'!$F$102*'Discipline Analysis'!$B19,"") | R19: ='13'!$F$102 | S19: =IFERROR('13'!$F$103*'Discipline Analysis'!$B19,"") | T19: ='13'!$F$103 | U19: =IFERROR('13'!$F$104*'Discipline Analysis'!$B19,"") -> 3072.24 | V19: ='13'!$F$104 -> 0.34 | X19: Health Occupations - Respiratory Therapy
A20: Dallas | B20: =OFFSET('14'!$D$4,$A$3,0) -> 78084 | C20: =OFFSET('14'!$E$4,$A$3,0) -> 986188.42 | D20: =OFFSET('14'!$F$4,$A$3,0) -> 12.63 | E20: =OFFSET('14'!$E$66,$A$3,0) -> 380468 | F20: =OFFSET('14'!$F$66,$A$3,0) -> 4.87 | G20: =IFERROR('14'!$F$100*'Discipline Analysis'!$B20,"") -> 24986.88 | H20: ='14'!$F$100 -> 0.32 | I20: =IFERROR('14'!$F$98*'Discipline Analysis'!$B20,"") -> 97605 | J20: ='14'!$F$98 -> 1.25 | K20: =IFERROR('14'!$F$99*'Discipline Analysis'!$B20,"") -> 49973.76 | L20: ='14'!$F$99 -> 0.64 | M20: =OFFSET('14'!$E$35,$A$3,0) -> 396609 | N20: =OFFSET('14'!$F$35,$A$3,0) -> 5.08 | O20: =IFERROR('14'!$F$101*'Discipline Analysis'!$B20,"") -> 17959.32 | P20: ='14'!$F$101 -> 0.23 | Q20: =IFERROR('14'!$F$102*'Discipline Analysis'!$B20,"") -> 2342.52 | R20: ='14'!$F$102 -> 0.03 | S20: =IFERROR('14'!$F$103*'Discipline Analysis'!$B20,"") | T20: ='14'!$F$103 | U20: =IFERROR('14'!$F$104*'Discipline Analysis'!$B20,"") -> 17178.48 | V20: ='14'!$F$104 -> 0.22 | X20: Health Occupations - Vocational Nursing
A21: Del Mar | B21: =OFFSET('15'!$D$4,$A$3,0) -> 0 | C21: =OFFSET('15'!$E$4,$A$3,0) -> 0 | D21: =OFFSET('15'!$F$4,$A$3,0) | E21: =OFFSET('15'!$E$66,$A$3,0) -> 0 | F21: =OFFSET('15'!$F$66,$A$3,0) | G21: =IFERROR('15'!$F$100*'Discipline Analysis'!$B21,"") | H21: ='15'!$F$100 | I21: =IFERROR('15'!$F$98*'Discipline Analysis'!$B21,"") | J21: ='15'!$F$98 | K21: =IFERROR('15'!$F$99*'Discipline Analysis'!$B21,"") | L21: ='15'!$F$99 | M21: =OFFSET('15'!$E$35,$A$3,0) -> 0 | N21: =OFFSET('15'!$F$35,$A$3,0) | O21: =IFERROR('15'!$F$101*'Discipline Analysis'!$B21,"") | P21: ='15'!$F$101 | Q21: =IFERROR('15'!$F$102*'Discipline Analysis'!$B21,"") | R21: ='15'!$F$102 | S21: =IFERROR('15'!$F$103*'Discipline Analysis'!$B21,"") | T21: ='15'!$F$103 | U21: =IFERROR('15'!$F$104*'Discipline Analysis'!$B21,"") | V21: ='15'!$F$104 | X21: Mathematics
A22: El Paso | B22: =OFFSET('16'!$D$4,$A$3,0) -> 0 | C22: =OFFSET('16'!$E$4,$A$3,0) -> 0 | D22: =OFFSET('16'!$F$4,$A$3,0) | E22: =OFFSET('16'!$E$66,$A$3,0) -> 0 | F22: =OFFSET('16'!$F$66,$A$3,0) | G22: =IFERROR('16'!$F$100*'Discipline Analysis'!$B22,"") -> 0 | H22: ='16'!$F$100 -> 0.37 | I22: =IFERROR('16'!$F$98*'Discipline Analysis'!$B22,"") -> 0 | J22: ='16'!$F$98 -> 1.52 | K22: =IFERROR('16'!$F$99*'Discipline Analysis'!$B22,"") -> 0 | L22: ='16'!$F$99 -> 0.71 | M22: =OFFSET('16'!$E$35,$A$3,0) -> 0 | N22: =OFFSET('16'!$F$35,$A$3,0) | O22: =IFERROR('16'!$F$101*'Discipline Analysis'!$B22,"") -> 0 | P22: ='16'!$F$101 -> 0.66 | Q22: =IFERROR('16'!$F$102*'Discipline Analysis'!$B22,"") -> 0 | R22: ='16'!$F$102 -> 0.01 | S22: =IFERROR('16'!$F$103*'Discipline Analysis'!$B22,"") | T22: ='16'!$F$103 | U22: =IFERROR('16'!$F$104*'Discipline Analysis'!$B22,"") -> 0 | V22: ='16'!$F$104 -> 0.37 | X22: Mechanics and Repairers - Automotive
A23: Frank Phillips | B23: =OFFSET('17'!$D$4,$A$3,0) -> 22176 | C23: =OFFSET('17'!$E$4,$A$3,0) -> 182221.03 | D23: =OFFSET('17'!$F$4,$A$3,0) -> 8.22 | E23: =OFFSET('17'!$E$66,$A$3,0) -> 105321 | F23: =OFFSET('17'!$F$66,$A$3,0) -> 4.75 | G23: =IFERROR('17'!$F$100*'Discipline Analysis'!$B23,"") -> 4435.2 | H23: ='17'!$F$100 -> 0.2 | I23: =IFERROR('17'!$F$98*'Discipline Analysis'!$B23,"") -> 25058.88 | J23: ='17'!$F$98 -> 1.13 | K23: =IFERROR('17'!$F$99*'Discipline Analysis'!$B23,"") -> 11088 | L23: ='17'!$F$99 -> 0.5 | M23: =OFFSET('17'!$E$35,$A$3,0) -> 12982 | N23: =OFFSET('17'!$F$35,$A$3,0) -> 0.59 | O23: =IFERROR('17'!$F$101*'Discipline Analysis'!$B23,"") -> 16410.24 | P23: ='17'!$F$101 -> 0.74 | Q23: =IFERROR('17'!$F$102*'Discipline Analysis'!$B23,"") -> 1330.56 | R23: ='17'!$F$102 -> 0.06 | S23: =IFERROR('17'!$F$103*'Discipline Analysis'!$B23,"") | T23: ='17'!$F$103 | U23: =IFERROR('17'!$F$104*'Discipline Analysis'!$B23,"") -> 5322.24 | V23: ='17'!$F$104 -> 0.24 | X23: Mechanics and Repairers - Diesel, Aviation Mechanics, and Transportation Workers
A24: Galveston | B24: =OFFSET('18'!$D$4,$A$3,0) -> 0 | C24: =OFFSET('18'!$E$4,$A$3,0) -> 0 | D24: =OFFSET('18'!$F$4,$A$3,0) | E24: =OFFSET('18'!$E$66,$A$3,0) -> 0 | F24: =OFFSET('18'!$F$66,$A$3,0) | G24: =IFERROR('18'!$F$100*'Discipline Analysis'!$B24,"") -> 0 | H24: ='18'!$F$100 -> 0.27 | I24: =IFERROR('18'!$F$98*'Discipline Analysis'!$B24,"") -> 0 | J24: ='18'!$F$98 -> 1.62 | K24: =IFERROR('18'!$F$99*'Discipline Analysis'!$B24,"") -> 0 | L24: ='18'!$F$99 -> 0.42 | M24: =OFFSET('18'!$E$35,$A$3,0) -> 0 | N24: =OFFSET('18'!$F$35,$A$3,0) | O24: =IFERROR('18'!$F$101*'Discipline Analysis'!$B24,"") -> 0 | P24: ='18'!$F$101 -> 0.84 | Q24: =IFERROR('18'!$F$102*'Discipline Analysis'!$B24,"") -> 0 | R24: ='18'!$F$102 -> 0.14 | S24: =IFERROR('18'!$F$103*'Discipline Analysis'!$B24,"") | T24: ='18'!$F$103 | U24: =IFERROR('18'!$F$104*'Discipline Analysis'!$B24,"") -> 0 | V24: ='18'!$F$104 -> 0.71 | X24: Mechanics and Repairers - Electronics
A25: Grayson | B25: =OFFSET('19'!$D$4,$A$3,0) -> 15912 | C25: =OFFSET('19'!$E$4,$A$3,0) -> 100368.89 | D25: =OFFSET('19'!$F$4,$A$3,0) -> 6.31 | E25: =OFFSET('19'!$E$66,$A$3,0) -> 48212 | F25: =OFFSET('19'!$F$66,$A$3,0) -> 3.03 | G25: =IFERROR('19'!$F$100*'Discipline Analysis'!$B25,"") -> 2545.92 | H25: ='19'!$F$100 -> 0.16 | I25: =IFERROR('19'!$F$98*'Discipline Analysis'!$B25,"") -> 15593.76 | J25: ='19'!$F$98 -> 0.98 | K25: =IFERROR('19'!$F$99*'Discipline Analysis'!$B25,"") -> 8433.36 | L25: ='19'!$F$99 -> 0.53 | M25: =OFFSET('19'!$E$35,$A$3,0) -> 14671 | N25: =OFFSET('19'!$F$35,$A$3,0) -> 0.92 | O25: =IFERROR('19'!$F$101*'Discipline Analysis'!$B25,"") -> 3341.52 | P25: ='19'!$F$101 -> 0.21 | Q25: =IFERROR('19'!$F$102*'Discipline Analysis'!$B25,"") -> 477.36 | R25: ='19'!$F$102 -> 0.03 | S25: =IFERROR('19'!$F$103*'Discipline Analysis'!$B25,"") | T25: ='19'!$F$103 | U25: =IFERROR('19'!$F$104*'Discipline Analysis'!$B25,"") -> 7160.4 | V25: ='19'!$F$104 -> 0.45 | X25: Physical Education and Fitness
A26: Hill | B26: =OFFSET('20'!$D$4,$A$3,0) -> 10200 | C26: =OFFSET('20'!$E$4,$A$3,0) -> 74205.989 | D26: =OFFSET('20'!$F$4,$A$3,0) -> 7.28 | E26: =OFFSET('20'!$E$66,$A$3,0) -> 40034 | F26: =OFFSET('20'!$F$66,$A$3,0) -> 3.92 | G26: =IFERROR('20'!$F$100*'Discipline Analysis'!$B26,"") -> 5916 | H26: ='20'!$F$100 -> 0.58 | I26: =IFERROR('20'!$F$98*'Discipline Analysis'!$B26,"") -> 9384 | J26: ='20'!$F$98 -> 0.92 | K26: =IFERROR('20'!$F$99*'Discipline Analysis'!$B26,"") -> 4998 | L26: ='20'!$F$99 -> 0.49 | M26: =OFFSET('20'!$E$35,$A$3,0) -> 9525 | N26: =OFFSET('20'!$F$35,$A$3,0) -> 0.93 | O26: =IFERROR('20'!$F$101*'Discipline Analysis'!$B26,"") -> 2958 | P26: ='20'!$F$101 -> 0.29 | Q26: =IFERROR('20'!$F$102*'Discipline Analysis'!$B26,"") | R26: ='20'!$F$102 | S26: =IFERROR('20'!$F$103*'Discipline Analysis'!$B26,"") | T26: ='20'!$F$103 | U26: =IFERROR('20'!$F$104*'Discipline Analysis'!$B26,"") -> 1326 | V26: ='20'!$F$104 -> 0.13 | X26: Protective Services and Public Administration
A27: Houston | B27: =OFFSET('21'!$D$4,$A$3,0) -> 129567 | C27: =OFFSET('21'!$E$4,$A$3,0) -> 749535.29 | D27: =OFFSET('21'!$F$4,$A$3,0) -> 5.78 | E27: =OFFSET('21'!$E$66,$A$3,0) -> 188055 | F27: =OFFSET('21'!$F$66,$A$3,0) -> 1.45 | G27: =IFERROR('21'!$F$100*'Discipline Analysis'!$B27,"") -> 23322.06 | H27: ='21'!$F$100 -> 0.18 | I27: =IFERROR('21'!$F$98*'Discipline Analysis'!$B27,"") -> 270795.03 | J27: ='21'!$F$98 -> 2.09 | K27: =IFERROR('21'!$F$99*'Discipline Analysis'!$B27,"") -> 82922.88 | L27: ='21'!$F$99 -> 0.64 | M27: =OFFSET('21'!$E$35,$A$3,0) -> 95665 | N27: =OFFSET('21'!$F$35,$A$3,0) -> 0.74 | O27: =IFERROR('21'!$F$101*'Discipline Analysis'!$B27,"") -> 67374.84 | P27: ='21'!$F$101 -> 0.52 | Q27: =IFERROR('21'!$F$102*'Discipline Analysis'!$B27,"") -> 1295.67 | R27: ='21'!$F$102 -> 0.01 | S27: =IFERROR('21'!$F$103*'Discipline Analysis'!$B27,"") | T27: ='21'!$F$103 | U27: =IFERROR('21'!$F$104*'Discipline Analysis'!$B27,"") -> 22026.39 | V27: ='21'!$F$104 -> 0.17 | X27: Psychology, Social Sciences, and History
A28: Howard | B28: =OFFSET('22'!$D$4,$A$3,0) -> 63769 | C28: =OFFSET('22'!$E$4,$A$3,0) -> 303356.88 | D28: =OFFSET('22'!$F$4,$A$3,0) -> 4.76 | E28: =OFFSET('22'!$E$66,$A$3,0) -> 154984 | F28: =OFFSET('22'!$F$66,$A$3,0) -> 2.43 | G28: =IFERROR('22'!$F$100*'Discipline Analysis'!$B28,"") -> 7014.59 | H28: ='22'!$F$100 -> 0.11 | I28: =IFERROR('22'!$F$98*'Discipline Analysis'!$B28,"") -> 47189.06 | J28: ='22'!$F$98 -> 0.74 | K28: =IFERROR('22'!$F$99*'Discipline Analysis'!$B28,"") -> 26145.29 | L28: ='22'!$F$99 -> 0.41 | M28: =OFFSET('22'!$E$35,$A$3,0) -> 30404 | N28: =OFFSET('22'!$F$35,$A$3,0) -> 0.48 | O28: =IFERROR('22'!$F$101*'Discipline Analysis'!$B28,"") -> 17855.32 | P28: ='22'!$F$101 -> 0.28 | Q28: =IFERROR('22'!$F$102*'Discipline Analysis'!$B28,"") | R28: ='22'!$F$102 | S28: =IFERROR('22'!$F$103*'Discipline Analysis'!$B28,"") | T28: ='22'!$F$103 | U28: =IFERROR('22'!$F$104*'Discipline Analysis'!$B28,"") -> 20406.08 | V28: ='22'!$F$104 -> 0.32 | X28: Visual and Performing Arts
A29: Kilgore | B29: =OFFSET('23'!$D$4,$A$3,0) -> 0 | C29: =OFFSET('23'!$E$4,$A$3,0) -> 0 | D29: =OFFSET('23'!$F$4,$A$3,0) | E29: =OFFSET('23'!$E$66,$A$3,0) -> 0 | F29: =OFFSET('23'!$F$66,$A$3,0) | G29: =IFERROR('23'!$F$100*'Discipline Analysis'!$B29,"") | H29: ='23'!$F$100 | I29: =IFERROR('23'!$F$98*'Discipline Analysis'!$B29,"") | J29: ='23'!$F$98 | K29: =IFERROR('23'!$F$99*'Discipline Analysis'!$B29,"") | L29: ='23'!$F$99 | M29: =OFFSET('23'!$E$35,$A$3,0) -> 0 | N29: =OFFSET('23'!$F$35,$A$3,0) | O29: =IFERROR('23'!$F$101*'Discipline Analysis'!$B29,"") | P29: ='23'!$F$101 | Q29: =IFERROR('23'!$F$102*'Discipline Analysis'!$B29,"") | R29: ='23'!$F$102 | S29: =IFERROR('23'!$F$103*'Discipline Analysis'!$B29,"") | T29: ='23'!$F$103 | U29: =IFERROR('23'!$F$104*'Discipline Analysis'!$B29,"") | V29: ='23'!$F$104 | X29: Developmental Education - Math
A30: Laredo | B30: =OFFSET('24'!$D$4,$A$3,0) -> 0 | C30: =OFFSET('24'!$E$4,$A$3,0) -> 0 | D30: =OFFSET('24'!$F$4,$A$3,0) | E30: =OFFSET('24'!$E$66,$A$3,0) -> 0 | F30: =OFFSET('24'!$F$66,$A$3,0) | G30: =IFERROR('24'!$F$100*'Discipline Analysis'!$B30,"") -> 0 | H30: ='24'!$F$100 -> 0.33 | I30: =IFERROR('24'!$F$98*'Discipline Analysis'!$B30,"") -> 0 | J30: ='24'!$F$98 -> 1.24 | K30: =IFERROR('24'!$F$99*'Discipline Analysis'!$B30,"") -> 0 | L30: ='24'!$F$99 -> 0.65 | M30: =OFFSET('24'!$E$35,$A$3,0) -> 0 | N30: =OFFSET('24'!$F$35,$A$3,0) | O30: =IFERROR('24'!$F$101*'Discipline Analysis'!$B30,"") -> 0 | P30: ='24'!$F$101 -> 0.15 | Q30: =IFERROR('24'!$F$102*'Discipline Analysis'!$B30,"") | R30: ='24'!$F$102 | S30: =IFERROR('24'!$F$103*'Discipline Analysis'!$B30,"") | T30: ='24'!$F$103 | U30: =IFERROR('24'!$F$104*'Discipline Analysis'!$B30,"") -> 0 | V30: ='24'!$F$104 -> 0.66 | X30: Developmental Education - Reading/Writing
A31: Lee | B31: =OFFSET('25'!$D$4,$A$3,0) -> 64800 | C31: =OFFSET('25'!$E$4,$A$3,0) -> 390646 | D31: =OFFSET('25'!$F$4,$A$3,0) -> 6.03 | E31: =OFFSET('25'!$E$66,$A$3,0) -> 114356 | F31: =OFFSET('25'!$F$66,$A$3,0) -> 1.76 | G31: =IFERROR('25'!$F$100*'Discipline Analysis'!$B31,"") -> 15552 | H31: ='25'!$F$100 -> 0.24 | I31: =IFERROR('25'!$F$98*'Discipline Analysis'!$B31,"") -> 115992 | J31: ='25'!$F$98 -> 1.79 | K31: =IFERROR('25'!$F$99*'Discipline Analysis'!$B31,"") -> 29160 | L31: ='25'!$F$99 -> 0.45 | M31: =OFFSET('25'!$E$35,$A$3,0) -> 37032 | N31: =OFFSET('25'!$F$35,$A$3,0) -> 0.57 | O31: =IFERROR('25'!$F$101*'Discipline Analysis'!$B31,"") -> 38232 | P31: ='25'!$F$101 -> 0.59 | Q31: =IFERROR('25'!$F$102*'Discipline Analysis'!$B31,"") | R31: ='25'!$F$102 | S31: =IFERROR('25'!$F$103*'Discipline Analysis'!$B31,"") | T31: ='25'!$F$103 | U31: =IFERROR('25'!$F$104*'Discipline Analysis'!$B31,"") -> 40176 | V31: ='25'!$F$104 -> 0.62 | X31: All Disciplines
A32: Lonestar | B32: =OFFSET('26'!$D$4,$A$3,0) -> 30084 | C32: =OFFSET('26'!$E$4,$A$3,0) -> 337089.95 | D32: =OFFSET('26'!$F$4,$A$3,0) -> 11.2 | E32: =OFFSET('26'!$E$66,$A$3,0) -> 132065 | F32: =OFFSET('26'!$F$66,$A$3,0) -> 4.39 | G32: =IFERROR('26'!$F$100*'Discipline Analysis'!$B32,"") -> 12033.6 | H32: ='26'!$F$100 -> 0.4 | I32: =IFERROR('26'!$F$98*'Discipline Analysis'!$B32,"") -> 32490.72 | J32: ='26'!$F$98 -> 1.08 | K32: =IFERROR('26'!$F$99*'Discipline Analysis'!$B32,"") -> 20757.96 | L32: ='26'!$F$99 -> 0.69 | M32: =OFFSET('26'!$E$35,$A$3,0) -> 104601 | N32: =OFFSET('26'!$F$35,$A$3,0) -> 3.48 | O32: =IFERROR('26'!$F$101*'Discipline Analysis'!$B32,"") -> 26774.76 | P32: ='26'!$F$101 -> 0.89 | Q32: =IFERROR('26'!$F$102*'Discipline Analysis'!$B32,"") -> 0 | R32: ='26'!$F$102 -> 0 | S32: =IFERROR('26'!$F$103*'Discipline Analysis'!$B32,"") | T32: ='26'!$F$103 | U32: =IFERROR('26'!$F$104*'Discipline Analysis'!$B32,"") -> 8423.52 | V32: ='26'!$F$104 -> 0.28
A33: Mclennan | B33: =OFFSET('27'!$D$4,$A$3,0) -> 0 | C33: =OFFSET('27'!$E$4,$A$3,0) -> 0 | D33: =OFFSET('27'!$F$4,$A$3,0) | E33: =OFFSET('27'!$E$66,$A$3,0) -> 0 | F33: =OFFSET('27'!$F$66,$A$3,0) | G33: =IFERROR('27'!$F$100*'Discipline Analysis'!$B33,"") -> 0 | H33: ='27'!$F$100 -> 0.43 | I33: =IFERROR('27'!$F$98*'Discipline Analysis'!$B33,"") -> 0 | J33: ='27'!$F$98 -> 1.21 | K33: =IFERROR('27'!$F$99*'Discipline Analysis'!$B33,"") -> 0 | L33: ='27'!$F$99 -> 0.44 | M33: =OFFSET('27'!$E$35,$A$3,0) -> 0 | N33: =OFFSET('27'!$F$35,$A$3,0) | O33: =IFERROR('27'!$F$101*'Discipline Analysis'!$B33,"") -> 0 | P33: ='27'!$F$101 -> 0.03 | Q33: =IFERROR('27'!$F$102*'Discipline Analysis'!$B33,"") -> 0 | R33: ='27'!$F$102 -> 0.11 | S33: =IFERROR('27'!$F$103*'Discipline Analysis'!$B33,"") | T33: ='27'!$F$103 | U33: =IFERROR('27'!$F$104*'Discipline Analysis'!$B33,"") | V33: ='27'!$F$104
A34: Midland | B34: =OFFSET('28'!$D$4,$A$3,0) -> 11184 | C34: =OFFSET('28'!$E$4,$A$3,0) -> 177555.22 | D34: =OFFSET('28'!$F$4,$A$3,0) -> 15.88 | E34: =OFFSET('28'!$E$66,$A$3,0) -> 70223 | F34: =OFFSET('28'!$F$66,$A$3,0) -> 6.28 | G34: =IFERROR('28'!$F$100*'Discipline Analysis'!$B34,"") -> 2572.32 | H34: ='28'!$F$100 -> 0.23 | I34: =IFERROR('28'!$F$98*'Discipline Analysis'!$B34,"") -> 9953.76 | J34: ='28'!$F$98 -> 0.89 | K34: =IFERROR('28'!$F$99*'Discipline Analysis'!$B34,"") -> 6598.56 | L34: ='28'!$F$99 -> 0.59 | M34: =OFFSET('28'!$E$35,$A$3,0) -> 72732 | N34: =OFFSET('28'!$F$35,$A$3,0) -> 6.5 | O34: =IFERROR('28'!$F$101*'Discipline Analysis'!$B34,"") -> 7381.44 | P34: ='28'!$F$101 -> 0.66 | Q34: =IFERROR('28'!$F$102*'Discipline Analysis'!$B34,"") -> 894.72 | R34: ='28'!$F$102 -> 0.08 | S34: =IFERROR('28'!$F$103*'Discipline Analysis'!$B34,"") | T34: ='28'!$F$103 | U34: =IFERROR('28'!$F$104*'Discipline Analysis'!$B34,"") -> 7157.76 | V34: ='28'!$F$104 -> 0.64
A35: Navarro | B35: =OFFSET('29'!$D$4,$A$3,0) -> 2832 | C35: =OFFSET('29'!$E$4,$A$3,0) -> 9226.8217 | D35: =OFFSET('29'!$F$4,$A$3,0) -> 3.26 | E35: =OFFSET('29'!$E$66,$A$3,0) -> 1600 | F35: =OFFSET('29'!$F$66,$A$3,0) -> 0.56 | G35: =IFERROR('29'!$F$100*'Discipline Analysis'!$B35,"") -> 764.64 | H35: ='29'!$F$100 -> 0.27 | I35: =IFERROR('29'!$F$98*'Discipline Analysis'!$B35,"") -> 2520.48 | J35: ='29'!$F$98 -> 0.89 | K35: =IFERROR('29'!$F$99*'Discipline Analysis'!$B35,"") -> 1246.08 | L35: ='29'!$F$99 -> 0.44 | M35: =OFFSET('29'!$E$35,$A$3,0) -> 819 | N35: =OFFSET('29'!$F$35,$A$3,0) -> 0.29 | O35: =IFERROR('29'!$F$101*'Discipline Analysis'!$B35,"") -> 877.92 | P35: ='29'!$F$101 -> 0.31 | Q35: =IFERROR('29'!$F$102*'Discipline Analysis'!$B35,"") | R35: ='29'!$F$102 | S35: =IFERROR('29'!$F$103*'Discipline Analysis'!$B35,"") | T35: ='29'!$F$103 | U35: =IFERROR('29'!$F$104*'Discipline Analysis'!$B35,"") -> 1387.68 | V35: ='29'!$F$104 -> 0.49
A36: North Central Texas | B36: =OFFSET('30'!$D$4,$A$3,0) -> 43972 | C36: =OFFSET('30'!$E$4,$A$3,0) -> 354452.14 | D36: =OFFSET('30'!$F$4,$A$3,0) -> 8.06 | E36: =OFFSET('30'!$E$66,$A$3,0) -> 157757 | F36: =OFFSET('30'!$F$66,$A$3,0) -> 3.59 | G36: =IFERROR('30'!$F$100*'Discipline Analysis'!$B36,"") -> 6156.08 | H36: ='30'!$F$100 -> 0.14 | I36: =IFERROR('30'!$F$98*'Discipline Analysis'!$B36,"") -> 34737.88 | J36: ='30'!$F$98 -> 0.79 | K36: =IFERROR('30'!$F$99*'Discipline Analysis'!$B36,"") -> 14950.48 | L36: ='30'!$F$99 -> 0.34 | M36: =OFFSET('30'!$E$35,$A$3,0) -> 114227 | N36: =OFFSET('30'!$F$35,$A$3,0) -> 2.6 | O36: =IFERROR('30'!$F$101*'Discipline Analysis'!$B36,"") -> 17149.08 | P36: ='30'!$F$101 -> 0.39 | Q36: =IFERROR('30'!$F$102*'Discipline Analysis'!$B36,"") | R36: ='30'!$F$102 | S36: =IFERROR('30'!$F$103*'Discipline Analysis'!$B36,"") | T36: ='30'!$F$103 | U36: =IFERROR('30'!$F$104*'Discipline Analysis'!$B36,"") -> 9673.84 | V36: ='30'!$F$104 -> 0.22
A37: Northeast Texas | B37: =OFFSET('31'!$D$4,$A$3,0) -> 14432 | C37: =OFFSET('31'!$E$4,$A$3,0) -> 95580.198 | D37: =OFFSET('31'!$F$4,$A$3,0) -> 6.62 | E37: =OFFSET('31'!$E$66,$A$3,0) -> 42831 | F37: =OFFSET('31'!$F$66,$A$3,0) -> 2.97 | G37: =IFERROR('31'!$F$100*'Discipline Analysis'!$B37,"") -> 3463.68 | H37: ='31'!$F$100 -> 0.24 | I37: =IFERROR('31'!$F$98*'Discipline Analysis'!$B37,"") -> 24534.4 | J37: ='31'!$F$98 -> 1.7 | K37: =IFERROR('31'!$F$99*'Discipline Analysis'!$B37,"") -> 6061.44 | L37: ='31'!$F$99 -> 0.42 | M37: =OFFSET('31'!$E$35,$A$3,0) -> 5269 | N37: =OFFSET('31'!$F$35,$A$3,0) -> 0.37 | O37: =IFERROR('31'!$F$101*'Discipline Analysis'!$B37,"") -> 7937.6 | P37: ='31'!$F$101 -> 0.55 | Q37: =IFERROR('31'!$F$102*'Discipline Analysis'!$B37,"") -> 1298.88 | R37: ='31'!$F$102 -> 0.09 | S37: =IFERROR('31'!$F$103*'Discipline Analysis'!$B37,"") | T37: ='31'!$F$103 | U37: =IFERROR('31'!$F$104*'Discipline Analysis'!$B37,"") -> 4185.28 | V37: ='31'!$F$104 -> 0.29
A38: Odessa | B38: =OFFSET('32'!$D$4,$A$3,0) -> 9472 | C38: =OFFSET('32'!$E$4,$A$3,0) -> 50393.322 | D38: =OFFSET('32'!$F$4,$A$3,0) -> 5.32 | E38: =OFFSET('32'!$E$66,$A$3,0) -> 14019 | F38: =OFFSET('32'!$F$66,$A$3,0) -> 1.48 | G38: =IFERROR('32'!$F$100*'Discipline Analysis'!$B38,"") -> 2368 | H38: ='32'!$F$100 -> 0.25 | I38: =IFERROR('32'!$F$98*'Discipline Analysis'!$B38,"") -> 11082.24 | J38: ='32'!$F$98 -> 1.17 | K38: =IFERROR('32'!$F$99*'Discipline Analysis'!$B38,"") -> 6062.08 | L38: ='32'!$F$99 -> 0.64 | M38: =OFFSET('32'!$E$35,$A$3,0) -> 6554 | N38: =OFFSET('32'!$F$35,$A$3,0) -> 0.69 | O38: =IFERROR('32'!$F$101*'Discipline Analysis'!$B38,"") -> 3788.8 | P38: ='32'!$F$101 -> 0.4 | Q38: =IFERROR('32'!$F$102*'Discipline Analysis'!$B38,"") -> 1799.68 | R38: ='32'!$F$102 -> 0.19 | S38: =IFERROR('32'!$F$103*'Discipline Analysis'!$B38,"") | T38: ='32'!$F$103 | U38: =IFERROR('32'!$F$104*'Discipline Analysis'!$B38,"") -> 4736 | V38: ='32'!$F$104 -> 0.5
A39: Panola | B39: =OFFSET('33'!$D$4,$A$3,0) -> 33395 | C39: =OFFSET('33'!$E$4,$A$3,0) -> 282663.6 | D39: =OFFSET('33'!$F$4,$A$3,0) -> 8.46 | E39: =OFFSET('33'!$E$66,$A$3,0) -> 174179 | F39: =OFFSET('33'!$F$66,$A$3,0) -> 5.22 | G39: =IFERROR('33'!$F$100*'Discipline Analysis'!$B39,"") -> 10686.4 | H39: ='33'!$F$100 -> 0.32 | I39: =IFERROR('33'!$F$98*'Discipline Analysis'!$B39,"") -> 43413.5 | J39: ='33'!$F$98 -> 1.3 | K39: =IFERROR('33'!$F$99*'Discipline Analysis'!$B39,"") -> 19035.15 | L39: ='33'!$F$99 -> 0.57 | M39: =OFFSET('33'!$E$35,$A$3,0) -> 12469 | N39: =OFFSET('33'!$F$35,$A$3,0) -> 0.37 | O39: =IFERROR('33'!$F$101*'Discipline Analysis'!$B39,"") -> 22708.6 | P39: ='33'!$F$101 -> 0.68 | Q39: =IFERROR('33'!$F$102*'Discipline Analysis'!$B39,"") | R39: ='33'!$F$102 | S39: =IFERROR('33'!$F$103*'Discipline Analysis'!$B39,"") | T39: ='33'!$F$103 | U39: =IFERROR('33'!$F$104*'Discipline Analysis'!$B39,"") | V39: ='33'!$F$104
A40: Paris | B40: =OFFSET('34'!$D$4,$A$3,0) -> 6624 | C40: =OFFSET('34'!$E$4,$A$3,0) -> 61931.497 | D40: =OFFSET('34'!$F$4,$A$3,0) -> 9.35 | E40: =OFFSET('34'!$E$66,$A$3,0) -> 32606 | F40: =OFFSET('34'!$F$66,$A$3,0) -> 4.92 | G40: =IFERROR('34'!$F$100*'Discipline Analysis'!$B40,"") -> 1258.56 | H40: ='34'!$F$100 -> 0.19 | I40: =IFERROR('34'!$F$98*'Discipline Analysis'!$B40,"") -> 6491.52 | J40: ='34'!$F$98 -> 0.98 | K40: =IFERROR('34'!$F$99*'Discipline Analysis'!$B40,"") -> 2252.16 | L40: ='34'!$F$99 -> 0.34 | M40: =OFFSET('34'!$E$35,$A$3,0) -> 14998 | N40: =OFFSET('34'!$F$35,$A$3,0) -> 2.26 | O40: =IFERROR('34'!$F$101*'Discipline Analysis'!$B40,"") -> 1722.24 | P40: ='34'!$F$101 -> 0.26 | Q40: =IFERROR('34'!$F$102*'Discipline Analysis'!$B40,"") -> 66.24 | R40: ='34'!$F$102 -> 0.01 | S40: =IFERROR('34'!$F$103*'Discipline Analysis'!$B40,"") | T40: ='34'!$F$103 | U40: =IFERROR('34'!$F$104*'Discipline Analysis'!$B40,"") -> 2583.36 | V40: ='34'!$F$104 -> 0.39
A41: Ranger | B41: =OFFSET('35'!$D$4,$A$3,0) -> 1824 | C41: =OFFSET('35'!$E$4,$A$3,0) -> 6453.2766 | D41: =OFFSET('35'!$F$4,$A$3,0) -> 3.54 | E41: =OFFSET('35'!$E$66,$A$3,0) -> 1950 | F41: =OFFSET('35'!$F$66,$A$3,0) -> 1.07 | G41: =IFERROR('35'!$F$100*'Discipline Analysis'!$B41,"") -> 346.56 | H41: ='35'!$F$100 -> 0.19 | I41: =IFERROR('35'!$F$98*'Discipline Analysis'!$B41,"") -> 2225.28 | J41: ='35'!$F$98 -> 1.22 | K41: =IFERROR('35'!$F$99*'Discipline Analysis'!$B41,"") -> 984.96 | L41: ='35'!$F$99 -> 0.54 | M41: =OFFSET('35'!$E$35,$A$3,0) -> 131 | N41: =OFFSET('35'!$F$35,$A$3,0) -> 0.07 | O41: =IFERROR('35'!$F$101*'Discipline Analysis'!$B41,"") -> 492.48 | P41: ='35'!$F$101 -> 0.27 | Q41: =IFERROR('35'!$F$102*'Discipline Analysis'!$B41,"") | R41: ='35'!$F$102 | S41: =IFERROR('35'!$F$103*'Discipline Analysis'!$B41,"") | T41: ='35'!$F$103 | U41: =IFERROR('35'!$F$104*'Discipline Analysis'!$B41,"") -> 328.32 | V41: ='35'!$F$104 -> 0.18
A42: San Jacinto | B42: =OFFSET('36'!$D$4,$A$3,0) -> 2976 | C42: =OFFSET('36'!$E$4,$A$3,0) -> 11524.097 | D42: =OFFSET('36'!$F$4,$A$3,0) -> 3.87 | E42: =OFFSET('36'!$E$66,$A$3,0) -> 3482 | F42: =OFFSET('36'!$F$66,$A$3,0) -> 1.17 | G42: =IFERROR('36'!$F$100*'Discipline Analysis'!$B42,"") -> 624.96 | H42: ='36'!$F$100 -> 0.21 | I42: =IFERROR('36'!$F$98*'Discipline Analysis'!$B42,"") -> 3333.12 | J42: ='36'!$F$98 -> 1.12 | K42: =IFERROR('36'!$F$99*'Discipline Analysis'!$B42,"") -> 1815.36 | L42: ='36'!$F$99 -> 0.61 | M42: =OFFSET('36'!$E$35,$A$3,0) -> 0 | N42: =OFFSET('36'!$F$35,$A$3,0) | O42: =IFERROR('36'!$F$101*'Discipline Analysis'!$B42,"") -> 1160.64 | P42: ='36'!$F$101 -> 0.39 | Q42: =IFERROR('36'!$F$102*'Discipline Analysis'!$B42,"") | R42: ='36'!$F$102 | S42: =IFERROR('36'!$F$103*'Discipline Analysis'!$B42,"") | T42: ='36'!$F$103 | U42: =IFERROR('36'!$F$104*'Discipline Analysis'!$B42,"") -> 1071.36 | V42: ='36'!$F$104 -> 0.36
A43: South Plains | B43: =OFFSET('37'!$D$4,$A$3,0) -> 27040 | C43: =OFFSET('37'!$E$4,$A$3,0) -> 219644.06 | D43: =OFFSET('37'!$F$4,$A$3,0) -> 8.12 | E43: =OFFSET('37'!$E$66,$A$3,0) -> 109585 | F43: =OFFSET('37'!$F$66,$A$3,0) -> 4.05 | G43: =IFERROR('37'!$F$100*'Discipline Analysis'!$B43,"") -> 4596.8 | H43: ='37'!$F$100 -> 0.17 | I43: =IFERROR('37'!$F$98*'Discipline Analysis'!$B43,"") -> 21632 | J43: ='37'!$F$98 -> 0.8 | K43: =IFERROR('37'!$F$99*'Discipline Analysis'!$B43,"") -> 11897.6 | L43: ='37'!$F$99 -> 0.44 | M43: =OFFSET('37'!$E$35,$A$3,0) -> 46533 | N43: =OFFSET('37'!$F$35,$A$3,0) -> 1.72 | O43: =IFERROR('37'!$F$101*'Discipline Analysis'!$B43,"") -> 2163.2 | P43: ='37'!$F$101 -> 0.08 | Q43: =IFERROR('37'!$F$102*'Discipline Analysis'!$B43,"") -> 2433.6 | R43: ='37'!$F$102 -> 0.09 | S43: =IFERROR('37'!$F$103*'Discipline Analysis'!$B43,"") | T43: ='37'!$F$103 | U43: =IFERROR('37'!$F$104*'Discipline Analysis'!$B43,"") -> 20820.8 | V43: ='37'!$F$104 -> 0.77
A44: South Texas | B44: =OFFSET('38'!$D$4,$A$3,0) -> 0 | C44: =OFFSET('38'!$E$4,$A$3,0) -> 0 | D44: =OFFSET('38'!$F$4,$A$3,0) | E44: =OFFSET('38'!$E$66,$A$3,0) -> 0 | F44: =OFFSET('38'!$F$66,$A$3,0) | G44: =IFERROR('38'!$F$100*'Discipline Analysis'!$B44,"") -> 0 | H44: ='38'!$F$100 -> 0.11 | I44: =IFERROR('38'!$F$98*'Discipline Analysis'!$B44,"") -> 0 | J44: ='38'!$F$98 -> 1.18 | K44: =IFERROR('38'!$F$99*'Discipline Analysis'!$B44,"") -> 0 | L44: ='38'!$F$99 -> 0.51 | M44: =OFFSET('38'!$E$35,$A$3,0) -> 0 | N44: =OFFSET('38'!$F$35,$A$3,0) | O44: =IFERROR('38'!$F$101*'Discipline Analysis'!$B44,"") -> 0 | P44: ='38'!$F$101 -> 0.33 | Q44: =IFERROR('38'!$F$102*'Discipline Analysis'!$B44,"") | R44: ='38'!$F$102 | S44: =IFERROR('38'!$F$103*'Discipline Analysis'!$B44,"") | T44: ='38'!$F$103 | U44: =IFERROR('38'!$F$104*'Discipline Analysis'!$B44,"") -> 0 | V44: ='38'!$F$104 -> 0.5
A45: Southwest Texas | B45: =OFFSET('39'!$D$4,$A$3,0) -> 23712 | C45: =OFFSET('39'!$E$4,$A$3,0) -> 228442.51 | D45: =OFFSET('39'!$F$4,$A$3,0) -> 9.63 | E45: =OFFSET('39'!$E$66,$A$3,0) -> 146984 | F45: =OFFSET('39'!$F$66,$A$3,0) -> 6.2 | G45: =IFERROR('39'!$F$100*'Discipline Analysis'!$B45,"") -> 6165.12 | H45: ='39'!$F$100 -> 0.26 | I45: =IFERROR('39'!$F$98*'Discipline Analysis'!$B45,"") -> 27743.04 | J45: ='39'!$F$98 -> 1.17 | K45: =IFERROR('39'!$F$99*'Discipline Analysis'!$B45,"") -> 9959.04 | L45: ='39'!$F$99 -> 0.42 | M45: =OFFSET('39'!$E$35,$A$3,0) -> 21707 | N45: =OFFSET('39'!$F$35,$A$3,0) -> 0.92 | O45: =IFERROR('39'!$F$101*'Discipline Analysis'!$B45,"") -> 10196.16 | P45: ='39'!$F$101 -> 0.43 | Q45: =IFERROR('39'!$F$102*'Discipline Analysis'!$B45,"") | R45: ='39'!$F$102 | S45: =IFERROR('39'!$F$103*'Discipline Analysis'!$B45,"") | T45: ='39'!$F$103 | U45: =IFERROR('39'!$F$104*'Discipline Analysis'!$B45,"") -> 5690.88 | V45: ='39'!$F$104 -> 0.24
A46: Tarrant | B46: =OFFSET('40'!$D$4,$A$3,0) -> 20708 | C46: =OFFSET('40'!$E$4,$A$3,0) -> 163789.25 | D46: =OFFSET('40'!$F$4,$A$3,0) -> 7.91 | E46: =OFFSET('40'!$E$66,$A$3,0) -> 69921 | F46: =OFFSET('40'!$F$66,$A$3,0) -> 3.38 | G46: =IFERROR('40'!$F$100*'Discipline Analysis'!$B46,"") -> 7661.96 | H46: ='40'!$F$100 -> 0.37 | I46: =IFERROR('40'!$F$98*'Discipline Analysis'!$B46,"") -> 20293.84 | J46: ='40'!$F$98 -> 0.98 | K46: =IFERROR('40'!$F$99*'Discipline Analysis'!$B46,"") -> 12838.96 | L46: ='40'!$F$99 -> 0.62 | M46: =OFFSET('40'!$E$35,$A$3,0) -> 36143 | N46: =OFFSET('40'!$F$35,$A$3,0) -> 1.75 | O46: =IFERROR('40'!$F$101*'Discipline Analysis'!$B46,"") -> 3934.52 | P46: ='40'!$F$101 -> 0.19 | Q46: =IFERROR('40'!$F$102*'Discipline Analysis'!$B46,"") | R46: ='40'!$F$102 | S46: =IFERROR('40'!$F$103*'Discipline Analysis'!$B46,"") | T46: ='40'!$F$103 | U46: =IFERROR('40'!$F$104*'Discipline Analysis'!$B46,"") -> 13046.04 | V46: ='40'!$F$104 -> 0.63
A47: Temple | B47: =OFFSET('41'!$D$4,$A$3,0) -> 0 | C47: =OFFSET('41'!$E$4,$A$3,0) -> 0 | D47: =OFFSET('41'!$F$4,$A$3,0) | E47: =OFFSET('41'!$E$66,$A$3,0) -> 0 | F47: =OFFSET('41'!$F$66,$A$3,0) | G47: =IFERROR('41'!$F$100*'Discipline Analysis'!$B47,"") -> 0 | H47: ='41'!$F$100 -> 0.36 | I47: =IFERROR('41'!$F$98*'Discipline Analysis'!$B47,"") -> 0 | J47: ='41'!$F$98 -> 0.92 | K47: =IFERROR('41'!$F$99*'Discipline Analysis'!$B47,"") -> 0 | L47: ='41'!$F$99 -> 0.54 | M47: =OFFSET('41'!$E$35,$A$3,0) -> 0 | N47: =OFFSET('41'!$F$35,$A$3,0) | O47: =IFERROR('41'!$F$101*'Discipline Analysis'!$B47,"") -> 0 | P47: ='41'!$F$101 -> 0.11 | Q47: =IFERROR('41'!$F$102*'Discipline Analysis'!$B47,"") | R47: ='41'!$F$102 | S47: =IFERROR('41'!$F$103*'Discipline Analysis'!$B47,"") | T47: ='41'!$F$103 | U47: =IFERROR('41'!$F$104*'Discipline Analysis'!$B47,"") -> 0 | V47: ='41'!$F$104 -> 0.54
A48: Texarkana | B48: =OFFSET('42'!$D$4,$A$3,0) -> 36649 | C48: =OFFSET('42'!$E$4,$A$3,0) -> 200411.37 | D48: =OFFSET('42'!$F$4,$A$3,0) -> 5.47 | E48: =OFFSET('42'!$E$66,$A$3,0) -> 102268 | F48: =OFFSET('42'!$F$66,$A$3,0) -> 2.79 | G48: =IFERROR('42'!$F$100*'Discipline Analysis'!$B48,"") -> 8062.78 | H48: ='42'!$F$100 -> 0.22 | I48: =IFERROR('42'!$F$98*'Discipline Analysis'!$B48,"") -> 22722.38 | J48: ='42'!$F$98 -> 0.62 | K48: =IFERROR('42'!$F$99*'Discipline Analysis'!$B48,"") -> 9162.25 | L48: ='42'!$F$99 -> 0.25 | M48: =OFFSET('42'!$E$35,$A$3,0) -> 40662 | N48: =OFFSET('42'!$F$35,$A$3,0) -> 1.11 | O48: =IFERROR('42'!$F$101*'Discipline Analysis'!$B48,"") -> 3298.41 | P48: ='42'!$F$101 -> 0.09 | Q48: =IFERROR('42'!$F$102*'Discipline Analysis'!$B48,"") | R48: ='42'!$F$102 | S48: =IFERROR('42'!$F$103*'Discipline Analysis'!$B48,"") | T48: ='42'!$F$103 | U48: =IFERROR('42'!$F$104*'Discipline Analysis'!$B48,"") -> 14293.11 | V48: ='42'!$F$104 -> 0.39
A49: Texas Southmost | B49: =OFFSET('43'!$D$4,$A$3,0) -> 0 | C49: =OFFSET('43'!$E$4,$A$3,0) -> 0 | D49: =OFFSET('43'!$F$4,$A$3,0) | E49: =OFFSET('43'!$E$66,$A$3,0) -> 0 | F49: =OFFSET('43'!$F$66,$A$3,0) | G49: =IFERROR('43'!$F$100*'Discipline Analysis'!$B49,"") -> 0 | H49: ='43'!$F$100 -> 0.36 | I49: =IFERROR('43'!$F$98*'Discipline Analysis'!$B49,"") -> 0 | J49: ='43'!$F$98 -> 0.87 | K49: =IFERROR('43'!$F$99*'Discipline Analysis'!$B49,"") -> 0 | L49: ='43'!$F$99 -> 0.62 | M49: =OFFSET('43'!$E$35,$A$3,0) -> 0 | N49: =OFFSET('43'!$F$35,$A$3,0) | O49: =IFERROR('43'!$F$101*'Discipline Analysis'!$B49,"") -> 0 | P49: ='43'!$F$101 -> 0.21 | Q49: =IFERROR('43'!$F$102*'Discipline Analysis'!$B49,"") | R49: ='43'!$F$102 | S49: =IFERROR('43'!$F$103*'Discipline Analysis'!$B49,"") | T49: ='43'!$F$103 | U49: =IFERROR('43'!$F$104*'Discipline Analysis'!$B49,"") -> 0 | V49: ='43'!$F$104 -> 1
A50: Trinity Valley | B50: =OFFSET('44'!$D$4,$A$3,0) -> 63838 | C50: =OFFSET('44'!$E$4,$A$3,0) -> 427073.06 | D50: =OFFSET('44'!$F$4,$A$3,0) -> 6.69 | E50: =OFFSET('44'!$E$66,$A$3,0) -> 217885 | F50: =OFFSET('44'!$F$66,$A$3,0) -> 3.41 | G50: =IFERROR('44'!$F$100*'Discipline Analysis'!$B50,"") -> 17236.26 | H50: ='44'!$F$100 -> 0.27 | I50: =IFERROR('44'!$F$98*'Discipline Analysis'!$B50,"") -> 38302.8 | J50: ='44'!$F$98 -> 0.6 | K50: =IFERROR('44'!$F$99*'Discipline Analysis'!$B50,"") -> 28088.72 | L50: ='44'!$F$99 -> 0.44 | M50: =OFFSET('44'!$E$35,$A$3,0) -> 68846 | N50: =OFFSET('44'!$F$35,$A$3,0) -> 1.08 | O50: =IFERROR('44'!$F$101*'Discipline Analysis'!$B50,"") -> 14682.74 | P50: ='44'!$F$101 -> 0.23 | Q50: =IFERROR('44'!$F$102*'Discipline Analysis'!$B50,"") -> 5745.42 | R50: ='44'!$F$102 -> 0.09 | S50: =IFERROR('44'!$F$103*'Discipline Analysis'!$B50,"") | T50: ='44'!$F$103 | U50: =IFERROR('44'!$F$104*'Discipline Analysis'!$B50,"") -> 35749.28 | V50: ='44'!$F$104 -> 0.56
A51: Tyler | B51: =OFFSET('45'!$D$4,$A$3,0) -> 15856 | C51: =OFFSET('45'!$E$4,$A$3,0) -> 129035.3 | D51: =OFFSET('45'!$F$4,$A$3,0) -> 8.14 | E51: =OFFSET('45'!$E$66,$A$3,0) -> 77519 | F51: =OFFSET('45'!$F$66,$A$3,0) -> 4.89 | G51: =IFERROR('45'!$F$100*'Discipline Analysis'!$B51,"") -> 3488.32 | H51: ='45'!$F$100 -> 0.22 | I51: =IFERROR('45'!$F$98*'Discipline Analysis'!$B51,"") -> 15063.2 | J51: ='45'!$F$98 -> 0.95 | K51: =IFERROR('45'!$F$99*'Discipline Analysis'!$B51,"") -> 11574.88 | L51: ='45'!$F$99 -> 0.73 | M51: =OFFSET('45'!$E$35,$A$3,0) -> 14095 | N51: =OFFSET('45'!$F$35,$A$3,0) -> 0.89 | O51: =IFERROR('45'!$F$101*'Discipline Analysis'!$B51,"") -> 3805.44 | P51: ='45'!$F$101 -> 0.24 | Q51: =IFERROR('45'!$F$102*'Discipline Analysis'!$B51,"") | R51: ='45'!$F$102 | S51: =IFERROR('45'!$F$103*'Discipline Analysis'!$B51,"") | T51: ='45'!$F$103 | U51: =IFERROR('45'!$F$104*'Discipline Analysis'!$B51,"") -> 3646.88 | V51: ='45'!$F$104 -> 0.23
A52: Vernon | B52: =OFFSET('46'!$D$4,$A$3,0) -> 12976 | C52: =OFFSET('46'!$E$4,$A$3,0) -> 86609.219 | D52: =OFFSET('46'!$F$4,$A$3,0) -> 6.67 | E52: =OFFSET('46'!$E$66,$A$3,0) -> 40628 | F52: =OFFSET('46'!$F$66,$A$3,0) -> 3.13 | G52: =IFERROR('46'!$F$100*'Discipline Analysis'!$B52,"") -> 2465.44 | H52: ='46'!$F$100 -> 0.19 | I52: =IFERROR('46'!$F$98*'Discipline Analysis'!$B52,"") -> 13754.56 | J52: ='46'!$F$98 -> 1.06 | K52: =IFERROR('46'!$F$99*'Discipline Analysis'!$B52,"") -> 7007.04 | L52: ='46'!$F$99 -> 0.54 | M52: =OFFSET('46'!$E$35,$A$3,0) -> 9937 | N52: =OFFSET('46'!$F$35,$A$3,0) -> 0.77 | O52: =IFERROR('46'!$F$101*'Discipline Analysis'!$B52,"") -> 8434.4 | P52: ='46'!$F$101 -> 0.65 | Q52: =IFERROR('46'!$F$102*'Discipline Analysis'!$B52,"") -> 389.28 | R52: ='46'!$F$102 -> 0.03 | S52: =IFERROR('46'!$F$103*'Discipline Analysis'!$B52,"") | T52: ='46'!$F$103 | U52: =IFERROR('46'!$F$104*'Discipline Analysis'!$B52,"") -> 4022.56 | V52: ='46'!$F$104 -> 0.31
A53: Victoria | B53: =OFFSET('47'!$D$4,$A$3,0) -> 2256 | C53: =OFFSET('47'!$E$4,$A$3,0) -> 12130.587 | D53: =OFFSET('47'!$F$4,$A$3,0) -> 5.38 | E53: =OFFSET('47'!$E$66,$A$3,0) -> 6354 | F53: =OFFSET('47'!$F$66,$A$3,0) -> 2.82 | G53: =IFERROR('47'!$F$100*'Discipline Analysis'!$B53,"") -> 631.68 | H53: ='47'!$F$100 -> 0.28 | I53: =IFERROR('47'!$F$98*'Discipline Analysis'!$B53,"") -> 2098.08 | J53: ='47'!$F$98 -> 0.93 | K53: =IFERROR('47'!$F$99*'Discipline Analysis'!$B53,"") -> 1218.24 | L53: ='47'!$F$99 -> 0.54 | M53: =OFFSET('47'!$E$35,$A$3,0) -> 0 | N53: =OFFSET('47'!$F$35,$A$3,0) | O53: =IFERROR('47'!$F$101*'Discipline Analysis'!$B53,"") -> 518.88 | P53: ='47'!$F$101 -> 0.23 | Q53: =IFERROR('47'!$F$102*'Discipline Analysis'!$B53,"") | R53: ='47'!$F$102 | S53: =IFERROR('47'!$F$103*'Discipline Analysis'!$B53,"") | T53: ='47'!$F$103 | U53: =IFERROR('47'!$F$104*'Discipline Analysis'!$B53,"") -> 1331.04 | V53: ='47'!$F$104 -> 0.59
A54: Weatherford | B54: =OFFSET('48'!$D$4,$A$3,0) -> 26808 | C54: =OFFSET('48'!$E$4,$A$3,0) -> 204324.97 | D54: =OFFSET('48'!$F$4,$A$3,0) -> 7.62 | E54: =OFFSET('48'!$E$66,$A$3,0) -> 92876 | F54: =OFFSET('48'!$F$66,$A$3,0) -> 3.46 | G54: =IFERROR('48'!$F$100*'Discipline Analysis'!$B54,"") -> 6165.84 | H54: ='48'!$F$100 -> 0.23 | I54: =IFERROR('48'!$F$98*'Discipline Analysis'!$B54,"") -> 34314.24 | J54: ='48'!$F$98 -> 1.28 | K54: =IFERROR('48'!$F$99*'Discipline Analysis'!$B54,"") -> 10991.28 | L54: ='48'!$F$99 -> 0.41 | M54: =OFFSET('48'!$E$35,$A$3,0) -> 55043 | N54: =OFFSET('48'!$F$35,$A$3,0) -> 2.05 | O54: =IFERROR('48'!$F$101*'Discipline Analysis'!$B54,"") -> 3485.04 | P54: ='48'!$F$101 -> 0.13 | Q54: =IFERROR('48'!$F$102*'Discipline Analysis'!$B54,"") | R54: ='48'!$F$102 | S54: =IFERROR('48'!$F$103*'Discipline Analysis'!$B54,"") | T54: ='48'!$F$103 | U54: =IFERROR('48'!$F$104*'Discipline Analysis'!$B54,"") -> 1340.4 | V54: ='48'!$F$104 -> 0.05
A55: Western Texas | B55: =OFFSET('49'!$D$4,$A$3,0) -> 93440 | C55: =OFFSET('49'!$E$4,$A$3,0) -> 595884.67 | D55: =OFFSET('49'!$F$4,$A$3,0) -> 6.38 | E55: =OFFSET('49'!$E$66,$A$3,0) -> 236231 | F55: =OFFSET('49'!$F$66,$A$3,0) -> 2.53 | G55: =IFERROR('49'!$F$100*'Discipline Analysis'!$B55,"") -> 17753.6 | H55: ='49'!$F$100 -> 0.19 | I55: =IFERROR('49'!$F$98*'Discipline Analysis'!$B55,"") -> 149504 | J55: ='49'!$F$98 -> 1.6 | K55: =IFERROR('49'!$F$99*'Discipline Analysis'!$B55,"") -> 44851.2 | L55: ='49'!$F$99 -> 0.48 | M55: =OFFSET('49'!$E$35,$A$3,0) -> 85836 | N55: =OFFSET('49'!$F$35,$A$3,0) -> 0.92 | O55: =IFERROR('49'!$F$101*'Discipline Analysis'!$B55,"") -> 57932.8 | P55: ='49'!$F$101 -> 0.62 | Q55: =IFERROR('49'!$F$102*'Discipline Analysis'!$B55,"") | R55: ='49'!$F$102 | S55: =IFERROR('49'!$F$103*'Discipline Analysis'!$B55,"") | T55: ='49'!$F$103 | U55: =IFERROR('49'!$F$104*'Discipline Analysis'!$B55,"") -> 3737.6 | V55: ='49'!$F$104 -> 0.04
A56: Wharton | B56: =OFFSET('50'!$D$4,$A$3,0) -> 20754 | C56: =OFFSET('50'!$E$4,$A$3,0) -> 118937.29 | D56: =OFFSET('50'!$F$4,$A$3,0) -> 5.73 | E56: =OFFSET('50'!$E$66,$A$3,0) -> 52049 | F56: =OFFSET('50'!$F$66,$A$3,0) -> 2.51 | G56: =IFERROR('50'!$F$100*'Discipline Analysis'!$B56,"") -> 4565.88 | H56: ='50'!$F$100 -> 0.22 | I56: =IFERROR('50'!$F$98*'Discipline Analysis'!$B56,"") -> 30923.46 | J56: ='50'!$F$98 -> 1.49 | K56: =IFERROR('50'!$F$99*'Discipline Analysis'!$B56,"") -> 8924.22 | L56: ='50'!$F$99 -> 0.43 | M56: =OFFSET('50'!$E$35,$A$3,0) -> 2377 | N56: =OFFSET('50'!$F$35,$A$3,0) -> 0.11 | O56: =IFERROR('50'!$F$101*'Discipline Analysis'!$B56,"") -> 10584.54 | P56: ='50'!$F$101 -> 0.51 | Q56: =IFERROR('50'!$F$102*'Discipline Analysis'!$B56,"") | R56: ='50'!$F$102 | S56: =IFERROR('50'!$F$103*'Discipline Analysis'!$B56,"") | T56: ='50'!$F$103 | U56: =IFERROR('50'!$F$104*'Discipline Analysis'!$B56,"") -> 9339.3 | V56: ='50'!$F$104 -> 0.45
A57: TSTC-Harlingen | B57: =OFFSET('51'!$D$4,$A$3,0) -> 18564 | C57: =OFFSET('51'!$E$4,$A$3,0) -> 168223.23 | D57: =OFFSET('51'!$F$4,$A$3,0) -> 9.06 | E57: =OFFSET('51'!$E$66,$A$3,0) -> 44305 | F57: =OFFSET('51'!$F$66,$A$3,0) -> 2.39 | G57: =IFERROR('51'!$F$100*'Discipline Analysis'!$B57,"") -> 2784.6 | H57: ='51'!$F$100 -> 0.15 | I57: =IFERROR('51'!$F$98*'Discipline Analysis'!$B57,"") -> 14665.56 | J57: ='51'!$F$98 -> 0.79 | K57: =IFERROR('51'!$F$99*'Discipline Analysis'!$B57,"") -> 4084.08 | L57: ='51'!$F$99 -> 0.22 | M57: =OFFSET('51'!$E$35,$A$3,0) -> 96377 | N57: =OFFSET('51'!$F$35,$A$3,0) -> 5.19 | O57: =IFERROR('51'!$F$101*'Discipline Analysis'!$B57,"") -> 2598.96 | P57: ='51'!$F$101 -> 0.14 | Q57: =IFERROR('51'!$F$102*'Discipline Analysis'!$B57,"") | R57: ='51'!$F$102 | S57: =IFERROR('51'!$F$103*'Discipline Analysis'!$B57,"") | T57: ='51'!$F$103 | U57: =IFERROR('51'!$F$104*'Discipline Analysis'!$B57,"") -> 3527.16 | V57: ='51'!$F$104 -> 0.19
A58: TSTC-West Texas | B58: =OFFSET('52'!$D$4,$A$3,0) -> 2304 | C58: =OFFSET('52'!$E$4,$A$3,0) -> 14261.641 | D58: =OFFSET('52'!$F$4,$A$3,0) -> 6.19 | E58: =OFFSET('52'!$E$66,$A$3,0) -> 7500 | F58: =OFFSET('52'!$F$66,$A$3,0) -> 3.26 | G58: =IFERROR('52'!$F$100*'Discipline Analysis'!$B58,"") -> 276.48 | H58: ='52'!$F$100 -> 0.12 | I58: =IFERROR('52'!$F$98*'Discipline Analysis'!$B58,"") -> 2741.76 | J58: ='52'!$F$98 -> 1.19 | K58: =IFERROR('52'!$F$99*'Discipline Analysis'!$B58,"") -> 1059.84 | L58: ='52'!$F$99 -> 0.46 | M58: =OFFSET('52'!$E$35,$A$3,0) -> 2052 | N58: =OFFSET('52'!$F$35,$A$3,0) -> 0.89 | O58: =IFERROR('52'!$F$101*'Discipline Analysis'!$B58,"") -> 161.28 | P58: ='52'!$F$101 -> 0.07 | Q58: =IFERROR('52'!$F$102*'Discipline Analysis'!$B58,"") | R58: ='52'!$F$102 | S58: =IFERROR('52'!$F$103*'Discipline Analysis'!$B58,"") | T58: ='52'!$F$103 | U58: =IFERROR('52'!$F$104*'Discipline Analysis'!$B58,"") -> 460.8 | V58: ='52'!$F$104 -> 0.2
A59: TSTC-Marshall | B59: =OFFSET('53'!$D$4,$A$3,0) -> 0 | C59: =OFFSET('53'!$E$4,$A$3,0) -> 0 | D59: =OFFSET('53'!$F$4,$A$3,0) | E59: =OFFSET('53'!$E$66,$A$3,0) -> 0 | F59: =OFFSET('53'!$F$66,$A$3,0) | G59: =IFERROR('53'!$F$100*'Discipline Analysis'!$B59,"") | H59: ='53'!$F$100 | I59: =IFERROR('53'!$F$98*'Discipline Analysis'!$B59,"") | J59: ='53'!$F$98 | K59: =IFERROR('53'!$F$99*'Discipline Analysis'!$B59,"") | L59: ='53'!$F$99 | M59: =OFFSET('53'!$E$35,$A$3,0) -> 0 | N59: =OFFSET('53'!$F$35,$A$3,0) | O59: =IFERROR('53'!$F$101*'Discipline Analysis'!$B59,"") | P59: ='53'!$F$101 | Q59: =IFERROR('53'!$F$102*'Discipline Analysis'!$B59,"") | R59: ='53'!$F$102 | S59: =IFERROR('53'!$F$103*'Discipline Analysis'!$B59,"") | T59: ='53'!$F$103 | U59: =IFERROR('53'!$F$104*'Discipline Analysis'!$B59,"") | V59: ='53'!$F$104
A60: TSTC-Waco | B60: =OFFSET('54'!$D$4,$A$3,0) -> 79872 | C60: =OFFSET('54'!$E$4,$A$3,0) -> 660182.75 | D60: =OFFSET('54'!$F$4,$A$3,0) -> 8.27 | E60: =OFFSET('54'!$E$66,$A$3,0) -> 349257 | F60: =OFFSET('54'!$F$66,$A$3,0) -> 4.37 | G60: =IFERROR('54'!$F$100*'Discipline Analysis'!$B60,"") -> 7987.2 | H60: ='54'!$F$100 -> 0.1 | I60: =IFERROR('54'!$F$98*'Discipline Analysis'!$B60,"") -> 51916.8 | J60: ='54'!$F$98 -> 0.65 | K60: =IFERROR('54'!$F$99*'Discipline Analysis'!$B60,"") -> 19169.28 | L60: ='54'!$F$99 -> 0.24 | M60: =OFFSET('54'!$E$35,$A$3,0) -> 209816 | N60: =OFFSET('54'!$F$35,$A$3,0) -> 2.63 | O60: =IFERROR('54'!$F$101*'Discipline Analysis'!$B60,"") -> 7188.48 | P60: ='54'!$F$101 -> 0.09 | Q60: =IFERROR('54'!$F$102*'Discipline Analysis'!$B60,"") | R60: ='54'!$F$102 | S60: =IFERROR('54'!$F$103*'Discipline Analysis'!$B60,"") | T60: ='54'!$F$103 | U60: =IFERROR('54'!$F$104*'Discipline Analysis'!$B60,"") -> 14376.96 | V60: ='54'!$F$104 -> 0.18
A61: Lamar-IOT | B61: =OFFSET('55'!$D$4,$A$3,0) -> 0 | C61: =OFFSET('55'!$E$4,$A$3,0) -> 0 | D61: =OFFSET('55'!$F$4,$A$3,0) | E61: =OFFSET('55'!$E$66,$A$3,0) -> 0 | F61: =OFFSET('55'!$F$66,$A$3,0) | G61: =IFERROR('55'!$F$100*'Discipline Analysis'!$B61,"") | H61: ='55'!$F$100 | I61: =IFERROR('55'!$F$98*'Discipline Analysis'!$B61,"") | J61: ='55'!$F$98 | K61: =IFERROR('55'!$F$99*'Discipline Analysis'!$B61,"") | L61: ='55'!$F$99 | M61: =OFFSET('55'!$E$35,$A$3,0) -> 0 | N61: =OFFSET('55'!$F$35,$A$3,0) | O61: =IFERROR('55'!$F$101*'Discipline Analysis'!$B61,"") | P61: ='55'!$F$101 | Q61: =IFERROR('55'!$F$102*'Discipline Analysis'!$B61,"") | R61: ='55'!$F$102 | S61: =IFERROR('55'!$F$103*'Discipline Analysis'!$B61,"") | T61: ='55'!$F$103 | U61: =IFERROR('55'!$F$104*'Discipline Analysis'!$B61,"") | V61: ='55'!$F$104
A62: Lamar-Orange | B62: =OFFSET('56'!$D$4,$A$3,0) -> 1072 | C62: =OFFSET('56'!$E$4,$A$3,0) -> 7224.4169 | D62: =OFFSET('56'!$F$4,$A$3,0) -> 6.74 | E62: =OFFSET('56'!$E$66,$A$3,0) -> 3323 | F62: =OFFSET('56'!$F$66,$A$3,0) -> 3.1 | G62: =IFERROR('56'!$F$100*'Discipline Analysis'!$B62,"") -> 536 | H62: ='56'!$F$100 -> 0.5 | I62: =IFERROR('56'!$F$98*'Discipline Analysis'!$B62,"") -> 1340 | J62: ='56'!$F$98 -> 1.25 | K62: =IFERROR('56'!$F$99*'Discipline Analysis'!$B62,"") -> 868.32 | L62: ='56'!$F$99 -> 0.81 | M62: =OFFSET('56'!$E$35,$A$3,0) -> 457 | N62: =OFFSET('56'!$F$35,$A$3,0) -> 0.43 | O62: =IFERROR('56'!$F$101*'Discipline Analysis'!$B62,"") -> 364.48 | P62: ='56'!$F$101 -> 0.34 | Q62: =IFERROR('56'!$F$102*'Discipline Analysis'!$B62,"") | R62: ='56'!$F$102 | S62: =IFERROR('56'!$F$103*'Discipline Analysis'!$B62,"") | T62: ='56'!$F$103 | U62: =IFERROR('56'!$F$104*'Discipline Analysis'!$B62,"") -> 321.6 | V62: ='56'!$F$104 -> 0.3
A63: Lamar-Port Arthur | B63: =OFFSET('57'!$D$4,$A$3,0) -> 0 | C63: =OFFSET('57'!$E$4,$A$3,0) -> 0 | D63: =OFFSET('57'!$F$4,$A$3,0) | E63: =OFFSET('57'!$E$66,$A$3,0) -> 0 | F63: =OFFSET('57'!$F$66,$A$3,0) | G63: =IFERROR('57'!$F$100*'Discipline Analysis'!$B63,"") -> 0 | H63: ='57'!$F$100 -> 0.36 | I63: =IFERROR('57'!$F$98*'Discipline Analysis'!$B63,"") -> 0 | J63: ='57'!$F$98 -> 1.34 | K63: =IFERROR('57'!$F$99*'Discipline Analysis'!$B63,"") -> 0 | L63: ='57'!$F$99 -> 0.42 | M63: =OFFSET('57'!$E$35,$A$3,0) -> 0 | N63: =OFFSET('57'!$F$35,$A$3,0) | O63: =IFERROR('57'!$F$101*'Discipline Analysis'!$B63,"") -> 0 | P63: ='57'!$F$101 -> 0.13 | Q63: =IFERROR('57'!$F$102*'Discipline Analysis'!$B63,"") | R63: ='57'!$F$102 | S63: =IFERROR('57'!$F$103*'Discipline Analysis'!$B63,"") | T63: ='57'!$F$103 | U63: =IFERROR('57'!$F$104*'Discipline Analysis'!$B63,"") -> 0 | V63: ='57'!$F$104 -> 0.31
A64: Total | B64: =OFFSET(Summary!$D$4,$A$3,0) -> 1156306 | C64: =OFFSET(Summary!$E$4,$A$3,0) -> 8858021.5 | D64: =MEDIAN(D7:D63) -> 6.725 | E64: =OFFSET(Summary!$E$66,$A$3,0) -> 3793956 | F64: =MEDIAN(F7:F63) -> 3.32 | G64: =Summary!$F$100*B64 -> 265950.38 | H64: =MEDIAN(H7:H63) -> 0.23 | I64: =Summary!$F$98*'Discipline Analysis'!B64 -> 1306625.8 | J64: =MEDIAN(J7:J63) -> 1.13 | K64: =Summary!$F$99*'Discipline Analysis'!B64 -> 589716.06 | L64: =MEDIAN(L7:L63) -> 0.51 | M64: =OFFSET(Summary!$E$35,$A$3,0) -> 1784347 | N64: =MEDIAN(N7:N63) -> 0.92 | O64: =IFERROR(Summary!$F$101*'Discipline Analysis'!B64,"") -> 358454.86 | P64: =MEDIAN(P7:P63) -> 0.31 | Q64: =Summary!$F$102*'Discipline Analysis'!B64 -> 69378.36 | R64: =MEDIAN(R7:R63) -> 0.06 | S64: =Summary!$F$103*'Discipline Analysis'!B64 -> 0 | T64: =MEDIAN(T7:T63) -> 0 | U64: =Summary!$F$104*'Discipline Analysis'!B64 -> 381580.98 | V64: =MEDIAN(V7:V63) -> 0.33

Sheet 1
A1: =Summary!A1 -> Community and Technical Colleges, Report of Fundable Operating Expenses, Fiscal Year (FY) 1999
A2: 003607 | B2: =VLOOKUP(A2,Data!A:G,7,0) -> Alamo Community College District
F3: =IFERROR(VLOOKUP(A2,Data!A:C,3,0),"0") -> 1
A4: Fund | B4: Total Expense by Discipline | D4: Contact Hours | E4: Expense | F4: Expense per Contact Hour
A5: 1 | B5: Agriculture | D5: =D36 -> 22080 | E5: =E36+E67+IFERROR($E$105/$D$105*D5,0) -> 140133.37 | F5: =IF(OR(D5=0,E5=0),"",ROUND(E5/D5,2)) -> 6.35
A6: 2 | B6: Architecture and Precision Production Trades | D6: =D37 -> 177333 | E6: =E37+E68+IFERROR($E$105/$D$105*D6,0) -> 1583729.9 | F6: =IF(OR(D6=0,E6=0),"",ROUND(E6/D6,2)) -> 8.93
A7: 3 | B7: Biology, Physical Sciences, and Science Technology | D7: =D38 -> 1476192 | E7: =E38+E69+IFERROR($E$105/$D$105*D7,0) -> 10549635 | F7: =IF(OR(D7=0,E7=0),"",ROUND(E7/D7,2)) -> 7.15
A8: 4 | B8: Business Management, Marketing, and Administrative Services | D8: =D39 -> 1411904 | E8: =E39+E70+IFERROR($E$105/$D$105*D8,0) -> 12443471 | F8: =IF(OR(D8=0,E8=0),"",ROUND(E8/D8,2)) -> 8.81
A9: 5 | B9: Career Pilot | D9: =D40 -> 14144 | E9: =E40+E71+IFERROR($E$105/$D$105*D9,0) -> 347294.73 | F9: =IF(OR(D9=0,E9=0),"",ROUND(E9/D9,2)) -> 24.55
A10: 6 | B10: Communications | D10: =D41 -> 49760 | E10: =E41+E72+IFERROR($E$105/$D$105*D10,0) -> 654184.44 | F10: =IF(OR(D10=0,E10=0),"",ROUND(E10/D10,2)) -> 13.15
A11: 7 | B11: Computer and Information Sciences | D11: =D42 -> 254880 | E11: =E42+E73+IFERROR($E$105/$D$105*D11,0) -> 1597259.1 | F11: =IF(OR(D11=0,E11=0),"",ROUND(E11/D11,2)) -> 6.27
A12: 8 | B12: Construction Trades | D12: =D43 -> 0 | E12: =E43+E74+IFERROR($E$105/$D$105*D12,0) -> 0 | F12: =IF(OR(D12=0,E12=0),"",ROUND(E12/D12,2))
A13: 9 | B13: Consumer and Homemaking Education | D13: =D44 -> 284471 | E13: =E44+E75+IFERROR($E$105/$D$105*D13,0) -> 2687936.2 | F13: =IF(OR(D13=0,E13=0),"",ROUND(E13/D13,2)) -> 9.45
A14: 10 | B14: Engineering | D14: =D45 -> 31328 | E14: =E45+E76+IFERROR($E$105/$D$105*D14,0) -> 569119.42 | F14: =IF(OR(D14=0,E14=0),"",ROUND(E14/D14,2)) -> 18.17
A15: 11 | B15: Engineering Related | D15: =D46 -> 284950 | E15: =E46+E77+IFERROR($E$105/$D$105*D15,0) -> 2505698.8 | F15: =IF(OR(D15=0,E15=0),"",ROUND(E15/D15,2)) -> 8.79
A16: 12 | B16: English Language, Lit, Philosophy, Humanities, & Interdisciplinary | D16: =D47 -> 2830491 | E16: =E47+E78+IFERROR($E$105/$D$105*D16,0) -> 18061724 | F16: =IF(OR(D16=0,E16=0),"",ROUND(E16/D16,2)) -> 6.38
... A32: 29 | B32: Developmental Education - Reading/Writing | D32: =D63 -> 0 | E32: =E63+E94+IFERROR($E$105/$D$105*D32,0) -> 0 | F32: =IF(OR(D32=0,E32=0),"",ROUND(E32/D32,2))
C33: Total | D33: =SUM(D5:D32) -> 14785954 | E33: =SUM(E5:E32) -> 1.1017196e+08 | F33: =IF(OR(D33=0,E33=0),"",ROUND(E33/D33,2)) -> 7.45
A35: Fund | B35: Departmental Operating Expense by Discipline | D35: Contact Hours | E35: Expense | F35: Expense per Contact Hour
A36: 1 | B36: Agriculture | D36: =IF(F3="1",SUMIF(Data!A:A,$A$2,Data!CU:CU),0) -> 22080 | E36: =IF(F3="1",SUMIF(Data!$A:$A,$A$2,Data!IO:IO),0) -> 2068 | F36: =IF(OR(D36=0,E36=0),"",ROUND(E36/D36,2)) -> 0.09
A37: 2 | B37: Architecture and Precision Production Trades | D37: =IF(F3="1",SUMIF(Data!A:A,$A$2,Data!CV:CV),0) -> 177333 | E37: =IF(F3="1",SUMIF(Data!$A:$A,$A$2,Data!IP:IP),0) -> 106314 | F37: =IF(OR(D37=0,E37=0),"",ROUND(E37/D37,2)) -> 0.6
A38: 3 | B38: Biology, Physical Sciences, and Science Technology | D38: =IF(F3="1",SUMIF(Data!A:A,$A$2,Data!CW:CW),0) -> 1476192 | E38: =IF($F$3="1",SUMIF(Data!$A:$A,$A$2,Data!IQ:IQ),0) -> 731542 | F38: =IF(OR(D38=0,E38=0),"",ROUND(E38/D38,2)) -> 0.5
A39: 4 | B39: Business Management, Marketing, and Administrative Services | D39: =IF(F3="1",SUMIF(Data!A:A,$A$2,Data!CX:CX),0) -> 1411904 | E39: =IF($F$3="1",SUMIF(Data!$A:$A,$A$2,Data!IR:IR),0) -> 1482154 | F39: =IF(OR(D39=0,E39=0),"",ROUND(E39/D39,2)) -> 1.05
A40: 5 | B40: Career Pilot | D40: =IF(F3="1",SUMIF(Data!A:A,$A$2,Data!CY:CY),0) -> 14144 | E40: =IF($F$3="1",SUMIF(Data!$A:$A,$A$2,Data!IS:IS),0) -> 212915 | F40: =IF(OR(D40=0,E40=0),"",ROUND(E40/D40,2)) -> 15.05
A41: 6 | B41: Communications | D41: =IF(F3="1",SUMIF(Data!A:A,$A$2,Data!CZ:CZ),0) -> 49760 | E41: =IF($F$3="1",SUMIF(Data!$A:$A,$A$2,Data!IT:IT),0) -> 149324 | F41: =IF(OR(D41=0,E41=0),"",ROUND(E41/D41,2)) -> 3
A42: 7 | B42: Computer and Information Sciences | D42: =IF(F3="1",SUMIF(Data!A:A,$A$2,Data!DA:DA),0) -> 254880 | E42: =IF($F$3="1",SUMIF(Data!$A:$A,$A$2,Data!IU:IU),0) -> 215077 | F42: =IF(OR(D42=0,E42=0),"",ROUND(E42/D42,2)) -> 0.84
A43: 8 | B43: Construction Trades | D43: =IF(F3="1",SUMIF(Data!A:A,$A$2,Data!DB:DB),0) -> 0 | E43: =IF($F$3="1",SUMIF(Data!$A:$A,$A$2,Data!IV:IV),0) -> 0 | F43: =IF(OR(D43=0,E43=0),"",ROUND(E43/D43,2))
A44: 9 | B44: Consumer and Homemaking Education | D44: =IF(F3="1",SUMIF(Data!A:A,$A$2,Data!DC:DC),0) -> 284471 | E44: =IF($F$3="1",SUMIF(Data!$A:$A,$A$2,Data!IW:IW),0) -> 399941 | F44: =IF(OR(D44=0,E44=0),"",ROUND(E44/D44,2)) -> 1.41
A45: 10 | B45: Engineering | D45: =IF(F3="1",SUMIF(Data!A:A,$A$2,Data!DD:DD),0) -> 31328 | E45: =IF($F$3="1",SUMIF(Data!$A:$A,$A$2,Data!IX:IX),0) -> 320060 | F45: =IF(OR(D45=0,E45=0),"",ROUND(E45/D45,2)) -> 10.22
A46: 11 | B46: Engineering Related | D46: =IF(F3="1",SUMIF(Data!A:A,$A$2,Data!DE:DE),0) -> 284950 | E46: =IF($F$3="1",SUMIF(Data!$A:$A,$A$2,Data!IY:IY),0) -> 197391 | F46: =IF(OR(D46=0,E46=0),"",ROUND(E46/D46,2)) -> 0.69
A47: 12 | B47: English Language, Lit, Philosophy, Humanities, & Interdisciplinary | D47: =IF(F3="1",SUMIF(Data!A:A,$A$2,Data!DF:DF),0) -> 2830491 | E47: =IF($F$3="1",SUMIF(Data!$A:$A,$A$2,Data!IZ:IZ),0) -> 972106 | F47: =IF(OR(D47=0,E47=0),"",ROUND(E47/D47,2)) -> 0.34
A48: 13 | B48: Foreign Languages | D48: =IF(F3="1",SUMIF(Data!A:A,$A$2,Data!DG:DG),0) -> 461118 | E48: =IF($F$3="1",SUMIF(Data!$A:$A,$A$2,Data!JA:JA),0) -> 133442 | F48: =IF(OR(D48=0,E48=0),"",ROUND(E48/D48,2)) -> 0.29
A49: 14 | B49: Health Occupations - Dental Assistants, Medical Lab, and Assoc. Degree Nursing | D49: =IF(F3="1",SUMIF(Data!A:A,$A$2,Data!DH:DH),0) -> 336088 | E49: =IF($F$3="1",SUMIF(Data!$A:$A,$A$2,Data!JB:JB),0) -> 195690 | F49: =IF(OR(D49=0,E49=0),"",ROUND(E49/D49,2)) -> 0.58
A50: 15 | B50: Health Occupations - Dental Hygiene | D50: =IF(F3="1",SUMIF(Data!A:A,$A$2,Data!DI:DI),0) -> 0 | E50: =IF($F$3="1",SUMIF(Data!$A:$A,$A$2,Data!JC:JC),0) -> 0 | F50: =IF(OR(D50=0,E50=0),"",ROUND(E50/D50,2))
A51: 16 | B51: Health Occupations - Other | D51: =IF(F3="1",SUMIF(Data!A:A,$A$2,Data!DJ:DJ),0) -> 554059 | E51: =IF($F$3="1",SUMIF(Data!$A:$A,$A$2,Data!JD:JD),0) -> 213060 | F51: =IF(OR(D51=0,E51=0),"",ROUND(E51/D51,2)) -> 0.38
A52: 17 | B52: Health Occupations - Respiratory Therapy | D52: =IF(F3="1",SUMIF(Data!A:A,$A$2,Data!DK:DK),0) -> 44832 | E52: =IF($F$3="1",SUMIF(Data!$A:$A,$A$2,Data!JE:JE),0) -> 12598 | F52: =IF(OR(D52=0,E52=0),"",ROUND(E52/D52,2)) -> 0.28
A53: 18 | B53: Health Occupations - Vocational Nursing | D53: =IF(F3="1",SUMIF(Data!A:A,$A$2,Data!DL:DL),0) -> 282023 | E53: =IF($F$3="1",SUMIF(Data!$A:$A,$A$2,Data!JF:JF),0) -> 143716 | F53: =IF(OR(D53=0,E53=0),"",ROUND(E53/D53,2)) -> 0.51
A54: 19 | B54: Mathematics | D54: =IF(F3="1",SUMIF(Data!A:A,$A$2,Data!DM:DM),0) -> 2235380 | E54: =IF($F$3="1",SUMIF(Data!$A:$A,$A$2,Data!JG:JG),0) -> 551230 | F54: =IF(OR(D54=0,E54=0),"",ROUND(E54/D54,2)) -> 0.25
A55: 20 | B55: Mechanics and Repairers - Automotive | D55: =IF(F3="1",SUMIF(Data!A:A,$A$2,Data!DN:DN),0) -> 203800 | E55: =IF($F$3="1",SUMIF(Data!$A:$A,$A$2,Data!JH:JH),0) -> 444592 | F55: =IF(OR(D55=0,E55=0),"",ROUND(E55/D55,2)) -> 2.18
A56: 21 | B56: Mechanics and Repairers - Diesel, Aviation Mechanics, and Transportation Workers | D56: =IF(F3="1",SUMIF(Data!A:A,$A$2,Data!DO:DO),0) -> 57984 | E56: =IF($F$3="1",SUMIF(Data!$A:$A,$A$2,Data!JI:JI),0) -> 35563 | F56: =IF(OR(D56=0,E56=0),"",ROUND(E56/D56,2)) -> 0.61
A57: 22 | B57: Mechanics and Repairers - Electronics | D57: =IF(F3="1",SUMIF(Data!A:A,$A$2,Data!DP:DP),0) -> 199537 | E57: =IF($F$3="1",SUMIF(Data!$A:$A,$A$2,Data!JJ:JJ),0) -> 155886 | F57: =IF(OR(D57=0,E57=0),"",ROUND(E57/D57,2)) -> 0.78
A58: 23 | B58: Physical Education and Fitness | D58: =IF(F3="1",SUMIF(Data!A:A,$A$2,Data!DQ:DQ),0) -> 339792 | E58: =IF($F$3="1",SUMIF(Data!$A:$A,$A$2,Data!JK:JK),0) -> 134806 | F58: =IF(OR(D58=0,E58=0),"",ROUND(E58/D58,2)) -> 0.4
A59: 24 | B59: Protective Services and Public Administration | D59: =IF(F3="1",SUMIF(Data!A:A,$A$2,Data!DR:DR),0) -> 347296 | E59: =IF($F$3="1",SUMIF(Data!$A:$A,$A$2,Data!JL:JL),0) -> 79738 | F59: =IF(OR(D59=0,E59=0),"",ROUND(E59/D59,2)) -> 0.23
A60: 25 | B60: Psychology, Social Sciences, and History | D60: =IF(F3="1",SUMIF(Data!A:A,$A$2,Data!DS:DS),0) -> 2280640 | E60: =IF($F$3="1",SUMIF(Data!$A:$A,$A$2,Data!JM:JM),0) -> 662866 | F60: =IF(OR(D60=0,E60=0),"",ROUND(E60/D60,2)) -> 0.29
A61: 26 | B61: Visual and Performing Arts | D61: =IF(F3="1",SUMIF(Data!A:A,$A$2,Data!DT:DT),0) -> 605872 | E61: =IF($F$3="1",SUMIF(Data!$A:$A,$A$2,Data!JN:JN),0) -> 571539 | F61: =IF(OR(D61=0,E61=0),"",ROUND(E61/D61,2)) -> 0.94
A62: 28 | B62: Developmental Education - Math | D62: =IF(F3="1",SUMIF(Data!A:A,$A$2,Data!DV:DV),0) -> 0 | E62: =IF($F$3="1",SUMIF(Data!$A:$A,$A$2,Data!JP:JP),0) -> 0 | F62: =IF(OR(D62=0,E62=0),"",ROUND(E62/D62,2))
A63: 29 | B63: Developmental Education - Reading/Writing | D63: =IF(F3="1",SUMIF(Data!A:A,$A$2,Data!DW:DW),0) -> 0 | E63: =IF($F$3="1",SUMIF(Data!$A:$A,$A$2,Data!JQ:JQ),0) -> 0 | F63: =IF(OR(D63=0,E63=0),"",ROUND(E63/D63,2))
C64: Total | D64: =SUM(D36:D63) -> 14785954 | E64: =SUM(E36:E63) -> 8123618 | F64: =IF(OR(D64=0,E64=0),"",ROUND(E64/D64,2)) -> 0.55
A66: Fund | B66: Faculty Salaries by Discipline | D66: Contact Hours | E66: Expense | F66: Expense per Contact Hour
A67: 1 | B67: Agriculture | D67: =D36 -> 22080 | E67: =IF(F3="1",SUMIF(Data!A:A,$A$2,Data!DY:DY),0) -> 57648 | F67: =IF(OR(D67=0,E67=0),"",ROUND(E67/D67,2)) -> 2.61
A68: 2 | B68: Architecture and Precision Production Trades | D68: =D37 -> 177333 | E68: =IF(F3="1",SUMIF(Data!A:A,$A$2,Data!DZ:DZ),0) -> 831553 | F68: =IF(OR(D68=0,E68=0),"",ROUND(E68/D68,2)) -> 4.69
A69: 3 | B69: Biology, Physical Sciences, and Science Technology | D69: =D38 -> 1476192 | E69: =IF(F3="1",SUMIF(Data!A:A,$A$2,Data!EA:EA),0) -> 4441668 | F69: =IF(OR(D69=0,E69=0),"",ROUND(E69/D69,2)) -> 3.01
A70: 4 | B70: Business Management, Marketing, and Administrative Services | D70: =D39 -> 1411904 | E70: =IF(F3="1",SUMIF(Data!A:A,$A$2,Data!EB:EB),0) -> 5819034 | F70: =IF(OR(D70=0,E70=0),"",ROUND(E70/D70,2)) -> 4.12
A71: 5 | B71: Career Pilot | D71: =D40 -> 14144 | E71: =IF(F3="1",SUMIF(Data!A:A,$A$2,Data!EC:EC),0) -> 82866 | F71: =IF(OR(D71=0,E71=0),"",ROUND(E71/D71,2)) -> 5.86
A72: 6 | B72: Communications | D72: =D41 -> 49760 | E72: =IF(F3="1",SUMIF(Data!A:A,$A$2,Data!ED:ED),0) -> 323630 | F72: =IF(OR(D72=0,E72=0),"",ROUND(E72/D72,2)) -> 6.5
A73: 7 | B73: Computer and Information Sciences | D73: =D42 -> 254880 | E73: =IF(F3="1",SUMIF(Data!A:A,$A$2,Data!EE:EE),0) -> 453886 | F73: =IF(OR(D73=0,E73=0),"",ROUND(E73/D73,2)) -> 1.78
A74: 8 | B74: Construction Trades | D74: =D43 -> 0 | E74: =IF(F3="1",SUMIF(Data!A:A,$A$2,Data!EF:EF),0) -> 0 | F74: =IF(OR(D74=0,E74=0),"",ROUND(E74/D74,2))
A75: 9 | B75: Consumer and Homemaking Education | D75: =D44 -> 284471 | E75: =IF(F3="1",SUMIF(Data!A:A,$A$2,Data!EG:EG),0) -> 1251926 | F75: =IF(OR(D75=0,E75=0),"",ROUND(E75/D75,2)) -> 4.4
A76: 10 | B76: Engineering | D76: =D45 -> 31328 | E76: =IF(F3="1",SUMIF(Data!A:A,$A$2,Data!EH:EH),0) -> 134960 | F76: =IF(OR(D76=0,E76=0),"",ROUND(E76/D76,2)) -> 4.31
A77: 11 | B77: Engineering Related | D77: =D46 -> 284950 | E77: =IF(F3="1",SUMIF(Data!A:A,$A$2,Data!EI:EI),0) -> 1270494 | F77: =IF(OR(D77=0,E77=0),"",ROUND(E77/D77,2)) -> 4.46
A78: 12 | B78: English Language, Lit, Philosophy, Humanities, & Interdisciplinary | D78: =D47 -> 2830491 | E78: =IF(F3="1",SUMIF(Data!A:A,$A$2,Data!EJ:EJ),0) -> 6780712 | F78: =IF(OR(D78=0,E78=0),"",ROUND(E78/D78,2)) -> 2.4
A79: 13 | B79: Foreign Languages | D79: =D48 -> 461118 | E79: =IF(F3="1",SUMIF(Data!A:A,$A$2,Data!EK:EK),0) -> 1330336 | F79: =IF(OR(D79=0,E79=0),"",ROUND(E79/D79,2)) -> 2.89
A80: 14 | B80: Health Occupations - Dental Assistants, Medical Lab, and Assoc. Degree Nursing | D80: =D49 -> 336088 | E80: =IF(F3="1",SUMIF(Data!A:A,$A$2,Data!EL:EL),0) -> 2489873 | F80: =IF(OR(D80=0,E80=0),"",ROUND(E80/D80,2)) -> 7.41
A81: 15 | B81: Health Occupations - Dental Hygiene | D81: =D50 -> 0 | E81: =IF(F3="1",SUMIF(Data!A:A,$A$2,Data!EM:EM),0) -> 0 | F81: =IF(OR(D81=0,E81=0),"",ROUND(E81/D81,2))
A82: 16 | B82: Health Occupations - Other | D82: =D51 -> 554059 | E82: =IF(F3="1",SUMIF(Data!A:A,$A$2,Data!EN:EN),0) -> 1531477 | F82: =IF(OR(D82=0,E82=0),"",ROUND(E82/D82,2)) -> 2.76
A83: 17 | B83: Health Occupations - Respiratory Therapy | D83: =D52 -> 44832 | E83: =IF(F3="1",SUMIF(Data!A:A,$A$2,Data!EO:EO),0) -> 280352 | F83: =IF(OR(D83=0,E83=0),"",ROUND(E83/D83,2)) -> 6.25
A84: 18 | B84: Health Occupations - Vocational Nursing | D84: =D53 -> 282023 | E84: =IF(F3="1",SUMIF(Data!A:A,$A$2,Data!EP:EP),0) -> 1059371 | F84: =IF(OR(D84=0,E84=0),"",ROUND(E84/D84,2)) -> 3.76
A85: 19 | B85: Mathematics | D85: =D54 -> 2235380 | E85: =IF(F3="1",SUMIF(Data!A:A,$A$2,Data!EQ:EQ),0) -> 5791195 | F85: =IF(OR(D85=0,E85=0),"",ROUND(E85/D85,2)) -> 2.59
A86: 20 | B86: Mechanics and Repairers - Automotive | D86: =D55 -> 203800 | E86: =IF(F3="1",SUMIF(Data!A:A,$A$2,Data!ER:ER),0) -> 650333 | F86: =IF(OR(D86=0,E86=0),"",ROUND(E86/D86,2)) -> 3.19
A87: 21 | B87: Mechanics and Repairers - Diesel, Aviation Mechanics, and Transportation Workers | D87: =D56 -> 57984 | E87: =IF(F3="1",SUMIF(Data!A:A,$A$2,Data!ES:ES),0) -> 266580 | F87: =IF(OR(D87=0,E87=0),"",ROUND(E87/D87,2)) -> 4.6
A88: 22 | B88: Mechanics and Repairers - Electronics | D88: =D57 -> 199537 | E88: =IF(F3="1",SUMIF(Data!A:A,$A$2,Data!ET:ET),0) -> 559895 | F88: =IF(OR(D88=0,E88=0),"",ROUND(E88/D88,2)) -> 2.81
A89: 23 | B89: Physical Education and Fitness | D89: =D58 -> 339792 | E89: =IF(F3="1",SUMIF(Data!A:A,$A$2,Data!EU:EU),0) -> 1222981 | F89: =IF(OR(D89=0,E89=0),"",ROUND(E89/D89,2)) -> 3.6
A90: 24 | B90: Protective Services and Public Administration | D90: =D59 -> 347296 | E90: =IF(F3="1",SUMIF(Data!A:A,$A$2,Data!EV:EV),0) -> 754461 | F90: =IF(OR(D90=0,E90=0),"",ROUND(E90/D90,2)) -> 2.17
A91: 25 | B91: Psychology, Social Sciences, and History | D91: =D60 -> 2280640 | E91: =IF(F3="1",SUMIF(Data!A:A,$A$2,Data!EW:EW),0) -> 7992617 | F91: =IF(OR(D91=0,E91=0),"",ROUND(E91/D91,2)) -> 3.5
A92: 26 | B92: Visual and Performing Arts | D92: =D61 -> 605872 | E92: =IF(F3="1",SUMIF(Data!A:A,$A$2,Data!EX:EX),0) -> 2818705 | F92: =IF(OR(D92=0,E92=0),"",ROUND(E92/D92,2)) -> 4.65
A93: 28 | B93: Developmental Education - Math | D93: =D62 -> 0 | E93: =IF(F3="1",SUMIF(Data!A:A,$A$2,Data!EZ:EZ),0) -> 0 | F93: =IF(OR(D93=0,E93=0),"",ROUND(E93/D93,2))
A94: 29 | B94: Developmental Education - Reading/Writing | D94: =D63 -> 0 | E94: =IF(F3="1",SUMIF(Data!A:A,$A$2,Data!FA:FA),0) -> 0 | F94: =IF(OR(D94=0,E94=0),"",ROUND(E94/D94,2))
C95: Total | D95: =SUM(D67:D94) -> 14785954 | E95: =SUM(E67:E94) -> 48196553 | F95: =IF(OR(D95=0,E95=0),"",ROUND(E95/D95,2)) -> 3.26
B97: Allocated Administrative Expense | D97: Contact Hours | E97: Expense | F97: Expense per Contact Hour
B98: Institutional Support | E98: =IF(F3="1",SUMIF(Data!A:A,$A$2,Data!AH:AH),0) -> 18997448 | F98: =IF(OR(E98=0,E98=0),"",ROUND(E98/$D$105,2)) -> 1.28
B99: Student Services | E99: =IF(F3="1",SUMIF(Data!A:A,$A$2,Data!AI:AI),0) -> 11184014 | F99: =IF(OR(E99=0,E99=0),"",ROUND(E99/$D$105,2)) -> 0.76
B100: Library | E100: =IF(F3="1",SUMIF(Data!A:A,$A$2,Data!AJ:AJ),0) -> 4620192 | F100: =IF(OR(E100=0,E100=0),"",ROUND(E100/$D$105,2)) -> 0.31
B101: Instructional Administration | E101: =IF(F3="1",SUMIF(Data!A:A,$A$2,Data!AK:AK),0) -> 7702348 | F101: =IF(OR(E101=0,E101=0),"",ROUND(E101/$D$105,2)) -> 0.52
B102: Organized Activities | E102: =IF(F3="1",SUMIF(Data!A:A,$A$2,Data!AL:AL),0) -> 163560 | F102: =IF(OR(E102=0,E102=0),"",ROUND(E102/$D$105,2)) -> 0.01
B103: Equipment Depreciation | E103: =IF(F3="1",SUMIF(Data!A:A,$A$2,Data!AM:AM),0) -> 1e-06 | F103: =IF(OR(E103=0,E103=0),"",ROUND(E103/$D$105,2)) -> 0
B104: Local Benefits | E104: =IF(F3="1",SUMIF(Data!A:A,$A$2,Data!Q:Q),0) -> 11184227 | F104: =IF(OR(E104=0,E104=0),"",ROUND(E104/$D$105,2)) -> 0.76
C105: Total | D105: =D95 -> 14785954 | E105: =SUM(E98:E104) -> 53851789 | F105: =IF($D$105=0,"",ROUND(E105/$D$105,2)) -> 3.64
B107: Annual Financial Report - Schedule B
B108: Unrestricted - Educational Activities | C108: Salaries and Wages | D108: Local Benefits | E108: Other Expenses | F108: Total
B109: Instruction | C109: =E95+IF(F3="1",SUMIF(Data!$A:$A,$A$2,Data!GF:GF),0) -> 48196553 | D109: =IF(F3="1",SUMIF(Data!$A:$A,$A$2,Data!HJ:HJ),0) -> 0 | E109: =IF(F3="1",SUMIF(Data!$A:$A,$A$2,Data!IN:IN),0) -> 0 | F109: =SUM(C109:E109) -> 48196553
B110: Research | C110: =IF(F3="1",SUMIF(Data!A:A,$A$2,Data!W:W),0) -> 0 | E110: =IF(F3="1",SUMIF(Data!A:A,$A$2,Data!W:W),0) -> 0 | F110: =SUM(C110:E110) -> 0
B111: Public Service | C111: =IF(F3="1",SUMIF(Data!A:A,$A$2,Data!AS:AS),0) -> 0 | E111: =IF(F3="1",SUMIF(Data!A:A,$A$2,Data!AX:AX),0) -> 0 | F111: =SUM(C111:E111) -> 0
B112: Academic Support | C112: =IF(F3="1",SUMIF(Data!A:A,$A$2,Data!V:V),0) -> 0 | E112: =IF(F3="1",SUMIF(Data!A:A,$A$2,Data!AC:AC),0) -> 0 | F112: =SUM(C112:E112) -> 0
B113: Student Services | C113: =IF(F3="1",SUMIF(Data!A:A,$A$2,Data!U:U),0) -> 0 | E113: =IF(F3="1",SUMIF(Data!A:A,$A$2,Data!AB:AB),0) -> 0 | F113: =SUM(C113:E113) -> 0
B114: Instructional Support | C114: =IF(F3="1",SUMIF(Data!A:A,$A$2,Data!T:T),0) -> 0 | E114: =IF(F3="1",SUMIF(Data!A:A,$A$2,Data!AA:AA),0) -> 0 | F114: =SUM(C114:E114) -> 0
B115: Operation and Maintenance of Plant | C115: =IF(F3="1",SUMIF(Data!A:A,$A$2,Data!BI:BI),0) -> 0 | D115: =IF(F3="1",SUMIF(Data!A:A,$A$2,Data!BL:BL),0) -> 0 | E115: =IF(F3="1",SUMIF(Data!A:A,$A$2,Data!BU:BU),0) -> 0 | F115: =SUM(C115:E115) -> 0
B116: Scholarships and Fellowships | C116: =IF(F3="1",SUMIF(Data!A:A,$A$2,Data!X:X),0) -> 0 | E116: =E102 -> 163560 | F116: =SUM(C116:E116) -> 163560
B117: Other | D117: =IF(F3="1",SUMIF(Data!A:A,$A$2,Data!Q:Q),0) -> 11184227 | F117: =SUM(C117:E117) -> 11184227
B118: Total | C118: =SUM(C109:C116) -> 48196553 | D118: =SUM(D109:D116) -> 0 | E118: =SUM(E109:E116) -> 163560 | F118: =SUM(F109:F116) -> 48360113
B120: Depreciation Expense - Equipment | E120: =IF(F3="1",SUMIF(Data!A:A,$A$2,Data!AM:AM),0) -> 1e-06 | F120: =SUM(C120:E120) -> 1e-06
...

Sheet 2
A1: =Summary!A1 -> Community and Technical Colleges, Report of Fundable Operating Expenses, Fiscal Year (FY) 1999
A2: 003539 | B2: =VLOOKUP(A2,Data!A:G,7,0) -> Alvin Community College
F3: =IFERROR(VLOOKUP(A2,Data!A:C,3,0),"0") -> 1
A4: Fund | B4: Total Expense by Discipline | D4: Contact Hours | E4: Expense | F4: Expense per Contact Hour
A5: 1 | B5: Agriculture | D5: =D36 -> 28654 | E5: =E36+E67+IFERROR($E$105/$D$105*D5,0) -> 141037.41 | F5: =IF(OR(D5=0,E5=0),"",ROUND(E5/D5,2)) -> 4.92
A6: 2 | B6: Architecture and Precision Production Trades | D6: =D37 -> 80960 | E6: =E37+E68+IFERROR($E$105/$D$105*D6,0) -> 432074.34 | F6: =IF(OR(D6=0,E6=0),"",ROUND(E6/D6,2)) -> 5.34
A7: 3 | B7: Biology, Physical Sciences, and Science Technology | D7: =D38 -> 166976 | E7: =E38+E69+IFERROR($E$105/$D$105*D7,0) -> 1004595.5 | F7: =IF(OR(D7=0,E7=0),"",ROUND(E7/D7,2)) -> 6.02
A8: 4 | B8: Business Management, Marketing, and Administrative Services | D8: =D39 -> 224218 | E8: =E39+E70+IFERROR($E$105/$D$105*D8,0) -> 1374681.3 | F8: =IF(OR(D8=0,E8=0),"",ROUND(E8/D8,2)) -> 6.13
A9: 5 | B9: Career Pilot | D9: =D40 -> 0 | E9: =E40+E71+IFERROR($E$105/$D$105*D9,0) -> 0 | F9: =IF(OR(D9=0,E9=0),"",ROUND(E9/D9,2))
A10: 6 | B10: Communications | D10: =D41 -> 61872 | E10: =E41+E72+IFERROR($E$105/$D$105*D10,0) -> 317822.63 | F10: =IF(OR(D10=0,E10=0),"",ROUND(E10/D10,2)) -> 5.14
A11: 7 | B11: Computer and Information Sciences | D11: =D42 -> 190157 | E11: =E42+E73+IFERROR($E$105/$D$105*D11,0) -> 1037608.9 | F11: =IF(OR(D11=0,E11=0),"",ROUND(E11/D11,2)) -> 5.46
A12: 8 | B12: Construction Trades | D12: =D43 -> 0 | E12: =E43+E74+IFERROR($E$105/$D$105*D12,0) -> 0 | F12: =IF(OR(D12=0,E12=0),"",ROUND(E12/D12,2))
A13: 9 | B13: Consumer and Homemaking Education | D13: =D44 -> 34024 | E13: =E44+E75+IFERROR($E$105/$D$105*D13,0) -> 239915.62 | F13: =IF(OR(D13=0,E13=0),"",ROUND(E13/D13,2)) -> 7.05
A14: 10 | B14: Engineering | D14: =D45 -> 0 | E14: =E45+E76+IFERROR($E$105/$D$105*D14,0) -> 0 | F14: =IF(OR(D14=0,E14=0),"",ROUND(E14/D14,2))
A15: 11 | B15: Engineering Related | D15: =D46 -> 38820 | E15: =E46+E77+IFERROR($E$105/$D$105*D15,0) -> 169167.99 | F15: =IF(OR(D15=0,E15=0),"",ROUND(E15/D15,2)) -> 4.36
A16: 12 | B16: English Language, Lit, Philosophy, Humanities, & Interdisciplinary | D16: =D47 -> 342352 | E16: =E47+E78+IFERROR($E$105/$D$105*D16,0) -> 1676621.4 | F16: =IF(OR(D16=0,E16=0),"",ROUND(E16/D16,2)) -> 4.9
... A32: 29 | B32: Developmental Education - Reading/Writing | D32: =D63 -> 0 | E32: =E63+E94+IFERROR($E$105/$D$105*D32,0) -> 0 | F32: =IF(OR(D32=0,E32=0),"",ROUND(E32/D32,2))
B33: Total | D33: =SUM(D5:D32) -> 2038151 | E33: =SUM(E5:E32) -> 12071182 | F33: =IF(OR(D33=0,E33=0),"",ROUND(E33/D33,2)) -> 5.92
A35: Fund | B35: Departmental Operating Expense by Discipline | D35: Contact Hours | E35: Expense | F35: Expense per Contact Hour
A36: 1 | B36: Agriculture | D36: =IF(F3="1",SUMIF(Data!A:A,'2'!$A$2,Data!CU:CU),0) -> 28654 | E36: =IF(F3="1",SUMIF(Data!$A:$A,$A$2,Data!IO:IO),0) -> 13379 | F36: =IF(OR(D36=0,E36=0),"",ROUND(E36/D36,2)) -> 0.47
A37: 2 | B37: Architecture and Precision Production Trades | D37: =IF(F3="1",SUMIF(Data!A:A,'2'!$A$2,Data!CV:CV),0) -> 80960 | E37: =IF(F3="1",SUMIF(Data!$A:$A,$A$2,Data!IP:IP),0) -> 46179 | F37: =IF(OR(D37=0,E37=0),"",ROUND(E37/D37,2)) -> 0.57
A38: 3 | B38: Biology, Physical Sciences, and Science Technology | D38: =IF(F3="1",SUMIF(Data!A:A,'2'!$A$2,Data!CW:CW),0) -> 166976 | E38: =IF($F$3="1",SUMIF(Data!$A:$A,$A$2,Data!IQ:IQ),0) -> 78330 | F38: =IF(OR(D38=0,E38=0),"",ROUND(E38/D38,2)) -> 0.47
A39: 4 | B39: Business Management, Marketing, and Administrative Services | D39: =IF(F3="1",SUMIF(Data!A:A,'2'!$A$2,Data!CX:CX),0) -> 224218 | E39: =IF($F$3="1",SUMIF(Data!$A:$A,$A$2,Data!IR:IR),0) -> 98780 | F39: =IF(OR(D39=0,E39=0),"",ROUND(E39/D39,2)) -> 0.44
A40: 5 | B40: Career Pilot | D40: =IF(F3="1",SUMIF(Data!A:A,'2'!$A$2,Data!CY:CY),0) -> 0 | E40: =IF($F$3="1",SUMIF(Data!$A:$A,$A$2,Data!IS:IS),0) -> 0 | F40: =IF(OR(D40=0,E40=0),"",ROUND(E40/D40,2))
A41: 6 | B41: Communications | D41: =IF(F3="1",SUMIF(Data!A:A,'2'!$A$2,Data!CZ:CZ),0) -> 61872 | E41: =IF($F$3="1",SUMIF(Data!$A:$A,$A$2,Data!IT:IT),0) -> 37386 | F41: =IF(OR(D41=0,E41=0),"",ROUND(E41/D41,2)) -> 0.6
A42: 7 | B42: Computer and Information Sciences | D42: =IF(F3="1",SUMIF(Data!A:A,'2'!$A$2,Data!DA:DA),0) -> 190157 | E42: =IF($F$3="1",SUMIF(Data!$A:$A,$A$2,Data!IU:IU),0) -> 126199 | F42: =IF(OR(D42=0,E42=0),"",ROUND(E42/D42,2)) -> 0.66
A43: 8 | B43: Construction Trades | D43: =IF(F3="1",SUMIF(Data!A:A,'2'!$A$2,Data!DB:DB),0) -> 0 | E43: =IF($F$3="1",SUMIF(Data!$A:$A,$A$2,Data!IV:IV),0) -> 0 | F43: =IF(OR(D43=0,E43=0),"",ROUND(E43/D43,2))
A44: 9 | B44: Consumer and Homemaking Education | D44: =IF(F3="1",SUMIF(Data!A:A,'2'!$A$2,Data!DC:DC),0) -> 34024 | E44: =IF($F$3="1",SUMIF(Data!$A:$A,$A$2,Data!IW:IW),0) -> 44834 | F44: =IF(OR(D44=0,E44=0),"",ROUND(E44/D44,2)) -> 1.32
A45: 10 | B45: Engineering | D45: =IF(F3="1",SUMIF(Data!A:A,'2'!$A$2,Data!DD:DD),0) -> 0 | E45: =IF($F$3="1",SUMIF(Data!$A:$A,$A$2,Data!IX:IX),0) -> 0 | F45: =IF(OR(D45=0,E45=0),"",ROUND(E45/D45,2))
A46: 11 | B46: Engineering Related | D46: =IF(F3="1",SUMIF(Data!A:A,'2'!$A$2,Data!DE:DE),0) -> 38820 | E46: =IF($F$3="1",SUMIF(Data!$A:$A,$A$2,Data!IY:IY),0) -> 31405 | F46: =IF(OR(D46=0,E46=0),"",ROUND(E46/D46,2)) -> 0.81
A47: 12 | B47: English Language, Lit, Philosophy, Humanities, & Interdisciplinary | D47: =IF(F3="1",SUMIF(Data!A:A,'2'!$A$2,Data!DF:DF),0) -> 342352 | E47: =IF($F$3="1",SUMIF(Data!$A:$A,$A$2,Data!IZ:IZ),0) -> 77722 | F47: =IF(OR(D47=0,E47=0),"",ROUND(E47/D47,2)) -> 0.23
A48: 13 | B48: Foreign Languages | D48: =IF(F3="1",SUMIF(Data!A:A,'2'!$A$2,Data!DG:DG),0) -> 19792 | E48: =IF($F$3="1",SUMIF(Data!$A:$A,$A$2,Data!JA:JA),0) -> 7307 | F48: =IF(OR(D48=0,E48=0),"",ROUND(E48/D48,2)) -> 0.37
A49: 14 | B49: Health Occupations - Dental Assistants, Medical Lab, and Assoc. Degree Nursing | D49: =IF(F3="1",SUMIF(Data!A:A,'2'!$A$2,Data!DH:DH),0) -> 99463 | E49: =IF($F$3="1",SUMIF(Data!$A:$A,$A$2,Data!JB:JB),0) -> 136663 | F49: =IF(OR(D49=0,E49=0),"",ROUND(E49/D49,2)) -> 1.37
A50: 15 | B50: Health Occupations - Dental Hygiene | D50: =IF(F3="1",SUMIF(Data!A:A,'2'!$A$2,Data!DI:DI),0) -> 0 | E50: =IF($F$3="1",SUMIF(Data!$A:$A,$A$2,Data!JC:JC),0) -> 0 | F50: =IF(OR(D50=0,E50=0),"",ROUND(E50/D50,2))
A51: 16 | B51: Health Occupations - Other | D51: =IF(F3="1",SUMIF(Data!A:A,'2'!$A$2,Data!DJ:DJ),0) -> 63863 | E51: =IF($F$3="1",SUMIF(Data!$A:$A,$A$2,Data!JD:JD),0) -> 46850 | F51: =IF(OR(D51=0,E51=0),"",ROUND(E51/D51,2)) -> 0.73
A52: 17 | B52: Health Occupations - Respiratory Therapy | D52: =IF(F3="1",SUMIF(Data!A:A,'2'!$A$2,Data!DK:DK),0) -> 16656 | E52: =IF($F$3="1",SUMIF(Data!$A:$A,$A$2,Data!JE:JE),0) -> 17419 | F52: =IF(OR(D52=0,E52=0),"",ROUND(E52/D52,2)) -> 1.05
A53: 18 | B53: Health Occupations - Vocational Nursing | D53: =IF(F3="1",SUMIF(Data!A:A,'2'!$A$2,Data!DL:DL),0) -> 12311 | E53: =IF($F$3="1",SUMIF(Data!$A:$A,$A$2,Data!JF:JF),0) -> 9264 | F53: =IF(OR(D53=0,E53=0),"",ROUND(E53/D53,2)) -> 0.75
A54: 19 | B54: Mathematics | D54: =IF(F3="1",SUMIF(Data!A:A,'2'!$A$2,Data!DM:DM),0) -> 73654 | E54: =IF($F$3="1",SUMIF(Data!$A:$A,$A$2,Data!JG:JG),0) -> 23059 | F54: =IF(OR(D54=0,E54=0),"",ROUND(E54/D54,2)) -> 0.31
A55: 20 | B55: Mechanics and Repairers - Automotive | D55: =IF(F3="1",SUMIF(Data!A:A,'2'!$A$2,Data!DN:DN),0) -> 40517 | E55: =IF($F$3="1",SUMIF(Data!$A:$A,$A$2,Data!JH:JH),0) -> 11062 | F55: =IF(OR(D55=0,E55=0),"",ROUND(E55/D55,2)) -> 0.27
A56: 21 | B56: Mechanics and Repairers - Diesel, Aviation Mechanics, and Transportation Workers | D56: =IF(F3="1",SUMIF(Data!A:A,'2'!$A$2,Data!DO:DO),0) -> 0 | E56: =IF($F$3="1",SUMIF(Data!$A:$A,$A$2,Data!JI:JI),0) -> 0 | F56: =IF(OR(D56=0,E56=0),"",ROUND(E56/D56,2))
A57: 22 | B57: Mechanics and Repairers - Electronics | D57: =IF(F3="1",SUMIF(Data!A:A,'2'!$A$2,Data!DP:DP),0) -> 0 | E57: =IF($F$3="1",SUMIF(Data!$A:$A,$A$2,Data!JJ:JJ),0) -> 0 | F57: =IF(OR(D57=0,E57=0),"",ROUND(E57/D57,2))
A58: 23 | B58: Physical Education and Fitness | D58: =IF(F3="1",SUMIF(Data!A:A,'2'!$A$2,Data!DQ:DQ),0) -> 64128 | E58: =IF($F$3="1",SUMIF(Data!$A:$A,$A$2,Data!JK:JK),0) -> 43425 | F58: =IF(OR(D58=0,E58=0),"",ROUND(E58/D58,2)) -> 0.68
A59: 24 | B59: Protective Services and Public Administration | D59: =IF(F3="1",SUMIF(Data!A:A,'2'!$A$2,Data!DR:DR),0) -> 118998 | E59: =IF($F$3="1",SUMIF(Data!$A:$A,$A$2,Data!JL:JL),0) -> 55832 | F59: =IF(OR(D59=0,E59=0),"",ROUND(E59/D59,2)) -> 0.47
A60: 25 | B60: Psychology, Social Sciences, and History | D60: =IF(F3="1",SUMIF(Data!A:A,'2'!$A$2,Data!DS:DS),0) -> 291984 | E60: =IF($F$3="1",SUMIF(Data!$A:$A,$A$2,Data!JM:JM),0) -> 60968 | F60: =IF(OR(D60=0,E60=0),"",ROUND(E60/D60,2)) -> 0.21
A61: 26 | B61: Visual and Performing Arts | D61: =IF(F3="1",SUMIF(Data!A:A,'2'!$A$2,Data!DT:DT),0) -> 68752 | E61: =IF($F$3="1",SUMIF(Data!$A:$A,$A$2,Data!JN:JN),0) -> 98015 | F61: =IF(OR(D61=0,E61=0),"",ROUND(E61/D61,2)) -> 1.43
A62: 28 | B62: Developmental Education - Math | D62: =IF(F3="1",SUMIF(Data!A:A,'2'!$A$2,Data!DV:DV),0) -> 0 | E62: =IF($F$3="1",SUMIF(Data!$A:$A,$A$2,Data!JP:JP),0) -> 0 | F62: =IF(OR(D62=0,E62=0),"",ROUND(E62/D62,2))
A63: 29 | B63: Developmental Education - Reading/Writing | D63: =IF(F3="1",SUMIF(Data!A:A,'2'!$A$2,Data!DW:DW),0) -> 0 | E63: =IF($F$3="1",SUMIF(Data!$A:$A,$A$2,Data!JQ:JQ),0) -> 0 | F63: =IF(OR(D63=0,E63=0),"",ROUND(E63/D63,2))
B64: Total | D64: =SUM(D36:D63) -> 2038151 | E64: =SUM(E36:E63) -> 1064078 | F64: =IF(OR(D64=0,E64=0),"",ROUND(E64/D64,2)) -> 0.52
A66: Fund | B66: Faculty Salaries by Discipline | D66: Contact Hours | E66: Expense | F66: Expense per Contact Hour
A67: 1 | B67: Agriculture | D67: =D36 -> 28654 | E67: =IF(F3="1",SUMIF(Data!A:A,'2'!$A$2,Data!DY:DY),0) -> 58178 | F67: =IF(OR(D67=0,E67=0),"",ROUND(E67/D67,2)) -> 2.03
A68: 2 | B68: Architecture and Precision Production Trades | D68: =D37 -> 80960 | E68: =IF(F3="1",SUMIF(Data!A:A,'2'!$A$2,Data!DZ:DZ),0) -> 189583 | F68: =IF(OR(D68=0,E68=0),"",ROUND(E68/D68,2)) -> 2.34
A69: 3 | B69: Biology, Physical Sciences, and Science Technology | D69: =D38 -> 166976 | E69: =IF(F3="1",SUMIF(Data!A:A,'2'!$A$2,Data!EA:EA),0) -> 521381 | F69: =IF(OR(D69=0,E69=0),"",ROUND(E69/D69,2)) -> 3.12
A70: 4 | B70: Business Management, Marketing, and Administrative Services | D70: =D39 -> 224218 | E70: =IF(F3="1",SUMIF(Data!A:A,'2'!$A$2,Data!EB:EB),0) -> 732216 | F70: =IF(OR(D70=0,E70=0),"",ROUND(E70/D70,2)) -> 3.27
A71: 5 | B71: Career Pilot | D71: =D40 -> 0 | E71: =IF(F3="1",SUMIF(Data!A:A,'2'!$A$2,Data!EC:EC),0) -> 0 | F71: =IF(OR(D71=0,E71=0),"",ROUND(E71/D71,2))
A72: 6 | B72: Communications | D72: =D41 -> 61872 | E72: =IF(F3="1",SUMIF(Data!A:A,'2'!$A$2,Data!ED:ED),0) -> 130409 | F72: =IF(OR(D72=0,E72=0),"",ROUND(E72/D72,2)) -> 2.11
A73: 7 | B73: Computer and Information Sciences | D73: =D42 -> 190157 | E73: =IF(F3="1",SUMIF(Data!A:A,'2'!$A$2,Data!EE:EE),0) -> 450316 | F73: =IF(OR(D73=0,E73=0),"",ROUND(E73/D73,2)) -> 2.37
A74: 8 | B74: Construction Trades | D74: =D43 -> 0 | E74: =IF(F3="1",SUMIF(Data!A:A,'2'!$A$2,Data!EF:EF),0) -> 0 | F74: =IF(OR(D74=0,E74=0),"",ROUND(E74/D74,2))
A75: 9 | B75: Consumer and Homemaking Education | D75: =D44 -> 34024 | E75: =IF(F3="1",SUMIF(Data!A:A,'2'!$A$2,Data!EG:EG),0) -> 112580 | F75: =IF(OR(D75=0,E75=0),"",ROUND(E75/D75,2)) -> 3.31
A76: 10 | B76: Engineering | D76: =D45 -> 0 | E76: =IF(F3="1",SUMIF(Data!A:A,'2'!$A$2,Data!EH:EH),0) -> 0 | F76: =IF(OR(D76=0,E76=0),"",ROUND(E76/D76,2))
A77: 11 | B77: Engineering Related | D77: =D46 -> 38820 | E77: =IF(F3="1",SUMIF(Data!A:A,'2'!$A$2,Data!EI:EI),0) -> 43632 | F77: =IF(OR(D77=0,E77=0),"",ROUND(E77/D77,2)) -> 1.12
A78: 12 | B78: English Language, Lit, Philosophy, Humanities, & Interdisciplinary | D78: =D47 -> 342352 | E78: =IF(F3="1",SUMIF(Data!A:A,'2'!$A$2,Data!EJ:EJ),0) -> 768762 | F78: =IF(OR(D78=0,E78=0),"",ROUND(E78/D78,2)) -> 2.25
A79: 13 | B79: Foreign Languages | D79: =D48 -> 19792 | E79: =IF(F3="1",SUMIF(Data!A:A,'2'!$A$2,Data!EK:EK),0) -> 56785 | F79: =IF(OR(D79=0,E79=0),"",ROUND(E79/D79,2)) -> 2.87
A80: 14 | B80: Health Occupations - Dental Assistants, Medical Lab, and Assoc. Degree Nursing | D80: =D49 -> 99463 | E80: =IF(F3="1",SUMIF(Data!A:A,'2'!$A$2,Data!EL:EL),0) -> 408155 | F80: =IF(OR(D80=0,E80=0),"",ROUND(E80/D80,2)) -> 4.1
A81: 15 | B81: Health Occupations - Dental Hygiene | D81: =D50 -> 0 | E81: =IF(F3="1",SUMIF(Data!A:A,'2'!$A$2,Data!EM:EM),0) -> 0 | F81: =IF(OR(D81=0,E81=0),"",ROUND(E81/D81,2))
A82: 16 | B82: Health Occupations - Other | D82: =D51 -> 63863 | E82: =IF(F3="1",SUMIF(Data!A:A,'2'!$A$2,Data!EN:EN),0) -> 283199 | F82: =IF(OR(D82=0,E82=0),"",ROUND(E82/D82,2)) -> 4.43
A83: 17 | B83: Health Occupations - Respiratory Therapy | D83: =D52 -> 16656 | E83: =IF(F3="1",SUMIF(Data!A:A,'2'!$A$2,Data!EO:EO),0) -> 153378 | F83: =IF(OR(D83=0,E83=0),"",ROUND(E83/D83,2)) -> 9.21
A84: 18 | B84: Health Occupations - Vocational Nursing | D84: =D53 -> 12311 | E84: =IF(F3="1",SUMIF(Data!A:A,'2'!$A$2,Data!EP:EP),0) -> 112841 | F84: =IF(OR(D84=0,E84=0),"",ROUND(E84/D84,2)) -> 9.17
A85: 19 | B85: Mathematics | D85: =D54 -> 73654 | E85: =IF(F3="1",SUMIF(Data!A:A,'2'!$A$2,Data!EQ:EQ),0) -> 479561 | F85: =IF(OR(D85=0,E85=0),"",ROUND(E85/D85,2)) -> 6.51
A86: 20 | B86: Mechanics and Repairers - Automotive | D86: =D55 -> 40517 | E86: =IF(F3="1",SUMIF(Data!A:A,'2'!$A$2,Data!ER:ER),0) -> 97568 | F86: =IF(OR(D86=0,E86=0),"",ROUND(E86/D86,2)) -> 2.41
A87: 21 | B87: Mechanics and Repairers - Diesel, Aviation Mechanics, and Transportation Workers | D87: =D56 -> 0 | E87: =IF(F3="1",SUMIF(Data!A:A,'2'!$A$2,Data!ES:ES),0) -> 0 | F87: =IF(OR(D87=0,E87=0),"",ROUND(E87/D87,2))
A88: 22 | B88: Mechanics and Repairers - Electronics | D88: =D57 -> 0 | E88: =IF(F3="1",SUMIF(Data!A:A,'2'!$A$2,Data!ET:ET),0) -> 0 | F88: =IF(OR(D88=0,E88=0),"",ROUND(E88/D88,2))
A89: 23 | B89: Physical Education and Fitness | D89: =D58 -> 64128 | E89: =IF(F3="1",SUMIF(Data!A:A,'2'!$A$2,Data!EU:EU),0) -> 280948 | F89: =IF(OR(D89=0,E89=0),"",ROUND(E89/D89,2)) -> 4.38
A90: 24 | B90: Protective Services and Public Administration | D90: =D59 -> 118998 | E90: =IF(F3="1",SUMIF(Data!A:A,'2'!$A$2,Data!EV:EV),0) -> 272010 | F90: =IF(OR(D90=0,E90=0),"",ROUND(E90/D90,2)) -> 2.29
A91: 25 | B91: Psychology, Social Sciences, and History | D91: =D60 -> 291984 | E91: =IF(F3="1",SUMIF(Data!A:A,'2'!$A$2,Data!EW:EW),0) -> 644026 | F91: =IF(OR(D91=0,E91=0),"",ROUND(E91/D91,2)) -> 2.21
A92: 26 | B92: Visual and Performing Arts | D92: =D61 -> 68752 | E92: =IF(F3="1",SUMIF(Data!A:A,'2'!$A$2,Data!EX:EX),0) -> 269454 | F92: =IF(OR(D92=0,E92=0),"",ROUND(E92/D92,2)) -> 3.92
A93: 28 | B93: Developmental Education - Math | D93: =D62 -> 0 | E93: =IF(F3="1",SUMIF(Data!A:A,'2'!$A$2,Data!EZ:EZ),0) -> 0 | F93: =IF(OR(D93=0,E93=0),"",ROUND(E93/D93,2))
A94: 29 | B94: Developmental Education - Reading/Writing | D94: =D63 -> 0 | E94: =IF(F3="1",SUMIF(Data!A:A,'2'!$A$2,Data!FA:FA),0) -> 0 | F94: =IF(OR(D94=0,E94=0),"",ROUND(E94/D94,2))
B95: Total | D95: =SUM(D67:D94) -> 2038151 | E95: =SUM(E67:E94) -> 6064982 | F95: =IF(OR(D95=0,E95=0),"",ROUND(E95/D95,2)) -> 2.98
B97: Allocated Administrative Expense | D97: Contact Hours | E97: Expense | F97: Expense per Contact Hour
B98: Institutional Support | E98: =IF(F3="1",SUMIF(Data!A:A,'2'!$A$2,Data!AH:AH),0) -> 1948504 | F98: =IF(OR(E98=0,E98=0),"",ROUND(E98/$D$105,2)) -> 0.96
B99: Student Services | E99: =IF(F3="1",SUMIF(Data!A:A,'2'!$A$2,Data!AI:AI),0) -> 1225919 | F99: =IF(OR(E99=0,E99=0),"",ROUND(E99/$D$105,2)) -> 0.6
B100: Library | E100: =IF(F3="1",SUMIF(Data!A:A,'2'!$A$2,Data!AJ:AJ),0) -> 532907 | F100: =IF(OR(E100=0,E100=0),"",ROUND(E100/$D$105,2)) -> 0.26
B101: Instructional Administration | E101: =IF(F3="1",SUMIF(Data!A:A,'2'!$A$2,Data!AK:AK),0) -> 703962 | F101: =IF(OR(E101=0,E101=0),"",ROUND(E101/$D$105,2)) -> 0.35
B102: Organized Activities | E102: =IF(F3="1",SUMIF(Data!A:A,'2'!$A$2,Data!AL:AL),0) -> 0 | F102: =IF(OR(E102=0,E102=0),"",ROUND(E102/$D$105,2))
B103: Equipment Depreciation | E103: =IF(F3="1",SUMIF(Data!A:A,'2'!$A$2,Data!AM:AM),0) -> 0 | F103: =IF(OR(E103=0,E103=0),"",ROUND(E103/$D$105,2))
B104: Local Benefits | E104: =IF(F3="1",SUMIF(Data!A:A,'2'!$A$2,Data!Q:Q),0) -> 530830 | F104: =IF(OR(E104=0,E104=0),"",ROUND(E104/$D$105,2)) -> 0.26
B105: Total | D105: =D95 -> 2038151 | E105: =SUM(E98:E104) -> 4942122 | F105: =IF($D$105=0,"",ROUND(E105/$D$105,2)) -> 2.42
B107: Annual Financial Report - Schedule B
B108: Unrestricted - Educational Activities | C108: Salaries and Wages | D108: Local Benefits | E108: Other Expenses | F108: Total
B109: Instruction | C109: =E95+IF(F3="1",SUMIF(Data!$A:$A,$A$2,Data!GF:GF),0) -> 6064982 | D109: =IF(F3="1",SUMIF(Data!$A:$A,$A$2,Data!HJ:HJ),0) -> 0 | E109: =IF(F3="1",SUMIF(Data!$A:$A,$A$2,Data!IN:IN),0) -> 0 | F109: =SUM(C109:E109) -> 6064982
B110: Research | C110: =IF(F3="1",SUMIF(Data!A:A,$A$2,Data!W:W),0) -> 0 | E110: =IF(F3="1",SUMIF(Data!A:A,$A$2,Data!W:W),0) -> 0 | F110: =SUM(C110:E110) -> 0
B111: Public Service | C111: =IF(F3="1",SUMIF(Data!A:A,$A$2,Data!AS:AS),0) -> 0 | E111: =IF(F3="1",SUMIF(Data!A:A,$A$2,Data!AX:AX),0) -> 0 | F111: =SUM(C111:E111) -> 0
B112: Academic Support | C112: =IF(F3="1",SUMIF(Data!A:A,$A$2,Data!V:V),0) -> 0 | E112: =IF(F3="1",SUMIF(Data!A:A,$A$2,Data!AC:AC),0) -> 0 | F112: =SUM(C112:E112) -> 0
B113: Student Services | C113: =IF(F3="1",SUMIF(Data!A:A,$A$2,Data!U:U),0) -> 0 | E113: =IF(F3="1",SUMIF(Data!A:A,$A$2,Data!AB:AB),0) -> 0 | F113: =SUM(C113:E113) -> 0
B114: Instructional Support | C114: =IF(F3="1",SUMIF(Data!A:A,$A$2,Data!T:T),0) -> 0 | E114: =IF(F3="1",SUMIF(Data!A:A,$A$2,Data!AA:AA),0) -> 0 | F114: =SUM(C114:E114) -> 0
B115: Operation and Maintenance of Plant | C115: =IF(F3="1",SUMIF(Data!A:A,$A$2,Data!BI:BI),0) -> 0 | D115: =IF(F3="1",SUMIF(Data!A:A,$A$2,Data!BL:BL),0) -> 0 | E115: =IF(F3="1",SUMIF(Data!A:A,$A$2,Data!BU:BU),0) -> 0 | F115: =SUM(C115:E115) -> 0
B116: Scholarships and Fellowships | C116: =IF(F3="1",SUMIF(Data!A:A,$A$2,Data!X:X),0) -> 0 | E116: =E102 -> 0 | F116: =SUM(C116:E116) -> 0
B117: Other | D117: =IF(F3="1",SUMIF(Data!A:A,$A$2,Data!Q:Q),0) -> 530830 | F117: =SUM(C117:E117) -> 530830
B118: Total | C118: =SUM(C109:C116) -> 6064982 | D118: =SUM(D109:D116) -> 0 | E118: =SUM(E109:E116) -> 0 | F118: =SUM(F109:F116) -> 6064982
B120: Depreciation Expense - Equipment | E120: =IF(F3="1",SUMIF(Data!A:A,'2'!$A$2,Data!AM:AM),0) -> 0 | F120: =SUM(C120:E120) -> 0
...

Sheet 3
A1: =Summary!A1 -> Community and Technical Colleges, Report of Fundable Operating Expenses, Fiscal Year (FY) 1999
A2: 003540 | B2: =VLOOKUP(A2,Data!A:G,7,0) -> Amarillo College
F3: =IFERROR(VLOOKUP(A2,Data!A:C,3,0),"0") -> 1
A4: Fund | B4: Total Expense by Discipline | D4: Contact Hours | E4: Expense | F4: Expense per Contact Hour
A5: 1 | B5: Agriculture | D5: =D36 -> 2552 | E5: =E36+E67+IFERROR($E$105/$D$105*D5,0) -> 28324.803 | F5: =IF(OR(D5=0,E5=0),"",ROUND(E5/D5,2)) -> 11.1
A6: 2 | B6: Architecture and Precision Production Trades | D6: =D37 -> 101057 | E6: =E37+E68+IFERROR($E$105/$D$105*D6,0) -> 777214.85 | F6: =IF(OR(D6=0,E6=0),"",ROUND(E6/D6,2)) -> 7.69
A7: 3 | B7: Biology, Physical Sciences, and Science Technology | D7: =D38 -> 337568 | E7: =E38+E69+IFERROR($E$105/$D$105*D7,0) -> 1853118.9 | F7: =IF(OR(D7=0,E7=0),"",ROUND(E7/D7,2)) -> 5.49
A8: 4 | B8: Business Management, Marketing, and Administrative Services | D8: =D39 -> 228606 | E8: =E39+E70+IFERROR($E$105/$D$105*D8,0) -> 1476074.4 | F8: =IF(OR(D8=0,E8=0),"",ROUND(E8/D8,2)) -> 6.46
A9: 5 | B9: Career Pilot | D9: =D40 -> 0 | E9: =E40+E71+IFERROR($E$105/$D$105*D9,0) -> 0 | F9: =IF(OR(D9=0,E9=0),"",ROUND(E9/D9,2))
A10: 6 | B10: Communications | D10: =D41 -> 30544 | E10: =E41+E72+IFERROR($E$105/$D$105*D10,0) -> 286964.8 | F10: =IF(OR(D10=0,E10=0),"",ROUND(E10/D10,2)) -> 9.4
A11: 7 | B11: Computer and Information Sciences | D11: =D42 -> 274523 | E11: =E42+E73+IFERROR($E$105/$D$105*D11,0) -> 1512032.3 | F11: =IF(OR(D11=0,E11=0),"",ROUND(E11/D11,2)) -> 5.51
A12: 8 | B12: Construction Trades | D12: =D43 -> 16521 | E12: =E43+E74+IFERROR($E$105/$D$105*D12,0) -> 71232.035 | F12: =IF(OR(D12=0,E12=0),"",ROUND(E12/D12,2)) -> 4.31
A13: 9 | B13: Consumer and Homemaking Education | D13: =D44 -> 110143 | E13: =E44+E75+IFERROR($E$105/$D$105*D13,0) -> 603366.48 | F13: =IF(OR(D13=0,E13=0),"",ROUND(E13/D13,2)) -> 5.48
A14: 10 | B14: Engineering | D14: =D45 -> 656 | E14: =E45+E76+IFERROR($E$105/$D$105*D14,0) -> 4776.2126 | F14: =IF(OR(D14=0,E14=0),"",ROUND(E14/D14,2)) -> 7.28
A15: 11 | B15: Engineering Related | D15: =D46 -> 144529 | E15: =E46+E77+IFERROR($E$105/$D$105*D15,0) -> 1152111.1 | F15: =IF(OR(D15=0,E15=0),"",ROUND(E15/D15,2)) -> 7.97
A16: 12 | B16: English Language, Lit, Philosophy, Humanities, & Interdisciplinary | D16: =D47 -> 580770 | E16: =E47+E78+IFERROR($E$105/$D$105*D16,0) -> 3378414.5 | F16: =IF(OR(D16=0,E16=0),"",ROUND(E16/D16,2)) -> 5.82
... A32: 29 | B32: Developmental Education - Reading/Writing | D32: =D63 -> 0 | E32: =E63+E94+IFERROR($E$105/$D$105*D32,0) -> 0 | F32: =IF(OR(D32=0,E32=0),"",ROUND(E32/D32,2))
B33: Total | D33: =SUM(D5:D32) -> 4089448 | E33: =SUM(E5:E32) -> 25602472 | F33: =IF(OR(D33=0,E33=0),"",ROUND(E33/D33,2)) -> 6.26
A35: Fund | B35: Departmental Operating Expense by Discipline | D35: Contact Hours | E35: Expense | F35: Expense per Contact Hour
A36: 1 | B36: Agriculture | D36: =IF(F3="1",SUMIF(Data!A:A,'3'!$A$2,Data!CU:CU),0) -> 2552 | E36: =IF(F3="1",SUMIF(Data!$A:$A,$A$2,Data!IO:IO),0) -> 3905 | F36: =IF(OR(D36=0,E36=0),"",ROUND(E36/D36,2)) -> 1.53
A37: 2 | B37: Architecture and Precision Production Trades | D37: =IF(F3="1",SUMIF(Data!A:A,'3'!$A$2,Data!CV:CV),0) -> 101057 | E37: =IF(F3="1",SUMIF(Data!$A:$A,$A$2,Data!IP:IP),0) -> 154806 | F37: =IF(OR(D37=0,E37=0),"",ROUND(E37/D37,2)) -> 1.53
A38: 3 | B38: Biology, Physical Sciences, and Science Technology | D38: =IF(F3="1",SUMIF(Data!A:A,'3'!$A$2,Data!CW:CW),0) -> 337568 | E38: =IF($F$3="1",SUMIF(Data!$A:$A,$A$2,Data!IQ:IQ),0) -> 153063 | F38: =IF(OR(D38=0,E38=0),"",ROUND(E38/D38,2)) -> 0.45
A39: 4 | B39: Business Management, Marketing, and Administrative Services | D39: =IF(F3="1",SUMIF(Data!A:A,'3'!$A$2,Data!CX:CX),0) -> 228606 | E39: =IF($F$3="1",SUMIF(Data!$A:$A,$A$2,Data!IR:IR),0) -> 136429 | F39: =IF(OR(D39=0,E39=0),"",ROUND(E39/D39,2)) -> 0.6
A40: 5 | B40: Career Pilot | D40: =IF(F3="1",SUMIF(Data!A:A,'3'!$A$2,Data!CY:CY),0) -> 0 | E40: =IF($F$3="1",SUMIF(Data!$A:$A,$A$2,Data!IS:IS),0) -> 0 | F40: =IF(OR(D40=0,E40=0),"",ROUND(E40/D40,2))
A41: 6 | B41: Communications | D41: =IF(F3="1",SUMIF(Data!A:A,'3'!$A$2,Data!CZ:CZ),0) -> 30544 | E41: =IF($F$3="1",SUMIF(Data!$A:$A,$A$2,Data!IT:IT),0) -> 85186 | F41: =IF(OR(D41=0,E41=0),"",ROUND(E41/D41,2)) -> 2.79
A42: 7 | B42: Computer and Information Sciences | D42: =IF(F3="1",SUMIF(Data!A:A,'3'!$A$2,Data!DA:DA),0) -> 274523 | E42: =IF($F$3="1",SUMIF(Data!$A:$A,$A$2,Data!IU:IU),0) -> 174102 | F42: =IF(OR(D42=0,E42=0),"",ROUND(E42/D42,2)) -> 0.63
A43: 8 | B43: Construction Trades | D43: =IF(F3="1",SUMIF(Data!A:A,'3'!$A$2,Data!DB:DB),0) -> 16521 | E43: =IF($F$3="1",SUMIF(Data!$A:$A,$A$2,Data!IV:IV),0) -> 6518 | F43: =IF(OR(D43=0,E43=0),"",ROUND(E43/D43,2)) -> 0.39
A44: 9 | B44: Consumer and Homemaking Education | D44: =IF(F3="1",SUMIF(Data!A:A,'3'!$A$2,Data!DC:DC),0) -> 110143 | E44: =IF($F$3="1",SUMIF(Data!$A:$A,$A$2,Data!IW:IW),0) -> 34086 | F44: =IF(OR(D44=0,E44=0),"",ROUND(E44/D44,2)) -> 0.31
A45: 10 | B45: Engineering | D45: =IF(F3="1",SUMIF(Data!A:A,'3'!$A$2,Data!DD:DD),0) -> 656 | E45: =IF($F$3="1",SUMIF(Data!$A:$A,$A$2,Data!IX:IX),0) -> 274 | F45: =IF(OR(D45=0,E45=0),"",ROUND(E45/D45,2)) -> 0.42
A46: 11 | B46: Engineering Related | D46: =IF(F3="1",SUMIF(Data!A:A,'3'!$A$2,Data!DE:DE),0) -> 144529 | E46: =IF($F$3="1",SUMIF(Data!$A:$A,$A$2,Data!IY:IY),0) -> 290000 | F46: =IF(OR(D46=0,E46=0),"",ROUND(E46/D46,2)) -> 2.01
A47: 12 | B47: English Language, Lit, Philosophy, Humanities, & Interdisciplinary | D47: =IF(F3="1",SUMIF(Data!A:A,'3'!$A$2,Data!DF:DF),0) -> 580770 | E47: =IF($F$3="1",SUMIF(Data!$A:$A,$A$2,Data!IZ:IZ),0) -> 318830 | F47: =IF(OR(D47=0,E47=0),"",ROUND(E47/D47,2)) -> 0.55
A48: 13 | B48: Foreign Languages | D48: =IF(F3="1",SUMIF(Data!A:A,'3'!$A$2,Data!DG:DG),0) -> 25248 | E48: =IF($F$3="1",SUMIF(Data!$A:$A,$A$2,Data!JA:JA),0) -> 3831 | F48: =IF(OR(D48=0,E48=0),"",ROUND(E48/D48,2)) -> 0.15
A49: 14 | B49: Health Occupations - Dental Assistants, Medical Lab, and Assoc. Degree Nursing | D49: =IF(F3="1",SUMIF(Data!A:A,'3'!$A$2,Data!DH:DH),0) -> 190521 | E49: =IF($F$3="1",SUMIF(Data!$A:$A,$A$2,Data!JB:JB),0) -> 132538 | F49: =IF(OR(D49=0,E49=0),"",ROUND(E49/D49,2)) -> 0.7
A50: 15 | B50: Health Occupations - Dental Hygiene | D50: =IF(F3="1",SUMIF(Data!A:A,'3'!$A$2,Data!DI:DI),0) -> 41616 | E50: =IF($F$3="1",SUMIF(Data!$A:$A,$A$2,Data!JC:JC),0) -> 63652 | F50: =IF(OR(D50=0,E50=0),"",ROUND(E50/D50,2)) -> 1.53
A51: 16 | B51: Health Occupations - Other | D51: =IF(F3="1",SUMIF(Data!A:A,'3'!$A$2,Data!DJ:DJ),0) -> 414918 | E51: =IF($F$3="1",SUMIF(Data!$A:$A,$A$2,Data!JD:JD),0) -> 245523 | F51: =IF(OR(D51=0,E51=0),"",ROUND(E51/D51,2)) -> 0.59
A52: 17 | B52: Health Occupations - Respiratory Therapy | D52: =IF(F3="1",SUMIF(Data!A:A,'3'!$A$2,Data!DK:DK),0) -> 26752 | E52: =IF($F$3="1",SUMIF(Data!$A:$A,$A$2,Data!JE:JE),0) -> 5265 | F52: =IF(OR(D52=0,E52=0),"",ROUND(E52/D52,2)) -> 0.2
A53: 18 | B53: Health Occupations - Vocational Nursing | D53: =IF(F3="1",SUMIF(Data!A:A,'3'!$A$2,Data!DL:DL),0) -> 87304 | E53: =IF($F$3="1",SUMIF(Data!$A:$A,$A$2,Data!JF:JF),0) -> 27540 | F53: =IF(OR(D53=0,E53=0),"",ROUND(E53/D53,2)) -> 0.32
A54: 19 | B54: Mathematics | D54: =IF(F3="1",SUMIF(Data!A:A,'3'!$A$2,Data!DM:DM),0) -> 340885 | E54: =IF($F$3="1",SUMIF(Data!$A:$A,$A$2,Data!JG:JG),0) -> 125471 | F54: =IF(OR(D54=0,E54=0),"",ROUND(E54/D54,2)) -> 0.37
A55: 20 | B55: Mechanics and Repairers - Automotive | D55: =IF(F3="1",SUMIF(Data!A:A,'3'!$A$2,Data!DN:DN),0) -> 110578 | E55: =IF($F$3="1",SUMIF(Data!$A:$A,$A$2,Data!JH:JH),0) -> 89893 | F55: =IF(OR(D55=0,E55=0),"",ROUND(E55/D55,2)) -> 0.81
A56: 21 | B56: Mechanics and Repairers - Diesel, Aviation Mechanics, and Transportation Workers | D56: =IF(F3="1",SUMIF(Data!A:A,'3'!$A$2,Data!DO:DO),0) -> 118366 | E56: =IF($F$3="1",SUMIF(Data!$A:$A,$A$2,Data!JI:JI),0) -> 179816 | F56: =IF(OR(D56=0,E56=0),"",ROUND(E56/D56,2)) -> 1.52
A57: 22 | B57: Mechanics and Repairers - Electronics | D57: =IF(F3="1",SUMIF(Data!A:A,'3'!$A$2,Data!DP:DP),0) -> 10000 | E57: =IF($F$3="1",SUMIF(Data!$A:$A,$A$2,Data!JJ:JJ),0) -> 13095 | F57: =IF(OR(D57=0,E57=0),"",ROUND(E57/D57,2)) -> 1.31
A58: 23 | B58: Physical Education and Fitness | D58: =IF(F3="1",SUMIF(Data!A:A,'3'!$A$2,Data!DQ:DQ),0) -> 96944 | E58: =IF($F$3="1",SUMIF(Data!$A:$A,$A$2,Data!JK:JK),0) -> 88580 | F58: =IF(OR(D58=0,E58=0),"",ROUND(E58/D58,2)) -> 0.91
A59: 24 | B59: Protective Services and Public Administration | D59: =IF(F3="1",SUMIF(Data!A:A,'3'!$A$2,Data!DR:DR),0) -> 311849 | E59: =IF($F$3="1",SUMIF(Data!$A:$A,$A$2,Data!JL:JL),0) -> 386421 | F59: =IF(OR(D59=0,E59=0),"",ROUND(E59/D59,2)) -> 1.24
A60: 25 | B60: Psychology, Social Sciences, and History | D60: =IF(F3="1",SUMIF(Data!A:A,'3'!$A$2,Data!DS:DS),0) -> 322519 | E60: =IF($F$3="1",SUMIF(Data!$A:$A,$A$2,Data!JM:JM),0) -> 80690 | F60: =IF(OR(D60=0,E60=0),"",ROUND(E60/D60,2)) -> 0.25
A61: 26 | B61: Visual and Performing Arts | D61: =IF(F3="1",SUMIF(Data!A:A,'3'!$A$2,Data!DT:DT),0) -> 164479 | E61: =IF($F$3="1",SUMIF(Data!$A:$A,$A$2,Data!JN:JN),0) -> 287282 | F61: =IF(OR(D61=0,E61=0),"",ROUND(E61/D61,2)) -> 1.75
A62: 28 | B62: Developmental Education - Math | D62: =IF(F3="1",SUMIF(Data!A:A,'3'!$A$2,Data!DV:DV),0) -> 0 | E62: =IF($F$3="1",SUMIF(Data!$A:$A,$A$2,Data!JP:JP),0) -> 0 | F62: =IF(OR(D62=0,E62=0),"",ROUND(E62/D62,2))
A63: 29 | B63: Developmental Education - Reading/Writing | D63: =IF(F3="1",SUMIF(Data!A:A,'3'!$A$2,Data!DW:DW),0) -> 0 | E63: =IF($F$3="1",SUMIF(Data!$A:$A,$A$2,Data!JQ:JQ),0) -> 0 | F63: =IF(OR(D63=0,E63=0),"",ROUND(E63/D63,2))
B64: Total | D64: =SUM(D36:D63) -> 4089448 | E64: =SUM(E36:E63) -> 3086796 | F64: =IF(OR(D64=0,E64=0),"",ROUND(E64/D64,2)) -> 0.75
A66: Fund | B66: Faculty Salaries by Discipline | D66: Contact Hours | E66: Expense | F66: Expense per Contact Hour
A67: 1 | B67: Agriculture | D67: =D36 -> 2552 | E67: =IF(F3="1",SUMIF(Data!A:A,'3'!$A$2,Data!DY:DY),0) -> 16833 | F67: =IF(OR(D67=0,E67=0),"",ROUND(E67/D67,2)) -> 6.6
A68: 2 | B68: Architecture and Precision Production Trades | D68: =D37 -> 101057 | E68: =IF(F3="1",SUMIF(Data!A:A,'3'!$A$2,Data!DZ:DZ),0) -> 321978 | F68: =IF(OR(D68=0,E68=0),"",ROUND(E68/D68,2)) -> 3.19
A69: 3 | B69: Biology, Physical Sciences, and Science Technology | D69: =D38 -> 337568 | E69: =IF(F3="1",SUMIF(Data!A:A,'3'!$A$2,Data!EA:EA),0) -> 696505 | F69: =IF(OR(D69=0,E69=0),"",ROUND(E69/D69,2)) -> 2.06
A70: 4 | B70: Business Management, Marketing, and Administrative Services | D70: =D39 -> 228606 | E70: =IF(F3="1",SUMIF(Data!A:A,'3'!$A$2,Data!EB:EB),0) -> 660026 | F70: =IF(OR(D70=0,E70=0),"",ROUND(E70/D70,2)) -> 2.89
A71: 5 | B71: Career Pilot | D71: =D40 -> 0 | E71: =IF(F3="1",SUMIF(Data!A:A,'3'!$A$2,Data!EC:EC),0) -> 0 | F71: =IF(OR(D71=0,E71=0),"",ROUND(E71/D71,2))
A72: 6 | B72: Communications | D72: =D41 -> 30544 | E72: =IF(F3="1",SUMIF(Data!A:A,'3'!$A$2,Data!ED:ED),0) -> 110975 | F72: =IF(OR(D72=0,E72=0),"",ROUND(E72/D72,2)) -> 3.63
A73: 7 | B73: Computer and Information Sciences | D73: =D42 -> 274523 | E73: =IF(F3="1",SUMIF(Data!A:A,'3'!$A$2,Data!EE:EE),0) -> 521805 | F73: =IF(OR(D73=0,E73=0),"",ROUND(E73/D73,2)) -> 1.9
A74: 8 | B74: Construction Trades | D74: =D43 -> 16521 | E74: =IF(F3="1",SUMIF(Data!A:A,'3'!$A$2,Data!EF:EF),0) -> 15599 | F74: =IF(OR(D74=0,E74=0),"",ROUND(E74/D74,2)) -> 0.94
A75: 9 | B75: Consumer and Homemaking Education | D75: =D44 -> 110143 | E75: =IF(F3="1",SUMIF(Data!A:A,'3'!$A$2,Data!EG:EG),0) -> 241838 | F75: =IF(OR(D75=0,E75=0),"",ROUND(E75/D75,2)) -> 2.2
A76: 10 | B76: Engineering | D76: =D45 -> 656 | E76: =IF(F3="1",SUMIF(Data!A:A,'3'!$A$2,Data!EH:EH),0) -> 2552 | F76: =IF(OR(D76=0,E76=0),"",ROUND(E76/D76,2)) -> 3.89
A77: 11 | B77: Engineering Related | D77: =D46 -> 144529 | E77: =IF(F3="1",SUMIF(Data!A:A,'3'!$A$2,Data!EI:EI),0) -> 432443 | F77: =IF(OR(D77=0,E77=0),"",ROUND(E77/D77,2)) -> 2.99
A78: 12 | B78: English Language, Lit, Philosophy, Humanities, & Interdisciplinary | D78: =D47 -> 580770 | E78: =IF(F3="1",SUMIF(Data!A:A,'3'!$A$2,Data!EJ:EJ),0) -> 1333022 | F78: =IF(OR(D78=0,E78=0),"",ROUND(E78/D78,2)) -> 2.3
A79: 13 | B79: Foreign Languages | D79: =D48 -> 25248 | E79: =IF(F3="1",SUMIF(Data!A:A,'3'!$A$2,Data!EK:EK),0) -> 112509 | F79: =IF(OR(D79=0,E79=0),"",ROUND(E79/D79,2)) -> 4.46
A80: 14 | B80: Health Occupations - Dental Assistants, Medical Lab, and Assoc. Degree Nursing | D80: =D49 -> 190521 | E80: =IF(F3="1",SUMIF(Data!A:A,'3'!$A$2,Data!EL:EL),0) -> 807716 | F80: =IF(OR(D80=0,E80=0),"",ROUND(E80/D80,2)) -> 4.24
A81: 15 | B81: Health Occupations - Dental Hygiene | D81: =D50 -> 41616 | E81: =IF(F3="1",SUMIF(Data!A:A,'3'!$A$2,Data!EM:EM),0) -> 222232 | F81: =IF(OR(D81=0,E81=0),"",ROUND(E81/D81,2)) -> 5.34
A82: 16 | B82: Health Occupations - Other | D82: =D51 -> 414918 | E82: =IF(F3="1",SUMIF(Data!A:A,'3'!$A$2,Data!EN:EN),0) -> 995598 | F82: =IF(OR(D82=0,E82=0),"",ROUND(E82/D82,2)) -> 2.4
A83: 17 | B83: Health Occupations - Respiratory Therapy | D83: =D52 -> 26752 | E83: =IF(F3="1",SUMIF(Data!A:A,'3'!$A$2,Data!EO:EO),0) -> 141442 | F83: =IF(OR(D83=0,E83=0),"",ROUND(E83/D83,2)) -> 5.29
A84: 18 | B84: Health Occupations - Vocational Nursing | D84: =D53 -> 87304 | E84: =IF(F3="1",SUMIF(Data!A:A,'3'!$A$2,Data!EP:EP),0) -> 239741 | F84: =IF(OR(D84=0,E84=0),"",ROUND(E84/D84,2)) -> 2.75
A85: 19 | B85: Mathematics | D85: =D54 -> 340885 | E85: =IF(F3="1",SUMIF(Data!A:A,'3'!$A$2,Data!EQ:EQ),0) -> 626784 | F85: =IF(OR(D85=0,E85=0),"",ROUND(E85/D85,2)) -> 1.84
A86: 20 | B86: Mechanics and Repairers - Automotive | D86: =D55 -> 110578 | E86: =IF(F3="1",SUMIF(Data!A:A,'3'!$A$2,Data!ER:ER),0) -> 490649 | F86: =IF(OR(D86=0,E86=0),"",ROUND(E86/D86,2)) -> 4.44
A87: 21 | B87: Mechanics and Repairers - Diesel, Aviation Mechanics, and Transportation Workers | D87: =D56 -> 118366 | E87: =IF(F3="1",SUMIF(Data!A:A,'3'!$A$2,Data!ES:ES),0) -> 270311 | F87: =IF(OR(D87=0,E87=0),"",ROUND(E87/D87,2)) -> 2.28
A88: 22 | B88: Mechanics and Repairers - Electronics | D88: =D57 -> 10000 | E88: =IF(F3="1",SUMIF(Data!A:A,'3'!$A$2,Data!ET:ET),0) -> 36057 | F88: =IF(OR(D88=0,E88=0),"",ROUND(E88/D88,2)) -> 3.61
A89: 23 | B89: Physical Education and Fitness | D89: =D58 -> 96944 | E89: =IF(F3="1",SUMIF(Data!A:A,'3'!$A$2,Data!EU:EU),0) -> 169125 | F89: =IF(OR(D89=0,E89=0),"",ROUND(E89/D89,2)) -> 1.74
A90: 24 | B90: Protective Services and Public Administration | D90: =D59 -> 311849 | E90: =IF(F3="1",SUMIF(Data!A:A,'3'!$A$2,Data!EV:EV),0) -> 423056 | F90: =IF(OR(D90=0,E90=0),"",ROUND(E90/D90,2)) -> 1.36
A91: 25 | B91: Psychology, Social Sciences, and History | D91: =D60 -> 322519 | E91: =IF(F3="1",SUMIF(Data!A:A,'3'!$A$2,Data!EW:EW),0) -> 724994 | F91: =IF(OR(D91=0,E91=0),"",ROUND(E91/D91,2)) -> 2.25
A92: 26 | B92: Visual and Performing Arts | D92: =D61 -> 164479 | E92: =IF(F3="1",SUMIF(Data!A:A,'3'!$A$2,Data!EX:EX),0) -> 744427 | F92: =IF(OR(D92=0,E92=0),"",ROUND(E92/D92,2)) -> 4.53
A93: 28 | B93: Developmental Education - Math | D93: =D62 -> 0 | E93: =IF(F3="1",SUMIF(Data!A:A,'3'!$A$2,Data!EZ:EZ),0) -> 0 | F93: =IF(OR(D93=0,E93=0),"",ROUND(E93/D93,2))
A94: 29 | B94: Developmental Education - Reading/Writing | D94: =D63 -> 0 | E94: =IF(F3="1",SUMIF(Data!A:A,'3'!$A$2,Data!FA:FA),0) -> 0 | F94: =IF(OR(D94=0,E94=0),"",ROUND(E94/D94,2))
B95: Total | D95: =SUM(D67:D94) -> 4089448 | E95: =SUM(E67:E94) -> 10358217 | F95: =IF(OR(D95=0,E95=0),"",ROUND(E95/D95,2)) -> 2.53
B97: Allocated Administrative Expense | D97: Contact Hours | E97: Expense | F97: Expense per Contact Hour
B98: Institutional Support | E98: =IF(F3="1",SUMIF(Data!A:A,'3'!$A$2,Data!AH:AH),0) -> 5601909 | F98: =IF(OR(E98=0,E98=0),"",ROUND(E98/$D$105,2)) -> 1.37
B99: Student Services | E99: =IF(F3="1",SUMIF(Data!A:A,'3'!$A$2,Data!AI:AI),0) -> 2169433 | F99: =IF(OR(E99=0,E99=0),"",ROUND(E99/$D$105,2)) -> 0.53
B100: Library | E100: =IF(F3="1",SUMIF(Data!A:A,'3'!$A$2,Data!AJ:AJ),0) -> 862389 | F100: =IF(OR(E100=0,E100=0),"",ROUND(E100/$D$105,2)) -> 0.21
B101: Instructional Administration | E101: =IF(F3="1",SUMIF(Data!A:A,'3'!$A$2,Data!AK:AK),0) -> 1264843 | F101: =IF(OR(E101=0,E101=0),"",ROUND(E101/$D$105,2)) -> 0.31
B102: Organized Activities | E102: =IF(F3="1",SUMIF(Data!A:A,'3'!$A$2,Data!AL:AL),0) -> 274030 | F102: =IF(OR(E102=0,E102=0),"",ROUND(E102/$D$105,2)) -> 0.07
B103: Equipment Depreciation | E103: =IF(F3="1",SUMIF(Data!A:A,'3'!$A$2,Data!AM:AM),0) -> 0 | F103: =IF(OR(E103=0,E103=0),"",ROUND(E103/$D$105,2))
B104: Local Benefits | E104: =IF(F3="1",SUMIF(Data!A:A,'3'!$A$2,Data!Q:Q),0) -> 1984855 | F104: =IF(OR(E104=0,E104=0),"",ROUND(E104/$D$105,2)) -> 0.49
B105: Total | D105: =D95 -> 4089448 | E105: =SUM(E98:E104) -> 12157459 | F105: =IF($D$105=0,"",ROUND(E105/$D$105,2)) -> 2.97
B107: Annual Financial Report - Schedule B
B108: Unrestricted - Educational Activities | C108: Salaries and Wages | D108: Local Benefits | E108: Other Expenses | F108: Total
B109: Instruction | C109: =E95+IF(F3="1",SUMIF(Data!$A:$A,$A$2,Data!GF:GF),0) -> 10358217 | D109: =IF(F3="1",SUMIF(Data!$A:$A,$A$2,Data!HJ:HJ),0) -> 0 | E109: =IF(F3="1",SUMIF(Data!$A:$A,$A$2,Data!IN:IN),0) -> 0 | F109: =SUM(C109:E109) -> 10358217
B110: Research | C110: =IF(F3="1",SUMIF(Data!A:A,$A$2,Data!W:W),0) -> 0 | E110: =IF(F3="1",SUMIF(Data!A:A,$A$2,Data!W:W),0) -> 0 | F110: =SUM(C110:E110) -> 0
B111: Public Service | C111: =IF(F3="1",SUMIF(Data!A:A,$A$2,Data!AS:AS),0) -> 0 | E111: =IF(F3="1",SUMIF(Data!A:A,$A$2,Data!AX:AX),0) -> 0 | F111: =SUM(C111:E111) -> 0
B112: Academic Support | C112: =IF(F3="1",SUMIF(Data!A:A,$A$2,Data!V:V),0) -> 0 | E112: =IF(F3="1",SUMIF(Data!A:A,$A$2,Data!AC:AC),0) -> 0 | F112: =SUM(C112:E112) -> 0
B113: Student Services | C113: =IF(F3="1",SUMIF(Data!A:A,$A$2,Data!U:U),0) -> 0 | E113: =IF(F3="1",SUMIF(Data!A:A,$A$2,Data!AB:AB),0) -> 0 | F113: =SUM(C113:E113) -> 0
B114: Instructional Support | C114: =IF(F3="1",SUMIF(Data!A:A,$A$2,Data!T:T),0) -> 0 | E114: =IF(F3="1",SUMIF(Data!A:A,$A$2,Data!AA:AA),0) -> 0 | F114: =SUM(C114:E114) -> 0
B115: Operation and Maintenance of Plant | C115: =IF(F3="1",SUMIF(Data!A:A,$A$2,Data!BI:BI),0) -> 0 | D115: =IF(F3="1",SUMIF(Data!A:A,$A$2,Data!BL:BL),0) -> 0 | E115: =IF(F3="1",SUMIF(Data!A:A,$A$2,Data!BU:BU),0) -> 0 | F115: =SUM(C115:E115) -> 0
B116: Scholarships and Fellowships | C116: =IF(F3="1",SUMIF(Data!A:A,$A$2,Data!X:X),0) -> 0 | E116: =E102 -> 274030 | F116: =SUM(C116:E116) -> 274030
B117: Other | D117: =IF(F3="1",SUMIF(Data!A:A,$A$2,Data!Q:Q),0) -> 1984855 | F117: =SUM(C117:E117) -> 1984855
B118: Total | C118: =SUM(C109:C116) -> 10358217 | D118: =SUM(D109:D116) -> 0 | E118: =SUM(E109:E116) -> 274030 | F118: =SUM(F109:F116) -> 10632247
B120: Depreciation Expense - Equipment | E120: =IF(F3="1",SUMIF(Data!A:A,'3'!$A$2,Data!AM:AM),0) -> 0 | F120: =SUM(C120:E120) -> 0
...

Sheet 4
A1: =Summary!A1 -> Community and Technical Colleges, Report of Fundable Operating Expenses, Fiscal Year (FY) 1999
A2: 006661 | B2: =VLOOKUP(A2,Data!A:G,7,0) -> Angelina College
F3: =IFERROR(VLOOKUP(A2,Data!A:C,3,0),"0") -> 1
A4: Fund | B4: Total Expense by Discipline | D4: Contact Hours | E4: Expense | F4: Expense per Contact Hour
A5: 1 | B5: Agriculture | D5: =D36 -> 120 | E5: =E36+E67+IFERROR($E$105/$D$105*D5,0) -> 713.38161 | F5: =IF(OR(D5=0,E5=0),"",ROUND(E5/D5,2)) -> 5.94
A6: 2 | B6: Architecture and Precision Production Trades | D6: =D37 -> 146620 | E6: =E37+E68+IFERROR($E$105/$D$105*D6,0) -> 613267.76 | F6: =IF(OR(D6=0,E6=0),"",ROUND(E6/D6,2)) -> 4.18
A7: 3 | B7: Biology, Physical Sciences, and Science Technology | D7: =D38 -> 168144 | E7: =E38+E69+IFERROR($E$105/$D$105*D7,0) -> 671677.11 | F7: =IF(OR(D7=0,E7=0),"",ROUND(E7/D7,2)) -> 3.99
A8: 4 | B8: Business Management, Marketing, and Administrative Services | D8: =D39 -> 117567 | E8: =E39+E70+IFERROR($E$105/$D$105*D8,0) -> 686607.2 | F8: =IF(OR(D8=0,E8=0),"",ROUND(E8/D8,2)) -> 5.84
A9: 5 | B9: Career Pilot | D9: =D40 -> 0 | E9: =E40+E71+IFERROR($E$105/$D$105*D9,0) -> 0 | F9: =IF(OR(D9=0,E9=0),"",ROUND(E9/D9,2))
A10: 6 | B10: Communications | D10: =D41 -> 6176 | E10: =E41+E72+IFERROR($E$105/$D$105*D10,0) -> 38413.24 | F10: =IF(OR(D10=0,E10=0),"",ROUND(E10/D10,2)) -> 6.22
A11: 7 | B11: Computer and Information Sciences | D11: =D42 -> 65893 | E11: =E42+E73+IFERROR($E$105/$D$105*D11,0) -> 409474.72 | F11: =IF(OR(D11=0,E11=0),"",ROUND(E11/D11,2)) -> 6.21
A12: 8 | B12: Construction Trades | D12: =D43 -> 72 | E12: =E43+E74+IFERROR($E$105/$D$105*D12,0) -> 424.42897 | F12: =IF(OR(D12=0,E12=0),"",ROUND(E12/D12,2)) -> 5.89
A13: 9 | B13: Consumer and Homemaking Education | D13: =D44 -> 35008 | E13: =E44+E75+IFERROR($E$105/$D$105*D13,0) -> 167227.13 | F13: =IF(OR(D13=0,E13=0),"",ROUND(E13/D13,2)) -> 4.78
A14: 10 | B14: Engineering | D14: =D45 -> 5232 | E14: =E45+E76+IFERROR($E$105/$D$105*D14,0) -> 56600.838 | F14: =IF(OR(D14=0,E14=0),"",ROUND(E14/D14,2)) -> 10.82
A15: 11 | B15: Engineering Related | D15: =D46 -> 29652 | E15: =E46+E77+IFERROR($E$105/$D$105*D15,0) -> 104758 | F15: =IF(OR(D15=0,E15=0),"",ROUND(E15/D15,2)) -> 3.53
A16: 12 | B16: English Language, Lit, Philosophy, Humanities, & Interdisciplinary | D16: =D47 -> 262352 | E16: =E47+E78+IFERROR($E$105/$D$105*D16,0) -> 1019653.5 | F16: =IF(OR(D16=0,E16=0),"",ROUND(E16/D16,2)) -> 3.89
... A32: 29 | B32: Developmental Education - Reading/Writing | D32: =D63 -> 0 | E32: =E63+E94+IFERROR($E$105/$D$105*D32,0) -> 0 | F32: =IF(OR(D32=0,E32=0),"",ROUND(E32/D32,2))
B33: Total | D33: =SUM(D5:D32) -> 1943728 | E33: =SUM(E5:E32) -> 9238820 | F33: =IF(OR(D33=0,E33=0),"",ROUND(E33/D33,2)) -> 4.75
A35: Fund | B35: Departmental Operating Expense by Discipline | D35: Contact Hours | E35: Expense | F35: Expense per Contact Hour
A36: 1 | B36: Agriculture | D36: =IF(F3="1",SUMIF(Data!A:A,'4'!$A$2,Data!CU:CU),0) -> 120 | E36: =IF(F3="1",SUMIF(Data!$A:$A,$A$2,Data!IO:IO),0) -> 431 | F36: =IF(OR(D36=0,E36=0),"",ROUND(E36/D36,2)) -> 3.59
A37: 2 | B37: Architecture and Precision Production Trades | D37: =IF(F3="1",SUMIF(Data!A:A,'4'!$A$2,Data!CV:CV),0) -> 146620 | E37: =IF(F3="1",SUMIF(Data!$A:$A,$A$2,Data!IP:IP),0) -> 189007 | F37: =IF(OR(D37=0,E37=0),"",ROUND(E37/D37,2)) -> 1.29
A38: 3 | B38: Biology, Physical Sciences, and Science Technology | D38: =IF(F3="1",SUMIF(Data!A:A,'4'!$A$2,Data!CW:CW),0) -> 168144 | E38: =IF($F$3="1",SUMIF(Data!$A:$A,$A$2,Data!IQ:IQ),0) -> 56090 | F38: =IF(OR(D38=0,E38=0),"",ROUND(E38/D38,2)) -> 0.33
A39: 4 | B39: Business Management, Marketing, and Administrative Services | D39: =IF(F3="1",SUMIF(Data!A:A,'4'!$A$2,Data!CX:CX),0) -> 117567 | E39: =IF($F$3="1",SUMIF(Data!$A:$A,$A$2,Data!IR:IR),0) -> 79287 | F39: =IF(OR(D39=0,E39=0),"",ROUND(E39/D39,2)) -> 0.67
A40: 5 | B40: Career Pilot | D40: =IF(F3="1",SUMIF(Data!A:A,'4'!$A$2,Data!CY:CY),0) -> 0 | E40: =IF($F$3="1",SUMIF(Data!$A:$A,$A$2,Data!IS:IS),0) -> 0 | F40: =IF(OR(D40=0,E40=0),"",ROUND(E40/D40,2))
A41: 6 | B41: Communications | D41: =IF(F3="1",SUMIF(Data!A:A,'4'!$A$2,Data!CZ:CZ),0) -> 6176 | E41: =IF($F$3="1",SUMIF(Data!$A:$A,$A$2,Data!IT:IT),0) -> 2424 | F41: =IF(OR(D41=0,E41=0),"",ROUND(E41/D41,2)) -> 0.39
A42: 7 | B42: Computer and Information Sciences | D42: =IF(F3="1",SUMIF(Data!A:A,'4'!$A$2,Data!DA:DA),0) -> 65893 | E42: =IF($F$3="1",SUMIF(Data!$A:$A,$A$2,Data!IU:IU),0) -> 108939 | F42: =IF(OR(D42=0,E42=0),"",ROUND(E42/D42,2)) -> 1.65
A43: 8 | B43: Construction Trades | D43: =IF(F3="1",SUMIF(Data!A:A,'4'!$A$2,Data!DB:DB),0) -> 72 | E43: =IF($F$3="1",SUMIF(Data!$A:$A,$A$2,Data!IV:IV),0) -> 255 | F43: =IF(OR(D43=0,E43=0),"",ROUND(E43/D43,2)) -> 3.54
A44: 9 | B44: Consumer and Homemaking Education | D44: =IF(F3="1",SUMIF(Data!A:A,'4'!$A$2,Data!DC:DC),0) -> 35008 | E44: =IF($F$3="1",SUMIF(Data!$A:$A,$A$2,Data!IW:IW),0) -> 31413 | F44: =IF(OR(D44=0,E44=0),"",ROUND(E44/D44,2)) -> 0.9
A45: 10 | B45: Engineering | D45: =IF(F3="1",SUMIF(Data!A:A,'4'!$A$2,Data!DD:DD),0) -> 5232 | E45: =IF($F$3="1",SUMIF(Data!$A:$A,$A$2,Data!IX:IX),0) -> 722 | F45: =IF(OR(D45=0,E45=0),"",ROUND(E45/D45,2)) -> 0.14
A46: 11 | B46: Engineering Related | D46: =IF(F3="1",SUMIF(Data!A:A,'4'!$A$2,Data!DE:DE),0) -> 29652 | E46: =IF($F$3="1",SUMIF(Data!$A:$A,$A$2,Data!IY:IY),0) -> 30624 | F46: =IF(OR(D46=0,E46=0),"",ROUND(E46/D46,2)) -> 1.03
A47: 12 | B47: English Language, Lit, Philosophy, Humanities, & Interdisciplinary | D47: =IF(F3="1",SUMIF(Data!A:A,'4'!$A$2,Data!DF:DF),0) -> 262352 | E47: =IF($F$3="1",SUMIF(Data!$A:$A,$A$2,Data!IZ:IZ),0) -> 34588 | F47: =IF(OR(D47=0,E47=0),"",ROUND(E47/D47,2)) -> 0.13
A48: 13 | B48: Foreign Languages | D48: =IF(F3="1",SUMIF(Data!A:A,'4'!$A$2,Data!DG:DG),0) -> 19472 | E48: =IF($F$3="1",SUMIF(Data!$A:$A,$A$2,Data!JA:JA),0) -> 2381 | F48: =IF(OR(D48=0,E48=0),"",ROUND(E48/D48,2)) -> 0.12
A49: 14 | B49: Health Occupations - Dental Assistants, Medical Lab, and Assoc. Degree Nursing | D49: =IF(F3="1",SUMIF(Data!A:A,'4'!$A$2,Data!DH:DH),0) -> 103306 | E49: =IF($F$3="1",SUMIF(Data!$A:$A,$A$2,Data!JB:JB),0) -> 95631 | F49: =IF(OR(D49=0,E49=0),"",ROUND(E49/D49,2)) -> 0.93
A50: 15 | B50: Health Occupations - Dental Hygiene | D50: =IF(F3="1",SUMIF(Data!A:A,'4'!$A$2,Data!DI:DI),0) -> 0 | E50: =IF($F$3="1",SUMIF(Data!$A:$A,$A$2,Data!JC:JC),0) -> 0 | F50: =IF(OR(D50=0,E50=0),"",ROUND(E50/D50,2))
A51: 16 | B51: Health Occupations - Other | D51: =IF(F3="1",SUMIF(Data!A:A,'4'!$A$2,Data!DJ:DJ),0) -> 95009 | E51: =IF($F$3="1",SUMIF(Data!$A:$A,$A$2,Data!JD:JD),0) -> 81995 | F51: =IF(OR(D51=0,E51=0),"",ROUND(E51/D51,2)) -> 0.86
A52: 17 | B52: Health Occupations - Respiratory Therapy | D52: =IF(F3="1",SUMIF(Data!A:A,'4'!$A$2,Data!DK:DK),0) -> 30464 | E52: =IF($F$3="1",SUMIF(Data!$A:$A,$A$2,Data!JE:JE),0) -> 18113 | F52: =IF(OR(D52=0,E52=0),"",ROUND(E52/D52,2)) -> 0.59
A53: 18 | B53: Health Occupations - Vocational Nursing | D53: =IF(F3="1",SUMIF(Data!A:A,'4'!$A$2,Data!DL:DL),0) -> 75467 | E53: =IF($F$3="1",SUMIF(Data!$A:$A,$A$2,Data!JF:JF),0) -> 204877 | F53: =IF(OR(D53=0,E53=0),"",ROUND(E53/D53,2)) -> 2.71
A54: 19 | B54: Mathematics | D54: =IF(F3="1",SUMIF(Data!A:A,'4'!$A$2,Data!DM:DM),0) -> 199360 | E54: =IF($F$3="1",SUMIF(Data!$A:$A,$A$2,Data!JG:JG),0) -> 34989 | F54: =IF(OR(D54=0,E54=0),"",ROUND(E54/D54,2)) -> 0.18
A55: 20 | B55: Mechanics and Repairers - Automotive | D55: =IF(F3="1",SUMIF(Data!A:A,'4'!$A$2,Data!DN:DN),0) -> 14160 | E55: =IF($F$3="1",SUMIF(Data!$A:$A,$A$2,Data!JH:JH),0) -> 7441 | F55: =IF(OR(D55=0,E55=0),"",ROUND(E55/D55,2)) -> 0.53
A56: 21 | B56: Mechanics and Repairers - Diesel, Aviation Mechanics, and Transportation Workers | D56: =IF(F3="1",SUMIF(Data!A:A,'4'!$A$2,Data!DO:DO),0) -> 7968 | E56: =IF($F$3="1",SUMIF(Data!$A:$A,$A$2,Data!JI:JI),0) -> 22042 | F56: =IF(OR(D56=0,E56=0),"",ROUND(E56/D56,2)) -> 2.77
A57: 22 | B57: Mechanics and Repairers - Electronics | D57: =IF(F3="1",SUMIF(Data!A:A,'4'!$A$2,Data!DP:DP),0) -> 61312 | E57: =IF($F$3="1",SUMIF(Data!$A:$A,$A$2,Data!JJ:JJ),0) -> 15688 | F57: =IF(OR(D57=0,E57=0),"",ROUND(E57/D57,2)) -> 0.26
A58: 23 | B58: Physical Education and Fitness | D58: =IF(F3="1",SUMIF(Data!A:A,'4'!$A$2,Data!DQ:DQ),0) -> 53632 | E58: =IF($F$3="1",SUMIF(Data!$A:$A,$A$2,Data!JK:JK),0) -> 19712 | F58: =IF(OR(D58=0,E58=0),"",ROUND(E58/D58,2)) -> 0.37
A59: 24 | B59: Protective Services and Public Administration | D59: =IF(F3="1",SUMIF(Data!A:A,'4'!$A$2,Data!DR:DR),0) -> 114422 | E59: =IF($F$3="1",SUMIF(Data!$A:$A,$A$2,Data!JL:JL),0) -> 173393 | F59: =IF(OR(D59=0,E59=0),"",ROUND(E59/D59,2)) -> 1.52
A60: 25 | B60: Psychology, Social Sciences, and History | D60: =IF(F3="1",SUMIF(Data!A:A,'4'!$A$2,Data!DS:DS),0) -> 264144 | E60: =IF($F$3="1",SUMIF(Data!$A:$A,$A$2,Data!JM:JM),0) -> 64852 | F60: =IF(OR(D60=0,E60=0),"",ROUND(E60/D60,2)) -> 0.25
A61: 26 | B61: Visual and Performing Arts | D61: =IF(F3="1",SUMIF(Data!A:A,'4'!$A$2,Data!DT:DT),0) -> 68176 | E61: =IF($F$3="1",SUMIF(Data!$A:$A,$A$2,Data!JN:JN),0) -> 69581 | F61: =IF(OR(D61=0,E61=0),"",ROUND(E61/D61,2)) -> 1.02
A62: 28 | B62: Developmental Education - Math | D62: =IF(F3="1",SUMIF(Data!A:A,'4'!$A$2,Data!DV:DV),0) -> 0 | E62: =IF($F$3="1",SUMIF(Data!$A:$A,$A$2,Data!JP:JP),0) -> 0 | F62: =IF(OR(D62=0,E62=0),"",ROUND(E62/D62,2))
A63: 29 | B63: Developmental Education - Reading/Writing | D63: =IF(F3="1",SUMIF(Data!A:A,'4'!$A$2,Data!DW:DW),0) -> 0 | E63: =IF($F$3="1",SUMIF(Data!$A:$A,$A$2,Data!JQ:JQ),0) -> 0 | F63: =IF(OR(D63=0,E63=0),"",ROUND(E63/D63,2))
B64: Total | D64: =SUM(D36:D63) -> 1943728 | E64: =SUM(E36:E63) -> 1344475 | F64: =IF(OR(D64=0,E64=0),"",ROUND(E64/D64,2)) -> 0.69
A66: Fund | B66: Faculty Salaries by Discipline | D66: Contact Hours | E66: Expense | F66: Expense per Contact Hour
A67: 1 | B67: Agriculture | D67: =D36 -> 120 | E67: =IF(F3="1",SUMIF(Data!A:A,'4'!$A$2,Data!DY:DY),0) -> 105 | F67: =IF(OR(D67=0,E67=0),"",ROUND(E67/D67,2)) -> 0.88
A68: 2 | B68: Architecture and Precision Production Trades | D68: =D37 -> 146620 | E68: =IF(F3="1",SUMIF(Data!A:A,'4'!$A$2,Data!DZ:DZ),0) -> 207530 | F68: =IF(OR(D68=0,E68=0),"",ROUND(E68/D68,2)) -> 1.42
A69: 3 | B69: Biology, Physical Sciences, and Science Technology | D69: =D38 -> 168144 | E69: =IF(F3="1",SUMIF(Data!A:A,'4'!$A$2,Data!EA:EA),0) -> 367040 | F69: =IF(OR(D69=0,E69=0),"",ROUND(E69/D69,2)) -> 2.18
A70: 4 | B70: Business Management, Marketing, and Administrative Services | D70: =D39 -> 117567 | E70: =IF(F3="1",SUMIF(Data!A:A,'4'!$A$2,Data!EB:EB),0) -> 433535 | F70: =IF(OR(D70=0,E70=0),"",ROUND(E70/D70,2)) -> 3.69
A71: 5 | B71: Career Pilot | D71: =D40 -> 0 | E71: =IF(F3="1",SUMIF(Data!A:A,'4'!$A$2,Data!EC:EC),0) -> 0 | F71: =IF(OR(D71=0,E71=0),"",ROUND(E71/D71,2))
A72: 6 | B72: Communications | D72: =D41 -> 6176 | E72: =IF(F3="1",SUMIF(Data!A:A,'4'!$A$2,Data!ED:ED),0) -> 26860 | F72: =IF(OR(D72=0,E72=0),"",ROUND(E72/D72,2)) -> 4.35
A73: 7 | B73: Computer and Information Sciences | D73: =D42 -> 65893 | E73: =IF(F3="1",SUMIF(Data!A:A,'4'!$A$2,Data!EE:EE),0) -> 203134 | F73: =IF(OR(D73=0,E73=0),"",ROUND(E73/D73,2)) -> 3.08
A74: 8 | B74: Construction Trades | D74: =D43 -> 72 | E74: =IF(F3="1",SUMIF(Data!A:A,'4'!$A$2,Data!EF:EF),0) -> 63 | F74: =IF(OR(D74=0,E74=0),"",ROUND(E74/D74,2)) -> 0.88
A75: 9 | B75: Consumer and Homemaking Education | D75: =D44 -> 35008 | E75: =IF(F3="1",SUMIF(Data!A:A,'4'!$A$2,Data!EG:EG),0) -> 84066 | F75: =IF(OR(D75=0,E75=0),"",ROUND(E75/D75,2)) -> 2.4
A76: 10 | B76: Engineering | D76: =D45 -> 5232 | E76: =IF(F3="1",SUMIF(Data!A:A,'4'!$A$2,Data!EH:EH),0) -> 48145 | F76: =IF(OR(D76=0,E76=0),"",ROUND(E76/D76,2)) -> 9.2
A77: 11 | B77: Engineering Related | D77: =D46 -> 29652 | E77: =IF(F3="1",SUMIF(Data!A:A,'4'!$A$2,Data!EI:EI),0) -> 30303 | F77: =IF(OR(D77=0,E77=0),"",ROUND(E77/D77,2)) -> 1.02
A78: 12 | B78: English Language, Lit, Philosophy, Humanities, & Interdisciplinary | D78: =D47 -> 262352 | E78: =IF(F3="1",SUMIF(Data!A:A,'4'!$A$2,Data!EJ:EJ),0) -> 597262 | F78: =IF(OR(D78=0,E78=0),"",ROUND(E78/D78,2)) -> 2.28
A79: 13 | B79: Foreign Languages | D79: =D48 -> 19472 | E79: =IF(F3="1",SUMIF(Data!A:A,'4'!$A$2,Data!EK:EK),0) -> 68276 | F79: =IF(OR(D79=0,E79=0),"",ROUND(E79/D79,2)) -> 3.51
A80: 14 | B80: Health Occupations - Dental Assistants, Medical Lab, and Assoc. Degree Nursing | D80: =D49 -> 103306 | E80: =IF(F3="1",SUMIF(Data!A:A,'4'!$A$2,Data!EL:EL),0) -> 447377 | F80: =IF(OR(D80=0,E80=0),"",ROUND(E80/D80,2)) -> 4.33
A81: 15 | B81: Health Occupations - Dental Hygiene | D81: =D50 -> 0 | E81: =IF(F3="1",SUMIF(Data!A:A,'4'!$A$2,Data!EM:EM),0) -> 0 | F81: =IF(OR(D81=0,E81=0),"",ROUND(E81/D81,2))
A82: 16 | B82: Health Occupations - Other | D82: =D51 -> 95009 | E82: =IF(F3="1",SUMIF(Data!A:A,'4'!$A$2,Data!EN:EN),0) -> 399163 | F82: =IF(OR(D82=0,E82=0),"",ROUND(E82/D82,2)) -> 4.2
A83: 17 | B83: Health Occupations - Respiratory Therapy | D83: =D52 -> 30464 | E83: =IF(F3="1",SUMIF(Data!A:A,'4'!$A$2,Data!EO:EO),0) -> 131556 | F83: =IF(OR(D83=0,E83=0),"",ROUND(E83/D83,2)) -> 4.32
A84: 18 | B84: Health Occupations - Vocational Nursing | D84: =D53 -> 75467 | E84: =IF(F3="1",SUMIF(Data!A:A,'4'!$A$2,Data!EP:EP),0) -> 148886 | F84: =IF(OR(D84=0,E84=0),"",ROUND(E84/D84,2)) -> 1.97
A85: 19 | B85: Mathematics | D85: =D54 -> 199360 | E85: =IF(F3="1",SUMIF(Data!A:A,'4'!$A$2,Data!EQ:EQ),0) -> 445088 | F85: =IF(OR(D85=0,E85=0),"",ROUND(E85/D85,2)) -> 2.23
A86: 20 | B86: Mechanics and Repairers - Automotive | D86: =D55 -> 14160 | E86: =IF(F3="1",SUMIF(Data!A:A,'4'!$A$2,Data!ER:ER),0) -> 50767 | F86: =IF(OR(D86=0,E86=0),"",ROUND(E86/D86,2)) -> 3.59
A87: 21 | B87: Mechanics and Repairers - Diesel, Aviation Mechanics, and Transportation Workers | D87: =D56 -> 7968 | E87: =IF(F3="1",SUMIF(Data!A:A,'4'!$A$2,Data!ES:ES),0) -> 15181 | F87: =IF(OR(D87=0,E87=0),"",ROUND(E87/D87,2)) -> 1.91
A88: 22 | B88: Mechanics and Repairers - Electronics | D88: =D57 -> 61312 | E88: =IF(F3="1",SUMIF(Data!A:A,'4'!$A$2,Data!ET:ET),0) -> 232842 | F88: =IF(OR(D88=0,E88=0),"",ROUND(E88/D88,2)) -> 3.8
A89: 23 | B89: Physical Education and Fitness | D89: =D58 -> 53632 | E89: =IF(F3="1",SUMIF(Data!A:A,'4'!$A$2,Data!EU:EU),0) -> 147843 | F89: =IF(OR(D89=0,E89=0),"",ROUND(E89/D89,2)) -> 2.76
A90: 24 | B90: Protective Services and Public Administration | D90: =D59 -> 114422 | E90: =IF(F3="1",SUMIF(Data!A:A,'4'!$A$2,Data!EV:EV),0) -> 190752 | F90: =IF(OR(D90=0,E90=0),"",ROUND(E90/D90,2)) -> 1.67
A91: 25 | B91: Psychology, Social Sciences, and History | D91: =D60 -> 264144 | E91: =IF(F3="1",SUMIF(Data!A:A,'4'!$A$2,Data!EW:EW),0) -> 515427 | F91: =IF(OR(D91=0,E91=0),"",ROUND(E91/D91,2)) -> 1.95
A92: 26 | B92: Visual and Performing Arts | D92: =D61 -> 68176 | E92: =IF(F3="1",SUMIF(Data!A:A,'4'!$A$2,Data!EX:EX),0) -> 229964 | F92: =IF(OR(D92=0,E92=0),"",ROUND(E92/D92,2)) -> 3.37
A93: 28 | B93: Developmental Education - Math | D93: =D62 -> 0 | E93: =IF(F3="1",SUMIF(Data!A:A,'4'!$A$2,Data!EZ:EZ),0) -> 0 | F93: =IF(OR(D93=0,E93=0),"",ROUND(E93/D93,2))
A94: 29 | B94: Developmental Education - Reading/Writing | D94: =D63 -> 0 | E94: =IF(F3="1",SUMIF(Data!A:A,'4'!$A$2,Data!FA:FA),0) -> 0 | F94: =IF(OR(D94=0,E94=0),"",ROUND(E94/D94,2))
B95: Total | D95: =SUM(D67:D94) -> 1943728 | E95: =SUM(E67:E94) -> 5021165 | F95: =IF(OR(D95=0,E95=0),"",ROUND(E95/D95,2)) -> 2.58
B97: Allocated Administrative Expense | D97: Contact Hours | E97: Expense | F97: Expense per Contact Hour
B98: Institutional Support | E98: =IF(F3="1",SUMIF(Data!A:A,'4'!$A$2,Data!AH:AH),0) -> 1024270 | F98: =IF(OR(E98=0,E98=0),"",ROUND(E98/$D$105,2)) -> 0.53
B99: Student Services | E99: =IF(F3="1",SUMIF(Data!A:A,'4'!$A$2,Data!AI:AI),0) -> 689268 | F99: =IF(OR(E99=0,E99=0),"",ROUND(E99/$D$105,2)) -> 0.35
B100: Library | E100: =IF(F3="1",SUMIF(Data!A:A,'4'!$A$2,Data!AJ:AJ),0) -> 281677 | F100: =IF(OR(E100=0,E100=0),"",ROUND(E100/$D$105,2)) -> 0.14
B101: Instructional Administration | E101: =IF(F3="1",SUMIF(Data!A:A,'4'!$A$2,Data!AK:AK),0) -> 628828 | F101: =IF(OR(E101=0,E101=0),"",ROUND(E101/$D$105,2)) -> 0.32
B102: Organized Activities | E102: =IF(F3="1",SUMIF(Data!A:A,'4'!$A$2,Data!AL:AL),0) -> 0 | F102: =IF(OR(E102=0,E102=0),"",ROUND(E102/$D$105,2))
B103: Equipment Depreciation | E103: =IF(F3="1",SUMIF(Data!A:A,'4'!$A$2,Data!AM:AM),0) -> 0 | F103: =IF(OR(E103=0,E103=0),"",ROUND(E103/$D$105,2))
B104: Local Benefits | E104: =IF(F3="1",SUMIF(Data!A:A,'4'!$A$2,Data!Q:Q),0) -> 249137 | F104: =IF(OR(E104=0,E104=0),"",ROUND(E104/$D$105,2)) -> 0.13
B105: Total | D105: =D95 -> 1943728 | E105: =SUM(E98:E104) -> 2873180 | F105: =IF($D$105=0,"",ROUND(E105/$D$105,2)) -> 1.48
B107: Annual Financial Report - Schedule B
B108: Unrestricted - Educational Activities | C108: Salaries and Wages | D108: Local Benefits | E108: Other Expenses | F108: Total
B109: Instruction | C109: =E95+IF(F3="1",SUMIF(Data!$A:$A,$A$2,Data!GF:GF),0) -> 5021165 | D109: =IF(F3="1",SUMIF(Data!$A:$A,$A$2,Data!HJ:HJ),0) -> 0 | E109: =IF(F3="1",SUMIF(Data!$A:$A,$A$2,Data!IN:IN),0) -> 0 | F109: =SUM(C109:E109) -> 5021165
B110: Research | C110: =IF(F3="1",SUMIF(Data!A:A,$A$2,Data!W:W),0) -> 0 | E110: =IF(F3="1",SUMIF(Data!A:A,$A$2,Data!W:W),0) -> 0 | F110: =SUM(C110:E110) -> 0
B111: Public Service | C111: =IF(F3="1",SUMIF(Data!A:A,$A$2,Data!AS:AS),0) -> 0 | E111: =IF(F3="1",SUMIF(Data!A:A,$A$2,Data!AX:AX),0) -> 0 | F111: =SUM(C111:E111) -> 0
B112: Academic Support | C112: =IF(F3="1",SUMIF(Data!A:A,$A$2,Data!V:V),0) -> 0 | E112: =IF(F3="1",SUMIF(Data!A:A,$A$2,Data!AC:AC),0) -> 0 | F112: =SUM(C112:E112) -> 0
B113: Student Services | C113: =IF(F3="1",SUMIF(Data!A:A,$A$2,Data!U:U),0) -> 0 | E113: =IF(F3="1",SUMIF(Data!A:A,$A$2,Data!AB:AB),0) -> 0 | F113: =SUM(C113:E113) -> 0
B114: Instructional Support | C114: =IF(F3="1",SUMIF(Data!A:A,$A$2,Data!T:T),0) -> 0 | E114: =IF(F3="1",SUMIF(Data!A:A,$A$2,Data!AA:AA),0) -> 0 | F114: =SUM(C114:E114) -> 0
B115: Operation and Maintenance of Plant | C115: =IF(F3="1",SUMIF(Data!A:A,$A$2,Data!BI:BI),0) -> 0 | D115: =IF(F3="1",SUMIF(Data!A:A,$A$2,Data!BL:BL),0) -> 0 | E115: =IF(F3="1",SUMIF(Data!A:A,$A$2,Data!BU:BU),0) -> 0 | F115: =SUM(C115:E115) -> 0
B116: Scholarships and Fellowships | C116: =IF(F3="1",SUMIF(Data!A:A,$A$2,Data!X:X),0) -> 0 | E116: =E102 -> 0 | F116: =SUM(C116:E116) -> 0
B117: Other | D117: =IF(F3="1",SUMIF(Data!A:A,$A$2,Data!Q:Q),0) -> 249137 | F117: =SUM(C117:E117) -> 249137
B118: Total | C118: =SUM(C109:C116) -> 5021165 | D118: =SUM(D109:D116) -> 0 | E118: =SUM(E109:E116) -> 0 | F118: =SUM(F109:F116) -> 5021165
B120: Depreciation Expense - Equipment | E120: =IF(F3="1",SUMIF(Data!A:A,'4'!$A$2,Data!AM:AM),0) -> 0 | F120: =SUM(C120:E120) -> 0
...

Sheet 5
A1: =Summary!A1 -> Community and Technical Colleges, Report of Fundable Operating Expenses, Fiscal Year (FY) 1999
A2: 012015 | B2: =VLOOKUP(A2,Data!A:G,7,0) -> Austin Community College
F3: =IFERROR(VLOOKUP(A2,Data!A:C,3,0),"0") -> 1
A4: Fund | B4: Total Expense by Discipline | D4: Contact Hours | E4: Expense | F4: Expense per Contact Hour
A5: 1 | B5: Agriculture | D5: =D36 -> 0 | E5: =E36+E67+IFERROR($E$105/$D$105*D5,0) -> 0 | F5: =IF(OR(D5=0,E5=0),"",ROUND(E5/D5,2))
A6: 2 | B6: Architecture and Precision Production Trades | D6: =D37 -> 220992 | E6: =E37+E68+IFERROR($E$105/$D$105*D6,0) -> 2109666 | F6: =IF(OR(D6=0,E6=0),"",ROUND(E6/D6,2)) -> 9.55
A7: 3 | B7: Biology, Physical Sciences, and Science Technology | D7: =D38 -> 1043488 | E7: =E38+E69+IFERROR($E$105/$D$105*D7,0) -> 7302920.1 | F7: =IF(OR(D7=0,E7=0),"",ROUND(E7/D7,2)) -> 7
A8: 4 | B8: Business Management, Marketing, and Administrative Services | D8: =D39 -> 516800 | E8: =E39+E70+IFERROR($E$105/$D$105*D8,0) -> 4020326.4 | F8: =IF(OR(D8=0,E8=0),"",ROUND(E8/D8,2)) -> 7.78
A9: 5 | B9: Career Pilot | D9: =D40 -> 0 | E9: =E40+E71+IFERROR($E$105/$D$105*D9,0) -> 0 | F9: =IF(OR(D9=0,E9=0),"",ROUND(E9/D9,2))
A10: 6 | B10: Communications | D10: =D41 -> 59104 | E10: =E41+E72+IFERROR($E$105/$D$105*D10,0) -> 431584.16 | F10: =IF(OR(D10=0,E10=0),"",ROUND(E10/D10,2)) -> 7.3
A11: 7 | B11: Computer and Information Sciences | D11: =D42 -> 732480 | E11: =E42+E73+IFERROR($E$105/$D$105*D11,0) -> 5122395.6 | F11: =IF(OR(D11=0,E11=0),"",ROUND(E11/D11,2)) -> 6.99
A12: 8 | B12: Construction Trades | D12: =D43 -> 53056 | E12: =E43+E74+IFERROR($E$105/$D$105*D12,0) -> 569377.76 | F12: =IF(OR(D12=0,E12=0),"",ROUND(E12/D12,2)) -> 10.73
A13: 9 | B13: Consumer and Homemaking Education | D13: =D44 -> 81696 | E13: =E44+E75+IFERROR($E$105/$D$105*D13,0) -> 619731.47 | F13: =IF(OR(D13=0,E13=0),"",ROUND(E13/D13,2)) -> 7.59
A14: 10 | B14: Engineering | D14: =D45 -> 8064 | E14: =E45+E76+IFERROR($E$105/$D$105*D14,0) -> 98327.531 | F14: =IF(OR(D14=0,E14=0),"",ROUND(E14/D14,2)) -> 12.19
A15: 11 | B15: Engineering Related | D15: =D46 -> 77328 | E15: =E46+E77+IFERROR($E$105/$D$105*D15,0) -> 757518.02 | F15: =IF(OR(D15=0,E15=0),"",ROUND(E15/D15,2)) -> 9.8
A16: 12 | B16: English Language, Lit, Philosophy, Humanities, & Interdisciplinary | D16: =D47 -> 1234448 | E16: =E47+E78+IFERROR($E$105/$D$105*D16,0) -> 8164746.1 | F16: =IF(OR(D16=0,E16=0),"",ROUND(E16/D16,2)) -> 6.61
... A32: 29 | B32: Developmental Education - Reading/Writing | D32: =D63 -> 0 | E32: =E63+E94+IFERROR($E$105/$D$105*D32,0) -> 0 | F32: =IF(OR(D32=0,E32=0),"",ROUND(E32/D32,2))
B33: Total | D33: =SUM(D5:D32) -> 9620432 | E33: =SUM(E5:E32) -> 67025182 | F33: =IF(OR(D33=0,E33=0),"",ROUND(E33/D33,2)) -> 6.97
A35: Fund | B35: Departmental Operating Expense by Discipline | D35: Contact Hours | E35: Expense | F35: Expense per Contact Hour
A36: 1 | B36: Agriculture | D36: =IF(F3="1",SUMIF(Data!A:A,'5'!$A$2,Data!CU:CU),0) -> 0 | E36: =IF(F3="1",SUMIF(Data!$A:$A,$A$2,Data!IO:IO),0) -> 0 | F36: =IF(OR(D36=0,E36=0),"",ROUND(E36/D36,2))
A37: 2 | B37: Architecture and Precision Production Trades | D37: =IF(F3="1",SUMIF(Data!A:A,'5'!$A$2,Data!CV:CV),0) -> 220992 | E37: =IF(F3="1",SUMIF(Data!$A:$A,$A$2,Data!IP:IP),0) -> 328803 | F37: =IF(OR(D37=0,E37=0),"",ROUND(E37/D37,2)) -> 1.49
A38: 3 | B38: Biology, Physical Sciences, and Science Technology | D38: =IF(F3="1",SUMIF(Data!A:A,'5'!$A$2,Data!CW:CW),0) -> 1043488 | E38: =IF($F$3="1",SUMIF(Data!$A:$A,$A$2,Data!IQ:IQ),0) -> 1041897 | F38: =IF(OR(D38=0,E38=0),"",ROUND(E38/D38,2)) -> 1
